{
  "type": "Feature",
  "properties": {
    "addr:full":"Turnhoutsebaan 120 Antwerpen Antwerpen 2140",
    "addr:housenumber":"120",
    "addr:postcode":"2140",
    "addr:street":"Turnhoutsebaan",
    "iso:country":"BE",
    "sg:address":"Turnhoutsebaan 120",
    "sg:city":"Antwerpen",
    "sg:orig_category":"Auto-\u00e9coles",
    "sg:phone":"+32 3 235 13 50",
    "sg:postcode":"2140",
    "sg:province":"Antwerpen",
    "wof:name":"Rijschool Sanderus",
    "wof:placetype":"venue"
},
  "geometry": {"coordinates":[4.4332199097,51.2137565613],"type":"Point"}
}