{
  "type": "Feature",
  "properties": {
    "addr:full":"Avenue Emile Herman 454 Manage Hainaut 7170",
    "addr:housenumber":"454",
    "addr:postcode":"7170",
    "addr:street":"Avenue Emile Herman",
    "iso:country":"BE",
    "sg:address":"Avenue Emile Herman 454",
    "sg:city":"Manage",
    "sg:orig_category":"Apotheken",
    "sg:phone":"+32 64 22 14 51",
    "sg:postcode":"7170",
    "sg:province":"Hainaut",
    "wof:name":"Pharm. De La Bifurcation",
    "wof:placetype":"venue"
},
  "geometry": {"coordinates":[4.2269849777,50.4885101318],"type":"Point"}
}