{
  "type": "Feature",
  "properties": {
    "addr:full":"Remerstraat 143 Begijnendijk Vlaams-Brabant 3130",
    "addr:housenumber":"143",
    "addr:postcode":"3130",
    "addr:street":"Remerstraat",
    "iso:country":"BE",
    "sg:address":"Remerstraat 143",
    "sg:city":"Begijnendijk",
    "sg:orig_category":"Dierentuinen, botanische tuinen, sterrenwachten and natuurreservaten",
    "sg:phone":"+32 16 53 04 43",
    "sg:postcode":"3130",
    "sg:province":"Vlaams-Brabant",
    "wof:name":"Molenberg (begijnendijk)",
    "wof:placetype":"venue"
},
  "geometry": {"coordinates":[4.7701458931,51.0122795105],"type":"Point"}
}