{
  "type": "Feature",
  "properties": {
    "addr:full":"Boterbloemenln 3 Bornem Antwerpen 2880",
    "addr:housenumber":"3",
    "addr:postcode":"2880",
    "addr:street":"Boterbloemenln",
    "iso:country":"BE",
    "sg:address":"Boterbloemenln 3",
    "sg:city":"Bornem",
    "sg:classifiers":[
        {
            "category":"Shopping",
            "type":"Retail Goods"
        }
    ],
    "sg:phone":"+32 3 844 56 56",
    "sg:postcode":"2880",
    "sg:province":"Antwerpen",
    "sg:tags":[
        "metallurgy",
        "finished",
        "-",
        "metalworking",
        "metallic"
    ],
    "wof:name":"Ecopack International Nv",
    "wof:placetype":"venue"
},
  "geometry": {"coordinates":[4.2096071243,51.0834732056],"type":"Point"}
}