{
  "type": "Feature",
  "properties": {
    "iso:country":"BE",
    "sg:address":"Houtduivendreef 22",
    "sg:city":"Schoten",
    "sg:orig_category":"Editeurs de revues and p\u00e9riodiques. Editeurs de journaux",
    "sg:phone":"+32 3 658 91 53",
    "sg:postcode":"2900",
    "sg:province":"Antwerpen",
    "wof:name":"Uitgeverij De Puzzelaar",
    "wof:placetype":"venue"
},
  "geometry": {"coordinates":[4.5277500153,51.242351532],"type":"Point"}
}