{
  "type": "Feature",
  "properties": {
    "iso:country":"BE",
    "sg:address":"Bredabaan 424",
    "sg:city":"Brasschaat",
    "sg:classifiers":[
        {
            "category":"Building & Trades",
            "subcategory":"Electrical",
            "type":"Services"
        }
    ],
    "sg:phone":"+32 3 650 15 20",
    "sg:postcode":"2930",
    "sg:province":"Antwerpen",
    "sg:tags":[
        "industrial",
        "-",
        "electric",
        "contractor"
    ],
    "wof:name":"Elektriciteit Vochten",
    "wof:placetype":"venue"
},
  "geometry": {"coordinates":[4.4964399338,51.2952766418],"type":"Point"}
}