{
  "type": "Feature",
  "properties": {
    "iso:country":"BE",
    "sg:address":"Brugstraat 52",
    "sg:city":"Brecht",
    "sg:orig_category":"Bloemen and planten",
    "sg:phone":"+32 3 636 32 42",
    "sg:postcode":"2960",
    "sg:province":"Antwerpen",
    "wof:name":"'t Vergeet-me -nietje",
    "wof:placetype":"venue"
},
  "geometry": {"coordinates":[4.5758371353,51.2949447632],"type":"Point"}
}