{
  "type": "Feature",
  "properties": {
    "iso:country":"BE",
    "sg:address":"Steenweg Naar Halle 317",
    "sg:city":"Beersel (alsemberg)",
    "sg:classifiers":[
        {
            "category":"Health Services",
            "subcategory":"Doctor",
            "type":"Services"
        }
    ],
    "sg:phone":"+32 2 331 14 10",
    "sg:postcode":"1652",
    "sg:province":"Vlaams-Brabant",
    "sg:tags":[
        "medicinephysicians",
        "surgeon"
    ],
    "wof:name":"Brimioulle S",
    "wof:placetype":"venue"
},
  "geometry": {"coordinates":[4.3218040466,50.7327308655],"type":"Point"}
}