{
  "type": "Feature",
  "properties": {
    "iso:country":"BE",
    "sg:address":"Burgemeester Bruneellaan 4",
    "sg:city":"Harelbeke",
    "sg:orig_category":"Plomberie, chauffage and installations sanitaires",
    "sg:phone":"+32 56 72 82 99",
    "sg:postcode":"8531",
    "sg:province":"West-Vlaanderen",
    "wof:name":"Serge Baert",
    "wof:placetype":"venue"
},
  "geometry": {"coordinates":[3.2948210239,50.8807792664],"type":"Point"}
}