{
  "type": "Feature",
  "properties": {
    "addr:full":"Avenue Brugmann 353a Bruxelles (uccle) Bruxelles-Capitale 1180",
    "addr:housenumber":"353a",
    "addr:postcode":"1180",
    "addr:street":"Avenue Brugmann",
    "iso:country":"BE",
    "sg:address":"Avenue Brugmann 353a",
    "sg:city":"Bruxelles (uccle)",
    "sg:classifiers":[
        {
            "category":"Farming",
            "subcategory":"Fish & Marine Products",
            "type":"Manufacturing & Wholesale Goods"
        }
    ],
    "sg:phone":"+32 2 345 49 61",
    "sg:postcode":"1180",
    "sg:province":"Bruxelles-Capitale",
    "sg:tags":[
        "photographer",
        "fashion",
        "-"
    ],
    "wof:name":"Mirza Production",
    "wof:placetype":"venue"
},
  "geometry": {"coordinates":[4.3453769684,50.8099784851],"type":"Point"}
}