{
  "type": "Feature",
  "properties": {
    "addr:full":"Bossestraat 12 Aarschot Vlaams-Brabant 3201",
    "addr:housenumber":"12",
    "addr:postcode":"3201",
    "addr:street":"Bossestraat",
    "iso:country":"BE",
    "sg:address":"Bossestraat 12",
    "sg:city":"Aarschot",
    "sg:orig_category":"Plomberie, chauffage and installations sanitaires",
    "sg:phone":"+32 16 56 55 77",
    "sg:postcode":"3201",
    "sg:province":"Vlaams-Brabant",
    "wof:name":"Patrick Verdonck",
    "wof:placetype":"venue"
},
  "geometry": {"coordinates":[4.862226963,50.9975357056],"type":"Point"}
}