{
  "type": "Feature",
  "properties": {
    "iso:country":"BE",
    "sg:address":"Bierbeekstraat 148",
    "sg:city":"Bierbeek",
    "sg:orig_category":"Agences de publicit\u00e9",
    "sg:phone":"+32 16 46 04 69",
    "sg:postcode":"3360",
    "sg:province":"Vlaams-Brabant",
    "wof:name":"Bureau Alopex",
    "wof:placetype":"venue"
},
  "geometry": {"coordinates":[4.7608628273,50.8537979126],"type":"Point"}
}