{
  "type": "Feature",
  "properties": {
    "iso:country":"BE",
    "sg:address":"Rue Thomas Edison 32",
    "sg:city":"Grace-hollogne",
    "sg:orig_category":"Epiceries",
    "sg:phone":"+32 4 235 68 03",
    "sg:postcode":"4460",
    "sg:province":"Li\u00e8ge",
    "wof:name":"Giulia Metello",
    "wof:placetype":"venue"
},
  "geometry": {"coordinates":[5.4987421036,50.6338424683],"type":"Point"}
}