{
  "type": "Feature",
  "properties": {
    "iso:country":"BE",
    "sg:address":"Rue Du Commerce 89",
    "sg:city":"Ciney",
    "sg:classifiers":[
        {
            "category":"Food & Beverages",
            "subcategory":"Chocolate",
            "type":"Retail Goods"
        }
    ],
    "sg:phone":"+32 83 61 37 27",
    "sg:postcode":"5590",
    "sg:province":"Namur",
    "sg:tags":[
        "confectionery",
        "-"
    ],
    "wof:name":"Saveurs & D\u00e9lices",
    "wof:placetype":"venue"
},
  "geometry": {"coordinates":[5.0958971977,50.2919502258],"type":"Point"}
}