{
  "type": "Feature",
  "properties": {
    "iso:country":"BE",
    "sg:address":"Rue De La Station 52",
    "sg:city":"Soignies",
    "sg:classifiers":[
        {
            "category":"Professional",
            "subcategory":"Lawyer & Legal Services",
            "type":"Services"
        }
    ],
    "sg:phone":"+32 67 34 76 33",
    "sg:postcode":"7060",
    "sg:province":"Hainaut",
    "wof:name":"Van Haverbeke Pierre",
    "wof:placetype":"venue"
},
  "geometry": {"coordinates":[4.0698871613,50.5754814148],"type":"Point"}
}