{
  "type": "Feature",
  "properties": {
    "addr:full":"Peperstraat 129 Eeklo Oost-Vlaanderen 9900",
    "addr:housenumber":"129",
    "addr:postcode":"9900",
    "addr:street":"Peperstraat",
    "iso:country":"BE",
    "sg:address":"Peperstraat 129",
    "sg:city":"Eeklo",
    "sg:orig_category":"Eleveurs de bovins",
    "sg:phone":"+32 9 377 63 31",
    "sg:postcode":"9900",
    "sg:province":"Oost-Vlaanderen",
    "wof:name":"Jan Van Houcke",
    "wof:placetype":"venue"
},
  "geometry": {"coordinates":[3.5720040798,51.2146034241],"type":"Point"}
}