{
  "type": "Feature",
  "properties": {
    "addr:full":"Rue De La Clawenne 69 Herstal Li\u00e8ge 4040",
    "addr:housenumber":"69",
    "addr:postcode":"4040",
    "addr:street":"Rue De La Clawenne",
    "iso:country":"BE",
    "sg:address":"Rue De La Clawenne 69",
    "sg:city":"Herstal",
    "sg:classifiers":[
        {
            "category":"Autos & Motor Vehicles",
            "subcategory":"Boat Sales",
            "type":"Retail Goods"
        }
    ],
    "sg:phone":"+32 4 240 48 16",
    "sg:postcode":"4040",
    "sg:province":"Li\u00e8ge",
    "sg:tags":[
        "balloon"
    ],
    "wof:name":"Horrion T",
    "wof:placetype":"venue"
},
  "geometry": {"coordinates":[5.6381921768,50.6743240356],"type":"Point"}
}