{
  "type": "Feature",
  "properties": {
    "addr:full":"Raymond Delbekestraat 95 Zoersel Antwerpen 2980",
    "addr:housenumber":"95",
    "addr:postcode":"2980",
    "addr:street":"Delbekestraat",
    "iso:country":"BE",
    "sg:address":"Raymond Delbekestraat 95",
    "sg:city":"Zoersel",
    "sg:orig_category":"Travaux de pl\u00e2trage",
    "sg:phone":"+32 3 383 31 65",
    "sg:postcode":"2980",
    "sg:province":"Antwerpen",
    "wof:name":"Dirk De Roover",
    "wof:placetype":"venue"
},
  "geometry": {"coordinates":[4.6240611076,51.2778205872],"type":"Point"}
}