{
  "type": "Feature",
  "properties": {
    "iso:country":"BE",
    "sg:address":"Rue Du Ch\u00c2teau D'eau 6",
    "sg:city":"Neupre",
    "sg:orig_category":"Installatie van houten of kunststof schrijnwerk Installatie van metalen schrijnwerk Woningbouw",
    "sg:phone":"+32 4 371 43 04",
    "sg:postcode":"4121",
    "sg:province":"Li\u00e8ge",
    "wof:name":"Adelaire Marcel",
    "wof:placetype":"venue"
},
  "geometry": {"coordinates":[5.4626069069,50.5404396057],"type":"Point"}
}