{
  "type": "Feature",
  "properties": {
    "iso:country":"BE",
    "sg:address":"Brielensestraat 123",
    "sg:city":"Ieper",
    "sg:orig_category":"Diverse bouwafwerking and reiniging Gespecialiseerde residenti\u00eble bouw Verhuur video and audio Wonin",
    "sg:phone":"+32 57 20 34 15",
    "sg:postcode":"8908",
    "sg:province":"West-Vlaanderen",
    "wof:name":"Dehouck-vanneste",
    "wof:placetype":"venue"
},
  "geometry": {"coordinates":[2.8266661167,50.8559532166],"type":"Point"}
}