{
  "type": "Feature",
  "properties": {
    "iso:country":"BE",
    "sg:address":"Mierdsedijk 84",
    "sg:city":"Ravels",
    "sg:orig_category":"Eleveurs and marchands de porcs",
    "sg:phone":"+32 14 65 54 59",
    "sg:postcode":"2382",
    "sg:province":"Antwerpen",
    "wof:name":"Paulus Bertens",
    "wof:placetype":"venue"
},
  "geometry": {"coordinates":[5.041768074,51.4469108582],"type":"Point"}
}