{
  "type": "Feature",
  "properties": {
    "addr:full":"Kouter 35 Merchtem Vlaams-Brabant 1785",
    "addr:housenumber":"35",
    "addr:postcode":"1785",
    "addr:street":"Kouter",
    "iso:country":"BE",
    "sg:address":"Kouter 35",
    "sg:city":"Merchtem",
    "sg:classifiers":[
        {
            "category":"Landmark",
            "subcategory":"City Walls",
            "type":"Public Place"
        }
    ],
    "sg:phone":"+32 52 37 13 90",
    "sg:postcode":"1785",
    "sg:province":"Vlaams-Brabant",
    "sg:tags":[
        "plywood"
    ],
    "wof:name":"Finaply Bvba",
    "wof:placetype":"venue"
},
  "geometry": {"coordinates":[4.2315268517,50.9713020325],"type":"Point"}
}