{
  "type": "Feature",
  "properties": {
    "iso:country":"BE",
    "sg:address":"Menenstraat 412",
    "sg:city":"Moeskroen/mouscron",
    "sg:classifiers":[
        {
            "category":"Fast Food",
            "type":"Food & Drink"
        }
    ],
    "sg:phone":"+32 56 34 87 39",
    "sg:postcode":"7700",
    "sg:province":"Hainaut",
    "sg:tags":[
        "meeneem",
        "restaurant"
    ],
    "wof:name":"Torre Di Pisa",
    "wof:placetype":"venue"
},
  "geometry": {"coordinates":[3.2323200703,50.7400932312],"type":"Point"}
}