{
  "type": "Feature",
  "properties": {
    "addr:full":"Wijngaardveld 7 Aalst Oost-Vlaanderen 9300",
    "addr:housenumber":"7",
    "addr:postcode":"9300",
    "addr:street":"Wijngaardveld",
    "iso:country":"BE",
    "sg:address":"Wijngaardveld 7",
    "sg:city":"Aalst",
    "sg:orig_category":"Entreprises de travail adapt\u00e9",
    "sg:phone":"+32 53 70 14 24",
    "sg:postcode":"9300",
    "sg:province":"Oost-Vlaanderen",
    "wof:name":"Beschuttende Werkplaatsen",
    "wof:placetype":"venue"
},
  "geometry": {"coordinates":[4.0437917709,50.9595375061],"type":"Point"}
}