{
  "type": "Feature",
  "properties": {
    "addr:full":"Rue Jean Stas 11 Bruxelles (saint-gilles) Bruxelles-Capitale 1060",
    "addr:housenumber":"11",
    "addr:postcode":"1060",
    "addr:street":"Rue Jean Stas",
    "iso:country":"BE",
    "sg:address":"Rue Jean Stas 11",
    "sg:city":"Bruxelles (saint-gilles)",
    "sg:classifiers":[
        {
            "category":"Shopping",
            "subcategory":"Luggage & Leather Goods",
            "type":"Retail Goods"
        }
    ],
    "sg:phone":"+32 2 539 09 96",
    "sg:postcode":"1060",
    "sg:province":"Bruxelles-Capitale",
    "sg:tags":[
        "-"
    ],
    "wof:name":"Mano A Mano",
    "wof:placetype":"venue"
},
  "geometry": {"coordinates":[4.3558068275,50.8343276978],"type":"Point"}
}