{
  "type": "Feature",
  "properties": {
    "iso:country":"BE",
    "sg:address":"Rue Major P\u00e9tillon 4",
    "sg:city":"Bruxelles (etterbeek)",
    "sg:classifiers":[
        {
            "category":"Professional",
            "subcategory":"Art Services",
            "type":"Services"
        }
    ],
    "sg:phone":"+32 2 742 36 32",
    "sg:postcode":"1040",
    "sg:province":"Bruxelles-Capitale",
    "sg:tags":[
        "graphic",
        "designer"
    ],
    "wof:name":"Anderson",
    "wof:placetype":"venue"
},
  "geometry": {"coordinates":[4.4024448395,50.8287963867],"type":"Point"}
}