{
  "type": "Feature",
  "properties": {
    "addr:full":"Maalbroekstraat 12 Sint-lievens-houtem Oost-Vlaanderen 9520",
    "addr:housenumber":"12",
    "addr:postcode":"9520",
    "addr:street":"Maalbroekstraat;Oost-Vlaanderen",
    "iso:country":"BE",
    "sg:address":"Maalbroekstraat 12",
    "sg:city":"Sint-lievens-houtem",
    "sg:orig_category":"Groenten and fruit Gh",
    "sg:phone":"+32 9 362 77 14",
    "sg:postcode":"9520",
    "sg:province":"Oost-Vlaanderen",
    "wof:name":"Etienne Berckmoes",
    "wof:placetype":"venue"
},
  "geometry": {"coordinates":[3.8580899239,50.9409332275],"type":"Point"}
}