{
  "type": "Feature",
  "properties": {
    "addr:full":"Blauwstraat 8 Boom Antwerpen 2850",
    "addr:housenumber":"8",
    "addr:postcode":"2850",
    "addr:street":"Blauwstraat",
    "iso:country":"BE",
    "sg:address":"Blauwstraat 8",
    "sg:city":"Boom",
    "sg:classifiers":[
        {
            "category":"Restaurant",
            "type":"Food & Drink"
        }
    ],
    "sg:phone":"+32 3 888 15 67",
    "sg:postcode":"2850",
    "sg:province":"Antwerpen",
    "wof:name":"T Spiegeltje",
    "wof:placetype":"venue"
},
  "geometry": {"coordinates":[4.3666501045,51.0860061646],"type":"Point"}
}