{
  "type": "Feature",
  "properties": {
    "iso:country":"BE",
    "sg:address":"Rue Du Bois De Huy 8",
    "sg:city":"Amay",
    "sg:orig_category":"Boomkwekerijen",
    "sg:phone":"+32 85 23 19 99",
    "sg:postcode":"4540",
    "sg:province":"Li\u00e8ge",
    "wof:name":"Martine Quoibion",
    "wof:placetype":"venue"
},
  "geometry": {"coordinates":[5.2630200386,50.5447463989],"type":"Point"}
}