{
  "type": "Feature",
  "properties": {
    "iso:country":"BE",
    "sg:address":"Aarschotsesteenweg 191",
    "sg:city":"Begijnendijk",
    "sg:orig_category":"Groenten and fruit Gh",
    "sg:phone":"+32 16 56 68 93",
    "sg:postcode":"3130",
    "sg:province":"Vlaams-Brabant",
    "wof:name":"Vandenberg Rene",
    "wof:placetype":"venue"
},
  "geometry": {"coordinates":[4.8047590256,50.9903411865],"type":"Point"}
}