{
  "type": "Feature",
  "properties": {
    "addr:full":"Place Albert I 28 Malmedy Li\u00e8ge 4960",
    "addr:housenumber":"28",
    "addr:postcode":"4960",
    "addr:street":"Place Albert I",
    "iso:country":"BE",
    "sg:address":"Place Albert I 28",
    "sg:city":"Malmedy",
    "sg:classifiers":[
        {
            "category":"Shopping",
            "subcategory":"Shoes",
            "type":"Retail Goods"
        }
    ],
    "sg:phone":"+32 80 33 03 28",
    "sg:postcode":"4960",
    "sg:province":"Li\u00e8ge",
    "sg:tags":[
        "slipper",
        "-"
    ],
    "wof:name":"Solheid Chaussures Sprl",
    "wof:placetype":"venue"
},
  "geometry": {"coordinates":[6.0306248665,50.4252433777],"type":"Point"}
}