{
  "type": "Feature",
  "properties": {
    "addr:full":"Route De Hannut 255 Namur Namur 5021",
    "addr:housenumber":"255",
    "addr:postcode":"5021",
    "addr:street":"Route De Hannut",
    "iso:country":"BE",
    "sg:address":"Route De Hannut 255",
    "sg:city":"Namur",
    "sg:orig_category":"Studios photographiques",
    "sg:phone":"+32 81 21 15 78",
    "sg:postcode":"5021",
    "sg:province":"Namur",
    "wof:name":"Gilles Moniotte",
    "wof:placetype":"venue"
},
  "geometry": {"coordinates":[4.9345002174,50.4965438843],"type":"Point"}
}