{
  "type": "Feature",
  "properties": {
    "iso:country":"BE",
    "sg:address":"Rue Dommartin 20",
    "sg:city":"Saint-georges-sur-meuse",
    "sg:orig_category":"Enseignement maternel and primaire",
    "sg:phone":"+32 4 259 51 85",
    "sg:postcode":"4470",
    "sg:province":"Li\u00e8ge",
    "wof:name":"Ecole Fondamentale Libre",
    "wof:placetype":"venue"
},
  "geometry": {"coordinates":[5.3582558632,50.6007537842],"type":"Point"}
}