{
  "type": "Feature",
  "properties": {
    "addr:full":"Diestsestraat 242 Leuven Vlaams-Brabant 3000",
    "addr:housenumber":"242",
    "addr:postcode":"3000",
    "addr:street":"Diestsestraat",
    "iso:country":"BE",
    "sg:address":"Diestsestraat 242",
    "sg:city":"Leuven",
    "sg:classifiers":[
        {
            "category":"Manufacturing",
            "subcategory":"Furniture",
            "type":"Manufacturing & Wholesale Goods"
        }
    ],
    "sg:phone":"+32 16 23 08 04",
    "sg:postcode":"3000",
    "sg:province":"Vlaams-Brabant",
    "sg:tags":[
        "design",
        "-"
    ],
    "wof:name":"Loncin Interieur",
    "wof:placetype":"venue"
},
  "geometry": {"coordinates":[4.7135119438,50.8820419312],"type":"Point"}
}