{
  "type": "Feature",
  "properties": {
    "addr:full":"Klapperstraat 117 Beveren (grand) - Flandre Orientale Oost-Vlaanderen 9120",
    "addr:housenumber":"117",
    "addr:postcode":"9120",
    "addr:street":"Klapperstraat",
    "iso:country":"BE",
    "sg:address":"Klapperstraat 117",
    "sg:city":"Beveren (grand) - Flandre Orientale",
    "sg:classifiers":[
        {
            "category":"Insurance",
            "subcategory":"Insurance Agent",
            "type":"Services"
        }
    ],
    "sg:phone":"+32 3 755 45 04",
    "sg:postcode":"9120",
    "sg:province":"Oost-Vlaanderen",
    "sg:tags":[
        "verzekeringsmakelaars",
        "expert"
    ],
    "wof:name":"Herman Smet",
    "wof:placetype":"venue"
},
  "geometry": {"coordinates":[4.2452149391,51.2125549316],"type":"Point"}
}