{
  "type": "Feature",
  "properties": {
    "iso:country":"BE",
    "sg:address":"Rue De Gouy 37",
    "sg:city":"Chapelle-lez-herlaimont",
    "sg:classifiers":[
        {
            "category":"Bars & Pubs",
            "type":"Food & Drink"
        }
    ],
    "sg:phone":"+32 64 44 92 56",
    "sg:postcode":"7160",
    "sg:province":"Hainaut",
    "wof:name":"Saint-germain (le)",
    "wof:placetype":"venue"
},
  "geometry": {"coordinates":[4.2852897644,50.4710922241],"type":"Point"}
}