{
  "type": "Feature",
  "properties": {
    "addr:full":"Luikersteenweg 266 Sint-truiden (brustem) Limburg 3800",
    "addr:housenumber":"266",
    "addr:postcode":"3800",
    "addr:street":"Luikersteenweg",
    "iso:country":"BE",
    "sg:address":"Luikersteenweg 266",
    "sg:city":"Sint-truiden (brustem)",
    "sg:classifiers":[
        {
            "category":"Shopping",
            "subcategory":"Bicycles & Sporting Goods",
            "type":"Retail Goods"
        }
    ],
    "sg:phone":"+32 11 68 34 91",
    "sg:postcode":"3800",
    "sg:province":"Limburg",
    "sg:tags":[
        "tyre"
    ],
    "wof:name":"Banden Max",
    "wof:placetype":"venue"
},
  "geometry": {"coordinates":[5.2029700279,50.8036193848],"type":"Point"}
}