{
  "type": "Feature",
  "properties": {
    "addr:full":"Kustlaan 122 Knokke-heist (knokke) West-Vlaanderen 8300",
    "addr:housenumber":"122",
    "addr:postcode":"8300",
    "addr:street":"Kustlaan",
    "iso:country":"BE",
    "sg:address":"Kustlaan 122",
    "sg:city":"Knokke-heist (knokke)",
    "sg:classifiers":[
        {
            "category":"Arts & Performance",
            "subcategory":"Art Gallery",
            "type":"Entertainment"
        }
    ],
    "sg:phone":"+32 50 60 42 52",
    "sg:postcode":"8300",
    "sg:province":"West-Vlaanderen",
    "wof:name":"Offa Bvba",
    "wof:placetype":"venue"
},
  "geometry": {"coordinates":[3.287694931,51.3467254639],"type":"Point"}
}