{
  "type": "Feature",
  "properties": {
    "addr:full":"Avenue Des Lilas 16 Jemeppe-sur-sambre (ham-sur-sambre) Namur 5190",
    "addr:housenumber":"16",
    "addr:postcode":"5190",
    "addr:street":"Avenue Des Lilas;Ham-Sur-Sambre",
    "iso:country":"BE",
    "sg:address":"Avenue Des Lilas 16",
    "sg:city":"Jemeppe-sur-sambre (ham-sur-sambre)",
    "sg:classifiers":[
        {
            "category":"Government",
            "subcategory":"Fire Station",
            "type":"Public Place"
        }
    ],
    "sg:phone":"+32 71 78 36 40",
    "sg:postcode":"5190",
    "sg:province":"Namur",
    "sg:tags":[
        "hot",
        "generator",
        "air"
    ],
    "wof:name":"Infra-blitz-salmon",
    "wof:placetype":"venue"
},
  "geometry": {"coordinates":[4.6703448296,50.4645042419],"type":"Point"}
}