{
  "type": "Feature",
  "properties": {
    "iso:country":"BE",
    "sg:address":"Kloosterdreef 25",
    "sg:city":"Wortegem-petegem",
    "sg:orig_category":"Artistes ind\u00e9pendants",
    "sg:phone":"+32 56 68 15 02",
    "sg:postcode":"9790",
    "sg:province":"Oost-Vlaanderen",
    "wof:name":"Hubert Huys",
    "wof:placetype":"venue"
},
  "geometry": {"coordinates":[3.5177218914,50.8255996704],"type":"Point"}
}