{
  "type": "Feature",
  "properties": {
    "addr:full":"Chemin Rejet \u00c0 Rhosnes 4 Mont-de-l'enclus Hainaut 7750",
    "addr:housenumber":"4",
    "addr:postcode":"7750",
    "addr:street":"Chemin Rejet A\u0300 Rhosnes;Hainaut",
    "iso:country":"BE",
    "sg:address":"Chemin Rejet \u00c0 Rhosnes 4",
    "sg:city":"Mont-de-l'enclus",
    "sg:orig_category":"Rundveehouders",
    "sg:phone":"+32 69 76 80 12",
    "sg:postcode":"7750",
    "sg:province":"Hainaut",
    "wof:name":"Jean-pierre Brunin",
    "wof:placetype":"venue"
},
  "geometry": {"coordinates":[2.6025109291,46.3370933533],"type":"Point"}
}