{
  "type": "Feature",
  "properties": {
    "addr:full":"Reginald Warnefordstraat 100 Gent (sint-amandsberg) Oost-Vlaanderen 9040",
    "addr:housenumber":"100",
    "addr:postcode":"9040",
    "addr:street":"Warnefordstraat",
    "iso:country":"BE",
    "sg:address":"Reginald Warnefordstraat 100",
    "sg:city":"Gent (sint-amandsberg)",
    "sg:classifiers":[
        {
            "category":"Health Services",
            "subcategory":"Health Practitioner",
            "type":"Services"
        }
    ],
    "sg:phone":"+32 476 22 08 81",
    "sg:postcode":"9040",
    "sg:province":"Oost-Vlaanderen",
    "sg:tags":[
        "alternative",
        "therapy",
        "treatment"
    ],
    "wof:name":"Antajj",
    "wof:placetype":"venue"
},
  "geometry": {"coordinates":[3.7478749752,51.0593414307],"type":"Point"}
}