{
  "type": "Feature",
  "properties": {
    "addr:full":"Rue Thtodule Canfijn 63 Ronse/renaix Oost-Vlaanderen 9600",
    "addr:housenumber":"63",
    "addr:postcode":"9600",
    "addr:street":"Rue Thtodule Canfijn",
    "iso:country":"BE",
    "sg:address":"Rue Thtodule Canfijn 63",
    "sg:city":"Ronse/renaix",
    "sg:classifiers":[
        {
            "category":"Professional",
            "type":"Services"
        }
    ],
    "sg:phone":"+32 55 21 48 60",
    "sg:postcode":"9600",
    "sg:province":"Oost-Vlaanderen",
    "sg:tags":[
        "aux",
        "diver",
        "personnes"
    ],
    "wof:name":"Rtgis Piccoli",
    "wof:placetype":"venue"
},
  "geometry": {"coordinates":[3.6088280678,50.7493743896],"type":"Point"}
}