{
  "type": "Feature",
  "properties": {
    "iso:country":"BE",
    "sg:address":"Rodenbachlaan 5",
    "sg:city":"Rotselaar",
    "sg:orig_category":"Slagers",
    "sg:phone":"+32 16 44 52 17",
    "sg:postcode":"3110",
    "sg:province":"Vlaams-Brabant",
    "wof:name":"Slagerij Dama",
    "wof:placetype":"venue"
},
  "geometry": {"coordinates":[4.7109689713,50.9496765137],"type":"Point"}
}