{
  "type": "Feature",
  "properties": {
    "iso:country":"BE",
    "sg:address":"Grote Haagstraat 139",
    "sg:city":"Brussel",
    "sg:classifiers":[
        {
            "category":"Professional",
            "subcategory":"Accounting & Tax Preparation",
            "type":"Services"
        }
    ],
    "sg:phone":"+32 3 326 06 26",
    "sg:postcode":"1040",
    "sg:province":"Bruxelles-Capitale",
    "sg:tags":[
        "bookkeeping"
    ],
    "wof:name":"Agiver Accountancekantoor B.v.b.a.",
    "wof:placetype":"venue"
},
  "geometry": {"coordinates":[4.4685840607,51.2341499329],"type":"Point"}
}