{
  "type": "Feature",
  "properties": {
    "iso:country":"BE",
    "sg:address":"Brouwerijstraat 5",
    "sg:city":"Kortenberg",
    "sg:classifiers":[
        {
            "category":"Building & Trades",
            "subcategory":"Locksmith",
            "type":"Services"
        }
    ],
    "sg:phone":"+32 2 757 65 29",
    "sg:postcode":"3070",
    "sg:province":"Vlaams-Brabant",
    "sg:tags":[
        "lock",
        "key"
    ],
    "wof:name":"Aa Bvba",
    "wof:placetype":"venue"
},
  "geometry": {"coordinates":[4.5404062271,50.8857498169],"type":"Point"}
}