{
  "type": "Feature",
  "properties": {
    "addr:full":"Kerkstraat 215 Grimbergen Vlaams-Brabant 1851",
    "addr:housenumber":"215",
    "addr:postcode":"1851",
    "addr:street":"Kerkstraat",
    "iso:country":"BE",
    "sg:address":"Kerkstraat 215",
    "sg:city":"Grimbergen",
    "sg:orig_category":"Banques and organismes de cr\u00e9dit",
    "sg:phone":"+32 2 269 83 57",
    "sg:postcode":"1851",
    "sg:province":"Vlaams-Brabant",
    "wof:name":"Fortis",
    "wof:placetype":"venue"
},
  "geometry": {"coordinates":[4.3883938789,50.9763946533],"type":"Point"}
}