{
  "type": "Feature",
  "properties": {
    "iso:country":"BE",
    "sg:address":"Avenue Du Bois Jacob 2",
    "sg:city":"La Hulpe",
    "sg:orig_category":"Dierenartsen",
    "sg:phone":"+32 2 653 28 41",
    "sg:postcode":"1310",
    "sg:province":"Brabant Wallon",
    "wof:name":"Ren\u00c9 Jaumotte",
    "wof:placetype":"venue"
},
  "geometry": {"coordinates":[4.473482132,50.7334327698],"type":"Point"}
}