{
  "type": "Feature",
  "properties": {
    "iso:country":"BE",
    "sg:address":"Bergbosstraat 13",
    "sg:city":"Merelbeke",
    "sg:classifiers":[
        {
            "category":"Personal",
            "subcategory":"Nail Salon",
            "type":"Services"
        }
    ],
    "sg:phone":"+32 9 231 54 13",
    "sg:postcode":"9820",
    "sg:province":"Oost-Vlaanderen",
    "sg:tags":[
        "pedicure"
    ],
    "wof:name":"De Clercq A",
    "wof:placetype":"venue"
},
  "geometry": {"coordinates":[3.7440440655,50.9864807129],"type":"Point"}
}