{
  "type": "Feature",
  "properties": {
    "addr:full":"Duinkerkestraat 112 Poperinge West-Vlaanderen 8970",
    "addr:housenumber":"112",
    "addr:postcode":"8970",
    "addr:street":"Duinkerkestraat",
    "iso:country":"BE",
    "sg:address":"Duinkerkestraat 112",
    "sg:city":"Poperinge",
    "sg:orig_category":"Entretien and r\u00e9parations de voitures. V\u00e9hicules automobiles. Motos. R\u00e9parations and entretien de mo",
    "sg:phone":"+32 57 33 34 19",
    "sg:postcode":"8970",
    "sg:province":"West-Vlaanderen",
    "wof:name":"Huis Dumont",
    "wof:placetype":"venue"
},
  "geometry": {"coordinates":[2.7153310776,50.8556747437],"type":"Point"}
}