{
  "type": "Feature",
  "properties": {
    "addr:full":"Odilon Vanderlindenstraat 7 Gent (gentbrugge) Oost-Vlaanderen 9050",
    "addr:housenumber":"7",
    "addr:postcode":"9050",
    "addr:street":"Vanderlindenstraat",
    "iso:country":"BE",
    "sg:address":"Odilon Vanderlindenstraat 7",
    "sg:city":"Gent (gentbrugge)",
    "sg:classifiers":[
        {
            "category":"Personal",
            "subcategory":"Barber",
            "type":"Services"
        }
    ],
    "sg:phone":"+32 9 230 31 30",
    "sg:postcode":"9050",
    "sg:province":"Oost-Vlaanderen",
    "sg:tags":[
        "gentleman",
        "salon",
        "-",
        "hairdressing"
    ],
    "wof:name":"Nelson Hairteam",
    "wof:placetype":"venue"
},
  "geometry": {"coordinates":[3.7559950352,51.0445671082],"type":"Point"}
}