{
  "type": "Feature",
  "properties": {
    "iso:country":"BE",
    "sg:address":"Orbanlaan 2",
    "sg:city":"Sint-pieters-woluwe/woluwe-saint-pierre",
    "sg:orig_category":"Restaurants Voedingsspeciaalzaken",
    "sg:phone":"+32 2 770 31 06",
    "sg:postcode":"1150",
    "sg:province":"Bruxelles-Capitale",
    "wof:name":"Ch\u00c2let Rouge",
    "wof:placetype":"venue"
},
  "geometry": {"coordinates":[4.4516701698,50.8312110901],"type":"Point"}
}