{
  "type": "Feature",
  "properties": {
    "addr:full":"Alsembergse Steenweg 1184 Ukkel/uccle Bruxelles-Capitale 1180",
    "addr:postcode":"1184;1180",
    "addr:street":"Alsembergse Steenweg",
    "iso:country":"BE",
    "sg:address":"Alsembergse Steenweg 1184",
    "sg:city":"Ukkel/uccle",
    "sg:orig_category":"Kapsalons",
    "sg:phone":"+32 2 376 21 35",
    "sg:postcode":"1180",
    "sg:province":"Bruxelles-Capitale",
    "wof:name":"Haute Coiffure Cesar",
    "wof:placetype":"venue"
},
  "geometry": {"coordinates":[4.329436779,50.7863578796],"type":"Point"}
}