{
  "type": "Feature",
  "properties": {
    "addr:full":"Omgangstraat 35 Zingem Oost-Vlaanderen 9750",
    "addr:housenumber":"35",
    "addr:postcode":"9750",
    "addr:street":"Omgangstraat",
    "iso:country":"BE",
    "sg:address":"Omgangstraat 35",
    "sg:city":"Zingem",
    "sg:classifiers":[
        {
            "category":"Professional",
            "subcategory":"Computer Services",
            "type":"Services"
        }
    ],
    "sg:phone":"+32 495 40 25 03",
    "sg:postcode":"9750",
    "sg:province":"Oost-Vlaanderen",
    "sg:tags":[
        "webdesign",
        "-",
        "internet"
    ],
    "wof:name":"Hertens It Services",
    "wof:placetype":"venue"
},
  "geometry": {"coordinates":[3.6617939472,50.9009361267],"type":"Point"}
}