{
  "type": "Feature",
  "properties": {
    "iso:country":"BE",
    "sg:address":"Pollarebaan 31",
    "sg:city":"Ninove (pollare)",
    "sg:classifiers":[
        {
            "category":"Health Services",
            "subcategory":"Doctor",
            "type":"Services"
        }
    ],
    "sg:phone":"+32 54 33 65 87",
    "sg:postcode":"9401",
    "sg:province":"Oost-Vlaanderen",
    "sg:tags":[
        "medicinephysicians",
        "surgeon"
    ],
    "wof:name":"Gijssels T",
    "wof:placetype":"venue"
},
  "geometry": {"coordinates":[4.0228691101,50.8285484314],"type":"Point"}
}