{
  "type": "Feature",
  "properties": {
    "addr:full":"Kerkham 1 Destelbergen Oost-Vlaanderen 9070",
    "addr:housenumber":"1",
    "addr:postcode":"9070",
    "addr:street":"Kerkham",
    "iso:country":"BE",
    "sg:address":"Kerkham 1",
    "sg:city":"Destelbergen",
    "sg:orig_category":"Enseignement maternel and primaire",
    "sg:phone":"+32 9 228 44 70",
    "sg:postcode":"9070",
    "sg:province":"Oost-Vlaanderen",
    "wof:name":"Vrije Gemengde Basisschool",
    "wof:placetype":"venue"
},
  "geometry": {"coordinates":[3.7992401123,51.0532608032],"type":"Point"}
}