{
  "type": "Feature",
  "properties": {
    "iso:country":"BE",
    "sg:address":"Oudergemselaan 280",
    "sg:city":"Etterbeek",
    "sg:classifiers":[
        {
            "category":"Fast Food",
            "type":"Food & Drink"
        }
    ],
    "sg:phone":"+32 2 646 13 86",
    "sg:postcode":"1040",
    "sg:province":"Bruxelles-Capitale",
    "sg:tags":[
        "meeneem",
        "restaurant"
    ],
    "wof:name":"Salam Bombay",
    "wof:placetype":"venue"
},
  "geometry": {"coordinates":[4.3894281387,50.8323554993],"type":"Point"}
}