{
  "type": "Feature",
  "properties": {
    "addr:full":"Quai De Rome 43 Li\u00c8ge Li\u00e8ge 4000",
    "addr:housenumber":"43",
    "addr:postcode":"4000",
    "addr:street":"Quai De Rome",
    "iso:country":"BE",
    "sg:address":"Quai De Rome 43",
    "sg:city":"Li\u00c8ge",
    "sg:orig_category":"Activit\u00e9s d\u00b4action sociale sans h\u00e9bergement",
    "sg:phone":"+32 4 252 67 31",
    "sg:postcode":"4000",
    "sg:province":"Li\u00e8ge",
    "wof:name":"Centre P.m.s.",
    "wof:placetype":"venue"
},
  "geometry": {"coordinates":[5.5758447647,50.6241149902],"type":"Point"}
}