{
  "type": "Feature",
  "properties": {
    "addr:full":"Voie De Li\u00e8ge 102 Welkenraedt Li\u00e8ge 4840",
    "addr:housenumber":"102",
    "addr:postcode":"4840",
    "addr:street":"Voie De Lie\u0300Ge",
    "iso:country":"BE",
    "sg:address":"Voie De Li\u00e8ge 102",
    "sg:city":"Welkenraedt",
    "sg:classifiers":[
        {
            "category":"Home & Garden",
            "subcategory":"Carpets & Floor Coverings",
            "type":"Retail Goods"
        }
    ],
    "sg:phone":"+32 87 88 30 18",
    "sg:postcode":"4840",
    "sg:province":"Li\u00e8ge",
    "sg:tags":[
        "tile"
    ],
    "wof:name":"Serge Carrelage",
    "wof:placetype":"venue"
},
  "geometry": {"coordinates":[5.9790930748,50.6510124207],"type":"Point"}
}