{
  "type": "Feature",
  "properties": {
    "addr:full":"Rue Du Point Du Jour 3 Quevy Hainaut 7040",
    "addr:housenumber":"3",
    "addr:postcode":"7040",
    "addr:street":"Rue Du Point Du Jour;Hainaut",
    "iso:country":"BE",
    "sg:address":"Rue Du Point Du Jour 3",
    "sg:city":"Quevy",
    "sg:orig_category":"Eleveurs de bovins",
    "sg:phone":"+32 65 56 83 68",
    "sg:postcode":"7040",
    "sg:province":"Hainaut",
    "wof:name":"Donchaux Clement Jean Pol",
    "wof:placetype":"venue"
},
  "geometry": {"coordinates":[3.9350121021,50.3716850281],"type":"Point"}
}