{
  "type": "Feature",
  "properties": {
    "addr:full":"Saffierstraat 33 Schaarbeek/schaerbeek Bruxelles-Capitale 1030",
    "addr:housenumber":"33",
    "addr:postcode":"1030",
    "addr:street":"Saffierstraat",
    "iso:country":"BE",
    "sg:address":"Saffierstraat 33",
    "sg:city":"Schaarbeek/schaerbeek",
    "sg:orig_category":"Artsen and specialisten",
    "sg:phone":"+32 2 735 15 15",
    "sg:postcode":"1030",
    "sg:province":"Bruxelles-Capitale",
    "wof:name":"W. Page",
    "wof:placetype":"venue"
},
  "geometry": {"coordinates":[4.3989238739,50.8532752991],"type":"Point"}
}