{
  "type": "Feature",
  "properties": {
    "addr:full":"Chauss\u00e9e D'ixelles 224 Bruxelles (ixelles) Bruxelles-Capitale 1050",
    "addr:housenumber":"224",
    "addr:postcode":"1050",
    "addr:street":"Chausse\u0301E D'Ixelles",
    "iso:country":"BE",
    "sg:address":"Chauss\u00e9e D'ixelles 224",
    "sg:city":"Bruxelles (ixelles)",
    "sg:classifiers":[
        {
            "category":"Education",
            "subcategory":"Music School",
            "type":"Public Place"
        }
    ],
    "sg:phone":"+32 2 640 01 03",
    "sg:postcode":"1050",
    "sg:province":"Bruxelles-Capitale",
    "sg:tags":[
        "-",
        "teacher",
        "private"
    ],
    "wof:name":"Chaise Musicale (la)",
    "wof:placetype":"venue"
},
  "geometry": {"coordinates":[4.3689341545,50.8309783936],"type":"Point"}
}