{
  "type": "Feature",
  "properties": {
    "addr:full":"Boulevard Cuivre Et Zinc 35 Li\u00e8ge 1 (grivegn\u00e9e) Li\u00e8ge 4030",
    "addr:housenumber":"35;1",
    "addr:postcode":"4030",
    "addr:street":"Boulevard Cuivre Et Zinc",
    "iso:country":"BE",
    "sg:address":"Boulevard Cuivre Et Zinc 35",
    "sg:city":"Li\u00e8ge 1 (grivegn\u00e9e)",
    "sg:orig_category":"Newspapers, magazines, periodicals - Distribution",
    "sg:phone":"+32 4 340 21 10",
    "sg:postcode":"4030",
    "sg:province":"Li\u00e8ge",
    "wof:name":"Distrisud Bellens Sa",
    "wof:placetype":"venue"
},
  "geometry": {"coordinates":[5.5929441452,50.6234588623],"type":"Point"}
}