{
  "type": "Feature",
  "properties": {
    "addr:full":"Zandstraat 14a Lichtervelde West-Vlaanderen 8810",
    "addr:housenumber":"14a",
    "addr:postcode":"8810",
    "addr:street":"Zandstraat",
    "iso:country":"BE",
    "sg:address":"Zandstraat 14a",
    "sg:city":"Lichtervelde",
    "sg:classifiers":[
        {
            "category":"Travel",
            "subcategory":"Resort",
            "type":"Entertainment"
        }
    ],
    "sg:phone":"+32 51 72 62 69",
    "sg:postcode":"8810",
    "sg:province":"West-Vlaanderen",
    "sg:tags":[
        "health"
    ],
    "wof:name":"Shiva",
    "wof:placetype":"venue"
},
  "geometry": {"coordinates":[3.1360049248,51.0282058716],"type":"Point"}
}