{
  "type": "Feature",
  "properties": {
    "addr:full":"Stationsstraat 22 Avelgem West-Vlaanderen 8580",
    "addr:housenumber":"22",
    "addr:postcode":"8580",
    "addr:street":"Stationsstraat",
    "iso:country":"BE",
    "sg:address":"Stationsstraat 22",
    "sg:city":"Avelgem",
    "sg:orig_category":"Tabac. Journaux",
    "sg:phone":"+32 56 64 61 86",
    "sg:postcode":"8580",
    "sg:province":"West-Vlaanderen",
    "wof:name":"Anna Drouillon",
    "wof:placetype":"venue"
},
  "geometry": {"coordinates":[3.4432299137,50.7714233398],"type":"Point"}
}