{
  "type": "Feature",
  "properties": {
    "addr:full":"Heilighuisdreef 32 Gent Oost-Vlaanderen 9031",
    "addr:housenumber":"32",
    "addr:postcode":"9031",
    "addr:street":"Heilighuisdreef;Oost-Vlaanderen",
    "iso:country":"BE",
    "sg:address":"Heilighuisdreef 32",
    "sg:city":"Gent",
    "sg:orig_category":"Sportclubs",
    "sg:phone":"+32 9 227 28 67",
    "sg:postcode":"9031",
    "sg:province":"Oost-Vlaanderen",
    "wof:name":"B.b.c. Brother Gentson",
    "wof:placetype":"venue"
},
  "geometry": {"coordinates":[3.6471869946,51.041633606],"type":"Point"}
}