{
  "type": "Feature",
  "properties": {
    "iso:country":"BE",
    "sg:address":"Avenue De Haussy 3",
    "sg:city":"Manage",
    "sg:orig_category":"Mutualities",
    "sg:phone":"+32 64 54 05 58",
    "sg:postcode":"7170",
    "sg:province":"Hainaut",
    "wof:name":"Mutualit\u00e9 Chr\u00e9tienne",
    "wof:placetype":"venue"
},
  "geometry": {"coordinates":[4.2353701591,50.5030097961],"type":"Point"}
}