{
  "type": "Feature",
  "properties": {
    "addr:full":"Rue De L'equateur 21 Bruxelles (uccle) Bruxelles-Capitale 1180",
    "addr:housenumber":"21",
    "addr:postcode":"1180",
    "addr:street":"Rue De L'Equateur",
    "iso:country":"BE",
    "sg:address":"Rue De L'equateur 21",
    "sg:city":"Bruxelles (uccle)",
    "sg:classifiers":[
        {
            "category":"Professional",
            "subcategory":"Accounting & Tax Preparation",
            "type":"Services"
        }
    ],
    "sg:phone":"+32 2 375 89 51",
    "sg:postcode":"1180",
    "sg:province":"Bruxelles-Capitale",
    "sg:tags":[
        "bookkeeper"
    ],
    "wof:name":"Mastalski & Brodzka Sprl",
    "wof:placetype":"venue"
},
  "geometry": {"coordinates":[4.3626317978,50.7955627441],"type":"Point"}
}