{
  "type": "Feature",
  "properties": {
    "iso:country":"BE",
    "sg:address":"Vogelmarkt 11",
    "sg:city":"Gent",
    "sg:classifiers":[
        {
            "category":"Health Services",
            "subcategory":"Hospital",
            "type":"Services"
        }
    ],
    "sg:phone":"+32 9 224 80 66",
    "sg:postcode":"9000",
    "sg:province":"Oost-Vlaanderen",
    "wof:name":"Progecov Vzw",
    "wof:placetype":"venue"
},
  "geometry": {"coordinates":[3.7259540558,51.0504188538],"type":"Point"}
}