{
  "type": "Feature",
  "properties": {
    "addr:full":"Van Hemelrijcklei 5 Brasschaat Antwerpen 2930",
    "addr:housenumber":"5",
    "addr:postcode":"2930",
    "iso:country":"BE",
    "sg:address":"Van Hemelrijcklei 5",
    "sg:city":"Brasschaat",
    "sg:orig_category":"Tweedehandsgoederen Verlichting and huishoudartikelen",
    "sg:phone":"+32 3 651 46 06",
    "sg:postcode":"2930",
    "sg:province":"Antwerpen",
    "wof:name":"Oxfam Wereldwinkel",
    "wof:placetype":"venue"
},
  "geometry": {"coordinates":[4.4943590164,51.2930107117],"type":"Point"}
}