{
  "type": "Feature",
  "properties": {
    "iso:country":"BE",
    "sg:address":"Dokter Louis Schuermansstraat 15",
    "sg:city":"Turnhout",
    "sg:classifiers":[
        {
            "category":"Health Services",
            "subcategory":"Doctor",
            "type":"Services"
        }
    ],
    "sg:phone":"+32 14 41 20 50",
    "sg:postcode":"2300",
    "sg:province":"Antwerpen",
    "sg:tags":[
        "medicinephysicians",
        "surgeon"
    ],
    "wof:name":"Desart A",
    "wof:placetype":"venue"
},
  "geometry": {"coordinates":[4.9615950584,51.3047142029],"type":"Point"}
}