{
  "type": "Feature",
  "properties": {
    "iso:country":"BE",
    "sg:address":"138",
    "sg:city":"Boulevard Du Jubile 1080 Bruxelles",
    "sg:classifiers":[
        {
            "category":"Professional",
            "subcategory":"Engineering",
            "type":"Services"
        }
    ],
    "sg:phone":"+32 2 425 15 15",
    "sg:postcode":"138",
    "sg:tags":[
        "machine",
        "-",
        "mechanical"
    ],
    "wof:name":"Jubile Automobile Sa",
    "wof:placetype":"venue"
},
  "geometry": {"coordinates":[4.3374252319,50.8645706177],"type":"Point"}
}