{
  "type": "Feature",
  "properties": {
    "addr:full":"Nicolaylaan 45 Leopoldsburg Limburg 3970",
    "addr:housenumber":"45",
    "addr:postcode":"3970",
    "addr:street":"Nicolaylaan",
    "iso:country":"BE",
    "sg:address":"Nicolaylaan 45",
    "sg:city":"Leopoldsburg",
    "sg:orig_category":"Slagers",
    "sg:phone":"+32 11 34 61 25",
    "sg:postcode":"3970",
    "sg:province":"Limburg",
    "wof:name":"Jacques Vereecke",
    "wof:placetype":"venue"
},
  "geometry": {"coordinates":[5.2587032318,51.1168785095],"type":"Point"}
}