{
  "type": "Feature",
  "properties": {
    "addr:full":"Rue De Ch\u00c2telet 17ba Gerpinnes Hainaut 6280",
    "addr:housenumber":"17ba",
    "addr:postcode":"6280",
    "addr:street":"Rue De Cha\u0302Telet;Hainaut",
    "iso:country":"BE",
    "sg:address":"Rue De Ch\u00c2telet 17ba",
    "sg:city":"Gerpinnes",
    "sg:orig_category":"R\u00e9alisation de programmes and logiciels. Conseils en syst\u00e8mes informatiques. Entretien and r\u00e9paratio",
    "sg:phone":"+32 71 50 50 66",
    "sg:postcode":"6280",
    "sg:province":"Hainaut",
    "wof:name":"Bureau Informatique Akela",
    "wof:placetype":"venue"
},
  "geometry": {"coordinates":[4.5654101372,50.3567695618],"type":"Point"}
}