{
  "type": "Feature",
  "properties": {
    "addr:full":"Sparrentuin 3 Waregem West-Vlaanderen 8793",
    "addr:housenumber":"3",
    "addr:postcode":"8793",
    "addr:street":"Sparrentuin",
    "iso:country":"BE",
    "sg:address":"Sparrentuin 3",
    "sg:city":"Waregem",
    "sg:classifiers":[
        {
            "category":"Professional",
            "subcategory":"Accounting & Tax Preparation",
            "type":"Services"
        }
    ],
    "sg:phone":"+32 56 60 25 87",
    "sg:postcode":"8793",
    "sg:province":"West-Vlaanderen",
    "sg:tags":[
        "accountant"
    ],
    "wof:name":"Filip Debel",
    "wof:placetype":"venue"
},
  "geometry": {"coordinates":[3.3929159641,50.8993682861],"type":"Point"}
}