{
  "type": "Feature",
  "properties": {
    "iso:country":"BE",
    "sg:address":"Rue Edouard Anseele 12",
    "sg:city":"Charleroi",
    "sg:orig_category":"Bagage and lederwaren",
    "sg:phone":"+32 71 34 30 46",
    "sg:postcode":"6040",
    "sg:province":"Hainaut",
    "wof:name":"Kakakis Savas",
    "wof:placetype":"venue"
},
  "geometry": {"coordinates":[4.4111328125,50.4420433044],"type":"Point"}
}