{
  "type": "Feature",
  "properties": {
    "iso:country":"BE",
    "sg:address":"Rue Chisaire 13",
    "sg:city":"Mons",
    "sg:orig_category":"Artsen and specialisten",
    "sg:phone":"+32 65 35 45 79",
    "sg:postcode":"7000",
    "sg:province":"Hainaut",
    "wof:name":"J.p. Merlin",
    "wof:placetype":"venue"
},
  "geometry": {"coordinates":[3.9427928925,50.4513511658],"type":"Point"}
}