{
  "type": "Feature",
  "properties": {
    "iso:country":"BE",
    "sg:address":"Zandstraat 162",
    "sg:city":"Turnhout",
    "sg:orig_category":"Sportclubs",
    "sg:phone":"+32 14 41 01 16",
    "sg:postcode":"2300",
    "sg:province":"Antwerpen",
    "wof:name":"White Caps",
    "wof:placetype":"venue"
},
  "geometry": {"coordinates":[4.9280948639,51.3195838928],"type":"Point"}
}