{
  "type": "Feature",
  "properties": {
    "iso:country":"BE",
    "sg:address":"Goedmoedstraat 18",
    "sg:city":"Brugge (assebroek)",
    "sg:classifiers":[
        {
            "category":"Professional",
            "subcategory":"Engineering",
            "type":"Services"
        }
    ],
    "sg:phone":"+32 476 67 07 81",
    "sg:postcode":"8310",
    "sg:province":"West-Vlaanderen",
    "sg:tags":[
        "environmental",
        "technique",
        "-"
    ],
    "wof:name":"Emonument",
    "wof:placetype":"venue"
},
  "geometry": {"coordinates":[3.2796599865,51.2128486633],"type":"Point"}
}