{
  "type": "Feature",
  "properties": {
    "addr:full":"Avenue Eug\u00c8ne Mascaux 484 Charleroi Hainaut 6001",
    "addr:housenumber":"484",
    "addr:postcode":"6001",
    "addr:street":"Avenue Euge\u0300Ne Mascaux;Hainaut",
    "iso:country":"BE",
    "sg:address":"Avenue Eug\u00c8ne Mascaux 484",
    "sg:city":"Charleroi",
    "sg:orig_category":"Banques and organismes de cr\u00e9dit",
    "sg:phone":"+32 71 36 94 50",
    "sg:postcode":"6001",
    "sg:province":"Hainaut",
    "wof:name":"Bbl",
    "wof:placetype":"venue"
},
  "geometry": {"coordinates":[4.4448251724,50.3973655701],"type":"Point"}
}