{
  "type": "Feature",
  "properties": {
    "addr:full":"Hooiwege 49 Evergem Oost-Vlaanderen 9940",
    "addr:housenumber":"49",
    "addr:postcode":"9940",
    "addr:street":"Hooiwege;Oost-Vlaanderen",
    "iso:country":"BE",
    "sg:address":"Hooiwege 49",
    "sg:city":"Evergem",
    "sg:classifiers":[
        {
            "category":"Restaurant",
            "type":"Food & Drink"
        }
    ],
    "sg:phone":"+32 9 357 68 15",
    "sg:postcode":"9940",
    "sg:province":"Oost-Vlaanderen",
    "wof:name":"Pattaya",
    "wof:placetype":"venue"
},
  "geometry": {"coordinates":[3.675467968,51.1410636902],"type":"Point"}
}