{
  "type": "Feature",
  "properties": {
    "addr:full":"Place Joseph Wauters 16 Fl\u00e9malle Li\u00e8ge 4400",
    "addr:housenumber":"16",
    "addr:postcode":"4400",
    "addr:street":"Place Joseph Wauters",
    "iso:country":"BE",
    "sg:address":"Place Joseph Wauters 16",
    "sg:city":"Fl\u00e9malle",
    "sg:classifiers":[
        {
            "category":"Personal",
            "subcategory":"Beauty Salon",
            "type":"Services"
        }
    ],
    "sg:phone":"+32 4 233 35 38",
    "sg:postcode":"4400",
    "sg:province":"Li\u00e8ge",
    "wof:name":"Aigue Marine",
    "wof:placetype":"venue"
},
  "geometry": {"coordinates":[5.4737710953,50.6147918701],"type":"Point"}
}