{
  "type": "Feature",
  "properties": {
    "addr:full":"Luikersteenweg 41 Sint-truiden Limburg 3800",
    "addr:housenumber":"41",
    "addr:postcode":"3800",
    "addr:street":"Luikersteenweg",
    "iso:country":"BE",
    "sg:address":"Luikersteenweg 41",
    "sg:city":"Sint-truiden",
    "sg:classifiers":[
        {
            "category":"Bars & Pubs",
            "type":"Food & Drink"
        }
    ],
    "sg:phone":"+32 11 69 40 13",
    "sg:postcode":"3800",
    "sg:province":"Limburg",
    "wof:name":"Shable",
    "wof:placetype":"venue"
},
  "geometry": {"coordinates":[5.1900191307,50.8112716675],"type":"Point"}
}