{
  "type": "Feature",
  "properties": {
    "addr:full":"Rue De La R\u00c9gence 26 Charleroi Hainaut 6000",
    "addr:housenumber":"26",
    "addr:postcode":"6000",
    "addr:street":"Rue De La Re\u0301Gence;Hainaut",
    "iso:country":"BE",
    "sg:address":"Rue De La R\u00c9gence 26",
    "sg:city":"Charleroi",
    "sg:orig_category":"Warenhuizen",
    "sg:phone":"+32 71 32 80 10",
    "sg:postcode":"6000",
    "sg:province":"Hainaut",
    "wof:name":"Filoma",
    "wof:placetype":"venue"
},
  "geometry": {"coordinates":[4.4457330704,50.4129676819],"type":"Point"}
}