{
  "type": "Feature",
  "properties": {
    "iso:country":"BE",
    "sg:address":"Stationsstraat 46b1",
    "sg:city":"Mechelen",
    "sg:orig_category":"Ordinateurs and \u00e9quipement informatique",
    "sg:phone":"+32 15 43 61 59",
    "sg:postcode":"2800",
    "sg:province":"Antwerpen",
    "wof:name":"Data Management Consulting",
    "wof:placetype":"venue"
},
  "geometry": {"coordinates":[4.4831981659,51.0187149048],"type":"Point"}
}