{
  "type": "Feature",
  "properties": {
    "addr:full":"Chauss\u00c9e De Louvain 948 Evere Bruxelles-Capitale 1140",
    "addr:housenumber":"948",
    "addr:postcode":"1140",
    "addr:street":"Chausse\u0301E De Louvain",
    "iso:country":"BE",
    "sg:address":"Chauss\u00c9e De Louvain 948",
    "sg:city":"Evere",
    "sg:classifiers":[
        {
            "category":"Personal",
            "subcategory":"Beauty Salon",
            "type":"Services"
        }
    ],
    "sg:phone":"+32 2 726 62 44",
    "sg:postcode":"1140",
    "sg:province":"Bruxelles-Capitale",
    "sg:tags":[
        "de",
        "coiffure"
    ],
    "wof:name":"Coiffure Jehanne",
    "wof:placetype":"venue"
},
  "geometry": {"coordinates":[4.4154949188,50.8591918945],"type":"Point"}
}