{
  "type": "Feature",
  "properties": {
    "iso:country":"BE",
    "sg:address":"Oostrozebekestraat 4",
    "sg:city":"Ingelmunster",
    "sg:orig_category":"Overheidsdiensten",
    "sg:phone":"+32 51 31 13 03",
    "sg:postcode":"8770",
    "sg:province":"West-Vlaanderen",
    "wof:name":"O.c.m.w.",
    "wof:placetype":"venue"
},
  "geometry": {"coordinates":[3.2553720474,50.9202537537],"type":"Point"}
}