{
  "type": "Feature",
  "properties": {
    "iso:country":"BE",
    "sg:address":"Statiestraat 33",
    "sg:city":"Diest",
    "sg:classifiers":[
        {
            "category":"Building & Trades",
            "subcategory":"Construction",
            "type":"Services"
        }
    ],
    "sg:phone":"+32 13 52 37 27",
    "sg:postcode":"3290",
    "sg:province":"Vlaams-Brabant",
    "sg:tags":[
        "truss-makers"
    ],
    "wof:name":"Spronken Orthopedie",
    "wof:placetype":"venue"
},
  "geometry": {"coordinates":[5.0498018265,50.988155365],"type":"Point"}
}