{
  "type": "Feature",
  "properties": {
    "addr:full":"Avenue Wanderpepen 15 Binche Hainaut 7130",
    "addr:housenumber":"15",
    "addr:postcode":"7130",
    "addr:street":"Avenue Wanderpepen",
    "iso:country":"BE",
    "sg:address":"Avenue Wanderpepen 15",
    "sg:city":"Binche",
    "sg:classifiers":[
        {
            "category":"Personal",
            "subcategory":"Barber",
            "type":"Services"
        }
    ],
    "sg:phone":"+32 64 33 69 46",
    "sg:postcode":"7130",
    "sg:province":"Hainaut",
    "sg:tags":[
        "gentleman",
        "salon",
        "-",
        "hairdressing"
    ],
    "wof:name":"Gillain M",
    "wof:placetype":"venue"
},
  "geometry": {"coordinates":[4.1686038971,50.41223526],"type":"Point"}
}