{
  "type": "Feature",
  "properties": {
    "iso:country":"BE",
    "sg:address":"Voie D'hainin 17",
    "sg:city":"Dour",
    "sg:classifiers":[
        {
            "category":"Cafe",
            "type":"Food & Drink"
        }
    ],
    "sg:phone":"+32 65 65 11 38",
    "sg:postcode":"7370",
    "sg:province":"Hainaut",
    "sg:tags":[
        "caf\u00e9s"
    ],
    "wof:name":"Roberto Di Antonio",
    "wof:placetype":"venue"
},
  "geometry": {"coordinates":[3.7787408829,50.4032974243],"type":"Point"}
}