{
  "type": "Feature",
  "properties": {
    "addr:full":"Klinkstraat 3 Turnhout Antwerpen 2300",
    "addr:housenumber":"3",
    "addr:postcode":"2300",
    "addr:street":"Klinkstraat",
    "iso:country":"BE",
    "sg:address":"Klinkstraat 3",
    "sg:city":"Turnhout",
    "sg:orig_category":"Technisch and beroeps secundair onderwijs",
    "sg:phone":"+32 14 41 23 92",
    "sg:postcode":"2300",
    "sg:province":"Antwerpen",
    "wof:name":"St.lutgardisinstituut",
    "wof:placetype":"venue"
},
  "geometry": {"coordinates":[4.9533400536,51.3223495483],"type":"Point"}
}