{
  "type": "Feature",
  "properties": {
    "addr:full":"Fraterstraat 37 Merelbeke Oost-Vlaanderen 9820",
    "addr:housenumber":"37",
    "addr:postcode":"9820",
    "addr:street":"Fraterstraat",
    "iso:country":"BE",
    "sg:address":"Fraterstraat 37",
    "sg:city":"Merelbeke",
    "sg:classifiers":[
        {
            "category":"Building & Trades",
            "subcategory":"Plumbing",
            "type":"Services"
        }
    ],
    "sg:phone":"+32 9 230 55 36",
    "sg:postcode":"9820",
    "sg:province":"Oost-Vlaanderen",
    "sg:tags":[
        "repair",
        "mainten",
        "-",
        "central",
        "heating"
    ],
    "wof:name":"Van Damme Willy & Zn Bvba",
    "wof:placetype":"venue"
},
  "geometry": {"coordinates":[3.7614569664,51.0125579834],"type":"Point"}
}