{
  "type": "Feature",
  "properties": {
    "iso:country":"BE",
    "sg:address":"Chemin Aux Loups 20",
    "sg:city":"Braine-le-comte",
    "sg:orig_category":"Eleveurs de bovins",
    "sg:phone":"+32 67 55 33 93",
    "sg:postcode":"7090",
    "sg:province":"Hainaut",
    "wof:name":"Didier Grisez",
    "wof:placetype":"venue"
},
  "geometry": {"coordinates":[4.1779289246,50.5992507935],"type":"Point"}
}