{
  "type": "Feature",
  "properties": {
    "addr:full":"Scarphoutdreef 2 Merksplas Antwerpen 2330",
    "addr:housenumber":"2",
    "addr:postcode":"2330",
    "addr:street":"Scarphoutdreef",
    "iso:country":"BE",
    "sg:address":"Scarphoutdreef 2",
    "sg:city":"Merksplas",
    "sg:orig_category":"Woningbouw",
    "sg:phone":"+32 14 63 47 63",
    "sg:postcode":"2330",
    "sg:province":"Antwerpen",
    "wof:name":"Bouwwerken Meulders",
    "wof:placetype":"venue"
},
  "geometry": {"coordinates":[4.8464012146,51.3972969055],"type":"Point"}
}