{
  "type": "Feature",
  "properties": {
    "iso:country":"BE",
    "sg:address":"Rue Fontaine De Spa 5",
    "sg:city":"Morlanwelz",
    "sg:orig_category":"Installation de menuiserie en bois and plastique",
    "sg:phone":"+32 64 21 13 83",
    "sg:postcode":"7140",
    "sg:province":"Hainaut",
    "wof:name":"Ets. Delchambre",
    "wof:placetype":"venue"
},
  "geometry": {"coordinates":[4.2210202217,50.4648742676],"type":"Point"}
}