{
  "type": "Feature",
  "properties": {
    "iso:country":"BE",
    "sg:address":"Rue Saint-ghislain 16",
    "sg:city":"Brussel/bruxelles",
    "sg:orig_category":"R\u00e9parations de chaussures and articles en cuir. Magasins de r\u00e9parations d'articles personnels et m\u00e9n",
    "sg:phone":"+32 2 511 71 18",
    "sg:postcode":"1000",
    "sg:province":"Bruxelles-Capitale",
    "wof:name":"Rivero Tomas",
    "wof:placetype":"venue"
},
  "geometry": {"coordinates":[4.3469119072,50.8394317627],"type":"Point"}
}