{
  "type": "Feature",
  "properties": {
    "addr:full":"Kleempoelstraat 52 Zemst Vlaams-Brabant 1980",
    "addr:housenumber":"52",
    "addr:postcode":"1980",
    "addr:street":"Kleempoelstraat;Vlaams-Brabant",
    "iso:country":"BE",
    "sg:address":"Kleempoelstraat 52",
    "sg:city":"Zemst",
    "sg:classifiers":[
        {
            "category":"Retail",
            "subcategory":"Auto Repair",
            "type":"Services"
        }
    ],
    "sg:phone":"+32 15 61 10 77",
    "sg:postcode":"1980",
    "sg:province":"Vlaams-Brabant",
    "sg:tags":[
        "automobile-body"
    ],
    "wof:name":"Houman Garage-carrosserie",
    "wof:placetype":"venue"
},
  "geometry": {"coordinates":[4.4513859749,50.9859237671],"type":"Point"}
}