{
  "type": "Feature",
  "properties": {
    "iso:country":"BE",
    "sg:address":"Mechelsevest 72",
    "sg:city":"Leuven",
    "sg:classifiers":[
        {
            "category":"Education",
            "subcategory":"School",
            "type":"Public Place"
        }
    ],
    "sg:phone":"+32 16 23 69 51",
    "sg:postcode":"3000",
    "sg:province":"Vlaams-Brabant",
    "sg:tags":[
        "secondary"
    ],
    "wof:name":"De Wijnpers",
    "wof:placetype":"venue"
},
  "geometry": {"coordinates":[4.6988329887,50.8824691772],"type":"Point"}
}