{
  "type": "Feature",
  "properties": {
    "addr:full":"Grote Markt 65 Sint-truiden Limburg 3800",
    "addr:housenumber":"65",
    "addr:postcode":"3800",
    "addr:street":"Grote Markt",
    "iso:country":"BE",
    "sg:address":"Grote Markt 65",
    "sg:city":"Sint-truiden",
    "sg:orig_category":"Geschenken and souvenirs Verlichting and huishoudartikelen",
    "sg:phone":"+32 11 69 65 79",
    "sg:postcode":"3800",
    "sg:province":"Limburg",
    "wof:name":"Huis Divine",
    "wof:placetype":"venue"
},
  "geometry": {"coordinates":[5.1870141029,50.8159980774],"type":"Point"}
}