{
  "type": "Feature",
  "properties": {
    "addr:full":"Warnach 4b Fauvillers (tintange) Luxembourg 6637",
    "addr:housenumber":"4b",
    "addr:postcode":"6637",
    "addr:street":"Warnach",
    "iso:country":"BE",
    "sg:address":"Warnach 4b",
    "sg:city":"Fauvillers (tintange)",
    "sg:classifiers":[
        {
            "category":"Communications",
            "type":"Services"
        }
    ],
    "sg:phone":"+32 63 43 45 48",
    "sg:postcode":"6637",
    "sg:province":"Luxembourg",
    "sg:tags":[
        "translator"
    ],
    "wof:name":"Cenne B",
    "wof:placetype":"venue"
},
  "geometry": {"coordinates":[5.6638197899,49.8519592285],"type":"Point"}
}