{
  "type": "Feature",
  "properties": {
    "addr:full":"Rue De L\u00b4angle 3 Brussel/bruxelles Bruxelles-Capitale 1000",
    "addr:housenumber":"3",
    "addr:postcode":"1000",
    "addr:street":"Rue De L\u00b4Angle;/",
    "iso:country":"BE",
    "sg:address":"Rue De L\u00b4angle 3",
    "sg:city":"Brussel/bruxelles",
    "sg:orig_category":"M\u00e9decins and sp\u00e9cialistes",
    "sg:phone":"+32 2 203 05 91",
    "sg:postcode":"1000",
    "sg:province":"Bruxelles-Capitale",
    "wof:name":"G\u00c9raldine Kono Mballa",
    "wof:placetype":"venue"
},
  "geometry": {"coordinates":[4.3522782326,50.8573379517],"type":"Point"}
}