{
  "type": "Feature",
  "properties": {
    "addr:full":"Strandlaan 241 Koksijde West-Vlaanderen 8670",
    "addr:housenumber":"241",
    "addr:postcode":"8670",
    "addr:street":"Strandlaan",
    "iso:country":"BE",
    "sg:address":"Strandlaan 241",
    "sg:city":"Koksijde",
    "sg:orig_category":"Blanchisseries and teintureries",
    "sg:phone":"+32 58 51 55 20",
    "sg:postcode":"8670",
    "sg:province":"West-Vlaanderen",
    "wof:name":"Droogkuis De Welkom",
    "wof:placetype":"venue"
},
  "geometry": {"coordinates":[2.6135759354,51.1082801819],"type":"Point"}
}