{
  "type": "Feature",
  "properties": {
    "iso:country":"BE",
    "sg:address":"Rue C\u00c9sar De Paepe 52",
    "sg:city":"Soumagne",
    "sg:orig_category":"Pain, p\u00e2tisseries and confiseries",
    "sg:phone":"+32 4 377 63 01",
    "sg:postcode":"4630",
    "sg:province":"Li\u00e8ge",
    "wof:name":"Boulangerie Riga",
    "wof:placetype":"venue"
},
  "geometry": {"coordinates":[5.7346000671,50.6324996948],"type":"Point"}
}