{
  "type": "Feature",
  "properties": {
    "addr:full":"Rue Paul Emile Janson 3a Bruxelles Bruxelles-Capitale 1000",
    "addr:housenumber":"3a",
    "addr:postcode":"1000",
    "addr:street":"Rue Paul Emile Janson",
    "iso:country":"BE",
    "sg:address":"Rue Paul Emile Janson 3a",
    "sg:city":"Bruxelles",
    "sg:classifiers":[
        {
            "category":"Health Services",
            "subcategory":"Dentist",
            "type":"Services"
        }
    ],
    "sg:phone":"+32 2 537 73 96",
    "sg:postcode":"1000",
    "sg:province":"Bruxelles-Capitale",
    "wof:name":"Dekie Jean-claude",
    "wof:placetype":"venue"
},
  "geometry": {"coordinates":[4.3615779877,50.8279762268],"type":"Point"}
}