{
  "type": "Feature",
  "properties": {
    "iso:country":"BE",
    "sg:address":"Liersesteenweg 29",
    "sg:city":"Berlaar",
    "sg:classifiers":[
        {
            "category":"Building & Trades",
            "subcategory":"Construction",
            "type":"Services"
        }
    ],
    "sg:phone":"+32 3 420 00 90",
    "sg:postcode":"2590",
    "sg:province":"Antwerpen",
    "sg:tags":[
        "ceiling"
    ],
    "wof:name":"Armalu",
    "wof:placetype":"venue"
},
  "geometry": {"coordinates":[4.647808075,51.1171035767],"type":"Point"}
}