{
  "type": "Feature",
  "properties": {
    "addr:full":"Meyerode 73 Amel (meyerode) Li\u00e8ge 4770",
    "addr:housenumber":"73",
    "addr:postcode":"4770",
    "addr:street":"Meyerode;Meyerode",
    "iso:country":"BE",
    "sg:address":"Meyerode 73",
    "sg:city":"Amel (meyerode)",
    "sg:classifiers":[
        {
            "category":"Community Center",
            "subcategory":"Youth",
            "type":"Public Place"
        }
    ],
    "sg:phone":"+32 80 34 82 10",
    "sg:postcode":"4770",
    "sg:province":"Li\u00e8ge",
    "sg:tags":[
        "workshop",
        "sheltered"
    ],
    "wof:name":"Die Zukunft",
    "wof:placetype":"venue"
},
  "geometry": {"coordinates":[6.1689629555,50.3543167114],"type":"Point"}
}