{
  "type": "Feature",
  "properties": {
    "addr:full":"Demerstraat 33 Diest Vlaams-Brabant 3290",
    "addr:housenumber":"33",
    "addr:postcode":"3290",
    "addr:street":"Demerstraat",
    "iso:country":"BE",
    "sg:address":"Demerstraat 33",
    "sg:city":"Diest",
    "sg:classifiers":[
        {
            "category":"Manufacturing",
            "subcategory":"Textiles",
            "type":"Manufacturing & Wholesale Goods"
        }
    ],
    "sg:phone":"+32 13 31 15 80",
    "sg:postcode":"3290",
    "sg:province":"Vlaams-Brabant",
    "sg:tags":[
        "retail",
        "-"
    ],
    "wof:name":"Jonckers G",
    "wof:placetype":"venue"
},
  "geometry": {"coordinates":[5.0485501289,50.9870796204],"type":"Point"}
}