{
  "type": "Feature",
  "properties": {
    "iso:country":"BE",
    "sg:address":"Groenstraat 167",
    "sg:city":"Wilrijk",
    "sg:orig_category":"Bloemen and planten",
    "sg:phone":"+32 3 827 27 68",
    "sg:postcode":"2610",
    "sg:province":"Antwerpen",
    "wof:name":"Ketels Bloemen",
    "wof:placetype":"venue"
},
  "geometry": {"coordinates":[4.3588881493,51.1631622314],"type":"Point"}
}