{
  "type": "Feature",
  "properties": {
    "iso:country":"BE",
    "sg:address":"Gildestraat 14",
    "sg:city":"Kruibeke",
    "sg:classifiers":[
        {
            "category":"Bars & Pubs",
            "type":"Food & Drink"
        }
    ],
    "sg:phone":"+32 3 774 28 65",
    "sg:postcode":"9150",
    "sg:province":"Oost-Vlaanderen",
    "wof:name":"Lichttoren (de)",
    "wof:placetype":"venue"
},
  "geometry": {"coordinates":[4.3127708435,51.1751670837],"type":"Point"}
}