{
  "type": "Feature",
  "properties": {
    "iso:country":"BE",
    "sg:address":"Grand-rue 3",
    "sg:city":"Bouillon",
    "sg:orig_category":"Pharmaciens",
    "sg:phone":"+32 61 46 62 14",
    "sg:postcode":"6830",
    "sg:province":"Luxembourg",
    "wof:name":"Populaires Li\u00c8geoises",
    "wof:placetype":"venue"
},
  "geometry": {"coordinates":[5.0694198608,49.7953491211],"type":"Point"}
}