{
  "type": "Feature",
  "properties": {
    "iso:country":"BE",
    "sg:address":"Avenue Emile Herman 76a",
    "sg:city":"Manage (fayt-lez-manage)",
    "sg:classifiers":[
        {
            "category":"Insurance",
            "subcategory":"Insurance Agent",
            "type":"Services"
        }
    ],
    "sg:phone":"+32 64 55 83 53",
    "sg:postcode":"7170",
    "sg:province":"Hainaut",
    "sg:tags":[
        "broker"
    ],
    "wof:name":"Assurances G Bonnenge",
    "wof:placetype":"venue"
},
  "geometry": {"coordinates":[4.2266521454,50.4894332886],"type":"Point"}
}