{
  "type": "Feature",
  "properties": {
    "iso:country":"BE",
    "sg:address":"Edmond Picardstraat 36",
    "sg:city":"Elsene/ixelles",
    "sg:orig_category":"Artsen and specialisten",
    "sg:phone":"+32 2 344 42 60",
    "sg:postcode":"1050",
    "sg:province":"Bruxelles-Capitale",
    "wof:name":"C. Paternostre",
    "wof:placetype":"venue"
},
  "geometry": {"coordinates":[4.3543038368,50.8153610229],"type":"Point"}
}