{
  "type": "Feature",
  "properties": {
    "addr:full":"Antwerpsesteenweg 261 Mechelen Antwerpen 2800",
    "addr:housenumber":"261",
    "addr:postcode":"2800",
    "addr:street":"Antwerpsesteenweg",
    "iso:country":"BE",
    "sg:address":"Antwerpsesteenweg 261",
    "sg:city":"Mechelen",
    "sg:orig_category":"S\u00e9curit\u00e9 sociale",
    "sg:phone":"+32 15 21 58 11",
    "sg:postcode":"2800",
    "sg:province":"Antwerpen",
    "wof:name":"Christelijke Mutualiteit",
    "wof:placetype":"venue"
},
  "geometry": {"coordinates":[4.4606719017,51.0581855774],"type":"Point"}
}