{
  "type": "Feature",
  "properties": {
    "iso:country":"BE",
    "sg:address":"Rue De Cartier 49",
    "sg:city":"Charleroi",
    "sg:orig_category":"Mat\u00e9riel m\u00e9dical and orthop\u00e9dique and proth\u00e8ses Fab",
    "sg:phone":"+32 71 51 15 65",
    "sg:postcode":"6030",
    "sg:province":"Hainaut",
    "wof:name":"Art Et Technique",
    "wof:placetype":"venue"
},
  "geometry": {"coordinates":[4.3950939178,50.4035339355],"type":"Point"}
}