{
  "type": "Feature",
  "properties": {
    "addr:full":"Bogaardestraat 27 Maldegem Oost-Vlaanderen 9990",
    "addr:housenumber":"27",
    "addr:postcode":"9990",
    "addr:street":"Bogaardestraat",
    "iso:country":"BE",
    "sg:address":"Bogaardestraat 27",
    "sg:city":"Maldegem",
    "sg:classifiers":[
        {
            "category":"Real Estate",
            "subcategory":"Surveying",
            "type":"Services"
        }
    ],
    "sg:phone":"+32 50 72 00 65",
    "sg:postcode":"9990",
    "sg:province":"Oost-Vlaanderen",
    "sg:tags":[
        "lettering",
        "letter"
    ],
    "wof:name":"Qrt Publicity Art",
    "wof:placetype":"venue"
},
  "geometry": {"coordinates":[3.4403970242,51.2080307007],"type":"Point"}
}