{
  "type": "Feature",
  "properties": {
    "iso:country":"BE",
    "sg:address":"Marktstraat 49",
    "sg:city":"Oudenburg",
    "sg:orig_category":"Banques and organismes de cr\u00e9dit",
    "sg:phone":"+32 59 26 69 21",
    "sg:postcode":"8460",
    "sg:province":"West-Vlaanderen",
    "wof:name":"Bbl",
    "wof:placetype":"venue"
},
  "geometry": {"coordinates":[3.0067329407,51.184211731],"type":"Point"}
}