{
  "type": "Feature",
  "properties": {
    "addr:full":"Avenue Joseph Lejeune 30 Trois-ponts Li\u00e8ge 4980",
    "addr:housenumber":"30",
    "addr:postcode":"4980",
    "addr:street":"Avenue Joseph Lejeune",
    "iso:country":"BE",
    "sg:address":"Avenue Joseph Lejeune 30",
    "sg:city":"Trois-ponts",
    "sg:orig_category":"Installation \u00e9lectrique r\u00e9sidentielle",
    "sg:phone":"+32 80 68 44 54",
    "sg:postcode":"4980",
    "sg:province":"Li\u00e8ge",
    "wof:name":"Robert Moutschen",
    "wof:placetype":"venue"
},
  "geometry": {"coordinates":[5.8659949303,50.3695259094],"type":"Point"}
}