{
  "type": "Feature",
  "properties": {
    "addr:full":"Edouard Rooselaersstraat 33 Sint-pieters-leeuw Vlaams-Brabant 1600",
    "addr:housenumber":"33",
    "addr:postcode":"1600",
    "addr:street":"Rooselaersstraat",
    "iso:country":"BE",
    "sg:address":"Edouard Rooselaersstraat 33",
    "sg:city":"Sint-pieters-leeuw",
    "sg:classifiers":[
        {
            "category":"Banks & Credit Unions",
            "subcategory":"Investment Brokerage",
            "type":"Services"
        }
    ],
    "sg:phone":"+32 2 361 33 95",
    "sg:postcode":"1600",
    "sg:province":"Vlaams-Brabant",
    "sg:tags":[
        "fence"
    ],
    "wof:name":"Beauty Garden",
    "wof:placetype":"venue"
},
  "geometry": {"coordinates":[4.2509860992,50.7805557251],"type":"Point"}
}