{
  "type": "Feature",
  "properties": {
    "iso:country":"BE",
    "sg:address":"Chauss\u00c9e De Mons 3",
    "sg:city":"Anderlecht",
    "sg:orig_category":"Telecommunicatieapparaten",
    "sg:phone":"+32 2 524 14 14",
    "sg:postcode":"1070",
    "sg:province":"Bruxelles-Capitale",
    "wof:name":"Gsm Planet",
    "wof:placetype":"venue"
},
  "geometry": {"coordinates":[4.2891402245,50.8080978394],"type":"Point"}
}