{
  "type": "Feature",
  "properties": {
    "addr:full":"Rue Neuve 253 Colfontaine Hainaut 7340",
    "addr:housenumber":"253",
    "addr:postcode":"7340",
    "addr:street":"Rue Neuve",
    "iso:country":"BE",
    "sg:address":"Rue Neuve 253",
    "sg:city":"Colfontaine",
    "sg:orig_category":"Epiceries",
    "sg:phone":"+32 65 67 24 52",
    "sg:postcode":"7340",
    "sg:province":"Hainaut",
    "wof:name":"Bien-etre",
    "wof:placetype":"venue"
},
  "geometry": {"coordinates":[3.8500590324,50.3983573914],"type":"Point"}
}