{
  "type": "Feature",
  "properties": {
    "iso:country":"BE",
    "sg:address":"Nieuwstraat 36",
    "sg:city":"Retie",
    "sg:orig_category":"Banques and organismes de cr\u00e9dit",
    "sg:phone":"+32 14 37 80 68",
    "sg:postcode":"2470",
    "sg:province":"Antwerpen",
    "wof:name":"Citibank",
    "wof:placetype":"venue"
},
  "geometry": {"coordinates":[5.0830497742,51.2622833252],"type":"Point"}
}