{
  "type": "Feature",
  "properties": {
    "addr:full":"Rue Du Grand Feu 102 Namur Namur 5004",
    "addr:housenumber":"102",
    "addr:postcode":"5004",
    "addr:street":"Rue Du Grand Feu",
    "iso:country":"BE",
    "sg:address":"Rue Du Grand Feu 102",
    "sg:city":"Namur",
    "sg:orig_category":"M\u00e9decines alternatives",
    "sg:phone":"+32 81 21 51 78",
    "sg:postcode":"5004",
    "sg:province":"Namur",
    "wof:name":"Michel Mahiat",
    "wof:placetype":"venue"
},
  "geometry": {"coordinates":[4.8986048698,50.4727172852],"type":"Point"}
}