{
  "type": "Feature",
  "properties": {
    "addr:full":"Koning Albertlaan 143 Gent Oost-Vlaanderen 9000",
    "addr:housenumber":"143",
    "addr:postcode":"9000",
    "addr:street":"Koning Albertlaan;Oost-Vlaanderen",
    "iso:country":"BE",
    "sg:address":"Koning Albertlaan 143",
    "sg:city":"Gent",
    "sg:orig_category":"M\u00e9decins and sp\u00e9cialistes",
    "sg:phone":"+32 9 222 24 02",
    "sg:postcode":"9000",
    "sg:province":"Oost-Vlaanderen",
    "wof:name":"M. Vrijens",
    "wof:placetype":"venue"
},
  "geometry": {"coordinates":[3.7100930214,51.0416717529],"type":"Point"}
}