{
  "type": "Feature",
  "properties": {
    "iso:country":"BE",
    "sg:address":"Chauss\u00c9e De Tongres 494",
    "sg:city":"Liege",
    "sg:orig_category":"Emballages en plastique Fab. Papeteries. Agences de publicit\u00e9. V\u00eatements, chaussures and accessoires",
    "sg:phone":"+32 4 247 29 26",
    "sg:postcode":"4000",
    "sg:province":"Li\u00e8ge",
    "wof:name":"Omni-media",
    "wof:placetype":"venue"
},
  "geometry": {"coordinates":[5.5448150635,50.677947998],"type":"Point"}
}