{
  "type": "Feature",
  "properties": {
    "iso:country":"BE",
    "sg:address":"Kortrijksestraat 8",
    "sg:city":"Ardooie",
    "sg:orig_category":"Ladies' Hats",
    "sg:phone":"+32 51 74 50 98",
    "sg:postcode":"8850",
    "sg:province":"West-Vlaanderen",
    "wof:name":"Declercq & Declercq Nv",
    "wof:placetype":"venue"
},
  "geometry": {"coordinates":[3.1978709698,50.9779205322],"type":"Point"}
}