{
  "type": "Feature",
  "properties": {
    "iso:country":"BE",
    "sg:address":"Rue De Brionsart 15",
    "sg:city":"Gesves",
    "sg:classifiers":[
        {
            "category":"Retail",
            "subcategory":"Auto Repair",
            "type":"Services"
        }
    ],
    "sg:phone":"+32 83 67 79 72",
    "sg:postcode":"5340",
    "sg:province":"Namur",
    "sg:tags":[
        "garage"
    ],
    "wof:name":"Gesves Auto Sprl",
    "wof:placetype":"venue"
},
  "geometry": {"coordinates":[5.0751547813,50.4147567749],"type":"Point"}
}