{
  "type": "Feature",
  "properties": {
    "addr:full":"Rue De Li\u00e8ge 96 Li\u00e8ge 1 (jupille-sur-meuse) Li\u00e8ge 4020",
    "addr:housenumber":"96;1",
    "addr:postcode":"4020",
    "addr:street":"Rue De Lie\u0300Ge;Jupille-Sur-Meuse Lie\u0300Ge",
    "iso:country":"BE",
    "sg:address":"Rue De Li\u00e8ge 96",
    "sg:city":"Li\u00e8ge 1 (jupille-sur-meuse)",
    "sg:classifiers":[
        {
            "category":"Building & Trades",
            "subcategory":"Equipment Rental",
            "type":"Services"
        }
    ],
    "sg:phone":"+32 4 370 61 86",
    "sg:postcode":"4020",
    "sg:province":"Li\u00e8ge",
    "sg:tags":[
        "safety",
        "collective",
        "individual",
        "-"
    ],
    "wof:name":"Ravet-new Cobelca",
    "wof:placetype":"venue"
},
  "geometry": {"coordinates":[5.6158938408,50.6428833008],"type":"Point"}
}