{
  "type": "Feature",
  "properties": {
    "addr:full":"Burgemeester J. Van Aperenstraat 8 Hoogstraten Antwerpen 2320",
    "addr:housenumber":"8",
    "addr:postcode":"2320",
    "addr:street":"Burgemeester J. Van Aperenstraat",
    "iso:country":"BE",
    "sg:address":"Burgemeester J. Van Aperenstraat 8",
    "sg:city":"Hoogstraten",
    "sg:classifiers":[
        {
            "category":"Professional",
            "subcategory":"Lawyer & Legal Services",
            "type":"Services"
        }
    ],
    "sg:phone":"+32 3 314 51 77",
    "sg:postcode":"2320",
    "sg:province":"Antwerpen",
    "sg:tags":[
        "notary"
    ],
    "wof:name":"Michoel J",
    "wof:placetype":"venue"
},
  "geometry": {"coordinates":[4.7583708763,51.4004211426],"type":"Point"}
}