{
  "type": "Feature",
  "properties": {
    "addr:full":"Kasteelstraat 1 Tielt West-Vlaanderen 8700",
    "addr:housenumber":"1",
    "addr:postcode":"8700",
    "addr:street":"Kasteelstraat",
    "iso:country":"BE",
    "sg:address":"Kasteelstraat 1",
    "sg:city":"Tielt",
    "sg:orig_category":"Parfumeries",
    "sg:phone":"+32 51 40 25 45",
    "sg:postcode":"8700",
    "sg:province":"West-Vlaanderen",
    "wof:name":"Parfumerie Modern",
    "wof:placetype":"venue"
},
  "geometry": {"coordinates":[3.3251550198,50.9939613342],"type":"Point"}
}