{
  "type": "Feature",
  "properties": {
    "iso:country":"BE",
    "sg:address":"Rue Vandervelde 242",
    "sg:city":"Thuin",
    "sg:orig_category":"V\u00e9hicules automobiles",
    "sg:phone":"+32 71 59 13 72",
    "sg:postcode":"6534",
    "sg:province":"Hainaut",
    "wof:name":"Garage Berlier",
    "wof:placetype":"venue"
},
  "geometry": {"coordinates":[4.3218817711,50.3630867004],"type":"Point"}
}