{
  "type": "Feature",
  "properties": {
    "iso:country":"BE",
    "sg:address":"Avenue Adolphe Buyl 96",
    "sg:city":"Elsene/ixelles",
    "sg:orig_category":"Blanchisseries and teintureries",
    "sg:phone":"+32 2 648 10 30",
    "sg:postcode":"1050",
    "sg:province":"Bruxelles-Capitale",
    "wof:name":"Nettoyage \u00c0 Sec Clean",
    "wof:placetype":"venue"
},
  "geometry": {"coordinates":[4.3829569817,50.8161888123],"type":"Point"}
}