{
  "type": "Feature",
  "properties": {
    "iso:country":"BE",
    "sg:address":"Turnhoutsebaan 171",
    "sg:city":"Diest",
    "sg:orig_category":"Installation de menuiserie en bois and plastique",
    "sg:phone":"+32 13 32 32 38",
    "sg:postcode":"3290",
    "sg:province":"Vlaams-Brabant",
    "wof:name":"Princen R",
    "wof:placetype":"venue"
},
  "geometry": {"coordinates":[5.0516438484,50.9926795959],"type":"Point"}
}