{
  "type": "Feature",
  "properties": {
    "addr:full":"Leopoldplaats 1 Antwerpen Antwerpen 2000",
    "addr:housenumber":"1",
    "addr:postcode":"2000",
    "addr:street":"Leopoldplaats",
    "iso:country":"BE",
    "sg:address":"Leopoldplaats 1",
    "sg:city":"Antwerpen",
    "sg:classifiers":[
        {
            "category":"Cafe",
            "type":"Food & Drink"
        }
    ],
    "sg:phone":"+32 3 227 42 06",
    "sg:postcode":"2000",
    "sg:province":"Antwerpen",
    "sg:tags":[
        "caf\u00e9s"
    ],
    "wof:name":"Caf\u00c9 't Thaeterke",
    "wof:placetype":"venue"
},
  "geometry": {"coordinates":[4.4068989754,51.2126159668],"type":"Point"}
}