{
  "type": "Feature",
  "properties": {
    "iso:country":"BE",
    "sg:address":"Stoktevijver 57bd",
    "sg:city":"Zomergem",
    "sg:orig_category":"Loodgieterij, verwarming and sanitaire installaties",
    "sg:phone":"+32 9 372 62 59",
    "sg:postcode":"9932",
    "sg:province":"Oost-Vlaanderen",
    "wof:name":"Sani-service",
    "wof:placetype":"venue"
},
  "geometry": {"coordinates":[3.5589470863,51.1369514465],"type":"Point"}
}