{
  "type": "Feature",
  "properties": {
    "addr:full":"Rue De La Consolation 46 Schaarbeek/schaerbeek Bruxelles-Capitale 1030",
    "addr:housenumber":"46",
    "addr:postcode":"1030",
    "addr:street":"Rue De La Consolation",
    "iso:country":"BE",
    "sg:address":"Rue De La Consolation 46",
    "sg:city":"Schaarbeek/schaerbeek",
    "sg:orig_category":"Activit\u00e9s diverses d'imprimerie",
    "sg:phone":"+32 2 241 87 19",
    "sg:postcode":"1030",
    "sg:province":"Bruxelles-Capitale",
    "wof:name":"Patrick Shifner",
    "wof:placetype":"venue"
},
  "geometry": {"coordinates":[4.377658844,50.8560066223],"type":"Point"}
}