{
  "type": "Feature",
  "properties": {
    "addr:full":"Meersstraat 84 Ternat (sint-katherina-lombeek) Vlaams-Brabant 1742",
    "addr:housenumber":"84",
    "addr:postcode":"1742",
    "addr:street":"Meersstraat",
    "iso:country":"BE",
    "sg:address":"Meersstraat 84",
    "sg:city":"Ternat (sint-katherina-lombeek)",
    "sg:classifiers":[
        {
            "category":"Health Services",
            "subcategory":"Doctor",
            "type":"Services"
        }
    ],
    "sg:phone":"+32 2 581 08 00",
    "sg:postcode":"1742",
    "sg:province":"Vlaams-Brabant",
    "sg:tags":[
        "medicinephysicians",
        "surgeon"
    ],
    "wof:name":"Cauwenbergs Frank",
    "wof:placetype":"venue"
},
  "geometry": {"coordinates":[4.1425051689,50.8806343079],"type":"Point"}
}