{
  "type": "Feature",
  "properties": {
    "addr:full":"Gemeentehuisstraat 21 Ternat Vlaams-Brabant 1740",
    "addr:housenumber":"21",
    "addr:postcode":"1740",
    "addr:street":"Gemeentehuisstraat",
    "iso:country":"BE",
    "sg:address":"Gemeentehuisstraat 21",
    "sg:city":"Ternat",
    "sg:orig_category":"Werk and personeelsselectie",
    "sg:phone":"+32 2 582 10 06",
    "sg:postcode":"1740",
    "sg:province":"Vlaams-Brabant",
    "wof:name":"Pwa Ternat",
    "wof:placetype":"venue"
},
  "geometry": {"coordinates":[4.1800088882,50.8704032898],"type":"Point"}
}