{
  "type": "Feature",
  "properties": {
    "iso:country":"BE",
    "sg:address":"Terreststraat 22",
    "sg:city":"Houthulst",
    "sg:orig_category":"HUISBRANDOLIE",
    "sg:phone":"+32 51 70 14 59",
    "sg:postcode":"8650",
    "sg:province":"West-Vlaanderen",
    "wof:name":"Norbert Despeghel",
    "wof:placetype":"venue"
},
  "geometry": {"coordinates":[2.9527869225,50.9809417725],"type":"Point"}
}