{
  "type": "Feature",
  "properties": {
    "addr:full":"Industriepark 1205 Halen Limburg 3545",
    "addr:postcode":"1205 halen;3545",
    "addr:street":"Industriepark",
    "iso:country":"BE",
    "sg:address":"Industriepark 1205",
    "sg:city":"Halen",
    "sg:orig_category":"Herstellingen and onderhoud van auto's Voertuigen",
    "sg:phone":"+32 13 44 27 95",
    "sg:postcode":"3545",
    "sg:province":"Limburg",
    "wof:name":"Andre Janssens",
    "wof:placetype":"venue"
},
  "geometry": {"coordinates":[5.1114802361,50.953540802],"type":"Point"}
}