{
  "type": "Feature",
  "properties": {
    "iso:country":"BE",
    "sg:address":"Vlaanderenstraat 51",
    "sg:city":"Gent",
    "sg:classifiers":[
        {
            "category":"Professional",
            "subcategory":"Advertising",
            "type":"Services"
        }
    ],
    "sg:phone":"+32 9 225 43 08",
    "sg:postcode":"9000",
    "sg:province":"Oost-Vlaanderen",
    "sg:tags":[
        "photography"
    ],
    "wof:name":"Francken C.p.m. Nv",
    "wof:placetype":"venue"
},
  "geometry": {"coordinates":[3.7299239635,51.0506439209],"type":"Point"}
}