{
  "type": "Feature",
  "properties": {
    "addr:full":"Rue Wahenge 32 Beauvechain Brabant Wallon 1320",
    "addr:housenumber":"32",
    "addr:postcode":"1320",
    "addr:street":"Rue Wahenge",
    "iso:country":"BE",
    "sg:address":"Rue Wahenge 32",
    "sg:city":"Beauvechain",
    "sg:orig_category":"Varkenskwekers",
    "sg:phone":"+32 10 86 66 22",
    "sg:postcode":"1320",
    "sg:province":"Brabant Wallon",
    "wof:name":"Paul Paul-vermeulen",
    "wof:placetype":"venue"
},
  "geometry": {"coordinates":[4.7975068092,50.7642707825],"type":"Point"}
}