{
  "type": "Feature",
  "properties": {
    "iso:country":"BE",
    "sg:address":"Rue Des Coquer\u00c9es 5",
    "sg:city":"Ottignies-louvain-la-neuve",
    "sg:classifiers":[
        {
            "category":"Personal",
            "subcategory":"Beauty Salon",
            "type":"Services"
        }
    ],
    "sg:phone":"+32 10 61 51 63",
    "sg:postcode":"1341",
    "sg:province":"Brabant Wallon",
    "sg:tags":[
        "de",
        "coiffure"
    ],
    "wof:name":"Cr\u00c9ation Marianne",
    "wof:placetype":"venue"
},
  "geometry": {"coordinates":[4.5627598763,50.6583099365],"type":"Point"}
}