{
  "type": "Feature",
  "properties": {
    "addr:full":"Avenue Eug\u00c8ne Demolder 109 Schaarbeek/schaerbeek Bruxelles-Capitale 1030",
    "addr:housenumber":"109",
    "addr:postcode":"1030",
    "addr:street":"Avenue Euge\u0300Ne Demolder",
    "iso:country":"BE",
    "sg:address":"Avenue Eug\u00c8ne Demolder 109",
    "sg:city":"Schaarbeek/schaerbeek",
    "sg:orig_category":"M\u00e9decins and sp\u00e9cialistes",
    "sg:phone":"+32 2 216 31 02",
    "sg:postcode":"1030",
    "sg:province":"Bruxelles-Capitale",
    "wof:name":"Michel Vermeulen",
    "wof:placetype":"venue"
},
  "geometry": {"coordinates":[4.3817667961,50.8728294373],"type":"Point"}
}