{
  "type": "Feature",
  "properties": {
    "iso:country":"BE",
    "sg:address":"Avenue Leopold Ii 8",
    "sg:city":"Namur",
    "sg:classifiers":[
        {
            "category":"Health Services",
            "subcategory":"Doctor",
            "type":"Services"
        }
    ],
    "sg:phone":"+32 81 73 73 99",
    "sg:postcode":"5000",
    "sg:province":"Namur",
    "sg:tags":[
        "medicinephysicians",
        "surgeon"
    ],
    "wof:name":"Henry Ph",
    "wof:placetype":"venue"
},
  "geometry": {"coordinates":[4.8527507782,50.46667099],"type":"Point"}
}