{
  "type": "Feature",
  "properties": {
    "addr:full":"Rue Sainte-marie 5 Li\u00c8ge Li\u00e8ge 4000",
    "addr:housenumber":"5",
    "addr:postcode":"4000",
    "addr:street":"Rue Sainte-Marie",
    "iso:country":"BE",
    "sg:address":"Rue Sainte-marie 5",
    "sg:city":"Li\u00c8ge",
    "sg:orig_category":"Assurances habitation compagnies. Assurances vie compagnies. Banques and organismes de cr\u00e9dit",
    "sg:phone":"+32 4 229 48 11",
    "sg:postcode":"4000",
    "sg:province":"Li\u00e8ge",
    "wof:name":"Fortis",
    "wof:placetype":"venue"
},
  "geometry": {"coordinates":[5.5649318695,50.6323013306],"type":"Point"}
}