{
  "type": "Feature",
  "properties": {
    "iso:country":"BE",
    "sg:address":"Rue De L'esp\u00eache 19",
    "sg:city":"Pont-\u00e0-celles (viesville)",
    "sg:classifiers":[
        {
            "category":"Communications",
            "type":"Services"
        }
    ],
    "sg:phone":"+32 71 34 68 70",
    "sg:postcode":"6230",
    "sg:province":"Hainaut",
    "sg:tags":[
        "translator"
    ],
    "wof:name":"1h+l-agnessens C",
    "wof:placetype":"venue"
},
  "geometry": {"coordinates":[4.4031238556,50.4893112183],"type":"Point"}
}