{
  "type": "Feature",
  "properties": {
    "iso:country":"BE",
    "sg:address":"Rue Archim\u00c8de 34",
    "sg:city":"Brussel/bruxelles",
    "sg:orig_category":"Salles de conf\u00e9rences and de r\u00e9ceptions. Restaurants. Bars. Caf\u00e9s",
    "sg:phone":"+32 2 230 98 94",
    "sg:postcode":"1000",
    "sg:province":"Bruxelles-Capitale",
    "wof:name":"James-joyce",
    "wof:placetype":"venue"
},
  "geometry": {"coordinates":[4.3835158348,50.8451309204],"type":"Point"}
}