{
  "type": "Feature",
  "properties": {
    "iso:country":"BE",
    "sg:address":"Rue Du March\u00e9 Au Charbon 11",
    "sg:city":"Bruxelles",
    "sg:classifiers":[
        {
            "category":"Wholesale",
            "subcategory":"Jewelry",
            "type":"Manufacturing & Wholesale Goods"
        }
    ],
    "sg:phone":"+32 2 512 12 26",
    "sg:postcode":"1000",
    "sg:province":"Bruxelles-Capitale",
    "sg:tags":[
        "equipment",
        "jeweller",
        "-",
        "supply"
    ],
    "wof:name":"Yannart-remacle R",
    "wof:placetype":"venue"
},
  "geometry": {"coordinates":[4.3504657745,50.8466300964],"type":"Point"}
}