{
  "type": "Feature",
  "properties": {
    "addr:full":"Henri Dunantstr. 11/b Tielt West-Vlaanderen 8700",
    "addr:housenumber":"11 / b",
    "addr:postcode":"8700",
    "addr:street":"Henri Dunantstr.",
    "iso:country":"BE",
    "sg:address":"Henri Dunantstr. 11/b",
    "sg:city":"Tielt",
    "sg:classifiers":[
        {
            "category":"Manufacturing",
            "subcategory":"Chemicals & Compounds",
            "type":"Manufacturing & Wholesale Goods"
        }
    ],
    "sg:phone":"+32 51 40 38 01",
    "sg:postcode":"8700",
    "sg:province":"West-Vlaanderen",
    "sg:tags":[
        "pharmaceutical",
        "chemistry",
        "-",
        "by-product"
    ],
    "wof:name":"Rpm Belgium Nv",
    "wof:placetype":"venue"
},
  "geometry": {"coordinates":[3.3470981121,51.0007820129],"type":"Point"}
}