{
  "type": "Feature",
  "properties": {
    "addr:full":"A. Vaucampslaan 28 Beersel (huizingen) Vlaams-Brabant 1654",
    "addr:housenumber":"28",
    "addr:postcode":"1654",
    "addr:street":"Vaucampslaan",
    "iso:country":"BE",
    "sg:address":"A. Vaucampslaan 28",
    "sg:city":"Beersel (huizingen)",
    "sg:classifiers":[
        {
            "category":"Wholesale",
            "subcategory":"Machinery & Supplies",
            "type":"Manufacturing & Wholesale Goods"
        }
    ],
    "sg:phone":"+32 2 363 59 59",
    "sg:postcode":"1654",
    "sg:province":"Vlaams-Brabant",
    "sg:tags":[
        "packing"
    ],
    "wof:name":"Createch Engineering",
    "wof:placetype":"venue"
},
  "geometry": {"coordinates":[4.2620658875,50.7521781921],"type":"Point"}
}