{
  "type": "Feature",
  "properties": {
    "addr:full":"Rue Du M\u00e9ridien 53 Bruxelles (saint-josse-ten-noode) Bruxelles-Capitale 1210",
    "addr:housenumber":"53",
    "addr:postcode":"1210",
    "addr:street":"Rue Du Me\u0301Ridien",
    "iso:country":"BE",
    "sg:address":"Rue Du M\u00e9ridien 53",
    "sg:city":"Bruxelles (saint-josse-ten-noode)",
    "sg:classifiers":[
        {
            "category":"Retail",
            "subcategory":"Event Space",
            "type":"Services"
        }
    ],
    "sg:phone":"+32 2 219 41 78",
    "sg:postcode":"1210",
    "sg:province":"Bruxelles-Capitale",
    "sg:tags":[
        "product",
        "snack",
        "speciality",
        "potato",
        "stand",
        "fried"
    ],
    "wof:name":"Unver",
    "wof:placetype":"venue"
},
  "geometry": {"coordinates":[4.3688049316,50.8546524048],"type":"Point"}
}