{
  "type": "Feature",
  "properties": {
    "addr:full":"Rijksweg 287 Wielsbeke West-Vlaanderen 8710",
    "addr:housenumber":"287",
    "addr:postcode":"8710",
    "addr:street":"Rijksweg;West-Vlaanderen",
    "iso:country":"BE",
    "sg:address":"Rijksweg 287",
    "sg:city":"Wielsbeke",
    "sg:classifiers":[
        {
            "category":"Insurance",
            "subcategory":"Insurance Agent",
            "type":"Services"
        }
    ],
    "sg:phone":"+32 56 66 79 34",
    "sg:postcode":"8710",
    "sg:province":"West-Vlaanderen",
    "sg:tags":[
        "verzekeringsmakelaars",
        "expert"
    ],
    "wof:name":"F. Missiaen",
    "wof:placetype":"venue"
},
  "geometry": {"coordinates":[3.3694410324,50.9120025635],"type":"Point"}
}