{
  "type": "Feature",
  "properties": {
    "addr:full":"Raafstraat 104 Schaarbeek/schaerbeek Bruxelles-Capitale 1030",
    "addr:housenumber":"104",
    "addr:postcode":"1030",
    "addr:street":"Raafstraat",
    "iso:country":"BE",
    "sg:address":"Raafstraat 104",
    "sg:city":"Schaarbeek/schaerbeek",
    "sg:orig_category":"Glaszetten and glaswerk Herstellingswinkels voor diverse persoonlijke and huishoudartikelen Serres a",
    "sg:phone":"+32 2 242 28 63",
    "sg:postcode":"1030",
    "sg:province":"Bruxelles-Capitale",
    "wof:name":"Serruvitre",
    "wof:placetype":"venue"
},
  "geometry": {"coordinates":[4.3932142258,50.8732528687],"type":"Point"}
}