{
  "type": "Feature",
  "properties": {
    "addr:full":"Chemin Du Bois P\u00c9rier 5 Leuze-en-hainaut Hainaut 7900",
    "addr:housenumber":"5",
    "addr:postcode":"7900",
    "addr:street":"Chemin Du Bois Pe\u0301Rier",
    "iso:country":"BE",
    "sg:address":"Chemin Du Bois P\u00c9rier 5",
    "sg:city":"Leuze-en-hainaut",
    "sg:orig_category":"Instituts pour adultes moins valides",
    "sg:phone":"+32 69 66 69 41",
    "sg:postcode":"7900",
    "sg:province":"Hainaut",
    "wof:name":"Home Albatros",
    "wof:placetype":"venue"
},
  "geometry": {"coordinates":[3.5994820595,50.5786018372],"type":"Point"}
}