{
  "type": "Feature",
  "properties": {
    "iso:country":"BE",
    "sg:address":"Gustave Latinislaan 31",
    "sg:city":"Schaarbeek/schaerbeek",
    "sg:orig_category":"Film-, tv- and videoproductie",
    "sg:phone":"+32 2 216 02 21",
    "sg:postcode":"1030",
    "sg:province":"Bruxelles-Capitale",
    "wof:name":"Sylvie Periquet",
    "wof:placetype":"venue"
},
  "geometry": {"coordinates":[4.3872289658,50.8667030334],"type":"Point"}
}