{
  "type": "Feature",
  "properties": {
    "iso:country":"BE",
    "sg:address":"Rommershoeve 4",
    "sg:city":"Heist-op-den-berg",
    "sg:classifiers":[
        {
            "category":"Sports & Exercise",
            "subcategory":"Sports Center",
            "type":"Entertainment"
        }
    ],
    "sg:phone":"+32 15 22 37 50",
    "sg:postcode":"2221",
    "sg:province":"Antwerpen",
    "sg:tags":[
        "terrain",
        "hors",
        "de",
        "installation",
        "sportifs"
    ],
    "wof:name":"De Rommershoeve",
    "wof:placetype":"venue"
},
  "geometry": {"coordinates":[4.7739758492,51.0512428284],"type":"Point"}
}