{
  "type": "Feature",
  "properties": {
    "iso:country":"BE",
    "sg:address":"Clos De La Pin\u00e8de 8",
    "sg:city":"Jurbise (erbisoeul)",
    "sg:classifiers":[
        {
            "category":"Health Services",
            "subcategory":"Doctor",
            "type":"Services"
        }
    ],
    "sg:phone":"+32 65 22 58 88",
    "sg:postcode":"7050",
    "sg:province":"Hainaut",
    "sg:tags":[
        "medicinephysicians",
        "surgeon"
    ],
    "wof:name":"Hornyak Albert",
    "wof:placetype":"venue"
},
  "geometry": {"coordinates":[3.9137790203,50.5099868774],"type":"Point"}
}