{
  "type": "Feature",
  "properties": {
    "addr:full":"Turnhoutsebaan 124 Scherpenheuvel-zichem (zichem) Vlaams-Brabant 3271",
    "addr:housenumber":"124",
    "addr:postcode":"3271",
    "addr:street":"Turnhoutsebaan",
    "iso:country":"BE",
    "sg:address":"Turnhoutsebaan 124",
    "sg:city":"Scherpenheuvel-zichem (zichem)",
    "sg:classifiers":[
        {
            "category":"Recreation",
            "subcategory":"Dance Hall",
            "type":"Entertainment"
        }
    ],
    "sg:phone":"+32 13 77 80 59",
    "sg:postcode":"3271",
    "sg:province":"Vlaams-Brabant",
    "sg:tags":[
        "discotheque"
    ],
    "wof:name":"Heideroosje",
    "wof:placetype":"venue"
},
  "geometry": {"coordinates":[5.0096569061,51.0385856628],"type":"Point"}
}