{
  "type": "Feature",
  "properties": {
    "iso:country":"BE",
    "sg:address":"Fritz Vinckelaan 11",
    "sg:city":"Bredene",
    "sg:classifiers":[
        {
            "category":"Bars & Pubs",
            "type":"Food & Drink"
        }
    ],
    "sg:phone":"+32 59 32 00 49",
    "sg:postcode":"8450",
    "sg:province":"West-Vlaanderen",
    "wof:name":"Vissershuis",
    "wof:placetype":"venue"
},
  "geometry": {"coordinates":[2.9617569447,51.2244148254],"type":"Point"}
}