{
  "type": "Feature",
  "properties": {
    "iso:country":"BE",
    "sg:address":"Rue Notre-dame 27",
    "sg:city":"Walcourt",
    "sg:classifiers":[
        {
            "category":"Shopping",
            "subcategory":"Party Supplies",
            "type":"Retail Goods"
        }
    ],
    "sg:phone":"+32 71 61 21 47",
    "sg:postcode":"5650",
    "sg:province":"Namur",
    "sg:tags":[
        "rental",
        "-"
    ],
    "wof:name":"Art De La Table (l')",
    "wof:placetype":"venue"
},
  "geometry": {"coordinates":[4.42973423,50.250793457],"type":"Point"}
}