{
  "type": "Feature",
  "properties": {
    "iso:country":"BE",
    "sg:address":"Place Chapelle Saint-roch 6",
    "sg:city":"Fosses-la-ville",
    "sg:classifiers":[
        {
            "category":"Freight",
            "type":"Transportation"
        }
    ],
    "sg:phone":"+32 71 71 16 12",
    "sg:postcode":"5070",
    "sg:province":"Namur",
    "sg:tags":[
        "-",
        "transport"
    ],
    "wof:name":"Michel E & Fils (ets)",
    "wof:placetype":"venue"
},
  "geometry": {"coordinates":[4.7042078972,50.3945846558],"type":"Point"}
}