{
  "type": "Feature",
  "properties": {
    "iso:country":"BE",
    "sg:address":"Rue De Namur 92-94",
    "sg:city":"Charleroi (gosselies)",
    "sg:classifiers":[
        {
            "category":"Sports & Exercise",
            "subcategory":"Stables",
            "type":"Entertainment"
        }
    ],
    "sg:phone":"+32 71 34 07 23",
    "sg:postcode":"6041",
    "sg:province":"Hainaut",
    "sg:tags":[
        "riding",
        "school"
    ],
    "wof:name":"Cercle Equestre De Gosselies",
    "wof:placetype":"venue"
},
  "geometry": {"coordinates":[4.4417748451,50.4210357666],"type":"Point"}
}