{
  "type": "Feature",
  "properties": {
    "iso:country":"BE",
    "sg:address":"Boddenveldweg 11",
    "sg:city":"Zonhoven",
    "sg:orig_category":"Overheidsdiensten",
    "sg:phone":"+32 11 81 25 40",
    "sg:postcode":"3520",
    "sg:province":"Limburg",
    "wof:name":"Interc.mij Hulp Gehandic.",
    "wof:placetype":"venue"
},
  "geometry": {"coordinates":[5.3827371597,50.9939537048],"type":"Point"}
}