{
  "type": "Feature",
  "properties": {
    "addr:full":"Pastorijstraat 31a Bilzen (grote-spouwen) Limburg 3740",
    "addr:housenumber":"31a",
    "addr:postcode":"3740",
    "addr:street":"Pastorijstraat",
    "iso:country":"BE",
    "sg:address":"Pastorijstraat 31a",
    "sg:city":"Bilzen (grote-spouwen)",
    "sg:classifiers":[
        {
            "category":"Home & Garden",
            "subcategory":"Home Furnishings",
            "type":"Retail Goods"
        }
    ],
    "sg:phone":"+32 12 45 21 35",
    "sg:postcode":"3740",
    "sg:province":"Limburg",
    "sg:tags":[
        "curtain",
        "-",
        "fixture"
    ],
    "wof:name":"Myriam Gordijnen",
    "wof:placetype":"venue"
},
  "geometry": {"coordinates":[5.5523462296,50.8347091675],"type":"Point"}
}