{
  "type": "Feature",
  "properties": {
    "iso:country":"BE",
    "sg:address":"Zi C",
    "sg:city":"Seneffe",
    "sg:classifiers":[
        {
            "category":"Wholesale",
            "subcategory":"Medical Equipment & Supplies",
            "type":"Manufacturing & Wholesale Goods"
        }
    ],
    "sg:phone":"+32 64 52 08 11",
    "sg:postcode":"7180",
    "sg:province":"Hainaut",
    "sg:tags":[
        "instrument",
        "health",
        "-",
        "precision"
    ],
    "wof:name":"International Brachytherapy Sa",
    "wof:placetype":"venue"
},
  "geometry": {"coordinates":[4.2591218948,50.5296554565],"type":"Point"}
}