{
  "type": "Feature",
  "properties": {
    "addr:full":"Bergstraat 56 Kampenhout Vlaams-Brabant 1910",
    "addr:housenumber":"56",
    "addr:postcode":"1910",
    "addr:street":"Bergstraat",
    "iso:country":"BE",
    "sg:address":"Bergstraat 56",
    "sg:city":"Kampenhout",
    "sg:classifiers":[
        {
            "category":"Insurance",
            "subcategory":"Insurance Agent",
            "type":"Services"
        }
    ],
    "sg:phone":"+32 16 65 60 61",
    "sg:postcode":"1910",
    "sg:province":"Vlaams-Brabant",
    "sg:tags":[
        "verzekeringsmakelaars",
        "expert"
    ],
    "wof:name":"Vanhoof",
    "wof:placetype":"venue"
},
  "geometry": {"coordinates":[4.5400252342,50.9307403564],"type":"Point"}
}