{
  "type": "Feature",
  "properties": {
    "addr:full":"Deuzeldlaan 161 Schoten Antwerpen 2900",
    "addr:housenumber":"161",
    "addr:postcode":"2900",
    "addr:street":"Deuzeldlaan",
    "iso:country":"BE",
    "sg:address":"Deuzeldlaan 161",
    "sg:city":"Schoten",
    "sg:orig_category":"Woningbouw",
    "sg:phone":"+32 3 647 03 39",
    "sg:postcode":"2900",
    "sg:province":"Antwerpen",
    "wof:name":"Tilburgs A.",
    "wof:placetype":"venue"
},
  "geometry": {"coordinates":[4.4609408379,51.2450408936],"type":"Point"}
}