{
  "type": "Feature",
  "properties": {
    "iso:country":"BE",
    "sg:address":"Route De Limbourg 65ba",
    "sg:city":"Jalhay",
    "sg:orig_category":"Plomberie, chauffage and installations sanitaires",
    "sg:phone":"+32 87 47 42 27",
    "sg:postcode":"4845",
    "sg:province":"Li\u00e8ge",
    "wof:name":"Philippe Mathy",
    "wof:placetype":"venue"
},
  "geometry": {"coordinates":[5.9172801971,50.5234832764],"type":"Point"}
}