{
  "type": "Feature",
  "properties": {
    "iso:country":"BE",
    "sg:address":"Bredabaan 953",
    "sg:city":"Wuustwezel",
    "sg:classifiers":[
        {
            "category":"Bars & Pubs",
            "type":"Food & Drink"
        }
    ],
    "sg:phone":"+32 3 663 01 03",
    "sg:postcode":"2990",
    "sg:province":"Antwerpen",
    "wof:name":"Hoek (op Den)",
    "wof:placetype":"venue"
},
  "geometry": {"coordinates":[4.5375499725,51.3459014893],"type":"Point"}
}