{
  "type": "Feature",
  "properties": {
    "iso:country":"BE",
    "sg:address":"Chemin Des Moulyniers 37",
    "sg:city":"Dalhem (feneur)",
    "sg:classifiers":[
        {
            "category":"Professional",
            "subcategory":"Engineering",
            "type":"Services"
        }
    ],
    "sg:phone":"+32 4 379 53 00",
    "sg:postcode":"4607",
    "sg:province":"Li\u00e8ge",
    "sg:tags":[
        "precision"
    ],
    "wof:name":"Moor Amg Sa",
    "wof:placetype":"venue"
},
  "geometry": {"coordinates":[5.7234959602,50.713634491],"type":"Point"}
}