{
  "type": "Feature",
  "properties": {
    "iso:country":"BE",
    "sg:address":"Charles Michielslaan 178",
    "sg:city":"Watermaal-bosvoorde/watermael-boitsfort",
    "sg:orig_category":"Fotografen and fotostudio's",
    "sg:phone":"+32 2 675 66 15",
    "sg:postcode":"1170",
    "sg:province":"Bruxelles-Capitale",
    "wof:name":"Ugo Cantoni",
    "wof:placetype":"venue"
},
  "geometry": {"coordinates":[4.4029479027,50.8146247864],"type":"Point"}
}