{
  "type": "Feature",
  "properties": {
    "iso:country":"BE",
    "sg:address":"Leopold Ruelensstraat 18",
    "sg:city":"Leuven",
    "sg:orig_category":"Public-relationsbureaus",
    "sg:phone":"+32 16 77 10 48",
    "sg:postcode":"3010",
    "sg:province":"Vlaams-Brabant",
    "wof:name":"Lutgarde Willems",
    "wof:placetype":"venue"
},
  "geometry": {"coordinates":[4.7304501534,50.889755249],"type":"Point"}
}