{
  "type": "Feature",
  "properties": {
    "addr:full":"Kerkstraat 166 Sint-pieters-woluwe/woluwe-saint-pierre Bruxelles-Capitale 1150",
    "addr:housenumber":"166",
    "addr:postcode":"1150",
    "addr:street":"Kerkstraat;/",
    "iso:country":"BE",
    "sg:address":"Kerkstraat 166",
    "sg:city":"Sint-pieters-woluwe/woluwe-saint-pierre",
    "sg:orig_category":"Dameskledingzaken Herenkledingzaken",
    "sg:phone":"+32 2 779 05 90",
    "sg:postcode":"1150",
    "sg:province":"Bruxelles-Capitale",
    "wof:name":"Baudouin Couture Sportwear",
    "wof:placetype":"venue"
},
  "geometry": {"coordinates":[4.4666128159,50.8403663635],"type":"Point"}
}