{
  "type": "Feature",
  "properties": {
    "iso:country":"BE",
    "sg:address":"Sijselestraat 6",
    "sg:city":"Beernem (groot)",
    "sg:classifiers":[
        {
            "category":"Insurance",
            "subcategory":"Life Insurance",
            "type":"Services"
        }
    ],
    "sg:phone":"+32 50 79 07 08",
    "sg:postcode":"8730",
    "sg:province":"West-Vlaanderen",
    "sg:tags":[
        "assurance"
    ],
    "wof:name":"Dhoore",
    "wof:placetype":"venue"
},
  "geometry": {"coordinates":[3.3391699791,51.1703147888],"type":"Point"}
}