{
  "type": "Feature",
  "properties": {
    "addr:full":"Kerkstraat 11 Moerbeke Oost-Vlaanderen 9180",
    "addr:housenumber":"11",
    "addr:postcode":"9180",
    "addr:street":"Kerkstraat",
    "iso:country":"BE",
    "sg:address":"Kerkstraat 11",
    "sg:city":"Moerbeke",
    "sg:orig_category":"Epiceries",
    "sg:phone":"+32 3 779 72 09",
    "sg:postcode":"9180",
    "sg:province":"Oost-Vlaanderen",
    "wof:name":"Freddy Van Rattingen",
    "wof:placetype":"venue"
},
  "geometry": {"coordinates":[3.937474966,51.1739997864],"type":"Point"}
}