{
  "type": "Feature",
  "properties": {
    "addr:full":"Brabantsebaan 419 Sint-pieters-leeuw Vlaams-Brabant 1600",
    "addr:housenumber":"419",
    "addr:postcode":"1600",
    "addr:street":"Brabantsebaan",
    "iso:country":"BE",
    "sg:address":"Brabantsebaan 419",
    "sg:city":"Sint-pieters-leeuw",
    "sg:orig_category":"Boekhouders",
    "sg:phone":"+32 2 532 01 32",
    "sg:postcode":"1600",
    "sg:province":"Vlaams-Brabant",
    "wof:name":"Albert Defranc",
    "wof:placetype":"venue"
},
  "geometry": {"coordinates":[4.2103099823,50.7826805115],"type":"Point"}
}