{
  "type": "Feature",
  "properties": {
    "addr:full":"Vogelhoekstraat 90 Gent (gentbrugge) Oost-Vlaanderen 9050",
    "addr:housenumber":"90",
    "addr:postcode":"9050",
    "addr:street":"Vogelhoekstraat",
    "iso:country":"BE",
    "sg:address":"Vogelhoekstraat 90",
    "sg:city":"Gent (gentbrugge)",
    "sg:classifiers":[
        {
            "category":"Banks & Credit Unions",
            "subcategory":"Investment Brokerage",
            "type":"Services"
        }
    ],
    "sg:phone":"+32 9 230 17 93",
    "sg:postcode":"9050",
    "sg:province":"Oost-Vlaanderen",
    "sg:tags":[
        "repair",
        "-",
        "installation",
        "sanitary",
        "article"
    ],
    "wof:name":"Merckx E",
    "wof:placetype":"venue"
},
  "geometry": {"coordinates":[3.7659230232,51.0243415833],"type":"Point"}
}