{
  "type": "Feature",
  "properties": {
    "addr:full":"Zandstraat 18 Maaseik (opoeteren) Limburg 3680",
    "addr:housenumber":"18",
    "addr:postcode":"3680",
    "addr:street":"Zandstraat",
    "iso:country":"BE",
    "sg:address":"Zandstraat 18",
    "sg:city":"Maaseik (opoeteren)",
    "sg:classifiers":[
        {
            "category":"Building & Trades",
            "subcategory":"Construction",
            "type":"Services"
        }
    ],
    "sg:phone":"+32 89 86 55 03",
    "sg:postcode":"3680",
    "sg:province":"Limburg",
    "sg:tags":[
        "ecological"
    ],
    "wof:name":"H.s.m. Industries",
    "wof:placetype":"venue"
},
  "geometry": {"coordinates":[5.6600651741,51.0679702759],"type":"Point"}
}