{
  "type": "Feature",
  "properties": {
    "addr:full":"Vijversstraat 13 Hasselt Limburg 3500",
    "addr:housenumber":"13",
    "addr:postcode":"3500",
    "addr:street":"Vijversstraat",
    "iso:country":"BE",
    "sg:address":"Vijversstraat 13",
    "sg:city":"Hasselt",
    "sg:classifiers":[
        {
            "category":"Health Services",
            "subcategory":"Dentist",
            "type":"Services"
        }
    ],
    "sg:phone":"+32 11 21 12 84",
    "sg:postcode":"3500",
    "sg:province":"Limburg",
    "wof:name":"Smeyers Truus",
    "wof:placetype":"venue"
},
  "geometry": {"coordinates":[5.3539757729,50.9635620117],"type":"Point"}
}