{
  "type": "Feature",
  "properties": {
    "iso:country":"BE",
    "sg:address":"Place Verte 64",
    "sg:city":"Ottignies-louvain-la-neuve (louvain-la-neuve)",
    "sg:classifiers":[
        {
            "category":"Professional",
            "subcategory":"Testing Lab",
            "type":"Services"
        }
    ],
    "sg:phone":"+32 10 45 80 58",
    "sg:postcode":"1348",
    "sg:province":"Brabant Wallon",
    "sg:tags":[
        "chemist"
    ],
    "wof:name":"Pharmacie De Lauzelle",
    "wof:placetype":"venue"
},
  "geometry": {"coordinates":[4.6170301437,50.6740608215],"type":"Point"}
}