{
  "type": "Feature",
  "properties": {
    "iso:country":"BE",
    "sg:address":"Kruisstraat 158",
    "sg:city":"Duffel",
    "sg:classifiers":[
        {
            "category":"Building & Trades",
            "subcategory":"Landscaping Services",
            "type":"Services"
        }
    ],
    "sg:phone":"+32 15 32 22 89",
    "sg:postcode":"2570",
    "sg:province":"Antwerpen",
    "sg:tags":[
        "gardening",
        "garden",
        "maintenance"
    ],
    "wof:name":"Hopchet Axel & Co G.c.v.",
    "wof:placetype":"venue"
},
  "geometry": {"coordinates":[4.4805750847,51.0877761841],"type":"Point"}
}