{
  "type": "Feature",
  "properties": {
    "iso:country":"BE",
    "sg:address":"Kardinaal Mercierlaan 92",
    "sg:city":"Leuven (heverlee)",
    "sg:classifiers":[
        {
            "category":"Organizations",
            "subcategory":"Non-profit Organization",
            "type":"Services"
        }
    ],
    "sg:phone":"+32 16 22 94 27",
    "sg:postcode":"3001",
    "sg:province":"Vlaams-Brabant",
    "sg:tags":[
        "international",
        "organisation"
    ],
    "wof:name":"International Society For Horticultural Science",
    "wof:placetype":"venue"
},
  "geometry": {"coordinates":[4.688598156,50.8631401062],"type":"Point"}
}