{
  "type": "Feature",
  "properties": {
    "addr:full":"Chauss\u00c9e De Braine 116 Soignies Hainaut 7060",
    "addr:housenumber":"116",
    "addr:postcode":"7060",
    "addr:street":"Chausse\u0301E De Braine",
    "iso:country":"BE",
    "sg:address":"Chauss\u00c9e De Braine 116",
    "sg:city":"Soignies",
    "sg:orig_category":"Onderdelen and accessoires voor auto's",
    "sg:phone":"+32 67 33 07 77",
    "sg:postcode":"7060",
    "sg:province":"Hainaut",
    "wof:name":"Pneumac Soignies",
    "wof:placetype":"venue"
},
  "geometry": {"coordinates":[4.0851221085,50.5859260559],"type":"Point"}
}