{
  "type": "Feature",
  "properties": {
    "iso:country":"BE",
    "sg:address":"Avenue Prince Charles 3",
    "sg:city":"Waterloo",
    "sg:orig_category":"Muziekinstrumenten Verhuur televisie- and audiovisuele apparatuur",
    "sg:phone":"+32 495 50 13 23",
    "sg:postcode":"1410",
    "sg:province":"Brabant Wallon",
    "wof:name":"The Audio Event Company",
    "wof:placetype":"venue"
},
  "geometry": {"coordinates":[4.4083719254,50.707950592],"type":"Point"}
}