{
  "type": "Feature",
  "properties": {
    "iso:country":"BE",
    "sg:address":"Ten Edestraat 44",
    "sg:city":"Gavere (semmerzake)",
    "sg:classifiers":[
        {
            "category":"Manufacturing",
            "subcategory":"Musical Instruments",
            "type":"Manufacturing & Wholesale Goods"
        }
    ],
    "sg:phone":"+32 9 384 25 34",
    "sg:postcode":"9890",
    "sg:province":"Oost-Vlaanderen",
    "sg:tags":[
        "repair",
        "mainten",
        "-"
    ],
    "wof:name":"Laureys M",
    "wof:placetype":"venue"
},
  "geometry": {"coordinates":[3.6799860001,50.9356269836],"type":"Point"}
}