{
  "type": "Feature",
  "properties": {
    "iso:country":"BE",
    "sg:address":"Moerdijkbeek Oost 20",
    "sg:city":"Koekelare",
    "sg:orig_category":"Rundveehouders Varkenskwekers",
    "sg:phone":"+32 59 27 66 99",
    "sg:postcode":"8680",
    "sg:province":"West-Vlaanderen",
    "wof:name":"Honore Strubbe",
    "wof:placetype":"venue"
},
  "geometry": {"coordinates":[2.9684569836,51.1218338013],"type":"Point"}
}