{
  "type": "Feature",
  "properties": {
    "iso:country":"BE",
    "sg:address":"Rechtstraat 358",
    "sg:city":"Lokeren",
    "sg:orig_category":"Textiel",
    "sg:phone":"+32 9 346 90 74",
    "sg:postcode":"9160",
    "sg:province":"Oost-Vlaanderen",
    "wof:name":"Linda David",
    "wof:placetype":"venue"
},
  "geometry": {"coordinates":[3.9159379005,51.1323471069],"type":"Point"}
}