{
  "type": "Feature",
  "properties": {
    "addr:full":"Vildersstraat 26 Hasselt Limburg 3500",
    "addr:housenumber":"26",
    "addr:postcode":"3500",
    "addr:street":"Vildersstraat",
    "iso:country":"BE",
    "sg:address":"Vildersstraat 26",
    "sg:city":"Hasselt",
    "sg:classifiers":[
        {
            "category":"Shopping",
            "subcategory":"Pets & Pet Supplies",
            "type":"Retail Goods"
        }
    ],
    "sg:phone":"+32 11 21 00 82",
    "sg:postcode":"3500",
    "sg:province":"Limburg",
    "sg:tags":[
        "aquarium",
        "accessory"
    ],
    "wof:name":"Hustinx Aquaristiek Nv",
    "wof:placetype":"venue"
},
  "geometry": {"coordinates":[5.3454961777,50.9353637695],"type":"Point"}
}