{
  "type": "Feature",
  "properties": {
    "addr:full":"Boulevard Leopold Ii 118 Bruxelles (molenbeek-saint-jean) Bruxelles-Capitale 1080",
    "addr:housenumber":"118",
    "addr:postcode":"1080",
    "addr:street":"Boulevard Leopold Ii",
    "iso:country":"BE",
    "sg:address":"Boulevard Leopold Ii 118",
    "sg:city":"Bruxelles (molenbeek-saint-jean)",
    "sg:classifiers":[
        {
            "category":"Food & Beverages",
            "subcategory":"Groceries & Convenience Stores",
            "type":"Retail Goods"
        }
    ],
    "sg:phone":"+32 2 410 43 20",
    "sg:postcode":"1080",
    "sg:province":"Bruxelles-Capitale",
    "sg:tags":[
        "grocer"
    ],
    "wof:name":"Khael",
    "wof:placetype":"venue"
},
  "geometry": {"coordinates":[4.3390631676,50.8604660034],"type":"Point"}
}