{
  "type": "Feature",
  "properties": {
    "iso:country":"BE",
    "sg:address":"Dobbelenbergstraat 7",
    "sg:city":"Brussel/bruxelles",
    "sg:orig_category":"Airconditioning and ventilatie Loodgieterij and centrale verwarming Gh",
    "sg:phone":"+32 2 240 61 61",
    "sg:postcode":"1130",
    "sg:province":"Bruxelles-Capitale",
    "wof:name":"Gea Happel Belgium/happel",
    "wof:placetype":"venue"
},
  "geometry": {"coordinates":[4.4223470688,50.9013061523],"type":"Point"}
}