{
  "type": "Feature",
  "properties": {
    "iso:country":"BE",
    "sg:address":"Boulevard Sylvain Dupuis 83",
    "sg:city":"Bruxelles",
    "sg:classifiers":[
        {
            "category":"Military Area",
            "subcategory":"Army Base",
            "type":"Public Place"
        }
    ],
    "sg:phone":"+32 2 523 20 23",
    "sg:postcode":"1070",
    "sg:province":"Bruxelles-Capitale",
    "sg:tags":[
        "safes",
        "room",
        "strong"
    ],
    "wof:name":"Danotherm S.p.r.l.",
    "wof:placetype":"venue"
},
  "geometry": {"coordinates":[4.3019218445,50.8374824524],"type":"Point"}
}