{
  "type": "Feature",
  "properties": {
    "iso:country":"BE",
    "sg:address":"Chauss\u00c9e Paul Houtart 208",
    "sg:city":"La Louviere",
    "sg:orig_category":"Rev\u00eatements de sols and murs",
    "sg:phone":"+32 64 21 42 21",
    "sg:postcode":"7110",
    "sg:province":"Hainaut",
    "wof:name":"Tapisdiscount",
    "wof:placetype":"venue"
},
  "geometry": {"coordinates":[4.1607952118,50.4852409363],"type":"Point"}
}