{
  "type": "Feature",
  "properties": {
    "addr:full":"Rue De Brionsart 38 Gesves Namur 5340",
    "addr:housenumber":"38",
    "addr:postcode":"5340",
    "addr:street":"Rue De Brionsart",
    "iso:country":"BE",
    "sg:address":"Rue De Brionsart 38",
    "sg:city":"Gesves",
    "sg:classifiers":[
        {
            "category":"Personal",
            "subcategory":"Beauty Salon",
            "type":"Services"
        }
    ],
    "sg:phone":"+32 83 67 74 98",
    "sg:postcode":"5340",
    "sg:province":"Namur",
    "sg:tags":[
        "de",
        "coiffure"
    ],
    "wof:name":"Maryse Goffin",
    "wof:placetype":"venue"
},
  "geometry": {"coordinates":[5.0791702271,50.4178504944],"type":"Point"}
}