{
  "type": "Feature",
  "properties": {
    "iso:country":"BE",
    "sg:address":"Boulevard Cuivre Et Zinc11",
    "sg:city":"Grivegn\u00c9e",
    "sg:orig_category":"Entretien and r\u00e9parations de voitures",
    "sg:phone":"+32 4 342 50 70",
    "sg:postcode":"4030",
    "sg:province":"Li\u00e8ge",
    "wof:name":"Carrosserie Vignette",
    "wof:placetype":"venue"
},
  "geometry": {"coordinates":[5.5907230377,50.6254081726],"type":"Point"}
}