{
  "type": "Feature",
  "properties": {
    "addr:full":"Rue De Brabant 63 Bruxelles (schaerbeek) Bruxelles-Capitale 1030",
    "addr:housenumber":"63",
    "addr:postcode":"1030",
    "addr:street":"Rue De Brabant",
    "iso:country":"BE",
    "sg:address":"Rue De Brabant 63",
    "sg:city":"Bruxelles (schaerbeek)",
    "sg:classifiers":[
        {
            "category":"Transit Center",
            "subcategory":"Freight",
            "type":"Transportation"
        }
    ],
    "sg:phone":"+32 2 223 39 37",
    "sg:postcode":"1030",
    "sg:province":"Bruxelles-Capitale",
    "sg:tags":[
        "import",
        "export",
        "-"
    ],
    "wof:name":"Momatex",
    "wof:placetype":"venue"
},
  "geometry": {"coordinates":[4.3628211021,50.860042572],"type":"Point"}
}