{
  "type": "Feature",
  "properties": {
    "addr:full":"Prelaat Deckersstraat 4b2 Kalmthout Antwerpen 2920",
    "addr:housenumber":"4b2",
    "addr:postcode":"2920",
    "addr:street":"Prelaat Deckersstraat",
    "iso:country":"BE",
    "sg:address":"Prelaat Deckersstraat 4b2",
    "sg:city":"Kalmthout",
    "sg:orig_category":"Brood, gebak and snoepgoed",
    "sg:phone":"+32 3 667 49 09",
    "sg:postcode":"2920",
    "sg:province":"Antwerpen",
    "wof:name":"Bakkerij \u00b4t Pleintje",
    "wof:placetype":"venue"
},
  "geometry": {"coordinates":[4.5173401833,51.43542099],"type":"Point"}
}