{
  "type": "Feature",
  "properties": {
    "iso:country":"BE",
    "sg:address":"Kammenstraat 76",
    "sg:city":"Antwerpen",
    "sg:classifiers":[
        {
            "category":"Professional",
            "subcategory":"Art Services",
            "type":"Services"
        }
    ],
    "sg:phone":"+32 3 232 18 97",
    "sg:postcode":"2000",
    "sg:province":"Antwerpen",
    "sg:tags":[
        "picture",
        "framer"
    ],
    "wof:name":"Kunsthuis Bvba",
    "wof:placetype":"venue"
},
  "geometry": {"coordinates":[4.40163517,51.2159729004],"type":"Point"}
}