{
  "type": "Feature",
  "properties": {
    "iso:country":"BE",
    "sg:address":"Mechelsesteenweg 42",
    "sg:city":"Kontich",
    "sg:orig_category":"Fotogravure and zetwerk",
    "sg:phone":"+32 3 457 25 47",
    "sg:postcode":"2550",
    "sg:province":"Antwerpen",
    "wof:name":"Piessens",
    "wof:placetype":"venue"
},
  "geometry": {"coordinates":[4.4455051422,51.1333732605],"type":"Point"}
}