{
  "type": "Feature",
  "properties": {
    "addr:full":"Hille 144 Wingene (zwevezele) West-Vlaanderen 8750",
    "addr:housenumber":"144",
    "addr:postcode":"8750",
    "addr:street":"Hille",
    "iso:country":"BE",
    "sg:address":"Hille 144",
    "sg:city":"Wingene (zwevezele)",
    "sg:classifiers":[
        {
            "category":"Professional",
            "subcategory":"Accounting & Tax Preparation",
            "type":"Services"
        }
    ],
    "sg:phone":"+32 51 61 29 88",
    "sg:postcode":"8750",
    "sg:province":"West-Vlaanderen",
    "sg:tags":[
        "bookkeeper"
    ],
    "wof:name":"Detavenier U",
    "wof:placetype":"venue"
},
  "geometry": {"coordinates":[3.2259390354,51.0463485718],"type":"Point"}
}