{
  "type": "Feature",
  "properties": {
    "addr:full":"Ankerstraat 134 Sint-niklaas Oost-Vlaanderen 9100",
    "addr:housenumber":"134",
    "addr:postcode":"9100",
    "addr:street":"Ankerstraat",
    "iso:country":"BE",
    "sg:address":"Ankerstraat 134",
    "sg:city":"Sint-niklaas",
    "sg:classifiers":[
        {
            "category":"Health Services",
            "subcategory":"Doctor",
            "type":"Services"
        }
    ],
    "sg:phone":"+32 3 777 41 50",
    "sg:postcode":"9100",
    "sg:province":"Oost-Vlaanderen",
    "sg:tags":[
        "medicinephysicians",
        "surgeon"
    ],
    "wof:name":"De Bruyne T",
    "wof:placetype":"venue"
},
  "geometry": {"coordinates":[4.1477589607,51.1677360535],"type":"Point"}
}