{
  "type": "Feature",
  "properties": {
    "addr:full":"Rue Ferrer 2 Soignies Hainaut 7060",
    "addr:housenumber":"2",
    "addr:postcode":"7060",
    "addr:street":"Rue Ferrer",
    "iso:country":"BE",
    "sg:address":"Rue Ferrer 2",
    "sg:city":"Soignies",
    "sg:orig_category":"Pain, p\u00e2tisseries and confiseries",
    "sg:phone":"+32 67 33 25 49",
    "sg:postcode":"7060",
    "sg:province":"Hainaut",
    "wof:name":"Patrice Poliart",
    "wof:placetype":"venue"
},
  "geometry": {"coordinates":[4.0712800026,50.5791931152],"type":"Point"}
}