{
  "type": "Feature",
  "properties": {
    "addr:full":"Hopland 3-5 Box 12 Antwerpen Antwerpen 2000",
    "addr:housenumber":"3-5 box 12",
    "addr:postcode":"2000",
    "addr:street":"Hopland",
    "iso:country":"BE",
    "sg:address":"Hopland 3-5 Box 12",
    "sg:city":"Antwerpen",
    "sg:classifiers":[
        {
            "category":"Manufacturing",
            "subcategory":"Furniture",
            "type":"Manufacturing & Wholesale Goods"
        }
    ],
    "sg:phone":"+32 3 231 88 26",
    "sg:postcode":"2000",
    "sg:province":"Antwerpen",
    "sg:tags":[
        "design",
        "-"
    ],
    "wof:name":"Avant Scene Cvba",
    "wof:placetype":"venue"
},
  "geometry": {"coordinates":[4.4094648361,51.2167167664],"type":"Point"}
}