{
  "type": "Feature",
  "properties": {
    "addr:full":"Weststraat 170 Sleidinge Oost-Vlaanderen 9940",
    "addr:housenumber":"170",
    "addr:postcode":"9940",
    "addr:street":"Weststraat;Oost-Vlaanderen",
    "iso:country":"BE",
    "sg:address":"Weststraat 170",
    "sg:city":"Sleidinge",
    "sg:classifiers":[
        {
            "category":"Retail",
            "subcategory":"Storage",
            "type":"Services"
        }
    ],
    "sg:phone":"+32 9 357 31 66",
    "sg:postcode":"9940",
    "sg:province":"Oost-Vlaanderen",
    "sg:tags":[
        "transport",
        "groupage"
    ],
    "wof:name":"Vervoer Geleyte Willy Nv",
    "wof:placetype":"venue"
},
  "geometry": {"coordinates":[3.6678779125,51.1270294189],"type":"Point"}
}