{
  "type": "Feature",
  "properties": {
    "iso:country":"BE",
    "sg:address":"Rue Asty Moulin 3",
    "sg:city":"Namur",
    "sg:classifiers":[
        {
            "category":"Professional",
            "type":"Services"
        }
    ],
    "sg:phone":"+32 81 74 69 30",
    "sg:postcode":"5000",
    "sg:province":"Namur",
    "sg:tags":[
        "auction",
        "room"
    ],
    "wof:name":"Entrep\u00f4t (l')",
    "wof:placetype":"venue"
},
  "geometry": {"coordinates":[4.8593797684,50.4701805115],"type":"Point"}
}