{
  "type": "Feature",
  "properties": {
    "iso:country":"BE",
    "sg:address":"Kapelstraat 22",
    "sg:city":"Hove",
    "sg:orig_category":"Services fun\u00e9raires",
    "sg:phone":"+32 3 449 68 61",
    "sg:postcode":"2540",
    "sg:province":"Antwerpen",
    "wof:name":"Goossens & Celis",
    "wof:placetype":"venue"
},
  "geometry": {"coordinates":[4.4693908691,51.1543235779],"type":"Point"}
}