{
  "type": "Feature",
  "properties": {
    "addr:full":"Schuiferskapellestraat 20 Pittem West-Vlaanderen 8740",
    "addr:housenumber":"20",
    "addr:postcode":"8740",
    "addr:street":"Schuiferskapellestraat",
    "iso:country":"BE",
    "sg:address":"Schuiferskapellestraat 20",
    "sg:city":"Pittem",
    "sg:orig_category":"Artsen and specialisten",
    "sg:phone":"+32 51 46 42 83",
    "sg:postcode":"8740",
    "sg:province":"West-Vlaanderen",
    "wof:name":"Marijke Lootens",
    "wof:placetype":"venue"
},
  "geometry": {"coordinates":[3.2678890228,50.9962692261],"type":"Point"}
}