{
  "type": "Feature",
  "properties": {
    "iso:country":"BE",
    "sg:address":"Goudstraat 12",
    "sg:city":"Gent",
    "sg:orig_category":"V\u00e9t\u00e9rinaires",
    "sg:phone":"+32 9 224 05 27",
    "sg:postcode":"9000",
    "sg:province":"Oost-Vlaanderen",
    "wof:name":"Godelieve Okerman",
    "wof:placetype":"venue"
},
  "geometry": {"coordinates":[3.7273540497,51.0592765808],"type":"Point"}
}