{
  "type": "Feature",
  "properties": {
    "addr:full":"Tongersesteenweg 139 Riemst Limburg 3770",
    "addr:housenumber":"139",
    "addr:postcode":"3770",
    "addr:street":"Tongersesteenweg",
    "iso:country":"BE",
    "sg:address":"Tongersesteenweg 139",
    "sg:city":"Riemst",
    "sg:classifiers":[
        {
            "category":"Home & Garden",
            "subcategory":"Home Furnishings",
            "type":"Retail Goods"
        }
    ],
    "sg:phone":"+32 70 22 27 22",
    "sg:postcode":"3770",
    "sg:province":"Limburg",
    "sg:tags":[
        "-",
        "furniture"
    ],
    "wof:name":"Eycken Meubelen",
    "wof:placetype":"venue"
},
  "geometry": {"coordinates":[5.5895900726,50.8097305298],"type":"Point"}
}