{
  "type": "Feature",
  "properties": {
    "iso:country":"BE",
    "sg:address":"Rue Jonckeu 12bc",
    "sg:city":"Heron",
    "sg:orig_category":"Fabrication and montage de mobilier. Installation de menuiserie en bois and plastique. Meubles D\u00e9tai",
    "sg:phone":"+32 85 71 39 30",
    "sg:postcode":"4218",
    "sg:province":"Li\u00e8ge",
    "wof:name":"Eric Billiet",
    "wof:placetype":"venue"
},
  "geometry": {"coordinates":[5.1382331848,50.5359954834],"type":"Point"}
}