{
  "type": "Feature",
  "properties": {
    "iso:country":"BE",
    "sg:address":"Preachesdreef 7",
    "sg:city":"Moeskroen/mouscron",
    "sg:orig_category":"Voertuigen",
    "sg:phone":"+32 56 48 73 30",
    "sg:postcode":"7711",
    "sg:province":"Hainaut",
    "wof:name":"M-auto",
    "wof:placetype":"venue"
},
  "geometry": {"coordinates":[3.2819769382,50.7344055176],"type":"Point"}
}