{
  "type": "Feature",
  "properties": {
    "iso:country":"BE",
    "sg:address":"Kasteellaan 285",
    "sg:city":"Gent",
    "sg:orig_category":"Kapsalons",
    "sg:phone":"+32 9 223 29 46",
    "sg:postcode":"9000",
    "sg:province":"Oost-Vlaanderen",
    "wof:name":"Ivan Bulcke",
    "wof:placetype":"venue"
},
  "geometry": {"coordinates":[3.7402820587,51.0520095825],"type":"Point"}
}