{
  "type": "Feature",
  "properties": {
    "addr:full":"Industriepark 22 Heist-op-den-berg Antwerpen 2220",
    "addr:housenumber":"22",
    "addr:postcode":"2220",
    "addr:street":"Industriepark",
    "iso:country":"BE",
    "sg:address":"Industriepark 22",
    "sg:city":"Heist-op-den-berg",
    "sg:orig_category":"Pi\u00e8ces and accessoires de v\u00e9hicules automobiles Gr",
    "sg:phone":"+32 15 24 63 81",
    "sg:postcode":"2220",
    "sg:province":"Antwerpen",
    "wof:name":"Electro Diesel Rebuild",
    "wof:placetype":"venue"
},
  "geometry": {"coordinates":[4.7271709442,51.0614395142],"type":"Point"}
}