{
  "type": "Feature",
  "properties": {
    "iso:country":"BE",
    "sg:address":"Stationstraat 10",
    "sg:city":"Komen-waasten/comines-warneton",
    "sg:orig_category":"Drukkerijen and copyshops Kantoormateriaal",
    "sg:phone":"+32 56 55 57 91",
    "sg:postcode":"7780",
    "sg:province":"Hainaut",
    "wof:name":"Etienne Becquart",
    "wof:placetype":"venue"
},
  "geometry": {"coordinates":[2.9984300137,50.7863311768],"type":"Point"}
}