{
  "type": "Feature",
  "properties": {
    "addr:full":"Chauss\u00c9e De Louvain 162 Wavre Brabant Wallon 1300",
    "addr:housenumber":"162;1300",
    "addr:street":"Chausse\u0301E De Louvain",
    "iso:country":"BE",
    "sg:address":"Chauss\u00c9e De Louvain 162",
    "sg:city":"Wavre",
    "sg:orig_category":"Installatie van houten of kunststof schrijnwerk",
    "sg:phone":"+32 10 22 79 17",
    "sg:postcode":"1300",
    "sg:province":"Brabant Wallon",
    "wof:name":"Alberto Silveira Bastos",
    "wof:placetype":"venue"
},
  "geometry": {"coordinates":[4.6205539703,50.7165756226],"type":"Point"}
}