{
  "type": "Feature",
  "properties": {
    "addr:full":"Schendekouterstraat 8b Wervik West-Vlaanderen 8940",
    "addr:housenumber":"8b",
    "addr:postcode":"8940",
    "addr:street":"Schendekouterstraat",
    "iso:country":"BE",
    "sg:address":"Schendekouterstraat 8b",
    "sg:city":"Wervik",
    "sg:orig_category":"Installation de menuiserie en bois and plastique",
    "sg:phone":"+32 56 51 58 67",
    "sg:postcode":"8940",
    "sg:province":"West-Vlaanderen",
    "wof:name":"Rodico",
    "wof:placetype":"venue"
},
  "geometry": {"coordinates":[3.0905199051,50.8156929016],"type":"Point"}
}