{
  "type": "Feature",
  "properties": {
    "iso:country":"BE",
    "sg:address":"Beysstraat 112",
    "sg:city":"Liedekerke",
    "sg:classifiers":[
        {
            "category":"Shopping",
            "subcategory":"Florist",
            "type":"Retail Goods"
        }
    ],
    "sg:phone":"+32 53 66 50 04",
    "sg:postcode":"1770",
    "sg:province":"Vlaams-Brabant",
    "wof:name":"Bloemen Creatiefje Miguel",
    "wof:placetype":"venue"
},
  "geometry": {"coordinates":[4.0839681625,50.8680458069],"type":"Point"}
}