{
  "type": "Feature",
  "properties": {
    "addr:full":"Rue De La Moinerie 3 Verviers (petit-rechain) Li\u00e8ge 4800",
    "addr:housenumber":"3",
    "addr:postcode":"4800",
    "addr:street":"Rue De La Moinerie",
    "iso:country":"BE",
    "sg:address":"Rue De La Moinerie 3",
    "sg:city":"Verviers (petit-rechain)",
    "sg:classifiers":[
        {
            "category":"Bakery",
            "type":"Food & Drink"
        }
    ],
    "sg:phone":"+32 87 33 40 11",
    "sg:postcode":"4800",
    "sg:province":"Li\u00e8ge",
    "sg:tags":[
        "confectioner",
        "baker"
    ],
    "wof:name":"Grignard G",
    "wof:placetype":"venue"
},
  "geometry": {"coordinates":[5.8582248688,50.5891952515],"type":"Point"}
}