{
  "type": "Feature",
  "properties": {
    "iso:country":"BE",
    "sg:address":"Rue Des Bach\u00e8res 19",
    "sg:city":"Sambreville (tamines)",
    "sg:classifiers":[
        {
            "category":"Health Services",
            "subcategory":"Doctor",
            "type":"Services"
        }
    ],
    "sg:phone":"+32 71 77 10 07",
    "sg:postcode":"5060",
    "sg:province":"Namur",
    "sg:tags":[
        "medicinephysicians",
        "surgeon"
    ],
    "wof:name":"Colmant Luc",
    "wof:placetype":"venue"
},
  "geometry": {"coordinates":[4.5887608528,50.4374885559],"type":"Point"}
}