{
  "type": "Feature",
  "properties": {
    "addr:full":"Sprinkhaanveldestraat 7b8 Borsbeek Antwerpen 2150",
    "addr:housenumber":"7b8",
    "addr:postcode":"2150",
    "addr:street":"Sprinkhaanveldestraat",
    "iso:country":"BE",
    "sg:address":"Sprinkhaanveldestraat 7b8",
    "sg:city":"Borsbeek",
    "sg:orig_category":"Experts-comptables",
    "sg:phone":"+32 3 321 07 41",
    "sg:postcode":"2150",
    "sg:province":"Antwerpen",
    "wof:name":"Erik Samson",
    "wof:placetype":"venue"
},
  "geometry": {"coordinates":[4.4833312035,51.1978988647],"type":"Point"}
}