{
  "type": "Feature",
  "properties": {
    "addr:full":"Rue De L' Industrie 44 Bruxelles (etterbeek) Bruxelles-Capitale 1040",
    "addr:housenumber":"44",
    "addr:postcode":"1040",
    "addr:street":"Rue De L ' Industrie",
    "iso:country":"BE",
    "sg:address":"Rue De L' Industrie 44",
    "sg:city":"Bruxelles (etterbeek)",
    "sg:classifiers":[
        {
            "category":"Banks & Credit Unions",
            "subcategory":"Bank",
            "type":"Services"
        }
    ],
    "sg:postcode":"1040",
    "sg:province":"Bruxelles-Capitale",
    "wof:name":"Deschuytter-verzekeringskantoor Nv",
    "wof:placetype":"venue"
},
  "geometry": {"coordinates":[2.7263898849,50.8555984497],"type":"Point"}
}