{
  "type": "Feature",
  "properties": {
    "addr:full":"Avenue De La Couronne 332 Bruxelles Bruxelles-Capitale 1050",
    "addr:housenumber":"332",
    "addr:postcode":"1050",
    "addr:street":"Avenue De La Couronne",
    "iso:country":"BE",
    "sg:address":"Avenue De La Couronne 332",
    "sg:city":"Bruxelles",
    "sg:orig_category":"Quincailleries",
    "sg:phone":"+32 2 646 63 33",
    "sg:postcode":"1050",
    "sg:province":"Bruxelles-Capitale",
    "wof:name":"Art Et D\u00c9cor",
    "wof:placetype":"venue"
},
  "geometry": {"coordinates":[4.3860049248,50.8243675232],"type":"Point"}
}