{
  "type": "Feature",
  "properties": {
    "addr:full":"Rue Du Parc 25 Li\u00e8ge Li\u00e8ge 4020",
    "addr:housenumber":"25",
    "addr:postcode":"4020",
    "addr:street":"Rue Du Parc",
    "iso:country":"BE",
    "sg:address":"Rue Du Parc 25",
    "sg:city":"Li\u00e8ge",
    "sg:classifiers":[
        {
            "category":"Wholesale",
            "subcategory":"Medical Equipment & Supplies",
            "type":"Manufacturing & Wholesale Goods"
        }
    ],
    "sg:phone":"+32 2 366 30 60",
    "sg:postcode":"4020",
    "sg:province":"Li\u00e8ge",
    "sg:tags":[
        "instrument",
        "health",
        "-",
        "precision"
    ],
    "wof:name":"Derby Sopal Belgium Sprl",
    "wof:placetype":"venue"
},
  "geometry": {"coordinates":[4.2687120438,50.6824455261],"type":"Point"}
}