{
  "type": "Feature",
  "properties": {
    "iso:country":"BE",
    "sg:address":"Chauss\u00e9e Brunehault 2",
    "sg:city":"Silly (hoves)",
    "sg:classifiers":[
        {
            "category":"Sports & Exercise",
            "subcategory":"Stables",
            "type":"Entertainment"
        }
    ],
    "sg:phone":"+32 2 395 83 58",
    "sg:postcode":"7830",
    "sg:province":"Hainaut",
    "sg:tags":[
        "riding",
        "school"
    ],
    "wof:name":"Ferme Du Parc Sprl",
    "wof:placetype":"venue"
},
  "geometry": {"coordinates":[4.0452051163,50.6739463806],"type":"Point"}
}