{
  "type": "Feature",
  "properties": {
    "addr:full":"Oostnieuwkerkesteenweg 207 Roeselare West-Vlaanderen 8800",
    "addr:housenumber":"207",
    "addr:postcode":"8800",
    "addr:street":"Oostnieuwkerkesteenweg",
    "iso:country":"BE",
    "sg:address":"Oostnieuwkerkesteenweg 207",
    "sg:city":"Roeselare",
    "sg:classifiers":[
        {
            "category":"Manufacturing",
            "subcategory":"Rubber & Plastics",
            "type":"Manufacturing & Wholesale Goods"
        }
    ],
    "sg:phone":"+32 51 22 95 95",
    "sg:postcode":"8800",
    "sg:province":"West-Vlaanderen",
    "sg:tags":[
        "packaging",
        "material",
        "-"
    ],
    "wof:name":"Van Hollebeke Plastics Nv",
    "wof:placetype":"venue"
},
  "geometry": {"coordinates":[3.0893230438,50.9450683594],"type":"Point"}
}