{
  "type": "Feature",
  "properties": {
    "addr:full":"Koevliet 2 Zele Oost-Vlaanderen 9240",
    "addr:housenumber":"2",
    "addr:postcode":"9240",
    "addr:street":"Koevliet",
    "iso:country":"BE",
    "sg:address":"Koevliet 2",
    "sg:city":"Zele",
    "sg:orig_category":"Maisons de repos and r\u00e9sidences",
    "sg:phone":"+32 52 44 83 44",
    "sg:postcode":"9240",
    "sg:province":"Oost-Vlaanderen",
    "wof:name":"Rusthuis De Vliet",
    "wof:placetype":"venue"
},
  "geometry": {"coordinates":[4.0265002251,51.0667533875],"type":"Point"}
}