{
  "type": "Feature",
  "properties": {
    "addr:full":"Zittaardstraat 46 Halen Limburg 3545",
    "addr:housenumber":"46",
    "addr:postcode":"3545",
    "addr:street":"Zittaardstraat",
    "iso:country":"BE",
    "sg:address":"Zittaardstraat 46",
    "sg:city":"Halen",
    "sg:orig_category":"Banken and kredietinstellingen",
    "sg:phone":"+32 13 46 16 85",
    "sg:postcode":"3545",
    "sg:province":"Limburg",
    "wof:name":"Citibank",
    "wof:placetype":"venue"
},
  "geometry": {"coordinates":[5.1054291725,50.9423522949],"type":"Point"}
}