{
  "type": "Feature",
  "properties": {
    "addr:full":"Karmelietenstraat 51 Geraardsbergen Oost-Vlaanderen 9500",
    "addr:housenumber":"51",
    "addr:postcode":"9500",
    "addr:street":"Karmelietenstraat",
    "iso:country":"BE",
    "sg:address":"Karmelietenstraat 51",
    "sg:city":"Geraardsbergen",
    "sg:orig_category":"Avocats and conseillers juridiques",
    "sg:phone":"+32 54 41 55 62",
    "sg:postcode":"9500",
    "sg:province":"Oost-Vlaanderen",
    "wof:name":"Guido De Padt",
    "wof:placetype":"venue"
},
  "geometry": {"coordinates":[3.878401041,50.7745361328],"type":"Point"}
}