{
  "type": "Feature",
  "properties": {
    "addr:full":"Beekboshoek 148 Kontich Antwerpen 2550",
    "addr:housenumber":"148",
    "addr:postcode":"2550",
    "addr:street":"Beekboshoek",
    "iso:country":"BE",
    "sg:address":"Beekboshoek 148",
    "sg:city":"Kontich",
    "sg:orig_category":"Peinture. Rev\u00eatements pour sols and murs",
    "sg:phone":"+32 15 31 07 58",
    "sg:postcode":"2550",
    "sg:province":"Antwerpen",
    "wof:name":"Maria Peeters",
    "wof:placetype":"venue"
},
  "geometry": {"coordinates":[4.469851017,51.1063232422],"type":"Point"}
}