{
  "type": "Feature",
  "properties": {
    "iso:country":"BE",
    "sg:address":"Bergstraat 8",
    "sg:city":"Kampenhout",
    "sg:orig_category":"Kapsalons",
    "sg:phone":"+32 16 65 60 06",
    "sg:postcode":"1910",
    "sg:province":"Vlaams-Brabant",
    "wof:name":"Coiffure Greet",
    "wof:placetype":"venue"
},
  "geometry": {"coordinates":[4.5370178223,50.9319343567],"type":"Point"}
}