{
  "type": "Feature",
  "properties": {
    "iso:country":"BE",
    "sg:address":"Rue Petit Bois 9",
    "sg:city":"Huy",
    "sg:orig_category":"Artsen and specialisten",
    "sg:phone":"+32 85 21 40 33",
    "sg:postcode":"4500",
    "sg:province":"Li\u00e8ge",
    "wof:name":"Jean-claude Colon",
    "wof:placetype":"venue"
},
  "geometry": {"coordinates":[5.2382488251,50.5319976807],"type":"Point"}
}