{
  "type": "Feature",
  "properties": {
    "iso:country":"BE",
    "sg:address":"Gentsesteenweg 51",
    "sg:city":"Damme",
    "sg:orig_category":"Tuinen",
    "sg:phone":"+32 50 37 79 02",
    "sg:postcode":"8730",
    "sg:province":"West-Vlaanderen",
    "wof:name":"Deschepper Geert",
    "wof:placetype":"venue"
},
  "geometry": {"coordinates":[3.3408629894,51.143787384],"type":"Point"}
}