{
  "type": "Feature",
  "properties": {
    "iso:country":"BE",
    "sg:address":"Bogaardenstraat 80",
    "sg:city":"Leuven",
    "sg:classifiers":[
        {
            "category":"Communications",
            "subcategory":"Film & Video Production",
            "type":"Services"
        }
    ],
    "sg:phone":"+32 16 23 03 10",
    "sg:postcode":"3000",
    "sg:province":"Vlaams-Brabant",
    "sg:tags":[
        "hiring",
        "-",
        "equipment"
    ],
    "wof:name":"Bfl-videovision Vzw",
    "wof:placetype":"venue"
},
  "geometry": {"coordinates":[4.7109999657,50.8774261475],"type":"Point"}
}