{
  "type": "Feature",
  "properties": {
    "iso:country":"BE",
    "sg:address":"Eeksken 45",
    "sg:city":"Lovendegem",
    "sg:orig_category":"Woningbouw",
    "sg:phone":"+32 9 357 43 51",
    "sg:postcode":"9920",
    "sg:province":"Oost-Vlaanderen",
    "wof:name":"Lozie Gebroeders",
    "wof:placetype":"venue"
},
  "geometry": {"coordinates":[3.6464500427,51.1284103394],"type":"Point"}
}