{
  "type": "Feature",
  "properties": {
    "addr:full":"Chauss\u00c9e De Gand 194 Sint-jans-molenbeek/molenbeek-saint-jean Bruxelles-Capitale 1080",
    "addr:housenumber":"194;/",
    "addr:postcode":"1080",
    "addr:street":"Chausse\u0301E De Gand;Sint-Jans-Molenbeek",
    "iso:country":"BE",
    "sg:address":"Chauss\u00c9e De Gand 194",
    "sg:city":"Sint-jans-molenbeek/molenbeek-saint-jean",
    "sg:orig_category":"Boucheries",
    "sg:phone":"+32 2 411 14 88",
    "sg:postcode":"1080",
    "sg:province":"Bruxelles-Capitale",
    "wof:name":"Boucherie Bassma",
    "wof:placetype":"venue"
},
  "geometry": {"coordinates":[4.3332719803,50.8569564819],"type":"Point"}
}