{
  "type": "Feature",
  "properties": {
    "addr:full":"Oude Wichelsesteenweg 3 Lede Oost-Vlaanderen 9340",
    "addr:housenumber":"3",
    "addr:postcode":"9340",
    "addr:street":"Oude Wichelsesteenweg",
    "iso:country":"BE",
    "sg:address":"Oude Wichelsesteenweg 3",
    "sg:city":"Lede",
    "sg:classifiers":[
        {
            "category":"Insurance",
            "subcategory":"Insurance Agent",
            "type":"Services"
        }
    ],
    "sg:phone":"+32 53 80 60 50",
    "sg:postcode":"9340",
    "sg:province":"Oost-Vlaanderen",
    "sg:tags":[
        "verzekeringsmakelaars",
        "expert"
    ],
    "wof:name":"Zakenkantoor Sonck",
    "wof:placetype":"venue"
},
  "geometry": {"coordinates":[3.974545002,50.9802284241],"type":"Point"}
}