{
  "type": "Feature",
  "properties": {
    "iso:country":"BE",
    "sg:address":"Transportstraat 1",
    "sg:city":"Tessenderlo",
    "sg:classifiers":[
        {
            "category":"Manufacturing",
            "subcategory":"Electronics",
            "type":"Manufacturing & Wholesale Goods"
        }
    ],
    "sg:phone":"+32 13 67 07 80",
    "sg:postcode":"3980",
    "sg:province":"Limburg",
    "sg:tags":[
        "sub-assembly",
        "electronic"
    ],
    "wof:name":"Epiq Nv",
    "wof:placetype":"venue"
},
  "geometry": {"coordinates":[5.0875849724,51.0672340393],"type":"Point"}
}