{
  "type": "Feature",
  "properties": {
    "addr:full":"Veerstraat 57 Gent Oost-Vlaanderen 9031",
    "addr:housenumber":"57",
    "addr:postcode":"9031",
    "addr:street":"Veerstraat;Oost-Vlaanderen",
    "iso:country":"BE",
    "sg:address":"Veerstraat 57",
    "sg:city":"Gent",
    "sg:classifiers":[
        {
            "category":"Insurance",
            "subcategory":"Insurance Agent",
            "type":"Services"
        }
    ],
    "sg:phone":"+32 9 237 01 88",
    "sg:postcode":"9031",
    "sg:province":"Oost-Vlaanderen",
    "sg:tags":[
        "verzekeringsmakelaars",
        "expert"
    ],
    "wof:name":"Van De Wilde",
    "wof:placetype":"venue"
},
  "geometry": {"coordinates":[3.6668899059,51.0510787964],"type":"Point"}
}