{
  "type": "Feature",
  "properties": {
    "addr:full":"Pater Beckstraat 43 Box 22 Kortrijk West-Vlaanderen 8500",
    "addr:housenumber":"43 box 22",
    "addr:postcode":"8500",
    "addr:street":"Pater Beckstraat",
    "iso:country":"BE",
    "sg:address":"Pater Beckstraat 43 Box 22",
    "sg:city":"Kortrijk",
    "sg:classifiers":[
        {
            "category":"Professional",
            "type":"Services"
        }
    ],
    "sg:phone":"+32 56 21 83 31",
    "sg:postcode":"8500",
    "sg:province":"West-Vlaanderen",
    "sg:tags":[
        "surveyor",
        "-",
        "valuer"
    ],
    "wof:name":"Exco",
    "wof:placetype":"venue"
},
  "geometry": {"coordinates":[3.2668840885,50.8201408386],"type":"Point"}
}