{
  "type": "Feature",
  "properties": {
    "iso:country":"BE",
    "sg:address":"Rue De Courcelles 10",
    "sg:city":"Charleroi (roux)",
    "sg:classifiers":[
        {
            "category":"Education",
            "subcategory":"University",
            "type":"Public Place"
        }
    ],
    "sg:phone":"+32 71 45 11 08",
    "sg:postcode":"6044",
    "sg:province":"Hainaut",
    "sg:tags":[
        "higher"
    ],
    "wof:name":"Centre D'enseognement Sup\u00e9rieur Pour Adultes",
    "wof:placetype":"venue"
},
  "geometry": {"coordinates":[4.3859081268,50.4414291382],"type":"Point"}
}