{
  "type": "Feature",
  "properties": {
    "addr:full":"Kerkstraat 33 Waarschoot Oost-Vlaanderen 9950",
    "addr:housenumber":"33",
    "addr:postcode":"9950",
    "addr:street":"Kerkstraat",
    "iso:country":"BE",
    "sg:address":"Kerkstraat 33",
    "sg:city":"Waarschoot",
    "sg:orig_category":"Installation de menuiserie en bois and plastique",
    "sg:phone":"+32 9 377 08 27",
    "sg:postcode":"9950",
    "sg:province":"Oost-Vlaanderen",
    "wof:name":"R Batsleer",
    "wof:placetype":"venue"
},
  "geometry": {"coordinates":[3.6054968834,51.1494789124],"type":"Point"}
}