{
  "type": "Feature",
  "properties": {
    "addr:full":"Aachener Strasse 173 Sankt Vith Li\u00e8ge 4780",
    "addr:housenumber":"173",
    "addr:postcode":"4780",
    "addr:street":"Aachener Strasse",
    "iso:country":"BE",
    "sg:address":"Aachener Strasse 173",
    "sg:city":"Sankt Vith",
    "sg:classifiers":[
        {
            "category":"Professional",
            "subcategory":"Accounting & Tax Preparation",
            "type":"Services"
        }
    ],
    "sg:phone":"+32 80 22 13 55",
    "sg:postcode":"4780",
    "sg:province":"Li\u00e8ge",
    "sg:tags":[
        "bookkeeper"
    ],
    "wof:name":"Thelen W",
    "wof:placetype":"venue"
},
  "geometry": {"coordinates":[6.138657093,50.2974205017],"type":"Point"}
}