{
  "type": "Feature",
  "properties": {
    "addr:full":"Chauss\u00c9e De Charleroi 65d Charleroi Hainaut 6060",
    "addr:housenumber":"65d",
    "addr:postcode":"6060",
    "addr:street":"Chausse\u0301E De Charleroi;Hainaut",
    "iso:country":"BE",
    "sg:address":"Chauss\u00c9e De Charleroi 65d",
    "sg:city":"Charleroi",
    "sg:orig_category":"Caf\u00e9s Sportterreinen and installaties behalve sportcentra",
    "sg:phone":"+32 71 42 01 28",
    "sg:postcode":"6060",
    "sg:province":"Hainaut",
    "wof:name":"Le Charbon Blanc",
    "wof:placetype":"venue"
},
  "geometry": {"coordinates":[4.4754500389,50.4013328552],"type":"Point"}
}