{
  "type": "Feature",
  "properties": {
    "iso:country":"BE",
    "sg:address":"Zeelsebaan 26",
    "sg:city":"Grembergen",
    "sg:classifiers":[
        {
            "category":"Shopping",
            "type":"Retail Goods"
        }
    ],
    "sg:phone":"+32 52 21 17 04",
    "sg:postcode":"9200",
    "sg:province":"Oost-Vlaanderen",
    "sg:tags":[
        "metallurgy",
        "finished",
        "-",
        "metalworking",
        "metallic"
    ],
    "wof:name":"Metaalkonstrukties Moens Nv",
    "wof:placetype":"venue"
},
  "geometry": {"coordinates":[4.0938057899,51.0444755554],"type":"Point"}
}