{
  "type": "Feature",
  "properties": {
    "iso:country":"BE",
    "sg:address":"Lindelsebaan 65",
    "sg:city":"Overpelt",
    "sg:classifiers":[
        {
            "category":"Health Services",
            "subcategory":"Health Practitioner",
            "type":"Services"
        }
    ],
    "sg:phone":"+32 11 79 29 63",
    "sg:postcode":"3900",
    "sg:province":"Limburg",
    "sg:tags":[
        "physiotherapist"
    ],
    "wof:name":"Spooren Joeri",
    "wof:placetype":"venue"
},
  "geometry": {"coordinates":[5.4095749855,51.205997467],"type":"Point"}
}