{
  "type": "Feature",
  "properties": {
    "addr:full":"Otegemse Steenweg 17 Deerlijk West-Vlaanderen 8540",
    "addr:housenumber":"17",
    "addr:postcode":"8540",
    "addr:street":"Steenweg",
    "iso:country":"BE",
    "sg:address":"Otegemse Steenweg 17",
    "sg:city":"Deerlijk",
    "sg:classifiers":[
        {
            "category":"Park",
            "subcategory":"National",
            "type":"Public Place"
        }
    ],
    "sg:phone":"+32 496 54 07 86",
    "sg:postcode":"8540",
    "sg:province":"West-Vlaanderen",
    "sg:tags":[
        "recreation"
    ],
    "wof:name":"Toverfluit (de)",
    "wof:placetype":"venue"
},
  "geometry": {"coordinates":[3.3741409779,50.8155136108],"type":"Point"}
}