{
  "type": "Feature",
  "properties": {
    "iso:country":"BE",
    "sg:address":"Quai De L'industrie 44",
    "sg:city":"Ciney",
    "sg:classifiers":[
        {
            "category":"Health Services",
            "subcategory":"Health Practitioner",
            "type":"Services"
        }
    ],
    "sg:phone":"+32 83 21 62 61",
    "sg:postcode":"5590",
    "sg:province":"Namur",
    "sg:tags":[
        "physiotherapist"
    ],
    "wof:name":"Moors F",
    "wof:placetype":"venue"
},
  "geometry": {"coordinates":[5.0895428658,50.2956695557],"type":"Point"}
}