{
  "type": "Feature",
  "properties": {
    "iso:country":"BE",
    "sg:address":"Kwadamstraat 52",
    "sg:city":"Knesselare",
    "sg:orig_category":"Plaatsen van vloer- and muurbekleding Schilders",
    "sg:phone":"+32 9 374 39 17",
    "sg:postcode":"9910",
    "sg:province":"Oost-Vlaanderen",
    "wof:name":"Erik Vermeire",
    "wof:placetype":"venue"
},
  "geometry": {"coordinates":[3.4028658867,51.1317634583],"type":"Point"}
}