{
  "type": "Feature",
  "properties": {
    "addr:full":"Leopoldstraat 19 Merksplas Antwerpen 2330",
    "addr:housenumber":"19",
    "addr:postcode":"2330",
    "addr:street":"Leopoldstraat",
    "iso:country":"BE",
    "sg:address":"Leopoldstraat 19",
    "sg:city":"Merksplas",
    "sg:orig_category":"Brood, gebak and snoepgoed",
    "sg:phone":"+32 14 63 30 42",
    "sg:postcode":"2330",
    "sg:province":"Antwerpen",
    "wof:name":"Bakkerij Hendriks-teise",
    "wof:placetype":"venue"
},
  "geometry": {"coordinates":[4.8644800186,51.3571090698],"type":"Point"}
}