{
  "type": "Feature",
  "properties": {
    "iso:country":"BE",
    "sg:address":"Brandekensweg 92",
    "sg:city":"Schelle",
    "sg:orig_category":"Fietsen Fab",
    "sg:phone":"+32 3 880 63 80",
    "sg:postcode":"2627",
    "sg:province":"Antwerpen",
    "wof:name":"Van Der Wal",
    "wof:placetype":"venue"
},
  "geometry": {"coordinates":[4.3712358475,51.1163482666],"type":"Point"}
}