{
  "type": "Feature",
  "properties": {
    "addr:full":"Rue Haute-crotte 47 Verviers (stembert) Li\u00e8ge 4801",
    "addr:housenumber":"47",
    "addr:postcode":"4801",
    "addr:street":"Rue Haute-Crotte",
    "iso:country":"BE",
    "sg:address":"Rue Haute-crotte 47",
    "sg:city":"Verviers (stembert)",
    "sg:classifiers":[
        {
            "category":"Retail",
            "subcategory":"Auto Repair",
            "type":"Services"
        }
    ],
    "sg:phone":"+32 87 78 66 52",
    "sg:postcode":"4801",
    "sg:province":"Li\u00e8ge",
    "sg:tags":[
        "garage",
        "mainten",
        "-",
        "truck"
    ],
    "wof:name":"O.c.m.",
    "wof:placetype":"venue"
},
  "geometry": {"coordinates":[5.8966932297,50.6028175354],"type":"Point"}
}