{
  "type": "Feature",
  "properties": {
    "addr:full":"Brakelsesteenweg 492 Ninove Oost-Vlaanderen 9400",
    "addr:housenumber":"492",
    "addr:postcode":"9400",
    "addr:street":"Brakelsesteenweg",
    "iso:country":"BE",
    "sg:address":"Brakelsesteenweg 492",
    "sg:city":"Ninove",
    "sg:orig_category":"Woningbouw",
    "sg:phone":"+32 54 32 83 57",
    "sg:postcode":"9400",
    "sg:province":"Oost-Vlaanderen",
    "wof:name":"Ronsyn Bruno",
    "wof:placetype":"venue"
},
  "geometry": {"coordinates":[4.0039701462,50.8359107971],"type":"Point"}
}