{
  "type": "Feature",
  "properties": {
    "addr:full":"Rue De Berghes 2 Li\u00c8ge Li\u00e8ge 4020",
    "addr:housenumber":"2",
    "addr:postcode":"4020",
    "addr:street":"Rue De Berghes",
    "iso:country":"BE",
    "sg:address":"Rue De Berghes 2",
    "sg:city":"Li\u00c8ge",
    "sg:classifiers":[
        {
            "category":"Cafe",
            "type":"Food & Drink"
        }
    ],
    "sg:phone":"+32 4 342 61 15",
    "sg:postcode":"4020",
    "sg:province":"Li\u00e8ge",
    "sg:tags":[
        "caf\u00e9s"
    ],
    "wof:name":"Caf\u00c9 Le Notger",
    "wof:placetype":"venue"
},
  "geometry": {"coordinates":[5.5832548141,50.6393318176],"type":"Point"}
}