{
  "type": "Feature",
  "properties": {
    "iso:country":"BE",
    "sg:address":"Eikelstraat 32",
    "sg:city":"De Pinte",
    "sg:orig_category":"Artsen and specialisten",
    "sg:phone":"+32 9 281 05 78",
    "sg:postcode":"9840",
    "sg:province":"Oost-Vlaanderen",
    "wof:name":"Ivo Taeymans",
    "wof:placetype":"venue"
},
  "geometry": {"coordinates":[3.6459679604,50.9977455139],"type":"Point"}
}