{
  "type": "Feature",
  "properties": {
    "addr:full":"Gentseweg 181 Beveren Oost-Vlaanderen 9120",
    "addr:housenumber":"181",
    "addr:postcode":"9120",
    "addr:street":"Gentseweg",
    "iso:country":"BE",
    "sg:address":"Gentseweg 181",
    "sg:city":"Beveren",
    "sg:orig_category":"Electrom\u00e9nager, t\u00e9l\u00e9visions and radios",
    "sg:phone":"+32 3 775 83 12",
    "sg:postcode":"9120",
    "sg:province":"Oost-Vlaanderen",
    "wof:name":"Klimalux",
    "wof:placetype":"venue"
},
  "geometry": {"coordinates":[4.2315878868,51.2010002136],"type":"Point"}
}