{
  "type": "Feature",
  "properties": {
    "iso:country":"BE",
    "sg:address":"Chauss\u00e9e De L'ourthe 193",
    "sg:city":"Marche-en-famenne",
    "sg:classifiers":[
        {
            "category":"Building & Trades",
            "subcategory":"Landscaping Services",
            "type":"Services"
        }
    ],
    "sg:phone":"+32 84 31 37 70",
    "sg:postcode":"6900",
    "sg:province":"Luxembourg",
    "sg:tags":[
        "gardening",
        "garden",
        "maintenance"
    ],
    "wof:name":"Gillet Y",
    "wof:placetype":"venue"
},
  "geometry": {"coordinates":[5.3717541695,50.2391166687],"type":"Point"}
}