{
  "type": "Feature",
  "properties": {
    "iso:country":"BE",
    "sg:address":"Industrieweg-noord 1137",
    "sg:city":"Opglabbeek",
    "sg:classifiers":[
        {
            "category":"Building & Trades",
            "subcategory":"Construction",
            "type":"Services"
        }
    ],
    "sg:phone":"+32 89 81 02 30",
    "sg:postcode":"3660",
    "sg:province":"Limburg",
    "sg:tags":[
        "roadway"
    ],
    "wof:name":"Hoogmartens Nv",
    "wof:placetype":"venue"
},
  "geometry": {"coordinates":[5.5441970825,51.0380401611],"type":"Point"}
}