{
  "type": "Feature",
  "properties": {
    "addr:full":"Wildert 74 Antwerpen (merksem) Antwerpen 2170",
    "addr:housenumber":"74",
    "addr:postcode":"2170",
    "addr:street":"Wildert",
    "iso:country":"BE",
    "sg:address":"Wildert 74",
    "sg:city":"Antwerpen (merksem)",
    "sg:classifiers":[
        {
            "category":"Wholesale",
            "subcategory":"Books, Periodicals, & Newspapers",
            "type":"Manufacturing & Wholesale Goods"
        }
    ],
    "sg:phone":"+32 3 647 12 34",
    "sg:postcode":"2170",
    "sg:province":"Antwerpen",
    "sg:tags":[
        "publisher"
    ],
    "wof:name":"Uitgeverij Marcom Bvba",
    "wof:placetype":"venue"
},
  "geometry": {"coordinates":[4.4505147934,51.246723175],"type":"Point"}
}