{
  "type": "Feature",
  "properties": {
    "addr:full":"Avenue Joseph Lejeune 25 Trois-ponts Li\u00e8ge 4980",
    "addr:housenumber":"25",
    "addr:postcode":"4980",
    "addr:street":"Avenue Joseph Lejeune",
    "iso:country":"BE",
    "sg:address":"Avenue Joseph Lejeune 25",
    "sg:city":"Trois-ponts",
    "sg:orig_category":"Artsen and specialisten",
    "sg:phone":"+32 80 68 49 02",
    "sg:postcode":"4980",
    "sg:province":"Li\u00e8ge",
    "wof:name":"Isabelle Laurent",
    "wof:placetype":"venue"
},
  "geometry": {"coordinates":[5.8688998222,50.3714065552],"type":"Point"}
}