{
  "type": "Feature",
  "properties": {
    "addr:full":"Rue Emile Vandervelde 29 Morlanwelz Hainaut 7141",
    "addr:housenumber":"29",
    "addr:postcode":"7141",
    "addr:street":"Rue Emile Vandervelde",
    "iso:country":"BE",
    "sg:address":"Rue Emile Vandervelde 29",
    "sg:city":"Morlanwelz",
    "sg:classifiers":[
        {
            "category":"Cafe",
            "type":"Food & Drink"
        }
    ],
    "sg:phone":"+32 64 44 33 49",
    "sg:postcode":"7141",
    "sg:province":"Hainaut",
    "sg:tags":[
        "caf\u00e9s"
    ],
    "wof:name":"Maison Du Peuple",
    "wof:placetype":"venue"
},
  "geometry": {"coordinates":[4.2584490776,50.4481086731],"type":"Point"}
}