{
  "type": "Feature",
  "properties": {
    "addr:full":"Dentergemstraat 76 Deinze Oost-Vlaanderen 9800",
    "addr:housenumber":"76",
    "addr:postcode":"9800",
    "addr:street":"Dentergemstraat",
    "iso:country":"BE",
    "sg:address":"Dentergemstraat 76",
    "sg:city":"Deinze",
    "sg:classifiers":[
        {
            "category":"Insurance",
            "subcategory":"Life Insurance",
            "type":"Services"
        }
    ],
    "sg:phone":"+32 51 63 59 27",
    "sg:postcode":"9800",
    "sg:province":"Oost-Vlaanderen",
    "sg:tags":[
        "assurance"
    ],
    "wof:name":"Zakenkantoor De Neve",
    "wof:placetype":"venue"
},
  "geometry": {"coordinates":[3.4412510395,50.9773902893],"type":"Point"}
}