{
  "type": "Feature",
  "properties": {
    "addr:full":"Brusselsestraat 21 Leuven Vlaams-Brabant 3000",
    "addr:housenumber":"21",
    "addr:postcode":"3000",
    "addr:street":"Brusselsestraat",
    "iso:country":"BE",
    "sg:address":"Brusselsestraat 21",
    "sg:city":"Leuven",
    "sg:orig_category":"Dameskledingzaken",
    "sg:phone":"+32 16 22 38 63",
    "sg:postcode":"3000",
    "sg:province":"Vlaams-Brabant",
    "wof:name":"Huis Devernois",
    "wof:placetype":"venue"
},
  "geometry": {"coordinates":[4.69911623,50.8794326782],"type":"Point"}
}