{
  "type": "Feature",
  "properties": {
    "iso:country":"BE",
    "sg:address":"Beversesteenweg 112",
    "sg:city":"Roeselare",
    "sg:orig_category":"Artsen and specialisten",
    "sg:phone":"+32 51 22 15 46",
    "sg:postcode":"8800",
    "sg:province":"West-Vlaanderen",
    "wof:name":"Veerle Sterkmans",
    "wof:placetype":"venue"
},
  "geometry": {"coordinates":[3.1320118904,50.9535446167],"type":"Point"}
}