{
  "type": "Feature",
  "properties": {
    "addr:full":"Rue Sainte-croix 10 Tournai Hainaut 7500",
    "addr:housenumber":"10",
    "addr:postcode":"7500",
    "addr:street":"Rue Sainte-Croix",
    "iso:country":"BE",
    "sg:address":"Rue Sainte-croix 10",
    "sg:city":"Tournai",
    "sg:classifiers":[
        {
            "category":"Restaurant",
            "type":"Food & Drink"
        }
    ],
    "sg:phone":"+32 69 84 58 28",
    "sg:postcode":"7500",
    "sg:province":"Hainaut",
    "sg:tags":[
        "caf\u00e9s"
    ],
    "wof:name":"Taverne Le Pardieu",
    "wof:placetype":"venue"
},
  "geometry": {"coordinates":[3.3857729435,50.6102638245],"type":"Point"}
}