{
  "type": "Feature",
  "properties": {
    "addr:full":"Oliekouterstraat 14 Ardooie West-Vlaanderen 8850",
    "addr:housenumber":"14",
    "addr:postcode":"8850",
    "addr:street":"Oliekouterstraat",
    "iso:country":"BE",
    "sg:address":"Oliekouterstraat 14",
    "sg:city":"Ardooie",
    "sg:orig_category":"Producteurs de l\u00e9gumes",
    "sg:phone":"+32 51 74 47 71",
    "sg:postcode":"8850",
    "sg:province":"West-Vlaanderen",
    "wof:name":"Parmentier J. & B.",
    "wof:placetype":"venue"
},
  "geometry": {"coordinates":[3.1833209991,50.971244812],"type":"Point"}
}