{
  "type": "Feature",
  "properties": {
    "iso:country":"BE",
    "sg:address":"Papaverstr 39",
    "sg:city":"Merksem",
    "sg:classifiers":[
        {
            "category":"Professional",
            "subcategory":"Computer Services",
            "type":"Services"
        }
    ],
    "sg:phone":"+32 3 646 46 27",
    "sg:postcode":"2170",
    "sg:province":"Antwerpen",
    "sg:tags":[
        "information",
        "technology",
        "software"
    ],
    "wof:name":"Infoserv Nv",
    "wof:placetype":"venue"
},
  "geometry": {"coordinates":[4.4400348663,51.2526283264],"type":"Point"}
}