{
  "type": "Feature",
  "properties": {
    "iso:country":"BE",
    "sg:address":"Rue Du Prince 29",
    "sg:city":"Verviers",
    "sg:classifiers":[
        {
            "category":"Building & Trades",
            "subcategory":"Construction",
            "type":"Services"
        }
    ],
    "sg:phone":"+32 87 31 11 38",
    "sg:postcode":"4800",
    "sg:province":"Li\u00e8ge",
    "sg:tags":[
        "stair"
    ],
    "wof:name":"Sanitel",
    "wof:placetype":"venue"
},
  "geometry": {"coordinates":[5.8750929832,50.5981254578],"type":"Point"}
}