{
  "type": "Feature",
  "properties": {
    "iso:country":"BE",
    "sg:address":"Rue De Tournai 29",
    "sg:city":"Pecq",
    "sg:orig_category":"Boissons",
    "sg:phone":"+32 69 55 81 80",
    "sg:postcode":"7740",
    "sg:province":"Hainaut",
    "wof:name":"In Vino Veritas",
    "wof:placetype":"venue"
},
  "geometry": {"coordinates":[3.3385260105,50.6845397949],"type":"Point"}
}