{
  "type": "Feature",
  "properties": {
    "addr:full":"Rue Jean-martin Mar\u00c9chal 31 Verviers Li\u00e8ge 4800",
    "addr:housenumber":"31",
    "addr:postcode":"4800",
    "addr:street":"Rue Jean-Martin Mare\u0301Chal",
    "iso:country":"BE",
    "sg:address":"Rue Jean-martin Mar\u00c9chal 31",
    "sg:city":"Verviers",
    "sg:orig_category":"Plaatsen van vloer- and muurbekleding Woningbouw",
    "sg:phone":"+32 87 33 93 88",
    "sg:postcode":"4800",
    "sg:province":"Li\u00e8ge",
    "wof:name":"E.m.c. Constructions",
    "wof:placetype":"venue"
},
  "geometry": {"coordinates":[5.8594508171,50.5917663574],"type":"Point"}
}