{
  "type": "Feature",
  "properties": {
    "iso:country":"BE",
    "sg:address":"Rue Esp\u00e9ranto 26",
    "sg:city":"Erquelinnes (solre-sur-sambre)",
    "sg:classifiers":[
        {
            "category":"Personal",
            "subcategory":"Beauty Salon",
            "type":"Services"
        }
    ],
    "sg:phone":"+32 71 55 55 16",
    "sg:postcode":"6560",
    "sg:province":"Hainaut",
    "sg:tags":[
        "lady",
        "-",
        "hairdressing"
    ],
    "wof:name":"Maryline",
    "wof:placetype":"venue"
},
  "geometry": {"coordinates":[4.1594262123,50.3083648682],"type":"Point"}
}