{
  "type": "Feature",
  "properties": {
    "iso:country":"BE",
    "sg:address":"Vondelstraat 9",
    "sg:city":"Antwerpen",
    "sg:classifiers":[
        {
            "category":"Cafe",
            "type":"Food & Drink"
        }
    ],
    "sg:phone":"+32 3 227 43 17",
    "sg:postcode":"2060",
    "sg:province":"Antwerpen",
    "sg:tags":[
        "snack-bars"
    ],
    "wof:name":"A Janero",
    "wof:placetype":"venue"
},
  "geometry": {"coordinates":[4.4160909653,51.2247314453],"type":"Point"}
}