{
  "type": "Feature",
  "properties": {
    "addr:full":"Attenhovendreef 13 Holsbeek Vlaams-Brabant 3220",
    "addr:housenumber":"13",
    "addr:postcode":"3220",
    "addr:street":"Attenhovendreef",
    "iso:country":"BE",
    "sg:address":"Attenhovendreef 13",
    "sg:city":"Holsbeek",
    "sg:classifiers":[
        {
            "category":"Arts & Performance",
            "subcategory":"Art Gallery",
            "type":"Entertainment"
        }
    ],
    "sg:phone":"+32 16 44 43 66",
    "sg:postcode":"3220",
    "sg:province":"Vlaams-Brabant",
    "wof:name":"Mu-creation Bvba",
    "wof:placetype":"venue"
},
  "geometry": {"coordinates":[4.739590168,50.9130592346],"type":"Point"}
}