{
  "type": "Feature",
  "properties": {
    "addr:full":"Dorpstraat 67 Temse (elversele) Oost-Vlaanderen 9140",
    "addr:housenumber":"67",
    "addr:postcode":"9140",
    "addr:street":"Dorpstraat",
    "iso:country":"BE",
    "sg:address":"Dorpstraat 67",
    "sg:city":"Temse (elversele)",
    "sg:classifiers":[
        {
            "category":"Health Services",
            "subcategory":"Doctor",
            "type":"Services"
        }
    ],
    "sg:phone":"+32 52 46 36 67",
    "sg:postcode":"9140",
    "sg:province":"Oost-Vlaanderen",
    "sg:tags":[
        "medicinephysicians",
        "surgeon"
    ],
    "wof:name":"Deschuttere M",
    "wof:placetype":"venue"
},
  "geometry": {"coordinates":[4.1389379501,51.1146888733],"type":"Point"}
}