{
  "type": "Feature",
  "properties": {
    "addr:full":"Grotestraat 77 Geraardsbergen Oost-Vlaanderen 9500",
    "addr:housenumber":"77",
    "addr:postcode":"9500",
    "addr:street":"Grotestraat",
    "iso:country":"BE",
    "sg:address":"Grotestraat 77",
    "sg:city":"Geraardsbergen",
    "sg:orig_category":"Parfumeries",
    "sg:phone":"+32 54 41 11 24",
    "sg:postcode":"9500",
    "sg:province":"Oost-Vlaanderen",
    "wof:name":"Huis Dina",
    "wof:placetype":"venue"
},
  "geometry": {"coordinates":[3.87657094,50.7719192505],"type":"Point"}
}