{
  "type": "Feature",
  "properties": {
    "addr:full":"Rue Jules Dekeyn 10 Braine-le-comte Hainaut 7090",
    "addr:housenumber":"10",
    "addr:postcode":"7090",
    "addr:street":"Rue Jules Dekeyn",
    "iso:country":"BE",
    "sg:address":"Rue Jules Dekeyn 10",
    "sg:city":"Braine-le-comte",
    "sg:orig_category":"Reliure and finition",
    "sg:phone":"+32 67 64 60 04",
    "sg:postcode":"7090",
    "sg:province":"Hainaut",
    "wof:name":"Aurore Lechene",
    "wof:placetype":"venue"
},
  "geometry": {"coordinates":[4.2224378586,50.6095619202],"type":"Point"}
}