{
  "type": "Feature",
  "properties": {
    "iso:country":"BE",
    "sg:address":"Brugstraat 7",
    "sg:city":"Wevelgem",
    "sg:orig_category":"R\u00e9parations d'horloges, montres and bijoux. Bijouteries and horlogeries",
    "sg:phone":"+32 56 42 02 11",
    "sg:postcode":"8560",
    "sg:province":"West-Vlaanderen",
    "wof:name":"Huis Vandeginste",
    "wof:placetype":"venue"
},
  "geometry": {"coordinates":[3.1851830482,50.8097343445],"type":"Point"}
}