{
  "type": "Feature",
  "properties": {
    "addr:full":"Blokstraat 56 Londerzeel Vlaams-Brabant 1840",
    "addr:housenumber":"56",
    "addr:postcode":"1840",
    "addr:street":"Blokstraat",
    "iso:country":"BE",
    "sg:address":"Blokstraat 56",
    "sg:city":"Londerzeel",
    "sg:orig_category":"Gespecialiseerde residenti\u00eble bouw",
    "sg:phone":"+32 52 30 01 69",
    "sg:postcode":"1840",
    "sg:province":"Vlaams-Brabant",
    "wof:name":"Kiekens Kris & Co",
    "wof:placetype":"venue"
},
  "geometry": {"coordinates":[4.2549500465,51.0181617737],"type":"Point"}
}