{
  "type": "Feature",
  "properties": {
    "addr:full":"Rue Du Laveu 30 Li\u00c8ge Li\u00e8ge 4000",
    "addr:housenumber":"30",
    "addr:postcode":"4000",
    "addr:street":"Rue Du Laveu",
    "iso:country":"BE",
    "sg:address":"Rue Du Laveu 30",
    "sg:city":"Li\u00c8ge",
    "sg:orig_category":"Boucheries",
    "sg:phone":"+32 4 252 50 85",
    "sg:postcode":"4000",
    "sg:province":"Li\u00e8ge",
    "wof:name":"Henri Scheen",
    "wof:placetype":"venue"
},
  "geometry": {"coordinates":[5.5568981171,50.6315574646],"type":"Point"}
}