{
  "type": "Feature",
  "properties": {
    "addr:full":"Groenstraat 18 Putte Antwerpen 2580",
    "addr:housenumber":"18",
    "addr:postcode":"2580",
    "addr:street":"Groenstraat",
    "iso:country":"BE",
    "sg:address":"Groenstraat 18",
    "sg:city":"Putte",
    "sg:orig_category":"Diverse opleidingen and onderwijs Groententeelt",
    "sg:phone":"+32 15 76 16 08",
    "sg:postcode":"2580",
    "sg:province":"Antwerpen",
    "wof:name":"Market Response",
    "wof:placetype":"venue"
},
  "geometry": {"coordinates":[4.5890870094,51.0461273193],"type":"Point"}
}