{
  "type": "Feature",
  "properties": {
    "iso:country":"BE",
    "sg:address":"Rue Des Tomballes 9",
    "sg:city":"Seraing",
    "sg:orig_category":"M\u00e9decines alternatives",
    "sg:phone":"+32 4 234 42 39",
    "sg:postcode":"4101",
    "sg:province":"Li\u00e8ge",
    "wof:name":"D. Lef\u00c8vre",
    "wof:placetype":"venue"
},
  "geometry": {"coordinates":[5.4956111908,50.6190490723],"type":"Point"}
}