{
  "type": "Feature",
  "properties": {
    "iso:country":"BE",
    "sg:address":"Rue Du Ch\u00c2teau 9",
    "sg:city":"Celles",
    "sg:orig_category":"V\u00e9t\u00e9rinaires",
    "sg:phone":"+32 69 45 49 93",
    "sg:postcode":"7760",
    "sg:province":"Hainaut",
    "wof:name":"St\u00c9phanie Vanseymortier",
    "wof:placetype":"venue"
},
  "geometry": {"coordinates":[3.4264349937,50.69581604],"type":"Point"}
}