{
  "type": "Feature",
  "properties": {
    "addr:full":"Rue Rodenbach 64 Bruxelles (forest) Bruxelles-Capitale 1190",
    "addr:housenumber":"64",
    "addr:postcode":"1190",
    "addr:street":"Rue Rodenbach",
    "iso:country":"BE",
    "sg:address":"Rue Rodenbach 64",
    "sg:city":"Bruxelles (forest)",
    "sg:classifiers":[
        {
            "category":"Building & Trades",
            "subcategory":"Landscaping Services",
            "type":"Services"
        }
    ],
    "sg:phone":"+32 2 344 25 52",
    "sg:postcode":"1190",
    "sg:province":"Bruxelles-Capitale",
    "sg:tags":[
        "gardening",
        "garden",
        "maintenance"
    ],
    "wof:name":"Cr\u00e9avert",
    "wof:placetype":"venue"
},
  "geometry": {"coordinates":[4.3444738388,50.8181991577],"type":"Point"}
}