{
  "type": "Feature",
  "properties": {
    "addr:full":"Cingel 16 Vosselaar Antwerpen 2350",
    "addr:housenumber":"16",
    "addr:postcode":"2350",
    "addr:street":"Cingel",
    "iso:country":"BE",
    "sg:address":"Cingel 16",
    "sg:city":"Vosselaar",
    "sg:classifiers":[
        {
            "category":"Banks & Credit Unions",
            "subcategory":"Bank",
            "type":"Services"
        }
    ],
    "sg:phone":"+32 14 61 30 64",
    "sg:postcode":"2350",
    "sg:province":"Antwerpen",
    "wof:name":"Gemeentekrediet",
    "wof:placetype":"venue"
},
  "geometry": {"coordinates":[4.8876361847,51.3131484985],"type":"Point"}
}