{
  "type": "Feature",
  "properties": {
    "iso:country":"BE",
    "sg:address":"Brugsesteenweg 190",
    "sg:city":"Kortrijk",
    "sg:classifiers":[
        {
            "category":"Personal",
            "subcategory":"Beauty Salon",
            "type":"Services"
        }
    ],
    "sg:phone":"+32 56 36 03 66",
    "sg:postcode":"8500",
    "sg:province":"West-Vlaanderen",
    "sg:tags":[
        "lady",
        "-",
        "hairdressing"
    ],
    "wof:name":"Styling Marno",
    "wof:placetype":"venue"
},
  "geometry": {"coordinates":[3.2665860653,50.8427886963],"type":"Point"}
}