{
  "type": "Feature",
  "properties": {
    "addr:full":"Rue De Cerfontaine 5a Couvin (boussu-en-fagne) Namur 5660",
    "addr:housenumber":"5a",
    "addr:postcode":"5660",
    "addr:street":"Rue De Cerfontaine",
    "iso:country":"BE",
    "sg:address":"Rue De Cerfontaine 5a",
    "sg:city":"Couvin (boussu-en-fagne)",
    "sg:classifiers":[
        {
            "category":"Farming",
            "subcategory":"Farm & Veterinary Services",
            "type":"Manufacturing & Wholesale Goods"
        }
    ],
    "sg:phone":"+32 60 31 11 16",
    "sg:postcode":"5660",
    "sg:province":"Namur",
    "sg:tags":[
        "agricultural",
        "contractor"
    ],
    "wof:name":"Piron H",
    "wof:placetype":"venue"
},
  "geometry": {"coordinates":[4.4081540108,50.1192398071],"type":"Point"}
}