{
  "type": "Feature",
  "properties": {
    "addr:full":"Rue Du Press\u00c9 30 Binche Hainaut 7134",
    "addr:housenumber":"30",
    "addr:postcode":"7134",
    "addr:street":"Rue Du Presse\u0301",
    "iso:country":"BE",
    "sg:address":"Rue Du Press\u00c9 30",
    "sg:city":"Binche",
    "sg:classifiers":[
        {
            "category":"Personal",
            "subcategory":"Beauty Salon",
            "type":"Services"
        }
    ],
    "sg:phone":"+32 64 33 87 40",
    "sg:postcode":"7134",
    "sg:province":"Hainaut",
    "sg:tags":[
        "de",
        "coiffure"
    ],
    "wof:name":"Coiffure Fabienne",
    "wof:placetype":"venue"
},
  "geometry": {"coordinates":[4.2201910019,50.4156646729],"type":"Point"}
}