{
  "type": "Feature",
  "properties": {
    "addr:full":"Antwerpsestraat 298 Niel Antwerpen 2845",
    "addr:housenumber":"298",
    "addr:postcode":"2845",
    "addr:street":"Antwerpsestraat",
    "iso:country":"BE",
    "sg:address":"Antwerpsestraat 298",
    "sg:city":"Niel",
    "sg:classifiers":[
        {
            "category":"Building & Trades",
            "subcategory":"Construction",
            "type":"Services"
        }
    ],
    "sg:phone":"+32 3 290 48 39",
    "sg:postcode":"2845",
    "sg:province":"Antwerpen",
    "sg:tags":[
        "ceiling"
    ],
    "wof:name":"Algyp Bvba",
    "wof:placetype":"venue"
},
  "geometry": {"coordinates":[4.3320159912,51.1148948669],"type":"Point"}
}