{
  "type": "Feature",
  "properties": {
    "iso:country":"BE",
    "sg:address":"Middenlaan 34",
    "sg:city":"Leopoldsburg",
    "sg:orig_category":"DIVERSE RECREATIEVE ACTIVITEITEN",
    "sg:phone":"+32 11 34 30 27",
    "sg:postcode":"3971",
    "sg:province":"Limburg",
    "wof:name":"Bridge Club M.b.c.l.",
    "wof:placetype":"venue"
},
  "geometry": {"coordinates":[5.231180191,51.1209831238],"type":"Point"}
}