{
  "type": "Feature",
  "properties": {
    "addr:full":"Place Ernest Rongvaux 8a-o Waremme Li\u00e8ge 4300",
    "addr:housenumber":"8a-o",
    "addr:postcode":"4300",
    "addr:street":"Place Ernest Rongvaux",
    "iso:country":"BE",
    "sg:address":"Place Ernest Rongvaux 8a-o",
    "sg:city":"Waremme",
    "sg:classifiers":[
        {
            "category":"Building & Trades",
            "subcategory":"Locksmith",
            "type":"Services"
        }
    ],
    "sg:phone":"+32 19 33 18 90",
    "sg:postcode":"4300",
    "sg:province":"Li\u00e8ge",
    "sg:tags":[
        "lock",
        "key"
    ],
    "wof:name":"Jl Soci\u00e9t\u00e9",
    "wof:placetype":"venue"
},
  "geometry": {"coordinates":[5.2565498352,50.6982498169],"type":"Point"}
}