{
  "type": "Feature",
  "properties": {
    "addr:full":"Boulevard Martin 6 Ottignies-louvain-la-neuve (ottignies) Brabant Wallon 1340",
    "addr:housenumber":"6",
    "addr:postcode":"1340",
    "addr:street":"Boulevard Martin",
    "iso:country":"BE",
    "sg:address":"Boulevard Martin 6",
    "sg:city":"Ottignies-louvain-la-neuve (ottignies)",
    "sg:classifiers":[
        {
            "category":"Personal",
            "subcategory":"Beauty Salon",
            "type":"Services"
        }
    ],
    "sg:phone":"+32 10 41 15 04",
    "sg:postcode":"1340",
    "sg:province":"Brabant Wallon",
    "wof:name":"Massart C",
    "wof:placetype":"venue"
},
  "geometry": {"coordinates":[4.5690178871,50.6655197144],"type":"Point"}
}