{
  "type": "Feature",
  "properties": {
    "addr:full":"Kerkstraat 66 Lokeren Oost-Vlaanderen 9160",
    "addr:housenumber":"66",
    "addr:postcode":"9160",
    "addr:street":"Kerkstraat",
    "iso:country":"BE",
    "sg:address":"Kerkstraat 66",
    "sg:city":"Lokeren",
    "sg:orig_category":"Notarissen",
    "sg:phone":"+32 9 348 13 25",
    "sg:postcode":"9160",
    "sg:province":"Oost-Vlaanderen",
    "wof:name":"Jean Matthys",
    "wof:placetype":"venue"
},
  "geometry": {"coordinates":[3.9940600395,51.1028747559],"type":"Point"}
}