{
  "type": "Feature",
  "properties": {
    "iso:country":"BE",
    "sg:address":"Kleine Warmestraat 27",
    "sg:city":"Maldegem",
    "sg:orig_category":"Travaux de pl\u00e2trage",
    "sg:phone":"+32 50 71 28 84",
    "sg:postcode":"9990",
    "sg:province":"Oost-Vlaanderen",
    "wof:name":"Fa. De Baets R. & Zn",
    "wof:placetype":"venue"
},
  "geometry": {"coordinates":[3.4519441128,51.2171516418],"type":"Point"}
}