{
  "type": "Feature",
  "properties": {
    "iso:country":"BE",
    "sg:address":"Rue Des Bonnes-villes 68",
    "sg:city":"Li\u00c8ge",
    "sg:orig_category":"R\u00e9parations de chaussures and articles en cuir",
    "sg:phone":"+32 4 343 52 73",
    "sg:postcode":"4020",
    "sg:province":"Li\u00e8ge",
    "wof:name":"Jean-claude Brants",
    "wof:placetype":"venue"
},
  "geometry": {"coordinates":[5.5897269249,50.6425209045],"type":"Point"}
}