{
  "type": "Feature",
  "properties": {
    "iso:country":"BE",
    "sg:address":"Place Sainte-marguerite 4",
    "sg:city":"Namur",
    "sg:orig_category":"M\u00e9decins and sp\u00e9cialistes",
    "sg:phone":"+32 81 21 51 66",
    "sg:postcode":"5004",
    "sg:province":"Namur",
    "wof:name":"V\u00c9ronique Bloquiaux",
    "wof:placetype":"venue"
},
  "geometry": {"coordinates":[4.8912858963,50.4716720581],"type":"Point"}
}