{
  "type": "Feature",
  "properties": {
    "iso:country":"BE",
    "sg:address":"Begonialaan 10",
    "sg:city":"Lochristi",
    "sg:orig_category":"Instituts de beaut\u00e9",
    "sg:phone":"+32 9 355 14 45",
    "sg:postcode":"9080",
    "sg:province":"Oost-Vlaanderen",
    "wof:name":"Kathleen Van Maldegem",
    "wof:placetype":"venue"
},
  "geometry": {"coordinates":[3.8174190521,51.092956543],"type":"Point"}
}