{
  "type": "Feature",
  "properties": {
    "iso:country":"BE",
    "sg:address":"Rue Du Grand Central 24",
    "sg:city":"Charleroi",
    "sg:classifiers":[
        {
            "category":"Restaurant",
            "type":"Food & Drink"
        }
    ],
    "sg:phone":"+32 71 32 37 70",
    "sg:postcode":"6000",
    "sg:province":"Hainaut",
    "wof:name":"La Rivi\u00c8re Des Parfums",
    "wof:placetype":"venue"
},
  "geometry": {"coordinates":[4.4376702309,50.4106674194],"type":"Point"}
}