{
  "type": "Feature",
  "properties": {
    "addr:full":"Weststraat 27 Koksijde (oostduinkerke) West-Vlaanderen 8670",
    "addr:housenumber":"27",
    "addr:postcode":"8670",
    "addr:street":"Weststraat",
    "iso:country":"BE",
    "sg:address":"Weststraat 27",
    "sg:city":"Koksijde (oostduinkerke)",
    "sg:classifiers":[
        {
            "category":"Autos & Motor Vehicles",
            "subcategory":"Automobile Sales",
            "type":"Retail Goods"
        }
    ],
    "sg:phone":"+32 58 51 67 19",
    "sg:postcode":"8670",
    "sg:province":"West-Vlaanderen",
    "sg:tags":[
        "car",
        "used",
        "-"
    ],
    "wof:name":"Maveau",
    "wof:placetype":"venue"
},
  "geometry": {"coordinates":[2.6712501049,51.1132354736],"type":"Point"}
}