{
  "type": "Feature",
  "properties": {
    "iso:country":"BE",
    "sg:address":"Hodbomont 24",
    "sg:city":"Theux",
    "sg:classifiers":[
        {
            "category":"Restaurant",
            "type":"Food & Drink"
        }
    ],
    "sg:phone":"+32 87 54 10 12",
    "sg:postcode":"4910",
    "sg:province":"Li\u00e8ge",
    "wof:name":"Restaurant Le Vivandier",
    "wof:placetype":"venue"
},
  "geometry": {"coordinates":[5.776309967,50.5276527405],"type":"Point"}
}