{
  "type": "Feature",
  "properties": {
    "addr:full":"Smedenstraat 38 Brugge West-Vlaanderen 8000",
    "addr:housenumber":"38",
    "addr:postcode":"8000",
    "addr:street":"Smedenstraat",
    "iso:country":"BE",
    "sg:address":"Smedenstraat 38",
    "sg:city":"Brugge",
    "sg:classifiers":[
        {
            "category":"Shopping",
            "subcategory":"Shoes",
            "type":"Retail Goods"
        }
    ],
    "sg:phone":"+32 50 33 76 52",
    "sg:postcode":"8000",
    "sg:province":"West-Vlaanderen",
    "sg:tags":[
        "slipper",
        "-"
    ],
    "wof:name":"De 7 Mijlslaars",
    "wof:placetype":"venue"
},
  "geometry": {"coordinates":[3.2149488926,51.2054748535],"type":"Point"}
}