{
  "type": "Feature",
  "properties": {
    "addr:full":"Rue Du Parc 42 Fontaine-l'ev\u00eaque Hainaut 6140",
    "addr:housenumber":"42",
    "addr:postcode":"6140",
    "addr:street":"Rue Du Parc;\u0302Que Hainaut",
    "iso:country":"BE",
    "sg:address":"Rue Du Parc 42",
    "sg:city":"Fontaine-l'ev\u00eaque",
    "sg:classifiers":[
        {
            "category":"Professional",
            "subcategory":"Lawyer & Legal Services",
            "type":"Services"
        }
    ],
    "sg:phone":"+32 71 52 57 25",
    "sg:postcode":"6140",
    "sg:province":"Hainaut",
    "wof:name":"Attout Emmanuelle",
    "wof:placetype":"venue"
},
  "geometry": {"coordinates":[-111.9644622803,46.2507972717],"type":"Point"}
}