{
  "type": "Feature",
  "properties": {
    "addr:full":"Oude Burg 15 Brugge West-Vlaanderen 8000",
    "addr:housenumber":"15",
    "addr:postcode":"8000",
    "addr:street":"Oude Burg",
    "iso:country":"BE",
    "sg:address":"Oude Burg 15",
    "sg:city":"Brugge",
    "sg:orig_category":"Agences de voyages",
    "sg:phone":"+32 50 33 26 62",
    "sg:postcode":"8000",
    "sg:province":"West-Vlaanderen",
    "wof:name":"Ultra Montes Brugge",
    "wof:placetype":"venue"
},
  "geometry": {"coordinates":[3.2263131142,51.2083702087],"type":"Point"}
}