{
  "type": "Feature",
  "properties": {
    "iso:country":"BE",
    "sg:address":"Beling 32",
    "sg:city":"Beersel",
    "sg:orig_category":"Reliure and finition",
    "sg:phone":"+32 2 380 31 52",
    "sg:postcode":"1653",
    "sg:province":"Vlaams-Brabant",
    "wof:name":"Francine Haesaerts",
    "wof:placetype":"venue"
},
  "geometry": {"coordinates":[4.2991251945,50.7301254272],"type":"Point"}
}