{
  "type": "Feature",
  "properties": {
    "addr:full":"Rue Pr\u00c9-du-cygne 45 Li\u00c8ge Li\u00e8ge 4020",
    "addr:housenumber":"45",
    "addr:postcode":"4020",
    "addr:street":"Rue Pre\u0301-Du-Cygne",
    "iso:country":"BE",
    "sg:address":"Rue Pr\u00c9-du-cygne 45",
    "sg:city":"Li\u00c8ge",
    "sg:orig_category":"Equipement divers pour commerces Produits chimiques D\u00e9chets and d\u00e9bris Gr",
    "sg:phone":"+32 4 343 98 05",
    "sg:postcode":"4020",
    "sg:province":"Li\u00e8ge",
    "wof:name":"Debouny A.",
    "wof:placetype":"venue"
},
  "geometry": {"coordinates":[5.6346750259,50.6462516785],"type":"Point"}
}