{
  "type": "Feature",
  "properties": {
    "addr:full":"Stationsstraat 28 Sint-niklaas Oost-Vlaanderen 9100",
    "addr:housenumber":"28",
    "addr:postcode":"9100",
    "addr:street":"Stationsstraat",
    "iso:country":"BE",
    "sg:address":"Stationsstraat 28",
    "sg:city":"Sint-niklaas",
    "sg:classifiers":[
        {
            "category":"Shopping",
            "subcategory":"Clothing, Apparel, & Fashions",
            "type":"Retail Goods"
        }
    ],
    "sg:phone":"+32 3 777 74 94",
    "sg:postcode":"9100",
    "sg:province":"Oost-Vlaanderen",
    "sg:tags":[
        "v\u00eatements",
        "pour",
        "dame"
    ],
    "wof:name":"We Women",
    "wof:placetype":"venue"
},
  "geometry": {"coordinates":[4.1413488388,51.1659660339],"type":"Point"}
}