{
  "type": "Feature",
  "properties": {
    "addr:full":"Meerlaan 176-178 Zottegem Oost-Vlaanderen 9620",
    "addr:housenumber":"176-178",
    "addr:postcode":"9620",
    "addr:street":"Meerlaan",
    "iso:country":"BE",
    "sg:address":"Meerlaan 176-178",
    "sg:city":"Zottegem",
    "sg:orig_category":"Entretien and r\u00e9parations de voitures. V\u00e9hicules automobiles",
    "sg:phone":"+32 9 360 21 95",
    "sg:postcode":"9620",
    "sg:province":"Oost-Vlaanderen",
    "wof:name":"B.m.w. Zottegem Motors",
    "wof:placetype":"venue"
},
  "geometry": {"coordinates":[3.8123300076,50.861328125],"type":"Point"}
}