{
  "type": "Feature",
  "properties": {
    "addr:full":"Rue Des R\u00f4tisseurs 4 Assesse (flor\u00e9e) Namur 5334",
    "addr:housenumber":"4",
    "addr:postcode":"5334",
    "addr:street":"Rue Des Ro\u0302Tisseurs",
    "iso:country":"BE",
    "sg:address":"Rue Des R\u00f4tisseurs 4",
    "sg:city":"Assesse (flor\u00e9e)",
    "sg:classifiers":[
        {
            "category":"Sports & Exercise",
            "subcategory":"Stables",
            "type":"Entertainment"
        }
    ],
    "sg:phone":"+32 478 25 31 57",
    "sg:postcode":"5334",
    "sg:province":"Namur",
    "sg:tags":[
        "riding",
        "school"
    ],
    "wof:name":"Galops Nature",
    "wof:placetype":"venue"
},
  "geometry": {"coordinates":[5.0661940575,50.3803100586],"type":"Point"}
}