{
  "type": "Feature",
  "properties": {
    "iso:country":"BE",
    "sg:address":"J. Sandersin 164",
    "sg:city":"Hemiksem",
    "sg:orig_category":"Bouwmaterialen Gh",
    "sg:phone":"+32 3 877 59 31",
    "sg:postcode":"2620",
    "sg:province":"Antwerpen",
    "wof:name":"V.d. Construction",
    "wof:placetype":"venue"
},
  "geometry": {"coordinates":[4.3521580696,51.1379508972],"type":"Point"}
}