{
  "type": "Feature",
  "properties": {
    "addr:full":"Bornstraat 49 Kortessem Limburg 3721",
    "addr:housenumber":"49",
    "addr:postcode":"3721",
    "addr:street":"Bornstraat",
    "iso:country":"BE",
    "sg:address":"Bornstraat 49",
    "sg:city":"Kortessem",
    "sg:orig_category":"Gespecialiseerde residenti\u00eble bouw Pleisterwerk Woningbouw",
    "sg:phone":"+32 11 37 52 23",
    "sg:postcode":"3721",
    "sg:province":"Limburg",
    "wof:name":"Noel Slegers",
    "wof:placetype":"venue"
},
  "geometry": {"coordinates":[5.4359650612,50.868938446],"type":"Point"}
}