{
  "type": "Feature",
  "properties": {
    "iso:country":"BE",
    "sg:address":"Pannewinning 46",
    "sg:city":"Heusden-zolder",
    "sg:orig_category":"Installation \u00e9lectrique industrielle",
    "sg:phone":"+32 11 87 24 79",
    "sg:postcode":"3550",
    "sg:province":"Limburg",
    "wof:name":"Alarm Vandael Security",
    "wof:placetype":"venue"
},
  "geometry": {"coordinates":[5.2737579346,50.9767112732],"type":"Point"}
}