{
  "type": "Feature",
  "properties": {
    "iso:country":"BE",
    "sg:address":"Centrum-zuid 2067",
    "sg:city":"Houthalen",
    "sg:classifiers":[
        {
            "category":"Military Area",
            "subcategory":"Air Force Base",
            "type":"Public Place"
        }
    ],
    "sg:phone":"+32 11 52 50 00",
    "sg:postcode":"3530",
    "sg:province":"Limburg",
    "sg:tags":[
        "prime",
        "contractor",
        "contractors"
    ],
    "wof:name":"Piet Luys & Partners Nv",
    "wof:placetype":"venue"
},
  "geometry": {"coordinates":[5.3623380661,51.0148010254],"type":"Point"}
}