{
  "type": "Feature",
  "properties": {
    "addr:full":"Rue De La Praule 22 La Bruy\u00e8re (meux) Namur 5081",
    "addr:housenumber":"22",
    "addr:postcode":"5081",
    "addr:street":"Rue De La Praule",
    "iso:country":"BE",
    "sg:address":"Rue De La Praule 22",
    "sg:city":"La Bruy\u00e8re (meux)",
    "sg:classifiers":[
        {
            "category":"Home & Garden",
            "subcategory":"Garden Supply",
            "type":"Retail Goods"
        }
    ],
    "sg:phone":"+32 81 56 83 59",
    "sg:postcode":"5081",
    "sg:province":"Namur",
    "sg:tags":[
        "lawn",
        "mower"
    ],
    "wof:name":"Hebert S",
    "wof:placetype":"venue"
},
  "geometry": {"coordinates":[4.7861208916,50.5521888733],"type":"Point"}
}