{
  "type": "Feature",
  "properties": {
    "iso:country":"BE",
    "sg:address":"Zone Industrielle De Noville Les Bois 10",
    "sg:city":"Fernelmont (noville-les-bois)",
    "sg:classifiers":[
        {
            "category":"Home & Garden",
            "subcategory":"Building Materials",
            "type":"Retail Goods"
        }
    ],
    "sg:phone":"+32 81 83 45 48",
    "sg:postcode":"5380",
    "sg:province":"Namur",
    "sg:tags":[
        "window"
    ],
    "wof:name":"Hicguet",
    "wof:placetype":"venue"
},
  "geometry": {"coordinates":[4.9694199562,50.5806312561],"type":"Point"}
}