{
  "type": "Feature",
  "properties": {
    "addr:full":"Deinsesteenweg 215 Kruishoutem Oost-Vlaanderen 9770",
    "addr:housenumber":"215",
    "addr:postcode":"9770",
    "addr:street":"Deinsesteenweg",
    "iso:country":"BE",
    "sg:address":"Deinsesteenweg 215",
    "sg:city":"Kruishoutem",
    "sg:orig_category":"Rundveehouders",
    "sg:phone":"+32 9 386 34 16",
    "sg:postcode":"9770",
    "sg:province":"Oost-Vlaanderen",
    "wof:name":"Etienne Rogge",
    "wof:placetype":"venue"
},
  "geometry": {"coordinates":[3.5386250019,50.9370613098],"type":"Point"}
}