{
  "type": "Feature",
  "properties": {
    "addr:full":"J.van Elewijckstraat 103b10 Grimbergen Vlaams-Brabant 1853",
    "addr:housenumber":"103b10",
    "addr:postcode":"1853",
    "addr:street":"J.Van Elewijckstraat",
    "iso:country":"BE",
    "sg:address":"J.van Elewijckstraat 103b10",
    "sg:city":"Grimbergen",
    "sg:orig_category":"Belastingconsulenten Diverse bedrijfsbeheeradviesbureaus Diverse juridische dienstverlening",
    "sg:phone":"+32 2 261 05 55",
    "sg:postcode":"1853",
    "sg:province":"Vlaams-Brabant",
    "wof:name":"W.p.&b. Btw Adviseurs",
    "wof:placetype":"venue"
},
  "geometry": {"coordinates":[4.3502588272,50.9028396606],"type":"Point"}
}