{
  "type": "Feature",
  "properties": {
    "iso:country":"BE",
    "sg:address":"Katelijnestr 17",
    "sg:city":"Linter",
    "sg:classifiers":[
        {
            "category":"Personal",
            "subcategory":"Beauty Salon",
            "type":"Services"
        }
    ],
    "sg:phone":"+32 16 78 88 86",
    "sg:postcode":"3350",
    "sg:province":"Vlaams-Brabant",
    "sg:tags":[
        "de",
        "coiffure"
    ],
    "wof:name":"Haarstudio Sandra",
    "wof:placetype":"venue"
},
  "geometry": {"coordinates":[5.0118288994,50.8137435913],"type":"Point"}
}