{
  "type": "Feature",
  "properties": {
    "iso:country":"BE",
    "sg:address":"Rue D'incourt 21",
    "sg:city":"Jodoigne",
    "sg:orig_category":"Charpentes and couvertures",
    "sg:phone":"+32 10 88 94 03",
    "sg:postcode":"1370",
    "sg:province":"Brabant Wallon",
    "wof:name":"Gressens Bernard",
    "wof:placetype":"venue"
},
  "geometry": {"coordinates":[4.8152298927,50.6958503723],"type":"Point"}
}