{
  "type": "Feature",
  "properties": {
    "addr:full":"Ruggestraat 44 Avelgem West-Vlaanderen 8580",
    "addr:housenumber":"44",
    "addr:postcode":"8580",
    "addr:street":"Ruggestraat",
    "iso:country":"BE",
    "sg:address":"Ruggestraat 44",
    "sg:city":"Avelgem",
    "sg:classifiers":[
        {
            "category":"Professional",
            "subcategory":"Art Services",
            "type":"Services"
        }
    ],
    "sg:phone":"+32 56 64 75 71",
    "sg:postcode":"8580",
    "sg:province":"West-Vlaanderen",
    "sg:tags":[
        "photographer"
    ],
    "wof:name":"Objectiv Foto",
    "wof:placetype":"venue"
},
  "geometry": {"coordinates":[3.4652678967,50.7794036865],"type":"Point"}
}