{
  "type": "Feature",
  "properties": {
    "addr:full":"Handelslei 250 Zoersel Antwerpen 2980",
    "addr:housenumber":"250",
    "addr:postcode":"2980",
    "iso:country":"BE",
    "sg:address":"Handelslei 250",
    "sg:city":"Zoersel",
    "sg:orig_category":"Pain, p\u00e2tisseries and confiseries",
    "sg:phone":"+32 3 383 64 60",
    "sg:postcode":"2980",
    "sg:province":"Antwerpen",
    "wof:name":"Bakkerij Bethani\u00cb",
    "wof:placetype":"venue"
},
  "geometry": {"coordinates":[4.6484851837,51.2733726501],"type":"Point"}
}