{
  "type": "Feature",
  "properties": {
    "addr:full":"Rue Du Haut-bois 35 Mons Hainaut 7000",
    "addr:housenumber":"35",
    "addr:postcode":"7000",
    "addr:street":"Rue Du Haut-Bois;Hainaut",
    "iso:country":"BE",
    "sg:address":"Rue Du Haut-bois 35",
    "sg:city":"Mons",
    "sg:orig_category":"Salles de spectacles",
    "sg:phone":"+32 65 31 70 97",
    "sg:postcode":"7000",
    "sg:province":"Hainaut",
    "wof:name":"Galerie Du Pistolet D\u00b4or",
    "wof:placetype":"venue"
},
  "geometry": {"coordinates":[3.9544448853,50.4530067444],"type":"Point"}
}