{
  "type": "Feature",
  "properties": {
    "addr:full":"Rijke Beukelaarstraat 8 Antwerpen Antwerpen 2000",
    "addr:housenumber":"8",
    "addr:postcode":"2000",
    "addr:street":"Rijke Beukelaarstraat",
    "iso:country":"BE",
    "sg:address":"Rijke Beukelaarstraat 8",
    "sg:city":"Antwerpen",
    "sg:orig_category":"Artistes ind\u00e9pendants",
    "sg:phone":"+32 3 233 22 62",
    "sg:postcode":"2000",
    "sg:province":"Antwerpen",
    "wof:name":"Atelier Maeckelbergh",
    "wof:placetype":"venue"
},
  "geometry": {"coordinates":[4.3966779709,51.2157211304],"type":"Point"}
}