{
  "type": "Feature",
  "properties": {
    "addr:full":"Ieperstraat 10-12 Nieuwpoort West-Vlaanderen 8620",
    "addr:housenumber":"10-12",
    "addr:postcode":"8620",
    "addr:street":"Ieperstraat",
    "iso:country":"BE",
    "sg:address":"Ieperstraat 10-12",
    "sg:city":"Nieuwpoort",
    "sg:classifiers":[
        {
            "category":"Shopping",
            "subcategory":"Florist",
            "type":"Retail Goods"
        }
    ],
    "sg:phone":"+32 58 23 35 83",
    "sg:postcode":"8620",
    "sg:province":"West-Vlaanderen",
    "wof:name":"Orchidee",
    "wof:placetype":"venue"
},
  "geometry": {"coordinates":[2.7549118996,51.1332473755],"type":"Point"}
}