{
  "type": "Feature",
  "properties": {
    "addr:full":"Steenweg Op Antwerpen 74 Turnhout Antwerpen 2300",
    "addr:housenumber":"74",
    "addr:postcode":"2300",
    "addr:street":"Steenweg Op Antwerpen",
    "iso:country":"BE",
    "sg:address":"Steenweg Op Antwerpen 74",
    "sg:city":"Turnhout",
    "sg:orig_category":"Drukkerijen and copyshops Fotogravure and zetwerk Secretariaatsdiensten",
    "sg:phone":"+32 14 43 53 28",
    "sg:postcode":"2300",
    "sg:province":"Antwerpen",
    "wof:name":"W.v.m. Belgium",
    "wof:placetype":"venue"
},
  "geometry": {"coordinates":[4.920841217,51.3194770813],"type":"Point"}
}