{
  "type": "Feature",
  "properties": {
    "iso:country":"BE",
    "sg:address":"Generaal Jacqueslaan 2b3e",
    "sg:city":"Elsene/ixelles",
    "sg:orig_category":"Architecten",
    "sg:phone":"+32 2 646 73 25",
    "sg:postcode":"1050",
    "sg:province":"Bruxelles-Capitale",
    "wof:name":"Philippe Leblanc",
    "wof:placetype":"venue"
},
  "geometry": {"coordinates":[4.3780198097,50.8166885376],"type":"Point"}
}