{
  "type": "Feature",
  "properties": {
    "iso:country":"BE",
    "sg:address":"Rue L\u00e9on Fr\u00e9d\u00e9ricq 28",
    "sg:city":"Li\u00e8ge 1 (li\u00e8ge 2)",
    "sg:classifiers":[
        {
            "category":"Social Services",
            "type":"Services"
        }
    ],
    "sg:phone":"+32 4 341 20 58",
    "sg:postcode":"4020",
    "sg:province":"Li\u00e8ge",
    "wof:name":"Sauvegarde Familiale (la)",
    "wof:placetype":"venue"
},
  "geometry": {"coordinates":[5.5756378174,50.6338233948],"type":"Point"}
}