{
  "type": "Feature",
  "properties": {
    "iso:country":"BE",
    "sg:address":"Rue De Tournai 45ba",
    "sg:city":"Peruwelz",
    "sg:orig_category":"Enseignement maternel and primaire",
    "sg:phone":"+32 69 78 00 90",
    "sg:postcode":"7604",
    "sg:province":"Hainaut",
    "wof:name":"Ecole Fondamentale Libre",
    "wof:placetype":"venue"
},
  "geometry": {"coordinates":[3.5243198872,50.5309829712],"type":"Point"}
}