{
  "type": "Feature",
  "properties": {
    "iso:country":"BE",
    "sg:address":"Rue Dolimont 18a",
    "sg:city":"Wavre (bierges)",
    "sg:classifiers":[
        {
            "category":"Professional",
            "subcategory":"Accounting & Tax Preparation",
            "type":"Services"
        }
    ],
    "sg:phone":"+32 2 652 31 27",
    "sg:postcode":"1301",
    "sg:province":"Brabant Wallon",
    "sg:tags":[
        "accountant"
    ],
    "wof:name":"Collin A",
    "wof:placetype":"venue"
},
  "geometry": {"coordinates":[4.5611371994,50.7324256897],"type":"Point"}
}