{
  "type": "Feature",
  "properties": {
    "addr:full":"Prins Albertstraat 9 Sint-niklaas Oost-Vlaanderen 9100",
    "addr:housenumber":"9",
    "addr:postcode":"9100",
    "addr:street":"Prins Albertstraat",
    "iso:country":"BE",
    "sg:address":"Prins Albertstraat 9",
    "sg:city":"Sint-niklaas",
    "sg:orig_category":"Centres de relaxation and bien-\u00eatre. Instituts de beaut\u00e9",
    "sg:phone":"+32 3 766 62 25",
    "sg:postcode":"9100",
    "sg:province":"Oost-Vlaanderen",
    "wof:name":"Schoonheidsinstituut Isabelle",
    "wof:placetype":"venue"
},
  "geometry": {"coordinates":[4.1431250572,51.1700553894],"type":"Point"}
}