{
  "type": "Feature",
  "properties": {
    "addr:full":"La Houssi\u00e8re 16 Frasnes-lez-anvaing (frasnes - Lez - Buissenal) Hainaut 7911",
    "addr:housenumber":"16",
    "addr:postcode":"7911",
    "addr:street":"Houssie\u0300Re",
    "iso:country":"BE",
    "sg:address":"La Houssi\u00e8re 16",
    "sg:city":"Frasnes-lez-anvaing (frasnes - Lez - Buissenal)",
    "sg:classifiers":[
        {
            "category":"Insurance",
            "subcategory":"Insurance Agent",
            "type":"Services"
        }
    ],
    "sg:phone":"+32 69 86 66 49",
    "sg:postcode":"7911",
    "sg:province":"Hainaut",
    "sg:tags":[
        "broker"
    ],
    "wof:name":"Socha C",
    "wof:placetype":"venue"
},
  "geometry": {"coordinates":[3.6661009789,50.7010307312],"type":"Point"}
}