{
  "type": "Feature",
  "properties": {
    "iso:country":"BE",
    "sg:address":"Groteheidestraat 75",
    "sg:city":"Beveren",
    "sg:orig_category":"Jardinage",
    "sg:phone":"+32 3 755 40 66",
    "sg:postcode":"9120",
    "sg:province":"Oost-Vlaanderen",
    "wof:name":"Bruno De Wilde",
    "wof:placetype":"venue"
},
  "geometry": {"coordinates":[4.2239980698,51.2032623291],"type":"Point"}
}