{
  "type": "Feature",
  "properties": {
    "addr:full":"Leffingestraat 56 Oostende West-Vlaanderen 8400",
    "addr:housenumber":"56",
    "addr:postcode":"8400",
    "addr:street":"Leffingestraat",
    "iso:country":"BE",
    "sg:address":"Leffingestraat 56",
    "sg:city":"Oostende",
    "sg:orig_category":"Caf\u00e9, th\u00e9, cacao and \u00e9pices Produits surgel\u00e9s Fruits and l\u00e9gumes Gr",
    "sg:phone":"+32 59 70 41 95",
    "sg:postcode":"8400",
    "sg:province":"West-Vlaanderen",
    "wof:name":"Ir. Quality Food",
    "wof:placetype":"venue"
},
  "geometry": {"coordinates":[2.9135580063,51.2203330994],"type":"Point"}
}