{
  "type": "Feature",
  "properties": {
    "iso:country":"BE",
    "sg:address":"Gestelsesteenweg 108",
    "sg:city":"Meerhout",
    "sg:classifiers":[
        {
            "category":"Health Services",
            "subcategory":"Health Practitioner",
            "type":"Services"
        }
    ],
    "sg:phone":"+32 14 30 16 80",
    "sg:postcode":"2450",
    "sg:province":"Antwerpen",
    "sg:tags":[
        "physiotherapist"
    ],
    "wof:name":"Huysmans Wim",
    "wof:placetype":"venue"
},
  "geometry": {"coordinates":[5.0917100906,51.1197013855],"type":"Point"}
}