{
  "type": "Feature",
  "properties": {
    "addr:full":"Heide Statiestraat 10 Kalmthout Antwerpen 2920",
    "addr:housenumber":"10",
    "addr:postcode":"2920",
    "addr:street":"Statiestraat",
    "iso:country":"BE",
    "sg:address":"Heide Statiestraat 10",
    "sg:city":"Kalmthout",
    "sg:orig_category":"Ordinateurs and \u00e9quipement informatique. Entretien and r\u00e9parations de machines de bureau and ordinat",
    "sg:phone":"+32 3 666 10 91",
    "sg:postcode":"2920",
    "sg:province":"Antwerpen",
    "wof:name":"C- World Computers",
    "wof:placetype":"venue"
},
  "geometry": {"coordinates":[4.4734959602,51.3939437866],"type":"Point"}
}