{
  "type": "Feature",
  "properties": {
    "addr:full":"Spijker 15 Essen Antwerpen 2910",
    "addr:housenumber":"15",
    "addr:postcode":"2910",
    "addr:street":"Spijker",
    "iso:country":"BE",
    "sg:address":"Spijker 15",
    "sg:city":"Essen",
    "sg:orig_category":"Reclamebureaus",
    "sg:phone":"+32 3 677 22 98",
    "sg:postcode":"2910",
    "sg:province":"Antwerpen",
    "wof:name":"Bureau Audax",
    "wof:placetype":"venue"
},
  "geometry": {"coordinates":[4.4749650955,51.4561729431],"type":"Point"}
}