{
  "type": "Feature",
  "properties": {
    "addr:full":"Zeedijk Wenduine 34 De Haan West-Vlaanderen 8420",
    "addr:housenumber":"34",
    "addr:postcode":"8420",
    "addr:street":"Zeedijk Wenduine",
    "iso:country":"BE",
    "sg:address":"Zeedijk Wenduine 34",
    "sg:city":"De Haan",
    "sg:classifiers":[
        {
            "category":"Restaurant",
            "type":"Food & Drink"
        }
    ],
    "sg:phone":"+32 50 42 59 07",
    "sg:postcode":"8420",
    "sg:province":"West-Vlaanderen",
    "wof:name":"Restaurant Zeerust",
    "wof:placetype":"venue"
},
  "geometry": {"coordinates":[3.0809929371,51.3022117615],"type":"Point"}
}