{
  "type": "Feature",
  "properties": {
    "addr:full":"Rue Du Chevalier 33 Juprelle Li\u00e8ge 4458",
    "addr:housenumber":"33",
    "addr:postcode":"4458",
    "addr:street":"Rue Du Chevalier",
    "iso:country":"BE",
    "sg:address":"Rue Du Chevalier 33",
    "sg:city":"Juprelle",
    "sg:classifiers":[
        {
            "category":"Arena",
            "subcategory":"Sports Club",
            "type":"Entertainment"
        }
    ],
    "sg:phone":"+32 4 278 17 24",
    "sg:postcode":"4458",
    "sg:province":"Li\u00e8ge",
    "sg:tags":[
        "de"
    ],
    "wof:name":"J.c. Vall\u00c9e Du Geer",
    "wof:placetype":"venue"
},
  "geometry": {"coordinates":[5.569712162,50.7215194702],"type":"Point"}
}