{
  "type": "Feature",
  "properties": {
    "addr:full":"Hertstraat 100 Denderleeuw Oost-Vlaanderen 9473",
    "addr:housenumber":"100",
    "addr:postcode":"9473",
    "addr:street":"Hertstraat",
    "iso:country":"BE",
    "sg:address":"Hertstraat 100",
    "sg:city":"Denderleeuw",
    "sg:classifiers":[
        {
            "category":"Wholesale",
            "subcategory":"Vending Machines",
            "type":"Manufacturing & Wholesale Goods"
        }
    ],
    "sg:phone":"+32 53 64 73 73",
    "sg:postcode":"9473",
    "sg:province":"Oost-Vlaanderen",
    "sg:tags":[
        "mat\u00e9riel",
        "de",
        "bureau",
        "gr",
        "fournitures"
    ],
    "wof:name":"Goossens",
    "wof:placetype":"venue"
},
  "geometry": {"coordinates":[4.052795887,50.9047622681],"type":"Point"}
}