{
  "type": "Feature",
  "properties": {
    "addr:full":"Larumseweg 8 Olen Antwerpen 2250",
    "addr:housenumber":"8",
    "addr:postcode":"2250",
    "addr:street":"Larumseweg",
    "iso:country":"BE",
    "sg:address":"Larumseweg 8",
    "sg:city":"Olen",
    "sg:classifiers":[
        {
            "category":"Fast Food",
            "type":"Food & Drink"
        }
    ],
    "sg:phone":"+32 14 22 61 99",
    "sg:postcode":"2250",
    "sg:province":"Antwerpen",
    "sg:tags":[
        "meeneem",
        "restaurant"
    ],
    "wof:name":"China House",
    "wof:placetype":"venue"
},
  "geometry": {"coordinates":[4.9106898308,51.1668891907],"type":"Point"}
}