{
  "type": "Feature",
  "properties": {
    "addr:full":"Rue De L'h\u00f4tel Des Monnaies 124a Bruxelles (saint-gilles) Bruxelles-Capitale 1060",
    "addr:housenumber":"124a",
    "addr:postcode":"1060",
    "addr:street":"Rue De L'Ho;Des Monnaies",
    "iso:country":"BE",
    "sg:address":"Rue De L'h\u00f4tel Des Monnaies 124a",
    "sg:city":"Bruxelles (saint-gilles)",
    "sg:classifiers":[
        {
            "category":"Building & Trades",
            "subcategory":"Construction",
            "type":"Services"
        }
    ],
    "sg:phone":"+32 2 332 07 21",
    "sg:postcode":"1060",
    "sg:province":"Bruxelles-Capitale",
    "sg:tags":[
        "ceiling"
    ],
    "wof:name":"Batijotex Sprl",
    "wof:placetype":"venue"
},
  "geometry": {"coordinates":[4.3469438553,50.829246521],"type":"Point"}
}