{
  "type": "Feature",
  "properties": {
    "addr:full":"Boulevard De L'empereur 15 Bruxelles Bruxelles-Capitale 1000",
    "addr:housenumber":"15",
    "addr:postcode":"1000",
    "addr:street":"Boulevard De L'Empereur",
    "iso:country":"BE",
    "sg:address":"Boulevard De L'empereur 15",
    "sg:city":"Bruxelles",
    "sg:classifiers":[
        {
            "category":"Professional",
            "subcategory":"Research",
            "type":"Services"
        }
    ],
    "sg:phone":"+32 2 514 44 41",
    "sg:postcode":"1000",
    "sg:province":"Bruxelles-Capitale",
    "sg:tags":[
        "actuary"
    ],
    "wof:name":"Jwa Actuaires International Sa",
    "wof:placetype":"venue"
},
  "geometry": {"coordinates":[4.3518710136,50.8426551819],"type":"Point"}
}