{
  "type": "Feature",
  "properties": {
    "addr:full":"Offendonkstraat 9 Sint-katelijne-waver Antwerpen 2860",
    "addr:housenumber":"9",
    "addr:postcode":"2860",
    "addr:street":"Offendonkstraat",
    "iso:country":"BE",
    "sg:address":"Offendonkstraat 9",
    "sg:city":"Sint-katelijne-waver",
    "sg:orig_category":"Plomberie, chauffage and installations sanitaires",
    "sg:phone":"+32 15 31 75 92",
    "sg:postcode":"2860",
    "sg:province":"Antwerpen",
    "wof:name":"Paul Van Lany",
    "wof:placetype":"venue"
},
  "geometry": {"coordinates":[4.5329818726,51.073589325],"type":"Point"}
}