{
  "type": "Feature",
  "properties": {
    "iso:country":"BE",
    "sg:address":"Lakstraat 3",
    "sg:city":"Laakdal (veerle)",
    "sg:classifiers":[
        {
            "category":"Health Services",
            "subcategory":"Health Practitioner",
            "type":"Services"
        }
    ],
    "sg:phone":"+32 14 84 13 35",
    "sg:postcode":"2431",
    "sg:province":"Antwerpen",
    "sg:tags":[
        "physiotherapist"
    ],
    "wof:name":"Mellebeek Jos",
    "wof:placetype":"venue"
},
  "geometry": {"coordinates":[4.9824080467,51.0658721924],"type":"Point"}
}