{
  "type": "Feature",
  "properties": {
    "addr:full":"Rue Des 2 Auvelais 13 Sambreville Namur 5060",
    "addr:housenumber":"13",
    "addr:postcode":"5060",
    "addr:street":"Rue Des 2 Auvelais",
    "iso:country":"BE",
    "sg:address":"Rue Des 2 Auvelais 13",
    "sg:city":"Sambreville",
    "sg:orig_category":"Dameskledingzaken Herenkledingzaken Kleding",
    "sg:phone":"+32 71 77 71 51",
    "sg:postcode":"5060",
    "sg:province":"Namur",
    "wof:name":"New Look",
    "wof:placetype":"venue"
},
  "geometry": {"coordinates":[4.63357687,50.4474830627],"type":"Point"}
}