{
  "type": "Feature",
  "properties": {
    "iso:country":"BE",
    "sg:address":"Liersesteenweg 203",
    "sg:city":"Mortsel",
    "sg:classifiers":[
        {
            "category":"Social Services",
            "subcategory":"Child Care",
            "type":"Services"
        }
    ],
    "sg:phone":"+32 3 455 34 93",
    "sg:postcode":"2640",
    "sg:province":"Antwerpen",
    "sg:tags":[
        "baby",
        "nursery",
        "day",
        "sitting"
    ],
    "wof:name":"Bibiche",
    "wof:placetype":"venue"
},
  "geometry": {"coordinates":[4.4703550339,51.1689376831],"type":"Point"}
}