{
  "type": "Feature",
  "properties": {
    "iso:country":"BE",
    "sg:address":"Ter Lindenstraat 11",
    "sg:city":"Waregem (desselgem)",
    "sg:orig_category":"Non-Classified Establishments",
    "sg:phone":"+32 56 71 23 83",
    "sg:postcode":"8792",
    "sg:province":"West-Vlaanderen",
    "wof:name":"Pauwels-lucien",
    "wof:placetype":"venue"
},
  "geometry": {"coordinates":[3.3546700478,50.8900489807],"type":"Point"}
}