{
  "type": "Feature",
  "properties": {
    "iso:country":"BE",
    "sg:address":"Vaartstraat 12",
    "sg:city":"Veurne",
    "sg:classifiers":[
        {
            "category":"Sports & Exercise",
            "subcategory":"Sports Center",
            "type":"Entertainment"
        }
    ],
    "sg:phone":"+32 58 31 33 05",
    "sg:postcode":"8630",
    "sg:province":"West-Vlaanderen",
    "sg:tags":[
        "de",
        "fitness"
    ],
    "wof:name":"Cristifa",
    "wof:placetype":"venue"
},
  "geometry": {"coordinates":[2.6691260338,51.0708045959],"type":"Point"}
}