{
  "type": "Feature",
  "properties": {
    "iso:country":"BE",
    "sg:address":"Battenbroek 10",
    "sg:city":"Mechelen (walem)",
    "sg:classifiers":[
        {
            "category":"Manufacturing",
            "subcategory":"Aerospace",
            "type":"Manufacturing & Wholesale Goods"
        }
    ],
    "sg:phone":"+32 15 28 91 81",
    "sg:postcode":"2800",
    "sg:province":"Antwerpen",
    "sg:tags":[
        "equipment",
        "airplane"
    ],
    "wof:name":"Air Technology Belgium",
    "wof:placetype":"venue"
},
  "geometry": {"coordinates":[4.4854397774,51.0289268494],"type":"Point"}
}