{
  "type": "Feature",
  "properties": {
    "addr:full":"Morkhovenseweg 149 Herentals (noorderwijk) Antwerpen 2200",
    "addr:housenumber":"149",
    "addr:postcode":"2200",
    "addr:street":"Morkhovenseweg",
    "iso:country":"BE",
    "sg:address":"Morkhovenseweg 149",
    "sg:city":"Herentals (noorderwijk)",
    "sg:classifiers":[
        {
            "category":"Transit Center",
            "subcategory":"Freight",
            "type":"Transportation"
        }
    ],
    "sg:phone":"+32 14 27 99 60",
    "sg:postcode":"2200",
    "sg:province":"Antwerpen",
    "sg:tags":[
        "import",
        "export",
        "-"
    ],
    "wof:name":"Metro Impex Belgium",
    "wof:placetype":"venue"
},
  "geometry": {"coordinates":[4.8257899284,51.1239204407],"type":"Point"}
}