{
  "type": "Feature",
  "properties": {
    "addr:full":"Rue Victor Greyson 1 Bruxelles (ixelles) Bruxelles-Capitale 1050",
    "addr:housenumber":"1",
    "addr:postcode":"1050",
    "addr:street":"Rue Victor Greyson",
    "iso:country":"BE",
    "sg:address":"Rue Victor Greyson 1",
    "sg:city":"Bruxelles (ixelles)",
    "sg:classifiers":[
        {
            "category":"Personal",
            "subcategory":"Shoe Repair & Shine",
            "type":"Services"
        }
    ],
    "sg:phone":"+32 2 648 22 89",
    "sg:postcode":"1050",
    "sg:province":"Bruxelles-Capitale",
    "sg:tags":[
        "shoemaker"
    ],
    "wof:name":"Etangs (cordonnerie Des)",
    "wof:placetype":"venue"
},
  "geometry": {"coordinates":[4.3766651154,50.8233184814],"type":"Point"}
}