{
  "type": "Feature",
  "properties": {
    "addr:full":"Rue Garde-dieu 25 Li\u00c8ge Li\u00e8ge 4031",
    "addr:housenumber":"25",
    "addr:postcode":"4031",
    "addr:street":"Rue Garde-Dieu",
    "iso:country":"BE",
    "sg:address":"Rue Garde-dieu 25",
    "sg:city":"Li\u00c8ge",
    "sg:orig_category":"Biens d'occasion. V\u00eatements",
    "sg:phone":"+32 4 344 35 28",
    "sg:postcode":"4031",
    "sg:province":"Li\u00e8ge",
    "wof:name":"Le Service D'or",
    "wof:placetype":"venue"
},
  "geometry": {"coordinates":[5.5846300125,50.6190643311],"type":"Point"}
}