{
  "type": "Feature",
  "properties": {
    "iso:country":"BE",
    "sg:address":"Botermarkt 25",
    "sg:city":"Hasselt",
    "sg:classifiers":[
        {
            "category":"Restaurant",
            "type":"Food & Drink"
        }
    ],
    "sg:phone":"+32 11 22 02 97",
    "sg:postcode":"3500",
    "sg:province":"Limburg",
    "wof:name":"Visionair - Bar A Manger",
    "wof:placetype":"venue"
},
  "geometry": {"coordinates":[5.3392148018,50.9303321838],"type":"Point"}
}