{
  "type": "Feature",
  "properties": {
    "iso:country":"BE",
    "sg:address":"Rotselaarsebaan 12",
    "sg:city":"Holsbeek",
    "sg:classifiers":[
        {
            "category":"Real Estate",
            "subcategory":"Architect",
            "type":"Services"
        }
    ],
    "sg:phone":"+32 16 44 67 47",
    "sg:postcode":"3220",
    "sg:province":"Vlaams-Brabant",
    "wof:name":"Boonen E",
    "wof:placetype":"venue"
},
  "geometry": {"coordinates":[4.755355835,50.922252655],"type":"Point"}
}