{
  "type": "Feature",
  "properties": {
    "addr:full":"Rue Saint-pierre 31 Huy Li\u00e8ge 4500",
    "addr:housenumber":"31",
    "addr:postcode":"4500",
    "addr:street":"Rue Saint-Pierre",
    "iso:country":"BE",
    "sg:address":"Rue Saint-pierre 31",
    "sg:city":"Huy",
    "sg:orig_category":"Apotheken",
    "sg:phone":"+32 85 21 14 38",
    "sg:postcode":"4500",
    "sg:province":"Li\u00e8ge",
    "wof:name":"P. Cornil",
    "wof:placetype":"venue"
},
  "geometry": {"coordinates":[5.2351608276,50.5222702026],"type":"Point"}
}