{
  "type": "Feature",
  "properties": {
    "addr:full":"Rue Des D\u00c9port\u00c9s 19 Bastogne Luxembourg 6600",
    "addr:housenumber":"19",
    "addr:postcode":"6600",
    "addr:street":"Rue Des De\u0301Porte\u0301S",
    "iso:country":"BE",
    "sg:address":"Rue Des D\u00c9port\u00c9s 19",
    "sg:city":"Bastogne",
    "sg:orig_category":"S\u00e9curit\u00e9 sociale",
    "sg:phone":"+32 61 21 38 34",
    "sg:postcode":"6600",
    "sg:province":"Luxembourg",
    "wof:name":"Mutualit\u00c9 Neutre",
    "wof:placetype":"venue"
},
  "geometry": {"coordinates":[5.7230172157,50.0087203979],"type":"Point"}
}