{
  "type": "Feature",
  "properties": {
    "addr:full":"Rue Alfred Henno 54 Mouscron Hainaut 7700",
    "addr:housenumber":"54",
    "addr:postcode":"7700",
    "addr:street":"Rue Alfred Henno",
    "iso:country":"BE",
    "sg:address":"Rue Alfred Henno 54",
    "sg:city":"Mouscron",
    "sg:classifiers":[
        {
            "category":"Health Services",
            "subcategory":"Dentist",
            "type":"Services"
        }
    ],
    "sg:phone":"+32 56 34 38 10",
    "sg:postcode":"7700",
    "sg:province":"Hainaut",
    "wof:name":"Collette S",
    "wof:placetype":"venue"
},
  "geometry": {"coordinates":[3.1983139515,50.7445297241],"type":"Point"}
}