{
  "type": "Feature",
  "properties": {
    "iso:country":"BE",
    "sg:address":"Diesterstraat 23b011",
    "sg:city":"Sint-truiden",
    "sg:orig_category":"Kansspelen",
    "sg:phone":"+32 11 68 86 29",
    "sg:postcode":"3800",
    "sg:province":"Limburg",
    "wof:name":"Pmu",
    "wof:placetype":"venue"
},
  "geometry": {"coordinates":[5.1855249405,50.8174476624],"type":"Point"}
}