{
  "type": "Feature",
  "properties": {
    "iso:country":"BE",
    "sg:address":"Ommegangstraat 12-14",
    "sg:city":"Izegem",
    "sg:classifiers":[
        {
            "category":"Shopping",
            "subcategory":"Baby Store",
            "type":"Retail Goods"
        }
    ],
    "sg:phone":"+32 51 30 28 18",
    "sg:postcode":"8870",
    "sg:province":"West-Vlaanderen",
    "sg:tags":[
        "-",
        "accessory"
    ],
    "wof:name":"Bambino",
    "wof:placetype":"venue"
},
  "geometry": {"coordinates":[3.209651947,50.9186553955],"type":"Point"}
}