{
  "type": "Feature",
  "properties": {
    "addr:full":"Stationsstr 4 Eeklo Oost-Vlaanderen 9900",
    "addr:housenumber":"4",
    "addr:postcode":"9900",
    "addr:street":"Stationsstr",
    "iso:country":"BE",
    "sg:address":"Stationsstr 4",
    "sg:city":"Eeklo",
    "sg:classifiers":[
        {
            "category":"Banks & Credit Unions",
            "subcategory":"Bank",
            "type":"Services"
        }
    ],
    "sg:phone":"+32 69 77 74 74",
    "sg:postcode":"9900",
    "sg:province":"Oost-Vlaanderen",
    "wof:name":"G\u00e9n\u00e9rale De Banque Sa",
    "wof:placetype":"venue"
},
  "geometry": {"coordinates":[3.5732970238,51.1816558838],"type":"Point"}
}