{
  "type": "Feature",
  "properties": {
    "iso:country":"BE",
    "sg:address":"Rue De Vis\u00c9 154",
    "sg:city":"Vise",
    "sg:orig_category":"Herstellingen and onderhoud van auto's",
    "sg:phone":"+32 4 362 63 01",
    "sg:postcode":"4602",
    "sg:province":"Li\u00e8ge",
    "wof:name":"Carrosserie Poes",
    "wof:placetype":"venue"
},
  "geometry": {"coordinates":[5.6712708473,50.6843528748],"type":"Point"}
}