{
  "type": "Feature",
  "properties": {
    "addr:full":"Avenue Moli\u00c8re 464 Bruxelles Bruxelles-Capitale 1050",
    "addr:housenumber":"464",
    "addr:postcode":"1050",
    "addr:street":"Avenue Molie\u0300Re",
    "iso:country":"BE",
    "sg:address":"Avenue Moli\u00c8re 464",
    "sg:city":"Bruxelles",
    "sg:orig_category":"Ambassades and consulats",
    "sg:phone":"+32 2 345 26 60",
    "sg:postcode":"1050",
    "sg:province":"Bruxelles-Capitale",
    "wof:name":"Ambassade Et Consulat D\u00b4azerba\u00cfdjan",
    "wof:placetype":"venue"
},
  "geometry": {"coordinates":[4.3633799553,50.8163070679],"type":"Point"}
}