{
  "type": "Feature",
  "properties": {
    "addr:full":"Alfons Biebuycklaan 17 Gent (gentbrugge) Oost-Vlaanderen 9050",
    "addr:housenumber":"17",
    "addr:postcode":"9050",
    "addr:street":"Alfons Biebuycklaan",
    "iso:country":"BE",
    "sg:address":"Alfons Biebuycklaan 17",
    "sg:city":"Gent (gentbrugge)",
    "sg:classifiers":[
        {
            "category":"Health Services",
            "subcategory":"Doctor",
            "type":"Services"
        }
    ],
    "sg:phone":"+32 9 230 67 87",
    "sg:postcode":"9050",
    "sg:province":"Oost-Vlaanderen",
    "sg:tags":[
        "medicinephysicians",
        "surgeon"
    ],
    "wof:name":"De Langhe H",
    "wof:placetype":"venue"
},
  "geometry": {"coordinates":[3.7597210407,51.0289993286],"type":"Point"}
}