{
  "type": "Feature",
  "properties": {
    "addr:full":"Turnhoutsebaan 5b78 Wijnegem Antwerpen 2110",
    "addr:housenumber":"5b78",
    "addr:postcode":"2110",
    "addr:street":"Turnhoutsebaan",
    "iso:country":"BE",
    "sg:address":"Turnhoutsebaan 5b78",
    "sg:city":"Wijnegem",
    "sg:classifiers":[
        {
            "category":"Restaurant",
            "type":"Food & Drink"
        }
    ],
    "sg:phone":"+32 3 353 76 77",
    "sg:postcode":"2110",
    "sg:province":"Antwerpen",
    "wof:name":"Ijssalon Johen Truz",
    "wof:placetype":"venue"
},
  "geometry": {"coordinates":[4.5043401718,51.2240219116],"type":"Point"}
}