{
  "type": "Feature",
  "properties": {
    "iso:country":"BE",
    "sg:address":"Rue Joseph Wauters 8",
    "sg:city":"Villers-le-bouillet (warnant-dreye)",
    "sg:classifiers":[
        {
            "category":"Bars & Pubs",
            "type":"Food & Drink"
        }
    ],
    "sg:phone":"+32 19 58 79 50",
    "sg:postcode":"4530",
    "sg:province":"Li\u00e8ge",
    "wof:name":"D'jin's (le)",
    "wof:placetype":"venue"
},
  "geometry": {"coordinates":[5.2279381752,50.5944633484],"type":"Point"}
}