{
  "type": "Feature",
  "properties": {
    "addr:full":"Biezenstraat 1 Evergem Oost-Vlaanderen 9940",
    "addr:housenumber":"1",
    "addr:postcode":"9940",
    "addr:street":"Biezenstraat;Oost-Vlaanderen",
    "iso:country":"BE",
    "sg:address":"Biezenstraat 1",
    "sg:city":"Evergem",
    "sg:orig_category":"Herstellingen and onderhoud van auto's Verhuur voertuigen behalve auto's",
    "sg:phone":"+32 9 357 58 16",
    "sg:postcode":"9940",
    "sg:province":"Oost-Vlaanderen",
    "wof:name":"De Caluw\u00c9 Gebrs",
    "wof:placetype":"venue"
},
  "geometry": {"coordinates":[3.6657259464,51.1113510132],"type":"Point"}
}