{
  "type": "Feature",
  "properties": {
    "addr:full":"Saghermansstraat 1 Gent Oost-Vlaanderen 9000",
    "addr:housenumber":"1",
    "addr:postcode":"9000",
    "addr:street":"Saghermansstraat;Oost-Vlaanderen",
    "iso:country":"BE",
    "sg:address":"Saghermansstraat 1",
    "sg:city":"Gent",
    "sg:orig_category":"Advocaten and juridische adviseurs",
    "sg:phone":"+32 9 224 33 38",
    "sg:postcode":"9000",
    "sg:province":"Oost-Vlaanderen",
    "wof:name":"Stephanie De Witte",
    "wof:placetype":"venue"
},
  "geometry": {"coordinates":[3.7266249657,51.0502357483],"type":"Point"}
}