{
  "type": "Feature",
  "properties": {
    "iso:country":"BE",
    "sg:address":"Industrielaan 33",
    "sg:city":"Olen",
    "sg:orig_category":"Installatie van houten of kunststof schrijnwerk",
    "sg:phone":"+32 14 24 87 10",
    "sg:postcode":"2250",
    "sg:province":"Antwerpen",
    "wof:name":"Campforts Schrijnwerkerij",
    "wof:placetype":"venue"
},
  "geometry": {"coordinates":[4.8845381737,51.1461639404],"type":"Point"}
}