{
  "type": "Feature",
  "properties": {
    "iso:country":"BE",
    "sg:address":"Aachener Strasse 295",
    "sg:city":"Eupen",
    "sg:orig_category":"Onderdelen and accessoires voor auto's",
    "sg:phone":"+32 87 56 15 56",
    "sg:postcode":"4701",
    "sg:province":"Li\u00e8ge",
    "wof:name":"Reifen Express Belux",
    "wof:placetype":"venue"
},
  "geometry": {"coordinates":[6.0412201881,50.6376190186],"type":"Point"}
}