{
  "type": "Feature",
  "properties": {
    "addr:full":"Venlosesteenweg 128 Kinrooi Limburg 3640",
    "addr:housenumber":"128",
    "addr:postcode":"3640",
    "addr:street":"Venlosesteenweg",
    "iso:country":"BE",
    "sg:address":"Venlosesteenweg 128",
    "sg:city":"Kinrooi",
    "sg:orig_category":"Bloemen and planten Geschenken and souvenirs Huisdieren and benodigdheden Tuinbenodigdheden",
    "sg:phone":"+32 89 56 60 40",
    "sg:postcode":"3640",
    "sg:province":"Limburg",
    "wof:name":"Tuincentrum Silkens",
    "wof:placetype":"venue"
},
  "geometry": {"coordinates":[5.8034892082,51.1293869019],"type":"Point"}
}