{
  "type": "Feature",
  "properties": {
    "addr:full":"Rue Cujenne 19 Beyne-heusay Li\u00e8ge 4610",
    "addr:housenumber":"19",
    "addr:postcode":"4610",
    "addr:street":"Rue Cujenne",
    "iso:country":"BE",
    "sg:address":"Rue Cujenne 19",
    "sg:city":"Beyne-heusay",
    "sg:orig_category":"Schoonheidssalons",
    "sg:phone":"+32 4 362 43 80",
    "sg:postcode":"4610",
    "sg:province":"Li\u00e8ge",
    "wof:name":"P\u00c9dicure Marie-rose",
    "wof:placetype":"venue"
},
  "geometry": {"coordinates":[5.6644849777,50.6422157288],"type":"Point"}
}