{
  "type": "Feature",
  "properties": {
    "addr:full":"Wallemolenstraat 12 Langemark-poelkapelle (poelkapelle) West-Vlaanderen 8920",
    "addr:housenumber":"12",
    "addr:postcode":"8920",
    "addr:street":"Wallemolenstraat",
    "iso:country":"BE",
    "sg:address":"Wallemolenstraat 12",
    "sg:city":"Langemark-poelkapelle (poelkapelle)",
    "sg:classifiers":[
        {
            "category":"Health Services",
            "subcategory":"Health Practitioner",
            "type":"Services"
        }
    ],
    "sg:phone":"+32 57 48 60 93",
    "sg:postcode":"8920",
    "sg:province":"West-Vlaanderen",
    "sg:tags":[
        "physiotherapist"
    ],
    "wof:name":"Olivier M",
    "wof:placetype":"venue"
},
  "geometry": {"coordinates":[2.919770956,50.9132423401],"type":"Point"}
}