{
  "type": "Feature",
  "properties": {
    "iso:country":"BE",
    "sg:address":"Kortrijksesteenweg 470",
    "sg:city":"Gent",
    "sg:orig_category":"Immobili\u00ebnkantoren",
    "sg:phone":"+32 9 222 90 90",
    "sg:postcode":"9000",
    "sg:province":"Oost-Vlaanderen",
    "wof:name":"Era Vastgoed Verheire",
    "wof:placetype":"venue"
},
  "geometry": {"coordinates":[3.7164969444,51.0362052917],"type":"Point"}
}