{
  "type": "Feature",
  "properties": {
    "addr:full":"Vanderstichelenstraat 34 Blankenberge West-Vlaanderen 8370",
    "addr:housenumber":"34",
    "addr:postcode":"8370",
    "addr:street":"Vanderstichelenstraat",
    "iso:country":"BE",
    "sg:address":"Vanderstichelenstraat 34",
    "sg:city":"Blankenberge",
    "sg:classifiers":[
        {
            "category":"Bakery",
            "type":"Food & Drink"
        }
    ],
    "sg:phone":"+32 50 41 24 48",
    "sg:postcode":"8370",
    "sg:province":"West-Vlaanderen",
    "sg:tags":[
        "confectioner",
        "baker"
    ],
    "wof:name":"Ketelers",
    "wof:placetype":"venue"
},
  "geometry": {"coordinates":[3.1242890358,51.3147201538],"type":"Point"}
}