{
  "type": "Feature",
  "properties": {
    "addr:full":"Chauss\u00c9e De Dinant 652 Namur Namur 5100",
    "addr:housenumber":"652",
    "addr:postcode":"5100",
    "addr:street":"Chausse\u0301E De Dinant",
    "iso:country":"BE",
    "sg:address":"Chauss\u00c9e De Dinant 652",
    "sg:city":"Namur",
    "sg:classifiers":[
        {
            "category":"Restaurant",
            "type":"Food & Drink"
        }
    ],
    "sg:phone":"+32 81 46 19 61",
    "sg:postcode":"5100",
    "sg:province":"Namur",
    "sg:tags":[
        "organisatie",
        "feesten",
        "van",
        "catering"
    ],
    "wof:name":"Traiteur P\u00c8re Courtin",
    "wof:placetype":"venue"
},
  "geometry": {"coordinates":[4.8626680374,50.4338111877],"type":"Point"}
}