{
  "type": "Feature",
  "properties": {
    "iso:country":"BE",
    "sg:address":"Waregemsesteenweg 124",
    "sg:city":"Kruishoutem",
    "sg:classifiers":[
        {
            "category":"Professional",
            "subcategory":"Management & Consulting",
            "type":"Services"
        }
    ],
    "sg:phone":"+32 9 280 02 04",
    "sg:postcode":"9770",
    "sg:province":"Oost-Vlaanderen",
    "sg:tags":[
        "marketing",
        "-",
        "direct",
        "consultant"
    ],
    "wof:name":"Mink Nv",
    "wof:placetype":"venue"
},
  "geometry": {"coordinates":[3.5095779896,50.9015388489],"type":"Point"}
}