{
  "type": "Feature",
  "properties": {
    "addr:full":"Wanzelesteenweg 1be Wichelen Oost-Vlaanderen 9260",
    "addr:housenumber":"1be",
    "addr:postcode":"9260",
    "addr:street":"Wanzelesteenweg",
    "iso:country":"BE",
    "sg:address":"Wanzelesteenweg 1be",
    "sg:city":"Wichelen",
    "sg:orig_category":"IJzerwaren, bouw- and verfmaterialen Installatie van houten of kunststof schrijnwerk",
    "sg:phone":"+32 9 368 22 77",
    "sg:postcode":"9260",
    "sg:province":"Oost-Vlaanderen",
    "wof:name":"Van Caelenbergh",
    "wof:placetype":"venue"
},
  "geometry": {"coordinates":[3.9539170265,50.99451828],"type":"Point"}
}