{
  "type": "Feature",
  "properties": {
    "addr:full":"Ringlaan 39 Ichtegem West-Vlaanderen 8480",
    "addr:housenumber":"39",
    "addr:postcode":"8480",
    "addr:street":"Ringlaan",
    "iso:country":"BE",
    "sg:address":"Ringlaan 39",
    "sg:city":"Ichtegem",
    "sg:classifiers":[
        {
            "category":"Home & Garden",
            "subcategory":"Building Materials",
            "type":"Retail Goods"
        }
    ],
    "sg:phone":"+32 51 58 00 22",
    "sg:postcode":"8480",
    "sg:province":"West-Vlaanderen",
    "sg:tags":[
        "article",
        "-",
        "do-it-yourself"
    ],
    "wof:name":"Maxi-stock",
    "wof:placetype":"venue"
},
  "geometry": {"coordinates":[3.024420023,51.1013221741],"type":"Point"}
}