{
  "type": "Feature",
  "properties": {
    "addr:full":"Kantstraat 40 Dessel Antwerpen 2480",
    "addr:housenumber":"40",
    "addr:postcode":"2480",
    "addr:street":"Kantstraat",
    "iso:country":"BE",
    "sg:address":"Kantstraat 40",
    "sg:city":"Dessel",
    "sg:orig_category":"Gespecialiseerde residenti\u00eble bouw",
    "sg:phone":"+32 14 37 09 92",
    "sg:postcode":"2480",
    "sg:province":"Antwerpen",
    "wof:name":"Broeckx",
    "wof:placetype":"venue"
},
  "geometry": {"coordinates":[5.1296029091,51.2544212341],"type":"Point"}
}