{
  "type": "Feature",
  "properties": {
    "iso:country":"BE",
    "sg:address":"Rummenweg 109",
    "sg:city":"Herk-de-stad",
    "sg:classifiers":[
        {
            "category":"Real Estate",
            "subcategory":"Architect",
            "type":"Services"
        }
    ],
    "sg:phone":"+32 475 25 40 90",
    "sg:postcode":"3540",
    "sg:province":"Limburg",
    "wof:name":"Alen E",
    "wof:placetype":"venue"
},
  "geometry": {"coordinates":[5.1587247849,50.9257545471],"type":"Point"}
}