{
  "type": "Feature",
  "properties": {
    "addr:full":"Arteveldestraat 41 Brussel/bruxelles Bruxelles-Capitale 1000",
    "addr:housenumber":"41",
    "addr:postcode":"1000",
    "addr:street":"Arteveldestraat;/",
    "iso:country":"BE",
    "sg:address":"Arteveldestraat 41",
    "sg:city":"Brussel/bruxelles",
    "sg:orig_category":"Fietsen",
    "sg:phone":"+32 2 513 81 99",
    "sg:postcode":"1000",
    "sg:province":"Bruxelles-Capitale",
    "wof:name":"Velodroom",
    "wof:placetype":"venue"
},
  "geometry": {"coordinates":[4.3462958336,50.848274231],"type":"Point"}
}