{
  "type": "Feature",
  "properties": {
    "iso:country":"BE",
    "sg:address":"Kaudenaardedreef 12",
    "sg:city":"Dilbeek",
    "sg:classifiers":[
        {
            "category":"Retail",
            "subcategory":"Repair Shop",
            "type":"Services"
        }
    ],
    "sg:phone":"+32 2 567 98 16",
    "sg:postcode":"1700",
    "sg:province":"Vlaams-Brabant",
    "sg:tags":[
        "denture"
    ],
    "wof:name":"Van De Sande",
    "wof:placetype":"venue"
},
  "geometry": {"coordinates":[4.2728939056,50.8436965942],"type":"Point"}
}