{
  "type": "Feature",
  "properties": {
    "iso:country":"BE",
    "sg:address":"Jacob Jordaenslaan 47",
    "sg:city":"Lier",
    "sg:orig_category":"Schoonmaakbedrijven and ongediertebestrijding",
    "sg:phone":"+32 3 480 68 58",
    "sg:postcode":"2500",
    "sg:province":"Antwerpen",
    "wof:name":"Jean Hermans",
    "wof:placetype":"venue"
},
  "geometry": {"coordinates":[4.553850174,51.1297264099],"type":"Point"}
}