{
  "type": "Feature",
  "properties": {
    "iso:country":"BE",
    "sg:address":"Rue Du Chanoine Scarmure 60",
    "sg:city":"Soignies",
    "sg:classifiers":[
        {
            "category":"Insurance",
            "subcategory":"Insurance Agent",
            "type":"Services"
        }
    ],
    "sg:phone":"+32 67 33 25 80",
    "sg:postcode":"7060",
    "sg:province":"Hainaut",
    "sg:tags":[
        "verzekeringsmakelaars",
        "expert"
    ],
    "wof:name":"X. Colinet",
    "wof:placetype":"venue"
},
  "geometry": {"coordinates":[4.0741810799,50.580116272],"type":"Point"}
}