{
  "type": "Feature",
  "properties": {
    "addr:full":"Rogierlaan 55 Oostende West-Vlaanderen 8400",
    "addr:housenumber":"55",
    "addr:postcode":"8400",
    "addr:street":"Rogierlaan",
    "iso:country":"BE",
    "sg:address":"Rogierlaan 55",
    "sg:city":"Oostende",
    "sg:orig_category":"Studios photographiques",
    "sg:phone":"+32 59 70 80 02",
    "sg:postcode":"8400",
    "sg:province":"West-Vlaanderen",
    "wof:name":"Yves De Cock",
    "wof:placetype":"venue"
},
  "geometry": {"coordinates":[2.9119400978,51.2262496948],"type":"Point"}
}