{
  "type": "Feature",
  "properties": {
    "addr:full":"Rue Du Pont Du Christ 3 Wavre Brabant Wallon 1300",
    "addr:housenumber":"3;1300",
    "addr:street":"Rue Du Pont Du Christ",
    "iso:country":"BE",
    "sg:address":"Rue Du Pont Du Christ 3",
    "sg:city":"Wavre",
    "sg:orig_category":"Bijouteries and horlogeries. R\u00e9parations d'horloges, montres and bijoux",
    "sg:phone":"+32 10 22 23 36",
    "sg:postcode":"1300",
    "sg:province":"Brabant Wallon",
    "wof:name":"Maison Pitsi",
    "wof:placetype":"venue"
},
  "geometry": {"coordinates":[4.6105737686,50.7151489258],"type":"Point"}
}