{
  "type": "Feature",
  "properties": {
    "addr:full":"Rue De Mont\u00c9n\u00c9gro 21 Sint-gillis/saint-gilles Bruxelles-Capitale 1060",
    "addr:housenumber":"21",
    "addr:postcode":"1060",
    "addr:street":"Rue De Monte\u0301Ne\u0301Gro",
    "iso:country":"BE",
    "sg:address":"Rue De Mont\u00c9n\u00c9gro 21",
    "sg:city":"Sint-gillis/saint-gilles",
    "sg:orig_category":"Enseignement maternel and primaire",
    "sg:phone":"+32 2 538 06 28",
    "sg:postcode":"1060",
    "sg:province":"Bruxelles-Capitale",
    "wof:name":"Vrije Basisschool",
    "wof:placetype":"venue"
},
  "geometry": {"coordinates":[4.3382740021,50.8288650513],"type":"Point"}
}