{
  "type": "Feature",
  "properties": {
    "iso:country":"BE",
    "sg:address":"Appensvoordestraat 52",
    "sg:city":"Lovendegem",
    "sg:orig_category":"Artsen and specialisten",
    "sg:phone":"+32 9 372 42 16",
    "sg:postcode":"9920",
    "sg:province":"Oost-Vlaanderen",
    "wof:name":"P. Berten",
    "wof:placetype":"venue"
},
  "geometry": {"coordinates":[3.6226449013,51.0958518982],"type":"Point"}
}