{
  "type": "Feature",
  "properties": {
    "iso:country":"BE",
    "sg:address":"Hannekensboslaan 24",
    "sg:city":"Overijse",
    "sg:classifiers":[
        {
            "category":"Personal",
            "subcategory":"Beauty Salon",
            "type":"Services"
        }
    ],
    "sg:phone":"+32 2 305 77 89",
    "sg:postcode":"3090",
    "sg:province":"Vlaams-Brabant",
    "wof:name":"Babor Beautyworld",
    "wof:placetype":"venue"
},
  "geometry": {"coordinates":[4.5446481705,50.7618865967],"type":"Point"}
}