{
  "type": "Feature",
  "properties": {
    "iso:country":"BE",
    "sg:address":"Rue Bassenge 18",
    "sg:city":"Li\u00c8ge",
    "sg:orig_category":"Loodgieterij, verwarming and sanitaire installaties Schoonmaakbedrijven and ongediertebestrijding",
    "sg:phone":"+32 4 232 17 37",
    "sg:postcode":"4000",
    "sg:province":"Li\u00e8ge",
    "wof:name":"Chemi-net",
    "wof:placetype":"venue"
},
  "geometry": {"coordinates":[5.5597858429,50.6359291077],"type":"Point"}
}