{
  "type": "Feature",
  "properties": {
    "addr:full":"Emanuel Hielstraat 100 Gent (gentbrugge) Oost-Vlaanderen 9050",
    "addr:housenumber":"100",
    "addr:postcode":"9050",
    "addr:street":"Emanuel Hielstraat",
    "iso:country":"BE",
    "sg:address":"Emanuel Hielstraat 100",
    "sg:city":"Gent (gentbrugge)",
    "sg:classifiers":[
        {
            "category":"Professional",
            "subcategory":"Art Services",
            "type":"Services"
        }
    ],
    "sg:phone":"+32 9 230 53 71",
    "sg:postcode":"9050",
    "sg:province":"Oost-Vlaanderen",
    "sg:tags":[
        "photographer"
    ],
    "wof:name":"Vermeulen R",
    "wof:placetype":"venue"
},
  "geometry": {"coordinates":[3.7606189251,51.0414466858],"type":"Point"}
}