{
  "type": "Feature",
  "properties": {
    "iso:country":"BE",
    "sg:address":"Rue Willy Brogneaux 22",
    "sg:city":"Ham-sur-heure-nalinnes (jamioulx)",
    "sg:classifiers":[
        {
            "category":"Health Services",
            "subcategory":"Health Practitioner",
            "type":"Services"
        }
    ],
    "sg:phone":"+32 71 21 73 74",
    "sg:postcode":"6120",
    "sg:province":"Hainaut",
    "sg:tags":[
        "physiotherapist"
    ],
    "wof:name":"Theys D",
    "wof:placetype":"venue"
},
  "geometry": {"coordinates":[4.4145240784,50.3554458618],"type":"Point"}
}