{
  "type": "Feature",
  "properties": {
    "iso:country":"BE",
    "sg:address":"Ch De Waterloo 715",
    "sg:city":"Uccle",
    "sg:classifiers":[
        {
            "category":"Professional",
            "subcategory":"Printing & Photocopies",
            "type":"Services"
        }
    ],
    "sg:phone":"+32 2 343 48 68",
    "sg:postcode":"1180",
    "sg:province":"Bruxelles-Capitale",
    "sg:tags":[
        "electronic",
        "publishing"
    ],
    "wof:name":"Photo Hall Center Sa",
    "wof:placetype":"venue"
},
  "geometry": {"coordinates":[4.3669800758,50.815700531],"type":"Point"}
}