{
  "type": "Feature",
  "properties": {
    "addr:full":"Vlietenlaan 14 Meise (wolvertem) Vlaams-Brabant 1861",
    "addr:housenumber":"14",
    "addr:postcode":"1861",
    "addr:street":"Vlietenlaan",
    "iso:country":"BE",
    "sg:address":"Vlietenlaan 14",
    "sg:city":"Meise (wolvertem)",
    "sg:classifiers":[
        {
            "category":"Health Services",
            "subcategory":"Doctor",
            "type":"Services"
        }
    ],
    "sg:phone":"+32 2 270 05 05",
    "sg:postcode":"1861",
    "sg:province":"Vlaams-Brabant",
    "sg:tags":[
        "medicinephysicians",
        "surgeon"
    ],
    "wof:name":"Belgrado G",
    "wof:placetype":"venue"
},
  "geometry": {"coordinates":[4.3021631241,50.9545173645],"type":"Point"}
}