{
  "type": "Feature",
  "properties": {
    "iso:country":"BE",
    "sg:address":"Vlaanderenkaai 27ba",
    "sg:city":"Kortrijk",
    "sg:orig_category":"Rev\u00eatements de sols and murs. Rev\u00eatements pour sols and murs",
    "sg:phone":"+32 56 20 52 79",
    "sg:postcode":"8500",
    "sg:province":"West-Vlaanderen",
    "wof:name":"Tegelbedrijf Devos",
    "wof:placetype":"venue"
},
  "geometry": {"coordinates":[3.2726960182,50.833782196],"type":"Point"}
}