{
  "type": "Feature",
  "properties": {
    "iso:country":"BE",
    "sg:address":"Marcel Windelsstraat 19",
    "sg:city":"Waregem",
    "sg:orig_category":"Services fun\u00e9raires",
    "sg:phone":"+32 56 60 21 50",
    "sg:postcode":"8790",
    "sg:province":"West-Vlaanderen",
    "wof:name":"Vanhoutteghem",
    "wof:placetype":"venue"
},
  "geometry": {"coordinates":[3.4304680824,50.8905677795],"type":"Point"}
}