{
  "type": "Feature",
  "properties": {
    "iso:country":"BE",
    "sg:address":"J.f. Kennedyplein 8",
    "sg:city":"Zaventem",
    "sg:orig_category":"Filter Rolls",
    "sg:phone":"+32 2 725 00 12",
    "sg:postcode":"1930",
    "sg:province":"Vlaams-Brabant",
    "wof:name":"Hanseatic Trading West Gmbh",
    "wof:placetype":"venue"
},
  "geometry": {"coordinates":[4.4840202332,50.8754348755],"type":"Point"}
}