{
  "type": "Feature",
  "properties": {
    "addr:full":"Glabbeeksesteenweg 98 Tielt-winge Vlaams-Brabant 3391",
    "addr:housenumber":"98",
    "addr:postcode":"3391",
    "addr:street":"Glabbeeksesteenweg",
    "iso:country":"BE",
    "sg:address":"Glabbeeksesteenweg 98",
    "sg:city":"Tielt-winge",
    "sg:orig_category":"Catering and organisation de f\u00eates. Alimentation sp\u00e9cialis\u00e9e",
    "sg:phone":"+32 16 63 23 64",
    "sg:postcode":"3391",
    "sg:province":"Vlaams-Brabant",
    "wof:name":"Daniel Vandevelde",
    "wof:placetype":"venue"
},
  "geometry": {"coordinates":[4.8954730034,50.8959236145],"type":"Point"}
}