{
  "type": "Feature",
  "properties": {
    "iso:country":"BE",
    "sg:address":"Priorijstraat 14",
    "sg:city":"Waarschoot",
    "sg:classifiers":[
        {
            "category":"Building & Trades",
            "subcategory":"Landscaping Services",
            "type":"Services"
        }
    ],
    "sg:phone":"+32 9 371 44 32",
    "sg:postcode":"9950",
    "sg:province":"Oost-Vlaanderen",
    "sg:tags":[
        "architect",
        "landscape"
    ],
    "wof:name":"Hinnekens C",
    "wof:placetype":"venue"
},
  "geometry": {"coordinates":[3.6116418839,51.1593170166],"type":"Point"}
}