{
  "type": "Feature",
  "properties": {
    "iso:country":"BE",
    "sg:address":"Boulevard Joseph Ii 2",
    "sg:city":"Charleroi",
    "sg:orig_category":"Mat\u00e9riel m\u00e9dical and orthop\u00e9dique and proth\u00e8ses Fab",
    "sg:phone":"+32 71 31 35 77",
    "sg:postcode":"6000",
    "sg:province":"Hainaut",
    "wof:name":"Cabinet Dentaire Mallet",
    "wof:placetype":"venue"
},
  "geometry": {"coordinates":[4.449529171,50.4134902954],"type":"Point"}
}