{
  "type": "Feature",
  "properties": {
    "addr:full":"Av De Pervuren 72 Bruxelles Brabant Wallon 1400",
    "addr:housenumber":"72",
    "addr:postcode":"1400",
    "addr:street":"Av De Pervuren;Wallon",
    "iso:country":"BE",
    "sg:address":"Av De Pervuren 72",
    "sg:city":"Bruxelles",
    "sg:classifiers":[
        {
            "category":"Manufacturing",
            "subcategory":"Wood Products",
            "type":"Manufacturing & Wholesale Goods"
        }
    ],
    "sg:phone":"+32 2 237 09 00",
    "sg:postcode":"1400",
    "sg:province":"Brabant Wallon",
    "sg:tags":[
        "professional",
        "furniture"
    ],
    "wof:name":"Ibf International Consulting Sa",
    "wof:placetype":"venue"
},
  "geometry": {"coordinates":[4.3496799469,50.8483810425],"type":"Point"}
}