{
  "type": "Feature",
  "properties": {
    "iso:country":"BE",
    "sg:address":"Rue Josaphat 69",
    "sg:city":"Schaarbeek/schaerbeek",
    "sg:orig_category":"Pain, p\u00e2tisseries and confiseries",
    "sg:phone":"+32 2 218 21 38",
    "sg:postcode":"1030",
    "sg:province":"Bruxelles-Capitale",
    "wof:name":"Cheikh",
    "wof:placetype":"venue"
},
  "geometry": {"coordinates":[4.373404026,50.8578987122],"type":"Point"}
}