{
  "type": "Feature",
  "properties": {
    "iso:country":"BE",
    "sg:address":"Ange Angillisstraat 14",
    "sg:city":"Roeselare (rumbeke)",
    "sg:classifiers":[
        {
            "category":"Manufacturing",
            "subcategory":"Printing",
            "type":"Manufacturing & Wholesale Goods"
        }
    ],
    "sg:phone":"+32 51 22 72 87",
    "sg:postcode":"8800",
    "sg:province":"West-Vlaanderen",
    "sg:tags":[
        "textile",
        "-"
    ],
    "wof:name":"Rosseel J",
    "wof:placetype":"venue"
},
  "geometry": {"coordinates":[3.1367731094,50.9334793091],"type":"Point"}
}