{
  "type": "Feature",
  "properties": {
    "addr:full":"Gennepstraat 31 Halen Limburg 3545",
    "addr:housenumber":"31",
    "addr:postcode":"3545",
    "addr:street":"Gennepstraat",
    "iso:country":"BE",
    "sg:address":"Gennepstraat 31",
    "sg:city":"Halen",
    "sg:classifiers":[
        {
            "category":"Professional",
            "subcategory":"Accounting & Tax Preparation",
            "type":"Services"
        }
    ],
    "sg:phone":"+32 13 33 39 66",
    "sg:postcode":"3545",
    "sg:province":"Limburg",
    "sg:tags":[
        "accountant"
    ],
    "wof:name":"Jos Macquoi",
    "wof:placetype":"venue"
},
  "geometry": {"coordinates":[5.0852527618,50.9835777283],"type":"Point"}
}