{
  "type": "Feature",
  "properties": {
    "iso:country":"BE",
    "sg:address":"Rue Des Sicambres 20a",
    "sg:city":"Bruxelles (etterbeek)",
    "sg:classifiers":[
        {
            "category":"Communications",
            "subcategory":"News Services",
            "type":"Services"
        }
    ],
    "sg:phone":"+32 2 733 28 81",
    "sg:postcode":"1040",
    "sg:province":"Bruxelles-Capitale",
    "sg:tags":[
        "illustrator"
    ],
    "wof:name":"Lejeune-massinger",
    "wof:placetype":"venue"
},
  "geometry": {"coordinates":[4.4030461311,50.8321762085],"type":"Point"}
}