{
  "type": "Feature",
  "properties": {
    "iso:country":"BE",
    "sg:address":"Boulevard Neuf 1",
    "sg:city":"Villers-la-ville",
    "sg:orig_category":"M\u00e9decins and sp\u00e9cialistes",
    "sg:phone":"+32 71 87 76 62",
    "sg:postcode":"1495",
    "sg:province":"Brabant Wallon",
    "wof:name":"J. Pauluis",
    "wof:placetype":"venue"
},
  "geometry": {"coordinates":[4.5374622345,50.5807228088],"type":"Point"}
}