{
  "type": "Feature",
  "properties": {
    "iso:country":"BE",
    "sg:address":"Beukenstraat 12",
    "sg:city":"Bocholt",
    "sg:classifiers":[
        {
            "category":"Arena",
            "subcategory":"Sports Club",
            "type":"Entertainment"
        }
    ],
    "sg:phone":"+32 89 46 26 68",
    "sg:postcode":"3950",
    "sg:province":"Limburg",
    "sg:tags":[
        "de"
    ],
    "wof:name":"Bocholter Wielerclub",
    "wof:placetype":"venue"
},
  "geometry": {"coordinates":[5.5856261253,51.1713447571],"type":"Point"}
}