{
  "type": "Feature",
  "properties": {
    "addr:full":"Rue Godefroid 55 Namur Namur 5000",
    "addr:housenumber":"55",
    "addr:postcode":"5000",
    "addr:street":"Rue Godefroid",
    "iso:country":"BE",
    "sg:address":"Rue Godefroid 55",
    "sg:city":"Namur",
    "sg:orig_category":"Banques and organismes de cr\u00e9dit",
    "sg:phone":"+32 81 23 11 81",
    "sg:postcode":"5000",
    "sg:province":"Namur",
    "wof:name":"Bacob",
    "wof:placetype":"venue"
},
  "geometry": {"coordinates":[4.86226511,50.4680290222],"type":"Point"}
}