{
  "type": "Feature",
  "properties": {
    "iso:country":"BE",
    "sg:address":"Venecolaan 28",
    "sg:city":"Aalter",
    "sg:orig_category":"Non-Classified Establishments",
    "sg:phone":"+32 9 375 16 14",
    "sg:postcode":"9880",
    "sg:province":"Oost-Vlaanderen",
    "wof:name":"Altra Trading Company Bvba",
    "wof:placetype":"venue"
},
  "geometry": {"coordinates":[3.44866395,51.1060714722],"type":"Point"}
}