{
  "type": "Feature",
  "properties": {
    "iso:country":"BE",
    "sg:address":"Rue Ribatte 14",
    "sg:city":"Donceel (haneffe)",
    "sg:classifiers":[
        {
            "category":"Food & Beverages",
            "subcategory":"Specialty",
            "type":"Retail Goods"
        }
    ],
    "sg:phone":"+32 4 259 50 56",
    "sg:postcode":"4357",
    "sg:province":"Li\u00e8ge",
    "sg:tags":[
        "health",
        "dietary",
        "-",
        "biological"
    ],
    "wof:name":"Ferme Schalenbourg",
    "wof:placetype":"venue"
},
  "geometry": {"coordinates":[5.3179411888,50.6375694275],"type":"Point"}
}