{
  "type": "Feature",
  "properties": {
    "addr:full":"Avenue Du Val D'or 44 Bruxelles (woluwe-saint-pierre) Bruxelles-Capitale 1150",
    "addr:housenumber":"44",
    "addr:postcode":"1150",
    "addr:street":"Avenue Du Val D'Or",
    "iso:country":"BE",
    "sg:address":"Avenue Du Val D'or 44",
    "sg:city":"Bruxelles (woluwe-saint-pierre)",
    "sg:classifiers":[
        {
            "category":"Health Services",
            "subcategory":"Health Practitioner",
            "type":"Services"
        }
    ],
    "sg:phone":"+32 476 35 99 07",
    "sg:postcode":"1150",
    "sg:province":"Bruxelles-Capitale",
    "sg:tags":[
        "psychologist"
    ],
    "wof:name":"Sempoux F",
    "wof:placetype":"venue"
},
  "geometry": {"coordinates":[4.4404001236,50.8336410522],"type":"Point"}
}