{
  "type": "Feature",
  "properties": {
    "iso:country":"BE",
    "sg:address":"Boommeerstraat 32",
    "sg:city":"Genk",
    "sg:orig_category":"Transports a\u00e9riens non-r\u00e9guliers. Transports a\u00e9riens r\u00e9guliers. Ecoles de pilotage de bateaux and d\u00b4",
    "sg:phone":"+32 89 38 56 05",
    "sg:postcode":"3600",
    "sg:province":"Limburg",
    "wof:name":"Pegasus Aviation Services",
    "wof:placetype":"venue"
},
  "geometry": {"coordinates":[5.5419597626,50.9894943237],"type":"Point"}
}