{
  "type": "Feature",
  "properties": {
    "addr:full":"Nieuwstraat 27 Lede Oost-Vlaanderen 9340",
    "addr:housenumber":"27",
    "addr:postcode":"9340",
    "addr:street":"Nieuwstraat",
    "iso:country":"BE",
    "sg:address":"Nieuwstraat 27",
    "sg:city":"Lede",
    "sg:classifiers":[
        {
            "category":"Cafe",
            "type":"Food & Drink"
        }
    ],
    "sg:phone":"+32 53 80 47 79",
    "sg:postcode":"9340",
    "sg:province":"Oost-Vlaanderen",
    "sg:tags":[
        "snack-bars"
    ],
    "wof:name":"Chaplin's",
    "wof:placetype":"venue"
},
  "geometry": {"coordinates":[3.9793579578,50.9653358459],"type":"Point"}
}