{
  "type": "Feature",
  "properties": {
    "iso:country":"BE",
    "sg:address":"Gavergrachtstraat 48",
    "sg:city":"Gent",
    "sg:orig_category":"Catering and organisation de f\u00eates",
    "sg:phone":"+32 9 226 57 92",
    "sg:postcode":"9031",
    "sg:province":"Oost-Vlaanderen",
    "wof:name":"Marc & Jenny",
    "wof:placetype":"venue"
},
  "geometry": {"coordinates":[3.6258409023,51.0705986023],"type":"Point"}
}