{
  "type": "Feature",
  "properties": {
    "addr:full":"Blanklaerstraat 6 Diest 3295",
    "addr:housenumber":"6",
    "addr:postcode":"3295",
    "addr:street":"Blanklaerstraat",
    "iso:country":"BE",
    "sg:address":"Blanklaerstraat 6",
    "sg:city":"Diest",
    "sg:orig_category":"Bloemen and planten",
    "sg:phone":"+32 13 32 67 62",
    "sg:postcode":"3295",
    "wof:name":"Riviera",
    "wof:placetype":"venue"
},
  "geometry": {"coordinates":[5.1189279556,51.0109100342],"type":"Point"}
}