{
  "type": "Feature",
  "properties": {
    "iso:country":"BE",
    "sg:address":"Rue Des Xviii Bonniers 90",
    "sg:city":"Grace-hollogne",
    "sg:orig_category":"Travaux de finition and nettoyage de b\u00e2timents. Peinture. Construction de maisons. Constructions r\u00e9s",
    "sg:phone":"+32 4 247 37 77",
    "sg:postcode":"4460",
    "sg:province":"Li\u00e8ge",
    "wof:name":"B\u00c9tonr\u00c9sine",
    "wof:placetype":"venue"
},
  "geometry": {"coordinates":[5.487801075,50.6434440613],"type":"Point"}
}