{
  "type": "Feature",
  "properties": {
    "addr:full":"Heirbaan 104 Anzegem West-Vlaanderen 8570",
    "addr:housenumber":"104",
    "addr:postcode":"8570",
    "addr:street":"Heirbaan",
    "iso:country":"BE",
    "sg:address":"Heirbaan 104",
    "sg:city":"Anzegem",
    "sg:orig_category":"Catering and organisatie van feesten",
    "sg:phone":"+32 56 77 32 12",
    "sg:postcode":"8570",
    "sg:province":"West-Vlaanderen",
    "wof:name":"Jo Demerie",
    "wof:placetype":"venue"
},
  "geometry": {"coordinates":[3.4285669327,50.842830658],"type":"Point"}
}