{
  "type": "Feature",
  "properties": {
    "iso:country":"BE",
    "sg:address":"Rue Renkin 21",
    "sg:city":"Verviers",
    "sg:orig_category":"M\u00e9decins and sp\u00e9cialistes",
    "sg:phone":"+32 87 22 78 50",
    "sg:postcode":"4800",
    "sg:province":"Li\u00e8ge",
    "wof:name":"Bernadette Dogniez",
    "wof:placetype":"venue"
},
  "geometry": {"coordinates":[5.8573451042,50.5884132385],"type":"Point"}
}