{
  "type": "Feature",
  "properties": {
    "addr:full":"Rue De Caraman 91 Boussu Hainaut 7300",
    "addr:housenumber":"91",
    "addr:postcode":"7300",
    "addr:street":"Rue De Caraman",
    "iso:country":"BE",
    "sg:address":"Rue De Caraman 91",
    "sg:city":"Boussu",
    "sg:orig_category":"M\u00e9decins and sp\u00e9cialistes",
    "sg:phone":"+32 65 78 40 50",
    "sg:postcode":"7300",
    "sg:province":"Hainaut",
    "wof:name":"Cl\u00c9ment Henrion",
    "wof:placetype":"venue"
},
  "geometry": {"coordinates":[3.7879641056,50.4341545105],"type":"Point"}
}