{
  "type": "Feature",
  "properties": {
    "addr:full":"Wegvoeringstraat 150 Wetteren Oost-Vlaanderen 9230",
    "addr:housenumber":"150",
    "addr:postcode":"9230",
    "addr:street":"Wegvoeringstraat",
    "iso:country":"BE",
    "sg:address":"Wegvoeringstraat 150",
    "sg:city":"Wetteren",
    "sg:classifiers":[
        {
            "category":"Building & Trades",
            "subcategory":"Electrical",
            "type":"Services"
        }
    ],
    "sg:phone":"+32 9 369 64 56",
    "sg:postcode":"9230",
    "sg:province":"Oost-Vlaanderen",
    "sg:tags":[
        "electric",
        "-",
        "housewiring",
        "contractor"
    ],
    "wof:name":"Jps",
    "wof:placetype":"venue"
},
  "geometry": {"coordinates":[3.8944890499,51.0084877014],"type":"Point"}
}