{
  "type": "Feature",
  "properties": {
    "addr:full":"Rue De Tournai 32 Tournai Hainaut 7520",
    "addr:housenumber":"32",
    "addr:postcode":"7520",
    "addr:street":"Rue De Tournai",
    "iso:country":"BE",
    "sg:address":"Rue De Tournai 32",
    "sg:city":"Tournai",
    "sg:classifiers":[
        {
            "category":"Insurance",
            "subcategory":"Insurance Agent",
            "type":"Services"
        }
    ],
    "sg:phone":"+32 69 35 23 71",
    "sg:postcode":"7520",
    "sg:province":"Hainaut",
    "sg:tags":[
        "verzekeringsmakelaars",
        "expert"
    ],
    "wof:name":"Rysman & Fran\u00c7ois",
    "wof:placetype":"venue"
},
  "geometry": {"coordinates":[3.2858190536,50.6438827515],"type":"Point"}
}