{
  "type": "Feature",
  "properties": {
    "addr:full":"Doornikserijksweg 264 Kortrijk West-Vlaanderen 8510",
    "addr:housenumber":"264",
    "addr:postcode":"8510",
    "iso:country":"BE",
    "sg:address":"Doornikserijksweg 264",
    "sg:city":"Kortrijk",
    "sg:classifiers":[
        {
            "category":"Cafe",
            "type":"Food & Drink"
        }
    ],
    "sg:phone":"+32 56 22 01 21",
    "sg:postcode":"8510",
    "sg:province":"West-Vlaanderen",
    "sg:tags":[
        "caf\u00e9s"
    ],
    "wof:name":"Caf\u00c9 't Konijntje",
    "wof:placetype":"venue"
},
  "geometry": {"coordinates":[3.3111801147,50.7581291199],"type":"Point"}
}