{
  "type": "Feature",
  "properties": {
    "addr:full":"Oude Zeedijk 50 Diksmuide West-Vlaanderen 8600",
    "addr:housenumber":"50",
    "addr:postcode":"8600",
    "addr:street":"Oude Zeedijk",
    "iso:country":"BE",
    "sg:address":"Oude Zeedijk 50",
    "sg:city":"Diksmuide",
    "sg:orig_category":"Eleveurs de bovins",
    "sg:phone":"+32 51 55 50 55",
    "sg:postcode":"8600",
    "sg:province":"West-Vlaanderen",
    "wof:name":"Koen Danneels",
    "wof:placetype":"venue"
},
  "geometry": {"coordinates":[2.7681200504,51.0425949097],"type":"Point"}
}