{
  "type": "Feature",
  "properties": {
    "addr:full":"Leffingestraat 158 Oostende West-Vlaanderen 8400",
    "addr:housenumber":"158",
    "addr:postcode":"8400",
    "addr:street":"Leffingestraat",
    "iso:country":"BE",
    "sg:address":"Leffingestraat 158",
    "sg:city":"Oostende",
    "sg:orig_category":"Artistes ind\u00e9pendants",
    "sg:phone":"+32 59 70 80 44",
    "sg:postcode":"8400",
    "sg:province":"West-Vlaanderen",
    "wof:name":"M. Plettinck",
    "wof:placetype":"venue"
},
  "geometry": {"coordinates":[2.9068439007,51.2175636292],"type":"Point"}
}