{
  "type": "Feature",
  "properties": {
    "addr:full":"Rue De Bastogne 42 Arlon Luxembourg 6700",
    "addr:housenumber":"42",
    "addr:postcode":"6700",
    "addr:street":"Rue De Bastogne",
    "iso:country":"BE",
    "sg:address":"Rue De Bastogne 42",
    "sg:city":"Arlon",
    "sg:orig_category":"Schoonheidssalons",
    "sg:phone":"+32 63 22 43 39",
    "sg:postcode":"6700",
    "sg:province":"Luxembourg",
    "wof:name":"Dumont",
    "wof:placetype":"venue"
},
  "geometry": {"coordinates":[5.8099632263,49.6878204346],"type":"Point"}
}