{
  "type": "Feature",
  "properties": {
    "iso:country":"BE",
    "sg:address":"Rue Des Bach\u00e8res 9",
    "sg:city":"Sambreville (tamines)",
    "sg:classifiers":[
        {
            "category":"Professional",
            "subcategory":"Accounting & Tax Preparation",
            "type":"Services"
        }
    ],
    "sg:phone":"+32 71 77 34 00",
    "sg:postcode":"5060",
    "sg:province":"Namur",
    "sg:tags":[
        "bookkeeper"
    ],
    "wof:name":"Vanderus E",
    "wof:placetype":"venue"
},
  "geometry": {"coordinates":[4.5887608528,50.4374885559],"type":"Point"}
}