{
  "type": "Feature",
  "properties": {
    "addr:full":"Heirbaan 252 Dendermonde Oost-Vlaanderen 9200",
    "addr:housenumber":"252",
    "addr:postcode":"9200",
    "addr:street":"Heirbaan;Oost-Vlaanderen",
    "iso:country":"BE",
    "sg:address":"Heirbaan 252",
    "sg:city":"Dendermonde",
    "sg:orig_category":"Bouwmaterialen Gh",
    "sg:phone":"+32 52 21 23 75",
    "sg:postcode":"9200",
    "sg:province":"Oost-Vlaanderen",
    "wof:name":"M. Van Goethem",
    "wof:placetype":"venue"
},
  "geometry": {"coordinates":[4.1173210144,51.0113639832],"type":"Point"}
}