{
  "type": "Feature",
  "properties": {
    "iso:country":"BE",
    "sg:address":"Leestraat 14",
    "sg:city":"Sint-niklaas (sinaai)",
    "sg:classifiers":[
        {
            "category":"Freight",
            "type":"Transportation"
        }
    ],
    "sg:phone":"+32 3 772 54 59",
    "sg:postcode":"9112",
    "sg:province":"Oost-Vlaanderen",
    "sg:tags":[
        "-",
        "transport"
    ],
    "wof:name":"Dullaert W Bvba",
    "wof:placetype":"venue"
},
  "geometry": {"coordinates":[4.0148258209,51.1409568787],"type":"Point"}
}