{
  "type": "Feature",
  "properties": {
    "iso:country":"BE",
    "sg:address":"Rue De Freylange 69",
    "sg:city":"Arlon",
    "sg:orig_category":"Cin\u00e9mas",
    "sg:phone":"+32 63 23 92 74",
    "sg:postcode":"6700",
    "sg:province":"Luxembourg",
    "wof:name":"Le Plaza",
    "wof:placetype":"venue"
},
  "geometry": {"coordinates":[5.7897801399,49.6980895996],"type":"Point"}
}