{
  "type": "Feature",
  "properties": {
    "addr:full":"Petit Hollaye 29 Celles Hainaut 7760",
    "addr:housenumber":"29",
    "addr:postcode":"7760",
    "addr:street":"Petit Hollaye",
    "iso:country":"BE",
    "sg:address":"Petit Hollaye 29",
    "sg:city":"Celles",
    "sg:orig_category":"Slagers",
    "sg:phone":"+32 69 45 40 75",
    "sg:postcode":"7760",
    "sg:province":"Hainaut",
    "wof:name":"Viandes Samain",
    "wof:placetype":"venue"
},
  "geometry": {"coordinates":[3.469340086,50.713218689],"type":"Point"}
}