{
  "type": "Feature",
  "properties": {
    "iso:country":"BE",
    "sg:address":"Esdoornlaan 21",
    "sg:city":"Kalmthout",
    "sg:classifiers":[
        {
            "category":"Real Estate",
            "subcategory":"Developer",
            "type":"Services"
        }
    ],
    "sg:phone":"+32 3 666 36 91",
    "sg:postcode":"2920",
    "sg:province":"Antwerpen",
    "sg:tags":[
        "project"
    ],
    "wof:name":"Werco",
    "wof:placetype":"venue"
},
  "geometry": {"coordinates":[4.4856038094,51.3558883667],"type":"Point"}
}