{
  "type": "Feature",
  "properties": {
    "iso:country":"BE",
    "sg:address":"Boulevard De La Sauveni\u00e8re 164",
    "sg:city":"Li\u00e8ge 1",
    "sg:classifiers":[
        {
            "category":"Food & Beverages",
            "subcategory":"Specialty",
            "type":"Retail Goods"
        }
    ],
    "sg:phone":"+32 4 232 02 60",
    "sg:postcode":"4000",
    "sg:province":"Li\u00e8ge",
    "sg:tags":[
        "health",
        "dietary",
        "-",
        "biological"
    ],
    "wof:name":"Proteika",
    "wof:placetype":"venue"
},
  "geometry": {"coordinates":[5.5677390099,50.6407356262],"type":"Point"}
}