{
  "type": "Feature",
  "properties": {
    "iso:country":"BE",
    "sg:address":"Rue Du Centry 55b57",
    "sg:city":"Grez-doiceau",
    "sg:orig_category":"Experts-comptables",
    "sg:phone":"+32 10 84 59 09",
    "sg:postcode":"1390",
    "sg:province":"Brabant Wallon",
    "wof:name":"Yves Mikolajczak",
    "wof:placetype":"venue"
},
  "geometry": {"coordinates":[4.6844420433,50.7373085022],"type":"Point"}
}