{
  "type": "Feature",
  "properties": {
    "addr:full":"Volkstraat 14 Antwerpen Antwerpen 2000",
    "addr:housenumber":"14",
    "addr:postcode":"2000",
    "addr:street":"Volkstraat",
    "iso:country":"BE",
    "sg:address":"Volkstraat 14",
    "sg:city":"Antwerpen",
    "sg:orig_category":"Epiceries",
    "sg:phone":"+32 3 237 97 78",
    "sg:postcode":"2000",
    "sg:province":"Antwerpen",
    "wof:name":"Christel Ruyssinck",
    "wof:placetype":"venue"
},
  "geometry": {"coordinates":[4.396545887,51.211730957],"type":"Point"}
}