{
  "type": "Feature",
  "properties": {
    "addr:full":"Boezingestraat 35 Langemark-poelkapelle West-Vlaanderen 8920",
    "addr:housenumber":"35",
    "addr:postcode":"8920",
    "addr:street":"Boezingestraat",
    "iso:country":"BE",
    "sg:address":"Boezingestraat 35",
    "sg:city":"Langemark-poelkapelle",
    "sg:classifiers":[
        {
            "category":"Insurance",
            "subcategory":"Life Insurance",
            "type":"Services"
        }
    ],
    "sg:phone":"+32 51 70 18 88",
    "sg:postcode":"8920",
    "sg:province":"West-Vlaanderen",
    "sg:tags":[
        "assurance"
    ],
    "wof:name":"Verz. Vandenbulcke Donald",
    "wof:placetype":"venue"
},
  "geometry": {"coordinates":[2.919770956,50.9132423401],"type":"Point"}
}