{
  "type": "Feature",
  "properties": {
    "iso:country":"BE",
    "sg:address":"Rue Chapelle Sainte Anne 10",
    "sg:city":"Walhain (walhain-saint-paul)",
    "sg:classifiers":[
        {
            "category":"Retail",
            "subcategory":"Funeral Services",
            "type":"Services"
        }
    ],
    "sg:phone":"+32 10 65 52 05",
    "sg:postcode":"1457",
    "sg:province":"Brabant Wallon",
    "sg:tags":[
        "director"
    ],
    "wof:name":"Tassin E",
    "wof:placetype":"venue"
},
  "geometry": {"coordinates":[4.6986689568,50.617313385],"type":"Point"}
}