{
  "type": "Feature",
  "properties": {
    "addr:full":"Rue De Warpotte 46 Chi\u00e8vres (ladeuze) Hainaut 7950",
    "addr:housenumber":"46",
    "addr:postcode":"7950",
    "addr:street":"Rue De Warpotte;Ladeuze Hainaut",
    "iso:country":"BE",
    "sg:address":"Rue De Warpotte 46",
    "sg:city":"Chi\u00e8vres (ladeuze)",
    "sg:classifiers":[
        {
            "category":"Building & Trades",
            "subcategory":"Landscaping Services",
            "type":"Services"
        }
    ],
    "sg:phone":"+32 69 68 80 88",
    "sg:postcode":"7950",
    "sg:province":"Hainaut",
    "sg:tags":[
        "gardening",
        "garden",
        "maintenance"
    ],
    "wof:name":"Bassee S",
    "wof:placetype":"venue"
},
  "geometry": {"coordinates":[3.7574179173,50.5542564392],"type":"Point"}
}