{
  "type": "Feature",
  "properties": {
    "addr:full":"Rue Du Sonnet 15 Sint-jans-molenbeek/molenbeek-saint-jean Bruxelles-Capitale 1080",
    "addr:housenumber":"15",
    "addr:postcode":"1080",
    "addr:street":"Rue Du Sonnet",
    "iso:country":"BE",
    "sg:address":"Rue Du Sonnet 15",
    "sg:city":"Sint-jans-molenbeek/molenbeek-saint-jean",
    "sg:orig_category":"Agences de presse",
    "sg:phone":"+32 2 410 78 50",
    "sg:postcode":"1080",
    "sg:province":"Bruxelles-Capitale",
    "wof:name":"Alain De Kuyssche",
    "wof:placetype":"venue"
},
  "geometry": {"coordinates":[4.3151941299,50.8542289734],"type":"Point"}
}