{
  "type": "Feature",
  "properties": {
    "addr:full":"Belzeelse Kerkweg 10ba Evergem Oost-Vlaanderen 9940",
    "addr:housenumber":"10ba",
    "addr:postcode":"9940",
    "addr:street":"Kerkweg;Oost-Vlaanderen",
    "iso:country":"BE",
    "sg:address":"Belzeelse Kerkweg 10ba",
    "sg:city":"Evergem",
    "sg:orig_category":"Diverse bouwafwerking and reiniging Gespecialiseerde residenti\u00eble bouw",
    "sg:phone":"+32 9 253 04 54",
    "sg:postcode":"9940",
    "sg:province":"Oost-Vlaanderen",
    "wof:name":"D'haemers",
    "wof:placetype":"venue"
},
  "geometry": {"coordinates":[3.6768538952,51.1040649414],"type":"Point"}
}