{
  "type": "Feature",
  "properties": {
    "addr:full":"Hoogkouterbaan 26 Haaltert Oost-Vlaanderen 9450",
    "addr:housenumber":"26",
    "addr:postcode":"9450",
    "addr:street":"Hoogkouterbaan",
    "iso:country":"BE",
    "sg:address":"Hoogkouterbaan 26",
    "sg:city":"Haaltert",
    "sg:orig_category":"Diverse bouwafwerking and reiniging Gespecialiseerde residenti\u00eble bouw Woningbouw",
    "sg:phone":"+32 53 83 51 10",
    "sg:postcode":"9450",
    "sg:province":"Oost-Vlaanderen",
    "wof:name":"Willy Van Impe",
    "wof:placetype":"venue"
},
  "geometry": {"coordinates":[3.9848349094,50.900062561],"type":"Point"}
}