{
  "type": "Feature",
  "properties": {
    "addr:full":"Rue De L'ourthe 1 Li\u00c8ge Li\u00e8ge 4020",
    "addr:housenumber":"1",
    "addr:postcode":"4020",
    "addr:street":"Rue De L'Ourthe",
    "iso:country":"BE",
    "sg:address":"Rue De L'ourthe 1",
    "sg:city":"Li\u00c8ge",
    "sg:classifiers":[
        {
            "category":"Arena",
            "subcategory":"Sports Club",
            "type":"Entertainment"
        }
    ],
    "sg:phone":"+32 4 342 81 76",
    "sg:postcode":"4020",
    "sg:province":"Li\u00e8ge",
    "sg:tags":[
        "terrain",
        "hors",
        "de",
        "installation",
        "sportifs"
    ],
    "wof:name":"Piscine D'outremeuse",
    "wof:placetype":"venue"
},
  "geometry": {"coordinates":[5.5859651566,50.637840271],"type":"Point"}
}