{
  "type": "Feature",
  "properties": {
    "iso:country":"BE",
    "sg:address":"Rue Dagly 8",
    "sg:city":"Spa",
    "sg:classifiers":[
        {
            "category":"Cafe",
            "type":"Food & Drink"
        }
    ],
    "sg:phone":"+32 87 77 20 06",
    "sg:postcode":"4900",
    "sg:province":"Li\u00e8ge",
    "sg:tags":[
        "snack-bars"
    ],
    "wof:name":"Francesca (snack Pita)",
    "wof:placetype":"venue"
},
  "geometry": {"coordinates":[5.8658790588,50.4924812317],"type":"Point"}
}