{
  "type": "Feature",
  "properties": {
    "iso:country":"BE",
    "sg:address":"Stationsstraat 34",
    "sg:city":"Denderleeuw",
    "sg:classifiers":[
        {
            "category":"Cemetery",
            "type":"Public Place"
        }
    ],
    "sg:phone":"+32 53 66 62 43",
    "sg:postcode":"9470",
    "sg:province":"Oost-Vlaanderen",
    "sg:tags":[
        "crematory"
    ],
    "wof:name":"Depoorter W",
    "wof:placetype":"venue"
},
  "geometry": {"coordinates":[4.0725097656,50.892868042],"type":"Point"}
}