{
  "type": "Feature",
  "properties": {
    "iso:country":"BE",
    "sg:address":"Place Du Roi Albert 1",
    "sg:city":"Remicourt (pousset)",
    "sg:classifiers":[
        {
            "category":"Professional",
            "subcategory":"Art Services",
            "type":"Services"
        }
    ],
    "sg:phone":"+32 19 58 78 28",
    "sg:postcode":"4350",
    "sg:province":"Li\u00e8ge",
    "sg:tags":[
        "photographer",
        "aerial",
        "-"
    ],
    "wof:name":"De Neuville J",
    "wof:placetype":"venue"
},
  "geometry": {"coordinates":[5.3047251701,50.6945762634],"type":"Point"}
}