{
  "type": "Feature",
  "properties": {
    "addr:full":"Pruimenbosstraat 2 De Pinte Oost-Vlaanderen 9840",
    "addr:housenumber":"2",
    "addr:postcode":"9840",
    "addr:street":"Pruimenbosstraat",
    "iso:country":"BE",
    "sg:address":"Pruimenbosstraat 2",
    "sg:city":"De Pinte",
    "sg:classifiers":[
        {
            "category":"Professional",
            "subcategory":"Accounting & Tax Preparation",
            "type":"Services"
        }
    ],
    "sg:phone":"+32 9 282 99 55",
    "sg:postcode":"9840",
    "sg:province":"Oost-Vlaanderen",
    "sg:tags":[
        "accountant"
    ],
    "wof:name":"Arktos Bvba",
    "wof:placetype":"venue"
},
  "geometry": {"coordinates":[3.6353359222,50.9974327087],"type":"Point"}
}