{
  "type": "Feature",
  "properties": {
    "addr:full":"Rue Godefroid Guffens 5 Schaarbeek/schaerbeek Bruxelles-Capitale 1030",
    "addr:housenumber":"5",
    "addr:postcode":"1030",
    "addr:street":"Rue Godefroid Guffens",
    "iso:country":"BE",
    "sg:address":"Rue Godefroid Guffens 5",
    "sg:city":"Schaarbeek/schaerbeek",
    "sg:orig_category":"Activit\u00e9s diverses d'imprimerie",
    "sg:phone":"+32 2 241 33 99",
    "sg:postcode":"1030",
    "sg:province":"Bruxelles-Capitale",
    "wof:name":"Frederic Thiry",
    "wof:placetype":"venue"
},
  "geometry": {"coordinates":[4.3929691315,50.8685073853],"type":"Point"}
}