{
  "type": "Feature",
  "properties": {
    "iso:country":"BE",
    "sg:address":"Avenue Mar\u00c9chal Ney 36",
    "sg:city":"Braine-l\u00b4alleud",
    "sg:orig_category":"Services annexes des transports terrestres",
    "sg:phone":"+32 2 385 23 70",
    "sg:postcode":"1420",
    "sg:province":"Brabant Wallon",
    "wof:name":"City Parking",
    "wof:placetype":"venue"
},
  "geometry": {"coordinates":[4.3789100647,50.6848564148],"type":"Point"}
}