{
  "type": "Feature",
  "properties": {
    "addr:full":"Stationsplein 2 Zemst (weerde) Vlaams-Brabant 1982",
    "addr:housenumber":"2",
    "addr:postcode":"1982",
    "addr:street":"Stationsplein",
    "iso:country":"BE",
    "sg:address":"Stationsplein 2",
    "sg:city":"Zemst (weerde)",
    "sg:classifiers":[
        {
            "category":"Bars & Pubs",
            "type":"Food & Drink"
        }
    ],
    "sg:phone":"+32 15 62 15 50",
    "sg:postcode":"1982",
    "sg:province":"Vlaams-Brabant",
    "wof:name":"De Rut",
    "wof:placetype":"venue"
},
  "geometry": {"coordinates":[4.4706268311,50.9760627747],"type":"Point"}
}