{
  "type": "Feature",
  "properties": {
    "iso:country":"BE",
    "sg:address":"Oud-dorpsstraat 136 Box 5",
    "sg:city":"Wuustwezel (loenhout)",
    "sg:classifiers":[
        {
            "category":"Real Estate",
            "subcategory":"Architect",
            "type":"Services"
        }
    ],
    "sg:phone":"+32 3 669 80 99",
    "sg:postcode":"2990",
    "sg:province":"Antwerpen",
    "wof:name":"Van Dijck P",
    "wof:placetype":"venue"
},
  "geometry": {"coordinates":[4.5983700752,51.3888816833],"type":"Point"}
}