{
  "type": "Feature",
  "properties": {
    "iso:country":"BE",
    "sg:address":"Avenue Eug\u00c8ne Ysaye 33",
    "sg:city":"Anderlecht/anderlecht",
    "sg:orig_category":"Agences immobili\u00e8res",
    "sg:phone":"+32 2 558 14 90",
    "sg:postcode":"1070",
    "sg:province":"Bruxelles-Capitale",
    "wof:name":"Bureau Dal Construct",
    "wof:placetype":"venue"
},
  "geometry": {"coordinates":[4.2961168289,50.8310813904],"type":"Point"}
}