{
  "type": "Feature",
  "properties": {
    "addr:full":"Ninoofsesteenweg 1009 Dilbeek Vlaams-Brabant 1703",
    "addr:housenumber":"1009",
    "addr:postcode":"1703",
    "addr:street":"Ninoofsesteenweg",
    "iso:country":"BE",
    "sg:address":"Ninoofsesteenweg 1009",
    "sg:city":"Dilbeek",
    "sg:orig_category":"Dancings and bo\u00eetes de nuit",
    "sg:phone":"+32 2 569 22 39",
    "sg:postcode":"1703",
    "sg:province":"Vlaams-Brabant",
    "wof:name":"Salons The Lord",
    "wof:placetype":"venue"
},
  "geometry": {"coordinates":[4.1886401176,50.83776474],"type":"Point"}
}