{
  "type": "Feature",
  "properties": {
    "addr:full":"Rue Winston Churchill 383 Courcelles Hainaut 6180",
    "addr:housenumber":"383",
    "addr:postcode":"6180",
    "addr:street":"Rue Winston Churchill",
    "iso:country":"BE",
    "sg:address":"Rue Winston Churchill 383",
    "sg:city":"Courcelles",
    "sg:classifiers":[
        {
            "category":"Wholesale",
            "subcategory":"Sporting Goods",
            "type":"Manufacturing & Wholesale Goods"
        }
    ],
    "sg:phone":"+32 71 46 09 64",
    "sg:postcode":"6180",
    "sg:province":"Hainaut",
    "sg:tags":[
        "windsurfing",
        "accessory"
    ],
    "wof:name":"Charleroi Marine",
    "wof:placetype":"venue"
},
  "geometry": {"coordinates":[4.3995900154,50.4623985291],"type":"Point"}
}