{
  "type": "Feature",
  "properties": {
    "addr:full":"Gentweg 18a Evergem Oost-Vlaanderen 9940",
    "addr:housenumber":"18a",
    "addr:postcode":"9940",
    "addr:street":"Gentweg;Oost-Vlaanderen",
    "iso:country":"BE",
    "sg:address":"Gentweg 18a",
    "sg:city":"Evergem",
    "sg:classifiers":[
        {
            "category":"Utilities",
            "subcategory":"Recycling",
            "type":"Services"
        }
    ],
    "sg:phone":"+32 9 369 82 62",
    "sg:postcode":"9940",
    "sg:province":"Oost-Vlaanderen",
    "sg:tags":[
        "plastic"
    ],
    "wof:name":"Areb Nv",
    "wof:placetype":"venue"
},
  "geometry": {"coordinates":[3.7457680702,51.1173629761],"type":"Point"}
}