{
  "type": "Feature",
  "properties": {
    "iso:country":"BE",
    "sg:address":"Ossebergstraat 25",
    "sg:city":"Zutendaal",
    "sg:orig_category":"M\u00e9decins and sp\u00e9cialistes",
    "sg:phone":"+32 89 62 24 34",
    "sg:postcode":"3690",
    "sg:province":"Limburg",
    "wof:name":"Veerle Roussard",
    "wof:placetype":"venue"
},
  "geometry": {"coordinates":[5.579624176,50.9323043823],"type":"Point"}
}