{
  "type": "Feature",
  "properties": {
    "iso:country":"BE",
    "sg:address":"L\u00e9once Roelsstraat 7",
    "sg:city":"Zottegem",
    "sg:classifiers":[
        {
            "category":"Health Services",
            "subcategory":"Dentist",
            "type":"Services"
        }
    ],
    "sg:phone":"+32 9 360 11 30",
    "sg:postcode":"9620",
    "sg:province":"Oost-Vlaanderen",
    "wof:name":"Caekebeke Peter",
    "wof:placetype":"venue"
},
  "geometry": {"coordinates":[3.8130440712,50.8652763367],"type":"Point"}
}