{
  "type": "Feature",
  "properties": {
    "addr:full":"Bredaseweg 18 Hoogstraten (minderhout) Antwerpen 2322",
    "addr:housenumber":"18",
    "addr:postcode":"2322",
    "addr:street":"Bredaseweg",
    "iso:country":"BE",
    "sg:address":"Bredaseweg 18",
    "sg:city":"Hoogstraten (minderhout)",
    "sg:classifiers":[
        {
            "category":"Building & Trades",
            "subcategory":"Landscaping Services",
            "type":"Services"
        }
    ],
    "sg:phone":"+32 3 315 81 67",
    "sg:postcode":"2322",
    "sg:province":"Antwerpen",
    "sg:tags":[
        "gardening",
        "garden",
        "maintenance"
    ],
    "wof:name":"Bartholomeeusen J",
    "wof:placetype":"venue"
},
  "geometry": {"coordinates":[4.763384819,51.4160041809],"type":"Point"}
}