{
  "type": "Feature",
  "properties": {
    "iso:country":"BE",
    "sg:address":"Rue Des Carri\u00c8res 4",
    "sg:city":"Froidchapelle",
    "sg:orig_category":"Vins Fab. Distilleries",
    "sg:phone":"+32 71 63 35 11",
    "sg:postcode":"6440",
    "sg:province":"Hainaut",
    "wof:name":"La Ruchette",
    "wof:placetype":"venue"
},
  "geometry": {"coordinates":[4.3734288216,50.2149543762],"type":"Point"}
}