{
  "type": "Feature",
  "properties": {
    "iso:country":"BE",
    "sg:address":"Groenstraat 11",
    "sg:city":"Bierbeek",
    "sg:orig_category":"M\u00e9decins and sp\u00e9cialistes",
    "sg:phone":"+32 16 46 28 19",
    "sg:postcode":"3360",
    "sg:province":"Vlaams-Brabant",
    "wof:name":"Geertrui Craeynest",
    "wof:placetype":"venue"
},
  "geometry": {"coordinates":[4.7882370949,50.8448791504],"type":"Point"}
}