{
  "type": "Feature",
  "properties": {
    "iso:country":"BE",
    "sg:address":"Hofdreef 93",
    "sg:city":"Wuustwezel (loenhout)",
    "sg:classifiers":[
        {
            "category":"Banks & Credit Unions",
            "subcategory":"Bureau De Change",
            "type":"Services"
        }
    ],
    "sg:phone":"+32 3 669 75 07",
    "sg:postcode":"2990",
    "sg:province":"Antwerpen",
    "sg:tags":[
        "-",
        "household",
        "gas"
    ],
    "wof:name":"Van Aelst",
    "wof:placetype":"venue"
},
  "geometry": {"coordinates":[4.6318030357,51.401599884],"type":"Point"}
}