{
  "type": "Feature",
  "properties": {
    "iso:country":"BE",
    "sg:address":"Diependaelweg 11",
    "sg:city":"Riemst",
    "sg:orig_category":"Charpentes and couvertures",
    "sg:phone":"+32 12 45 53 03",
    "sg:postcode":"3770",
    "sg:province":"Limburg",
    "wof:name":"Haesen Pierre Dakwerken",
    "wof:placetype":"venue"
},
  "geometry": {"coordinates":[5.6490168571,50.8321609497],"type":"Point"}
}