{
  "type": "Feature",
  "properties": {
    "iso:country":"BE",
    "sg:address":"Kronevoordestraat 47",
    "sg:city":"Kortemark",
    "sg:orig_category":"Supermarch\u00e9s",
    "sg:phone":"+32 51 56 88 33",
    "sg:postcode":"8610",
    "sg:province":"West-Vlaanderen",
    "wof:name":"Unic",
    "wof:placetype":"venue"
},
  "geometry": {"coordinates":[3.0040779114,51.0214271545],"type":"Point"}
}