{
  "type": "Feature",
  "properties": {
    "iso:country":"BE",
    "sg:address":"Rue Du Nouveau Monde 106",
    "sg:city":"Mouscron",
    "sg:classifiers":[
        {
            "category":"Food & Beverages",
            "subcategory":"Fruits & Vegetables",
            "type":"Retail Goods"
        }
    ],
    "sg:phone":"+32 56 34 19 18",
    "sg:postcode":"7700",
    "sg:province":"Hainaut",
    "sg:tags":[
        "-"
    ],
    "wof:name":"Myriam & Danny",
    "wof:placetype":"venue"
},
  "geometry": {"coordinates":[3.2044870853,50.7466087341],"type":"Point"}
}