{
  "type": "Feature",
  "properties": {
    "addr:full":"Rue De L'industrie 2 La Louviere Hainaut 7100",
    "addr:housenumber":"2",
    "addr:postcode":"7100",
    "addr:street":"Rue De L'Industrie",
    "iso:country":"BE",
    "sg:address":"Rue De L'industrie 2",
    "sg:city":"La Louviere",
    "sg:orig_category":"MEUBELONTWERP AND -INSTALLATIE",
    "sg:phone":"+32 64 28 44 95",
    "sg:postcode":"7100",
    "sg:province":"Hainaut",
    "wof:name":"C.g.p. Entreprise",
    "wof:placetype":"venue"
},
  "geometry": {"coordinates":[4.2147631645,50.4644012451],"type":"Point"}
}