{
  "type": "Feature",
  "properties": {
    "iso:country":"BE",
    "sg:address":"Dijkstraat 17",
    "sg:city":"Mol",
    "sg:orig_category":"Viessmann. Plomberie, chauffage and installations sanitaires",
    "sg:phone":"+32 14 31 74 21",
    "sg:postcode":"2400",
    "sg:province":"Antwerpen",
    "wof:name":"Kahn R",
    "wof:placetype":"venue"
},
  "geometry": {"coordinates":[5.1547551155,51.213092804],"type":"Point"}
}