{
  "type": "Feature",
  "properties": {
    "addr:full":"Ruelle Des Vieux Foss\u00e9s 11 Wavre Brabant Wallon 1300",
    "addr:housenumber":"11;1300",
    "addr:street":"Ruelle Des Vieux Fosse\u0301S",
    "iso:country":"BE",
    "sg:address":"Ruelle Des Vieux Foss\u00e9s 11",
    "sg:city":"Wavre",
    "sg:classifiers":[
        {
            "category":"Professional",
            "subcategory":"Art Services",
            "type":"Services"
        }
    ],
    "sg:phone":"+32 10 24 86 88",
    "sg:postcode":"1300",
    "sg:province":"Brabant Wallon",
    "sg:tags":[
        "automobile",
        "transit",
        "-",
        "export",
        "import"
    ],
    "wof:name":"Redfil Sprl",
    "wof:placetype":"venue"
},
  "geometry": {"coordinates":[4.6105389595,50.7178573608],"type":"Point"}
}