{
  "type": "Feature",
  "properties": {
    "iso:country":"BE",
    "sg:address":"32-34 Opstalstraat",
    "sg:city":"Desselgem",
    "sg:classifiers":[
        {
            "category":"Shopping",
            "subcategory":"Hobbies, Toys, & Games",
            "type":"Retail Goods"
        }
    ],
    "sg:phone":"+32 56 71 21 97",
    "sg:postcode":"8792",
    "sg:province":"West-Vlaanderen",
    "sg:tags":[
        "product",
        "miscellaneous",
        "entertainment"
    ],
    "wof:name":"Dhondt Hobby- Products Bvba",
    "wof:placetype":"venue"
},
  "geometry": {"coordinates":[3.3687169552,50.8922233582],"type":"Point"}
}