{
  "type": "Feature",
  "properties": {
    "addr:full":"Rue De Belle Vue 15 La Louvi\u00e8re Hainaut 7100",
    "addr:housenumber":"15",
    "addr:postcode":"7100",
    "addr:street":"Rue De Belle Vue",
    "iso:country":"BE",
    "sg:address":"Rue De Belle Vue 15",
    "sg:city":"La Louvi\u00e8re",
    "sg:classifiers":[
        {
            "category":"Professional",
            "subcategory":"Computer Services",
            "type":"Services"
        }
    ],
    "sg:phone":"+32 64 84 81 56",
    "sg:postcode":"7100",
    "sg:province":"Hainaut",
    "sg:tags":[
        "-",
        "processing",
        "data"
    ],
    "wof:name":"C.g.n. Informatique",
    "wof:placetype":"venue"
},
  "geometry": {"coordinates":[4.1873278618,50.4744758606],"type":"Point"}
}