{
  "type": "Feature",
  "properties": {
    "addr:full":"Grand Breucq 10 Celles Hainaut 7760",
    "addr:housenumber":"10",
    "addr:postcode":"7760",
    "addr:street":"Breucq",
    "iso:country":"BE",
    "sg:address":"Grand Breucq 10",
    "sg:city":"Celles",
    "sg:orig_category":"V\u00e9t\u00e9rinaires",
    "sg:phone":"+32 69 45 41 32",
    "sg:postcode":"7760",
    "sg:province":"Hainaut",
    "wof:name":"Ghislain Moyart",
    "wof:placetype":"venue"
},
  "geometry": {"coordinates":[3.4337570667,50.7372055054],"type":"Point"}
}