{
  "type": "Feature",
  "properties": {
    "addr:full":"Raas Van Gaverestraat 35 Gent Oost-Vlaanderen 9000",
    "addr:housenumber":"35",
    "addr:postcode":"9000",
    "addr:street":"Raas;Gaverestraat;Oost-Vlaanderen",
    "iso:country":"BE",
    "sg:address":"Raas Van Gaverestraat 35",
    "sg:city":"Gent",
    "sg:classifiers":[
        {
            "category":"Professional",
            "subcategory":"Computer Services",
            "type":"Services"
        }
    ],
    "sg:phone":"+32 9 223 74 34",
    "sg:postcode":"9000",
    "sg:province":"Oost-Vlaanderen",
    "sg:tags":[
        "-",
        "processing",
        "data",
        "software"
    ],
    "wof:name":"Eggermont G",
    "wof:placetype":"venue"
},
  "geometry": {"coordinates":[3.7086598873,51.0505752563],"type":"Point"}
}