{
  "type": "Feature",
  "properties": {
    "iso:country":"BE",
    "sg:address":"Elfde Novemberwal 13",
    "sg:city":"Tongeren",
    "sg:classifiers":[
        {
            "category":"Professional",
            "subcategory":"Lawyer & Legal Services",
            "type":"Services"
        }
    ],
    "sg:phone":"+32 12 23 29 54",
    "sg:postcode":"3700",
    "sg:province":"Limburg",
    "wof:name":"Leenders Patrick",
    "wof:placetype":"venue"
},
  "geometry": {"coordinates":[5.4647459984,50.7834472656],"type":"Point"}
}