{
  "type": "Feature",
  "properties": {
    "addr:full":"Daloensdelle 29 Overijse Vlaams-Brabant 3090",
    "addr:housenumber":"29",
    "addr:postcode":"3090",
    "addr:street":"Daloensdelle",
    "iso:country":"BE",
    "sg:address":"Daloensdelle 29",
    "sg:city":"Overijse",
    "sg:classifiers":[
        {
            "category":"Professional",
            "subcategory":"Management & Consulting",
            "type":"Services"
        }
    ],
    "sg:phone":"+32 2 687 81 19",
    "sg:postcode":"3090",
    "sg:province":"Vlaams-Brabant",
    "sg:tags":[
        "consultant"
    ],
    "wof:name":"Verbraeken H",
    "wof:placetype":"venue"
},
  "geometry": {"coordinates":[4.5377340317,50.7648658752],"type":"Point"}
}