{
  "type": "Feature",
  "properties": {
    "iso:country":"BE",
    "sg:address":"Rue Grande 1",
    "sg:city":"Honnelles",
    "sg:orig_category":"Werk and personeelsselectie",
    "sg:phone":"+32 65 75 92 22",
    "sg:postcode":"7387",
    "sg:province":"Hainaut",
    "wof:name":"Ale Honnelles",
    "wof:placetype":"venue"
},
  "geometry": {"coordinates":[3.7353589535,50.3490104675],"type":"Point"}
}