{
  "type": "Feature",
  "properties": {
    "addr:full":"Rue De La Station 20 Frameries Hainaut 7080",
    "addr:housenumber":"20",
    "addr:postcode":"7080",
    "addr:street":"Rue De La Station",
    "iso:country":"BE",
    "sg:address":"Rue De La Station 20",
    "sg:city":"Frameries",
    "sg:classifiers":[
        {
            "category":"Personal",
            "subcategory":"Nail Salon",
            "type":"Services"
        }
    ],
    "sg:phone":"+32 65 66 46 08",
    "sg:postcode":"7080",
    "sg:province":"Hainaut",
    "sg:tags":[
        "pedicure"
    ],
    "wof:name":"Dufrane P",
    "wof:placetype":"venue"
},
  "geometry": {"coordinates":[3.904294014,50.4090919495],"type":"Point"}
}