{
  "type": "Feature",
  "properties": {
    "addr:full":"Mechelsestraat 34 Leuven Vlaams-Brabant 3000",
    "addr:housenumber":"34",
    "addr:postcode":"3000",
    "addr:street":"Mechelsestraat",
    "iso:country":"BE",
    "sg:address":"Mechelsestraat 34",
    "sg:city":"Leuven",
    "sg:classifiers":[
        {
            "category":"Shopping",
            "subcategory":"Clothing, Apparel, & Fashions",
            "type":"Retail Goods"
        }
    ],
    "sg:phone":"+32 16 23 41 04",
    "sg:postcode":"3000",
    "sg:province":"Vlaams-Brabant",
    "sg:tags":[
        "clothing",
        "-",
        "gentleman"
    ],
    "wof:name":"Jonas Herenkleding",
    "wof:placetype":"venue"
},
  "geometry": {"coordinates":[4.7000999451,50.8807907104],"type":"Point"}
}