{
  "type": "Feature",
  "properties": {
    "iso:country":"BE",
    "sg:address":"Du Montstraat 2",
    "sg:city":"Antwerpen (deurne)",
    "sg:classifiers":[
        {
            "category":"Bars & Pubs",
            "type":"Food & Drink"
        }
    ],
    "sg:phone":"+32 3 326 12 16",
    "sg:postcode":"2100",
    "sg:province":"Antwerpen",
    "wof:name":"Kerkeveld",
    "wof:placetype":"venue"
},
  "geometry": {"coordinates":[4.4598360062,51.2264213562],"type":"Point"}
}