{
  "type": "Feature",
  "properties": {
    "addr:full":"Rue De Li\u00e8ge 48 Lixhe Li\u00e8ge 4600",
    "addr:housenumber":"48",
    "addr:postcode":"4600",
    "addr:street":"Rue De Lie\u0300Ge",
    "iso:country":"BE",
    "sg:address":"Rue De Li\u00e8ge 48",
    "sg:city":"Lixhe",
    "sg:classifiers":[
        {
            "category":"Building & Trades",
            "subcategory":"Construction",
            "type":"Services"
        }
    ],
    "sg:phone":"+32 4 379 15 62",
    "sg:postcode":"4600",
    "sg:province":"Li\u00e8ge",
    "sg:tags":[
        "work",
        "public"
    ],
    "wof:name":"Jean Pierre Tasset Sprl",
    "wof:placetype":"venue"
},
  "geometry": {"coordinates":[5.6805357933,50.7612762451],"type":"Point"}
}