{
  "type": "Feature",
  "properties": {
    "addr:full":"Heirstraat 10 Kruibeke Oost-Vlaanderen 9150",
    "addr:housenumber":"10",
    "addr:postcode":"9150",
    "addr:street":"Heirstraat",
    "iso:country":"BE",
    "sg:address":"Heirstraat 10",
    "sg:city":"Kruibeke",
    "sg:classifiers":[
        {
            "category":"Cafe",
            "type":"Food & Drink"
        }
    ],
    "sg:phone":"+32 3 774 03 37",
    "sg:postcode":"9150",
    "sg:province":"Oost-Vlaanderen",
    "sg:tags":[
        "caf\u00e9s"
    ],
    "wof:name":"Marie Stevens",
    "wof:placetype":"venue"
},
  "geometry": {"coordinates":[4.2593078613,51.1447143555],"type":"Point"}
}