{
  "type": "Feature",
  "properties": {
    "iso:country":"BE",
    "sg:address":"Sint-pietersstraat 16",
    "sg:city":"Diksmuide (woumen)",
    "sg:classifiers":[
        {
            "category":"Health Services",
            "subcategory":"Dentist",
            "type":"Services"
        }
    ],
    "sg:phone":"+32 51 50 06 99",
    "sg:postcode":"8600",
    "sg:province":"West-Vlaanderen",
    "wof:name":"Bouckenooghe I",
    "wof:placetype":"venue"
},
  "geometry": {"coordinates":[2.8724060059,50.9963417053],"type":"Point"}
}