{
  "type": "Feature",
  "properties": {
    "iso:country":"BE",
    "sg:address":"Stijn Streuvelslaan 60",
    "sg:city":"Kortrijk (heule)",
    "sg:classifiers":[
        {
            "category":"Health Services",
            "subcategory":"Health Practitioner",
            "type":"Services"
        }
    ],
    "sg:phone":"+32 56 35 62 63",
    "sg:postcode":"8501",
    "sg:province":"West-Vlaanderen",
    "sg:tags":[
        "physiotherapist"
    ],
    "wof:name":"Vergote Luc",
    "wof:placetype":"venue"
},
  "geometry": {"coordinates":[3.2369120121,50.8414306641],"type":"Point"}
}