{
  "type": "Feature",
  "properties": {
    "addr:full":"Kleine Snijderstraat 30 Lebbeke Oost-Vlaanderen 9280",
    "addr:housenumber":"30",
    "addr:postcode":"9280",
    "addr:street":"Kleine Snijderstraat",
    "iso:country":"BE",
    "sg:address":"Kleine Snijderstraat 30",
    "sg:city":"Lebbeke",
    "sg:orig_category":"Parfumeries",
    "sg:phone":"+32 52 41 46 18",
    "sg:postcode":"9280",
    "sg:province":"Oost-Vlaanderen",
    "wof:name":"Fernand Tas",
    "wof:placetype":"venue"
},
  "geometry": {"coordinates":[4.1491370201,51.0064926147],"type":"Point"}
}