{
  "type": "Feature",
  "properties": {
    "addr:full":"Hoge Mauw 11 Arendonk Antwerpen 2370",
    "addr:housenumber":"11",
    "addr:postcode":"2370",
    "addr:street":"Hoge Mauw",
    "iso:country":"BE",
    "sg:address":"Hoge Mauw 11",
    "sg:city":"Arendonk",
    "sg:classifiers":[
        {
            "category":"Structure",
            "subcategory":"Bridge",
            "type":"Public Place"
        }
    ],
    "sg:phone":"+32 3 820 40 11",
    "sg:postcode":"2370",
    "sg:province":"Antwerpen",
    "sg:tags":[
        "construction"
    ],
    "wof:name":"Maatschappij Voor Bouw- En Grondwerken Nv",
    "wof:placetype":"venue"
},
  "geometry": {"coordinates":[4.3948969841,51.1746673584],"type":"Point"}
}