{
  "type": "Feature",
  "properties": {
    "addr:full":"Oordegemsesteenweg 119 Wetteren Oost-Vlaanderen 9230",
    "addr:housenumber":"119",
    "addr:postcode":"9230",
    "addr:street":"Oordegemsesteenweg",
    "iso:country":"BE",
    "sg:address":"Oordegemsesteenweg 119",
    "sg:city":"Wetteren",
    "sg:classifiers":[
        {
            "category":"Shopping",
            "subcategory":"Clothing, Apparel, & Fashions",
            "type":"Retail Goods"
        }
    ],
    "sg:phone":"+32 9 369 12 65",
    "sg:postcode":"9230",
    "sg:province":"Oost-Vlaanderen",
    "sg:tags":[
        "lingerie",
        "sous-v\u00eatements"
    ],
    "wof:name":"A. Bontinck",
    "wof:placetype":"venue"
},
  "geometry": {"coordinates":[3.8859291077,50.9976615906],"type":"Point"}
}