{
  "type": "Feature",
  "properties": {
    "addr:full":"Iveldingen 60 Amel/ambleve Li\u00e8ge 4770",
    "addr:housenumber":"60",
    "addr:postcode":"4770",
    "addr:street":"Iveldingen",
    "iso:country":"BE",
    "sg:address":"Iveldingen 60",
    "sg:city":"Amel/ambleve",
    "sg:classifiers":[
        {
            "category":"Insurance",
            "subcategory":"Insurance Agent",
            "type":"Services"
        }
    ],
    "sg:phone":"+32 80 34 91 60",
    "sg:postcode":"4770",
    "sg:province":"Li\u00e8ge",
    "sg:tags":[
        "verzekeringsmakelaars",
        "expert"
    ],
    "wof:name":"Schroeder Frank",
    "wof:placetype":"venue"
},
  "geometry": {"coordinates":[6.1876211166,50.3251914978],"type":"Point"}
}