{
  "type": "Feature",
  "properties": {
    "iso:country":"BE",
    "sg:address":"Rue Du Luxembourg 38",
    "sg:city":"Marche-en-famenne",
    "sg:classifiers":[
        {
            "category":"Health Services",
            "subcategory":"Doctor",
            "type":"Services"
        }
    ],
    "sg:phone":"+32 84 31 56 60",
    "sg:postcode":"6900",
    "sg:province":"Luxembourg",
    "sg:tags":[
        "medicinephysicians",
        "surgeon"
    ],
    "wof:name":"Delreux Vincent",
    "wof:placetype":"venue"
},
  "geometry": {"coordinates":[5.3457231522,50.2233810425],"type":"Point"}
}