{
  "type": "Feature",
  "properties": {
    "iso:country":"BE",
    "sg:address":"Tongersesteenweg 131",
    "sg:city":"Borgloon",
    "sg:orig_category":"Kapsalons Mobiele kappers",
    "sg:phone":"+32 12 74 27 82",
    "sg:postcode":"3840",
    "sg:province":"Limburg",
    "wof:name":"Guillaume Vandenrhijn",
    "wof:placetype":"venue"
},
  "geometry": {"coordinates":[5.3585758209,50.799243927],"type":"Point"}
}