{
  "type": "Feature",
  "properties": {
    "iso:country":"BE",
    "sg:address":"Hasseltsesteenweg 623",
    "sg:city":"Tongeren",
    "sg:orig_category":"Fruitteelt Rundveehouders",
    "sg:phone":"+32 12 23 10 17",
    "sg:postcode":"3700",
    "sg:province":"Limburg",
    "wof:name":"Paul Deploige",
    "wof:placetype":"venue"
},
  "geometry": {"coordinates":[5.459335804,50.7829055786],"type":"Point"}
}