{
  "type": "Feature",
  "properties": {
    "addr:full":"Grand Route 20 Hotton (marenne) Luxembourg 6990",
    "addr:postcode":"6990",
    "addr:street":"Grand Route 20",
    "iso:country":"BE",
    "sg:address":"Grand Route 20",
    "sg:city":"Hotton (marenne)",
    "sg:classifiers":[
        {
            "category":"Building & Trades",
            "subcategory":"Construction",
            "type":"Services"
        }
    ],
    "sg:phone":"+32 84 32 15 11",
    "sg:postcode":"6990",
    "sg:province":"Luxembourg",
    "sg:tags":[
        "carpenter"
    ],
    "wof:name":"Delgombe M.e.s. Sprl",
    "wof:placetype":"venue"
},
  "geometry": {"coordinates":[5.3978800774,50.2483329773],"type":"Point"}
}