{
  "type": "Feature",
  "properties": {
    "iso:country":"BE",
    "sg:address":"Tulpinstraat 75",
    "sg:city":"Hasselt",
    "sg:classifiers":[
        {
            "category":"Education",
            "subcategory":"University",
            "type":"Public Place"
        }
    ],
    "sg:phone":"+32 11 21 24 32",
    "sg:postcode":"3500",
    "sg:province":"Limburg",
    "sg:tags":[
        "higher"
    ],
    "wof:name":"Grootseminarie",
    "wof:placetype":"venue"
},
  "geometry": {"coordinates":[5.3654680252,50.9584350586],"type":"Point"}
}