{
  "type": "Feature",
  "properties": {
    "addr:full":"Damberdstraat 24 Wevelgem West-Vlaanderen 8560",
    "addr:housenumber":"24",
    "addr:postcode":"8560",
    "addr:street":"Damberdstraat",
    "iso:country":"BE",
    "sg:address":"Damberdstraat 24",
    "sg:city":"Wevelgem",
    "sg:orig_category":"Banques and organismes de cr\u00e9dit",
    "sg:phone":"+32 56 41 61 94",
    "sg:postcode":"8560",
    "sg:province":"West-Vlaanderen",
    "wof:name":"Bacob",
    "wof:placetype":"venue"
},
  "geometry": {"coordinates":[3.1625630856,50.8394393921],"type":"Point"}
}