{
  "type": "Feature",
  "properties": {
    "addr:full":"Rue Saint-l\u00e9onard 234 Li\u00e8ge 1 Li\u00e8ge 4000",
    "addr:housenumber":"234;1",
    "addr:postcode":"4000",
    "addr:street":"Rue Saint-Le\u0301Onard",
    "iso:country":"BE",
    "sg:address":"Rue Saint-l\u00e9onard 234",
    "sg:city":"Li\u00e8ge 1",
    "sg:classifiers":[
        {
            "category":"Building & Trades",
            "subcategory":"Equipment Rental",
            "type":"Services"
        }
    ],
    "sg:phone":"+32 4 227 23 00",
    "sg:postcode":"4000",
    "sg:province":"Li\u00e8ge",
    "sg:tags":[
        "sound",
        "-",
        "system"
    ],
    "wof:name":"Engrenage Sprl",
    "wof:placetype":"venue"
},
  "geometry": {"coordinates":[5.5917329788,50.6492881775],"type":"Point"}
}