{
  "type": "Feature",
  "properties": {
    "addr:full":"Kapellestraat 76 Aartselaar Antwerpen 2630",
    "addr:housenumber":"76",
    "addr:postcode":"2630",
    "addr:street":"Kapellestraat",
    "iso:country":"BE",
    "sg:address":"Kapellestraat 76",
    "sg:city":"Aartselaar",
    "sg:classifiers":[
        {
            "category":"Personal",
            "subcategory":"Beauty Salon",
            "type":"Services"
        }
    ],
    "sg:phone":"+32 3 887 60 82",
    "sg:postcode":"2630",
    "sg:province":"Antwerpen",
    "sg:tags":[
        "de",
        "coiffure"
    ],
    "wof:name":"Hairstyle Juve",
    "wof:placetype":"venue"
},
  "geometry": {"coordinates":[4.3891749382,51.1308135986],"type":"Point"}
}