{
  "type": "Feature",
  "properties": {
    "addr:full":"Dam 71 Kortrijk West-Vlaanderen 8500",
    "addr:housenumber":"71",
    "addr:postcode":"8500",
    "addr:street":"Dam",
    "iso:country":"BE",
    "sg:address":"Dam 71",
    "sg:city":"Kortrijk",
    "sg:orig_category":"Avocats and conseillers juridiques",
    "sg:phone":"+32 56 21 31 58",
    "sg:postcode":"8500",
    "sg:province":"West-Vlaanderen",
    "wof:name":"Ilse Algoet",
    "wof:placetype":"venue"
},
  "geometry": {"coordinates":[3.2668159008,50.8316421509],"type":"Point"}
}