{
  "type": "Feature",
  "properties": {
    "addr:full":"Av. De For\u00cat De Soignes 300 Sint-genesius-rode/rhode-saint-genese Vlaams-Brabant 1640",
    "addr:housenumber":"300",
    "addr:postcode":"1640",
    "addr:street":"Av. De Fore\u0302T De Soignes",
    "iso:country":"BE",
    "sg:address":"Av. De For\u00cat De Soignes 300",
    "sg:city":"Sint-genesius-rode/rhode-saint-genese",
    "sg:orig_category":"M\u00e9decins and sp\u00e9cialistes",
    "sg:phone":"+32 2 358 59 90",
    "sg:postcode":"1640",
    "sg:province":"Vlaams-Brabant",
    "wof:name":"Isabelle Telerman",
    "wof:placetype":"venue"
},
  "geometry": {"coordinates":[4.3776011467,50.7559738159],"type":"Point"}
}