{
  "type": "Feature",
  "properties": {
    "addr:full":"Bergstraat 79 Kortrijk (groot) West-Vlaanderen 8500",
    "addr:housenumber":"79",
    "addr:postcode":"8500",
    "addr:street":"Bergstraat;Groot West-Vlaanderen",
    "iso:country":"BE",
    "sg:address":"Bergstraat 79",
    "sg:city":"Kortrijk (groot)",
    "sg:orig_category":"Waterzuivering",
    "sg:phone":"+32 56 41 44 33",
    "sg:postcode":"8500",
    "sg:province":"West-Vlaanderen",
    "wof:name":"Battaille Raf",
    "wof:placetype":"venue"
},
  "geometry": {"coordinates":[3.2393229008,50.7758331299],"type":"Point"}
}