{
  "type": "Feature",
  "properties": {
    "addr:full":"Karperstraat 12 Torhout (wijnendale) West-Vlaanderen 8820",
    "addr:housenumber":"12",
    "addr:postcode":"8820",
    "addr:street":"Karperstraat",
    "iso:country":"BE",
    "sg:address":"Karperstraat 12",
    "sg:city":"Torhout (wijnendale)",
    "sg:classifiers":[
        {
            "category":"Building & Trades",
            "subcategory":"Landscaping Services",
            "type":"Services"
        }
    ],
    "sg:phone":"+32 50 21 45 48",
    "sg:postcode":"8820",
    "sg:province":"West-Vlaanderen",
    "sg:tags":[
        "slaughterer"
    ],
    "wof:name":"Bolle R",
    "wof:placetype":"venue"
},
  "geometry": {"coordinates":[3.0715610981,51.0935935974],"type":"Point"}
}