{
  "type": "Feature",
  "properties": {
    "iso:country":"BE",
    "sg:address":"Martelarenstraat 59 Box 1",
    "sg:city":"Mol",
    "sg:classifiers":[
        {
            "category":"Insurance",
            "subcategory":"Insurance Agent",
            "type":"Services"
        }
    ],
    "sg:phone":"+32 14 31 27 37",
    "sg:postcode":"2400",
    "sg:province":"Antwerpen",
    "sg:tags":[
        "broker"
    ],
    "wof:name":"Saenen",
    "wof:placetype":"venue"
},
  "geometry": {"coordinates":[5.0982937813,51.1862487793],"type":"Point"}
}