{
  "type": "Feature",
  "properties": {
    "iso:country":"BE",
    "sg:address":"Bruggesteenweg 48",
    "sg:city":"Ruiselede",
    "sg:orig_category":"Production de films, t\u00e9l\u00e9films and vid\u00e9os. Secr\u00e9tariats",
    "sg:phone":"+32 51 68 73 07",
    "sg:postcode":"8755",
    "sg:province":"West-Vlaanderen",
    "wof:name":"2b",
    "wof:placetype":"venue"
},
  "geometry": {"coordinates":[3.3770530224,51.0573959351],"type":"Point"}
}