{
  "type": "Feature",
  "properties": {
    "iso:country":"BE",
    "sg:address":"Etikhoveplein 1",
    "sg:city":"Maarkedal",
    "sg:orig_category":"Caf\u00e9s Dranken",
    "sg:phone":"+32 55 31 44 67",
    "sg:postcode":"9680",
    "sg:province":"Oost-Vlaanderen",
    "wof:name":"Caf\u00c9 Arendshof",
    "wof:placetype":"venue"
},
  "geometry": {"coordinates":[3.6264619827,50.8124313354],"type":"Point"}
}