{
  "type": "Feature",
  "properties": {
    "addr:full":"De Kerchove D\u00b4exaerdestr 19 Halle Vlaams-Brabant 1501",
    "addr:housenumber":"19",
    "addr:postcode":"1501",
    "addr:street":"De Kerchove D\u00b4Exaerdestr",
    "iso:country":"BE",
    "sg:address":"De Kerchove D\u00b4exaerdestr 19",
    "sg:city":"Halle",
    "sg:orig_category":"Herstellingen and onderhoud van auto's",
    "sg:phone":"+32 2 361 19 77",
    "sg:postcode":"1501",
    "sg:province":"Vlaams-Brabant",
    "wof:name":"Carrosserie L.d.k.",
    "wof:placetype":"venue"
},
  "geometry": {"coordinates":[4.2506008148,50.7414703369],"type":"Point"}
}