{
  "type": "Feature",
  "properties": {
    "addr:full":"Nieuwstraat 57 Hamont-achel Limburg 3930",
    "addr:housenumber":"57",
    "addr:postcode":"3930",
    "addr:street":"Nieuwstraat",
    "iso:country":"BE",
    "sg:address":"Nieuwstraat 57",
    "sg:city":"Hamont-achel",
    "sg:orig_category":"Plaatsen van vloer- and muurbekleding Schilders",
    "sg:phone":"+32 11 44 84 12",
    "sg:postcode":"3930",
    "sg:province":"Limburg",
    "wof:name":"Schilderwerken Michel",
    "wof:placetype":"venue"
},
  "geometry": {"coordinates":[5.5450549126,51.2511863708],"type":"Point"}
}