{
  "type": "Feature",
  "properties": {
    "iso:country":"BE",
    "sg:address":"Van Hembdenstraat 28",
    "sg:city":"Oostende",
    "sg:classifiers":[
        {
            "category":"Professional",
            "subcategory":"Detective & Security Services",
            "type":"Services"
        }
    ],
    "sg:phone":"+32 59 33 35 97",
    "sg:postcode":"8400",
    "sg:province":"West-Vlaanderen",
    "sg:tags":[
        "fab",
        "de",
        "travail",
        "v\u00eatements",
        "protection"
    ],
    "wof:name":"Triton Alfa",
    "wof:placetype":"venue"
},
  "geometry": {"coordinates":[2.9479570389,51.2330284119],"type":"Point"}
}