{
  "type": "Feature",
  "properties": {
    "iso:country":"BE",
    "sg:address":"Moorstraat 26",
    "sg:city":"Nevele",
    "sg:orig_category":"Herstellingen and onderhoud van auto's Voertuigen",
    "sg:phone":"+32 9 282 74 89",
    "sg:postcode":"9850",
    "sg:province":"Oost-Vlaanderen",
    "wof:name":"Garage Huysman",
    "wof:placetype":"venue"
},
  "geometry": {"coordinates":[3.5827798843,51.0530395508],"type":"Point"}
}