{
  "type": "Feature",
  "properties": {
    "addr:full":"Avenue Winston Churchill 194b1 Ukkel/uccle Bruxelles-Capitale 1180",
    "addr:housenumber":"194b1",
    "addr:postcode":"1180",
    "addr:street":"Avenue Winston Churchill;/",
    "iso:country":"BE",
    "sg:address":"Avenue Winston Churchill 194b1",
    "sg:city":"Ukkel/uccle",
    "sg:orig_category":"M\u00e9decins and sp\u00e9cialistes",
    "sg:phone":"+32 2 345 60 78",
    "sg:postcode":"1180",
    "sg:province":"Bruxelles-Capitale",
    "wof:name":"Philippe Sellier",
    "wof:placetype":"venue"
},
  "geometry": {"coordinates":[4.3614587784,50.8115844727],"type":"Point"}
}