{
  "type": "Feature",
  "properties": {
    "addr:full":"Tuinwijk 109 Halle (buizingen) Vlaams-Brabant 1501",
    "addr:housenumber":"109",
    "addr:postcode":"1501",
    "addr:street":"Tuinwijk",
    "iso:country":"BE",
    "sg:address":"Tuinwijk 109",
    "sg:city":"Halle (buizingen)",
    "sg:classifiers":[
        {
            "category":"Building & Trades",
            "subcategory":"Landscaping Services",
            "type":"Services"
        }
    ],
    "sg:phone":"+32 2 360 19 85",
    "sg:postcode":"1501",
    "sg:province":"Vlaams-Brabant",
    "sg:tags":[
        "gardening",
        "garden",
        "maintenance"
    ],
    "wof:name":"De Larivi\u00e8re J P",
    "wof:placetype":"venue"
},
  "geometry": {"coordinates":[4.2652220726,50.7456054688],"type":"Point"}
}