{
  "type": "Feature",
  "properties": {
    "addr:full":"Magdalenastraat 21 Wervik West-Vlaanderen 8940",
    "addr:housenumber":"21",
    "addr:postcode":"8940",
    "addr:street":"Magdalenastraat",
    "iso:country":"BE",
    "sg:address":"Magdalenastraat 21",
    "sg:city":"Wervik",
    "sg:classifiers":[
        {
            "category":"Professional",
            "subcategory":"Testing Lab",
            "type":"Services"
        }
    ],
    "sg:phone":"+32 56 31 14 94",
    "sg:postcode":"8940",
    "sg:province":"West-Vlaanderen",
    "sg:tags":[
        "chemist"
    ],
    "wof:name":"Deleu R",
    "wof:placetype":"venue"
},
  "geometry": {"coordinates":[3.0398769379,50.778301239],"type":"Point"}
}