{
  "type": "Feature",
  "properties": {
    "addr:full":"Doornikserijksweg 142 Kortrijk (bellegem) West-Vlaanderen 8510",
    "addr:housenumber":"142",
    "addr:postcode":"8510",
    "addr:street":"Kortrijk",
    "iso:country":"BE",
    "sg:address":"Doornikserijksweg 142",
    "sg:city":"Kortrijk (bellegem)",
    "sg:classifiers":[
        {
            "category":"Building & Trades",
            "subcategory":"Landscaping Services",
            "type":"Services"
        }
    ],
    "sg:phone":"+32 56 22 40 21",
    "sg:postcode":"8510",
    "sg:province":"West-Vlaanderen",
    "sg:tags":[
        "gardening",
        "garden",
        "maintenance"
    ],
    "wof:name":"Lefevre Pol Bvba",
    "wof:placetype":"venue"
},
  "geometry": {"coordinates":[3.3047559261,50.7769622803],"type":"Point"}
}