{
  "type": "Feature",
  "properties": {
    "addr:full":"Fraterstraat 88 Merelbeke Oost-Vlaanderen 9820",
    "addr:housenumber":"88",
    "addr:postcode":"9820",
    "addr:street":"Fraterstraat",
    "iso:country":"BE",
    "sg:address":"Fraterstraat 88",
    "sg:city":"Merelbeke",
    "sg:orig_category":"Bijouteries and horlogeries",
    "sg:phone":"+32 9 232 03 13",
    "sg:postcode":"9820",
    "sg:province":"Oost-Vlaanderen",
    "wof:name":"Yuvaco",
    "wof:placetype":"venue"
},
  "geometry": {"coordinates":[3.7611670494,51.0130004883],"type":"Point"}
}