{
  "type": "Feature",
  "properties": {
    "iso:country":"BE",
    "sg:address":"Rue A. Lev\u00caque 37c",
    "sg:city":"Nivelles",
    "sg:orig_category":"Editeurs de journaux. Editeurs de revues and p\u00e9riodiques",
    "sg:phone":"+32 67 21 18 61",
    "sg:postcode":"1400",
    "sg:province":"Brabant Wallon",
    "wof:name":"Notre Jardin",
    "wof:placetype":"venue"
},
  "geometry": {"coordinates":[4.3378181458,50.6037979126],"type":"Point"}
}