{
  "type": "Feature",
  "properties": {
    "addr:full":"Mechelseweg 239 Kapelle-op-den-bos Vlaams-Brabant 1880",
    "addr:housenumber":"239",
    "addr:postcode":"1880",
    "addr:street":"Mechelseweg",
    "iso:country":"BE",
    "sg:address":"Mechelseweg 239",
    "sg:city":"Kapelle-op-den-bos",
    "sg:classifiers":[
        {
            "category":"Food & Beverages",
            "subcategory":"Chocolate",
            "type":"Retail Goods"
        }
    ],
    "sg:phone":"+32 15 71 11 86",
    "sg:postcode":"1880",
    "sg:province":"Vlaams-Brabant",
    "sg:tags":[
        "confectionery",
        "-"
    ],
    "wof:name":"Expresservice Bvba",
    "wof:placetype":"venue"
},
  "geometry": {"coordinates":[4.3611459732,51.0123596191],"type":"Point"}
}