{
  "type": "Feature",
  "properties": {
    "iso:country":"BE",
    "sg:address":"Dendermondsesteenweg 28",
    "sg:city":"Willebroek",
    "sg:orig_category":"Begrafeniswezen Diverse persoonlijke diensten",
    "sg:phone":"+32 3 886 63 01",
    "sg:postcode":"2830",
    "sg:province":"Antwerpen",
    "wof:name":"Begrafenisond. Goossens",
    "wof:placetype":"venue"
},
  "geometry": {"coordinates":[4.3567819595,51.0603981018],"type":"Point"}
}