{
  "type": "Feature",
  "properties": {
    "addr:full":"Chauss\u00c9e D'ivoz 247 Flemalle Li\u00e8ge 4400",
    "addr:housenumber":"247",
    "addr:postcode":"4400",
    "addr:street":"Chausse\u0301E D'Ivoz",
    "iso:country":"BE",
    "sg:address":"Chauss\u00c9e D'ivoz 247",
    "sg:city":"Flemalle",
    "sg:orig_category":"Entretien and r\u00e9parations de voitures",
    "sg:phone":"+32 4 337 71 31",
    "sg:postcode":"4400",
    "sg:province":"Li\u00e8ge",
    "wof:name":"Carrosserie Fusco",
    "wof:placetype":"venue"
},
  "geometry": {"coordinates":[5.477162838,50.5919799805],"type":"Point"}
}