{
  "type": "Feature",
  "properties": {
    "iso:country":"BE",
    "sg:address":"Pellemanstraat 61",
    "sg:city":"Kasterlee",
    "sg:orig_category":"Voedingsspeciaalzaken",
    "sg:phone":"+32 14 85 18 99",
    "sg:postcode":"2460",
    "sg:province":"Antwerpen",
    "wof:name":"De Meidoorn",
    "wof:placetype":"venue"
},
  "geometry": {"coordinates":[4.9579291344,51.2433166504],"type":"Point"}
}