{
  "type": "Feature",
  "properties": {
    "iso:country":"BE",
    "sg:address":"Rue Des Minimes 22",
    "sg:city":"Brussel/bruxelles",
    "sg:orig_category":"Antiquit\u00e9s",
    "sg:phone":"+32 2 511 09 89",
    "sg:postcode":"1000",
    "sg:province":"Bruxelles-Capitale",
    "wof:name":"Maison Drees-archeo",
    "wof:placetype":"venue"
},
  "geometry": {"coordinates":[4.353782177,50.840763092],"type":"Point"}
}