{
  "type": "Feature",
  "properties": {
    "addr:full":"Vlijtingerweg 12 Riemst (vlijtingen) Limburg 3770",
    "addr:housenumber":"12",
    "addr:postcode":"3770",
    "addr:street":"Vlijtingerweg",
    "iso:country":"BE",
    "sg:address":"Vlijtingerweg 12",
    "sg:city":"Riemst (vlijtingen)",
    "sg:classifiers":[
        {
            "category":"Autos & Motor Vehicles",
            "subcategory":"Automobile Sales",
            "type":"Retail Goods"
        }
    ],
    "sg:postcode":"3770",
    "sg:province":"Limburg",
    "sg:tags":[
        "ceremony",
        "car"
    ],
    "wof:name":"Starline Limousineservice",
    "wof:placetype":"venue"
},
  "geometry": {"coordinates":[5.6261620522,50.8356170654],"type":"Point"}
}