{
  "type": "Feature",
  "properties": {
    "iso:country":"BE",
    "sg:address":"Rue De L'arbre B\u00e9nit 64",
    "sg:city":"Bruxelles (ixelles)",
    "sg:classifiers":[
        {
            "category":"Retail",
            "subcategory":"Repair Shop",
            "type":"Services"
        }
    ],
    "sg:phone":"+32 2 514 43 34",
    "sg:postcode":"1050",
    "sg:province":"Bruxelles-Capitale",
    "sg:tags":[
        "denture"
    ],
    "wof:name":"Sahbi (laboratoire Dentaire)",
    "wof:placetype":"venue"
},
  "geometry": {"coordinates":[4.3639950752,50.8330116272],"type":"Point"}
}