{
  "type": "Feature",
  "properties": {
    "iso:country":"BE",
    "sg:address":"Evendijk-west 21",
    "sg:city":"Blankenberge",
    "sg:orig_category":"Afvalwaterverwerking and ontstoppingsdiensten Huisvuilophaling and -verwerking",
    "sg:phone":"+32 50 41 98 69",
    "sg:postcode":"8370",
    "sg:province":"West-Vlaanderen",
    "wof:name":"Francier",
    "wof:placetype":"venue"
},
  "geometry": {"coordinates":[3.137016058,51.3056106567],"type":"Point"}
}