{
  "type": "Feature",
  "properties": {
    "iso:country":"BE",
    "sg:address":"Steenweg 106",
    "sg:city":"Nazareth (eke)",
    "sg:classifiers":[
        {
            "category":"Health Services",
            "subcategory":"Health Practitioner",
            "type":"Services"
        }
    ],
    "sg:phone":"+32 9 385 82 53",
    "sg:postcode":"9810",
    "sg:province":"Oost-Vlaanderen",
    "sg:tags":[
        "physiotherapist"
    ],
    "wof:name":"Danneels V\u00e9ronique",
    "wof:placetype":"venue"
},
  "geometry": {"coordinates":[3.6425890923,50.959022522],"type":"Point"}
}