{
  "type": "Feature",
  "properties": {
    "addr:full":"Transportcentrum Lar Blok M-7 Rekkem West-Vlaanderen 8930",
    "addr:postcode":"8930",
    "addr:street":"M-7",
    "iso:country":"BE",
    "sg:address":"Transportcentrum Lar Blok M-7",
    "sg:city":"Rekkem",
    "sg:classifiers":[
        {
            "category":"Professional",
            "subcategory":"Engineering",
            "type":"Services"
        }
    ],
    "sg:phone":"+32 56 43 01 90",
    "sg:postcode":"8930",
    "sg:province":"West-Vlaanderen",
    "sg:tags":[
        "machine",
        "-",
        "mechanical"
    ],
    "wof:name":"Cardever Nv",
    "wof:placetype":"venue"
},
  "geometry": {"coordinates":[3.1209149361,50.7961845398],"type":"Point"}
}