{
  "type": "Feature",
  "properties": {
    "addr:full":"Rue Emile Henricot 19 Court-saint-etienne Brabant Wallon 1490",
    "addr:housenumber":"19;1490",
    "addr:street":"Rue Emile Henricot",
    "iso:country":"BE",
    "sg:address":"Rue Emile Henricot 19",
    "sg:city":"Court-saint-etienne",
    "sg:orig_category":"Instituts de beaut\u00e9",
    "sg:phone":"+32 10 61 63 29",
    "sg:postcode":"1490",
    "sg:province":"Brabant Wallon",
    "wof:name":"Pham Thi Xuan Thu",
    "wof:placetype":"venue"
},
  "geometry": {"coordinates":[4.5670080185,50.6448898315],"type":"Point"}
}