{
  "type": "Feature",
  "properties": {
    "addr:full":"All\u00c9e Sur Sainval 12 Chaudfontaine Li\u00e8ge 4052",
    "addr:housenumber":"12",
    "addr:postcode":"4052",
    "addr:street":"Alle\u0301E Sur Sainval",
    "iso:country":"BE",
    "sg:address":"All\u00c9e Sur Sainval 12",
    "sg:city":"Chaudfontaine",
    "sg:orig_category":"Agences de mannequins and h\u00f4tesses",
    "sg:phone":"+32 4 368 61 58",
    "sg:postcode":"4052",
    "sg:province":"Li\u00e8ge",
    "wof:name":"Ghislain Saive Jean-robert",
    "wof:placetype":"venue"
},
  "geometry": {"coordinates":[5.6170148849,50.5711784363],"type":"Point"}
}