{
  "type": "Feature",
  "properties": {
    "addr:full":"Staatsbaan 88 Halen Limburg 3545",
    "addr:housenumber":"88",
    "addr:postcode":"3545",
    "addr:street":"Staatsbaan",
    "iso:country":"BE",
    "sg:address":"Staatsbaan 88",
    "sg:city":"Halen",
    "sg:classifiers":[
        {
            "category":"Home & Garden",
            "subcategory":"Building Materials",
            "type":"Retail Goods"
        }
    ],
    "sg:phone":"+32 13 44 44 92",
    "sg:postcode":"3545",
    "sg:province":"Limburg",
    "sg:tags":[
        "granite",
        "stone",
        "natural",
        "marble"
    ],
    "wof:name":"Granit Stone Art Nv",
    "wof:placetype":"venue"
},
  "geometry": {"coordinates":[5.0889282227,50.958782196],"type":"Point"}
}