{
  "type": "Feature",
  "properties": {
    "iso:country":"BE",
    "sg:address":"Beirstoppellos 31",
    "sg:city":"Wetteren",
    "sg:orig_category":"Jardinage",
    "sg:phone":"+32 9 369 55 13",
    "sg:postcode":"9230",
    "sg:province":"Oost-Vlaanderen",
    "wof:name":"Van Kerckhove Eric",
    "wof:placetype":"venue"
},
  "geometry": {"coordinates":[3.8718578815,51.0120201111],"type":"Point"}
}