{
  "type": "Feature",
  "properties": {
    "addr:full":"Felix Timmermansplein 1 Lier Antwerpen 2500",
    "addr:housenumber":"1",
    "addr:postcode":"2500",
    "addr:street":"Felix Timmermansplein",
    "iso:country":"BE",
    "sg:address":"Felix Timmermansplein 1",
    "sg:city":"Lier",
    "sg:orig_category":"Services divers aux entreprises. Agences immobili\u00e8res. Evaluation and estimation de biens immobilier",
    "sg:phone":"+32 3 489 15 89",
    "sg:postcode":"2500",
    "sg:province":"Antwerpen",
    "wof:name":"Inkove",
    "wof:placetype":"venue"
},
  "geometry": {"coordinates":[4.5708370209,51.1301727295],"type":"Point"}
}