{
  "type": "Feature",
  "properties": {
    "iso:country":"BE",
    "sg:address":"Chauss\u00e9e De Louvain 831",
    "sg:city":"Bruxelles (evere)",
    "sg:classifiers":[
        {
            "category":"Personal",
            "subcategory":"Barber",
            "type":"Services"
        }
    ],
    "sg:phone":"+32 2 726 84 55",
    "sg:postcode":"1140",
    "sg:province":"Bruxelles-Capitale",
    "sg:tags":[
        "gentleman",
        "salon",
        "-",
        "hairdressing"
    ],
    "wof:name":"D.d. Men's Coif'",
    "wof:placetype":"venue"
},
  "geometry": {"coordinates":[4.4152607918,50.8594245911],"type":"Point"}
}