{
  "type": "Feature",
  "properties": {
    "iso:country":"BE",
    "sg:address":"Hugo Verriestlaan 133",
    "sg:city":"Kortrijk",
    "sg:orig_category":"Pain, p\u00e2tisseries and confiseries",
    "sg:phone":"+32 56 21 17 75",
    "sg:postcode":"8500",
    "sg:province":"West-Vlaanderen",
    "wof:name":"Patrick Taveirne",
    "wof:placetype":"venue"
},
  "geometry": {"coordinates":[3.282861948,50.8231391907],"type":"Point"}
}