{
  "type": "Feature",
  "properties": {
    "addr:full":"Geelsebaan 74 Tessenderlo Limburg 3980",
    "addr:housenumber":"74",
    "addr:postcode":"3980",
    "addr:street":"Geelsebaan",
    "iso:country":"BE",
    "sg:address":"Geelsebaan 74",
    "sg:city":"Tessenderlo",
    "sg:classifiers":[
        {
            "category":"Building & Trades",
            "subcategory":"Construction",
            "type":"Services"
        }
    ],
    "sg:phone":"+32 13 66 41 14",
    "sg:postcode":"3980",
    "sg:province":"Limburg",
    "sg:tags":[
        "tool",
        "cutting"
    ],
    "wof:name":"C.w.s. Tools",
    "wof:placetype":"venue"
},
  "geometry": {"coordinates":[5.0835747719,51.072845459],"type":"Point"}
}