{
  "type": "Feature",
  "properties": {
    "addr:full":"Rue Frans Hals 15 Bruxelles (anderlecht) Bruxelles-Capitale 1070",
    "addr:housenumber":"15",
    "addr:postcode":"1070",
    "addr:street":"Rue Frans Hals",
    "iso:country":"BE",
    "sg:address":"Rue Frans Hals 15",
    "sg:city":"Bruxelles (anderlecht)",
    "sg:classifiers":[
        {
            "category":"Building & Trades",
            "subcategory":"Plumbing",
            "type":"Services"
        }
    ],
    "sg:phone":"+32 497 68 70 70",
    "sg:postcode":"1070",
    "sg:province":"Bruxelles-Capitale",
    "sg:tags":[
        "contractor"
    ],
    "wof:name":"A. Sanilanc",
    "wof:placetype":"venue"
},
  "geometry": {"coordinates":[4.2930550575,50.8243904114],"type":"Point"}
}