{
  "type": "Feature",
  "properties": {
    "iso:country":"BE",
    "sg:address":"Broekelken 9",
    "sg:city":"Maldegem",
    "sg:orig_category":"Eleveurs and marchands de porcs",
    "sg:phone":"+32 50 71 47 59",
    "sg:postcode":"9991",
    "sg:province":"Oost-Vlaanderen",
    "wof:name":"Michel Lonneville",
    "wof:placetype":"venue"
},
  "geometry": {"coordinates":[3.4717280865,51.2097473145],"type":"Point"}
}