{
  "type": "Feature",
  "properties": {
    "addr:full":"Avenue Des Champs Clairs 15 Braine L'alleud (braine-l'alleud) Brabant Wallon 1420",
    "addr:housenumber":"15",
    "addr:postcode":"1420",
    "addr:street":"Avenue Des Champs Clairs",
    "iso:country":"BE",
    "sg:address":"Avenue Des Champs Clairs 15",
    "sg:city":"Braine L'alleud (braine-l'alleud)",
    "sg:classifiers":[
        {
            "category":"Professional",
            "subcategory":"Advertising",
            "type":"Services"
        }
    ],
    "sg:phone":"+32 2 387 48 41",
    "sg:postcode":"1420",
    "sg:province":"Brabant Wallon",
    "sg:tags":[
        "bill",
        "-",
        "posting"
    ],
    "wof:name":"Affiches Diffusion Sprl",
    "wof:placetype":"venue"
},
  "geometry": {"coordinates":[-0.7004899979,47.369140625],"type":"Point"}
}