{
  "type": "Feature",
  "properties": {
    "addr:full":"Rue De La Fr\u00cate 11 Ramillies Brabant Wallon 1367",
    "addr:housenumber":"11",
    "addr:postcode":"1367",
    "addr:street":"Rue De La Fre\u0302Te",
    "iso:country":"BE",
    "sg:address":"Rue De La Fr\u00cate 11",
    "sg:city":"Ramillies",
    "sg:orig_category":"Jardinage",
    "sg:phone":"+32 81 87 93 38",
    "sg:postcode":"1367",
    "sg:province":"Brabant Wallon",
    "wof:name":"V T Jardinage",
    "wof:placetype":"venue"
},
  "geometry": {"coordinates":[4.9195728302,50.6343688965],"type":"Point"}
}