{
  "type": "Feature",
  "properties": {
    "iso:country":"BE",
    "sg:address":"Prins Albertstraat 44",
    "sg:city":"Sint-niklaas",
    "sg:orig_category":"Notarissen",
    "sg:phone":"+32 3 776 01 24",
    "sg:postcode":"9100",
    "sg:province":"Oost-Vlaanderen",
    "wof:name":"Edmond Leclair",
    "wof:placetype":"venue"
},
  "geometry": {"coordinates":[4.1442070007,51.169418335],"type":"Point"}
}