{
  "type": "Feature",
  "properties": {
    "iso:country":"BE",
    "sg:address":"Sint-michielsplein 9a",
    "sg:city":"Westerlo",
    "sg:orig_category":"Banken and kredietinstellingen",
    "sg:phone":"+32 14 23 11 24",
    "sg:postcode":"2260",
    "sg:province":"Antwerpen",
    "wof:name":"Citibank",
    "wof:placetype":"venue"
},
  "geometry": {"coordinates":[4.9050498009,51.1393737793],"type":"Point"}
}