{
  "type": "Feature",
  "properties": {
    "iso:country":"BE",
    "sg:address":"Schoonderbeukenweg 64",
    "sg:city":"Aarschot",
    "sg:orig_category":"R\u00e9parations de chaussures and articles en cuir",
    "sg:phone":"+32 16 50 07 65",
    "sg:postcode":"3202",
    "sg:province":"Vlaams-Brabant",
    "wof:name":"Florentinus Wolput",
    "wof:placetype":"venue"
},
  "geometry": {"coordinates":[4.9027447701,50.9730453491],"type":"Point"}
}