{
  "type": "Feature",
  "properties": {
    "addr:full":"Brandstraat 93 Sint-martens-latem Oost-Vlaanderen 9830",
    "addr:housenumber":"93",
    "addr:postcode":"9830",
    "addr:street":"Brandstraat",
    "iso:country":"BE",
    "sg:address":"Brandstraat 93",
    "sg:city":"Sint-martens-latem",
    "sg:classifiers":[
        {
            "category":"Banks & Credit Unions",
            "subcategory":"Investment Brokerage",
            "type":"Services"
        }
    ],
    "sg:phone":"+32 9 281 04 39",
    "sg:postcode":"9830",
    "sg:province":"Oost-Vlaanderen",
    "sg:tags":[
        "auditor"
    ],
    "wof:name":"Claeys B",
    "wof:placetype":"venue"
},
  "geometry": {"coordinates":[3.6205630302,51.0054626465],"type":"Point"}
}