{
  "type": "Feature",
  "properties": {
    "iso:country":"BE",
    "sg:address":"Begijnhofstraat 7",
    "sg:city":"Zoutleeuw",
    "sg:classifiers":[
        {
            "category":"Shopping",
            "subcategory":"Florist",
            "type":"Retail Goods"
        }
    ],
    "sg:phone":"+32 11 58 29 66",
    "sg:postcode":"3440",
    "sg:province":"Vlaams-Brabant",
    "wof:name":"Bloembinderij Leen & Lena",
    "wof:placetype":"venue"
},
  "geometry": {"coordinates":[5.1012940407,50.832901001],"type":"Point"}
}