{
  "type": "Feature",
  "properties": {
    "iso:country":"BE",
    "sg:address":"Leren Veld 45",
    "sg:city":"Lint",
    "sg:orig_category":"Entretien and r\u00e9parations de voitures. R\u00e9cup\u00e9ration de mati\u00e8res m\u00e9talliques recyclables and d\u00e9moliss",
    "sg:phone":"+32 3 488 27 89",
    "sg:postcode":"2547",
    "sg:province":"Antwerpen",
    "wof:name":"Jeep Design",
    "wof:placetype":"venue"
},
  "geometry": {"coordinates":[4.5118751526,51.1271781921],"type":"Point"}
}