{
  "type": "Feature",
  "properties": {
    "iso:country":"BE",
    "sg:address":"Herkenrodesingel 23b13",
    "sg:city":"Hasselt",
    "sg:classifiers":[
        {
            "category":"Professional",
            "subcategory":"Accounting & Tax Preparation",
            "type":"Services"
        }
    ],
    "sg:phone":"+32 11 25 19 40",
    "sg:postcode":"3500",
    "sg:province":"Limburg",
    "sg:tags":[
        "accountant"
    ],
    "wof:name":"Fa. Jordens",
    "wof:placetype":"venue"
},
  "geometry": {"coordinates":[5.3218369484,50.941204071],"type":"Point"}
}