{
  "type": "Feature",
  "properties": {
    "iso:country":"BE",
    "sg:address":"Vliegpleinstraat 1-5",
    "sg:city":"Evere",
    "sg:orig_category":"Sportclubs",
    "sg:phone":"+32 2 241 06 66",
    "sg:postcode":"1140",
    "sg:province":"Bruxelles-Capitale",
    "wof:name":"Boxing Team One Two One",
    "wof:placetype":"venue"
},
  "geometry": {"coordinates":[4.4022722244,50.8766822815],"type":"Point"}
}