{
  "type": "Feature",
  "properties": {
    "addr:full":"Belegstraat 20 Antwerpen Antwerpen 2018",
    "addr:housenumber":"20",
    "addr:postcode":"2018",
    "addr:street":"Belegstraat",
    "iso:country":"BE",
    "sg:address":"Belegstraat 20",
    "sg:city":"Antwerpen",
    "sg:classifiers":[
        {
            "category":"Professional",
            "subcategory":"Credit Reporting & Collection",
            "type":"Services"
        }
    ],
    "sg:phone":"+32 3 238 02 81",
    "sg:postcode":"2018",
    "sg:province":"Antwerpen",
    "sg:tags":[
        "bailiff"
    ],
    "wof:name":"De Troij L-weyns J",
    "wof:placetype":"venue"
},
  "geometry": {"coordinates":[4.3941869736,51.2053756714],"type":"Point"}
}