{
  "type": "Feature",
  "properties": {
    "addr:full":"Clos Wagram 5 Waterloo Brabant Wallon 1410",
    "addr:housenumber":"5",
    "addr:postcode":"1410",
    "addr:street":"Clos Wagram",
    "iso:country":"BE",
    "sg:address":"Clos Wagram 5",
    "sg:city":"Waterloo",
    "sg:classifiers":[
        {
            "category":"Professional",
            "subcategory":"Management & Consulting",
            "type":"Services"
        }
    ],
    "sg:phone":"+32 2 351 00 37",
    "sg:postcode":"1410",
    "sg:province":"Brabant Wallon",
    "sg:tags":[
        "-",
        "processing",
        "data",
        "consultant"
    ],
    "wof:name":"Edapro Systems",
    "wof:placetype":"venue"
},
  "geometry": {"coordinates":[4.4053587914,50.7112808228],"type":"Point"}
}