{
  "type": "Feature",
  "properties": {
    "addr:full":"Wollegrasstraat 2 Antwerpen Antwerpen 2040",
    "addr:housenumber":"2",
    "addr:postcode":"2040",
    "addr:street":"Wollegrasstraat",
    "iso:country":"BE",
    "sg:address":"Wollegrasstraat 2",
    "sg:city":"Antwerpen",
    "sg:classifiers":[
        {
            "category":"Cafe",
            "type":"Food & Drink"
        }
    ],
    "sg:phone":"+32 3 569 07 33",
    "sg:postcode":"2040",
    "sg:province":"Antwerpen",
    "sg:tags":[
        "caf\u00e9s"
    ],
    "wof:name":"Christine Vande Langerijt",
    "wof:placetype":"venue"
},
  "geometry": {"coordinates":[4.3141150475,51.3429756165],"type":"Point"}
}