{
  "type": "Feature",
  "properties": {
    "addr:full":"Kustlaan 268 Brugge West-Vlaanderen 8380",
    "addr:housenumber":"268",
    "addr:postcode":"8380",
    "addr:street":"Kustlaan",
    "iso:country":"BE",
    "sg:address":"Kustlaan 268",
    "sg:city":"Brugge",
    "sg:orig_category":"Benzinestations and brandstoffen Onderdelen and accessoires voor auto's",
    "sg:phone":"+32 50 54 41 01",
    "sg:postcode":"8380",
    "sg:province":"West-Vlaanderen",
    "wof:name":"Dumolyn Vandycke",
    "wof:placetype":"venue"
},
  "geometry": {"coordinates":[3.2288448811,51.2742958069],"type":"Point"}
}