{
  "type": "Feature",
  "properties": {
    "iso:country":"BE",
    "sg:address":"Rue Basse-wez 333",
    "sg:city":"Li\u00c8ge",
    "sg:orig_category":"Avocats and conseillers juridiques",
    "sg:phone":"+32 4 344 05 09",
    "sg:postcode":"4020",
    "sg:province":"Li\u00e8ge",
    "wof:name":"R. Truillet",
    "wof:placetype":"venue"
},
  "geometry": {"coordinates":[5.5882592201,50.6318473816],"type":"Point"}
}