{
  "type": "Feature",
  "properties": {
    "addr:full":"Industrieterrein Kolmen 1620 Alken Limburg 3570",
    "addr:housenumber":"1620",
    "addr:postcode":"3570",
    "addr:street":"Industrieterrein Kolmen",
    "iso:country":"BE",
    "sg:address":"Industrieterrein Kolmen 1620",
    "sg:city":"Alken",
    "sg:orig_category":"Koekjes, gebak and taart Fab",
    "sg:phone":"+32 11 59 18 66",
    "sg:postcode":"3570",
    "sg:province":"Limburg",
    "wof:name":"Kimm",
    "wof:placetype":"venue"
},
  "geometry": {"coordinates":[5.3005661964,50.8882484436],"type":"Point"}
}