{
  "type": "Feature",
  "properties": {
    "addr:full":"Hagelkruis 9 Wuustwezel Antwerpen 2990",
    "addr:housenumber":"9",
    "addr:postcode":"2990",
    "addr:street":"Hagelkruis",
    "iso:country":"BE",
    "sg:address":"Hagelkruis 9",
    "sg:city":"Wuustwezel",
    "sg:orig_category":"Elektrische installaties voor woningen",
    "sg:phone":"+32 3 669 99 61",
    "sg:postcode":"2990",
    "sg:province":"Antwerpen",
    "wof:name":"Guy Janssens",
    "wof:placetype":"venue"
},
  "geometry": {"coordinates":[4.5926609039,51.3899803162],"type":"Point"}
}