{
  "type": "Feature",
  "properties": {
    "iso:country":"BE",
    "sg:address":"Stationsplein 11",
    "sg:city":"Roeselare",
    "sg:orig_category":"Caf\u00e9s. Taxis services sp\u00e9ciaux. Services divers aux personnes",
    "sg:phone":"+32 51 22 16 11",
    "sg:postcode":"8800",
    "sg:province":"West-Vlaanderen",
    "wof:name":"Caf\u00c9 Damier",
    "wof:placetype":"venue"
},
  "geometry": {"coordinates":[3.1299118996,50.9487800598],"type":"Point"}
}