{
  "type": "Feature",
  "properties": {
    "addr:full":"Bois Hennon 4 Thimister-clermont (clermont) Li\u00e8ge 4890",
    "addr:housenumber":"4",
    "addr:postcode":"4890",
    "iso:country":"BE",
    "sg:address":"Bois Hennon 4",
    "sg:city":"Thimister-clermont (clermont)",
    "sg:classifiers":[
        {
            "category":"Building & Trades",
            "subcategory":"Landscaping Services",
            "type":"Services"
        }
    ],
    "sg:phone":"+32 87 44 63 99",
    "sg:postcode":"4890",
    "sg:province":"Li\u00e8ge",
    "sg:tags":[
        "gardening",
        "garden",
        "maintenance"
    ],
    "wof:name":"Monseur Bernard",
    "wof:placetype":"venue"
},
  "geometry": {"coordinates":[5.8879351616,50.648349762],"type":"Point"}
}