{
  "type": "Feature",
  "properties": {
    "addr:full":"Chauss\u00c9e De Nivelles 160 Genappe Brabant Wallon 1472",
    "addr:housenumber":"160",
    "addr:postcode":"1472",
    "addr:street":"Chausse\u0301E De Nivelles;Wallon",
    "iso:country":"BE",
    "sg:address":"Chauss\u00c9e De Nivelles 160",
    "sg:city":"Genappe",
    "sg:orig_category":"Rundveehouders Varkenskwekers",
    "sg:phone":"+32 67 77 20 79",
    "sg:postcode":"1472",
    "sg:province":"Brabant Wallon",
    "wof:name":"Denis Van Renterghem",
    "wof:placetype":"venue"
},
  "geometry": {"coordinates":[4.42964077,50.6066246033],"type":"Point"}
}