{
  "type": "Feature",
  "properties": {
    "iso:country":"BE",
    "sg:address":"Kerkplein 11",
    "sg:city":"Sint-agatha-berchem/berchem-sainte-agathe",
    "sg:orig_category":"Fotografen and fotostudio's",
    "sg:phone":"+32 2 465 89 69",
    "sg:postcode":"1082",
    "sg:province":"Bruxelles-Capitale",
    "wof:name":"Alain Verbaert",
    "wof:placetype":"venue"
},
  "geometry": {"coordinates":[4.2921299934,50.8612937927],"type":"Point"}
}