{
  "type": "Feature",
  "properties": {
    "iso:country":"BE",
    "sg:address":"Beheerstraat 17",
    "sg:city":"Kortrijk",
    "sg:classifiers":[
        {
            "category":"Professional",
            "subcategory":"Engineering",
            "type":"Services"
        }
    ],
    "sg:phone":"+32 56 22 30 71",
    "sg:postcode":"8500",
    "sg:province":"West-Vlaanderen",
    "sg:tags":[
        "machine",
        "-",
        "environment",
        "equipment",
        "machinery",
        "mechanical"
    ],
    "wof:name":"Rogers Air Cleaning Bvba",
    "wof:placetype":"venue"
},
  "geometry": {"coordinates":[3.2579228878,50.8263168335],"type":"Point"}
}