{
  "type": "Feature",
  "properties": {
    "addr:full":". Dilsen-stokkem Limburg 3650",
    "addr:postcode":"3650",
    "iso:country":"BE",
    "sg:address":".",
    "sg:city":"Dilsen-stokkem",
    "sg:orig_category":"Apotheken",
    "sg:phone":"+32 900 10 500",
    "sg:postcode":"3650",
    "sg:province":"Limburg",
    "wof:name":"Apothekers Van Wacht",
    "wof:placetype":"venue"
},
  "geometry": {"coordinates":[5.727396965,51.0364189148],"type":"Point"}
}