{
  "type": "Feature",
  "properties": {
    "addr:full":"Priester Coulonstraat 100 Menen (rekkem) West-Vlaanderen 8930",
    "addr:housenumber":"100",
    "addr:postcode":"8930",
    "addr:street":"Priester Coulonstraat",
    "iso:country":"BE",
    "sg:address":"Priester Coulonstraat 100",
    "sg:city":"Menen (rekkem)",
    "sg:classifiers":[
        {
            "category":"Retail",
            "subcategory":"Storage",
            "type":"Services"
        }
    ],
    "sg:phone":"+32 56 41 24 07",
    "sg:postcode":"8930",
    "sg:province":"West-Vlaanderen",
    "sg:tags":[
        "access",
        "-",
        "pigeon",
        "fancier"
    ],
    "wof:name":"Vanrobaeys Nv",
    "wof:placetype":"venue"
},
  "geometry": {"coordinates":[3.1725709438,50.7862129211],"type":"Point"}
}