{
  "type": "Feature",
  "properties": {
    "iso:country":"BE",
    "sg:address":"Bergstraat 18a",
    "sg:city":"Heuvelland",
    "sg:orig_category":"Assurances. Bureaux de poste",
    "sg:phone":"+32 57 44 43 96",
    "sg:postcode":"8956",
    "sg:province":"West-Vlaanderen",
    "wof:name":"De Post",
    "wof:placetype":"venue"
},
  "geometry": {"coordinates":[2.823980093,50.7818717957],"type":"Point"}
}