{
  "type": "Feature",
  "properties": {
    "addr:full":"Kleine Pathoekeweg 13-15 Brugge West-Vlaanderen 8000",
    "addr:housenumber":"13-15",
    "addr:postcode":"8000",
    "addr:street":"Kleine Pathoekeweg",
    "iso:country":"BE",
    "sg:address":"Kleine Pathoekeweg 13-15",
    "sg:city":"Brugge",
    "sg:classifiers":[
        {
            "category":"Manufacturing",
            "subcategory":"Motor Vehicles & Parts",
            "type":"Manufacturing & Wholesale Goods"
        }
    ],
    "sg:phone":"+32 50 31 50 83",
    "sg:postcode":"8000",
    "sg:province":"West-Vlaanderen",
    "sg:tags":[
        "machine",
        "-",
        "indivisible",
        "transport"
    ],
    "wof:name":"R.v.m.",
    "wof:placetype":"venue"
},
  "geometry": {"coordinates":[3.2098100185,51.2458457947],"type":"Point"}
}