{
  "type": "Feature",
  "properties": {
    "iso:country":"BE",
    "sg:address":"Lindestraat 200",
    "sg:city":"Waregem (sint-eloois-vijve)",
    "sg:classifiers":[
        {
            "category":"Freight",
            "type":"Transportation"
        }
    ],
    "sg:phone":"+32 56 60 37 68",
    "sg:postcode":"8793",
    "sg:province":"West-Vlaanderen",
    "sg:tags":[
        "-",
        "transport"
    ],
    "wof:name":"Wyffels Bvba",
    "wof:placetype":"venue"
},
  "geometry": {"coordinates":[3.4064691067,50.8974685669],"type":"Point"}
}