{
  "type": "Feature",
  "properties": {
    "addr:full":"Rue Du Longfaux 100 Binche (buvrinnes) Hainaut 7133",
    "addr:housenumber":"100",
    "addr:postcode":"7133",
    "addr:street":"Rue Du Longfaux",
    "iso:country":"BE",
    "sg:address":"Rue Du Longfaux 100",
    "sg:city":"Binche (buvrinnes)",
    "sg:classifiers":[
        {
            "category":"Building & Trades",
            "subcategory":"Construction",
            "type":"Services"
        }
    ],
    "sg:phone":"+32 64 37 03 36",
    "sg:postcode":"7133",
    "sg:province":"Hainaut",
    "sg:tags":[
        "carpenter"
    ],
    "wof:name":"Froid Manteau Sprl",
    "wof:placetype":"venue"
},
  "geometry": {"coordinates":[4.2089209557,50.3880348206],"type":"Point"}
}