{
  "type": "Feature",
  "properties": {
    "addr:full":"Hodonk 86 Retie Antwerpen 2470",
    "addr:housenumber":"86",
    "addr:postcode":"2470",
    "addr:street":"Hodonk",
    "iso:country":"BE",
    "sg:address":"Hodonk 86",
    "sg:city":"Retie",
    "sg:orig_category":"Rundveehouders",
    "sg:phone":"+32 14 37 13 14",
    "sg:postcode":"2470",
    "sg:province":"Antwerpen",
    "wof:name":"Gustaaf Verwaest",
    "wof:placetype":"venue"
},
  "geometry": {"coordinates":[5.1144199371,51.2653541565],"type":"Point"}
}