{
  "type": "Feature",
  "properties": {
    "addr:full":"2200 Herentals (groot) Antwerpen 2200",
    "addr:postcode":"2200;2200",
    "addr:street":"Groot Antwerpen",
    "iso:country":"BE",
    "sg:address":"2200",
    "sg:city":"Herentals (groot)",
    "sg:orig_category":"Pharmaciens",
    "sg:phone":"+32 900 10 500",
    "sg:postcode":"2200",
    "sg:province":"Antwerpen",
    "wof:name":"Pharmacies De Garde",
    "wof:placetype":"venue"
},
  "geometry": {"coordinates":[4.8360338211,51.1774635315],"type":"Point"}
}