{
  "type": "Feature",
  "properties": {
    "iso:country":"BE",
    "sg:address":"Onze-lieve-vrouwplein 9",
    "sg:city":"Kruibeke",
    "sg:classifiers":[
        {
            "category":"Bars & Pubs",
            "type":"Food & Drink"
        }
    ],
    "sg:phone":"+32 3 774 17 00",
    "sg:postcode":"9150",
    "sg:province":"Oost-Vlaanderen",
    "wof:name":"Ons Huis",
    "wof:placetype":"venue"
},
  "geometry": {"coordinates":[4.311507225,51.1714134216],"type":"Point"}
}