{
  "type": "Feature",
  "properties": {
    "addr:full":"Brugstraat 16 Dendermonde Oost-Vlaanderen 9200",
    "addr:housenumber":"16",
    "addr:postcode":"9200",
    "addr:street":"Brugstraat;Oost-Vlaanderen",
    "iso:country":"BE",
    "sg:address":"Brugstraat 16",
    "sg:city":"Dendermonde",
    "sg:classifiers":[
        {
            "category":"Restaurant",
            "type":"Food & Drink"
        }
    ],
    "sg:phone":"+32 52 42 30 51",
    "sg:postcode":"9200",
    "sg:province":"Oost-Vlaanderen",
    "wof:name":"De Brouwer",
    "wof:placetype":"venue"
},
  "geometry": {"coordinates":[4.0822291374,51.0188522339],"type":"Point"}
}