{
  "type": "Feature",
  "properties": {
    "addr:full":"Avenue Georges Truffaut 42 Li\u00e8ge Li\u00e8ge 4020",
    "addr:housenumber":"42",
    "addr:postcode":"4020",
    "addr:street":"Avenue Georges Truffaut",
    "iso:country":"BE",
    "sg:address":"Avenue Georges Truffaut 42",
    "sg:city":"Li\u00e8ge",
    "sg:orig_category":"Electromagnetic Brakes",
    "sg:phone":"+32 4 370 09 77",
    "sg:postcode":"4020",
    "sg:province":"Li\u00e8ge",
    "wof:name":"Eurofreins S.a.",
    "wof:placetype":"venue"
},
  "geometry": {"coordinates":[5.6116957664,50.6498031616],"type":"Point"}
}