{
  "type": "Feature",
  "properties": {
    "addr:full":"Elzelestraat 99 Ronse Oost-Vlaanderen 9600",
    "addr:housenumber":"99",
    "addr:postcode":"9600",
    "addr:street":"Elzelestraat",
    "iso:country":"BE",
    "sg:address":"Elzelestraat 99",
    "sg:city":"Ronse",
    "sg:classifiers":[
        {
            "category":"Banks & Credit Unions",
            "subcategory":"Bank",
            "type":"Services"
        }
    ],
    "sg:phone":"+32 55 21 38 88",
    "sg:postcode":"9600",
    "sg:province":"Oost-Vlaanderen",
    "wof:name":"Aslk-cger Bank",
    "wof:placetype":"venue"
},
  "geometry": {"coordinates":[3.6084001064,50.74559021],"type":"Point"}
}