{
  "type": "Feature",
  "properties": {
    "iso:country":"BE",
    "sg:address":"Klein Zottegem 6",
    "sg:city":"Sint-lievens-houtem",
    "sg:orig_category":"Produits laitiers and huiles comestibles Gr",
    "sg:phone":"+32 53 62 23 33",
    "sg:postcode":"9521",
    "sg:province":"Oost-Vlaanderen",
    "wof:name":"Steppe D",
    "wof:placetype":"venue"
},
  "geometry": {"coordinates":[3.8800840378,50.9251213074],"type":"Point"}
}