{
  "type": "Feature",
  "properties": {
    "iso:country":"BE",
    "sg:address":"Bergenstraat 2",
    "sg:city":"Wijnegem",
    "sg:classifiers":[
        {
            "category":"Education",
            "subcategory":"School",
            "type":"Public Place"
        }
    ],
    "sg:phone":"+32 3 353 75 41",
    "sg:postcode":"2110",
    "sg:province":"Antwerpen",
    "sg:tags":[
        "secondary"
    ],
    "wof:name":"Gemeentelijke Muziekacademie zoltan Kodaly",
    "wof:placetype":"venue"
},
  "geometry": {"coordinates":[4.5209450722,51.2284088135],"type":"Point"}
}