{
  "type": "Feature",
  "properties": {
    "addr:full":"Rue Muzet 47 Namur (saint-servais) Namur 5002",
    "addr:housenumber":"47",
    "addr:postcode":"5002",
    "addr:street":"Rue Muzet",
    "iso:country":"BE",
    "sg:address":"Rue Muzet 47",
    "sg:city":"Namur (saint-servais)",
    "sg:classifiers":[
        {
            "category":"Education",
            "subcategory":"School",
            "type":"Public Place"
        }
    ],
    "sg:phone":"+32 81 73 08 23",
    "sg:postcode":"5002",
    "sg:province":"Namur",
    "sg:tags":[
        "boarding"
    ],
    "wof:name":"Internat Autonome Gar\u00e7ons",
    "wof:placetype":"venue"
},
  "geometry": {"coordinates":[4.8547101021,50.4718017578],"type":"Point"}
}