{
  "type": "Feature",
  "properties": {
    "addr:full":"Turnhoutseweg 71 Beerse Antwerpen 2340",
    "addr:housenumber":"71",
    "addr:postcode":"2340",
    "addr:street":"Turnhoutseweg",
    "iso:country":"BE",
    "sg:address":"Turnhoutseweg 71",
    "sg:city":"Beerse",
    "sg:classifiers":[
        {
            "category":"Recreation",
            "subcategory":"Dance Hall",
            "type":"Entertainment"
        }
    ],
    "sg:phone":"+32 14 61 61 79",
    "sg:postcode":"2340",
    "sg:province":"Antwerpen",
    "sg:tags":[
        "discotheque"
    ],
    "wof:name":"Dancing Dennenoord Bvba",
    "wof:placetype":"venue"
},
  "geometry": {"coordinates":[4.8666009903,51.3119277954],"type":"Point"}
}