{
  "type": "Feature",
  "properties": {
    "iso:country":"BE",
    "sg:address":"Kloosterstraat 53",
    "sg:city":"Londerzeel (malderen)",
    "sg:classifiers":[
        {
            "category":"Building & Trades",
            "subcategory":"Construction",
            "type":"Services"
        }
    ],
    "sg:phone":"+32 52 33 32 96",
    "sg:postcode":"1840",
    "sg:province":"Vlaams-Brabant",
    "sg:tags":[
        "carpenter"
    ],
    "wof:name":"Van Sande C",
    "wof:placetype":"venue"
},
  "geometry": {"coordinates":[4.2426152229,51.0161399841],"type":"Point"}
}