{
  "type": "Feature",
  "properties": {
    "iso:country":"BE",
    "sg:address":"Avenue De La Lib\u00c9ration 17",
    "sg:city":"Soumagne",
    "sg:orig_category":"Fournitures de bureau. Tabac. Journaux",
    "sg:phone":"+32 4 358 86 13",
    "sg:postcode":"4630",
    "sg:province":"Li\u00e8ge",
    "wof:name":"Felix Kockelkorn",
    "wof:placetype":"venue"
},
  "geometry": {"coordinates":[5.712334156,50.6097259521],"type":"Point"}
}