{
  "type": "Feature",
  "properties": {
    "iso:country":"BE",
    "sg:address":"Heembeeksestraat 71",
    "sg:city":"Brussel/bruxelles",
    "sg:orig_category":"Loodgieterij, verwarming and sanitaire installaties",
    "sg:phone":"+32 497 53 45 83",
    "sg:postcode":"1120",
    "sg:province":"Bruxelles-Capitale",
    "wof:name":"Chauffage A.d.g.",
    "wof:placetype":"venue"
},
  "geometry": {"coordinates":[4.3774518967,50.8898010254],"type":"Point"}
}