{
  "type": "Feature",
  "properties": {
    "addr:full":"Van Tieghemstraat 2 Berlare Oost-Vlaanderen 9290",
    "addr:housenumber":"2",
    "addr:postcode":"9290",
    "addr:street":"Van Tieghemstraat",
    "iso:country":"BE",
    "sg:address":"Van Tieghemstraat 2",
    "sg:city":"Berlare",
    "sg:orig_category":"Fleurs and plantes",
    "sg:phone":"+32 52 42 31 33",
    "sg:postcode":"9290",
    "sg:province":"Oost-Vlaanderen",
    "wof:name":"Van Lerberghe",
    "wof:placetype":"venue"
},
  "geometry": {"coordinates":[4.0074682236,51.0217285156],"type":"Point"}
}