{
  "type": "Feature",
  "properties": {
    "iso:country":"BE",
    "sg:address":"Avenue De La Gare 1",
    "sg:city":"Arlon",
    "sg:orig_category":"Hypotheken and hypotheekbanken Verbruikerskredietinstellingen",
    "sg:phone":"+32 63 23 26 74",
    "sg:postcode":"6700",
    "sg:province":"Luxembourg",
    "wof:name":"C.o.a.l.",
    "wof:placetype":"venue"
},
  "geometry": {"coordinates":[5.811560154,49.6808242798],"type":"Point"}
}