{
  "type": "Feature",
  "properties": {
    "iso:country":"BE",
    "sg:address":"Landbouwersstraat 22",
    "sg:city":"Oostende",
    "sg:classifiers":[
        {
            "category":"Communications",
            "subcategory":"Radio Station",
            "type":"Services"
        }
    ],
    "sg:phone":"+32 59 50 46 40",
    "sg:postcode":"8400",
    "sg:province":"West-Vlaanderen",
    "sg:tags":[
        "diffusion",
        "production",
        "de",
        "programme"
    ],
    "wof:name":"Radio 't Visschertje",
    "wof:placetype":"venue"
},
  "geometry": {"coordinates":[2.8940210342,51.2168197632],"type":"Point"}
}