{
  "type": "Feature",
  "properties": {
    "iso:country":"BE",
    "sg:address":"Veldstraat 4be",
    "sg:city":"Bilzen",
    "sg:orig_category":"Installation \u00e9lectrique r\u00e9sidentielle",
    "sg:phone":"+32 89 41 31 21",
    "sg:postcode":"3740",
    "sg:province":"Limburg",
    "wof:name":"Electro Biesmans Install.",
    "wof:placetype":"venue"
},
  "geometry": {"coordinates":[5.5744361877,50.8787536621],"type":"Point"}
}