{
  "type": "Feature",
  "properties": {
    "iso:country":"BE",
    "sg:address":"Rue D'angleterre 42",
    "sg:city":"Sint-gillis/saint-gilles",
    "sg:classifiers":[
        {
            "category":"Restaurant",
            "type":"Food & Drink"
        }
    ],
    "sg:phone":"+32 2 537 09 78",
    "sg:postcode":"1060",
    "sg:province":"Bruxelles-Capitale",
    "wof:name":"Snack-bar Le Calao",
    "wof:placetype":"venue"
},
  "geometry": {"coordinates":[4.3406400681,50.8351211548],"type":"Point"}
}