{
  "type": "Feature",
  "properties": {
    "iso:country":"BE",
    "sg:address":"Stationsstraat 33",
    "sg:city":"Leopoldsburg",
    "sg:classifiers":[
        {
            "category":"Shopping",
            "subcategory":"Clothing, Apparel, & Fashions",
            "type":"Retail Goods"
        }
    ],
    "sg:phone":"+32 11 34 67 82",
    "sg:postcode":"3970",
    "sg:province":"Limburg",
    "sg:tags":[
        "boutique"
    ],
    "wof:name":"Vestido",
    "wof:placetype":"venue"
},
  "geometry": {"coordinates":[5.2607188225,51.1178512573],"type":"Point"}
}