{
  "type": "Feature",
  "properties": {
    "addr:full":"Moeskroenstraat 461 Menen (rekkem) West-Vlaanderen 8930",
    "addr:housenumber":"461",
    "addr:postcode":"8930",
    "addr:street":"Moeskroenstraat",
    "iso:country":"BE",
    "sg:address":"Moeskroenstraat 461",
    "sg:city":"Menen (rekkem)",
    "sg:classifiers":[
        {
            "category":"Home & Garden",
            "subcategory":"Garden Supply",
            "type":"Retail Goods"
        }
    ],
    "sg:phone":"+32 56 40 19 86",
    "sg:postcode":"8930",
    "sg:province":"West-Vlaanderen",
    "sg:tags":[
        "lawn",
        "mower"
    ],
    "wof:name":"Kint M",
    "wof:placetype":"venue"
},
  "geometry": {"coordinates":[3.1625540257,50.7847099304],"type":"Point"}
}