{
  "type": "Feature",
  "properties": {
    "addr:full":"Avenue De Norv\u00e8ge 14 Malmedy Li\u00e8ge 4960",
    "addr:housenumber":"14",
    "addr:postcode":"4960",
    "addr:street":"Avenue De Norve\u0300Ge",
    "iso:country":"BE",
    "sg:address":"Avenue De Norv\u00e8ge 14",
    "sg:city":"Malmedy",
    "sg:classifiers":[
        {
            "category":"Wholesale",
            "subcategory":"Meat",
            "type":"Manufacturing & Wholesale Goods"
        }
    ],
    "sg:phone":"+32 80 77 03 72",
    "sg:postcode":"4960",
    "sg:province":"Li\u00e8ge",
    "sg:tags":[
        "whol",
        "-"
    ],
    "wof:name":"Porc Qualit\u00e9 Ardenne",
    "wof:placetype":"venue"
},
  "geometry": {"coordinates":[6.0031409264,50.4154472351],"type":"Point"}
}