{
  "type": "Feature",
  "properties": {
    "addr:full":"Rue Des P\u00e9pini\u00e8res 64 Li\u00e8ge 1 (ch\u00ean\u00e9e) Li\u00e8ge 4032",
    "addr:housenumber":"64;1",
    "addr:postcode":"4032",
    "addr:street":"Rue Des Pe\u0301Pinie\u0300Res",
    "iso:country":"BE",
    "sg:address":"Rue Des P\u00e9pini\u00e8res 64",
    "sg:city":"Li\u00e8ge 1 (ch\u00ean\u00e9e)",
    "sg:classifiers":[
        {
            "category":"Food & Beverages",
            "subcategory":"Groceries & Convenience Stores",
            "type":"Retail Goods"
        }
    ],
    "sg:phone":"+32 4 366 03 33",
    "sg:postcode":"4032",
    "sg:province":"Li\u00e8ge",
    "sg:tags":[
        "grocer"
    ],
    "wof:name":"Salade De Fruits",
    "wof:placetype":"venue"
},
  "geometry": {"coordinates":[5.6219792366,50.6225280762],"type":"Point"}
}