{
  "type": "Feature",
  "properties": {
    "addr:full":"Dorp West 14 Zwijndrecht Antwerpen 2070",
    "addr:housenumber":"14",
    "addr:postcode":"2070",
    "addr:street":"Dorp West",
    "iso:country":"BE",
    "sg:address":"Dorp West 14",
    "sg:city":"Zwijndrecht",
    "sg:orig_category":"Kapsalons",
    "sg:phone":"+32 3 252 84 91",
    "sg:postcode":"2070",
    "sg:province":"Antwerpen",
    "wof:name":"Coiffure Penelope",
    "wof:placetype":"venue"
},
  "geometry": {"coordinates":[4.3255190849,51.2190856934],"type":"Point"}
}