{
  "type": "Feature",
  "properties": {
    "addr:full":"Kortrijkstraat 52 Ingelmunster West-Vlaanderen 8770",
    "addr:housenumber":"52",
    "addr:postcode":"8770",
    "addr:street":"Kortrijkstraat",
    "iso:country":"BE",
    "sg:address":"Kortrijkstraat 52",
    "sg:city":"Ingelmunster",
    "sg:classifiers":[
        {
            "category":"Insurance",
            "subcategory":"Life Insurance",
            "type":"Services"
        }
    ],
    "sg:phone":"+32 51 30 95 00",
    "sg:postcode":"8770",
    "sg:province":"West-Vlaanderen",
    "sg:tags":[
        "assurance"
    ],
    "wof:name":"Ippa",
    "wof:placetype":"venue"
},
  "geometry": {"coordinates":[3.2583770752,50.9104614258],"type":"Point"}
}