{
  "type": "Feature",
  "properties": {
    "iso:country":"BE",
    "sg:address":"Voie Des Sauvages M\u00eal\u00e9es 38",
    "sg:city":"Bl\u00e9gny (saive)",
    "sg:classifiers":[
        {
            "category":"Building & Trades",
            "subcategory":"Landscaping Services",
            "type":"Services"
        }
    ],
    "sg:phone":"+32 4 362 47 00",
    "sg:postcode":"4671",
    "sg:province":"Li\u00e8ge",
    "sg:tags":[
        "-",
        "lopping",
        "work",
        "tree",
        "felling"
    ],
    "wof:name":"Machiels J-p",
    "wof:placetype":"venue"
},
  "geometry": {"coordinates":[5.6734981537,50.6457939148],"type":"Point"}
}