{
  "type": "Feature",
  "properties": {
    "addr:full":"Opitterkiezel 238 Bree (opitter) Limburg 3960",
    "addr:housenumber":"238",
    "addr:postcode":"3960",
    "addr:street":"Opitterkiezel",
    "iso:country":"BE",
    "sg:address":"Opitterkiezel 238",
    "sg:city":"Bree (opitter)",
    "sg:orig_category":"Non-Classified Establishments",
    "sg:phone":"+32 89 86 41 52",
    "sg:postcode":"3960",
    "sg:province":"Limburg",
    "wof:name":"L T M",
    "wof:placetype":"venue"
},
  "geometry": {"coordinates":[5.6164898872,51.1324691772],"type":"Point"}
}