{
  "type": "Feature",
  "properties": {
    "iso:country":"BE",
    "sg:address":"Hoeksken 12",
    "sg:city":"Evergem",
    "sg:orig_category":"Slagers",
    "sg:phone":"+32 9 253 83 17",
    "sg:postcode":"9940",
    "sg:province":"Oost-Vlaanderen",
    "wof:name":"Beenhouwerij Chris",
    "wof:placetype":"venue"
},
  "geometry": {"coordinates":[3.7067298889,51.110080719],"type":"Point"}
}