{
  "type": "Feature",
  "properties": {
    "addr:full":"Boudewijnstraat 17 Brecht Antwerpen 2960",
    "addr:housenumber":"17",
    "addr:postcode":"2960",
    "addr:street":"Boudewijnstraat",
    "iso:country":"BE",
    "sg:address":"Boudewijnstraat 17",
    "sg:city":"Brecht",
    "sg:orig_category":"Goederenvervoer over de weg",
    "sg:phone":"+32 3 313 71 06",
    "sg:postcode":"2960",
    "sg:province":"Antwerpen",
    "wof:name":"Boogaerts",
    "wof:placetype":"venue"
},
  "geometry": {"coordinates":[4.6490850449,51.3336372375],"type":"Point"}
}