{
  "type": "Feature",
  "properties": {
    "addr:full":"Rue De L\u00b4abattoir 32 Waudrez Hainaut 7131",
    "addr:housenumber":"32",
    "addr:postcode":"7131",
    "addr:street":"Rue De L\u00b4Abattoir;Hainaut",
    "iso:country":"BE",
    "sg:address":"Rue De L\u00b4abattoir 32",
    "sg:city":"Waudrez",
    "sg:orig_category":"Elektrische installaties voor woningen Plaatsen van vloer- and muurbekleding Schilders",
    "sg:phone":"+32 64 33 12 13",
    "sg:postcode":"7131",
    "sg:province":"Hainaut",
    "wof:name":"Domoservice",
    "wof:placetype":"venue"
},
  "geometry": {"coordinates":[4.1608581543,50.4155731201],"type":"Point"}
}