{
  "type": "Feature",
  "properties": {
    "iso:country":"BE",
    "sg:address":"Walheimer Strasse 37",
    "sg:city":"Raeren",
    "sg:orig_category":"Meubelzaken, woning- and keukeninrichting",
    "sg:phone":"+32 87 85 04 88",
    "sg:postcode":"4730",
    "sg:province":"Li\u00e8ge",
    "wof:name":"Interbett",
    "wof:placetype":"venue"
},
  "geometry": {"coordinates":[6.1394600868,50.6789512634],"type":"Point"}
}