{
  "type": "Feature",
  "properties": {
    "iso:country":"BE",
    "sg:address":"Mosstraat 2",
    "sg:city":"Halen",
    "sg:orig_category":"Plomberie, chauffage and installations sanitaires",
    "sg:phone":"+32 13 44 11 89",
    "sg:postcode":"3545",
    "sg:province":"Limburg",
    "wof:name":"Herbots",
    "wof:placetype":"venue"
},
  "geometry": {"coordinates":[5.11587286,50.9499664307],"type":"Point"}
}