{
  "type": "Feature",
  "properties": {
    "addr:full":"Vlaanderenstraat 13 Destelbergen Oost-Vlaanderen 9070",
    "addr:housenumber":"13",
    "addr:postcode":"9070",
    "addr:street":"Vlaanderenstraat",
    "iso:country":"BE",
    "sg:address":"Vlaanderenstraat 13",
    "sg:city":"Destelbergen",
    "sg:classifiers":[
        {
            "category":"Building & Trades",
            "subcategory":"Landscaping Services",
            "type":"Services"
        }
    ],
    "sg:phone":"+32 9 228 17 28",
    "sg:postcode":"9070",
    "sg:province":"Oost-Vlaanderen",
    "sg:tags":[
        "architect",
        "landscape"
    ],
    "wof:name":"Otium",
    "wof:placetype":"venue"
},
  "geometry": {"coordinates":[3.7669270039,51.0545120239],"type":"Point"}
}