{
  "type": "Feature",
  "properties": {
    "iso:country":"BE",
    "sg:address":"Mechelsesteenweg 37",
    "sg:city":"Sint-katelijne-waver",
    "sg:orig_category":"Loodgieterij, verwarming and sanitaire installaties",
    "sg:phone":"+32 15 55 08 95",
    "sg:postcode":"2860",
    "sg:province":"Antwerpen",
    "wof:name":"W Vercammen",
    "wof:placetype":"venue"
},
  "geometry": {"coordinates":[4.5300908089,51.0631065369],"type":"Point"}
}