{
  "type": "Feature",
  "properties": {
    "addr:full":"Nieuwstraat 1 Geel Antwerpen 2440",
    "addr:housenumber":"1",
    "addr:postcode":"2440",
    "addr:street":"Nieuwstraat",
    "iso:country":"BE",
    "sg:address":"Nieuwstraat 1",
    "sg:city":"Geel",
    "sg:orig_category":"Agences d\u00b4interim and personnel temporaire",
    "sg:phone":"+32 14 56 46 40",
    "sg:postcode":"2440",
    "sg:province":"Antwerpen",
    "wof:name":"Ago Interim",
    "wof:placetype":"venue"
},
  "geometry": {"coordinates":[4.9912939072,51.1624717712],"type":"Point"}
}