{
  "type": "Feature",
  "properties": {
    "iso:country":"BE",
    "sg:address":"Coupure Links 369",
    "sg:city":"Gent",
    "sg:orig_category":"M\u00e9decins and sp\u00e9cialistes",
    "sg:phone":"+32 9 225 16 08",
    "sg:postcode":"9000",
    "sg:province":"Oost-Vlaanderen",
    "wof:name":"Annie Morraye",
    "wof:placetype":"venue"
},
  "geometry": {"coordinates":[3.7110879421,51.0493774414],"type":"Point"}
}