{
  "type": "Feature",
  "properties": {
    "addr:full":"Kortessemstraat 27 Wellen Limburg 3830",
    "addr:housenumber":"27",
    "addr:postcode":"3830",
    "addr:street":"Kortessemstraat",
    "iso:country":"BE",
    "sg:address":"Kortessemstraat 27",
    "sg:city":"Wellen",
    "sg:orig_category":"Enseignement maternel and primaire",
    "sg:phone":"+32 12 74 40 51",
    "sg:postcode":"3830",
    "sg:province":"Limburg",
    "wof:name":"Vrije Kleuterschool",
    "wof:placetype":"venue"
},
  "geometry": {"coordinates":[5.3582820892,50.8357620239],"type":"Point"}
}