{
  "type": "Feature",
  "properties": {
    "iso:country":"BE",
    "sg:address":"Nati\u00ebnlaan 85",
    "sg:city":"Knokke-heist (knokke)",
    "sg:classifiers":[
        {
            "category":"Retail",
            "subcategory":"Funeral Services",
            "type":"Services"
        }
    ],
    "sg:phone":"+32 50 60 56 05",
    "sg:postcode":"8300",
    "sg:province":"West-Vlaanderen",
    "sg:tags":[
        "director"
    ],
    "wof:name":"Abo Oostkust-uitvaartcentrum",
    "wof:placetype":"venue"
},
  "geometry": {"coordinates":[3.2890501022,51.3361816406],"type":"Point"}
}