{
  "type": "Feature",
  "properties": {
    "addr:full":"Antwerpsesteenweg 100 Gent Oost-Vlaanderen 9000",
    "addr:housenumber":"100",
    "addr:postcode":"9000",
    "addr:street":"Antwerpsesteenweg;Oost-Vlaanderen",
    "iso:country":"BE",
    "sg:address":"Antwerpsesteenweg 100",
    "sg:city":"Gent",
    "sg:orig_category":"Apotheken",
    "sg:phone":"+32 9 228 17 17",
    "sg:postcode":"9000",
    "sg:province":"Oost-Vlaanderen",
    "wof:name":"Johan Coppens",
    "wof:placetype":"venue"
},
  "geometry": {"coordinates":[3.7440199852,51.0586509705],"type":"Point"}
}