{
  "type": "Feature",
  "properties": {
    "addr:full":"All\u00e9e De Buzet 10 Vis\u00e9 (richelle) Li\u00e8ge 4600",
    "addr:housenumber":"10",
    "addr:postcode":"4600",
    "addr:street":"Alle\u0301E De Buzet",
    "iso:country":"BE",
    "sg:address":"All\u00e9e De Buzet 10",
    "sg:city":"Vis\u00e9 (richelle)",
    "sg:classifiers":[
        {
            "category":"Building & Trades",
            "subcategory":"Landscaping Services",
            "type":"Services"
        }
    ],
    "sg:phone":"+32 4 379 62 64",
    "sg:postcode":"4600",
    "sg:province":"Li\u00e8ge",
    "sg:tags":[
        "equipment",
        "swimming",
        "-",
        "pool",
        "contractor"
    ],
    "wof:name":"Nd Piscines",
    "wof:placetype":"venue"
},
  "geometry": {"coordinates":[5.6971969604,50.7173042297],"type":"Point"}
}