{
  "type": "Feature",
  "properties": {
    "addr:full":"Rue De Loverval 145 Chatelet Hainaut 6200",
    "addr:housenumber":"145",
    "addr:postcode":"chatelet;6200",
    "addr:street":"Rue De Loverval",
    "iso:country":"BE",
    "sg:address":"Rue De Loverval 145",
    "sg:city":"Chatelet",
    "sg:orig_category":"Enseignement maternel and primaire",
    "sg:phone":"+32 71 38 59 86",
    "sg:postcode":"6200",
    "sg:province":"Hainaut",
    "wof:name":"Ecole Fond. Communale",
    "wof:placetype":"venue"
},
  "geometry": {"coordinates":[4.4983649254,50.3910751343],"type":"Point"}
}