{
  "type": "Feature",
  "properties": {
    "addr:full":"Oosterzelesteenweg 127 Wetteren Oost-Vlaanderen 9230",
    "addr:housenumber":"127",
    "addr:postcode":"9230",
    "addr:street":"Oosterzelesteenweg",
    "iso:country":"BE",
    "sg:address":"Oosterzelesteenweg 127",
    "sg:city":"Wetteren",
    "sg:classifiers":[
        {
            "category":"Shopping",
            "subcategory":"Bicycles & Sporting Goods",
            "type":"Retail Goods"
        }
    ],
    "sg:phone":"+32 9 366 48 47",
    "sg:postcode":"9230",
    "sg:province":"Oost-Vlaanderen",
    "sg:tags":[
        "sport",
        "-"
    ],
    "wof:name":"Gunther Schepens Sport",
    "wof:placetype":"venue"
},
  "geometry": {"coordinates":[3.8318450451,50.9733848572],"type":"Point"}
}