{
  "type": "Feature",
  "properties": {
    "addr:full":"Lochtemanweg 7 Beringen Limburg 3580",
    "addr:housenumber":"7",
    "addr:postcode":"3580",
    "addr:street":"Lochtemanweg",
    "iso:country":"BE",
    "sg:address":"Lochtemanweg 7",
    "sg:city":"Beringen",
    "sg:classifiers":[
        {
            "category":"Food & Beverages",
            "subcategory":"Groceries & Convenience Stores",
            "type":"Retail Goods"
        }
    ],
    "sg:phone":"+32 11 45 04 20",
    "sg:postcode":"3580",
    "sg:province":"Limburg",
    "sg:tags":[
        "product",
        "grain",
        "cereal",
        "related"
    ],
    "wof:name":"Crea Food Nv",
    "wof:placetype":"venue"
},
  "geometry": {"coordinates":[5.2244172096,51.0376701355],"type":"Point"}
}