{
  "type": "Feature",
  "properties": {
    "iso:country":"BE",
    "sg:address":"Bilzersteenweg 90",
    "sg:city":"Riemst (vlijtingen)",
    "sg:classifiers":[
        {
            "category":"Banks & Credit Unions",
            "subcategory":"Investment Brokerage",
            "type":"Services"
        }
    ],
    "sg:phone":"+32 12 45 11 70",
    "sg:postcode":"3770",
    "sg:province":"Limburg",
    "sg:tags":[
        "repair",
        "-",
        "installation",
        "sanitary",
        "article"
    ],
    "wof:name":"Daenen-box & Zoon",
    "wof:placetype":"venue"
},
  "geometry": {"coordinates":[5.591750145,50.8165893555],"type":"Point"}
}