{
  "type": "Feature",
  "properties": {
    "iso:country":"BE",
    "sg:address":"Chauss\u00e9e De Mons 91",
    "sg:city":"Seneffe",
    "sg:classifiers":[
        {
            "category":"Fast Food",
            "type":"Food & Drink"
        }
    ],
    "sg:phone":"+32 64 55 70 75",
    "sg:postcode":"7180",
    "sg:province":"Hainaut",
    "sg:tags":[
        "fried",
        "stand",
        "potato"
    ],
    "wof:name":"Pont De Binche (au)",
    "wof:placetype":"venue"
},
  "geometry": {"coordinates":[4.2503628731,50.5204315186],"type":"Point"}
}