{
  "type": "Feature",
  "properties": {
    "iso:country":"BE",
    "sg:address":"Drogenbroodstraat 10",
    "sg:city":"Aalter",
    "sg:orig_category":"Locations de machines and \u00e9quipement pour la construction. Promoteurs immobiliers",
    "sg:phone":"+32 9 374 04 06",
    "sg:postcode":"9880",
    "sg:province":"Oost-Vlaanderen",
    "wof:name":"Ginvest",
    "wof:placetype":"venue"
},
  "geometry": {"coordinates":[3.4449028969,51.0962524414],"type":"Point"}
}