{
  "type": "Feature",
  "properties": {
    "addr:full":"Rue Lesbroussart 76 Bruxelles (ixelles) Bruxelles-Capitale 1050",
    "addr:housenumber":"76",
    "addr:postcode":"1050",
    "addr:street":"Rue Lesbroussart",
    "iso:country":"BE",
    "sg:address":"Rue Lesbroussart 76",
    "sg:city":"Bruxelles (ixelles)",
    "sg:classifiers":[
        {
            "category":"Retail",
            "subcategory":"Event Space",
            "type":"Services"
        }
    ],
    "sg:phone":"+32 2 644 04 09",
    "sg:postcode":"1050",
    "sg:province":"Bruxelles-Capitale",
    "sg:tags":[
        "organisation"
    ],
    "wof:name":"Pearl Agency",
    "wof:placetype":"venue"
},
  "geometry": {"coordinates":[4.3673090935,50.8275337219],"type":"Point"}
}