{
  "type": "Feature",
  "properties": {
    "iso:country":"BE",
    "sg:address":"Begijnengracht 9",
    "sg:city":"Gent",
    "sg:orig_category":"R\u00e9paration and restauration de meubles. Artistes ind\u00e9pendants",
    "sg:phone":"+32 9 223 49 54",
    "sg:postcode":"9000",
    "sg:province":"Oost-Vlaanderen",
    "wof:name":"Bart Verbeke",
    "wof:placetype":"venue"
},
  "geometry": {"coordinates":[3.7137799263,51.0561103821],"type":"Point"}
}