{
  "type": "Feature",
  "properties": {
    "addr:full":"Zuidervest 15 Peer Limburg 3990",
    "addr:housenumber":"15",
    "addr:postcode":"3990",
    "addr:street":"Zuidervest",
    "iso:country":"BE",
    "sg:address":"Zuidervest 15",
    "sg:city":"Peer",
    "sg:orig_category":"Radioproductie and uitzendingen",
    "sg:phone":"+32 11 63 17 82",
    "sg:postcode":"3990",
    "sg:province":"Limburg",
    "wof:name":"Radio Holiday",
    "wof:placetype":"venue"
},
  "geometry": {"coordinates":[5.4761929512,51.0805091858],"type":"Point"}
}