{
  "type": "Feature",
  "properties": {
    "iso:country":"BE",
    "sg:address":"Rue Du Brou 54",
    "sg:city":"Verviers",
    "sg:orig_category":"Juwelen and horloges",
    "sg:phone":"+32 87 34 04 03",
    "sg:postcode":"4800",
    "sg:province":"Li\u00e8ge",
    "wof:name":"M\u00c9taux Pr\u00c9cieux",
    "wof:placetype":"venue"
},
  "geometry": {"coordinates":[5.8583889008,50.5924377441],"type":"Point"}
}