{
  "type": "Feature",
  "properties": {
    "addr:full":"Brusselsesteenweg 2 Mechelen (groot) Antwerpen 2800",
    "addr:housenumber":"2",
    "addr:postcode":"2800",
    "addr:street":"Brusselsesteenweg;Groot Antwerpen",
    "iso:country":"BE",
    "sg:address":"Brusselsesteenweg 2",
    "sg:city":"Mechelen (groot)",
    "sg:classifiers":[
        {
            "category":"Travel",
            "subcategory":"Hotels & Motels",
            "type":"Entertainment"
        }
    ],
    "sg:phone":"+32 15 42 25 35",
    "sg:postcode":"2800",
    "sg:province":"Antwerpen",
    "sg:tags":[
        "western",
        "best"
    ],
    "wof:name":"Bw Hotel Gulden Anker",
    "wof:placetype":"venue"
},
  "geometry": {"coordinates":[4.471601963,51.0208358765],"type":"Point"}
}