{
  "type": "Feature",
  "properties": {
    "iso:country":"BE",
    "sg:address":"Rue Brogniez 72",
    "sg:city":"Bruxelles (anderlecht)",
    "sg:orig_category":"Non-Classified Establishments",
    "sg:phone":"+32 2 521 21 05",
    "sg:postcode":"1070",
    "sg:province":"Bruxelles-Capitale",
    "wof:name":"Jar International",
    "wof:placetype":"venue"
},
  "geometry": {"coordinates":[4.3356871605,50.8406982422],"type":"Point"}
}