{
  "type": "Feature",
  "properties": {
    "addr:full":"Rue E. Parfonry 94 Hotton Luxembourg 6990",
    "addr:housenumber":"94",
    "addr:postcode":"6990",
    "addr:street":"Rue E. Parfonry",
    "iso:country":"BE",
    "sg:address":"Rue E. Parfonry 94",
    "sg:city":"Hotton",
    "sg:orig_category":"Herstellingen and onderhoud van auto's Onderdelen and accessoires voor auto's",
    "sg:phone":"+32 84 46 63 43",
    "sg:postcode":"6990",
    "sg:province":"Luxembourg",
    "wof:name":"Lucky Pneus",
    "wof:placetype":"venue"
},
  "geometry": {"coordinates":[5.4353947639,50.2622184753],"type":"Point"}
}