{
  "type": "Feature",
  "properties": {
    "addr:full":"Ambachtsschoolstraat 27 Hasselt Limburg 3500",
    "addr:housenumber":"27",
    "addr:postcode":"3500",
    "addr:street":"Ambachtsschoolstraat",
    "iso:country":"BE",
    "sg:address":"Ambachtsschoolstraat 27",
    "sg:city":"Hasselt",
    "sg:orig_category":"Machines-outils Pompes and compresseurs Fab",
    "sg:phone":"+32 11 25 22 44",
    "sg:postcode":"3500",
    "sg:province":"Limburg",
    "wof:name":"Strok Pompen",
    "wof:placetype":"venue"
},
  "geometry": {"coordinates":[5.3214578629,50.9341011047],"type":"Point"}
}