{
  "type": "Feature",
  "properties": {
    "addr:full":"Rue L\u00e9opold Et Victorien Barr\u00e9 19 Dinant Namur 5500",
    "addr:housenumber":"19",
    "addr:postcode":"5500",
    "addr:street":"Rue Le\u0301Opold Et Victorien Barre\u0301",
    "iso:country":"BE",
    "sg:address":"Rue L\u00e9opold Et Victorien Barr\u00e9 19",
    "sg:city":"Dinant",
    "sg:classifiers":[
        {
            "category":"Professional",
            "subcategory":"Accounting & Tax Preparation",
            "type":"Services"
        }
    ],
    "sg:phone":"+32 82 22 42 08",
    "sg:postcode":"5500",
    "sg:province":"Namur",
    "sg:tags":[
        "bookkeeper"
    ],
    "wof:name":"Fivet D",
    "wof:placetype":"venue"
},
  "geometry": {"coordinates":[4.9087848663,50.263961792],"type":"Point"}
}