{
  "type": "Feature",
  "properties": {
    "iso:country":"BE",
    "sg:address":"Reaalstraat 12",
    "sg:city":"Ninove",
    "sg:orig_category":"Rundveehouders",
    "sg:phone":"+32 54 33 85 76",
    "sg:postcode":"9400",
    "sg:province":"Oost-Vlaanderen",
    "wof:name":"Albert Scheerlinck",
    "wof:placetype":"venue"
},
  "geometry": {"coordinates":[3.9705600739,50.8488693237],"type":"Point"}
}