{
  "type": "Feature",
  "properties": {
    "addr:full":"Rue Des Choux 41 Ronse/renaix Oost-Vlaanderen 9600",
    "addr:housenumber":"41",
    "addr:postcode":"9600",
    "addr:street":"Rue Des Choux",
    "iso:country":"BE",
    "sg:address":"Rue Des Choux 41",
    "sg:city":"Ronse/renaix",
    "sg:orig_category":"Electrom\u00e9nager, t\u00e9l\u00e9visions and radios",
    "sg:phone":"+32 55 21 24 66",
    "sg:postcode":"9600",
    "sg:province":"Oost-Vlaanderen",
    "wof:name":"Hifi-dia Gallery",
    "wof:placetype":"venue"
},
  "geometry": {"coordinates":[3.6192901134,50.7563476562],"type":"Point"}
}