{
  "type": "Feature",
  "properties": {
    "addr:full":"Retiesebaan 18 Kasterlee Antwerpen 2460",
    "addr:housenumber":"18",
    "addr:postcode":"2460",
    "addr:street":"Retiesebaan",
    "iso:country":"BE",
    "sg:address":"Retiesebaan 18",
    "sg:city":"Kasterlee",
    "sg:orig_category":"Epiceries",
    "sg:phone":"+32 14 85 09 22",
    "sg:postcode":"2460",
    "sg:province":"Antwerpen",
    "wof:name":"Spar",
    "wof:placetype":"venue"
},
  "geometry": {"coordinates":[4.9699139595,51.2409934998],"type":"Point"}
}