{
  "type": "Feature",
  "properties": {
    "addr:full":"Kloosterstraat 90 Lille Antwerpen 2275",
    "addr:housenumber":"90",
    "addr:postcode":"2275",
    "addr:street":"Kloosterstraat",
    "iso:country":"BE",
    "sg:address":"Kloosterstraat 90",
    "sg:city":"Lille",
    "sg:classifiers":[
        {
            "category":"Cafe",
            "type":"Food & Drink"
        }
    ],
    "sg:phone":"+32 14 55 78 36",
    "sg:postcode":"2275",
    "sg:province":"Antwerpen",
    "sg:tags":[
        "caf\u00e9s"
    ],
    "wof:name":"Maria Proost",
    "wof:placetype":"venue"
},
  "geometry": {"coordinates":[4.8621029854,51.2631378174],"type":"Point"}
}