{
  "type": "Feature",
  "properties": {
    "addr:full":"Noordlaan 10 Genk Limburg 3600",
    "addr:housenumber":"10",
    "addr:postcode":"3600",
    "addr:street":"Noordlaan",
    "iso:country":"BE",
    "sg:address":"Noordlaan 10",
    "sg:city":"Genk",
    "sg:classifiers":[
        {
            "category":"Bars & Pubs",
            "type":"Food & Drink"
        }
    ],
    "sg:phone":"+32 89 30 76 35",
    "sg:postcode":"3600",
    "sg:province":"Limburg",
    "wof:name":"Limburg",
    "wof:placetype":"venue"
},
  "geometry": {"coordinates":[5.4806418419,50.9774093628],"type":"Point"}
}