{
  "type": "Feature",
  "properties": {
    "iso:country":"BE",
    "sg:address":"Casselstraat 39",
    "sg:city":"Poperinge",
    "sg:classifiers":[
        {
            "category":"Insurance",
            "subcategory":"Insurance Agent",
            "type":"Services"
        }
    ],
    "sg:phone":"+32 57 33 38 93",
    "sg:postcode":"8970",
    "sg:province":"West-Vlaanderen",
    "sg:tags":[
        "verzekeringsmakelaars",
        "expert"
    ],
    "wof:name":"Poperings Verz.buro",
    "wof:placetype":"venue"
},
  "geometry": {"coordinates":[2.721544981,50.8531532288],"type":"Point"}
}