{
  "type": "Feature",
  "properties": {
    "iso:country":"BE",
    "sg:address":"Lisperstraat 9",
    "sg:city":"Lier",
    "sg:classifiers":[
        {
            "category":"Professional",
            "subcategory":"Testing Lab",
            "type":"Services"
        }
    ],
    "sg:phone":"+32 3 488 00 67",
    "sg:postcode":"2500",
    "sg:province":"Antwerpen",
    "sg:tags":[
        "chemist"
    ],
    "wof:name":"Van Dyck K",
    "wof:placetype":"venue"
},
  "geometry": {"coordinates":[4.5694708824,51.1317634583],"type":"Point"}
}