{
  "type": "Feature",
  "properties": {
    "addr:full":"Petite Rue Des Bouchers 25 Brussel/bruxelles Bruxelles-Capitale 1000",
    "addr:housenumber":"25",
    "addr:postcode":"1000",
    "addr:street":"Petite Rue Des Bouchers;/",
    "iso:country":"BE",
    "sg:address":"Petite Rue Des Bouchers 25",
    "sg:city":"Brussel/bruxelles",
    "sg:classifiers":[
        {
            "category":"Restaurant",
            "type":"Food & Drink"
        }
    ],
    "sg:phone":"+32 2 513 70 55",
    "sg:postcode":"1000",
    "sg:province":"Bruxelles-Capitale",
    "wof:name":"La Petite Provence",
    "wof:placetype":"venue"
},
  "geometry": {"coordinates":[4.3538508415,50.8479003906],"type":"Point"}
}