{
  "type": "Feature",
  "properties": {
    "addr:full":"Statieplaats 14 Veurne West-Vlaanderen 8630",
    "addr:housenumber":"14",
    "addr:postcode":"8630",
    "addr:street":"Statieplaats",
    "iso:country":"BE",
    "sg:address":"Statieplaats 14",
    "sg:city":"Veurne",
    "sg:orig_category":"Airconditioning and ventilatie Elektrische installaties voor woningen Huishoudapparaten, televisies ",
    "sg:phone":"+32 58 31 30 13",
    "sg:postcode":"8630",
    "sg:province":"West-Vlaanderen",
    "wof:name":"Elektro De Westhoek",
    "wof:placetype":"venue"
},
  "geometry": {"coordinates":[2.6708879471,51.0733070374],"type":"Point"}
}