{
  "type": "Feature",
  "properties": {
    "iso:country":"BE",
    "sg:address":"Schrijbergstraat 136",
    "sg:city":"Waasmunster",
    "sg:classifiers":[
        {
            "category":"Health Services",
            "subcategory":"Optometrist",
            "type":"Services"
        }
    ],
    "sg:phone":"+32 3 772 40 66",
    "sg:postcode":"9250",
    "sg:province":"Oost-Vlaanderen",
    "wof:name":"Brillenhuis",
    "wof:placetype":"venue"
},
  "geometry": {"coordinates":[4.0693697929,51.1391487122],"type":"Point"}
}