{
  "type": "Feature",
  "properties": {
    "iso:country":"BE",
    "sg:address":"Dullaertweg 81",
    "sg:city":"Gistel",
    "sg:orig_category":"Groententeelt",
    "sg:phone":"+32 59 27 80 27",
    "sg:postcode":"8470",
    "sg:province":"West-Vlaanderen",
    "wof:name":"Fernand Gevaert",
    "wof:placetype":"venue"
},
  "geometry": {"coordinates":[2.9962909222,51.1540908813],"type":"Point"}
}