{
  "type": "Feature",
  "properties": {
    "addr:full":"Troonstraat 20 Brussel/bruxelles Bruxelles-Capitale 1000",
    "addr:housenumber":"20",
    "addr:postcode":"1000",
    "addr:street":"Troonstraat;/",
    "iso:country":"BE",
    "sg:address":"Troonstraat 20",
    "sg:city":"Brussel/bruxelles",
    "sg:orig_category":"Artsen and specialisten",
    "sg:phone":"+32 2 512 53 47",
    "sg:postcode":"1000",
    "sg:province":"Bruxelles-Capitale",
    "wof:name":"Dick De Clercq",
    "wof:placetype":"venue"
},
  "geometry": {"coordinates":[4.3670830727,50.8395843506],"type":"Point"}
}