{
  "type": "Feature",
  "properties": {
    "iso:country":"BE",
    "sg:address":"Rue Chambre-au-pont 9",
    "sg:city":"Jemeppe-sur-sambre",
    "sg:orig_category":"Entretien and r\u00e9parations de voitures",
    "sg:phone":"+32 71 78 74 93",
    "sg:postcode":"5190",
    "sg:province":"Namur",
    "wof:name":"Carrosserie Dardenne",
    "wof:placetype":"venue"
},
  "geometry": {"coordinates":[4.6722941399,50.46352005],"type":"Point"}
}