{
  "type": "Feature",
  "properties": {
    "addr:full":"Untere Rottstrasse 17a Raeren Li\u00e8ge 4730",
    "addr:housenumber":"17a",
    "addr:postcode":"4730",
    "addr:street":"Untere Rottstrasse",
    "iso:country":"BE",
    "sg:address":"Untere Rottstrasse 17a",
    "sg:city":"Raeren",
    "sg:classifiers":[
        {
            "category":"Personal",
            "subcategory":"Beauty Salon",
            "type":"Services"
        }
    ],
    "sg:phone":"+32 87 85 18 34",
    "sg:postcode":"4730",
    "sg:province":"Li\u00e8ge",
    "sg:tags":[
        "lady",
        "-",
        "hairdressing"
    ],
    "wof:name":"Marion Salon",
    "wof:placetype":"venue"
},
  "geometry": {"coordinates":[6.1121811867,50.6648445129],"type":"Point"}
}