{
  "type": "Feature",
  "properties": {
    "iso:country":"BE",
    "sg:address":"Rue Horloz",
    "sg:city":"Saint-nicolas",
    "sg:orig_category":"Salles de conf\u00e9rences and de r\u00e9ceptions",
    "sg:phone":"+32 4 224 35 01",
    "sg:postcode":"4420",
    "sg:province":"Li\u00e8ge",
    "wof:name":"La Maison Blanche",
    "wof:placetype":"venue"
},
  "geometry": {"coordinates":[5.530933857,50.6285476685],"type":"Point"}
}