{
  "type": "Feature",
  "properties": {
    "addr:full":"Chemin De La Maison Du Roi 180 Braine-l'alleud Brabant Wallon 1420",
    "addr:housenumber":"180",
    "addr:postcode":"1420",
    "addr:street":"Chemin De La Maison Du Roi",
    "iso:country":"BE",
    "sg:address":"Chemin De La Maison Du Roi 180",
    "sg:city":"Braine-l'alleud",
    "sg:orig_category":"P\u00e9pini\u00e9ristes. Jardinage",
    "sg:phone":"+32 2 384 74 89",
    "sg:postcode":"1420",
    "sg:province":"Brabant Wallon",
    "wof:name":"Stanford Gardens",
    "wof:placetype":"venue"
},
  "geometry": {"coordinates":[4.7333202362,47.6654129028],"type":"Point"}
}