{
  "type": "Feature",
  "properties": {
    "iso:country":"BE",
    "sg:address":"Smalleweg 7",
    "sg:city":"Zottegem",
    "sg:classifiers":[
        {
            "category":"Manufacturing",
            "subcategory":"Rubber & Plastics",
            "type":"Manufacturing & Wholesale Goods"
        }
    ],
    "sg:phone":"+32 9 364 42 00",
    "sg:postcode":"9620",
    "sg:province":"Oost-Vlaanderen",
    "sg:tags":[
        "packaging",
        "material",
        "-"
    ],
    "wof:name":"Beschermde Werkplaats Vzw",
    "wof:placetype":"venue"
},
  "geometry": {"coordinates":[3.8170759678,50.880897522],"type":"Point"}
}