{
  "type": "Feature",
  "properties": {
    "addr:full":"Mechelsestraat 41 Leuven Vlaams-Brabant 3000",
    "addr:housenumber":"41",
    "addr:postcode":"3000",
    "addr:street":"Mechelsestraat",
    "iso:country":"BE",
    "sg:address":"Mechelsestraat 41",
    "sg:city":"Leuven",
    "sg:classifiers":[
        {
            "category":"Shopping",
            "subcategory":"Clothing, Apparel, & Fashions",
            "type":"Retail Goods"
        }
    ],
    "sg:phone":"+32 16 29 58 58",
    "sg:postcode":"3000",
    "sg:province":"Vlaams-Brabant",
    "sg:tags":[
        "boutique"
    ],
    "wof:name":"College",
    "wof:placetype":"venue"
},
  "geometry": {"coordinates":[4.6995358467,50.8809547424],"type":"Point"}
}