{
  "type": "Feature",
  "properties": {
    "iso:country":"BE",
    "sg:address":"Centrum Zuid 2049",
    "sg:city":"Houthalen-helchteren",
    "sg:orig_category":"Industri\u00eble and commerci\u00eble bouw",
    "sg:phone":"+32 11 60 56 56",
    "sg:postcode":"3530",
    "sg:province":"Limburg",
    "wof:name":"Interieur Reynders",
    "wof:placetype":"venue"
},
  "geometry": {"coordinates":[5.365486145,51.0150680542],"type":"Point"}
}