{
  "type": "Feature",
  "properties": {
    "addr:full":"Wittingstraat 33 Stekene Oost-Vlaanderen 9190",
    "addr:housenumber":"33",
    "addr:postcode":"9190",
    "addr:street":"Wittingstraat",
    "iso:country":"BE",
    "sg:address":"Wittingstraat 33",
    "sg:city":"Stekene",
    "sg:orig_category":"Eleveurs and marchands de porcs",
    "sg:phone":"+32 3 779 77 34",
    "sg:postcode":"9190",
    "sg:province":"Oost-Vlaanderen",
    "wof:name":"Gerard Linthout",
    "wof:placetype":"venue"
},
  "geometry": {"coordinates":[3.9984169006,51.1927947998],"type":"Point"}
}