{
  "type": "Feature",
  "properties": {
    "addr:full":"Pullaarsteenweg 83 Puurs Antwerpen 2870",
    "addr:housenumber":"83",
    "addr:postcode":"2870",
    "addr:street":"Pullaarsteenweg",
    "iso:country":"BE",
    "sg:address":"Pullaarsteenweg 83",
    "sg:city":"Puurs",
    "sg:orig_category":"M\u00e9decins and sp\u00e9cialistes",
    "sg:phone":"+32 3 866 22 72",
    "sg:postcode":"2870",
    "sg:province":"Antwerpen",
    "wof:name":"Ann Van Strubarq",
    "wof:placetype":"venue"
},
  "geometry": {"coordinates":[4.323882103,51.0704116821],"type":"Point"}
}