{
  "type": "Feature",
  "properties": {
    "addr:full":"Erpekommerweg 41 Peer (grote Brogel) Limburg 3990",
    "addr:housenumber":"41",
    "addr:postcode":"3990",
    "addr:street":"Erpekommerweg;Grote Brogel Limburg",
    "iso:country":"BE",
    "sg:address":"Erpekommerweg 41",
    "sg:city":"Peer (grote Brogel)",
    "sg:classifiers":[
        {
            "category":"Banks & Credit Unions",
            "subcategory":"Investment Brokerage",
            "type":"Services"
        }
    ],
    "sg:phone":"+32 11 63 10 68",
    "sg:postcode":"3990",
    "sg:province":"Limburg",
    "sg:tags":[
        "fence"
    ],
    "wof:name":"Evens Smederij",
    "wof:placetype":"venue"
},
  "geometry": {"coordinates":[5.4946160316,51.1217765808],"type":"Point"}
}