{
  "type": "Feature",
  "properties": {
    "iso:country":"BE",
    "sg:address":"Bergstrasse 158",
    "sg:city":"Eupen/eupen",
    "sg:orig_category":"Slagers",
    "sg:phone":"+32 87 74 26 94",
    "sg:postcode":"4700",
    "sg:province":"Li\u00e8ge",
    "wof:name":"Ludwig Dohm",
    "wof:placetype":"venue"
},
  "geometry": {"coordinates":[6.0344510078,50.6249160767],"type":"Point"}
}