{
  "type": "Feature",
  "properties": {
    "iso:country":"BE",
    "sg:address":"Ezelstraat 38",
    "sg:city":"Brugge",
    "sg:classifiers":[
        {
            "category":"Insurance",
            "subcategory":"Insurance Agent",
            "type":"Services"
        }
    ],
    "sg:phone":"+32 50 34 58 72",
    "sg:postcode":"8000",
    "sg:province":"West-Vlaanderen",
    "sg:tags":[
        "verzekeringsmakelaars",
        "expert"
    ],
    "wof:name":"P. Leysen",
    "wof:placetype":"venue"
},
  "geometry": {"coordinates":[3.2186479568,51.2131576538],"type":"Point"}
}