{
  "type": "Feature",
  "properties": {
    "iso:country":"BE",
    "sg:address":"Rue \u00e0 Dettes 49",
    "sg:city":"Anderlues",
    "sg:classifiers":[
        {
            "category":"Freight",
            "type":"Transportation"
        }
    ],
    "sg:phone":"+32 71 52 59 17",
    "sg:postcode":"6150",
    "sg:province":"Hainaut",
    "sg:tags":[
        "-",
        "transport"
    ],
    "wof:name":"Wilmart",
    "wof:placetype":"venue"
},
  "geometry": {"coordinates":[4.2762818336,50.3875923157],"type":"Point"}
}