{
  "type": "Feature",
  "properties": {
    "iso:country":"BE",
    "sg:address":"Grachtscheldestraat 8b4",
    "sg:city":"Oudenaarde",
    "sg:orig_category":"Advocaten and juridische adviseurs",
    "sg:phone":"+32 55 31 70 13",
    "sg:postcode":"9700",
    "sg:province":"Oost-Vlaanderen",
    "wof:name":"N. Rijckaert",
    "wof:placetype":"venue"
},
  "geometry": {"coordinates":[3.6075100899,50.8429069519],"type":"Point"}
}