{
  "type": "Feature",
  "properties": {
    "addr:full":"Ringlaan 40 Heusden-zolder Limburg 3550",
    "addr:housenumber":"40",
    "addr:postcode":"3550",
    "addr:street":"Ringlaan",
    "iso:country":"BE",
    "sg:address":"Ringlaan 40",
    "sg:city":"Heusden-zolder",
    "sg:orig_category":"Maisons de repos and r\u00e9sidences",
    "sg:phone":"+32 11 53 04 00",
    "sg:postcode":"3550",
    "sg:province":"Limburg",
    "wof:name":"Rusthuis De Bloemelingen",
    "wof:placetype":"venue"
},
  "geometry": {"coordinates":[5.314458847,51.0247421265],"type":"Point"}
}