{
  "type": "Feature",
  "properties": {
    "iso:country":"BE",
    "sg:address":"Stationstraat 63",
    "sg:city":"Sint-truiden",
    "sg:orig_category":"Biljart- and snookerzalen",
    "sg:phone":"+32 11 68 61 32",
    "sg:postcode":"3800",
    "sg:province":"Limburg",
    "wof:name":"Snooker Palace",
    "wof:placetype":"venue"
},
  "geometry": {"coordinates":[5.1768898964,50.8172492981],"type":"Point"}
}