{
  "type": "Feature",
  "properties": {
    "addr:full":"Scheldelaan 420 Antwerpen Antwerpen 2040",
    "addr:housenumber":"420",
    "addr:postcode":"2040",
    "addr:street":"Scheldelaan",
    "iso:country":"BE",
    "sg:address":"Scheldelaan 420",
    "sg:city":"Antwerpen",
    "sg:classifiers":[
        {
            "category":"Manufacturing",
            "subcategory":"Chemicals & Compounds",
            "type":"Manufacturing & Wholesale Goods"
        }
    ],
    "sg:phone":"+32 3 540 30 11",
    "sg:postcode":"2040",
    "sg:province":"Antwerpen",
    "sg:tags":[
        "sulphate",
        "ammonium"
    ],
    "wof:name":"Bayer Antwerpen Nv",
    "wof:placetype":"venue"
},
  "geometry": {"coordinates":[4.2969307899,51.304725647],"type":"Point"}
}