{
  "type": "Feature",
  "properties": {
    "iso:country":"BE",
    "sg:address":"Rue Baron De Castro 65",
    "sg:city":"Bruxelles",
    "sg:classifiers":[
        {
            "category":"Home & Garden",
            "subcategory":"Household Appliances",
            "type":"Retail Goods"
        }
    ],
    "sg:phone":"+32 2 735 44 42",
    "sg:postcode":"1040",
    "sg:province":"Bruxelles-Capitale",
    "sg:tags":[
        "plants",
        "dryer",
        "drying"
    ],
    "wof:name":"Niro Belgium",
    "wof:placetype":"venue"
},
  "geometry": {"coordinates":[4.4069571495,50.8293609619],"type":"Point"}
}