{
  "type": "Feature",
  "properties": {
    "iso:country":"BE",
    "sg:address":"Heiveldekens 9",
    "sg:city":"Kontich",
    "sg:classifiers":[
        {
            "category":"Utilities",
            "subcategory":"Recycling",
            "type":"Services"
        }
    ],
    "sg:phone":"+32 3 455 00 95",
    "sg:postcode":"2550",
    "sg:province":"Antwerpen",
    "wof:name":"W-supplies Belgium Bvba",
    "wof:placetype":"venue"
},
  "geometry": {"coordinates":[4.4596071243,51.1225585938],"type":"Point"}
}