{
  "type": "Feature",
  "properties": {
    "iso:country":"BE",
    "sg:address":"Rue George Rodenbach 21",
    "sg:city":"Frameries",
    "sg:orig_category":"Entretien and r\u00e9parations de voitures",
    "sg:phone":"+32 65 67 44 36",
    "sg:postcode":"7080",
    "sg:province":"Hainaut",
    "wof:name":"Yvon Roland",
    "wof:placetype":"venue"
},
  "geometry": {"coordinates":[3.8967039585,50.412651062],"type":"Point"}
}