{
  "type": "Feature",
  "properties": {
    "addr:full":"Molenstraat 36 Torhout West-Vlaanderen 8820",
    "addr:housenumber":"36",
    "addr:postcode":"8820",
    "addr:street":"Molenstraat",
    "iso:country":"BE",
    "sg:address":"Molenstraat 36",
    "sg:city":"Torhout",
    "sg:classifiers":[
        {
            "category":"Cafe",
            "type":"Food & Drink"
        }
    ],
    "sg:phone":"+32 50 21 38 76",
    "sg:postcode":"8820",
    "sg:province":"West-Vlaanderen",
    "sg:tags":[
        "caf\u00e9s"
    ],
    "wof:name":"Caf\u00c9 Germinal",
    "wof:placetype":"venue"
},
  "geometry": {"coordinates":[3.0899710655,51.0641441345],"type":"Point"}
}