{
  "type": "Feature",
  "properties": {
    "addr:full":"Burgemeester Capellelaan 35 Damme West-Vlaanderen 8340",
    "addr:housenumber":"35",
    "addr:postcode":"8340",
    "addr:street":"Burgemeester Capellelaan",
    "iso:country":"BE",
    "sg:address":"Burgemeester Capellelaan 35",
    "sg:city":"Damme",
    "sg:classifiers":[
        {
            "category":"Taxi",
            "type":"Transportation"
        }
    ],
    "sg:phone":"+32 50 35 90 00",
    "sg:postcode":"8340",
    "sg:province":"West-Vlaanderen",
    "wof:name":"Speedy Airport Service",
    "wof:placetype":"venue"
},
  "geometry": {"coordinates":[3.3113899231,51.2103233337],"type":"Point"}
}