{
  "type": "Feature",
  "properties": {
    "iso:country":"BE",
    "sg:address":"Bredabaan 397",
    "sg:city":"Wuustwezel",
    "sg:classifiers":[
        {
            "category":"Manufacturing",
            "subcategory":"Furniture",
            "type":"Manufacturing & Wholesale Goods"
        }
    ],
    "sg:phone":"+32 3 669 62 35",
    "sg:postcode":"2990",
    "sg:province":"Antwerpen",
    "sg:tags":[
        "design",
        "-"
    ],
    "wof:name":"Hofman Meubelhuis Nv",
    "wof:placetype":"venue"
},
  "geometry": {"coordinates":[4.5946559906,51.3923034668],"type":"Point"}
}