{
  "type": "Feature",
  "properties": {
    "addr:full":"Wolvertemsesteenweg 100 Grimbergen Vlaams-Brabant 1850",
    "addr:housenumber":"100",
    "addr:postcode":"1850",
    "addr:street":"Wolvertemsesteenweg",
    "iso:country":"BE",
    "sg:address":"Wolvertemsesteenweg 100",
    "sg:city":"Grimbergen",
    "sg:classifiers":[
        {
            "category":"Autos & Motor Vehicles",
            "subcategory":"Auto Supplies",
            "type":"Retail Goods"
        }
    ],
    "sg:phone":"+32 2 270 40 50",
    "sg:postcode":"1850",
    "sg:province":"Vlaams-Brabant",
    "sg:tags":[
        "automobile",
        "-",
        "radio"
    ],
    "wof:name":"Ace Telecom Nv",
    "wof:placetype":"venue"
},
  "geometry": {"coordinates":[4.3655338287,50.936000824],"type":"Point"}
}