{
  "type": "Feature",
  "properties": {
    "iso:country":"BE",
    "sg:address":"Rue D'audenarde 44",
    "sg:city":"Ellezelles",
    "sg:classifiers":[
        {
            "category":"Health Services",
            "subcategory":"Health Practitioner",
            "type":"Services"
        }
    ],
    "sg:phone":"+32 68 54 31 70",
    "sg:postcode":"7890",
    "sg:province":"Hainaut",
    "sg:tags":[
        "physiotherapist"
    ],
    "wof:name":"Hayette Herv\u00e9",
    "wof:placetype":"venue"
},
  "geometry": {"coordinates":[3.6816129684,50.7358665466],"type":"Point"}
}