{
  "type": "Feature",
  "properties": {
    "iso:country":"BE",
    "sg:address":"Grote Baan 23",
    "sg:city":"Geetbets",
    "sg:orig_category":"Gespecialiseerde residenti\u00eble bouw",
    "sg:phone":"+32 11 58 75 29",
    "sg:postcode":"3454",
    "sg:province":"Vlaams-Brabant",
    "wof:name":"E. Vandenrijt",
    "wof:placetype":"venue"
},
  "geometry": {"coordinates":[5.1647658348,50.8868751526],"type":"Point"}
}