{
  "type": "Feature",
  "properties": {
    "addr:full":"Quai Du Halage 8 Flemalle Li\u00e8ge 4400",
    "addr:housenumber":"8",
    "addr:postcode":"4400",
    "addr:street":"Quai Du Halage",
    "iso:country":"BE",
    "sg:address":"Quai Du Halage 8",
    "sg:city":"Flemalle",
    "sg:orig_category":"Installatie van houten of kunststof schrijnwerk",
    "sg:phone":"+32 4 233 25 41",
    "sg:postcode":"4400",
    "sg:province":"Li\u00e8ge",
    "wof:name":"Atelier Schepers",
    "wof:placetype":"venue"
},
  "geometry": {"coordinates":[5.4816260338,50.6004447937],"type":"Point"}
}