{
  "type": "Feature",
  "properties": {
    "iso:country":"BE",
    "sg:address":"Nieuwe Westweg 14",
    "sg:city":"Antwerpen",
    "sg:classifiers":[
        {
            "category":"Professional",
            "subcategory":"Engineering",
            "type":"Services"
        }
    ],
    "sg:phone":"+32 3 560 12 11",
    "sg:postcode":"2040",
    "sg:province":"Antwerpen",
    "sg:tags":[
        "plants",
        "harbours",
        "infrastructure",
        "power",
        "environmental"
    ],
    "wof:name":"Abt Nv",
    "wof:placetype":"venue"
},
  "geometry": {"coordinates":[4.3392128944,51.3333396912],"type":"Point"}
}