{
  "type": "Feature",
  "properties": {
    "addr:full":"Rue Stanislas Legrelle 50 Bruxelles (jette) Bruxelles-Capitale 1090",
    "addr:housenumber":"50",
    "addr:postcode":"1090",
    "addr:street":"Rue Stanislas Legrelle",
    "iso:country":"BE",
    "sg:address":"Rue Stanislas Legrelle 50",
    "sg:city":"Bruxelles (jette)",
    "sg:classifiers":[
        {
            "category":"Building & Trades",
            "subcategory":"Electrical",
            "type":"Services"
        }
    ],
    "sg:phone":"+32 2 427 37 34",
    "sg:postcode":"1090",
    "sg:province":"Bruxelles-Capitale",
    "sg:tags":[
        "electric",
        "-",
        "housewiring",
        "contractor"
    ],
    "wof:name":"Suys A",
    "wof:placetype":"venue"
},
  "geometry": {"coordinates":[4.3221678734,50.8760490417],"type":"Point"}
}