{
  "type": "Feature",
  "properties": {
    "addr:full":"Kremerstraat 12b Zonhoven Limburg 3520",
    "addr:housenumber":"12b",
    "addr:postcode":"3520",
    "addr:street":"Kremerstraat",
    "iso:country":"BE",
    "sg:address":"Kremerstraat 12b",
    "sg:city":"Zonhoven",
    "sg:orig_category":"Plomberie, chauffage and installations sanitaires",
    "sg:phone":"+32 11 81 40 95",
    "sg:postcode":"3520",
    "sg:province":"Limburg",
    "wof:name":"Timmy Kumbruck",
    "wof:placetype":"venue"
},
  "geometry": {"coordinates":[5.3785028458,50.9970436096],"type":"Point"}
}