{
  "type": "Feature",
  "properties": {
    "addr:full":"Gentstr 2 Gent Oost-Vlaanderen 9041",
    "addr:housenumber":"2",
    "addr:postcode":"9041",
    "addr:street":"Gentstr;Oost-Vlaanderen",
    "iso:country":"BE",
    "sg:address":"Gentstr 2",
    "sg:city":"Gent",
    "sg:classifiers":[
        {
            "category":"Travel",
            "subcategory":"Hotels & Motels",
            "type":"Entertainment"
        }
    ],
    "sg:phone":"+32 9 251 03 14",
    "sg:postcode":"9041",
    "sg:province":"Oost-Vlaanderen",
    "sg:tags":[
        "hotels",
        "business",
        "restaurant"
    ],
    "wof:name":"Van Den Abeele Nv",
    "wof:placetype":"venue"
},
  "geometry": {"coordinates":[3.7576758862,51.0800628662],"type":"Point"}
}