{
  "type": "Feature",
  "properties": {
    "addr:full":"Opperstraat 50 Moerbeke (moerbeke-waas) Oost-Vlaanderen 9180",
    "addr:housenumber":"50",
    "addr:postcode":"9180",
    "addr:street":"Opperstraat",
    "iso:country":"BE",
    "sg:address":"Opperstraat 50",
    "sg:city":"Moerbeke (moerbeke-waas)",
    "sg:classifiers":[
        {
            "category":"Food & Beverages",
            "subcategory":"Cheese",
            "type":"Retail Goods"
        }
    ],
    "sg:phone":"+32 9 346 64 49",
    "sg:postcode":"9180",
    "sg:province":"Oost-Vlaanderen",
    "sg:tags":[
        "-"
    ],
    "wof:name":"'t Kaasplankje",
    "wof:placetype":"venue"
},
  "geometry": {"coordinates":[3.938092947,51.1742095947],"type":"Point"}
}