{
  "type": "Feature",
  "properties": {
    "iso:country":"BE",
    "sg:address":"Bergensesteenweg 468",
    "sg:city":"Sint-pieters-leeuw",
    "sg:classifiers":[
        {
            "category":"Autos & Motor Vehicles",
            "subcategory":"Automobile Sales",
            "type":"Retail Goods"
        }
    ],
    "sg:phone":"+32 2 331 11 05",
    "sg:postcode":"1600",
    "sg:province":"Vlaams-Brabant",
    "sg:tags":[
        "car",
        "used",
        "-"
    ],
    "wof:name":"Eeckhoudt S",
    "wof:placetype":"venue"
},
  "geometry": {"coordinates":[4.2720999718,50.7794418335],"type":"Point"}
}