{
  "type": "Feature",
  "properties": {
    "iso:country":"BE",
    "sg:address":"Grand Rue 107",
    "sg:city":"Mouscron",
    "sg:classifiers":[
        {
            "category":"Autos & Motor Vehicles",
            "subcategory":"Fuel & Gas Station",
            "type":"Retail Goods"
        }
    ],
    "sg:phone":"+32 56 34 45 88",
    "sg:postcode":"7700",
    "sg:province":"Hainaut",
    "wof:name":"Triangle 2000",
    "wof:placetype":"venue"
},
  "geometry": {"coordinates":[3.1939909458,50.7261772156],"type":"Point"}
}