{
  "type": "Feature",
  "properties": {
    "addr:full":"Rue Combat. L. Mahieu 60 Hensies Hainaut 7350",
    "addr:housenumber":"60",
    "addr:postcode":"7350",
    "addr:street":"Rue Combat. L. Mahieu",
    "iso:country":"BE",
    "sg:address":"Rue Combat. L. Mahieu 60",
    "sg:city":"Hensies",
    "sg:orig_category":"Herstellingen and onderhoud van auto's Voertuigen",
    "sg:phone":"+32 65 65 28 08",
    "sg:postcode":"7350",
    "sg:province":"Hainaut",
    "wof:name":"Garage Roosa",
    "wof:placetype":"venue"
},
  "geometry": {"coordinates":[3.684994936,50.4326210022],"type":"Point"}
}