{
  "type": "Feature",
  "properties": {
    "addr:full":"Chauss\u00e9e De Bruxelles 311c Waterloo Brabant Wallon 1410",
    "addr:housenumber":"311c",
    "addr:postcode":"1410",
    "addr:street":"Chausse\u0301E De Bruxelles",
    "iso:country":"BE",
    "sg:address":"Chauss\u00e9e De Bruxelles 311c",
    "sg:city":"Waterloo",
    "sg:classifiers":[
        {
            "category":"Home & Garden",
            "subcategory":"Household Appliances",
            "type":"Retail Goods"
        }
    ],
    "sg:phone":"+32 2 354 83 78",
    "sg:postcode":"1410",
    "sg:province":"Brabant Wallon",
    "sg:tags":[
        "repair",
        "stove",
        "-"
    ],
    "wof:name":"Chantier De Waterloo Sprl",
    "wof:placetype":"venue"
},
  "geometry": {"coordinates":[4.401758194,50.70753479],"type":"Point"}
}