{
  "type": "Feature",
  "properties": {
    "iso:country":"BE",
    "sg:address":"Rue Royale 110",
    "sg:city":"Cerfontaine (silenrieux)",
    "sg:classifiers":[
        {
            "category":"Retail",
            "subcategory":"Animal Services",
            "type":"Services"
        }
    ],
    "sg:phone":"+32 71 63 43 13",
    "sg:postcode":"5630",
    "sg:province":"Namur",
    "sg:tags":[
        "breeding",
        "selling",
        "-",
        "dog"
    ],
    "wof:name":"Centre Canin De L'eau D'heure",
    "wof:placetype":"venue"
},
  "geometry": {"coordinates":[4.4487199783,50.2156639099],"type":"Point"}
}