{
  "type": "Feature",
  "properties": {
    "addr:full":"Fortenstraat 9 Waasmunster Oost-Vlaanderen 9250",
    "addr:housenumber":"9",
    "addr:postcode":"9250",
    "addr:street":"Fortenstraat",
    "iso:country":"BE",
    "sg:address":"Fortenstraat 9",
    "sg:city":"Waasmunster",
    "sg:orig_category":"Woningbouw",
    "sg:phone":"+32 52 46 10 56",
    "sg:postcode":"9250",
    "sg:province":"Oost-Vlaanderen",
    "wof:name":"Georges De Laet",
    "wof:placetype":"venue"
},
  "geometry": {"coordinates":[4.1145448685,51.1238746643],"type":"Point"}
}