{
  "type": "Feature",
  "properties": {
    "addr:full":"Roze 44/1 Eeklo Oost-Vlaanderen 9900",
    "addr:housenumber":"44 / 1",
    "addr:postcode":"9900",
    "addr:street":"Roze",
    "iso:country":"BE",
    "sg:address":"Roze 44/1",
    "sg:city":"Eeklo",
    "sg:orig_category":"Belastingconsulenten Diverse juridische dienstverlening",
    "sg:phone":"+32 9 378 32 12",
    "sg:postcode":"9900",
    "sg:province":"Oost-Vlaanderen",
    "wof:name":"Michiels L. & Co",
    "wof:placetype":"venue"
},
  "geometry": {"coordinates":[3.5727930069,51.1880645752],"type":"Point"}
}