{
  "type": "Feature",
  "properties": {
    "addr:full":"Gasthuisstraat 30 Kuurne West-Vlaanderen 8520",
    "addr:housenumber":"30",
    "addr:postcode":"8520",
    "addr:street":"Gasthuisstraat",
    "iso:country":"BE",
    "sg:address":"Gasthuisstraat 30",
    "sg:city":"Kuurne",
    "sg:orig_category":"Enseignement maternel and primaire",
    "sg:phone":"+32 56 71 10 32",
    "sg:postcode":"8520",
    "sg:province":"West-Vlaanderen",
    "wof:name":"Gemeentelijke Basisschool",
    "wof:placetype":"venue"
},
  "geometry": {"coordinates":[3.284539938,50.8498001099],"type":"Point"}
}