{
  "type": "Feature",
  "properties": {
    "addr:full":"Henry Fordlaan 50 Genk Limburg 3600",
    "addr:housenumber":"50",
    "addr:postcode":"3600",
    "addr:street":"Henry Fordlaan",
    "iso:country":"BE",
    "sg:address":"Henry Fordlaan 50",
    "sg:city":"Genk",
    "sg:classifiers":[
        {
            "category":"Autos & Motor Vehicles",
            "subcategory":"Fuel & Gas Station",
            "type":"Retail Goods"
        }
    ],
    "sg:phone":"+32 89 30 43 20",
    "sg:postcode":"3600",
    "sg:province":"Limburg",
    "sg:tags":[
        "stations-service",
        "carburants"
    ],
    "wof:name":"Q8",
    "wof:placetype":"venue"
},
  "geometry": {"coordinates":[5.4798221588,50.926574707],"type":"Point"}
}