{
  "type": "Feature",
  "properties": {
    "iso:country":"BE",
    "sg:address":"Veldonkstraat 299",
    "sg:city":"Tremelo",
    "sg:classifiers":[
        {
            "category":"Building & Trades",
            "subcategory":"Cleaning & Sanitation",
            "type":"Services"
        }
    ],
    "sg:phone":"+32 16 53 72 52",
    "sg:postcode":"3120",
    "sg:province":"Vlaams-Brabant",
    "sg:tags":[
        "cleaner",
        "window"
    ],
    "wof:name":"Entreprise Europa Vitres",
    "wof:placetype":"venue"
},
  "geometry": {"coordinates":[4.731760025,50.9881896973],"type":"Point"}
}