{
  "type": "Feature",
  "properties": {
    "addr:full":"Chauss\u00e9e De Mons 39 Bruxelles (anderlecht) Bruxelles-Capitale 1070",
    "addr:housenumber":"39",
    "addr:postcode":"1070",
    "addr:street":"Chausse\u0301E De Mons",
    "iso:country":"BE",
    "sg:address":"Chauss\u00e9e De Mons 39",
    "sg:city":"Bruxelles (anderlecht)",
    "sg:classifiers":[
        {
            "category":"Travel",
            "subcategory":"Hotels & Motels",
            "type":"Entertainment"
        }
    ],
    "sg:phone":"+32 2 521 35 16",
    "sg:postcode":"1070",
    "sg:province":"Bruxelles-Capitale",
    "wof:name":"Van Belle (hotel)",
    "wof:placetype":"venue"
},
  "geometry": {"coordinates":[4.3365058899,50.8442993164],"type":"Point"}
}