{
  "type": "Feature",
  "properties": {
    "iso:country":"BE",
    "sg:address":"Kerkstraat 43",
    "sg:city":"Vilvoorde (peutie)",
    "sg:classifiers":[
        {
            "category":"Bars & Pubs",
            "type":"Food & Drink"
        }
    ],
    "sg:phone":"+32 2 252 13 64",
    "sg:postcode":"1800",
    "sg:province":"Vlaams-Brabant",
    "wof:name":"Sax (the)",
    "wof:placetype":"venue"
},
  "geometry": {"coordinates":[4.4543848038,50.9273529053],"type":"Point"}
}