{
  "type": "Feature",
  "properties": {
    "iso:country":"BE",
    "sg:address":"Rue Oltr\u00e9mont 87",
    "sg:city":"Saint-nicolas (montegn\u00e9e)",
    "sg:classifiers":[
        {
            "category":"Health Services",
            "subcategory":"Health Practitioner",
            "type":"Services"
        }
    ],
    "sg:phone":"+32 4 247 40 86",
    "sg:postcode":"4420",
    "sg:province":"Li\u00e8ge",
    "sg:tags":[
        "therapist",
        "speech"
    ],
    "wof:name":"Dethier M A",
    "wof:placetype":"venue"
},
  "geometry": {"coordinates":[5.5165271759,50.6377983093],"type":"Point"}
}