{
  "type": "Feature",
  "properties": {
    "addr:full":"Kortestraat 14 Leuven Vlaams-Brabant 3000",
    "addr:housenumber":"14",
    "addr:postcode":"3000",
    "addr:street":"Kortestraat",
    "iso:country":"BE",
    "sg:address":"Kortestraat 14",
    "sg:city":"Leuven",
    "sg:classifiers":[
        {
            "category":"Fast Food",
            "type":"Food & Drink"
        }
    ],
    "sg:phone":"+32 16 22 06 46",
    "sg:postcode":"3000",
    "sg:province":"Vlaams-Brabant",
    "sg:tags":[
        "meeneem",
        "restaurant"
    ],
    "wof:name":"Ali Baba",
    "wof:placetype":"venue"
},
  "geometry": {"coordinates":[4.6999797821,50.8788108826],"type":"Point"}
}