{
  "type": "Feature",
  "properties": {
    "iso:country":"BE",
    "sg:address":"Rue Des Fran\u00c7ais 29",
    "sg:city":"Chatelet",
    "sg:classifiers":[
        {
            "category":"Arena",
            "subcategory":"Sports Club",
            "type":"Entertainment"
        }
    ],
    "sg:phone":"+32 71 23 16 26",
    "sg:postcode":"6200",
    "sg:province":"Hainaut",
    "sg:tags":[
        "de"
    ],
    "wof:name":"Kamikaze Team",
    "wof:placetype":"venue"
},
  "geometry": {"coordinates":[4.5314087868,50.401638031],"type":"Point"}
}