{
  "type": "Feature",
  "properties": {
    "addr:full":"Route Du Tonnelet Spa Li\u00e8ge 4900",
    "addr:postcode":"4900",
    "addr:street":"Route Du Tonnelet",
    "iso:country":"BE",
    "sg:address":"Route Du Tonnelet",
    "sg:city":"Spa",
    "sg:classifiers":[
        {
            "category":"Shopping Center",
            "type":"Public Place"
        }
    ],
    "sg:phone":"+32 87 77 39 76",
    "sg:postcode":"4900",
    "sg:province":"Li\u00e8ge",
    "sg:tags":[
        "enseignement",
        "formation"
    ],
    "wof:name":"Dialogue",
    "wof:placetype":"venue"
},
  "geometry": {"coordinates":[5.8842740059,50.4916534424],"type":"Point"}
}