{
  "type": "Feature",
  "properties": {
    "addr:full":"Baarle-frankrijkstraat 10 Sint-martens-latem Oost-Vlaanderen 9830",
    "addr:housenumber":"10",
    "addr:postcode":"9830",
    "addr:street":"Baarle-Frankrijkstraat",
    "iso:country":"BE",
    "sg:address":"Baarle-frankrijkstraat 10",
    "sg:city":"Sint-martens-latem",
    "sg:classifiers":[
        {
            "category":"Travel",
            "subcategory":"Hotels & Motels",
            "type":"Entertainment"
        }
    ],
    "sg:phone":"+32 9 282 33 20",
    "sg:postcode":"9830",
    "sg:province":"Oost-Vlaanderen",
    "wof:name":"Hotel Torenhof",
    "wof:placetype":"venue"
},
  "geometry": {"coordinates":[3.6230530739,51.0261955261],"type":"Point"}
}