{
  "type": "Feature",
  "properties": {
    "addr:full":"T'serclaesstraat 16 Ternat Vlaams-Brabant 1740",
    "addr:housenumber":"16",
    "addr:postcode":"1740",
    "addr:street":"T'Serclaesstraat",
    "iso:country":"BE",
    "sg:address":"T'serclaesstraat 16",
    "sg:city":"Ternat",
    "sg:orig_category":"M\u00e9decins and sp\u00e9cialistes",
    "sg:phone":"+32 2 582 19 78",
    "sg:postcode":"1740",
    "sg:province":"Vlaams-Brabant",
    "wof:name":"Marc Gadeyne",
    "wof:placetype":"venue"
},
  "geometry": {"coordinates":[4.170527935,50.8681411743],"type":"Point"}
}