{
  "type": "Feature",
  "properties": {
    "iso:country":"BE",
    "sg:address":"Kanunnik Davidstraat 17",
    "sg:city":"Oostkamp",
    "sg:classifiers":[
        {
            "category":"Professional",
            "subcategory":"Computer Services",
            "type":"Services"
        }
    ],
    "sg:phone":"+32 50 82 79 79",
    "sg:postcode":"8020",
    "sg:province":"West-Vlaanderen",
    "sg:tags":[
        "-",
        "processing",
        "data"
    ],
    "wof:name":"Petss Cv",
    "wof:placetype":"venue"
},
  "geometry": {"coordinates":[3.2351760864,51.1356391907],"type":"Point"}
}