{
  "type": "Feature",
  "properties": {
    "addr:full":"Olieslagerijstraat 6 Boechout Antwerpen 2530",
    "addr:housenumber":"6",
    "addr:postcode":"2530",
    "addr:street":"Olieslagerijstraat",
    "iso:country":"BE",
    "sg:address":"Olieslagerijstraat 6",
    "sg:city":"Boechout",
    "sg:orig_category":"Groententeelt",
    "sg:phone":"+32 3 455 54 43",
    "sg:postcode":"2530",
    "sg:province":"Antwerpen",
    "wof:name":"Jules De Ridder",
    "wof:placetype":"venue"
},
  "geometry": {"coordinates":[4.5013108253,51.1783370972],"type":"Point"}
}