{
  "type": "Feature",
  "properties": {
    "iso:country":"BE",
    "sg:address":"Rue Des Moissons 15",
    "sg:city":"Bouillon (rochehaut)",
    "sg:classifiers":[
        {
            "category":"Food & Beverages",
            "subcategory":"Groceries & Convenience Stores",
            "type":"Retail Goods"
        }
    ],
    "sg:phone":"+32 61 46 41 20",
    "sg:postcode":"6830",
    "sg:province":"Luxembourg",
    "sg:tags":[
        "grocer"
    ],
    "wof:name":"Spar-lambot Carine Sprl",
    "wof:placetype":"venue"
},
  "geometry": {"coordinates":[5.0699849129,49.7954597473],"type":"Point"}
}