{
  "type": "Feature",
  "properties": {
    "addr:full":"Diesterstraat 17 Sint-truiden Limburg 3800",
    "addr:housenumber":"17",
    "addr:postcode":"3800",
    "addr:street":"Diesterstraat",
    "iso:country":"BE",
    "sg:address":"Diesterstraat 17",
    "sg:city":"Sint-truiden",
    "sg:orig_category":"Textiel",
    "sg:phone":"+32 11 68 27 27",
    "sg:postcode":"3800",
    "sg:province":"Limburg",
    "wof:name":"Huis Hobbieke",
    "wof:placetype":"venue"
},
  "geometry": {"coordinates":[5.1857948303,50.8173027039],"type":"Point"}
}