{
  "type": "Feature",
  "properties": {
    "iso:country":"BE",
    "sg:address":"Brusselsestraat 54",
    "sg:city":"Dendermonde (groot)",
    "sg:orig_category":"V\u00eatements. Textiles",
    "sg:phone":"+32 52 22 22 93",
    "sg:postcode":"9200",
    "sg:province":"Oost-Vlaanderen",
    "wof:name":"Veritas",
    "wof:placetype":"venue"
},
  "geometry": {"coordinates":[4.0999860764,51.0271987915],"type":"Point"}
}