{
  "type": "Feature",
  "properties": {
    "addr:full":"Rue De La Justice 8 Li\u00e8ge 1 (li\u00e8ge 2) Li\u00e8ge 4020",
    "addr:housenumber":"8;1;2",
    "addr:postcode":"4020",
    "addr:street":"Rue De La Justice",
    "iso:country":"BE",
    "sg:address":"Rue De La Justice 8",
    "sg:city":"Li\u00e8ge 1 (li\u00e8ge 2)",
    "sg:classifiers":[
        {
            "category":"Health Services",
            "subcategory":"Doctor",
            "type":"Services"
        }
    ],
    "sg:phone":"+32 4 341 23 36",
    "sg:postcode":"4020",
    "sg:province":"Li\u00e8ge",
    "sg:tags":[
        "medicinephysicians",
        "surgeon"
    ],
    "wof:name":"Lange C",
    "wof:placetype":"venue"
},
  "geometry": {"coordinates":[5.5888600349,50.6416778564],"type":"Point"}
}