{
  "type": "Feature",
  "properties": {
    "addr:full":"Rue Edmond Tollenaere 56-76 Bruxelles Bruxelles-Capitale 1020",
    "addr:housenumber":"56-76",
    "addr:postcode":"1020",
    "addr:street":"Rue Edmond Tollenaere",
    "iso:country":"BE",
    "sg:address":"Rue Edmond Tollenaere 56-76",
    "sg:city":"Bruxelles",
    "sg:classifiers":[
        {
            "category":"Professional",
            "subcategory":"Management & Consulting",
            "type":"Services"
        }
    ],
    "sg:phone":"+32 2 474 67 37",
    "sg:postcode":"1020",
    "sg:province":"Bruxelles-Capitale",
    "sg:tags":[
        "consultant",
        "promotion",
        "-",
        "sale"
    ],
    "wof:name":"Demonstrate Nv",
    "wof:placetype":"venue"
},
  "geometry": {"coordinates":[4.3403339386,50.8752593994],"type":"Point"}
}