{
  "type": "Feature",
  "properties": {
    "addr:full":"Rupelmondestraat 25a Temse Oost-Vlaanderen 9140",
    "addr:housenumber":"25a",
    "addr:postcode":"9140",
    "addr:street":"Rupelmondestraat",
    "iso:country":"BE",
    "sg:address":"Rupelmondestraat 25a",
    "sg:city":"Temse",
    "sg:classifiers":[
        {
            "category":"Manufacturing",
            "subcategory":"Metals",
            "type":"Manufacturing & Wholesale Goods"
        }
    ],
    "sg:phone":"+32 3 771 08 57",
    "sg:postcode":"9140",
    "sg:province":"Oost-Vlaanderen",
    "sg:tags":[
        "ironwork"
    ],
    "wof:name":"Van Leugenhaege",
    "wof:placetype":"venue"
},
  "geometry": {"coordinates":[4.2204928398,51.1479721069],"type":"Point"}
}