{
  "type": "Feature",
  "properties": {
    "iso:country":"BE",
    "sg:address":"Brusselsesteenweg 660",
    "sg:city":"Zellik",
    "sg:classifiers":[
        {
            "category":"Restaurant",
            "type":"Food & Drink"
        }
    ],
    "sg:phone":"+32 2 468 39 81",
    "sg:postcode":"1731",
    "sg:province":"Vlaams-Brabant",
    "wof:name":"Kenza",
    "wof:placetype":"venue"
},
  "geometry": {"coordinates":[4.2762870789,50.8828582764],"type":"Point"}
}