{
  "type": "Feature",
  "properties": {
    "iso:country":"BE",
    "sg:address":"Weggevoerdenstraat 95",
    "sg:city":"Leuven",
    "sg:classifiers":[
        {
            "category":"Food & Beverages",
            "subcategory":"Fruits & Vegetables",
            "type":"Retail Goods"
        }
    ],
    "sg:phone":"+32 16 44 89 70",
    "sg:postcode":"3012",
    "sg:province":"Vlaams-Brabant",
    "sg:tags":[
        "l\u00e9gumes",
        "gr"
    ],
    "wof:name":"Schoolmeesters",
    "wof:placetype":"venue"
},
  "geometry": {"coordinates":[4.7139558792,50.9249000549],"type":"Point"}
}