{
  "type": "Feature",
  "properties": {
    "addr:full":"Braesberg 7 Plombi\u00e8res (hombourg) Li\u00e8ge 4852",
    "addr:housenumber":"7",
    "addr:postcode":"4852",
    "addr:street":"Braesberg",
    "iso:country":"BE",
    "sg:address":"Braesberg 7",
    "sg:city":"Plombi\u00e8res (hombourg)",
    "sg:classifiers":[
        {
            "category":"Home & Garden",
            "subcategory":"Carpets & Floor Coverings",
            "type":"Retail Goods"
        }
    ],
    "sg:phone":"+32 87 78 73 32",
    "sg:postcode":"4852",
    "sg:province":"Li\u00e8ge",
    "sg:tags":[
        "armoring"
    ],
    "wof:name":"Brugnetti G",
    "wof:placetype":"venue"
},
  "geometry": {"coordinates":[5.9583349228,50.7378540039],"type":"Point"}
}