{
  "type": "Feature",
  "properties": {
    "iso:country":"BE",
    "sg:address":"Zwanenlaan 4",
    "sg:city":"Oostende",
    "sg:orig_category":"Afbraak- and draineerwerken Verhuur bouwmachines",
    "sg:phone":"+32 59 26 55 39",
    "sg:postcode":"8400",
    "sg:province":"West-Vlaanderen",
    "wof:name":"Grondwerken De Rese",
    "wof:placetype":"venue"
},
  "geometry": {"coordinates":[2.9685161114,51.2020988464],"type":"Point"}
}