{
  "type": "Feature",
  "properties": {
    "iso:country":"BE",
    "sg:address":"Bredepleinstraat 88",
    "sg:city":"Boortmeerbeek",
    "sg:orig_category":"Services fun\u00e9raires",
    "sg:phone":"+32 15 51 46 55",
    "sg:postcode":"3190",
    "sg:province":"Vlaams-Brabant",
    "wof:name":"Begrafenissen Gooris & Zn",
    "wof:placetype":"venue"
},
  "geometry": {"coordinates":[4.5773000717,50.9733390808],"type":"Point"}
}