{
  "type": "Feature",
  "properties": {
    "addr:full":"Churchillsteenweg 8 Aalst (erembodegem) Oost-Vlaanderen 9320",
    "addr:housenumber":"8",
    "addr:postcode":"9320",
    "addr:street":"Churchillsteenweg",
    "iso:country":"BE",
    "sg:address":"Churchillsteenweg 8",
    "sg:city":"Aalst (erembodegem)",
    "sg:classifiers":[
        {
            "category":"Autos & Motor Vehicles",
            "subcategory":"Automobile Sales",
            "type":"Retail Goods"
        }
    ],
    "sg:phone":"+32 53 84 14 00",
    "sg:postcode":"9320",
    "sg:province":"Oost-Vlaanderen",
    "sg:tags":[
        "car",
        "used",
        "-"
    ],
    "wof:name":"Mizani Parbiz Bvba",
    "wof:placetype":"venue"
},
  "geometry": {"coordinates":[4.0553851128,50.9209976196],"type":"Point"}
}