{
  "type": "Feature",
  "properties": {
    "iso:country":"BE",
    "sg:address":"Arme Klarenstraat 2",
    "sg:city":"Roeselare",
    "sg:orig_category":"Non-Classified Establishments",
    "sg:phone":"+32 51 25 08 45",
    "sg:postcode":"8800",
    "sg:province":"West-Vlaanderen",
    "wof:name":"Vandeputte-vanbesien Bvba",
    "wof:placetype":"venue"
},
  "geometry": {"coordinates":[3.1228899956,50.944229126],"type":"Point"}
}