{
  "type": "Feature",
  "properties": {
    "addr:full":"Margarethalaan 74 Genk Limburg 3600",
    "addr:housenumber":"74",
    "addr:postcode":"3600",
    "addr:street":"Margarethalaan",
    "iso:country":"BE",
    "sg:address":"Margarethalaan 74",
    "sg:city":"Genk",
    "sg:orig_category":"M\u00e9decins and sp\u00e9cialistes",
    "sg:phone":"+32 89 35 38 37",
    "sg:postcode":"3600",
    "sg:province":"Limburg",
    "wof:name":"Johny Van Aerde",
    "wof:placetype":"venue"
},
  "geometry": {"coordinates":[5.4802122116,50.9712715149],"type":"Point"}
}