{
  "type": "Feature",
  "properties": {
    "iso:country":"BE",
    "sg:address":"Spoorwegstraat 67",
    "sg:city":"Harelbeke",
    "sg:orig_category":"Bouwmaterialen Gh Installatie van houten of kunststof schrijnwerk Woningbouw",
    "sg:phone":"+32 56 20 13 44",
    "sg:postcode":"8530",
    "sg:province":"West-Vlaanderen",
    "wof:name":"Vlieghe Rik",
    "wof:placetype":"venue"
},
  "geometry": {"coordinates":[3.2939870358,50.8354415894],"type":"Point"}
}