{
  "type": "Feature",
  "properties": {
    "iso:country":"BE",
    "sg:address":"Beverhoutstraat 43",
    "sg:city":"Oostkamp",
    "sg:orig_category":"Eleveurs de bovins",
    "sg:phone":"+32 50 35 14 01",
    "sg:postcode":"8020",
    "sg:province":"West-Vlaanderen",
    "wof:name":"Marleen Timmerman",
    "wof:placetype":"venue"
},
  "geometry": {"coordinates":[3.2712140083,51.1806602478],"type":"Point"}
}