{
  "type": "Feature",
  "properties": {
    "iso:country":"BE",
    "sg:address":"Rue De La Cit\u00e9 2",
    "sg:city":"Bruxelles (ixelles)",
    "sg:classifiers":[
        {
            "category":"Home & Garden",
            "subcategory":"Carpets & Floor Coverings",
            "type":"Retail Goods"
        }
    ],
    "sg:phone":"+32 2 647 83 58",
    "sg:postcode":"1050",
    "sg:province":"Bruxelles-Capitale",
    "sg:tags":[
        "parquet"
    ],
    "wof:name":"Int\u00e9rieur Bois",
    "wof:placetype":"venue"
},
  "geometry": {"coordinates":[4.3698740005,50.8322982788],"type":"Point"}
}