{
  "type": "Feature",
  "properties": {
    "addr:full":"Clos Pr\u00e9 Cola 14 Mouscron Hainaut 7700",
    "addr:housenumber":"14",
    "addr:postcode":"7700",
    "addr:street":"Clos Pre\u0301 Cola",
    "iso:country":"BE",
    "sg:address":"Clos Pr\u00e9 Cola 14",
    "sg:city":"Mouscron",
    "sg:classifiers":[
        {
            "category":"Professional",
            "subcategory":"Engineering",
            "type":"Services"
        }
    ],
    "sg:phone":"+32 56 34 33 31",
    "sg:postcode":"7700",
    "sg:province":"Hainaut",
    "sg:tags":[
        "-"
    ],
    "wof:name":"Lum",
    "wof:placetype":"venue"
},
  "geometry": {"coordinates":[3.2347049713,50.7503623962],"type":"Point"}
}