{
  "type": "Feature",
  "properties": {
    "iso:country":"BE",
    "sg:address":"Merelbekestraat 55",
    "sg:city":"Melle",
    "sg:classifiers":[
        {
            "category":"Food & Beverages",
            "subcategory":"Groceries & Convenience Stores",
            "type":"Retail Goods"
        }
    ],
    "sg:phone":"+32 9 230 88 72",
    "sg:postcode":"9090",
    "sg:province":"Oost-Vlaanderen",
    "sg:tags":[
        "grocer"
    ],
    "wof:name":"De Deyn",
    "wof:placetype":"venue"
},
  "geometry": {"coordinates":[3.7704150677,51.0224342346],"type":"Point"}
}