{
  "type": "Feature",
  "properties": {
    "addr:full":"Rue Peltzer De Clermont 6 Verviers Li\u00e8ge 4800",
    "addr:housenumber":"6",
    "addr:postcode":"4800",
    "addr:street":"Rue Peltzer De Clermont",
    "iso:country":"BE",
    "sg:address":"Rue Peltzer De Clermont 6",
    "sg:city":"Verviers",
    "sg:classifiers":[
        {
            "category":"Manufacturing",
            "subcategory":"Textiles",
            "type":"Manufacturing & Wholesale Goods"
        }
    ],
    "sg:phone":"+32 87 31 17 24",
    "sg:postcode":"4800",
    "sg:province":"Li\u00e8ge",
    "wof:name":"Maison Laura S\u00c9lection",
    "wof:placetype":"venue"
},
  "geometry": {"coordinates":[5.8542709351,50.5918159485],"type":"Point"}
}