{
  "type": "Feature",
  "properties": {
    "addr:full":"Beneluxln 12 Poperinge West-Vlaanderen 8970",
    "addr:housenumber":"12",
    "addr:postcode":"8970",
    "addr:street":"Beneluxln",
    "iso:country":"BE",
    "sg:address":"Beneluxln 12",
    "sg:city":"Poperinge",
    "sg:classifiers":[
        {
            "category":"Professional",
            "type":"Services"
        }
    ],
    "sg:phone":"+32 57 33 49 71",
    "sg:postcode":"8970",
    "sg:province":"West-Vlaanderen",
    "sg:tags":[
        "transport",
        "road"
    ],
    "wof:name":"Fury Nv",
    "wof:placetype":"venue"
},
  "geometry": {"coordinates":[2.7471530437,50.8497581482],"type":"Point"}
}