{
  "type": "Feature",
  "properties": {
    "addr:full":"Rue Charles Lemaire 1 Oudergem/auderghem Bruxelles-Capitale 1170",
    "addr:housenumber":"1",
    "addr:postcode":"1170",
    "addr:street":"Rue Charles Lemaire;/",
    "iso:country":"BE",
    "sg:address":"Rue Charles Lemaire 1",
    "sg:city":"Oudergem/auderghem",
    "sg:orig_category":"Catering and organisation de f\u00eates. Restauration pour collectivit\u00e9s",
    "sg:phone":"+32 2 679 12 11",
    "sg:postcode":"1170",
    "sg:province":"Bruxelles-Capitale",
    "wof:name":"Sodexho Belgi\u00cb/sodexho Belgique",
    "wof:placetype":"venue"
},
  "geometry": {"coordinates":[4.4041399956,50.8091392517],"type":"Point"}
}