{
  "type": "Feature",
  "properties": {
    "addr:full":"Rue De La Coquinie 168-118 Mouscron Hainaut 7700",
    "addr:postcode":"168-118;7700",
    "addr:street":"Rue De La Coquinie;Hainaut",
    "iso:country":"BE",
    "sg:address":"Rue De La Coquinie 168-118",
    "sg:city":"Mouscron",
    "sg:classifiers":[
        {
            "category":"Education",
            "subcategory":"School",
            "type":"Public Place"
        }
    ],
    "sg:phone":"+32 56 34 66 40",
    "sg:postcode":"7700",
    "sg:province":"Hainaut",
    "sg:tags":[
        "primary"
    ],
    "wof:name":"Ecole Champ D'oiseaux",
    "wof:placetype":"venue"
},
  "geometry": {"coordinates":[3.2188711166,50.7532119751],"type":"Point"}
}