{
  "type": "Feature",
  "properties": {
    "iso:country":"BE",
    "sg:address":"Vondelstraat 15",
    "sg:city":"Lennik (sint-kwintens-lennik)",
    "sg:classifiers":[
        {
            "category":"Sports & Exercise",
            "subcategory":"Gym",
            "type":"Entertainment"
        }
    ],
    "sg:phone":"+32 2 532 24 33",
    "sg:postcode":"1750",
    "sg:province":"Vlaams-Brabant",
    "sg:tags":[
        "fitness"
    ],
    "wof:name":"Callanetics Studio Lennik",
    "wof:placetype":"venue"
},
  "geometry": {"coordinates":[4.1577391624,50.8074836731],"type":"Point"}
}