{
  "type": "Feature",
  "properties": {
    "addr:full":"Koning Albert I Laan 62 Wemmel Vlaams-Brabant 1780",
    "addr:housenumber":"62",
    "addr:postcode":"1780",
    "addr:street":"Koning Albert I Laan;Vlaams-Brabant",
    "iso:country":"BE",
    "sg:address":"Koning Albert I Laan 62",
    "sg:city":"Wemmel",
    "sg:classifiers":[
        {
            "category":"Recreation",
            "subcategory":"Water Park",
            "type":"Entertainment"
        }
    ],
    "sg:phone":"+32 2 456 02 60",
    "sg:postcode":"1780",
    "sg:province":"Vlaams-Brabant",
    "sg:tags":[
        "agent",
        "purification"
    ],
    "wof:name":"Nalco Belgium - Business Unit Aquazur N.v.-s.a.",
    "wof:placetype":"venue"
},
  "geometry": {"coordinates":[4.3198552132,50.8989334106],"type":"Point"}
}