{
  "type": "Feature",
  "properties": {
    "addr:full":"Hofstraat 10 Schoten Antwerpen 2900",
    "addr:housenumber":"10",
    "addr:postcode":"2900",
    "addr:street":"Hofstraat",
    "iso:country":"BE",
    "sg:address":"Hofstraat 10",
    "sg:city":"Schoten",
    "sg:orig_category":"Landmeters",
    "sg:phone":"+32 3 658 95 29",
    "sg:postcode":"2900",
    "sg:province":"Antwerpen",
    "wof:name":"Ludovicus Bresseleers",
    "wof:placetype":"venue"
},
  "geometry": {"coordinates":[4.495013237,51.2410545349],"type":"Point"}
}