{
  "type": "Feature",
  "properties": {
    "addr:full":"Haanhoutstraat 17 Lochristi (beervelde) Oost-Vlaanderen 9080",
    "addr:housenumber":"17",
    "addr:postcode":"9080",
    "addr:street":"Haanhoutstraat",
    "iso:country":"BE",
    "sg:address":"Haanhoutstraat 17",
    "sg:city":"Lochristi (beervelde)",
    "sg:classifiers":[
        {
            "category":"Building & Trades",
            "subcategory":"Construction",
            "type":"Services"
        }
    ],
    "sg:phone":"+32 9 355 84 25",
    "sg:postcode":"9080",
    "sg:province":"Oost-Vlaanderen",
    "sg:tags":[
        "carpenter"
    ],
    "wof:name":"Neyt Gebr Bvba",
    "wof:placetype":"venue"
},
  "geometry": {"coordinates":[3.8702011108,51.0796470642],"type":"Point"}
}