{
  "type": "Feature",
  "properties": {
    "iso:country":"BE",
    "sg:address":"Kardinaal Cardijnlaan 32",
    "sg:city":"Willebroek",
    "sg:orig_category":"Herstelling leer and schoeisel",
    "sg:phone":"+32 3 886 54 71",
    "sg:postcode":"2830",
    "sg:province":"Antwerpen",
    "wof:name":"Jan Verschueren",
    "wof:placetype":"venue"
},
  "geometry": {"coordinates":[4.3533291817,51.033870697],"type":"Point"}
}