{
  "type": "Feature",
  "properties": {
    "addr:full":"Avenue Du Ch\u00eane 132 Verviers (heusy) Li\u00e8ge 4802",
    "addr:housenumber":"132",
    "addr:postcode":"4802",
    "addr:street":"Avenue Du Che\u0302Ne",
    "iso:country":"BE",
    "sg:address":"Avenue Du Ch\u00eane 132",
    "sg:city":"Verviers (heusy)",
    "sg:classifiers":[
        {
            "category":"Education",
            "subcategory":"School",
            "type":"Public Place"
        }
    ],
    "sg:phone":"+32 87 22 58 60",
    "sg:postcode":"4802",
    "sg:province":"Li\u00e8ge",
    "sg:tags":[
        "boarding"
    ],
    "wof:name":"Internat Global Mixte",
    "wof:placetype":"venue"
},
  "geometry": {"coordinates":[5.8662018776,50.5729141235],"type":"Point"}
}