{
  "type": "Feature",
  "properties": {
    "addr:full":"Voogdijstraat 24 Mol Antwerpen 2400",
    "addr:housenumber":"24",
    "addr:postcode":"2400",
    "addr:street":"Voogdijstraat",
    "iso:country":"BE",
    "sg:address":"Voogdijstraat 24",
    "sg:city":"Mol",
    "sg:classifiers":[
        {
            "category":"Health Services",
            "subcategory":"Health Practitioner",
            "type":"Services"
        }
    ],
    "sg:phone":"+32 14 31 33 23",
    "sg:postcode":"2400",
    "sg:province":"Antwerpen",
    "sg:tags":[
        "physiotherapist"
    ],
    "wof:name":"Theunis Pascale",
    "wof:placetype":"venue"
},
  "geometry": {"coordinates":[5.1198101044,51.1874008179],"type":"Point"}
}