{
  "type": "Feature",
  "properties": {
    "addr:full":"Chauss\u00c9e D\u00b4andenne 23 Hamois Namur 5363",
    "addr:housenumber":"23",
    "addr:postcode":"5363",
    "addr:street":"Chausse\u0301E D\u00b4Andenne",
    "iso:country":"BE",
    "sg:address":"Chauss\u00c9e D\u00b4andenne 23",
    "sg:city":"Hamois",
    "sg:orig_category":"Installation \u00e9lectrique r\u00e9sidentielle",
    "sg:phone":"+32 83 61 26 28",
    "sg:postcode":"5363",
    "sg:province":"Namur",
    "wof:name":"Stany Delhaye",
    "wof:placetype":"venue"
},
  "geometry": {"coordinates":[5.1051249504,50.3483085632],"type":"Point"}
}