{
  "type": "Feature",
  "properties": {
    "iso:country":"BE",
    "sg:address":"Havenstraat 6",
    "sg:city":"Brugge",
    "sg:classifiers":[
        {
            "category":"Fast Food",
            "type":"Food & Drink"
        }
    ],
    "sg:phone":"+32 50 34 25 80",
    "sg:postcode":"8000",
    "sg:province":"West-Vlaanderen",
    "sg:tags":[
        "\u00c0",
        "emporter",
        "restaurants"
    ],
    "wof:name":"Frietshop",
    "wof:placetype":"venue"
},
  "geometry": {"coordinates":[3.227353096,51.222946167],"type":"Point"}
}