{
  "type": "Feature",
  "properties": {
    "addr:full":"Rue Beaussart 69 Charleroi Hainaut 6031",
    "addr:housenumber":"69",
    "addr:postcode":"6031",
    "addr:street":"Rue Beaussart;Hainaut",
    "iso:country":"BE",
    "sg:address":"Rue Beaussart 69",
    "sg:city":"Charleroi",
    "sg:orig_category":"Installatie van houten of kunststof schrijnwerk",
    "sg:phone":"+32 71 30 23 52",
    "sg:postcode":"6031",
    "sg:province":"Hainaut",
    "wof:name":"Argento",
    "wof:placetype":"venue"
},
  "geometry": {"coordinates":[4.38022995,50.4121742249],"type":"Point"}
}