{
  "type": "Feature",
  "properties": {
    "addr:full":"Oud Arenberg 71 Beveren Oost-Vlaanderen 9130",
    "addr:housenumber":"71",
    "addr:postcode":"9130",
    "addr:street":"Oud Arenberg",
    "iso:country":"BE",
    "sg:address":"Oud Arenberg 71",
    "sg:city":"Beveren",
    "sg:orig_category":"Rundveehouders",
    "sg:phone":"+32 3 773 52 47",
    "sg:postcode":"9130",
    "sg:province":"Oost-Vlaanderen",
    "wof:name":"Frans Van Overloop",
    "wof:placetype":"venue"
},
  "geometry": {"coordinates":[4.205892086,51.2887153625],"type":"Point"}
}