{
  "type": "Feature",
  "properties": {
    "addr:full":"Rue De Launoy 3 Meix-devant-virton Luxembourg 6769",
    "addr:housenumber":"3",
    "addr:postcode":"6769",
    "addr:street":"Rue De Launoy",
    "iso:country":"BE",
    "sg:address":"Rue De Launoy 3",
    "sg:city":"Meix-devant-virton",
    "sg:orig_category":"Boucheries",
    "sg:phone":"+32 63 57 74 37",
    "sg:postcode":"6769",
    "sg:province":"Luxembourg",
    "wof:name":"Jacques Roussel",
    "wof:placetype":"venue"
},
  "geometry": {"coordinates":[5.4814372063,49.6038169861],"type":"Point"}
}