{
  "type": "Feature",
  "properties": {
    "addr:full":"Ch\u00c9e De Braine-l'alleud 141 Sint-genesius-rode/rhode-saint-genese Vlaams-Brabant 1640",
    "addr:housenumber":"141;/",
    "addr:postcode":"1640",
    "addr:street":"Sint-Genesius-Rode;Vlaams-Brabant",
    "iso:country":"BE",
    "sg:address":"Ch\u00c9e De Braine-l'alleud 141",
    "sg:city":"Sint-genesius-rode/rhode-saint-genese",
    "sg:classifiers":[
        {
            "category":"Autos & Motor Vehicles",
            "subcategory":"Fuel & Gas Station",
            "type":"Retail Goods"
        }
    ],
    "sg:phone":"+32 2 380 33 67",
    "sg:postcode":"1640",
    "sg:province":"Vlaams-Brabant",
    "sg:tags":[
        "stations-service",
        "carburants"
    ],
    "wof:name":"Texaco",
    "wof:placetype":"venue"
},
  "geometry": {"coordinates":[4.3400931358,50.7326698303],"type":"Point"}
}