{
  "type": "Feature",
  "properties": {
    "iso:country":"BE",
    "sg:address":"Tushoekstraat 14",
    "sg:city":"Tessenderlo",
    "sg:classifiers":[
        {
            "category":"Health Services",
            "subcategory":"Health Practitioner",
            "type":"Services"
        }
    ],
    "sg:phone":"+32 13 66 37 14",
    "sg:postcode":"3980",
    "sg:province":"Limburg",
    "sg:tags":[
        "physiotherapist"
    ],
    "wof:name":"Verniers Ruth",
    "wof:placetype":"venue"
},
  "geometry": {"coordinates":[5.1300811768,51.0692977905],"type":"Point"}
}