{
  "type": "Feature",
  "properties": {
    "addr:full":"Rue De Waremme 31 Villers-le-bouillet Li\u00e8ge 4530",
    "addr:housenumber":"31",
    "addr:postcode":"4530",
    "addr:street":"Rue De Waremme",
    "iso:country":"BE",
    "sg:address":"Rue De Waremme 31",
    "sg:city":"Villers-le-bouillet",
    "sg:classifiers":[
        {
            "category":"Bars & Pubs",
            "type":"Food & Drink"
        }
    ],
    "sg:phone":"+32 85 23 16 77",
    "sg:postcode":"4530",
    "sg:province":"Li\u00e8ge",
    "wof:name":"Marronnier",
    "wof:placetype":"venue"
},
  "geometry": {"coordinates":[5.2664189339,50.5697402954],"type":"Point"}
}