{
  "type": "Feature",
  "properties": {
    "iso:country":"BE",
    "sg:address":"Van Wesenbekestr 51-55",
    "sg:city":"Antwerpen",
    "sg:classifiers":[
        {
            "category":"Home & Garden",
            "subcategory":"Furniture",
            "type":"Retail Goods"
        }
    ],
    "sg:phone":"+32 3 233 54 18",
    "sg:postcode":"2060",
    "sg:province":"Antwerpen",
    "sg:tags":[
        "household",
        "wood"
    ],
    "wof:name":"Billards Thissen Nv",
    "wof:placetype":"venue"
},
  "geometry": {"coordinates":[4.4205899239,51.2205276489],"type":"Point"}
}