{
  "type": "Feature",
  "properties": {
    "iso:country":"BE",
    "sg:address":"Steenweg 244",
    "sg:city":"Alken",
    "sg:orig_category":"Kapsalons",
    "sg:phone":"+32 11 59 21 69",
    "sg:postcode":"3570",
    "sg:province":"Limburg",
    "wof:name":"Coiffure Brigitte",
    "wof:placetype":"venue"
},
  "geometry": {"coordinates":[5.2715010643,50.8790016174],"type":"Point"}
}