{
  "type": "Feature",
  "properties": {
    "iso:country":"BE",
    "sg:address":"Leopoldslei 3",
    "sg:city":"Brasschaat",
    "sg:orig_category":"Textiel",
    "sg:phone":"+32 3 653 14 88",
    "sg:postcode":"2930",
    "sg:province":"Antwerpen",
    "wof:name":"White-house",
    "wof:placetype":"venue"
},
  "geometry": {"coordinates":[4.4876151085,51.2887649536],"type":"Point"}
}