{
  "type": "Feature",
  "properties": {
    "addr:full":"Antwerpsebaan 105 Antwerpen Antwerpen 2040",
    "addr:housenumber":"105",
    "addr:postcode":"2040",
    "addr:street":"Antwerpsebaan",
    "iso:country":"BE",
    "sg:address":"Antwerpsebaan 105",
    "sg:city":"Antwerpen",
    "sg:orig_category":"Benzinestations and brandstoffen Voertuigen",
    "sg:phone":"+32 3 568 62 51",
    "sg:postcode":"2040",
    "sg:province":"Antwerpen",
    "wof:name":"Fa. Kerschot-gabriels& Zn",
    "wof:placetype":"venue"
},
  "geometry": {"coordinates":[4.3218011856,51.3389434814],"type":"Point"}
}