{
  "type": "Feature",
  "properties": {
    "addr:full":"Rue Jules Ruelle 40 Saint-ghislain (sirault) Hainaut 7332",
    "addr:housenumber":"40",
    "addr:postcode":"7332",
    "addr:street":"Rue Jules Ruelle",
    "iso:country":"BE",
    "sg:address":"Rue Jules Ruelle 40",
    "sg:city":"Saint-ghislain (sirault)",
    "sg:classifiers":[
        {
            "category":"Building & Trades",
            "subcategory":"Plumbing",
            "type":"Services"
        }
    ],
    "sg:phone":"+32 65 52 04 70",
    "sg:postcode":"7332",
    "sg:province":"Hainaut",
    "sg:tags":[
        "repair",
        "mainten",
        "-",
        "central",
        "heating"
    ],
    "wof:name":"A Banneel",
    "wof:placetype":"venue"
},
  "geometry": {"coordinates":[3.786839962,50.5054969788],"type":"Point"}
}