{
  "type": "Feature",
  "properties": {
    "iso:country":"BE",
    "sg:address":"Karel De Grotelaan 1 Box 17",
    "sg:city":"International Press Center",
    "sg:classifiers":[
        {
            "category":"Communications",
            "subcategory":"News Services",
            "type":"Services"
        }
    ],
    "sg:phone":"+32 2 230 36 91",
    "sg:postcode":"1041",
    "sg:tags":[
        "agency"
    ],
    "wof:name":"Deutsche Presse-agentur Bvba",
    "wof:placetype":"venue"
},
  "geometry": {"coordinates":[-94.2034988403,31.7978382111],"type":"Point"}
}