{
  "type": "Feature",
  "properties": {
    "iso:country":"BE",
    "sg:address":"Rue Du Ch\u00c2teau 38",
    "sg:city":"Eghezee",
    "sg:orig_category":"Antiquit\u00e9s. Eclairage et \u00e9quipements du foyer",
    "sg:phone":"+32 81 65 65 48",
    "sg:postcode":"5310",
    "sg:province":"Namur",
    "wof:name":"La Viole Du Huchier",
    "wof:placetype":"venue"
},
  "geometry": {"coordinates":[4.8291668892,50.5963287354],"type":"Point"}
}