{
  "type": "Feature",
  "properties": {
    "addr:full":"Karel Oomsstraat 21 Turnhout Antwerpen 2300",
    "addr:housenumber":"21",
    "addr:postcode":"2300",
    "addr:street":"Karel Oomsstraat",
    "iso:country":"BE",
    "sg:address":"Karel Oomsstraat 21",
    "sg:city":"Turnhout",
    "sg:orig_category":"Boekhouders",
    "sg:phone":"+32 14 42 58 56",
    "sg:postcode":"2300",
    "sg:province":"Antwerpen",
    "wof:name":"Sigrid Swerts",
    "wof:placetype":"venue"
},
  "geometry": {"coordinates":[4.9321360588,51.3253746033],"type":"Point"}
}