{
  "type": "Feature",
  "properties": {
    "addr:full":"Rue D'enfer 35 Florenville Luxembourg 6820",
    "addr:housenumber":"35",
    "addr:postcode":"6820",
    "addr:street":"Rue D'Enfer",
    "iso:country":"BE",
    "sg:address":"Rue D'enfer 35",
    "sg:city":"Florenville",
    "sg:orig_category":"Offices du tourisme",
    "sg:phone":"+32 61 32 00 19",
    "sg:postcode":"6820",
    "sg:province":"Luxembourg",
    "wof:name":"Syndicat D'initiative",
    "wof:placetype":"venue"
},
  "geometry": {"coordinates":[5.1790819168,49.7181167603],"type":"Point"}
}