{
  "type": "Feature",
  "properties": {
    "iso:country":"BE",
    "sg:address":"P Mellaertsstraat 31",
    "sg:city":"Heist-op-den-berg",
    "sg:orig_category":"Electrom\u00e9nager, t\u00e9l\u00e9visions and radios. R\u00e9parations d'appareils \u00e9lectrom\u00e9nagers. Mat\u00e9riel de T\u00e9l\u00e9com",
    "sg:phone":"+32 15 24 84 71",
    "sg:postcode":"2220",
    "sg:province":"Antwerpen",
    "wof:name":"A.v.n.",
    "wof:placetype":"venue"
},
  "geometry": {"coordinates":[4.7192502022,51.0442085266],"type":"Point"}
}