{
  "type": "Feature",
  "properties": {
    "iso:country":"BE",
    "sg:address":"Markt 65",
    "sg:city":"Eeklo",
    "sg:orig_category":"Bijouteries and horlogeries",
    "sg:phone":"+32 9 378 02 82",
    "sg:postcode":"9900",
    "sg:province":"Oost-Vlaanderen",
    "wof:name":"Goudkramer",
    "wof:placetype":"venue"
},
  "geometry": {"coordinates":[3.5652859211,51.184513092],"type":"Point"}
}