{
  "type": "Feature",
  "properties": {
    "iso:country":"BE",
    "sg:address":"Langdorpsesteenweg 199",
    "sg:city":"Aarschot",
    "sg:orig_category":"Catering and organisatie van feesten",
    "sg:phone":"+32 16 56 96 95",
    "sg:postcode":"3201",
    "sg:province":"Vlaams-Brabant",
    "wof:name":"Traiteur Tope",
    "wof:placetype":"venue"
},
  "geometry": {"coordinates":[4.8563890457,50.9928627014],"type":"Point"}
}