{
  "type": "Feature",
  "properties": {
    "iso:country":"BE",
    "sg:address":"Bilkske 55",
    "sg:city":"Brugge",
    "sg:orig_category":"Slagers",
    "sg:phone":"+32 50 33 11 04",
    "sg:postcode":"8000",
    "sg:province":"West-Vlaanderen",
    "wof:name":"Roger Reyserhove",
    "wof:placetype":"venue"
},
  "geometry": {"coordinates":[3.2365241051,51.2088127136],"type":"Point"}
}