{
  "type": "Feature",
  "properties": {
    "addr:full":"Rue Lamberts 59 Welkenraedt Li\u00e8ge 4840",
    "addr:housenumber":"59",
    "addr:postcode":"4840",
    "addr:street":"Rue Lamberts",
    "iso:country":"BE",
    "sg:address":"Rue Lamberts 59",
    "sg:city":"Welkenraedt",
    "sg:orig_category":"Cliniques and h\u00f4pitaux",
    "sg:phone":"+32 87 88 27 16",
    "sg:postcode":"4840",
    "sg:province":"Li\u00e8ge",
    "wof:name":"Laboratoires Dr.ph.ralet",
    "wof:placetype":"venue"
},
  "geometry": {"coordinates":[5.9765520096,50.6606292725],"type":"Point"}
}