{
  "type": "Feature",
  "properties": {
    "iso:country":"BE",
    "sg:address":"Koningin Elisabethlaan 49",
    "sg:city":"Brugge",
    "sg:classifiers":[
        {
            "category":"Shopping",
            "subcategory":"Gifts & Souvenirs",
            "type":"Retail Goods"
        }
    ],
    "sg:phone":"+32 474 55 83 16",
    "sg:postcode":"8000",
    "sg:province":"West-Vlaanderen",
    "sg:tags":[
        "postcard",
        "picture",
        "greeting",
        "card"
    ],
    "wof:name":"Beeldend Kalligrafie",
    "wof:placetype":"venue"
},
  "geometry": {"coordinates":[3.2185399532,51.2172622681],"type":"Point"}
}