{
  "type": "Feature",
  "properties": {
    "addr:full":". Charleroi Hainaut 6040",
    "addr:postcode":"6040",
    "addr:street":"Hainaut",
    "iso:country":"BE",
    "sg:address":".",
    "sg:city":"Charleroi",
    "sg:orig_category":"Diverse machines voor de nijverheid Gh",
    "sg:phone":"+32 71 37 13 70",
    "sg:postcode":"6040",
    "sg:province":"Hainaut",
    "wof:name":"Thomas",
    "wof:placetype":"venue"
},
  "geometry": {"coordinates":[4.4245052338,50.4448814392],"type":"Point"}
}