{
  "type": "Feature",
  "properties": {
    "iso:country":"BE",
    "sg:address":"Breendonkstraat 376",
    "sg:city":"Willebroek",
    "sg:orig_category":"Transports terrestres de voyageurs",
    "sg:phone":"+32 3 886 60 29",
    "sg:postcode":"2830",
    "sg:province":"Antwerpen",
    "wof:name":"Autobus Klein Brabant",
    "wof:placetype":"venue"
},
  "geometry": {"coordinates":[4.3317298889,51.0417671204],"type":"Point"}
}