{
  "type": "Feature",
  "properties": {
    "addr:full":"Gloxinialaan 11 De Pinte Oost-Vlaanderen 9840",
    "addr:housenumber":"11",
    "addr:postcode":"9840",
    "addr:street":"Gloxinialaan",
    "iso:country":"BE",
    "sg:address":"Gloxinialaan 11",
    "sg:city":"De Pinte",
    "sg:classifiers":[
        {
            "category":"Government",
            "subcategory":"Fire Station",
            "type":"Public Place"
        }
    ],
    "sg:phone":"+32 473 85 38 88",
    "sg:postcode":"9840",
    "sg:province":"Oost-Vlaanderen",
    "sg:tags":[
        "detection",
        "installation",
        "material",
        "-"
    ],
    "wof:name":"Axs Systems Technology Bvba",
    "wof:placetype":"venue"
},
  "geometry": {"coordinates":[3.6563150883,50.9963874817],"type":"Point"}
}