{
  "type": "Feature",
  "properties": {
    "iso:country":"BE",
    "sg:address":"Plassendaalsesteenweg 19",
    "sg:city":"Oostende (zandvoorde)",
    "sg:classifiers":[
        {
            "category":"Organizations",
            "subcategory":"Labor Organization",
            "type":"Services"
        }
    ],
    "sg:phone":"+32 59 32 27 32",
    "sg:postcode":"8400",
    "sg:province":"West-Vlaanderen",
    "sg:tags":[
        "draining",
        "work"
    ],
    "wof:name":"Goethals & Zonen Nv",
    "wof:placetype":"venue"
},
  "geometry": {"coordinates":[2.9954299927,51.2196769714],"type":"Point"}
}