{
  "type": "Feature",
  "properties": {
    "addr:full":"Route De Bouillon 16 Arlon (heinsch) Luxembourg 6700",
    "addr:housenumber":"16",
    "addr:postcode":"6700",
    "addr:street":"Route De Bouillon",
    "iso:country":"BE",
    "sg:address":"Route De Bouillon 16",
    "sg:city":"Arlon (heinsch)",
    "sg:classifiers":[
        {
            "category":"Home & Garden",
            "subcategory":"Household Appliances",
            "type":"Retail Goods"
        }
    ],
    "sg:phone":"+32 63 22 71 38",
    "sg:postcode":"6700",
    "sg:province":"Luxembourg",
    "sg:tags":[
        "repair",
        "mainten",
        "-",
        "electric"
    ],
    "wof:name":"Boutet R",
    "wof:placetype":"venue"
},
  "geometry": {"coordinates":[5.8126749992,49.6823234558],"type":"Point"}
}