{
  "type": "Feature",
  "properties": {
    "addr:full":"Rue L Debelle 28 Manage Hainaut 7170",
    "addr:housenumber":"28",
    "addr:postcode":"7170",
    "addr:street":"Rue L Debelle",
    "iso:country":"BE",
    "sg:address":"Rue L Debelle 28",
    "sg:city":"Manage",
    "sg:classifiers":[
        {
            "category":"Banks & Credit Unions",
            "subcategory":"Bank",
            "type":"Services"
        }
    ],
    "sg:postcode":"7170",
    "sg:province":"Hainaut",
    "wof:name":"Banque Bruxelles Lambert Sa",
    "wof:placetype":"venue"
},
  "geometry": {"coordinates":[4.2327899933,50.5008239746],"type":"Point"}
}