{
  "type": "Feature",
  "properties": {
    "iso:country":"BE",
    "sg:address":"Onze-lieve-vrouwstraat 90",
    "sg:city":"Heusden-zolder (zolder)",
    "sg:classifiers":[
        {
            "category":"Professional",
            "subcategory":"Computer Services",
            "type":"Services"
        }
    ],
    "sg:phone":"+32 11 53 34 54",
    "sg:postcode":"3550",
    "sg:province":"Limburg",
    "sg:tags":[
        "-",
        "processing",
        "data"
    ],
    "wof:name":"Erocos International Bvba",
    "wof:placetype":"venue"
},
  "geometry": {"coordinates":[5.2790551186,51.0138778687],"type":"Point"}
}