{
  "type": "Feature",
  "properties": {
    "addr:full":"Driesstraat 53 Bornem Antwerpen 2880",
    "addr:housenumber":"53",
    "addr:postcode":"2880",
    "addr:street":"Driesstraat",
    "iso:country":"BE",
    "sg:address":"Driesstraat 53",
    "sg:city":"Bornem",
    "sg:classifiers":[
        {
            "category":"Personal",
            "subcategory":"Beauty Salon",
            "type":"Services"
        }
    ],
    "sg:phone":"+32 3 889 03 13",
    "sg:postcode":"2880",
    "sg:province":"Antwerpen",
    "sg:tags":[
        "de",
        "coiffure"
    ],
    "wof:name":"Coiffure Mimosa",
    "wof:placetype":"venue"
},
  "geometry": {"coordinates":[4.2348451614,51.1007614136],"type":"Point"}
}