{
  "type": "Feature",
  "properties": {
    "iso:country":"BE",
    "sg:address":"Rue Hov\u00c9mont 145",
    "sg:city":"Theux",
    "sg:orig_category":"Herstellingen and onderhoud van auto's",
    "sg:phone":"+32 87 54 27 87",
    "sg:postcode":"4910",
    "sg:province":"Li\u00e8ge",
    "wof:name":"Philippe Sougne",
    "wof:placetype":"venue"
},
  "geometry": {"coordinates":[5.8151898384,50.5320892334],"type":"Point"}
}