{
  "type": "Feature",
  "properties": {
    "addr:full":"Chauss\u00e9e Du Roeulx 366 Mons Hainaut 7000",
    "addr:housenumber":"366",
    "addr:postcode":"7000",
    "addr:street":"Chausse\u0301E Du Roeulx;Hainaut",
    "iso:country":"BE",
    "sg:address":"Chauss\u00e9e Du Roeulx 366",
    "sg:city":"Mons",
    "sg:classifiers":[
        {
            "category":"Banks & Credit Unions",
            "subcategory":"Financial Services",
            "type":"Services"
        }
    ],
    "sg:phone":"+32 65 34 07 03",
    "sg:postcode":"7000",
    "sg:province":"Hainaut",
    "sg:tags":[
        "loan",
        "mortgage"
    ],
    "wof:name":"Cr\u00e9dit Montois",
    "wof:placetype":"venue"
},
  "geometry": {"coordinates":[3.9936549664,50.4578285217],"type":"Point"}
}