{
  "type": "Feature",
  "properties": {
    "iso:country":"BE",
    "sg:address":"Kouterweg 11",
    "sg:city":"Izegem",
    "sg:classifiers":[
        {
            "category":"Personal",
            "subcategory":"Beauty Salon",
            "type":"Services"
        }
    ],
    "sg:phone":"+32 51 30 85 26",
    "sg:postcode":"8870",
    "sg:province":"West-Vlaanderen",
    "sg:tags":[
        "de",
        "coiffure"
    ],
    "wof:name":"Monica",
    "wof:placetype":"venue"
},
  "geometry": {"coordinates":[3.2274649143,50.9235687256],"type":"Point"}
}