{
  "type": "Feature",
  "properties": {
    "iso:country":"BE",
    "sg:address":"Terbekehofdreef 65",
    "sg:city":"Wilrijk",
    "sg:classifiers":[
        {
            "category":"Autos & Motor Vehicles",
            "subcategory":"Automobile Sales",
            "type":"Retail Goods"
        }
    ],
    "sg:phone":"+32 3 828 11 36",
    "sg:postcode":"2610",
    "sg:province":"Antwerpen",
    "sg:tags":[
        "equipment",
        "transport"
    ],
    "wof:name":"Sapim Nv",
    "wof:placetype":"venue"
},
  "geometry": {"coordinates":[4.3688998222,51.1591682434],"type":"Point"}
}