{
  "type": "Feature",
  "properties": {
    "addr:full":"Lindestraat 33 Lochristi (zaffelare) Oost-Vlaanderen 9080",
    "addr:housenumber":"33",
    "addr:postcode":"9080",
    "addr:street":"Lindestraat",
    "iso:country":"BE",
    "sg:address":"Lindestraat 33",
    "sg:city":"Lochristi (zaffelare)",
    "sg:classifiers":[
        {
            "category":"Health Services",
            "subcategory":"Doctor",
            "type":"Services"
        }
    ],
    "sg:phone":"+32 9 356 90 22",
    "sg:postcode":"9080",
    "sg:province":"Oost-Vlaanderen",
    "sg:tags":[
        "medicinephysicians",
        "surgeon"
    ],
    "wof:name":"Goeminne Ann",
    "wof:placetype":"venue"
},
  "geometry": {"coordinates":[3.8275470734,51.1212730408],"type":"Point"}
}