{
  "type": "Feature",
  "properties": {
    "iso:country":"BE",
    "sg:address":"Rue Du Douaire 40",
    "sg:city":"Anderlues",
    "sg:classifiers":[
        {
            "category":"Organizations",
            "subcategory":"Community Association",
            "type":"Services"
        }
    ],
    "sg:phone":"+32 71 54 84 34",
    "sg:postcode":"6150",
    "sg:province":"Hainaut",
    "sg:tags":[
        "organisation"
    ],
    "wof:name":"Jeunesse & Sant\u00c9",
    "wof:placetype":"venue"
},
  "geometry": {"coordinates":[4.2746920586,50.3983383179],"type":"Point"}
}