{
  "type": "Feature",
  "properties": {
    "addr:full":"Rue Saint-roch 10 Mouscron Hainaut 7712",
    "addr:housenumber":"10",
    "addr:postcode":"7712",
    "addr:street":"Rue Saint-Roch",
    "iso:country":"BE",
    "sg:address":"Rue Saint-roch 10",
    "sg:city":"Mouscron",
    "sg:orig_category":"Koerierbedrijven Verhuisdiensten",
    "sg:phone":"+32 56 84 69 61",
    "sg:postcode":"7712",
    "sg:province":"Hainaut",
    "wof:name":"Transport Demolans",
    "wof:placetype":"venue"
},
  "geometry": {"coordinates":[3.2448129654,50.7193183899],"type":"Point"}
}