{
  "type": "Feature",
  "properties": {
    "addr:full":"Chauss\u00e9e De Wavre 150 Perwez Brabant Wallon 1360",
    "addr:housenumber":"150",
    "addr:postcode":"1360",
    "addr:street":"Chausse\u0301E De Wavre",
    "iso:country":"BE",
    "sg:address":"Chauss\u00e9e De Wavre 150",
    "sg:city":"Perwez",
    "sg:classifiers":[
        {
            "category":"Shopping",
            "subcategory":"Clothing, Apparel, & Fashions",
            "type":"Retail Goods"
        }
    ],
    "sg:phone":"+32 81 65 94 90",
    "sg:postcode":"1360",
    "sg:province":"Brabant Wallon",
    "sg:tags":[
        "underwear",
        "lingerie",
        "-"
    ],
    "wof:name":"Lingerie Flo",
    "wof:placetype":"venue"
},
  "geometry": {"coordinates":[4.8033800125,50.6295204163],"type":"Point"}
}