{
  "type": "Feature",
  "properties": {
    "iso:country":"BE",
    "sg:address":"Hulst 120",
    "sg:city":"Lede",
    "sg:orig_category":"Matrices",
    "sg:phone":"+32 53 80 46 27",
    "sg:postcode":"9340",
    "sg:province":"Oost-Vlaanderen",
    "wof:name":"De Vuyst F",
    "wof:placetype":"venue"
},
  "geometry": {"coordinates":[3.9773280621,50.9667625427],"type":"Point"}
}