{
  "type": "Feature",
  "properties": {
    "iso:country":"BE",
    "sg:address":"Stalenstraat 105",
    "sg:city":"Genk",
    "sg:classifiers":[
        {
            "category":"Cafe",
            "type":"Food & Drink"
        }
    ],
    "sg:phone":"+32 89 84 23 10",
    "sg:postcode":"3600",
    "sg:province":"Limburg",
    "sg:tags":[
        "caf\u00e9s"
    ],
    "wof:name":"Caf\u00c9 Starlet",
    "wof:placetype":"venue"
},
  "geometry": {"coordinates":[5.5199542046,50.994430542],"type":"Point"}
}