{
  "type": "Feature",
  "properties": {
    "iso:country":"BE",
    "sg:address":"Rue Tigr\u00e9e 27",
    "sg:city":"Sombreffe (ligny)",
    "sg:classifiers":[
        {
            "category":"Insurance",
            "subcategory":"Insurance Agent",
            "type":"Services"
        }
    ],
    "sg:phone":"+32 71 88 78 13",
    "sg:postcode":"5140",
    "sg:province":"Namur",
    "sg:tags":[
        "broker"
    ],
    "wof:name":"Vounckx P",
    "wof:placetype":"venue"
},
  "geometry": {"coordinates":[4.5737810135,50.5149154663],"type":"Point"}
}