{
  "type": "Feature",
  "properties": {
    "addr:full":"Rue Albert Ier 31 Hannut Li\u00e8ge 4280",
    "addr:housenumber":"31",
    "addr:postcode":"4280",
    "addr:street":"Rue Albert Ier",
    "iso:country":"BE",
    "sg:address":"Rue Albert Ier 31",
    "sg:city":"Hannut",
    "sg:orig_category":"Textiles. Rev\u00eatements de sols and murs. Installation de menuiserie en bois and plastique. Drogueries",
    "sg:phone":"+32 19 51 11 37",
    "sg:postcode":"4280",
    "sg:province":"Li\u00e8ge",
    "wof:name":"Maquet",
    "wof:placetype":"venue"
},
  "geometry": {"coordinates":[5.0821142197,50.6704444885],"type":"Point"}
}