{
  "type": "Feature",
  "properties": {
    "addr:full":"Neve De Mevergniesstraat 1 Merelbeke Oost-Vlaanderen 9820",
    "addr:housenumber":"1",
    "addr:postcode":"9820",
    "addr:street":"Mevergniesstraat",
    "iso:country":"BE",
    "sg:address":"Neve De Mevergniesstraat 1",
    "sg:city":"Merelbeke",
    "sg:classifiers":[
        {
            "category":"Personal",
            "subcategory":"Beauty Salon",
            "type":"Services"
        }
    ],
    "sg:phone":"+32 9 362 36 02",
    "sg:postcode":"9820",
    "sg:province":"Oost-Vlaanderen",
    "sg:tags":[
        "de",
        "coiffure"
    ],
    "wof:name":"Wendy\u00b4s Hairstudio",
    "wof:placetype":"venue"
},
  "geometry": {"coordinates":[3.7548370361,50.9634094238],"type":"Point"}
}