{
  "type": "Feature",
  "properties": {
    "addr:full":"Markt 24 Oudenaarde Oost-Vlaanderen 9700",
    "addr:housenumber":"24",
    "addr:postcode":"9700",
    "addr:street":"Markt",
    "iso:country":"BE",
    "sg:address":"Markt 24",
    "sg:city":"Oudenaarde",
    "sg:classifiers":[
        {
            "category":"Professional",
            "subcategory":"Testing Lab",
            "type":"Services"
        }
    ],
    "sg:phone":"+32 55 30 50 50",
    "sg:postcode":"9700",
    "sg:province":"Oost-Vlaanderen",
    "sg:tags":[
        "chemist"
    ],
    "wof:name":"Pype C",
    "wof:placetype":"venue"
},
  "geometry": {"coordinates":[3.6048328876,50.8427467346],"type":"Point"}
}