{
  "type": "Feature",
  "properties": {
    "iso:country":"BE",
    "sg:address":"Jacob De Roorestraat 23",
    "sg:city":"Edegem",
    "sg:orig_category":"Pain, p\u00e2tisseries and confiseries",
    "sg:phone":"+32 3 449 88 33",
    "sg:postcode":"2650",
    "sg:province":"Antwerpen",
    "wof:name":"Chocolaterie Mascotte",
    "wof:placetype":"venue"
},
  "geometry": {"coordinates":[4.4371590614,51.1694984436],"type":"Point"}
}