{
  "type": "Feature",
  "properties": {
    "addr:full":"Abeel 9 Sint-katelijne-waver Antwerpen 2860",
    "addr:housenumber":"9",
    "addr:postcode":"2860",
    "addr:street":"Abeel",
    "iso:country":"BE",
    "sg:address":"Abeel 9",
    "sg:city":"Sint-katelijne-waver",
    "sg:orig_category":"Imprimeries and copyshops",
    "sg:phone":"+32 15 31 28 01",
    "sg:postcode":"2860",
    "sg:province":"Antwerpen",
    "wof:name":"Publi Idee",
    "wof:placetype":"venue"
},
  "geometry": {"coordinates":[4.5505337715,51.0714035034],"type":"Point"}
}