{
  "type": "Feature",
  "properties": {
    "iso:country":"BE",
    "sg:address":"Chauss\u00c9e D'audenarde 213",
    "sg:city":"Pecq",
    "sg:orig_category":"Epiceries",
    "sg:phone":"+32 69 55 74 59",
    "sg:postcode":"7742",
    "sg:province":"Hainaut",
    "wof:name":"Regine Delroeux",
    "wof:placetype":"venue"
},
  "geometry": {"coordinates":[3.3617990017,50.6957397461],"type":"Point"}
}