{
  "type": "Feature",
  "properties": {
    "iso:country":"BE",
    "sg:address":"Vogelstraat 20",
    "sg:city":"Putte",
    "sg:orig_category":"Groententeelt",
    "sg:phone":"+32 15 75 78 52",
    "sg:postcode":"2580",
    "sg:province":"Antwerpen",
    "wof:name":"Frans Frans",
    "wof:placetype":"venue"
},
  "geometry": {"coordinates":[4.6402111053,51.04637146],"type":"Point"}
}