{
  "type": "Feature",
  "properties": {
    "iso:country":"BE",
    "sg:address":"Burkel 12",
    "sg:city":"Peer",
    "sg:orig_category":"Supermarch\u00e9s",
    "sg:postcode":"3990",
    "sg:province":"Limburg",
    "wof:name":"Aldi",
    "wof:placetype":"venue"
},
  "geometry": {"coordinates":[5.4587068558,51.1296043396],"type":"Point"}
}