{
  "type": "Feature",
  "properties": {
    "iso:country":"BE",
    "sg:address":"Avenue Brugmann 303",
    "sg:city":"Bruxelles (uccle)",
    "sg:classifiers":[
        {
            "category":"Professional",
            "subcategory":"Secretarial Services",
            "type":"Services"
        }
    ],
    "sg:phone":"+32 2 227 13 90",
    "sg:postcode":"1180",
    "sg:province":"Bruxelles-Capitale",
    "sg:tags":[
        "firm"
    ],
    "wof:name":"Pharos Corporation Sa",
    "wof:placetype":"venue"
},
  "geometry": {"coordinates":[4.3461880684,50.8112602234],"type":"Point"}
}