{
  "type": "Feature",
  "properties": {
    "iso:country":"BE",
    "sg:address":"Schutterslaan 7",
    "sg:city":"Meeuwen-gruitrode (ellikom)",
    "sg:classifiers":[
        {
            "category":"Manufacturing",
            "subcategory":"Building Materials",
            "type":"Manufacturing & Wholesale Goods"
        }
    ],
    "sg:phone":"+32 11 61 01 61",
    "sg:postcode":"3670",
    "sg:province":"Limburg",
    "sg:tags":[
        "boiler",
        "manufacturer"
    ],
    "wof:name":"Ellimetal Nv",
    "wof:placetype":"venue"
},
  "geometry": {"coordinates":[5.5205497742,51.0963516235],"type":"Point"}
}