{
  "type": "Feature",
  "properties": {
    "addr:full":"Haldertstraat 10 Tielt-winge Vlaams-Brabant 3390",
    "addr:housenumber":"10",
    "addr:postcode":"3390",
    "addr:street":"Haldertstraat",
    "iso:country":"BE",
    "sg:address":"Haldertstraat 10",
    "sg:city":"Tielt-winge",
    "sg:orig_category":"Benzinestations and brandstoffen Herstellingen and onderhoud van auto's Motorfietsen",
    "sg:phone":"+32 16 63 46 94",
    "sg:postcode":"3390",
    "sg:province":"Vlaams-Brabant",
    "wof:name":"Garage Coeckaerts",
    "wof:placetype":"venue"
},
  "geometry": {"coordinates":[4.8663258553,50.9364471436],"type":"Point"}
}