{
  "type": "Feature",
  "properties": {
    "addr:full":"Rue De L'yser 15 Aywaille Li\u00e8ge 4920",
    "addr:housenumber":"15",
    "addr:postcode":"4920",
    "addr:street":"Rue De L'Yser",
    "iso:country":"BE",
    "sg:address":"Rue De L'yser 15",
    "sg:city":"Aywaille",
    "sg:orig_category":"Enseignement secondaire g\u00e9n\u00e9ral. Enseignement maternel and primaire",
    "sg:phone":"+32 4 384 42 45",
    "sg:postcode":"4920",
    "sg:province":"Li\u00e8ge",
    "wof:name":"Ecole Fondamentale",
    "wof:placetype":"venue"
},
  "geometry": {"coordinates":[5.6717619896,50.475402832],"type":"Point"}
}