{
  "type": "Feature",
  "properties": {
    "addr:full":"Rue Baudrihaye 25ba Soumagne Li\u00e8ge 4630",
    "addr:housenumber":"25ba",
    "addr:postcode":"4630",
    "addr:street":"Rue Baudrihaye",
    "iso:country":"BE",
    "sg:address":"Rue Baudrihaye 25ba",
    "sg:city":"Soumagne",
    "sg:orig_category":"Boekhouders",
    "sg:phone":"+32 4 377 52 17",
    "sg:postcode":"4630",
    "sg:province":"Li\u00e8ge",
    "wof:name":"Anne-marie Ory",
    "wof:placetype":"venue"
},
  "geometry": {"coordinates":[5.7392549515,50.6060066223],"type":"Point"}
}