{
  "type": "Feature",
  "properties": {
    "iso:country":"BE",
    "sg:address":"Rue Rioul 13",
    "sg:city":"Huy",
    "sg:orig_category":"Apotheken",
    "sg:phone":"+32 85 21 19 63",
    "sg:postcode":"4500",
    "sg:province":"Li\u00e8ge",
    "wof:name":"Pharmacie Populaire",
    "wof:placetype":"venue"
},
  "geometry": {"coordinates":[5.2443070412,50.5235023499],"type":"Point"}
}