{
  "type": "Feature",
  "properties": {
    "addr:full":"Rue Du Chemin De Fer 48 Ath Hainaut 7800",
    "addr:housenumber":"48",
    "addr:postcode":"7800",
    "addr:street":"Rue Du Chemin De Fer",
    "iso:country":"BE",
    "sg:address":"Rue Du Chemin De Fer 48",
    "sg:city":"Ath",
    "sg:classifiers":[
        {
            "category":"Banks & Credit Unions",
            "subcategory":"Investment Brokerage",
            "type":"Services"
        }
    ],
    "sg:phone":"+32 68 28 32 90",
    "sg:postcode":"7800",
    "sg:province":"Hainaut",
    "sg:tags":[
        "printing",
        "-"
    ],
    "wof:name":"Impribel",
    "wof:placetype":"venue"
},
  "geometry": {"coordinates":[3.7860429287,50.623878479],"type":"Point"}
}