{
  "type": "Feature",
  "properties": {
    "addr:full":"Scheldestraat 28 Antwerpen Antwerpen 2000",
    "addr:housenumber":"28",
    "addr:postcode":"2000",
    "addr:street":"Scheldestraat",
    "iso:country":"BE",
    "sg:address":"Scheldestraat 28",
    "sg:city":"Antwerpen",
    "sg:orig_category":"Enregistrements sonores",
    "sg:phone":"+32 3 257 24 97",
    "sg:postcode":"2000",
    "sg:province":"Antwerpen",
    "wof:name":"Studio Vitanova",
    "wof:placetype":"venue"
},
  "geometry": {"coordinates":[4.3921661377,51.2127838135],"type":"Point"}
}