{
  "type": "Feature",
  "properties": {
    "addr:full":"Rue D'omerie 19 Tournai Hainaut 7540",
    "addr:housenumber":"19",
    "addr:postcode":"7540",
    "addr:street":"Rue D'Omerie",
    "iso:country":"BE",
    "sg:address":"Rue D'omerie 19",
    "sg:city":"Tournai",
    "sg:orig_category":"Groenten and fruit Gh",
    "sg:phone":"+32 69 21 37 94",
    "sg:postcode":"7540",
    "sg:province":"Hainaut",
    "wof:name":"First International",
    "wof:placetype":"venue"
},
  "geometry": {"coordinates":[3.3918190002,50.6405181885],"type":"Point"}
}