{
  "type": "Feature",
  "properties": {
    "addr:full":"Nieuwstraat 141b Diepenbeek Limburg 3590",
    "addr:housenumber":"141b",
    "addr:postcode":"3590",
    "addr:street":"Nieuwstraat",
    "iso:country":"BE",
    "sg:address":"Nieuwstraat 141b",
    "sg:city":"Diepenbeek",
    "sg:orig_category":"Eclairage et \u00e9quipements du foyer. Textiles. R\u00e9paration and restauration de meubles",
    "sg:phone":"+32 11 32 44 43",
    "sg:postcode":"3590",
    "sg:province":"Limburg",
    "wof:name":"Engelen",
    "wof:placetype":"venue"
},
  "geometry": {"coordinates":[5.4493341446,50.9231643677],"type":"Point"}
}