{
  "type": "Feature",
  "properties": {
    "addr:full":"Bormstr 24 Willebroek Antwerpen 2830",
    "addr:housenumber":"24",
    "addr:postcode":"2830",
    "addr:street":"Bormstr",
    "iso:country":"BE",
    "sg:address":"Bormstr 24",
    "sg:city":"Willebroek",
    "sg:classifiers":[
        {
            "category":"Professional",
            "subcategory":"Engineering",
            "type":"Services"
        }
    ],
    "sg:phone":"+32 15 71 81 00",
    "sg:postcode":"2830",
    "sg:province":"Antwerpen",
    "sg:tags":[
        "machine",
        "-",
        "environment",
        "equipment",
        "machinery",
        "mechanical"
    ],
    "wof:name":"Promat International Nv",
    "wof:placetype":"venue"
},
  "geometry": {"coordinates":[4.3600797653,51.0191879272],"type":"Point"}
}