{
  "type": "Feature",
  "properties": {
    "iso:country":"BE",
    "sg:address":"Koning Albertlaan 9",
    "sg:city":"Neerpelt",
    "sg:classifiers":[
        {
            "category":"Insurance",
            "subcategory":"Insurance Agent",
            "type":"Services"
        }
    ],
    "sg:phone":"+32 11 64 12 04",
    "sg:postcode":"3910",
    "sg:province":"Limburg",
    "sg:tags":[
        "broker"
    ],
    "wof:name":"Mortelmans Verzekeringen",
    "wof:placetype":"venue"
},
  "geometry": {"coordinates":[5.4315428734,51.2268409729],"type":"Point"}
}