{
  "type": "Feature",
  "properties": {
    "iso:country":"BE",
    "sg:address":"Bethani\u00cbnlei 34",
    "sg:city":"Zoersel",
    "sg:orig_category":"Entretien and r\u00e9parations de voitures",
    "sg:phone":"+32 3 383 15 41",
    "sg:postcode":"2980",
    "sg:province":"Antwerpen",
    "wof:name":"Garage Willems",
    "wof:placetype":"venue"
},
  "geometry": {"coordinates":[4.6349020004,51.2737350464],"type":"Point"}
}