{
  "type": "Feature",
  "properties": {
    "addr:full":"Vliegwezenlaan 70 Asse (zellik) Vlaams-Brabant 1731",
    "addr:housenumber":"70",
    "addr:postcode":"1731",
    "addr:street":"Vliegwezenlaan",
    "iso:country":"BE",
    "sg:address":"Vliegwezenlaan 70",
    "sg:city":"Asse (zellik)",
    "sg:classifiers":[
        {
            "category":"Social Services",
            "subcategory":"Job Training",
            "type":"Services"
        }
    ],
    "sg:phone":"+32 2 456 83 45",
    "sg:postcode":"1731",
    "sg:province":"Vlaams-Brabant",
    "sg:tags":[
        "personnel",
        "-selection",
        "recruitment"
    ],
    "wof:name":"Automotive Consult",
    "wof:placetype":"venue"
},
  "geometry": {"coordinates":[4.276263237,50.8905525208],"type":"Point"}
}