{
  "type": "Feature",
  "properties": {
    "addr:full":"Rue Du Marechal De Saxe 50 Antoing Hainaut 7643",
    "addr:housenumber":"50",
    "addr:postcode":"7643",
    "addr:street":"Rue Du Marechal De Saxe",
    "iso:country":"BE",
    "sg:address":"Rue Du Marechal De Saxe 50",
    "sg:city":"Antoing",
    "sg:orig_category":"Kapsalons",
    "sg:phone":"+32 69 44 13 82",
    "sg:postcode":"7643",
    "sg:province":"Hainaut",
    "wof:name":"Coiffure Jacqueline",
    "wof:placetype":"venue"
},
  "geometry": {"coordinates":[3.467236042,50.5668411255],"type":"Point"}
}