{
  "type": "Feature",
  "properties": {
    "iso:country":"BE",
    "sg:address":"Valmeerstraat 122",
    "sg:city":"Riemst",
    "sg:orig_category":"Eleveurs de bovins",
    "sg:phone":"+32 12 45 54 57",
    "sg:postcode":"3770",
    "sg:province":"Limburg",
    "wof:name":"Arnaud Jackers",
    "wof:placetype":"venue"
},
  "geometry": {"coordinates":[5.581949234,50.7963943481],"type":"Point"}
}