{
  "type": "Feature",
  "properties": {
    "iso:country":"BE",
    "sg:address":"Kerkhofblommenstraat 50",
    "sg:city":"Staden",
    "sg:orig_category":"Varkenskwekers",
    "sg:phone":"+32 51 70 11 71",
    "sg:postcode":"8840",
    "sg:province":"West-Vlaanderen",
    "wof:name":"Willy Boone",
    "wof:placetype":"venue"
},
  "geometry": {"coordinates":[3.0299110413,50.9699058533],"type":"Point"}
}