{
  "type": "Feature",
  "properties": {
    "iso:country":"BE",
    "sg:address":"Zogsebaan 19",
    "sg:city":"Dendermonde (grembergen)",
    "sg:classifiers":[
        {
            "category":"Utilities",
            "subcategory":"Cable",
            "type":"Services"
        }
    ],
    "sg:phone":"+32 52 21 65 75",
    "sg:postcode":"9200",
    "sg:province":"Oost-Vlaanderen",
    "sg:tags":[
        "rope",
        "twine"
    ],
    "wof:name":"Intercord Nv",
    "wof:placetype":"venue"
},
  "geometry": {"coordinates":[4.1070947647,51.0643730164],"type":"Point"}
}