{
  "type": "Feature",
  "properties": {
    "iso:country":"BE",
    "sg:address":"Groenstraat 19",
    "sg:city":"Hechtel-eksel",
    "sg:orig_category":"Services de publipostage",
    "sg:phone":"+32 11 73 46 11",
    "sg:postcode":"3941",
    "sg:province":"Limburg",
    "wof:name":"Postverzending",
    "wof:placetype":"venue"
},
  "geometry": {"coordinates":[5.3927140236,51.1555023193],"type":"Point"}
}