{
  "type": "Feature",
  "properties": {
    "iso:country":"BE",
    "sg:address":"Wortegemstraat 33",
    "sg:city":"Oudenaarde",
    "sg:classifiers":[
        {
            "category":"Professional",
            "subcategory":"Management & Consulting",
            "type":"Services"
        }
    ],
    "sg:phone":"+32 55 31 99 05",
    "sg:postcode":"9700",
    "sg:province":"Oost-Vlaanderen",
    "sg:tags":[
        "consultant"
    ],
    "wof:name":"B&b Solutions Bvba",
    "wof:placetype":"venue"
},
  "geometry": {"coordinates":[3.593503952,50.8521614075],"type":"Point"}
}