{
  "type": "Feature",
  "properties": {
    "addr:full":"Landbouwstraat 2 Hamme Oost-Vlaanderen 9220",
    "addr:housenumber":"2",
    "addr:postcode":"9220",
    "addr:street":"Landbouwstraat",
    "iso:country":"BE",
    "sg:address":"Landbouwstraat 2",
    "sg:city":"Hamme",
    "sg:orig_category":"Kapsalons",
    "sg:phone":"+32 52 47 99 27",
    "sg:postcode":"9220",
    "sg:province":"Oost-Vlaanderen",
    "wof:name":"Martine Cool",
    "wof:placetype":"venue"
},
  "geometry": {"coordinates":[4.1474881172,51.0912017822],"type":"Point"}
}