{
  "type": "Feature",
  "properties": {
    "iso:country":"BE",
    "sg:address":"Canadalaan 39",
    "sg:city":"Nieuwpoort",
    "sg:orig_category":"Sociale huisvestingsmaatschappijen",
    "sg:phone":"+32 58 23 40 18",
    "sg:postcode":"8620",
    "sg:province":"West-Vlaanderen",
    "wof:name":"Nieuwpoortse Volkswoning",
    "wof:placetype":"venue"
},
  "geometry": {"coordinates":[2.7407460213,51.1289787292],"type":"Point"}
}