{
  "type": "Feature",
  "properties": {
    "iso:country":"BE",
    "sg:address":"Sint-annastraat 3",
    "sg:city":"Lummen",
    "sg:orig_category":"Travaux de pl\u00e2trage",
    "sg:phone":"+32 13 33 68 82",
    "sg:postcode":"3560",
    "sg:province":"Limburg",
    "wof:name":"Ludo Gijbels",
    "wof:placetype":"venue"
},
  "geometry": {"coordinates":[5.1526231766,50.9942054749],"type":"Point"}
}