{
  "type": "Feature",
  "properties": {
    "iso:country":"BE",
    "sg:address":"Alfred Amelotstraat 28",
    "sg:city":"Zingem",
    "sg:classifiers":[
        {
            "category":"Cafe",
            "type":"Food & Drink"
        }
    ],
    "sg:phone":"+32 9 384 16 61",
    "sg:postcode":"9750",
    "sg:province":"Oost-Vlaanderen",
    "sg:tags":[
        "caf\u00e9s"
    ],
    "wof:name":"Caf\u00c9 Ons Tehuis",
    "wof:placetype":"venue"
},
  "geometry": {"coordinates":[3.6530909538,50.9051971436],"type":"Point"}
}