{
  "type": "Feature",
  "properties": {
    "iso:country":"BE",
    "sg:address":"Place Des Martyrs 2",
    "sg:city":"Mons",
    "sg:classifiers":[
        {
            "category":"Bars & Pubs",
            "type":"Food & Drink"
        }
    ],
    "sg:phone":"+32 65 34 62 44",
    "sg:postcode":"7000",
    "sg:province":"Hainaut",
    "wof:name":"Bertaimont (le)",
    "wof:placetype":"venue"
},
  "geometry": {"coordinates":[3.9494431019,50.4495887756],"type":"Point"}
}