{
  "type": "Feature",
  "properties": {
    "addr:full":"Boulevard Du Nord 44 Namur Namur 5000",
    "addr:housenumber":"44",
    "addr:postcode":"5000",
    "addr:street":"Boulevard Du Nord",
    "iso:country":"BE",
    "sg:address":"Boulevard Du Nord 44",
    "sg:city":"Namur",
    "sg:classifiers":[
        {
            "category":"Home & Garden",
            "subcategory":"Household Appliances",
            "type":"Retail Goods"
        }
    ],
    "sg:phone":"+32 81 22 02 53",
    "sg:postcode":"5000",
    "sg:province":"Namur",
    "sg:tags":[
        "repair",
        "stove",
        "-"
    ],
    "wof:name":"N E C Sc-ansotte Nouveau Ets",
    "wof:placetype":"venue"
},
  "geometry": {"coordinates":[4.865249157,50.4702415466],"type":"Point"}
}