{
  "type": "Feature",
  "properties": {
    "iso:country":"BE",
    "sg:address":"Avenue De La Rochette 4",
    "sg:city":"Chaudfontaine",
    "sg:classifiers":[
        {
            "category":"Manufacturing",
            "subcategory":"Metals",
            "type":"Manufacturing & Wholesale Goods"
        }
    ],
    "sg:phone":"+32 4 365 12 42",
    "sg:postcode":"4050",
    "sg:province":"Li\u00e8ge",
    "sg:tags":[
        "treatment",
        "surface"
    ],
    "wof:name":"Galvanoplastie-m.gilson",
    "wof:placetype":"venue"
},
  "geometry": {"coordinates":[5.6572351456,50.5828285217],"type":"Point"}
}