{
  "type": "Feature",
  "properties": {
    "iso:country":"BE",
    "sg:address":"Village 3",
    "sg:city":"Stoumont",
    "sg:classifiers":[
        {
            "category":"Retail",
            "subcategory":"Veterinary Services",
            "type":"Services"
        }
    ],
    "sg:phone":"+32 80 51 15 55",
    "sg:postcode":"4987",
    "sg:province":"Li\u00e8ge",
    "sg:tags":[
        "veterinarian"
    ],
    "wof:name":"Dester A",
    "wof:placetype":"venue"
},
  "geometry": {"coordinates":[5.8087267876,50.4057540894],"type":"Point"}
}