{
  "type": "Feature",
  "properties": {
    "addr:full":"Meentakstraat 2h Meulebeke West-Vlaanderen 8760",
    "addr:housenumber":"2h",
    "addr:postcode":"8760",
    "addr:street":"Meentakstraat",
    "iso:country":"BE",
    "sg:address":"Meentakstraat 2h",
    "sg:city":"Meulebeke",
    "sg:classifiers":[
        {
            "category":"Shopping",
            "subcategory":"Antiques",
            "type":"Retail Goods"
        }
    ],
    "sg:phone":"+32 51 48 88 82",
    "sg:postcode":"8760",
    "sg:province":"West-Vlaanderen",
    "sg:tags":[
        "restoration"
    ],
    "wof:name":"E.d. Meubelatelier",
    "wof:placetype":"venue"
},
  "geometry": {"coordinates":[3.2999830246,50.9577102661],"type":"Point"}
}