{
  "type": "Feature",
  "properties": {
    "addr:full":"Chauss\u00c9e De Namur 303 Eghezee Namur 5310",
    "addr:housenumber":"303",
    "addr:postcode":"5310",
    "addr:street":"Chausse\u0301E De Namur;Namur",
    "iso:country":"BE",
    "sg:address":"Chauss\u00c9e De Namur 303",
    "sg:city":"Eghezee",
    "sg:orig_category":"Installation de menuiserie en bois and plastique. Vitrage. Installation de serres, double vitrage an",
    "sg:phone":"+32 81 51 21 02",
    "sg:postcode":"5310",
    "sg:province":"Namur",
    "wof:name":"Ramisol",
    "wof:placetype":"venue"
},
  "geometry": {"coordinates":[4.9103899002,50.5753898621],"type":"Point"}
}