{
  "type": "Feature",
  "properties": {
    "iso:country":"BE",
    "sg:address":"Rue Masui 96",
    "sg:city":"Bruxelles",
    "sg:classifiers":[
        {
            "category":"Wholesale",
            "subcategory":"Wine & Distilled Alcoholic Beverages",
            "type":"Manufacturing & Wholesale Goods"
        }
    ],
    "sg:phone":"+32 2 203 42 00",
    "sg:postcode":"1000",
    "sg:province":"Bruxelles-Capitale",
    "sg:tags":[
        "whol",
        "-",
        "spirit",
        "mfg"
    ],
    "wof:name":"Greco Products",
    "wof:placetype":"venue"
},
  "geometry": {"coordinates":[4.3589701653,50.8671722412],"type":"Point"}
}