{
  "type": "Feature",
  "properties": {
    "iso:country":"BE",
    "sg:address":"Korenmarkt 42",
    "sg:city":"Mechelen",
    "sg:orig_category":"M\u00e9decins and sp\u00e9cialistes",
    "sg:phone":"+32 15 43 27 66",
    "sg:postcode":"2800",
    "sg:province":"Antwerpen",
    "wof:name":"W. Storms",
    "wof:placetype":"venue"
},
  "geometry": {"coordinates":[4.4753928185,51.0240631104],"type":"Point"}
}