{
  "type": "Feature",
  "properties": {
    "iso:country":"BE",
    "sg:address":"Treft 68a",
    "sg:city":"Grimbergen (strombeek-bever)",
    "sg:classifiers":[
        {
            "category":"Utilities",
            "subcategory":"Water",
            "type":"Services"
        }
    ],
    "sg:phone":"+32 2 460 22 88",
    "sg:postcode":"1853",
    "sg:province":"Vlaams-Brabant",
    "sg:tags":[
        "purification"
    ],
    "wof:name":"Ronoh Sa",
    "wof:placetype":"venue"
},
  "geometry": {"coordinates":[4.3371472359,50.9056015015],"type":"Point"}
}