{
  "type": "Feature",
  "properties": {
    "addr:full":"Rue Olivier Gille 69 Chatelet Hainaut 6200",
    "addr:housenumber":"69",
    "addr:postcode":"6200",
    "addr:street":"Rue Olivier Gille;Hainaut",
    "iso:country":"BE",
    "sg:address":"Rue Olivier Gille 69",
    "sg:city":"Chatelet",
    "sg:orig_category":"R\u00e9parations d'horloges, montres and bijoux. Bijoux Fab. Bijouteries and horlogeries",
    "sg:phone":"+32 71 39 09 59",
    "sg:postcode":"6200",
    "sg:province":"Hainaut",
    "wof:name":"Christian Jouret",
    "wof:placetype":"venue"
},
  "geometry": {"coordinates":[4.5332360268,50.4017868042],"type":"Point"}
}