{
  "type": "Feature",
  "properties": {
    "addr:full":"Quai Des Usines 12 Ath Hainaut 7800",
    "addr:housenumber":"12",
    "addr:postcode":"7800",
    "addr:street":"Quai Des Usines",
    "iso:country":"BE",
    "sg:address":"Quai Des Usines 12",
    "sg:city":"Ath",
    "sg:orig_category":"Chemicali\u00ebn Gh",
    "sg:phone":"+32 68 28 19 12",
    "sg:postcode":"7800",
    "sg:province":"Hainaut",
    "wof:name":"Floridienne Chimie",
    "wof:placetype":"venue"
},
  "geometry": {"coordinates":[3.7723009586,50.6299858093],"type":"Point"}
}