{
  "type": "Feature",
  "properties": {
    "addr:full":"Brugstaat 14 Asse (grand) Vlaams-Brabant 1730",
    "addr:housenumber":"14",
    "addr:postcode":"1730",
    "addr:street":"Brugstaat",
    "iso:country":"BE",
    "sg:address":"Brugstaat 14",
    "sg:city":"Asse (grand)",
    "sg:orig_category":"Kapsalons",
    "sg:phone":"+32 2 425 82 75",
    "sg:postcode":"1730",
    "sg:province":"Vlaams-Brabant",
    "wof:name":"Sandra",
    "wof:placetype":"venue"
},
  "geometry": {"coordinates":[4.1986222267,50.9108505249],"type":"Point"}
}