{
  "type": "Feature",
  "properties": {
    "addr:full":"Dorpsstraat 125 Overpelt Limburg 3900",
    "addr:housenumber":"125",
    "addr:postcode":"3900",
    "addr:street":"Dorpsstraat",
    "iso:country":"BE",
    "sg:address":"Dorpsstraat 125",
    "sg:city":"Overpelt",
    "sg:orig_category":"Equipement photographique. Studios photographiques",
    "sg:phone":"+32 11 64 22 13",
    "sg:postcode":"3900",
    "sg:province":"Limburg",
    "wof:name":"Foto Studio Witters",
    "wof:placetype":"venue"
},
  "geometry": {"coordinates":[5.4184398651,51.209022522],"type":"Point"}
}