{
  "type": "Feature",
  "properties": {
    "addr:full":"Dorp-schellebelle 24 Wichelen Oost-Vlaanderen 9260",
    "addr:housenumber":"24",
    "addr:postcode":"9260",
    "addr:street":"Dorp-Schellebelle",
    "iso:country":"BE",
    "sg:address":"Dorp-schellebelle 24",
    "sg:city":"Wichelen",
    "sg:classifiers":[
        {
            "category":"Cafe",
            "type":"Food & Drink"
        }
    ],
    "sg:phone":"+32 9 366 32 63",
    "sg:postcode":"9260",
    "sg:province":"Oost-Vlaanderen",
    "sg:tags":[
        "caf\u00e9s"
    ],
    "wof:name":"Caf\u00c9 't Steksken",
    "wof:placetype":"venue"
},
  "geometry": {"coordinates":[3.9743049145,51.0067749023],"type":"Point"}
}