{
  "type": "Feature",
  "properties": {
    "addr:full":"Westendelaan 6 Middelkerke West-Vlaanderen 8430",
    "addr:housenumber":"6",
    "addr:postcode":"8430",
    "addr:street":"Westendelaan",
    "iso:country":"BE",
    "sg:address":"Westendelaan 6",
    "sg:city":"Middelkerke",
    "sg:orig_category":"Messageries. Clubs de sport",
    "sg:phone":"+32 59 30 02 43",
    "sg:postcode":"8430",
    "sg:province":"West-Vlaanderen",
    "wof:name":"Ostend Parcel Service",
    "wof:placetype":"venue"
},
  "geometry": {"coordinates":[2.8198549747,51.1847877502],"type":"Point"}
}