{
  "type": "Feature",
  "properties": {
    "addr:full":"Avenue Edouard Lacombl\u00c9 17 Etterbeek Bruxelles-Capitale 1040",
    "addr:housenumber":"17",
    "addr:postcode":"1040",
    "addr:street":"Avenue Edouard Lacomble\u0301",
    "iso:country":"BE",
    "sg:address":"Avenue Edouard Lacombl\u00c9 17",
    "sg:city":"Etterbeek",
    "sg:orig_category":"Boekhouders",
    "sg:phone":"+32 2 733 67 84",
    "sg:postcode":"1040",
    "sg:province":"Bruxelles-Capitale",
    "wof:name":"Hottois Claire",
    "wof:placetype":"venue"
},
  "geometry": {"coordinates":[4.4092960358,50.8325843811],"type":"Point"}
}