{
  "type": "Feature",
  "properties": {
    "iso:country":"BE",
    "sg:address":"Bieshof 2",
    "sg:city":"Hoogstraten (meer)",
    "sg:classifiers":[
        {
            "category":"Building & Trades",
            "subcategory":"Landscaping Services",
            "type":"Services"
        }
    ],
    "sg:phone":"+32 3 315 12 06",
    "sg:postcode":"2321",
    "sg:province":"Antwerpen",
    "sg:tags":[
        "gardening",
        "garden",
        "maintenance"
    ],
    "wof:name":"Delcourt Tuinarchitectuur",
    "wof:placetype":"venue"
},
  "geometry": {"coordinates":[4.7320761681,51.4705314636],"type":"Point"}
}