{
  "type": "Feature",
  "properties": {
    "addr:full":"Dorpstraat 48 Huldenberg Vlaams-Brabant 3040",
    "addr:housenumber":"48",
    "addr:postcode":"3040",
    "addr:street":"Dorpstraat",
    "iso:country":"BE",
    "sg:address":"Dorpstraat 48",
    "sg:city":"Huldenberg",
    "sg:orig_category":"Enseignement maternel and primaire",
    "sg:phone":"+32 16 47 74 97",
    "sg:postcode":"3040",
    "sg:province":"Vlaams-Brabant",
    "wof:name":"Vrije Basisschool",
    "wof:placetype":"venue"
},
  "geometry": {"coordinates":[4.6243958473,50.8178749084],"type":"Point"}
}