{
  "type": "Feature",
  "properties": {
    "addr:full":"Dorpsstraat 49 Damme West-Vlaanderen 8340",
    "addr:housenumber":"49",
    "addr:postcode":"8340",
    "addr:street":"Dorpsstraat",
    "iso:country":"BE",
    "sg:address":"Dorpsstraat 49",
    "sg:city":"Damme",
    "sg:classifiers":[
        {
            "category":"Shopping",
            "subcategory":"Clothing, Apparel, & Fashions",
            "type":"Retail Goods"
        }
    ],
    "sg:phone":"+32 50 35 52 79",
    "sg:postcode":"8340",
    "sg:province":"West-Vlaanderen",
    "sg:tags":[
        "ondergoed",
        "lingerie"
    ],
    "wof:name":"Huis Kathy",
    "wof:placetype":"venue"
},
  "geometry": {"coordinates":[3.3275060654,51.2016334534],"type":"Point"}
}