{
  "type": "Feature",
  "properties": {
    "iso:country":"BE",
    "sg:address":"Avenue Armand Huysmans 20",
    "sg:city":"Elsene/ixelles",
    "sg:orig_category":"Administration d'immeubles. Agences immobili\u00e8res. Evaluation and estimation de biens immobiliers",
    "sg:phone":"+32 2 640 85 31",
    "sg:postcode":"1050",
    "sg:province":"Bruxelles-Capitale",
    "wof:name":"Eurog\u00c9rance",
    "wof:placetype":"venue"
},
  "geometry": {"coordinates":[4.3846478462,50.8151359558],"type":"Point"}
}