{
  "type": "Feature",
  "properties": {
    "addr:full":"Bevrijdingslaan 8 Gent Oost-Vlaanderen 9000",
    "addr:housenumber":"8",
    "addr:postcode":"9000",
    "addr:street":"Bevrijdingslaan;Oost-Vlaanderen",
    "iso:country":"BE",
    "sg:address":"Bevrijdingslaan 8",
    "sg:city":"Gent",
    "sg:orig_category":"Medische and orthopedische apparaten Opticiens",
    "sg:phone":"+32 9 226 85 74",
    "sg:postcode":"9000",
    "sg:province":"Oost-Vlaanderen",
    "wof:name":"Huis Cheyns",
    "wof:placetype":"venue"
},
  "geometry": {"coordinates":[3.6973121166,51.0631752014],"type":"Point"}
}