{
  "type": "Feature",
  "properties": {
    "iso:country":"BE",
    "sg:address":"Boulevard Sylvain Dupuis 315",
    "sg:city":"Anderlecht",
    "sg:orig_category":"Jeux and jouets",
    "sg:phone":"+32 2 523 84 73",
    "sg:postcode":"1070",
    "sg:province":"Bruxelles-Capitale",
    "wof:name":"Christiaensen",
    "wof:placetype":"venue"
},
  "geometry": {"coordinates":[4.2888298035,50.8378486633],"type":"Point"}
}