{
  "type": "Feature",
  "properties": {
    "addr:full":"Seestrasse 7-16 B\u00fctgenbach Li\u00e8ge 4750",
    "addr:housenumber":"7-16",
    "addr:postcode":"4750",
    "addr:street":"Seestrasse",
    "iso:country":"BE",
    "sg:address":"Seestrasse 7-16",
    "sg:city":"B\u00fctgenbach",
    "sg:classifiers":[
        {
            "category":"Home & Garden",
            "subcategory":"Home Furnishings",
            "type":"Retail Goods"
        }
    ],
    "sg:phone":"+32 80 44 50 51",
    "sg:postcode":"4750",
    "sg:province":"Li\u00e8ge",
    "sg:tags":[
        "-",
        "furniture"
    ],
    "wof:name":"Heck Halmes Gmbh Sprl",
    "wof:placetype":"venue"
},
  "geometry": {"coordinates":[6.2069220543,50.4258003235],"type":"Point"}
}