{
  "type": "Feature",
  "properties": {
    "iso:country":"BE",
    "sg:address":"Ossenbroeck 5",
    "sg:city":"Lede",
    "sg:orig_category":"Groententeelt",
    "sg:phone":"+32 9 369 40 87",
    "sg:postcode":"9340",
    "sg:province":"Oost-Vlaanderen",
    "wof:name":"Filip Tavernier",
    "wof:placetype":"venue"
},
  "geometry": {"coordinates":[3.8750200272,50.9592933655],"type":"Point"}
}