{
  "type": "Feature",
  "properties": {
    "addr:full":"Lod. Van Velthemstraat 2 Roeselare West-Vlaanderen 8800",
    "addr:housenumber":"2",
    "addr:postcode":"8800",
    "addr:street":"Lod. Van Velthemstraat",
    "iso:country":"BE",
    "sg:address":"Lod. Van Velthemstraat 2",
    "sg:city":"Roeselare",
    "sg:orig_category":"R\u00e9cup\u00e9ration de mati\u00e8res m\u00e9talliques recyclables and d\u00e9molisseurs de voitures",
    "sg:phone":"+32 51 24 06 98",
    "sg:postcode":"8800",
    "sg:province":"West-Vlaanderen",
    "wof:name":"Fa. Westauto's",
    "wof:placetype":"venue"
},
  "geometry": {"coordinates":[3.133671999,50.965877533],"type":"Point"}
}