{
  "type": "Feature",
  "properties": {
    "addr:full":"Chauss\u00c9e De La Hulpe 51-53 Ukkel/uccle Bruxelles-Capitale 1180",
    "addr:housenumber":"51-53",
    "addr:postcode":"1180",
    "addr:street":"Chausse\u0301E De La Hulpe;/",
    "iso:country":"BE",
    "sg:address":"Chauss\u00c9e De La Hulpe 51-53",
    "sg:city":"Ukkel/uccle",
    "sg:orig_category":"Services divers aux entreprises. Salles de conf\u00e9rences and de r\u00e9ceptions",
    "sg:phone":"+32 2 660 87 38",
    "sg:postcode":"1180",
    "sg:province":"Bruxelles-Capitale",
    "wof:name":"Hippodream",
    "wof:placetype":"venue"
},
  "geometry": {"coordinates":[4.3973522186,50.7966651917],"type":"Point"}
}