{
  "type": "Feature",
  "properties": {
    "addr:full":"Balleistraat 57 Affligem (teralfene) Vlaams-Brabant 1790",
    "addr:housenumber":"57",
    "addr:postcode":"1790",
    "addr:street":"Balleistraat",
    "iso:country":"BE",
    "sg:address":"Balleistraat 57",
    "sg:city":"Affligem (teralfene)",
    "sg:classifiers":[
        {
            "category":"Professional",
            "subcategory":"Employment Agencies",
            "type":"Services"
        }
    ],
    "sg:phone":"+32 53 66 78 50",
    "sg:postcode":"1790",
    "sg:province":"Vlaams-Brabant",
    "sg:tags":[
        "market",
        "research"
    ],
    "wof:name":"Ravian",
    "wof:placetype":"venue"
},
  "geometry": {"coordinates":[4.0948271751,50.8996963501],"type":"Point"}
}