{
  "type": "Feature",
  "properties": {
    "iso:country":"BE",
    "sg:address":"Rue Africaine 96",
    "sg:city":"Bruxelles (saint-gilles)",
    "sg:classifiers":[
        {
            "category":"Health Services",
            "subcategory":"Doctor",
            "type":"Services"
        }
    ],
    "sg:phone":"+32 2 539 21 06",
    "sg:postcode":"1060",
    "sg:province":"Bruxelles-Capitale",
    "sg:tags":[
        "medicinephysicians",
        "surgeon"
    ],
    "wof:name":"Grassart A",
    "wof:placetype":"venue"
},
  "geometry": {"coordinates":[4.3575921059,50.8251876831],"type":"Point"}
}