{
  "type": "Feature",
  "properties": {
    "iso:country":"BE",
    "sg:address":"Kouter 65",
    "sg:city":"Mechelen (leest)",
    "sg:classifiers":[
        {
            "category":"Building & Trades",
            "subcategory":"Landscaping Services",
            "type":"Services"
        }
    ],
    "sg:phone":"+32 15 34 30 63",
    "sg:postcode":"2811",
    "sg:province":"Antwerpen",
    "sg:tags":[
        "gardening",
        "garden",
        "maintenance"
    ],
    "wof:name":"Tavernier M",
    "wof:placetype":"venue"
},
  "geometry": {"coordinates":[4.4257278442,51.0250434875],"type":"Point"}
}