{
  "type": "Feature",
  "properties": {
    "addr:full":"Ekkersputstraat 20 Zonhoven Limburg 3520",
    "addr:housenumber":"20",
    "addr:postcode":"3520",
    "addr:street":"Ekkersputstraat",
    "iso:country":"BE",
    "sg:address":"Ekkersputstraat 20",
    "sg:city":"Zonhoven",
    "sg:orig_category":"Travaux de pl\u00e2trage",
    "sg:phone":"+32 11 81 79 33",
    "sg:postcode":"3520",
    "sg:province":"Limburg",
    "wof:name":"R. Swennen",
    "wof:placetype":"venue"
},
  "geometry": {"coordinates":[5.3575701714,50.9972419739],"type":"Point"}
}