{
  "type": "Feature",
  "properties": {
    "addr:full":"Place Joseph Meunier 27 Mettet Namur 5640",
    "addr:housenumber":"27",
    "addr:postcode":"5640",
    "addr:street":"Place Joseph Meunier",
    "iso:country":"BE",
    "sg:address":"Place Joseph Meunier 27",
    "sg:city":"Mettet",
    "sg:classifiers":[
        {
            "category":"Health Services",
            "subcategory":"Dentist",
            "type":"Services"
        }
    ],
    "sg:phone":"+32 71 72 83 07",
    "sg:postcode":"5640",
    "sg:province":"Namur",
    "wof:name":"Massaux Jacqueline",
    "wof:placetype":"venue"
},
  "geometry": {"coordinates":[4.6579751968,50.3198051453],"type":"Point"}
}