{
  "type": "Feature",
  "properties": {
    "iso:country":"BE",
    "sg:address":"Rue De Bruxelles 4",
    "sg:city":"Wavre",
    "sg:classifiers":[
        {
            "category":"Food & Beverages",
            "subcategory":"Specialty",
            "type":"Retail Goods"
        }
    ],
    "sg:phone":"+32 10 86 76 00",
    "sg:postcode":"1300",
    "sg:province":"Brabant Wallon",
    "sg:tags":[
        "health",
        "dietary",
        "-",
        "biological"
    ],
    "wof:name":"Ferme A (a La)",
    "wof:placetype":"venue"
},
  "geometry": {"coordinates":[4.6106128693,50.717414856],"type":"Point"}
}