{
  "type": "Feature",
  "properties": {
    "iso:country":"BE",
    "sg:address":"Bleidenhoek 3bb",
    "sg:city":"Duffel",
    "sg:orig_category":"Groententeelt",
    "sg:phone":"+32 15 31 46 45",
    "sg:postcode":"2570",
    "sg:province":"Antwerpen",
    "wof:name":"Leo Celis",
    "wof:placetype":"venue"
},
  "geometry": {"coordinates":[4.5603508949,51.09167099],"type":"Point"}
}