{
  "type": "Feature",
  "properties": {
    "addr:full":"Meuleschettestraat 32 Aalst Oost-Vlaanderen 9300",
    "addr:housenumber":"32",
    "addr:postcode":"9300",
    "addr:street":"Meuleschettestraat",
    "iso:country":"BE",
    "sg:address":"Meuleschettestraat 32",
    "sg:city":"Aalst",
    "sg:orig_category":"M\u00e9decins and sp\u00e9cialistes",
    "sg:phone":"+32 53 21 59 50",
    "sg:postcode":"9300",
    "sg:province":"Oost-Vlaanderen",
    "wof:name":"Consultatiebur.jonge Kind",
    "wof:placetype":"venue"
},
  "geometry": {"coordinates":[4.0303201675,50.9413604736],"type":"Point"}
}