{
  "type": "Feature",
  "properties": {
    "addr:full":"Rue Grand\u00b4route 268 Beyne-heusay Li\u00e8ge 4610",
    "addr:housenumber":"268",
    "addr:postcode":"4610",
    "addr:street":"Rue Grand\u00b4Route",
    "iso:country":"BE",
    "sg:address":"Rue Grand\u00b4route 268",
    "sg:city":"Beyne-heusay",
    "sg:orig_category":"Benzinestations and brandstoffen Herstellingen and onderhoud van auto's",
    "sg:phone":"+32 4 358 13 94",
    "sg:postcode":"4610",
    "sg:province":"Li\u00e8ge",
    "wof:name":"Q8",
    "wof:placetype":"venue"
},
  "geometry": {"coordinates":[5.6528830528,50.6225547791],"type":"Point"}
}