{
  "type": "Feature",
  "properties": {
    "addr:full":"Kloosterstraat 48 Lommel Limburg 3920",
    "addr:housenumber":"48",
    "addr:postcode":"3920",
    "addr:street":"Kloosterstraat",
    "iso:country":"BE",
    "sg:address":"Kloosterstraat 48",
    "sg:city":"Lommel",
    "sg:classifiers":[
        {
            "category":"Health Services",
            "subcategory":"Doctor",
            "type":"Services"
        }
    ],
    "sg:phone":"+32 11 55 28 52",
    "sg:postcode":"3920",
    "sg:province":"Limburg",
    "sg:tags":[
        "medicinephysicians",
        "surgeon"
    ],
    "wof:name":"Linsen Christel",
    "wof:placetype":"venue"
},
  "geometry": {"coordinates":[5.3162608147,51.2300987244],"type":"Point"}
}