{
  "type": "Feature",
  "properties": {
    "addr:full":"Klaverbladstraat 17a Lummen Limburg 3560",
    "addr:housenumber":"17a",
    "addr:postcode":"3560",
    "addr:street":"Klaverbladstraat",
    "iso:country":"BE",
    "sg:address":"Klaverbladstraat 17a",
    "sg:city":"Lummen",
    "sg:classifiers":[
        {
            "category":"Retail",
            "subcategory":"Auto Repair",
            "type":"Services"
        }
    ],
    "sg:phone":"+32 495 57 55 88",
    "sg:postcode":"3560",
    "sg:province":"Limburg",
    "sg:tags":[
        "truck-body"
    ],
    "wof:name":"Rigo's Horse Trucks",
    "wof:placetype":"venue"
},
  "geometry": {"coordinates":[5.2290492058,50.9965515137],"type":"Point"}
}