{
  "type": "Feature",
  "properties": {
    "addr:full":"Rue Jules Empain 20 Manage Hainaut 7170",
    "addr:housenumber":"20",
    "addr:postcode":"7170",
    "addr:street":"Rue Jules Empain",
    "iso:country":"BE",
    "sg:address":"Rue Jules Empain 20",
    "sg:city":"Manage",
    "sg:orig_category":"Catering and organisation de f\u00eates",
    "sg:phone":"+32 64 55 56 95",
    "sg:postcode":"7170",
    "sg:province":"Hainaut",
    "wof:name":"Thierry Morel",
    "wof:placetype":"venue"
},
  "geometry": {"coordinates":[4.2291698456,50.4991989136],"type":"Point"}
}