{
  "type": "Feature",
  "properties": {
    "addr:full":"Oude Beurs 58 Antwerpen Antwerpen 2000",
    "addr:housenumber":"58",
    "addr:postcode":"2000",
    "addr:street":"Oude Beurs",
    "iso:country":"BE",
    "sg:address":"Oude Beurs 58",
    "sg:city":"Antwerpen",
    "sg:classifiers":[
        {
            "category":"Bars & Pubs",
            "type":"Food & Drink"
        }
    ],
    "sg:phone":"+32 3 288 66 82",
    "sg:postcode":"2000",
    "sg:province":"Antwerpen",
    "wof:name":"Fotocaf\u00e9",
    "wof:placetype":"venue"
},
  "geometry": {"coordinates":[4.402176857,51.2213821411],"type":"Point"}
}