{
  "type": "Feature",
  "properties": {
    "iso:country":"BE",
    "sg:address":"Hoornstraat 1",
    "sg:city":"Beernem",
    "sg:orig_category":"Drukkerijen and copyshops",
    "sg:phone":"+32 50 79 18 79",
    "sg:postcode":"8730",
    "sg:province":"West-Vlaanderen",
    "wof:name":"Drukkerij Harlekijn",
    "wof:placetype":"venue"
},
  "geometry": {"coordinates":[3.340790987,51.1428604126],"type":"Point"}
}