{
  "type": "Feature",
  "properties": {
    "iso:country":"BE",
    "sg:address":"Olmstraat 129",
    "sg:city":"Vilvoorde",
    "sg:classifiers":[
        {
            "category":"Cafe",
            "type":"Food & Drink"
        }
    ],
    "sg:phone":"+32 2 251 52 00",
    "sg:postcode":"1800",
    "sg:province":"Vlaams-Brabant",
    "sg:tags":[
        "caf\u00e9s"
    ],
    "wof:name":"Caramba",
    "wof:placetype":"venue"
},
  "geometry": {"coordinates":[4.4343791008,50.9307670593],"type":"Point"}
}