{
  "type": "Feature",
  "properties": {
    "addr:full":"Rue Du Couvent 50 Libin (transinne) Luxembourg 6890",
    "addr:housenumber":"50",
    "addr:postcode":"6890",
    "addr:street":"Rue Du Couvent",
    "iso:country":"BE",
    "sg:address":"Rue Du Couvent 50",
    "sg:city":"Libin (transinne)",
    "sg:classifiers":[
        {
            "category":"Travel",
            "subcategory":"Hotels & Motels",
            "type":"Entertainment"
        }
    ],
    "sg:phone":"+32 61 65 58 74",
    "sg:postcode":"6890",
    "sg:province":"Luxembourg",
    "wof:name":"Hostellerie Du Wezerin",
    "wof:placetype":"venue"
},
  "geometry": {"coordinates":[5.2562999725,49.9827537537],"type":"Point"}
}