{
  "type": "Feature",
  "properties": {
    "iso:country":"BE",
    "sg:address":"Avenue Prekelinden 21",
    "sg:city":"Sint-lambrechts-woluwe/woluwe-saint-lambert",
    "sg:orig_category":"Cr\u00e8ches and garderies d'enfants",
    "sg:phone":"+32 2 734 52 57",
    "sg:postcode":"1200",
    "sg:province":"Bruxelles-Capitale",
    "wof:name":"Cr\u00c8che Le Jardinet",
    "wof:placetype":"venue"
},
  "geometry": {"coordinates":[4.4104118347,50.8396377563],"type":"Point"}
}