{
  "type": "Feature",
  "properties": {
    "iso:country":"BE",
    "sg:address":"Nieuwe Heidestraat 111",
    "sg:city":"Hasselt",
    "sg:orig_category":"Non-Classified Establishments",
    "sg:phone":"+32 11 24 29 64",
    "sg:postcode":"3500",
    "sg:province":"Limburg",
    "wof:name":"Tojacom Bvba",
    "wof:placetype":"venue"
},
  "geometry": {"coordinates":[5.3837928772,50.9578552246],"type":"Point"}
}