{
  "type": "Feature",
  "properties": {
    "addr:full":"Venakker 21 Aalter Oost-Vlaanderen 9880",
    "addr:housenumber":"21",
    "addr:postcode":"9880",
    "addr:street":"Venakker",
    "iso:country":"BE",
    "sg:address":"Venakker 21",
    "sg:city":"Aalter",
    "sg:classifiers":[
        {
            "category":"Retail",
            "subcategory":"Animal Services",
            "type":"Services"
        }
    ],
    "sg:phone":"+32 9 375 04 40",
    "sg:postcode":"9880",
    "sg:province":"Oost-Vlaanderen",
    "sg:tags":[
        "grooming",
        "-",
        "dog"
    ],
    "wof:name":"Poquito",
    "wof:placetype":"venue"
},
  "geometry": {"coordinates":[3.4459490776,51.0958328247],"type":"Point"}
}