{
  "type": "Feature",
  "properties": {
    "iso:country":"BE",
    "sg:address":"Oud-dorpsstraat 38",
    "sg:city":"Wuustwezel",
    "sg:classifiers":[
        {
            "category":"Restaurant",
            "type":"Food & Drink"
        }
    ],
    "sg:phone":"+32 3 669 77 79",
    "sg:postcode":"2990",
    "sg:province":"Antwerpen",
    "wof:name":"'t Schalienhuis",
    "wof:placetype":"venue"
},
  "geometry": {"coordinates":[4.6413731575,51.4018745422],"type":"Point"}
}