{
  "type": "Feature",
  "properties": {
    "addr:full":"August Nihoulstraat 157 Scherpenheuvel-zichem Vlaams-Brabant 3270",
    "addr:housenumber":"157",
    "addr:postcode":"3270",
    "addr:street":"Nihoulstraat",
    "iso:country":"BE",
    "sg:address":"August Nihoulstraat 157",
    "sg:city":"Scherpenheuvel-zichem",
    "sg:orig_category":"Elektrische installaties voor woningen",
    "sg:phone":"+32 13 77 33 22",
    "sg:postcode":"3270",
    "sg:province":"Vlaams-Brabant",
    "wof:name":"Frans Isenborghs",
    "wof:placetype":"venue"
},
  "geometry": {"coordinates":[4.9711470604,50.9713020325],"type":"Point"}
}