{
  "type": "Feature",
  "properties": {
    "addr:full":"Rue Verte 24 Quevy Hainaut 7041",
    "addr:housenumber":"24",
    "addr:postcode":"7041",
    "addr:street":"Rue Verte;Hainaut",
    "iso:country":"BE",
    "sg:address":"Rue Verte 24",
    "sg:city":"Quevy",
    "sg:orig_category":"Eleveurs de bovins",
    "sg:phone":"+32 65 56 94 83",
    "sg:postcode":"7041",
    "sg:province":"Hainaut",
    "wof:name":"Maurice Dejardin",
    "wof:placetype":"venue"
},
  "geometry": {"coordinates":[3.9834198952,50.3583030701],"type":"Point"}
}