{
  "type": "Feature",
  "properties": {
    "addr:full":"Tuinstraat 17 Balen Antwerpen 2490",
    "addr:housenumber":"17",
    "addr:postcode":"2490",
    "addr:street":"Tuinstraat",
    "iso:country":"BE",
    "sg:address":"Tuinstraat 17",
    "sg:city":"Balen",
    "sg:orig_category":"Waterzuivering",
    "sg:phone":"+32 14 81 13 16",
    "sg:postcode":"2490",
    "sg:province":"Antwerpen",
    "wof:name":"B&d Systems",
    "wof:placetype":"venue"
},
  "geometry": {"coordinates":[5.2277917862,51.1860198975],"type":"Point"}
}