{
  "type": "Feature",
  "properties": {
    "addr:full":"Grote Leiestraat 62 Anzegem West-Vlaanderen 8570",
    "addr:housenumber":"62",
    "addr:postcode":"8570",
    "addr:street":"Grote Leiestraat",
    "iso:country":"BE",
    "sg:address":"Grote Leiestraat 62",
    "sg:city":"Anzegem",
    "sg:classifiers":[
        {
            "category":"Manufacturing",
            "subcategory":"Tobacco Products",
            "type":"Manufacturing & Wholesale Goods"
        }
    ],
    "sg:phone":"+32 56 68 80 06",
    "sg:postcode":"8570",
    "sg:province":"West-Vlaanderen",
    "sg:tags":[
        "fertilizer",
        "merchant",
        "-"
    ],
    "wof:name":"Van Houcke Nv",
    "wof:placetype":"venue"
},
  "geometry": {"coordinates":[3.4611020088,50.8539962769],"type":"Point"}
}