{
  "type": "Feature",
  "properties": {
    "addr:full":"Molenstraat 129 Eeklo Oost-Vlaanderen 9900",
    "addr:housenumber":"129",
    "addr:postcode":"9900",
    "addr:street":"Molenstraat",
    "iso:country":"BE",
    "sg:address":"Molenstraat 129",
    "sg:city":"Eeklo",
    "sg:orig_category":"M\u00e9decins and sp\u00e9cialistes",
    "sg:phone":"+32 9 377 90 77",
    "sg:postcode":"9900",
    "sg:province":"Oost-Vlaanderen",
    "wof:name":"Ingrid Berghman",
    "wof:placetype":"venue"
},
  "geometry": {"coordinates":[3.5594139099,51.1878585815],"type":"Point"}
}