{
  "type": "Feature",
  "properties": {
    "iso:country":"BE",
    "sg:address":"Boulevard Industriel 1a",
    "sg:city":"Comines-warneton (comines)",
    "sg:classifiers":[
        {
            "category":"Professional",
            "subcategory":"Accounting & Tax Preparation",
            "type":"Services"
        }
    ],
    "sg:phone":"+32 56 55 63 54",
    "sg:postcode":"7780",
    "sg:province":"Hainaut",
    "sg:tags":[
        "accountant"
    ],
    "wof:name":"Leclercq M",
    "wof:placetype":"venue"
},
  "geometry": {"coordinates":[3.0157558918,50.7767868042],"type":"Point"}
}