{
  "type": "Feature",
  "properties": {
    "addr:full":"Hulstraat 4 Hoeselt Limburg 3730",
    "addr:housenumber":"4",
    "addr:postcode":"3730",
    "addr:street":"Hulstraat",
    "iso:country":"BE",
    "sg:address":"Hulstraat 4",
    "sg:city":"Hoeselt",
    "sg:orig_category":"Maisons de repos and r\u00e9sidences",
    "sg:phone":"+32 89 41 11 84",
    "sg:postcode":"3730",
    "sg:province":"Limburg",
    "wof:name":"Rusthuis Ter Hulst",
    "wof:placetype":"venue"
},
  "geometry": {"coordinates":[5.4859747887,50.8512458801],"type":"Point"}
}