{
  "type": "Feature",
  "properties": {
    "addr:full":"Av. Gloires Nationales 126 Ganshoren Bruxelles-Capitale 1083",
    "addr:housenumber":"126",
    "addr:postcode":"1083",
    "addr:street":"Av. Gloires Nationales",
    "iso:country":"BE",
    "sg:address":"Av. Gloires Nationales 126",
    "sg:city":"Ganshoren",
    "sg:orig_category":"Enseignement maternel and primaire",
    "sg:phone":"+32 2 426 86 45",
    "sg:postcode":"1083",
    "sg:province":"Bruxelles-Capitale",
    "wof:name":"Vrije Basisschool",
    "wof:placetype":"venue"
},
  "geometry": {"coordinates":[4.31478405,50.8677787781],"type":"Point"}
}