{
  "type": "Feature",
  "properties": {
    "iso:country":"BE",
    "sg:address":"Nieuwedijk 37",
    "sg:city":"Dessel",
    "sg:orig_category":"Woningbouw",
    "sg:phone":"+32 14 37 31 16",
    "sg:postcode":"2480",
    "sg:province":"Antwerpen",
    "wof:name":"Alfons Dries",
    "wof:placetype":"venue"
},
  "geometry": {"coordinates":[5.1621098518,51.2345809937],"type":"Point"}
}