{
  "type": "Feature",
  "properties": {
    "addr:full":"Cesar Meeusstraat 8 Zele Oost-Vlaanderen 9240",
    "addr:housenumber":"8",
    "addr:postcode":"9240",
    "addr:street":"Meeusstraat",
    "iso:country":"BE",
    "sg:address":"Cesar Meeusstraat 8",
    "sg:city":"Zele",
    "sg:orig_category":"Apotheken",
    "sg:phone":"+32 52 44 40 07",
    "sg:postcode":"9240",
    "sg:province":"Oost-Vlaanderen",
    "wof:name":"Apoteek C Janssens",
    "wof:placetype":"venue"
},
  "geometry": {"coordinates":[4.0365462303,51.0675964355],"type":"Point"}
}