{
  "type": "Feature",
  "properties": {
    "addr:full":"Rue Gr\u00c9goire Chapuis 6 Seraing Li\u00e8ge 4100",
    "addr:housenumber":"6",
    "addr:postcode":"4100",
    "addr:street":"Rue Gre\u0301Goire Chapuis",
    "iso:country":"BE",
    "sg:address":"Rue Gr\u00c9goire Chapuis 6",
    "sg:city":"Seraing",
    "sg:classifiers":[
        {
            "category":"Shopping",
            "subcategory":"Clothing, Apparel, & Fashions",
            "type":"Retail Goods"
        }
    ],
    "sg:phone":"+32 4 337 53 29",
    "sg:postcode":"4100",
    "sg:province":"Li\u00e8ge",
    "sg:tags":[
        "v\u00eatements",
        "pour",
        "dame"
    ],
    "wof:name":"Mila Nikolic",
    "wof:placetype":"venue"
},
  "geometry": {"coordinates":[5.5112757683,50.5987014771],"type":"Point"}
}