{
  "type": "Feature",
  "properties": {
    "iso:country":"BE",
    "sg:address":"Desire De Bodtkaai 27",
    "sg:city":"Ninove",
    "sg:classifiers":[
        {
            "category":"Manufacturing",
            "subcategory":"Motor Vehicles & Parts",
            "type":"Manufacturing & Wholesale Goods"
        }
    ],
    "sg:phone":"+32 54 31 13 11",
    "sg:postcode":"9400",
    "sg:province":"Oost-Vlaanderen",
    "sg:tags":[
        "synthetic",
        "purely",
        "fibre"
    ],
    "wof:name":"Fabelta Ninove Nv",
    "wof:placetype":"venue"
},
  "geometry": {"coordinates":[4.0261058807,50.8339118958],"type":"Point"}
}