{
  "type": "Feature",
  "properties": {
    "addr:full":"Beukenlaan 74 Rotselaar Vlaams-Brabant 3110",
    "addr:housenumber":"74",
    "addr:postcode":"3110",
    "addr:street":"Beukenlaan",
    "iso:country":"BE",
    "sg:address":"Beukenlaan 74",
    "sg:city":"Rotselaar",
    "sg:classifiers":[
        {
            "category":"Education",
            "subcategory":"Dance Studio",
            "type":"Public Place"
        }
    ],
    "sg:phone":"+32 16 58 13 62",
    "sg:postcode":"3110",
    "sg:province":"Vlaams-Brabant",
    "sg:tags":[
        "ballet",
        "school"
    ],
    "wof:name":"Rainbow Ballet (the)",
    "wof:placetype":"venue"
},
  "geometry": {"coordinates":[4.7107920647,50.9508590698],"type":"Point"}
}