{
  "type": "Feature",
  "properties": {
    "iso:country":"BE",
    "sg:address":"Koning Albertstraat 99",
    "sg:city":"Diest",
    "sg:orig_category":"Epiceries",
    "sg:postcode":"3290",
    "sg:province":"Vlaams-Brabant",
    "wof:name":"Automatische Muurwinkel",
    "wof:placetype":"venue"
},
  "geometry": {"coordinates":[5.0557808876,50.9872093201],"type":"Point"}
}