{
  "type": "Feature",
  "properties": {
    "addr:full":"Grand Rue N\u00b0 7 Virton Luxembourg 6760",
    "addr:housenumber":"7",
    "addr:postcode":"6760",
    "addr:street":"Grand Rue N\u00b0",
    "iso:country":"BE",
    "sg:address":"Grand Rue N\u00b0 7",
    "sg:city":"Virton",
    "sg:classifiers":[
        {
            "category":"Banks & Credit Unions",
            "subcategory":"Financial Services",
            "type":"Services"
        }
    ],
    "sg:phone":"+32 63 57 74 48",
    "sg:postcode":"6760",
    "sg:province":"Luxembourg",
    "sg:tags":[
        "banking",
        "finance",
        "insurance"
    ],
    "wof:name":"Gaume Service Sc",
    "wof:placetype":"venue"
},
  "geometry": {"coordinates":[5.5347180367,49.5672607422],"type":"Point"}
}