{
  "type": "Feature",
  "properties": {
    "iso:country":"BE",
    "sg:address":"Rue De La Ridale 5",
    "sg:city":"La Bruyere",
    "sg:orig_category":"Notaires",
    "sg:phone":"+32 81 56 62 56",
    "sg:postcode":"5081",
    "sg:province":"Namur",
    "wof:name":"Debouche H.",
    "wof:placetype":"venue"
},
  "geometry": {"coordinates":[4.7966151237,50.5474014282],"type":"Point"}
}