{
  "type": "Feature",
  "properties": {
    "addr:full":"Groenestraat 33 Alveringem West-Vlaanderen 8691",
    "addr:housenumber":"33",
    "addr:postcode":"8691",
    "addr:street":"Groenestraat",
    "iso:country":"BE",
    "sg:address":"Groenestraat 33",
    "sg:city":"Alveringem",
    "sg:orig_category":"Musea and historische gebouwen",
    "sg:phone":"+32 58 29 92 44",
    "sg:postcode":"8691",
    "sg:province":"West-Vlaanderen",
    "wof:name":"Museum Pette Blaevoet",
    "wof:placetype":"venue"
},
  "geometry": {"coordinates":[2.6652519703,50.9701004028],"type":"Point"}
}