{
  "type": "Feature",
  "properties": {
    "iso:country":"BE",
    "sg:address":"Avenue De La Gare",
    "sg:city":"Pont-a-celles",
    "sg:classifiers":[
        {
            "category":"Sports & Exercise",
            "subcategory":"Sports Center",
            "type":"Entertainment"
        }
    ],
    "sg:phone":"+32 71 84 47 47",
    "sg:postcode":"6238",
    "sg:province":"Hainaut",
    "sg:tags":[
        "terrain",
        "hors",
        "de",
        "installation",
        "sportifs"
    ],
    "wof:name":"Grazy Orks Volley Luttre",
    "wof:placetype":"venue"
},
  "geometry": {"coordinates":[4.3858599663,50.5057907104],"type":"Point"}
}