{
  "type": "Feature",
  "properties": {
    "addr:full":"Broekstraat 1 Turnhout Antwerpen 2300",
    "addr:housenumber":"1",
    "addr:postcode":"2300",
    "addr:street":"Broekstraat",
    "iso:country":"BE",
    "sg:address":"Broekstraat 1",
    "sg:city":"Turnhout",
    "sg:orig_category":"Epiceries. Journaux",
    "sg:phone":"+32 14 41 28 67",
    "sg:postcode":"2300",
    "sg:province":"Antwerpen",
    "wof:name":"Van Den Broeck Zelfbediening",
    "wof:placetype":"venue"
},
  "geometry": {"coordinates":[4.9601969719,51.3155593872],"type":"Point"}
}