{
  "type": "Feature",
  "properties": {
    "addr:full":"Steenweg 550 Denderleeuw Oost-Vlaanderen 9470",
    "addr:housenumber":"550",
    "addr:postcode":"9470",
    "addr:street":"Steenweg",
    "iso:country":"BE",
    "sg:address":"Steenweg 550",
    "sg:city":"Denderleeuw",
    "sg:orig_category":"Ruimtes voor conferenties, recepties and feesten",
    "sg:phone":"+32 53 66 75 52",
    "sg:postcode":"9470",
    "sg:province":"Oost-Vlaanderen",
    "wof:name":"Horizon",
    "wof:placetype":"venue"
},
  "geometry": {"coordinates":[4.0615448952,50.8801803589],"type":"Point"}
}