{
  "type": "Feature",
  "properties": {
    "iso:country":"BE",
    "sg:address":"Aartbruggestraat 62",
    "sg:city":"Alken",
    "sg:orig_category":"Woningbouw",
    "sg:phone":"+32 11 31 33 26",
    "sg:postcode":"3570",
    "sg:province":"Limburg",
    "wof:name":"Croes W.",
    "wof:placetype":"venue"
},
  "geometry": {"coordinates":[5.2965807915,50.8786811829],"type":"Point"}
}