{
  "type": "Feature",
  "properties": {
    "addr:full":"Bruinborrelaan 36 Meise Vlaams-Brabant 1860",
    "addr:housenumber":"36",
    "addr:postcode":"1860",
    "addr:street":"Bruinborrelaan",
    "iso:country":"BE",
    "sg:address":"Bruinborrelaan 36",
    "sg:city":"Meise",
    "sg:orig_category":"Tuinen",
    "sg:phone":"+32 2 269 83 97",
    "sg:postcode":"1860",
    "sg:province":"Vlaams-Brabant",
    "wof:name":"Tuin & Landschap",
    "wof:placetype":"venue"
},
  "geometry": {"coordinates":[4.3441910744,50.9392967224],"type":"Point"}
}