{
  "type": "Feature",
  "properties": {
    "addr:full":"Rue De La D\u00c9portation 68 La Louviere Hainaut 7100",
    "addr:housenumber":"68",
    "addr:postcode":"7100",
    "addr:street":"Rue De La De\u0301Portation",
    "iso:country":"BE",
    "sg:address":"Rue De La D\u00c9portation 68",
    "sg:city":"La Louviere",
    "sg:orig_category":"Herstellingen and onderhoud van auto's",
    "sg:phone":"+32 64 27 34 34",
    "sg:postcode":"7100",
    "sg:province":"Hainaut",
    "wof:name":"Toyota",
    "wof:placetype":"venue"
},
  "geometry": {"coordinates":[4.19871521,50.4658508301],"type":"Point"}
}