{
  "type": "Feature",
  "properties": {
    "addr:full":"Rue Mandenne 6 Momignies Hainaut 6590",
    "addr:housenumber":"6",
    "addr:postcode":"6590",
    "addr:street":"Rue Mandenne;Hainaut",
    "iso:country":"BE",
    "sg:address":"Rue Mandenne 6",
    "sg:city":"Momignies",
    "sg:orig_category":"Plomberie, chauffage and installations sanitaires",
    "sg:phone":"+32 60 51 12 09",
    "sg:postcode":"6590",
    "sg:province":"Hainaut",
    "wof:name":"Leon Donner",
    "wof:placetype":"venue"
},
  "geometry": {"coordinates":[4.1574821472,50.0264282227],"type":"Point"}
}