{
  "type": "Feature",
  "properties": {
    "addr:full":"Mie\u00ebnbroekstraat 28 Genk Limburg 3600",
    "addr:housenumber":"28",
    "addr:postcode":"3600",
    "addr:street":"Miee\u0308Nbroekstraat",
    "iso:country":"BE",
    "sg:address":"Mie\u00ebnbroekstraat 28",
    "sg:city":"Genk",
    "sg:classifiers":[
        {
            "category":"Building & Trades",
            "subcategory":"Cleaning & Sanitation",
            "type":"Services"
        }
    ],
    "sg:phone":"+32 89 86 98 86",
    "sg:postcode":"3600",
    "sg:province":"Limburg",
    "sg:tags":[
        "janitor"
    ],
    "wof:name":"Service Net Nv",
    "wof:placetype":"venue"
},
  "geometry": {"coordinates":[5.4990282059,50.9411468506],"type":"Point"}
}