{
  "type": "Feature",
  "properties": {
    "addr:full":"Graanstraat 19 Balen Antwerpen 2490",
    "addr:housenumber":"19",
    "addr:postcode":"2490",
    "addr:street":"Graanstraat",
    "iso:country":"BE",
    "sg:address":"Graanstraat 19",
    "sg:city":"Balen",
    "sg:orig_category":"Schoonheidssalons",
    "sg:phone":"+32 14 32 09 19",
    "sg:postcode":"2490",
    "sg:province":"Antwerpen",
    "wof:name":"Instituut Ingrid",
    "wof:placetype":"venue"
},
  "geometry": {"coordinates":[5.1363749504,51.1663513184],"type":"Point"}
}