{
  "type": "Feature",
  "properties": {
    "addr:full":"Jules De Saint-genoisstraat 108 Gent (gentbrugge) Oost-Vlaanderen 9050",
    "addr:housenumber":"108",
    "addr:postcode":"9050",
    "addr:street":"Jules De Saint-Genoisstraat",
    "iso:country":"BE",
    "sg:address":"Jules De Saint-genoisstraat 108",
    "sg:city":"Gent (gentbrugge)",
    "sg:classifiers":[
        {
            "category":"Professional",
            "subcategory":"Management & Consulting",
            "type":"Services"
        }
    ],
    "sg:phone":"+32 9 231 50 65",
    "sg:postcode":"9050",
    "sg:province":"Oost-Vlaanderen",
    "sg:tags":[
        "marketing",
        "-",
        "consultant"
    ],
    "wof:name":"Demets P",
    "wof:placetype":"venue"
},
  "geometry": {"coordinates":[3.7565209866,51.0280990601],"type":"Point"}
}