{
  "type": "Feature",
  "properties": {
    "iso:country":"BE",
    "sg:address":"Itali\u00eblei 67-69",
    "sg:city":"Antwerpen",
    "sg:classifiers":[
        {
            "category":"Retail",
            "subcategory":"Event Space",
            "type":"Services"
        }
    ],
    "sg:phone":"+32 3 232 80 47",
    "sg:postcode":"2000",
    "sg:province":"Antwerpen",
    "sg:tags":[
        "rental",
        "-",
        "hall"
    ],
    "wof:name":"Fins Huis",
    "wof:placetype":"venue"
},
  "geometry": {"coordinates":[4.4148368835,51.2272491455],"type":"Point"}
}