{
  "type": "Feature",
  "properties": {
    "iso:country":"BE",
    "sg:address":"Rue Marengo 4",
    "sg:city":"Li\u00c8ge",
    "sg:orig_category":"Boucheries",
    "sg:phone":"+32 4 227 76 61",
    "sg:postcode":"4000",
    "sg:province":"Li\u00e8ge",
    "wof:name":"Dufrais",
    "wof:placetype":"venue"
},
  "geometry": {"coordinates":[5.5907578468,50.6487159729],"type":"Point"}
}