{
  "type": "Feature",
  "properties": {
    "addr:full":"Demerbroekstraat 40 Rotselaar (werchter) Vlaams-Brabant 3118",
    "addr:housenumber":"40",
    "addr:postcode":"3118",
    "addr:street":"Demerbroekstraat",
    "iso:country":"BE",
    "sg:address":"Demerbroekstraat 40",
    "sg:city":"Rotselaar (werchter)",
    "sg:classifiers":[
        {
            "category":"Health Services",
            "subcategory":"Health Practitioner",
            "type":"Services"
        }
    ],
    "sg:phone":"+32 16 60 09 61",
    "sg:postcode":"3118",
    "sg:province":"Vlaams-Brabant",
    "sg:tags":[
        "physiotherapist"
    ],
    "wof:name":"Mans A",
    "wof:placetype":"venue"
},
  "geometry": {"coordinates":[4.6940898895,50.970489502],"type":"Point"}
}