{
  "type": "Feature",
  "properties": {
    "addr:full":"Rue D'havr\u00c9 137b Mons Hainaut 7000",
    "addr:housenumber":"137b",
    "addr:postcode":"7000",
    "addr:street":"Rue D'Havre \u0301;Hainaut",
    "iso:country":"BE",
    "sg:address":"Rue D'havr\u00c9 137b",
    "sg:city":"Mons",
    "sg:classifiers":[
        {
            "category":"Fast Food",
            "type":"Food & Drink"
        }
    ],
    "sg:phone":"+32 65 84 05 20",
    "sg:postcode":"7000",
    "sg:province":"Hainaut",
    "sg:tags":[
        "meeneem",
        "restaurant"
    ],
    "wof:name":"Snack-bar Le Malibu",
    "wof:placetype":"venue"
},
  "geometry": {"coordinates":[3.9587759972,50.4540138245],"type":"Point"}
}