{
  "type": "Feature",
  "properties": {
    "addr:full":"De Bosschaertstraat 320 Antwerpen Antwerpen 2020",
    "addr:housenumber":"320",
    "addr:postcode":"2020",
    "addr:street":"De Bosschaertstraat",
    "iso:country":"BE",
    "sg:address":"De Bosschaertstraat 320",
    "sg:city":"Antwerpen",
    "sg:orig_category":"Services pour animaux domestiques",
    "sg:phone":"+32 3 237 09 91",
    "sg:postcode":"2020",
    "sg:province":"Antwerpen",
    "wof:name":"Hondenkapsalon Beauty",
    "wof:placetype":"venue"
},
  "geometry": {"coordinates":[4.3874468803,51.1845741272],"type":"Point"}
}