{
  "type": "Feature",
  "properties": {
    "addr:full":"Hugo Verriestlaan 99-1 Wevelgem (gullegem) West-Vlaanderen 8560",
    "addr:housenumber":"99-1",
    "addr:postcode":"8560",
    "addr:street":"Hugo Verriestlaan",
    "iso:country":"BE",
    "sg:address":"Hugo Verriestlaan 99-1",
    "sg:city":"Wevelgem (gullegem)",
    "sg:classifiers":[
        {
            "category":"Health Services",
            "subcategory":"Health Practitioner",
            "type":"Services"
        }
    ],
    "sg:phone":"+32 56 42 81 46",
    "sg:postcode":"8560",
    "sg:province":"West-Vlaanderen",
    "sg:tags":[
        "physiotherapist"
    ],
    "wof:name":"Gheysen Lies",
    "wof:placetype":"venue"
},
  "geometry": {"coordinates":[3.2022519112,50.8386421204],"type":"Point"}
}