{
  "type": "Feature",
  "properties": {
    "iso:country":"BE",
    "sg:address":"Edewallestraat 66",
    "sg:city":"Kortemark",
    "sg:orig_category":"Rundveehouders Varkenskwekers",
    "sg:phone":"+32 51 56 72 98",
    "sg:postcode":"8610",
    "sg:province":"West-Vlaanderen",
    "wof:name":"Daniel Beuselinck",
    "wof:placetype":"venue"
},
  "geometry": {"coordinates":[3.0096049309,51.0344734192],"type":"Point"}
}