{
  "type": "Feature",
  "properties": {
    "addr:full":"Malmedyer Strasse 91 Sankt Vith Li\u00e8ge 4780",
    "addr:housenumber":"91",
    "addr:postcode":"4780",
    "addr:street":"Malmedyer Strasse",
    "iso:country":"BE",
    "sg:address":"Malmedyer Strasse 91",
    "sg:city":"Sankt Vith",
    "sg:classifiers":[
        {
            "category":"Communications",
            "subcategory":"Radio Station",
            "type":"Services"
        }
    ],
    "sg:phone":"+32 80 22 61 11",
    "sg:postcode":"4780",
    "sg:province":"Li\u00e8ge",
    "sg:tags":[
        "diffusion",
        "production",
        "de",
        "programme"
    ],
    "wof:name":"Radio Ok",
    "wof:placetype":"venue"
},
  "geometry": {"coordinates":[6.1176481247,50.290725708],"type":"Point"}
}