{
  "type": "Feature",
  "properties": {
    "addr:full":"Rumbeeksegravier 158 Roeselare West-Vlaanderen 8800",
    "addr:housenumber":"158",
    "addr:postcode":"8800",
    "addr:street":"Rumbeeksegravier",
    "iso:country":"BE",
    "sg:address":"Rumbeeksegravier 158",
    "sg:city":"Roeselare",
    "sg:orig_category":"Groententeelt",
    "sg:phone":"+32 51 20 24 51",
    "sg:postcode":"8800",
    "sg:province":"West-Vlaanderen",
    "wof:name":"Willy Dewulf",
    "wof:placetype":"venue"
},
  "geometry": {"coordinates":[3.1630349159,50.9440116882],"type":"Point"}
}