{
  "type": "Feature",
  "properties": {
    "iso:country":"BE",
    "sg:address":"Rue Sainte-anne 90",
    "sg:city":"Grace-hollogne",
    "sg:orig_category":"Ruimtes voor conferenties, recepties and feesten",
    "sg:phone":"+32 4 263 45 13",
    "sg:postcode":"4460",
    "sg:province":"Li\u00e8ge",
    "wof:name":"Cellier St.anne",
    "wof:placetype":"venue"
},
  "geometry": {"coordinates":[5.4797348976,50.6463088989],"type":"Point"}
}