{
  "type": "Feature",
  "properties": {
    "iso:country":"BE",
    "sg:address":"Rue Victor Martin 8",
    "sg:city":"Wanze",
    "sg:orig_category":"Elektrische installaties voor woningen",
    "sg:phone":"+32 85 23 50 83",
    "sg:postcode":"4520",
    "sg:province":"Li\u00e8ge",
    "wof:name":"Adam Fr\u00c9d\u00c9ric",
    "wof:placetype":"venue"
},
  "geometry": {"coordinates":[5.2482800484,50.5470085144],"type":"Point"}
}