{
  "type": "Feature",
  "properties": {
    "addr:full":"Steenweg Van Grembergen 25 Dendermonde Oost-Vlaanderen 9200",
    "addr:housenumber":"25",
    "addr:postcode":"9200",
    "addr:street":"Steenweg Van Grembergen;Oost-Vlaanderen",
    "iso:country":"BE",
    "sg:address":"Steenweg Van Grembergen 25",
    "sg:city":"Dendermonde",
    "sg:classifiers":[
        {
            "category":"Building & Trades",
            "subcategory":"Landscaping Services",
            "type":"Services"
        }
    ],
    "sg:phone":"+32 52 22 55 10",
    "sg:postcode":"9200",
    "sg:province":"Oost-Vlaanderen",
    "sg:tags":[
        "architect",
        "landscape"
    ],
    "wof:name":"Hortus",
    "wof:placetype":"venue"
},
  "geometry": {"coordinates":[4.100933075,51.0373458862],"type":"Point"}
}