{
  "type": "Feature",
  "properties": {
    "iso:country":"BE",
    "sg:address":"Jacquet Boslaan 5",
    "sg:city":"Moeskroen",
    "sg:orig_category":"Souvenirs and objets artisanaux",
    "sg:phone":"+32 56 48 51 91",
    "sg:postcode":"7711",
    "sg:province":"Hainaut",
    "wof:name":"Craeymeersch",
    "wof:placetype":"venue"
},
  "geometry": {"coordinates":[3.3178079128,50.7265472412],"type":"Point"}
}