{
  "type": "Feature",
  "properties": {
    "addr:full":"Rue Sainte-colombe 13 Doische (soulme) Namur 5680",
    "addr:housenumber":"13",
    "addr:postcode":"5680",
    "addr:street":"Rue Sainte-Colombe",
    "iso:country":"BE",
    "sg:address":"Rue Sainte-colombe 13",
    "sg:city":"Doische (soulme)",
    "sg:classifiers":[
        {
            "category":"Building & Trades",
            "subcategory":"Landscaping Services",
            "type":"Services"
        }
    ],
    "sg:phone":"+32 82 67 86 15",
    "sg:postcode":"5680",
    "sg:province":"Namur",
    "sg:tags":[
        "access",
        "pond",
        "laying-out",
        "-"
    ],
    "wof:name":"Desmanet Jardins",
    "wof:placetype":"venue"
},
  "geometry": {"coordinates":[4.7456698418,50.1359405518],"type":"Point"}
}