{
  "type": "Feature",
  "properties": {
    "iso:country":"BE",
    "sg:address":"Rue Andr\u00c9 Paganetti 2",
    "sg:city":"Gerpinnes",
    "sg:orig_category":"Enseignement maternel and primaire",
    "sg:phone":"+32 71 50 27 92",
    "sg:postcode":"6280",
    "sg:province":"Hainaut",
    "wof:name":"E.f.c. Henri Deglume",
    "wof:placetype":"venue"
},
  "geometry": {"coordinates":[4.4916448593,50.339515686],"type":"Point"}
}