{
  "type": "Feature",
  "properties": {
    "iso:country":"BE",
    "sg:address":"Boulevard Heynen 1",
    "sg:city":"Bouillon",
    "sg:classifiers":[
        {
            "category":"Restaurant",
            "type":"Food & Drink"
        }
    ],
    "sg:phone":"+32 61 46 72 36",
    "sg:postcode":"6830",
    "sg:province":"Luxembourg",
    "wof:name":"Windsor",
    "wof:placetype":"venue"
},
  "geometry": {"coordinates":[5.0697360039,49.7950363159],"type":"Point"}
}