{
  "type": "Feature",
  "properties": {
    "addr:full":"Antwerpsesteenweg 208 Vosselaar Antwerpen 2350",
    "addr:housenumber":"208",
    "addr:postcode":"2350",
    "addr:street":"Antwerpsesteenweg",
    "iso:country":"BE",
    "sg:address":"Antwerpsesteenweg 208",
    "sg:city":"Vosselaar",
    "sg:orig_category":"Experts-comptables. Comptables",
    "sg:phone":"+32 14 61 12 16",
    "sg:postcode":"2350",
    "sg:province":"Antwerpen",
    "wof:name":"J. Kenis",
    "wof:placetype":"venue"
},
  "geometry": {"coordinates":[4.877530098,51.3134536743],"type":"Point"}
}