{
  "type": "Feature",
  "properties": {
    "addr:full":"Les Arsilli\u00e8res 41 Momignies Hainaut 6590",
    "addr:housenumber":"41",
    "addr:postcode":"6590",
    "addr:street":"Hainaut",
    "iso:country":"BE",
    "sg:address":"Les Arsilli\u00e8res 41",
    "sg:city":"Momignies",
    "sg:classifiers":[
        {
            "category":"Personal",
            "subcategory":"Beauty Salon",
            "type":"Services"
        }
    ],
    "sg:phone":"+32 60 51 11 92",
    "sg:postcode":"6590",
    "sg:province":"Hainaut",
    "sg:tags":[
        "lady",
        "-",
        "hairdressing"
    ],
    "wof:name":"Boucle D'or",
    "wof:placetype":"venue"
},
  "geometry": {"coordinates":[4.1699271202,50.027721405],"type":"Point"}
}