{
  "type": "Feature",
  "properties": {
    "iso:country":"BE",
    "sg:address":"Antwerpsesteenweg 115",
    "sg:city":"Geel",
    "sg:orig_category":"Mat\u00e9riel de T\u00e9l\u00e9communication",
    "sg:phone":"+32 14 59 29 77",
    "sg:postcode":"2440",
    "sg:province":"Antwerpen",
    "wof:name":"Eldi",
    "wof:placetype":"venue"
},
  "geometry": {"coordinates":[4.9552497864,51.1453895569],"type":"Point"}
}