{
  "type": "Feature",
  "properties": {
    "addr:full":"Rue Louis De Gunst 125 Bruxelles (molenbeek-saint-jean) Bruxelles-Capitale 1080",
    "addr:housenumber":"125",
    "addr:postcode":"1080",
    "addr:street":"Rue Louis De Gunst",
    "iso:country":"BE",
    "sg:address":"Rue Louis De Gunst 125",
    "sg:city":"Bruxelles (molenbeek-saint-jean)",
    "sg:classifiers":[
        {
            "category":"Sports & Exercise",
            "subcategory":"Swimming Pool",
            "type":"Entertainment"
        }
    ],
    "sg:phone":"+32 2 410 21 54",
    "sg:postcode":"1080",
    "sg:province":"Bruxelles-Capitale",
    "sg:tags":[
        "tank",
        "septic"
    ],
    "wof:name":"Vidange Loiseau Sa",
    "wof:placetype":"venue"
},
  "geometry": {"coordinates":[4.3240599632,50.8510932922],"type":"Point"}
}