{
  "type": "Feature",
  "properties": {
    "addr:full":"Masuistraat 90 Brussel/bruxelles Bruxelles-Capitale 1000",
    "addr:housenumber":"90",
    "addr:postcode":"1000",
    "addr:street":"Masuistraat;/",
    "iso:country":"BE",
    "sg:address":"Masuistraat 90",
    "sg:city":"Brussel/bruxelles",
    "sg:classifiers":[
        {
            "category":"Cafe",
            "type":"Food & Drink"
        }
    ],
    "sg:phone":"+32 2 203 51 60",
    "sg:postcode":"1000",
    "sg:province":"Bruxelles-Capitale",
    "sg:tags":[
        "caf\u00e9s"
    ],
    "wof:name":"Georgios Fiskatoris",
    "wof:placetype":"venue"
},
  "geometry": {"coordinates":[4.3586001396,50.8667793274],"type":"Point"}
}