{
  "type": "Feature",
  "properties": {
    "iso:country":"BE",
    "sg:address":"Trieststraat 26",
    "sg:city":"Kapelle-op-den-bos",
    "sg:orig_category":"Producteurs de l\u00e9gumes",
    "sg:phone":"+32 15 71 13 50",
    "sg:postcode":"1880",
    "sg:province":"Vlaams-Brabant",
    "wof:name":"Luc Van Den Broeck",
    "wof:placetype":"venue"
},
  "geometry": {"coordinates":[4.3643779755,51.0233421326],"type":"Point"}
}