{
  "type": "Feature",
  "properties": {
    "iso:country":"BE",
    "sg:address":"Dadizeelsestraat 255",
    "sg:city":"Moorslede",
    "sg:orig_category":"Gespecialiseerde residenti\u00eble bouw",
    "sg:phone":"+32 56 50 09 88",
    "sg:postcode":"8890",
    "sg:province":"West-Vlaanderen",
    "wof:name":"Herve Petillion",
    "wof:placetype":"venue"
},
  "geometry": {"coordinates":[3.0876400471,50.8572425842],"type":"Point"}
}