{
  "type": "Feature",
  "properties": {
    "addr:full":"Krekelput 1 Oudenaarde Oost-Vlaanderen 9700",
    "addr:housenumber":"1",
    "addr:postcode":"9700",
    "addr:street":"Krekelput",
    "iso:country":"BE",
    "sg:address":"Krekelput 1",
    "sg:city":"Oudenaarde",
    "sg:orig_category":"Textiel Verlichting and huishoudartikelen",
    "sg:phone":"+32 55 31 94 49",
    "sg:postcode":"9700",
    "sg:province":"Oost-Vlaanderen",
    "wof:name":"Huis Neos",
    "wof:placetype":"venue"
},
  "geometry": {"coordinates":[3.6067230701,50.843208313],"type":"Point"}
}