{
  "type": "Feature",
  "properties": {
    "addr:full":"X De Cocklaa Sint-martens-latem Oost-Vlaanderen 9831",
    "addr:postcode":"9831",
    "addr:street":"Oost-Vlaanderen",
    "iso:country":"BE",
    "sg:address":"X De Cocklaa",
    "sg:city":"Sint-martens-latem",
    "sg:orig_category":"Rev\u00eatements de sols and murs. Rev\u00eatements pour sols and murs",
    "sg:phone":"+32 9 281 24 78",
    "sg:postcode":"9831",
    "sg:province":"Oost-Vlaanderen",
    "wof:name":"De Nieuwe Tegel",
    "wof:placetype":"venue"
},
  "geometry": {"coordinates":[3.6009049416,51.0073394775],"type":"Point"}
}