{
  "type": "Feature",
  "properties": {
    "iso:country":"BE",
    "sg:address":"Zusters Van Onze Lieve Vrouw Str 42-44",
    "sg:city":"Merksem",
    "sg:classifiers":[
        {
            "category":"Manufacturing",
            "subcategory":"Wood Products",
            "type":"Manufacturing & Wholesale Goods"
        }
    ],
    "sg:phone":"+32 3 324 06 07",
    "sg:postcode":"2170",
    "sg:province":"Antwerpen",
    "sg:tags":[
        "household",
        "-",
        "machine",
        "engineering",
        "mechanical",
        "furniture"
    ],
    "wof:name":"Heating Efficiency Service Cy Bvba",
    "wof:placetype":"venue"
},
  "geometry": {"coordinates":[4.4359531403,51.2420806885],"type":"Point"}
}