{
  "type": "Feature",
  "properties": {
    "addr:full":"Sint-truidersteenweg 467 Hasselt (groot) Limburg 3500",
    "addr:housenumber":"467",
    "addr:postcode":"3500",
    "addr:street":"Sint-Truidersteenweg;Groot Limburg",
    "iso:country":"BE",
    "sg:address":"Sint-truidersteenweg 467",
    "sg:city":"Hasselt (groot)",
    "sg:orig_category":"Kapsalons",
    "sg:phone":"+32 11 27 14 33",
    "sg:postcode":"3500",
    "sg:province":"Limburg",
    "wof:name":"Coiffure Marleen",
    "wof:placetype":"venue"
},
  "geometry": {"coordinates":[5.327709198,50.9188766479],"type":"Point"}
}