{
  "type": "Feature",
  "properties": {
    "addr:full":"Wemmelse Steenweg 71 Jette/jette Bruxelles-Capitale 1090",
    "addr:housenumber":"71",
    "addr:postcode":"1090",
    "addr:street":"Wemmelse Steenweg",
    "iso:country":"BE",
    "sg:address":"Wemmelse Steenweg 71",
    "sg:city":"Jette/jette",
    "sg:orig_category":"Sportclubs",
    "sg:phone":"+32 2 219 48 03",
    "sg:postcode":"1090",
    "sg:province":"Bruxelles-Capitale",
    "wof:name":"Koshi Jette",
    "wof:placetype":"venue"
},
  "geometry": {"coordinates":[4.3254098892,50.874874115],"type":"Point"}
}