{
  "type": "Feature",
  "properties": {
    "addr:full":"Parc Forges Thiry 1c Theux Li\u00e8ge 4910",
    "addr:housenumber":"1c",
    "addr:postcode":"4910",
    "addr:street":"Forges Thiry",
    "iso:country":"BE",
    "sg:address":"Parc Forges Thiry 1c",
    "sg:city":"Theux",
    "sg:classifiers":[
        {
            "category":"Structure",
            "subcategory":"Office Building",
            "type":"Public Place"
        }
    ],
    "sg:phone":"+32 87 53 06 06",
    "sg:postcode":"4910",
    "sg:province":"Li\u00e8ge",
    "sg:tags":[
        "roofing",
        "slate"
    ],
    "wof:name":"Bley F Sprl",
    "wof:placetype":"venue"
},
  "geometry": {"coordinates":[5.8075509071,50.5482940674],"type":"Point"}
}