{
  "type": "Feature",
  "properties": {
    "addr:full":"Industriestraat 44 Zele Oost-Vlaanderen 9240",
    "addr:housenumber":"44",
    "addr:postcode":"9240",
    "addr:street":"Industriestraat",
    "iso:country":"BE",
    "sg:address":"Industriestraat 44",
    "sg:city":"Zele",
    "sg:classifiers":[
        {
            "category":"Home & Garden",
            "subcategory":"Furniture",
            "type":"Retail Goods"
        }
    ],
    "sg:phone":"+32 52 44 45 57",
    "sg:postcode":"9240",
    "sg:province":"Oost-Vlaanderen",
    "sg:tags":[
        "wood"
    ],
    "wof:name":"B J Parket Bvba",
    "wof:placetype":"venue"
},
  "geometry": {"coordinates":[4.0480837822,51.0712203979],"type":"Point"}
}