{
  "type": "Feature",
  "properties": {
    "iso:country":"BE",
    "sg:address":"Wilselsesteenweg 93",
    "sg:city":"Herent",
    "sg:classifiers":[
        {
            "category":"Tea Room",
            "subcategory":"None",
            "type":"Food & Drink"
        }
    ],
    "sg:phone":"+32 16 22 37 45",
    "sg:postcode":"3020",
    "sg:province":"Vlaams-Brabant",
    "wof:name":"Protea",
    "wof:placetype":"venue"
},
  "geometry": {"coordinates":[4.6823959351,50.9052963257],"type":"Point"}
}