{
  "type": "Feature",
  "properties": {
    "addr:full":"Wahisstraat 230 Menen West-Vlaanderen 8930",
    "addr:housenumber":"230",
    "addr:postcode":"8930",
    "addr:street":"Wahisstraat",
    "iso:country":"BE",
    "sg:address":"Wahisstraat 230",
    "sg:city":"Menen",
    "sg:classifiers":[
        {
            "category":"Bars & Pubs",
            "type":"Food & Drink"
        }
    ],
    "sg:phone":"+32 56 51 93 93",
    "sg:postcode":"8930",
    "sg:province":"West-Vlaanderen",
    "wof:name":"Dixie",
    "wof:placetype":"venue"
},
  "geometry": {"coordinates":[3.1146509647,50.7993011475],"type":"Point"}
}