{
  "type": "Feature",
  "properties": {
    "addr:full":"Gemeenteplein 9 Huldenberg Vlaams-Brabant 3040",
    "addr:housenumber":"9",
    "addr:postcode":"3040",
    "addr:street":"Gemeenteplein",
    "iso:country":"BE",
    "sg:address":"Gemeenteplein 9",
    "sg:city":"Huldenberg",
    "sg:orig_category":"Banques and organismes de cr\u00e9dit",
    "sg:phone":"+32 2 687 71 09",
    "sg:postcode":"3040",
    "sg:province":"Vlaams-Brabant",
    "wof:name":"Kbc",
    "wof:placetype":"venue"
},
  "geometry": {"coordinates":[4.5829868317,50.7889060974],"type":"Point"}
}