{
  "type": "Feature",
  "properties": {
    "addr:full":"Avenue De Bouillon 32 Libramont-chevigny Luxembourg 6800",
    "addr:housenumber":"32",
    "addr:postcode":"6800",
    "addr:street":"Avenue De Bouillon",
    "iso:country":"BE",
    "sg:address":"Avenue De Bouillon 32",
    "sg:city":"Libramont-chevigny",
    "sg:classifiers":[
        {
            "category":"Shopping Center",
            "type":"Public Place"
        }
    ],
    "sg:phone":"+32 61 29 00 10",
    "sg:postcode":"6800",
    "sg:province":"Luxembourg",
    "sg:tags":[
        "enseignement",
        "formation"
    ],
    "wof:name":"Carrefour Formation",
    "wof:placetype":"venue"
},
  "geometry": {"coordinates":[5.3683838844,49.9167366028],"type":"Point"}
}