{
  "type": "Feature",
  "properties": {
    "iso:country":"BE",
    "sg:address":"Rue Culot Fayt 37",
    "sg:city":"Anderlues",
    "sg:classifiers":[
        {
            "category":"Real Estate",
            "subcategory":"Architect",
            "type":"Services"
        }
    ],
    "sg:phone":"+32 71 52 56 19",
    "sg:postcode":"6150",
    "sg:province":"Hainaut",
    "wof:name":"Gasbarro G",
    "wof:placetype":"venue"
},
  "geometry": {"coordinates":[4.2825498581,50.3980102539],"type":"Point"}
}