{
  "type": "Feature",
  "properties": {
    "addr:full":"Dr\u00c8ve Richelle 108 Waterloo Brabant Wallon 1410",
    "addr:housenumber":"108",
    "addr:postcode":"1410",
    "addr:street":"Dre\u0300Ve Richelle",
    "iso:country":"BE",
    "sg:address":"Dr\u00c8ve Richelle 108",
    "sg:city":"Waterloo",
    "sg:orig_category":"Epiceries",
    "sg:phone":"+32 2 351 06 27",
    "sg:postcode":"1410",
    "sg:province":"Brabant Wallon",
    "wof:name":"Vita Food",
    "wof:placetype":"venue"
},
  "geometry": {"coordinates":[4.4101829529,50.7073898315],"type":"Point"}
}