{
  "type": "Feature",
  "properties": {
    "iso:country":"BE",
    "sg:address":"Lange Akker 8",
    "sg:city":"Zele",
    "sg:orig_category":"Brood, gebak and snoepgoed",
    "sg:phone":"+32 52 44 93 07",
    "sg:postcode":"9240",
    "sg:province":"Oost-Vlaanderen",
    "wof:name":"Huis Etrian",
    "wof:placetype":"venue"
},
  "geometry": {"coordinates":[4.0294427872,51.0667190552],"type":"Point"}
}