{
  "type": "Feature",
  "properties": {
    "iso:country":"BE",
    "sg:address":"Druivenstraat 9",
    "sg:city":"Rotselaar",
    "sg:classifiers":[
        {
            "category":"Personal",
            "subcategory":"Beauty Salon",
            "type":"Services"
        }
    ],
    "sg:phone":"+32 16 44 59 49",
    "sg:postcode":"3110",
    "sg:province":"Vlaams-Brabant",
    "sg:tags":[
        "lady",
        "-",
        "hairdressing"
    ],
    "wof:name":"Coiffure Werner",
    "wof:placetype":"venue"
},
  "geometry": {"coordinates":[4.7130241394,50.948299408],"type":"Point"}
}