{
  "type": "Feature",
  "properties": {
    "iso:country":"BE",
    "sg:address":"Dalstraat 44",
    "sg:city":"Brussel/bruxelles",
    "sg:orig_category":"Kantoormateriaal",
    "sg:phone":"+32 2 640 68 88",
    "sg:postcode":"1000",
    "sg:province":"Bruxelles-Capitale",
    "wof:name":"Synergic",
    "wof:placetype":"venue"
},
  "geometry": {"coordinates":[4.3711957932,50.8230819702],"type":"Point"}
}