{
  "type": "Feature",
  "properties": {
    "addr:full":"Otegemstraat 35 Zwevegem West-Vlaanderen 8550",
    "addr:housenumber":"35",
    "addr:postcode":"8550",
    "addr:street":"Otegemstraat",
    "iso:country":"BE",
    "sg:address":"Otegemstraat 35",
    "sg:city":"Zwevegem",
    "sg:orig_category":"Banques and organismes de cr\u00e9dit",
    "sg:phone":"+32 56 75 70 91",
    "sg:postcode":"8550",
    "sg:province":"West-Vlaanderen",
    "wof:name":"Anhyp",
    "wof:placetype":"venue"
},
  "geometry": {"coordinates":[3.3361051083,50.8129196167],"type":"Point"}
}