{
  "type": "Feature",
  "properties": {
    "iso:country":"BE",
    "sg:address":"Rue Renardi 30",
    "sg:city":"Li\u00e8ge 1",
    "sg:classifiers":[
        {
            "category":"Real Estate",
            "subcategory":"Architect",
            "type":"Services"
        }
    ],
    "sg:phone":"+32 4 227 19 35",
    "sg:postcode":"4000",
    "sg:province":"Li\u00e8ge",
    "wof:name":"Forthomme F",
    "wof:placetype":"venue"
},
  "geometry": {"coordinates":[5.6054830551,50.6596183777],"type":"Point"}
}