{
  "type": "Feature",
  "properties": {
    "addr:full":"Bergstraat 3a Riemst (valmeer) Limburg 3770",
    "addr:housenumber":"3a",
    "addr:postcode":"3770",
    "addr:street":"Bergstraat",
    "iso:country":"BE",
    "sg:address":"Bergstraat 3a",
    "sg:city":"Riemst (valmeer)",
    "sg:classifiers":[
        {
            "category":"Food & Beverages",
            "subcategory":"Groceries & Convenience Stores",
            "type":"Retail Goods"
        }
    ],
    "sg:phone":"+32 12 74 79 71",
    "sg:postcode":"3770",
    "sg:province":"Limburg",
    "sg:tags":[
        "grocer"
    ],
    "wof:name":"Voeding An",
    "wof:placetype":"venue"
},
  "geometry": {"coordinates":[5.5893168449,50.7911872864],"type":"Point"}
}