{
  "type": "Feature",
  "properties": {
    "addr:full":"Malendriesstraat 54 Boutersem Vlaams-Brabant 3370",
    "addr:housenumber":"54",
    "addr:postcode":"3370",
    "addr:street":"Malendriesstraat",
    "iso:country":"BE",
    "sg:address":"Malendriesstraat 54",
    "sg:city":"Boutersem",
    "sg:orig_category":"Forge, Moulage and Profilage des M\u00e9taux",
    "sg:phone":"+32 16 73 47 55",
    "sg:postcode":"3370",
    "sg:province":"Vlaams-Brabant",
    "wof:name":"Atelier Sont-elooy",
    "wof:placetype":"venue"
},
  "geometry": {"coordinates":[4.8675880432,50.8576622009],"type":"Point"}
}