{
  "type": "Feature",
  "properties": {
    "iso:country":"BE",
    "sg:address":"Nieuwe Steenweg 127",
    "sg:city":"Temse",
    "sg:orig_category":"Transports terrestres de voyageurs. Taxis services sp\u00e9ciaux",
    "sg:phone":"+32 52 46 05 00",
    "sg:postcode":"9140",
    "sg:province":"Oost-Vlaanderen",
    "wof:name":"Heidebloem Cars",
    "wof:placetype":"venue"
},
  "geometry": {"coordinates":[4.1451067924,51.1278533936],"type":"Point"}
}