{
  "type": "Feature",
  "properties": {
    "addr:full":"Drapstraat 14 Nazareth Oost-Vlaanderen 9810",
    "addr:housenumber":"14",
    "addr:postcode":"9810",
    "addr:street":"Drapstraat",
    "iso:country":"BE",
    "sg:address":"Drapstraat 14",
    "sg:city":"Nazareth",
    "sg:orig_category":"Pain, p\u00e2tisseries and confiseries",
    "sg:phone":"+32 9 385 42 57",
    "sg:postcode":"9810",
    "sg:province":"Oost-Vlaanderen",
    "wof:name":"Rony Van De Kerckhove",
    "wof:placetype":"venue"
},
  "geometry": {"coordinates":[3.599627018,50.9595527649],"type":"Point"}
}