{
  "type": "Feature",
  "properties": {
    "addr:full":"Rue Pieter 62 Bruxelles (forest) Bruxelles-Capitale 1190",
    "addr:housenumber":"62",
    "addr:postcode":"1190",
    "addr:street":"Rue Pieter",
    "iso:country":"BE",
    "sg:address":"Rue Pieter 62",
    "sg:city":"Bruxelles (forest)",
    "sg:classifiers":[
        {
            "category":"Professional",
            "subcategory":"Management & Consulting",
            "type":"Services"
        }
    ],
    "sg:phone":"+32 475 81 26 49",
    "sg:postcode":"1190",
    "sg:province":"Bruxelles-Capitale",
    "sg:tags":[
        "consultant",
        "agency",
        "advertising"
    ],
    "wof:name":"Jr Consult Sprl",
    "wof:placetype":"venue"
},
  "geometry": {"coordinates":[4.3189458847,50.8085136414],"type":"Point"}
}