{
  "type": "Feature",
  "properties": {
    "iso:country":"BE",
    "sg:address":"Oostendestraat 26",
    "sg:city":"Torhout",
    "sg:classifiers":[
        {
            "category":"Restaurant",
            "type":"Food & Drink"
        }
    ],
    "sg:phone":"+32 50 22 10 30",
    "sg:postcode":"8820",
    "sg:province":"West-Vlaanderen",
    "wof:name":"Socrates",
    "wof:placetype":"venue"
},
  "geometry": {"coordinates":[3.0992100239,51.0655784607],"type":"Point"}
}