{
  "type": "Feature",
  "properties": {
    "iso:country":"BE",
    "sg:address":"Kasteelstraat 46",
    "sg:city":"Harelbeke",
    "sg:orig_category":"Architecten",
    "sg:phone":"+32 56 71 15 02",
    "sg:postcode":"8531",
    "sg:province":"West-Vlaanderen",
    "wof:name":"Maarten Gheysen",
    "wof:placetype":"venue"
},
  "geometry": {"coordinates":[3.2988879681,50.882522583],"type":"Point"}
}