{
  "type": "Feature",
  "properties": {
    "addr:full":"Rue Des Nerviens 16 Aiseau-presles Hainaut 6250",
    "addr:housenumber":"16",
    "addr:postcode":"6250",
    "addr:street":"Rue Des Nerviens;Hainaut",
    "iso:country":"BE",
    "sg:address":"Rue Des Nerviens 16",
    "sg:city":"Aiseau-presles",
    "sg:orig_category":"Medische apparatuur, orthopedische artikelen and prothesen Fab",
    "sg:phone":"+32 71 39 53 95",
    "sg:postcode":"6250",
    "sg:province":"Hainaut",
    "wof:name":"Michel Salandini",
    "wof:placetype":"venue"
},
  "geometry": {"coordinates":[4.5863847733,50.40990448],"type":"Point"}
}