{
  "type": "Feature",
  "properties": {
    "addr:full":"Gevaertsdreef 12 Oudenaarde Oost-Vlaanderen 9700",
    "addr:housenumber":"12",
    "addr:postcode":"9700",
    "addr:street":"Gevaertsdreef",
    "iso:country":"BE",
    "sg:address":"Gevaertsdreef 12",
    "sg:city":"Oudenaarde",
    "sg:orig_category":"Banques and organismes de cr\u00e9dit",
    "sg:phone":"+32 55 31 40 42",
    "sg:postcode":"9700",
    "sg:province":"Oost-Vlaanderen",
    "wof:name":"Landbouwkrediet",
    "wof:placetype":"venue"
},
  "geometry": {"coordinates":[3.6025979519,50.8471794128],"type":"Point"}
}