{
  "type": "Feature",
  "properties": {
    "iso:country":"BE",
    "sg:address":"Aartrijkestraat 65a",
    "sg:city":"Ichtegem",
    "sg:orig_category":"Herstelling leer and schoeisel",
    "sg:phone":"+32 59 29 05 40",
    "sg:postcode":"8480",
    "sg:province":"West-Vlaanderen",
    "wof:name":"Franky Dumarey",
    "wof:placetype":"venue"
},
  "geometry": {"coordinates":[3.0301229954,51.126285553],"type":"Point"}
}