{
  "type": "Feature",
  "properties": {
    "addr:full":"Caudronstraat 6 Aalst Oost-Vlaanderen 9300",
    "addr:housenumber":"6",
    "addr:postcode":"9300",
    "addr:street":"Caudronstraat",
    "iso:country":"BE",
    "sg:address":"Caudronstraat 6",
    "sg:city":"Aalst",
    "sg:classifiers":[
        {
            "category":"Professional",
            "subcategory":"Art Services",
            "type":"Services"
        }
    ],
    "sg:phone":"+32 53 77 39 23",
    "sg:postcode":"9300",
    "sg:province":"Oost-Vlaanderen",
    "sg:tags":[
        "realization",
        "audio-visual"
    ],
    "wof:name":"Van Reeth K",
    "wof:placetype":"venue"
},
  "geometry": {"coordinates":[4.0322132111,50.9427947998],"type":"Point"}
}