{
  "type": "Feature",
  "properties": {
    "addr:full":"Rue Des Longs Trieux 7 Estaimpuis Hainaut 7730",
    "addr:housenumber":"7",
    "addr:postcode":"7730",
    "addr:street":"Rue Des Longs Trieux;Hainaut",
    "iso:country":"BE",
    "sg:address":"Rue Des Longs Trieux 7",
    "sg:city":"Estaimpuis",
    "sg:orig_category":"Travaux de pl\u00e2trage. Rev\u00eatements pour sols and murs. Travaux de finition and nettoyage de b\u00e2timents",
    "sg:phone":"+32 56 48 97 22",
    "sg:postcode":"7730",
    "sg:province":"Hainaut",
    "wof:name":"Cera Platre",
    "wof:placetype":"venue"
},
  "geometry": {"coordinates":[3.2676670551,50.6870918274],"type":"Point"}
}