{
  "type": "Feature",
  "properties": {
    "iso:country":"BE",
    "sg:address":"Corsicalaan 26",
    "sg:city":"Kapellen",
    "sg:orig_category":"Activit\u00e9s r\u00e9cr\u00e9atives diverses",
    "sg:phone":"+32 3 666 39 08",
    "sg:postcode":"2950",
    "sg:province":"Antwerpen",
    "wof:name":"Bridge Club Excelsior",
    "wof:placetype":"venue"
},
  "geometry": {"coordinates":[4.4482932091,51.3597450256],"type":"Point"}
}