{
  "type": "Feature",
  "properties": {
    "addr:full":"Rue Des Martyrs 13 Chapelle-lez-herlaimont Hainaut 7160",
    "addr:housenumber":"13",
    "addr:postcode":"7160",
    "addr:street":"Rue Des Martyrs",
    "iso:country":"BE",
    "sg:address":"Rue Des Martyrs 13",
    "sg:city":"Chapelle-lez-herlaimont",
    "sg:orig_category":"Herstelling and restauratie van meubelen",
    "sg:phone":"+32 64 44 89 99",
    "sg:postcode":"7160",
    "sg:province":"Hainaut",
    "wof:name":"Antik Concept",
    "wof:placetype":"venue"
},
  "geometry": {"coordinates":[4.2810049057,50.4714736938],"type":"Point"}
}