{
  "type": "Feature",
  "properties": {
    "addr:full":"Sint-truidersteenweg 246 Tongeren Limburg 3700",
    "addr:housenumber":"246",
    "addr:postcode":"3700",
    "addr:street":"Sint-Truidersteenweg",
    "iso:country":"BE",
    "sg:address":"Sint-truidersteenweg 246",
    "sg:city":"Tongeren",
    "sg:orig_category":"Kapsalons",
    "sg:phone":"+32 12 23 15 80",
    "sg:postcode":"3700",
    "sg:province":"Limburg",
    "wof:name":"Kelly Driesen",
    "wof:placetype":"venue"
},
  "geometry": {"coordinates":[5.4386639595,50.7767944336],"type":"Point"}
}