{
  "type": "Feature",
  "properties": {
    "iso:country":"BE",
    "sg:address":"Tiensesteenweg 137",
    "sg:city":"Lubbeek",
    "sg:orig_category":"Onderdelen and accessoires voor auto's",
    "sg:phone":"+32 16 82 02 61",
    "sg:postcode":"3211",
    "sg:province":"Vlaams-Brabant",
    "wof:name":"De Bandenman",
    "wof:placetype":"venue"
},
  "geometry": {"coordinates":[4.8978648186,50.8579292297],"type":"Point"}
}