{
  "type": "Feature",
  "properties": {
    "iso:country":"BE",
    "sg:address":"Veldstraat 3",
    "sg:city":"Gistel",
    "sg:orig_category":"Rundveehouders",
    "sg:phone":"+32 59 27 71 25",
    "sg:postcode":"8470",
    "sg:province":"West-Vlaanderen",
    "wof:name":"Willy Pieters",
    "wof:placetype":"venue"
},
  "geometry": {"coordinates":[2.9266159534,51.1747589111],"type":"Point"}
}