{
  "type": "Feature",
  "properties": {
    "addr:full":"Dikkebusseweg 18 Ieper West-Vlaanderen 8900",
    "addr:housenumber":"18",
    "addr:postcode":"8900",
    "addr:street":"Dikkebusseweg",
    "iso:country":"BE",
    "sg:address":"Dikkebusseweg 18",
    "sg:city":"Ieper",
    "sg:orig_category":"Radioproductie and uitzendingen",
    "sg:phone":"+32 57 20 44 54",
    "sg:postcode":"8900",
    "sg:province":"West-Vlaanderen",
    "wof:name":"Radio Vrie",
    "wof:placetype":"venue"
},
  "geometry": {"coordinates":[2.8768370152,50.8456192017],"type":"Point"}
}