{
  "type": "Feature",
  "properties": {
    "iso:country":"BE",
    "sg:address":"Molenheide 20ba",
    "sg:city":"Puurs",
    "sg:orig_category":"Rundveehouders",
    "sg:phone":"+32 3 886 50 73",
    "sg:postcode":"2870",
    "sg:province":"Antwerpen",
    "wof:name":"Kerremans Willy & Albert",
    "wof:placetype":"venue"
},
  "geometry": {"coordinates":[4.2882962227,51.0733566284],"type":"Point"}
}