{
  "type": "Feature",
  "properties": {
    "addr:full":"Langemarkstraat 116 Zonnebeke West-Vlaanderen 8980",
    "addr:housenumber":"116",
    "addr:postcode":"8980",
    "addr:street":"Langemarkstraat",
    "iso:country":"BE",
    "sg:address":"Langemarkstraat 116",
    "sg:city":"Zonnebeke",
    "sg:orig_category":"Eleveurs and marchands de porcs. Eleveurs de bovins",
    "sg:phone":"+32 51 77 77 86",
    "sg:postcode":"8980",
    "sg:province":"West-Vlaanderen",
    "wof:name":"Marc Vandoorne",
    "wof:placetype":"venue"
},
  "geometry": {"coordinates":[2.979172945,50.8783378601],"type":"Point"}
}