{
  "type": "Feature",
  "properties": {
    "iso:country":"BE",
    "sg:address":"Stationlei 15",
    "sg:city":"Vilvoorde",
    "sg:classifiers":[
        {
            "category":"Professional",
            "subcategory":"Lawyer & Legal Services",
            "type":"Services"
        }
    ],
    "sg:phone":"+32 2 252 01 95",
    "sg:postcode":"1800",
    "sg:province":"Vlaams-Brabant",
    "wof:name":"Noben Yves",
    "wof:placetype":"venue"
},
  "geometry": {"coordinates":[4.4289112091,50.9257507324],"type":"Point"}
}