{
  "type": "Feature",
  "properties": {
    "addr:full":"Rue Vandervelde 26 Le Roeulx Hainaut 7070",
    "addr:housenumber":"26",
    "addr:postcode":"7070",
    "addr:street":"Rue Vandervelde",
    "iso:country":"BE",
    "sg:address":"Rue Vandervelde 26",
    "sg:city":"Le Roeulx",
    "sg:orig_category":"Microsoft. Ordinateurs and \u00e9quipement informatique",
    "sg:phone":"+32 64 67 65 23",
    "sg:postcode":"7070",
    "sg:province":"Hainaut",
    "wof:name":"Ciges",
    "wof:placetype":"venue"
},
  "geometry": {"coordinates":[4.1098232269,50.5033226013],"type":"Point"}
}