{
  "type": "Feature",
  "properties": {
    "iso:country":"BE",
    "sg:address":"Chauss\u00c9e De Bruxelles 11",
    "sg:city":"Wavre",
    "sg:orig_category":"Overheidsdiensten",
    "sg:phone":"+32 10 22 70 99",
    "sg:postcode":"1300",
    "sg:province":"Brabant Wallon",
    "wof:name":"Admin. Contrib. Directes",
    "wof:placetype":"venue"
},
  "geometry": {"coordinates":[4.6127958298,50.7191314697],"type":"Point"}
}