{
  "type": "Feature",
  "properties": {
    "addr:full":"Veldstraat 206 Box 1 Kortrijk West-Vlaanderen 8500",
    "addr:housenumber":"206;1",
    "addr:postcode":"8500",
    "addr:street":"Veldstraat;Box",
    "iso:country":"BE",
    "sg:address":"Veldstraat 206 Box 1",
    "sg:city":"Kortrijk",
    "sg:classifiers":[
        {
            "category":"Health Services",
            "subcategory":"Health Practitioner",
            "type":"Services"
        }
    ],
    "sg:phone":"+32 497 39 33 14",
    "sg:postcode":"8500",
    "sg:province":"West-Vlaanderen",
    "sg:tags":[
        "physiotherapist"
    ],
    "wof:name":"Blondelle Drieke",
    "wof:placetype":"venue"
},
  "geometry": {"coordinates":[3.2771749496,50.82654953],"type":"Point"}
}