{
  "type": "Feature",
  "properties": {
    "addr:full":"Lerenveld 20 Lint Antwerpen 2547",
    "addr:housenumber":"20",
    "addr:postcode":"2547",
    "addr:street":"Lerenveld",
    "iso:country":"BE",
    "sg:address":"Lerenveld 20",
    "sg:city":"Lint",
    "sg:classifiers":[
        {
            "category":"Manufacturing",
            "subcategory":"Metals",
            "type":"Manufacturing & Wholesale Goods"
        }
    ],
    "sg:phone":"+32 3 488 48 00",
    "sg:postcode":"2547",
    "sg:province":"Antwerpen",
    "sg:tags":[
        "steel",
        "stainless"
    ],
    "wof:name":"Dylan Belgi\u00eb Bvba",
    "wof:placetype":"venue"
},
  "geometry": {"coordinates":[4.5142560005,51.1278648376],"type":"Point"}
}