{
  "type": "Feature",
  "properties": {
    "iso:country":"BE",
    "sg:address":"Rue De Maredsous Denee 13",
    "sg:city":"Anh\u00e9e",
    "sg:classifiers":[
        {
            "category":"Food & Beverages",
            "subcategory":"Cheese",
            "type":"Retail Goods"
        }
    ],
    "sg:phone":"+32 82 69 96 11",
    "sg:postcode":"5537",
    "sg:province":"Namur",
    "wof:name":"Maredsous Fromagerie Brasserie S.a.",
    "wof:placetype":"venue"
},
  "geometry": {"coordinates":[4.8771848679,50.3114013672],"type":"Point"}
}