{
  "type": "Feature",
  "properties": {
    "addr:full":"Rue Du Dohy 4 Chievres Hainaut 7950",
    "addr:housenumber":"4",
    "addr:postcode":"7950",
    "addr:street":"Rue Du Dohy;Hainaut",
    "iso:country":"BE",
    "sg:address":"Rue Du Dohy 4",
    "sg:city":"Chievres",
    "sg:orig_category":"Rundveehouders",
    "sg:phone":"+32 68 65 81 73",
    "sg:postcode":"7950",
    "sg:province":"Hainaut",
    "wof:name":"Philippe Goetgebuer",
    "wof:placetype":"venue"
},
  "geometry": {"coordinates":[3.7923278809,50.5956459045],"type":"Point"}
}