{
  "type": "Feature",
  "properties": {
    "iso:country":"BE",
    "sg:address":"Rue Piconnette 16a",
    "sg:city":"Sombreffe (boign\u00e9e)",
    "sg:classifiers":[
        {
            "category":"Building & Trades",
            "subcategory":"Construction",
            "type":"Services"
        }
    ],
    "sg:phone":"+32 71 43 97 40",
    "sg:postcode":"5140",
    "sg:province":"Namur",
    "sg:tags":[
        "carpenter"
    ],
    "wof:name":"Bernard Denis Ets",
    "wof:placetype":"venue"
},
  "geometry": {"coordinates":[4.6155490875,50.5035629272],"type":"Point"}
}