{
  "type": "Feature",
  "properties": {
    "addr:full":"Avenue Des Arts 11 Ottignies-louvain-la-neuve (louvain-la-neuve) Brabant Wallon 1348",
    "addr:housenumber":"11",
    "addr:postcode":"1348",
    "addr:street":"Avenue Des Arts",
    "iso:country":"BE",
    "sg:address":"Avenue Des Arts 11",
    "sg:city":"Ottignies-louvain-la-neuve (louvain-la-neuve)",
    "sg:classifiers":[
        {
            "category":"Education",
            "subcategory":"School",
            "type":"Public Place"
        }
    ],
    "sg:phone":"+32 10 45 16 66",
    "sg:postcode":"1348",
    "sg:province":"Brabant Wallon",
    "sg:tags":[
        "secondary"
    ],
    "wof:name":"Ecole Des Bruy\u00e9res",
    "wof:placetype":"venue"
},
  "geometry": {"coordinates":[4.611369133,50.6643333435],"type":"Point"}
}