{
  "type": "Feature",
  "properties": {
    "iso:country":"BE",
    "sg:address":"Heidestraat 90",
    "sg:city":"Ternat (sint-katherina-lombeek)",
    "sg:classifiers":[
        {
            "category":"Freight",
            "type":"Transportation"
        }
    ],
    "sg:phone":"+32 2 582 69 53",
    "sg:postcode":"1742",
    "sg:province":"Vlaams-Brabant",
    "sg:tags":[
        "-",
        "transport"
    ],
    "wof:name":"Jema",
    "wof:placetype":"venue"
},
  "geometry": {"coordinates":[4.1405701637,50.8692207336],"type":"Point"}
}