{
  "type": "Feature",
  "properties": {
    "iso:country":"BE",
    "sg:address":"Rue Haute 20",
    "sg:city":"Hensies",
    "sg:orig_category":"Boucheries",
    "sg:phone":"+32 65 45 72 05",
    "sg:postcode":"7350",
    "sg:province":"Hainaut",
    "wof:name":"M. Polloni",
    "wof:placetype":"venue"
},
  "geometry": {"coordinates":[3.6833269596,50.43384552],"type":"Point"}
}