{
  "type": "Feature",
  "properties": {
    "iso:country":"BE",
    "sg:address":"Sint-annastraat 4",
    "sg:city":"Hoeilaart",
    "sg:orig_category":"Installatie van metalen schrijnwerk",
    "sg:phone":"+32 2 657 22 85",
    "sg:postcode":"1560",
    "sg:province":"Vlaams-Brabant",
    "wof:name":"Josse Debontridder",
    "wof:placetype":"venue"
},
  "geometry": {"coordinates":[4.479968071,50.762878418],"type":"Point"}
}