{
  "type": "Feature",
  "properties": {
    "iso:country":"BE",
    "sg:address":"Boulevard Joseph Tirou 20",
    "sg:city":"Charleroi",
    "sg:classifiers":[
        {
            "category":"Professional",
            "subcategory":"Computer Services",
            "type":"Services"
        }
    ],
    "sg:phone":"+32 71 30 33 83",
    "sg:postcode":"6000",
    "sg:province":"Hainaut",
    "sg:tags":[
        "-",
        "processing",
        "data"
    ],
    "wof:name":"Pc Troc",
    "wof:placetype":"venue"
},
  "geometry": {"coordinates":[4.4387598038,50.4082794189],"type":"Point"}
}