{
  "type": "Feature",
  "properties": {
    "addr:full":"Avenue Dailly 150 Bruxelles (schaerbeek) Bruxelles-Capitale 1030",
    "addr:housenumber":"150",
    "addr:postcode":"1030",
    "addr:street":"Avenue Dailly",
    "iso:country":"BE",
    "sg:address":"Avenue Dailly 150",
    "sg:city":"Bruxelles (schaerbeek)",
    "sg:classifiers":[
        {
            "category":"Bars & Pubs",
            "type":"Food & Drink"
        }
    ],
    "sg:phone":"+32 2 245 68 97",
    "sg:postcode":"1030",
    "sg:province":"Bruxelles-Capitale",
    "wof:name":"Ste Alice",
    "wof:placetype":"venue"
},
  "geometry": {"coordinates":[4.3851370811,50.8548126221],"type":"Point"}
}