{
  "type": "Feature",
  "properties": {
    "iso:country":"BE",
    "sg:address":"Kiviethoek 4",
    "sg:city":"Lo-reninge",
    "sg:orig_category":"Rundveehouders Varkenskwekers",
    "sg:phone":"+32 58 28 87 60",
    "sg:postcode":"8647",
    "sg:province":"West-Vlaanderen",
    "wof:name":"Fernand Vanstechelman",
    "wof:placetype":"venue"
},
  "geometry": {"coordinates":[2.7545130253,50.9718475342],"type":"Point"}
}