{
  "type": "Feature",
  "properties": {
    "iso:country":"BE",
    "sg:address":"Rue Aux Crameux 1",
    "sg:city":"Bassenge",
    "sg:classifiers":[
        {
            "category":"Cafe",
            "type":"Food & Drink"
        }
    ],
    "sg:phone":"+32 4 286 41 29",
    "sg:postcode":"4690",
    "sg:province":"Li\u00e8ge",
    "sg:tags":[
        "caf\u00e9s"
    ],
    "wof:name":"Union Roclenge-wonck",
    "wof:placetype":"venue"
},
  "geometry": {"coordinates":[5.5705018044,50.7533187866],"type":"Point"}
}