{
  "type": "Feature",
  "properties": {
    "addr:full":"Steenstraat 3 Brugge West-Vlaanderen 8000",
    "addr:housenumber":"3",
    "addr:postcode":"8000",
    "addr:street":"Steenstraat",
    "iso:country":"BE",
    "sg:address":"Steenstraat 3",
    "sg:city":"Brugge",
    "sg:orig_category":"V\u00eatements pour Dames. V\u00eatements pour b\u00e9b\u00e9s and enfants. V\u00eatements pour Hommes",
    "sg:phone":"+32 50 33 42 92",
    "sg:postcode":"8000",
    "sg:province":"West-Vlaanderen",
    "wof:name":"The Tintin Shop",
    "wof:placetype":"venue"
},
  "geometry": {"coordinates":[3.2241659164,51.2083015442],"type":"Point"}
}