{
  "type": "Feature",
  "properties": {
    "iso:country":"BE",
    "sg:address":"Chauss\u00e9e De Namur 32",
    "sg:city":"Incourt (pi\u00e8trebais)",
    "sg:classifiers":[
        {
            "category":"Conference Center",
            "type":"Public Place"
        }
    ],
    "sg:phone":"+32 10 84 40 88",
    "sg:postcode":"1315",
    "sg:province":"Brabant Wallon",
    "sg:tags":[
        "terrain",
        "vehicle"
    ],
    "wof:name":"Swinne Garage",
    "wof:placetype":"venue"
},
  "geometry": {"coordinates":[4.8042221069,50.6948051453],"type":"Point"}
}