{
  "type": "Feature",
  "properties": {
    "iso:country":"BE",
    "sg:address":"Rue Rodolphe Destrebecq 22",
    "sg:city":"Leuze-en-hainaut",
    "sg:orig_category":"Elektrische installaties voor woningen",
    "sg:phone":"+32 69 66 50 81",
    "sg:postcode":"7900",
    "sg:province":"Hainaut",
    "wof:name":"Devenyns",
    "wof:placetype":"venue"
},
  "geometry": {"coordinates":[3.6382300854,50.6232872009],"type":"Point"}
}