{
  "type": "Feature",
  "properties": {
    "addr:full":"Bruggestraat 173a Wingene (zwevezele) West-Vlaanderen 8750",
    "addr:housenumber":"173a",
    "addr:postcode":"8750",
    "addr:street":"Bruggestraat",
    "iso:country":"BE",
    "sg:address":"Bruggestraat 173a",
    "sg:city":"Wingene (zwevezele)",
    "sg:classifiers":[
        {
            "category":"Health Services",
            "subcategory":"Health Practitioner",
            "type":"Services"
        }
    ],
    "sg:phone":"+32 51 61 19 13",
    "sg:postcode":"8750",
    "sg:province":"West-Vlaanderen",
    "sg:tags":[
        "physiotherapist"
    ],
    "wof:name":"Vannieuwenborgh Martine",
    "wof:placetype":"venue"
},
  "geometry": {"coordinates":[3.2206370831,51.0419807434],"type":"Point"}
}