{
  "type": "Feature",
  "properties": {
    "iso:country":"BE",
    "sg:address":"Oude Vaartstraat 39",
    "sg:city":"Turnhout",
    "sg:classifiers":[
        {
            "category":"Professional",
            "subcategory":"Lawyer & Legal Services",
            "type":"Services"
        }
    ],
    "sg:phone":"+32 14 41 80 28",
    "sg:postcode":"2300",
    "sg:province":"Antwerpen",
    "wof:name":"Debonnaire M",
    "wof:placetype":"venue"
},
  "geometry": {"coordinates":[4.9462089539,51.3278083801],"type":"Point"}
}