{
  "type": "Feature",
  "properties": {
    "iso:country":"BE",
    "sg:address":"Tentoonstellingslaan 38",
    "sg:city":"Gent",
    "sg:classifiers":[
        {
            "category":"Real Estate",
            "subcategory":"Architect",
            "type":"Services"
        }
    ],
    "sg:phone":"+32 9 234 23 40",
    "sg:postcode":"9000",
    "sg:province":"Oost-Vlaanderen",
    "wof:name":"Rogiers B",
    "wof:placetype":"venue"
},
  "geometry": {"coordinates":[3.732665062,51.0404853821],"type":"Point"}
}