{
  "type": "Feature",
  "properties": {
    "addr:full":"Graaf Van Egmontstraat 2 Mechelen Antwerpen 2800",
    "addr:housenumber":"2",
    "addr:postcode":"2800",
    "addr:street":"Graaf Van Egmontstraat",
    "iso:country":"BE",
    "sg:address":"Graaf Van Egmontstraat 2",
    "sg:city":"Mechelen",
    "sg:orig_category":"Agences de voyages",
    "sg:phone":"+32 15 43 66 61",
    "sg:postcode":"2800",
    "sg:province":"Antwerpen",
    "wof:name":"Bruul Travel Center",
    "wof:placetype":"venue"
},
  "geometry": {"coordinates":[4.4820671082,51.0208091736],"type":"Point"}
}