{
  "type": "Feature",
  "properties": {
    "addr:full":"Muntweide 6 Merchtem (brussegem) Vlaams-Brabant 1785",
    "addr:housenumber":"6",
    "addr:postcode":"1785",
    "addr:street":"Muntweide",
    "iso:country":"BE",
    "sg:address":"Muntweide 6",
    "sg:city":"Merchtem (brussegem)",
    "sg:orig_category":"Non-Classified Establishments",
    "sg:phone":"+32 2 461 14 93",
    "sg:postcode":"1785",
    "sg:province":"Vlaams-Brabant",
    "wof:name":"Ardel-line Sa",
    "wof:placetype":"venue"
},
  "geometry": {"coordinates":[4.2685098648,50.928730011],"type":"Point"}
}