{
  "type": "Feature",
  "properties": {
    "iso:country":"BE",
    "sg:address":"Rue Mar\u00e9chal Foch 26",
    "sg:city":"Ch\u00e2telet (ch\u00e2telineau)",
    "sg:classifiers":[
        {
            "category":"Shopping",
            "subcategory":"Stationery & Office Supplies",
            "type":"Retail Goods"
        }
    ],
    "sg:phone":"+32 71 39 23 28",
    "sg:postcode":"6200",
    "sg:province":"Hainaut",
    "wof:name":"Della Rocca Sprl",
    "wof:placetype":"venue"
},
  "geometry": {"coordinates":[4.5181322098,50.4104995728],"type":"Point"}
}