{
  "type": "Feature",
  "properties": {
    "iso:country":"BE",
    "sg:address":"Av.jean & Pierre Carsoel 76",
    "sg:city":"Ukkel/uccle",
    "sg:orig_category":"M\u00e9decins and sp\u00e9cialistes",
    "sg:phone":"+32 2 374 74 61",
    "sg:postcode":"1180",
    "sg:province":"Bruxelles-Capitale",
    "wof:name":"Raymond Bricart",
    "wof:placetype":"venue"
},
  "geometry": {"coordinates":[4.3580517769,50.7945861816],"type":"Point"}
}