{
  "type": "Feature",
  "properties": {
    "iso:country":"BE",
    "sg:address":"Rue Scheutveld 50/52",
    "sg:city":"Anderlecht",
    "sg:orig_category":"Astrologen, grafologen and mediums",
    "sg:phone":"+32 2 523 37 64",
    "sg:postcode":"1070",
    "sg:province":"Bruxelles-Capitale",
    "wof:name":"Madame M\u00c2",
    "wof:placetype":"venue"
},
  "geometry": {"coordinates":[4.314743042,50.8423881531],"type":"Point"}
}