{
  "type": "Feature",
  "properties": {
    "iso:country":"BE",
    "sg:address":"Rue De Focagne 7",
    "sg:city":"Hotton (marenne)",
    "sg:classifiers":[
        {
            "category":"Professional",
            "subcategory":"Accounting & Tax Preparation",
            "type":"Services"
        }
    ],
    "sg:phone":"+32 84 31 41 70",
    "sg:postcode":"6990",
    "sg:province":"Luxembourg",
    "sg:tags":[
        "accountant"
    ],
    "wof:name":"Hick M",
    "wof:placetype":"venue"
},
  "geometry": {"coordinates":[5.3927612305,50.2483177185],"type":"Point"}
}