{
  "type": "Feature",
  "properties": {
    "addr:full":"Gentsesteenweg 58 Lokeren Oost-Vlaanderen 9160",
    "addr:housenumber":"58",
    "addr:postcode":"9160",
    "addr:street":"Gentsesteenweg",
    "iso:country":"BE",
    "sg:address":"Gentsesteenweg 58",
    "sg:city":"Lokeren",
    "sg:classifiers":[
        {
            "category":"Autos & Motor Vehicles",
            "subcategory":"Fuel & Gas Station",
            "type":"Retail Goods"
        }
    ],
    "sg:phone":"+32 9 348 16 35",
    "sg:postcode":"9160",
    "sg:province":"Oost-Vlaanderen",
    "sg:tags":[
        "stations-service",
        "carburants"
    ],
    "wof:name":"Service Station Neyt",
    "wof:placetype":"venue"
},
  "geometry": {"coordinates":[3.9621939659,51.1111183167],"type":"Point"}
}