{
  "type": "Feature",
  "properties": {
    "iso:country":"BE",
    "sg:address":"Rue Des Priesses 535",
    "sg:city":"Andenne",
    "sg:classifiers":[
        {
            "category":"Food & Beverages",
            "subcategory":"Fruits & Vegetables",
            "type":"Retail Goods"
        }
    ],
    "sg:phone":"+32 81 58 01 64",
    "sg:postcode":"5300",
    "sg:province":"Namur",
    "sg:tags":[
        "groenten"
    ],
    "wof:name":"Jean Vandenbosch",
    "wof:placetype":"venue"
},
  "geometry": {"coordinates":[5.0162849426,50.4988212585],"type":"Point"}
}