{
  "type": "Feature",
  "properties": {
    "addr:full":"Rue De L'hospice Communal 50 Bruxelles (watermael-boitsfort) Bruxelles-Capitale 1170",
    "addr:housenumber":"50",
    "addr:postcode":"1170",
    "addr:street":"Rue De L'Hospice Communal",
    "iso:country":"BE",
    "sg:address":"Rue De L'hospice Communal 50",
    "sg:city":"Bruxelles (watermael-boitsfort)",
    "sg:classifiers":[
        {
            "category":"Communications",
            "type":"Services"
        }
    ],
    "sg:phone":"+32 2 660 36 26",
    "sg:postcode":"1170",
    "sg:province":"Bruxelles-Capitale",
    "sg:tags":[
        "translator"
    ],
    "wof:name":"Bertrand Y",
    "wof:placetype":"venue"
},
  "geometry": {"coordinates":[4.4189939499,50.8003311157],"type":"Point"}
}