{
  "type": "Feature",
  "properties": {
    "iso:country":"BE",
    "sg:address":"Lindestraat 5b",
    "sg:city":"Wortegem-petegem (petegem-aan-de-schelde)",
    "sg:classifiers":[
        {
            "category":"Banks & Credit Unions",
            "subcategory":"Investment Brokerage",
            "type":"Services"
        }
    ],
    "sg:phone":"+32 55 31 27 91",
    "sg:postcode":"9790",
    "sg:province":"Oost-Vlaanderen",
    "sg:tags":[
        "printing",
        "-"
    ],
    "wof:name":"Lelieur",
    "wof:placetype":"venue"
},
  "geometry": {"coordinates":[3.5514569283,50.8442649841],"type":"Point"}
}