{
  "type": "Feature",
  "properties": {
    "addr:full":"Driehoeksplein 8 Knokke-heist West-Vlaanderen 8300",
    "addr:housenumber":"8",
    "addr:postcode":"8300",
    "addr:street":"Driehoeksplein",
    "iso:country":"BE",
    "sg:address":"Driehoeksplein 8",
    "sg:city":"Knokke-heist",
    "sg:classifiers":[
        {
            "category":"Restaurant",
            "type":"Food & Drink"
        }
    ],
    "sg:phone":"+32 50 60 06 04",
    "sg:postcode":"8300",
    "sg:province":"West-Vlaanderen",
    "wof:name":"La Ciboulette",
    "wof:placetype":"venue"
},
  "geometry": {"coordinates":[3.287694931,51.3467254639],"type":"Point"}
}