{
  "type": "Feature",
  "properties": {
    "addr:full":"Boulevard De La Cense 15 Waterloo Brabant Wallon 1410",
    "addr:housenumber":"15",
    "addr:postcode":"1410",
    "addr:street":"Boulevard De La Cense",
    "iso:country":"BE",
    "sg:address":"Boulevard De La Cense 15",
    "sg:city":"Waterloo",
    "sg:orig_category":"Articles m\u00e9dicaux and orthop\u00e9diques",
    "sg:phone":"+32 2 353 12 96",
    "sg:postcode":"1410",
    "sg:province":"Brabant Wallon",
    "wof:name":"Blondiau",
    "wof:placetype":"venue"
},
  "geometry": {"coordinates":[4.3965997696,50.7114868164],"type":"Point"}
}