{
  "type": "Feature",
  "properties": {
    "addr:full":"Leopold Ii Laan 19 Brugge West-Vlaanderen 8000",
    "addr:housenumber":"19",
    "addr:postcode":"8000",
    "addr:street":"Leopold Ii Laan",
    "iso:country":"BE",
    "sg:address":"Leopold Ii Laan 19",
    "sg:city":"Brugge",
    "sg:orig_category":"V\u00e9los Fab",
    "sg:phone":"+32 50 33 28 02",
    "sg:postcode":"8000",
    "sg:province":"West-Vlaanderen",
    "wof:name":"Cycles Lea",
    "wof:placetype":"venue"
},
  "geometry": {"coordinates":[3.2162489891,51.219417572],"type":"Point"}
}