{
  "type": "Feature",
  "properties": {
    "addr:full":"Avenue Seghers 71 Bruxelles (koekelberg) Bruxelles-Capitale 1081",
    "addr:housenumber":"71",
    "addr:postcode":"1081",
    "addr:street":"Avenue Seghers",
    "iso:country":"BE",
    "sg:address":"Avenue Seghers 71",
    "sg:city":"Bruxelles (koekelberg)",
    "sg:classifiers":[
        {
            "category":"Professional",
            "subcategory":"Art Services",
            "type":"Services"
        }
    ],
    "sg:phone":"+32 2 411 28 89",
    "sg:postcode":"1081",
    "sg:province":"Bruxelles-Capitale",
    "sg:tags":[
        "designer",
        "display"
    ],
    "wof:name":"Art-decor",
    "wof:placetype":"venue"
},
  "geometry": {"coordinates":[4.3208808899,50.8640670776],"type":"Point"}
}