{
  "type": "Feature",
  "properties": {
    "addr:full":"Lascheid 20 Burg-reuland/burg-reuland Li\u00e8ge 4790",
    "addr:housenumber":"20",
    "addr:postcode":"4790",
    "addr:street":"Lascheid",
    "iso:country":"BE",
    "sg:address":"Lascheid 20",
    "sg:city":"Burg-reuland/burg-reuland",
    "sg:orig_category":"Rundveehouders",
    "sg:phone":"+32 80 32 94 73",
    "sg:postcode":"4790",
    "sg:province":"Li\u00e8ge",
    "wof:name":"Leonhard Scharres",
    "wof:placetype":"venue"
},
  "geometry": {"coordinates":[6.1153740883,50.1849632263],"type":"Point"}
}