{
  "type": "Feature",
  "properties": {
    "iso:country":"BE",
    "sg:address":"Lehnenweg 10",
    "sg:city":"Butgenbach",
    "sg:orig_category":"Charpentes and couvertures. Maisons de vacances",
    "sg:phone":"+32 80 44 53 06",
    "sg:postcode":"4750",
    "sg:province":"Li\u00e8ge",
    "wof:name":"Chalet Jacobs",
    "wof:placetype":"venue"
},
  "geometry": {"coordinates":[6.1651391983,50.4377822876],"type":"Point"}
}