{
  "type": "Feature",
  "properties": {
    "addr:full":"Acacialaan 45ba Kasterlee Antwerpen 2460",
    "addr:housenumber":"45ba",
    "addr:postcode":"2460",
    "addr:street":"Acacialaan",
    "iso:country":"BE",
    "sg:address":"Acacialaan 45ba",
    "sg:city":"Kasterlee",
    "sg:orig_category":"P\u00e9pini\u00e9ristes",
    "sg:phone":"+32 14 85 06 39",
    "sg:postcode":"2460",
    "sg:province":"Antwerpen",
    "wof:name":"Ernie Colebunders",
    "wof:placetype":"venue"
},
  "geometry": {"coordinates":[4.9777097702,51.237449646],"type":"Point"}
}