{
  "type": "Feature",
  "properties": {
    "addr:full":"Gasthuisstraat 14 Merchtem Vlaams-Brabant 1785",
    "addr:housenumber":"14",
    "addr:postcode":"1785",
    "addr:street":"Gasthuisstraat",
    "iso:country":"BE",
    "sg:address":"Gasthuisstraat 14",
    "sg:city":"Merchtem",
    "sg:orig_category":"Animations diverses",
    "sg:phone":"+32 52 37 07 13",
    "sg:postcode":"1785",
    "sg:province":"Vlaams-Brabant",
    "wof:name":"Discobar Rudi Grim",
    "wof:placetype":"venue"
},
  "geometry": {"coordinates":[4.2307429314,50.9613647461],"type":"Point"}
}