{
  "type": "Feature",
  "properties": {
    "iso:country":"BE",
    "sg:address":"Stoepestraat 7g",
    "sg:city":"Assenede",
    "sg:classifiers":[
        {
            "category":"Building & Trades",
            "subcategory":"Landscaping Services",
            "type":"Services"
        }
    ],
    "sg:phone":"+32 9 342 93 50",
    "sg:postcode":"9960",
    "sg:province":"Oost-Vlaanderen",
    "sg:tags":[
        "equipment",
        "swimming",
        "-",
        "pool",
        "contractor"
    ],
    "wof:name":"Nymphea Bvba",
    "wof:placetype":"venue"
},
  "geometry": {"coordinates":[3.7608640194,51.2022399902],"type":"Point"}
}