{
  "type": "Feature",
  "properties": {
    "iso:country":"BE",
    "sg:address":"Rue Du Vingt-quatre Ao\u00fbt 65",
    "sg:city":"Habay (houdemont)",
    "sg:classifiers":[
        {
            "category":"Professional",
            "subcategory":"Management & Consulting",
            "type":"Services"
        }
    ],
    "sg:phone":"+32 63 43 47 57",
    "sg:postcode":"6724",
    "sg:province":"Luxembourg",
    "sg:tags":[
        "marketing",
        "-",
        "consultant"
    ],
    "wof:name":"Open",
    "wof:placetype":"venue"
},
  "geometry": {"coordinates":[5.5863890648,49.7191352844],"type":"Point"}
}