{
  "type": "Feature",
  "properties": {
    "iso:country":"BE",
    "sg:address":"Blaasveldstraat 193",
    "sg:city":"Willebroek",
    "sg:orig_category":"Groententeelt",
    "sg:phone":"+32 3 886 88 92",
    "sg:postcode":"2830",
    "sg:province":"Antwerpen",
    "wof:name":"Van Den Broeck Fr. & L.",
    "wof:placetype":"venue"
},
  "geometry": {"coordinates":[4.3769822121,51.0436668396],"type":"Point"}
}