{
  "type": "Feature",
  "properties": {
    "addr:full":"Place Joseph Wauters 2 Watermaal-bosvoorde/watermael-boitsfort Bruxelles-Capitale 1170",
    "addr:housenumber":"2",
    "addr:postcode":"1170",
    "addr:street":"Place Joseph Wauters",
    "iso:country":"BE",
    "sg:address":"Place Joseph Wauters 2",
    "sg:city":"Watermaal-bosvoorde/watermael-boitsfort",
    "sg:classifiers":[
        {
            "category":"Personal",
            "subcategory":"Beauty Salon",
            "type":"Services"
        }
    ],
    "sg:phone":"+32 2 672 88 49",
    "sg:postcode":"1170",
    "sg:province":"Bruxelles-Capitale",
    "sg:tags":[
        "de",
        "coiffure"
    ],
    "wof:name":"Coiffure Robert",
    "wof:placetype":"venue"
},
  "geometry": {"coordinates":[4.4189658165,50.8083610535],"type":"Point"}
}