{
  "type": "Feature",
  "properties": {
    "addr:full":"Ankerstraat 57 Sint-niklaas Oost-Vlaanderen 9100",
    "addr:housenumber":"57",
    "addr:postcode":"9100",
    "addr:street":"Ankerstraat",
    "iso:country":"BE",
    "sg:address":"Ankerstraat 57",
    "sg:city":"Sint-niklaas",
    "sg:classifiers":[
        {
            "category":"Government",
            "subcategory":"Fire Station",
            "type":"Public Place"
        }
    ],
    "sg:phone":"+32 3 766 40 82",
    "sg:postcode":"9100",
    "sg:province":"Oost-Vlaanderen",
    "sg:tags":[
        "packard",
        "nec",
        "bell"
    ],
    "wof:name":"Ac & T",
    "wof:placetype":"venue"
},
  "geometry": {"coordinates":[4.1456451416,51.1656646729],"type":"Point"}
}