{
  "type": "Feature",
  "properties": {
    "addr:full":"Kluisstraat 26 Bornem Antwerpen 2880",
    "addr:housenumber":"26",
    "addr:postcode":"2880",
    "addr:street":"Kluisstraat",
    "iso:country":"BE",
    "sg:address":"Kluisstraat 26",
    "sg:city":"Bornem",
    "sg:orig_category":"Elektrische installaties voor woningen",
    "sg:phone":"+32 3 899 03 93",
    "sg:postcode":"2880",
    "sg:province":"Antwerpen",
    "wof:name":"Geert Verstraeten",
    "wof:placetype":"venue"
},
  "geometry": {"coordinates":[4.2467198372,51.0853500366],"type":"Point"}
}