{
  "type": "Feature",
  "properties": {
    "iso:country":"BE",
    "sg:address":"Rue Des Cloutiers 34",
    "sg:city":"Charleroi",
    "sg:orig_category":"D\u00e9molition d\u00b4immeubles and terrassements",
    "sg:phone":"+32 71 34 25 53",
    "sg:postcode":"6044",
    "sg:province":"Hainaut",
    "wof:name":"Terramat",
    "wof:placetype":"venue"
},
  "geometry": {"coordinates":[4.401843071,50.4393005371],"type":"Point"}
}