{
  "type": "Feature",
  "properties": {
    "iso:country":"BE",
    "sg:address":"Chauss\u00c9e De March\u00c9 5",
    "sg:city":"Assesse",
    "sg:orig_category":"HUISBRANDOLIE Speelgoed",
    "sg:phone":"+32 83 65 50 99",
    "sg:postcode":"5330",
    "sg:province":"Namur",
    "wof:name":"Botton",
    "wof:placetype":"venue"
},
  "geometry": {"coordinates":[5.0176000595,50.3754005432],"type":"Point"}
}