{
  "type": "Feature",
  "properties": {
    "addr:full":"Volhardingslaan 11 Deinze Oost-Vlaanderen 9800",
    "addr:housenumber":"11",
    "addr:postcode":"9800",
    "addr:street":"Volhardingslaan",
    "iso:country":"BE",
    "sg:address":"Volhardingslaan 11",
    "sg:city":"Deinze",
    "sg:orig_category":"Enseignement secondaire g\u00e9n\u00e9ral. Enseignement secondaire technique and professionnel",
    "sg:phone":"+32 9 386 29 43",
    "sg:postcode":"9800",
    "sg:province":"Oost-Vlaanderen",
    "wof:name":"Koninklijk Atheneum",
    "wof:placetype":"venue"
},
  "geometry": {"coordinates":[3.5272750854,50.9759063721],"type":"Point"}
}