{
  "type": "Feature",
  "properties": {
    "iso:country":"BE",
    "sg:address":"Mechelsesteenweg 146",
    "sg:city":"Edegem",
    "sg:classifiers":[
        {
            "category":"Building & Trades",
            "subcategory":"Cleaning & Sanitation",
            "type":"Services"
        }
    ],
    "sg:phone":"+32 3 454 50 20",
    "sg:postcode":"2650",
    "sg:province":"Antwerpen",
    "sg:tags":[
        "cleaner",
        "domestic",
        "vacuum"
    ],
    "wof:name":"Liberty Rainbow Bvba",
    "wof:placetype":"venue"
},
  "geometry": {"coordinates":[4.4632201195,51.1495780945],"type":"Point"}
}