{
  "type": "Feature",
  "properties": {
    "addr:full":"Groendreef 69 Brussel/bruxelles Bruxelles-Capitale 1000",
    "addr:housenumber":"69",
    "addr:postcode":"1000",
    "addr:street":"Groendreef;/",
    "iso:country":"BE",
    "sg:address":"Groendreef 69",
    "sg:city":"Brussel/bruxelles",
    "sg:orig_category":"Herstellingen and onderhoud van auto's",
    "sg:phone":"+32 2 203 65 81",
    "sg:postcode":"1000",
    "sg:province":"Bruxelles-Capitale",
    "wof:name":"Carrosserie Edell",
    "wof:placetype":"venue"
},
  "geometry": {"coordinates":[4.3588452339,50.8691215515],"type":"Point"}
}