{
  "type": "Feature",
  "properties": {
    "addr:full":"Heesterstraat 14 Maasmechelen Limburg 3630",
    "addr:housenumber":"14",
    "addr:postcode":"3630",
    "addr:street":"Heesterstraat",
    "iso:country":"BE",
    "sg:address":"Heesterstraat 14",
    "sg:city":"Maasmechelen",
    "sg:classifiers":[
        {
            "category":"Building & Trades",
            "subcategory":"Landscaping Services",
            "type":"Services"
        }
    ],
    "sg:postcode":"3630",
    "sg:province":"Limburg",
    "sg:tags":[
        "gardening",
        "garden",
        "maintenance"
    ],
    "wof:name":"Kuypers Graszoden",
    "wof:placetype":"venue"
},
  "geometry": {"coordinates":[80.8512420654,17.600479126],"type":"Point"}
}