{
  "type": "Feature",
  "properties": {
    "addr:full":"Beelbroekstraat 81 Gent Oost-Vlaanderen 9040",
    "addr:housenumber":"81",
    "addr:postcode":"9040",
    "addr:street":"Beelbroekstraat;Oost-Vlaanderen",
    "iso:country":"BE",
    "sg:address":"Beelbroekstraat 81",
    "sg:city":"Gent",
    "sg:orig_category":"Bloemen and planten Gh",
    "sg:phone":"+32 9 228 15 70",
    "sg:postcode":"9040",
    "sg:province":"Oost-Vlaanderen",
    "wof:name":"Van Peteghem R",
    "wof:placetype":"venue"
},
  "geometry": {"coordinates":[3.7885799408,51.0695304871],"type":"Point"}
}