{
  "type": "Feature",
  "properties": {
    "addr:full":"Rue Gatti De Gamond 10a Bruxelles (uccle) Bruxelles-Capitale 1180",
    "addr:housenumber":"10a",
    "addr:postcode":"1180",
    "addr:street":"Rue Gatti De Gamond",
    "iso:country":"BE",
    "sg:address":"Rue Gatti De Gamond 10a",
    "sg:city":"Bruxelles (uccle)",
    "sg:classifiers":[
        {
            "category":"Health Services",
            "subcategory":"Doctor",
            "type":"Services"
        }
    ],
    "sg:phone":"+32 2 376 71 11",
    "sg:postcode":"1180",
    "sg:province":"Bruxelles-Capitale",
    "sg:tags":[
        "medicinephysicians",
        "surgeon"
    ],
    "wof:name":"Dawagne M P",
    "wof:placetype":"venue"
},
  "geometry": {"coordinates":[4.3285450935,50.8058586121],"type":"Point"}
}