{
  "type": "Feature",
  "properties": {
    "iso:country":"BE",
    "sg:address":"Leynseelstraat 154",
    "sg:city":"Avelgem",
    "sg:classifiers":[
        {
            "category":"Utilities",
            "subcategory":"Fuel Oil & Lpg",
            "type":"Services"
        }
    ],
    "sg:phone":"+32 56 64 49 70",
    "sg:postcode":"8580",
    "sg:province":"West-Vlaanderen",
    "wof:name":"Vantieghem Eric Nv",
    "wof:placetype":"venue"
},
  "geometry": {"coordinates":[3.4260540009,50.7787399292],"type":"Point"}
}