{
  "type": "Feature",
  "properties": {
    "iso:country":"BE",
    "sg:address":"Rue De La Casquette 36",
    "sg:city":"Liege",
    "sg:classifiers":[
        {
            "category":"Restaurant",
            "type":"Food & Drink"
        }
    ],
    "sg:phone":"+32 4 222 12 32",
    "sg:postcode":"4000",
    "sg:province":"Li\u00e8ge",
    "wof:name":"Au Pays Des Merveilles",
    "wof:placetype":"venue"
},
  "geometry": {"coordinates":[5.5675320625,50.6420783997],"type":"Point"}
}