{
  "type": "Feature",
  "properties": {
    "addr:full":"Smidsestraat 9 Asse Vlaams-Brabant 1730",
    "addr:housenumber":"9",
    "addr:postcode":"1730",
    "addr:street":"Smidsestraat",
    "iso:country":"BE",
    "sg:address":"Smidsestraat 9",
    "sg:city":"Asse",
    "sg:orig_category":"Landbouwmachines Gh",
    "sg:phone":"+32 2 452 24 45",
    "sg:postcode":"1730",
    "sg:province":"Vlaams-Brabant",
    "wof:name":"H.s.m.",
    "wof:placetype":"venue"
},
  "geometry": {"coordinates":[4.228990078,50.9293708801],"type":"Point"}
}