{
  "type": "Feature",
  "properties": {
    "iso:country":"BE",
    "sg:address":"Rue Baudouin I 8",
    "sg:city":"Mouscron",
    "sg:classifiers":[
        {
            "category":"Airport",
            "subcategory":"International",
            "type":"Transportation"
        }
    ],
    "sg:phone":"+32 56 33 41 63",
    "sg:postcode":"7700",
    "sg:province":"Hainaut",
    "sg:tags":[
        "-",
        "transport"
    ],
    "wof:name":"Transports Wyseur Sprl",
    "wof:placetype":"venue"
},
  "geometry": {"coordinates":[3.187361002,50.7540626526],"type":"Point"}
}