{
  "type": "Feature",
  "properties": {
    "addr:full":"Rue Des R\u00c9collets 1 Bastogne Luxembourg 6600",
    "addr:housenumber":"1",
    "addr:postcode":"6600",
    "addr:street":"Rue Des Re\u0301Collets",
    "iso:country":"BE",
    "sg:address":"Rue Des R\u00c9collets 1",
    "sg:city":"Bastogne",
    "sg:orig_category":"S\u00e9curit\u00e9 sociale",
    "sg:phone":"+32 61 21 34 03",
    "sg:postcode":"6600",
    "sg:province":"Luxembourg",
    "wof:name":"Mutualit\u00c9 Socialiste",
    "wof:placetype":"venue"
},
  "geometry": {"coordinates":[5.7178940773,50.0024757385],"type":"Point"}
}