{
  "type": "Feature",
  "properties": {
    "addr:full":"Stuivenberstr 91 Izegem West-Vlaanderen 8870",
    "addr:housenumber":"91",
    "addr:postcode":"8870",
    "addr:street":"Stuivenberstr",
    "iso:country":"BE",
    "sg:address":"Stuivenberstr 91",
    "sg:city":"Izegem",
    "sg:classifiers":[
        {
            "category":"Shopping",
            "type":"Retail Goods"
        }
    ],
    "sg:phone":"+32 64 27 27 11",
    "sg:postcode":"8870",
    "sg:province":"West-Vlaanderen",
    "sg:tags":[
        "metallurgy",
        "finished",
        "-",
        "metalworking",
        "metallic"
    ],
    "wof:name":"Duferco La Louviere",
    "wof:placetype":"venue"
},
  "geometry": {"coordinates":[4.1737689972,50.4808502197],"type":"Point"}
}