{
  "type": "Feature",
  "properties": {
    "addr:full":"Daalstraat 86 Erpe-mere Oost-Vlaanderen 9420",
    "addr:housenumber":"86",
    "addr:postcode":"9420",
    "addr:street":"Daalstraat",
    "iso:country":"BE",
    "sg:address":"Daalstraat 86",
    "sg:city":"Erpe-mere",
    "sg:classifiers":[
        {
            "category":"Insurance",
            "subcategory":"Insurance Agent",
            "type":"Services"
        }
    ],
    "sg:phone":"+32 53 83 02 35",
    "sg:postcode":"9420",
    "sg:province":"Oost-Vlaanderen",
    "sg:tags":[
        "verzekeringsmakelaars",
        "expert"
    ],
    "wof:name":"M. Burms",
    "wof:placetype":"venue"
},
  "geometry": {"coordinates":[3.9736580849,50.9183235168],"type":"Point"}
}