{
  "type": "Feature",
  "properties": {
    "addr:full":"Rue Du Vieux Pr\u00c9 6 Chaudfontaine Li\u00e8ge 4050",
    "addr:housenumber":"6",
    "addr:postcode":"4050",
    "addr:street":"Rue Du Vieux Pre\u0301",
    "iso:country":"BE",
    "sg:address":"Rue Du Vieux Pr\u00c9 6",
    "sg:city":"Chaudfontaine",
    "sg:classifiers":[
        {
            "category":"Military Area",
            "subcategory":"Armory",
            "type":"Public Place"
        }
    ],
    "sg:phone":"+32 4 368 69 78",
    "sg:postcode":"4050",
    "sg:province":"Li\u00e8ge",
    "sg:tags":[
        "armes",
        "munition"
    ],
    "wof:name":"Maison Doms",
    "wof:placetype":"venue"
},
  "geometry": {"coordinates":[5.6411728859,50.575969696],"type":"Point"}
}