{
  "type": "Feature",
  "properties": {
    "iso:country":"BE",
    "sg:address":"Terbekehofdreef 46-48",
    "sg:city":"Wilrijk",
    "sg:classifiers":[
        {
            "category":"Manufacturing",
            "subcategory":"Tools & Machinery",
            "type":"Manufacturing & Wholesale Goods"
        }
    ],
    "sg:phone":"+32 3 828 12 72",
    "sg:postcode":"2610",
    "sg:province":"Antwerpen",
    "sg:tags":[
        "metallurgy",
        "metalworking"
    ],
    "wof:name":"Van Meerbeeck Metalen Nv",
    "wof:placetype":"venue"
},
  "geometry": {"coordinates":[4.371322155,51.157749176],"type":"Point"}
}