{
  "type": "Feature",
  "properties": {
    "iso:country":"BE",
    "sg:address":"Avenue H. Liebrecht 76",
    "sg:city":"Bruxelles",
    "sg:orig_category":"Kapsalons",
    "sg:phone":"+32 2 479 81 75",
    "sg:postcode":"1090",
    "sg:province":"Bruxelles-Capitale",
    "wof:name":"Coiffure Claude",
    "wof:placetype":"venue"
},
  "geometry": {"coordinates":[4.3178339005,50.8906898499],"type":"Point"}
}