{
  "type": "Feature",
  "properties": {
    "addr:full":"Rue Du Moulin D'en Haut 128a Mons (fl\u00e9nu) Hainaut 7012",
    "addr:housenumber":"128a",
    "addr:postcode":"7012",
    "addr:street":"Rue Du Moulin D'En Haut",
    "iso:country":"BE",
    "sg:address":"Rue Du Moulin D'en Haut 128a",
    "sg:city":"Mons (fl\u00e9nu)",
    "sg:classifiers":[
        {
            "category":"Retail",
            "subcategory":"Animal Services",
            "type":"Services"
        }
    ],
    "sg:phone":"+32 65 82 36 65",
    "sg:postcode":"7012",
    "sg:province":"Hainaut",
    "sg:tags":[
        "grooming",
        "-",
        "dog"
    ],
    "wof:name":"Poil Unique (au)",
    "wof:placetype":"venue"
},
  "geometry": {"coordinates":[3.8994269371,50.438911438],"type":"Point"}
}