{
  "type": "Feature",
  "properties": {
    "iso:country":"BE",
    "sg:address":"Paddeschootdreef 4a",
    "sg:city":"Sint-niklaas",
    "sg:orig_category":"Textile Cleaning Systems",
    "sg:phone":"+32 3 780 74 00",
    "sg:postcode":"9100",
    "sg:province":"Oost-Vlaanderen",
    "wof:name":"Varteks Nv",
    "wof:placetype":"venue"
},
  "geometry": {"coordinates":[4.1285881996,51.1681251526],"type":"Point"}
}