{
  "type": "Feature",
  "properties": {
    "addr:full":"Tomberg 78 Brussel/bruxelles Bruxelles-Capitale 1200",
    "addr:housenumber":"78",
    "addr:postcode":"1200",
    "addr:street":"Tomberg;/",
    "iso:country":"BE",
    "sg:address":"Tomberg 78",
    "sg:city":"Brussel/bruxelles",
    "sg:orig_category":"Fleurs and plantes",
    "sg:phone":"+32 2 762 02 24",
    "sg:postcode":"1200",
    "sg:province":"Bruxelles-Capitale",
    "wof:name":"Van Moer",
    "wof:placetype":"venue"
},
  "geometry": {"coordinates":[4.4280929565,50.8422584534],"type":"Point"}
}