{
  "type": "Feature",
  "properties": {
    "addr:full":"Zomerstraat-west 4 Damme West-Vlaanderen 8340",
    "addr:housenumber":"4",
    "addr:postcode":"8340",
    "addr:street":"Zomerstraat-West",
    "iso:country":"BE",
    "sg:address":"Zomerstraat-west 4",
    "sg:city":"Damme",
    "sg:orig_category":"Rundveehouders Varkenskwekers",
    "sg:phone":"+32 50 35 43 57",
    "sg:postcode":"8340",
    "sg:province":"West-Vlaanderen",
    "wof:name":"Van Belleghem Eric & Gino",
    "wof:placetype":"venue"
},
  "geometry": {"coordinates":[3.313172102,51.1970176697],"type":"Point"}
}