{
  "type": "Feature",
  "properties": {
    "iso:country":"BE",
    "sg:address":"Diksmuidsestraat 32",
    "sg:city":"Ieper",
    "sg:orig_category":"Boekhouders",
    "sg:phone":"+32 57 20 27 64",
    "sg:postcode":"8900",
    "sg:province":"West-Vlaanderen",
    "wof:name":"Bernard D'hont",
    "wof:placetype":"venue"
},
  "geometry": {"coordinates":[2.8866510391,50.8529090881],"type":"Point"}
}