{
  "type": "Feature",
  "properties": {
    "addr:full":"Rue Du Centre 19 Sainte-ode Luxembourg 6680",
    "addr:housenumber":"19",
    "addr:postcode":"6680",
    "addr:street":"Rue Du Centre",
    "iso:country":"BE",
    "sg:address":"Rue Du Centre 19",
    "sg:city":"Sainte-ode",
    "sg:orig_category":"Boekhouders",
    "sg:phone":"+32 61 68 81 19",
    "sg:postcode":"6680",
    "sg:province":"Luxembourg",
    "wof:name":"Devaux Beno\u00cet",
    "wof:placetype":"venue"
},
  "geometry": {"coordinates":[5.5304489136,50.0108299255],"type":"Point"}
}