{
  "type": "Feature",
  "properties": {
    "addr:full":"Immerzeeldreef 223 Aalst Oost-Vlaanderen 9300",
    "addr:housenumber":"223",
    "addr:postcode":"9300",
    "iso:country":"BE",
    "sg:address":"Immerzeeldreef 223",
    "sg:city":"Aalst",
    "sg:orig_category":"V\u00e9t\u00e9rinaires",
    "sg:phone":"+32 53 70 15 34",
    "sg:postcode":"9300",
    "sg:province":"Oost-Vlaanderen",
    "wof:name":"William Beeckman",
    "wof:placetype":"venue"
},
  "geometry": {"coordinates":[4.0747761726,50.9314346313],"type":"Point"}
}