{
  "type": "Feature",
  "properties": {
    "iso:country":"BE",
    "sg:address":"Rue De La R\u00c9volution 93",
    "sg:city":"Charleroi",
    "sg:orig_category":"Motoren, transformatoren and generatoren Fab",
    "sg:phone":"+32 71 35 20 26",
    "sg:postcode":"6040",
    "sg:province":"Hainaut",
    "wof:name":"Maison Aigrisse",
    "wof:placetype":"venue"
},
  "geometry": {"coordinates":[4.4610800743,50.4450912476],"type":"Point"}
}