{
  "type": "Feature",
  "properties": {
    "iso:country":"BE",
    "sg:address":"Overbroekstraat 71b",
    "sg:city":"Wellen",
    "sg:classifiers":[
        {
            "category":"Home & Garden",
            "subcategory":"Carpets & Floor Coverings",
            "type":"Retail Goods"
        }
    ],
    "sg:phone":"+32 12 74 67 41",
    "sg:postcode":"3830",
    "sg:province":"Limburg",
    "sg:tags":[
        "tile"
    ],
    "wof:name":"Smolders M Bvba",
    "wof:placetype":"venue"
},
  "geometry": {"coordinates":[5.3221030235,50.8299674988],"type":"Point"}
}