{
  "type": "Feature",
  "properties": {
    "addr:full":"Natienlaan 77 Knokke-heist West-Vlaanderen 8300",
    "addr:housenumber":"77",
    "addr:postcode":"8300",
    "addr:street":"Natienlaan",
    "iso:country":"BE",
    "sg:address":"Natienlaan 77",
    "sg:city":"Knokke-heist",
    "sg:orig_category":"Supermarkten Telecommunicatieapparaten",
    "sg:phone":"+32 50 63 06 11",
    "sg:postcode":"8300",
    "sg:province":"West-Vlaanderen",
    "wof:name":"Carrefour",
    "wof:placetype":"venue"
},
  "geometry": {"coordinates":[3.2889609337,51.3365058899],"type":"Point"}
}