{
  "type": "Feature",
  "properties": {
    "addr:full":"Sint-annaboomstraat 31 Zwijndrecht Antwerpen 2070",
    "addr:housenumber":"31",
    "addr:postcode":"2070",
    "addr:street":"Sint-Annaboomstraat",
    "iso:country":"BE",
    "sg:address":"Sint-annaboomstraat 31",
    "sg:city":"Zwijndrecht",
    "sg:classifiers":[
        {
            "category":"Cafe",
            "type":"Food & Drink"
        }
    ],
    "sg:phone":"+32 3 252 94 44",
    "sg:postcode":"2070",
    "sg:province":"Antwerpen",
    "sg:tags":[
        "caf\u00e9s"
    ],
    "wof:name":"Mariette Van De Voorde",
    "wof:placetype":"venue"
},
  "geometry": {"coordinates":[4.3232870102,51.2182197571],"type":"Point"}
}