{
  "type": "Feature",
  "properties": {
    "addr:full":"Overheulestraat 106 Wevelgem West-Vlaanderen 8560",
    "addr:housenumber":"106",
    "addr:postcode":"8560",
    "addr:street":"Overheulestraat",
    "iso:country":"BE",
    "sg:address":"Overheulestraat 106",
    "sg:city":"Wevelgem",
    "sg:orig_category":"Boekhouders",
    "sg:phone":"+32 56 42 50 88",
    "sg:postcode":"8560",
    "sg:province":"West-Vlaanderen",
    "wof:name":"Jean Allaert",
    "wof:placetype":"venue"
},
  "geometry": {"coordinates":[3.1642069817,50.8451919556],"type":"Point"}
}