{
  "type": "Feature",
  "properties": {
    "iso:country":"BE",
    "sg:address":"Kerkstraat 1",
    "sg:city":"Diksmuide",
    "sg:orig_category":"Slagers",
    "sg:phone":"+32 51 50 04 26",
    "sg:postcode":"8600",
    "sg:province":"West-Vlaanderen",
    "wof:name":"Slagerij Anneca",
    "wof:placetype":"venue"
},
  "geometry": {"coordinates":[2.869795084,51.0017585754],"type":"Point"}
}