{
  "type": "Feature",
  "properties": {
    "addr:full":"Leemstraat 56 Essen Antwerpen 2910",
    "addr:housenumber":"56",
    "addr:postcode":"2910",
    "addr:street":"Leemstraat",
    "iso:country":"BE",
    "sg:address":"Leemstraat 56",
    "sg:city":"Essen",
    "sg:orig_category":"Boekhouders",
    "sg:phone":"+32 3 677 35 70",
    "sg:postcode":"2910",
    "sg:province":"Antwerpen",
    "wof:name":"Roger De Brouwer",
    "wof:placetype":"venue"
},
  "geometry": {"coordinates":[4.4454641342,51.4517707825],"type":"Point"}
}