{
  "type": "Feature",
  "properties": {
    "iso:country":"BE",
    "sg:address":"Emiel Derooverlaan 38",
    "sg:city":"Halle",
    "sg:orig_category":"M\u00e9decins and sp\u00e9cialistes",
    "sg:phone":"+32 2 356 78 41",
    "sg:postcode":"1501",
    "sg:province":"Vlaams-Brabant",
    "wof:name":"E. De Keersmaeker",
    "wof:placetype":"venue"
},
  "geometry": {"coordinates":[4.2637262344,50.7428970337],"type":"Point"}
}