{
  "type": "Feature",
  "properties": {
    "addr:full":"H.frere Orbanlaan 151 Gent-centrum Oost-Vlaanderen 9000",
    "addr:housenumber":"151",
    "addr:postcode":"9000",
    "addr:street":"Orbanlaan;Oost-Vlaanderen",
    "iso:country":"BE",
    "sg:address":"H.frere Orbanlaan 151",
    "sg:city":"Gent-centrum",
    "sg:orig_category":"Advocaten and juridische adviseurs Balie van Gent",
    "sg:phone":"+32 9 233 27 28",
    "sg:postcode":"9000",
    "sg:province":"Oost-Vlaanderen",
    "wof:name":"Claeys Stefaan",
    "wof:placetype":"venue"
},
  "geometry": {"coordinates":[3.7341470718,51.0442771912],"type":"Point"}
}