{
  "type": "Feature",
  "properties": {
    "iso:country":"BE",
    "sg:address":"Hasseltweg 441",
    "sg:city":"Genk",
    "sg:classifiers":[
        {
            "category":"Travel",
            "subcategory":"Hotels & Motels",
            "type":"Entertainment"
        }
    ],
    "sg:phone":"+32 11 26 20 83",
    "sg:postcode":"3600",
    "sg:province":"Limburg",
    "wof:name":"Cupido",
    "wof:placetype":"venue"
},
  "geometry": {"coordinates":[5.4345149994,50.9573249817],"type":"Point"}
}