{
  "type": "Feature",
  "properties": {
    "addr:full":"Rue Try-\u00c0-la-vigne 30 Gembloux Namur 5030",
    "addr:housenumber":"30",
    "addr:postcode":"5030",
    "addr:street":"Rue Try-A\u0300-La-Vigne;Namur",
    "iso:country":"BE",
    "sg:address":"Rue Try-\u00c0-la-vigne 30",
    "sg:city":"Gembloux",
    "sg:orig_category":"Salles de conf\u00e9rences and de r\u00e9ceptions. Catering and organisation de f\u00eates",
    "sg:phone":"+32 81 61 41 15",
    "sg:postcode":"5030",
    "sg:province":"Namur",
    "wof:name":"Domaine De L'orneau",
    "wof:placetype":"venue"
},
  "geometry": {"coordinates":[4.7291998863,50.5811195374],"type":"Point"}
}