{
  "type": "Feature",
  "properties": {
    "addr:full":"Rue Du Grand Champ 4 Fernelmont (noville-les-bois) Namur 5380",
    "addr:housenumber":"4",
    "addr:postcode":"5380",
    "addr:street":"Rue Du Grand Champ",
    "iso:country":"BE",
    "sg:address":"Rue Du Grand Champ 4",
    "sg:city":"Fernelmont (noville-les-bois)",
    "sg:orig_category":"Non-Classified Establishments",
    "sg:phone":"+32 81 83 02 30",
    "sg:postcode":"5380",
    "sg:province":"Namur",
    "wof:name":"Megadif Sa",
    "wof:placetype":"venue"
},
  "geometry": {"coordinates":[4.9752240181,50.5364990234],"type":"Point"}
}