{
  "type": "Feature",
  "properties": {
    "addr:full":"Boulevard Joseph Tirou 17b51 Charleroi Hainaut 6000",
    "addr:housenumber":"17b51",
    "addr:postcode":"6000",
    "addr:street":"Boulevard Joseph Tirou;Hainaut",
    "iso:country":"BE",
    "sg:address":"Boulevard Joseph Tirou 17b51",
    "sg:city":"Charleroi",
    "sg:orig_category":"Woningbouw",
    "sg:phone":"+32 71 30 25 51",
    "sg:postcode":"6000",
    "sg:province":"Hainaut",
    "wof:name":"Gagneraud",
    "wof:placetype":"venue"
},
  "geometry": {"coordinates":[4.4380922318,50.4086761475],"type":"Point"}
}