{
  "type": "Feature",
  "properties": {
    "addr:full":"1930 Zaventem Vlaams-Brabant 1930",
    "addr:postcode":"1930;1930",
    "iso:country":"BE",
    "sg:address":"1930",
    "sg:city":"Zaventem",
    "sg:orig_category":"Services annexes des transports terrestres",
    "sg:phone":"+32 2 715 21 10",
    "sg:postcode":"1930",
    "sg:province":"Vlaams-Brabant",
    "wof:name":"Frontpark Parking P1",
    "wof:placetype":"venue"
},
  "geometry": {"coordinates":[4.4872097969,50.8848686218],"type":"Point"}
}