{
  "type": "Feature",
  "properties": {
    "addr:full":"Grote Markt 18 Beveren Oost-Vlaanderen 9120",
    "addr:housenumber":"18",
    "addr:postcode":"9120",
    "addr:street":"Grote Markt",
    "iso:country":"BE",
    "sg:address":"Grote Markt 18",
    "sg:city":"Beveren",
    "sg:orig_category":"Kantoormateriaal",
    "sg:phone":"+32 3 775 99 28",
    "sg:postcode":"9120",
    "sg:province":"Oost-Vlaanderen",
    "wof:name":"Fa. Pijl-mertens",
    "wof:placetype":"venue"
},
  "geometry": {"coordinates":[4.2555909157,51.2133293152],"type":"Point"}
}