{
  "type": "Feature",
  "properties": {
    "addr:full":"Rue De Laeken 162 Brussel/bruxelles Bruxelles-Capitale 1000",
    "addr:housenumber":"162",
    "addr:postcode":"1000",
    "addr:street":"Rue De Laeken;/",
    "iso:country":"BE",
    "sg:address":"Rue De Laeken 162",
    "sg:city":"Brussel/bruxelles",
    "sg:orig_category":"Reisbureaus",
    "sg:phone":"+32 2 223 15 31",
    "sg:postcode":"1000",
    "sg:province":"Bruxelles-Capitale",
    "wof:name":"Starbus",
    "wof:placetype":"venue"
},
  "geometry": {"coordinates":[4.3525428772,50.8561401367],"type":"Point"}
}