{
  "type": "Feature",
  "properties": {
    "iso:country":"BE",
    "sg:address":"Borzestraat 28-30",
    "sg:city":"Mechelen",
    "sg:classifiers":[
        {
            "category":"Autos & Motor Vehicles",
            "subcategory":"Boat Sales",
            "type":"Retail Goods"
        }
    ],
    "sg:phone":"+32 15 21 20 81",
    "sg:postcode":"2800",
    "sg:province":"Antwerpen",
    "sg:tags":[
        "balloon"
    ],
    "wof:name":"Snuffels",
    "wof:placetype":"venue"
},
  "geometry": {"coordinates":[4.4803051949,51.0262145996],"type":"Point"}
}