{
  "type": "Feature",
  "properties": {
    "addr:full":"Hendrik Speecqvest 2b1 Mechelen Antwerpen 2800",
    "addr:housenumber":"2b1",
    "addr:postcode":"2800",
    "addr:street":"Hendrik Speecqvest",
    "iso:country":"BE",
    "sg:address":"Hendrik Speecqvest 2b1",
    "sg:city":"Mechelen",
    "sg:orig_category":"Syst\u00e8mes de t\u00e9l\u00e9communications",
    "sg:phone":"+32 15 43 10 38",
    "sg:postcode":"2800",
    "sg:province":"Antwerpen",
    "wof:name":"Ricoh-topdeal",
    "wof:placetype":"venue"
},
  "geometry": {"coordinates":[4.4837069511,51.0204544067],"type":"Point"}
}