{
  "type": "Feature",
  "properties": {
    "iso:country":"BE",
    "sg:address":"Dremelheidebaan 1",
    "sg:city":"Brecht",
    "sg:classifiers":[
        {
            "category":"Food & Beverages",
            "subcategory":"Fruits & Vegetables",
            "type":"Retail Goods"
        }
    ],
    "sg:phone":"+32 3 636 15 54",
    "sg:postcode":"2960",
    "sg:province":"Antwerpen",
    "sg:tags":[
        "-"
    ],
    "wof:name":"Waeyaert J",
    "wof:placetype":"venue"
},
  "geometry": {"coordinates":[4.5756449699,51.3039207458],"type":"Point"}
}