{
  "type": "Feature",
  "properties": {
    "addr:full":"Sinaaidorp 22b1 Sint-niklaas Oost-Vlaanderen 9112",
    "addr:housenumber":"22b1",
    "addr:postcode":"9112",
    "addr:street":"Sinaaidorp",
    "iso:country":"BE",
    "sg:address":"Sinaaidorp 22b1",
    "sg:city":"Sint-niklaas",
    "sg:orig_category":"Boekhouders",
    "sg:phone":"+32 3 772 17 05",
    "sg:postcode":"9112",
    "sg:province":"Oost-Vlaanderen",
    "wof:name":"Ronny De Meersman",
    "wof:placetype":"venue"
},
  "geometry": {"coordinates":[4.039358139,51.1575775146],"type":"Point"}
}