{
  "type": "Feature",
  "properties": {
    "iso:country":"BE",
    "sg:address":"Chauss\u00c9e De Bruxelles 110",
    "sg:city":"Charleroi",
    "sg:orig_category":"Dakwerken",
    "sg:phone":"+32 71 35 75 48",
    "sg:postcode":"6040",
    "sg:province":"Hainaut",
    "wof:name":"Ets. Wiaux",
    "wof:placetype":"venue"
},
  "geometry": {"coordinates":[4.4390468597,50.4385185242],"type":"Point"}
}