{
  "type": "Feature",
  "properties": {
    "addr:full":"Emile Van Becelaerelaan 76 Watermaal-bosvoorde/watermael-boitsfort Bruxelles-Capitale 1170",
    "addr:housenumber":"76",
    "addr:postcode":"1170",
    "addr:street":"Emile Van Becelaerelaan",
    "iso:country":"BE",
    "sg:address":"Emile Van Becelaerelaan 76",
    "sg:city":"Watermaal-bosvoorde/watermael-boitsfort",
    "sg:orig_category":"Sportclubs",
    "sg:phone":"+32 2 673 20 80",
    "sg:postcode":"1170",
    "sg:province":"Bruxelles-Capitale",
    "wof:name":"M.c. L'equipe",
    "wof:placetype":"venue"
},
  "geometry": {"coordinates":[4.40396595,50.8017501831],"type":"Point"}
}