{
  "type": "Feature",
  "properties": {
    "iso:country":"BE",
    "sg:address":"Grote Thems 37 Box D",
    "sg:city":"Jabbeke (varsenare)",
    "sg:classifiers":[
        {
            "category":"Social Services",
            "subcategory":"Job Training",
            "type":"Services"
        }
    ],
    "sg:phone":"+32 50 31 04 21",
    "sg:postcode":"8490",
    "sg:province":"West-Vlaanderen",
    "sg:tags":[
        "personnel"
    ],
    "wof:name":"Ifbd",
    "wof:placetype":"venue"
},
  "geometry": {"coordinates":[3.0923700333,51.1824378967],"type":"Point"}
}