{
  "type": "Feature",
  "properties": {
    "iso:country":"BE",
    "sg:address":"Rue De La Maladr\u00c9e 81",
    "sg:city":"Gembloux",
    "sg:orig_category":"Juwelen and horloges",
    "sg:phone":"+32 81 61 57 96",
    "sg:postcode":"5030",
    "sg:province":"Namur",
    "wof:name":"Ornella Debelle",
    "wof:placetype":"venue"
},
  "geometry": {"coordinates":[4.7279000282,50.5462226868],"type":"Point"}
}