{
  "type": "Feature",
  "properties": {
    "addr:full":"Patersstraat 5 Eeklo Oost-Vlaanderen 9900",
    "addr:housenumber":"5",
    "addr:postcode":"9900",
    "addr:street":"Patersstraat",
    "iso:country":"BE",
    "sg:address":"Patersstraat 5",
    "sg:city":"Eeklo",
    "sg:orig_category":"Kapsalons",
    "sg:phone":"+32 9 378 24 70",
    "sg:postcode":"9900",
    "sg:province":"Oost-Vlaanderen",
    "wof:name":"Coiffure Hilde",
    "wof:placetype":"venue"
},
  "geometry": {"coordinates":[3.5662961006,51.1818695068],"type":"Point"}
}