{
  "type": "Feature",
  "properties": {
    "addr:full":"Rue Winston Churchill 18 Li\u00e8ge 1 (li\u00e8ge 2) Li\u00e8ge 4020",
    "addr:housenumber":"18;1;2",
    "addr:postcode":"4020",
    "addr:street":"Rue Winston Churchill",
    "iso:country":"BE",
    "sg:address":"Rue Winston Churchill 18",
    "sg:city":"Li\u00e8ge 1 (li\u00e8ge 2)",
    "sg:classifiers":[
        {
            "category":"Building & Trades",
            "subcategory":"Electrical",
            "type":"Services"
        }
    ],
    "sg:phone":"+32 4 340 06 87",
    "sg:postcode":"4020",
    "sg:province":"Li\u00e8ge",
    "sg:tags":[
        "electric",
        "-",
        "housewiring",
        "contractor"
    ],
    "wof:name":"Marsiat D",
    "wof:placetype":"venue"
},
  "geometry": {"coordinates":[5.5967741013,50.6382904053],"type":"Point"}
}