{
  "type": "Feature",
  "properties": {
    "addr:full":"Montagne De Saint-job 39 Ukkel/uccle Bruxelles-Capitale 1180",
    "addr:housenumber":"39",
    "addr:postcode":"1180",
    "addr:street":"Montagne De Saint-Job;/",
    "iso:country":"BE",
    "sg:address":"Montagne De Saint-job 39",
    "sg:city":"Ukkel/uccle",
    "sg:classifiers":[
        {
            "category":"Restaurant",
            "type":"Food & Drink"
        }
    ],
    "sg:phone":"+32 2 375 30 53",
    "sg:postcode":"1180",
    "sg:province":"Bruxelles-Capitale",
    "wof:name":"Au Repos De La Montagne",
    "wof:placetype":"venue"
},
  "geometry": {"coordinates":[4.3657951355,50.7932434082],"type":"Point"}
}