{
  "type": "Feature",
  "properties": {
    "addr:full":"Albrecht Rodenbachlaan 2 Torhout West-Vlaanderen 8820",
    "addr:housenumber":"2",
    "addr:postcode":"8820",
    "addr:street":"Albrecht Rodenbachlaan",
    "iso:country":"BE",
    "sg:address":"Albrecht Rodenbachlaan 2",
    "sg:city":"Torhout",
    "sg:orig_category":"Sportclubs",
    "sg:phone":"+32 50 22 29 50",
    "sg:postcode":"8820",
    "sg:province":"West-Vlaanderen",
    "wof:name":"V.c. Punta Torhout",
    "wof:placetype":"venue"
},
  "geometry": {"coordinates":[3.108412981,51.0672721863],"type":"Point"}
}