{
  "type": "Feature",
  "properties": {
    "addr:full":"Noordstraat 14 Maldegem Oost-Vlaanderen 9990",
    "addr:housenumber":"14",
    "addr:postcode":"9990",
    "addr:street":"Noordstraat",
    "iso:country":"BE",
    "sg:address":"Noordstraat 14",
    "sg:city":"Maldegem",
    "sg:orig_category":"Bijouteries and horlogeries",
    "sg:phone":"+32 50 71 20 49",
    "sg:postcode":"9990",
    "sg:province":"Oost-Vlaanderen",
    "wof:name":"Lutgarde De Lille",
    "wof:placetype":"venue"
},
  "geometry": {"coordinates":[3.447977066,51.2097015381],"type":"Point"}
}