{
  "type": "Feature",
  "properties": {
    "iso:country":"BE",
    "sg:address":"Boomgaardstraat 2bc",
    "sg:city":"Zoutleeuw",
    "sg:orig_category":"Gespecialiseerde residenti\u00eble bouw",
    "sg:phone":"+32 11 58 10 23",
    "sg:postcode":"3440",
    "sg:province":"Vlaams-Brabant",
    "wof:name":"Pascal Swaen",
    "wof:placetype":"venue"
},
  "geometry": {"coordinates":[5.0947008133,50.8688774109],"type":"Point"}
}