{
  "type": "Feature",
  "properties": {
    "iso:country":"BE",
    "sg:address":"Rue Grande 51",
    "sg:city":"Dour",
    "sg:orig_category":"V\u00eatements pour Dames. V\u00eatements pour Hommes",
    "sg:phone":"+32 65 65 29 40",
    "sg:postcode":"7370",
    "sg:province":"Hainaut",
    "wof:name":"Robert Dormont",
    "wof:placetype":"venue"
},
  "geometry": {"coordinates":[3.7801990509,50.3984909058],"type":"Point"}
}