{
  "type": "Feature",
  "properties": {
    "iso:country":"BE",
    "sg:address":"Beervelde-dorp 75",
    "sg:city":"Lochristi (beervelde)",
    "sg:classifiers":[
        {
            "category":"Banks & Credit Unions",
            "subcategory":"Investment Brokerage",
            "type":"Services"
        }
    ],
    "sg:phone":"+32 9 355 55 40",
    "sg:postcode":"9080",
    "sg:province":"Oost-Vlaanderen",
    "sg:tags":[
        "auditor"
    ],
    "wof:name":"Leflot F",
    "wof:placetype":"venue"
},
  "geometry": {"coordinates":[3.8789989948,51.0801887512],"type":"Point"}
}