{
  "type": "Feature",
  "properties": {
    "iso:country":"BE",
    "sg:address":"Iddergemstraat 65",
    "sg:city":"Denderleeuw",
    "sg:classifiers":[
        {
            "category":"Bars & Pubs",
            "type":"Food & Drink"
        }
    ],
    "sg:phone":"+32 53 68 24 12",
    "sg:postcode":"9470",
    "sg:province":"Oost-Vlaanderen",
    "sg:tags":[
        "tavern"
    ],
    "wof:name":"Roll's",
    "wof:placetype":"venue"
},
  "geometry": {"coordinates":[4.0558838844,50.8758964539],"type":"Point"}
}