{
  "type": "Feature",
  "properties": {
    "iso:country":"BE",
    "sg:address":"Drevendaal 40",
    "sg:city":"Sint-katelijne-waver",
    "sg:orig_category":"Cases For Batteries And Accumulators",
    "sg:phone":"+32 15 30 54 30",
    "sg:postcode":"2860",
    "sg:province":"Antwerpen",
    "wof:name":"Belloy & Zonen B.v.b.a.",
    "wof:placetype":"venue"
},
  "geometry": {"coordinates":[4.5099959373,51.0692863464],"type":"Point"}
}