{
  "type": "Feature",
  "properties": {
    "iso:country":"BE",
    "sg:address":"Meersstraat 176",
    "sg:city":"Ternat",
    "sg:classifiers":[
        {
            "category":"Cafe",
            "type":"Food & Drink"
        }
    ],
    "sg:phone":"+32 2 582 47 31",
    "sg:postcode":"1742",
    "sg:province":"Vlaams-Brabant",
    "sg:tags":[
        "caf\u00e9s"
    ],
    "wof:name":"Marcel De Bisschop",
    "wof:placetype":"venue"
},
  "geometry": {"coordinates":[4.1555399895,50.8733253479],"type":"Point"}
}