{
  "type": "Feature",
  "properties": {
    "addr:full":"Woudlaan 13 Wezembeek-oppem/wezembeek-oppem Vlaams-Brabant 1970",
    "addr:housenumber":"13",
    "addr:postcode":"1970",
    "addr:street":"Woudlaan",
    "iso:country":"BE",
    "sg:address":"Woudlaan 13",
    "sg:city":"Wezembeek-oppem/wezembeek-oppem",
    "sg:classifiers":[
        {
            "category":"Professional",
            "subcategory":"Accounting & Tax Preparation",
            "type":"Services"
        }
    ],
    "sg:phone":"+32 2 731 48 35",
    "sg:postcode":"1970",
    "sg:province":"Vlaams-Brabant",
    "sg:tags":[
        "accountant"
    ],
    "wof:name":"Fe. Lemercinier Philippe",
    "wof:placetype":"venue"
},
  "geometry": {"coordinates":[4.4730300903,50.8418388367],"type":"Point"}
}