{
  "type": "Feature",
  "properties": {
    "addr:full":"Paalstraat 127 Schoten Antwerpen 2900",
    "addr:housenumber":"127",
    "addr:postcode":"2900",
    "addr:street":"Paalstraat",
    "iso:country":"BE",
    "sg:address":"Paalstraat 127",
    "sg:city":"Schoten",
    "sg:classifiers":[
        {
            "category":"Shopping",
            "subcategory":"Pets & Pet Supplies",
            "type":"Retail Goods"
        }
    ],
    "sg:phone":"+32 3 658 26 61",
    "sg:postcode":"2900",
    "sg:province":"Antwerpen",
    "sg:tags":[
        "shop",
        "-"
    ],
    "wof:name":"Parkiet (de)",
    "wof:placetype":"venue"
},
  "geometry": {"coordinates":[4.5028018951,51.254108429],"type":"Point"}
}