{
  "type": "Feature",
  "properties": {
    "addr:full":"Rue De Beaurieux 2b Court-saint-etienne Brabant Wallon 1490",
    "addr:housenumber":"2b;1490",
    "addr:street":"Rue De Beaurieux",
    "iso:country":"BE",
    "sg:address":"Rue De Beaurieux 2b",
    "sg:city":"Court-saint-etienne",
    "sg:classifiers":[
        {
            "category":"Retail",
            "subcategory":"Veterinary Services",
            "type":"Services"
        }
    ],
    "sg:phone":"+32 10 61 19 71",
    "sg:postcode":"1490",
    "sg:province":"Brabant Wallon",
    "sg:tags":[
        "veterinarian"
    ],
    "wof:name":"Warnotte A",
    "wof:placetype":"venue"
},
  "geometry": {"coordinates":[4.5724549294,50.6418457031],"type":"Point"}
}