{
  "type": "Feature",
  "properties": {
    "iso:country":"BE",
    "sg:address":"Boulevard Emile De Laveleye 79",
    "sg:city":"Li\u00e8ge 1 (li\u00e8ge 2)",
    "sg:classifiers":[
        {
            "category":"Sports & Exercise",
            "subcategory":"Gym",
            "type":"Entertainment"
        }
    ],
    "sg:phone":"+32 4 344 20 50",
    "sg:postcode":"4020",
    "sg:province":"Li\u00e8ge",
    "sg:tags":[
        "fitness"
    ],
    "wof:name":"Vital Club Ingrid Berghmans",
    "wof:placetype":"venue"
},
  "geometry": {"coordinates":[5.5850200653,50.6244812012],"type":"Point"}
}