{
  "type": "Feature",
  "properties": {
    "addr:full":"Gustaaf Peetersstraat 64 Ranst Antwerpen 2520",
    "addr:housenumber":"64",
    "addr:postcode":"2520",
    "addr:street":"Gustaaf Peetersstraat",
    "iso:country":"BE",
    "sg:address":"Gustaaf Peetersstraat 64",
    "sg:city":"Ranst",
    "sg:orig_category":"Banques and organismes de cr\u00e9dit",
    "sg:phone":"+32 3 485 64 11",
    "sg:postcode":"2520",
    "sg:province":"Antwerpen",
    "wof:name":"Centea",
    "wof:placetype":"venue"
},
  "geometry": {"coordinates":[4.6069569588,51.179523468],"type":"Point"}
}