{
  "type": "Feature",
  "properties": {
    "addr:full":"Impasse De La Cense Gain 17 Mons Hainaut 7000",
    "addr:housenumber":"17",
    "addr:postcode":"7000",
    "addr:street":"Impasse De La Cense Gain;Hainaut",
    "iso:country":"BE",
    "sg:address":"Impasse De La Cense Gain 17",
    "sg:city":"Mons",
    "sg:orig_category":"Eleveurs de bovins",
    "sg:phone":"+32 65 31 30 13",
    "sg:postcode":"7000",
    "sg:province":"Hainaut",
    "wof:name":"Pierre Claustriaux",
    "wof:placetype":"venue"
},
  "geometry": {"coordinates":[3.9890329838,50.4521903992],"type":"Point"}
}