{
  "type": "Feature",
  "properties": {
    "iso:country":"BE",
    "sg:address":"Rue Jules-cralle 50",
    "sg:city":"Li\u00e8ge 1 (grivegn\u00e9e)",
    "sg:classifiers":[
        {
            "category":"Arena",
            "subcategory":"Sports Club",
            "type":"Entertainment"
        }
    ],
    "sg:phone":"+32 4 367 25 55",
    "sg:postcode":"4030",
    "sg:province":"Li\u00e8ge",
    "sg:tags":[
        "martial art",
        "accessory"
    ],
    "wof:name":"Dynamic Sphere",
    "wof:placetype":"venue"
},
  "geometry": {"coordinates":[5.6068129539,50.6199073792],"type":"Point"}
}