{
  "type": "Feature",
  "properties": {
    "addr:full":"Rue Gaston Gr\u00e9goire 15 Amay Li\u00e8ge 4540",
    "addr:housenumber":"15",
    "addr:postcode":"4540",
    "addr:street":"Rue Gaston Gre\u0301Goire",
    "iso:country":"BE",
    "sg:address":"Rue Gaston Gr\u00e9goire 15",
    "sg:city":"Amay",
    "sg:classifiers":[
        {
            "category":"Personal",
            "subcategory":"Beauty Salon",
            "type":"Services"
        }
    ],
    "sg:phone":"+32 85 31 22 41",
    "sg:postcode":"4540",
    "sg:province":"Li\u00e8ge",
    "sg:tags":[
        "lady",
        "-",
        "hairdressing"
    ],
    "wof:name":"Gabrielle",
    "wof:placetype":"venue"
},
  "geometry": {"coordinates":[5.3185691833,50.5488014221],"type":"Point"}
}