{
  "type": "Feature",
  "properties": {
    "iso:country":"BE",
    "sg:address":"Oude Koornmarkt 42",
    "sg:city":"Antwerpen",
    "sg:classifiers":[
        {
            "category":"Bars & Pubs",
            "type":"Food & Drink"
        }
    ],
    "sg:phone":"+32 3 227 03 33",
    "sg:postcode":"2000",
    "sg:province":"Antwerpen",
    "wof:name":"Fancy Fun",
    "wof:placetype":"venue"
},
  "geometry": {"coordinates":[4.4003248215,51.219871521],"type":"Point"}
}