{
  "type": "Feature",
  "properties": {
    "addr:full":"Kouterslag 29 Nevele Oost-Vlaanderen 9850",
    "addr:housenumber":"29",
    "addr:postcode":"9850",
    "addr:street":"Kouterslag",
    "iso:country":"BE",
    "sg:address":"Kouterslag 29",
    "sg:city":"Nevele",
    "sg:classifiers":[
        {
            "category":"Food & Beverages",
            "subcategory":"Fruits & Vegetables",
            "type":"Retail Goods"
        }
    ],
    "sg:phone":"+32 9 371 55 41",
    "sg:postcode":"9850",
    "sg:province":"Oost-Vlaanderen",
    "sg:tags":[
        "groenten"
    ],
    "wof:name":"M. De Meyer",
    "wof:placetype":"venue"
},
  "geometry": {"coordinates":[3.572206974,51.0743598938],"type":"Point"}
}