{
  "type": "Feature",
  "properties": {
    "addr:full":"Rue Arbre Courte Joie 48 Rocourt Li\u00e8ge 4000",
    "addr:housenumber":"48",
    "addr:postcode":"4000",
    "addr:street":"Rue Arbre Courte Joie",
    "iso:country":"BE",
    "sg:address":"Rue Arbre Courte Joie 48",
    "sg:city":"Rocourt",
    "sg:classifiers":[
        {
            "category":"Building & Trades",
            "subcategory":"Electrical",
            "type":"Services"
        }
    ],
    "sg:phone":"+32 4 224 77 24",
    "sg:postcode":"4000",
    "sg:province":"Li\u00e8ge",
    "sg:tags":[
        "electronic",
        "lighting",
        "equipment"
    ],
    "wof:name":"Paque Yvan Sa",
    "wof:placetype":"venue"
},
  "geometry": {"coordinates":[5.5550079346,50.664440155],"type":"Point"}
}