{
  "type": "Feature",
  "properties": {
    "addr:full":"Rue Parmentier 16bb Rebecq Brabant Wallon 1430",
    "addr:housenumber":"16bb",
    "addr:postcode":"1430",
    "addr:street":"Rue Parmentier",
    "iso:country":"BE",
    "sg:address":"Rue Parmentier 16bb",
    "sg:city":"Rebecq",
    "sg:classifiers":[
        {
            "category":"Government",
            "subcategory":"Police Station",
            "type":"Public Place"
        }
    ],
    "sg:phone":"+32 67 63 82 13",
    "sg:postcode":"1430",
    "sg:province":"Brabant Wallon",
    "sg:tags":[
        "gendarmerie"
    ],
    "wof:name":"Police F\u00c9d\u00c9rale/federale Politie",
    "wof:placetype":"venue"
},
  "geometry": {"coordinates":[4.1351537704,50.6666259766],"type":"Point"}
}