{
  "type": "Feature",
  "properties": {
    "iso:country":"BE",
    "sg:address":"Ankerrui 2",
    "sg:city":"Antwerpen",
    "sg:orig_category":"Zeevrachtagentschappen",
    "sg:phone":"+32 3 224 56 40",
    "sg:postcode":"2000",
    "sg:province":"Antwerpen",
    "wof:name":"Srn Shipping",
    "wof:placetype":"venue"
},
  "geometry": {"coordinates":[4.4098749161,51.2273750305],"type":"Point"}
}