{
  "type": "Feature",
  "properties": {
    "addr:full":"Schrieksebaan 34 Tremelo Vlaams-Brabant 3120",
    "addr:housenumber":"34",
    "addr:postcode":"3120",
    "addr:street":"Schrieksebaan",
    "iso:country":"BE",
    "sg:address":"Schrieksebaan 34",
    "sg:city":"Tremelo",
    "sg:orig_category":"Equipement photographique. Studios photographiques",
    "sg:phone":"+32 16 53 12 53",
    "sg:postcode":"3120",
    "sg:province":"Vlaams-Brabant",
    "wof:name":"Marcel Verbeeck",
    "wof:placetype":"venue"
},
  "geometry": {"coordinates":[4.7065711021,50.9927864075],"type":"Point"}
}