{
  "type": "Feature",
  "properties": {
    "addr:full":"Rue De La Limerie 23 Mons Hainaut 7000",
    "addr:housenumber":"23",
    "addr:postcode":"7000",
    "addr:street":"Rue De La Limerie;Hainaut",
    "iso:country":"BE",
    "sg:address":"Rue De La Limerie 23",
    "sg:city":"Mons",
    "sg:classifiers":[
        {
            "category":"Landmark",
            "subcategory":"Scenic View",
            "type":"Public Place"
        }
    ],
    "sg:phone":"+32 65 33 53 47",
    "sg:postcode":"7000",
    "sg:province":"Hainaut",
    "sg:tags":[
        "setting",
        "photographic"
    ],
    "wof:name":"Glineur (imprimerie)",
    "wof:placetype":"venue"
},
  "geometry": {"coordinates":[3.953676939,50.4469184875],"type":"Point"}
}