{
  "type": "Feature",
  "properties": {
    "addr:full":"Joe Englishstraat 7 Brugge West-Vlaanderen 8000",
    "addr:housenumber":"7",
    "addr:postcode":"8000",
    "addr:street":"Joe Englishstraat",
    "iso:country":"BE",
    "sg:address":"Joe Englishstraat 7",
    "sg:city":"Brugge",
    "sg:orig_category":"Artsen and specialisten",
    "sg:phone":"+32 50 31 31 22",
    "sg:postcode":"8000",
    "sg:province":"West-Vlaanderen",
    "wof:name":"Michel Van Zandycke",
    "wof:placetype":"venue"
},
  "geometry": {"coordinates":[3.2082378864,51.2164840698],"type":"Point"}
}