{
  "type": "Feature",
  "properties": {
    "addr:full":"Rue Pont D'avroy 48 Li\u00e8ge 1 Li\u00e8ge 4000",
    "addr:housenumber":"48;1",
    "addr:postcode":"4000",
    "addr:street":"Rue Pont D'Avroy",
    "iso:country":"BE",
    "sg:address":"Rue Pont D'avroy 48",
    "sg:city":"Li\u00e8ge 1",
    "sg:classifiers":[
        {
            "category":"Shopping",
            "subcategory":"Shoes",
            "type":"Retail Goods"
        }
    ],
    "sg:phone":"+32 4 223 72 45",
    "sg:postcode":"4000",
    "sg:province":"Li\u00e8ge",
    "sg:tags":[
        "slipper",
        "-"
    ],
    "wof:name":"Maxy Chaussures",
    "wof:placetype":"venue"
},
  "geometry": {"coordinates":[5.5689878464,50.6403770447],"type":"Point"}
}