{
  "type": "Feature",
  "properties": {
    "addr:full":"Rue De Maredsous 11 Anh\u00e9e (den\u00e9e) Namur 5537",
    "addr:housenumber":"11",
    "addr:postcode":"5537",
    "addr:street":"Rue De Maredsous",
    "iso:country":"BE",
    "sg:address":"Rue De Maredsous 11",
    "sg:city":"Anh\u00e9e (den\u00e9e)",
    "sg:classifiers":[
        {
            "category":"Shopping",
            "subcategory":"Crafts & Fabrics",
            "type":"Retail Goods"
        }
    ],
    "sg:phone":"+32 82 69 83 18",
    "sg:postcode":"5537",
    "sg:province":"Namur",
    "sg:tags":[
        "ceramic"
    ],
    "wof:name":"Ateliers D'art De Maredsous",
    "wof:placetype":"venue"
},
  "geometry": {"coordinates":[4.7660250664,50.3008842468],"type":"Point"}
}