{
  "type": "Feature",
  "properties": {
    "addr:full":"Eikenstraat 6 Oostkamp West-Vlaanderen 8020",
    "addr:housenumber":"6",
    "addr:postcode":"8020",
    "addr:street":"Eikenstraat",
    "iso:country":"BE",
    "sg:address":"Eikenstraat 6",
    "sg:city":"Oostkamp",
    "sg:orig_category":"Rundveehouders Varkenskwekers",
    "sg:phone":"+32 50 27 60 23",
    "sg:postcode":"8020",
    "sg:province":"West-Vlaanderen",
    "wof:name":"Guido Veys",
    "wof:placetype":"venue"
},
  "geometry": {"coordinates":[3.2018899918,51.0716552734],"type":"Point"}
}