{
  "type": "Feature",
  "properties": {
    "addr:full":"Rue De La Station 13 Seraing Li\u00e8ge 4101",
    "addr:housenumber":"13",
    "addr:postcode":"4101",
    "addr:street":"Rue De La Station",
    "iso:country":"BE",
    "sg:address":"Rue De La Station 13",
    "sg:city":"Seraing",
    "sg:orig_category":"Sportterreinen and installaties behalve sportcentra",
    "sg:phone":"+32 4 234 11 55",
    "sg:postcode":"4101",
    "sg:province":"Li\u00e8ge",
    "wof:name":"Bowling De Jemeppe",
    "wof:placetype":"venue"
},
  "geometry": {"coordinates":[5.5003190041,50.6149749756],"type":"Point"}
}