{
  "type": "Feature",
  "properties": {
    "addr:full":"Rue Leopold Thonon 49 Herstal (liers) Li\u00e8ge 4042",
    "addr:housenumber":"49",
    "addr:postcode":"4042",
    "addr:street":"Rue Leopold Thonon",
    "iso:country":"BE",
    "sg:address":"Rue Leopold Thonon 49",
    "sg:city":"Herstal (liers)",
    "sg:classifiers":[
        {
            "category":"Exhibition Hall",
            "type":"Public Place"
        }
    ],
    "sg:phone":"+32 4 278 71 81",
    "sg:postcode":"4042",
    "sg:province":"Li\u00e8ge",
    "sg:tags":[
        "stand"
    ],
    "wof:name":"Viviani A",
    "wof:placetype":"venue"
},
  "geometry": {"coordinates":[5.5604529381,50.6967124939],"type":"Point"}
}