{
  "type": "Feature",
  "properties": {
    "addr:full":"Waterloose Steenweg 678 Ukkel/uccle Bruxelles-Capitale 1180",
    "addr:housenumber":"678",
    "addr:postcode":"1180",
    "addr:street":"Waterloose Steenweg;/",
    "iso:country":"BE",
    "sg:address":"Waterloose Steenweg 678",
    "sg:city":"Ukkel/uccle",
    "sg:classifiers":[
        {
            "category":"Fast Food",
            "type":"Food & Drink"
        }
    ],
    "sg:phone":"+32 2 649 88 99",
    "sg:postcode":"1180",
    "sg:province":"Bruxelles-Capitale",
    "sg:tags":[
        "meeneem",
        "restaurant"
    ],
    "wof:name":"Restaurant Anlo Ii",
    "wof:placetype":"venue"
},
  "geometry": {"coordinates":[4.3669967651,50.8165130615],"type":"Point"}
}