{
  "type": "Feature",
  "properties": {
    "iso:country":"BE",
    "sg:address":"Kuringersteenweg 544",
    "sg:city":"Hasselt",
    "sg:classifiers":[
        {
            "category":"Manufacturing",
            "subcategory":"Furniture",
            "type":"Manufacturing & Wholesale Goods"
        }
    ],
    "sg:phone":"+32 11 25 37 18",
    "sg:postcode":"3500",
    "sg:province":"Limburg",
    "sg:tags":[
        "design",
        "-"
    ],
    "wof:name":"Hermans Interieur Bvba",
    "wof:placetype":"venue"
},
  "geometry": {"coordinates":[5.3112659454,50.9367523193],"type":"Point"}
}