{
  "type": "Feature",
  "properties": {
    "addr:full":"Oude Keerbergsebaan 8 Rijmenam Antwerpen 2820",
    "addr:housenumber":"8",
    "addr:postcode":"2820",
    "addr:street":"Oude Keerbergsebaan",
    "iso:country":"BE",
    "sg:address":"Oude Keerbergsebaan 8",
    "sg:city":"Rijmenam",
    "sg:classifiers":[
        {
            "category":"Home & Garden",
            "subcategory":"Furniture",
            "type":"Retail Goods"
        }
    ],
    "sg:phone":"+32 15 51 80 50",
    "sg:postcode":"2820",
    "sg:province":"Antwerpen",
    "sg:tags":[
        "wood"
    ],
    "wof:name":"De Meulemeester Nv",
    "wof:placetype":"venue"
},
  "geometry": {"coordinates":[4.5942111015,51.0026473999],"type":"Point"}
}