{
  "type": "Feature",
  "properties": {
    "iso:country":"BE",
    "sg:address":"Herbesthaler Strasse 124",
    "sg:city":"Eupen",
    "sg:classifiers":[
        {
            "category":"Restaurant",
            "type":"Food & Drink"
        }
    ],
    "sg:phone":"+32 87 56 00 62",
    "sg:postcode":"4700",
    "sg:province":"Li\u00e8ge",
    "wof:name":"Taco",
    "wof:placetype":"venue"
},
  "geometry": {"coordinates":[6.0174179077,50.6383934021],"type":"Point"}
}