{
  "type": "Feature",
  "properties": {
    "addr:full":"Kerkhovensesteenweg 433 Lommel Limburg 3920",
    "addr:housenumber":"433",
    "addr:postcode":"3920",
    "addr:street":"Kerkhovensesteenweg",
    "iso:country":"BE",
    "sg:address":"Kerkhovensesteenweg 433",
    "sg:city":"Lommel",
    "sg:orig_category":"Slagers",
    "sg:phone":"+32 11 34 18 65",
    "sg:postcode":"3920",
    "sg:province":"Limburg",
    "wof:name":"Eddy Claes",
    "wof:placetype":"venue"
},
  "geometry": {"coordinates":[5.2663908005,51.1618423462],"type":"Point"}
}