{
  "type": "Feature",
  "properties": {
    "addr:full":"Putse Baan 93 Antwerpen Antwerpen 2040",
    "addr:housenumber":"93",
    "addr:postcode":"2040",
    "addr:street":"Putse Baan",
    "iso:country":"BE",
    "sg:address":"Putse Baan 93",
    "sg:city":"Antwerpen",
    "sg:classifiers":[
        {
            "category":"Manufacturing",
            "subcategory":"Rubber & Plastics",
            "type":"Manufacturing & Wholesale Goods"
        }
    ],
    "sg:phone":"+32 3 568 08 13",
    "sg:postcode":"2040",
    "sg:province":"Antwerpen",
    "sg:tags":[
        "pipe",
        "-"
    ],
    "wof:name":"Versteden Kunststoftechniek Bvba",
    "wof:placetype":"venue"
},
  "geometry": {"coordinates":[4.3311300278,51.3580284119],"type":"Point"}
}