{
  "type": "Feature",
  "properties": {
    "addr:full":"Jottrandlaan 55 Sint-joost-ten-node/saint-josse-ten-noode Bruxelles-Capitale 1210",
    "addr:housenumber":"55",
    "addr:postcode":"1210",
    "addr:street":"Jottrandlaan",
    "iso:country":"BE",
    "sg:address":"Jottrandlaan 55",
    "sg:city":"Sint-joost-ten-node/saint-josse-ten-noode",
    "sg:classifiers":[
        {
            "category":"Cafe",
            "type":"Food & Drink"
        }
    ],
    "sg:phone":"+32 2 217 83 10",
    "sg:postcode":"1210",
    "sg:province":"Bruxelles-Capitale",
    "sg:tags":[
        "caf\u00e9s"
    ],
    "wof:name":"Caf\u00c9 Bon Accueil",
    "wof:placetype":"venue"
},
  "geometry": {"coordinates":[4.3772859573,50.8527755737],"type":"Point"}
}