{
  "type": "Feature",
  "properties": {
    "addr:full":"Luikersteenweg 97 Tongeren Limburg 3700",
    "addr:housenumber":"97",
    "addr:postcode":"3700",
    "addr:street":"Luikersteenweg",
    "iso:country":"BE",
    "sg:address":"Luikersteenweg 97",
    "sg:city":"Tongeren",
    "sg:classifiers":[
        {
            "category":"Food & Beverages",
            "subcategory":"Groceries & Convenience Stores",
            "type":"Retail Goods"
        }
    ],
    "sg:phone":"+32 12 23 19 89",
    "sg:postcode":"3700",
    "sg:province":"Limburg",
    "sg:tags":[
        "grocer"
    ],
    "wof:name":"Merken",
    "wof:placetype":"venue"
},
  "geometry": {"coordinates":[5.4608931541,50.7718544006],"type":"Point"}
}