{
  "type": "Feature",
  "properties": {
    "addr:full":"Vlezenbeeklaan 91 Sint-pieters-leeuw Vlaams-Brabant 1600",
    "addr:housenumber":"91",
    "addr:postcode":"1600",
    "addr:street":"Vlezenbeeklaan",
    "iso:country":"BE",
    "sg:address":"Vlezenbeeklaan 91",
    "sg:city":"Sint-pieters-leeuw",
    "sg:classifiers":[
        {
            "category":"Bars & Pubs",
            "type":"Food & Drink"
        }
    ],
    "sg:phone":"+32 2 377 89 20",
    "sg:postcode":"1600",
    "sg:province":"Vlaams-Brabant",
    "wof:name":"Vagevuur",
    "wof:placetype":"venue"
},
  "geometry": {"coordinates":[4.2401828766,50.7965240479],"type":"Point"}
}