{
  "type": "Feature",
  "properties": {
    "addr:full":"Avenue De La Paix 55 Ans Li\u00e8ge 4430",
    "addr:housenumber":"55",
    "addr:postcode":"4430",
    "addr:street":"Avenue De La Paix",
    "iso:country":"BE",
    "sg:address":"Avenue De La Paix 55",
    "sg:city":"Ans",
    "sg:classifiers":[
        {
            "category":"Arena",
            "subcategory":"Sports Club",
            "type":"Entertainment"
        }
    ],
    "sg:phone":"+32 4 263 04 90",
    "sg:postcode":"4430",
    "sg:province":"Li\u00e8ge",
    "sg:tags":[
        "de"
    ],
    "wof:name":"J.c. Loncin",
    "wof:placetype":"venue"
},
  "geometry": {"coordinates":[5.5225691795,50.6642532349],"type":"Point"}
}