{
  "type": "Feature",
  "properties": {
    "addr:full":"Lage Kaart 266 Brasschaat Antwerpen 2930",
    "addr:housenumber":"266",
    "addr:postcode":"2930",
    "addr:street":"Lage Kaart",
    "iso:country":"BE",
    "sg:address":"Lage Kaart 266",
    "sg:city":"Brasschaat",
    "sg:orig_category":"Enseignement maternel and primaire",
    "sg:phone":"+32 3 651 50 25",
    "sg:postcode":"2930",
    "sg:province":"Antwerpen",
    "wof:name":"Vrije Basisschool",
    "wof:placetype":"venue"
},
  "geometry": {"coordinates":[4.4811449051,51.3003082275],"type":"Point"}
}