{
  "type": "Feature",
  "properties": {
    "iso:country":"BE",
    "sg:address":"Veurnseweg 525",
    "sg:city":"Ieper",
    "sg:classifiers":[
        {
            "category":"Restaurant",
            "type":"Food & Drink"
        }
    ],
    "sg:phone":"+32 57 42 37 41",
    "sg:postcode":"8906",
    "sg:province":"West-Vlaanderen",
    "wof:name":"De Warande",
    "wof:placetype":"venue"
},
  "geometry": {"coordinates":[2.8180809021,50.8855781555],"type":"Point"}
}