{
  "type": "Feature",
  "properties": {
    "iso:country":"BE",
    "sg:address":"Rue De Couillet 93",
    "sg:city":"Chatelet",
    "sg:orig_category":"V\u00e9hicules automobiles",
    "sg:phone":"+32 71 39 31 58",
    "sg:postcode":"6200",
    "sg:province":"Hainaut",
    "wof:name":"Ch\u00c2telet Motor Service",
    "wof:placetype":"venue"
},
  "geometry": {"coordinates":[4.5119018555,50.4019508362],"type":"Point"}
}