{
  "type": "Feature",
  "properties": {
    "addr:full":"Place Henri-collignon 10ba Onhaye Namur 5520",
    "addr:housenumber":"10ba",
    "addr:postcode":"5520",
    "addr:street":"Place Henri-Collignon",
    "iso:country":"BE",
    "sg:address":"Place Henri-collignon 10ba",
    "sg:city":"Onhaye",
    "sg:orig_category":"Peinture. Rev\u00eatements pour sols and murs",
    "sg:phone":"+32 82 64 61 12",
    "sg:postcode":"5520",
    "sg:province":"Namur",
    "wof:name":"Thierry Petit",
    "wof:placetype":"venue"
},
  "geometry": {"coordinates":[4.8402600288,50.2425193787],"type":"Point"}
}