{
  "type": "Feature",
  "properties": {
    "addr:full":"Nerenhoek 3 Beveren Oost-Vlaanderen 9120",
    "addr:housenumber":"3",
    "addr:postcode":"9120",
    "addr:street":"Nerenhoek",
    "iso:country":"BE",
    "sg:address":"Nerenhoek 3",
    "sg:city":"Beveren",
    "sg:orig_category":"Eleveurs and marchands de porcs. Eleveurs de bovins",
    "sg:phone":"+32 3 755 05 16",
    "sg:postcode":"9120",
    "sg:province":"Oost-Vlaanderen",
    "wof:name":"Herman Maes",
    "wof:placetype":"venue"
},
  "geometry": {"coordinates":[4.2097358704,51.2228126526],"type":"Point"}
}