{
  "type": "Feature",
  "properties": {
    "addr:full":"Leuvensebaan 168 Holsbeek Vlaams-Brabant 3220",
    "addr:housenumber":"168",
    "addr:postcode":"3220",
    "addr:street":"Leuvensebaan",
    "iso:country":"BE",
    "sg:address":"Leuvensebaan 168",
    "sg:city":"Holsbeek",
    "sg:classifiers":[
        {
            "category":"Real Estate",
            "subcategory":"Architect",
            "type":"Services"
        }
    ],
    "sg:phone":"+32 496 12 25 95",
    "sg:postcode":"3220",
    "sg:province":"Vlaams-Brabant",
    "wof:name":"Gijsemans P",
    "wof:placetype":"venue"
},
  "geometry": {"coordinates":[4.7359619141,50.9139671326],"type":"Point"}
}