{
  "type": "Feature",
  "properties": {
    "addr:full":"Rue Joseph Dupont 10 Brussel/bruxelles Bruxelles-Capitale 1000",
    "addr:housenumber":"10",
    "addr:postcode":"1000",
    "addr:street":"Rue Joseph Dupont;/",
    "iso:country":"BE",
    "sg:address":"Rue Joseph Dupont 10",
    "sg:city":"Brussel/bruxelles",
    "sg:orig_category":"Assistances juridiques. Conseillers fiscaux",
    "sg:phone":"+32 2 514 32 98",
    "sg:postcode":"1000",
    "sg:province":"Bruxelles-Capitale",
    "wof:name":"Anubis Patrim. Plan.cons.",
    "wof:placetype":"venue"
},
  "geometry": {"coordinates":[4.3554530144,50.8384170532],"type":"Point"}
}