{
  "type": "Feature",
  "properties": {
    "iso:country":"BE",
    "sg:address":"Brusselsesteenweg 441",
    "sg:city":"Melle",
    "sg:orig_category":"Elektrische installaties voor woningen Loodgieterij, verwarming and sanitaire installaties Schoonmaa",
    "sg:phone":"+32 9 252 50 15",
    "sg:postcode":"9090",
    "sg:province":"Oost-Vlaanderen",
    "wof:name":"Francis & Tytgat",
    "wof:placetype":"venue"
},
  "geometry": {"coordinates":[3.8086578846,50.9993629456],"type":"Point"}
}