{
  "type": "Feature",
  "properties": {
    "iso:country":"BE",
    "sg:address":"Diestersteenweg 352",
    "sg:city":"Maaseik",
    "sg:orig_category":"Woningbouw",
    "sg:phone":"+32 89 56 78 61",
    "sg:postcode":"3680",
    "sg:province":"Limburg",
    "wof:name":"Christiaan Kessels",
    "wof:placetype":"venue"
},
  "geometry": {"coordinates":[5.7496099472,51.1019210815],"type":"Point"}
}