{
  "type": "Feature",
  "properties": {
    "iso:country":"BE",
    "sg:address":"Jutestraat 5",
    "sg:city":"Waregem",
    "sg:orig_category":"Paramedische behandelingen",
    "sg:phone":"+32 56 61 42 39",
    "sg:postcode":"8790",
    "sg:province":"West-Vlaanderen",
    "wof:name":"Sylvie Hebbrecht",
    "wof:placetype":"venue"
},
  "geometry": {"coordinates":[3.4350960255,50.8950538635],"type":"Point"}
}