{
  "type": "Feature",
  "properties": {
    "iso:country":"BE",
    "sg:address":"Tentoonstellingslaan 36",
    "sg:city":"Antwerpen",
    "sg:classifiers":[
        {
            "category":"Food Court",
            "type":"Food & Drink"
        }
    ],
    "sg:phone":"+32 3 454 19 16",
    "sg:postcode":"2020",
    "sg:province":"Antwerpen",
    "sg:tags":[
        "product",
        "related"
    ],
    "wof:name":"B-export Nv",
    "wof:placetype":"venue"
},
  "geometry": {"coordinates":[4.3913269043,51.1921958923],"type":"Point"}
}