{
  "type": "Feature",
  "properties": {
    "addr:full":"Menenstraat 12b Wervik West-Vlaanderen 8940",
    "addr:housenumber":"12b",
    "addr:postcode":"8940",
    "addr:street":"Menenstraat",
    "iso:country":"BE",
    "sg:address":"Menenstraat 12b",
    "sg:city":"Wervik",
    "sg:orig_category":"Banques and organismes de cr\u00e9dit",
    "sg:phone":"+32 56 51 20 49",
    "sg:postcode":"8940",
    "sg:province":"West-Vlaanderen",
    "wof:name":"Kbc",
    "wof:placetype":"venue"
},
  "geometry": {"coordinates":[3.0798950195,50.8098449707],"type":"Point"}
}