{
  "type": "Feature",
  "properties": {
    "addr:full":"Av. C. De Gerlache 40 Li\u00e8ge Li\u00e8ge 4000",
    "addr:housenumber":"40",
    "addr:postcode":"4000",
    "addr:street":"Av. C. De Gerlache",
    "iso:country":"BE",
    "sg:address":"Av. C. De Gerlache 40",
    "sg:city":"Li\u00e8ge",
    "sg:orig_category":"Acoustics Planning, Planning Offices For Acoustics",
    "sg:phone":"+32 4 253 64 94",
    "sg:postcode":"4000",
    "sg:province":"Li\u00e8ge",
    "wof:name":"Aba Son Sprl",
    "wof:placetype":"venue"
},
  "geometry": {"coordinates":[5.5724301338,50.6170768738],"type":"Point"}
}