{
  "type": "Feature",
  "properties": {
    "addr:full":"Chauss\u00e9e De Namur 144 Gembloux-sur-orneau (gembloux) Namur 5030",
    "addr:housenumber":"144",
    "addr:postcode":"5030",
    "addr:street":"Chausse\u0301E De Namur;Namur",
    "iso:country":"BE",
    "sg:address":"Chauss\u00e9e De Namur 144",
    "sg:city":"Gembloux-sur-orneau (gembloux)",
    "sg:classifiers":[
        {
            "category":"Building & Trades",
            "subcategory":"Plumbing",
            "type":"Services"
        }
    ],
    "sg:phone":"+32 81 61 25 56",
    "sg:postcode":"5030",
    "sg:province":"Namur",
    "sg:tags":[
        "repair",
        "mainten",
        "-",
        "central",
        "heating"
    ],
    "wof:name":"Dethier P",
    "wof:placetype":"venue"
},
  "geometry": {"coordinates":[4.7097148895,50.5519981384],"type":"Point"}
}