{
  "type": "Feature",
  "properties": {
    "iso:country":"BE",
    "sg:address":"Rijksweg 408",
    "sg:city":"Maasmechelen",
    "sg:orig_category":"Quincailleries",
    "sg:phone":"+32 89 77 14 64",
    "sg:postcode":"3630",
    "sg:province":"Limburg",
    "wof:name":"2 The Point",
    "wof:placetype":"venue"
},
  "geometry": {"coordinates":[5.6958107948,50.9654998779],"type":"Point"}
}