{
  "type": "Feature",
  "properties": {
    "iso:country":"BE",
    "sg:address":"Peperstraat 13",
    "sg:city":"Herzele",
    "sg:orig_category":"Equipement photographique. Studios photographiques",
    "sg:phone":"+32 53 62 67 21",
    "sg:postcode":"9550",
    "sg:province":"Oost-Vlaanderen",
    "wof:name":"Foto Perfectie",
    "wof:placetype":"venue"
},
  "geometry": {"coordinates":[3.8944020271,50.8846206665],"type":"Point"}
}