{
  "type": "Feature",
  "properties": {
    "iso:country":"BE",
    "sg:address":"Rue De L'ecole 46",
    "sg:city":"Rebecq (quenast)",
    "sg:classifiers":[
        {
            "category":"Building & Trades",
            "subcategory":"Landscaping Services",
            "type":"Services"
        }
    ],
    "sg:phone":"+32 477 84 27 75",
    "sg:postcode":"1430",
    "sg:province":"Brabant Wallon",
    "sg:tags":[
        "architect",
        "landscape"
    ],
    "wof:name":"A B C Gardens",
    "wof:placetype":"venue"
},
  "geometry": {"coordinates":[4.1317100525,50.6643714905],"type":"Point"}
}