{
  "type": "Feature",
  "properties": {
    "addr:full":"Geitenhoek 1 Maarkedal Oost-Vlaanderen 9680",
    "addr:housenumber":"1",
    "addr:postcode":"9680",
    "addr:street":"Geitenhoek",
    "iso:country":"BE",
    "sg:address":"Geitenhoek 1",
    "sg:city":"Maarkedal",
    "sg:orig_category":"Eleveurs de bovins",
    "sg:phone":"+32 55 31 17 62",
    "sg:postcode":"9680",
    "sg:province":"Oost-Vlaanderen",
    "wof:name":"Joan Declercq",
    "wof:placetype":"venue"
},
  "geometry": {"coordinates":[3.6156189442,50.8220062256],"type":"Point"}
}