{
  "type": "Feature",
  "properties": {
    "addr:full":"Chauss\u00c9e De Luingne 2 Moeskroen/mouscron Hainaut 7712",
    "addr:housenumber":"2",
    "addr:postcode":"7712",
    "addr:street":"Chausse\u0301E De Luingne",
    "iso:country":"BE",
    "sg:address":"Chauss\u00c9e De Luingne 2",
    "sg:city":"Moeskroen/mouscron",
    "sg:orig_category":"Banques and organismes de cr\u00e9dit",
    "sg:phone":"+32 56 33 17 59",
    "sg:postcode":"7712",
    "sg:province":"Hainaut",
    "wof:name":"Fortis",
    "wof:placetype":"venue"
},
  "geometry": {"coordinates":[3.2535879612,50.714931488],"type":"Point"}
}