{
  "type": "Feature",
  "properties": {
    "iso:country":"BE",
    "sg:address":"Kelsbeek 57",
    "sg:city":"Sint-truiden",
    "sg:orig_category":"Fruitteelt Varkenskwekers",
    "sg:phone":"+32 11 68 40 28",
    "sg:postcode":"3800",
    "sg:province":"Limburg",
    "wof:name":"Joseph Motmans",
    "wof:placetype":"venue"
},
  "geometry": {"coordinates":[5.1843481064,50.8547744751],"type":"Point"}
}