{
  "type": "Feature",
  "properties": {
    "iso:country":"BE",
    "sg:address":"Ter Zwanekerke 62",
    "sg:city":"Brugge (sint-michiels)",
    "sg:classifiers":[
        {
            "category":"Communications",
            "type":"Services"
        }
    ],
    "sg:phone":"+32 50 38 19 82",
    "sg:postcode":"8200",
    "sg:province":"West-Vlaanderen",
    "sg:tags":[
        "translator"
    ],
    "wof:name":"Solo Espa\u00d1ol",
    "wof:placetype":"venue"
},
  "geometry": {"coordinates":[3.2138090134,51.1889152527],"type":"Point"}
}