{
  "type": "Feature",
  "properties": {
    "addr:full":"Laarstraat 21 Landen Vlaams-Brabant 3400",
    "addr:housenumber":"21",
    "addr:postcode":"3400",
    "addr:street":"Laarstraat",
    "iso:country":"BE",
    "sg:address":"Laarstraat 21",
    "sg:city":"Landen",
    "sg:orig_category":"Enseignement maternel and primaire",
    "sg:phone":"+32 16 78 81 62",
    "sg:postcode":"3400",
    "sg:province":"Vlaams-Brabant",
    "wof:name":"Gemeentelijke Basisschool",
    "wof:placetype":"venue"
},
  "geometry": {"coordinates":[5.0348739624,50.765460968],"type":"Point"}
}