{
  "type": "Feature",
  "properties": {
    "addr:full":"Stationlaan 8-5 Bilzen Limburg 3740",
    "addr:housenumber":"8-5",
    "addr:postcode":"3740",
    "addr:street":"Stationlaan",
    "iso:country":"BE",
    "sg:address":"Stationlaan 8-5",
    "sg:city":"Bilzen",
    "sg:classifiers":[
        {
            "category":"Real Estate",
            "subcategory":"Architect",
            "type":"Services"
        }
    ],
    "sg:phone":"+32 89 51 50 45",
    "sg:postcode":"3740",
    "sg:province":"Limburg",
    "wof:name":"Architectenbureau J Nelissen",
    "wof:placetype":"venue"
},
  "geometry": {"coordinates":[5.5129218102,50.869682312],"type":"Point"}
}