{
  "type": "Feature",
  "properties": {
    "addr:full":"Rue Fernand Neuray 27 Bruxelles (ixelles) Bruxelles-Capitale 1050",
    "addr:housenumber":"27",
    "addr:postcode":"1050",
    "addr:street":"Rue Fernand Neuray",
    "iso:country":"BE",
    "sg:address":"Rue Fernand Neuray 27",
    "sg:city":"Bruxelles (ixelles)",
    "sg:classifiers":[
        {
            "category":"Professional",
            "subcategory":"Management & Consulting",
            "type":"Services"
        }
    ],
    "sg:phone":"+32 2 346 31 01",
    "sg:postcode":"1050",
    "sg:province":"Bruxelles-Capitale",
    "sg:tags":[
        "consultant",
        "agency",
        "advertising"
    ],
    "wof:name":"Orlow-andersen",
    "wof:placetype":"venue"
},
  "geometry": {"coordinates":[4.3559470177,50.8207092285],"type":"Point"}
}