{
  "type": "Feature",
  "properties": {
    "addr:full":"Rue De La Station 121 Les Bons Villers (r\u00eaves) Hainaut 6210",
    "addr:housenumber":"121",
    "addr:postcode":"6210",
    "addr:street":"Rue De La Station",
    "iso:country":"BE",
    "sg:address":"Rue De La Station 121",
    "sg:city":"Les Bons Villers (r\u00eaves)",
    "sg:classifiers":[
        {
            "category":"Retail",
            "subcategory":"Event Space",
            "type":"Services"
        }
    ],
    "sg:postcode":"6210",
    "sg:province":"Hainaut",
    "sg:tags":[
        "organisation"
    ],
    "wof:name":"Aux 4 Chapitres",
    "wof:placetype":"venue"
},
  "geometry": {"coordinates":[4.4120059013,50.5501365662],"type":"Point"}
}