{
  "type": "Feature",
  "properties": {
    "iso:country":"BE",
    "sg:address":"Van Schoonbekestraat 125",
    "sg:city":"Antwerpen",
    "sg:orig_category":"Advocaten and juridische adviseurs",
    "sg:phone":"+32 3 237 59 93",
    "sg:postcode":"2018",
    "sg:province":"Antwerpen",
    "wof:name":"Michel Van Hentenrijk",
    "wof:placetype":"venue"
},
  "geometry": {"coordinates":[4.404979229,51.2003364563],"type":"Point"}
}