{
  "type": "Feature",
  "properties": {
    "iso:country":"BE",
    "sg:address":"Belseledorp 95 Box 2",
    "sg:city":"Sint-niklaas (belsele)",
    "sg:classifiers":[
        {
            "category":"Professional",
            "subcategory":"Advertising",
            "type":"Services"
        }
    ],
    "sg:phone":"+32 475 80 89 96",
    "sg:postcode":"9111",
    "sg:province":"Oost-Vlaanderen",
    "sg:tags":[
        "aerial",
        "-"
    ],
    "wof:name":"Air Man Ballooning Bvba",
    "wof:placetype":"venue"
},
  "geometry": {"coordinates":[4.0905909538,51.1465530396],"type":"Point"}
}