{
  "type": "Feature",
  "properties": {
    "addr:full":"Sint-elooisplein 2 Waregem (sint-eloois-vijve) West-Vlaanderen 8793",
    "addr:housenumber":"2",
    "addr:postcode":"8793",
    "addr:street":"Sint-Elooisplein",
    "iso:country":"BE",
    "sg:address":"Sint-elooisplein 2",
    "sg:city":"Waregem (sint-eloois-vijve)",
    "sg:classifiers":[
        {
            "category":"Travel",
            "subcategory":"Hotels & Motels",
            "type":"Entertainment"
        }
    ],
    "sg:phone":"+32 56 60 95 96",
    "sg:postcode":"8793",
    "sg:province":"West-Vlaanderen",
    "wof:name":"De Jager",
    "wof:placetype":"venue"
},
  "geometry": {"coordinates":[3.4039289951,50.9058952332],"type":"Point"}
}