{
  "type": "Feature",
  "properties": {
    "addr:full":"Kammenstraat 22 Aalst Oost-Vlaanderen 9308",
    "addr:housenumber":"22",
    "addr:postcode":"9308",
    "addr:street":"Kammenstraat",
    "iso:country":"BE",
    "sg:address":"Kammenstraat 22",
    "sg:city":"Aalst",
    "sg:orig_category":"Dakwerken",
    "sg:phone":"+32 53 77 73 08",
    "sg:postcode":"9308",
    "sg:province":"Oost-Vlaanderen",
    "wof:name":"H. Ghijsels",
    "wof:placetype":"venue"
},
  "geometry": {"coordinates":[4.0347590446,50.9603500366],"type":"Point"}
}