{
  "type": "Feature",
  "properties": {
    "addr:full":"Geraardsbergsestraat 127ba Dilbeek Vlaams-Brabant 1703",
    "addr:postcode":"1703",
    "addr:street":"Geraardsbergsestraat;Vlaams-Brabant",
    "iso:country":"BE",
    "sg:address":"Geraardsbergsestraat 127ba",
    "sg:city":"Dilbeek",
    "sg:orig_category":"Dakwerken Woningbouw",
    "sg:phone":"+32 2 569 60 68",
    "sg:postcode":"1703",
    "sg:province":"Vlaams-Brabant",
    "wof:name":"Bartholomeus Spapens",
    "wof:placetype":"venue"
},
  "geometry": {"coordinates":[4.191754818,50.8335113525],"type":"Point"}
}