{
  "type": "Feature",
  "properties": {
    "addr:full":"Rue Des Cent Bonniers 68 Anderlues Hainaut 6150",
    "addr:housenumber":"68",
    "addr:postcode":"6150",
    "addr:street":"Rue Des Cent Bonniers",
    "iso:country":"BE",
    "sg:address":"Rue Des Cent Bonniers 68",
    "sg:city":"Anderlues",
    "sg:orig_category":"Enseignement maternel and primaire",
    "sg:phone":"+32 71 52 70 74",
    "sg:postcode":"6150",
    "sg:province":"Hainaut",
    "wof:name":"Ecole Fond. Communale",
    "wof:placetype":"venue"
},
  "geometry": {"coordinates":[4.2755298615,50.3894920349],"type":"Point"}
}