{
  "type": "Feature",
  "properties": {
    "addr:full":"Kruishuisstraat 36 Turnhout Antwerpen 2300",
    "addr:housenumber":"36",
    "addr:postcode":"2300",
    "addr:street":"Kruishuisstraat",
    "iso:country":"BE",
    "sg:address":"Kruishuisstraat 36",
    "sg:city":"Turnhout",
    "sg:orig_category":"Tuinen",
    "sg:phone":"+32 14 41 46 31",
    "sg:postcode":"2300",
    "sg:province":"Antwerpen",
    "wof:name":"Rens Tuinbouw & Onderhoud",
    "wof:placetype":"venue"
},
  "geometry": {"coordinates":[4.940718174,51.3204421997],"type":"Point"}
}