{
  "type": "Feature",
  "properties": {
    "addr:full":"Rue Des B\u00e9guines 15 Bruxelles (molenbeek-saint-jean) Bruxelles-Capitale 1080",
    "addr:housenumber":"15",
    "addr:postcode":"1080",
    "addr:street":"Rue Des Be\u0301Guines",
    "iso:country":"BE",
    "sg:address":"Rue Des B\u00e9guines 15",
    "sg:city":"Bruxelles (molenbeek-saint-jean)",
    "sg:classifiers":[
        {
            "category":"Shopping",
            "subcategory":"Books",
            "type":"Retail Goods"
        }
    ],
    "sg:phone":"+32 2 410 33 27",
    "sg:postcode":"1080",
    "sg:province":"Bruxelles-Capitale",
    "sg:tags":[
        "antiquarian",
        "trade"
    ],
    "wof:name":"Adcl",
    "wof:placetype":"venue"
},
  "geometry": {"coordinates":[4.3172187805,50.857749939],"type":"Point"}
}