{
  "type": "Feature",
  "properties": {
    "addr:full":"Putsesteenweg 71 Sint-katelijne-waver Antwerpen 2860",
    "addr:housenumber":"71",
    "addr:postcode":"2860",
    "addr:street":"Putsesteenweg",
    "iso:country":"BE",
    "sg:address":"Putsesteenweg 71",
    "sg:city":"Sint-katelijne-waver",
    "sg:orig_category":"Avocats and conseillers juridiques",
    "sg:phone":"+32 15 55 00 40",
    "sg:postcode":"2860",
    "sg:province":"Antwerpen",
    "wof:name":"D. Everaert",
    "wof:placetype":"venue"
},
  "geometry": {"coordinates":[4.5126161575,51.0348014832],"type":"Point"}
}