{
  "type": "Feature",
  "properties": {
    "addr:full":"12-14 Rue Americaine Bruxelles Bruxelles-Capitale 1060",
    "addr:housenumber":"12-14",
    "addr:postcode":"1060",
    "addr:street":"Rue Americaine",
    "iso:country":"BE",
    "sg:address":"12-14 Rue Americaine",
    "sg:city":"Bruxelles",
    "sg:classifiers":[
        {
            "category":"Autos & Motor Vehicles",
            "subcategory":"Automobile Sales",
            "type":"Retail Goods"
        }
    ],
    "sg:phone":"+32 2 538 26 88",
    "sg:postcode":"1060",
    "sg:province":"Bruxelles-Capitale",
    "sg:tags":[
        "equipment",
        "motor-cars",
        "transport"
    ],
    "wof:name":"Garage Vanspringel Et Fils Sa",
    "wof:placetype":"venue"
},
  "geometry": {"coordinates":[4.3552851677,50.8243751526],"type":"Point"}
}