{
  "type": "Feature",
  "properties": {
    "iso:country":"BE",
    "sg:address":"Avenue De La Pairelle 77 Box 11",
    "sg:city":"Namur",
    "sg:classifiers":[
        {
            "category":"Building & Trades",
            "subcategory":"Landscaping Services",
            "type":"Services"
        }
    ],
    "sg:postcode":"5000",
    "sg:province":"Namur",
    "sg:tags":[
        "gardening",
        "garden",
        "maintenance"
    ],
    "wof:name":"Jardins D'eric (les)",
    "wof:placetype":"venue"
},
  "geometry": {"coordinates":[4.8615670204,50.4378852844],"type":"Point"}
}