{
  "type": "Feature",
  "properties": {
    "addr:full":"Terlinden 208 Merchtem Vlaams-Brabant 1785",
    "addr:housenumber":"208",
    "addr:postcode":"1785",
    "addr:street":"Terlinden",
    "iso:country":"BE",
    "sg:address":"Terlinden 208",
    "sg:city":"Merchtem",
    "sg:orig_category":"Eleveurs de bovins",
    "sg:phone":"+32 52 37 38 03",
    "sg:postcode":"1785",
    "sg:province":"Vlaams-Brabant",
    "wof:name":"Edward Saerens",
    "wof:placetype":"venue"
},
  "geometry": {"coordinates":[4.2538051605,50.9711456299],"type":"Point"}
}