{
  "type": "Feature",
  "properties": {
    "iso:country":"BE",
    "sg:address":"Rue Cortil Moray 1",
    "sg:city":"Blegny",
    "sg:orig_category":"Brood, gebak and snoepgoed",
    "sg:phone":"+32 4 362 74 02",
    "sg:postcode":"4671",
    "sg:province":"Li\u00e8ge",
    "wof:name":"Boulangerie Massart",
    "wof:placetype":"venue"
},
  "geometry": {"coordinates":[5.6829018593,50.6529464722],"type":"Point"}
}