{
  "type": "Feature",
  "properties": {
    "addr:full":"Koningin Astridlaan 40 Kapellen Antwerpen 2950",
    "addr:housenumber":"40",
    "addr:postcode":"2950",
    "addr:street":"Koningin Astridlaan",
    "iso:country":"BE",
    "sg:address":"Koningin Astridlaan 40",
    "sg:city":"Kapellen",
    "sg:orig_category":"R\u00e9cup\u00e9ration de mati\u00e8res m\u00e9talliques recyclables and d\u00e9molisseurs de voitures. Entretien et r\u00e9parati",
    "sg:phone":"+32 3 664 12 62",
    "sg:postcode":"2950",
    "sg:province":"Antwerpen",
    "wof:name":"Fa. Michel",
    "wof:placetype":"venue"
},
  "geometry": {"coordinates":[4.4410700798,51.3125152588],"type":"Point"}
}