{
  "type": "Feature",
  "properties": {
    "iso:country":"BE",
    "sg:address":"Rue Des D\u00e9port\u00e9s 5",
    "sg:city":"Tournai (froidmont)",
    "sg:classifiers":[
        {
            "category":"Professional",
            "subcategory":"Accounting & Tax Preparation",
            "type":"Services"
        }
    ],
    "sg:phone":"+32 69 64 12 87",
    "sg:postcode":"7504",
    "sg:province":"Hainaut",
    "sg:tags":[
        "bookkeeper"
    ],
    "wof:name":"Wattiez Th-m",
    "wof:placetype":"venue"
},
  "geometry": {"coordinates":[3.3283588886,50.57654953],"type":"Point"}
}