{
  "type": "Feature",
  "properties": {
    "iso:country":"BE",
    "sg:address":"Kouter 77",
    "sg:city":"Deinze",
    "sg:orig_category":"Rev\u00eatements pour sols and murs. Peinture",
    "sg:phone":"+32 9 380 36 24",
    "sg:postcode":"9800",
    "sg:province":"Oost-Vlaanderen",
    "wof:name":"Roger Vercaemer",
    "wof:placetype":"venue"
},
  "geometry": {"coordinates":[3.5095789433,50.9905090332],"type":"Point"}
}