{
  "type": "Feature",
  "properties": {
    "iso:country":"BE",
    "sg:address":"Rue Hardichamps 1",
    "sg:city":"Mettet",
    "sg:orig_category":"Foundry Sand",
    "sg:phone":"+32 71 72 70 35",
    "sg:postcode":"5640",
    "sg:province":"Namur",
    "wof:name":"Sibelco Minerals And Chemicals S.a.",
    "wof:placetype":"venue"
},
  "geometry": {"coordinates":[4.6376209259,50.293586731],"type":"Point"}
}