{
  "type": "Feature",
  "properties": {
    "addr:full":"Ter Ferrants 11 Kuurne West-Vlaanderen 8520",
    "addr:housenumber":"11",
    "addr:postcode":"8520",
    "iso:country":"BE",
    "sg:address":"Ter Ferrants 11",
    "sg:city":"Kuurne",
    "sg:orig_category":"Supermarkten",
    "sg:postcode":"8520",
    "sg:province":"West-Vlaanderen",
    "wof:name":"Aldi",
    "wof:placetype":"venue"
},
  "geometry": {"coordinates":[3.2649819851,50.8496208191],"type":"Point"}
}