{
  "type": "Feature",
  "properties": {
    "iso:country":"BE",
    "sg:address":"Centrumstraat 46",
    "sg:city":"Zulte (olsene)",
    "sg:classifiers":[
        {
            "category":"Food & Beverages",
            "subcategory":"Groceries & Convenience Stores",
            "type":"Retail Goods"
        }
    ],
    "sg:phone":"+32 9 388 86 51",
    "sg:postcode":"9870",
    "sg:province":"Oost-Vlaanderen",
    "sg:tags":[
        "grocer"
    ],
    "wof:name":"Snoeck G",
    "wof:placetype":"venue"
},
  "geometry": {"coordinates":[3.4677898884,50.9338645935],"type":"Point"}
}