{
  "type": "Feature",
  "properties": {
    "addr:full":"Rue Nestor Royer 1 Crisnee Li\u00e8ge 4367",
    "addr:housenumber":"1",
    "addr:postcode":"4367",
    "addr:street":"Rue Nestor Royer",
    "iso:country":"BE",
    "sg:address":"Rue Nestor Royer 1",
    "sg:city":"Crisnee",
    "sg:orig_category":"Diensten voor huisdieren Huisdierenkwekers",
    "sg:phone":"+32 4 257 42 56",
    "sg:postcode":"4367",
    "sg:province":"Li\u00e8ge",
    "wof:name":"Domaine D'aubrac",
    "wof:placetype":"venue"
},
  "geometry": {"coordinates":[5.3849902153,50.7029914856],"type":"Point"}
}