{
  "type": "Feature",
  "properties": {
    "iso:country":"BE",
    "sg:address":"Heirbaan 99",
    "sg:city":"Arendonk",
    "sg:classifiers":[
        {
            "category":"Ferry Terminal",
            "type":"Transportation"
        }
    ],
    "sg:phone":"+32 14 67 03 65",
    "sg:postcode":"2370",
    "sg:province":"Antwerpen",
    "sg:tags":[
        "mast",
        "pylon"
    ],
    "wof:name":"Lauwers J",
    "wof:placetype":"venue"
},
  "geometry": {"coordinates":[5.0408759117,51.3235244751],"type":"Point"}
}