{
  "type": "Feature",
  "properties": {
    "iso:country":"BE",
    "sg:address":"Rue De Saint-georges 27",
    "sg:city":"Seneffe",
    "sg:orig_category":"Boucheries",
    "sg:phone":"+32 67 87 71 44",
    "sg:postcode":"7181",
    "sg:province":"Hainaut",
    "wof:name":"Boucherie Florent",
    "wof:placetype":"venue"
},
  "geometry": {"coordinates":[4.2552318573,50.5550956726],"type":"Point"}
}