{
  "type": "Feature",
  "properties": {
    "iso:country":"BE",
    "sg:address":"Houtstraat 3",
    "sg:city":"Westerlo",
    "sg:orig_category":"Kantoormateriaal Gh Muziekinstrumenten",
    "sg:phone":"+32 14 57 59 11",
    "sg:postcode":"2260",
    "sg:province":"Antwerpen",
    "wof:name":"Roland Dg Benelux",
    "wof:placetype":"venue"
},
  "geometry": {"coordinates":[4.9112768173,51.0883636475],"type":"Point"}
}