{
  "type": "Feature",
  "properties": {
    "addr:full":"Kazernestraat 7 Menen West-Vlaanderen 8930",
    "addr:housenumber":"7",
    "addr:postcode":"8930",
    "addr:street":"Kazernestraat",
    "iso:country":"BE",
    "sg:address":"Kazernestraat 7",
    "sg:city":"Menen",
    "sg:orig_category":"Entreprises de travail adapt\u00e9",
    "sg:phone":"+32 56 52 00 84",
    "sg:postcode":"8930",
    "sg:province":"West-Vlaanderen",
    "wof:name":"Integraal",
    "wof:placetype":"venue"
},
  "geometry": {"coordinates":[3.1210830212,50.7985153198],"type":"Point"}
}