{
  "type": "Feature",
  "properties": {
    "addr:full":"Rue D'angleterre 13 Chimay Hainaut 6460",
    "addr:housenumber":"13",
    "addr:postcode":"6460",
    "addr:street":"Rue D'Angleterre",
    "iso:country":"BE",
    "sg:address":"Rue D'angleterre 13",
    "sg:city":"Chimay",
    "sg:orig_category":"Boucheries",
    "sg:phone":"+32 60 21 11 49",
    "sg:postcode":"6460",
    "sg:province":"Hainaut",
    "wof:name":"Denis Hardy",
    "wof:placetype":"venue"
},
  "geometry": {"coordinates":[4.3148641586,50.0484161377],"type":"Point"}
}