{
  "type": "Feature",
  "properties": {
    "iso:country":"BE",
    "sg:address":"John F. Kennedylaan 24",
    "sg:city":"Aartselaar",
    "sg:classifiers":[
        {
            "category":"Cafe",
            "type":"Food & Drink"
        }
    ],
    "sg:phone":"+32 3 877 07 51",
    "sg:postcode":"2630",
    "sg:province":"Antwerpen",
    "sg:tags":[
        "caf\u00e9s"
    ],
    "wof:name":"Piet Pot",
    "wof:placetype":"venue"
},
  "geometry": {"coordinates":[4.3875098228,51.1406784058],"type":"Point"}
}