{
  "type": "Feature",
  "properties": {
    "addr:full":"Stationsplein 30 Herentals Antwerpen 2200",
    "addr:housenumber":"30",
    "addr:postcode":"2200",
    "addr:street":"Stationsplein",
    "iso:country":"BE",
    "sg:address":"Stationsplein 30",
    "sg:city":"Herentals",
    "sg:orig_category":"Farmaceutische producten Gh",
    "sg:phone":"+32 14 23 04 77",
    "sg:postcode":"2200",
    "sg:province":"Antwerpen",
    "wof:name":"Osteon",
    "wof:placetype":"venue"
},
  "geometry": {"coordinates":[4.8300938606,51.1810684204],"type":"Point"}
}