{
  "type": "Feature",
  "properties": {
    "addr:full":"Ernest Cambierlaan 107 Schaarbeek/schaerbeek Bruxelles-Capitale 1030",
    "addr:housenumber":"107",
    "addr:postcode":"1030",
    "addr:street":"Ernest Cambierlaan",
    "iso:country":"BE",
    "sg:address":"Ernest Cambierlaan 107",
    "sg:city":"Schaarbeek/schaerbeek",
    "sg:classifiers":[
        {
            "category":"Insurance",
            "subcategory":"Insurance Agent",
            "type":"Services"
        }
    ],
    "sg:phone":"+32 2 705 30 75",
    "sg:postcode":"1030",
    "sg:province":"Bruxelles-Capitale",
    "sg:tags":[
        "verzekeringsmakelaars",
        "expert"
    ],
    "wof:name":"Anna Falzone",
    "wof:placetype":"venue"
},
  "geometry": {"coordinates":[4.3952660561,50.8568153381],"type":"Point"}
}