{
  "type": "Feature",
  "properties": {
    "iso:country":"BE",
    "sg:address":"Koophandelstraat 29 Box 202",
    "sg:city":"Lokeren",
    "sg:classifiers":[
        {
            "category":"Real Estate",
            "subcategory":"Architect",
            "type":"Services"
        }
    ],
    "sg:phone":"+32 9 348 25 40",
    "sg:postcode":"9160",
    "sg:province":"Oost-Vlaanderen",
    "wof:name":"De Bock K",
    "wof:placetype":"venue"
},
  "geometry": {"coordinates":[3.9892179966,51.1075592041],"type":"Point"}
}