{
  "type": "Feature",
  "properties": {
    "iso:country":"BE",
    "sg:address":"Rue Ernest Gilot 49",
    "sg:city":"Wanze",
    "sg:classifiers":[
        {
            "category":"Arena",
            "subcategory":"Sports Club",
            "type":"Entertainment"
        }
    ],
    "sg:phone":"+32 85 23 19 77",
    "sg:postcode":"4520",
    "sg:province":"Li\u00e8ge",
    "sg:tags":[
        "de"
    ],
    "wof:name":"Val M\u00c9haigne Natat. Wanze",
    "wof:placetype":"venue"
},
  "geometry": {"coordinates":[5.2356128693,50.5436935425],"type":"Point"}
}