{
  "type": "Feature",
  "properties": {
    "addr:full":"Rue Grande 135 Bernissart Hainaut 7320",
    "addr:housenumber":"135",
    "addr:postcode":"7320",
    "addr:street":"Rue Grande",
    "iso:country":"BE",
    "sg:address":"Rue Grande 135",
    "sg:city":"Bernissart",
    "sg:classifiers":[
        {
            "category":"Professional",
            "subcategory":"Employment Agencies",
            "type":"Services"
        }
    ],
    "sg:phone":"+32 69 58 01 42",
    "sg:postcode":"7320",
    "sg:province":"Hainaut",
    "sg:tags":[
        "temping",
        "-",
        "manual"
    ],
    "wof:name":"A.l.e. Asbl",
    "wof:placetype":"venue"
},
  "geometry": {"coordinates":[3.6514670849,50.4759941101],"type":"Point"}
}