{
  "type": "Feature",
  "properties": {
    "addr:full":"Hekkestraat 26 Sint-amands Antwerpen 2890",
    "addr:housenumber":"26",
    "addr:postcode":"2890",
    "addr:street":"Hekkestraat",
    "iso:country":"BE",
    "sg:address":"Hekkestraat 26",
    "sg:city":"Sint-amands",
    "sg:orig_category":"Enseignement maternel and primaire",
    "sg:phone":"+32 52 33 47 43",
    "sg:postcode":"2890",
    "sg:province":"Antwerpen",
    "wof:name":"Gemeentel. Lagere School",
    "wof:placetype":"venue"
},
  "geometry": {"coordinates":[4.2026128769,51.0524253845],"type":"Point"}
}