{
  "type": "Feature",
  "properties": {
    "iso:country":"BE",
    "sg:address":"Gasthuisstraat 52",
    "sg:city":"Geel",
    "sg:orig_category":"Goederenvervoer over de weg",
    "sg:phone":"+32 14 58 84 24",
    "sg:postcode":"2440",
    "sg:province":"Antwerpen",
    "wof:name":"De Smedt",
    "wof:placetype":"venue"
},
  "geometry": {"coordinates":[4.9961490631,51.15883255],"type":"Point"}
}