{
  "type": "Feature",
  "properties": {
    "addr:full":"Amelbergastraat 52 Zandhoven Antwerpen 2240",
    "addr:housenumber":"52",
    "addr:postcode":"2240",
    "addr:street":"Amelbergastraat",
    "iso:country":"BE",
    "sg:address":"Amelbergastraat 52",
    "sg:city":"Zandhoven",
    "sg:orig_category":"Openbare veiligheid",
    "sg:phone":"+32 3 484 30 05",
    "sg:postcode":"2240",
    "sg:province":"Antwerpen",
    "wof:name":"Federale Politie/police F\u00c9d\u00c9rale",
    "wof:placetype":"venue"
},
  "geometry": {"coordinates":[4.6635861397,51.2174911499],"type":"Point"}
}