{
  "type": "Feature",
  "properties": {
    "addr:full":"Avenue Gabriel Emile Lebon 53 Box 39 Bruxelles (auderghem) Bruxelles-Capitale 1160",
    "addr:housenumber":"53 box 39",
    "addr:postcode":"1160",
    "addr:street":"Avenue Gabriel Emile Lebon",
    "iso:country":"BE",
    "sg:address":"Avenue Gabriel Emile Lebon 53 Box 39",
    "sg:city":"Bruxelles (auderghem)",
    "sg:classifiers":[
        {
            "category":"Building & Trades",
            "subcategory":"Construction",
            "type":"Services"
        }
    ],
    "sg:phone":"+32 2 675 66 79",
    "sg:postcode":"1160",
    "sg:province":"Bruxelles-Capitale",
    "sg:tags":[
        "industrial",
        "design"
    ],
    "wof:name":"Blyweert P",
    "wof:placetype":"venue"
},
  "geometry": {"coordinates":[4.4083638191,50.824256897],"type":"Point"}
}