{
  "type": "Feature",
  "properties": {
    "addr:full":"Rameistraat 135 Overijse Vlaams-Brabant 3090",
    "addr:housenumber":"135",
    "addr:postcode":"3090",
    "addr:street":"Rameistraat",
    "iso:country":"BE",
    "sg:address":"Rameistraat 135",
    "sg:city":"Overijse",
    "sg:orig_category":"Rundveehouders",
    "sg:phone":"+32 2 687 52 53",
    "sg:postcode":"3090",
    "sg:province":"Vlaams-Brabant",
    "wof:name":"Willy Alsteens",
    "wof:placetype":"venue"
},
  "geometry": {"coordinates":[4.540157795,50.7513313293],"type":"Point"}
}