{
  "type": "Feature",
  "properties": {
    "addr:full":"Dosseweg 28 Tielt West-Vlaanderen 8700",
    "addr:housenumber":"28",
    "addr:postcode":"8700",
    "addr:street":"Dosseweg",
    "iso:country":"BE",
    "sg:address":"Dosseweg 28",
    "sg:city":"Tielt",
    "sg:orig_category":"Installation de menuiserie en bois and plastique",
    "sg:phone":"+32 51 40 13 66",
    "sg:postcode":"8700",
    "sg:province":"West-Vlaanderen",
    "wof:name":"Robert Debrabandere",
    "wof:placetype":"venue"
},
  "geometry": {"coordinates":[3.3298130035,51.0269088745],"type":"Point"}
}