{
  "type": "Feature",
  "properties": {
    "addr:full":"Rue De La Station 66 Sambreville Namur 5060",
    "addr:housenumber":"66",
    "addr:postcode":"5060",
    "addr:street":"Rue De La Station",
    "iso:country":"BE",
    "sg:address":"Rue De La Station 66",
    "sg:city":"Sambreville",
    "sg:orig_category":"Rev\u00eatements de sols and murs",
    "sg:phone":"+32 71 77 14 61",
    "sg:postcode":"5060",
    "sg:province":"Namur",
    "wof:name":"Tapis D\u00c9cor",
    "wof:placetype":"venue"
},
  "geometry": {"coordinates":[4.6115899086,50.431640625],"type":"Point"}
}