{
  "type": "Feature",
  "properties": {
    "addr:full":"Rue Louis Hymans 9-b Bruxelles (ixelles) Bruxelles-Capitale 1050",
    "addr:housenumber":"9-b",
    "addr:postcode":"1050",
    "addr:street":"Rue Louis Hymans",
    "iso:country":"BE",
    "sg:address":"Rue Louis Hymans 9-b",
    "sg:city":"Bruxelles (ixelles)",
    "sg:classifiers":[
        {
            "category":"Travel",
            "subcategory":"Resort",
            "type":"Entertainment"
        }
    ],
    "sg:phone":"+32 2 345 50 85",
    "sg:postcode":"1050",
    "sg:province":"Bruxelles-Capitale",
    "sg:tags":[
        "rental",
        "accomodation",
        "holiday",
        "-"
    ],
    "wof:name":"Zamorano J",
    "wof:placetype":"venue"
},
  "geometry": {"coordinates":[4.3567910194,50.8169593811],"type":"Point"}
}