{
  "type": "Feature",
  "properties": {
    "iso:country":"BE",
    "sg:address":"Zagerijstraat 28",
    "sg:city":"Lille",
    "sg:classifiers":[
        {
            "category":"Fast Food",
            "type":"Food & Drink"
        }
    ],
    "sg:phone":"+32 14 88 03 44",
    "sg:postcode":"2275",
    "sg:province":"Antwerpen",
    "sg:tags":[
        "fried",
        "stand",
        "potato"
    ],
    "wof:name":"Lieckens F",
    "wof:placetype":"venue"
},
  "geometry": {"coordinates":[4.8244071007,51.233127594],"type":"Point"}
}