{
  "type": "Feature",
  "properties": {
    "addr:full":"Rue De Dalhem 15 Vis\u00e9 Li\u00e8ge 4600",
    "addr:housenumber":"15",
    "addr:postcode":"4600",
    "addr:street":"Rue De Dalhem",
    "iso:country":"BE",
    "sg:address":"Rue De Dalhem 15",
    "sg:city":"Vis\u00e9",
    "sg:classifiers":[
        {
            "category":"Home & Garden",
            "subcategory":"Garden Supply",
            "type":"Retail Goods"
        }
    ],
    "sg:phone":"+32 4 379 12 13",
    "sg:postcode":"4600",
    "sg:province":"Li\u00e8ge",
    "sg:tags":[
        "lawn",
        "mower"
    ],
    "wof:name":"Peuvrate Sa",
    "wof:placetype":"venue"
},
  "geometry": {"coordinates":[5.6984410286,50.7302589417],"type":"Point"}
}