{
  "type": "Feature",
  "properties": {
    "iso:country":"BE",
    "sg:address":"Kortrijksestraat 496",
    "sg:city":"Oostkamp",
    "sg:orig_category":"Boissons",
    "sg:phone":"+32 50 27 80 99",
    "sg:postcode":"8020",
    "sg:province":"West-Vlaanderen",
    "wof:name":"Dominique Vanhaverbeke",
    "wof:placetype":"venue"
},
  "geometry": {"coordinates":[3.2207899094,51.1221809387],"type":"Point"}
}