{
  "type": "Feature",
  "properties": {
    "iso:country":"BE",
    "sg:address":"All\u00e9e Des Balsamines 3-3",
    "sg:city":"Wanze",
    "sg:classifiers":[
        {
            "category":"Personal",
            "subcategory":"Beauty Salon",
            "type":"Services"
        }
    ],
    "sg:phone":"+32 85 25 14 84",
    "sg:postcode":"4520",
    "sg:province":"Li\u00e8ge",
    "sg:tags":[
        "lady",
        "-",
        "hairdressing"
    ],
    "wof:name":"Espace Coiffure",
    "wof:placetype":"venue"
},
  "geometry": {"coordinates":[5.2152299881,50.5371589661],"type":"Point"}
}