{
  "type": "Feature",
  "properties": {
    "iso:country":"BE",
    "sg:address":"Melkstraat 5",
    "sg:city":"Halle",
    "sg:orig_category":"V\u00eatements pour b\u00e9b\u00e9s and enfants",
    "sg:phone":"+32 2 356 43 12",
    "sg:postcode":"1500",
    "sg:province":"Vlaams-Brabant",
    "wof:name":"Fabienne",
    "wof:placetype":"venue"
},
  "geometry": {"coordinates":[4.2369151115,50.7360610962],"type":"Point"}
}