{
  "type": "Feature",
  "properties": {
    "iso:country":"BE",
    "sg:address":"Zandpoortvest 9b",
    "sg:city":"Mechelen",
    "sg:orig_category":"Maatschappelijke dienstverlening",
    "sg:phone":"+32 15 21 88 50",
    "sg:postcode":"2800",
    "sg:province":"Antwerpen",
    "wof:name":"Vclb-centrum",
    "wof:placetype":"venue"
},
  "geometry": {"coordinates":[4.4886488914,51.02576828],"type":"Point"}
}