{
  "type": "Feature",
  "properties": {
    "iso:country":"BE",
    "sg:address":"Rue De La Vall\u00c9e 10",
    "sg:city":"Ch\u00c2telet",
    "sg:orig_category":"Beautyfarms, relaxatie and lichamelijk welzijn Schoonheidssalons",
    "sg:phone":"+32 71 40 54 87",
    "sg:postcode":"6200",
    "sg:province":"Hainaut",
    "wof:name":"Institut Amaryllis",
    "wof:placetype":"venue"
},
  "geometry": {"coordinates":[4.5190200806,50.4134254456],"type":"Point"}
}