{
  "type": "Feature",
  "properties": {
    "addr:full":"Ledebergstraat 13 Herzele (hillegem) Oost-Vlaanderen 9550",
    "addr:housenumber":"13",
    "addr:postcode":"9550",
    "addr:street":"Ledebergstraat",
    "iso:country":"BE",
    "sg:address":"Ledebergstraat 13",
    "sg:city":"Herzele (hillegem)",
    "sg:classifiers":[
        {
            "category":"Building & Trades",
            "subcategory":"Construction",
            "type":"Services"
        }
    ],
    "sg:phone":"+32 9 342 05 51",
    "sg:postcode":"9550",
    "sg:province":"Oost-Vlaanderen",
    "sg:tags":[
        "ventilating",
        "system"
    ],
    "wof:name":"Baele Ventilatie Bvba",
    "wof:placetype":"venue"
},
  "geometry": {"coordinates":[3.8612170219,50.8999862671],"type":"Point"}
}