{
  "type": "Feature",
  "properties": {
    "iso:country":"BE",
    "sg:address":"Stationsstraat 108",
    "sg:city":"Nazareth",
    "sg:orig_category":"Medische and orthopedische apparaten",
    "sg:phone":"+32 9 385 42 35",
    "sg:postcode":"9810",
    "sg:province":"Oost-Vlaanderen",
    "wof:name":"Albrecht Geeraert",
    "wof:placetype":"venue"
},
  "geometry": {"coordinates":[3.6308429241,50.9598236084],"type":"Point"}
}