{
  "type": "Feature",
  "properties": {
    "addr:full":"Brugsesteenweg 212 Gent Oost-Vlaanderen 9000",
    "addr:housenumber":"212",
    "addr:postcode":"9000",
    "addr:street":"Brugsesteenweg;Oost-Vlaanderen",
    "iso:country":"BE",
    "sg:address":"Brugsesteenweg 212",
    "sg:city":"Gent",
    "sg:orig_category":"Fournitures de bureau. Jeux and jouets. Ordinateurs and \u00e9quipement informatique",
    "sg:phone":"+32 9 236 16 07",
    "sg:postcode":"9000",
    "sg:province":"Oost-Vlaanderen",
    "wof:name":"Extra Soft",
    "wof:placetype":"venue"
},
  "geometry": {"coordinates":[3.6898760796,51.0654830933],"type":"Point"}
}