{
  "type": "Feature",
  "properties": {
    "iso:country":"BE",
    "sg:address":"Bergense Steenweg 93",
    "sg:city":"Anderlecht/anderlecht",
    "sg:orig_category":"Herstellingen and onderhoud van auto's Onderdelen and accessoires voor auto's Voertuigen",
    "sg:phone":"+32 2 521 05 19",
    "sg:postcode":"1070",
    "sg:province":"Bruxelles-Capitale",
    "wof:name":"Garage Liverpool",
    "wof:placetype":"venue"
},
  "geometry": {"coordinates":[4.3338007927,50.8435249329],"type":"Point"}
}