{
  "type": "Feature",
  "properties": {
    "iso:country":"BE",
    "sg:address":"Olmendreef 10",
    "sg:city":"Brugge",
    "sg:orig_category":"Experts-comptables",
    "sg:phone":"+32 50 35 20 37",
    "sg:postcode":"8310",
    "sg:province":"West-Vlaanderen",
    "wof:name":"Arseen Verhaeghe",
    "wof:placetype":"venue"
},
  "geometry": {"coordinates":[3.2526059151,51.1952285767],"type":"Point"}
}