{
  "type": "Feature",
  "properties": {
    "iso:country":"BE",
    "sg:address":"Rue De Huleu 3bb",
    "sg:city":"Ittre",
    "sg:orig_category":"Woningbouw",
    "sg:phone":"+32 67 64 62 01",
    "sg:postcode":"5660",
    "sg:province":"Namur",
    "wof:name":"Construct Home Belgium",
    "wof:placetype":"venue"
},
  "geometry": {"coordinates":[4.4966731071,50.0532150269],"type":"Point"}
}