{
  "type": "Feature",
  "properties": {
    "iso:country":"BE",
    "sg:address":"Winkelhoekstraat 52",
    "sg:city":"Izegem",
    "sg:classifiers":[
        {
            "category":"Freight",
            "type":"Transportation"
        }
    ],
    "sg:phone":"+32 51 30 03 51",
    "sg:postcode":"8870",
    "sg:province":"West-Vlaanderen",
    "sg:tags":[
        "-",
        "transport"
    ],
    "wof:name":"Debrabandere N",
    "wof:placetype":"venue"
},
  "geometry": {"coordinates":[3.2347660065,50.8992004395],"type":"Point"}
}