{
  "type": "Feature",
  "properties": {
    "addr:full":"Markt 4ba Gavere Oost-Vlaanderen 9890",
    "addr:housenumber":"4ba",
    "addr:postcode":"9890",
    "addr:street":"Markt",
    "iso:country":"BE",
    "sg:address":"Markt 4ba",
    "sg:city":"Gavere",
    "sg:classifiers":[
        {
            "category":"Insurance",
            "subcategory":"Insurance Agent",
            "type":"Services"
        }
    ],
    "sg:phone":"+32 9 384 62 14",
    "sg:postcode":"9890",
    "sg:province":"Oost-Vlaanderen",
    "sg:tags":[
        "verzekeringsmakelaars",
        "expert"
    ],
    "wof:name":"G. Renneboog",
    "wof:placetype":"venue"
},
  "geometry": {"coordinates":[3.6594479084,50.9284553528],"type":"Point"}
}