{
  "type": "Feature",
  "properties": {
    "addr:full":"Try-des-bruy\u00c8res 9 Onhaye Namur 5522",
    "addr:housenumber":"9",
    "addr:postcode":"5522",
    "addr:street":"Try-Des-Bruye\u0300Res",
    "iso:country":"BE",
    "sg:address":"Try-des-bruy\u00c8res 9",
    "sg:city":"Onhaye",
    "sg:orig_category":"Installation de menuiserie en bois and plastique",
    "sg:phone":"+32 82 69 95 98",
    "sg:postcode":"5522",
    "sg:province":"Namur",
    "wof:name":"Minet Luc",
    "wof:placetype":"venue"
},
  "geometry": {"coordinates":[4.7934651375,50.2775688171],"type":"Point"}
}