{
  "type": "Feature",
  "properties": {
    "addr:full":"Wolterslaan 73 Gent (sint-amandsberg) Oost-Vlaanderen 9040",
    "addr:housenumber":"73",
    "addr:postcode":"9040",
    "addr:street":"Wolterslaan",
    "iso:country":"BE",
    "sg:address":"Wolterslaan 73",
    "sg:city":"Gent (sint-amandsberg)",
    "sg:classifiers":[
        {
            "category":"Health Services",
            "subcategory":"Health Practitioner",
            "type":"Services"
        }
    ],
    "sg:phone":"+32 9 228 01 62",
    "sg:postcode":"9040",
    "sg:province":"Oost-Vlaanderen",
    "sg:tags":[
        "physiotherapist"
    ],
    "wof:name":"Criel Philip",
    "wof:placetype":"venue"
},
  "geometry": {"coordinates":[3.7484030724,51.0489768982],"type":"Point"}
}