{
  "type": "Feature",
  "properties": {
    "iso:country":"BE",
    "sg:address":"Rue Du Doyenn\u00c9 112",
    "sg:city":"Ukkel/uccle",
    "sg:orig_category":"Banques and organismes de cr\u00e9dit",
    "sg:phone":"+32 2 516 04 00",
    "sg:postcode":"1180",
    "sg:province":"Bruxelles-Capitale",
    "wof:name":"Deutsche Bank",
    "wof:placetype":"venue"
},
  "geometry": {"coordinates":[4.3403959274,50.8034858704],"type":"Point"}
}