{
  "type": "Feature",
  "properties": {
    "addr:full":"Rue Antoine Gautier 104 Etterbeek/etterbeek Bruxelles-Capitale 1040",
    "addr:housenumber":"104",
    "addr:postcode":"1040",
    "addr:street":"Rue Antoine Gautier",
    "iso:country":"BE",
    "sg:address":"Rue Antoine Gautier 104",
    "sg:city":"Etterbeek/etterbeek",
    "sg:orig_category":"M\u00e9decins and sp\u00e9cialistes",
    "sg:phone":"+32 2 732 59 65",
    "sg:postcode":"1040",
    "sg:province":"Bruxelles-Capitale",
    "wof:name":"Alix Fleurisca",
    "wof:placetype":"venue"
},
  "geometry": {"coordinates":[4.3914899826,50.8336601257],"type":"Point"}
}