{
  "type": "Feature",
  "properties": {
    "iso:country":"BE",
    "sg:address":"Kwakkelstraat 84",
    "sg:city":"Stekene",
    "sg:orig_category":"Goederenvervoer over de weg",
    "sg:phone":"+32 3 779 80 45",
    "sg:postcode":"9190",
    "sg:province":"Oost-Vlaanderen",
    "wof:name":"Block-transport",
    "wof:placetype":"venue"
},
  "geometry": {"coordinates":[4.0568499565,51.1934814453],"type":"Point"}
}