{
  "type": "Feature",
  "properties": {
    "iso:country":"BE",
    "sg:address":"Olenseweg 4",
    "sg:city":"Herentals",
    "sg:orig_category":"Imprimeries and copyshops",
    "sg:phone":"+32 14 26 25 72",
    "sg:postcode":"2200",
    "sg:province":"Antwerpen",
    "wof:name":"Drukkerij Jabri",
    "wof:placetype":"venue"
},
  "geometry": {"coordinates":[4.8430500031,51.1417808533],"type":"Point"}
}