{
  "type": "Feature",
  "properties": {
    "addr:full":"Steenovens 26 Geel Antwerpen 2440",
    "addr:housenumber":"26",
    "addr:postcode":"2440",
    "addr:street":"Steenovens",
    "iso:country":"BE",
    "sg:address":"Steenovens 26",
    "sg:city":"Geel",
    "sg:classifiers":[
        {
            "category":"Health Services",
            "subcategory":"Health Practitioner",
            "type":"Services"
        }
    ],
    "sg:phone":"+32 14 59 31 74",
    "sg:postcode":"2440",
    "sg:province":"Antwerpen",
    "sg:tags":[
        "physiotherapist"
    ],
    "wof:name":"Op De Beeck Paul",
    "wof:placetype":"venue"
},
  "geometry": {"coordinates":[4.9439492226,51.1454811096],"type":"Point"}
}