{
  "type": "Feature",
  "properties": {
    "addr:full":"Hoekje 19 Begijnendijk Vlaams-Brabant 3130",
    "addr:housenumber":"19",
    "addr:postcode":"3130",
    "addr:street":"Hoekje",
    "iso:country":"BE",
    "sg:address":"Hoekje 19",
    "sg:city":"Begijnendijk",
    "sg:orig_category":"Woningbouw",
    "sg:phone":"+32 16 53 10 63",
    "sg:postcode":"3130",
    "sg:province":"Vlaams-Brabant",
    "wof:name":"Bosmans J. & B.",
    "wof:placetype":"venue"
},
  "geometry": {"coordinates":[4.7697639465,51.0270805359],"type":"Point"}
}