{
  "type": "Feature",
  "properties": {
    "addr:full":"Lummense-kiezel 58 Hasselt (kermt) Limburg 3510",
    "addr:housenumber":"58",
    "addr:postcode":"3510",
    "addr:street":"Lummense-Kiezel",
    "iso:country":"BE",
    "sg:address":"Lummense-kiezel 58",
    "sg:city":"Hasselt (kermt)",
    "sg:classifiers":[
        {
            "category":"Real Estate",
            "subcategory":"Surveying",
            "type":"Services"
        }
    ],
    "sg:phone":"+32 11 87 13 17",
    "sg:postcode":"3510",
    "sg:province":"Limburg",
    "sg:tags":[
        "lettering",
        "letter"
    ],
    "wof:name":"J P Letterdesign",
    "wof:placetype":"venue"
},
  "geometry": {"coordinates":[5.2392201424,50.9569587708],"type":"Point"}
}