{
  "type": "Feature",
  "properties": {
    "iso:country":"BE",
    "sg:address":"Avenue Van Volxem 445",
    "sg:city":"Bruxelles (forest)",
    "sg:classifiers":[
        {
            "category":"Home & Garden",
            "subcategory":"Furniture",
            "type":"Retail Goods"
        }
    ],
    "sg:phone":"+32 2 538 33 38",
    "sg:postcode":"1190",
    "sg:province":"Bruxelles-Capitale",
    "sg:tags":[
        "-"
    ],
    "wof:name":"Createch",
    "wof:placetype":"venue"
},
  "geometry": {"coordinates":[4.3280148506,50.827457428],"type":"Point"}
}