{
  "type": "Feature",
  "properties": {
    "addr:full":"Hutstraat 11a Kampenhout Vlaams-Brabant 1910",
    "addr:housenumber":"11a",
    "addr:postcode":"1910",
    "addr:street":"Hutstraat",
    "iso:country":"BE",
    "sg:address":"Hutstraat 11a",
    "sg:city":"Kampenhout",
    "sg:classifiers":[
        {
            "category":"Insurance",
            "subcategory":"Insurance Agent",
            "type":"Services"
        }
    ],
    "sg:phone":"+32 16 65 74 70",
    "sg:postcode":"1910",
    "sg:province":"Vlaams-Brabant",
    "sg:tags":[
        "broker"
    ],
    "wof:name":"De Smedt Jp",
    "wof:placetype":"venue"
},
  "geometry": {"coordinates":[4.5825982094,50.9484481812],"type":"Point"}
}