{
  "type": "Feature",
  "properties": {
    "iso:country":"BE",
    "sg:address":"Fonteinstraat 15",
    "sg:city":"Lummen",
    "sg:orig_category":"V\u00e9t\u00e9rinaires",
    "sg:phone":"+32 13 53 20 27",
    "sg:postcode":"3560",
    "sg:province":"Limburg",
    "wof:name":"A. Ector",
    "wof:placetype":"venue"
},
  "geometry": {"coordinates":[5.1847858429,50.9906425476],"type":"Point"}
}