{
  "type": "Feature",
  "properties": {
    "addr:full":"Avenue De La Lib\u00e9ration 7 Malmedy Li\u00e8ge 4960",
    "addr:housenumber":"7",
    "addr:postcode":"4960",
    "addr:street":"Avenue De La Libe\u0301Ration",
    "iso:country":"BE",
    "sg:address":"Avenue De La Lib\u00e9ration 7",
    "sg:city":"Malmedy",
    "sg:classifiers":[
        {
            "category":"Shopping",
            "subcategory":"Antiques",
            "type":"Retail Goods"
        }
    ],
    "sg:phone":"+32 80 33 05 63",
    "sg:postcode":"4960",
    "sg:province":"Li\u00e8ge",
    "wof:name":"Richter",
    "wof:placetype":"venue"
},
  "geometry": {"coordinates":[6.0294718742,50.4365577698],"type":"Point"}
}