{
  "type": "Feature",
  "properties": {
    "addr:full":"Prins Albertstraat 10 Sint-niklaas Oost-Vlaanderen 9100",
    "addr:housenumber":"10",
    "addr:postcode":"9100",
    "addr:street":"Prins Albertstraat",
    "iso:country":"BE",
    "sg:address":"Prins Albertstraat 10",
    "sg:city":"Sint-niklaas",
    "sg:classifiers":[
        {
            "category":"Home & Garden",
            "subcategory":"Household Appliances",
            "type":"Retail Goods"
        }
    ],
    "sg:phone":"+32 3 777 74 40",
    "sg:postcode":"9100",
    "sg:province":"Oost-Vlaanderen",
    "sg:tags":[
        "heating",
        "apparatus"
    ],
    "wof:name":"Wick Company",
    "wof:placetype":"venue"
},
  "geometry": {"coordinates":[4.1435232162,51.1701583862],"type":"Point"}
}