{
  "type": "Feature",
  "properties": {
    "iso:country":"BE",
    "sg:address":"Sint-katelijnestraat 51",
    "sg:city":"Mechelen",
    "sg:classifiers":[
        {
            "category":"Professional",
            "subcategory":"Art Services",
            "type":"Services"
        }
    ],
    "sg:phone":"+32 15 20 52 37",
    "sg:postcode":"2800",
    "sg:province":"Antwerpen",
    "sg:tags":[
        "picture",
        "framer"
    ],
    "wof:name":"Herbert (huis)",
    "wof:placetype":"venue"
},
  "geometry": {"coordinates":[4.476213932,51.0306472778],"type":"Point"}
}