{
  "type": "Feature",
  "properties": {
    "addr:full":"Nijverheidsstraat 7b Zaventem Vlaams-Brabant 1930",
    "addr:housenumber":"7b",
    "addr:postcode":"1930",
    "addr:street":"Nijverheidsstraat",
    "iso:country":"BE",
    "sg:address":"Nijverheidsstraat 7b",
    "sg:city":"Zaventem",
    "sg:orig_category":"Non-Classified Establishments",
    "sg:phone":"+32 2 720 15 28",
    "sg:postcode":"1930",
    "sg:province":"Vlaams-Brabant",
    "wof:name":"Avak",
    "wof:placetype":"venue"
},
  "geometry": {"coordinates":[4.471739769,50.8875808716],"type":"Point"}
}