{
  "type": "Feature",
  "properties": {
    "iso:country":"BE",
    "sg:address":"Avenue Des Arts 58 Bte 1",
    "sg:city":"Brussels",
    "sg:classifiers":[
        {
            "category":"Banks & Credit Unions",
            "subcategory":"Bank",
            "type":"Services"
        }
    ],
    "sg:postcode":"1000",
    "sg:province":"Bruxelles-Capitale",
    "wof:name":"Bank Of Tokyo-mitsubishi (belgium) Sa",
    "wof:placetype":"venue"
},
  "geometry": {"coordinates":[4.366309166,50.8406295776],"type":"Point"}
}