{
  "type": "Feature",
  "properties": {
    "addr:full":"Rue Du Tilleul 50 Rixensart (genval) Brabant Wallon 1332",
    "addr:housenumber":"50",
    "addr:postcode":"1332",
    "addr:street":"Rue Du Tilleul",
    "iso:country":"BE",
    "sg:address":"Rue Du Tilleul 50",
    "sg:city":"Rixensart (genval)",
    "sg:classifiers":[
        {
            "category":"Social Services",
            "type":"Services"
        }
    ],
    "sg:phone":"+32 2 652 00 14",
    "sg:postcode":"1332",
    "sg:province":"Brabant Wallon",
    "wof:name":"Ecole Des Devoirs Des Charmettes",
    "wof:placetype":"venue"
},
  "geometry": {"coordinates":[4.496532917,50.7229766846],"type":"Point"}
}