{
  "type": "Feature",
  "properties": {
    "addr:full":"Bankstraat 126 Leuven Vlaams-Brabant 3000",
    "addr:housenumber":"126",
    "addr:postcode":"3000",
    "addr:street":"Bankstraat",
    "iso:country":"BE",
    "sg:address":"Bankstraat 126",
    "sg:city":"Leuven",
    "sg:orig_category":"Cr\u00e8ches and garderies d'enfants",
    "sg:phone":"+32 16 20 68 11",
    "sg:postcode":"3000",
    "sg:province":"Vlaams-Brabant",
    "wof:name":"De Ballon",
    "wof:placetype":"venue"
},
  "geometry": {"coordinates":[4.6857681274,50.8765144348],"type":"Point"}
}