{
  "type": "Feature",
  "properties": {
    "iso:country":"BE",
    "sg:address":"Dorpsstraat 2 Box 1",
    "sg:city":"As",
    "sg:classifiers":[
        {
            "category":"Bars & Pubs",
            "type":"Food & Drink"
        }
    ],
    "sg:phone":"+32 89 36 46 40",
    "sg:postcode":"3665",
    "sg:province":"Limburg",
    "sg:tags":[
        "tavern"
    ],
    "wof:name":"Verlorenhoek (de)",
    "wof:placetype":"venue"
},
  "geometry": {"coordinates":[5.5882439613,51.0077590942],"type":"Point"}
}