{
  "type": "Feature",
  "properties": {
    "iso:country":"BE",
    "sg:address":"Binnensteenweg 240",
    "sg:city":"Boechout",
    "sg:orig_category":"Verhuisdiensten",
    "sg:phone":"+32 3 455 61 21",
    "sg:postcode":"2530",
    "sg:province":"Antwerpen",
    "wof:name":"Van Brussel & Zonen",
    "wof:placetype":"venue"
},
  "geometry": {"coordinates":[4.4949040413,51.1662330627],"type":"Point"}
}