{
  "type": "Feature",
  "properties": {
    "addr:full":"Rue Saint-quentin 17 Enghien Hainaut 7850",
    "addr:housenumber":"17",
    "addr:postcode":"7850",
    "addr:street":"Rue Saint-Quentin",
    "iso:country":"BE",
    "sg:address":"Rue Saint-quentin 17",
    "sg:city":"Enghien",
    "sg:classifiers":[
        {
            "category":"Professional",
            "subcategory":"Management & Consulting",
            "type":"Services"
        }
    ],
    "sg:phone":"+32 2 395 31 72",
    "sg:postcode":"7850",
    "sg:province":"Hainaut",
    "sg:tags":[
        "tax-consultants"
    ],
    "wof:name":"Weverbergh O",
    "wof:placetype":"venue"
},
  "geometry": {"coordinates":[4.0436310768,50.6939430237],"type":"Point"}
}