{
  "type": "Feature",
  "properties": {
    "addr:full":"Schotlandstraat 67 Sint-gillis/saint-gilles Bruxelles-Capitale 1060",
    "addr:housenumber":"67",
    "addr:postcode":"1060",
    "addr:street":"Schotlandstraat",
    "iso:country":"BE",
    "sg:address":"Schotlandstraat 67",
    "sg:city":"Sint-gillis/saint-gilles",
    "sg:orig_category":"Boekhouders",
    "sg:phone":"+32 2 534 49 29",
    "sg:postcode":"1060",
    "sg:province":"Bruxelles-Capitale",
    "wof:name":"Christine Coenen",
    "wof:placetype":"venue"
},
  "geometry": {"coordinates":[4.3512802124,50.8311233521],"type":"Point"}
}