{
  "type": "Feature",
  "properties": {
    "iso:country":"BE",
    "sg:address":"Rue Saint-laurent 29",
    "sg:city":"Li\u00c8ge",
    "sg:orig_category":"Technisch and beroeps secundair onderwijs",
    "sg:phone":"+32 4 223 78 80",
    "sg:postcode":"4000",
    "sg:province":"Li\u00e8ge",
    "wof:name":"Institut St.laurent",
    "wof:placetype":"venue"
},
  "geometry": {"coordinates":[5.5611391068,50.6434440613],"type":"Point"}
}