{
  "type": "Feature",
  "properties": {
    "iso:country":"BE",
    "sg:address":"Dreefstraat 8",
    "sg:city":"Ninove",
    "sg:classifiers":[
        {
            "category":"Bars & Pubs",
            "type":"Food & Drink"
        }
    ],
    "sg:phone":"+32 54 33 15 65",
    "sg:postcode":"9400",
    "sg:province":"Oost-Vlaanderen",
    "wof:name":"De Kring",
    "wof:placetype":"venue"
},
  "geometry": {"coordinates":[4.0256791115,50.836933136],"type":"Point"}
}