{
  "type": "Feature",
  "properties": {
    "addr:full":"Avenue Baron Louis Huart 9 Namur Namur 5000",
    "addr:housenumber":"9",
    "addr:postcode":"5000",
    "addr:street":"Avenue Baron Louis Huart",
    "iso:country":"BE",
    "sg:address":"Avenue Baron Louis Huart 9",
    "sg:city":"Namur",
    "sg:classifiers":[
        {
            "category":"Banks & Credit Unions",
            "subcategory":"Financial Services",
            "type":"Services"
        }
    ],
    "sg:phone":"+32 81 22 00 53",
    "sg:postcode":"5000",
    "sg:province":"Namur",
    "sg:tags":[
        "financing"
    ],
    "wof:name":"Pretservice Sa",
    "wof:placetype":"venue"
},
  "geometry": {"coordinates":[4.8679041862,50.4604606628],"type":"Point"}
}