{
  "type": "Feature",
  "properties": {
    "iso:country":"BE",
    "sg:address":"Rue Haute 73",
    "sg:city":"Herve",
    "sg:classifiers":[
        {
            "category":"Real Estate",
            "subcategory":"Architect",
            "type":"Services"
        }
    ],
    "sg:phone":"+32 87 66 14 92",
    "sg:postcode":"4650",
    "sg:province":"Li\u00e8ge",
    "wof:name":"Simar R",
    "wof:placetype":"venue"
},
  "geometry": {"coordinates":[5.7956161499,50.6427192688],"type":"Point"}
}