{
  "type": "Feature",
  "properties": {
    "iso:country":"BE",
    "sg:address":"Rue Louis De Brouck\u00e8re 102",
    "sg:city":"La Louvi\u00e8re",
    "sg:classifiers":[
        {
            "category":"Building & Trades",
            "subcategory":"Equipment Rental",
            "type":"Services"
        }
    ],
    "sg:phone":"+32 64 21 72 07",
    "sg:postcode":"7100",
    "sg:province":"Hainaut",
    "sg:tags":[
        "sound",
        "-",
        "system"
    ],
    "wof:name":"Diapason",
    "wof:placetype":"venue"
},
  "geometry": {"coordinates":[4.1918940544,50.4809188843],"type":"Point"}
}