{
  "type": "Feature",
  "properties": {
    "addr:full":"Notelaarstraat 8 Alveringem West-Vlaanderen 8691",
    "addr:housenumber":"8",
    "addr:postcode":"8691",
    "addr:street":"Notelaarstraat",
    "iso:country":"BE",
    "sg:address":"Notelaarstraat 8",
    "sg:city":"Alveringem",
    "sg:orig_category":"Eleveurs de bovins. Eleveurs and marchands de porcs",
    "sg:phone":"+32 57 40 01 53",
    "sg:postcode":"8691",
    "sg:province":"West-Vlaanderen",
    "wof:name":"Willy Butaye",
    "wof:placetype":"venue"
},
  "geometry": {"coordinates":[2.6940050125,50.9326057434],"type":"Point"}
}