{
  "type": "Feature",
  "properties": {
    "addr:full":"Victor Dumonlaan 11 Willebroek Antwerpen 2830",
    "addr:housenumber":"11",
    "addr:postcode":"2830",
    "addr:street":"Victor Dumonlaan",
    "iso:country":"BE",
    "sg:address":"Victor Dumonlaan 11",
    "sg:city":"Willebroek",
    "sg:classifiers":[
        {
            "category":"Professional",
            "type":"Services"
        }
    ],
    "sg:phone":"+32 3 222 95 10",
    "sg:postcode":"2830",
    "sg:province":"Antwerpen",
    "sg:tags":[
        "forwarding",
        "agency"
    ],
    "wof:name":"Forlog Nv",
    "wof:placetype":"venue"
},
  "geometry": {"coordinates":[4.3621311188,51.077419281],"type":"Point"}
}