{
  "type": "Feature",
  "properties": {
    "addr:full":"Botermelkdijk 254 Schoten Antwerpen 2900",
    "addr:housenumber":"254",
    "addr:postcode":"2900",
    "addr:street":"Botermelkdijk",
    "iso:country":"BE",
    "sg:address":"Botermelkdijk 254",
    "sg:city":"Schoten",
    "sg:classifiers":[
        {
            "category":"Retail",
            "subcategory":"Animal Services",
            "type":"Services"
        }
    ],
    "sg:phone":"+32 3 685 14 59",
    "sg:postcode":"2900",
    "sg:province":"Antwerpen",
    "sg:tags":[
        "grooming",
        "-",
        "dog"
    ],
    "wof:name":"Fiocco",
    "wof:placetype":"venue"
},
  "geometry": {"coordinates":[4.5219020844,51.2724266052],"type":"Point"}
}