{
  "type": "Feature",
  "properties": {
    "addr:full":"A. Rodenbachstraat 2a Ieper West-Vlaanderen 8908",
    "addr:housenumber":"2a",
    "addr:postcode":"8908",
    "addr:street":"A. Rodenbachstraat",
    "iso:country":"BE",
    "sg:address":"A. Rodenbachstraat 2a",
    "sg:city":"Ieper",
    "sg:orig_category":"Elektrische installaties voor woningen HERSTELLING ELEKTRISCHE HUISHOUDAPPARATEN Huishoudapparaten, ",
    "sg:phone":"+32 57 20 55 59",
    "sg:postcode":"8908",
    "sg:province":"West-Vlaanderen",
    "wof:name":"Knockaert",
    "wof:placetype":"venue"
},
  "geometry": {"coordinates":[2.8205749989,50.8549461365],"type":"Point"}
}