{
  "type": "Feature",
  "properties": {
    "iso:country":"BE",
    "sg:address":"Kanunnik Melinlaan 9",
    "sg:city":"Hasselt",
    "sg:classifiers":[
        {
            "category":"Real Estate",
            "subcategory":"Real Estate Services",
            "type":"Services"
        }
    ],
    "sg:phone":"+32 11 27 43 73",
    "sg:postcode":"3500",
    "sg:province":"Limburg",
    "wof:name":"Limburgse Huizenwinkel (de) Bvba",
    "wof:placetype":"venue"
},
  "geometry": {"coordinates":[5.3201460838,50.9201278687],"type":"Point"}
}