{
  "type": "Feature",
  "properties": {
    "iso:country":"BE",
    "sg:address":"Laagland 10",
    "sg:city":"Herentals",
    "sg:orig_category":"Installation de menuiserie m\u00e9tallique. Installation de menuiserie en bois and plastique. Installatio",
    "sg:phone":"+32 14 21 34 02",
    "sg:postcode":"2200",
    "sg:province":"Antwerpen",
    "wof:name":"Vermat Ramen En Zonwering",
    "wof:placetype":"venue"
},
  "geometry": {"coordinates":[4.8158788681,51.1729545593],"type":"Point"}
}