{
  "type": "Feature",
  "properties": {
    "addr:full":"Biestmolenstraat 31 Zwalm Oost-Vlaanderen 9636",
    "addr:housenumber":"31",
    "addr:postcode":"9636",
    "addr:street":"Biestmolenstraat;Oost-Vlaanderen",
    "iso:country":"BE",
    "sg:address":"Biestmolenstraat 31",
    "sg:city":"Zwalm",
    "sg:orig_category":"GROENTEN AND FRUIT Groenten and fruit Gh",
    "sg:phone":"+32 55 49 96 62",
    "sg:postcode":"9636",
    "sg:province":"Oost-Vlaanderen",
    "wof:name":"Antoine Caryn",
    "wof:placetype":"venue"
},
  "geometry": {"coordinates":[3.6944689751,50.8804397583],"type":"Point"}
}