{
  "type": "Feature",
  "properties": {
    "addr:full":"Nijverheidstraat 6a Gent (sint-amandsberg) Oost-Vlaanderen 9040",
    "addr:housenumber":"6a",
    "addr:postcode":"9040",
    "addr:street":"Nijverheidstraat",
    "iso:country":"BE",
    "sg:address":"Nijverheidstraat 6a",
    "sg:city":"Gent (sint-amandsberg)",
    "sg:classifiers":[
        {
            "category":"Building & Trades",
            "subcategory":"Pest Control",
            "type":"Services"
        }
    ],
    "sg:phone":"+32 9 228 20 87",
    "sg:postcode":"9040",
    "sg:province":"Oost-Vlaanderen",
    "sg:tags":[
        "painting",
        "contractor"
    ],
    "wof:name":"De Paepe-vervynck Nv",
    "wof:placetype":"venue"
},
  "geometry": {"coordinates":[3.7457010746,51.0528259277],"type":"Point"}
}