{
  "type": "Feature",
  "properties": {
    "addr:full":"Boudewijn Hapkenstraat 14 Zedelgem (veldegem) West-Vlaanderen 8210",
    "addr:housenumber":"14",
    "addr:postcode":"8210",
    "addr:street":"Hapkenstraat",
    "iso:country":"BE",
    "sg:address":"Boudewijn Hapkenstraat 14",
    "sg:city":"Zedelgem (veldegem)",
    "sg:classifiers":[
        {
            "category":"Arts & Performance",
            "subcategory":"Art Gallery",
            "type":"Entertainment"
        }
    ],
    "sg:phone":"+32 50 27 79 26",
    "sg:postcode":"8210",
    "sg:province":"West-Vlaanderen",
    "sg:tags":[
        "rendering"
    ],
    "wof:name":"De Jaeghere Bvba",
    "wof:placetype":"venue"
},
  "geometry": {"coordinates":[3.1458399296,51.1376457214],"type":"Point"}
}