{
  "type": "Feature",
  "properties": {
    "addr:full":"Melkmarkt 29 Antwerpen Antwerpen 2000",
    "addr:housenumber":"29",
    "addr:postcode":"2000",
    "addr:street":"Melkmarkt",
    "iso:country":"BE",
    "sg:address":"Melkmarkt 29",
    "sg:city":"Antwerpen",
    "sg:orig_category":"Ice-cream parlours",
    "sg:phone":"+32 3 232 77 06",
    "sg:postcode":"2000",
    "sg:province":"Antwerpen",
    "wof:name":"Leon",
    "wof:placetype":"venue"
},
  "geometry": {"coordinates":[4.4028978348,51.2200622559],"type":"Point"}
}