{
  "type": "Feature",
  "properties": {
    "iso:country":"BE",
    "sg:address":"Vlaestraat 19",
    "sg:city":"Kortemark (zarren-werken)",
    "sg:classifiers":[
        {
            "category":"Farming",
            "subcategory":"Farm & Veterinary Services",
            "type":"Manufacturing & Wholesale Goods"
        }
    ],
    "sg:phone":"+32 51 70 12 63",
    "sg:postcode":"8610",
    "sg:province":"West-Vlaanderen",
    "sg:tags":[
        "agricultural",
        "contractor"
    ],
    "wof:name":"Scheldeman D",
    "wof:placetype":"venue"
},
  "geometry": {"coordinates":[2.9750680923,50.9925575256],"type":"Point"}
}