{
  "type": "Feature",
  "properties": {
    "addr:full":"Rue Du Fichaux 10 Pont-\u00e0-celles Hainaut 6230",
    "addr:housenumber":"10",
    "addr:postcode":"6230",
    "addr:street":"Rue Du Fichaux",
    "iso:country":"BE",
    "sg:address":"Rue Du Fichaux 10",
    "sg:city":"Pont-\u00e0-celles",
    "sg:classifiers":[
        {
            "category":"Animal Shelter",
            "type":"Public Place"
        }
    ],
    "sg:phone":"+32 71 84 41 97",
    "sg:postcode":"6230",
    "sg:province":"Hainaut",
    "sg:tags":[
        "nutrition",
        "husbandry"
    ],
    "wof:name":"Etablissements Sibille S.a.",
    "wof:placetype":"venue"
},
  "geometry": {"coordinates":[4.3552980423,50.5144042969],"type":"Point"}
}