{
  "type": "Feature",
  "properties": {
    "iso:country":"BE",
    "sg:address":"Westdoorn 16",
    "sg:city":"Wuustwezel",
    "sg:classifiers":[
        {
            "category":"Retail",
            "subcategory":"Auto Repair",
            "type":"Services"
        }
    ],
    "sg:phone":"+32 3 669 66 44",
    "sg:postcode":"2990",
    "sg:province":"Antwerpen",
    "sg:tags":[
        "garage"
    ],
    "wof:name":"Auto & Truck Service Vdc Bvba",
    "wof:placetype":"venue"
},
  "geometry": {"coordinates":[4.5620269775,51.3802566528],"type":"Point"}
}