{
  "type": "Feature",
  "properties": {
    "addr:full":"Rue Du Village 28 Fl\u00e9malle Li\u00e8ge 4400",
    "addr:housenumber":"28",
    "addr:postcode":"4400",
    "addr:street":"Rue Du Village",
    "iso:country":"BE",
    "sg:address":"Rue Du Village 28",
    "sg:city":"Fl\u00e9malle",
    "sg:classifiers":[
        {
            "category":"Health Services",
            "subcategory":"Doctor",
            "type":"Services"
        }
    ],
    "sg:phone":"+32 4 233 71 53",
    "sg:postcode":"4400",
    "sg:province":"Li\u00e8ge",
    "sg:tags":[
        "medicinephysicians",
        "surgeon"
    ],
    "wof:name":"Bertrand Eric",
    "wof:placetype":"venue"
},
  "geometry": {"coordinates":[5.4642291069,50.5983543396],"type":"Point"}
}