{
  "type": "Feature",
  "properties": {
    "addr:full":"Avenue Du Prince H\u00e9ritier 176 Bruxelles (woluwe-saint-lambert) Bruxelles-Capitale 1200",
    "addr:housenumber":"176",
    "addr:postcode":"1200",
    "addr:street":"Avenue Du Prince He\u0301Ritier",
    "iso:country":"BE",
    "sg:address":"Avenue Du Prince H\u00e9ritier 176",
    "sg:city":"Bruxelles (woluwe-saint-lambert)",
    "sg:classifiers":[
        {
            "category":"Communications",
            "subcategory":"Film & Video Production",
            "type":"Services"
        }
    ],
    "sg:phone":"+32 2 736 61 11",
    "sg:postcode":"1200",
    "sg:province":"Bruxelles-Capitale",
    "sg:tags":[
        "equipment",
        "-",
        "sale",
        "supply"
    ],
    "wof:name":"Amiga City",
    "wof:placetype":"venue"
},
  "geometry": {"coordinates":[4.4089407921,50.8465003967],"type":"Point"}
}