{
  "type": "Feature",
  "properties": {
    "iso:country":"BE",
    "sg:address":"Ten Berkel 7",
    "sg:city":"Diksmuide",
    "sg:orig_category":"Meubles Fab",
    "sg:phone":"+32 51 55 52 01",
    "sg:postcode":"8600",
    "sg:province":"West-Vlaanderen",
    "wof:name":"Verschaeve C",
    "wof:placetype":"venue"
},
  "geometry": {"coordinates":[2.8657801151,51.0334663391],"type":"Point"}
}