{
  "type": "Feature",
  "properties": {
    "iso:country":"BE",
    "sg:address":"Rue Du Veill\u00e9 44",
    "sg:city":"Brunehaut (wez-velvain)",
    "sg:classifiers":[
        {
            "category":"Health Services",
            "subcategory":"Doctor",
            "type":"Services"
        }
    ],
    "sg:phone":"+32 69 64 94 21",
    "sg:postcode":"7620",
    "sg:province":"Hainaut",
    "sg:tags":[
        "medicinephysicians",
        "surgeon"
    ],
    "wof:name":"Bonnet V",
    "wof:placetype":"venue"
},
  "geometry": {"coordinates":[3.3765089512,50.5482559204],"type":"Point"}
}