{
  "type": "Feature",
  "properties": {
    "iso:country":"BE",
    "sg:address":"Rue Des Grands Champs 21",
    "sg:city":"Li\u00e8ge 1",
    "sg:classifiers":[
        {
            "category":"Fast Food",
            "type":"Food & Drink"
        }
    ],
    "sg:phone":"+32 4 252 99 73",
    "sg:postcode":"4000",
    "sg:province":"Li\u00e8ge",
    "sg:tags":[
        "fried",
        "stand",
        "potato"
    ],
    "wof:name":"Grands Champs (les)",
    "wof:placetype":"venue"
},
  "geometry": {"coordinates":[5.5441431999,50.62865448],"type":"Point"}
}