{
  "type": "Feature",
  "properties": {
    "addr:full":"Steenhuisdreef 20 Gent Oost-Vlaanderen 9031",
    "addr:housenumber":"20",
    "addr:postcode":"9031",
    "addr:street":"Steenhuisdreef;Oost-Vlaanderen",
    "iso:country":"BE",
    "sg:address":"Steenhuisdreef 20",
    "sg:city":"Gent",
    "sg:classifiers":[
        {
            "category":"Insurance",
            "subcategory":"Insurance Agent",
            "type":"Services"
        }
    ],
    "sg:phone":"+32 9 226 47 21",
    "sg:postcode":"9031",
    "sg:province":"Oost-Vlaanderen",
    "sg:tags":[
        "verzekeringsmakelaars",
        "expert"
    ],
    "wof:name":"M.d.b.",
    "wof:placetype":"venue"
},
  "geometry": {"coordinates":[3.6640241146,51.0518379211],"type":"Point"}
}