{
  "type": "Feature",
  "properties": {
    "addr:full":"Sint-ursmarsstraat 27 Brakel Oost-Vlaanderen 9660",
    "addr:housenumber":"27",
    "addr:postcode":"9660",
    "addr:street":"Sint-Ursmarsstraat",
    "iso:country":"BE",
    "sg:address":"Sint-ursmarsstraat 27",
    "sg:city":"Brakel",
    "sg:orig_category":"Plaatsen van vloer- and muurbekleding Schilders",
    "sg:phone":"+32 55 45 64 25",
    "sg:postcode":"9660",
    "sg:province":"Oost-Vlaanderen",
    "wof:name":"Gabriels Leon & Robert",
    "wof:placetype":"venue"
},
  "geometry": {"coordinates":[3.7164280415,50.820476532],"type":"Point"}
}