{
  "type": "Feature",
  "properties": {
    "addr:full":"Avenue Des Pl\u00e9iades 65 Wavre (limal) Brabant Wallon 1300",
    "addr:housenumber":"65",
    "addr:postcode":"1300",
    "addr:street":"Avenue Des Ple\u0301Iades;Wallon",
    "iso:country":"BE",
    "sg:address":"Avenue Des Pl\u00e9iades 65",
    "sg:city":"Wavre (limal)",
    "sg:classifiers":[
        {
            "category":"Health Services",
            "subcategory":"Health Practitioner",
            "type":"Services"
        }
    ],
    "sg:phone":"+32 10 41 13 91",
    "sg:postcode":"1300",
    "sg:province":"Brabant Wallon",
    "sg:tags":[
        "physiotherapist"
    ],
    "wof:name":"Impens C",
    "wof:placetype":"venue"
},
  "geometry": {"coordinates":[4.5596637726,50.7084007263],"type":"Point"}
}