{
  "type": "Feature",
  "properties": {
    "addr:full":"Harelbekestr 79 Deerlijk West-Vlaanderen 8540",
    "addr:housenumber":"79",
    "addr:postcode":"8540",
    "addr:street":"Harelbekestr",
    "iso:country":"BE",
    "sg:address":"Harelbekestr 79",
    "sg:city":"Deerlijk",
    "sg:classifiers":[
        {
            "category":"Manufacturing",
            "subcategory":"Printing",
            "type":"Manufacturing & Wholesale Goods"
        }
    ],
    "sg:phone":"+32 56 73 63 53",
    "sg:postcode":"8540",
    "sg:province":"West-Vlaanderen",
    "sg:tags":[
        "publishing"
    ],
    "wof:name":"Grafimat Nv",
    "wof:placetype":"venue"
},
  "geometry": {"coordinates":[3.3493540287,50.852268219],"type":"Point"}
}