{
  "type": "Feature",
  "properties": {
    "iso:country":"BE",
    "sg:address":"Diestsestraat 8",
    "sg:city":"Aarschot",
    "sg:orig_category":"Meubles D\u00e9taillants, Am\u00e9nagement de B\u00e2timents et de Cuisines. Meubles Fab",
    "sg:phone":"+32 16 56 49 17",
    "sg:postcode":"3200",
    "sg:province":"Vlaams-Brabant",
    "wof:name":"Depeche Agencies",
    "wof:placetype":"venue"
},
  "geometry": {"coordinates":[4.8367390633,50.9836463928],"type":"Point"}
}