{
  "type": "Feature",
  "properties": {
    "iso:country":"BE",
    "sg:address":"Sterrewijk 41",
    "sg:city":"Aalter",
    "sg:orig_category":"Eleveurs de bovins. Eleveurs and marchands de porcs",
    "sg:phone":"+32 9 374 34 52",
    "sg:postcode":"9880",
    "sg:province":"Oost-Vlaanderen",
    "wof:name":"Marcel Lannoo",
    "wof:placetype":"venue"
},
  "geometry": {"coordinates":[3.4196829796,51.0752792358],"type":"Point"}
}