{
  "type": "Feature",
  "properties": {
    "iso:country":"BE",
    "sg:address":"Grensstraat 64",
    "sg:city":"Sint-joost-ten-node/saint-josse-ten-noode",
    "sg:orig_category":"Artsen and specialisten",
    "sg:phone":"+32 2 219 84 67",
    "sg:postcode":"1210",
    "sg:province":"Bruxelles-Capitale",
    "wof:name":"N. Jabour",
    "wof:placetype":"venue"
},
  "geometry": {"coordinates":[4.371462822,50.854598999],"type":"Point"}
}