{
  "type": "Feature",
  "properties": {
    "iso:country":"BE",
    "sg:address":"Melkmarkt 40",
    "sg:city":"Antwerpen",
    "sg:classifiers":[
        {
            "category":"Shopping",
            "subcategory":"Beauty & Cosmetics",
            "type":"Retail Goods"
        }
    ],
    "sg:phone":"+32 3 707 22 77",
    "sg:postcode":"2000",
    "sg:province":"Antwerpen",
    "sg:tags":[
        "-",
        "perfumery"
    ],
    "wof:name":"Soap Factory",
    "wof:placetype":"venue"
},
  "geometry": {"coordinates":[4.4030199051,51.2196006775],"type":"Point"}
}