{
  "type": "Feature",
  "properties": {
    "iso:country":"BE",
    "sg:address":"De Merodedreef 46",
    "sg:city":"Westerlo",
    "sg:classifiers":[
        {
            "category":"Professional",
            "subcategory":"Art Services",
            "type":"Services"
        }
    ],
    "sg:phone":"+32 14 71 77 17",
    "sg:postcode":"2260",
    "sg:province":"Antwerpen",
    "sg:tags":[
        "interior",
        "designer"
    ],
    "wof:name":"Prims Klaar",
    "wof:placetype":"venue"
},
  "geometry": {"coordinates":[4.9111709595,51.0862312317],"type":"Point"}
}