{
  "type": "Feature",
  "properties": {
    "iso:country":"BE",
    "sg:address":"Rue Des Combattants 127",
    "sg:city":"La Hulpe",
    "sg:classifiers":[
        {
            "category":"Shopping",
            "subcategory":"Books",
            "type":"Retail Goods"
        }
    ],
    "sg:phone":"+32 2 653 44 49",
    "sg:postcode":"1310",
    "sg:province":"Brabant Wallon",
    "sg:tags":[
        "bookseller"
    ],
    "wof:name":"R\u00e9cr\u00e9 (la)",
    "wof:placetype":"venue"
},
  "geometry": {"coordinates":[4.4851059914,50.7306060791],"type":"Point"}
}