{
  "type": "Feature",
  "properties": {
    "addr:full":"Vrijheidstraat 71 Temse Oost-Vlaanderen 9140",
    "addr:housenumber":"71",
    "addr:postcode":"9140",
    "addr:street":"Vrijheidstraat",
    "iso:country":"BE",
    "sg:address":"Vrijheidstraat 71",
    "sg:city":"Temse",
    "sg:orig_category":"Openbare veiligheid",
    "sg:phone":"+32 3 771 00 04",
    "sg:postcode":"9140",
    "sg:province":"Oost-Vlaanderen",
    "wof:name":"Federale Politie/police F\u00c9d\u00c9rale",
    "wof:placetype":"venue"
},
  "geometry": {"coordinates":[4.2194728851,51.1288719177],"type":"Point"}
}