{
  "type": "Feature",
  "properties": {
    "addr:full":"Avenue De La Basilique 327b10 Koekelberg Bruxelles-Capitale 1081",
    "addr:housenumber":"327b10",
    "addr:postcode":"1081",
    "addr:street":"Avenue De La Basilique",
    "iso:country":"BE",
    "sg:address":"Avenue De La Basilique 327b10",
    "sg:city":"Koekelberg",
    "sg:classifiers":[
        {
            "category":"Building & Trades",
            "subcategory":"Landscaping Services",
            "type":"Services"
        }
    ],
    "sg:phone":"+32 2 469 15 41",
    "sg:postcode":"1081",
    "sg:province":"Bruxelles-Capitale",
    "sg:tags":[
        "etude",
        "technique",
        "ing\u00e9nierie"
    ],
    "wof:name":"Gazz\u00c9",
    "wof:placetype":"venue"
},
  "geometry": {"coordinates":[4.3075470924,50.8645973206],"type":"Point"}
}