{
  "type": "Feature",
  "properties": {
    "iso:country":"BE",
    "sg:address":"Rittwegerlaan 40",
    "sg:city":"Machelen",
    "sg:classifiers":[
        {
            "category":"Shopping",
            "type":"Retail Goods"
        }
    ],
    "sg:phone":"+32 2 252 01 11",
    "sg:postcode":"1830",
    "sg:province":"Vlaams-Brabant",
    "sg:tags":[
        "metallurgy",
        "finished",
        "-",
        "metalworking",
        "metallic"
    ],
    "wof:name":"Geberit Nv",
    "wof:placetype":"venue"
},
  "geometry": {"coordinates":[4.4222741127,50.9074134827],"type":"Point"}
}