{
  "type": "Feature",
  "properties": {
    "iso:country":"BE",
    "sg:address":"Neerhofstraat 2",
    "sg:city":"Dilbeek",
    "sg:classifiers":[
        {
            "category":"Community Center",
            "subcategory":"Youth",
            "type":"Public Place"
        }
    ],
    "sg:phone":"+32 2 569 14 45",
    "sg:postcode":"1700",
    "sg:province":"Vlaams-Brabant",
    "sg:tags":[
        "club"
    ],
    "wof:name":"Neerhof (het)",
    "wof:placetype":"venue"
},
  "geometry": {"coordinates":[4.2590589523,50.8387069702],"type":"Point"}
}