{
  "type": "Feature",
  "properties": {
    "iso:country":"BE",
    "sg:address":"Rue De La Gare 11",
    "sg:city":"Rochefort (eprave)",
    "sg:classifiers":[
        {
            "category":"Building & Trades",
            "subcategory":"Landscaping Services",
            "type":"Services"
        }
    ],
    "sg:phone":"+32 84 38 98 53",
    "sg:postcode":"5580",
    "sg:province":"Namur",
    "sg:tags":[
        "gardening",
        "garden",
        "maintenance"
    ],
    "wof:name":"Lambert S",
    "wof:placetype":"venue"
},
  "geometry": {"coordinates":[5.1623029709,50.1452789307],"type":"Point"}
}