{
  "type": "Feature",
  "properties": {
    "iso:country":"BE",
    "sg:address":"Veldstraat 26",
    "sg:city":"Wervik",
    "sg:classifiers":[
        {
            "category":"Cafe",
            "type":"Food & Drink"
        }
    ],
    "sg:phone":"+32 56 31 55 30",
    "sg:postcode":"8940",
    "sg:province":"West-Vlaanderen",
    "sg:tags":[
        "caf\u00e9s"
    ],
    "wof:name":"Robert Bille",
    "wof:placetype":"venue"
},
  "geometry": {"coordinates":[3.0232160091,50.8171806335],"type":"Point"}
}