{
  "type": "Feature",
  "properties": {
    "addr:full":"Nestor De Ti\u00c8restraat 106 Oudenaarde Oost-Vlaanderen 9700",
    "addr:housenumber":"106",
    "addr:postcode":"9700",
    "addr:street":"Nestor De Tie\u0300Restraat",
    "iso:country":"BE",
    "sg:address":"Nestor De Ti\u00c8restraat 106",
    "sg:city":"Oudenaarde",
    "sg:orig_category":"Banken and kredietinstellingen",
    "sg:phone":"+32 55 31 24 78",
    "sg:postcode":"9700",
    "sg:province":"Oost-Vlaanderen",
    "wof:name":"Dexia",
    "wof:placetype":"venue"
},
  "geometry": {"coordinates":[3.6180129051,50.8670196533],"type":"Point"}
}