{
  "type": "Feature",
  "properties": {
    "iso:country":"BE",
    "sg:address":"Hoogstraat 11",
    "sg:city":"Oudenburg",
    "sg:orig_category":"Rev\u00eatements de sols and murs. Peinture. Rev\u00eatements pour sols and murs",
    "sg:phone":"+32 59 26 60 75",
    "sg:postcode":"8460",
    "sg:province":"West-Vlaanderen",
    "wof:name":"Huis Van Hecke",
    "wof:placetype":"venue"
},
  "geometry": {"coordinates":[3.0055150986,51.1828842163],"type":"Point"}
}