{
  "type": "Feature",
  "properties": {
    "addr:full":"Galgestraat 41 Langemark-poelkapelle West-Vlaanderen 8920",
    "addr:housenumber":"41",
    "addr:postcode":"8920",
    "addr:street":"Galgestraat",
    "iso:country":"BE",
    "sg:address":"Galgestraat 41",
    "sg:city":"Langemark-poelkapelle",
    "sg:orig_category":"Rundveehouders Varkenskwekers",
    "sg:phone":"+32 57 48 82 67",
    "sg:postcode":"8920",
    "sg:province":"West-Vlaanderen",
    "wof:name":"De Kervel G. & G.",
    "wof:placetype":"venue"
},
  "geometry": {"coordinates":[2.9156320095,50.9323768616],"type":"Point"}
}