{
  "type": "Feature",
  "properties": {
    "iso:country":"BE",
    "sg:address":"Rosweg 54",
    "sg:city":"Lennik",
    "sg:orig_category":"Producteurs de fruits",
    "sg:phone":"+32 2 532 44 61",
    "sg:postcode":"1750",
    "sg:province":"Vlaams-Brabant",
    "wof:name":"Eduardus Eylenbosch",
    "wof:placetype":"venue"
},
  "geometry": {"coordinates":[4.1964211464,50.8199424744],"type":"Point"}
}