{
  "type": "Feature",
  "properties": {
    "addr:full":"Oude Hostartstraat 36 Genk Limburg 3600",
    "addr:housenumber":"36",
    "addr:postcode":"3600",
    "addr:street":"Oude Hostartstraat",
    "iso:country":"BE",
    "sg:address":"Oude Hostartstraat 36",
    "sg:city":"Genk",
    "sg:classifiers":[
        {
            "category":"Professional",
            "subcategory":"Art Services",
            "type":"Services"
        }
    ],
    "sg:phone":"+32 89 36 21 83",
    "sg:postcode":"3600",
    "sg:province":"Limburg",
    "sg:tags":[
        "graphic",
        "designer"
    ],
    "wof:name":"Studio Ango-dtp",
    "wof:placetype":"venue"
},
  "geometry": {"coordinates":[5.4958200455,50.9739379883],"type":"Point"}
}