{
  "type": "Feature",
  "properties": {
    "iso:country":"BE",
    "sg:address":"Rue Pont D'avroy 8",
    "sg:city":"Liege",
    "sg:orig_category":"V\u00eatements",
    "sg:phone":"+32 4 223 21 34",
    "sg:postcode":"4000",
    "sg:province":"Li\u00e8ge",
    "wof:name":"American Jeans",
    "wof:placetype":"venue"
},
  "geometry": {"coordinates":[5.5703868866,50.6409263611],"type":"Point"}
}