{
  "type": "Feature",
  "properties": {
    "addr:full":"Breughelpark 9 Box 50 Asse (zellik) Vlaams-Brabant 1731",
    "addr:housenumber":"9 box 50",
    "addr:postcode":"1731",
    "addr:street":"Breughelpark",
    "iso:country":"BE",
    "sg:address":"Breughelpark 9 Box 50",
    "sg:city":"Asse (zellik)",
    "sg:classifiers":[
        {
            "category":"Arts & Performance",
            "subcategory":"Theater",
            "type":"Entertainment"
        }
    ],
    "sg:postcode":"1731",
    "sg:province":"Vlaams-Brabant",
    "sg:tags":[
        "theatrical",
        "agency"
    ],
    "wof:name":"Classique Striptease Show",
    "wof:placetype":"venue"
},
  "geometry": {"coordinates":[4.2701039314,50.8847694397],"type":"Point"}
}