{
  "type": "Feature",
  "properties": {
    "iso:country":"BE",
    "sg:address":"Statiestraat 32b",
    "sg:city":"Nijlen",
    "sg:orig_category":"Agences de voyages",
    "sg:phone":"+32 3 481 69 69",
    "sg:postcode":"2560",
    "sg:province":"Antwerpen",
    "wof:name":"De Reisspecialist",
    "wof:placetype":"venue"
},
  "geometry": {"coordinates":[4.6689519882,51.1609268188],"type":"Point"}
}