{
  "type": "Feature",
  "properties": {
    "iso:country":"BE",
    "sg:address":"Rue Des Fontaines 11",
    "sg:city":"Hotton",
    "sg:classifiers":[
        {
            "category":"Freight",
            "type":"Transportation"
        }
    ],
    "sg:phone":"+32 84 46 77 85",
    "sg:postcode":"6990",
    "sg:province":"Luxembourg",
    "sg:tags":[
        "-",
        "transport"
    ],
    "wof:name":"Lecaillie A Transport",
    "wof:placetype":"venue"
},
  "geometry": {"coordinates":[5.4800829887,50.2847595215],"type":"Point"}
}