{
  "type": "Feature",
  "properties": {
    "iso:country":"BE",
    "sg:address":"Felix Roggemanskaai 16",
    "sg:city":"Halle (buizingen)",
    "sg:classifiers":[
        {
            "category":"Government",
            "subcategory":"Fire Station",
            "type":"Public Place"
        }
    ],
    "sg:phone":"+32 2 360 11 88",
    "sg:postcode":"1501",
    "sg:province":"Vlaams-Brabant",
    "sg:tags":[
        "water",
        "restoration",
        "damage"
    ],
    "wof:name":"Ren-o-vate Bvba",
    "wof:placetype":"venue"
},
  "geometry": {"coordinates":[4.2518901825,50.7486000061],"type":"Point"}
}