{
  "type": "Feature",
  "properties": {
    "addr:full":"Molenblookstraat 3a Zutendaal Limburg 3690",
    "addr:housenumber":"3a",
    "addr:postcode":"3690",
    "addr:street":"Molenblookstraat",
    "iso:country":"BE",
    "sg:address":"Molenblookstraat 3a",
    "sg:city":"Zutendaal",
    "sg:classifiers":[
        {
            "category":"Home & Garden",
            "subcategory":"Building Materials",
            "type":"Retail Goods"
        }
    ],
    "sg:phone":"+32 89 61 12 61",
    "sg:postcode":"3690",
    "sg:province":"Limburg",
    "sg:tags":[
        "aluminium",
        "construction",
        "-"
    ],
    "wof:name":"Aluminium Gapa",
    "wof:placetype":"venue"
},
  "geometry": {"coordinates":[5.5589962006,50.9394111633],"type":"Point"}
}