{
  "type": "Feature",
  "properties": {
    "addr:full":"Chauss\u00e9e De Ch\u00e2telet 121 Charleroi (gilly) Hainaut 6060",
    "addr:housenumber":"121",
    "addr:postcode":"6060",
    "addr:street":"Chausse\u0301E De Cha\u0302Telet",
    "iso:country":"BE",
    "sg:address":"Chauss\u00e9e De Ch\u00e2telet 121",
    "sg:city":"Charleroi (gilly)",
    "sg:classifiers":[
        {
            "category":"Professional",
            "subcategory":"Lawyer & Legal Services",
            "type":"Services"
        }
    ],
    "sg:phone":"+32 71 48 96 10",
    "sg:postcode":"6060",
    "sg:province":"Hainaut",
    "wof:name":"Zabeau C",
    "wof:placetype":"venue"
},
  "geometry": {"coordinates":[4.4880981445,50.4251937866],"type":"Point"}
}