{
  "type": "Feature",
  "properties": {
    "iso:country":"BE",
    "sg:address":"Arloncourt 14",
    "sg:city":"Bastogne",
    "sg:orig_category":"Eleveurs de bovins",
    "sg:phone":"+32 61 21 15 68",
    "sg:postcode":"6600",
    "sg:province":"Luxembourg",
    "wof:name":"Andre Lutgen",
    "wof:placetype":"venue"
},
  "geometry": {"coordinates":[5.7181549072,49.9966125488],"type":"Point"}
}