{
  "type": "Feature",
  "properties": {
    "iso:country":"BE",
    "sg:address":"Rue De Zone 23",
    "sg:city":"Mont-sur-marchienne",
    "sg:classifiers":[
        {
            "category":"Wholesale",
            "subcategory":"Metals & Minerals",
            "type":"Manufacturing & Wholesale Goods"
        }
    ],
    "sg:phone":"+32 71 47 10 40",
    "sg:postcode":"6032",
    "sg:province":"Hainaut",
    "sg:tags":[
        "wall",
        "facing",
        "sheet",
        "roof",
        "profiled"
    ],
    "wof:name":"Acompanyrs Grosjean S.a.",
    "wof:placetype":"venue"
},
  "geometry": {"coordinates":[4.400329113,50.3963737488],"type":"Point"}
}