{
  "type": "Feature",
  "properties": {
    "iso:country":"BE",
    "sg:address":"Sint-gillislaan 35",
    "sg:city":"Dendermonde",
    "sg:orig_category":"M\u00e9decins and sp\u00e9cialistes",
    "sg:phone":"+32 52 22 00 47",
    "sg:postcode":"9200",
    "sg:province":"Oost-Vlaanderen",
    "wof:name":"A. Woods",
    "wof:placetype":"venue"
},
  "geometry": {"coordinates":[4.1075181961,51.0221481323],"type":"Point"}
}