{
  "type": "Feature",
  "properties": {
    "iso:country":"BE",
    "sg:address":"Burgemeester Gillonlaan 22",
    "sg:city":"Kortrijk",
    "sg:classifiers":[
        {
            "category":"Bakery",
            "type":"Food & Drink"
        }
    ],
    "sg:phone":"+32 56 21 34 40",
    "sg:postcode":"8500",
    "sg:province":"West-Vlaanderen",
    "sg:tags":[
        "confectioner",
        "baker"
    ],
    "wof:name":"Debacker E",
    "wof:placetype":"venue"
},
  "geometry": {"coordinates":[3.2790269852,50.8186225891],"type":"Point"}
}