{
  "type": "Feature",
  "properties": {
    "iso:country":"BE",
    "sg:address":"Weg Naar Opoeteren 167",
    "sg:city":"Opglabbeek",
    "sg:classifiers":[
        {
            "category":"Home & Garden",
            "subcategory":"Building Materials",
            "type":"Retail Goods"
        }
    ],
    "sg:phone":"+32 89 85 44 59",
    "sg:postcode":"3660",
    "sg:province":"Limburg",
    "sg:tags":[
        "veranda"
    ],
    "wof:name":"Mecona Bvba",
    "wof:placetype":"venue"
},
  "geometry": {"coordinates":[5.5991501808,51.0492782593],"type":"Point"}
}