{
  "type": "Feature",
  "properties": {
    "addr:full":"Meistraat 3 Kermt Limburg 3510",
    "addr:housenumber":"3",
    "addr:postcode":"3510",
    "addr:street":"Meistraat",
    "iso:country":"BE",
    "sg:address":"Meistraat 3",
    "sg:city":"Kermt",
    "sg:orig_category":"Woningbouw",
    "sg:phone":"+32 477 28 14 46",
    "sg:postcode":"3510",
    "sg:province":"Limburg",
    "wof:name":"Elibo",
    "wof:placetype":"venue"
},
  "geometry": {"coordinates":[5.2406768799,50.948097229],"type":"Point"}
}