{
  "type": "Feature",
  "properties": {
    "addr:full":"Bredabaan 582 Brasschaat Antwerpen 2930",
    "addr:housenumber":"582",
    "addr:postcode":"2930",
    "addr:street":"Bredabaan",
    "iso:country":"BE",
    "sg:address":"Bredabaan 582",
    "sg:city":"Brasschaat",
    "sg:orig_category":"Tuinbenodigdheden",
    "sg:phone":"+32 3 651 84 31",
    "sg:postcode":"2930",
    "sg:province":"Antwerpen",
    "wof:name":"De Sierspar",
    "wof:placetype":"venue"
},
  "geometry": {"coordinates":[4.5058221817,51.3063392639],"type":"Point"}
}