{
  "type": "Feature",
  "properties": {
    "addr:full":"Maastrichtersteenweg 5 Tongeren Limburg 3700",
    "addr:housenumber":"5",
    "addr:postcode":"3700",
    "addr:street":"Maastrichtersteenweg",
    "iso:country":"BE",
    "sg:address":"Maastrichtersteenweg 5",
    "sg:city":"Tongeren",
    "sg:orig_category":"Peinture. Rev\u00eatements pour sols and murs. D\u00e9corateurs d'int\u00e9rieur",
    "sg:phone":"+32 12 23 70 65",
    "sg:postcode":"3700",
    "sg:province":"Limburg",
    "wof:name":"Delnat",
    "wof:placetype":"venue"
},
  "geometry": {"coordinates":[5.4746937752,50.7831382751],"type":"Point"}
}