{
  "type": "Feature",
  "properties": {
    "iso:country":"BE",
    "sg:address":"Rue De Vieusart 5",
    "sg:city":"Chaumont-gistoux",
    "sg:classifiers":[
        {
            "category":"Building & Trades",
            "subcategory":"Landscaping Services",
            "type":"Services"
        }
    ],
    "sg:phone":"+32 10 68 02 60",
    "sg:postcode":"1325",
    "sg:province":"Brabant Wallon",
    "sg:tags":[
        "architect",
        "landscape"
    ],
    "wof:name":"Arboris Sprl",
    "wof:placetype":"venue"
},
  "geometry": {"coordinates":[4.6813797951,50.6806373596],"type":"Point"}
}