{
  "type": "Feature",
  "properties": {
    "addr:full":"Avenue Blonden 50 Box 11 Li\u00e8ge 1 Li\u00e8ge 4000",
    "addr:housenumber":"50 box 11;1",
    "addr:postcode":"4000",
    "addr:street":"Avenue Blonden;Lie\u0300Ge",
    "iso:country":"BE",
    "sg:address":"Avenue Blonden 50 Box 11",
    "sg:city":"Li\u00e8ge 1",
    "sg:classifiers":[
        {
            "category":"Banks & Credit Unions",
            "subcategory":"Financial Services",
            "type":"Services"
        }
    ],
    "sg:phone":"+32 4 252 00 19",
    "sg:postcode":"4000",
    "sg:province":"Li\u00e8ge",
    "sg:tags":[
        "loan",
        "mortgage"
    ],
    "wof:name":"Cr\u00e9dit Plus (le)",
    "wof:placetype":"venue"
},
  "geometry": {"coordinates":[5.570333004,50.6287689209],"type":"Point"}
}