{
  "type": "Feature",
  "properties": {
    "addr:full":"Hubert-jean Coenenstraat 10 Oudergem/auderghem Bruxelles-Capitale 1160",
    "addr:housenumber":"10",
    "addr:postcode":"1160",
    "addr:street":"Hubert-Jean Coenenstraat;/",
    "iso:country":"BE",
    "sg:address":"Hubert-jean Coenenstraat 10",
    "sg:city":"Oudergem/auderghem",
    "sg:orig_category":"Artsen and specialisten",
    "sg:phone":"+32 2 673 98 94",
    "sg:postcode":"1160",
    "sg:province":"Bruxelles-Capitale",
    "wof:name":"Sylvie Van Den Eynde",
    "wof:placetype":"venue"
},
  "geometry": {"coordinates":[4.4380822182,50.8005180359],"type":"Point"}
}