{
  "type": "Feature",
  "properties": {
    "addr:full":"Hoornblaas 4 Scherpenheuvel-zichem (zichem) Vlaams-Brabant 3271",
    "addr:housenumber":"4",
    "addr:postcode":"3271",
    "addr:street":"Hoornblaas",
    "iso:country":"BE",
    "sg:address":"Hoornblaas 4",
    "sg:city":"Scherpenheuvel-zichem (zichem)",
    "sg:classifiers":[
        {
            "category":"Wholesale",
            "subcategory":"Furniture",
            "type":"Manufacturing & Wholesale Goods"
        }
    ],
    "sg:phone":"+32 473 97 49 63",
    "sg:postcode":"3271",
    "sg:province":"Vlaams-Brabant",
    "sg:tags":[
        "-",
        "collectivities"
    ],
    "wof:name":"Arcedes",
    "wof:placetype":"venue"
},
  "geometry": {"coordinates":[4.99229002,51.009563446],"type":"Point"}
}