{
  "type": "Feature",
  "properties": {
    "addr:full":"Sint-rochusstraat 20 Halle Vlaams-Brabant 1500",
    "addr:housenumber":"20",
    "addr:postcode":"1500",
    "addr:street":"Sint-Rochusstraat",
    "iso:country":"BE",
    "sg:address":"Sint-rochusstraat 20",
    "sg:city":"Halle",
    "sg:orig_category":"Pain, p\u00e2tisseries and confiseries",
    "sg:phone":"+32 2 356 01 32",
    "sg:postcode":"1500",
    "sg:province":"Vlaams-Brabant",
    "wof:name":"Bruno Decuyper",
    "wof:placetype":"venue"
},
  "geometry": {"coordinates":[4.2390727997,50.7315406799],"type":"Point"}
}