{
  "type": "Feature",
  "properties": {
    "addr:full":"Bilzerbaan 77 Lanaken (veldwezelt) Limburg 3620",
    "addr:housenumber":"77",
    "addr:postcode":"3620",
    "addr:street":"Bilzerbaan",
    "iso:country":"BE",
    "sg:address":"Bilzerbaan 77",
    "sg:city":"Lanaken (veldwezelt)",
    "sg:orig_category":"Non-Classified Establishments",
    "sg:phone":"+32 89 71 33 88",
    "sg:postcode":"3620",
    "sg:province":"Limburg",
    "wof:name":"Darius Chocolaterie",
    "wof:placetype":"venue"
},
  "geometry": {"coordinates":[5.6551351547,50.8912277222],"type":"Point"}
}