{
  "type": "Feature",
  "properties": {
    "iso:country":"BE",
    "sg:address":"Eikerlandstraat 6",
    "sg:city":"Puurs (ruisbroek)",
    "sg:classifiers":[
        {
            "category":"Professional",
            "subcategory":"Testing Lab",
            "type":"Services"
        }
    ],
    "sg:phone":"+32 3 886 84 05",
    "sg:postcode":"2870",
    "sg:province":"Antwerpen",
    "sg:tags":[
        "chemist"
    ],
    "wof:name":"Bogaerts M",
    "wof:placetype":"venue"
},
  "geometry": {"coordinates":[4.3274922371,51.0778617859],"type":"Point"}
}