{
  "type": "Feature",
  "properties": {
    "addr:full":"Maesstraat 73 Elsene/ixelles Bruxelles-Capitale 1050",
    "addr:housenumber":"73",
    "addr:postcode":"1050",
    "addr:street":"Maesstraat",
    "iso:country":"BE",
    "sg:address":"Maesstraat 73",
    "sg:city":"Elsene/ixelles",
    "sg:orig_category":"Medische apparatuur, orthopedische artikelen and prothesen Fab",
    "sg:phone":"+32 2 647 77 57",
    "sg:postcode":"1050",
    "sg:province":"Bruxelles-Capitale",
    "wof:name":"Marc Desmecht",
    "wof:placetype":"venue"
},
  "geometry": {"coordinates":[4.3722681999,50.8307266235],"type":"Point"}
}