{
  "type": "Feature",
  "properties": {
    "iso:country":"BE",
    "sg:address":"Haardstraat 1",
    "sg:city":"Genk (waterschei)",
    "sg:orig_category":"Non-Classified Establishments",
    "sg:phone":"+32 89 84 49 25",
    "sg:postcode":"3600",
    "sg:province":"Limburg",
    "wof:name":"Eurolab Cosmetics Nv",
    "wof:placetype":"venue"
},
  "geometry": {"coordinates":[5.5078940392,51.0060272217],"type":"Point"}
}