{
  "type": "Feature",
  "properties": {
    "iso:country":"BE",
    "sg:address":"Moniestraat 53",
    "sg:city":"Zemst",
    "sg:orig_category":"Woningbouw",
    "sg:phone":"+32 15 61 01 62",
    "sg:postcode":"1981",
    "sg:province":"Vlaams-Brabant",
    "wof:name":"De Nijs Jos",
    "wof:placetype":"venue"
},
  "geometry": {"coordinates":[4.490254879,50.9908943176],"type":"Point"}
}