{
  "type": "Feature",
  "properties": {
    "addr:full":". Libin (groot) Luxembourg 6890",
    "addr:postcode":"6890",
    "addr:street":"Groot Luxembourg",
    "iso:country":"BE",
    "sg:address":".",
    "sg:city":"Libin (groot)",
    "sg:orig_category":"Apotheken",
    "sg:phone":"+32 900 10 500",
    "sg:postcode":"6890",
    "sg:province":"Luxembourg",
    "wof:name":"Apothekers Van Wacht",
    "wof:placetype":"venue"
},
  "geometry": {"coordinates":[5.2562999725,49.9827537537],"type":"Point"}
}