{
  "type": "Feature",
  "properties": {
    "addr:full":"Bruneaustraat 74 Gooik (kester) Vlaams-Brabant 1755",
    "addr:housenumber":"74;1755",
    "addr:street":"Bruneaustraat",
    "iso:country":"BE",
    "sg:address":"Bruneaustraat 74",
    "sg:city":"Gooik (kester)",
    "sg:classifiers":[
        {
            "category":"Health Services",
            "subcategory":"Health Practitioner",
            "type":"Services"
        }
    ],
    "sg:phone":"+32 54 56 68 63",
    "sg:postcode":"1755",
    "sg:province":"Vlaams-Brabant",
    "sg:tags":[
        "physiotherapist"
    ],
    "wof:name":"De Doncker Anne-mie",
    "wof:placetype":"venue"
},
  "geometry": {"coordinates":[4.1192002296,50.7638893127],"type":"Point"}
}