{
  "type": "Feature",
  "properties": {
    "iso:country":"BE",
    "sg:address":"Chauss\u00c9e De Louvain 21",
    "sg:city":"Beauvechain",
    "sg:orig_category":"Banques and organismes de cr\u00e9dit",
    "sg:phone":"+32 10 86 63 86",
    "sg:postcode":"1320",
    "sg:province":"Brabant Wallon",
    "wof:name":"Fortis",
    "wof:placetype":"venue"
},
  "geometry": {"coordinates":[4.7159070969,50.7807693481],"type":"Point"}
}