{
  "type": "Feature",
  "properties": {
    "iso:country":"BE",
    "sg:address":"Marktplein 56",
    "sg:city":"Sint-lievens-houtem",
    "sg:orig_category":"Dranken",
    "sg:phone":"+32 53 62 25 94",
    "sg:postcode":"9520",
    "sg:province":"Oost-Vlaanderen",
    "wof:name":"Pede",
    "wof:placetype":"venue"
},
  "geometry": {"coordinates":[3.8559780121,50.9207839966],"type":"Point"}
}