{
  "type": "Feature",
  "properties": {
    "addr:full":"Begijnenstraat 23 Turnhout Antwerpen 2300",
    "addr:housenumber":"23",
    "addr:postcode":"2300",
    "addr:street":"Begijnenstraat",
    "iso:country":"BE",
    "sg:address":"Begijnenstraat 23",
    "sg:city":"Turnhout",
    "sg:orig_category":"Eclairage et \u00e9quipements du foyer. Biens d'occasion",
    "sg:phone":"+32 14 41 53 38",
    "sg:postcode":"2300",
    "sg:province":"Antwerpen",
    "wof:name":"Oxfam Wereldwinkel",
    "wof:placetype":"venue"
},
  "geometry": {"coordinates":[4.9413070679,51.326374054],"type":"Point"}
}