{
  "type": "Feature",
  "properties": {
    "iso:country":"BE",
    "sg:address":"Kampenhoutsebaan 16",
    "sg:city":"Zemst (elewijt)",
    "sg:classifiers":[
        {
            "category":"Retail",
            "subcategory":"Event Space",
            "type":"Services"
        }
    ],
    "sg:phone":"+32 15 62 10 50",
    "sg:postcode":"1982",
    "sg:province":"Vlaams-Brabant",
    "sg:tags":[
        "pipeline"
    ],
    "wof:name":"Brugg Pipesystems Nv",
    "wof:placetype":"venue"
},
  "geometry": {"coordinates":[4.5076022148,50.9745597839],"type":"Point"}
}