{
  "type": "Feature",
  "properties": {
    "addr:full":"Kasteelstraat 36 Kruishoutem Oost-Vlaanderen 9770",
    "addr:housenumber":"36",
    "addr:postcode":"9770",
    "addr:street":"Kasteelstraat",
    "iso:country":"BE",
    "sg:address":"Kasteelstraat 36",
    "sg:city":"Kruishoutem",
    "sg:orig_category":"Alimentation sp\u00e9cialis\u00e9e. Cr\u00e9meries",
    "sg:phone":"+32 9 383 50 27",
    "sg:postcode":"9770",
    "sg:province":"Oost-Vlaanderen",
    "wof:name":"Upignac Le Foie Gras",
    "wof:placetype":"venue"
},
  "geometry": {"coordinates":[3.5624079704,50.9174461365],"type":"Point"}
}