{
  "type": "Feature",
  "properties": {
    "iso:country":"BE",
    "sg:address":"Bissegemstraat 25",
    "sg:city":"Wevelgem",
    "sg:orig_category":"Textiel",
    "sg:phone":"+32 56 40 09 85",
    "sg:postcode":"8560",
    "sg:province":"West-Vlaanderen",
    "wof:name":"Naaiboetiek",
    "wof:placetype":"venue"
},
  "geometry": {"coordinates":[3.2056879997,50.8423461914],"type":"Point"}
}