{
  "type": "Feature",
  "properties": {
    "addr:full":"Prins Van Luiklaan 162 Anderlecht/anderlecht Bruxelles-Capitale 1070",
    "addr:housenumber":"162",
    "addr:postcode":"1070",
    "addr:street":"Prins Van Luiklaan",
    "iso:country":"BE",
    "sg:address":"Prins Van Luiklaan 162",
    "sg:city":"Anderlecht/anderlecht",
    "sg:orig_category":"Artiesten and kunstenaars",
    "sg:phone":"+32 2 522 75 79",
    "sg:postcode":"1070",
    "sg:province":"Bruxelles-Capitale",
    "wof:name":"J. Vanopdenbosch",
    "wof:placetype":"venue"
},
  "geometry": {"coordinates":[4.3029198647,50.8423538208],"type":"Point"}
}