{
  "type": "Feature",
  "properties": {
    "iso:country":"BE",
    "sg:address":"Ruiseledesteenweg 60ba",
    "sg:city":"Wingene",
    "sg:orig_category":"Entretien and r\u00e9parations de voitures",
    "sg:phone":"+32 51 65 73 80",
    "sg:postcode":"8750",
    "sg:province":"West-Vlaanderen",
    "wof:name":"Carrosserie Vromman",
    "wof:placetype":"venue"
},
  "geometry": {"coordinates":[3.3018200397,51.055431366],"type":"Point"}
}