{
  "type": "Feature",
  "properties": {
    "addr:full":"Spoorstraat 17 Bilzen Limburg 3740",
    "addr:housenumber":"17",
    "addr:postcode":"3740",
    "addr:street":"Spoorstraat",
    "iso:country":"BE",
    "sg:address":"Spoorstraat 17",
    "sg:city":"Bilzen",
    "sg:orig_category":"Fleurs and plantes",
    "sg:phone":"+32 89 41 88 65",
    "sg:postcode":"3740",
    "sg:province":"Limburg",
    "wof:name":"Daniel Lathouwers",
    "wof:placetype":"venue"
},
  "geometry": {"coordinates":[5.5094609261,50.8777618408],"type":"Point"}
}