{
  "type": "Feature",
  "properties": {
    "addr:full":"Standonk 6 Geel Antwerpen 2440",
    "addr:housenumber":"6",
    "addr:postcode":"2440",
    "addr:street":"Standonk",
    "iso:country":"BE",
    "sg:address":"Standonk 6",
    "sg:city":"Geel",
    "sg:orig_category":"Services pour animaux domestiques",
    "sg:phone":"+32 14 58 38 33",
    "sg:postcode":"2440",
    "sg:province":"Antwerpen",
    "wof:name":"Pension Akbash",
    "wof:placetype":"venue"
},
  "geometry": {"coordinates":[4.9660568237,51.1510620117],"type":"Point"}
}