{
  "type": "Feature",
  "properties": {
    "addr:full":"Molenstraat 1ba Evergem Oost-Vlaanderen 9940",
    "addr:housenumber":"1ba",
    "addr:postcode":"9940",
    "addr:street":"Molenstraat;Oost-Vlaanderen",
    "iso:country":"BE",
    "sg:address":"Molenstraat 1ba",
    "sg:city":"Evergem",
    "sg:orig_category":"Traitements param\u00e9dicaux",
    "sg:phone":"+32 9 344 74 43",
    "sg:postcode":"9940",
    "sg:province":"Oost-Vlaanderen",
    "wof:name":"Wit-gele Kruis",
    "wof:placetype":"venue"
},
  "geometry": {"coordinates":[3.6728150845,51.1037406921],"type":"Point"}
}