{
  "type": "Feature",
  "properties": {
    "addr:full":"Rue De La Briqueterie 32 Eghez\u00c9e Namur 5310",
    "addr:housenumber":"32",
    "addr:postcode":"5310",
    "addr:street":"Rue De La Briqueterie",
    "iso:country":"BE",
    "sg:address":"Rue De La Briqueterie 32",
    "sg:city":"Eghez\u00c9e",
    "sg:orig_category":"Loodgieterij, verwarming and sanitaire installaties",
    "sg:phone":"+32 81 51 29 91",
    "sg:postcode":"5310",
    "sg:province":"Namur",
    "wof:name":"A.t.b.r.",
    "wof:placetype":"venue"
},
  "geometry": {"coordinates":[4.9105381966,50.5566864014],"type":"Point"}
}