{
  "type": "Feature",
  "properties": {
    "iso:country":"BE",
    "sg:address":"Rue De Philipeville39",
    "sg:city":"Charleroi",
    "sg:orig_category":"Rijscholen",
    "sg:phone":"+32 71 36 08 65",
    "sg:postcode":"6010",
    "sg:province":"Hainaut",
    "wof:name":"Auto-ecole Henry",
    "wof:placetype":"venue"
},
  "geometry": {"coordinates":[4.4677200317,50.3921051025],"type":"Point"}
}