{
  "type": "Feature",
  "properties": {
    "iso:country":"BE",
    "sg:address":"Pannestraat 227",
    "sg:city":"Veurne",
    "sg:orig_category":"Dranken Dranken Gh Voedingsspeciaalzaken",
    "sg:phone":"+32 58 31 21 74",
    "sg:postcode":"8630",
    "sg:province":"West-Vlaanderen",
    "wof:name":"Interbrew Veurne",
    "wof:placetype":"venue"
},
  "geometry": {"coordinates":[2.6416289806,51.0813751221],"type":"Point"}
}