{
  "type": "Feature",
  "properties": {
    "addr:full":"Bessemerstraat 22 Lanaken Limburg 3620",
    "addr:housenumber":"22",
    "addr:postcode":"3620",
    "addr:street":"Bessemerstraat",
    "iso:country":"BE",
    "sg:address":"Bessemerstraat 22",
    "sg:city":"Lanaken",
    "sg:classifiers":[
        {
            "category":"Building & Trades",
            "subcategory":"Plumbing",
            "type":"Services"
        }
    ],
    "sg:phone":"+32 89 71 55 50",
    "sg:postcode":"3620",
    "sg:province":"Limburg",
    "sg:tags":[
        "contractor"
    ],
    "wof:name":"Herreman A",
    "wof:placetype":"venue"
},
  "geometry": {"coordinates":[5.6504721642,50.8908538818],"type":"Point"}
}