{
  "type": "Feature",
  "properties": {
    "iso:country":"BE",
    "sg:address":"Boulevard Zenobe Gramme 212",
    "sg:city":"Herstal",
    "sg:classifiers":[
        {
            "category":"Cafe",
            "type":"Food & Drink"
        }
    ],
    "sg:postcode":"4040",
    "sg:province":"Li\u00e8ge",
    "sg:tags":[
        "caf\u00e9s"
    ],
    "wof:name":"Giovanni Contino",
    "wof:placetype":"venue"
},
  "geometry": {"coordinates":[5.6263661385,50.6578674316],"type":"Point"}
}