{
  "type": "Feature",
  "properties": {
    "iso:country":"BE",
    "sg:address":"Meerskant 2",
    "sg:city":"Lebbeke (denderbelle)",
    "sg:classifiers":[
        {
            "category":"Retail",
            "subcategory":"Event Space",
            "type":"Services"
        }
    ],
    "sg:phone":"+32 52 41 57 50",
    "sg:postcode":"9280",
    "sg:province":"Oost-Vlaanderen",
    "sg:tags":[
        "organisation"
    ],
    "wof:name":"Plektrum Events",
    "wof:placetype":"venue"
},
  "geometry": {"coordinates":[4.0859918594,51.0001525879],"type":"Point"}
}