{
  "type": "Feature",
  "properties": {
    "addr:full":"Rue Astrid 51 Peruwelz Hainaut 7600",
    "addr:housenumber":"51",
    "addr:postcode":"7600",
    "addr:street":"Rue Astrid;Hainaut",
    "iso:country":"BE",
    "sg:address":"Rue Astrid 51",
    "sg:city":"Peruwelz",
    "sg:orig_category":"Apotheken",
    "sg:phone":"+32 69 77 21 78",
    "sg:postcode":"7600",
    "sg:province":"Hainaut",
    "wof:name":"Bernard Cayman",
    "wof:placetype":"venue"
},
  "geometry": {"coordinates":[3.5913410187,50.5127639771],"type":"Point"}
}