{
  "type": "Feature",
  "properties": {
    "addr:full":"Rue De Bruxelles 42 Binche Hainaut 7130",
    "addr:housenumber":"42",
    "addr:postcode":"7130",
    "addr:street":"Rue De Bruxelles",
    "iso:country":"BE",
    "sg:address":"Rue De Bruxelles 42",
    "sg:city":"Binche",
    "sg:classifiers":[
        {
            "category":"Personal",
            "subcategory":"Nail Salon",
            "type":"Services"
        }
    ],
    "sg:phone":"+32 64 36 68 90",
    "sg:postcode":"7130",
    "sg:province":"Hainaut",
    "sg:tags":[
        "pedicure"
    ],
    "wof:name":"Libra Soins",
    "wof:placetype":"venue"
},
  "geometry": {"coordinates":[4.1679201126,50.4161491394],"type":"Point"}
}