{
  "type": "Feature",
  "properties": {
    "iso:country":"BE",
    "sg:address":"La-campagnette 1",
    "sg:city":"Marche-en-famenne",
    "sg:orig_category":"M\u00e9decins and sp\u00e9cialistes",
    "sg:phone":"+32 84 31 47 49",
    "sg:postcode":"6900",
    "sg:province":"Luxembourg",
    "wof:name":"Vincent Paris",
    "wof:placetype":"venue"
},
  "geometry": {"coordinates":[5.3495597839,50.2203712463],"type":"Point"}
}