{
  "type": "Feature",
  "properties": {
    "addr:full":"Battelsesteenweg 259 Mechelen Antwerpen 2800",
    "addr:housenumber":"259",
    "addr:postcode":"2800",
    "addr:street":"Battelsesteenweg",
    "iso:country":"BE",
    "sg:address":"Battelsesteenweg 259",
    "sg:city":"Mechelen",
    "sg:orig_category":"Enseignement maternel and primaire",
    "sg:phone":"+32 15 20 54 17",
    "sg:postcode":"2800",
    "sg:province":"Antwerpen",
    "wof:name":"Stedelijke Basisschool",
    "wof:placetype":"venue"
},
  "geometry": {"coordinates":[4.4612522125,51.030921936],"type":"Point"}
}