{
  "type": "Feature",
  "properties": {
    "addr:full":"Rue Prince Royal 102 Elsene/ixelles Bruxelles-Capitale 1050",
    "addr:housenumber":"102",
    "addr:postcode":"1050",
    "addr:street":"Rue Prince Royal",
    "iso:country":"BE",
    "sg:address":"Rue Prince Royal 102",
    "sg:city":"Elsene/ixelles",
    "sg:orig_category":"Traitement de donn\u00e9es",
    "sg:phone":"+32 2 509 57 11",
    "sg:postcode":"1050",
    "sg:province":"Bruxelles-Capitale",
    "wof:name":"Smals-mvm",
    "wof:placetype":"venue"
},
  "geometry": {"coordinates":[4.3594079018,50.833530426],"type":"Point"}
}