{
  "type": "Feature",
  "properties": {
    "iso:country":"BE",
    "sg:address":"Hauptstrasse 57",
    "sg:city":"Raeren",
    "sg:orig_category":"Boekhandels Kansspelen",
    "sg:phone":"+32 87 86 62 11",
    "sg:postcode":"4730",
    "sg:province":"Li\u00e8ge",
    "wof:name":"Zeitschriften Mauel",
    "wof:placetype":"venue"
},
  "geometry": {"coordinates":[6.1125707626,50.6753959656],"type":"Point"}
}