{
  "type": "Feature",
  "properties": {
    "iso:country":"BE",
    "sg:address":"Grand Place 1",
    "sg:city":"Mons",
    "sg:classifiers":[
        {
            "category":"Cafe",
            "type":"Food & Drink"
        }
    ],
    "sg:phone":"+32 65 36 18 68",
    "sg:postcode":"7000",
    "sg:province":"Hainaut",
    "sg:tags":[
        "snack-bars"
    ],
    "wof:name":"Henri (sandwicherie)",
    "wof:placetype":"venue"
},
  "geometry": {"coordinates":[3.9519600868,50.454158783],"type":"Point"}
}