{
  "type": "Feature",
  "properties": {
    "iso:country":"BE",
    "sg:address":"Antwerpsesteenweg 401",
    "sg:city":"Lier",
    "sg:orig_category":"Artsen and specialisten",
    "sg:phone":"+32 3 480 35 82",
    "sg:postcode":"2500",
    "sg:province":"Antwerpen",
    "wof:name":"F. Verheyden",
    "wof:placetype":"venue"
},
  "geometry": {"coordinates":[4.5402398109,51.1462440491],"type":"Point"}
}