{
  "type": "Feature",
  "properties": {
    "iso:country":"BE",
    "sg:address":"Kerkstraat 26",
    "sg:city":"Balen",
    "sg:classifiers":[
        {
            "category":"Professional",
            "subcategory":"Accounting & Tax Preparation",
            "type":"Services"
        }
    ],
    "sg:phone":"+32 14 81 19 09",
    "sg:postcode":"2490",
    "sg:province":"Antwerpen",
    "sg:tags":[
        "accountant"
    ],
    "wof:name":"Geubbelmans Willy Bvba",
    "wof:placetype":"venue"
},
  "geometry": {"coordinates":[5.1700558662,51.1729011536],"type":"Point"}
}