{
  "type": "Feature",
  "properties": {
    "addr:full":"Champs Elys\u00e9es 3 Ciney Namur 5590",
    "addr:housenumber":"3",
    "addr:postcode":"5590",
    "addr:street":"Elyse\u0301Es",
    "iso:country":"BE",
    "sg:address":"Champs Elys\u00e9es 3",
    "sg:city":"Ciney",
    "sg:classifiers":[
        {
            "category":"Autos & Motor Vehicles",
            "subcategory":"Automobile Sales",
            "type":"Retail Goods"
        }
    ],
    "sg:phone":"+32 83 21 12 52",
    "sg:postcode":"5590",
    "sg:province":"Namur",
    "sg:tags":[
        "car",
        "used",
        "-"
    ],
    "wof:name":"Beaujean R",
    "wof:placetype":"venue"
},
  "geometry": {"coordinates":[5.098197937,50.3132514954],"type":"Point"}
}