{
  "type": "Feature",
  "properties": {
    "addr:full":"Rue De Huy 61 Hannut Li\u00e8ge 4280",
    "addr:housenumber":"61",
    "addr:postcode":"4280",
    "addr:street":"Rue De Huy",
    "iso:country":"BE",
    "sg:address":"Rue De Huy 61",
    "sg:city":"Hannut",
    "sg:orig_category":"Onderdelen and accessoires voor auto's",
    "sg:phone":"+32 19 51 29 35",
    "sg:postcode":"4280",
    "sg:province":"Li\u00e8ge",
    "wof:name":"V.p.pneus",
    "wof:placetype":"venue"
},
  "geometry": {"coordinates":[5.0925440788,50.6644706726],"type":"Point"}
}