{
  "type": "Feature",
  "properties": {
    "iso:country":"BE",
    "sg:address":"Wellingstraat 97",
    "sg:city":"Destelbergen",
    "sg:classifiers":[
        {
            "category":"Sports & Exercise",
            "subcategory":"Sports Center",
            "type":"Entertainment"
        }
    ],
    "sg:phone":"+32 9 252 61 08",
    "sg:postcode":"9070",
    "sg:province":"Oost-Vlaanderen",
    "sg:tags":[
        "terrain",
        "hors",
        "de",
        "installation",
        "sportifs"
    ],
    "wof:name":"V/d Sype Jean-pierre",
    "wof:placetype":"venue"
},
  "geometry": {"coordinates":[3.8072109222,51.0088539124],"type":"Point"}
}