{
  "type": "Feature",
  "properties": {
    "addr:full":"Sterrenbosstraat 53 Nazareth Oost-Vlaanderen 9810",
    "addr:housenumber":"53",
    "addr:postcode":"9810",
    "addr:street":"Sterrenbosstraat",
    "iso:country":"BE",
    "sg:address":"Sterrenbosstraat 53",
    "sg:city":"Nazareth",
    "sg:classifiers":[
        {
            "category":"Health Services",
            "subcategory":"Doctor",
            "type":"Services"
        }
    ],
    "sg:phone":"+32 9 385 50 65",
    "sg:postcode":"9810",
    "sg:province":"Oost-Vlaanderen",
    "sg:tags":[
        "medicinephysicians",
        "surgeon"
    ],
    "wof:name":"Brijs S",
    "wof:placetype":"venue"
},
  "geometry": {"coordinates":[3.6077399254,50.9607200623],"type":"Point"}
}