{
  "type": "Feature",
  "properties": {
    "addr:full":"Ploegsteertstraat 117 Komen-waasten/comines-warneton Hainaut 7782",
    "addr:housenumber":"117",
    "addr:postcode":"7782",
    "addr:street":"Ploegsteertstraat",
    "iso:country":"BE",
    "sg:address":"Ploegsteertstraat 117",
    "sg:city":"Komen-waasten/comines-warneton",
    "sg:classifiers":[
        {
            "category":"Cafe",
            "type":"Food & Drink"
        }
    ],
    "sg:phone":"+32 56 58 96 15",
    "sg:postcode":"7782",
    "sg:province":"Hainaut",
    "sg:tags":[
        "caf\u00e9s"
    ],
    "wof:name":"La Ferme De Myko",
    "wof:placetype":"venue"
},
  "geometry": {"coordinates":[2.8795371056,50.7278747559],"type":"Point"}
}