{
  "type": "Feature",
  "properties": {
    "iso:country":"BE",
    "sg:address":"Guldendallaan 4b3",
    "sg:city":"Sint-pieters-woluwe/woluwe-saint-pierre",
    "sg:classifiers":[
        {
            "category":"Professional",
            "subcategory":"Accounting & Tax Preparation",
            "type":"Services"
        }
    ],
    "sg:phone":"+32 2 771 10 39",
    "sg:postcode":"1150",
    "sg:province":"Bruxelles-Capitale",
    "sg:tags":[
        "accountant"
    ],
    "wof:name":"Jean Debourse",
    "wof:placetype":"venue"
},
  "geometry": {"coordinates":[4.4258742332,50.8353271484],"type":"Point"}
}