{
  "type": "Feature",
  "properties": {
    "iso:country":"BE",
    "sg:address":"Alice Nahonlei 80",
    "sg:city":"Schoten",
    "sg:orig_category":"Bagage and lederwaren Fab Diverse producten Gh Kleding, schoenen and accessoires Gh",
    "sg:phone":"+32 3 685 00 38",
    "sg:postcode":"2900",
    "sg:province":"Antwerpen",
    "wof:name":"Van Dijk Regenschermen",
    "wof:placetype":"venue"
},
  "geometry": {"coordinates":[4.5376620293,51.2638816833],"type":"Point"}
}