{
  "type": "Feature",
  "properties": {
    "addr:full":"Tervuursesteenweg 301 Mechelen Antwerpen 2800",
    "addr:housenumber":"301",
    "addr:postcode":"2800",
    "addr:street":"Tervuursesteenweg",
    "iso:country":"BE",
    "sg:address":"Tervuursesteenweg 301",
    "sg:city":"Mechelen",
    "sg:classifiers":[
        {
            "category":"Fast Food",
            "type":"Food & Drink"
        }
    ],
    "sg:phone":"+32 15 43 24 54",
    "sg:postcode":"2800",
    "sg:province":"Antwerpen",
    "sg:tags":[
        "fried",
        "stand",
        "potato"
    ],
    "wof:name":"Amalga Bvba",
    "wof:placetype":"venue"
},
  "geometry": {"coordinates":[4.4862961769,51.0060653687],"type":"Point"}
}