{
  "type": "Feature",
  "properties": {
    "addr:full":"Koekoekstraat 53 Aartselaar Antwerpen 2630",
    "addr:housenumber":"53",
    "addr:postcode":"2630",
    "addr:street":"Koekoekstraat",
    "iso:country":"BE",
    "sg:address":"Koekoekstraat 53",
    "sg:city":"Aartselaar",
    "sg:orig_category":"Producteurs de l\u00e9gumes",
    "sg:phone":"+32 3 888 26 12",
    "sg:postcode":"2630",
    "sg:province":"Antwerpen",
    "wof:name":"Luc Verbruggen",
    "wof:placetype":"venue"
},
  "geometry": {"coordinates":[4.3591890335,51.1128501892],"type":"Point"}
}