{
  "type": "Feature",
  "properties": {
    "addr:full":"Vlaamsekaai 28-31 Antwerpen Antwerpen 2000",
    "addr:postcode":"28-31;2000",
    "addr:street":"Vlaamsekaai",
    "iso:country":"BE",
    "sg:address":"Vlaamsekaai 28-31",
    "sg:city":"Antwerpen",
    "sg:classifiers":[
        {
            "category":"Community Center",
            "type":"Public Place"
        }
    ],
    "sg:phone":"+32 3 238 71 41",
    "sg:postcode":"2000",
    "sg:province":"Antwerpen",
    "sg:tags":[
        "medical"
    ],
    "wof:name":"Stomatologisch Centrum Vlaamse Kaai",
    "wof:placetype":"venue"
},
  "geometry": {"coordinates":[4.3918762207,51.2104492188],"type":"Point"}
}