{
  "type": "Feature",
  "properties": {
    "addr:full":"Zwijnaardsesteenweg 12 Gent Oost-Vlaanderen 9000",
    "addr:housenumber":"12",
    "addr:postcode":"9000",
    "addr:street":"Zwijnaardsesteenweg;Oost-Vlaanderen",
    "iso:country":"BE",
    "sg:address":"Zwijnaardsesteenweg 12",
    "sg:city":"Gent",
    "sg:classifiers":[
        {
            "category":"Bars & Pubs",
            "type":"Food & Drink"
        }
    ],
    "sg:phone":"+32 9 222 13 94",
    "sg:postcode":"9000",
    "sg:province":"Oost-Vlaanderen",
    "wof:name":"Tobbe (de)",
    "wof:placetype":"venue"
},
  "geometry": {"coordinates":[3.7262759209,51.0367431641],"type":"Point"}
}