{
  "type": "Feature",
  "properties": {
    "iso:country":"BE",
    "sg:address":"Gentseheerweg 80",
    "sg:city":"Izegem",
    "sg:classifiers":[
        {
            "category":"Cafe",
            "type":"Food & Drink"
        }
    ],
    "sg:phone":"+32 51 31 28 28",
    "sg:postcode":"8870",
    "sg:province":"West-Vlaanderen",
    "sg:tags":[
        "caf\u00e9s"
    ],
    "wof:name":"M Craeynest",
    "wof:placetype":"venue"
},
  "geometry": {"coordinates":[3.2316119671,50.9167976379],"type":"Point"}
}