{
  "type": "Feature",
  "properties": {
    "addr:full":"Zwarte-arendlaan 23 Antwerpen Antwerpen 2100",
    "addr:housenumber":"23",
    "addr:postcode":"2100",
    "addr:street":"Zwarte-Arendlaan",
    "iso:country":"BE",
    "sg:address":"Zwarte-arendlaan 23",
    "sg:city":"Antwerpen",
    "sg:orig_category":"Experts-comptables",
    "sg:phone":"+32 3 325 13 77",
    "sg:postcode":"2100",
    "sg:province":"Antwerpen",
    "wof:name":"Ren\u00c9 Verdickt",
    "wof:placetype":"venue"
},
  "geometry": {"coordinates":[4.4278612137,51.206741333],"type":"Point"}
}