{
  "type": "Feature",
  "properties": {
    "iso:country":"BE",
    "sg:address":"Staatsbaan 147",
    "sg:city":"Kortemark",
    "sg:orig_category":"Paramedische behandelingen",
    "sg:phone":"+32 51 56 77 77",
    "sg:postcode":"8610",
    "sg:province":"West-Vlaanderen",
    "wof:name":"Ludwina Jaecques",
    "wof:placetype":"venue"
},
  "geometry": {"coordinates":[3.0162580013,51.0216026306],"type":"Point"}
}