{
  "type": "Feature",
  "properties": {
    "addr:full":"Ch\u00c2teau De Laval 2 Sainte-ode Luxembourg 6680",
    "addr:housenumber":"2",
    "addr:postcode":"6680",
    "addr:street":"Sainte-Ode Luxembourg",
    "iso:country":"BE",
    "sg:address":"Ch\u00c2teau De Laval 2",
    "sg:city":"Sainte-ode",
    "sg:orig_category":"Maisons de vacances",
    "sg:phone":"+32 61 68 81 21",
    "sg:postcode":"6680",
    "sg:province":"Luxembourg",
    "wof:name":"Denis Jean-marie",
    "wof:placetype":"venue"
},
  "geometry": {"coordinates":[5.5304489136,50.0108299255],"type":"Point"}
}