{
  "type": "Feature",
  "properties": {
    "addr:full":"Nederkouter 11 Gent Oost-Vlaanderen 9000",
    "addr:housenumber":"11",
    "addr:postcode":"9000",
    "addr:street":"Nederkouter;Oost-Vlaanderen",
    "iso:country":"BE",
    "sg:address":"Nederkouter 11",
    "sg:city":"Gent",
    "sg:classifiers":[
        {
            "category":"Food & Beverages",
            "subcategory":"Chocolate",
            "type":"Retail Goods"
        }
    ],
    "sg:phone":"+32 9 234 31 71",
    "sg:postcode":"9000",
    "sg:province":"Oost-Vlaanderen",
    "sg:tags":[
        "confectionery",
        "-"
    ],
    "wof:name":"Suikerhuisje ('t)",
    "wof:placetype":"venue"
},
  "geometry": {"coordinates":[3.7214660645,51.0486221313],"type":"Point"}
}