{
  "type": "Feature",
  "properties": {
    "addr:full":"Rue Alfred Defuisseaux 43 Awans Li\u00e8ge 4340",
    "addr:housenumber":"43",
    "addr:postcode":"4340",
    "addr:street":"Rue Alfred Defuisseaux",
    "iso:country":"BE",
    "sg:address":"Rue Alfred Defuisseaux 43",
    "sg:city":"Awans",
    "sg:classifiers":[
        {
            "category":"Health Services",
            "subcategory":"Doctor",
            "type":"Services"
        }
    ],
    "sg:phone":"+32 4 246 48 00",
    "sg:postcode":"4340",
    "sg:province":"Li\u00e8ge",
    "sg:tags":[
        "medicinephysicians",
        "surgeon"
    ],
    "wof:name":"Lacremans Alain",
    "wof:placetype":"venue"
},
  "geometry": {"coordinates":[5.4580731392,50.6661224365],"type":"Point"}
}