{
  "type": "Feature",
  "properties": {
    "addr:full":"Europaplein 36 Maasmechelen (eisden) Limburg 3630",
    "addr:housenumber":"36",
    "addr:postcode":"3630",
    "addr:street":"Europaplein",
    "iso:country":"BE",
    "sg:address":"Europaplein 36",
    "sg:city":"Maasmechelen (eisden)",
    "sg:classifiers":[
        {
            "category":"Education",
            "subcategory":"University",
            "type":"Public Place"
        }
    ],
    "sg:phone":"+32 89 77 09 55",
    "sg:postcode":"3630",
    "sg:province":"Limburg",
    "sg:tags":[
        "adult"
    ],
    "wof:name":"P.c.v.o.-kempen-maasland",
    "wof:placetype":"venue"
},
  "geometry": {"coordinates":[5.6961350441,50.963848114],"type":"Point"}
}