{
  "type": "Feature",
  "properties": {
    "addr:full":"Koolmijnenkaai 40 Sint-jans-molenbeek/molenbeek-saint-jean Bruxelles-Capitale 1080",
    "addr:housenumber":"40",
    "addr:postcode":"1080",
    "addr:street":"Koolmijnenkaai",
    "iso:country":"BE",
    "sg:address":"Koolmijnenkaai 40",
    "sg:city":"Sint-jans-molenbeek/molenbeek-saint-jean",
    "sg:classifiers":[
        {
            "category":"Cafe",
            "type":"Food & Drink"
        }
    ],
    "sg:phone":"+32 2 411 73 18",
    "sg:postcode":"1080",
    "sg:province":"Bruxelles-Capitale",
    "sg:tags":[
        "caf\u00e9s"
    ],
    "wof:name":"Caf\u00c9 Des Arcades",
    "wof:placetype":"venue"
},
  "geometry": {"coordinates":[4.3427119255,50.8555335999],"type":"Point"}
}