{
  "type": "Feature",
  "properties": {
    "iso:country":"BE",
    "sg:address":"Koning Leopold Iii Plein 1",
    "sg:city":"Blankenberge",
    "sg:orig_category":"Maroquinerie and articles de voyage",
    "sg:phone":"+32 50 41 16 46",
    "sg:postcode":"8370",
    "sg:province":"West-Vlaanderen",
    "wof:name":"Scarpo",
    "wof:placetype":"venue"
},
  "geometry": {"coordinates":[3.1317439079,51.3132019043],"type":"Point"}
}