{
  "type": "Feature",
  "properties": {
    "addr:full":"Markt 2 Wielsbeke West-Vlaanderen 8710",
    "addr:housenumber":"2",
    "addr:postcode":"8710",
    "addr:street":"Markt;West-Vlaanderen",
    "iso:country":"BE",
    "sg:address":"Markt 2",
    "sg:city":"Wielsbeke",
    "sg:orig_category":"Banken and kredietinstellingen",
    "sg:phone":"+32 56 66 67 07",
    "sg:postcode":"8710",
    "sg:province":"West-Vlaanderen",
    "wof:name":"Dexia",
    "wof:placetype":"venue"
},
  "geometry": {"coordinates":[3.3690760136,50.9093437195],"type":"Point"}
}