{
  "type": "Feature",
  "properties": {
    "addr:full":"Van Havermaetstraat 9 Sint-niklaas Oost-Vlaanderen 9100",
    "addr:housenumber":"9",
    "addr:postcode":"9100",
    "addr:street":"Havermaetstraat",
    "iso:country":"BE",
    "sg:address":"Van Havermaetstraat 9",
    "sg:city":"Sint-niklaas",
    "sg:classifiers":[
        {
            "category":"Personal",
            "subcategory":"Nail Salon",
            "type":"Services"
        }
    ],
    "sg:phone":"+32 3 778 03 08",
    "sg:postcode":"9100",
    "sg:province":"Oost-Vlaanderen",
    "sg:tags":[
        "pedicure"
    ],
    "wof:name":"De Moor I",
    "wof:placetype":"venue"
},
  "geometry": {"coordinates":[4.155479908,51.1711273193],"type":"Point"}
}