{
  "type": "Feature",
  "properties": {
    "addr:full":"Avenue Brugmann 99 Bruxelles (forest) Bruxelles-Capitale 1190",
    "addr:housenumber":"99",
    "addr:postcode":"1190",
    "addr:street":"Avenue Brugmann",
    "iso:country":"BE",
    "sg:address":"Avenue Brugmann 99",
    "sg:city":"Bruxelles (forest)",
    "sg:classifiers":[
        {
            "category":"Professional",
            "subcategory":"Computer Services",
            "type":"Services"
        }
    ],
    "sg:phone":"+32 2 344 19 22",
    "sg:postcode":"1190",
    "sg:province":"Bruxelles-Capitale",
    "sg:tags":[
        "webdesign",
        "-",
        "internet"
    ],
    "wof:name":"Acapella Sprl",
    "wof:placetype":"venue"
},
  "geometry": {"coordinates":[4.351380825,50.8194732666],"type":"Point"}
}