{
  "type": "Feature",
  "properties": {
    "iso:country":"BE",
    "sg:address":"Noendreef 11",
    "sg:city":"Beernem",
    "sg:classifiers":[
        {
            "category":"Building & Trades",
            "subcategory":"Construction",
            "type":"Services"
        }
    ],
    "sg:phone":"+32 50 79 24 67",
    "sg:postcode":"8730",
    "sg:province":"West-Vlaanderen",
    "sg:tags":[
        "stucco",
        "contractor"
    ],
    "wof:name":"Provost K",
    "wof:placetype":"venue"
},
  "geometry": {"coordinates":[3.3258140087,51.1068763733],"type":"Point"}
}