{
  "type": "Feature",
  "properties": {
    "iso:country":"BE",
    "sg:address":"Groenestraat 5",
    "sg:city":"Roeselare",
    "sg:orig_category":"Non-Classified Establishments",
    "sg:phone":"+32 51 22 15 81",
    "sg:postcode":"8800",
    "sg:province":"West-Vlaanderen",
    "wof:name":"Casteleyn J",
    "wof:placetype":"venue"
},
  "geometry": {"coordinates":[3.1186549664,50.9452934265],"type":"Point"}
}