{
  "type": "Feature",
  "properties": {
    "iso:country":"BE",
    "sg:address":"Place Du March\u00c9 10",
    "sg:city":"Li\u00c8ge",
    "sg:orig_category":"V\u00eatements. Sous-v\u00eatements and lingerie",
    "sg:phone":"+32 4 223 44 68",
    "sg:postcode":"4000",
    "sg:province":"Li\u00e8ge",
    "wof:name":"Fe. Nymph\u00c9a",
    "wof:placetype":"venue"
},
  "geometry": {"coordinates":[5.5760860443,50.6454963684],"type":"Point"}
}