{
  "type": "Feature",
  "properties": {
    "iso:country":"BE",
    "sg:address":"Sweigers Zuid 3a",
    "sg:city":"Temse",
    "sg:classifiers":[
        {
            "category":"Structure",
            "subcategory":"Office Building",
            "type":"Public Place"
        }
    ],
    "sg:phone":"+32 3 711 08 49",
    "sg:postcode":"9140",
    "sg:province":"Oost-Vlaanderen",
    "sg:tags":[
        "drawing"
    ],
    "wof:name":"Axispro Bvba",
    "wof:placetype":"venue"
},
  "geometry": {"coordinates":[4.2117938995,51.1456451416],"type":"Point"}
}