{
  "type": "Feature",
  "properties": {
    "addr:full":"Chauss\u00c9e De Mons 200 Anderlecht Bruxelles-Capitale 1070",
    "addr:housenumber":"200",
    "addr:postcode":"1070",
    "addr:street":"Chausse\u0301E De Mons",
    "iso:country":"BE",
    "sg:address":"Chauss\u00c9e De Mons 200",
    "sg:city":"Anderlecht",
    "sg:orig_category":"Pi\u00e8ces and accessoires de v\u00e9hicules automobiles D\u00e9taillants en pi\u00e8ces and accessoires de voitures",
    "sg:phone":"+32 2 521 36 44",
    "sg:postcode":"1070",
    "sg:province":"Bruxelles-Capitale",
    "wof:name":"Lepas",
    "wof:placetype":"venue"
},
  "geometry": {"coordinates":[4.3284897804,50.8410568237],"type":"Point"}
}