{
  "type": "Feature",
  "properties": {
    "addr:full":"Haaghoek 25 Brakel Oost-Vlaanderen 9660",
    "addr:housenumber":"25",
    "addr:postcode":"9660",
    "addr:street":"Haaghoek",
    "iso:country":"BE",
    "sg:address":"Haaghoek 25",
    "sg:city":"Brakel",
    "sg:orig_category":"Dakwerken Woningbouw",
    "sg:phone":"+32 55 45 52 18",
    "sg:postcode":"9660",
    "sg:province":"Oost-Vlaanderen",
    "wof:name":"Verbodak",
    "wof:placetype":"venue"
},
  "geometry": {"coordinates":[3.714400053,50.8249511719],"type":"Point"}
}