{
  "type": "Feature",
  "properties": {
    "addr:full":"Avenue Mariemont 17-1 La Louvi\u00e8re (haine-saint-pierre) Hainaut 7100",
    "addr:housenumber":"17-1",
    "addr:postcode":"7100",
    "addr:street":"Avenue Mariemont",
    "iso:country":"BE",
    "sg:address":"Avenue Mariemont 17-1",
    "sg:city":"La Louvi\u00e8re (haine-saint-pierre)",
    "sg:classifiers":[
        {
            "category":"Arena",
            "subcategory":"Sports Club",
            "type":"Entertainment"
        }
    ],
    "sg:phone":"+32 64 28 45 72",
    "sg:postcode":"7100",
    "sg:province":"Hainaut",
    "wof:name":"Squash Club La Louviere",
    "wof:placetype":"venue"
},
  "geometry": {"coordinates":[4.1850848198,50.4748649597],"type":"Point"}
}