{
  "type": "Feature",
  "properties": {
    "addr:full":"Stationsstraat 14 Landen Vlaams-Brabant 3400",
    "addr:housenumber":"14",
    "addr:postcode":"3400",
    "addr:street":"Stationsstraat",
    "iso:country":"BE",
    "sg:address":"Stationsstraat 14",
    "sg:city":"Landen",
    "sg:orig_category":"Pharmaciens",
    "sg:phone":"+32 11 88 11 20",
    "sg:postcode":"3400",
    "sg:province":"Vlaams-Brabant",
    "wof:name":"A. Meyers",
    "wof:placetype":"venue"
},
  "geometry": {"coordinates":[5.0808358192,50.7534751892],"type":"Point"}
}