{
  "type": "Feature",
  "properties": {
    "addr:full":"Stationsstraat 40 Harelbeke West-Vlaanderen 8530",
    "addr:housenumber":"40",
    "addr:postcode":"8530",
    "addr:street":"Stationsstraat",
    "iso:country":"BE",
    "sg:address":"Stationsstraat 40",
    "sg:city":"Harelbeke",
    "sg:orig_category":"Boekhouders",
    "sg:phone":"+32 56 72 06 06",
    "sg:postcode":"8530",
    "sg:province":"West-Vlaanderen",
    "wof:name":"Henk Vanmarcke",
    "wof:placetype":"venue"
},
  "geometry": {"coordinates":[3.3135020733,50.8556632996],"type":"Point"}
}