{
  "type": "Feature",
  "properties": {
    "iso:country":"BE",
    "sg:address":"Begijnenstraat 149",
    "sg:city":"Sint-niklaas",
    "sg:orig_category":"Slagers",
    "sg:phone":"+32 3 776 95 41",
    "sg:postcode":"9100",
    "sg:province":"Oost-Vlaanderen",
    "wof:name":"W. De Maeyer",
    "wof:placetype":"venue"
},
  "geometry": {"coordinates":[4.1499638557,51.1762199402],"type":"Point"}
}