{
  "type": "Feature",
  "properties": {
    "iso:country":"BE",
    "sg:address":"Wijnegembaan 6",
    "sg:city":"Schoten",
    "sg:classifiers":[
        {
            "category":"Wholesale",
            "subcategory":"Hardware",
            "type":"Manufacturing & Wholesale Goods"
        }
    ],
    "sg:phone":"+32 3 658 45 53",
    "sg:postcode":"2900",
    "sg:province":"Antwerpen",
    "sg:tags":[
        "lubricating",
        "compound"
    ],
    "wof:name":"Belco Motor Oil Nv",
    "wof:placetype":"venue"
},
  "geometry": {"coordinates":[4.5013980865,51.2419586182],"type":"Point"}
}