{
  "type": "Feature",
  "properties": {
    "iso:country":"BE",
    "sg:address":"Heldenlaan 12",
    "sg:city":"Zottegem",
    "sg:orig_category":"Apotheken",
    "sg:phone":"+32 9 360 00 59",
    "sg:postcode":"9620",
    "sg:province":"Oost-Vlaanderen",
    "wof:name":"Optifarm",
    "wof:placetype":"venue"
},
  "geometry": {"coordinates":[3.8098568916,50.8701210022],"type":"Point"}
}