{
  "type": "Feature",
  "properties": {
    "addr:full":"Rue Blanche Borne 32 Ch\u00e2telet (bouffioulx) Hainaut 6200",
    "addr:housenumber":"32",
    "addr:postcode":"6200",
    "addr:street":"Rue Blanche Borne",
    "iso:country":"BE",
    "sg:address":"Rue Blanche Borne 32",
    "sg:city":"Ch\u00e2telet (bouffioulx)",
    "sg:classifiers":[
        {
            "category":"Farming",
            "subcategory":"Fish & Marine Products",
            "type":"Manufacturing & Wholesale Goods"
        }
    ],
    "sg:phone":"+32 71 39 32 68",
    "sg:postcode":"6200",
    "sg:province":"Hainaut",
    "sg:tags":[
        "breeding"
    ],
    "wof:name":"Calitri Sprl",
    "wof:placetype":"venue"
},
  "geometry": {"coordinates":[4.4983000755,50.3908805847],"type":"Point"}
}