{
  "type": "Feature",
  "properties": {
    "iso:country":"BE",
    "sg:address":"Textielstraat 19",
    "sg:city":"Waregem",
    "sg:classifiers":[
        {
            "category":"Building & Trades",
            "subcategory":"Construction",
            "type":"Services"
        }
    ],
    "sg:phone":"+32 56 72 05 72",
    "sg:postcode":"8790",
    "sg:province":"West-Vlaanderen",
    "sg:tags":[
        "fork",
        "lift",
        "truck"
    ],
    "wof:name":"Hm International",
    "wof:placetype":"venue"
},
  "geometry": {"coordinates":[3.3996779919,50.8587722778],"type":"Point"}
}