{
  "type": "Feature",
  "properties": {
    "addr:full":"Merellaan 46 Ninove Oost-Vlaanderen 9400",
    "addr:housenumber":"46",
    "addr:postcode":"9400",
    "addr:street":"Merellaan",
    "iso:country":"BE",
    "sg:address":"Merellaan 46",
    "sg:city":"Ninove",
    "sg:classifiers":[
        {
            "category":"Retail",
            "subcategory":"Repair Shop",
            "type":"Services"
        }
    ],
    "sg:phone":"+32 54 32 62 11",
    "sg:postcode":"9400",
    "sg:province":"Oost-Vlaanderen",
    "sg:tags":[
        "jobbing",
        "tailoring",
        "-"
    ],
    "wof:name":"Clo\u00eb Bvba",
    "wof:placetype":"venue"
},
  "geometry": {"coordinates":[4.0320158005,50.842300415],"type":"Point"}
}