{
  "type": "Feature",
  "properties": {
    "iso:country":"BE",
    "sg:address":"Kerkhofstraat 7",
    "sg:city":"Niel",
    "sg:orig_category":"Computers and computerapparatuur Diverse informatica-activiteiten Informaticaconsulenten Onderhoud v",
    "sg:phone":"+32 3 844 69 27",
    "sg:postcode":"2845",
    "sg:province":"Antwerpen",
    "wof:name":"M.l.m.-systems",
    "wof:placetype":"venue"
},
  "geometry": {"coordinates":[4.3267889023,51.1109809875],"type":"Point"}
}