{
  "type": "Feature",
  "properties": {
    "addr:full":"Jan Rosierlaan 14 Lanaken Limburg 3620",
    "addr:housenumber":"14",
    "addr:postcode":"3620",
    "addr:street":"Jan Rosierlaan",
    "iso:country":"BE",
    "sg:address":"Jan Rosierlaan 14",
    "sg:city":"Lanaken",
    "sg:orig_category":"Dameskledingzaken",
    "sg:phone":"+32 89 72 32 50",
    "sg:postcode":"3620",
    "sg:province":"Limburg",
    "wof:name":"Elle Clothing",
    "wof:placetype":"venue"
},
  "geometry": {"coordinates":[5.6552600861,50.8885116577],"type":"Point"}
}