{
  "type": "Feature",
  "properties": {
    "addr:full":"Rue Haute 61 Sombreffe Namur 5140",
    "addr:housenumber":"61",
    "addr:postcode":"5140",
    "addr:street":"Rue Haute",
    "iso:country":"BE",
    "sg:address":"Rue Haute 61",
    "sg:city":"Sombreffe",
    "sg:orig_category":"Traitements param\u00e9dicaux",
    "sg:phone":"+32 71 88 82 80",
    "sg:postcode":"5140",
    "sg:province":"Namur",
    "wof:name":"M. Gardien",
    "wof:placetype":"venue"
},
  "geometry": {"coordinates":[4.5726060867,50.510017395],"type":"Point"}
}