{
  "type": "Feature",
  "properties": {
    "addr:full":"Medell 118 Amel/ambleve Li\u00e8ge 4770",
    "addr:housenumber":"118",
    "addr:postcode":"4770",
    "addr:street":"Medell",
    "iso:country":"BE",
    "sg:address":"Medell 118",
    "sg:city":"Amel/ambleve",
    "sg:classifiers":[
        {
            "category":"Cafe",
            "type":"Food & Drink"
        }
    ],
    "sg:phone":"+32 80 34 93 44",
    "sg:postcode":"4770",
    "sg:province":"Li\u00e8ge",
    "sg:tags":[
        "caf\u00e9s"
    ],
    "wof:name":"St.hubertus",
    "wof:placetype":"venue"
},
  "geometry": {"coordinates":[6.1876211166,50.3251914978],"type":"Point"}
}