{
  "type": "Feature",
  "properties": {
    "addr:full":"Place Du March\u00c9 18 Saint-hubert Luxembourg 6870",
    "addr:housenumber":"18",
    "addr:postcode":"6870",
    "addr:street":"Place Du Marche\u0301",
    "iso:country":"BE",
    "sg:address":"Place Du March\u00c9 18",
    "sg:city":"Saint-hubert",
    "sg:classifiers":[
        {
            "category":"Travel",
            "subcategory":"Hotels & Motels",
            "type":"Entertainment"
        }
    ],
    "sg:phone":"+32 61 61 10 23",
    "sg:postcode":"6870",
    "sg:province":"Luxembourg",
    "sg:tags":[
        "restaurant"
    ],
    "wof:name":"H\u00d4tel De L'abbaye",
    "wof:placetype":"venue"
},
  "geometry": {"coordinates":[5.3730831146,50.0259437561],"type":"Point"}
}