{
  "type": "Feature",
  "properties": {
    "addr:full":"Eerdegemstraat 76 Aalst Oost-Vlaanderen 9310",
    "addr:housenumber":"76",
    "addr:postcode":"9310",
    "addr:street":"Eerdegemstraat",
    "iso:country":"BE",
    "sg:address":"Eerdegemstraat 76",
    "sg:city":"Aalst",
    "sg:orig_category":"Installation \u00e9lectrique r\u00e9sidentielle. Plomberie, chauffage and installations sanitaires",
    "sg:phone":"+32 52 55 46 83",
    "sg:postcode":"9310",
    "sg:province":"Oost-Vlaanderen",
    "wof:name":"Freddy Van Den Abbeele",
    "wof:placetype":"venue"
},
  "geometry": {"coordinates":[4.1237821579,50.9661979675],"type":"Point"}
}