{
  "type": "Feature",
  "properties": {
    "iso:country":"BE",
    "sg:address":"Rue De Ninove 23",
    "sg:city":"Ronse/renaix",
    "sg:orig_category":"M\u00e9decins and sp\u00e9cialistes",
    "sg:phone":"+32 55 21 27 62",
    "sg:postcode":"9600",
    "sg:province":"Oost-Vlaanderen",
    "wof:name":"D. Spileers",
    "wof:placetype":"venue"
},
  "geometry": {"coordinates":[3.6057810783,50.7499885559],"type":"Point"}
}