{
  "type": "Feature",
  "properties": {
    "addr:full":"Kattestraat 43 Scherpenheuvel-zichem Vlaams-Brabant 3272",
    "addr:housenumber":"43",
    "addr:postcode":"3272",
    "addr:street":"Kattestraat",
    "iso:country":"BE",
    "sg:address":"Kattestraat 43",
    "sg:city":"Scherpenheuvel-zichem",
    "sg:orig_category":"Articles pour b\u00e9b\u00e9s. V\u00eatements pour b\u00e9b\u00e9s and enfants",
    "sg:phone":"+32 13 77 22 11",
    "sg:postcode":"3272",
    "sg:province":"Vlaams-Brabant",
    "wof:name":"Nijntje",
    "wof:placetype":"venue"
},
  "geometry": {"coordinates":[4.9398789406,50.9959945679],"type":"Point"}
}