{
  "type": "Feature",
  "properties": {
    "addr:full":"Chauss\u00c9e De Roeulx 246 Mons (grand) Hainaut 7000",
    "addr:housenumber":"246",
    "addr:postcode":"7000",
    "addr:street":"Chausse\u0301E De Roeulx",
    "iso:country":"BE",
    "sg:address":"Chauss\u00c9e De Roeulx 246",
    "sg:city":"Mons (grand)",
    "sg:classifiers":[
        {
            "category":"Communications",
            "subcategory":"Television Station",
            "type":"Services"
        }
    ],
    "sg:phone":"+32 65 36 21 32",
    "sg:postcode":"7000",
    "sg:province":"Hainaut",
    "sg:tags":[
        "video",
        "audio",
        "verhuur"
    ],
    "wof:name":"Vid\u00c9o News",
    "wof:placetype":"venue"
},
  "geometry": {"coordinates":[3.9792439938,50.4563293457],"type":"Point"}
}