{
  "type": "Feature",
  "properties": {
    "addr:full":"Place Verte 45 Verviers Li\u00e8ge 4800",
    "addr:housenumber":"45",
    "addr:postcode":"4800",
    "addr:street":"Place Verte",
    "iso:country":"BE",
    "sg:address":"Place Verte 45",
    "sg:city":"Verviers",
    "sg:classifiers":[
        {
            "category":"Health Services",
            "subcategory":"Health Practitioner",
            "type":"Services"
        }
    ],
    "sg:phone":"+32 87 35 13 13",
    "sg:postcode":"4800",
    "sg:province":"Li\u00e8ge",
    "sg:tags":[
        "physiotherapist"
    ],
    "wof:name":"Erkens Marie-france",
    "wof:placetype":"venue"
},
  "geometry": {"coordinates":[5.8620262146,50.5923805237],"type":"Point"}
}