{
  "type": "Feature",
  "properties": {
    "iso:country":"BE",
    "sg:address":"Rue Souveraine 88",
    "sg:city":"Bruxelles (ixelles)",
    "sg:classifiers":[
        {
            "category":"Professional",
            "subcategory":"Management & Consulting",
            "type":"Services"
        }
    ],
    "sg:phone":"+32 2 648 49 53",
    "sg:postcode":"1050",
    "sg:province":"Bruxelles-Capitale",
    "sg:tags":[
        "consultant"
    ],
    "wof:name":"C.i.t.s. Sa",
    "wof:placetype":"venue"
},
  "geometry": {"coordinates":[4.3628621101,50.8313598633],"type":"Point"}
}