{
  "type": "Feature",
  "properties": {
    "addr:full":"Gemeentestraat 14 Westerlo (oevel) Antwerpen 2260",
    "addr:housenumber":"14",
    "addr:postcode":"2260",
    "addr:street":"Gemeentestraat",
    "iso:country":"BE",
    "sg:address":"Gemeentestraat 14",
    "sg:city":"Westerlo (oevel)",
    "sg:classifiers":[
        {
            "category":"Bars & Pubs",
            "type":"Food & Drink"
        }
    ],
    "sg:phone":"+32 14 23 36 46",
    "sg:postcode":"2260",
    "sg:province":"Antwerpen",
    "wof:name":"De Babbelbox",
    "wof:placetype":"venue"
},
  "geometry": {"coordinates":[4.9057898521,51.1385574341],"type":"Point"}
}