{
  "type": "Feature",
  "properties": {
    "iso:country":"BE",
    "sg:address":"Rue De Renory 499",
    "sg:city":"Angleur",
    "sg:classifiers":[
        {
            "category":"Bars & Pubs",
            "subcategory":"Biergarten",
            "type":"Food & Drink"
        }
    ],
    "sg:phone":"+32 4 349 86 86",
    "sg:postcode":"4031",
    "sg:province":"Li\u00e8ge",
    "sg:tags":[
        "foil",
        "polyethylene"
    ],
    "wof:name":"Ace S.a.",
    "wof:placetype":"venue"
},
  "geometry": {"coordinates":[5.5660200119,50.6068305969],"type":"Point"}
}