{
  "type": "Feature",
  "properties": {
    "addr:full":"Melkweg 11 Kuurne West-Vlaanderen 8520",
    "addr:housenumber":"11",
    "addr:postcode":"8520",
    "addr:street":"Melkweg",
    "iso:country":"BE",
    "sg:address":"Melkweg 11",
    "sg:city":"Kuurne",
    "sg:orig_category":"Dranken",
    "sg:phone":"+32 56 72 41 20",
    "sg:postcode":"8520",
    "sg:province":"West-Vlaanderen",
    "wof:name":"Bossuyt Pol",
    "wof:placetype":"venue"
},
  "geometry": {"coordinates":[3.2647309303,50.8643112183],"type":"Point"}
}