{
  "type": "Feature",
  "properties": {
    "iso:country":"BE",
    "sg:address":"Rue G. Norga 37",
    "sg:city":"Brussel",
    "sg:orig_category":"Installation \u00e9lectrique r\u00e9sidentielle",
    "sg:phone":"+32 2 216 39 84",
    "sg:postcode":"1140",
    "sg:province":"Bruxelles-Capitale",
    "wof:name":"Alfa Hi Tech",
    "wof:placetype":"venue"
},
  "geometry": {"coordinates":[4.4016499519,50.8787078857],"type":"Point"}
}