{
  "type": "Feature",
  "properties": {
    "addr:full":"Rue Val\u00e8re Letot 46 Jurbise (herchies) Hainaut 7050",
    "addr:housenumber":"46",
    "addr:postcode":"7050",
    "addr:street":"Rue Vale\u0300Re Letot",
    "iso:country":"BE",
    "sg:address":"Rue Val\u00e8re Letot 46",
    "sg:city":"Jurbise (herchies)",
    "sg:classifiers":[
        {
            "category":"Banks & Credit Unions",
            "subcategory":"Investment Brokerage",
            "type":"Services"
        }
    ],
    "sg:phone":"+32 475 20 51 29",
    "sg:postcode":"7050",
    "sg:province":"Hainaut",
    "sg:tags":[
        "repair",
        "-",
        "installation",
        "sanitary",
        "article"
    ],
    "wof:name":"Dominique Ets",
    "wof:placetype":"venue"
},
  "geometry": {"coordinates":[3.8562159538,50.5111999512],"type":"Point"}
}