{
  "type": "Feature",
  "properties": {
    "iso:country":"BE",
    "sg:address":"Rue Saint-joseph 183bc",
    "sg:city":"Tellin",
    "sg:orig_category":"Sportclubs",
    "sg:phone":"+32 84 36 65 16",
    "sg:postcode":"6927",
    "sg:province":"Luxembourg",
    "wof:name":"T.c. Wellinois",
    "wof:placetype":"venue"
},
  "geometry": {"coordinates":[5.2245001793,50.0828018188],"type":"Point"}
}