{
  "type": "Feature",
  "properties": {
    "addr:full":"Rue Z\u00e9nobe Gramme 42 Hannut Li\u00e8ge 4280",
    "addr:housenumber":"42",
    "addr:postcode":"4280",
    "addr:street":"Rue Ze\u0301Nobe Gramme",
    "iso:country":"BE",
    "sg:address":"Rue Z\u00e9nobe Gramme 42",
    "sg:city":"Hannut",
    "sg:classifiers":[
        {
            "category":"Social Services",
            "type":"Services"
        }
    ],
    "sg:phone":"+32 19 51 09 79",
    "sg:postcode":"4280",
    "sg:province":"Li\u00e8ge",
    "wof:name":"Collectif Logement",
    "wof:placetype":"venue"
},
  "geometry": {"coordinates":[5.0753479004,50.6712646484],"type":"Point"}
}