{
  "type": "Feature",
  "properties": {
    "addr:full":"Baksveld 35 Westerlo Antwerpen 2260",
    "addr:housenumber":"35",
    "addr:postcode":"2260",
    "addr:street":"Baksveld",
    "iso:country":"BE",
    "sg:address":"Baksveld 35",
    "sg:city":"Westerlo",
    "sg:orig_category":"M\u00e9decins and sp\u00e9cialistes",
    "sg:phone":"+32 14 54 72 00",
    "sg:postcode":"2260",
    "sg:province":"Antwerpen",
    "wof:name":"Jan Gryffroy",
    "wof:placetype":"venue"
},
  "geometry": {"coordinates":[4.9170050621,51.0918769836],"type":"Point"}
}