{
  "type": "Feature",
  "properties": {
    "addr:full":"Pleinlaan 2bc119 Elsene/ixelles Bruxelles-Capitale 1050",
    "addr:postcode":"1050",
    "addr:street":"Pleinlaan",
    "iso:country":"BE",
    "sg:address":"Pleinlaan 2bc119",
    "sg:city":"Elsene/ixelles",
    "sg:orig_category":"Hoger onderwijs",
    "sg:phone":"+32 2 629 25 08",
    "sg:postcode":"1050",
    "sg:province":"Bruxelles-Capitale",
    "wof:name":"V.u.b.-fac.econ.soc.wet.",
    "wof:placetype":"venue"
},
  "geometry": {"coordinates":[4.3929901123,50.8209838867],"type":"Point"}
}