{
  "type": "Feature",
  "properties": {
    "iso:country":"BE",
    "sg:address":"Chemin Du Vieux Comt\u00c9 9",
    "sg:city":"Tournai",
    "sg:orig_category":"Eleveurs de bovins",
    "sg:phone":"+32 69 85 96 02",
    "sg:postcode":"7542",
    "sg:province":"Hainaut",
    "wof:name":"Jean-michel Bonte",
    "wof:placetype":"venue"
},
  "geometry": {"coordinates":[3.4176371098,50.6611442566],"type":"Point"}
}