{
  "type": "Feature",
  "properties": {
    "addr:full":"Chauss\u00c9e De Bruxelles 518 Waterloo Brabant Wallon 1410",
    "addr:housenumber":"518",
    "addr:postcode":"1410",
    "addr:street":"Chausse\u0301E De Bruxelles",
    "iso:country":"BE",
    "sg:address":"Chauss\u00c9e De Bruxelles 518",
    "sg:city":"Waterloo",
    "sg:orig_category":"Banques and organismes de cr\u00e9dit",
    "sg:phone":"+32 2 357 04 60",
    "sg:postcode":"1410",
    "sg:province":"Brabant Wallon",
    "wof:name":"Dexia",
    "wof:placetype":"venue"
},
  "geometry": {"coordinates":[4.4018220901,50.7022590637],"type":"Point"}
}