{
  "type": "Feature",
  "properties": {
    "iso:country":"BE",
    "sg:address":"Rue De L'ecluse 44",
    "sg:city":"Vis\u00e9 (lixhe)",
    "sg:classifiers":[
        {
            "category":"Farming",
            "subcategory":"Livestock Farm",
            "type":"Manufacturing & Wholesale Goods"
        }
    ],
    "sg:phone":"+32 475 93 81 31",
    "sg:postcode":"4600",
    "sg:province":"Li\u00e8ge",
    "sg:tags":[
        "buyer"
    ],
    "wof:name":"Stommen M",
    "wof:placetype":"venue"
},
  "geometry": {"coordinates":[5.6830821037,50.7446098328],"type":"Point"}
}