{
  "type": "Feature",
  "properties": {
    "addr:full":"Rue De Namur 40 Wavre Brabant Wallon 1300",
    "addr:housenumber":"40;1300",
    "addr:street":"Rue De Namur",
    "iso:country":"BE",
    "sg:address":"Rue De Namur 40",
    "sg:city":"Wavre",
    "sg:orig_category":"Rundveehouders",
    "sg:phone":"+32 10 22 21 78",
    "sg:postcode":"1300",
    "sg:province":"Brabant Wallon",
    "wof:name":"Marcel Libert",
    "wof:placetype":"venue"
},
  "geometry": {"coordinates":[4.6124300957,50.7124328613],"type":"Point"}
}