{
  "type": "Feature",
  "properties": {
    "iso:country":"BE",
    "sg:address":"Brusselsesteenweg 261",
    "sg:city":"Overijse",
    "sg:orig_category":"Grossistes divers",
    "sg:phone":"+32 2 687 76 29",
    "sg:postcode":"3090",
    "sg:province":"Vlaams-Brabant",
    "wof:name":"Fourmi-cords",
    "wof:placetype":"venue"
},
  "geometry": {"coordinates":[4.5016498566,50.7854309082],"type":"Point"}
}