{
  "type": "Feature",
  "properties": {
    "addr:full":"Chauss\u00c9e De Mons 434 Halle Vlaams-Brabant 1500",
    "addr:housenumber":"434",
    "addr:postcode":"1500",
    "addr:street":"Chausse\u0301E De Mons",
    "iso:country":"BE",
    "sg:address":"Chauss\u00c9e De Mons 434",
    "sg:city":"Halle",
    "sg:classifiers":[
        {
            "category":"Autos & Motor Vehicles",
            "subcategory":"Automobile Sales",
            "type":"Retail Goods"
        }
    ],
    "sg:phone":"+32 2 356 64 92",
    "sg:postcode":"1500",
    "sg:province":"Vlaams-Brabant",
    "sg:tags":[
        "mazda"
    ],
    "wof:name":"Garage Herremans J. B.v.b.a.",
    "wof:placetype":"venue"
},
  "geometry": {"coordinates":[4.2332601547,50.737953186],"type":"Point"}
}