{
  "type": "Feature",
  "properties": {
    "addr:full":"Krijgsgasthuisstraat 6 Gent Oost-Vlaanderen 9000",
    "addr:housenumber":"6",
    "addr:postcode":"9000",
    "addr:street":"Krijgsgasthuisstraat;Oost-Vlaanderen",
    "iso:country":"BE",
    "sg:address":"Krijgsgasthuisstraat 6",
    "sg:city":"Gent",
    "sg:classifiers":[
        {
            "category":"Cafe",
            "type":"Food & Drink"
        }
    ],
    "sg:phone":"+32 9 233 85 04",
    "sg:postcode":"9000",
    "sg:province":"Oost-Vlaanderen",
    "sg:tags":[
        "caf\u00e9s"
    ],
    "wof:name":"Caf\u00c9 Dikke Boom",
    "wof:placetype":"venue"
},
  "geometry": {"coordinates":[3.7043159008,51.0510978699],"type":"Point"}
}