{
  "type": "Feature",
  "properties": {
    "iso:country":"BE",
    "sg:address":"Rue Bruy\u00c8re Alconval 20",
    "sg:city":"Braine-l'alleud",
    "sg:orig_category":"G\u00e9om\u00e8tres",
    "sg:phone":"+32 2 648 33 51",
    "sg:postcode":"1420",
    "sg:province":"Brabant Wallon",
    "wof:name":"Jean-luc Perdaens",
    "wof:placetype":"venue"
},
  "geometry": {"coordinates":[-75.60595703120001,37.7877616882],"type":"Point"}
}