{
  "type": "Feature",
  "properties": {
    "iso:country":"BE",
    "sg:address":"Ch De Bruxelles 233",
    "sg:city":"Lodelinsart",
    "sg:classifiers":[
        {
            "category":"Home & Garden",
            "subcategory":"Furniture",
            "type":"Retail Goods"
        }
    ],
    "sg:phone":"+32 71 32 09 09",
    "sg:postcode":"6042",
    "sg:province":"Hainaut",
    "sg:tags":[
        "wood"
    ],
    "wof:name":"M\u00c9tiers Du Bois Sa",
    "wof:placetype":"venue"
},
  "geometry": {"coordinates":[4.4408321381,50.4279785156],"type":"Point"}
}