{
  "type": "Feature",
  "properties": {
    "addr:full":"Rue Des Meuniers 5 Remicourt (grand) Li\u00e8ge 4350",
    "addr:housenumber":"5",
    "addr:postcode":"4350",
    "addr:street":"Rue Des Meuniers;Grand Lie\u0300Ge",
    "iso:country":"BE",
    "sg:address":"Rue Des Meuniers 5",
    "sg:city":"Remicourt (grand)",
    "sg:orig_category":"Herstelling and restauratie van meubelen",
    "sg:phone":"+32 19 58 78 05",
    "sg:postcode":"4350",
    "sg:province":"Li\u00e8ge",
    "wof:name":"Terracchio Giacomo",
    "wof:placetype":"venue"
},
  "geometry": {"coordinates":[5.3025522232,50.6923904419],"type":"Point"}
}