{
  "type": "Feature",
  "properties": {
    "addr:full":"Groot-bijgaardenstraat 342 Sint-agatha-berchem/berchem-sa Bruxelles-Capitale 1082",
    "addr:housenumber":"342;/ berchem-sa",
    "addr:postcode":"1082",
    "addr:street":"Groot-Bijgaardenstraat;Sint-Agatha-Berchem",
    "iso:country":"BE",
    "sg:address":"Groot-bijgaardenstraat 342",
    "sg:city":"Sint-agatha-berchem/berchem-sa",
    "sg:orig_category":"Fleurs and plantes",
    "sg:phone":"+32 2 465 18 66",
    "sg:postcode":"1082",
    "sg:province":"Bruxelles-Capitale",
    "wof:name":"Van Acoleyen",
    "wof:placetype":"venue"
},
  "geometry": {"coordinates":[4.2909641266,50.8618164062],"type":"Point"}
}