{
  "type": "Feature",
  "properties": {
    "iso:country":"BE",
    "sg:address":"Torhoutsesteenweg 45",
    "sg:city":"Oostende",
    "sg:classifiers":[
        {
            "category":"Shopping",
            "subcategory":"Bicycles & Sporting Goods",
            "type":"Retail Goods"
        }
    ],
    "sg:phone":"+32 59 51 28 51",
    "sg:postcode":"8400",
    "sg:province":"West-Vlaanderen",
    "sg:tags":[
        "article",
        "de",
        "sport",
        "camping"
    ],
    "wof:name":"Espa Biljartspeciaalzaak",
    "wof:placetype":"venue"
},
  "geometry": {"coordinates":[2.9092130661,51.2256774902],"type":"Point"}
}