{
  "type": "Feature",
  "properties": {
    "addr:full":"Bredabaan 1203 Schoten Antwerpen 2900",
    "addr:housenumber":"1203",
    "addr:postcode":"2900",
    "addr:street":"Bredabaan",
    "iso:country":"BE",
    "sg:address":"Bredabaan 1203",
    "sg:city":"Schoten",
    "sg:orig_category":"Verlichting and huishoudartikelen",
    "sg:phone":"+32 3 646 54 41",
    "sg:postcode":"2900",
    "sg:province":"Antwerpen",
    "wof:name":"Home Market",
    "wof:placetype":"venue"
},
  "geometry": {"coordinates":[4.4635081291,51.2645111084],"type":"Point"}
}