{
  "type": "Feature",
  "properties": {
    "iso:country":"BE",
    "sg:address":"Oud-dorpsstraat 35",
    "sg:city":"Wuustwezel",
    "sg:orig_category":"Avocats and conseillers juridiques",
    "sg:phone":"+32 3 669 90 29",
    "sg:postcode":"2990",
    "sg:province":"Antwerpen",
    "wof:name":"A. De Proost",
    "wof:placetype":"venue"
},
  "geometry": {"coordinates":[4.5938930511,51.3886299133],"type":"Point"}
}