{
  "type": "Feature",
  "properties": {
    "iso:country":"BE",
    "sg:address":"Oude Geelsebaan 28",
    "sg:city":"Laakdal (veerle)",
    "sg:classifiers":[
        {
            "category":"Building & Trades",
            "subcategory":"Pest Control",
            "type":"Services"
        }
    ],
    "sg:phone":"+32 14 86 77 85",
    "sg:postcode":"2431",
    "sg:province":"Antwerpen",
    "sg:tags":[
        "painting",
        "contractor"
    ],
    "wof:name":"Stevens P",
    "wof:placetype":"venue"
},
  "geometry": {"coordinates":[4.9765172005,51.0675048828],"type":"Point"}
}