{
  "type": "Feature",
  "properties": {
    "iso:country":"BE",
    "sg:address":"Jonkershovestraat 103a",
    "sg:city":"Houthulst",
    "sg:classifiers":[
        {
            "category":"Bars & Pubs",
            "type":"Food & Drink"
        }
    ],
    "sg:phone":"+32 51 46 47 71",
    "sg:postcode":"8650",
    "sg:province":"West-Vlaanderen",
    "wof:name":"Extra Time",
    "wof:placetype":"venue"
},
  "geometry": {"coordinates":[2.9309849739,50.9722442627],"type":"Point"}
}