{
  "type": "Feature",
  "properties": {
    "iso:country":"BE",
    "sg:address":"Balland 1",
    "sg:city":"Anzegem",
    "sg:orig_category":"Architectes",
    "sg:phone":"+32 56 68 80 57",
    "sg:postcode":"8573",
    "sg:province":"West-Vlaanderen",
    "wof:name":"Geert Steenhaut",
    "wof:placetype":"venue"
},
  "geometry": {"coordinates":[3.4654951096,50.8068237305],"type":"Point"}
}