{
  "type": "Feature",
  "properties": {
    "iso:country":"BE",
    "sg:address":"Bruulstraat 116",
    "sg:city":"Haaltert",
    "sg:classifiers":[
        {
            "category":"Restaurant",
            "type":"Food & Drink"
        }
    ],
    "sg:phone":"+32 53 83 62 54",
    "sg:postcode":"9450",
    "sg:province":"Oost-Vlaanderen",
    "wof:name":"Hof Ten Bruul",
    "wof:placetype":"venue"
},
  "geometry": {"coordinates":[4.0019397736,50.9052505493],"type":"Point"}
}