{
  "type": "Feature",
  "properties": {
    "iso:country":"BE",
    "sg:address":"Rue De La Comtesse De Flandre 8",
    "sg:city":"Bruxelles",
    "sg:classifiers":[
        {
            "category":"Retail",
            "subcategory":"Event Space",
            "type":"Services"
        }
    ],
    "sg:phone":"+32 2 201 17 13",
    "sg:postcode":"1020",
    "sg:province":"Bruxelles-Capitale",
    "sg:tags":[
        "organisation"
    ],
    "wof:name":"Festival International Du Film Fantastique De Bruxelles De Science Fiction & Triller",
    "wof:placetype":"venue"
},
  "geometry": {"coordinates":[4.352768898,50.8739051819],"type":"Point"}
}