{
  "type": "Feature",
  "properties": {
    "addr:full":"Hogestraat 111 Torhout West-Vlaanderen 8820",
    "addr:housenumber":"111",
    "addr:postcode":"8820",
    "addr:street":"Hogestraat",
    "iso:country":"BE",
    "sg:address":"Hogestraat 111",
    "sg:city":"Torhout",
    "sg:orig_category":"Rundveehouders Varkenskwekers",
    "sg:phone":"+32 50 21 12 86",
    "sg:postcode":"8820",
    "sg:province":"West-Vlaanderen",
    "wof:name":"Joseph Decock",
    "wof:placetype":"venue"
},
  "geometry": {"coordinates":[3.0888800621,51.0778884888],"type":"Point"}
}