{
  "type": "Feature",
  "properties": {
    "addr:full":"Rue Outre L'eau 80 P\u00e9ruwelz Hainaut 7600",
    "addr:housenumber":"80",
    "addr:postcode":"7600",
    "addr:street":"Rue Outre L'Eau",
    "iso:country":"BE",
    "sg:address":"Rue Outre L'eau 80",
    "sg:city":"P\u00e9ruwelz",
    "sg:classifiers":[
        {
            "category":"Building & Trades",
            "subcategory":"Electrical",
            "type":"Services"
        }
    ],
    "sg:phone":"+32 69 77 58 01",
    "sg:postcode":"7600",
    "sg:province":"Hainaut",
    "sg:tags":[
        "electric",
        "-",
        "housewiring",
        "contractor"
    ],
    "wof:name":"Meziani E",
    "wof:placetype":"venue"
},
  "geometry": {"coordinates":[3.6108400822,50.5094108582],"type":"Point"}
}