{
  "type": "Feature",
  "properties": {
    "addr:full":"Kerhoek 5 Zomergem Oost-Vlaanderen 9930",
    "addr:housenumber":"5",
    "addr:postcode":"9930",
    "addr:street":"Kerhoek",
    "iso:country":"BE",
    "sg:address":"Kerhoek 5",
    "sg:city":"Zomergem",
    "sg:orig_category":"Rundveehouders Varkenskwekers",
    "sg:phone":"+32 9 372 80 65",
    "sg:postcode":"9930",
    "sg:province":"Oost-Vlaanderen",
    "wof:name":"Valeer De Jaeger",
    "wof:placetype":"venue"
},
  "geometry": {"coordinates":[3.5753560066,51.1210861206],"type":"Point"}
}