{
  "type": "Feature",
  "properties": {
    "addr:full":"Le Jardin 2 Rendeux (hodister) Luxembourg 6987",
    "addr:housenumber":"2",
    "addr:postcode":"6987",
    "iso:country":"BE",
    "sg:address":"Le Jardin 2",
    "sg:city":"Rendeux (hodister)",
    "sg:classifiers":[
        {
            "category":"Banks & Credit Unions",
            "subcategory":"Investment Brokerage",
            "type":"Services"
        }
    ],
    "sg:phone":"+32 84 47 72 51",
    "sg:postcode":"6987",
    "sg:province":"Luxembourg",
    "sg:tags":[
        "printing",
        "-"
    ],
    "wof:name":"Mylena Atelier",
    "wof:placetype":"venue"
},
  "geometry": {"coordinates":[5.4943871498,50.2001037598],"type":"Point"}
}