{
  "type": "Feature",
  "properties": {
    "addr:full":"Raidillon Du Thier 2 Hamoir Li\u00e8ge 4180",
    "addr:housenumber":"2",
    "addr:postcode":"4180",
    "addr:street":"Raidillon Du Thier",
    "iso:country":"BE",
    "sg:address":"Raidillon Du Thier 2",
    "sg:city":"Hamoir",
    "sg:orig_category":"Enseignement maternel and primaire",
    "sg:phone":"+32 86 38 85 50",
    "sg:postcode":"4180",
    "sg:province":"Li\u00e8ge",
    "wof:name":"Ecole Primaire Libre",
    "wof:placetype":"venue"
},
  "geometry": {"coordinates":[5.5317168236,50.4277648926],"type":"Point"}
}