{
  "type": "Feature",
  "properties": {
    "iso:country":"BE",
    "sg:address":"Paveestrasse 4",
    "sg:city":"Eupen",
    "sg:classifiers":[
        {
            "category":"Fast Food",
            "type":"Food & Drink"
        }
    ],
    "sg:phone":"+32 87 74 23 30",
    "sg:postcode":"4700",
    "sg:province":"Li\u00e8ge",
    "sg:tags":[
        "huis",
        "aan",
        "levering",
        "meeneem",
        "restaurant"
    ],
    "wof:name":"Restaurant Hongkong City",
    "wof:placetype":"venue"
},
  "geometry": {"coordinates":[6.0293650627,50.6313285828],"type":"Point"}
}