{
  "type": "Feature",
  "properties": {
    "addr:full":"Rue De L\u00b4ancien-canal 12 Ittre Brabant Wallon 1460",
    "addr:housenumber":"12;1460",
    "addr:street":"Rue De L\u00b4Ancien-Canal",
    "iso:country":"BE",
    "sg:address":"Rue De L\u00b4ancien-canal 12",
    "sg:city":"Ittre",
    "sg:orig_category":"Landmeters Landmeters and schatters",
    "sg:phone":"+32 67 64 93 15",
    "sg:postcode":"1460",
    "sg:province":"Brabant Wallon",
    "wof:name":"Arpendis",
    "wof:placetype":"venue"
},
  "geometry": {"coordinates":[4.238339901,50.6430549622],"type":"Point"}
}