{
  "type": "Feature",
  "properties": {
    "iso:country":"BE",
    "sg:address":"Kattenbos 67",
    "sg:city":"Lommel",
    "sg:orig_category":"Pain, p\u00e2tisseries and confiseries",
    "sg:phone":"+32 11 54 14 28",
    "sg:postcode":"3920",
    "sg:province":"Limburg",
    "wof:name":"Luc Geys",
    "wof:placetype":"venue"
},
  "geometry": {"coordinates":[5.3091039658,51.2072792053],"type":"Point"}
}