{
  "type": "Feature",
  "properties": {
    "iso:country":"BE",
    "sg:address":"Rue L. Fortune 48",
    "sg:city":"Wavre",
    "sg:orig_category":"Secr\u00e9tariats sociaux",
    "sg:phone":"+32 10 22 58 98",
    "sg:postcode":"1300",
    "sg:province":"Brabant Wallon",
    "wof:name":"Ucm",
    "wof:placetype":"venue"
},
  "geometry": {"coordinates":[4.6102471352,50.7180786133],"type":"Point"}
}