{
  "type": "Feature",
  "properties": {
    "addr:full":"Kerkdries 10 Zaventem Vlaams-Brabant 1933",
    "addr:housenumber":"10",
    "addr:postcode":"1933",
    "addr:street":"Kerkdries",
    "iso:country":"BE",
    "sg:address":"Kerkdries 10",
    "sg:city":"Zaventem",
    "sg:orig_category":"Herstelling and restauratie van meubelen",
    "sg:phone":"+32 2 731 19 85",
    "sg:postcode":"1933",
    "sg:province":"Vlaams-Brabant",
    "wof:name":"E. Culot",
    "wof:placetype":"venue"
},
  "geometry": {"coordinates":[4.5124387741,50.8610229492],"type":"Point"}
}