{
  "type": "Feature",
  "properties": {
    "addr:full":"Hoogstraat 4 Hofstade Oost-Vlaanderen 9308",
    "addr:housenumber":"4",
    "addr:postcode":"9308",
    "addr:street":"Hoogstraat",
    "iso:country":"BE",
    "sg:address":"Hoogstraat 4",
    "sg:city":"Hofstade",
    "sg:classifiers":[
        {
            "category":"Banks & Credit Unions",
            "subcategory":"Bank",
            "type":"Services"
        }
    ],
    "sg:phone":"+32 53 77 43 58",
    "sg:postcode":"9308",
    "sg:province":"Oost-Vlaanderen",
    "wof:name":"Aslk-cger Bank",
    "wof:placetype":"venue"
},
  "geometry": {"coordinates":[4.0333299637,50.961101532],"type":"Point"}
}