{
  "type": "Feature",
  "properties": {
    "addr:full":"Prins Boudewijnlaan 2 Antwerpen (berchem) Antwerpen 2600",
    "addr:housenumber":"2",
    "addr:postcode":"2600",
    "addr:street":"Prins Boudewijnlaan;Antwerpen",
    "iso:country":"BE",
    "sg:address":"Prins Boudewijnlaan 2",
    "sg:city":"Antwerpen (berchem)",
    "sg:classifiers":[
        {
            "category":"Autos & Motor Vehicles",
            "subcategory":"Fuel & Gas Station",
            "type":"Retail Goods"
        }
    ],
    "sg:phone":"+32 3 218 83 93",
    "sg:postcode":"2600",
    "sg:province":"Antwerpen",
    "wof:name":"V & V Car Center",
    "wof:placetype":"venue"
},
  "geometry": {"coordinates":[4.4232449532,51.1811714172],"type":"Point"}
}