{
  "type": "Feature",
  "properties": {
    "addr:full":"Manderfeld 25 B\u00dcllingen/bullange Li\u00e8ge 4760",
    "addr:housenumber":"25",
    "addr:postcode":"4760",
    "addr:street":"Manderfeld",
    "iso:country":"BE",
    "sg:address":"Manderfeld 25",
    "sg:city":"B\u00dcllingen/bullange",
    "sg:classifiers":[
        {
            "category":"Fast Food",
            "type":"Food & Drink"
        }
    ],
    "sg:phone":"+32 80 54 86 59",
    "sg:postcode":"4760",
    "sg:province":"Li\u00e8ge",
    "sg:tags":[
        "\u00c0",
        "emporter",
        "restaurants"
    ],
    "wof:name":"Calipso",
    "wof:placetype":"venue"
},
  "geometry": {"coordinates":[6.304910183,50.4083137512],"type":"Point"}
}