{
  "type": "Feature",
  "properties": {
    "addr:full":"Vronerodelaan 130 Ukkel/uccle Bruxelles-Capitale 1180",
    "addr:housenumber":"130",
    "addr:postcode":"1180",
    "addr:street":"Vronerodelaan;/",
    "iso:country":"BE",
    "sg:address":"Vronerodelaan 130",
    "sg:city":"Ukkel/uccle",
    "sg:orig_category":"Artsen and specialisten",
    "sg:phone":"+32 2 374 82 16",
    "sg:postcode":"1180",
    "sg:province":"Bruxelles-Capitale",
    "wof:name":"M. Brouwez",
    "wof:placetype":"venue"
},
  "geometry": {"coordinates":[4.3788619041,50.7819976807],"type":"Point"}
}