{
  "type": "Feature",
  "properties": {
    "addr:full":"Kruiskenstraat 62 Sint-laureins Oost-Vlaanderen 9980",
    "addr:housenumber":"62",
    "addr:postcode":"9980",
    "addr:street":"Kruiskenstraat",
    "iso:country":"BE",
    "sg:address":"Kruiskenstraat 62",
    "sg:city":"Sint-laureins",
    "sg:orig_category":"Varkenskwekers",
    "sg:phone":"+32 9 379 88 06",
    "sg:postcode":"9980",
    "sg:province":"Oost-Vlaanderen",
    "wof:name":"De Baets",
    "wof:placetype":"venue"
},
  "geometry": {"coordinates":[3.5622570515,51.2317390442],"type":"Point"}
}