{
  "type": "Feature",
  "properties": {
    "addr:full":"Tolstraat 42 Herzele Oost-Vlaanderen 9550",
    "addr:housenumber":"42",
    "addr:postcode":"9550",
    "addr:street":"Tolstraat;Oost-Vlaanderen",
    "iso:country":"BE",
    "sg:address":"Tolstraat 42",
    "sg:city":"Herzele",
    "sg:orig_category":"Brood, gebak and snoepgoed Zuivelproducten",
    "sg:phone":"+32 54 50 01 02",
    "sg:postcode":"9550",
    "sg:province":"Oost-Vlaanderen",
    "wof:name":"Herman De Campenaere",
    "wof:placetype":"venue"
},
  "geometry": {"coordinates":[3.8829030991,50.8379592896],"type":"Point"}
}