{
  "type": "Feature",
  "properties": {
    "iso:country":"BE",
    "sg:address":"Tongerlostraat 117",
    "sg:city":"Westerlo (oevel)",
    "sg:classifiers":[
        {
            "category":"Professional",
            "subcategory":"Accounting & Tax Preparation",
            "type":"Services"
        }
    ],
    "sg:phone":"+32 14 23 04 51",
    "sg:postcode":"2260",
    "sg:province":"Antwerpen",
    "sg:tags":[
        "accountant"
    ],
    "wof:name":"Driesen F",
    "wof:placetype":"venue"
},
  "geometry": {"coordinates":[4.9078350067,51.1255378723],"type":"Point"}
}