{
  "type": "Feature",
  "properties": {
    "addr:full":"Chauss\u00e9e De Louvain 485 Wavre Brabant Wallon 1300",
    "addr:housenumber":"485;1300",
    "addr:street":"Chausse\u0301E De Louvain",
    "iso:country":"BE",
    "sg:address":"Chauss\u00e9e De Louvain 485",
    "sg:city":"Wavre",
    "sg:classifiers":[
        {
            "category":"Professional",
            "subcategory":"Accounting & Tax Preparation",
            "type":"Services"
        }
    ],
    "sg:phone":"+32 10 24 67 70",
    "sg:postcode":"1300",
    "sg:province":"Brabant Wallon",
    "sg:tags":[
        "accountant"
    ],
    "wof:name":"Fretin Et Associ\u00e9s Bureau B.f.a. Sprl",
    "wof:placetype":"venue"
},
  "geometry": {"coordinates":[4.6326270103,50.7234077454],"type":"Point"}
}