{
  "type": "Feature",
  "properties": {
    "iso:country":"BE",
    "sg:address":"Sint-katelijnestraat 115",
    "sg:city":"Mechelen",
    "sg:classifiers":[
        {
            "category":"Bakery",
            "type":"Food & Drink"
        }
    ],
    "sg:phone":"+32 15 20 56 86",
    "sg:postcode":"2800",
    "sg:province":"Antwerpen",
    "sg:tags":[
        "confectioner",
        "baker"
    ],
    "wof:name":"Collaer",
    "wof:placetype":"venue"
},
  "geometry": {"coordinates":[4.4755220413,51.032535553],"type":"Point"}
}