{
  "type": "Feature",
  "properties": {
    "addr:full":"Raymond Delbekestraat 373 Zoersel Antwerpen 2980",
    "addr:housenumber":"373",
    "addr:postcode":"2980",
    "addr:street":"Delbekestraat",
    "iso:country":"BE",
    "sg:address":"Raymond Delbekestraat 373",
    "sg:city":"Zoersel",
    "sg:classifiers":[
        {
            "category":"Professional",
            "subcategory":"Management & Consulting",
            "type":"Services"
        }
    ],
    "sg:phone":"+32 3 380 17 80",
    "sg:postcode":"2980",
    "sg:province":"Antwerpen",
    "sg:tags":[
        "consultant",
        "law"
    ],
    "wof:name":"Accova",
    "wof:placetype":"venue"
},
  "geometry": {"coordinates":[4.6080799103,51.2538032532],"type":"Point"}
}