{
  "type": "Feature",
  "properties": {
    "iso:country":"BE",
    "sg:address":"Velodroomstraat 33",
    "sg:city":"Geel",
    "sg:orig_category":"Enseignement maternel and primaire",
    "sg:phone":"+32 14 58 87 58",
    "sg:postcode":"2440",
    "sg:province":"Antwerpen",
    "wof:name":"B.s.g.o. Holven",
    "wof:placetype":"venue"
},
  "geometry": {"coordinates":[4.989967823,51.1736412048],"type":"Point"}
}