{
  "type": "Feature",
  "properties": {
    "iso:country":"BE",
    "sg:address":"Rue Sainte-walburge 352",
    "sg:city":"Li\u00c8ge",
    "sg:orig_category":"Rusthuizen and serviceflats",
    "sg:phone":"+32 4 225 06 29",
    "sg:postcode":"4000",
    "sg:province":"Li\u00e8ge",
    "wof:name":"Closerie St.walburge",
    "wof:placetype":"venue"
},
  "geometry": {"coordinates":[5.5645198822,50.6614646912],"type":"Point"}
}