{
  "type": "Feature",
  "properties": {
    "iso:country":"BE",
    "sg:address":"Ronsesestraat 201",
    "sg:city":"Brakel (opbrakel)",
    "sg:classifiers":[
        {
            "category":"Retail",
            "subcategory":"Repair Shop",
            "type":"Services"
        }
    ],
    "sg:phone":"+32 55 42 38 96",
    "sg:postcode":"9660",
    "sg:province":"Oost-Vlaanderen",
    "sg:tags":[
        "jobbing",
        "tailoring",
        "-"
    ],
    "wof:name":"Delvaeye",
    "wof:placetype":"venue"
},
  "geometry": {"coordinates":[3.7288639545,50.7881126404],"type":"Point"}
}