{
  "type": "Feature",
  "properties": {
    "addr:full":"Maalse Steenweg 204 Brugge West-Vlaanderen 8310",
    "addr:housenumber":"204",
    "addr:postcode":"8310",
    "addr:street":"Maalse Steenweg",
    "iso:country":"BE",
    "sg:address":"Maalse Steenweg 204",
    "sg:city":"Brugge",
    "sg:orig_category":"Supermarkten",
    "sg:postcode":"8310",
    "sg:province":"West-Vlaanderen",
    "wof:name":"Aldi",
    "wof:placetype":"venue"
},
  "geometry": {"coordinates":[3.2525360584,51.2097892761],"type":"Point"}
}