{
  "type": "Feature",
  "properties": {
    "iso:country":"BE",
    "sg:address":"Rink 31",
    "sg:city":"Sint-pieters-leeuw",
    "sg:orig_category":"Newspapers, magazines, periodicals - Distribution",
    "sg:phone":"+32 2 377 22 37",
    "sg:postcode":"1600",
    "sg:province":"Vlaams-Brabant",
    "wof:name":"Bazaar Van 't Centrum",
    "wof:placetype":"venue"
},
  "geometry": {"coordinates":[4.2428431511,50.7788162231],"type":"Point"}
}