{
  "type": "Feature",
  "properties": {
    "iso:country":"BE",
    "sg:address":"Clos Henri G\u00c9rard 23",
    "sg:city":"Brunehaut",
    "sg:classifiers":[
        {
            "category":"Personal",
            "subcategory":"Beauty Salon",
            "type":"Services"
        }
    ],
    "sg:phone":"+32 69 34 62 68",
    "sg:postcode":"7623",
    "sg:province":"Hainaut",
    "sg:tags":[
        "de",
        "coiffure"
    ],
    "wof:name":"Jean Voet",
    "wof:placetype":"venue"
},
  "geometry": {"coordinates":[3.3965001106,50.5090484619],"type":"Point"}
}