{
  "type": "Feature",
  "properties": {
    "iso:country":"BE",
    "sg:address":"Antwerpsesteenweg 330",
    "sg:city":"Lier",
    "sg:classifiers":[
        {
            "category":"Restaurant",
            "type":"Food & Drink"
        }
    ],
    "sg:phone":"+32 3 489 13 00",
    "sg:postcode":"2500",
    "sg:province":"Antwerpen",
    "wof:name":"Zuid-west",
    "wof:placetype":"venue"
},
  "geometry": {"coordinates":[4.5449538231,51.1445350647],"type":"Point"}
}