{
  "type": "Feature",
  "properties": {
    "iso:country":"BE",
    "sg:address":"Neerwaastenstraat 19",
    "sg:city":"Ieper (hollebeke)",
    "sg:classifiers":[
        {
            "category":"Building & Trades",
            "subcategory":"Plumbing",
            "type":"Services"
        }
    ],
    "sg:phone":"+32 57 20 32 75",
    "sg:postcode":"8902",
    "sg:province":"West-Vlaanderen",
    "sg:tags":[
        "repair",
        "mainten",
        "-",
        "central",
        "heating"
    ],
    "wof:name":"Goudezeune R",
    "wof:placetype":"venue"
},
  "geometry": {"coordinates":[2.9366559982,50.7966079712],"type":"Point"}
}