{
  "type": "Feature",
  "properties": {
    "addr:full":"Oekensestraat 1 Izegem West-Vlaanderen 8870",
    "addr:housenumber":"1",
    "addr:postcode":"8870",
    "addr:street":"Oekensestraat",
    "iso:country":"BE",
    "sg:address":"Oekensestraat 1",
    "sg:city":"Izegem",
    "sg:classifiers":[
        {
            "category":"Home & Garden",
            "subcategory":"Carpets & Floor Coverings",
            "type":"Retail Goods"
        }
    ],
    "sg:phone":"+32 51 31 58 71",
    "sg:postcode":"8870",
    "sg:province":"West-Vlaanderen",
    "sg:tags":[
        "layer",
        "mosaicists"
    ],
    "wof:name":"Bruyneel N",
    "wof:placetype":"venue"
},
  "geometry": {"coordinates":[3.1888999939,50.9245681763],"type":"Point"}
}