{
  "type": "Feature",
  "properties": {
    "addr:full":"Maaldersstraat 25 Antwerpen Antwerpen 2060",
    "addr:housenumber":"25",
    "addr:postcode":"2060",
    "addr:street":"Maaldersstraat",
    "iso:country":"BE",
    "sg:address":"Maaldersstraat 25",
    "sg:city":"Antwerpen",
    "sg:classifiers":[
        {
            "category":"Real Estate",
            "subcategory":"Architect",
            "type":"Services"
        }
    ],
    "sg:phone":"+32 3 297 07 12",
    "sg:postcode":"2060",
    "sg:province":"Antwerpen",
    "wof:name":"Bellens C",
    "wof:placetype":"venue"
},
  "geometry": {"coordinates":[4.4239068031,51.2250900269],"type":"Point"}
}