{
  "type": "Feature",
  "properties": {
    "iso:country":"BE",
    "sg:address":"Petit-audenardestraat 13",
    "sg:city":"Moeskroen/mouscron",
    "sg:classifiers":[
        {
            "category":"Fast Food",
            "type":"Food & Drink"
        }
    ],
    "sg:phone":"+32 56 33 76 87",
    "sg:postcode":"7712",
    "sg:province":"Hainaut",
    "sg:tags":[
        "meeneem",
        "restaurant"
    ],
    "wof:name":"Friterie Patrice",
    "wof:placetype":"venue"
},
  "geometry": {"coordinates":[3.2535879612,50.714931488],"type":"Point"}
}