{
  "type": "Feature",
  "properties": {
    "addr:full":"Ringlaan 150 De Haan (wenduine) West-Vlaanderen 8420",
    "addr:housenumber":"150",
    "addr:postcode":"8420",
    "addr:street":"Ringlaan",
    "iso:country":"BE",
    "sg:address":"Ringlaan 150",
    "sg:city":"De Haan (wenduine)",
    "sg:classifiers":[
        {
            "category":"Arena",
            "subcategory":"Sports Club",
            "type":"Entertainment"
        }
    ],
    "sg:phone":"+32 59 23 87 55",
    "sg:postcode":"8420",
    "sg:province":"West-Vlaanderen",
    "wof:name":"T.o.m.s.vzw",
    "wof:placetype":"venue"
},
  "geometry": {"coordinates":[3.0183300972,51.2662582397],"type":"Point"}
}