{
  "type": "Feature",
  "properties": {
    "iso:country":"BE",
    "sg:address":"Bouquette 47ba",
    "sg:city":"Verviers",
    "sg:orig_category":"Diensten voor huisdieren Diverse organisaties and verenigingen",
    "sg:phone":"+32 87 22 79 49",
    "sg:postcode":"4800",
    "sg:province":"Li\u00e8ge",
    "wof:name":"Lig. Roy. Belg. Protection Oiseaux",
    "wof:placetype":"venue"
},
  "geometry": {"coordinates":[5.8594508171,50.5917663574],"type":"Point"}
}