{
  "type": "Feature",
  "properties": {
    "addr:full":"Galerie Commerciale Du C.h.u. Sart Tilman Liege Li\u00e8ge 4031",
    "addr:postcode":"4031",
    "addr:street":"Galerie",
    "iso:country":"BE",
    "sg:address":"Galerie Commerciale Du C.h.u. Sart Tilman",
    "sg:city":"Liege",
    "sg:orig_category":"Opticiens",
    "sg:phone":"+32 4 366 88 93",
    "sg:postcode":"4031",
    "sg:province":"Li\u00e8ge",
    "wof:name":"Optica",
    "wof:placetype":"venue"
},
  "geometry": {"coordinates":[5.5596117973,50.6029930115],"type":"Point"}
}