{
  "type": "Feature",
  "properties": {
    "addr:full":"Thier Goffin 7 Heron Li\u00e8ge 4217",
    "addr:housenumber":"7",
    "addr:postcode":"4217",
    "addr:street":"Thier Goffin;Heron Lie\u0300Ge",
    "iso:country":"BE",
    "sg:address":"Thier Goffin 7",
    "sg:city":"Heron",
    "sg:orig_category":"Chaussures",
    "sg:phone":"+32 85 71 37 54",
    "sg:postcode":"4217",
    "sg:province":"Li\u00e8ge",
    "wof:name":"Bernard Paulus",
    "wof:placetype":"venue"
},
  "geometry": {"coordinates":[5.1203432083,50.5508003235],"type":"Point"}
}