{
  "type": "Feature",
  "properties": {
    "addr:full":"Rue Tienne De Mont 37 Sombreffe Namur 5140",
    "addr:housenumber":"37",
    "addr:postcode":"5140",
    "addr:street":"Rue Tienne De Mont",
    "iso:country":"BE",
    "sg:address":"Rue Tienne De Mont 37",
    "sg:city":"Sombreffe",
    "sg:classifiers":[
        {
            "category":"Communications",
            "type":"Services"
        }
    ],
    "sg:phone":"+32 71 88 79 49",
    "sg:postcode":"5140",
    "sg:province":"Namur",
    "sg:tags":[
        "translator"
    ],
    "wof:name":"Halleux F",
    "wof:placetype":"venue"
},
  "geometry": {"coordinates":[4.6011247635,50.523727417],"type":"Point"}
}