{
  "type": "Feature",
  "properties": {
    "addr:full":"Avenue Des Combattants 35 Ottignies-louvain-la-neuve Brabant Wallon 1340",
    "addr:housenumber":"35",
    "addr:postcode":"1340",
    "addr:street":"Avenue Des Combattants",
    "iso:country":"BE",
    "sg:address":"Avenue Des Combattants 35",
    "sg:city":"Ottignies-louvain-la-neuve",
    "sg:orig_category":"Overheidsdiensten",
    "sg:phone":"+32 10 43 78 11",
    "sg:postcode":"1340",
    "sg:province":"Brabant Wallon",
    "wof:name":"Administration Communale",
    "wof:placetype":"venue"
},
  "geometry": {"coordinates":[4.566242218,50.6647834778],"type":"Point"}
}