{
  "type": "Feature",
  "properties": {
    "iso:country":"BE",
    "sg:address":"Rue Basse-wez 34",
    "sg:city":"Li\u00e8ge 1 (li\u00e8ge 2)",
    "sg:classifiers":[
        {
            "category":"Military Area",
            "subcategory":"Naval Base",
            "type":"Public Place"
        }
    ],
    "sg:phone":"+32 4 275 56 24",
    "sg:postcode":"4020",
    "sg:province":"Li\u00e8ge",
    "sg:tags":[
        "chair",
        "-",
        "invalid"
    ],
    "wof:name":"Devill\u00e9 Sprl",
    "wof:placetype":"venue"
},
  "geometry": {"coordinates":[5.5874409676,50.6370887756],"type":"Point"}
}