{
  "type": "Feature",
  "properties": {
    "addr:full":"Vinkenlaan 9 Schilde ('s Gravenwezel) Antwerpen 2970",
    "addr:housenumber":"9",
    "addr:postcode":"2970",
    "addr:street":"Vinkenlaan;S",
    "iso:country":"BE",
    "sg:address":"Vinkenlaan 9",
    "sg:city":"Schilde ('s Gravenwezel)",
    "sg:classifiers":[
        {
            "category":"Building & Trades",
            "subcategory":"Construction",
            "type":"Services"
        }
    ],
    "sg:phone":"+32 3 685 09 37",
    "sg:postcode":"2970",
    "sg:province":"Antwerpen",
    "sg:tags":[
        "ceiling"
    ],
    "wof:name":"G & W Nv",
    "wof:placetype":"venue"
},
  "geometry": {"coordinates":[4.5495028496,51.2574691772],"type":"Point"}
}