{
  "type": "Feature",
  "properties": {
    "iso:country":"BE",
    "sg:address":"Route Du Vieux Campinaire 40",
    "sg:city":"Fleurus",
    "sg:classifiers":[
        {
            "category":"Manufacturing",
            "subcategory":"Building Materials",
            "type":"Manufacturing & Wholesale Goods"
        }
    ],
    "sg:phone":"+32 71 81 24 17",
    "sg:postcode":"6220",
    "sg:province":"Hainaut",
    "sg:tags":[
        "boiler",
        "manufacturer"
    ],
    "wof:name":"Stiwal Bvb Sa",
    "wof:placetype":"venue"
},
  "geometry": {"coordinates":[4.5289030075,50.4550437927],"type":"Point"}
}