{
  "type": "Feature",
  "properties": {
    "addr:full":"Hoge Weg 171 Stabroek (hoevenen) Antwerpen 2940",
    "addr:housenumber":"171",
    "addr:postcode":"2940",
    "addr:street":"Hoge Weg",
    "iso:country":"BE",
    "sg:address":"Hoge Weg 171",
    "sg:city":"Stabroek (hoevenen)",
    "sg:classifiers":[
        {
            "category":"Personal",
            "subcategory":"Nail Salon",
            "type":"Services"
        }
    ],
    "sg:phone":"+32 3 605 33 19",
    "sg:postcode":"2940",
    "sg:province":"Antwerpen",
    "sg:tags":[
        "pedicure"
    ],
    "wof:name":"Carine",
    "wof:placetype":"venue"
},
  "geometry": {"coordinates":[4.3944401741,51.3153266907],"type":"Point"}
}