{
  "type": "Feature",
  "properties": {
    "iso:country":"BE",
    "sg:address":"Rue Des Sapini\u00c8res 137",
    "sg:city":"Chimay",
    "sg:classifiers":[
        {
            "category":"Sports & Exercise",
            "subcategory":"Sports Center",
            "type":"Entertainment"
        }
    ],
    "sg:phone":"+32 60 37 76 77",
    "sg:postcode":"6464",
    "sg:province":"Hainaut",
    "sg:tags":[
        "terrain",
        "hors",
        "de",
        "installation",
        "sportifs"
    ],
    "wof:name":"C.e. Sambre Et Meuse",
    "wof:placetype":"venue"
},
  "geometry": {"coordinates":[4.4016251564,49.9495544434],"type":"Point"}
}