{
  "type": "Feature",
  "properties": {
    "addr:full":"Kortrijksestraat 118 Kuurne West-Vlaanderen 8520",
    "addr:housenumber":"118",
    "addr:postcode":"8520",
    "addr:street":"Kortrijksestraat",
    "iso:country":"BE",
    "sg:address":"Kortrijksestraat 118",
    "sg:city":"Kuurne",
    "sg:orig_category":"Drogueries",
    "sg:phone":"+32 56 37 01 52",
    "sg:postcode":"8520",
    "sg:province":"West-Vlaanderen",
    "wof:name":"Hans Vandorpe",
    "wof:placetype":"venue"
},
  "geometry": {"coordinates":[3.2778470516,50.8463401794],"type":"Point"}
}