{
  "type": "Feature",
  "properties": {
    "addr:full":"Steenstraat 35 Brugge West-Vlaanderen 8000",
    "addr:housenumber":"35",
    "addr:postcode":"8000",
    "addr:street":"Steenstraat",
    "iso:country":"BE",
    "sg:address":"Steenstraat 35",
    "sg:city":"Brugge",
    "sg:orig_category":"R\u00e9parations de chaussures and articles en cuir",
    "sg:phone":"+32 50 34 67 89",
    "sg:postcode":"8000",
    "sg:province":"West-Vlaanderen",
    "wof:name":"Sneldienst Rene",
    "wof:placetype":"venue"
},
  "geometry": {"coordinates":[3.2231359482,51.2074317932],"type":"Point"}
}