{
  "type": "Feature",
  "properties": {
    "iso:country":"BE",
    "sg:address":"Kruiskalsijdestraat 19ba",
    "sg:city":"Ieper",
    "sg:orig_category":"Producteurs de l\u00e9gumes",
    "sg:phone":"+32 57 20 60 33",
    "sg:postcode":"8900",
    "sg:province":"West-Vlaanderen",
    "wof:name":"D. Masschelein",
    "wof:placetype":"venue"
},
  "geometry": {"coordinates":[2.916713953,50.8527641296],"type":"Point"}
}