{
  "type": "Feature",
  "properties": {
    "iso:country":"BE",
    "sg:address":"De Breyne Peellaertstr. 48",
    "sg:city":"Diksmuide",
    "sg:orig_category":"Glaszetten and glaswerk Plaatsen van vloer- and muurbekleding Schilders Verlichting and huishoudarti",
    "sg:phone":"+32 51 50 08 63",
    "sg:postcode":"8600",
    "sg:province":"West-Vlaanderen",
    "wof:name":"D'haenebreyne",
    "wof:placetype":"venue"
},
  "geometry": {"coordinates":[2.8658061028,51.035572052],"type":"Point"}
}