{
  "type": "Feature",
  "properties": {
    "iso:country":"BE",
    "sg:address":"Geuzenstraat 21",
    "sg:city":"Antwerpen Kern",
    "sg:orig_category":"Instruments de musique Fab. Instruments de musique",
    "sg:phone":"+32 3 237 28 24",
    "sg:postcode":"2000",
    "sg:province":"Antwerpen",
    "wof:name":"Melante",
    "wof:placetype":"venue"
},
  "geometry": {"coordinates":[4.3974809647,51.2113456726],"type":"Point"}
}