{
  "type": "Feature",
  "properties": {
    "addr:full":"Rue De L'h\u00d6tel De Ville 7 Charleroi Hainaut 6031",
    "addr:housenumber":"7",
    "addr:postcode":"6031",
    "addr:street":"Rue De L'Hoetel De Ville;Hainaut",
    "iso:country":"BE",
    "sg:address":"Rue De L'h\u00d6tel De Ville 7",
    "sg:city":"Charleroi",
    "sg:classifiers":[
        {
            "category":"Government",
            "subcategory":"Police Station",
            "type":"Public Place"
        }
    ],
    "sg:phone":"+32 71 23 73 58",
    "sg:postcode":"6031",
    "sg:province":"Hainaut",
    "sg:tags":[
        "gendarmerie"
    ],
    "wof:name":"Police F\u00c9d\u00c9rale",
    "wof:placetype":"venue"
},
  "geometry": {"coordinates":[4.4694509506,50.438785553],"type":"Point"}
}