{
  "type": "Feature",
  "properties": {
    "addr:full":"Kapucijnenvoer 86 Leuven Vlaams-Brabant 3000",
    "addr:housenumber":"86",
    "addr:postcode":"3000",
    "addr:street":"Kapucijnenvoer",
    "iso:country":"BE",
    "sg:address":"Kapucijnenvoer 86",
    "sg:city":"Leuven",
    "sg:classifiers":[
        {
            "category":"Health Services",
            "subcategory":"Health Practitioner",
            "type":"Services"
        }
    ],
    "sg:phone":"+32 16 22 18 43",
    "sg:postcode":"3000",
    "sg:province":"Vlaams-Brabant",
    "sg:tags":[
        "physiotherapist"
    ],
    "wof:name":"Van Doren Hilde",
    "wof:placetype":"venue"
},
  "geometry": {"coordinates":[4.6906528473,50.8754043579],"type":"Point"}
}