{
  "type": "Feature",
  "properties": {
    "addr:full":"Rue Du Bosquet 6 Jodoigne Brabant Wallon 1370",
    "addr:housenumber":"6",
    "addr:postcode":"1370",
    "addr:street":"Rue Du Bosquet",
    "iso:country":"BE",
    "sg:address":"Rue Du Bosquet 6",
    "sg:city":"Jodoigne",
    "sg:orig_category":"Epiceries",
    "sg:phone":"+32 10 81 60 07",
    "sg:postcode":"1370",
    "sg:province":"Brabant Wallon",
    "wof:name":"Delhaize",
    "wof:placetype":"venue"
},
  "geometry": {"coordinates":[4.8719100952,50.7242774963],"type":"Point"}
}