{
  "type": "Feature",
  "properties": {
    "iso:country":"BE",
    "sg:address":"Leuvensestraat 39 Box 41",
    "sg:city":"Vilvoorde",
    "sg:classifiers":[
        {
            "category":"Shopping",
            "subcategory":"Clothing, Apparel, & Fashions",
            "type":"Retail Goods"
        }
    ],
    "sg:phone":"+32 2 252 55 77",
    "sg:postcode":"1800",
    "sg:province":"Vlaams-Brabant",
    "sg:tags":[
        "large",
        "-",
        "clothing",
        "sale-rooms"
    ],
    "wof:name":"M & S Mode",
    "wof:placetype":"venue"
},
  "geometry": {"coordinates":[4.4266009331,50.9282684326],"type":"Point"}
}