{
  "type": "Feature",
  "properties": {
    "iso:country":"BE",
    "sg:address":"Chauss\u00e9e De Louvain 27",
    "sg:city":"Beauvechain (hamme-mille)",
    "sg:classifiers":[
        {
            "category":"Professional",
            "subcategory":"Computer Services",
            "type":"Services"
        }
    ],
    "sg:phone":"+32 10 86 75 00",
    "sg:postcode":"1320",
    "sg:province":"Brabant Wallon",
    "sg:tags":[
        "-",
        "processing",
        "data"
    ],
    "wof:name":"Synergy Informatic Sa",
    "wof:placetype":"venue"
},
  "geometry": {"coordinates":[4.7154450417,50.7814331055],"type":"Point"}
}