{
  "type": "Feature",
  "properties": {
    "iso:country":"BE",
    "sg:address":"Leopoldstraat 112",
    "sg:city":"Okegem",
    "sg:classifiers":[
        {
            "category":"Arts & Performance",
            "subcategory":"Art Gallery",
            "type":"Entertainment"
        }
    ],
    "sg:phone":"+32 54 33 17 51",
    "sg:postcode":"9400",
    "sg:province":"Oost-Vlaanderen",
    "sg:tags":[
        "baseboard",
        "wood",
        "made"
    ],
    "wof:name":"Houthandel De Roose Nv",
    "wof:placetype":"venue"
},
  "geometry": {"coordinates":[4.05017519,50.8627128601],"type":"Point"}
}