{
  "type": "Feature",
  "properties": {
    "addr:full":"Rue Du Repos 74 Bruxelles (uccle) Bruxelles-Capitale 1180",
    "addr:housenumber":"74",
    "addr:postcode":"1180",
    "addr:street":"Rue Du Repos",
    "iso:country":"BE",
    "sg:address":"Rue Du Repos 74",
    "sg:city":"Bruxelles (uccle)",
    "sg:classifiers":[
        {
            "category":"Home & Garden",
            "subcategory":"Home Furnishings",
            "type":"Retail Goods"
        }
    ],
    "sg:phone":"+32 2 375 96 63",
    "sg:postcode":"1180",
    "sg:province":"Bruxelles-Capitale",
    "sg:tags":[
        "interior",
        "decoration"
    ],
    "wof:name":"Plutzer (maison De D\u00e9coration)",
    "wof:placetype":"venue"
},
  "geometry": {"coordinates":[4.3455958366,50.7957572937],"type":"Point"}
}