{
  "type": "Feature",
  "properties": {
    "iso:country":"BE",
    "sg:address":"Rue Du Moulin 6",
    "sg:city":"Soumagne (evegn\u00e9e-tign\u00e9e)",
    "sg:classifiers":[
        {
            "category":"Shopping",
            "subcategory":"Party Supplies",
            "type":"Retail Goods"
        }
    ],
    "sg:phone":"+32 4 377 17 08",
    "sg:postcode":"4631",
    "sg:province":"Li\u00e8ge",
    "sg:tags":[
        "rental",
        "-"
    ],
    "wof:name":"Babette Location",
    "wof:placetype":"venue"
},
  "geometry": {"coordinates":[5.6989579201,50.6483078003],"type":"Point"}
}