{
  "type": "Feature",
  "properties": {
    "addr:full":"Rue De Sardanson 64 Namur (bouge) Namur 5004",
    "addr:housenumber":"64",
    "addr:postcode":"5004",
    "addr:street":"Rue De Sardanson",
    "iso:country":"BE",
    "sg:address":"Rue De Sardanson 64",
    "sg:city":"Namur (bouge)",
    "sg:classifiers":[
        {
            "category":"Retail",
            "subcategory":"Funeral Services",
            "type":"Services"
        }
    ],
    "sg:phone":"+32 81 20 19 90",
    "sg:postcode":"5004",
    "sg:province":"Namur",
    "sg:tags":[
        "director"
    ],
    "wof:name":"Funerailles Bodson Sprl",
    "wof:placetype":"venue"
},
  "geometry": {"coordinates":[4.8762598038,50.4729728699],"type":"Point"}
}