{
  "type": "Feature",
  "properties": {
    "iso:country":"BE",
    "sg:address":"Poodtstraat 3",
    "sg:city":"Ternat",
    "sg:classifiers":[
        {
            "category":"Health Services",
            "subcategory":"Doctor",
            "type":"Services"
        }
    ],
    "sg:phone":"+32 2 582 16 28",
    "sg:postcode":"1740",
    "sg:province":"Vlaams-Brabant",
    "sg:tags":[
        "medicinephysicians",
        "surgeon"
    ],
    "wof:name":"Belsack G",
    "wof:placetype":"venue"
},
  "geometry": {"coordinates":[4.1767520905,50.8712921143],"type":"Point"}
}