{
  "type": "Feature",
  "properties": {
    "iso:country":"BE",
    "sg:address":"Lindelsebaan 9",
    "sg:city":"Overpelt",
    "sg:classifiers":[
        {
            "category":"Shopping",
            "subcategory":"Florist",
            "type":"Retail Goods"
        }
    ],
    "sg:phone":"+32 11 64 12 53",
    "sg:postcode":"3900",
    "sg:province":"Limburg",
    "wof:name":"Aarts P",
    "wof:placetype":"venue"
},
  "geometry": {"coordinates":[5.4172930717,51.2086105347],"type":"Point"}
}