{
  "type": "Feature",
  "properties": {
    "addr:full":"M. Pyckstraat 18 Blankenberge West-Vlaanderen 8370",
    "addr:housenumber":"18",
    "addr:postcode":"8370",
    "addr:street":"Pyckstraat",
    "iso:country":"BE",
    "sg:address":"M. Pyckstraat 18",
    "sg:city":"Blankenberge",
    "sg:orig_category":"Elektrische installaties voor woningen Huishoudapparaten, televisies and radio's",
    "sg:phone":"+32 50 41 71 67",
    "sg:postcode":"8370",
    "sg:province":"West-Vlaanderen",
    "wof:name":"Roger Verlinde",
    "wof:placetype":"venue"
},
  "geometry": {"coordinates":[3.130961895,51.3082351685],"type":"Point"}
}