{
  "type": "Feature",
  "properties": {
    "addr:full":"Begonialaan 4 Schilde Antwerpen 2970",
    "addr:housenumber":"4",
    "addr:postcode":"2970",
    "addr:street":"Begonialaan",
    "iso:country":"BE",
    "sg:address":"Begonialaan 4",
    "sg:city":"Schilde",
    "sg:classifiers":[
        {
            "category":"Real Estate",
            "subcategory":"Developer",
            "type":"Services"
        }
    ],
    "sg:phone":"+32 3 353 10 02",
    "sg:postcode":"2970",
    "sg:province":"Antwerpen",
    "sg:tags":[
        "plomberie",
        "chauffage",
        "mat\u00e9riel",
        "gr",
        "pour"
    ],
    "wof:name":"Van Hecke R",
    "wof:placetype":"venue"
},
  "geometry": {"coordinates":[4.5551872253,51.2430915833],"type":"Point"}
}