{
  "type": "Feature",
  "properties": {
    "iso:country":"BE",
    "sg:address":"Rue Bois-du-sart B42",
    "sg:city":"Courcelles",
    "sg:orig_category":"Onderdelen and accessoires voor auto's",
    "sg:phone":"+32 71 45 97 62",
    "sg:postcode":"6180",
    "sg:province":"Hainaut",
    "wof:name":"Courcelles Pneus",
    "wof:placetype":"venue"
},
  "geometry": {"coordinates":[4.3743700981,50.4565086365],"type":"Point"}
}