{
  "type": "Feature",
  "properties": {
    "iso:country":"BE",
    "sg:address":"Molenplein 15",
    "sg:city":"Tongeren (vreren)",
    "sg:orig_category":"Non-Classified Establishments",
    "sg:phone":"+32 12 23 13 82",
    "sg:postcode":"3700",
    "sg:province":"Limburg",
    "wof:name":"Jacques A",
    "wof:placetype":"venue"
},
  "geometry": {"coordinates":[5.4573349953,50.7754974365],"type":"Point"}
}