{
  "type": "Feature",
  "properties": {
    "addr:full":"Gentsesteenweg 137 Aalst Oost-Vlaanderen 9300",
    "addr:housenumber":"137",
    "addr:postcode":"9300",
    "addr:street":"Gentsesteenweg",
    "iso:country":"BE",
    "sg:address":"Gentsesteenweg 137",
    "sg:city":"Aalst",
    "sg:classifiers":[
        {
            "category":"Fast Food",
            "type":"Food & Drink"
        }
    ],
    "sg:phone":"+32 53 78 73 10",
    "sg:postcode":"9300",
    "sg:province":"Oost-Vlaanderen",
    "sg:tags":[
        "\u00c0",
        "restaurants",
        "emporter",
        "restaurant"
    ],
    "wof:name":"Meeneemrestaurant New Garden",
    "wof:placetype":"venue"
},
  "geometry": {"coordinates":[4.0204138756,50.9391059875],"type":"Point"}
}