{
  "type": "Feature",
  "properties": {
    "iso:country":"BE",
    "sg:address":"Rue Nationale 50",
    "sg:city":"Waremme",
    "sg:orig_category":"Slagers",
    "sg:phone":"+32 19 32 27 87",
    "sg:postcode":"4300",
    "sg:province":"Li\u00e8ge",
    "wof:name":"Jean-marie Van Der Weegh",
    "wof:placetype":"venue"
},
  "geometry": {"coordinates":[5.2811098099,50.7122612],"type":"Point"}
}