{
  "type": "Feature",
  "properties": {
    "addr:full":"Hazendreef 33 Hoeilaart Vlaams-Brabant 1560",
    "addr:housenumber":"33",
    "addr:postcode":"1560",
    "addr:street":"Hazendreef",
    "iso:country":"BE",
    "sg:address":"Hazendreef 33",
    "sg:city":"Hoeilaart",
    "sg:orig_category":"Plomberie, chauffage and installations sanitaires",
    "sg:phone":"+32 2 657 04 51",
    "sg:postcode":"1560",
    "sg:province":"Vlaams-Brabant",
    "wof:name":"Biesmans Roger",
    "wof:placetype":"venue"
},
  "geometry": {"coordinates":[4.4713168144,50.7542572021],"type":"Point"}
}