{
  "type": "Feature",
  "properties": {
    "addr:full":"Kerkplein 1b1 Hechtel-eksel Limburg 3941",
    "addr:housenumber":"1b1",
    "addr:postcode":"3941",
    "addr:street":"Kerkplein",
    "iso:country":"BE",
    "sg:address":"Kerkplein 1b1",
    "sg:city":"Hechtel-eksel",
    "sg:orig_category":"Banques and organismes de cr\u00e9dit",
    "sg:phone":"+32 11 73 18 20",
    "sg:postcode":"3941",
    "sg:province":"Limburg",
    "wof:name":"Kbc",
    "wof:placetype":"venue"
},
  "geometry": {"coordinates":[5.3963460922,51.154258728],"type":"Point"}
}