{
  "type": "Feature",
  "properties": {
    "iso:country":"BE",
    "sg:address":"Norbert Neeckxlaan 10",
    "sg:city":"Lommel",
    "sg:classifiers":[
        {
            "category":"Health Services",
            "subcategory":"Health Practitioner",
            "type":"Services"
        }
    ],
    "sg:phone":"+32 11 55 36 64",
    "sg:postcode":"3920",
    "sg:province":"Limburg",
    "sg:tags":[
        "physiotherapist"
    ],
    "wof:name":"Loenders Heidi",
    "wof:placetype":"venue"
},
  "geometry": {"coordinates":[5.3176870346,51.2279205322],"type":"Point"}
}