{
  "type": "Feature",
  "properties": {
    "iso:country":"BE",
    "sg:address":"Amsterdamstr 14",
    "sg:city":"Hoogstraten",
    "sg:classifiers":[
        {
            "category":"Banks & Credit Unions",
            "subcategory":"Bank",
            "type":"Services"
        }
    ],
    "sg:phone":"+32 3 315 07 27",
    "sg:postcode":"2320",
    "sg:province":"Antwerpen",
    "wof:name":"G\u00e9n\u00e9rale De Banque Sa",
    "wof:placetype":"venue"
},
  "geometry": {"coordinates":[4.7613801956,51.4013137817],"type":"Point"}
}