{
  "type": "Feature",
  "properties": {
    "iso:country":"BE",
    "sg:address":"Puttensdreef 21",
    "sg:city":"Pittem",
    "sg:classifiers":[
        {
            "category":"Farming",
            "subcategory":"Crops",
            "type":"Manufacturing & Wholesale Goods"
        }
    ],
    "sg:phone":"+32 51 40 62 74",
    "sg:postcode":"8740",
    "sg:province":"West-Vlaanderen",
    "sg:tags":[
        "vegetable",
        "fruit",
        "-",
        "grower"
    ],
    "wof:name":"Hellebos Fruittuin",
    "wof:placetype":"venue"
},
  "geometry": {"coordinates":[3.3031210899,50.9981613159],"type":"Point"}
}