{
  "type": "Feature",
  "properties": {
    "addr:full":"Hasseltse Dreef 81 Hasselt Limburg 3512",
    "addr:housenumber":"81",
    "addr:postcode":"3512",
    "addr:street":"Dreef",
    "iso:country":"BE",
    "sg:address":"Hasseltse Dreef 81",
    "sg:city":"Hasselt",
    "sg:orig_category":"Plaatsen van vloer- and muurbekleding Schilders",
    "sg:phone":"+32 11 28 36 56",
    "sg:postcode":"3512",
    "sg:province":"Limburg",
    "wof:name":"Huis M. Deco",
    "wof:placetype":"venue"
},
  "geometry": {"coordinates":[5.2564291954,50.9185066223],"type":"Point"}
}