{
  "type": "Feature",
  "properties": {
    "iso:country":"BE",
    "sg:address":"Molenberg 1",
    "sg:city":"Brakel (michelbeke)",
    "sg:classifiers":[
        {
            "category":"Travel",
            "subcategory":"Hotels & Motels",
            "type":"Entertainment"
        }
    ],
    "sg:phone":"+32 55 42 31 93",
    "sg:postcode":"9660",
    "sg:province":"Oost-Vlaanderen",
    "wof:name":"Moriaan",
    "wof:placetype":"venue"
},
  "geometry": {"coordinates":[3.7698049545,50.8147735596],"type":"Point"}
}