{
  "type": "Feature",
  "properties": {
    "addr:full":"Rue De La Lib\u00e9ration 34 Braine-le-ch\u00e2teau Brabant Wallon 1440",
    "addr:housenumber":"34",
    "addr:postcode":"1440",
    "addr:street":"Rue De La Libe\u0301Ration",
    "iso:country":"BE",
    "sg:address":"Rue De La Lib\u00e9ration 34",
    "sg:city":"Braine-le-ch\u00e2teau",
    "sg:classifiers":[
        {
            "category":"Real Estate",
            "subcategory":"Architect",
            "type":"Services"
        }
    ],
    "sg:phone":"+32 2 366 47 96",
    "sg:postcode":"1440",
    "sg:province":"Brabant Wallon",
    "wof:name":"W & Vdd Sprl-vanden Driessche A Mme",
    "wof:placetype":"venue"
},
  "geometry": {"coordinates":[4.2706718445,50.6822013855],"type":"Point"}
}