{
  "type": "Feature",
  "properties": {
    "iso:country":"BE",
    "sg:address":"Molenstraat 29",
    "sg:city":"Herenthout",
    "sg:classifiers":[
        {
            "category":"Personal",
            "subcategory":"Beauty Salon",
            "type":"Services"
        }
    ],
    "sg:phone":"+32 14 50 61 19",
    "sg:postcode":"2270",
    "sg:province":"Antwerpen",
    "wof:name":"Schoonheidsinstituut sophie",
    "wof:placetype":"venue"
},
  "geometry": {"coordinates":[4.7585949898,51.1399345398],"type":"Point"}
}