{
  "type": "Feature",
  "properties": {
    "addr:full":"Rue De La R\u00c9forme 4 Elsene/ixelles Bruxelles-Capitale 1050",
    "addr:housenumber":"4",
    "addr:postcode":"1050",
    "addr:street":"Rue De La Re\u0301Forme",
    "iso:country":"BE",
    "sg:address":"Rue De La R\u00c9forme 4",
    "sg:city":"Elsene/ixelles",
    "sg:orig_category":"Agences de relations publiques",
    "sg:phone":"+32 2 346 60 59",
    "sg:postcode":"1050",
    "sg:province":"Bruxelles-Capitale",
    "wof:name":"Bureau Gracious",
    "wof:placetype":"venue"
},
  "geometry": {"coordinates":[4.3548488617,50.8207817078],"type":"Point"}
}