{
  "type": "Feature",
  "properties": {
    "iso:country":"BE",
    "sg:address":"Rue Rouge-flamme 15",
    "sg:city":"Wanze (antheit)",
    "sg:orig_category":"Non-Classified Establishments",
    "sg:phone":"+32 85 25 11 66",
    "sg:postcode":"4520",
    "sg:province":"Li\u00e8ge",
    "wof:name":"Chapiteau Wegria Sprl",
    "wof:placetype":"venue"
},
  "geometry": {"coordinates":[5.2284917831,50.5414924622],"type":"Point"}
}