{
  "type": "Feature",
  "properties": {
    "iso:country":"BE",
    "sg:address":"Kortrijksesteenweg 52",
    "sg:city":"Deinze",
    "sg:orig_category":"Kapsalons",
    "sg:phone":"+32 9 386 03 54",
    "sg:postcode":"9800",
    "sg:province":"Oost-Vlaanderen",
    "wof:name":"Coiffure Pierre",
    "wof:placetype":"venue"
},
  "geometry": {"coordinates":[3.5262880325,50.9762687683],"type":"Point"}
}