{
  "type": "Feature",
  "properties": {
    "addr:full":"Rue De La Cath\u00e9drale 27a Li\u00e8ge 1 Li\u00e8ge 4000",
    "addr:housenumber":"27a;1",
    "addr:postcode":"4000",
    "addr:street":"Rue De La Cathe\u0301Drale",
    "iso:country":"BE",
    "sg:address":"Rue De La Cath\u00e9drale 27a",
    "sg:city":"Li\u00e8ge 1",
    "sg:classifiers":[
        {
            "category":"Personal",
            "subcategory":"Beauty Salon",
            "type":"Services"
        }
    ],
    "sg:phone":"+32 4 223 71 91",
    "sg:postcode":"4000",
    "sg:province":"Li\u00e8ge",
    "sg:tags":[
        "lady",
        "-",
        "hairdressing"
    ],
    "wof:name":"Studio Coiff Sprl",
    "wof:placetype":"venue"
},
  "geometry": {"coordinates":[5.5760188103,50.6429176331],"type":"Point"}
}