{
  "type": "Feature",
  "properties": {
    "addr:full":"Zoutwerf 28-1 Mechelen Antwerpen 2800",
    "addr:housenumber":"28-1",
    "addr:postcode":"2800",
    "addr:street":"Zoutwerf",
    "iso:country":"BE",
    "sg:address":"Zoutwerf 28-1",
    "sg:city":"Mechelen",
    "sg:classifiers":[
        {
            "category":"Professional",
            "subcategory":"Computer Services",
            "type":"Services"
        }
    ],
    "sg:phone":"+32 15 33 60 91",
    "sg:postcode":"2800",
    "sg:province":"Antwerpen",
    "sg:tags":[
        "-",
        "processing",
        "data",
        "software"
    ],
    "wof:name":"Sola-r Software Bvba",
    "wof:placetype":"venue"
},
  "geometry": {"coordinates":[4.4788599014,51.0251312256],"type":"Point"}
}