{
  "type": "Feature",
  "properties": {
    "addr:full":"Hoksentstraat 19 Hechtel-eksel (eksel) Limburg 3941",
    "addr:housenumber":"19",
    "addr:postcode":"3941",
    "addr:street":"Hoksentstraat",
    "iso:country":"BE",
    "sg:address":"Hoksentstraat 19",
    "sg:city":"Hechtel-eksel (eksel)",
    "sg:classifiers":[
        {
            "category":"Building & Trades",
            "subcategory":"Construction",
            "type":"Services"
        }
    ],
    "sg:phone":"+32 11 63 28 16",
    "sg:postcode":"3941",
    "sg:province":"Limburg",
    "sg:tags":[
        "stair"
    ],
    "wof:name":"Palmans L",
    "wof:placetype":"venue"
},
  "geometry": {"coordinates":[5.4169511795,51.1545333862],"type":"Point"}
}