{
  "type": "Feature",
  "properties": {
    "iso:country":"BE",
    "sg:address":"Rue De La Br\u00dbl\u00c9e 6",
    "sg:city":"Thuin",
    "sg:orig_category":"Paramedische behandelingen",
    "sg:phone":"+32 71 59 12 17",
    "sg:postcode":"6533",
    "sg:province":"Hainaut",
    "wof:name":"L. Bastin",
    "wof:placetype":"venue"
},
  "geometry": {"coordinates":[4.260723114,50.3217391968],"type":"Point"}
}