{
  "type": "Feature",
  "properties": {
    "addr:full":"Rue Provinciale 173 Celles Hainaut 7760",
    "addr:housenumber":"173",
    "addr:postcode":"7760",
    "addr:street":"Rue Provinciale",
    "iso:country":"BE",
    "sg:address":"Rue Provinciale 173",
    "sg:city":"Celles",
    "sg:orig_category":"Electrom\u00e9nager, t\u00e9l\u00e9visions and radios",
    "sg:phone":"+32 69 45 51 86",
    "sg:postcode":"7760",
    "sg:province":"Hainaut",
    "wof:name":"J.l. Riquier",
    "wof:placetype":"venue"
},
  "geometry": {"coordinates":[3.455329895,50.7194595337],"type":"Point"}
}