{
  "type": "Feature",
  "properties": {
    "addr:full":"Sint-gillisbaan 158 Sint-niklaas Oost-Vlaanderen 9100",
    "addr:housenumber":"158",
    "addr:postcode":"9100",
    "addr:street":"Sint-Niklaas Oost-Vlaanderen",
    "iso:country":"BE",
    "sg:address":"Sint-gillisbaan 158",
    "sg:city":"Sint-niklaas",
    "sg:orig_category":"Artsen and specialisten",
    "sg:phone":"+32 3 776 15 29",
    "sg:postcode":"9100",
    "sg:province":"Oost-Vlaanderen",
    "wof:name":"Lieven De Weirdt",
    "wof:placetype":"venue"
},
  "geometry": {"coordinates":[4.1425747871,51.1847000122],"type":"Point"}
}