{
  "type": "Feature",
  "properties": {
    "addr:full":"Rue De La Pirire 38 Marche-en-famenne Luxembourg 6900",
    "addr:housenumber":"38",
    "addr:postcode":"6900",
    "addr:street":"Rue De La Pirire",
    "iso:country":"BE",
    "sg:address":"Rue De La Pirire 38",
    "sg:city":"Marche-en-famenne",
    "sg:orig_category":"Farmaceutische bereidingen and geneesmiddelen Fab",
    "sg:phone":"+32 84 32 04 50",
    "sg:postcode":"6900",
    "sg:province":"Luxembourg",
    "wof:name":"S.m.b. Technology",
    "wof:placetype":"venue"
},
  "geometry": {"coordinates":[5.3327422142,50.2242507935],"type":"Point"}
}