{
  "type": "Feature",
  "properties": {
    "addr:full":"Rue Sainte-walburge 10 Li\u00c8ge Li\u00e8ge 4000",
    "addr:housenumber":"10",
    "addr:postcode":"4000",
    "addr:street":"Rue Sainte-Walburge",
    "iso:country":"BE",
    "sg:address":"Rue Sainte-walburge 10",
    "sg:city":"Li\u00c8ge",
    "sg:classifiers":[
        {
            "category":"Fast Food",
            "type":"Food & Drink"
        }
    ],
    "sg:phone":"+32 4 224 22 70",
    "sg:postcode":"4000",
    "sg:province":"Li\u00e8ge",
    "sg:tags":[
        "\u00c0",
        "emporter",
        "restaurants"
    ],
    "wof:name":"F. Toschi",
    "wof:placetype":"venue"
},
  "geometry": {"coordinates":[5.5727200508,50.655128479],"type":"Point"}
}