{
  "type": "Feature",
  "properties": {
    "addr:full":"De Wittestraat 49 Antwerpen (berchem) Antwerpen 2600",
    "addr:housenumber":"49",
    "addr:postcode":"2600",
    "addr:street":"De Wittestraat;Antwerpen",
    "iso:country":"BE",
    "sg:address":"De Wittestraat 49",
    "sg:city":"Antwerpen (berchem)",
    "sg:classifiers":[
        {
            "category":"Real Estate",
            "subcategory":"Architect",
            "type":"Services"
        }
    ],
    "sg:phone":"+32 3 239 06 33",
    "sg:postcode":"2600",
    "sg:province":"Antwerpen",
    "wof:name":"Maes B",
    "wof:placetype":"venue"
},
  "geometry": {"coordinates":[4.3859138489,51.1888694763],"type":"Point"}
}