{
  "type": "Feature",
  "properties": {
    "addr:full":"Avenue Marcel Thiry 200 Sint-lambrechts-woluwe/woluwe-saint-lambert Bruxelles-Capitale 1200",
    "addr:housenumber":"200",
    "addr:postcode":"1200",
    "addr:street":"Avenue Marcel Thiry",
    "iso:country":"BE",
    "sg:address":"Avenue Marcel Thiry 200",
    "sg:city":"Sint-lambrechts-woluwe/woluwe-saint-lambert",
    "sg:orig_category":"Traitement de donn\u00e9es",
    "sg:phone":"+32 2 774 92 22",
    "sg:postcode":"1200",
    "sg:province":"Bruxelles-Capitale",
    "wof:name":"E. & Y. Consulting",
    "wof:placetype":"venue"
},
  "geometry": {"coordinates":[4.4351449013,50.8567581177],"type":"Point"}
}