{
  "type": "Feature",
  "properties": {
    "addr:full":"Tiensestraat 26 Leuven Vlaams-Brabant 3000",
    "addr:housenumber":"26",
    "addr:postcode":"3000",
    "addr:street":"Tiensestraat",
    "iso:country":"BE",
    "sg:address":"Tiensestraat 26",
    "sg:city":"Leuven",
    "sg:classifiers":[
        {
            "category":"Bars & Pubs",
            "type":"Food & Drink"
        }
    ],
    "sg:phone":"+32 16 23 89 32",
    "sg:postcode":"3000",
    "sg:province":"Vlaams-Brabant",
    "wof:name":"Artishock",
    "wof:placetype":"venue"
},
  "geometry": {"coordinates":[4.7032790184,50.8781890869],"type":"Point"}
}