{
  "type": "Feature",
  "properties": {
    "iso:country":"BE",
    "sg:address":"Avenue Albert Giraud 93",
    "sg:city":"Bruxelles (schaerbeek)",
    "sg:classifiers":[
        {
            "category":"Retail",
            "subcategory":"Event Space",
            "type":"Services"
        }
    ],
    "sg:phone":"+32 2 216 04 52",
    "sg:postcode":"1030",
    "sg:province":"Bruxelles-Capitale",
    "sg:tags":[
        "rental",
        "-",
        "hall"
    ],
    "wof:name":"Respel Sa",
    "wof:placetype":"venue"
},
  "geometry": {"coordinates":[4.3813648224,50.8751564026],"type":"Point"}
}