{
  "type": "Feature",
  "properties": {
    "iso:country":"BE",
    "sg:address":"Quellinstraat 46",
    "sg:city":"Antwerpen",
    "sg:orig_category":"V\u00eatements pour b\u00e9b\u00e9s and enfants. V\u00eatements. V\u00eatements de mariage and c\u00e9r\u00e9monies",
    "sg:phone":"+32 3 232 17 43",
    "sg:postcode":"2018",
    "sg:province":"Antwerpen",
    "wof:name":"Huis Unif",
    "wof:placetype":"venue"
},
  "geometry": {"coordinates":[4.4157252312,51.2156600952],"type":"Point"}
}