{
  "type": "Feature",
  "properties": {
    "addr:full":"Pereboomstraat 4 Kortemark West-Vlaanderen 8610",
    "addr:housenumber":"4",
    "addr:postcode":"8610",
    "addr:street":"Pereboomstraat",
    "iso:country":"BE",
    "sg:address":"Pereboomstraat 4",
    "sg:city":"Kortemark",
    "sg:orig_category":"Eleveurs and marchands de porcs",
    "sg:phone":"+32 51 56 64 05",
    "sg:postcode":"8610",
    "sg:province":"West-Vlaanderen",
    "wof:name":"Marc Jonckheere",
    "wof:placetype":"venue"
},
  "geometry": {"coordinates":[3.0226240158,51.0395393372],"type":"Point"}
}