{
  "type": "Feature",
  "properties": {
    "addr:full":"Pottelberg 17 Kortrijk West-Vlaanderen 8500",
    "addr:housenumber":"17",
    "addr:postcode":"8500",
    "addr:street":"Pottelberg",
    "iso:country":"BE",
    "sg:address":"Pottelberg 17",
    "sg:city":"Kortrijk",
    "sg:orig_category":"Installation \u00e9lectrique r\u00e9sidentielle",
    "sg:phone":"+32 56 22 66 63",
    "sg:postcode":"8500",
    "sg:province":"West-Vlaanderen",
    "wof:name":"Elektro D.v.o.",
    "wof:placetype":"venue"
},
  "geometry": {"coordinates":[3.253715992,50.8152923584],"type":"Point"}
}