{
  "type": "Feature",
  "properties": {
    "iso:country":"BE",
    "sg:address":"Rue Paul Henri Spaak 5bb",
    "sg:city":"Peruwelz",
    "sg:orig_category":"Artsen and specialisten",
    "sg:phone":"+32 69 77 40 09",
    "sg:postcode":"7608",
    "sg:province":"Hainaut",
    "wof:name":"Carine Dervaux",
    "wof:placetype":"venue"
},
  "geometry": {"coordinates":[3.5358130932,50.5055732727],"type":"Point"}
}