{
  "type": "Feature",
  "properties": {
    "iso:country":"BE",
    "sg:address":"Brugsesteenweg 536",
    "sg:city":"Kuurne",
    "sg:orig_category":"Jardinage",
    "sg:phone":"+32 56 72 46 56",
    "sg:postcode":"8520",
    "sg:province":"West-Vlaanderen",
    "wof:name":"Meulemans K",
    "wof:placetype":"venue"
},
  "geometry": {"coordinates":[3.2720739841,50.8770332336],"type":"Point"}
}