{
  "type": "Feature",
  "properties": {
    "addr:full":"Avenue Henri Strauven 14 Bruxelles (auderghem) Bruxelles-Capitale 1160",
    "addr:housenumber":"14",
    "addr:postcode":"1160",
    "addr:street":"Avenue Henri Strauven",
    "iso:country":"BE",
    "sg:address":"Avenue Henri Strauven 14",
    "sg:city":"Bruxelles (auderghem)",
    "sg:classifiers":[
        {
            "category":"Real Estate",
            "subcategory":"Architect",
            "type":"Services"
        }
    ],
    "sg:phone":"+32 2 426 17 00",
    "sg:postcode":"1160",
    "sg:province":"Bruxelles-Capitale",
    "wof:name":"Florin C",
    "wof:placetype":"venue"
},
  "geometry": {"coordinates":[4.4163398743,50.8179855347],"type":"Point"}
}