{
  "type": "Feature",
  "properties": {
    "addr:full":"Avenue De L'or\u00c9e 8 Brussel/bruxelles Bruxelles-Capitale 1000",
    "addr:housenumber":"8",
    "addr:postcode":"1000",
    "addr:street":"Avenue De L'Ore \u0301E;/",
    "iso:country":"BE",
    "sg:address":"Avenue De L'or\u00c9e 8",
    "sg:city":"Brussel/bruxelles",
    "sg:orig_category":"M\u00e9decins and sp\u00e9cialistes",
    "sg:phone":"+32 2 648 95 09",
    "sg:postcode":"1000",
    "sg:province":"Bruxelles-Capitale",
    "wof:name":"Claude Cahen",
    "wof:placetype":"venue"
},
  "geometry": {"coordinates":[4.3837771416,50.8094596863],"type":"Point"}
}