{
  "type": "Feature",
  "properties": {
    "addr:full":"Abeleplein 19 Poperinge West-Vlaanderen 8978",
    "addr:housenumber":"19",
    "addr:postcode":"8978",
    "addr:street":"Abeleplein",
    "iso:country":"BE",
    "sg:address":"Abeleplein 19",
    "sg:city":"Poperinge",
    "sg:orig_category":"Pain, p\u00e2tisseries and confiseries",
    "sg:phone":"+32 57 33 44 76",
    "sg:postcode":"8978",
    "sg:province":"West-Vlaanderen",
    "wof:name":"La Maison Des Dragees",
    "wof:placetype":"venue"
},
  "geometry": {"coordinates":[2.6206049919,50.8592453003],"type":"Point"}
}