{
  "type": "Feature",
  "properties": {
    "addr:full":"Stoofstraat 26 Brussel/bruxelles Bruxelles-Capitale 1000",
    "addr:housenumber":"26",
    "addr:postcode":"1000",
    "addr:street":"Stoofstraat;/",
    "iso:country":"BE",
    "sg:address":"Stoofstraat 26",
    "sg:city":"Brussel/bruxelles",
    "sg:orig_category":"Verlichting and huishoudartikelen",
    "sg:phone":"+32 2 513 11 31",
    "sg:postcode":"1000",
    "sg:province":"Bruxelles-Capitale",
    "wof:name":"B-palace",
    "wof:placetype":"venue"
},
  "geometry": {"coordinates":[4.350684166,50.8453216553],"type":"Point"}
}