{
  "type": "Feature",
  "properties": {
    "addr:full":"De Renlaan 19 Brecht Antwerpen 2960",
    "addr:housenumber":"19",
    "addr:postcode":"2960",
    "addr:street":"Renlaan",
    "iso:country":"BE",
    "sg:address":"De Renlaan 19",
    "sg:city":"Brecht",
    "sg:classifiers":[
        {
            "category":"Professional",
            "subcategory":"Art Services",
            "type":"Services"
        }
    ],
    "sg:phone":"+32 3 636 05 06",
    "sg:postcode":"2960",
    "sg:province":"Antwerpen",
    "sg:tags":[
        "graphic",
        "designer"
    ],
    "wof:name":"Mangelschots J",
    "wof:placetype":"venue"
},
  "geometry": {"coordinates":[4.5734248161,51.300403595],"type":"Point"}
}