{
  "type": "Feature",
  "properties": {
    "iso:country":"BE",
    "sg:address":"Gravin Elisabethlaan 30",
    "sg:city":"Hoogstraten",
    "sg:classifiers":[
        {
            "category":"Education",
            "subcategory":"School",
            "type":"Public Place"
        }
    ],
    "sg:phone":"+32 3 340 40 30",
    "sg:postcode":"2320",
    "sg:province":"Antwerpen",
    "sg:tags":[
        "secondary"
    ],
    "wof:name":"Vrij Instituut Voor Technisch Onderwijs",
    "wof:placetype":"venue"
},
  "geometry": {"coordinates":[4.7532439232,51.4024353027],"type":"Point"}
}