{
  "type": "Feature",
  "properties": {
    "iso:country":"BE",
    "sg:address":"Wakkerzeelsebaan 139",
    "sg:city":"Leuven",
    "sg:orig_category":"Beheer van reclamemedia",
    "sg:phone":"+32 16 44 39 79",
    "sg:postcode":"3018",
    "sg:province":"Vlaams-Brabant",
    "wof:name":"Mobifree",
    "wof:placetype":"venue"
},
  "geometry": {"coordinates":[4.6896691322,50.9315719604],"type":"Point"}
}