{
  "type": "Feature",
  "properties": {
    "iso:country":"BE",
    "sg:address":"Gistelstraat 90",
    "sg:city":"Ingelmunster",
    "sg:orig_category":"Animaux domestiques and accessoires",
    "sg:phone":"+32 51 31 61 57",
    "sg:postcode":"8770",
    "sg:province":"West-Vlaanderen",
    "wof:name":"Sidarta",
    "wof:placetype":"venue"
},
  "geometry": {"coordinates":[3.2381210327,50.9290351868],"type":"Point"}
}