{
  "type": "Feature",
  "properties": {
    "addr:full":"Route De Ch\u00c2telet 50 Charleroi Hainaut 6010",
    "addr:housenumber":"50",
    "addr:postcode":"6010",
    "addr:street":"Route De Cha\u0302Telet;Hainaut",
    "iso:country":"BE",
    "sg:address":"Route De Ch\u00c2telet 50",
    "sg:city":"Charleroi",
    "sg:classifiers":[
        {
            "category":"Cafe",
            "type":"Food & Drink"
        }
    ],
    "sg:phone":"+32 71 43 42 71",
    "sg:postcode":"6010",
    "sg:province":"Hainaut",
    "sg:tags":[
        "caf\u00e9s"
    ],
    "wof:name":"Jenny Vanbrabande",
    "wof:placetype":"venue"
},
  "geometry": {"coordinates":[4.457007885,50.3913764954],"type":"Point"}
}