{
  "type": "Feature",
  "properties": {
    "iso:country":"BE",
    "sg:address":"Avenue Des D\u00c9mineurs 2ba",
    "sg:city":"Stavelot",
    "sg:orig_category":"HERSTELLING ELEKTRISCHE HUISHOUDAPPARATEN Huishoudapparaten, televisies and radio's",
    "sg:phone":"+32 80 86 24 98",
    "sg:postcode":"4970",
    "sg:province":"Li\u00e8ge",
    "wof:name":"Alphonse Comte",
    "wof:placetype":"venue"
},
  "geometry": {"coordinates":[5.9335560799,50.3962783813],"type":"Point"}
}