{
  "type": "Feature",
  "properties": {
    "iso:country":"BE",
    "sg:address":"Hervormingslaan 76b27",
    "sg:city":"Ganshoren",
    "sg:orig_category":"Beheer onroerend goed",
    "sg:phone":"+32 2 425 76 81",
    "sg:postcode":"1083",
    "sg:province":"Bruxelles-Capitale",
    "wof:name":"Jean-marie Spiritus",
    "wof:placetype":"venue"
},
  "geometry": {"coordinates":[4.3104729652,50.8748893738],"type":"Point"}
}