{
  "type": "Feature",
  "properties": {
    "addr:full":"Rue De Mianoye 19 Yvoir (durnal) Namur 5530",
    "addr:housenumber":"19",
    "addr:postcode":"5530",
    "addr:street":"Rue De Mianoye",
    "iso:country":"BE",
    "sg:address":"Rue De Mianoye 19",
    "sg:city":"Yvoir (durnal)",
    "sg:classifiers":[
        {
            "category":"Bars & Pubs",
            "type":"Food & Drink"
        }
    ],
    "sg:phone":"+32 83 69 05 84",
    "sg:postcode":"5530",
    "sg:province":"Namur",
    "wof:name":"Caf\u00e9 Des Pahauts",
    "wof:placetype":"venue"
},
  "geometry": {"coordinates":[4.9828739166,50.3382987976],"type":"Point"}
}