{
  "type": "Feature",
  "properties": {
    "iso:country":"BE",
    "sg:address":"Quai Des Saulx",
    "sg:city":"Bouillon",
    "sg:classifiers":[
        {
            "category":"Banks & Credit Unions",
            "subcategory":"Investment Brokerage",
            "type":"Services"
        }
    ],
    "sg:phone":"+32 61 46 91 24",
    "sg:postcode":"6830",
    "sg:province":"Luxembourg",
    "sg:tags":[
        "rental",
        "-",
        "yacht",
        "boat",
        "pleasure"
    ],
    "wof:name":"Boegen C",
    "wof:placetype":"venue"
},
  "geometry": {"coordinates":[5.0696229935,49.7941818237],"type":"Point"}
}