{
  "type": "Feature",
  "properties": {
    "iso:country":"BE",
    "sg:address":"Schrijberg 201",
    "sg:city":"Sint-niklaas",
    "sg:orig_category":"Reclamebureaus",
    "sg:phone":"+32 3 772 39 01",
    "sg:postcode":"9111",
    "sg:province":"Oost-Vlaanderen",
    "wof:name":"Dirk Verhoeven",
    "wof:placetype":"venue"
},
  "geometry": {"coordinates":[4.0732278824,51.1366233826],"type":"Point"}
}