{
  "type": "Feature",
  "properties": {
    "addr:full":"Rue Neuve Du Pont 19 Renaix Oost-Vlaanderen 9600",
    "addr:housenumber":"19",
    "addr:postcode":"9600",
    "addr:street":"Rue Neuve Du Pont",
    "iso:country":"BE",
    "sg:address":"Rue Neuve Du Pont 19",
    "sg:city":"Renaix",
    "sg:classifiers":[
        {
            "category":"Education",
            "subcategory":"Vocational School",
            "type":"Public Place"
        }
    ],
    "sg:phone":"+32 55 20 84 25",
    "sg:postcode":"9600",
    "sg:province":"Oost-Vlaanderen",
    "sg:tags":[
        "teaching",
        "material"
    ],
    "wof:name":"Projection & Presentation Bvba",
    "wof:placetype":"venue"
},
  "geometry": {"coordinates":[3.5813589096,50.7349472046],"type":"Point"}
}