{
  "type": "Feature",
  "properties": {
    "iso:country":"BE",
    "sg:address":"Rue De Genval 1",
    "sg:city":"La Hulpe",
    "sg:classifiers":[
        {
            "category":"Retail",
            "subcategory":"Laundry & Dry Cleaning",
            "type":"Services"
        }
    ],
    "sg:phone":"+32 2 653 31 21",
    "sg:postcode":"1310",
    "sg:province":"Brabant Wallon",
    "wof:name":"Euro Wash",
    "wof:placetype":"venue"
},
  "geometry": {"coordinates":[4.485809803,50.7308311462],"type":"Point"}
}