{
  "type": "Feature",
  "properties": {
    "iso:country":"BE",
    "sg:address":"Rue Du Pr\u00e9 Sabot 11",
    "sg:city":"Ecaussinnes (marche-lez-ecaussines)",
    "sg:classifiers":[
        {
            "category":"Building & Trades",
            "subcategory":"Landscaping Services",
            "type":"Services"
        }
    ],
    "sg:phone":"+32 67 48 55 55",
    "sg:postcode":"7190",
    "sg:province":"Hainaut",
    "sg:tags":[
        "gardening",
        "garden",
        "maintenance"
    ],
    "wof:name":"Un Jour, Un Arbre",
    "wof:placetype":"venue"
},
  "geometry": {"coordinates":[4.1788649559,50.5526123047],"type":"Point"}
}