{
  "type": "Feature",
  "properties": {
    "iso:country":"BE",
    "sg:address":"Hasseltweg 46",
    "sg:city":"Genk",
    "sg:classifiers":[
        {
            "category":"Building & Trades",
            "subcategory":"Construction",
            "type":"Services"
        }
    ],
    "sg:phone":"+32 89 35 68 07",
    "sg:postcode":"3600",
    "sg:province":"Limburg",
    "sg:tags":[
        "carpenter"
    ],
    "wof:name":"Bormans H",
    "wof:placetype":"venue"
},
  "geometry": {"coordinates":[5.4721698761,50.9641838074],"type":"Point"}
}