{
  "type": "Feature",
  "properties": {
    "addr:full":"Chemin Jean Lariguette 5 Ottignies-louvain-la-neuve (louvain-la-neuve) Brabant Wallon 1348",
    "addr:housenumber":"5",
    "addr:postcode":"1348",
    "addr:street":"Chemin Jean Lariguette",
    "iso:country":"BE",
    "sg:address":"Chemin Jean Lariguette 5",
    "sg:city":"Ottignies-louvain-la-neuve (louvain-la-neuve)",
    "sg:classifiers":[
        {
            "category":"Real Estate",
            "subcategory":"Architect",
            "type":"Services"
        }
    ],
    "sg:phone":"+32 10 45 06 31",
    "sg:postcode":"1348",
    "sg:province":"Brabant Wallon",
    "wof:name":"Van Noorbeeck B",
    "wof:placetype":"venue"
},
  "geometry": {"coordinates":[4.6125249863,50.6738090515],"type":"Point"}
}