{
  "type": "Feature",
  "properties": {
    "addr:full":"Hasseltsesteenweg 639 Tongeren Limburg 3700",
    "addr:housenumber":"639",
    "addr:postcode":"3700",
    "addr:street":"Hasseltsesteenweg",
    "iso:country":"BE",
    "sg:address":"Hasseltsesteenweg 639",
    "sg:city":"Tongeren",
    "sg:orig_category":"Fleurs and plantes",
    "sg:phone":"+32 12 23 25 79",
    "sg:postcode":"3700",
    "sg:province":"Limburg",
    "wof:name":"Huis 't Meiklokje",
    "wof:placetype":"venue"
},
  "geometry": {"coordinates":[5.459335804,50.7829055786],"type":"Point"}
}