{
  "type": "Feature",
  "properties": {
    "iso:country":"BE",
    "sg:address":"Sint-bavoplein 5",
    "sg:city":"Boechout",
    "sg:orig_category":"Agences d'exp\u00e9dition",
    "sg:phone":"+32 3 454 19 16",
    "sg:postcode":"2530",
    "sg:province":"Antwerpen",
    "wof:name":"B. Export",
    "wof:placetype":"venue"
},
  "geometry": {"coordinates":[4.4918041229,51.1595993042],"type":"Point"}
}