{
  "type": "Feature",
  "properties": {
    "iso:country":"BE",
    "sg:address":"Doylijkstraat 15",
    "sg:city":"Dilbeek (itterbeek)",
    "sg:classifiers":[
        {
            "category":"Education",
            "subcategory":"School",
            "type":"Public Place"
        }
    ],
    "sg:phone":"+32 2 569 38 35",
    "sg:postcode":"1701",
    "sg:province":"Vlaams-Brabant",
    "sg:tags":[
        "-",
        "private"
    ],
    "wof:name":"Coene L",
    "wof:placetype":"venue"
},
  "geometry": {"coordinates":[4.2192177773,50.826259613],"type":"Point"}
}