{
  "type": "Feature",
  "properties": {
    "iso:country":"BE",
    "sg:address":"Rue De Praetere 12",
    "sg:city":"Elsene/ixelles",
    "sg:orig_category":"Avocats and conseillers juridiques",
    "sg:phone":"+32 2 644 00 64",
    "sg:postcode":"1050",
    "sg:province":"Bruxelles-Capitale",
    "wof:name":"A. Portelange",
    "wof:placetype":"venue"
},
  "geometry": {"coordinates":[4.3701491356,50.8170127869],"type":"Point"}
}