{
  "type": "Feature",
  "properties": {
    "addr:full":"Veldwijkstraat 2 Gent Oost-Vlaanderen 9050",
    "addr:housenumber":"2",
    "addr:postcode":"9050",
    "addr:street":"Veldwijkstraat;Oost-Vlaanderen",
    "iso:country":"BE",
    "sg:address":"Veldwijkstraat 2",
    "sg:city":"Gent",
    "sg:orig_category":"Slagers",
    "sg:phone":"+32 9 231 23 53",
    "sg:postcode":"9050",
    "sg:province":"Oost-Vlaanderen",
    "wof:name":"Lawa",
    "wof:placetype":"venue"
},
  "geometry": {"coordinates":[3.7450859547,51.0343093872],"type":"Point"}
}