{
  "type": "Feature",
  "properties": {
    "iso:country":"BE",
    "sg:address":"Thiers Depas 9",
    "sg:city":"Braives",
    "sg:orig_category":"D\u00e9molition d\u00b4immeubles and terrassements. Transports routiers de marchandises. Construction de rev\u00eat",
    "sg:phone":"+32 19 69 95 13",
    "sg:postcode":"4260",
    "sg:province":"Li\u00e8ge",
    "wof:name":"Robert Gaby Entreprises",
    "wof:placetype":"venue"
},
  "geometry": {"coordinates":[5.1478729248,50.6277618408],"type":"Point"}
}