{
  "type": "Feature",
  "properties": {
    "addr:full":"Bosstraat 38 Lier Antwerpen 2500",
    "addr:housenumber":"38",
    "addr:postcode":"2500",
    "addr:street":"Bosstraat",
    "iso:country":"BE",
    "sg:address":"Bosstraat 38",
    "sg:city":"Lier",
    "sg:orig_category":"Activit\u00e9s r\u00e9cr\u00e9atives diverses",
    "sg:phone":"+32 3 480 66 28",
    "sg:postcode":"2500",
    "sg:province":"Antwerpen",
    "wof:name":"Fed.postzegelverzamelaars",
    "wof:placetype":"venue"
},
  "geometry": {"coordinates":[4.5529928207,51.1284103394],"type":"Point"}
}