{
  "type": "Feature",
  "properties": {
    "iso:country":"BE",
    "sg:address":"Westlaan 417",
    "sg:city":"Roeselare",
    "sg:orig_category":"Catering and organisation de f\u00eates. Salles de conf\u00e9rences and de r\u00e9ceptions",
    "sg:phone":"+32 51 20 68 83",
    "sg:postcode":"8800",
    "sg:province":"West-Vlaanderen",
    "wof:name":"Mandelhove",
    "wof:placetype":"venue"
},
  "geometry": {"coordinates":[3.1132390499,50.9540214539],"type":"Point"}
}