{
  "type": "Feature",
  "properties": {
    "addr:full":"Rijsestr. 70 Wijtschate West-Vlaanderen 8953",
    "addr:housenumber":"70",
    "addr:postcode":"8953",
    "addr:street":"Rijsestr.;West-Vlaanderen",
    "iso:country":"BE",
    "sg:address":"Rijsestr. 70",
    "sg:city":"Wijtschate",
    "sg:classifiers":[
        {
            "category":"Farming",
            "subcategory":"Livestock Farm",
            "type":"Manufacturing & Wholesale Goods"
        }
    ],
    "sg:phone":"+32 57 44 50 02",
    "sg:postcode":"8953",
    "sg:province":"West-Vlaanderen",
    "sg:tags":[
        "grain",
        "agriculture",
        "cereal"
    ],
    "wof:name":"Joye Gerard En Zoon Bvba",
    "wof:placetype":"venue"
},
  "geometry": {"coordinates":[2.928426981,50.7714691162],"type":"Point"}
}