{
  "type": "Feature",
  "properties": {
    "addr:full":"Koningin Elisabethlaan 70 Merelbeke Oost-Vlaanderen 9820",
    "addr:housenumber":"70",
    "addr:postcode":"9820",
    "addr:street":"Koningin Elisabethlaan",
    "iso:country":"BE",
    "sg:address":"Koningin Elisabethlaan 70",
    "sg:city":"Merelbeke",
    "sg:classifiers":[
        {
            "category":"Retail",
            "subcategory":"Veterinary Services",
            "type":"Services"
        }
    ],
    "sg:phone":"+32 9 231 63 85",
    "sg:postcode":"9820",
    "sg:province":"Oost-Vlaanderen",
    "sg:tags":[
        "veterinarian"
    ],
    "wof:name":"Fiers D",
    "wof:placetype":"venue"
},
  "geometry": {"coordinates":[3.7574961185,51.016040802],"type":"Point"}
}