{
  "type": "Feature",
  "properties": {
    "addr:full":"Avenue Gilbert 150 Fleurus Hainaut 6220",
    "addr:housenumber":"150",
    "addr:postcode":"6220",
    "addr:street":"Avenue Gilbert",
    "iso:country":"BE",
    "sg:address":"Avenue Gilbert 150",
    "sg:city":"Fleurus",
    "sg:orig_category":"Artsen and specialisten",
    "sg:phone":"+32 71 38 02 09",
    "sg:postcode":"6220",
    "sg:province":"Hainaut",
    "wof:name":"Caroline Colbrant",
    "wof:placetype":"venue"
},
  "geometry": {"coordinates":[4.5100388527,50.4461746216],"type":"Point"}
}