{
  "type": "Feature",
  "properties": {
    "addr:full":"Brusselbaan 385 Sint-pieters-leeuw Vlaams-Brabant 1600",
    "addr:housenumber":"385",
    "addr:postcode":"1600",
    "addr:street":"Brusselbaan",
    "iso:country":"BE",
    "sg:address":"Brusselbaan 385",
    "sg:city":"Sint-pieters-leeuw",
    "sg:classifiers":[
        {
            "category":"Health Services",
            "subcategory":"Health Practitioner",
            "type":"Services"
        }
    ],
    "sg:phone":"+32 2 378 22 11",
    "sg:postcode":"1600",
    "sg:province":"Vlaams-Brabant",
    "sg:tags":[
        "physiotherapist"
    ],
    "wof:name":"Van Den Broeck Sigrid",
    "wof:placetype":"venue"
},
  "geometry": {"coordinates":[4.2564401627,50.79662323],"type":"Point"}
}