{
  "type": "Feature",
  "properties": {
    "iso:country":"BE",
    "sg:address":"P.i. Taymansstraat 1",
    "sg:city":"Overijse",
    "sg:orig_category":"Mat\u00e9riel m\u00e9dical and orthop\u00e9dique and proth\u00e8ses Fab",
    "sg:phone":"+32 2 687 63 34",
    "sg:postcode":"3090",
    "sg:province":"Vlaams-Brabant",
    "wof:name":"M. Bruffaerts",
    "wof:placetype":"venue"
},
  "geometry": {"coordinates":[4.5372657776,50.7734146118],"type":"Point"}
}