{
  "type": "Feature",
  "properties": {
    "addr:full":"Tiensevest 188 Leuven Vlaams-Brabant 3000",
    "addr:housenumber":"188",
    "addr:postcode":"3000",
    "addr:street":"Tiensevest",
    "iso:country":"BE",
    "sg:address":"Tiensevest 188",
    "sg:city":"Leuven",
    "sg:orig_category":"Banken and kredietinstellingen",
    "sg:phone":"+32 16 22 15 04",
    "sg:postcode":"3000",
    "sg:province":"Vlaams-Brabant",
    "wof:name":"Groep Argenta",
    "wof:placetype":"venue"
},
  "geometry": {"coordinates":[4.710668087,50.8746681213],"type":"Point"}
}