{
  "type": "Feature",
  "properties": {
    "addr:full":"Place De Londres 6 Elsene/ixelles Bruxelles-Capitale 1050",
    "addr:housenumber":"6",
    "addr:postcode":"1050",
    "addr:street":"Place De Londres",
    "iso:country":"BE",
    "sg:address":"Place De Londres 6",
    "sg:city":"Elsene/ixelles",
    "sg:classifiers":[
        {
            "category":"Restaurant",
            "type":"Food & Drink"
        }
    ],
    "sg:phone":"+32 2 511 75 94",
    "sg:postcode":"1050",
    "sg:province":"Bruxelles-Capitale",
    "wof:name":"Snack-bar Sur Le Pouce",
    "wof:placetype":"venue"
},
  "geometry": {"coordinates":[4.3684740067,50.8377494812],"type":"Point"}
}