{
  "type": "Feature",
  "properties": {
    "iso:country":"BE",
    "sg:address":"Lekestraat 70",
    "sg:city":"Eeklo",
    "sg:classifiers":[
        {
            "category":"Personal",
            "subcategory":"Beauty Salon",
            "type":"Services"
        }
    ],
    "sg:phone":"+32 9 377 30 30",
    "sg:postcode":"9900",
    "sg:province":"Oost-Vlaanderen",
    "sg:tags":[
        "de",
        "coiffure"
    ],
    "wof:name":"Rita De Pauw",
    "wof:placetype":"venue"
},
  "geometry": {"coordinates":[3.5831758976,51.1792411804],"type":"Point"}
}