{
  "type": "Feature",
  "properties": {
    "iso:country":"BE",
    "sg:address":"Maarschalk Gerardstraat 23",
    "sg:city":"Antwerpen",
    "sg:classifiers":[
        {
            "category":"Restaurant",
            "type":"Food & Drink"
        }
    ],
    "sg:phone":"+32 3 203 00 09",
    "sg:postcode":"2000",
    "sg:province":"Antwerpen",
    "wof:name":"Otero",
    "wof:placetype":"venue"
},
  "geometry": {"coordinates":[4.4038438797,51.212387085],"type":"Point"}
}