{
  "type": "Feature",
  "properties": {
    "iso:country":"BE",
    "sg:address":"Avenue Victor Tesch 89",
    "sg:city":"Arlon",
    "sg:classifiers":[
        {
            "category":"Shopping",
            "subcategory":"Clothing, Apparel, & Fashions",
            "type":"Retail Goods"
        }
    ],
    "sg:phone":"+32 63 22 29 64",
    "sg:postcode":"6700",
    "sg:province":"Luxembourg",
    "sg:tags":[
        "boutique"
    ],
    "wof:name":"Triangle Boutique",
    "wof:placetype":"venue"
},
  "geometry": {"coordinates":[5.817920208,49.6819915771],"type":"Point"}
}