{
  "type": "Feature",
  "properties": {
    "iso:country":"BE",
    "sg:address":"Hospitaalstraat 23",
    "sg:city":"Ieper",
    "sg:orig_category":"Pluimveekwekers",
    "sg:phone":"+32 57 20 30 16",
    "sg:postcode":"8908",
    "sg:province":"West-Vlaanderen",
    "wof:name":"Stefaan Pattyn",
    "wof:placetype":"venue"
},
  "geometry": {"coordinates":[2.8160738945,50.8590736389],"type":"Point"}
}