{
  "type": "Feature",
  "properties": {
    "iso:country":"BE",
    "sg:address":"Rue De Chi\u00c8vres 106",
    "sg:city":"Saint-ghislain (grand)",
    "sg:classifiers":[
        {
            "category":"Personal",
            "subcategory":"Beauty Salon",
            "type":"Services"
        }
    ],
    "sg:phone":"+32 65 62 18 60",
    "sg:postcode":"7331",
    "sg:province":"Hainaut",
    "sg:tags":[
        "de",
        "coiffure"
    ],
    "wof:name":"Tif'phanie",
    "wof:placetype":"venue"
},
  "geometry": {"coordinates":[3.8071808815,50.4927711487],"type":"Point"}
}