{
  "type": "Feature",
  "properties": {
    "iso:country":"BE",
    "sg:address":"Helmetsesteenweg 192",
    "sg:city":"Schaarbeek/schaerbeek",
    "sg:orig_category":"Artsen and specialisten",
    "sg:phone":"+32 2 268 61 52",
    "sg:postcode":"1030",
    "sg:province":"Bruxelles-Capitale",
    "wof:name":"Philippe Volcke",
    "wof:placetype":"venue"
},
  "geometry": {"coordinates":[4.38667202,50.8729095459],"type":"Point"}
}