{
  "type": "Feature",
  "properties": {
    "addr:full":"Rue Saint-remy 10h Li\u00e8ge 1 Li\u00e8ge 4000",
    "addr:housenumber":"10h;1",
    "addr:postcode":"4000",
    "addr:street":"Rue Saint-Remy",
    "iso:country":"BE",
    "sg:address":"Rue Saint-remy 10h",
    "sg:city":"Li\u00e8ge 1",
    "sg:classifiers":[
        {
            "category":"Health Services",
            "subcategory":"Dentist",
            "type":"Services"
        }
    ],
    "sg:phone":"+32 4 223 38 49",
    "sg:postcode":"4000",
    "sg:province":"Li\u00e8ge",
    "wof:name":"Andr\u00e9 Fran\u00e7oise",
    "wof:placetype":"venue"
},
  "geometry": {"coordinates":[5.5696048737,50.638633728],"type":"Point"}
}