{
  "type": "Feature",
  "properties": {
    "addr:full":"Rue Du Cur\u00c9 41 Hannut Li\u00e8ge 4280",
    "addr:housenumber":"41",
    "addr:postcode":"4280",
    "addr:street":"Rue Du Cure\u0301",
    "iso:country":"BE",
    "sg:address":"Rue Du Cur\u00c9 41",
    "sg:city":"Hannut",
    "sg:orig_category":"Installatie van houten of kunststof schrijnwerk",
    "sg:phone":"+32 19 69 98 84",
    "sg:postcode":"4280",
    "sg:province":"Li\u00e8ge",
    "wof:name":"Joseph Fontaine",
    "wof:placetype":"venue"
},
  "geometry": {"coordinates":[5.068133831,50.6299209595],"type":"Point"}
}