{
  "type": "Feature",
  "properties": {
    "addr:full":"Statiestraat 56a Mol Antwerpen 2400",
    "addr:housenumber":"56a",
    "addr:postcode":"2400",
    "addr:street":"Statiestraat",
    "iso:country":"BE",
    "sg:address":"Statiestraat 56a",
    "sg:city":"Mol",
    "sg:classifiers":[
        {
            "category":"Tea Room",
            "subcategory":"None",
            "type":"Food & Drink"
        }
    ],
    "sg:phone":"+32 14 32 15 00",
    "sg:postcode":"2400",
    "sg:province":"Antwerpen",
    "wof:name":"Snackske ('t)",
    "wof:placetype":"venue"
},
  "geometry": {"coordinates":[5.1182022095,51.1898498535],"type":"Point"}
}