{
  "type": "Feature",
  "properties": {
    "addr:full":"R Waucomont 58 Herve (chaineux) Li\u00e8ge 4650",
    "addr:housenumber":"58",
    "addr:postcode":"4650",
    "iso:country":"BE",
    "sg:address":"R Waucomont 58",
    "sg:city":"Herve (chaineux)",
    "sg:classifiers":[
        {
            "category":"Health Services",
            "subcategory":"Dentist",
            "type":"Services"
        }
    ],
    "sg:phone":"+32 87 67 50 96",
    "sg:postcode":"4650",
    "sg:province":"Li\u00e8ge",
    "wof:name":"Masereel P",
    "wof:placetype":"venue"
},
  "geometry": {"coordinates":[5.829433918,50.6431312561],"type":"Point"}
}