{
  "type": "Feature",
  "properties": {
    "addr:full":"De Mosten 1 Hoogstraten (meer) Antwerpen 2321",
    "addr:housenumber":"1",
    "addr:postcode":"2321",
    "addr:street":"De Mosten;Meer",
    "iso:country":"BE",
    "sg:address":"De Mosten 1",
    "sg:city":"Hoogstraten (meer)",
    "sg:classifiers":[
        {
            "category":"Manufacturing",
            "subcategory":"Tools & Machinery",
            "type":"Manufacturing & Wholesale Goods"
        }
    ],
    "sg:phone":"+32 3 315 84 77",
    "sg:postcode":"2321",
    "sg:province":"Antwerpen",
    "sg:tags":[
        "builder"
    ],
    "wof:name":"Jochems Constructie & Machinebouw Bvba",
    "wof:placetype":"venue"
},
  "geometry": {"coordinates":[4.7366099358,51.442325592],"type":"Point"}
}