{
  "type": "Feature",
  "properties": {
    "addr:full":"Kardinaal Cardijnstraat 8 Aarschot Vlaams-Brabant 3200",
    "addr:housenumber":"8",
    "addr:postcode":"3200",
    "addr:street":"Kardinaal Cardijnstraat",
    "iso:country":"BE",
    "sg:address":"Kardinaal Cardijnstraat 8",
    "sg:city":"Aarschot",
    "sg:orig_category":"Sportclubs",
    "sg:phone":"+32 16 56 24 00",
    "sg:postcode":"3200",
    "sg:province":"Vlaams-Brabant",
    "wof:name":"T.c. 82",
    "wof:placetype":"venue"
},
  "geometry": {"coordinates":[4.8492040634,50.9955215454],"type":"Point"}
}