{
  "type": "Feature",
  "properties": {
    "addr:full":"Schoolstraat 1 Wemmel/wemmel Vlaams-Brabant 1780",
    "addr:housenumber":"1",
    "addr:postcode":"1780",
    "addr:street":"Schoolstraat",
    "iso:country":"BE",
    "sg:address":"Schoolstraat 1",
    "sg:city":"Wemmel/wemmel",
    "sg:orig_category":"Banken and kredietinstellingen",
    "sg:phone":"+32 2 460 16 30",
    "sg:postcode":"1780",
    "sg:province":"Vlaams-Brabant",
    "wof:name":"Bacob",
    "wof:placetype":"venue"
},
  "geometry": {"coordinates":[4.3070898056,50.9067382812],"type":"Point"}
}