{
  "type": "Feature",
  "properties": {
    "addr:full":"Boterstraat 5 Veurne West-Vlaanderen 8630",
    "addr:housenumber":"5",
    "addr:postcode":"8630",
    "addr:street":"Boterstraat",
    "iso:country":"BE",
    "sg:address":"Boterstraat 5",
    "sg:city":"Veurne",
    "sg:orig_category":"Electrom\u00e9nager, t\u00e9l\u00e9visions and radios. Installation \u00e9lectrique r\u00e9sidentielle",
    "sg:phone":"+32 58 31 50 22",
    "sg:postcode":"8630",
    "sg:province":"West-Vlaanderen",
    "wof:name":"Elektro Gantois",
    "wof:placetype":"venue"
},
  "geometry": {"coordinates":[2.6617588997,51.072681427],"type":"Point"}
}