{
  "type": "Feature",
  "properties": {
    "iso:country":"BE",
    "sg:address":"Weversstraat 16",
    "sg:city":"Gent",
    "sg:classifiers":[
        {
            "category":"Bakery",
            "type":"Food & Drink"
        }
    ],
    "sg:phone":"+32 9 226 60 06",
    "sg:postcode":"9000",
    "sg:province":"Oost-Vlaanderen",
    "sg:tags":[
        "confectioner",
        "baker"
    ],
    "wof:name":"Van Hecke L",
    "wof:placetype":"venue"
},
  "geometry": {"coordinates":[3.7025370598,51.0582618713],"type":"Point"}
}