{
  "type": "Feature",
  "properties": {
    "iso:country":"BE",
    "sg:address":"Stotert 55",
    "sg:city":"Balen",
    "sg:orig_category":"Enseignement maternel and primaire",
    "sg:phone":"+32 11 34 21 22",
    "sg:postcode":"2491",
    "sg:province":"Antwerpen",
    "wof:name":"Vrije Kleuterschool",
    "wof:placetype":"venue"
},
  "geometry": {"coordinates":[5.1772642136,51.1293678284],"type":"Point"}
}