{
  "type": "Feature",
  "properties": {
    "addr:full":"Nijverheidsstraat 12 Peer Limburg 3990",
    "addr:housenumber":"12",
    "addr:postcode":"3990",
    "addr:street":"Nijverheidsstraat",
    "iso:country":"BE",
    "sg:address":"Nijverheidsstraat 12",
    "sg:city":"Peer",
    "sg:orig_category":"Boissons Gr",
    "sg:phone":"+32 11 63 10 90",
    "sg:postcode":"3990",
    "sg:province":"Limburg",
    "wof:name":"Fa. Renckens",
    "wof:placetype":"venue"
},
  "geometry": {"coordinates":[5.4475598335,51.138671875],"type":"Point"}
}