{
  "type": "Feature",
  "properties": {
    "addr:full":"Ankerrui 12 Antwerpen Antwerpen 2000",
    "addr:housenumber":"12",
    "addr:postcode":"2000",
    "addr:street":"Ankerrui",
    "iso:country":"BE",
    "sg:address":"Ankerrui 12",
    "sg:city":"Antwerpen",
    "sg:classifiers":[
        {
            "category":"Professional",
            "subcategory":"Computer Services",
            "type":"Services"
        }
    ],
    "sg:phone":"+32 3 232 28 24",
    "sg:postcode":"2000",
    "sg:province":"Antwerpen",
    "sg:tags":[
        "-",
        "processing",
        "data"
    ],
    "wof:name":"Computer Recycling Europe",
    "wof:placetype":"venue"
},
  "geometry": {"coordinates":[4.4101629257,51.2268714905],"type":"Point"}
}