{
  "type": "Feature",
  "properties": {
    "addr:full":"Chauss\u00c9e Du Roeulux Mons Hainaut 7000",
    "addr:postcode":"7000",
    "addr:street":"Chausse\u0301E Du Roeulux;Hainaut",
    "iso:country":"BE",
    "sg:address":"Chauss\u00c9e Du Roeulux",
    "sg:city":"Mons",
    "sg:orig_category":"Herstellingen and onderhoud van auto's",
    "sg:phone":"+32 65 35 21 06",
    "sg:postcode":"7000",
    "sg:province":"Hainaut",
    "wof:name":"Alim Sprl",
    "wof:placetype":"venue"
},
  "geometry": {"coordinates":[3.9760088921,50.4567642212],"type":"Point"}
}