{
  "type": "Feature",
  "properties": {
    "addr:full":"Bisschopsweyerstraat 17 Alken Limburg 3570",
    "addr:housenumber":"17",
    "addr:postcode":"3570",
    "addr:street":"Bisschopsweyerstraat",
    "iso:country":"BE",
    "sg:address":"Bisschopsweyerstraat 17",
    "sg:city":"Alken",
    "sg:orig_category":"Rev\u00eatements pour sols and murs. Travaux de finition and nettoyage de b\u00e2timents. Peinture. Installati",
    "sg:phone":"+32 11 31 20 77",
    "sg:postcode":"3570",
    "sg:province":"Limburg",
    "wof:name":"Vandebos",
    "wof:placetype":"venue"
},
  "geometry": {"coordinates":[5.2718839645,50.8598213196],"type":"Point"}
}