{
  "type": "Feature",
  "properties": {
    "iso:country":"BE",
    "sg:address":"Leuvensesteenweg 149",
    "sg:city":"Boortmeerbeek",
    "sg:orig_category":"Imprimeries and copyshops. Services fun\u00e9raires",
    "sg:phone":"+32 15 51 10 19",
    "sg:postcode":"3191",
    "sg:province":"Vlaams-Brabant",
    "wof:name":"Van Camp",
    "wof:placetype":"venue"
},
  "geometry": {"coordinates":[4.5494561195,50.9836387634],"type":"Point"}
}