{
  "type": "Feature",
  "properties": {
    "iso:country":"BE",
    "sg:address":"Vossemberg 1",
    "sg:city":"Tervuren",
    "sg:orig_category":"Artsen and specialisten",
    "sg:phone":"+32 2 767 23 80",
    "sg:postcode":"3080",
    "sg:province":"Vlaams-Brabant",
    "wof:name":"Alain Hottart",
    "wof:placetype":"venue"
},
  "geometry": {"coordinates":[4.5644478798,50.8333969116],"type":"Point"}
}