{
  "type": "Feature",
  "properties": {
    "iso:country":"BE",
    "sg:address":"Place Albert I 42",
    "sg:city":"Charleroi (montignies-sur-sambre)",
    "sg:classifiers":[
        {
            "category":"Shopping",
            "subcategory":"Clothing, Apparel, & Fashions",
            "type":"Retail Goods"
        }
    ],
    "sg:phone":"+32 71 32 95 79",
    "sg:postcode":"6061",
    "sg:province":"Hainaut",
    "sg:tags":[
        "underwear",
        "lingerie",
        "-"
    ],
    "wof:name":"Bacarini (lingerie)",
    "wof:placetype":"venue"
},
  "geometry": {"coordinates":[4.4795150757,50.4009437561],"type":"Point"}
}