{
  "type": "Feature",
  "properties": {
    "addr:full":"Chauss\u00c9e De Dinant 61 Anhee Namur 5537",
    "addr:housenumber":"61",
    "addr:postcode":"5537",
    "addr:street":"Chausse\u0301E De Dinant;Namur",
    "iso:country":"BE",
    "sg:address":"Chauss\u00c9e De Dinant 61",
    "sg:city":"Anhee",
    "sg:orig_category":"Traitements param\u00e9dicaux",
    "sg:phone":"+32 82 61 33 35",
    "sg:postcode":"5537",
    "sg:province":"Namur",
    "wof:name":"F. Ligna",
    "wof:placetype":"venue"
},
  "geometry": {"coordinates":[4.8847618103,50.3051528931],"type":"Point"}
}