{
  "type": "Feature",
  "properties": {
    "addr:full":"Vennestraat 15 Beringen (beverlo) Limburg 3581",
    "addr:housenumber":"15",
    "addr:postcode":"3581",
    "addr:street":"Vennestraat",
    "iso:country":"BE",
    "sg:address":"Vennestraat 15",
    "sg:city":"Beringen (beverlo)",
    "sg:orig_category":"Ice-cream parlours",
    "sg:phone":"+32 11 34 60 47",
    "sg:postcode":"3581",
    "sg:province":"Limburg",
    "wof:name":"Kasteeltje ('t)",
    "wof:placetype":"venue"
},
  "geometry": {"coordinates":[5.2029647827,51.084236145],"type":"Point"}
}