{
  "type": "Feature",
  "properties": {
    "addr:full":"Sint-guidostraat 8 Anderlecht Bruxelles-Capitale 1070",
    "addr:housenumber":"8",
    "addr:postcode":"1070",
    "addr:street":"Sint-Guidostraat",
    "iso:country":"BE",
    "sg:address":"Sint-guidostraat 8",
    "sg:city":"Anderlecht",
    "sg:orig_category":"Verplichte sociale verzekeringen",
    "sg:phone":"+32 2 521 53 09",
    "sg:postcode":"1070",
    "sg:province":"Bruxelles-Capitale",
    "wof:name":"Kristelijk Ziekenfonds",
    "wof:placetype":"venue"
},
  "geometry": {"coordinates":[4.3058772087,50.8351020813],"type":"Point"}
}