{
  "type": "Feature",
  "properties": {
    "iso:country":"BE",
    "sg:address":"Oostnieuwkerksesteenweg 209",
    "sg:city":"Roeselare",
    "sg:orig_category":"Entretien and r\u00e9parations de voitures. Emballages en plastique Fab",
    "sg:phone":"+32 51 22 95 95",
    "sg:postcode":"8800",
    "sg:province":"West-Vlaanderen",
    "wof:name":"Paul Van Hollebeke",
    "wof:placetype":"venue"
},
  "geometry": {"coordinates":[3.0885179043,50.9448051453],"type":"Point"}
}