{
  "type": "Feature",
  "properties": {
    "addr:full":"Rue De La Bataille 4 Neufchateau Luxembourg 6840",
    "addr:housenumber":"4",
    "addr:postcode":"6840",
    "addr:street":"Rue De La Bataille",
    "iso:country":"BE",
    "sg:address":"Rue De La Bataille 4",
    "sg:city":"Neufchateau",
    "sg:orig_category":"Notaires",
    "sg:phone":"+32 61 27 71 59",
    "sg:postcode":"6840",
    "sg:province":"Luxembourg",
    "wof:name":"J.f. Koeckx",
    "wof:placetype":"venue"
},
  "geometry": {"coordinates":[5.4320850372,49.841835022],"type":"Point"}
}