{
  "type": "Feature",
  "properties": {
    "addr:full":"Kettingbrugweg 50 Bocholt Limburg 3950",
    "addr:housenumber":"50",
    "addr:postcode":"3950",
    "addr:street":"Kettingbrugweg",
    "iso:country":"BE",
    "sg:address":"Kettingbrugweg 50",
    "sg:city":"Bocholt",
    "sg:orig_category":"Gespecialiseerde niet-residenti\u00eble bouw Industri\u00eble and commerci\u00eble bouw",
    "sg:phone":"+32 11 62 21 30",
    "sg:postcode":"3950",
    "sg:province":"Limburg",
    "wof:name":"Inboco",
    "wof:placetype":"venue"
},
  "geometry": {"coordinates":[5.5217380524,51.2119522095],"type":"Point"}
}