{
  "type": "Feature",
  "properties": {
    "addr:full":"Rue E B\u00c9ro 8 Graven Brabant Wallon 1390",
    "addr:housenumber":"8",
    "addr:postcode":"1390",
    "addr:street":"Rue E Be\u0301Ro",
    "iso:country":"BE",
    "sg:address":"Rue E B\u00c9ro 8",
    "sg:city":"Graven",
    "sg:orig_category":"Winkelinrichting and handelsuitrusting Gh",
    "sg:phone":"+32 10 84 22 92",
    "sg:postcode":"1390",
    "sg:province":"Brabant Wallon",
    "wof:name":"Begifroid",
    "wof:placetype":"venue"
},
  "geometry": {"coordinates":[4.6970720291,50.7384757996],"type":"Point"}
}