{
  "type": "Feature",
  "properties": {
    "iso:country":"BE",
    "sg:address":"Lembekedorp 42",
    "sg:city":"Kaprijke",
    "sg:orig_category":"Slagers",
    "sg:phone":"+32 9 377 20 48",
    "sg:postcode":"9971",
    "sg:province":"Oost-Vlaanderen",
    "wof:name":"Rudy Madou",
    "wof:placetype":"venue"
},
  "geometry": {"coordinates":[3.6313729286,51.1945343018],"type":"Point"}
}