{
  "type": "Feature",
  "properties": {
    "iso:country":"BE",
    "sg:address":"Kelfsstraat 51",
    "sg:city":"Haacht",
    "sg:orig_category":"Centres de relaxation and bien-\u00eatre. Instituts de beaut\u00e9",
    "sg:phone":"+32 16 60 08 14",
    "sg:postcode":"3150",
    "sg:province":"Vlaams-Brabant",
    "wof:name":"Het Klein Verschil",
    "wof:placetype":"venue"
},
  "geometry": {"coordinates":[4.679473877,50.9512176514],"type":"Point"}
}