{
  "type": "Feature",
  "properties": {
    "iso:country":"BE",
    "sg:address":"Markt 12",
    "sg:city":"Waregem",
    "sg:orig_category":"Banken and kredietinstellingen",
    "sg:phone":"+32 56 60 48 00",
    "sg:postcode":"8790",
    "sg:province":"West-Vlaanderen",
    "wof:name":"Dexia",
    "wof:placetype":"venue"
},
  "geometry": {"coordinates":[3.4317800999,50.8867416382],"type":"Point"}
}