{
  "type": "Feature",
  "properties": {
    "addr:full":"Lieven Delaruyestraat 38 Gent Oost-Vlaanderen 9050",
    "addr:housenumber":"38",
    "addr:postcode":"9050",
    "addr:street":"Delaruyestraat;Oost-Vlaanderen",
    "iso:country":"BE",
    "sg:address":"Lieven Delaruyestraat 38",
    "sg:city":"Gent",
    "sg:orig_category":"Charpentes and couvertures",
    "sg:phone":"+32 9 231 04 48",
    "sg:postcode":"9050",
    "sg:province":"Oost-Vlaanderen",
    "wof:name":"Mobi-clean",
    "wof:placetype":"venue"
},
  "geometry": {"coordinates":[3.7473499775,51.0402488708],"type":"Point"}
}