{
  "type": "Feature",
  "properties": {
    "addr:full":"Leuvensesteenweg 3ba Tervuren Vlaams-Brabant 3080",
    "addr:housenumber":"3ba",
    "addr:postcode":"3080",
    "addr:street":"Leuvensesteenweg",
    "iso:country":"BE",
    "sg:address":"Leuvensesteenweg 3ba",
    "sg:city":"Tervuren",
    "sg:orig_category":"Eclairage et \u00e9quipements du foyer",
    "sg:phone":"+32 2 767 29 86",
    "sg:postcode":"3080",
    "sg:province":"Vlaams-Brabant",
    "wof:name":"La Torcia",
    "wof:placetype":"venue"
},
  "geometry": {"coordinates":[4.513297081,50.8246612549],"type":"Point"}
}