{
  "type": "Feature",
  "properties": {
    "addr:full":"Spoorwegstraat 59 Kasterlee Antwerpen 2460",
    "addr:housenumber":"59",
    "addr:postcode":"2460",
    "addr:street":"Spoorwegstraat",
    "iso:country":"BE",
    "sg:address":"Spoorwegstraat 59",
    "sg:city":"Kasterlee",
    "sg:orig_category":"V\u00e9t\u00e9rinaires",
    "sg:phone":"+32 14 55 45 28",
    "sg:postcode":"2460",
    "sg:province":"Antwerpen",
    "wof:name":"Fernand Marien",
    "wof:placetype":"venue"
},
  "geometry": {"coordinates":[4.8993592262,51.2479782104],"type":"Point"}
}