{
  "type": "Feature",
  "properties": {
    "iso:country":"BE",
    "sg:address":"Rue Saint-barth\u00e9lemy 45",
    "sg:city":"Fleurus (heppignies)",
    "sg:classifiers":[
        {
            "category":"Personal",
            "subcategory":"Nail Salon",
            "type":"Services"
        }
    ],
    "sg:phone":"+32 71 85 45 27",
    "sg:postcode":"6220",
    "sg:province":"Hainaut",
    "sg:tags":[
        "pedicure"
    ],
    "wof:name":"Lenoir P",
    "wof:placetype":"venue"
},
  "geometry": {"coordinates":[4.4951138496,50.4827575684],"type":"Point"}
}