{
  "type": "Feature",
  "properties": {
    "addr:full":"Pauwengraaf 23-25 Maasmechelen (eisden) Limburg 3630",
    "addr:housenumber":"23-25",
    "addr:postcode":"3630",
    "iso:country":"BE",
    "sg:address":"Pauwengraaf 23-25",
    "sg:city":"Maasmechelen (eisden)",
    "sg:classifiers":[
        {
            "category":"Banks & Credit Unions",
            "subcategory":"Investment Brokerage",
            "type":"Services"
        }
    ],
    "sg:phone":"+32 89 77 14 24",
    "sg:postcode":"3630",
    "sg:province":"Limburg",
    "sg:tags":[
        "jean",
        "casual",
        "wear"
    ],
    "wof:name":"Peppe Jeans",
    "wof:placetype":"venue"
},
  "geometry": {"coordinates":[5.6961350441,50.963848114],"type":"Point"}
}