{
  "type": "Feature",
  "properties": {
    "iso:country":"BE",
    "sg:address":"Rue Vandergoten 4",
    "sg:city":"Oudergem",
    "sg:classifiers":[
        {
            "category":"Shopping",
            "subcategory":"Computers & Home Electronics",
            "type":"Retail Goods"
        }
    ],
    "sg:phone":"+32 2 675 56 73",
    "sg:postcode":"1160",
    "sg:province":"Bruxelles-Capitale",
    "sg:tags":[
        "individual",
        "software"
    ],
    "wof:name":"Bgi S.a.",
    "wof:placetype":"venue"
},
  "geometry": {"coordinates":[4.4247498512,50.8172492981],"type":"Point"}
}