{
  "type": "Feature",
  "properties": {
    "addr:full":"Rue Du Soleil 196 Ronse/renaix Oost-Vlaanderen 9600",
    "addr:housenumber":"196",
    "addr:postcode":"9600",
    "addr:street":"Rue Du Soleil",
    "iso:country":"BE",
    "sg:address":"Rue Du Soleil 196",
    "sg:city":"Ronse/renaix",
    "sg:classifiers":[
        {
            "category":"Fast Food",
            "type":"Food & Drink"
        }
    ],
    "sg:phone":"+32 55 20 99 73",
    "sg:postcode":"9600",
    "sg:province":"Oost-Vlaanderen",
    "sg:tags":[
        "restaurant",
        "\u00c0",
        "domicile",
        "emporter",
        "livraison",
        "restaurants"
    ],
    "wof:name":"Sun Shop",
    "wof:placetype":"venue"
},
  "geometry": {"coordinates":[3.5992999077,50.7470397949],"type":"Point"}
}