{
  "type": "Feature",
  "properties": {
    "addr:full":"Rue De Maharenne 25 Anh\u00e9e (den\u00e9e) Namur 5537",
    "addr:housenumber":"25",
    "addr:postcode":"5537",
    "addr:street":"Rue De Maharenne",
    "iso:country":"BE",
    "sg:address":"Rue De Maharenne 25",
    "sg:city":"Anh\u00e9e (den\u00e9e)",
    "sg:classifiers":[
        {
            "category":"Personal",
            "subcategory":"Nail Salon",
            "type":"Services"
        }
    ],
    "sg:phone":"+32 71 79 95 68",
    "sg:postcode":"5537",
    "sg:province":"Namur",
    "sg:tags":[
        "pedicure"
    ],
    "wof:name":"Feraille",
    "wof:placetype":"venue"
},
  "geometry": {"coordinates":[4.7576088905,50.3174285889],"type":"Point"}
}