{
  "type": "Feature",
  "properties": {
    "iso:country":"BE",
    "sg:address":"Ieperstraat 246a",
    "sg:city":"Menen",
    "sg:orig_category":"Boucheries",
    "sg:phone":"+32 56 51 24 39",
    "sg:postcode":"8930",
    "sg:province":"West-Vlaanderen",
    "wof:name":"D'hallewin Dieter",
    "wof:placetype":"venue"
},
  "geometry": {"coordinates":[3.1091990471,50.7997169495],"type":"Point"}
}