{
  "type": "Feature",
  "properties": {
    "addr:full":"Burg. Rollierstraat 41 Denderleeuw Oost-Vlaanderen 9470",
    "addr:housenumber":"41",
    "addr:postcode":"9470",
    "addr:street":"Burg. Rollierstraat",
    "iso:country":"BE",
    "sg:address":"Burg. Rollierstraat 41",
    "sg:city":"Denderleeuw",
    "sg:orig_category":"Herstellingen and onderhoud van auto's Voertuigen",
    "sg:phone":"+32 53 66 88 02",
    "sg:postcode":"9470",
    "sg:province":"Oost-Vlaanderen",
    "wof:name":"Garage Van Neck",
    "wof:placetype":"venue"
},
  "geometry": {"coordinates":[4.0735340118,50.8864707947],"type":"Point"}
}