{
  "type": "Feature",
  "properties": {
    "addr:full":"Mechelsesteenweg 380 Lier Antwerpen 2500",
    "addr:housenumber":"380",
    "addr:postcode":"2500",
    "addr:street":"Mechelsesteenweg",
    "iso:country":"BE",
    "sg:address":"Mechelsesteenweg 380",
    "sg:city":"Lier",
    "sg:classifiers":[
        {
            "category":"Arena",
            "subcategory":"Sports Club",
            "type":"Entertainment"
        }
    ],
    "sg:phone":"+32 15 31 42 49",
    "sg:postcode":"2500",
    "sg:province":"Antwerpen",
    "sg:tags":[
        "terrain",
        "hors",
        "de",
        "installation",
        "sportifs"
    ],
    "wof:name":"Tennis 't Sas",
    "wof:placetype":"venue"
},
  "geometry": {"coordinates":[4.5251221657,51.1093215942],"type":"Point"}
}