{
  "type": "Feature",
  "properties": {
    "iso:country":"BE",
    "sg:address":"Ondernemingenstr 5",
    "sg:city":"Veurne",
    "sg:classifiers":[
        {
            "category":"Bakery",
            "type":"Food & Drink"
        }
    ],
    "sg:phone":"+32 58 33 06 60",
    "sg:postcode":"8630",
    "sg:province":"West-Vlaanderen",
    "sg:tags":[
        "cake",
        "product",
        "related",
        "bread"
    ],
    "wof:name":"Diksmuidse Pannenkoeken Bvba",
    "wof:placetype":"venue"
},
  "geometry": {"coordinates":[2.677850008,51.0620689392],"type":"Point"}
}