{
  "type": "Feature",
  "properties": {
    "addr:full":"Chauss\u00c9e De Bruxelles 218 Waterloo Brabant Wallon 1410",
    "addr:housenumber":"218",
    "addr:postcode":"1410",
    "addr:street":"Chausse\u0301E De Bruxelles",
    "iso:country":"BE",
    "sg:address":"Chauss\u00c9e De Bruxelles 218",
    "sg:city":"Waterloo",
    "sg:orig_category":"Offices du tourisme",
    "sg:phone":"+32 2 351 12 00",
    "sg:postcode":"1410",
    "sg:province":"Brabant Wallon",
    "wof:name":"Fed. Tourist. Prov. Brab.",
    "wof:placetype":"venue"
},
  "geometry": {"coordinates":[4.3977642059,50.7176322937],"type":"Point"}
}