{
  "type": "Feature",
  "properties": {
    "addr:full":"Rue Des Pr\u00e9s Fleuris 25 Couvin Namur 5660",
    "addr:housenumber":"25",
    "addr:postcode":"5660",
    "addr:street":"Rue Des Pre\u0301S Fleuris",
    "iso:country":"BE",
    "sg:address":"Rue Des Pr\u00e9s Fleuris 25",
    "sg:city":"Couvin",
    "sg:classifiers":[
        {
            "category":"Retail",
            "subcategory":"Veterinary Services",
            "type":"Services"
        }
    ],
    "sg:phone":"+32 60 34 54 29",
    "sg:postcode":"5660",
    "sg:province":"Namur",
    "sg:tags":[
        "veterinarian"
    ],
    "wof:name":"Lecomte G",
    "wof:placetype":"venue"
},
  "geometry": {"coordinates":[4.4800310135,50.0547904968],"type":"Point"}
}