{
  "type": "Feature",
  "properties": {
    "iso:country":"BE",
    "sg:address":"Haarkenstraat 11",
    "sg:city":"Nevele",
    "sg:orig_category":"Producteurs de l\u00e9gumes",
    "sg:phone":"+32 9 371 50 59",
    "sg:postcode":"9850",
    "sg:province":"Oost-Vlaanderen",
    "wof:name":"Dirk Sergeant",
    "wof:placetype":"venue"
},
  "geometry": {"coordinates":[3.5854520798,51.0553474426],"type":"Point"}
}