{
  "type": "Feature",
  "properties": {
    "addr:full":"Place Communale D'auderghem 20 Bruxelles (auderghem) Bruxelles-Capitale 1160",
    "addr:housenumber":"20",
    "addr:postcode":"1160",
    "addr:street":"Place Communale D'Auderghem",
    "iso:country":"BE",
    "sg:address":"Place Communale D'auderghem 20",
    "sg:city":"Bruxelles (auderghem)",
    "sg:classifiers":[
        {
            "category":"Parking",
            "subcategory":"Lot",
            "type":"Transportation"
        }
    ],
    "sg:phone":"+32 2 673 76 46",
    "sg:postcode":"1160",
    "sg:province":"Bruxelles-Capitale",
    "sg:tags":[
        "armoured",
        "door",
        "fireproof"
    ],
    "wof:name":"Euro-security",
    "wof:placetype":"venue"
},
  "geometry": {"coordinates":[4.4281959534,50.8155403137],"type":"Point"}
}