{
  "type": "Feature",
  "properties": {
    "iso:country":"BE",
    "sg:address":"Burgstrasse 111",
    "sg:city":"Raeren",
    "sg:classifiers":[
        {
            "category":"Farming",
            "subcategory":"Livestock Farm",
            "type":"Manufacturing & Wholesale Goods"
        }
    ],
    "sg:phone":"+32 87 85 14 86",
    "sg:postcode":"4730",
    "sg:province":"Li\u00e8ge",
    "sg:tags":[
        "buyer"
    ],
    "wof:name":"Creutz A",
    "wof:placetype":"venue"
},
  "geometry": {"coordinates":[6.1223688126,50.6786117554],"type":"Point"}
}