{
  "type": "Feature",
  "properties": {
    "addr:full":"Rue Victor Brodure 38 Theux (polleur) Li\u00e8ge 4910",
    "addr:housenumber":"38",
    "addr:postcode":"4910",
    "addr:street":"Rue Victor Brodure",
    "iso:country":"BE",
    "sg:address":"Rue Victor Brodure 38",
    "sg:city":"Theux (polleur)",
    "sg:classifiers":[
        {
            "category":"Professional",
            "subcategory":"Accounting & Tax Preparation",
            "type":"Services"
        }
    ],
    "sg:phone":"+32 87 26 61 20",
    "sg:postcode":"4910",
    "sg:province":"Li\u00e8ge",
    "sg:tags":[
        "bookkeeper"
    ],
    "wof:name":"De La Cerda P",
    "wof:placetype":"venue"
},
  "geometry": {"coordinates":[5.8130488396,50.5356216431],"type":"Point"}
}