{
  "type": "Feature",
  "properties": {
    "iso:country":"BE",
    "sg:address":"Leuvensestraat 14",
    "sg:city":"Tienen",
    "sg:classifiers":[
        {
            "category":"Wholesale",
            "subcategory":"Medical Equipment & Supplies",
            "type":"Manufacturing & Wholesale Goods"
        }
    ],
    "sg:phone":"+32 16 81 27 45",
    "sg:postcode":"3300",
    "sg:province":"Vlaams-Brabant",
    "sg:tags":[
        "aid",
        "hearing"
    ],
    "wof:name":"Optiek D",
    "wof:placetype":"venue"
},
  "geometry": {"coordinates":[4.928814888,50.8097991943],"type":"Point"}
}