{
  "type": "Feature",
  "properties": {
    "iso:country":"BE",
    "sg:address":"Avenue Du Bosquet 30",
    "sg:city":"Huy (ben-ahin)",
    "sg:classifiers":[
        {
            "category":"Retail",
            "subcategory":"Auto Rental",
            "type":"Services"
        }
    ],
    "sg:phone":"+32 85 21 25 25",
    "sg:postcode":"4500",
    "sg:province":"Li\u00e8ge",
    "sg:tags":[
        "automobile",
        "-",
        "car",
        "self-drive"
    ],
    "wof:name":"Charlier D\u00e9pannage",
    "wof:placetype":"venue"
},
  "geometry": {"coordinates":[5.2157521248,50.5266342163],"type":"Point"}
}