{
  "type": "Feature",
  "properties": {
    "iso:country":"BE",
    "sg:address":"Rue Brogniez 37",
    "sg:city":"Anderlecht/anderlecht",
    "sg:orig_category":"Alimentation sp\u00e9cialis\u00e9e",
    "sg:phone":"+32 2 520 42 80",
    "sg:postcode":"1070",
    "sg:province":"Bruxelles-Capitale",
    "wof:name":"Elkeslassy Mazeltov",
    "wof:placetype":"venue"
},
  "geometry": {"coordinates":[4.3374490738,50.8421401978],"type":"Point"}
}