{
  "type": "Feature",
  "properties": {
    "addr:full":"Leopold De Vriesstraat 10 Antwerpen Antwerpen 2600",
    "addr:housenumber":"10",
    "addr:postcode":"2600",
    "addr:street":"Leopold De Vriesstraat",
    "iso:country":"BE",
    "sg:address":"Leopold De Vriesstraat 10",
    "sg:city":"Antwerpen",
    "sg:orig_category":"V\u00eatements sur mesure Fab",
    "sg:phone":"+32 3 230 07 69",
    "sg:postcode":"2600",
    "sg:province":"Antwerpen",
    "wof:name":"Odrada Vercammen",
    "wof:placetype":"venue"
},
  "geometry": {"coordinates":[4.3935108185,51.2586288452],"type":"Point"}
}