{
  "type": "Feature",
  "properties": {
    "addr:full":"Chauss\u00c9e De Huy 197 Chaumont-gistoux Brabant Wallon 1325",
    "addr:housenumber":"197",
    "addr:postcode":"1325",
    "addr:street":"Chausse\u0301E De Huy",
    "iso:country":"BE",
    "sg:address":"Chauss\u00c9e De Huy 197",
    "sg:city":"Chaumont-gistoux",
    "sg:orig_category":"Drogisterijen",
    "sg:phone":"+32 10 68 91 47",
    "sg:postcode":"1325",
    "sg:province":"Brabant Wallon",
    "wof:name":"E. Stouffs",
    "wof:placetype":"venue"
},
  "geometry": {"coordinates":[4.6914768219,50.6868591309],"type":"Point"}
}