{
  "type": "Feature",
  "properties": {
    "addr:full":"Avenue Minjean 9 Tournai Hainaut 7500",
    "addr:housenumber":"9",
    "addr:postcode":"7500",
    "addr:street":"Avenue Minjean",
    "iso:country":"BE",
    "sg:address":"Avenue Minjean 9",
    "sg:city":"Tournai",
    "sg:classifiers":[
        {
            "category":"Organizations",
            "subcategory":"Community Association",
            "type":"Services"
        }
    ],
    "sg:phone":"+32 69 21 14 35",
    "sg:postcode":"7500",
    "sg:province":"Hainaut",
    "sg:tags":[
        "organisation"
    ],
    "wof:name":"M.j. Port'ouverte",
    "wof:placetype":"venue"
},
  "geometry": {"coordinates":[3.3676431179,50.6060218811],"type":"Point"}
}