{
  "type": "Feature",
  "properties": {
    "addr:full":"Goed Ter Linden 5 Kortrijk West-Vlaanderen 8500",
    "addr:housenumber":"5",
    "addr:postcode":"8500",
    "addr:street":"Goed Ter Linden",
    "iso:country":"BE",
    "sg:address":"Goed Ter Linden 5",
    "sg:city":"Kortrijk",
    "sg:orig_category":"Diverse grafische activiteiten",
    "sg:phone":"+32 56 20 13 81",
    "sg:postcode":"8500",
    "sg:province":"West-Vlaanderen",
    "wof:name":"Stock Graphic Design",
    "wof:placetype":"venue"
},
  "geometry": {"coordinates":[3.2649960518,50.8086700439],"type":"Point"}
}