{
  "type": "Feature",
  "properties": {
    "addr:full":"Chemin De Casteau 32 Soignies Hainaut 7063",
    "addr:housenumber":"32",
    "addr:postcode":"7063",
    "addr:street":"Chemin De Casteau",
    "iso:country":"BE",
    "sg:address":"Chemin De Casteau 32",
    "sg:city":"Soignies",
    "sg:orig_category":"Catering and organisation de f\u00eates",
    "sg:phone":"+32 65 72 37 72",
    "sg:postcode":"7063",
    "sg:province":"Hainaut",
    "wof:name":"Christophe Malree",
    "wof:placetype":"venue"
},
  "geometry": {"coordinates":[3.993940115,50.5837898254],"type":"Point"}
}