{
  "type": "Feature",
  "properties": {
    "iso:country":"BE",
    "sg:address":"Jakob Van Arteveldestraat 18",
    "sg:city":"Wevelgem",
    "sg:classifiers":[
        {
            "category":"Building & Trades",
            "subcategory":"Pest Control",
            "type":"Services"
        }
    ],
    "sg:phone":"+32 56 42 11 28",
    "sg:postcode":"8560",
    "sg:province":"West-Vlaanderen",
    "sg:tags":[
        "painting",
        "contractor"
    ],
    "wof:name":"Daels H",
    "wof:placetype":"venue"
},
  "geometry": {"coordinates":[3.1804459095,50.8189735413],"type":"Point"}
}