{
  "type": "Feature",
  "properties": {
    "iso:country":"BE",
    "sg:address":"Berkenlaan 97",
    "sg:city":"Harelbeke",
    "sg:orig_category":"Avocats and conseillers juridiques",
    "sg:phone":"+32 56 71 84 85",
    "sg:postcode":"8530",
    "sg:province":"West-Vlaanderen",
    "wof:name":"T. Vandewalle",
    "wof:placetype":"venue"
},
  "geometry": {"coordinates":[3.2979938984,50.8397521973],"type":"Point"}
}