{
  "type": "Feature",
  "properties": {
    "addr:full":"Donk 45 Lier Antwerpen 2500",
    "addr:housenumber":"45",
    "addr:postcode":"2500",
    "addr:street":"Donk",
    "iso:country":"BE",
    "sg:address":"Donk 45",
    "sg:city":"Lier",
    "sg:orig_category":"Elektrische installaties voor woningen",
    "sg:phone":"+32 3 488 58 75",
    "sg:postcode":"2500",
    "sg:province":"Antwerpen",
    "wof:name":"Tony Janssens",
    "wof:placetype":"venue"
},
  "geometry": {"coordinates":[4.5515999794,51.1393814087],"type":"Point"}
}