{
  "type": "Feature",
  "properties": {
    "addr:full":"Dorpsstraat 37 Middelkerke West-Vlaanderen 8432",
    "addr:housenumber":"37",
    "addr:postcode":"8432",
    "addr:street":"Dorpsstraat",
    "iso:country":"BE",
    "sg:address":"Dorpsstraat 37",
    "sg:city":"Middelkerke",
    "sg:orig_category":"Epiceries",
    "sg:phone":"+32 59 30 02 90",
    "sg:postcode":"8432",
    "sg:province":"West-Vlaanderen",
    "wof:name":"Spar",
    "wof:placetype":"venue"
},
  "geometry": {"coordinates":[2.8768401146,51.1755104065],"type":"Point"}
}