{
  "type": "Feature",
  "properties": {
    "addr:full":"Elslo 11 Evergem Oost-Vlaanderen 9940",
    "addr:housenumber":"11",
    "addr:postcode":"9940",
    "addr:street":"Elslo;Oost-Vlaanderen",
    "iso:country":"BE",
    "sg:address":"Elslo 11",
    "sg:city":"Evergem",
    "sg:orig_category":"Installatie van metalen schrijnwerk",
    "sg:phone":"+32 9 253 23 27",
    "sg:postcode":"9940",
    "sg:province":"Oost-Vlaanderen",
    "wof:name":"Frank Thilemans",
    "wof:placetype":"venue"
},
  "geometry": {"coordinates":[3.7138381004,51.1156463623],"type":"Point"}
}