{
  "type": "Feature",
  "properties": {
    "addr:full":"Brusselsesteenweg 351 Melle Oost-Vlaanderen 9090",
    "addr:housenumber":"351",
    "addr:postcode":"9090",
    "addr:street":"Brusselsesteenweg",
    "iso:country":"BE",
    "sg:address":"Brusselsesteenweg 351",
    "sg:city":"Melle",
    "sg:orig_category":"Drogisterijen IJzerwaren, bouw- and verfmaterialen Textiel Verlichting and huishoudartikelen",
    "sg:phone":"+32 9 252 15 81",
    "sg:postcode":"9090",
    "sg:province":"Oost-Vlaanderen",
    "wof:name":"Ars Vivendi",
    "wof:placetype":"venue"
},
  "geometry": {"coordinates":[3.8026850224,51.002532959],"type":"Point"}
}