{
  "type": "Feature",
  "properties": {
    "iso:country":"BE",
    "sg:address":"Saunierlei 66",
    "sg:city":"Hemiksem",
    "sg:classifiers":[
        {
            "category":"Home & Garden",
            "subcategory":"Home Furnishings",
            "type":"Retail Goods"
        }
    ],
    "sg:phone":"+32 3 887 47 40",
    "sg:postcode":"2620",
    "sg:province":"Antwerpen",
    "sg:tags":[
        "curtain",
        "-",
        "fixture"
    ],
    "wof:name":"In De Witte Poort",
    "wof:placetype":"venue"
},
  "geometry": {"coordinates":[4.3378372192,51.136882782],"type":"Point"}
}