{
  "type": "Feature",
  "properties": {
    "iso:country":"BE",
    "sg:address":"Nassaulaan 1",
    "sg:city":"Baarle-hertog",
    "sg:orig_category":"Imprimeries and copyshops",
    "sg:phone":"+32 14 69 91 19",
    "sg:postcode":"2387",
    "sg:province":"Antwerpen",
    "wof:name":"Drukkerij Uitg. Dejong",
    "wof:placetype":"venue"
},
  "geometry": {"coordinates":[4.9338960648,51.4474487305],"type":"Point"}
}