{
  "type": "Feature",
  "properties": {
    "iso:country":"BE",
    "sg:address":"Tolhuisstraat 1312",
    "sg:city":"Schelle",
    "sg:orig_category":"Zuivelproducten",
    "sg:phone":"+32 3 887 94 07",
    "sg:postcode":"2627",
    "sg:province":"Antwerpen",
    "wof:name":"Huis Campo Gebrs",
    "wof:placetype":"venue"
},
  "geometry": {"coordinates":[4.3122048378,51.119102478],"type":"Point"}
}