{
  "type": "Feature",
  "properties": {
    "addr:full":"Verzoeningsstraat 12 Anderlecht Bruxelles-Capitale 1070",
    "addr:housenumber":"12",
    "addr:postcode":"1070",
    "addr:street":"Verzoeningsstraat",
    "iso:country":"BE",
    "sg:address":"Verzoeningsstraat 12",
    "sg:city":"Anderlecht",
    "sg:orig_category":"Boekhouders",
    "sg:phone":"+32 2 523 04 29",
    "sg:postcode":"1070",
    "sg:province":"Bruxelles-Capitale",
    "wof:name":"Huguette Joie",
    "wof:placetype":"venue"
},
  "geometry": {"coordinates":[4.3123178482,50.8368453979],"type":"Point"}
}