{
  "type": "Feature",
  "properties": {
    "iso:country":"BE",
    "sg:address":"Oude Antwerpse Baan 121",
    "sg:city":"Mechelen",
    "sg:orig_category":"Blanchisseries and teintureries",
    "sg:phone":"+32 15 20 33 24",
    "sg:postcode":"2800",
    "sg:province":"Antwerpen",
    "wof:name":"Helwit Was- En Zelfwasserij",
    "wof:placetype":"venue"
},
  "geometry": {"coordinates":[4.4666471481,51.0419197083],"type":"Point"}
}