{
  "type": "Feature",
  "properties": {
    "addr:full":"Fonteinestraat 2 Lichtervelde West-Vlaanderen 8810",
    "addr:housenumber":"2",
    "addr:postcode":"8810",
    "addr:street":"Fonteinestraat",
    "iso:country":"BE",
    "sg:address":"Fonteinestraat 2",
    "sg:city":"Lichtervelde",
    "sg:classifiers":[
        {
            "category":"Real Estate",
            "subcategory":"Surveying",
            "type":"Services"
        }
    ],
    "sg:phone":"+32 51 72 52 73",
    "sg:postcode":"8810",
    "sg:province":"West-Vlaanderen",
    "sg:tags":[
        "surveyor",
        "land"
    ],
    "wof:name":"Eeckhout E",
    "wof:placetype":"venue"
},
  "geometry": {"coordinates":[3.1682019234,51.0137786865],"type":"Point"}
}