{
  "type": "Feature",
  "properties": {
    "addr:full":"Rue Saint-jacques 33 Tournai Hainaut 7500",
    "addr:housenumber":"33",
    "addr:postcode":"7500",
    "addr:street":"Rue Saint-Jacques",
    "iso:country":"BE",
    "sg:address":"Rue Saint-jacques 33",
    "sg:city":"Tournai",
    "sg:classifiers":[
        {
            "category":"Health Services",
            "subcategory":"Health Practitioner",
            "type":"Services"
        }
    ],
    "sg:phone":"+32 69 23 46 42",
    "sg:postcode":"7500",
    "sg:province":"Hainaut",
    "sg:tags":[
        "physiotherapist"
    ],
    "wof:name":"Piagnerelli Ga\u00ebtan",
    "wof:placetype":"venue"
},
  "geometry": {"coordinates":[3.3836479187,50.6096191406],"type":"Point"}
}