{
  "type": "Feature",
  "properties": {
    "iso:country":"BE",
    "sg:address":"Schauwbosweg 10",
    "sg:city":"Wuustwezel (loenhout)",
    "sg:classifiers":[
        {
            "category":"Farming",
            "subcategory":"Crops",
            "type":"Manufacturing & Wholesale Goods"
        }
    ],
    "sg:phone":"+32 3 669 94 92",
    "sg:postcode":"2990",
    "sg:province":"Antwerpen",
    "sg:tags":[
        "vegetable",
        "fruit",
        "-",
        "grower"
    ],
    "wof:name":"Vermeiren J",
    "wof:placetype":"venue"
},
  "geometry": {"coordinates":[4.6536631584,51.4161643982],"type":"Point"}
}