{
  "type": "Feature",
  "properties": {
    "iso:country":"BE",
    "sg:address":"Generaal De Wittestraat 13",
    "sg:city":"Halen",
    "sg:orig_category":"Apotheken",
    "sg:phone":"+32 13 44 11 09",
    "sg:postcode":"3545",
    "sg:province":"Limburg",
    "wof:name":"Apotheek Neven",
    "wof:placetype":"venue"
},
  "geometry": {"coordinates":[5.1125731468,50.9483413696],"type":"Point"}
}