{
  "type": "Feature",
  "properties": {
    "iso:country":"BE",
    "sg:address":"Rue De Bray 196",
    "sg:city":"La Louvi\u00e8re (maurage)",
    "sg:classifiers":[
        {
            "category":"Landmark",
            "subcategory":"City Walls",
            "type":"Public Place"
        }
    ],
    "sg:phone":"+32 64 67 87 49",
    "sg:postcode":"7110",
    "sg:province":"Hainaut",
    "sg:tags":[
        "covering"
    ],
    "wof:name":"De Nora M",
    "wof:placetype":"venue"
},
  "geometry": {"coordinates":[4.0995697975,50.4466590881],"type":"Point"}
}