{
  "type": "Feature",
  "properties": {
    "iso:country":"BE",
    "sg:address":"Oude Mechelsebaan 565",
    "sg:city":"Aarschot (langdorp)",
    "sg:classifiers":[
        {
            "category":"Shopping",
            "subcategory":"Pets & Pet Supplies",
            "type":"Retail Goods"
        }
    ],
    "sg:phone":"+32 16 56 72 47",
    "sg:postcode":"3201",
    "sg:province":"Vlaams-Brabant",
    "sg:tags":[
        "shop",
        "-"
    ],
    "wof:name":"Theys/r",
    "wof:placetype":"venue"
},
  "geometry": {"coordinates":[4.8970789909,51.0086212158],"type":"Point"}
}