{
  "type": "Feature",
  "properties": {
    "iso:country":"BE",
    "sg:address":"Z.a Rue Des Pieds D'alouette",
    "sg:city":"Namen",
    "sg:orig_category":"Jeux and jouets",
    "sg:phone":"+32 81 40 11 81",
    "sg:postcode":"5100",
    "sg:province":"Namur",
    "wof:name":"Broze Fils Jouets",
    "wof:placetype":"venue"
},
  "geometry": {"coordinates":[4.9245581627,50.4265937805],"type":"Point"}
}