{
  "type": "Feature",
  "properties": {
    "addr:full":"Appeldonkstraat 173b10 Willebroek Antwerpen 2830",
    "addr:housenumber":"173b10",
    "addr:postcode":"2830",
    "addr:street":"Appeldonkstraat",
    "iso:country":"BE",
    "sg:address":"Appeldonkstraat 173b10",
    "sg:city":"Willebroek",
    "sg:orig_category":"Mat\u00e9riaux de construction Gr",
    "sg:phone":"+32 3 866 17 17",
    "sg:postcode":"2830",
    "sg:province":"Antwerpen",
    "wof:name":"All Piping Services",
    "wof:placetype":"venue"
},
  "geometry": {"coordinates":[4.352722168,51.0705490112],"type":"Point"}
}