{
  "type": "Feature",
  "properties": {
    "addr:full":"Pachthoevestraat 12 Kraainem/kraainem Vlaams-Brabant 1950",
    "addr:housenumber":"12",
    "addr:postcode":"1950",
    "addr:street":"Pachthoevestraat",
    "iso:country":"BE",
    "sg:address":"Pachthoevestraat 12",
    "sg:city":"Kraainem/kraainem",
    "sg:orig_category":"Sportclubs",
    "sg:phone":"+32 2 731 45 62",
    "sg:postcode":"1950",
    "sg:province":"Vlaams-Brabant",
    "wof:name":"H.c. Avia",
    "wof:placetype":"venue"
},
  "geometry": {"coordinates":[4.4681639671,50.8392562866],"type":"Point"}
}