{
  "type": "Feature",
  "properties": {
    "iso:country":"BE",
    "sg:address":"Kapelsesteenweg 219",
    "sg:city":"Antwerpen (ekeren)",
    "sg:classifiers":[
        {
            "category":"Real Estate",
            "subcategory":"Surveying",
            "type":"Services"
        }
    ],
    "sg:phone":"+32 3 645 02 86",
    "sg:postcode":"2180",
    "sg:province":"Antwerpen",
    "sg:tags":[
        "surveyor",
        "land"
    ],
    "wof:name":"Laureyssens W",
    "wof:placetype":"venue"
},
  "geometry": {"coordinates":[4.4586000443,51.2716217041],"type":"Point"}
}