{
  "type": "Feature",
  "properties": {
    "iso:country":"BE",
    "sg:address":"Rue Joseph Dufrane 20",
    "sg:city":"Frameries",
    "sg:orig_category":"Peinture. Rev\u00eatements pour sols and murs",
    "sg:phone":"+32 65 67 47 30",
    "sg:postcode":"7080",
    "sg:province":"Hainaut",
    "wof:name":"Bertiaux J.c. & Fils",
    "wof:placetype":"venue"
},
  "geometry": {"coordinates":[3.8917410374,50.407497406],"type":"Point"}
}