{
  "type": "Feature",
  "properties": {
    "iso:country":"BE",
    "sg:address":"Cambeenbolsn 30c",
    "sg:city":"Brecht",
    "sg:orig_category":"Vakantiehuizen",
    "sg:phone":"+32 3 636 32 79",
    "sg:postcode":"2960",
    "sg:province":"Antwerpen",
    "wof:name":"Country Cottage Holidays",
    "wof:placetype":"venue"
},
  "geometry": {"coordinates":[4.6415200233,51.3512115479],"type":"Point"}
}