{
  "type": "Feature",
  "properties": {
    "addr:full":"Auguste Reyerslaan 108 Schaarbeek/schaerbeek Bruxelles-Capitale 1030",
    "addr:housenumber":"108",
    "addr:postcode":"1030",
    "addr:street":"Auguste Reyerslaan",
    "iso:country":"BE",
    "sg:address":"Auguste Reyerslaan 108",
    "sg:city":"Schaarbeek/schaerbeek",
    "sg:orig_category":"Marketingbureaus Marktonderzoekbureaus Reclamebureaus",
    "sg:phone":"+32 2 733 26 50",
    "sg:postcode":"1030",
    "sg:province":"Bruxelles-Capitale",
    "wof:name":"Irb Europe",
    "wof:placetype":"venue"
},
  "geometry": {"coordinates":[4.4032649994,50.8482971191],"type":"Point"}
}