{
  "type": "Feature",
  "properties": {
    "iso:country":"BE",
    "sg:address":"Route De Mellet 171",
    "sg:city":"Fleurus",
    "sg:orig_category":"Bouwmaterialen Gh Zand and grindontginning",
    "sg:phone":"+32 71 81 50 21",
    "sg:postcode":"6220",
    "sg:province":"Hainaut",
    "wof:name":"Barium Minerals Inc.",
    "wof:placetype":"venue"
},
  "geometry": {"coordinates":[4.5262122154,50.4876937866],"type":"Point"}
}