{
  "type": "Feature",
  "properties": {
    "iso:country":"BE",
    "sg:address":"E. Thieffrylaan 118",
    "sg:city":"Mortsel",
    "sg:orig_category":"Artsen and specialisten",
    "sg:phone":"+32 3 449 06 04",
    "sg:postcode":"2640",
    "sg:province":"Antwerpen",
    "wof:name":"Westerlinck",
    "wof:placetype":"venue"
},
  "geometry": {"coordinates":[4.4507918358,51.1663665771],"type":"Point"}
}