{
  "type": "Feature",
  "properties": {
    "addr:full":"Kerhoek 24 Zomergem Oost-Vlaanderen 9930",
    "addr:housenumber":"24",
    "addr:postcode":"9930",
    "addr:street":"Kerhoek",
    "iso:country":"BE",
    "sg:address":"Kerhoek 24",
    "sg:city":"Zomergem",
    "sg:orig_category":"V\u00e9t\u00e9rinaires",
    "sg:phone":"+32 9 372 03 34",
    "sg:postcode":"9930",
    "sg:province":"Oost-Vlaanderen",
    "wof:name":"Hans Nauwynck",
    "wof:placetype":"venue"
},
  "geometry": {"coordinates":[3.5828819275,51.1279678345],"type":"Point"}
}