{
  "type": "Feature",
  "properties": {
    "iso:country":"BE",
    "sg:address":"Parkietenlaan 3",
    "sg:city":"Kortrijk",
    "sg:orig_category":"Evaluation and estimation de biens immobiliers",
    "sg:phone":"+32 56 35 94 73",
    "sg:postcode":"8500",
    "sg:province":"West-Vlaanderen",
    "wof:name":"Jean-luc De Bruycker",
    "wof:placetype":"venue"
},
  "geometry": {"coordinates":[3.2714219093,50.8380126953],"type":"Point"}
}