{
  "type": "Feature",
  "properties": {
    "addr:full":"Grand-rue 92 Moeskroen/mouscron Hainaut 7700",
    "addr:housenumber":"92",
    "addr:postcode":"7700",
    "addr:street":"Grand-Rue",
    "iso:country":"BE",
    "sg:address":"Grand-rue 92",
    "sg:city":"Moeskroen/mouscron",
    "sg:orig_category":"Agences de voyages",
    "sg:phone":"+32 56 34 32 05",
    "sg:postcode":"7700",
    "sg:province":"Hainaut",
    "wof:name":"Drakkar Voyages",
    "wof:placetype":"venue"
},
  "geometry": {"coordinates":[3.2323200703,50.7400932312],"type":"Point"}
}