{
  "type": "Feature",
  "properties": {
    "iso:country":"BE",
    "sg:address":"Weg Naar Zwartberg 88ba",
    "sg:city":"Houthalen-helchteren",
    "sg:orig_category":"Alimentation sp\u00e9cialis\u00e9e. Epiceries",
    "sg:phone":"+32 89 38 62 00",
    "sg:postcode":"3530",
    "sg:province":"Limburg",
    "wof:name":"Mini-sconti-market",
    "wof:placetype":"venue"
},
  "geometry": {"coordinates":[5.4662008286,51.022277832],"type":"Point"}
}