{
  "type": "Feature",
  "properties": {
    "addr:full":"Rid. Walter Van Havreln 300 Schoten Antwerpen 2900",
    "addr:housenumber":"300",
    "addr:postcode":"2900",
    "iso:country":"BE",
    "sg:address":"Rid. Walter Van Havreln 300",
    "sg:city":"Schoten",
    "sg:orig_category":"Reliure and finition",
    "sg:phone":"+32 3 658 57 05",
    "sg:postcode":"2900",
    "sg:province":"Antwerpen",
    "wof:name":"Leo Desmaretz",
    "wof:placetype":"venue"
},
  "geometry": {"coordinates":[4.4864602089,51.2523765564],"type":"Point"}
}