{
  "type": "Feature",
  "properties": {
    "iso:country":"BE",
    "sg:address":"Rue De La Supinette 5",
    "sg:city":"Saint-hubert",
    "sg:orig_category":"Eleveurs de bovins",
    "sg:phone":"+32 61 61 18 74",
    "sg:postcode":"6870",
    "sg:province":"Luxembourg",
    "wof:name":"Andr\u00c9e Marchand",
    "wof:placetype":"venue"
},
  "geometry": {"coordinates":[5.3159499168,50.0326271057],"type":"Point"}
}