{
  "type": "Feature",
  "properties": {
    "addr:full":"Sint-petrus En Paulusstraat 14 Roeselare (rumbeke) West-Vlaanderen 8800",
    "addr:housenumber":"14",
    "addr:postcode":"8800",
    "addr:street":"Paulusstraat",
    "iso:country":"BE",
    "sg:address":"Sint-petrus En Paulusstraat 14",
    "sg:city":"Roeselare (rumbeke)",
    "sg:classifiers":[
        {
            "category":"Shopping",
            "subcategory":"Hobbies, Toys, & Games",
            "type":"Retail Goods"
        }
    ],
    "sg:phone":"+32 51 20 87 58",
    "sg:postcode":"8800",
    "sg:province":"West-Vlaanderen",
    "sg:tags":[
        "toy",
        "-"
    ],
    "wof:name":"Hollebol (de)",
    "wof:placetype":"venue"
},
  "geometry": {"coordinates":[3.1550281048,50.9343223572],"type":"Point"}
}