{
  "type": "Feature",
  "properties": {
    "iso:country":"BE",
    "sg:address":"Door Verstraetenplaats 4",
    "sg:city":"Antwerpen",
    "sg:orig_category":"Werk and personeelsselectie",
    "sg:phone":"+32 3 236 34 78",
    "sg:postcode":"2018",
    "sg:province":"Antwerpen",
    "wof:name":"Pwa Antwerpen",
    "wof:placetype":"venue"
},
  "geometry": {"coordinates":[4.4325289726,51.2079162598],"type":"Point"}
}