{
  "type": "Feature",
  "properties": {
    "iso:country":"BE",
    "sg:address":"Bergstraat 47",
    "sg:city":"Heist-op-den-berg",
    "sg:orig_category":"Diverse kredietdiensten",
    "sg:postcode":"2220",
    "sg:province":"Antwerpen",
    "wof:name":"Bancontact-mister Cash",
    "wof:placetype":"venue"
},
  "geometry": {"coordinates":[4.7233910561,51.0757293701],"type":"Point"}
}