{
  "type": "Feature",
  "properties": {
    "addr:full":"Mandekensstraat 206 Dendermonde Oost-Vlaanderen 9200",
    "addr:housenumber":"206",
    "addr:postcode":"9200",
    "addr:street":"Mandekensstraat;Oost-Vlaanderen",
    "iso:country":"BE",
    "sg:address":"Mandekensstraat 206",
    "sg:city":"Dendermonde",
    "sg:orig_category":"Travaux de pl\u00e2trage",
    "sg:phone":"+32 52 33 40 77",
    "sg:postcode":"9200",
    "sg:province":"Oost-Vlaanderen",
    "wof:name":"Vereeken Julien",
    "wof:placetype":"venue"
},
  "geometry": {"coordinates":[4.0983099937,51.0315208435],"type":"Point"}
}