{
  "type": "Feature",
  "properties": {
    "iso:country":"BE",
    "sg:address":"Eugeen De Grootelaan 60",
    "sg:city":"Houthulst",
    "sg:classifiers":[
        {
            "category":"Restaurant",
            "type":"Food & Drink"
        }
    ],
    "sg:phone":"+32 51 70 18 44",
    "sg:postcode":"8650",
    "sg:province":"West-Vlaanderen",
    "wof:name":"De Jachthoorn",
    "wof:placetype":"venue"
},
  "geometry": {"coordinates":[2.9558069706,50.9758682251],"type":"Point"}
}