{
  "type": "Feature",
  "properties": {
    "addr:full":"Rijsseveldstraat 59 Staden West-Vlaanderen 8840",
    "addr:housenumber":"59",
    "addr:postcode":"8840",
    "addr:street":"Rijsseveldstraat",
    "iso:country":"BE",
    "sg:address":"Rijsseveldstraat 59",
    "sg:city":"Staden",
    "sg:orig_category":"Plaatsen van vloer- and muurbekleding",
    "sg:phone":"+32 51 70 58 20",
    "sg:postcode":"8840",
    "sg:province":"West-Vlaanderen",
    "wof:name":"Ronny Bernaert",
    "wof:placetype":"venue"
},
  "geometry": {"coordinates":[3.0127930641,50.9751815796],"type":"Point"}
}