{
  "type": "Feature",
  "properties": {
    "iso:country":"BE",
    "sg:address":"Spoorwegstraat 35",
    "sg:city":"Landen",
    "sg:orig_category":"Kapsalons",
    "sg:phone":"+32 16 78 93 99",
    "sg:postcode":"3400",
    "sg:province":"Vlaams-Brabant",
    "wof:name":"Tania Allard",
    "wof:placetype":"venue"
},
  "geometry": {"coordinates":[5.0217871666,50.7645149231],"type":"Point"}
}