{
  "type": "Feature",
  "properties": {
    "addr:full":"Rue De La Houillere 74 Saint-nicolas Li\u00e8ge 4420",
    "addr:housenumber":"74",
    "addr:postcode":"4420",
    "addr:street":"Rue De La Houillere",
    "iso:country":"BE",
    "sg:address":"Rue De La Houillere 74",
    "sg:city":"Saint-nicolas",
    "sg:orig_category":"E-activit\u00e9s",
    "sg:phone":"+32 4 252 43 32",
    "sg:postcode":"4420",
    "sg:province":"Li\u00e8ge",
    "wof:name":"Natalis",
    "wof:placetype":"venue"
},
  "geometry": {"coordinates":[5.5433468819,50.6261672974],"type":"Point"}
}