{
  "type": "Feature",
  "properties": {
    "addr:full":"Rue Joseph Wettinck 65 Seraing (jemeppe-sur-meuse) Li\u00e8ge 4101",
    "addr:housenumber":"65",
    "addr:postcode":"4101",
    "addr:street":"Rue Joseph Wettinck;Jemeppe-Sur-Meuse",
    "iso:country":"BE",
    "sg:address":"Rue Joseph Wettinck 65",
    "sg:city":"Seraing (jemeppe-sur-meuse)",
    "sg:classifiers":[
        {
            "category":"Shopping",
            "subcategory":"Jewelry",
            "type":"Retail Goods"
        }
    ],
    "sg:phone":"+32 4 231 00 66",
    "sg:postcode":"4101",
    "sg:province":"Li\u00e8ge",
    "sg:tags":[
        "jeweller",
        "-"
    ],
    "wof:name":"Comptoir Luxembourgeois Des Metaux Precieux-dall'or",
    "wof:placetype":"venue"
},
  "geometry": {"coordinates":[5.5015058517,50.6148414612],"type":"Point"}
}