{
  "type": "Feature",
  "properties": {
    "addr:full":"Spurk 7b Bilzen Limburg 3740",
    "addr:housenumber":"7b",
    "addr:postcode":"3740",
    "addr:street":"Spurk",
    "iso:country":"BE",
    "sg:address":"Spurk 7b",
    "sg:city":"Bilzen",
    "sg:orig_category":"Maisons de vacances",
    "sg:phone":"+32 89 41 56 43",
    "sg:postcode":"3740",
    "sg:province":"Limburg",
    "wof:name":"Vanhees",
    "wof:placetype":"venue"
},
  "geometry": {"coordinates":[5.5041589737,50.8870849609],"type":"Point"}
}