{
  "type": "Feature",
  "properties": {
    "iso:country":"BE",
    "sg:address":"Aux Arches 194",
    "sg:city":"Andenne (coutisse)",
    "sg:classifiers":[
        {
            "category":"Building & Trades",
            "subcategory":"Construction",
            "type":"Services"
        }
    ],
    "sg:phone":"+32 85 61 30 04",
    "sg:postcode":"5300",
    "sg:province":"Namur",
    "sg:tags":[
        "carpenter"
    ],
    "wof:name":"Septon Menuiserie",
    "wof:placetype":"venue"
},
  "geometry": {"coordinates":[5.1522622108,50.46875],"type":"Point"}
}