{
  "type": "Feature",
  "properties": {
    "addr:full":"Rue Du March\u00e9 2 Fontaine-l'ev\u00eaque Hainaut 6140",
    "addr:housenumber":"2",
    "addr:postcode":"6140",
    "addr:street":"Rue Du Marche\u0301;\u0302Que Hainaut",
    "iso:country":"BE",
    "sg:address":"Rue Du March\u00e9 2",
    "sg:city":"Fontaine-l'ev\u00eaque",
    "sg:classifiers":[
        {
            "category":"Personal",
            "subcategory":"Barber",
            "type":"Services"
        }
    ],
    "sg:phone":"+32 71 52 60 27",
    "sg:postcode":"6140",
    "sg:province":"Hainaut",
    "sg:tags":[
        "gentleman",
        "salon",
        "-",
        "hairdressing"
    ],
    "wof:name":"Livio",
    "wof:placetype":"venue"
},
  "geometry": {"coordinates":[4.3241481781,50.4109153748],"type":"Point"}
}