{
  "type": "Feature",
  "properties": {
    "addr:full":"Rue De La Filature 4 Mons Hainaut 7034",
    "addr:housenumber":"4",
    "addr:postcode":"7034",
    "addr:street":"Rue De La Filature;Hainaut",
    "iso:country":"BE",
    "sg:address":"Rue De La Filature 4",
    "sg:city":"Mons",
    "sg:orig_category":"Zalen voor culturele evenementen",
    "sg:phone":"+32 65 72 30 02",
    "sg:postcode":"7034",
    "sg:province":"Hainaut",
    "wof:name":"Les Six Faux Nez",
    "wof:placetype":"venue"
},
  "geometry": {"coordinates":[4.0086159706,50.4765396118],"type":"Point"}
}