{
  "type": "Feature",
  "properties": {
    "iso:country":"BE",
    "sg:address":"Steenweg 63",
    "sg:city":"Heers",
    "sg:classifiers":[
        {
            "category":"Cafe",
            "type":"Food & Drink"
        }
    ],
    "sg:phone":"+32 11 48 40 60",
    "sg:postcode":"3870",
    "sg:province":"Limburg",
    "sg:tags":[
        "caf\u00e9s"
    ],
    "wof:name":"Vital Budo",
    "wof:placetype":"venue"
},
  "geometry": {"coordinates":[5.2802300453,50.7583084106],"type":"Point"}
}