{
  "type": "Feature",
  "properties": {
    "addr:full":"Bovenrij 57 Herentals Antwerpen 2200",
    "addr:housenumber":"57",
    "addr:postcode":"2200",
    "addr:street":"Bovenrij",
    "iso:country":"BE",
    "sg:address":"Bovenrij 57",
    "sg:city":"Herentals",
    "sg:orig_category":"Agences d\u00b4interim and personnel temporaire",
    "sg:phone":"+32 14 28 65 75",
    "sg:postcode":"2200",
    "sg:province":"Antwerpen",
    "wof:name":"View Interim",
    "wof:placetype":"venue"
},
  "geometry": {"coordinates":[4.8372120857,51.1750450134],"type":"Point"}
}