{
  "type": "Feature",
  "properties": {
    "iso:country":"BE",
    "sg:address":"Dorpsstraat 21",
    "sg:city":"Middelkerke",
    "sg:orig_category":"Etalage- and showroomontwerpers",
    "sg:phone":"+32 59 31 03 67",
    "sg:postcode":"8432",
    "sg:province":"West-Vlaanderen",
    "wof:name":"Etalages Fabienne",
    "wof:placetype":"venue"
},
  "geometry": {"coordinates":[2.8768401146,51.1755104065],"type":"Point"}
}