{
  "type": "Feature",
  "properties": {
    "addr:full":"Herenlaakweg 68 Maaseik Limburg 3680",
    "addr:housenumber":"68",
    "addr:postcode":"3680",
    "addr:street":"Herenlaakweg",
    "iso:country":"BE",
    "sg:address":"Herenlaakweg 68",
    "sg:city":"Maaseik",
    "sg:classifiers":[
        {
            "category":"Sports & Exercise",
            "subcategory":"Sports Center",
            "type":"Entertainment"
        }
    ],
    "sg:phone":"+32 89 56 77 61",
    "sg:postcode":"3680",
    "sg:province":"Limburg",
    "sg:tags":[
        "holiday",
        "language"
    ],
    "wof:name":"Sporta Beachclub",
    "wof:placetype":"venue"
},
  "geometry": {"coordinates":[5.8090701103,51.1017990112],"type":"Point"}
}