{
  "type": "Feature",
  "properties": {
    "iso:country":"BE",
    "sg:address":"Meersstraat 7",
    "sg:city":"Ingelmunster",
    "sg:orig_category":"Zuivelproducten",
    "sg:phone":"+32 51 48 89 73",
    "sg:postcode":"8770",
    "sg:province":"West-Vlaanderen",
    "wof:name":"Roger Libbrecht",
    "wof:placetype":"venue"
},
  "geometry": {"coordinates":[3.2526450157,50.9390258789],"type":"Point"}
}