{
  "type": "Feature",
  "properties": {
    "iso:country":"BE",
    "sg:address":"Victor Nelisstraat 14",
    "sg:city":"Schoten",
    "sg:orig_category":"Imprimeries and copyshops",
    "sg:phone":"+32 3 658 40 34",
    "sg:postcode":"2900",
    "sg:province":"Antwerpen",
    "wof:name":"Fa. Verberck-manderveld",
    "wof:placetype":"venue"
},
  "geometry": {"coordinates":[4.4819488525,51.2506065369],"type":"Point"}
}