{
  "type": "Feature",
  "properties": {
    "iso:country":"BE",
    "sg:address":"Neerstraat 25",
    "sg:city":"Wuustwezel",
    "sg:orig_category":"Rev\u00eatements pour sols and murs. Peinture",
    "sg:phone":"+32 3 669 52 84",
    "sg:postcode":"2990",
    "sg:province":"Antwerpen",
    "wof:name":"F. Paelinckx",
    "wof:placetype":"venue"
},
  "geometry": {"coordinates":[4.5807042122,51.3892402649],"type":"Point"}
}