{
  "type": "Feature",
  "properties": {
    "iso:country":"BE",
    "sg:address":"Grote Baan 73",
    "sg:city":"Beveren",
    "sg:orig_category":"Producteurs de fruits",
    "sg:phone":"+32 3 775 07 01",
    "sg:postcode":"9120",
    "sg:province":"Oost-Vlaanderen",
    "wof:name":"Francois Van Puymbroeck",
    "wof:placetype":"venue"
},
  "geometry": {"coordinates":[4.2992677689,51.2215118408],"type":"Point"}
}