{
  "type": "Feature",
  "properties": {
    "iso:country":"BE",
    "sg:address":"Rue Du Relais 3",
    "sg:city":"Somme-leuze",
    "sg:orig_category":"G\u00e9om\u00e8tres",
    "sg:phone":"+32 83 68 84 06",
    "sg:postcode":"5377",
    "sg:province":"Namur",
    "wof:name":"Denis Crucifix",
    "wof:placetype":"venue"
},
  "geometry": {"coordinates":[5.2471551895,50.2683448792],"type":"Point"}
}