{
  "type": "Feature",
  "properties": {
    "addr:full":"Chauss\u00c9e De Fleurus 36 Charleroi Hainaut 6041",
    "addr:housenumber":"36",
    "addr:postcode":"6041",
    "addr:street":"Chausse\u0301E De Fleurus;Hainaut",
    "iso:country":"BE",
    "sg:address":"Chauss\u00c9e De Fleurus 36",
    "sg:city":"Charleroi",
    "sg:orig_category":"Paramedische behandelingen",
    "sg:phone":"+32 71 34 23 99",
    "sg:postcode":"6041",
    "sg:province":"Hainaut",
    "wof:name":"S. Hiernaux",
    "wof:placetype":"venue"
},
  "geometry": {"coordinates":[4.4720478058,50.4434967041],"type":"Point"}
}