{
  "type": "Feature",
  "properties": {
    "addr:full":"Vijverstraat 17 Overpelt Limburg 3900",
    "addr:housenumber":"17",
    "addr:postcode":"3900",
    "addr:street":"Vijverstraat",
    "iso:country":"BE",
    "sg:address":"Vijverstraat 17",
    "sg:city":"Overpelt",
    "sg:orig_category":"Eleveurs de bovins",
    "sg:phone":"+32 11 64 47 42",
    "sg:postcode":"3900",
    "sg:province":"Limburg",
    "wof:name":"Henricus Janssen",
    "wof:placetype":"venue"
},
  "geometry": {"coordinates":[5.3757829666,51.1947212219],"type":"Point"}
}