{
  "type": "Feature",
  "properties": {
    "addr:full":"Kapelstraat 67 Bornem (groot) Antwerpen 2880",
    "addr:housenumber":"67",
    "addr:postcode":"2880",
    "addr:street":"Kapelstraat;Groot Antwerpen",
    "iso:country":"BE",
    "sg:address":"Kapelstraat 67",
    "sg:city":"Bornem (groot)",
    "sg:orig_category":"Textiel",
    "sg:phone":"+32 3 889 40 41",
    "sg:postcode":"2880",
    "sg:province":"Antwerpen",
    "wof:name":"Modestoffen Nicole",
    "wof:placetype":"venue"
},
  "geometry": {"coordinates":[4.2357392311,51.0968818665],"type":"Point"}
}