{
  "type": "Feature",
  "properties": {
    "addr:full":"Elzerijstraat 36 Moorslede West-Vlaanderen 8890",
    "addr:housenumber":"36",
    "addr:postcode":"8890",
    "addr:street":"Elzerijstraat",
    "iso:country":"BE",
    "sg:address":"Elzerijstraat 36",
    "sg:city":"Moorslede",
    "sg:orig_category":"Eleveurs de bovins",
    "sg:phone":"+32 51 77 84 84",
    "sg:postcode":"8890",
    "sg:province":"West-Vlaanderen",
    "wof:name":"Hugo Cappelle",
    "wof:placetype":"venue"
},
  "geometry": {"coordinates":[3.0575199127,50.9079055786],"type":"Point"}
}