{
  "type": "Feature",
  "properties": {
    "iso:country":"BE",
    "sg:address":"Wilgenlaan 40",
    "sg:city":"Stabroek",
    "sg:orig_category":"R\u00e9alisation de programmes and logiciels",
    "sg:phone":"+32 3 605 47 65",
    "sg:postcode":"2940",
    "sg:province":"Antwerpen",
    "wof:name":"M.e.s.",
    "wof:placetype":"venue"
},
  "geometry": {"coordinates":[4.3649148941,51.331943512],"type":"Point"}
}