{
  "type": "Feature",
  "properties": {
    "iso:country":"BE",
    "sg:address":"Rue Saint-bernard 70",
    "sg:city":"Sint-gillis/saint-gilles",
    "sg:orig_category":"M\u00e9decins and sp\u00e9cialistes",
    "sg:phone":"+32 2 537 50 07",
    "sg:postcode":"1060",
    "sg:province":"Bruxelles-Capitale",
    "wof:name":"Marguerite Wibo",
    "wof:placetype":"venue"
},
  "geometry": {"coordinates":[4.353495121,50.8281364441],"type":"Point"}
}