{
  "type": "Feature",
  "properties": {
    "iso:country":"BE",
    "sg:address":"Rue Sylvain Guyaux 5",
    "sg:city":"La Louvi\u00e8re",
    "sg:classifiers":[
        {
            "category":"Bars & Pubs",
            "type":"Food & Drink"
        }
    ],
    "sg:phone":"+32 64 22 36 28",
    "sg:postcode":"7100",
    "sg:province":"Hainaut",
    "wof:name":"Au Succ\u00e8s",
    "wof:placetype":"venue"
},
  "geometry": {"coordinates":[4.1867599487,50.4748306274],"type":"Point"}
}