{
  "type": "Feature",
  "properties": {
    "addr:full":"Clos Du Colbie 49 Braine L'alleud (braine-l'alleud) Brabant Wallon 1420",
    "addr:housenumber":"49",
    "addr:postcode":"1420",
    "addr:street":"Clos Du Colbie",
    "iso:country":"BE",
    "sg:address":"Clos Du Colbie 49",
    "sg:city":"Braine L'alleud (braine-l'alleud)",
    "sg:classifiers":[
        {
            "category":"Building & Trades",
            "subcategory":"Construction",
            "type":"Services"
        }
    ],
    "sg:phone":"+32 2 384 51 70",
    "sg:postcode":"1420",
    "sg:province":"Brabant Wallon",
    "sg:tags":[
        "carpenter"
    ],
    "wof:name":"I.d. Menuiserie Sprl",
    "wof:placetype":"venue"
},
  "geometry": {"coordinates":[-0.6790779829,47.3779411316],"type":"Point"}
}