{
  "type": "Feature",
  "properties": {
    "addr:full":"Kartuizersstraat 54 Oud-heverlee (blanden) Vlaams-Brabant 3052",
    "addr:housenumber":"54",
    "addr:postcode":"3052",
    "addr:street":"Kartuizersstraat",
    "iso:country":"BE",
    "sg:address":"Kartuizersstraat 54",
    "sg:city":"Oud-heverlee (blanden)",
    "sg:classifiers":[
        {
            "category":"Building & Trades",
            "subcategory":"Landscaping Services",
            "type":"Services"
        }
    ],
    "sg:phone":"+32 16 40 32 85",
    "sg:postcode":"3052",
    "sg:province":"Vlaams-Brabant",
    "sg:tags":[
        "gardening",
        "garden",
        "maintenance"
    ],
    "wof:name":"Plantoon Bvba",
    "wof:placetype":"venue"
},
  "geometry": {"coordinates":[4.7187299728,50.8247413635],"type":"Point"}
}