{
  "type": "Feature",
  "properties": {
    "iso:country":"BE",
    "sg:address":"6\u00e8me Avenue 57",
    "sg:city":"Charleroi (marcinelle)",
    "sg:classifiers":[
        {
            "category":"Government",
            "subcategory":"Embassy",
            "type":"Public Place"
        }
    ],
    "sg:phone":"+32 71 43 81 85",
    "sg:postcode":"6001",
    "sg:province":"Hainaut",
    "sg:tags":[
        "consulate"
    ],
    "wof:name":"Su\u00e8de (consulat)",
    "wof:placetype":"venue"
},
  "geometry": {"coordinates":[4.4408459663,50.3549804688],"type":"Point"}
}