{
  "type": "Feature",
  "properties": {
    "addr:full":"Ieperstraat 26 Menen West-Vlaanderen 8930",
    "addr:housenumber":"26",
    "addr:postcode":"8930",
    "addr:street":"Ieperstraat",
    "iso:country":"BE",
    "sg:address":"Ieperstraat 26",
    "sg:city":"Menen",
    "sg:classifiers":[
        {
            "category":"Health Services",
            "subcategory":"Doctor",
            "type":"Services"
        }
    ],
    "sg:phone":"+32 56 53 26 07",
    "sg:postcode":"8930",
    "sg:province":"West-Vlaanderen",
    "sg:tags":[
        "medicinephysicians",
        "surgeon"
    ],
    "wof:name":"Carron Kris",
    "wof:placetype":"venue"
},
  "geometry": {"coordinates":[3.117634058,50.7964134216],"type":"Point"}
}