{
  "type": "Feature",
  "properties": {
    "addr:full":"Gaverstraat 9 Oostrozebeke West-Vlaanderen 8780",
    "addr:housenumber":"9",
    "addr:postcode":"8780",
    "addr:street":"Gaverstraat",
    "iso:country":"BE",
    "sg:address":"Gaverstraat 9",
    "sg:city":"Oostrozebeke",
    "sg:orig_category":"Elektrische installaties voor woningen",
    "sg:phone":"+32 56 66 87 87",
    "sg:postcode":"8780",
    "sg:province":"West-Vlaanderen",
    "wof:name":"Wilfried Stevens",
    "wof:placetype":"venue"
},
  "geometry": {"coordinates":[3.344340086,50.9188995361],"type":"Point"}
}