{
  "type": "Feature",
  "properties": {
    "addr:full":"Mechelsesteenweg 34b2 Antwerpen Antwerpen 2018",
    "addr:housenumber":"34b2",
    "addr:postcode":"2018",
    "addr:street":"Mechelsesteenweg",
    "iso:country":"BE",
    "sg:address":"Mechelsesteenweg 34b2",
    "sg:city":"Antwerpen",
    "sg:orig_category":"Deurwaarders",
    "sg:phone":"+32 3 260 60 50",
    "sg:postcode":"2018",
    "sg:province":"Antwerpen",
    "wof:name":"Nico Bourdeaud\u00b4hui",
    "wof:placetype":"venue"
},
  "geometry": {"coordinates":[4.4077467918,51.2100524902],"type":"Point"}
}