{
  "type": "Feature",
  "properties": {
    "addr:full":"Heerbaan 15 Maaseik (neeroeteren) Limburg 3680",
    "addr:housenumber":"15",
    "addr:postcode":"3680",
    "addr:street":"Heerbaan",
    "iso:country":"BE",
    "sg:address":"Heerbaan 15",
    "sg:city":"Maaseik (neeroeteren)",
    "sg:classifiers":[
        {
            "category":"Health Services",
            "subcategory":"Health Practitioner",
            "type":"Services"
        }
    ],
    "sg:phone":"+32 89 86 39 10",
    "sg:postcode":"3680",
    "sg:province":"Limburg",
    "sg:tags":[
        "physiotherapist"
    ],
    "wof:name":"Martens A",
    "wof:placetype":"venue"
},
  "geometry": {"coordinates":[5.6972298622,51.0947799683],"type":"Point"}
}