{
  "type": "Feature",
  "properties": {
    "iso:country":"BE",
    "sg:address":"Brusselsesteenweg 310",
    "sg:city":"Hoeilaart",
    "sg:classifiers":[
        {
            "category":"Health Services",
            "subcategory":"Health Practitioner",
            "type":"Services"
        }
    ],
    "sg:phone":"+32 2 657 10 67",
    "sg:postcode":"1560",
    "sg:province":"Vlaams-Brabant",
    "sg:tags":[
        "therapist",
        "speech"
    ],
    "wof:name":"Van Laeken I",
    "wof:placetype":"venue"
},
  "geometry": {"coordinates":[4.4589600563,50.7772216797],"type":"Point"}
}