{
  "type": "Feature",
  "properties": {
    "addr:full":"Rue Brogniez 149 Anderlecht/anderlecht Bruxelles-Capitale 1070",
    "addr:housenumber":"149",
    "addr:postcode":"1070",
    "addr:street":"Rue Brogniez",
    "iso:country":"BE",
    "sg:address":"Rue Brogniez 149",
    "sg:city":"Anderlecht/anderlecht",
    "sg:orig_category":"Rev\u00eatements de sols and murs. Travaux de pl\u00e2trage",
    "sg:phone":"+32 2 524 31 93",
    "sg:postcode":"1070",
    "sg:province":"Bruxelles-Capitale",
    "wof:name":"Francesco Laera",
    "wof:placetype":"venue"
},
  "geometry": {"coordinates":[4.3324818611,50.8387336731],"type":"Point"}
}