{
  "type": "Feature",
  "properties": {
    "addr:full":"Koningin Astridlaan 15 Kuurne West-Vlaanderen 8520",
    "addr:housenumber":"15",
    "addr:postcode":"8520",
    "addr:street":"Koningin Astridlaan",
    "iso:country":"BE",
    "sg:address":"Koningin Astridlaan 15",
    "sg:city":"Kuurne",
    "sg:classifiers":[
        {
            "category":"Professional",
            "subcategory":"Art Services",
            "type":"Services"
        }
    ],
    "sg:phone":"+32 56 32 35 08",
    "sg:postcode":"8520",
    "sg:province":"West-Vlaanderen",
    "sg:tags":[
        "graphic",
        "designer"
    ],
    "wof:name":"Degrieck W",
    "wof:placetype":"venue"
},
  "geometry": {"coordinates":[3.2923219204,50.8555412292],"type":"Point"}
}