{
  "type": "Feature",
  "properties": {
    "iso:country":"BE",
    "sg:address":"Pagodenlaan 386",
    "sg:city":"Brussel/bruxelles",
    "sg:orig_category":"Fotografen and fotostudio's",
    "sg:phone":"+32 2 262 01 25",
    "sg:postcode":"1020",
    "sg:province":"Bruxelles-Capitale",
    "wof:name":"Jean-claude Toubeau",
    "wof:placetype":"venue"
},
  "geometry": {"coordinates":[4.3609528542,50.895690918],"type":"Point"}
}