{
  "type": "Feature",
  "properties": {
    "iso:country":"BE",
    "sg:address":"Rue De Magn\u00c9e 96",
    "sg:city":"Fleron",
    "sg:orig_category":"Equipement divers pour commerces Travaux de finition and nettoyage de b\u00e2timents. Produits chimiques ",
    "sg:phone":"+32 4 358 24 43",
    "sg:postcode":"4620",
    "sg:province":"Li\u00e8ge",
    "wof:name":"Lamy",
    "wof:placetype":"venue"
},
  "geometry": {"coordinates":[5.6776518822,50.6101112366],"type":"Point"}
}