{
  "type": "Feature",
  "properties": {
    "addr:full":"Place Emile-de-lalieux 16 Nivelles Brabant Wallon 1400",
    "addr:housenumber":"16",
    "addr:postcode":"1400",
    "addr:street":"Place Emile-De-Lalieux",
    "iso:country":"BE",
    "sg:address":"Place Emile-de-lalieux 16",
    "sg:city":"Nivelles",
    "sg:orig_category":"Kansspelen",
    "sg:phone":"+32 67 21 58 17",
    "sg:postcode":"1400",
    "sg:province":"Brabant Wallon",
    "wof:name":"Ladbroke",
    "wof:placetype":"venue"
},
  "geometry": {"coordinates":[4.3281698227,50.5981674194],"type":"Point"}
}