{
  "type": "Feature",
  "properties": {
    "addr:full":"Westlaan 466 Box 3 Roeselare West-Vlaanderen 8800",
    "addr:housenumber":"466;3",
    "addr:postcode":"8800",
    "addr:street":"Westlaan;Box",
    "iso:country":"BE",
    "sg:address":"Westlaan 466 Box 3",
    "sg:city":"Roeselare",
    "sg:classifiers":[
        {
            "category":"Utilities",
            "subcategory":"Telephone",
            "type":"Services"
        }
    ],
    "sg:phone":"+32 51 21 25 21",
    "sg:postcode":"8800",
    "sg:province":"West-Vlaanderen",
    "sg:tags":[
        "-",
        "internet"
    ],
    "wof:name":"Serve-it Bvba",
    "wof:placetype":"venue"
},
  "geometry": {"coordinates":[3.1123468876,50.9514312744],"type":"Point"}
}