{
  "type": "Feature",
  "properties": {
    "addr:full":"Tieltsesteenweg 57 Eeklo Oost-Vlaanderen 9900",
    "addr:housenumber":"57",
    "addr:postcode":"9900",
    "addr:street":"Tieltsesteenweg",
    "iso:country":"BE",
    "sg:address":"Tieltsesteenweg 57",
    "sg:city":"Eeklo",
    "sg:classifiers":[
        {
            "category":"Retail",
            "subcategory":"Veterinary Services",
            "type":"Services"
        }
    ],
    "sg:phone":"+32 9 377 18 78",
    "sg:postcode":"9900",
    "sg:province":"Oost-Vlaanderen",
    "sg:tags":[
        "veterinarian"
    ],
    "wof:name":"Van Den Braembussche C",
    "wof:placetype":"venue"
},
  "geometry": {"coordinates":[3.5559680462,51.1839447021],"type":"Point"}
}