{
  "type": "Feature",
  "properties": {
    "addr:full":"Rue Paul-henri Spaak 5b P\u00e9ruwelz (wiers) Hainaut 7608",
    "addr:housenumber":"5b",
    "addr:postcode":"7608",
    "addr:street":"Rue Paul-Henri Spaak",
    "iso:country":"BE",
    "sg:address":"Rue Paul-henri Spaak 5b",
    "sg:city":"P\u00e9ruwelz (wiers)",
    "sg:classifiers":[
        {
            "category":"Health Services",
            "subcategory":"Doctor",
            "type":"Services"
        }
    ],
    "sg:phone":"+32 69 77 40 09",
    "sg:postcode":"7608",
    "sg:province":"Hainaut",
    "sg:tags":[
        "medicinephysicians",
        "surgeon"
    ],
    "wof:name":"Dervaux Carine",
    "wof:placetype":"venue"
},
  "geometry": {"coordinates":[3.5358130932,50.5055732727],"type":"Point"}
}