{
  "type": "Feature",
  "properties": {
    "iso:country":"BE",
    "sg:address":"Kleine Laan 8",
    "sg:city":"Sint-niklaas",
    "sg:classifiers":[
        {
            "category":"Home & Garden",
            "subcategory":"Household Appliances",
            "type":"Retail Goods"
        }
    ],
    "sg:phone":"+32 3 776 56 85",
    "sg:postcode":"9100",
    "sg:province":"Oost-Vlaanderen",
    "sg:tags":[
        "repair",
        "mainten",
        "-",
        "electric"
    ],
    "wof:name":"Mariman Piet-miele",
    "wof:placetype":"venue"
},
  "geometry": {"coordinates":[4.1397490501,51.1697349548],"type":"Point"}
}