{
  "type": "Feature",
  "properties": {
    "iso:country":"BE",
    "sg:address":"Grote Bameriklaan 71",
    "sg:city":"Hasselt",
    "sg:orig_category":"Diverse bouwafwerking and reiniging",
    "sg:phone":"+32 11 25 44 44",
    "sg:postcode":"3511",
    "sg:province":"Limburg",
    "wof:name":"Josef Vaesen",
    "wof:placetype":"venue"
},
  "geometry": {"coordinates":[5.2974061966,50.9495048523],"type":"Point"}
}