{
  "type": "Feature",
  "properties": {
    "iso:country":"BE",
    "sg:address":"Tongersteenweg 27",
    "sg:city":"Riemst",
    "sg:orig_category":"HERSTELLING ELEKTRISCHE HUISHOUDAPPARATEN Huishoudapparaten, televisies and radio's Telecommunicatie",
    "sg:phone":"+32 12 45 68 68",
    "sg:postcode":"3770",
    "sg:province":"Limburg",
    "wof:name":"Coswi",
    "wof:placetype":"venue"
},
  "geometry": {"coordinates":[5.5921330452,50.810459137],"type":"Point"}
}