{
  "type": "Feature",
  "properties": {
    "iso:country":"BE",
    "sg:address":"Stormestraat 76",
    "sg:city":"Waregem",
    "sg:orig_category":"Baby- and kinderkleding",
    "sg:phone":"+32 56 61 69 20",
    "sg:postcode":"8790",
    "sg:province":"West-Vlaanderen",
    "wof:name":"Knabbel & Babbel",
    "wof:placetype":"venue"
},
  "geometry": {"coordinates":[3.4296851158,50.8861122131],"type":"Point"}
}