{
  "type": "Feature",
  "properties": {
    "iso:country":"BE",
    "sg:address":"Belgi\u00cblei 184",
    "sg:city":"Antwerpen",
    "sg:orig_category":"Administration d'immeubles",
    "sg:phone":"+32 3 230 52 37",
    "sg:postcode":"2018",
    "sg:province":"Antwerpen",
    "wof:name":"Ringer",
    "wof:placetype":"venue"
},
  "geometry": {"coordinates":[4.4135489464,51.2029685974],"type":"Point"}
}