{
  "type": "Feature",
  "properties": {
    "addr:full":"Rue Sainte-barbe 5 Rendeux Luxembourg 6987",
    "addr:housenumber":"5",
    "addr:postcode":"6987",
    "addr:street":"Rue Sainte-Barbe",
    "iso:country":"BE",
    "sg:address":"Rue Sainte-barbe 5",
    "sg:city":"Rendeux",
    "sg:orig_category":"Eleveurs de bovins",
    "sg:phone":"+32 84 47 76 48",
    "sg:postcode":"6987",
    "sg:province":"Luxembourg",
    "wof:name":"Louis Delcourt",
    "wof:placetype":"venue"
},
  "geometry": {"coordinates":[5.5485100746,50.2155570984],"type":"Point"}
}