{
  "type": "Feature",
  "properties": {
    "addr:full":"Industrielaan 4 Maasmechelen Limburg 3630",
    "addr:housenumber":"4",
    "addr:postcode":"3630",
    "addr:street":"Industrielaan",
    "iso:country":"BE",
    "sg:address":"Industrielaan 4",
    "sg:city":"Maasmechelen",
    "sg:orig_category":"Supermarch\u00e9s",
    "sg:postcode":"3630",
    "sg:province":"Limburg",
    "wof:name":"Aldi",
    "wof:placetype":"venue"
},
  "geometry": {"coordinates":[5.6956110001,50.9559020996],"type":"Point"}
}