{
  "type": "Feature",
  "properties": {
    "iso:country":"BE",
    "sg:address":"Parc Industriel 5",
    "sg:city":"Espierres-helchin (espierres)",
    "sg:orig_category":"Non-Classified Establishments",
    "sg:phone":"+32 56 46 11 11",
    "sg:postcode":"8587",
    "sg:province":"West-Vlaanderen",
    "wof:name":"Vincent Sheppard Nv",
    "wof:placetype":"venue"
},
  "geometry": {"coordinates":[3.3284161091,50.7230606079],"type":"Point"}
}