{
  "type": "Feature",
  "properties": {
    "addr:full":"Paddegatstraat 100 Kapelle-op-den-bos Vlaams-Brabant 1880",
    "addr:housenumber":"100",
    "addr:postcode":"1880",
    "addr:street":"Paddegatstraat",
    "iso:country":"BE",
    "sg:address":"Paddegatstraat 100",
    "sg:city":"Kapelle-op-den-bos",
    "sg:classifiers":[
        {
            "category":"Insurance",
            "subcategory":"Life Insurance",
            "type":"Services"
        }
    ],
    "sg:phone":"+32 15 71 18 14",
    "sg:postcode":"1880",
    "sg:province":"Vlaams-Brabant",
    "sg:tags":[
        "assurance"
    ],
    "wof:name":"Van Buggenhout",
    "wof:placetype":"venue"
},
  "geometry": {"coordinates":[4.3505630493,50.9800605774],"type":"Point"}
}