{
  "type": "Feature",
  "properties": {
    "iso:country":"BE",
    "sg:address":"Spoorwegstraat 17b1",
    "sg:city":"Tessenderlo",
    "sg:orig_category":"Dakwerken Diverse bouwafwerking and reiniging Gespecialiseerde residenti\u00eble bouw Woningbouw",
    "sg:phone":"+32 13 67 55 04",
    "sg:postcode":"3980",
    "sg:province":"Limburg",
    "wof:name":"Al Boreno",
    "wof:placetype":"venue"
},
  "geometry": {"coordinates":[5.1014289856,51.0688552856],"type":"Point"}
}