{
  "type": "Feature",
  "properties": {
    "addr:full":"Rue Harenheyde 7 Brussel/bruxelles Bruxelles-Capitale 1130",
    "addr:housenumber":"7",
    "addr:postcode":"1130",
    "addr:street":"Rue Harenheyde;/",
    "iso:country":"BE",
    "sg:address":"Rue Harenheyde 7",
    "sg:city":"Brussel/bruxelles",
    "sg:orig_category":"Banques and organismes de cr\u00e9dit",
    "sg:phone":"+32 2 242 03 38",
    "sg:postcode":"1130",
    "sg:province":"Bruxelles-Capitale",
    "wof:name":"Fortis",
    "wof:placetype":"venue"
},
  "geometry": {"coordinates":[4.4189109802,50.8918228149],"type":"Point"}
}