{
  "type": "Feature",
  "properties": {
    "iso:country":"BE",
    "sg:address":"All\u00c9e Du Bois De Bassin 15",
    "sg:city":"Havelange",
    "sg:orig_category":"Paramedische behandelingen",
    "sg:phone":"+32 83 63 47 99",
    "sg:postcode":"5370",
    "sg:province":"Namur",
    "wof:name":"S. Marot",
    "wof:placetype":"venue"
},
  "geometry": {"coordinates":[5.2487740517,50.3980445862],"type":"Point"}
}