{
  "type": "Feature",
  "properties": {
    "iso:country":"BE",
    "sg:address":"Neervelpsestraat 34",
    "sg:city":"Bierbeek",
    "sg:orig_category":"Voertuigen",
    "sg:phone":"+32 16 46 14 79",
    "sg:postcode":"3360",
    "sg:province":"Vlaams-Brabant",
    "wof:name":"Christiaan Arnauts",
    "wof:placetype":"venue"
},
  "geometry": {"coordinates":[4.780807972,50.8263435364],"type":"Point"}
}