{
  "type": "Feature",
  "properties": {
    "addr:full":"Rue Darwin 48 Bruxelles (ixelles) Bruxelles-Capitale 1050",
    "addr:housenumber":"48",
    "addr:postcode":"1050",
    "addr:street":"Rue Darwin",
    "iso:country":"BE",
    "sg:address":"Rue Darwin 48",
    "sg:city":"Bruxelles (ixelles)",
    "sg:classifiers":[
        {
            "category":"Health Services",
            "subcategory":"Doctor",
            "type":"Services"
        }
    ],
    "sg:phone":"+32 2 347 36 37",
    "sg:postcode":"1050",
    "sg:province":"Bruxelles-Capitale",
    "sg:tags":[
        "medicinephysicians",
        "surgeon"
    ],
    "wof:name":"Lhonneux C",
    "wof:placetype":"venue"
},
  "geometry": {"coordinates":[4.3534798622,50.8178939819],"type":"Point"}
}