{
  "type": "Feature",
  "properties": {
    "addr:full":"Dulle Grietlaan 17/3 Gentbrugge 9050",
    "addr:housenumber":"17 / 3",
    "addr:postcode":"9050",
    "addr:street":"Grietlaan",
    "iso:country":"BE",
    "sg:address":"Dulle Grietlaan 17/3",
    "sg:city":"Gentbrugge",
    "sg:classifiers":[
        {
            "category":"Manufacturing",
            "subcategory":"Electronics",
            "type":"Manufacturing & Wholesale Goods"
        }
    ],
    "sg:postcode":"9050",
    "sg:website":"http://www.trinean.com",
    "wof:name":"Trinean",
    "wof:placetype":"venue"
},
  "geometry": {"coordinates":[3.7500072,51.0459353],"type":"Point"}
}