{
  "type": "Feature",
  "properties": {
    "addr:full":"Avenue De L\u00b4echevinage 20 Ukkel/uccle Bruxelles-Capitale 1180",
    "addr:housenumber":"20",
    "addr:postcode":"1180",
    "addr:street":"Avenue De L\u00b4Echevinage;/",
    "iso:country":"BE",
    "sg:address":"Avenue De L\u00b4echevinage 20",
    "sg:city":"Ukkel/uccle",
    "sg:orig_category":"M\u00e9decins and sp\u00e9cialistes",
    "sg:phone":"+32 2 375 04 80",
    "sg:postcode":"1180",
    "sg:province":"Bruxelles-Capitale",
    "wof:name":"L. Cock",
    "wof:placetype":"venue"
},
  "geometry": {"coordinates":[4.3437538147,50.8041610718],"type":"Point"}
}