{
  "type": "Feature",
  "properties": {
    "iso:country":"BE",
    "sg:address":"Grand-rue 2b14",
    "sg:city":"Ottignies-louvain-la-neuve",
    "sg:orig_category":"Imprimeries and copyshops. Fournitures de bureau",
    "sg:phone":"+32 10 45 18 41",
    "sg:postcode":"1348",
    "sg:province":"Brabant Wallon",
    "wof:name":"Ciaco Papeterie",
    "wof:placetype":"venue"
},
  "geometry": {"coordinates":[4.567553997,50.6661262512],"type":"Point"}
}