{
  "type": "Feature",
  "properties": {
    "iso:country":"BE",
    "sg:address":"Diestersebaan 78",
    "sg:city":"Hechtel-eksel (eksel)",
    "sg:classifiers":[
        {
            "category":"Personal",
            "subcategory":"Beauty Salon",
            "type":"Services"
        }
    ],
    "sg:phone":"+32 11 73 27 00",
    "sg:postcode":"3941",
    "sg:province":"Limburg",
    "sg:tags":[
        "lady",
        "-",
        "hairdressing"
    ],
    "wof:name":"Jos\u00e9e",
    "wof:placetype":"venue"
},
  "geometry": {"coordinates":[5.3944358826,51.1637382507],"type":"Point"}
}