{
  "type": "Feature",
  "properties": {
    "addr:full":"J.b. Now\u00c9lei 45 Vilvoorde Vlaams-Brabant 1800",
    "addr:housenumber":"45",
    "addr:postcode":"1800",
    "iso:country":"BE",
    "sg:address":"J.b. Now\u00c9lei 45",
    "sg:city":"Vilvoorde",
    "sg:orig_category":"Editeurs de journaux. Editeurs de revues and p\u00e9riodiques",
    "sg:phone":"+32 2 257 87 11",
    "sg:postcode":"1800",
    "sg:province":"Vlaams-Brabant",
    "wof:name":"De Streekkrant",
    "wof:placetype":"venue"
},
  "geometry": {"coordinates":[4.4258608818,50.9269294739],"type":"Point"}
}