{
  "type": "Feature",
  "properties": {
    "addr:full":"Gaardeniersweg 77b14 Gent Oost-Vlaanderen 9000",
    "addr:housenumber":"77b14",
    "addr:postcode":"9000",
    "addr:street":"Gaardeniersweg;Oost-Vlaanderen",
    "iso:country":"BE",
    "sg:address":"Gaardeniersweg 77b14",
    "sg:city":"Gent",
    "sg:orig_category":"Metaalbehandeling and -bekleding",
    "sg:phone":"+32 9 227 44 94",
    "sg:postcode":"9000",
    "sg:province":"Oost-Vlaanderen",
    "wof:name":"Efk Products",
    "wof:placetype":"venue"
},
  "geometry": {"coordinates":[3.7164700031,51.0700187683],"type":"Point"}
}