{
  "type": "Feature",
  "properties": {
    "iso:country":"BE",
    "sg:address":"Rue Des D\u00c9port\u00c9s 25",
    "sg:city":"Tubize",
    "sg:classifiers":[
        {
            "category":"Cafe",
            "type":"Food & Drink"
        }
    ],
    "sg:phone":"+32 2 355 29 56",
    "sg:postcode":"1480",
    "sg:province":"Brabant Wallon",
    "sg:tags":[
        "caf\u00e9s"
    ],
    "wof:name":"Malika El Khattabi",
    "wof:placetype":"venue"
},
  "geometry": {"coordinates":[4.2219867706,50.6911392212],"type":"Point"}
}