{
  "type": "Feature",
  "properties": {
    "addr:full":"Chauss\u00c9e De Lille 30 Tournai Hainaut 7500",
    "addr:housenumber":"30",
    "addr:postcode":"7500",
    "addr:street":"Chausse\u0301E De Lille",
    "iso:country":"BE",
    "sg:address":"Chauss\u00c9e De Lille 30",
    "sg:city":"Tournai",
    "sg:orig_category":"M\u00e9decins and sp\u00e9cialistes",
    "sg:phone":"+32 69 22 14 16",
    "sg:postcode":"7500",
    "sg:province":"Hainaut",
    "wof:name":"Roger Fievet",
    "wof:placetype":"venue"
},
  "geometry": {"coordinates":[3.3729219437,50.6047477722],"type":"Point"}
}