{
  "type": "Feature",
  "properties": {
    "addr:full":"Zwijnaardsesteenweg 664 Gent Oost-Vlaanderen 9000",
    "addr:housenumber":"664",
    "addr:postcode":"9000",
    "addr:street":"Zwijnaardsesteenweg;Oost-Vlaanderen",
    "iso:country":"BE",
    "sg:address":"Zwijnaardsesteenweg 664",
    "sg:city":"Gent",
    "sg:classifiers":[
        {
            "category":"Fast Food",
            "type":"Food & Drink"
        }
    ],
    "sg:phone":"+32 9 221 16 60",
    "sg:postcode":"9000",
    "sg:province":"Oost-Vlaanderen",
    "sg:tags":[
        "meeneem",
        "restaurant"
    ],
    "wof:name":"Frituur Freddy",
    "wof:placetype":"venue"
},
  "geometry": {"coordinates":[3.7202370167,51.0223731995],"type":"Point"}
}