{
  "type": "Feature",
  "properties": {
    "addr:full":"Rue D'insevaux 102 Namur Namur 5020",
    "addr:housenumber":"102",
    "addr:postcode":"5020",
    "addr:street":"Rue D'Insevaux",
    "iso:country":"BE",
    "sg:address":"Rue D'insevaux 102",
    "sg:city":"Namur",
    "sg:orig_category":"Pharmaciens",
    "sg:phone":"+32 81 44 41 71",
    "sg:postcode":"5020",
    "sg:province":"Namur",
    "wof:name":"Pharmacie Lastelle",
    "wof:placetype":"venue"
},
  "geometry": {"coordinates":[4.8753781319,50.5016975403],"type":"Point"}
}