{
  "type": "Feature",
  "properties": {
    "iso:country":"BE",
    "sg:address":"Rue De Villers-en-fagne 2",
    "sg:city":"Philippeville",
    "sg:orig_category":"Installatie van houten of kunststof schrijnwerk",
    "sg:phone":"+32 71 66 78 38",
    "sg:postcode":"5600",
    "sg:province":"Namur",
    "wof:name":"Andre Martinet",
    "wof:placetype":"venue"
},
  "geometry": {"coordinates":[4.6181588173,50.1542167664],"type":"Point"}
}