{
  "type": "Feature",
  "properties": {
    "iso:country":"BE",
    "sg:address":"Chauss\u00c9e De Tournai 16",
    "sg:city":"Leuze-en-hainaut",
    "sg:orig_category":"Entretien and r\u00e9parations de voitures. V\u00e9hicules automobiles",
    "sg:phone":"+32 69 66 12 09",
    "sg:postcode":"7904",
    "sg:province":"Hainaut",
    "wof:name":"Garage Merlot",
    "wof:placetype":"venue"
},
  "geometry": {"coordinates":[3.5772058964,50.5929946899],"type":"Point"}
}