{
  "type": "Feature",
  "properties": {
    "iso:country":"BE",
    "sg:address":"Kerkstraat 2",
    "sg:city":"Puurs",
    "sg:classifiers":[
        {
            "category":"Bars & Pubs",
            "type":"Food & Drink"
        }
    ],
    "sg:phone":"+32 3 886 25 55",
    "sg:postcode":"2870",
    "sg:province":"Antwerpen",
    "wof:name":"Vliet (de)",
    "wof:placetype":"venue"
},
  "geometry": {"coordinates":[4.3289709091,51.0868034363],"type":"Point"}
}