{
  "type": "Feature",
  "properties": {
    "addr:full":"Vijversstraat 1 Hasselt Limburg 3500",
    "addr:housenumber":"1",
    "addr:postcode":"3500",
    "addr:street":"Vijversstraat",
    "iso:country":"BE",
    "sg:address":"Vijversstraat 1",
    "sg:city":"Hasselt",
    "sg:classifiers":[
        {
            "category":"Food & Beverages",
            "subcategory":"Groceries & Convenience Stores",
            "type":"Retail Goods"
        }
    ],
    "sg:phone":"+32 11 87 44 77",
    "sg:postcode":"3500",
    "sg:province":"Limburg",
    "sg:tags":[
        "grocer"
    ],
    "wof:name":"Domus Mea",
    "wof:placetype":"venue"
},
  "geometry": {"coordinates":[5.354403019,50.9635124207],"type":"Point"}
}