{
  "type": "Feature",
  "properties": {
    "addr:full":"Rue De La Neuville 103 Seraing Li\u00e8ge 4100",
    "addr:housenumber":"103",
    "addr:postcode":"4100",
    "addr:street":"Rue De La Neuville",
    "iso:country":"BE",
    "sg:address":"Rue De La Neuville 103",
    "sg:city":"Seraing",
    "sg:classifiers":[
        {
            "category":"Building & Trades",
            "subcategory":"Construction",
            "type":"Services"
        }
    ],
    "sg:phone":"+32 4 336 68 47",
    "sg:postcode":"4100",
    "sg:province":"Li\u00e8ge",
    "sg:tags":[
        "installation",
        "-",
        "central",
        "heating"
    ],
    "wof:name":"Kittel J-m",
    "wof:placetype":"venue"
},
  "geometry": {"coordinates":[5.501226902,50.5848464966],"type":"Point"}
}