{
  "type": "Feature",
  "properties": {
    "addr:full":"Generaal Eenensstraat 32 Schaarbeek/schaerbeek Bruxelles-Capitale 1030",
    "addr:housenumber":"32",
    "addr:postcode":"1030",
    "addr:street":"Generaal Eenensstraat",
    "iso:country":"BE",
    "sg:address":"Generaal Eenensstraat 32",
    "sg:city":"Schaarbeek/schaerbeek",
    "sg:orig_category":"Telecommunicatiesystemen",
    "sg:phone":"+32 2 241 25 94",
    "sg:postcode":"1030",
    "sg:province":"Bruxelles-Capitale",
    "wof:name":"Espace Phone",
    "wof:placetype":"venue"
},
  "geometry": {"coordinates":[4.3757119179,50.868347168],"type":"Point"}
}