{
  "type": "Feature",
  "properties": {
    "addr:full":"Kursaal Westhelling 5 Oostende West-Vlaanderen 8400",
    "addr:housenumber":"5",
    "addr:postcode":"8400",
    "iso:country":"BE",
    "sg:address":"Kursaal Westhelling 5",
    "sg:city":"Oostende",
    "sg:orig_category":"Centres de relaxation and bien-\u00eatre. Salles de conf\u00e9rences and de r\u00e9ceptions. Restaurants. H\u00f4tels",
    "sg:phone":"+32 59 80 66 11",
    "sg:postcode":"8400",
    "sg:province":"West-Vlaanderen",
    "wof:name":"Gloria",
    "wof:placetype":"venue"
},
  "geometry": {"coordinates":[2.9115788937,51.2311592102],"type":"Point"}
}