{
  "type": "Feature",
  "properties": {
    "iso:country":"BE",
    "sg:address":"Herdebeekstraat 42",
    "sg:city":"Dilbeek (itterbeek)",
    "sg:classifiers":[
        {
            "category":"Real Estate",
            "subcategory":"Architect",
            "type":"Services"
        }
    ],
    "sg:phone":"+32 2 569 69 10",
    "sg:postcode":"1701",
    "sg:province":"Vlaams-Brabant",
    "wof:name":"Lemaire E",
    "wof:placetype":"venue"
},
  "geometry": {"coordinates":[4.2290282249,50.8380050659],"type":"Point"}
}