{
  "type": "Feature",
  "properties": {
    "iso:country":"BE",
    "sg:address":"Lieven Bauwensstraat 25a",
    "sg:city":"Brugge (sint-andries)",
    "sg:classifiers":[
        {
            "category":"Communications",
            "subcategory":"Radio Station",
            "type":"Services"
        }
    ],
    "sg:phone":"+32 50 32 06 11",
    "sg:postcode":"8200",
    "sg:province":"West-Vlaanderen",
    "sg:tags":[
        "transmission"
    ],
    "wof:name":"Procotec Bvba",
    "wof:placetype":"venue"
},
  "geometry": {"coordinates":[3.1954209805,51.2134895325],"type":"Point"}
}