{
  "type": "Feature",
  "properties": {
    "iso:country":"BE",
    "sg:address":"Weg Nr. Helchteren 61",
    "sg:city":"Meeuwen-gruitrode (meeuwen)",
    "sg:classifiers":[
        {
            "category":"Fast Food",
            "type":"Food & Drink"
        }
    ],
    "sg:phone":"+32 11 79 19 89",
    "sg:postcode":"3670",
    "sg:province":"Limburg",
    "sg:tags":[
        "fried",
        "stand",
        "potato"
    ],
    "wof:name":"Meeuw (de)",
    "wof:placetype":"venue"
},
  "geometry": {"coordinates":[5.5059528351,51.0951766968],"type":"Point"}
}