{
  "type": "Feature",
  "properties": {
    "addr:full":"Molenhoekstraat 3 Zonnebeke West-Vlaanderen 8980",
    "addr:housenumber":"3",
    "addr:postcode":"8980",
    "addr:street":"Molenhoekstraat",
    "iso:country":"BE",
    "sg:address":"Molenhoekstraat 3",
    "sg:city":"Zonnebeke",
    "sg:orig_category":"Belastingconsulenten Diverse juridische dienstverlening",
    "sg:phone":"+32 57 46 74 00",
    "sg:postcode":"8980",
    "sg:province":"West-Vlaanderen",
    "wof:name":"Frank De Ruddere",
    "wof:placetype":"venue"
},
  "geometry": {"coordinates":[2.9872550964,50.8730812073],"type":"Point"}
}