{
  "type": "Feature",
  "properties": {
    "addr:full":"Schoorstr 38 Heist-op-den-berg Antwerpen 2220",
    "addr:housenumber":"38",
    "addr:postcode":"2220",
    "addr:street":"Schoorstr",
    "iso:country":"BE",
    "sg:address":"Schoorstr 38",
    "sg:city":"Heist-op-den-berg",
    "sg:classifiers":[
        {
            "category":"Professional",
            "type":"Services"
        }
    ],
    "sg:phone":"+32 15 25 71 90",
    "sg:postcode":"2220",
    "sg:province":"Antwerpen",
    "sg:tags":[
        "transport",
        "road"
    ],
    "wof:name":"Van Egdom - Mari\u00cbn Nv",
    "wof:placetype":"venue"
},
  "geometry": {"coordinates":[4.7139787674,51.0589103699],"type":"Point"}
}