{
  "type": "Feature",
  "properties": {
    "iso:country":"BE",
    "sg:address":"Leiestraat 44",
    "sg:city":"Kortrijk",
    "sg:orig_category":"V\u00eatements de mariage and c\u00e9r\u00e9monies",
    "sg:phone":"+32 56 21 92 46",
    "sg:postcode":"8500",
    "sg:province":"West-Vlaanderen",
    "wof:name":"Bo Couture",
    "wof:placetype":"venue"
},
  "geometry": {"coordinates":[3.2646028996,50.8293800354],"type":"Point"}
}