{
  "type": "Feature",
  "properties": {
    "iso:country":"BE",
    "sg:address":"Heidestraat 25",
    "sg:city":"Ieper (elverdinge)",
    "sg:classifiers":[
        {
            "category":"Home & Garden",
            "subcategory":"Carpets & Floor Coverings",
            "type":"Retail Goods"
        }
    ],
    "sg:phone":"+32 57 42 36 72",
    "sg:postcode":"8906",
    "sg:province":"West-Vlaanderen",
    "sg:tags":[
        "layer",
        "mosaicists"
    ],
    "wof:name":"Deroo",
    "wof:placetype":"venue"
},
  "geometry": {"coordinates":[2.8247170448,50.8858566284],"type":"Point"}
}