{
  "type": "Feature",
  "properties": {
    "addr:full":"Heesterveldwg 6 Industrieterrein Tongeren Oost Tongeren Limburg 3700",
    "addr:housenumber":"6",
    "addr:postcode":"tongeren;3700",
    "addr:street":"Heesterveldwg;Industrieterrein Tongeren",
    "iso:country":"BE",
    "sg:address":"Heesterveldwg 6 Industrieterrein Tongeren Oost",
    "sg:city":"Tongeren",
    "sg:classifiers":[
        {
            "category":"Manufacturing",
            "subcategory":"Metals",
            "type":"Manufacturing & Wholesale Goods"
        }
    ],
    "sg:phone":"+32 12 39 19 19",
    "sg:postcode":"3700",
    "sg:province":"Limburg",
    "sg:tags":[
        "metallurgy",
        "metalworking",
        "processing"
    ],
    "wof:name":"Press & Plat Nv",
    "wof:placetype":"venue"
},
  "geometry": {"coordinates":[5.5278987885,50.7924537659],"type":"Point"}
}