{
  "type": "Feature",
  "properties": {
    "iso:country":"BE",
    "sg:address":"Rue Ch\u00c2mont 32",
    "sg:city":"La Roche-en-ardenne",
    "sg:classifiers":[
        {
            "category":"Restaurant",
            "type":"Food & Drink"
        }
    ],
    "sg:phone":"+32 84 41 17 73",
    "sg:postcode":"6980",
    "sg:province":"Luxembourg",
    "wof:name":"La Fontanella",
    "wof:placetype":"venue"
},
  "geometry": {"coordinates":[5.5778398514,50.184627533],"type":"Point"}
}