{
  "type": "Feature",
  "properties": {
    "addr:full":"Brand Whitlocklaan 84 Sint-lambrechts-woluwe/woluwe-saint-lambert Bruxelles-Capitale 1200",
    "addr:housenumber":"84",
    "addr:postcode":"1200",
    "addr:street":"Brand Whitlocklaan",
    "iso:country":"BE",
    "sg:address":"Brand Whitlocklaan 84",
    "sg:city":"Sint-lambrechts-woluwe/woluwe-saint-lambert",
    "sg:orig_category":"Artsen and specialisten",
    "sg:phone":"+32 2 732 78 25",
    "sg:postcode":"1200",
    "sg:province":"Bruxelles-Capitale",
    "wof:name":"R. Pelaez Lopez",
    "wof:placetype":"venue"
},
  "geometry": {"coordinates":[4.4071121216,50.8418045044],"type":"Point"}
}