{
  "type": "Feature",
  "properties": {
    "iso:country":"BE",
    "sg:address":"Rue Winston Churchill",
    "sg:city":"Eugies",
    "sg:orig_category":"Huisdieren and benodigdheden Royal Canin",
    "sg:phone":"+32 65 67 71 14",
    "sg:postcode":"7340",
    "sg:province":"Hainaut",
    "wof:name":"Lambrechts",
    "wof:placetype":"venue"
},
  "geometry": {"coordinates":[3.870472908,50.3934326172],"type":"Point"}
}