{
  "type": "Feature",
  "properties": {
    "iso:country":"BE",
    "sg:address":"Durmstraat 108a",
    "sg:city":"Zomergem",
    "sg:classifiers":[
        {
            "category":"Personal",
            "subcategory":"Beauty Salon",
            "type":"Services"
        }
    ],
    "sg:phone":"+32 9 371 56 48",
    "sg:postcode":"9930",
    "sg:province":"Oost-Vlaanderen",
    "sg:tags":[
        "lady",
        "-",
        "hairdressing"
    ],
    "wof:name":"Patsy",
    "wof:placetype":"venue"
},
  "geometry": {"coordinates":[3.5712609291,51.0979156494],"type":"Point"}
}