{
  "type": "Feature",
  "properties": {
    "addr:full":"Stationstraat 2b1 Haaltert Oost-Vlaanderen 9450",
    "addr:housenumber":"2b1",
    "addr:postcode":"9450",
    "addr:street":"Stationstraat",
    "iso:country":"BE",
    "sg:address":"Stationstraat 2b1",
    "sg:city":"Haaltert",
    "sg:orig_category":"Chaussures. Articles de camping and de sport",
    "sg:phone":"+32 53 83 64 62",
    "sg:postcode":"9450",
    "sg:province":"Oost-Vlaanderen",
    "wof:name":"Fun Sports",
    "wof:placetype":"venue"
},
  "geometry": {"coordinates":[4.0068597794,50.9017410278],"type":"Point"}
}