{
  "type": "Feature",
  "properties": {
    "iso:country":"BE",
    "sg:address":"Akkerstraat 4",
    "sg:city":"Hove",
    "sg:orig_category":"Film-, tv- and videoproductie",
    "sg:phone":"+32 3 454 02 57",
    "sg:postcode":"2540",
    "sg:province":"Antwerpen",
    "wof:name":"I.p. Productions",
    "wof:placetype":"venue"
},
  "geometry": {"coordinates":[4.4912281036,51.135848999],"type":"Point"}
}