{
  "type": "Feature",
  "properties": {
    "addr:full":"Chauss\u00e9e Romaine 177 Waremme Li\u00e8ge 4300",
    "addr:housenumber":"177",
    "addr:postcode":"4300",
    "addr:street":"Chausse\u0301E Romaine",
    "iso:country":"BE",
    "sg:address":"Chauss\u00e9e Romaine 177",
    "sg:city":"Waremme",
    "sg:orig_category":"Non-Classified Establishments",
    "sg:phone":"+32 19 32 86 06",
    "sg:postcode":"4300",
    "sg:province":"Li\u00e8ge",
    "wof:name":"Robert Sa",
    "wof:placetype":"venue"
},
  "geometry": {"coordinates":[5.2680449486,50.6935157776],"type":"Point"}
}