{
  "type": "Feature",
  "properties": {
    "iso:country":"BE",
    "sg:address":"Rue De Mettet 68",
    "sg:city":"Florennes",
    "sg:orig_category":"Huisdieren and benodigdheden",
    "sg:phone":"+32 71 68 75 34",
    "sg:postcode":"5620",
    "sg:province":"Namur",
    "wof:name":"Fe. Aqua Hobby",
    "wof:placetype":"venue"
},
  "geometry": {"coordinates":[4.608288765,50.2561836243],"type":"Point"}
}