{
  "type": "Feature",
  "properties": {
    "addr:full":"Rue Haute 2-6 Ath Hainaut 7800",
    "addr:housenumber":"2-6",
    "addr:postcode":"7800",
    "addr:street":"Rue Haute",
    "iso:country":"BE",
    "sg:address":"Rue Haute 2-6",
    "sg:city":"Ath",
    "sg:classifiers":[
        {
            "category":"Retail",
            "subcategory":"Repair Shop",
            "type":"Services"
        }
    ],
    "sg:phone":"+32 68 28 32 77",
    "sg:postcode":"7800",
    "sg:province":"Hainaut",
    "sg:tags":[
        "-",
        "mainten",
        "watch",
        "clock"
    ],
    "wof:name":"Evrart H Sa",
    "wof:placetype":"venue"
},
  "geometry": {"coordinates":[3.7803161144,50.6289176941],"type":"Point"}
}