{
  "type": "Feature",
  "properties": {
    "addr:full":"Rue Du Ch\u00cane 50 Chapelle-lez-herlaimont Hainaut 7160",
    "addr:housenumber":"50",
    "addr:postcode":"7160",
    "addr:street":"Rue Du Che\u0302Ne",
    "iso:country":"BE",
    "sg:address":"Rue Du Ch\u00cane 50",
    "sg:city":"Chapelle-lez-herlaimont",
    "sg:orig_category":"DIVERSE RECREATIEVE ACTIVITEITEN",
    "sg:phone":"+32 64 45 13 44",
    "sg:postcode":"7160",
    "sg:province":"Hainaut",
    "wof:name":"Model Club Chapellois",
    "wof:placetype":"venue"
},
  "geometry": {"coordinates":[4.279624939,50.4741821289],"type":"Point"}
}