{
  "type": "Feature",
  "properties": {
    "addr:full":"Avenue D'avon-les-roches 3 Brugelette Hainaut 7940",
    "addr:housenumber":"3",
    "addr:postcode":"7940",
    "addr:street":"Avenue D'Avon-Les-Roches;Hainaut",
    "iso:country":"BE",
    "sg:address":"Avenue D'avon-les-roches 3",
    "sg:city":"Brugelette",
    "sg:orig_category":"Artsen and specialisten",
    "sg:phone":"+32 68 45 48 61",
    "sg:postcode":"7940",
    "sg:province":"Hainaut",
    "wof:name":"D. Vanmansart",
    "wof:placetype":"venue"
},
  "geometry": {"coordinates":[3.8694300652,50.5962791443],"type":"Point"}
}