{
  "type": "Feature",
  "properties": {
    "addr:full":"Paalsesteenweg 302 Beringen Limburg 3583",
    "addr:housenumber":"302",
    "addr:postcode":"3583",
    "addr:street":"Paalsesteenweg",
    "iso:country":"BE",
    "sg:address":"Paalsesteenweg 302",
    "sg:city":"Beringen",
    "sg:orig_category":"Epiceries",
    "sg:phone":"+32 11 42 25 57",
    "sg:postcode":"3583",
    "sg:province":"Limburg",
    "wof:name":"Spar",
    "wof:placetype":"venue"
},
  "geometry": {"coordinates":[5.1706700325,51.0389442444],"type":"Point"}
}