{
  "type": "Feature",
  "properties": {
    "iso:country":"BE",
    "sg:address":"Burchtdam 4",
    "sg:city":"Ninove",
    "sg:orig_category":"Furniture Trimmings",
    "sg:phone":"+32 54 33 20 62",
    "sg:postcode":"9400",
    "sg:province":"Oost-Vlaanderen",
    "wof:name":"Edgar Moeremans En Companie B.v.b.a.",
    "wof:placetype":"venue"
},
  "geometry": {"coordinates":[4.0233001709,50.831199646],"type":"Point"}
}