{
  "type": "Feature",
  "properties": {
    "iso:country":"BE",
    "sg:address":"Leenbosstraat 14",
    "sg:city":"Ardooie",
    "sg:orig_category":"Eleveurs and marchands de porcs",
    "sg:phone":"+32 51 31 08 77",
    "sg:postcode":"8850",
    "sg:province":"West-Vlaanderen",
    "wof:name":"Eddy Naert",
    "wof:placetype":"venue"
},
  "geometry": {"coordinates":[3.2250220776,50.9510879517],"type":"Point"}
}