{
  "type": "Feature",
  "properties": {
    "addr:full":"Rue Des Champs 28 Grace-hollogne Li\u00e8ge 4460",
    "addr:housenumber":"28",
    "addr:postcode":"4460",
    "addr:street":"Rue Des Champs",
    "iso:country":"BE",
    "sg:address":"Rue Des Champs 28",
    "sg:city":"Grace-hollogne",
    "sg:orig_category":"Gespecialiseerde residenti\u00eble bouw",
    "sg:phone":"+32 4 247 23 36",
    "sg:postcode":"4460",
    "sg:province":"Li\u00e8ge",
    "wof:name":"Meovine Rejointoyage",
    "wof:placetype":"venue"
},
  "geometry": {"coordinates":[5.4815411568,50.6456298828],"type":"Point"}
}