{
  "type": "Feature",
  "properties": {
    "iso:country":"BE",
    "sg:address":"Lange Meire 82",
    "sg:city":"Laarne",
    "sg:orig_category":"Caravans, aanhangwagens and opleggers",
    "sg:phone":"+32 9 369 14 48",
    "sg:postcode":"9270",
    "sg:province":"Oost-Vlaanderen",
    "wof:name":"Fa. Depauw",
    "wof:placetype":"venue"
},
  "geometry": {"coordinates":[3.8673141003,51.0219268799],"type":"Point"}
}