{
  "type": "Feature",
  "properties": {
    "addr:full":"Rue De La Solitude 47 Tournai Hainaut 7540",
    "addr:housenumber":"47",
    "addr:postcode":"7540",
    "addr:street":"Rue De La Solitude",
    "iso:country":"BE",
    "sg:address":"Rue De La Solitude 47",
    "sg:city":"Tournai",
    "sg:orig_category":"Enseignement maternel and primaire",
    "sg:phone":"+32 69 21 00 50",
    "sg:postcode":"7540",
    "sg:province":"Hainaut",
    "wof:name":"Ecole Fondamentale Libre",
    "wof:placetype":"venue"
},
  "geometry": {"coordinates":[3.4283180237,50.6188316345],"type":"Point"}
}