{
  "type": "Feature",
  "properties": {
    "iso:country":"BE",
    "sg:address":"Sint-niklaasstraat 46",
    "sg:city":"Gent",
    "sg:classifiers":[
        {
            "category":"Personal",
            "subcategory":"Beauty Salon",
            "type":"Services"
        }
    ],
    "sg:phone":"+32 9 234 34 26",
    "sg:postcode":"9000",
    "sg:province":"Oost-Vlaanderen",
    "sg:tags":[
        "lady",
        "-",
        "hairdressing"
    ],
    "wof:name":"Kaprijke",
    "wof:placetype":"venue"
},
  "geometry": {"coordinates":[3.7228150368,51.0527839661],"type":"Point"}
}