{
  "type": "Feature",
  "properties": {
    "addr:full":"Chauss\u00c9e De Charleroi 175 Sombreffe Namur 5140",
    "addr:housenumber":"175",
    "addr:postcode":"5140",
    "addr:street":"Chausse\u0301E De Charleroi",
    "iso:country":"BE",
    "sg:address":"Chauss\u00c9e De Charleroi 175",
    "sg:city":"Sombreffe",
    "sg:orig_category":"Travaux de pl\u00e2trage",
    "sg:phone":"+32 71 88 80 39",
    "sg:postcode":"5140",
    "sg:province":"Namur",
    "wof:name":"D.a. Construct",
    "wof:placetype":"venue"
},
  "geometry": {"coordinates":[4.5787901878,50.499458313],"type":"Point"}
}