{
  "type": "Feature",
  "properties": {
    "addr:full":"Leuvensestraat 92 Oud-heverlee (sint-joris-weert) Vlaams-Brabant 3051",
    "addr:housenumber":"92",
    "addr:postcode":"3051",
    "addr:street":"Leuvensestraat",
    "iso:country":"BE",
    "sg:address":"Leuvensestraat 92",
    "sg:city":"Oud-heverlee (sint-joris-weert)",
    "sg:classifiers":[
        {
            "category":"Building & Trades",
            "subcategory":"Electrical",
            "type":"Services"
        }
    ],
    "sg:phone":"+32 474 70 93 76",
    "sg:postcode":"3051",
    "sg:province":"Vlaams-Brabant",
    "sg:tags":[
        "electric",
        "-",
        "housewiring",
        "contractor"
    ],
    "wof:name":"Daman Jan",
    "wof:placetype":"venue"
},
  "geometry": {"coordinates":[4.6505761147,50.8106079102],"type":"Point"}
}