{
  "type": "Feature",
  "properties": {
    "addr:full":"Rue Du Brutz 1 Bouillon Luxembourg 6830",
    "addr:housenumber":"1",
    "addr:postcode":"6830",
    "addr:street":"Rue Du Brutz",
    "iso:country":"BE",
    "sg:address":"Rue Du Brutz 1",
    "sg:city":"Bouillon",
    "sg:orig_category":"M\u00e9decins and sp\u00e9cialistes",
    "sg:phone":"+32 61 46 60 28",
    "sg:postcode":"6830",
    "sg:province":"Luxembourg",
    "wof:name":"Jacques Buchet",
    "wof:placetype":"venue"
},
  "geometry": {"coordinates":[5.068529129,49.7956771851],"type":"Point"}
}