{
  "type": "Feature",
  "properties": {
    "addr:full":"Chauss\u00c9e De Waterloo 389 Namur Namur 5002",
    "addr:housenumber":"389",
    "addr:postcode":"5002",
    "addr:street":"Chausse\u0301E De Waterloo",
    "iso:country":"BE",
    "sg:address":"Chauss\u00c9e De Waterloo 389",
    "sg:city":"Namur",
    "sg:orig_category":"Fleurs and plantes",
    "sg:phone":"+32 81 73 04 72",
    "sg:postcode":"5002",
    "sg:province":"Namur",
    "wof:name":"X. Van Twembeke",
    "wof:placetype":"venue"
},
  "geometry": {"coordinates":[4.8462319374,50.4782791138],"type":"Point"}
}