{
  "type": "Feature",
  "properties": {
    "iso:country":"BE",
    "sg:address":"Basse Cour 22",
    "sg:city":"Durbuy (barvaux-sur-ourthe)",
    "sg:classifiers":[
        {
            "category":"Wholesale",
            "subcategory":"Meat",
            "type":"Manufacturing & Wholesale Goods"
        }
    ],
    "sg:phone":"+32 86 21 11 98",
    "sg:postcode":"6940",
    "sg:province":"Luxembourg",
    "sg:tags":[
        "whol",
        "-"
    ],
    "wof:name":"Jugnot",
    "wof:placetype":"venue"
},
  "geometry": {"coordinates":[5.497633934,50.3517799377],"type":"Point"}
}