{
  "type": "Feature",
  "properties": {
    "addr:full":"Kortrijksesteenweg 106 Gent Oost-Vlaanderen 9000",
    "addr:housenumber":"106",
    "addr:postcode":"9000",
    "addr:street":"Kortrijksesteenweg;Oost-Vlaanderen",
    "iso:country":"BE",
    "sg:address":"Kortrijksesteenweg 106",
    "sg:city":"Gent",
    "sg:orig_category":"Services de Nettoyage and de D\u00e9sinfection. Charpentes and couvertures. Plomberie, chauffage and inst",
    "sg:phone":"+32 9 222 49 99",
    "sg:postcode":"9000",
    "sg:province":"Oost-Vlaanderen",
    "wof:name":"City Service",
    "wof:placetype":"venue"
},
  "geometry": {"coordinates":[3.717236042,51.0405769348],"type":"Point"}
}