{
  "type": "Feature",
  "properties": {
    "addr:full":"Schrieksebaan 144 Tremelo Vlaams-Brabant 3120",
    "addr:housenumber":"144",
    "addr:postcode":"3120",
    "addr:street":"Schrieksebaan",
    "iso:country":"BE",
    "sg:address":"Schrieksebaan 144",
    "sg:city":"Tremelo",
    "sg:orig_category":"Loodgieterij, verwarming and sanitaire installaties",
    "sg:phone":"+32 16 53 15 03",
    "sg:postcode":"3120",
    "sg:province":"Vlaams-Brabant",
    "wof:name":"Fa. Van Dyck R. & Zn",
    "wof:placetype":"venue"
},
  "geometry": {"coordinates":[4.7068309784,51.0010948181],"type":"Point"}
}