{
  "type": "Feature",
  "properties": {
    "iso:country":"BE",
    "sg:address":"Rue De L\u00b4autonomie 3",
    "sg:city":"Anderlecht",
    "sg:classifiers":[
        {
            "category":"Restaurant",
            "type":"Food & Drink"
        }
    ],
    "sg:phone":"+32 2 524 42 23",
    "sg:postcode":"1070",
    "sg:province":"Bruxelles-Capitale",
    "wof:name":"Snack-bar Supreme",
    "wof:placetype":"venue"
},
  "geometry": {"coordinates":[4.3384318352,50.8406257629],"type":"Point"}
}