{
  "type": "Feature",
  "properties": {
    "addr:full":"Bredabaan 407 Brasschaat Antwerpen 2930",
    "addr:housenumber":"407",
    "addr:postcode":"2930",
    "addr:street":"Bredabaan",
    "iso:country":"BE",
    "sg:address":"Bredabaan 407",
    "sg:city":"Brasschaat",
    "sg:classifiers":[
        {
            "category":"Education",
            "subcategory":"Library",
            "type":"Public Place"
        }
    ],
    "sg:phone":"+32 3 650 03 60",
    "sg:postcode":"2930",
    "sg:province":"Antwerpen",
    "wof:name":"Gemeentelijke Openbare Bibliotheken Brasschaat",
    "wof:placetype":"venue"
},
  "geometry": {"coordinates":[4.4931840897,51.2909965515],"type":"Point"}
}