{
  "type": "Feature",
  "properties": {
    "addr:full":"Artanstraat 142 Schaarbeek/schaerbeek Bruxelles-Capitale 1030",
    "addr:housenumber":"142",
    "addr:postcode":"1030",
    "addr:street":"Artanstraat",
    "iso:country":"BE",
    "sg:address":"Artanstraat 142",
    "sg:city":"Schaarbeek/schaerbeek",
    "sg:orig_category":"Boekhouders",
    "sg:phone":"+32 2 410 28 16",
    "sg:postcode":"1030",
    "sg:province":"Bruxelles-Capitale",
    "wof:name":"Olivier Dubois",
    "wof:placetype":"venue"
},
  "geometry": {"coordinates":[4.3835868835,50.8527641296],"type":"Point"}
}