{
  "type": "Feature",
  "properties": {
    "addr:full":"Dorpsstraat 31 Beveren Oost-Vlaanderen 9130",
    "addr:housenumber":"31",
    "addr:postcode":"9130",
    "addr:street":"Dorpsstraat",
    "iso:country":"BE",
    "sg:address":"Dorpsstraat 31",
    "sg:city":"Beveren",
    "sg:orig_category":"Diepvriesproducten Gh",
    "sg:phone":"+32 3 773 56 65",
    "sg:postcode":"9130",
    "sg:province":"Oost-Vlaanderen",
    "wof:name":"Andre De Cock",
    "wof:placetype":"venue"
},
  "geometry": {"coordinates":[4.1745390892,51.2904396057],"type":"Point"}
}