{
  "type": "Feature",
  "properties": {
    "addr:full":"Rue Des Blancs Chevaux 7 Ottignies-louvain-la-neuve Brabant Wallon 1348",
    "addr:housenumber":"7",
    "addr:postcode":"1348",
    "addr:street":"Rue Des Blancs Chevaux",
    "iso:country":"BE",
    "sg:address":"Rue Des Blancs Chevaux 7",
    "sg:city":"Ottignies-louvain-la-neuve",
    "sg:orig_category":"Fast food and meeneem restaurants Ruimtes voor conferenties, recepties and feesten",
    "sg:phone":"+32 10 45 08 06",
    "sg:postcode":"1348",
    "sg:province":"Brabant Wallon",
    "wof:name":"Le Piano",
    "wof:placetype":"venue"
},
  "geometry": {"coordinates":[4.6092700958,50.6713180542],"type":"Point"}
}