{
  "type": "Feature",
  "properties": {
    "addr:full":"Kunstenaarstraat 1 Gent Oost-Vlaanderen 9040",
    "addr:housenumber":"1",
    "addr:postcode":"9040",
    "addr:street":"Kunstenaarstraat;Oost-Vlaanderen",
    "iso:country":"BE",
    "sg:address":"Kunstenaarstraat 1",
    "sg:city":"Gent",
    "sg:classifiers":[
        {
            "category":"Fast Food",
            "type":"Food & Drink"
        }
    ],
    "sg:phone":"+32 9 238 24 22",
    "sg:postcode":"9040",
    "sg:province":"Oost-Vlaanderen",
    "sg:tags":[
        "meeneem",
        "restaurant"
    ],
    "wof:name":"Pizza Hut",
    "wof:placetype":"venue"
},
  "geometry": {"coordinates":[3.748032093,51.0523948669],"type":"Point"}
}