{
  "type": "Feature",
  "properties": {
    "iso:country":"BE",
    "sg:address":"Petermansstraat 44",
    "sg:city":"Beringen",
    "sg:orig_category":"D\u00e9molition d\u00b4immeubles and terrassements",
    "sg:phone":"+32 475 73 05 78",
    "sg:postcode":"3583",
    "sg:province":"Limburg",
    "wof:name":"Fa. Rustica",
    "wof:placetype":"venue"
},
  "geometry": {"coordinates":[5.1706700325,51.0389442444],"type":"Point"}
}