{
  "type": "Feature",
  "properties": {
    "addr:full":"Britse Lei 49 Antwerpen Antwerpen 2000",
    "addr:housenumber":"49",
    "addr:postcode":"2000",
    "addr:street":"Lei",
    "iso:country":"BE",
    "sg:address":"Britse Lei 49",
    "sg:city":"Antwerpen",
    "sg:classifiers":[
        {
            "category":"Health Services",
            "subcategory":"Dentist",
            "type":"Services"
        }
    ],
    "sg:phone":"+32 3 216 07 07",
    "sg:postcode":"2000",
    "sg:province":"Antwerpen",
    "wof:name":"Meeussen Inge",
    "wof:placetype":"venue"
},
  "geometry": {"coordinates":[4.4050087929,51.2093315125],"type":"Point"}
}