{
  "type": "Feature",
  "properties": {
    "addr:full":"Chauss\u00c9e De Roodebeek 61 Sint-lambrechts-woluwe/woluwe-saint-lambert Bruxelles-Capitale 1200",
    "addr:housenumber":"61",
    "addr:postcode":"1200",
    "addr:street":"Chausse\u0301E De Roodebeek",
    "iso:country":"BE",
    "sg:address":"Chauss\u00c9e De Roodebeek 61",
    "sg:city":"Sint-lambrechts-woluwe/woluwe-saint-lambert",
    "sg:orig_category":"Meubles D\u00e9taillants, Am\u00e9nagement de B\u00e2timents et de Cuisines. Fabrication and montage de mobilier",
    "sg:phone":"+32 2 762 29 99",
    "sg:postcode":"1200",
    "sg:province":"Bruxelles-Capitale",
    "wof:name":"D. Van De Velde/daniel Van De Velde",
    "wof:placetype":"venue"
},
  "geometry": {"coordinates":[4.4336891174,50.8486366272],"type":"Point"}
}