{
  "type": "Feature",
  "properties": {
    "iso:country":"BE",
    "sg:address":"Boerenstraat 152",
    "sg:city":"Beveren",
    "sg:orig_category":"Fietsen Watersport-, Sport- and Kampeerbenodigdheden Verhuur",
    "sg:phone":"+32 3 775 43 45",
    "sg:postcode":"9120",
    "sg:province":"Oost-Vlaanderen",
    "wof:name":"Nico Lauwaert",
    "wof:placetype":"venue"
},
  "geometry": {"coordinates":[4.212998867,51.1990661621],"type":"Point"}
}