{
  "type": "Feature",
  "properties": {
    "addr:full":"Nauwstraat 27 Sint-niklaas Oost-Vlaanderen 9111",
    "addr:housenumber":"27",
    "addr:postcode":"9111",
    "addr:street":"Nauwstraat",
    "iso:country":"BE",
    "sg:address":"Nauwstraat 27",
    "sg:city":"Sint-niklaas",
    "sg:orig_category":"Installation de menuiserie m\u00e9tallique. Installation de menuiserie en bois and plastique",
    "sg:phone":"+32 3 776 32 94",
    "sg:postcode":"9111",
    "sg:province":"Oost-Vlaanderen",
    "wof:name":"Van Roeyen",
    "wof:placetype":"venue"
},
  "geometry": {"coordinates":[4.1006422043,51.1764411926],"type":"Point"}
}