{
  "type": "Feature",
  "properties": {
    "addr:full":"Rue Haute 58 Ottignies-louvain-la-neuve Brabant Wallon 1348",
    "addr:housenumber":"58",
    "addr:postcode":"1348",
    "addr:street":"Rue Haute",
    "iso:country":"BE",
    "sg:address":"Rue Haute 58",
    "sg:city":"Ottignies-louvain-la-neuve",
    "sg:orig_category":"Reliure and finition",
    "sg:phone":"+32 10 45 08 49",
    "sg:postcode":"1348",
    "sg:province":"Brabant Wallon",
    "wof:name":"Monast\u00c8re St.gertrude",
    "wof:placetype":"venue"
},
  "geometry": {"coordinates":[4.6035342216,50.6690673828],"type":"Point"}
}