{
  "type": "Feature",
  "properties": {
    "iso:country":"BE",
    "sg:address":"Zuringstraat 4",
    "sg:city":"Wuustwezel",
    "sg:classifiers":[
        {
            "category":"Personal",
            "subcategory":"Beauty Salon",
            "type":"Services"
        }
    ],
    "sg:phone":"+32 3 663 72 23",
    "sg:postcode":"2990",
    "sg:province":"Antwerpen",
    "wof:name":"Trend Style & Beauty",
    "wof:placetype":"venue"
},
  "geometry": {"coordinates":[4.5546197891,51.3622360229],"type":"Point"}
}