{
  "type": "Feature",
  "properties": {
    "iso:country":"BE",
    "sg:address":"Avenue Docteur Decroly 58",
    "sg:city":"Ukkel/uccle",
    "sg:orig_category":"Elektrische installaties voor woningen",
    "sg:phone":"+32 475 82 70 40",
    "sg:postcode":"1180",
    "sg:province":"Bruxelles-Capitale",
    "wof:name":"Depr\u00c9 Bertrand",
    "wof:placetype":"venue"
},
  "geometry": {"coordinates":[4.3291459084,50.8038101196],"type":"Point"}
}