{
  "type": "Feature",
  "properties": {
    "iso:country":"BE",
    "sg:address":"Rue Docteur L\u00c9on Neuens 1",
    "sg:city":"Chatelet",
    "sg:orig_category":"Pain, p\u00e2tisseries and confiseries",
    "sg:phone":"+32 71 38 29 06",
    "sg:postcode":"6200",
    "sg:province":"Hainaut",
    "wof:name":"La Palette Sucr\u00c9e",
    "wof:placetype":"venue"
},
  "geometry": {"coordinates":[4.5162768364,50.4026031494],"type":"Point"}
}