{
  "type": "Feature",
  "properties": {
    "addr:full":"Zuidstraat 35 Torhout West-Vlaanderen 8820",
    "addr:housenumber":"35",
    "addr:postcode":"8820",
    "addr:street":"Zuidstraat",
    "iso:country":"BE",
    "sg:address":"Zuidstraat 35",
    "sg:city":"Torhout",
    "sg:classifiers":[
        {
            "category":"Personal",
            "subcategory":"Beauty Salon",
            "type":"Services"
        }
    ],
    "sg:phone":"+32 50 22 12 21",
    "sg:postcode":"8820",
    "sg:province":"West-Vlaanderen",
    "sg:tags":[
        "de",
        "coiffure"
    ],
    "wof:name":"Coiffure Aquarelle",
    "wof:placetype":"venue"
},
  "geometry": {"coordinates":[3.1024079323,51.0634307861],"type":"Point"}
}