{
  "type": "Feature",
  "properties": {
    "addr:full":"Koolputstraat 2 Beveren Oost-Vlaanderen 9120",
    "addr:housenumber":"2",
    "addr:postcode":"9120",
    "addr:street":"Koolputstraat",
    "iso:country":"BE",
    "sg:address":"Koolputstraat 2",
    "sg:city":"Beveren",
    "sg:orig_category":"Sportclubs",
    "sg:phone":"+32 3 755 13 17",
    "sg:postcode":"9120",
    "sg:province":"Oost-Vlaanderen",
    "wof:name":"H.c. Rapid Temse",
    "wof:placetype":"venue"
},
  "geometry": {"coordinates":[4.2705931664,51.23179245],"type":"Point"}
}