{
  "type": "Feature",
  "properties": {
    "iso:country":"BE",
    "sg:address":"Sint-antoniusstraat 19",
    "sg:city":"Turnhout",
    "sg:classifiers":[
        {
            "category":"Cafe",
            "type":"Food & Drink"
        }
    ],
    "sg:phone":"+32 14 42 64 69",
    "sg:postcode":"2300",
    "sg:province":"Antwerpen",
    "sg:tags":[
        "snack-bars"
    ],
    "wof:name":"Caf\u00e9 Glac\u00e9",
    "wof:placetype":"venue"
},
  "geometry": {"coordinates":[4.9437041283,51.3231811523],"type":"Point"}
}