{
  "type": "Feature",
  "properties": {
    "addr:full":"Rootenstraat 9 Box 14 Genk Limburg 3600",
    "addr:housenumber":"9 box 14",
    "addr:postcode":"3600",
    "addr:street":"Rootenstraat",
    "iso:country":"BE",
    "sg:address":"Rootenstraat 9 Box 14",
    "sg:city":"Genk",
    "sg:classifiers":[
        {
            "category":"Shopping",
            "subcategory":"Clothing, Apparel, & Fashions",
            "type":"Retail Goods"
        }
    ],
    "sg:phone":"+32 89 61 51 11",
    "sg:postcode":"3600",
    "sg:province":"Limburg",
    "sg:tags":[
        "clothing",
        "-",
        "gentleman"
    ],
    "wof:name":"D'tail Shopping Twee",
    "wof:placetype":"venue"
},
  "geometry": {"coordinates":[5.5028338432,50.9652481079],"type":"Point"}
}