{
  "type": "Feature",
  "properties": {
    "iso:country":"BE",
    "sg:address":"Ketelbuizerstraat 35",
    "sg:city":"Lichtervelde",
    "sg:orig_category":"Non-Classified Establishments",
    "sg:phone":"+32 51 72 25 29",
    "sg:postcode":"8810",
    "sg:province":"West-Vlaanderen",
    "wof:name":"Beeusaert M",
    "wof:placetype":"venue"
},
  "geometry": {"coordinates":[3.1279389858,51.0281028748],"type":"Point"}
}