{
  "type": "Feature",
  "properties": {
    "addr:full":"Durmen 164 Zele Oost-Vlaanderen 9240",
    "addr:housenumber":"164",
    "addr:postcode":"9240",
    "addr:street":"Durmen",
    "iso:country":"BE",
    "sg:address":"Durmen 164",
    "sg:city":"Zele",
    "sg:classifiers":[
        {
            "category":"Cafe",
            "type":"Food & Drink"
        }
    ],
    "sg:phone":"+32 52 44 91 19",
    "sg:postcode":"9240",
    "sg:province":"Oost-Vlaanderen",
    "sg:tags":[
        "caf\u00e9s"
    ],
    "wof:name":"Caf\u00c9 Durmenhof",
    "wof:placetype":"venue"
},
  "geometry": {"coordinates":[4.0548911095,51.0856246948],"type":"Point"}
}