{
  "type": "Feature",
  "properties": {
    "iso:country":"BE",
    "sg:address":"Sint-augustinuslaan 30",
    "sg:city":"Vorst/forest",
    "sg:orig_category":"Architecten",
    "sg:phone":"+32 2 343 23 57",
    "sg:postcode":"1190",
    "sg:province":"Bruxelles-Capitale",
    "wof:name":"Jorge Slautsky",
    "wof:placetype":"venue"
},
  "geometry": {"coordinates":[4.339099884,50.8167800903],"type":"Point"}
}