{
  "type": "Feature",
  "properties": {
    "iso:country":"BE",
    "sg:address":"Steenweg 233ba",
    "sg:city":"Nazareth",
    "sg:orig_category":"Herstellingen and onderhoud van auto's Voertuigen",
    "sg:phone":"+32 9 385 47 47",
    "sg:postcode":"9810",
    "sg:province":"Oost-Vlaanderen",
    "wof:name":"Cardoen",
    "wof:placetype":"venue"
},
  "geometry": {"coordinates":[3.5967800617,50.9596405029],"type":"Point"}
}