{
  "type": "Feature",
  "properties": {
    "iso:country":"BE",
    "sg:address":"Rue Du Waux Hall 14",
    "sg:city":"Grez-doiceau",
    "sg:classifiers":[
        {
            "category":"Retail",
            "subcategory":"Funeral Services",
            "type":"Services"
        }
    ],
    "sg:phone":"+32 10 84 14 78",
    "sg:postcode":"1390",
    "sg:province":"Brabant Wallon",
    "sg:tags":[
        "director"
    ],
    "wof:name":"Saublens C",
    "wof:placetype":"venue"
},
  "geometry": {"coordinates":[4.6990008354,50.7386016846],"type":"Point"}
}