{
  "type": "Feature",
  "properties": {
    "iso:country":"BE",
    "sg:address":"Rue Sauveni\u00c8re 25",
    "sg:city":"Ouffet (groot)",
    "sg:classifiers":[
        {
            "category":"Personal",
            "subcategory":"Beauty Salon",
            "type":"Services"
        }
    ],
    "sg:phone":"+32 866881",
    "sg:postcode":"4590",
    "sg:province":"Li\u00e8ge",
    "sg:tags":[
        "de",
        "coiffure"
    ],
    "wof:name":"Imaginatif",
    "wof:placetype":"venue"
},
  "geometry": {"coordinates":[5.4640541077,50.4394340515],"type":"Point"}
}