{
  "type": "Feature",
  "properties": {
    "iso:country":"BE",
    "sg:address":"Chee De Bruxelles 10",
    "sg:city":"Ath",
    "sg:orig_category":"Non-Classified Establishments",
    "sg:phone":"+32 68 28 52 77",
    "sg:postcode":"7800",
    "sg:province":"Hainaut",
    "wof:name":"Heusschen",
    "wof:placetype":"venue"
},
  "geometry": {"coordinates":[3.7853240967,50.6310081482],"type":"Point"}
}