{
  "type": "Feature",
  "properties": {
    "iso:country":"BE",
    "sg:address":"Zandvoordsestraat 181",
    "sg:city":"Oudenburg",
    "sg:orig_category":"HUISBRANDOLIE Hout and afgeleiden Gh IJzerwaren, bouw- and verfmaterialen",
    "sg:phone":"+32 59 27 87 60",
    "sg:postcode":"8460",
    "sg:province":"West-Vlaanderen",
    "wof:name":"Rodanar",
    "wof:placetype":"venue"
},
  "geometry": {"coordinates":[2.9904549122,51.1908760071],"type":"Point"}
}