{
  "type": "Feature",
  "properties": {
    "iso:country":"BE",
    "sg:address":"Edingsesteenweg 48",
    "sg:city":"Herne",
    "sg:orig_category":"Fleurs and plantes",
    "sg:phone":"+32 2 396 27 72",
    "sg:postcode":"1540",
    "sg:province":"Vlaams-Brabant",
    "wof:name":"Plasschaert",
    "wof:placetype":"venue"
},
  "geometry": {"coordinates":[4.0284252167,50.7073364258],"type":"Point"}
}