{
  "type": "Feature",
  "properties": {
    "addr:full":"Pasteelsstraat 44 Mortsel Antwerpen 2640",
    "addr:housenumber":"44",
    "addr:postcode":"2640",
    "addr:street":"Pasteelsstraat",
    "iso:country":"BE",
    "sg:address":"Pasteelsstraat 44",
    "sg:city":"Mortsel",
    "sg:orig_category":"Advocaten and juridische adviseurs",
    "sg:phone":"+32 3 440 10 01",
    "sg:postcode":"2640",
    "sg:province":"Antwerpen",
    "wof:name":"A. Arien",
    "wof:placetype":"venue"
},
  "geometry": {"coordinates":[4.4667000771,51.1676216125],"type":"Point"}
}