{
  "type": "Feature",
  "properties": {
    "addr:full":"Mispelaarstraat 16 Genk Limburg 3600",
    "addr:housenumber":"16",
    "addr:postcode":"3600",
    "addr:street":"Mispelaarstraat",
    "iso:country":"BE",
    "sg:address":"Mispelaarstraat 16",
    "sg:city":"Genk",
    "sg:classifiers":[
        {
            "category":"Health Services",
            "subcategory":"Health Practitioner",
            "type":"Services"
        }
    ],
    "sg:phone":"+32 89 30 75 00",
    "sg:postcode":"3600",
    "sg:province":"Limburg",
    "sg:tags":[
        "physiotherapist"
    ],
    "wof:name":"Lens Joris",
    "wof:placetype":"venue"
},
  "geometry": {"coordinates":[5.526913166,50.9761619568],"type":"Point"}
}