{
  "type": "Feature",
  "properties": {
    "iso:country":"BE",
    "sg:address":"Stokerijstraat 15",
    "sg:city":"Wijnegem",
    "sg:orig_category":"Antiquit\u00e9s",
    "sg:phone":"+32 3 355 33 00",
    "sg:postcode":"2110",
    "sg:province":"Antwerpen",
    "wof:name":"Vervoordt Axel",
    "wof:placetype":"venue"
},
  "geometry": {"coordinates":[4.5320739746,51.2275733948],"type":"Point"}
}