{
  "type": "Feature",
  "properties": {
    "iso:country":"BE",
    "sg:address":"Schiemorter 1",
    "sg:city":"Lint",
    "sg:orig_category":"Instituts de beaut\u00e9",
    "sg:phone":"+32 3 455 59 07",
    "sg:postcode":"2547",
    "sg:province":"Antwerpen",
    "wof:name":"Instituut Amaryllis",
    "wof:placetype":"venue"
},
  "geometry": {"coordinates":[4.490626812,51.1218910217],"type":"Point"}
}