{
  "type": "Feature",
  "properties": {
    "addr:full":"Kortrijksestraat 183 Izegem West-Vlaanderen 8870",
    "addr:housenumber":"183",
    "addr:postcode":"8870",
    "addr:street":"Kortrijksestraat",
    "iso:country":"BE",
    "sg:address":"Kortrijksestraat 183",
    "sg:city":"Izegem",
    "sg:classifiers":[
        {
            "category":"Travel",
            "subcategory":"Hotels & Motels",
            "type":"Entertainment"
        }
    ],
    "sg:phone":"+32 51 30 50 95",
    "sg:postcode":"8870",
    "sg:province":"West-Vlaanderen",
    "sg:tags":[
        "equipment",
        "installation",
        "hotels"
    ],
    "wof:name":"Himpe-desmet Bvba",
    "wof:placetype":"venue"
},
  "geometry": {"coordinates":[3.2172689438,50.9110107422],"type":"Point"}
}