{
  "type": "Feature",
  "properties": {
    "addr:full":"Rumbeeksesteenweg 396 Roeselare West-Vlaanderen 8800",
    "addr:housenumber":"396",
    "addr:postcode":"8800",
    "addr:street":"Rumbeeksesteenweg",
    "iso:country":"BE",
    "sg:address":"Rumbeeksesteenweg 396",
    "sg:city":"Roeselare",
    "sg:classifiers":[
        {
            "category":"Fast Food",
            "type":"Food & Drink"
        }
    ],
    "sg:phone":"+32 51 20 43 61",
    "sg:postcode":"8800",
    "sg:province":"West-Vlaanderen",
    "sg:tags":[
        "meeneem",
        "restaurant"
    ],
    "wof:name":"Prinsenhof",
    "wof:placetype":"venue"
},
  "geometry": {"coordinates":[3.1369390488,50.9381027222],"type":"Point"}
}