{
  "type": "Feature",
  "properties": {
    "addr:full":"Weststraat 11b4 Ingelmunster West-Vlaanderen 8770",
    "addr:housenumber":"11b4",
    "addr:postcode":"8770",
    "addr:street":"Weststraat",
    "iso:country":"BE",
    "sg:address":"Weststraat 11b4",
    "sg:city":"Ingelmunster",
    "sg:classifiers":[
        {
            "category":"Food & Beverages",
            "subcategory":"Fruits & Vegetables",
            "type":"Retail Goods"
        }
    ],
    "sg:phone":"+32 51 30 06 04",
    "sg:postcode":"8770",
    "sg:province":"West-Vlaanderen",
    "sg:tags":[
        "l\u00e9gumes",
        "gr"
    ],
    "wof:name":"Odiel Bonte",
    "wof:placetype":"venue"
},
  "geometry": {"coordinates":[3.2517330647,50.9207267761],"type":"Point"}
}