{
  "type": "Feature",
  "properties": {
    "iso:country":"BE",
    "sg:address":"Touquetstraat 228",
    "sg:city":"Ploegsteert",
    "sg:classifiers":[
        {
            "category":"Manufacturing",
            "subcategory":"Building Materials",
            "type":"Manufacturing & Wholesale Goods"
        }
    ],
    "sg:phone":"+32 56 56 56 56",
    "sg:postcode":"7782",
    "sg:province":"Hainaut",
    "sg:tags":[
        "masonry",
        "brick",
        "fired"
    ],
    "wof:name":"Ploegsteert Steenbakkerijen Nv",
    "wof:placetype":"venue"
},
  "geometry": {"coordinates":[2.8795371056,50.7278747559],"type":"Point"}
}