{
  "type": "Feature",
  "properties": {
    "iso:country":"BE",
    "sg:address":"Delacenseriestraat 20",
    "sg:city":"De Haan",
    "sg:classifiers":[
        {
            "category":"Personal",
            "subcategory":"Beauty Salon",
            "type":"Services"
        }
    ],
    "sg:phone":"+32 50 41 41 81",
    "sg:postcode":"8420",
    "sg:province":"West-Vlaanderen",
    "sg:tags":[
        "de",
        "coiffure"
    ],
    "wof:name":"Frans Honorez",
    "wof:placetype":"venue"
},
  "geometry": {"coordinates":[3.0793740749,51.3003349304],"type":"Point"}
}