{
  "type": "Feature",
  "properties": {
    "addr:full":"Rue Rikir 30 Vise Li\u00e8ge 4602",
    "addr:housenumber":"30",
    "addr:postcode":"4602",
    "addr:street":"Rue Rikir",
    "iso:country":"BE",
    "sg:address":"Rue Rikir 30",
    "sg:city":"Vise",
    "sg:orig_category":"Gespecialiseerde residenti\u00eble bouw",
    "sg:phone":"+32 4 362 81 68",
    "sg:postcode":"4602",
    "sg:province":"Li\u00e8ge",
    "wof:name":"Adam Francis",
    "wof:placetype":"venue"
},
  "geometry": {"coordinates":[5.6851601601,50.685131073],"type":"Point"}
}