{
  "type": "Feature",
  "properties": {
    "addr:full":"Rue D'argile 4 Kraainem/kraainem Vlaams-Brabant 1950",
    "addr:housenumber":"4",
    "addr:postcode":"1950",
    "addr:street":"Rue D'Argile",
    "iso:country":"BE",
    "sg:address":"Rue D'argile 4",
    "sg:city":"Kraainem/kraainem",
    "sg:orig_category":"Disquaires",
    "sg:phone":"+32 2 731 63 62",
    "sg:postcode":"1950",
    "sg:province":"Vlaams-Brabant",
    "wof:name":"Mark Sound",
    "wof:placetype":"venue"
},
  "geometry": {"coordinates":[4.4671931267,50.8402938843],"type":"Point"}
}