{
  "type": "Feature",
  "properties": {
    "iso:country":"BE",
    "sg:address":"Hanegraefstraat 32b15",
    "sg:city":"Antwerpen",
    "sg:orig_category":"Entretien and r\u00e9parations de machines de bureau and ordinateurs. Ordinateurs and \u00e9quipement informat",
    "sg:phone":"+32 3 219 56 87",
    "sg:postcode":"2050",
    "sg:province":"Antwerpen",
    "wof:name":"Patrick Heylen",
    "wof:placetype":"venue"
},
  "geometry": {"coordinates":[4.3795599937,51.2190589905],"type":"Point"}
}