{
  "type": "Feature",
  "properties": {
    "iso:country":"BE",
    "sg:address":"Antwerpse Steenweg 97",
    "sg:city":"Sint-niklaas",
    "sg:orig_category":"Bloemen and planten",
    "sg:phone":"+32 3 776 28 54",
    "sg:postcode":"9100",
    "sg:province":"Oost-Vlaanderen",
    "wof:name":"Mega 1001 Store",
    "wof:placetype":"venue"
},
  "geometry": {"coordinates":[4.1474871635,51.146232605],"type":"Point"}
}