{
  "type": "Feature",
  "properties": {
    "addr:full":"Rue Du Centre 73 Tinlot (soheit-tinlot) Li\u00e8ge 4557",
    "addr:housenumber":"73",
    "addr:postcode":"4557",
    "addr:street":"Rue Du Centre;Soheit-Tinlot",
    "iso:country":"BE",
    "sg:address":"Rue Du Centre 73",
    "sg:city":"Tinlot (soheit-tinlot)",
    "sg:classifiers":[
        {
            "category":"Shopping",
            "subcategory":"Bicycles & Sporting Goods",
            "type":"Retail Goods"
        }
    ],
    "sg:phone":"+32 85 51 19 51",
    "sg:postcode":"4557",
    "sg:province":"Li\u00e8ge",
    "sg:tags":[
        "equipment",
        "camping"
    ],
    "wof:name":"Levooz Auvents De Caravanes",
    "wof:placetype":"venue"
},
  "geometry": {"coordinates":[5.37830019,50.4777183533],"type":"Point"}
}