{
  "type": "Feature",
  "properties": {
    "addr:full":"Koning Albert L-laan 33 Roeselare West-Vlaanderen 8800",
    "addr:housenumber":"33",
    "addr:postcode":"8800",
    "addr:street":"Koning Albert L-Laan",
    "iso:country":"BE",
    "sg:address":"Koning Albert L-laan 33",
    "sg:city":"Roeselare",
    "sg:orig_category":"Telecommunicatieapparaten",
    "sg:phone":"+32 51 25 33 65",
    "sg:postcode":"8800",
    "sg:province":"West-Vlaanderen",
    "wof:name":"Debussere",
    "wof:placetype":"venue"
},
  "geometry": {"coordinates":[3.1313230991,50.9418792725],"type":"Point"}
}