{
  "type": "Feature",
  "properties": {
    "iso:country":"BE",
    "sg:address":"Rue Vaudr\u00e9e 105 Box 26",
    "sg:city":"Li\u00e8ge 1 (angleur)",
    "sg:classifiers":[
        {
            "category":"Health Services",
            "subcategory":"Doctor",
            "type":"Services"
        }
    ],
    "sg:phone":"+32 4 367 14 68",
    "sg:postcode":"4031",
    "sg:province":"Li\u00e8ge",
    "sg:tags":[
        "medicinephysicians",
        "surgeon"
    ],
    "wof:name":"Dioh Alioune",
    "wof:placetype":"venue"
},
  "geometry": {"coordinates":[5.5939569473,50.6125602722],"type":"Point"}
}