{
  "type": "Feature",
  "properties": {
    "iso:country":"BE",
    "sg:address":"Hogenakkerstraat 113",
    "sg:city":"Sint-niklaas",
    "sg:orig_category":"Assurances. Bureaux de poste",
    "sg:phone":"+32 3 776 37 89",
    "sg:postcode":"9100",
    "sg:province":"Oost-Vlaanderen",
    "wof:name":"De Post",
    "wof:placetype":"venue"
},
  "geometry": {"coordinates":[4.1594371796,51.165019989],"type":"Point"}
}