{
  "type": "Feature",
  "properties": {
    "addr:full":"Westkerkestraat 3 Ichtegem West-Vlaanderen 8480",
    "addr:housenumber":"3",
    "addr:postcode":"8480",
    "addr:street":"Westkerkestraat",
    "iso:country":"BE",
    "sg:address":"Westkerkestraat 3",
    "sg:city":"Ichtegem",
    "sg:orig_category":"Opticiens",
    "sg:phone":"+32 59 29 90 70",
    "sg:postcode":"8480",
    "sg:province":"West-Vlaanderen",
    "wof:name":"Optiek Ter Duinen",
    "wof:placetype":"venue"
},
  "geometry": {"coordinates":[3.0273890495,51.1305427551],"type":"Point"}
}