{
  "type": "Feature",
  "properties": {
    "iso:country":"BE",
    "sg:address":"Boeretangsedreef 1",
    "sg:city":"Dessel",
    "sg:orig_category":"Location d'articles de sport, de sport nautique and de camping. V\u00e9los",
    "sg:phone":"+32 14 37 73 73",
    "sg:postcode":"2480",
    "sg:province":"Antwerpen",
    "wof:name":"Fietsen Luc Smets",
    "wof:placetype":"venue"
},
  "geometry": {"coordinates":[5.1069421768,51.2389259338],"type":"Point"}
}