{
  "type": "Feature",
  "properties": {
    "iso:country":"BE",
    "sg:address":"Boomsesteenweg 444",
    "sg:city":"Antwerpen",
    "sg:orig_category":"Apotheken",
    "sg:phone":"+32 3 237 71 20",
    "sg:postcode":"2020",
    "sg:province":"Antwerpen",
    "wof:name":"A. Wymeersch",
    "wof:placetype":"venue"
},
  "geometry": {"coordinates":[4.388625145,51.1847763062],"type":"Point"}
}