{
  "type": "Feature",
  "properties": {
    "addr:full":"Onze-lieve-vrouwstraat 207 Heusden-zolder Limburg 3550",
    "addr:housenumber":"207",
    "addr:postcode":"3550",
    "addr:street":"Onze-Lieve-Vrouwstraat",
    "iso:country":"BE",
    "sg:address":"Onze-lieve-vrouwstraat 207",
    "sg:city":"Heusden-zolder",
    "sg:orig_category":"Installation \u00e9lectrique r\u00e9sidentielle",
    "sg:phone":"+32 11 53 74 87",
    "sg:postcode":"3550",
    "sg:province":"Limburg",
    "wof:name":"Peters",
    "wof:placetype":"venue"
},
  "geometry": {"coordinates":[5.2669157982,51.0093803406],"type":"Point"}
}