{
  "type": "Feature",
  "properties": {
    "iso:country":"BE",
    "sg:address":"Avenue De La Salm 24",
    "sg:city":"Trois-ponts - Fosse",
    "sg:classifiers":[
        {
            "category":"Personal",
            "subcategory":"Beauty Salon",
            "type":"Services"
        }
    ],
    "sg:phone":"+32 80 31 84 96",
    "sg:postcode":"4980",
    "sg:province":"Li\u00e8ge",
    "sg:tags":[
        "lady",
        "-",
        "hairdressing"
    ],
    "wof:name":"Ligne Du Temps",
    "wof:placetype":"venue"
},
  "geometry": {"coordinates":[5.8739700317,50.3665008545],"type":"Point"}
}