{
  "type": "Feature",
  "properties": {
    "iso:country":"BE",
    "sg:address":"Rue De La Station 152",
    "sg:city":"Jemeppe-sur-sambre",
    "sg:orig_category":"Pain, p\u00e2tisseries and confiseries",
    "sg:phone":"+32 71 78 36 66",
    "sg:postcode":"5190",
    "sg:province":"Namur",
    "wof:name":"Boulangerie L\u00b4epi D\u00b4or",
    "wof:placetype":"venue"
},
  "geometry": {"coordinates":[4.694975853,50.4547958374],"type":"Point"}
}