{
  "type": "Feature",
  "properties": {
    "iso:country":"BE",
    "sg:address":"Gransveldestraat 8",
    "sg:city":"Wetteren",
    "sg:classifiers":[
        {
            "category":"Bars & Pubs",
            "type":"Food & Drink"
        }
    ],
    "sg:phone":"+32 9 366 29 98",
    "sg:postcode":"9230",
    "sg:province":"Oost-Vlaanderen",
    "wof:name":"Paal (de)",
    "wof:placetype":"venue"
},
  "geometry": {"coordinates":[3.8734300137,51.0145072937],"type":"Point"}
}