{
  "type": "Feature",
  "properties": {
    "iso:country":"BE",
    "sg:address":"Lokouter 10",
    "sg:city":"Aalter",
    "sg:orig_category":"Installatie van houten of kunststof schrijnwerk",
    "sg:phone":"+32 51 68 92 89",
    "sg:postcode":"9880",
    "sg:province":"Oost-Vlaanderen",
    "wof:name":"Patrick Schoutteet",
    "wof:placetype":"venue"
},
  "geometry": {"coordinates":[3.4659850597,51.0499229431],"type":"Point"}
}