{
  "type": "Feature",
  "properties": {
    "addr:full":"Rue De La Plagne 12 Fontaine-l'ev\u00caque Hainaut 6142",
    "addr:housenumber":"12",
    "addr:postcode":"6142",
    "addr:street":"Rue De La Plagne;\u0302Que Hainaut",
    "iso:country":"BE",
    "sg:address":"Rue De La Plagne 12",
    "sg:city":"Fontaine-l'ev\u00caque",
    "sg:orig_category":"Boekhouders",
    "sg:phone":"+32 71 52 38 78",
    "sg:postcode":"6142",
    "sg:province":"Hainaut",
    "wof:name":"P. D'hoedt",
    "wof:placetype":"venue"
},
  "geometry": {"coordinates":[-111.9644622803,46.2507972717],"type":"Point"}
}