{
  "type": "Feature",
  "properties": {
    "iso:country":"BE",
    "sg:address":"Grotestraat 57",
    "sg:city":"Geraardsbergen",
    "sg:orig_category":"Textiles. Eclairage et \u00e9quipements du foyer",
    "sg:phone":"+32 54 41 09 80",
    "sg:postcode":"9500",
    "sg:province":"Oost-Vlaanderen",
    "wof:name":"Draperiehuis",
    "wof:placetype":"venue"
},
  "geometry": {"coordinates":[3.8773100376,50.7719345093],"type":"Point"}
}