{
  "type": "Feature",
  "properties": {
    "addr:full":"Karreweg 135 Kruishoutem Oost-Vlaanderen 9770",
    "addr:housenumber":"135",
    "addr:postcode":"9770",
    "iso:country":"BE",
    "sg:address":"Karreweg 135",
    "sg:city":"Kruishoutem",
    "sg:orig_category":"Diverse bedrijfsbeheeradviesbureaus",
    "sg:phone":"+32 9 388 78 37",
    "sg:postcode":"9770",
    "sg:province":"Oost-Vlaanderen",
    "wof:name":"Alpha-com Belgium",
    "wof:placetype":"venue"
},
  "geometry": {"coordinates":[3.4890658855,50.918170929],"type":"Point"}
}