{
  "type": "Feature",
  "properties": {
    "iso:country":"BE",
    "sg:address":"Quai De L'industrie 103",
    "sg:city":"Bruxelles (molenbeek-saint-jean)",
    "sg:classifiers":[
        {
            "category":"Retail",
            "subcategory":"Repair Shop",
            "type":"Services"
        }
    ],
    "sg:phone":"+32 2 522 11 14",
    "sg:postcode":"1080",
    "sg:province":"Bruxelles-Capitale",
    "sg:tags":[
        "upholsterer"
    ],
    "wof:name":"De Saeger Ets",
    "wof:placetype":"venue"
},
  "geometry": {"coordinates":[4.3294248581,50.8466644287],"type":"Point"}
}