{
  "type": "Feature",
  "properties": {
    "addr:full":"Rue Du Domaine De N\u00e9gri 7 Ottignies-louvain-la-neuve (c\u00e9roux-mousty) Brabant Wallon 1341",
    "addr:housenumber":"7",
    "addr:postcode":"1341",
    "addr:street":"Rue Du Domaine De Ne\u0301Gri;Ce\u0301Roux-Mousty;Wallon",
    "iso:country":"BE",
    "sg:address":"Rue Du Domaine De N\u00e9gri 7",
    "sg:city":"Ottignies-louvain-la-neuve (c\u00e9roux-mousty)",
    "sg:classifiers":[
        {
            "category":"Professional",
            "type":"Services"
        }
    ],
    "sg:phone":"+32 10 61 68 81",
    "sg:postcode":"1341",
    "sg:province":"Brabant Wallon",
    "sg:tags":[
        "entertainer"
    ],
    "wof:name":"Fakir Rams\u00e8s",
    "wof:placetype":"venue"
},
  "geometry": {"coordinates":[4.5627598763,50.6583099365],"type":"Point"}
}