{
  "type": "Feature",
  "properties": {
    "addr:full":"Oude Lendeleedsestraat 2 Lede West-Vlaanderen 8880",
    "addr:housenumber":"2",
    "addr:postcode":"8880",
    "addr:street":"Oude Lendeleedsestraat",
    "iso:country":"BE",
    "sg:address":"Oude Lendeleedsestraat 2",
    "sg:city":"Lede",
    "sg:orig_category":"Diverse bedrijfsbeheeradviesbureaus",
    "sg:phone":"+32 56 50 41 45",
    "sg:postcode":"8880",
    "sg:province":"West-Vlaanderen",
    "wof:name":"A.&c. Bedrijfsadvies",
    "wof:placetype":"venue"
},
  "geometry": {"coordinates":[3.1824810505,50.877494812],"type":"Point"}
}