{
  "type": "Feature",
  "properties": {
    "addr:full":"Hildering 22 Vorselaar Antwerpen 2290",
    "addr:housenumber":"22",
    "addr:postcode":"2290",
    "addr:street":"Hildering",
    "iso:country":"BE",
    "sg:address":"Hildering 22",
    "sg:city":"Vorselaar",
    "sg:orig_category":"Installatie van houten of kunststof schrijnwerk Woningbouw",
    "sg:phone":"+32 14 51 37 32",
    "sg:postcode":"2290",
    "sg:province":"Antwerpen",
    "wof:name":"Webo",
    "wof:placetype":"venue"
},
  "geometry": {"coordinates":[4.7626881599,51.1995773315],"type":"Point"}
}