{
  "type": "Feature",
  "properties": {
    "addr:full":"Leiestraat 29 Kortrijk West-Vlaanderen 8500",
    "addr:housenumber":"29",
    "addr:postcode":"8500",
    "addr:street":"Leiestraat",
    "iso:country":"BE",
    "sg:address":"Leiestraat 29",
    "sg:city":"Kortrijk",
    "sg:orig_category":"Tijdelijke werkgelegenheid and uitzendkantoren",
    "sg:phone":"+32 56 20 33 99",
    "sg:postcode":"8500",
    "sg:province":"West-Vlaanderen",
    "wof:name":"Creyf\u00b4s Interim",
    "wof:placetype":"venue"
},
  "geometry": {"coordinates":[3.2643880844,50.8288917542],"type":"Point"}
}