{
  "type": "Feature",
  "properties": {
    "addr:full":"Terelststraat 69 Edegem Antwerpen 2650",
    "addr:housenumber":"69",
    "addr:postcode":"2650",
    "addr:street":"Terelststraat",
    "iso:country":"BE",
    "sg:address":"Terelststraat 69",
    "sg:city":"Edegem",
    "sg:orig_category":"Enseignement artistique",
    "sg:phone":"+32 3 289 23 60",
    "sg:postcode":"2650",
    "sg:province":"Antwerpen",
    "wof:name":"Academie Voor Muziek En Woord",
    "wof:placetype":"venue"
},
  "geometry": {"coordinates":[4.4411320686,51.1552696228],"type":"Point"}
}