{
  "type": "Feature",
  "properties": {
    "addr:full":"Rue Mahy 14 Momignies Hainaut 6590",
    "addr:housenumber":"14",
    "addr:postcode":"6590",
    "addr:street":"Rue Mahy;Hainaut",
    "iso:country":"BE",
    "sg:address":"Rue Mahy 14",
    "sg:city":"Momignies",
    "sg:classifiers":[
        {
            "category":"Freight",
            "type":"Transportation"
        }
    ],
    "sg:phone":"+32 60 51 10 59",
    "sg:postcode":"6590",
    "sg:province":"Hainaut",
    "sg:tags":[
        "-",
        "transport"
    ],
    "wof:name":"Demaret & Fils Sprl",
    "wof:placetype":"venue"
},
  "geometry": {"coordinates":[4.1623687744,50.0228309631],"type":"Point"}
}