{
  "type": "Feature",
  "properties": {
    "addr:full":"Entrepotstraat 3 Sint-niklaas Oost-Vlaanderen 9100",
    "addr:housenumber":"3",
    "addr:postcode":"9100",
    "addr:street":"Entrepotstraat",
    "iso:country":"BE",
    "sg:address":"Entrepotstraat 3",
    "sg:city":"Sint-niklaas",
    "sg:orig_category":"Studios photographiques",
    "sg:phone":"+32 3 760 11 20",
    "sg:postcode":"9100",
    "sg:province":"Oost-Vlaanderen",
    "wof:name":"Epts",
    "wof:placetype":"venue"
},
  "geometry": {"coordinates":[4.1672339439,51.174987793],"type":"Point"}
}