{
  "type": "Feature",
  "properties": {
    "iso:country":"BE",
    "sg:address":"Roeselaarsestraat 45",
    "sg:city":"Kortrijk (heule)",
    "sg:classifiers":[
        {
            "category":"Government",
            "subcategory":"Fire Station",
            "type":"Public Place"
        }
    ],
    "sg:phone":"+32 56 35 54 76",
    "sg:postcode":"8501",
    "sg:province":"West-Vlaanderen",
    "sg:tags":[
        "detection",
        "installation",
        "material",
        "-"
    ],
    "wof:name":"Elg Nv",
    "wof:placetype":"venue"
},
  "geometry": {"coordinates":[3.2232279778,50.8480033875],"type":"Point"}
}