{
  "type": "Feature",
  "properties": {
    "addr:full":"Lombardsijdelaan 156 Middelkerke (westende) West-Vlaanderen 8434",
    "addr:housenumber":"156",
    "addr:postcode":"8434",
    "addr:street":"Lombardsijdelaan",
    "iso:country":"BE",
    "sg:address":"Lombardsijdelaan 156",
    "sg:city":"Middelkerke (westende)",
    "sg:orig_category":"Non-Classified Establishments",
    "sg:phone":"+32 58 23 32 99",
    "sg:postcode":"8434",
    "sg:province":"West-Vlaanderen",
    "wof:name":"Scootercenter V.f. Racing",
    "wof:placetype":"venue"
},
  "geometry": {"coordinates":[2.7578699589,51.1500511169],"type":"Point"}
}