{
  "type": "Feature",
  "properties": {
    "iso:country":"BE",
    "sg:address":"Lampettenstraat 2",
    "sg:city":"Ingelmunster",
    "sg:orig_category":"Eleveurs and marchands de porcs",
    "sg:phone":"+32 51 30 16 03",
    "sg:postcode":"8770",
    "sg:province":"West-Vlaanderen",
    "wof:name":"Johan Pieters",
    "wof:placetype":"venue"
},
  "geometry": {"coordinates":[3.26978302,50.9303855896],"type":"Point"}
}