{
  "type": "Feature",
  "properties": {
    "addr:full":"Reistraat 9 Lanaken Limburg 3620",
    "addr:housenumber":"9",
    "addr:postcode":"3620",
    "addr:street":"Reistraat",
    "iso:country":"BE",
    "sg:address":"Reistraat 9",
    "sg:city":"Lanaken",
    "sg:orig_category":"Kapsalons Speciaalzaken",
    "sg:phone":"+32 89 71 12 12",
    "sg:postcode":"3620",
    "sg:province":"Limburg",
    "wof:name":"Coiffure Emile",
    "wof:placetype":"venue"
},
  "geometry": {"coordinates":[5.6551351547,50.8912277222],"type":"Point"}
}