{
  "type": "Feature",
  "properties": {
    "iso:country":"BE",
    "sg:address":"Avenue Albert Einstein 11d",
    "sg:city":"Louvain-la-neuve",
    "sg:classifiers":[
        {
            "category":"Organizations",
            "subcategory":"Non-profit Organization",
            "type":"Services"
        }
    ],
    "sg:phone":"+32 10 45 26 36",
    "sg:postcode":"1348",
    "sg:province":"Brabant Wallon",
    "sg:tags":[
        "information",
        "system",
        "indicating"
    ],
    "wof:name":"Alpha Electronics Europe S.a.",
    "wof:placetype":"venue"
},
  "geometry": {"coordinates":[4.6297311783,50.66456604],"type":"Point"}
}