{
  "type": "Feature",
  "properties": {
    "iso:country":"BE",
    "sg:address":"Rue Hoyoux 135",
    "sg:city":"Herstal",
    "sg:orig_category":"M\u00e9decins and sp\u00e9cialistes",
    "sg:phone":"+32 4 264 34 40",
    "sg:postcode":"4040",
    "sg:province":"Li\u00e8ge",
    "wof:name":"L. Deltombe",
    "wof:placetype":"venue"
},
  "geometry": {"coordinates":[5.6256160736,50.6606674194],"type":"Point"}
}