{
  "type": "Feature",
  "properties": {
    "iso:country":"BE",
    "sg:address":"Prumer Strasse 17",
    "sg:city":"Sankt Vith/saint-vith",
    "sg:orig_category":"Herstellingen and onderhoud van auto's",
    "sg:phone":"+32 80 54 81 08",
    "sg:postcode":"4780",
    "sg:province":"Li\u00e8ge",
    "wof:name":"Garage Inh Bach",
    "wof:placetype":"venue"
},
  "geometry": {"coordinates":[6.0429549217,50.3349761963],"type":"Point"}
}