{
  "type": "Feature",
  "properties": {
    "iso:country":"BE",
    "sg:address":"Geenrijt 11",
    "sg:city":"Heusden-zolder",
    "sg:classifiers":[
        {
            "category":"Home & Garden",
            "subcategory":"Carpets & Floor Coverings",
            "type":"Retail Goods"
        }
    ],
    "sg:phone":"+32 11 42 27 79",
    "sg:postcode":"3550",
    "sg:province":"Limburg",
    "sg:tags":[
        "commerce",
        "equipement",
        "de",
        "\u00e9v\u00e9nements",
        "pour",
        "diver",
        "bien",
        "mat\u00e9riel",
        "location",
        "banquet"
    ],
    "wof:name":"Luc Dries",
    "wof:placetype":"venue"
},
  "geometry": {"coordinates":[5.2789678574,51.037361145],"type":"Point"}
}