{
  "type": "Feature",
  "properties": {
    "addr:full":"Rue De La Carri\u00e8re 1-3 Fl\u00e9ron (magn\u00e9e) Li\u00e8ge 4623",
    "addr:housenumber":"1-3",
    "addr:postcode":"4623",
    "addr:street":"Rue De La Carrie\u0300Re",
    "iso:country":"BE",
    "sg:address":"Rue De La Carri\u00e8re 1-3",
    "sg:city":"Fl\u00e9ron (magn\u00e9e)",
    "sg:classifiers":[
        {
            "category":"Food & Beverages",
            "subcategory":"Groceries & Convenience Stores",
            "type":"Retail Goods"
        }
    ],
    "sg:phone":"+32 4 358 24 94",
    "sg:postcode":"4623",
    "sg:province":"Li\u00e8ge",
    "sg:tags":[
        "grocer"
    ],
    "wof:name":"Garde-manger",
    "wof:placetype":"venue"
},
  "geometry": {"coordinates":[5.6808691025,50.6038589478],"type":"Point"}
}