{
  "type": "Feature",
  "properties": {
    "addr:full":"Gierstraat 11 Antwerpen Antwerpen 2000",
    "addr:housenumber":"11",
    "addr:postcode":"2000",
    "addr:street":"Gierstraat",
    "iso:country":"BE",
    "sg:address":"Gierstraat 11",
    "sg:city":"Antwerpen",
    "sg:classifiers":[
        {
            "category":"Arts & Performance",
            "subcategory":"Art Gallery",
            "type":"Entertainment"
        }
    ],
    "sg:phone":"+32 3 231 22 50",
    "sg:postcode":"2000",
    "sg:province":"Antwerpen",
    "wof:name":"Palumbus",
    "wof:placetype":"venue"
},
  "geometry": {"coordinates":[4.4001169205,51.2183685303],"type":"Point"}
}