{
  "type": "Feature",
  "properties": {
    "iso:country":"BE",
    "sg:address":"Gaversesteenweg 118",
    "sg:city":"Oosterzele",
    "sg:orig_category":"Boucheries",
    "sg:phone":"+32 9 362 53 79",
    "sg:postcode":"9860",
    "sg:province":"Oost-Vlaanderen",
    "wof:name":"Andre Cnudde",
    "wof:placetype":"venue"
},
  "geometry": {"coordinates":[3.7553119659,50.9347457886],"type":"Point"}
}