{
  "type": "Feature",
  "properties": {
    "iso:country":"BE",
    "sg:address":"Acul 1",
    "sg:city":"Sainte-ode",
    "sg:orig_category":"Rundveehouders",
    "sg:phone":"+32 61 68 87 10",
    "sg:postcode":"6680",
    "sg:province":"Luxembourg",
    "wof:name":"Andre Duplicy",
    "wof:placetype":"venue"
},
  "geometry": {"coordinates":[5.5304489136,50.0108299255],"type":"Point"}
}