{
  "type": "Feature",
  "properties": {
    "addr:full":"Mechelbaan 97 Lier Antwerpen 2500",
    "addr:housenumber":"97",
    "addr:postcode":"2500",
    "addr:street":"Mechelbaan",
    "iso:country":"BE",
    "sg:address":"Mechelbaan 97",
    "sg:city":"Lier",
    "sg:orig_category":"Chaussures",
    "sg:phone":"+32 3 422 50 38",
    "sg:postcode":"2500",
    "sg:province":"Antwerpen",
    "wof:name":"De Meyer Chris",
    "wof:placetype":"venue"
},
  "geometry": {"coordinates":[4.6077899933,51.0892486572],"type":"Point"}
}