{
  "type": "Feature",
  "properties": {
    "iso:country":"BE",
    "sg:address":"Steenweg 23",
    "sg:city":"Asse",
    "sg:orig_category":"Chaussures. Maroquinerie and articles de voyage",
    "sg:phone":"+32 2 453 19 91",
    "sg:postcode":"1730",
    "sg:province":"Vlaams-Brabant",
    "wof:name":"Torfs Schoenen",
    "wof:placetype":"venue"
},
  "geometry": {"coordinates":[4.1977310181,50.9110565186],"type":"Point"}
}