{
  "type": "Feature",
  "properties": {
    "addr:full":"Kerkstraat 79 Blankenberge West-Vlaanderen 8370",
    "addr:housenumber":"79",
    "addr:postcode":"8370",
    "addr:street":"Kerkstraat",
    "iso:country":"BE",
    "sg:address":"Kerkstraat 79",
    "sg:city":"Blankenberge",
    "sg:classifiers":[
        {
            "category":"Tea Room",
            "subcategory":"None",
            "type":"Food & Drink"
        }
    ],
    "sg:phone":"+32 50 41 51 79",
    "sg:postcode":"8370",
    "sg:province":"West-Vlaanderen",
    "wof:name":"Elan",
    "wof:placetype":"venue"
},
  "geometry": {"coordinates":[3.1300609112,51.3142242432],"type":"Point"}
}