{
  "type": "Feature",
  "properties": {
    "iso:country":"BE",
    "sg:address":"Graaf Van Landaststraat 115",
    "sg:city":"Oudenaarde",
    "sg:orig_category":"V\u00e9hicules automobiles. Entretien and r\u00e9parations de voitures",
    "sg:phone":"+32 55 31 15 00",
    "sg:postcode":"9700",
    "sg:province":"Oost-Vlaanderen",
    "wof:name":"Garage De Schelde",
    "wof:placetype":"venue"
},
  "geometry": {"coordinates":[3.6178519726,50.8772163391],"type":"Point"}
}