{
  "type": "Feature",
  "properties": {
    "addr:full":"Kronkelstraat 7 Retie Antwerpen 2470",
    "addr:housenumber":"7",
    "addr:postcode":"2470",
    "addr:street":"Kronkelstraat",
    "iso:country":"BE",
    "sg:address":"Kronkelstraat 7",
    "sg:city":"Retie",
    "sg:orig_category":"Mus\u00e9es and patrimoine culturel",
    "sg:phone":"+32 14 81 45 94",
    "sg:postcode":"2470",
    "sg:province":"Antwerpen",
    "wof:name":"De Heerser",
    "wof:placetype":"venue"
},
  "geometry": {"coordinates":[5.0734529495,51.2789649963],"type":"Point"}
}