{
  "type": "Feature",
  "properties": {
    "iso:country":"BE",
    "sg:address":"Rue Michel Servet 91-3",
    "sg:city":"Seraing",
    "sg:classifiers":[
        {
            "category":"Building & Trades",
            "subcategory":"Construction",
            "type":"Services"
        }
    ],
    "sg:phone":"+32 4 336 88 19",
    "sg:postcode":"4100",
    "sg:province":"Li\u00e8ge",
    "sg:tags":[
        "carpenter"
    ],
    "wof:name":"Acampo J",
    "wof:placetype":"venue"
},
  "geometry": {"coordinates":[5.5255041122,50.5980148315],"type":"Point"}
}