{
  "type": "Feature",
  "properties": {
    "iso:country":"BE",
    "sg:address":"Chemin Des Mourdreux 5a",
    "sg:city":"Mons",
    "sg:classifiers":[
        {
            "category":"Professional",
            "subcategory":"Testing Lab",
            "type":"Services"
        }
    ],
    "sg:phone":"+32 65 33 66 15",
    "sg:postcode":"7000",
    "sg:province":"Hainaut",
    "sg:tags":[
        "chemist"
    ],
    "wof:name":"De Neef N",
    "wof:placetype":"venue"
},
  "geometry": {"coordinates":[3.9797730446,50.4531364441],"type":"Point"}
}