{
  "type": "Feature",
  "properties": {
    "iso:country":"BE",
    "sg:address":"Westerloseweg 12",
    "sg:city":"Geel",
    "sg:classifiers":[
        {
            "category":"Health Services",
            "subcategory":"Health Practitioner",
            "type":"Services"
        }
    ],
    "sg:phone":"+32 14 54 45 31",
    "sg:postcode":"2440",
    "sg:province":"Antwerpen",
    "sg:tags":[
        "physiotherapist"
    ],
    "wof:name":"Vleugels S",
    "wof:placetype":"venue"
},
  "geometry": {"coordinates":[4.9431967735,51.0966339111],"type":"Point"}
}