{
  "type": "Feature",
  "properties": {
    "addr:full":"Kattendijkdok Westkaai 21 Antwerpen Antwerpen 2000",
    "addr:housenumber":"21",
    "addr:postcode":"2000",
    "addr:street":"Westkaai",
    "iso:country":"BE",
    "sg:address":"Kattendijkdok Westkaai 21",
    "sg:city":"Antwerpen",
    "sg:classifiers":[
        {
            "category":"Professional",
            "subcategory":"Employment Agencies",
            "type":"Services"
        }
    ],
    "sg:phone":"+32 3 545 06 11",
    "sg:postcode":"2000",
    "sg:province":"Antwerpen",
    "sg:tags":[
        "shipping"
    ],
    "wof:name":"Hapag-lloyd Belgium Nv",
    "wof:placetype":"venue"
},
  "geometry": {"coordinates":[4.404902935,51.2324409485],"type":"Point"}
}