{
  "type": "Feature",
  "properties": {
    "iso:country":"BE",
    "sg:address":"Oscar Van Kesbeeckstraat 9b602",
    "sg:city":"Mechelen",
    "sg:classifiers":[
        {
            "category":"Organizations",
            "subcategory":"Community Association",
            "type":"Services"
        }
    ],
    "sg:phone":"+32 15 21 15 48",
    "sg:postcode":"2800",
    "sg:province":"Antwerpen",
    "sg:tags":[
        "organisation"
    ],
    "wof:name":"J.a. Vrijzinnig Ja",
    "wof:placetype":"venue"
},
  "geometry": {"coordinates":[4.4728507996,51.0356063843],"type":"Point"}
}