{
  "type": "Feature",
  "properties": {
    "iso:country":"BE",
    "sg:address":"Rue De L'eglise 46",
    "sg:city":"Beyne-heusay",
    "sg:orig_category":"Pain, p\u00e2tisseries and confiseries",
    "sg:phone":"+32 4 362 66 08",
    "sg:postcode":"4610",
    "sg:province":"Li\u00e8ge",
    "wof:name":"Boulangerie Massart",
    "wof:placetype":"venue"
},
  "geometry": {"coordinates":[5.6661520004,50.6447715759],"type":"Point"}
}