{
  "type": "Feature",
  "properties": {
    "iso:country":"BE",
    "sg:address":"Botermarkt 9",
    "sg:city":"Herenthout",
    "sg:classifiers":[
        {
            "category":"Fast Food",
            "type":"Food & Drink"
        }
    ],
    "sg:phone":"+32 14 51 77 26",
    "sg:postcode":"2270",
    "sg:province":"Antwerpen",
    "sg:tags":[
        "\u00c0",
        "emporter",
        "restaurants"
    ],
    "wof:name":"Frituur Leo",
    "wof:placetype":"venue"
},
  "geometry": {"coordinates":[4.755918026,51.1396598816],"type":"Point"}
}