{
  "type": "Feature",
  "properties": {
    "addr:full":"Rue Blanche 2 Libramont-chevigny Luxembourg 6800",
    "addr:housenumber":"2",
    "addr:postcode":"6800",
    "addr:street":"Rue Blanche",
    "iso:country":"BE",
    "sg:address":"Rue Blanche 2",
    "sg:city":"Libramont-chevigny",
    "sg:orig_category":"Landmeters",
    "sg:phone":"+32 61 22 30 91",
    "sg:postcode":"6800",
    "sg:province":"Luxembourg",
    "wof:name":"Fernand Guebs",
    "wof:placetype":"venue"
},
  "geometry": {"coordinates":[5.3627028465,49.9164466858],"type":"Point"}
}