{
  "type": "Feature",
  "properties": {
    "addr:full":"Rue De Renory 28 Ougr\u00e9e Li\u00e8ge 4102",
    "addr:housenumber":"28",
    "addr:postcode":"4102",
    "addr:street":"Rue De Renory",
    "iso:country":"BE",
    "sg:address":"Rue De Renory 28",
    "sg:city":"Ougr\u00e9e",
    "sg:classifiers":[
        {
            "category":"Manufacturing",
            "subcategory":"Soap",
            "type":"Manufacturing & Wholesale Goods"
        }
    ],
    "sg:phone":"+32 4 338 93 89",
    "sg:postcode":"4102",
    "sg:province":"Li\u00e8ge",
    "sg:tags":[
        "raw",
        "material",
        "detergent"
    ],
    "wof:name":"Manro S.a.",
    "wof:placetype":"venue"
},
  "geometry": {"coordinates":[5.5570697784,50.6038017273],"type":"Point"}
}