{
  "type": "Feature",
  "properties": {
    "addr:full":"Strandlaan 132 Koksijde West-Vlaanderen 8670",
    "addr:housenumber":"132",
    "addr:postcode":"8670",
    "addr:street":"Strandlaan",
    "iso:country":"BE",
    "sg:address":"Strandlaan 132",
    "sg:city":"Koksijde",
    "sg:classifiers":[
        {
            "category":"Cafe",
            "type":"Food & Drink"
        }
    ],
    "sg:phone":"+32 58 51 11 46",
    "sg:postcode":"8670",
    "sg:province":"West-Vlaanderen",
    "sg:tags":[
        "caf\u00e9s"
    ],
    "wof:name":"Caf\u00c9 Lusthof",
    "wof:placetype":"venue"
},
  "geometry": {"coordinates":[2.6179280281,51.1038665771],"type":"Point"}
}