{
  "type": "Feature",
  "properties": {
    "iso:country":"BE",
    "sg:address":"Hogesteenweg 24",
    "sg:city":"Grimbergen",
    "sg:classifiers":[
        {
            "category":"Banks & Credit Unions",
            "subcategory":"Bank",
            "type":"Services"
        }
    ],
    "sg:phone":"+32 2 270 29 20",
    "sg:postcode":"1850",
    "sg:province":"Vlaams-Brabant",
    "wof:name":"Argenta Spaarbank Grimbergen",
    "wof:placetype":"venue"
},
  "geometry": {"coordinates":[4.3723249435,50.9331855774],"type":"Point"}
}