{
  "type": "Feature",
  "properties": {
    "iso:country":"BE",
    "sg:address":"Kloosterweg 2",
    "sg:city":"De Panne",
    "sg:orig_category":"Enseignement maternel and primaire",
    "sg:phone":"+32 58 41 50 25",
    "sg:postcode":"8660",
    "sg:province":"West-Vlaanderen",
    "wof:name":"Vrije Basisschool",
    "wof:placetype":"venue"
},
  "geometry": {"coordinates":[2.6039550304,51.0748939514],"type":"Point"}
}