{
  "type": "Feature",
  "properties": {
    "addr:full":"Rue Du Chapitre 3 Frameries Hainaut 7080",
    "addr:housenumber":"3",
    "addr:postcode":"7080",
    "addr:street":"Rue Du Chapitre",
    "iso:country":"BE",
    "sg:address":"Rue Du Chapitre 3",
    "sg:city":"Frameries",
    "sg:orig_category":"Cafetarias and selfservice restaurants",
    "sg:phone":"+32 65 60 19 59",
    "sg:postcode":"7080",
    "sg:province":"Hainaut",
    "wof:name":"Guermant G",
    "wof:placetype":"venue"
},
  "geometry": {"coordinates":[3.894382,50.4138526917],"type":"Point"}
}