{
  "type": "Feature",
  "properties": {
    "addr:full":"Parklaan 47 Box 16 Aalst Oost-Vlaanderen 9300",
    "addr:housenumber":"47 box 16",
    "addr:postcode":"9300",
    "addr:street":"Parklaan",
    "iso:country":"BE",
    "sg:address":"Parklaan 47 Box 16",
    "sg:city":"Aalst",
    "sg:classifiers":[
        {
            "category":"Wholesale",
            "subcategory":"Construction Materials",
            "type":"Manufacturing & Wholesale Goods"
        }
    ],
    "sg:phone":"+32 53 78 11 89",
    "sg:postcode":"9300",
    "sg:province":"Oost-Vlaanderen",
    "sg:tags":[
        "sewing",
        "thread"
    ],
    "wof:name":"Coats Opti Nv",
    "wof:placetype":"venue"
},
  "geometry": {"coordinates":[4.0432457924,50.9313011169],"type":"Point"}
}