{
  "type": "Feature",
  "properties": {
    "addr:full":"Rue De Wanferc\u00e9e Baulet 7 Fleurus (wanferc\u00e9e-baulet) Hainaut 6224",
    "addr:housenumber":"7",
    "addr:postcode":"6224",
    "addr:street":"Rue De Wanferce\u0301E Baulet",
    "iso:country":"BE",
    "sg:address":"Rue De Wanferc\u00e9e Baulet 7",
    "sg:city":"Fleurus (wanferc\u00e9e-baulet)",
    "sg:classifiers":[
        {
            "category":"Structure",
            "subcategory":"Building",
            "type":"Public Place"
        }
    ],
    "sg:phone":"+32 71 81 30 60",
    "sg:postcode":"6224",
    "sg:province":"Hainaut",
    "sg:tags":[
        "door"
    ],
    "wof:name":"Debay",
    "wof:placetype":"venue"
},
  "geometry": {"coordinates":[4.580783844,50.4729270935],"type":"Point"}
}