{
  "type": "Feature",
  "properties": {
    "addr:full":"Vaderlandsplein 26 Schaarbeek/schaerbeek Bruxelles-Capitale 1030",
    "addr:housenumber":"26",
    "addr:postcode":"1030",
    "addr:street":"Vaderlandsplein",
    "iso:country":"BE",
    "sg:address":"Vaderlandsplein 26",
    "sg:city":"Schaarbeek/schaerbeek",
    "sg:classifiers":[
        {
            "category":"Fast Food",
            "type":"Food & Drink"
        }
    ],
    "sg:phone":"+32 2 216 79 50",
    "sg:postcode":"1030",
    "sg:province":"Bruxelles-Capitale",
    "sg:tags":[
        "meeneem",
        "restaurant"
    ],
    "wof:name":"Anak Timoer",
    "wof:placetype":"venue"
},
  "geometry": {"coordinates":[4.3913030624,50.8567314148],"type":"Point"}
}