{
  "type": "Feature",
  "properties": {
    "iso:country":"BE",
    "sg:address":"Blijde Inkomststraat 164",
    "sg:city":"Leuven",
    "sg:classifiers":[
        {
            "category":"Retail",
            "subcategory":"Driving School",
            "type":"Services"
        }
    ],
    "sg:phone":"+32 16 23 35 81",
    "sg:postcode":"3000",
    "sg:province":"Vlaams-Brabant",
    "sg:tags":[
        "automobile",
        "officially",
        "-",
        "recognized"
    ],
    "wof:name":"Moderna Rijschool",
    "wof:placetype":"venue"
},
  "geometry": {"coordinates":[4.7136468887,50.8739738464],"type":"Point"}
}