{
  "type": "Feature",
  "properties": {
    "iso:country":"BE",
    "sg:address":"Woluwelaan 9",
    "sg:city":"Vilvoorde",
    "sg:classifiers":[
        {
            "category":"Autos & Motor Vehicles",
            "subcategory":"Auto Supplies",
            "type":"Retail Goods"
        }
    ],
    "sg:phone":"+32 2 254 14 82",
    "sg:postcode":"1800",
    "sg:province":"Vlaams-Brabant",
    "sg:tags":[
        "hydraulics"
    ],
    "wof:name":"Hytrans",
    "wof:placetype":"venue"
},
  "geometry": {"coordinates":[4.4458999634,50.9233093262],"type":"Point"}
}