{
  "type": "Feature",
  "properties": {
    "iso:country":"BE",
    "sg:address":"Viseweg 270",
    "sg:city":"Riemst",
    "sg:orig_category":"Mat\u00e9riaux de construction Bois Gr. Rev\u00eatements de sols and murs. Installation de menuiserie en bois ",
    "sg:phone":"+32 12 45 33 02",
    "sg:postcode":"3770",
    "sg:province":"Limburg",
    "wof:name":"Modest Hout Doe-het-zelf",
    "wof:placetype":"venue"
},
  "geometry": {"coordinates":[5.606347084,50.8036117554],"type":"Point"}
}