{
  "type": "Feature",
  "properties": {
    "addr:full":"Am Sonnenhang 3 Sankt Vith Li\u00e8ge 4780",
    "addr:housenumber":"3",
    "addr:postcode":"4780",
    "addr:street":"Am Sonnenhang",
    "iso:country":"BE",
    "sg:address":"Am Sonnenhang 3",
    "sg:city":"Sankt Vith",
    "sg:classifiers":[
        {
            "category":"Education",
            "subcategory":"Dance Studio",
            "type":"Public Place"
        }
    ],
    "sg:phone":"+32 80 22 17 71",
    "sg:postcode":"4780",
    "sg:province":"Li\u00e8ge",
    "sg:tags":[
        "pallet"
    ],
    "wof:name":"Holimat Sa",
    "wof:placetype":"venue"
},
  "geometry": {"coordinates":[6.1187582016,50.2754364014],"type":"Point"}
}