{
  "type": "Feature",
  "properties": {
    "addr:full":"Rue De M\u00c9rode 349 Vorst/forest Bruxelles-Capitale 1190",
    "addr:housenumber":"349",
    "addr:postcode":"1190",
    "addr:street":"Rue De Me\u0301Rode;/ Forest",
    "iso:country":"BE",
    "sg:address":"Rue De M\u00c9rode 349",
    "sg:city":"Vorst/forest",
    "sg:orig_category":"Epiceries",
    "sg:phone":"+32 2 534 01 02",
    "sg:postcode":"1190",
    "sg:province":"Bruxelles-Capitale",
    "wof:name":"Assoc. Benali-kherroubi",
    "wof:placetype":"venue"
},
  "geometry": {"coordinates":[4.3293862343,50.8272705078],"type":"Point"}
}