{
  "type": "Feature",
  "properties": {
    "addr:full":"Rue Sainte-walburge 115-117 Li\u00e8ge 1 Li\u00e8ge 4000",
    "addr:postcode":"115-117;4000",
    "addr:street":"Rue Sainte-Walburge",
    "iso:country":"BE",
    "sg:address":"Rue Sainte-walburge 115-117",
    "sg:city":"Li\u00e8ge 1",
    "sg:classifiers":[
        {
            "category":"Shopping",
            "subcategory":"Computers & Home Electronics",
            "type":"Retail Goods"
        }
    ],
    "sg:phone":"+32 4 226 24 46",
    "sg:postcode":"4000",
    "sg:province":"Li\u00e8ge",
    "sg:tags":[
        "personal",
        "-",
        "processing",
        "data"
    ],
    "wof:name":"Valkenborgh Informatique",
    "wof:placetype":"venue"
},
  "geometry": {"coordinates":[5.5704069138,50.6566505432],"type":"Point"}
}