{
  "type": "Feature",
  "properties": {
    "iso:country":"BE",
    "sg:address":"Chauss\u00c9e De Verviers 54",
    "sg:city":"Theux",
    "sg:orig_category":"V\u00e9t\u00e9rinaires",
    "sg:phone":"+32 87 53 06 55",
    "sg:postcode":"4910",
    "sg:province":"Li\u00e8ge",
    "wof:name":"Kristel Van Den Abeele",
    "wof:placetype":"venue"
},
  "geometry": {"coordinates":[5.8213047981,50.539276123],"type":"Point"}
}