{
  "type": "Feature",
  "properties": {
    "addr:full":"Rue Des Alli\u00e9s 294-296 Bruxelles (forest) Bruxelles-Capitale 1190",
    "addr:postcode":"294-296;1190",
    "addr:street":"Rue Des Allie\u0301S",
    "iso:country":"BE",
    "sg:address":"Rue Des Alli\u00e9s 294-296",
    "sg:city":"Bruxelles (forest)",
    "sg:classifiers":[
        {
            "category":"Banks & Credit Unions",
            "subcategory":"Investment Brokerage",
            "type":"Services"
        }
    ],
    "sg:phone":"+32 2 345 49 82",
    "sg:postcode":"1190",
    "sg:province":"Bruxelles-Capitale",
    "sg:tags":[
        "repair",
        "-",
        "installation",
        "sanitary",
        "article"
    ],
    "wof:name":"Carrel Freres Grimaldi G Et C",
    "wof:placetype":"venue"
},
  "geometry": {"coordinates":[4.3273200989,50.8228912354],"type":"Point"}
}