{
  "type": "Feature",
  "properties": {
    "iso:country":"BE",
    "sg:address":"Lochtemanweg 60",
    "sg:city":"Beringen",
    "sg:orig_category":"Non-Classified Establishments",
    "sg:phone":"+32 11 45 55 20",
    "sg:postcode":"3580",
    "sg:province":"Limburg",
    "wof:name":"Gijbels Nv Glasindustrie",
    "wof:placetype":"venue"
},
  "geometry": {"coordinates":[5.2285690308,51.0324249268],"type":"Point"}
}