{
  "type": "Feature",
  "properties": {
    "iso:country":"BE",
    "sg:address":"Burgstraat 2",
    "sg:city":"Assenede",
    "sg:orig_category":"Boucheries",
    "sg:phone":"+32 9 344 69 40",
    "sg:postcode":"9960",
    "sg:province":"Oost-Vlaanderen",
    "wof:name":"Bekaert Ronald & Michel",
    "wof:placetype":"venue"
},
  "geometry": {"coordinates":[3.7428729534,51.2205505371],"type":"Point"}
}