{
  "type": "Feature",
  "properties": {
    "addr:full":"Jules Klockplein 11b1 Hasselt Limburg 3500",
    "addr:housenumber":"11b1",
    "addr:postcode":"3500",
    "iso:country":"BE",
    "sg:address":"Jules Klockplein 11b1",
    "sg:city":"Hasselt",
    "sg:orig_category":"Artsen and specialisten",
    "sg:phone":"+32 11 27 27 91",
    "sg:postcode":"3500",
    "sg:province":"Limburg",
    "wof:name":"Guido Mennes",
    "wof:placetype":"venue"
},
  "geometry": {"coordinates":[5.3288521767,50.9216346741],"type":"Point"}
}