{
  "type": "Feature",
  "properties": {
    "addr:full":"Rue De L\u00b4institut 71 Bl\u00c9gny Li\u00e8ge 4670",
    "addr:housenumber":"71",
    "addr:postcode":"4670",
    "addr:street":"Rue De L\u00b4Institut",
    "iso:country":"BE",
    "sg:address":"Rue De L\u00b4institut 71",
    "sg:city":"Bl\u00c9gny",
    "sg:classifiers":[
        {
            "category":"Government",
            "subcategory":"Police Station",
            "type":"Public Place"
        }
    ],
    "sg:phone":"+32 4 387 43 43",
    "sg:postcode":"4670",
    "sg:province":"Li\u00e8ge",
    "sg:tags":[
        "gendarmerie"
    ],
    "wof:name":"Police F\u00c9d\u00c9rale/federale Politie",
    "wof:placetype":"venue"
},
  "geometry": {"coordinates":[5.7176442146,50.6738586426],"type":"Point"}
}