{
  "type": "Feature",
  "properties": {
    "iso:country":"BE",
    "sg:address":"Spinnersstraat 6",
    "sg:city":"Roeselare",
    "sg:classifiers":[
        {
            "category":"Professional",
            "type":"Services"
        }
    ],
    "sg:phone":"+32 51 24 97 78",
    "sg:postcode":"8800",
    "sg:province":"West-Vlaanderen",
    "sg:tags":[
        "auction",
        "room"
    ],
    "wof:name":"Snuistergalerij",
    "wof:placetype":"venue"
},
  "geometry": {"coordinates":[3.1337189674,50.9498825073],"type":"Point"}
}