{
  "type": "Feature",
  "properties": {
    "addr:full":"Hoezestraat 125 Aalst Oost-Vlaanderen 9300",
    "addr:housenumber":"125",
    "addr:postcode":"9300",
    "addr:street":"Hoezestraat",
    "iso:country":"BE",
    "sg:address":"Hoezestraat 125",
    "sg:city":"Aalst",
    "sg:orig_category":"Artiesten and kunstenaars",
    "sg:phone":"+32 53 21 25 16",
    "sg:postcode":"9300",
    "sg:province":"Oost-Vlaanderen",
    "wof:name":"M. De Bruyn",
    "wof:placetype":"venue"
},
  "geometry": {"coordinates":[4.0289731026,50.9231414795],"type":"Point"}
}