{
  "type": "Feature",
  "properties": {
    "addr:full":"Begijnenstraat 18 Sint-niklaas Oost-Vlaanderen 9100",
    "addr:housenumber":"18",
    "addr:postcode":"9100",
    "addr:street":"Begijnenstraat",
    "iso:country":"BE",
    "sg:address":"Begijnenstraat 18",
    "sg:city":"Sint-niklaas",
    "sg:orig_category":"Non-Classified Establishments",
    "sg:phone":"+32 3 776 29 18",
    "sg:postcode":"9100",
    "sg:province":"Oost-Vlaanderen",
    "wof:name":"Petrine",
    "wof:placetype":"venue"
},
  "geometry": {"coordinates":[4.1428031921,51.1764793396],"type":"Point"}
}