{
  "type": "Feature",
  "properties": {
    "addr:full":"Avenue Reine Astrid 4 Gerpinnes Hainaut 6280",
    "addr:housenumber":"4",
    "addr:postcode":"6280",
    "addr:street":"Avenue Reine Astrid;Hainaut",
    "iso:country":"BE",
    "sg:address":"Avenue Reine Astrid 4",
    "sg:city":"Gerpinnes",
    "sg:classifiers":[
        {
            "category":"Health Services",
            "subcategory":"Dentist",
            "type":"Services"
        }
    ],
    "sg:phone":"+32 71 50 26 80",
    "sg:postcode":"6280",
    "sg:province":"Hainaut",
    "wof:name":"Fosseur Olivier",
    "wof:placetype":"venue"
},
  "geometry": {"coordinates":[4.5273852348,50.3375358582],"type":"Point"}
}