{
  "type": "Feature",
  "properties": {
    "iso:country":"BE",
    "sg:address":"Leopoldplein 50",
    "sg:city":"Hasselt",
    "sg:classifiers":[
        {
            "category":"Health Services",
            "subcategory":"Doctor",
            "type":"Services"
        }
    ],
    "sg:phone":"+32 11 22 25 40",
    "sg:postcode":"3500",
    "sg:province":"Limburg",
    "sg:tags":[
        "medicinephysicians",
        "surgeon"
    ],
    "wof:name":"Herman F",
    "wof:placetype":"venue"
},
  "geometry": {"coordinates":[5.3332128525,50.9283180237],"type":"Point"}
}