{
  "type": "Feature",
  "properties": {
    "iso:country":"BE",
    "sg:address":"093770150",
    "sg:city":"Halle",
    "sg:orig_category":"Dancings and bo\u00eetes de nuit",
    "sg:phone":"+32 9 377 01 50",
    "sg:postcode":"9971",
    "sg:province":"Oost-Vlaanderen",
    "wof:name":"New Dallas",
    "wof:placetype":"venue"
},
  "geometry": {"coordinates":[-91.33019256590001,33.5353012085],"type":"Point"}
}