{
  "type": "Feature",
  "properties": {
    "iso:country":"BE",
    "sg:address":"Chauss\u00c9e De Lodelinsart 86",
    "sg:city":"Charleroi",
    "sg:orig_category":"Opticiens",
    "sg:phone":"+32 71 41 04 04",
    "sg:postcode":"6060",
    "sg:province":"Hainaut",
    "wof:name":"Pol Damman",
    "wof:placetype":"venue"
},
  "geometry": {"coordinates":[4.4500160217,50.4211082458],"type":"Point"}
}