{
  "type": "Feature",
  "properties": {
    "iso:country":"BE",
    "sg:address":"Rue Du Ch\u00c2teau St.-marc 42",
    "sg:city":"Namur",
    "sg:orig_category":"Experts-comptables",
    "sg:phone":"+32 81 73 23 38",
    "sg:postcode":"5003",
    "sg:province":"Namur",
    "wof:name":"Roger Marroy",
    "wof:placetype":"venue"
},
  "geometry": {"coordinates":[4.8498501778,50.4949493408],"type":"Point"}
}