{
  "type": "Feature",
  "properties": {
    "iso:country":"BE",
    "sg:address":"Nieuwpoortsesteenweg 24",
    "sg:city":"Oostende",
    "sg:orig_category":"Boucheries",
    "sg:phone":"+32 59 70 29 44",
    "sg:postcode":"8400",
    "sg:province":"West-Vlaanderen",
    "wof:name":"Omer Verstegen",
    "wof:placetype":"venue"
},
  "geometry": {"coordinates":[2.9077479839,51.2241821289],"type":"Point"}
}