{
  "type": "Feature",
  "properties": {
    "iso:country":"BE",
    "sg:address":"Stroperstraat 77",
    "sg:city":"Kemzeke",
    "sg:orig_category":"Meubles D\u00e9taillants, Am\u00e9nagement de B\u00e2timents et de Cuisines",
    "sg:phone":"+32 3 789 24 84",
    "sg:postcode":"9190",
    "sg:province":"Oost-Vlaanderen",
    "wof:name":"In De Oude Hoeve",
    "wof:placetype":"venue"
},
  "geometry": {"coordinates":[4.0603480339,51.2378234863],"type":"Point"}
}