{
  "type": "Feature",
  "properties": {
    "iso:country":"BE",
    "sg:address":"Rue Chanoine Theys 4",
    "sg:city":"Fleurus",
    "sg:classifiers":[
        {
            "category":"Health Services",
            "subcategory":"Doctor",
            "type":"Services"
        }
    ],
    "sg:phone":"+32 71 81 31 29",
    "sg:postcode":"6220",
    "sg:province":"Hainaut",
    "sg:tags":[
        "medicinephysicians",
        "surgeon"
    ],
    "wof:name":"Clinquart H",
    "wof:placetype":"venue"
},
  "geometry": {"coordinates":[4.5488982201,50.4830856323],"type":"Point"}
}