{
  "type": "Feature",
  "properties": {
    "addr:full":"Clos Des Pommiers 9 Braine L'alleud (braine-l'alleud) Brabant Wallon 1420",
    "addr:housenumber":"9",
    "addr:postcode":"1420",
    "addr:street":"Clos Des Pommiers",
    "iso:country":"BE",
    "sg:address":"Clos Des Pommiers 9",
    "sg:city":"Braine L'alleud (braine-l'alleud)",
    "sg:classifiers":[
        {
            "category":"Building & Trades",
            "subcategory":"Plumbing",
            "type":"Services"
        }
    ],
    "sg:phone":"+32 2 387 50 11",
    "sg:postcode":"1420",
    "sg:province":"Brabant Wallon",
    "sg:tags":[
        "repair",
        "mainten",
        "-",
        "central",
        "heating"
    ],
    "wof:name":"Guillec P",
    "wof:placetype":"venue"
},
  "geometry": {"coordinates":[-0.6790779829,47.3779411316],"type":"Point"}
}