{
  "type": "Feature",
  "properties": {
    "addr:full":"Rue De La Petite Guirlande 17 Mons Hainaut 7000",
    "addr:housenumber":"17",
    "addr:postcode":"7000",
    "addr:street":"Rue De La Petite Guirlande;Hainaut",
    "iso:country":"BE",
    "sg:address":"Rue De La Petite Guirlande 17",
    "sg:city":"Mons",
    "sg:classifiers":[
        {
            "category":"Shopping",
            "subcategory":"Clothing, Apparel, & Fashions",
            "type":"Retail Goods"
        }
    ],
    "sg:phone":"+32 65 84 58 45",
    "sg:postcode":"7000",
    "sg:province":"Hainaut",
    "sg:tags":[
        "underwear",
        "lingerie",
        "-"
    ],
    "wof:name":"Night And Day",
    "wof:placetype":"venue"
},
  "geometry": {"coordinates":[3.9454119205,50.4512939453],"type":"Point"}
}