{
  "type": "Feature",
  "properties": {
    "addr:full":"Kruibeeksesteenweg 162 Zwijndrecht Antwerpen 2070",
    "addr:housenumber":"162",
    "addr:postcode":"2070",
    "addr:street":"Kruibeeksesteenweg",
    "iso:country":"BE",
    "sg:address":"Kruibeeksesteenweg 162",
    "sg:city":"Zwijndrecht",
    "sg:orig_category":"Verhuur bouwmachines",
    "sg:phone":"+32 3 254 15 19",
    "sg:postcode":"2070",
    "sg:province":"Antwerpen",
    "wof:name":"M.d.u.",
    "wof:placetype":"venue"
},
  "geometry": {"coordinates":[4.3257398605,51.1869316101],"type":"Point"}
}