{
  "type": "Feature",
  "properties": {
    "addr:full":"De Nieuwe Vierschaar 14 Kuurne West-Vlaanderen 8520",
    "addr:housenumber":"14",
    "addr:postcode":"8520",
    "addr:street":"De;Vierschaar",
    "iso:country":"BE",
    "sg:address":"De Nieuwe Vierschaar 14",
    "sg:city":"Kuurne",
    "sg:classifiers":[
        {
            "category":"Building & Trades",
            "subcategory":"Construction",
            "type":"Services"
        }
    ],
    "sg:phone":"+32 56 35 79 33",
    "sg:postcode":"8520",
    "sg:province":"West-Vlaanderen",
    "sg:tags":[
        "stucco",
        "contractor"
    ],
    "wof:name":"Breye Dirk Bvba",
    "wof:placetype":"venue"
},
  "geometry": {"coordinates":[3.2453401089,50.87109375],"type":"Point"}
}