{
  "type": "Feature",
  "properties": {
    "addr:full":"Chauss\u00c9e De Wavre 1508 Oudergem/auderghem Bruxelles-Capitale 1160",
    "addr:postcode":"1508;1160",
    "addr:street":"Chausse\u0301E De Wavre",
    "iso:country":"BE",
    "sg:address":"Chauss\u00c9e De Wavre 1508",
    "sg:city":"Oudergem/auderghem",
    "sg:classifiers":[
        {
            "category":"Communications",
            "subcategory":"Television Station",
            "type":"Services"
        }
    ],
    "sg:phone":"+32 2 660 00 75",
    "sg:postcode":"1160",
    "sg:province":"Bruxelles-Capitale",
    "sg:tags":[
        "video",
        "audio",
        "verhuur"
    ],
    "wof:name":"Cinebank",
    "wof:placetype":"venue"
},
  "geometry": {"coordinates":[4.4199748039,50.8178024292],"type":"Point"}
}