{
  "type": "Feature",
  "properties": {
    "addr:full":"Kortrijkstr. 79 Zwevegem West-Vlaanderen 8540",
    "addr:housenumber":"79",
    "addr:postcode":"8540",
    "addr:street":"Kortrijkstr.",
    "iso:country":"BE",
    "sg:address":"Kortrijkstr. 79",
    "sg:city":"Zwevegem",
    "sg:classifiers":[
        {
            "category":"Shopping",
            "subcategory":"Crafts & Fabrics",
            "type":"Retail Goods"
        }
    ],
    "sg:phone":"+32 56 20 51 62",
    "sg:postcode":"8540",
    "sg:province":"West-Vlaanderen",
    "sg:tags":[
        "textile",
        "clothing"
    ],
    "wof:name":"Maderna Textiles Bvba",
    "wof:placetype":"venue"
},
  "geometry": {"coordinates":[3.3255269527,50.8133659363],"type":"Point"}
}