{
  "type": "Feature",
  "properties": {
    "iso:country":"BE",
    "sg:address":"Avenue Princesse Elisabeth 54",
    "sg:city":"Brussel/bruxelles",
    "sg:orig_category":"Opticiens",
    "sg:phone":"+32 2 216 01 65",
    "sg:postcode":"1030",
    "sg:province":"Bruxelles-Capitale",
    "wof:name":"Optic D. Hertsens",
    "wof:placetype":"venue"
},
  "geometry": {"coordinates":[4.3770098686,50.8733024597],"type":"Point"}
}