{
  "type": "Feature",
  "properties": {
    "addr:full":"Moerenstraat 11 Tongeren Limburg 3700",
    "addr:housenumber":"11",
    "addr:postcode":"3700",
    "addr:street":"Moerenstraat",
    "iso:country":"BE",
    "sg:address":"Moerenstraat 11",
    "sg:city":"Tongeren",
    "sg:orig_category":"Kapsalons",
    "sg:phone":"+32 12 23 13 59",
    "sg:postcode":"3700",
    "sg:province":"Limburg",
    "wof:name":"Coiffure Wilmans",
    "wof:placetype":"venue"
},
  "geometry": {"coordinates":[5.4691929817,50.7809333801],"type":"Point"}
}