{
  "type": "Feature",
  "properties": {
    "iso:country":"BE",
    "sg:address":"Rue Des Echevins 36",
    "sg:city":"Elsene/ixelles",
    "sg:orig_category":"Architectes",
    "sg:phone":"+32 2 647 26 71",
    "sg:postcode":"1050",
    "sg:province":"Bruxelles-Capitale",
    "wof:name":"Claude Delfosse",
    "wof:placetype":"venue"
},
  "geometry": {"coordinates":[4.3770298958,50.8223762512],"type":"Point"}
}