{
  "type": "Feature",
  "properties": {
    "addr:full":"Hoevestraat 37 Kortrijk West-Vlaanderen 8500",
    "addr:housenumber":"37",
    "addr:postcode":"8500",
    "addr:street":"Hoevestraat",
    "iso:country":"BE",
    "sg:address":"Hoevestraat 37",
    "sg:city":"Kortrijk",
    "sg:orig_category":"Winkelinrichting and handelsuitrusting Gh",
    "sg:phone":"+32 56 20 49 76",
    "sg:postcode":"8500",
    "sg:province":"West-Vlaanderen",
    "wof:name":"Fa. Castel & Brighton",
    "wof:placetype":"venue"
},
  "geometry": {"coordinates":[3.2929899693,50.8319549561],"type":"Point"}
}