{
  "type": "Feature",
  "properties": {
    "iso:country":"BE",
    "sg:address":"Rue Des Communes 6",
    "sg:city":"Malmedy/malmedy",
    "sg:classifiers":[
        {
            "category":"Professional",
            "subcategory":"Accounting & Tax Preparation",
            "type":"Services"
        }
    ],
    "sg:phone":"+32 80 33 83 99",
    "sg:postcode":"4960",
    "sg:province":"Li\u00e8ge",
    "sg:tags":[
        "accountant"
    ],
    "wof:name":"Jean-marie Schneiders",
    "wof:placetype":"venue"
},
  "geometry": {"coordinates":[6.0588469505,50.4050216675],"type":"Point"}
}