{
  "type": "Feature",
  "properties": {
    "addr:full":"Voistraat 25 Erpe-mere Oost-Vlaanderen 9420",
    "addr:housenumber":"25",
    "addr:postcode":"9420",
    "addr:street":"Voistraat",
    "iso:country":"BE",
    "sg:address":"Voistraat 25",
    "sg:city":"Erpe-mere",
    "sg:orig_category":"Fabrication and montage de mobilier. Installation de menuiserie en bois and plastique",
    "sg:phone":"+32 53 80 55 05",
    "sg:postcode":"9420",
    "sg:province":"Oost-Vlaanderen",
    "wof:name":"Van Den Rijse",
    "wof:placetype":"venue"
},
  "geometry": {"coordinates":[3.9292469025,50.9381217957],"type":"Point"}
}