{
  "type": "Feature",
  "properties": {
    "addr:full":"Marialoopplaats 5 Meulebeke West-Vlaanderen 8760",
    "addr:housenumber":"5",
    "addr:postcode":"8760",
    "addr:street":"Marialoopplaats",
    "iso:country":"BE",
    "sg:address":"Marialoopplaats 5",
    "sg:city":"Meulebeke",
    "sg:classifiers":[
        {
            "category":"Social Services",
            "subcategory":"Child Care",
            "type":"Services"
        }
    ],
    "sg:phone":"+32 51 40 86 64",
    "sg:postcode":"8760",
    "sg:province":"West-Vlaanderen",
    "sg:tags":[
        "baby",
        "nursery",
        "day",
        "sitting"
    ],
    "wof:name":"Jip En Janneke",
    "wof:placetype":"venue"
},
  "geometry": {"coordinates":[3.3007650375,50.9589157104],"type":"Point"}
}