{
  "type": "Feature",
  "properties": {
    "addr:full":"Middelweg 205 Leuven Vlaams-Brabant 3001",
    "addr:housenumber":"205",
    "addr:postcode":"3001",
    "addr:street":"Middelweg",
    "iso:country":"BE",
    "sg:address":"Middelweg 205",
    "sg:city":"Leuven",
    "sg:orig_category":"Mat\u00e9riel m\u00e9dical and orthop\u00e9dique and proth\u00e8ses Fab",
    "sg:phone":"+32 16 40 20 53",
    "sg:postcode":"3001",
    "sg:province":"Vlaams-Brabant",
    "wof:name":"Keratec Dental Ker.pavil.",
    "wof:placetype":"venue"
},
  "geometry": {"coordinates":[4.6907191277,50.8517456055],"type":"Point"}
}