{
  "type": "Feature",
  "properties": {
    "iso:country":"BE",
    "sg:address":"Dessus-le-bois 63",
    "sg:city":"Herve (bolland)",
    "sg:classifiers":[
        {
            "category":"Building & Trades",
            "subcategory":"Electrical",
            "type":"Services"
        }
    ],
    "sg:phone":"+32 4 387 83 78",
    "sg:postcode":"4653",
    "sg:province":"Li\u00e8ge",
    "sg:tags":[
        "electric",
        "-",
        "housewiring",
        "contractor"
    ],
    "wof:name":"Derooz J-m",
    "wof:placetype":"venue"
},
  "geometry": {"coordinates":[5.7589969635,50.661365509],"type":"Point"}
}