{
  "type": "Feature",
  "properties": {
    "addr:full":"Kastijdestraat 15 Merelbeke (schelderode) Oost-Vlaanderen 9820",
    "addr:housenumber":"15",
    "addr:postcode":"9820",
    "addr:street":"Kastijdestraat",
    "iso:country":"BE",
    "sg:address":"Kastijdestraat 15",
    "sg:city":"Merelbeke (schelderode)",
    "sg:classifiers":[
        {
            "category":"Travel",
            "subcategory":"Resort",
            "type":"Entertainment"
        }
    ],
    "sg:phone":"+32 9 362 10 22",
    "sg:postcode":"9820",
    "sg:province":"Oost-Vlaanderen",
    "sg:tags":[
        "rental",
        "accomodation",
        "holiday",
        "-"
    ],
    "wof:name":"T'bakkershof",
    "wof:placetype":"venue"
},
  "geometry": {"coordinates":[3.7176299095,50.9415397644],"type":"Point"}
}