{
  "type": "Feature",
  "properties": {
    "addr:full":"Rue Victor Forthomme 25 Sprimont Li\u00e8ge 4140",
    "addr:housenumber":"25",
    "addr:postcode":"4140",
    "addr:street":"Rue Victor Forthomme",
    "iso:country":"BE",
    "sg:address":"Rue Victor Forthomme 25",
    "sg:city":"Sprimont",
    "sg:orig_category":"Eleveurs de bovins",
    "sg:phone":"+32 4 382 26 07",
    "sg:postcode":"4140",
    "sg:province":"Li\u00e8ge",
    "wof:name":"Enrico Leonardi",
    "wof:placetype":"venue"
},
  "geometry": {"coordinates":[5.6597499847,50.5072059631],"type":"Point"}
}