{
  "type": "Feature",
  "properties": {
    "addr:full":"Lange Zoutstraat 57 Aalst Oost-Vlaanderen 9300",
    "addr:housenumber":"57",
    "addr:postcode":"9300",
    "addr:street":"Lange Zoutstraat",
    "iso:country":"BE",
    "sg:address":"Lange Zoutstraat 57",
    "sg:city":"Aalst",
    "sg:classifiers":[
        {
            "category":"Banks & Credit Unions",
            "subcategory":"Investment Brokerage",
            "type":"Services"
        }
    ],
    "sg:phone":"+32 53 75 09 57",
    "sg:postcode":"9300",
    "sg:province":"Oost-Vlaanderen",
    "sg:tags":[
        "jean",
        "casual",
        "wear"
    ],
    "wof:name":"Indigo Blue Bvba",
    "wof:placetype":"venue"
},
  "geometry": {"coordinates":[4.0396661758,50.9365005493],"type":"Point"}
}