{
  "type": "Feature",
  "properties": {
    "addr:full":"Heirbaan 12 Dendermonde Oost-Vlaanderen 9200",
    "addr:housenumber":"12",
    "addr:postcode":"9200",
    "addr:street":"Heirbaan;Oost-Vlaanderen",
    "iso:country":"BE",
    "sg:address":"Heirbaan 12",
    "sg:city":"Dendermonde",
    "sg:orig_category":"Boucheries",
    "sg:phone":"+32 52 22 31 55",
    "sg:postcode":"9200",
    "sg:province":"Oost-Vlaanderen",
    "wof:name":"Renmans",
    "wof:placetype":"venue"
},
  "geometry": {"coordinates":[4.1126728058,51.0169868469],"type":"Point"}
}