{
  "type": "Feature",
  "properties": {
    "addr:full":"Chauss\u00c9e De Leuze 8 Frasnes-lez-anvaing Hainaut 7911",
    "addr:housenumber":"8",
    "addr:postcode":"7911",
    "addr:street":"Chausse\u0301E De Leuze",
    "iso:country":"BE",
    "sg:address":"Chauss\u00c9e De Leuze 8",
    "sg:city":"Frasnes-lez-anvaing",
    "sg:orig_category":"Benzinestations and brandstoffen Herstellingen and onderhoud van auto's Voertuigen",
    "sg:phone":"+32 69 86 63 57",
    "sg:postcode":"7911",
    "sg:province":"Hainaut",
    "wof:name":"Garage Hayt",
    "wof:placetype":"venue"
},
  "geometry": {"coordinates":[3.6043450832,50.636100769],"type":"Point"}
}