{
  "type": "Feature",
  "properties": {
    "addr:full":"Bredabaan 364 Brasschaat Antwerpen 2930",
    "addr:housenumber":"364",
    "addr:postcode":"2930",
    "addr:street":"Bredabaan",
    "iso:country":"BE",
    "sg:address":"Bredabaan 364",
    "sg:city":"Brasschaat",
    "sg:orig_category":"Jeux and jouets",
    "sg:phone":"+32 3 652 11 59",
    "sg:postcode":"2930",
    "sg:province":"Antwerpen",
    "wof:name":"Speel-goed",
    "wof:placetype":"venue"
},
  "geometry": {"coordinates":[4.4949998856,51.2935676575],"type":"Point"}
}