{
  "type": "Feature",
  "properties": {
    "addr:full":"Aartrijkestraat 132 Box 1 Torhout West-Vlaanderen 8820",
    "addr:housenumber":"132;1",
    "addr:postcode":"8820",
    "addr:street":"Aartrijkestraat;Box",
    "iso:country":"BE",
    "sg:address":"Aartrijkestraat 132 Box 1",
    "sg:city":"Torhout",
    "sg:classifiers":[
        {
            "category":"Professional",
            "subcategory":"Accounting & Tax Preparation",
            "type":"Services"
        }
    ],
    "sg:phone":"+32 50 20 09 74",
    "sg:postcode":"8820",
    "sg:province":"West-Vlaanderen",
    "sg:tags":[
        "bookkeeper"
    ],
    "wof:name":"Fibam Administratiekantoor Bvba",
    "wof:placetype":"venue"
},
  "geometry": {"coordinates":[3.0977509022,51.0785675049],"type":"Point"}
}