{
  "type": "Feature",
  "properties": {
    "addr:full":"Van Eycklei 30 Box 6 Antwerpen Antwerpen 2018",
    "addr:housenumber":"30;6",
    "addr:postcode":"2018",
    "addr:street":"Van Eycklei;Box",
    "iso:country":"BE",
    "sg:address":"Van Eycklei 30 Box 6",
    "sg:city":"Antwerpen",
    "sg:classifiers":[
        {
            "category":"Transit Center",
            "subcategory":"Freight",
            "type":"Transportation"
        }
    ],
    "sg:phone":"+32 3 218 80 63",
    "sg:postcode":"2018",
    "sg:province":"Antwerpen",
    "sg:tags":[
        "import",
        "export",
        "-"
    ],
    "wof:name":"Bemor Bvba",
    "wof:placetype":"venue"
},
  "geometry": {"coordinates":[4.4153800011,51.210231781],"type":"Point"}
}