{
  "type": "Feature",
  "properties": {
    "addr:full":"Diestersteenweg 43 Nieuwerkerken Limburg 3850",
    "addr:housenumber":"43",
    "addr:postcode":"3850",
    "addr:street":"Diestersteenweg",
    "iso:country":"BE",
    "sg:address":"Diestersteenweg 43",
    "sg:city":"Nieuwerkerken",
    "sg:classifiers":[
        {
            "category":"Home & Garden",
            "subcategory":"Carpets & Floor Coverings",
            "type":"Retail Goods"
        }
    ],
    "sg:phone":"+32 476 74 39 54",
    "sg:postcode":"3850",
    "sg:province":"Limburg",
    "sg:tags":[
        "parquet"
    ],
    "wof:name":"Kravanja Hubert",
    "wof:placetype":"venue"
},
  "geometry": {"coordinates":[5.1888551712,50.8589668274],"type":"Point"}
}