{
  "type": "Feature",
  "properties": {
    "iso:country":"BE",
    "sg:address":"Ave Max Buset",
    "sg:city":"La Louvi\u00e8re",
    "sg:classifiers":[
        {
            "category":"Banks & Credit Unions",
            "subcategory":"Bank",
            "type":"Services"
        }
    ],
    "sg:phone":"+32 64 21 27 27",
    "sg:postcode":"7100",
    "sg:province":"Hainaut",
    "wof:name":"Aslk-cger Bank",
    "wof:placetype":"venue"
},
  "geometry": {"coordinates":[4.2060389519,50.4787445068],"type":"Point"}
}