{
  "type": "Feature",
  "properties": {
    "addr:full":"Baronval 18 Ham-sur-heure-nalinnes Hainaut 6120",
    "addr:housenumber":"18",
    "addr:postcode":"6120",
    "addr:street":"Baronval;Hainaut",
    "iso:country":"BE",
    "sg:address":"Baronval 18",
    "sg:city":"Ham-sur-heure-nalinnes",
    "sg:orig_category":"Dakwerken Loodgieterij, verwarming and sanitaire installaties",
    "sg:phone":"+32 71 21 66 79",
    "sg:postcode":"6120",
    "sg:province":"Hainaut",
    "wof:name":"Deloie",
    "wof:placetype":"venue"
},
  "geometry": {"coordinates":[4.4303159714,50.3280258179],"type":"Point"}
}