{
  "type": "Feature",
  "properties": {
    "iso:country":"BE",
    "sg:address":"Rue De Biomont 102",
    "sg:city":"Herve (grand-rechain)",
    "sg:orig_category":"Non-Classified Establishments",
    "sg:phone":"+32 87 67 40 71",
    "sg:postcode":"4650",
    "sg:province":"Li\u00e8ge",
    "wof:name":"Corman Fm",
    "wof:placetype":"venue"
},
  "geometry": {"coordinates":[5.7941417694,50.6130561829],"type":"Point"}
}