{
  "type": "Feature",
  "properties": {
    "iso:country":"BE",
    "sg:address":"Rue Reine Astrid 5b7",
    "sg:city":"Engis",
    "sg:classifiers":[
        {
            "category":"Communications",
            "subcategory":"Radio Station",
            "type":"Services"
        }
    ],
    "sg:phone":"+32 4 275 01 93",
    "sg:postcode":"4480",
    "sg:province":"Li\u00e8ge",
    "sg:tags":[
        "diffusion",
        "production",
        "de",
        "programme"
    ],
    "wof:name":"Radio Test Engis",
    "wof:placetype":"venue"
},
  "geometry": {"coordinates":[5.4047961235,50.5822677612],"type":"Point"}
}