{
  "type": "Feature",
  "properties": {
    "iso:country":"BE",
    "sg:address":"Liersesteenweg 92",
    "sg:city":"Lint",
    "sg:orig_category":"Brood, gebak and snoepgoed",
    "sg:phone":"+32 3 454 34 93",
    "sg:postcode":"2547",
    "sg:province":"Antwerpen",
    "wof:name":"Ons Dagelijks Brood",
    "wof:placetype":"venue"
},
  "geometry": {"coordinates":[4.5015268326,51.126701355],"type":"Point"}
}