{
  "type": "Feature",
  "properties": {
    "iso:country":"BE",
    "sg:address":"Jan Frans Willemsstraat 61",
    "sg:city":"Boechout",
    "sg:orig_category":"Pain, p\u00e2tisseries and confiseries",
    "sg:phone":"+32 3 455 76 10",
    "sg:postcode":"2530",
    "sg:province":"Antwerpen",
    "wof:name":"Bakkerij Tijl",
    "wof:placetype":"venue"
},
  "geometry": {"coordinates":[4.4952411652,51.1611404419],"type":"Point"}
}