{
  "type": "Feature",
  "properties": {
    "iso:country":"BE",
    "sg:address":"Grand-rue De Feluy 22",
    "sg:city":"Seneffe",
    "sg:orig_category":"Diverse organisaties and verenigingen",
    "sg:phone":"+32 67 87 84 02",
    "sg:postcode":"7181",
    "sg:province":"Hainaut",
    "wof:name":"Maison Jeunes & Culture",
    "wof:placetype":"venue"
},
  "geometry": {"coordinates":[4.2513928413,50.5639343262],"type":"Point"}
}