{
  "type": "Feature",
  "properties": {
    "iso:country":"BE",
    "sg:address":"Elfde Novemberwal 28 Box 1",
    "sg:city":"Tongeren",
    "sg:classifiers":[
        {
            "category":"Health Services",
            "subcategory":"Dentist",
            "type":"Services"
        }
    ],
    "sg:phone":"+32 12 23 75 60",
    "sg:postcode":"3700",
    "sg:province":"Limburg",
    "wof:name":"Horman D",
    "wof:placetype":"venue"
},
  "geometry": {"coordinates":[5.4660358429,50.7834815979],"type":"Point"}
}