{
  "type": "Feature",
  "properties": {
    "iso:country":"BE",
    "sg:address":"Zi Av De Spirou 23",
    "sg:city":"Fleurus",
    "sg:classifiers":[
        {
            "category":"Professional",
            "subcategory":"Printing & Photocopies",
            "type":"Services"
        }
    ],
    "sg:phone":"+32 71 81 01 01",
    "sg:postcode":"6220",
    "sg:province":"Hainaut",
    "sg:tags":[
        "publishing"
    ],
    "wof:name":"Helio Charleroi Sa",
    "wof:placetype":"venue"
},
  "geometry": {"coordinates":[4.537735939,50.4556541443],"type":"Point"}
}