{
  "type": "Feature",
  "properties": {
    "addr:full":"Rue Capitaine Joubert 4 Bruxelles (etterbeek) Bruxelles-Capitale 1040",
    "addr:housenumber":"4",
    "addr:postcode":"1040",
    "addr:street":"Rue Capitaine Joubert",
    "iso:country":"BE",
    "sg:address":"Rue Capitaine Joubert 4",
    "sg:city":"Bruxelles (etterbeek)",
    "sg:classifiers":[
        {
            "category":"Health Services",
            "subcategory":"Doctor",
            "type":"Services"
        }
    ],
    "sg:phone":"+32 2 735 96 46",
    "sg:postcode":"1040",
    "sg:province":"Bruxelles-Capitale",
    "sg:tags":[
        "psychotherapist",
        "psychoanalyst"
    ],
    "wof:name":"Gailly C",
    "wof:placetype":"venue"
},
  "geometry": {"coordinates":[4.400662899,50.8268318176],"type":"Point"}
}