{
  "type": "Feature",
  "properties": {
    "addr:full":"Rolliersstraat 47 Sint-niklaas Oost-Vlaanderen 9100",
    "addr:housenumber":"47",
    "addr:postcode":"9100",
    "addr:street":"Rolliersstraat",
    "iso:country":"BE",
    "sg:address":"Rolliersstraat 47",
    "sg:city":"Sint-niklaas",
    "sg:orig_category":"Dierenartsen",
    "sg:phone":"+32 3 776 67 85",
    "sg:postcode":"9100",
    "sg:province":"Oost-Vlaanderen",
    "wof:name":"Patrick Corrijn",
    "wof:placetype":"venue"
},
  "geometry": {"coordinates":[4.1322312355,51.1660003662],"type":"Point"}
}