{
  "type": "Feature",
  "properties": {
    "iso:country":"BE",
    "sg:address":"Pillendijk 6bb",
    "sg:city":"Beveren",
    "sg:orig_category":"Peinture. Construction de maisons. Rev\u00eatements pour sols and murs",
    "sg:phone":"+32 3 773 44 74",
    "sg:postcode":"9130",
    "sg:province":"Oost-Vlaanderen",
    "wof:name":"Luc De Wolf-tack",
    "wof:placetype":"venue"
},
  "geometry": {"coordinates":[4.1730771065,51.293422699],"type":"Point"}
}