{
  "type": "Feature",
  "properties": {
    "iso:country":"BE",
    "sg:address":"Briel 103",
    "sg:city":"Lede (smetlede)",
    "sg:classifiers":[
        {
            "category":"Shopping",
            "subcategory":"Discount & Variety Stores",
            "type":"Retail Goods"
        }
    ],
    "sg:phone":"+32 9 366 45 02",
    "sg:postcode":"9340",
    "sg:province":"Oost-Vlaanderen",
    "sg:tags":[
        "shop",
        "clearers",
        "curiosity",
        "furniture"
    ],
    "wof:name":"Locotrade Bvba",
    "wof:placetype":"venue"
},
  "geometry": {"coordinates":[3.9266629219,50.9704170227],"type":"Point"}
}