{
  "type": "Feature",
  "properties": {
    "addr:full":"Rue De L\u00b4ourthe 45 Somme-leuze Namur 5377",
    "addr:housenumber":"45",
    "addr:postcode":"5377",
    "addr:street":"Rue De L\u00b4Ourthe",
    "iso:country":"BE",
    "sg:address":"Rue De L\u00b4ourthe 45",
    "sg:city":"Somme-leuze",
    "sg:orig_category":"Charpentes and couvertures",
    "sg:phone":"+32 86 32 23 07",
    "sg:postcode":"5377",
    "sg:province":"Namur",
    "wof:name":"Toitures Franco",
    "wof:placetype":"venue"
},
  "geometry": {"coordinates":[5.37733078,50.3004226685],"type":"Point"}
}