{
  "type": "Feature",
  "properties": {
    "iso:country":"BE",
    "sg:address":"Galgenveldstraat 22",
    "sg:city":"Tielt",
    "sg:classifiers":[
        {
            "category":"Transit Center",
            "subcategory":"Freight",
            "type":"Transportation"
        }
    ],
    "sg:phone":"+32 51 40 36 61",
    "sg:postcode":"8700",
    "sg:province":"West-Vlaanderen",
    "sg:tags":[
        "food"
    ],
    "wof:name":"De Meulemeester & Zoon B.v.b.a.",
    "wof:placetype":"venue"
},
  "geometry": {"coordinates":[3.3440799713,51.0036392212],"type":"Point"}
}