{
  "type": "Feature",
  "properties": {
    "addr:full":"Langestraat 170 Zandhoven Antwerpen 2240",
    "addr:housenumber":"170",
    "addr:postcode":"2240",
    "addr:street":"Langestraat",
    "iso:country":"BE",
    "sg:address":"Langestraat 170",
    "sg:city":"Zandhoven",
    "sg:classifiers":[
        {
            "category":"Travel",
            "subcategory":"Resort",
            "type":"Entertainment"
        }
    ],
    "sg:phone":"+32 3 464 04 04",
    "sg:postcode":"2240",
    "sg:province":"Antwerpen",
    "sg:tags":[
        "vacation"
    ],
    "wof:name":"Domein Hooidonk",
    "wof:placetype":"venue"
},
  "geometry": {"coordinates":[4.6869659424,51.2335891724],"type":"Point"}
}