{
  "type": "Feature",
  "properties": {
    "iso:country":"BE",
    "sg:address":"Antwerpsestraat 29",
    "sg:city":"Mortsel",
    "sg:classifiers":[
        {
            "category":"Food & Beverages",
            "subcategory":"Chocolate",
            "type":"Retail Goods"
        }
    ],
    "sg:phone":"+32 3 440 27 78",
    "sg:postcode":"2640",
    "sg:province":"Antwerpen",
    "sg:tags":[
        "confectionery",
        "-"
    ],
    "wof:name":"Breugelmans Bvba",
    "wof:placetype":"venue"
},
  "geometry": {"coordinates":[4.4475779533,51.1714401245],"type":"Point"}
}