{
  "type": "Feature",
  "properties": {
    "iso:country":"BE",
    "sg:address":"Karel De Stoutelaan 98",
    "sg:city":"Brugge",
    "sg:classifiers":[
        {
            "category":"Building & Trades",
            "subcategory":"Landscaping Services",
            "type":"Services"
        }
    ],
    "sg:phone":"+32 50 31 22 97",
    "sg:postcode":"8000",
    "sg:province":"West-Vlaanderen",
    "sg:tags":[
        "gardening",
        "garden",
        "maintenance"
    ],
    "wof:name":"Holvoet P",
    "wof:placetype":"venue"
},
  "geometry": {"coordinates":[3.2081611156,51.2133789062],"type":"Point"}
}