{
  "type": "Feature",
  "properties": {
    "iso:country":"BE",
    "sg:address":"Deken Adamsstraat 29",
    "sg:city":"Turnhout",
    "sg:classifiers":[
        {
            "category":"Health Services",
            "subcategory":"Doctor",
            "type":"Services"
        }
    ],
    "sg:phone":"+32 14 41 68 15",
    "sg:postcode":"2300",
    "sg:province":"Antwerpen",
    "sg:tags":[
        "medicinephysicians",
        "surgeon"
    ],
    "wof:name":"Arnouts P",
    "wof:placetype":"venue"
},
  "geometry": {"coordinates":[4.9466757774,51.3204154968],"type":"Point"}
}