{
  "type": "Feature",
  "properties": {
    "addr:full":"Rue Du Cow\u00e2 6 Fl\u00e9malle (awirs) Li\u00e8ge 4400",
    "addr:housenumber":"6",
    "addr:postcode":"4400",
    "addr:street":"Rue Du Cowa\u0302",
    "iso:country":"BE",
    "sg:address":"Rue Du Cow\u00e2 6",
    "sg:city":"Fl\u00e9malle (awirs)",
    "sg:classifiers":[
        {
            "category":"Parking",
            "subcategory":"Lot",
            "type":"Transportation"
        }
    ],
    "sg:phone":"+32 4 275 19 00",
    "sg:postcode":"4400",
    "sg:province":"Li\u00e8ge",
    "sg:tags":[
        "parking-places",
        "laying-out"
    ],
    "wof:name":"Dalla Costa Sprl",
    "wof:placetype":"venue"
},
  "geometry": {"coordinates":[5.4134559631,50.6158294678],"type":"Point"}
}