{
  "type": "Feature",
  "properties": {
    "addr:full":"Provinciebaan 8 Retie Antwerpen 2470",
    "addr:housenumber":"8",
    "addr:postcode":"2470",
    "addr:street":"Provinciebaan",
    "iso:country":"BE",
    "sg:address":"Provinciebaan 8",
    "sg:city":"Retie",
    "sg:orig_category":"Instituts de beaut\u00e9",
    "sg:phone":"+32 14 67 03 33",
    "sg:postcode":"2470",
    "sg:province":"Antwerpen",
    "wof:name":"Annick Peeters",
    "wof:placetype":"venue"
},
  "geometry": {"coordinates":[5.0548191071,51.2834587097],"type":"Point"}
}