{
  "type": "Feature",
  "properties": {
    "iso:country":"BE",
    "sg:address":"August Van Landeghemstr. 22",
    "sg:city":"Willebroek",
    "sg:orig_category":"Geluidsopnames",
    "sg:phone":"+32 3 866 39 78",
    "sg:postcode":"2830",
    "sg:province":"Antwerpen",
    "wof:name":"Studio Starbase",
    "wof:placetype":"venue"
},
  "geometry": {"coordinates":[4.3612179756,51.0620651245],"type":"Point"}
}