{
  "type": "Feature",
  "properties": {
    "addr:full":"Rue De La Station 42 Beaumont Hainaut 6511",
    "addr:housenumber":"42",
    "addr:postcode":"6511",
    "addr:street":"Rue De La Station;Hainaut",
    "iso:country":"BE",
    "sg:address":"Rue De La Station 42",
    "sg:city":"Beaumont",
    "sg:orig_category":"Drukkerijen and copyshops Papierwaren and schoolbenodigdheden Gh",
    "sg:phone":"+32 71 53 30 69",
    "sg:postcode":"6511",
    "sg:province":"Hainaut",
    "wof:name":"Dantinne Str\u00c9e",
    "wof:placetype":"venue"
},
  "geometry": {"coordinates":[4.3030700684,50.2719192505],"type":"Point"}
}