{
  "type": "Feature",
  "properties": {
    "iso:country":"BE",
    "sg:address":"Monseigneur De Haerneln 5",
    "sg:city":"Kortrijk",
    "sg:orig_category":"R\u00e9alisation de programmes and logiciels. Conseils en syst\u00e8mes informatiques",
    "sg:phone":"+32 56 21 05 07",
    "sg:postcode":"8500",
    "sg:province":"West-Vlaanderen",
    "wof:name":"Astroweb",
    "wof:placetype":"venue"
},
  "geometry": {"coordinates":[3.2575550079,50.8223991394],"type":"Point"}
}