{
  "type": "Feature",
  "properties": {
    "iso:country":"BE",
    "sg:address":"Tisseltstraat 3",
    "sg:city":"Kapelle-op-den-bos",
    "sg:classifiers":[
        {
            "category":"Personal",
            "subcategory":"Beauty Salon",
            "type":"Services"
        }
    ],
    "sg:phone":"+32 15 71 45 82",
    "sg:postcode":"1880",
    "sg:province":"Vlaams-Brabant",
    "sg:tags":[
        "de",
        "coiffure"
    ],
    "wof:name":"Diane Lens",
    "wof:placetype":"venue"
},
  "geometry": {"coordinates":[4.3349051476,51.0149917603],"type":"Point"}
}