{
  "type": "Feature",
  "properties": {
    "iso:country":"BE",
    "sg:address":"Vanderperrenstraat 37",
    "sg:city":"Jette",
    "sg:classifiers":[
        {
            "category":"Restaurant",
            "type":"Food & Drink"
        }
    ],
    "sg:phone":"+32 2 426 44 23",
    "sg:postcode":"1090",
    "sg:province":"Bruxelles-Capitale",
    "wof:name":"Taverne Sunshine",
    "wof:placetype":"venue"
},
  "geometry": {"coordinates":[4.3335847855,50.8677330017],"type":"Point"}
}