{
  "type": "Feature",
  "properties": {
    "addr:full":"Rue De La R\u00e9sistance 8 Saint-nicolas (montegn\u00e9e) Li\u00e8ge 4420",
    "addr:housenumber":"8",
    "addr:postcode":"4420",
    "addr:street":"Rue De La Re\u0301Sistance;Montegne\u0301E",
    "iso:country":"BE",
    "sg:address":"Rue De La R\u00e9sistance 8",
    "sg:city":"Saint-nicolas (montegn\u00e9e)",
    "sg:classifiers":[
        {
            "category":"Health Services",
            "subcategory":"Dentist",
            "type":"Services"
        }
    ],
    "sg:phone":"+32 4 246 14 41",
    "sg:postcode":"4420",
    "sg:province":"Li\u00e8ge",
    "wof:name":"Dessart Christian",
    "wof:placetype":"venue"
},
  "geometry": {"coordinates":[5.5207548141,50.6414299011],"type":"Point"}
}