{
  "type": "Feature",
  "properties": {
    "addr:full":"Renaat Veremansstraat 6 Box 82 Antwerpen Antwerpen 2030",
    "addr:housenumber":"6 box 82",
    "addr:postcode":"2030",
    "addr:street":"Renaat Veremansstraat",
    "iso:country":"BE",
    "sg:address":"Renaat Veremansstraat 6 Box 82",
    "sg:city":"Antwerpen",
    "sg:classifiers":[
        {
            "category":"Organizations",
            "subcategory":"Community Association",
            "type":"Services"
        }
    ],
    "sg:phone":"+32 3 297 15 85",
    "sg:postcode":"2030",
    "sg:province":"Antwerpen",
    "sg:tags":[
        "cultural"
    ],
    "wof:name":"Lys",
    "wof:placetype":"venue"
},
  "geometry": {"coordinates":[4.4174189568,51.2695426941],"type":"Point"}
}