{
  "type": "Feature",
  "properties": {
    "iso:country":"BE",
    "sg:address":"Avenue Reine Astrid 59",
    "sg:city":"Spa",
    "sg:orig_category":"M\u00e9decins and sp\u00e9cialistes",
    "sg:phone":"+32 87 77 44 44",
    "sg:postcode":"4900",
    "sg:province":"Li\u00e8ge",
    "wof:name":"Jo\u00cblle Vandendooren",
    "wof:placetype":"venue"
},
  "geometry": {"coordinates":[5.8593959808,50.4920806885],"type":"Point"}
}