{
  "type": "Feature",
  "properties": {
    "addr:full":"Traktaatstraat 11 Antwerpen Antwerpen 2030",
    "addr:housenumber":"11",
    "addr:postcode":"2030",
    "addr:street":"Traktaatstraat",
    "iso:country":"BE",
    "sg:address":"Traktaatstraat 11",
    "sg:city":"Antwerpen",
    "sg:orig_category":"M\u00e9decins and sp\u00e9cialistes",
    "sg:phone":"+32 3 541 10 53",
    "sg:postcode":"2030",
    "sg:province":"Antwerpen",
    "wof:name":"Brigitte Meir",
    "wof:placetype":"venue"
},
  "geometry": {"coordinates":[4.4118819237,51.2842636108],"type":"Point"}
}