{
  "type": "Feature",
  "properties": {
    "iso:country":"BE",
    "sg:address":"Colmanstraat 50",
    "sg:city":"Laarne (kalken)",
    "sg:classifiers":[
        {
            "category":"Wholesale",
            "subcategory":"Fruits & Vegetables",
            "type":"Manufacturing & Wholesale Goods"
        }
    ],
    "sg:phone":"+32 9 369 39 78",
    "sg:postcode":"9270",
    "sg:province":"Oost-Vlaanderen",
    "sg:tags":[
        "whol",
        "-",
        "potato"
    ],
    "wof:name":"Belpaco Bvba",
    "wof:placetype":"venue"
},
  "geometry": {"coordinates":[3.8917651176,51.03490448],"type":"Point"}
}