{
  "type": "Feature",
  "properties": {
    "iso:country":"BE",
    "sg:address":"Vierde Lansierslaan 4",
    "sg:city":"Tienen",
    "sg:classifiers":[
        {
            "category":"Professional",
            "subcategory":"Lawyer & Legal Services",
            "type":"Services"
        }
    ],
    "sg:phone":"+32 476 25 59 81",
    "sg:postcode":"3300",
    "sg:province":"Vlaams-Brabant",
    "wof:name":"Vandebempt E",
    "wof:placetype":"venue"
},
  "geometry": {"coordinates":[4.9297699928,50.8094940186],"type":"Point"}
}