{
  "type": "Feature",
  "properties": {
    "addr:full":"Rue De Pont \u00e0 Migneloux 6b Les Bons Villers (wayaux) Hainaut 6210",
    "addr:housenumber":"6b",
    "addr:postcode":"6210",
    "addr:street":"Rue De Pont A\u0300 Migneloux;Hainaut",
    "iso:country":"BE",
    "sg:address":"Rue De Pont \u00e0 Migneloux 6b",
    "sg:city":"Les Bons Villers (wayaux)",
    "sg:classifiers":[
        {
            "category":"Professional",
            "subcategory":"Accounting & Tax Preparation",
            "type":"Services"
        }
    ],
    "sg:phone":"+32 71 85 39 59",
    "sg:postcode":"6210",
    "sg:province":"Hainaut",
    "sg:tags":[
        "bookkeeper"
    ],
    "wof:name":"Armillotta P",
    "wof:placetype":"venue"
},
  "geometry": {"coordinates":[4.4511561394,50.5378227234],"type":"Point"}
}