{
  "type": "Feature",
  "properties": {
    "iso:country":"BE",
    "sg:address":"Kerkstraat 6",
    "sg:city":"Turnhout",
    "sg:orig_category":"M\u00e9decins and sp\u00e9cialistes",
    "sg:phone":"+32 14 43 86 91",
    "sg:postcode":"2300",
    "sg:province":"Antwerpen",
    "wof:name":"H. Loncin",
    "wof:placetype":"venue"
},
  "geometry": {"coordinates":[4.9420962334,51.3218154907],"type":"Point"}
}