{
  "type": "Feature",
  "properties": {
    "addr:full":"Kievitstraat 3 Vosselaar Antwerpen 2350",
    "addr:housenumber":"3",
    "addr:postcode":"2350",
    "addr:street":"Kievitstraat",
    "iso:country":"BE",
    "sg:address":"Kievitstraat 3",
    "sg:city":"Vosselaar",
    "sg:orig_category":"Architecten",
    "sg:phone":"+32 14 41 25 80",
    "sg:postcode":"2350",
    "sg:province":"Antwerpen",
    "wof:name":"Roel Hofkens",
    "wof:placetype":"venue"
},
  "geometry": {"coordinates":[4.9081048965,51.3027877808],"type":"Point"}
}