{
  "type": "Feature",
  "properties": {
    "addr:full":"Rue Du Biran 11 Houyet Namur 5564",
    "addr:housenumber":"11",
    "addr:postcode":"5564",
    "addr:street":"Rue Du Biran",
    "iso:country":"BE",
    "sg:address":"Rue Du Biran 11",
    "sg:city":"Houyet",
    "sg:orig_category":"Plantes and fleurs Gr",
    "sg:phone":"+32 82 66 63 78",
    "sg:postcode":"5564",
    "sg:province":"Namur",
    "wof:name":"Haveaux J",
    "wof:placetype":"venue"
},
  "geometry": {"coordinates":[5.0614261627,50.1595497131],"type":"Point"}
}