{
  "type": "Feature",
  "properties": {
    "addr:full":"Rue E Claus 49b1 Elsene Bruxelles-Capitale 1050",
    "addr:housenumber":"49b1",
    "addr:postcode":"1050",
    "addr:street":"Rue E Claus",
    "iso:country":"BE",
    "sg:address":"Rue E Claus 49b1",
    "sg:city":"Elsene",
    "sg:orig_category":"Agences d'exp\u00e9dition",
    "sg:phone":"+32 2 649 98 70",
    "sg:postcode":"1050",
    "sg:province":"Bruxelles-Capitale",
    "wof:name":"Belmar",
    "wof:placetype":"venue"
},
  "geometry": {"coordinates":[4.3682579994,50.8160171509],"type":"Point"}
}