{
  "type": "Feature",
  "properties": {
    "addr:full":"Tienne Robau 18 Ch\u00e2telet Hainaut 6200",
    "addr:housenumber":"18",
    "addr:postcode":"6200",
    "addr:street":"Robau",
    "iso:country":"BE",
    "sg:address":"Tienne Robau 18",
    "sg:city":"Ch\u00e2telet",
    "sg:classifiers":[
        {
            "category":"Health Services",
            "subcategory":"Health Practitioner",
            "type":"Services"
        }
    ],
    "sg:phone":"+32 71 38 46 87",
    "sg:postcode":"6200",
    "sg:province":"Hainaut",
    "sg:tags":[
        "physiotherapist"
    ],
    "wof:name":"Rousseau A",
    "wof:placetype":"venue"
},
  "geometry": {"coordinates":[4.5292072296,50.4009284973],"type":"Point"}
}