{
  "type": "Feature",
  "properties": {
    "addr:full":"Riddersstraat 17 Leuven Vlaams-Brabant 3000",
    "addr:housenumber":"17",
    "addr:postcode":"3000",
    "addr:street":"Riddersstraat",
    "iso:country":"BE",
    "sg:address":"Riddersstraat 17",
    "sg:city":"Leuven",
    "sg:classifiers":[
        {
            "category":"Travel",
            "subcategory":"Travel Agent",
            "type":"Entertainment"
        }
    ],
    "sg:phone":"+32 16 23 80 83",
    "sg:postcode":"3000",
    "sg:province":"Vlaams-Brabant",
    "sg:tags":[
        "agency"
    ],
    "wof:name":"Rego Coach Travel",
    "wof:placetype":"venue"
},
  "geometry": {"coordinates":[4.6903948784,50.8816184998],"type":"Point"}
}