{
  "type": "Feature",
  "properties": {
    "addr:full":"Langemuntstraat 50 Zele Oost-Vlaanderen 9240",
    "addr:housenumber":"50",
    "addr:postcode":"9240",
    "addr:street":"Langemuntstraat",
    "iso:country":"BE",
    "sg:address":"Langemuntstraat 50",
    "sg:city":"Zele",
    "sg:classifiers":[
        {
            "category":"Arena",
            "subcategory":"Sports Club",
            "type":"Entertainment"
        }
    ],
    "sg:phone":"+32 52 44 47 35",
    "sg:postcode":"9240",
    "sg:province":"Oost-Vlaanderen",
    "sg:tags":[
        "de"
    ],
    "wof:name":"A.c. Zele",
    "wof:placetype":"venue"
},
  "geometry": {"coordinates":[4.0341892242,51.069694519],"type":"Point"}
}