{
  "type": "Feature",
  "properties": {
    "addr:full":"Avenue De La Facult\u00c9 41 Gembloux Namur 5030",
    "addr:housenumber":"41",
    "addr:postcode":"5030",
    "addr:street":"Avenue De La Faculte\u0301;Namur",
    "iso:country":"BE",
    "sg:address":"Avenue De La Facult\u00c9 41",
    "sg:city":"Gembloux",
    "sg:orig_category":"Agences de publicit\u00e9. Installation \u00e9lectrique industrielle. D\u00e9taillants en pi\u00e8ces and accessoires de",
    "sg:phone":"+32 81 61 26 26",
    "sg:postcode":"5030",
    "sg:province":"Namur",
    "wof:name":"Dd Design",
    "wof:placetype":"venue"
},
  "geometry": {"coordinates":[4.6959700584,50.5652008057],"type":"Point"}
}