{
  "type": "Feature",
  "properties": {
    "addr:full":"Keerbaan 149 Wommelgem Antwerpen 2160",
    "addr:housenumber":"149",
    "addr:postcode":"2160",
    "addr:street":"Keerbaan",
    "iso:country":"BE",
    "sg:address":"Keerbaan 149",
    "sg:city":"Wommelgem",
    "sg:classifiers":[
        {
            "category":"Building & Trades",
            "subcategory":"Landscaping Services",
            "type":"Services"
        }
    ],
    "sg:phone":"+32 3 353 34 80",
    "sg:postcode":"2160",
    "sg:province":"Antwerpen",
    "sg:tags":[
        "forestry"
    ],
    "wof:name":"Van Buel M",
    "wof:placetype":"venue"
},
  "geometry": {"coordinates":[4.5405502319,51.2093658447],"type":"Point"}
}