{
  "type": "Feature",
  "properties": {
    "iso:country":"BE",
    "sg:address":"Astridplein 54",
    "sg:city":"Grobbendonk",
    "sg:orig_category":"M\u00e9decins and sp\u00e9cialistes",
    "sg:phone":"+32 14 51 15 40",
    "sg:postcode":"2280",
    "sg:province":"Antwerpen",
    "wof:name":"Van Der Donck",
    "wof:placetype":"venue"
},
  "geometry": {"coordinates":[4.7381711006,51.1922798157],"type":"Point"}
}