{
  "type": "Feature",
  "properties": {
    "addr:full":"Zuidzandstraat 2 Box 6 Brugge West-Vlaanderen 8000",
    "addr:housenumber":"2;6",
    "addr:postcode":"8000",
    "addr:street":"Zuidzandstraat;Box",
    "iso:country":"BE",
    "sg:address":"Zuidzandstraat 2 Box 6",
    "sg:city":"Brugge",
    "sg:classifiers":[
        {
            "category":"Shopping",
            "subcategory":"Clothing, Apparel, & Fashions",
            "type":"Retail Goods"
        }
    ],
    "sg:phone":"+32 50 33 13 06",
    "sg:postcode":"8000",
    "sg:province":"West-Vlaanderen",
    "sg:tags":[
        "boutique"
    ],
    "wof:name":"Mariella Burani Nv",
    "wof:placetype":"venue"
},
  "geometry": {"coordinates":[3.2205400467,51.2056655884],"type":"Point"}
}