{
  "type": "Feature",
  "properties": {
    "addr:full":"Terhagelaan 34 Wommelgem Antwerpen 2160",
    "addr:housenumber":"34",
    "addr:postcode":"2160",
    "addr:street":"Terhagelaan",
    "iso:country":"BE",
    "sg:address":"Terhagelaan 34",
    "sg:city":"Wommelgem",
    "sg:classifiers":[
        {
            "category":"Personal",
            "subcategory":"Beauty Salon",
            "type":"Services"
        }
    ],
    "sg:phone":"+32 3 353 90 45",
    "sg:postcode":"2160",
    "sg:province":"Antwerpen",
    "sg:tags":[
        "lady",
        "-",
        "hairdressing"
    ],
    "wof:name":"Nicole",
    "wof:placetype":"venue"
},
  "geometry": {"coordinates":[4.5301089287,51.2015533447],"type":"Point"}
}