{
  "type": "Feature",
  "properties": {
    "addr:full":"Avenue Franklin Roosevelt 82 Bruxelles (ixelles) Bruxelles-Capitale 1050",
    "addr:housenumber":"82",
    "addr:postcode":"1050",
    "addr:street":"Avenue Franklin Roosevelt",
    "iso:country":"BE",
    "sg:address":"Avenue Franklin Roosevelt 82",
    "sg:city":"Bruxelles (ixelles)",
    "sg:classifiers":[
        {
            "category":"Health Services",
            "subcategory":"Dentist",
            "type":"Services"
        }
    ],
    "sg:phone":"+32 2 646 32 36",
    "sg:postcode":"1050",
    "sg:province":"Bruxelles-Capitale",
    "wof:name":"Krischek Muriel",
    "wof:placetype":"venue"
},
  "geometry": {"coordinates":[4.3838877678,50.8093414307],"type":"Point"}
}