{
  "type": "Feature",
  "properties": {
    "iso:country":"BE",
    "sg:address":"Stormestraat 11",
    "sg:city":"Waregem",
    "sg:orig_category":"Pain, p\u00e2tisseries and confiseries. Restaurants",
    "sg:phone":"+32 56 61 10 90",
    "sg:postcode":"8790",
    "sg:province":"West-Vlaanderen",
    "wof:name":"Huis Carline",
    "wof:placetype":"venue"
},
  "geometry": {"coordinates":[3.4311819077,50.8863334656],"type":"Point"}
}