{
  "type": "Feature",
  "properties": {
    "addr:full":"Lentestraat 10 Hasselt Limburg 3500",
    "addr:housenumber":"10",
    "addr:postcode":"3500",
    "addr:street":"Lentestraat",
    "iso:country":"BE",
    "sg:address":"Lentestraat 10",
    "sg:city":"Hasselt",
    "sg:orig_category":"Schoonheidssalons",
    "sg:phone":"+32 11 28 32 91",
    "sg:postcode":"3500",
    "sg:province":"Limburg",
    "wof:name":"Alexander Bots",
    "wof:placetype":"venue"
},
  "geometry": {"coordinates":[5.345126152,50.9200286865],"type":"Point"}
}