{
  "type": "Feature",
  "properties": {
    "iso:country":"BE",
    "sg:address":"Hopmarkt 11",
    "sg:city":"Aalst",
    "sg:orig_category":"S\u00e9lection de personnel and placement",
    "sg:phone":"+32 53 76 71 71",
    "sg:postcode":"9300",
    "sg:province":"Oost-Vlaanderen",
    "wof:name":"Vdab",
    "wof:placetype":"venue"
},
  "geometry": {"coordinates":[4.0376238823,50.9377326965],"type":"Point"}
}