{
  "type": "Feature",
  "properties": {
    "addr:full":"Rue De La Station 1a Ans Li\u00e8ge 4430",
    "addr:housenumber":"1a",
    "addr:postcode":"4430",
    "addr:street":"Rue De La Station",
    "iso:country":"BE",
    "sg:address":"Rue De La Station 1a",
    "sg:city":"Ans",
    "sg:orig_category":"Reisbureaus",
    "sg:phone":"+32 4 247 30 77",
    "sg:postcode":"4430",
    "sg:province":"Li\u00e8ge",
    "wof:name":"Euring Travel",
    "wof:placetype":"venue"
},
  "geometry": {"coordinates":[5.5114340782,50.6637268066],"type":"Point"}
}