{
  "type": "Feature",
  "properties": {
    "iso:country":"BE",
    "sg:address":"Vis\u00c9weg 455",
    "sg:city":"Tongeren",
    "sg:orig_category":"Sportclubs Sportterreinen and installaties behalve sportcentra",
    "sg:phone":"+32 12 23 25 71",
    "sg:postcode":"3700",
    "sg:province":"Limburg",
    "wof:name":"Voetbalclub Sluizen",
    "wof:placetype":"venue"
},
  "geometry": {"coordinates":[5.5148901939,50.7829093933],"type":"Point"}
}