{
  "type": "Feature",
  "properties": {
    "addr:full":"Kapellestraat 55 Zwevegem 8552",
    "addr:housenumber":"55",
    "addr:postcode":"8552",
    "addr:street":"Kapellestraat",
    "iso:country":"BE",
    "sg:address":"Kapellestraat 55",
    "sg:city":"Zwevegem",
    "sg:orig_category":"Alimentation sp\u00e9cialis\u00e9e. Boucheries",
    "sg:phone":"+32 56 64 46 11",
    "sg:postcode":"8552",
    "wof:name":"Beenhouwerij Patrick",
    "wof:placetype":"venue"
},
  "geometry": {"coordinates":[3.3993918896,50.7678337097],"type":"Point"}
}