{
  "type": "Feature",
  "properties": {
    "addr:full":"Rue Pierre Timmermans 14 Jette Bruxelles-Capitale 1090",
    "addr:housenumber":"14",
    "addr:postcode":"1090",
    "addr:street":"Rue Pierre Timmermans",
    "iso:country":"BE",
    "sg:address":"Rue Pierre Timmermans 14",
    "sg:city":"Jette",
    "sg:classifiers":[
        {
            "category":"Personal",
            "subcategory":"Beauty Salon",
            "type":"Services"
        }
    ],
    "sg:phone":"+32 2 427 57 62",
    "sg:postcode":"1090",
    "sg:province":"Bruxelles-Capitale",
    "sg:tags":[
        "de",
        "coiffure"
    ],
    "wof:name":"Dimension (coiffure)",
    "wof:placetype":"venue"
},
  "geometry": {"coordinates":[4.3244700432,50.873210907],"type":"Point"}
}