{
  "type": "Feature",
  "properties": {
    "addr:full":"Rue De La Chauss\u00c9e 70d Mons Hainaut 7000",
    "addr:housenumber":"70d",
    "addr:postcode":"7000",
    "addr:street":"Rue De La Chausse\u0301E;Hainaut",
    "iso:country":"BE",
    "sg:address":"Rue De La Chauss\u00c9e 70d",
    "sg:city":"Mons",
    "sg:orig_category":"Dameskledingzaken",
    "sg:phone":"+32 65 35 58 38",
    "sg:postcode":"7000",
    "sg:province":"Hainaut",
    "wof:name":"We Women",
    "wof:placetype":"venue"
},
  "geometry": {"coordinates":[3.9500100613,50.452507019],"type":"Point"}
}