{
  "type": "Feature",
  "properties": {
    "addr:full":"Noorderlaan 50 Waregem (groot) West-Vlaanderen 8790",
    "addr:housenumber":"50",
    "addr:postcode":"8790",
    "addr:street":"Noorderlaan;Groot West-Vlaanderen",
    "iso:country":"BE",
    "sg:address":"Noorderlaan 50",
    "sg:city":"Waregem (groot)",
    "sg:orig_category":"Supermarkten",
    "sg:phone":"+32 56 60 44 33",
    "sg:postcode":"8790",
    "sg:province":"West-Vlaanderen",
    "wof:name":"Colruyt",
    "wof:placetype":"venue"
},
  "geometry": {"coordinates":[3.4238829613,50.8907585144],"type":"Point"}
}