{
  "type": "Feature",
  "properties": {
    "iso:country":"BE",
    "sg:address":"Plasstraat 4a",
    "sg:city":"Meise",
    "sg:classifiers":[
        {
            "category":"Manufacturing",
            "subcategory":"Building Materials",
            "type":"Manufacturing & Wholesale Goods"
        }
    ],
    "sg:phone":"+32 2 267 44 56",
    "sg:postcode":"1860",
    "sg:province":"Vlaams-Brabant",
    "sg:tags":[
        "fixture",
        "store"
    ],
    "wof:name":"Retail Match",
    "wof:placetype":"venue"
},
  "geometry": {"coordinates":[4.3261170387,50.9457893372],"type":"Point"}
}