{
  "type": "Feature",
  "properties": {
    "addr:full":"Hoksentstraat 38 Hechtel-eksel Limburg 3941",
    "addr:housenumber":"38",
    "addr:postcode":"3941",
    "addr:street":"Hoksentstraat",
    "iso:country":"BE",
    "sg:address":"Hoksentstraat 38",
    "sg:city":"Hechtel-eksel",
    "sg:orig_category":"Eleveurs de bovins",
    "sg:phone":"+32 11 63 28 20",
    "sg:postcode":"3941",
    "sg:province":"Limburg",
    "wof:name":"Alfons Vanherck",
    "wof:placetype":"venue"
},
  "geometry": {"coordinates":[5.4264750481,51.1600418091],"type":"Point"}
}