{
  "type": "Feature",
  "properties": {
    "iso:country":"BE",
    "sg:address":"Gulden-sporenstraat 7",
    "sg:city":"Harelbeke",
    "sg:classifiers":[
        {
            "category":"Professional",
            "subcategory":"Computer Services",
            "type":"Services"
        }
    ],
    "sg:phone":"+32 56 71 95 69",
    "sg:postcode":"8530",
    "sg:province":"West-Vlaanderen",
    "sg:tags":[
        "-",
        "processing",
        "data",
        "software"
    ],
    "wof:name":"Blommaert Manag & Consult",
    "wof:placetype":"venue"
},
  "geometry": {"coordinates":[3.3077409267,50.8467559814],"type":"Point"}
}