{
  "type": "Feature",
  "properties": {
    "addr:full":"Rue Des Vingt-deux 23 Li\u00e8ge 1 Li\u00e8ge 4000",
    "addr:housenumber":"23;1",
    "addr:postcode":"4000",
    "addr:street":"Rue Des Vingt-Deux",
    "iso:country":"BE",
    "sg:address":"Rue Des Vingt-deux 23",
    "sg:city":"Li\u00e8ge 1",
    "sg:classifiers":[
        {
            "category":"Real Estate",
            "subcategory":"Architect",
            "type":"Services"
        }
    ],
    "sg:phone":"+32 4 253 54 44",
    "sg:postcode":"4000",
    "sg:province":"Li\u00e8ge",
    "wof:name":"Mormont A-c",
    "wof:placetype":"venue"
},
  "geometry": {"coordinates":[5.569715023,50.6282081604],"type":"Point"}
}