{
  "type": "Feature",
  "properties": {
    "addr:full":"Burg. Vandenbogaerdelaan 70 Izegem West-Vlaanderen 8870",
    "addr:housenumber":"70",
    "addr:postcode":"8870",
    "addr:street":"Burg. Vandenbogaerdelaan",
    "iso:country":"BE",
    "sg:address":"Burg. Vandenbogaerdelaan 70",
    "sg:city":"Izegem",
    "sg:orig_category":"Secr\u00e9tariats sociaux",
    "sg:phone":"+32 51 30 08 62",
    "sg:postcode":"8870",
    "sg:province":"West-Vlaanderen",
    "wof:name":"Admb",
    "wof:placetype":"venue"
},
  "geometry": {"coordinates":[3.2096319199,50.912322998],"type":"Point"}
}