{
  "type": "Feature",
  "properties": {
    "iso:country":"BE",
    "sg:address":"Guido Gezellelaan 60",
    "sg:city":"Menen",
    "sg:orig_category":"Apotheken",
    "sg:phone":"+32 56 51 21 84",
    "sg:postcode":"8930",
    "sg:province":"West-Vlaanderen",
    "wof:name":"Farmathe",
    "wof:placetype":"venue"
},
  "geometry": {"coordinates":[3.1101229191,50.8016586304],"type":"Point"}
}