{
  "type": "Feature",
  "properties": {
    "iso:country":"BE",
    "sg:address":"Kwekerijstraat 24",
    "sg:city":"Schilde",
    "sg:classifiers":[
        {
            "category":"Building & Trades",
            "subcategory":"Construction",
            "type":"Services"
        }
    ],
    "sg:phone":"+32 3 385 07 27",
    "sg:postcode":"2970",
    "sg:province":"Antwerpen",
    "sg:tags":[
        "surveyor",
        "-"
    ],
    "wof:name":"Weyers L",
    "wof:placetype":"venue"
},
  "geometry": {"coordinates":[4.5848622322,51.2375335693],"type":"Point"}
}