{
  "type": "Feature",
  "properties": {
    "addr:full":"Chauss\u00c9e De La Hulpe 186- 188 Bruxelles Bruxelles-Capitale 1170",
    "addr:housenumber":"186",
    "addr:postcode":"188;1170",
    "addr:street":"Chausse\u0301E De La Hulpe",
    "iso:country":"BE",
    "sg:address":"Chauss\u00c9e De La Hulpe 186- 188",
    "sg:city":"Bruxelles",
    "sg:orig_category":"Agences immobili\u00e8res",
    "sg:phone":"+32 2 660 70 80",
    "sg:postcode":"1170",
    "sg:province":"Bruxelles-Capitale",
    "wof:name":"Immo Dussart",
    "wof:placetype":"venue"
},
  "geometry": {"coordinates":[4.4174308777,50.7942123413],"type":"Point"}
}