{
  "type": "Feature",
  "properties": {
    "addr:full":"Vuurgatstraat 86 Overijse Vlaams-Brabant 3090",
    "addr:housenumber":"86",
    "addr:postcode":"3090",
    "addr:street":"Vuurgatstraat",
    "iso:country":"BE",
    "sg:address":"Vuurgatstraat 86",
    "sg:city":"Overijse",
    "sg:orig_category":"Articles de jardin. Animaux domestiques and accessoires. Fleurs and plantes. Souvenirs and objets ar",
    "sg:phone":"+32 2 657 40 49",
    "sg:postcode":"3090",
    "sg:province":"Vlaams-Brabant",
    "wof:name":"Vera",
    "wof:placetype":"venue"
},
  "geometry": {"coordinates":[4.4793491364,50.7851257324],"type":"Point"}
}