{
  "type": "Feature",
  "properties": {
    "addr:full":"Leopoldstraat 133 Grobbendonk Antwerpen 2280",
    "addr:housenumber":"133",
    "addr:postcode":"2280",
    "addr:street":"Leopoldstraat",
    "iso:country":"BE",
    "sg:address":"Leopoldstraat 133",
    "sg:city":"Grobbendonk",
    "sg:orig_category":"Huisdieren and benodigdheden Royal Canin",
    "sg:phone":"+32 14 51 18 61",
    "sg:postcode":"2280",
    "sg:province":"Antwerpen",
    "wof:name":"Stassijns Zaadhandel",
    "wof:placetype":"venue"
},
  "geometry": {"coordinates":[4.7193951607,51.1949806213],"type":"Point"}
}