{
  "type": "Feature",
  "properties": {
    "addr:full":"X De Cocklaan 66 Bus 8 Sint-martens-latem Oost-Vlaanderen 9830",
    "addr:housenumber":"66 bus 8",
    "addr:postcode":"9830",
    "addr:street":"De Cocklaan;Sint-Martens-Latem Oost-Vlaanderen",
    "iso:country":"BE",
    "sg:address":"X De Cocklaan 66 Bus 8",
    "sg:city":"Sint-martens-latem",
    "sg:classifiers":[
        {
            "category":"Shopping",
            "subcategory":"Computers & Home Electronics",
            "type":"Retail Goods"
        }
    ],
    "sg:phone":"+32 9 280 88 11",
    "sg:postcode":"9830",
    "sg:province":"Oost-Vlaanderen",
    "sg:tags":[
        "ontwerp",
        "computerapparatuur",
        "ontwikkeling",
        "microsoft",
        "software"
    ],
    "wof:name":"Connect-it",
    "wof:placetype":"venue"
},
  "geometry": {"coordinates":[3.6212100983,51.0038795471],"type":"Point"}
}