{
  "type": "Feature",
  "properties": {
    "addr:full":"Rue De La D\u00c9portation 79 La Louviere Hainaut 7100",
    "addr:housenumber":"79",
    "addr:postcode":"7100",
    "addr:street":"Rue De La De\u0301Portation",
    "iso:country":"BE",
    "sg:address":"Rue De La D\u00c9portation 79",
    "sg:city":"La Louviere",
    "sg:orig_category":"R\u00e9cup\u00e9ration de mati\u00e8res m\u00e9talliques recyclables and d\u00e9molisseurs de voitures",
    "sg:phone":"+32 64 22 87 12",
    "sg:postcode":"7100",
    "sg:province":"Hainaut",
    "wof:name":"Fe. Van Coppenolle",
    "wof:placetype":"venue"
},
  "geometry": {"coordinates":[4.1986479759,50.4655647278],"type":"Point"}
}