{
  "type": "Feature",
  "properties": {
    "addr:full":"Kronevoordestraat 85 Kortemark West-Vlaanderen 8610",
    "addr:housenumber":"85",
    "addr:postcode":"8610",
    "addr:street":"Kronevoordestraat",
    "iso:country":"BE",
    "sg:address":"Kronevoordestraat 85",
    "sg:city":"Kortemark",
    "sg:classifiers":[
        {
            "category":"Insurance",
            "subcategory":"Insurance Agent",
            "type":"Services"
        }
    ],
    "sg:phone":"+32 51 56 72 20",
    "sg:postcode":"8610",
    "sg:province":"West-Vlaanderen",
    "sg:tags":[
        "verzekeringsmakelaars",
        "expert"
    ],
    "wof:name":"Bureau Vandewalle H. & J.",
    "wof:placetype":"venue"
},
  "geometry": {"coordinates":[3.0044350624,51.0204658508],"type":"Point"}
}