{
  "type": "Feature",
  "properties": {
    "iso:country":"BE",
    "sg:address":"Paul Jansonlaan 36",
    "sg:city":"Anderlecht",
    "sg:orig_category":"Advocaten and juridische adviseurs",
    "sg:phone":"+32 2 644 37 10",
    "sg:postcode":"1070",
    "sg:province":"Bruxelles-Capitale",
    "wof:name":"St\u00c9phane Vanommeslaeghe",
    "wof:placetype":"venue"
},
  "geometry": {"coordinates":[4.3054251671,50.8343849182],"type":"Point"}
}