{
  "type": "Feature",
  "properties": {
    "addr:full":"Generaal Lartiguelaan 18 Sint-lambrechts-woluwe/woluwe-saint-lambert Bruxelles-Capitale 1200",
    "addr:housenumber":"18",
    "addr:postcode":"1200",
    "addr:street":"Generaal Lartiguelaan",
    "iso:country":"BE",
    "sg:address":"Generaal Lartiguelaan 18",
    "sg:city":"Sint-lambrechts-woluwe/woluwe-saint-lambert",
    "sg:orig_category":"Dierenartsen",
    "sg:phone":"+32 2 733 93 50",
    "sg:postcode":"1200",
    "sg:province":"Bruxelles-Capitale",
    "wof:name":"Aur\u00c9lien Schmoker",
    "wof:placetype":"venue"
},
  "geometry": {"coordinates":[4.4106669426,50.846988678],"type":"Point"}
}