{
  "type": "Feature",
  "properties": {
    "iso:country":"BE",
    "sg:address":"Morgenrood 10",
    "sg:city":"Schilde ('s Gravenwezel)",
    "sg:classifiers":[
        {
            "category":"Banks & Credit Unions",
            "subcategory":"Investment Brokerage",
            "type":"Services"
        }
    ],
    "sg:phone":"+32 3 658 57 61",
    "sg:postcode":"2970",
    "sg:province":"Antwerpen",
    "sg:tags":[
        "auditor"
    ],
    "wof:name":"Van Herck L",
    "wof:placetype":"venue"
},
  "geometry": {"coordinates":[4.5664172173,51.2732505798],"type":"Point"}
}