{
  "type": "Feature",
  "properties": {
    "addr:full":"Quai Marcellis 4 Li\u00e8ge 1 (li\u00e8ge 2) Li\u00e8ge 4020",
    "addr:housenumber":"4;1;2",
    "addr:postcode":"4020",
    "addr:street":"Quai Marcellis",
    "iso:country":"BE",
    "sg:address":"Quai Marcellis 4",
    "sg:city":"Li\u00e8ge 1 (li\u00e8ge 2)",
    "sg:classifiers":[
        {
            "category":"Health Services",
            "subcategory":"Doctor",
            "type":"Services"
        }
    ],
    "sg:phone":"+32 4 341 42 86",
    "sg:postcode":"4020",
    "sg:province":"Li\u00e8ge",
    "sg:tags":[
        "medicinephysicians",
        "surgeon"
    ],
    "wof:name":"Hurlet A",
    "wof:placetype":"venue"
},
  "geometry": {"coordinates":[5.5765271187,50.6361122131],"type":"Point"}
}