{
  "type": "Feature",
  "properties": {
    "iso:country":"BE",
    "sg:address":"Avenue De Reykiavik Batiment 504",
    "sg:city":"Mons",
    "sg:orig_category":"Opticiens",
    "sg:phone":"+32 65 36 46 84",
    "sg:postcode":"7010",
    "wof:name":"Ch. Roland",
    "wof:placetype":"venue"
},
  "geometry": {"coordinates":[3.9827299118,50.5000114441],"type":"Point"}
}