{
  "type": "Feature",
  "properties": {
    "addr:full":"Gustave De Stuersstraat 31 Ieper West-Vlaanderen 8900",
    "addr:housenumber":"31",
    "addr:postcode":"8900",
    "addr:street":"Gustave De Stuersstraat",
    "iso:country":"BE",
    "sg:address":"Gustave De Stuersstraat 31",
    "sg:city":"Ieper",
    "sg:orig_category":"Beautyfarms, relaxatie and lichamelijk welzijn Cosmetica and toiletartikelen Schoonheidssalons",
    "sg:phone":"+32 57 20 85 40",
    "sg:postcode":"8900",
    "sg:province":"West-Vlaanderen",
    "wof:name":"Dejaegher Christel",
    "wof:placetype":"venue"
},
  "geometry": {"coordinates":[2.8796219826,50.8498573303],"type":"Point"}
}