{
  "type": "Feature",
  "properties": {
    "addr:full":"Bouwelsesteenweg 267 Nijlen Antwerpen 2560",
    "addr:housenumber":"267",
    "addr:postcode":"2560",
    "addr:street":"Bouwelsesteenweg",
    "iso:country":"BE",
    "sg:address":"Bouwelsesteenweg 267",
    "sg:city":"Nijlen",
    "sg:classifiers":[
        {
            "category":"Building & Trades",
            "subcategory":"Cleaning & Sanitation",
            "type":"Services"
        }
    ],
    "sg:phone":"+32 3 481 95 69",
    "sg:postcode":"2560",
    "sg:province":"Antwerpen",
    "sg:tags":[
        "janitor"
    ],
    "wof:name":"Pro-clean Cvba",
    "wof:placetype":"venue"
},
  "geometry": {"coordinates":[4.6978039742,51.164691925],"type":"Point"}
}