{
  "type": "Feature",
  "properties": {
    "iso:country":"BE",
    "sg:address":"Watertorenhoek 31",
    "sg:city":"Kortrijk",
    "sg:classifiers":[
        {
            "category":"Health Services",
            "subcategory":"Health Practitioner",
            "type":"Services"
        }
    ],
    "sg:phone":"+32 56 22 31 31",
    "sg:postcode":"8500",
    "sg:province":"West-Vlaanderen",
    "sg:tags":[
        "physiotherapist"
    ],
    "wof:name":"Masselis Rose-marie",
    "wof:placetype":"venue"
},
  "geometry": {"coordinates":[3.2871279716,50.7991867065],"type":"Point"}
}