{
  "type": "Feature",
  "properties": {
    "addr:full":"Klipstraat 2ba Zoutleeuw Vlaams-Brabant 3440",
    "addr:housenumber":"2ba",
    "addr:postcode":"3440",
    "addr:street":"Klipstraat;Vlaams-Brabant",
    "iso:country":"BE",
    "sg:address":"Klipstraat 2ba",
    "sg:city":"Zoutleeuw",
    "sg:orig_category":"Entretien and r\u00e9parations de voitures",
    "sg:phone":"+32 11 78 03 82",
    "sg:postcode":"3440",
    "sg:province":"Vlaams-Brabant",
    "wof:name":"Julien Croes",
    "wof:placetype":"venue"
},
  "geometry": {"coordinates":[5.1109828949,50.858379364],"type":"Point"}
}