{
  "type": "Feature",
  "properties": {
    "iso:country":"BE",
    "sg:address":"Rue Du Vieux Moulin 45",
    "sg:city":"Bassenge",
    "sg:orig_category":"Charpentes and couvertures. Installation de menuiserie en bois and plastique. Bois Gr",
    "sg:phone":"+32 4 286 17 53",
    "sg:postcode":"4690",
    "sg:province":"Li\u00e8ge",
    "wof:name":"Jean-marie Delleur",
    "wof:placetype":"venue"
},
  "geometry": {"coordinates":[5.6635241508,50.7843513489],"type":"Point"}
}