{
  "type": "Feature",
  "properties": {
    "iso:country":"BE",
    "sg:address":"Koebrugstraat 64",
    "sg:city":"Stekene",
    "sg:classifiers":[
        {
            "category":"Home & Garden",
            "subcategory":"Carpets & Floor Coverings",
            "type":"Retail Goods"
        }
    ],
    "sg:phone":"+32 9 346 64 19",
    "sg:postcode":"9190",
    "sg:province":"Oost-Vlaanderen",
    "sg:tags":[
        "layer",
        "mosaicists"
    ],
    "wof:name":"De Rudder B&e Bvba",
    "wof:placetype":"venue"
},
  "geometry": {"coordinates":[3.9923269749,51.1805648804],"type":"Point"}
}