{
  "type": "Feature",
  "properties": {
    "addr:full":"Kolonel Begaultlaan 15b19 Leuven Vlaams-Brabant 3012",
    "addr:housenumber":"15b19",
    "addr:postcode":"3012",
    "addr:street":"Kolonel Begaultlaan",
    "iso:country":"BE",
    "sg:address":"Kolonel Begaultlaan 15b19",
    "sg:city":"Leuven",
    "sg:orig_category":"Fotografen and fotostudio's",
    "sg:phone":"+32 16 23 16 92",
    "sg:postcode":"3012",
    "sg:province":"Vlaams-Brabant",
    "wof:name":"Wim Advertising Photography",
    "wof:placetype":"venue"
},
  "geometry": {"coordinates":[4.7059540749,50.8914337158],"type":"Point"}
}