{
  "type": "Feature",
  "properties": {
    "iso:country":"BE",
    "sg:address":"Rue De La Bonne-fontaine 10",
    "sg:city":"Bertrix",
    "sg:orig_category":"D\u00e9molition d\u00b4immeubles and terrassements",
    "sg:phone":"+32 61 41 37 44",
    "sg:postcode":"6880",
    "sg:province":"Luxembourg",
    "wof:name":"Houthoofdt-collette A.",
    "wof:placetype":"venue"
},
  "geometry": {"coordinates":[5.2459039688,49.8550071716],"type":"Point"}
}