{
  "type": "Feature",
  "properties": {
    "addr:full":"Rue Cardinal Mercier 16 Mons (harveng) Hainaut 7022",
    "addr:housenumber":"16",
    "addr:postcode":"7022",
    "addr:street":"Rue Cardinal Mercier",
    "iso:country":"BE",
    "sg:address":"Rue Cardinal Mercier 16",
    "sg:city":"Mons (harveng)",
    "sg:classifiers":[
        {
            "category":"Health Services",
            "subcategory":"Doctor",
            "type":"Services"
        }
    ],
    "sg:phone":"+32 65 59 02 84",
    "sg:postcode":"7022",
    "sg:province":"Hainaut",
    "sg:tags":[
        "medicinephysicians",
        "surgeon"
    ],
    "wof:name":"Lefevre Nathalie",
    "wof:placetype":"venue"
},
  "geometry": {"coordinates":[3.9863359928,50.3962898254],"type":"Point"}
}