{
  "type": "Feature",
  "properties": {
    "addr:full":"Avenue L\u00c9on Jourez 51 Braine-l\u00b4alleud Brabant Wallon 1420",
    "addr:housenumber":"51",
    "addr:postcode":"1420",
    "addr:street":"Avenue Le\u0301On Jourez;Brabant Wallon",
    "iso:country":"BE",
    "sg:address":"Avenue L\u00c9on Jourez 51",
    "sg:city":"Braine-l\u00b4alleud",
    "sg:orig_category":"Advocaten and juridische adviseurs",
    "sg:phone":"+32 2 384 59 68",
    "sg:postcode":"1420",
    "sg:province":"Brabant Wallon",
    "wof:name":"Nathalie Evrard",
    "wof:placetype":"venue"
},
  "geometry": {"coordinates":[4.3715782166,50.6843566895],"type":"Point"}
}