{
  "type": "Feature",
  "properties": {
    "iso:country":"BE",
    "sg:address":"Place De La Vieille Halle Aux Bl\u00e9s 45",
    "sg:city":"Bruxelles",
    "sg:classifiers":[
        {
            "category":"Tea Room",
            "subcategory":"None",
            "type":"Food & Drink"
        }
    ],
    "sg:phone":"+32 2 502 45 59",
    "sg:postcode":"1000",
    "sg:province":"Bruxelles-Capitale",
    "sg:tags":[
        "whol",
        "-",
        "broker"
    ],
    "wof:name":"Palais Des Th\u00e9s (le)",
    "wof:placetype":"venue"
},
  "geometry": {"coordinates":[4.3526358604,50.8442611694],"type":"Point"}
}