{
  "type": "Feature",
  "properties": {
    "iso:country":"BE",
    "sg:address":"Vredelaan 65",
    "sg:city":"Kortrijk",
    "sg:orig_category":"Horloges, m\u00e9taux pr\u00e9cieux and bijoux Gr",
    "sg:phone":"+32 56 20 40 87",
    "sg:postcode":"8500",
    "sg:province":"West-Vlaanderen",
    "wof:name":"Gossieaux P",
    "wof:placetype":"venue"
},
  "geometry": {"coordinates":[3.2880520821,50.8272399902],"type":"Point"}
}