{
  "type": "Feature",
  "properties": {
    "iso:country":"BE",
    "sg:address":"Kruisstraat 30b1",
    "sg:city":"Putte",
    "sg:orig_category":"Producteurs de l\u00e9gumes",
    "sg:phone":"+32 15 75 54 34",
    "sg:postcode":"2580",
    "sg:province":"Antwerpen",
    "wof:name":"Willy Frans",
    "wof:placetype":"venue"
},
  "geometry": {"coordinates":[4.5902900696,51.0469245911],"type":"Point"}
}