{
  "type": "Feature",
  "properties": {
    "addr:full":"Albert Rowiesstraat 12ba Hoeilaart Vlaams-Brabant 1560",
    "addr:housenumber":"12ba",
    "addr:postcode":"1560",
    "addr:street":"Albert Rowiesstraat",
    "iso:country":"BE",
    "sg:address":"Albert Rowiesstraat 12ba",
    "sg:city":"Hoeilaart",
    "sg:orig_category":"Artistes ind\u00e9pendants",
    "sg:phone":"+32 2 657 36 87",
    "sg:postcode":"1560",
    "sg:province":"Vlaams-Brabant",
    "wof:name":"P. De Gryse",
    "wof:placetype":"venue"
},
  "geometry": {"coordinates":[4.473033905,50.762462616],"type":"Point"}
}