{
  "type": "Feature",
  "properties": {
    "addr:full":"Genststraat 26 Beersel Vlaams-Brabant 1651",
    "addr:housenumber":"26",
    "addr:postcode":"1651",
    "addr:street":"Genststraat",
    "iso:country":"BE",
    "sg:address":"Genststraat 26",
    "sg:city":"Beersel",
    "sg:orig_category":"Eleveurs and marchands de porcs",
    "sg:phone":"+32 2 356 96 15",
    "sg:postcode":"1651",
    "sg:province":"Vlaams-Brabant",
    "wof:name":"Willy Daneau",
    "wof:placetype":"venue"
},
  "geometry": {"coordinates":[4.2724809647,50.761013031],"type":"Point"}
}