{
  "type": "Feature",
  "properties": {
    "addr:full":"Burg. Van Loonstraat 12 Oud-turnhout Antwerpen 2360",
    "addr:housenumber":"12",
    "addr:postcode":"2360",
    "addr:street":"Burg. Van Loonstraat",
    "iso:country":"BE",
    "sg:address":"Burg. Van Loonstraat 12",
    "sg:city":"Oud-turnhout",
    "sg:orig_category":"Warenhuizen",
    "sg:phone":"+32 14 43 79 24",
    "sg:postcode":"2360",
    "sg:province":"Antwerpen",
    "wof:name":"Danny Maes",
    "wof:placetype":"venue"
},
  "geometry": {"coordinates":[4.982629776,51.3177986145],"type":"Point"}
}