{
  "type": "Feature",
  "properties": {
    "addr:full":"Industrieweg 7 Boom Antwerpen 2850",
    "addr:housenumber":"7",
    "addr:postcode":"2850",
    "addr:street":"Industrieweg",
    "iso:country":"BE",
    "sg:address":"Industrieweg 7",
    "sg:city":"Boom",
    "sg:classifiers":[
        {
            "category":"Banks & Credit Unions",
            "subcategory":"Atm",
            "type":"Services"
        }
    ],
    "sg:phone":"+32 3 870 36 80",
    "sg:postcode":"2850",
    "sg:province":"Antwerpen",
    "sg:tags":[
        "belt",
        "chain",
        "conveyor"
    ],
    "wof:name":"Bmcs Nv",
    "wof:placetype":"venue"
},
  "geometry": {"coordinates":[4.3536720276,51.0997276306],"type":"Point"}
}