{
  "type": "Feature",
  "properties": {
    "addr:full":"Kaanal Noord 1461 Bree Limburg 3960",
    "addr:housenumber":"1461",
    "addr:postcode":"3960",
    "addr:street":"Noord",
    "iso:country":"BE",
    "sg:address":"Kaanal Noord 1461",
    "sg:city":"Bree",
    "sg:orig_category":"B\u00e9ton pr\u00eat \u00e0 l'emploi Fab. Rev\u00eatements de sols and murs",
    "sg:phone":"+32 89 46 28 38",
    "sg:postcode":"3960",
    "sg:province":"Limburg",
    "wof:name":"N.l.b",
    "wof:placetype":"venue"
},
  "geometry": {"coordinates":[5.5944190025,51.1405677795],"type":"Point"}
}