{
  "type": "Feature",
  "properties": {
    "iso:country":"BE",
    "sg:address":"Rue De Saint-l\u00e9ger 28",
    "sg:city":"Pecq",
    "sg:classifiers":[
        {
            "category":"Home & Garden",
            "subcategory":"Kitchen Supply",
            "type":"Retail Goods"
        }
    ],
    "sg:phone":"+32 69 55 61 74",
    "sg:postcode":"7740",
    "sg:province":"Hainaut",
    "sg:tags":[
        "equipment",
        "baker",
        "-"
    ],
    "wof:name":"Bossut Ghislain",
    "wof:placetype":"venue"
},
  "geometry": {"coordinates":[3.3347549438,50.6907272339],"type":"Point"}
}