{
  "type": "Feature",
  "properties": {
    "addr:full":"Chauss\u00c9e Verte 94b1 Crisn\u00c9e Li\u00e8ge 4367",
    "addr:housenumber":"94b1",
    "addr:postcode":"4367",
    "addr:street":"Chausse\u0301E Verte",
    "iso:country":"BE",
    "sg:address":"Chauss\u00c9e Verte 94b1",
    "sg:city":"Crisn\u00c9e",
    "sg:classifiers":[
        {
            "category":"Restaurant",
            "type":"Food & Drink"
        }
    ],
    "sg:phone":"+32 4 257 76 92",
    "sg:postcode":"4367",
    "sg:province":"Li\u00e8ge",
    "wof:name":"Tea-room L\u00b4arnica",
    "wof:placetype":"venue"
},
  "geometry": {"coordinates":[5.4043979645,50.7035980225],"type":"Point"}
}