{
  "type": "Feature",
  "properties": {
    "iso:country":"BE",
    "sg:address":"Maastrichterstraat 95",
    "sg:city":"Tongeren",
    "sg:orig_category":"Chaussures",
    "sg:phone":"+32 12 39 14 05",
    "sg:postcode":"3700",
    "sg:province":"Limburg",
    "wof:name":"Huis Carthago",
    "wof:placetype":"venue"
},
  "geometry": {"coordinates":[5.4775710106,50.783744812],"type":"Point"}
}