{
  "type": "Feature",
  "properties": {
    "addr:full":"Place Roi Albert I 1 Rochefort Namur 5580",
    "addr:housenumber":"1",
    "addr:postcode":"5580",
    "addr:street":"Place Roi Albert I",
    "iso:country":"BE",
    "sg:address":"Place Roi Albert I 1",
    "sg:city":"Rochefort",
    "sg:classifiers":[
        {
            "category":"Utilities",
            "subcategory":"Electric",
            "type":"Services"
        }
    ],
    "sg:phone":"+32 84 22 06 19",
    "sg:postcode":"5580",
    "sg:province":"Namur",
    "sg:tags":[
        "energy",
        "renewable"
    ],
    "wof:name":"Hydroval Sa",
    "wof:placetype":"venue"
},
  "geometry": {"coordinates":[5.2228631973,50.1577644348],"type":"Point"}
}