{
  "type": "Feature",
  "properties": {
    "iso:country":"BE",
    "sg:address":"Avenue De La F\u00d4ret De Soignes 373",
    "sg:city":"Sint-genesius-rode",
    "sg:orig_category":"Meubelzaken, woning- and keukeninrichting",
    "sg:phone":"+32 2 358 32 46",
    "sg:postcode":"1640",
    "sg:province":"Vlaams-Brabant",
    "wof:name":"Duchesse Bris\u00c9e",
    "wof:placetype":"venue"
},
  "geometry": {"coordinates":[4.3819108009,50.7583808899],"type":"Point"}
}