{
  "type": "Feature",
  "properties": {
    "addr:full":"Keiberg 13 Lierde Oost-Vlaanderen 9572",
    "addr:housenumber":"13",
    "addr:postcode":"9572",
    "addr:street":"Keiberg",
    "iso:country":"BE",
    "sg:address":"Keiberg 13",
    "sg:city":"Lierde",
    "sg:orig_category":"Producteurs de l\u00e9gumes",
    "sg:phone":"+32 54 41 32 44",
    "sg:postcode":"9572",
    "sg:province":"Oost-Vlaanderen",
    "wof:name":"Karel De Staercke",
    "wof:placetype":"venue"
},
  "geometry": {"coordinates":[3.8462779522,50.8027877808],"type":"Point"}
}