{
  "type": "Feature",
  "properties": {
    "addr:full":"Roeselaarsestraat 234 Moorslede West-Vlaanderen 8890",
    "addr:housenumber":"234",
    "addr:postcode":"8890",
    "addr:street":"Roeselaarsestraat",
    "iso:country":"BE",
    "sg:address":"Roeselaarsestraat 234",
    "sg:city":"Moorslede",
    "sg:classifiers":[
        {
            "category":"Food & Beverages",
            "subcategory":"Groceries & Convenience Stores",
            "type":"Retail Goods"
        }
    ],
    "sg:phone":"+32 51 77 75 13",
    "sg:postcode":"8890",
    "sg:province":"West-Vlaanderen",
    "sg:tags":[
        "grocer"
    ],
    "wof:name":"Roose-vantomme",
    "wof:placetype":"venue"
},
  "geometry": {"coordinates":[3.0775969028,50.9131393433],"type":"Point"}
}