{
  "type": "Feature",
  "properties": {
    "addr:full":"Rue Joseph Jadot 54 Orp-jauche Brabant Wallon 1350",
    "addr:housenumber":"54",
    "addr:postcode":"1350",
    "addr:street":"Rue Joseph Jadot",
    "iso:country":"BE",
    "sg:address":"Rue Joseph Jadot 54",
    "sg:city":"Orp-jauche",
    "sg:orig_category":"Sportclubs",
    "sg:phone":"+32 19 63 35 71",
    "sg:postcode":"1350",
    "sg:province":"Brabant Wallon",
    "wof:name":"A.m.c. Orp-le-grand",
    "wof:placetype":"venue"
},
  "geometry": {"coordinates":[4.9913949966,50.692741394],"type":"Point"}
}