{
  "type": "Feature",
  "properties": {
    "addr:full":"Merchtemsesteenweg 93c Meise (wolvertem) Vlaams-Brabant 1861",
    "addr:housenumber":"93c",
    "addr:postcode":"1861",
    "addr:street":"Merchtemsesteenweg",
    "iso:country":"BE",
    "sg:address":"Merchtemsesteenweg 93c",
    "sg:city":"Meise (wolvertem)",
    "sg:classifiers":[
        {
            "category":"Autos & Motor Vehicles",
            "subcategory":"Motorcycle Sales",
            "type":"Retail Goods"
        }
    ],
    "sg:phone":"+32 2 269 30 17",
    "sg:postcode":"1861",
    "sg:province":"Vlaams-Brabant",
    "sg:tags":[
        "motorbike"
    ],
    "wof:name":"Raiglot Moto",
    "wof:placetype":"venue"
},
  "geometry": {"coordinates":[4.2947220802,50.9523010254],"type":"Point"}
}