{
  "type": "Feature",
  "properties": {
    "iso:country":"BE",
    "sg:address":"Rue Du Cimeti\u00e8re 21",
    "sg:city":"Fourons (fouron-le-comte)",
    "sg:classifiers":[
        {
            "category":"Building & Trades",
            "subcategory":"Construction",
            "type":"Services"
        }
    ],
    "sg:phone":"+32 4 381 01 55",
    "sg:postcode":"3798",
    "sg:province":"Limburg",
    "sg:tags":[
        "carpenter"
    ],
    "wof:name":"Droeven M",
    "wof:placetype":"venue"
},
  "geometry": {"coordinates":[5.7604289055,50.7605285645],"type":"Point"}
}