{
  "type": "Feature",
  "properties": {
    "addr:full":"Avelgemstraat 250 Zwevegem West-Vlaanderen 8550",
    "addr:housenumber":"250",
    "addr:postcode":"8550",
    "addr:street":"Avelgemstraat",
    "iso:country":"BE",
    "sg:address":"Avelgemstraat 250",
    "sg:city":"Zwevegem",
    "sg:classifiers":[
        {
            "category":"Real Estate",
            "subcategory":"Architect",
            "type":"Services"
        }
    ],
    "sg:phone":"+32 56 75 55 43",
    "sg:postcode":"8550",
    "sg:province":"West-Vlaanderen",
    "wof:name":"Libbrecht G",
    "wof:placetype":"venue"
},
  "geometry": {"coordinates":[3.3479480743,50.8013420105],"type":"Point"}
}