{
  "type": "Feature",
  "properties": {
    "iso:country":"BE",
    "sg:address":"Baan Naar Bree 121a",
    "sg:city":"Peer",
    "sg:classifiers":[
        {
            "category":"Manufacturing",
            "subcategory":"Furniture",
            "type":"Manufacturing & Wholesale Goods"
        }
    ],
    "sg:phone":"+32 11 61 06 70",
    "sg:postcode":"3990",
    "sg:province":"Limburg",
    "sg:tags":[
        "design",
        "-"
    ],
    "wof:name":"Interieur Plus",
    "wof:placetype":"venue"
},
  "geometry": {"coordinates":[5.4986982346,51.1355247498],"type":"Point"}
}