{
  "type": "Feature",
  "properties": {
    "iso:country":"BE",
    "sg:address":"Nieuwstraat 7",
    "sg:city":"Aartselaar",
    "sg:orig_category":"Kapsalons",
    "sg:phone":"+32 3 887 10 75",
    "sg:postcode":"2630",
    "sg:province":"Antwerpen",
    "wof:name":"Sacha Van Och",
    "wof:placetype":"venue"
},
  "geometry": {"coordinates":[4.3890919685,51.1303710938],"type":"Point"}
}