{
  "type": "Feature",
  "properties": {
    "addr:full":"Dendermondsesteenweg Overmere Oost-Vlaanderen 9290",
    "addr:postcode":"9290",
    "addr:street":"Dendermondsesteenweg;Oost-Vlaanderen",
    "iso:country":"BE",
    "sg:address":"Dendermondsesteenweg",
    "sg:city":"Overmere",
    "sg:orig_category":"Parfumeries. Centres de relaxation and bien-\u00eatre. Instituts de beaut\u00e9",
    "sg:phone":"+32 9 222 32 90",
    "sg:postcode":"9290",
    "sg:province":"Oost-Vlaanderen",
    "wof:name":"Pimm\u00b4s",
    "wof:placetype":"venue"
},
  "geometry": {"coordinates":[3.9690899849,51.0484733582],"type":"Point"}
}