{
  "type": "Feature",
  "properties": {
    "addr:full":"Rue Du Gymnase 48 Verviers Li\u00e8ge 4800",
    "addr:housenumber":"48",
    "addr:postcode":"4800",
    "addr:street":"Rue Du Gymnase",
    "iso:country":"BE",
    "sg:address":"Rue Du Gymnase 48",
    "sg:city":"Verviers",
    "sg:orig_category":"Kapsalons",
    "sg:phone":"+32 87 31 61 26",
    "sg:postcode":"4800",
    "sg:province":"Li\u00e8ge",
    "wof:name":"Baln\u00c9 Hair",
    "wof:placetype":"venue"
},
  "geometry": {"coordinates":[5.8598928452,50.5937461853],"type":"Point"}
}