{
  "type": "Feature",
  "properties": {
    "iso:country":"BE",
    "sg:address":"Rue De La Lib\u00c9ration 8",
    "sg:city":"Verviers",
    "sg:orig_category":"Rev\u00eatements pour sols and murs",
    "sg:phone":"+32 87 22 40 70",
    "sg:postcode":"4800",
    "sg:province":"Li\u00e8ge",
    "wof:name":"Anthony Palange",
    "wof:placetype":"venue"
},
  "geometry": {"coordinates":[5.8677239418,50.5652732849],"type":"Point"}
}