{
  "type": "Feature",
  "properties": {
    "iso:country":"BE",
    "sg:address":"Lange Breestraat 79",
    "sg:city":"Lebbeke",
    "sg:orig_category":"Verhuisdiensten",
    "sg:phone":"+32 52 35 86 89",
    "sg:postcode":"9280",
    "sg:province":"Oost-Vlaanderen",
    "wof:name":"Moens Paul Vervoer",
    "wof:placetype":"venue"
},
  "geometry": {"coordinates":[4.1546339989,50.9849357605],"type":"Point"}
}