{
  "type": "Feature",
  "properties": {
    "addr:full":"Rue Reine Astrid 52 Saint-georges-sur-meuse Li\u00e8ge 4470",
    "addr:housenumber":"52",
    "addr:postcode":"4470",
    "addr:street":"Rue Reine Astrid",
    "iso:country":"BE",
    "sg:address":"Rue Reine Astrid 52",
    "sg:city":"Saint-georges-sur-meuse",
    "sg:orig_category":"Diverse textielproducten Fab Drukkerijen and copyshops Kleding Werk- and beschermkleding Fab",
    "sg:phone":"+32 4 275 03 06",
    "sg:postcode":"4470",
    "sg:province":"Li\u00e8ge",
    "wof:name":"D-clic Broderie",
    "wof:placetype":"venue"
},
  "geometry": {"coordinates":[5.3590202332,50.5849304199],"type":"Point"}
}