{
  "type": "Feature",
  "properties": {
    "addr:full":"Baron-holvoetlaan 62 Moorslede West-Vlaanderen 8890",
    "addr:housenumber":"62",
    "addr:postcode":"8890",
    "addr:street":"Baron-Holvoetlaan",
    "iso:country":"BE",
    "sg:address":"Baron-holvoetlaan 62",
    "sg:city":"Moorslede",
    "sg:orig_category":"Charpentes and couvertures. Travaux de pl\u00e2trage",
    "sg:phone":"+32 56 50 25 23",
    "sg:postcode":"8890",
    "sg:province":"West-Vlaanderen",
    "wof:name":"Deroo Claude",
    "wof:placetype":"venue"
},
  "geometry": {"coordinates":[3.1037299633,50.8473434448],"type":"Point"}
}