{
  "type": "Feature",
  "properties": {
    "addr:full":"Rue D'ans 153 Li\u00c8ge Li\u00e8ge 4000",
    "addr:housenumber":"153",
    "addr:postcode":"4000",
    "addr:street":"Rue D'Ans",
    "iso:country":"BE",
    "sg:address":"Rue D'ans 153",
    "sg:city":"Li\u00c8ge",
    "sg:orig_category":"Baby- and kinderkleding",
    "sg:phone":"+32 4 247 04 98",
    "sg:postcode":"4000",
    "sg:province":"Li\u00e8ge",
    "wof:name":"Maison z",
    "wof:placetype":"venue"
},
  "geometry": {"coordinates":[5.5383172035,50.6366958618],"type":"Point"}
}