{
  "type": "Feature",
  "properties": {
    "iso:country":"BE",
    "sg:address":"Chasse De Saint-ghislain 4",
    "sg:city":"Boussu",
    "sg:classifiers":[
        {
            "category":"Restaurant",
            "type":"Food & Drink"
        }
    ],
    "sg:phone":"+32 65 79 18 52",
    "sg:postcode":"7300",
    "sg:province":"Hainaut",
    "wof:name":"Restaurant Le Minaret",
    "wof:placetype":"venue"
},
  "geometry": {"coordinates":[3.7981259823,50.4383926392],"type":"Point"}
}