{
  "type": "Feature",
  "properties": {
    "iso:country":"BE",
    "sg:address":"Rue Darchis 10",
    "sg:city":"Li\u00e8ge 1",
    "sg:classifiers":[
        {
            "category":"Wholesale",
            "subcategory":"Books, Periodicals, & Newspapers",
            "type":"Manufacturing & Wholesale Goods"
        }
    ],
    "sg:phone":"+32 4 223 00 54",
    "sg:postcode":"4000",
    "sg:province":"Li\u00e8ge",
    "sg:tags":[
        "publisher"
    ],
    "wof:name":"Vista Editions",
    "wof:placetype":"venue"
},
  "geometry": {"coordinates":[5.5670018196,50.637348175],"type":"Point"}
}