{
  "type": "Feature",
  "properties": {
    "iso:country":"BE",
    "sg:address":"Sint-renildestraat 12",
    "sg:city":"Hamme",
    "sg:orig_category":"Instituts de beaut\u00e9",
    "sg:phone":"+32 52 48 09 14",
    "sg:postcode":"9220",
    "sg:province":"Oost-Vlaanderen",
    "wof:name":"Annick Pauwels",
    "wof:placetype":"venue"
},
  "geometry": {"coordinates":[4.1344180107,51.083190918],"type":"Point"}
}