{
  "type": "Feature",
  "properties": {
    "iso:country":"BE",
    "sg:address":"Rue D'udange 43",
    "sg:city":"Messancy (wolkrange)",
    "sg:classifiers":[
        {
            "category":"Health Services",
            "subcategory":"Doctor",
            "type":"Services"
        }
    ],
    "sg:phone":"+32 63 22 81 54",
    "sg:postcode":"6780",
    "sg:province":"Luxembourg",
    "sg:tags":[
        "medicinephysicians",
        "surgeon"
    ],
    "wof:name":"Fontaine R",
    "wof:placetype":"venue"
},
  "geometry": {"coordinates":[5.7945051193,49.631652832],"type":"Point"}
}