{
  "type": "Feature",
  "properties": {
    "addr:full":"Rue De Cuesmes 9 Mons (jemappes) Hainaut 7012",
    "addr:housenumber":"9",
    "addr:postcode":"7012",
    "addr:street":"Rue De Cuesmes",
    "iso:country":"BE",
    "sg:address":"Rue De Cuesmes 9",
    "sg:city":"Mons (jemappes)",
    "sg:classifiers":[
        {
            "category":"Food & Beverages",
            "subcategory":"Groceries & Convenience Stores",
            "type":"Retail Goods"
        }
    ],
    "sg:phone":"+32 65 82 36 62",
    "sg:postcode":"7012",
    "sg:province":"Hainaut",
    "sg:tags":[
        "grocer"
    ],
    "wof:name":"Lina (chez)",
    "wof:placetype":"venue"
},
  "geometry": {"coordinates":[3.9449210167,50.4402542114],"type":"Point"}
}