{
  "type": "Feature",
  "properties": {
    "addr:full":"Rue De L'etoile 2 Assesse (sart-bernard) Namur 5330",
    "addr:housenumber":"2",
    "addr:postcode":"5330",
    "addr:street":"Rue De L'Etoile",
    "iso:country":"BE",
    "sg:address":"Rue De L'etoile 2",
    "sg:city":"Assesse (sart-bernard)",
    "sg:classifiers":[
        {
            "category":"Building & Trades",
            "subcategory":"Construction",
            "type":"Services"
        }
    ],
    "sg:phone":"+32 81 40 26 27",
    "sg:postcode":"5330",
    "sg:province":"Namur",
    "sg:tags":[
        "carpenter"
    ],
    "wof:name":"Huybens L (menuiserie) Sprl",
    "wof:placetype":"venue"
},
  "geometry": {"coordinates":[4.9543061256,50.4060668945],"type":"Point"}
}