{
  "type": "Feature",
  "properties": {
    "iso:country":"BE",
    "sg:address":"Beestenmarkt 17",
    "sg:city":"Halle",
    "sg:classifiers":[
        {
            "category":"Bars & Pubs",
            "type":"Food & Drink"
        }
    ],
    "sg:phone":"+32 2 356 34 19",
    "sg:postcode":"1500",
    "sg:province":"Vlaams-Brabant",
    "wof:name":"Ambiorix",
    "wof:placetype":"venue"
},
  "geometry": {"coordinates":[4.2362599373,50.7361450195],"type":"Point"}
}