{
  "type": "Feature",
  "properties": {
    "addr:full":"Avenue Henri Matisse 16 Bruxelles (evere) Bruxelles-Capitale 1140",
    "addr:housenumber":"16",
    "addr:postcode":"1140",
    "addr:street":"Avenue Henri Matisse",
    "iso:country":"BE",
    "sg:address":"Avenue Henri Matisse 16",
    "sg:city":"Bruxelles (evere)",
    "sg:classifiers":[
        {
            "category":"Banks & Credit Unions",
            "subcategory":"Financial Services",
            "type":"Services"
        }
    ],
    "sg:phone":"+32 2 728 95 30",
    "sg:postcode":"1140",
    "sg:province":"Bruxelles-Capitale",
    "sg:tags":[
        "debt",
        "recovery"
    ],
    "wof:name":"Fiducre Nv",
    "wof:placetype":"venue"
},
  "geometry": {"coordinates":[4.4106411934,50.8764152527],"type":"Point"}
}