{
  "type": "Feature",
  "properties": {
    "addr:full":"Ankelaarstraat 2 Tielt West-Vlaanderen 8700",
    "addr:housenumber":"2",
    "addr:postcode":"8700",
    "addr:street":"Ankelaarstraat",
    "iso:country":"BE",
    "sg:address":"Ankelaarstraat 2",
    "sg:city":"Tielt",
    "sg:orig_category":"Gespecialiseerde residenti\u00eble bouw",
    "sg:phone":"+32 51 63 64 38",
    "sg:postcode":"8700",
    "sg:province":"West-Vlaanderen",
    "wof:name":"Etienne Van Parijs",
    "wof:placetype":"venue"
},
  "geometry": {"coordinates":[3.3899230957,50.9921913147],"type":"Point"}
}