{
  "type": "Feature",
  "properties": {
    "addr:full":"Rue Charles Dubois 6 Ottignies-louvain-la-neuve Brabant Wallon 1342",
    "addr:housenumber":"6",
    "addr:postcode":"1342",
    "addr:street":"Rue Charles Dubois",
    "iso:country":"BE",
    "sg:address":"Rue Charles Dubois 6",
    "sg:city":"Ottignies-louvain-la-neuve",
    "sg:orig_category":"Supermarkten Voedingsspeciaalzaken",
    "sg:phone":"+32 10 41 12 00",
    "sg:postcode":"1342",
    "sg:province":"Brabant Wallon",
    "wof:name":"Louis Delhaize",
    "wof:placetype":"venue"
},
  "geometry": {"coordinates":[4.5738577843,50.6849517822],"type":"Point"}
}