{
  "type": "Feature",
  "properties": {
    "addr:full":"Route Charlemagne 120 Welkenraedt Li\u00e8ge 4841",
    "addr:housenumber":"120",
    "addr:postcode":"4841",
    "addr:street":"Route Charlemagne",
    "iso:country":"BE",
    "sg:address":"Route Charlemagne 120",
    "sg:city":"Welkenraedt",
    "sg:orig_category":"Herstellingen and onderhoud van auto's",
    "sg:phone":"+32 87 88 39 85",
    "sg:postcode":"4841",
    "sg:province":"Li\u00e8ge",
    "wof:name":"Car-wash Fidelity",
    "wof:placetype":"venue"
},
  "geometry": {"coordinates":[5.9298272133,50.6768951416],"type":"Point"}
}