{
  "type": "Feature",
  "properties": {
    "addr:full":"Chauss\u00c9e De Binche 177bc1 Mons Hainaut 7000",
    "addr:housenumber":"177bc1",
    "addr:postcode":"7000",
    "addr:street":"Chausse\u0301E De Binche;Hainaut",
    "iso:country":"BE",
    "sg:address":"Chauss\u00c9e De Binche 177bc1",
    "sg:city":"Mons",
    "sg:orig_category":"Boekhouders",
    "sg:phone":"+32 65 34 90 12",
    "sg:postcode":"7000",
    "sg:province":"Hainaut",
    "wof:name":"Louis-philippe Thys",
    "wof:placetype":"venue"
},
  "geometry": {"coordinates":[3.9872169495,50.4501686096],"type":"Point"}
}