{
  "type": "Feature",
  "properties": {
    "iso:country":"BE",
    "sg:address":"Rue De Serinchamps 16",
    "sg:city":"Rochefort (buissonville)",
    "sg:classifiers":[
        {
            "category":"Building & Trades",
            "subcategory":"Electrical",
            "type":"Services"
        }
    ],
    "sg:phone":"+32 84 21 34 84",
    "sg:postcode":"5580",
    "sg:province":"Namur",
    "sg:tags":[
        "electric",
        "-",
        "housewiring",
        "contractor"
    ],
    "wof:name":"Dumont J Ets",
    "wof:placetype":"venue"
},
  "geometry": {"coordinates":[5.2233490944,50.2043571472],"type":"Point"}
}