{
  "type": "Feature",
  "properties": {
    "iso:country":"BE",
    "sg:address":"Rue Du Culot 22b1",
    "sg:city":"Beauvechain",
    "sg:orig_category":"Woningbouw",
    "sg:phone":"+32 10 86 72 74",
    "sg:postcode":"1320",
    "sg:province":"Brabant Wallon",
    "wof:name":"Didier Huget",
    "wof:placetype":"venue"
},
  "geometry": {"coordinates":[4.7450509071,50.7865257263],"type":"Point"}
}