{
  "type": "Feature",
  "properties": {
    "iso:country":"BE",
    "sg:address":"De Ster 49",
    "sg:city":"Hove",
    "sg:classifiers":[
        {
            "category":"Real Estate",
            "subcategory":"Architect",
            "type":"Services"
        }
    ],
    "sg:phone":"+32 3 455 99 59",
    "sg:postcode":"2540",
    "sg:province":"Antwerpen",
    "wof:name":"Cols T",
    "wof:placetype":"venue"
},
  "geometry": {"coordinates":[4.4643731117,51.1609535217],"type":"Point"}
}