{
  "type": "Feature",
  "properties": {
    "iso:country":"BE",
    "sg:address":"Place Du March\u00c9 10",
    "sg:city":"Vise",
    "sg:orig_category":"WAPENS AND MUNITIE",
    "sg:phone":"+32 4 374 21 28",
    "sg:postcode":"4600",
    "sg:province":"Li\u00e8ge",
    "wof:name":"Armurerie Des Remparts",
    "wof:placetype":"venue"
},
  "geometry": {"coordinates":[5.6968197823,50.7337989807],"type":"Point"}
}