{
  "type": "Feature",
  "properties": {
    "addr:full":"Blarenbergln 19 Mechelen Antwerpen 2800",
    "addr:housenumber":"19",
    "addr:postcode":"2800",
    "addr:street":"Blarenbergln",
    "iso:country":"BE",
    "sg:address":"Blarenbergln 19",
    "sg:city":"Mechelen",
    "sg:classifiers":[
        {
            "category":"Professional",
            "subcategory":"Business Services",
            "type":"Services"
        }
    ],
    "sg:phone":"+32 15 28 78 50",
    "sg:postcode":"2800",
    "sg:province":"Antwerpen",
    "sg:tags":[
        "training",
        "advice"
    ],
    "wof:name":"Flexcom-azlan Nv",
    "wof:placetype":"venue"
},
  "geometry": {"coordinates":[4.4500389099,51.0522651672],"type":"Point"}
}