{
  "type": "Feature",
  "properties": {
    "addr:full":"Oude Putsebaan 24 Keerbergen Vlaams-Brabant 3140",
    "addr:housenumber":"24",
    "addr:postcode":"3140",
    "addr:street":"Oude Putsebaan",
    "iso:country":"BE",
    "sg:address":"Oude Putsebaan 24",
    "sg:city":"Keerbergen",
    "sg:classifiers":[
        {
            "category":"Professional",
            "subcategory":"Management & Consulting",
            "type":"Services"
        }
    ],
    "sg:phone":"+32 15 52 70 22",
    "sg:postcode":"3140",
    "sg:province":"Vlaams-Brabant",
    "sg:tags":[
        "consultant"
    ],
    "wof:name":"Queo Bvba",
    "wof:placetype":"venue"
},
  "geometry": {"coordinates":[4.6466388702,50.9963989258],"type":"Point"}
}