{
  "type": "Feature",
  "properties": {
    "addr:full":"Avenue Emile Verhaeren 106 Schaarbeek/schaerbeek Bruxelles-Capitale 1030",
    "addr:housenumber":"106",
    "addr:postcode":"1030",
    "addr:street":"Avenue Emile Verhaeren",
    "iso:country":"BE",
    "sg:address":"Avenue Emile Verhaeren 106",
    "sg:city":"Schaarbeek/schaerbeek",
    "sg:orig_category":"Studios photographiques",
    "sg:phone":"+32 2 245 34 36",
    "sg:postcode":"1030",
    "sg:province":"Bruxelles-Capitale",
    "wof:name":"A. Daussin",
    "wof:placetype":"venue"
},
  "geometry": {"coordinates":[4.3833217621,50.8740005493],"type":"Point"}
}