{
  "type": "Feature",
  "properties": {
    "addr:full":"Beukenlaan 47 Dendermonde Oost-Vlaanderen 9200",
    "addr:housenumber":"47",
    "addr:postcode":"9200",
    "addr:street":"Beukenlaan;Oost-Vlaanderen",
    "iso:country":"BE",
    "sg:address":"Beukenlaan 47",
    "sg:city":"Dendermonde",
    "sg:orig_category":"Rev\u00eatements de sols and murs. Magasins sp\u00e9cialis\u00e9s",
    "sg:phone":"+32 52 22 33 65",
    "sg:postcode":"9200",
    "sg:province":"Oost-Vlaanderen",
    "wof:name":"Antiek Peelman",
    "wof:placetype":"venue"
},
  "geometry": {"coordinates":[4.1174330711,51.029335022],"type":"Point"}
}