{
  "type": "Feature",
  "properties": {
    "iso:country":"BE",
    "sg:address":"Weverstraat 34",
    "sg:city":"Hechtel-eksel (eksel)",
    "sg:classifiers":[
        {
            "category":"Professional",
            "type":"Services"
        }
    ],
    "sg:phone":"+32 11 73 19 64",
    "sg:postcode":"3941",
    "sg:province":"Limburg",
    "sg:tags":[
        "surveyor",
        "-",
        "valuer"
    ],
    "wof:name":"Wijnands",
    "wof:placetype":"venue"
},
  "geometry": {"coordinates":[5.3815917969,51.1571731567],"type":"Point"}
}