{
  "type": "Feature",
  "properties": {
    "iso:country":"BE",
    "sg:address":"29",
    "sg:city":"Rue Edouard-andre 6762 Saint-mard",
    "sg:classifiers":[
        {
            "category":"Manufacturing",
            "subcategory":"Metals",
            "type":"Manufacturing & Wholesale Goods"
        }
    ],
    "sg:phone":"+32 63 57 17 60",
    "sg:postcode":"29",
    "sg:tags":[
        "metallurgy",
        "-",
        "metalworking",
        "metallic",
        "machine",
        "engineering",
        "finished",
        "mechanical"
    ],
    "wof:name":"Etablissements Yvan Hutin Sprl",
    "wof:placetype":"venue"
},
  "geometry": {"coordinates":[5.5171499252,49.5636253357],"type":"Point"}
}