{
  "type": "Feature",
  "properties": {
    "addr:full":"Jachtlaan 132 Etterbeek/etterbeek Bruxelles-Capitale 1040",
    "addr:housenumber":"132",
    "addr:postcode":"1040",
    "addr:street":"Jachtlaan",
    "iso:country":"BE",
    "sg:address":"Jachtlaan 132",
    "sg:city":"Etterbeek/etterbeek",
    "sg:orig_category":"Advocaten and juridische adviseurs",
    "sg:phone":"+32 2 735 29 48",
    "sg:postcode":"1040",
    "sg:province":"Bruxelles-Capitale",
    "wof:name":"Ph. Galand",
    "wof:placetype":"venue"
},
  "geometry": {"coordinates":[4.3932509422,50.8344726562],"type":"Point"}
}