{
  "type": "Feature",
  "properties": {
    "addr:full":"Chemin Du Comte 70 Marchin Li\u00e8ge 4570",
    "addr:housenumber":"70",
    "addr:postcode":"4570",
    "addr:street":"Chemin Du Comte",
    "iso:country":"BE",
    "sg:address":"Chemin Du Comte 70",
    "sg:city":"Marchin",
    "sg:classifiers":[
        {
            "category":"Health Services",
            "subcategory":"Health Practitioner",
            "type":"Services"
        }
    ],
    "sg:phone":"+32 85 23 67 74",
    "sg:postcode":"4570",
    "sg:province":"Li\u00e8ge",
    "sg:tags":[
        "physiotherapist"
    ],
    "wof:name":"Luten Ingrid",
    "wof:placetype":"venue"
},
  "geometry": {"coordinates":[5.2404842377,50.4972229004],"type":"Point"}
}