{
  "type": "Feature",
  "properties": {
    "iso:country":"BE",
    "sg:address":"Rue De La Station 39",
    "sg:city":"Frasnes-lez-anvaing",
    "sg:orig_category":"Banques and organismes de cr\u00e9dit",
    "sg:phone":"+32 69 76 82 26",
    "sg:postcode":"7912",
    "sg:province":"Hainaut",
    "wof:name":"Dexia",
    "wof:placetype":"venue"
},
  "geometry": {"coordinates":[3.5860259533,50.7153968811],"type":"Point"}
}