{
  "type": "Feature",
  "properties": {
    "iso:country":"BE",
    "sg:address":"Tiende Linieregimentstr. 4",
    "sg:city":"Kortemark",
    "sg:orig_category":"M\u00e9decins and sp\u00e9cialistes",
    "sg:phone":"+32 51 56 73 40",
    "sg:postcode":"8610",
    "sg:province":"West-Vlaanderen",
    "wof:name":"G. Mattelin",
    "wof:placetype":"venue"
},
  "geometry": {"coordinates":[3.0424449444,51.028503418],"type":"Point"}
}