{
  "type": "Feature",
  "properties": {
    "iso:country":"BE",
    "sg:address":"Rue De Marche 59",
    "sg:city":"Rochefort",
    "sg:classifiers":[
        {
            "category":"Bars & Pubs",
            "type":"Food & Drink"
        }
    ],
    "sg:phone":"+32 84 24 49 20",
    "sg:postcode":"5580",
    "sg:province":"Namur",
    "wof:name":"V\u00e9lodrome De Rochefort (au)",
    "wof:placetype":"venue"
},
  "geometry": {"coordinates":[5.2248220444,50.1577529907],"type":"Point"}
}