{
  "type": "Feature",
  "properties": {
    "iso:country":"BE",
    "sg:address":"Rue D'eghez\u00c9e 80",
    "sg:city":"Fernelmont",
    "sg:orig_category":"Catering and organisation de f\u00eates",
    "sg:phone":"+32 71 26 12 31",
    "sg:postcode":"5380",
    "sg:province":"Namur",
    "wof:name":"Traiteurs J.a. Demeuse",
    "wof:placetype":"venue"
},
  "geometry": {"coordinates":[4.9952020645,50.5750923157],"type":"Point"}
}