{
  "type": "Feature",
  "properties": {
    "iso:country":"BE",
    "sg:address":"De Castrodreef 1",
    "sg:city":"Sint-niklaas",
    "sg:orig_category":"Opvangtehuizen and vluchthuizen",
    "sg:phone":"+32 3 760 38 25",
    "sg:postcode":"9100",
    "sg:province":"Oost-Vlaanderen",
    "wof:name":"Dienst Maatschapp. Werk",
    "wof:placetype":"venue"
},
  "geometry": {"coordinates":[4.1387910843,51.1625366211],"type":"Point"}
}