{
  "type": "Feature",
  "properties": {
    "iso:country":"BE",
    "sg:address":"Rue Du Ham 258",
    "sg:city":"Moeskroen/mouscron",
    "sg:orig_category":"Pain, p\u00e2tisseries and confiseries",
    "sg:phone":"+32 56 34 99 45",
    "sg:postcode":"7712",
    "sg:province":"Hainaut",
    "wof:name":"Jean-claude Piers",
    "wof:placetype":"venue"
},
  "geometry": {"coordinates":[3.2224369049,50.7159957886],"type":"Point"}
}