{
  "type": "Feature",
  "properties": {
    "iso:country":"BE",
    "sg:address":"Tenbos 20",
    "sg:city":"Affligem",
    "sg:orig_category":"Artsen and specialisten",
    "sg:phone":"+32 53 68 21 24",
    "sg:postcode":"1790",
    "sg:province":"Vlaams-Brabant",
    "wof:name":"Pieter Van Der Spek",
    "wof:placetype":"venue"
},
  "geometry": {"coordinates":[4.08953619,50.9041404724],"type":"Point"}
}