{
  "type": "Feature",
  "properties": {
    "addr:full":"Rue Omer Lef\u00c8vre 33 La Louviere Hainaut 7100",
    "addr:housenumber":"33",
    "addr:postcode":"7100",
    "addr:street":"Rue Omer Lefe\u0300Vre",
    "iso:country":"BE",
    "sg:address":"Rue Omer Lef\u00c8vre 33",
    "sg:city":"La Louviere",
    "sg:orig_category":"Notaires",
    "sg:phone":"+32 64 22 16 32",
    "sg:postcode":"7100",
    "sg:province":"Hainaut",
    "wof:name":"Alain Jacquet",
    "wof:placetype":"venue"
},
  "geometry": {"coordinates":[4.1938471794,50.4760818481],"type":"Point"}
}