{
  "type": "Feature",
  "properties": {
    "addr:full":"Place Joseph Gr\u00c9goire 4 Orp-jauche Brabant Wallon 1350",
    "addr:housenumber":"4",
    "addr:postcode":"1350",
    "addr:street":"Place Joseph Gre\u0301Goire",
    "iso:country":"BE",
    "sg:address":"Place Joseph Gr\u00c9goire 4",
    "sg:city":"Orp-jauche",
    "sg:orig_category":"Banques and organismes de cr\u00e9dit",
    "sg:phone":"+32 19 63 34 23",
    "sg:postcode":"1350",
    "sg:province":"Brabant Wallon",
    "wof:name":"Cr\u00c9dit Agricole",
    "wof:placetype":"venue"
},
  "geometry": {"coordinates":[4.9874930382,50.6968002319],"type":"Point"}
}