{
  "type": "Feature",
  "properties": {
    "addr:full":"Dautzenbergstraat 31 Elsene/ixelles Bruxelles-Capitale 1050",
    "addr:housenumber":"31",
    "addr:postcode":"1050",
    "addr:street":"Dautzenbergstraat",
    "iso:country":"BE",
    "sg:address":"Dautzenbergstraat 31",
    "sg:city":"Elsene/ixelles",
    "sg:orig_category":"Modellenbureaus",
    "sg:phone":"+32 2 649 20 90",
    "sg:postcode":"1050",
    "sg:province":"Bruxelles-Capitale",
    "wof:name":"Team",
    "wof:placetype":"venue"
},
  "geometry": {"coordinates":[4.3675742149,50.827041626],"type":"Point"}
}