{
  "type": "Feature",
  "properties": {
    "iso:country":"BE",
    "sg:address":"Rue Des Croix Du Feu 5",
    "sg:city":"Braine L'alleud (braine-l'alleud)",
    "sg:classifiers":[
        {
            "category":"Organizations",
            "subcategory":"Professional Association",
            "type":"Services"
        }
    ],
    "sg:phone":"+32 2 384 35 52",
    "sg:postcode":"1420",
    "sg:province":"Brabant Wallon",
    "sg:tags":[
        "trade-union",
        "federation"
    ],
    "wof:name":"Chambre Royale Artisanale Patronale De La Construction Brabant Wallon",
    "wof:placetype":"venue"
},
  "geometry": {"coordinates":[-75.60595703120001,37.7877616882],"type":"Point"}
}