{
  "type": "Feature",
  "properties": {
    "addr:full":"Heirbrugstraat 34 Lokeren Oost-Vlaanderen 9160",
    "addr:housenumber":"34",
    "addr:postcode":"9160",
    "addr:street":"Heirbrugstraat",
    "iso:country":"BE",
    "sg:address":"Heirbrugstraat 34",
    "sg:city":"Lokeren",
    "sg:orig_category":"Boucheries",
    "sg:phone":"+32 9 348 56 77",
    "sg:postcode":"9160",
    "sg:province":"Oost-Vlaanderen",
    "wof:name":"Maurice De Clercq",
    "wof:placetype":"venue"
},
  "geometry": {"coordinates":[3.9808590412,51.1021347046],"type":"Point"}
}