{
  "type": "Feature",
  "properties": {
    "addr:full":"Ouden Dendermondse Steenweg 350 Aalst Oost-Vlaanderen 9300",
    "addr:housenumber":"350",
    "addr:postcode":"9300",
    "addr:street":"Steenweg",
    "iso:country":"BE",
    "sg:address":"Ouden Dendermondse Steenweg 350",
    "sg:city":"Aalst",
    "sg:classifiers":[
        {
            "category":"Building & Trades",
            "subcategory":"Cleaning & Sanitation",
            "type":"Services"
        }
    ],
    "sg:phone":"+32 53 70 43 43",
    "sg:postcode":"9300",
    "sg:province":"Oost-Vlaanderen",
    "sg:tags":[
        "cleaner",
        "window"
    ],
    "wof:name":"De Meersman Topcleaning Bvba",
    "wof:placetype":"venue"
},
  "geometry": {"coordinates":[4.0568161011,50.9561195374],"type":"Point"}
}