{
  "type": "Feature",
  "properties": {
    "addr:full":"Rue Phocas Lejeune 32 Gembloux-sur-orneau (isnes) Namur 5032",
    "addr:housenumber":"32",
    "addr:postcode":"5032",
    "addr:street":"Rue Phocas Lejeune;Namur",
    "iso:country":"BE",
    "sg:address":"Rue Phocas Lejeune 32",
    "sg:city":"Gembloux-sur-orneau (isnes)",
    "sg:classifiers":[
        {
            "category":"Professional",
            "subcategory":"Management & Consulting",
            "type":"Services"
        }
    ],
    "sg:phone":"+32 81 81 03 81",
    "sg:postcode":"5032",
    "sg:province":"Namur",
    "sg:tags":[
        "-",
        "processing",
        "data",
        "consultant"
    ],
    "wof:name":"Definition Sa",
    "wof:placetype":"venue"
},
  "geometry": {"coordinates":[4.7220830917,50.4997901917],"type":"Point"}
}