{
  "type": "Feature",
  "properties": {
    "addr:full":"Rue De Bi\u00c8vre 6 Vresse-sur-semois Namur 5550",
    "addr:housenumber":"6",
    "addr:postcode":"vresse-sur-semois;5550",
    "addr:street":"Rue De Bie\u0300Vre",
    "iso:country":"BE",
    "sg:address":"Rue De Bi\u00c8vre 6",
    "sg:city":"Vresse-sur-semois",
    "sg:orig_category":"Boomkwekerijen",
    "sg:phone":"+32 61 50 09 20",
    "sg:postcode":"5550",
    "sg:province":"Namur",
    "wof:name":"G. Labb\u00c9",
    "wof:placetype":"venue"
},
  "geometry": {"coordinates":[4.9336900711,49.8729820251],"type":"Point"}
}