{
  "type": "Feature",
  "properties": {
    "addr:full":"Rue De Couillet 113 Charleroi (marcinelle) Hainaut 6001",
    "addr:housenumber":"113",
    "addr:postcode":"6001",
    "addr:street":"Rue De Couillet",
    "iso:country":"BE",
    "sg:address":"Rue De Couillet 113",
    "sg:city":"Charleroi (marcinelle)",
    "sg:classifiers":[
        {
            "category":"Bars & Pubs",
            "type":"Food & Drink"
        }
    ],
    "sg:phone":"+32 71 36 38 81",
    "sg:postcode":"6001",
    "sg:province":"Hainaut",
    "wof:name":"Esp\u00e9rance (a L')",
    "wof:placetype":"venue"
},
  "geometry": {"coordinates":[4.46037817,50.3981666565],"type":"Point"}
}