{
  "type": "Feature",
  "properties": {
    "iso:country":"BE",
    "sg:address":"Stwg Op Baarle-hertog 72",
    "sg:city":"Turnhout",
    "sg:orig_category":"Afbraak- and draineerwerken",
    "sg:phone":"+32 14 41 43 82",
    "sg:postcode":"2300",
    "sg:province":"Antwerpen",
    "wof:name":"Willems J. & E.",
    "wof:placetype":"venue"
},
  "geometry": {"coordinates":[4.9359331131,51.3782043457],"type":"Point"}
}