{
  "type": "Feature",
  "properties": {
    "iso:country":"BE",
    "sg:address":"De Kluis 1",
    "sg:city":"Oud-heverlee",
    "sg:orig_category":"Vakantiedorpen",
    "sg:phone":"+32 16 47 71 72",
    "sg:postcode":"3051",
    "sg:province":"Vlaams-Brabant",
    "wof:name":"De Kluis",
    "wof:placetype":"venue"
},
  "geometry": {"coordinates":[4.6531858444,50.8032302856],"type":"Point"}
}