{
  "type": "Feature",
  "properties": {
    "addr:full":"Rue De La Cure 15 Viroinval Namur 5670",
    "addr:housenumber":"15",
    "addr:postcode":"5670",
    "addr:street":"Rue De La Cure",
    "iso:country":"BE",
    "sg:address":"Rue De La Cure 15",
    "sg:city":"Viroinval",
    "sg:orig_category":"Librairies",
    "sg:phone":"+32 60 39 97 19",
    "sg:postcode":"5670",
    "sg:province":"Namur",
    "wof:name":"Magelux",
    "wof:placetype":"venue"
},
  "geometry": {"coordinates":[4.6394000053,50.0235099792],"type":"Point"}
}