{
  "type": "Feature",
  "properties": {
    "iso:country":"BE",
    "sg:address":"Rue De La Station 16",
    "sg:city":"Andenne (seilles)",
    "sg:classifiers":[
        {
            "category":"Health Services",
            "subcategory":"Health Practitioner",
            "type":"Services"
        }
    ],
    "sg:phone":"+32 85 82 76 96",
    "sg:postcode":"5300",
    "sg:province":"Namur",
    "sg:tags":[
        "physiotherapist"
    ],
    "wof:name":"Chiaradia Maria Pia",
    "wof:placetype":"venue"
},
  "geometry": {"coordinates":[5.0942959785,50.4974327087],"type":"Point"}
}