{
  "type": "Feature",
  "properties": {
    "addr:full":"Smisstraat 7 Tervuren Vlaams-Brabant 3080",
    "addr:housenumber":"7",
    "addr:postcode":"3080",
    "addr:street":"Smisstraat",
    "iso:country":"BE",
    "sg:address":"Smisstraat 7",
    "sg:city":"Tervuren",
    "sg:orig_category":"Brood, gebak and snoepgoed",
    "sg:phone":"+32 2 768 13 13",
    "sg:postcode":"3080",
    "sg:province":"Vlaams-Brabant",
    "wof:name":"Vogelaers",
    "wof:placetype":"venue"
},
  "geometry": {"coordinates":[4.5559601784,50.8343811035],"type":"Point"}
}