{
  "type": "Feature",
  "properties": {
    "addr:full":"Luingnestraat 229 Kortrijk West-Vlaanderen 8511",
    "addr:housenumber":"229",
    "addr:postcode":"8511",
    "addr:street":"Luingnestraat",
    "iso:country":"BE",
    "sg:address":"Luingnestraat 229",
    "sg:city":"Kortrijk",
    "sg:orig_category":"Slagers",
    "sg:phone":"+32 56 42 55 77",
    "sg:postcode":"8511",
    "sg:province":"West-Vlaanderen",
    "wof:name":"Dieter Lavaert",
    "wof:placetype":"venue"
},
  "geometry": {"coordinates":[3.2395899296,50.7604103088],"type":"Point"}
}