{
  "type": "Feature",
  "properties": {
    "iso:country":"BE",
    "sg:address":"Rue De La Fusee 60",
    "sg:city":"Bruxelles",
    "sg:classifiers":[
        {
            "category":"Banks & Credit Unions",
            "subcategory":"Investment Brokerage",
            "type":"Services"
        }
    ],
    "sg:phone":"+32 3 645 33 35",
    "sg:postcode":"1130",
    "sg:province":"Bruxelles-Capitale",
    "sg:tags":[
        "filters"
    ],
    "wof:name":"General Filters Nv",
    "wof:placetype":"venue"
},
  "geometry": {"coordinates":[4.4406142235,51.2434616089],"type":"Point"}
}