{
  "type": "Feature",
  "properties": {
    "iso:country":"BE",
    "sg:address":"Rue De La For\u00cat 28",
    "sg:city":"Luik (groot)",
    "sg:classifiers":[
        {
            "category":"Personal",
            "subcategory":"Beauty Salon",
            "type":"Services"
        }
    ],
    "sg:phone":"+32 475 64 95 71",
    "sg:postcode":"4020",
    "sg:province":"Li\u00e8ge",
    "sg:tags":[
        "de",
        "coiffure"
    ],
    "wof:name":"Decontract'hair",
    "wof:placetype":"venue"
},
  "geometry": {"coordinates":[5.6446881294,50.6532669067],"type":"Point"}
}