{
  "type": "Feature",
  "properties": {
    "addr:full":"Misweg 37 Riemst Limburg 3770",
    "addr:housenumber":"37",
    "addr:postcode":"3770",
    "addr:street":"Misweg",
    "iso:country":"BE",
    "sg:address":"Misweg 37",
    "sg:city":"Riemst",
    "sg:orig_category":"Installation de menuiserie en bois and plastique",
    "sg:phone":"+32 12 45 12 60",
    "sg:postcode":"3770",
    "sg:province":"Limburg",
    "wof:name":"Theunissen Geert",
    "wof:placetype":"venue"
},
  "geometry": {"coordinates":[5.5969901085,50.8109016418],"type":"Point"}
}