{
  "type": "Feature",
  "properties": {
    "addr:full":"Interleuvenlaan 40 Leuven Vlaams-Brabant 3000",
    "addr:housenumber":"40",
    "addr:postcode":"3000",
    "addr:street":"Interleuvenlaan",
    "iso:country":"BE",
    "sg:address":"Interleuvenlaan 40",
    "sg:city":"Leuven",
    "sg:classifiers":[
        {
            "category":"Health Services",
            "subcategory":"Medical Lab",
            "type":"Services"
        }
    ],
    "sg:phone":"+32 16 38 12 11",
    "sg:postcode":"3000",
    "sg:province":"Vlaams-Brabant",
    "sg:tags":[
        "article",
        "disposable"
    ],
    "wof:name":"Terumo Europe Nv",
    "wof:placetype":"venue"
},
  "geometry": {"coordinates":[4.7324872017,50.8465995789],"type":"Point"}
}