{
  "type": "Feature",
  "properties": {
    "iso:country":"BE",
    "sg:address":"Centrum Zuid 1515",
    "sg:city":"Houthalen-helchteren (houthalen)",
    "sg:classifiers":[
        {
            "category":"Food & Beverages",
            "subcategory":"Specialty",
            "type":"Retail Goods"
        }
    ],
    "sg:phone":"+32 11 59 01 59",
    "sg:postcode":"3530",
    "sg:province":"Limburg",
    "sg:tags":[
        "sinking",
        "groundwater"
    ],
    "wof:name":"Gm Consulting",
    "wof:placetype":"venue"
},
  "geometry": {"coordinates":[5.3620591164,51.0243453979],"type":"Point"}
}