{
  "type": "Feature",
  "properties": {
    "iso:country":"BE",
    "sg:address":"Dorpsstraat 111",
    "sg:city":"Middelkerke (leffinge)",
    "sg:classifiers":[
        {
            "category":"Professional",
            "subcategory":"Printing & Photocopies",
            "type":"Services"
        }
    ],
    "sg:phone":"+32 59 30 00 52",
    "sg:postcode":"8432",
    "sg:province":"West-Vlaanderen",
    "sg:tags":[
        "-",
        "offset"
    ],
    "wof:name":"Grafisch Bedrijf Lover Bvba",
    "wof:placetype":"venue"
},
  "geometry": {"coordinates":[2.8771800995,51.1750984192],"type":"Point"}
}