{
  "type": "Feature",
  "properties": {
    "addr:full":"Kwetshagestraat 13 Jabbeke West-Vlaanderen 8490",
    "addr:housenumber":"13",
    "addr:postcode":"8490",
    "addr:street":"Kwetshagestraat",
    "iso:country":"BE",
    "sg:address":"Kwetshagestraat 13",
    "sg:city":"Jabbeke",
    "sg:orig_category":"Eleveurs de bovins",
    "sg:phone":"+32 50 39 54 70",
    "sg:postcode":"8490",
    "sg:province":"West-Vlaanderen",
    "wof:name":"Jozef Coene",
    "wof:placetype":"venue"
},
  "geometry": {"coordinates":[3.1194500923,51.1954994202],"type":"Point"}
}