{
  "type": "Feature",
  "properties": {
    "addr:full":"Rue Louis Pasteur 1 Charleroi Hainaut 6001",
    "addr:housenumber":"1",
    "addr:postcode":"6001",
    "addr:street":"Rue Louis Pasteur;Hainaut",
    "iso:country":"BE",
    "sg:address":"Rue Louis Pasteur 1",
    "sg:city":"Charleroi",
    "sg:orig_category":"Openbare bibliotheken and archieven",
    "sg:phone":"+32 71 36 62 56",
    "sg:postcode":"6001",
    "sg:province":"Hainaut",
    "wof:name":"Biblioth\u00c8que St.louis",
    "wof:placetype":"venue"
},
  "geometry": {"coordinates":[4.4448251724,50.3973655701],"type":"Point"}
}