{
  "type": "Feature",
  "properties": {
    "addr:full":"Kleine Schuurstraat 1 Gent Oost-Vlaanderen 9040",
    "addr:housenumber":"1",
    "addr:postcode":"9040",
    "addr:street":"Kleine Schuurstraat;Oost-Vlaanderen",
    "iso:country":"BE",
    "sg:address":"Kleine Schuurstraat 1",
    "sg:city":"Gent",
    "sg:orig_category":"Kapsalons",
    "sg:phone":"+32 9 229 19 38",
    "sg:postcode":"9040",
    "sg:province":"Oost-Vlaanderen",
    "wof:name":"Sandy Scheltens",
    "wof:placetype":"venue"
},
  "geometry": {"coordinates":[3.7761580944,51.072807312],"type":"Point"}
}