{
  "type": "Feature",
  "properties": {
    "iso:country":"BE",
    "sg:address":"Avenue Du Val St.georges 1",
    "sg:city":"Namur",
    "sg:orig_category":"Epiceries",
    "sg:phone":"+32 81 73 76 48",
    "sg:postcode":"5000",
    "sg:province":"Namur",
    "wof:name":"Michel Maree",
    "wof:placetype":"venue"
},
  "geometry": {"coordinates":[4.8390498161,50.4613494873],"type":"Point"}
}