{
  "type": "Feature",
  "properties": {
    "addr:full":"Avenue Clemenceau 50 Anderlecht Bruxelles-Capitale 1070",
    "addr:housenumber":"50",
    "addr:postcode":"1070",
    "addr:street":"Avenue Clemenceau",
    "iso:country":"BE",
    "sg:address":"Avenue Clemenceau 50",
    "sg:city":"Anderlecht",
    "sg:classifiers":[
        {
            "category":"Restaurant",
            "type":"Food & Drink"
        }
    ],
    "sg:phone":"+32 2 521 31 99",
    "sg:postcode":"1070",
    "sg:province":"Bruxelles-Capitale",
    "wof:name":"Chez Maria",
    "wof:placetype":"venue"
},
  "geometry": {"coordinates":[4.3337888718,50.8405265808],"type":"Point"}
}