{
  "type": "Feature",
  "properties": {
    "addr:full":"Rue Des Combattants 119 Anderlues Hainaut 6150",
    "addr:housenumber":"119",
    "addr:postcode":"6150",
    "addr:street":"Rue Des Combattants",
    "iso:country":"BE",
    "sg:address":"Rue Des Combattants 119",
    "sg:city":"Anderlues",
    "sg:classifiers":[
        {
            "category":"Arena",
            "subcategory":"Sports Club",
            "type":"Entertainment"
        }
    ],
    "sg:phone":"+32 71 54 47 97",
    "sg:postcode":"6150",
    "sg:province":"Hainaut",
    "sg:tags":[
        "de"
    ],
    "wof:name":"Crazy Bikers Anderlues",
    "wof:placetype":"venue"
},
  "geometry": {"coordinates":[4.2628722191,50.4118881226],"type":"Point"}
}