{
  "type": "Feature",
  "properties": {
    "iso:country":"BE",
    "sg:address":"Ernest Ourystraat 2-4",
    "sg:city":"Hoegaarden",
    "sg:classifiers":[
        {
            "category":"Bars & Pubs",
            "type":"Food & Drink"
        }
    ],
    "sg:phone":"+32 16 76 77 96",
    "sg:postcode":"3320",
    "sg:province":"Vlaams-Brabant",
    "wof:name":"'t Nieuwhuys",
    "wof:placetype":"venue"
},
  "geometry": {"coordinates":[4.8931379318,50.7744483948],"type":"Point"}
}