{
  "type": "Feature",
  "properties": {
    "addr:full":"Vissersplein 9 Oostende West-Vlaanderen 8400",
    "addr:housenumber":"9",
    "addr:postcode":"8400",
    "addr:street":"Vissersplein",
    "iso:country":"BE",
    "sg:address":"Vissersplein 9",
    "sg:city":"Oostende",
    "sg:classifiers":[
        {
            "category":"Bars & Pubs",
            "type":"Food & Drink"
        }
    ],
    "sg:phone":"+32 59 50 62 57",
    "sg:postcode":"8400",
    "sg:province":"West-Vlaanderen",
    "wof:name":"Zeester",
    "wof:placetype":"venue"
},
  "geometry": {"coordinates":[2.9217469692,51.2325325012],"type":"Point"}
}