{
  "type": "Feature",
  "properties": {
    "iso:country":"BE",
    "sg:address":"Hellestraat 65",
    "sg:city":"Boechout",
    "sg:orig_category":"Avocats and conseillers juridiques",
    "sg:phone":"+32 3 455 64 83",
    "sg:postcode":"2530",
    "sg:province":"Antwerpen",
    "wof:name":"Bureau Van Den Broeck",
    "wof:placetype":"venue"
},
  "geometry": {"coordinates":[4.5155701637,51.166053772],"type":"Point"}
}