{
  "type": "Feature",
  "properties": {
    "iso:country":"BE",
    "sg:address":"Kempenstraat 165",
    "sg:city":"Diepenbeek",
    "sg:orig_category":"Computers and computerapparatuur Onderhoud van kantoor- and computeruitrusting Software ontwikkeling",
    "sg:phone":"+32 11 33 23 23",
    "sg:postcode":"3590",
    "sg:province":"Limburg",
    "wof:name":"Datacenter Lipa",
    "wof:placetype":"venue"
},
  "geometry": {"coordinates":[5.4364590645,50.9286422729],"type":"Point"}
}