{
  "type": "Feature",
  "properties": {
    "addr:full":"Rue Samiette 1 Nivelles Brabant Wallon 1400",
    "addr:housenumber":"1",
    "addr:postcode":"1400",
    "addr:street":"Rue Samiette",
    "iso:country":"BE",
    "sg:address":"Rue Samiette 1",
    "sg:city":"Nivelles",
    "sg:orig_category":"Rusthuizen and serviceflats",
    "sg:phone":"+32 67 21 66 30",
    "sg:postcode":"1400",
    "sg:province":"Brabant Wallon",
    "wof:name":"R\u00c9sidence Samiette",
    "wof:placetype":"venue"
},
  "geometry": {"coordinates":[4.3174080849,50.5957489014],"type":"Point"}
}