{
  "type": "Feature",
  "properties": {
    "iso:country":"BE",
    "sg:address":"Industrielaan 15",
    "sg:city":"Olen",
    "sg:classifiers":[
        {
            "category":"Food & Beverages",
            "subcategory":"Meat & Fish",
            "type":"Retail Goods"
        }
    ],
    "sg:phone":"+32 14 21 51 50",
    "sg:postcode":"2250",
    "sg:province":"Antwerpen",
    "sg:tags":[
        "fresh"
    ],
    "wof:name":"Slachthuis Vanlommel Nv",
    "wof:placetype":"venue"
},
  "geometry": {"coordinates":[4.8754281998,51.1505508423],"type":"Point"}
}