{
  "type": "Feature",
  "properties": {
    "iso:country":"BE",
    "sg:address":"Juniorslaan 18",
    "sg:city":"Mechelen",
    "sg:classifiers":[
        {
            "category":"Food & Beverages",
            "subcategory":"Fruits & Vegetables",
            "type":"Retail Goods"
        }
    ],
    "sg:phone":"+32 15 27 76 25",
    "sg:postcode":"2811",
    "sg:province":"Antwerpen",
    "sg:tags":[
        "l\u00e9gumes",
        "gr"
    ],
    "wof:name":"M & H",
    "wof:placetype":"venue"
},
  "geometry": {"coordinates":[4.40625,51.0323867798],"type":"Point"}
}