{
  "type": "Feature",
  "properties": {
    "addr:full":"Moerkerkse Steenweg 105 Brugge West-Vlaanderen 8310",
    "addr:housenumber":"105",
    "addr:postcode":"8310",
    "addr:street":"Moerkerkse Steenweg",
    "iso:country":"BE",
    "sg:address":"Moerkerkse Steenweg 105",
    "sg:city":"Brugge",
    "sg:orig_category":"Opticiens",
    "sg:phone":"+32 50 35 48 29",
    "sg:postcode":"8310",
    "sg:province":"West-Vlaanderen",
    "wof:name":"Optiek Van Maele",
    "wof:placetype":"venue"
},
  "geometry": {"coordinates":[3.2463378906,51.213180542],"type":"Point"}
}