{
  "type": "Feature",
  "properties": {
    "iso:country":"BE",
    "sg:address":"Mechelsebaan 23",
    "sg:city":"Duffel",
    "sg:classifiers":[
        {
            "category":"Professional",
            "subcategory":"Art Services",
            "type":"Services"
        }
    ],
    "sg:phone":"+32 15 31 99 58",
    "sg:postcode":"2570",
    "sg:province":"Antwerpen",
    "sg:tags":[
        "designer",
        "ontwerpers"
    ],
    "wof:name":"Doubble Stress",
    "wof:placetype":"venue"
},
  "geometry": {"coordinates":[4.510819912,51.0901374817],"type":"Point"}
}