{
  "type": "Feature",
  "properties": {
    "iso:country":"BE",
    "sg:address":"Sanatoriumstraat 251",
    "sg:city":"Beersel (alsemberg)",
    "sg:classifiers":[
        {
            "category":"Home & Garden",
            "subcategory":"Building Materials",
            "type":"Retail Goods"
        }
    ],
    "sg:phone":"+32 2 380 86 19",
    "sg:postcode":"1652",
    "sg:province":"Vlaams-Brabant",
    "sg:tags":[
        "wall",
        "cupboard"
    ],
    "wof:name":"Costantino",
    "wof:placetype":"venue"
},
  "geometry": {"coordinates":[4.3065400124,50.7574806213],"type":"Point"}
}