{
  "type": "Feature",
  "properties": {
    "addr:full":"Perklaan 29 Tielt-winge Vlaams-Brabant 3390",
    "addr:housenumber":"29",
    "addr:postcode":"3390",
    "addr:street":"Perklaan",
    "iso:country":"BE",
    "sg:address":"Perklaan 29",
    "sg:city":"Tielt-winge",
    "sg:orig_category":"Sportclubs Sportterreinen and installaties behalve sportcentra",
    "sg:phone":"+32 16 63 15 35",
    "sg:postcode":"3390",
    "sg:province":"Vlaams-Brabant",
    "wof:name":"Girls Tielt Winge",
    "wof:placetype":"venue"
},
  "geometry": {"coordinates":[4.8813381195,50.9063186646],"type":"Point"}
}