{
  "type": "Feature",
  "properties": {
    "iso:country":"BE",
    "sg:address":"Rue De Fafchamps 56",
    "sg:city":"Bl\u00e9gny (trembleur)",
    "sg:classifiers":[
        {
            "category":"Utilities",
            "subcategory":"Fuel Oil & Lpg",
            "type":"Services"
        }
    ],
    "sg:phone":"+32 4 387 46 98",
    "sg:postcode":"4670",
    "sg:province":"Li\u00e8ge",
    "wof:name":"Ets Massuir Alain",
    "wof:placetype":"venue"
},
  "geometry": {"coordinates":[5.7264671326,50.6685600281],"type":"Point"}
}