{
  "type": "Feature",
  "properties": {
    "addr:full":"Karreweg 26 Zulte Oost-Vlaanderen 9870",
    "addr:housenumber":"26",
    "addr:postcode":"9870",
    "addr:street":"Karreweg",
    "iso:country":"BE",
    "sg:address":"Karreweg 26",
    "sg:city":"Zulte",
    "sg:orig_category":"Pluimveekwekers",
    "sg:phone":"+32 9 388 93 67",
    "sg:postcode":"9870",
    "sg:province":"Oost-Vlaanderen",
    "wof:name":"Fernand Godefroidt",
    "wof:placetype":"venue"
},
  "geometry": {"coordinates":[3.4688210487,50.9062652588],"type":"Point"}
}