{
  "type": "Feature",
  "properties": {
    "addr:full":"Ch De Louvrain 13 Eghezee Namur 5310",
    "addr:housenumber":"13",
    "addr:postcode":"5310",
    "addr:street":"Ch De Louvrain;Namur",
    "iso:country":"BE",
    "sg:address":"Ch De Louvrain 13",
    "sg:city":"Eghezee",
    "sg:classifiers":[
        {
            "category":"Personal",
            "subcategory":"Beauty Salon",
            "type":"Services"
        }
    ],
    "sg:phone":"+32 81 74 75 95",
    "sg:postcode":"5310",
    "sg:province":"Namur",
    "sg:tags":[
        "lady",
        "-",
        "hairdressing"
    ],
    "wof:name":"Dachkin O",
    "wof:placetype":"venue"
},
  "geometry": {"coordinates":[4.9071350098,50.5914764404],"type":"Point"}
}