{
  "type": "Feature",
  "properties": {
    "addr:full":"Rue Des R\u00e9sistants 1 Mouscron Hainaut 7700",
    "addr:housenumber":"1",
    "addr:postcode":"7700",
    "addr:street":"Rue Des Re\u0301Sistants",
    "iso:country":"BE",
    "sg:address":"Rue Des R\u00e9sistants 1",
    "sg:city":"Mouscron",
    "sg:classifiers":[
        {
            "category":"Bars & Pubs",
            "type":"Food & Drink"
        }
    ],
    "sg:phone":"+32 56 34 85 08",
    "sg:postcode":"7700",
    "sg:province":"Hainaut",
    "wof:name":"Astoria",
    "wof:placetype":"venue"
},
  "geometry": {"coordinates":[3.2138340473,50.743637085],"type":"Point"}
}