{
  "type": "Feature",
  "properties": {
    "addr:full":"Veldstraat 36b50 Begijnendijk Vlaams-Brabant 3130",
    "addr:housenumber":"36b50",
    "addr:postcode":"3130",
    "addr:street":"Veldstraat",
    "iso:country":"BE",
    "sg:address":"Veldstraat 36b50",
    "sg:city":"Begijnendijk",
    "sg:orig_category":"Diverse opleidingen and onderwijs",
    "sg:phone":"+32 16 53 78 53",
    "sg:postcode":"3130",
    "sg:province":"Vlaams-Brabant",
    "wof:name":"Syntex & Endeavour",
    "wof:placetype":"venue"
},
  "geometry": {"coordinates":[4.7957820892,51.0228500366],"type":"Point"}
}