{
  "type": "Feature",
  "properties": {
    "iso:country":"BE",
    "sg:address":"Bergensesteenweg 6",
    "sg:city":"Halle",
    "sg:classifiers":[
        {
            "category":"Building & Trades",
            "subcategory":"Construction",
            "type":"Services"
        }
    ],
    "sg:phone":"+32 2 356 53 62",
    "sg:postcode":"1500",
    "sg:province":"Vlaams-Brabant",
    "sg:tags":[
        "stair"
    ],
    "wof:name":"A.b. Eurovera Nv",
    "wof:placetype":"venue"
},
  "geometry": {"coordinates":[4.2354998589,50.7344741821],"type":"Point"}
}