{
  "type": "Feature",
  "properties": {
    "iso:country":"BE",
    "sg:address":"Izegemsestraat 172",
    "sg:city":"Kortrijk",
    "sg:orig_category":"Artsen and specialisten",
    "sg:phone":"+32 56 35 52 50",
    "sg:postcode":"8501",
    "sg:province":"West-Vlaanderen",
    "wof:name":"Luc Joye",
    "wof:placetype":"venue"
},
  "geometry": {"coordinates":[3.2573730946,50.840057373],"type":"Point"}
}