{
  "type": "Feature",
  "properties": {
    "addr:full":"Bivakstraat 96 Leopoldsburg Limburg 3971",
    "addr:housenumber":"96",
    "addr:postcode":"3971",
    "addr:street":"Bivakstraat",
    "iso:country":"BE",
    "sg:address":"Bivakstraat 96",
    "sg:city":"Leopoldsburg",
    "sg:orig_category":"Sportclubs",
    "sg:phone":"+32 11 34 50 54",
    "sg:postcode":"3971",
    "sg:province":"Limburg",
    "wof:name":"Turnhoutse Schuttersclub",
    "wof:placetype":"venue"
},
  "geometry": {"coordinates":[5.2507801056,51.1015396118],"type":"Point"}
}