{
  "type": "Feature",
  "properties": {
    "iso:country":"BE",
    "sg:address":"Molenaarsstraat 111 Box 20",
    "sg:city":"Gent",
    "sg:classifiers":[
        {
            "category":"Real Estate",
            "subcategory":"Architect",
            "type":"Services"
        }
    ],
    "sg:phone":"+32 9 223 03 61",
    "sg:postcode":"9000",
    "sg:province":"Oost-Vlaanderen",
    "wof:name":"Lust H",
    "wof:placetype":"venue"
},
  "geometry": {"coordinates":[3.718034029,51.0632095337],"type":"Point"}
}