{
  "type": "Feature",
  "properties": {
    "iso:country":"BE",
    "sg:address":"Meensesteenweg 776",
    "sg:city":"Roeselare",
    "sg:orig_category":"Imprimeries and copyshops",
    "sg:phone":"+32 51 77 73 67",
    "sg:postcode":"8800",
    "sg:province":"West-Vlaanderen",
    "wof:name":"Bart Vandenbroucke",
    "wof:placetype":"venue"
},
  "geometry": {"coordinates":[3.1138820648,50.8922080994],"type":"Point"}
}