{
  "type": "Feature",
  "properties": {
    "iso:country":"BE",
    "sg:address":"Rue Du Baron Nothomb 34",
    "sg:city":"Philippeville (merlemont)",
    "sg:classifiers":[
        {
            "category":"Professional",
            "subcategory":"Accounting & Tax Preparation",
            "type":"Services"
        }
    ],
    "sg:phone":"+32 71 66 74 69",
    "sg:postcode":"5600",
    "sg:province":"Namur",
    "sg:tags":[
        "bookkeeper"
    ],
    "wof:name":"Martinet M",
    "wof:placetype":"venue"
},
  "geometry": {"coordinates":[4.6042017937,50.1721458435],"type":"Point"}
}