{
  "type": "Feature",
  "properties": {
    "iso:country":"BE",
    "sg:address":"Gr. Leiestraat 203",
    "sg:city":"Anzegem",
    "sg:orig_category":"Tuinen",
    "sg:phone":"+32 56 60 05 86",
    "sg:postcode":"8570",
    "sg:province":"West-Vlaanderen",
    "wof:name":"Verschuere L",
    "wof:placetype":"venue"
},
  "geometry": {"coordinates":[3.4473209381,50.8622436523],"type":"Point"}
}