{
  "type": "Feature",
  "properties": {
    "addr:full":"Rue De La Verrerie 212 Seraing Li\u00e8ge 4100",
    "addr:housenumber":"212",
    "addr:postcode":"4100",
    "addr:street":"Rue De La Verrerie",
    "iso:country":"BE",
    "sg:address":"Rue De La Verrerie 212",
    "sg:city":"Seraing",
    "sg:classifiers":[
        {
            "category":"Health Services",
            "subcategory":"Health Practitioner",
            "type":"Services"
        }
    ],
    "sg:phone":"+32 475 41 67 44",
    "sg:postcode":"4100",
    "sg:province":"Li\u00e8ge",
    "sg:tags":[
        "physiotherapist"
    ],
    "wof:name":"Bury V\u00e9ronique",
    "wof:placetype":"venue"
},
  "geometry": {"coordinates":[5.5019698143,50.5773696899],"type":"Point"}
}