{
  "type": "Feature",
  "properties": {
    "addr:full":"Hauptstrasse 41 Raeren Li\u00e8ge 4730",
    "addr:housenumber":"41",
    "addr:postcode":"4730",
    "addr:street":"Hauptstrasse",
    "iso:country":"BE",
    "sg:address":"Hauptstrasse 41",
    "sg:city":"Raeren",
    "sg:orig_category":"Slagers",
    "sg:phone":"+32 87 85 12 78",
    "sg:postcode":"4730",
    "sg:province":"Li\u00e8ge",
    "wof:name":"Kreusch",
    "wof:placetype":"venue"
},
  "geometry": {"coordinates":[6.1116428375,50.6760635376],"type":"Point"}
}