{
  "type": "Feature",
  "properties": {
    "iso:country":"BE",
    "sg:address":"Rue Steyls 17",
    "sg:city":"Bruxelles",
    "sg:classifiers":[
        {
            "category":"Shopping",
            "subcategory":"Antiques",
            "type":"Retail Goods"
        }
    ],
    "sg:phone":"+32 2 428 34 05",
    "sg:postcode":"1020",
    "sg:province":"Bruxelles-Capitale",
    "sg:tags":[
        "restoration"
    ],
    "wof:name":"Spironello J",
    "wof:placetype":"venue"
},
  "geometry": {"coordinates":[4.344399929,50.8789520264],"type":"Point"}
}