{
  "type": "Feature",
  "properties": {
    "addr:full":"Marktplein 20 Ternat Vlaams-Brabant 1740",
    "addr:housenumber":"20",
    "addr:postcode":"1740",
    "addr:street":"Marktplein",
    "iso:country":"BE",
    "sg:address":"Marktplein 20",
    "sg:city":"Ternat",
    "sg:orig_category":"Banques and organismes de cr\u00e9dit",
    "sg:phone":"+32 2 582 05 95",
    "sg:postcode":"1740",
    "sg:province":"Vlaams-Brabant",
    "wof:name":"Dexia",
    "wof:placetype":"venue"
},
  "geometry": {"coordinates":[4.1780400276,50.8713989258],"type":"Point"}
}