{
  "type": "Feature",
  "properties": {
    "addr:full":"Markt 10 Nevele Oost-Vlaanderen 9850",
    "addr:housenumber":"10",
    "addr:postcode":"9850",
    "addr:street":"Markt",
    "iso:country":"BE",
    "sg:address":"Markt 10",
    "sg:city":"Nevele",
    "sg:orig_category":"Banques and organismes de cr\u00e9dit",
    "sg:phone":"+32 9 371 69 22",
    "sg:postcode":"9850",
    "sg:province":"Oost-Vlaanderen",
    "wof:name":"Fortis",
    "wof:placetype":"venue"
},
  "geometry": {"coordinates":[3.5497460365,51.0333938599],"type":"Point"}
}