{
  "type": "Feature",
  "properties": {
    "addr:full":"Turfstraat 162 Genk Limburg 3600",
    "addr:housenumber":"162",
    "addr:postcode":"3600",
    "addr:street":"Turfstraat",
    "iso:country":"BE",
    "sg:address":"Turfstraat 162",
    "sg:city":"Genk",
    "sg:classifiers":[
        {
            "category":"Health Services",
            "subcategory":"Nursing And Care Facility",
            "type":"Services"
        }
    ],
    "sg:phone":"+32 89 30 38 81",
    "sg:postcode":"3600",
    "sg:province":"Limburg",
    "sg:tags":[
        "home"
    ],
    "wof:name":"Van Reppelen Marijke",
    "wof:placetype":"venue"
},
  "geometry": {"coordinates":[5.4335861206,50.963142395],"type":"Point"}
}