{
  "type": "Feature",
  "properties": {
    "iso:country":"BE",
    "sg:address":"Ottergemsesteenweg Zuid 720",
    "sg:city":"Gand",
    "sg:orig_category":"Winkelinrichting and handelsuitrusting Gh",
    "sg:phone":"+32 9 241 51 11",
    "sg:postcode":"9000",
    "sg:province":"Oost-Vlaanderen",
    "wof:name":"Ispc",
    "wof:placetype":"venue"
},
  "geometry": {"coordinates":[3.7379009724,51.0172691345],"type":"Point"}
}