{
  "type": "Feature",
  "properties": {
    "addr:full":"Vanderborghtstraat 88 Jette/jette Bruxelles-Capitale 1090",
    "addr:housenumber":"88",
    "addr:postcode":"1090",
    "addr:street":"Vanderborghtstraat",
    "iso:country":"BE",
    "sg:address":"Vanderborghtstraat 88",
    "sg:city":"Jette/jette",
    "sg:orig_category":"Artsen and specialisten",
    "sg:phone":"+32 2 427 80 93",
    "sg:postcode":"1090",
    "sg:province":"Bruxelles-Capitale",
    "wof:name":"Touria Baladi",
    "wof:placetype":"venue"
},
  "geometry": {"coordinates":[4.3249158859,50.8683547974],"type":"Point"}
}