{
  "type": "Feature",
  "properties": {
    "iso:country":"BE",
    "sg:address":"Zonneweelde 56",
    "sg:city":"Sint-pieters-leeuw",
    "sg:classifiers":[
        {
            "category":"Personal",
            "subcategory":"Beauty Salon",
            "type":"Services"
        }
    ],
    "sg:phone":"+32 2 377 92 93",
    "sg:postcode":"1600",
    "sg:province":"Vlaams-Brabant",
    "sg:tags":[
        "de",
        "coiffure"
    ],
    "wof:name":"Mia Stas",
    "wof:placetype":"venue"
},
  "geometry": {"coordinates":[4.2538609505,50.7977981567],"type":"Point"}
}