{
  "type": "Feature",
  "properties": {
    "iso:country":"BE",
    "sg:address":"Rue De Lantin 150",
    "sg:city":"Ans (alleur)",
    "sg:classifiers":[
        {
            "category":"Health Services",
            "subcategory":"Health Practitioner",
            "type":"Services"
        }
    ],
    "sg:phone":"+32 4 246 26 99",
    "sg:postcode":"4432",
    "sg:province":"Li\u00e8ge",
    "sg:tags":[
        "physiotherapist"
    ],
    "wof:name":"Devreux Jacques",
    "wof:placetype":"venue"
},
  "geometry": {"coordinates":[5.522591114,50.6824073792],"type":"Point"}
}