{
  "type": "Feature",
  "properties": {
    "iso:country":"BE",
    "sg:address":"Stalenstraat 2",
    "sg:city":"Genk",
    "sg:orig_category":"M\u00e9decins and sp\u00e9cialistes",
    "sg:phone":"+32 89 84 79 40",
    "sg:postcode":"3600",
    "sg:province":"Limburg",
    "wof:name":"R. Witvrouw",
    "wof:placetype":"venue"
},
  "geometry": {"coordinates":[5.5225749016,50.9970169067],"type":"Point"}
}