{
  "type": "Feature",
  "properties": {
    "iso:country":"BE",
    "sg:address":"Molenstraat 110",
    "sg:city":"Gavere",
    "sg:classifiers":[
        {
            "category":"Brewery",
            "type":"Food & Drink"
        }
    ],
    "sg:phone":"+32 9 384 27 06",
    "sg:postcode":"9890",
    "sg:province":"Oost-Vlaanderen",
    "wof:name":"Contreras W",
    "wof:placetype":"venue"
},
  "geometry": {"coordinates":[3.6731369495,50.9241638184],"type":"Point"}
}