{
  "type": "Feature",
  "properties": {
    "iso:country":"BE",
    "sg:address":"Stokthoekstraat 51",
    "sg:city":"Temse",
    "sg:orig_category":"Software ontwikkeling and ontwerp",
    "sg:phone":"+32 52 46 11 10",
    "sg:postcode":"9140",
    "sg:province":"Oost-Vlaanderen",
    "wof:name":"Dwm-soft",
    "wof:placetype":"venue"
},
  "geometry": {"coordinates":[4.1333341599,51.1254119873],"type":"Point"}
}