{
  "type": "Feature",
  "properties": {
    "addr:full":"Grand-rue 13 Arlon Luxembourg 6700",
    "addr:housenumber":"13",
    "addr:postcode":"6700",
    "addr:street":"Grand-Rue",
    "iso:country":"BE",
    "sg:address":"Grand-rue 13",
    "sg:city":"Arlon",
    "sg:classifiers":[
        {
            "category":"Shopping",
            "subcategory":"Clothing, Apparel, & Fashions",
            "type":"Retail Goods"
        }
    ],
    "sg:phone":"+32 63 23 54 23",
    "sg:postcode":"6700",
    "sg:province":"Luxembourg",
    "sg:tags":[
        "lady",
        "clothing",
        "-"
    ],
    "wof:name":"Schmit-beaufays Pour Elle",
    "wof:placetype":"venue"
},
  "geometry": {"coordinates":[5.8154249191,49.6829681396],"type":"Point"}
}