{
  "type": "Feature",
  "properties": {
    "iso:country":"BE",
    "sg:address":"Vossenstraat 3",
    "sg:city":"Brussel/bruxelles",
    "sg:classifiers":[
        {
            "category":"Restaurant",
            "type":"Food & Drink"
        }
    ],
    "sg:phone":"+32 2 502 96 14",
    "sg:postcode":"1000",
    "sg:province":"Bruxelles-Capitale",
    "wof:name":"Auberge Du Bovendael",
    "wof:placetype":"venue"
},
  "geometry": {"coordinates":[4.3467178345,50.8375015259],"type":"Point"}
}