{
  "type": "Feature",
  "properties": {
    "iso:country":"BE",
    "sg:address":"Rubensstraat 142",
    "sg:city":"Turnhout",
    "sg:classifiers":[
        {
            "category":"Cafe",
            "type":"Food & Drink"
        }
    ],
    "sg:phone":"+32 14 42 82 97",
    "sg:postcode":"2300",
    "sg:province":"Antwerpen",
    "sg:tags":[
        "snack-bars"
    ],
    "wof:name":"Coertjens F",
    "wof:placetype":"venue"
},
  "geometry": {"coordinates":[4.9438529015,51.3147277832],"type":"Point"}
}