{
  "type": "Feature",
  "properties": {
    "addr:full":"Kortrijksesteenweg 1101ba Gent Oost-Vlaanderen 9051",
    "addr:postcode":"1101ba;9051",
    "addr:street":"Kortrijksesteenweg",
    "iso:country":"BE",
    "sg:address":"Kortrijksesteenweg 1101ba",
    "sg:city":"Gent",
    "sg:orig_category":"Studios photographiques",
    "sg:phone":"+32 9 221 80 33",
    "sg:postcode":"9051",
    "sg:province":"Oost-Vlaanderen",
    "wof:name":"Herreman Lieven",
    "wof:placetype":"venue"
},
  "geometry": {"coordinates":[3.680740118,51.0196418762],"type":"Point"}
}