{
  "type": "Feature",
  "properties": {
    "iso:country":"BE",
    "sg:address":"Avenue D'hyon 52",
    "sg:city":"Mons",
    "sg:classifiers":[
        {
            "category":"Shopping",
            "subcategory":"Discount & Variety Stores",
            "type":"Retail Goods"
        }
    ],
    "sg:phone":"+32 65 33 47 38",
    "sg:postcode":"7000",
    "sg:province":"Hainaut",
    "sg:tags":[
        "shop",
        "clearers",
        "curiosity",
        "furniture"
    ],
    "wof:name":"Druart L.",
    "wof:placetype":"venue"
},
  "geometry": {"coordinates":[3.9546060562,50.4469795227],"type":"Point"}
}