{
  "type": "Feature",
  "properties": {
    "addr:full":"Quai Marcellis 4b11 Li\u00c8ge Li\u00e8ge 4020",
    "addr:housenumber":"4b11",
    "addr:postcode":"4020",
    "addr:street":"Quai Marcellis",
    "iso:country":"BE",
    "sg:address":"Quai Marcellis 4b11",
    "sg:city":"Li\u00c8ge",
    "sg:orig_category":"Avocats and conseillers juridiques",
    "sg:phone":"+32 4 343 56 06",
    "sg:postcode":"4020",
    "sg:province":"Li\u00e8ge",
    "wof:name":"Jean-paul Tasset",
    "wof:placetype":"venue"
},
  "geometry": {"coordinates":[5.5765681267,50.6361312866],"type":"Point"}
}