{
  "type": "Feature",
  "properties": {
    "addr:full":"Schoorbakkestraat 35 Diksmuide (pervijze) West-Vlaanderen 8600",
    "addr:housenumber":"35",
    "addr:postcode":"8600",
    "addr:street":"Schoorbakkestraat",
    "iso:country":"BE",
    "sg:address":"Schoorbakkestraat 35",
    "sg:city":"Diksmuide (pervijze)",
    "sg:classifiers":[
        {
            "category":"Farming",
            "subcategory":"Poultry Farm",
            "type":"Manufacturing & Wholesale Goods"
        }
    ],
    "sg:phone":"+32 51 55 50 25",
    "sg:postcode":"8600",
    "sg:province":"West-Vlaanderen",
    "sg:tags":[
        "rabbit",
        "slaughterhouse"
    ],
    "wof:name":"Sinnaeve Pluimveeslachterij",
    "wof:placetype":"venue"
},
  "geometry": {"coordinates":[2.8657801151,51.0334663391],"type":"Point"}
}