{
  "type": "Feature",
  "properties": {
    "iso:country":"BE",
    "sg:address":"Rue De Bl\u00c9zy 97",
    "sg:city":"Bertrix",
    "sg:orig_category":"Dakwerken",
    "sg:phone":"+32 61 41 44 40",
    "sg:postcode":"6880",
    "sg:province":"Luxembourg",
    "wof:name":"H.d. Toitures",
    "wof:placetype":"venue"
},
  "geometry": {"coordinates":[5.2746100426,49.8609657288],"type":"Point"}
}