{
  "type": "Feature",
  "properties": {
    "addr:full":"Rue De Gilly 79 Ch\u00e2telet (ch\u00e2telineau) Hainaut 6200",
    "addr:housenumber":"79",
    "addr:postcode":"6200",
    "addr:street":"Rue De Gilly",
    "iso:country":"BE",
    "sg:address":"Rue De Gilly 79",
    "sg:city":"Ch\u00e2telet (ch\u00e2telineau)",
    "sg:classifiers":[
        {
            "category":"Retail",
            "subcategory":"Driving School",
            "type":"Services"
        }
    ],
    "sg:phone":"+32 71 38 85 59",
    "sg:postcode":"6200",
    "sg:province":"Hainaut",
    "sg:tags":[
        "automobile",
        "officially",
        "-",
        "recognized"
    ],
    "wof:name":"Auto-ecole Starter",
    "wof:placetype":"venue"
},
  "geometry": {"coordinates":[4.5142951012,50.4098777771],"type":"Point"}
}