{
  "type": "Feature",
  "properties": {
    "iso:country":"BE",
    "sg:address":"Albert Li\u00c9nartstraat 25",
    "sg:city":"Aalst",
    "sg:classifiers":[
        {
            "category":"Insurance",
            "subcategory":"Insurance Agent",
            "type":"Services"
        }
    ],
    "sg:phone":"+32 53 78 98 14",
    "sg:postcode":"9300",
    "sg:province":"Oost-Vlaanderen",
    "sg:tags":[
        "verzekeringsmakelaars",
        "expert"
    ],
    "wof:name":"Bureau Eurasca",
    "wof:placetype":"venue"
},
  "geometry": {"coordinates":[4.0393691063,50.9419517517],"type":"Point"}
}