{
  "type": "Feature",
  "properties": {
    "iso:country":"BE",
    "sg:address":"Koebrugstraat 60",
    "sg:city":"Aalst",
    "sg:classifiers":[
        {
            "category":"Food & Beverages",
            "subcategory":"Fruits & Vegetables",
            "type":"Retail Goods"
        }
    ],
    "sg:phone":"+32 53 77 43 77",
    "sg:postcode":"9310",
    "sg:province":"Oost-Vlaanderen",
    "sg:tags":[
        "groenten"
    ],
    "wof:name":"Eddie Philips",
    "wof:placetype":"venue"
},
  "geometry": {"coordinates":[4.0909490585,50.9434089661],"type":"Point"}
}