{
  "type": "Feature",
  "properties": {
    "iso:country":"BE",
    "sg:address":"Leurebroekdreef 2",
    "sg:city":"Aalter",
    "sg:orig_category":"Rundveehouders",
    "sg:phone":"+32 51 68 83 64",
    "sg:postcode":"9880",
    "sg:province":"Oost-Vlaanderen",
    "wof:name":"Marc De Clercq",
    "wof:placetype":"venue"
},
  "geometry": {"coordinates":[3.4638500214,51.0379333496],"type":"Point"}
}