{
  "type": "Feature",
  "properties": {
    "addr:full":"Heistraat 188 Sint-niklaas Oost-Vlaanderen 9100",
    "addr:housenumber":"188",
    "addr:postcode":"9100",
    "addr:street":"Heistraat",
    "iso:country":"BE",
    "sg:address":"Heistraat 188",
    "sg:city":"Sint-niklaas",
    "sg:orig_category":"Verplichte sociale verzekeringen",
    "sg:phone":"+32 3 766 56 09",
    "sg:postcode":"9100",
    "sg:province":"Oost-Vlaanderen",
    "wof:name":"Christelijke Mutualiteit",
    "wof:placetype":"venue"
},
  "geometry": {"coordinates":[4.1380572319,51.1760673523],"type":"Point"}
}