{
  "type": "Feature",
  "properties": {
    "addr:full":"Avenue De La Coop\u00c9ration 5 Soumagne Li\u00e8ge 4630",
    "addr:housenumber":"5",
    "addr:postcode":"4630",
    "addr:street":"Avenue De La Coope\u0301Ration",
    "iso:country":"BE",
    "sg:address":"Avenue De La Coop\u00c9ration 5",
    "sg:city":"Soumagne",
    "sg:orig_category":"Geluidsopnames",
    "sg:phone":"+32 4 377 44 33",
    "sg:postcode":"4630",
    "sg:province":"Li\u00e8ge",
    "wof:name":"Init Sound Studio",
    "wof:placetype":"venue"
},
  "geometry": {"coordinates":[5.7320199013,50.6324195862],"type":"Point"}
}