{
  "type": "Feature",
  "properties": {
    "addr:full":"Keulestraat 8 Tielt-winge (tielt) Vlaams-Brabant 3390",
    "addr:housenumber":"8",
    "addr:postcode":"3390",
    "addr:street":"Keulestraat",
    "iso:country":"BE",
    "sg:address":"Keulestraat 8",
    "sg:city":"Tielt-winge (tielt)",
    "sg:classifiers":[
        {
            "category":"Utilities",
            "subcategory":"Refuse",
            "type":"Services"
        }
    ],
    "sg:phone":"+32 16 63 41 58",
    "sg:postcode":"3390",
    "sg:province":"Vlaams-Brabant",
    "sg:tags":[
        "miller"
    ],
    "wof:name":"De Blick V",
    "wof:placetype":"venue"
},
  "geometry": {"coordinates":[4.88960886,50.9308128357],"type":"Point"}
}