{
  "type": "Feature",
  "properties": {
    "addr:full":"Rue De La Chata\u00eegne 4 Renaix Oost-Vlaanderen 9600",
    "addr:housenumber":"4",
    "addr:postcode":"9600",
    "addr:street":"Rue De La Chatai\u0302Gne",
    "iso:country":"BE",
    "sg:address":"Rue De La Chata\u00eegne 4",
    "sg:city":"Renaix",
    "sg:classifiers":[
        {
            "category":"Insurance",
            "subcategory":"Insurance Agent",
            "type":"Services"
        }
    ],
    "sg:phone":"+32 55 50 66 80",
    "sg:postcode":"9600",
    "sg:province":"Oost-Vlaanderen",
    "sg:tags":[
        "broker"
    ],
    "wof:name":"Verhofax Nv",
    "wof:placetype":"venue"
},
  "geometry": {"coordinates":[3.6425430775,50.7694549561],"type":"Point"}
}