{
  "type": "Feature",
  "properties": {
    "iso:country":"BE",
    "sg:address":"Rue Sainte Catherine 139",
    "sg:city":"Manage",
    "sg:orig_category":"Metalen and ertsen Gh",
    "sg:phone":"+32 64 55 79 39",
    "sg:postcode":"7170",
    "sg:province":"Hainaut",
    "wof:name":"Chantier Brousmiche",
    "wof:placetype":"venue"
},
  "geometry": {"coordinates":[4.2298197746,50.5083694458],"type":"Point"}
}