{
  "type": "Feature",
  "properties": {
    "addr:full":"Rue Tillieux 38 Namur Namur 5100",
    "addr:housenumber":"38",
    "addr:postcode":"5100",
    "addr:street":"Rue Tillieux",
    "iso:country":"BE",
    "sg:address":"Rue Tillieux 38",
    "sg:city":"Namur",
    "sg:orig_category":"M\u00e9decins and sp\u00e9cialistes",
    "sg:phone":"+32 81 31 03 01",
    "sg:postcode":"5100",
    "sg:province":"Namur",
    "wof:name":"Myriam Dubois",
    "wof:placetype":"venue"
},
  "geometry": {"coordinates":[4.8713750839,50.4566345215],"type":"Point"}
}