{
  "type": "Feature",
  "properties": {
    "addr:full":"Blaubergsedreef 15 Herselt Antwerpen 2230",
    "addr:housenumber":"15",
    "addr:postcode":"2230",
    "addr:street":"Blaubergsedreef",
    "iso:country":"BE",
    "sg:address":"Blaubergsedreef 15",
    "sg:city":"Herselt",
    "sg:orig_category":"Woningbouw",
    "sg:phone":"+32 14 54 92 09",
    "sg:postcode":"2230",
    "sg:province":"Antwerpen",
    "wof:name":"Joris Verstappen",
    "wof:placetype":"venue"
},
  "geometry": {"coordinates":[4.8854632378,51.052772522],"type":"Point"}
}