{
  "type": "Feature",
  "properties": {
    "addr:full":"Notelaarsstraat 112 Schaarbeek/schaerbeek Bruxelles-Capitale 1030",
    "addr:housenumber":"112",
    "addr:postcode":"1030",
    "addr:street":"Notelaarsstraat",
    "iso:country":"BE",
    "sg:address":"Notelaarsstraat 112",
    "sg:city":"Schaarbeek/schaerbeek",
    "sg:orig_category":"Artsen and specialisten",
    "sg:phone":"+32 2 734 78 35",
    "sg:postcode":"1030",
    "sg:province":"Bruxelles-Capitale",
    "wof:name":"Pascal Sisani",
    "wof:placetype":"venue"
},
  "geometry": {"coordinates":[4.3890528679,50.8497161865],"type":"Point"}
}