{
  "type": "Feature",
  "properties": {
    "addr:full":"Boulevard Du Jubil\u00e9 160 Bruxelles (molenbeek-saint-jean) Bruxelles-Capitale 1080",
    "addr:housenumber":"160",
    "addr:postcode":"1080",
    "addr:street":"Boulevard Du Jubile\u0301",
    "iso:country":"BE",
    "sg:address":"Boulevard Du Jubil\u00e9 160",
    "sg:city":"Bruxelles (molenbeek-saint-jean)",
    "sg:classifiers":[
        {
            "category":"Professional",
            "subcategory":"Management & Consulting",
            "type":"Services"
        }
    ],
    "sg:phone":"+32 2 426 15 18",
    "sg:postcode":"1080",
    "sg:province":"Bruxelles-Capitale",
    "sg:tags":[
        "consultant"
    ],
    "wof:name":"Gernay C",
    "wof:placetype":"venue"
},
  "geometry": {"coordinates":[4.3403949738,50.8676834106],"type":"Point"}
}