{
  "type": "Feature",
  "properties": {
    "addr:full":"Vervoortplaats 21 Diest Vlaams-Brabant 3290",
    "addr:housenumber":"21",
    "addr:postcode":"3290",
    "addr:street":"Vervoortplaats",
    "iso:country":"BE",
    "sg:address":"Vervoortplaats 21",
    "sg:city":"Diest",
    "sg:classifiers":[
        {
            "category":"Landmark",
            "subcategory":"Memorial",
            "type":"Public Place"
        }
    ],
    "sg:phone":"+32 13 31 15 23",
    "sg:postcode":"3290",
    "sg:province":"Vlaams-Brabant",
    "sg:tags":[
        "-",
        "monument"
    ],
    "wof:name":"Juchtmans Hans",
    "wof:placetype":"venue"
},
  "geometry": {"coordinates":[5.0598158836,50.9797782898],"type":"Point"}
}