{
  "type": "Feature",
  "properties": {
    "iso:country":"BE",
    "sg:address":"Mechelsevest 108",
    "sg:city":"Leuven",
    "sg:classifiers":[
        {
            "category":"Organizations",
            "subcategory":"Community Association",
            "type":"Services"
        }
    ],
    "sg:phone":"+32 16 22 02 01",
    "sg:postcode":"3000",
    "sg:province":"Vlaams-Brabant",
    "sg:tags":[
        "cultural"
    ],
    "wof:name":"Monumentenwacht Vzw",
    "wof:placetype":"venue"
},
  "geometry": {"coordinates":[4.689658165,50.8874320984],"type":"Point"}
}