{
  "type": "Feature",
  "properties": {
    "iso:country":"BE",
    "sg:address":"Meersstraat 1",
    "sg:city":"Roeselare",
    "sg:classifiers":[
        {
            "category":"Manufacturing",
            "subcategory":"Textiles",
            "type":"Manufacturing & Wholesale Goods"
        }
    ],
    "sg:phone":"+32 51 24 26 24",
    "sg:postcode":"8800",
    "sg:province":"West-Vlaanderen",
    "sg:tags":[
        "raw",
        "material",
        "-"
    ],
    "wof:name":"Sarubo Nv",
    "wof:placetype":"venue"
},
  "geometry": {"coordinates":[3.138283968,50.9525794983],"type":"Point"}
}