{
  "type": "Feature",
  "properties": {
    "iso:country":"BE",
    "sg:address":"Rue Tout-vent 58",
    "sg:city":"Gosselies",
    "sg:classifiers":[
        {
            "category":"Cinema",
            "subcategory":"Movie Theater",
            "type":"Entertainment"
        }
    ],
    "sg:phone":"+32 71 34 03 34",
    "sg:postcode":"6041",
    "sg:province":"Hainaut",
    "sg:tags":[
        "transfer",
        "firing",
        "picture"
    ],
    "wof:name":"Landgraf A. & Co S.a.",
    "wof:placetype":"venue"
},
  "geometry": {"coordinates":[4.4266061783,50.4730796814],"type":"Point"}
}