{
  "type": "Feature",
  "properties": {
    "addr:full":"Herlaar 17 Herenthout Antwerpen 2270",
    "addr:housenumber":"17",
    "addr:postcode":"2270",
    "addr:street":"Herlaar",
    "iso:country":"BE",
    "sg:address":"Herlaar 17",
    "sg:city":"Herenthout",
    "sg:classifiers":[
        {
            "category":"Professional",
            "subcategory":"Management & Consulting",
            "type":"Services"
        }
    ],
    "sg:phone":"+32 14 51 95 11",
    "sg:postcode":"2270",
    "sg:province":"Antwerpen",
    "sg:tags":[
        "consultant"
    ],
    "wof:name":"C.m.a. Research Bvba",
    "wof:placetype":"venue"
},
  "geometry": {"coordinates":[4.7471079826,51.1202926636],"type":"Point"}
}