{
  "type": "Feature",
  "properties": {
    "addr:full":"Rue L\u00c9onard 223 Charleroi Hainaut 6061",
    "addr:housenumber":"223",
    "addr:postcode":"6061",
    "addr:street":"Rue Le\u0301Onard;Hainaut",
    "iso:country":"BE",
    "sg:address":"Rue L\u00c9onard 223",
    "sg:city":"Charleroi",
    "sg:classifiers":[
        {
            "category":"Restaurant",
            "type":"Food & Drink"
        }
    ],
    "sg:phone":"+32 71 32 42 54",
    "sg:postcode":"6061",
    "sg:province":"Hainaut",
    "wof:name":"Knossos",
    "wof:placetype":"venue"
},
  "geometry": {"coordinates":[4.4795150757,50.4009437561],"type":"Point"}
}