{
  "type": "Feature",
  "properties": {
    "addr:full":"Rue Du Ch\u00e2telain 32 Bruxelles (ixelles) Bruxelles-Capitale 1050",
    "addr:housenumber":"32",
    "addr:postcode":"1050",
    "addr:street":"Rue Du Cha\u0302Telain",
    "iso:country":"BE",
    "sg:address":"Rue Du Ch\u00e2telain 32",
    "sg:city":"Bruxelles (ixelles)",
    "sg:classifiers":[
        {
            "category":"Real Estate",
            "subcategory":"Developer",
            "type":"Services"
        }
    ],
    "sg:phone":"+32 2 627 19 11",
    "sg:postcode":"1050",
    "sg:province":"Bruxelles-Capitale",
    "sg:tags":[
        "project"
    ],
    "wof:name":"Wilhelm & Co Sa",
    "wof:placetype":"venue"
},
  "geometry": {"coordinates":[4.3622078896,50.8254318237],"type":"Point"}
}