{
  "type": "Feature",
  "properties": {
    "iso:country":"BE",
    "sg:address":"Schaarbeeklei 132",
    "sg:city":"Vilvoorde",
    "sg:orig_category":"Herstellingen and onderhoud van auto's",
    "sg:phone":"+32 2 251 19 45",
    "sg:postcode":"1800",
    "sg:province":"Vlaams-Brabant",
    "wof:name":"Carrosserie Italo-belge",
    "wof:placetype":"venue"
},
  "geometry": {"coordinates":[4.4268460274,50.9220466614],"type":"Point"}
}