{
  "type": "Feature",
  "properties": {
    "addr:full":"Moutstraat 3 Harelbeke (bavikhove) West-Vlaanderen 8531",
    "addr:housenumber":"3",
    "addr:postcode":"8531",
    "addr:street":"Moutstraat",
    "iso:country":"BE",
    "sg:address":"Moutstraat 3",
    "sg:city":"Harelbeke (bavikhove)",
    "sg:classifiers":[
        {
            "category":"Communications",
            "type":"Services"
        }
    ],
    "sg:phone":"+32 56 72 75 25",
    "sg:postcode":"8531",
    "sg:province":"West-Vlaanderen",
    "sg:tags":[
        "translator"
    ],
    "wof:name":"Cristoforo Colombo Bvba",
    "wof:placetype":"venue"
},
  "geometry": {"coordinates":[3.2979609966,50.8608055115],"type":"Point"}
}