{
  "type": "Feature",
  "properties": {
    "addr:full":"Rue De Bourlers 10 Chimay Hainaut 6460",
    "addr:housenumber":"10",
    "addr:postcode":"6460",
    "addr:street":"Rue De Bourlers",
    "iso:country":"BE",
    "sg:address":"Rue De Bourlers 10",
    "sg:city":"Chimay",
    "sg:orig_category":"Dierenartsen",
    "sg:phone":"+32 60 21 22 26",
    "sg:postcode":"6460",
    "sg:province":"Hainaut",
    "wof:name":"H. Barvaux",
    "wof:placetype":"venue"
},
  "geometry": {"coordinates":[4.3221101761,50.0467681885],"type":"Point"}
}