{
  "type": "Feature",
  "properties": {
    "iso:country":"BE",
    "sg:address":"Stationsstr 40",
    "sg:city":"Beveren",
    "sg:classifiers":[
        {
            "category":"Professional",
            "subcategory":"Business Services",
            "type":"Services"
        }
    ],
    "sg:phone":"+32 3 775 79 44",
    "sg:postcode":"9120",
    "sg:province":"Oost-Vlaanderen",
    "sg:tags":[
        "travel",
        "fair"
    ],
    "wof:name":"Scala Bvba",
    "wof:placetype":"venue"
},
  "geometry": {"coordinates":[4.257349968,51.210609436],"type":"Point"}
}