{
  "type": "Feature",
  "properties": {
    "addr:full":"Rue Du Facteur 9 Bruxelles (molenbeek-saint-jean) Bruxelles-Capitale 1080",
    "addr:housenumber":"9",
    "addr:postcode":"1080",
    "addr:street":"Rue Du Facteur",
    "iso:country":"BE",
    "sg:address":"Rue Du Facteur 9",
    "sg:city":"Bruxelles (molenbeek-saint-jean)",
    "sg:classifiers":[
        {
            "category":"Arena",
            "subcategory":"Sports Club",
            "type":"Entertainment"
        }
    ],
    "sg:phone":"+32 2 414 16 19",
    "sg:postcode":"1080",
    "sg:province":"Bruxelles-Capitale",
    "wof:name":"Body Building Atlas Gym",
    "wof:placetype":"venue"
},
  "geometry": {"coordinates":[4.338903904,50.8558235168],"type":"Point"}
}