{
  "type": "Feature",
  "properties": {
    "addr:full":"Place De La Sarthe 1 Sambreville Namur 5060",
    "addr:housenumber":"1",
    "addr:postcode":"5060",
    "addr:street":"Place De La Sarthe",
    "iso:country":"BE",
    "sg:address":"Place De La Sarthe 1",
    "sg:city":"Sambreville",
    "sg:orig_category":"Epiceries",
    "sg:phone":"+32 71 74 06 16",
    "sg:postcode":"5060",
    "sg:province":"Namur",
    "wof:name":"Maryver",
    "wof:placetype":"venue"
},
  "geometry": {"coordinates":[4.6285200119,50.4448738098],"type":"Point"}
}