{
  "type": "Feature",
  "properties": {
    "addr:full":"Orval 16 Florenville Luxembourg 6823",
    "addr:housenumber":"16",
    "addr:postcode":"6823",
    "iso:country":"BE",
    "sg:address":"Orval 16",
    "sg:city":"Florenville",
    "sg:orig_category":"Maisons de repos and r\u00e9sidences. Maisons de vacances",
    "sg:phone":"+32 61 31 37 16",
    "sg:postcode":"6823",
    "sg:province":"Luxembourg",
    "wof:name":"Senior R\u00c9sidence D'orval",
    "wof:placetype":"venue"
},
  "geometry": {"coordinates":[5.3443751335,49.6343421936],"type":"Point"}
}