{
  "type": "Feature",
  "properties": {
    "iso:country":"BE",
    "sg:address":"Rue Du Done\u00fb 36",
    "sg:city":"Rochefort (buissonville)",
    "sg:classifiers":[
        {
            "category":"Farming",
            "subcategory":"Livestock Farm",
            "type":"Manufacturing & Wholesale Goods"
        }
    ],
    "sg:phone":"+32 83 68 85 96",
    "sg:postcode":"5580",
    "sg:province":"Namur",
    "sg:tags":[
        "poultry",
        "rabbit"
    ],
    "wof:name":"Autrucherie Du Doneu",
    "wof:placetype":"venue"
},
  "geometry": {"coordinates":[5.1825699806,50.2034454346],"type":"Point"}
}