{
  "type": "Feature",
  "properties": {
    "iso:country":"BE",
    "sg:address":"Steenweg Op Mol 179",
    "sg:city":"Oud-turnhout",
    "sg:orig_category":"Epiceries",
    "sg:phone":"+32 14 45 20 20",
    "sg:postcode":"2360",
    "sg:province":"Antwerpen",
    "wof:name":"Supra",
    "wof:placetype":"venue"
},
  "geometry": {"coordinates":[5.0000801086,51.3108787537],"type":"Point"}
}