{
  "type": "Feature",
  "properties": {
    "addr:full":"Groenstraat 83 Lokeren Oost-Vlaanderen 9160",
    "addr:housenumber":"83",
    "addr:postcode":"9160",
    "addr:street":"Groenstraat",
    "iso:country":"BE",
    "sg:address":"Groenstraat 83",
    "sg:city":"Lokeren",
    "sg:orig_category":"Herstelling and restauratie van meubelen",
    "sg:phone":"+32 9 348 84 39",
    "sg:postcode":"9160",
    "sg:province":"Oost-Vlaanderen",
    "wof:name":"Jan Buyl",
    "wof:placetype":"venue"
},
  "geometry": {"coordinates":[4.0192451477,51.1143531799],"type":"Point"}
}