{
  "type": "Feature",
  "properties": {
    "iso:country":"BE",
    "sg:address":"Place Docteur Edouard Lodewijckx 5b",
    "sg:city":"Jodoigne",
    "sg:classifiers":[
        {
            "category":"Bars & Pubs",
            "type":"Food & Drink"
        }
    ],
    "sg:phone":"+32 10 81 60 70",
    "sg:postcode":"1370",
    "sg:province":"Brabant Wallon",
    "sg:tags":[
        "tavern"
    ],
    "wof:name":"O'leary's (le)",
    "wof:placetype":"venue"
},
  "geometry": {"coordinates":[4.8690052032,50.7250747681],"type":"Point"}
}