{
  "type": "Feature",
  "properties": {
    "addr:full":"Rue De Courri\u00e8re 30 Gesves (faulx-les-tombes) Namur 5340",
    "addr:housenumber":"30",
    "addr:postcode":"5340",
    "addr:street":"Rue De Courrie\u0300Re",
    "iso:country":"BE",
    "sg:address":"Rue De Courri\u00e8re 30",
    "sg:city":"Gesves (faulx-les-tombes)",
    "sg:classifiers":[
        {
            "category":"Professional",
            "subcategory":"Engineering",
            "type":"Services"
        }
    ],
    "sg:phone":"+32 81 57 06 29",
    "sg:postcode":"5340",
    "sg:province":"Namur",
    "sg:tags":[
        "precision"
    ],
    "wof:name":"Haquenne Sa",
    "wof:placetype":"venue"
},
  "geometry": {"coordinates":[5.0014281273,50.4221343994],"type":"Point"}
}