{
  "type": "Feature",
  "properties": {
    "addr:full":"Dendermondesteenweg 241 Destelbergen Oost-Vlaanderen 9070",
    "addr:housenumber":"241",
    "addr:postcode":"9070",
    "addr:street":"Dendermondesteenweg",
    "iso:country":"BE",
    "sg:address":"Dendermondesteenweg 241",
    "sg:city":"Destelbergen",
    "sg:orig_category":"Rev\u00eatements de sols and murs",
    "sg:phone":"+32 9 229 30 30",
    "sg:postcode":"9070",
    "sg:province":"Oost-Vlaanderen",
    "wof:name":"V.m. Tegels",
    "wof:placetype":"venue"
},
  "geometry": {"coordinates":[3.7694900036,51.0534591675],"type":"Point"}
}