{
  "type": "Feature",
  "properties": {
    "addr:full":"Avenue Bouvier 63 Virton Luxembourg 6760",
    "addr:housenumber":"63",
    "addr:postcode":"6760",
    "addr:street":"Avenue Bouvier",
    "iso:country":"BE",
    "sg:address":"Avenue Bouvier 63",
    "sg:city":"Virton",
    "sg:classifiers":[
        {
            "category":"Food & Beverages",
            "subcategory":"Specialty",
            "type":"Retail Goods"
        }
    ],
    "sg:phone":"+32 63 45 71 21",
    "sg:postcode":"6760",
    "sg:province":"Luxembourg",
    "sg:tags":[
        "health",
        "dietary",
        "-",
        "biological"
    ],
    "wof:name":"Gaune Nature",
    "wof:placetype":"venue"
},
  "geometry": {"coordinates":[5.5252799988,49.5647735596],"type":"Point"}
}