{
  "type": "Feature",
  "properties": {
    "addr:full":"Rue Du Chateau 4 Tournai Hainaut 7534",
    "addr:housenumber":"4",
    "addr:postcode":"7534",
    "addr:street":"Rue Du Chateau",
    "iso:country":"BE",
    "sg:address":"Rue Du Chateau 4",
    "sg:city":"Tournai",
    "sg:orig_category":"Binnenhuisarchitecten",
    "sg:phone":"+32 69 54 70 55",
    "sg:postcode":"7534",
    "sg:province":"Hainaut",
    "wof:name":"Coss\u00c9e De Maulde",
    "wof:placetype":"venue"
},
  "geometry": {"coordinates":[3.3872520924,50.6113052368],"type":"Point"}
}