{
  "type": "Feature",
  "properties": {
    "iso:country":"BE",
    "sg:address":"Gebr. Vandeveldestraat 46",
    "sg:city":"Gent",
    "sg:orig_category":"Deurwaarders",
    "sg:phone":"+32 9 225 34 44",
    "sg:postcode":"9000",
    "sg:province":"Oost-Vlaanderen",
    "wof:name":"Jean Vandenberghe",
    "wof:placetype":"venue"
},
  "geometry": {"coordinates":[3.7183709145,51.0507392883],"type":"Point"}
}