{
  "type": "Feature",
  "properties": {
    "addr:full":"Hogeweg 118 Geraardsbergen Oost-Vlaanderen 9500",
    "addr:housenumber":"118",
    "addr:postcode":"9500",
    "addr:street":"Hogeweg",
    "iso:country":"BE",
    "sg:address":"Hogeweg 118",
    "sg:city":"Geraardsbergen",
    "sg:orig_category":"Kapsalons",
    "sg:phone":"+32 54 42 13 90",
    "sg:postcode":"9500",
    "sg:province":"Oost-Vlaanderen",
    "wof:name":"Annebel Stevens",
    "wof:placetype":"venue"
},
  "geometry": {"coordinates":[3.8619170189,50.7658348083],"type":"Point"}
}