{
  "type": "Feature",
  "properties": {
    "iso:country":"BE",
    "sg:address":"Kruishoutemseweg 17",
    "sg:city":"Wortegem-petegem",
    "sg:orig_category":"Dansscholen Sportclubs Sportterreinen and installaties behalve sportcentra",
    "sg:phone":"+32 56 68 04 15",
    "sg:postcode":"9790",
    "sg:province":"Oost-Vlaanderen",
    "wof:name":"Sparta Wortegem",
    "wof:placetype":"venue"
},
  "geometry": {"coordinates":[3.5216350555,50.8586616516],"type":"Point"}
}