{
  "type": "Feature",
  "properties": {
    "iso:country":"BE",
    "sg:address":"Kazelstraat 20",
    "sg:city":"Sint-truiden",
    "sg:classifiers":[
        {
            "category":"Retail",
            "subcategory":"Car Wash",
            "type":"Services"
        }
    ],
    "sg:phone":"+32 11 69 29 01",
    "sg:postcode":"3800",
    "sg:province":"Limburg",
    "sg:tags":[
        "automobile",
        "washing",
        "-",
        "truck"
    ],
    "wof:name":"Car Cleaning Center",
    "wof:placetype":"venue"
},
  "geometry": {"coordinates":[5.1931939125,50.8175773621],"type":"Point"}
}