{
  "type": "Feature",
  "properties": {
    "iso:country":"BE",
    "sg:address":"Lieremanstraat 42",
    "sg:city":"Gent",
    "sg:orig_category":"Peinture. Eclairage et \u00e9quipements du foyer. Rev\u00eatements pour sols and murs",
    "sg:phone":"+32 9 226 28 73",
    "sg:postcode":"9000",
    "sg:province":"Oost-Vlaanderen",
    "wof:name":"Hans Govaert",
    "wof:placetype":"venue"
},
  "geometry": {"coordinates":[3.6993598938,51.055896759],"type":"Point"}
}