{
  "type": "Feature",
  "properties": {
    "addr:full":"Oudenaardsesteenweg 373 Erpe-mere (erpe) Oost-Vlaanderen 9420",
    "addr:housenumber":"373",
    "addr:postcode":"9420",
    "addr:street":"Oudenaardsesteenweg",
    "iso:country":"BE",
    "sg:address":"Oudenaardsesteenweg 373",
    "sg:city":"Erpe-mere (erpe)",
    "sg:classifiers":[
        {
            "category":"Cafe",
            "type":"Food & Drink"
        }
    ],
    "sg:phone":"+32 53 83 95 00",
    "sg:postcode":"9420",
    "sg:province":"Oost-Vlaanderen",
    "sg:tags":[
        "snack-bars"
    ],
    "wof:name":"Snack (de)",
    "wof:placetype":"venue"
},
  "geometry": {"coordinates":[3.9569480419,50.9266891479],"type":"Point"}
}