{
  "type": "Feature",
  "properties": {
    "addr:full":"Rue Trixhe \u00c0 L\u00b4arbre 11 Hannut Li\u00e8ge 4280",
    "addr:housenumber":"11",
    "addr:postcode":"4280",
    "addr:street":"Rue Trixhe A\u0300 L\u00b4Arbre",
    "iso:country":"BE",
    "sg:address":"Rue Trixhe \u00c0 L\u00b4arbre 11",
    "sg:city":"Hannut",
    "sg:classifiers":[
        {
            "category":"Arena",
            "subcategory":"Sports Club",
            "type":"Entertainment"
        }
    ],
    "sg:phone":"+32 19 51 26 80",
    "sg:postcode":"4280",
    "sg:province":"Li\u00e8ge",
    "sg:tags":[
        "de"
    ],
    "wof:name":"Les Amis Henry Fontaine",
    "wof:placetype":"venue"
},
  "geometry": {"coordinates":[5.0387420654,50.6987190247],"type":"Point"}
}