{
  "type": "Feature",
  "properties": {
    "addr:full":"Rue D\u00b4audernade 10 Ellezelles Hainaut 7890",
    "addr:housenumber":"10",
    "addr:postcode":"7890",
    "addr:street":"Rue D\u00b4Audernade",
    "iso:country":"BE",
    "sg:address":"Rue D\u00b4audernade 10",
    "sg:city":"Ellezelles",
    "sg:orig_category":"Journaux. Tabac",
    "sg:phone":"+32 68 54 39 02",
    "sg:postcode":"7890",
    "sg:province":"Hainaut",
    "wof:name":"Librairie Michel",
    "wof:placetype":"venue"
},
  "geometry": {"coordinates":[3.6815640926,50.7346916199],"type":"Point"}
}