{
  "type": "Feature",
  "properties": {
    "addr:full":"Zandstraat 6 Begijnendijk Vlaams-Brabant 3130",
    "addr:housenumber":"6",
    "addr:postcode":"3130",
    "addr:street":"Zandstraat",
    "iso:country":"BE",
    "sg:address":"Zandstraat 6",
    "sg:city":"Begijnendijk",
    "sg:orig_category":"Beautyfarms, relaxatie and lichamelijk welzijn Schoonheidssalons",
    "sg:phone":"+32 16 53 31 11",
    "sg:postcode":"3130",
    "sg:province":"Vlaams-Brabant",
    "wof:name":"Instituut Ikia",
    "wof:placetype":"venue"
},
  "geometry": {"coordinates":[4.7730278969,51.0162963867],"type":"Point"}
}