{
  "type": "Feature",
  "properties": {
    "addr:full":"Staatsbaan 89 Bekkevoort Vlaams-Brabant 3460",
    "addr:housenumber":"89",
    "addr:postcode":"3460",
    "addr:street":"Staatsbaan",
    "iso:country":"BE",
    "sg:address":"Staatsbaan 89",
    "sg:city":"Bekkevoort",
    "sg:classifiers":[
        {
            "category":"Tea Room",
            "subcategory":"None",
            "type":"Food & Drink"
        }
    ],
    "sg:phone":"+32 13 32 31 27",
    "sg:postcode":"3460",
    "sg:province":"Vlaams-Brabant",
    "sg:tags":[
        "rental",
        "-",
        "furnished"
    ],
    "wof:name":"Cupido",
    "wof:placetype":"venue"
},
  "geometry": {"coordinates":[5.0074529648,50.9556236267],"type":"Point"}
}