{
  "type": "Feature",
  "properties": {
    "iso:country":"BE",
    "sg:address":"Rue Des Rouaux 10",
    "sg:city":"Assesse",
    "sg:classifiers":[
        {
            "category":"Personal",
            "subcategory":"Beauty Salon",
            "type":"Services"
        }
    ],
    "sg:phone":"+32 83 65 56 88",
    "sg:postcode":"5336",
    "sg:province":"Namur",
    "sg:tags":[
        "de",
        "coiffure"
    ],
    "wof:name":"Lucy Et Mireille Coiffure",
    "wof:placetype":"venue"
},
  "geometry": {"coordinates":[4.9967088699,50.3900375366],"type":"Point"}
}