{
  "type": "Feature",
  "properties": {
    "addr:full":"Stationsstraat 157 Berlaar Antwerpen 2590",
    "addr:housenumber":"157",
    "addr:postcode":"2590",
    "addr:street":"Stationsstraat",
    "iso:country":"BE",
    "sg:address":"Stationsstraat 157",
    "sg:city":"Berlaar",
    "sg:classifiers":[
        {
            "category":"Building & Trades",
            "subcategory":"Electrical",
            "type":"Services"
        }
    ],
    "sg:phone":"+32 3 482 14 11",
    "sg:postcode":"2590",
    "sg:province":"Antwerpen",
    "sg:tags":[
        "electric",
        "-",
        "housewiring",
        "contractor"
    ],
    "wof:name":"Kempenaers R",
    "wof:placetype":"venue"
},
  "geometry": {"coordinates":[4.6424160004,51.1138916016],"type":"Point"}
}