{
  "type": "Feature",
  "properties": {
    "addr:full":"Rue Des Clarisses Li\u00e8ge Li\u00e8ge 4000",
    "addr:postcode":"4000",
    "addr:street":"Rue Des Clarisses",
    "iso:country":"BE",
    "sg:address":"Rue Des Clarisses",
    "sg:city":"Li\u00e8ge",
    "sg:classifiers":[
        {
            "category":"Banks & Credit Unions",
            "subcategory":"Bank",
            "type":"Services"
        }
    ],
    "sg:phone":"+32 41207511",
    "sg:postcode":"4000",
    "sg:province":"Li\u00e8ge",
    "wof:name":"Soci\u00e9t\u00e9 Nationale De Cr\u00e9dit, \u00e0 I'industrie Sa",
    "wof:placetype":"venue"
},
  "geometry": {"coordinates":[5.5700950623,50.6382217407],"type":"Point"}
}