{
  "type": "Feature",
  "properties": {
    "iso:country":"BE",
    "sg:address":"Koningin Astrid Plein 16",
    "sg:city":"Jette/jette",
    "sg:classifiers":[
        {
            "category":"Cafe",
            "type":"Food & Drink"
        }
    ],
    "sg:phone":"+32 2 428 68 51",
    "sg:postcode":"1090",
    "sg:province":"Bruxelles-Capitale",
    "sg:tags":[
        "caf\u00e9s"
    ],
    "wof:name":"Caf\u00c9 Petit Luna",
    "wof:placetype":"venue"
},
  "geometry": {"coordinates":[4.3248949051,50.8724822998],"type":"Point"}
}