{
  "type": "Feature",
  "properties": {
    "iso:country":"BE",
    "sg:address":"Krijgsbaan 86",
    "sg:city":"Mortsel",
    "sg:orig_category":"Fotografen and fotostudio's",
    "sg:phone":"+32 3 448 21 49",
    "sg:postcode":"2640",
    "sg:province":"Antwerpen",
    "wof:name":"Studio 3",
    "wof:placetype":"venue"
},
  "geometry": {"coordinates":[4.451529026,51.173614502],"type":"Point"}
}