{
  "type": "Feature",
  "properties": {
    "addr:full":"Neerstraat 100 Waasmunster Oost-Vlaanderen 9250",
    "addr:housenumber":"100",
    "addr:postcode":"9250",
    "addr:street":"Neerstraat",
    "iso:country":"BE",
    "sg:address":"Neerstraat 100",
    "sg:city":"Waasmunster",
    "sg:classifiers":[
        {
            "category":"Manufacturing",
            "subcategory":"Metals",
            "type":"Manufacturing & Wholesale Goods"
        }
    ],
    "sg:phone":"+32 52 46 08 81",
    "sg:postcode":"9250",
    "sg:province":"Oost-Vlaanderen",
    "sg:tags":[
        "processing",
        "component",
        "shaped"
    ],
    "wof:name":"Wase Verspanningsmaatschappij Nv",
    "wof:placetype":"venue"
},
  "geometry": {"coordinates":[4.0700497627,51.1100845337],"type":"Point"}
}