{
  "type": "Feature",
  "properties": {
    "addr:full":"Kloosterstraat 82bb Moeskroen/mouscron Hainaut 7700",
    "addr:housenumber":"82bb moeskroen;mouscron",
    "addr:postcode":"7700",
    "addr:street":"Kloosterstraat;Hainaut",
    "iso:country":"BE",
    "sg:address":"Kloosterstraat 82bb",
    "sg:city":"Moeskroen/mouscron",
    "sg:orig_category":"Hoger onderwijs",
    "sg:phone":"+32 56 33 29 00",
    "sg:postcode":"7700",
    "sg:province":"Hainaut",
    "wof:name":"I.t.e.h.o.",
    "wof:placetype":"venue"
},
  "geometry": {"coordinates":[3.2323200703,50.7400932312],"type":"Point"}
}