{
  "type": "Feature",
  "properties": {
    "addr:full":"Baalsebaan 252 Tremelo Vlaams-Brabant 3128",
    "addr:housenumber":"252",
    "addr:postcode":"3128",
    "addr:street":"Baalsebaan",
    "iso:country":"BE",
    "sg:address":"Baalsebaan 252",
    "sg:city":"Tremelo",
    "sg:orig_category":"Woningbouw",
    "sg:phone":"+32 16 53 30 75",
    "sg:postcode":"3128",
    "sg:province":"Vlaams-Brabant",
    "wof:name":"Gebroeders De Roover",
    "wof:placetype":"venue"
},
  "geometry": {"coordinates":[4.7404332161,50.9949417114],"type":"Point"}
}