{
  "type": "Feature",
  "properties": {
    "iso:country":"BE",
    "sg:address":"Verte Herbe 11",
    "sg:city":"Antoing",
    "sg:orig_category":"Herstellingen and onderhoud van auto's",
    "sg:phone":"+32 69 44 32 63",
    "sg:postcode":"7640",
    "sg:province":"Hainaut",
    "wof:name":"Preumont",
    "wof:placetype":"venue"
},
  "geometry": {"coordinates":[3.4494299889,50.5632705688],"type":"Point"}
}