{
  "type": "Feature",
  "properties": {
    "addr:full":"Nieuwstraat 27 Grobbendonk Antwerpen 2280",
    "addr:housenumber":"27",
    "addr:postcode":"2280",
    "addr:street":"Nieuwstraat",
    "iso:country":"BE",
    "sg:address":"Nieuwstraat 27",
    "sg:city":"Grobbendonk",
    "sg:orig_category":"Sportterreinen and installaties behalve sportcentra",
    "sg:phone":"+32 475 45 41 14",
    "sg:postcode":"2280",
    "sg:province":"Antwerpen",
    "wof:name":"Arlonta Rijschool",
    "wof:placetype":"venue"
},
  "geometry": {"coordinates":[4.7338051796,51.1826820374],"type":"Point"}
}