{
  "type": "Feature",
  "properties": {
    "addr:full":"Rue Du G\u00c9n\u00c9ral Leman 23 Dour Hainaut 7370",
    "addr:housenumber":"23",
    "addr:postcode":"7370",
    "addr:street":"Rue Du Ge\u0301Ne\u0301Ral Leman;Hainaut",
    "iso:country":"BE",
    "sg:address":"Rue Du G\u00c9n\u00c9ral Leman 23",
    "sg:city":"Dour",
    "sg:orig_category":"M\u00e9decins and sp\u00e9cialistes",
    "sg:phone":"+32 65 65 41 11",
    "sg:postcode":"7370",
    "sg:province":"Hainaut",
    "wof:name":"Ch. Dfouni",
    "wof:placetype":"venue"
},
  "geometry": {"coordinates":[3.7827110291,50.4004821777],"type":"Point"}
}