{
  "type": "Feature",
  "properties": {
    "addr:full":"Albert Woutersstraat 54 Leuven Vlaams-Brabant 3012",
    "addr:housenumber":"54",
    "addr:postcode":"3012",
    "addr:street":"Albert Woutersstraat",
    "iso:country":"BE",
    "sg:address":"Albert Woutersstraat 54",
    "sg:city":"Leuven",
    "sg:orig_category":"Boekhouders",
    "sg:phone":"+32 16 23 56 48",
    "sg:postcode":"3012",
    "sg:province":"Vlaams-Brabant",
    "wof:name":"Marc Ceusters",
    "wof:placetype":"venue"
},
  "geometry": {"coordinates":[4.6982541084,50.8919830322],"type":"Point"}
}