{
  "type": "Feature",
  "properties": {
    "addr:full":"Langensteenweg 69 Merchtem Vlaams-Brabant 1785",
    "addr:housenumber":"69",
    "addr:postcode":"1785",
    "addr:street":"Langensteenweg",
    "iso:country":"BE",
    "sg:address":"Langensteenweg 69",
    "sg:city":"Merchtem",
    "sg:classifiers":[
        {
            "category":"Bakery",
            "type":"Food & Drink"
        }
    ],
    "sg:phone":"+32 52 37 19 38",
    "sg:postcode":"1785",
    "sg:province":"Vlaams-Brabant",
    "sg:tags":[
        "confectioner",
        "baker"
    ],
    "wof:name":"Joos",
    "wof:placetype":"venue"
},
  "geometry": {"coordinates":[4.2326798439,50.9595489502],"type":"Point"}
}