{
  "type": "Feature",
  "properties": {
    "iso:country":"BE",
    "sg:address":"Dijkstraat 33",
    "sg:city":"Zandhoven (viersel)",
    "sg:classifiers":[
        {
            "category":"Animal Shelter",
            "type":"Public Place"
        }
    ],
    "sg:phone":"+32 3 484 40 23",
    "sg:postcode":"2240",
    "sg:province":"Antwerpen",
    "wof:name":"Kattenpension Roskam",
    "wof:placetype":"venue"
},
  "geometry": {"coordinates":[4.6623067856,51.1925544739],"type":"Point"}
}