{
  "type": "Feature",
  "properties": {
    "iso:country":"BE",
    "sg:address":"Mandekensstraat 24",
    "sg:city":"Lebbeke",
    "sg:classifiers":[
        {
            "category":"Bakery",
            "type":"Food & Drink"
        }
    ],
    "sg:phone":"+32 52 34 28 31",
    "sg:postcode":"9280",
    "sg:province":"Oost-Vlaanderen",
    "sg:tags":[
        "confectioner",
        "baker"
    ],
    "wof:name":"Loverie",
    "wof:placetype":"venue"
},
  "geometry": {"coordinates":[4.1540970802,51.0204048157],"type":"Point"}
}