{
  "type": "Feature",
  "properties": {
    "addr:full":"Ternatsestraat 9 Affligem Vlaams-Brabant 1790",
    "addr:housenumber":"9",
    "addr:postcode":"1790",
    "addr:street":"Ternatsestraat",
    "iso:country":"BE",
    "sg:address":"Ternatsestraat 9",
    "sg:city":"Affligem",
    "sg:orig_category":"Enseignement maternel and primaire",
    "sg:phone":"+32 2 582 37 87",
    "sg:postcode":"1790",
    "sg:province":"Vlaams-Brabant",
    "wof:name":"Gemeentelijke Basisschool",
    "wof:placetype":"venue"
},
  "geometry": {"coordinates":[4.1373848915,50.9006652832],"type":"Point"}
}