{
  "type": "Feature",
  "properties": {
    "iso:country":"BE",
    "sg:address":"Langestraat 173",
    "sg:city":"Brugge",
    "sg:orig_category":"Cr\u00e9meries. Produits surgel\u00e9s Gr",
    "sg:phone":"+32 50 33 20 08",
    "sg:postcode":"8000",
    "sg:province":"West-Vlaanderen",
    "wof:name":"Ijsboerke",
    "wof:placetype":"venue"
},
  "geometry": {"coordinates":[3.2391109467,51.2126312256],"type":"Point"}
}