{
  "type": "Feature",
  "properties": {
    "addr:full":"Turnhoutsebaan 152 Retie Antwerpen 2470",
    "addr:housenumber":"152",
    "addr:postcode":"2470",
    "addr:street":"Turnhoutsebaan",
    "iso:country":"BE",
    "sg:address":"Turnhoutsebaan 152",
    "sg:city":"Retie",
    "sg:orig_category":"Epiceries",
    "sg:phone":"+32 14 37 87 89",
    "sg:postcode":"2470",
    "sg:province":"Antwerpen",
    "wof:name":"D. Paeshuyse",
    "wof:placetype":"venue"
},
  "geometry": {"coordinates":[5.0643072128,51.2783660889],"type":"Point"}
}