{
  "type": "Feature",
  "properties": {
    "iso:country":"BE",
    "sg:address":"Boulevard Lambermont 310",
    "sg:city":"Brussel/bruxelles",
    "sg:orig_category":"Animations diverses",
    "sg:phone":"+32 2 242 80 61",
    "sg:postcode":"1030",
    "sg:province":"Bruxelles-Capitale",
    "wof:name":"Jade Management",
    "wof:placetype":"venue"
},
  "geometry": {"coordinates":[4.3857398033,50.866519928],"type":"Point"}
}