{
  "type": "Feature",
  "properties": {
    "addr:full":"Heilige Geeststraat 7 Kortrijk West-Vlaanderen 8500",
    "addr:housenumber":"7",
    "addr:postcode":"8500",
    "addr:street":"Heilige Geeststraat",
    "iso:country":"BE",
    "sg:address":"Heilige Geeststraat 7",
    "sg:city":"Kortrijk",
    "sg:orig_category":"Imprimeries and copyshops. Activit\u00e9s diverses d'imprimerie",
    "sg:phone":"+32 56 21 45 12",
    "sg:postcode":"8500",
    "sg:province":"West-Vlaanderen",
    "wof:name":"Diaboliks-arribal",
    "wof:placetype":"venue"
},
  "geometry": {"coordinates":[3.2623529434,50.8281593323],"type":"Point"}
}