{
  "type": "Feature",
  "properties": {
    "iso:country":"BE",
    "sg:address":"Boulevard De La Fleur-de-lys 25",
    "sg:city":"Nivelles",
    "sg:orig_category":"Sociale huisvestingsmaatschappijen",
    "sg:phone":"+32 67 84 23 96",
    "sg:postcode":"1400",
    "sg:province":"Brabant Wallon",
    "wof:name":"N\u00d4tre Maison",
    "wof:placetype":"venue"
},
  "geometry": {"coordinates":[4.3271040916,50.5995445251],"type":"Point"}
}