{
  "type": "Feature",
  "properties": {
    "addr:full":"Chemin De L'eglise Saint-pierre 3 Genappe (glabais) Brabant Wallon 1473",
    "addr:housenumber":"3",
    "addr:postcode":"1473",
    "addr:street":"Chemin De L'Eglise Saint-Pierre;Wallon",
    "iso:country":"BE",
    "sg:address":"Chemin De L'eglise Saint-pierre 3",
    "sg:city":"Genappe (glabais)",
    "sg:classifiers":[
        {
            "category":"Travel",
            "subcategory":"Resort",
            "type":"Entertainment"
        }
    ],
    "sg:phone":"+32 67 77 32 50",
    "sg:postcode":"1473",
    "sg:province":"Brabant Wallon",
    "sg:tags":[
        "vacation"
    ],
    "wof:name":"Ferme St-pierre",
    "wof:placetype":"venue"
},
  "geometry": {"coordinates":[4.4532399178,50.6299095154],"type":"Point"}
}