{
  "type": "Feature",
  "properties": {
    "addr:full":"Oude Weg 15 Kapellen (mariaburg) Antwerpen 2950",
    "addr:housenumber":"15",
    "addr:postcode":"2950",
    "addr:street":"Oude Weg",
    "iso:country":"BE",
    "sg:address":"Oude Weg 15",
    "sg:city":"Kapellen (mariaburg)",
    "sg:classifiers":[
        {
            "category":"Professional",
            "subcategory":"Management & Consulting",
            "type":"Services"
        }
    ],
    "sg:phone":"+32 3 605 78 70",
    "sg:postcode":"2950",
    "sg:province":"Antwerpen",
    "sg:tags":[
        "-",
        "processing",
        "data",
        "consultant"
    ],
    "wof:name":"G.v.r.",
    "wof:placetype":"venue"
},
  "geometry": {"coordinates":[4.4336590767,51.3040504456],"type":"Point"}
}