{
  "type": "Feature",
  "properties": {
    "addr:full":"Irislaan 38 Middelkerke West-Vlaanderen 8434",
    "addr:housenumber":"38",
    "addr:postcode":"8434",
    "addr:street":"Irislaan",
    "iso:country":"BE",
    "sg:address":"Irislaan 38",
    "sg:city":"Middelkerke",
    "sg:orig_category":"H\u00f4tels",
    "sg:phone":"+32 59 30 16 81",
    "sg:postcode":"8434",
    "sg:province":"West-Vlaanderen",
    "wof:name":"Hotel De Wielingen",
    "wof:placetype":"venue"
},
  "geometry": {"coordinates":[2.7696759701,51.1654510498],"type":"Point"}
}