{
  "type": "Feature",
  "properties": {
    "addr:full":"Rue Des Aulnes 32 Mont-saint-guibert Brabant Wallon 1435",
    "addr:housenumber":"32",
    "addr:postcode":"1435",
    "addr:street":"Rue Des Aulnes",
    "iso:country":"BE",
    "sg:address":"Rue Des Aulnes 32",
    "sg:city":"Mont-saint-guibert",
    "sg:classifiers":[
        {
            "category":"Community Center",
            "type":"Public Place"
        }
    ],
    "sg:phone":"+32 2 241 98 01",
    "sg:postcode":"1435",
    "sg:province":"Brabant Wallon",
    "sg:tags":[
        "medical"
    ],
    "wof:name":"Pinochiom Sprl",
    "wof:placetype":"venue"
},
  "geometry": {"coordinates":[4.6242852211,50.6387863159],"type":"Point"}
}