{
  "type": "Feature",
  "properties": {
    "addr:full":"Rue Mandenne 36 Momignies Hainaut 6590",
    "addr:housenumber":"36",
    "addr:postcode":"6590",
    "addr:street":"Rue Mandenne;Hainaut",
    "iso:country":"BE",
    "sg:address":"Rue Mandenne 36",
    "sg:city":"Momignies",
    "sg:classifiers":[
        {
            "category":"Fast Food",
            "type":"Food & Drink"
        }
    ],
    "sg:phone":"+32 60 51 30 02",
    "sg:postcode":"6590",
    "sg:province":"Hainaut",
    "sg:tags":[
        "\u00c0",
        "emporter",
        "restaurants"
    ],
    "wof:name":"Delice Frit'",
    "wof:placetype":"venue"
},
  "geometry": {"coordinates":[4.1464347839,50.0286216736],"type":"Point"}
}