{
  "type": "Feature",
  "properties": {
    "iso:country":"BE",
    "sg:address":"Rue Antoine Melin 14",
    "sg:city":"Namur",
    "sg:classifiers":[
        {
            "category":"Insurance",
            "subcategory":"Life Insurance",
            "type":"Services"
        }
    ],
    "sg:phone":"+32 81 46 01 02",
    "sg:postcode":"5100",
    "sg:province":"Namur",
    "sg:tags":[
        "assurance"
    ],
    "wof:name":"Ban - Andre Dejaie",
    "wof:placetype":"venue"
},
  "geometry": {"coordinates":[4.8751440048,50.4205474854],"type":"Point"}
}