{
  "type": "Feature",
  "properties": {
    "addr:full":"Rue D'ougr\u00e9e 65 Seraing (boncelles) Li\u00e8ge 4100",
    "addr:housenumber":"65",
    "addr:postcode":"4100",
    "addr:street":"Rue D'Ougre \u0301E",
    "iso:country":"BE",
    "sg:address":"Rue D'ougr\u00e9e 65",
    "sg:city":"Seraing (boncelles)",
    "sg:classifiers":[
        {
            "category":"Retail",
            "subcategory":"Auto Repair",
            "type":"Services"
        }
    ],
    "sg:phone":"+32 4 337 22 38",
    "sg:postcode":"4100",
    "sg:province":"Li\u00e8ge",
    "sg:tags":[
        "automobile-body"
    ],
    "wof:name":"Ernotte S Carrosserie",
    "wof:placetype":"venue"
},
  "geometry": {"coordinates":[5.5082731247,50.5836410522],"type":"Point"}
}