{
  "type": "Feature",
  "properties": {
    "iso:country":"BE",
    "sg:address":"Rue De Dave 9-11",
    "sg:city":"Namur (jambes)",
    "sg:classifiers":[
        {
            "category":"Banks & Credit Unions",
            "subcategory":"Investment Brokerage",
            "type":"Services"
        }
    ],
    "sg:phone":"+32 81 30 03 16",
    "sg:postcode":"5100",
    "sg:province":"Namur",
    "sg:tags":[
        "printing",
        "-"
    ],
    "wof:name":"Imprimerie Gilson R Sprl",
    "wof:placetype":"venue"
},
  "geometry": {"coordinates":[4.8713750839,50.4566345215],"type":"Point"}
}