{
  "type": "Feature",
  "properties": {
    "iso:country":"BE",
    "sg:address":"Rue Neuve 11",
    "sg:city":"Huy",
    "sg:classifiers":[
        {
            "category":"Shopping",
            "subcategory":"Gifts & Souvenirs",
            "type":"Retail Goods"
        }
    ],
    "sg:phone":"+32 85 23 41 00",
    "sg:postcode":"4500",
    "sg:province":"Li\u00e8ge",
    "sg:tags":[
        "geschenken"
    ],
    "wof:name":"Exclusiv",
    "wof:placetype":"venue"
},
  "geometry": {"coordinates":[5.2358951569,50.5205612183],"type":"Point"}
}