{
  "type": "Feature",
  "properties": {
    "addr:full":"Sint-truidensesteenweg 132 Linter (orsmaal-gussenhoven) Vlaams-Brabant 3350",
    "addr:housenumber":"132",
    "addr:postcode":"3350",
    "addr:street":"Sint-Truidensesteenweg",
    "iso:country":"BE",
    "sg:address":"Sint-truidensesteenweg 132",
    "sg:city":"Linter (orsmaal-gussenhoven)",
    "sg:classifiers":[
        {
            "category":"Retail",
            "subcategory":"Auto Repair",
            "type":"Services"
        }
    ],
    "sg:phone":"+32 16 78 80 84",
    "sg:postcode":"3350",
    "sg:province":"Vlaams-Brabant",
    "sg:tags":[
        "automobile",
        "-",
        "wrecking"
    ],
    "wof:name":"Maho Petrus En Zn",
    "wof:placetype":"venue"
},
  "geometry": {"coordinates":[5.0107297897,50.7979125977],"type":"Point"}
}