{
  "type": "Feature",
  "properties": {
    "addr:full":"Mari\u00cbnhovedreef 11 Jabbeke West-Vlaanderen 8490",
    "addr:housenumber":"11",
    "addr:postcode":"8490",
    "addr:street":"Marie\u0308Nhovedreef",
    "iso:country":"BE",
    "sg:address":"Mari\u00cbnhovedreef 11",
    "sg:city":"Jabbeke",
    "sg:orig_category":"RESTAURANTS: ALIMENTATION SP\u00c9CIALIS\u00c9E",
    "sg:phone":"+32 50 38 83 70",
    "sg:postcode":"8490",
    "sg:province":"West-Vlaanderen",
    "wof:name":"Solvida",
    "wof:placetype":"venue"
},
  "geometry": {"coordinates":[3.1436910629,51.1811981201],"type":"Point"}
}