{
  "type": "Feature",
  "properties": {
    "iso:country":"BE",
    "sg:address":"Bd De La Sauveni\u00c8re 134",
    "sg:city":"Li\u00c8ge",
    "sg:classifiers":[
        {
            "category":"Cinema",
            "subcategory":"Movie Rental",
            "type":"Entertainment"
        }
    ],
    "sg:phone":"+32 4 223 09 65",
    "sg:postcode":"4000",
    "sg:province":"Li\u00e8ge",
    "sg:tags":[
        "de",
        "cassette",
        "location",
        "vid\u00e9o",
        "audio"
    ],
    "wof:name":"Vid\u00c9orama",
    "wof:placetype":"venue"
},
  "geometry": {"coordinates":[5.566411972,50.6417388916],"type":"Point"}
}