{
  "type": "Feature",
  "properties": {
    "addr:full":"Herentalsesteenweg 86 Kasterlee Antwerpen 2460",
    "addr:housenumber":"86",
    "addr:postcode":"2460",
    "addr:street":"Herentalsesteenweg",
    "iso:country":"BE",
    "sg:address":"Herentalsesteenweg 86",
    "sg:city":"Kasterlee",
    "sg:orig_category":"Erotische Etablissementen",
    "sg:phone":"+32 14 55 76 43",
    "sg:postcode":"2460",
    "sg:province":"Antwerpen",
    "wof:name":"Landjuweeltje",
    "wof:placetype":"venue"
},
  "geometry": {"coordinates":[4.8964028358,51.2076873779],"type":"Point"}
}