{
  "type": "Feature",
  "properties": {
    "iso:country":"BE",
    "sg:address":"Oude Ieperstraat 4",
    "sg:city":"Wevelgem",
    "sg:orig_category":"Avocats and conseillers juridiques",
    "sg:phone":"+32 56 41 68 54",
    "sg:postcode":"8560",
    "sg:province":"West-Vlaanderen",
    "wof:name":"Filip Houvenaghel",
    "wof:placetype":"venue"
},
  "geometry": {"coordinates":[3.2122740746,50.8356437683],"type":"Point"}
}