{
  "type": "Feature",
  "properties": {
    "iso:country":"BE",
    "sg:address":"Chauss\u00c9e De Bruxelles 376",
    "sg:city":"Tournai",
    "sg:orig_category":"Hout and afgeleiden Gh IJzerwaren, bouw- and verfmaterialen Verhuur doe-het-zelf materiaal",
    "sg:phone":"+32 69 89 03 03",
    "sg:postcode":"7500",
    "sg:province":"Hainaut",
    "wof:name":"Gamma",
    "wof:placetype":"venue"
},
  "geometry": {"coordinates":[3.4236249924,50.6031303406],"type":"Point"}
}