{
  "type": "Feature",
  "properties": {
    "iso:country":"BE",
    "sg:address":"Bedrijvenlaan 14",
    "sg:city":"Lochristi",
    "sg:classifiers":[
        {
            "category":"Professional",
            "subcategory":"Engineering",
            "type":"Services"
        }
    ],
    "sg:phone":"+32 9 265 75 55",
    "sg:postcode":"9080",
    "sg:province":"Oost-Vlaanderen",
    "sg:tags":[
        "machine",
        "-",
        "mechanical"
    ],
    "wof:name":"Dehaeck Construct Nv",
    "wof:placetype":"venue"
},
  "geometry": {"coordinates":[3.8704099655,51.1043891907],"type":"Point"}
}