{
  "type": "Feature",
  "properties": {
    "addr:full":"Kleinedijk Diksmuide West-Vlaanderen 8600",
    "addr:postcode":"8600",
    "iso:country":"BE",
    "sg:address":"Kleinedijk",
    "sg:city":"Diksmuide",
    "sg:orig_category":"MBK. Entretien and r\u00e9parations de voitures",
    "sg:phone":"+32 51 50 09 70",
    "sg:postcode":"8600",
    "sg:province":"West-Vlaanderen",
    "wof:name":"Van Houtte",
    "wof:placetype":"venue"
},
  "geometry": {"coordinates":[2.8599998951,51.0340766907],"type":"Point"}
}