{
  "type": "Feature",
  "properties": {
    "iso:country":"BE",
    "sg:address":"Rue Du Comptoir 8",
    "sg:city":"Koekelberg",
    "sg:orig_category":"Services de Nettoyage and de D\u00e9sinfection",
    "sg:phone":"+32 2 414 74 58",
    "sg:postcode":"1081",
    "sg:province":"Bruxelles-Capitale",
    "wof:name":"Vitro-flex",
    "wof:placetype":"venue"
},
  "geometry": {"coordinates":[4.3136291504,50.865032196],"type":"Point"}
}