{
  "type": "Feature",
  "properties": {
    "iso:country":"BE",
    "sg:address":"Neerveldstraat 21",
    "sg:city":"Erpe-mere (erpe)",
    "sg:classifiers":[
        {
            "category":"Real Estate",
            "subcategory":"Architect",
            "type":"Services"
        }
    ],
    "sg:phone":"+32 53 77 03 45",
    "sg:postcode":"9420",
    "sg:province":"Oost-Vlaanderen",
    "wof:name":"Van De Cauter H",
    "wof:placetype":"venue"
},
  "geometry": {"coordinates":[4.0023918152,50.9459342957],"type":"Point"}
}