{
  "type": "Feature",
  "properties": {
    "iso:country":"BE",
    "sg:address":"Rue De L'artisanat 5",
    "sg:city":"Nivelles",
    "sg:classifiers":[
        {
            "category":"Professional",
            "subcategory":"Engineering",
            "type":"Services"
        }
    ],
    "sg:phone":"+32 67 89 47 90",
    "sg:postcode":"1400",
    "sg:province":"Brabant Wallon",
    "sg:tags":[
        "machine",
        "-",
        "mechanical"
    ],
    "wof:name":"Primus Sievert-belgium S.a.",
    "wof:placetype":"venue"
},
  "geometry": {"coordinates":[4.3630142212,50.5974655151],"type":"Point"}
}