{
  "type": "Feature",
  "properties": {
    "iso:country":"BE",
    "sg:address":"Kattelinnestraat 99",
    "sg:city":"Erpe-mere",
    "sg:classifiers":[
        {
            "category":"Insurance",
            "subcategory":"Insurance Agent",
            "type":"Services"
        }
    ],
    "sg:phone":"+32 53 78 66 11",
    "sg:postcode":"9420",
    "sg:province":"Oost-Vlaanderen",
    "sg:tags":[
        "verzekeringsmakelaars",
        "expert"
    ],
    "wof:name":"Parewyck",
    "wof:placetype":"venue"
},
  "geometry": {"coordinates":[3.9979929924,50.9459114075],"type":"Point"}
}