{
  "type": "Feature",
  "properties": {
    "addr:full":"Rue De La Montagne Bte 1 10 - Brussels Bruxelles-Capitale 1000",
    "addr:housenumber":"1 10",
    "addr:postcode":"1000",
    "addr:street":"Rue De La Montagne Bte",
    "iso:country":"BE",
    "sg:address":"Rue De La Montagne Bte 1 10 -",
    "sg:city":"Brussels",
    "sg:classifiers":[
        {
            "category":"Professional",
            "subcategory":"Art Services",
            "type":"Services"
        }
    ],
    "sg:phone":"+32 2 346 18 80",
    "sg:postcode":"1000",
    "sg:province":"Bruxelles-Capitale",
    "sg:tags":[
        "export-import"
    ],
    "wof:name":"Angola Embassy",
    "wof:placetype":"venue"
},
  "geometry": {"coordinates":[4.3612570763,50.8492431641],"type":"Point"}
}