{
  "type": "Feature",
  "properties": {
    "addr:full":"Marktpln 80 St. Lievens Oost-Vlaanderen 9520",
    "addr:housenumber":"80",
    "addr:postcode":"9520",
    "addr:street":"Marktpln",
    "iso:country":"BE",
    "sg:address":"Marktpln 80",
    "sg:city":"St. Lievens",
    "sg:classifiers":[
        {
            "category":"Banks & Credit Unions",
            "subcategory":"Bank",
            "type":"Services"
        }
    ],
    "sg:phone":"+32 53 62 43 96",
    "sg:postcode":"9520",
    "sg:province":"Oost-Vlaanderen",
    "wof:name":"Kredietbank",
    "wof:placetype":"venue"
},
  "geometry": {"coordinates":[3.8672559261,50.9193916321],"type":"Point"}
}