{
  "type": "Feature",
  "properties": {
    "addr:full":"Gentsesteenweg 73 Eeklo Oost-Vlaanderen 9900",
    "addr:housenumber":"73",
    "addr:postcode":"9900",
    "addr:street":"Gentsesteenweg",
    "iso:country":"BE",
    "sg:address":"Gentsesteenweg 73",
    "sg:city":"Eeklo",
    "sg:classifiers":[
        {
            "category":"Autos & Motor Vehicles",
            "subcategory":"Fuel & Gas Station",
            "type":"Retail Goods"
        }
    ],
    "sg:phone":"+32 9 377 42 35",
    "sg:postcode":"9900",
    "sg:province":"Oost-Vlaanderen",
    "sg:tags":[
        "stations-service",
        "carburants"
    ],
    "wof:name":"Jet",
    "wof:placetype":"venue"
},
  "geometry": {"coordinates":[3.5806069374,51.1757240295],"type":"Point"}
}