{
  "type": "Feature",
  "properties": {
    "iso:country":"BE",
    "sg:address":"Oliemolenstraat 36",
    "sg:city":"Brugge",
    "sg:orig_category":"Sportclubs Sportterreinen and installaties behalve sportcentra",
    "sg:phone":"+32 50 36 21 44",
    "sg:postcode":"8310",
    "sg:province":"West-Vlaanderen",
    "wof:name":"V.k. Clark Hurth",
    "wof:placetype":"venue"
},
  "geometry": {"coordinates":[3.2471370697,51.1976165771],"type":"Point"}
}