{
  "type": "Feature",
  "properties": {
    "iso:country":"BE",
    "sg:address":"President Kennedypark 37",
    "sg:city":"Kortrijk",
    "sg:classifiers":[
        {
            "category":"Professional",
            "subcategory":"Lawyer & Legal Services",
            "type":"Services"
        }
    ],
    "sg:phone":"+32 56 26 08 60",
    "sg:postcode":"8500",
    "sg:province":"West-Vlaanderen",
    "wof:name":"Dejonghe Dieter",
    "wof:placetype":"venue"
},
  "geometry": {"coordinates":[3.2745509148,50.7990951538],"type":"Point"}
}