{
  "type": "Feature",
  "properties": {
    "addr:full":"Welleplein 11-13 Denderleeuw (welle) Oost-Vlaanderen 9473",
    "addr:housenumber":"11-13",
    "addr:postcode":"9473",
    "addr:street":"Welleplein",
    "iso:country":"BE",
    "sg:address":"Welleplein 11-13",
    "sg:city":"Denderleeuw (welle)",
    "sg:classifiers":[
        {
            "category":"Personal",
            "subcategory":"Beauty Salon",
            "type":"Services"
        }
    ],
    "sg:phone":"+32 53 68 33 03",
    "sg:postcode":"9473",
    "sg:province":"Oost-Vlaanderen",
    "sg:tags":[
        "lady",
        "-",
        "hairdressing"
    ],
    "wof:name":"Fascino",
    "wof:placetype":"venue"
},
  "geometry": {"coordinates":[4.0544290543,50.8973007202],"type":"Point"}
}