{
  "type": "Feature",
  "properties": {
    "addr:full":"Aux Grands Champs 14 Chaudfontaine Li\u00e8ge 4052",
    "addr:housenumber":"14",
    "addr:postcode":"4052",
    "addr:street":"Aux Grands Champs",
    "iso:country":"BE",
    "sg:address":"Aux Grands Champs 14",
    "sg:city":"Chaudfontaine",
    "sg:orig_category":"Instituts de beaut\u00e9",
    "sg:phone":"+32 4 368 63 35",
    "sg:postcode":"4052",
    "sg:province":"Li\u00e8ge",
    "wof:name":"Cecille D'ans",
    "wof:placetype":"venue"
},
  "geometry": {"coordinates":[5.6276569366,50.5697250366],"type":"Point"}
}