{
  "type": "Feature",
  "properties": {
    "iso:country":"BE",
    "sg:address":"Rue De La Chauss\u00c9e 52",
    "sg:city":"Mons",
    "sg:classifiers":[
        {
            "category":"Cafe",
            "type":"Food & Drink"
        }
    ],
    "sg:phone":"+32 65 31 85 87",
    "sg:postcode":"7000",
    "sg:province":"Hainaut",
    "sg:tags":[
        "caf\u00e9s"
    ],
    "wof:name":"Caf\u00c9 Le Paysan",
    "wof:placetype":"venue"
},
  "geometry": {"coordinates":[3.9506750107,50.4529151917],"type":"Point"}
}