{
  "type": "Feature",
  "properties": {
    "addr:full":"Oude Mechelse Baan 342 Aarschot Vlaams-Brabant 3200",
    "addr:housenumber":"342",
    "addr:postcode":"3200",
    "addr:street":"Oude Mechelse Baan",
    "iso:country":"BE",
    "sg:address":"Oude Mechelse Baan 342",
    "sg:city":"Aarschot",
    "sg:classifiers":[
        {
            "category":"Health Services",
            "subcategory":"Health Practitioner",
            "type":"Services"
        }
    ],
    "sg:phone":"+32 16 56 26 21",
    "sg:postcode":"3200",
    "sg:province":"Vlaams-Brabant",
    "sg:tags":[
        "physiotherapist"
    ],
    "wof:name":"Dehond S",
    "wof:placetype":"venue"
},
  "geometry": {"coordinates":[4.8447799683,51.0093307495],"type":"Point"}
}