{
  "type": "Feature",
  "properties": {
    "addr:full":"Yshoute 23 Oosterzele (balegem) Oost-Vlaanderen 9860",
    "addr:housenumber":"23",
    "addr:postcode":"9860",
    "addr:street":"Yshoute",
    "iso:country":"BE",
    "sg:address":"Yshoute 23",
    "sg:city":"Oosterzele (balegem)",
    "sg:classifiers":[
        {
            "category":"Wholesale",
            "subcategory":"Poultry",
            "type":"Manufacturing & Wholesale Goods"
        }
    ],
    "sg:phone":"+32 9 362 58 75",
    "sg:postcode":"9860",
    "sg:province":"Oost-Vlaanderen",
    "sg:tags":[
        "whol",
        "-",
        "egg"
    ],
    "wof:name":"Steppe M",
    "wof:placetype":"venue"
},
  "geometry": {"coordinates":[3.8267440796,50.928981781],"type":"Point"}
}