{
  "type": "Feature",
  "properties": {
    "addr:full":"Jan Vinckestraat 21 Tielt West-Vlaanderen 8700",
    "addr:housenumber":"21",
    "addr:postcode":"8700",
    "addr:street":"Jan Vinckestraat",
    "iso:country":"BE",
    "sg:address":"Jan Vinckestraat 21",
    "sg:city":"Tielt",
    "sg:orig_category":"V\u00e9t\u00e9rinaires",
    "sg:phone":"+32 51 40 31 16",
    "sg:postcode":"8700",
    "sg:province":"West-Vlaanderen",
    "wof:name":"Christiaan Vandewiele",
    "wof:placetype":"venue"
},
  "geometry": {"coordinates":[3.3316888809,51.033744812],"type":"Point"}
}