{
  "type": "Feature",
  "properties": {
    "iso:country":"BE",
    "sg:address":"Chauss\u00e9e De Hannut 54",
    "sg:city":"Jodoigne",
    "sg:classifiers":[
        {
            "category":"Retail",
            "subcategory":"Auto Repair",
            "type":"Services"
        }
    ],
    "sg:phone":"+32 10 81 25 76",
    "sg:postcode":"1370",
    "sg:province":"Brabant Wallon",
    "sg:tags":[
        "automobile-body"
    ],
    "wof:name":"Gar Fraipont",
    "wof:placetype":"venue"
},
  "geometry": {"coordinates":[4.8814020157,50.7194404602],"type":"Point"}
}