{
  "type": "Feature",
  "properties": {
    "addr:full":"Place De L'universit\u00e9 13 Ottignies-louvain-la-neuve (louvain-la-neuve) Brabant Wallon 1348",
    "addr:housenumber":"13",
    "addr:postcode":"1348",
    "addr:street":"Place De L'Universite \u0301",
    "iso:country":"BE",
    "sg:address":"Place De L'universit\u00e9 13",
    "sg:city":"Ottignies-louvain-la-neuve (louvain-la-neuve)",
    "sg:classifiers":[
        {
            "category":"Retail",
            "subcategory":"Repair Shop",
            "type":"Services"
        }
    ],
    "sg:phone":"+32 10 45 43 00",
    "sg:postcode":"1348",
    "sg:province":"Brabant Wallon",
    "sg:tags":[
        "photographic",
        "equipment",
        "-",
        "accessory"
    ],
    "wof:name":"Photogenie",
    "wof:placetype":"venue"
},
  "geometry": {"coordinates":[4.6150960922,50.6702728271],"type":"Point"}
}