{
  "type": "Feature",
  "properties": {
    "addr:full":"Rue De Bastogne 7 Arlon Luxembourg 6700",
    "addr:housenumber":"7",
    "addr:postcode":"6700",
    "addr:street":"Rue De Bastogne",
    "iso:country":"BE",
    "sg:address":"Rue De Bastogne 7",
    "sg:city":"Arlon",
    "sg:classifiers":[
        {
            "category":"Cafe",
            "type":"Food & Drink"
        }
    ],
    "sg:phone":"+32 63 22 99 09",
    "sg:postcode":"6700",
    "sg:province":"Luxembourg",
    "sg:tags":[
        "snack-bars"
    ],
    "wof:name":"Cocoon Service",
    "wof:placetype":"venue"
},
  "geometry": {"coordinates":[5.810573101,49.6863479614],"type":"Point"}
}