{
  "type": "Feature",
  "properties": {
    "addr:full":"Stationsstraat 46 Houthulst West-Vlaanderen 8650",
    "addr:housenumber":"46",
    "addr:postcode":"8650",
    "addr:street":"Stationsstraat",
    "iso:country":"BE",
    "sg:address":"Stationsstraat 46",
    "sg:city":"Houthulst",
    "sg:orig_category":"Installation \u00e9lectrique r\u00e9sidentielle. Installation \u00e9lectrique industrielle",
    "sg:phone":"+32 51 54 57 67",
    "sg:postcode":"8650",
    "sg:province":"West-Vlaanderen",
    "wof:name":"Wim Dubois",
    "wof:placetype":"venue"
},
  "geometry": {"coordinates":[2.8640420437,50.9564208984],"type":"Point"}
}