{
  "type": "Feature",
  "properties": {
    "addr:full":"Rue Saint-v\u00e9ron 2 Braine-le-ch\u00e2teau Brabant Wallon 1440",
    "addr:housenumber":"2",
    "addr:postcode":"1440",
    "addr:street":"Rue Saint-Ve\u0301Ron",
    "iso:country":"BE",
    "sg:address":"Rue Saint-v\u00e9ron 2",
    "sg:city":"Braine-le-ch\u00e2teau",
    "sg:classifiers":[
        {
            "category":"Bars & Pubs",
            "type":"Food & Drink"
        }
    ],
    "sg:phone":"+32 2 366 96 50",
    "sg:postcode":"1440",
    "sg:province":"Brabant Wallon",
    "sg:tags":[
        "tavern"
    ],
    "wof:name":"Meurisses (les)",
    "wof:placetype":"venue"
},
  "geometry": {"coordinates":[4.2641048431,50.6990852356],"type":"Point"}
}