{
  "type": "Feature",
  "properties": {
    "addr:full":"Rue Des Pr\u00e9montr\u00e9s 40 Li\u00e8ge 1 Li\u00e8ge 4000",
    "addr:housenumber":"40;1",
    "addr:postcode":"4000",
    "addr:street":"Rue Des Pre\u0301Montre\u0301S",
    "iso:country":"BE",
    "sg:address":"Rue Des Pr\u00e9montr\u00e9s 40",
    "sg:city":"Li\u00e8ge 1",
    "sg:classifiers":[
        {
            "category":"Arena",
            "subcategory":"Sports Club",
            "type":"Entertainment"
        }
    ],
    "sg:phone":"+32 4 222 01 30",
    "sg:postcode":"4000",
    "sg:province":"Li\u00e8ge",
    "sg:tags":[
        "martial art",
        "accessory"
    ],
    "wof:name":"Katsujin Ken Dojo",
    "wof:placetype":"venue"
},
  "geometry": {"coordinates":[5.5746431351,50.6373138428],"type":"Point"}
}