{
  "type": "Feature",
  "properties": {
    "addr:full":"Rue Jules Destr\u00c9e 98 Charleroi Hainaut 6043",
    "addr:housenumber":"98",
    "addr:postcode":"6043",
    "addr:street":"Rue Jules Destre\u0301E;Hainaut",
    "iso:country":"BE",
    "sg:address":"Rue Jules Destr\u00c9e 98",
    "sg:city":"Charleroi",
    "sg:orig_category":"Paramedische behandelingen",
    "sg:phone":"+32 71 37 37 04",
    "sg:postcode":"6043",
    "sg:province":"Hainaut",
    "wof:name":"N. Verbanck",
    "wof:placetype":"venue"
},
  "geometry": {"coordinates":[4.4517412186,50.4210090637],"type":"Point"}
}