{
  "type": "Feature",
  "properties": {
    "iso:country":"BE",
    "sg:address":"Dieplaan 35",
    "sg:city":"Genk",
    "sg:orig_category":"Journaux. Tabac",
    "sg:phone":"+32 89 30 64 82",
    "sg:postcode":"3600",
    "sg:province":"Limburg",
    "wof:name":"Huis Actuapress",
    "wof:placetype":"venue"
},
  "geometry": {"coordinates":[5.4944372177,50.9642486572],"type":"Point"}
}