{
  "type": "Feature",
  "properties": {
    "iso:country":"BE",
    "sg:address":"Beaumont 26",
    "sg:city":"Stavelot",
    "sg:orig_category":"Jardinage",
    "sg:phone":"+32 80 86 22 05",
    "sg:postcode":"4970",
    "sg:province":"Li\u00e8ge",
    "wof:name":"Macquet",
    "wof:placetype":"venue"
},
  "geometry": {"coordinates":[5.996732235,50.380657196],"type":"Point"}
}