{
  "type": "Feature",
  "properties": {
    "addr:full":"Dikkebusseweg 151 Ieper West-Vlaanderen 8900",
    "addr:housenumber":"151",
    "addr:postcode":"8900",
    "iso:country":"BE",
    "sg:address":"Dikkebusseweg 151",
    "sg:city":"Ieper",
    "sg:classifiers":[
        {
            "category":"Shopping",
            "subcategory":"Florist",
            "type":"Retail Goods"
        }
    ],
    "sg:phone":"+32 495 90 48 81",
    "sg:postcode":"8900",
    "sg:province":"West-Vlaanderen",
    "wof:name":"Artistic",
    "wof:placetype":"venue"
},
  "geometry": {"coordinates":[2.87104702,50.8412132263],"type":"Point"}
}