{
  "type": "Feature",
  "properties": {
    "iso:country":"BE",
    "sg:address":"Molenstraat 20",
    "sg:city":"Kortenaken (waanrode)",
    "sg:classifiers":[
        {
            "category":"Insurance",
            "subcategory":"Insurance Agent",
            "type":"Services"
        }
    ],
    "sg:phone":"+32 16 77 83 31",
    "sg:postcode":"3473",
    "sg:province":"Vlaams-Brabant",
    "sg:tags":[
        "broker"
    ],
    "wof:name":"Vanhemelen W",
    "wof:placetype":"venue"
},
  "geometry": {"coordinates":[5.0090107918,50.9186134338],"type":"Point"}
}