{
  "type": "Feature",
  "properties": {
    "addr:full":"Elsense Steenweg 303 Elsene Bruxelles-Capitale 1050",
    "addr:housenumber":"303",
    "addr:postcode":"1050",
    "addr:street":"Elsense Steenweg",
    "iso:country":"BE",
    "sg:address":"Elsense Steenweg 303",
    "sg:city":"Elsene",
    "sg:orig_category":"Huisdieren and benodigdheden Royal Canin",
    "sg:phone":"+32 2 648 52 75",
    "sg:postcode":"1050",
    "sg:province":"Bruxelles-Capitale",
    "wof:name":"M Ramaekers",
    "wof:placetype":"venue"
},
  "geometry": {"coordinates":[4.369699955,50.8295631409],"type":"Point"}
}