{
  "type": "Feature",
  "properties": {
    "addr:full":"Rollegemstraat 180 Ledegem West-Vlaanderen 8880",
    "addr:housenumber":"180",
    "addr:postcode":"8880",
    "addr:street":"Rollegemstraat",
    "iso:country":"BE",
    "sg:address":"Rollegemstraat 180",
    "sg:city":"Ledegem",
    "sg:classifiers":[
        {
            "category":"Personal",
            "subcategory":"Beauty Salon",
            "type":"Services"
        }
    ],
    "sg:phone":"+32 56 50 10 00",
    "sg:postcode":"8880",
    "sg:province":"West-Vlaanderen",
    "wof:name":"Iris",
    "wof:placetype":"venue"
},
  "geometry": {"coordinates":[3.1376729012,50.8627967834],"type":"Point"}
}