{
  "type": "Feature",
  "properties": {
    "iso:country":"BE",
    "sg:address":"Belgi\u00cblaan 58",
    "sg:city":"Herentals",
    "sg:orig_category":"Dranken",
    "sg:phone":"+32 14 22 28 14",
    "sg:postcode":"2200",
    "sg:province":"Antwerpen",
    "wof:name":"Geudens",
    "wof:placetype":"venue"
},
  "geometry": {"coordinates":[4.831384182,51.1816596985],"type":"Point"}
}