{
  "type": "Feature",
  "properties": {
    "addr:full":"Belgi\u00cblaan 58 Herentals Antwerpen 2200",
    "addr:housenumber":"58",
    "addr:postcode":"2200",
    "addr:street":"Belgie\u0308Laan",
    "iso:country":"BE",
    "sg:address":"Belgi\u00cblaan 58",
    "sg:city":"Herentals",
    "sg:orig_category":"Dranken",
    "sg:phone":"+32 14 22 28 14",
    "sg:postcode":"2200",
    "sg:province":"Antwerpen",
    "wof:name":"Geudens",
    "wof:placetype":"venue"
},
  "geometry": {"coordinates":[4.831384182,51.1816596985],"type":"Point"}
}