{
  "type": "Feature",
  "properties": {
    "iso:country":"BE",
    "sg:address":"Brumierstraat 6",
    "sg:city":"Kortrijk",
    "sg:orig_category":"Forge, Moulage and Profilage des M\u00e9taux. Artistes ind\u00e9pendants",
    "sg:phone":"+32 56 41 96 73",
    "sg:postcode":"8511",
    "sg:province":"West-Vlaanderen",
    "wof:name":"Alexis Vanneste",
    "wof:placetype":"venue"
},
  "geometry": {"coordinates":[3.2115960121,50.7735443115],"type":"Point"}
}