{
  "type": "Feature",
  "properties": {
    "iso:country":"BE",
    "sg:address":"Place De Liberchies 94",
    "sg:city":"Pont-\u00e0-celles (luttre)",
    "sg:classifiers":[
        {
            "category":"Health Services",
            "subcategory":"Health Practitioner",
            "type":"Services"
        }
    ],
    "sg:phone":"+32 71 84 58 77",
    "sg:postcode":"6238",
    "sg:province":"Hainaut",
    "sg:tags":[
        "physiotherapist"
    ],
    "wof:name":"Godfraind L",
    "wof:placetype":"venue"
},
  "geometry": {"coordinates":[4.4036688805,50.5129508972],"type":"Point"}
}