{
  "type": "Feature",
  "properties": {
    "iso:country":"BE",
    "sg:address":"Ferme De La Choquen\u00c9e 33",
    "sg:city":"Ciney",
    "sg:orig_category":"Rundveehouders",
    "sg:phone":"+32 83 21 12 10",
    "sg:postcode":"5590",
    "sg:province":"Namur",
    "wof:name":"Jean-luc Lissoir",
    "wof:placetype":"venue"
},
  "geometry": {"coordinates":[5.1022520065,50.297088623],"type":"Point"}
}