{
  "type": "Feature",
  "properties": {
    "iso:country":"BE",
    "sg:address":"Lange Vesting 40",
    "sg:city":"Brugge",
    "sg:classifiers":[
        {
            "category":"Banks & Credit Unions",
            "subcategory":"Investment Brokerage",
            "type":"Services"
        }
    ],
    "sg:phone":"+32 50 31 56 04",
    "sg:postcode":"8200",
    "sg:province":"West-Vlaanderen",
    "sg:tags":[
        "pension"
    ],
    "wof:name":"Martens",
    "wof:placetype":"venue"
},
  "geometry": {"coordinates":[3.2106750011,51.2057228088],"type":"Point"}
}