{
  "type": "Feature",
  "properties": {
    "addr:full":"R Du Ban 69 Florennes (hanzinne) Namur 5621",
    "addr:housenumber":"69",
    "addr:postcode":"5621",
    "addr:street":"R Du Ban",
    "iso:country":"BE",
    "sg:address":"R Du Ban 69",
    "sg:city":"Florennes (hanzinne)",
    "sg:classifiers":[
        {
            "category":"Retail",
            "subcategory":"Auto Repair",
            "type":"Services"
        }
    ],
    "sg:phone":"+32 71 50 15 02",
    "sg:postcode":"5621",
    "sg:province":"Namur",
    "sg:tags":[
        "automobile",
        "servic",
        "electrical",
        "-"
    ],
    "wof:name":"Gonthier P",
    "wof:placetype":"venue"
},
  "geometry": {"coordinates":[4.5549921989,50.3148193359],"type":"Point"}
}