{
  "type": "Feature",
  "properties": {
    "iso:country":"BE",
    "sg:address":"Goudbloemlaan 31",
    "sg:city":"Zoersel (halle)",
    "sg:classifiers":[
        {
            "category":"Communications",
            "subcategory":"Film & Video Production",
            "type":"Services"
        }
    ],
    "sg:phone":"+32 3 281 40 77",
    "sg:postcode":"2980",
    "sg:province":"Antwerpen",
    "sg:tags":[
        "sound",
        "recording",
        "studio"
    ],
    "wof:name":"Spotlight Reclame",
    "wof:placetype":"venue"
},
  "geometry": {"coordinates":[4.713435173,51.269985199],"type":"Point"}
}