{
  "type": "Feature",
  "properties": {
    "iso:country":"BE",
    "sg:address":"Rue De Frelinghien 13",
    "sg:city":"Komen-waasten/comines-warneton",
    "sg:orig_category":"Eleveurs de bovins. Eleveurs and marchands de porcs",
    "sg:phone":"+32 56 58 88 40",
    "sg:postcode":"7784",
    "sg:province":"Hainaut",
    "wof:name":"Willy Carbon",
    "wof:placetype":"venue"
},
  "geometry": {"coordinates":[2.9182379246,50.7220497131],"type":"Point"}
}