{
  "type": "Feature",
  "properties": {
    "iso:country":"BE",
    "sg:address":"Kustlaan 89c",
    "sg:city":"Knokke-heist (knokke)",
    "sg:classifiers":[
        {
            "category":"Shopping",
            "subcategory":"Jewelry",
            "type":"Retail Goods"
        }
    ],
    "sg:phone":"+32 50 61 08 63",
    "sg:postcode":"8300",
    "sg:province":"West-Vlaanderen",
    "sg:tags":[
        "jeweller",
        "-"
    ],
    "wof:name":"Verbruggen Oro-gem Nv",
    "wof:placetype":"venue"
},
  "geometry": {"coordinates":[3.287694931,51.3467254639],"type":"Point"}
}