{
  "type": "Feature",
  "properties": {
    "iso:country":"BE",
    "sg:address":"Rue Sur Le Bois 45",
    "sg:city":"Vise",
    "sg:classifiers":[
        {
            "category":"Restaurant",
            "type":"Food & Drink"
        }
    ],
    "sg:phone":"+32 4 379 35 21",
    "sg:postcode":"4601",
    "sg:province":"Li\u00e8ge",
    "wof:name":"Au Capuccino",
    "wof:placetype":"venue"
},
  "geometry": {"coordinates":[5.6819438934,50.6991271973],"type":"Point"}
}