{
  "type": "Feature",
  "properties": {
    "addr:full":"Chauss\u00c9e De Beaumont 194 Mons Hainaut 7032",
    "addr:housenumber":"194",
    "addr:postcode":"7032",
    "addr:street":"Chausse\u0301E De Beaumont;Hainaut",
    "iso:country":"BE",
    "sg:address":"Chauss\u00c9e De Beaumont 194",
    "sg:city":"Mons",
    "sg:orig_category":"Catering and organisatie van feesten Fast food and meeneem restaurants Krantenwinkels Levering aan h",
    "sg:phone":"+32 65 35 46 70",
    "sg:postcode":"7032",
    "sg:province":"Hainaut",
    "wof:name":"Taverne De La Barri\u00c8re",
    "wof:placetype":"venue"
},
  "geometry": {"coordinates":[3.9869709015,50.4255142212],"type":"Point"}
}