{
  "type": "Feature",
  "properties": {
    "addr:full":"Vliekaertstraat 3a Lichtervelde West-Vlaanderen 8810",
    "addr:housenumber":"3a",
    "addr:postcode":"8810",
    "addr:street":"Vliekaertstraat",
    "iso:country":"BE",
    "sg:address":"Vliekaertstraat 3a",
    "sg:city":"Lichtervelde",
    "sg:classifiers":[
        {
            "category":"Sports & Exercise",
            "subcategory":"Skate Park",
            "type":"Entertainment"
        }
    ],
    "sg:phone":"+32 51 74 66 56",
    "sg:postcode":"8810",
    "sg:province":"West-Vlaanderen",
    "sg:tags":[
        "mushroom"
    ],
    "wof:name":"Gryp F",
    "wof:placetype":"venue"
},
  "geometry": {"coordinates":[3.1580739021,50.997089386],"type":"Point"}
}