{
  "type": "Feature",
  "properties": {
    "iso:country":"BE",
    "sg:address":"Rue Prince-de-li\u00c8ge 88",
    "sg:city":"Li\u00c8ge",
    "sg:orig_category":"Electrom\u00e9nager, t\u00e9l\u00e9visions and radios. R\u00e9parations d'appareils \u00e9lectrom\u00e9nagers",
    "sg:phone":"+32 4 367 11 78",
    "sg:postcode":"4030",
    "sg:province":"Li\u00e8ge",
    "wof:name":"Multi Services M\u00c9nagers",
    "wof:placetype":"venue"
},
  "geometry": {"coordinates":[5.6178121567,50.6432876587],"type":"Point"}
}