{
  "type": "Feature",
  "properties": {
    "addr:full":"R De Brabant 202 Bruxelles Bruxelles-Capitale 1030",
    "addr:housenumber":"202",
    "addr:postcode":"1030",
    "iso:country":"BE",
    "sg:address":"R De Brabant 202",
    "sg:city":"Bruxelles",
    "sg:classifiers":[
        {
            "category":"Manufacturing",
            "subcategory":"Textiles",
            "type":"Manufacturing & Wholesale Goods"
        }
    ],
    "sg:phone":"+32 2 219 87 37",
    "sg:postcode":"1030",
    "sg:province":"Bruxelles-Capitale",
    "sg:tags":[
        "clothing",
        "accessory"
    ],
    "wof:name":"Heurotex Sa",
    "wof:placetype":"venue"
},
  "geometry": {"coordinates":[4.364677906,50.861618042],"type":"Point"}
}