{
  "type": "Feature",
  "properties": {
    "iso:country":"BE",
    "sg:address":"Oude Bruggestraat 75-77",
    "sg:city":"Wingene",
    "sg:classifiers":[
        {
            "category":"Shopping",
            "subcategory":"Gifts & Souvenirs",
            "type":"Retail Goods"
        }
    ],
    "sg:postcode":"8750",
    "sg:province":"West-Vlaanderen",
    "sg:tags":[
        "-"
    ],
    "wof:name":"B & S Import",
    "wof:placetype":"venue"
},
  "geometry": {"coordinates":[3.2718129158,51.0578193665],"type":"Point"}
}