{
  "type": "Feature",
  "properties": {
    "addr:full":"Rue Fond De Bologne 6 Ohey Namur 5350",
    "addr:housenumber":"6",
    "addr:postcode":"5350",
    "addr:street":"Rue Fond De Bologne",
    "iso:country":"BE",
    "sg:address":"Rue Fond De Bologne 6",
    "sg:city":"Ohey",
    "sg:orig_category":"Charpentes and couvertures",
    "sg:phone":"+32 85 61 22 13",
    "sg:postcode":"5350",
    "sg:province":"Namur",
    "wof:name":"Christian Abraham",
    "wof:placetype":"venue"
},
  "geometry": {"coordinates":[5.1304078102,50.4410743713],"type":"Point"}
}