{
  "type": "Feature",
  "properties": {
    "iso:country":"BE",
    "sg:address":"Waterhoenlaan 22",
    "sg:city":"Antwerpen",
    "sg:orig_category":"Services fun\u00e9raires",
    "sg:phone":"+32 3 219 04 04",
    "sg:postcode":"2050",
    "sg:province":"Antwerpen",
    "wof:name":"Begrafenissen Van Bogaert",
    "wof:placetype":"venue"
},
  "geometry": {"coordinates":[4.382130146,51.2194099426],"type":"Point"}
}