{
  "type": "Feature",
  "properties": {
    "addr:full":"Dorpstraat 125 Wuustwezel Antwerpen 2990",
    "addr:housenumber":"125",
    "addr:postcode":"2990",
    "addr:street":"Dorpstraat",
    "iso:country":"BE",
    "sg:address":"Dorpstraat 125",
    "sg:city":"Wuustwezel",
    "sg:orig_category":"Animaux domestiques and accessoires",
    "sg:phone":"+32 3 669 51 13",
    "sg:postcode":"2990",
    "sg:province":"Antwerpen",
    "wof:name":"De Meulen",
    "wof:placetype":"venue"
},
  "geometry": {"coordinates":[4.5991101265,51.3892059326],"type":"Point"}
}