{
  "type": "Feature",
  "properties": {
    "iso:country":"BE",
    "sg:address":"Rue Des Bedennes 257 Box 1",
    "sg:city":"Li\u00e8ge 1 (ch\u00ean\u00e9e)",
    "sg:classifiers":[
        {
            "category":"Retail",
            "subcategory":"Auto Repair",
            "type":"Services"
        }
    ],
    "sg:phone":"+32 476 30 02 64",
    "sg:postcode":"4032",
    "sg:province":"Li\u00e8ge",
    "sg:tags":[
        "automobile",
        "servic",
        "electrical",
        "-"
    ],
    "wof:name":"Acting-out",
    "wof:placetype":"venue"
},
  "geometry": {"coordinates":[5.6155872345,50.6185913086],"type":"Point"}
}