{
  "type": "Feature",
  "properties": {
    "addr:full":"Herkkantstraat 58 Hasselt Limburg 3512",
    "addr:housenumber":"58",
    "addr:postcode":"3512",
    "addr:street":"Herkkantstraat",
    "iso:country":"BE",
    "sg:address":"Herkkantstraat 58",
    "sg:city":"Hasselt",
    "sg:classifiers":[
        {
            "category":"Restaurant",
            "type":"Food & Drink"
        }
    ],
    "sg:phone":"+32 11 31 30 91",
    "sg:postcode":"3512",
    "sg:province":"Limburg",
    "wof:name":"Restaurant Elsartmolen",
    "wof:placetype":"venue"
},
  "geometry": {"coordinates":[5.2296757698,50.9223976135],"type":"Point"}
}