{
  "type": "Feature",
  "properties": {
    "addr:full":"Rue Hilaire Parmentier 71 Braine-le-ch\u00e2teau (wauthier-braine) Brabant Wallon 1440",
    "addr:housenumber":"71",
    "addr:postcode":"1440",
    "addr:street":"Rue Hilaire Parmentier",
    "iso:country":"BE",
    "sg:address":"Rue Hilaire Parmentier 71",
    "sg:city":"Braine-le-ch\u00e2teau (wauthier-braine)",
    "sg:classifiers":[
        {
            "category":"Building & Trades",
            "subcategory":"Construction",
            "type":"Services"
        }
    ],
    "sg:phone":"+32 2 366 02 57",
    "sg:postcode":"1440",
    "sg:province":"Brabant Wallon",
    "sg:tags":[
        "carpenter"
    ],
    "wof:name":"J & V Vanesbeck Consultant Ets",
    "wof:placetype":"venue"
},
  "geometry": {"coordinates":[4.3036150932,50.6923217773],"type":"Point"}
}