{
  "type": "Feature",
  "properties": {
    "addr:full":"Blaesstraat 31 Brussel/bruxelles Bruxelles-Capitale 1000",
    "addr:housenumber":"31",
    "addr:postcode":"1000",
    "addr:street":"Blaesstraat;/",
    "iso:country":"BE",
    "sg:address":"Blaesstraat 31",
    "sg:city":"Brussel/bruxelles",
    "sg:orig_category":"Antiek",
    "sg:phone":"+32 2 513 69 82",
    "sg:postcode":"1000",
    "sg:province":"Bruxelles-Capitale",
    "wof:name":"Marie Francois",
    "wof:placetype":"venue"
},
  "geometry": {"coordinates":[4.3500227928,50.8404388428],"type":"Point"}
}