{
  "type": "Feature",
  "properties": {
    "addr:full":"Boomsesteenweg 109 Willebroek Antwerpen 2830",
    "addr:housenumber":"109",
    "addr:postcode":"2830",
    "addr:street":"Boomsesteenweg",
    "iso:country":"BE",
    "sg:address":"Boomsesteenweg 109",
    "sg:city":"Willebroek",
    "sg:classifiers":[
        {
            "category":"Home & Garden",
            "subcategory":"Garden Supply",
            "type":"Retail Goods"
        }
    ],
    "sg:phone":"+32 3 886 61 60",
    "sg:postcode":"2830",
    "sg:province":"Antwerpen",
    "sg:tags":[
        "wood"
    ],
    "wof:name":"De Roover Gustaaf Houthandel Nv",
    "wof:placetype":"venue"
},
  "geometry": {"coordinates":[4.3606300354,51.0722007751],"type":"Point"}
}