{
  "type": "Feature",
  "properties": {
    "addr:full":"Rue Des Masures 2 Binche Hainaut 7130",
    "addr:housenumber":"2",
    "addr:postcode":"7130",
    "addr:street":"Rue Des Masures",
    "iso:country":"BE",
    "sg:address":"Rue Des Masures 2",
    "sg:city":"Binche",
    "sg:orig_category":"Krantenuitgeverijen Tijdschriftenuitgeverijen",
    "sg:phone":"+32 64 33 87 69",
    "sg:postcode":"7130",
    "sg:province":"Hainaut",
    "wof:name":"Editions Le Frontalier",
    "wof:placetype":"venue"
},
  "geometry": {"coordinates":[4.1640138626,50.4100646973],"type":"Point"}
}