{
  "type": "Feature",
  "properties": {
    "addr:full":"Ouwegemsesteenweg 64 Zingem Oost-Vlaanderen 9750",
    "addr:housenumber":"64",
    "addr:postcode":"9750",
    "addr:street":"Ouwegemsesteenweg",
    "iso:country":"BE",
    "sg:address":"Ouwegemsesteenweg 64",
    "sg:city":"Zingem",
    "sg:orig_category":"Pleisterwerk",
    "sg:phone":"+32 9 384 99 09",
    "sg:postcode":"9750",
    "sg:province":"Oost-Vlaanderen",
    "wof:name":"Casa Verde",
    "wof:placetype":"venue"
},
  "geometry": {"coordinates":[3.6115300655,50.9101982117],"type":"Point"}
}