{
  "type": "Feature",
  "properties": {
    "iso:country":"BE",
    "sg:address":"Larum 21",
    "sg:city":"Geel",
    "sg:classifiers":[
        {
            "category":"Food & Beverages",
            "subcategory":"Fruits & Vegetables",
            "type":"Retail Goods"
        }
    ],
    "sg:phone":"+32 14 59 48 90",
    "sg:postcode":"2440",
    "sg:province":"Antwerpen",
    "sg:tags":[
        "-"
    ],
    "wof:name":"Fruitboom (de)",
    "wof:placetype":"venue"
},
  "geometry": {"coordinates":[4.9707651138,51.1648902893],"type":"Point"}
}