{
  "type": "Feature",
  "properties": {
    "addr:full":"Avenue Emile Herman 174 Manage (fayt-lez-manage) Hainaut 7170",
    "addr:housenumber":"174",
    "addr:postcode":"7170",
    "addr:street":"Avenue Emile Herman",
    "iso:country":"BE",
    "sg:address":"Avenue Emile Herman 174",
    "sg:city":"Manage (fayt-lez-manage)",
    "sg:classifiers":[
        {
            "category":"Health Services",
            "subcategory":"Health Practitioner",
            "type":"Services"
        }
    ],
    "sg:phone":"+32 64 55 68 31",
    "sg:postcode":"7170",
    "sg:province":"Hainaut",
    "sg:tags":[
        "physiotherapist"
    ],
    "wof:name":"Francq Stephane",
    "wof:placetype":"venue"
},
  "geometry": {"coordinates":[4.2276668549,50.4864196777],"type":"Point"}
}