{
  "type": "Feature",
  "properties": {
    "addr:full":"Cit\u00c9-du-centenaire 249 Tellin Luxembourg 6927",
    "addr:housenumber":"249",
    "addr:postcode":"6927",
    "iso:country":"BE",
    "sg:address":"Cit\u00c9-du-centenaire 249",
    "sg:city":"Tellin",
    "sg:orig_category":"Installation de menuiserie en bois and plastique",
    "sg:phone":"+32 84 36 69 26",
    "sg:postcode":"6927",
    "sg:province":"Luxembourg",
    "wof:name":"Gerard Volvert",
    "wof:placetype":"venue"
},
  "geometry": {"coordinates":[5.2151322365,50.0874099731],"type":"Point"}
}