{
  "type": "Feature",
  "properties": {
    "iso:country":"BE",
    "sg:address":"Rue Schirmeyer 25",
    "sg:city":"Thuin",
    "sg:orig_category":"Peinture. Rev\u00eatements pour sols and murs",
    "sg:phone":"+32 71 51 65 37",
    "sg:postcode":"6534",
    "sg:province":"Hainaut",
    "wof:name":"Renova",
    "wof:placetype":"venue"
},
  "geometry": {"coordinates":[4.3506340981,50.3325042725],"type":"Point"}
}