{
  "type": "Feature",
  "properties": {
    "addr:full":"Rue De La Tulipe 67 Elsene/ixelles Bruxelles-Capitale 1050",
    "addr:housenumber":"67",
    "addr:postcode":"1050",
    "addr:street":"Rue De La Tulipe",
    "iso:country":"BE",
    "sg:address":"Rue De La Tulipe 67",
    "sg:city":"Elsene/ixelles",
    "sg:classifiers":[
        {
            "category":"Personal",
            "subcategory":"Beauty Salon",
            "type":"Services"
        }
    ],
    "sg:phone":"+32 2 513 20 29",
    "sg:postcode":"1050",
    "sg:province":"Bruxelles-Capitale",
    "sg:tags":[
        "de",
        "coiffure"
    ],
    "wof:name":"Mario Lupoli",
    "wof:placetype":"venue"
},
  "geometry": {"coordinates":[4.3682990074,50.8359184265],"type":"Point"}
}