{
  "type": "Feature",
  "properties": {
    "iso:country":"BE",
    "sg:address":"Rue Gande 29",
    "sg:city":"Dinant",
    "sg:orig_category":"Kansspelen",
    "sg:phone":"+32 82 69 99 94",
    "sg:postcode":"5500",
    "sg:province":"Namur",
    "wof:name":"Casino Dinantais",
    "wof:placetype":"venue"
},
  "geometry": {"coordinates":[4.9154100418,50.2569198608],"type":"Point"}
}