{
  "type": "Feature",
  "properties": {
    "addr:full":"Avenue Delleur 20 Bruxelles (watermael-boitsfort) Bruxelles-Capitale 1170",
    "addr:housenumber":"20",
    "addr:postcode":"1170",
    "addr:street":"Avenue Delleur",
    "iso:country":"BE",
    "sg:address":"Avenue Delleur 20",
    "sg:city":"Bruxelles (watermael-boitsfort)",
    "sg:classifiers":[
        {
            "category":"Health Services",
            "subcategory":"Doctor",
            "type":"Services"
        }
    ],
    "sg:phone":"+32 2 673 21 21",
    "sg:postcode":"1170",
    "sg:province":"Bruxelles-Capitale",
    "sg:tags":[
        "medicinephysicians",
        "surgeon"
    ],
    "wof:name":"Mainguet Paul",
    "wof:placetype":"venue"
},
  "geometry": {"coordinates":[4.4090199471,50.7952384949],"type":"Point"}
}