{
  "type": "Feature",
  "properties": {
    "addr:full":"Tieltstraat 26 Pittem West-Vlaanderen 8740",
    "addr:housenumber":"26",
    "addr:postcode":"8740",
    "addr:street":"Tieltstraat",
    "iso:country":"BE",
    "sg:address":"Tieltstraat 26",
    "sg:city":"Pittem",
    "sg:orig_category":"Banken and kredietinstellingen",
    "sg:phone":"+32 51 46 65 37",
    "sg:postcode":"8740",
    "sg:province":"West-Vlaanderen",
    "wof:name":"Kbc",
    "wof:placetype":"venue"
},
  "geometry": {"coordinates":[3.2647340298,50.9931221008],"type":"Point"}
}