{
  "type": "Feature",
  "properties": {
    "addr:full":"August Nobelsstraat 19 Box 4 Sint-niklaas Oost-Vlaanderen 9100",
    "addr:housenumber":"19;4",
    "addr:postcode":"9100",
    "addr:street":"Nobelsstraat;Box",
    "iso:country":"BE",
    "sg:address":"August Nobelsstraat 19 Box 4",
    "sg:city":"Sint-niklaas",
    "sg:classifiers":[
        {
            "category":"Transit Center",
            "subcategory":"Freight",
            "type":"Transportation"
        }
    ],
    "sg:phone":"+32 3 776 10 01",
    "sg:postcode":"9100",
    "sg:province":"Oost-Vlaanderen",
    "sg:tags":[
        "import",
        "export",
        "-"
    ],
    "wof:name":"Lok H",
    "wof:placetype":"venue"
},
  "geometry": {"coordinates":[4.1455478668,51.1603012085],"type":"Point"}
}