{
  "type": "Feature",
  "properties": {
    "iso:country":"BE",
    "sg:address":"Poortakkerstraat 94",
    "sg:city":"Gent (sint-denijs-westrem - Afsnee)",
    "sg:classifiers":[
        {
            "category":"Health Services",
            "subcategory":"Hospital",
            "type":"Services"
        }
    ],
    "sg:phone":"+32 9 243 40 10",
    "sg:postcode":"9051",
    "sg:province":"Oost-Vlaanderen",
    "wof:name":"Iid Vzw",
    "wof:placetype":"venue"
},
  "geometry": {"coordinates":[3.6683819294,51.020690918],"type":"Point"}
}