{
  "type": "Feature",
  "properties": {
    "addr:full":"Diestsesteenweg 400 Aarschot Vlaams-Brabant 3202",
    "addr:housenumber":"400",
    "addr:postcode":"3202",
    "addr:street":"Diestsesteenweg",
    "iso:country":"BE",
    "sg:address":"Diestsesteenweg 400",
    "sg:city":"Aarschot",
    "sg:orig_category":"Banques and organismes de cr\u00e9dit",
    "sg:phone":"+32 16 50 12 01",
    "sg:postcode":"3202",
    "sg:province":"Vlaams-Brabant",
    "wof:name":"Bacob",
    "wof:placetype":"venue"
},
  "geometry": {"coordinates":[4.8958711624,50.9742164612],"type":"Point"}
}