{
  "type": "Feature",
  "properties": {
    "iso:country":"BE",
    "sg:address":"Rue Traverse 7",
    "sg:city":"Trois-ponts",
    "sg:orig_category":"Kinderopvang",
    "sg:phone":"+32 80 68 41 36",
    "sg:postcode":"4980",
    "sg:province":"Li\u00e8ge",
    "wof:name":"Les Petits Pas",
    "wof:placetype":"venue"
},
  "geometry": {"coordinates":[5.8690700531,50.3723716736],"type":"Point"}
}