{
  "type": "Feature",
  "properties": {
    "iso:country":"BE",
    "sg:address":"Oosteinde 41bb",
    "sg:city":"Lochristi",
    "sg:orig_category":"Alternatieve geneeskunde",
    "sg:phone":"+32 9 356 75 54",
    "sg:postcode":"9080",
    "sg:province":"Oost-Vlaanderen",
    "wof:name":"S. Carlier",
    "wof:placetype":"venue"
},
  "geometry": {"coordinates":[3.8675129414,51.1344070435],"type":"Point"}
}