{
  "type": "Feature",
  "properties": {
    "iso:country":"BE",
    "sg:address":"Paquaylaan 184",
    "sg:city":"Heusden-zolder",
    "sg:classifiers":[
        {
            "category":"Professional",
            "subcategory":"Computer Services",
            "type":"Services"
        }
    ],
    "sg:phone":"+32 11 57 11 28",
    "sg:postcode":"3550",
    "sg:province":"Limburg",
    "sg:tags":[
        "administration",
        "software"
    ],
    "wof:name":"Fidro Informatica Nv",
    "wof:placetype":"venue"
},
  "geometry": {"coordinates":[5.3139648438,51.0231018066],"type":"Point"}
}