{
  "type": "Feature",
  "properties": {
    "addr:full":"Paul Van Tieghemlaan 27a Gent (mariakerke) Oost-Vlaanderen 9030",
    "addr:housenumber":"27a",
    "addr:postcode":"9030",
    "addr:street":"Paul;Tieghemlaan",
    "iso:country":"BE",
    "sg:address":"Paul Van Tieghemlaan 27a",
    "sg:city":"Gent (mariakerke)",
    "sg:classifiers":[
        {
            "category":"Professional",
            "subcategory":"Art Services",
            "type":"Services"
        }
    ],
    "sg:phone":"+32 9 226 26 29",
    "sg:postcode":"9030",
    "sg:province":"Oost-Vlaanderen",
    "sg:tags":[
        "sculptor"
    ],
    "wof:name":"Walgraeve M",
    "wof:placetype":"venue"
},
  "geometry": {"coordinates":[3.6814699173,51.0774383545],"type":"Point"}
}