{
  "type": "Feature",
  "properties": {
    "iso:country":"BE",
    "sg:address":"Rue La Haie-le-comte 43",
    "sg:city":"Namur",
    "sg:orig_category":"Loodgieterij, verwarming and sanitaire installaties",
    "sg:phone":"+32 81 73 49 49",
    "sg:postcode":"5001",
    "sg:province":"Namur",
    "wof:name":"Dubasin Francis",
    "wof:placetype":"venue"
},
  "geometry": {"coordinates":[4.8257050514,50.4722557068],"type":"Point"}
}