{
  "type": "Feature",
  "properties": {
    "addr:full":"Rue Saint-norbert 12 Jette/jette Bruxelles-Capitale 1090",
    "addr:housenumber":"12",
    "addr:postcode":"1090",
    "addr:street":"Rue Saint-Norbert",
    "iso:country":"BE",
    "sg:address":"Rue Saint-norbert 12",
    "sg:city":"Jette/jette",
    "sg:orig_category":"Experts-comptables",
    "sg:phone":"+32 2 479 16 63",
    "sg:postcode":"1090",
    "sg:province":"Bruxelles-Capitale",
    "wof:name":"Gustave De Jonghe",
    "wof:placetype":"venue"
},
  "geometry": {"coordinates":[4.3364310265,50.8821792603],"type":"Point"}
}