{
  "type": "Feature",
  "properties": {
    "iso:country":"BE",
    "sg:address":"Rupsenstraat 16",
    "sg:city":"Wingene (zwevezele)",
    "sg:classifiers":[
        {
            "category":"Manufacturing",
            "subcategory":"Building Materials",
            "type":"Manufacturing & Wholesale Goods"
        }
    ],
    "sg:postcode":"8750",
    "sg:province":"West-Vlaanderen",
    "sg:tags":[
        "fixture",
        "store"
    ],
    "wof:name":"Loomans Bouwbedrijf Bv",
    "wof:placetype":"venue"
},
  "geometry": {"coordinates":[5.4179439545,51.4804763794],"type":"Point"}
}