{
  "type": "Feature",
  "properties": {
    "addr:full":"Rue De Morialm\u00c9 6 Mettet Namur 5640",
    "addr:housenumber":"6",
    "addr:postcode":"5640",
    "addr:street":"Rue De Morialme\u0301",
    "iso:country":"BE",
    "sg:address":"Rue De Morialm\u00c9 6",
    "sg:city":"Mettet",
    "sg:orig_category":"Metaalafval, schrootrecyclage and sloperijen",
    "sg:phone":"+32 71 68 99 68",
    "sg:postcode":"5640",
    "sg:province":"Namur",
    "wof:name":"Serge Vandenberghe",
    "wof:placetype":"venue"
},
  "geometry": {"coordinates":[4.6230301857,50.2966308594],"type":"Point"}
}