{
  "type": "Feature",
  "properties": {
    "iso:country":"BE",
    "sg:address":"Eikstraat 109",
    "sg:city":"Gent",
    "sg:orig_category":"Journaux. Tabac",
    "sg:phone":"+32 9 251 28 27",
    "sg:postcode":"9041",
    "sg:province":"Oost-Vlaanderen",
    "wof:name":"M. De Mey",
    "wof:placetype":"venue"
},
  "geometry": {"coordinates":[3.7651240826,51.0888977051],"type":"Point"}
}