{
  "type": "Feature",
  "properties": {
    "iso:country":"BE",
    "sg:address":"Steenhoevestraat 6",
    "sg:city":"Mechelen",
    "sg:orig_category":"Elektrische installaties voor woningen",
    "sg:phone":"+32 15 28 72 00",
    "sg:postcode":"2800",
    "sg:province":"Antwerpen",
    "wof:name":"Checkpoint Systems",
    "wof:placetype":"venue"
},
  "geometry": {"coordinates":[4.4441962242,51.0494155884],"type":"Point"}
}