{
  "type": "Feature",
  "properties": {
    "addr:full":"Baalsesteenweg 12 Begijnendijk Vlaams-Brabant 3130",
    "addr:housenumber":"12",
    "addr:postcode":"3130",
    "addr:street":"Baalsesteenweg",
    "iso:country":"BE",
    "sg:address":"Baalsesteenweg 12",
    "sg:city":"Begijnendijk",
    "sg:classifiers":[
        {
            "category":"Food & Beverages",
            "subcategory":"Supermarket",
            "type":"Retail Goods"
        }
    ],
    "sg:phone":"+32 16 53 06 46",
    "sg:postcode":"3130",
    "sg:province":"Vlaams-Brabant",
    "sg:tags":[
        "department",
        "store"
    ],
    "wof:name":"Gb Contact Nv",
    "wof:placetype":"venue"
},
  "geometry": {"coordinates":[4.7818598747,51.0183486938],"type":"Point"}
}