{
  "type": "Feature",
  "properties": {
    "addr:full":"Kastelsedijk 34 Dessel Antwerpen 2480",
    "addr:housenumber":"34",
    "addr:postcode":"2480",
    "addr:street":"Kastelsedijk",
    "iso:country":"BE",
    "sg:address":"Kastelsedijk 34",
    "sg:city":"Dessel",
    "sg:classifiers":[
        {
            "category":"Home & Garden",
            "subcategory":"Home Furnishings",
            "type":"Retail Goods"
        }
    ],
    "sg:phone":"+32 14 32 60 25",
    "sg:postcode":"2480",
    "sg:province":"Antwerpen",
    "sg:tags":[
        "interior",
        "decoration"
    ],
    "wof:name":"Tc Design Bvba",
    "wof:placetype":"venue"
},
  "geometry": {"coordinates":[5.0869650841,51.2322044373],"type":"Point"}
}