{
  "type": "Feature",
  "properties": {
    "iso:country":"BE",
    "sg:address":"Miksebaan 306",
    "sg:city":"Brasschaat",
    "sg:orig_category":"Installation \u00e9lectrique r\u00e9sidentielle",
    "sg:phone":"+32 3 663 40 45",
    "sg:postcode":"2930",
    "sg:province":"Antwerpen",
    "wof:name":"Guido Janssens",
    "wof:placetype":"venue"
},
  "geometry": {"coordinates":[4.5230097771,51.2994308472],"type":"Point"}
}