{
  "type": "Feature",
  "properties": {
    "iso:country":"BE",
    "sg:address":"Textielstraat 2",
    "sg:city":"Zele",
    "sg:orig_category":"Editeurs de journaux. Editeurs de revues and p\u00e9riodiques",
    "sg:phone":"+32 52 45 40 60",
    "sg:postcode":"9240",
    "sg:province":"Oost-Vlaanderen",
    "wof:name":"Het Blad",
    "wof:placetype":"venue"
},
  "geometry": {"coordinates":[4.052341938,51.0718383789],"type":"Point"}
}