{
  "type": "Feature",
  "properties": {
    "iso:country":"BE",
    "sg:address":"Schutterstraat 17",
    "sg:city":"Arendonk",
    "sg:classifiers":[
        {
            "category":"Shopping",
            "subcategory":"Department Store",
            "type":"Retail Goods"
        }
    ],
    "sg:phone":"+32 14 67 89 12",
    "sg:postcode":"2370",
    "sg:province":"Antwerpen",
    "sg:tags":[
        "surplus",
        "army"
    ],
    "wof:name":"Amerikaanse Stock",
    "wof:placetype":"venue"
},
  "geometry": {"coordinates":[5.0794591904,51.323928833],"type":"Point"}
}