{
  "type": "Feature",
  "properties": {
    "addr:full":"Avenue Des Eglantiers 21 Ukkel/uccle Bruxelles-Capitale 1180",
    "addr:housenumber":"21",
    "addr:postcode":"1180",
    "addr:street":"Avenue Des Eglantiers;/",
    "iso:country":"BE",
    "sg:address":"Avenue Des Eglantiers 21",
    "sg:city":"Ukkel/uccle",
    "sg:orig_category":"Enseignement maternel and primaire",
    "sg:phone":"+32 2 375 86 57",
    "sg:postcode":"1180",
    "sg:province":"Bruxelles-Capitale",
    "wof:name":"Ecole Fond. Communale",
    "wof:placetype":"venue"
},
  "geometry": {"coordinates":[4.3729720116,50.7832145691],"type":"Point"}
}