{
  "type": "Feature",
  "properties": {
    "addr:full":"Veeweidestraat 1bb Lubbeek Vlaams-Brabant 3210",
    "addr:housenumber":"1bb",
    "addr:postcode":"3210",
    "addr:street":"Veeweidestraat",
    "iso:country":"BE",
    "sg:address":"Veeweidestraat 1bb",
    "sg:city":"Lubbeek",
    "sg:orig_category":"Plomberie, chauffage and installations sanitaires",
    "sg:phone":"+32 16 25 32 00",
    "sg:postcode":"3210",
    "sg:province":"Vlaams-Brabant",
    "wof:name":"Alg.aann.verwarmingsinst.",
    "wof:placetype":"venue"
},
  "geometry": {"coordinates":[4.7519378662,50.8922424316],"type":"Point"}
}