{
  "type": "Feature",
  "properties": {
    "iso:country":"BE",
    "sg:address":"Rue De Leumont 46",
    "sg:city":"Wanze (antheit)",
    "sg:classifiers":[
        {
            "category":"Professional",
            "subcategory":"Management & Consulting",
            "type":"Services"
        }
    ],
    "sg:phone":"+32 85 25 42 36",
    "sg:postcode":"4520",
    "sg:province":"Li\u00e8ge",
    "sg:tags":[
        "-",
        "processing",
        "data",
        "consultant"
    ],
    "wof:name":"Aroba Consult",
    "wof:placetype":"venue"
},
  "geometry": {"coordinates":[5.2242941856,50.5354690552],"type":"Point"}
}