{
  "type": "Feature",
  "properties": {
    "iso:country":"BE",
    "sg:address":"7",
    "sg:city":"Sint-pietersvliet Pb 8 2000 Antwerpen",
    "sg:classifiers":[
        {
            "category":"Professional",
            "subcategory":"Engineering",
            "type":"Services"
        }
    ],
    "sg:phone":"+32 3 203 97 00",
    "sg:postcode":"7",
    "sg:tags":[
        "machine",
        "-",
        "mechanical"
    ],
    "wof:name":"Sqm Europe Nv",
    "wof:placetype":"venue"
},
  "geometry": {"coordinates":[4.4009599686,51.2252006531],"type":"Point"}
}