{
  "type": "Feature",
  "properties": {
    "iso:country":"BE",
    "sg:address":"Rue Des Pieds D'alouette 18",
    "sg:city":"Namur (naninne)",
    "sg:classifiers":[
        {
            "category":"Professional",
            "subcategory":"Management & Consulting",
            "type":"Services"
        }
    ],
    "sg:phone":"+32 81 22 59 57",
    "sg:postcode":"5100",
    "sg:province":"Namur",
    "sg:tags":[
        "consultant",
        "agency",
        "advertising"
    ],
    "wof:name":"C.i.c.",
    "wof:placetype":"venue"
},
  "geometry": {"coordinates":[4.9259200096,50.4251365662],"type":"Point"}
}