{
  "type": "Feature",
  "properties": {
    "iso:country":"BE",
    "sg:address":"Rue Du Centre 35",
    "sg:city":"Tinlot",
    "sg:orig_category":"Offices du tourisme",
    "sg:phone":"+32 85 51 15 72",
    "sg:postcode":"4557",
    "sg:province":"Li\u00e8ge",
    "wof:name":"Syndicat D\u00b4initiative",
    "wof:placetype":"venue"
},
  "geometry": {"coordinates":[5.37830019,50.4777183533],"type":"Point"}
}