{
  "type": "Feature",
  "properties": {
    "iso:country":"BE",
    "sg:address":"Rue Bawepuce 30",
    "sg:city":"Sprimont",
    "sg:orig_category":"R\u00e9paration and restauration de meubles",
    "sg:phone":"+32 4 382 12 82",
    "sg:postcode":"4140",
    "sg:province":"Li\u00e8ge",
    "wof:name":"Sylvia Bar",
    "wof:placetype":"venue"
},
  "geometry": {"coordinates":[5.6414618492,50.5070075989],"type":"Point"}
}