{
  "type": "Feature",
  "properties": {
    "iso:country":"BE",
    "sg:address":"Heirbaan 8a",
    "sg:city":"Glabbeek",
    "sg:orig_category":"Tuinen",
    "sg:phone":"+32 16 77 01 58",
    "sg:postcode":"3384",
    "sg:province":"Vlaams-Brabant",
    "wof:name":"Staes Guillaume",
    "wof:placetype":"venue"
},
  "geometry": {"coordinates":[4.9119129181,50.8813934326],"type":"Point"}
}