{
  "type": "Feature",
  "properties": {
    "iso:country":"BE",
    "sg:address":"Rue De Bruxelles 90",
    "sg:city":"Awans",
    "sg:orig_category":"Voertuigen",
    "sg:phone":"+32 4 257 47 29",
    "sg:postcode":"4340",
    "sg:province":"Li\u00e8ge",
    "wof:name":"Garage Bar\u00c9e",
    "wof:placetype":"venue"
},
  "geometry": {"coordinates":[5.4780731201,50.6769294739],"type":"Point"}
}