{
  "type": "Feature",
  "properties": {
    "addr:full":"Lijkveldestraat 16 Sint-gillis-waas Oost-Vlaanderen 9170",
    "addr:housenumber":"16",
    "addr:postcode":"9170",
    "addr:street":"Lijkveldestraat",
    "iso:country":"BE",
    "sg:address":"Lijkveldestraat 16",
    "sg:city":"Sint-gillis-waas",
    "sg:orig_category":"Diverse bouwafwerking and reiniging Woningbouw",
    "sg:phone":"+32 3 777 97 38",
    "sg:postcode":"9170",
    "sg:province":"Oost-Vlaanderen",
    "wof:name":"Wuytack",
    "wof:placetype":"venue"
},
  "geometry": {"coordinates":[4.0884170532,51.1868057251],"type":"Point"}
}