{
  "type": "Feature",
  "properties": {
    "iso:country":"BE",
    "sg:address":"Maalbeeklaan 18",
    "sg:city":"Etterbeek",
    "sg:orig_category":"Zalen voor culturele evenementen",
    "sg:phone":"+32 2 230 29 88",
    "sg:postcode":"1040",
    "sg:province":"Bruxelles-Capitale",
    "wof:name":"Centre Culturel",
    "wof:placetype":"venue"
},
  "geometry": {"coordinates":[4.380027771,50.836933136],"type":"Point"}
}