{
  "type": "Feature",
  "properties": {
    "addr:full":"Chauss\u00e9e De Charleroi 75 Gembloux-sur-orneau (gembloux) Namur 5030",
    "addr:housenumber":"75",
    "addr:postcode":"5030",
    "addr:street":"Chausse\u0301E De Charleroi;Namur",
    "iso:country":"BE",
    "sg:address":"Chauss\u00e9e De Charleroi 75",
    "sg:city":"Gembloux-sur-orneau (gembloux)",
    "sg:classifiers":[
        {
            "category":"Real Estate",
            "subcategory":"Surveying",
            "type":"Services"
        }
    ],
    "sg:phone":"+32 81 61 17 07",
    "sg:postcode":"5030",
    "sg:province":"Namur",
    "sg:tags":[
        "surveyor",
        "land"
    ],
    "wof:name":"G\u00e9otec Sprl",
    "wof:placetype":"venue"
},
  "geometry": {"coordinates":[4.6866550446,50.5635757446],"type":"Point"}
}