{
  "type": "Feature",
  "properties": {
    "iso:country":"BE",
    "sg:address":"Avenue De Falichamps 20",
    "sg:city":"Namur",
    "sg:orig_category":"Elektrische installaties voor woningen",
    "sg:phone":"+32 81 31 04 23",
    "sg:postcode":"5100",
    "sg:province":"Namur",
    "wof:name":"Frederic Hanse",
    "wof:placetype":"venue"
},
  "geometry": {"coordinates":[4.8713750839,50.4566345215],"type":"Point"}
}