{
  "type": "Feature",
  "properties": {
    "addr:full":"Spildoornstraat 34 Waregem West-Vlaanderen 8792",
    "addr:housenumber":"34",
    "addr:postcode":"8792",
    "addr:street":"Spildoornstraat",
    "iso:country":"BE",
    "sg:address":"Spildoornstraat 34",
    "sg:city":"Waregem",
    "sg:orig_category":"Bouwwerktuigen Gh Verhuur bouwmachines",
    "sg:phone":"+32 56 72 05 72",
    "sg:postcode":"8792",
    "sg:province":"West-Vlaanderen",
    "wof:name":"Hd International",
    "wof:placetype":"venue"
},
  "geometry": {"coordinates":[3.3694229126,50.8950195312],"type":"Point"}
}