{
  "type": "Feature",
  "properties": {
    "addr:full":"Chauss\u00e9e De Stockel 270 Bruxelles (woluwe-saint-lambert) Bruxelles-Capitale 1200",
    "addr:housenumber":"270",
    "addr:postcode":"1200",
    "addr:street":"Chausse\u0301E De Stockel",
    "iso:country":"BE",
    "sg:address":"Chauss\u00e9e De Stockel 270",
    "sg:city":"Bruxelles (woluwe-saint-lambert)",
    "sg:classifiers":[
        {
            "category":"Education",
            "subcategory":"School",
            "type":"Public Place"
        }
    ],
    "sg:phone":"+32 2 771 84 11",
    "sg:postcode":"1200",
    "sg:province":"Bruxelles-Capitale",
    "sg:tags":[
        "secondary"
    ],
    "wof:name":"College Don Bosco Wsl",
    "wof:placetype":"venue"
},
  "geometry": {"coordinates":[4.4491991997,50.8413543701],"type":"Point"}
}