{
  "type": "Feature",
  "properties": {
    "addr:full":"Molenstraat 92 Sint-laureins Oost-Vlaanderen 9988",
    "addr:housenumber":"92",
    "addr:postcode":"9988",
    "addr:street":"Molenstraat",
    "iso:country":"BE",
    "sg:address":"Molenstraat 92",
    "sg:city":"Sint-laureins",
    "sg:orig_category":"Belastingconsulenten Diverse juridische dienstverlening",
    "sg:phone":"+32 9 379 97 16",
    "sg:postcode":"9988",
    "sg:province":"Oost-Vlaanderen",
    "wof:name":"N. Van Den Bulcke",
    "wof:placetype":"venue"
},
  "geometry": {"coordinates":[3.6258270741,51.2817497253],"type":"Point"}
}