{
  "type": "Feature",
  "properties": {
    "iso:country":"BE",
    "sg:address":"Warmestraat 30",
    "sg:city":"Maldegem",
    "sg:orig_category":"Eleveurs de bovins",
    "sg:phone":"+32 50 71 26 50",
    "sg:postcode":"9990",
    "sg:province":"Oost-Vlaanderen",
    "wof:name":"Jean Cauwels",
    "wof:placetype":"venue"
},
  "geometry": {"coordinates":[3.4717309475,51.2152099609],"type":"Point"}
}