{
  "type": "Feature",
  "properties": {
    "addr:full":"Beukenlei 9 Brecht Antwerpen 2960",
    "addr:housenumber":"9",
    "addr:postcode":"2960",
    "addr:street":"Beukenlei",
    "iso:country":"BE",
    "sg:address":"Beukenlei 9",
    "sg:city":"Brecht",
    "sg:orig_category":"Supermarkten",
    "sg:phone":"+32 3 636 42 65",
    "sg:postcode":"2960",
    "sg:province":"Antwerpen",
    "wof:name":"Ad Delhaize",
    "wof:placetype":"venue"
},
  "geometry": {"coordinates":[4.5665950775,51.3047065735],"type":"Point"}
}