{
  "type": "Feature",
  "properties": {
    "iso:country":"BE",
    "sg:address":"Leukenstraat 26",
    "sg:city":"Peer",
    "sg:classifiers":[
        {
            "category":"Building & Trades",
            "subcategory":"Electrical",
            "type":"Services"
        }
    ],
    "sg:phone":"+32 11 63 56 20",
    "sg:postcode":"3990",
    "sg:province":"Limburg",
    "sg:tags":[
        "electric",
        "-",
        "housewiring",
        "contractor"
    ],
    "wof:name":"Feyen Bvba",
    "wof:placetype":"venue"
},
  "geometry": {"coordinates":[5.4502220154,51.1372833252],"type":"Point"}
}