{
  "type": "Feature",
  "properties": {
    "iso:country":"BE",
    "sg:address":"Blokstraat 1",
    "sg:city":"Boortmeerbeek",
    "sg:orig_category":"Entretien and r\u00e9parations de voitures",
    "sg:phone":"+32 15 61 62 91",
    "sg:postcode":"3191",
    "sg:province":"Vlaams-Brabant",
    "wof:name":"Car Repair Company",
    "wof:placetype":"venue"
},
  "geometry": {"coordinates":[4.5395698547,50.9775314331],"type":"Point"}
}