{
  "type": "Feature",
  "properties": {
    "addr:full":"Rue Bonny-d'au-ban 43 Yvoir (groot) Namur 5530",
    "addr:housenumber":"43",
    "addr:postcode":"5530",
    "addr:street":"Rue Bonny-D'Au-Ban;Groot Namur",
    "iso:country":"BE",
    "sg:address":"Rue Bonny-d'au-ban 43",
    "sg:city":"Yvoir (groot)",
    "sg:orig_category":"Elektrische installaties voor woningen",
    "sg:phone":"+32 83 69 98 86",
    "sg:postcode":"5530",
    "sg:province":"Namur",
    "wof:name":"Ema Services",
    "wof:placetype":"venue"
},
  "geometry": {"coordinates":[4.8771700859,50.3269081116],"type":"Point"}
}