{
  "type": "Feature",
  "properties": {
    "addr:full":"Brandsmisstraat 25 Deerlijk West-Vlaanderen 8540",
    "addr:housenumber":"25",
    "addr:postcode":"8540",
    "addr:street":"Brandsmisstraat",
    "iso:country":"BE",
    "sg:address":"Brandsmisstraat 25",
    "sg:city":"Deerlijk",
    "sg:classifiers":[
        {
            "category":"Science Facility",
            "type":"Public Place"
        }
    ],
    "sg:phone":"+32 479 99 71 82",
    "sg:postcode":"8540",
    "sg:province":"West-Vlaanderen",
    "sg:tags":[
        "industrial",
        "-",
        "robot"
    ],
    "wof:name":"Handsaeme J",
    "wof:placetype":"venue"
},
  "geometry": {"coordinates":[3.3622291088,50.8276062012],"type":"Point"}
}