{
  "type": "Feature",
  "properties": {
    "addr:full":"Avenue Jules Bordet 11 Bruxelles (evere) Bruxelles-Capitale 1140",
    "addr:housenumber":"11",
    "addr:postcode":"1140",
    "addr:street":"Avenue Jules Bordet",
    "iso:country":"BE",
    "sg:address":"Avenue Jules Bordet 11",
    "sg:city":"Bruxelles (evere)",
    "sg:classifiers":[
        {
            "category":"Shopping",
            "subcategory":"Computers & Home Electronics",
            "type":"Retail Goods"
        }
    ],
    "sg:phone":"+32 2 706 03 30",
    "sg:postcode":"1140",
    "sg:province":"Bruxelles-Capitale",
    "sg:tags":[
        "-",
        "peripheral",
        "processing",
        "data",
        "equipment"
    ],
    "wof:name":"Storage Technology Belgium Nv",
    "wof:placetype":"venue"
},
  "geometry": {"coordinates":[4.4143872261,50.8736038208],"type":"Point"}
}