{
  "type": "Feature",
  "properties": {
    "iso:country":"BE",
    "sg:address":"Parking De L'\u00c9cole",
    "sg:city":"Antoing",
    "sg:classifiers":[
        {
            "category":"Fast Food",
            "type":"Food & Drink"
        }
    ],
    "sg:phone":"+32 69 44 42 35",
    "sg:postcode":"7640",
    "sg:province":"Hainaut",
    "sg:tags":[
        "meeneem",
        "restaurant"
    ],
    "wof:name":"Dominique Daye",
    "wof:placetype":"venue"
},
  "geometry": {"coordinates":[3.5027699471,50.5577697754],"type":"Point"}
}