{
  "type": "Feature",
  "properties": {
    "addr:full":"Kwadenplasstraat 33 Heist-op-den-berg Antwerpen 2220",
    "addr:housenumber":"33",
    "addr:postcode":"2220",
    "addr:street":"Kwadenplasstraat",
    "iso:country":"BE",
    "sg:address":"Kwadenplasstraat 33",
    "sg:city":"Heist-op-den-berg",
    "sg:orig_category":"Fruitteelt",
    "sg:phone":"+32 15 22 01 44",
    "sg:postcode":"2220",
    "sg:province":"Antwerpen",
    "wof:name":"Jozef Claes",
    "wof:placetype":"venue"
},
  "geometry": {"coordinates":[4.7427639961,51.0467300415],"type":"Point"}
}