{
  "type": "Feature",
  "properties": {
    "iso:country":"BE",
    "sg:address":"Ramstraat 28",
    "sg:city":"Antwerpen",
    "sg:classifiers":[
        {
            "category":"Real Estate",
            "subcategory":"Architect",
            "type":"Services"
        }
    ],
    "sg:phone":"+32 3 236 99 82",
    "sg:postcode":"2018",
    "sg:province":"Antwerpen",
    "wof:name":"Mermans P",
    "wof:placetype":"venue"
},
  "geometry": {"coordinates":[4.4289031029,51.207698822],"type":"Point"}
}