{
  "type": "Feature",
  "properties": {
    "addr:full":"Wielemans Ceuppenslaan 115 Vorst/forest Bruxelles-Capitale 1190",
    "addr:housenumber":"115",
    "addr:postcode":"1190",
    "addr:street":"Wielemans Ceuppenslaan;/ Forest",
    "iso:country":"BE",
    "sg:address":"Wielemans Ceuppenslaan 115",
    "sg:city":"Vorst/forest",
    "sg:orig_category":"Architecten",
    "sg:phone":"+32 2 345 54 25",
    "sg:postcode":"1190",
    "sg:province":"Bruxelles-Capitale",
    "wof:name":"Jean Richir",
    "wof:placetype":"venue"
},
  "geometry": {"coordinates":[4.3314609528,50.8240509033],"type":"Point"}
}