{
  "type": "Feature",
  "properties": {
    "addr:full":"Rue De La Sucrerie 33a Hannut (trogn\u00e9e) Li\u00e8ge 4280",
    "addr:housenumber":"33a",
    "addr:postcode":"4280",
    "addr:street":"Rue De La Sucrerie;Trogne\u0301E",
    "iso:country":"BE",
    "sg:address":"Rue De La Sucrerie 33a",
    "sg:city":"Hannut (trogn\u00e9e)",
    "sg:classifiers":[
        {
            "category":"Freight",
            "type":"Transportation"
        }
    ],
    "sg:phone":"+32 19 51 59 10",
    "sg:postcode":"4280",
    "sg:province":"Li\u00e8ge",
    "sg:tags":[
        "-",
        "transport"
    ],
    "wof:name":"Transport Louis Vanderoel Sprl",
    "wof:placetype":"venue"
},
  "geometry": {"coordinates":[5.1216077805,50.6833572388],"type":"Point"}
}