{
  "type": "Feature",
  "properties": {
    "addr:full":"Place Thomas Balis 3 Bruxelles (auderghem) Bruxelles-Capitale 1160",
    "addr:housenumber":"3",
    "addr:postcode":"1160",
    "addr:street":"Place Thomas Balis",
    "iso:country":"BE",
    "sg:address":"Place Thomas Balis 3",
    "sg:city":"Bruxelles (auderghem)",
    "sg:classifiers":[
        {
            "category":"Professional",
            "subcategory":"Detective & Security Services",
            "type":"Services"
        }
    ],
    "sg:postcode":"1160",
    "sg:province":"Bruxelles-Capitale",
    "sg:tags":[
        "installation",
        "alarm",
        "-",
        "system"
    ],
    "wof:name":"Agil S\u00e9curit\u00e9",
    "wof:placetype":"venue"
},
  "geometry": {"coordinates":[4.4119348526,50.8197021484],"type":"Point"}
}