{
  "type": "Feature",
  "properties": {
    "addr:full":"Mudaeusstraat 2 Brecht Antwerpen 2960",
    "addr:housenumber":"2",
    "addr:postcode":"2960",
    "addr:street":"Mudaeusstraat",
    "iso:country":"BE",
    "sg:address":"Mudaeusstraat 2",
    "sg:city":"Brecht",
    "sg:orig_category":"Mus\u00e9es and patrimoine culturel",
    "sg:phone":"+32 3 313 97 79",
    "sg:postcode":"2960",
    "sg:province":"Antwerpen",
    "wof:name":"Kempisch Museum",
    "wof:placetype":"venue"
},
  "geometry": {"coordinates":[4.6417489052,51.3478965759],"type":"Point"}
}