{
  "type": "Feature",
  "properties": {
    "iso:country":"BE",
    "sg:address":"Beekstraat 23",
    "sg:city":"Haaltert",
    "sg:orig_category":"Boucheries",
    "sg:phone":"+32 53 83 22 74",
    "sg:postcode":"9451",
    "sg:province":"Oost-Vlaanderen",
    "wof:name":"Carla Buydens",
    "wof:placetype":"venue"
},
  "geometry": {"coordinates":[3.9923579693,50.887172699],"type":"Point"}
}