{
  "type": "Feature",
  "properties": {
    "addr:full":"Pakenstraat 5 Leuven (heverlee) Vlaams-Brabant 3001",
    "addr:housenumber":"5",
    "addr:postcode":"3001",
    "addr:street":"Pakenstraat",
    "iso:country":"BE",
    "sg:address":"Pakenstraat 5",
    "sg:city":"Leuven (heverlee)",
    "sg:classifiers":[
        {
            "category":"Professional",
            "subcategory":"Testing Lab",
            "type":"Services"
        }
    ],
    "sg:phone":"+32 16 40 50 17",
    "sg:postcode":"3001",
    "sg:province":"Vlaams-Brabant",
    "sg:tags":[
        "chemist"
    ],
    "wof:name":"Cleeremans H",
    "wof:placetype":"venue"
},
  "geometry": {"coordinates":[4.7113881111,50.8625183105],"type":"Point"}
}