{
  "type": "Feature",
  "properties": {
    "iso:country":"BE",
    "sg:address":"Pastoor Van Mierlolaan 36 Box 1",
    "sg:city":"Heusden-zolder (heusden)",
    "sg:classifiers":[
        {
            "category":"Insurance",
            "subcategory":"Insurance Agent",
            "type":"Services"
        }
    ],
    "sg:phone":"+32 11 43 12 80",
    "sg:postcode":"3550",
    "sg:province":"Limburg",
    "sg:tags":[
        "broker"
    ],
    "wof:name":"Oben M Bvba",
    "wof:placetype":"venue"
},
  "geometry": {"coordinates":[5.2802209854,51.0319480896],"type":"Point"}
}