{
  "type": "Feature",
  "properties": {
    "addr:full":"Rue Bourlon 136 Silly (bassilly) Hainaut 7830",
    "addr:housenumber":"136",
    "addr:postcode":"7830",
    "addr:street":"Rue Bourlon",
    "iso:country":"BE",
    "sg:address":"Rue Bourlon 136",
    "sg:city":"Silly (bassilly)",
    "sg:classifiers":[
        {
            "category":"Professional",
            "subcategory":"Accounting & Tax Preparation",
            "type":"Services"
        }
    ],
    "sg:phone":"+32 68 55 23 44",
    "sg:postcode":"7830",
    "sg:province":"Hainaut",
    "sg:tags":[
        "bookkeeper"
    ],
    "wof:name":"Gen-fisco Sprl",
    "wof:placetype":"venue"
},
  "geometry": {"coordinates":[3.9168870449,50.6736679077],"type":"Point"}
}