{
  "type": "Feature",
  "properties": {
    "addr:full":"Hoornstraat 8 Halle Vlaams-Brabant 1500",
    "addr:housenumber":"8",
    "addr:postcode":"1500",
    "addr:street":"Hoornstraat",
    "iso:country":"BE",
    "sg:address":"Hoornstraat 8",
    "sg:city":"Halle",
    "sg:classifiers":[
        {
            "category":"Personal",
            "subcategory":"Beauty Salon",
            "type":"Services"
        }
    ],
    "sg:phone":"+32 2 356 97 10",
    "sg:postcode":"1500",
    "sg:province":"Vlaams-Brabant",
    "sg:tags":[
        "lady",
        "-",
        "hairdressing"
    ],
    "wof:name":"Brigitte",
    "wof:placetype":"venue"
},
  "geometry": {"coordinates":[4.2364888191,50.7364845276],"type":"Point"}
}