{
  "type": "Feature",
  "properties": {
    "iso:country":"BE",
    "sg:address":"Avenue Neptune 6",
    "sg:city":"Vorst/forest",
    "sg:orig_category":"M\u00e9decins and sp\u00e9cialistes",
    "sg:phone":"+32 2 344 76 43",
    "sg:postcode":"1190",
    "sg:province":"Bruxelles-Capitale",
    "wof:name":"V\u00c9ronique Gaudy",
    "wof:placetype":"venue"
},
  "geometry": {"coordinates":[4.3317508698,50.8138008118],"type":"Point"}
}