{
  "type": "Feature",
  "properties": {
    "addr:full":"Rue De L'abbaye 3bb Walhain Brabant Wallon 1457",
    "addr:housenumber":"1457",
    "addr:postcode":"3bb",
    "addr:street":"Rue De L'Abbaye",
    "iso:country":"BE",
    "sg:address":"Rue De L'abbaye 3bb",
    "sg:city":"Walhain",
    "sg:orig_category":"Traitements param\u00e9dicaux",
    "sg:phone":"+32 10 65 86 55",
    "sg:postcode":"1457",
    "sg:province":"Brabant Wallon",
    "wof:name":"M. Baby",
    "wof:placetype":"venue"
},
  "geometry": {"coordinates":[4.6951799393,50.6165390015],"type":"Point"}
}