{
  "type": "Feature",
  "properties": {
    "iso:country":"BE",
    "sg:address":"Hulsterweg 130",
    "sg:city":"Tessenderlo",
    "sg:classifiers":[
        {
            "category":"Health Services",
            "subcategory":"Dentist",
            "type":"Services"
        }
    ],
    "sg:phone":"+32 13 66 65 47",
    "sg:postcode":"3980",
    "sg:province":"Limburg",
    "wof:name":"Deferme Bart",
    "wof:placetype":"venue"
},
  "geometry": {"coordinates":[5.1185002327,51.0694198608],"type":"Point"}
}