{
  "type": "Feature",
  "properties": {
    "addr:full":"Brusselsestraat 61 Leuven Vlaams-Brabant 3000",
    "addr:housenumber":"61",
    "addr:postcode":"3000",
    "addr:street":"Brusselsestraat",
    "iso:country":"BE",
    "sg:address":"Brusselsestraat 61",
    "sg:city":"Leuven",
    "sg:classifiers":[
        {
            "category":"Retail",
            "subcategory":"Funeral Services",
            "type":"Services"
        }
    ],
    "sg:phone":"+32 16 22 54 29",
    "sg:postcode":"3000",
    "sg:province":"Vlaams-Brabant",
    "sg:tags":[
        "director"
    ],
    "wof:name":"Van Weverenbergh-tossyn",
    "wof:placetype":"venue"
},
  "geometry": {"coordinates":[4.6965851784,50.8801383972],"type":"Point"}
}