{
  "type": "Feature",
  "properties": {
    "addr:full":"Windmolenstraat 14 Beersel Vlaams-Brabant 1650",
    "addr:housenumber":"14",
    "addr:postcode":"1650",
    "addr:street":"Windmolenstraat",
    "iso:country":"BE",
    "sg:address":"Windmolenstraat 14",
    "sg:city":"Beersel",
    "sg:orig_category":"Woningbouw",
    "sg:phone":"+32 2 331 06 68",
    "sg:postcode":"1650",
    "sg:province":"Vlaams-Brabant",
    "wof:name":"Janssens En Zoon",
    "wof:placetype":"venue"
},
  "geometry": {"coordinates":[4.3133559227,50.7695236206],"type":"Point"}
}