{
  "type": "Feature",
  "properties": {
    "addr:full":"Rozeveldstraat 86 Torhout West-Vlaanderen 8820",
    "addr:housenumber":"86",
    "addr:postcode":"8820",
    "addr:street":"Rozeveldstraat",
    "iso:country":"BE",
    "sg:address":"Rozeveldstraat 86",
    "sg:city":"Torhout",
    "sg:classifiers":[
        {
            "category":"Manufacturing",
            "subcategory":"Paper Products",
            "type":"Manufacturing & Wholesale Goods"
        }
    ],
    "sg:phone":"+32 485 69 65 58",
    "sg:postcode":"8820",
    "sg:province":"West-Vlaanderen",
    "sg:tags":[
        "bookbinding"
    ],
    "wof:name":"Artistiek Boekbinden",
    "wof:placetype":"venue"
},
  "geometry": {"coordinates":[3.1351180077,51.0882568359],"type":"Point"}
}