{
  "type": "Feature",
  "properties": {
    "addr:full":"Rue De La Couronne 12 Wavre Brabant Wallon 1301",
    "addr:housenumber":"12;1301",
    "addr:street":"Rue De La Couronne",
    "iso:country":"BE",
    "sg:address":"Rue De La Couronne 12",
    "sg:city":"Wavre",
    "sg:orig_category":"Mat\u00e9riel de T\u00e9l\u00e9communication",
    "sg:phone":"+32 10 22 91 81",
    "sg:postcode":"1301",
    "sg:province":"Brabant Wallon",
    "wof:name":"Communication Center",
    "wof:placetype":"venue"
},
  "geometry": {"coordinates":[4.6109490395,50.7078132629],"type":"Point"}
}