{
  "type": "Feature",
  "properties": {
    "addr:full":"Rue Du Sart Helman 9 Fernelmont (franc-waret) Namur 5380",
    "addr:housenumber":"9",
    "addr:postcode":"5380",
    "addr:street":"Rue Du Sart Helman",
    "iso:country":"BE",
    "sg:address":"Rue Du Sart Helman 9",
    "sg:city":"Fernelmont (franc-waret)",
    "sg:classifiers":[
        {
            "category":"Health Services",
            "subcategory":"Health Practitioner",
            "type":"Services"
        }
    ],
    "sg:phone":"+32 81 83 35 74",
    "sg:postcode":"5380",
    "sg:province":"Namur",
    "sg:tags":[
        "physiotherapist"
    ],
    "wof:name":"Lisin M",
    "wof:placetype":"venue"
},
  "geometry": {"coordinates":[4.980948925,50.5214767456],"type":"Point"}
}