{
  "type": "Feature",
  "properties": {
    "addr:full":"Sint-elooistraat 24 Lochristi (zeveneken) Oost-Vlaanderen 9080",
    "addr:housenumber":"24",
    "addr:postcode":"9080",
    "addr:street":"Sint-Elooistraat",
    "iso:country":"BE",
    "sg:address":"Sint-elooistraat 24",
    "sg:city":"Lochristi (zeveneken)",
    "sg:classifiers":[
        {
            "category":"Real Estate",
            "subcategory":"Architect",
            "type":"Services"
        }
    ],
    "sg:phone":"+32 9 355 64 03",
    "sg:postcode":"9080",
    "sg:province":"Oost-Vlaanderen",
    "wof:name":"Van Peteghem E",
    "wof:placetype":"venue"
},
  "geometry": {"coordinates":[3.8978319168,51.1064376831],"type":"Point"}
}