{
  "type": "Feature",
  "properties": {
    "addr:full":"Stasegemsesteenweg 154 Harelbeke West-Vlaanderen 8530",
    "addr:housenumber":"154",
    "addr:postcode":"8530",
    "addr:street":"Stasegemsesteenweg",
    "iso:country":"BE",
    "sg:address":"Stasegemsesteenweg 154",
    "sg:city":"Harelbeke",
    "sg:orig_category":"Boekhouders",
    "sg:phone":"+32 56 71 50 36",
    "sg:postcode":"8530",
    "sg:province":"West-Vlaanderen",
    "wof:name":"Germain Vandendriessche",
    "wof:placetype":"venue"
},
  "geometry": {"coordinates":[3.3101398945,50.8407325745],"type":"Point"}
}