{
  "type": "Feature",
  "properties": {
    "iso:country":"BE",
    "sg:address":"Lauwestraat 6",
    "sg:city":"Wevelgem",
    "sg:orig_category":"Werk and personeelsselectie",
    "sg:phone":"+32 56 41 12 37",
    "sg:postcode":"8560",
    "sg:province":"West-Vlaanderen",
    "wof:name":"Pwa Wevelgem",
    "wof:placetype":"venue"
},
  "geometry": {"coordinates":[3.184869051,50.80884552],"type":"Point"}
}