{
  "type": "Feature",
  "properties": {
    "iso:country":"BE",
    "sg:address":"Lange Ommegangstraat 50",
    "sg:city":"Erpe-mere (erpe)",
    "sg:classifiers":[
        {
            "category":"Building & Trades",
            "subcategory":"Construction",
            "type":"Services"
        }
    ],
    "sg:phone":"+32 477 66 74 16",
    "sg:postcode":"9420",
    "sg:province":"Oost-Vlaanderen",
    "sg:tags":[
        "installation",
        "-",
        "central",
        "heating"
    ],
    "wof:name":"Sanitherm",
    "wof:placetype":"venue"
},
  "geometry": {"coordinates":[3.983246088,50.9279785156],"type":"Point"}
}