{
  "type": "Feature",
  "properties": {
    "iso:country":"BE",
    "sg:address":"Rue Archim\u00e8de 5-13",
    "sg:city":"Bruxelles",
    "sg:classifiers":[
        {
            "category":"Banks & Credit Unions",
            "subcategory":"Financial Services",
            "type":"Services"
        }
    ],
    "sg:phone":"+32 2 286 90 00",
    "sg:postcode":"1000",
    "sg:province":"Bruxelles-Capitale",
    "sg:tags":[
        "financing"
    ],
    "wof:name":"Finaco-hypofinance Nv",
    "wof:placetype":"venue"
},
  "geometry": {"coordinates":[4.3841152191,50.8430137634],"type":"Point"}
}