{
  "type": "Feature",
  "properties": {
    "addr:full":"E. Eylenboschstraat 14 Dilbeek Vlaams-Brabant 1703",
    "addr:housenumber":"14",
    "addr:postcode":"1703",
    "addr:street":"E. Eylenboschstraat",
    "iso:country":"BE",
    "sg:address":"E. Eylenboschstraat 14",
    "sg:city":"Dilbeek",
    "sg:classifiers":[
        {
            "category":"Personal",
            "subcategory":"Beauty Salon",
            "type":"Services"
        }
    ],
    "sg:phone":"+32 2 569 63 32",
    "sg:postcode":"1703",
    "sg:province":"Vlaams-Brabant",
    "sg:tags":[
        "de",
        "coiffure"
    ],
    "wof:name":"Coiffure Rita",
    "wof:placetype":"venue"
},
  "geometry": {"coordinates":[4.193251133,50.8353538513],"type":"Point"}
}