{
  "type": "Feature",
  "properties": {
    "iso:country":"BE",
    "sg:address":"Rittenweg 25",
    "sg:city":"Opglabbeek",
    "sg:classifiers":[
        {
            "category":"Personal",
            "subcategory":"Beauty Salon",
            "type":"Services"
        }
    ],
    "sg:phone":"+32 89 85 52 10",
    "sg:postcode":"3660",
    "sg:province":"Limburg",
    "sg:tags":[
        "de",
        "coiffure"
    ],
    "wof:name":"Coiffure Bernadette",
    "wof:placetype":"venue"
},
  "geometry": {"coordinates":[5.6124429703,51.0490989685],"type":"Point"}
}