{
  "type": "Feature",
  "properties": {
    "addr:full":"Heiveldstraat 12 Gent Oost-Vlaanderen 9040",
    "addr:housenumber":"12",
    "addr:postcode":"9040",
    "addr:street":"Heiveldstraat;Oost-Vlaanderen",
    "iso:country":"BE",
    "sg:address":"Heiveldstraat 12",
    "sg:city":"Gent",
    "sg:orig_category":"Artiesten and kunstenaars Divers amusement",
    "sg:phone":"+32 9 229 17 88",
    "sg:postcode":"9040",
    "sg:province":"Oost-Vlaanderen",
    "wof:name":"De Zachte Klaarte",
    "wof:placetype":"venue"
},
  "geometry": {"coordinates":[3.7524020672,51.0623664856],"type":"Point"}
}