{
  "type": "Feature",
  "properties": {
    "iso:country":"BE",
    "sg:address":"Rue Gr\u00c9try 46a",
    "sg:city":"Li\u00c8ge",
    "sg:orig_category":"Magasins de r\u00e9parations d'articles personnels et m\u00e9nagers divers. Composition and photogravure. R\u00e9pa",
    "sg:phone":"+32 4 344 58 47",
    "sg:postcode":"4020",
    "sg:province":"Li\u00e8ge",
    "wof:name":"Jean-claude Ansenne",
    "wof:placetype":"venue"
},
  "geometry": {"coordinates":[5.5804738998,50.6353302002],"type":"Point"}
}