{
  "type": "Feature",
  "properties": {
    "addr:full":"Orbanlaan 81 Sint-pieters-woluwe/woluwe-saint-pierre Bruxelles-Capitale 1150",
    "addr:housenumber":"81",
    "addr:postcode":"1150",
    "addr:street":"Orbanlaan;/",
    "iso:country":"BE",
    "sg:address":"Orbanlaan 81",
    "sg:city":"Sint-pieters-woluwe/woluwe-saint-pierre",
    "sg:orig_category":"Artsen and specialisten",
    "sg:phone":"+32 2 771 30 33",
    "sg:postcode":"1150",
    "sg:province":"Bruxelles-Capitale",
    "wof:name":"Jacques Engels",
    "wof:placetype":"venue"
},
  "geometry": {"coordinates":[4.456428051,50.8343544006],"type":"Point"}
}