{
  "type": "Feature",
  "properties": {
    "iso:country":"BE",
    "sg:address":"Poelstraat 2",
    "sg:city":"Sint-gillis-waas",
    "sg:orig_category":"Non-Classified Establishments",
    "sg:phone":"+32 3 777 50 02",
    "sg:postcode":"9170",
    "sg:province":"Oost-Vlaanderen",
    "wof:name":"Tilleman Th Bvba",
    "wof:placetype":"venue"
},
  "geometry": {"coordinates":[4.1473221779,51.1966247559],"type":"Point"}
}