{
  "type": "Feature",
  "properties": {
    "addr:full":"Kerkstraat 146 Arendonk Antwerpen 2370",
    "addr:housenumber":"146",
    "addr:postcode":"2370",
    "addr:street":"Kerkstraat",
    "iso:country":"BE",
    "sg:address":"Kerkstraat 146",
    "sg:city":"Arendonk",
    "sg:orig_category":"Loodgieterij, verwarming and sanitaire installaties",
    "sg:phone":"+32 14 67 98 84",
    "sg:postcode":"2370",
    "sg:province":"Antwerpen",
    "wof:name":"Paul Bols",
    "wof:placetype":"venue"
},
  "geometry": {"coordinates":[5.0767040253,51.3136253357],"type":"Point"}
}