{
  "type": "Feature",
  "properties": {
    "addr:full":"Langenberg 11 Diest (molenstede) Vlaams-Brabant 3294",
    "addr:housenumber":"11",
    "addr:postcode":"3294",
    "addr:street":"Langenberg",
    "iso:country":"BE",
    "sg:address":"Langenberg 11",
    "sg:city":"Diest (molenstede)",
    "sg:classifiers":[
        {
            "category":"Building & Trades",
            "subcategory":"Pest Control",
            "type":"Services"
        }
    ],
    "sg:phone":"+32 13 33 58 87",
    "sg:postcode":"3294",
    "sg:province":"Vlaams-Brabant",
    "sg:tags":[
        "painting",
        "contractor"
    ],
    "wof:name":"Jonckers L",
    "wof:placetype":"venue"
},
  "geometry": {"coordinates":[5.0324997902,50.9959106445],"type":"Point"}
}