{
  "type": "Feature",
  "properties": {
    "addr:full":"Kloosterstraat 12 Zwijndrecht Antwerpen 2070",
    "addr:housenumber":"12",
    "addr:postcode":"2070",
    "addr:street":"Kloosterstraat",
    "iso:country":"BE",
    "sg:address":"Kloosterstraat 12",
    "sg:city":"Zwijndrecht",
    "sg:classifiers":[
        {
            "category":"Personal",
            "subcategory":"Beauty Salon",
            "type":"Services"
        }
    ],
    "sg:phone":"+32 3 252 79 17",
    "sg:postcode":"2070",
    "sg:province":"Antwerpen",
    "sg:tags":[
        "de",
        "coiffure"
    ],
    "wof:name":"Eugeen Van Buel",
    "wof:placetype":"venue"
},
  "geometry": {"coordinates":[4.3442540169,51.2026977539],"type":"Point"}
}