{
  "type": "Feature",
  "properties": {
    "addr:full":"Avenue Edmond Leburton 39 Waremme Li\u00e8ge 4300",
    "addr:housenumber":"39",
    "addr:postcode":"4300",
    "addr:street":"Avenue Edmond Leburton",
    "iso:country":"BE",
    "sg:address":"Avenue Edmond Leburton 39",
    "sg:city":"Waremme",
    "sg:orig_category":"Bioscopen",
    "sg:phone":"+32 19 32 29 55",
    "sg:postcode":"4300",
    "sg:province":"Li\u00e8ge",
    "wof:name":"Vari\u00c9t\u00c9s Cin\u00c9ma",
    "wof:placetype":"venue"
},
  "geometry": {"coordinates":[5.2607097626,50.698059082],"type":"Point"}
}