{
  "type": "Feature",
  "properties": {
    "addr:full":"Rijfstraat 1b10 Antwerpen Antwerpen 2018",
    "addr:housenumber":"1b10",
    "addr:postcode":"2018",
    "addr:street":"Rijfstraat",
    "iso:country":"BE",
    "sg:address":"Rijfstraat 1b10",
    "sg:city":"Antwerpen",
    "sg:orig_category":"Produits interm\u00e9diaires Gr",
    "sg:phone":"+32 3 232 78 93",
    "sg:postcode":"2018",
    "sg:province":"Antwerpen",
    "wof:name":"Gold & Diamonds For Ever",
    "wof:placetype":"venue"
},
  "geometry": {"coordinates":[4.4195208549,51.2161178589],"type":"Point"}
}