{
  "type": "Feature",
  "properties": {
    "addr:full":"Brugsesteenweg 229 Kortrijk West-Vlaanderen 8500",
    "addr:housenumber":"229",
    "addr:postcode":"8500",
    "addr:street":"Brugsesteenweg",
    "iso:country":"BE",
    "sg:address":"Brugsesteenweg 229",
    "sg:city":"Kortrijk",
    "sg:orig_category":"Eclairage et \u00e9quipements du foyer",
    "sg:phone":"+32 56 35 73 81",
    "sg:postcode":"8500",
    "sg:province":"West-Vlaanderen",
    "wof:name":"Home Market",
    "wof:placetype":"venue"
},
  "geometry": {"coordinates":[3.2657430172,50.8421363831],"type":"Point"}
}