{
  "type": "Feature",
  "properties": {
    "iso:country":"BE",
    "sg:address":"Place Saint-g\u00e9ry 35",
    "sg:city":"Bruxelles",
    "sg:classifiers":[
        {
            "category":"Bars & Pubs",
            "type":"Food & Drink"
        }
    ],
    "sg:phone":"+32 2 511 09 01",
    "sg:postcode":"1000",
    "sg:province":"Bruxelles-Capitale",
    "wof:name":"Zebra Sprl",
    "wof:placetype":"venue"
},
  "geometry": {"coordinates":[4.3477811813,50.8481903076],"type":"Point"}
}