{
  "type": "Feature",
  "properties": {
    "iso:country":"BE",
    "sg:address":"Jaak Calloensstraat 14",
    "sg:city":"Sint-pieters-leeuw",
    "sg:classifiers":[
        {
            "category":"Home & Garden",
            "subcategory":"Building Materials",
            "type":"Retail Goods"
        }
    ],
    "sg:phone":"+32 2 306 35 64",
    "sg:postcode":"1600",
    "sg:province":"Vlaams-Brabant",
    "sg:tags":[
        "window"
    ],
    "wof:name":"Willems B",
    "wof:placetype":"venue"
},
  "geometry": {"coordinates":[4.2343420982,50.7886276245],"type":"Point"}
}