{
  "type": "Feature",
  "properties": {
    "addr:full":"Rue Du Marais 2 Arlon Luxembourg 6700",
    "addr:housenumber":"2",
    "addr:postcode":"6700",
    "addr:street":"Rue Du Marais",
    "iso:country":"BE",
    "sg:address":"Rue Du Marais 2",
    "sg:city":"Arlon",
    "sg:classifiers":[
        {
            "category":"Cafe",
            "type":"Food & Drink"
        }
    ],
    "sg:phone":"+32 63 21 71 09",
    "sg:postcode":"6700",
    "sg:province":"Luxembourg",
    "sg:tags":[
        "caf\u00e9s"
    ],
    "wof:name":"Caf\u00c9 Des Sports",
    "wof:placetype":"venue"
},
  "geometry": {"coordinates":[5.7124228477,49.6891365051],"type":"Point"}
}