{
  "type": "Feature",
  "properties": {
    "addr:full":"Rue Fond Des Tawes 93 Li\u00e8ge 1 Li\u00e8ge 4000",
    "addr:housenumber":"93;1",
    "addr:postcode":"4000",
    "addr:street":"Rue Fond Des Tawes",
    "iso:country":"BE",
    "sg:address":"Rue Fond Des Tawes 93",
    "sg:city":"Li\u00e8ge 1",
    "sg:classifiers":[
        {
            "category":"Retail",
            "subcategory":"Auto Repair",
            "type":"Services"
        }
    ],
    "sg:phone":"+32 4 227 98 04",
    "sg:postcode":"4000",
    "sg:province":"Li\u00e8ge",
    "sg:tags":[
        "automobile",
        "-",
        "wrecking"
    ],
    "wof:name":"Ap Auto 93",
    "wof:placetype":"venue"
},
  "geometry": {"coordinates":[5.5862689018,50.6567993164],"type":"Point"}
}