{
  "type": "Feature",
  "properties": {
    "addr:full":"Antwerpsestraat 26 Diest Vlaams-Brabant 3290",
    "addr:housenumber":"26",
    "addr:postcode":"3290",
    "addr:street":"Antwerpsestraat",
    "iso:country":"BE",
    "sg:address":"Antwerpsestraat 26",
    "sg:city":"Diest",
    "sg:orig_category":"Assurances. Banques and organismes de cr\u00e9dit",
    "sg:phone":"+32 13 31 45 72",
    "sg:postcode":"3290",
    "sg:province":"Vlaams-Brabant",
    "wof:name":"Groep Argenta",
    "wof:placetype":"venue"
},
  "geometry": {"coordinates":[5.0556077957,50.9904403687],"type":"Point"}
}