{
  "type": "Feature",
  "properties": {
    "iso:country":"BE",
    "sg:address":"Groot Begijnhof 26",
    "sg:city":"Gent (sint-amandsberg)",
    "sg:classifiers":[
        {
            "category":"Social Services",
            "type":"Services"
        }
    ],
    "sg:phone":"+32 9 228 99 29",
    "sg:postcode":"9040",
    "sg:province":"Oost-Vlaanderen",
    "sg:tags":[
        "handicapped",
        "-"
    ],
    "wof:name":"Thuisbegeleiding Mentaal Gehandicapten De Tandem Vzw",
    "wof:placetype":"venue"
},
  "geometry": {"coordinates":[3.7497830391,51.0575942993],"type":"Point"}
}