{
  "type": "Feature",
  "properties": {
    "addr:full":"Chauss\u00e9e De Namur 89 Anh\u00e9e Namur 5537",
    "addr:housenumber":"89",
    "addr:postcode":"5537",
    "addr:street":"Chausse\u0301E De Namur",
    "iso:country":"BE",
    "sg:address":"Chauss\u00e9e De Namur 89",
    "sg:city":"Anh\u00e9e",
    "sg:classifiers":[
        {
            "category":"Health Services",
            "subcategory":"Health Practitioner",
            "type":"Services"
        }
    ],
    "sg:phone":"+32 82 64 48 37",
    "sg:postcode":"5537",
    "sg:province":"Namur",
    "sg:tags":[
        "physiotherapist"
    ],
    "wof:name":"Anciaux Geraldine",
    "wof:placetype":"venue"
},
  "geometry": {"coordinates":[4.8736982346,50.3212509155],"type":"Point"}
}