{
  "type": "Feature",
  "properties": {
    "iso:country":"BE",
    "sg:address":"Av. Gloires Nationales 80b2",
    "sg:city":"Ganshoren",
    "sg:orig_category":"Jardinage",
    "sg:phone":"+32 2 424 18 12",
    "sg:postcode":"1083",
    "sg:province":"Bruxelles-Capitale",
    "wof:name":"Jardin De Robin",
    "wof:placetype":"venue"
},
  "geometry": {"coordinates":[4.3192148209,50.8679199219],"type":"Point"}
}