{
  "type": "Feature",
  "properties": {
    "addr:full":"Langeweg 16 Overijse Vlaams-Brabant 3090",
    "addr:housenumber":"16",
    "addr:postcode":"3090",
    "addr:street":"Langeweg",
    "iso:country":"BE",
    "sg:address":"Langeweg 16",
    "sg:city":"Overijse",
    "sg:orig_category":"Boekhouders",
    "sg:phone":"+32 2 687 36 13",
    "sg:postcode":"3090",
    "sg:province":"Vlaams-Brabant",
    "wof:name":"Dany Smet",
    "wof:placetype":"venue"
},
  "geometry": {"coordinates":[4.5116767883,50.7495498657],"type":"Point"}
}