{
  "type": "Feature",
  "properties": {
    "addr:full":"Rue Henri Lecocq 14 Namur Namur 5000",
    "addr:housenumber":"14",
    "addr:postcode":"5000",
    "addr:street":"Rue Henri Lecocq",
    "iso:country":"BE",
    "sg:address":"Rue Henri Lecocq 14",
    "sg:city":"Namur",
    "sg:classifiers":[
        {
            "category":"Organizations",
            "subcategory":"Professional Association",
            "type":"Services"
        }
    ],
    "sg:phone":"+32 71 73 66 22",
    "sg:postcode":"5000",
    "sg:province":"Namur",
    "sg:tags":[
        "trade-union",
        "federation"
    ],
    "wof:name":"G.r.a.c.q. Asbl",
    "wof:placetype":"venue"
},
  "geometry": {"coordinates":[4.8419218063,50.4603500366],"type":"Point"}
}