{
  "type": "Feature",
  "properties": {
    "iso:country":"BE",
    "sg:address":"Kattestraat 21ba",
    "sg:city":"Aalst",
    "sg:orig_category":"Pharmaciens",
    "sg:phone":"+32 53 21 54 25",
    "sg:postcode":"9300",
    "sg:province":"Oost-Vlaanderen",
    "wof:name":"Apotheek De Valkeneer",
    "wof:placetype":"venue"
},
  "geometry": {"coordinates":[4.0383210182,50.9391098022],"type":"Point"}
}