{
  "type": "Feature",
  "properties": {
    "iso:country":"BE",
    "sg:address":"Tijl Uilenspiegelpad 45",
    "sg:city":"Rotselaar (wezemaal)",
    "sg:classifiers":[
        {
            "category":"Retail",
            "subcategory":"Event Space",
            "type":"Services"
        }
    ],
    "sg:phone":"+32 16 58 15 71",
    "sg:postcode":"3111",
    "sg:province":"Vlaams-Brabant",
    "sg:tags":[
        "organisation"
    ],
    "wof:name":"Creasons",
    "wof:placetype":"venue"
},
  "geometry": {"coordinates":[4.7839250565,50.9530754089],"type":"Point"}
}