{
  "type": "Feature",
  "properties": {
    "addr:full":"Doorniksewijk 26 Kortrijk West-Vlaanderen 8500",
    "addr:housenumber":"26",
    "addr:postcode":"8500",
    "addr:street":"Doorniksewijk",
    "iso:country":"BE",
    "sg:address":"Doorniksewijk 26",
    "sg:city":"Kortrijk",
    "sg:orig_category":"Architectes",
    "sg:phone":"+32 56 21 86 07",
    "sg:postcode":"8500",
    "sg:province":"West-Vlaanderen",
    "wof:name":"Tom Broekaert",
    "wof:placetype":"venue"
},
  "geometry": {"coordinates":[3.2682609558,50.8228416443],"type":"Point"}
}