{
  "type": "Feature",
  "properties": {
    "iso:country":"BE",
    "sg:address":"Rue Maurice Canon 13",
    "sg:city":"Ecaussinnes (ecaussinnes-d'enghien)",
    "sg:classifiers":[
        {
            "category":"Retail",
            "subcategory":"Funeral Services",
            "type":"Services"
        }
    ],
    "sg:phone":"+32 67 44 21 19",
    "sg:postcode":"7190",
    "sg:province":"Hainaut",
    "sg:tags":[
        "director"
    ],
    "wof:name":"Biermans Mercier",
    "wof:placetype":"venue"
},
  "geometry": {"coordinates":[4.1753687859,50.5702133179],"type":"Point"}
}