{
  "type": "Feature",
  "properties": {
    "addr:full":"Rue De Pi\u00e9train 3 Orp-jauche (noduwez) Brabant Wallon 1350",
    "addr:housenumber":"3",
    "addr:postcode":"1350",
    "addr:street":"Rue De Pie\u0301Train",
    "iso:country":"BE",
    "sg:address":"Rue De Pi\u00e9train 3",
    "sg:city":"Orp-jauche (noduwez)",
    "sg:classifiers":[
        {
            "category":"Communications",
            "subcategory":"News Services",
            "type":"Services"
        }
    ],
    "sg:phone":"+32 19 65 59 88",
    "sg:postcode":"1350",
    "sg:province":"Brabant Wallon",
    "sg:tags":[
        "agency"
    ],
    "wof:name":"Capricorn Image Products Sprl",
    "wof:placetype":"venue"
},
  "geometry": {"coordinates":[4.97920084,50.6738891602],"type":"Point"}
}