{
  "type": "Feature",
  "properties": {
    "iso:country":"BE",
    "sg:address":"Walshoutemstraat 75",
    "sg:city":"Landen (walshoutem)",
    "sg:classifiers":[
        {
            "category":"Social Services",
            "subcategory":"Retirement Home",
            "type":"Services"
        }
    ],
    "sg:phone":"+32 11 88 05 60",
    "sg:postcode":"3401",
    "sg:province":"Vlaams-Brabant",
    "sg:tags":[
        "residence"
    ],
    "wof:name":"Huize Zevenbronnen R.v.t.-r.o.b. Vzw",
    "wof:placetype":"venue"
},
  "geometry": {"coordinates":[5.0890021324,50.7201271057],"type":"Point"}
}