{
  "type": "Feature",
  "properties": {
    "iso:country":"BE",
    "sg:address":"Bethunestraat 1",
    "sg:city":"Poperinge",
    "sg:orig_category":"Varkenskwekers",
    "sg:phone":"+32 57 33 31 40",
    "sg:postcode":"8970",
    "sg:province":"West-Vlaanderen",
    "wof:name":"Leon Quaghebeur",
    "wof:placetype":"venue"
},
  "geometry": {"coordinates":[2.7031199932,50.829990387],"type":"Point"}
}