{
  "type": "Feature",
  "properties": {
    "iso:country":"BE",
    "sg:address":"Rue Des R\u00e9sidences 19",
    "sg:city":"Jemeppe-sur-sambre (moustier-sur-sambre)",
    "sg:classifiers":[
        {
            "category":"Health Services",
            "subcategory":"Health Practitioner",
            "type":"Services"
        }
    ],
    "sg:phone":"+32 71 78 74 97",
    "sg:postcode":"5190",
    "sg:province":"Namur",
    "sg:tags":[
        "physiotherapist"
    ],
    "wof:name":"Herreman G",
    "wof:placetype":"venue"
},
  "geometry": {"coordinates":[4.6894259453,50.4568367004],"type":"Point"}
}