{
  "type": "Feature",
  "properties": {
    "iso:country":"BE",
    "sg:address":"Meersestraat 14",
    "sg:city":"Horebeke (sint-maria-horebeke)",
    "sg:classifiers":[
        {
            "category":"Banks & Credit Unions",
            "subcategory":"Investment Brokerage",
            "type":"Services"
        }
    ],
    "sg:phone":"+32 55 49 76 10",
    "sg:postcode":"9667",
    "sg:province":"Oost-Vlaanderen",
    "sg:tags":[
        "fence"
    ],
    "wof:name":"Hertegonne Rudy",
    "wof:placetype":"venue"
},
  "geometry": {"coordinates":[3.7074139118,50.8423194885],"type":"Point"}
}