{
  "type": "Feature",
  "properties": {
    "addr:full":"Chauss\u00e9e De Wavre 1077 Bruxelles (auderghem) Bruxelles-Capitale 1160",
    "addr:postcode":"1077;1160",
    "addr:street":"Chausse\u0301E De Wavre",
    "iso:country":"BE",
    "sg:address":"Chauss\u00e9e De Wavre 1077",
    "sg:city":"Bruxelles (auderghem)",
    "sg:classifiers":[
        {
            "category":"Social Services",
            "type":"Services"
        }
    ],
    "sg:phone":"+32 2 629 27 50",
    "sg:postcode":"1160",
    "sg:province":"Bruxelles-Capitale",
    "wof:name":"Uitstraling Permanente Vorming Vzw",
    "wof:placetype":"venue"
},
  "geometry": {"coordinates":[4.3996977806,50.8244514465],"type":"Point"}
}