{
  "type": "Feature",
  "properties": {
    "iso:country":"BE",
    "sg:address":"Espendonk 33",
    "sg:city":"Arendonk",
    "sg:orig_category":"Kapsalons",
    "sg:phone":"+32 14 67 93 06",
    "sg:postcode":"2370",
    "sg:province":"Antwerpen",
    "wof:name":"Marie Cuypers",
    "wof:placetype":"venue"
},
  "geometry": {"coordinates":[5.0908727646,51.3196983337],"type":"Point"}
}