{
  "type": "Feature",
  "properties": {
    "addr:full":"Rue De Bomer\u00c9e 142b2 Charleroi Hainaut 6032",
    "addr:housenumber":"142b2",
    "addr:postcode":"6032",
    "addr:street":"Rue De Bomere\u0301E;Hainaut",
    "iso:country":"BE",
    "sg:address":"Rue De Bomer\u00c9e 142b2",
    "sg:city":"Charleroi",
    "sg:orig_category":"Experts-comptables",
    "sg:phone":"+32 71 43 92 28",
    "sg:postcode":"6032",
    "sg:province":"Hainaut",
    "wof:name":"Nathalie Vanhoorde",
    "wof:placetype":"venue"
},
  "geometry": {"coordinates":[4.3987321854,50.3722915649],"type":"Point"}
}