{
  "type": "Feature",
  "properties": {
    "iso:country":"BE",
    "sg:address":"Boulevard Du R\u00e9gent 47-48",
    "sg:city":"Bruxelles",
    "sg:classifiers":[
        {
            "category":"Banks & Credit Unions",
            "subcategory":"Bureau De Change",
            "type":"Services"
        }
    ],
    "sg:phone":"+32 2 511 84 10",
    "sg:postcode":"1000",
    "sg:province":"Bruxelles-Capitale",
    "sg:tags":[
        "belgian",
        "-",
        "broker",
        "exchange"
    ],
    "wof:name":"Havaux Sa",
    "wof:placetype":"venue"
},
  "geometry": {"coordinates":[4.368885994,50.8472061157],"type":"Point"}
}