{
  "type": "Feature",
  "properties": {
    "iso:country":"BE",
    "sg:address":"Ambachtsweg 36",
    "sg:city":"Merelbeke",
    "sg:classifiers":[
        {
            "category":"Professional",
            "subcategory":"Computer Services",
            "type":"Services"
        }
    ],
    "sg:phone":"+32 9 252 63 65",
    "sg:postcode":"9820",
    "sg:province":"Oost-Vlaanderen",
    "sg:tags":[
        "network"
    ],
    "wof:name":"Eds",
    "wof:placetype":"venue"
},
  "geometry": {"coordinates":[3.7621281147,50.9923248291],"type":"Point"}
}