{
  "type": "Feature",
  "properties": {
    "iso:country":"BE",
    "sg:address":"Chauss\u00c9e De Wavre 1530",
    "sg:city":"Oudergem/auderghem",
    "sg:orig_category":"Bloemen and planten",
    "sg:phone":"+32 2 672 01 62",
    "sg:postcode":"1160",
    "sg:province":"Bruxelles-Capitale",
    "wof:name":"Phillys Flor & Gardens",
    "wof:placetype":"venue"
},
  "geometry": {"coordinates":[4.4212532043,50.8175849915],"type":"Point"}
}