{
  "type": "Feature",
  "properties": {
    "addr:full":"Hees 10b1 Hamont-achel Limburg 3930",
    "addr:housenumber":"10b1",
    "addr:postcode":"3930",
    "addr:street":"Hees",
    "iso:country":"BE",
    "sg:address":"Hees 10b1",
    "sg:city":"Hamont-achel",
    "sg:orig_category":"Eleveurs and marchands de porcs. Eleveurs de bovins",
    "sg:phone":"+32 11 44 53 04",
    "sg:postcode":"3930",
    "sg:province":"Limburg",
    "wof:name":"Theo Joosten",
    "wof:placetype":"venue"
},
  "geometry": {"coordinates":[5.5450549126,51.2511863708],"type":"Point"}
}