{
  "type": "Feature",
  "properties": {
    "iso:country":"BE",
    "sg:address":"De Heuvels 11",
    "sg:city":"Brasschaat",
    "sg:orig_category":"Warenhuizen",
    "sg:phone":"+32 3 651 58 96",
    "sg:postcode":"2930",
    "sg:province":"Antwerpen",
    "wof:name":"Robert Lammens",
    "wof:placetype":"venue"
},
  "geometry": {"coordinates":[4.5052428246,51.2888298035],"type":"Point"}
}