{
  "type": "Feature",
  "properties": {
    "addr:full":"Zakstraat 86 Dilbeek Vlaams-Brabant 1700",
    "addr:housenumber":"86",
    "addr:postcode":"1700",
    "addr:street":"Zakstraat",
    "iso:country":"BE",
    "sg:address":"Zakstraat 86",
    "sg:city":"Dilbeek",
    "sg:orig_category":"V\u00e9los. Agences d'exp\u00e9dition",
    "sg:phone":"+32 2 569 13 96",
    "sg:postcode":"1700",
    "sg:province":"Vlaams-Brabant",
    "wof:name":"Intercycle",
    "wof:placetype":"venue"
},
  "geometry": {"coordinates":[4.2435131073,50.8370819092],"type":"Point"}
}