{
  "type": "Feature",
  "properties": {
    "addr:full":"Chemin Des Trihes 19 Saint-georges-sur-meuse Li\u00e8ge 4470",
    "addr:housenumber":"19",
    "addr:postcode":"4470",
    "addr:street":"Chemin Des Trihes",
    "iso:country":"BE",
    "sg:address":"Chemin Des Trihes 19",
    "sg:city":"Saint-georges-sur-meuse",
    "sg:orig_category":"Instituts de beaut\u00e9",
    "sg:phone":"+32 4 275 00 03",
    "sg:postcode":"4470",
    "sg:province":"Li\u00e8ge",
    "wof:name":"Danielle Pedoux",
    "wof:placetype":"venue"
},
  "geometry": {"coordinates":[5.3852300644,50.6066856384],"type":"Point"}
}