{
  "type": "Feature",
  "properties": {
    "addr:full":"Lesagestraat 12a Steenokkerzeel Vlaams-Brabant 1820",
    "addr:housenumber":"12a",
    "addr:postcode":"1820",
    "addr:street":"Lesagestraat",
    "iso:country":"BE",
    "sg:address":"Lesagestraat 12a",
    "sg:city":"Steenokkerzeel",
    "sg:classifiers":[
        {
            "category":"Retail",
            "subcategory":"Animal Services",
            "type":"Services"
        }
    ],
    "sg:phone":"+32 2 751 87 41",
    "sg:postcode":"1820",
    "sg:province":"Vlaams-Brabant",
    "sg:tags":[
        "grooming",
        "-",
        "dog"
    ],
    "wof:name":"Chantal",
    "wof:placetype":"venue"
},
  "geometry": {"coordinates":[4.5129599571,50.9208145142],"type":"Point"}
}