{
  "type": "Feature",
  "properties": {
    "addr:full":"Bitterstraat 2 Jabbeke West-Vlaanderen 8490",
    "addr:housenumber":"2",
    "addr:postcode":"8490",
    "addr:street":"Bitterstraat",
    "iso:country":"BE",
    "sg:address":"Bitterstraat 2",
    "sg:city":"Jabbeke",
    "sg:classifiers":[
        {
            "category":"Health Services",
            "subcategory":"Health Practitioner",
            "type":"Services"
        }
    ],
    "sg:phone":"+32 50 81 33 51",
    "sg:postcode":"8490",
    "sg:province":"West-Vlaanderen",
    "sg:tags":[
        "physiotherapist"
    ],
    "wof:name":"Van Huele Ann",
    "wof:placetype":"venue"
},
  "geometry": {"coordinates":[3.0881230831,51.1820335388],"type":"Point"}
}