{
  "type": "Feature",
  "properties": {
    "iso:country":"BE",
    "sg:address":"Route De Str\u00c9e 10",
    "sg:city":"Modave",
    "sg:orig_category":"Artsen and specialisten",
    "sg:phone":"+32 85 51 10 61",
    "sg:postcode":"4577",
    "sg:province":"Li\u00e8ge",
    "wof:name":"Carole Schumesch",
    "wof:placetype":"venue"
},
  "geometry": {"coordinates":[5.3236222267,50.4897689819],"type":"Point"}
}