{
  "type": "Feature",
  "properties": {
    "addr:full":"Schepen Dejonghstraat 1 Sint-truiden Limburg 3800",
    "addr:housenumber":"1",
    "addr:postcode":"3800",
    "addr:street":"Schepen Dejonghstraat",
    "iso:country":"BE",
    "sg:address":"Schepen Dejonghstraat 1",
    "sg:city":"Sint-truiden",
    "sg:classifiers":[
        {
            "category":"Shopping",
            "subcategory":"Shoes",
            "type":"Retail Goods"
        }
    ],
    "sg:phone":"+32 11 67 29 31",
    "sg:postcode":"3800",
    "sg:province":"Limburg",
    "sg:tags":[
        "slipper",
        "-"
    ],
    "wof:name":"Carthago Schoenen",
    "wof:placetype":"venue"
},
  "geometry": {"coordinates":[5.1890897751,50.8140182495],"type":"Point"}
}