{
  "type": "Feature",
  "properties": {
    "iso:country":"BE",
    "sg:address":"Groendalstraat 17",
    "sg:city":"Antwerpen",
    "sg:classifiers":[
        {
            "category":"Shopping",
            "subcategory":"Clothing, Apparel, & Fashions",
            "type":"Retail Goods"
        }
    ],
    "sg:phone":"+32 3 225 16 19",
    "sg:postcode":"2000",
    "sg:province":"Antwerpen",
    "sg:tags":[
        "v\u00eatements",
        "pour",
        "dame"
    ],
    "wof:name":"Huis Sugar",
    "wof:placetype":"venue"
},
  "geometry": {"coordinates":[4.4050660133,51.217666626],"type":"Point"}
}