{
  "type": "Feature",
  "properties": {
    "addr:full":"Broekstraat 120 Buggenhout Oost-Vlaanderen 9255",
    "addr:housenumber":"120",
    "addr:postcode":"9255",
    "addr:street":"Broekstraat",
    "iso:country":"BE",
    "sg:address":"Broekstraat 120",
    "sg:city":"Buggenhout",
    "sg:classifiers":[
        {
            "category":"Place Of Worship",
            "subcategory":"Church",
            "type":"Public Place"
        }
    ],
    "sg:phone":"+32 52 35 86 58",
    "sg:postcode":"9255",
    "sg:province":"Oost-Vlaanderen",
    "sg:tags":[
        "article",
        "baptismal"
    ],
    "wof:name":"Creabox",
    "wof:placetype":"venue"
},
  "geometry": {"coordinates":[4.1677398682,50.988368988],"type":"Point"}
}