{
  "type": "Feature",
  "properties": {
    "iso:country":"BE",
    "sg:address":"Karel De Bondtlaan 4",
    "sg:city":"Gent (drongen)",
    "sg:classifiers":[
        {
            "category":"Professional",
            "subcategory":"Accounting & Tax Preparation",
            "type":"Services"
        }
    ],
    "sg:phone":"+32 9 281 14 18",
    "sg:postcode":"9031",
    "sg:province":"Oost-Vlaanderen",
    "sg:tags":[
        "bookkeeper"
    ],
    "wof:name":"Van Laere A-m",
    "wof:placetype":"venue"
},
  "geometry": {"coordinates":[3.6630249023,51.0503692627],"type":"Point"}
}