{
  "type": "Feature",
  "properties": {
    "addr:full":"Rue Des Tayettes 28 Gerpinnes Hainaut 6280",
    "addr:housenumber":"28",
    "addr:postcode":"6280",
    "addr:street":"Rue Des Tayettes;Hainaut",
    "iso:country":"BE",
    "sg:address":"Rue Des Tayettes 28",
    "sg:city":"Gerpinnes",
    "sg:orig_category":"Traitements param\u00e9dicaux",
    "sg:phone":"+32 71 50 24 07",
    "sg:postcode":"6280",
    "sg:province":"Hainaut",
    "wof:name":"L. Depaepe",
    "wof:placetype":"venue"
},
  "geometry": {"coordinates":[4.4865779877,50.3413352966],"type":"Point"}
}