{
  "type": "Feature",
  "properties": {
    "addr:full":"Rue De L'a\u00e9rodrome 62 Bruxelles Bruxelles-Capitale 1130",
    "addr:housenumber":"62",
    "addr:postcode":"1130",
    "addr:street":"Rue De L'Ae \u0301Rodrome",
    "iso:country":"BE",
    "sg:address":"Rue De L'a\u00e9rodrome 62",
    "sg:city":"Bruxelles",
    "sg:classifiers":[
        {
            "category":"Retail",
            "subcategory":"Auto Repair",
            "type":"Services"
        }
    ],
    "sg:phone":"+32 2 705 18 56",
    "sg:postcode":"1130",
    "sg:province":"Bruxelles-Capitale",
    "sg:tags":[
        "garage"
    ],
    "wof:name":"Duyck En Zonen Nv",
    "wof:placetype":"venue"
},
  "geometry": {"coordinates":[4.4273548126,50.8873100281],"type":"Point"}
}