{
  "type": "Feature",
  "properties": {
    "iso:country":"BE",
    "sg:address":"Lariksdreef 85",
    "sg:city":"Schoten",
    "sg:classifiers":[
        {
            "category":"Building & Trades",
            "subcategory":"Pest Control",
            "type":"Services"
        }
    ],
    "sg:phone":"+32 3 685 06 39",
    "sg:postcode":"2900",
    "sg:province":"Antwerpen",
    "sg:tags":[
        "painting",
        "contractor"
    ],
    "wof:name":"Vandenbroeck W",
    "wof:placetype":"venue"
},
  "geometry": {"coordinates":[4.519133091,51.26927948],"type":"Point"}
}