{
  "type": "Feature",
  "properties": {
    "iso:country":"BE",
    "sg:address":"Rue Madame 33",
    "sg:city":"Beaumont",
    "sg:classifiers":[
        {
            "category":"Food & Beverages",
            "subcategory":"Groceries & Convenience Stores",
            "type":"Retail Goods"
        }
    ],
    "sg:phone":"+32 71 58 85 65",
    "sg:postcode":"6500",
    "sg:province":"Hainaut",
    "sg:tags":[
        "grocer"
    ],
    "wof:name":"Anne-catherine (chez)",
    "wof:placetype":"venue"
},
  "geometry": {"coordinates":[4.2394618988,50.2372550964],"type":"Point"}
}