{
  "type": "Feature",
  "properties": {
    "iso:country":"BE",
    "sg:address":"Graaf De Theuxlaan 8a",
    "sg:city":"Heusden-zolder",
    "sg:classifiers":[
        {
            "category":"Insurance",
            "subcategory":"Insurance Agent",
            "type":"Services"
        }
    ],
    "sg:phone":"+32 11 42 29 88",
    "sg:postcode":"3550",
    "sg:province":"Limburg",
    "sg:tags":[
        "verzekeringsmakelaars",
        "expert"
    ],
    "wof:name":"Hagelsteens",
    "wof:placetype":"venue"
},
  "geometry": {"coordinates":[5.2677588463,51.025478363],"type":"Point"}
}