{
  "type": "Feature",
  "properties": {
    "iso:country":"BE",
    "sg:address":"Schoenlapperstraat 2",
    "sg:city":"Gent",
    "sg:classifiers":[
        {
            "category":"Transit Center",
            "subcategory":"Freight",
            "type":"Transportation"
        }
    ],
    "sg:phone":"+32 9 269 04 07",
    "sg:postcode":"9000",
    "sg:province":"Oost-Vlaanderen",
    "sg:tags":[
        "import",
        "export",
        "-"
    ],
    "wof:name":"Step & Go",
    "wof:placetype":"venue"
},
  "geometry": {"coordinates":[3.7231578827,51.0565834045],"type":"Point"}
}