{
  "type": "Feature",
  "properties": {
    "iso:country":"BE",
    "sg:address":"Avenue De La Closi\u00e8re 11",
    "sg:city":"Waterloo",
    "sg:classifiers":[
        {
            "category":"Personal",
            "subcategory":"Massage",
            "type":"Services"
        }
    ],
    "sg:phone":"+32 2 354 18 54",
    "sg:postcode":"1410",
    "sg:province":"Brabant Wallon",
    "wof:name":"De Pierpont B",
    "wof:placetype":"venue"
},
  "geometry": {"coordinates":[4.3883662224,50.7087631226],"type":"Point"}
}