{
  "type": "Feature",
  "properties": {
    "iso:country":"BE",
    "sg:address":"Avenue De Bruxelles 49",
    "sg:city":"Tubize",
    "sg:orig_category":"Herstellingen and onderhoud van auto's Voertuigen",
    "sg:phone":"+32 2 355 86 07",
    "sg:postcode":"1480",
    "sg:province":"Brabant Wallon",
    "wof:name":"Ledermann",
    "wof:placetype":"venue"
},
  "geometry": {"coordinates":[4.2040262222,50.6952705383],"type":"Point"}
}