{
  "type": "Feature",
  "properties": {
    "addr:full":"Veemarkt 27 Tienen Vlaams-Brabant 3300",
    "addr:housenumber":"27",
    "addr:postcode":"3300",
    "addr:street":"Veemarkt",
    "iso:country":"BE",
    "sg:address":"Veemarkt 27",
    "sg:city":"Tienen",
    "sg:orig_category":"V\u00eatements pour Dames. V\u00eatements pour Hommes",
    "sg:phone":"+32 16 81 16 49",
    "sg:postcode":"3300",
    "sg:province":"Vlaams-Brabant",
    "wof:name":"Argo Fashion",
    "wof:placetype":"venue"
},
  "geometry": {"coordinates":[4.939789772,50.8052406311],"type":"Point"}
}