{
  "type": "Feature",
  "properties": {
    "iso:country":"BE",
    "sg:address":"Rue Des Ferons 5",
    "sg:city":"Mettet (biesme)",
    "sg:classifiers":[
        {
            "category":"Professional",
            "subcategory":"Management & Consulting",
            "type":"Services"
        }
    ],
    "sg:phone":"+32 71 72 72 58",
    "sg:postcode":"5640",
    "sg:province":"Namur",
    "sg:tags":[
        "-",
        "processing",
        "data",
        "consultant"
    ],
    "wof:name":"Delforge M",
    "wof:placetype":"venue"
},
  "geometry": {"coordinates":[4.6165070534,50.3464775085],"type":"Point"}
}