{
  "type": "Feature",
  "properties": {
    "addr:full":"Tongersesteenweg 259 Sint-truiden Limburg 3800",
    "addr:housenumber":"259",
    "addr:postcode":"sint-truiden;3800",
    "addr:street":"Tongersesteenweg",
    "iso:country":"BE",
    "sg:address":"Tongersesteenweg 259",
    "sg:city":"Sint-truiden",
    "sg:classifiers":[
        {
            "category":"Insurance",
            "subcategory":"Insurance Agent",
            "type":"Services"
        }
    ],
    "sg:phone":"+32 11 68 68 97",
    "sg:postcode":"3800",
    "sg:province":"Limburg",
    "sg:tags":[
        "verzekeringsmakelaars",
        "expert"
    ],
    "wof:name":"Limbratex",
    "wof:placetype":"venue"
},
  "geometry": {"coordinates":[5.2143378258,50.8103065491],"type":"Point"}
}