{
  "type": "Feature",
  "properties": {
    "addr:full":"Rosbergstraat 8 Tongeren (mal) Limburg 3700",
    "addr:housenumber":"8",
    "addr:postcode":"3700",
    "addr:street":"Rosbergstraat;Mal Limburg",
    "iso:country":"BE",
    "sg:address":"Rosbergstraat 8",
    "sg:city":"Tongeren (mal)",
    "sg:classifiers":[
        {
            "category":"Building & Trades",
            "subcategory":"Locksmith",
            "type":"Services"
        }
    ],
    "sg:phone":"+32 12 26 25 33",
    "sg:postcode":"3700",
    "sg:province":"Limburg",
    "sg:tags":[
        "material",
        "road"
    ],
    "wof:name":"Maurissen H",
    "wof:placetype":"venue"
},
  "geometry": {"coordinates":[5.4636240005,50.7807197571],"type":"Point"}
}