{
  "type": "Feature",
  "properties": {
    "addr:full":"Fostierlaan 27 Ronse/renaix Oost-Vlaanderen 9600",
    "addr:housenumber":"27",
    "addr:postcode":"9600",
    "addr:street":"Fostierlaan",
    "iso:country":"BE",
    "sg:address":"Fostierlaan 27",
    "sg:city":"Ronse/renaix",
    "sg:orig_category":"Artsen and specialisten",
    "sg:phone":"+32 55 21 21 84",
    "sg:postcode":"9600",
    "sg:province":"Oost-Vlaanderen",
    "wof:name":"Marcel Bersez/m. Bersez",
    "wof:placetype":"venue"
},
  "geometry": {"coordinates":[3.5976688862,50.744846344],"type":"Point"}
}