{
  "type": "Feature",
  "properties": {
    "iso:country":"BE",
    "sg:address":"Werbrouckstraat 1",
    "sg:city":"Antwerpen",
    "sg:classifiers":[
        {
            "category":"Food & Beverages",
            "subcategory":"Fruits & Vegetables",
            "type":"Retail Goods"
        }
    ],
    "sg:phone":"+32 3 238 68 84",
    "sg:postcode":"2020",
    "sg:province":"Antwerpen",
    "sg:tags":[
        "groenten"
    ],
    "wof:name":"Huis Sec",
    "wof:placetype":"venue"
},
  "geometry": {"coordinates":[4.3759598732,51.1873703003],"type":"Point"}
}