{
  "type": "Feature",
  "properties": {
    "addr:full":"Vogelzang 4 Laakdal Antwerpen 2430",
    "addr:housenumber":"4",
    "addr:postcode":"2430",
    "addr:street":"Vogelzang",
    "iso:country":"BE",
    "sg:address":"Vogelzang 4",
    "sg:city":"Laakdal",
    "sg:orig_category":"Ordinateurs and \u00e9quipement informatique",
    "sg:phone":"+32 13 67 47 46",
    "sg:postcode":"2430",
    "sg:province":"Antwerpen",
    "wof:name":"Humsoft",
    "wof:placetype":"venue"
},
  "geometry": {"coordinates":[5.0194439888,51.0826873779],"type":"Point"}
}