{
  "type": "Feature",
  "properties": {
    "iso:country":"BE",
    "sg:address":"Burggravenlaan 213",
    "sg:city":"Gent",
    "sg:classifiers":[
        {
            "category":"Communications",
            "subcategory":"Film & Video Production",
            "type":"Services"
        }
    ],
    "sg:phone":"+32 9 222 11 97",
    "sg:postcode":"9000",
    "sg:province":"Oost-Vlaanderen",
    "sg:tags":[
        "commerce",
        "electrom\u00e9nager",
        "t\u00e9l\u00e9visions",
        "equipement",
        "pour",
        "radio",
        "diver"
    ],
    "wof:name":"Linkens Koeltechniek",
    "wof:placetype":"venue"
},
  "geometry": {"coordinates":[3.7252709866,51.0322914124],"type":"Point"}
}