{
  "type": "Feature",
  "properties": {
    "addr:full":"Avenue Des Immortelles 1 Bruxelles (anderlecht) Bruxelles-Capitale 1070",
    "addr:housenumber":"1",
    "addr:postcode":"1070",
    "addr:street":"Avenue Des Immortelles",
    "iso:country":"BE",
    "sg:address":"Avenue Des Immortelles 1",
    "sg:city":"Bruxelles (anderlecht)",
    "sg:classifiers":[
        {
            "category":"Health Services",
            "subcategory":"Health Practitioner",
            "type":"Services"
        }
    ],
    "sg:phone":"+32 2 523 51 08",
    "sg:postcode":"1070",
    "sg:province":"Bruxelles-Capitale",
    "sg:tags":[
        "physiotherapist"
    ],
    "wof:name":"Fosset B",
    "wof:placetype":"venue"
},
  "geometry": {"coordinates":[4.2822461128,50.8173942566],"type":"Point"}
}