{
  "type": "Feature",
  "properties": {
    "addr:full":"Jozef Mertensstraat 90a Dilbeek (groot - Bijgaarden) Vlaams-Brabant 1702",
    "addr:housenumber":"90a;1702",
    "addr:street":"Jozef Mertensstraat;Groot Bijgaarden Vlaams-Brabant",
    "iso:country":"BE",
    "sg:address":"Jozef Mertensstraat 90a",
    "sg:city":"Dilbeek (groot - Bijgaarden)",
    "sg:classifiers":[
        {
            "category":"Real Estate",
            "subcategory":"Surveying",
            "type":"Services"
        }
    ],
    "sg:phone":"+32 2 466 09 91",
    "sg:postcode":"1702",
    "sg:province":"Vlaams-Brabant",
    "sg:tags":[
        "lettering",
        "letter"
    ],
    "wof:name":"Publiaplic Sprl",
    "wof:placetype":"venue"
},
  "geometry": {"coordinates":[4.2542181015,50.8771209717],"type":"Point"}
}