{
  "type": "Feature",
  "properties": {
    "iso:country":"BE",
    "sg:address":"Eksaardedorp 23",
    "sg:city":"Lokeren",
    "sg:orig_category":"Pain, p\u00e2tisseries and confiseries",
    "sg:phone":"+32 9 346 83 39",
    "sg:postcode":"9160",
    "sg:province":"Oost-Vlaanderen",
    "wof:name":"Bakkerij Bolleken",
    "wof:placetype":"venue"
},
  "geometry": {"coordinates":[3.962346077,51.1147918701],"type":"Point"}
}