{
  "type": "Feature",
  "properties": {
    "addr:full":"50 Nieuwstraat 3540 Herk-de-stad 50",
    "addr:housenumber":"50",
    "addr:postcode":"3540",
    "addr:street":"Nieuwstraat",
    "iso:country":"BE",
    "sg:address":"50",
    "sg:city":"Nieuwstraat 3540 Herk-de-stad",
    "sg:classifiers":[
        {
            "category":"Building & Trades",
            "subcategory":"Construction",
            "type":"Services"
        }
    ],
    "sg:phone":"+32 13 44 12 29",
    "sg:postcode":"50",
    "sg:tags":[
        "work",
        "public"
    ],
    "wof:name":"Algemene Ondernemingen Claes Bvba",
    "wof:placetype":"venue"
},
  "geometry": {"coordinates":[5.1370749474,50.939250946],"type":"Point"}
}