{
  "type": "Feature",
  "properties": {
    "addr:full":"Kruisstraat 21 Meeuwen-gruitrode Limburg 3670",
    "addr:housenumber":"21",
    "addr:postcode":"3670",
    "addr:street":"Kruisstraat",
    "iso:country":"BE",
    "sg:address":"Kruisstraat 21",
    "sg:city":"Meeuwen-gruitrode",
    "sg:orig_category":"Architectes",
    "sg:phone":"+32 11 79 22 25",
    "sg:postcode":"3670",
    "sg:province":"Limburg",
    "wof:name":"Benny Eerdekens",
    "wof:placetype":"venue"
},
  "geometry": {"coordinates":[5.5208930969,51.0896873474],"type":"Point"}
}