{
  "type": "Feature",
  "properties": {
    "iso:country":"BE",
    "sg:address":"Heiveld 12",
    "sg:city":"Tessenderlo",
    "sg:classifiers":[
        {
            "category":"Arena",
            "subcategory":"Sports Club",
            "type":"Entertainment"
        }
    ],
    "sg:phone":"+32 13 32 17 63",
    "sg:postcode":"3980",
    "sg:province":"Limburg",
    "sg:tags":[
        "de"
    ],
    "wof:name":"B.c. Sportagon",
    "wof:placetype":"venue"
},
  "geometry": {"coordinates":[5.0547227859,51.0277862549],"type":"Point"}
}