{
  "type": "Feature",
  "properties": {
    "addr:full":"Avenue Beau S\u00e9jour 18 Bruxelles (uccle) Bruxelles-Capitale 1180",
    "addr:housenumber":"18",
    "addr:postcode":"1180",
    "addr:street":"Avenue Beau Se\u0301Jour",
    "iso:country":"BE",
    "sg:address":"Avenue Beau S\u00e9jour 18",
    "sg:city":"Bruxelles (uccle)",
    "sg:classifiers":[
        {
            "category":"Professional",
            "subcategory":"Management & Consulting",
            "type":"Services"
        }
    ],
    "sg:phone":"+32 2 375 26 62",
    "sg:postcode":"1180",
    "sg:province":"Bruxelles-Capitale",
    "sg:tags":[
        "-",
        "processing",
        "data",
        "consultant"
    ],
    "wof:name":"Panier N",
    "wof:placetype":"venue"
},
  "geometry": {"coordinates":[4.3690748215,50.8093223572],"type":"Point"}
}