{
  "type": "Feature",
  "properties": {
    "iso:country":"BE",
    "sg:address":"Vaartdijk 25",
    "sg:city":"Mechelen",
    "sg:classifiers":[
        {
            "category":"Professional",
            "subcategory":"Lawyer & Legal Services",
            "type":"Services"
        }
    ],
    "sg:phone":"+32 15 41 22 00",
    "sg:postcode":"2800",
    "sg:province":"Antwerpen",
    "sg:tags":[
        "notary"
    ],
    "wof:name":"Leemans M",
    "wof:placetype":"venue"
},
  "geometry": {"coordinates":[4.4738907814,51.0201911926],"type":"Point"}
}