{
  "type": "Feature",
  "properties": {
    "iso:country":"BE",
    "sg:address":"Hoogstraat 233",
    "sg:city":"Sint-niklaas",
    "sg:orig_category":"Boekhouders",
    "sg:phone":"+32 3 776 19 08",
    "sg:postcode":"9100",
    "sg:province":"Oost-Vlaanderen",
    "wof:name":"Dani\u00cbl De Maagd",
    "wof:placetype":"venue"
},
  "geometry": {"coordinates":[4.1398119926,51.1908416748],"type":"Point"}
}