{
  "type": "Feature",
  "properties": {
    "iso:country":"BE",
    "sg:address":"Abdijstraat 88",
    "sg:city":"Antwerpen",
    "sg:orig_category":"Slagers Voedingsspeciaalzaken",
    "sg:phone":"+32 3 238 20 85",
    "sg:postcode":"2020",
    "sg:province":"Antwerpen",
    "wof:name":"Dirk Verlinde",
    "wof:placetype":"venue"
},
  "geometry": {"coordinates":[4.3808660507,51.1890602112],"type":"Point"}
}