{
  "type": "Feature",
  "properties": {
    "addr:full":"Place Du March\u00c9 1 Vaux-sur-sure Luxembourg 6640",
    "addr:housenumber":"1",
    "addr:postcode":"6640",
    "addr:street":"Place Du Marche\u0301",
    "iso:country":"BE",
    "sg:address":"Place Du March\u00c9 1",
    "sg:city":"Vaux-sur-sure",
    "sg:orig_category":"S\u00e9lection de personnel and placement",
    "sg:phone":"+32 61 25 00 14",
    "sg:postcode":"6640",
    "sg:province":"Luxembourg",
    "wof:name":"Ale",
    "wof:placetype":"venue"
},
  "geometry": {"coordinates":[5.5652179718,49.9103622437],"type":"Point"}
}