{
  "type": "Feature",
  "properties": {
    "iso:country":"BE",
    "sg:address":"Rue Du Tchet 63",
    "sg:city":"Farciennes",
    "sg:classifiers":[
        {
            "category":"Community Center",
            "subcategory":"Youth",
            "type":"Public Place"
        }
    ],
    "sg:phone":"+32 71 40 16 18",
    "sg:postcode":"6240",
    "sg:province":"Hainaut",
    "sg:tags":[
        "club"
    ],
    "wof:name":"Centre Jeunesse (animation & Information)",
    "wof:placetype":"venue"
},
  "geometry": {"coordinates":[4.5505552292,50.4267616272],"type":"Point"}
}