{
  "type": "Feature",
  "properties": {
    "addr:full":"Vieljaren 30 Plombieres/plombieres Li\u00e8ge 4852",
    "addr:housenumber":"30",
    "addr:postcode":"4852",
    "addr:street":"Vieljaren",
    "iso:country":"BE",
    "sg:address":"Vieljaren 30",
    "sg:city":"Plombieres/plombieres",
    "sg:orig_category":"Eleveurs de bovins. Eleveurs and marchands de porcs",
    "sg:phone":"+32 87 68 83 89",
    "sg:postcode":"4852",
    "sg:province":"Li\u00e8ge",
    "wof:name":"Paul Hausman",
    "wof:placetype":"venue"
},
  "geometry": {"coordinates":[5.9204001427,50.7230834961],"type":"Point"}
}