{
  "type": "Feature",
  "properties": {
    "addr:full":"Baron Van Der Bruggenlaan 25 Wielsbeke West-Vlaanderen 8710",
    "addr:housenumber":"25",
    "addr:postcode":"8710",
    "addr:street":"Baron Van Der Bruggenlaan;West-Vlaanderen",
    "iso:country":"BE",
    "sg:address":"Baron Van Der Bruggenlaan 25",
    "sg:city":"Wielsbeke",
    "sg:classifiers":[
        {
            "category":"Health Services",
            "subcategory":"Doctor",
            "type":"Services"
        }
    ],
    "sg:phone":"+32 56 66 97 97",
    "sg:postcode":"8710",
    "sg:province":"West-Vlaanderen",
    "sg:tags":[
        "medicinephysicians",
        "surgeon"
    ],
    "wof:name":"Geeroms Jan",
    "wof:placetype":"venue"
},
  "geometry": {"coordinates":[3.3704469204,50.9097290039],"type":"Point"}
}