{
  "type": "Feature",
  "properties": {
    "addr:full":"Landweg 3 Mechelen Antwerpen 2800",
    "addr:housenumber":"3",
    "addr:postcode":"2800",
    "addr:street":"Landweg",
    "iso:country":"BE",
    "sg:address":"Landweg 3",
    "sg:city":"Mechelen",
    "sg:classifiers":[
        {
            "category":"Professional",
            "subcategory":"Lawyer & Legal Services",
            "type":"Services"
        }
    ],
    "sg:phone":"+32 15 21 92 30",
    "sg:postcode":"2800",
    "sg:province":"Antwerpen",
    "wof:name":"Hendrickx Marc",
    "wof:placetype":"venue"
},
  "geometry": {"coordinates":[4.4542832375,51.0345840454],"type":"Point"}
}