{
  "type": "Feature",
  "properties": {
    "iso:country":"BE",
    "sg:address":"Avenue Jean Pochet 44",
    "sg:city":"Namur",
    "sg:orig_category":"Disquaires",
    "sg:phone":"+32 81 73 49 06",
    "sg:postcode":"5001",
    "sg:province":"Namur",
    "wof:name":"Michelle Hurtebize",
    "wof:placetype":"venue"
},
  "geometry": {"coordinates":[4.8179831505,50.4723510742],"type":"Point"}
}