{
  "type": "Feature",
  "properties": {
    "iso:country":"BE",
    "sg:address":"Cornelstraat 5",
    "sg:city":"Bilzen",
    "sg:classifiers":[
        {
            "category":"Cafe",
            "type":"Food & Drink"
        }
    ],
    "sg:phone":"+32 89 41 23 79",
    "sg:postcode":"3740",
    "sg:province":"Limburg",
    "sg:tags":[
        "caf\u00e9s"
    ],
    "wof:name":"Hendrik Lambrechts",
    "wof:placetype":"venue"
},
  "geometry": {"coordinates":[5.5308141708,50.8863372803],"type":"Point"}
}