{
  "type": "Feature",
  "properties": {
    "addr:full":"Rue Des R\u00e9sistants 55 Mons (saint-symphorien) Hainaut 7030",
    "addr:housenumber":"55",
    "addr:postcode":"7030",
    "addr:street":"Rue Des Re\u0301Sistants",
    "iso:country":"BE",
    "sg:address":"Rue Des R\u00e9sistants 55",
    "sg:city":"Mons (saint-symphorien)",
    "sg:classifiers":[
        {
            "category":"Banks & Credit Unions",
            "subcategory":"Investment Brokerage",
            "type":"Services"
        }
    ],
    "sg:phone":"+32 64 28 34 49",
    "sg:postcode":"7030",
    "sg:province":"Hainaut",
    "sg:tags":[
        "fence"
    ],
    "wof:name":"Julien M",
    "wof:placetype":"venue"
},
  "geometry": {"coordinates":[4.0108299255,50.4393882751],"type":"Point"}
}