{
  "type": "Feature",
  "properties": {
    "iso:country":"BE",
    "sg:address":"Rue De Houyet 205",
    "sg:city":"Beauraing",
    "sg:classifiers":[
        {
            "category":"Building & Trades",
            "subcategory":"Construction",
            "type":"Services"
        }
    ],
    "sg:phone":"+32 82 71 18 04",
    "sg:postcode":"5570",
    "sg:province":"Namur",
    "sg:tags":[
        "carpenter"
    ],
    "wof:name":"Demars R",
    "wof:placetype":"venue"
},
  "geometry": {"coordinates":[4.9564118385,50.1278343201],"type":"Point"}
}