{
  "type": "Feature",
  "properties": {
    "addr:full":"Kalvariebergstraat 23 Geel Antwerpen 2440",
    "addr:housenumber":"23",
    "addr:postcode":"2440",
    "addr:street":"Kalvariebergstraat",
    "iso:country":"BE",
    "sg:address":"Kalvariebergstraat 23",
    "sg:city":"Geel",
    "sg:classifiers":[
        {
            "category":"Cafe",
            "type":"Food & Drink"
        }
    ],
    "sg:phone":"+32 14 86 76 95",
    "sg:postcode":"2440",
    "sg:province":"Antwerpen",
    "sg:tags":[
        "caf\u00e9s"
    ],
    "wof:name":"Jozef Hillen",
    "wof:placetype":"venue"
},
  "geometry": {"coordinates":[4.9705557823,51.1053199768],"type":"Point"}
}