{
  "type": "Feature",
  "properties": {
    "addr:full":"Voie De L'ardenne 43 Chaudfontaine Li\u00e8ge 4053",
    "addr:housenumber":"43",
    "addr:postcode":"4053",
    "addr:street":"Voie De L'Ardenne",
    "iso:country":"BE",
    "sg:address":"Voie De L'ardenne 43",
    "sg:city":"Chaudfontaine",
    "sg:orig_category":"Industri\u00eble wasserijen and droogkuis",
    "sg:phone":"+32 4 367 33 78",
    "sg:postcode":"4053",
    "sg:province":"Li\u00e8ge",
    "wof:name":"Clean-embourg",
    "wof:placetype":"venue"
},
  "geometry": {"coordinates":[5.6068840027,50.5948600769],"type":"Point"}
}