{
  "type": "Feature",
  "properties": {
    "iso:country":"BE",
    "sg:address":"Tremelosesteenweg 3",
    "sg:city":"Begijnendijk",
    "sg:orig_category":"Elektrische installaties voor woningen",
    "sg:phone":"+32 16 56 80 80",
    "sg:postcode":"3130",
    "sg:province":"Vlaams-Brabant",
    "wof:name":"Design En Telecom",
    "wof:placetype":"venue"
},
  "geometry": {"coordinates":[4.7816967964,50.989780426],"type":"Point"}
}