{
  "type": "Feature",
  "properties": {
    "addr:full":"Rue Des Brasseurs 145 Namur Namur 5000",
    "addr:housenumber":"145",
    "addr:postcode":"5000",
    "addr:street":"Rue Des Brasseurs",
    "iso:country":"BE",
    "sg:address":"Rue Des Brasseurs 145",
    "sg:city":"Namur",
    "sg:classifiers":[
        {
            "category":"Insurance",
            "subcategory":"Insurance Agent",
            "type":"Services"
        }
    ],
    "sg:phone":"+32 81 65 55 91",
    "sg:postcode":"5000",
    "sg:province":"Namur",
    "sg:tags":[
        "-",
        "representative"
    ],
    "wof:name":"Bureau D'assurances Storms",
    "wof:placetype":"venue"
},
  "geometry": {"coordinates":[4.8620228767,50.4620628357],"type":"Point"}
}