{
  "type": "Feature",
  "properties": {
    "addr:full":"Rue Du Pont D'arcole 113 Charleroi Hainaut 6060",
    "addr:housenumber":"113",
    "addr:postcode":"6060",
    "addr:street":"Rue Du Pont D'Arcole;Hainaut",
    "iso:country":"BE",
    "sg:address":"Rue Du Pont D'arcole 113",
    "sg:city":"Charleroi",
    "sg:orig_category":"Brood, gebak and snoepgoed",
    "sg:phone":"+32 71 41 33 18",
    "sg:postcode":"6060",
    "sg:province":"Hainaut",
    "wof:name":"Serge Martinquet",
    "wof:placetype":"venue"
},
  "geometry": {"coordinates":[4.4977807999,50.435131073],"type":"Point"}
}