{
  "type": "Feature",
  "properties": {
    "addr:full":"Kiezelweg 121 Herk-de-stad Limburg 3540",
    "addr:housenumber":"121",
    "addr:postcode":"3540",
    "addr:street":"Kiezelweg",
    "iso:country":"BE",
    "sg:address":"Kiezelweg 121",
    "sg:city":"Herk-de-stad",
    "sg:orig_category":"Huishoudapparaten, televisies and radio's",
    "sg:phone":"+32 13 55 22 82",
    "sg:postcode":"3540",
    "sg:province":"Limburg",
    "wof:name":"Andr\u00c9 Surkijn",
    "wof:placetype":"venue"
},
  "geometry": {"coordinates":[5.1767969131,50.9575538635],"type":"Point"}
}