{
  "type": "Feature",
  "properties": {
    "addr:full":"Itterplein 3 Bree (opitter) Limburg 3960",
    "addr:housenumber":"3",
    "addr:postcode":"3960",
    "addr:street":"Itterplein",
    "iso:country":"BE",
    "sg:address":"Itterplein 3",
    "sg:city":"Bree (opitter)",
    "sg:classifiers":[
        {
            "category":"Bakery",
            "type":"Food & Drink"
        }
    ],
    "sg:postcode":"3960",
    "sg:province":"Limburg",
    "sg:tags":[
        "confectioner",
        "baker"
    ],
    "wof:name":"Dictus Johan",
    "wof:placetype":"venue"
},
  "geometry": {"coordinates":[5.5944190025,51.1405677795],"type":"Point"}
}