{
  "type": "Feature",
  "properties": {
    "iso:country":"BE",
    "sg:address":"Woestenstraat 23",
    "sg:city":"Vleteren",
    "sg:orig_category":"Eleveurs de bovins. Eleveurs and marchands de porcs",
    "sg:phone":"+32 57 40 02 73",
    "sg:postcode":"8640",
    "sg:province":"West-Vlaanderen",
    "wof:name":"Wilfried Dejonckheere",
    "wof:placetype":"venue"
},
  "geometry": {"coordinates":[2.7401180267,50.9295082092],"type":"Point"}
}