{
  "type": "Feature",
  "properties": {
    "addr:full":"Waversesteenweg 117 Overijse Vlaams-Brabant 3090",
    "addr:housenumber":"117",
    "addr:postcode":"3090",
    "addr:street":"Waversesteenweg",
    "iso:country":"BE",
    "sg:address":"Waversesteenweg 117",
    "sg:city":"Overijse",
    "sg:orig_category":"R\u00e9cup\u00e9ration de mati\u00e8res m\u00e9talliques recyclables and d\u00e9molisseurs de voitures. V\u00e9hicules automobiles",
    "sg:phone":"+32 2 687 43 49",
    "sg:postcode":"3090",
    "sg:province":"Vlaams-Brabant",
    "wof:name":"Garage Courtens",
    "wof:placetype":"venue"
},
  "geometry": {"coordinates":[4.5430488586,50.772026062],"type":"Point"}
}