{
  "type": "Feature",
  "properties": {
    "addr:full":"Ninoofsesteenweg 81 Galmaarden Vlaams-Brabant 1570",
    "addr:housenumber":"81",
    "addr:postcode":"1570",
    "addr:street":"Ninoofsesteenweg",
    "iso:country":"BE",
    "sg:address":"Ninoofsesteenweg 81",
    "sg:city":"Galmaarden",
    "sg:classifiers":[
        {
            "category":"Personal",
            "subcategory":"Beauty Salon",
            "type":"Services"
        }
    ],
    "sg:phone":"+32 54 56 79 53",
    "sg:postcode":"1570",
    "sg:province":"Vlaams-Brabant",
    "sg:tags":[
        "de",
        "coiffure"
    ],
    "wof:name":"Coiffure Rita",
    "wof:placetype":"venue"
},
  "geometry": {"coordinates":[4.0247998238,50.7615013123],"type":"Point"}
}