{
  "type": "Feature",
  "properties": {
    "iso:country":"BE",
    "sg:address":"Place Joseph Wauters 7ba",
    "sg:city":"Burdinne",
    "sg:orig_category":"Enseignement maternel and primaire",
    "sg:phone":"+32 85 71 32 76",
    "sg:postcode":"4210",
    "sg:province":"Li\u00e8ge",
    "wof:name":"E.m.l. St.th\u00c9r\u00c8se",
    "wof:placetype":"venue"
},
  "geometry": {"coordinates":[5.1431112289,50.5791740417],"type":"Point"}
}