{
  "type": "Feature",
  "properties": {
    "iso:country":"BE",
    "sg:address":"Hamerstraat 2",
    "sg:city":"Ruiselede",
    "sg:orig_category":"Varkenskwekers",
    "sg:phone":"+32 51 68 81 89",
    "sg:postcode":"8755",
    "sg:province":"West-Vlaanderen",
    "wof:name":"Ghislain Lekens",
    "wof:placetype":"venue"
},
  "geometry": {"coordinates":[3.3553760052,51.0645484924],"type":"Point"}
}