{
  "type": "Feature",
  "properties": {
    "iso:country":"BE",
    "sg:address":"Rue Pont-\u00c0-la-faulx 66",
    "sg:city":"Peruwelz",
    "sg:orig_category":"Enseignement secondaire technique and professionnel. Enseignement secondaire g\u00e9n\u00e9ral",
    "sg:phone":"+32 69 77 21 35",
    "sg:postcode":"7600",
    "sg:province":"Hainaut",
    "wof:name":"Institut Charles",
    "wof:placetype":"venue"
},
  "geometry": {"coordinates":[3.5975329876,50.5115776062],"type":"Point"}
}