{
  "type": "Feature",
  "properties": {
    "iso:country":"BE",
    "sg:address":"Dorpsstraat 27",
    "sg:city":"Diepenbeek",
    "sg:classifiers":[
        {
            "category":"Personal",
            "subcategory":"Beauty Salon",
            "type":"Services"
        }
    ],
    "sg:phone":"+32 11 32 32 94",
    "sg:postcode":"3590",
    "sg:province":"Limburg",
    "sg:tags":[
        "lady",
        "-",
        "hairdressing"
    ],
    "wof:name":"Lutgart Coiffure",
    "wof:placetype":"venue"
},
  "geometry": {"coordinates":[5.4187669754,50.9091491699],"type":"Point"}
}