{
  "type": "Feature",
  "properties": {
    "addr:full":"Sint-jansbergsteenweg 46 Huldenberg Vlaams-Brabant 3040",
    "addr:housenumber":"46",
    "addr:postcode":"3040",
    "addr:street":"Sint-Jansbergsteenweg",
    "iso:country":"BE",
    "sg:address":"Sint-jansbergsteenweg 46",
    "sg:city":"Huldenberg",
    "sg:classifiers":[
        {
            "category":"Personal",
            "subcategory":"Beauty Salon",
            "type":"Services"
        }
    ],
    "sg:phone":"+32 16 47 08 47",
    "sg:postcode":"3040",
    "sg:province":"Vlaams-Brabant",
    "wof:name":"Oceana",
    "wof:placetype":"venue"
},
  "geometry": {"coordinates":[4.5990819931,50.7986869812],"type":"Point"}
}