{
  "type": "Feature",
  "properties": {
    "addr:full":"Koning Leopoldlaan 94 Lommel Limburg 3920",
    "addr:housenumber":"94",
    "addr:postcode":"3920",
    "addr:street":"Koning Leopoldlaan",
    "iso:country":"BE",
    "sg:address":"Koning Leopoldlaan 94",
    "sg:city":"Lommel",
    "sg:classifiers":[
        {
            "category":"Restaurant",
            "type":"Food & Drink"
        }
    ],
    "sg:phone":"+32 11 54 10 34",
    "sg:postcode":"3920",
    "sg:province":"Limburg",
    "wof:name":"St.jan",
    "wof:placetype":"venue"
},
  "geometry": {"coordinates":[5.3257040977,51.2300796509],"type":"Point"}
}