{
  "type": "Feature",
  "properties": {
    "addr:full":"Moerbroek 18 I.z. Klein Gent Herenthout Antwerpen 2270",
    "addr:housenumber":"18",
    "addr:postcode":"2270",
    "addr:street":"Moerbroek;I.Z. Klein Gent",
    "iso:country":"BE",
    "sg:address":"Moerbroek 18 I.z. Klein Gent",
    "sg:city":"Herenthout",
    "sg:classifiers":[
        {
            "category":"Farming",
            "subcategory":"Livestock Farm",
            "type":"Manufacturing & Wholesale Goods"
        }
    ],
    "sg:phone":"+32 14 23 01 86",
    "sg:postcode":"2270",
    "sg:province":"Antwerpen",
    "sg:tags":[
        "breeding",
        "agriculture",
        "animal"
    ],
    "wof:name":"Arijs Nv",
    "wof:placetype":"venue"
},
  "geometry": {"coordinates":[4.7963628769,51.1449394226],"type":"Point"}
}