{
  "type": "Feature",
  "properties": {
    "iso:country":"BE",
    "sg:address":"Ninovesteenweg 154",
    "sg:city":"Aalst",
    "sg:orig_category":"Boucheries",
    "sg:phone":"+32 53 21 29 86",
    "sg:postcode":"9320",
    "sg:province":"Oost-Vlaanderen",
    "wof:name":"Jan Verleysen",
    "wof:placetype":"venue"
},
  "geometry": {"coordinates":[4.0553851128,50.9209976196],"type":"Point"}
}