{
  "type": "Feature",
  "properties": {
    "addr:full":"Rue De Brabant 184a Bruxelles (schaerbeek) Bruxelles-Capitale 1030",
    "addr:housenumber":"184a",
    "addr:postcode":"1030",
    "addr:street":"Rue De Brabant",
    "iso:country":"BE",
    "sg:address":"Rue De Brabant 184a",
    "sg:city":"Bruxelles (schaerbeek)",
    "sg:classifiers":[
        {
            "category":"Shopping",
            "subcategory":"Clothing, Apparel, & Fashions",
            "type":"Retail Goods"
        }
    ],
    "sg:phone":"+32 2 223 12 34",
    "sg:postcode":"1030",
    "sg:province":"Bruxelles-Capitale",
    "sg:tags":[
        "boutique"
    ],
    "wof:name":"For You",
    "wof:placetype":"venue"
},
  "geometry": {"coordinates":[4.365732193,50.8634033203],"type":"Point"}
}