{
  "type": "Feature",
  "properties": {
    "iso:country":"BE",
    "sg:address":"Chauss\u00c9e De Vleurgat 80",
    "sg:city":"Elsene/ixelles",
    "sg:classifiers":[
        {
            "category":"Health Services",
            "subcategory":"Hospital",
            "type":"Services"
        }
    ],
    "sg:phone":"+32 2 649 50 10",
    "sg:postcode":"1050",
    "sg:province":"Bruxelles-Capitale",
    "sg:tags":[
        "ambulance"
    ],
    "wof:name":"Het Belgische Rode Kruis/croix Rouge De Belgique",
    "wof:placetype":"venue"
},
  "geometry": {"coordinates":[4.3693962097,50.825176239],"type":"Point"}
}