{
  "type": "Feature",
  "properties": {
    "iso:country":"BE",
    "sg:address":"Molenstraat 72",
    "sg:city":"Hasselt",
    "sg:orig_category":"Dakwerken",
    "sg:phone":"+32 11 25 00 51",
    "sg:postcode":"3510",
    "sg:province":"Limburg",
    "wof:name":"Valkeneers",
    "wof:placetype":"venue"
},
  "geometry": {"coordinates":[5.2355499268,50.9506416321],"type":"Point"}
}