{
  "type": "Feature",
  "properties": {
    "iso:country":"BE",
    "sg:address":"Rue Ferdinand Nicolay 344",
    "sg:city":"Saint-nicolas",
    "sg:orig_category":"Woningbouw",
    "sg:phone":"+32 4 234 06 22",
    "sg:postcode":"4420",
    "sg:province":"Li\u00e8ge",
    "wof:name":"Vincenzo Greco",
    "wof:placetype":"venue"
},
  "geometry": {"coordinates":[5.5329360962,50.6288948059],"type":"Point"}
}