{
  "type": "Feature",
  "properties": {
    "addr:full":"Rue De Luttre 121 Courcelles (gouy-lez-pi\u00e9ton) Hainaut 6181",
    "addr:housenumber":"121",
    "addr:postcode":"6181",
    "addr:street":"Rue De Luttre",
    "iso:country":"BE",
    "sg:address":"Rue De Luttre 121",
    "sg:city":"Courcelles (gouy-lez-pi\u00e9ton)",
    "sg:classifiers":[
        {
            "category":"Cafe",
            "type":"Food & Drink"
        }
    ],
    "sg:phone":"+32 71 84 04 04",
    "sg:postcode":"6181",
    "sg:province":"Hainaut",
    "sg:tags":[
        "snack-bars"
    ],
    "wof:name":"Chateau D'eau",
    "wof:placetype":"venue"
},
  "geometry": {"coordinates":[4.3373432159,50.4911422729],"type":"Point"}
}