{
  "type": "Feature",
  "properties": {
    "iso:country":"BE",
    "sg:address":"31",
    "sg:city":"Peraltastraat 8000 Brugge",
    "sg:classifiers":[
        {
            "category":"Manufacturing",
            "subcategory":"Metals",
            "type":"Manufacturing & Wholesale Goods"
        }
    ],
    "sg:phone":"+32 50 31 10 27",
    "sg:postcode":"31",
    "sg:tags":[
        "metallurgy",
        "metalworking",
        "processing"
    ],
    "wof:name":"Brusselle Bvba",
    "wof:placetype":"venue"
},
  "geometry": {"coordinates":[3.2126500607,51.2411766052],"type":"Point"}
}