{
  "type": "Feature",
  "properties": {
    "addr:full":"Brugstraat 7 Lanaken Limburg 3620",
    "addr:housenumber":"7",
    "addr:postcode":"3620",
    "addr:street":"Brugstraat",
    "iso:country":"BE",
    "sg:address":"Brugstraat 7",
    "sg:city":"Lanaken",
    "sg:orig_category":"Boucheries",
    "sg:phone":"+32 89 71 37 66",
    "sg:postcode":"3620",
    "sg:province":"Limburg",
    "wof:name":"Johnny Goyens",
    "wof:placetype":"venue"
},
  "geometry": {"coordinates":[5.674156189,50.8824234009],"type":"Point"}
}