{
  "type": "Feature",
  "properties": {
    "addr:full":"Dambruggestraat 315 Antwerpen Antwerpen 2060",
    "addr:housenumber":"315",
    "addr:postcode":"2060",
    "addr:street":"Dambruggestraat",
    "iso:country":"BE",
    "sg:address":"Dambruggestraat 315",
    "sg:city":"Antwerpen",
    "sg:classifiers":[
        {
            "category":"Shopping",
            "subcategory":"Gifts & Souvenirs",
            "type":"Retail Goods"
        }
    ],
    "sg:phone":"+32 3 213 11 38",
    "sg:postcode":"2060",
    "sg:province":"Antwerpen",
    "sg:tags":[
        "-"
    ],
    "wof:name":"Jabell",
    "wof:placetype":"venue"
},
  "geometry": {"coordinates":[4.4212331772,51.2288475037],"type":"Point"}
}