{
  "type": "Feature",
  "properties": {
    "addr:full":"Kerselarenweg 11 Herent Vlaams-Brabant 3020",
    "addr:housenumber":"11",
    "addr:postcode":"3020",
    "addr:street":"Kerselarenweg",
    "iso:country":"BE",
    "sg:address":"Kerselarenweg 11",
    "sg:city":"Herent",
    "sg:classifiers":[
        {
            "category":"Health Services",
            "subcategory":"Doctor",
            "type":"Services"
        }
    ],
    "sg:phone":"+32 16 22 62 32",
    "sg:postcode":"3020",
    "sg:province":"Vlaams-Brabant",
    "sg:tags":[
        "medicinephysicians",
        "surgeon"
    ],
    "wof:name":"Joossens Jozef",
    "wof:placetype":"venue"
},
  "geometry": {"coordinates":[4.6841621399,50.8952598572],"type":"Point"}
}