{
  "type": "Feature",
  "properties": {
    "iso:country":"BE",
    "sg:address":"Rue Du Roi Albert",
    "sg:city":"Oupeye",
    "sg:orig_category":"Royal Canin. Animaux domestiques and accessoires",
    "sg:phone":"+32 4 248 15 94",
    "sg:postcode":"4680",
    "sg:province":"Li\u00e8ge",
    "wof:name":"Graineterie Fraikin",
    "wof:placetype":"venue"
},
  "geometry": {"coordinates":[5.6523628235,50.7025985718],"type":"Point"}
}