{
  "type": "Feature",
  "properties": {
    "iso:country":"BE",
    "sg:address":"Liersesteenweg 245",
    "sg:city":"Begijnendijk",
    "sg:orig_category":"Goederenvervoer over de weg",
    "sg:phone":"+32 16 56 21 26",
    "sg:postcode":"3130",
    "sg:province":"Vlaams-Brabant",
    "wof:name":"Verduyckt Vervoer",
    "wof:placetype":"venue"
},
  "geometry": {"coordinates":[4.8014302254,51.0161743164],"type":"Point"}
}