{
  "type": "Feature",
  "properties": {
    "addr:full":"Krijgslaan 195 Gent Oost-Vlaanderen 9000",
    "addr:housenumber":"195",
    "addr:postcode":"9000",
    "addr:street":"Krijgslaan;Oost-Vlaanderen",
    "iso:country":"BE",
    "sg:address":"Krijgslaan 195",
    "sg:city":"Gent",
    "sg:classifiers":[
        {
            "category":"Health Services",
            "subcategory":"Health Practitioner",
            "type":"Services"
        }
    ],
    "sg:phone":"+32 9 221 13 87",
    "sg:postcode":"9000",
    "sg:province":"Oost-Vlaanderen",
    "sg:tags":[
        "osteopath"
    ],
    "wof:name":"Farasyn A (herkend D.o.)",
    "wof:placetype":"venue"
},
  "geometry": {"coordinates":[3.7190799713,51.0289611816],"type":"Point"}
}