{
  "type": "Feature",
  "properties": {
    "iso:country":"BE",
    "sg:address":"Dillenbossen 2",
    "sg:city":"Mol",
    "sg:classifiers":[
        {
            "category":"Building & Trades",
            "subcategory":"Landscaping Services",
            "type":"Services"
        }
    ],
    "sg:phone":"+32 14 31 10 10",
    "sg:postcode":"2400",
    "sg:province":"Antwerpen",
    "sg:tags":[
        "gardening",
        "garden",
        "maintenance"
    ],
    "wof:name":"Verbruggen U Tuinarchitektuur",
    "wof:placetype":"venue"
},
  "geometry": {"coordinates":[5.1265220642,51.1774330139],"type":"Point"}
}