{
  "type": "Feature",
  "properties": {
    "addr:full":"Bld De La Sauveni\u00c8re 68 Li\u00c8ge Li\u00e8ge 4000",
    "addr:housenumber":"68",
    "addr:postcode":"4000",
    "addr:street":"Bld De La Sauvenie\u0300Re",
    "iso:country":"BE",
    "sg:address":"Bld De La Sauveni\u00c8re 68",
    "sg:city":"Li\u00c8ge",
    "sg:orig_category":"Agences d\u00b4interim and personnel temporaire",
    "sg:phone":"+32 4 223 35 54",
    "sg:postcode":"4000",
    "sg:province":"Li\u00e8ge",
    "wof:name":"Content",
    "wof:placetype":"venue"
},
  "geometry": {"coordinates":[5.5665559769,50.6439476013],"type":"Point"}
}