{
  "type": "Feature",
  "properties": {
    "addr:full":"Stationsstr 8 Landegem Oost-Vlaanderen 9840",
    "addr:housenumber":"8",
    "addr:postcode":"9840",
    "addr:street":"Stationsstr;Oost-Vlaanderen",
    "iso:country":"BE",
    "sg:address":"Stationsstr 8",
    "sg:city":"Landegem",
    "sg:classifiers":[
        {
            "category":"Banks & Credit Unions",
            "subcategory":"Bank",
            "type":"Services"
        }
    ],
    "sg:phone":"+32 55 71 61 95",
    "sg:postcode":"9840",
    "sg:province":"Oost-Vlaanderen",
    "wof:name":"Kredietbank",
    "wof:placetype":"venue"
},
  "geometry": {"coordinates":[3.6503789425,50.9965248108],"type":"Point"}
}