{
  "type": "Feature",
  "properties": {
    "addr:full":"Frans Beirenslaan 118 Borsbeek Antwerpen 2150",
    "addr:housenumber":"118",
    "addr:postcode":"2150",
    "addr:street":"Frans Beirenslaan",
    "iso:country":"BE",
    "sg:address":"Frans Beirenslaan 118",
    "sg:city":"Borsbeek",
    "sg:orig_category":"Baby- and kinderkleding Dameskledingzaken Herenkledingzaken",
    "sg:phone":"+32 3 366 09 26",
    "sg:postcode":"2150",
    "sg:province":"Antwerpen",
    "wof:name":"Superconfex",
    "wof:placetype":"venue"
},
  "geometry": {"coordinates":[4.4805369377,51.1966934204],"type":"Point"}
}