{
  "type": "Feature",
  "properties": {
    "addr:full":"Bredabaan 462 Wuustwezel Antwerpen 2990",
    "addr:housenumber":"462",
    "addr:postcode":"2990",
    "addr:street":"Bredabaan",
    "iso:country":"BE",
    "sg:address":"Bredabaan 462",
    "sg:city":"Wuustwezel",
    "sg:orig_category":"Non-Classified Establishments",
    "sg:phone":"+32 3 669 72 29",
    "sg:postcode":"2990",
    "sg:province":"Antwerpen",
    "wof:name":"Elite",
    "wof:placetype":"venue"
},
  "geometry": {"coordinates":[4.5918197632,51.3904304504],"type":"Point"}
}