{
  "type": "Feature",
  "properties": {
    "iso:country":"BE",
    "sg:address":"Rue Bonvoisin 111",
    "sg:city":"Verviers",
    "sg:orig_category":"Diensten voor huisdieren",
    "sg:phone":"+32 87 31 61 85",
    "sg:postcode":"4800",
    "sg:province":"Li\u00e8ge",
    "wof:name":"Ch. Meunier",
    "wof:placetype":"venue"
},
  "geometry": {"coordinates":[5.8594508171,50.5917663574],"type":"Point"}
}