{
  "type": "Feature",
  "properties": {
    "iso:country":"BE",
    "sg:address":"Lammerdries 13",
    "sg:city":"Geel",
    "sg:classifiers":[
        {
            "category":"Wholesale",
            "subcategory":"Fruits & Vegetables",
            "type":"Manufacturing & Wholesale Goods"
        }
    ],
    "sg:phone":"+32 14 23 58 80",
    "sg:postcode":"2440",
    "sg:province":"Antwerpen",
    "sg:tags":[
        "whol",
        "-",
        "potato"
    ],
    "wof:name":"Best-frites Bvba",
    "wof:placetype":"venue"
},
  "geometry": {"coordinates":[4.9210991859,51.1466789246],"type":"Point"}
}