{
  "type": "Feature",
  "properties": {
    "addr:full":"Zepperenweg 68 Sint-truiden Limburg 3800",
    "addr:housenumber":"68",
    "addr:postcode":"3800",
    "addr:street":"Zepperenweg",
    "iso:country":"BE",
    "sg:address":"Zepperenweg 68",
    "sg:city":"Sint-truiden",
    "sg:orig_category":"Pain, p\u00e2tisseries and confiseries",
    "sg:phone":"+32 11 68 37 39",
    "sg:postcode":"3800",
    "sg:province":"Limburg",
    "wof:name":"Fa. Brans J.-schroyen",
    "wof:placetype":"venue"
},
  "geometry": {"coordinates":[5.1993598938,50.81772995],"type":"Point"}
}