{
  "type": "Feature",
  "properties": {
    "addr:full":"Jezusstraat 20 Antwerpen Antwerpen 2000",
    "addr:housenumber":"20",
    "addr:postcode":"2000",
    "addr:street":"Jezusstraat",
    "iso:country":"BE",
    "sg:address":"Jezusstraat 20",
    "sg:city":"Antwerpen",
    "sg:classifiers":[
        {
            "category":"Tea Room",
            "subcategory":"None",
            "type":"Food & Drink"
        }
    ],
    "sg:phone":"+32 3 226 04 65",
    "sg:postcode":"2000",
    "sg:province":"Antwerpen",
    "wof:name":"Bel-air",
    "wof:placetype":"venue"
},
  "geometry": {"coordinates":[4.4138321877,51.2189292908],"type":"Point"}
}