{
  "type": "Feature",
  "properties": {
    "addr:full":"Stationsstraat 103 Waregem West-Vlaanderen 8790",
    "addr:housenumber":"103",
    "addr:postcode":"8790",
    "addr:street":"Stationsstraat",
    "iso:country":"BE",
    "sg:address":"Stationsstraat 103",
    "sg:city":"Waregem",
    "sg:orig_category":"V\u00eatements",
    "sg:phone":"+32 56 60 01 42",
    "sg:postcode":"8790",
    "sg:province":"West-Vlaanderen",
    "wof:name":"Luc De Bock",
    "wof:placetype":"venue"
},
  "geometry": {"coordinates":[3.4289689064,50.8899917603],"type":"Point"}
}