{
  "type": "Feature",
  "properties": {
    "iso:country":"BE",
    "sg:address":"Rue Beauchamp 2",
    "sg:city":"Komen-waasten/comines-warneton",
    "sg:orig_category":"Location de logements sociaux",
    "sg:phone":"+32 56 55 77 71",
    "sg:postcode":"7780",
    "sg:province":"Hainaut",
    "wof:name":"Lysco",
    "wof:placetype":"venue"
},
  "geometry": {"coordinates":[2.9959759712,50.7783699036],"type":"Point"}
}