{
  "type": "Feature",
  "properties": {
    "iso:country":"BE",
    "sg:address":"Boulevard De L'abattoir 26",
    "sg:city":"Bruxelles",
    "sg:orig_category":"V\u00e9hicules automobiles",
    "sg:phone":"+32 475 81 84 81",
    "sg:postcode":"1000",
    "sg:province":"Bruxelles-Capitale",
    "wof:name":"Azk International",
    "wof:placetype":"venue"
},
  "geometry": {"coordinates":[4.3386459351,50.8468971252],"type":"Point"}
}