{
  "type": "Feature",
  "properties": {
    "addr:full":"Bettegem 3 Zellik Vlaams-Brabant 1731",
    "addr:housenumber":"3",
    "addr:postcode":"1731",
    "addr:street":"Bettegem",
    "iso:country":"BE",
    "sg:address":"Bettegem 3",
    "sg:city":"Zellik",
    "sg:classifiers":[
        {
            "category":"Manufacturing",
            "subcategory":"Food",
            "type":"Manufacturing & Wholesale Goods"
        }
    ],
    "sg:phone":"+32 2 467 64 11",
    "sg:postcode":"1731",
    "sg:province":"Vlaams-Brabant",
    "sg:tags":[
        "frozen"
    ],
    "wof:name":"Christian Salvesen Belgium Nv",
    "wof:placetype":"venue"
},
  "geometry": {"coordinates":[4.2495150566,50.8995742798],"type":"Point"}
}