{
  "type": "Feature",
  "properties": {
    "iso:country":"BE",
    "sg:address":"Okegembaan 90",
    "sg:city":"Ninove",
    "sg:classifiers":[
        {
            "category":"Health Services",
            "subcategory":"Health Practitioner",
            "type":"Services"
        }
    ],
    "sg:phone":"+32 54 33 50 13",
    "sg:postcode":"9400",
    "sg:province":"Oost-Vlaanderen",
    "sg:tags":[
        "physiotherapist"
    ],
    "wof:name":"Bliki Helga",
    "wof:placetype":"venue"
},
  "geometry": {"coordinates":[4.0350799561,50.8474159241],"type":"Point"}
}