{
  "type": "Feature",
  "properties": {
    "iso:country":"BE",
    "sg:address":"Donkerstraat 94",
    "sg:city":"Zulte (machelen)",
    "sg:classifiers":[
        {
            "category":"Health Services",
            "subcategory":"Dentist",
            "type":"Services"
        }
    ],
    "sg:phone":"+32 9 380 44 84",
    "sg:postcode":"9870",
    "sg:province":"Oost-Vlaanderen",
    "wof:name":"Van De Keer Isabel",
    "wof:placetype":"venue"
},
  "geometry": {"coordinates":[3.4951100349,50.9568328857],"type":"Point"}
}