{
  "type": "Feature",
  "properties": {
    "addr:full":"Meerlaan 41 Zottegem Oost-Vlaanderen 9620",
    "addr:housenumber":"41",
    "addr:postcode":"9620",
    "addr:street":"Meerlaan",
    "iso:country":"BE",
    "sg:address":"Meerlaan 41",
    "sg:city":"Zottegem",
    "sg:classifiers":[
        {
            "category":"Real Estate",
            "subcategory":"Surveying",
            "type":"Services"
        }
    ],
    "sg:phone":"+32 9 360 13 62",
    "sg:postcode":"9620",
    "sg:province":"Oost-Vlaanderen",
    "sg:tags":[
        "surveyor",
        "land"
    ],
    "wof:name":"Van Wambeke P",
    "wof:placetype":"venue"
},
  "geometry": {"coordinates":[3.8109738827,50.864364624],"type":"Point"}
}