{
  "type": "Feature",
  "properties": {
    "addr:full":"Rue Gravier 4 Wavre Brabant Wallon 1300",
    "addr:housenumber":"4;1300",
    "addr:street":"Rue Gravier",
    "iso:country":"BE",
    "sg:address":"Rue Gravier 4",
    "sg:city":"Wavre",
    "sg:orig_category":"Brood, gebak and snoepgoed",
    "sg:phone":"+32 10 22 33 73",
    "sg:postcode":"1300",
    "sg:province":"Brabant Wallon",
    "wof:name":"Subisco",
    "wof:placetype":"venue"
},
  "geometry": {"coordinates":[4.6059632301,50.7143363953],"type":"Point"}
}