{
  "type": "Feature",
  "properties": {
    "addr:full":"Rue De La Bach\u00e9e 27 Lasne (plancenoit) Brabant Wallon 1380",
    "addr:housenumber":"27",
    "addr:postcode":"1380",
    "addr:street":"Rue De La Bache\u0301E",
    "iso:country":"BE",
    "sg:address":"Rue De La Bach\u00e9e 27",
    "sg:city":"Lasne (plancenoit)",
    "sg:orig_category":"Non-Classified Establishments",
    "sg:phone":"+32 2 633 33 12",
    "sg:postcode":"1380",
    "sg:province":"Brabant Wallon",
    "wof:name":"De Ro A & Fils Sprl",
    "wof:placetype":"venue"
},
  "geometry": {"coordinates":[4.4268932343,50.6596031189],"type":"Point"}
}