{
  "type": "Feature",
  "properties": {
    "iso:country":"BE",
    "sg:address":"Chauss\u00c9e De Louvain 184",
    "sg:city":"Sint-joost-ten-node/saint-josse-ten-noode",
    "sg:orig_category":"V\u00eatements pour Hommes",
    "sg:phone":"+32 2 230 28 02",
    "sg:postcode":"1210",
    "sg:province":"Bruxelles-Capitale",
    "wof:name":"Maison Latino",
    "wof:placetype":"venue"
},
  "geometry": {"coordinates":[4.3777179718,50.8498153687],"type":"Point"}
}