{
  "type": "Feature",
  "properties": {
    "iso:country":"BE",
    "sg:address":"Vieux Chemin De Namur 66",
    "sg:city":"Gembloux-sur-orneau (gembloux)",
    "sg:classifiers":[
        {
            "category":"Communications",
            "type":"Services"
        }
    ],
    "sg:phone":"+32 81 61 34 94",
    "sg:postcode":"5030",
    "sg:province":"Namur",
    "sg:tags":[
        "translator"
    ],
    "wof:name":"Vanderbeken M-c",
    "wof:placetype":"venue"
},
  "geometry": {"coordinates":[4.7293248177,50.548992157],"type":"Point"}
}