{
  "type": "Feature",
  "properties": {
    "addr:full":"Nieuwstraat 32 Dilsen-stokkem Limburg 3650",
    "addr:housenumber":"32",
    "addr:postcode":"3650",
    "addr:street":"Nieuwstraat",
    "iso:country":"BE",
    "sg:address":"Nieuwstraat 32",
    "sg:city":"Dilsen-stokkem",
    "sg:classifiers":[
        {
            "category":"Government",
            "subcategory":"Police Station",
            "type":"Public Place"
        }
    ],
    "sg:phone":"+32 89 79 09 01",
    "sg:postcode":"3650",
    "sg:province":"Limburg",
    "sg:tags":[
        "gendarmerie"
    ],
    "wof:name":"Federale Politie",
    "wof:placetype":"venue"
},
  "geometry": {"coordinates":[5.7243580818,51.0159873962],"type":"Point"}
}