{
  "type": "Feature",
  "properties": {
    "addr:full":"Rue Raoul Warocqu\u00e9 2 Morlanwelz (morlanwelz-mariemont) Hainaut 7140",
    "addr:housenumber":"2",
    "addr:postcode":"7140",
    "addr:street":"Rue Raoul Warocque\u0301",
    "iso:country":"BE",
    "sg:address":"Rue Raoul Warocqu\u00e9 2",
    "sg:city":"Morlanwelz (morlanwelz-mariemont)",
    "sg:classifiers":[
        {
            "category":"Professional",
            "subcategory":"Employment Agencies",
            "type":"Services"
        }
    ],
    "sg:phone":"+32 64 43 17 15",
    "sg:postcode":"7140",
    "sg:province":"Hainaut",
    "wof:name":"Agence Locale Pour L'emploi",
    "wof:placetype":"venue"
},
  "geometry": {"coordinates":[4.2419929504,50.4561004639],"type":"Point"}
}