{
  "type": "Feature",
  "properties": {
    "iso:country":"BE",
    "sg:address":"Avenue De La Couronne 299",
    "sg:city":"Elsene/ixelles",
    "sg:orig_category":"Meubles D\u00e9taillants, Am\u00e9nagement de B\u00e2timents et de Cuisines",
    "sg:phone":"+32 2 646 48 22",
    "sg:postcode":"1050",
    "sg:province":"Bruxelles-Capitale",
    "wof:name":"Sacr\u00c9 Matelas",
    "wof:placetype":"venue"
},
  "geometry": {"coordinates":[4.3909392357,50.8196258545],"type":"Point"}
}