{
  "type": "Feature",
  "properties": {
    "addr:full":"Bethovenstraat 30a Brecht Antwerpen 2960",
    "addr:housenumber":"30a",
    "addr:postcode":"2960",
    "addr:street":"Bethovenstraat",
    "iso:country":"BE",
    "sg:address":"Bethovenstraat 30a",
    "sg:city":"Brecht",
    "sg:classifiers":[
        {
            "category":"Personal",
            "subcategory":"Beauty Salon",
            "type":"Services"
        }
    ],
    "sg:phone":"+32 3 313 44 14",
    "sg:postcode":"2960",
    "sg:province":"Antwerpen",
    "wof:name":"Caress",
    "wof:placetype":"venue"
},
  "geometry": {"coordinates":[4.6365499496,51.3504524231],"type":"Point"}
}