{
  "type": "Feature",
  "properties": {
    "iso:country":"BE",
    "sg:address":"Chauss\u00e9e D' Ellezelles 167",
    "sg:city":"Renaix",
    "sg:classifiers":[
        {
            "category":"Home & Garden",
            "subcategory":"Garden Supply",
            "type":"Retail Goods"
        }
    ],
    "sg:phone":"+32 55 21 66 32",
    "sg:postcode":"9600",
    "sg:province":"Oost-Vlaanderen",
    "wof:name":"Deschaumes Stefaan - Goeminne",
    "wof:placetype":"venue"
},
  "geometry": {"coordinates":[3.6128470898,50.7433853149],"type":"Point"}
}