{
  "type": "Feature",
  "properties": {
    "addr:full":"Avenue Albert 205a Bruxelles (forest) Bruxelles-Capitale 1190",
    "addr:housenumber":"205a",
    "addr:postcode":"1190",
    "addr:street":"Avenue Albert",
    "iso:country":"BE",
    "sg:address":"Avenue Albert 205a",
    "sg:city":"Bruxelles (forest)",
    "sg:classifiers":[
        {
            "category":"Communications",
            "type":"Services"
        }
    ],
    "sg:phone":"+32 2 347 40 18",
    "sg:postcode":"1190",
    "sg:province":"Bruxelles-Capitale",
    "sg:tags":[
        "translator"
    ],
    "wof:name":"Bizot C",
    "wof:placetype":"venue"
},
  "geometry": {"coordinates":[4.346186161,50.8167076111],"type":"Point"}
}