{
  "type": "Feature",
  "properties": {
    "iso:country":"BE",
    "sg:address":"Rue De Tournai 10",
    "sg:city":"Estaimpuis (estaimbourg)",
    "sg:classifiers":[
        {
            "category":"Animal Shelter",
            "type":"Public Place"
        }
    ],
    "sg:phone":"+32 69 55 61 00",
    "sg:postcode":"7730",
    "sg:province":"Hainaut",
    "wof:name":"Ferme Nys",
    "wof:placetype":"venue"
},
  "geometry": {"coordinates":[3.2941319942,50.6793060303],"type":"Point"}
}