{
  "type": "Feature",
  "properties": {
    "addr:full":"Rue Saint-jean 14 Mons Hainaut 7021",
    "addr:housenumber":"14",
    "addr:postcode":"7021",
    "addr:street":"Rue Saint-Jean;Hainaut",
    "iso:country":"BE",
    "sg:address":"Rue Saint-jean 14",
    "sg:city":"Mons",
    "sg:orig_category":"Catering and organisation de f\u00eates",
    "sg:phone":"+32 65 87 29 21",
    "sg:postcode":"7021",
    "sg:province":"Hainaut",
    "wof:name":"Luc Devos",
    "wof:placetype":"venue"
},
  "geometry": {"coordinates":[4.0460529327,50.4668083191],"type":"Point"}
}