{
  "type": "Feature",
  "properties": {
    "addr:full":"Chauss\u00c9e D'audenarde 3 Tournai Hainaut 7500",
    "addr:housenumber":"3",
    "addr:postcode":"7500",
    "addr:street":"Chausse\u0301E D'Audenarde",
    "iso:country":"BE",
    "sg:address":"Chauss\u00c9e D'audenarde 3",
    "sg:city":"Tournai",
    "sg:orig_category":"Meubelzaken, woning- and keukeninrichting Plaatsen van vloer- and muurbekleding Schilders Vloer- and",
    "sg:phone":"+32 69 22 60 04",
    "sg:postcode":"7500",
    "sg:province":"Hainaut",
    "wof:name":"Devertex",
    "wof:placetype":"venue"
},
  "geometry": {"coordinates":[3.3893079758,50.6157226562],"type":"Point"}
}