{
  "type": "Feature",
  "properties": {
    "iso:country":"BE",
    "sg:address":"Rue De L'arbre Unique 105",
    "sg:city":"Bruxelles (evere)",
    "sg:classifiers":[
        {
            "category":"Professional",
            "subcategory":"Management & Consulting",
            "type":"Services"
        }
    ],
    "sg:phone":"+32 2 726 80 84",
    "sg:postcode":"1140",
    "sg:province":"Bruxelles-Capitale",
    "sg:tags":[
        "marketing",
        "-",
        "direct",
        "consultant"
    ],
    "wof:name":"Tilt Factory",
    "wof:placetype":"venue"
},
  "geometry": {"coordinates":[4.4128980637,50.867401123],"type":"Point"}
}