{
  "type": "Feature",
  "properties": {
    "iso:country":"BE",
    "sg:address":"Rue Louis Jamme 53",
    "sg:city":"Li\u00c8ge",
    "sg:orig_category":"Magasins de r\u00e9parations d'articles personnels et m\u00e9nagers divers. R\u00e9parations de chaussures and arti",
    "sg:phone":"+32 4 341 36 16",
    "sg:postcode":"4020",
    "sg:province":"Li\u00e8ge",
    "wof:name":"Cordonnerie Expres",
    "wof:placetype":"venue"
},
  "geometry": {"coordinates":[5.5859918594,50.6383476257],"type":"Point"}
}