{
  "type": "Feature",
  "properties": {
    "addr:full":"Rue Du Hollu 33 Sprimont (rouvreux) Li\u00e8ge 4140",
    "addr:housenumber":"33",
    "addr:postcode":"4140",
    "addr:street":"Rue Du Hollu;Rouvreux",
    "iso:country":"BE",
    "sg:address":"Rue Du Hollu 33",
    "sg:city":"Sprimont (rouvreux)",
    "sg:classifiers":[
        {
            "category":"Professional",
            "subcategory":"Management & Consulting",
            "type":"Services"
        }
    ],
    "sg:phone":"+32 4 384 86 53",
    "sg:postcode":"4140",
    "sg:province":"Li\u00e8ge",
    "sg:tags":[
        "consultant"
    ],
    "wof:name":"Action Id Sprl",
    "wof:placetype":"venue"
},
  "geometry": {"coordinates":[5.6597499847,50.5072059631],"type":"Point"}
}