{
  "type": "Feature",
  "properties": {
    "iso:country":"BE",
    "sg:address":"Generaal De Wittelaan 9-6b",
    "sg:city":"Mechelen",
    "sg:classifiers":[
        {
            "category":"Home & Garden",
            "subcategory":"Carpets & Floor Coverings",
            "type":"Retail Goods"
        }
    ],
    "sg:phone":"+32 15 20 14 62",
    "sg:postcode":"2800",
    "sg:province":"Antwerpen",
    "sg:tags":[
        "industrial",
        "-"
    ],
    "wof:name":"Mc-bauchemi-belgium Nv",
    "wof:placetype":"venue"
},
  "geometry": {"coordinates":[4.4518809319,51.0549049377],"type":"Point"}
}