{
  "type": "Feature",
  "properties": {
    "addr:full":"Bijlokstraat 169 Herent Vlaams-Brabant 3020",
    "addr:housenumber":"169",
    "addr:postcode":"3020",
    "addr:street":"Bijlokstraat",
    "iso:country":"BE",
    "sg:address":"Bijlokstraat 169",
    "sg:city":"Herent",
    "sg:classifiers":[
        {
            "category":"Real Estate",
            "subcategory":"Architect",
            "type":"Services"
        }
    ],
    "sg:phone":"+32 16 25 39 38",
    "sg:postcode":"3020",
    "sg:province":"Vlaams-Brabant",
    "wof:name":"Pues E",
    "wof:placetype":"venue"
},
  "geometry": {"coordinates":[4.6846227646,50.9006767273],"type":"Point"}
}