{
  "type": "Feature",
  "properties": {
    "addr:full":"Rue Albert Ier 223 Messancy Luxembourg 6780",
    "addr:housenumber":"223",
    "addr:postcode":"6780",
    "addr:street":"Rue Albert Ier",
    "iso:country":"BE",
    "sg:address":"Rue Albert Ier 223",
    "sg:city":"Messancy",
    "sg:orig_category":"R\u00e9parations d'appareils \u00e9lectrom\u00e9nagers. Installation \u00e9lectrique r\u00e9sidentielle. Electrom\u00e9nager, t\u00e9l\u00e9",
    "sg:phone":"+32 63 22 66 82",
    "sg:postcode":"6780",
    "sg:province":"Luxembourg",
    "wof:name":"Jean Crespin",
    "wof:placetype":"venue"
},
  "geometry": {"coordinates":[5.8153700829,49.5921859741],"type":"Point"}
}