{
  "type": "Feature",
  "properties": {
    "iso:country":"BE",
    "sg:address":"Nieuwstraat 8",
    "sg:city":"Geel",
    "sg:classifiers":[
        {
            "category":"Shopping",
            "subcategory":"Bicycles & Sporting Goods",
            "type":"Retail Goods"
        }
    ],
    "sg:phone":"+32 14 58 77 77",
    "sg:postcode":"2440",
    "sg:province":"Antwerpen",
    "sg:tags":[
        "sport",
        "-"
    ],
    "wof:name":"Speedo Shop-van Menen",
    "wof:placetype":"venue"
},
  "geometry": {"coordinates":[4.9913330078,51.1627655029],"type":"Point"}
}