{
  "type": "Feature",
  "properties": {
    "iso:country":"BE",
    "sg:address":"Oudenaardsesteenweg 272",
    "sg:city":"Avelgem",
    "sg:orig_category":"Herstellingen and onderhoud van auto's",
    "sg:phone":"+32 55 38 80 61",
    "sg:postcode":"8581",
    "sg:province":"West-Vlaanderen",
    "wof:name":"Garage Verhoest",
    "wof:placetype":"venue"
},
  "geometry": {"coordinates":[3.4719910622,50.7869300842],"type":"Point"}
}