{
  "type": "Feature",
  "properties": {
    "addr:full":"Everspoelstraat 3 Landen Vlaams-Brabant 3400",
    "addr:housenumber":"3",
    "addr:postcode":"3400",
    "addr:street":"Everspoelstraat",
    "iso:country":"BE",
    "sg:address":"Everspoelstraat 3",
    "sg:city":"Landen",
    "sg:orig_category":"Artiesten and kunstenaars",
    "sg:phone":"+32 16 78 83 43",
    "sg:postcode":"3400",
    "sg:province":"Vlaams-Brabant",
    "wof:name":"Jean Loriers",
    "wof:placetype":"venue"
},
  "geometry": {"coordinates":[5.0267882347,50.7704086304],"type":"Point"}
}