{
  "type": "Feature",
  "properties": {
    "iso:country":"BE",
    "sg:address":"Rue Des Maraichers 65",
    "sg:city":"Li\u00c8ge",
    "sg:orig_category":"V\u00e9t\u00e9rinaires",
    "sg:phone":"+32 4 343 86 09",
    "sg:postcode":"4020",
    "sg:province":"Li\u00e8ge",
    "wof:name":"Jean Schmitz",
    "wof:placetype":"venue"
},
  "geometry": {"coordinates":[5.5940308571,50.6388015747],"type":"Point"}
}