{
  "type": "Feature",
  "properties": {
    "addr:full":"Van Cauwelaertstraat 27 Ternat Vlaams-Brabant 1740",
    "addr:housenumber":"27",
    "addr:postcode":"1740",
    "addr:street":"Cauwelaertstraat",
    "iso:country":"BE",
    "sg:address":"Van Cauwelaertstraat 27",
    "sg:city":"Ternat",
    "sg:classifiers":[
        {
            "category":"Cafe",
            "type":"Food & Drink"
        }
    ],
    "sg:phone":"+32 2 582 21 08",
    "sg:postcode":"1740",
    "sg:province":"Vlaams-Brabant",
    "sg:tags":[
        "caf\u00e9s"
    ],
    "wof:name":"John Van Krieken",
    "wof:placetype":"venue"
},
  "geometry": {"coordinates":[4.1755070686,50.8693351746],"type":"Point"}
}