{
  "type": "Feature",
  "properties": {
    "addr:full":"Hoogveld 3 Dendermonde (sint-gillis-bij-dendermonde) Oost-Vlaanderen 9200",
    "addr:housenumber":"3",
    "addr:postcode":"9200",
    "addr:street":"Hoogveld",
    "iso:country":"BE",
    "sg:address":"Hoogveld 3",
    "sg:city":"Dendermonde (sint-gillis-bij-dendermonde)",
    "sg:classifiers":[
        {
            "category":"Building & Trades",
            "subcategory":"Construction",
            "type":"Services"
        }
    ],
    "sg:phone":"+32 52 37 56 51",
    "sg:postcode":"9200",
    "sg:province":"Oost-Vlaanderen",
    "sg:tags":[
        "heat",
        "exchanger"
    ],
    "wof:name":"Blygold Belgium & Luxemburg",
    "wof:placetype":"venue"
},
  "geometry": {"coordinates":[4.1313247681,51.0365867615],"type":"Point"}
}