{
  "type": "Feature",
  "properties": {
    "iso:country":"BE",
    "sg:address":"Kloosterstraat 61",
    "sg:city":"Zele",
    "sg:orig_category":"Elektrische installaties voor woningen HERSTELLING ELEKTRISCHE HUISHOUDAPPARATEN Verlichting and hui",
    "sg:phone":"+32 52 44 52 42",
    "sg:postcode":"9240",
    "sg:province":"Oost-Vlaanderen",
    "wof:name":"Huis Van Kerckhove",
    "wof:placetype":"venue"
},
  "geometry": {"coordinates":[4.0431637764,51.0688247681],"type":"Point"}
}