{
  "type": "Feature",
  "properties": {
    "addr:full":"Klarewal 2 Alveringem West-Vlaanderen 8690",
    "addr:housenumber":"2",
    "addr:postcode":"8690",
    "addr:street":"Klarewal",
    "iso:country":"BE",
    "sg:address":"Klarewal 2",
    "sg:city":"Alveringem",
    "sg:classifiers":[
        {
            "category":"Farming",
            "subcategory":"Farm & Veterinary Services",
            "type":"Manufacturing & Wholesale Goods"
        }
    ],
    "sg:phone":"+32 58 28 86 19",
    "sg:postcode":"8690",
    "sg:province":"West-Vlaanderen",
    "sg:tags":[
        "agricultural",
        "contractor"
    ],
    "wof:name":"Luyssen S",
    "wof:placetype":"venue"
},
  "geometry": {"coordinates":[2.714621067,51.0065078735],"type":"Point"}
}