{
  "type": "Feature",
  "properties": {
    "iso:country":"BE",
    "sg:address":"Scheldestraat 46",
    "sg:city":"Antwerpen",
    "sg:orig_category":"Persagentschappen",
    "sg:phone":"+32 3 237 88 81",
    "sg:postcode":"2000",
    "sg:province":"Antwerpen",
    "wof:name":"Greta Mangelschots",
    "wof:placetype":"venue"
},
  "geometry": {"coordinates":[4.3944439888,51.211643219],"type":"Point"}
}