{
  "type": "Feature",
  "properties": {
    "iso:country":"BE",
    "sg:address":"Leon Dumortierstraat 168",
    "sg:city":"Hove",
    "sg:classifiers":[
        {
            "category":"Wholesale",
            "subcategory":"Beer",
            "type":"Manufacturing & Wholesale Goods"
        }
    ],
    "sg:phone":"+32 3 454 13 99",
    "sg:postcode":"2540",
    "sg:province":"Antwerpen",
    "sg:tags":[
        "ale",
        "-"
    ],
    "wof:name":"Huybrechts Dranken",
    "wof:placetype":"venue"
},
  "geometry": {"coordinates":[4.4712867737,51.1499443054],"type":"Point"}
}