{
  "type": "Feature",
  "properties": {
    "iso:country":"BE",
    "sg:address":"Wallemotestraat 22",
    "sg:city":"Izegem",
    "sg:classifiers":[
        {
            "category":"Fast Food",
            "type":"Food & Drink"
        }
    ],
    "sg:phone":"+32 51 31 48 59",
    "sg:postcode":"8870",
    "sg:province":"West-Vlaanderen",
    "sg:tags":[
        "\u00c0",
        "emporter",
        "restaurants"
    ],
    "wof:name":"Frituur 't Hoeksken",
    "wof:placetype":"venue"
},
  "geometry": {"coordinates":[3.1990439892,50.9127082825],"type":"Point"}
}