{
  "type": "Feature",
  "properties": {
    "addr:full":"Tervuursesteenweg 526 Bertem Vlaams-Brabant 3061",
    "addr:housenumber":"526",
    "addr:postcode":"3061",
    "addr:street":"Tervuursesteenweg",
    "iso:country":"BE",
    "sg:address":"Tervuursesteenweg 526",
    "sg:city":"Bertem",
    "sg:orig_category":"Belastingconsulenten Diverse juridische dienstverlening",
    "sg:phone":"+32 2 767 29 65",
    "sg:postcode":"3061",
    "sg:province":"Vlaams-Brabant",
    "wof:name":"Comes Consulting Grp",
    "wof:placetype":"venue"
},
  "geometry": {"coordinates":[4.5839791298,50.8533172607],"type":"Point"}
}