{
  "type": "Feature",
  "properties": {
    "addr:full":"Route Des Ecluses 46 Comines-warneton (warneton) Hainaut 7784",
    "addr:housenumber":"46",
    "addr:postcode":"7784",
    "addr:street":"Route Des Ecluses",
    "iso:country":"BE",
    "sg:address":"Route Des Ecluses 46",
    "sg:city":"Comines-warneton (warneton)",
    "sg:orig_category":"Fa\u00e7ade covering",
    "sg:phone":"+32 56 56 01 07",
    "sg:postcode":"7784",
    "sg:province":"Hainaut",
    "wof:name":"S.e.i.b.",
    "wof:placetype":"venue"
},
  "geometry": {"coordinates":[2.9882800579,50.7601661682],"type":"Point"}
}