{
  "type": "Feature",
  "properties": {
    "addr:full":"Kerkplein 3 Beerse Antwerpen 2340",
    "addr:housenumber":"3",
    "addr:postcode":"2340",
    "addr:street":"Kerkplein",
    "iso:country":"BE",
    "sg:address":"Kerkplein 3",
    "sg:city":"Beerse",
    "sg:orig_category":"Banken and kredietinstellingen",
    "sg:phone":"+32 14 61 21 97",
    "sg:postcode":"2340",
    "sg:province":"Antwerpen",
    "wof:name":"Dexia",
    "wof:placetype":"venue"
},
  "geometry": {"coordinates":[4.8552570343,51.3195114136],"type":"Point"}
}