{
  "type": "Feature",
  "properties": {
    "iso:country":"BE",
    "sg:address":"Holt 72",
    "sg:city":"Bilzen (beverst)",
    "sg:orig_category":"Accumulators",
    "sg:phone":"+32 89 41 12 20",
    "sg:postcode":"3740",
    "sg:province":"Limburg",
    "wof:name":"L.b. Trading Bvba",
    "wof:placetype":"venue"
},
  "geometry": {"coordinates":[5.4806680679,50.8872642517],"type":"Point"}
}