{
  "type": "Feature",
  "properties": {
    "iso:country":"BE",
    "sg:address":"Preisbergstraat 58",
    "sg:city":"Kortrijk (aalbeke)",
    "sg:classifiers":[
        {
            "category":"Building & Trades",
            "subcategory":"Construction",
            "type":"Services"
        }
    ],
    "sg:phone":"+32 56 41 31 36",
    "sg:postcode":"8511",
    "sg:province":"West-Vlaanderen",
    "sg:tags":[
        "work",
        "waterproofing"
    ],
    "wof:name":"Verrue K",
    "wof:placetype":"venue"
},
  "geometry": {"coordinates":[3.2160360813,50.7874603271],"type":"Point"}
}