{
  "type": "Feature",
  "properties": {
    "iso:country":"BE",
    "sg:address":"Rue Des Egalots 2-4",
    "sg:city":"Fosses-la-ville",
    "sg:classifiers":[
        {
            "category":"Building & Trades",
            "subcategory":"Electrical",
            "type":"Services"
        }
    ],
    "sg:phone":"+32 71 71 11 44",
    "sg:postcode":"5070",
    "sg:province":"Namur",
    "sg:tags":[
        "tool",
        "electric"
    ],
    "wof:name":"Clause",
    "wof:placetype":"venue"
},
  "geometry": {"coordinates":[4.6962051392,50.3955154419],"type":"Point"}
}