{
  "type": "Feature",
  "properties": {
    "addr:full":"Chauss\u00c9e De Waterloo 19 Namur Namur 5000",
    "addr:housenumber":"19",
    "addr:postcode":"5000",
    "addr:street":"Chausse\u0301E De Waterloo",
    "iso:country":"BE",
    "sg:address":"Chauss\u00c9e De Waterloo 19",
    "sg:city":"Namur",
    "sg:orig_category":"Advocaten and juridische adviseurs",
    "sg:phone":"+32 81 71 97 93",
    "sg:postcode":"5000",
    "sg:province":"Namur",
    "wof:name":"Laurent Geuens",
    "wof:placetype":"venue"
},
  "geometry": {"coordinates":[4.8509078026,50.47108078],"type":"Point"}
}