{
  "type": "Feature",
  "properties": {
    "iso:country":"BE",
    "sg:address":"Bethani\u00ebnlei 108b",
    "sg:city":"Zoersel",
    "sg:classifiers":[
        {
            "category":"Retail",
            "subcategory":"Event Space",
            "type":"Services"
        }
    ],
    "sg:phone":"+32 3 383 57 26",
    "sg:postcode":"2980",
    "sg:province":"Antwerpen",
    "sg:tags":[
        "rental",
        "-",
        "hall"
    ],
    "wof:name":"Vriendenband (de)",
    "wof:placetype":"venue"
},
  "geometry": {"coordinates":[4.6296429634,51.2763137817],"type":"Point"}
}