{
  "type": "Feature",
  "properties": {
    "addr:full":"Zeedijk-het Zoute 772 Knokke-heist (knokke) West-Vlaanderen 8300",
    "addr:housenumber":"772",
    "addr:postcode":"8300",
    "addr:street":"Zoute",
    "iso:country":"BE",
    "sg:address":"Zeedijk-het Zoute 772",
    "sg:city":"Knokke-heist (knokke)",
    "sg:classifiers":[
        {
            "category":"Shopping",
            "subcategory":"Shoes",
            "type":"Retail Goods"
        }
    ],
    "sg:phone":"+32 50 60 82 32",
    "sg:postcode":"8300",
    "sg:province":"West-Vlaanderen",
    "sg:tags":[
        "slipper",
        "-"
    ],
    "wof:name":"Blue",
    "wof:placetype":"venue"
},
  "geometry": {"coordinates":[3.3267199993,51.3504714966],"type":"Point"}
}