{
  "type": "Feature",
  "properties": {
    "addr:full":"Roeselarestraat 85 Wevelgem West-Vlaanderen 8560",
    "addr:housenumber":"85",
    "addr:postcode":"8560",
    "addr:street":"Roeselarestraat",
    "iso:country":"BE",
    "sg:address":"Roeselarestraat 85",
    "sg:city":"Wevelgem",
    "sg:classifiers":[
        {
            "category":"Real Estate",
            "subcategory":"Real Estate Services",
            "type":"Services"
        }
    ],
    "sg:phone":"+32 56 41 10 19",
    "sg:postcode":"8560",
    "sg:province":"West-Vlaanderen",
    "wof:name":"Dewa-building Cv",
    "wof:placetype":"venue"
},
  "geometry": {"coordinates":[3.1799430847,50.813129425],"type":"Point"}
}