{
  "type": "Feature",
  "properties": {
    "iso:country":"BE",
    "sg:address":"Reeckervelt 1250",
    "sg:city":"Riemst",
    "sg:classifiers":[
        {
            "category":"Banks & Credit Unions",
            "subcategory":"Atm",
            "type":"Services"
        }
    ],
    "sg:phone":"+32 12 45 14 47",
    "sg:postcode":"3770",
    "sg:province":"Limburg",
    "sg:tags":[
        "case",
        "crate",
        "maker"
    ],
    "wof:name":"Benedco Bvba",
    "wof:placetype":"venue"
},
  "geometry": {"coordinates":[5.5957398415,50.8174781799],"type":"Point"}
}