{
  "type": "Feature",
  "properties": {
    "addr:full":"Morgenster 13 Kuurne West-Vlaanderen 8520",
    "addr:housenumber":"13",
    "addr:postcode":"8520",
    "addr:street":"Morgenster",
    "iso:country":"BE",
    "sg:address":"Morgenster 13",
    "sg:city":"Kuurne",
    "sg:orig_category":"Non-Classified Establishments",
    "sg:phone":"+32 56 35 74 00",
    "sg:postcode":"8520",
    "sg:province":"West-Vlaanderen",
    "wof:name":"Verreyst J",
    "wof:placetype":"venue"
},
  "geometry": {"coordinates":[3.2668249607,50.8637580872],"type":"Point"}
}