{
  "type": "Feature",
  "properties": {
    "addr:full":"Hogeschoollaan 6 Elsene/ixelles Bruxelles-Capitale 1050",
    "addr:housenumber":"6",
    "addr:postcode":"1050",
    "addr:street":"Hogeschoollaan",
    "iso:country":"BE",
    "sg:address":"Hogeschoollaan 6",
    "sg:city":"Elsene/ixelles",
    "sg:orig_category":"Banken and kredietinstellingen",
    "sg:phone":"+32 2 640 19 88",
    "sg:postcode":"1050",
    "sg:province":"Bruxelles-Capitale",
    "wof:name":"Fortis",
    "wof:placetype":"venue"
},
  "geometry": {"coordinates":[4.3894371986,50.8153572083],"type":"Point"}
}