{
  "type": "Feature",
  "properties": {
    "iso:country":"BE",
    "sg:address":"Hogeweg 22",
    "sg:city":"Geraardsbergen",
    "sg:orig_category":"Imprimeries and copyshops",
    "sg:phone":"+32 54 41 84 34",
    "sg:postcode":"9500",
    "sg:province":"Oost-Vlaanderen",
    "wof:name":"Bruno De Vos",
    "wof:placetype":"venue"
},
  "geometry": {"coordinates":[3.8661239147,50.7665252686],"type":"Point"}
}