{
  "type": "Feature",
  "properties": {
    "addr:full":"Brusselbaan 35 Herzele Oost-Vlaanderen 9550",
    "addr:housenumber":"35",
    "addr:postcode":"9550",
    "addr:street":"Brusselbaan;Oost-Vlaanderen",
    "iso:country":"BE",
    "sg:address":"Brusselbaan 35",
    "sg:city":"Herzele",
    "sg:classifiers":[
        {
            "category":"Food & Beverages",
            "subcategory":"Fruits & Vegetables",
            "type":"Retail Goods"
        }
    ],
    "sg:phone":"+32 54 50 13 84",
    "sg:postcode":"9550",
    "sg:province":"Oost-Vlaanderen",
    "sg:tags":[
        "l\u00e9gumes"
    ],
    "wof:name":"Jeannine De Vulder",
    "wof:placetype":"venue"
},
  "geometry": {"coordinates":[3.9161970615,50.8274497986],"type":"Point"}
}