{
  "type": "Feature",
  "properties": {
    "iso:country":"BE",
    "sg:address":"Rue Meyers Hennau 5-11",
    "sg:city":"Bruxelles",
    "sg:classifiers":[
        {
            "category":"Shopping",
            "subcategory":"Computers & Home Electronics",
            "type":"Retail Goods"
        }
    ],
    "sg:phone":"+32 2 420 04 34",
    "sg:postcode":"1020",
    "sg:province":"Bruxelles-Capitale",
    "sg:tags":[
        "-",
        "processing",
        "data",
        "cleaning"
    ],
    "wof:name":"I P C Sprl",
    "wof:placetype":"venue"
},
  "geometry": {"coordinates":[4.3490710258,50.8748817444],"type":"Point"}
}