{
  "type": "Feature",
  "properties": {
    "iso:country":"BE",
    "sg:address":"Rue D'arlon 1",
    "sg:city":"Virton",
    "sg:classifiers":[
        {
            "category":"Building & Trades",
            "subcategory":"Electrical",
            "type":"Services"
        }
    ],
    "sg:phone":"+32 63 58 88 00",
    "sg:postcode":"6760",
    "sg:province":"Luxembourg",
    "sg:tags":[
        "-",
        "electric",
        "contractor"
    ],
    "wof:name":"Ricaille D",
    "wof:placetype":"venue"
},
  "geometry": {"coordinates":[5.5548248291,49.580078125],"type":"Point"}
}