{
  "type": "Feature",
  "properties": {
    "iso:country":"BE",
    "sg:address":"Voie Du Tram 7",
    "sg:city":"Wavre",
    "sg:classifiers":[
        {
            "category":"Retail",
            "subcategory":"Auto Rental",
            "type":"Services"
        }
    ],
    "sg:phone":"+32 10 22 95 28",
    "sg:postcode":"1300",
    "sg:province":"Brabant Wallon",
    "sg:tags":[
        "automobile",
        "-",
        "car",
        "self-drive"
    ],
    "wof:name":"Lp Rent A Car Sprl",
    "wof:placetype":"venue"
},
  "geometry": {"coordinates":[4.6107058525,50.7132377625],"type":"Point"}
}