{
  "type": "Feature",
  "properties": {
    "iso:country":"BE",
    "sg:address":"Place Du Village 17",
    "sg:city":"Blegny",
    "sg:classifiers":[
        {
            "category":"Personal",
            "subcategory":"Beauty Salon",
            "type":"Services"
        }
    ],
    "sg:phone":"+32 4 387 62 84",
    "sg:postcode":"4670",
    "sg:province":"Li\u00e8ge",
    "sg:tags":[
        "de",
        "coiffure"
    ],
    "wof:name":"Coiffure Baguette",
    "wof:placetype":"venue"
},
  "geometry": {"coordinates":[5.7720341682,50.6846733093],"type":"Point"}
}