{
  "type": "Feature",
  "properties": {
    "addr:full":"Place Didier 24 Arlon Luxembourg 6700",
    "addr:housenumber":"24",
    "addr:postcode":"6700",
    "addr:street":"Place Didier",
    "iso:country":"BE",
    "sg:address":"Place Didier 24",
    "sg:city":"Arlon",
    "sg:classifiers":[
        {
            "category":"Real Estate",
            "subcategory":"Real Estate Services",
            "type":"Services"
        }
    ],
    "sg:phone":"+32 63 22 04 40",
    "sg:postcode":"6700",
    "sg:province":"Luxembourg",
    "wof:name":"Breny Immobili\u00e8re",
    "wof:placetype":"venue"
},
  "geometry": {"coordinates":[5.8128252029,49.6845703125],"type":"Point"}
}