{
  "type": "Feature",
  "properties": {
    "iso:country":"BE",
    "sg:address":"Thier De L'eglise 1",
    "sg:city":"Burdinne",
    "sg:orig_category":"Editeurs de livres",
    "sg:phone":"+32 85 71 13 85",
    "sg:postcode":"4210",
    "sg:province":"Li\u00e8ge",
    "wof:name":"Ludwig Nols",
    "wof:placetype":"venue"
},
  "geometry": {"coordinates":[5.1263718605,50.5817184448],"type":"Point"}
}