{
  "type": "Feature",
  "properties": {
    "addr:full":"Rue Po\u00c8te Folie 56 Fleurus Hainaut 6220",
    "addr:housenumber":"56",
    "addr:postcode":"6220",
    "addr:street":"Rue Poe\u0300Te Folie",
    "iso:country":"BE",
    "sg:address":"Rue Po\u00c8te Folie 56",
    "sg:city":"Fleurus",
    "sg:orig_category":"Catering and organisation de f\u00eates",
    "sg:phone":"+32 71 81 31 18",
    "sg:postcode":"6220",
    "sg:province":"Hainaut",
    "wof:name":"Traiteur Ada",
    "wof:placetype":"venue"
},
  "geometry": {"coordinates":[4.5463581085,50.4807510376],"type":"Point"}
}