{
  "type": "Feature",
  "properties": {
    "addr:full":"Place Andr\u00c9 Ryckmans 6 Namur Namur 5000",
    "addr:housenumber":"6",
    "addr:postcode":"5000",
    "addr:street":"Place Andre\u0301 Ryckmans",
    "iso:country":"BE",
    "sg:address":"Place Andr\u00c9 Ryckmans 6",
    "sg:city":"Namur",
    "sg:orig_category":"Architecten",
    "sg:phone":"+32 81 74 57 55",
    "sg:postcode":"5000",
    "sg:province":"Namur",
    "wof:name":"Yves Stiennon",
    "wof:placetype":"venue"
},
  "geometry": {"coordinates":[4.8510699272,50.4670028687],"type":"Point"}
}