{
  "type": "Feature",
  "properties": {
    "addr:full":"Grand-place 27 Paliseul Luxembourg 6850",
    "addr:housenumber":"27",
    "addr:postcode":"6850",
    "addr:street":"Grand-Place",
    "iso:country":"BE",
    "sg:address":"Grand-place 27",
    "sg:city":"Paliseul",
    "sg:classifiers":[
        {
            "category":"Cafe",
            "type":"Food & Drink"
        }
    ],
    "sg:phone":"+32 61 53 37 67",
    "sg:postcode":"6850",
    "sg:province":"Luxembourg",
    "sg:tags":[
        "caf\u00e9s"
    ],
    "wof:name":"Caf\u00c9 Sur Le Pouce",
    "wof:placetype":"venue"
},
  "geometry": {"coordinates":[5.136329174,49.904006958],"type":"Point"}
}