{
  "type": "Feature",
  "properties": {
    "iso:country":"BE",
    "sg:address":"Open Luchtlaan 39",
    "sg:city":"Sint-genesius-rode/rhode-saint-genese",
    "sg:orig_category":"Woningbouw",
    "sg:phone":"+32 2 358 31 43",
    "sg:postcode":"1640",
    "sg:province":"Vlaams-Brabant",
    "wof:name":"Ghysels R Et Fils",
    "wof:placetype":"venue"
},
  "geometry": {"coordinates":[4.3657431602,50.7588539124],"type":"Point"}
}