{
  "type": "Feature",
  "properties": {
    "iso:country":"BE",
    "sg:address":"2110",
    "sg:city":"Wijnegem",
    "sg:orig_category":"Librairies",
    "sg:phone":"+32 56 36 04 44",
    "sg:postcode":"2110",
    "sg:province":"Antwerpen",
    "wof:name":"Artis Historia",
    "wof:placetype":"venue"
},
  "geometry": {"coordinates":[4.5248470306,51.2279434204],"type":"Point"}
}