{
  "type": "Feature",
  "properties": {
    "addr:full":"Pastoor Verrieststraat 98 Anzegem (ingooigem) West-Vlaanderen 8570",
    "addr:housenumber":"98",
    "addr:postcode":"8570",
    "addr:street":"Pastoor Verrieststraat",
    "iso:country":"BE",
    "sg:address":"Pastoor Verrieststraat 98",
    "sg:city":"Anzegem (ingooigem)",
    "sg:classifiers":[
        {
            "category":"Professional",
            "subcategory":"Accounting & Tax Preparation",
            "type":"Services"
        }
    ],
    "sg:phone":"+32 56 77 80 76",
    "sg:postcode":"8570",
    "sg:province":"West-Vlaanderen",
    "sg:tags":[
        "accountant"
    ],
    "wof:name":"Demeijer R",
    "wof:placetype":"venue"
},
  "geometry": {"coordinates":[3.4432110786,50.8241539001],"type":"Point"}
}