{
  "type": "Feature",
  "properties": {
    "iso:country":"BE",
    "sg:address":"Rue De La Vall\u00c9e 47",
    "sg:city":"Orp-jauche",
    "sg:orig_category":"Charpentes and couvertures",
    "sg:phone":"+32 19 63 45 42",
    "sg:postcode":"1350",
    "sg:province":"Brabant Wallon",
    "wof:name":"Alain Bierlaire",
    "wof:placetype":"venue"
},
  "geometry": {"coordinates":[4.97920084,50.6738891602],"type":"Point"}
}