{
  "type": "Feature",
  "properties": {
    "addr:full":"Rue Blanche Borne 79 Ch\u00e2telet (bouffioulx) Hainaut 6200",
    "addr:housenumber":"79",
    "addr:postcode":"6200",
    "addr:street":"Rue Blanche Borne",
    "iso:country":"BE",
    "sg:address":"Rue Blanche Borne 79",
    "sg:city":"Ch\u00e2telet (bouffioulx)",
    "sg:classifiers":[
        {
            "category":"Health Services",
            "subcategory":"Doctor",
            "type":"Services"
        }
    ],
    "sg:phone":"+32 71 40 39 13",
    "sg:postcode":"6200",
    "sg:province":"Hainaut",
    "sg:tags":[
        "psychotherapist",
        "psychoanalyst"
    ],
    "wof:name":"Centre Psychologique De Guidance Et De D\u00e9veloppement Personnel C.p.a.m.",
    "wof:placetype":"venue"
},
  "geometry": {"coordinates":[4.4979381561,50.3908653259],"type":"Point"}
}