{
  "type": "Feature",
  "properties": {
    "addr:full":"Rue Louis Piret 20 Walcourt Namur 5651",
    "addr:housenumber":"20",
    "addr:postcode":"5651",
    "addr:street":"Rue Louis Piret",
    "iso:country":"BE",
    "sg:address":"Rue Louis Piret 20",
    "sg:city":"Walcourt",
    "sg:orig_category":"Rusthuizen and serviceflats",
    "sg:phone":"+32 71 61 23 76",
    "sg:postcode":"5651",
    "sg:province":"Namur",
    "wof:name":"Home De La Thyria",
    "wof:placetype":"venue"
},
  "geometry": {"coordinates":[4.4387631416,50.2833480835],"type":"Point"}
}