{
  "type": "Feature",
  "properties": {
    "iso:country":"BE",
    "sg:address":"Place Henri Hallet 1",
    "sg:city":"Hannut",
    "sg:orig_category":"Articles de camping and de sport. Chaussures",
    "sg:phone":"+32 19 51 26 01",
    "sg:postcode":"4280",
    "sg:province":"Li\u00e8ge",
    "wof:name":"Franck Sports",
    "wof:placetype":"venue"
},
  "geometry": {"coordinates":[5.0789542198,50.67162323],"type":"Point"}
}