{
  "type": "Feature",
  "properties": {
    "iso:country":"BE",
    "sg:address":"Felix Wittouckstraat 1",
    "sg:city":"Sint-pieters-leeuw",
    "sg:classifiers":[
        {
            "category":"Restaurant",
            "type":"Food & Drink"
        }
    ],
    "sg:phone":"+32 2 331 45 85",
    "sg:postcode":"1600",
    "sg:province":"Vlaams-Brabant",
    "wof:name":"Sofra",
    "wof:placetype":"venue"
},
  "geometry": {"coordinates":[4.2893328667,50.8077926636],"type":"Point"}
}