{
  "type": "Feature",
  "properties": {
    "iso:country":"BE",
    "sg:address":"Rue De Moignel\u00c9e 113",
    "sg:city":"Fleurus",
    "sg:orig_category":"Souvenirs and objets artisanaux. Fleurs and plantes. Jardinage",
    "sg:phone":"+32 71 77 74 02",
    "sg:postcode":"6220",
    "sg:province":"Hainaut",
    "wof:name":"Renard Christian",
    "wof:placetype":"venue"
},
  "geometry": {"coordinates":[4.5823311806,50.4475593567],"type":"Point"}
}