{
  "type": "Feature",
  "properties": {
    "iso:country":"BE",
    "sg:address":"Route Du Coignelot 13",
    "sg:city":"Manhay (vaux-chavanne)",
    "sg:classifiers":[
        {
            "category":"Government",
            "subcategory":"Fire Station",
            "type":"Public Place"
        }
    ],
    "sg:phone":"+32 86 45 56 94",
    "sg:postcode":"6960",
    "sg:province":"Luxembourg",
    "sg:tags":[
        "installation",
        "-",
        "air conditioning"
    ],
    "wof:name":"Evrard Y",
    "wof:placetype":"venue"
},
  "geometry": {"coordinates":[5.6786570549,50.3176612854],"type":"Point"}
}