{
  "type": "Feature",
  "properties": {
    "addr:full":"Goedestraat 44 Kortenberg Vlaams-Brabant 3078",
    "addr:housenumber":"44",
    "addr:postcode":"3078",
    "addr:street":"Goedestraat;Vlaams-Brabant",
    "iso:country":"BE",
    "sg:address":"Goedestraat 44",
    "sg:city":"Kortenberg",
    "sg:classifiers":[
        {
            "category":"Cafe",
            "type":"Food & Drink"
        }
    ],
    "sg:phone":"+32 2 759 20 22",
    "sg:postcode":"3078",
    "sg:province":"Vlaams-Brabant",
    "sg:tags":[
        "caf\u00e9s"
    ],
    "wof:name":"Caf\u00c9 't Orakel",
    "wof:placetype":"venue"
},
  "geometry": {"coordinates":[4.5993170738,50.8895950317],"type":"Point"}
}