{
  "type": "Feature",
  "properties": {
    "iso:country":"BE",
    "sg:address":"Bornstraat 27",
    "sg:city":"Kortessem (vliermaalroot)",
    "sg:classifiers":[
        {
            "category":"Home & Garden",
            "subcategory":"Hardware",
            "type":"Retail Goods"
        }
    ],
    "sg:phone":"+32 11 72 09 80",
    "sg:postcode":"3721",
    "sg:province":"Limburg",
    "sg:tags":[
        "tarpaulin"
    ],
    "wof:name":"Slegers R",
    "wof:placetype":"venue"
},
  "geometry": {"coordinates":[5.4298858643,50.8689079285],"type":"Point"}
}