{
  "type": "Feature",
  "properties": {
    "iso:country":"BE",
    "sg:address":"Route De Ploegsteert 43",
    "sg:city":"Komen-waasten/comines-warneton",
    "sg:orig_category":"RESTAURANTS: CAF\u00c9S",
    "sg:phone":"+32 56 58 77 80",
    "sg:postcode":"7784",
    "sg:province":"Hainaut",
    "wof:name":"Au Relais Du Gheer",
    "wof:placetype":"venue"
},
  "geometry": {"coordinates":[2.9317200184,50.7410202026],"type":"Point"}
}