{
  "type": "Feature",
  "properties": {
    "iso:country":"BE",
    "sg:address":"Rue De La Montagne 63",
    "sg:city":"Sambreville",
    "sg:orig_category":"Gespecialiseerde niet-residenti\u00eble bouw Installatie van metalen schrijnwerk",
    "sg:phone":"+32 71 77 20 08",
    "sg:postcode":"5060",
    "sg:province":"Namur",
    "wof:name":"Walry Francis",
    "wof:placetype":"venue"
},
  "geometry": {"coordinates":[4.6285200119,50.4448738098],"type":"Point"}
}