{
  "type": "Feature",
  "properties": {
    "addr:full":"Dullaertweg 93 Gistel West-Vlaanderen 8470",
    "addr:housenumber":"93",
    "addr:postcode":"8470",
    "addr:street":"Dullaertweg",
    "iso:country":"BE",
    "sg:address":"Dullaertweg 93",
    "sg:city":"Gistel",
    "sg:orig_category":"Groententeelt",
    "sg:phone":"+32 59 27 82 70",
    "sg:postcode":"8470",
    "sg:province":"West-Vlaanderen",
    "wof:name":"Daniel Derynck",
    "wof:placetype":"venue"
},
  "geometry": {"coordinates":[2.9985220432,51.1540489197],"type":"Point"}
}