{
  "type": "Feature",
  "properties": {
    "addr:full":"Rue De La Couturelle 2 Mettet Namur 5640",
    "addr:housenumber":"2",
    "addr:postcode":"5640",
    "addr:street":"Rue De La Couturelle",
    "iso:country":"BE",
    "sg:address":"Rue De La Couturelle 2",
    "sg:city":"Mettet",
    "sg:orig_category":"Enseignement maternel and primaire",
    "sg:phone":"+32 71 72 86 90",
    "sg:postcode":"5640",
    "sg:province":"Namur",
    "wof:name":"Ecole Fondamentale Libre",
    "wof:placetype":"venue"
},
  "geometry": {"coordinates":[4.6578397751,50.3198051453],"type":"Point"}
}