{
  "type": "Feature",
  "properties": {
    "addr:full":"Rue Hector Denis 204 Quaregnon Hainaut 7390",
    "addr:housenumber":"204",
    "addr:postcode":"7390",
    "addr:street":"Rue Hector Denis",
    "iso:country":"BE",
    "sg:address":"Rue Hector Denis 204",
    "sg:city":"Quaregnon",
    "sg:orig_category":"Sportclubs",
    "sg:phone":"+32 65 78 25 76",
    "sg:postcode":"7390",
    "sg:province":"Hainaut",
    "wof:name":"V.c. Union Quaregnon",
    "wof:placetype":"venue"
},
  "geometry": {"coordinates":[3.8645839691,50.4348564148],"type":"Point"}
}