{
  "type": "Feature",
  "properties": {
    "iso:country":"BE",
    "sg:address":"Rue Des Bergeries 35",
    "sg:city":"Fosses-la-ville",
    "sg:classifiers":[
        {
            "category":"Banks & Credit Unions",
            "subcategory":"Bank",
            "type":"Services"
        }
    ],
    "sg:phone":"+32 71 71 11 14",
    "sg:postcode":"5070",
    "sg:province":"Namur",
    "sg:tags":[
        "savings-banks"
    ],
    "wof:name":"Axa",
    "wof:placetype":"venue"
},
  "geometry": {"coordinates":[4.6911058426,50.3896331787],"type":"Point"}
}