{
  "type": "Feature",
  "properties": {
    "addr:full":"Neereindestraat 60 Zele Oost-Vlaanderen 9240",
    "addr:housenumber":"60",
    "addr:postcode":"9240",
    "addr:street":"Neereindestraat",
    "iso:country":"BE",
    "sg:address":"Neereindestraat 60",
    "sg:city":"Zele",
    "sg:orig_category":"Rundveehouders",
    "sg:phone":"+32 52 45 01 83",
    "sg:postcode":"9240",
    "sg:province":"Oost-Vlaanderen",
    "wof:name":"Jenny Van Langenhove",
    "wof:placetype":"venue"
},
  "geometry": {"coordinates":[4.0697360039,51.0585861206],"type":"Point"}
}