{
  "type": "Feature",
  "properties": {
    "addr:full":"Volhardingstraat 53 Antwerpen Antwerpen 2020",
    "addr:housenumber":"53",
    "addr:postcode":"2020",
    "addr:street":"Volhardingstraat",
    "iso:country":"BE",
    "sg:address":"Volhardingstraat 53",
    "sg:city":"Antwerpen",
    "sg:classifiers":[
        {
            "category":"Professional",
            "subcategory":"Management & Consulting",
            "type":"Services"
        }
    ],
    "sg:phone":"+32 3 216 10 11",
    "sg:postcode":"2020",
    "sg:province":"Antwerpen",
    "sg:tags":[
        "consultant",
        "agency",
        "advertising"
    ],
    "wof:name":"Andries Design Bvba",
    "wof:placetype":"venue"
},
  "geometry": {"coordinates":[4.3911261559,51.1910209656],"type":"Point"}
}