{
  "type": "Feature",
  "properties": {
    "addr:full":"Roeselaarsestraat 402 Izegem West-Vlaanderen 8870",
    "addr:housenumber":"402",
    "addr:postcode":"8870",
    "addr:street":"Roeselaarsestraat",
    "iso:country":"BE",
    "sg:address":"Roeselaarsestraat 402",
    "sg:city":"Izegem",
    "sg:classifiers":[
        {
            "category":"Manufacturing",
            "subcategory":"Tools & Machinery",
            "type":"Manufacturing & Wholesale Goods"
        }
    ],
    "sg:phone":"+32 51 31 74 48",
    "sg:postcode":"8870",
    "sg:province":"West-Vlaanderen",
    "sg:tags":[
        "leather",
        "machine",
        "working"
    ],
    "wof:name":"Omicor",
    "wof:placetype":"venue"
},
  "geometry": {"coordinates":[3.1951110363,50.9230499268],"type":"Point"}
}