{
  "type": "Feature",
  "properties": {
    "addr:full":"Industrieln 13 Eeklo Oost-Vlaanderen 9900",
    "addr:housenumber":"13",
    "addr:postcode":"9900",
    "addr:street":"Industrieln",
    "iso:country":"BE",
    "sg:address":"Industrieln 13",
    "sg:city":"Eeklo",
    "sg:classifiers":[
        {
            "category":"Government",
            "subcategory":"Department Of Motor Vehicles",
            "type":"Public Place"
        }
    ],
    "sg:phone":"+32 9 377 45 05",
    "sg:postcode":"9900",
    "sg:province":"Oost-Vlaanderen",
    "sg:tags":[
        "equipment",
        "industrial",
        "transport",
        "motor-cars"
    ],
    "wof:name":"Autop Nv",
    "wof:placetype":"venue"
},
  "geometry": {"coordinates":[3.5442569256,51.1820831299],"type":"Point"}
}