{
  "type": "Feature",
  "properties": {
    "addr:full":"Vulderstraat 12 Maldegem (adegem) Oost-Vlaanderen 9991",
    "addr:housenumber":"12",
    "addr:postcode":"9991",
    "addr:street":"Vulderstraat",
    "iso:country":"BE",
    "sg:address":"Vulderstraat 12",
    "sg:city":"Maldegem (adegem)",
    "sg:orig_category":"Non-Classified Establishments",
    "sg:phone":"+32 9 377 92 70",
    "sg:postcode":"9991",
    "sg:province":"Oost-Vlaanderen",
    "wof:name":"Ifomac Bvba",
    "wof:placetype":"venue"
},
  "geometry": {"coordinates":[3.5127029419,51.1747207642],"type":"Point"}
}