{
  "type": "Feature",
  "properties": {
    "iso:country":"BE",
    "sg:address":"Bosvoordse Steenweg 26",
    "sg:city":"Elsene/ixelles",
    "sg:orig_category":"Antiek",
    "sg:phone":"+32 2 672 66 24",
    "sg:postcode":"1050",
    "sg:province":"Bruxelles-Capitale",
    "wof:name":"Bureau Willems Jean",
    "wof:placetype":"venue"
},
  "geometry": {"coordinates":[4.3929600716,50.8074913025],"type":"Point"}
}