{
  "type": "Feature",
  "properties": {
    "addr:full":"Rue De Barisart 215-217 Spa Li\u00e8ge 4900",
    "addr:housenumber":"215-217",
    "addr:postcode":"4900",
    "addr:street":"Rue De Barisart",
    "iso:country":"BE",
    "sg:address":"Rue De Barisart 215-217",
    "sg:city":"Spa",
    "sg:classifiers":[
        {
            "category":"Travel",
            "subcategory":"Hotels & Motels",
            "type":"Entertainment"
        }
    ],
    "sg:phone":"+32 87 77 16 88",
    "sg:postcode":"4900",
    "sg:province":"Li\u00e8ge",
    "wof:name":"Le Domaine Des Sorbiers",
    "wof:placetype":"venue"
},
  "geometry": {"coordinates":[5.8596639633,50.4838066101],"type":"Point"}
}