{
  "type": "Feature",
  "properties": {
    "addr:full":"Middelburgstraat 77 Watermaal-bosvoorde/watermael-boitsfort Bruxelles-Capitale 1170",
    "addr:housenumber":"77",
    "addr:postcode":"1170",
    "addr:street":"Middelburgstraat",
    "iso:country":"BE",
    "sg:address":"Middelburgstraat 77",
    "sg:city":"Watermaal-bosvoorde/watermael-boitsfort",
    "sg:orig_category":"Verhuur bouwmachines",
    "sg:phone":"+32 2 672 11 32",
    "sg:postcode":"1170",
    "sg:province":"Bruxelles-Capitale",
    "wof:name":"Versant Belgium",
    "wof:placetype":"venue"
},
  "geometry": {"coordinates":[4.4181838036,50.7943572998],"type":"Point"}
}