{
  "type": "Feature",
  "properties": {
    "addr:full":"Koning Albert Ii Laan 27 Brussel Bruxelles-Capitale 1030",
    "addr:housenumber":"27",
    "addr:postcode":"1030",
    "addr:street":"Koning Albert Ii Laan",
    "iso:country":"BE",
    "sg:address":"Koning Albert Ii Laan 27",
    "sg:city":"Brussel",
    "sg:classifiers":[
        {
            "category":"Communications",
            "subcategory":"Television Station",
            "type":"Services"
        }
    ],
    "sg:phone":"+32 2 202 81 11",
    "sg:postcode":"1030",
    "sg:province":"Bruxelles-Capitale",
    "sg:tags":[
        "machine",
        "answering"
    ],
    "wof:name":"Belgacom Nv",
    "wof:placetype":"venue"
},
  "geometry": {"coordinates":[4.3573651314,50.8603782654],"type":"Point"}
}