{
  "type": "Feature",
  "properties": {
    "addr:full":"Luitenant Jacopsstraat 94 Lennik Vlaams-Brabant 1750",
    "addr:housenumber":"94;1750",
    "addr:street":"Luitenant Jacopsstraat;Vlaams-Brabant",
    "iso:country":"BE",
    "sg:address":"Luitenant Jacopsstraat 94",
    "sg:city":"Lennik",
    "sg:orig_category":"Brood, gebak and snoepgoed",
    "sg:phone":"+32 2 582 45 10",
    "sg:postcode":"1750",
    "sg:province":"Vlaams-Brabant",
    "wof:name":"Freddy Van Der Haegen",
    "wof:placetype":"venue"
},
  "geometry": {"coordinates":[4.1356368065,50.8386955261],"type":"Point"}
}