{
  "type": "Feature",
  "properties": {
    "addr:full":"All\u00e9e Pr\u00e9 Lorette 9 Nivelles Brabant Wallon 1400",
    "addr:housenumber":"9",
    "addr:postcode":"1400",
    "addr:street":"Alle\u0301E Pre\u0301 Lorette",
    "iso:country":"BE",
    "sg:address":"All\u00e9e Pr\u00e9 Lorette 9",
    "sg:city":"Nivelles",
    "sg:classifiers":[
        {
            "category":"Professional",
            "subcategory":"Accounting & Tax Preparation",
            "type":"Services"
        }
    ],
    "sg:phone":"+32 67 21 37 37",
    "sg:postcode":"1400",
    "sg:province":"Brabant Wallon",
    "sg:tags":[
        "accountant"
    ],
    "wof:name":"Hallet J",
    "wof:placetype":"venue"
},
  "geometry": {"coordinates":[4.3176817894,50.6035499573],"type":"Point"}
}