{
  "type": "Feature",
  "properties": {
    "addr:full":"Brusselsesteenweg 508 Halle Vlaams-Brabant 1500",
    "addr:housenumber":"508",
    "addr:postcode":"1500",
    "addr:street":"Brusselsesteenweg",
    "iso:country":"BE",
    "sg:address":"Brusselsesteenweg 508",
    "sg:city":"Halle",
    "sg:classifiers":[
        {
            "category":"Utilities",
            "subcategory":"Sewage",
            "type":"Services"
        }
    ],
    "sg:phone":"+32 52 47 93 25",
    "sg:postcode":"1500",
    "sg:province":"Vlaams-Brabant",
    "sg:tags":[
        "agitator",
        "treatment"
    ],
    "wof:name":"Werkhuizen Huwaert Nv",
    "wof:placetype":"venue"
},
  "geometry": {"coordinates":[4.1396398544,51.0778694153],"type":"Point"}
}