{
  "type": "Feature",
  "properties": {
    "iso:country":"BE",
    "sg:address":"Rammelstraat 26",
    "sg:city":"Lede",
    "sg:classifiers":[
        {
            "category":"Shopping",
            "subcategory":"Clothing, Apparel, & Fashions",
            "type":"Retail Goods"
        }
    ],
    "sg:phone":"+32 53 80 67 23",
    "sg:postcode":"9340",
    "sg:province":"Oost-Vlaanderen",
    "sg:tags":[
        "-",
        "clothing",
        "child"
    ],
    "wof:name":"Gamino",
    "wof:placetype":"venue"
},
  "geometry": {"coordinates":[3.9770379066,50.967124939],"type":"Point"}
}