{
  "type": "Feature",
  "properties": {
    "addr:full":"Rue Emile Vandervelde 10 Comblain-au-pont Li\u00e8ge 4170",
    "addr:housenumber":"10",
    "addr:postcode":"4170",
    "addr:street":"Rue Emile Vandervelde",
    "iso:country":"BE",
    "sg:address":"Rue Emile Vandervelde 10",
    "sg:city":"Comblain-au-pont",
    "sg:classifiers":[
        {
            "category":"Health Services",
            "subcategory":"Doctor",
            "type":"Services"
        }
    ],
    "sg:phone":"+32 4 369 11 07",
    "sg:postcode":"4170",
    "sg:province":"Li\u00e8ge",
    "sg:tags":[
        "medicinephysicians",
        "surgeon"
    ],
    "wof:name":"De Ti\u00e8ge Pierre",
    "wof:placetype":"venue"
},
  "geometry": {"coordinates":[5.5786290169,50.4727554321],"type":"Point"}
}