{
  "type": "Feature",
  "properties": {
    "iso:country":"BE",
    "sg:address":"Lange Dijkstraat 22b1",
    "sg:city":"Dendermonde",
    "sg:orig_category":"Eleveurs de bovins",
    "sg:phone":"+32 52 21 61 68",
    "sg:postcode":"9200",
    "sg:province":"Oost-Vlaanderen",
    "wof:name":"Alexis Van Cauwenberghe",
    "wof:placetype":"venue"
},
  "geometry": {"coordinates":[4.1001901627,51.0303459167],"type":"Point"}
}