{
  "type": "Feature",
  "properties": {
    "addr:full":"Antwerpsesteenweg 303a Malle (westmalle) Antwerpen 2390",
    "addr:housenumber":"303a",
    "addr:postcode":"2390",
    "addr:street":"Antwerpsesteenweg",
    "iso:country":"BE",
    "sg:address":"Antwerpsesteenweg 303a",
    "sg:city":"Malle (westmalle)",
    "sg:classifiers":[
        {
            "category":"Shopping",
            "subcategory":"Clothing, Apparel, & Fashions",
            "type":"Retail Goods"
        }
    ],
    "sg:phone":"+32 3 311 58 41",
    "sg:postcode":"2390",
    "sg:province":"Antwerpen",
    "sg:tags":[
        "-",
        "clothing",
        "child"
    ],
    "wof:name":"Scoubi-kids",
    "wof:placetype":"venue"
},
  "geometry": {"coordinates":[4.6896348,51.297039032],"type":"Point"}
}