{
  "type": "Feature",
  "properties": {
    "addr:full":"Meir 44ba Antwerpen Antwerpen 2000",
    "addr:housenumber":"44ba",
    "addr:postcode":"2000",
    "addr:street":"Meir",
    "iso:country":"BE",
    "sg:address":"Meir 44ba",
    "sg:city":"Antwerpen",
    "sg:orig_category":"Animaux domestiques and accessoires",
    "sg:phone":"+32 3 330 14 40",
    "sg:postcode":"2000",
    "sg:province":"Antwerpen",
    "wof:name":"Huis Van Riel Distripet",
    "wof:placetype":"venue"
},
  "geometry": {"coordinates":[4.4077129364,51.2180252075],"type":"Point"}
}