{
  "type": "Feature",
  "properties": {
    "addr:full":"Dommelweg 3 Neerpelt Limburg 3910",
    "addr:housenumber":"3",
    "addr:postcode":"3910",
    "addr:street":"Dommelweg",
    "iso:country":"BE",
    "sg:address":"Dommelweg 3",
    "sg:city":"Neerpelt",
    "sg:classifiers":[
        {
            "category":"Arena",
            "subcategory":"Sports Club",
            "type":"Entertainment"
        }
    ],
    "sg:phone":"+32 11 64 70 87",
    "sg:postcode":"3910",
    "sg:province":"Limburg",
    "sg:tags":[
        "de"
    ],
    "wof:name":"Neerpelt Bc",
    "wof:placetype":"venue"
},
  "geometry": {"coordinates":[5.4403700829,51.2188262939],"type":"Point"}
}