{
  "type": "Feature",
  "properties": {
    "iso:country":"BE",
    "sg:address":"Kerkstraat 109",
    "sg:city":"Blankenberge",
    "sg:classifiers":[
        {
            "category":"Cafe",
            "type":"Food & Drink"
        }
    ],
    "sg:phone":"+32 50 41 23 02",
    "sg:postcode":"8370",
    "sg:province":"West-Vlaanderen",
    "sg:tags":[
        "snack-bars"
    ],
    "wof:name":"Sarina",
    "wof:placetype":"venue"
},
  "geometry": {"coordinates":[3.1306540966,51.3137321472],"type":"Point"}
}