{
  "type": "Feature",
  "properties": {
    "iso:country":"BE",
    "sg:address":"Rue De La R\u00e9sistance 21",
    "sg:city":"Huy",
    "sg:classifiers":[
        {
            "category":"Health Services",
            "subcategory":"Health Practitioner",
            "type":"Services"
        }
    ],
    "sg:phone":"+32 85 25 12 60",
    "sg:postcode":"4500",
    "sg:province":"Li\u00e8ge",
    "sg:tags":[
        "physiotherapist"
    ],
    "wof:name":"Pr\u00e9vot I",
    "wof:placetype":"venue"
},
  "geometry": {"coordinates":[5.2436628342,50.5207481384],"type":"Point"}
}