{
  "type": "Feature",
  "properties": {
    "addr:full":"Molenstraat 26ba Aalst Oost-Vlaanderen 9320",
    "addr:housenumber":"26ba",
    "addr:postcode":"9320",
    "addr:street":"Molenstraat",
    "iso:country":"BE",
    "sg:address":"Molenstraat 26ba",
    "sg:city":"Aalst",
    "sg:classifiers":[
        {
            "category":"Shopping",
            "subcategory":"Clothing, Apparel, & Fashions",
            "type":"Retail Goods"
        }
    ],
    "sg:phone":"+32 53 83 49 93",
    "sg:postcode":"9320",
    "sg:province":"Oost-Vlaanderen",
    "sg:tags":[
        "v\u00eatements",
        "pour",
        "dame"
    ],
    "wof:name":"Maurits Daelman",
    "wof:placetype":"venue"
},
  "geometry": {"coordinates":[4.040640831,50.9391136169],"type":"Point"}
}