{
  "type": "Feature",
  "properties": {
    "iso:country":"BE",
    "sg:address":"Schorvoortstraat 12",
    "sg:city":"Turnhout",
    "sg:classifiers":[
        {
            "category":"Wholesale",
            "subcategory":"Beer",
            "type":"Manufacturing & Wholesale Goods"
        }
    ],
    "sg:phone":"+32 14 72 08 38",
    "sg:postcode":"2300",
    "sg:province":"Antwerpen",
    "sg:tags":[
        "ale",
        "-"
    ],
    "wof:name":"Prik & Tik",
    "wof:placetype":"venue"
},
  "geometry": {"coordinates":[4.9517159462,51.3073730469],"type":"Point"}
}