{
  "type": "Feature",
  "properties": {
    "addr:full":"Leopoldplein 8 Hasselt Limburg 3500",
    "addr:housenumber":"8",
    "addr:postcode":"3500",
    "addr:street":"Leopoldplein",
    "iso:country":"BE",
    "sg:address":"Leopoldplein 8",
    "sg:city":"Hasselt",
    "sg:orig_category":"Avocats and conseillers juridiques",
    "sg:phone":"+32 11 22 15 35",
    "sg:postcode":"3500",
    "sg:province":"Limburg",
    "wof:name":"Christophe Bielen",
    "wof:placetype":"venue"
},
  "geometry": {"coordinates":[5.3354649544,50.9272956848],"type":"Point"}
}