{
  "type": "Feature",
  "properties": {
    "iso:country":"BE",
    "sg:address":"Vissersstraat 59",
    "sg:city":"De Haan",
    "sg:orig_category":"Artistes ind\u00e9pendants",
    "sg:phone":"+32 59 23 35 74",
    "sg:postcode":"8420",
    "sg:province":"West-Vlaanderen",
    "wof:name":"Vanheche",
    "wof:placetype":"venue"
},
  "geometry": {"coordinates":[3.0007519722,51.2579154968],"type":"Point"}
}