{
  "type": "Feature",
  "properties": {
    "iso:country":"BE",
    "sg:address":"Hendrik Consciencelaan 28-73",
    "sg:city":"Waarschoot",
    "sg:classifiers":[
        {
            "category":"Sports & Exercise",
            "subcategory":"Race Track",
            "type":"Entertainment"
        }
    ],
    "sg:phone":"+32 9 377 67 65",
    "sg:postcode":"9950",
    "sg:province":"Oost-Vlaanderen",
    "sg:tags":[
        "-",
        "stratified",
        "panel"
    ],
    "wof:name":"Luko Interieur Bvba",
    "wof:placetype":"venue"
},
  "geometry": {"coordinates":[3.5997469425,51.1517448425],"type":"Point"}
}