{
  "type": "Feature",
  "properties": {
    "addr:full":"Oudescheldestraat 8b Gent Oost-Vlaanderen 9000",
    "addr:housenumber":"8b",
    "addr:postcode":"9000",
    "addr:street":"Oudescheldestraat;Oost-Vlaanderen",
    "iso:country":"BE",
    "sg:address":"Oudescheldestraat 8b",
    "sg:city":"Gent",
    "sg:classifiers":[
        {
            "category":"Professional",
            "subcategory":"Management & Consulting",
            "type":"Services"
        }
    ],
    "sg:phone":"+32 475 40 31 85",
    "sg:postcode":"9000",
    "sg:province":"Oost-Vlaanderen",
    "sg:tags":[
        "-",
        "processing",
        "data",
        "consultant"
    ],
    "wof:name":"Npd Services",
    "wof:placetype":"venue"
},
  "geometry": {"coordinates":[3.7305641174,51.0489501953],"type":"Point"}
}