{
  "type": "Feature",
  "properties": {
    "iso:country":"BE",
    "sg:address":"K. Deswertlaan 84",
    "sg:city":"Blankenberge",
    "sg:orig_category":"G\u00e2teaux, p\u00e2tisserie and biscuits Fab",
    "sg:phone":"+32 50 41 17 64",
    "sg:postcode":"8370",
    "sg:province":"West-Vlaanderen",
    "wof:name":"Fa. Beyaert",
    "wof:placetype":"venue"
},
  "geometry": {"coordinates":[3.1296598911,51.3094444275],"type":"Point"}
}