{
  "type": "Feature",
  "properties": {
    "iso:country":"BE",
    "sg:address":"Wittewalle 20",
    "sg:city":"Gent",
    "sg:orig_category":"M\u00e9decins and sp\u00e9cialistes",
    "sg:phone":"+32 9 259 01 06",
    "sg:postcode":"9041",
    "sg:province":"Oost-Vlaanderen",
    "wof:name":"L. Vanden Bossche",
    "wof:placetype":"venue"
},
  "geometry": {"coordinates":[3.7641880512,51.1065788269],"type":"Point"}
}