{
  "type": "Feature",
  "properties": {
    "iso:country":"BE",
    "sg:address":"Anna Bijnsstraat 3",
    "sg:city":"Niel",
    "sg:classifiers":[
        {
            "category":"Professional",
            "subcategory":"Computer Services",
            "type":"Services"
        }
    ],
    "sg:phone":"+32 475 89 54 16",
    "sg:postcode":"2845",
    "sg:province":"Antwerpen",
    "sg:tags":[
        "webdesign",
        "-",
        "internet"
    ],
    "wof:name":"E-solving.be Bvba",
    "wof:placetype":"venue"
},
  "geometry": {"coordinates":[4.3488087654,51.1099205017],"type":"Point"}
}