{
  "type": "Feature",
  "properties": {
    "addr:full":"Dr\u00c8ve De Willerieken 50 Oudergem/auderghem Bruxelles-Capitale 1160",
    "addr:housenumber":"50",
    "addr:postcode":"1160",
    "addr:street":"Dre\u0300Ve De Willerieken;/",
    "iso:country":"BE",
    "sg:address":"Dr\u00c8ve De Willerieken 50",
    "sg:city":"Oudergem/auderghem",
    "sg:orig_category":"M\u00e9decins and sp\u00e9cialistes",
    "sg:phone":"+32 2 673 00 94",
    "sg:postcode":"1160",
    "sg:province":"Bruxelles-Capitale",
    "wof:name":"Int\u00c9gration",
    "wof:placetype":"venue"
},
  "geometry": {"coordinates":[4.4724411964,50.7903785706],"type":"Point"}
}