{
  "type": "Feature",
  "properties": {
    "iso:country":"BE",
    "sg:address":"Albrecht Rodenbachstraat 2a",
    "sg:city":"Ieper (vlamertinge)",
    "sg:classifiers":[
        {
            "category":"Home & Garden",
            "subcategory":"Household Appliances",
            "type":"Retail Goods"
        }
    ],
    "sg:phone":"+32 57 20 55 59",
    "sg:postcode":"8908",
    "sg:province":"West-Vlaanderen",
    "sg:tags":[
        "repair",
        "mainten",
        "-",
        "electric"
    ],
    "wof:name":"Knockaert Gerrie Nv",
    "wof:placetype":"venue"
},
  "geometry": {"coordinates":[2.8239369392,50.852897644],"type":"Point"}
}