{
  "type": "Feature",
  "properties": {
    "iso:country":"BE",
    "sg:address":"Korte Moeie 53",
    "sg:city":"Eeklo",
    "sg:classifiers":[
        {
            "category":"Shopping",
            "subcategory":"Crafts & Fabrics",
            "type":"Retail Goods"
        }
    ],
    "sg:phone":"+32 9 376 77 11",
    "sg:postcode":"9900",
    "sg:province":"Oost-Vlaanderen",
    "sg:tags":[
        "nappy"
    ],
    "wof:name":"Ontex Afd. Eutima Nv",
    "wof:placetype":"venue"
},
  "geometry": {"coordinates":[3.549366951,51.1837844849],"type":"Point"}
}