{
  "type": "Feature",
  "properties": {
    "addr:full":"Avenue De La Belle Voie 18 Wavre Brabant Wallon 1300",
    "addr:housenumber":"18;1300",
    "addr:street":"Avenue De La Belle Voie",
    "iso:country":"BE",
    "sg:address":"Avenue De La Belle Voie 18",
    "sg:city":"Wavre",
    "sg:classifiers":[
        {
            "category":"Personal",
            "subcategory":"Beauty Salon",
            "type":"Services"
        }
    ],
    "sg:phone":"+32 10 24 30 73",
    "sg:postcode":"1300",
    "sg:province":"Brabant Wallon",
    "wof:name":"Tollet F",
    "wof:placetype":"venue"
},
  "geometry": {"coordinates":[4.6169171333,50.7196083069],"type":"Point"}
}