{
  "type": "Feature",
  "properties": {
    "addr:full":"Avenue De L'europe 5 Leuze-en-hainaut (chapelle-\u00e0-wattines) Hainaut 7903",
    "addr:housenumber":"5;7903",
    "addr:street":"Avenue De L'Europe;Chapelle-A\u0300-Wattines Hainaut",
    "iso:country":"BE",
    "sg:address":"Avenue De L'europe 5",
    "sg:city":"Leuze-en-hainaut (chapelle-\u00e0-wattines)",
    "sg:classifiers":[
        {
            "category":"Retail",
            "subcategory":"Auto Repair",
            "type":"Services"
        }
    ],
    "sg:phone":"+32 69 66 55 58",
    "sg:postcode":"7903",
    "sg:province":"Hainaut",
    "sg:tags":[
        "garage"
    ],
    "wof:name":"Phil-occas",
    "wof:placetype":"venue"
},
  "geometry": {"coordinates":[3.657296896,50.6060142517],"type":"Point"}
}