{
  "type": "Feature",
  "properties": {
    "iso:country":"BE",
    "sg:address":"Rue De La Station 28",
    "sg:city":"Courcelles (gouy-lez-pi\u00e9ton)",
    "sg:classifiers":[
        {
            "category":"Retail",
            "subcategory":"Event Space",
            "type":"Services"
        }
    ],
    "sg:phone":"+32 71 84 03 73",
    "sg:postcode":"6181",
    "sg:province":"Hainaut",
    "sg:tags":[
        "organisation"
    ],
    "wof:name":"Quatre Chapitre (aux)",
    "wof:placetype":"venue"
},
  "geometry": {"coordinates":[4.3296399117,50.4896354675],"type":"Point"}
}