{
  "type": "Feature",
  "properties": {
    "addr:full":"Van Kerckhovenstraat 62 Puurs Antwerpen 2870",
    "addr:housenumber":"62",
    "addr:postcode":"2870",
    "addr:street":"Van Kerckhovenstraat",
    "iso:country":"BE",
    "sg:address":"Van Kerckhovenstraat 62",
    "sg:city":"Puurs",
    "sg:orig_category":"Sportclubs Sportterreinen and installaties behalve sportcentra",
    "sg:phone":"+32 3 899 21 37",
    "sg:postcode":"2870",
    "sg:province":"Antwerpen",
    "wof:name":"Kalfort Sportif",
    "wof:placetype":"venue"
},
  "geometry": {"coordinates":[4.2963218689,51.0749206543],"type":"Point"}
}