{
  "type": "Feature",
  "properties": {
    "iso:country":"BE",
    "sg:address":"Waversebaan 8",
    "sg:city":"Leuven",
    "sg:orig_category":"Instituts de beaut\u00e9",
    "sg:phone":"+32 16 23 35 06",
    "sg:postcode":"3001",
    "sg:province":"Vlaams-Brabant",
    "wof:name":"Instituut Cosmovita",
    "wof:placetype":"venue"
},
  "geometry": {"coordinates":[4.6957101822,50.8656806946],"type":"Point"}
}