{
  "type": "Feature",
  "properties": {
    "iso:country":"BE",
    "sg:address":"Troonstraat 130",
    "sg:city":"Elsene",
    "sg:orig_category":"Chemicali\u00ebn Gh",
    "sg:phone":"+32 2 639 18 11",
    "sg:postcode":"1050",
    "sg:province":"Bruxelles-Capitale",
    "wof:name":"Tessenderlo Chemie",
    "wof:placetype":"venue"
},
  "geometry": {"coordinates":[4.3714909554,50.8359489441],"type":"Point"}
}