{
  "type": "Feature",
  "properties": {
    "addr:full":"Place Froissart 13 Chimay Hainaut 6460",
    "addr:housenumber":"13",
    "addr:postcode":"6460",
    "addr:street":"Place Froissart",
    "iso:country":"BE",
    "sg:address":"Place Froissart 13",
    "sg:city":"Chimay",
    "sg:orig_category":"Banques and organismes de cr\u00e9dit",
    "sg:phone":"+32 60 21 40 53",
    "sg:postcode":"6460",
    "sg:province":"Hainaut",
    "wof:name":"C.p.h.",
    "wof:placetype":"venue"
},
  "geometry": {"coordinates":[4.3135328293,50.0472259521],"type":"Point"}
}