{
  "type": "Feature",
  "properties": {
    "iso:country":"BE",
    "sg:address":"Eug\u00c8ne Plaskysquare 90",
    "sg:city":"Schaarbeek/schaerbeek",
    "sg:orig_category":"Herstelling horloges and juwelen",
    "sg:phone":"+32 2 733 73 52",
    "sg:postcode":"1030",
    "sg:province":"Bruxelles-Capitale",
    "wof:name":"Joseph Theys",
    "wof:placetype":"venue"
},
  "geometry": {"coordinates":[4.3956108093,50.8509292603],"type":"Point"}
}