{
  "type": "Feature",
  "properties": {
    "addr:full":"Renouprez 817 Herve (charneux) Li\u00e8ge 4654",
    "addr:housenumber":"817",
    "addr:postcode":"4654",
    "addr:street":"Renouprez",
    "iso:country":"BE",
    "sg:address":"Renouprez 817",
    "sg:city":"Herve (charneux)",
    "sg:classifiers":[
        {
            "category":"Health Services",
            "subcategory":"Doctor",
            "type":"Services"
        }
    ],
    "sg:phone":"+32 87 68 64 45",
    "sg:postcode":"4654",
    "sg:province":"Li\u00e8ge",
    "sg:tags":[
        "psychotherapist",
        "psychoanalyst"
    ],
    "wof:name":"Bruyninx M-c",
    "wof:placetype":"venue"
},
  "geometry": {"coordinates":[5.8042421341,50.6694908142],"type":"Point"}
}