{
  "type": "Feature",
  "properties": {
    "iso:country":"BE",
    "sg:address":"Leenhaagstraat 21a",
    "sg:city":"Zoutleeuw",
    "sg:orig_category":"Eclairage et \u00e9quipements du foyer",
    "sg:phone":"+32 11 58 97 22",
    "sg:postcode":"3440",
    "sg:province":"Vlaams-Brabant",
    "wof:name":"Crystal Valley",
    "wof:placetype":"venue"
},
  "geometry": {"coordinates":[5.0686721802,50.8701972961],"type":"Point"}
}