{
  "type": "Feature",
  "properties": {
    "addr:full":"Chauss\u00e9e Verte 12 Remicourt (momalle) Li\u00e8ge 4350",
    "addr:housenumber":"12",
    "addr:postcode":"4350",
    "addr:street":"Chausse\u0301E Verte",
    "iso:country":"BE",
    "sg:address":"Chauss\u00e9e Verte 12",
    "sg:city":"Remicourt (momalle)",
    "sg:classifiers":[
        {
            "category":"Retail",
            "subcategory":"Auto Repair",
            "type":"Services"
        }
    ],
    "sg:phone":"+32 4 257 72 57",
    "sg:postcode":"4350",
    "sg:province":"Li\u00e8ge",
    "sg:tags":[
        "breakdown",
        "automobile",
        "-",
        "recovery"
    ],
    "wof:name":"Garage Munsters Tcs Sprl",
    "wof:placetype":"venue"
},
  "geometry": {"coordinates":[5.3954739571,50.6901397705],"type":"Point"}
}