{
  "type": "Feature",
  "properties": {
    "addr:full":"Waterloose Steenweg 1485 Ukkel/uccle Bruxelles-Capitale 1180",
    "addr:housenumber":"1485",
    "addr:postcode":"1180",
    "addr:street":"Waterloose Steenweg;/",
    "iso:country":"BE",
    "sg:address":"Waterloose Steenweg 1485",
    "sg:city":"Ukkel/uccle",
    "sg:orig_category":"Antiek",
    "sg:phone":"+32 2 374 07 04",
    "sg:postcode":"1180",
    "sg:province":"Bruxelles-Capitale",
    "wof:name":"Maison Young",
    "wof:placetype":"venue"
},
  "geometry": {"coordinates":[4.3791718483,50.7831001282],"type":"Point"}
}