{
  "type": "Feature",
  "properties": {
    "addr:full":"Regentieplein 44 Sint-niklaas Oost-Vlaanderen 9100",
    "addr:housenumber":"44",
    "addr:postcode":"9100",
    "addr:street":"Regentieplein",
    "iso:country":"BE",
    "sg:address":"Regentieplein 44",
    "sg:city":"Sint-niklaas",
    "sg:classifiers":[
        {
            "category":"Bars & Pubs",
            "type":"Food & Drink"
        }
    ],
    "sg:phone":"+32 3 777 07 13",
    "sg:postcode":"9100",
    "sg:province":"Oost-Vlaanderen",
    "wof:name":"Barfly",
    "wof:placetype":"venue"
},
  "geometry": {"coordinates":[4.1473250389,51.168170929],"type":"Point"}
}