{
  "type": "Feature",
  "properties": {
    "addr:full":"Torrekensstraat 2 Steenokkerzeel Vlaams-Brabant 1820",
    "addr:housenumber":"2",
    "addr:postcode":"1820",
    "addr:street":"Torrekensstraat",
    "iso:country":"BE",
    "sg:address":"Torrekensstraat 2",
    "sg:city":"Steenokkerzeel",
    "sg:classifiers":[
        {
            "category":"Bars & Pubs",
            "type":"Food & Drink"
        }
    ],
    "sg:phone":"+32 2 759 93 36",
    "sg:postcode":"1820",
    "sg:province":"Vlaams-Brabant",
    "sg:tags":[
        "tavern"
    ],
    "wof:name":"Kraaienest ('t) Bvba",
    "wof:placetype":"venue"
},
  "geometry": {"coordinates":[4.5116758347,50.9091529846],"type":"Point"}
}