{
  "type": "Feature",
  "properties": {
    "addr:full":"Rue D'anth\u00e9e 29 Mettet (ermeton-sur-biert) Namur 5644",
    "addr:housenumber":"29",
    "addr:postcode":"5644",
    "addr:street":"Rue D'Anthe \u0301E;Ermeton-Sur-Biert",
    "iso:country":"BE",
    "sg:address":"Rue D'anth\u00e9e 29",
    "sg:city":"Mettet (ermeton-sur-biert)",
    "sg:classifiers":[
        {
            "category":"Health Services",
            "subcategory":"Health Practitioner",
            "type":"Services"
        }
    ],
    "sg:phone":"+32 71 72 77 39",
    "sg:postcode":"5644",
    "sg:province":"Namur",
    "sg:tags":[
        "physiotherapist"
    ],
    "wof:name":"Gustin F",
    "wof:placetype":"venue"
},
  "geometry": {"coordinates":[4.7210922241,50.2987670898],"type":"Point"}
}