{
  "type": "Feature",
  "properties": {
    "addr:full":"Kapelstraat 30 Wuustwezel (loenhout) Antwerpen 2990",
    "addr:housenumber":"30",
    "addr:postcode":"2990",
    "addr:street":"Kapelstraat",
    "iso:country":"BE",
    "sg:address":"Kapelstraat 30",
    "sg:city":"Wuustwezel (loenhout)",
    "sg:classifiers":[
        {
            "category":"Health Services",
            "subcategory":"Dentist",
            "type":"Services"
        }
    ],
    "sg:phone":"+32 3 669 97 55",
    "sg:postcode":"2990",
    "sg:province":"Antwerpen",
    "wof:name":"Delcroix Gilberte",
    "wof:placetype":"venue"
},
  "geometry": {"coordinates":[4.6460299492,51.3997154236],"type":"Point"}
}