{
  "type": "Feature",
  "properties": {
    "iso:country":"BE",
    "sg:address":"Rue De Stassart 109",
    "sg:city":"Bruxelles (ixelles)",
    "sg:classifiers":[
        {
            "category":"Professional",
            "subcategory":"Art Services",
            "type":"Services"
        }
    ],
    "sg:phone":"+32 474 49 80 15",
    "sg:postcode":"1050",
    "sg:province":"Bruxelles-Capitale",
    "sg:tags":[
        "children's",
        "animation"
    ],
    "wof:name":"Ange Du Sud (l')",
    "wof:placetype":"venue"
},
  "geometry": {"coordinates":[4.358757019,50.8345947266],"type":"Point"}
}