{
  "type": "Feature",
  "properties": {
    "addr:full":"Henri Werriestraat 85 Jette/jette Bruxelles-Capitale 1090",
    "addr:housenumber":"85",
    "addr:postcode":"1090",
    "addr:street":"Henri Werriestraat",
    "iso:country":"BE",
    "sg:address":"Henri Werriestraat 85",
    "sg:city":"Jette/jette",
    "sg:orig_category":"Boekhandels",
    "sg:phone":"+32 2 428 43 19",
    "sg:postcode":"1090",
    "sg:province":"Bruxelles-Capitale",
    "wof:name":"Bookcenter",
    "wof:placetype":"venue"
},
  "geometry": {"coordinates":[4.3276720047,50.8766479492],"type":"Point"}
}