{
  "type": "Feature",
  "properties": {
    "addr:full":"Av L\u00e9opold Iii 363 P\u00e9ronnes-lez-binche Hainaut 7134",
    "addr:housenumber":"363",
    "addr:postcode":"7134",
    "addr:street":"Av Le\u0301Opold Iii;Hainaut",
    "iso:country":"BE",
    "sg:address":"Av L\u00e9opold Iii 363",
    "sg:city":"P\u00e9ronnes-lez-binche",
    "sg:classifiers":[
        {
            "category":"Food & Beverages",
            "subcategory":"Fruits & Vegetables",
            "type":"Retail Goods"
        }
    ],
    "sg:phone":"+32 9 381 83 00",
    "sg:postcode":"7134",
    "sg:province":"Hainaut",
    "sg:tags":[
        "frozen",
        "product",
        "related"
    ],
    "wof:name":"Nv Willequet Potato Products",
    "wof:placetype":"venue"
},
  "geometry": {"coordinates":[3.5542340279,50.953338623],"type":"Point"}
}