{
  "type": "Feature",
  "properties": {
    "iso:country":"BE",
    "sg:address":"Zonnestraat 4",
    "sg:city":"Haaltert",
    "sg:orig_category":"Enseignement maternel and primaire",
    "sg:phone":"+32 54 33 92 13",
    "sg:postcode":"9450",
    "sg:province":"Oost-Vlaanderen",
    "wof:name":"Vrije Basisschool",
    "wof:placetype":"venue"
},
  "geometry": {"coordinates":[4.0053901672,50.9010658264],"type":"Point"}
}