{
  "type": "Feature",
  "properties": {
    "iso:country":"BE",
    "sg:address":"Rue Du Beau Site 9",
    "sg:city":"Charleroi (mont-sur-marchienne)",
    "sg:classifiers":[
        {
            "category":"Manufacturing",
            "subcategory":"Furniture",
            "type":"Manufacturing & Wholesale Goods"
        }
    ],
    "sg:postcode":"6032",
    "sg:province":"Hainaut",
    "sg:tags":[
        "design",
        "-"
    ],
    "wof:name":"Acanthe-hocepied Thierry",
    "wof:placetype":"venue"
},
  "geometry": {"coordinates":[4.4211540222,50.3969573975],"type":"Point"}
}