{
  "type": "Feature",
  "properties": {
    "addr:full":"Brusselstraat 3 Ternat Vlaams-Brabant 1740",
    "addr:housenumber":"3",
    "addr:postcode":"1740",
    "addr:street":"Brusselstraat",
    "iso:country":"BE",
    "sg:address":"Brusselstraat 3",
    "sg:city":"Ternat",
    "sg:orig_category":"Fleurs and plantes",
    "sg:phone":"+32 2 582 70 00",
    "sg:postcode":"1740",
    "sg:province":"Vlaams-Brabant",
    "wof:name":"Tim Flower",
    "wof:placetype":"venue"
},
  "geometry": {"coordinates":[4.179017067,50.8723754883],"type":"Point"}
}