{
  "type": "Feature",
  "properties": {
    "iso:country":"BE",
    "sg:address":"Rue Du Tiblereau 1",
    "sg:city":"Binche (ressaix)",
    "sg:classifiers":[
        {
            "category":"Shopping",
            "subcategory":"Stationery & Office Supplies",
            "type":"Retail Goods"
        }
    ],
    "sg:phone":"+32 64 44 14 77",
    "sg:postcode":"7134",
    "sg:province":"Hainaut",
    "sg:tags":[
        "partition"
    ],
    "wof:name":"Techno-platre Sprl",
    "wof:placetype":"venue"
},
  "geometry": {"coordinates":[4.1974802017,50.4315185547],"type":"Point"}
}