{
  "type": "Feature",
  "properties": {
    "iso:country":"BE",
    "sg:address":"Tuimelaarstraat 10",
    "sg:city":"Zele",
    "sg:orig_category":"Plantes and fleurs Gr",
    "sg:phone":"+32 52 44 82 26",
    "sg:postcode":"9240",
    "sg:province":"Oost-Vlaanderen",
    "wof:name":"Beirens",
    "wof:placetype":"venue"
},
  "geometry": {"coordinates":[4.0271191597,51.0757637024],"type":"Point"}
}