{
  "type": "Feature",
  "properties": {
    "addr:full":"Rue De Montigny 145 Charleroi Hainaut 6000",
    "addr:housenumber":"145",
    "addr:postcode":"6000",
    "addr:street":"Rue De Montigny;Hainaut",
    "iso:country":"BE",
    "sg:address":"Rue De Montigny 145",
    "sg:city":"Charleroi",
    "sg:classifiers":[
        {
            "category":"Communications",
            "subcategory":"Television Station",
            "type":"Services"
        }
    ],
    "sg:phone":"+32 71 70 22 80",
    "sg:postcode":"6000",
    "sg:province":"Hainaut",
    "sg:tags":[
        "video",
        "audio",
        "verhuur"
    ],
    "wof:name":"City Vid\u00c9o-dvd",
    "wof:placetype":"venue"
},
  "geometry": {"coordinates":[4.4504098892,50.4055480957],"type":"Point"}
}