{
  "type": "Feature",
  "properties": {
    "addr:full":"Rijselsestraat 14 Loppem West-Vlaanderen 8210",
    "addr:housenumber":"14",
    "addr:postcode":"8210",
    "addr:street":"Rijselsestraat",
    "iso:country":"BE",
    "sg:address":"Rijselsestraat 14",
    "sg:city":"Loppem",
    "sg:orig_category":"R\u00e9parations d'appareils \u00e9lectrom\u00e9nagers. Electrom\u00e9nager, t\u00e9l\u00e9visions and radios",
    "sg:phone":"+32 50 82 35 99",
    "sg:postcode":"8210",
    "sg:province":"West-Vlaanderen",
    "wof:name":"Elektro Vandenberghe",
    "wof:placetype":"venue"
},
  "geometry": {"coordinates":[3.1965939999,51.1546936035],"type":"Point"}
}