{
  "type": "Feature",
  "properties": {
    "iso:country":"BE",
    "sg:address":"Excelsiorlaan 1b81",
    "sg:city":"Zaventem",
    "sg:orig_category":"Farmaceutische producten Gh",
    "sg:phone":"+32 2 725 20 52",
    "sg:postcode":"1930",
    "sg:province":"Vlaams-Brabant",
    "wof:name":"Instrumentation Laboratory",
    "wof:placetype":"venue"
},
  "geometry": {"coordinates":[4.4564580917,50.8810844421],"type":"Point"}
}