{
  "type": "Feature",
  "properties": {
    "iso:country":"BE",
    "sg:address":"Rue Du Centre 77",
    "sg:city":"L\u00c9glise",
    "sg:orig_category":"Instellingen voor mindervalide volwassenen",
    "sg:phone":"+32 63 60 08 00",
    "sg:postcode":"6860",
    "sg:province":"Luxembourg",
    "wof:name":"La Maison De Volaiville",
    "wof:placetype":"venue"
},
  "geometry": {"coordinates":[5.5349779129,49.7996826172],"type":"Point"}
}