{
  "type": "Feature",
  "properties": {
    "addr:full":"Rue D'ab\u00c9e 27b Tinlot Li\u00e8ge 4557",
    "addr:housenumber":"27b",
    "addr:postcode":"4557",
    "addr:street":"Rue D'Abe \u0301E",
    "iso:country":"BE",
    "sg:address":"Rue D'ab\u00c9e 27b",
    "sg:city":"Tinlot",
    "sg:orig_category":"Installatie van houten of kunststof schrijnwerk",
    "sg:phone":"+32 85 51 22 04",
    "sg:postcode":"4557",
    "sg:province":"Li\u00e8ge",
    "wof:name":"Gerard Demoitie",
    "wof:placetype":"venue"
},
  "geometry": {"coordinates":[5.3797860146,50.4808921814],"type":"Point"}
}