{
  "type": "Feature",
  "properties": {
    "addr:full":"Beukenhofstraat 112 Anzegem West-Vlaanderen 8570",
    "addr:housenumber":"112",
    "addr:postcode":"8570",
    "addr:street":"Beukenhofstraat",
    "iso:country":"BE",
    "sg:address":"Beukenhofstraat 112",
    "sg:city":"Anzegem",
    "sg:orig_category":"Assistances juridiques",
    "sg:phone":"+32 56 77 56 38",
    "sg:postcode":"8570",
    "sg:province":"West-Vlaanderen",
    "wof:name":"Eur.trading Auction House",
    "wof:placetype":"venue"
},
  "geometry": {"coordinates":[3.3912060261,50.8336906433],"type":"Point"}
}