{
  "type": "Feature",
  "properties": {
    "addr:full":"Hulstbaan 249 Sint-niklaas (sinaai) Oost-Vlaanderen 9112",
    "addr:housenumber":"249",
    "addr:postcode":"9112",
    "iso:country":"BE",
    "sg:address":"Hulstbaan 249",
    "sg:city":"Sint-niklaas (sinaai)",
    "sg:classifiers":[
        {
            "category":"Shopping",
            "type":"Retail Goods"
        }
    ],
    "sg:phone":"+32 3 772 65 22",
    "sg:postcode":"9112",
    "sg:province":"Oost-Vlaanderen",
    "sg:tags":[
        "product",
        "cleaning",
        "maintenance"
    ],
    "wof:name":"Tasha International Bvba",
    "wof:placetype":"venue"
},
  "geometry": {"coordinates":[4.0246458054,51.1389923096],"type":"Point"}
}