{
  "type": "Feature",
  "properties": {
    "addr:full":"Bredestraat 204 Aalst Oost-Vlaanderen 9300",
    "addr:housenumber":"204",
    "addr:postcode":"9300",
    "addr:street":"Bredestraat",
    "iso:country":"BE",
    "sg:address":"Bredestraat 204",
    "sg:city":"Aalst",
    "sg:classifiers":[
        {
            "category":"Government",
            "subcategory":"Post Office",
            "type":"Public Place"
        }
    ],
    "sg:phone":"+32 53 77 74 90",
    "sg:postcode":"9300",
    "sg:province":"Oost-Vlaanderen",
    "sg:tags":[
        "yoga"
    ],
    "wof:name":"Yoga",
    "wof:placetype":"venue"
},
  "geometry": {"coordinates":[4.0441741943,50.9541130066],"type":"Point"}
}