{
  "type": "Feature",
  "properties": {
    "iso:country":"BE",
    "sg:address":"Taaienberg 6",
    "sg:city":"Maarkedal",
    "sg:orig_category":"Landmeters",
    "sg:phone":"+32 55 31 61 97",
    "sg:postcode":"9680",
    "sg:province":"Oost-Vlaanderen",
    "wof:name":"J. Duc\u00c2tillon",
    "wof:placetype":"venue"
},
  "geometry": {"coordinates":[3.6352899075,50.7957191467],"type":"Point"}
}