{
  "type": "Feature",
  "properties": {
    "iso:country":"BE",
    "sg:address":"Stationsplein 2",
    "sg:city":"Bornem",
    "sg:classifiers":[
        {
            "category":"Travel",
            "subcategory":"Hotels & Motels",
            "type":"Entertainment"
        }
    ],
    "sg:phone":"+32 3 889 13 67",
    "sg:postcode":"2880",
    "sg:province":"Antwerpen",
    "wof:name":"Notelaer (de)",
    "wof:placetype":"venue"
},
  "geometry": {"coordinates":[4.2410569191,51.0986022949],"type":"Point"}
}