{
  "type": "Feature",
  "properties": {
    "addr:full":"Jan Sanderslaan 98 Hemiksem Antwerpen 2620",
    "addr:housenumber":"98",
    "addr:postcode":"2620",
    "addr:street":"Jan Sanderslaan",
    "iso:country":"BE",
    "sg:address":"Jan Sanderslaan 98",
    "sg:city":"Hemiksem",
    "sg:classifiers":[
        {
            "category":"Autos & Motor Vehicles",
            "subcategory":"Fuel & Gas Station",
            "type":"Retail Goods"
        }
    ],
    "sg:phone":"+32 3 887 51 88",
    "sg:postcode":"2620",
    "sg:province":"Antwerpen",
    "wof:name":"98 Hemiksem",
    "wof:placetype":"venue"
},
  "geometry": {"coordinates":[4.3502931595,51.1371765137],"type":"Point"}
}