{
  "type": "Feature",
  "properties": {
    "addr:full":"Lierseweg 104 Herentals Antwerpen 2200",
    "addr:housenumber":"104",
    "addr:postcode":"2200",
    "addr:street":"Lierseweg",
    "iso:country":"BE",
    "sg:address":"Lierseweg 104",
    "sg:city":"Herentals",
    "sg:classifiers":[
        {
            "category":"Professional",
            "subcategory":"Lawyer & Legal Services",
            "type":"Services"
        }
    ],
    "sg:phone":"+32 14 21 56 86",
    "sg:postcode":"2200",
    "sg:province":"Antwerpen",
    "wof:name":"Verhaegen H",
    "wof:placetype":"venue"
},
  "geometry": {"coordinates":[4.8249650002,51.1758422852],"type":"Point"}
}