{
  "type": "Feature",
  "properties": {
    "addr:full":"Rue Georges Bodard 71 Musson Luxembourg 6750",
    "addr:housenumber":"71",
    "addr:postcode":"6750",
    "addr:street":"Rue Georges Bodard",
    "iso:country":"BE",
    "sg:address":"Rue Georges Bodard 71",
    "sg:city":"Musson",
    "sg:classifiers":[
        {
            "category":"Insurance",
            "subcategory":"Insurance Agent",
            "type":"Services"
        }
    ],
    "sg:phone":"+32 63 67 53 45",
    "sg:postcode":"6750",
    "sg:province":"Luxembourg",
    "sg:tags":[
        "verzekeringsmakelaars",
        "expert"
    ],
    "wof:name":"J. Pierson",
    "wof:placetype":"venue"
},
  "geometry": {"coordinates":[5.7190599442,49.5588417053],"type":"Point"}
}