{
  "type": "Feature",
  "properties": {
    "iso:country":"BE",
    "sg:address":"Beekstraat 75",
    "sg:city":"Sint-niklaas",
    "sg:orig_category":"Newspapers, magazines, periodicals - Distribution",
    "sg:phone":"+32 3 777 27 78",
    "sg:postcode":"9100",
    "sg:province":"Oost-Vlaanderen",
    "wof:name":"Van Diggelen I",
    "wof:placetype":"venue"
},
  "geometry": {"coordinates":[4.1358151436,51.1611251831],"type":"Point"}
}