{
  "type": "Feature",
  "properties": {
    "iso:country":"BE",
    "sg:address":"Rue Cyrille Bauwens 27",
    "sg:city":"Grez-doiceau",
    "sg:orig_category":"Travaux de pl\u00e2trage. Rev\u00eatements pour sols and murs. Installation de menuiserie en bois and plastiqu",
    "sg:phone":"+32 10 84 02 62",
    "sg:postcode":"1390",
    "sg:province":"Brabant Wallon",
    "wof:name":"Adrien Pierre",
    "wof:placetype":"venue"
},
  "geometry": {"coordinates":[4.6497030258,50.7740402222],"type":"Point"}
}