{
  "type": "Feature",
  "properties": {
    "addr:full":"Notmeir 82 Duffel Antwerpen 2570",
    "addr:housenumber":"82",
    "addr:postcode":"2570",
    "addr:street":"Notmeir",
    "iso:country":"BE",
    "sg:address":"Notmeir 82",
    "sg:city":"Duffel",
    "sg:classifiers":[
        {
            "category":"Building & Trades",
            "subcategory":"Plumbing",
            "type":"Services"
        }
    ],
    "sg:phone":"+32 15 31 27 98",
    "sg:postcode":"2570",
    "sg:province":"Antwerpen",
    "sg:tags":[
        "diver",
        "commerce",
        "gr",
        "pour",
        "equipement"
    ],
    "wof:name":"Borvo",
    "wof:placetype":"venue"
},
  "geometry": {"coordinates":[4.4696989059,51.0798072815],"type":"Point"}
}