{
  "type": "Feature",
  "properties": {
    "iso:country":"BE",
    "sg:address":"7130",
    "sg:city":"Binche (groot)",
    "sg:orig_category":"Pharmaciens",
    "sg:phone":"+32 900 10 500",
    "sg:postcode":"7130",
    "sg:province":"Hainaut",
    "wof:name":"Pharmacies De Garde",
    "wof:placetype":"venue"
},
  "geometry": {"coordinates":[4.0946698189,50.4318199158],"type":"Point"}
}