{
  "type": "Feature",
  "properties": {
    "iso:country":"BE",
    "sg:address":"Turnhoutsebaan 5 Bus A-0",
    "sg:city":"Wijnegem",
    "sg:orig_category":"V\u00eatements pour b\u00e9b\u00e9s and enfants. V\u00eatements pour Hommes. V\u00eatements pour Dames",
    "sg:phone":"+32 3 353 30 66",
    "sg:postcode":"2110",
    "sg:province":"Antwerpen",
    "wof:name":"C&a",
    "wof:placetype":"venue"
},
  "geometry": {"coordinates":[4.5248470306,51.2279434204],"type":"Point"}
}