{
  "type": "Feature",
  "properties": {
    "addr:full":"Hulstplein 36 Tielt West-Vlaanderen 8700",
    "addr:housenumber":"36",
    "addr:postcode":"8700",
    "addr:street":"Hulstplein",
    "iso:country":"BE",
    "sg:address":"Hulstplein 36",
    "sg:city":"Tielt",
    "sg:classifiers":[
        {
            "category":"Professional",
            "subcategory":"Business Services",
            "type":"Services"
        }
    ],
    "sg:phone":"+32 56 60 20 42",
    "sg:postcode":"8700",
    "sg:province":"West-Vlaanderen",
    "sg:tags":[
        "advice",
        "fabric",
        "clothes"
    ],
    "wof:name":"Yves Maenhout Bvba Textiles Recycling",
    "wof:placetype":"venue"
},
  "geometry": {"coordinates":[3.3307700157,50.9965591431],"type":"Point"}
}