{
  "type": "Feature",
  "properties": {
    "iso:country":"BE",
    "sg:address":"Rue Bureau 56",
    "sg:city":"Fleron",
    "sg:orig_category":"Plaatsen van vloer- and muurbekleding Schilders Verlichting and huishoudartikelen",
    "sg:phone":"+32 4 358 86 66",
    "sg:postcode":"4621",
    "sg:province":"Li\u00e8ge",
    "wof:name":"Home Market",
    "wof:placetype":"venue"
},
  "geometry": {"coordinates":[5.6940169334,50.6134376526],"type":"Point"}
}