{
  "type": "Feature",
  "properties": {
    "addr:full":"Lorzestraat 3 Dessel Antwerpen 2480",
    "addr:housenumber":"3",
    "addr:postcode":"2480",
    "addr:street":"Lorzestraat",
    "iso:country":"BE",
    "sg:address":"Lorzestraat 3",
    "sg:city":"Dessel",
    "sg:orig_category":"Banken and kredietinstellingen",
    "sg:phone":"+32 14 37 78 11",
    "sg:postcode":"2480",
    "sg:province":"Antwerpen",
    "wof:name":"Fortis",
    "wof:placetype":"venue"
},
  "geometry": {"coordinates":[5.1150817871,51.2392463684],"type":"Point"}
}