{
  "type": "Feature",
  "properties": {
    "addr:full":"Hauptstrasse 93 Sankt Vith Li\u00e8ge 4780",
    "addr:housenumber":"93",
    "addr:postcode":"4780",
    "addr:street":"Hauptstrasse",
    "iso:country":"BE",
    "sg:address":"Hauptstrasse 93",
    "sg:city":"Sankt Vith",
    "sg:classifiers":[
        {
            "category":"Shopping",
            "subcategory":"Hobbies, Toys, & Games",
            "type":"Retail Goods"
        }
    ],
    "sg:phone":"+32 80 22 81 28",
    "sg:postcode":"4780",
    "sg:province":"Li\u00e8ge",
    "sg:tags":[
        "toy",
        "-"
    ],
    "wof:name":"Kinderparadies",
    "wof:placetype":"venue"
},
  "geometry": {"coordinates":[6.1245880127,50.2821426392],"type":"Point"}
}