{
  "type": "Feature",
  "properties": {
    "addr:full":"Ambachtstraat 26 Beerse Antwerpen 2340",
    "addr:housenumber":"26",
    "addr:postcode":"2340",
    "addr:street":"Ambachtstraat",
    "iso:country":"BE",
    "sg:address":"Ambachtstraat 26",
    "sg:city":"Beerse",
    "sg:classifiers":[
        {
            "category":"Restaurant",
            "type":"Food & Drink"
        }
    ],
    "sg:phone":"+32 14 61 67 57",
    "sg:postcode":"2340",
    "sg:province":"Antwerpen",
    "sg:tags":[
        "industrial",
        "kitchen",
        "catering"
    ],
    "wof:name":"Adriaantje Roomijs",
    "wof:placetype":"venue"
},
  "geometry": {"coordinates":[4.8339700699,51.3025283813],"type":"Point"}
}