{
  "type": "Feature",
  "properties": {
    "addr:full":"Rue Jean-baptiste Loriaux 3b Frasnes-lez-gosselies Hainaut 6210",
    "addr:housenumber":"3b",
    "addr:postcode":"6210",
    "addr:street":"Rue Jean-Baptiste Loriaux",
    "iso:country":"BE",
    "sg:address":"Rue Jean-baptiste Loriaux 3b",
    "sg:city":"Frasnes-lez-gosselies",
    "sg:classifiers":[
        {
            "category":"Home & Garden",
            "subcategory":"Carpets & Floor Coverings",
            "type":"Retail Goods"
        }
    ],
    "sg:phone":"+32 71 85 11 24",
    "sg:postcode":"6210",
    "sg:province":"Hainaut",
    "wof:name":"M\u00e9lon S.a.",
    "wof:placetype":"venue"
},
  "geometry": {"coordinates":[4.4496450424,50.5312309265],"type":"Point"}
}