{
  "type": "Feature",
  "properties": {
    "addr:full":"Rue G. Defnet 14 Soumagne Li\u00e8ge 4630",
    "addr:housenumber":"14",
    "addr:postcode":"4630",
    "addr:street":"Rue G. Defnet",
    "iso:country":"BE",
    "sg:address":"Rue G. Defnet 14",
    "sg:city":"Soumagne",
    "sg:orig_category":"Mat\u00e9riel \u00e9lectrique and \u00e9lectronique Gr",
    "sg:phone":"+32 4 377 38 98",
    "sg:postcode":"4630",
    "sg:province":"Li\u00e8ge",
    "wof:name":"Dardenne",
    "wof:placetype":"venue"
},
  "geometry": {"coordinates":[5.7472958565,50.6121063232],"type":"Point"}
}