{
  "type": "Feature",
  "properties": {
    "iso:country":"BE",
    "sg:address":"All\u00c9e Des Coquelicots 2",
    "sg:city":"Vise",
    "sg:orig_category":"Tuinen",
    "sg:phone":"+32 4 379 61 93",
    "sg:postcode":"4600",
    "sg:province":"Li\u00e8ge",
    "wof:name":"Bruno Clesse",
    "wof:placetype":"venue"
},
  "geometry": {"coordinates":[5.7049651146,50.7342834473],"type":"Point"}
}