{
  "type": "Feature",
  "properties": {
    "addr:full":"Kapelleweg 6 Haacht Vlaams-Brabant 3150",
    "addr:housenumber":"6",
    "addr:postcode":"3150",
    "addr:street":"Kapelleweg",
    "iso:country":"BE",
    "sg:address":"Kapelleweg 6",
    "sg:city":"Haacht",
    "sg:orig_category":"Locations de machines and \u00e9quipement pour la construction. Moteurs, transformateurs and groupes \u00e9lec",
    "sg:phone":"+32 16 60 81 82",
    "sg:postcode":"3150",
    "sg:province":"Vlaams-Brabant",
    "wof:name":"The Powershop",
    "wof:placetype":"venue"
},
  "geometry": {"coordinates":[4.6598029137,50.9443588257],"type":"Point"}
}