{
  "type": "Feature",
  "properties": {
    "addr:full":"Meerdorp 35 Hoogstraten Antwerpen 2321",
    "addr:housenumber":"35",
    "addr:postcode":"2321",
    "addr:street":"Meerdorp",
    "iso:country":"BE",
    "sg:address":"Meerdorp 35",
    "sg:city":"Hoogstraten",
    "sg:orig_category":"Assurances. Bureaux de poste",
    "sg:phone":"+32 3 315 71 12",
    "sg:postcode":"2321",
    "sg:province":"Antwerpen",
    "wof:name":"De Post",
    "wof:placetype":"venue"
},
  "geometry": {"coordinates":[4.7366099358,51.442325592],"type":"Point"}
}