{
  "type": "Feature",
  "properties": {
    "addr:full":"Rue De L'autonomie 22 Bruxelles (anderlecht) Bruxelles-Capitale 1070",
    "addr:housenumber":"22",
    "addr:postcode":"1070",
    "addr:street":"Rue De L'Autonomie",
    "iso:country":"BE",
    "sg:address":"Rue De L'autonomie 22",
    "sg:city":"Bruxelles (anderlecht)",
    "sg:classifiers":[
        {
            "category":"Social Services",
            "type":"Services"
        }
    ],
    "sg:phone":"+32 2 527 25 75",
    "sg:postcode":"1070",
    "sg:province":"Bruxelles-Capitale",
    "wof:name":"F\u00e9d\u00e9ration Des Associations De Parents De L'enseignement Officiel",
    "wof:placetype":"venue"
},
  "geometry": {"coordinates":[4.3378009796,50.8401832581],"type":"Point"}
}