{
  "type": "Feature",
  "properties": {
    "iso:country":"BE",
    "sg:address":"Rue Des Bocages 40",
    "sg:city":"Aubel",
    "sg:orig_category":"Schoenen",
    "sg:phone":"+32 87 68 70 54",
    "sg:postcode":"4880",
    "sg:province":"Li\u00e8ge",
    "wof:name":"Marie-ange Willems",
    "wof:placetype":"venue"
},
  "geometry": {"coordinates":[5.8477802277,50.698638916],"type":"Point"}
}