{
  "type": "Feature",
  "properties": {
    "iso:country":"BE",
    "sg:address":"Avenue De Monte Carlo 102 88",
    "sg:city":"Bruxelles",
    "sg:classifiers":[
        {
            "category":"Autos & Motor Vehicles",
            "subcategory":"Fuel & Gas Station",
            "type":"Retail Goods"
        }
    ],
    "sg:phone":"+32 2 343 26 70",
    "sg:postcode":"1190",
    "sg:province":"Bruxelles-Capitale",
    "sg:tags":[
        "condenser",
        "air"
    ],
    "wof:name":"Balcke - Durr S.a.",
    "wof:placetype":"venue"
},
  "geometry": {"coordinates":[4.3226699829,50.8112716675],"type":"Point"}
}