{
  "type": "Feature",
  "properties": {
    "iso:country":"BE",
    "sg:address":"Aarschotsesteenweg 153",
    "sg:city":"Rotselaar (wezemaal)",
    "sg:orig_category":"Newspapers, magazines, periodicals - Distribution",
    "sg:phone":"+32 16 50 04 92",
    "sg:postcode":"3111",
    "sg:province":"Vlaams-Brabant",
    "wof:name":"Press & Service",
    "wof:placetype":"venue"
},
  "geometry": {"coordinates":[4.7501301765,50.9466514587],"type":"Point"}
}