{
  "type": "Feature",
  "properties": {
    "iso:country":"BE",
    "sg:address":"Rue Berckmans 4",
    "sg:city":"Sint-gillis/saint-gilles",
    "sg:orig_category":"Salles de spectacles",
    "sg:phone":"+32 2 539 34 70",
    "sg:postcode":"1060",
    "sg:province":"Bruxelles-Capitale",
    "wof:name":"Grommelo Company",
    "wof:placetype":"venue"
},
  "geometry": {"coordinates":[4.3573741913,50.8312072754],"type":"Point"}
}