{
  "type": "Feature",
  "properties": {
    "addr:full":"Chauss\u00e9e Brunehaut 137 Beloeil (quevaucamps) Hainaut 7972",
    "addr:housenumber":"137",
    "addr:postcode":"7972",
    "addr:street":"Chausse\u0301E Brunehaut",
    "iso:country":"BE",
    "sg:address":"Chauss\u00e9e Brunehaut 137",
    "sg:city":"Beloeil (quevaucamps)",
    "sg:classifiers":[
        {
            "category":"Communications",
            "subcategory":"Radio Station",
            "type":"Services"
        }
    ],
    "sg:phone":"+32 69 56 18 49",
    "sg:postcode":"7972",
    "sg:province":"Hainaut",
    "sg:tags":[
        "local"
    ],
    "wof:name":"Radio Beloeil",
    "wof:placetype":"venue"
},
  "geometry": {"coordinates":[3.690969944,50.542301178],"type":"Point"}
}