{
  "type": "Feature",
  "properties": {
    "addr:full":"Dorpsstraat 24 Middelkerke West-Vlaanderen 8432",
    "addr:housenumber":"24",
    "addr:postcode":"8432",
    "addr:street":"Dorpsstraat",
    "iso:country":"BE",
    "sg:address":"Dorpsstraat 24",
    "sg:city":"Middelkerke",
    "sg:orig_category":"Verplichte sociale verzekeringen",
    "sg:phone":"+32 59 31 43 35",
    "sg:postcode":"8432",
    "sg:province":"West-Vlaanderen",
    "wof:name":"Christelijke Mutualiteit",
    "wof:placetype":"venue"
},
  "geometry": {"coordinates":[2.8773488998,51.1767501831],"type":"Point"}
}