{
  "type": "Feature",
  "properties": {
    "addr:full":"Jan Frans Willemsstraat 71 Lommel Limburg 3920",
    "addr:housenumber":"71",
    "addr:postcode":"3920",
    "addr:street":"Jan Frans Willemsstraat",
    "iso:country":"BE",
    "sg:address":"Jan Frans Willemsstraat 71",
    "sg:city":"Lommel",
    "sg:classifiers":[
        {
            "category":"Professional",
            "subcategory":"Accounting & Tax Preparation",
            "type":"Services"
        }
    ],
    "sg:phone":"+32 11 54 11 09",
    "sg:postcode":"3920",
    "sg:province":"Limburg",
    "sg:tags":[
        "bookkeeping"
    ],
    "wof:name":"Publi-flash Nv",
    "wof:placetype":"venue"
},
  "geometry": {"coordinates":[5.2825188637,51.2284622192],"type":"Point"}
}