{
  "type": "Feature",
  "properties": {
    "iso:country":"BE",
    "sg:address":"Rue Des Combattants 5",
    "sg:city":"Berloz (rosoux-crenwick)",
    "sg:classifiers":[
        {
            "category":"Farming",
            "subcategory":"Farm & Veterinary Services",
            "type":"Manufacturing & Wholesale Goods"
        }
    ],
    "sg:phone":"+32 19 32 31 19",
    "sg:postcode":"4257",
    "sg:province":"Li\u00e8ge",
    "sg:tags":[
        "agricultural",
        "contractor"
    ],
    "wof:name":"Jamilu Sc",
    "wof:placetype":"venue"
},
  "geometry": {"coordinates":[5.1880488396,50.7055473328],"type":"Point"}
}