{
  "type": "Feature",
  "properties": {
    "addr:full":"Koningin Elisabethlaan 29 Gent Oost-Vlaanderen 9000",
    "addr:housenumber":"29",
    "addr:postcode":"9000",
    "addr:street":"Koningin Elisabethlaan;Oost-Vlaanderen",
    "iso:country":"BE",
    "sg:address":"Koningin Elisabethlaan 29",
    "sg:city":"Gent",
    "sg:classifiers":[
        {
            "category":"Cafe",
            "type":"Food & Drink"
        }
    ],
    "sg:phone":"+32 9 245 66 77",
    "sg:postcode":"9000",
    "sg:province":"Oost-Vlaanderen",
    "sg:tags":[
        "snack-bars"
    ],
    "wof:name":"Snack Moriti",
    "wof:placetype":"venue"
},
  "geometry": {"coordinates":[3.7136061192,51.0370101929],"type":"Point"}
}