{
  "type": "Feature",
  "properties": {
    "addr:full":"Hopstraat 40bb/5 Brussel/bruxelles Bruxelles-Capitale 1000",
    "addr:housenumber":"40bb / 5",
    "addr:postcode":"1000",
    "addr:street":"Hopstraat;/",
    "iso:country":"BE",
    "sg:address":"Hopstraat 40bb/5",
    "sg:city":"Brussel/bruxelles",
    "sg:classifiers":[
        {
            "category":"Cafe",
            "type":"Food & Drink"
        }
    ],
    "sg:phone":"+32 2 512 23 48",
    "sg:postcode":"1000",
    "sg:province":"Bruxelles-Capitale",
    "sg:tags":[
        "caf\u00e9s"
    ],
    "wof:name":"Olivier Battifoy",
    "wof:placetype":"venue"
},
  "geometry": {"coordinates":[4.3410620689,50.8510246277],"type":"Point"}
}