{
  "type": "Feature",
  "properties": {
    "addr:full":"P Leopoldplein 13 Sint-niklaas Oost-Vlaanderen 9100",
    "addr:housenumber":"13",
    "addr:postcode":"9100",
    "addr:street":"P Leopoldplein",
    "iso:country":"BE",
    "sg:address":"P Leopoldplein 13",
    "sg:city":"Sint-niklaas",
    "sg:orig_category":"Diverse bedrijfsbeheeradviesbureaus",
    "sg:phone":"+32 3 766 07 70",
    "sg:postcode":"9100",
    "sg:province":"Oost-Vlaanderen",
    "wof:name":"Euroconsult",
    "wof:placetype":"venue"
},
  "geometry": {"coordinates":[4.1521639824,51.1694641113],"type":"Point"}
}