{
  "type": "Feature",
  "properties": {
    "iso:country":"BE",
    "sg:address":"Kerkstraat 2",
    "sg:city":"Lovendegem",
    "sg:orig_category":"Banken and kredietinstellingen",
    "sg:phone":"+32 9 372 82 42",
    "sg:postcode":"9920",
    "sg:province":"Oost-Vlaanderen",
    "wof:name":"Fortis",
    "wof:placetype":"venue"
},
  "geometry": {"coordinates":[3.6068320274,51.094783783],"type":"Point"}
}