{
  "type": "Feature",
  "properties": {
    "addr:full":"Galgenstraat 1 Wijnegem Antwerpen 2110",
    "addr:housenumber":"1",
    "addr:postcode":"2110",
    "addr:street":"Galgenstraat",
    "iso:country":"BE",
    "sg:address":"Galgenstraat 1",
    "sg:city":"Wijnegem",
    "sg:classifiers":[
        {
            "category":"Autos & Motor Vehicles",
            "subcategory":"Automobile Sales",
            "type":"Retail Goods"
        }
    ],
    "sg:phone":"+32 3 353 45 85",
    "sg:postcode":"2110",
    "sg:province":"Antwerpen",
    "sg:tags":[
        "car",
        "used",
        "-"
    ],
    "wof:name":"Jazz Cars",
    "wof:placetype":"venue"
},
  "geometry": {"coordinates":[4.4970321655,51.2202110291],"type":"Point"}
}