{
  "type": "Feature",
  "properties": {
    "addr:full":"Rue Gr\u00e9try 71 Li\u00e8ge 1 (li\u00e8ge 2) Li\u00e8ge 4020",
    "addr:housenumber":"71;1;2",
    "addr:postcode":"4020",
    "addr:street":"Rue Gre\u0301Try",
    "iso:country":"BE",
    "sg:address":"Rue Gr\u00e9try 71",
    "sg:city":"Li\u00e8ge 1 (li\u00e8ge 2)",
    "sg:classifiers":[
        {
            "category":"Building & Trades",
            "subcategory":"Landscaping Services",
            "type":"Services"
        }
    ],
    "sg:phone":"+32 4 344 31 88",
    "sg:postcode":"4020",
    "sg:province":"Li\u00e8ge",
    "sg:tags":[
        "handicraft"
    ],
    "wof:name":"Art Et Bobe Sprl",
    "wof:placetype":"venue"
},
  "geometry": {"coordinates":[5.5843319893,50.6320381165],"type":"Point"}
}