{
  "type": "Feature",
  "properties": {
    "addr:full":"Brandheide 74 Bornem Antwerpen 2880",
    "addr:housenumber":"74",
    "addr:postcode":"2880",
    "addr:street":"Brandheide",
    "iso:country":"BE",
    "sg:address":"Brandheide 74",
    "sg:city":"Bornem",
    "sg:orig_category":"Travaux de finition and nettoyage de b\u00e2timents",
    "sg:phone":"+32 3 889 88 06",
    "sg:postcode":"2880",
    "sg:province":"Antwerpen",
    "wof:name":"Cowal",
    "wof:placetype":"venue"
},
  "geometry": {"coordinates":[4.2201890945,51.0864639282],"type":"Point"}
}