{
  "type": "Feature",
  "properties": {
    "addr:full":"Avenue Des Ch\u00e2teaux 119 Comines-warneton (comines) Hainaut 7780",
    "addr:housenumber":"119",
    "addr:postcode":"7780",
    "addr:street":"Avenue Des Cha\u0302Teaux",
    "iso:country":"BE",
    "sg:address":"Avenue Des Ch\u00e2teaux 119",
    "sg:city":"Comines-warneton (comines)",
    "sg:classifiers":[
        {
            "category":"Manufacturing",
            "subcategory":"Textiles",
            "type":"Manufacturing & Wholesale Goods"
        }
    ],
    "sg:phone":"+32 56 56 12 00",
    "sg:postcode":"7780",
    "sg:province":"Hainaut",
    "sg:tags":[
        "finishing"
    ],
    "wof:name":"Socomaille Sa",
    "wof:placetype":"venue"
},
  "geometry": {"coordinates":[2.998914957,50.7775382996],"type":"Point"}
}