{
  "type": "Feature",
  "properties": {
    "addr:full":"Oud Strijdersplein 1 Dendermonde Oost-Vlaanderen 9200",
    "addr:housenumber":"1",
    "addr:postcode":"9200",
    "addr:street":"Oud Strijdersplein;Oost-Vlaanderen",
    "iso:country":"BE",
    "sg:address":"Oud Strijdersplein 1",
    "sg:city":"Dendermonde",
    "sg:orig_category":"Boucheries",
    "sg:phone":"+32 52 21 16 01",
    "sg:postcode":"9200",
    "sg:province":"Oost-Vlaanderen",
    "wof:name":"A. Opdecam",
    "wof:placetype":"venue"
},
  "geometry": {"coordinates":[4.1124019623,51.0156974792],"type":"Point"}
}