{
  "type": "Feature",
  "properties": {
    "addr:full":"Avenue Des Tourterelles 24 Perwez Brabant Wallon 1360",
    "addr:housenumber":"24",
    "addr:postcode":"1360",
    "addr:street":"Avenue Des Tourterelles",
    "iso:country":"BE",
    "sg:address":"Avenue Des Tourterelles 24",
    "sg:city":"Perwez",
    "sg:orig_category":"Avocats and conseillers juridiques",
    "sg:phone":"+32 81 65 67 47",
    "sg:postcode":"1360",
    "sg:province":"Brabant Wallon",
    "wof:name":"A. Dekeuster",
    "wof:placetype":"venue"
},
  "geometry": {"coordinates":[4.8083558083,50.622718811],"type":"Point"}
}