{
  "type": "Feature",
  "properties": {
    "iso:country":"BE",
    "sg:address":"Place Roi-albert-ier 26",
    "sg:city":"Rochefort",
    "sg:orig_category":"Herstelling horloges and juwelen Juwelen and horloges",
    "sg:phone":"+32 84 21 13 00",
    "sg:postcode":"5580",
    "sg:province":"Namur",
    "wof:name":"Jules Devaux",
    "wof:placetype":"venue"
},
  "geometry": {"coordinates":[5.223045826,50.1577148438],"type":"Point"}
}