{
  "type": "Feature",
  "properties": {
    "iso:country":"BE",
    "sg:address":"Tervuursesteenweg 193a",
    "sg:city":"Leuven (heverlee)",
    "sg:classifiers":[
        {
            "category":"Home & Garden",
            "subcategory":"Furniture",
            "type":"Retail Goods"
        }
    ],
    "sg:phone":"+32 16 22 98 01",
    "sg:postcode":"3001",
    "sg:province":"Vlaams-Brabant",
    "sg:tags":[
        "used",
        "-"
    ],
    "wof:name":"Bij Staf",
    "wof:placetype":"venue"
},
  "geometry": {"coordinates":[4.6765432358,50.8751564026],"type":"Point"}
}