{
  "type": "Feature",
  "properties": {
    "iso:country":"BE",
    "sg:address":"Onder D'eike 2",
    "sg:city":"Arendonk",
    "sg:classifiers":[
        {
            "category":"Education",
            "subcategory":"School",
            "type":"Public Place"
        }
    ],
    "sg:phone":"+32 14 58 02 22",
    "sg:postcode":"2370",
    "sg:province":"Antwerpen",
    "sg:tags":[
        "breeding",
        "livestock",
        "cattle"
    ],
    "wof:name":"Vilatca Nv",
    "wof:placetype":"venue"
},
  "geometry": {"coordinates":[5.1052670479,51.3416175842],"type":"Point"}
}