{
  "type": "Feature",
  "properties": {
    "iso:country":"BE",
    "sg:address":"Nachtegalenstraat 106",
    "sg:city":"Lubbeek",
    "sg:orig_category":"M\u00e9decins and sp\u00e9cialistes",
    "sg:phone":"+32 16 25 49 42",
    "sg:postcode":"3210",
    "sg:province":"Vlaams-Brabant",
    "wof:name":"Marina Sente",
    "wof:placetype":"venue"
},
  "geometry": {"coordinates":[4.7542209625,50.893787384],"type":"Point"}
}