{
  "type": "Feature",
  "properties": {
    "iso:country":"BE",
    "sg:address":"Rue De La Villa Romaine 35",
    "sg:city":"Houffalize (nadrin)",
    "sg:classifiers":[
        {
            "category":"Building & Trades",
            "subcategory":"Construction",
            "type":"Services"
        }
    ],
    "sg:phone":"+32 84 44 43 72",
    "sg:postcode":"6660",
    "sg:province":"Luxembourg",
    "sg:tags":[
        "carpenter"
    ],
    "wof:name":"Hastir S",
    "wof:placetype":"venue"
},
  "geometry": {"coordinates":[5.677218914,50.1643028259],"type":"Point"}
}