{
  "type": "Feature",
  "properties": {
    "addr:full":"Zanddijk 35ba Dessel Antwerpen 2480",
    "addr:housenumber":"35ba",
    "addr:postcode":"2480",
    "addr:street":"Zanddijk",
    "iso:country":"BE",
    "sg:address":"Zanddijk 35ba",
    "sg:city":"Dessel",
    "sg:orig_category":"Location de v\u00e9hicules sauf voitures. Articles de camping and de sport",
    "sg:phone":"+32 14 37 36 67",
    "sg:postcode":"2480",
    "sg:province":"Antwerpen",
    "wof:name":"Deckx",
    "wof:placetype":"venue"
},
  "geometry": {"coordinates":[5.1341409683,51.2530021667],"type":"Point"}
}