{
  "type": "Feature",
  "properties": {
    "iso:country":"BE",
    "sg:address":"Avenue De L'exposition 426 Boite 53",
    "sg:city":"Jette (bruxelles)",
    "sg:orig_category":"Elektrische installaties voor woningen",
    "sg:phone":"+32 2 476 16 08",
    "sg:postcode":"1090",
    "sg:province":"Bruxelles-Capitale",
    "wof:name":"Rpm Electro",
    "wof:placetype":"venue"
},
  "geometry": {"coordinates":[4.3156991005,50.8904151917],"type":"Point"}
}