{
  "type": "Feature",
  "properties": {
    "iso:country":"BE",
    "sg:address":"Nieuwstraat 19",
    "sg:city":"Geel",
    "sg:orig_category":"Banques and organismes de cr\u00e9dit",
    "sg:phone":"+32 14 58 12 97",
    "sg:postcode":"2440",
    "sg:province":"Antwerpen",
    "wof:name":"Dexia",
    "wof:placetype":"venue"
},
  "geometry": {"coordinates":[4.9921121597,51.1626586914],"type":"Point"}
}