{
  "type": "Feature",
  "properties": {
    "iso:country":"BE",
    "sg:address":"Rue Abb\u00e9 Dropsy 39",
    "sg:city":"Tournai (kain)",
    "sg:classifiers":[
        {
            "category":"Shopping",
            "subcategory":"Florist",
            "type":"Retail Goods"
        }
    ],
    "sg:phone":"+32 69 22 65 20",
    "sg:postcode":"7540",
    "sg:province":"Hainaut",
    "wof:name":"Vandevondel Floreal Rene Sprl",
    "wof:placetype":"venue"
},
  "geometry": {"coordinates":[3.3916859627,50.6325836182],"type":"Point"}
}