{
  "type": "Feature",
  "properties": {
    "iso:country":"BE",
    "sg:address":"Oudekerkstraat 10",
    "sg:city":"Kinrooi (molenbeersel)",
    "sg:classifiers":[
        {
            "category":"Bakery",
            "type":"Food & Drink"
        }
    ],
    "sg:phone":"+32 89 70 15 27",
    "sg:postcode":"3640",
    "sg:province":"Limburg",
    "sg:tags":[
        "confectioner",
        "baker"
    ],
    "wof:name":"Stals M",
    "wof:placetype":"venue"
},
  "geometry": {"coordinates":[5.7360057831,51.169506073],"type":"Point"}
}