{
  "type": "Feature",
  "properties": {
    "iso:country":"BE",
    "sg:address":"Grote Baan 297ba",
    "sg:city":"Aalst",
    "sg:orig_category":"Boucheries",
    "sg:phone":"+32 53 70 26 57",
    "sg:postcode":"9310",
    "sg:province":"Oost-Vlaanderen",
    "wof:name":"Jean Vinck",
    "wof:placetype":"venue"
},
  "geometry": {"coordinates":[4.0762858391,50.9755477905],"type":"Point"}
}