{
  "type": "Feature",
  "properties": {
    "iso:country":"BE",
    "sg:address":"Vaartstraat 6-8",
    "sg:city":"Willebroek",
    "sg:classifiers":[
        {
            "category":"Travel",
            "subcategory":"Bed & Breakfast",
            "type":"Entertainment"
        }
    ],
    "sg:phone":"+32 3 886 58 25",
    "sg:postcode":"2830",
    "sg:province":"Antwerpen",
    "sg:tags":[
        "limestone"
    ],
    "wof:name":"Promonta Nv",
    "wof:placetype":"venue"
},
  "geometry": {"coordinates":[4.3641839027,51.0688514709],"type":"Point"}
}