{
  "type": "Feature",
  "properties": {
    "iso:country":"BE",
    "sg:address":"Alsembergse Steenweg 711",
    "sg:city":"Ukkel/uccle",
    "sg:orig_category":"Boekhandels Tweedehandsgoederen",
    "sg:phone":"+32 2 343 77 50",
    "sg:postcode":"1180",
    "sg:province":"Bruxelles-Capitale",
    "wof:name":"A.z. Bouquins",
    "wof:placetype":"venue"
},
  "geometry": {"coordinates":[4.3365778923,50.8049087524],"type":"Point"}
}