{
  "type": "Feature",
  "properties": {
    "addr:full":"Weg Naar As 340 Genk Limburg 3600",
    "addr:housenumber":"340",
    "addr:postcode":"3600",
    "addr:street":"Weg Naar As",
    "iso:country":"BE",
    "sg:address":"Weg Naar As 340",
    "sg:city":"Genk",
    "sg:orig_category":"Entretien and r\u00e9parations de voitures",
    "sg:phone":"+32 89 84 38 65",
    "sg:postcode":"3600",
    "sg:province":"Limburg",
    "wof:name":"Carrosserie D & S",
    "wof:placetype":"venue"
},
  "geometry": {"coordinates":[5.5257401466,50.9776496887],"type":"Point"}
}