{
  "type": "Feature",
  "properties": {
    "iso:country":"BE",
    "sg:address":"Meesterstraat 88",
    "sg:city":"Sint-niklaas",
    "sg:orig_category":"Woningbouw",
    "sg:phone":"+32 3 766 30 56",
    "sg:postcode":"9100",
    "sg:province":"Oost-Vlaanderen",
    "wof:name":"Keppens Wilmer",
    "wof:placetype":"venue"
},
  "geometry": {"coordinates":[4.175825119,51.1867828369],"type":"Point"}
}