{
  "type": "Feature",
  "properties": {
    "addr:full":"Lippensln 214 Knokke-heist West-Vlaanderen 8300",
    "addr:housenumber":"214",
    "addr:postcode":"8300",
    "addr:street":"Knokke-Heist West-Vlaanderen",
    "iso:country":"BE",
    "sg:address":"Lippensln 214",
    "sg:city":"Knokke-heist",
    "sg:classifiers":[
        {
            "category":"Banks & Credit Unions",
            "subcategory":"Investment Brokerage",
            "type":"Services"
        }
    ],
    "sg:phone":"+32 50 54 57 95",
    "sg:postcode":"8300",
    "sg:province":"West-Vlaanderen",
    "sg:tags":[
        "-",
        "transport",
        "related"
    ],
    "wof:name":"Lc Forwarding Nv",
    "wof:placetype":"venue"
},
  "geometry": {"coordinates":[3.287694931,51.3467254639],"type":"Point"}
}