{
  "type": "Feature",
  "properties": {
    "iso:country":"BE",
    "sg:address":"Rue L\u00e9on Colleaux 5",
    "sg:city":"Virton (saint-mard)",
    "sg:classifiers":[
        {
            "category":"Health Services",
            "subcategory":"Doctor",
            "type":"Services"
        }
    ],
    "sg:phone":"+32 63 57 72 22",
    "sg:postcode":"6762",
    "sg:province":"Luxembourg",
    "sg:tags":[
        "orthopedist"
    ],
    "wof:name":"Asselborn Vreuls",
    "wof:placetype":"venue"
},
  "geometry": {"coordinates":[5.5299978256,49.5560493469],"type":"Point"}
}