{
  "type": "Feature",
  "properties": {
    "iso:country":"BE",
    "sg:address":"Rue L Macours 13",
    "sg:city":"Awans",
    "sg:orig_category":"Diverse bedrijfsbeheeradviesbureaus",
    "sg:phone":"+32 19 32 54 84",
    "sg:postcode":"4340",
    "sg:province":"Li\u00e8ge",
    "wof:name":"Godefroid P",
    "wof:placetype":"venue"
},
  "geometry": {"coordinates":[5.4620018005,50.663772583],"type":"Point"}
}