{
  "type": "Feature",
  "properties": {
    "iso:country":"BE",
    "sg:address":"R\u00c9sidence M. Carbonnelle 7bb",
    "sg:city":"Tournai",
    "sg:orig_category":"Enseignement maternel and primaire",
    "sg:phone":"+32 69 22 97 25",
    "sg:postcode":"7500",
    "sg:province":"Hainaut",
    "wof:name":"Ecole Prim. Communale",
    "wof:placetype":"venue"
},
  "geometry": {"coordinates":[3.3935399055,50.6126174927],"type":"Point"}
}