{
  "type": "Feature",
  "properties": {
    "addr:full":"Av De L'expansion 16d Alleur Li\u00e8ge 4432",
    "addr:housenumber":"16d",
    "addr:postcode":"4432",
    "addr:street":"Av De L'Expansion",
    "iso:country":"BE",
    "sg:address":"Av De L'expansion 16d",
    "sg:city":"Alleur",
    "sg:classifiers":[
        {
            "category":"Professional",
            "subcategory":"Engineering",
            "type":"Services"
        }
    ],
    "sg:phone":"+32 4 247 03 00",
    "sg:postcode":"4432",
    "sg:province":"Li\u00e8ge",
    "sg:tags":[
        "machine",
        "-",
        "environment",
        "equipment",
        "machinery",
        "mechanical"
    ],
    "wof:name":"Notifier Benelux Sa",
    "wof:placetype":"venue"
},
  "geometry": {"coordinates":[5.5242800713,50.6659317017],"type":"Point"}
}