{
  "type": "Feature",
  "properties": {
    "addr:full":"Rue De Chi\u00c8vres 12 Beloeil Hainaut 7970",
    "addr:housenumber":"12",
    "addr:postcode":"7970",
    "addr:street":"Rue De Chie\u0300Vres",
    "iso:country":"BE",
    "sg:address":"Rue De Chi\u00c8vres 12",
    "sg:city":"Beloeil",
    "sg:orig_category":"S\u00e9curit\u00e9 sociale",
    "sg:phone":"+32 69 68 83 84",
    "sg:postcode":"7970",
    "sg:province":"Hainaut",
    "wof:name":"Mutualit\u00c9 Libre",
    "wof:placetype":"venue"
},
  "geometry": {"coordinates":[3.734167099,50.5492095947],"type":"Point"}
}