{
  "type": "Feature",
  "properties": {
    "addr:full":"Beekstraat 25 Haaltert (kerksken) Oost-Vlaanderen 9451",
    "addr:housenumber":"25",
    "addr:postcode":"9451",
    "addr:street":"Beekstraat",
    "iso:country":"BE",
    "sg:address":"Beekstraat 25",
    "sg:city":"Haaltert (kerksken)",
    "sg:classifiers":[
        {
            "category":"Communications",
            "subcategory":"Newspaper",
            "type":"Services"
        }
    ],
    "sg:phone":"+32 53 83 70 78",
    "sg:postcode":"9451",
    "sg:province":"Oost-Vlaanderen",
    "sg:tags":[
        "paper",
        "local",
        "free"
    ],
    "wof:name":"Aktueel",
    "wof:placetype":"venue"
},
  "geometry": {"coordinates":[3.9923329353,50.8872451782],"type":"Point"}
}