{
  "type": "Feature",
  "properties": {
    "iso:country":"BE",
    "sg:address":"Streepstraat 164",
    "sg:city":"Kapellen",
    "sg:classifiers":[
        {
            "category":"Utilities",
            "subcategory":"Fuel Oil & Lpg",
            "type":"Services"
        }
    ],
    "sg:phone":"+32 3 605 70 17",
    "sg:postcode":"2950",
    "sg:province":"Antwerpen",
    "wof:name":"Antraco Bvba",
    "wof:placetype":"venue"
},
  "geometry": {"coordinates":[4.4172210693,51.3153343201],"type":"Point"}
}