{
  "type": "Feature",
  "properties": {
    "iso:country":"BE",
    "sg:address":"Rue Gallait 62",
    "sg:city":"Schaarbeek/schaerbeek",
    "sg:orig_category":"Avocats and conseillers juridiques",
    "sg:phone":"+32 2 241 37 97",
    "sg:postcode":"1030",
    "sg:province":"Bruxelles-Capitale",
    "wof:name":"Geertrui Leysen",
    "wof:placetype":"venue"
},
  "geometry": {"coordinates":[4.3681879044,50.8662796021],"type":"Point"}
}