{
  "type": "Feature",
  "properties": {
    "addr:full":"Brusselsesteenweg 230 Melle Oost-Vlaanderen 9090",
    "addr:housenumber":"230",
    "addr:postcode":"9090",
    "addr:street":"Brusselsesteenweg",
    "iso:country":"BE",
    "sg:address":"Brusselsesteenweg 230",
    "sg:city":"Melle",
    "sg:classifiers":[
        {
            "category":"Insurance",
            "subcategory":"Life Insurance",
            "type":"Services"
        }
    ],
    "sg:phone":"+32 9 252 69 85",
    "sg:postcode":"9090",
    "sg:province":"Oost-Vlaanderen",
    "sg:tags":[
        "assurance"
    ],
    "wof:name":"Verhaeghe",
    "wof:placetype":"venue"
},
  "geometry": {"coordinates":[3.8020000458,51.0025444031],"type":"Point"}
}