{
  "type": "Feature",
  "properties": {
    "iso:country":"BE",
    "sg:address":"Rue De Spa 49",
    "sg:city":"Aywaille",
    "sg:classifiers":[
        {
            "category":"Government",
            "subcategory":"Fire Station",
            "type":"Public Place"
        }
    ],
    "sg:phone":"+32 4 384 66 30",
    "sg:postcode":"4920",
    "sg:province":"Li\u00e8ge",
    "sg:tags":[
        "conditionn\u00e9",
        "chauffage",
        "pour",
        "air",
        "ventilation",
        "mat\u00e9riel",
        "plomberie"
    ],
    "wof:name":"Dynavent",
    "wof:placetype":"venue"
},
  "geometry": {"coordinates":[5.6782069206,50.4738540649],"type":"Point"}
}