{
  "type": "Feature",
  "properties": {
    "iso:country":"BE",
    "sg:address":"Rue Du Ch\u00c2teau D'eau 32",
    "sg:city":"Hamois",
    "sg:orig_category":"Artsen and specialisten",
    "sg:phone":"+32 83 21 59 46",
    "sg:postcode":"5360",
    "sg:province":"Namur",
    "wof:name":"F. Dujardin",
    "wof:placetype":"venue"
},
  "geometry": {"coordinates":[5.0538868904,50.3389549255],"type":"Point"}
}