{
  "type": "Feature",
  "properties": {
    "addr:full":"Kortenbosstraat 5 Dilbeek Vlaams-Brabant 1701",
    "addr:housenumber":"5",
    "addr:postcode":"1701",
    "addr:street":"Kortenbosstraat",
    "iso:country":"BE",
    "sg:address":"Kortenbosstraat 5",
    "sg:city":"Dilbeek",
    "sg:orig_category":"Entretien and r\u00e9parations de voitures. R\u00e9cup\u00e9ration de mati\u00e8res m\u00e9talliques recyclables and d\u00e9moliss",
    "sg:phone":"+32 2 569 74 53",
    "sg:postcode":"1701",
    "sg:province":"Vlaams-Brabant",
    "wof:name":"Garage Brusselmans",
    "wof:placetype":"venue"
},
  "geometry": {"coordinates":[4.2374801636,50.8284492493],"type":"Point"}
}