{
  "type": "Feature",
  "properties": {
    "iso:country":"BE",
    "sg:address":"Rue Saint-m\u00e9dard 34",
    "sg:city":"Jodoigne",
    "sg:classifiers":[
        {
            "category":"Banks & Credit Unions",
            "subcategory":"Investment Brokerage",
            "type":"Services"
        }
    ],
    "sg:phone":"+32 10 81 34 74",
    "sg:postcode":"1370",
    "sg:province":"Brabant Wallon",
    "sg:tags":[
        "repair",
        "-",
        "installation",
        "sanitary",
        "article"
    ],
    "wof:name":"Sagot P",
    "wof:placetype":"venue"
},
  "geometry": {"coordinates":[4.8682870865,50.7221794128],"type":"Point"}
}