{
  "type": "Feature",
  "properties": {
    "addr:full":"Rue De Barvaux 23 Hotton Luxembourg 6990",
    "addr:housenumber":"23",
    "addr:postcode":"6990",
    "addr:street":"Rue De Barvaux",
    "iso:country":"BE",
    "sg:address":"Rue De Barvaux 23",
    "sg:city":"Hotton",
    "sg:orig_category":"Installatie van houten of kunststof schrijnwerk Installatie van metalen schrijnwerk Vloer- and muurb",
    "sg:phone":"+32 84 46 66 30",
    "sg:postcode":"6990",
    "sg:province":"Luxembourg",
    "wof:name":"J. Demarche",
    "wof:placetype":"venue"
},
  "geometry": {"coordinates":[5.4593610764,50.2856216431],"type":"Point"}
}