{
  "type": "Feature",
  "properties": {
    "addr:full":"Rue De L\u00b4eglise 5 Perwez Brabant Wallon 1360",
    "addr:housenumber":"5",
    "addr:postcode":"1360",
    "addr:street":"Rue De L\u00b4Eglise",
    "iso:country":"BE",
    "sg:address":"Rue De L\u00b4eglise 5",
    "sg:city":"Perwez",
    "sg:orig_category":"Services de Nettoyage and de D\u00e9sinfection. Collecte and \u00e9puration des eaux us\u00e9es",
    "sg:phone":"+32 10 88 84 60",
    "sg:postcode":"1360",
    "sg:province":"Brabant Wallon",
    "wof:name":"Id\u00c9al Vidange",
    "wof:placetype":"venue"
},
  "geometry": {"coordinates":[4.7824258804,50.6577186584],"type":"Point"}
}