{
  "type": "Feature",
  "properties": {
    "addr:full":"Oelegemsesteenweg 16a Ranst (broechem) Antwerpen 2520",
    "addr:housenumber":"16a",
    "addr:postcode":"2520",
    "addr:street":"Oelegemsesteenweg",
    "iso:country":"BE",
    "sg:address":"Oelegemsesteenweg 16a",
    "sg:city":"Ranst (broechem)",
    "sg:classifiers":[
        {
            "category":"Home & Garden",
            "subcategory":"Building Materials",
            "type":"Retail Goods"
        }
    ],
    "sg:phone":"+32 3 475 02 17",
    "sg:postcode":"2520",
    "sg:province":"Antwerpen",
    "sg:tags":[
        "window"
    ],
    "wof:name":"Nauwelaers G",
    "wof:placetype":"venue"
},
  "geometry": {"coordinates":[4.5553097725,51.2172584534],"type":"Point"}
}