{
  "type": "Feature",
  "properties": {
    "iso:country":"BE",
    "sg:address":"Av. De La Reine Des Pr\u00c9s 24",
    "sg:city":"Brussel/bruxelles",
    "sg:orig_category":"M\u00e9decins and sp\u00e9cialistes",
    "sg:phone":"+32 2 241 08 69",
    "sg:postcode":"1020",
    "sg:province":"Bruxelles-Capitale",
    "wof:name":"Caroline De Moffarts",
    "wof:placetype":"venue"
},
  "geometry": {"coordinates":[4.3731398582,50.8909111023],"type":"Point"}
}