{
  "type": "Feature",
  "properties": {
    "iso:country":"BE",
    "sg:address":"Kerkplaats 2",
    "sg:city":"Wommelgem",
    "sg:orig_category":"Boucheries",
    "sg:phone":"+32 3 353 61 53",
    "sg:postcode":"2160",
    "sg:province":"Antwerpen",
    "wof:name":"Dirk Voorspoels",
    "wof:placetype":"venue"
},
  "geometry": {"coordinates":[4.5226120949,51.2040672302],"type":"Point"}
}