{
  "type": "Feature",
  "properties": {
    "iso:country":"BE",
    "sg:address":"Av. Comte G\u00c9rard D\u00b4ursel 68",
    "sg:city":"Grez-doiceau",
    "sg:orig_category":"Agences de publicit\u00e9",
    "sg:phone":"+32 10 84 23 83",
    "sg:postcode":"1390",
    "sg:province":"Brabant Wallon",
    "wof:name":"S M Design",
    "wof:placetype":"venue"
},
  "geometry": {"coordinates":[4.663310051,50.7212715149],"type":"Point"}
}