{
  "type": "Feature",
  "properties": {
    "iso:country":"BE",
    "sg:address":"Rue L\u00e9on Theodor 140-146",
    "sg:city":"Bruxelles (jette)",
    "sg:classifiers":[
        {
            "category":"Banks & Credit Unions",
            "subcategory":"Investment Brokerage",
            "type":"Services"
        }
    ],
    "sg:phone":"+32 2 426 22 31",
    "sg:postcode":"1090",
    "sg:province":"Bruxelles-Capitale",
    "sg:tags":[
        "printing",
        "-"
    ],
    "wof:name":"De Boeck Emile Sprl Imprimerie",
    "wof:placetype":"venue"
},
  "geometry": {"coordinates":[4.3281459808,50.8771057129],"type":"Point"}
}