{
  "type": "Feature",
  "properties": {
    "iso:country":"BE",
    "sg:address":"Azaleastraat 1",
    "sg:city":"Waarschoot",
    "sg:classifiers":[
        {
            "category":"Professional",
            "subcategory":"Art Services",
            "type":"Services"
        }
    ],
    "sg:phone":"+32 9 372 68 11",
    "sg:postcode":"9950",
    "sg:province":"Oost-Vlaanderen",
    "sg:tags":[
        "interior",
        "designer"
    ],
    "wof:name":"De Muer K",
    "wof:placetype":"venue"
},
  "geometry": {"coordinates":[3.6067659855,51.1526412964],"type":"Point"}
}