{
  "type": "Feature",
  "properties": {
    "addr:full":"Avenue Raymond Brassinne 18 Braine-l'alleud Brabant Wallon 1420",
    "addr:housenumber":"18",
    "addr:postcode":"1420",
    "addr:street":"Avenue Raymond Brassinne",
    "iso:country":"BE",
    "sg:address":"Avenue Raymond Brassinne 18",
    "sg:city":"Braine-l'alleud",
    "sg:orig_category":"Banken and kredietinstellingen",
    "sg:phone":"+32 2 384 93 88",
    "sg:postcode":"1420",
    "sg:province":"Brabant Wallon",
    "wof:name":"Cbc",
    "wof:placetype":"venue"
},
  "geometry": {"coordinates":[-0.7004899979,47.369140625],"type":"Point"}
}