{
  "type": "Feature",
  "properties": {
    "addr:full":"Place Albert Ier 4 Fleurus Hainaut 6220",
    "addr:housenumber":"4",
    "addr:postcode":"6220",
    "addr:street":"Place Albert Ier",
    "iso:country":"BE",
    "sg:address":"Place Albert Ier 4",
    "sg:city":"Fleurus",
    "sg:orig_category":"Huishoudapparaten, televisies and radio's Industri\u00eble elektrische installaties",
    "sg:phone":"+32 71 81 66 06",
    "sg:postcode":"6220",
    "sg:province":"Hainaut",
    "wof:name":"A.t.s.",
    "wof:placetype":"venue"
},
  "geometry": {"coordinates":[4.5556540489,50.4588661194],"type":"Point"}
}