{
  "type": "Feature",
  "properties": {
    "iso:country":"BE",
    "sg:address":"Rue Des Tongres 59",
    "sg:city":"Bruxelles (etterbeek)",
    "sg:classifiers":[
        {
            "category":"Social Services",
            "subcategory":"Job Training",
            "type":"Services"
        }
    ],
    "sg:phone":"+32 2 733 97 34",
    "sg:postcode":"1040",
    "sg:province":"Bruxelles-Capitale",
    "sg:tags":[
        "interpreter"
    ],
    "wof:name":"Riches J",
    "wof:placetype":"venue"
},
  "geometry": {"coordinates":[4.4008259773,50.8402061462],"type":"Point"}
}