{
  "type": "Feature",
  "properties": {
    "addr:full":"Zenneweg 37 Zemst (eppegem) Vlaams-Brabant 1980",
    "addr:housenumber":"37",
    "addr:postcode":"1980",
    "addr:street":"Zenneweg",
    "iso:country":"BE",
    "sg:address":"Zenneweg 37",
    "sg:city":"Zemst (eppegem)",
    "sg:classifiers":[
        {
            "category":"Arts & Performance",
            "subcategory":"Music",
            "type":"Entertainment"
        }
    ],
    "sg:phone":"+32 2 251 46 68",
    "sg:postcode":"1980",
    "sg:province":"Vlaams-Brabant",
    "sg:tags":[
        "disc-jockeys"
    ],
    "wof:name":"Discobar Spirit",
    "wof:placetype":"venue"
},
  "geometry": {"coordinates":[4.4592671394,50.9637527466],"type":"Point"}
}