{
  "type": "Feature",
  "properties": {
    "iso:country":"BE",
    "sg:address":"Tiensestraat 37",
    "sg:city":"Leuven",
    "sg:classifiers":[
        {
            "category":"Professional",
            "subcategory":"Art Services",
            "type":"Services"
        }
    ],
    "sg:phone":"+32 16 23 90 05",
    "sg:postcode":"3000",
    "sg:province":"Vlaams-Brabant",
    "sg:tags":[
        "photographer"
    ],
    "wof:name":"'t Oogenblik Fotografie",
    "wof:placetype":"venue"
},
  "geometry": {"coordinates":[4.7037620544,50.8780021667],"type":"Point"}
}