{
  "type": "Feature",
  "properties": {
    "addr:full":"Rue Pont D'avroy 34 Li\u00c8ge Li\u00e8ge 4000",
    "addr:housenumber":"34",
    "addr:postcode":"4000",
    "addr:street":"Rue Pont D'Avroy",
    "iso:country":"BE",
    "sg:address":"Rue Pont D'avroy 34",
    "sg:city":"Li\u00c8ge",
    "sg:orig_category":"Brood, gebak and snoepgoed",
    "sg:phone":"+32 4 222 10 64",
    "sg:postcode":"4000",
    "sg:province":"Li\u00e8ge",
    "wof:name":"Godiva",
    "wof:placetype":"venue"
},
  "geometry": {"coordinates":[5.5696148872,50.6406288147],"type":"Point"}
}