{
  "type": "Feature",
  "properties": {
    "iso:country":"BE",
    "sg:address":"Passendalesteenweg 9",
    "sg:city":"Staden (westrozebeke)",
    "sg:classifiers":[
        {
            "category":"Freight",
            "type":"Transportation"
        }
    ],
    "sg:phone":"+32 51 77 73 54",
    "sg:postcode":"8840",
    "sg:province":"West-Vlaanderen",
    "sg:tags":[
        "-",
        "transport"
    ],
    "wof:name":"Vermeulen Dominiek Bvba",
    "wof:placetype":"venue"
},
  "geometry": {"coordinates":[3.0133810043,50.9276237488],"type":"Point"}
}