{
  "type": "Feature",
  "properties": {
    "addr:full":"Lange Koepoortstraat 55 Antwerpen Antwerpen 2000",
    "addr:housenumber":"55",
    "addr:postcode":"2000",
    "addr:street":"Lange Koepoortstraat",
    "iso:country":"BE",
    "sg:address":"Lange Koepoortstraat 55",
    "sg:city":"Antwerpen",
    "sg:classifiers":[
        {
            "category":"Professional",
            "subcategory":"Testing Lab",
            "type":"Services"
        }
    ],
    "sg:phone":"+32 3 233 35 78",
    "sg:postcode":"2000",
    "sg:province":"Antwerpen",
    "sg:tags":[
        "chemist"
    ],
    "wof:name":"Van Den Putte",
    "wof:placetype":"venue"
},
  "geometry": {"coordinates":[4.4024572372,51.2222328186],"type":"Point"}
}