{
  "type": "Feature",
  "properties": {
    "addr:full":"Osylei 37 Mortsel Antwerpen 2640",
    "addr:housenumber":"37",
    "addr:postcode":"2640",
    "addr:street":"Osylei",
    "iso:country":"BE",
    "sg:address":"Osylei 37",
    "sg:city":"Mortsel",
    "sg:orig_category":"Sportclubs",
    "sg:phone":"+32 3 449 74 89",
    "sg:postcode":"2640",
    "sg:province":"Antwerpen",
    "wof:name":"Tecemo",
    "wof:placetype":"venue"
},
  "geometry": {"coordinates":[4.4517102242,51.180229187],"type":"Point"}
}