{
  "type": "Feature",
  "properties": {
    "iso:country":"BE",
    "sg:address":"Rue De Pootter 3",
    "sg:city":"Brussel/bruxelles",
    "sg:orig_category":"Eclairage et \u00e9quipements du foyer",
    "sg:phone":"+32 2 376 09 20",
    "sg:postcode":"1030",
    "sg:province":"Bruxelles-Capitale",
    "wof:name":"Havaux",
    "wof:placetype":"venue"
},
  "geometry": {"coordinates":[4.3644661903,50.8639755249],"type":"Point"}
}