{
  "type": "Feature",
  "properties": {
    "addr:full":"Rue Du Commerce 137 Ciney Namur 5590",
    "addr:housenumber":"137",
    "addr:postcode":"5590",
    "addr:street":"Rue Du Commerce",
    "iso:country":"BE",
    "sg:address":"Rue Du Commerce 137",
    "sg:city":"Ciney",
    "sg:classifiers":[
        {
            "category":"Organizations",
            "subcategory":"Professional Association",
            "type":"Services"
        }
    ],
    "sg:phone":"+32 83 21 29 24",
    "sg:postcode":"5590",
    "sg:province":"Namur",
    "sg:tags":[
        "trade-union",
        "federation"
    ],
    "wof:name":"Bureau Regional Ecolo",
    "wof:placetype":"venue"
},
  "geometry": {"coordinates":[5.092977047,50.2909164429],"type":"Point"}
}