{
  "type": "Feature",
  "properties": {
    "addr:full":"Panisbornestraat 14a Zoutleeuw Vlaams-Brabant 3440",
    "addr:housenumber":"14a",
    "addr:postcode":"3440",
    "addr:street":"Panisbornestraat;Vlaams-Brabant",
    "iso:country":"BE",
    "sg:address":"Panisbornestraat 14a",
    "sg:city":"Zoutleeuw",
    "sg:orig_category":"Groenten and fruit Gh",
    "sg:phone":"+32 11 58 90 43",
    "sg:postcode":"3440",
    "sg:province":"Vlaams-Brabant",
    "wof:name":"Mathues",
    "wof:placetype":"venue"
},
  "geometry": {"coordinates":[5.0559282303,50.8673591614],"type":"Point"}
}