{
  "type": "Feature",
  "properties": {
    "iso:country":"BE",
    "sg:address":"Halmaaldorp 63",
    "sg:city":"Sint-truiden",
    "sg:orig_category":"Kapsalons",
    "sg:phone":"+32 11 68 84 29",
    "sg:postcode":"3800",
    "sg:province":"Limburg",
    "wof:name":"Coiffure Gilberte",
    "wof:placetype":"venue"
},
  "geometry": {"coordinates":[5.1512470245,50.8013191223],"type":"Point"}
}