{
  "type": "Feature",
  "properties": {
    "iso:country":"BE",
    "sg:address":"Eik 24",
    "sg:city":"Bilzen",
    "sg:orig_category":"Instituts de beaut\u00e9",
    "sg:phone":"+32 89 41 84 04",
    "sg:postcode":"3740",
    "sg:province":"Limburg",
    "wof:name":"Instituut Pascale",
    "wof:placetype":"venue"
},
  "geometry": {"coordinates":[5.5082530975,50.8974914551],"type":"Point"}
}