{
  "type": "Feature",
  "properties": {
    "addr:full":"Grand'place 34 Beloeil Hainaut 7970",
    "addr:housenumber":"34",
    "addr:postcode":"7970",
    "addr:street":"Grand'Place",
    "iso:country":"BE",
    "sg:address":"Grand'place 34",
    "sg:city":"Beloeil",
    "sg:classifiers":[
        {
            "category":"Shopping",
            "subcategory":"Crafts & Fabrics",
            "type":"Retail Goods"
        }
    ],
    "sg:phone":"+32 69 68 83 61",
    "sg:postcode":"7970",
    "sg:province":"Hainaut",
    "sg:tags":[
        "plant",
        "flower",
        "artificial"
    ],
    "wof:name":"Beloeillet (le)",
    "wof:placetype":"venue"
},
  "geometry": {"coordinates":[3.6489059925,50.5256309509],"type":"Point"}
}