{
  "type": "Feature",
  "properties": {
    "iso:country":"BE",
    "sg:address":"Dokter Spitaelslaan 454",
    "sg:city":"Halle (lembeek)",
    "sg:classifiers":[
        {
            "category":"Professional",
            "subcategory":"Computer Services",
            "type":"Services"
        }
    ],
    "sg:phone":"+32 2 361 12 34",
    "sg:postcode":"1502",
    "sg:province":"Vlaams-Brabant",
    "sg:tags":[
        "-",
        "processing",
        "data",
        "software"
    ],
    "wof:name":"Ict-4s Bvba",
    "wof:placetype":"venue"
},
  "geometry": {"coordinates":[4.2509131432,50.7060127258],"type":"Point"}
}