{
  "type": "Feature",
  "properties": {
    "iso:country":"BE",
    "sg:address":"Groenstr. 256",
    "sg:city":"Vilvoorde",
    "sg:classifiers":[
        {
            "category":"Utilities",
            "subcategory":"Electric",
            "type":"Services"
        }
    ],
    "sg:phone":"+32 2 253 07 00",
    "sg:postcode":"1800",
    "sg:province":"Vlaams-Brabant",
    "sg:tags":[
        "electricity",
        "electronic",
        "electrical",
        "equipment"
    ],
    "wof:name":"La Grange Nv",
    "wof:placetype":"venue"
},
  "geometry": {"coordinates":[4.4356198311,50.9359092712],"type":"Point"}
}