{
  "type": "Feature",
  "properties": {
    "addr:full":"Rue Des Pr\u00e9s Mercq 27 Soignies (naast) Hainaut 7062",
    "addr:housenumber":"27",
    "addr:postcode":"7062",
    "addr:street":"Rue Des Pre\u0301S Mercq",
    "iso:country":"BE",
    "sg:address":"Rue Des Pr\u00e9s Mercq 27",
    "sg:city":"Soignies (naast)",
    "sg:classifiers":[
        {
            "category":"Building & Trades",
            "subcategory":"Cleaning & Sanitation",
            "type":"Services"
        }
    ],
    "sg:phone":"+32 67 33 01 29",
    "sg:postcode":"7062",
    "sg:province":"Hainaut",
    "sg:tags":[
        "fa\u00e7ade",
        "maintenance"
    ],
    "wof:name":"Foucart Ets",
    "wof:placetype":"venue"
},
  "geometry": {"coordinates":[4.108300209,50.558631897],"type":"Point"}
}