{
  "type": "Feature",
  "properties": {
    "addr:full":"159 Quai Des Usines 1000 Bruxelles 159",
    "addr:housenumber":"159",
    "addr:postcode":"1000;159",
    "addr:street":"Quai Des Usines",
    "iso:country":"BE",
    "sg:address":"159",
    "sg:city":"Quai Des Usines 1000 Bruxelles",
    "sg:classifiers":[
        {
            "category":"Farming",
            "subcategory":"Crops",
            "type":"Manufacturing & Wholesale Goods"
        }
    ],
    "sg:phone":"+32 2 245 07 81",
    "sg:postcode":"159",
    "sg:tags":[
        "vegetable",
        "fruit",
        "agriculture",
        "livestock"
    ],
    "wof:name":"Restofrais Sprl",
    "wof:placetype":"venue"
},
  "geometry": {"coordinates":[4.3636498451,50.8755111694],"type":"Point"}
}