{
  "type": "Feature",
  "properties": {
    "addr:full":"Halsesteenweg 395 Ninove Oost-Vlaanderen 9403",
    "addr:housenumber":"395",
    "addr:postcode":"9403",
    "addr:street":"Halsesteenweg",
    "iso:country":"BE",
    "sg:address":"Halsesteenweg 395",
    "sg:city":"Ninove",
    "sg:orig_category":"Plaatsen van vloer- and muurbekleding Woningbouw",
    "sg:phone":"+32 54 33 85 88",
    "sg:postcode":"9403",
    "sg:province":"Oost-Vlaanderen",
    "wof:name":"Van Laethem",
    "wof:placetype":"venue"
},
  "geometry": {"coordinates":[4.0594549179,50.8027954102],"type":"Point"}
}