{
  "type": "Feature",
  "properties": {
    "iso:country":"BE",
    "sg:address":"Centrum Zuid 1520",
    "sg:city":"Houthalen-helchteren",
    "sg:orig_category":"Plomberie, chauffage and installations sanitaires. Air conditionn\u00e9 and ventilation. Mat\u00e9riaux de con",
    "sg:phone":"+32 11 52 57 91",
    "sg:postcode":"3530",
    "sg:province":"Limburg",
    "wof:name":"Geva",
    "wof:placetype":"venue"
},
  "geometry": {"coordinates":[5.3625049591,51.0245094299],"type":"Point"}
}