{
  "type": "Feature",
  "properties": {
    "addr:full":"Rue Edouard Stuckens 128 Evere/evere Bruxelles-Capitale 1140",
    "addr:housenumber":"128",
    "addr:postcode":"1140",
    "addr:street":"Rue Edouard Stuckens",
    "iso:country":"BE",
    "sg:address":"Rue Edouard Stuckens 128",
    "sg:city":"Evere/evere",
    "sg:orig_category":"Entretien and r\u00e9parations de voitures",
    "sg:phone":"+32 2 215 47 38",
    "sg:postcode":"1140",
    "sg:province":"Bruxelles-Capitale",
    "wof:name":"Pierre De Swert",
    "wof:placetype":"venue"
},
  "geometry": {"coordinates":[4.3984298706,50.8761672974],"type":"Point"}
}