{
  "type": "Feature",
  "properties": {
    "addr:full":"Wirixdreef 28 Niel Antwerpen 2845",
    "addr:housenumber":"28",
    "addr:postcode":"2845",
    "addr:street":"Wirixdreef",
    "iso:country":"BE",
    "sg:address":"Wirixdreef 28",
    "sg:city":"Niel",
    "sg:classifiers":[
        {
            "category":"Health Services",
            "subcategory":"Health Practitioner",
            "type":"Services"
        }
    ],
    "sg:phone":"+32 3 844 42 00",
    "sg:postcode":"2845",
    "sg:province":"Antwerpen",
    "sg:tags":[
        "physiotherapist"
    ],
    "wof:name":"Bertels Kim",
    "wof:placetype":"venue"
},
  "geometry": {"coordinates":[4.3226108551,51.1071014404],"type":"Point"}
}