{
  "type": "Feature",
  "properties": {
    "addr:full":"Provinciesteenweg 28 Boortmeerbeek Vlaams-Brabant 3190",
    "addr:housenumber":"28",
    "addr:postcode":"3190",
    "addr:street":"Provinciesteenweg",
    "iso:country":"BE",
    "sg:address":"Provinciesteenweg 28",
    "sg:city":"Boortmeerbeek",
    "sg:classifiers":[
        {
            "category":"Wholesale",
            "subcategory":"Beer",
            "type":"Manufacturing & Wholesale Goods"
        }
    ],
    "sg:phone":"+32 16 60 15 01",
    "sg:postcode":"3190",
    "sg:province":"Vlaams-Brabant",
    "wof:name":"Brouwerij Haacht Brasserie Nv",
    "wof:placetype":"venue"
},
  "geometry": {"coordinates":[4.6101398468,50.9655075073],"type":"Point"}
}