{
  "type": "Feature",
  "properties": {
    "addr:full":"Doornstraat 87-89 Edegem Antwerpen 2650",
    "addr:postcode":"87-89;2650",
    "addr:street":"Doornstraat",
    "iso:country":"BE",
    "sg:address":"Doornstraat 87-89",
    "sg:city":"Edegem",
    "sg:classifiers":[
        {
            "category":"Health Services",
            "subcategory":"Nursing And Care Facility",
            "type":"Services"
        }
    ],
    "sg:phone":"+32 3 457 66 76",
    "sg:postcode":"2650",
    "sg:province":"Antwerpen",
    "sg:tags":[
        "balneology",
        "electrotherapy",
        "fitting",
        "physiotherapy"
    ],
    "wof:name":"Fysiomed Nv",
    "wof:placetype":"venue"
},
  "geometry": {"coordinates":[4.4025921822,51.1526756287],"type":"Point"}
}