{
  "type": "Feature",
  "properties": {
    "addr:full":"Het Veldeke 49 Wezembeek-oppem/wezembeek-oppem Vlaams-Brabant 1970",
    "addr:housenumber":"49",
    "addr:postcode":"1970",
    "addr:street":"Het Veldeke",
    "iso:country":"BE",
    "sg:address":"Het Veldeke 49",
    "sg:city":"Wezembeek-oppem/wezembeek-oppem",
    "sg:orig_category":"Artsen and specialisten",
    "sg:phone":"+32 2 731 86 17",
    "sg:postcode":"1970",
    "sg:province":"Vlaams-Brabant",
    "wof:name":"Yves Appelmans",
    "wof:placetype":"venue"
},
  "geometry": {"coordinates":[4.4877390862,50.8463478088],"type":"Point"}
}