{
  "type": "Feature",
  "properties": {
    "addr:full":"Rue D'enhaive 177 Namur Namur 5100",
    "addr:housenumber":"177",
    "addr:postcode":"5100",
    "addr:street":"Rue D'Enhaive",
    "iso:country":"BE",
    "sg:address":"Rue D'enhaive 177",
    "sg:city":"Namur",
    "sg:orig_category":"Kapsalons",
    "sg:phone":"+32 81 31 04 76",
    "sg:postcode":"5100",
    "sg:province":"Namur",
    "wof:name":"Jacqueline",
    "wof:placetype":"venue"
},
  "geometry": {"coordinates":[4.8797621727,50.4615516663],"type":"Point"}
}