{
  "type": "Feature",
  "properties": {
    "addr:full":"Gentsesteenweg 22 Aalst Oost-Vlaanderen 9300",
    "addr:housenumber":"22",
    "addr:postcode":"9300",
    "addr:street":"Gentsesteenweg",
    "iso:country":"BE",
    "sg:address":"Gentsesteenweg 22",
    "sg:city":"Aalst",
    "sg:classifiers":[
        {
            "category":"Farming",
            "subcategory":"Fish & Marine Products",
            "type":"Manufacturing & Wholesale Goods"
        }
    ],
    "sg:phone":"+32 53 78 58 34",
    "sg:postcode":"9300",
    "sg:province":"Oost-Vlaanderen",
    "sg:tags":[
        "retail",
        "-",
        "shellfish"
    ],
    "wof:name":"Boel W",
    "wof:placetype":"venue"
},
  "geometry": {"coordinates":[4.0256838799,50.937789917],"type":"Point"}
}