{
  "type": "Feature",
  "properties": {
    "iso:country":"BE",
    "sg:address":"Grote Markt 2",
    "sg:city":"Lier",
    "sg:orig_category":"Pharmaciens",
    "sg:phone":"+32 3 480 03 63",
    "sg:postcode":"2500",
    "sg:province":"Antwerpen",
    "wof:name":"Antoon Mas",
    "wof:placetype":"venue"
},
  "geometry": {"coordinates":[4.5708727837,51.13022995],"type":"Point"}
}