{
  "type": "Feature",
  "properties": {
    "addr:full":"Rue Aripette 134 Seraing Li\u00e8ge 4101",
    "addr:housenumber":"134",
    "addr:postcode":"4101",
    "addr:street":"Rue Aripette",
    "iso:country":"BE",
    "sg:address":"Rue Aripette 134",
    "sg:city":"Seraing",
    "sg:orig_category":"Installatie van houten of kunststof schrijnwerk",
    "sg:phone":"+32 4 234 07 34",
    "sg:postcode":"4101",
    "sg:province":"Li\u00e8ge",
    "wof:name":"J.l.m.",
    "wof:placetype":"venue"
},
  "geometry": {"coordinates":[5.4969000816,50.6148605347],"type":"Point"}
}