{
  "type": "Feature",
  "properties": {
    "addr:full":"Edouard Joossensplein 8 Bruges (grand) West-Vlaanderen 8310",
    "addr:housenumber":"8",
    "addr:postcode":"8310",
    "addr:street":"Bruges Grand West-Vlaanderen",
    "iso:country":"BE",
    "sg:address":"Edouard Joossensplein 8",
    "sg:city":"Bruges (grand)",
    "sg:orig_category":"Erotische Etablissementen Erotische- and Escortediensten",
    "sg:phone":"+32 495 78 20 90",
    "sg:postcode":"8310",
    "sg:province":"West-Vlaanderen",
    "wof:name":"Juffrouw Tine",
    "wof:placetype":"venue"
},
  "geometry": {"coordinates":[3.2304930687,51.1930885315],"type":"Point"}
}