{
  "type": "Feature",
  "properties": {
    "addr:full":"Rue De Seumay 18a Perwez Brabant Wallon 1360",
    "addr:housenumber":"18a",
    "addr:postcode":"1360",
    "addr:street":"Rue De Seumay",
    "iso:country":"BE",
    "sg:address":"Rue De Seumay 18a",
    "sg:city":"Perwez",
    "sg:classifiers":[
        {
            "category":"Manufacturing",
            "subcategory":"Metals",
            "type":"Manufacturing & Wholesale Goods"
        }
    ],
    "sg:phone":"+32 81 65 81 61",
    "sg:postcode":"1360",
    "sg:province":"Brabant Wallon",
    "sg:tags":[
        "ornamental",
        "work",
        "-"
    ],
    "wof:name":"Ferrodel",
    "wof:placetype":"venue"
},
  "geometry": {"coordinates":[4.8211398125,50.626209259],"type":"Point"}
}