{
  "type": "Feature",
  "properties": {
    "iso:country":"BE",
    "sg:address":"Vranksberg 37",
    "sg:city":"Huldenberg",
    "sg:orig_category":"Architecten",
    "sg:phone":"+32 2 687 43 65",
    "sg:postcode":"3040",
    "sg:province":"Vlaams-Brabant",
    "wof:name":"Francis Hermans",
    "wof:placetype":"venue"
},
  "geometry": {"coordinates":[4.5948300362,50.8028869629],"type":"Point"}
}