{
  "type": "Feature",
  "properties": {
    "iso:country":"BE",
    "sg:address":"Mechelsesteenweg 88",
    "sg:city":"Mortsel",
    "sg:classifiers":[
        {
            "category":"Personal",
            "subcategory":"Beauty Salon",
            "type":"Services"
        }
    ],
    "sg:phone":"+32 3 440 08 21",
    "sg:postcode":"2640",
    "sg:province":"Antwerpen",
    "sg:tags":[
        "lady",
        "-",
        "hairdressing"
    ],
    "wof:name":"Jef's Hairdesign",
    "wof:placetype":"venue"
},
  "geometry": {"coordinates":[4.4517059326,51.167842865],"type":"Point"}
}