{
  "type": "Feature",
  "properties": {
    "iso:country":"BE",
    "sg:address":"Rue De Bouillon 100",
    "sg:city":"Bi\u00e8vre",
    "sg:classifiers":[
        {
            "category":"Retail",
            "subcategory":"Auto Repair",
            "type":"Services"
        }
    ],
    "sg:phone":"+32 61 51 10 32",
    "sg:postcode":"5555",
    "sg:province":"Namur",
    "sg:tags":[
        "garage"
    ],
    "wof:name":"Ets Lucy Sa",
    "wof:placetype":"venue"
},
  "geometry": {"coordinates":[5.0315480232,49.9276847839],"type":"Point"}
}