{
  "type": "Feature",
  "properties": {
    "addr:full":". Sint-joost-ten-node/saint-joss Bruxelles-Capitale 1210",
    "addr:housenumber":"sint-joost-ten-node",
    "addr:postcode":"1210",
    "iso:country":"BE",
    "sg:address":".",
    "sg:city":"Sint-joost-ten-node/saint-joss",
    "sg:classifiers":[
        {
            "category":"Recreation",
            "type":"Entertainment"
        }
    ],
    "sg:phone":"+32 475 92 98 59",
    "sg:postcode":"1210",
    "sg:province":"Bruxelles-Capitale",
    "sg:tags":[
        "diver",
        "amusement"
    ],
    "wof:name":"Agency Nikita",
    "wof:placetype":"venue"
},
  "geometry": {"coordinates":[4.3721051216,50.8498458862],"type":"Point"}
}