{
  "type": "Feature",
  "properties": {
    "iso:country":"BE",
    "sg:address":"Hemelrijkstraat 1",
    "sg:city":"De (groot)",
    "sg:orig_category":"Balie van Gent. Avocats and conseillers juridiques",
    "sg:phone":"+32 9 280 70 70",
    "sg:postcode":"9840",
    "sg:province":"Oost-Vlaanderen",
    "wof:name":"De Vleeschauwer Philippe",
    "wof:placetype":"venue"
},
  "geometry": {"coordinates":[3.6678819656,50.9965171814],"type":"Point"}
}