{
  "type": "Feature",
  "properties": {
    "addr:full":"Rue De Senzeilles 24 Cerfontaine Namur 5630",
    "addr:housenumber":"24",
    "addr:postcode":"5630",
    "addr:street":"Rue De Senzeilles",
    "iso:country":"BE",
    "sg:address":"Rue De Senzeilles 24",
    "sg:city":"Cerfontaine",
    "sg:classifiers":[
        {
            "category":"Shopping",
            "subcategory":"Shoes",
            "type":"Retail Goods"
        }
    ],
    "sg:phone":"+32 71 64 41 23",
    "sg:postcode":"5630",
    "sg:province":"Namur",
    "sg:tags":[
        "slipper",
        "-"
    ],
    "wof:name":"Chaussures Sirjacques",
    "wof:placetype":"venue"
},
  "geometry": {"coordinates":[4.4143900871,50.1715164185],"type":"Point"}
}