{
  "type": "Feature",
  "properties": {
    "iso:country":"BE",
    "sg:address":"Vis\u00c9laan 25",
    "sg:city":"Watermaal-bosvoorde/watermael-boitsfort",
    "sg:orig_category":"Artsen and specialisten",
    "sg:phone":"+32 2 673 83 82",
    "sg:postcode":"1170",
    "sg:province":"Bruxelles-Capitale",
    "wof:name":"Luc Baeyens",
    "wof:placetype":"venue"
},
  "geometry": {"coordinates":[4.3970880508,50.8104362488],"type":"Point"}
}