{
  "type": "Feature",
  "properties": {
    "addr:full":"Lotenhullestraat 21 Aalter (bellem) Oost-Vlaanderen 9881",
    "addr:housenumber":"21",
    "addr:postcode":"9881",
    "addr:street":"Lotenhullestraat",
    "iso:country":"BE",
    "sg:address":"Lotenhullestraat 21",
    "sg:city":"Aalter (bellem)",
    "sg:classifiers":[
        {
            "category":"Personal",
            "subcategory":"Nail Salon",
            "type":"Services"
        }
    ],
    "sg:phone":"+32 9 325 06 36",
    "sg:postcode":"9881",
    "sg:province":"Oost-Vlaanderen",
    "sg:tags":[
        "screw",
        "cutting"
    ],
    "wof:name":"Van Daele Vof",
    "wof:placetype":"venue"
},
  "geometry": {"coordinates":[3.4807910919,51.0721092224],"type":"Point"}
}