{
  "type": "Feature",
  "properties": {
    "iso:country":"BE",
    "sg:address":"R De Taillis-pr\u00e9 68b",
    "sg:city":"Ch\u00e2telineau",
    "sg:classifiers":[
        {
            "category":"Manufacturing",
            "subcategory":"Metals",
            "type":"Manufacturing & Wholesale Goods"
        }
    ],
    "sg:phone":"+32 71 39 50 57",
    "sg:postcode":"6200",
    "sg:province":"Hainaut",
    "sg:tags":[
        "-",
        "machine",
        "equipment",
        "engineering",
        "machinery",
        "mechanical"
    ],
    "wof:name":"Macar Scrl",
    "wof:placetype":"venue"
},
  "geometry": {"coordinates":[4.5071759224,50.4332809448],"type":"Point"}
}