{
  "type": "Feature",
  "properties": {
    "iso:country":"BE",
    "sg:address":"Bareldreef 12",
    "sg:city":"Bornem",
    "sg:orig_category":"Epiceries",
    "sg:phone":"+32 3 899 28 16",
    "sg:postcode":"2880",
    "sg:province":"Antwerpen",
    "wof:name":"Carine Peeters",
    "wof:placetype":"venue"
},
  "geometry": {"coordinates":[4.2315587997,51.0871505737],"type":"Point"}
}