{
  "type": "Feature",
  "properties": {
    "iso:country":"BE",
    "sg:address":"Rue Ranson 80",
    "sg:city":"Brussel",
    "sg:orig_category":"Secr\u00e9tariats",
    "sg:phone":"+32 2 242 45 29",
    "sg:postcode":"1130",
    "sg:province":"Bruxelles-Capitale",
    "wof:name":"Robert R",
    "wof:placetype":"venue"
},
  "geometry": {"coordinates":[4.4068660736,50.8857574463],"type":"Point"}
}