{
  "type": "Feature",
  "properties": {
    "addr:full":"Route De L'etat 200 Lasne (lasne-chapelle-saint-lambert) Brabant Wallon 1380",
    "addr:housenumber":"200",
    "addr:postcode":"1380",
    "addr:street":"Route De L'Etat;Wallon",
    "iso:country":"BE",
    "sg:address":"Route De L'etat 200",
    "sg:city":"Lasne (lasne-chapelle-saint-lambert)",
    "sg:classifiers":[
        {
            "category":"Personal",
            "subcategory":"Beauty Salon",
            "type":"Services"
        }
    ],
    "sg:phone":"+32 2 653 18 64",
    "sg:postcode":"1380",
    "sg:province":"Brabant Wallon",
    "sg:tags":[
        "lady",
        "-",
        "hairdressing"
    ],
    "wof:name":"Lineaire Coiffure",
    "wof:placetype":"venue"
},
  "geometry": {"coordinates":[4.4650979042,50.6699104309],"type":"Point"}
}