{
  "type": "Feature",
  "properties": {
    "addr:full":"Hulststraat 1 Glabbeek Vlaams-Brabant 3381",
    "addr:housenumber":"1",
    "addr:postcode":"3381",
    "addr:street":"Hulststraat",
    "iso:country":"BE",
    "sg:address":"Hulststraat 1",
    "sg:city":"Glabbeek",
    "sg:orig_category":"Eleveurs de bovins",
    "sg:phone":"+32 16 77 76 86",
    "sg:postcode":"3381",
    "sg:province":"Vlaams-Brabant",
    "wof:name":"Michel Coekelberghs",
    "wof:placetype":"venue"
},
  "geometry": {"coordinates":[4.953417778,50.886428833],"type":"Point"}
}