{
  "type": "Feature",
  "properties": {
    "addr:full":"Hannuitsesteenweg 209 Landen Vlaams-Brabant 3401",
    "addr:housenumber":"209",
    "addr:postcode":"3401",
    "addr:street":"Hannuitsesteenweg",
    "iso:country":"BE",
    "sg:address":"Hannuitsesteenweg 209",
    "sg:city":"Landen",
    "sg:orig_category":"Electrom\u00e9nager, t\u00e9l\u00e9visions and radios",
    "sg:phone":"+32 11 88 42 94",
    "sg:postcode":"3401",
    "sg:province":"Vlaams-Brabant",
    "wof:name":"E.s.w.",
    "wof:placetype":"venue"
},
  "geometry": {"coordinates":[5.0813670158,50.7370948792],"type":"Point"}
}