{
  "type": "Feature",
  "properties": {
    "addr:full":"Rue Des Combattants 39a Thuin Hainaut 6536",
    "addr:housenumber":"39a",
    "addr:postcode":"6536",
    "addr:street":"Rue Des Combattants",
    "iso:country":"BE",
    "sg:address":"Rue Des Combattants 39a",
    "sg:city":"Thuin",
    "sg:orig_category":"Meubelzaken, woning- and keukeninrichting Textiel Verlichting and huishoudartikelen",
    "sg:phone":"+32 71 53 37 84",
    "sg:postcode":"6536",
    "sg:province":"Hainaut",
    "wof:name":"Jadis - L'art Du Cadeau",
    "wof:placetype":"venue"
},
  "geometry": {"coordinates":[4.3290910721,50.2941627502],"type":"Point"}
}