{
  "type": "Feature",
  "properties": {
    "iso:country":"BE",
    "sg:address":"Haesendonckstraat 51",
    "sg:city":"Vilvoorde",
    "sg:classifiers":[
        {
            "category":"Health Services",
            "subcategory":"Doctor",
            "type":"Services"
        }
    ],
    "sg:phone":"+32 2 251 95 04",
    "sg:postcode":"1800",
    "sg:province":"Vlaams-Brabant",
    "sg:tags":[
        "medicinephysicians",
        "surgeon"
    ],
    "wof:name":"Franck E",
    "wof:placetype":"venue"
},
  "geometry": {"coordinates":[4.4693779945,50.951210022],"type":"Point"}
}