{
  "type": "Feature",
  "properties": {
    "addr:full":"Grotstraat 18 Peer Limburg 3990",
    "addr:housenumber":"18",
    "addr:postcode":"3990",
    "addr:street":"Grotstraat",
    "iso:country":"BE",
    "sg:address":"Grotstraat 18",
    "sg:city":"Peer",
    "sg:classifiers":[
        {
            "category":"Personal",
            "subcategory":"Beauty Salon",
            "type":"Services"
        }
    ],
    "sg:phone":"+32 11 79 37 77",
    "sg:postcode":"3990",
    "sg:province":"Limburg",
    "sg:tags":[
        "child",
        "-",
        "hairdressing"
    ],
    "wof:name":"Monique",
    "wof:placetype":"venue"
},
  "geometry": {"coordinates":[5.4412078857,51.0966720581],"type":"Point"}
}