{
  "type": "Feature",
  "properties": {
    "iso:country":"BE",
    "sg:address":"Jean-baptiste Meunierstr 27",
    "sg:city":"Elsene/ixelles",
    "sg:orig_category":"Elektrische installaties voor woningen",
    "sg:phone":"+32 2 344 43 82",
    "sg:postcode":"1050",
    "sg:province":"Bruxelles-Capitale",
    "wof:name":"Herv\u00c9 Dulait",
    "wof:placetype":"venue"
},
  "geometry": {"coordinates":[4.3500437737,50.8147468567],"type":"Point"}
}