{
  "type": "Feature",
  "properties": {
    "iso:country":"BE",
    "sg:address":"Koningin Astridlaan 44",
    "sg:city":"Kontich",
    "sg:classifiers":[
        {
            "category":"Transit Center",
            "subcategory":"Passenger",
            "type":"Transportation"
        }
    ],
    "sg:phone":"+32 3 457 67 44",
    "sg:postcode":"2550",
    "sg:province":"Antwerpen",
    "sg:tags":[
        "car",
        "trailer"
    ],
    "wof:name":"Aerts P",
    "wof:placetype":"venue"
},
  "geometry": {"coordinates":[4.4557771683,51.1309547424],"type":"Point"}
}