{
  "type": "Feature",
  "properties": {
    "iso:country":"BE",
    "sg:address":"Walplein 41",
    "sg:city":"Brugge",
    "sg:orig_category":"Antiek Meubelzaken, woning- and keukeninrichting",
    "sg:phone":"+32 50 33 66 87",
    "sg:postcode":"8000",
    "sg:province":"West-Vlaanderen",
    "wof:name":"Antiques Papyrus",
    "wof:placetype":"venue"
},
  "geometry": {"coordinates":[3.2243800163,51.2028083801],"type":"Point"}
}