{
  "type": "Feature",
  "properties": {
    "addr:full":"Jukstraat 25 Hasselt Limburg 3500",
    "addr:housenumber":"25",
    "addr:postcode":"3500",
    "addr:street":"Jukstraat",
    "iso:country":"BE",
    "sg:address":"Jukstraat 25",
    "sg:city":"Hasselt",
    "sg:orig_category":"Rev\u00eatements de sols and murs. Installation de menuiserie en bois and plastique",
    "sg:phone":"+32 11 31 16 10",
    "sg:postcode":"3500",
    "sg:province":"Limburg",
    "wof:name":"Vanholst",
    "wof:placetype":"venue"
},
  "geometry": {"coordinates":[5.3043761253,50.9026451111],"type":"Point"}
}