{
  "type": "Feature",
  "properties": {
    "addr:full":"Avenue Des H\u00c9liotropes 5 Schaarbeek/schaerbeek Bruxelles-Capitale 1030",
    "addr:housenumber":"5",
    "addr:postcode":"1030",
    "addr:street":"Avenue Des He\u0301Liotropes",
    "iso:country":"BE",
    "sg:address":"Avenue Des H\u00c9liotropes 5",
    "sg:city":"Schaarbeek/schaerbeek",
    "sg:orig_category":"M\u00e9decins and sp\u00e9cialistes",
    "sg:phone":"+32 2 241 53 93",
    "sg:postcode":"1030",
    "sg:province":"Bruxelles-Capitale",
    "wof:name":"C. Pierreux",
    "wof:placetype":"venue"
},
  "geometry": {"coordinates":[4.3869509697,50.8633384705],"type":"Point"}
}