{
  "type": "Feature",
  "properties": {
    "iso:country":"BE",
    "sg:address":"15",
    "sg:city":"Rue Du Rempart 7900 Leuze-en-hainaut",
    "sg:classifiers":[
        {
            "category":"Professional",
            "subcategory":"Engineering",
            "type":"Services"
        }
    ],
    "sg:phone":"+32 69 66 32 61",
    "sg:postcode":"15",
    "sg:tags":[
        "machine",
        "-",
        "mechanical"
    ],
    "wof:name":"Wallays Sprl",
    "wof:placetype":"venue"
},
  "geometry": {"coordinates":[3.6206839085,50.5992164612],"type":"Point"}
}