{
  "type": "Feature",
  "properties": {
    "iso:country":"BE",
    "sg:address":"Rue De La Halette 159",
    "sg:city":"Seraing (jemeppe-sur-meuse)",
    "sg:classifiers":[
        {
            "category":"Communications",
            "type":"Services"
        }
    ],
    "sg:phone":"+32 4 229 38 99",
    "sg:postcode":"4101",
    "sg:province":"Li\u00e8ge",
    "sg:tags":[
        "translator"
    ],
    "wof:name":"World Translation Services",
    "wof:placetype":"venue"
},
  "geometry": {"coordinates":[5.5081391335,50.6226234436],"type":"Point"}
}