{
  "type": "Feature",
  "properties": {
    "iso:country":"BE",
    "sg:address":"Zuidzandstraat 10",
    "sg:city":"Brugge",
    "sg:classifiers":[
        {
            "category":"Bakery",
            "type":"Food & Drink"
        }
    ],
    "sg:phone":"+32 50 33 33 84",
    "sg:postcode":"8000",
    "sg:province":"West-Vlaanderen",
    "sg:tags":[
        "confectioner",
        "baker"
    ],
    "wof:name":"St-salvator",
    "wof:placetype":"venue"
},
  "geometry": {"coordinates":[3.2203710079,51.2056617737],"type":"Point"}
}