{
  "type": "Feature",
  "properties": {
    "iso:country":"BE",
    "sg:address":"Chauss\u00e9e De Bruxelles 474",
    "sg:city":"Enghien (petit-enghien)",
    "sg:classifiers":[
        {
            "category":"Health Services",
            "subcategory":"Health Practitioner",
            "type":"Services"
        }
    ],
    "sg:phone":"+32 2 395 89 42",
    "sg:postcode":"7850",
    "sg:province":"Hainaut",
    "sg:tags":[
        "therapist",
        "speech"
    ],
    "wof:name":"Vandorpe Val\u00e9rie",
    "wof:placetype":"venue"
},
  "geometry": {"coordinates":[4.0501379967,50.6929473877],"type":"Point"}
}