{
  "type": "Feature",
  "properties": {
    "addr:full":"Vrijdagmarkt 10 Gent Oost-Vlaanderen 9000",
    "addr:housenumber":"10",
    "addr:postcode":"9000",
    "addr:street":"Vrijdagmarkt;Oost-Vlaanderen",
    "iso:country":"BE",
    "sg:address":"Vrijdagmarkt 10",
    "sg:city":"Gent",
    "sg:orig_category":"Diverse organisaties and verenigingen",
    "sg:phone":"+32 9 234 04 64",
    "sg:postcode":"9000",
    "sg:province":"Oost-Vlaanderen",
    "wof:name":"M.j.a.",
    "wof:placetype":"venue"
},
  "geometry": {"coordinates":[3.7253270149,51.0574264526],"type":"Point"}
}