{
  "type": "Feature",
  "properties": {
    "iso:country":"BE",
    "sg:address":"Albert I-promenade 9",
    "sg:city":"Oostende",
    "sg:orig_category":"RESTAURANTS: ALIMENTATION SP\u00c9CIALIS\u00c9E",
    "sg:phone":"+32 59 70 35 56",
    "sg:postcode":"8400",
    "sg:province":"West-Vlaanderen",
    "wof:name":"Restaurant Marina",
    "wof:placetype":"venue"
},
  "geometry": {"coordinates":[2.9201319218,51.2348175049],"type":"Point"}
}