{
  "type": "Feature",
  "properties": {
    "addr:full":"Schepdaalstraat 83 Dilbeek Vlaams-Brabant 1700",
    "addr:housenumber":"83",
    "addr:postcode":"1700",
    "addr:street":"Schepdaalstraat",
    "iso:country":"BE",
    "sg:address":"Schepdaalstraat 83",
    "sg:city":"Dilbeek",
    "sg:classifiers":[
        {
            "category":"Food & Beverages",
            "subcategory":"Fruits & Vegetables",
            "type":"Retail Goods"
        }
    ],
    "sg:phone":"+32 2 582 26 94",
    "sg:postcode":"1700",
    "sg:province":"Vlaams-Brabant",
    "sg:tags":[
        "l\u00e9gumes",
        "gr"
    ],
    "wof:name":"Andre Van Belle",
    "wof:placetype":"venue"
},
  "geometry": {"coordinates":[4.2051720619,50.8524932861],"type":"Point"}
}