{
  "type": "Feature",
  "properties": {
    "iso:country":"BE",
    "sg:address":"Veldstraat 160",
    "sg:city":"Koekelare",
    "sg:orig_category":"Eleveurs and marchands de porcs. Eleveurs de bovins",
    "sg:phone":"+32 51 58 89 30",
    "sg:postcode":"8680",
    "sg:province":"West-Vlaanderen",
    "wof:name":"Michel Depreitere",
    "wof:placetype":"venue"
},
  "geometry": {"coordinates":[2.9680960178,51.0789031982],"type":"Point"}
}