{
  "type": "Feature",
  "properties": {
    "addr:full":"Liersesteenweg 56 Aarschot Vlaams-Brabant 3200",
    "addr:housenumber":"56",
    "addr:postcode":"3200",
    "addr:street":"Liersesteenweg",
    "iso:country":"BE",
    "sg:address":"Liersesteenweg 56",
    "sg:city":"Aarschot",
    "sg:classifiers":[
        {
            "category":"Professional",
            "subcategory":"Art Services",
            "type":"Services"
        }
    ],
    "sg:phone":"+32 16 56 56 21",
    "sg:postcode":"3200",
    "sg:province":"Vlaams-Brabant",
    "sg:tags":[
        "children's",
        "animation"
    ],
    "wof:name":"Ambipleks",
    "wof:placetype":"venue"
},
  "geometry": {"coordinates":[4.8307619095,50.9997444153],"type":"Point"}
}