{
  "type": "Feature",
  "properties": {
    "addr:full":"Langerei 68 Brugge West-Vlaanderen 8000",
    "addr:housenumber":"68",
    "addr:postcode":"8000",
    "addr:street":"Langerei",
    "iso:country":"BE",
    "sg:address":"Langerei 68",
    "sg:city":"Brugge",
    "sg:orig_category":"Bijouteries and horlogeries",
    "sg:phone":"+32 50 34 38 03",
    "sg:postcode":"8000",
    "sg:province":"West-Vlaanderen",
    "wof:name":"Valerie V",
    "wof:placetype":"venue"
},
  "geometry": {"coordinates":[3.229131937,51.2183265686],"type":"Point"}
}