{
  "type": "Feature",
  "properties": {
    "iso:country":"BE",
    "sg:address":"Place L\u00c9opold 6",
    "sg:city":"Arlon",
    "sg:classifiers":[
        {
            "category":"Restaurant",
            "type":"Food & Drink"
        }
    ],
    "sg:phone":"+32 63 22 28 30",
    "sg:postcode":"6700",
    "sg:province":"Luxembourg",
    "wof:name":"L'arlequin",
    "wof:placetype":"venue"
},
  "geometry": {"coordinates":[5.8132982254,49.6833190918],"type":"Point"}
}