{
  "type": "Feature",
  "properties": {
    "addr:full":"Sterrebeekstraat 1811c-2c Zaventem Vlaams-Brabant 1930",
    "addr:housenumber":"1811c-2c",
    "addr:postcode":"1930",
    "addr:street":"Sterrebeekstraat",
    "iso:country":"BE",
    "sg:address":"Sterrebeekstraat 1811c-2c",
    "sg:city":"Zaventem",
    "sg:orig_category":"Non-Classified Establishments",
    "sg:phone":"+32 2 715 20 80",
    "sg:postcode":"1930",
    "sg:province":"Vlaams-Brabant",
    "wof:name":"Duscholux Belgium Nv",
    "wof:placetype":"venue"
},
  "geometry": {"coordinates":[4.4880671501,50.8698387146],"type":"Point"}
}