{
  "type": "Feature",
  "properties": {
    "iso:country":"BE",
    "sg:address":"Werchtersesteenweg 164",
    "sg:city":"Haacht",
    "sg:orig_category":"Experts-comptables",
    "sg:phone":"+32 16 60 54 88",
    "sg:postcode":"3150",
    "sg:province":"Vlaams-Brabant",
    "wof:name":"Andreas Hens",
    "wof:placetype":"venue"
},
  "geometry": {"coordinates":[4.6640439034,50.9720153809],"type":"Point"}
}