{
  "type": "Feature",
  "properties": {
    "addr:full":"Rue Grande 61 Quievrain Hainaut 7380",
    "addr:housenumber":"61",
    "addr:postcode":"7380",
    "addr:street":"Rue Grande;Hainaut",
    "iso:country":"BE",
    "sg:address":"Rue Grande 61",
    "sg:city":"Quievrain",
    "sg:classifiers":[
        {
            "category":"Food & Beverages",
            "subcategory":"Fruits & Vegetables",
            "type":"Retail Goods"
        }
    ],
    "sg:phone":"+32 65 43 06 48",
    "sg:postcode":"7380",
    "sg:province":"Hainaut",
    "sg:tags":[
        "groenten"
    ],
    "wof:name":"Au Maraicher",
    "wof:placetype":"venue"
},
  "geometry": {"coordinates":[3.6829929352,50.405418396],"type":"Point"}
}