{
  "type": "Feature",
  "properties": {
    "addr:full":"Oostendestraat 107 Sint-jans-molenbeek/molenbeek-saint-jean Bruxelles-Capitale 1080",
    "addr:housenumber":"107",
    "addr:postcode":"1080",
    "addr:street":"Oostendestraat",
    "iso:country":"BE",
    "sg:address":"Oostendestraat 107",
    "sg:city":"Sint-jans-molenbeek/molenbeek-saint-jean",
    "sg:orig_category":"Persagentschappen",
    "sg:phone":"+32 2 410 64 56",
    "sg:postcode":"1080",
    "sg:province":"Bruxelles-Capitale",
    "wof:name":"Samira Loulidi",
    "wof:placetype":"venue"
},
  "geometry": {"coordinates":[4.3292651176,50.8551254272],"type":"Point"}
}