{
  "type": "Feature",
  "properties": {
    "addr:full":"Alfons Pieterslaan 86 Oostende West-Vlaanderen 8400",
    "addr:housenumber":"86",
    "addr:postcode":"8400",
    "addr:street":"Alfons Pieterslaan",
    "iso:country":"BE",
    "sg:address":"Alfons Pieterslaan 86",
    "sg:city":"Oostende",
    "sg:classifiers":[
        {
            "category":"Communications",
            "subcategory":"Radio Station",
            "type":"Services"
        }
    ],
    "sg:phone":"+32 59 80 47 04",
    "sg:postcode":"8400",
    "sg:province":"West-Vlaanderen",
    "sg:tags":[
        "local"
    ],
    "wof:name":"Radio Mango Oostende",
    "wof:placetype":"venue"
},
  "geometry": {"coordinates":[2.9114069939,51.2251777649],"type":"Point"}
}