{
  "type": "Feature",
  "properties": {
    "iso:country":"BE",
    "sg:address":"Rue De L'enseignement 11",
    "sg:city":"Sprimont",
    "sg:orig_category":"Rundveehouders",
    "sg:phone":"+32 4 382 10 71",
    "sg:postcode":"4140",
    "sg:province":"Li\u00e8ge",
    "wof:name":"Minguet",
    "wof:placetype":"venue"
},
  "geometry": {"coordinates":[5.6315369606,50.5133171082],"type":"Point"}
}