{
  "type": "Feature",
  "properties": {
    "iso:country":"BE",
    "sg:address":"Rue De La Couture 22",
    "sg:city":"Houyet",
    "sg:classifiers":[
        {
            "category":"Insurance",
            "subcategory":"Insurance Agent",
            "type":"Services"
        }
    ],
    "sg:phone":"+32 82 66 64 16",
    "sg:postcode":"5560",
    "sg:province":"Namur",
    "sg:tags":[
        "broker"
    ],
    "wof:name":"Dethise J",
    "wof:placetype":"venue"
},
  "geometry": {"coordinates":[5.0143208504,50.1806411743],"type":"Point"}
}