{
  "type": "Feature",
  "properties": {
    "addr:full":"Hasseltweg 423 Genk Limburg 3600",
    "addr:housenumber":"423",
    "addr:postcode":"3600",
    "addr:street":"Hasseltweg",
    "iso:country":"BE",
    "sg:address":"Hasseltweg 423",
    "sg:city":"Genk",
    "sg:classifiers":[
        {
            "category":"Health Services",
            "subcategory":"Dentist",
            "type":"Services"
        }
    ],
    "sg:phone":"+32 11 22 95 57",
    "sg:postcode":"3600",
    "sg:province":"Limburg",
    "wof:name":"Vanschoenbeek Renaat",
    "wof:placetype":"venue"
},
  "geometry": {"coordinates":[5.4345149994,50.9573249817],"type":"Point"}
}