{
  "type": "Feature",
  "properties": {
    "addr:full":"Scheepstraat 2 Maasmechelen Limburg 3630",
    "addr:housenumber":"2",
    "addr:postcode":"3630",
    "addr:street":"Scheepstraat",
    "iso:country":"BE",
    "sg:address":"Scheepstraat 2",
    "sg:city":"Maasmechelen",
    "sg:orig_category":"Goederenvervoer over de weg Koerierbedrijven",
    "sg:phone":"+32 89 77 12 78",
    "sg:postcode":"3630",
    "sg:province":"Limburg",
    "wof:name":"Tar Freight",
    "wof:placetype":"venue"
},
  "geometry": {"coordinates":[5.6970472336,50.9486808777],"type":"Point"}
}