{
  "type": "Feature",
  "properties": {
    "iso:country":"BE",
    "sg:address":"Elsstraat 31",
    "sg:city":"Gent",
    "sg:classifiers":[
        {
            "category":"Shopping",
            "subcategory":"Clothing, Apparel, & Fashions",
            "type":"Retail Goods"
        }
    ],
    "sg:phone":"+32 9 223 60 50",
    "sg:postcode":"9000",
    "sg:province":"Oost-Vlaanderen",
    "sg:tags":[
        "purchase",
        "clothing",
        "-",
        "sale",
        "second-hand"
    ],
    "wof:name":"Tele Kleding Vzw",
    "wof:placetype":"venue"
},
  "geometry": {"coordinates":[3.712362051,51.0647201538],"type":"Point"}
}