{
  "type": "Feature",
  "properties": {
    "iso:country":"BE",
    "sg:address":"Rue Du Paquis 66",
    "sg:city":"Etalle",
    "sg:classifiers":[
        {
            "category":"Landmark",
            "subcategory":"Memorial",
            "type":"Public Place"
        }
    ],
    "sg:phone":"+32 63 45 52 50",
    "sg:postcode":"6740",
    "sg:province":"Luxembourg",
    "sg:tags":[
        "-",
        "monument"
    ],
    "wof:name":"Hanus Ets",
    "wof:placetype":"venue"
},
  "geometry": {"coordinates":[5.6061367989,49.6734046936],"type":"Point"}
}