{
  "type": "Feature",
  "properties": {
    "iso:country":"BE",
    "sg:address":"Rue Arthur Mahaux 44",
    "sg:city":"Namur (boninne - Gelbress\u00e9e)",
    "sg:classifiers":[
        {
            "category":"Health Services",
            "subcategory":"Health Practitioner",
            "type":"Services"
        }
    ],
    "sg:phone":"+32 81 21 03 30",
    "sg:postcode":"5021",
    "sg:province":"Namur",
    "sg:tags":[
        "physiotherapist"
    ],
    "wof:name":"Verhelpen M",
    "wof:placetype":"venue"
},
  "geometry": {"coordinates":[4.9269981384,50.4956893921],"type":"Point"}
}