{
  "type": "Feature",
  "properties": {
    "addr:full":"Avenue De La Bruy\u00e8re 10 Rhode-saint-gen\u00e8se Vlaams-Brabant 1640",
    "addr:housenumber":"10",
    "addr:postcode":"1640",
    "addr:street":"Avenue De La Bruye\u0300Re",
    "iso:country":"BE",
    "sg:address":"Avenue De La Bruy\u00e8re 10",
    "sg:city":"Rhode-saint-gen\u00e8se",
    "sg:classifiers":[
        {
            "category":"Building & Trades",
            "subcategory":"Landscaping Services",
            "type":"Services"
        }
    ],
    "sg:phone":"+32 2 380 05 75",
    "sg:postcode":"1640",
    "sg:province":"Vlaams-Brabant",
    "sg:tags":[
        "access",
        "pond",
        "laying-out",
        "-"
    ],
    "wof:name":"Technigarden Int.",
    "wof:placetype":"venue"
},
  "geometry": {"coordinates":[4.3242602348,50.7281990051],"type":"Point"}
}