{
  "type": "Feature",
  "properties": {
    "iso:country":"BE",
    "sg:address":"Jan Van Looylaan 4",
    "sg:city":"Koksijde",
    "sg:classifiers":[
        {
            "category":"Health Services",
            "subcategory":"Health Practitioner",
            "type":"Services"
        }
    ],
    "sg:phone":"+32 58 51 57 76",
    "sg:postcode":"8670",
    "sg:province":"West-Vlaanderen",
    "sg:tags":[
        "physiotherapist"
    ],
    "wof:name":"Louwagie Monique",
    "wof:placetype":"venue"
},
  "geometry": {"coordinates":[2.6155509949,51.1051902771],"type":"Point"}
}