{
  "type": "Feature",
  "properties": {
    "iso:country":"BE",
    "sg:address":"Rue De Lens 143",
    "sg:city":"Soignies (casteau)",
    "sg:classifiers":[
        {
            "category":"Home & Garden",
            "subcategory":"Building Materials",
            "type":"Retail Goods"
        }
    ],
    "sg:phone":"+32 65 73 19 92",
    "sg:postcode":"7061",
    "sg:province":"Hainaut",
    "sg:tags":[
        "window"
    ],
    "wof:name":"Poly System V",
    "wof:placetype":"venue"
},
  "geometry": {"coordinates":[3.9877130985,50.5198898315],"type":"Point"}
}