{
  "type": "Feature",
  "properties": {
    "addr:full":"Verboekt 167 Laakdal (forest) Antwerpen 2430",
    "addr:housenumber":"167",
    "addr:postcode":"2430",
    "addr:street":"Verboekt",
    "iso:country":"BE",
    "sg:address":"Verboekt 167",
    "sg:city":"Laakdal (forest)",
    "sg:classifiers":[
        {
            "category":"Personal",
            "subcategory":"Beauty Salon",
            "type":"Services"
        }
    ],
    "sg:phone":"+32 13 66 65 73",
    "sg:postcode":"2430",
    "sg:province":"Antwerpen",
    "sg:tags":[
        "lady",
        "-",
        "hairdressing"
    ],
    "wof:name":"Gerda",
    "wof:placetype":"venue"
},
  "geometry": {"coordinates":[5.0872821808,51.0938682556],"type":"Point"}
}