{
  "type": "Feature",
  "properties": {
    "addr:full":"Rue Nicolas-spiroux 207 Li\u00e8ge 1 (grivegn\u00e9e) Li\u00e8ge 4030",
    "addr:housenumber":"207;1",
    "addr:postcode":"4030",
    "addr:street":"Rue Nicolas-Spiroux",
    "iso:country":"BE",
    "sg:address":"Rue Nicolas-spiroux 207",
    "sg:city":"Li\u00e8ge 1 (grivegn\u00e9e)",
    "sg:classifiers":[
        {
            "category":"Insurance",
            "subcategory":"Insurance Agent",
            "type":"Services"
        }
    ],
    "sg:phone":"+32 4 361 01 01",
    "sg:postcode":"4030",
    "sg:province":"Li\u00e8ge",
    "sg:tags":[
        "broker"
    ],
    "wof:name":"Delrez E",
    "wof:placetype":"venue"
},
  "geometry": {"coordinates":[5.6161971092,50.6252555847],"type":"Point"}
}