{
  "type": "Feature",
  "properties": {
    "addr:full":"Grote Markt 25 Menen West-Vlaanderen 8930",
    "addr:housenumber":"25",
    "addr:postcode":"8930",
    "addr:street":"Grote Markt",
    "iso:country":"BE",
    "sg:address":"Grote Markt 25",
    "sg:city":"Menen",
    "sg:orig_category":"S\u00e9curit\u00e9 sociale",
    "sg:phone":"+32 56 52 10 60",
    "sg:postcode":"8930",
    "sg:province":"West-Vlaanderen",
    "wof:name":"Christelijke Mutualiteit",
    "wof:placetype":"venue"
},
  "geometry": {"coordinates":[3.1203069687,50.7963218689],"type":"Point"}
}