{
  "type": "Feature",
  "properties": {
    "iso:country":"BE",
    "sg:address":"Schuttersstraat 13",
    "sg:city":"Peer",
    "sg:orig_category":"M\u00e9decins and sp\u00e9cialistes",
    "sg:phone":"+32 11 63 35 31",
    "sg:postcode":"3990",
    "sg:province":"Limburg",
    "wof:name":"Sylvie Schepers",
    "wof:placetype":"venue"
},
  "geometry": {"coordinates":[5.5109977722,51.1561965942],"type":"Point"}
}