{
  "type": "Feature",
  "properties": {
    "iso:country":"BE",
    "sg:address":"Beauvoislaan 18",
    "sg:city":"Kalmthout",
    "sg:orig_category":"Artistes ind\u00e9pendants",
    "sg:phone":"+32 3 666 09 67",
    "sg:postcode":"2920",
    "sg:province":"Antwerpen",
    "wof:name":"Alex Wilequet",
    "wof:placetype":"venue"
},
  "geometry": {"coordinates":[4.4714918137,51.3671875],"type":"Point"}
}