{
  "type": "Feature",
  "properties": {
    "addr:full":"Heilig Hartstraat 14 Antwerpen (berchem) Antwerpen 2600",
    "addr:housenumber":"14",
    "addr:postcode":"2600",
    "addr:street":"Heilig Hartstraat;Antwerpen",
    "iso:country":"BE",
    "sg:address":"Heilig Hartstraat 14",
    "sg:city":"Antwerpen (berchem)",
    "sg:orig_category":"Newspapers, magazines, periodicals - Publishers",
    "sg:phone":"+32 3 281 21 00",
    "sg:postcode":"2600",
    "sg:province":"Antwerpen",
    "wof:name":"Bruid & Bruidegom Magazine",
    "wof:placetype":"venue"
},
  "geometry": {"coordinates":[4.4174151421,51.1974411011],"type":"Point"}
}