{
  "type": "Feature",
  "properties": {
    "addr:full":"Rue De Jolimont 117 Manage (la Hestre) Hainaut 7170",
    "addr:housenumber":"117",
    "addr:postcode":"7170",
    "addr:street":"Rue De Jolimont;La;Hainaut",
    "iso:country":"BE",
    "sg:address":"Rue De Jolimont 117",
    "sg:city":"Manage (la Hestre)",
    "sg:classifiers":[
        {
            "category":"Health Services",
            "subcategory":"Doctor",
            "type":"Services"
        }
    ],
    "sg:phone":"+32 64 84 79 32",
    "sg:postcode":"7170",
    "sg:province":"Hainaut",
    "sg:tags":[
        "medicinephysicians",
        "surgeon"
    ],
    "wof:name":"Legat P",
    "wof:placetype":"venue"
},
  "geometry": {"coordinates":[4.2307600975,50.4763183594],"type":"Point"}
}