{
  "type": "Feature",
  "properties": {
    "iso:country":"BE",
    "sg:address":"Rue Du Pont 29",
    "sg:city":"Andenne",
    "sg:orig_category":"Instituts de beaut\u00e9",
    "sg:phone":"+32 85 84 60 92",
    "sg:postcode":"5300",
    "sg:province":"Namur",
    "wof:name":"Patricia Gustin",
    "wof:placetype":"venue"
},
  "geometry": {"coordinates":[5.0957269669,50.4927597046],"type":"Point"}
}