{
  "type": "Feature",
  "properties": {
    "addr:full":"Grote Markt 27 Tienen Vlaams-Brabant 3300",
    "addr:housenumber":"27",
    "addr:postcode":"3300",
    "addr:street":"Grote Markt",
    "iso:country":"BE",
    "sg:address":"Grote Markt 27",
    "sg:city":"Tienen",
    "sg:classifiers":[
        {
            "category":"Health Services",
            "subcategory":"Nursing And Care Facility",
            "type":"Services"
        }
    ],
    "sg:phone":"+32 16 80 57 68",
    "sg:postcode":"3300",
    "sg:province":"Vlaams-Brabant",
    "sg:tags":[
        "public"
    ],
    "wof:name":"Stadsbestuur",
    "wof:placetype":"venue"
},
  "geometry": {"coordinates":[4.9372358322,50.8069190979],"type":"Point"}
}