{
  "type": "Feature",
  "properties": {
    "iso:country":"BE",
    "sg:address":"Chemin Du Paradis 4",
    "sg:city":"Quaregnon",
    "sg:classifiers":[
        {
            "category":"Building & Trades",
            "subcategory":"Cleaning & Sanitation",
            "type":"Services"
        }
    ],
    "sg:phone":"+32 65 80 08 47",
    "sg:postcode":"7390",
    "sg:province":"Hainaut",
    "sg:tags":[
        "cleaner",
        "window"
    ],
    "wof:name":"Manu Vitres",
    "wof:placetype":"venue"
},
  "geometry": {"coordinates":[3.8696429729,50.43983078],"type":"Point"}
}