{
  "type": "Feature",
  "properties": {
    "addr:full":"Rue De La Station 85 Braine-le-comte Hainaut 7090",
    "addr:housenumber":"85",
    "addr:postcode":"7090",
    "addr:street":"Rue De La Station",
    "iso:country":"BE",
    "sg:address":"Rue De La Station 85",
    "sg:city":"Braine-le-comte",
    "sg:orig_category":"Electrom\u00e9nager, t\u00e9l\u00e9visions and radios. Mat\u00e9riel de T\u00e9l\u00e9communication. R\u00e9parations d'appareils \u00e9lect",
    "sg:phone":"+32 67 55 22 61",
    "sg:postcode":"7090",
    "sg:province":"Hainaut",
    "wof:name":"Maison Beretta",
    "wof:placetype":"venue"
},
  "geometry": {"coordinates":[4.137365818,50.6075363159],"type":"Point"}
}