{
  "type": "Feature",
  "properties": {
    "iso:country":"BE",
    "sg:address":"Rue Max Fassiaux 9",
    "sg:city":"Soignies (naast)",
    "sg:classifiers":[
        {
            "category":"Bars & Pubs",
            "type":"Food & Drink"
        }
    ],
    "sg:phone":"+32 67 33 51 37",
    "sg:postcode":"7062",
    "sg:province":"Hainaut",
    "wof:name":"Sports (caf\u00e9 Des)",
    "wof:placetype":"venue"
},
  "geometry": {"coordinates":[4.0996851921,50.5541000366],"type":"Point"}
}