{
  "type": "Feature",
  "properties": {
    "addr:full":"Sint-jozef 60 Rijkevorsel Antwerpen 2310",
    "addr:housenumber":"60",
    "addr:postcode":"2310",
    "iso:country":"BE",
    "sg:address":"Sint-jozef 60",
    "sg:city":"Rijkevorsel",
    "sg:orig_category":"Imprimeries and copyshops",
    "sg:phone":"+32 3 311 70 75",
    "sg:postcode":"2310",
    "sg:province":"Antwerpen",
    "wof:name":"Marc Geerts",
    "wof:placetype":"venue"
},
  "geometry": {"coordinates":[4.7848992348,51.3278045654],"type":"Point"}
}