{
  "type": "Feature",
  "properties": {
    "addr:full":"Hendrik Deberghstraat 8 Vleteren West-Vlaanderen 8640",
    "addr:housenumber":"8",
    "addr:postcode":"8640",
    "addr:street":"Deberghstraat",
    "iso:country":"BE",
    "sg:address":"Hendrik Deberghstraat 8",
    "sg:city":"Vleteren",
    "sg:orig_category":"Enseignement maternel and primaire",
    "sg:phone":"+32 57 40 04 40",
    "sg:postcode":"8640",
    "sg:province":"West-Vlaanderen",
    "wof:name":"Basisschool",
    "wof:placetype":"venue"
},
  "geometry": {"coordinates":[2.7385599613,50.9313850403],"type":"Point"}
}