{
  "type": "Feature",
  "properties": {
    "iso:country":"BE",
    "sg:address":"Stationsstraat 14",
    "sg:city":"Eeklo",
    "sg:orig_category":"Parfumeries. Instituts de beaut\u00e9",
    "sg:phone":"+32 9 377 23 84",
    "sg:postcode":"9900",
    "sg:province":"Oost-Vlaanderen",
    "wof:name":"Pieters Parfumerie",
    "wof:placetype":"venue"
},
  "geometry": {"coordinates":[3.5736050606,51.1814041138],"type":"Point"}
}