{
  "type": "Feature",
  "properties": {
    "iso:country":"BE",
    "sg:address":"Dr\u00c8ve Du Moulin 93",
    "sg:city":"Waterloo",
    "sg:orig_category":"Rundveehouders",
    "sg:phone":"+32 2 354 77 28",
    "sg:postcode":"1410",
    "sg:province":"Brabant Wallon",
    "wof:name":"Fernand Taminiau",
    "wof:placetype":"venue"
},
  "geometry": {"coordinates":[4.3959732056,50.7183456421],"type":"Point"}
}