{
  "type": "Feature",
  "properties": {
    "iso:country":"BE",
    "sg:address":"Liersesteenweg 307",
    "sg:city":"Begijnendijk",
    "sg:orig_category":"Peinture. Rev\u00eatements pour sols and murs. Drogueries. Rev\u00eatements de sols and murs. Quincailleries",
    "sg:phone":"+32 16 56 07 35",
    "sg:postcode":"3130",
    "sg:province":"Vlaams-Brabant",
    "wof:name":"Verdonck",
    "wof:placetype":"venue"
},
  "geometry": {"coordinates":[4.8081979752,51.0117912292],"type":"Point"}
}