{
  "type": "Feature",
  "properties": {
    "iso:country":"BE",
    "sg:address":"Sint-pietersaalststraat 42",
    "sg:city":"Gent-centrum",
    "sg:orig_category":"Advocaten and juridische adviseurs Balie van Gent",
    "sg:phone":"+32 9 245 11 62",
    "sg:postcode":"9000",
    "sg:province":"Oost-Vlaanderen",
    "wof:name":"Van Eeckaute Joyce",
    "wof:placetype":"venue"
},
  "geometry": {"coordinates":[3.7145779133,51.0306549072],"type":"Point"}
}