{
  "type": "Feature",
  "properties": {
    "addr:full":"Stokerijstraat 32 Lommel Limburg 3920",
    "addr:housenumber":"32",
    "addr:postcode":"3920",
    "addr:street":"Stokerijstraat",
    "iso:country":"BE",
    "sg:address":"Stokerijstraat 32",
    "sg:city":"Lommel",
    "sg:classifiers":[
        {
            "category":"Insurance",
            "subcategory":"Insurance Agent",
            "type":"Services"
        }
    ],
    "sg:phone":"+32 11 54 04 44",
    "sg:postcode":"3920",
    "sg:province":"Limburg",
    "sg:tags":[
        "verzekeringsmakelaars",
        "expert"
    ],
    "wof:name":"Bureau Geuens",
    "wof:placetype":"venue"
},
  "geometry": {"coordinates":[5.3214578629,51.2246322632],"type":"Point"}
}