{
  "type": "Feature",
  "properties": {
    "iso:country":"BE",
    "sg:address":"Rue De Gohyssart 62",
    "sg:city":"Charleroi (roux)",
    "sg:classifiers":[
        {
            "category":"Health Services",
            "subcategory":"Health Practitioner",
            "type":"Services"
        }
    ],
    "sg:phone":"+32 71 35 21 60",
    "sg:postcode":"6044",
    "sg:province":"Hainaut",
    "sg:tags":[
        "physiotherapist"
    ],
    "wof:name":"Di Primio L",
    "wof:placetype":"venue"
},
  "geometry": {"coordinates":[4.4040021896,50.4326438904],"type":"Point"}
}