{
  "type": "Feature",
  "properties": {
    "addr:full":"Poelstraat 75 Oostkamp West-Vlaanderen 8020",
    "addr:housenumber":"75",
    "addr:postcode":"8020",
    "addr:street":"Poelstraat",
    "iso:country":"BE",
    "sg:address":"Poelstraat 75",
    "sg:city":"Oostkamp",
    "sg:classifiers":[
        {
            "category":"Home & Garden",
            "subcategory":"Building Materials",
            "type":"Retail Goods"
        }
    ],
    "sg:phone":"+32 50 82 38 51",
    "sg:postcode":"8020",
    "sg:province":"West-Vlaanderen",
    "sg:tags":[
        "aluminium",
        "window"
    ],
    "wof:name":"Van Hauwaert B.v.b.a.",
    "wof:placetype":"venue"
},
  "geometry": {"coordinates":[3.2291901112,51.1617927551],"type":"Point"}
}