{
  "type": "Feature",
  "properties": {
    "iso:country":"BE",
    "sg:address":"Avenue Edmond Parmentier 150 Box 13",
    "sg:city":"Bruxelles (woluwe-saint-pierre)",
    "sg:classifiers":[
        {
            "category":"Professional",
            "subcategory":"Accounting & Tax Preparation",
            "type":"Services"
        }
    ],
    "sg:phone":"+32 2 771 07 81",
    "sg:postcode":"1150",
    "sg:province":"Bruxelles-Capitale",
    "sg:tags":[
        "accountant"
    ],
    "wof:name":"Atelier D'exp Compt Thierry Schwers Sprl",
    "wof:placetype":"venue"
},
  "geometry": {"coordinates":[4.4449701309,50.8318214417],"type":"Point"}
}