{
  "type": "Feature",
  "properties": {
    "iso:country":"BE",
    "sg:address":"Hollestraat 11",
    "sg:city":"Erpe-mere",
    "sg:orig_category":"Paramedische behandelingen",
    "sg:phone":"+32 53 62 27 21",
    "sg:postcode":"9420",
    "sg:province":"Oost-Vlaanderen",
    "wof:name":"J. Denaeyer",
    "wof:placetype":"venue"
},
  "geometry": {"coordinates":[3.9421749115,50.8908615112],"type":"Point"}
}