{
  "type": "Feature",
  "properties": {
    "addr:full":"Avenue Mar\u00e9chal Juin 12 Gembloux-sur-orneau (gembloux) Namur 5030",
    "addr:housenumber":"12",
    "addr:postcode":"5030",
    "addr:street":"Avenue Mare\u0301Chal Juin;Namur",
    "iso:country":"BE",
    "sg:address":"Avenue Mar\u00e9chal Juin 12",
    "sg:city":"Gembloux-sur-orneau (gembloux)",
    "sg:classifiers":[
        {
            "category":"Personal",
            "subcategory":"Beauty Salon",
            "type":"Services"
        }
    ],
    "sg:phone":"+32 81 60 04 44",
    "sg:postcode":"5030",
    "sg:province":"Namur",
    "wof:name":"Bel Alibi",
    "wof:placetype":"venue"
},
  "geometry": {"coordinates":[4.7011919022,50.5618247986],"type":"Point"}
}