{
  "type": "Feature",
  "properties": {
    "addr:full":"Meulenbroekstraat 4 Hamme Oost-Vlaanderen 9220",
    "addr:housenumber":"4",
    "addr:postcode":"9220",
    "addr:street":"Meulenbroekstraat",
    "iso:country":"BE",
    "sg:address":"Meulenbroekstraat 4",
    "sg:city":"Hamme",
    "sg:orig_category":"Centres sportifs",
    "sg:phone":"+32 52 47 63 74",
    "sg:postcode":"9220",
    "sg:province":"Oost-Vlaanderen",
    "wof:name":"Meulenbroek",
    "wof:placetype":"venue"
},
  "geometry": {"coordinates":[4.1370749474,51.1004486084],"type":"Point"}
}