{
  "type": "Feature",
  "properties": {
    "iso:country":"BE",
    "sg:address":"Chauss\u00c9e De Russeignies 1",
    "sg:city":"Ronse",
    "sg:orig_category":"Drogueries. Jeux and jouets. Salons de coiffure. Jeux and jouets",
    "sg:phone":"+32 55 20 98 19",
    "sg:postcode":"9600",
    "sg:province":"Oost-Vlaanderen",
    "wof:name":"Booking",
    "wof:placetype":"venue"
},
  "geometry": {"coordinates":[3.557199955,50.7492294312],"type":"Point"}
}