{
  "type": "Feature",
  "properties": {
    "iso:country":"BE",
    "sg:address":"Brandakkers 4",
    "sg:city":"Rijkevorsel",
    "sg:classifiers":[
        {
            "category":"Farming",
            "subcategory":"Crops",
            "type":"Manufacturing & Wholesale Goods"
        }
    ],
    "sg:phone":"+32 3 314 33 99",
    "sg:postcode":"2310",
    "sg:province":"Antwerpen",
    "sg:tags":[
        "vegetable",
        "fruit",
        "-",
        "grower"
    ],
    "wof:name":"Bruneel-cox Bvba",
    "wof:placetype":"venue"
},
  "geometry": {"coordinates":[4.7968268394,51.3632125854],"type":"Point"}
}