{
  "type": "Feature",
  "properties": {
    "iso:country":"BE",
    "sg:address":"Perrestraat 58",
    "sg:city":"Herzele",
    "sg:orig_category":"Slagers",
    "sg:phone":"+32 9 360 16 74",
    "sg:postcode":"9550",
    "sg:province":"Oost-Vlaanderen",
    "wof:name":"Johan Vlaeminck",
    "wof:placetype":"venue"
},
  "geometry": {"coordinates":[3.8574240208,50.8920860291],"type":"Point"}
}