{
  "type": "Feature",
  "properties": {
    "addr:full":"Place Paul Roger 2 Virton Luxembourg 6760",
    "addr:housenumber":"2",
    "addr:postcode":"6760",
    "addr:street":"Place Paul Roger",
    "iso:country":"BE",
    "sg:address":"Place Paul Roger 2",
    "sg:city":"Virton",
    "sg:orig_category":"Ordinateurs and \u00e9quipement informatique",
    "sg:phone":"+32 63 57 82 75",
    "sg:postcode":"6760",
    "sg:province":"Luxembourg",
    "wof:name":"Virus.com",
    "wof:placetype":"venue"
},
  "geometry": {"coordinates":[5.5334620476,49.5663414001],"type":"Point"}
}