{
  "type": "Feature",
  "properties": {
    "addr:full":"Houtemstraat 30 Zonnebeke West-Vlaanderen 8980",
    "addr:housenumber":"30",
    "addr:postcode":"8980",
    "addr:street":"Houtemstraat",
    "iso:country":"BE",
    "sg:address":"Houtemstraat 30",
    "sg:city":"Zonnebeke",
    "sg:orig_category":"Rundveehouders Varkenskwekers",
    "sg:phone":"+32 57 46 64 84",
    "sg:postcode":"8980",
    "sg:province":"West-Vlaanderen",
    "wof:name":"Marc Ghekiere",
    "wof:placetype":"venue"
},
  "geometry": {"coordinates":[2.9872550964,50.8730812073],"type":"Point"}
}