{
  "type": "Feature",
  "properties": {
    "addr:full":"Stationsstraat 21 Essen Antwerpen 2910",
    "addr:housenumber":"21",
    "addr:postcode":"2910",
    "addr:street":"Stationsstraat",
    "iso:country":"BE",
    "sg:address":"Stationsstraat 21",
    "sg:city":"Essen",
    "sg:orig_category":"Banken and kredietinstellingen",
    "sg:phone":"+32 3 667 66 71",
    "sg:postcode":"2910",
    "sg:province":"Antwerpen",
    "wof:name":"Dexia",
    "wof:placetype":"venue"
},
  "geometry": {"coordinates":[4.4668707848,51.46692276],"type":"Point"}
}