{
  "type": "Feature",
  "properties": {
    "addr:full":"Waregemstraat 378 Deerlijk West-Vlaanderen 8540",
    "addr:housenumber":"378",
    "addr:postcode":"8540",
    "addr:street":"Waregemstraat",
    "iso:country":"BE",
    "sg:address":"Waregemstraat 378",
    "sg:city":"Deerlijk",
    "sg:orig_category":"P\u00e9pini\u00e9ristes. Clubs de sport",
    "sg:phone":"+32 56 70 61 90",
    "sg:postcode":"8540",
    "sg:province":"West-Vlaanderen",
    "wof:name":"Deerlijkse Zwemvereniging",
    "wof:placetype":"venue"
},
  "geometry": {"coordinates":[3.3788781166,50.8597793579],"type":"Point"}
}