{
  "type": "Feature",
  "properties": {
    "addr:full":"Avenue De L'aulne 106b1 Ukkel/uccle Bruxelles-Capitale 1180",
    "addr:housenumber":"106b1",
    "addr:postcode":"1180",
    "addr:street":"Avenue De L'Aulne;/",
    "iso:country":"BE",
    "sg:address":"Avenue De L'aulne 106b1",
    "sg:city":"Ukkel/uccle",
    "sg:orig_category":"Installation \u00e9lectrique r\u00e9sidentielle",
    "sg:phone":"+32 2 376 69 64",
    "sg:postcode":"1180",
    "sg:province":"Bruxelles-Capitale",
    "wof:name":"Christophe Quintin",
    "wof:placetype":"venue"
},
  "geometry": {"coordinates":[4.3307437897,50.8050079346],"type":"Point"}
}