{
  "type": "Feature",
  "properties": {
    "addr:full":"Rue Du Croupet 1 Bassenge (boirs) Li\u00e8ge 4690",
    "addr:housenumber":"1",
    "addr:postcode":"4690",
    "addr:street":"Rue Du Croupet",
    "iso:country":"BE",
    "sg:address":"Rue Du Croupet 1",
    "sg:city":"Bassenge (boirs)",
    "sg:classifiers":[
        {
            "category":"Farming",
            "subcategory":"Fish & Marine Products",
            "type":"Manufacturing & Wholesale Goods"
        }
    ],
    "sg:phone":"+32 4 286 21 54",
    "sg:postcode":"4690",
    "sg:province":"Li\u00e8ge",
    "sg:tags":[
        "retail",
        "-",
        "shellfish"
    ],
    "wof:name":"Franky Poissonnerie",
    "wof:placetype":"venue"
},
  "geometry": {"coordinates":[5.5723791122,50.7540245056],"type":"Point"}
}