{
  "type": "Feature",
  "properties": {
    "addr:full":"Rue De La Caserne 78 Brussel/bruxelles Bruxelles-Capitale 1000",
    "addr:housenumber":"78",
    "addr:postcode":"1000",
    "addr:street":"Rue De La Caserne;/",
    "iso:country":"BE",
    "sg:address":"Rue De La Caserne 78",
    "sg:city":"Brussel/bruxelles",
    "sg:classifiers":[
        {
            "category":"Professional",
            "subcategory":"Business Services",
            "type":"Services"
        }
    ],
    "sg:phone":"+32 2 502 08 09",
    "sg:postcode":"1000",
    "sg:province":"Bruxelles-Capitale",
    "sg:tags":[
        "aux",
        "diver",
        "entreprises"
    ],
    "wof:name":"Jean-pierre Mels",
    "wof:placetype":"venue"
},
  "geometry": {"coordinates":[4.3418388367,50.8417358398],"type":"Point"}
}