{
  "type": "Feature",
  "properties": {
    "iso:country":"BE",
    "sg:address":"Oude Heerweg 147",
    "sg:city":"Tienen",
    "sg:orig_category":"Varkenskwekers",
    "sg:phone":"+32 16 78 86 62",
    "sg:postcode":"3300",
    "sg:province":"Vlaams-Brabant",
    "wof:name":"Raymond Hoebrechts",
    "wof:placetype":"venue"
},
  "geometry": {"coordinates":[4.9685249329,50.7977218628],"type":"Point"}
}