{
  "type": "Feature",
  "properties": {
    "addr:full":"Zelebaan 132 Lokeren Oost-Vlaanderen 9160",
    "addr:housenumber":"132",
    "addr:postcode":"9160",
    "addr:street":"Lokeren Oost-Vlaanderen",
    "iso:country":"BE",
    "sg:address":"Zelebaan 132",
    "sg:city":"Lokeren",
    "sg:classifiers":[
        {
            "category":"Retail",
            "subcategory":"Auto Repair",
            "type":"Services"
        }
    ],
    "sg:phone":"+32 9 348 50 40",
    "sg:postcode":"9160",
    "sg:province":"Oost-Vlaanderen",
    "sg:tags":[
        "automobile-body"
    ],
    "wof:name":"De Smedt Motors Bvba",
    "wof:placetype":"venue"
},
  "geometry": {"coordinates":[4.0178141594,51.0914039612],"type":"Point"}
}