{
  "type": "Feature",
  "properties": {
    "addr:full":"Alfred Nichelsstraat 57 Aalst Oost-Vlaanderen 9300",
    "addr:housenumber":"57",
    "addr:postcode":"9300",
    "addr:street":"Alfred Nichelsstraat",
    "iso:country":"BE",
    "sg:address":"Alfred Nichelsstraat 57",
    "sg:city":"Aalst",
    "sg:orig_category":"Douanekantoren Vrachtvervoer",
    "sg:phone":"+32 53 77 03 18",
    "sg:postcode":"9300",
    "sg:province":"Oost-Vlaanderen",
    "wof:name":"Thames Dender Service",
    "wof:placetype":"venue"
},
  "geometry": {"coordinates":[4.0475020409,50.9347572327],"type":"Point"}
}