{
  "type": "Feature",
  "properties": {
    "iso:country":"BE",
    "sg:address":"Rue Des Hauchies 25a",
    "sg:city":"Charleroi",
    "sg:orig_category":"Dakwerken Loodgieterij, verwarming and sanitaire installaties",
    "sg:phone":"+32 71 41 46 20",
    "sg:postcode":"6042",
    "sg:province":"Hainaut",
    "wof:name":"Pierre Devos",
    "wof:placetype":"venue"
},
  "geometry": {"coordinates":[4.4594531059,50.3889541626],"type":"Point"}
}