{
  "type": "Feature",
  "properties": {
    "iso:country":"BE",
    "sg:address":"Lode De Boningestraat 3",
    "sg:city":"Edegem",
    "sg:classifiers":[
        {
            "category":"Insurance",
            "subcategory":"Insurance Agent",
            "type":"Services"
        }
    ],
    "sg:phone":"+32 3 458 06 63",
    "sg:postcode":"2650",
    "sg:province":"Antwerpen",
    "sg:tags":[
        "verzekeringsmakelaars",
        "expert"
    ],
    "wof:name":"Ren\u00c9 Janssens",
    "wof:placetype":"venue"
},
  "geometry": {"coordinates":[4.425260067,51.1535758972],"type":"Point"}
}