{
  "type": "Feature",
  "properties": {
    "iso:country":"BE",
    "sg:address":"Rue De Longtain 95",
    "sg:city":"La Louviere",
    "sg:orig_category":"Charpentes and couvertures. Construction de maisons",
    "sg:phone":"+32 64 28 13 08",
    "sg:postcode":"7100",
    "sg:province":"Hainaut",
    "wof:name":"Tecren",
    "wof:placetype":"venue"
},
  "geometry": {"coordinates":[4.20566082,50.4799118042],"type":"Point"}
}