{
  "type": "Feature",
  "properties": {
    "iso:country":"BE",
    "sg:address":"Rue Du Lac 40",
    "sg:city":"Bruxelles",
    "sg:classifiers":[
        {
            "category":"Health Services",
            "subcategory":"Dentist",
            "type":"Services"
        }
    ],
    "sg:phone":"+32 2 640 11 59",
    "sg:postcode":"1000",
    "sg:province":"Bruxelles-Capitale",
    "wof:name":"Manche Genevi\u00e8ve",
    "wof:placetype":"venue"
},
  "geometry": {"coordinates":[4.3698182106,50.8231239319],"type":"Point"}
}