{
  "type": "Feature",
  "properties": {
    "addr:full":"Steenweg Hulst-lessen 85 Temse Oost-Vlaanderen 9140",
    "addr:housenumber":"85",
    "addr:postcode":"9140",
    "addr:street":"Steenweg Hulst-Lessen",
    "iso:country":"BE",
    "sg:address":"Steenweg Hulst-lessen 85",
    "sg:city":"Temse",
    "sg:orig_category":"Brood, gebak and snoepgoed",
    "sg:phone":"+32 52 46 24 51",
    "sg:postcode":"9140",
    "sg:province":"Oost-Vlaanderen",
    "wof:name":"Ruth Polfliet",
    "wof:placetype":"venue"
},
  "geometry": {"coordinates":[4.135327816,51.1300735474],"type":"Point"}
}