{
  "type": "Feature",
  "properties": {
    "addr:full":"Haagdam 2 Ba Temse Oost-Vlaanderen 9140",
    "addr:housenumber":"2",
    "addr:postcode":"9140",
    "addr:street":"Haagdam;Oost-Vlaanderen",
    "iso:country":"BE",
    "sg:address":"Haagdam 2 Ba",
    "sg:city":"Temse",
    "sg:orig_category":"Production and transformation de viande. Boucheries",
    "sg:phone":"+32 3 775 51 68",
    "sg:postcode":"9140",
    "sg:province":"Oost-Vlaanderen",
    "wof:name":"Van Hoey",
    "wof:placetype":"venue"
},
  "geometry": {"coordinates":[4.2221589088,51.1755447388],"type":"Point"}
}