{
  "type": "Feature",
  "properties": {
    "addr:full":"Rue Terre-neuve 136b11/1 Brussel/bruxelles Bruxelles-Capitale 1000",
    "addr:housenumber":"136b11 / 1",
    "addr:postcode":"1000",
    "addr:street":"Rue Terre-Neuve;/",
    "iso:country":"BE",
    "sg:address":"Rue Terre-neuve 136b11/1",
    "sg:city":"Brussel/bruxelles",
    "sg:orig_category":"V\u00eatements sur mesure Fab",
    "sg:phone":"+32 2 511 65 42",
    "sg:postcode":"1000",
    "sg:province":"Bruxelles-Capitale",
    "wof:name":"Francesca Aumento",
    "wof:placetype":"venue"
},
  "geometry": {"coordinates":[4.3438677788,50.8393287659],"type":"Point"}
}