{
  "type": "Feature",
  "properties": {
    "iso:country":"BE",
    "sg:address":"Brugsepoortstraat 35",
    "sg:city":"Gent",
    "sg:orig_category":"Diverse juridische dienstverlening",
    "sg:phone":"+32 9 225 10 52",
    "sg:postcode":"9000",
    "sg:province":"Oost-Vlaanderen",
    "wof:name":"Verkoopzaal Sirejacobs",
    "wof:placetype":"venue"
},
  "geometry": {"coordinates":[3.7097969055,51.0564956665],"type":"Point"}
}