{
  "type": "Feature",
  "properties": {
    "iso:country":"BE",
    "sg:address":"Les-hayons 7",
    "sg:city":"Florenville",
    "sg:orig_category":"Eleveurs de bovins",
    "sg:phone":"+32 61 31 10 63",
    "sg:postcode":"6820",
    "sg:province":"Luxembourg",
    "wof:name":"Jules Henriquet",
    "wof:placetype":"venue"
},
  "geometry": {"coordinates":[5.3284778595,49.6869773865],"type":"Point"}
}