{
  "type": "Feature",
  "properties": {
    "addr:full":"Haagstraat 17 Zomergem Oost-Vlaanderen 9930",
    "addr:housenumber":"17",
    "addr:postcode":"9930",
    "addr:street":"Haagstraat",
    "iso:country":"BE",
    "sg:address":"Haagstraat 17",
    "sg:city":"Zomergem",
    "sg:orig_category":"Forge, Moulage and Profilage des M\u00e9taux. Installation de menuiserie m\u00e9tallique",
    "sg:phone":"+32 9 372 78 80",
    "sg:postcode":"9930",
    "sg:province":"Oost-Vlaanderen",
    "wof:name":"De Brouwer",
    "wof:placetype":"venue"
},
  "geometry": {"coordinates":[3.5450649261,51.1138153076],"type":"Point"}
}