{
  "type": "Feature",
  "properties": {
    "iso:country":"BE",
    "sg:address":"Rue De Verviers 173",
    "sg:city":"Herve",
    "sg:orig_category":"Installatie van houten of kunststof schrijnwerk Installatie van metalen schrijnwerk",
    "sg:phone":"+32 475 71 52 96",
    "sg:postcode":"4650",
    "sg:province":"Li\u00e8ge",
    "wof:name":"Cts",
    "wof:placetype":"venue"
},
  "geometry": {"coordinates":[5.8262600899,50.6255683899],"type":"Point"}
}