{
  "type": "Feature",
  "properties": {
    "iso:country":"BE",
    "sg:address":"Rue Neuve 69",
    "sg:city":"Pepinster",
    "sg:orig_category":"Kapsalons",
    "sg:phone":"+32 87 46 90 63",
    "sg:postcode":"4860",
    "sg:province":"Li\u00e8ge",
    "wof:name":"Coiffure Guido & Richard",
    "wof:placetype":"venue"
},
  "geometry": {"coordinates":[5.8032550812,50.5661277771],"type":"Point"}
}