{
  "type": "Feature",
  "properties": {
    "addr:full":"Denderbellestraat 2 Dendermonde (sint-gillis-bij-dendermonde) Oost-Vlaanderen 9200",
    "addr:housenumber":"2",
    "addr:postcode":"9200",
    "addr:street":"Denderbellestraat",
    "iso:country":"BE",
    "sg:address":"Denderbellestraat 2",
    "sg:city":"Dendermonde (sint-gillis-bij-dendermonde)",
    "sg:classifiers":[
        {
            "category":"Social Services",
            "subcategory":"Child Care",
            "type":"Services"
        }
    ],
    "sg:phone":"+32 52 20 22 95",
    "sg:postcode":"9200",
    "sg:province":"Oost-Vlaanderen",
    "sg:tags":[
        "baby",
        "nursery",
        "day",
        "sitting"
    ],
    "wof:name":"De Speeltrein",
    "wof:placetype":"venue"
},
  "geometry": {"coordinates":[4.0943331718,51.0183105469],"type":"Point"}
}