{
  "type": "Feature",
  "properties": {
    "addr:full":"Boekweitstraat 69 Schoten Antwerpen 2900",
    "addr:housenumber":"69",
    "addr:postcode":"2900",
    "addr:street":"Boekweitstraat",
    "iso:country":"BE",
    "sg:address":"Boekweitstraat 69",
    "sg:city":"Schoten",
    "sg:classifiers":[
        {
            "category":"Building & Trades",
            "subcategory":"Construction",
            "type":"Services"
        }
    ],
    "sg:phone":"+32 3 685 24 97",
    "sg:postcode":"2900",
    "sg:province":"Antwerpen",
    "sg:tags":[
        "glazier"
    ],
    "wof:name":"Glaswerken Steve Gedopt",
    "wof:placetype":"venue"
},
  "geometry": {"coordinates":[4.501349926,51.2593841553],"type":"Point"}
}