{
  "type": "Feature",
  "properties": {
    "iso:country":"BE",
    "sg:address":"Bisschoppenhoflaan 302",
    "sg:city":"Deurne",
    "sg:classifiers":[
        {
            "category":"Utilities",
            "subcategory":"Telephone",
            "type":"Services"
        }
    ],
    "sg:phone":"+32 3 326 46 00",
    "sg:postcode":"2100",
    "sg:province":"Antwerpen",
    "sg:tags":[
        "telecommunication"
    ],
    "wof:name":"Arrow Air Nv",
    "wof:placetype":"venue"
},
  "geometry": {"coordinates":[4.4596290588,51.2327651978],"type":"Point"}
}