{
  "type": "Feature",
  "properties": {
    "addr:full":"Rietweg 3 Merelbeke Oost-Vlaanderen 9820",
    "addr:housenumber":"3",
    "addr:postcode":"9820",
    "addr:street":"Rietweg",
    "iso:country":"BE",
    "sg:address":"Rietweg 3",
    "sg:city":"Merelbeke",
    "sg:classifiers":[
        {
            "category":"Real Estate",
            "subcategory":"Architect",
            "type":"Services"
        }
    ],
    "sg:phone":"+32 9 230 05 52",
    "sg:postcode":"9820",
    "sg:province":"Oost-Vlaanderen",
    "wof:name":"Van Der Meirsch K",
    "wof:placetype":"venue"
},
  "geometry": {"coordinates":[3.7471449375,51.0172080994],"type":"Point"}
}