{
  "type": "Feature",
  "properties": {
    "addr:full":"Avenue Chazal 53 Schaarbeek/schaerbeek Bruxelles-Capitale 1030",
    "addr:housenumber":"53",
    "addr:postcode":"1030",
    "addr:street":"Avenue Chazal",
    "iso:country":"BE",
    "sg:address":"Avenue Chazal 53",
    "sg:city":"Schaarbeek/schaerbeek",
    "sg:orig_category":"Travaux de pl\u00e2trage. Construction de maisons",
    "sg:phone":"+32 2 736 75 97",
    "sg:postcode":"1030",
    "sg:province":"Bruxelles-Capitale",
    "wof:name":"Barry Construction",
    "wof:placetype":"venue"
},
  "geometry": {"coordinates":[4.3893671036,50.8550109863],"type":"Point"}
}