{
  "type": "Feature",
  "properties": {
    "addr:full":"Keistraat 2 Gent (sint-denijs-westrem - Afsnee) Oost-Vlaanderen 9051",
    "addr:housenumber":"2",
    "addr:postcode":"9051",
    "addr:street":"Keistraat;Oost-Vlaanderen",
    "iso:country":"BE",
    "sg:address":"Keistraat 2",
    "sg:city":"Gent (sint-denijs-westrem - Afsnee)",
    "sg:classifiers":[
        {
            "category":"Health Services",
            "subcategory":"Health Practitioner",
            "type":"Services"
        }
    ],
    "sg:phone":"+32 9 282 73 27",
    "sg:postcode":"9051",
    "sg:province":"Oost-Vlaanderen",
    "sg:tags":[
        "physiotherapist"
    ],
    "wof:name":"Demeulemeester Anne-marie",
    "wof:placetype":"venue"
},
  "geometry": {"coordinates":[3.6563830376,51.00806427],"type":"Point"}
}