{
  "type": "Feature",
  "properties": {
    "iso:country":"BE",
    "sg:address":"Rue Du Ch\u00cane Br\u00dbl\u00c9 4",
    "sg:city":"Dour",
    "sg:orig_category":"Paramedische behandelingen",
    "sg:phone":"+32 65 65 07 70",
    "sg:postcode":"7370",
    "sg:province":"Hainaut",
    "wof:name":"Nathalie Aucello",
    "wof:placetype":"venue"
},
  "geometry": {"coordinates":[3.7877459526,50.3940582275],"type":"Point"}
}