{
  "type": "Feature",
  "properties": {
    "iso:country":"BE",
    "sg:address":"Placette Aux Oignons 9bis",
    "sg:city":"Tournai",
    "sg:classifiers":[
        {
            "category":"Professional",
            "subcategory":"Management & Consulting",
            "type":"Services"
        }
    ],
    "sg:phone":"+32 69 22 34 42",
    "sg:postcode":"7500",
    "sg:province":"Hainaut",
    "sg:tags":[
        "consultant",
        "-",
        "legislation",
        "social"
    ],
    "wof:name":"Caisse De Compensation Des Allocations Familiales Du Tournaisis",
    "wof:placetype":"venue"
},
  "geometry": {"coordinates":[3.3848600388,50.6078262329],"type":"Point"}
}