{
  "type": "Feature",
  "properties": {
    "addr:full":"Maatheide 1302 Lommel Limburg 3920",
    "addr:housenumber":"1302",
    "addr:postcode":"3920",
    "addr:street":"Maatheide",
    "iso:country":"BE",
    "sg:address":"Maatheide 1302",
    "sg:city":"Lommel",
    "sg:classifiers":[
        {
            "category":"Structure",
            "subcategory":"Tower",
            "type":"Public Place"
        }
    ],
    "sg:phone":"+32 11 54 11 59",
    "sg:postcode":"3920",
    "sg:province":"Limburg",
    "sg:tags":[
        "steel"
    ],
    "wof:name":"Edibo Nv",
    "wof:placetype":"venue"
},
  "geometry": {"coordinates":[5.2657299042,51.234539032],"type":"Point"}
}