{
  "type": "Feature",
  "properties": {
    "iso:country":"BE",
    "sg:address":"Overbroekstraat 5",
    "sg:city":"Brecht",
    "sg:orig_category":"Charpentes and couvertures",
    "sg:phone":"+32 3 313 86 66",
    "sg:postcode":"2960",
    "sg:province":"Antwerpen",
    "wof:name":"Seal Roof Company",
    "wof:placetype":"venue"
},
  "geometry": {"coordinates":[4.6047101021,51.3486671448],"type":"Point"}
}