{
  "type": "Feature",
  "properties": {
    "addr:full":"Amerikalei 77 Antwerpen Antwerpen 2000",
    "addr:housenumber":"77",
    "addr:postcode":"2000",
    "addr:street":"Amerikalei",
    "iso:country":"BE",
    "sg:address":"Amerikalei 77",
    "sg:city":"Antwerpen",
    "sg:classifiers":[
        {
            "category":"Arena",
            "subcategory":"Sports Club",
            "type":"Entertainment"
        }
    ],
    "sg:phone":"+32 3 216 10 64",
    "sg:postcode":"2000",
    "sg:province":"Antwerpen",
    "sg:tags":[
        "federation"
    ],
    "wof:name":"European Football Consulting",
    "wof:placetype":"venue"
},
  "geometry": {"coordinates":[4.3982210159,51.2072868347],"type":"Point"}
}