{
  "type": "Feature",
  "properties": {
    "iso:country":"BE",
    "sg:address":"Rue De La Station 12",
    "sg:city":"Orp-jauche",
    "sg:orig_category":"Betonnen bouwelementen Fab",
    "sg:phone":"+32 19 63 31 24",
    "sg:postcode":"1350",
    "sg:province":"Brabant Wallon",
    "wof:name":"Ghetobloc",
    "wof:placetype":"venue"
},
  "geometry": {"coordinates":[4.98726511,50.6948814392],"type":"Point"}
}