{
  "type": "Feature",
  "properties": {
    "addr:full":"Rue De La Franco-belge 28 La Louvi\u00e8re Hainaut 7100",
    "addr:housenumber":"28",
    "addr:postcode":"7100",
    "addr:street":"Rue De La Franco-Belge",
    "iso:country":"BE",
    "sg:address":"Rue De La Franco-belge 28",
    "sg:city":"La Louvi\u00e8re",
    "sg:classifiers":[
        {
            "category":"Shopping",
            "subcategory":"Clothing, Apparel, & Fashions",
            "type":"Retail Goods"
        }
    ],
    "sg:phone":"+32 64 26 34 65",
    "sg:postcode":"7100",
    "sg:province":"Hainaut",
    "sg:tags":[
        "boutique"
    ],
    "wof:name":"H & M",
    "wof:placetype":"venue"
},
  "geometry": {"coordinates":[4.206633091,50.4872627258],"type":"Point"}
}