{
  "type": "Feature",
  "properties": {
    "addr:full":"Rue Fernand Neuray 32 Elsene/ixelles Bruxelles-Capitale 1050",
    "addr:housenumber":"32",
    "addr:postcode":"1050",
    "addr:street":"Rue Fernand Neuray",
    "iso:country":"BE",
    "sg:address":"Rue Fernand Neuray 32",
    "sg:city":"Elsene/ixelles",
    "sg:orig_category":"Antiquit\u00e9s",
    "sg:phone":"+32 2 345 41 30",
    "sg:postcode":"1050",
    "sg:province":"Bruxelles-Capitale",
    "wof:name":"Maison Temp\u00c9rance",
    "wof:placetype":"venue"
},
  "geometry": {"coordinates":[4.3560438156,50.8202629089],"type":"Point"}
}