{
  "type": "Feature",
  "properties": {
    "addr:full":"Rijmsnoerstraat 40 Kortrijk West-Vlaanderen 8501",
    "addr:housenumber":"40",
    "addr:postcode":"8501",
    "addr:street":"Rijmsnoerstraat",
    "iso:country":"BE",
    "sg:address":"Rijmsnoerstraat 40",
    "sg:city":"Kortrijk",
    "sg:orig_category":"Cr\u00e8ches and garderies d'enfants",
    "sg:phone":"+32 56 37 22 42",
    "sg:postcode":"8501",
    "sg:province":"West-Vlaanderen",
    "wof:name":"Kribbe 't Kabouterke",
    "wof:placetype":"venue"
},
  "geometry": {"coordinates":[3.2248179913,50.8268814087],"type":"Point"}
}