{
  "type": "Feature",
  "properties": {
    "iso:country":"BE",
    "sg:address":"Pierstraat 377",
    "sg:city":"Rumst",
    "sg:orig_category":"Diverse bedrijfsbeheeradviesbureaus",
    "sg:phone":"+32 3 888 02 47",
    "sg:postcode":"2840",
    "sg:province":"Antwerpen",
    "wof:name":"Verlinden",
    "wof:placetype":"venue"
},
  "geometry": {"coordinates":[4.3601207733,51.1093978882],"type":"Point"}
}