{
  "type": "Feature",
  "properties": {
    "addr:full":"Hoogstraat 19 Ronse/renaix Oost-Vlaanderen 9600",
    "addr:housenumber":"19",
    "addr:postcode":"9600",
    "addr:street":"Hoogstraat",
    "iso:country":"BE",
    "sg:address":"Hoogstraat 19",
    "sg:city":"Ronse/renaix",
    "sg:orig_category":"Elektrische installaties voor woningen Huishoudapparaten, televisies and radio's",
    "sg:phone":"+32 55 21 26 19",
    "sg:postcode":"9600",
    "sg:province":"Oost-Vlaanderen",
    "wof:name":"Electro D'hondt J. & F.",
    "wof:placetype":"venue"
},
  "geometry": {"coordinates":[3.5969619751,50.7458572388],"type":"Point"}
}