{
  "type": "Feature",
  "properties": {
    "addr:full":"Blauw-torenplein 6-8 Antwerpen Antwerpen 2000",
    "addr:housenumber":"6-8",
    "addr:postcode":"2000",
    "addr:street":"Blauw-Torenplein",
    "iso:country":"BE",
    "sg:address":"Blauw-torenplein 6-8",
    "sg:city":"Antwerpen",
    "sg:classifiers":[
        {
            "category":"Professional",
            "subcategory":"Computer Services",
            "type":"Services"
        }
    ],
    "sg:phone":"+32 3 226 20 06",
    "sg:postcode":"2000",
    "sg:province":"Antwerpen",
    "sg:tags":[
        "-",
        "processing",
        "data"
    ],
    "wof:name":"I.t. Pro Nv",
    "wof:placetype":"venue"
},
  "geometry": {"coordinates":[4.4087510109,51.21276474],"type":"Point"}
}