{
  "type": "Feature",
  "properties": {
    "addr:full":"Vogelzangstraat 34 Dessel Antwerpen 2480",
    "addr:housenumber":"34",
    "addr:postcode":"2480",
    "addr:street":"Vogelzangstraat",
    "iso:country":"BE",
    "sg:address":"Vogelzangstraat 34",
    "sg:city":"Dessel",
    "sg:orig_category":"Woningbouw",
    "sg:phone":"+32 14 37 13 17",
    "sg:postcode":"2480",
    "sg:province":"Antwerpen",
    "wof:name":"Ludo Wuyts",
    "wof:placetype":"venue"
},
  "geometry": {"coordinates":[5.0888328552,51.2411460876],"type":"Point"}
}