{
  "type": "Feature",
  "properties": {
    "addr:full":"Rue De Soumoy 26 Cerfontaine Namur 5630",
    "addr:housenumber":"26",
    "addr:postcode":"5630",
    "addr:street":"Rue De Soumoy",
    "iso:country":"BE",
    "sg:address":"Rue De Soumoy 26",
    "sg:city":"Cerfontaine",
    "sg:classifiers":[
        {
            "category":"Retail",
            "subcategory":"Auto Repair",
            "type":"Services"
        }
    ],
    "sg:phone":"+32 71 64 42 95",
    "sg:postcode":"5630",
    "sg:province":"Namur",
    "sg:tags":[
        "automobile-body"
    ],
    "wof:name":"Maufroid Garage",
    "wof:placetype":"venue"
},
  "geometry": {"coordinates":[4.4190530777,50.1722450256],"type":"Point"}
}