{
  "type": "Feature",
  "properties": {
    "addr:full":"De Belder 12 Kinrooi Limburg 3640",
    "addr:housenumber":"12",
    "addr:postcode":"3640",
    "addr:street":"Belder",
    "iso:country":"BE",
    "sg:address":"De Belder 12",
    "sg:city":"Kinrooi",
    "sg:orig_category":"Enseignement maternel and primaire",
    "sg:phone":"+32 89 56 53 47",
    "sg:postcode":"3640",
    "sg:province":"Limburg",
    "wof:name":"Gemeentelijke Basisschool",
    "wof:placetype":"venue"
},
  "geometry": {"coordinates":[5.7422151566,51.1452484131],"type":"Point"}
}