{
  "type": "Feature",
  "properties": {
    "iso:country":"BE",
    "sg:address":"Meir 26 Box 4",
    "sg:city":"Antwerpen",
    "sg:classifiers":[
        {
            "category":"Farming",
            "subcategory":"Berry Farm",
            "type":"Manufacturing & Wholesale Goods"
        }
    ],
    "sg:phone":"+32 3 213 93 80",
    "sg:postcode":"2000",
    "sg:province":"Antwerpen",
    "sg:tags":[
        "horticulture",
        "-",
        "broker",
        "whol",
        "seed",
        "grain",
        "agriculture"
    ],
    "wof:name":"Granaria",
    "wof:placetype":"venue"
},
  "geometry": {"coordinates":[4.4065871239,51.2180862427],"type":"Point"}
}