{
  "type": "Feature",
  "properties": {
    "addr:full":"Zandvoordsestraat 130 Oudenburg West-Vlaanderen 8460",
    "addr:housenumber":"130",
    "addr:postcode":"8460",
    "addr:street":"Zandvoordsestraat",
    "iso:country":"BE",
    "sg:address":"Zandvoordsestraat 130",
    "sg:city":"Oudenburg",
    "sg:orig_category":"Activit\u00e9s d\u00b4action sociale sans h\u00e9bergement",
    "sg:phone":"+32 59 26 69 83",
    "sg:postcode":"8460",
    "sg:province":"West-Vlaanderen",
    "wof:name":"Rode Kruis Oudenburg - Jabbeke",
    "wof:placetype":"venue"
},
  "geometry": {"coordinates":[2.9864609241,51.1940078735],"type":"Point"}
}