{
  "type": "Feature",
  "properties": {
    "addr:full":"Rue De Houssoi 296bc Andenne Namur 5300",
    "addr:housenumber":"296bc",
    "addr:postcode":"5300",
    "addr:street":"Rue De Houssoi",
    "iso:country":"BE",
    "sg:address":"Rue De Houssoi 296bc",
    "sg:city":"Andenne",
    "sg:orig_category":"Woningbouw",
    "sg:phone":"+32 81 58 02 67",
    "sg:postcode":"5300",
    "sg:province":"Namur",
    "wof:name":"Franco Pistrin",
    "wof:placetype":"venue"
},
  "geometry": {"coordinates":[5.0982642174,50.4863739014],"type":"Point"}
}