{
  "type": "Feature",
  "properties": {
    "iso:country":"BE",
    "sg:address":"Aardbeienstraat 14",
    "sg:city":"Ardooie",
    "sg:orig_category":"Onderdelen and accessoires voor auto's",
    "sg:phone":"+32 51 74 63 37",
    "sg:postcode":"8850",
    "sg:province":"West-Vlaanderen",
    "wof:name":"Den Technics",
    "wof:placetype":"venue"
},
  "geometry": {"coordinates":[3.1944758892,50.9825515747],"type":"Point"}
}