{
  "type": "Feature",
  "properties": {
    "iso:country":"BE",
    "sg:address":"Voltairelaan 161",
    "sg:city":"Schaarbeek/schaerbeek",
    "sg:orig_category":"Paramedische behandelingen Schoonheidssalons",
    "sg:phone":"+32 2 242 89 08",
    "sg:postcode":"1030",
    "sg:province":"Bruxelles-Capitale",
    "wof:name":"D'hu",
    "wof:placetype":"venue"
},
  "geometry": {"coordinates":[4.3802680969,50.8654212952],"type":"Point"}
}