{
  "type": "Feature",
  "properties": {
    "iso:country":"BE",
    "sg:address":"Odiel Spruyttestraat 34",
    "sg:city":"Izegem",
    "sg:classifiers":[
        {
            "category":"Professional",
            "subcategory":"Computer Services",
            "type":"Services"
        }
    ],
    "sg:phone":"+32 51 31 83 96",
    "sg:postcode":"8870",
    "sg:province":"West-Vlaanderen",
    "sg:tags":[
        "-",
        "processing",
        "data",
        "software"
    ],
    "wof:name":"H.s.q.",
    "wof:placetype":"venue"
},
  "geometry": {"coordinates":[3.2019929886,50.9098892212],"type":"Point"}
}