{
  "type": "Feature",
  "properties": {
    "iso:country":"BE",
    "sg:address":"Avenue De Limburg Stirum 106",
    "sg:city":"Wemmel",
    "sg:classifiers":[
        {
            "category":"Health Services",
            "subcategory":"Dentist",
            "type":"Services"
        }
    ],
    "sg:phone":"+32 2 460 76 28",
    "sg:postcode":"1780",
    "sg:province":"Vlaams-Brabant",
    "wof:name":"De Bondt Joss",
    "wof:placetype":"venue"
},
  "geometry": {"coordinates":[4.3183078766,50.9018058777],"type":"Point"}
}