{
  "type": "Feature",
  "properties": {
    "addr:full":"Dampoortstraat 41 Gent Oost-Vlaanderen 9000",
    "addr:housenumber":"41",
    "addr:postcode":"9000",
    "addr:street":"Dampoortstraat;Oost-Vlaanderen",
    "iso:country":"BE",
    "sg:address":"Dampoortstraat 41",
    "sg:city":"Gent",
    "sg:orig_category":"Opticiens",
    "sg:phone":"+32 9 225 06 53",
    "sg:postcode":"9000",
    "sg:province":"Oost-Vlaanderen",
    "wof:name":"Trioptic",
    "wof:placetype":"venue"
},
  "geometry": {"coordinates":[3.7350020409,51.0568962097],"type":"Point"}
}