{
  "type": "Feature",
  "properties": {
    "addr:full":"Kapelstraat 9 Antwerpen (hoboken) Antwerpen 2660",
    "addr:housenumber":"9",
    "addr:postcode":"2660",
    "addr:street":"Kapelstraat",
    "iso:country":"BE",
    "sg:address":"Kapelstraat 9",
    "sg:city":"Antwerpen (hoboken)",
    "sg:classifiers":[
        {
            "category":"Real Estate",
            "subcategory":"Real Estate Services",
            "type":"Services"
        }
    ],
    "sg:phone":"+32 3 825 16 32",
    "sg:postcode":"2660",
    "sg:province":"Antwerpen",
    "wof:name":"Marand Invest",
    "wof:placetype":"venue"
},
  "geometry": {"coordinates":[4.3272171021,51.350730896],"type":"Point"}
}