{
  "type": "Feature",
  "properties": {
    "iso:country":"BE",
    "sg:address":"Grand Rue 36",
    "sg:city":"Ligneuville",
    "sg:orig_category":"Installatie van houten of kunststof schrijnwerk MEUBELONTWERP AND -INSTALLATIE Siematic Keukens",
    "sg:phone":"+32 80 57 00 92",
    "sg:postcode":"4960",
    "sg:province":"Li\u00e8ge",
    "wof:name":"Meubles Warland",
    "wof:placetype":"venue"
},
  "geometry": {"coordinates":[6.0550851822,50.3746299744],"type":"Point"}
}