{
  "type": "Feature",
  "properties": {
    "addr:full":"Vrasenestraat 22 Sint-niklaas Oost-Vlaanderen 9100",
    "addr:housenumber":"22",
    "addr:postcode":"9100",
    "addr:street":"Vrasenestraat",
    "iso:country":"BE",
    "sg:address":"Vrasenestraat 22",
    "sg:city":"Sint-niklaas",
    "sg:orig_category":"Journaux. Fournitures de bureau. Tabac",
    "sg:phone":"+32 3 766 52 14",
    "sg:postcode":"9100",
    "sg:province":"Oost-Vlaanderen",
    "wof:name":"Huis Biblos",
    "wof:placetype":"venue"
},
  "geometry": {"coordinates":[4.1791038513,51.1948013306],"type":"Point"}
}