{
  "type": "Feature",
  "properties": {
    "iso:country":"BE",
    "sg:address":"Marktplein 17",
    "sg:city":"Diepenbeek",
    "sg:classifiers":[
        {
            "category":"Professional",
            "subcategory":"Testing Lab",
            "type":"Services"
        }
    ],
    "sg:phone":"+32 11 33 26 42",
    "sg:postcode":"3590",
    "sg:province":"Limburg",
    "sg:tags":[
        "chemist"
    ],
    "wof:name":"Souren P",
    "wof:placetype":"venue"
},
  "geometry": {"coordinates":[5.4186367989,50.9073982239],"type":"Point"}
}