{
  "type": "Feature",
  "properties": {
    "iso:country":"BE",
    "sg:address":"Rue Rioul 8",
    "sg:city":"Huy",
    "sg:orig_category":"Pr\u00eats hypoth\u00e9caires and cr\u00e9dits immobiliers. Cr\u00e9dit \u00e0 la consommation. Location de logements sociaux",
    "sg:phone":"+32 85 23 05 77",
    "sg:postcode":"4500",
    "sg:province":"Li\u00e8ge",
    "wof:name":"Foyer Huy-waremme",
    "wof:placetype":"venue"
},
  "geometry": {"coordinates":[5.2439398766,50.5226554871],"type":"Point"}
}