{
  "type": "Feature",
  "properties": {
    "iso:country":"BE",
    "sg:address":"Scharebrugstraat 75",
    "sg:city":"Blankenberge",
    "sg:orig_category":"Promoteurs immobiliers",
    "sg:phone":"+32 50 41 52 86",
    "sg:postcode":"8370",
    "sg:province":"West-Vlaanderen",
    "wof:name":"Celimmo",
    "wof:placetype":"venue"
},
  "geometry": {"coordinates":[3.1336610317,51.3066368103],"type":"Point"}
}