{
  "type": "Feature",
  "properties": {
    "addr:full":"Brugsesteenweg 682 Gent (mariakerke) Oost-Vlaanderen 9030",
    "addr:housenumber":"682",
    "addr:postcode":"9030",
    "addr:street":"Brugsesteenweg",
    "iso:country":"BE",
    "sg:address":"Brugsesteenweg 682",
    "sg:city":"Gent (mariakerke)",
    "sg:classifiers":[
        {
            "category":"Real Estate",
            "subcategory":"Architect",
            "type":"Services"
        }
    ],
    "sg:phone":"+32 9 227 92 39",
    "sg:postcode":"9030",
    "sg:province":"Oost-Vlaanderen",
    "wof:name":"De Smet W",
    "wof:placetype":"venue"
},
  "geometry": {"coordinates":[3.6778969765,51.0773277283],"type":"Point"}
}