{
  "type": "Feature",
  "properties": {
    "iso:country":"BE",
    "sg:address":"Sint-agatha-berchemlaan 18",
    "sg:city":"Koekelberg",
    "sg:orig_category":"Drukkerijen and copyshops Reclamebureaus",
    "sg:phone":"+32 2 414 12 12",
    "sg:postcode":"1081",
    "sg:province":"Bruxelles-Capitale",
    "wof:name":"Imprimerie Oprinta",
    "wof:placetype":"venue"
},
  "geometry": {"coordinates":[4.3171310425,50.8650894165],"type":"Point"}
}