{
  "type": "Feature",
  "properties": {
    "iso:country":"BE",
    "sg:address":"Kerselaarstraat 10",
    "sg:city":"Alveringem (leisele)",
    "sg:classifiers":[
        {
            "category":"Manufacturing",
            "subcategory":"Lumber",
            "type":"Manufacturing & Wholesale Goods"
        }
    ],
    "sg:phone":"+32 58 29 90 65",
    "sg:postcode":"8691",
    "sg:province":"West-Vlaanderen",
    "sg:tags":[
        "timber"
    ],
    "wof:name":"Ryckeboer R Nv",
    "wof:placetype":"venue"
},
  "geometry": {"coordinates":[2.6340529919,50.9881591797],"type":"Point"}
}