{
  "type": "Feature",
  "properties": {
    "addr:full":"Place Saint-lambert 6 Walcourt Namur 5651",
    "addr:housenumber":"6",
    "addr:postcode":"5651",
    "addr:street":"Place Saint-Lambert",
    "iso:country":"BE",
    "sg:address":"Place Saint-lambert 6",
    "sg:city":"Walcourt",
    "sg:orig_category":"Installation \u00e9lectrique r\u00e9sidentielle. R\u00e9parations d'appareils \u00e9lectrom\u00e9nagers. Electrom\u00e9nager, t\u00e9l\u00e9",
    "sg:phone":"+32 71 65 53 83",
    "sg:postcode":"5651",
    "sg:province":"Namur",
    "wof:name":"Jean-fran\u00c7ois Labruyere",
    "wof:placetype":"venue"
},
  "geometry": {"coordinates":[4.4944429398,50.2783050537],"type":"Point"}
}