{
  "type": "Feature",
  "properties": {
    "addr:full":"Turnhoutsebaan 5a Schilde Antwerpen 2970",
    "addr:housenumber":"5a",
    "addr:postcode":"2970",
    "addr:street":"Turnhoutsebaan",
    "iso:country":"BE",
    "sg:address":"Turnhoutsebaan 5a",
    "sg:city":"Schilde",
    "sg:classifiers":[
        {
            "category":"Restaurant",
            "type":"Food & Drink"
        }
    ],
    "sg:phone":"+32 3 353 02 17",
    "sg:postcode":"2970",
    "sg:province":"Antwerpen",
    "wof:name":"Hoeve De Zevenster",
    "wof:placetype":"venue"
},
  "geometry": {"coordinates":[4.5546140671,51.2321624756],"type":"Point"}
}