{
  "type": "Feature",
  "properties": {
    "addr:full":"Avenue Fran\u00c7ois Villon 44 Evere/evere Bruxelles-Capitale 1140",
    "addr:housenumber":"44",
    "addr:postcode":"1140",
    "addr:street":"Avenue Franc\u0327Ois Villon",
    "iso:country":"BE",
    "sg:address":"Avenue Fran\u00c7ois Villon 44",
    "sg:city":"Evere/evere",
    "sg:classifiers":[
        {
            "category":"Arena",
            "subcategory":"Sports Club",
            "type":"Entertainment"
        }
    ],
    "sg:phone":"+32 2 726 69 82",
    "sg:postcode":"1140",
    "sg:province":"Bruxelles-Capitale",
    "sg:tags":[
        "de"
    ],
    "wof:name":"Green-life Evere T.c.",
    "wof:placetype":"venue"
},
  "geometry": {"coordinates":[4.4245038033,50.8622817993],"type":"Point"}
}