{
  "type": "Feature",
  "properties": {
    "addr:full":"Rue Des Eperonniers 31 Bruxelles Bruxelles-Capitale 1000",
    "addr:housenumber":"31",
    "addr:postcode":"1000",
    "addr:street":"Rue Des Eperonniers",
    "iso:country":"BE",
    "sg:address":"Rue Des Eperonniers 31",
    "sg:city":"Bruxelles",
    "sg:classifiers":[
        {
            "category":"Shopping",
            "subcategory":"Clothing, Apparel, & Fashions",
            "type":"Retail Goods"
        }
    ],
    "sg:phone":"+32 2 502 69 41",
    "sg:postcode":"1000",
    "sg:province":"Bruxelles-Capitale",
    "sg:tags":[
        "boutique"
    ],
    "wof:name":"Hardrock Market",
    "wof:placetype":"venue"
},
  "geometry": {"coordinates":[4.353705883,50.8456611633],"type":"Point"}
}