{
  "type": "Feature",
  "properties": {
    "addr:full":"Avenue Des Cerisiers 132 Bruxelles (woluwe-saint-lambert) Bruxelles-Capitale 1200",
    "addr:housenumber":"132",
    "addr:postcode":"1200",
    "addr:street":"Avenue Des Cerisiers",
    "iso:country":"BE",
    "sg:address":"Avenue Des Cerisiers 132",
    "sg:city":"Bruxelles (woluwe-saint-lambert)",
    "sg:classifiers":[
        {
            "category":"Exhibition Hall",
            "type":"Public Place"
        }
    ],
    "sg:phone":"+32 2 736 24 16",
    "sg:postcode":"1200",
    "sg:province":"Bruxelles-Capitale",
    "sg:tags":[
        "stand"
    ],
    "wof:name":"Stadeco Sa",
    "wof:placetype":"venue"
},
  "geometry": {"coordinates":[4.4119582176,50.8471183777],"type":"Point"}
}