{
  "type": "Feature",
  "properties": {
    "iso:country":"BE",
    "sg:address":"Kortrijkstraat 25",
    "sg:city":"Tielt",
    "sg:orig_category":"Parfumeries",
    "sg:phone":"+32 51 40 86 36",
    "sg:postcode":"8700",
    "sg:province":"West-Vlaanderen",
    "wof:name":"Faubourg St.honor\u00c9",
    "wof:placetype":"venue"
},
  "geometry": {"coordinates":[3.3265841007,50.9988861084],"type":"Point"}
}