{
  "type": "Feature",
  "properties": {
    "addr:full":"Rue Sous Le Ch\u00c2teau 118 Huy Li\u00e8ge 4500",
    "addr:housenumber":"118",
    "addr:postcode":"4500",
    "addr:street":"Rue Sous Le Cha\u0302Teau",
    "iso:country":"BE",
    "sg:address":"Rue Sous Le Ch\u00c2teau 118",
    "sg:city":"Huy",
    "sg:orig_category":"Dakwerken Elektrische installaties voor woningen Loodgieterij, verwarming and sanitaire installaties",
    "sg:phone":"+32 85 61 38 11",
    "sg:postcode":"4500",
    "sg:province":"Li\u00e8ge",
    "wof:name":"Terly & Cie",
    "wof:placetype":"venue"
},
  "geometry": {"coordinates":[5.2369818687,50.5151062012],"type":"Point"}
}