{
  "type": "Feature",
  "properties": {
    "iso:country":"BE",
    "sg:address":"Rue Basse-wez 47",
    "sg:city":"Li\u00c8ge",
    "sg:orig_category":"Slagers Voedingsspeciaalzaken",
    "sg:phone":"+32 4 343 28 57",
    "sg:postcode":"4020",
    "sg:province":"Li\u00e8ge",
    "wof:name":"Lallemand Schlosser",
    "wof:placetype":"venue"
},
  "geometry": {"coordinates":[5.5878281593,50.6370162964],"type":"Point"}
}