{
  "type": "Feature",
  "properties": {
    "iso:country":"BE",
    "sg:address":"Rivage De Boubier 25",
    "sg:city":"Chatelet",
    "sg:orig_category":"Afval and schroot Gh Huisvuilophaling and -verwerking",
    "sg:phone":"+32 71 39 39 90",
    "sg:postcode":"6200",
    "sg:province":"Hainaut",
    "wof:name":"Recymet",
    "wof:placetype":"venue"
},
  "geometry": {"coordinates":[4.512720108,50.4036216736],"type":"Point"}
}