{
  "type": "Feature",
  "properties": {
    "addr:full":"Gasthuisstraat 61 Aarschot Vlaams-Brabant 3200",
    "addr:housenumber":"61",
    "addr:postcode":"3200",
    "addr:street":"Gasthuisstraat",
    "iso:country":"BE",
    "sg:address":"Gasthuisstraat 61",
    "sg:city":"Aarschot",
    "sg:orig_category":"Herstellingswinkels voor diverse persoonlijke and huishoudartikelen",
    "sg:phone":"+32 16 56 18 98",
    "sg:postcode":"3200",
    "sg:province":"Vlaams-Brabant",
    "wof:name":"Chr Vanden Eynde",
    "wof:placetype":"venue"
},
  "geometry": {"coordinates":[4.84025383,50.9882202148],"type":"Point"}
}