{
  "type": "Feature",
  "properties": {
    "addr:full":"Rue De La Station 31 Havelange Namur 5370",
    "addr:housenumber":"31",
    "addr:postcode":"5370",
    "addr:street":"Rue De La Station",
    "iso:country":"BE",
    "sg:address":"Rue De La Station 31",
    "sg:city":"Havelange",
    "sg:orig_category":"Banken and kredietinstellingen",
    "sg:phone":"+32 83 63 68 80",
    "sg:postcode":"5370",
    "sg:province":"Namur",
    "wof:name":"Fortis",
    "wof:placetype":"venue"
},
  "geometry": {"coordinates":[5.2398920059,50.3886070251],"type":"Point"}
}