{
  "type": "Feature",
  "properties": {
    "addr:full":"Rue De La Justice 142 Chatelet Hainaut 6200",
    "addr:housenumber":"142",
    "addr:postcode":"chatelet;6200",
    "addr:street":"Rue De La Justice",
    "iso:country":"BE",
    "sg:address":"Rue De La Justice 142",
    "sg:city":"Chatelet",
    "sg:orig_category":"Eleveurs de bovins",
    "sg:phone":"+32 71 38 47 35",
    "sg:postcode":"6200",
    "sg:province":"Hainaut",
    "wof:name":"Emile George",
    "wof:placetype":"venue"
},
  "geometry": {"coordinates":[4.5381221771,50.3961524963],"type":"Point"}
}