{
  "type": "Feature",
  "properties": {
    "addr:full":"Fabriekstraat 136 Sint-pieters-leeuw Vlaams-Brabant 1601",
    "addr:housenumber":"136",
    "addr:postcode":"1601",
    "addr:street":"Fabriekstraat",
    "iso:country":"BE",
    "sg:address":"Fabriekstraat 136",
    "sg:city":"Sint-pieters-leeuw",
    "sg:orig_category":"Banken and kredietinstellingen",
    "sg:phone":"+32 2 331 09 80",
    "sg:postcode":"1601",
    "sg:province":"Vlaams-Brabant",
    "wof:name":"Fortis",
    "wof:placetype":"venue"
},
  "geometry": {"coordinates":[4.2924408913,50.7840423584],"type":"Point"}
}