{
  "type": "Feature",
  "properties": {
    "addr:full":"Wijnegemsesteenweg 72b2 Schilde Antwerpen 2970",
    "addr:housenumber":"72b2",
    "addr:postcode":"2970",
    "addr:street":"Wijnegemsesteenweg",
    "iso:country":"BE",
    "sg:address":"Wijnegemsesteenweg 72b2",
    "sg:city":"Schilde",
    "sg:orig_category":"Boissons",
    "sg:phone":"+32 495 53 18 00",
    "sg:postcode":"2970",
    "sg:province":"Antwerpen",
    "wof:name":"Ferdi Tyteca & Co",
    "wof:placetype":"venue"
},
  "geometry": {"coordinates":[4.5798120499,51.2392082214],"type":"Point"}
}