{
  "type": "Feature",
  "properties": {
    "addr:full":"Rue De La Source 41 Bruxelles (saint-gilles) Bruxelles-Capitale 1060",
    "addr:housenumber":"41",
    "addr:postcode":"1060",
    "addr:street":"Rue De La Source",
    "iso:country":"BE",
    "sg:address":"Rue De La Source 41",
    "sg:city":"Bruxelles (saint-gilles)",
    "sg:classifiers":[
        {
            "category":"Professional",
            "subcategory":"Testing Lab",
            "type":"Services"
        }
    ],
    "sg:phone":"+32 2 538 20 16",
    "sg:postcode":"1060",
    "sg:province":"Bruxelles-Capitale",
    "sg:tags":[
        "chemist"
    ],
    "wof:name":"Pharmacie De La Source",
    "wof:placetype":"venue"
},
  "geometry": {"coordinates":[4.3514428139,50.831363678],"type":"Point"}
}