{
  "type": "Feature",
  "properties": {
    "iso:country":"BE",
    "sg:address":"Boulevard Du Roi Albert 44",
    "sg:city":"Tournai",
    "sg:classifiers":[
        {
            "category":"Retail",
            "subcategory":"Repair Shop",
            "type":"Services"
        }
    ],
    "sg:phone":"+32 69 22 18 47",
    "sg:postcode":"7500",
    "sg:province":"Hainaut",
    "sg:tags":[
        "denture"
    ],
    "wof:name":"I.d.t.",
    "wof:placetype":"venue"
},
  "geometry": {"coordinates":[3.3955199718,50.6005897522],"type":"Point"}
}