{
  "type": "Feature",
  "properties": {
    "iso:country":"BE",
    "sg:address":"Heldenlaan 71",
    "sg:city":"Zottegem",
    "sg:classifiers":[
        {
            "category":"Home & Garden",
            "subcategory":"Kitchen Supply",
            "type":"Retail Goods"
        }
    ],
    "sg:phone":"+32 9 360 23 34",
    "sg:postcode":"9620",
    "sg:province":"Oost-Vlaanderen",
    "sg:tags":[
        "installation"
    ],
    "wof:name":"D Line Interiors Rouquart",
    "wof:placetype":"venue"
},
  "geometry": {"coordinates":[3.8100891113,50.8717498779],"type":"Point"}
}