{
  "type": "Feature",
  "properties": {
    "addr:full":"Nijverheidstraat 5 Machelen Vlaams-Brabant 1830",
    "addr:housenumber":"5",
    "addr:postcode":"1830",
    "addr:street":"Nijverheidstraat",
    "iso:country":"BE",
    "sg:address":"Nijverheidstraat 5",
    "sg:city":"Machelen",
    "sg:orig_category":"Verhuur bouwmachines",
    "sg:phone":"+32 2 649 20 57",
    "sg:postcode":"1830",
    "sg:province":"Vlaams-Brabant",
    "wof:name":"Materdak",
    "wof:placetype":"venue"
},
  "geometry": {"coordinates":[4.4265170097,50.9146652222],"type":"Point"}
}