{
  "type": "Feature",
  "properties": {
    "iso:country":"BE",
    "sg:address":"Chauss\u00c9e De Courtrai 2",
    "sg:city":"Tournai",
    "sg:classifiers":[
        {
            "category":"Cafe",
            "type":"Food & Drink"
        }
    ],
    "sg:phone":"+32 69 21 46 19",
    "sg:postcode":"7503",
    "sg:province":"Hainaut",
    "sg:tags":[
        "caf\u00e9s"
    ],
    "wof:name":"Caf\u00c9 Au Pont Royal",
    "wof:placetype":"venue"
},
  "geometry": {"coordinates":[3.3692340851,50.6208152771],"type":"Point"}
}