{
  "type": "Feature",
  "properties": {
    "addr:full":"Waterstraat 46-1 Bilzen (munsterbilzen) Limburg 3740",
    "addr:housenumber":"46-1",
    "addr:postcode":"3740",
    "addr:street":"Waterstraat",
    "iso:country":"BE",
    "sg:address":"Waterstraat 46-1",
    "sg:city":"Bilzen (munsterbilzen)",
    "sg:classifiers":[
        {
            "category":"Health Services",
            "subcategory":"Health Practitioner",
            "type":"Services"
        }
    ],
    "sg:phone":"+32 89 61 59 39",
    "sg:postcode":"3740",
    "sg:province":"Limburg",
    "sg:tags":[
        "physiotherapist"
    ],
    "wof:name":"Vanroy Kim",
    "wof:placetype":"venue"
},
  "geometry": {"coordinates":[5.5248150826,50.8956718445],"type":"Point"}
}