{
  "type": "Feature",
  "properties": {
    "addr:full":"Otegemstraat 1 Zwevegem West-Vlaanderen 8550",
    "addr:housenumber":"1",
    "addr:postcode":"8550",
    "addr:street":"Otegemstraat",
    "iso:country":"BE",
    "sg:address":"Otegemstraat 1",
    "sg:city":"Zwevegem",
    "sg:orig_category":"R\u00e9parations d'horloges, montres and bijoux. Bijouteries and horlogeries",
    "sg:phone":"+32 56 75 57 64",
    "sg:postcode":"8550",
    "sg:province":"West-Vlaanderen",
    "wof:name":"Huis Vaes",
    "wof:placetype":"venue"
},
  "geometry": {"coordinates":[3.3345110416,50.8130531311],"type":"Point"}
}