{
  "type": "Feature",
  "properties": {
    "addr:full":"Biermanstraat 1a Tielt (schuiferskapelle) West-Vlaanderen 8700",
    "addr:housenumber":"1a",
    "addr:postcode":"8700",
    "addr:street":"Biermanstraat",
    "iso:country":"BE",
    "sg:address":"Biermanstraat 1a",
    "sg:city":"Tielt (schuiferskapelle)",
    "sg:classifiers":[
        {
            "category":"Farming",
            "subcategory":"Livestock Farm",
            "type":"Manufacturing & Wholesale Goods"
        }
    ],
    "sg:phone":"+32 51 40 05 25",
    "sg:postcode":"8700",
    "sg:province":"West-Vlaanderen",
    "sg:tags":[
        "buyer"
    ],
    "wof:name":"Vermeire U",
    "wof:placetype":"venue"
},
  "geometry": {"coordinates":[3.334758997,51.0326004028],"type":"Point"}
}