{
  "type": "Feature",
  "properties": {
    "addr:full":"Brugdreef 13 Destelbergen (heusden) Oost-Vlaanderen 9070",
    "addr:housenumber":"13",
    "addr:postcode":"9070",
    "addr:street":"Brugdreef",
    "iso:country":"BE",
    "sg:address":"Brugdreef 13",
    "sg:city":"Destelbergen (heusden)",
    "sg:classifiers":[
        {
            "category":"Health Services",
            "subcategory":"Health Practitioner",
            "type":"Services"
        }
    ],
    "sg:phone":"+32 9 230 91 29",
    "sg:postcode":"9070",
    "sg:province":"Oost-Vlaanderen",
    "sg:tags":[
        "physiotherapist"
    ],
    "wof:name":"Vercruyssen",
    "wof:placetype":"venue"
},
  "geometry": {"coordinates":[3.79874897,51.0261802673],"type":"Point"}
}