{
  "type": "Feature",
  "properties": {
    "iso:country":"BE",
    "sg:address":"Gulden-sporenstraat 40",
    "sg:city":"Harelbeke",
    "sg:orig_category":"Diverse opleidingen and onderwijs",
    "sg:phone":"+32 56 72 59 55",
    "sg:postcode":"8530",
    "sg:province":"West-Vlaanderen",
    "wof:name":"Luc Chanteloup",
    "wof:placetype":"venue"
},
  "geometry": {"coordinates":[3.307363987,50.8469543457],"type":"Point"}
}