{
  "type": "Feature",
  "properties": {
    "iso:country":"BE",
    "sg:address":"Tamme Kastanjebomenlaan 7",
    "sg:city":"Moeskroen/mouscron",
    "sg:orig_category":"Installatie van houten of kunststof schrijnwerk MEUBELONTWERP AND -INSTALLATIE",
    "sg:phone":"+32 56 48 72 06",
    "sg:postcode":"7711",
    "sg:province":"Hainaut",
    "wof:name":"Claude Van Den Berghe",
    "wof:placetype":"venue"
},
  "geometry": {"coordinates":[3.2670669556,50.736907959],"type":"Point"}
}