{
  "type": "Feature",
  "properties": {
    "addr:full":"Antwerpsestraat 185 Mortsel Antwerpen 2640",
    "addr:housenumber":"185",
    "addr:postcode":"2640",
    "addr:street":"Antwerpsestraat",
    "iso:country":"BE",
    "sg:address":"Antwerpsestraat 185",
    "sg:city":"Mortsel",
    "sg:orig_category":"Biens d'occasion",
    "sg:phone":"+32 3 449 15 60",
    "sg:postcode":"2640",
    "sg:province":"Antwerpen",
    "wof:name":"Huis Woefke",
    "wof:placetype":"venue"
},
  "geometry": {"coordinates":[4.439260006,51.1748428345],"type":"Point"}
}