{
  "type": "Feature",
  "properties": {
    "iso:country":"BE",
    "sg:address":"Avenue Jacques Brel 18",
    "sg:city":"Soignies",
    "sg:orig_category":"Afbraak- and draineerwerken",
    "sg:phone":"+32 67 33 42 40",
    "sg:postcode":"7060",
    "sg:province":"Hainaut",
    "wof:name":"Ryckaert",
    "wof:placetype":"venue"
},
  "geometry": {"coordinates":[4.0590882301,50.5873947144],"type":"Point"}
}