{
  "type": "Feature",
  "properties": {
    "iso:country":"BE",
    "sg:address":"Vogelkerslaan 20",
    "sg:city":"Kapellen",
    "sg:orig_category":"Production de films, t\u00e9l\u00e9films and vid\u00e9os",
    "sg:phone":"+32 3 666 52 13",
    "sg:postcode":"2950",
    "sg:province":"Antwerpen",
    "wof:name":"York Dynamics",
    "wof:placetype":"venue"
},
  "geometry": {"coordinates":[4.4489068985,51.3530082703],"type":"Point"}
}