{
  "type": "Feature",
  "properties": {
    "iso:country":"BE",
    "sg:address":"Boerenkrijgplaats 6",
    "sg:city":"Alken",
    "sg:orig_category":"Dansscholen",
    "sg:phone":"+32 11 31 14 68",
    "sg:postcode":"3570",
    "sg:province":"Limburg",
    "wof:name":"Dansclub Isadora",
    "wof:placetype":"venue"
},
  "geometry": {"coordinates":[5.2754969597,50.9012641907],"type":"Point"}
}