{
  "type": "Feature",
  "properties": {
    "addr:full":"Wakkensesteenweg 85a Dentergem West-Vlaanderen 8720",
    "addr:housenumber":"85a",
    "addr:postcode":"8720",
    "addr:street":"Wakkensesteenweg",
    "iso:country":"BE",
    "sg:address":"Wakkensesteenweg 85a",
    "sg:city":"Dentergem",
    "sg:orig_category":"Tuinen",
    "sg:phone":"+32 9 388 41 56",
    "sg:postcode":"8720",
    "sg:province":"West-Vlaanderen",
    "wof:name":"Tuinen Vanhaverbeke Koen",
    "wof:placetype":"venue"
},
  "geometry": {"coordinates":[3.4292290211,50.9336776733],"type":"Point"}
}