{
  "type": "Feature",
  "properties": {
    "addr:full":"Avenue Alexandre Fleming 1 Louvain-la-neuve Brabant Wallon 1348",
    "addr:housenumber":"1",
    "addr:postcode":"1348",
    "addr:street":"Avenue Alexandre Fleming",
    "iso:country":"BE",
    "sg:address":"Avenue Alexandre Fleming 1",
    "sg:city":"Louvain-la-neuve",
    "sg:classifiers":[
        {
            "category":"Train Station",
            "subcategory":"Rail",
            "type":"Transportation"
        }
    ],
    "sg:phone":"+32 10 47 01 47",
    "sg:postcode":"1348",
    "sg:province":"Brabant Wallon",
    "sg:tags":[
        "acid-proof",
        "stainless",
        "steel",
        "flange"
    ],
    "wof:name":"Somco S.a.",
    "wof:placetype":"venue"
},
  "geometry": {"coordinates":[4.6372771263,50.6632728577],"type":"Point"}
}