{
  "type": "Feature",
  "properties": {
    "addr:full":"Rue Des Viaducs 304 Mons Hainaut 7020",
    "addr:housenumber":"304",
    "addr:postcode":"7020",
    "addr:street":"Rue Des Viaducs;Hainaut",
    "iso:country":"BE",
    "sg:address":"Rue Des Viaducs 304",
    "sg:city":"Mons",
    "sg:orig_category":"Artsen and specialisten",
    "sg:phone":"+32 65 35 35 85",
    "sg:postcode":"7020",
    "sg:province":"Hainaut",
    "wof:name":"F. Nuthals",
    "wof:placetype":"venue"
},
  "geometry": {"coordinates":[3.9553449154,50.4761772156],"type":"Point"}
}