{
  "type": "Feature",
  "properties": {
    "iso:country":"BE",
    "sg:address":"Bredabaan 93bb",
    "sg:city":"Wuustwezel",
    "sg:orig_category":"Woningbouw",
    "sg:phone":"+32 3 669 84 72",
    "sg:postcode":"2990",
    "sg:province":"Antwerpen",
    "wof:name":"Matheeussen",
    "wof:placetype":"venue"
},
  "geometry": {"coordinates":[4.6180868149,51.4175949097],"type":"Point"}
}