{
  "type": "Feature",
  "properties": {
    "addr:full":"Groenstraat 7 Zoutleeuw Vlaams-Brabant 3440",
    "addr:housenumber":"7",
    "addr:postcode":"3440",
    "addr:street":"Groenstraat;Vlaams-Brabant",
    "iso:country":"BE",
    "sg:address":"Groenstraat 7",
    "sg:city":"Zoutleeuw",
    "sg:orig_category":"Banken and kredietinstellingen",
    "sg:phone":"+32 11 58 60 00",
    "sg:postcode":"3440",
    "sg:province":"Vlaams-Brabant",
    "wof:name":"Groep Argenta",
    "wof:placetype":"venue"
},
  "geometry": {"coordinates":[5.0976548195,50.8659629822],"type":"Point"}
}