{
  "type": "Feature",
  "properties": {
    "addr:full":"Avenue Albert I 6 Paliseul (maissin) Luxembourg 6852",
    "addr:housenumber":"6",
    "addr:postcode":"6852",
    "addr:street":"Avenue Albert I",
    "iso:country":"BE",
    "sg:address":"Avenue Albert I 6",
    "sg:city":"Paliseul (maissin)",
    "sg:classifiers":[
        {
            "category":"Education",
            "subcategory":"School",
            "type":"Public Place"
        }
    ],
    "sg:phone":"+32 61 65 53 32",
    "sg:postcode":"6852",
    "sg:province":"Luxembourg",
    "sg:tags":[
        "primary"
    ],
    "wof:name":"Ecole Communale Maissin",
    "wof:placetype":"venue"
},
  "geometry": {"coordinates":[5.180284977,49.9653739929],"type":"Point"}
}