{
  "type": "Feature",
  "properties": {
    "addr:full":"Rue Campinaire 61 Aiseau-presles Hainaut 6250",
    "addr:housenumber":"61",
    "addr:postcode":"6250",
    "addr:street":"Rue Campinaire;Hainaut",
    "iso:country":"BE",
    "sg:address":"Rue Campinaire 61",
    "sg:city":"Aiseau-presles",
    "sg:orig_category":"Quincailleries. Combustibles",
    "sg:phone":"+32 71 39 16 04",
    "sg:postcode":"6250",
    "sg:province":"Hainaut",
    "wof:name":"Fe. Fersini",
    "wof:placetype":"venue"
},
  "geometry": {"coordinates":[4.5463199615,50.4170761108],"type":"Point"}
}