{
  "type": "Feature",
  "properties": {
    "iso:country":"BE",
    "sg:address":"Boulevard Lalaing 35",
    "sg:city":"Tournai",
    "sg:classifiers":[
        {
            "category":"Health Services",
            "subcategory":"Health Practitioner",
            "type":"Services"
        }
    ],
    "sg:phone":"+32 69 22 86 88",
    "sg:postcode":"7500",
    "sg:province":"Hainaut",
    "sg:tags":[
        "physiotherapist"
    ],
    "wof:name":"Delcourt Brigitte",
    "wof:placetype":"venue"
},
  "geometry": {"coordinates":[3.3856160641,50.6007537842],"type":"Point"}
}