{
  "type": "Feature",
  "properties": {
    "iso:country":"BE",
    "sg:address":"Aalbeeksesteenweg 21a",
    "sg:city":"Kortrijk",
    "sg:orig_category":"Non-Classified Establishments",
    "sg:phone":"+32 56 21 24 10",
    "sg:postcode":"8500",
    "sg:province":"West-Vlaanderen",
    "wof:name":"De Clerck Pol Bvba",
    "wof:placetype":"venue"
},
  "geometry": {"coordinates":[3.2584109306,50.8210525513],"type":"Point"}
}