{
  "type": "Feature",
  "properties": {
    "iso:country":"BE",
    "sg:address":"Rue Des Brasseurs 95",
    "sg:city":"Tournai",
    "sg:classifiers":[
        {
            "category":"Professional",
            "subcategory":"Art Services",
            "type":"Services"
        }
    ],
    "sg:phone":"+32 69 22 92 10",
    "sg:postcode":"7500",
    "sg:province":"Hainaut",
    "sg:tags":[
        "photographer"
    ],
    "wof:name":"Labo Robb Sprl",
    "wof:placetype":"venue"
},
  "geometry": {"coordinates":[3.3990709782,50.6186676025],"type":"Point"}
}