{
  "type": "Feature",
  "properties": {
    "addr:full":"Kerkplein 9 Lanaken Limburg 3620",
    "addr:housenumber":"9",
    "addr:postcode":"3620",
    "addr:street":"Kerkplein",
    "iso:country":"BE",
    "sg:address":"Kerkplein 9",
    "sg:city":"Lanaken",
    "sg:orig_category":"Pharmaciens",
    "sg:phone":"+32 89 73 14 45",
    "sg:postcode":"3620",
    "sg:province":"Limburg",
    "wof:name":"Volksapotheek Paulissen",
    "wof:placetype":"venue"
},
  "geometry": {"coordinates":[5.6334290504,50.8637123108],"type":"Point"}
}