{
  "type": "Feature",
  "properties": {
    "iso:country":"BE",
    "sg:address":"Maison Blanche 145a",
    "sg:city":"Fourons (mouland)",
    "sg:classifiers":[
        {
            "category":"Personal",
            "subcategory":"Beauty Salon",
            "type":"Services"
        }
    ],
    "sg:phone":"+32 4 381 05 51",
    "sg:postcode":"3790",
    "sg:province":"Limburg",
    "sg:tags":[
        "lady",
        "-",
        "hairdressing"
    ],
    "wof:name":"Nadine Coiffure",
    "wof:placetype":"venue"
},
  "geometry": {"coordinates":[5.721350193,50.763999939],"type":"Point"}
}