{
  "type": "Feature",
  "properties": {
    "iso:country":"BE",
    "sg:address":"Ambacht. Zone Balendijk 2220",
    "sg:city":"Lommel",
    "sg:orig_category":"Diverse bouwinstallaties Reclamebureaus Verlichting and huishoudartikelen Verlichtingsapparaten and ",
    "sg:phone":"+32 11 54 04 07",
    "sg:postcode":"3920",
    "sg:province":"Limburg",
    "wof:name":"Publi Joni",
    "wof:placetype":"venue"
},
  "geometry": {"coordinates":[5.2645001411,51.2141990662],"type":"Point"}
}