{
  "type": "Feature",
  "properties": {
    "addr:full":"Rue Du Tienne 31 Hamois (natoye) Namur 5360",
    "addr:housenumber":"31",
    "addr:postcode":"5360",
    "addr:street":"Rue Du Tienne",
    "iso:country":"BE",
    "sg:address":"Rue Du Tienne 31",
    "sg:city":"Hamois (natoye)",
    "sg:classifiers":[
        {
            "category":"Health Services",
            "subcategory":"Health Practitioner",
            "type":"Services"
        }
    ],
    "sg:phone":"+32 81 58 24 08",
    "sg:postcode":"5360",
    "sg:province":"Namur",
    "sg:tags":[
        "therapist",
        "speech"
    ],
    "wof:name":"Verbaert I",
    "wof:placetype":"venue"
},
  "geometry": {"coordinates":[5.0616998672,50.3443984985],"type":"Point"}
}