{
  "type": "Feature",
  "properties": {
    "addr:full":"Boulevard Du Souverain 144 Bruxelles (auderghem) Bruxelles-Capitale 1160",
    "addr:housenumber":"144",
    "addr:postcode":"1160",
    "addr:street":"Boulevard Du Souverain",
    "iso:country":"BE",
    "sg:address":"Boulevard Du Souverain 144",
    "sg:city":"Bruxelles (auderghem)",
    "sg:classifiers":[
        {
            "category":"Professional",
            "subcategory":"Art Services",
            "type":"Services"
        }
    ],
    "sg:phone":"+32 2 672 97 46",
    "sg:postcode":"1160",
    "sg:province":"Bruxelles-Capitale",
    "sg:tags":[
        "-",
        "painter",
        "artist"
    ],
    "wof:name":"Thomas G",
    "wof:placetype":"venue"
},
  "geometry": {"coordinates":[4.4267568588,50.8105506897],"type":"Point"}
}