{
  "type": "Feature",
  "properties": {
    "iso:country":"BE",
    "sg:address":"Rue D'houdeng 207",
    "sg:city":"Le Roeulx",
    "sg:orig_category":"Location de v\u00eatements, chaussures and textiles",
    "sg:phone":"+32 64 67 51 10",
    "sg:postcode":"7070",
    "sg:province":"Hainaut",
    "wof:name":"Festival Center",
    "wof:placetype":"venue"
},
  "geometry": {"coordinates":[4.1264691353,50.4972686768],"type":"Point"}
}