{
  "type": "Feature",
  "properties": {
    "iso:country":"BE",
    "sg:address":"Rue Du M\u00c9ridien 68",
    "sg:city":"Sint-joost-ten-node/saint-joss",
    "sg:classifiers":[
        {
            "category":"Recreation",
            "type":"Entertainment"
        }
    ],
    "sg:phone":"+32 2 209 63 90",
    "sg:postcode":"1210",
    "sg:province":"Bruxelles-Capitale",
    "sg:tags":[
        "diver",
        "amusement"
    ],
    "wof:name":"R\u00c9seaux D'echange De Savoir",
    "wof:placetype":"venue"
},
  "geometry": {"coordinates":[4.3690748215,50.8552742004],"type":"Point"}
}