{
  "type": "Feature",
  "properties": {
    "addr:full":"Avenue Charle-albert 12 Watermaal-bosvoorde/watermael-boitsfort Bruxelles-Capitale 1170",
    "addr:housenumber":"12",
    "addr:postcode":"1170",
    "addr:street":"Avenue Charle-Albert",
    "iso:country":"BE",
    "sg:address":"Avenue Charle-albert 12",
    "sg:city":"Watermaal-bosvoorde/watermael-boitsfort",
    "sg:orig_category":"Artistes ind\u00e9pendants",
    "sg:phone":"+32 2 660 60 74",
    "sg:postcode":"1170",
    "sg:province":"Bruxelles-Capitale",
    "wof:name":"Fran\u00c7ois Torres",
    "wof:placetype":"venue"
},
  "geometry": {"coordinates":[4.4309391975,50.8019218445],"type":"Point"}
}