{
  "type": "Feature",
  "properties": {
    "addr:full":"Demerstraat 89 Hasselt Limburg 3500",
    "addr:housenumber":"89",
    "addr:postcode":"3500",
    "addr:street":"Demerstraat",
    "iso:country":"BE",
    "sg:address":"Demerstraat 89",
    "sg:city":"Hasselt",
    "sg:classifiers":[
        {
            "category":"Restaurant",
            "type":"Food & Drink"
        }
    ],
    "sg:phone":"+32 11 22 71 71",
    "sg:postcode":"3500",
    "sg:province":"Limburg",
    "sg:tags":[
        "caf\u00e9s"
    ],
    "wof:name":"Taverne De Hertog",
    "wof:placetype":"venue"
},
  "geometry": {"coordinates":[5.3390598297,50.9331665039],"type":"Point"}
}