{
  "type": "Feature",
  "properties": {
    "iso:country":"BE",
    "sg:address":"Kloosterstraat 7",
    "sg:city":"Antwerpen",
    "sg:orig_category":"Reisbureaus",
    "sg:phone":"+32 3 541 86 74",
    "sg:postcode":"2180",
    "sg:province":"Antwerpen",
    "wof:name":"M.j. Reizen",
    "wof:placetype":"venue"
},
  "geometry": {"coordinates":[4.3958101273,51.2170944214],"type":"Point"}
}