{
  "type": "Feature",
  "properties": {
    "addr:full":"Rue De Manaihant 30-32 Petit-rechain Li\u00e8ge 4800",
    "addr:housenumber":"30-32",
    "addr:postcode":"4800",
    "addr:street":"Rue De Manaihant",
    "iso:country":"BE",
    "sg:address":"Rue De Manaihant 30-32",
    "sg:city":"Petit-rechain",
    "sg:classifiers":[
        {
            "category":"Manufacturing",
            "subcategory":"Rubber & Plastics",
            "type":"Manufacturing & Wholesale Goods"
        }
    ],
    "sg:phone":"+32 87 67 50 50",
    "sg:postcode":"4800",
    "sg:province":"Li\u00e8ge",
    "sg:tags":[
        "profile"
    ],
    "wof:name":"Durechain S.p.r.l.",
    "wof:placetype":"venue"
},
  "geometry": {"coordinates":[5.823387146,50.6231994629],"type":"Point"}
}