{
  "type": "Feature",
  "properties": {
    "addr:full":"Rue Du Xiii Ao\u00dbt 50 Chaudfontaine Li\u00e8ge 4050",
    "addr:housenumber":"50",
    "addr:postcode":"4050",
    "addr:street":"Rue Du Xiii Aou\u0302T",
    "iso:country":"BE",
    "sg:address":"Rue Du Xiii Ao\u00dbt 50",
    "sg:city":"Chaudfontaine",
    "sg:orig_category":"M\u00e9decins and sp\u00e9cialistes",
    "sg:phone":"+32 4 365 12 45",
    "sg:postcode":"4050",
    "sg:province":"Li\u00e8ge",
    "wof:name":"Ren\u00c9 Lambotte",
    "wof:placetype":"venue"
},
  "geometry": {"coordinates":[5.642947197,50.5926780701],"type":"Point"}
}