{
  "type": "Feature",
  "properties": {
    "iso:country":"BE",
    "sg:address":"Jules Maloulaan 51",
    "sg:city":"Etterbeek/etterbeek",
    "sg:orig_category":"Plaatsen van vloer- and muurbekleding Schilders",
    "sg:phone":"+32 2 647 70 32",
    "sg:postcode":"1040",
    "sg:province":"Bruxelles-Capitale",
    "wof:name":"Antonio Trovato",
    "wof:placetype":"venue"
},
  "geometry": {"coordinates":[4.3856668472,50.8306236267],"type":"Point"}
}