{
  "type": "Feature",
  "properties": {
    "iso:country":"BE",
    "sg:address":"Chauss\u00e9e De Mons 509",
    "sg:city":"Bruxelles (anderlecht)",
    "sg:classifiers":[
        {
            "category":"Health Services",
            "subcategory":"Doctor",
            "type":"Services"
        }
    ],
    "sg:phone":"+32 2 569 72 29",
    "sg:postcode":"1070",
    "sg:province":"Bruxelles-Capitale",
    "sg:tags":[
        "medicinephysicians",
        "surgeon"
    ],
    "wof:name":"Doyen Jean-luc",
    "wof:placetype":"venue"
},
  "geometry": {"coordinates":[4.315887928,50.8351821899],"type":"Point"}
}