{
  "type": "Feature",
  "properties": {
    "iso:country":"BE",
    "sg:address":"Leemkuilstraat 117",
    "sg:city":"Alken",
    "sg:orig_category":"Travaux de pl\u00e2trage",
    "sg:phone":"+32 11 59 27 48",
    "sg:postcode":"3570",
    "sg:province":"Limburg",
    "wof:name":"Ludo Palmers",
    "wof:placetype":"venue"
},
  "geometry": {"coordinates":[5.3312358856,50.8702545166],"type":"Point"}
}