{
  "type": "Feature",
  "properties": {
    "iso:country":"BE",
    "sg:address":"Eric Sasselaan 75",
    "sg:city":"Antwerpen",
    "sg:orig_category":"Advocaten and juridische adviseurs",
    "sg:phone":"+32 3 257 15 15",
    "sg:postcode":"2020",
    "sg:province":"Antwerpen",
    "wof:name":"Peter Siebens",
    "wof:placetype":"venue"
},
  "geometry": {"coordinates":[4.3928699493,51.1939888],"type":"Point"}
}