{
  "type": "Feature",
  "properties": {
    "iso:country":"BE",
    "sg:address":"Haifastraat 5",
    "sg:city":"Antwerpen",
    "sg:orig_category":"Agences d'exp\u00e9dition",
    "sg:phone":"+32 3 776 10 01",
    "sg:postcode":"2030",
    "sg:province":"Antwerpen",
    "wof:name":"Lok H.",
    "wof:placetype":"venue"
},
  "geometry": {"coordinates":[10.2244195938,63.960269928],"type":"Point"}
}