{
  "type": "Feature",
  "properties": {
    "iso:country":"BE",
    "sg:address":"Rue Emile Landeut 23",
    "sg:city":"Orp-jauche",
    "sg:orig_category":"Afvalwaterverwerking and ontstoppingsdiensten Loodgieterij, verwarming and sanitaire installaties",
    "sg:phone":"+32 19 65 63 09",
    "sg:postcode":"1350",
    "sg:province":"Brabant Wallon",
    "wof:name":"Balon Freddy",
    "wof:placetype":"venue"
},
  "geometry": {"coordinates":[4.97920084,50.6738891602],"type":"Point"}
}