{
  "type": "Feature",
  "properties": {
    "addr:full":"Rue Des Ardennes 45 Cortil-wodon Namur 5380",
    "addr:housenumber":"45",
    "addr:postcode":"5380",
    "addr:street":"Rue Des Ardennes",
    "iso:country":"BE",
    "sg:address":"Rue Des Ardennes 45",
    "sg:city":"Cortil-wodon",
    "sg:orig_category":"Herstellingen and onderhoud van auto's",
    "sg:phone":"+32 81 83 35 03",
    "sg:postcode":"5380",
    "sg:province":"Namur",
    "wof:name":"Carrosserie Depas",
    "wof:placetype":"venue"
},
  "geometry": {"coordinates":[4.9739170074,50.5797576904],"type":"Point"}
}