{
  "type": "Feature",
  "properties": {
    "addr:full":"Sint-servaasstraat 3 Hasselt Limburg 3500",
    "addr:housenumber":"3",
    "addr:postcode":"3500",
    "addr:street":"Sint-Servaasstraat",
    "iso:country":"BE",
    "sg:address":"Sint-servaasstraat 3",
    "sg:city":"Hasselt",
    "sg:orig_category":"Boekhouders",
    "sg:phone":"+32 11 28 56 50",
    "sg:postcode":"3500",
    "sg:province":"Limburg",
    "wof:name":"Stevens Patrick",
    "wof:placetype":"venue"
},
  "geometry": {"coordinates":[5.315887928,50.9294090271],"type":"Point"}
}