{
  "type": "Feature",
  "properties": {
    "iso:country":"BE",
    "sg:address":"Rue Saint-laurent 125",
    "sg:city":"Li\u00c8ge",
    "sg:orig_category":"Artsen and specialisten",
    "sg:phone":"+32 4 221 15 51",
    "sg:postcode":"4000",
    "sg:province":"Li\u00e8ge",
    "wof:name":"Philippe Olivier",
    "wof:placetype":"venue"
},
  "geometry": {"coordinates":[5.556994915,50.6391487122],"type":"Point"}
}