{
  "type": "Feature",
  "properties": {
    "addr:full":"Chauss\u00c9e D'ixelles 77 Elsene/ixelles Bruxelles-Capitale 1050",
    "addr:housenumber":"77",
    "addr:postcode":"1050",
    "addr:street":"Chausse\u0301E D'Ixelles",
    "iso:country":"BE",
    "sg:address":"Chauss\u00c9e D'ixelles 77",
    "sg:city":"Elsene/ixelles",
    "sg:orig_category":"Accessoires vestimentaires",
    "sg:phone":"+32 2 511 12 38",
    "sg:postcode":"1050",
    "sg:province":"Bruxelles-Capitale",
    "wof:name":"Maison Delvida",
    "wof:placetype":"venue"
},
  "geometry": {"coordinates":[4.3632421494,50.8357162476],"type":"Point"}
}