{
  "type": "Feature",
  "properties": {
    "iso:country":"BE",
    "sg:address":"Oude Kapellestraat 50",
    "sg:city":"Tielt",
    "sg:classifiers":[
        {
            "category":"Professional",
            "subcategory":"Engineering",
            "type":"Services"
        }
    ],
    "sg:phone":"+32 51 40 87 27",
    "sg:postcode":"8700",
    "sg:province":"West-Vlaanderen",
    "sg:tags":[
        "-"
    ],
    "wof:name":"A.i.s. Bvba",
    "wof:placetype":"venue"
},
  "geometry": {"coordinates":[3.3305280209,51.0068664551],"type":"Point"}
}