{
  "type": "Feature",
  "properties": {
    "iso:country":"BE",
    "sg:address":"Route De Marche 10",
    "sg:city":"Somme-leuze",
    "sg:orig_category":"Verlichting and huishoudartikelen",
    "sg:phone":"+32 84 31 30 56",
    "sg:postcode":"5377",
    "sg:province":"Namur",
    "wof:name":"Laloux Stores",
    "wof:placetype":"venue"
},
  "geometry": {"coordinates":[5.3648061752,50.3393745422],"type":"Point"}
}