{
  "type": "Feature",
  "properties": {
    "addr:full":"Hoornzeelstraat 33 Tervuren Vlaams-Brabant 3080",
    "addr:housenumber":"33",
    "addr:postcode":"3080",
    "addr:street":"Hoornzeelstraat",
    "iso:country":"BE",
    "sg:address":"Hoornzeelstraat 33",
    "sg:city":"Tervuren",
    "sg:classifiers":[
        {
            "category":"Retail",
            "subcategory":"Repair Shop",
            "type":"Services"
        }
    ],
    "sg:phone":"+32 2 767 41 75",
    "sg:postcode":"3080",
    "sg:province":"Vlaams-Brabant",
    "sg:tags":[
        "upholsterer"
    ],
    "wof:name":"Janssens Garnierders",
    "wof:placetype":"venue"
},
  "geometry": {"coordinates":[4.5128831863,50.8219680786],"type":"Point"}
}