{
  "type": "Feature",
  "properties": {
    "iso:country":"BE",
    "sg:address":"Steenweg Buda 50",
    "sg:city":"Machelen",
    "sg:classifiers":[
        {
            "category":"Social Services",
            "subcategory":"Job Training",
            "type":"Services"
        }
    ],
    "sg:phone":"+32 2 253 16 00",
    "sg:postcode":"1830",
    "sg:province":"Vlaams-Brabant",
    "sg:tags":[
        "barcode",
        "scanner",
        "printer"
    ],
    "wof:name":"Leuze Electronic Nv",
    "wof:placetype":"venue"
},
  "geometry": {"coordinates":[4.4266400337,50.9030418396],"type":"Point"}
}