{
  "type": "Feature",
  "properties": {
    "addr:full":"Leopold Ii-dam 0 Brugge West-Vlaanderen 8380",
    "addr:housenumber":"0",
    "addr:postcode":"8380",
    "iso:country":"BE",
    "sg:address":"Leopold Ii-dam 0",
    "sg:city":"Brugge",
    "sg:orig_category":"Agences d'exp\u00e9dition. Agences en douane",
    "sg:phone":"+32 50 55 07 19",
    "sg:postcode":"8380",
    "sg:province":"West-Vlaanderen",
    "wof:name":"Van Landeghem",
    "wof:placetype":"venue"
},
  "geometry": {"coordinates":[3.2288448811,51.2742958069],"type":"Point"}
}