{
  "type": "Feature",
  "properties": {
    "iso:country":"BE",
    "sg:address":"Rue De Goz\u00c9e 230",
    "sg:city":"Montigny-le-tilleul",
    "sg:classifiers":[
        {
            "category":"Insurance",
            "subcategory":"Life Insurance",
            "type":"Services"
        }
    ],
    "sg:phone":"+32 71 56 09 21",
    "sg:postcode":"6110",
    "sg:province":"Hainaut",
    "sg:tags":[
        "assurance"
    ],
    "wof:name":"Laurent Diderich",
    "wof:placetype":"venue"
},
  "geometry": {"coordinates":[4.3793768883,50.3845062256],"type":"Point"}
}