{
  "type": "Feature",
  "properties": {
    "iso:country":"BE",
    "sg:address":"Gemeentestraat 4b6",
    "sg:city":"Turnhout",
    "sg:orig_category":"Avocats and conseillers juridiques",
    "sg:phone":"+32 14 42 26 63",
    "sg:postcode":"2300",
    "sg:province":"Antwerpen",
    "wof:name":"Jef Peeters",
    "wof:placetype":"venue"
},
  "geometry": {"coordinates":[4.9424982071,51.3232917786],"type":"Point"}
}