{
  "type": "Feature",
  "properties": {
    "addr:full":"Rue De Laitte 5 Bouillon Luxembourg 6830",
    "addr:housenumber":"5",
    "addr:postcode":"6830",
    "addr:street":"Rue De Laitte",
    "iso:country":"BE",
    "sg:address":"Rue De Laitte 5",
    "sg:city":"Bouillon",
    "sg:orig_category":"Kansspelen",
    "sg:phone":"+32 61 46 76 88",
    "sg:postcode":"6830",
    "sg:province":"Luxembourg",
    "wof:name":"Frequence",
    "wof:placetype":"venue"
},
  "geometry": {"coordinates":[5.0667619705,49.791103363],"type":"Point"}
}