{
  "type": "Feature",
  "properties": {
    "iso:country":"BE",
    "sg:address":"Minderbroedersstraat 26",
    "sg:city":"Brugge",
    "sg:orig_category":"Bars Caf\u00e9s Catering and organisatie van feesten Fast food and meeneem restaurants Restaurants",
    "sg:phone":"+32 50 33 27 90",
    "sg:postcode":"8000",
    "sg:province":"West-Vlaanderen",
    "wof:name":"'t Botaniekske",
    "wof:placetype":"venue"
},
  "geometry": {"coordinates":[3.2321200371,51.2065048218],"type":"Point"}
}