{
  "type": "Feature",
  "properties": {
    "iso:country":"BE",
    "sg:address":"Diestsestraat 14",
    "sg:city":"Aarschot",
    "sg:orig_category":"Chaussures",
    "sg:phone":"+32 16 56 50 63",
    "sg:postcode":"3200",
    "sg:province":"Vlaams-Brabant",
    "wof:name":"De Blauwe Veter",
    "wof:placetype":"venue"
},
  "geometry": {"coordinates":[4.8367362022,50.9834709167],"type":"Point"}
}