{
  "type": "Feature",
  "properties": {
    "iso:country":"BE",
    "sg:address":"Meulebekestraat 141",
    "sg:city":"Ingelmunster",
    "sg:classifiers":[
        {
            "category":"Manufacturing",
            "subcategory":"Rubber & Plastics",
            "type":"Manufacturing & Wholesale Goods"
        }
    ],
    "sg:phone":"+32 51 48 47 46",
    "sg:postcode":"8770",
    "sg:province":"West-Vlaanderen",
    "sg:tags":[
        "profile"
    ],
    "wof:name":"Plastivan Plastics Nv",
    "wof:placetype":"venue"
},
  "geometry": {"coordinates":[3.2688291073,50.9359550476],"type":"Point"}
}