{
  "type": "Feature",
  "properties": {
    "addr:full":"Industrielaan 4 Overpelt Limburg 3900",
    "addr:housenumber":"4",
    "addr:postcode":"3900",
    "addr:street":"Industrielaan",
    "iso:country":"BE",
    "sg:address":"Industrielaan 4",
    "sg:city":"Overpelt",
    "sg:classifiers":[
        {
            "category":"Home & Garden",
            "subcategory":"Carpets & Floor Coverings",
            "type":"Retail Goods"
        }
    ],
    "sg:phone":"+32 11 64 30 22",
    "sg:postcode":"3900",
    "sg:province":"Limburg",
    "sg:tags":[
        "carpeting"
    ],
    "wof:name":"Allied Textile Nv",
    "wof:placetype":"venue"
},
  "geometry": {"coordinates":[5.3726320267,51.2166748047],"type":"Point"}
}