{
  "type": "Feature",
  "properties": {
    "addr:full":"Vrijheid 90 Hoogstraten Antwerpen 2320",
    "addr:housenumber":"90",
    "addr:postcode":"2320",
    "addr:street":"Vrijheid",
    "iso:country":"BE",
    "sg:address":"Vrijheid 90",
    "sg:city":"Hoogstraten",
    "sg:orig_category":"Dameskledingzaken",
    "sg:phone":"+32 3 314 30 10",
    "sg:postcode":"2320",
    "sg:province":"Antwerpen",
    "wof:name":"Studio Jess",
    "wof:placetype":"venue"
},
  "geometry": {"coordinates":[4.762403965,51.4044075012],"type":"Point"}
}