{
  "type": "Feature",
  "properties": {
    "iso:country":"BE",
    "sg:address":"Kanaalstraat 15",
    "sg:city":"Lummen",
    "sg:orig_category":"Gereedschapswerktuigen Gh",
    "sg:phone":"+32 11 45 10 22",
    "sg:postcode":"3560",
    "sg:province":"Limburg",
    "wof:name":"Werkhuizen Jacobs",
    "wof:placetype":"venue"
},
  "geometry": {"coordinates":[5.2267408371,51.0240364075],"type":"Point"}
}