{
  "type": "Feature",
  "properties": {
    "addr:full":"Ardooisesteenweg 32 Roeselare West-Vlaanderen 8800",
    "addr:housenumber":"32",
    "addr:postcode":"8800",
    "addr:street":"Ardooisesteenweg",
    "iso:country":"BE",
    "sg:address":"Ardooisesteenweg 32",
    "sg:city":"Roeselare",
    "sg:orig_category":"Banques and organismes de cr\u00e9dit",
    "sg:phone":"+32 51 21 07 81",
    "sg:postcode":"8800",
    "sg:province":"West-Vlaanderen",
    "wof:name":"Fortis",
    "wof:placetype":"venue"
},
  "geometry": {"coordinates":[3.1323049068,50.9492874146],"type":"Point"}
}