{
  "type": "Feature",
  "properties": {
    "addr:full":"Rue Fosses Berger 33 Olne Li\u00e8ge 4877",
    "addr:housenumber":"33",
    "addr:postcode":"4877",
    "addr:street":"Rue Fosses Berger",
    "iso:country":"BE",
    "sg:address":"Rue Fosses Berger 33",
    "sg:city":"Olne",
    "sg:classifiers":[
        {
            "category":"Real Estate",
            "subcategory":"Architect",
            "type":"Services"
        }
    ],
    "sg:phone":"+32 87 26 85 56",
    "sg:postcode":"4877",
    "sg:province":"Li\u00e8ge",
    "wof:name":"Grommet A",
    "wof:placetype":"venue"
},
  "geometry": {"coordinates":[5.7394719124,50.5891990662],"type":"Point"}
}