{
  "type": "Feature",
  "properties": {
    "iso:country":"BE",
    "sg:address":"Boulevard Auguste Reyers 156",
    "sg:city":"Bruxelles (schaerbeek)",
    "sg:classifiers":[
        {
            "category":"Autos & Motor Vehicles",
            "subcategory":"Boat Sales",
            "type":"Retail Goods"
        }
    ],
    "sg:phone":"+32 2 241 88 22",
    "sg:postcode":"1030",
    "sg:province":"Bruxelles-Capitale",
    "sg:tags":[
        "automobile",
        "racing",
        "accessory"
    ],
    "wof:name":"Red & White Sportswear Sprl",
    "wof:placetype":"venue"
},
  "geometry": {"coordinates":[4.4040060043,50.8470230103],"type":"Point"}
}