{
  "type": "Feature",
  "properties": {
    "iso:country":"BE",
    "sg:address":"Nijverheidslaan 1529",
    "sg:city":"Opglabbeek",
    "sg:orig_category":"Rev\u00eatements de sols and murs",
    "sg:phone":"+32 89 56 98 20",
    "sg:postcode":"3660",
    "sg:province":"Limburg",
    "wof:name":"Reijnen Graniet Belgium",
    "wof:placetype":"venue"
},
  "geometry": {"coordinates":[5.5495657921,51.04347229],"type":"Point"}
}