{
  "type": "Feature",
  "properties": {
    "iso:country":"BE",
    "sg:address":"De Nefstraat 9",
    "sg:city":"Lille",
    "sg:orig_category":"Electrom\u00e9nager, t\u00e9l\u00e9visions and radios",
    "sg:phone":"+32 14 55 73 12",
    "sg:postcode":"2275",
    "sg:province":"Antwerpen",
    "wof:name":"Jozef Thijs",
    "wof:placetype":"venue"
},
  "geometry": {"coordinates":[4.8679771423,51.2686882019],"type":"Point"}
}