{
  "type": "Feature",
  "properties": {
    "addr:full":"Blakstraat 2 Eeklo Oost-Vlaanderen 9900",
    "addr:housenumber":"2",
    "addr:postcode":"9900",
    "addr:street":"Blakstraat",
    "iso:country":"BE",
    "sg:address":"Blakstraat 2",
    "sg:city":"Eeklo",
    "sg:orig_category":"Huisdieren and benodigdheden",
    "sg:phone":"+32 9 378 02 49",
    "sg:postcode":"9900",
    "sg:province":"Oost-Vlaanderen",
    "wof:name":"Catterij Phicaro",
    "wof:placetype":"venue"
},
  "geometry": {"coordinates":[3.5460600853,51.192363739],"type":"Point"}
}