{
  "type": "Feature",
  "properties": {
    "addr:full":"Lakenmakersstraat 12b1 Mechelen Antwerpen 2800",
    "addr:housenumber":"12b1",
    "addr:postcode":"2800",
    "addr:street":"Lakenmakersstraat",
    "iso:country":"BE",
    "sg:address":"Lakenmakersstraat 12b1",
    "sg:city":"Mechelen",
    "sg:orig_category":"Verhuur bouwmachines",
    "sg:phone":"+32 15 55 81 59",
    "sg:postcode":"2800",
    "sg:province":"Antwerpen",
    "wof:name":"V.i.a.",
    "wof:placetype":"venue"
},
  "geometry": {"coordinates":[4.4946789742,51.029384613],"type":"Point"}
}