{
  "type": "Feature",
  "properties": {
    "iso:country":"BE",
    "sg:address":"Rue Des Mar\u00cats 88",
    "sg:city":"Li\u00c8ge",
    "sg:orig_category":"Articles de f\u00eate, farces and attrapes",
    "sg:phone":"+32 475 43 63 98",
    "sg:postcode":"4020",
    "sg:province":"Li\u00e8ge",
    "wof:name":"Bruno Pandini",
    "wof:placetype":"venue"
},
  "geometry": {"coordinates":[5.5944471359,50.6388015747],"type":"Point"}
}