{
  "type": "Feature",
  "properties": {
    "iso:country":"BE",
    "sg:address":"Avenue De Maire 104",
    "sg:city":"Tournai",
    "sg:classifiers":[
        {
            "category":"Bars & Pubs",
            "type":"Food & Drink"
        }
    ],
    "sg:phone":"+32 69 23 50 58",
    "sg:postcode":"7500",
    "sg:province":"Hainaut",
    "wof:name":"Derby (du)",
    "wof:placetype":"venue"
},
  "geometry": {"coordinates":[3.3747119904,50.6153640747],"type":"Point"}
}