{
  "type": "Feature",
  "properties": {
    "addr:full":"Brugsesteenweg 292 Roeselare West-Vlaanderen 8800",
    "addr:housenumber":"292",
    "addr:postcode":"8800",
    "addr:street":"Brugsesteenweg",
    "iso:country":"BE",
    "sg:address":"Brugsesteenweg 292",
    "sg:city":"Roeselare",
    "sg:classifiers":[
        {
            "category":"Insurance",
            "subcategory":"Insurance Agent",
            "type":"Services"
        }
    ],
    "sg:phone":"+32 51 20 01 23",
    "sg:postcode":"8800",
    "sg:province":"West-Vlaanderen",
    "sg:tags":[
        "broker"
    ],
    "wof:name":"Atelia Roeselare",
    "wof:placetype":"venue"
},
  "geometry": {"coordinates":[3.1208848953,50.9638366699],"type":"Point"}
}