{
  "type": "Feature",
  "properties": {
    "addr:full":"Scheepswerfstraat 43 Dendermonde Oost-Vlaanderen 9200",
    "addr:housenumber":"43",
    "addr:postcode":"9200",
    "addr:street":"Scheepswerfstraat;Oost-Vlaanderen",
    "iso:country":"BE",
    "sg:address":"Scheepswerfstraat 43",
    "sg:city":"Dendermonde",
    "sg:orig_category":"Brood, gebak and snoepgoed",
    "sg:phone":"+32 52 33 43 39",
    "sg:postcode":"9200",
    "sg:province":"Oost-Vlaanderen",
    "wof:name":"Matoontje",
    "wof:placetype":"venue"
},
  "geometry": {"coordinates":[4.0983099937,51.0315208435],"type":"Point"}
}