{
  "type": "Feature",
  "properties": {
    "iso:country":"BE",
    "sg:address":"Industriezone Webbekom 8",
    "sg:city":"Diest",
    "sg:orig_category":"Airconditioning and ventilatie Loodgieterij, verwarming and sanitaire installaties",
    "sg:phone":"+32 475 30 98 26",
    "sg:postcode":"3290",
    "sg:province":"Vlaams-Brabant",
    "wof:name":"Phoenix",
    "wof:placetype":"venue"
},
  "geometry": {"coordinates":[5.0605301857,50.9681587219],"type":"Point"}
}