{
  "type": "Feature",
  "properties": {
    "iso:country":"BE",
    "sg:address":"Place Jean Vander Elst 25",
    "sg:city":"Ukkel/uccle",
    "sg:orig_category":"Enseignement secondaire technique and professionnel",
    "sg:phone":"+32 2 345 46 26",
    "sg:postcode":"1180",
    "sg:province":"Bruxelles-Capitale",
    "wof:name":"Inst. St.vincent De Paul",
    "wof:placetype":"venue"
},
  "geometry": {"coordinates":[4.3332080841,50.8038330078],"type":"Point"}
}