{
  "type": "Feature",
  "properties": {
    "addr:full":"Rue Des Ecoles 13 Hamoir (comblain-fairon) Li\u00e8ge 4180",
    "addr:housenumber":"13",
    "addr:postcode":"4180",
    "addr:street":"Rue Des Ecoles;Comblain-Fairon",
    "iso:country":"BE",
    "sg:address":"Rue Des Ecoles 13",
    "sg:city":"Hamoir (comblain-fairon)",
    "sg:classifiers":[
        {
            "category":"Building & Trades",
            "subcategory":"Cleaning & Sanitation",
            "type":"Services"
        }
    ],
    "sg:phone":"+32 4 369 12 25",
    "sg:postcode":"4180",
    "sg:province":"Li\u00e8ge",
    "sg:tags":[
        "cleaner",
        "window"
    ],
    "wof:name":"As De Carreau",
    "wof:placetype":"venue"
},
  "geometry": {"coordinates":[5.570289135,50.4541015625],"type":"Point"}
}