{
  "type": "Feature",
  "properties": {
    "iso:country":"BE",
    "sg:address":"Apolloniadreef 6",
    "sg:city":"Poperinge",
    "sg:orig_category":"Eleveurs and marchands de porcs",
    "sg:phone":"+32 57 38 82 78",
    "sg:postcode":"8978",
    "sg:province":"West-Vlaanderen",
    "wof:name":"Jean Demuys",
    "wof:placetype":"venue"
},
  "geometry": {"coordinates":[2.6206049919,50.8592453003],"type":"Point"}
}