{
  "type": "Feature",
  "properties": {
    "iso:country":"BE",
    "sg:address":"P. De Colvenaerplein 9",
    "sg:city":"Zelzate",
    "sg:classifiers":[
        {
            "category":"Insurance",
            "subcategory":"Life Insurance",
            "type":"Services"
        }
    ],
    "sg:phone":"+32 9 342 92 68",
    "sg:postcode":"9060",
    "sg:province":"Oost-Vlaanderen",
    "sg:tags":[
        "assurance"
    ],
    "wof:name":"P. De Smet",
    "wof:placetype":"venue"
},
  "geometry": {"coordinates":[3.8125081062,51.1987113953],"type":"Point"}
}