{
  "type": "Feature",
  "properties": {
    "addr:full":"Dubois-thornstraat 105 Sint-jans-molenbeek/molenbeek-saint-jean Bruxelles-Capitale 1080",
    "addr:housenumber":"105",
    "addr:postcode":"1080",
    "addr:street":"Dubois-Thornstraat",
    "iso:country":"BE",
    "sg:address":"Dubois-thornstraat 105",
    "sg:city":"Sint-jans-molenbeek/molenbeek-saint-jean",
    "sg:orig_category":"Meubelzaken, woning- and keukeninrichting",
    "sg:phone":"+32 2 410 46 75",
    "sg:postcode":"1080",
    "sg:province":"Bruxelles-Capitale",
    "wof:name":"F S Et Managements",
    "wof:placetype":"venue"
},
  "geometry": {"coordinates":[4.3233118057,50.8550186157],"type":"Point"}
}