{
  "type": "Feature",
  "properties": {
    "iso:country":"BE",
    "sg:address":"Heerweg 11",
    "sg:city":"Beersel",
    "sg:orig_category":"Jardinage",
    "sg:phone":"+32 2 331 32 62",
    "sg:postcode":"1650",
    "sg:province":"Vlaams-Brabant",
    "wof:name":"Armand Jacobs",
    "wof:placetype":"venue"
},
  "geometry": {"coordinates":[4.3166899681,50.7646255493],"type":"Point"}
}