{
  "type": "Feature",
  "properties": {
    "addr:full":"Gentsesteenweg 196-198 Deinze Oost-Vlaanderen 9800",
    "addr:housenumber":"196-198",
    "addr:postcode":"9800",
    "addr:street":"Gentsesteenweg",
    "iso:country":"BE",
    "sg:address":"Gentsesteenweg 196-198",
    "sg:city":"Deinze",
    "sg:classifiers":[
        {
            "category":"Manufacturing",
            "subcategory":"Furniture",
            "type":"Manufacturing & Wholesale Goods"
        }
    ],
    "sg:phone":"+32 9 386 87 77",
    "sg:postcode":"9800",
    "sg:province":"Oost-Vlaanderen",
    "sg:tags":[
        "rattan"
    ],
    "wof:name":"Riet & Rotan Woonwereld",
    "wof:placetype":"venue"
},
  "geometry": {"coordinates":[3.5452289581,50.980846405],"type":"Point"}
}