{
  "type": "Feature",
  "properties": {
    "addr:full":"De Robianostraat 118 Borsbeek Antwerpen 2150",
    "addr:housenumber":"118",
    "addr:postcode":"2150",
    "addr:street":"De Robianostraat",
    "iso:country":"BE",
    "sg:address":"De Robianostraat 118",
    "sg:city":"Borsbeek",
    "sg:classifiers":[
        {
            "category":"Building & Trades",
            "subcategory":"Landscaping Services",
            "type":"Services"
        }
    ],
    "sg:phone":"+32 3 321 86 38",
    "sg:postcode":"2150",
    "sg:province":"Antwerpen",
    "sg:tags":[
        "gardening",
        "garden",
        "maintenance"
    ],
    "wof:name":"Van Osselaer M",
    "wof:placetype":"venue"
},
  "geometry": {"coordinates":[4.4807138443,51.1949462891],"type":"Point"}
}