{
  "type": "Feature",
  "properties": {
    "iso:country":"BE",
    "sg:address":"Sint-martinusstraat 13",
    "sg:city":"Wortegem-petegem",
    "sg:orig_category":"Advocaten and juridische adviseurs",
    "sg:phone":"+32 55 30 99 18",
    "sg:postcode":"9790",
    "sg:province":"Oost-Vlaanderen",
    "wof:name":"Tom Wittebroodt",
    "wof:placetype":"venue"
},
  "geometry": {"coordinates":[3.5587260723,50.8345413208],"type":"Point"}
}