{
  "type": "Feature",
  "properties": {
    "iso:country":"BE",
    "sg:address":"Zuidstraat 50",
    "sg:city":"Roeselare",
    "sg:classifiers":[
        {
            "category":"Restaurant",
            "type":"Food & Drink"
        }
    ],
    "sg:phone":"+32 51 22 01 48",
    "sg:postcode":"8800",
    "sg:province":"West-Vlaanderen",
    "wof:name":"Brasserie Saint-georges",
    "wof:placetype":"venue"
},
  "geometry": {"coordinates":[3.124309063,50.9421234131],"type":"Point"}
}