{
  "type": "Feature",
  "properties": {
    "iso:country":"BE",
    "sg:address":"Chauss\u00e9e De Valenciennes 51",
    "sg:city":"Ath",
    "sg:classifiers":[
        {
            "category":"Real Estate",
            "subcategory":"Architect",
            "type":"Services"
        }
    ],
    "sg:phone":"+32 68 55 34 07",
    "sg:postcode":"7800",
    "sg:province":"Hainaut",
    "wof:name":"Vander Haegen C",
    "wof:placetype":"venue"
},
  "geometry": {"coordinates":[3.7690420151,50.6242828369],"type":"Point"}
}