{
  "type": "Feature",
  "properties": {
    "addr:full":"Vervierser Strasse 89 Eupen Li\u00e8ge 4700",
    "addr:housenumber":"89",
    "addr:postcode":"4700",
    "addr:street":"Vervierser Strasse",
    "iso:country":"BE",
    "sg:address":"Vervierser Strasse 89",
    "sg:city":"Eupen",
    "sg:classifiers":[
        {
            "category":"Education",
            "subcategory":"University",
            "type":"Public Place"
        }
    ],
    "sg:phone":"+32 87 74 02 36",
    "sg:postcode":"4700",
    "sg:province":"Li\u00e8ge",
    "sg:tags":[
        "higher"
    ],
    "wof:name":"Institut De Promotion Sociale De La Communaut\u00e9 Germanophone",
    "wof:placetype":"venue"
},
  "geometry": {"coordinates":[6.0179700851,50.6321907043],"type":"Point"}
}