{
  "type": "Feature",
  "properties": {
    "addr:full":"Chauss\u00e9e De Vilvorde 152 Bruxelles Bruxelles-Capitale 1120",
    "addr:housenumber":"152",
    "addr:postcode":"1120",
    "addr:street":"Chausse\u0301E De Vilvorde",
    "iso:country":"BE",
    "sg:address":"Chauss\u00e9e De Vilvorde 152",
    "sg:city":"Bruxelles",
    "sg:classifiers":[
        {
            "category":"Building & Trades",
            "subcategory":"Equipment Rental",
            "type":"Services"
        }
    ],
    "sg:phone":"+32 2 675 59 02",
    "sg:postcode":"1120",
    "sg:province":"Bruxelles-Capitale",
    "sg:tags":[
        "use",
        "apparatus",
        "tool",
        "-",
        "professional",
        "machines"
    ],
    "wof:name":"Atelier Locma",
    "wof:placetype":"venue"
},
  "geometry": {"coordinates":[4.4003281593,50.8963317871],"type":"Point"}
}