{
  "type": "Feature",
  "properties": {
    "addr:full":"Nieuwlandlaan 25 Aarschot Vlaams-Brabant 3200",
    "addr:housenumber":"25",
    "addr:postcode":"3200",
    "addr:street":"Nieuwlandlaan",
    "iso:country":"BE",
    "sg:address":"Nieuwlandlaan 25",
    "sg:city":"Aarschot",
    "sg:classifiers":[
        {
            "category":"Banks & Credit Unions",
            "subcategory":"Investment Brokerage",
            "type":"Services"
        }
    ],
    "sg:phone":"+32 16 57 23 28",
    "sg:postcode":"3200",
    "sg:province":"Vlaams-Brabant",
    "sg:tags":[
        "-",
        "plastic"
    ],
    "wof:name":"V.d. Plastics Bvba",
    "wof:placetype":"venue"
},
  "geometry": {"coordinates":[4.8163628578,50.9857025146],"type":"Point"}
}