{
  "type": "Feature",
  "properties": {
    "iso:country":"BE",
    "sg:address":"Chauss\u00e9e De Marche 37",
    "sg:city":"Assesse",
    "sg:classifiers":[
        {
            "category":"Mining & Drilling",
            "type":"Manufacturing & Wholesale Goods"
        }
    ],
    "sg:phone":"+32 83 65 55 88",
    "sg:postcode":"5330",
    "sg:province":"Namur",
    "sg:tags":[
        "quarry"
    ],
    "wof:name":"Carri\u00e8res Lizin Goffaux Sprl",
    "wof:placetype":"venue"
},
  "geometry": {"coordinates":[5.0215492249,50.3728141785],"type":"Point"}
}