{
  "type": "Feature",
  "properties": {
    "iso:country":"BE",
    "sg:address":"Vichtestraat 12",
    "sg:city":"Zwevegem",
    "sg:classifiers":[
        {
            "category":"Restaurant",
            "type":"Food & Drink"
        }
    ],
    "sg:phone":"+32 56 77 89 43",
    "sg:postcode":"8553",
    "sg:province":"West-Vlaanderen",
    "sg:tags":[
        "organisatie",
        "feesten",
        "van",
        "catering"
    ],
    "wof:name":"Stropuyt",
    "wof:placetype":"venue"
},
  "geometry": {"coordinates":[3.3935530186,50.8209838867],"type":"Point"}
}