{
  "type": "Feature",
  "properties": {
    "addr:full":"Diestersteenweg 128 Leopoldsburg Limburg 3970",
    "addr:housenumber":"128",
    "addr:postcode":"3970",
    "addr:street":"Diestersteenweg",
    "iso:country":"BE",
    "sg:address":"Diestersteenweg 128",
    "sg:city":"Leopoldsburg",
    "sg:orig_category":"Motos. V\u00e9los",
    "sg:phone":"+32 11 34 57 51",
    "sg:postcode":"3970",
    "sg:province":"Limburg",
    "wof:name":"Willy Schraeyen",
    "wof:placetype":"venue"
},
  "geometry": {"coordinates":[5.2476820946,51.1144371033],"type":"Point"}
}