{
  "type": "Feature",
  "properties": {
    "addr:full":"Reibroekstraat 156 Evergem Oost-Vlaanderen 9940",
    "addr:housenumber":"156",
    "addr:postcode":"9940",
    "addr:street":"Reibroekstraat;Oost-Vlaanderen",
    "iso:country":"BE",
    "sg:address":"Reibroekstraat 156",
    "sg:city":"Evergem",
    "sg:orig_category":"Eleveurs de bovins. Eleveurs and marchands de porcs",
    "sg:phone":"+32 9 357 37 60",
    "sg:postcode":"9940",
    "sg:province":"Oost-Vlaanderen",
    "wof:name":"Emiel Roete",
    "wof:placetype":"venue"
},
  "geometry": {"coordinates":[3.7044870853,51.1206474304],"type":"Point"}
}