{
  "type": "Feature",
  "properties": {
    "addr:full":"Zeelaan 116 De Panne West-Vlaanderen 8660",
    "addr:housenumber":"116",
    "addr:postcode":"8660",
    "addr:street":"Zeelaan",
    "iso:country":"BE",
    "sg:address":"Zeelaan 116",
    "sg:city":"De Panne",
    "sg:orig_category":"V\u00eatements",
    "sg:phone":"+32 58 41 44 01",
    "sg:postcode":"8660",
    "sg:province":"West-Vlaanderen",
    "wof:name":"Hermes",
    "wof:placetype":"venue"
},
  "geometry": {"coordinates":[2.5925009251,51.1002807617],"type":"Point"}
}