{
  "type": "Feature",
  "properties": {
    "iso:country":"BE",
    "sg:address":"Sint-annastraat 4",
    "sg:city":"Hoeilaart",
    "sg:classifiers":[
        {
            "category":"Arena",
            "subcategory":"Sports Club",
            "type":"Entertainment"
        }
    ],
    "sg:phone":"+32 2 657 22 65",
    "sg:postcode":"1560",
    "sg:province":"Vlaams-Brabant",
    "sg:tags":[
        "de"
    ],
    "wof:name":"Y.c.h.m.",
    "wof:placetype":"venue"
},
  "geometry": {"coordinates":[4.479968071,50.762878418],"type":"Point"}
}