{
  "type": "Feature",
  "properties": {
    "addr:full":"Rue Du Ronquoy 4 Antoing Hainaut 7643",
    "addr:housenumber":"4",
    "addr:postcode":"7643",
    "addr:street":"Rue Du Ronquoy",
    "iso:country":"BE",
    "sg:address":"Rue Du Ronquoy 4",
    "sg:city":"Antoing",
    "sg:orig_category":"Rundveehouders",
    "sg:phone":"+32 69 44 28 73",
    "sg:postcode":"7643",
    "sg:province":"Hainaut",
    "wof:name":"Charles Gallaix",
    "wof:placetype":"venue"
},
  "geometry": {"coordinates":[3.4807519913,50.5611343384],"type":"Point"}
}