{
  "type": "Feature",
  "properties": {
    "addr:full":"Diksmuidseweg 257 Ieper West-Vlaanderen 8904",
    "addr:housenumber":"257",
    "addr:postcode":"8904",
    "iso:country":"BE",
    "sg:address":"Diksmuidseweg 257",
    "sg:city":"Ieper",
    "sg:orig_category":"Eleveurs de bovins. Eleveurs and marchands de porcs",
    "sg:phone":"+32 57 42 22 63",
    "sg:postcode":"8904",
    "sg:province":"West-Vlaanderen",
    "wof:name":"Rik Vandewalle",
    "wof:placetype":"venue"
},
  "geometry": {"coordinates":[2.8660900593,50.8828926086],"type":"Point"}
}