{
  "type": "Feature",
  "properties": {
    "addr:full":"Rue G\u00e9n\u00e9raux Cuvelier 21 Florenville Luxembourg 6820",
    "addr:housenumber":"21",
    "addr:postcode":"6820",
    "addr:street":"Rue Ge\u0301Ne\u0301Raux Cuvelier",
    "iso:country":"BE",
    "sg:address":"Rue G\u00e9n\u00e9raux Cuvelier 21",
    "sg:city":"Florenville",
    "sg:classifiers":[
        {
            "category":"Health Services",
            "subcategory":"Doctor",
            "type":"Services"
        }
    ],
    "sg:phone":"+32 61 31 36 26",
    "sg:postcode":"6820",
    "sg:province":"Luxembourg",
    "sg:tags":[
        "medicinephysicians",
        "surgeon"
    ],
    "wof:name":"Haulet D",
    "wof:placetype":"venue"
},
  "geometry": {"coordinates":[5.3088459969,49.6977882385],"type":"Point"}
}