{
  "type": "Feature",
  "properties": {
    "iso:country":"BE",
    "sg:address":"Kruisberg 1ba",
    "sg:city":"Bornem",
    "sg:classifiers":[
        {
            "category":"Shopping",
            "subcategory":"Clothing, Apparel, & Fashions",
            "type":"Retail Goods"
        }
    ],
    "sg:phone":"+32 3 899 00 89",
    "sg:postcode":"2880",
    "sg:province":"Antwerpen",
    "sg:tags":[
        "v\u00eatements",
        "pour",
        "dame"
    ],
    "wof:name":"Huis Divino",
    "wof:placetype":"venue"
},
  "geometry": {"coordinates":[4.2328867912,51.0951461792],"type":"Point"}
}