{
  "type": "Feature",
  "properties": {
    "addr:full":"Ossendriesstraat 70 Zonhoven Limburg 3520",
    "addr:housenumber":"70",
    "addr:postcode":"3520",
    "addr:street":"Ossendriesstraat",
    "iso:country":"BE",
    "sg:address":"Ossendriesstraat 70",
    "sg:city":"Zonhoven",
    "sg:classifiers":[
        {
            "category":"Building & Trades",
            "subcategory":"Electrical",
            "type":"Services"
        }
    ],
    "sg:phone":"+32 11 81 43 32",
    "sg:postcode":"3520",
    "sg:province":"Limburg",
    "sg:tags":[
        "electric",
        "-",
        "housewiring",
        "contractor"
    ],
    "wof:name":"Polmans A",
    "wof:placetype":"venue"
},
  "geometry": {"coordinates":[5.3753809929,51.0034294128],"type":"Point"}
}