{
  "type": "Feature",
  "properties": {
    "iso:country":"BE",
    "sg:address":"Boulevard Albert Elisabeth 67",
    "sg:city":"Mons",
    "sg:classifiers":[
        {
            "category":"Health Services",
            "subcategory":"Doctor",
            "type":"Services"
        }
    ],
    "sg:phone":"+32 65 40 81 00",
    "sg:postcode":"7000",
    "sg:province":"Hainaut",
    "sg:tags":[
        "medicinephysicians",
        "surgeon"
    ],
    "wof:name":"Flamant M",
    "wof:placetype":"venue"
},
  "geometry": {"coordinates":[3.9519910812,50.4461326599],"type":"Point"}
}