{
  "type": "Feature",
  "properties": {
    "iso:country":"BE",
    "sg:address":"Hoge Mauw 34",
    "sg:city":"Arendonk",
    "sg:classifiers":[
        {
            "category":"Manufacturing",
            "subcategory":"Food",
            "type":"Manufacturing & Wholesale Goods"
        }
    ],
    "sg:phone":"+32 14 68 70 83",
    "sg:postcode":"2370",
    "sg:province":"Antwerpen",
    "sg:tags":[
        "industry",
        "-",
        "ingredient"
    ],
    "wof:name":"Bioland",
    "wof:placetype":"venue"
},
  "geometry": {"coordinates":[5.1094222069,51.297542572],"type":"Point"}
}