{
  "type": "Feature",
  "properties": {
    "iso:country":"BE",
    "sg:address":"Rue De La Station De Woluw\u00c9 113",
    "sg:city":"Sint-pieters-woluwe/woluwe-sai",
    "sg:orig_category":"Installation de menuiserie m\u00e9tallique. Mat\u00e9riaux de construction Gr",
    "sg:phone":"+32 2 770 22 33",
    "sg:postcode":"1150",
    "sg:province":"Bruxelles-Capitale",
    "wof:name":"Vanheule",
    "wof:placetype":"venue"
},
  "geometry": {"coordinates":[4.4305348396,50.837020874],"type":"Point"}
}