{
  "type": "Feature",
  "properties": {
    "addr:full":"Rue Eudore Pirmez 9 Charleroi (marcinelle) Hainaut 6001",
    "addr:housenumber":"9",
    "addr:postcode":"6001",
    "addr:street":"Rue Eudore Pirmez",
    "iso:country":"BE",
    "sg:address":"Rue Eudore Pirmez 9",
    "sg:city":"Charleroi (marcinelle)",
    "sg:classifiers":[
        {
            "category":"Manufacturing",
            "subcategory":"Metals",
            "type":"Manufacturing & Wholesale Goods"
        }
    ],
    "sg:phone":"+32 495 57 26 85",
    "sg:postcode":"6001",
    "sg:province":"Hainaut",
    "sg:tags":[
        "ironwork"
    ],
    "wof:name":"Plagmerelli M",
    "wof:placetype":"venue"
},
  "geometry": {"coordinates":[4.4482002258,50.3989982605],"type":"Point"}
}