{
  "type": "Feature",
  "properties": {
    "addr:full":"Bruinbekestraat 34 Wichelen Oost-Vlaanderen 9260",
    "addr:housenumber":"34",
    "addr:postcode":"9260",
    "addr:street":"Bruinbekestraat",
    "iso:country":"BE",
    "sg:address":"Bruinbekestraat 34",
    "sg:city":"Wichelen",
    "sg:orig_category":"Woningbouw",
    "sg:phone":"+32 9 369 40 82",
    "sg:postcode":"9260",
    "sg:province":"Oost-Vlaanderen",
    "wof:name":"Braeckman Etienne",
    "wof:placetype":"venue"
},
  "geometry": {"coordinates":[3.9512739182,50.9984169006],"type":"Point"}
}