{
  "type": "Feature",
  "properties": {
    "addr:full":"Klein Broek 15 Kasterlee Antwerpen 2460",
    "addr:housenumber":"15",
    "addr:postcode":"2460",
    "addr:street":"Klein Broek",
    "iso:country":"BE",
    "sg:address":"Klein Broek 15",
    "sg:city":"Kasterlee",
    "sg:orig_category":"Groententeelt Hout and afgeleiden Gh IJzerwaren, bouw- and verfmaterialen Tuinen",
    "sg:phone":"+32 14 55 47 56",
    "sg:postcode":"2460",
    "sg:province":"Antwerpen",
    "wof:name":"Eykens Houthandel",
    "wof:placetype":"venue"
},
  "geometry": {"coordinates":[5.0273580551,51.2607574463],"type":"Point"}
}