{
  "type": "Feature",
  "properties": {
    "iso:country":"BE",
    "sg:address":"Deerlijkseweg 264",
    "sg:city":"Waregem",
    "sg:orig_category":"Entretien et r\u00e9parations de v\u00e9hicules \u00e0 domicile",
    "sg:phone":"+32 56 60 16 64",
    "sg:postcode":"8790",
    "sg:province":"West-Vlaanderen",
    "wof:name":"Van Wijnsberghe Dirk Bvba",
    "wof:placetype":"venue"
},
  "geometry": {"coordinates":[3.4023430347,50.8688812256],"type":"Point"}
}