{
  "type": "Feature",
  "properties": {
    "addr:full":"Dalestraat 14 Nevele Oost-Vlaanderen 9850",
    "addr:housenumber":"14",
    "addr:postcode":"9850",
    "addr:street":"Dalestraat",
    "iso:country":"BE",
    "sg:address":"Dalestraat 14",
    "sg:city":"Nevele",
    "sg:orig_category":"Rundveehouders Varkenskwekers",
    "sg:phone":"+32 9 371 57 59",
    "sg:postcode":"9850",
    "sg:province":"Oost-Vlaanderen",
    "wof:name":"Luc De Smet",
    "wof:placetype":"venue"
},
  "geometry": {"coordinates":[3.5291879177,51.060798645],"type":"Point"}
}