{
  "type": "Feature",
  "properties": {
    "addr:full":"Massemsesteenweg 87 Wetteren Oost-Vlaanderen 9230",
    "addr:housenumber":"87",
    "addr:postcode":"9230",
    "addr:street":"Massemsesteenweg",
    "iso:country":"BE",
    "sg:address":"Massemsesteenweg 87",
    "sg:city":"Wetteren",
    "sg:classifiers":[
        {
            "category":"Food & Beverages",
            "subcategory":"Groceries & Convenience Stores",
            "type":"Retail Goods"
        }
    ],
    "sg:phone":"+32 9 366 33 82",
    "sg:postcode":"9230",
    "sg:province":"Oost-Vlaanderen",
    "sg:tags":[
        "grocer"
    ],
    "wof:name":"Het Meiroosje",
    "wof:placetype":"venue"
},
  "geometry": {"coordinates":[3.8788299561,50.9933776855],"type":"Point"}
}