{
  "type": "Feature",
  "properties": {
    "iso:country":"BE",
    "sg:address":"Lil 53",
    "sg:city":"Meerhout",
    "sg:orig_category":"Location d'appareils audio-visuels. Equipement divers pour commerces Location de mat\u00e9riel pour banqu",
    "sg:phone":"+32 14 30 39 97",
    "sg:postcode":"2450",
    "sg:province":"Antwerpen",
    "wof:name":"Racor",
    "wof:placetype":"venue"
},
  "geometry": {"coordinates":[5.0874090195,51.1446495056],"type":"Point"}
}