{
  "type": "Feature",
  "properties": {
    "addr:full":"Hennemarkt 17 Tienen Vlaams-Brabant 3300",
    "addr:housenumber":"17",
    "addr:postcode":"3300",
    "addr:street":"Hennemarkt",
    "iso:country":"BE",
    "sg:address":"Hennemarkt 17",
    "sg:city":"Tienen",
    "sg:orig_category":"Geschenken and souvenirs Verlichting and huishoudartikelen",
    "sg:phone":"+32 16 82 38 46",
    "sg:postcode":"3300",
    "sg:province":"Vlaams-Brabant",
    "wof:name":"Casa",
    "wof:placetype":"venue"
},
  "geometry": {"coordinates":[4.9403090477,50.8059959412],"type":"Point"}
}