{
  "type": "Feature",
  "properties": {
    "addr:full":"Schoolstraat 2 Lokeren Oost-Vlaanderen 9160",
    "addr:housenumber":"2",
    "addr:postcode":"9160",
    "addr:street":"Schoolstraat",
    "iso:country":"BE",
    "sg:address":"Schoolstraat 2",
    "sg:city":"Lokeren",
    "sg:orig_category":"Foto-uitrusting Fotografen and fotostudio's Telecommunicatieapparaten",
    "sg:phone":"+32 9 348 57 67",
    "sg:postcode":"9160",
    "sg:province":"Oost-Vlaanderen",
    "wof:name":"Top Camera Foto Gie Sels",
    "wof:placetype":"venue"
},
  "geometry": {"coordinates":[3.9906721115,51.1038742065],"type":"Point"}
}