{
  "type": "Feature",
  "properties": {
    "addr:full":"Torhoutsesteenweg 262 Oostende West-Vlaanderen 8400",
    "addr:housenumber":"262",
    "addr:postcode":"8400",
    "addr:street":"Torhoutsesteenweg",
    "iso:country":"BE",
    "sg:address":"Torhoutsesteenweg 262",
    "sg:city":"Oostende",
    "sg:orig_category":"Poissonniers and \u00e9caillers. Alimentation sp\u00e9cialis\u00e9e",
    "sg:phone":"+32 59 50 03 15",
    "sg:postcode":"8400",
    "sg:province":"West-Vlaanderen",
    "wof:name":"Huis 't Schipje",
    "wof:placetype":"venue"
},
  "geometry": {"coordinates":[2.9072659016,51.216594696],"type":"Point"}
}