{
  "type": "Feature",
  "properties": {
    "addr:full":"Kazernestraat 1 Zottegem Oost-Vlaanderen 9620",
    "addr:housenumber":"1",
    "addr:postcode":"9620",
    "addr:street":"Kazernestraat",
    "iso:country":"BE",
    "sg:address":"Kazernestraat 1",
    "sg:city":"Zottegem",
    "sg:orig_category":"Sportclubs",
    "sg:phone":"+32 9 360 58 11",
    "sg:postcode":"9620",
    "sg:province":"Oost-Vlaanderen",
    "wof:name":"Wijkkomitee Bevegem",
    "wof:placetype":"venue"
},
  "geometry": {"coordinates":[3.8138899803,50.8683586121],"type":"Point"}
}