{
  "type": "Feature",
  "properties": {
    "addr:full":"Rijksweg 380 Maasmechelen Limburg 3630",
    "addr:housenumber":"380",
    "addr:postcode":"3630",
    "addr:street":"Rijksweg",
    "iso:country":"BE",
    "sg:address":"Rijksweg 380",
    "sg:city":"Maasmechelen",
    "sg:classifiers":[
        {
            "category":"Fast Food",
            "type":"Food & Drink"
        }
    ],
    "sg:phone":"+32 89 77 18 58",
    "sg:postcode":"3630",
    "sg:province":"Limburg",
    "sg:tags":[
        "\u00c0",
        "emporter",
        "restaurants"
    ],
    "wof:name":"Snackbar Acropolis",
    "wof:placetype":"venue"
},
  "geometry": {"coordinates":[5.6961359978,50.966342926],"type":"Point"}
}