{
  "type": "Feature",
  "properties": {
    "addr:full":"Vinkertstraat 21 Lommel Limburg 3920",
    "addr:housenumber":"21",
    "addr:postcode":"3920",
    "addr:street":"Vinkertstraat",
    "iso:country":"BE",
    "sg:address":"Vinkertstraat 21",
    "sg:city":"Lommel",
    "sg:classifiers":[
        {
            "category":"Health Services",
            "subcategory":"Health Practitioner",
            "type":"Services"
        }
    ],
    "sg:phone":"+32 11 54 37 53",
    "sg:postcode":"3920",
    "sg:province":"Limburg",
    "sg:tags":[
        "physiotherapist"
    ],
    "wof:name":"Hoedemaekers Carine",
    "wof:placetype":"venue"
},
  "geometry": {"coordinates":[5.3272590637,51.2298774719],"type":"Point"}
}