{
  "type": "Feature",
  "properties": {
    "addr:full":"Leopoldstraat 33 Antwerpen Antwerpen 2000",
    "addr:housenumber":"33",
    "addr:postcode":"2000",
    "addr:street":"Leopoldstraat",
    "iso:country":"BE",
    "sg:address":"Leopoldstraat 33",
    "sg:city":"Antwerpen",
    "sg:classifiers":[
        {
            "category":"Home & Garden",
            "subcategory":"Home Furnishings",
            "type":"Retail Goods"
        }
    ],
    "sg:phone":"+32 3 225 30 04",
    "sg:postcode":"2000",
    "sg:province":"Antwerpen",
    "sg:tags":[
        "-",
        "furniture"
    ],
    "wof:name":"Red Wood",
    "wof:placetype":"venue"
},
  "geometry": {"coordinates":[4.4072241783,51.2144813538],"type":"Point"}
}