{
  "type": "Feature",
  "properties": {
    "iso:country":"BE",
    "sg:address":"Rue Du Sommet 32",
    "sg:city":"Corbion",
    "sg:classifiers":[
        {
            "category":"Wholesale",
            "subcategory":"Construction Materials",
            "type":"Manufacturing & Wholesale Goods"
        }
    ],
    "sg:phone":"+32 3 665 08 00",
    "sg:postcode":"6838",
    "sg:province":"Luxembourg",
    "sg:tags":[
        "textile",
        "dye"
    ],
    "wof:name":"Dictus Zeefdrukkerij B.v.b.a.",
    "wof:placetype":"venue"
},
  "geometry": {"coordinates":[4.4373488426,51.3012542725],"type":"Point"}
}