{
  "type": "Feature",
  "properties": {
    "addr:full":"Rue Des Fontaines 44a Wavre Brabant Wallon 1300",
    "addr:housenumber":"44a;1300",
    "addr:street":"Rue Des Fontaines",
    "iso:country":"BE",
    "sg:address":"Rue Des Fontaines 44a",
    "sg:city":"Wavre",
    "sg:orig_category":"Opticiens",
    "sg:phone":"+32 10 22 33 43",
    "sg:postcode":"1300",
    "sg:province":"Brabant Wallon",
    "wof:name":"Optique Point De Mire",
    "wof:placetype":"venue"
},
  "geometry": {"coordinates":[4.608684063,50.7140693665],"type":"Point"}
}