{
  "type": "Feature",
  "properties": {
    "addr:full":"Rue Bollinckx 254 Bruxelles Bruxelles-Capitale 1070",
    "addr:housenumber":"254",
    "addr:postcode":"1070",
    "addr:street":"Rue Bollinckx",
    "iso:country":"BE",
    "sg:address":"Rue Bollinckx 254",
    "sg:city":"Bruxelles",
    "sg:classifiers":[
        {
            "category":"Professional",
            "subcategory":"Credit Reporting & Collection",
            "type":"Services"
        }
    ],
    "sg:phone":"+32 64 66 21 75",
    "sg:postcode":"1070",
    "sg:province":"Bruxelles-Capitale",
    "sg:tags":[
        "disposable",
        "syrinx"
    ],
    "wof:name":"Sitkoplas Belgium S.p.r.l.",
    "wof:placetype":"venue"
},
  "geometry": {"coordinates":[4.126760006,50.4973907471],"type":"Point"}
}