{
  "type": "Feature",
  "properties": {
    "iso:country":"BE",
    "sg:address":"Avenue De La Couronne 110",
    "sg:city":"Elsene/ixelles",
    "sg:orig_category":"Tabac. Journaux",
    "sg:phone":"+32 2 648 28 50",
    "sg:postcode":"1050",
    "sg:province":"Bruxelles-Capitale",
    "wof:name":"Media Press",
    "wof:placetype":"venue"
},
  "geometry": {"coordinates":[4.3796801567,50.8294181824],"type":"Point"}
}