{
  "type": "Feature",
  "properties": {
    "iso:country":"BE",
    "sg:address":"Mont Saint-martin 93",
    "sg:city":"Li\u00c8ge",
    "sg:orig_category":"Secretariaatsdiensten",
    "sg:phone":"+32 4 222 95 74",
    "sg:postcode":"4000",
    "sg:province":"Li\u00e8ge",
    "wof:name":"B\u00c9n\u00c9dicte Brasseur",
    "wof:placetype":"venue"
},
  "geometry": {"coordinates":[5.5624961853,50.644115448],"type":"Point"}
}