{
  "type": "Feature",
  "properties": {
    "iso:country":"BE",
    "sg:address":"Dorpsstraat 23",
    "sg:city":"Beveren",
    "sg:orig_category":"Epiceries",
    "sg:phone":"+32 3 773 49 38",
    "sg:postcode":"9130",
    "sg:province":"Oost-Vlaanderen",
    "wof:name":"Schalane",
    "wof:placetype":"venue"
},
  "geometry": {"coordinates":[4.1747508049,51.2901687622],"type":"Point"}
}