{
  "type": "Feature",
  "properties": {
    "addr:full":"Keizer Karellaan 582 Sint-agatha-berchem/berchem-sainte-agathe Bruxelles-Capitale 1082",
    "addr:housenumber":"582;/",
    "addr:postcode":"1082",
    "addr:street":"Keizer Karellaan;Sint-Agatha-Berchem",
    "iso:country":"BE",
    "sg:address":"Keizer Karellaan 582",
    "sg:city":"Sint-agatha-berchem/berchem-sainte-agathe",
    "sg:orig_category":"Benzinestations and brandstoffen",
    "sg:phone":"+32 2 465 46 49",
    "sg:postcode":"1082",
    "sg:province":"Bruxelles-Capitale",
    "wof:name":"Fina",
    "wof:placetype":"venue"
},
  "geometry": {"coordinates":[4.2889671326,50.8712158203],"type":"Point"}
}