{
  "type": "Feature",
  "properties": {
    "iso:country":"BE",
    "sg:address":"Veemarkt 7",
    "sg:city":"Lier",
    "sg:orig_category":"Meubelzaken, woning- and keukeninrichting",
    "sg:phone":"+32 3 488 19 04",
    "sg:postcode":"2500",
    "sg:province":"Antwerpen",
    "wof:name":"Liers Slaapcenter",
    "wof:placetype":"venue"
},
  "geometry": {"coordinates":[4.5830388069,51.1286964417],"type":"Point"}
}