{
  "type": "Feature",
  "properties": {
    "addr:full":"Processiestraat 4 Lennik (sint-martens-lennik) Vlaams-Brabant 1750",
    "addr:housenumber":"4",
    "addr:postcode":"1750",
    "addr:street":"Processiestraat",
    "iso:country":"BE",
    "sg:address":"Processiestraat 4",
    "sg:city":"Lennik (sint-martens-lennik)",
    "sg:classifiers":[
        {
            "category":"Utilities",
            "subcategory":"Fuel Oil & Lpg",
            "type":"Services"
        }
    ],
    "sg:phone":"+32 2 532 43 24",
    "sg:postcode":"1750",
    "sg:province":"Vlaams-Brabant",
    "wof:name":"Meyts Van Molle",
    "wof:placetype":"venue"
},
  "geometry": {"coordinates":[4.1768112183,50.8135910034],"type":"Point"}
}