{
  "type": "Feature",
  "properties": {
    "addr:full":"Mariakerkelaan 273 Oostende West-Vlaanderen 8400",
    "addr:housenumber":"273",
    "addr:postcode":"8400",
    "addr:street":"Mariakerkelaan",
    "iso:country":"BE",
    "sg:address":"Mariakerkelaan 273",
    "sg:city":"Oostende",
    "sg:classifiers":[
        {
            "category":"Health Services",
            "subcategory":"Health Practitioner",
            "type":"Services"
        }
    ],
    "sg:phone":"+32 59 80 57 07",
    "sg:postcode":"8400",
    "sg:province":"West-Vlaanderen",
    "sg:tags":[
        "physiotherapist"
    ],
    "wof:name":"Lepoudre Martine",
    "wof:placetype":"venue"
},
  "geometry": {"coordinates":[2.8929600716,51.2128181458],"type":"Point"}
}