{
  "type": "Feature",
  "properties": {
    "iso:country":"BE",
    "sg:address":"Sint-andreaslaan 9",
    "sg:city":"Beernem",
    "sg:orig_category":"Pain, p\u00e2tisseries and confiseries",
    "sg:phone":"+32 50 78 13 78",
    "sg:postcode":"8730",
    "sg:province":"West-Vlaanderen",
    "wof:name":"Bakkerij Andreas",
    "wof:placetype":"venue"
},
  "geometry": {"coordinates":[3.3325378895,51.1308746338],"type":"Point"}
}