{
  "type": "Feature",
  "properties": {
    "addr:full":"Rue Van Opr\u00c9 75b6 Namur Namur 5100",
    "addr:housenumber":"75b6",
    "addr:postcode":"5100",
    "addr:street":"Rue Van Opre\u0301",
    "iso:country":"BE",
    "sg:address":"Rue Van Opr\u00c9 75b6",
    "sg:city":"Namur",
    "sg:orig_category":"Artistes ind\u00e9pendants",
    "sg:phone":"+32 81 30 57 15",
    "sg:postcode":"5100",
    "sg:province":"Namur",
    "wof:name":"Rene Dessaintes",
    "wof:placetype":"venue"
},
  "geometry": {"coordinates":[4.8742651939,50.4595870972],"type":"Point"}
}