{
  "type": "Feature",
  "properties": {
    "iso:country":"BE",
    "sg:address":"Hogevelden 24",
    "sg:city":"Duffel",
    "sg:classifiers":[
        {
            "category":"Health Services",
            "subcategory":"Health Practitioner",
            "type":"Services"
        }
    ],
    "sg:phone":"+32 15 31 11 34",
    "sg:postcode":"2570",
    "sg:province":"Antwerpen",
    "sg:tags":[
        "physiotherapist"
    ],
    "wof:name":"Van Den Broeck D",
    "wof:placetype":"venue"
},
  "geometry": {"coordinates":[4.5138430595,51.0923461914],"type":"Point"}
}