{
  "type": "Feature",
  "properties": {
    "addr:full":"Zevecotestraat 7 Sint-martens-latem Oost-Vlaanderen 9830",
    "addr:housenumber":"7",
    "addr:postcode":"9830",
    "addr:street":"Zevecotestraat",
    "iso:country":"BE",
    "sg:address":"Zevecotestraat 7",
    "sg:city":"Sint-martens-latem",
    "sg:orig_category":"Rundveehouders Varkenskwekers",
    "sg:phone":"+32 9 282 56 48",
    "sg:postcode":"9830",
    "sg:province":"Oost-Vlaanderen",
    "wof:name":"Rene Steyaert",
    "wof:placetype":"venue"
},
  "geometry": {"coordinates":[3.6483950615,51.0154953003],"type":"Point"}
}