{
  "type": "Feature",
  "properties": {
    "iso:country":"BE",
    "sg:address":"Steenweg Op Turnhout 3",
    "sg:city":"Oud-turnhout",
    "sg:orig_category":"D\u00e9corateurs d'int\u00e9rieur",
    "sg:phone":"+32 14 46 00 34",
    "sg:postcode":"2360",
    "sg:province":"Antwerpen",
    "wof:name":"M. Heeren",
    "wof:placetype":"venue"
},
  "geometry": {"coordinates":[4.9804720879,51.3184509277],"type":"Point"}
}