{
  "type": "Feature",
  "properties": {
    "addr:full":"Swinnenwijerweg 5 Genk Limburg 3600",
    "addr:housenumber":"5",
    "addr:postcode":"3600",
    "addr:street":"Swinnenwijerweg",
    "iso:country":"BE",
    "sg:address":"Swinnenwijerweg 5",
    "sg:city":"Genk",
    "sg:classifiers":[
        {
            "category":"Wholesale",
            "subcategory":"Metals & Minerals",
            "type":"Manufacturing & Wholesale Goods"
        }
    ],
    "sg:phone":"+32 89 62 15 27",
    "sg:postcode":"3600",
    "sg:province":"Limburg",
    "sg:tags":[
        "precious"
    ],
    "wof:name":"Heckett Multiserv",
    "wof:placetype":"venue"
},
  "geometry": {"coordinates":[5.50604105,50.9389801025],"type":"Point"}
}