{
  "type": "Feature",
  "properties": {
    "addr:full":"Schoon Uitzichtlaan 32 Ukkel/uccle Bruxelles-Capitale 1180",
    "addr:housenumber":"32",
    "addr:postcode":"1180",
    "addr:street":"Schoon Uitzichtlaan;/",
    "iso:country":"BE",
    "sg:address":"Schoon Uitzichtlaan 32",
    "sg:city":"Ukkel/uccle",
    "sg:orig_category":"Advocaten and juridische adviseurs",
    "sg:phone":"+32 2 344 18 35",
    "sg:postcode":"1180",
    "sg:province":"Bruxelles-Capitale",
    "wof:name":"M. Persoons",
    "wof:placetype":"venue"
},
  "geometry": {"coordinates":[4.3655290604,50.8129882812],"type":"Point"}
}