{
  "type": "Feature",
  "properties": {
    "addr:full":"Zoerselbaan 127 Malle Antwerpen 2390",
    "addr:housenumber":"127",
    "addr:postcode":"2390",
    "iso:country":"BE",
    "sg:address":"Zoerselbaan 127",
    "sg:city":"Malle",
    "sg:orig_category":"Gespecialiseerde residenti\u00eble bouw",
    "sg:phone":"+32 3 312 35 60",
    "sg:postcode":"2390",
    "sg:province":"Antwerpen",
    "wof:name":"Peeters",
    "wof:placetype":"venue"
},
  "geometry": {"coordinates":[4.7047719955,51.2850456238],"type":"Point"}
}