{
  "type": "Feature",
  "properties": {
    "iso:country":"BE",
    "sg:address":"Bonnerue 31",
    "sg:city":"Houffalize",
    "sg:orig_category":"Eleveurs de bovins",
    "sg:phone":"+32 61 28 82 21",
    "sg:postcode":"6663",
    "sg:province":"Luxembourg",
    "wof:name":"Francois Mathu",
    "wof:placetype":"venue"
},
  "geometry": {"coordinates":[5.7225131989,50.1190681458],"type":"Point"}
}