{
  "type": "Feature",
  "properties": {
    "iso:country":"BE",
    "sg:address":"Rue En-glain 7",
    "sg:city":"Liege",
    "sg:orig_category":"Ordinateurs and \u00e9quipement informatique",
    "sg:phone":"+32 4 224 09 32",
    "sg:postcode":"4000",
    "sg:province":"Li\u00e8ge",
    "wof:name":"Philippe Dujardin",
    "wof:placetype":"venue"
},
  "geometry": {"coordinates":[5.5491418839,50.6479034424],"type":"Point"}
}