{
  "type": "Feature",
  "properties": {
    "addr:full":"Rogierlaan 33 Oostende West-Vlaanderen 8400",
    "addr:housenumber":"33",
    "addr:postcode":"8400",
    "addr:street":"Rogierlaan",
    "iso:country":"BE",
    "sg:address":"Rogierlaan 33",
    "sg:city":"Oostende",
    "sg:classifiers":[
        {
            "category":"Health Services",
            "subcategory":"Health Practitioner",
            "type":"Services"
        }
    ],
    "sg:phone":"+32 59 50 61 87",
    "sg:postcode":"8400",
    "sg:province":"West-Vlaanderen",
    "sg:tags":[
        "physiotherapist"
    ],
    "wof:name":"Allard D",
    "wof:placetype":"venue"
},
  "geometry": {"coordinates":[2.9112770557,51.2269096375],"type":"Point"}
}