{
  "type": "Feature",
  "properties": {
    "addr:full":"Sint-truidensesteenweg 76 Zoutleeuw Vlaams-Brabant 3440",
    "addr:housenumber":"76",
    "addr:postcode":"3440",
    "addr:street":"Sint-Truidensesteenweg;Vlaams-Brabant",
    "iso:country":"BE",
    "sg:address":"Sint-truidensesteenweg 76",
    "sg:city":"Zoutleeuw",
    "sg:classifiers":[
        {
            "category":"Health Services",
            "subcategory":"Health Practitioner",
            "type":"Services"
        }
    ],
    "sg:phone":"+32 11 78 05 04",
    "sg:postcode":"3440",
    "sg:province":"Vlaams-Brabant",
    "sg:tags":[
        "physiotherapist"
    ],
    "wof:name":"Vanlaer Roger",
    "wof:placetype":"venue"
},
  "geometry": {"coordinates":[5.1157197952,50.8287887573],"type":"Point"}
}