{
  "type": "Feature",
  "properties": {
    "iso:country":"BE",
    "sg:address":"F. N\u00e8ve De M\u00e9vergniesstraat 4",
    "sg:city":"Merelbeke (bottelare)",
    "sg:classifiers":[
        {
            "category":"Retail",
            "subcategory":"Repair Shop",
            "type":"Services"
        }
    ],
    "sg:phone":"+32 9 362 61 43",
    "sg:postcode":"9820",
    "sg:province":"Oost-Vlaanderen",
    "sg:tags":[
        "-",
        "mainten",
        "watch",
        "clock"
    ],
    "wof:name":"Lagaert R",
    "wof:placetype":"venue"
},
  "geometry": {"coordinates":[3.7551629543,50.9635772705],"type":"Point"}
}