{
  "type": "Feature",
  "properties": {
    "addr:full":"Vossemberg 9 Tervuren Vlaams-Brabant 3080",
    "addr:housenumber":"9",
    "addr:postcode":"3080",
    "addr:street":"Vossemberg",
    "iso:country":"BE",
    "sg:address":"Vossemberg 9",
    "sg:city":"Tervuren",
    "sg:orig_category":"Epiceries",
    "sg:phone":"+32 2 767 55 03",
    "sg:postcode":"3080",
    "sg:province":"Vlaams-Brabant",
    "wof:name":"G. Thuriot",
    "wof:placetype":"venue"
},
  "geometry": {"coordinates":[4.5650568008,50.832824707],"type":"Point"}
}