{
  "type": "Feature",
  "properties": {
    "addr:full":"Antwerpsesteenweg 233 Vosselaar Antwerpen 2350",
    "addr:housenumber":"233",
    "addr:postcode":"2350",
    "addr:street":"Antwerpsesteenweg",
    "iso:country":"BE",
    "sg:address":"Antwerpsesteenweg 233",
    "sg:city":"Vosselaar",
    "sg:classifiers":[
        {
            "category":"Professional",
            "subcategory":"Accounting & Tax Preparation",
            "type":"Services"
        }
    ],
    "sg:phone":"+32 14 61 62 72",
    "sg:postcode":"2350",
    "sg:province":"Antwerpen",
    "sg:tags":[
        "accountant"
    ],
    "wof:name":"Van Gils Jos",
    "wof:placetype":"venue"
},
  "geometry": {"coordinates":[4.8725981712,51.3125114441],"type":"Point"}
}