{
  "type": "Feature",
  "properties": {
    "addr:full":"Rue Colonel Bourg 50 Bruxelles (schaerbeek) Bruxelles-Capitale 1030",
    "addr:housenumber":"50",
    "addr:postcode":"1030",
    "addr:street":"Rue Colonel Bourg",
    "iso:country":"BE",
    "sg:address":"Rue Colonel Bourg 50",
    "sg:city":"Bruxelles (schaerbeek)",
    "sg:classifiers":[
        {
            "category":"Communications",
            "subcategory":"Film & Video Production",
            "type":"Services"
        }
    ],
    "sg:phone":"+32 2 705 64 14",
    "sg:postcode":"1030",
    "sg:province":"Bruxelles-Capitale",
    "sg:tags":[
        "realisation",
        "-"
    ],
    "wof:name":"Kadenza Media",
    "wof:placetype":"venue"
},
  "geometry": {"coordinates":[4.4057531357,50.8517189026],"type":"Point"}
}