{
  "type": "Feature",
  "properties": {
    "iso:country":"BE",
    "sg:address":"Rue Lumsonry 54",
    "sg:city":"Walcourt (tarcienne)",
    "sg:classifiers":[
        {
            "category":"Real Estate",
            "subcategory":"Surveying",
            "type":"Services"
        }
    ],
    "sg:phone":"+32 71 22 06 01",
    "sg:postcode":"5651",
    "sg:province":"Namur",
    "sg:tags":[
        "surveyor",
        "land"
    ],
    "wof:name":"Philippart D",
    "wof:placetype":"venue"
},
  "geometry": {"coordinates":[4.4714741707,50.3113517761],"type":"Point"}
}