{
  "type": "Feature",
  "properties": {
    "addr:full":"Cesar Van Kerckhovenstraat 44 Bornem (hingene) Antwerpen 2880",
    "addr:housenumber":"44",
    "addr:postcode":"2880",
    "addr:street":"Cesar Van Kerckhovenstraat",
    "iso:country":"BE",
    "sg:address":"Cesar Van Kerckhovenstraat 44",
    "sg:city":"Bornem (hingene)",
    "sg:classifiers":[
        {
            "category":"Building & Trades",
            "subcategory":"Pest Control",
            "type":"Services"
        }
    ],
    "sg:phone":"+32 3 889 84 66",
    "sg:postcode":"2880",
    "sg:province":"Antwerpen",
    "sg:tags":[
        "painting",
        "contractor"
    ],
    "wof:name":"Aljomat",
    "wof:placetype":"venue"
},
  "geometry": {"coordinates":[4.2680101395,51.0967407227],"type":"Point"}
}