{
  "type": "Feature",
  "properties": {
    "addr:full":"Henri Horriestraat 35 Roeselare West-Vlaanderen 8800",
    "addr:housenumber":"35",
    "addr:postcode":"8800",
    "addr:street":"Henri Horriestraat",
    "iso:country":"BE",
    "sg:address":"Henri Horriestraat 35",
    "sg:city":"Roeselare",
    "sg:orig_category":"Action sociale avec h\u00e9bergement",
    "sg:phone":"+32 51 26 53 00",
    "sg:postcode":"8800",
    "sg:province":"West-Vlaanderen",
    "wof:name":"Dienst Maatschapp. Werk",
    "wof:placetype":"venue"
},
  "geometry": {"coordinates":[3.1239330769,50.9477577209],"type":"Point"}
}