{
  "type": "Feature",
  "properties": {
    "iso:country":"BE",
    "sg:address":"Hameau De G\u00c9ronsart 17",
    "sg:city":"Couvin",
    "sg:orig_category":"Maisons de vacances",
    "sg:phone":"+32 60 31 23 03",
    "sg:postcode":"5660",
    "sg:province":"Namur",
    "wof:name":"La Petite Cense",
    "wof:placetype":"venue"
},
  "geometry": {"coordinates":[4.4781031609,50.1047172546],"type":"Point"}
}