{
  "type": "Feature",
  "properties": {
    "iso:country":"BE",
    "sg:address":"Koevoetveld 1",
    "sg:city":"Zedelgem",
    "sg:orig_category":"Rundveehouders Varkenskwekers",
    "sg:phone":"+32 50 20 18 26",
    "sg:postcode":"8210",
    "sg:province":"West-Vlaanderen",
    "wof:name":"Maurits Devriendt",
    "wof:placetype":"venue"
},
  "geometry": {"coordinates":[3.1174108982,51.1296653748],"type":"Point"}
}