{
  "type": "Feature",
  "properties": {
    "addr:full":"Coupure Links 625 Gent Oost-Vlaanderen 9000",
    "addr:housenumber":"625",
    "addr:postcode":"9000",
    "addr:street":"Coupure Links;Oost-Vlaanderen",
    "iso:country":"BE",
    "sg:address":"Coupure Links 625",
    "sg:city":"Gent",
    "sg:classifiers":[
        {
            "category":"Bars & Pubs",
            "type":"Food & Drink"
        }
    ],
    "sg:phone":"+32 9 266 18 93",
    "sg:postcode":"9000",
    "sg:province":"Oost-Vlaanderen",
    "wof:name":"Netspace",
    "wof:placetype":"venue"
},
  "geometry": {"coordinates":[3.709346056,51.0522613525],"type":"Point"}
}