{
  "type": "Feature",
  "properties": {
    "addr:full":"Trapstraat 125 Geraardsbergen Oost-Vlaanderen 9500",
    "addr:housenumber":"125",
    "addr:postcode":"9500",
    "addr:street":"Trapstraat",
    "iso:country":"BE",
    "sg:address":"Trapstraat 125",
    "sg:city":"Geraardsbergen",
    "sg:classifiers":[
        {
            "category":"Food & Beverages",
            "subcategory":"Fruits & Vegetables",
            "type":"Retail Goods"
        }
    ],
    "sg:phone":"+32 54 58 08 74",
    "sg:postcode":"9500",
    "sg:province":"Oost-Vlaanderen",
    "sg:tags":[
        "l\u00e9gumes",
        "gr"
    ],
    "wof:name":"Verstuin",
    "wof:placetype":"venue"
},
  "geometry": {"coordinates":[3.9128708839,50.7333221436],"type":"Point"}
}