{
  "type": "Feature",
  "properties": {
    "iso:country":"BE",
    "sg:address":"Rue De Liege 7a Fontenaille",
    "sg:city":"Houffalize",
    "sg:classifiers":[
        {
            "category":"Home & Garden",
            "subcategory":"Hardware",
            "type":"Retail Goods"
        }
    ],
    "sg:phone":"+32 61 28 80 52",
    "sg:postcode":"6660",
    "sg:province":"Luxembourg",
    "sg:tags":[
        "agricultural",
        "implement"
    ],
    "wof:name":"Atelier J.p. Eschette",
    "wof:placetype":"venue"
},
  "geometry": {"coordinates":[5.7902050018,50.1322784424],"type":"Point"}
}