{
  "type": "Feature",
  "properties": {
    "addr:full":"Forendijs 1 Hoeilaart Vlaams-Brabant 1560",
    "addr:housenumber":"1",
    "addr:postcode":"1560",
    "addr:street":"Forendijs",
    "iso:country":"BE",
    "sg:address":"Forendijs 1",
    "sg:city":"Hoeilaart",
    "sg:orig_category":"Installation \u00e9lectrique industrielle. Installation \u00e9lectrique r\u00e9sidentielle",
    "sg:phone":"+32 2 657 94 65",
    "sg:postcode":"1560",
    "sg:province":"Vlaams-Brabant",
    "wof:name":"Seldis",
    "wof:placetype":"venue"
},
  "geometry": {"coordinates":[4.5041408539,50.7622528076],"type":"Point"}
}