{
  "type": "Feature",
  "properties": {
    "addr:full":"Koningin Astridplein 1 Antwerpen Antwerpen 2018",
    "addr:housenumber":"1",
    "addr:postcode":"2018",
    "addr:street":"Koningin Astridplein",
    "iso:country":"BE",
    "sg:address":"Koningin Astridplein 1",
    "sg:city":"Antwerpen",
    "sg:classifiers":[
        {
            "category":"Travel",
            "subcategory":"Hotels & Motels",
            "type":"Entertainment"
        }
    ],
    "sg:phone":"+32 3 203 12 34",
    "sg:postcode":"2018",
    "sg:province":"Antwerpen",
    "sg:tags":[
        "hotels",
        "business",
        "restaurant"
    ],
    "wof:name":"Astrid Park Plaza Nv",
    "wof:placetype":"venue"
},
  "geometry": {"coordinates":[4.421020031,51.217464447],"type":"Point"}
}