{
  "type": "Feature",
  "properties": {
    "iso:country":"BE",
    "sg:address":"Boulevard Barth\u00e9l\u00e9my 12-13",
    "sg:city":"Bruxelles",
    "sg:classifiers":[
        {
            "category":"Retail",
            "subcategory":"Auto Repair",
            "type":"Services"
        }
    ],
    "sg:phone":"+32 2 511 68 41",
    "sg:postcode":"1000",
    "sg:province":"Bruxelles-Capitale",
    "sg:tags":[
        "garage"
    ],
    "wof:name":"M.j. International Cars Spr",
    "wof:placetype":"venue"
},
  "geometry": {"coordinates":[4.3409619331,50.8523635864],"type":"Point"}
}