{
  "type": "Feature",
  "properties": {
    "iso:country":"BE",
    "sg:address":"Ninoofsesteenweg 48",
    "sg:city":"Lennik (sint-martens-lennik)",
    "sg:classifiers":[
        {
            "category":"Professional",
            "subcategory":"Testing Lab",
            "type":"Services"
        }
    ],
    "sg:phone":"+32 2 582 48 93",
    "sg:postcode":"1750",
    "sg:province":"Vlaams-Brabant",
    "sg:tags":[
        "chemist"
    ],
    "wof:name":"Hertecant V",
    "wof:placetype":"venue"
},
  "geometry": {"coordinates":[4.1497960091,50.8350524902],"type":"Point"}
}