{
  "type": "Feature",
  "properties": {
    "addr:full":"Broekweg 12 Berlaar Antwerpen 2590",
    "addr:housenumber":"12",
    "addr:postcode":"2590",
    "addr:street":"Broekweg",
    "iso:country":"BE",
    "sg:address":"Broekweg 12",
    "sg:city":"Berlaar",
    "sg:orig_category":"Eleveurs and marchands de porcs",
    "sg:phone":"+32 15 24 71 14",
    "sg:postcode":"2590",
    "sg:province":"Antwerpen",
    "wof:name":"Gommaar Leys",
    "wof:placetype":"venue"
},
  "geometry": {"coordinates":[4.6897549629,51.0964622498],"type":"Point"}
}