{
  "type": "Feature",
  "properties": {
    "iso:country":"BE",
    "sg:address":"Avenue Du Ciseau 6",
    "sg:city":"Ottignies-louvain-la-neuve (louvain-la-neuve)",
    "sg:classifiers":[
        {
            "category":"Organizations",
            "subcategory":"Community Association",
            "type":"Services"
        }
    ],
    "sg:phone":"+32 10 45 16 90",
    "sg:postcode":"1348",
    "sg:province":"Brabant Wallon",
    "sg:tags":[
        "cultural"
    ],
    "wof:name":"Jeunes Pour La Vie",
    "wof:placetype":"venue"
},
  "geometry": {"coordinates":[4.6116228104,50.6668701172],"type":"Point"}
}