{
  "type": "Feature",
  "properties": {
    "iso:country":"BE",
    "sg:address":"Rue De Villers 48",
    "sg:city":"Awans (hognoul)",
    "sg:classifiers":[
        {
            "category":"Professional",
            "subcategory":"Accounting & Tax Preparation",
            "type":"Services"
        }
    ],
    "sg:phone":"+32 4 257 57 76",
    "sg:postcode":"4342",
    "sg:province":"Li\u00e8ge",
    "sg:tags":[
        "bookkeeper"
    ],
    "wof:name":"Marquet V",
    "wof:placetype":"venue"
},
  "geometry": {"coordinates":[5.450056076,50.6847305298],"type":"Point"}
}