{
  "type": "Feature",
  "properties": {
    "addr:full":"Boulevard De L'humanit\u00c9 435 Drogenbos Vlaams-Brabant 1620",
    "addr:housenumber":"435",
    "addr:postcode":"1620",
    "addr:street":"Boulevard De L'Humanite \u0301",
    "iso:country":"BE",
    "sg:address":"Boulevard De L'humanit\u00c9 435",
    "sg:city":"Drogenbos",
    "sg:orig_category":"Agences de publicit\u00e9",
    "sg:phone":"+32 2 378 03 55",
    "sg:postcode":"1620",
    "sg:province":"Vlaams-Brabant",
    "wof:name":"Lettra",
    "wof:placetype":"venue"
},
  "geometry": {"coordinates":[4.3040289879,50.7969512939],"type":"Point"}
}