{
  "type": "Feature",
  "properties": {
    "iso:country":"BE",
    "sg:address":"Rue Blaes 177",
    "sg:city":"Bruxelles",
    "sg:classifiers":[
        {
            "category":"Bakery",
            "type":"Food & Drink"
        }
    ],
    "sg:phone":"+32 2 503 20 11",
    "sg:postcode":"1000",
    "sg:province":"Bruxelles-Capitale",
    "sg:tags":[
        "confectioner",
        "baker"
    ],
    "wof:name":"Nouveaux Delices D'orient",
    "wof:placetype":"venue"
},
  "geometry": {"coordinates":[4.3453230858,50.8363494873],"type":"Point"}
}