{
  "type": "Feature",
  "properties": {
    "iso:country":"BE",
    "sg:address":"Chemin Saint-martin 38",
    "sg:city":"Marche-en-famenne",
    "sg:orig_category":"Enseignement maternel and primaire",
    "sg:phone":"+32 84 31 22 59",
    "sg:postcode":"6900",
    "sg:province":"Luxembourg",
    "wof:name":"E.f.l. St.remacle",
    "wof:placetype":"venue"
},
  "geometry": {"coordinates":[5.3312277794,50.2323112488],"type":"Point"}
}