{
  "type": "Feature",
  "properties": {
    "iso:country":"BE",
    "sg:address":"Bredabaan 782a",
    "sg:city":"Brasschaat",
    "sg:classifiers":[
        {
            "category":"Personal",
            "subcategory":"Beauty Salon",
            "type":"Services"
        }
    ],
    "sg:phone":"+32 3 663 24 63",
    "sg:postcode":"2930",
    "sg:province":"Antwerpen",
    "sg:tags":[
        "lady",
        "-",
        "hairdressing"
    ],
    "wof:name":"Hippe Snit Bvba",
    "wof:placetype":"venue"
},
  "geometry": {"coordinates":[4.5202898979,51.3237190247],"type":"Point"}
}