{
  "type": "Feature",
  "properties": {
    "iso:country":"BE",
    "sg:address":"Frans Musinstraat 48",
    "sg:city":"Oostende",
    "sg:classifiers":[
        {
            "category":"Professional",
            "subcategory":"Management & Consulting",
            "type":"Services"
        }
    ],
    "sg:phone":"+32 59 51 59 41",
    "sg:postcode":"8400",
    "sg:province":"West-Vlaanderen",
    "sg:tags":[
        "consultant",
        "agency",
        "advertising"
    ],
    "wof:name":"Transparant",
    "wof:placetype":"venue"
},
  "geometry": {"coordinates":[2.9039239883,51.2242469788],"type":"Point"}
}