{
  "type": "Feature",
  "properties": {
    "addr:full":"Jozef Plateaustraat 1 Gent Oost-Vlaanderen 9000",
    "addr:housenumber":"1",
    "addr:postcode":"9000",
    "addr:street":"Jozef Plateaustraat;Oost-Vlaanderen",
    "iso:country":"BE",
    "sg:address":"Jozef Plateaustraat 1",
    "sg:city":"Gent",
    "sg:classifiers":[
        {
            "category":"Shopping",
            "subcategory":"Optician",
            "type":"Retail Goods"
        }
    ],
    "sg:phone":"+32 9 225 78 78",
    "sg:postcode":"9000",
    "sg:province":"Oost-Vlaanderen",
    "sg:tags":[
        "-"
    ],
    "wof:name":"Optiek Jo Dirickx Nv",
    "wof:placetype":"venue"
},
  "geometry": {"coordinates":[3.7224709988,51.0462837219],"type":"Point"}
}