{
  "type": "Feature",
  "properties": {
    "iso:country":"BE",
    "sg:address":"T' Serclaesstraat 1",
    "sg:city":"Ternat",
    "sg:orig_category":"Alternatieve geneeskunde Artsen and specialisten",
    "sg:phone":"+32 2 582 41 36",
    "sg:postcode":"1740",
    "sg:province":"Vlaams-Brabant",
    "wof:name":"Van Rampelbergh Suzanne",
    "wof:placetype":"venue"
},
  "geometry": {"coordinates":[4.172522068,50.8696861267],"type":"Point"}
}