{
  "type": "Feature",
  "properties": {
    "iso:country":"BE",
    "sg:address":"Rechtstraat 372",
    "sg:city":"Lokeren (eksaarde)",
    "sg:classifiers":[
        {
            "category":"Structure",
            "subcategory":"Office Building",
            "type":"Public Place"
        }
    ],
    "sg:phone":"+32 9 346 66 76",
    "sg:postcode":"9160",
    "sg:province":"Oost-Vlaanderen",
    "sg:tags":[
        "drawing"
    ],
    "wof:name":"Dds Engineering",
    "wof:placetype":"venue"
},
  "geometry": {"coordinates":[3.9152810574,51.1322174072],"type":"Point"}
}