{
  "type": "Feature",
  "properties": {
    "iso:country":"BE",
    "sg:address":"Stationsstraat 50",
    "sg:city":"Mechelen",
    "sg:orig_category":"Syndicats",
    "sg:phone":"+32 15 41 28 44",
    "sg:postcode":"2800",
    "sg:province":"Antwerpen",
    "wof:name":"A.b.v.v.-sector Mechelen",
    "wof:placetype":"venue"
},
  "geometry": {"coordinates":[4.4829239845,51.0184936523],"type":"Point"}
}