{
  "type": "Feature",
  "properties": {
    "iso:country":"BE",
    "sg:address":"Wijngaardlaan 13",
    "sg:city":"Schoten",
    "sg:orig_category":"Alimentation sp\u00e9cialis\u00e9e",
    "sg:phone":"+32 3 685 14 75",
    "sg:postcode":"2900",
    "sg:province":"Antwerpen",
    "wof:name":"Trydidact",
    "wof:placetype":"venue"
},
  "geometry": {"coordinates":[4.4840078354,51.2532958984],"type":"Point"}
}