{
  "type": "Feature",
  "properties": {
    "addr:full":"Rue De Zone 24 Charleroi (mont-sur-marchienne) Hainaut 6032",
    "addr:housenumber":"24",
    "addr:postcode":"6032",
    "addr:street":"Rue De Zone",
    "iso:country":"BE",
    "sg:address":"Rue De Zone 24",
    "sg:city":"Charleroi (mont-sur-marchienne)",
    "sg:classifiers":[
        {
            "category":"Building & Trades",
            "subcategory":"Construction",
            "type":"Services"
        }
    ],
    "sg:phone":"+32 71 36 01 05",
    "sg:postcode":"6032",
    "sg:province":"Hainaut",
    "sg:tags":[
        "ceiling"
    ],
    "wof:name":"Betim",
    "wof:placetype":"venue"
},
  "geometry": {"coordinates":[4.3999948502,50.3965530396],"type":"Point"}
}