{
  "type": "Feature",
  "properties": {
    "iso:country":"BE",
    "sg:address":"Notstraat 64",
    "sg:city":"Asse",
    "sg:orig_category":"Artsen and specialisten",
    "sg:phone":"+32 2 452 44 99",
    "sg:postcode":"1730",
    "sg:province":"Vlaams-Brabant",
    "wof:name":"Sven Janssens",
    "wof:placetype":"venue"
},
  "geometry": {"coordinates":[4.1710238457,50.9144020081],"type":"Point"}
}