{
  "type": "Feature",
  "properties": {
    "iso:country":"BE",
    "sg:address":"Sint-denijsstraat 276",
    "sg:city":"Vorst/forest",
    "sg:orig_category":"HERSTELLING ELEKTRISCHE HUISHOUDAPPARATEN",
    "sg:phone":"+32 2 345 98 76",
    "sg:postcode":"1190",
    "sg:province":"Bruxelles-Capitale",
    "wof:name":"Techni Square",
    "wof:placetype":"venue"
},
  "geometry": {"coordinates":[4.3207411766,50.8202171326],"type":"Point"}
}