{
  "type": "Feature",
  "properties": {
    "addr:full":"Huisepontweg 93 Nazareth Oost-Vlaanderen 9810",
    "addr:housenumber":"93",
    "addr:postcode":"9810",
    "addr:street":"Huisepontweg",
    "iso:country":"BE",
    "sg:address":"Huisepontweg 93",
    "sg:city":"Nazareth",
    "sg:orig_category":"R\u00e9alisation de programmes and logiciels. Conseils en syst\u00e8mes informatiques",
    "sg:phone":"+32 9 380 15 20",
    "sg:postcode":"9810",
    "sg:province":"Oost-Vlaanderen",
    "wof:name":"Gwapo & Cie",
    "wof:placetype":"venue"
},
  "geometry": {"coordinates":[3.5724620819,50.9377059937],"type":"Point"}
}