{
  "type": "Feature",
  "properties": {
    "addr:full":"Rue De La Mouchelotte 1 Jemeppe-sur-sambre (mornimont) Namur 5190",
    "addr:housenumber":"1",
    "addr:postcode":"5190",
    "addr:street":"Rue De La Mouchelotte;Namur",
    "iso:country":"BE",
    "sg:address":"Rue De La Mouchelotte 1",
    "sg:city":"Jemeppe-sur-sambre (mornimont)",
    "sg:classifiers":[
        {
            "category":"Parking",
            "subcategory":"Garage",
            "type":"Transportation"
        }
    ],
    "sg:phone":"+32 71 78 58 19",
    "sg:postcode":"5190",
    "sg:province":"Namur",
    "sg:tags":[
        "truck",
        "-",
        "dump",
        "transport"
    ],
    "wof:name":"Verstraete Andre Sprl",
    "wof:placetype":"venue"
},
  "geometry": {"coordinates":[4.6703448296,50.4645042419],"type":"Point"}
}