{
  "type": "Feature",
  "properties": {
    "iso:country":"BE",
    "sg:address":"Rue Du Marteau 2",
    "sg:city":"Houyet",
    "sg:orig_category":"Enseignement maternel and primaire",
    "sg:phone":"+32 82 74 43 28",
    "sg:postcode":"5560",
    "sg:province":"Namur",
    "wof:name":"Ecole Fond. Communale",
    "wof:placetype":"venue"
},
  "geometry": {"coordinates":[5.0096511841,50.1858215332],"type":"Point"}
}