{
  "type": "Feature",
  "properties": {
    "addr:full":"Hazepad 28 Tessenderlo Limburg 3980",
    "addr:housenumber":"28",
    "addr:postcode":"3980",
    "addr:street":"Hazepad",
    "iso:country":"BE",
    "sg:address":"Hazepad 28",
    "sg:city":"Tessenderlo",
    "sg:orig_category":"Etablissements Erotiques",
    "sg:phone":"+32 13 66 33 59",
    "sg:postcode":"3980",
    "sg:province":"Limburg",
    "wof:name":"Eric Vandecasteele",
    "wof:placetype":"venue"
},
  "geometry": {"coordinates":[5.0519781113,51.0592536926],"type":"Point"}
}