{
  "type": "Feature",
  "properties": {
    "addr:full":"Rue Walth\u00e8re Jamar 102 Ans Li\u00e8ge 4430",
    "addr:housenumber":"102",
    "addr:postcode":"4430",
    "addr:street":"Rue Walthe\u0300Re Jamar",
    "iso:country":"BE",
    "sg:address":"Rue Walth\u00e8re Jamar 102",
    "sg:city":"Ans",
    "sg:classifiers":[
        {
            "category":"Health Services",
            "subcategory":"Health Practitioner",
            "type":"Services"
        }
    ],
    "sg:phone":"+32 4 247 40 06",
    "sg:postcode":"4430",
    "sg:province":"Li\u00e8ge",
    "sg:tags":[
        "physiotherapist"
    ],
    "wof:name":"Jadoul Thierry",
    "wof:placetype":"venue"
},
  "geometry": {"coordinates":[5.5402550697,50.6528816223],"type":"Point"}
}