{
  "type": "Feature",
  "properties": {
    "addr:full":"Kouterstraat 48 Temse Oost-Vlaanderen 9140",
    "addr:housenumber":"48",
    "addr:postcode":"9140",
    "addr:street":"Kouterstraat",
    "iso:country":"BE",
    "sg:address":"Kouterstraat 48",
    "sg:city":"Temse",
    "sg:classifiers":[
        {
            "category":"Personal",
            "subcategory":"Beauty Salon",
            "type":"Services"
        }
    ],
    "sg:phone":"+32 3 771 13 52",
    "sg:postcode":"9140",
    "sg:province":"Oost-Vlaanderen",
    "sg:tags":[
        "lady",
        "-",
        "hairdressing"
    ],
    "wof:name":"Figaro",
    "wof:placetype":"venue"
},
  "geometry": {"coordinates":[4.2155637741,51.1275138855],"type":"Point"}
}