{
  "type": "Feature",
  "properties": {
    "iso:country":"BE",
    "sg:address":"Rue Thomas Bonehill 30",
    "sg:city":"Charleroi (marchienne-au-pont)",
    "sg:classifiers":[
        {
            "category":"Freight",
            "type":"Transportation"
        }
    ],
    "sg:phone":"+32 71 47 85 04",
    "sg:postcode":"6030",
    "sg:province":"Hainaut",
    "sg:tags":[
        "-",
        "transport"
    ],
    "wof:name":"Michel Trans",
    "wof:placetype":"venue"
},
  "geometry": {"coordinates":[4.3949289322,50.4065132141],"type":"Point"}
}