{
  "type": "Feature",
  "properties": {
    "addr:full":"Antwerpsestraat 26 Mortsel Antwerpen 2640",
    "addr:housenumber":"26",
    "addr:postcode":"2640",
    "addr:street":"Antwerpsestraat",
    "iso:country":"BE",
    "sg:address":"Antwerpsestraat 26",
    "sg:city":"Mortsel",
    "sg:orig_category":"Tijdelijke werkgelegenheid and uitzendkantoren",
    "sg:phone":"+32 3 443 99 99",
    "sg:postcode":"2640",
    "sg:province":"Antwerpen",
    "wof:name":"Top Interim",
    "wof:placetype":"venue"
},
  "geometry": {"coordinates":[4.4486041069,51.1712341309],"type":"Point"}
}