{
  "type": "Feature",
  "properties": {
    "addr:full":"Rue De La Poire D'or 18 Mons (cuesmes) Hainaut 7033",
    "addr:housenumber":"18",
    "addr:postcode":"7033",
    "addr:street":"Rue De La Poire D'Or",
    "iso:country":"BE",
    "sg:address":"Rue De La Poire D'or 18",
    "sg:city":"Mons (cuesmes)",
    "sg:classifiers":[
        {
            "category":"Building & Trades",
            "subcategory":"Cleaning & Sanitation",
            "type":"Services"
        }
    ],
    "sg:phone":"+32 65 39 56 00",
    "sg:postcode":"7033",
    "sg:province":"Hainaut",
    "sg:tags":[
        "equipment",
        "industrial",
        "maintenance"
    ],
    "wof:name":"S.d.i. Sa",
    "wof:placetype":"venue"
},
  "geometry": {"coordinates":[3.9233601093,50.4335708618],"type":"Point"}
}