{
  "type": "Feature",
  "properties": {
    "addr:full":"Kerkplein 4 Zomergem (ronsele) Oost-Vlaanderen 9932",
    "addr:housenumber":"4",
    "addr:postcode":"9932",
    "addr:street":"Kerkplein",
    "iso:country":"BE",
    "sg:address":"Kerkplein 4",
    "sg:city":"Zomergem (ronsele)",
    "sg:classifiers":[
        {
            "category":"Bars & Pubs",
            "type":"Food & Drink"
        }
    ],
    "sg:phone":"+32 9 372 62 07",
    "sg:postcode":"9932",
    "sg:province":"Oost-Vlaanderen",
    "wof:name":"Gemeentehuis",
    "wof:placetype":"venue"
},
  "geometry": {"coordinates":[3.552257061,51.1306915283],"type":"Point"}
}