{
  "type": "Feature",
  "properties": {
    "addr:full":"Schaluin 51 Aarschot Vlaams-Brabant 3200",
    "addr:housenumber":"51",
    "addr:postcode":"3200",
    "addr:street":"Schaluin",
    "iso:country":"BE",
    "sg:address":"Schaluin 51",
    "sg:city":"Aarschot",
    "sg:classifiers":[
        {
            "category":"Shopping",
            "subcategory":"Computers & Home Electronics",
            "type":"Retail Goods"
        }
    ],
    "sg:phone":"+32 16 56 28 40",
    "sg:postcode":"3200",
    "sg:province":"Vlaams-Brabant",
    "sg:tags":[
        "-",
        "television",
        "radio"
    ],
    "wof:name":"Bergen-ballings Elektro Shop",
    "wof:placetype":"venue"
},
  "geometry": {"coordinates":[4.841026783,50.9896736145],"type":"Point"}
}