{
  "type": "Feature",
  "properties": {
    "iso:country":"BE",
    "sg:address":"Kronestraat 26",
    "sg:city":"Zedelgem",
    "sg:orig_category":"Fleurs and plantes",
    "sg:phone":"+32 50 24 18 94",
    "sg:postcode":"8210",
    "sg:province":"West-Vlaanderen",
    "wof:name":"Kristof Verdonck",
    "wof:placetype":"venue"
},
  "geometry": {"coordinates":[3.1250400543,51.1446151733],"type":"Point"}
}