{
  "type": "Feature",
  "properties": {
    "iso:country":"BE",
    "sg:address":"Snijwitstraat 36",
    "sg:city":"Houthalen-helchteren",
    "sg:orig_category":"Loodgieterij, verwarming and sanitaire installaties",
    "sg:phone":"+32 11 52 12 31",
    "sg:postcode":"3530",
    "sg:province":"Limburg",
    "wof:name":"Robert Vandebroek",
    "wof:placetype":"venue"
},
  "geometry": {"coordinates":[5.3943891525,51.0252685547],"type":"Point"}
}