{
  "type": "Feature",
  "properties": {
    "iso:country":"BE",
    "sg:address":"Rue Monplaisir 27",
    "sg:city":"Walcourt",
    "sg:orig_category":"HUISBRANDOLIE Tuinen",
    "sg:phone":"+32 71 65 00 81",
    "sg:postcode":"5650",
    "sg:province":"Namur",
    "wof:name":"Philippe Gille",
    "wof:placetype":"venue"
},
  "geometry": {"coordinates":[4.4313349724,50.2514762878],"type":"Point"}
}