{
  "type": "Feature",
  "properties": {
    "iso:country":"BE",
    "sg:address":"Chauss\u00e9e De La Hulpe 150 Box 1",
    "sg:city":"Bruxelles (watermael-boitsfort)",
    "sg:classifiers":[
        {
            "category":"Social Services",
            "subcategory":"Job Training",
            "type":"Services"
        }
    ],
    "sg:phone":"+32 2 663 15 00",
    "sg:postcode":"1170",
    "sg:province":"Bruxelles-Capitale",
    "sg:tags":[
        "barcode",
        "scanner",
        "printer"
    ],
    "wof:name":"Symbol Technologies International",
    "wof:placetype":"venue"
},
  "geometry": {"coordinates":[4.4013972282,50.7964324951],"type":"Point"}
}