{
  "type": "Feature",
  "properties": {
    "addr:full":"Nieuweweg 12 Evergem Oost-Vlaanderen 9940",
    "addr:housenumber":"12",
    "addr:postcode":"9940",
    "addr:street":"Nieuweweg;Oost-Vlaanderen",
    "iso:country":"BE",
    "sg:address":"Nieuweweg 12",
    "sg:city":"Evergem",
    "sg:classifiers":[
        {
            "category":"Food & Beverages",
            "subcategory":"Fruits & Vegetables",
            "type":"Retail Goods"
        }
    ],
    "sg:phone":"+32 9 357 42 19",
    "sg:postcode":"9940",
    "sg:province":"Oost-Vlaanderen",
    "sg:tags":[
        "gum"
    ],
    "wof:name":"Confiserie 2ooo Nv",
    "wof:placetype":"venue"
},
  "geometry": {"coordinates":[3.7045168877,51.1464042664],"type":"Point"}
}