{
  "type": "Feature",
  "properties": {
    "iso:country":"BE",
    "sg:address":"Rue Masuy 85",
    "sg:city":"Herstal",
    "sg:orig_category":"Services fun\u00e9raires. Fleurs and plantes",
    "sg:phone":"+32 4 278 50 44",
    "sg:postcode":"4041",
    "sg:province":"Li\u00e8ge",
    "wof:name":"Fleurs J.c Philippet",
    "wof:placetype":"venue"
},
  "geometry": {"coordinates":[5.5975680351,50.6883811951],"type":"Point"}
}