{
  "type": "Feature",
  "properties": {
    "addr:full":"Steenstraat 63 Kortemark West-Vlaanderen 8610",
    "addr:housenumber":"63",
    "addr:postcode":"8610",
    "addr:street":"Steenstraat",
    "iso:country":"BE",
    "sg:address":"Steenstraat 63",
    "sg:city":"Kortemark",
    "sg:classifiers":[
        {
            "category":"Insurance",
            "subcategory":"Life Insurance",
            "type":"Services"
        }
    ],
    "sg:phone":"+32 51 56 80 53",
    "sg:postcode":"8610",
    "sg:province":"West-Vlaanderen",
    "sg:tags":[
        "assurance"
    ],
    "wof:name":"Maertens-lambert",
    "wof:placetype":"venue"
},
  "geometry": {"coordinates":[2.9685199261,51.0381622314],"type":"Point"}
}