{
  "type": "Feature",
  "properties": {
    "addr:full":"Rue De La Semois 54 Arlon Luxembourg 6700",
    "addr:housenumber":"54",
    "addr:postcode":"6700",
    "addr:street":"Rue De La Semois",
    "iso:country":"BE",
    "sg:address":"Rue De La Semois 54",
    "sg:city":"Arlon",
    "sg:orig_category":"Voertuigen",
    "sg:phone":"+32 63 21 74 78",
    "sg:postcode":"6700",
    "sg:province":"Luxembourg",
    "wof:name":"Auto Belot",
    "wof:placetype":"venue"
},
  "geometry": {"coordinates":[5.809035778,49.6786422729],"type":"Point"}
}