{
  "type": "Feature",
  "properties": {
    "addr:full":"Kardinaal Cardijnstraat 8bd Zwevegem West-Vlaanderen 8550",
    "addr:postcode":"8bd;8550",
    "addr:street":"Kardinaal Cardijnstraat",
    "iso:country":"BE",
    "sg:address":"Kardinaal Cardijnstraat 8bd",
    "sg:city":"Zwevegem",
    "sg:orig_category":"Ordinateurs and \u00e9quipement informatique",
    "sg:phone":"+32 56 75 39 78",
    "sg:postcode":"8550",
    "sg:province":"West-Vlaanderen",
    "wof:name":"D.c.s.",
    "wof:placetype":"venue"
},
  "geometry": {"coordinates":[3.3219850063,50.8118133545],"type":"Point"}
}