{
  "type": "Feature",
  "properties": {
    "iso:country":"BE",
    "sg:address":"Albrecht Rodenbachlaan 65",
    "sg:city":"Heule",
    "sg:classifiers":[
        {
            "category":"Government",
            "subcategory":"Office",
            "type":"Public Place"
        }
    ],
    "sg:phone":"+32 56 22 08 85",
    "sg:postcode":"8501",
    "sg:province":"West-Vlaanderen",
    "sg:tags":[
        "building",
        "industrial",
        "equipping",
        "furnishing"
    ],
    "wof:name":"Delobelle Jozef B.v.b.a.",
    "wof:placetype":"venue"
},
  "geometry": {"coordinates":[3.235532999,50.8376502991],"type":"Point"}
}