{
  "type": "Feature",
  "properties": {
    "addr:full":"Rue Du Grand Feu 70 Namur (bouge) Namur 5004",
    "addr:housenumber":"70",
    "addr:postcode":"5004",
    "addr:street":"Rue Du Grand Feu",
    "iso:country":"BE",
    "sg:address":"Rue Du Grand Feu 70",
    "sg:city":"Namur (bouge)",
    "sg:classifiers":[
        {
            "category":"Shopping",
            "subcategory":"Computers & Home Electronics",
            "type":"Retail Goods"
        }
    ],
    "sg:phone":"+32 81 21 34 60",
    "sg:postcode":"5004",
    "sg:province":"Namur",
    "sg:tags":[
        "spare",
        "part",
        "processing",
        "-",
        "data"
    ],
    "wof:name":"Pulsar-belgium",
    "wof:placetype":"venue"
},
  "geometry": {"coordinates":[4.8957629204,50.4720344543],"type":"Point"}
}