{
  "type": "Feature",
  "properties": {
    "addr:full":"Rue De La Chapelle 3 Hannut Li\u00e8ge 4280",
    "addr:housenumber":"3",
    "addr:postcode":"4280",
    "addr:street":"Rue De La Chapelle",
    "iso:country":"BE",
    "sg:address":"Rue De La Chapelle 3",
    "sg:city":"Hannut",
    "sg:orig_category":"Eleveurs and marchands de porcs",
    "sg:phone":"+32 81 85 59 25",
    "sg:postcode":"4280",
    "sg:province":"Li\u00e8ge",
    "wof:name":"Guy Baugniet",
    "wof:placetype":"venue"
},
  "geometry": {"coordinates":[4.9994740486,50.6556777954],"type":"Point"}
}