{
  "type": "Feature",
  "properties": {
    "addr:full":"Edgard Tinelstraat 21 Vilvoorde Vlaams-Brabant 1800",
    "addr:housenumber":"21",
    "addr:postcode":"1800",
    "addr:street":"Edgard Tinelstraat",
    "iso:country":"BE",
    "sg:address":"Edgard Tinelstraat 21",
    "sg:city":"Vilvoorde",
    "sg:orig_category":"Brood, gebak and snoepgoed",
    "sg:phone":"+32 2 251 17 44",
    "sg:postcode":"1800",
    "sg:province":"Vlaams-Brabant",
    "wof:name":"Nancy Clement",
    "wof:placetype":"venue"
},
  "geometry": {"coordinates":[4.431828022,50.9333267212],"type":"Point"}
}