{
  "type": "Feature",
  "properties": {
    "iso:country":"BE",
    "sg:address":"Op De Muur 1a",
    "sg:city":"Landen",
    "sg:orig_category":"V\u00e9los",
    "sg:phone":"+32 11 83 15 69",
    "sg:postcode":"3400",
    "sg:province":"Vlaams-Brabant",
    "wof:name":"M.j.p.",
    "wof:placetype":"venue"
},
  "geometry": {"coordinates":[5.0790848732,50.7543907166],"type":"Point"}
}