{
  "type": "Feature",
  "properties": {
    "iso:country":"BE",
    "sg:address":"Hoogstraat 1",
    "sg:city":"Denderleeuw",
    "sg:orig_category":"Electrom\u00e9nager, t\u00e9l\u00e9visions and radios",
    "sg:phone":"+32 53 66 76 19",
    "sg:postcode":"9472",
    "sg:province":"Oost-Vlaanderen",
    "wof:name":"Huis Witterzeel",
    "wof:placetype":"venue"
},
  "geometry": {"coordinates":[4.0553340912,50.8755569458],"type":"Point"}
}