{
  "type": "Feature",
  "properties": {
    "addr:full":"Place Des Tilleuls 44 Andenne Namur 5300",
    "addr:housenumber":"44",
    "addr:postcode":"5300",
    "addr:street":"Place Des Tilleuls",
    "iso:country":"BE",
    "sg:address":"Place Des Tilleuls 44",
    "sg:city":"Andenne",
    "sg:orig_category":"Equipement photographique. Mat\u00e9riel de T\u00e9l\u00e9communication. Studios photographiques",
    "sg:phone":"+32 85 84 11 77",
    "sg:postcode":"5300",
    "sg:province":"Namur",
    "wof:name":"Photo Denis Claude & F",
    "wof:placetype":"venue"
},
  "geometry": {"coordinates":[5.0956301689,50.4896583557],"type":"Point"}
}