{
  "type": "Feature",
  "properties": {
    "addr:full":"Rue Denis Deghaye 18 Oupeye Li\u00e8ge 4680",
    "addr:housenumber":"18",
    "addr:postcode":"4680",
    "addr:street":"Rue Denis Deghaye",
    "iso:country":"BE",
    "sg:address":"Rue Denis Deghaye 18",
    "sg:city":"Oupeye",
    "sg:orig_category":"Tuinen",
    "sg:phone":"+32 4 264 60 88",
    "sg:postcode":"4680",
    "sg:province":"Li\u00e8ge",
    "wof:name":"Serge Ransy",
    "wof:placetype":"venue"
},
  "geometry": {"coordinates":[5.6416687965,50.7083511353],"type":"Point"}
}