{
  "type": "Feature",
  "properties": {
    "iso:country":"BE",
    "sg:address":"Avenue De Ragnies 2",
    "sg:city":"Thuin",
    "sg:classifiers":[
        {
            "category":"Utilities",
            "subcategory":"Refuse",
            "type":"Services"
        }
    ],
    "sg:phone":"+32 71 59 52 95",
    "sg:postcode":"6530",
    "sg:province":"Hainaut",
    "sg:tags":[
        "management",
        "waste"
    ],
    "wof:name":"Dechets Verts",
    "wof:placetype":"venue"
},
  "geometry": {"coordinates":[4.2803330421,50.3401451111],"type":"Point"}
}