{
  "type": "Feature",
  "properties": {
    "addr:full":"Jachtmeestersstraat 85 Edingen/enghien Hainaut 7850",
    "addr:housenumber":"85",
    "addr:postcode":"7850",
    "addr:street":"Jachtmeestersstraat",
    "iso:country":"BE",
    "sg:address":"Jachtmeestersstraat 85",
    "sg:city":"Edingen/enghien",
    "sg:orig_category":"Speelgoed",
    "sg:phone":"+32 2 395 55 43",
    "sg:postcode":"7850",
    "sg:province":"Hainaut",
    "wof:name":"Yves Lievin",
    "wof:placetype":"venue"
},
  "geometry": {"coordinates":[4.0334601402,50.6914787292],"type":"Point"}
}