{
  "type": "Feature",
  "properties": {
    "iso:country":"BE",
    "sg:address":"Kouterstraat 23",
    "sg:city":"Hamme",
    "sg:orig_category":"M\u00e9decines alternatives",
    "sg:phone":"+32 52 47 16 67",
    "sg:postcode":"9220",
    "sg:province":"Oost-Vlaanderen",
    "wof:name":"Marc Rupus - Baf",
    "wof:placetype":"venue"
},
  "geometry": {"coordinates":[4.1485600471,51.0655593872],"type":"Point"}
}