{
  "type": "Feature",
  "properties": {
    "iso:country":"BE",
    "sg:address":"Carrefour De L'europe",
    "sg:city":"Bruxelles",
    "sg:classifiers":[
        {
            "category":"Health Services",
            "subcategory":"Medical Lab",
            "type":"Services"
        }
    ],
    "sg:phone":"+32 2 513 35 93",
    "sg:postcode":"1000",
    "sg:province":"Bruxelles-Capitale",
    "sg:tags":[
        "chemical",
        "pharmaceutical",
        "pharmacy"
    ],
    "wof:name":"Les Pharmacies De Gare Sa",
    "wof:placetype":"venue"
},
  "geometry": {"coordinates":[4.3562541008,50.8458900452],"type":"Point"}
}