{
  "type": "Feature",
  "properties": {
    "addr:full":"Gevaartsestraat 100 Oostkamp West-Vlaanderen 8020",
    "addr:housenumber":"100",
    "addr:postcode":"8020",
    "addr:street":"Gevaartsestraat",
    "iso:country":"BE",
    "sg:address":"Gevaartsestraat 100",
    "sg:city":"Oostkamp",
    "sg:classifiers":[
        {
            "category":"Home & Garden",
            "subcategory":"Carpets & Floor Coverings",
            "type":"Retail Goods"
        }
    ],
    "sg:phone":"+32 50 82 49 14",
    "sg:postcode":"8020",
    "sg:province":"West-Vlaanderen",
    "sg:tags":[
        "layer",
        "mosaicists"
    ],
    "wof:name":"Kerckaert R",
    "wof:placetype":"venue"
},
  "geometry": {"coordinates":[3.2768259048,51.1494483948],"type":"Point"}
}