{
  "type": "Feature",
  "properties": {
    "iso:country":"BE",
    "sg:address":"Ninoofsesteenweg 34",
    "sg:city":"Halle",
    "sg:classifiers":[
        {
            "category":"Insurance",
            "subcategory":"Life Insurance",
            "type":"Services"
        }
    ],
    "sg:phone":"+32 2 356 56 57",
    "sg:postcode":"1500",
    "sg:province":"Vlaams-Brabant",
    "sg:tags":[
        "assurance"
    ],
    "wof:name":"Goossens Fran\u00c7ois",
    "wof:placetype":"venue"
},
  "geometry": {"coordinates":[4.2350301743,50.7374382019],"type":"Point"}
}