{
  "type": "Feature",
  "properties": {
    "iso:country":"BE",
    "sg:address":"Sint-martinusplein 9e",
    "sg:city":"Genk",
    "sg:classifiers":[
        {
            "category":"Structure",
            "subcategory":"Office Building",
            "type":"Public Place"
        }
    ],
    "sg:phone":"+32 477 29 62 46",
    "sg:postcode":"3600",
    "sg:province":"Limburg",
    "sg:tags":[
        "drawing"
    ],
    "wof:name":"Caelen K",
    "wof:placetype":"venue"
},
  "geometry": {"coordinates":[5.4980020523,50.9649429321],"type":"Point"}
}