{
  "type": "Feature",
  "properties": {
    "iso:country":"BE",
    "sg:address":"Boulevard Du Roi Albert 1",
    "sg:city":"Tournai",
    "sg:classifiers":[
        {
            "category":"Education",
            "subcategory":"University",
            "type":"Public Place"
        }
    ],
    "sg:phone":"+32 69 22 44 90",
    "sg:postcode":"7500",
    "sg:province":"Hainaut",
    "sg:tags":[
        "higher"
    ],
    "wof:name":"Ecole Provinciale D'infirmi\u00e8res Hepho",
    "wof:placetype":"venue"
},
  "geometry": {"coordinates":[3.3982489109,50.6002120972],"type":"Point"}
}