{
  "type": "Feature",
  "properties": {
    "iso:country":"BE",
    "sg:address":"Kloosterstraat 22",
    "sg:city":"Bornem",
    "sg:orig_category":"Begrafeniswezen",
    "sg:phone":"+32 3 899 22 86",
    "sg:postcode":"2880",
    "sg:province":"Antwerpen",
    "wof:name":"Rouwcentrum De Cock-baete",
    "wof:placetype":"venue"
},
  "geometry": {"coordinates":[4.2297282219,51.0961952209],"type":"Point"}
}