{
  "type": "Feature",
  "properties": {
    "addr:full":"Molenweg 177 Opglabbeek Limburg 3660",
    "addr:housenumber":"177",
    "addr:postcode":"3660",
    "addr:street":"Molenweg",
    "iso:country":"BE",
    "sg:address":"Molenweg 177",
    "sg:city":"Opglabbeek",
    "sg:classifiers":[
        {
            "category":"Restaurant",
            "type":"Food & Drink"
        }
    ],
    "sg:phone":"+32 89 85 48 88",
    "sg:postcode":"3660",
    "sg:province":"Limburg",
    "wof:name":"De Slagmolen",
    "wof:placetype":"venue"
},
  "geometry": {"coordinates":[5.6159591675,51.0431022644],"type":"Point"}
}