{
  "type": "Feature",
  "properties": {
    "iso:country":"BE",
    "sg:address":"Bruinbergstraat 8",
    "sg:city":"Ardooie",
    "sg:classifiers":[
        {
            "category":"Wholesale",
            "subcategory":"Seafood",
            "type":"Manufacturing & Wholesale Goods"
        }
    ],
    "sg:phone":"+32 51 74 44 84",
    "sg:postcode":"8850",
    "sg:province":"West-Vlaanderen",
    "sg:tags":[
        "whol",
        "fish",
        "-",
        "shellfish"
    ],
    "wof:name":"Goldfish",
    "wof:placetype":"venue"
},
  "geometry": {"coordinates":[3.1996788979,50.955116272],"type":"Point"}
}