{
  "type": "Feature",
  "properties": {
    "iso:country":"BE",
    "sg:address":"Prins Leopoldstraat 24",
    "sg:city":"Oudenaarde",
    "sg:classifiers":[
        {
            "category":"Health Services",
            "subcategory":"Dentist",
            "type":"Services"
        }
    ],
    "sg:phone":"+32 55 30 21 29",
    "sg:postcode":"9700",
    "sg:province":"Oost-Vlaanderen",
    "wof:name":"Vannieuwenhuyze Katrien",
    "wof:placetype":"venue"
},
  "geometry": {"coordinates":[3.6112399101,50.8479118347],"type":"Point"}
}