{
  "type": "Feature",
  "properties": {
    "addr:full":"Rue Ch\u00c2mont 26 La Roche-en-ardenne Luxembourg 6980",
    "addr:housenumber":"26",
    "addr:postcode":"6980",
    "addr:street":"Rue Cha\u0302Mont",
    "iso:country":"BE",
    "sg:address":"Rue Ch\u00c2mont 26",
    "sg:city":"La Roche-en-ardenne",
    "sg:orig_category":"Banken and kredietinstellingen",
    "sg:phone":"+32 84 41 28 14",
    "sg:postcode":"6980",
    "sg:province":"Luxembourg",
    "wof:name":"Axa",
    "wof:placetype":"venue"
},
  "geometry": {"coordinates":[5.5776629448,50.1843681335],"type":"Point"}
}