{
  "type": "Feature",
  "properties": {
    "addr:full":"Rietstraat 11 Oostende West-Vlaanderen 8400",
    "addr:housenumber":"11",
    "addr:postcode":"8400",
    "addr:street":"Rietstraat",
    "iso:country":"BE",
    "sg:address":"Rietstraat 11",
    "sg:city":"Oostende",
    "sg:orig_category":"Koekjes, gebak and taart Fab Kruideniers",
    "sg:phone":"+32 59 70 71 44",
    "sg:postcode":"8400",
    "sg:province":"West-Vlaanderen",
    "wof:name":"Daniel Gallin",
    "wof:placetype":"venue"
},
  "geometry": {"coordinates":[2.9108231068,51.2185325623],"type":"Point"}
}