{
  "type": "Feature",
  "properties": {
    "addr:full":"Rue De La Conserverie 3 Geer Li\u00e8ge 4250",
    "addr:housenumber":"3",
    "addr:postcode":"4250",
    "addr:street":"Rue De La Conserverie",
    "iso:country":"BE",
    "sg:address":"Rue De La Conserverie 3",
    "sg:city":"Geer",
    "sg:classifiers":[
        {
            "category":"Bakery",
            "type":"Food & Drink"
        }
    ],
    "sg:phone":"+32 19 58 81 54",
    "sg:postcode":"4250",
    "sg:province":"Li\u00e8ge",
    "sg:tags":[
        "confectioner",
        "baker"
    ],
    "wof:name":"Aliger",
    "wof:placetype":"venue"
},
  "geometry": {"coordinates":[5.173661232,50.669883728],"type":"Point"}
}