{
  "type": "Feature",
  "properties": {
    "addr:full":"Rue Du Fond D'or 44b Waremme Li\u00e8ge 4300",
    "addr:housenumber":"44b",
    "addr:postcode":"4300",
    "addr:street":"Rue Du Fond D'Or",
    "iso:country":"BE",
    "sg:address":"Rue Du Fond D'or 44b",
    "sg:city":"Waremme",
    "sg:classifiers":[
        {
            "category":"Home & Garden",
            "subcategory":"Building Materials",
            "type":"Retail Goods"
        }
    ],
    "sg:phone":"+32 19 32 28 77",
    "sg:postcode":"4300",
    "sg:province":"Li\u00e8ge",
    "sg:tags":[
        "window"
    ],
    "wof:name":"Gesco Sprl",
    "wof:placetype":"venue"
},
  "geometry": {"coordinates":[5.2565498352,50.6982498169],"type":"Point"}
}