{
  "type": "Feature",
  "properties": {
    "addr:full":"P. De Denterghemlaan 14 Sint-martens-latem Oost-Vlaanderen 9831",
    "addr:housenumber":"14",
    "addr:postcode":"9831",
    "addr:street":"P.;Denterghemlaan",
    "iso:country":"BE",
    "sg:address":"P. De Denterghemlaan 14",
    "sg:city":"Sint-martens-latem",
    "sg:orig_category":"Fitnesscentra Sportcentra",
    "sg:phone":"+32 9 282 74 08",
    "sg:postcode":"9831",
    "sg:province":"Oost-Vlaanderen",
    "wof:name":"Toningcentrum",
    "wof:placetype":"venue"
},
  "geometry": {"coordinates":[3.6032860279,51.0083999634],"type":"Point"}
}