{
  "type": "Feature",
  "properties": {
    "addr:full":"Hulst 38 Opwijk Vlaams-Brabant 1745",
    "addr:housenumber":"38",
    "addr:postcode":"1745",
    "addr:street":"Hulst",
    "iso:country":"BE",
    "sg:address":"Hulst 38",
    "sg:city":"Opwijk",
    "sg:orig_category":"Kinderopvang",
    "sg:phone":"+32 52 35 13 68",
    "sg:postcode":"1745",
    "sg:province":"Vlaams-Brabant",
    "wof:name":"Kribbe Nijntje",
    "wof:placetype":"venue"
},
  "geometry": {"coordinates":[4.193007946,50.9624595642],"type":"Point"}
}