{
  "type": "Feature",
  "properties": {
    "iso:country":"BE",
    "sg:address":"Rue De La Station 12",
    "sg:city":"Baelen (membach)",
    "sg:classifiers":[
        {
            "category":"Home & Garden",
            "subcategory":"Building Materials",
            "type":"Retail Goods"
        }
    ],
    "sg:phone":"+32 87 55 25 54",
    "sg:postcode":"4837",
    "sg:province":"Li\u00e8ge",
    "sg:tags":[
        "shutter"
    ],
    "wof:name":"Stump A & Fils",
    "wof:placetype":"venue"
},
  "geometry": {"coordinates":[5.9988532066,50.6128387451],"type":"Point"}
}