{
  "type": "Feature",
  "properties": {
    "addr:full":"Berg 66 Balen Antwerpen 2490",
    "addr:housenumber":"66",
    "addr:postcode":"2490",
    "addr:street":"Berg",
    "iso:country":"BE",
    "sg:address":"Berg 66",
    "sg:city":"Balen",
    "sg:orig_category":"Charpentes and couvertures",
    "sg:phone":"+32 14 81 36 96",
    "sg:postcode":"2490",
    "sg:province":"Antwerpen",
    "wof:name":"Dakwerken Nuyts",
    "wof:placetype":"venue"
},
  "geometry": {"coordinates":[5.1563858986,51.1696434021],"type":"Point"}
}