{
  "type": "Feature",
  "properties": {
    "addr:full":"Houthulststraat 5 Staden West-Vlaanderen 8840",
    "addr:housenumber":"5",
    "addr:postcode":"8840",
    "addr:street":"Houthulststraat",
    "iso:country":"BE",
    "sg:address":"Houthulststraat 5",
    "sg:city":"Staden",
    "sg:classifiers":[
        {
            "category":"Farming",
            "subcategory":"Crops",
            "type":"Manufacturing & Wholesale Goods"
        }
    ],
    "sg:phone":"+32 51 70 14 92",
    "sg:postcode":"8840",
    "sg:province":"West-Vlaanderen",
    "sg:tags":[
        "vegetable",
        "fruit",
        "-",
        "grower"
    ],
    "wof:name":"Lef\u00e8vre N",
    "wof:placetype":"venue"
},
  "geometry": {"coordinates":[3.0034849644,50.9723472595],"type":"Point"}
}