{
  "type": "Feature",
  "properties": {
    "iso:country":"BE",
    "sg:address":"Bosschelstraat 10",
    "sg:city":"Kortessem",
    "sg:classifiers":[
        {
            "category":"Arena",
            "subcategory":"Sports Club",
            "type":"Entertainment"
        }
    ],
    "sg:phone":"+32 12 23 68 22",
    "sg:postcode":"3724",
    "sg:province":"Limburg",
    "sg:tags":[
        "de"
    ],
    "wof:name":"Verenigde Vrienden Vliermaal",
    "wof:placetype":"venue"
},
  "geometry": {"coordinates":[5.4316210747,50.8434791565],"type":"Point"}
}