{
  "type": "Feature",
  "properties": {
    "iso:country":"BE",
    "sg:address":"Oude Tieltstraat 23",
    "sg:city":"Meulebeke",
    "sg:classifiers":[
        {
            "category":"Health Services",
            "subcategory":"Health Practitioner",
            "type":"Services"
        }
    ],
    "sg:phone":"+32 51 48 60 85",
    "sg:postcode":"8760",
    "sg:province":"West-Vlaanderen",
    "sg:tags":[
        "physiotherapist"
    ],
    "wof:name":"Van Daele W",
    "wof:placetype":"venue"
},
  "geometry": {"coordinates":[3.2956600189,50.9575500488],"type":"Point"}
}