{
  "type": "Feature",
  "properties": {
    "addr:full":"Place Communale 8 Bruxelles (molenbeek-saint-jean) Bruxelles-Capitale 1080",
    "addr:housenumber":"8",
    "addr:postcode":"1080",
    "addr:street":"Place Communale",
    "iso:country":"BE",
    "sg:address":"Place Communale 8",
    "sg:city":"Bruxelles (molenbeek-saint-jean)",
    "sg:classifiers":[
        {
            "category":"Retail",
            "subcategory":"Veterinary Services",
            "type":"Services"
        }
    ],
    "sg:phone":"+32 2 411 42 29",
    "sg:postcode":"1080",
    "sg:province":"Bruxelles-Capitale",
    "sg:tags":[
        "veterinarian"
    ],
    "wof:name":"Aubert Pierre",
    "wof:placetype":"venue"
},
  "geometry": {"coordinates":[4.3382377625,50.854675293],"type":"Point"}
}