{
  "type": "Feature",
  "properties": {
    "iso:country":"BE",
    "sg:address":"Olmstraat 348",
    "sg:city":"Vilvoorde",
    "sg:classifiers":[
        {
            "category":"Community Center",
            "subcategory":"Youth",
            "type":"Public Place"
        }
    ],
    "sg:phone":"+32 2 251 47 80",
    "sg:postcode":"1800",
    "sg:province":"Vlaams-Brabant",
    "sg:tags":[
        "workshop",
        "sheltered"
    ],
    "wof:name":"Mivavil Vzw",
    "wof:placetype":"venue"
},
  "geometry": {"coordinates":[4.4370040894,50.9365539551],"type":"Point"}
}