{
  "type": "Feature",
  "properties": {
    "addr:full":"Rue Albert Ier 27 Moeskroen/mouscron Hainaut 7700",
    "addr:housenumber":"27",
    "addr:postcode":"7700",
    "addr:street":"Rue Albert Ier",
    "iso:country":"BE",
    "sg:address":"Rue Albert Ier 27",
    "sg:city":"Moeskroen/mouscron",
    "sg:classifiers":[
        {
            "category":"Personal",
            "subcategory":"Beauty Salon",
            "type":"Services"
        }
    ],
    "sg:phone":"+32 56 34 50 76",
    "sg:postcode":"7700",
    "sg:province":"Hainaut",
    "sg:tags":[
        "de",
        "coiffure"
    ],
    "wof:name":"Coiffure Veronique",
    "wof:placetype":"venue"
},
  "geometry": {"coordinates":[3.2323200703,50.7400932312],"type":"Point"}
}