{
  "type": "Feature",
  "properties": {
    "iso:country":"BE",
    "sg:address":"Zuidschotestraat 25",
    "sg:city":"Lo-reninge (reninge)",
    "sg:classifiers":[
        {
            "category":"Home & Garden",
            "subcategory":"Garden Supply",
            "type":"Retail Goods"
        }
    ],
    "sg:phone":"+32 57 40 04 70",
    "sg:postcode":"8647",
    "sg:province":"West-Vlaanderen",
    "sg:tags":[
        "machine",
        "agricultural",
        "-"
    ],
    "wof:name":"M Tramat Bvba",
    "wof:placetype":"venue"
},
  "geometry": {"coordinates":[2.803041935,50.9319076538],"type":"Point"}
}