{
  "type": "Feature",
  "properties": {
    "addr:full":"Oudeheerweg 3 Gent Oost-Vlaanderen 9051",
    "addr:housenumber":"3",
    "addr:postcode":"9051",
    "addr:street":"Oudeheerweg;Oost-Vlaanderen",
    "iso:country":"BE",
    "sg:address":"Oudeheerweg 3",
    "sg:city":"Gent",
    "sg:orig_category":"Enseignement maternel and primaire",
    "sg:phone":"+32 9 221 32 73",
    "sg:postcode":"9051",
    "sg:province":"Oost-Vlaanderen",
    "wof:name":"Vrije Basisschool",
    "wof:placetype":"venue"
},
  "geometry": {"coordinates":[3.6702139378,51.0202827454],"type":"Point"}
}