{
  "type": "Feature",
  "properties": {
    "addr:full":"Rue Du Romarin 61 Comines-warneton (ploegsteert) Hainaut 7782",
    "addr:housenumber":"61",
    "addr:postcode":"7782",
    "addr:street":"Rue Du Romarin",
    "iso:country":"BE",
    "sg:address":"Rue Du Romarin 61",
    "sg:city":"Comines-warneton (ploegsteert)",
    "sg:classifiers":[
        {
            "category":"Retail",
            "subcategory":"Auto Repair",
            "type":"Services"
        }
    ],
    "sg:phone":"+32 56 58 97 54",
    "sg:postcode":"7782",
    "sg:province":"Hainaut",
    "sg:tags":[
        "garage"
    ],
    "wof:name":"Hyundai-ghekiere Guy Sprl",
    "wof:placetype":"venue"
},
  "geometry": {"coordinates":[2.8795371056,50.7278747559],"type":"Point"}
}