{
  "type": "Feature",
  "properties": {
    "addr:full":"Charleroise Steenweg 252 Sint-gillis/saint-gilles Bruxelles-Capitale 1060",
    "addr:housenumber":"252",
    "addr:postcode":"1060",
    "addr:street":"Charleroise Steenweg",
    "iso:country":"BE",
    "sg:address":"Charleroise Steenweg 252",
    "sg:city":"Sint-gillis/saint-gilles",
    "sg:orig_category":"Apotheken",
    "sg:phone":"+32 2 537 74 68",
    "sg:postcode":"1060",
    "sg:province":"Bruxelles-Capitale",
    "wof:name":"Multipharma",
    "wof:placetype":"venue"
},
  "geometry": {"coordinates":[4.3540458679,50.8230552673],"type":"Point"}
}