{
  "type": "Feature",
  "properties": {
    "addr:full":"Baron A.de Heuschstraat 7 Kortessem Limburg 3721",
    "addr:housenumber":"7",
    "addr:postcode":"3721",
    "addr:street":"Baron A.De Heuschstraat",
    "iso:country":"BE",
    "sg:address":"Baron A.de Heuschstraat 7",
    "sg:city":"Kortessem",
    "sg:orig_category":"Gespecialiseerde residenti\u00eble bouw",
    "sg:phone":"+32 89 51 40 59",
    "sg:postcode":"3721",
    "sg:province":"Limburg",
    "wof:name":"Tonny Wolfs",
    "wof:placetype":"venue"
},
  "geometry": {"coordinates":[5.4359998703,50.862033844],"type":"Point"}
}