{
  "type": "Feature",
  "properties": {
    "iso:country":"BE",
    "sg:address":"Acaciastraat 15",
    "sg:city":"Neerpelt",
    "sg:classifiers":[
        {
            "category":"Arena",
            "subcategory":"Sports Club",
            "type":"Entertainment"
        }
    ],
    "sg:phone":"+32 11 64 91 89",
    "sg:postcode":"3910",
    "sg:province":"Limburg",
    "sg:tags":[
        "de"
    ],
    "wof:name":"Dommeltrippers",
    "wof:placetype":"venue"
},
  "geometry": {"coordinates":[5.4455928802,51.2227668762],"type":"Point"}
}