{
  "type": "Feature",
  "properties": {
    "addr:full":"Avenue Orion 14 Sint-lambrechts-woluwe/woluwe-saint-lambert Bruxelles-Capitale 1200",
    "addr:housenumber":"14",
    "addr:postcode":"1200",
    "addr:street":"Avenue Orion",
    "iso:country":"BE",
    "sg:address":"Avenue Orion 14",
    "sg:city":"Sint-lambrechts-woluwe/woluwe-saint-lambert",
    "sg:orig_category":"M\u00e9decins and sp\u00e9cialistes",
    "sg:phone":"+32 2 779 10 40",
    "sg:postcode":"1200",
    "sg:province":"Bruxelles-Capitale",
    "wof:name":"Grazia Operti",
    "wof:placetype":"venue"
},
  "geometry": {"coordinates":[4.416121006,50.8510055542],"type":"Point"}
}