{
  "type": "Feature",
  "properties": {
    "iso:country":"BE",
    "sg:address":"Adegemstraat 72",
    "sg:city":"Mechelen",
    "sg:classifiers":[
        {
            "category":"Personal",
            "subcategory":"Beauty Salon",
            "type":"Services"
        }
    ],
    "sg:phone":"+32 15 26 12 09",
    "sg:postcode":"2800",
    "sg:province":"Antwerpen",
    "sg:tags":[
        "lady",
        "-",
        "hairdressing"
    ],
    "wof:name":"Danielle",
    "wof:placetype":"venue"
},
  "geometry": {"coordinates":[4.4733791351,51.0264778137],"type":"Point"}
}