{
  "type": "Feature",
  "properties": {
    "addr:full":"Avenue Louise 287 Bruxelles Bruxelles-Capitale 1050",
    "addr:housenumber":"287",
    "addr:postcode":"1050",
    "addr:street":"Avenue Louise",
    "iso:country":"BE",
    "sg:address":"Avenue Louise 287",
    "sg:city":"Bruxelles",
    "sg:classifiers":[
        {
            "category":"Building & Trades",
            "subcategory":"Pest Control",
            "type":"Services"
        }
    ],
    "sg:phone":"+32 2 640 74 30",
    "sg:postcode":"1050",
    "sg:province":"Bruxelles-Capitale",
    "sg:tags":[
        "metallurgy",
        "sheet",
        "-",
        "metalworking",
        "pipe",
        "engineering",
        "machine",
        "mechanical"
    ],
    "wof:name":"Soconord Sa",
    "wof:placetype":"venue"
},
  "geometry": {"coordinates":[4.3671460152,50.8236999512],"type":"Point"}
}