{
  "type": "Feature",
  "properties": {
    "addr:full":"Rue De La Fontaine 76 Vise Li\u00e8ge 4600",
    "addr:housenumber":"76",
    "addr:postcode":"4600",
    "addr:street":"Rue De La Fontaine",
    "iso:country":"BE",
    "sg:address":"Rue De La Fontaine 76",
    "sg:city":"Vise",
    "sg:orig_category":"Maisons de repos and r\u00e9sidences",
    "sg:phone":"+32 4 379 16 55",
    "sg:postcode":"4600",
    "sg:province":"Li\u00e8ge",
    "wof:name":"Fe. Claire-fontaine",
    "wof:placetype":"venue"
},
  "geometry": {"coordinates":[5.7013969421,50.736038208],"type":"Point"}
}