{
  "type": "Feature",
  "properties": {
    "iso:country":"BE",
    "sg:address":"Leemakkerstraat 42",
    "sg:city":"Meeuwen-gruitrode",
    "sg:orig_category":"Woningbouw",
    "sg:phone":"+32 89 85 84 19",
    "sg:postcode":"3670",
    "sg:province":"Limburg",
    "wof:name":"Leo Schroyen",
    "wof:placetype":"venue"
},
  "geometry": {"coordinates":[5.5654249191,51.1057243347],"type":"Point"}
}