{
  "type": "Feature",
  "properties": {
    "addr:full":"Zonnelaan 6 Maaseik Limburg 3680",
    "addr:housenumber":"6",
    "addr:postcode":"3680",
    "addr:street":"Zonnelaan",
    "iso:country":"BE",
    "sg:address":"Zonnelaan 6",
    "sg:city":"Maaseik",
    "sg:classifiers":[
        {
            "category":"Personal",
            "subcategory":"Beauty Salon",
            "type":"Services"
        }
    ],
    "sg:phone":"+32 89 56 11 42",
    "sg:postcode":"3680",
    "sg:province":"Limburg",
    "sg:tags":[
        "lady",
        "-",
        "hairdressing"
    ],
    "wof:name":"Hairstudio Ronny",
    "wof:placetype":"venue"
},
  "geometry": {"coordinates":[5.7903800011,51.0897369385],"type":"Point"}
}