{
  "type": "Feature",
  "properties": {
    "iso:country":"BE",
    "sg:address":"Markt 7",
    "sg:city":"Lo-reninge",
    "sg:orig_category":"Boucheries",
    "sg:phone":"+32 58 28 80 32",
    "sg:postcode":"8647",
    "sg:province":"West-Vlaanderen",
    "wof:name":"Kurt Vanbecelaere",
    "wof:placetype":"venue"
},
  "geometry": {"coordinates":[2.7495150566,50.9800453186],"type":"Point"}
}