{
  "type": "Feature",
  "properties": {
    "addr:full":"Rue Des Fonds 10b Lasne (grand) Brabant Wallon 1380",
    "addr:housenumber":"10b",
    "addr:postcode":"1380",
    "addr:street":"Rue Des Fonds;Wallon",
    "iso:country":"BE",
    "sg:address":"Rue Des Fonds 10b",
    "sg:city":"Lasne (grand)",
    "sg:orig_category":"Elektrische installaties voor woningen",
    "sg:phone":"+32 2 633 51 90",
    "sg:postcode":"1380",
    "sg:province":"Brabant Wallon",
    "wof:name":"Wansard Electricit\u00c9",
    "wof:placetype":"venue"
},
  "geometry": {"coordinates":[4.4925069809,50.6674575806],"type":"Point"}
}