{
  "type": "Feature",
  "properties": {
    "iso:country":"BE",
    "sg:address":"Rue De Gravi\u00c8re 11",
    "sg:city":"Namur",
    "sg:classifiers":[
        {
            "category":"Community Center",
            "subcategory":"Social",
            "type":"Public Place"
        }
    ],
    "sg:phone":"+32 81 22 48 24",
    "sg:postcode":"5000",
    "sg:province":"Namur",
    "sg:tags":[
        "salon",
        "de",
        "bien-\u00eatre",
        "coiffure",
        "relaxation"
    ],
    "wof:name":"Coiffure R\u00c9gine",
    "wof:placetype":"venue"
},
  "geometry": {"coordinates":[4.8698558807,50.4634895325],"type":"Point"}
}