{
  "type": "Feature",
  "properties": {
    "addr:full":"Provinciebaan 19 Rotselaar Vlaams-Brabant 3110",
    "addr:housenumber":"19",
    "addr:postcode":"3110",
    "addr:street":"Provinciebaan",
    "iso:country":"BE",
    "sg:address":"Provinciebaan 19",
    "sg:city":"Rotselaar",
    "sg:classifiers":[
        {
            "category":"Insurance",
            "subcategory":"Life Insurance",
            "type":"Services"
        }
    ],
    "sg:phone":"+32 16 44 84 13",
    "sg:postcode":"3110",
    "sg:province":"Vlaams-Brabant",
    "sg:tags":[
        "assurance"
    ],
    "wof:name":"L.k.c. Makelaardij",
    "wof:placetype":"venue"
},
  "geometry": {"coordinates":[4.7100419998,50.9512062073],"type":"Point"}
}