{
  "type": "Feature",
  "properties": {
    "addr:full":"Appelweg 106 Holsbeek (nieuwrode) Vlaams-Brabant 3221",
    "addr:housenumber":"106",
    "addr:postcode":"3221",
    "addr:street":"Appelweg",
    "iso:country":"BE",
    "sg:address":"Appelweg 106",
    "sg:city":"Holsbeek (nieuwrode)",
    "sg:classifiers":[
        {
            "category":"Building & Trades",
            "subcategory":"Landscaping Services",
            "type":"Services"
        }
    ],
    "sg:phone":"+32 16 56 05 26",
    "sg:postcode":"3221",
    "sg:province":"Vlaams-Brabant",
    "sg:tags":[
        "architect",
        "landscape"
    ],
    "wof:name":"Ten Hove",
    "wof:placetype":"venue"
},
  "geometry": {"coordinates":[4.8179769516,50.9464111328],"type":"Point"}
}