{
  "type": "Feature",
  "properties": {
    "addr:full":"Rue Du Herdier 0 Flemalle Li\u00e8ge 4400",
    "addr:housenumber":"0",
    "addr:postcode":"4400",
    "addr:street":"Rue Du Herdier",
    "iso:country":"BE",
    "sg:address":"Rue Du Herdier 0",
    "sg:city":"Flemalle",
    "sg:orig_category":"Enseignement secondaire g\u00e9n\u00e9ral. Enseignement maternel and primaire",
    "sg:phone":"+32 4 275 58 88",
    "sg:postcode":"4400",
    "sg:province":"Li\u00e8ge",
    "wof:name":"E.p.s.e.s.c.f.",
    "wof:placetype":"venue"
},
  "geometry": {"coordinates":[5.4441962242,50.5972137451],"type":"Point"}
}