{
  "type": "Feature",
  "properties": {
    "addr:full":"Salvialei 130 Schoten Antwerpen 2900",
    "addr:housenumber":"130",
    "addr:postcode":"2900",
    "addr:street":"Salvialei",
    "iso:country":"BE",
    "sg:address":"Salvialei 130",
    "sg:city":"Schoten",
    "sg:orig_category":"Jardinage",
    "sg:phone":"+32 3 646 45 73",
    "sg:postcode":"2900",
    "sg:province":"Antwerpen",
    "wof:name":"Kristiaan Hofkens",
    "wof:placetype":"venue"
},
  "geometry": {"coordinates":[4.4588541985,51.2448310852],"type":"Point"}
}