{
  "type": "Feature",
  "properties": {
    "iso:country":"BE",
    "sg:address":"Hammestraat 50",
    "sg:city":"Hamme",
    "sg:orig_category":"Woningbouw",
    "sg:phone":"+32 52 47 94 81",
    "sg:postcode":"9220",
    "sg:province":"Oost-Vlaanderen",
    "wof:name":"Van De Voorde Bouwwerken",
    "wof:placetype":"venue"
},
  "geometry": {"coordinates":[4.1503009796,51.0721664429],"type":"Point"}
}