{
  "type": "Feature",
  "properties": {
    "addr:full":"Konijnenboslaan 20 Gistel West-Vlaanderen 8470",
    "addr:housenumber":"20",
    "addr:postcode":"8470",
    "addr:street":"Konijnenboslaan",
    "iso:country":"BE",
    "sg:address":"Konijnenboslaan 20",
    "sg:city":"Gistel",
    "sg:orig_category":"Herstellingen and onderhoud van auto's Metaalafval, schrootrecyclage and sloperijen Voertuigen",
    "sg:phone":"+32 59 27 68 54",
    "sg:postcode":"8470",
    "sg:province":"West-Vlaanderen",
    "wof:name":"Autoservice Gistel",
    "wof:placetype":"venue"
},
  "geometry": {"coordinates":[2.9481260777,51.150478363],"type":"Point"}
}