{
  "type": "Feature",
  "properties": {
    "addr:full":"Provinciebaan 3a Staden (westrozebeke) West-Vlaanderen 8840",
    "addr:housenumber":"3a",
    "addr:postcode":"8840",
    "addr:street":"Provinciebaan",
    "iso:country":"BE",
    "sg:address":"Provinciebaan 3a",
    "sg:city":"Staden (westrozebeke)",
    "sg:classifiers":[
        {
            "category":"Health Services",
            "subcategory":"Health Practitioner",
            "type":"Services"
        }
    ],
    "sg:phone":"+32 51 77 98 45",
    "sg:postcode":"8840",
    "sg:province":"West-Vlaanderen",
    "sg:tags":[
        "physiotherapist"
    ],
    "wof:name":"Vandamme Siegfried",
    "wof:placetype":"venue"
},
  "geometry": {"coordinates":[3.0457150936,50.9539299011],"type":"Point"}
}