{
  "type": "Feature",
  "properties": {
    "addr:full":"Avenue Du Haut Pays 104 Honnelles (athis) Hainaut 7387",
    "addr:housenumber":"104",
    "addr:postcode":"7387",
    "addr:street":"Avenue Du Haut Pays",
    "iso:country":"BE",
    "sg:address":"Avenue Du Haut Pays 104",
    "sg:city":"Honnelles (athis)",
    "sg:classifiers":[
        {
            "category":"Bakery",
            "type":"Food & Drink"
        }
    ],
    "sg:phone":"+32 65 63 03 31",
    "sg:postcode":"7387",
    "sg:province":"Hainaut",
    "sg:tags":[
        "confectioner",
        "baker"
    ],
    "wof:name":"Athis (boulangerie D')",
    "wof:placetype":"venue"
},
  "geometry": {"coordinates":[3.7800400257,50.3620796204],"type":"Point"}
}