{
  "type": "Feature",
  "properties": {
    "addr:full":"Ruelle Lucie 4 Profondeville Namur 5170",
    "addr:housenumber":"4",
    "addr:postcode":"5170",
    "addr:street":"Ruelle Lucie",
    "iso:country":"BE",
    "sg:address":"Ruelle Lucie 4",
    "sg:city":"Profondeville",
    "sg:orig_category":"M\u00e9decins and sp\u00e9cialistes",
    "sg:phone":"+32 81 41 19 67",
    "sg:postcode":"5170",
    "sg:province":"Namur",
    "wof:name":"Andr\u00c9 Lemoine",
    "wof:placetype":"venue"
},
  "geometry": {"coordinates":[4.8725481033,50.3781356812],"type":"Point"}
}