{
  "type": "Feature",
  "properties": {
    "addr:full":"Rue De La Chapelle 21 Fexhe-le-haut-clocher Li\u00e8ge 4347",
    "addr:housenumber":"21",
    "addr:postcode":"4347",
    "addr:street":"Rue De La Chapelle",
    "iso:country":"BE",
    "sg:address":"Rue De La Chapelle 21",
    "sg:city":"Fexhe-le-haut-clocher",
    "sg:classifiers":[
        {
            "category":"Airport",
            "subcategory":"International",
            "type":"Transportation"
        }
    ],
    "sg:phone":"+32 4 250 20 96",
    "sg:postcode":"4347",
    "sg:province":"Li\u00e8ge",
    "sg:tags":[
        "-",
        "transport"
    ],
    "wof:name":"Dup's",
    "wof:placetype":"venue"
},
  "geometry": {"coordinates":[5.4211959839,50.6577377319],"type":"Point"}
}