{
  "type": "Feature",
  "properties": {
    "addr:full":"Liersebaan 118 Lier Antwerpen 2500",
    "addr:housenumber":"118",
    "addr:postcode":"2500",
    "addr:street":"Liersebaan",
    "iso:country":"BE",
    "sg:address":"Liersebaan 118",
    "sg:city":"Lier",
    "sg:orig_category":"Quincailleries",
    "sg:phone":"+32 3 482 49 28",
    "sg:postcode":"2500",
    "sg:province":"Antwerpen",
    "wof:name":"Profit-stock",
    "wof:placetype":"venue"
},
  "geometry": {"coordinates":[4.6003551483,51.104133606],"type":"Point"}
}