{
  "type": "Feature",
  "properties": {
    "addr:full":"M. Pyckstraat 25 Blankenberge (grand) West-Vlaanderen 8370",
    "addr:housenumber":"25",
    "addr:postcode":"8370",
    "addr:street":"Pyckstraat;Grand West-Vlaanderen",
    "iso:country":"BE",
    "sg:address":"M. Pyckstraat 25",
    "sg:city":"Blankenberge (grand)",
    "sg:orig_category":"Paramedische behandelingen Schoonheidssalons",
    "sg:phone":"+32 50 41 48 17",
    "sg:postcode":"8370",
    "sg:province":"West-Vlaanderen",
    "wof:name":"Azur Beauty Studio",
    "wof:placetype":"venue"
},
  "geometry": {"coordinates":[3.1307780743,51.3085136414],"type":"Point"}
}