{
  "type": "Feature",
  "properties": {
    "addr:full":"Rue De L'acad\u00c9mie 37 Li\u00c8ge Li\u00e8ge 4000",
    "addr:housenumber":"37",
    "addr:postcode":"4000",
    "addr:street":"Rue De L'Acade \u0301Mie",
    "iso:country":"BE",
    "sg:address":"Rue De L'acad\u00c9mie 37",
    "sg:city":"Li\u00c8ge",
    "sg:orig_category":"M\u00e9decins and sp\u00e9cialistes",
    "sg:phone":"+32 4 222 39 76",
    "sg:postcode":"4000",
    "sg:province":"Li\u00e8ge",
    "wof:name":"Tchomba Mulamba",
    "wof:placetype":"venue"
},
  "geometry": {"coordinates":[5.5673718452,50.6467208862],"type":"Point"}
}