{
  "type": "Feature",
  "properties": {
    "iso:country":"BE",
    "sg:address":"Rue Des Coteaux 65",
    "sg:city":"Herstal (milmort)",
    "sg:classifiers":[
        {
            "category":"Professional",
            "subcategory":"Printing & Photocopies",
            "type":"Services"
        }
    ],
    "sg:phone":"+32 4 278 47 57",
    "sg:postcode":"4041",
    "sg:province":"Li\u00e8ge",
    "sg:tags":[
        "trophy",
        "medal"
    ],
    "wof:name":"Darcis M",
    "wof:placetype":"venue"
},
  "geometry": {"coordinates":[5.5922651291,50.6866874695],"type":"Point"}
}