{
  "type": "Feature",
  "properties": {
    "addr:full":"Rue Du Village 58 Ciney Namur 5590",
    "addr:housenumber":"58",
    "addr:postcode":"5590",
    "addr:street":"Rue Du Village",
    "iso:country":"BE",
    "sg:address":"Rue Du Village 58",
    "sg:city":"Ciney",
    "sg:orig_category":"Rundveehouders",
    "sg:phone":"+32 83 21 18 74",
    "sg:postcode":"5590",
    "sg:province":"Namur",
    "wof:name":"Jean-marc Puissant",
    "wof:placetype":"venue"
},
  "geometry": {"coordinates":[5.1037697792,50.2244644165],"type":"Point"}
}