{
  "type": "Feature",
  "properties": {
    "addr:full":"Daalstraat 4 Zutendaal Limburg 3690",
    "addr:housenumber":"4",
    "addr:postcode":"3690",
    "addr:street":"Daalstraat",
    "iso:country":"BE",
    "sg:address":"Daalstraat 4",
    "sg:city":"Zutendaal",
    "sg:classifiers":[
        {
            "category":"Arena",
            "subcategory":"Sports Club",
            "type":"Entertainment"
        }
    ],
    "sg:phone":"+32 89 61 17 85",
    "sg:postcode":"3690",
    "sg:province":"Limburg",
    "sg:tags":[
        "de"
    ],
    "wof:name":"V.c. Zutendaal",
    "wof:placetype":"venue"
},
  "geometry": {"coordinates":[5.571231842,50.9316596985],"type":"Point"}
}