{
  "type": "Feature",
  "properties": {
    "iso:country":"BE",
    "sg:address":"Daalhofstraat 5c",
    "sg:city":"Borgloon (hoepertingen)",
    "sg:classifiers":[
        {
            "category":"Professional",
            "subcategory":"Art Services",
            "type":"Services"
        }
    ],
    "sg:phone":"+32 12 74 67 61",
    "sg:postcode":"3840",
    "sg:province":"Limburg",
    "sg:tags":[
        "shop",
        "paint",
        "spraying"
    ],
    "wof:name":"Coppieters R",
    "wof:placetype":"venue"
},
  "geometry": {"coordinates":[5.3441700935,50.8012466431],"type":"Point"}
}