{
  "type": "Feature",
  "properties": {
    "addr:full":"Antwerpsesteenweg 729 Gent (sint-amandsberg) Oost-Vlaanderen 9040",
    "addr:housenumber":"729",
    "addr:postcode":"9040",
    "addr:street":"Antwerpsesteenweg",
    "iso:country":"BE",
    "sg:address":"Antwerpsesteenweg 729",
    "sg:city":"Gent (sint-amandsberg)",
    "sg:classifiers":[
        {
            "category":"Autos & Motor Vehicles",
            "subcategory":"Fuel & Gas Station",
            "type":"Retail Goods"
        }
    ],
    "sg:phone":"+32 9 228 71 78",
    "sg:postcode":"9040",
    "sg:province":"Oost-Vlaanderen",
    "wof:name":"Texaco",
    "wof:placetype":"venue"
},
  "geometry": {"coordinates":[3.7753961086,51.0728302002],"type":"Point"}
}