{
  "type": "Feature",
  "properties": {
    "addr:full":"Rue De La Croix 1 Assesse Namur 5334",
    "addr:housenumber":"1",
    "addr:postcode":"5334",
    "addr:street":"Rue De La Croix",
    "iso:country":"BE",
    "sg:address":"Rue De La Croix 1",
    "sg:city":"Assesse",
    "sg:orig_category":"Enseignement maternel and primaire",
    "sg:phone":"+32 83 65 55 16",
    "sg:postcode":"5334",
    "sg:province":"Namur",
    "wof:name":"Ecole Prim. Communale",
    "wof:placetype":"venue"
},
  "geometry": {"coordinates":[5.0691919327,50.3761291504],"type":"Point"}
}