{
  "type": "Feature",
  "properties": {
    "iso:country":"BE",
    "sg:address":"Molsekiezel 309",
    "sg:city":"Lommel",
    "sg:classifiers":[
        {
            "category":"Health Services",
            "subcategory":"Health Practitioner",
            "type":"Services"
        }
    ],
    "sg:phone":"+32 11 55 59 94",
    "sg:postcode":"3920",
    "sg:province":"Limburg",
    "sg:tags":[
        "physiotherapist"
    ],
    "wof:name":"Dries Anja",
    "wof:placetype":"venue"
},
  "geometry": {"coordinates":[5.2761411667,51.2311172485],"type":"Point"}
}