{
  "type": "Feature",
  "properties": {
    "addr:full":"Oude Luikerbaan 18b1 Hasselt Limburg 3500",
    "addr:housenumber":"18b1",
    "addr:postcode":"3500",
    "addr:street":"Oude Luikerbaan",
    "iso:country":"BE",
    "sg:address":"Oude Luikerbaan 18b1",
    "sg:city":"Hasselt",
    "sg:classifiers":[
        {
            "category":"Personal",
            "subcategory":"Beauty Salon",
            "type":"Services"
        }
    ],
    "sg:phone":"+32 11 24 18 08",
    "sg:postcode":"3500",
    "sg:province":"Limburg",
    "sg:tags":[
        "de",
        "coiffure"
    ],
    "wof:name":"Coiffure Deveux",
    "wof:placetype":"venue"
},
  "geometry": {"coordinates":[5.3421468735,50.9235191345],"type":"Point"}
}