{
  "type": "Feature",
  "properties": {
    "iso:country":"BE",
    "sg:address":"Graaf De Broquevillestraat 29",
    "sg:city":"Mol",
    "sg:classifiers":[
        {
            "category":"Professional",
            "subcategory":"Testing Lab",
            "type":"Services"
        }
    ],
    "sg:phone":"+32 14 31 55 58",
    "sg:postcode":"2400",
    "sg:province":"Antwerpen",
    "sg:tags":[
        "chemist"
    ],
    "wof:name":"Hoedemaekers H",
    "wof:placetype":"venue"
},
  "geometry": {"coordinates":[5.1167721748,51.1852722168],"type":"Point"}
}