{
  "type": "Feature",
  "properties": {
    "addr:full":"Speelpleinlaan 39 Brugge West-Vlaanderen 8310",
    "addr:housenumber":"39",
    "addr:postcode":"8310",
    "addr:street":"Speelpleinlaan",
    "iso:country":"BE",
    "sg:address":"Speelpleinlaan 39",
    "sg:city":"Brugge",
    "sg:orig_category":"Paramedische behandelingen",
    "sg:phone":"+32 50 35 08 06",
    "sg:postcode":"8310",
    "sg:province":"West-Vlaanderen",
    "wof:name":"Thuisverpleging Cura",
    "wof:placetype":"venue"
},
  "geometry": {"coordinates":[3.2447268963,51.2068786621],"type":"Point"}
}