{
  "type": "Feature",
  "properties": {
    "iso:country":"BE",
    "sg:address":"Beerzelplein 29",
    "sg:city":"Putte (beerzel)",
    "sg:classifiers":[
        {
            "category":"Bars & Pubs",
            "type":"Food & Drink"
        }
    ],
    "sg:phone":"+32 15 75 80 45",
    "sg:postcode":"2580",
    "sg:province":"Antwerpen",
    "wof:name":"Pleintje 't",
    "wof:placetype":"venue"
},
  "geometry": {"coordinates":[4.6719098091,51.0574111938],"type":"Point"}
}