{
  "type": "Feature",
  "properties": {
    "iso:country":"BE",
    "sg:address":"Margote 69",
    "sg:city":"Wichelen",
    "sg:classifiers":[
        {
            "category":"Insurance",
            "subcategory":"Insurance Agent",
            "type":"Services"
        }
    ],
    "sg:phone":"+32 52 42 24 95",
    "sg:postcode":"9260",
    "sg:province":"Oost-Vlaanderen",
    "sg:tags":[
        "-",
        "representative"
    ],
    "wof:name":"Van Den Bogaert P",
    "wof:placetype":"venue"
},
  "geometry": {"coordinates":[3.9754641056,51.006362915],"type":"Point"}
}