{
  "type": "Feature",
  "properties": {
    "iso:country":"BE",
    "sg:address":"Rue Maurice Duch\u00cane 52b",
    "sg:city":"Awans",
    "sg:orig_category":"Gespecialiseerde residenti\u00eble bouw Plaatsen van vloer- and muurbekleding Vloer- and muurbekleding",
    "sg:phone":"+32 4 257 42 74",
    "sg:postcode":"4340",
    "sg:province":"Li\u00e8ge",
    "wof:name":"Joseph Leduc Malaise",
    "wof:placetype":"venue"
},
  "geometry": {"coordinates":[5.4653391838,50.7208442688],"type":"Point"}
}