{
  "type": "Feature",
  "properties": {
    "iso:country":"BE",
    "sg:address":"Het Steegje 38",
    "sg:city":"Houthalen-helchteren (houthalen)",
    "sg:classifiers":[
        {
            "category":"Health Services",
            "subcategory":"Health Practitioner",
            "type":"Services"
        }
    ],
    "sg:phone":"+32 11 57 36 47",
    "sg:postcode":"3530",
    "sg:province":"Limburg",
    "sg:tags":[
        "physiotherapist"
    ],
    "wof:name":"Mekers Sarah",
    "wof:placetype":"venue"
},
  "geometry": {"coordinates":[5.3509311676,51.0467453003],"type":"Point"}
}