{
  "type": "Feature",
  "properties": {
    "iso:country":"BE",
    "sg:address":"Rue Fr. Jos. Peterinck 6b13",
    "sg:city":"Tournai",
    "sg:orig_category":"Sportclubs",
    "sg:phone":"+32 69 23 47 30",
    "sg:postcode":"7500",
    "sg:province":"Hainaut",
    "wof:name":"T.c.cent.reg.entr.hainaut",
    "wof:placetype":"venue"
},
  "geometry": {"coordinates":[3.3816719055,50.6122970581],"type":"Point"}
}