{
  "type": "Feature",
  "properties": {
    "iso:country":"BE",
    "sg:address":"Kelbergenstraat 1",
    "sg:city":"Diest (schaffen)",
    "sg:classifiers":[
        {
            "category":"Professional",
            "subcategory":"Art Services",
            "type":"Services"
        }
    ],
    "sg:phone":"+32 13 33 41 41",
    "sg:postcode":"3290",
    "sg:province":"Vlaams-Brabant",
    "sg:tags":[
        "shop",
        "paint",
        "spraying"
    ],
    "wof:name":"Alcoat Nv",
    "wof:placetype":"venue"
},
  "geometry": {"coordinates":[5.0914230347,51.0150299072],"type":"Point"}
}