{
  "type": "Feature",
  "properties": {
    "addr:full":"Kraaiendonk 28 Sint-martens-latem Oost-Vlaanderen 9830",
    "addr:housenumber":"28",
    "addr:postcode":"9830",
    "addr:street":"Kraaiendonk",
    "iso:country":"BE",
    "sg:address":"Kraaiendonk 28",
    "sg:city":"Sint-martens-latem",
    "sg:orig_category":"Advocaten and juridische adviseurs Balie van Gent",
    "sg:phone":"+32 9 281 00 62",
    "sg:postcode":"9830",
    "sg:province":"Oost-Vlaanderen",
    "wof:name":"Janssens Gudrun",
    "wof:placetype":"venue"
},
  "geometry": {"coordinates":[3.6359479427,51.0054588318],"type":"Point"}
}