{
  "type": "Feature",
  "properties": {
    "iso:country":"BE",
    "sg:address":"Rechtstraat 160",
    "sg:city":"Duffel",
    "sg:classifiers":[
        {
            "category":"Health Services",
            "subcategory":"Health Practitioner",
            "type":"Services"
        }
    ],
    "sg:phone":"+32 15 31 36 63",
    "sg:postcode":"2570",
    "sg:province":"Antwerpen",
    "sg:tags":[
        "physiotherapist"
    ],
    "wof:name":"Matthyssens Paul",
    "wof:placetype":"venue"
},
  "geometry": {"coordinates":[4.4762501717,51.1105117798],"type":"Point"}
}