{
  "type": "Feature",
  "properties": {
    "addr:full":"Astridlaan 10 Brugge West-Vlaanderen 8310",
    "addr:housenumber":"10",
    "addr:postcode":"8310",
    "addr:street":"Astridlaan",
    "iso:country":"BE",
    "sg:address":"Astridlaan 10",
    "sg:city":"Brugge",
    "sg:orig_category":"Opticiens",
    "sg:phone":"+32 50 36 34 34",
    "sg:postcode":"8310",
    "sg:province":"West-Vlaanderen",
    "wof:name":"Huis Landuyt",
    "wof:placetype":"venue"
},
  "geometry": {"coordinates":[3.2472379208,51.2002792358],"type":"Point"}
}