{
  "type": "Feature",
  "properties": {
    "iso:country":"BE",
    "sg:address":"Rue De L'ecole 17",
    "sg:city":"Floreffe",
    "sg:orig_category":"Enseignement maternel and primaire",
    "sg:phone":"+32 81 44 61 99",
    "sg:postcode":"5150",
    "sg:province":"Namur",
    "wof:name":"Ecole Fond. Communale",
    "wof:placetype":"venue"
},
  "geometry": {"coordinates":[4.7600998878,50.435710907],"type":"Point"}
}