{
  "type": "Feature",
  "properties": {
    "iso:country":"BE",
    "sg:address":"Rue Emile Cuvelier 47",
    "sg:city":"Namur",
    "sg:classifiers":[
        {
            "category":"Personal",
            "subcategory":"Nail Salon",
            "type":"Services"
        }
    ],
    "sg:phone":"+32 81 22 31 31",
    "sg:postcode":"5000",
    "sg:province":"Namur",
    "sg:tags":[
        "pedicure"
    ],
    "wof:name":"Bodart-kirsch Sa",
    "wof:placetype":"venue"
},
  "geometry": {"coordinates":[4.8661689758,50.4645690918],"type":"Point"}
}