{
  "type": "Feature",
  "properties": {
    "addr:full":"Laarstraat 19 Zwijndrecht Antwerpen 2070",
    "addr:housenumber":"19",
    "addr:postcode":"2070",
    "addr:street":"Laarstraat",
    "iso:country":"BE",
    "sg:address":"Laarstraat 19",
    "sg:city":"Zwijndrecht",
    "sg:orig_category":"V\u00eatements",
    "sg:phone":"+32 3 252 71 83",
    "sg:postcode":"2070",
    "sg:province":"Antwerpen",
    "wof:name":"Fa. Rens",
    "wof:placetype":"venue"
},
  "geometry": {"coordinates":[4.3328919411,51.214466095],"type":"Point"}
}