{
  "type": "Feature",
  "properties": {
    "iso:country":"BE",
    "sg:address":"Avenue Isidore Geyskens 138",
    "sg:city":"Oudergem/auderghem",
    "sg:classifiers":[
        {
            "category":"Building & Trades",
            "subcategory":"Plumbing",
            "type":"Services"
        }
    ],
    "sg:phone":"+32 2 725 80 15",
    "sg:postcode":"1160",
    "sg:province":"Bruxelles-Capitale",
    "sg:tags":[
        "diver",
        "commerce",
        "gr",
        "pour",
        "equipement"
    ],
    "wof:name":"Codibel",
    "wof:placetype":"venue"
},
  "geometry": {"coordinates":[4.4238348007,50.8214569092],"type":"Point"}
}