{
  "type": "Feature",
  "properties": {
    "iso:country":"BE",
    "sg:address":"Rue De La Couronne 74",
    "sg:city":"Estaimpuis",
    "sg:classifiers":[
        {
            "category":"Professional",
            "subcategory":"Printing & Photocopies",
            "type":"Services"
        }
    ],
    "sg:phone":"+32 56 48 10 20",
    "sg:postcode":"7730",
    "sg:province":"Hainaut",
    "sg:tags":[
        "cardboard",
        "processing"
    ],
    "wof:name":"Trehout Cartonnages S.a.",
    "wof:placetype":"venue"
},
  "geometry": {"coordinates":[3.271750927,50.7160186768],"type":"Point"}
}