{
  "type": "Feature",
  "properties": {
    "iso:country":"BE",
    "sg:address":"Avenue Des Volontaires 132-7",
    "sg:city":"Bruxelles (etterbeek)",
    "sg:classifiers":[
        {
            "category":"Professional",
            "subcategory":"Art Services",
            "type":"Services"
        }
    ],
    "sg:phone":"+32 2 736 80 82",
    "sg:postcode":"1040",
    "sg:province":"Bruxelles-Capitale",
    "sg:tags":[
        "graphic",
        "designer"
    ],
    "wof:name":"Mobouck P",
    "wof:placetype":"venue"
},
  "geometry": {"coordinates":[4.4075818062,50.8286018372],"type":"Point"}
}