{
  "type": "Feature",
  "properties": {
    "iso:country":"BE",
    "sg:address":"Zuid-torhoutstraat 5",
    "sg:city":"Houthulst",
    "sg:orig_category":"Eleveurs de bovins. Eleveurs and marchands de porcs",
    "sg:phone":"+32 51 54 42 67",
    "sg:postcode":"8650",
    "sg:province":"West-Vlaanderen",
    "wof:name":"Geert Loeters",
    "wof:placetype":"venue"
},
  "geometry": {"coordinates":[2.9113190174,50.9759902954],"type":"Point"}
}