{
  "type": "Feature",
  "properties": {
    "iso:country":"BE",
    "sg:address":"Oostendsesteenweg 52",
    "sg:city":"Brugge",
    "sg:orig_category":"Magasins de r\u00e9parations d'articles personnels et m\u00e9nagers divers. Installation de menuiserie m\u00e9talli",
    "sg:phone":"+32 50 31 71 71",
    "sg:postcode":"8000",
    "sg:province":"West-Vlaanderen",
    "wof:name":"Traen-van Parijs",
    "wof:placetype":"venue"
},
  "geometry": {"coordinates":[3.1900799274,51.2292709351],"type":"Point"}
}