{
  "type": "Feature",
  "properties": {
    "iso:country":"BE",
    "sg:address":"Ruelle Mottart 2",
    "sg:city":"Beauvechain (tourinnes-la-grosse)",
    "sg:classifiers":[
        {
            "category":"Retail",
            "subcategory":"Event Space",
            "type":"Services"
        }
    ],
    "sg:phone":"+32 10 86 82 50",
    "sg:postcode":"1320",
    "sg:province":"Brabant Wallon",
    "sg:tags":[
        "organisation"
    ],
    "wof:name":"Ecloosion Sa",
    "wof:placetype":"venue"
},
  "geometry": {"coordinates":[4.7560238838,50.7793464661],"type":"Point"}
}