{
  "type": "Feature",
  "properties": {
    "addr:full":"Rue Albert Dekkers 79 Dalhem (warsage) Li\u00e8ge 4608",
    "addr:housenumber":"79",
    "addr:postcode":"4608",
    "addr:street":"Rue Albert Dekkers",
    "iso:country":"BE",
    "sg:address":"Rue Albert Dekkers 79",
    "sg:city":"Dalhem (warsage)",
    "sg:classifiers":[
        {
            "category":"Farming",
            "subcategory":"Crops",
            "type":"Manufacturing & Wholesale Goods"
        }
    ],
    "sg:phone":"+32 4 376 63 29",
    "sg:postcode":"4608",
    "sg:province":"Li\u00e8ge",
    "sg:tags":[
        "vegetable",
        "fruit",
        "-",
        "grower"
    ],
    "wof:name":"Laduron G",
    "wof:placetype":"venue"
},
  "geometry": {"coordinates":[5.7819480896,50.73462677],"type":"Point"}
}