{
  "type": "Feature",
  "properties": {
    "addr:full":"Ebergiste De Deynestraat 2 Gent Oost-Vlaanderen 9000",
    "addr:housenumber":"2",
    "addr:postcode":"9000",
    "addr:street":"Deynestraat;Oost-Vlaanderen",
    "iso:country":"BE",
    "sg:address":"Ebergiste De Deynestraat 2",
    "sg:city":"Gent",
    "sg:orig_category":"Enseignement maternel and primaire",
    "sg:phone":"+32 9 222 11 68",
    "sg:postcode":"9000",
    "sg:province":"Oost-Vlaanderen",
    "wof:name":"Vrije Basisschool",
    "wof:placetype":"venue"
},
  "geometry": {"coordinates":[3.7115249634,51.017288208],"type":"Point"}
}