{
  "type": "Feature",
  "properties": {
    "iso:country":"BE",
    "sg:address":"Kerkstr 48",
    "sg:city":"Heist",
    "sg:classifiers":[
        {
            "category":"Social Services",
            "subcategory":"Retirement Home",
            "type":"Services"
        }
    ],
    "sg:phone":"+32 50 51 38 05",
    "sg:postcode":"8301",
    "sg:province":"West-Vlaanderen",
    "sg:tags":[
        "ceramic",
        "wood",
        "household",
        "good",
        "furniture"
    ],
    "wof:name":"Tapijten Vanraes Bvba",
    "wof:placetype":"venue"
},
  "geometry": {"coordinates":[3.2370150089,51.3395385742],"type":"Point"}
}