{
  "type": "Feature",
  "properties": {
    "addr:full":"Chauss\u00e9e De Gand 1255 Bruxelles (berchem-sainte-agathe) Bruxelles-Capitale 1082",
    "addr:postcode":"1255;berchem-sainte-agathe;1082",
    "addr:street":"Chausse\u0301E De Gand",
    "iso:country":"BE",
    "sg:address":"Chauss\u00e9e De Gand 1255",
    "sg:city":"Bruxelles (berchem-sainte-agathe)",
    "sg:classifiers":[
        {
            "category":"Retail",
            "subcategory":"Auto Repair",
            "type":"Services"
        }
    ],
    "sg:phone":"+32 2 465 95 95",
    "sg:postcode":"1082",
    "sg:province":"Bruxelles-Capitale",
    "sg:tags":[
        "garage"
    ],
    "wof:name":"Croiselet (ets)",
    "wof:placetype":"venue"
},
  "geometry": {"coordinates":[4.2936229706,50.8679847717],"type":"Point"}
}