{
  "type": "Feature",
  "properties": {
    "addr:full":"Aartrijkestraat 28 Torhout West-Vlaanderen 8820",
    "addr:housenumber":"28",
    "addr:postcode":"8820",
    "addr:street":"Aartrijkestraat",
    "iso:country":"BE",
    "sg:address":"Aartrijkestraat 28",
    "sg:city":"Torhout",
    "sg:classifiers":[
        {
            "category":"Professional",
            "subcategory":"Lawyer & Legal Services",
            "type":"Services"
        }
    ],
    "sg:phone":"+32 50 21 24 87",
    "sg:postcode":"8820",
    "sg:province":"West-Vlaanderen",
    "sg:tags":[
        "notary"
    ],
    "wof:name":"Mouriau C",
    "wof:placetype":"venue"
},
  "geometry": {"coordinates":[3.1001200676,51.0689697266],"type":"Point"}
}