{
  "type": "Feature",
  "properties": {
    "iso:country":"BE",
    "sg:address":"Zerkegemstraat 19",
    "sg:city":"Jabbeke",
    "sg:classifiers":[
        {
            "category":"Food & Beverages",
            "subcategory":"Chocolate",
            "type":"Retail Goods"
        }
    ],
    "sg:phone":"+32 50 81 38 63",
    "sg:postcode":"8490",
    "sg:province":"West-Vlaanderen",
    "sg:tags":[
        "confectionery",
        "-"
    ],
    "wof:name":"Connie Confiserie",
    "wof:placetype":"venue"
},
  "geometry": {"coordinates":[3.0857648849,51.1780815125],"type":"Point"}
}