{
  "type": "Feature",
  "properties": {
    "addr:full":"Bedrijvenln 3 Veurne West-Vlaanderen 8630",
    "addr:housenumber":"3",
    "addr:postcode":"8630",
    "addr:street":"Bedrijvenln",
    "iso:country":"BE",
    "sg:address":"Bedrijvenln 3",
    "sg:city":"Veurne",
    "sg:classifiers":[
        {
            "category":"Shopping",
            "type":"Retail Goods"
        }
    ],
    "sg:phone":"+32 58 23 72 93",
    "sg:postcode":"8630",
    "sg:province":"West-Vlaanderen",
    "sg:tags":[
        "metallurgy",
        "finished",
        "-",
        "metalworking",
        "metallic"
    ],
    "wof:name":"Goens Johan Bvba",
    "wof:placetype":"venue"
},
  "geometry": {"coordinates":[2.6617588997,51.072681427],"type":"Point"}
}