{
  "type": "Feature",
  "properties": {
    "addr:full":"Zwarte Vijversstraat 37 Brussel Bruxelles-Capitale 1080",
    "addr:housenumber":"37",
    "addr:postcode":"1080",
    "addr:street":"Zwarte Vijversstraat",
    "iso:country":"BE",
    "sg:address":"Zwarte Vijversstraat 37",
    "sg:city":"Brussel",
    "sg:classifiers":[
        {
            "category":"Food & Beverages",
            "subcategory":"Bakery",
            "type":"Retail Goods"
        }
    ],
    "sg:phone":"+32 2 410 27 00",
    "sg:postcode":"1080",
    "sg:province":"Bruxelles-Capitale",
    "sg:tags":[
        "waffle"
    ],
    "wof:name":"General Wafel Manifactoris B.v.b.a.",
    "wof:placetype":"venue"
},
  "geometry": {"coordinates":[4.3299598694,50.8562965393],"type":"Point"}
}