{
  "type": "Feature",
  "properties": {
    "addr:full":"Clerck's-straat 58 Wevelgem (moorsele) West-Vlaanderen 8560",
    "addr:housenumber":"58",
    "addr:postcode":"8560",
    "addr:street":"Clerck'S-Straat",
    "iso:country":"BE",
    "sg:address":"Clerck's-straat 58",
    "sg:city":"Wevelgem (moorsele)",
    "sg:classifiers":[
        {
            "category":"Health Services",
            "subcategory":"Health Practitioner",
            "type":"Services"
        }
    ],
    "sg:phone":"+32 56 50 00 42",
    "sg:postcode":"8560",
    "sg:province":"West-Vlaanderen",
    "sg:tags":[
        "therapist",
        "speech"
    ],
    "wof:name":"Michaux I",
    "wof:placetype":"venue"
},
  "geometry": {"coordinates":[3.1799199581,50.8080101013],"type":"Point"}
}