{
  "type": "Feature",
  "properties": {
    "iso:country":"BE",
    "sg:address":"Wissenstraat 18",
    "sg:city":"Dendermonde",
    "sg:orig_category":"Gestion des d\u00e9charges and sites d\u00e9finitifs de stockage",
    "sg:phone":"+32 52 21 48 10",
    "sg:postcode":"9200",
    "sg:province":"Oost-Vlaanderen",
    "wof:name":"Containerpark Dendermonder",
    "wof:placetype":"venue"
},
  "geometry": {"coordinates":[4.1451787949,51.0276794434],"type":"Point"}
}