{
  "type": "Feature",
  "properties": {
    "iso:country":"BE",
    "sg:address":"Hoogheide 6",
    "sg:city":"Hasselt (kuringen)",
    "sg:classifiers":[
        {
            "category":"Bars & Pubs",
            "type":"Food & Drink"
        }
    ],
    "sg:phone":"+32 11 23 48 33",
    "sg:postcode":"3511",
    "sg:province":"Limburg",
    "wof:name":"Vanvoorden M",
    "wof:placetype":"venue"
},
  "geometry": {"coordinates":[5.3371539116,50.9299621582],"type":"Point"}
}