{
  "type": "Feature",
  "properties": {
    "addr:full":"Rue Ferme Du Coq 18 Court-saint-etienne Brabant Wallon 1490",
    "addr:housenumber":"18;1490",
    "addr:street":"Rue Ferme Du Coq",
    "iso:country":"BE",
    "sg:address":"Rue Ferme Du Coq 18",
    "sg:city":"Court-saint-etienne",
    "sg:classifiers":[
        {
            "category":"Retail",
            "subcategory":"Auto Repair",
            "type":"Services"
        }
    ],
    "sg:phone":"+32 10 61 33 00",
    "sg:postcode":"1490",
    "sg:province":"Brabant Wallon",
    "sg:tags":[
        "automobile-body"
    ],
    "wof:name":"B.m. Carrosserie",
    "wof:placetype":"venue"
},
  "geometry": {"coordinates":[4.5486187935,50.6361503601],"type":"Point"}
}