{
  "type": "Feature",
  "properties": {
    "addr:full":"Sint-goriksplein 11 Edegem Antwerpen 2650",
    "addr:housenumber":"11",
    "addr:postcode":"2650",
    "addr:street":"Sint-Goriksplein",
    "iso:country":"BE",
    "sg:address":"Sint-goriksplein 11",
    "sg:city":"Edegem",
    "sg:classifiers":[
        {
            "category":"Community Center",
            "subcategory":"Social",
            "type":"Public Place"
        }
    ],
    "sg:phone":"+32 3 457 27 68",
    "sg:postcode":"2650",
    "sg:province":"Antwerpen",
    "sg:tags":[
        "polishing",
        "abrasive",
        "compound"
    ],
    "wof:name":"Klingspor Nv",
    "wof:placetype":"venue"
},
  "geometry": {"coordinates":[4.4542870522,51.148979187],"type":"Point"}
}