{
  "type": "Feature",
  "properties": {
    "addr:full":"Rue Tasson-snel 24b1 Sint-gillis/saint-gilles Bruxelles-Capitale 1060",
    "addr:housenumber":"24b1",
    "addr:postcode":"1060",
    "addr:street":"Rue Tasson-Snel",
    "iso:country":"BE",
    "sg:address":"Rue Tasson-snel 24b1",
    "sg:city":"Sint-gillis/saint-gilles",
    "sg:orig_category":"Artistes ind\u00e9pendants",
    "sg:phone":"+32 2 538 30 78",
    "sg:postcode":"1060",
    "sg:province":"Bruxelles-Capitale",
    "wof:name":"Anne Chappuis",
    "wof:placetype":"venue"
},
  "geometry": {"coordinates":[4.3563351631,50.8272399902],"type":"Point"}
}