{
  "type": "Feature",
  "properties": {
    "addr:full":"Peter Benoitlaan 42 Veurne West-Vlaanderen 8630",
    "addr:housenumber":"42",
    "addr:postcode":"8630",
    "addr:street":"Peter Benoitlaan",
    "iso:country":"BE",
    "sg:address":"Peter Benoitlaan 42",
    "sg:city":"Veurne",
    "sg:classifiers":[
        {
            "category":"Taxi",
            "type":"Transportation"
        }
    ],
    "sg:phone":"+32 58 31 56 00",
    "sg:postcode":"8630",
    "sg:province":"West-Vlaanderen",
    "wof:name":"Taxi Geert",
    "wof:placetype":"venue"
},
  "geometry": {"coordinates":[2.6599578857,51.0698928833],"type":"Point"}
}