{
  "type": "Feature",
  "properties": {
    "iso:country":"BE",
    "sg:address":"Moutstraat 62",
    "sg:city":"Gent",
    "sg:classifiers":[
        {
            "category":"Professional",
            "subcategory":"Computer Services",
            "type":"Services"
        }
    ],
    "sg:phone":"+32 9 240 15 11",
    "sg:postcode":"9000",
    "sg:province":"Oost-Vlaanderen",
    "sg:tags":[
        "-",
        "processing",
        "data",
        "software"
    ],
    "wof:name":"E&y Consulting",
    "wof:placetype":"venue"
},
  "geometry": {"coordinates":[3.7341060638,51.0292472839],"type":"Point"}
}