{
  "type": "Feature",
  "properties": {
    "addr:full":"Peerdsbosstraat 16 Herentals Antwerpen 2200",
    "addr:housenumber":"16",
    "addr:postcode":"2200",
    "addr:street":"Peerdsbosstraat",
    "iso:country":"BE",
    "sg:address":"Peerdsbosstraat 16",
    "sg:city":"Herentals",
    "sg:orig_category":"Gespecialiseerde residenti\u00eble bouw",
    "sg:phone":"+32 14 23 23 56",
    "sg:postcode":"2200",
    "sg:province":"Antwerpen",
    "wof:name":"Patrick Verlooy",
    "wof:placetype":"venue"
},
  "geometry": {"coordinates":[4.8271508217,51.1825256348],"type":"Point"}
}