{
  "type": "Feature",
  "properties": {
    "iso:country":"BE",
    "sg:address":"Leopoldplein 10",
    "sg:city":"Menen",
    "sg:classifiers":[
        {
            "category":"Bars & Pubs",
            "type":"Food & Drink"
        }
    ],
    "sg:phone":"+32 56 51 35 16",
    "sg:postcode":"8930",
    "sg:province":"West-Vlaanderen",
    "wof:name":"Barnou",
    "wof:placetype":"venue"
},
  "geometry": {"coordinates":[3.1258130074,50.7959823608],"type":"Point"}
}