{
  "type": "Feature",
  "properties": {
    "addr:full":"Kluizenhof 8ba Sint-gillis-waas Oost-Vlaanderen 9170",
    "addr:postcode":"9170",
    "addr:street":"Kluizenhof;Oost-Vlaanderen",
    "iso:country":"BE",
    "sg:address":"Kluizenhof 8ba",
    "sg:city":"Sint-gillis-waas",
    "sg:orig_category":"Meubelzaken, woning- and keukeninrichting",
    "sg:phone":"+32 3 727 13 75",
    "sg:postcode":"9170",
    "sg:province":"Oost-Vlaanderen",
    "wof:name":"Interieurs",
    "wof:placetype":"venue"
},
  "geometry": {"coordinates":[4.0986437798,51.2291984558],"type":"Point"}
}