{
  "type": "Feature",
  "properties": {
    "addr:full":"Zandbergstraat 80 Harelbeke West-Vlaanderen 8530",
    "addr:housenumber":"80",
    "addr:postcode":"8530",
    "addr:street":"Zandbergstraat",
    "iso:country":"BE",
    "sg:address":"Zandbergstraat 80",
    "sg:city":"Harelbeke",
    "sg:orig_category":"Ordinateurs Fab. R\u00e9alisation de programmes and logiciels. Ordinateurs and \u00e9quipement informatique",
    "sg:phone":"+32 56 21 00 92",
    "sg:postcode":"8530",
    "sg:province":"West-Vlaanderen",
    "wof:name":"C.p.s.",
    "wof:placetype":"venue"
},
  "geometry": {"coordinates":[3.2911651134,50.8389053345],"type":"Point"}
}