{
  "type": "Feature",
  "properties": {
    "addr:full":"Manitobalaan 46 Gistel West-Vlaanderen 8470",
    "addr:housenumber":"46",
    "addr:postcode":"8470",
    "addr:street":"Manitobalaan",
    "iso:country":"BE",
    "sg:address":"Manitobalaan 46",
    "sg:city":"Gistel",
    "sg:classifiers":[
        {
            "category":"Home & Garden",
            "subcategory":"Furniture",
            "type":"Retail Goods"
        }
    ],
    "sg:phone":"+32 59 27 62 93",
    "sg:postcode":"8470",
    "sg:province":"West-Vlaanderen",
    "sg:tags":[
        "wood"
    ],
    "wof:name":"Leirman & Zonen Bvba",
    "wof:placetype":"venue"
},
  "geometry": {"coordinates":[2.9568009377,51.1593360901],"type":"Point"}
}