{
  "type": "Feature",
  "properties": {
    "iso:country":"BE",
    "sg:address":"Rue De P\u00c2turages 122",
    "sg:city":"Quaregnon",
    "sg:orig_category":"Brood, gebak and snoepgoed",
    "sg:phone":"+32 65 67 11 57",
    "sg:postcode":"7390",
    "sg:province":"Hainaut",
    "wof:name":"P\u00c2tisserie Karel",
    "wof:placetype":"venue"
},
  "geometry": {"coordinates":[3.8640999794,50.4222679138],"type":"Point"}
}