{
  "type": "Feature",
  "properties": {
    "iso:country":"BE",
    "sg:address":"Maastrichterstraat 106",
    "sg:city":"Tongeren",
    "sg:orig_category":"Swatch. Bijouteries and horlogeries. R\u00e9parations d'horloges, montres and bijoux",
    "sg:phone":"+32 12 23 14 90",
    "sg:postcode":"3700",
    "sg:province":"Limburg",
    "wof:name":"Julien Rogister",
    "wof:placetype":"venue"
},
  "geometry": {"coordinates":[5.468146801,50.7828025818],"type":"Point"}
}