{
  "type": "Feature",
  "properties": {
    "addr:full":"Veldstraat 1 Moorslede West-Vlaanderen 8890",
    "addr:housenumber":"1",
    "addr:postcode":"8890",
    "addr:street":"Veldstraat",
    "iso:country":"BE",
    "sg:address":"Veldstraat 1",
    "sg:city":"Moorslede",
    "sg:classifiers":[
        {
            "category":"Health Services",
            "subcategory":"Health Practitioner",
            "type":"Services"
        }
    ],
    "sg:phone":"+32 51 77 82 24",
    "sg:postcode":"8890",
    "sg:province":"West-Vlaanderen",
    "sg:tags":[
        "physiotherapist"
    ],
    "wof:name":"Lefevre Christiaan",
    "wof:placetype":"venue"
},
  "geometry": {"coordinates":[3.0649950504,50.8951148987],"type":"Point"}
}