{
  "type": "Feature",
  "properties": {
    "iso:country":"BE",
    "sg:address":"Centre 28",
    "sg:city":"Thimister-clermont (thimister)",
    "sg:classifiers":[
        {
            "category":"Bars & Pubs",
            "type":"Food & Drink"
        }
    ],
    "sg:phone":"+32 87 44 60 66",
    "sg:postcode":"4890",
    "sg:province":"Li\u00e8ge",
    "wof:name":"Centre (du)",
    "wof:placetype":"venue"
},
  "geometry": {"coordinates":[5.8636670113,50.6536064148],"type":"Point"}
}