{
  "type": "Feature",
  "properties": {
    "iso:country":"BE",
    "sg:address":"J.p. Minckelersstraat 19",
    "sg:city":"Leuven",
    "sg:orig_category":"Advocaten and juridische adviseurs",
    "sg:phone":"+32 16 31 08 10",
    "sg:postcode":"3000",
    "sg:province":"Vlaams-Brabant",
    "wof:name":"Karolien Lysens",
    "wof:placetype":"venue"
},
  "geometry": {"coordinates":[4.7076568604,50.8817520142],"type":"Point"}
}