{
  "type": "Feature",
  "properties": {
    "addr:full":"Muziekbosstraat 13 Ronse/renaix Oost-Vlaanderen 9600",
    "addr:housenumber":"13",
    "addr:postcode":"9600",
    "addr:street":"Muziekbosstraat",
    "iso:country":"BE",
    "sg:address":"Muziekbosstraat 13",
    "sg:city":"Ronse/renaix",
    "sg:orig_category":"Paramedische behandelingen",
    "sg:phone":"+32 55 21 53 93",
    "sg:postcode":"9600",
    "sg:province":"Oost-Vlaanderen",
    "wof:name":"K. Carteus",
    "wof:placetype":"venue"
},
  "geometry": {"coordinates":[3.6311349869,50.7605781555],"type":"Point"}
}