{
  "type": "Feature",
  "properties": {
    "iso:country":"BE",
    "sg:address":"Rue L\u00e9on Theodor 123",
    "sg:city":"Bruxelles (jette)",
    "sg:classifiers":[
        {
            "category":"Personal",
            "subcategory":"Shoe Repair & Shine",
            "type":"Services"
        }
    ],
    "sg:phone":"+32 476 41 22 09",
    "sg:postcode":"1090",
    "sg:province":"Bruxelles-Capitale",
    "sg:tags":[
        "shoemaker"
    ],
    "wof:name":"Patrick",
    "wof:placetype":"venue"
},
  "geometry": {"coordinates":[4.3281450272,50.8765907288],"type":"Point"}
}