{
  "type": "Feature",
  "properties": {
    "addr:full":"Sint-jozefslaan 37 Mol Antwerpen 2400",
    "addr:housenumber":"37",
    "addr:postcode":"2400",
    "addr:street":"Sint-Jozefslaan",
    "iso:country":"BE",
    "sg:address":"Sint-jozefslaan 37",
    "sg:city":"Mol",
    "sg:classifiers":[
        {
            "category":"Shopping",
            "subcategory":"Florist",
            "type":"Retail Goods"
        }
    ],
    "sg:phone":"+32 14 81 28 00",
    "sg:postcode":"2400",
    "sg:province":"Antwerpen",
    "wof:name":"Florista",
    "wof:placetype":"venue"
},
  "geometry": {"coordinates":[5.2126708031,51.194858551],"type":"Point"}
}