{
  "type": "Feature",
  "properties": {
    "addr:full":"Poelstraat 48 Lebbeke Oost-Vlaanderen 9280",
    "addr:housenumber":"48",
    "addr:postcode":"9280",
    "addr:street":"Poelstraat",
    "iso:country":"BE",
    "sg:address":"Poelstraat 48",
    "sg:city":"Lebbeke",
    "sg:orig_category":"Technische studies and ingenieursactiviteiten",
    "sg:phone":"+32 52 41 03 18",
    "sg:postcode":"9280",
    "sg:province":"Oost-Vlaanderen",
    "wof:name":"Mikpunt",
    "wof:placetype":"venue"
},
  "geometry": {"coordinates":[4.1503567696,51.0109672546],"type":"Point"}
}