{
  "type": "Feature",
  "properties": {
    "addr:full":"Heidestraat 35 Ham (kwaadmechelen) Limburg 3945",
    "addr:housenumber":"35",
    "addr:postcode":"kwaadmechelen;3945",
    "addr:street":"Heidestraat",
    "iso:country":"BE",
    "sg:address":"Heidestraat 35",
    "sg:city":"Ham (kwaadmechelen)",
    "sg:orig_category":"Autombile concessionaires",
    "sg:phone":"+32 13 66 14 67",
    "sg:postcode":"3945",
    "sg:province":"Limburg",
    "wof:name":"Gar Lemmens",
    "wof:placetype":"venue"
},
  "geometry": {"coordinates":[5.1776199341,51.1046104431],"type":"Point"}
}