{
  "type": "Feature",
  "properties": {
    "addr:full":"Azaleastraat 56 Lovendegem Oost-Vlaanderen 9920",
    "addr:housenumber":"56",
    "addr:postcode":"9920",
    "addr:street":"Azaleastraat",
    "iso:country":"BE",
    "sg:address":"Azaleastraat 56",
    "sg:city":"Lovendegem",
    "sg:orig_category":"Centres de relaxation and bien-\u00eatre",
    "sg:phone":"+32 9 372 64 84",
    "sg:postcode":"9920",
    "sg:province":"Oost-Vlaanderen",
    "wof:name":"Sauna Asteria",
    "wof:placetype":"venue"
},
  "geometry": {"coordinates":[3.6414980888,51.1029014587],"type":"Point"}
}