{
  "type": "Feature",
  "properties": {
    "addr:full":"Staatsbaan 72 Lanaken Limburg 3620",
    "addr:housenumber":"72",
    "addr:postcode":"3620",
    "addr:street":"Staatsbaan",
    "iso:country":"BE",
    "sg:address":"Staatsbaan 72",
    "sg:city":"Lanaken",
    "sg:orig_category":"Antiquit\u00e9s",
    "sg:phone":"+32 89 76 36 93",
    "sg:postcode":"3620",
    "sg:province":"Limburg",
    "wof:name":"V. Zeegers",
    "wof:placetype":"venue"
},
  "geometry": {"coordinates":[5.6816759109,50.9105987549],"type":"Point"}
}