{
  "type": "Feature",
  "properties": {
    "addr:full":"Groenendaallaan 111 Antwerpen Antwerpen 2170",
    "addr:housenumber":"111",
    "addr:postcode":"2170",
    "addr:street":"Groenendaallaan",
    "iso:country":"BE",
    "sg:address":"Groenendaallaan 111",
    "sg:city":"Antwerpen",
    "sg:orig_category":"Supermarch\u00e9s",
    "sg:phone":"+32 3 646 32 62",
    "sg:postcode":"2170",
    "sg:province":"Antwerpen",
    "wof:name":"Colruyt",
    "wof:placetype":"venue"
},
  "geometry": {"coordinates":[4.4505147934,51.246723175],"type":"Point"}
}