{
  "type": "Feature",
  "properties": {
    "iso:country":"BE",
    "sg:address":"Kapellestraat 48",
    "sg:city":"Deinze",
    "sg:orig_category":"Herstelling horloges and juwelen Juwelen and horloges",
    "sg:phone":"+32 9 380 16 26",
    "sg:postcode":"9800",
    "sg:province":"Oost-Vlaanderen",
    "wof:name":"Huis Josiane",
    "wof:placetype":"venue"
},
  "geometry": {"coordinates":[3.5479300022,50.9813995361],"type":"Point"}
}