{
  "type": "Feature",
  "properties": {
    "addr:full":"Kruishoutemsesteenweg 39 Zingem Oost-Vlaanderen 9750",
    "addr:housenumber":"39",
    "addr:postcode":"9750",
    "addr:street":"Kruishoutemsesteenweg",
    "iso:country":"BE",
    "sg:address":"Kruishoutemsesteenweg 39",
    "sg:city":"Zingem",
    "sg:classifiers":[
        {
            "category":"Communications",
            "subcategory":"Television Station",
            "type":"Services"
        }
    ],
    "sg:phone":"+32 9 384 11 86",
    "sg:postcode":"9750",
    "sg:province":"Oost-Vlaanderen",
    "sg:tags":[
        "de",
        "production",
        "spectacle"
    ],
    "wof:name":"Fanfare St.cecilia",
    "wof:placetype":"venue"
},
  "geometry": {"coordinates":[3.6488780975,50.906665802],"type":"Point"}
}