{
  "type": "Feature",
  "properties": {
    "addr:full":"Huybrechtsstraat 3 Antwerpen Antwerpen 2060",
    "addr:housenumber":"3",
    "addr:postcode":"2060",
    "addr:street":"Huybrechtsstraat",
    "iso:country":"BE",
    "sg:address":"Huybrechtsstraat 3",
    "sg:city":"Antwerpen",
    "sg:orig_category":"Huisvuilophaling and -verwerking",
    "sg:phone":"+32 3 236 64 20",
    "sg:postcode":"2060",
    "sg:province":"Antwerpen",
    "wof:name":"Environm. Resources Mngt",
    "wof:placetype":"venue"
},
  "geometry": {"coordinates":[4.4303569794,51.2184562683],"type":"Point"}
}