{
  "type": "Feature",
  "properties": {
    "addr:full":"Sint-rochuslaan 104 Kortrijk West-Vlaanderen 8500",
    "addr:housenumber":"104",
    "addr:postcode":"8500",
    "iso:country":"BE",
    "sg:address":"Sint-rochuslaan 104",
    "sg:city":"Kortrijk",
    "sg:classifiers":[
        {
            "category":"Parking",
            "subcategory":"Lot",
            "type":"Transportation"
        }
    ],
    "sg:phone":"+32 56 31 01 37",
    "sg:postcode":"8500",
    "sg:province":"West-Vlaanderen",
    "sg:tags":[
        "parking-places",
        "laying-out"
    ],
    "wof:name":"Vercruysse B",
    "wof:placetype":"venue"
},
  "geometry": {"coordinates":[3.2702879906,50.817150116],"type":"Point"}
}