{
  "type": "Feature",
  "properties": {
    "addr:full":"Rue De La Rivelaine 2 Charleroi Hainaut 6061",
    "addr:housenumber":"2",
    "addr:postcode":"6061",
    "addr:street":"Rue De La Rivelaine;Hainaut",
    "iso:country":"BE",
    "sg:address":"Rue De La Rivelaine 2",
    "sg:city":"Charleroi",
    "sg:orig_category":"Secr\u00e9tariats sociaux",
    "sg:phone":"+32 71 31 30 41",
    "sg:postcode":"6061",
    "sg:province":"Hainaut",
    "wof:name":"Secr\u00c9t. Social Groupe S",
    "wof:placetype":"venue"
},
  "geometry": {"coordinates":[4.4566278458,50.4068374634],"type":"Point"}
}