{
  "type": "Feature",
  "properties": {
    "iso:country":"BE",
    "sg:address":"Nederstraat 17b Box 4",
    "sg:city":"Hoeselt",
    "sg:classifiers":[
        {
            "category":"Utilities",
            "subcategory":"Telephone",
            "type":"Services"
        }
    ],
    "sg:phone":"+32 89 50 36 16",
    "sg:postcode":"3730",
    "sg:province":"Limburg",
    "sg:tags":[
        "-",
        "internet"
    ],
    "wof:name":"Anima Gfx",
    "wof:placetype":"venue"
},
  "geometry": {"coordinates":[5.4851369858,50.869884491],"type":"Point"}
}