{
  "type": "Feature",
  "properties": {
    "iso:country":"BE",
    "sg:address":"E3-plein Belvedere 43",
    "sg:city":"Gent",
    "sg:orig_category":"Services Erotiques et d'Escorte",
    "sg:phone":"+32 475 83 81 84",
    "sg:postcode":"9000",
    "sg:province":"Oost-Vlaanderen",
    "wof:name":"Angel",
    "wof:placetype":"venue"
},
  "geometry": {"coordinates":[3.6956379414,51.0475692749],"type":"Point"}
}