{
  "type": "Feature",
  "properties": {
    "addr:full":"Hogekouterstraat 90 Gent (mariakerke) Oost-Vlaanderen 9030",
    "addr:housenumber":"90",
    "addr:postcode":"9030",
    "addr:street":"Hogekouterstraat",
    "iso:country":"BE",
    "sg:address":"Hogekouterstraat 90",
    "sg:city":"Gent (mariakerke)",
    "sg:classifiers":[
        {
            "category":"Parking",
            "subcategory":"Bicycle",
            "type":"Transportation"
        }
    ],
    "sg:phone":"+32 9 227 65 94",
    "sg:postcode":"9030",
    "sg:province":"Oost-Vlaanderen",
    "sg:tags":[
        "chiropodist"
    ],
    "wof:name":"Zanders R",
    "wof:placetype":"venue"
},
  "geometry": {"coordinates":[3.7004499435,51.0751800537],"type":"Point"}
}