{
  "type": "Feature",
  "properties": {
    "iso:country":"BE",
    "sg:address":"Bedrijvenstr 4",
    "sg:city":"Sint-truiden",
    "sg:classifiers":[
        {
            "category":"Shopping",
            "subcategory":"Hobbies, Toys, & Games",
            "type":"Retail Goods"
        }
    ],
    "sg:phone":"+32 11 68 74 62",
    "sg:postcode":"3800",
    "sg:province":"Limburg",
    "sg:tags":[
        "product",
        "miscellaneous",
        "entertainment"
    ],
    "wof:name":"Werti Nv",
    "wof:placetype":"venue"
},
  "geometry": {"coordinates":[5.2116570473,50.8112373352],"type":"Point"}
}