{
  "type": "Feature",
  "properties": {
    "addr:full":"Dorp 35 Aalst Oost-Vlaanderen 9310",
    "addr:housenumber":"35",
    "addr:postcode":"9310",
    "addr:street":"Dorp",
    "iso:country":"BE",
    "sg:address":"Dorp 35",
    "sg:city":"Aalst",
    "sg:classifiers":[
        {
            "category":"Cafe",
            "type":"Food & Drink"
        }
    ],
    "sg:phone":"+32 52 35 54 22",
    "sg:postcode":"9310",
    "sg:province":"Oost-Vlaanderen",
    "sg:tags":[
        "caf\u00e9s"
    ],
    "wof:name":"Caf\u00c9 De Kastelein",
    "wof:placetype":"venue"
},
  "geometry": {"coordinates":[4.098400116,50.9477767944],"type":"Point"}
}