{
  "type": "Feature",
  "properties": {
    "iso:country":"BE",
    "sg:address":"Bevingen 19",
    "sg:city":"Ninove (neigem)",
    "sg:classifiers":[
        {
            "category":"Freight",
            "type":"Transportation"
        }
    ],
    "sg:phone":"+32 54 34 20 04",
    "sg:postcode":"9403",
    "sg:province":"Oost-Vlaanderen",
    "sg:tags":[
        "-",
        "transport"
    ],
    "wof:name":"Trans T M",
    "wof:placetype":"venue"
},
  "geometry": {"coordinates":[4.0594549179,50.8027954102],"type":"Point"}
}