{
  "type": "Feature",
  "properties": {
    "iso:country":"BE",
    "sg:address":"Grote Daalstraat 176",
    "sg:city":"Zaventem",
    "sg:orig_category":"Kapsalons",
    "sg:phone":"+32 2 720 47 64",
    "sg:postcode":"1930",
    "sg:province":"Vlaams-Brabant",
    "wof:name":"Coiffure Paolo",
    "wof:placetype":"venue"
},
  "geometry": {"coordinates":[4.4701089859,50.8721847534],"type":"Point"}
}