{
  "type": "Feature",
  "properties": {
    "iso:country":"BE",
    "sg:address":"Steenweg Op Hoogstraten 2",
    "sg:city":"Merksplas",
    "sg:orig_category":"Meubelzaken, woning- and keukeninrichting",
    "sg:phone":"+32 14 63 31 92",
    "sg:postcode":"2330",
    "sg:province":"Antwerpen",
    "wof:name":"Merksplas Meubelpaleis",
    "wof:placetype":"venue"
},
  "geometry": {"coordinates":[4.8588218689,51.3618736267],"type":"Point"}
}