{
  "type": "Feature",
  "properties": {
    "addr:full":"Rue Antoine Br\u00e9art 71 Bruxelles (saint-gilles) Bruxelles-Capitale 1060",
    "addr:housenumber":"71",
    "addr:postcode":"1060",
    "addr:street":"Rue Antoine Bre\u0301Art",
    "iso:country":"BE",
    "sg:address":"Rue Antoine Br\u00e9art 71",
    "sg:city":"Bruxelles (saint-gilles)",
    "sg:classifiers":[
        {
            "category":"Real Estate",
            "subcategory":"Architect",
            "type":"Services"
        }
    ],
    "sg:phone":"+32 2 537 01 26",
    "sg:postcode":"1060",
    "sg:province":"Bruxelles-Capitale",
    "wof:name":"Poulet E",
    "wof:placetype":"venue"
},
  "geometry": {"coordinates":[4.3471088409,50.8237037659],"type":"Point"}
}