{
  "type": "Feature",
  "properties": {
    "iso:country":"BE",
    "sg:address":"Jan Baptist Van Der Lindenstraat 55",
    "sg:city":"Lennik (sint-kwintens-lennik)",
    "sg:classifiers":[
        {
            "category":"Wholesale",
            "subcategory":"Wine & Distilled Alcoholic Beverages",
            "type":"Manufacturing & Wholesale Goods"
        }
    ],
    "sg:phone":"+32 2 532 43 16",
    "sg:postcode":"1750",
    "sg:province":"Vlaams-Brabant",
    "sg:tags":[
        "whol",
        "-",
        "spirit",
        "mfg"
    ],
    "wof:name":"Vandam Oscar Bvba",
    "wof:placetype":"venue"
},
  "geometry": {"coordinates":[4.1574420929,50.8028869629],"type":"Point"}
}