{
  "type": "Feature",
  "properties": {
    "iso:country":"BE",
    "sg:address":"Dobbelenbergstraat 115",
    "sg:city":"Brussel/bruxelles",
    "sg:orig_category":"Voertuigen",
    "sg:phone":"+32 2 215 74 71",
    "sg:postcode":"1130",
    "sg:province":"Bruxelles-Capitale",
    "wof:name":"La Ferrar\u00c8se",
    "wof:placetype":"venue"
},
  "geometry": {"coordinates":[4.4171171188,50.9047355652],"type":"Point"}
}