{
  "type": "Feature",
  "properties": {
    "iso:country":"BE",
    "sg:address":"Duffelstraat 59",
    "sg:city":"Sint-katelijne-waver",
    "sg:orig_category":"Sportclubs",
    "sg:phone":"+32 15 31 52 14",
    "sg:postcode":"2860",
    "sg:province":"Antwerpen",
    "wof:name":"Noordervereniging",
    "wof:placetype":"venue"
},
  "geometry": {"coordinates":[4.5108838081,51.0771026611],"type":"Point"}
}