{
  "type": "Feature",
  "properties": {
    "addr:full":"Rue Institut Dogniaux 98 Charleroi Hainaut 6040",
    "addr:housenumber":"98",
    "addr:postcode":"6040",
    "addr:street":"Rue Institut Dogniaux;Hainaut",
    "iso:country":"BE",
    "sg:address":"Rue Institut Dogniaux 98",
    "sg:city":"Charleroi",
    "sg:orig_category":"Traitements param\u00e9dicaux",
    "sg:phone":"+32 71 35 22 21",
    "sg:postcode":"6040",
    "sg:province":"Hainaut",
    "wof:name":"Rectem",
    "wof:placetype":"venue"
},
  "geometry": {"coordinates":[4.406607151,50.4407691956],"type":"Point"}
}