{
  "type": "Feature",
  "properties": {
    "addr:full":"Lange Nieuwstraat 68 Antwerpen Antwerpen 2000",
    "addr:housenumber":"68",
    "addr:postcode":"2000",
    "addr:street":"Lange Nieuwstraat",
    "iso:country":"BE",
    "sg:address":"Lange Nieuwstraat 68",
    "sg:city":"Antwerpen",
    "sg:classifiers":[
        {
            "category":"Professional",
            "subcategory":"Advertising",
            "type":"Services"
        }
    ],
    "sg:phone":"+32 3 234 87 20",
    "sg:postcode":"2000",
    "sg:province":"Antwerpen",
    "sg:tags":[
        "agency"
    ],
    "wof:name":"Scholz & Friends Brussels S.a.",
    "wof:placetype":"venue"
},
  "geometry": {"coordinates":[4.4102311134,51.2195129395],"type":"Point"}
}