{
  "type": "Feature",
  "properties": {
    "addr:full":"Route De Spa 15 Stoumont Li\u00e8ge 4987",
    "addr:housenumber":"15",
    "addr:postcode":"4987",
    "addr:street":"Route De Spa",
    "iso:country":"BE",
    "sg:address":"Route De Spa 15",
    "sg:city":"Stoumont",
    "sg:orig_category":"Herstellingen and onderhoud van auto's",
    "sg:phone":"+32 475 26 04 32",
    "sg:postcode":"4987",
    "sg:province":"Li\u00e8ge",
    "wof:name":"N. Neuville",
    "wof:placetype":"venue"
},
  "geometry": {"coordinates":[5.8068637848,50.411945343],"type":"Point"}
}