{
  "type": "Feature",
  "properties": {
    "addr:full":"Schoonheidsleerlaan 0 Bredene West-Vlaanderen 8450",
    "addr:housenumber":"0",
    "addr:postcode":"8450",
    "addr:street":"Schoonheidsleerlaan",
    "iso:country":"BE",
    "sg:address":"Schoonheidsleerlaan 0",
    "sg:city":"Bredene",
    "sg:orig_category":"Enseignement maternel and primaire",
    "sg:phone":"+32 59 32 11 36",
    "sg:postcode":"8450",
    "sg:province":"West-Vlaanderen",
    "wof:name":"Basisschool",
    "wof:placetype":"venue"
},
  "geometry": {"coordinates":[2.9495089054,51.2419471741],"type":"Point"}
}