{
  "type": "Feature",
  "properties": {
    "iso:country":"BE",
    "sg:address":"Kauwplasstraat 15",
    "sg:city":"Halen",
    "sg:orig_category":"Fruitteelt",
    "sg:phone":"+32 13 46 10 22",
    "sg:postcode":"3545",
    "sg:province":"Limburg",
    "wof:name":"Peter Vanthienen",
    "wof:placetype":"venue"
},
  "geometry": {"coordinates":[5.0743350983,50.9384346008],"type":"Point"}
}