{
  "type": "Feature",
  "properties": {
    "iso:country":"BE",
    "sg:address":"Hoge-kamstraat 1",
    "sg:city":"Diksmuide",
    "sg:orig_category":"Pluimveekwekers Varkenskwekers",
    "sg:phone":"+32 51 50 10 30",
    "sg:postcode":"8600",
    "sg:province":"West-Vlaanderen",
    "wof:name":"Willy Bracquez",
    "wof:placetype":"venue"
},
  "geometry": {"coordinates":[2.9035289288,51.016330719],"type":"Point"}
}