{
  "type": "Feature",
  "properties": {
    "iso:country":"BE",
    "sg:address":"9470",
    "sg:city":"Denderleeuw (grand)",
    "sg:orig_category":"Pharmaciens",
    "sg:phone":"+32 900 10 500",
    "sg:postcode":"9470",
    "sg:province":"Oost-Vlaanderen",
    "wof:name":"Pharmacies De Garde",
    "wof:placetype":"venue"
},
  "geometry": {"coordinates":[4.0806999207,50.8829154968],"type":"Point"}
}