{
  "type": "Feature",
  "properties": {
    "addr:full":"Kroonstraat 25 Lier Antwerpen 2500",
    "addr:housenumber":"25",
    "addr:postcode":"2500",
    "addr:street":"Kroonstraat",
    "iso:country":"BE",
    "sg:address":"Kroonstraat 25",
    "sg:city":"Lier",
    "sg:classifiers":[
        {
            "category":"Retail",
            "subcategory":"Funeral Services",
            "type":"Services"
        }
    ],
    "sg:phone":"+32 3 480 28 80",
    "sg:postcode":"2500",
    "sg:province":"Antwerpen",
    "sg:tags":[
        "director"
    ],
    "wof:name":"Hellemans K",
    "wof:placetype":"venue"
},
  "geometry": {"coordinates":[4.5852799416,51.1269302368],"type":"Point"}
}