{
  "type": "Feature",
  "properties": {
    "addr:full":"Porte Des Aveugles 12 Huy Li\u00e8ge 4500",
    "addr:housenumber":"porte;12",
    "addr:postcode":"4500",
    "addr:street":"Des Aveugles",
    "iso:country":"BE",
    "sg:address":"Porte Des Aveugles 12",
    "sg:city":"Huy",
    "sg:orig_category":"Krantenwinkels Rookartikelen",
    "sg:phone":"+32 85 21 13 53",
    "sg:postcode":"4500",
    "sg:province":"Li\u00e8ge",
    "wof:name":"Librairie Quoidbach",
    "wof:placetype":"venue"
},
  "geometry": {"coordinates":[5.2299628258,50.5252761841],"type":"Point"}
}