{
  "type": "Feature",
  "properties": {
    "addr:full":"Hasseltsebaan 112 Hechtel-eksel (hechtel) Limburg 3940",
    "addr:housenumber":"112",
    "addr:postcode":"3940",
    "addr:street":"Hasseltsebaan",
    "iso:country":"BE",
    "sg:address":"Hasseltsebaan 112",
    "sg:city":"Hechtel-eksel (hechtel)",
    "sg:classifiers":[
        {
            "category":"Personal",
            "subcategory":"Nail Salon",
            "type":"Services"
        }
    ],
    "sg:phone":"+32 11 73 44 87",
    "sg:postcode":"3940",
    "sg:province":"Limburg",
    "sg:tags":[
        "pedicure"
    ],
    "wof:name":"Spelmans B",
    "wof:placetype":"venue"
},
  "geometry": {"coordinates":[5.3746128082,51.0967674255],"type":"Point"}
}