{
  "type": "Feature",
  "properties": {
    "iso:country":"BE",
    "sg:address":"Brunnenstrasse 5",
    "sg:city":"Bntgenbach/bntgenbach",
    "sg:orig_category":"Travaux de pl\u00e2trage",
    "sg:phone":"+32 80 44 62 18",
    "sg:postcode":"4750",
    "sg:province":"Li\u00e8ge",
    "wof:name":"Werner Becker",
    "wof:placetype":"venue"
},
  "geometry": {"coordinates":[6.1657848358,50.4320526123],"type":"Point"}
}