{
  "type": "Feature",
  "properties": {
    "iso:country":"BE",
    "sg:address":"Leiestraat 42",
    "sg:city":"Kortrijk",
    "sg:classifiers":[
        {
            "category":"Retail",
            "subcategory":"Repair Shop",
            "type":"Services"
        }
    ],
    "sg:phone":"+32 56 25 77 88",
    "sg:postcode":"8500",
    "sg:province":"West-Vlaanderen",
    "sg:tags":[
        "-",
        "mainten",
        "watch",
        "clock"
    ],
    "wof:name":"Kheops Juwelier",
    "wof:placetype":"venue"
},
  "geometry": {"coordinates":[3.2646620274,50.8293228149],"type":"Point"}
}