{
  "type": "Feature",
  "properties": {
    "addr:full":"Monnikenwerve 26 Brugge West-Vlaanderen 8000",
    "addr:housenumber":"26",
    "addr:postcode":"8000",
    "addr:street":"Monnikenwerve",
    "iso:country":"BE",
    "sg:address":"Monnikenwerve 26",
    "sg:city":"Brugge",
    "sg:classifiers":[
        {
            "category":"Farming",
            "subcategory":"Fish & Marine Products",
            "type":"Manufacturing & Wholesale Goods"
        }
    ],
    "sg:phone":"+32 50 31 67 14",
    "sg:postcode":"8000",
    "sg:province":"West-Vlaanderen",
    "sg:tags":[
        "retail",
        "-",
        "shellfish"
    ],
    "wof:name":"Dieter Nv",
    "wof:placetype":"venue"
},
  "geometry": {"coordinates":[3.1987841129,51.2481193542],"type":"Point"}
}