{
  "type": "Feature",
  "properties": {
    "iso:country":"BE",
    "sg:address":"Paardskerkhofstraat 20",
    "sg:city":"Heers",
    "sg:orig_category":"Offices du tourisme",
    "sg:phone":"+32 11 48 01 07",
    "sg:postcode":"3870",
    "sg:province":"Limburg",
    "wof:name":"Dienst Voor Toerisme",
    "wof:placetype":"venue"
},
  "geometry": {"coordinates":[5.2950620651,50.7529182434],"type":"Point"}
}