{
  "type": "Feature",
  "properties": {
    "addr:full":"Bertogne 33 Bertogne Luxembourg 6687",
    "addr:housenumber":"33",
    "addr:postcode":"6687",
    "addr:street":"Bertogne",
    "iso:country":"BE",
    "sg:address":"Bertogne 33",
    "sg:city":"Bertogne",
    "sg:classifiers":[
        {
            "category":"Retail",
            "subcategory":"Veterinary Services",
            "type":"Services"
        }
    ],
    "sg:phone":"+32 61 21 20 29",
    "sg:postcode":"6687",
    "sg:province":"Luxembourg",
    "sg:tags":[
        "veterinarian"
    ],
    "wof:name":"Faisant J",
    "wof:placetype":"venue"
},
  "geometry": {"coordinates":[5.6645569801,50.0807113647],"type":"Point"}
}