{
  "type": "Feature",
  "properties": {
    "addr:full":"Slachthuislaan 70 Antwerpen Antwerpen 2060",
    "addr:housenumber":"70",
    "addr:postcode":"2060",
    "addr:street":"Slachthuislaan",
    "iso:country":"BE",
    "sg:address":"Slachthuislaan 70",
    "sg:city":"Antwerpen",
    "sg:classifiers":[
        {
            "category":"Wholesale",
            "subcategory":"Meat",
            "type":"Manufacturing & Wholesale Goods"
        }
    ],
    "sg:phone":"+32 3 235 70 10",
    "sg:postcode":"2060",
    "sg:province":"Antwerpen",
    "sg:tags":[
        "whol",
        "-"
    ],
    "wof:name":"Van Den Bulck Bvba",
    "wof:placetype":"venue"
},
  "geometry": {"coordinates":[4.4370069504,51.2294235229],"type":"Point"}
}