{
  "type": "Feature",
  "properties": {
    "iso:country":"BE",
    "sg:address":"Braambeslaan 29",
    "sg:city":"Brecht",
    "sg:classifiers":[
        {
            "category":"Banks & Credit Unions",
            "subcategory":"Bureau De Change",
            "type":"Services"
        }
    ],
    "sg:phone":"+32 3 663 86 64",
    "sg:postcode":"2960",
    "sg:province":"Antwerpen",
    "sg:tags":[
        "measuring",
        "control",
        "apparatus"
    ],
    "wof:name":"Bowi Pumps & Levels Bvba",
    "wof:placetype":"venue"
},
  "geometry": {"coordinates":[4.6415200233,51.3512115479],"type":"Point"}
}