{
  "type": "Feature",
  "properties": {
    "iso:country":"BE",
    "sg:address":"Place De La Victoire 1",
    "sg:city":"Verviers",
    "sg:classifiers":[
        {
            "category":"Health Services",
            "subcategory":"Health Practitioner",
            "type":"Services"
        }
    ],
    "sg:phone":"+32 87 22 63 11",
    "sg:postcode":"4800",
    "sg:province":"Li\u00e8ge",
    "sg:tags":[
        "physiotherapist"
    ],
    "wof:name":"Corteil A",
    "wof:placetype":"venue"
},
  "geometry": {"coordinates":[5.8558912277,50.5888824463],"type":"Point"}
}