{
  "type": "Feature",
  "properties": {
    "iso:country":"BE",
    "sg:address":"Loddershoekstraat 2",
    "sg:city":"Liedekerke",
    "sg:orig_category":"Installatie van houten of kunststof schrijnwerk",
    "sg:phone":"+32 53 66 96 32",
    "sg:postcode":"1770",
    "sg:province":"Vlaams-Brabant",
    "wof:name":"Frans Gheysels",
    "wof:placetype":"venue"
},
  "geometry": {"coordinates":[4.0869340897,50.8681983948],"type":"Point"}
}