{
  "type": "Feature",
  "properties": {
    "addr:full":"Martelarenlaan 245 Box 301 Leuven (kessel-lo) Vlaams-Brabant 3010",
    "addr:housenumber":"245;301",
    "addr:postcode":"3010",
    "addr:street":"Martelarenlaan;Box",
    "iso:country":"BE",
    "sg:address":"Martelarenlaan 245 Box 301",
    "sg:city":"Leuven (kessel-lo)",
    "sg:classifiers":[
        {
            "category":"Health Services",
            "subcategory":"Health Practitioner",
            "type":"Services"
        }
    ],
    "sg:phone":"+32 16 35 34 01",
    "sg:postcode":"3010",
    "sg:province":"Vlaams-Brabant",
    "sg:tags":[
        "psychologist"
    ],
    "wof:name":"Mertens M",
    "wof:placetype":"venue"
},
  "geometry": {"coordinates":[4.7304501534,50.889755249],"type":"Point"}
}