{
  "type": "Feature",
  "properties": {
    "iso:country":"BE",
    "sg:address":"Komedieplaats 15",
    "sg:city":"Antwerpen",
    "sg:classifiers":[
        {
            "category":"Shopping",
            "subcategory":"Clothing, Apparel, & Fashions",
            "type":"Retail Goods"
        }
    ],
    "sg:phone":"+32 3 226 21 44",
    "sg:postcode":"2000",
    "sg:province":"Antwerpen",
    "sg:tags":[
        "boutique"
    ],
    "wof:name":"Gigue",
    "wof:placetype":"venue"
},
  "geometry": {"coordinates":[4.4064922333,51.2163505554],"type":"Point"}
}