{
  "type": "Feature",
  "properties": {
    "addr:full":"Rue De La Cour 7 Thuin Hainaut 6536",
    "addr:housenumber":"7",
    "addr:postcode":"6536",
    "addr:street":"Rue De La Cour",
    "iso:country":"BE",
    "sg:address":"Rue De La Cour 7",
    "sg:city":"Thuin",
    "sg:orig_category":"Pain, p\u00e2tisseries and confiseries",
    "sg:phone":"+32 71 53 32 82",
    "sg:postcode":"6536",
    "sg:province":"Hainaut",
    "wof:name":"Jacques Helson",
    "wof:placetype":"venue"
},
  "geometry": {"coordinates":[4.3285741806,50.2942123413],"type":"Point"}
}