{
  "type": "Feature",
  "properties": {
    "addr:full":"Korenheide 15 Huldenberg (loonbeek) Vlaams-Brabant 3040",
    "addr:housenumber":"15",
    "addr:postcode":"3040",
    "addr:street":"Korenheide",
    "iso:country":"BE",
    "sg:address":"Korenheide 15",
    "sg:city":"Huldenberg (loonbeek)",
    "sg:classifiers":[
        {
            "category":"Professional",
            "subcategory":"Management & Consulting",
            "type":"Services"
        }
    ],
    "sg:phone":"+32 16 47 47 99",
    "sg:postcode":"3040",
    "sg:province":"Vlaams-Brabant",
    "sg:tags":[
        "-",
        "processing",
        "data",
        "consultant"
    ],
    "wof:name":"Windmill Consulting",
    "wof:placetype":"venue"
},
  "geometry": {"coordinates":[4.6014900208,50.8041038513],"type":"Point"}
}