{
  "type": "Feature",
  "properties": {
    "iso:country":"BE",
    "sg:address":"Westvleterseweg 40",
    "sg:city":"Poperinge",
    "sg:orig_category":"Huishoudapparaten, televisies and radio's Verhuur televisie- and audiovisuele apparatuur Verlichting",
    "sg:phone":"+32 57 33 88 98",
    "sg:postcode":"8970",
    "sg:province":"West-Vlaanderen",
    "wof:name":"Martin Decrock",
    "wof:placetype":"venue"
},
  "geometry": {"coordinates":[2.7358689308,50.8733482361],"type":"Point"}
}