{
  "type": "Feature",
  "properties": {
    "addr:full":"Rue Du Chapitre 4 Fosses-la-ville Namur 5070",
    "addr:housenumber":"4",
    "addr:postcode":"5070",
    "addr:street":"Rue Du Chapitre",
    "iso:country":"BE",
    "sg:address":"Rue Du Chapitre 4",
    "sg:city":"Fosses-la-ville",
    "sg:classifiers":[
        {
            "category":"Transit Center",
            "subcategory":"Freight",
            "type":"Transportation"
        }
    ],
    "sg:phone":"+32 475 80 63 02",
    "sg:postcode":"5070",
    "sg:province":"Namur",
    "sg:tags":[
        "import",
        "export",
        "-"
    ],
    "wof:name":"Stepan J",
    "wof:placetype":"venue"
},
  "geometry": {"coordinates":[4.6968541145,50.3964576721],"type":"Point"}
}