{
  "type": "Feature",
  "properties": {
    "iso:country":"BE",
    "sg:address":"Kortrijkse Heerweg 53",
    "sg:city":"Deerlijk",
    "sg:orig_category":"V\u00e9hicules automobiles",
    "sg:phone":"+32 56 71 20 05",
    "sg:postcode":"8540",
    "sg:province":"West-Vlaanderen",
    "wof:name":"Garage Vandenbogaerde",
    "wof:placetype":"venue"
},
  "geometry": {"coordinates":[3.3442718983,50.8516960144],"type":"Point"}
}