{
  "type": "Feature",
  "properties": {
    "iso:country":"BE",
    "sg:address":"Noorderlaan 31ba",
    "sg:city":"Antwerpen",
    "sg:orig_category":"Herstellingen and onderhoud van auto's",
    "sg:phone":"+32 3 544 95 67",
    "sg:postcode":"2030",
    "sg:province":"Antwerpen",
    "wof:name":"P.c.s. Haven",
    "wof:placetype":"venue"
},
  "geometry": {"coordinates":[4.4193630219,51.2430038452],"type":"Point"}
}