{
  "type": "Feature",
  "properties": {
    "addr:full":"Petuniastraat 9 Watermaal-bosvoorde/watermael-boitsfort Bruxelles-Capitale 1170",
    "addr:housenumber":"9",
    "addr:postcode":"1170",
    "addr:street":"Petuniastraat",
    "iso:country":"BE",
    "sg:address":"Petuniastraat 9",
    "sg:city":"Watermaal-bosvoorde/watermael-boitsfort",
    "sg:orig_category":"Sportclubs",
    "sg:phone":"+32 2 673 31 45",
    "sg:postcode":"1170",
    "sg:province":"Bruxelles-Capitale",
    "wof:name":"P.c. Le Flor\u00c9al",
    "wof:placetype":"venue"
},
  "geometry": {"coordinates":[4.421189785,50.8103141785],"type":"Point"}
}