{
  "type": "Feature",
  "properties": {
    "iso:country":"BE",
    "sg:address":"Route De March\u00c9 44",
    "sg:city":"Ferrieres",
    "sg:orig_category":"Epiceries",
    "sg:phone":"+32 4 369 41 26",
    "sg:postcode":"4190",
    "sg:province":"Li\u00e8ge",
    "wof:name":"Dominique Bougard",
    "wof:placetype":"venue"
},
  "geometry": {"coordinates":[5.6087150574,50.4363670349],"type":"Point"}
}