{
  "type": "Feature",
  "properties": {
    "iso:country":"BE",
    "sg:address":"Ropswalle 10",
    "sg:city":"Menen",
    "sg:orig_category":"Emballages en plastique Fab",
    "sg:phone":"+32 56 51 57 72",
    "sg:postcode":"8930",
    "sg:province":"West-Vlaanderen",
    "wof:name":"A.b.s.-plastic Union",
    "wof:placetype":"venue"
},
  "geometry": {"coordinates":[3.102009058,50.788974762],"type":"Point"}
}