{
  "type": "Feature",
  "properties": {
    "addr:full":"Rue Saint-m\u00e9dard 20-22 Jodoigne Brabant Wallon 1370",
    "addr:postcode":"20-22;1370",
    "addr:street":"Rue Saint-Me\u0301Dard",
    "iso:country":"BE",
    "sg:address":"Rue Saint-m\u00e9dard 20-22",
    "sg:city":"Jodoigne",
    "sg:classifiers":[
        {
            "category":"Shopping",
            "subcategory":"Shoes",
            "type":"Retail Goods"
        }
    ],
    "sg:phone":"+32 10 81 12 51",
    "sg:postcode":"1370",
    "sg:province":"Brabant Wallon",
    "sg:tags":[
        "slipper",
        "-"
    ],
    "wof:name":"Merveille (la)",
    "wof:placetype":"venue"
},
  "geometry": {"coordinates":[4.8684921265,50.7225761414],"type":"Point"}
}