{
  "type": "Feature",
  "properties": {
    "addr:full":"Rue Naimette 12 Li\u00e8ge 1 Li\u00e8ge 4000",
    "addr:housenumber":"12;1",
    "addr:postcode":"4000",
    "addr:street":"Rue Naimette",
    "iso:country":"BE",
    "sg:address":"Rue Naimette 12",
    "sg:city":"Li\u00e8ge 1",
    "sg:classifiers":[
        {
            "category":"Wholesale",
            "subcategory":"Books, Periodicals, & Newspapers",
            "type":"Manufacturing & Wholesale Goods"
        }
    ],
    "sg:phone":"+32 4 225 16 75",
    "sg:postcode":"4000",
    "sg:province":"Li\u00e8ge",
    "sg:tags":[
        "publisher"
    ],
    "wof:name":"Pire L",
    "wof:placetype":"venue"
},
  "geometry": {"coordinates":[5.5640649796,50.6498565674],"type":"Point"}
}