{
  "type": "Feature",
  "properties": {
    "addr:full":"Rue G\u00e9rard Waelkens 2 Geer Li\u00e8ge 4250",
    "addr:housenumber":"2",
    "addr:postcode":"4250",
    "addr:street":"Rue Ge\u0301Rard Waelkens",
    "iso:country":"BE",
    "sg:address":"Rue G\u00e9rard Waelkens 2",
    "sg:city":"Geer",
    "sg:classifiers":[
        {
            "category":"Health Services",
            "subcategory":"Dentist",
            "type":"Services"
        }
    ],
    "sg:phone":"+32 19 58 85 95",
    "sg:postcode":"4250",
    "sg:province":"Li\u00e8ge",
    "wof:name":"Remy-paquay Pascal",
    "wof:placetype":"venue"
},
  "geometry": {"coordinates":[5.1705231667,50.669380188],"type":"Point"}
}