{
  "type": "Feature",
  "properties": {
    "iso:country":"BE",
    "sg:address":"Lierbaan 122",
    "sg:city":"Putte",
    "sg:classifiers":[
        {
            "category":"Insurance",
            "subcategory":"Insurance Agent",
            "type":"Services"
        }
    ],
    "sg:phone":"+32 15 76 15 55",
    "sg:postcode":"2580",
    "sg:province":"Antwerpen",
    "sg:tags":[
        "verzekeringsmakelaars",
        "expert"
    ],
    "wof:name":"Bureau Geeraerts-phan",
    "wof:placetype":"venue"
},
  "geometry": {"coordinates":[4.6283221245,51.0588798523],"type":"Point"}
}