{
  "type": "Feature",
  "properties": {
    "iso:country":"BE",
    "sg:address":"Kerkstraat 17",
    "sg:city":"Schilde",
    "sg:orig_category":"Toeristische diensten",
    "sg:phone":"+32 3 658 90 34",
    "sg:postcode":"2970",
    "sg:province":"Antwerpen",
    "wof:name":"V.v.v. Voorkempen",
    "wof:placetype":"venue"
},
  "geometry": {"coordinates":[4.5831718445,51.2397689819],"type":"Point"}
}