{
  "type": "Feature",
  "properties": {
    "iso:country":"BE",
    "sg:address":"Rue L.vandenhoven 55b",
    "sg:city":"Evere",
    "sg:orig_category":"Jardinage",
    "sg:phone":"+32 2 242 91 13",
    "sg:postcode":"1140",
    "sg:province":"Bruxelles-Capitale",
    "wof:name":"Fizaine J.-c.",
    "wof:placetype":"venue"
},
  "geometry": {"coordinates":[4.4057731628,50.8827285767],"type":"Point"}
}