{
  "type": "Feature",
  "properties": {
    "iso:country":"BE",
    "sg:address":"Scheepstraat 6",
    "sg:city":"Maasmechelen",
    "sg:classifiers":[
        {
            "category":"Banks & Credit Unions",
            "subcategory":"Financial Services",
            "type":"Services"
        }
    ],
    "sg:phone":"+32 89 76 04 50",
    "sg:postcode":"3630",
    "sg:province":"Limburg",
    "sg:tags":[
        "lens",
        "lens-shades",
        "hood"
    ],
    "wof:name":"Rolma Nv",
    "wof:placetype":"venue"
},
  "geometry": {"coordinates":[5.6971240044,50.9493942261],"type":"Point"}
}