{
  "type": "Feature",
  "properties": {
    "iso:country":"BE",
    "sg:address":"Place Du Conseil 8",
    "sg:city":"Anderlecht/anderlecht",
    "sg:orig_category":"Epiceries",
    "sg:phone":"+32 2 522 88 85",
    "sg:postcode":"1070",
    "sg:province":"Bruxelles-Capitale",
    "wof:name":"Umut",
    "wof:placetype":"venue"
},
  "geometry": {"coordinates":[4.3301701546,50.838973999],"type":"Point"}
}