{
  "type": "Feature",
  "properties": {
    "addr:full":"Pastoor D. Vanhautestraat 17 Kortemark (handzame) West-Vlaanderen 8610",
    "addr:housenumber":"17",
    "addr:postcode":"8610",
    "addr:street":"Pastoor D. Vanhautestraat",
    "iso:country":"BE",
    "sg:address":"Pastoor D. Vanhautestraat 17",
    "sg:city":"Kortemark (handzame)",
    "sg:classifiers":[
        {
            "category":"Bars & Pubs",
            "type":"Food & Drink"
        }
    ],
    "sg:phone":"+32 51 57 09 25",
    "sg:postcode":"8610",
    "sg:province":"West-Vlaanderen",
    "wof:name":"Zoeten Inval (de)",
    "wof:placetype":"venue"
},
  "geometry": {"coordinates":[3.0424630642,51.0276832581],"type":"Point"}
}