{
  "type": "Feature",
  "properties": {
    "addr:full":"Sint-martinusstraat 12 Westerlo Antwerpen 2260",
    "addr:housenumber":"12",
    "addr:postcode":"2260",
    "addr:street":"Sint-Martinusstraat",
    "iso:country":"BE",
    "sg:address":"Sint-martinusstraat 12",
    "sg:city":"Westerlo",
    "sg:classifiers":[
        {
            "category":"Banks & Credit Unions",
            "subcategory":"Investment Brokerage",
            "type":"Services"
        }
    ],
    "sg:phone":"+32 14 54 59 97",
    "sg:postcode":"2260",
    "sg:province":"Antwerpen",
    "sg:tags":[
        "repair",
        "-",
        "installation",
        "sanitary",
        "article"
    ],
    "wof:name":"K S M",
    "wof:placetype":"venue"
},
  "geometry": {"coordinates":[4.9155201912,51.0921516418],"type":"Point"}
}