{
  "type": "Feature",
  "properties": {
    "iso:country":"BE",
    "sg:address":"Vorsinkbaan 24",
    "sg:city":"Haaltert",
    "sg:orig_category":"Paramedische behandelingen",
    "sg:phone":"+32 53 83 76 45",
    "sg:postcode":"9450",
    "sg:province":"Oost-Vlaanderen",
    "wof:name":"M. Van Den Bremd",
    "wof:placetype":"venue"
},
  "geometry": {"coordinates":[3.977971077,50.9014167786],"type":"Point"}
}