{
  "type": "Feature",
  "properties": {
    "addr:full":"Beukenlaan 21a Rotselaar Vlaams-Brabant 3110",
    "addr:housenumber":"21a",
    "addr:postcode":"3110",
    "addr:street":"Beukenlaan",
    "iso:country":"BE",
    "sg:address":"Beukenlaan 21a",
    "sg:city":"Rotselaar",
    "sg:orig_category":"Instituts de beaut\u00e9. Traitements param\u00e9dicaux",
    "sg:phone":"+32 16 58 17 49",
    "sg:postcode":"3110",
    "sg:province":"Vlaams-Brabant",
    "wof:name":"Wery",
    "wof:placetype":"venue"
},
  "geometry": {"coordinates":[4.7107920647,50.9508590698],"type":"Point"}
}