{
  "type": "Feature",
  "properties": {
    "iso:country":"BE",
    "sg:address":"Driezenstraat 25",
    "sg:city":"Turnhout",
    "sg:orig_category":"Maatschappelijke dienstverlening",
    "sg:phone":"+32 14 42 35 83",
    "sg:postcode":"2300",
    "sg:province":"Antwerpen",
    "wof:name":"Kemp. Werkgr. Homofilie",
    "wof:placetype":"venue"
},
  "geometry": {"coordinates":[4.9472222328,51.3214263916],"type":"Point"}
}