{
  "type": "Feature",
  "properties": {
    "addr:full":"Les Digues 53 Theux Li\u00e8ge 4910",
    "addr:housenumber":"53",
    "addr:postcode":"4910",
    "addr:street":"Digues",
    "iso:country":"BE",
    "sg:address":"Les Digues 53",
    "sg:city":"Theux",
    "sg:orig_category":"Entretien and r\u00e9parations de voitures. D\u00e9taillants en pi\u00e8ces and accessoires de voitures",
    "sg:phone":"+32 87 77 32 17",
    "sg:postcode":"4910",
    "sg:province":"Li\u00e8ge",
    "wof:name":"G.s. Electric",
    "wof:placetype":"venue"
},
  "geometry": {"coordinates":[5.829269886,50.4939498901],"type":"Point"}
}