{
  "type": "Feature",
  "properties": {
    "addr:full":"Bondgenotenlaan 74 Leuven Vlaams-Brabant 3000",
    "addr:housenumber":"74",
    "addr:postcode":"3000",
    "addr:street":"Bondgenotenlaan",
    "iso:country":"BE",
    "sg:address":"Bondgenotenlaan 74",
    "sg:city":"Leuven",
    "sg:classifiers":[
        {
            "category":"Shopping",
            "subcategory":"Clothing, Apparel, & Fashions",
            "type":"Retail Goods"
        }
    ],
    "sg:phone":"+32 16 22 57 27",
    "sg:postcode":"3000",
    "sg:province":"Vlaams-Brabant",
    "sg:tags":[
        "boutique"
    ],
    "wof:name":"Madame",
    "wof:placetype":"venue"
},
  "geometry": {"coordinates":[4.7085571289,50.8800430298],"type":"Point"}
}