{
  "type": "Feature",
  "properties": {
    "iso:country":"BE",
    "sg:address":"Rue Du Parc Industriel 30",
    "sg:city":"Waremme",
    "sg:orig_category":"Koffie, thee, cacao and specerijen Gh",
    "sg:phone":"+32 19 32 27 78",
    "sg:postcode":"4300",
    "sg:province":"Li\u00e8ge",
    "wof:name":"Le Pays De La Sauce",
    "wof:placetype":"venue"
},
  "geometry": {"coordinates":[5.2721400261,50.6905212402],"type":"Point"}
}