{
  "type": "Feature",
  "properties": {
    "addr:full":"Rue Gustave Biot 22 Bruxelles (ixelles) Bruxelles-Capitale 1050",
    "addr:housenumber":"22",
    "addr:postcode":"1050",
    "addr:street":"Rue Gustave Biot",
    "iso:country":"BE",
    "sg:address":"Rue Gustave Biot 22",
    "sg:city":"Bruxelles (ixelles)",
    "sg:classifiers":[
        {
            "category":"Real Estate",
            "subcategory":"Architect",
            "type":"Services"
        }
    ],
    "sg:phone":"+32 2 646 46 20",
    "sg:postcode":"1050",
    "sg:province":"Bruxelles-Capitale",
    "wof:name":"Janssens De Varebeke G",
    "wof:placetype":"venue"
},
  "geometry": {"coordinates":[4.3801879883,50.8226127625],"type":"Point"}
}