{
  "type": "Feature",
  "properties": {
    "iso:country":"BE",
    "sg:address":"Koudekotstraat 19",
    "sg:city":"Heuvelland",
    "sg:orig_category":"Eleveurs de bovins",
    "sg:phone":"+32 57 44 45 75",
    "sg:postcode":"8951",
    "sg:province":"West-Vlaanderen",
    "wof:name":"Lucien Deconinck",
    "wof:placetype":"venue"
},
  "geometry": {"coordinates":[2.7635860443,50.7654380798],"type":"Point"}
}