{
  "type": "Feature",
  "properties": {
    "addr:full":"Stekelbesstraat 14 Westerlo Antwerpen 2260",
    "addr:housenumber":"14",
    "addr:postcode":"2260",
    "addr:street":"Stekelbesstraat",
    "iso:country":"BE",
    "sg:address":"Stekelbesstraat 14",
    "sg:city":"Westerlo",
    "sg:orig_category":"R\u00e9alisation de programmes and logiciels",
    "sg:phone":"+32 14 54 68 92",
    "sg:postcode":"2260",
    "sg:province":"Antwerpen",
    "wof:name":"Jag",
    "wof:placetype":"venue"
},
  "geometry": {"coordinates":[4.9032821655,51.0951004028],"type":"Point"}
}