{
  "type": "Feature",
  "properties": {
    "addr:full":"Chauss\u00e9e De Renaix 56 Tournai Hainaut 7500",
    "addr:housenumber":"56",
    "addr:postcode":"7500",
    "addr:street":"Chausse\u0301E De Renaix",
    "iso:country":"BE",
    "sg:address":"Chauss\u00e9e De Renaix 56",
    "sg:city":"Tournai",
    "sg:classifiers":[
        {
            "category":"Professional",
            "subcategory":"Testing Lab",
            "type":"Services"
        }
    ],
    "sg:phone":"+32 69 22 46 25",
    "sg:postcode":"7500",
    "sg:province":"Hainaut",
    "sg:tags":[
        "chemist"
    ],
    "wof:name":"Picart C",
    "wof:placetype":"venue"
},
  "geometry": {"coordinates":[3.4052679539,50.6135826111],"type":"Point"}
}