{
  "type": "Feature",
  "properties": {
    "iso:country":"BE",
    "sg:address":"Opperveldstraat 53",
    "sg:city":"Maasmechelen",
    "sg:classifiers":[
        {
            "category":"Professional",
            "subcategory":"Computer Services",
            "type":"Services"
        }
    ],
    "sg:phone":"+32 89 77 36 27",
    "sg:postcode":"3630",
    "sg:province":"Limburg",
    "sg:tags":[
        "webdesign",
        "-",
        "internet"
    ],
    "wof:name":"Webpagina-design",
    "wof:placetype":"venue"
},
  "geometry": {"coordinates":[5.6976079941,50.9577445984],"type":"Point"}
}