{
  "type": "Feature",
  "properties": {
    "iso:country":"BE",
    "sg:address":"Rue De La Croisette 61",
    "sg:city":"Eghezee",
    "sg:classifiers":[
        {
            "category":"Arena",
            "subcategory":"Sports Club",
            "type":"Entertainment"
        }
    ],
    "sg:phone":"+32 81 51 11 53",
    "sg:postcode":"5310",
    "sg:province":"Namur",
    "sg:tags":[
        "de"
    ],
    "wof:name":"A.c.n.a.m.",
    "wof:placetype":"venue"
},
  "geometry": {"coordinates":[4.9296159744,50.5382156372],"type":"Point"}
}