{
  "type": "Feature",
  "properties": {
    "iso:country":"BE",
    "sg:address":"Rue Dyna Beumer 1",
    "sg:city":"Rixensart",
    "sg:classifiers":[
        {
            "category":"Education",
            "subcategory":"School",
            "type":"Public Place"
        }
    ],
    "sg:phone":"+32 2 654 03 66",
    "sg:postcode":"1330",
    "sg:province":"Brabant Wallon",
    "sg:tags":[
        "-",
        "private"
    ],
    "wof:name":"Antoinette Smars Ateliers",
    "wof:placetype":"venue"
},
  "geometry": {"coordinates":[4.5083551407,50.7091598511],"type":"Point"}
}