{
  "type": "Feature",
  "properties": {
    "addr:full":"Smolderstraat 190 Herk-de-stad Limburg 3540",
    "addr:housenumber":"190",
    "addr:postcode":"3540",
    "addr:street":"Smolderstraat",
    "iso:country":"BE",
    "sg:address":"Smolderstraat 190",
    "sg:city":"Herk-de-stad",
    "sg:orig_category":"HUISBRANDOLIE",
    "sg:phone":"+32 11 58 18 09",
    "sg:postcode":"3540",
    "sg:province":"Limburg",
    "wof:name":"Luc Herbots",
    "wof:placetype":"venue"
},
  "geometry": {"coordinates":[5.1880531311,50.8975791931],"type":"Point"}
}