{
  "type": "Feature",
  "properties": {
    "addr:full":"Nederkouter 134 Gent Oost-Vlaanderen 9000",
    "addr:housenumber":"134",
    "addr:postcode":"9000",
    "addr:street":"Nederkouter;Oost-Vlaanderen",
    "iso:country":"BE",
    "sg:address":"Nederkouter 134",
    "sg:city":"Gent",
    "sg:classifiers":[
        {
            "category":"Organizations",
            "subcategory":"Professional Association",
            "type":"Services"
        }
    ],
    "sg:phone":"+32 9 265 71 62",
    "sg:postcode":"9000",
    "sg:province":"Oost-Vlaanderen",
    "sg:tags":[
        "call"
    ],
    "wof:name":"Ic Callcenter Nv",
    "wof:placetype":"venue"
},
  "geometry": {"coordinates":[3.7218930721,51.0465126038],"type":"Point"}
}