{
  "type": "Feature",
  "properties": {
    "addr:full":"Boulevard Lemonnier 121 Bruxellles Bruxelles-Capitale 1000",
    "addr:housenumber":"121",
    "addr:postcode":"1000",
    "addr:street":"Boulevard Lemonnier",
    "iso:country":"BE",
    "sg:address":"Boulevard Lemonnier 121",
    "sg:city":"Bruxellles",
    "sg:classifiers":[
        {
            "category":"Banks & Credit Unions",
            "subcategory":"Financial Services",
            "type":"Services"
        }
    ],
    "sg:phone":"+32 2 513 85 42",
    "sg:postcode":"1000",
    "sg:province":"Bruxelles-Capitale",
    "sg:tags":[
        "financier"
    ],
    "wof:name":"Atena Money Transfer / Bruxelles-midi",
    "wof:placetype":"venue"
},
  "geometry": {"coordinates":[-116.27327728269999,32.6635398865],"type":"Point"}
}