{
  "type": "Feature",
  "properties": {
    "addr:full":"Dorpsstraat 43 Zemst Vlaams-Brabant 1982",
    "addr:housenumber":"43",
    "addr:postcode":"1982",
    "addr:street":"Dorpsstraat;Vlaams-Brabant",
    "iso:country":"BE",
    "sg:address":"Dorpsstraat 43",
    "sg:city":"Zemst",
    "sg:classifiers":[
        {
            "category":"Personal",
            "subcategory":"Beauty Salon",
            "type":"Services"
        }
    ],
    "sg:phone":"+32 15 61 10 10",
    "sg:postcode":"1982",
    "sg:province":"Vlaams-Brabant",
    "sg:tags":[
        "de",
        "coiffure"
    ],
    "wof:name":"Coiffure Helene",
    "wof:placetype":"venue"
},
  "geometry": {"coordinates":[4.4793181419,50.9722557068],"type":"Point"}
}