{
  "type": "Feature",
  "properties": {
    "iso:country":"BE",
    "sg:address":"Wollestraat 19",
    "sg:city":"Brugge",
    "sg:orig_category":"V\u00eatements pour Dames. V\u00eatements de mariage and c\u00e9r\u00e9monies. V\u00eatements pour Hommes",
    "sg:phone":"+32 50 33 40 78",
    "sg:postcode":"8000",
    "sg:province":"West-Vlaanderen",
    "wof:name":"Huis De Kat",
    "wof:placetype":"venue"
},
  "geometry": {"coordinates":[3.2254750729,51.2080993652],"type":"Point"}
}