{
  "type": "Feature",
  "properties": {
    "addr:full":"Rue De Tourcoing 34 Mouscron Hainaut 7700",
    "addr:housenumber":"34",
    "addr:postcode":"7700",
    "addr:street":"Rue De Tourcoing",
    "iso:country":"BE",
    "sg:address":"Rue De Tourcoing 34",
    "sg:city":"Mouscron",
    "sg:classifiers":[
        {
            "category":"Food & Beverages",
            "subcategory":"Specialty",
            "type":"Retail Goods"
        }
    ],
    "sg:phone":"+32 56 34 47 42",
    "sg:postcode":"7700",
    "sg:province":"Hainaut",
    "sg:tags":[
        "health",
        "dietary",
        "-",
        "biological"
    ],
    "wof:name":"Produits Azaire",
    "wof:placetype":"venue"
},
  "geometry": {"coordinates":[3.2128710747,50.7438850403],"type":"Point"}
}