{
  "type": "Feature",
  "properties": {
    "addr:full":"Jules Steursstraat 61 Antwerpen (deurne) Antwerpen 2100",
    "addr:housenumber":"61",
    "addr:postcode":"2100",
    "addr:street":"Jules Steursstraat",
    "iso:country":"BE",
    "sg:address":"Jules Steursstraat 61",
    "sg:city":"Antwerpen (deurne)",
    "sg:classifiers":[
        {
            "category":"Freight",
            "type":"Transportation"
        }
    ],
    "sg:phone":"+32 3 325 09 15",
    "sg:postcode":"2100",
    "sg:province":"Antwerpen",
    "sg:tags":[
        "-",
        "transport"
    ],
    "wof:name":"Van Der Sanden E",
    "wof:placetype":"venue"
},
  "geometry": {"coordinates":[4.4586100578,51.2203941345],"type":"Point"}
}