{
  "type": "Feature",
  "properties": {
    "iso:country":"BE",
    "sg:address":"Place De La Bouxhe 10",
    "sg:city":"Chaudfontaine",
    "sg:orig_category":"Pharmaciens",
    "sg:phone":"+32 4 368 71 30",
    "sg:postcode":"4052",
    "sg:province":"Li\u00e8ge",
    "wof:name":"S. Thomas",
    "wof:placetype":"venue"
},
  "geometry": {"coordinates":[5.6384878159,50.5583229065],"type":"Point"}
}