{
  "type": "Feature",
  "properties": {
    "addr:full":"Place Saint-pierre 27-28b1 Etterbeek Bruxelles-Capitale 1040",
    "addr:postcode":"1040",
    "addr:street":"Place Saint-Pierre 27-28B1",
    "iso:country":"BE",
    "sg:address":"Place Saint-pierre 27-28b1",
    "sg:city":"Etterbeek",
    "sg:orig_category":"Informaticaconsulenten",
    "sg:phone":"+32 2 734 34 38",
    "sg:postcode":"1040",
    "sg:province":"Bruxelles-Capitale",
    "wof:name":"V D S Consulting Scris",
    "wof:placetype":"venue"
},
  "geometry": {"coordinates":[4.3960390091,50.8374671936],"type":"Point"}
}