{
  "type": "Feature",
  "properties": {
    "addr:full":"Koningin Elisabethlaan 114b2 Sint-niklaas Oost-Vlaanderen 9100",
    "addr:housenumber":"114b2",
    "addr:postcode":"9100",
    "addr:street":"Koningin Elisabethlaan",
    "iso:country":"BE",
    "sg:address":"Koningin Elisabethlaan 114b2",
    "sg:city":"Sint-niklaas",
    "sg:orig_category":"Quincailleries",
    "sg:phone":"+32 3 777 12 22",
    "sg:postcode":"9100",
    "sg:province":"Oost-Vlaanderen",
    "wof:name":"Huybrechts Waasland",
    "wof:placetype":"venue"
},
  "geometry": {"coordinates":[4.1549367905,51.1707801819],"type":"Point"}
}