{
  "type": "Feature",
  "properties": {
    "addr:full":"Heirbrugstraat 14 Lokeren Oost-Vlaanderen 9160",
    "addr:housenumber":"14",
    "addr:postcode":"9160",
    "addr:street":"Heirbrugstraat",
    "iso:country":"BE",
    "sg:address":"Heirbrugstraat 14",
    "sg:city":"Lokeren",
    "sg:classifiers":[
        {
            "category":"Professional",
            "subcategory":"Art Services",
            "type":"Services"
        }
    ],
    "sg:phone":"+32 9 348 10 29",
    "sg:postcode":"9160",
    "sg:province":"Oost-Vlaanderen",
    "sg:tags":[
        "picture",
        "framer"
    ],
    "wof:name":"Kader-in Bvba",
    "wof:placetype":"venue"
},
  "geometry": {"coordinates":[3.9815399647,51.1021194458],"type":"Point"}
}