{
  "type": "Feature",
  "properties": {
    "addr:full":"Chauss\u00c9e De Bruxelles 255 Wemmel/wemmel Vlaams-Brabant 1780",
    "addr:housenumber":"255",
    "addr:postcode":"1780",
    "addr:street":"Chausse\u0301E De Bruxelles",
    "iso:country":"BE",
    "sg:address":"Chauss\u00c9e De Bruxelles 255",
    "sg:city":"Wemmel/wemmel",
    "sg:orig_category":"Entretien and r\u00e9parations de voitures. Pi\u00e8ces and accessoires de v\u00e9hicules automobiles Stations-serv",
    "sg:phone":"+32 2 460 59 76",
    "sg:postcode":"1780",
    "sg:province":"Vlaams-Brabant",
    "wof:name":"Andre Panneels/a. Panneels",
    "wof:placetype":"venue"
},
  "geometry": {"coordinates":[4.3096590042,50.899772644],"type":"Point"}
}