{
  "type": "Feature",
  "properties": {
    "addr:full":"Rue De Montroeul 3 Qui\u00e9vrain Hainaut 7380",
    "addr:housenumber":"3",
    "addr:postcode":"7380",
    "addr:street":"Rue De Montroeul",
    "iso:country":"BE",
    "sg:address":"Rue De Montroeul 3",
    "sg:city":"Qui\u00e9vrain",
    "sg:orig_category":"Non-Classified Establishments",
    "sg:phone":"+32 65 43 09 16",
    "sg:postcode":"7380",
    "sg:province":"Hainaut",
    "wof:name":"Aux Manons",
    "wof:placetype":"venue"
},
  "geometry": {"coordinates":[3.684262991,50.4105567932],"type":"Point"}
}