{
  "type": "Feature",
  "properties": {
    "iso:country":"BE",
    "sg:address":"Leeuwstraat 66",
    "sg:city":"Gent",
    "sg:classifiers":[
        {
            "category":"Personal",
            "subcategory":"Beauty Salon",
            "type":"Services"
        }
    ],
    "sg:phone":"+32 9 225 60 84",
    "sg:postcode":"9000",
    "sg:province":"Oost-Vlaanderen",
    "sg:tags":[
        "de",
        "coiffure"
    ],
    "wof:name":"Lea Clemer",
    "wof:placetype":"venue"
},
  "geometry": {"coordinates":[3.7325179577,51.0397567749],"type":"Point"}
}