{
  "type": "Feature",
  "properties": {
    "iso:country":"BE",
    "sg:address":"Kronekalseide 295",
    "sg:city":"Maldegem",
    "sg:orig_category":"Diverse juridische dienstverlening",
    "sg:phone":"+32 50 71 97 21",
    "sg:postcode":"9990",
    "sg:province":"Oost-Vlaanderen",
    "wof:name":"Verkoopzaal Chris",
    "wof:placetype":"venue"
},
  "geometry": {"coordinates":[3.3850739002,51.2055358887],"type":"Point"}
}