{
  "type": "Feature",
  "properties": {
    "iso:country":"BE",
    "sg:address":"Mechelsesteenweg 48",
    "sg:city":"Kampenhout",
    "sg:orig_category":"Diverse zakelijke dienstverlening",
    "sg:phone":"+32 16 61 84 00",
    "sg:postcode":"1910",
    "sg:province":"Vlaams-Brabant",
    "wof:name":"Ac Team",
    "wof:placetype":"venue"
},
  "geometry": {"coordinates":[4.5856599808,50.9607658386],"type":"Point"}
}