{
  "type": "Feature",
  "properties": {
    "addr:full":"Place Du March\u00c9 12 Saint-hubert Luxembourg 6870",
    "addr:housenumber":"12",
    "addr:postcode":"6870",
    "addr:street":"Place Du Marche\u0301",
    "iso:country":"BE",
    "sg:address":"Place Du March\u00c9 12",
    "sg:city":"Saint-hubert",
    "sg:orig_category":"Banques and organismes de cr\u00e9dit",
    "sg:phone":"+32 61 61 11 84",
    "sg:postcode":"6870",
    "sg:province":"Luxembourg",
    "wof:name":"Dexia",
    "wof:placetype":"venue"
},
  "geometry": {"coordinates":[5.3731408119,50.0256729126],"type":"Point"}
}