{
  "type": "Feature",
  "properties": {
    "addr:full":"Zavelstraat 12a Sint-lievens-houtem (vlierzele) Oost-Vlaanderen 9520",
    "addr:housenumber":"12a",
    "addr:postcode":"9520",
    "addr:street":"Zavelstraat",
    "iso:country":"BE",
    "sg:address":"Zavelstraat 12a",
    "sg:city":"Sint-lievens-houtem (vlierzele)",
    "sg:classifiers":[
        {
            "category":"Arena",
            "subcategory":"Sports Club",
            "type":"Entertainment"
        }
    ],
    "sg:phone":"+32 53 62 77 14",
    "sg:postcode":"9520",
    "sg:province":"Oost-Vlaanderen",
    "wof:name":"Sk Vlierzele Vzw",
    "wof:placetype":"venue"
},
  "geometry": {"coordinates":[3.905356884,50.9295501709],"type":"Point"}
}