{
  "type": "Feature",
  "properties": {
    "iso:country":"BE",
    "sg:address":"Avenue De Broqueville 194",
    "sg:city":"Sint-lambrechts-woluwe/woluwe-saint-lambert",
    "sg:orig_category":"Traitements param\u00e9dicaux",
    "sg:phone":"+32 2 770 90 96",
    "sg:postcode":"1200",
    "sg:province":"Bruxelles-Capitale",
    "wof:name":"Carlier",
    "wof:placetype":"venue"
},
  "geometry": {"coordinates":[4.4176969528,50.8421401978],"type":"Point"}
}