{
  "type": "Feature",
  "properties": {
    "iso:country":"BE",
    "sg:address":"Oudergemselaan 333",
    "sg:city":"Etterbeek/etterbeek",
    "sg:orig_category":"Diverse kredietdiensten",
    "sg:postcode":"1040",
    "sg:province":"Bruxelles-Capitale",
    "wof:name":"Bancontact-mister Cash",
    "wof:placetype":"venue"
},
  "geometry": {"coordinates":[4.389799118,50.8306884766],"type":"Point"}
}