{
  "type": "Feature",
  "properties": {
    "addr:full":"Rue Au Beurre 31 Bruxelles Bruxelles-Capitale 1000",
    "addr:housenumber":"31",
    "addr:postcode":"1000",
    "addr:street":"Rue Au Beurre",
    "iso:country":"BE",
    "sg:address":"Rue Au Beurre 31",
    "sg:city":"Bruxelles",
    "sg:classifiers":[
        {
            "category":"Bakery",
            "type":"Food & Drink"
        }
    ],
    "sg:phone":"+32 2 511 03 26",
    "sg:postcode":"1000",
    "sg:province":"Bruxelles-Capitale",
    "sg:tags":[
        "cake",
        "product",
        "related",
        "bread"
    ],
    "wof:name":"Biscuiterie Dandoy Sa",
    "wof:placetype":"venue"
},
  "geometry": {"coordinates":[4.3515558243,50.8474006653],"type":"Point"}
}