{
  "type": "Feature",
  "properties": {
    "addr:full":"Groothofstraat 20 Riemst Limburg 3770",
    "addr:housenumber":"20",
    "addr:postcode":"3770",
    "addr:street":"Groothofstraat",
    "iso:country":"BE",
    "sg:address":"Groothofstraat 20",
    "sg:city":"Riemst",
    "sg:orig_category":"WAPENS AND MUNITIE",
    "sg:phone":"+32 12 45 56 53",
    "sg:postcode":"3770",
    "sg:province":"Limburg",
    "wof:name":"Victor Parthoens",
    "wof:placetype":"venue"
},
  "geometry": {"coordinates":[5.5726618767,50.8125572205],"type":"Point"}
}