{
  "type": "Feature",
  "properties": {
    "addr:full":"Juniorslaan 78 Mechelen (groot) Antwerpen 2811",
    "addr:housenumber":"78",
    "addr:postcode":"2811",
    "addr:street":"Juniorslaan;Groot Antwerpen",
    "iso:country":"BE",
    "sg:address":"Juniorslaan 78",
    "sg:city":"Mechelen (groot)",
    "sg:classifiers":[
        {
            "category":"Personal",
            "subcategory":"Beauty Salon",
            "type":"Services"
        }
    ],
    "sg:phone":"+32 15 71 32 84",
    "sg:postcode":"2811",
    "sg:province":"Antwerpen",
    "sg:tags":[
        "de",
        "coiffure"
    ],
    "wof:name":"Christiane Verschuren",
    "wof:placetype":"venue"
},
  "geometry": {"coordinates":[4.3955931664,51.0318450928],"type":"Point"}
}