{
  "type": "Feature",
  "properties": {
    "iso:country":"BE",
    "sg:address":"Rue Beauregard 25",
    "sg:city":"Li\u00c8ge",
    "sg:orig_category":"M\u00e9decins and sp\u00e9cialistes",
    "sg:phone":"+32 4 341 55 58",
    "sg:postcode":"4020",
    "sg:province":"Li\u00e8ge",
    "wof:name":"Peter Bogaty",
    "wof:placetype":"venue"
},
  "geometry": {"coordinates":[5.5837678909,50.6408309937],"type":"Point"}
}