{
  "type": "Feature",
  "properties": {
    "iso:country":"BE",
    "sg:address":"R\u00e9sidence Bel Air 3-5",
    "sg:city":"Ch\u00e2telet (ch\u00e2telineau)",
    "sg:classifiers":[
        {
            "category":"Health Services",
            "subcategory":"Health Practitioner",
            "type":"Services"
        }
    ],
    "sg:phone":"+32 71 38 60 57",
    "sg:postcode":"6200",
    "sg:province":"Hainaut",
    "sg:tags":[
        "physiotherapist"
    ],
    "wof:name":"Toussaint S",
    "wof:placetype":"venue"
},
  "geometry": {"coordinates":[4.5158061981,50.430267334],"type":"Point"}
}