{
  "type": "Feature",
  "properties": {
    "addr:full":"Rue G\u00c9ry Naveau 16 Erquelinnes Hainaut 6560",
    "addr:housenumber":"16",
    "addr:postcode":"6560",
    "addr:street":"Rue Ge\u0301Ry Naveau",
    "iso:country":"BE",
    "sg:address":"Rue G\u00c9ry Naveau 16",
    "sg:city":"Erquelinnes",
    "sg:orig_category":"Slagers",
    "sg:phone":"+32 64 77 11 34",
    "sg:postcode":"6560",
    "sg:province":"Hainaut",
    "wof:name":"Alain Devaux",
    "wof:placetype":"venue"
},
  "geometry": {"coordinates":[4.0766000748,50.3330383301],"type":"Point"}
}