{
  "type": "Feature",
  "properties": {
    "addr:full":"Euphrosina Beernaertstr. 83b2 Oostende West-Vlaanderen 8400",
    "addr:housenumber":"83b2",
    "addr:postcode":"8400",
    "addr:street":"Beernaertstr.",
    "iso:country":"BE",
    "sg:address":"Euphrosina Beernaertstr. 83b2",
    "sg:city":"Oostende",
    "sg:orig_category":"Avocats and conseillers juridiques",
    "sg:phone":"+32 59 70 22 47",
    "sg:postcode":"8400",
    "sg:province":"West-Vlaanderen",
    "wof:name":"Yves Miroir",
    "wof:placetype":"venue"
},
  "geometry": {"coordinates":[2.9093110561,51.2268943787],"type":"Point"}
}