{
  "type": "Feature",
  "properties": {
    "addr:full":"Rue Des Iles 14 Florenville Luxembourg 6821",
    "addr:housenumber":"14",
    "addr:postcode":"6821",
    "addr:street":"Rue Des Iles",
    "iso:country":"BE",
    "sg:address":"Rue Des Iles 14",
    "sg:city":"Florenville",
    "sg:classifiers":[
        {
            "category":"Cafe",
            "type":"Food & Drink"
        }
    ],
    "sg:phone":"+32 61 31 49 21",
    "sg:postcode":"6821",
    "sg:province":"Luxembourg",
    "sg:tags":[
        "caf\u00e9s"
    ],
    "wof:name":"Caf\u00c9 Le Panorama",
    "wof:placetype":"venue"
},
  "geometry": {"coordinates":[5.324529171,49.7104721069],"type":"Point"}
}