{
  "type": "Feature",
  "properties": {
    "addr:full":"Avenue Du Vieux Fr\u00c8ne 33 Gerpinnes Hainaut 6280",
    "addr:housenumber":"33",
    "addr:postcode":"6280",
    "addr:street":"Avenue Du Vieux Fre\u0300Ne;Hainaut",
    "iso:country":"BE",
    "sg:address":"Avenue Du Vieux Fr\u00c8ne 33",
    "sg:city":"Gerpinnes",
    "sg:orig_category":"Ordinateurs and \u00e9quipement informatique",
    "sg:phone":"+32 71 43 00 62",
    "sg:postcode":"6280",
    "sg:province":"Hainaut",
    "wof:name":"Hendrick Software",
    "wof:placetype":"venue"
},
  "geometry": {"coordinates":[4.4793891907,50.3720245361],"type":"Point"}
}