{
  "type": "Feature",
  "properties": {
    "addr:full":"Oordegemkouter 92 Lede Oost-Vlaanderen 9340",
    "addr:housenumber":"92",
    "addr:postcode":"9340",
    "addr:street":"Oordegemkouter",
    "iso:country":"BE",
    "sg:address":"Oordegemkouter 92",
    "sg:city":"Lede",
    "sg:orig_category":"Landmeters",
    "sg:phone":"+32 9 366 08 34",
    "sg:postcode":"9340",
    "sg:province":"Oost-Vlaanderen",
    "wof:name":"Luc Goethals",
    "wof:placetype":"venue"
},
  "geometry": {"coordinates":[3.9118309021,50.9621124268],"type":"Point"}
}