{
  "type": "Feature",
  "properties": {
    "addr:full":"Haut Rejet 13 Celles Hainaut 7760",
    "addr:housenumber":"13",
    "addr:postcode":"7760",
    "addr:street":"Haut Rejet",
    "iso:country":"BE",
    "sg:address":"Haut Rejet 13",
    "sg:city":"Celles",
    "sg:orig_category":"Instituts de beaut\u00e9",
    "sg:phone":"+32 69 45 45 40",
    "sg:postcode":"7760",
    "sg:province":"Hainaut",
    "wof:name":"S. Coup\u00c9",
    "wof:placetype":"venue"
},
  "geometry": {"coordinates":[3.4885261059,50.6978797913],"type":"Point"}
}