{
  "type": "Feature",
  "properties": {
    "iso:country":"BE",
    "sg:address":"Avenue Brousten 26",
    "sg:city":"Jette",
    "sg:classifiers":[
        {
            "category":"Banks & Credit Unions",
            "subcategory":"Bureau De Change",
            "type":"Services"
        }
    ],
    "sg:phone":"+32 2 425 09 05",
    "sg:postcode":"1090",
    "sg:province":"Bruxelles-Capitale",
    "sg:tags":[
        "restaurant",
        "organisation",
        "\u00c0",
        "domicile",
        "fast",
        "catering",
        "livraison",
        "f\u00cates",
        "restaurants"
    ],
    "wof:name":"Adrienne Et Yves",
    "wof:placetype":"venue"
},
  "geometry": {"coordinates":[4.3295850754,50.8734817505],"type":"Point"}
}