{
  "type": "Feature",
  "properties": {
    "addr:full":"Rue Des Ecomines 15 Spa Li\u00e8ge 4900",
    "addr:housenumber":"15",
    "addr:postcode":"4900",
    "addr:street":"Rue Des Ecomines",
    "iso:country":"BE",
    "sg:address":"Rue Des Ecomines 15",
    "sg:city":"Spa",
    "sg:orig_category":"Jeux and jouets",
    "sg:phone":"+32 87 77 03 80",
    "sg:postcode":"4900",
    "sg:province":"Li\u00e8ge",
    "wof:name":"Maison Le Marmot",
    "wof:placetype":"venue"
},
  "geometry": {"coordinates":[5.865585804,50.4908943176],"type":"Point"}
}