{
  "type": "Feature",
  "properties": {
    "iso:country":"BE",
    "sg:address":"Eekhoornlaan 10",
    "sg:city":"Schilde ('s Gravenwezel)",
    "sg:classifiers":[
        {
            "category":"Health Services",
            "subcategory":"Doctor",
            "type":"Services"
        }
    ],
    "sg:phone":"+32 3 658 00 95",
    "sg:postcode":"2970",
    "sg:province":"Antwerpen",
    "sg:tags":[
        "psychotherapist",
        "psychoanalyst"
    ],
    "wof:name":"Aertbeli\u00cbn Mieke Cv",
    "wof:placetype":"venue"
},
  "geometry": {"coordinates":[4.5567908287,51.2525444031],"type":"Point"}
}