{
  "type": "Feature",
  "properties": {
    "addr:full":"Paleizenstraat 88 Schaarbeek/schaerbeek Bruxelles-Capitale 1030",
    "addr:housenumber":"88",
    "addr:postcode":"1030",
    "addr:street":"Paleizenstraat",
    "iso:country":"BE",
    "sg:address":"Paleizenstraat 88",
    "sg:city":"Schaarbeek/schaerbeek",
    "sg:orig_category":"Muziekinstrumenten",
    "sg:phone":"+32 2 215 11 18",
    "sg:postcode":"1030",
    "sg:province":"Bruxelles-Capitale",
    "wof:name":"Maison Puissance",
    "wof:placetype":"venue"
},
  "geometry": {"coordinates":[4.3671422005,50.8619194031],"type":"Point"}
}