{
  "type": "Feature",
  "properties": {
    "addr:full":"Markt 8 Herk Limburg 3910",
    "addr:housenumber":"8",
    "addr:postcode":"3910",
    "addr:street":"Markt",
    "iso:country":"BE",
    "sg:address":"Markt 8",
    "sg:city":"Herk",
    "sg:classifiers":[
        {
            "category":"Banks & Credit Unions",
            "subcategory":"Bank",
            "type":"Services"
        }
    ],
    "sg:phone":"+32 13 55 11 89",
    "sg:postcode":"3910",
    "sg:province":"Limburg",
    "wof:name":"Banque Bruxelles Lambert Sa",
    "wof:placetype":"venue"
},
  "geometry": {"coordinates":[5.4310479164,51.2294769287],"type":"Point"}
}