{
  "type": "Feature",
  "properties": {
    "addr:full":"Prof.o.rubbrechtstraat 21 Poperinge West-Vlaanderen 8972",
    "addr:housenumber":"21",
    "addr:postcode":"8972",
    "addr:street":"Prof.O.Rubbrechtstraat",
    "iso:country":"BE",
    "sg:address":"Prof.o.rubbrechtstraat 21",
    "sg:city":"Poperinge",
    "sg:orig_category":"Epiceries",
    "sg:phone":"+32 57 30 05 85",
    "sg:postcode":"8972",
    "sg:province":"West-Vlaanderen",
    "wof:name":"Johan Buseyne",
    "wof:placetype":"venue"
},
  "geometry": {"coordinates":[2.6248500347,50.918598175],"type":"Point"}
}