{
  "type": "Feature",
  "properties": {
    "addr:full":"Pont De Sommeleville 1a Box 14 Verviers Li\u00e8ge 4800",
    "addr:housenumber":"1a box 14",
    "addr:postcode":"4800",
    "addr:street":"Pont;Sommeleville",
    "iso:country":"BE",
    "sg:address":"Pont De Sommeleville 1a Box 14",
    "sg:city":"Verviers",
    "sg:classifiers":[
        {
            "category":"Professional",
            "subcategory":"Computer Services",
            "type":"Services"
        }
    ],
    "sg:phone":"+32 87 31 64 18",
    "sg:postcode":"4800",
    "sg:province":"Li\u00e8ge",
    "sg:tags":[
        "-",
        "processing",
        "data"
    ],
    "wof:name":"Nemotique",
    "wof:placetype":"venue"
},
  "geometry": {"coordinates":[5.8700032234,50.5942230225],"type":"Point"}
}