{
  "type": "Feature",
  "properties": {
    "iso:country":"BE",
    "sg:address":"Rue Simonon 13",
    "sg:city":"Mons",
    "sg:orig_category":"Verplichte sociale verzekeringen",
    "sg:phone":"+32 65 31 25 08",
    "sg:postcode":"7011",
    "sg:province":"Hainaut",
    "wof:name":"Mutualit\u00c9 Socialiste",
    "wof:placetype":"venue"
},
  "geometry": {"coordinates":[3.912539959,50.4712982178],"type":"Point"}
}