{
  "type": "Feature",
  "properties": {
    "iso:country":"BE",
    "sg:address":"Chemin Sur Le Mont 4",
    "sg:city":"Ath",
    "sg:orig_category":"Vakantiehuizen",
    "sg:phone":"+32 68 64 59 93",
    "sg:postcode":"7812",
    "sg:province":"Hainaut",
    "wof:name":"La Triskele",
    "wof:placetype":"venue"
},
  "geometry": {"coordinates":[3.7113668919,50.6636581421],"type":"Point"}
}