{
  "type": "Feature",
  "properties": {
    "addr:full":"Rue Pierre Broodcoorens 53 Terhulpen Brabant Wallon 1310",
    "addr:housenumber":"53;1310",
    "addr:street":"Rue Pierre Broodcoorens;Brabant Wallon",
    "iso:country":"BE",
    "sg:address":"Rue Pierre Broodcoorens 53",
    "sg:city":"Terhulpen",
    "sg:orig_category":"Woningbouw",
    "sg:phone":"+32 2 653 53 77",
    "sg:postcode":"1310",
    "sg:province":"Brabant Wallon",
    "wof:name":"Debroux W",
    "wof:placetype":"venue"
},
  "geometry": {"coordinates":[4.4849338531,50.7274131775],"type":"Point"}
}