{
  "type": "Feature",
  "properties": {
    "iso:country":"BE",
    "sg:address":"Rue Stanley 64",
    "sg:city":"Bruxelles (uccle)",
    "sg:classifiers":[
        {
            "category":"Real Estate",
            "subcategory":"Surveying",
            "type":"Services"
        }
    ],
    "sg:phone":"+32 2 345 31 64",
    "sg:postcode":"1180",
    "sg:province":"Bruxelles-Capitale",
    "sg:tags":[
        "surveyor",
        "land"
    ],
    "wof:name":"Berg\u00e9 P",
    "wof:placetype":"venue"
},
  "geometry": {"coordinates":[4.3652410507,50.8153381348],"type":"Point"}
}