{
  "type": "Feature",
  "properties": {
    "addr:full":"Baan Naar Bree 10 Peer Limburg 3990",
    "addr:housenumber":"10",
    "addr:postcode":"3990",
    "addr:street":"Baan Naar Bree",
    "iso:country":"BE",
    "sg:address":"Baan Naar Bree 10",
    "sg:city":"Peer",
    "sg:classifiers":[
        {
            "category":"Fast Food",
            "type":"Food & Drink"
        }
    ],
    "sg:phone":"+32 11 63 16 26",
    "sg:postcode":"3990",
    "sg:province":"Limburg",
    "sg:tags":[
        "restaurant",
        "\u00c0",
        "domicile",
        "emporter",
        "livraison",
        "restaurants"
    ],
    "wof:name":"Loong Fong",
    "wof:placetype":"venue"
},
  "geometry": {"coordinates":[5.4605908394,51.13123703],"type":"Point"}
}