{
  "type": "Feature",
  "properties": {
    "addr:full":"Chauss\u00c9e De Roodebeek 431 Sint-lambrechts-woluwe/woluwe-saint-lambert Bruxelles-Capitale 1200",
    "addr:housenumber":"431;/",
    "addr:postcode":"1200",
    "addr:street":"Chausse\u0301E De Roodebeek;Sint-Lambrechts-Woluwe",
    "iso:country":"BE",
    "sg:address":"Chauss\u00c9e De Roodebeek 431",
    "sg:city":"Sint-lambrechts-woluwe/woluwe-saint-lambert",
    "sg:orig_category":"Entretien and r\u00e9parations de voitures. V\u00e9hicules automobiles",
    "sg:phone":"+32 2 770 65 69",
    "sg:postcode":"1200",
    "sg:province":"Bruxelles-Capitale",
    "wof:name":"Beno\u00cet Van Eyll",
    "wof:placetype":"venue"
},
  "geometry": {"coordinates":[4.417555809,50.8498420715],"type":"Point"}
}