{
  "type": "Feature",
  "properties": {
    "addr:full":"Spoorwegstraat 29 Harelbeke West-Vlaanderen 8530",
    "addr:housenumber":"29",
    "addr:postcode":"8530",
    "addr:street":"Spoorwegstraat",
    "iso:country":"BE",
    "sg:address":"Spoorwegstraat 29",
    "sg:city":"Harelbeke",
    "sg:classifiers":[
        {
            "category":"Utilities",
            "subcategory":"Refuse",
            "type":"Services"
        }
    ],
    "sg:phone":"+32 56 21 91 00",
    "sg:postcode":"8530",
    "sg:province":"West-Vlaanderen",
    "sg:tags":[
        "removal"
    ],
    "wof:name":"Volutra Nv",
    "wof:placetype":"venue"
},
  "geometry": {"coordinates":[3.289304018,50.8365135193],"type":"Point"}
}