{
  "type": "Feature",
  "properties": {
    "addr:full":"Kouterstraat 25 Wielsbeke West-Vlaanderen 8710",
    "addr:housenumber":"25",
    "addr:postcode":"8710",
    "addr:street":"Kouterstraat;West-Vlaanderen",
    "iso:country":"BE",
    "sg:address":"Kouterstraat 25",
    "sg:city":"Wielsbeke",
    "sg:orig_category":"Eleveurs and marchands de porcs",
    "sg:phone":"+32 56 66 75 60",
    "sg:postcode":"8710",
    "sg:province":"West-Vlaanderen",
    "wof:name":"Roger Desplenter",
    "wof:placetype":"venue"
},
  "geometry": {"coordinates":[3.3160459995,50.8977279663],"type":"Point"}
}