{
  "type": "Feature",
  "properties": {
    "iso:country":"BE",
    "sg:address":"Rue Mauditienne 19b1",
    "sg:city":"Floreffe",
    "sg:orig_category":"Sportclubs",
    "sg:phone":"+32 81 44 63 33",
    "sg:postcode":"5150",
    "sg:province":"Namur",
    "wof:name":"V.c. Floreffe",
    "wof:placetype":"venue"
},
  "geometry": {"coordinates":[4.7544260025,50.4361953735],"type":"Point"}
}