{
  "type": "Feature",
  "properties": {
    "addr:full":"Grand-place 4 Renaix Oost-Vlaanderen 9600",
    "addr:housenumber":"4",
    "addr:postcode":"9600",
    "addr:street":"Grand-Place",
    "iso:country":"BE",
    "sg:address":"Grand-place 4",
    "sg:city":"Renaix",
    "sg:classifiers":[
        {
            "category":"Bars & Pubs",
            "type":"Food & Drink"
        }
    ],
    "sg:phone":"+32 55 21 56 20",
    "sg:postcode":"9600",
    "sg:province":"Oost-Vlaanderen",
    "wof:name":"Klok (de)",
    "wof:placetype":"venue"
},
  "geometry": {"coordinates":[3.6015861034,50.747756958],"type":"Point"}
}