{
  "type": "Feature",
  "properties": {
    "iso:country":"BE",
    "sg:address":"Zwitserlandstraat 29b35",
    "sg:city":"Sint-gillis/saint-gilles",
    "sg:orig_category":"Advocaten and juridische adviseurs",
    "sg:phone":"+32 2 534 16 80",
    "sg:postcode":"1060",
    "sg:province":"Bruxelles-Capitale",
    "wof:name":"Marc Willemart",
    "wof:placetype":"venue"
},
  "geometry": {"coordinates":[4.3534908295,50.8324241638],"type":"Point"}
}