{
  "type": "Feature",
  "properties": {
    "addr:full":"Grote Nieuwedijkstraat 251 Mechelen Antwerpen 2800",
    "addr:housenumber":"251",
    "addr:postcode":"2800",
    "addr:street":"Grote Nieuwedijkstraat",
    "iso:country":"BE",
    "sg:address":"Grote Nieuwedijkstraat 251",
    "sg:city":"Mechelen",
    "sg:classifiers":[
        {
            "category":"Cinema",
            "subcategory":"Movie Rental",
            "type":"Entertainment"
        }
    ],
    "sg:phone":"+32 15 55 42 42",
    "sg:postcode":"2800",
    "sg:province":"Antwerpen",
    "sg:tags":[
        "de",
        "cassette",
        "location",
        "vid\u00e9o",
        "audio"
    ],
    "wof:name":"Videotheek Hollywood",
    "wof:placetype":"venue"
},
  "geometry": {"coordinates":[4.4943070412,51.0374641418],"type":"Point"}
}