{
  "type": "Feature",
  "properties": {
    "addr:full":"Volpestraat 16 Halle Vlaams-Brabant 1500",
    "addr:housenumber":"16",
    "addr:postcode":"1500",
    "addr:street":"Volpestraat",
    "iso:country":"BE",
    "sg:address":"Volpestraat 16",
    "sg:city":"Halle",
    "sg:orig_category":"Baby- and kinderkleding Dameskledingzaken Herenkledingzaken",
    "sg:phone":"+32 2 361 72 98",
    "sg:postcode":"1500",
    "sg:province":"Vlaams-Brabant",
    "wof:name":"Aspasia",
    "wof:placetype":"venue"
},
  "geometry": {"coordinates":[4.2355389595,50.7360153198],"type":"Point"}
}