{
  "type": "Feature",
  "properties": {
    "iso:country":"BE",
    "sg:address":"Bontestraat 31",
    "sg:city":"Londerzeel",
    "sg:orig_category":"Producteurs de l\u00e9gumes",
    "sg:phone":"+32 52 37 36 22",
    "sg:postcode":"1840",
    "sg:province":"Vlaams-Brabant",
    "wof:name":"Joris Van Ransbeeck",
    "wof:placetype":"venue"
},
  "geometry": {"coordinates":[4.2625322342,50.982257843],"type":"Point"}
}