{
  "type": "Feature",
  "properties": {
    "addr:full":"Rue Du Rwanda 41 Verviers Li\u00e8ge 4801",
    "addr:housenumber":"41",
    "addr:postcode":"4801",
    "addr:street":"Rue Du Rwanda",
    "iso:country":"BE",
    "sg:address":"Rue Du Rwanda 41",
    "sg:city":"Verviers",
    "sg:orig_category":"Boekhouders",
    "sg:phone":"+32 87 22 28 30",
    "sg:postcode":"4801",
    "sg:province":"Li\u00e8ge",
    "wof:name":"M. Orban",
    "wof:placetype":"venue"
},
  "geometry": {"coordinates":[5.8930549622,50.5922393799],"type":"Point"}
}