{
  "type": "Feature",
  "properties": {
    "addr:full":"Deinzestraat 170 Oudenaarde Oost-Vlaanderen 9700",
    "addr:housenumber":"170",
    "addr:postcode":"9700",
    "addr:street":"Deinzestraat",
    "iso:country":"BE",
    "sg:address":"Deinzestraat 170",
    "sg:city":"Oudenaarde",
    "sg:classifiers":[
        {
            "category":"Building & Trades",
            "subcategory":"Cleaning & Sanitation",
            "type":"Services"
        }
    ],
    "sg:phone":"+32 498 10 41 38",
    "sg:postcode":"9700",
    "sg:province":"Oost-Vlaanderen",
    "sg:tags":[
        "fa\u00e7ade",
        "maintenance"
    ],
    "wof:name":"Goethals",
    "wof:placetype":"venue"
},
  "geometry": {"coordinates":[3.5791800022,50.8600196838],"type":"Point"}
}