{
  "type": "Feature",
  "properties": {
    "iso:country":"BE",
    "sg:address":"Rooienberg 51",
    "sg:city":"Duffel",
    "sg:orig_category":"Eleveurs de bovins",
    "sg:phone":"+32 15 31 22 25",
    "sg:postcode":"2570",
    "sg:province":"Antwerpen",
    "wof:name":"Van Dyck I & K & M",
    "wof:placetype":"venue"
},
  "geometry": {"coordinates":[4.4879097939,51.0958442688],"type":"Point"}
}