{
  "type": "Feature",
  "properties": {
    "addr:full":"Stasegemdorp 151 Harelbeke West-Vlaanderen 8530",
    "addr:housenumber":"151",
    "addr:postcode":"8530",
    "iso:country":"BE",
    "sg:address":"Stasegemdorp 151",
    "sg:city":"Harelbeke",
    "sg:classifiers":[
        {
            "category":"Real Estate",
            "subcategory":"Architect",
            "type":"Services"
        }
    ],
    "sg:phone":"+32 56 21 96 11",
    "sg:postcode":"8530",
    "sg:province":"West-Vlaanderen",
    "wof:name":"De Hullu Ph En Vennoten Cv",
    "wof:placetype":"venue"
},
  "geometry": {"coordinates":[3.3071548939,50.8306083679],"type":"Point"}
}