{
  "type": "Feature",
  "properties": {
    "iso:country":"BE",
    "sg:address":"Horionlaan 29",
    "sg:city":"Sint-truiden",
    "sg:classifiers":[
        {
            "category":"Food & Beverages",
            "subcategory":"Fruits & Vegetables",
            "type":"Retail Goods"
        }
    ],
    "sg:phone":"+32 11 69 18 36",
    "sg:postcode":"3800",
    "sg:province":"Limburg",
    "sg:tags":[
        "l\u00e9gumes"
    ],
    "wof:name":"Yves Vanwelkenhuyzen",
    "wof:placetype":"venue"
},
  "geometry": {"coordinates":[5.1863641739,50.8153343201],"type":"Point"}
}