{
  "type": "Feature",
  "properties": {
    "addr:full":"Rue Sart-haut 54 Les Bons Villers Hainaut 6210",
    "addr:housenumber":"54",
    "addr:postcode":"6210",
    "addr:street":"Rue Sart-Haut",
    "iso:country":"BE",
    "sg:address":"Rue Sart-haut 54",
    "sg:city":"Les Bons Villers",
    "sg:classifiers":[
        {
            "category":"Insurance",
            "subcategory":"Life Insurance",
            "type":"Services"
        }
    ],
    "sg:phone":"+32 71 84 46 35",
    "sg:postcode":"6210",
    "sg:province":"Hainaut",
    "sg:tags":[
        "assurance"
    ],
    "wof:name":"Leton",
    "wof:placetype":"venue"
},
  "geometry": {"coordinates":[4.3959259987,50.550113678],"type":"Point"}
}