{
  "type": "Feature",
  "properties": {
    "addr:full":"Malmedyer Strasse 36 Sankt Vith/saint-vith Li\u00e8ge 4780",
    "addr:housenumber":"36",
    "addr:postcode":"4780",
    "addr:street":"Malmedyer Strasse",
    "iso:country":"BE",
    "sg:address":"Malmedyer Strasse 36",
    "sg:city":"Sankt Vith/saint-vith",
    "sg:classifiers":[
        {
            "category":"Fast Food",
            "type":"Food & Drink"
        }
    ],
    "sg:phone":"+32 80 22 95 50",
    "sg:postcode":"4780",
    "sg:province":"Li\u00e8ge",
    "sg:tags":[
        "\u00c0",
        "restaurants",
        "emporter",
        "restaurant"
    ],
    "wof:name":"Tisch Lein Deck Dich",
    "wof:placetype":"venue"
},
  "geometry": {"coordinates":[6.0429549217,50.3349761963],"type":"Point"}
}