{
  "type": "Feature",
  "properties": {
    "addr:full":"Renbaanlaan 154b1 Elsene/ixelles Bruxelles-Capitale 1050",
    "addr:housenumber":"154b1",
    "addr:postcode":"1050",
    "addr:street":"Renbaanlaan",
    "iso:country":"BE",
    "sg:address":"Renbaanlaan 154b1",
    "sg:city":"Elsene/ixelles",
    "sg:orig_category":"Kapsalons",
    "sg:phone":"+32 2 648 05 70",
    "sg:postcode":"1050",
    "sg:province":"Bruxelles-Capitale",
    "wof:name":"Sup'hair",
    "wof:placetype":"venue"
},
  "geometry": {"coordinates":[4.3777518272,50.8199081421],"type":"Point"}
}