{
  "type": "Feature",
  "properties": {
    "iso:country":"BE",
    "sg:address":"Rue Marie De Bourgogne 52",
    "sg:city":"Bruxelles",
    "sg:classifiers":[
        {
            "category":"Organizations",
            "subcategory":"Professional Association",
            "type":"Services"
        }
    ],
    "sg:phone":"+32 2 230 90 64",
    "sg:postcode":"1000",
    "sg:province":"Bruxelles-Capitale",
    "sg:tags":[
        "trade-union",
        "federation"
    ],
    "wof:name":"European Marine Equipment Council Asbl",
    "wof:placetype":"venue"
},
  "geometry": {"coordinates":[4.3717370033,50.8413581848],"type":"Point"}
}