{
  "type": "Feature",
  "properties": {
    "iso:country":"BE",
    "sg:address":"Chemin De La Cav\u00c9e 53",
    "sg:city":"Ath",
    "sg:orig_category":"Eleveurs de bovins",
    "sg:phone":"+32 68 28 72 02",
    "sg:postcode":"7822",
    "sg:province":"Hainaut",
    "wof:name":"Paula Bruneel",
    "wof:placetype":"venue"
},
  "geometry": {"coordinates":[3.8452620506,50.6482391357],"type":"Point"}
}