{
  "type": "Feature",
  "properties": {
    "addr:full":"Chauss\u00c9e Verte 199 Saint-georges-sur-meuse Li\u00e8ge 4470",
    "addr:housenumber":"199",
    "addr:postcode":"4470",
    "addr:street":"Chausse\u0301E Verte",
    "iso:country":"BE",
    "sg:address":"Chauss\u00c9e Verte 199",
    "sg:city":"Saint-georges-sur-meuse",
    "sg:orig_category":"D\u00e9m\u00e9nagements",
    "sg:phone":"+32 4 259 51 98",
    "sg:postcode":"4470",
    "sg:province":"Li\u00e8ge",
    "wof:name":"Fossoul J. & Fils",
    "wof:placetype":"venue"
},
  "geometry": {"coordinates":[5.3562898636,50.620010376],"type":"Point"}
}