{
  "type": "Feature",
  "properties": {
    "iso:country":"BE",
    "sg:address":"Diestseweg 186",
    "sg:city":"Geel",
    "sg:orig_category":"GROENTEN AND FRUIT Kruideniers",
    "sg:phone":"+32 14 58 47 37",
    "sg:postcode":"2440",
    "sg:province":"Antwerpen",
    "wof:name":"De Boomgaard",
    "wof:placetype":"venue"
},
  "geometry": {"coordinates":[4.9939031601,51.1541900635],"type":"Point"}
}