{
  "type": "Feature",
  "properties": {
    "addr:full":"Rue Des H\u00eatres 40 Libin (transinne) Luxembourg 6890",
    "addr:housenumber":"40",
    "addr:postcode":"6890",
    "addr:street":"Rue Des He\u0302Tres",
    "iso:country":"BE",
    "sg:address":"Rue Des H\u00eatres 40",
    "sg:city":"Libin (transinne)",
    "sg:classifiers":[
        {
            "category":"Recreation",
            "subcategory":"Campground",
            "type":"Entertainment"
        }
    ],
    "sg:phone":"+32 61 65 50 55",
    "sg:postcode":"6890",
    "sg:province":"Luxembourg",
    "sg:tags":[
        "site",
        "camping"
    ],
    "wof:name":"Camping Des Sapins",
    "wof:placetype":"venue"
},
  "geometry": {"coordinates":[5.2562999725,49.9827537537],"type":"Point"}
}