{
  "type": "Feature",
  "properties": {
    "iso:country":"BE",
    "sg:address":"Bloemendalestraat 82",
    "sg:city":"Beernem",
    "sg:classifiers":[
        {
            "category":"Wholesale",
            "subcategory":"Meat",
            "type":"Manufacturing & Wholesale Goods"
        }
    ],
    "sg:phone":"+32 50 78 83 94",
    "sg:postcode":"8730",
    "sg:province":"West-Vlaanderen",
    "sg:tags":[
        "whol",
        "-"
    ],
    "wof:name":"Sierens R",
    "wof:placetype":"venue"
},
  "geometry": {"coordinates":[3.3362360001,51.1399116516],"type":"Point"}
}