{
  "type": "Feature",
  "properties": {
    "iso:country":"BE",
    "sg:address":"Rue Les Fonds 64",
    "sg:city":"Gesves",
    "sg:classifiers":[
        {
            "category":"Health Services",
            "subcategory":"Doctor",
            "type":"Services"
        }
    ],
    "sg:phone":"+32 83 67 70 72",
    "sg:postcode":"5340",
    "sg:province":"Namur",
    "sg:tags":[
        "medicinephysicians",
        "surgeon"
    ],
    "wof:name":"Halleux Christian",
    "wof:placetype":"venue"
},
  "geometry": {"coordinates":[5.0610370636,50.4089241028],"type":"Point"}
}