{
  "type": "Feature",
  "properties": {
    "addr:full":"Vaartstraat 51ab9 Leuven Vlaams-Brabant 3000",
    "addr:housenumber":"51ab9",
    "addr:postcode":"3000",
    "addr:street":"Vaartstraat",
    "iso:country":"BE",
    "sg:address":"Vaartstraat 51ab9",
    "sg:city":"Leuven",
    "sg:orig_category":"Vertalers and tolken",
    "sg:phone":"+32 16 23 59 55",
    "sg:postcode":"3000",
    "sg:province":"Vlaams-Brabant",
    "wof:name":"Cc Japanese Translations",
    "wof:placetype":"venue"
},
  "geometry": {"coordinates":[4.7008919716,50.8828964233],"type":"Point"}
}