{
  "type": "Feature",
  "properties": {
    "iso:country":"BE",
    "sg:address":"Schroordijk 1a",
    "sg:city":"Brecht",
    "sg:orig_category":"Vakantiehuizen",
    "sg:phone":"+32 3 313 64 21",
    "sg:postcode":"2960",
    "sg:province":"Antwerpen",
    "wof:name":"De Schoordijk",
    "wof:placetype":"venue"
},
  "geometry": {"coordinates":[4.607694149,51.3502235413],"type":"Point"}
}