{
  "type": "Feature",
  "properties": {
    "addr:full":"Rijksweg 83 Wielsbeke West-Vlaanderen 8710",
    "addr:housenumber":"83",
    "addr:postcode":"8710",
    "addr:street":"Rijksweg",
    "iso:country":"BE",
    "sg:address":"Rijksweg 83",
    "sg:city":"Wielsbeke",
    "sg:orig_category":"Peinture. Rev\u00eatements pour sols and murs",
    "sg:phone":"+32 56 60 61 55",
    "sg:postcode":"8710",
    "sg:province":"West-Vlaanderen",
    "wof:name":"S I Bavo",
    "wof:placetype":"venue"
},
  "geometry": {"coordinates":[3.3838999271,50.9110298157],"type":"Point"}
}