{
  "type": "Feature",
  "properties": {
    "addr:full":"Faubourg-saint-germain 81 Couvin Namur 5660",
    "addr:housenumber":"81",
    "addr:postcode":"5660",
    "addr:street":"Faubourg-Saint-Germain",
    "iso:country":"BE",
    "sg:address":"Faubourg-saint-germain 81",
    "sg:city":"Couvin",
    "sg:orig_category":"Banques and organismes de cr\u00e9dit",
    "sg:phone":"+32 60 34 40 27",
    "sg:postcode":"5660",
    "sg:province":"Namur",
    "wof:name":"Fortis",
    "wof:placetype":"venue"
},
  "geometry": {"coordinates":[4.493929863,50.0523834229],"type":"Point"}
}