{
  "type": "Feature",
  "properties": {
    "addr:full":"Rue De La Waide 3 Bl\u00c9gny Li\u00e8ge 4670",
    "addr:housenumber":"3",
    "addr:postcode":"4670",
    "addr:street":"Rue De La Waide",
    "iso:country":"BE",
    "sg:address":"Rue De La Waide 3",
    "sg:city":"Bl\u00c9gny",
    "sg:orig_category":"Boekhouders",
    "sg:phone":"+32 4 387 49 09",
    "sg:postcode":"4670",
    "sg:province":"Li\u00e8ge",
    "wof:name":"Jean-claude Deli\u00c8ge",
    "wof:placetype":"venue"
},
  "geometry": {"coordinates":[5.724919796,50.6725769043],"type":"Point"}
}