{
  "type": "Feature",
  "properties": {
    "iso:country":"BE",
    "sg:address":"Chauss\u00c9e De Louvain 801",
    "sg:city":"Evere/evere",
    "sg:orig_category":"Boucheries",
    "sg:phone":"+32 2 705 34 09",
    "sg:postcode":"1140",
    "sg:province":"Bruxelles-Capitale",
    "wof:name":"Boucherie Herman",
    "wof:placetype":"venue"
},
  "geometry": {"coordinates":[4.4135141373,50.8589782715],"type":"Point"}
}