{
  "type": "Feature",
  "properties": {
    "iso:country":"BE",
    "sg:address":"Ganzeplas 79",
    "sg:city":"Aalter",
    "sg:classifiers":[
        {
            "category":"Building & Trades",
            "subcategory":"Pest Control",
            "type":"Services"
        }
    ],
    "sg:phone":"+32 9 374 54 89",
    "sg:postcode":"9880",
    "sg:province":"Oost-Vlaanderen",
    "sg:tags":[
        "painting",
        "contractor"
    ],
    "wof:name":"Van Paemele L",
    "wof:placetype":"venue"
},
  "geometry": {"coordinates":[3.4732019901,51.0692977905],"type":"Point"}
}