{
  "type": "Feature",
  "properties": {
    "iso:country":"BE",
    "sg:address":"Wayai 19ba",
    "sg:city":"Jalhay",
    "sg:orig_category":"Charpentes and couvertures",
    "sg:phone":"+32 87 47 45 11",
    "sg:postcode":"4845",
    "sg:province":"Li\u00e8ge",
    "wof:name":"Michoel-simar",
    "wof:placetype":"venue"
},
  "geometry": {"coordinates":[5.9508261681,50.5039138794],"type":"Point"}
}