{
  "type": "Feature",
  "properties": {
    "addr:full":"Wapenhaghestraat 12 Antwerpen Antwerpen 2600",
    "addr:housenumber":"12",
    "addr:postcode":"2600",
    "addr:street":"Wapenhaghestraat",
    "iso:country":"BE",
    "sg:address":"Wapenhaghestraat 12",
    "sg:city":"Antwerpen",
    "sg:orig_category":"Medische apparatuur, orthopedische artikelen and prothesen Fab",
    "sg:phone":"+32 3 239 74 28",
    "sg:postcode":"2600",
    "sg:province":"Antwerpen",
    "wof:name":"De Clerk M",
    "wof:placetype":"venue"
},
  "geometry": {"coordinates":[4.4174151421,51.1974411011],"type":"Point"}
}