{
  "type": "Feature",
  "properties": {
    "addr:full":"Lommelsesteenweg 23 Leopoldsburg Limburg 3970",
    "addr:housenumber":"23",
    "addr:postcode":"3970",
    "addr:street":"Lommelsesteenweg",
    "iso:country":"BE",
    "sg:address":"Lommelsesteenweg 23",
    "sg:city":"Leopoldsburg",
    "sg:classifiers":[
        {
            "category":"Wholesale",
            "subcategory":"Beer",
            "type":"Manufacturing & Wholesale Goods"
        }
    ],
    "sg:phone":"+32 11 40 22 02",
    "sg:postcode":"3970",
    "sg:province":"Limburg",
    "sg:tags":[
        "ale",
        "-"
    ],
    "wof:name":"Prik & Tik",
    "wof:placetype":"venue"
},
  "geometry": {"coordinates":[5.2565741539,51.1260147095],"type":"Point"}
}