{
  "type": "Feature",
  "properties": {
    "addr:full":"Falconplein 29 Antwerpen Antwerpen 2000",
    "addr:housenumber":"29",
    "addr:postcode":"2000",
    "addr:street":"Falconplein",
    "iso:country":"BE",
    "sg:address":"Falconplein 29",
    "sg:city":"Antwerpen",
    "sg:orig_category":"Huishoudapparaten, televisies and radio's",
    "sg:phone":"+32 3 232 42 78",
    "sg:postcode":"2000",
    "sg:province":"Antwerpen",
    "wof:name":"Raisatex",
    "wof:placetype":"venue"
},
  "geometry": {"coordinates":[4.4049811363,51.2257270813],"type":"Point"}
}