{
  "type": "Feature",
  "properties": {
    "addr:full":"Rue Etienne-lenoir 15 Arlon Luxembourg 6700",
    "addr:housenumber":"15",
    "addr:postcode":"6700",
    "addr:street":"Rue Etienne-Lenoir",
    "iso:country":"BE",
    "sg:address":"Rue Etienne-lenoir 15",
    "sg:city":"Arlon",
    "sg:orig_category":"Fleurs and plantes",
    "sg:phone":"+32 63 22 22 34",
    "sg:postcode":"6700",
    "sg:province":"Luxembourg",
    "wof:name":"Le Jardin D\u00b4evelyne",
    "wof:placetype":"venue"
},
  "geometry": {"coordinates":[5.8146958351,49.6830062866],"type":"Point"}
}