{
  "type": "Feature",
  "properties": {
    "addr:full":"Boulevard De Waterloo 37 Brussels Bruxelles-Capitale 1000",
    "addr:housenumber":"37",
    "addr:postcode":"1000",
    "addr:street":"Boulevard De Waterloo",
    "iso:country":"BE",
    "sg:address":"Boulevard De Waterloo 37",
    "sg:city":"Brussels",
    "sg:classifiers":[
        {
            "category":"Banks & Credit Unions",
            "subcategory":"Bank",
            "type":"Services"
        }
    ],
    "sg:postcode":"1000",
    "sg:province":"Bruxelles-Capitale",
    "wof:name":"Dvv Zakenkantoor Beveren Nv",
    "wof:placetype":"venue"
},
  "geometry": {"coordinates":[4.2574100494,51.213180542],"type":"Point"}
}