{
  "type": "Feature",
  "properties": {
    "addr:full":"Maldange 2 Burg-reuland/burg-reuland Li\u00e8ge 4791",
    "addr:housenumber":"2",
    "addr:postcode":"4791",
    "addr:street":"Maldange",
    "iso:country":"BE",
    "sg:address":"Maldange 2",
    "sg:city":"Burg-reuland/burg-reuland",
    "sg:classifiers":[
        {
            "category":"Cafe",
            "type":"Food & Drink"
        }
    ],
    "sg:phone":"+32 80 22 89 53",
    "sg:postcode":"4791",
    "sg:province":"Li\u00e8ge",
    "sg:tags":[
        "caf\u00e9s"
    ],
    "wof:name":"Gastst\u00c4tte Gennen",
    "wof:placetype":"venue"
},
  "geometry": {"coordinates":[6.0771751404,50.2173156738],"type":"Point"}
}