{
  "type": "Feature",
  "properties": {
    "addr:full":"Chauss\u00c9e D'alsemberg 637 Ukkel/uccle Bruxelles-Capitale 1180",
    "addr:housenumber":"637",
    "addr:postcode":"1180",
    "addr:street":"Chausse\u0301E D'Alsemberg;/",
    "iso:country":"BE",
    "sg:address":"Chauss\u00c9e D'alsemberg 637",
    "sg:city":"Ukkel/uccle",
    "sg:orig_category":"Entretien and r\u00e9parations de voitures. V\u00e9hicules automobiles",
    "sg:phone":"+32 2 345 55 79",
    "sg:postcode":"1180",
    "sg:province":"Bruxelles-Capitale",
    "wof:name":"Carrosserie Peten",
    "wof:placetype":"venue"
},
  "geometry": {"coordinates":[4.3366861343,50.8076019287],"type":"Point"}
}