{
  "type": "Feature",
  "properties": {
    "addr:full":"Rue Maghin 13 Li\u00e8ge 1 Li\u00e8ge 4000",
    "addr:housenumber":"13;1",
    "addr:postcode":"4000",
    "addr:street":"Rue Maghin",
    "iso:country":"BE",
    "sg:address":"Rue Maghin 13",
    "sg:city":"Li\u00e8ge 1",
    "sg:classifiers":[
        {
            "category":"Building & Trades",
            "subcategory":"Equipment Rental",
            "type":"Services"
        }
    ],
    "sg:phone":"+32 4 228 90 10",
    "sg:postcode":"4000",
    "sg:province":"Li\u00e8ge",
    "sg:tags":[
        "sound",
        "-",
        "system"
    ],
    "wof:name":"Wnm Sa",
    "wof:placetype":"venue"
},
  "geometry": {"coordinates":[5.5861139297,50.6486434937],"type":"Point"}
}