{
  "type": "Feature",
  "properties": {
    "addr:full":"Nokerstraat 22-24 Gent (desteldonk) Oost-Vlaanderen 9042",
    "addr:housenumber":"22-24",
    "addr:postcode":"9042",
    "addr:street":"Nokerstraat",
    "iso:country":"BE",
    "sg:address":"Nokerstraat 22-24",
    "sg:city":"Gent (desteldonk)",
    "sg:classifiers":[
        {
            "category":"Transit Center",
            "subcategory":"Freight",
            "type":"Transportation"
        }
    ],
    "sg:phone":"+32 9 353 91 91",
    "sg:postcode":"9042",
    "sg:province":"Oost-Vlaanderen",
    "sg:tags":[
        "plant",
        "-",
        "transport"
    ],
    "wof:name":"Kintrans Bvba",
    "wof:placetype":"venue"
},
  "geometry": {"coordinates":[3.7816700935,51.1223831177],"type":"Point"}
}