{
  "type": "Feature",
  "properties": {
    "iso:country":"BE",
    "sg:address":"Atlantische Oceaanlaan 124",
    "sg:city":"Sint-pieters-woluwe/woluwe-saint-pierre",
    "sg:orig_category":"Antiek Verlichting and huishoudartikelen",
    "sg:phone":"+32 2 771 71 25",
    "sg:postcode":"1150",
    "sg:province":"Bruxelles-Capitale",
    "wof:name":"Chris'ann",
    "wof:placetype":"venue"
},
  "geometry": {"coordinates":[4.4186477661,50.8280258179],"type":"Point"}
}