{
  "type": "Feature",
  "properties": {
    "addr:full":"Livingstonelaan 51 Tervuren Vlaams-Brabant 3080",
    "addr:housenumber":"51",
    "addr:postcode":"3080",
    "addr:street":"Livingstonelaan",
    "iso:country":"BE",
    "sg:address":"Livingstonelaan 51",
    "sg:city":"Tervuren",
    "sg:orig_category":"Schoonheidssalons",
    "sg:phone":"+32 2 767 67 17",
    "sg:postcode":"3080",
    "sg:province":"Vlaams-Brabant",
    "wof:name":"Jacqueline Vanderborght",
    "wof:placetype":"venue"
},
  "geometry": {"coordinates":[4.5385651588,50.8376464844],"type":"Point"}
}