{
  "type": "Feature",
  "properties": {
    "iso:country":"BE",
    "sg:address":"Rue Willems 31",
    "sg:city":"Bruxelles (saint-josse-ten-noode)",
    "sg:classifiers":[
        {
            "category":"Building & Trades",
            "subcategory":"Electrical",
            "type":"Services"
        }
    ],
    "sg:phone":"+32 2 230 34 45",
    "sg:postcode":"1210",
    "sg:province":"Bruxelles-Capitale",
    "sg:tags":[
        "electric",
        "-",
        "housewiring",
        "contractor"
    ],
    "wof:name":"Lizin G",
    "wof:placetype":"venue"
},
  "geometry": {"coordinates":[4.376308918,50.8495407104],"type":"Point"}
}