{
  "type": "Feature",
  "properties": {
    "addr:full":"Rue G\u00e9n\u00e9raux Cuvelier 18 Florenville Luxembourg 6820",
    "addr:housenumber":"18",
    "addr:postcode":"6820",
    "addr:street":"Rue Ge\u0301Ne\u0301Raux Cuvelier",
    "iso:country":"BE",
    "sg:address":"Rue G\u00e9n\u00e9raux Cuvelier 18",
    "sg:city":"Florenville",
    "sg:classifiers":[
        {
            "category":"Bakery",
            "type":"Food & Drink"
        }
    ],
    "sg:phone":"+32 61 31 12 04",
    "sg:postcode":"6820",
    "sg:province":"Luxembourg",
    "sg:tags":[
        "confectioner",
        "baker"
    ],
    "wof:name":"Poncelet J P",
    "wof:placetype":"venue"
},
  "geometry": {"coordinates":[5.3090238571,49.6980552673],"type":"Point"}
}