{
  "type": "Feature",
  "properties": {
    "iso:country":"BE",
    "sg:address":"Kuringersteenweg 76",
    "sg:city":"Hasselt",
    "sg:orig_category":"Meubelzaken, woning- and keukeninrichting",
    "sg:phone":"+32 11 87 40 62",
    "sg:postcode":"3500",
    "sg:province":"Limburg",
    "wof:name":"Matrassenhuis",
    "wof:placetype":"venue"
},
  "geometry": {"coordinates":[5.3237519264,50.9340057373],"type":"Point"}
}