{
  "type": "Feature",
  "properties": {
    "addr:full":"Ingelmunstersestraat 67 Izegem West-Vlaanderen 8870",
    "addr:housenumber":"67",
    "addr:postcode":"8870",
    "addr:street":"Ingelmunstersestraat",
    "iso:country":"BE",
    "sg:address":"Ingelmunstersestraat 67",
    "sg:city":"Izegem",
    "sg:orig_category":"Plaatsen van vloer- and muurbekleding Schilders",
    "sg:phone":"+32 51 30 87 87",
    "sg:postcode":"8870",
    "sg:province":"West-Vlaanderen",
    "wof:name":"Freddy Van Severen",
    "wof:placetype":"venue"
},
  "geometry": {"coordinates":[3.2353320122,50.9235076904],"type":"Point"}
}