{
  "type": "Feature",
  "properties": {
    "iso:country":"BE",
    "sg:address":"Rue Du Ternia 9",
    "sg:city":"Viroinval",
    "sg:orig_category":"Pain, p\u00e2tisseries and confiseries",
    "sg:phone":"+32 60 39 04 90",
    "sg:postcode":"5670",
    "sg:province":"Namur",
    "wof:name":"Boulangerie Moraux",
    "wof:placetype":"venue"
},
  "geometry": {"coordinates":[4.6705851555,50.0926017761],"type":"Point"}
}