{
  "type": "Feature",
  "properties": {
    "iso:country":"BE",
    "sg:address":"Achter De Hoven 22",
    "sg:city":"Bilzen (rijkhoven)",
    "sg:classifiers":[
        {
            "category":"Building & Trades",
            "subcategory":"Locksmith",
            "type":"Services"
        }
    ],
    "sg:phone":"+32 89 49 15 62",
    "sg:postcode":"3740",
    "sg:province":"Limburg",
    "sg:tags":[
        "material",
        "road"
    ],
    "wof:name":"Hensen J",
    "wof:placetype":"venue"
},
  "geometry": {"coordinates":[5.4834480286,50.9006156921],"type":"Point"}
}