{
  "type": "Feature",
  "properties": {
    "iso:country":"BE",
    "sg:address":"Industrieweg 111",
    "sg:city":"Westerlo",
    "sg:orig_category":"Rundveehouders",
    "sg:phone":"+32 16 69 78 72",
    "sg:postcode":"2260",
    "sg:province":"Antwerpen",
    "wof:name":"Emiel Warpij",
    "wof:placetype":"venue"
},
  "geometry": {"coordinates":[4.8236188889,51.0882987976],"type":"Point"}
}