{
  "type": "Feature",
  "properties": {
    "addr:full":"Putsesteenweg 34 Mechelen Antwerpen 2800",
    "addr:housenumber":"34",
    "addr:postcode":"2800",
    "addr:street":"Putsesteenweg",
    "iso:country":"BE",
    "sg:address":"Putsesteenweg 34",
    "sg:city":"Mechelen",
    "sg:classifiers":[
        {
            "category":"Shopping",
            "subcategory":"Jewelry",
            "type":"Retail Goods"
        }
    ],
    "sg:phone":"+32 15 55 13 97",
    "sg:postcode":"2800",
    "sg:province":"Antwerpen",
    "sg:tags":[
        "jeweller",
        "-"
    ],
    "wof:name":"Verelst Goudsmederij Bvba",
    "wof:placetype":"venue"
},
  "geometry": {"coordinates":[4.511510849,51.0345077515],"type":"Point"}
}