{
  "type": "Feature",
  "properties": {
    "iso:country":"BE",
    "sg:address":"Bremlaan 7",
    "sg:city":"Kapellen",
    "sg:classifiers":[
        {
            "category":"Building & Trades",
            "subcategory":"Construction",
            "type":"Services"
        }
    ],
    "sg:phone":"+32 3 666 55 52",
    "sg:postcode":"2950",
    "sg:province":"Antwerpen",
    "sg:tags":[
        "stucco",
        "contractor"
    ],
    "wof:name":"Boeren F",
    "wof:placetype":"venue"
},
  "geometry": {"coordinates":[4.4455342293,51.3521499634],"type":"Point"}
}