{
  "type": "Feature",
  "properties": {
    "iso:country":"BE",
    "sg:address":"Kapelweg 124",
    "sg:city":"Turnhout",
    "sg:classifiers":[
        {
            "category":"Food & Beverages",
            "subcategory":"Candy",
            "type":"Retail Goods"
        }
    ],
    "sg:phone":"+32 14 42 85 89",
    "sg:postcode":"2300",
    "sg:province":"Antwerpen",
    "sg:tags":[
        "fab",
        "producten",
        "diverse"
    ],
    "wof:name":"Dierckx",
    "wof:placetype":"venue"
},
  "geometry": {"coordinates":[4.9484400749,51.2823295593],"type":"Point"}
}