{
  "type": "Feature",
  "properties": {
    "addr:full":"Rue Dorez 20 Tournai Hainaut 7500",
    "addr:housenumber":"20",
    "addr:postcode":"7500",
    "addr:street":"Rue Dorez",
    "iso:country":"BE",
    "sg:address":"Rue Dorez 20",
    "sg:city":"Tournai",
    "sg:classifiers":[
        {
            "category":"Shopping",
            "subcategory":"Antiques",
            "type":"Retail Goods"
        }
    ],
    "sg:phone":"+32 69 22 32 52",
    "sg:postcode":"7500",
    "sg:province":"Hainaut",
    "wof:name":"Jeudy I",
    "wof:placetype":"venue"
},
  "geometry": {"coordinates":[3.3826909065,50.6065063477],"type":"Point"}
}