{
  "type": "Feature",
  "properties": {
    "addr:full":"Malachietstr 2 Haven 102 Antwerpen Antwerpen 2030",
    "addr:housenumber":"2;102",
    "addr:postcode":"2030",
    "addr:street":"Malachietstr;Haven",
    "iso:country":"BE",
    "sg:address":"Malachietstr 2 Haven 102",
    "sg:city":"Antwerpen",
    "sg:classifiers":[
        {
            "category":"Manufacturing",
            "subcategory":"Wood Products",
            "type":"Manufacturing & Wholesale Goods"
        }
    ],
    "sg:phone":"+32 3 542 22 95",
    "sg:postcode":"2030",
    "sg:province":"Antwerpen",
    "sg:tags":[
        "furniture"
    ],
    "wof:name":"Somex Nv",
    "wof:placetype":"venue"
},
  "geometry": {"coordinates":[4.408621788,51.2448539734],"type":"Point"}
}