{
  "type": "Feature",
  "properties": {
    "addr:full":"Chauss\u00c9e De Waterloo 524 Elsene/ixelles Bruxelles-Capitale 1050",
    "addr:housenumber":"524",
    "addr:postcode":"1050",
    "addr:street":"Chausse\u0301E De Waterloo",
    "iso:country":"BE",
    "sg:address":"Chauss\u00c9e De Waterloo 524",
    "sg:city":"Elsene/ixelles",
    "sg:orig_category":"V\u00eatements pour Hommes",
    "sg:phone":"+32 2 346 60 25",
    "sg:postcode":"1050",
    "sg:province":"Bruxelles-Capitale",
    "wof:name":"Boutique Fashion",
    "wof:placetype":"venue"
},
  "geometry": {"coordinates":[4.3604931831,50.8198280334],"type":"Point"}
}