{
  "type": "Feature",
  "properties": {
    "addr:full":"Christinastraat 51 Oostende West-Vlaanderen 8400",
    "addr:housenumber":"51",
    "addr:postcode":"8400",
    "addr:street":"Christinastraat",
    "iso:country":"BE",
    "sg:address":"Christinastraat 51",
    "sg:city":"Oostende",
    "sg:classifiers":[
        {
            "category":"Shopping",
            "subcategory":"Clothing, Apparel, & Fashions",
            "type":"Retail Goods"
        }
    ],
    "sg:phone":"+32 59 80 69 61",
    "sg:postcode":"8400",
    "sg:province":"West-Vlaanderen",
    "sg:tags":[
        "boutique"
    ],
    "wof:name":"Kazo Moda",
    "wof:placetype":"venue"
},
  "geometry": {"coordinates":[2.9165139198,51.2310447693],"type":"Point"}
}