{
  "type": "Feature",
  "properties": {
    "iso:country":"BE",
    "sg:address":"Martijn Van Torhoutstraat 112",
    "sg:city":"Oudenaarde",
    "sg:classifiers":[
        {
            "category":"Real Estate",
            "subcategory":"Architect",
            "type":"Services"
        }
    ],
    "sg:phone":"+32 55 33 12 20",
    "sg:postcode":"9700",
    "sg:province":"Oost-Vlaanderen",
    "wof:name":"Delobelle H",
    "wof:placetype":"venue"
},
  "geometry": {"coordinates":[3.6251130104,50.8499717712],"type":"Point"}
}