{
  "type": "Feature",
  "properties": {
    "addr:full":"Dr\u00e8ve Des Tr\u00e9vires 26 Wavre Brabant Wallon 1300",
    "addr:housenumber":"26;1300",
    "addr:street":"Dre\u0300Ve Des Tre\u0301Vires",
    "iso:country":"BE",
    "sg:address":"Dr\u00e8ve Des Tr\u00e9vires 26",
    "sg:city":"Wavre",
    "sg:classifiers":[
        {
            "category":"Recreation",
            "subcategory":"Amusement Park",
            "type":"Entertainment"
        }
    ],
    "sg:phone":"+32 475 61 44 96",
    "sg:postcode":"1300",
    "sg:province":"Brabant Wallon",
    "sg:tags":[
        "attraction",
        "-",
        "sale",
        "fair",
        "hiring"
    ],
    "wof:name":"Richard",
    "wof:placetype":"venue"
},
  "geometry": {"coordinates":[4.6127109528,50.7245368958],"type":"Point"}
}