{
  "type": "Feature",
  "properties": {
    "addr:full":"Balgerhoeke 48 Eeklo Oost-Vlaanderen 9900",
    "addr:housenumber":"48",
    "addr:postcode":"9900",
    "addr:street":"Balgerhoeke",
    "iso:country":"BE",
    "sg:address":"Balgerhoeke 48",
    "sg:city":"Eeklo",
    "sg:orig_category":"Travaux de pl\u00e2trage. Construction de rev\u00eatements and voies d'acc\u00e8s r\u00e9sidentiels",
    "sg:phone":"+32 9 377 43 44",
    "sg:postcode":"9900",
    "sg:province":"Oost-Vlaanderen",
    "wof:name":"Frank Cocquyt",
    "wof:placetype":"venue"
},
  "geometry": {"coordinates":[3.5251669884,51.2007675171],"type":"Point"}
}