{
  "type": "Feature",
  "properties": {
    "addr:full":"Menenstraat 38 Wevelgem West-Vlaanderen 8560",
    "addr:housenumber":"38",
    "addr:postcode":"8560",
    "addr:street":"Menenstraat",
    "iso:country":"BE",
    "sg:address":"Menenstraat 38",
    "sg:city":"Wevelgem",
    "sg:orig_category":"Plomberie, chauffage and installations sanitaires. Charpentes and couvertures",
    "sg:phone":"+32 56 41 21 42",
    "sg:postcode":"8560",
    "sg:province":"West-Vlaanderen",
    "wof:name":"Del'haye",
    "wof:placetype":"venue"
},
  "geometry": {"coordinates":[3.1751871109,50.8073654175],"type":"Point"}
}