{
  "type": "Feature",
  "properties": {
    "addr:full":"Sint-maartensveldstraat 17 Ardooie West-Vlaanderen 8851",
    "addr:housenumber":"17",
    "addr:postcode":"8851",
    "addr:street":"Sint-Maartensveldstraat",
    "iso:country":"BE",
    "sg:address":"Sint-maartensveldstraat 17",
    "sg:city":"Ardooie",
    "sg:orig_category":"Producteurs de fruits. Eleveurs and marchands de porcs. Producteurs de l\u00e9gumes",
    "sg:phone":"+32 51 74 62 23",
    "sg:postcode":"8851",
    "sg:province":"West-Vlaanderen",
    "wof:name":"Geert Latrez",
    "wof:placetype":"venue"
},
  "geometry": {"coordinates":[3.2207820415,50.9967880249],"type":"Point"}
}