{
  "type": "Feature",
  "properties": {
    "iso:country":"BE",
    "sg:address":"Stendrich 3",
    "sg:city":"Eupen",
    "sg:orig_category":"Meubelzaken, woning- and keukeninrichting",
    "sg:phone":"+32 87 33 91 75",
    "sg:postcode":"4700",
    "sg:province":"Li\u00e8ge",
    "wof:name":"M\u00d6bel Bau Und Gestaltung",
    "wof:placetype":"venue"
},
  "geometry": {"coordinates":[6.025657177,50.6274719238],"type":"Point"}
}