{
  "type": "Feature",
  "properties": {
    "iso:country":"BE",
    "sg:address":"Handelsstraat 131",
    "sg:city":"Brussel/bruxelles",
    "sg:orig_category":"Hypotheken and hypotheekbanken Verbruikerskredietinstellingen",
    "sg:phone":"+32 2 238 02 11",
    "sg:postcode":"1000",
    "sg:province":"Bruxelles-Capitale",
    "wof:name":"C.b.h.k./o.c.c.h.",
    "wof:placetype":"venue"
},
  "geometry": {"coordinates":[4.3706979752,50.8459243774],"type":"Point"}
}