{
  "type": "Feature",
  "properties": {
    "iso:country":"BE",
    "sg:address":"Pathoekeweg 400",
    "sg:city":"Brugge",
    "sg:classifiers":[
        {
            "category":"Professional",
            "subcategory":"Engineering",
            "type":"Services"
        }
    ],
    "sg:phone":"+32 50 32 07 99",
    "sg:postcode":"8000",
    "sg:province":"West-Vlaanderen",
    "sg:tags":[
        "road",
        "surfacing",
        "asphalt",
        "highway"
    ],
    "wof:name":"Lam-ro-co Nv",
    "wof:placetype":"venue"
},
  "geometry": {"coordinates":[3.2077949047,51.2685966492],"type":"Point"}
}