{
  "type": "Feature",
  "properties": {
    "iso:country":"BE",
    "sg:address":"Kalmthoutse Steenweg 284",
    "sg:city":"Wuustwezel",
    "sg:orig_category":"Installatie van houten of kunststof schrijnwerk",
    "sg:phone":"+32 3 666 50 37",
    "sg:postcode":"2990",
    "sg:province":"Antwerpen",
    "wof:name":"Marcel De Bie",
    "wof:placetype":"venue"
},
  "geometry": {"coordinates":[4.5155510902,51.3961372375],"type":"Point"}
}