{
  "type": "Feature",
  "properties": {
    "iso:country":"BE",
    "sg:address":"Spoorweglaan 6",
    "sg:city":"Wetteren",
    "sg:orig_category":"Animaux domestiques and accessoires",
    "sg:phone":"+32 9 366 05 28",
    "sg:postcode":"9980",
    "sg:province":"Oost-Vlaanderen",
    "wof:name":"Dierenweelde",
    "wof:placetype":"venue"
},
  "geometry": {"coordinates":[3.8818759918,51.0011558533],"type":"Point"}
}