{
  "type": "Feature",
  "properties": {
    "iso:country":"BE",
    "sg:address":"Eug\u00c8ne Toussaintstraat 81b3",
    "sg:city":"Jette",
    "sg:orig_category":"Artsen and specialisten",
    "sg:phone":"+32 2 428 95 40",
    "sg:postcode":"1090",
    "sg:province":"Bruxelles-Capitale",
    "wof:name":"Sylvie Barthels",
    "wof:placetype":"venue"
},
  "geometry": {"coordinates":[4.3213019371,50.8784255981],"type":"Point"}
}