{
  "type": "Feature",
  "properties": {
    "addr:full":"Swinnenwijerweg 0 Genk Limburg 3600",
    "addr:housenumber":"0",
    "addr:postcode":"3600",
    "addr:street":"Swinnenwijerweg",
    "iso:country":"BE",
    "sg:address":"Swinnenwijerweg 0",
    "sg:city":"Genk",
    "sg:classifiers":[
        {
            "category":"Farming",
            "subcategory":"Fish & Marine Products",
            "type":"Manufacturing & Wholesale Goods"
        }
    ],
    "sg:phone":"+32 89 35 80 64",
    "sg:postcode":"3600",
    "sg:province":"Limburg",
    "sg:tags":[
        "schaaldierenkwekers",
        "vis-"
    ],
    "wof:name":"Aquafarm",
    "wof:placetype":"venue"
},
  "geometry": {"coordinates":[5.5059728622,50.9391098022],"type":"Point"}
}