{
  "type": "Feature",
  "properties": {
    "addr:full":"Chauss\u00c9e De Marche 657 Namur Namur 5100",
    "addr:housenumber":"657",
    "addr:postcode":"5100",
    "addr:street":"Chausse\u0301E De Marche",
    "iso:country":"BE",
    "sg:address":"Chauss\u00c9e De Marche 657",
    "sg:city":"Namur",
    "sg:orig_category":"Installatie van houten of kunststof schrijnwerk Meubelzaken, woning- and keukeninrichting Textiel",
    "sg:phone":"+32 81 40 13 67",
    "sg:postcode":"5100",
    "sg:province":"Namur",
    "wof:name":"Center Literie",
    "wof:placetype":"venue"
},
  "geometry": {"coordinates":[4.8713750839,50.4566345215],"type":"Point"}
}