{
  "type": "Feature",
  "properties": {
    "addr:full":"Vooruitgangsstraat 24 Menen West-Vlaanderen 8930",
    "addr:housenumber":"24",
    "addr:postcode":"8930",
    "addr:street":"Vooruitgangsstraat",
    "iso:country":"BE",
    "sg:address":"Vooruitgangsstraat 24",
    "sg:city":"Menen",
    "sg:classifiers":[
        {
            "category":"Airport",
            "subcategory":"International",
            "type":"Transportation"
        }
    ],
    "sg:phone":"+32 56 32 77 15",
    "sg:postcode":"8930",
    "sg:province":"West-Vlaanderen",
    "sg:tags":[
        "-",
        "transport"
    ],
    "wof:name":"Sonneville Transport",
    "wof:placetype":"venue"
},
  "geometry": {"coordinates":[3.1097769737,50.8073806763],"type":"Point"}
}