{
  "type": "Feature",
  "properties": {
    "iso:country":"BE",
    "sg:address":"Rue Pierre Ouvrard 10",
    "sg:city":"Flobecq",
    "sg:classifiers":[
        {
            "category":"Home & Garden",
            "subcategory":"Household Appliances",
            "type":"Retail Goods"
        }
    ],
    "sg:phone":"+32 68 44 74 60",
    "sg:postcode":"7880",
    "sg:province":"Hainaut",
    "sg:tags":[
        "housewares",
        "-"
    ],
    "wof:name":"Verschueren",
    "wof:placetype":"venue"
},
  "geometry": {"coordinates":[3.7387650013,50.7369918823],"type":"Point"}
}