{
  "type": "Feature",
  "properties": {
    "iso:country":"BE",
    "sg:address":"Esplanadestraat 3",
    "sg:city":"Aalst",
    "sg:orig_category":"M\u00e9decins and sp\u00e9cialistes",
    "sg:phone":"+32 53 71 01 37",
    "sg:postcode":"9300",
    "sg:province":"Oost-Vlaanderen",
    "wof:name":"Etienne Rollier",
    "wof:placetype":"venue"
},
  "geometry": {"coordinates":[4.0369901657,50.9408111572],"type":"Point"}
}