{
  "type": "Feature",
  "properties": {
    "iso:country":"BE",
    "sg:address":"Brusselsesteenweg 301",
    "sg:city":"Mechelen",
    "sg:classifiers":[
        {
            "category":"Organizations",
            "subcategory":"Professional Association",
            "type":"Services"
        }
    ],
    "sg:phone":"+32 15 21 21 85",
    "sg:postcode":"2800",
    "sg:province":"Antwerpen",
    "sg:tags":[
        "organisation",
        "seminar"
    ],
    "wof:name":"Passade Brasserie",
    "wof:placetype":"venue"
},
  "geometry": {"coordinates":[4.4746870995,51.0079956055],"type":"Point"}
}