{
  "type": "Feature",
  "properties": {
    "addr:full":"Belseledorp 106a Sint-niklaas (belsele) Oost-Vlaanderen 9111",
    "addr:housenumber":"106a",
    "addr:postcode":"9111",
    "iso:country":"BE",
    "sg:address":"Belseledorp 106a",
    "sg:city":"Sint-niklaas (belsele)",
    "sg:classifiers":[
        {
            "category":"Shopping",
            "subcategory":"Clothing, Apparel, & Fashions",
            "type":"Retail Goods"
        }
    ],
    "sg:phone":"+32 3 772 73 12",
    "sg:postcode":"9111",
    "sg:province":"Oost-Vlaanderen",
    "sg:tags":[
        "clothing",
        "-",
        "gentleman"
    ],
    "wof:name":"Heirwegh",
    "wof:placetype":"venue"
},
  "geometry": {"coordinates":[4.0869069099,51.1461830139],"type":"Point"}
}