{
  "type": "Feature",
  "properties": {
    "addr:full":"Molenstraat 78 Westerlo Antwerpen 2260",
    "addr:housenumber":"78",
    "addr:postcode":"2260",
    "addr:street":"Molenstraat",
    "iso:country":"BE",
    "sg:address":"Molenstraat 78",
    "sg:city":"Westerlo",
    "sg:classifiers":[
        {
            "category":"Personal",
            "subcategory":"Beauty Salon",
            "type":"Services"
        }
    ],
    "sg:phone":"+32 16 69 90 60",
    "sg:postcode":"2260",
    "sg:province":"Antwerpen",
    "sg:tags":[
        "de",
        "coiffure"
    ],
    "wof:name":"R. Govarts",
    "wof:placetype":"venue"
},
  "geometry": {"coordinates":[4.8401107788,51.0800933838],"type":"Point"}
}