{
  "type": "Feature",
  "properties": {
    "iso:country":"BE",
    "sg:address":"Rue Heyvaert 38",
    "sg:city":"Bruxelles (molenbeek-saint-jean)",
    "sg:classifiers":[
        {
            "category":"Manufacturing",
            "subcategory":"Metals",
            "type":"Manufacturing & Wholesale Goods"
        }
    ],
    "sg:phone":"+32 2 521 19 38",
    "sg:postcode":"1080",
    "sg:province":"Bruxelles-Capitale",
    "sg:tags":[
        "nickel",
        "plating",
        "chromium"
    ],
    "wof:name":"Thomas R",
    "wof:placetype":"venue"
},
  "geometry": {"coordinates":[4.3343129158,50.8482093811],"type":"Point"}
}