{
  "type": "Feature",
  "properties": {
    "addr:full":"Rue Du Zouave Fran\u00e7ais Michel 12 Braine-le-ch\u00e2teau (wauthier-braine) Brabant Wallon 1440",
    "addr:housenumber":"12",
    "addr:postcode":"1440",
    "addr:street":"Rue Du Zouave Franc\u0327Ais Michel",
    "iso:country":"BE",
    "sg:address":"Rue Du Zouave Fran\u00e7ais Michel 12",
    "sg:city":"Braine-le-ch\u00e2teau (wauthier-braine)",
    "sg:classifiers":[
        {
            "category":"Manufacturing",
            "subcategory":"Furniture",
            "type":"Manufacturing & Wholesale Goods"
        }
    ],
    "sg:phone":"+32 2 366 92 17",
    "sg:postcode":"1440",
    "sg:province":"Brabant Wallon",
    "sg:tags":[
        "made",
        "-",
        "custom"
    ],
    "wof:name":"Ateliers Du Hain (les)",
    "wof:placetype":"venue"
},
  "geometry": {"coordinates":[4.2988657951,50.6810302734],"type":"Point"}
}