{
  "type": "Feature",
  "properties": {
    "iso:country":"BE",
    "sg:address":"Provinciebaan 125",
    "sg:city":"Ledegem",
    "sg:classifiers":[
        {
            "category":"Shopping",
            "subcategory":"Florist",
            "type":"Retail Goods"
        }
    ],
    "sg:phone":"+32 56 50 92 84",
    "sg:postcode":"8880",
    "sg:province":"West-Vlaanderen",
    "wof:name":"Bloemenweelde",
    "wof:placetype":"venue"
},
  "geometry": {"coordinates":[3.1098530293,50.8630409241],"type":"Point"}
}