{
  "type": "Feature",
  "properties": {
    "addr:full":"Place Th. Palm 15 Baelen Li\u00e8ge 4837",
    "addr:housenumber":"15",
    "addr:postcode":"4837",
    "addr:street":"Place Th. Palm",
    "iso:country":"BE",
    "sg:address":"Place Th. Palm 15",
    "sg:city":"Baelen",
    "sg:orig_category":"Enseignement maternel and primaire",
    "sg:phone":"+32 87 74 24 58",
    "sg:postcode":"4837",
    "sg:province":"Li\u00e8ge",
    "wof:name":"Ecole Prim. Communale",
    "wof:placetype":"venue"
},
  "geometry": {"coordinates":[5.9713449478,50.6319007874],"type":"Point"}
}