{
  "type": "Feature",
  "properties": {
    "iso:country":"BE",
    "sg:address":"Goudbergstraat 111",
    "sg:city":"Wevelgem",
    "sg:orig_category":"S\u00e9curit\u00e9 sociale",
    "sg:phone":"+32 56 40 13 72",
    "sg:postcode":"8560",
    "sg:province":"West-Vlaanderen",
    "wof:name":"Kind En Gezondheid",
    "wof:placetype":"venue"
},
  "geometry": {"coordinates":[3.1800949574,50.8034477234],"type":"Point"}
}