{
  "type": "Feature",
  "properties": {
    "addr:full":"Weggevoerdenstraat 21 Wevelgem West-Vlaanderen 8560",
    "addr:housenumber":"21",
    "addr:postcode":"8560",
    "addr:street":"Weggevoerdenstraat",
    "iso:country":"BE",
    "sg:address":"Weggevoerdenstraat 21",
    "sg:city":"Wevelgem",
    "sg:classifiers":[
        {
            "category":"Professional",
            "subcategory":"Management & Consulting",
            "type":"Services"
        }
    ],
    "sg:phone":"+32 497 57 47 77",
    "sg:postcode":"8560",
    "sg:province":"West-Vlaanderen",
    "sg:tags":[
        "-",
        "processing",
        "data",
        "consultant"
    ],
    "wof:name":"Vanwolleghem Bert & Co Bvba",
    "wof:placetype":"venue"
},
  "geometry": {"coordinates":[3.1759779453,50.8093261719],"type":"Point"}
}