{
  "type": "Feature",
  "properties": {
    "iso:country":"BE",
    "sg:address":"Dorpsstraat 8ba",
    "sg:city":"Neerpelt",
    "sg:orig_category":"Brood, gebak and snoepgoed",
    "sg:phone":"+32 11 64 22 51",
    "sg:postcode":"3910",
    "sg:province":"Limburg",
    "wof:name":"Bakkerij Jalina",
    "wof:placetype":"venue"
},
  "geometry": {"coordinates":[5.4830708504,51.226890564],"type":"Point"}
}