{
  "type": "Feature",
  "properties": {
    "addr:full":"Groenstraat 13 Meulebeke West-Vlaanderen 8760",
    "addr:housenumber":"13",
    "addr:postcode":"8760",
    "addr:street":"Groenstraat",
    "iso:country":"BE",
    "sg:address":"Groenstraat 13",
    "sg:city":"Meulebeke",
    "sg:classifiers":[
        {
            "category":"Cafe",
            "type":"Food & Drink"
        }
    ],
    "sg:phone":"+32 51 48 90 48",
    "sg:postcode":"8760",
    "sg:province":"West-Vlaanderen",
    "sg:tags":[
        "caf\u00e9s"
    ],
    "wof:name":"Christine Verhaeghe",
    "wof:placetype":"venue"
},
  "geometry": {"coordinates":[3.3055009842,50.9641075134],"type":"Point"}
}