{
  "type": "Feature",
  "properties": {
    "iso:country":"BE",
    "sg:address":"Noordomstraat 21",
    "sg:city":"Koekelare",
    "sg:classifiers":[
        {
            "category":"Health Services",
            "subcategory":"Health Practitioner",
            "type":"Services"
        }
    ],
    "sg:phone":"+32 51 58 86 89",
    "sg:postcode":"8680",
    "sg:province":"West-Vlaanderen",
    "sg:tags":[
        "physiotherapist"
    ],
    "wof:name":"Hindryckx D",
    "wof:placetype":"venue"
},
  "geometry": {"coordinates":[2.975771904,51.0906791687],"type":"Point"}
}