{
  "type": "Feature",
  "properties": {
    "iso:country":"BE",
    "sg:address":"Clos Des Chaumi\u00c8res 55",
    "sg:city":"Tournai",
    "sg:classifiers":[
        {
            "category":"Insurance",
            "subcategory":"Insurance Agent",
            "type":"Services"
        }
    ],
    "sg:phone":"+32 69 21 26 24",
    "sg:postcode":"7540",
    "sg:province":"Hainaut",
    "sg:tags":[
        "verzekeringsmakelaars",
        "expert"
    ],
    "wof:name":"Dubois Et Leulier",
    "wof:placetype":"venue"
},
  "geometry": {"coordinates":[3.3822140694,50.6256752014],"type":"Point"}
}