{
  "type": "Feature",
  "properties": {
    "addr:full":"Doorniksewijk 195 Kortrijk West-Vlaanderen 8500",
    "addr:housenumber":"195",
    "addr:postcode":"8500",
    "iso:country":"BE",
    "sg:address":"Doorniksewijk 195",
    "sg:city":"Kortrijk",
    "sg:classifiers":[
        {
            "category":"Shopping",
            "subcategory":"Florist",
            "type":"Retail Goods"
        }
    ],
    "sg:phone":"+32 56 20 32 70",
    "sg:postcode":"8500",
    "sg:province":"West-Vlaanderen",
    "wof:name":"Descaplant Bvba",
    "wof:placetype":"venue"
},
  "geometry": {"coordinates":[3.2702569962,50.816822052],"type":"Point"}
}