{
  "type": "Feature",
  "properties": {
    "iso:country":"BE",
    "sg:address":"Dr. Vanderhoeydonckstr. 23",
    "sg:city":"Lummen",
    "sg:orig_category":"Dancings and bo\u00eetes de nuit",
    "sg:phone":"+32 13 52 32 59",
    "sg:postcode":"3560",
    "sg:province":"Limburg",
    "wof:name":"Scala",
    "wof:placetype":"venue"
},
  "geometry": {"coordinates":[5.1945271492,50.988494873],"type":"Point"}
}