{
  "type": "Feature",
  "properties": {
    "iso:country":"BE",
    "sg:address":"Rue Louise Michel 36",
    "sg:city":"Colfontaine (p\u00e2turages)",
    "sg:classifiers":[
        {
            "category":"Health Services",
            "subcategory":"Nursing And Care Facility",
            "type":"Services"
        }
    ],
    "sg:phone":"+32 65 66 19 70",
    "sg:postcode":"7340",
    "sg:province":"Hainaut",
    "sg:tags":[
        "home"
    ],
    "wof:name":"Caudron Nandy",
    "wof:placetype":"venue"
},
  "geometry": {"coordinates":[3.8579928875,50.4181671143],"type":"Point"}
}