{
  "type": "Feature",
  "properties": {
    "iso:country":"BE",
    "sg:address":"Rue De Wellin 99",
    "sg:city":"Beauraing",
    "sg:orig_category":"Transports routiers de marchandises",
    "sg:phone":"+32 82 71 11 62",
    "sg:postcode":"5574",
    "sg:province":"Namur",
    "wof:name":"Albert Talmasse",
    "wof:placetype":"venue"
},
  "geometry": {"coordinates":[5.0101628304,50.0989646912],"type":"Point"}
}