{
  "type": "Feature",
  "properties": {
    "addr:full":"Avenue Du Panth\u00e9on 27 Bruxelles (koekelberg) Bruxelles-Capitale 1081",
    "addr:housenumber":"27",
    "addr:postcode":"1081",
    "addr:street":"Avenue Du Panthe\u0301On",
    "iso:country":"BE",
    "sg:address":"Avenue Du Panth\u00e9on 27",
    "sg:city":"Bruxelles (koekelberg)",
    "sg:classifiers":[
        {
            "category":"Communications",
            "subcategory":"Television Station",
            "type":"Services"
        }
    ],
    "sg:phone":"+32 478 80 22 17",
    "sg:postcode":"1081",
    "sg:province":"Bruxelles-Capitale",
    "sg:tags":[
        "report",
        "video"
    ],
    "wof:name":"Van Wanzeele B",
    "wof:placetype":"venue"
},
  "geometry": {"coordinates":[4.323679924,50.8638153076],"type":"Point"}
}