{
  "type": "Feature",
  "properties": {
    "addr:full":"Rue Lambert 28 Ans (xhendremael) Li\u00e8ge 4432",
    "addr:housenumber":"28",
    "addr:postcode":"4432",
    "addr:street":"Rue Lambert;Xhendremael",
    "iso:country":"BE",
    "sg:address":"Rue Lambert 28",
    "sg:city":"Ans (xhendremael)",
    "sg:classifiers":[
        {
            "category":"Real Estate",
            "subcategory":"Architect",
            "type":"Services"
        }
    ],
    "sg:phone":"+32 4 257 58 57",
    "sg:postcode":"4432",
    "sg:province":"Li\u00e8ge",
    "wof:name":"Lemmens J-p",
    "wof:placetype":"venue"
},
  "geometry": {"coordinates":[5.4858298302,50.7038040161],"type":"Point"}
}