{
  "type": "Feature",
  "properties": {
    "addr:full":"Hoeverkerkweg 54 Opglabbeek Limburg 3660",
    "addr:housenumber":"54",
    "addr:postcode":"3660",
    "addr:street":"Hoeverkerkweg",
    "iso:country":"BE",
    "sg:address":"Hoeverkerkweg 54",
    "sg:city":"Opglabbeek",
    "sg:orig_category":"Traitements param\u00e9dicaux",
    "sg:phone":"+32 89 85 65 40",
    "sg:postcode":"3660",
    "sg:province":"Limburg",
    "wof:name":"Dtv +",
    "wof:placetype":"venue"
},
  "geometry": {"coordinates":[5.5860719681,51.0384254456],"type":"Point"}
}