{
  "type": "Feature",
  "properties": {
    "iso:country":"BE",
    "sg:address":"Gasthuisstraat 69",
    "sg:city":"Turnhout",
    "sg:orig_category":"Pain, p\u00e2tisseries and confiseries",
    "sg:phone":"+32 14 41 10 88",
    "sg:postcode":"2300",
    "sg:province":"Antwerpen",
    "wof:name":"Huis Pralinco",
    "wof:placetype":"venue"
},
  "geometry": {"coordinates":[4.9436230659,51.3223381042],"type":"Point"}
}