{
  "type": "Feature",
  "properties": {
    "iso:country":"BE",
    "sg:address":"Rue D\u00b4artois 49",
    "sg:city":"Brussel/bruxelles",
    "sg:orig_category":"Studios photographiques",
    "sg:phone":"+32 2 512 64 27",
    "sg:postcode":"1000",
    "sg:province":"Bruxelles-Capitale",
    "wof:name":"B\u00c9n\u00c9dicte Meiers",
    "wof:placetype":"venue"
},
  "geometry": {"coordinates":[4.3413438797,50.8427467346],"type":"Point"}
}