{
  "type": "Feature",
  "properties": {
    "addr:full":"Stadspoortstraat 0 Herentals Antwerpen 2200",
    "addr:housenumber":"0",
    "addr:postcode":"2200",
    "addr:street":"Stadspoortstraat",
    "iso:country":"BE",
    "sg:address":"Stadspoortstraat 0",
    "sg:city":"Herentals",
    "sg:classifiers":[
        {
            "category":"Food & Beverages",
            "subcategory":"Fruits & Vegetables",
            "type":"Retail Goods"
        }
    ],
    "sg:phone":"+32 14 22 41 24",
    "sg:postcode":"2200",
    "sg:province":"Antwerpen",
    "sg:tags":[
        "groenten"
    ],
    "wof:name":"Fruitkraam Bovenpoort",
    "wof:placetype":"venue"
},
  "geometry": {"coordinates":[4.8380150795,51.1745414734],"type":"Point"}
}