{
  "type": "Feature",
  "properties": {
    "addr:full":"Waterstraat 43 Mol Antwerpen 2400",
    "addr:housenumber":"43",
    "addr:postcode":"2400",
    "addr:street":"Waterstraat",
    "iso:country":"BE",
    "sg:address":"Waterstraat 43",
    "sg:city":"Mol",
    "sg:classifiers":[
        {
            "category":"Restaurant",
            "type":"Food & Drink"
        }
    ],
    "sg:phone":"+32 14 81 60 07",
    "sg:postcode":"2400",
    "sg:province":"Antwerpen",
    "sg:tags":[
        "de",
        "organisation",
        "\u00c0",
        "fast",
        "catering",
        "emporter",
        "f\u00cates",
        "restaurants"
    ],
    "wof:name":"Jagershof",
    "wof:placetype":"venue"
},
  "geometry": {"coordinates":[5.2116317749,51.2375984192],"type":"Point"}
}