{
  "type": "Feature",
  "properties": {
    "iso:country":"BE",
    "sg:address":"Boucle Des Chevreuils 4",
    "sg:city":"Beaumont (barben\u00e7on)",
    "sg:classifiers":[
        {
            "category":"Real Estate",
            "subcategory":"Architect",
            "type":"Services"
        }
    ],
    "sg:phone":"+32 71 58 71 17",
    "sg:postcode":"6500",
    "sg:province":"Hainaut",
    "wof:name":"Russe O",
    "wof:placetype":"venue"
},
  "geometry": {"coordinates":[4.2353200912,50.2372131348],"type":"Point"}
}