{
  "type": "Feature",
  "properties": {
    "iso:country":"BE",
    "sg:address":"Schansstraat 33b",
    "sg:city":"Kortenaken",
    "sg:classifiers":[
        {
            "category":"Building & Trades",
            "subcategory":"Pest Control",
            "type":"Services"
        }
    ],
    "sg:phone":"+32 11 58 14 39",
    "sg:postcode":"3470",
    "sg:province":"Vlaams-Brabant",
    "sg:tags":[
        "painting",
        "contractor"
    ],
    "wof:name":"Van Der Molen H",
    "wof:placetype":"venue"
},
  "geometry": {"coordinates":[5.0668377876,50.9073982239],"type":"Point"}
}