{
  "type": "Feature",
  "properties": {
    "addr:full":"Naamsesteenweg 190 Leuven Vlaams-Brabant 3001",
    "addr:housenumber":"190",
    "addr:postcode":"3001",
    "addr:street":"Naamsesteenweg",
    "iso:country":"BE",
    "sg:address":"Naamsesteenweg 190",
    "sg:city":"Leuven",
    "sg:orig_category":"Banques and organismes de cr\u00e9dit",
    "sg:phone":"+32 16 40 74 53",
    "sg:postcode":"3001",
    "sg:province":"Vlaams-Brabant",
    "wof:name":"Groep Argenta",
    "wof:placetype":"venue"
},
  "geometry": {"coordinates":[4.695690155,50.8620262146],"type":"Point"}
}