{
  "type": "Feature",
  "properties": {
    "addr:full":"Nindsebaan 35 Keerbergen Vlaams-Brabant 3140",
    "addr:housenumber":"35",
    "addr:postcode":"3140",
    "addr:street":"Nindsebaan",
    "iso:country":"BE",
    "sg:address":"Nindsebaan 35",
    "sg:city":"Keerbergen",
    "sg:classifiers":[
        {
            "category":"Health Services",
            "subcategory":"Doctor",
            "type":"Services"
        }
    ],
    "sg:phone":"+32 15 23 48 54",
    "sg:postcode":"3140",
    "sg:province":"Vlaams-Brabant",
    "sg:tags":[
        "medicinephysicians",
        "surgeon"
    ],
    "wof:name":"De Somer F",
    "wof:placetype":"venue"
},
  "geometry": {"coordinates":[4.6556267738,50.9967842102],"type":"Point"}
}