{
  "type": "Feature",
  "properties": {
    "iso:country":"BE",
    "sg:address":"Rozendaal 82",
    "sg:city":"Geel",
    "sg:classifiers":[
        {
            "category":"Health Services",
            "subcategory":"Doctor",
            "type":"Services"
        }
    ],
    "sg:phone":"+32 14 58 54 40",
    "sg:postcode":"2440",
    "sg:province":"Antwerpen",
    "sg:tags":[
        "medicinephysicians",
        "surgeon"
    ],
    "wof:name":"Delanote M",
    "wof:placetype":"venue"
},
  "geometry": {"coordinates":[4.9936361313,51.1655006409],"type":"Point"}
}