{
  "type": "Feature",
  "properties": {
    "addr:full":"Schoolstraat 50 Herk-de-stad Limburg 3540",
    "addr:housenumber":"50",
    "addr:postcode":"3540",
    "addr:street":"Schoolstraat",
    "iso:country":"BE",
    "sg:address":"Schoolstraat 50",
    "sg:city":"Herk-de-stad",
    "sg:classifiers":[
        {
            "category":"Manufacturing",
            "subcategory":"Furniture",
            "type":"Manufacturing & Wholesale Goods"
        }
    ],
    "sg:phone":"+32 13 55 25 86",
    "sg:postcode":"3540",
    "sg:province":"Limburg",
    "sg:tags":[
        "hospital",
        "-"
    ],
    "wof:name":"Aks Benelux Bvba",
    "wof:placetype":"venue"
},
  "geometry": {"coordinates":[5.2054710388,50.9098205566],"type":"Point"}
}