{
  "type": "Feature",
  "properties": {
    "iso:country":"BE",
    "sg:address":"Rue Henri Lema\u00eetre 6",
    "sg:city":"Namur",
    "sg:classifiers":[
        {
            "category":"Health Services",
            "subcategory":"Doctor",
            "type":"Services"
        }
    ],
    "sg:phone":"+32 81 74 27 00",
    "sg:postcode":"5000",
    "sg:province":"Namur",
    "sg:tags":[
        "medicinephysicians",
        "surgeon"
    ],
    "wof:name":"L\u00e9onard Philippe",
    "wof:placetype":"venue"
},
  "geometry": {"coordinates":[4.853222847,50.4657554626],"type":"Point"}
}