{
  "type": "Feature",
  "properties": {
    "iso:country":"BE",
    "sg:address":"Hoogstraat 16",
    "sg:city":"Meise",
    "sg:orig_category":"Beautyfarms, relaxatie and lichamelijk welzijn Schoonheidssalons",
    "sg:phone":"+32 2 269 96 68",
    "sg:postcode":"1861",
    "sg:province":"Vlaams-Brabant",
    "wof:name":"Instituut Hilde",
    "wof:placetype":"venue"
},
  "geometry": {"coordinates":[4.3098812103,50.9518356323],"type":"Point"}
}