{
  "type": "Feature",
  "properties": {
    "iso:country":"BE",
    "sg:address":"Zandstraat 119",
    "sg:city":"Sint-gillis-waas",
    "sg:orig_category":"Maroquinerie and articles de voyage. Chaussures",
    "sg:phone":"+32 3 779 98 55",
    "sg:postcode":"9170",
    "sg:province":"Oost-Vlaanderen",
    "wof:name":"Schoenen Molders",
    "wof:placetype":"venue"
},
  "geometry": {"coordinates":[4.0850009918,51.1982536316],"type":"Point"}
}