{
  "type": "Feature",
  "properties": {
    "iso:country":"BE",
    "sg:address":"Nieuwmoerdorp 37",
    "sg:city":"Kalmthout",
    "sg:orig_category":"V\u00e9t\u00e9rinaires",
    "sg:phone":"+32 3 677 12 38",
    "sg:postcode":"2920",
    "sg:province":"Antwerpen",
    "wof:name":"Gerd Wauters",
    "wof:placetype":"venue"
},
  "geometry": {"coordinates":[4.5166358948,51.4327926636],"type":"Point"}
}