{
  "type": "Feature",
  "properties": {
    "addr:full":"Rue Hector Denis 6 Renaix Oost-Vlaanderen 9600",
    "addr:housenumber":"6",
    "addr:postcode":"9600",
    "addr:street":"Rue Hector Denis",
    "iso:country":"BE",
    "sg:address":"Rue Hector Denis 6",
    "sg:city":"Renaix",
    "sg:classifiers":[
        {
            "category":"Building & Trades",
            "subcategory":"Construction",
            "type":"Services"
        }
    ],
    "sg:phone":"+32 55 21 04 62",
    "sg:postcode":"9600",
    "sg:province":"Oost-Vlaanderen",
    "sg:tags":[
        "paper",
        "hanger"
    ],
    "wof:name":"Mathu E",
    "wof:placetype":"venue"
},
  "geometry": {"coordinates":[3.6052610874,50.7357978821],"type":"Point"}
}