{
  "type": "Feature",
  "properties": {
    "iso:country":"BE",
    "sg:address":"Markgravelei 51",
    "sg:city":"Antwerpen",
    "sg:classifiers":[
        {
            "category":"Social Services",
            "type":"Services"
        }
    ],
    "sg:phone":"+32 3 260 90 43",
    "sg:postcode":"2018",
    "sg:province":"Antwerpen",
    "sg:tags":[
        "handicapped",
        "-"
    ],
    "wof:name":"Vlaamse Klank- En Braille- Bibliotheek Licht En Liefde",
    "wof:placetype":"venue"
},
  "geometry": {"coordinates":[4.4000091553,51.2000274658],"type":"Point"}
}