{
  "type": "Feature",
  "properties": {
    "iso:country":"BE",
    "sg:address":"Dhoorestraat 17",
    "sg:city":"Brugge",
    "sg:orig_category":"Avocats and conseillers juridiques",
    "sg:phone":"+32 50 37 30 77",
    "sg:postcode":"8310",
    "sg:province":"West-Vlaanderen",
    "wof:name":"Raoul Kerstens",
    "wof:placetype":"venue"
},
  "geometry": {"coordinates":[3.2421090603,51.2002563477],"type":"Point"}
}