{
  "type": "Feature",
  "properties": {
    "iso:country":"BE",
    "sg:address":"Rue Du Quatre Ao\u00dbt 48",
    "sg:city":"Wavre",
    "sg:orig_category":"M\u00e9decins and sp\u00e9cialistes",
    "sg:phone":"+32 10 22 71 64",
    "sg:postcode":"1300",
    "sg:province":"Brabant Wallon",
    "wof:name":"S. Fauvel",
    "wof:placetype":"venue"
},
  "geometry": {"coordinates":[4.609609127,50.7187347412],"type":"Point"}
}