{
  "type": "Feature",
  "properties": {
    "iso:country":"BE",
    "sg:address":"Rue Du Progr\u00e8s 9",
    "sg:city":"Courcelles",
    "sg:classifiers":[
        {
            "category":"Manufacturing",
            "subcategory":"Tools & Machinery",
            "type":"Manufacturing & Wholesale Goods"
        }
    ],
    "sg:phone":"+32 71 45 08 12",
    "sg:postcode":"6180",
    "sg:province":"Hainaut",
    "sg:tags":[
        "builder"
    ],
    "wof:name":"Dilaville",
    "wof:placetype":"venue"
},
  "geometry": {"coordinates":[4.3826518059,50.4514160156],"type":"Point"}
}