{
  "type": "Feature",
  "properties": {
    "addr:full":"Oostendestraat 384 Torhout West-Vlaanderen 8820",
    "addr:housenumber":"384",
    "addr:postcode":"8820",
    "addr:street":"Oostendestraat",
    "iso:country":"BE",
    "sg:address":"Oostendestraat 384",
    "sg:city":"Torhout",
    "sg:classifiers":[
        {
            "category":"Restaurant",
            "type":"Food & Drink"
        }
    ],
    "sg:phone":"+32 50 21 66 19",
    "sg:postcode":"8820",
    "sg:province":"West-Vlaanderen",
    "wof:name":"Bistro Windes",
    "wof:placetype":"venue"
},
  "geometry": {"coordinates":[3.0649108887,51.0770263672],"type":"Point"}
}