{
  "type": "Feature",
  "properties": {
    "addr:full":"Rue Blaes 95-99 Bruxelles Bruxelles-Capitale 1000",
    "addr:housenumber":"95-99",
    "addr:postcode":"1000",
    "addr:street":"Rue Blaes",
    "iso:country":"BE",
    "sg:address":"Rue Blaes 95-99",
    "sg:city":"Bruxelles",
    "sg:classifiers":[
        {
            "category":"Home & Garden",
            "subcategory":"Home Furnishings",
            "type":"Retail Goods"
        }
    ],
    "sg:phone":"+32 2 511 53 52",
    "sg:postcode":"1000",
    "sg:province":"Bruxelles-Capitale",
    "sg:tags":[
        "interior",
        "decoration"
    ],
    "wof:name":"Aux 100.000 Rouleaux",
    "wof:placetype":"venue"
},
  "geometry": {"coordinates":[4.3483991623,50.8389625549],"type":"Point"}
}