{
  "type": "Feature",
  "properties": {
    "addr:full":"Rue Gare Du Nord 3 Thuin Hainaut 6530",
    "addr:housenumber":"3",
    "addr:postcode":"6530",
    "addr:street":"Rue Gare Du Nord",
    "iso:country":"BE",
    "sg:address":"Rue Gare Du Nord 3",
    "sg:city":"Thuin",
    "sg:classifiers":[
        {
            "category":"Bars & Pubs",
            "type":"Food & Drink"
        }
    ],
    "sg:phone":"+32 71 59 38 77",
    "sg:postcode":"6530",
    "sg:province":"Hainaut",
    "wof:name":"Taverne Le Splendid",
    "wof:placetype":"venue"
},
  "geometry": {"coordinates":[4.2876992226,50.3421974182],"type":"Point"}
}