{
  "type": "Feature",
  "properties": {
    "iso:country":"BE",
    "sg:address":"Brusselsestraat 128",
    "sg:city":"Leuven",
    "sg:classifiers":[
        {
            "category":"Communications",
            "type":"Services"
        }
    ],
    "sg:phone":"+32 16 62 49 92",
    "sg:postcode":"3000",
    "sg:province":"Vlaams-Brabant",
    "sg:tags":[
        "telecommunication"
    ],
    "wof:name":"Universal Telco",
    "wof:placetype":"venue"
},
  "geometry": {"coordinates":[4.694355011,50.8806381226],"type":"Point"}
}