{
  "type": "Feature",
  "properties": {
    "addr:full":"Andrimont 26 Stoumont Li\u00e8ge 4987",
    "addr:housenumber":"26",
    "addr:postcode":"4987",
    "addr:street":"Andrimont",
    "iso:country":"BE",
    "sg:address":"Andrimont 26",
    "sg:city":"Stoumont",
    "sg:orig_category":"Plomberie, chauffage and installations sanitaires",
    "sg:phone":"+32 80 78 56 93",
    "sg:postcode":"4987",
    "sg:province":"Li\u00e8ge",
    "wof:name":"Havet",
    "wof:placetype":"venue"
},
  "geometry": {"coordinates":[5.8098897934,50.4056663513],"type":"Point"}
}