{
  "type": "Feature",
  "properties": {
    "addr:full":"Chemin De Mons \u00e0 Gand 78 Lessines Hainaut 7860",
    "addr:housenumber":"78",
    "addr:postcode":"7860",
    "addr:street":"Chemin De Mons A\u0300 Gand;Hainaut",
    "iso:country":"BE",
    "sg:address":"Chemin De Mons \u00e0 Gand 78",
    "sg:city":"Lessines",
    "sg:classifiers":[
        {
            "category":"Shopping",
            "subcategory":"Stationery & Office Supplies",
            "type":"Retail Goods"
        }
    ],
    "sg:phone":"+32 68 33 73 14",
    "sg:postcode":"7860",
    "sg:province":"Hainaut",
    "sg:tags":[
        "partition"
    ],
    "wof:name":"Paracloisons Sc",
    "wof:placetype":"venue"
},
  "geometry": {"coordinates":[3.8497729301,50.7149543762],"type":"Point"}
}