{
  "type": "Feature",
  "properties": {
    "addr:full":"Kremerslei 2 Duffel Antwerpen 2570",
    "addr:housenumber":"2",
    "addr:postcode":"2570",
    "addr:street":"Kremerslei",
    "iso:country":"BE",
    "sg:address":"Kremerslei 2",
    "sg:city":"Duffel",
    "sg:orig_category":"Quincailleries. Meubles Fab. Installation de menuiserie en bois and plastique. Fabrication and monta",
    "sg:phone":"+32 15 31 52 83",
    "sg:postcode":"2570",
    "sg:province":"Antwerpen",
    "wof:name":"Vancoppenolle",
    "wof:placetype":"venue"
},
  "geometry": {"coordinates":[4.5018129349,51.100856781],"type":"Point"}
}