{
  "type": "Feature",
  "properties": {
    "addr:full":"Kerkhofstraat 19 Brecht (sint-job-in-'t Goor) Antwerpen 2960",
    "addr:housenumber":"19",
    "addr:postcode":"2960",
    "addr:street":"Kerkhofstraat;' T Goor",
    "iso:country":"BE",
    "sg:address":"Kerkhofstraat 19",
    "sg:city":"Brecht (sint-job-in-'t Goor)",
    "sg:classifiers":[
        {
            "category":"Building & Trades",
            "subcategory":"Cleaning & Sanitation",
            "type":"Services"
        }
    ],
    "sg:phone":"+32 3 311 79 66",
    "sg:postcode":"2960",
    "sg:province":"Antwerpen",
    "sg:tags":[
        "fa\u00e7ade",
        "maintenance"
    ],
    "wof:name":"Miba",
    "wof:placetype":"venue"
},
  "geometry": {"coordinates":[4.5789651871,51.2934303284],"type":"Point"}
}