{
  "type": "Feature",
  "properties": {
    "iso:country":"BE",
    "sg:address":"Rue De La Marzelle 66",
    "sg:city":"Sivry-rance",
    "sg:orig_category":"Kansspelen",
    "sg:phone":"+32 60 45 52 44",
    "sg:postcode":"6470",
    "sg:province":"Hainaut",
    "wof:name":"Ladbrokes",
    "wof:placetype":"venue"
},
  "geometry": {"coordinates":[4.1549201012,50.1671600342],"type":"Point"}
}