{
  "type": "Feature",
  "properties": {
    "iso:country":"BE",
    "sg:address":"Torhoutsesteenweg 32",
    "sg:city":"Oostende",
    "sg:classifiers":[
        {
            "category":"Bars & Pubs",
            "type":"Food & Drink"
        }
    ],
    "sg:phone":"+32 59 50 73 20",
    "sg:postcode":"8400",
    "sg:province":"West-Vlaanderen",
    "wof:name":"King's Horse",
    "wof:placetype":"venue"
},
  "geometry": {"coordinates":[2.9098620415,51.2264556885],"type":"Point"}
}