{
  "type": "Feature",
  "properties": {
    "addr:full":"Sint-rochusstraat 72 Halle Vlaams-Brabant 1500",
    "addr:housenumber":"72",
    "addr:postcode":"1500",
    "addr:street":"Sint-Rochusstraat",
    "iso:country":"BE",
    "sg:address":"Sint-rochusstraat 72",
    "sg:city":"Halle",
    "sg:orig_category":"S\u00e9curit\u00e9 sociale",
    "sg:phone":"+32 2 356 53 82",
    "sg:postcode":"1500",
    "sg:province":"Vlaams-Brabant",
    "wof:name":"Liberale Mutualiteit",
    "wof:placetype":"venue"
},
  "geometry": {"coordinates":[4.2400488853,50.7305450439],"type":"Point"}
}