{
  "type": "Feature",
  "properties": {
    "iso:country":"BE",
    "sg:address":"Rue Des Droits De L'enfant 8 Box 38",
    "sg:city":"Binche (p\u00e9ronnes-lez-binche)",
    "sg:classifiers":[
        {
            "category":"Travel",
            "subcategory":"Resort",
            "type":"Entertainment"
        }
    ],
    "sg:phone":"+32 64 33 56 87",
    "sg:postcode":"7134",
    "sg:province":"Hainaut",
    "sg:tags":[
        "vacation"
    ],
    "wof:name":"Centre Joseph Arman Asbl",
    "wof:placetype":"venue"
},
  "geometry": {"coordinates":[4.1589570045,50.4388656616],"type":"Point"}
}