{
  "type": "Feature",
  "properties": {
    "iso:country":"BE",
    "sg:address":"Avenue Du Roi 165",
    "sg:city":"Vorst/forest",
    "sg:orig_category":"M\u00e9decins and sp\u00e9cialistes",
    "sg:phone":"+32 2 534 10 06",
    "sg:postcode":"1190",
    "sg:province":"Bruxelles-Capitale",
    "wof:name":"Philippe Sorlin",
    "wof:placetype":"venue"
},
  "geometry": {"coordinates":[4.3341798782,50.8259506226],"type":"Point"}
}