{
  "type": "Feature",
  "properties": {
    "addr:full":"Oordegemsesteenweg 249 Wetteren Oost-Vlaanderen 9230",
    "addr:housenumber":"249",
    "addr:postcode":"9230",
    "addr:street":"Oordegemsesteenweg",
    "iso:country":"BE",
    "sg:address":"Oordegemsesteenweg 249",
    "sg:city":"Wetteren",
    "sg:classifiers":[
        {
            "category":"Autos & Motor Vehicles",
            "subcategory":"Automobile Sales",
            "type":"Retail Goods"
        }
    ],
    "sg:phone":"+32 9 368 01 46",
    "sg:postcode":"9230",
    "sg:province":"Oost-Vlaanderen",
    "sg:tags":[
        "car",
        "used",
        "-"
    ],
    "wof:name":"D'hauwe L",
    "wof:placetype":"venue"
},
  "geometry": {"coordinates":[3.8870398998,50.9932403564],"type":"Point"}
}