{
  "type": "Feature",
  "properties": {
    "iso:country":"BE",
    "sg:address":"Rozenlaan 33",
    "sg:city":"Peer",
    "sg:orig_category":"Ordinateurs and \u00e9quipement informatique",
    "sg:phone":"+32 11 63 12 54",
    "sg:postcode":"3990",
    "sg:province":"Limburg",
    "wof:name":"Cck Computers",
    "wof:placetype":"venue"
},
  "geometry": {"coordinates":[5.471039772,51.1421432495],"type":"Point"}
}