{
  "type": "Feature",
  "properties": {
    "addr:full":"Eikenstraat 43 Beringen Limburg 3580",
    "addr:housenumber":"43",
    "addr:postcode":"3580",
    "addr:street":"Eikenstraat",
    "iso:country":"BE",
    "sg:address":"Eikenstraat 43",
    "sg:city":"Beringen",
    "sg:orig_category":"Peinture. Travaux de finition and nettoyage de b\u00e2timents",
    "sg:phone":"+32 476 45 90 78",
    "sg:postcode":"3580",
    "sg:province":"Limburg",
    "wof:name":"Alroclean",
    "wof:placetype":"venue"
},
  "geometry": {"coordinates":[5.2150821686,51.0597763062],"type":"Point"}
}