{
  "type": "Feature",
  "properties": {
    "iso:country":"BE",
    "sg:address":"Vanderkinderestraat 103",
    "sg:city":"Ukkel/uccle",
    "sg:orig_category":"Herstellingen and onderhoud van auto's",
    "sg:phone":"+32 2 343 05 58",
    "sg:postcode":"1180",
    "sg:province":"Bruxelles-Capitale",
    "wof:name":"Garage Sauveni\u00c8re",
    "wof:placetype":"venue"
},
  "geometry": {"coordinates":[4.344080925,50.8135948181],"type":"Point"}
}