{
  "type": "Feature",
  "properties": {
    "addr:full":"Hundelgemsesteenweg 363 Merelbeke Oost-Vlaanderen 9820",
    "addr:housenumber":"363",
    "addr:postcode":"9820",
    "addr:street":"Hundelgemsesteenweg",
    "iso:country":"BE",
    "sg:address":"Hundelgemsesteenweg 363",
    "sg:city":"Merelbeke",
    "sg:orig_category":"Verplichte sociale verzekeringen",
    "sg:phone":"+32 9 231 49 19",
    "sg:postcode":"9820",
    "sg:province":"Oost-Vlaanderen",
    "wof:name":"Bond Moyson",
    "wof:placetype":"venue"
},
  "geometry": {"coordinates":[3.7459108829,50.9940757751],"type":"Point"}
}