{
  "type": "Feature",
  "properties": {
    "addr:full":"Sint-pieterskaai 25 Brugge West-Vlaanderen 8000",
    "addr:housenumber":"25",
    "addr:postcode":"8000",
    "addr:street":"Sint-Pieterskaai",
    "iso:country":"BE",
    "sg:address":"Sint-pieterskaai 25",
    "sg:city":"Brugge",
    "sg:orig_category":"Slagers",
    "sg:phone":"+32 50 31 33 28",
    "sg:postcode":"8000",
    "sg:province":"West-Vlaanderen",
    "wof:name":"Renmans",
    "wof:placetype":"venue"
},
  "geometry": {"coordinates":[3.2179501057,51.2210388184],"type":"Point"}
}