{
  "type": "Feature",
  "properties": {
    "addr:full":"Stationsstraat 65 Waregem West-Vlaanderen 8790",
    "addr:housenumber":"65",
    "addr:postcode":"8790",
    "addr:street":"Stationsstraat",
    "iso:country":"BE",
    "sg:address":"Stationsstraat 65",
    "sg:city":"Waregem",
    "sg:orig_category":"Slagers",
    "sg:phone":"+32 56 61 32 72",
    "sg:postcode":"8790",
    "sg:province":"West-Vlaanderen",
    "wof:name":"Slagerij Markey",
    "wof:placetype":"venue"
},
  "geometry": {"coordinates":[3.4300971031,50.8887519836],"type":"Point"}
}