{
  "type": "Feature",
  "properties": {
    "addr:full":"Chauss\u00c9e De Louvain 388 Zaventem Vlaams-Brabant 1932",
    "addr:housenumber":"388",
    "addr:postcode":"1932",
    "addr:street":"Chausse\u0301E De Louvain",
    "iso:country":"BE",
    "sg:address":"Chauss\u00c9e De Louvain 388",
    "sg:city":"Zaventem",
    "sg:orig_category":"R\u00e9alisation de programmes and logiciels. Traducteurs and interpr\u00e8tes. Production de films, t\u00e9l\u00e9films",
    "sg:phone":"+32 2 720 37 87",
    "sg:postcode":"1932",
    "sg:province":"Vlaams-Brabant",
    "wof:name":"Virtual Word",
    "wof:placetype":"venue"
},
  "geometry": {"coordinates":[4.462747097,50.8703422546],"type":"Point"}
}