{
  "type": "Feature",
  "properties": {
    "addr:full":"Bergenstraat 9 Alveringem West-Vlaanderen 8691",
    "addr:housenumber":"9",
    "addr:postcode":"8691",
    "addr:street":"Bergenstraat",
    "iso:country":"BE",
    "sg:address":"Bergenstraat 9",
    "sg:city":"Alveringem",
    "sg:orig_category":"G\u00e9om\u00e8tres",
    "sg:phone":"+32 57 30 12 42",
    "sg:postcode":"8691",
    "sg:province":"West-Vlaanderen",
    "wof:name":"Eddy Ameloot",
    "wof:placetype":"venue"
},
  "geometry": {"coordinates":[2.6200470924,50.9215736389],"type":"Point"}
}