{
  "type": "Feature",
  "properties": {
    "iso:country":"BE",
    "sg:address":"Brechtsebaan 129",
    "sg:city":"Brasschaat",
    "sg:orig_category":"Installation \u00e9lectrique r\u00e9sidentielle",
    "sg:phone":"+32 3 663 46 52",
    "sg:postcode":"2930",
    "sg:province":"Antwerpen",
    "wof:name":"Jozef Vierbergen",
    "wof:placetype":"venue"
},
  "geometry": {"coordinates":[4.5314249992,51.3265914917],"type":"Point"}
}