{
  "type": "Feature",
  "properties": {
    "iso:country":"BE",
    "sg:address":"Place Des B\u00c9guinages 5",
    "sg:city":"Liege",
    "sg:classifiers":[
        {
            "category":"Restaurant",
            "type":"Food & Drink"
        }
    ],
    "sg:phone":"+32 4 223 00 93",
    "sg:postcode":"4000",
    "sg:province":"Li\u00e8ge",
    "wof:name":"Coup De Coeur",
    "wof:placetype":"venue"
},
  "geometry": {"coordinates":[5.5642518997,50.6403007507],"type":"Point"}
}