{
  "type": "Feature",
  "properties": {
    "iso:country":"BE",
    "sg:address":"Naamsesteenweg 118",
    "sg:city":"Leuven (heverlee)",
    "sg:classifiers":[
        {
            "category":"Communications",
            "type":"Services"
        }
    ],
    "sg:phone":"+32 16 23 19 42",
    "sg:postcode":"3001",
    "sg:province":"Vlaams-Brabant",
    "sg:tags":[
        "translator"
    ],
    "wof:name":"Alfabet Vertaalbureau",
    "wof:placetype":"venue"
},
  "geometry": {"coordinates":[4.6958370209,50.8653526306],"type":"Point"}
}