{
  "type": "Feature",
  "properties": {
    "iso:country":"BE",
    "sg:address":"Chemin De La Procession 258a",
    "sg:city":"Mons",
    "sg:classifiers":[
        {
            "category":"Autos & Motor Vehicles",
            "subcategory":"Boat Sales",
            "type":"Retail Goods"
        }
    ],
    "sg:phone":"+32 475 28 46 59",
    "sg:postcode":"7000",
    "sg:province":"Hainaut",
    "sg:tags":[
        "automobile",
        "sunroof",
        "-",
        "roof"
    ],
    "wof:name":"Tint-tech",
    "wof:placetype":"venue"
},
  "geometry": {"coordinates":[3.9674360752,50.4620552063],"type":"Point"}
}