{
  "type": "Feature",
  "properties": {
    "iso:country":"BE",
    "sg:address":"J.-b. Vanp\u00c9straat 1",
    "sg:city":"Vorst/forest",
    "sg:classifiers":[
        {
            "category":"Cafe",
            "type":"Food & Drink"
        }
    ],
    "sg:phone":"+32 2 332 27 49",
    "sg:postcode":"1190",
    "sg:province":"Bruxelles-Capitale",
    "sg:tags":[
        "caf\u00e9s"
    ],
    "wof:name":"Wembley's Pub",
    "wof:placetype":"venue"
},
  "geometry": {"coordinates":[4.3177690506,50.8097000122],"type":"Point"}
}