{
  "type": "Feature",
  "properties": {
    "addr:full":"Rozenlaan 15 Rumst Antwerpen 2840",
    "addr:housenumber":"15",
    "addr:postcode":"2840",
    "addr:street":"Rozenlaan",
    "iso:country":"BE",
    "sg:address":"Rozenlaan 15",
    "sg:city":"Rumst",
    "sg:orig_category":"Koerierbedrijven",
    "sg:phone":"+32 3 888 56 13",
    "sg:postcode":"2840",
    "sg:province":"Antwerpen",
    "wof:name":"Partner Express",
    "wof:placetype":"venue"
},
  "geometry": {"coordinates":[4.3885560036,51.1054878235],"type":"Point"}
}