{
  "type": "Feature",
  "properties": {
    "iso:country":"BE",
    "sg:address":"Sint-annastraat 32",
    "sg:city":"Tielt-winge (tielt)",
    "sg:classifiers":[
        {
            "category":"Cafe",
            "type":"Food & Drink"
        }
    ],
    "sg:phone":"+32 16 63 20 10",
    "sg:postcode":"3390",
    "sg:province":"Vlaams-Brabant",
    "sg:tags":[
        "snack-bars"
    ],
    "wof:name":"Lemmens W",
    "wof:placetype":"venue"
},
  "geometry": {"coordinates":[4.9032168388,50.9379005432],"type":"Point"}
}