{
  "type": "Feature",
  "properties": {
    "addr:full":"Rue Du Bon Voisin 84a Tubize (oisquercq) Brabant Wallon 1480",
    "addr:housenumber":"84a",
    "addr:postcode":"1480",
    "addr:street":"Rue Du Bon Voisin;Wallon",
    "iso:country":"BE",
    "sg:address":"Rue Du Bon Voisin 84a",
    "sg:city":"Tubize (oisquercq)",
    "sg:classifiers":[
        {
            "category":"Wholesale",
            "subcategory":"Wine & Distilled Alcoholic Beverages",
            "type":"Manufacturing & Wholesale Goods"
        }
    ],
    "sg:phone":"+32 67 64 62 31",
    "sg:postcode":"1480",
    "sg:province":"Brabant Wallon",
    "sg:tags":[
        "whol",
        "-",
        "spirit",
        "mfg"
    ],
    "wof:name":"Sommelier (le)",
    "wof:placetype":"venue"
},
  "geometry": {"coordinates":[4.2342128754,50.6620025635],"type":"Point"}
}