{
  "type": "Feature",
  "properties": {
    "addr:full":"Dendermondsesteenweg 13 Hamme Oost-Vlaanderen 9220",
    "addr:housenumber":"13",
    "addr:postcode":"9220",
    "addr:street":"Dendermondsesteenweg",
    "iso:country":"BE",
    "sg:address":"Dendermondsesteenweg 13",
    "sg:city":"Hamme",
    "sg:orig_category":"Fabrication and montage de mobilier. Eclairage et \u00e9quipements du foyer",
    "sg:phone":"+32 52 47 94 13",
    "sg:postcode":"9220",
    "sg:province":"Oost-Vlaanderen",
    "wof:name":"Keukens De Decker & Zoon",
    "wof:placetype":"venue"
},
  "geometry": {"coordinates":[4.1221628189,51.0715942383],"type":"Point"}
}