{
  "type": "Feature",
  "properties": {
    "addr:full":"Avenue Raymond Vander Bruggen 54-60 Bruxelles (anderlecht) Bruxelles-Capitale 1070",
    "addr:postcode":"54-60;1070",
    "addr:street":"Avenue Raymond Vander Bruggen",
    "iso:country":"BE",
    "sg:address":"Avenue Raymond Vander Bruggen 54-60",
    "sg:city":"Bruxelles (anderlecht)",
    "sg:orig_category":"Non-Classified Establishments",
    "sg:phone":"+32 2 521 52 15",
    "sg:postcode":"1070",
    "sg:province":"Bruxelles-Capitale",
    "wof:name":"Vanden Bergh-bouss Sprl",
    "wof:placetype":"venue"
},
  "geometry": {"coordinates":[4.3143620491,50.8376579285],"type":"Point"}
}