{
  "type": "Feature",
  "properties": {
    "addr:full":"Doornstraat 84 Temse Oost-Vlaanderen 9140",
    "addr:housenumber":"84",
    "addr:postcode":"9140",
    "addr:street":"Doornstraat",
    "iso:country":"BE",
    "sg:address":"Doornstraat 84",
    "sg:city":"Temse",
    "sg:classifiers":[
        {
            "category":"Health Services",
            "subcategory":"Health Practitioner",
            "type":"Services"
        }
    ],
    "sg:phone":"+32 3 771 69 06",
    "sg:postcode":"9140",
    "sg:province":"Oost-Vlaanderen",
    "sg:tags":[
        "therapist",
        "speech"
    ],
    "wof:name":"Meeus Els",
    "wof:placetype":"venue"
},
  "geometry": {"coordinates":[4.2084360123,51.1405487061],"type":"Point"}
}