{
  "type": "Feature",
  "properties": {
    "addr:full":"R.g\u00c9n. G\u00c9rard & Vandamme 3 Sombreffe Namur 5140",
    "addr:housenumber":"3",
    "addr:postcode":"5140",
    "iso:country":"BE",
    "sg:address":"R.g\u00c9n. G\u00c9rard & Vandamme 3",
    "sg:city":"Sombreffe",
    "sg:orig_category":"Woningbouw",
    "sg:phone":"+32 71 88 75 54",
    "sg:postcode":"5140",
    "sg:province":"Namur",
    "wof:name":"Ruddy Franc",
    "wof:placetype":"venue"
},
  "geometry": {"coordinates":[4.5735421181,50.5139045715],"type":"Point"}
}