{
  "type": "Feature",
  "properties": {
    "iso:country":"BE",
    "sg:address":"Klein-malstraat 36",
    "sg:city":"Tongeren",
    "sg:orig_category":"Varkenskwekers",
    "sg:phone":"+32 12 23 19 19",
    "sg:postcode":"3700",
    "sg:province":"Limburg",
    "wof:name":"Germain Berckenbosch",
    "wof:placetype":"venue"
},
  "geometry": {"coordinates":[5.5189480782,50.7739944458],"type":"Point"}
}