{
  "type": "Feature",
  "properties": {
    "addr:full":"Pastinakenstraat 148 Asse Vlaams-Brabant 1730",
    "addr:housenumber":"148",
    "addr:postcode":"1730",
    "addr:street":"Pastinakenstraat",
    "iso:country":"BE",
    "sg:address":"Pastinakenstraat 148",
    "sg:city":"Asse",
    "sg:classifiers":[
        {
            "category":"Arena",
            "subcategory":"Sports Club",
            "type":"Entertainment"
        }
    ],
    "sg:phone":"+32 2 452 61 18",
    "sg:postcode":"1730",
    "sg:province":"Vlaams-Brabant",
    "sg:tags":[
        "de"
    ],
    "wof:name":"H.c. Green Devils",
    "wof:placetype":"venue"
},
  "geometry": {"coordinates":[4.2051520348,50.8969192505],"type":"Point"}
}