{
  "type": "Feature",
  "properties": {
    "iso:country":"BE",
    "sg:address":"Rue Gilles Magn\u00e9e 92-6",
    "sg:city":"Ans",
    "sg:classifiers":[
        {
            "category":"Communications",
            "subcategory":"Film & Video Production",
            "type":"Services"
        }
    ],
    "sg:phone":"+32 4 239 78 80",
    "sg:postcode":"4430",
    "sg:province":"Li\u00e8ge",
    "sg:tags":[
        "multimedia",
        "-",
        "system"
    ],
    "wof:name":"Deltatec Bureau D'etudes Electroniques",
    "wof:placetype":"venue"
},
  "geometry": {"coordinates":[5.5293679237,50.6607818604],"type":"Point"}
}