{
  "type": "Feature",
  "properties": {
    "addr:full":"Klostergasse 10 Kelmis Li\u00e8ge 4720",
    "addr:housenumber":"10",
    "addr:postcode":"4720",
    "addr:street":"Klostergasse",
    "iso:country":"BE",
    "sg:address":"Klostergasse 10",
    "sg:city":"Kelmis",
    "sg:classifiers":[
        {
            "category":"Banks & Credit Unions",
            "subcategory":"Investment Brokerage",
            "type":"Services"
        }
    ],
    "sg:phone":"+32 87 65 65 86",
    "sg:postcode":"4720",
    "sg:province":"Li\u00e8ge",
    "sg:tags":[
        "repair",
        "-",
        "installation",
        "sanitary",
        "article"
    ],
    "wof:name":"Braun Raymond",
    "wof:placetype":"venue"
},
  "geometry": {"coordinates":[6.0142297745,50.7160186768],"type":"Point"}
}