{
  "type": "Feature",
  "properties": {
    "iso:country":"BE",
    "sg:address":"Emiel Clausstraat 35",
    "sg:city":"Waregem (sint-eloois-vijve)",
    "sg:classifiers":[
        {
            "category":"Banks & Credit Unions",
            "subcategory":"Investment Brokerage",
            "type":"Services"
        }
    ],
    "sg:phone":"+32 56 62 51 41",
    "sg:postcode":"8793",
    "sg:province":"West-Vlaanderen",
    "sg:tags":[
        "supply",
        "processing",
        "-",
        "access",
        "carrier",
        "data"
    ],
    "wof:name":"Eurotra",
    "wof:placetype":"venue"
},
  "geometry": {"coordinates":[3.4088089466,50.9098243713],"type":"Point"}
}