{
  "type": "Feature",
  "properties": {
    "addr:full":"Bierbeekstraat 64b Bierbeek Vlaams-Brabant 3360",
    "addr:housenumber":"64b",
    "addr:postcode":"3360",
    "addr:street":"Bierbeekstraat",
    "iso:country":"BE",
    "sg:address":"Bierbeekstraat 64b",
    "sg:city":"Bierbeek",
    "sg:classifiers":[
        {
            "category":"Bars & Pubs",
            "type":"Food & Drink"
        }
    ],
    "sg:phone":"+32 16 46 11 18",
    "sg:postcode":"3360",
    "sg:province":"Vlaams-Brabant",
    "wof:name":"Dino's Cafe",
    "wof:placetype":"venue"
},
  "geometry": {"coordinates":[4.762075901,50.8593482971],"type":"Point"}
}