{
  "type": "Feature",
  "properties": {
    "addr:full":"Rue D'hervin 4bc Tellin Luxembourg 6927",
    "addr:housenumber":"4bc",
    "addr:postcode":"6927",
    "addr:street":"Rue D'Hervin",
    "iso:country":"BE",
    "sg:address":"Rue D'hervin 4bc",
    "sg:city":"Tellin",
    "sg:orig_category":"Eleveurs de bovins",
    "sg:phone":"+32 84 38 87 14",
    "sg:postcode":"6927",
    "sg:province":"Luxembourg",
    "wof:name":"Gilbert Lamotte",
    "wof:placetype":"venue"
},
  "geometry": {"coordinates":[5.2020201683,50.0837135315],"type":"Point"}
}