{
  "type": "Feature",
  "properties": {
    "addr:full":"Eppegemsesteenweg 31-33 Grimbergen Vlaams-Brabant 1850",
    "addr:postcode":"31-33;1850",
    "addr:street":"Eppegemsesteenweg",
    "iso:country":"BE",
    "sg:address":"Eppegemsesteenweg 31-33",
    "sg:city":"Grimbergen",
    "sg:orig_category":"DISTRIBUTORS: SYSTEMS",
    "sg:phone":"+32 2 255 12 41",
    "sg:postcode":"1850",
    "sg:province":"Vlaams-Brabant",
    "wof:name":"Sbt Nv",
    "wof:placetype":"venue"
},
  "geometry": {"coordinates":[4.4174690247,50.9498329163],"type":"Point"}
}