{
  "type": "Feature",
  "properties": {
    "iso:country":"BE",
    "sg:address":"Place Eug\u00e8ne Simonis 5",
    "sg:city":"Bruxelles (koekelberg)",
    "sg:classifiers":[
        {
            "category":"Professional",
            "subcategory":"Testing Lab",
            "type":"Services"
        }
    ],
    "sg:phone":"+32 2 410 65 77",
    "sg:postcode":"1081",
    "sg:province":"Bruxelles-Capitale",
    "sg:tags":[
        "chemist"
    ],
    "wof:name":"Parmentier D",
    "wof:placetype":"venue"
},
  "geometry": {"coordinates":[4.329750061,50.8632888794],"type":"Point"}
}