{
  "type": "Feature",
  "properties": {
    "addr:full":"Smoorstraat 29 Waasmunster Oost-Vlaanderen 9250",
    "addr:housenumber":"29",
    "addr:postcode":"9250",
    "addr:street":"Smoorstraat",
    "iso:country":"BE",
    "sg:address":"Smoorstraat 29",
    "sg:city":"Waasmunster",
    "sg:classifiers":[
        {
            "category":"Banks & Credit Unions",
            "subcategory":"Investment Brokerage",
            "type":"Services"
        }
    ],
    "sg:phone":"+32 52 22 00 43",
    "sg:postcode":"9250",
    "sg:province":"Oost-Vlaanderen",
    "sg:tags":[
        "repair",
        "-",
        "installation",
        "sanitary",
        "article"
    ],
    "wof:name":"Moens Bvba",
    "wof:placetype":"venue"
},
  "geometry": {"coordinates":[4.1251721382,51.11145401],"type":"Point"}
}