{
  "type": "Feature",
  "properties": {
    "addr:full":"Aalterbaan 230bb Maldegem Oost-Vlaanderen 9990",
    "addr:postcode":"9990",
    "addr:street":"Oost-Vlaanderen",
    "iso:country":"BE",
    "sg:address":"Aalterbaan 230bb",
    "sg:city":"Maldegem",
    "sg:orig_category":"Quincailleries",
    "sg:phone":"+32 50 71 11 34",
    "sg:postcode":"9990",
    "sg:province":"Oost-Vlaanderen",
    "wof:name":"Bouwstock Taeldeman",
    "wof:placetype":"venue"
},
  "geometry": {"coordinates":[3.4401988983,51.1638183594],"type":"Point"}
}