{
  "type": "Feature",
  "properties": {
    "addr:full":"Rue Du G\u00c9n\u00c9ral Bertrand 66 Li\u00c8ge Li\u00e8ge 4000",
    "addr:housenumber":"66",
    "addr:postcode":"4000",
    "addr:street":"Rue Du Ge\u0301Ne\u0301Ral Bertrand",
    "iso:country":"BE",
    "sg:address":"Rue Du G\u00c9n\u00c9ral Bertrand 66",
    "sg:city":"Li\u00c8ge",
    "sg:orig_category":"Apotheken",
    "sg:phone":"+32 4 226 23 34",
    "sg:postcode":"4000",
    "sg:province":"Li\u00e8ge",
    "wof:name":"Andre Honba-honba",
    "wof:placetype":"venue"
},
  "geometry": {"coordinates":[5.5561161041,50.6442756653],"type":"Point"}
}