{
  "type": "Feature",
  "properties": {
    "iso:country":"BE",
    "sg:address":"Kapelsesteenweg 406",
    "sg:city":"Brasschaat",
    "sg:classifiers":[
        {
            "category":"Organizations",
            "subcategory":"Professional Association",
            "type":"Services"
        }
    ],
    "sg:phone":"+32 3 295 82 59",
    "sg:postcode":"2930",
    "sg:province":"Antwerpen",
    "sg:tags":[
        "organisation",
        "seminar"
    ],
    "wof:name":"Prinses Sjalot Bvba",
    "wof:placetype":"venue"
},
  "geometry": {"coordinates":[4.4434480667,51.2934875488],"type":"Point"}
}