{
  "type": "Feature",
  "properties": {
    "addr:full":"Magnolialaan 3 Kapellen Antwerpen 2950",
    "addr:housenumber":"3",
    "addr:postcode":"2950",
    "addr:street":"Magnolialaan",
    "iso:country":"BE",
    "sg:address":"Magnolialaan 3",
    "sg:city":"Kapellen",
    "sg:classifiers":[
        {
            "category":"Professional",
            "type":"Services"
        }
    ],
    "sg:phone":"+32 3 660 26 65",
    "sg:postcode":"2950",
    "sg:province":"Antwerpen",
    "sg:tags":[
        "forwarding",
        "agency"
    ],
    "wof:name":"Intermar Shipping & Agencies Bvba",
    "wof:placetype":"venue"
},
  "geometry": {"coordinates":[4.4250478745,51.3293571472],"type":"Point"}
}