{
  "type": "Feature",
  "properties": {
    "addr:full":"Place Du Joncquois 11 Honnelles Hainaut 7387",
    "addr:housenumber":"11",
    "addr:postcode":"7387",
    "addr:street":"Place Du Joncquois;Hainaut",
    "iso:country":"BE",
    "sg:address":"Place Du Joncquois 11",
    "sg:city":"Honnelles",
    "sg:orig_category":"Enseignement maternel and primaire",
    "sg:phone":"+32 65 63 47 79",
    "sg:postcode":"7387",
    "sg:province":"Hainaut",
    "wof:name":"Ecole Matern. Communale",
    "wof:placetype":"venue"
},
  "geometry": {"coordinates":[3.6959199905,50.3683853149],"type":"Point"}
}