{
  "type": "Feature",
  "properties": {
    "addr:full":"Chauss\u00e9e Bara 357 Waterloo Brabant Wallon 1410",
    "addr:housenumber":"357",
    "addr:postcode":"1410",
    "addr:street":"Chausse\u0301E Bara",
    "iso:country":"BE",
    "sg:address":"Chauss\u00e9e Bara 357",
    "sg:city":"Waterloo",
    "sg:classifiers":[
        {
            "category":"Professional",
            "subcategory":"Management & Consulting",
            "type":"Services"
        }
    ],
    "sg:phone":"+32 2 357 01 10",
    "sg:postcode":"1410",
    "sg:province":"Brabant Wallon",
    "sg:tags":[
        "-",
        "processing",
        "data",
        "consultant"
    ],
    "wof:name":"M & B Consulting",
    "wof:placetype":"venue"
},
  "geometry": {"coordinates":[4.3936371803,50.7023162842],"type":"Point"}
}