{
  "type": "Feature",
  "properties": {
    "addr:full":"Espeler 58 Burg-reuland (thommen) Li\u00e8ge 4791",
    "addr:housenumber":"58",
    "addr:postcode":"4791",
    "addr:street":"Espeler;Thommen",
    "iso:country":"BE",
    "sg:address":"Espeler 58",
    "sg:city":"Burg-reuland (thommen)",
    "sg:classifiers":[
        {
            "category":"Real Estate",
            "subcategory":"Architect",
            "type":"Services"
        }
    ],
    "sg:phone":"+32 80 32 92 61",
    "sg:postcode":"4791",
    "sg:province":"Li\u00e8ge",
    "wof:name":"Michaelis L",
    "wof:placetype":"venue"
},
  "geometry": {"coordinates":[6.0944099426,50.2024497986],"type":"Point"}
}