{
  "type": "Feature",
  "properties": {
    "iso:country":"BE",
    "sg:address":"Sterrewijk 9",
    "sg:city":"Aalter",
    "sg:orig_category":"Rundveehouders",
    "sg:phone":"+32 9 374 28 07",
    "sg:postcode":"9880",
    "sg:province":"Oost-Vlaanderen",
    "wof:name":"Jo Smessaert",
    "wof:placetype":"venue"
},
  "geometry": {"coordinates":[3.4321329594,51.0807495117],"type":"Point"}
}