{
  "type": "Feature",
  "properties": {
    "addr:full":"Rue Du Fort 131 C\u00e9rexhe-heuseux Li\u00e8ge 4632",
    "addr:housenumber":"131",
    "addr:postcode":"4632",
    "addr:street":"Rue Du Fort",
    "iso:country":"BE",
    "sg:address":"Rue Du Fort 131",
    "sg:city":"C\u00e9rexhe-heuseux",
    "sg:classifiers":[
        {
            "category":"Farming",
            "subcategory":"Fish & Marine Products",
            "type":"Manufacturing & Wholesale Goods"
        }
    ],
    "sg:phone":"+32 69 53 25 11",
    "sg:postcode":"4632",
    "sg:province":"Li\u00e8ge",
    "sg:tags":[
        "asphalt"
    ],
    "wof:name":"Scredema S.a",
    "wof:placetype":"venue"
},
  "geometry": {"coordinates":[3.4895200729,50.5959091187],"type":"Point"}
}