{
  "type": "Feature",
  "properties": {
    "iso:country":"BE",
    "sg:address":"Quai Taille Pierres 10",
    "sg:city":"Tournai",
    "sg:classifiers":[
        {
            "category":"Real Estate",
            "subcategory":"Architect",
            "type":"Services"
        }
    ],
    "sg:phone":"+32 69 22 96 68",
    "sg:postcode":"7500",
    "sg:province":"Hainaut",
    "wof:name":"Magain A",
    "wof:placetype":"venue"
},
  "geometry": {"coordinates":[3.3966100216,50.6047172546],"type":"Point"}
}