{
  "type": "Feature",
  "properties": {
    "addr:full":"Place De Helmet 5 Bruxelles (schaerbeek) Bruxelles-Capitale 1030",
    "addr:housenumber":"5",
    "addr:postcode":"1030",
    "addr:street":"Place De Helmet",
    "iso:country":"BE",
    "sg:address":"Place De Helmet 5",
    "sg:city":"Bruxelles (schaerbeek)",
    "sg:classifiers":[
        {
            "category":"Shopping",
            "subcategory":"Beauty & Cosmetics",
            "type":"Retail Goods"
        }
    ],
    "sg:phone":"+32 2 215 76 60",
    "sg:postcode":"1030",
    "sg:province":"Bruxelles-Capitale",
    "sg:tags":[
        "-",
        "perfumery"
    ],
    "wof:name":"De Coopman Sprl",
    "wof:placetype":"venue"
},
  "geometry": {"coordinates":[4.3898200989,50.872844696],"type":"Point"}
}