{
  "type": "Feature",
  "properties": {
    "iso:country":"BE",
    "sg:address":"Ruddervoordestraat 208",
    "sg:city":"Torhout",
    "sg:orig_category":"Eleveurs de bovins",
    "sg:phone":"+32 50 21 34 60",
    "sg:postcode":"8820",
    "sg:province":"West-Vlaanderen",
    "wof:name":"Monique Defauw",
    "wof:placetype":"venue"
},
  "geometry": {"coordinates":[3.1491529942,51.066696167],"type":"Point"}
}