{
  "type": "Feature",
  "properties": {
    "addr:full":"Vlinderstraat 2 Oostende West-Vlaanderen 8400",
    "addr:housenumber":"2",
    "addr:postcode":"8400",
    "addr:street":"Vlinderstraat",
    "iso:country":"BE",
    "sg:address":"Vlinderstraat 2",
    "sg:city":"Oostende",
    "sg:orig_category":"Apotheken",
    "sg:phone":"+32 59 80 02 58",
    "sg:postcode":"8400",
    "sg:province":"West-Vlaanderen",
    "wof:name":"Ann Raes",
    "wof:placetype":"venue"
},
  "geometry": {"coordinates":[2.9249310493,51.2160224915],"type":"Point"}
}