{
  "type": "Feature",
  "properties": {
    "addr:full":"Chemin Maurice Bouvette 3 Rebecq Brabant Wallon 1430",
    "addr:housenumber":"3",
    "addr:postcode":"1430",
    "addr:street":"Chemin Maurice Bouvette",
    "iso:country":"BE",
    "sg:address":"Chemin Maurice Bouvette 3",
    "sg:city":"Rebecq",
    "sg:orig_category":"Rundveehouders",
    "sg:phone":"+32 67 63 64 09",
    "sg:postcode":"1430",
    "sg:province":"Brabant Wallon",
    "wof:name":"Frank Vermaut",
    "wof:placetype":"venue"
},
  "geometry": {"coordinates":[4.1112890244,50.6481971741],"type":"Point"}
}