{
  "type": "Feature",
  "properties": {
    "addr:full":"Rue De La Station 49 Awans Li\u00e8ge 4340",
    "addr:housenumber":"49",
    "addr:postcode":"4340",
    "addr:street":"Rue De La Station",
    "iso:country":"BE",
    "sg:address":"Rue De La Station 49",
    "sg:city":"Awans",
    "sg:orig_category":"Recyclage de mati\u00e8res non m\u00e9talliques",
    "sg:phone":"+32 4 263 68 67",
    "sg:postcode":"4340",
    "sg:province":"Li\u00e8ge",
    "wof:name":"Reconvertor",
    "wof:placetype":"venue"
},
  "geometry": {"coordinates":[5.4597549438,50.66040802],"type":"Point"}
}