{
  "type": "Feature",
  "properties": {
    "addr:full":"Gilseinde 99 Ravels Antwerpen 2380",
    "addr:housenumber":"99",
    "addr:postcode":"2380",
    "addr:street":"Gilseinde",
    "iso:country":"BE",
    "sg:address":"Gilseinde 99",
    "sg:city":"Ravels",
    "sg:classifiers":[
        {
            "category":"Building & Trades",
            "subcategory":"Landscaping Services",
            "type":"Services"
        }
    ],
    "sg:phone":"+32 14 65 21 93",
    "sg:postcode":"2380",
    "sg:province":"Antwerpen",
    "sg:tags":[
        "gardening",
        "garden",
        "maintenance"
    ],
    "wof:name":"Verelst P",
    "wof:placetype":"venue"
},
  "geometry": {"coordinates":[5.0062069893,51.3712425232],"type":"Point"}
}