{
  "type": "Feature",
  "properties": {
    "iso:country":"BE",
    "sg:address":"Bosduifstraat 6",
    "sg:city":"Ravels",
    "sg:orig_category":"Rundveehouders",
    "sg:phone":"+32 14 65 54 39",
    "sg:postcode":"2380",
    "sg:province":"Antwerpen",
    "wof:name":"Franciscus Van Den Heuvel",
    "wof:placetype":"venue"
},
  "geometry": {"coordinates":[4.9936499596,51.370929718],"type":"Point"}
}