{
  "type": "Feature",
  "properties": {
    "iso:country":"BE",
    "sg:address":"Rue Jean Jaur\u00e8s 281",
    "sg:city":"Charleroi (dampremy)",
    "sg:classifiers":[
        {
            "category":"Retail",
            "subcategory":"Veterinary Services",
            "type":"Services"
        }
    ],
    "sg:phone":"+32 71 30 42 76",
    "sg:postcode":"6020",
    "sg:province":"Hainaut",
    "sg:tags":[
        "veterinarian"
    ],
    "wof:name":"Gruselle P",
    "wof:placetype":"venue"
},
  "geometry": {"coordinates":[4.4256868362,50.422164917],"type":"Point"}
}