{
  "type": "Feature",
  "properties": {
    "iso:country":"BE",
    "sg:address":"Mathias Gesweinstraat 5",
    "sg:city":"Gent-centrum",
    "sg:orig_category":"Advocaten and juridische adviseurs Balie van Gent",
    "sg:phone":"+32 9 234 28 12",
    "sg:postcode":"9000",
    "sg:province":"Oost-Vlaanderen",
    "wof:name":"Aernoudts Natalie",
    "wof:placetype":"venue"
},
  "geometry": {"coordinates":[3.710654974,51.0578308105],"type":"Point"}
}