{
  "type": "Feature",
  "properties": {
    "iso:country":"BE",
    "sg:address":"Avenue De La Sapini\u00c8re 2",
    "sg:city":"Rixensart",
    "sg:orig_category":"Reclamebureaus",
    "sg:phone":"+32 2 653 37 62",
    "sg:postcode":"1331",
    "sg:province":"Brabant Wallon",
    "wof:name":"A Little Agency",
    "wof:placetype":"venue"
},
  "geometry": {"coordinates":[4.5410637856,50.7335472107],"type":"Point"}
}