{
  "type": "Feature",
  "properties": {
    "iso:country":"BE",
    "sg:address":"Verpleegstersstraat 165",
    "sg:city":"Gent",
    "sg:orig_category":"Studios photographiques",
    "sg:phone":"+32 9 220 78 51",
    "sg:postcode":"9000",
    "sg:province":"Oost-Vlaanderen",
    "wof:name":"Michel Mommens",
    "wof:placetype":"venue"
},
  "geometry": {"coordinates":[3.7011311054,51.0396461487],"type":"Point"}
}