{
  "type": "Feature",
  "properties": {
    "iso:country":"BE",
    "sg:address":"Godevaert Braemstraat 5",
    "sg:city":"Temse (elversele)",
    "sg:classifiers":[
        {
            "category":"Health Services",
            "subcategory":"Health Practitioner",
            "type":"Services"
        }
    ],
    "sg:phone":"+32 52 46 02 27",
    "sg:postcode":"9140",
    "sg:province":"Oost-Vlaanderen",
    "sg:tags":[
        "physiotherapist"
    ],
    "wof:name":"Hofman J",
    "wof:placetype":"venue"
},
  "geometry": {"coordinates":[4.1406669617,51.1132888794],"type":"Point"}
}