{
  "type": "Feature",
  "properties": {
    "addr:full":"Paalstraat 81 Schoten Antwerpen 2900",
    "addr:housenumber":"81",
    "addr:postcode":"2900",
    "addr:street":"Paalstraat",
    "iso:country":"BE",
    "sg:address":"Paalstraat 81",
    "sg:city":"Schoten",
    "sg:classifiers":[
        {
            "category":"Real Estate",
            "subcategory":"Real Estate Services",
            "type":"Services"
        }
    ],
    "sg:phone":"+32 3 658 11 77",
    "sg:postcode":"2900",
    "sg:province":"Antwerpen",
    "wof:name":"Century 21 A.v.s.",
    "wof:placetype":"venue"
},
  "geometry": {"coordinates":[4.5010309219,51.2525672913],"type":"Point"}
}