{
  "type": "Feature",
  "properties": {
    "addr:full":"Rue Du Cimeti\u00e8re 25 Saint-georges-sur-meuse Li\u00e8ge 4470",
    "addr:housenumber":"25",
    "addr:postcode":"4470",
    "addr:street":"Rue Du Cimetie\u0300Re",
    "iso:country":"BE",
    "sg:address":"Rue Du Cimeti\u00e8re 25",
    "sg:city":"Saint-georges-sur-meuse",
    "sg:classifiers":[
        {
            "category":"Health Services",
            "subcategory":"Health Practitioner",
            "type":"Services"
        }
    ],
    "sg:phone":"+32 4 275 68 29",
    "sg:postcode":"4470",
    "sg:province":"Li\u00e8ge",
    "sg:tags":[
        "physiotherapist"
    ],
    "wof:name":"Delbrouck E",
    "wof:placetype":"venue"
},
  "geometry": {"coordinates":[5.3552269936,50.584903717],"type":"Point"}
}