{
  "type": "Feature",
  "properties": {
    "iso:country":"BE",
    "sg:address":"Chemin D'horrues 16",
    "sg:city":"Braine-le-comte",
    "sg:orig_category":"Rundveehouders",
    "sg:phone":"+32 67 55 21 26",
    "sg:postcode":"7090",
    "sg:province":"Hainaut",
    "wof:name":"Marcel Tiste",
    "wof:placetype":"venue"
},
  "geometry": {"coordinates":[4.0978732109,50.6111526489],"type":"Point"}
}