{
  "type": "Feature",
  "properties": {
    "iso:country":"BE",
    "sg:address":"Isabellakaai 0",
    "sg:city":"Gent",
    "sg:orig_category":"Kinderopvang",
    "sg:phone":"+32 9 264 71 80",
    "sg:postcode":"9000",
    "sg:province":"Oost-Vlaanderen",
    "wof:name":"Kinderdagv.soc.sector Rug",
    "wof:placetype":"venue"
},
  "geometry": {"coordinates":[3.7287700176,51.0390472412],"type":"Point"}
}