{
  "type": "Feature",
  "properties": {
    "iso:country":"BE",
    "sg:address":"Rue De Rhisnes 20",
    "sg:city":"La Bruyere",
    "sg:orig_category":"Enseignement maternel and primaire",
    "sg:phone":"+32 81 21 36 39",
    "sg:postcode":"5080",
    "sg:province":"Namur",
    "wof:name":"Ecole Fond. Communale",
    "wof:placetype":"venue"
},
  "geometry": {"coordinates":[4.8407797813,50.512512207],"type":"Point"}
}