{
  "type": "Feature",
  "properties": {
    "addr:full":"Chauss\u00e9e De Mons 1039 Bruxelles (anderlecht) Bruxelles-Capitale 1070",
    "addr:postcode":"1039;1070",
    "addr:street":"Chausse\u0301E De Mons",
    "iso:country":"BE",
    "sg:address":"Chauss\u00e9e De Mons 1039",
    "sg:city":"Bruxelles (anderlecht)",
    "sg:classifiers":[
        {
            "category":"Cafe",
            "type":"Food & Drink"
        }
    ],
    "sg:phone":"+32 2 520 14 98",
    "sg:postcode":"1070",
    "sg:province":"Bruxelles-Capitale",
    "sg:tags":[
        "snack-bars"
    ],
    "wof:name":"Grec-grill",
    "wof:placetype":"venue"
},
  "geometry": {"coordinates":[4.2966217995,50.8248786926],"type":"Point"}
}