{
  "type": "Feature",
  "properties": {
    "iso:country":"BE",
    "sg:address":"Parklaan 22",
    "sg:city":"Turnhout",
    "sg:classifiers":[
        {
            "category":"Home & Garden",
            "subcategory":"Carpets & Floor Coverings",
            "type":"Retail Goods"
        }
    ],
    "sg:phone":"+32 9 227 93 51",
    "sg:postcode":"2300",
    "sg:province":"Antwerpen",
    "sg:tags":[
        "material",
        "plastic"
    ],
    "wof:name":"Resinit Products Nv",
    "wof:placetype":"venue"
},
  "geometry": {"coordinates":[3.6736330986,51.089427948],"type":"Point"}
}