{
  "type": "Feature",
  "properties": {
    "addr:full":"Goudbergstraat 3 Zonnebeke West-Vlaanderen 8980",
    "addr:housenumber":"3",
    "addr:postcode":"8980",
    "addr:street":"Goudbergstraat",
    "iso:country":"BE",
    "sg:address":"Goudbergstraat 3",
    "sg:city":"Zonnebeke",
    "sg:orig_category":"Eleveurs de bovins",
    "sg:phone":"+32 51 77 93 66",
    "sg:postcode":"8980",
    "sg:province":"West-Vlaanderen",
    "wof:name":"Emiel Depuydt",
    "wof:placetype":"venue"
},
  "geometry": {"coordinates":[2.9872550964,50.8730812073],"type":"Point"}
}