{
  "type": "Feature",
  "properties": {
    "iso:country":"BE",
    "sg:address":"Centrumwijk 6",
    "sg:city":"Laarne (kalken)",
    "sg:classifiers":[
        {
            "category":"Banks & Credit Unions",
            "subcategory":"Bank",
            "type":"Services"
        }
    ],
    "sg:phone":"+32 9 367 71 77",
    "sg:postcode":"9270",
    "sg:province":"Oost-Vlaanderen",
    "wof:name":"Argenta",
    "wof:placetype":"venue"
},
  "geometry": {"coordinates":[3.912266016,51.0373497009],"type":"Point"}
}