{
  "type": "Feature",
  "properties": {
    "addr:full":"Alkerstraat 28 Alken Limburg 3570",
    "addr:housenumber":"28",
    "addr:postcode":"3570",
    "addr:street":"Alkerstraat",
    "iso:country":"BE",
    "sg:address":"Alkerstraat 28",
    "sg:city":"Alken",
    "sg:orig_category":"M\u00e9decins and sp\u00e9cialistes",
    "sg:phone":"+32 11 31 62 72",
    "sg:postcode":"3570",
    "sg:province":"Limburg",
    "wof:name":"Erik Buntinx",
    "wof:placetype":"venue"
},
  "geometry": {"coordinates":[5.316754818,50.8758430481],"type":"Point"}
}