{
  "type": "Feature",
  "properties": {
    "iso:country":"BE",
    "sg:address":"Nieuwwerk 1",
    "sg:city":"Mechelen",
    "sg:classifiers":[
        {
            "category":"Bars & Pubs",
            "type":"Food & Drink"
        }
    ],
    "sg:phone":"+32 15 20 70 94",
    "sg:postcode":"2800",
    "sg:province":"Antwerpen",
    "sg:tags":[
        "tavern"
    ],
    "wof:name":"Dali's",
    "wof:placetype":"venue"
},
  "geometry": {"coordinates":[4.4793710709,51.0293045044],"type":"Point"}
}