{
  "type": "Feature",
  "properties": {
    "iso:country":"BE",
    "sg:address":"Langestraat 115",
    "sg:city":"Zandhoven",
    "sg:classifiers":[
        {
            "category":"Freight",
            "type":"Transportation"
        }
    ],
    "sg:phone":"+32 3 464 11 71",
    "sg:postcode":"2240",
    "sg:province":"Antwerpen",
    "sg:tags":[
        "-",
        "refrigerated",
        "transport"
    ],
    "wof:name":"Verellen Transport Bvba",
    "wof:placetype":"venue"
},
  "geometry": {"coordinates":[4.6790399551,51.228012085],"type":"Point"}
}