{
  "type": "Feature",
  "properties": {
    "iso:country":"BE",
    "sg:address":"Brouwerijstraat 69",
    "sg:city":"Lovendegem",
    "sg:orig_category":"Binnenhuisarchitecten",
    "sg:phone":"+32 9 371 68 87",
    "sg:postcode":"9920",
    "sg:province":"Oost-Vlaanderen",
    "wof:name":"Toon De Sonville",
    "wof:placetype":"venue"
},
  "geometry": {"coordinates":[3.6110150814,51.0842895508],"type":"Point"}
}