{
  "type": "Feature",
  "properties": {
    "iso:country":"BE",
    "sg:address":"Hoogstraat 98-100",
    "sg:city":"Haaltert",
    "sg:orig_category":"Autombile concessionaires",
    "sg:phone":"+32 53 83 19 15",
    "sg:postcode":"9450",
    "sg:province":"Oost-Vlaanderen",
    "wof:name":"Gar Etienne Volckaert Nv",
    "wof:placetype":"venue"
},
  "geometry": {"coordinates":[4.0020017624,50.8969764709],"type":"Point"}
}