{
  "type": "Feature",
  "properties": {
    "iso:country":"BE",
    "sg:address":"Weststraat 47",
    "sg:city":"Jabbeke",
    "sg:orig_category":"Rundveehouders Varkenskwekers",
    "sg:phone":"+32 50 81 20 53",
    "sg:postcode":"8490",
    "sg:province":"West-Vlaanderen",
    "wof:name":"Roger De Rudder",
    "wof:placetype":"venue"
},
  "geometry": {"coordinates":[3.0817239285,51.1844978333],"type":"Point"}
}