{
  "type": "Feature",
  "properties": {
    "iso:country":"BE",
    "sg:address":"Rue Du Pont D'yves 17",
    "sg:city":"Walcourt",
    "sg:orig_category":"Artsen and specialisten",
    "sg:phone":"+32 71 65 59 52",
    "sg:postcode":"5650",
    "sg:province":"Namur",
    "wof:name":"Ghislain Noel",
    "wof:placetype":"venue"
},
  "geometry": {"coordinates":[4.493994236,50.238368988],"type":"Point"}
}