{
  "type": "Feature",
  "properties": {
    "iso:country":"BE",
    "sg:address":"Moerkerkse Steenweg 151",
    "sg:city":"Brugge (sint-kruis)",
    "sg:classifiers":[
        {
            "category":"Food & Beverages",
            "subcategory":"Groceries & Convenience Stores",
            "type":"Retail Goods"
        }
    ],
    "sg:phone":"+32 50 37 37 29",
    "sg:postcode":"8310",
    "sg:province":"West-Vlaanderen",
    "sg:tags":[
        "grocer"
    ],
    "wof:name":"Spar (de)",
    "wof:placetype":"venue"
},
  "geometry": {"coordinates":[3.2487919331,51.2136154175],"type":"Point"}
}