{
  "type": "Feature",
  "properties": {
    "iso:country":"BE",
    "sg:address":"Heistraat 202",
    "sg:city":"Sint-niklaas",
    "sg:orig_category":"Production de films, t\u00e9l\u00e9films and vid\u00e9os",
    "sg:phone":"+32 3 776 12 03",
    "sg:postcode":"9100",
    "sg:province":"Oost-Vlaanderen",
    "wof:name":"Koen Van Aken",
    "wof:placetype":"venue"
},
  "geometry": {"coordinates":[4.1388301849,51.1761131287],"type":"Point"}
}