{
  "type": "Feature",
  "properties": {
    "addr:full":"Grand'route De Mons 143 Saint-ghislain Hainaut 7334",
    "addr:housenumber":"143",
    "addr:postcode":"7334",
    "addr:street":"Grand'Route De Mons;Hainaut",
    "iso:country":"BE",
    "sg:address":"Grand'route De Mons 143",
    "sg:city":"Saint-ghislain",
    "sg:orig_category":"Benzinestations and brandstoffen",
    "sg:phone":"+32 65 62 03 43",
    "sg:postcode":"7334",
    "sg:province":"Hainaut",
    "wof:name":"Olga Kuzmic",
    "wof:placetype":"venue"
},
  "geometry": {"coordinates":[3.7702739239,50.4781265259],"type":"Point"}
}