{
  "type": "Feature",
  "properties": {
    "iso:country":"BE",
    "sg:address":"Rue Du Beau-site 10",
    "sg:city":"Messancy",
    "sg:orig_category":"Artsen and specialisten",
    "sg:phone":"+32 63 37 00 77",
    "sg:postcode":"6780",
    "sg:province":"Luxembourg",
    "wof:name":"Huguette Delforge",
    "wof:placetype":"venue"
},
  "geometry": {"coordinates":[5.8227939606,49.5950508118],"type":"Point"}
}