{
  "type": "Feature",
  "properties": {
    "addr:full":"Rue De Bouillon 17 Bievre Namur 5555",
    "addr:housenumber":"17",
    "addr:postcode":"5555",
    "addr:street":"Rue De Bouillon",
    "iso:country":"BE",
    "sg:address":"Rue De Bouillon 17",
    "sg:city":"Bievre",
    "sg:orig_category":"Pharmaciens",
    "sg:phone":"+32 61 51 14 52",
    "sg:postcode":"5555",
    "sg:province":"Namur",
    "wof:name":"Pharden",
    "wof:placetype":"venue"
},
  "geometry": {"coordinates":[5.0202550888,49.9398078918],"type":"Point"}
}