{
  "type": "Feature",
  "properties": {
    "addr:full":"Zwaluwbeekstraat 12 Kruibeke Oost-Vlaanderen 9150",
    "addr:housenumber":"12",
    "addr:postcode":"9150",
    "addr:street":"Zwaluwbeekstraat",
    "iso:country":"BE",
    "sg:address":"Zwaluwbeekstraat 12",
    "sg:city":"Kruibeke",
    "sg:classifiers":[
        {
            "category":"Manufacturing",
            "subcategory":"Wood Products",
            "type":"Manufacturing & Wholesale Goods"
        }
    ],
    "sg:phone":"+32 3 253 01 91",
    "sg:postcode":"9150",
    "sg:province":"Oost-Vlaanderen",
    "sg:tags":[
        "professional",
        "furniture"
    ],
    "wof:name":"Werkhuizen Rubbens Nv",
    "wof:placetype":"venue"
},
  "geometry": {"coordinates":[4.3152270317,51.1964874268],"type":"Point"}
}