{
  "type": "Feature",
  "properties": {
    "iso:country":"BE",
    "sg:address":"Oude Veurnestraat 11",
    "sg:city":"Ieper",
    "sg:classifiers":[
        {
            "category":"Professional",
            "subcategory":"Accounting & Tax Preparation",
            "type":"Services"
        }
    ],
    "sg:phone":"+32 57 20 78 93",
    "sg:postcode":"8900",
    "sg:province":"West-Vlaanderen",
    "sg:tags":[
        "bookkeeper"
    ],
    "wof:name":"Kestelyn J",
    "wof:placetype":"venue"
},
  "geometry": {"coordinates":[2.8765859604,50.8586540222],"type":"Point"}
}