{
  "type": "Feature",
  "properties": {
    "addr:full":"Schranshoevebaan 20 Wommelgem Antwerpen 2160",
    "addr:housenumber":"20",
    "addr:postcode":"2160",
    "addr:street":"Schranshoevebaan",
    "iso:country":"BE",
    "sg:address":"Schranshoevebaan 20",
    "sg:city":"Wommelgem",
    "sg:orig_category":"Transports routiers de marchandises",
    "sg:phone":"+32 3 353 26 60",
    "sg:postcode":"2160",
    "sg:province":"Antwerpen",
    "wof:name":"Country Line",
    "wof:placetype":"venue"
},
  "geometry": {"coordinates":[4.5101919174,51.2003326416],"type":"Point"}
}