{
  "type": "Feature",
  "properties": {
    "iso:country":"BE",
    "sg:address":"Kribbestraat 24 Box 1",
    "sg:city":"Antwerpen",
    "sg:classifiers":[
        {
            "category":"Professional",
            "subcategory":"Computer Services",
            "type":"Services"
        }
    ],
    "sg:phone":"+32 3 231 07 31",
    "sg:postcode":"2000",
    "sg:province":"Antwerpen",
    "sg:tags":[
        "-",
        "processing",
        "data",
        "software"
    ],
    "wof:name":"Tresco Engineering",
    "wof:placetype":"venue"
},
  "geometry": {"coordinates":[4.409913063,51.2300682068],"type":"Point"}
}