{
  "type": "Feature",
  "properties": {
    "iso:country":"BE",
    "sg:address":"Oude Ophoverbaan 11",
    "sg:city":"Maaseik",
    "sg:orig_category":"Woningbouw",
    "sg:phone":"+32 89 56 46 68",
    "sg:postcode":"3680",
    "sg:province":"Limburg",
    "wof:name":"Bouwwerken Paulissen",
    "wof:placetype":"venue"
},
  "geometry": {"coordinates":[5.7970519066,51.1119041443],"type":"Point"}
}