{
  "type": "Feature",
  "properties": {
    "addr:full":"Rue De La Royaut\u00c9 54 Brussel/bruxelles Bruxelles-Capitale 1020",
    "addr:housenumber":"54",
    "addr:postcode":"1020",
    "addr:street":"Rue De La Royaute\u0301;/",
    "iso:country":"BE",
    "sg:address":"Rue De La Royaut\u00c9 54",
    "sg:city":"Brussel/bruxelles",
    "sg:orig_category":"M\u00e9decins and sp\u00e9cialistes",
    "sg:phone":"+32 2 425 47 55",
    "sg:postcode":"1020",
    "sg:province":"Bruxelles-Capitale",
    "wof:name":"Didier Claude",
    "wof:placetype":"venue"
},
  "geometry": {"coordinates":[4.352191925,50.8763656616],"type":"Point"}
}