{
  "type": "Feature",
  "properties": {
    "addr:full":"Monseigneur Koningsstr. 4 Maaseik Limburg 3680",
    "addr:housenumber":"4",
    "addr:postcode":"3680",
    "addr:street":"Monseigneur Koningsstr.",
    "iso:country":"BE",
    "sg:address":"Monseigneur Koningsstr. 4",
    "sg:city":"Maaseik",
    "sg:orig_category":"Services fun\u00e9raires",
    "sg:phone":"+32 89 56 43 59",
    "sg:postcode":"3680",
    "sg:province":"Limburg",
    "wof:name":"Van Cleef",
    "wof:placetype":"venue"
},
  "geometry": {"coordinates":[5.7948350906,51.0943489075],"type":"Point"}
}