{
  "type": "Feature",
  "properties": {
    "addr:full":"Lokerhoutstraat 85 Lokeren Oost-Vlaanderen 9160",
    "addr:housenumber":"85",
    "addr:postcode":"9160",
    "addr:street":"Lokerhoutstraat",
    "iso:country":"BE",
    "sg:address":"Lokerhoutstraat 85",
    "sg:city":"Lokeren",
    "sg:orig_category":"Tabac. Journaux",
    "sg:phone":"+32 9 349 32 17",
    "sg:postcode":"9160",
    "sg:province":"Oost-Vlaanderen",
    "wof:name":"Spoele",
    "wof:placetype":"venue"
},
  "geometry": {"coordinates":[3.9957299232,51.0955543518],"type":"Point"}
}