{
  "type": "Feature",
  "properties": {
    "addr:full":"Rue Des Chapeliers 39 Verviers Li\u00e8ge 4800",
    "addr:housenumber":"39",
    "addr:postcode":"4800",
    "addr:street":"Rue Des Chapeliers",
    "iso:country":"BE",
    "sg:address":"Rue Des Chapeliers 39",
    "sg:city":"Verviers",
    "sg:orig_category":"Kunststofrecipi\u00ebnten and -verpakkingen Fab",
    "sg:phone":"+32 87 33 79 64",
    "sg:postcode":"4800",
    "sg:province":"Li\u00e8ge",
    "wof:name":"X-pack",
    "wof:placetype":"venue"
},
  "geometry": {"coordinates":[5.8594508171,50.5917663574],"type":"Point"}
}