{
  "type": "Feature",
  "properties": {
    "iso:country":"BE",
    "sg:address":"Jasmijnlaan 5",
    "sg:city":"Boortmeerbeek",
    "sg:orig_category":"Ordinateurs and \u00e9quipement informatique",
    "sg:phone":"+32 15 62 13 13",
    "sg:postcode":"3191",
    "sg:province":"Vlaams-Brabant",
    "wof:name":"Axion",
    "wof:placetype":"venue"
},
  "geometry": {"coordinates":[4.554901123,50.9925537109],"type":"Point"}
}