{
  "type": "Feature",
  "properties": {
    "iso:country":"BE",
    "sg:address":"Avenue Van Overbeke 129",
    "sg:city":"Ganshoren",
    "sg:orig_category":"Fleurs and plantes",
    "sg:phone":"+32 2 420 24 03",
    "sg:postcode":"1083",
    "sg:province":"Bruxelles-Capitale",
    "wof:name":"Les Fleurs De Nadine",
    "wof:placetype":"venue"
},
  "geometry": {"coordinates":[4.313313961,50.8720779419],"type":"Point"}
}