{
  "type": "Feature",
  "properties": {
    "iso:country":"BE",
    "sg:address":"Rue Pepin 17",
    "sg:city":"Pepinster",
    "sg:classifiers":[
        {
            "category":"Professional",
            "subcategory":"Accounting & Tax Preparation",
            "type":"Services"
        }
    ],
    "sg:phone":"+32 87 46 01 81",
    "sg:postcode":"4860",
    "sg:province":"Li\u00e8ge",
    "sg:tags":[
        "bookkeeper"
    ],
    "wof:name":"Archambeau J",
    "wof:placetype":"venue"
},
  "geometry": {"coordinates":[5.8038802147,50.5671615601],"type":"Point"}
}