{
  "type": "Feature",
  "properties": {
    "addr:full":"Parklaan 86 Sint-niklaas Oost-Vlaanderen 9100",
    "addr:housenumber":"86",
    "addr:postcode":"9100",
    "addr:street":"Parklaan",
    "iso:country":"BE",
    "sg:address":"Parklaan 86",
    "sg:city":"Sint-niklaas",
    "sg:classifiers":[
        {
            "category":"Recreation",
            "subcategory":"Amusement Park",
            "type":"Entertainment"
        }
    ],
    "sg:phone":"+32 475 31 40 48",
    "sg:postcode":"9100",
    "sg:province":"Oost-Vlaanderen",
    "sg:tags":[
        "attraction",
        "-",
        "sale",
        "fair",
        "hiring"
    ],
    "wof:name":"Kermisamusement",
    "wof:placetype":"venue"
},
  "geometry": {"coordinates":[4.1523208618,51.1581077576],"type":"Point"}
}