{
  "type": "Feature",
  "properties": {
    "addr:full":"Chauss\u00c9e De Renaix 41 Frasnes-lez-anvaing Hainaut 7910",
    "addr:housenumber":"41",
    "addr:postcode":"7910",
    "addr:street":"Chausse\u0301E De Renaix",
    "iso:country":"BE",
    "sg:address":"Chauss\u00c9e De Renaix 41",
    "sg:city":"Frasnes-lez-anvaing",
    "sg:orig_category":"Charpentes and couvertures",
    "sg:phone":"+32 69 86 86 11",
    "sg:postcode":"7910",
    "sg:province":"Hainaut",
    "wof:name":"Rudy Boccauw",
    "wof:placetype":"venue"
},
  "geometry": {"coordinates":[3.5807249546,50.6912765503],"type":"Point"}
}