{
  "type": "Feature",
  "properties": {
    "addr:full":"Neerheide 91 Destelbergen (heusden) Oost-Vlaanderen 9070",
    "addr:housenumber":"91",
    "addr:postcode":"9070",
    "addr:street":"Neerheide",
    "iso:country":"BE",
    "sg:address":"Neerheide 91",
    "sg:city":"Destelbergen (heusden)",
    "sg:classifiers":[
        {
            "category":"Building & Trades",
            "subcategory":"Electrical",
            "type":"Services"
        }
    ],
    "sg:phone":"+32 9 231 12 80",
    "sg:postcode":"9070",
    "sg:province":"Oost-Vlaanderen",
    "sg:tags":[
        "electric",
        "-",
        "housewiring",
        "contractor"
    ],
    "wof:name":"Schulte P",
    "wof:placetype":"venue"
},
  "geometry": {"coordinates":[3.808259964,51.0248985291],"type":"Point"}
}