{
  "type": "Feature",
  "properties": {
    "iso:country":"BE",
    "sg:address":"De Froyennes",
    "sg:city":"Doornik",
    "sg:orig_category":"Meubelzaken, woning- and keukeninrichting",
    "sg:phone":"+32 69 84 15 83",
    "sg:postcode":"7503",
    "sg:province":"Hainaut",
    "wof:name":"Crusoe",
    "wof:placetype":"venue"
},
  "geometry": {"coordinates":[3.3540999889,50.6210441589],"type":"Point"}
}