{
  "type": "Feature",
  "properties": {
    "iso:country":"BE",
    "sg:address":"Rue Des Combattants 30",
    "sg:city":"Fernelmont",
    "sg:orig_category":"Pain, p\u00e2tisseries and confiseries",
    "sg:phone":"+32 81 83 31 60",
    "sg:postcode":"5380",
    "sg:province":"Namur",
    "wof:name":"P\u00c2tisserie Tilman P. & B.",
    "wof:placetype":"venue"
},
  "geometry": {"coordinates":[4.9862270355,50.5560112],"type":"Point"}
}