{
  "type": "Feature",
  "properties": {
    "iso:country":"BE",
    "sg:address":"Hoogstraat 5",
    "sg:city":"Zaventem",
    "sg:classifiers":[
        {
            "category":"Organizations",
            "subcategory":"Community Association",
            "type":"Services"
        }
    ],
    "sg:phone":"+32 2 721 96 75",
    "sg:postcode":"1930",
    "sg:province":"Vlaams-Brabant",
    "sg:tags":[
        "organisation"
    ],
    "wof:name":"Jeugdhuis Yucca",
    "wof:placetype":"venue"
},
  "geometry": {"coordinates":[4.4774389267,50.8828315735],"type":"Point"}
}