{
  "type": "Feature",
  "properties": {
    "iso:country":"BE",
    "sg:address":"Rue Emile Cuvelier 58",
    "sg:city":"Namur",
    "sg:classifiers":[
        {
            "category":"Utilities",
            "subcategory":"Mobile Phone",
            "type":"Services"
        }
    ],
    "sg:phone":"+32 81 26 22 42",
    "sg:postcode":"5000",
    "sg:province":"Namur",
    "sg:tags":[
        "access",
        "gsm",
        "-",
        "apparatus"
    ],
    "wof:name":"Point G",
    "wof:placetype":"venue"
},
  "geometry": {"coordinates":[4.8652729988,50.4650115967],"type":"Point"}
}