{
  "type": "Feature",
  "properties": {
    "addr:full":"Clinique Sainte-anne Dinant Namur 5500",
    "addr:postcode":"5500",
    "addr:street":"Clinique;Namur",
    "iso:country":"BE",
    "sg:address":"Clinique Sainte-anne",
    "sg:city":"Dinant",
    "sg:classifiers":[
        {
            "category":"Health Services",
            "subcategory":"Doctor",
            "type":"Services"
        }
    ],
    "sg:phone":"+32 82 21 24 31",
    "sg:postcode":"5500",
    "sg:province":"Namur",
    "sg:tags":[
        "medicinephysicians",
        "surgeon"
    ],
    "wof:name":"Marquet Th\u00e9r\u00e8se",
    "wof:placetype":"venue"
},
  "geometry": {"coordinates":[4.9160461426,50.2566947937],"type":"Point"}
}