{
  "type": "Feature",
  "properties": {
    "iso:country":"BE",
    "sg:address":"Kerselaarlaan 25",
    "sg:city":"Willebroek",
    "sg:orig_category":"Pleisterwerk",
    "sg:phone":"+32 3 886 17 20",
    "sg:postcode":"2830",
    "sg:province":"Antwerpen",
    "wof:name":"Ronald Ardies",
    "wof:placetype":"venue"
},
  "geometry": {"coordinates":[4.4058599472,51.0688247681],"type":"Point"}
}