{
  "type": "Feature",
  "properties": {
    "addr:full":"Sportlaan 19 Beveren Oost-Vlaanderen 9120",
    "addr:housenumber":"19",
    "addr:postcode":"9120",
    "addr:street":"Sportlaan",
    "iso:country":"BE",
    "sg:address":"Sportlaan 19",
    "sg:city":"Beveren",
    "sg:orig_category":"Zuivelproducten",
    "sg:phone":"+32 3 775 81 75",
    "sg:postcode":"9120",
    "sg:province":"Oost-Vlaanderen",
    "wof:name":"Alfons Van Noten",
    "wof:placetype":"venue"
},
  "geometry": {"coordinates":[4.1921339035,51.220500946],"type":"Point"}
}