{
  "type": "Feature",
  "properties": {
    "addr:full":"Rue De L'imprimerie 11-13 Quaregnon Hainaut 7390",
    "addr:housenumber":"11-13",
    "addr:postcode":"7390",
    "addr:street":"Rue De L'Imprimerie",
    "iso:country":"BE",
    "sg:address":"Rue De L'imprimerie 11-13",
    "sg:city":"Quaregnon",
    "sg:orig_category":"Imprimeries and copyshops",
    "sg:phone":"+32 65 78 30 35",
    "sg:postcode":"7390",
    "sg:province":"Hainaut",
    "wof:name":"Cocu Et Mairesse",
    "wof:placetype":"venue"
},
  "geometry": {"coordinates":[3.8650140762,50.4313049316],"type":"Point"}
}