{
  "type": "Feature",
  "properties": {
    "iso:country":"BE",
    "sg:address":"Smeetshofweg 49",
    "sg:city":"Peer (grote Brogel)",
    "sg:classifiers":[
        {
            "category":"Autos & Motor Vehicles",
            "subcategory":"Automobile Sales",
            "type":"Retail Goods"
        }
    ],
    "sg:phone":"+32 11 63 70 37",
    "sg:postcode":"3990",
    "sg:province":"Limburg",
    "sg:tags":[
        "car",
        "used",
        "-"
    ],
    "wof:name":"P.r.s.",
    "wof:placetype":"venue"
},
  "geometry": {"coordinates":[5.4956860542,51.148601532],"type":"Point"}
}