{
  "type": "Feature",
  "properties": {
    "addr:full":"Oud Strijdersplein 4 Ninove Oost-Vlaanderen 9400",
    "addr:housenumber":"4",
    "addr:postcode":"9400",
    "addr:street":"Oud Strijdersplein",
    "iso:country":"BE",
    "sg:address":"Oud Strijdersplein 4",
    "sg:city":"Ninove",
    "sg:orig_category":"Mat\u00e9riel de T\u00e9l\u00e9communication",
    "sg:phone":"+32 54 33 98 16",
    "sg:postcode":"9400",
    "sg:province":"Oost-Vlaanderen",
    "wof:name":"Sound Center",
    "wof:placetype":"venue"
},
  "geometry": {"coordinates":[4.0228238106,50.8349647522],"type":"Point"}
}