{
  "type": "Feature",
  "properties": {
    "iso:country":"BE",
    "sg:address":"Rue Burette 4",
    "sg:city":"Crisnee",
    "sg:orig_category":"M\u00e9decins and sp\u00e9cialistes",
    "sg:phone":"+32 4 257 43 96",
    "sg:postcode":"4367",
    "sg:province":"Li\u00e8ge",
    "wof:name":"Jean-marie Lamboray",
    "wof:placetype":"venue"
},
  "geometry": {"coordinates":[5.3967180252,50.7034416199],"type":"Point"}
}