{
  "type": "Feature",
  "properties": {
    "iso:country":"BE",
    "sg:address":"Rue De La Fourrag\u00e8re 5",
    "sg:city":"Bruxelles (uccle)",
    "sg:classifiers":[
        {
            "category":"Cafe",
            "type":"Food & Drink"
        }
    ],
    "sg:phone":"+32 2 345 24 30",
    "sg:postcode":"1180",
    "sg:province":"Bruxelles-Capitale",
    "sg:tags":[
        "snack-bars"
    ],
    "wof:name":"Mon Jardin Rose",
    "wof:placetype":"venue"
},
  "geometry": {"coordinates":[4.3379859924,50.8013267517],"type":"Point"}
}