{
  "type": "Feature",
  "properties": {
    "iso:country":"BE",
    "sg:address":"Rue De La Fronti\u00c8re 39",
    "sg:city":"Quievrain",
    "sg:orig_category":"Bouwmaterialen Gh Gespecialiseerde niet-residenti\u00eble bouw",
    "sg:phone":"+32 65 43 11 53",
    "sg:postcode":"7380",
    "sg:province":"Hainaut",
    "wof:name":"E.b.m.",
    "wof:placetype":"venue"
},
  "geometry": {"coordinates":[3.6747360229,50.4048843384],"type":"Point"}
}