{
  "type": "Feature",
  "properties": {
    "addr:full":"Rue Joseph Wauters 79 Saint-georges-sur-meuse Li\u00e8ge 4470",
    "addr:housenumber":"79",
    "addr:postcode":"4470",
    "addr:street":"Rue Joseph Wauters",
    "iso:country":"BE",
    "sg:address":"Rue Joseph Wauters 79",
    "sg:city":"Saint-georges-sur-meuse",
    "sg:orig_category":"Koerierbedrijven",
    "sg:phone":"+32 4 275 08 94",
    "sg:postcode":"4470",
    "sg:province":"Li\u00e8ge",
    "wof:name":"Transport T.e. Delaet",
    "wof:placetype":"venue"
},
  "geometry": {"coordinates":[5.3610072136,50.5784721375],"type":"Point"}
}