{
  "type": "Feature",
  "properties": {
    "iso:country":"BE",
    "sg:address":"Sint-maartenplein 29",
    "sg:city":"Hasselt",
    "sg:orig_category":"V\u00eatements pour b\u00e9b\u00e9s and enfants",
    "sg:phone":"+32 11 59 33 41",
    "sg:postcode":"3512",
    "sg:province":"Limburg",
    "wof:name":"Duimelotje",
    "wof:placetype":"venue"
},
  "geometry": {"coordinates":[5.2481999397,50.9169540405],"type":"Point"}
}