{
  "type": "Feature",
  "properties": {
    "addr:full":"Bergifa 19 Lierneux Li\u00e8ge 4990",
    "addr:housenumber":"19",
    "addr:postcode":"4990",
    "addr:street":"Bergifa",
    "iso:country":"BE",
    "sg:address":"Bergifa 19",
    "sg:city":"Lierneux",
    "sg:orig_category":"Travail and traitement du bois",
    "sg:phone":"+32 80 31 99 78",
    "sg:postcode":"4990",
    "sg:province":"Li\u00e8ge",
    "wof:name":"Fe. Jamoye Fils",
    "wof:placetype":"venue"
},
  "geometry": {"coordinates":[5.7599692345,50.3300819397],"type":"Point"}
}