{
  "type": "Feature",
  "properties": {
    "iso:country":"BE",
    "sg:address":"Katrienwiel 2",
    "sg:city":"Kuurne",
    "sg:classifiers":[
        {
            "category":"Health Services",
            "subcategory":"Doctor",
            "type":"Services"
        }
    ],
    "sg:phone":"+32 56 35 39 44",
    "sg:postcode":"8520",
    "sg:province":"West-Vlaanderen",
    "sg:tags":[
        "medicinephysicians",
        "surgeon"
    ],
    "wof:name":"Maes Lieven",
    "wof:placetype":"venue"
},
  "geometry": {"coordinates":[3.243516922,50.8694038391],"type":"Point"}
}