{
  "type": "Feature",
  "properties": {
    "iso:country":"BE",
    "sg:address":"Rue De La Gare 57",
    "sg:city":"Erquelinnes (solre-sur-sambre)",
    "sg:classifiers":[
        {
            "category":"Health Services",
            "subcategory":"Health Practitioner",
            "type":"Services"
        }
    ],
    "sg:phone":"+32 71 55 53 42",
    "sg:postcode":"6560",
    "sg:province":"Hainaut",
    "sg:tags":[
        "physiotherapist"
    ],
    "wof:name":"Bertani P",
    "wof:placetype":"venue"
},
  "geometry": {"coordinates":[4.1594491005,50.3184814453],"type":"Point"}
}