{
  "type": "Feature",
  "properties": {
    "addr:full":"Bokslaarstraat 5 Lokeren Oost-Vlaanderen 9160",
    "addr:housenumber":"5",
    "addr:postcode":"9160",
    "addr:street":"Bokslaarstraat",
    "iso:country":"BE",
    "sg:address":"Bokslaarstraat 5",
    "sg:city":"Lokeren",
    "sg:orig_category":"Eleveurs de bovins",
    "sg:phone":"+32 9 349 14 78",
    "sg:postcode":"9160",
    "sg:province":"Oost-Vlaanderen",
    "wof:name":"Jean Wulteputte",
    "wof:placetype":"venue"
},
  "geometry": {"coordinates":[4.007130146,51.0889015198],"type":"Point"}
}