{
  "type": "Feature",
  "properties": {
    "iso:country":"BE",
    "sg:address":"Zwaluwenlaan 71",
    "sg:city":"Antwerpen",
    "sg:orig_category":"Fotografen and fotostudio's",
    "sg:phone":"+32 3 449 77 24",
    "sg:postcode":"2610",
    "sg:province":"Antwerpen",
    "wof:name":"Michael Dehaspe",
    "wof:placetype":"venue"
},
  "geometry": {"coordinates":[4.4166398048,51.1712417603],"type":"Point"}
}