{
  "type": "Feature",
  "properties": {
    "iso:country":"BE",
    "sg:address":"Grote Baan 12",
    "sg:city":"Houthalen-helchteren",
    "sg:orig_category":"Syst\u00e8mes de t\u00e9l\u00e9communications. Mat\u00e9riel de T\u00e9l\u00e9communication",
    "sg:phone":"+32 11 60 10 05",
    "sg:postcode":"3530",
    "sg:province":"Limburg",
    "wof:name":"Telecom Gijsen",
    "wof:placetype":"venue"
},
  "geometry": {"coordinates":[5.3739228249,51.0200080872],"type":"Point"}
}