{
  "type": "Feature",
  "properties": {
    "addr:full":"Spreeuwstraat 1ba Kalmthout Antwerpen 2920",
    "addr:housenumber":"1ba",
    "addr:postcode":"2920",
    "addr:street":"Spreeuwstraat",
    "iso:country":"BE",
    "sg:address":"Spreeuwstraat 1ba",
    "sg:city":"Kalmthout",
    "sg:orig_category":"Woningbouw",
    "sg:phone":"+32 3 667 55 66",
    "sg:postcode":"2920",
    "sg:province":"Antwerpen",
    "wof:name":"Joannes Elst",
    "wof:placetype":"venue"
},
  "geometry": {"coordinates":[4.5252838135,51.4292755127],"type":"Point"}
}