{
  "type": "Feature",
  "properties": {
    "addr:full":"Voormuide 45 Gent Oost-Vlaanderen 9000",
    "addr:housenumber":"45",
    "addr:postcode":"9000",
    "addr:street":"Voormuide;Oost-Vlaanderen",
    "iso:country":"BE",
    "sg:address":"Voormuide 45",
    "sg:city":"Gent",
    "sg:orig_category":"Sportclubs",
    "sg:phone":"+32 9 224 32 02",
    "sg:postcode":"9000",
    "sg:province":"Oost-Vlaanderen",
    "wof:name":"Union Et Libert\u00c9",
    "wof:placetype":"venue"
},
  "geometry": {"coordinates":[3.7293460369,51.0684967041],"type":"Point"}
}