{
  "type": "Feature",
  "properties": {
    "iso:country":"BE",
    "sg:address":"Binnenweg 3",
    "sg:city":"Heist-op-den-berg",
    "sg:orig_category":"Verplichte sociale verzekeringen",
    "sg:phone":"+32 15 24 11 44",
    "sg:postcode":"2220",
    "sg:province":"Antwerpen",
    "wof:name":"Socialist. Mutualiteit",
    "wof:placetype":"venue"
},
  "geometry": {"coordinates":[4.7246789932,51.0761413574],"type":"Point"}
}