{
  "type": "Feature",
  "properties": {
    "iso:country":"BE",
    "sg:address":"Berendonk 72",
    "sg:city":"Arendonk",
    "sg:orig_category":"Afvalophaling and -verwerking industrie, landbouw and bouwpuin",
    "sg:phone":"+32 14 67 10 71",
    "sg:postcode":"2370",
    "sg:province":"Antwerpen",
    "wof:name":"Ecosol",
    "wof:placetype":"venue"
},
  "geometry": {"coordinates":[5.1086201668,51.304397583],"type":"Point"}
}