{
  "type": "Feature",
  "properties": {
    "addr:full":"Chauss\u00e9e De Charleroi 13a Jemeppe-sur-sambre Namur 5190",
    "addr:housenumber":"13a",
    "addr:postcode":"5190",
    "addr:street":"Chausse\u0301E De Charleroi",
    "iso:country":"BE",
    "sg:address":"Chauss\u00e9e De Charleroi 13a",
    "sg:city":"Jemeppe-sur-sambre",
    "sg:classifiers":[
        {
            "category":"Health Services",
            "subcategory":"Health Practitioner",
            "type":"Services"
        }
    ],
    "sg:phone":"+32 71 74 44 07",
    "sg:postcode":"5190",
    "sg:province":"Namur",
    "sg:tags":[
        "therapist",
        "speech"
    ],
    "wof:name":"Grosfils E",
    "wof:placetype":"venue"
},
  "geometry": {"coordinates":[4.6450161934,50.456161499],"type":"Point"}
}