{
  "type": "Feature",
  "properties": {
    "iso:country":"BE",
    "sg:address":"Slakweidestraat 31",
    "sg:city":"Maasmechelen",
    "sg:orig_category":"Air Texturing Machines",
    "sg:phone":"+32 89 77 07 00",
    "sg:postcode":"3630",
    "sg:province":"Limburg",
    "wof:name":"Graco Nv",
    "wof:placetype":"venue"
},
  "geometry": {"coordinates":[5.7026400566,50.952381134],"type":"Point"}
}