{
  "type": "Feature",
  "properties": {
    "addr:full":"Borgval 3 Bruxelles Bruxelles-Capitale 1000",
    "addr:housenumber":"3",
    "addr:postcode":"1000",
    "addr:street":"Borgval",
    "iso:country":"BE",
    "sg:address":"Borgval 3",
    "sg:city":"Bruxelles",
    "sg:classifiers":[
        {
            "category":"Professional",
            "subcategory":"Employment Agencies",
            "type":"Services"
        }
    ],
    "sg:phone":"+32 2 513 41 13",
    "sg:postcode":"1000",
    "sg:province":"Bruxelles-Capitale",
    "sg:tags":[
        "model",
        "modelling"
    ],
    "wof:name":"Bette V",
    "wof:placetype":"venue"
},
  "geometry": {"coordinates":[4.3485879898,50.8475875854],"type":"Point"}
}