{
  "type": "Feature",
  "properties": {
    "iso:country":"BE",
    "sg:address":"Avenue De Longwy 423",
    "sg:city":"Arlon",
    "sg:orig_category":"Installatie van houten of kunststof schrijnwerk Installatie van metalen schrijnwerk",
    "sg:phone":"+32 63 21 66 44",
    "sg:postcode":"6700",
    "sg:province":"Luxembourg",
    "wof:name":"Fe. Pierret",
    "wof:placetype":"venue"
},
  "geometry": {"coordinates":[5.8241500854,49.6712188721],"type":"Point"}
}