{
  "type": "Feature",
  "properties": {
    "addr:full":"Onze-lieve-vrouwestraat 139 Mechelen Antwerpen 2800",
    "addr:housenumber":"139",
    "addr:postcode":"2800",
    "addr:street":"Onze-Lieve-Vrouwestraat",
    "iso:country":"BE",
    "sg:address":"Onze-lieve-vrouwestraat 139",
    "sg:city":"Mechelen",
    "sg:orig_category":"Editeurs de livres",
    "sg:phone":"+32 15 43 35 57",
    "sg:postcode":"2800",
    "sg:province":"Antwerpen",
    "wof:name":"Music Corner",
    "wof:placetype":"venue"
},
  "geometry": {"coordinates":[4.4819121361,51.0226211548],"type":"Point"}
}