{
  "type": "Feature",
  "properties": {
    "iso:country":"BE",
    "sg:address":"Rue De Bruxelles 7",
    "sg:city":"Mouscron",
    "sg:classifiers":[
        {
            "category":"Bakery",
            "type":"Food & Drink"
        }
    ],
    "sg:phone":"+32 56 34 53 64",
    "sg:postcode":"7700",
    "sg:province":"Hainaut",
    "sg:tags":[
        "confectioner",
        "baker"
    ],
    "wof:name":"Mapat",
    "wof:placetype":"venue"
},
  "geometry": {"coordinates":[3.2122890949,50.744682312],"type":"Point"}
}