{
  "type": "Feature",
  "properties": {
    "addr:full":"8600 Diksmuide (groot) West-Vlaanderen 8600",
    "addr:postcode":"8600;8600",
    "addr:street":"Groot West-Vlaanderen",
    "iso:country":"BE",
    "sg:address":"8600",
    "sg:city":"Diksmuide (groot)",
    "sg:orig_category":"Pharmaciens",
    "sg:phone":"+32 900 10 500",
    "sg:postcode":"8600",
    "sg:province":"West-Vlaanderen",
    "wof:name":"Pharmacies De Garde",
    "wof:placetype":"venue"
},
  "geometry": {"coordinates":[2.8657801151,51.0334663391],"type":"Point"}
}