{
  "type": "Feature",
  "properties": {
    "iso:country":"BE",
    "sg:address":"Pullesebaan 9",
    "sg:city":"Vorselaar",
    "sg:orig_category":"Cad/Cam systems",
    "sg:phone":"+32 14 50 10 07",
    "sg:postcode":"2290",
    "sg:province":"Antwerpen",
    "wof:name":"Moortgat Bvba",
    "wof:placetype":"venue"
},
  "geometry": {"coordinates":[4.7561898232,51.2030181885],"type":"Point"}
}