{
  "type": "Feature",
  "properties": {
    "addr:full":"Graaf Witgerstraat 30 Mortsel Antwerpen 2640",
    "addr:housenumber":"30",
    "addr:postcode":"2640",
    "addr:street":"Graaf Witgerstraat",
    "iso:country":"BE",
    "sg:address":"Graaf Witgerstraat 30",
    "sg:city":"Mortsel",
    "sg:classifiers":[
        {
            "category":"Arena",
            "subcategory":"Sports Club",
            "type":"Entertainment"
        }
    ],
    "sg:phone":"+32 3 440 08 30",
    "sg:postcode":"2640",
    "sg:province":"Antwerpen",
    "sg:tags":[
        "de"
    ],
    "wof:name":"T.c. Cantincrode",
    "wof:placetype":"venue"
},
  "geometry": {"coordinates":[4.4550261497,51.1786689758],"type":"Point"}
}