{
  "type": "Feature",
  "properties": {
    "iso:country":"BE",
    "sg:address":"Lambertusstraat 165",
    "sg:city":"Borgloon",
    "sg:orig_category":"Epiceries",
    "sg:phone":"+32 12 74 18 06",
    "sg:postcode":"3840",
    "sg:province":"Limburg",
    "wof:name":"P. Baldewijns",
    "wof:placetype":"venue"
},
  "geometry": {"coordinates":[5.3290491104,50.7983360291],"type":"Point"}
}