{
  "type": "Feature",
  "properties": {
    "iso:country":"BE",
    "sg:address":"Avenue Louise 223",
    "sg:city":"Bruxelles (ixelles)",
    "sg:classifiers":[
        {
            "category":"Real Estate",
            "subcategory":"Developer",
            "type":"Services"
        }
    ],
    "sg:phone":"+32 2 648 08 06",
    "sg:postcode":"1050",
    "sg:province":"Bruxelles-Capitale",
    "sg:tags":[
        "project"
    ],
    "wof:name":"B E A G Sa",
    "wof:placetype":"venue"
},
  "geometry": {"coordinates":[4.3648080826,50.8257789612],"type":"Point"}
}