{
  "type": "Feature",
  "properties": {
    "addr:full":"Avenue C\u00c9sar Snoeck 30 Renaix Oost-Vlaanderen 9600",
    "addr:housenumber":"30",
    "addr:postcode":"9600",
    "addr:street":"Avenue Ce\u0301Sar Snoeck",
    "iso:country":"BE",
    "sg:address":"Avenue C\u00c9sar Snoeck 30",
    "sg:city":"Renaix",
    "sg:orig_category":"Kaardwolvezels Fab Wolweefsels Fab",
    "sg:phone":"+32 55 23 12 11",
    "sg:postcode":"9600",
    "sg:province":"Oost-Vlaanderen",
    "wof:name":"Utexbel",
    "wof:placetype":"venue"
},
  "geometry": {"coordinates":[3.5862250328,50.7471237183],"type":"Point"}
}