{
  "type": "Feature",
  "properties": {
    "iso:country":"BE",
    "sg:address":"Zuidlaan 238-175",
    "sg:city":"Zwalm (munkzwalm)",
    "sg:classifiers":[
        {
            "category":"Manufacturing",
            "subcategory":"Pottery",
            "type":"Manufacturing & Wholesale Goods"
        }
    ],
    "sg:phone":"+32 55 49 90 30",
    "sg:postcode":"9630",
    "sg:province":"Oost-Vlaanderen",
    "sg:tags":[
        "facing",
        "brick"
    ],
    "wof:name":"Steenbakkerij Van Roborst Nv",
    "wof:placetype":"venue"
},
  "geometry": {"coordinates":[3.7376670837,50.8590240479],"type":"Point"}
}