{
  "type": "Feature",
  "properties": {
    "addr:full":"Kerkplaats 29 Wommelgem Antwerpen 2160",
    "addr:housenumber":"29",
    "addr:postcode":"2160",
    "addr:street":"Kerkplaats",
    "iso:country":"BE",
    "sg:address":"Kerkplaats 29",
    "sg:city":"Wommelgem",
    "sg:classifiers":[
        {
            "category":"Government",
            "subcategory":"Police Station",
            "type":"Public Place"
        }
    ],
    "sg:phone":"+32 3 355 12 70",
    "sg:postcode":"2160",
    "sg:province":"Antwerpen",
    "sg:tags":[
        "gendarmerie"
    ],
    "wof:name":"Federale Politie",
    "wof:placetype":"venue"
},
  "geometry": {"coordinates":[4.5229458809,51.2037277222],"type":"Point"}
}