{
  "type": "Feature",
  "properties": {
    "addr:full":"Rue Colonel Bourg 4 Schaarbeek/schaerbeek Bruxelles-Capitale 1030",
    "addr:housenumber":"4",
    "addr:postcode":"1030",
    "addr:street":"Rue Colonel Bourg",
    "iso:country":"BE",
    "sg:address":"Rue Colonel Bourg 4",
    "sg:city":"Schaarbeek/schaerbeek",
    "sg:orig_category":"Enregistrements sonores",
    "sg:phone":"+32 2 705 10 56",
    "sg:postcode":"1030",
    "sg:province":"Bruxelles-Capitale",
    "wof:name":"Studio Silence Music",
    "wof:placetype":"venue"
},
  "geometry": {"coordinates":[4.4039859772,50.8512954712],"type":"Point"}
}