{
  "type": "Feature",
  "properties": {
    "addr:full":"Zuidlaan 124 Wetteren (groot) Oost-Vlaanderen 9230",
    "addr:housenumber":"124",
    "addr:postcode":"9230",
    "addr:street":"Zuidlaan;Groot Oost-Vlaanderen",
    "iso:country":"BE",
    "sg:address":"Zuidlaan 124",
    "sg:city":"Wetteren (groot)",
    "sg:orig_category":"Baby- and kinderkleding Dameskledingzaken Herenkledingzaken",
    "sg:phone":"+32 9 369 58 90",
    "sg:postcode":"9230",
    "sg:province":"Oost-Vlaanderen",
    "wof:name":"E5 Mode",
    "wof:placetype":"venue"
},
  "geometry": {"coordinates":[3.8814818859,50.9988746643],"type":"Point"}
}