{
  "type": "Feature",
  "properties": {
    "iso:country":"BE",
    "sg:address":"Rue Du Petit Bois 75",
    "sg:city":"Namur",
    "sg:orig_category":"Architecten",
    "sg:phone":"+32 81 44 59 21",
    "sg:postcode":"5020",
    "sg:province":"Namur",
    "wof:name":"Marie-no\u00cblle Meessen",
    "wof:placetype":"venue"
},
  "geometry": {"coordinates":[4.8009228706,50.4216461182],"type":"Point"}
}