{
  "type": "Feature",
  "properties": {
    "addr:full":"Avenue Jean Tast\u00c9 Verviers Li\u00e8ge 4802",
    "addr:postcode":"4802",
    "addr:street":"Avenue Jean Taste\u0301",
    "iso:country":"BE",
    "sg:address":"Avenue Jean Tast\u00c9",
    "sg:city":"Verviers",
    "sg:classifiers":[
        {
            "category":"Organizations",
            "subcategory":"Community Association",
            "type":"Services"
        }
    ],
    "sg:phone":"+32 87 22 96 57",
    "sg:postcode":"4802",
    "sg:province":"Li\u00e8ge",
    "sg:tags":[
        "organisation"
    ],
    "wof:name":"Associations De Protection De La Nature",
    "wof:placetype":"venue"
},
  "geometry": {"coordinates":[5.8804149628,50.5841217041],"type":"Point"}
}