{
  "type": "Feature",
  "properties": {
    "iso:country":"BE",
    "sg:address":"Willem Pantinlaan 1",
    "sg:city":"Tielt",
    "sg:orig_category":"Advocaten and juridische adviseurs",
    "sg:phone":"+32 51 40 83 85",
    "sg:postcode":"8700",
    "sg:province":"West-Vlaanderen",
    "wof:name":"Piet Rotsaert",
    "wof:placetype":"venue"
},
  "geometry": {"coordinates":[3.3313729763,50.99451828],"type":"Point"}
}