{
  "type": "Feature",
  "properties": {
    "iso:country":"BE",
    "sg:address":"Rue Verbist 30",
    "sg:city":"Sint-joost-ten-node/saint-josse-ten-noode",
    "sg:orig_category":"Boucheries",
    "sg:phone":"+32 2 219 04 19",
    "sg:postcode":"1210",
    "sg:province":"Bruxelles-Capitale",
    "wof:name":"Boucherie Chafaoui",
    "wof:placetype":"venue"
},
  "geometry": {"coordinates":[4.3766407967,50.8505477905],"type":"Point"}
}