{
  "type": "Feature",
  "properties": {
    "iso:country":"BE",
    "sg:address":"Bocholter Kiezel 76",
    "sg:city":"Bree",
    "sg:orig_category":"Drukkerijen and copyshops Papierwaren",
    "sg:phone":"+32 89 46 30 79",
    "sg:postcode":"3960",
    "sg:province":"Limburg",
    "wof:name":"Beerendruk",
    "wof:placetype":"venue"
},
  "geometry": {"coordinates":[5.5947399139,51.1489295959],"type":"Point"}
}