{
  "type": "Feature",
  "properties": {
    "addr:full":"Rue D'hubinne 1ba Hamois Namur 5360",
    "addr:housenumber":"1ba",
    "addr:postcode":"5360",
    "addr:street":"Rue D'Hubinne",
    "iso:country":"BE",
    "sg:address":"Rue D'hubinne 1ba",
    "sg:city":"Hamois",
    "sg:orig_category":"Enseignement maternel and primaire",
    "sg:phone":"+32 83 61 21 42",
    "sg:postcode":"5360",
    "sg:province":"Namur",
    "wof:name":"Ecole Fond. Communale",
    "wof:placetype":"venue"
},
  "geometry": {"coordinates":[5.1692237854,50.3396339417],"type":"Point"}
}