{
  "type": "Feature",
  "properties": {
    "addr:full":"Roomstraat 48 Lokeren Oost-Vlaanderen 9160",
    "addr:housenumber":"48",
    "addr:postcode":"9160",
    "addr:street":"Roomstraat",
    "iso:country":"BE",
    "sg:address":"Roomstraat 48",
    "sg:city":"Lokeren",
    "sg:orig_category":"Catering and organisatie van feesten Kruideniers Voedingsspeciaalzaken",
    "sg:phone":"+32 9 348 41 18",
    "sg:postcode":"9160",
    "sg:province":"Oost-Vlaanderen",
    "wof:name":"Traiteur De Gr\u00c8ve",
    "wof:placetype":"venue"
},
  "geometry": {"coordinates":[3.9881839752,51.1032981873],"type":"Point"}
}