{
  "type": "Feature",
  "properties": {
    "iso:country":"BE",
    "sg:address":"Rue Hov\u00e9mont 120",
    "sg:city":"Theux",
    "sg:orig_category":"Non-Classified Establishments",
    "sg:phone":"+32 87 54 21 11",
    "sg:postcode":"4910",
    "sg:province":"Li\u00e8ge",
    "wof:name":"Rm Distribution",
    "wof:placetype":"venue"
},
  "geometry": {"coordinates":[5.8152418137,50.5325393677],"type":"Point"}
}