{
  "type": "Feature",
  "properties": {
    "iso:country":"BE",
    "sg:address":"Koolstraat 2b1",
    "sg:city":"Mechelen",
    "sg:orig_category":"Instituts de beaut\u00e9",
    "sg:phone":"+32 15 26 09 26",
    "sg:postcode":"2800",
    "sg:province":"Antwerpen",
    "wof:name":"Instituut Prestige",
    "wof:placetype":"venue"
},
  "geometry": {"coordinates":[4.4643602371,51.0281105042],"type":"Point"}
}