{
  "type": "Feature",
  "properties": {
    "addr:full":"Alsembergse Steenweg 1152 Ukkel/uccle Bruxelles-Capitale 1180",
    "addr:postcode":"1152;1180",
    "addr:street":"Alsembergse Steenweg",
    "iso:country":"BE",
    "sg:address":"Alsembergse Steenweg 1152",
    "sg:city":"Ukkel/uccle",
    "sg:classifiers":[
        {
            "category":"Cafe",
            "type":"Food & Drink"
        }
    ],
    "sg:phone":"+32 2 332 01 23",
    "sg:postcode":"1180",
    "sg:province":"Bruxelles-Capitale",
    "sg:tags":[
        "caf\u00e9s"
    ],
    "wof:name":"Le Bistrot",
    "wof:placetype":"venue"
},
  "geometry": {"coordinates":[4.3298487663,50.7870101929],"type":"Point"}
}