{
  "type": "Feature",
  "properties": {
    "addr:full":"Dronckaertstraat 232 Menen West-Vlaanderen 8930",
    "addr:housenumber":"232",
    "addr:postcode":"8930",
    "addr:street":"Dronckaertstraat",
    "iso:country":"BE",
    "sg:address":"Dronckaertstraat 232",
    "sg:city":"Menen",
    "sg:orig_category":"D\u00e9corateurs d'int\u00e9rieur. Installation de menuiserie m\u00e9tallique",
    "sg:phone":"+32 56 42 19 39",
    "sg:postcode":"8930",
    "sg:province":"West-Vlaanderen",
    "wof:name":"Frank Van Raes",
    "wof:placetype":"venue"
},
  "geometry": {"coordinates":[3.1772139072,50.776473999],"type":"Point"}
}