{
  "type": "Feature",
  "properties": {
    "addr:full":"Chemin Des Villas 21 Profondeville (lustin) Namur 5170",
    "addr:housenumber":"21",
    "addr:postcode":"5170",
    "addr:street":"Chemin Des Villas",
    "iso:country":"BE",
    "sg:address":"Chemin Des Villas 21",
    "sg:city":"Profondeville (lustin)",
    "sg:classifiers":[
        {
            "category":"Professional",
            "subcategory":"Computer Services",
            "type":"Services"
        }
    ],
    "sg:phone":"+32 81 41 18 61",
    "sg:postcode":"5170",
    "sg:province":"Namur",
    "sg:tags":[
        "-",
        "processing",
        "data"
    ],
    "wof:name":"Computer World",
    "wof:placetype":"venue"
},
  "geometry": {"coordinates":[4.8756361008,50.3677711487],"type":"Point"}
}