{
  "type": "Feature",
  "properties": {
    "iso:country":"BE",
    "sg:address":"Rue Francisco Ferrer 2",
    "sg:city":"Grace-hollogne",
    "sg:orig_category":"Epiceries. Cr\u00e9meries",
    "sg:phone":"+32 4 246 55 84",
    "sg:postcode":"4460",
    "sg:province":"Li\u00e8ge",
    "wof:name":"Caterina Migliardi",
    "wof:placetype":"venue"
},
  "geometry": {"coordinates":[5.5017499924,50.6442985535],"type":"Point"}
}