{
  "type": "Feature",
  "properties": {
    "addr:full":"Kerkhofbaan 6 Aalst Oost-Vlaanderen 9320",
    "addr:housenumber":"6",
    "addr:postcode":"9320",
    "addr:street":"Kerkhofbaan",
    "iso:country":"BE",
    "sg:address":"Kerkhofbaan 6",
    "sg:city":"Aalst",
    "sg:orig_category":"Kapsalons",
    "sg:phone":"+32 53 78 61 47",
    "sg:postcode":"9320",
    "sg:province":"Oost-Vlaanderen",
    "wof:name":"Coiffure Margot",
    "wof:placetype":"venue"
},
  "geometry": {"coordinates":[4.0355029106,50.9306907654],"type":"Point"}
}