{
  "type": "Feature",
  "properties": {
    "addr:full":"Sint-sebastiaanstraat 23 Lummen Limburg 3560",
    "addr:housenumber":"23",
    "addr:postcode":"3560",
    "addr:street":"Sint-Sebastiaanstraat",
    "iso:country":"BE",
    "sg:address":"Sint-sebastiaanstraat 23",
    "sg:city":"Lummen",
    "sg:orig_category":"Eleveurs and marchands de porcs",
    "sg:phone":"+32 11 42 58 43",
    "sg:postcode":"3560",
    "sg:province":"Limburg",
    "wof:name":"Patrick Rediers",
    "wof:placetype":"venue"
},
  "geometry": {"coordinates":[5.2002019882,51.0275802612],"type":"Point"}
}