{
  "type": "Feature",
  "properties": {
    "iso:country":"BE",
    "sg:address":"Kasteeldreef 35",
    "sg:city":"Bornem",
    "sg:orig_category":"Mus\u00e9es and patrimoine culturel",
    "sg:phone":"+32 3 889 90 09",
    "sg:postcode":"2880",
    "sg:province":"Antwerpen",
    "wof:name":"Kast. M. Van St.aldegonde",
    "wof:placetype":"venue"
},
  "geometry": {"coordinates":[4.2326040268,51.1001091003],"type":"Point"}
}