{
  "type": "Feature",
  "properties": {
    "iso:country":"BE",
    "sg:address":"Avenue C Joset 19",
    "sg:city":"Etterbeek",
    "sg:orig_category":"Metaalbehandeling and -bekleding",
    "sg:phone":"+32 2 735 07 67",
    "sg:postcode":"1040",
    "sg:province":"Bruxelles-Capitale",
    "wof:name":"Odci",
    "wof:placetype":"venue"
},
  "geometry": {"coordinates":[4.3977828026,50.8315505981],"type":"Point"}
}