{
  "type": "Feature",
  "properties": {
    "iso:country":"BE",
    "sg:address":"Rue Du Vieux-moulin 6",
    "sg:city":"Bastogne",
    "sg:orig_category":"Maroquinerie and articles de voyage",
    "sg:phone":"+32 61 21 72 08",
    "sg:postcode":"6600",
    "sg:province":"Luxembourg",
    "wof:name":"Maroquinerie Sabrina",
    "wof:placetype":"venue"
},
  "geometry": {"coordinates":[5.7195391655,50.0020866394],"type":"Point"}
}