{
  "type": "Feature",
  "properties": {
    "iso:country":"BE",
    "sg:address":"Rue Des Tilleuls 7",
    "sg:city":"Dinant",
    "sg:orig_category":"Plomberie, chauffage and installations sanitaires",
    "sg:phone":"+32 82 22 53 77",
    "sg:postcode":"5500",
    "sg:province":"Namur",
    "wof:name":"Chaffoteaux & Maury",
    "wof:placetype":"venue"
},
  "geometry": {"coordinates":[4.9054780006,50.2375068665],"type":"Point"}
}