{
  "type": "Feature",
  "properties": {
    "addr:full":"Stationstraat 3 Beveren Oost-Vlaanderen 9120",
    "addr:housenumber":"3",
    "addr:postcode":"9120",
    "addr:street":"Stationstraat",
    "iso:country":"BE",
    "sg:address":"Stationstraat 3",
    "sg:city":"Beveren",
    "sg:classifiers":[
        {
            "category":"Restaurant",
            "type":"Food & Drink"
        }
    ],
    "sg:phone":"+32 3 775 30 30",
    "sg:postcode":"9120",
    "sg:province":"Oost-Vlaanderen",
    "wof:name":"Broeder Jules",
    "wof:placetype":"venue"
},
  "geometry": {"coordinates":[4.2571392059,51.2124099731],"type":"Point"}
}