{
  "type": "Feature",
  "properties": {
    "addr:full":"Rue Ladrie 21 Soumagne Li\u00e8ge 4630",
    "addr:housenumber":"21",
    "addr:postcode":"4630",
    "addr:street":"Rue Ladrie",
    "iso:country":"BE",
    "sg:address":"Rue Ladrie 21",
    "sg:city":"Soumagne",
    "sg:orig_category":"Installation de menuiserie en bois and plastique",
    "sg:phone":"+32 4 387 82 92",
    "sg:postcode":"4630",
    "sg:province":"Li\u00e8ge",
    "wof:name":"C.d.",
    "wof:placetype":"venue"
},
  "geometry": {"coordinates":[5.7495908737,50.6162643433],"type":"Point"}
}