{
  "type": "Feature",
  "properties": {
    "iso:country":"BE",
    "sg:address":"Herent 46",
    "sg:city":"Neerpelt",
    "sg:orig_category":"Drukkerijen and copyshops",
    "sg:phone":"+32 11 64 52 93",
    "sg:postcode":"3910",
    "sg:province":"Limburg",
    "wof:name":"Drukkerij Eerlingen",
    "wof:placetype":"venue"
},
  "geometry": {"coordinates":[5.4430961609,51.2080497742],"type":"Point"}
}