{
  "type": "Feature",
  "properties": {
    "iso:country":"BE",
    "sg:address":"Antwerpsesteenweg 8",
    "sg:city":"Kapellen",
    "sg:orig_category":"V\u00e9los",
    "sg:phone":"+32 3 605 98 06",
    "sg:postcode":"2950",
    "sg:province":"Antwerpen",
    "wof:name":"Mega Bike",
    "wof:placetype":"venue"
},
  "geometry": {"coordinates":[4.4292287827,51.3143997192],"type":"Point"}
}