{
  "type": "Feature",
  "properties": {
    "addr:full":"Kempisch Dok Westkaai 33a Antwerpen Antwerpen 2000",
    "addr:housenumber":"33a",
    "addr:postcode":"2000",
    "addr:street":"Westkaai",
    "iso:country":"BE",
    "sg:address":"Kempisch Dok Westkaai 33a",
    "sg:city":"Antwerpen",
    "sg:classifiers":[
        {
            "category":"Structure",
            "subcategory":"Office Building",
            "type":"Public Place"
        }
    ],
    "sg:phone":"+32 3 646 65 18",
    "sg:postcode":"2000",
    "sg:province":"Antwerpen",
    "sg:tags":[
        "-",
        "type",
        "door",
        "sliding",
        "overhead"
    ],
    "wof:name":"Van Paesschen-de Bruyne",
    "wof:placetype":"venue"
},
  "geometry": {"coordinates":[4.4049448967,51.2316131592],"type":"Point"}
}