{
  "type": "Feature",
  "properties": {
    "addr:full":"Minderbroedersstraat 8 Leuven Vlaams-Brabant 3000",
    "addr:housenumber":"8",
    "addr:postcode":"3000",
    "addr:street":"Minderbroedersstraat",
    "iso:country":"BE",
    "sg:address":"Minderbroedersstraat 8",
    "sg:city":"Leuven",
    "sg:classifiers":[
        {
            "category":"Social Services",
            "type":"Services"
        }
    ],
    "sg:phone":"+32 16 24 20 02",
    "sg:postcode":"3000",
    "sg:province":"Vlaams-Brabant",
    "wof:name":"Boerenbond",
    "wof:placetype":"venue"
},
  "geometry": {"coordinates":[4.6964907646,50.8777923584],"type":"Point"}
}