{
  "type": "Feature",
  "properties": {
    "addr:full":"Owenslei 1 Mol Antwerpen 2400",
    "addr:housenumber":"1",
    "addr:postcode":"2400",
    "addr:street":"Owenslei",
    "iso:country":"BE",
    "sg:address":"Owenslei 1",
    "sg:city":"Mol",
    "sg:classifiers":[
        {
            "category":"Banks & Credit Unions",
            "subcategory":"Investment Brokerage",
            "type":"Services"
        }
    ],
    "sg:phone":"+32 14 81 40 67",
    "sg:postcode":"2400",
    "sg:province":"Antwerpen",
    "sg:tags":[
        "-",
        "sale",
        "yachts",
        "accessory",
        "pleasure",
        "boat"
    ],
    "wof:name":"Dierckx Bvba",
    "wof:placetype":"venue"
},
  "geometry": {"coordinates":[5.1590499878,51.1922492981],"type":"Point"}
}