{
  "type": "Feature",
  "properties": {
    "addr:full":"Peperstraat 1ba Retie Antwerpen 2470",
    "addr:housenumber":"1ba",
    "addr:postcode":"2470",
    "addr:street":"Peperstraat",
    "iso:country":"BE",
    "sg:address":"Peperstraat 1ba",
    "sg:city":"Retie",
    "sg:orig_category":"Imprimeries and copyshops",
    "sg:phone":"+32 14 37 10 28",
    "sg:postcode":"2470",
    "sg:province":"Antwerpen",
    "wof:name":"Drukkerij E. & E.",
    "wof:placetype":"venue"
},
  "geometry": {"coordinates":[5.0836558342,51.2674484253],"type":"Point"}
}