{
  "type": "Feature",
  "properties": {
    "iso:country":"BE",
    "sg:address":"Houplinesstraat 15ba",
    "sg:city":"Komen-waasten/comines-warneton",
    "sg:orig_category":"Kansspelen",
    "sg:phone":"+32 56 58 85 63",
    "sg:postcode":"7783",
    "sg:province":"Hainaut",
    "wof:name":"Ladbroke",
    "wof:placetype":"venue"
},
  "geometry": {"coordinates":[2.8828949928,50.7069244385],"type":"Point"}
}