{
  "type": "Feature",
  "properties": {
    "addr:full":"Xavier De Cockln 66 Pb 6 Deurle Oost-Vlaanderen 9831",
    "addr:housenumber":"66;6",
    "addr:postcode":"9831",
    "addr:street":"Xavier;Pb;Oost-Vlaanderen",
    "iso:country":"BE",
    "sg:address":"Xavier De Cockln 66 Pb 6",
    "sg:city":"Deurle",
    "sg:classifiers":[
        {
            "category":"Professional",
            "subcategory":"Advertising",
            "type":"Services"
        }
    ],
    "sg:phone":"+32 9 280 94 20",
    "sg:postcode":"9831",
    "sg:province":"Oost-Vlaanderen",
    "sg:tags":[
        "marketing",
        "medium",
        "communication"
    ],
    "wof:name":"De Facto Imago Building Nv",
    "wof:placetype":"venue"
},
  "geometry": {"coordinates":[3.6009049416,51.0073394775],"type":"Point"}
}