{
  "type": "Feature",
  "properties": {
    "addr:full":"Rue Garde Dieu 79 Li\u00c8ge Li\u00e8ge 4031",
    "addr:housenumber":"79",
    "addr:postcode":"4031",
    "addr:street":"Rue Garde Dieu",
    "iso:country":"BE",
    "sg:address":"Rue Garde Dieu 79",
    "sg:city":"Li\u00c8ge",
    "sg:orig_category":"Gespecialiseerde residenti\u00eble bouw",
    "sg:phone":"+32 495 20 16 97",
    "sg:postcode":"4031",
    "sg:province":"Li\u00e8ge",
    "wof:name":"Hom",
    "wof:placetype":"venue"
},
  "geometry": {"coordinates":[5.583304882,50.61926651],"type":"Point"}
}