{
  "type": "Feature",
  "properties": {
    "addr:full":"Route De Bavay 22 Frameries Hainaut 7080",
    "addr:housenumber":"22",
    "addr:postcode":"7080",
    "addr:street":"Route De Bavay",
    "iso:country":"BE",
    "sg:address":"Route De Bavay 22",
    "sg:city":"Frameries",
    "sg:classifiers":[
        {
            "category":"Structure",
            "subcategory":"Warehouse",
            "type":"Public Place"
        }
    ],
    "sg:phone":"+32 65 67 37 54",
    "sg:postcode":"7080",
    "sg:province":"Hainaut",
    "sg:tags":[
        "catheter",
        "guide-wires"
    ],
    "wof:name":"Dimequip S.a.",
    "wof:placetype":"venue"
},
  "geometry": {"coordinates":[3.9189360142,50.4040336609],"type":"Point"}
}