{
  "type": "Feature",
  "properties": {
    "addr:full":"Victor Frislei 53 Schoten Antwerpen 2900",
    "addr:housenumber":"53",
    "addr:postcode":"2900",
    "addr:street":"Victor Frislei",
    "iso:country":"BE",
    "sg:address":"Victor Frislei 53",
    "sg:city":"Schoten",
    "sg:orig_category":"Persagentschappen",
    "sg:phone":"+32 3 685 09 20",
    "sg:postcode":"2900",
    "sg:province":"Antwerpen",
    "wof:name":"Frida Deceunynck",
    "wof:placetype":"venue"
},
  "geometry": {"coordinates":[4.5318479538,51.2458152771],"type":"Point"}
}