{
  "type": "Feature",
  "properties": {
    "addr:full":"Meerseweg 80b Hoogstraten Antwerpen 2321",
    "addr:housenumber":"80b",
    "addr:postcode":"2321",
    "addr:street":"Meerseweg",
    "iso:country":"BE",
    "sg:address":"Meerseweg 80b",
    "sg:city":"Hoogstraten",
    "sg:orig_category":"Syst\u00e8mes de t\u00e9l\u00e9communications. Mat\u00e9riel de T\u00e9l\u00e9communication",
    "sg:phone":"+32 3 315 09 09",
    "sg:postcode":"2321",
    "sg:province":"Antwerpen",
    "wof:name":"Softcomputer",
    "wof:placetype":"venue"
},
  "geometry": {"coordinates":[4.7366099358,51.442325592],"type":"Point"}
}