{
  "type": "Feature",
  "properties": {
    "addr:full":"Chauss\u00e9e De Ruisbroek 35 Box 2 Bruxelles (forest) Bruxelles-Capitale 1190",
    "addr:housenumber":"35;2",
    "addr:postcode":"1190",
    "addr:street":"Chausse\u0301E De Ruisbroek;Box",
    "iso:country":"BE",
    "sg:address":"Chauss\u00e9e De Ruisbroek 35 Box 2",
    "sg:city":"Bruxelles (forest)",
    "sg:classifiers":[
        {
            "category":"Communications",
            "type":"Services"
        }
    ],
    "sg:phone":"+32 2 376 22 16",
    "sg:postcode":"1190",
    "sg:province":"Bruxelles-Capitale",
    "sg:tags":[
        "telecommunication"
    ],
    "wof:name":"De Craecker S",
    "wof:placetype":"venue"
},
  "geometry": {"coordinates":[4.3159241676,50.7995681763],"type":"Point"}
}