{
  "type": "Feature",
  "properties": {
    "addr:full":"Damstraat 13 Pittem West-Vlaanderen 8740",
    "addr:housenumber":"13",
    "addr:postcode":"8740",
    "addr:street":"Damstraat",
    "iso:country":"BE",
    "sg:address":"Damstraat 13",
    "sg:city":"Pittem",
    "sg:orig_category":"Eleveurs de bovins. Eleveurs and marchands de porcs",
    "sg:phone":"+32 51 65 57 72",
    "sg:postcode":"8740",
    "sg:province":"West-Vlaanderen",
    "wof:name":"Van Walleghem Paul & Andy",
    "wof:placetype":"venue"
},
  "geometry": {"coordinates":[3.284373045,51.0294456482],"type":"Point"}
}