{
  "type": "Feature",
  "properties": {
    "iso:country":"BE",
    "sg:address":"Leopoldlaan 32ba",
    "sg:city":"Aalst",
    "sg:orig_category":"Avocats and conseillers juridiques",
    "sg:phone":"+32 53 77 36 35",
    "sg:postcode":"9300",
    "sg:province":"Oost-Vlaanderen",
    "wof:name":"Jo Vanbelle",
    "wof:placetype":"venue"
},
  "geometry": {"coordinates":[4.0528869629,50.9434280396],"type":"Point"}
}