{
  "type": "Feature",
  "properties": {
    "addr:full":"Avenue Josse Goffin 133 Sint-agatha-berchem/berchem-sainte-agathe Bruxelles-Capitale 1082",
    "addr:housenumber":"133;/",
    "addr:postcode":"1082",
    "addr:street":"Avenue Josse Goffin;Sint-Agatha-Berchem",
    "iso:country":"BE",
    "sg:address":"Avenue Josse Goffin 133",
    "sg:city":"Sint-agatha-berchem/berchem-sainte-agathe",
    "sg:orig_category":"Journaux. Tabac",
    "sg:phone":"+32 2 465 30 47",
    "sg:postcode":"1082",
    "sg:province":"Bruxelles-Capitale",
    "wof:name":"Libr. H\u00d4pital Fran\u00c7ais",
    "wof:placetype":"venue"
},
  "geometry": {"coordinates":[4.3038711548,50.8664054871],"type":"Point"}
}