{
  "type": "Feature",
  "properties": {
    "addr:full":"Rijksweg 718 Dilsen-stokkem Limburg 3650",
    "addr:housenumber":"718",
    "addr:postcode":"dilsen-stokkem;3650",
    "addr:street":"Rijksweg",
    "iso:country":"BE",
    "sg:address":"Rijksweg 718",
    "sg:city":"Dilsen-stokkem",
    "sg:classifiers":[
        {
            "category":"Cafe",
            "type":"Food & Drink"
        }
    ],
    "sg:phone":"+32 89 75 44 79",
    "sg:postcode":"3650",
    "sg:province":"Limburg",
    "sg:tags":[
        "caf\u00e9s"
    ],
    "wof:name":"Marion Franke",
    "wof:placetype":"venue"
},
  "geometry": {"coordinates":[5.7411899567,51.0534133911],"type":"Point"}
}