{
  "type": "Feature",
  "properties": {
    "addr:full":"Biessemstraat 12 Heers Limburg 3870",
    "addr:housenumber":"12",
    "addr:postcode":"3870",
    "addr:street":"Biessemstraat",
    "iso:country":"BE",
    "sg:address":"Biessemstraat 12",
    "sg:city":"Heers",
    "sg:orig_category":"Producteurs de fruits",
    "sg:phone":"+32 11 48 69 30",
    "sg:postcode":"3870",
    "sg:province":"Limburg",
    "wof:name":"Bernadette Robijns",
    "wof:placetype":"venue"
},
  "geometry": {"coordinates":[5.2563400269,50.7421112061],"type":"Point"}
}