{
  "type": "Feature",
  "properties": {
    "addr:full":"Noordlaan 48 Roeselare West-Vlaanderen 8800",
    "addr:housenumber":"48",
    "addr:postcode":"8800",
    "addr:street":"Noordlaan",
    "iso:country":"BE",
    "sg:address":"Noordlaan 48",
    "sg:city":"Roeselare",
    "sg:orig_category":"Maatkleding Fab",
    "sg:phone":"+32 51 22 54 65",
    "sg:postcode":"8800",
    "sg:province":"West-Vlaanderen",
    "wof:name":"Christine Vermeulen",
    "wof:placetype":"venue"
},
  "geometry": {"coordinates":[3.1183309555,50.955909729],"type":"Point"}
}