{
  "type": "Feature",
  "properties": {
    "iso:country":"BE",
    "sg:address":"Dorpsstraat 118",
    "sg:city":"Heusden-zolder (zolder)",
    "sg:classifiers":[
        {
            "category":"Personal",
            "subcategory":"Beauty Salon",
            "type":"Services"
        }
    ],
    "sg:phone":"+32 11 52 68 80",
    "sg:postcode":"3550",
    "sg:province":"Limburg",
    "wof:name":"Gently",
    "wof:placetype":"venue"
},
  "geometry": {"coordinates":[5.318089962,51.024269104],"type":"Point"}
}