{
  "type": "Feature",
  "properties": {
    "addr:full":"Sint-truidersteenweg 2 Hasselt Limburg 3500",
    "addr:housenumber":"2",
    "addr:postcode":"3500",
    "addr:street":"Sint-Truidersteenweg",
    "iso:country":"BE",
    "sg:address":"Sint-truidersteenweg 2",
    "sg:city":"Hasselt",
    "sg:orig_category":"Speelgoed",
    "sg:phone":"+32 11 26 25 47",
    "sg:postcode":"3500",
    "sg:province":"Limburg",
    "wof:name":"Game Nation Hasselt",
    "wof:placetype":"venue"
},
  "geometry": {"coordinates":[5.3358898163,50.9267692566],"type":"Point"}
}