{
  "type": "Feature",
  "properties": {
    "addr:full":"Rue Du Texas 25 Bruxelles (forest) Bruxelles-Capitale 1190",
    "addr:housenumber":"25",
    "addr:postcode":"1190",
    "addr:street":"Rue Du Texas",
    "iso:country":"BE",
    "sg:address":"Rue Du Texas 25",
    "sg:city":"Bruxelles (forest)",
    "sg:classifiers":[
        {
            "category":"Wholesale",
            "subcategory":"Vending Machines",
            "type":"Manufacturing & Wholesale Goods"
        }
    ],
    "sg:phone":"+32 2 344 23 21",
    "sg:postcode":"1190",
    "sg:province":"Bruxelles-Capitale",
    "sg:tags":[
        "polishing",
        "grinding"
    ],
    "wof:name":"Renwart Sa",
    "wof:placetype":"venue"
},
  "geometry": {"coordinates":[4.3210902214,50.8135299683],"type":"Point"}
}