{
  "type": "Feature",
  "properties": {
    "iso:country":"BE",
    "sg:address":"Tenhovestraat 9",
    "sg:city":"Tielt",
    "sg:orig_category":"Rev\u00eatements de sols and murs. Magasins sp\u00e9cialis\u00e9s",
    "sg:phone":"+32 51 40 70 59",
    "sg:postcode":"8700",
    "sg:province":"West-Vlaanderen",
    "wof:name":"Magma",
    "wof:placetype":"venue"
},
  "geometry": {"coordinates":[3.3388299942,50.982219696],"type":"Point"}
}