{
  "type": "Feature",
  "properties": {
    "addr:full":"Rue De La Semois 141 Etalle (vance) Luxembourg 6741",
    "addr:housenumber":"141",
    "addr:postcode":"6741",
    "addr:street":"Rue De La Semois",
    "iso:country":"BE",
    "sg:address":"Rue De La Semois 141",
    "sg:city":"Etalle (vance)",
    "sg:classifiers":[
        {
            "category":"Professional",
            "subcategory":"Testing Lab",
            "type":"Services"
        }
    ],
    "sg:phone":"+32 63 45 63 95",
    "sg:postcode":"6741",
    "sg:province":"Luxembourg",
    "sg:tags":[
        "chemist"
    ],
    "wof:name":"Epc",
    "wof:placetype":"venue"
},
  "geometry": {"coordinates":[5.6619501114,49.6695289612],"type":"Point"}
}