{
  "type": "Feature",
  "properties": {
    "addr:full":"Oevelseweg 50 Olen Antwerpen 2250",
    "addr:housenumber":"50",
    "addr:postcode":"2250",
    "addr:street":"Oevelseweg",
    "iso:country":"BE",
    "sg:address":"Oevelseweg 50",
    "sg:city":"Olen",
    "sg:classifiers":[
        {
            "category":"Health Services",
            "subcategory":"Health Practitioner",
            "type":"Services"
        }
    ],
    "sg:phone":"+32 14 21 94 18",
    "sg:postcode":"2250",
    "sg:province":"Antwerpen",
    "sg:tags":[
        "physiotherapist"
    ],
    "wof:name":"Neefs Luc",
    "wof:placetype":"venue"
},
  "geometry": {"coordinates":[4.9000020027,51.1636657715],"type":"Point"}
}