{
  "type": "Feature",
  "properties": {
    "iso:country":"BE",
    "sg:address":"H. Consciencelaan 42",
    "sg:city":"Overijse",
    "sg:orig_category":"Agences de marketing. Agences de voyages",
    "sg:phone":"+32 2 688 17 06",
    "sg:postcode":"3090",
    "sg:province":"Vlaams-Brabant",
    "wof:name":"Elbaco",
    "wof:placetype":"venue"
},
  "geometry": {"coordinates":[4.525821209,50.7813682556],"type":"Point"}
}