{
  "type": "Feature",
  "properties": {
    "addr:full":"Rue La Vau 60 Braine L'alleud (braine-l'alleud) Brabant Wallon 1420",
    "addr:housenumber":"60",
    "addr:postcode":"1420",
    "addr:street":"Rue La Vau",
    "iso:country":"BE",
    "sg:address":"Rue La Vau 60",
    "sg:city":"Braine L'alleud (braine-l'alleud)",
    "sg:classifiers":[
        {
            "category":"Education",
            "subcategory":"School",
            "type":"Public Place"
        }
    ],
    "sg:phone":"+32 2 384 15 92",
    "sg:postcode":"1420",
    "sg:province":"Brabant Wallon",
    "sg:tags":[
        "-",
        "private"
    ],
    "wof:name":"Atelier D'art De La Grange Des Champs (l') Asbl Asbl",
    "wof:placetype":"venue"
},
  "geometry": {"coordinates":[-0.6576030254,47.3839378357],"type":"Point"}
}