{
  "type": "Feature",
  "properties": {
    "addr:full":"Meensesteenweg 224 Izegem West-Vlaanderen 8870",
    "addr:housenumber":"224",
    "addr:postcode":"8870",
    "addr:street":"Meensesteenweg",
    "iso:country":"BE",
    "sg:address":"Meensesteenweg 224",
    "sg:city":"Izegem",
    "sg:orig_category":"Non-Classified Establishments",
    "sg:phone":"+32 51 30 32 16",
    "sg:postcode":"8870",
    "sg:province":"West-Vlaanderen",
    "wof:name":"Vanlaeken",
    "wof:placetype":"venue"
},
  "geometry": {"coordinates":[3.1917860508,50.9011611938],"type":"Point"}
}