{
  "type": "Feature",
  "properties": {
    "iso:country":"BE",
    "sg:address":"Rue De Bruxelles 219",
    "sg:city":"Genappe (vieux-genappe)",
    "sg:classifiers":[
        {
            "category":"Retail",
            "subcategory":"Auto Repair",
            "type":"Services"
        }
    ],
    "sg:phone":"+32 67 77 32 37",
    "sg:postcode":"1472",
    "sg:province":"Brabant Wallon",
    "sg:tags":[
        "garage"
    ],
    "wof:name":"Ets J. Desmadryl Sprl",
    "wof:placetype":"venue"
},
  "geometry": {"coordinates":[4.438849926,50.6078643799],"type":"Point"}
}