{
  "type": "Feature",
  "properties": {
    "iso:country":"BE",
    "sg:address":"Kon Albertlaan 32",
    "sg:city":"Bierbeek",
    "sg:orig_category":"Reisbureaus",
    "sg:phone":"+32 16 46 35 92",
    "sg:postcode":"3360",
    "sg:province":"Vlaams-Brabant",
    "wof:name":"Kreata-crea-langues",
    "wof:placetype":"venue"
},
  "geometry": {"coordinates":[4.7628569603,50.8641662598],"type":"Point"}
}