{
  "type": "Feature",
  "properties": {
    "iso:country":"BE",
    "sg:address":"Haverenbosstraat 72",
    "sg:city":"Alken",
    "sg:orig_category":"Artiesten and kunstenaars",
    "sg:phone":"+32 11 31 26 44",
    "sg:postcode":"3570",
    "sg:province":"Limburg",
    "wof:name":"Julia Luys",
    "wof:placetype":"venue"
},
  "geometry": {"coordinates":[5.2988500595,50.8668289185],"type":"Point"}
}