{
  "type": "Feature",
  "properties": {
    "iso:country":"BE",
    "sg:address":"Sint-rochusstraat 14",
    "sg:city":"Deerlijk",
    "sg:classifiers":[
        {
            "category":"Insurance",
            "subcategory":"Life Insurance",
            "type":"Services"
        }
    ],
    "sg:phone":"+32 56 70 61 48",
    "sg:postcode":"8540",
    "sg:province":"West-Vlaanderen",
    "sg:tags":[
        "assurance"
    ],
    "wof:name":"Par-invest En Co",
    "wof:placetype":"venue"
},
  "geometry": {"coordinates":[3.3585300446,50.8532104492],"type":"Point"}
}