{
  "type": "Feature",
  "properties": {
    "iso:country":"BE",
    "sg:address":"Sint-catharinaplein 27",
    "sg:city":"Oostende",
    "sg:orig_category":"Banques and organismes de cr\u00e9dit",
    "sg:phone":"+32 59 51 51 76",
    "sg:postcode":"8400",
    "sg:province":"West-Vlaanderen",
    "wof:name":"Groep Argenta",
    "wof:placetype":"venue"
},
  "geometry": {"coordinates":[2.9045870304,51.2166442871],"type":"Point"}
}