{
  "type": "Feature",
  "properties": {
    "addr:full":"Avenue Eug\u00c8ne Mascaux 118 Charleroi Hainaut 6001",
    "addr:housenumber":"118",
    "addr:postcode":"6001",
    "addr:street":"Avenue Euge\u0300Ne Mascaux;Hainaut",
    "iso:country":"BE",
    "sg:address":"Avenue Eug\u00c8ne Mascaux 118",
    "sg:city":"Charleroi",
    "sg:orig_category":"Dierenartsen",
    "sg:phone":"+32 71 36 26 76",
    "sg:postcode":"6001",
    "sg:province":"Hainaut",
    "wof:name":"Jean-louis Philippe",
    "wof:placetype":"venue"
},
  "geometry": {"coordinates":[4.4442191124,50.3969955444],"type":"Point"}
}