{
  "type": "Feature",
  "properties": {
    "iso:country":"BE",
    "sg:address":"Ten Bossestraat 94",
    "sg:city":"Brakel",
    "sg:orig_category":"Fujitsu Siemens. Conception d'\u00e9talages and de showrooms. Ordinateurs and \u00e9quipement informatique",
    "sg:phone":"+32 55 42 17 94",
    "sg:postcode":"9660",
    "sg:province":"Oost-Vlaanderen",
    "wof:name":"Edma",
    "wof:placetype":"venue"
},
  "geometry": {"coordinates":[3.7705209255,50.7973403931],"type":"Point"}
}