{
  "type": "Feature",
  "properties": {
    "addr:full":"Avenue Henri Bourgys 78 Waterloo Brabant Wallon 1410",
    "addr:housenumber":"78",
    "addr:postcode":"1410",
    "addr:street":"Avenue Henri Bourgys",
    "iso:country":"BE",
    "sg:address":"Avenue Henri Bourgys 78",
    "sg:city":"Waterloo",
    "sg:classifiers":[
        {
            "category":"Health Services",
            "subcategory":"Dentist",
            "type":"Services"
        }
    ],
    "sg:phone":"+32 2 354 65 29",
    "sg:postcode":"1410",
    "sg:province":"Brabant Wallon",
    "wof:name":"Stoimenov Ivan",
    "wof:placetype":"venue"
},
  "geometry": {"coordinates":[4.3898382187,50.7295951843],"type":"Point"}
}