{
  "type": "Feature",
  "properties": {
    "iso:country":"BE",
    "sg:address":"Gare Stoumont 1",
    "sg:city":"Stoumont",
    "sg:orig_category":"Treinen and spoorwegen",
    "sg:phone":"+32 80 78 56 83",
    "sg:postcode":"4987",
    "sg:province":"Li\u00e8ge",
    "wof:name":"Gare De Stoumont",
    "wof:placetype":"venue"
},
  "geometry": {"coordinates":[5.7713880539,50.4175643921],"type":"Point"}
}