{
  "type": "Feature",
  "properties": {
    "addr:full":"Avenue Louise 207 Box 14 Bruxelles (ixelles) Bruxelles-Capitale 1050",
    "addr:housenumber":"207 box 14",
    "addr:postcode":"1050",
    "addr:street":"Avenue Louise",
    "iso:country":"BE",
    "sg:address":"Avenue Louise 207 Box 14",
    "sg:city":"Bruxelles (ixelles)",
    "sg:classifiers":[
        {
            "category":"Professional",
            "subcategory":"Employment Agencies",
            "type":"Services"
        }
    ],
    "sg:phone":"+32 2 640 91 91",
    "sg:postcode":"1050",
    "sg:province":"Bruxelles-Capitale",
    "sg:tags":[
        "temping",
        "clerical",
        "-"
    ],
    "wof:name":"Avenue Louise Interim Sa",
    "wof:placetype":"venue"
},
  "geometry": {"coordinates":[4.3639807701,50.826587677],"type":"Point"}
}