{
  "type": "Feature",
  "properties": {
    "addr:full":"Avenue Brugmann 591 Bruxelles (uccle) Bruxelles-Capitale 1180",
    "addr:housenumber":"591",
    "addr:postcode":"1180",
    "addr:street":"Avenue Brugmann",
    "iso:country":"BE",
    "sg:address":"Avenue Brugmann 591",
    "sg:city":"Bruxelles (uccle)",
    "sg:classifiers":[
        {
            "category":"Parking",
            "subcategory":"Lot",
            "type":"Transportation"
        }
    ],
    "sg:phone":"+32 2 345 88 86",
    "sg:postcode":"1180",
    "sg:province":"Bruxelles-Capitale",
    "sg:tags":[
        "armoured",
        "door",
        "fireproof"
    ],
    "wof:name":"A Abc De La Serrure Du Globe",
    "wof:placetype":"venue"
},
  "geometry": {"coordinates":[4.3379869461,50.8009490967],"type":"Point"}
}