{
  "type": "Feature",
  "properties": {
    "addr:full":"Louizalaan 32 Elsene/ixelles Bruxelles-Capitale 1050",
    "addr:housenumber":"32",
    "addr:postcode":"1050",
    "addr:street":"Louizalaan",
    "iso:country":"BE",
    "sg:address":"Louizalaan 32",
    "sg:city":"Elsene/ixelles",
    "sg:orig_category":"Postzegels, munten and trofee\u00ebn",
    "sg:phone":"+32 2 514 58 00",
    "sg:postcode":"1050",
    "sg:province":"Bruxelles-Capitale",
    "wof:name":"Tradart Bruxelles",
    "wof:placetype":"venue"
},
  "geometry": {"coordinates":[4.3573069572,50.8343505859],"type":"Point"}
}