{
  "type": "Feature",
  "properties": {
    "addr:full":"Rue Saint Blaise 28 Ch\u00e2telet (bouffioulx) Hainaut 6200",
    "addr:housenumber":"28",
    "addr:postcode":"6200",
    "addr:street":"Rue Saint Blaise",
    "iso:country":"BE",
    "sg:address":"Rue Saint Blaise 28",
    "sg:city":"Ch\u00e2telet (bouffioulx)",
    "sg:classifiers":[
        {
            "category":"Building & Trades",
            "subcategory":"Construction",
            "type":"Services"
        }
    ],
    "sg:phone":"+32 71 39 68 99",
    "sg:postcode":"6200",
    "sg:province":"Hainaut",
    "sg:tags":[
        "installation",
        "-",
        "central",
        "heating"
    ],
    "wof:name":"All Concept Construct",
    "wof:placetype":"venue"
},
  "geometry": {"coordinates":[4.5232467651,50.3888778687],"type":"Point"}
}