{
  "type": "Feature",
  "properties": {
    "addr:full":"Rue Jules Hagnoul 8 Orp-jauche Brabant Wallon 1350",
    "addr:housenumber":"8",
    "addr:postcode":"1350",
    "addr:street":"Rue Jules Hagnoul",
    "iso:country":"BE",
    "sg:address":"Rue Jules Hagnoul 8",
    "sg:city":"Orp-jauche",
    "sg:orig_category":"V\u00eatements pour Hommes",
    "sg:phone":"+32 19 63 32 76",
    "sg:postcode":"1350",
    "sg:province":"Brabant Wallon",
    "wof:name":"Bernar",
    "wof:placetype":"venue"
},
  "geometry": {"coordinates":[4.97920084,50.6738891602],"type":"Point"}
}