{
  "type": "Feature",
  "properties": {
    "addr:full":"Van Lissumstraat 84 Antwerpen Antwerpen 2100",
    "addr:housenumber":"84",
    "addr:postcode":"2100",
    "addr:street":"Lissumstraat",
    "iso:country":"BE",
    "sg:address":"Van Lissumstraat 84",
    "sg:city":"Antwerpen",
    "sg:classifiers":[
        {
            "category":"Fast Food",
            "type":"Food & Drink"
        }
    ],
    "sg:phone":"+32 3 322 59 63",
    "sg:postcode":"2100",
    "sg:province":"Antwerpen",
    "sg:tags":[
        "meeneem",
        "restaurant"
    ],
    "wof:name":"Hong Kong",
    "wof:placetype":"venue"
},
  "geometry": {"coordinates":[4.4586100578,51.2203941345],"type":"Point"}
}