{
  "type": "Feature",
  "properties": {
    "addr:full":"Heikant 8 Heusden-zolder (zolder) Limburg 3550",
    "addr:housenumber":"8",
    "addr:postcode":"3550",
    "addr:street":"Heikant",
    "iso:country":"BE",
    "sg:address":"Heikant 8",
    "sg:city":"Heusden-zolder (zolder)",
    "sg:classifiers":[
        {
            "category":"Education",
            "subcategory":"University",
            "type":"Public Place"
        }
    ],
    "sg:phone":"+32 11 53 72 62",
    "sg:postcode":"3550",
    "sg:province":"Limburg",
    "sg:tags":[
        "adult"
    ],
    "wof:name":"Hosta Bvba",
    "wof:placetype":"venue"
},
  "geometry": {"coordinates":[5.3045649529,51.0163955688],"type":"Point"}
}