{
  "type": "Feature",
  "properties": {
    "iso:country":"BE",
    "sg:address":"Rue De L'arbre St.-roch 69",
    "sg:city":"Oupeye",
    "sg:orig_category":"M\u00e9decins and sp\u00e9cialistes",
    "sg:phone":"+32 4 264 53 06",
    "sg:postcode":"4683",
    "sg:province":"Li\u00e8ge",
    "wof:name":"Victor Lenaers",
    "wof:placetype":"venue"
},
  "geometry": {"coordinates":[5.639881134,50.7023620605],"type":"Point"}
}