{
  "type": "Feature",
  "properties": {
    "addr:full":"Bellestraat 113 Affligem Vlaams-Brabant 1790",
    "addr:housenumber":"113",
    "addr:postcode":"1790",
    "addr:street":"Bellestraat",
    "iso:country":"BE",
    "sg:address":"Bellestraat 113",
    "sg:city":"Affligem",
    "sg:classifiers":[
        {
            "category":"Government",
            "subcategory":"Police Station",
            "type":"Public Place"
        }
    ],
    "sg:phone":"+32 53 66 70 55",
    "sg:postcode":"1790",
    "sg:province":"Vlaams-Brabant",
    "sg:tags":[
        "gendarmerie"
    ],
    "wof:name":"Federale Politie",
    "wof:placetype":"venue"
},
  "geometry": {"coordinates":[4.1105298996,50.8934288025],"type":"Point"}
}