{
  "type": "Feature",
  "properties": {
    "iso:country":"BE",
    "sg:address":"'s Boschstraat 32ba",
    "sg:city":"Hoogstraten",
    "sg:orig_category":"Herstellingen and onderhoud van auto's Voertuigen",
    "sg:phone":"+32 3 314 10 33",
    "sg:postcode":"2320",
    "sg:province":"Antwerpen",
    "wof:name":"Carrosserie Gibosch",
    "wof:placetype":"venue"
},
  "geometry": {"coordinates":[4.7712931633,51.406665802],"type":"Point"}
}