{
  "type": "Feature",
  "properties": {
    "addr:full":"Gilainstr 114-116 Tienen Vlaams-Brabant 3300",
    "addr:housenumber":"114-116",
    "addr:postcode":"3300",
    "iso:country":"BE",
    "sg:address":"Gilainstr 114-116",
    "sg:city":"Tienen",
    "sg:classifiers":[
        {
            "category":"Banks & Credit Unions",
            "subcategory":"Bank",
            "type":"Services"
        }
    ],
    "sg:phone":"+32 16 81 60 29",
    "sg:postcode":"3300",
    "sg:province":"Vlaams-Brabant",
    "wof:name":"Gemeentekrediet",
    "wof:placetype":"venue"
},
  "geometry": {"coordinates":[4.9348478317,50.8121147156],"type":"Point"}
}