{
  "type": "Feature",
  "properties": {
    "addr:full":"Rue Augustin-romain 7 Gembloux Namur 5030",
    "addr:housenumber":"7",
    "addr:postcode":"5030",
    "addr:street":"Rue Augustin-Romain;Namur",
    "iso:country":"BE",
    "sg:address":"Rue Augustin-romain 7",
    "sg:city":"Gembloux",
    "sg:orig_category":"Fleurs and plantes",
    "sg:phone":"+32 81 60 05 07",
    "sg:postcode":"5030",
    "sg:province":"Namur",
    "wof:name":"S.m.t.j.",
    "wof:placetype":"venue"
},
  "geometry": {"coordinates":[4.6805047989,50.5761222839],"type":"Point"}
}