{
  "type": "Feature",
  "properties": {
    "iso:country":"BE",
    "sg:address":"Tommel 9",
    "sg:city":"Baarle-hertog",
    "sg:orig_category":"Rundveehouders",
    "sg:phone":"+32 14 69 91 06",
    "sg:postcode":"2387",
    "sg:province":"Antwerpen",
    "wof:name":"Wilhelmus Martens",
    "wof:placetype":"venue"
},
  "geometry": {"coordinates":[4.9263710976,51.4335746765],"type":"Point"}
}