{
  "type": "Feature",
  "properties": {
    "iso:country":"BE",
    "sg:address":"Rue Saint-jacques 20",
    "sg:city":"Namur",
    "sg:classifiers":[
        {
            "category":"Shopping",
            "subcategory":"Clothing, Apparel, & Fashions",
            "type":"Retail Goods"
        }
    ],
    "sg:phone":"+32 81 22 81 33",
    "sg:postcode":"5000",
    "sg:province":"Namur",
    "sg:tags":[
        "v\u00eatements",
        "pour",
        "dame"
    ],
    "wof:name":"Maison Ballade",
    "wof:placetype":"venue"
},
  "geometry": {"coordinates":[4.8643670082,50.4651603699],"type":"Point"}
}