{
  "type": "Feature",
  "properties": {
    "addr:full":"Heiveldstraat 130 Gent Oost-Vlaanderen 9040",
    "addr:housenumber":"130",
    "addr:postcode":"9040",
    "addr:street":"Heiveldstraat;Oost-Vlaanderen",
    "iso:country":"BE",
    "sg:address":"Heiveldstraat 130",
    "sg:city":"Gent",
    "sg:orig_category":"Boucheries",
    "sg:phone":"+32 9 228 45 51",
    "sg:postcode":"9040",
    "sg:province":"Oost-Vlaanderen",
    "wof:name":"Jose Snoeck",
    "wof:placetype":"venue"
},
  "geometry": {"coordinates":[3.7568800449,51.0630569458],"type":"Point"}
}