{
  "type": "Feature",
  "properties": {
    "addr:full":"Chauss\u00c9e De Wavre 1727 Oudergem/auderghem Bruxelles-Capitale 1160",
    "addr:postcode":"1727;1160",
    "addr:street":"Chausse\u0301E De Wavre",
    "iso:country":"BE",
    "sg:address":"Chauss\u00c9e De Wavre 1727",
    "sg:city":"Oudergem/auderghem",
    "sg:orig_category":"Boucheries",
    "sg:phone":"+32 2 672 35 25",
    "sg:postcode":"1160",
    "sg:province":"Bruxelles-Capitale",
    "wof:name":"Boucherie Baltus",
    "wof:placetype":"venue"
},
  "geometry": {"coordinates":[4.4268350601,50.8163108826],"type":"Point"}
}