{
  "type": "Feature",
  "properties": {
    "addr:full":"Nieuwstraat 9ba Heuvelland West-Vlaanderen 8956",
    "addr:housenumber":"9ba",
    "addr:postcode":"8956",
    "addr:street":"Nieuwstraat",
    "iso:country":"BE",
    "sg:address":"Nieuwstraat 9ba",
    "sg:city":"Heuvelland",
    "sg:orig_category":"Banques and organismes de cr\u00e9dit",
    "sg:phone":"+32 57 44 57 31",
    "sg:postcode":"8956",
    "sg:province":"West-Vlaanderen",
    "wof:name":"Groep Argenta",
    "wof:placetype":"venue"
},
  "geometry": {"coordinates":[2.8284869194,50.7859725952],"type":"Point"}
}