{
  "type": "Feature",
  "properties": {
    "iso:country":"BE",
    "sg:address":"Rue Warihet 12",
    "sg:city":"Saint-georges-sur-meuse",
    "sg:orig_category":"Artistes ind\u00e9pendants",
    "sg:phone":"+32 4 259 54 93",
    "sg:postcode":"4470",
    "sg:province":"Li\u00e8ge",
    "wof:name":"M. Musin",
    "wof:placetype":"venue"
},
  "geometry": {"coordinates":[5.3504500389,50.5920410156],"type":"Point"}
}