{
  "type": "Feature",
  "properties": {
    "iso:country":"BE",
    "sg:address":"Rue De Labliau 28",
    "sg:city":"Silly (hoves)",
    "sg:classifiers":[
        {
            "category":"Building & Trades",
            "subcategory":"Plumbing",
            "type":"Services"
        }
    ],
    "sg:phone":"+32 2 395 83 94",
    "sg:postcode":"7830",
    "sg:province":"Hainaut",
    "sg:tags":[
        "contractor"
    ],
    "wof:name":"Denayer Ets",
    "wof:placetype":"venue"
},
  "geometry": {"coordinates":[4.0251588821,50.6718597412],"type":"Point"}
}