{
  "type": "Feature",
  "properties": {
    "iso:country":"BE",
    "sg:address":"Antwerpsesteenweg 31",
    "sg:city":"Aartselaar",
    "sg:classifiers":[
        {
            "category":"Fast Food",
            "type":"Food & Drink"
        }
    ],
    "sg:phone":"+32 3 887 22 77",
    "sg:postcode":"2630",
    "sg:province":"Antwerpen",
    "sg:tags":[
        "fried",
        "stand",
        "potato"
    ],
    "wof:name":"Schelde (de)",
    "wof:placetype":"venue"
},
  "geometry": {"coordinates":[4.3787927628,51.1429023743],"type":"Point"}
}