{
  "type": "Feature",
  "properties": {
    "addr:full":"Rue Haute 65 Hotton Luxembourg 6990",
    "addr:housenumber":"65",
    "addr:postcode":"6990",
    "addr:street":"Rue Haute",
    "iso:country":"BE",
    "sg:address":"Rue Haute 65",
    "sg:city":"Hotton",
    "sg:orig_category":"Schoonheidssalons",
    "sg:phone":"+32 84 46 69 97",
    "sg:postcode":"6990",
    "sg:province":"Luxembourg",
    "wof:name":"Institut La Chrysalide",
    "wof:placetype":"venue"
},
  "geometry": {"coordinates":[5.4556570053,50.2688865662],"type":"Point"}
}