{
  "type": "Feature",
  "properties": {
    "addr:full":"Nieveldriesweg 29 Aalst Oost-Vlaanderen 9310",
    "addr:housenumber":"29",
    "addr:postcode":"9310",
    "addr:street":"Nieveldriesweg",
    "iso:country":"BE",
    "sg:address":"Nieveldriesweg 29",
    "sg:city":"Aalst",
    "sg:orig_category":"Herstellingen and onderhoud van auto's",
    "sg:phone":"+32 53 66 88 75",
    "sg:postcode":"9310",
    "sg:province":"Oost-Vlaanderen",
    "wof:name":"Garage Everaert",
    "wof:placetype":"venue"
},
  "geometry": {"coordinates":[4.121450901,50.9270401001],"type":"Point"}
}