{
  "type": "Feature",
  "properties": {
    "addr:full":"Rue Aux Deux Croix 15 Aywaille Li\u00e8ge 4920",
    "addr:housenumber":"15",
    "addr:postcode":"4920",
    "addr:street":"Rue Aux Deux Croix",
    "iso:country":"BE",
    "sg:address":"Rue Aux Deux Croix 15",
    "sg:city":"Aywaille",
    "sg:classifiers":[
        {
            "category":"Autos & Motor Vehicles",
            "subcategory":"Motorcycle Sales",
            "type":"Retail Goods"
        }
    ],
    "sg:phone":"+32 4 384 64 53",
    "sg:postcode":"4920",
    "sg:province":"Li\u00e8ge",
    "sg:tags":[
        "scooter",
        "-",
        "moped"
    ],
    "wof:name":"Bernard L",
    "wof:placetype":"venue"
},
  "geometry": {"coordinates":[5.673620224,50.4717712402],"type":"Point"}
}