{
  "type": "Feature",
  "properties": {
    "iso:country":"BE",
    "sg:address":"Wollestraat 19",
    "sg:city":"Oostkamp",
    "sg:classifiers":[
        {
            "category":"Building & Trades",
            "subcategory":"Pest Control",
            "type":"Services"
        }
    ],
    "sg:phone":"+32 50 82 70 58",
    "sg:postcode":"8020",
    "sg:province":"West-Vlaanderen",
    "sg:tags":[
        "painting",
        "contractor"
    ],
    "wof:name":"Color Twist Bvba",
    "wof:placetype":"venue"
},
  "geometry": {"coordinates":[3.255245924,51.1388587952],"type":"Point"}
}