{
  "type": "Feature",
  "properties": {
    "addr:full":"Rue Fond Cattelain 5 Mont-Saint-Guibert 1435",
    "addr:housenumber":"5",
    "addr:postcode":"1435",
    "addr:street":"Rue Fond Cattelain;Mont-Saint-Guibert",
    "iso:country":"BE",
    "sg:address":"Rue Fond Cattelain 5",
    "sg:city":"Mont-Saint-Guibert",
    "sg:classifiers":[
        {
            "category":"Professional",
            "subcategory":"Computer Services",
            "type":"Services"
        }
    ],
    "sg:postcode":"1435",
    "sg:website":"http://www.whatever-company.com",
    "wof:name":"Whatever",
    "wof:placetype":"venue"
},
  "geometry": {"coordinates":[4.6260441,50.6577563],"type":"Point"}
}