{
  "type": "Feature",
  "properties": {
    "addr:full":"Herentalsebaan 454-456 Deurne Antwerpen 2100",
    "addr:housenumber":"454-456",
    "addr:postcode":"2100",
    "addr:street":"Herentalsebaan",
    "iso:country":"BE",
    "sg:address":"Herentalsebaan 454-456",
    "sg:city":"Deurne",
    "sg:orig_category":"Begrafeniswezen",
    "sg:phone":"+32 3 321 51 84",
    "sg:postcode":"2100",
    "sg:province":"Antwerpen",
    "wof:name":"Begrafenisonderneming C. Vranken",
    "wof:placetype":"venue"
},
  "geometry": {"coordinates":[4.470307827,51.2058334351],"type":"Point"}
}