{
  "type": "Feature",
  "properties": {
    "iso:country":"BE",
    "sg:address":"Alkenstraat 22",
    "sg:city":"Hasselt",
    "sg:orig_category":"Fietsen",
    "sg:phone":"+32 11 31 24 27",
    "sg:postcode":"3512",
    "sg:province":"Limburg",
    "wof:name":"Huis Vandevoort",
    "wof:placetype":"venue"
},
  "geometry": {"coordinates":[5.2488861084,50.9163131714],"type":"Point"}
}