{
  "type": "Feature",
  "properties": {
    "iso:country":"BE",
    "sg:address":"16 Av Du Port",
    "sg:city":"Bruxelles",
    "sg:classifiers":[
        {
            "category":"Manufacturing",
            "subcategory":"Chemicals & Compounds",
            "type":"Manufacturing & Wholesale Goods"
        }
    ],
    "sg:phone":"+32 2 421 27 11",
    "sg:postcode":"1080",
    "sg:province":"Bruxelles-Capitale",
    "sg:tags":[
        "pharmaceutical",
        "chemistry",
        "-",
        "by-product"
    ],
    "wof:name":"Henkel Belgium Schwarzkopf",
    "wof:placetype":"venue"
},
  "geometry": {"coordinates":[4.3477897644,50.8618659973],"type":"Point"}
}