{
  "type": "Feature",
  "properties": {
    "addr:full":"Blankenbergse Steenweg 247 Brugge West-Vlaanderen 8000",
    "addr:housenumber":"247",
    "addr:postcode":"8000",
    "addr:street":"Blankenbergse Steenweg",
    "iso:country":"BE",
    "sg:address":"Blankenbergse Steenweg 247",
    "sg:city":"Brugge",
    "sg:orig_category":"Newspapers, magazines, periodicals - Distribution",
    "sg:phone":"+32 50 31 39 60",
    "sg:postcode":"8000",
    "sg:province":"West-Vlaanderen",
    "wof:name":"Hoekske ('t)",
    "wof:placetype":"venue"
},
  "geometry": {"coordinates":[3.2012999058,51.2372512817],"type":"Point"}
}