{
  "type": "Feature",
  "properties": {
    "addr:full":"Oudenaardsesteenweg 86a Kortrijk West-Vlaanderen 8500",
    "addr:housenumber":"86a",
    "addr:postcode":"8500",
    "addr:street":"Oudenaardsesteenweg",
    "iso:country":"BE",
    "sg:address":"Oudenaardsesteenweg 86a",
    "sg:city":"Kortrijk",
    "sg:classifiers":[
        {
            "category":"Building & Trades",
            "subcategory":"Plumbing",
            "type":"Services"
        }
    ],
    "sg:phone":"+32 56 23 11 99",
    "sg:postcode":"8500",
    "sg:province":"West-Vlaanderen",
    "sg:tags":[
        "contractor"
    ],
    "wof:name":"Lood- En Zinkproductie Bvba",
    "wof:placetype":"venue"
},
  "geometry": {"coordinates":[3.2825200558,50.8207740784],"type":"Point"}
}