{
  "type": "Feature",
  "properties": {
    "iso:country":"BE",
    "sg:address":"Dorp 52",
    "sg:city":"Zoersel",
    "sg:classifiers":[
        {
            "category":"Health Services",
            "subcategory":"Health Practitioner",
            "type":"Services"
        }
    ],
    "sg:phone":"+32 3 309 99 08",
    "sg:postcode":"2980",
    "sg:province":"Antwerpen",
    "sg:tags":[
        "physiotherapist"
    ],
    "wof:name":"Vermeulen Ingrid",
    "wof:placetype":"venue"
},
  "geometry": {"coordinates":[4.7131299973,51.269317627],"type":"Point"}
}