{
  "type": "Feature",
  "properties": {
    "addr:full":"Koningin Astridlaan 2 Turnhout Antwerpen 2300",
    "addr:housenumber":"2",
    "addr:postcode":"2300",
    "addr:street":"Koningin Astridlaan",
    "iso:country":"BE",
    "sg:address":"Koningin Astridlaan 2",
    "sg:city":"Turnhout",
    "sg:orig_category":"Reisbureaus",
    "sg:phone":"+32 14 42 58 01",
    "sg:postcode":"2300",
    "sg:province":"Antwerpen",
    "wof:name":"Freetours International",
    "wof:placetype":"venue"
},
  "geometry": {"coordinates":[4.9257321358,51.3202209473],"type":"Point"}
}