{
  "type": "Feature",
  "properties": {
    "iso:country":"BE",
    "sg:address":"Kringloopstraat 1",
    "sg:city":"Maasmechelen",
    "sg:orig_category":"Beheer van afvalopslag- and stortplaatsen Huisvuilophaling and -verwerking",
    "sg:phone":"+32 89 65 85 26",
    "sg:postcode":"3630",
    "sg:province":"Limburg",
    "wof:name":"Containerpark Maasmechelen",
    "wof:placetype":"venue"
},
  "geometry": {"coordinates":[5.6248898506,50.9956893921],"type":"Point"}
}