{
  "type": "Feature",
  "properties": {
    "addr:full":"L\u00fctticher Strasse 265 Kelmis Li\u00e8ge 4720",
    "addr:housenumber":"265",
    "addr:postcode":"4720",
    "addr:street":"Luetticher Strasse",
    "iso:country":"BE",
    "sg:address":"L\u00fctticher Strasse 265",
    "sg:city":"Kelmis",
    "sg:classifiers":[
        {
            "category":"Shopping",
            "subcategory":"Pets & Pet Supplies",
            "type":"Retail Goods"
        }
    ],
    "sg:phone":"+32 87 65 91 65",
    "sg:postcode":"4720",
    "sg:province":"Li\u00e8ge",
    "sg:tags":[
        "shop",
        "-"
    ],
    "wof:name":"Zeevaert Monica-futter",
    "wof:placetype":"venue"
},
  "geometry": {"coordinates":[6.0148301125,50.7149848938],"type":"Point"}
}