{
  "type": "Feature",
  "properties": {
    "iso:country":"BE",
    "sg:address":"Sparrelaan 2a",
    "sg:city":"Diepenbeek",
    "sg:classifiers":[
        {
            "category":"Retail",
            "subcategory":"Auto Repair",
            "type":"Services"
        }
    ],
    "sg:phone":"+32 11 32 46 62",
    "sg:postcode":"3590",
    "sg:province":"Limburg",
    "sg:tags":[
        "garage"
    ],
    "wof:name":"Coeymans F",
    "wof:placetype":"venue"
},
  "geometry": {"coordinates":[5.4243688583,50.9322433472],"type":"Point"}
}