{
  "type": "Feature",
  "properties": {
    "addr:full":"Veldestraat 43 Nevele (merendree) Oost-Vlaanderen 9850",
    "addr:housenumber":"43",
    "addr:postcode":"9850",
    "addr:street":"Veldestraat",
    "iso:country":"BE",
    "sg:address":"Veldestraat 43",
    "sg:city":"Nevele (merendree)",
    "sg:classifiers":[
        {
            "category":"Home & Garden",
            "subcategory":"Kitchen Supply",
            "type":"Retail Goods"
        }
    ],
    "sg:phone":"+32 9 371 60 26",
    "sg:postcode":"9850",
    "sg:province":"Oost-Vlaanderen",
    "sg:tags":[
        "installation"
    ],
    "wof:name":"Geirnaert O",
    "wof:placetype":"venue"
},
  "geometry": {"coordinates":[3.5760989189,51.0767707825],"type":"Point"}
}