{
  "type": "Feature",
  "properties": {
    "iso:country":"BE",
    "sg:address":"Sint-martinusplein 34-36",
    "sg:city":"Genk",
    "sg:classifiers":[
        {
            "category":"Tea Room",
            "subcategory":"None",
            "type":"Food & Drink"
        }
    ],
    "sg:phone":"+32 89 36 28 80",
    "sg:postcode":"3600",
    "sg:province":"Limburg",
    "wof:name":"Poels",
    "wof:placetype":"venue"
},
  "geometry": {"coordinates":[5.4932031631,50.9680938721],"type":"Point"}
}