{
  "type": "Feature",
  "properties": {
    "iso:country":"BE",
    "sg:address":"Dendermondsesteenweg 136",
    "sg:city":"Gent",
    "sg:classifiers":[
        {
            "category":"Professional",
            "subcategory":"Management & Consulting",
            "type":"Services"
        }
    ],
    "sg:phone":"+32 9 229 23 75",
    "sg:postcode":"9000",
    "sg:province":"Oost-Vlaanderen",
    "sg:tags":[
        "marketing",
        "-",
        "consultant"
    ],
    "wof:name":"Grami Consulting",
    "wof:placetype":"venue"
},
  "geometry": {"coordinates":[3.743434906,51.0537147522],"type":"Point"}
}