{
  "type": "Feature",
  "properties": {
    "iso:country":"BE",
    "sg:address":"Dokter Verhaeghestraat 107",
    "sg:city":"Oostende",
    "sg:orig_category":"Studios photographiques",
    "sg:phone":"+32 59 70 96 04",
    "sg:postcode":"8400",
    "sg:province":"West-Vlaanderen",
    "wof:name":"Patrick Pottier",
    "wof:placetype":"venue"
},
  "geometry": {"coordinates":[2.895827055,51.2180862427],"type":"Point"}
}