{
  "type": "Feature",
  "properties": {
    "iso:country":"BE",
    "sg:address":"Nieuwstraat 21",
    "sg:city":"Mol",
    "sg:classifiers":[
        {
            "category":"Insurance",
            "subcategory":"Insurance Agent",
            "type":"Services"
        }
    ],
    "sg:phone":"+32 14 31 31 29",
    "sg:postcode":"2400",
    "sg:province":"Antwerpen",
    "sg:tags":[
        "broker"
    ],
    "wof:name":"Leysen-van Bael Verzekeringen Bvba",
    "wof:placetype":"venue"
},
  "geometry": {"coordinates":[5.1145739555,51.1836624146],"type":"Point"}
}