{
  "type": "Feature",
  "properties": {
    "iso:country":"BE",
    "sg:address":"Meerlaan 32",
    "sg:city":"Knokke-heist",
    "sg:orig_category":"Biblioth\u00e8ques and archives publiques",
    "sg:phone":"+32 50 63 04 00",
    "sg:postcode":"8300",
    "sg:province":"West-Vlaanderen",
    "wof:name":"Speel-o-theek De Wip",
    "wof:placetype":"venue"
},
  "geometry": {"coordinates":[3.2786049843,51.3431396484],"type":"Point"}
}