{
  "type": "Feature",
  "properties": {
    "iso:country":"BE",
    "sg:address":"Drie-engelenberg 6",
    "sg:city":"Leuven",
    "sg:orig_category":"Geschenken and souvenirs Verlichting and huishoudartikelen",
    "sg:phone":"+32 16 23 27 79",
    "sg:postcode":"3000",
    "sg:province":"Vlaams-Brabant",
    "wof:name":"Oxin",
    "wof:placetype":"venue"
},
  "geometry": {"coordinates":[4.6995000839,50.8784713745],"type":"Point"}
}