{
  "type": "Feature",
  "properties": {
    "iso:country":"BE",
    "sg:address":"Pontdeeklaan 59",
    "sg:city":"Zellik",
    "sg:classifiers":[
        {
            "category":"Professional",
            "subcategory":"Printing & Photocopies",
            "type":"Services"
        }
    ],
    "sg:phone":"+32 2 481 86 86",
    "sg:postcode":"1731",
    "sg:province":"Vlaams-Brabant",
    "sg:tags":[
        "machine",
        "engineering",
        "-",
        "mechanical"
    ],
    "wof:name":"Hermes Graphics Sa",
    "wof:placetype":"venue"
},
  "geometry": {"coordinates":[4.2953419685,50.8799438477],"type":"Point"}
}