{
  "type": "Feature",
  "properties": {
    "addr:full":"Brugsesteenweg 90 Roeselare West-Vlaanderen 8800",
    "addr:housenumber":"90",
    "addr:postcode":"8800",
    "addr:street":"Brugsesteenweg",
    "iso:country":"BE",
    "sg:address":"Brugsesteenweg 90",
    "sg:city":"Roeselare",
    "sg:classifiers":[
        {
            "category":"Health Services",
            "subcategory":"Hospital",
            "type":"Services"
        }
    ],
    "sg:phone":"+32 51 23 61 11",
    "sg:postcode":"8800",
    "sg:province":"West-Vlaanderen",
    "wof:name":"Stedelijk Ziekenhuis Roeselare",
    "wof:placetype":"venue"
},
  "geometry": {"coordinates":[3.1221129894,50.9538230896],"type":"Point"}
}