{
  "type": "Feature",
  "properties": {
    "addr:full":"Chauss\u00c9e De Bruxelles 53 Charleroi Hainaut 6042",
    "addr:housenumber":"53",
    "addr:postcode":"6042",
    "addr:street":"Chausse\u0301E De Bruxelles;Hainaut",
    "iso:country":"BE",
    "sg:address":"Chauss\u00c9e De Bruxelles 53",
    "sg:city":"Charleroi",
    "sg:orig_category":"Meubles D\u00e9taillants, Am\u00e9nagement de B\u00e2timents et de Cuisines",
    "sg:phone":"+32 71 32 50 64",
    "sg:postcode":"6042",
    "sg:province":"Hainaut",
    "wof:name":"Joseph Bal",
    "wof:placetype":"venue"
},
  "geometry": {"coordinates":[4.439221859,50.436920166],"type":"Point"}
}