{
  "type": "Feature",
  "properties": {
    "iso:country":"BE",
    "sg:address":"Weverslaan 12",
    "sg:city":"Lokeren",
    "sg:orig_category":"Imprimeries and copyshops",
    "sg:phone":"+32 9 348 54 32",
    "sg:postcode":"9160",
    "sg:province":"Oost-Vlaanderen",
    "wof:name":"C. De Landtsheer",
    "wof:placetype":"venue"
},
  "geometry": {"coordinates":[4.0159831047,51.1084060669],"type":"Point"}
}