{
  "type": "Feature",
  "properties": {
    "iso:country":"BE",
    "sg:address":"Avenue Du Vert Bocage 15",
    "sg:city":"Waterloo",
    "sg:classifiers":[
        {
            "category":"Professional",
            "subcategory":"Accounting & Tax Preparation",
            "type":"Services"
        }
    ],
    "sg:phone":"+32 2 354 15 68",
    "sg:postcode":"1410",
    "sg:province":"Brabant Wallon",
    "sg:tags":[
        "accountant"
    ],
    "wof:name":"Vermeire J-p",
    "wof:placetype":"venue"
},
  "geometry": {"coordinates":[4.3923802376,50.7280349731],"type":"Point"}
}