{
  "type": "Feature",
  "properties": {
    "addr:full":"Rue De La Loi 28 Manage Hainaut 7170",
    "addr:housenumber":"28",
    "addr:postcode":"7170",
    "addr:street":"Rue De La Loi",
    "iso:country":"BE",
    "sg:address":"Rue De La Loi 28",
    "sg:city":"Manage",
    "sg:classifiers":[
        {
            "category":"Arena",
            "subcategory":"Sports Club",
            "type":"Entertainment"
        }
    ],
    "sg:phone":"+32 64 26 51 39",
    "sg:postcode":"7170",
    "sg:province":"Hainaut",
    "sg:tags":[
        "de"
    ],
    "wof:name":"Orca Diving Club",
    "wof:placetype":"venue"
},
  "geometry": {"coordinates":[4.2352671623,50.475944519],"type":"Point"}
}