{
  "type": "Feature",
  "properties": {
    "iso:country":"BE",
    "sg:address":"Katwilgweg 4b5",
    "sg:city":"Antwerpen",
    "sg:orig_category":"Agences d'exp\u00e9dition",
    "sg:phone":"+32 3 250 10 77",
    "sg:postcode":"2050",
    "sg:province":"Antwerpen",
    "wof:name":"Universal Shipping",
    "wof:placetype":"venue"
},
  "geometry": {"coordinates":[4.3595848083,51.217376709],"type":"Point"}
}