{
  "type": "Feature",
  "properties": {
    "addr:full":"Reigersstraat 19 Lochristi (beervelde) Oost-Vlaanderen 9080",
    "addr:housenumber":"19",
    "addr:postcode":"9080",
    "addr:street":"Reigersstraat",
    "iso:country":"BE",
    "sg:address":"Reigersstraat 19",
    "sg:city":"Lochristi (beervelde)",
    "sg:classifiers":[
        {
            "category":"Wholesale",
            "subcategory":"Plants",
            "type":"Manufacturing & Wholesale Goods"
        }
    ],
    "sg:phone":"+32 9 355 54 21",
    "sg:postcode":"9080",
    "sg:province":"Oost-Vlaanderen",
    "sg:tags":[
        "whol",
        "flower",
        "-",
        "grower"
    ],
    "wof:name":"De Vos D",
    "wof:placetype":"venue"
},
  "geometry": {"coordinates":[3.8416819572,51.0600280762],"type":"Point"}
}