{
  "type": "Feature",
  "properties": {
    "addr:full":"Rue Du Lombard 34-42 Bruxelles Bruxelles-Capitale 1000",
    "addr:postcode":"34-42;1000",
    "addr:street":"Rue Du Lombard",
    "iso:country":"BE",
    "sg:address":"Rue Du Lombard 34-42",
    "sg:city":"Bruxelles",
    "sg:classifiers":[
        {
            "category":"Organizations",
            "subcategory":"Professional Association",
            "type":"Services"
        }
    ],
    "sg:phone":"+32 2 545 57 05",
    "sg:postcode":"1000",
    "sg:province":"Bruxelles-Capitale",
    "sg:tags":[
        "trade-union",
        "federation"
    ],
    "wof:name":"Confederatie Bouw-vlaamse Schrijnwerkers",
    "wof:placetype":"venue"
},
  "geometry": {"coordinates":[4.3510780334,50.8455467224],"type":"Point"}
}