{
  "type": "Feature",
  "properties": {
    "addr:full":"Rue D'anthisnes 31 Hamoir (comblain-fairon) Li\u00e8ge 4180",
    "addr:housenumber":"31",
    "addr:postcode":"4180",
    "addr:street":"Rue D'Anthisnes;Comblain-Fairon",
    "iso:country":"BE",
    "sg:address":"Rue D'anthisnes 31",
    "sg:city":"Hamoir (comblain-fairon)",
    "sg:classifiers":[
        {
            "category":"Bakery",
            "type":"Food & Drink"
        }
    ],
    "sg:phone":"+32 86 38 81 62",
    "sg:postcode":"4180",
    "sg:province":"Li\u00e8ge",
    "sg:tags":[
        "confectioner",
        "baker"
    ],
    "wof:name":"Gilis F",
    "wof:placetype":"venue"
},
  "geometry": {"coordinates":[5.5381917953,50.4487266541],"type":"Point"}
}