{
  "type": "Feature",
  "properties": {
    "iso:country":"BE",
    "sg:address":"Rue Du Val D'awirs 12",
    "sg:city":"Engis",
    "sg:classifiers":[
        {
            "category":"Personal",
            "subcategory":"Beauty Salon",
            "type":"Services"
        }
    ],
    "sg:phone":"+32 4 275 08 64",
    "sg:postcode":"4480",
    "sg:province":"Li\u00e8ge",
    "sg:tags":[
        "de",
        "coiffure"
    ],
    "wof:name":"Daniele Comhaire",
    "wof:placetype":"venue"
},
  "geometry": {"coordinates":[5.4134287834,50.5876159668],"type":"Point"}
}