{
  "type": "Feature",
  "properties": {
    "addr:full":"Vieux Tauves 108 Andenne Namur 5300",
    "addr:housenumber":"108",
    "addr:postcode":"5300",
    "iso:country":"BE",
    "sg:address":"Vieux Tauves 108",
    "sg:city":"Andenne",
    "sg:orig_category":"G\u00e2teaux, p\u00e2tisserie and biscuits Fab. Producteurs de fruits",
    "sg:phone":"+32 85 61 17 73",
    "sg:postcode":"5300",
    "sg:province":"Namur",
    "wof:name":"Les Vergers Vieuxtauves",
    "wof:placetype":"venue"
},
  "geometry": {"coordinates":[5.1213750839,50.4588546753],"type":"Point"}
}