{
  "type": "Feature",
  "properties": {
    "addr:full":"Stalenstraat 148 Genk Limburg 3600",
    "addr:housenumber":"148",
    "addr:postcode":"3600",
    "addr:street":"Stalenstraat",
    "iso:country":"BE",
    "sg:address":"Stalenstraat 148",
    "sg:city":"Genk",
    "sg:orig_category":"V\u00e9hicules automobiles",
    "sg:phone":"+32 89 38 02 66",
    "sg:postcode":"3600",
    "sg:province":"Limburg",
    "wof:name":"Hermans Etablissementen",
    "wof:placetype":"venue"
},
  "geometry": {"coordinates":[5.5151281357,50.9919891357],"type":"Point"}
}