{
  "type": "Feature",
  "properties": {
    "addr:full":"Eernegemstraat 12 Ichtegem West-Vlaanderen 8480",
    "addr:housenumber":"12",
    "addr:postcode":"8480",
    "addr:street":"Eernegemstraat",
    "iso:country":"BE",
    "sg:address":"Eernegemstraat 12",
    "sg:city":"Ichtegem",
    "sg:orig_category":"Rundveehouders Varkenskwekers",
    "sg:phone":"+32 51 58 87 32",
    "sg:postcode":"8480",
    "sg:province":"West-Vlaanderen",
    "wof:name":"Marcel Beernaert",
    "wof:placetype":"venue"
},
  "geometry": {"coordinates":[3.0104839802,51.109413147],"type":"Point"}
}