{
  "type": "Feature",
  "properties": {
    "addr:full":"Rue De La Station 16 Beloeil (stambruges) Hainaut 7973",
    "addr:housenumber":"16",
    "addr:postcode":"7973",
    "addr:street":"Rue De La Station",
    "iso:country":"BE",
    "sg:address":"Rue De La Station 16",
    "sg:city":"Beloeil (stambruges)",
    "sg:classifiers":[
        {
            "category":"Professional",
            "subcategory":"Business Services",
            "type":"Services"
        }
    ],
    "sg:phone":"+32 69 56 08 82",
    "sg:postcode":"7973",
    "sg:province":"Hainaut",
    "sg:tags":[
        "bookkeeping"
    ],
    "wof:name":"Huvelle M",
    "wof:placetype":"venue"
},
  "geometry": {"coordinates":[3.6938509941,50.5069580078],"type":"Point"}
}