{
  "type": "Feature",
  "properties": {
    "addr:full":"Perreveld 36a Opwijk Vlaams-Brabant 1745",
    "addr:housenumber":"36a",
    "addr:postcode":"1745",
    "addr:street":"Perreveld",
    "iso:country":"BE",
    "sg:address":"Perreveld 36a",
    "sg:city":"Opwijk",
    "sg:classifiers":[
        {
            "category":"Shopping",
            "subcategory":"Used Merchandise",
            "type":"Retail Goods"
        }
    ],
    "sg:phone":"+32 52 35 07 69",
    "sg:postcode":"1745",
    "sg:province":"Vlaams-Brabant",
    "sg:tags":[
        "salvage",
        "surplus"
    ],
    "wof:name":"Chiep",
    "wof:placetype":"venue"
},
  "geometry": {"coordinates":[4.1689958572,50.9618301392],"type":"Point"}
}