{
  "type": "Feature",
  "properties": {
    "addr:full":"Molenbergstraat 43 Herselt Antwerpen 2230",
    "addr:housenumber":"43",
    "addr:postcode":"2230",
    "addr:street":"Molenbergstraat",
    "iso:country":"BE",
    "sg:address":"Molenbergstraat 43",
    "sg:city":"Herselt",
    "sg:orig_category":"Rev\u00eatements de sols and murs. Meubles D\u00e9taillants, Am\u00e9nagement de B\u00e2timents et de Cuisines. Installa",
    "sg:phone":"+32 14 54 78 34",
    "sg:postcode":"2230",
    "sg:province":"Antwerpen",
    "wof:name":"Wynants",
    "wof:placetype":"venue"
},
  "geometry": {"coordinates":[4.8846588135,51.0507507324],"type":"Point"}
}