{
  "type": "Feature",
  "properties": {
    "addr:full":"Givry 1153 Bertogne Luxembourg 6686",
    "addr:postcode":"1153;6686",
    "addr:street":"Givry",
    "iso:country":"BE",
    "sg:address":"Givry 1153",
    "sg:city":"Bertogne",
    "sg:orig_category":"Electrom\u00e9nager, t\u00e9l\u00e9visions and radios. R\u00e9parations d'appareils \u00e9lectrom\u00e9nagers",
    "sg:phone":"+32 61 21 20 51",
    "sg:postcode":"6686",
    "sg:province":"Luxembourg",
    "wof:name":"R. Bleret",
    "wof:placetype":"venue"
},
  "geometry": {"coordinates":[5.6022458076,50.0324134827],"type":"Point"}
}