{
  "type": "Feature",
  "properties": {
    "iso:country":"BE",
    "sg:address":"Hoekskenstraat 19ba",
    "sg:city":"Aalst",
    "sg:orig_category":"Koerierbedrijven",
    "sg:phone":"+32 53 71 15 81",
    "sg:postcode":"9310",
    "sg:province":"Oost-Vlaanderen",
    "wof:name":"Blue Arrow",
    "wof:placetype":"venue"
},
  "geometry": {"coordinates":[4.0939321518,50.9626579285],"type":"Point"}
}