{
  "type": "Feature",
  "properties": {
    "addr:full":"Pellenbergstraat 1 Bierbeek Vlaams-Brabant 3360",
    "addr:housenumber":"1",
    "addr:postcode":"3360",
    "addr:street":"Pellenbergstraat",
    "iso:country":"BE",
    "sg:address":"Pellenbergstraat 1",
    "sg:city":"Bierbeek",
    "sg:orig_category":"Eleveurs de bovins",
    "sg:phone":"+32 16 46 05 49",
    "sg:postcode":"3360",
    "sg:province":"Vlaams-Brabant",
    "wof:name":"Ernest Defilette",
    "wof:placetype":"venue"
},
  "geometry": {"coordinates":[4.7814221382,50.8584442139],"type":"Point"}
}