{
  "type": "Feature",
  "properties": {
    "addr:full":"Moorsledestraat 140 Brussel/bruxelles Bruxelles-Capitale 1020",
    "addr:housenumber":"140",
    "addr:postcode":"1020",
    "addr:street":"Moorsledestraat;/",
    "iso:country":"BE",
    "sg:address":"Moorsledestraat 140",
    "sg:city":"Brussel/bruxelles",
    "sg:orig_category":"Beheer onroerend goed",
    "sg:phone":"+32 2 428 25 54",
    "sg:postcode":"1020",
    "sg:province":"Bruxelles-Capitale",
    "wof:name":"Gerance D'immeubles",
    "wof:placetype":"venue"
},
  "geometry": {"coordinates":[4.3487071991,50.8727798462],"type":"Point"}
}