{
  "type": "Feature",
  "properties": {
    "iso:country":"BE",
    "sg:address":"Sint-corynstraat 5",
    "sg:city":"Lo-reninge",
    "sg:orig_category":"Eleveurs and marchands de porcs",
    "sg:phone":"+32 57 40 02 07",
    "sg:postcode":"8647",
    "sg:province":"West-Vlaanderen",
    "wof:name":"Karel Devreese",
    "wof:placetype":"venue"
},
  "geometry": {"coordinates":[2.7757530212,50.9328193665],"type":"Point"}
}