{
  "type": "Feature",
  "properties": {
    "iso:country":"BE",
    "sg:address":"Grote Baan 143",
    "sg:city":"Hulshout",
    "sg:classifiers":[
        {
            "category":"Cafe",
            "type":"Food & Drink"
        }
    ],
    "sg:phone":"+32 15 22 26 26",
    "sg:postcode":"2235",
    "sg:province":"Antwerpen",
    "sg:tags":[
        "caf\u00e9s"
    ],
    "wof:name":"Caf\u00c9 Baccara",
    "wof:placetype":"venue"
},
  "geometry": {"coordinates":[4.7943210602,51.0748100281],"type":"Point"}
}