{
  "type": "Feature",
  "properties": {
    "addr:full":"Gentsesteenweg 88 Wetteren Oost-Vlaanderen 9230",
    "addr:housenumber":"88",
    "addr:postcode":"9230",
    "addr:street":"Gentsesteenweg",
    "iso:country":"BE",
    "sg:address":"Gentsesteenweg 88",
    "sg:city":"Wetteren",
    "sg:orig_category":"Openbare veiligheid",
    "sg:phone":"+32 9 369 02 13",
    "sg:postcode":"9230",
    "sg:province":"Oost-Vlaanderen",
    "wof:name":"Federale Politie",
    "wof:placetype":"venue"
},
  "geometry": {"coordinates":[3.8721020222,51.000617981],"type":"Point"}
}