{
  "type": "Feature",
  "properties": {
    "addr:full":"Lombeekstraat 88 Affligem (essene) Vlaams-Brabant 1790",
    "addr:housenumber":"88",
    "addr:postcode":"1790",
    "addr:street":"Lombeekstraat",
    "iso:country":"BE",
    "sg:address":"Lombeekstraat 88",
    "sg:city":"Affligem (essene)",
    "sg:classifiers":[
        {
            "category":"Professional",
            "type":"Services"
        }
    ],
    "sg:phone":"+32 2 582 22 03",
    "sg:postcode":"1790",
    "sg:province":"Vlaams-Brabant",
    "sg:tags":[
        "surveyor",
        "-",
        "valuer"
    ],
    "wof:name":"R-d Scientific Consulting",
    "wof:placetype":"venue"
},
  "geometry": {"coordinates":[4.1367950439,50.8911743164],"type":"Point"}
}