{
  "type": "Feature",
  "properties": {
    "iso:country":"BE",
    "sg:address":"Dunberg 64",
    "sg:city":"Lubbeek",
    "sg:classifiers":[
        {
            "category":"Health Services",
            "subcategory":"Health Practitioner",
            "type":"Services"
        }
    ],
    "sg:phone":"+32 16 62 21 67",
    "sg:postcode":"3210",
    "sg:province":"Vlaams-Brabant",
    "sg:tags":[
        "physiotherapist"
    ],
    "wof:name":"Derveaux R",
    "wof:placetype":"venue"
},
  "geometry": {"coordinates":[4.8223152161,50.8926887512],"type":"Point"}
}