{
  "type": "Feature",
  "properties": {
    "iso:country":"BE",
    "sg:address":"Rue Du Cou\u00cbt 67",
    "sg:city":"Moeskroen/mouscron",
    "sg:orig_category":"Drogueries. Rev\u00eatements pour sols and murs. Peinture",
    "sg:phone":"+32 56 33 22 34",
    "sg:postcode":"7700",
    "sg:province":"Hainaut",
    "wof:name":"Verdonck G.",
    "wof:placetype":"venue"
},
  "geometry": {"coordinates":[3.2323200703,50.7400932312],"type":"Point"}
}