{
  "type": "Feature",
  "properties": {
    "addr:full":"Chauss\u00c9e Du Roeulx 302 Mons Hainaut 7000",
    "addr:housenumber":"302",
    "addr:postcode":"7000",
    "addr:street":"Chausse\u0301E Du Roeulx;Hainaut",
    "iso:country":"BE",
    "sg:address":"Chauss\u00c9e Du Roeulx 302",
    "sg:city":"Mons",
    "sg:orig_category":"Herstellingen and onderhoud aan huis voor voertuigen Metaalafval, schrootrecyclage and sloperijen",
    "sg:phone":"+32 65 84 08 95",
    "sg:postcode":"7000",
    "sg:province":"Hainaut",
    "wof:name":"D\u00c9pannage N.r.j.",
    "wof:placetype":"venue"
},
  "geometry": {"coordinates":[3.9841899872,50.456817627],"type":"Point"}
}