{
  "type": "Feature",
  "properties": {
    "addr:full":"Avenue Des Ardennes 34 Huy Li\u00e8ge 4500",
    "addr:housenumber":"34",
    "addr:postcode":"4500",
    "addr:street":"Avenue Des Ardennes",
    "iso:country":"BE",
    "sg:address":"Avenue Des Ardennes 34",
    "sg:city":"Huy",
    "sg:orig_category":"Banques and organismes de cr\u00e9dit",
    "sg:phone":"+32 85 27 02 11",
    "sg:postcode":"4500",
    "sg:province":"Li\u00e8ge",
    "wof:name":"Cr\u00c9dit G\u00c9n\u00c9rale De Banque",
    "wof:placetype":"venue"
},
  "geometry": {"coordinates":[5.2400760651,50.5171318054],"type":"Point"}
}