{
  "type": "Feature",
  "properties": {
    "addr:full":"Hoog Kallostraat 13a Beveren (kallo) Oost-Vlaanderen 9120",
    "addr:housenumber":"13a",
    "addr:postcode":"9120",
    "addr:street":"Hoog Kallostraat",
    "iso:country":"BE",
    "sg:address":"Hoog Kallostraat 13a",
    "sg:city":"Beveren (kallo)",
    "sg:classifiers":[
        {
            "category":"Transit Center",
            "subcategory":"Freight",
            "type":"Transportation"
        }
    ],
    "sg:phone":"+32 3 575 53 13",
    "sg:postcode":"9120",
    "sg:province":"Oost-Vlaanderen",
    "sg:tags":[
        "import",
        "export",
        "-"
    ],
    "wof:name":"Tcb",
    "wof:placetype":"venue"
},
  "geometry": {"coordinates":[4.2592120171,51.2169952393],"type":"Point"}
}