{
  "type": "Feature",
  "properties": {
    "iso:country":"BE",
    "sg:address":"Rue De La Couronne 6-8",
    "sg:city":"Mons",
    "sg:orig_category":"Grossistes divers. Articles m\u00e9talliques ouvr\u00e9s divers Fab. Articles divers Fab. Composition and phot",
    "sg:phone":"+32 65 31 68 15",
    "sg:postcode":"7000",
    "sg:province":"Hainaut",
    "wof:name":"Verhaegen",
    "wof:placetype":"venue"
},
  "geometry": {"coordinates":[3.9511449337,50.4528198242],"type":"Point"}
}