{
  "type": "Feature",
  "properties": {
    "addr:full":"Rue Des Vergers 16 Esneux Li\u00e8ge 4130",
    "addr:housenumber":"16",
    "addr:postcode":"4130",
    "addr:street":"Rue Des Vergers",
    "iso:country":"BE",
    "sg:address":"Rue Des Vergers 16",
    "sg:city":"Esneux",
    "sg:orig_category":"Plomberie, chauffage and installations sanitaires",
    "sg:phone":"+32 4 380 37 12",
    "sg:postcode":"4130",
    "sg:province":"Li\u00e8ge",
    "wof:name":"Paul Hoornaert",
    "wof:placetype":"venue"
},
  "geometry": {"coordinates":[5.5741372108,50.5413551331],"type":"Point"}
}