{
  "type": "Feature",
  "properties": {
    "addr:full":"Rue De Brabant 122 Chatelineau Hainaut 6200",
    "addr:housenumber":"122",
    "addr:postcode":"6200",
    "addr:street":"Rue De Brabant;Hainaut",
    "iso:country":"BE",
    "sg:address":"Rue De Brabant 122",
    "sg:city":"Chatelineau",
    "sg:orig_category":"Airconditioning and ventilatie Loodgieterij, verwarming and sanitaire installaties Viessmann",
    "sg:phone":"+32 71 39 39 29",
    "sg:postcode":"6200",
    "sg:province":"Hainaut",
    "wof:name":"Topcalor",
    "wof:placetype":"venue"
},
  "geometry": {"coordinates":[4.5186247826,50.4395866394],"type":"Point"}
}