{
  "type": "Feature",
  "properties": {
    "iso:country":"BE",
    "sg:address":"Rue Du Maquis 122",
    "sg:city":"Ronse/renaix",
    "sg:orig_category":"Rev\u00eatements pour sols and murs. Peinture",
    "sg:phone":"+32 55 21 83 39",
    "sg:postcode":"9600",
    "sg:province":"Oost-Vlaanderen",
    "wof:name":"Albert De Vlieger",
    "wof:placetype":"venue"
},
  "geometry": {"coordinates":[3.5992999077,50.7470397949],"type":"Point"}
}