{
  "type": "Feature",
  "properties": {
    "iso:country":"BE",
    "sg:address":"Wannegem-ledestraat 34a",
    "sg:city":"Kruishoutem (wannegem-lede)",
    "sg:classifiers":[
        {
            "category":"Professional",
            "subcategory":"Computer Services",
            "type":"Services"
        }
    ],
    "sg:phone":"+32 9 383 84 56",
    "sg:postcode":"9772",
    "sg:province":"Oost-Vlaanderen",
    "sg:tags":[
        "-",
        "processing",
        "data",
        "software"
    ],
    "wof:name":"Solid Systems Bvba",
    "wof:placetype":"venue"
},
  "geometry": {"coordinates":[3.5634899139,50.8897514343],"type":"Point"}
}