{
  "type": "Feature",
  "properties": {
    "addr:full":"Koevliet 1ba Zele Oost-Vlaanderen 9240",
    "addr:postcode":"9240",
    "addr:street":"Koevliet;Oost-Vlaanderen",
    "iso:country":"BE",
    "sg:address":"Koevliet 1ba",
    "sg:city":"Zele",
    "sg:orig_category":"Enseignement maternel and primaire",
    "sg:phone":"+32 52 44 69 31",
    "sg:postcode":"9240",
    "sg:province":"Oost-Vlaanderen",
    "wof:name":"Vrije Lagere School",
    "wof:placetype":"venue"
},
  "geometry": {"coordinates":[4.0262551308,51.0664215088],"type":"Point"}
}