{
  "type": "Feature",
  "properties": {
    "addr:full":"Rue Jules Des Essarts 92 Ch\u00e2telet (ch\u00e2telineau) Hainaut 6200",
    "addr:housenumber":"92",
    "addr:postcode":"6200",
    "addr:street":"Rue Jules Des Essarts",
    "iso:country":"BE",
    "sg:address":"Rue Jules Des Essarts 92",
    "sg:city":"Ch\u00e2telet (ch\u00e2telineau)",
    "sg:classifiers":[
        {
            "category":"Shopping",
            "subcategory":"Musical Instruments",
            "type":"Retail Goods"
        }
    ],
    "sg:phone":"+32 71 38 86 08",
    "sg:postcode":"6200",
    "sg:province":"Hainaut",
    "sg:tags":[
        "-"
    ],
    "wof:name":"Tecno-music",
    "wof:placetype":"venue"
},
  "geometry": {"coordinates":[4.5196700096,50.4163818359],"type":"Point"}
}