{
  "type": "Feature",
  "properties": {
    "iso:country":"BE",
    "sg:address":"Rue Albert De T'serclaes 64",
    "sg:city":"Dison",
    "sg:orig_category":"Centres de relaxation and bien-\u00eatre. Instituts de beaut\u00e9",
    "sg:phone":"+32 87 31 24 03",
    "sg:postcode":"4821",
    "sg:province":"Li\u00e8ge",
    "wof:name":"Institut Evelyne",
    "wof:placetype":"venue"
},
  "geometry": {"coordinates":[5.8650021553,50.601348877],"type":"Point"}
}