{
  "type": "Feature",
  "properties": {
    "addr:full":"Rue Du Bout De La Haut 283 Quaregnon Hainaut 7390",
    "addr:housenumber":"283",
    "addr:postcode":"7390",
    "addr:street":"Rue Du Bout De La Haut",
    "iso:country":"BE",
    "sg:address":"Rue Du Bout De La Haut 283",
    "sg:city":"Quaregnon",
    "sg:orig_category":"Artsen and specialisten",
    "sg:phone":"+32 65 67 67 58",
    "sg:postcode":"7390",
    "sg:province":"Hainaut",
    "wof:name":"Jean-marc Magy",
    "wof:placetype":"venue"
},
  "geometry": {"coordinates":[3.8705370426,50.4174804688],"type":"Point"}
}