{
  "type": "Feature",
  "properties": {
    "iso:country":"BE",
    "sg:address":"Brusselsesteenweg 14",
    "sg:city":"Wetteren",
    "sg:orig_category":"Pharmaciens",
    "sg:phone":"+32 9 252 16 64",
    "sg:postcode":"9230",
    "sg:province":"Oost-Vlaanderen",
    "wof:name":"Erna Claeys",
    "wof:placetype":"venue"
},
  "geometry": {"coordinates":[3.8451399803,50.9841995239],"type":"Point"}
}