{
  "type": "Feature",
  "properties": {
    "addr:full":"Dessus-de-la-ville 4 Couvin Namur 5660",
    "addr:housenumber":"4",
    "addr:postcode":"5660",
    "addr:street":"Dessus-De-La-Ville",
    "iso:country":"BE",
    "sg:address":"Dessus-de-la-ville 4",
    "sg:city":"Couvin",
    "sg:classifiers":[
        {
            "category":"Insurance",
            "subcategory":"Insurance Agent",
            "type":"Services"
        }
    ],
    "sg:phone":"+32 60 34 40 78",
    "sg:postcode":"5660",
    "sg:province":"Namur",
    "sg:tags":[
        "verzekeringsmakelaars",
        "expert"
    ],
    "wof:name":"Louis Mathieux",
    "wof:placetype":"venue"
},
  "geometry": {"coordinates":[4.4909648895,50.0502090454],"type":"Point"}
}