{
  "type": "Feature",
  "properties": {
    "addr:full":"Rue Saint-henri 89 Bruxelles (woluwe-saint-lambert) Bruxelles-Capitale 1200",
    "addr:housenumber":"89",
    "addr:postcode":"1200",
    "addr:street":"Rue Saint-Henri",
    "iso:country":"BE",
    "sg:address":"Rue Saint-henri 89",
    "sg:city":"Bruxelles (woluwe-saint-lambert)",
    "sg:classifiers":[
        {
            "category":"Organizations",
            "subcategory":"Community Association",
            "type":"Services"
        }
    ],
    "sg:phone":"+32 2 733 58 35",
    "sg:postcode":"1200",
    "sg:province":"Bruxelles-Capitale",
    "sg:tags":[
        "cultural"
    ],
    "wof:name":"A C I",
    "wof:placetype":"venue"
},
  "geometry": {"coordinates":[4.4075798988,50.8413314819],"type":"Point"}
}