{
  "type": "Feature",
  "properties": {
    "addr:full":"Rue De La Gendarmerie 33 Charleroi Hainaut 6030",
    "addr:housenumber":"33",
    "addr:postcode":"6030",
    "addr:street":"Rue De La Gendarmerie;Hainaut",
    "iso:country":"BE",
    "sg:address":"Rue De La Gendarmerie 33",
    "sg:city":"Charleroi",
    "sg:orig_category":"Huisdieren and benodigdheden Huisdierenkwekers",
    "sg:phone":"+32 71 51 30 45",
    "sg:postcode":"6030",
    "sg:province":"Hainaut",
    "wof:name":"Shar Pei Du Temple Yang",
    "wof:placetype":"venue"
},
  "geometry": {"coordinates":[4.3969759941,50.4047317505],"type":"Point"}
}