{
  "type": "Feature",
  "properties": {
    "addr:full":"Avenue Guillaume Lambert 84 Seraing Li\u00e8ge 4101",
    "addr:housenumber":"84",
    "addr:postcode":"4101",
    "addr:street":"Avenue Guillaume Lambert",
    "iso:country":"BE",
    "sg:address":"Avenue Guillaume Lambert 84",
    "sg:city":"Seraing",
    "sg:orig_category":"M\u00e9decins and sp\u00e9cialistes",
    "sg:phone":"+32 4 233 34 63",
    "sg:postcode":"4101",
    "sg:province":"Li\u00e8ge",
    "wof:name":"Edouard Smiejkowski",
    "wof:placetype":"venue"
},
  "geometry": {"coordinates":[5.4931640625,50.6180763245],"type":"Point"}
}