{
  "type": "Feature",
  "properties": {
    "iso:country":"BE",
    "sg:address":"Rue Saint-laurent 350",
    "sg:city":"Li\u00c8ge",
    "sg:classifiers":[
        {
            "category":"Insurance",
            "subcategory":"Life Insurance",
            "type":"Services"
        }
    ],
    "sg:phone":"+32 4 252 49 69",
    "sg:postcode":"4000",
    "sg:province":"Li\u00e8ge",
    "sg:tags":[
        "assurance"
    ],
    "wof:name":"Groupe G.e.s.i.a.c.",
    "wof:placetype":"venue"
},
  "geometry": {"coordinates":[5.5546751022,50.6396217346],"type":"Point"}
}