{
  "type": "Feature",
  "properties": {
    "addr:full":"8 Guilleminlaan 9500 Geraardsbergen 8",
    "addr:housenumber":"8",
    "addr:postcode":"9500",
    "addr:street":"Guilleminlaan",
    "iso:country":"BE",
    "sg:address":"8",
    "sg:city":"Guilleminlaan 9500 Geraardsbergen",
    "sg:classifiers":[
        {
            "category":"Professional",
            "type":"Services"
        }
    ],
    "sg:phone":"+32 54 41 25 59",
    "sg:postcode":"8",
    "sg:tags":[
        "transport",
        "road"
    ],
    "wof:name":"Belle Vue Nv",
    "wof:placetype":"venue"
},
  "geometry": {"coordinates":[3.8934400082,50.7716445923],"type":"Point"}
}