{
  "type": "Feature",
  "properties": {
    "addr:full":"Rue Bourbes\u00e9e 53 Pont-\u00e0-celles Hainaut 6230",
    "addr:housenumber":"53",
    "addr:postcode":"6230",
    "addr:street":"Rue Bourbese\u0301E",
    "iso:country":"BE",
    "sg:address":"Rue Bourbes\u00e9e 53",
    "sg:city":"Pont-\u00e0-celles",
    "sg:classifiers":[
        {
            "category":"Health Services",
            "subcategory":"Health Practitioner",
            "type":"Services"
        }
    ],
    "sg:phone":"+32 71 84 03 45",
    "sg:postcode":"6230",
    "sg:province":"Hainaut",
    "sg:tags":[
        "therapist",
        "speech"
    ],
    "wof:name":"Morbois D",
    "wof:placetype":"venue"
},
  "geometry": {"coordinates":[4.35415411,50.5229034424],"type":"Point"}
}