{
  "type": "Feature",
  "properties": {
    "addr:full":"Chauss\u00c9e Maieur Habils 85ba Rebecq Brabant Wallon 1430",
    "addr:housenumber":"85ba",
    "addr:postcode":"1430",
    "addr:street":"Chausse\u0301E Maieur Habils",
    "iso:country":"BE",
    "sg:address":"Chauss\u00c9e Maieur Habils 85ba",
    "sg:city":"Rebecq",
    "sg:orig_category":"Reliure and finition. Imprimeries and copyshops",
    "sg:phone":"+32 2 395 61 92",
    "sg:postcode":"1430",
    "sg:province":"Brabant Wallon",
    "wof:name":"Facovit",
    "wof:placetype":"venue"
},
  "geometry": {"coordinates":[4.1060829163,50.6916923523],"type":"Point"}
}