{
  "type": "Feature",
  "properties": {
    "addr:full":"Rue De Wansijn 23 Ukkel/uccle Bruxelles-Capitale 1180",
    "addr:housenumber":"23",
    "addr:postcode":"1180",
    "addr:street":"Rue De Wansijn;/",
    "iso:country":"BE",
    "sg:address":"Rue De Wansijn 23",
    "sg:city":"Ukkel/uccle",
    "sg:classifiers":[
        {
            "category":"Personal",
            "subcategory":"Beauty Salon",
            "type":"Services"
        }
    ],
    "sg:phone":"+32 2 374 52 43",
    "sg:postcode":"1180",
    "sg:province":"Bruxelles-Capitale",
    "sg:tags":[
        "de",
        "coiffure"
    ],
    "wof:name":"Coiffure Jenny",
    "wof:placetype":"venue"
},
  "geometry": {"coordinates":[4.3590188026,50.7912063599],"type":"Point"}
}