{
  "type": "Feature",
  "properties": {
    "addr:full":"Rue De L\u00b4agriculture 92-94 Herstal Li\u00e8ge 4040",
    "addr:postcode":"92-94;4040",
    "addr:street":"Rue De L\u00b4Agriculture",
    "iso:country":"BE",
    "sg:address":"Rue De L\u00b4agriculture 92-94",
    "sg:city":"Herstal",
    "sg:orig_category":"Bloemen and planten",
    "sg:phone":"+32 4 264 24 04",
    "sg:postcode":"4040",
    "sg:province":"Li\u00e8ge",
    "wof:name":"A La Baccara",
    "wof:placetype":"venue"
},
  "geometry": {"coordinates":[5.6169118881,50.6729240417],"type":"Point"}
}