{
  "type": "Feature",
  "properties": {
    "addr:full":"Daalstraat 6 Affligem Vlaams-Brabant 1790",
    "addr:housenumber":"6",
    "addr:postcode":"1790",
    "addr:street":"Daalstraat",
    "iso:country":"BE",
    "sg:address":"Daalstraat 6",
    "sg:city":"Affligem",
    "sg:orig_category":"Fleurs and plantes",
    "sg:phone":"+32 53 68 23 65",
    "sg:postcode":"1790",
    "sg:province":"Vlaams-Brabant",
    "wof:name":"Groendecor",
    "wof:placetype":"venue"
},
  "geometry": {"coordinates":[4.105984211,50.9132232666],"type":"Point"}
}