{
  "type": "Feature",
  "properties": {
    "addr:full":"Lentakkerstraat 2 Aalter (lotenhulle) Oost-Vlaanderen 9880",
    "addr:housenumber":"2",
    "addr:postcode":"9880",
    "addr:street":"Lentakkerstraat",
    "iso:country":"BE",
    "sg:address":"Lentakkerstraat 2",
    "sg:city":"Aalter (lotenhulle)",
    "sg:classifiers":[
        {
            "category":"Home & Garden",
            "subcategory":"Home Furnishings",
            "type":"Retail Goods"
        }
    ],
    "sg:phone":"+32 51 68 70 93",
    "sg:postcode":"9880",
    "sg:province":"Oost-Vlaanderen",
    "sg:tags":[
        "interior",
        "decoration"
    ],
    "wof:name":"Verloove I",
    "wof:placetype":"venue"
},
  "geometry": {"coordinates":[3.4759199619,51.0369300842],"type":"Point"}
}