{
  "type": "Feature",
  "properties": {
    "iso:country":"BE",
    "sg:address":"Chauss\u00e9e De Bruxelles 748",
    "sg:city":"Waterloo",
    "sg:classifiers":[
        {
            "category":"Utilities",
            "subcategory":"Water",
            "type":"Services"
        }
    ],
    "sg:phone":"+32 2 354 66 66",
    "sg:postcode":"1410",
    "sg:province":"Brabant Wallon",
    "sg:tags":[
        "purification"
    ],
    "wof:name":"Bob'service",
    "wof:placetype":"venue"
},
  "geometry": {"coordinates":[4.4068050385,50.689781189],"type":"Point"}
}