{
  "type": "Feature",
  "properties": {
    "iso:country":"BE",
    "sg:address":"Beiaardstraat 6",
    "sg:city":"Izegem",
    "sg:orig_category":"Sportclubs",
    "sg:phone":"+32 51 30 50 01",
    "sg:postcode":"8870",
    "sg:province":"West-Vlaanderen",
    "wof:name":"V.k. Izegem",
    "wof:placetype":"venue"
},
  "geometry": {"coordinates":[3.2115600109,50.9069252014],"type":"Point"}
}