{
  "type": "Feature",
  "properties": {
    "addr:full":"Berg 55 Deinze (meigem) Oost-Vlaanderen 9800",
    "addr:housenumber":"55",
    "addr:postcode":"9800",
    "addr:street":"Berg",
    "iso:country":"BE",
    "sg:address":"Berg 55",
    "sg:city":"Deinze (meigem)",
    "sg:classifiers":[
        {
            "category":"Building & Trades",
            "subcategory":"Cleaning & Sanitation",
            "type":"Services"
        }
    ],
    "sg:phone":"+32 486 06 33 44",
    "sg:postcode":"9800",
    "sg:province":"Oost-Vlaanderen",
    "sg:tags":[
        "cleaner",
        "window"
    ],
    "wof:name":"Bolle D & P",
    "wof:placetype":"venue"
},
  "geometry": {"coordinates":[3.5314500332,51.0212287903],"type":"Point"}
}