{
  "type": "Feature",
  "properties": {
    "addr:full":"Vossenplein 32 Brussel/bruxelles Bruxelles-Capitale 1000",
    "addr:housenumber":"32",
    "addr:postcode":"1000",
    "addr:street":"Vossenplein;/",
    "iso:country":"BE",
    "sg:address":"Vossenplein 32",
    "sg:city":"Brussel/bruxelles",
    "sg:orig_category":"Huishoudapparaten, televisies and radio's",
    "sg:phone":"+32 2 511 68 44",
    "sg:postcode":"1000",
    "sg:province":"Bruxelles-Capitale",
    "wof:name":"Maison Comptoir",
    "wof:placetype":"venue"
},
  "geometry": {"coordinates":[4.3450407982,50.8369216919],"type":"Point"}
}