{
  "type": "Feature",
  "properties": {
    "iso:country":"BE",
    "sg:address":"Kachtemsestraat 139",
    "sg:city":"Izegem",
    "sg:orig_category":"Geschenken and souvenirs Krantenwinkels Rookartikelen",
    "sg:phone":"+32 51 31 76 13",
    "sg:postcode":"8870",
    "sg:province":"West-Vlaanderen",
    "wof:name":"De Kriebel",
    "wof:placetype":"venue"
},
  "geometry": {"coordinates":[3.1937999725,50.9315071106],"type":"Point"}
}