{
  "type": "Feature",
  "properties": {
    "iso:country":"BE",
    "sg:address":"Franslaan 168",
    "sg:city":"Nieuwpoort",
    "sg:orig_category":"Assistances juridiques. Conseillers fiscaux",
    "sg:phone":"+32 58 23 44 96",
    "sg:postcode":"8620",
    "sg:province":"West-Vlaanderen",
    "wof:name":"Bureau Fidurent",
    "wof:placetype":"venue"
},
  "geometry": {"coordinates":[2.7067079544,51.1433105469],"type":"Point"}
}