{
  "type": "Feature",
  "properties": {
    "iso:country":"BE",
    "sg:address":"Sint-antoniusweg 31",
    "sg:city":"Neerpelt",
    "sg:orig_category":"Herstellingen and onderhoud van auto's Onderdelen and accessoires voertuigen Gh",
    "sg:phone":"+32 11 64 27 41",
    "sg:postcode":"3910",
    "sg:province":"Limburg",
    "wof:name":"Etn. Alders",
    "wof:placetype":"venue"
},
  "geometry": {"coordinates":[5.4473419189,51.2318115234],"type":"Point"}
}