{
  "type": "Feature",
  "properties": {
    "addr:full":"Rode Kruisplein 15 Mechelen Antwerpen 2800",
    "addr:housenumber":"15",
    "addr:postcode":"2800",
    "addr:street":"Rode Kruisplein",
    "iso:country":"BE",
    "sg:address":"Rode Kruisplein 15",
    "sg:city":"Mechelen",
    "sg:classifiers":[
        {
            "category":"Arena",
            "subcategory":"Sports Club",
            "type":"Entertainment"
        }
    ],
    "sg:phone":"+32 15 27 48 23",
    "sg:postcode":"2800",
    "sg:province":"Antwerpen",
    "wof:name":"Bce Snookercenter",
    "wof:placetype":"venue"
},
  "geometry": {"coordinates":[4.4720788002,51.0327453613],"type":"Point"}
}