{
  "type": "Feature",
  "properties": {
    "iso:country":"BE",
    "sg:address":"Rue De Libin 5",
    "sg:city":"Saint-hubert",
    "sg:orig_category":"Slagers",
    "sg:phone":"+32 61 61 12 00",
    "sg:postcode":"6870",
    "sg:province":"Luxembourg",
    "wof:name":"Philippe Francois",
    "wof:placetype":"venue"
},
  "geometry": {"coordinates":[5.373360157,50.0256156921],"type":"Point"}
}