{
  "type": "Feature",
  "properties": {
    "iso:country":"BE",
    "sg:address":"Kommenstraat 25",
    "sg:city":"Anderlecht",
    "sg:orig_category":"Elektrische installaties voor woningen",
    "sg:phone":"+32 2 521 91 15",
    "sg:postcode":"1070",
    "sg:province":"Bruxelles-Capitale",
    "wof:name":"Aetra",
    "wof:placetype":"venue"
},
  "geometry": {"coordinates":[4.3217148781,50.8357963562],"type":"Point"}
}