{
  "type": "Feature",
  "properties": {
    "iso:country":"BE",
    "sg:address":"Schavei 42",
    "sg:city":"Overijse",
    "sg:classifiers":[
        {
            "category":"Government",
            "subcategory":"Post Office",
            "type":"Public Place"
        }
    ],
    "sg:phone":"+32 2 688 28 53",
    "sg:postcode":"3090",
    "sg:province":"Vlaams-Brabant",
    "sg:tags":[
        "stamp"
    ],
    "wof:name":"Postzegelhandel Molenaers Werner",
    "wof:placetype":"venue"
},
  "geometry": {"coordinates":[4.5304169655,50.7747917175],"type":"Point"}
}