{
  "type": "Feature",
  "properties": {
    "addr:full":"Rue Louis-isidore Lamey 9 Bruxelles (auderghem) Bruxelles-Capitale 1160",
    "addr:housenumber":"9",
    "addr:postcode":"1160",
    "addr:street":"Rue Louis-Isidore Lamey",
    "iso:country":"BE",
    "sg:address":"Rue Louis-isidore Lamey 9",
    "sg:city":"Bruxelles (auderghem)",
    "sg:classifiers":[
        {
            "category":"Health Services",
            "subcategory":"Doctor",
            "type":"Services"
        }
    ],
    "sg:phone":"+32 2 672 86 99",
    "sg:postcode":"1160",
    "sg:province":"Bruxelles-Capitale",
    "sg:tags":[
        "medicinephysicians",
        "surgeon"
    ],
    "wof:name":"Brunard Th",
    "wof:placetype":"venue"
},
  "geometry": {"coordinates":[4.4127411842,50.8218460083],"type":"Point"}
}