{
  "type": "Feature",
  "properties": {
    "addr:full":"Rue De L'egalit\u00e9 61 Mouscron Hainaut 7700",
    "addr:housenumber":"61",
    "addr:postcode":"7700",
    "addr:street":"Rue De L'Egalite \u0301",
    "iso:country":"BE",
    "sg:address":"Rue De L'egalit\u00e9 61",
    "sg:city":"Mouscron",
    "sg:classifiers":[
        {
            "category":"Manufacturing",
            "subcategory":"Paper Products",
            "type":"Manufacturing & Wholesale Goods"
        }
    ],
    "sg:phone":"+32 56 86 33 44",
    "sg:postcode":"7700",
    "sg:province":"Hainaut",
    "sg:tags":[
        "bookbinding"
    ],
    "wof:name":"Ateliers M.c. (les) Sprl",
    "wof:placetype":"venue"
},
  "geometry": {"coordinates":[3.1988151073,50.7320098877],"type":"Point"}
}