{
  "type": "Feature",
  "properties": {
    "iso:country":"BE",
    "sg:address":"Antwerpseweg 81",
    "sg:city":"Geel",
    "sg:classifiers":[
        {
            "category":"Retail",
            "subcategory":"Auto Repair",
            "type":"Services"
        }
    ],
    "sg:phone":"+32 14 58 87 23",
    "sg:postcode":"2440",
    "sg:province":"Antwerpen",
    "sg:tags":[
        "garage"
    ],
    "wof:name":"Dams Cars Bvba",
    "wof:placetype":"venue"
},
  "geometry": {"coordinates":[4.958106041,51.1466331482],"type":"Point"}
}