{
  "type": "Feature",
  "properties": {
    "iso:country":"BE",
    "sg:address":"Jozef Ii Straat 48",
    "sg:city":"Oostende",
    "sg:orig_category":"Quincailleries. Bois Gr",
    "sg:phone":"+32 59 70 21 37",
    "sg:postcode":"8400",
    "sg:province":"West-Vlaanderen",
    "wof:name":"Thienpondt & Cie",
    "wof:placetype":"venue"
},
  "geometry": {"coordinates":[2.9194459915,51.2290725708],"type":"Point"}
}