{
  "type": "Feature",
  "properties": {
    "addr:full":"Chauss\u00e9e De Fleurus 44 Charleroi (gilly) Hainaut 6060",
    "addr:housenumber":"44",
    "addr:postcode":"6060",
    "addr:street":"Chausse\u0301E De Fleurus",
    "iso:country":"BE",
    "sg:address":"Chauss\u00e9e De Fleurus 44",
    "sg:city":"Charleroi (gilly)",
    "sg:classifiers":[
        {
            "category":"Personal",
            "subcategory":"Tattoo Parlor",
            "type":"Services"
        }
    ],
    "sg:phone":"+32 475 44 65 90",
    "sg:postcode":"6060",
    "sg:province":"Hainaut",
    "sg:tags":[
        "tattooists"
    ],
    "wof:name":"Art Du Point (l') - Tattoo'studio",
    "wof:placetype":"venue"
},
  "geometry": {"coordinates":[4.4720010757,50.4430198669],"type":"Point"}
}