{
  "type": "Feature",
  "properties": {
    "iso:country":"BE",
    "sg:address":"Mimosastraat 173",
    "sg:city":"Gent (mariakerke)",
    "sg:classifiers":[
        {
            "category":"Building & Trades",
            "subcategory":"Pest Control",
            "type":"Services"
        }
    ],
    "sg:phone":"+32 9 236 48 21",
    "sg:postcode":"9030",
    "sg:province":"Oost-Vlaanderen",
    "sg:tags":[
        "painting",
        "contractor"
    ],
    "wof:name":"Verschueren J",
    "wof:placetype":"venue"
},
  "geometry": {"coordinates":[3.7010970116,51.0750770569],"type":"Point"}
}