{
  "type": "Feature",
  "properties": {
    "iso:country":"BE",
    "sg:address":"Avenue Des Gaulois 15",
    "sg:city":"Bruxelles (etterbeek)",
    "sg:classifiers":[
        {
            "category":"Transit Center",
            "subcategory":"Freight",
            "type":"Transportation"
        }
    ],
    "sg:phone":"+32 10 84 67 26",
    "sg:postcode":"1040",
    "sg:province":"Bruxelles-Capitale",
    "sg:tags":[
        "import",
        "export",
        "-"
    ],
    "wof:name":"Ftp",
    "wof:placetype":"venue"
},
  "geometry": {"coordinates":[4.3949041367,50.8383903503],"type":"Point"}
}