{
  "type": "Feature",
  "properties": {
    "addr:full":"Esenweg 17 Diksmuide West-Vlaanderen 8600",
    "addr:housenumber":"17",
    "addr:postcode":"8600",
    "addr:street":"Esenweg",
    "iso:country":"BE",
    "sg:address":"Esenweg 17",
    "sg:city":"Diksmuide",
    "sg:orig_category":"Kapsalons",
    "sg:phone":"+32 51 50 19 85",
    "sg:postcode":"8600",
    "sg:province":"West-Vlaanderen",
    "wof:name":"Coiffure Nicole",
    "wof:placetype":"venue"
},
  "geometry": {"coordinates":[2.8693630695,51.031879425],"type":"Point"}
}