{
  "type": "Feature",
  "properties": {
    "addr:full":"Dekenstraat 51 Leuven Vlaams-Brabant 3000",
    "addr:housenumber":"51",
    "addr:postcode":"3000",
    "addr:street":"Dekenstraat",
    "iso:country":"BE",
    "sg:address":"Dekenstraat 51",
    "sg:city":"Leuven",
    "sg:orig_category":"Artsen and specialisten",
    "sg:phone":"+32 16 23 01 58",
    "sg:postcode":"3000",
    "sg:province":"Vlaams-Brabant",
    "wof:name":"W. Scholtus",
    "wof:placetype":"venue"
},
  "geometry": {"coordinates":[4.7112269402,50.8732147217],"type":"Point"}
}