{
  "type": "Feature",
  "properties": {
    "iso:country":"BE",
    "sg:address":"Rue Michel-ham\u00c9lius 3",
    "sg:city":"Arlon",
    "sg:orig_category":"Artsen and specialisten",
    "sg:phone":"+32 63 23 65 19",
    "sg:postcode":"6700",
    "sg:province":"Luxembourg",
    "wof:name":"Catherine Lemaire",
    "wof:placetype":"venue"
},
  "geometry": {"coordinates":[5.8237690926,49.684299469],"type":"Point"}
}