{
  "type": "Feature",
  "properties": {
    "addr:full":"Montenakenstraat 25 Gingelom Limburg 3890",
    "addr:housenumber":"25",
    "addr:postcode":"3890",
    "addr:street":"Montenakenstraat",
    "iso:country":"BE",
    "sg:address":"Montenakenstraat 25",
    "sg:city":"Gingelom",
    "sg:orig_category":"Speciaalzaken",
    "sg:phone":"+32 11 88 17 68",
    "sg:postcode":"3890",
    "sg:province":"Limburg",
    "wof:name":"Etn. Lacroix",
    "wof:placetype":"venue"
},
  "geometry": {"coordinates":[5.124101162,50.7386474609],"type":"Point"}
}