{
  "type": "Feature",
  "properties": {
    "addr:full":"Motbroekstraat 10 Tielt-winge Vlaams-Brabant 3390",
    "addr:housenumber":"10",
    "addr:postcode":"3390",
    "addr:street":"Motbroekstraat",
    "iso:country":"BE",
    "sg:address":"Motbroekstraat 10",
    "sg:city":"Tielt-winge",
    "sg:orig_category":"Epiceries",
    "sg:phone":"+32 16 63 53 16",
    "sg:postcode":"3390",
    "sg:province":"Vlaams-Brabant",
    "wof:name":"Germaine Reynders",
    "wof:placetype":"venue"
},
  "geometry": {"coordinates":[4.86810112,50.9205322266],"type":"Point"}
}