{
  "type": "Feature",
  "properties": {
    "addr:full":"Bagattenstraat 128 Gent Oost-Vlaanderen 9000",
    "addr:housenumber":"128",
    "addr:postcode":"9000",
    "addr:street":"Bagattenstraat;Oost-Vlaanderen",
    "iso:country":"BE",
    "sg:address":"Bagattenstraat 128",
    "sg:city":"Gent",
    "sg:orig_category":"Opticiens",
    "sg:phone":"+32 9 225 46 63",
    "sg:postcode":"9000",
    "sg:province":"Oost-Vlaanderen",
    "wof:name":"Joseph De Groote",
    "wof:placetype":"venue"
},
  "geometry": {"coordinates":[3.7243978977,51.0474700928],"type":"Point"}
}