{
  "type": "Feature",
  "properties": {
    "iso:country":"BE",
    "sg:address":"Staatsbaan 199",
    "sg:city":"Bekkevoort",
    "sg:orig_category":"Pain, p\u00e2tisseries and confiseries",
    "sg:phone":"+32 13 32 78 78",
    "sg:postcode":"3460",
    "sg:province":"Vlaams-Brabant",
    "wof:name":"Bakkerij Nijns Gebrs",
    "wof:placetype":"venue"
},
  "geometry": {"coordinates":[5.0074529648,50.9556236267],"type":"Point"}
}