{
  "type": "Feature",
  "properties": {
    "addr:full":"Rue L\u00e9opold 12 Gembloux-sur-orneau (gembloux) Namur 5030",
    "addr:housenumber":"12",
    "addr:postcode":"5030",
    "addr:street":"Rue Le\u0301Opold;Namur",
    "iso:country":"BE",
    "sg:address":"Rue L\u00e9opold 12",
    "sg:city":"Gembloux-sur-orneau (gembloux)",
    "sg:classifiers":[
        {
            "category":"Personal",
            "subcategory":"Beauty Salon",
            "type":"Services"
        }
    ],
    "sg:phone":"+32 81 61 02 61",
    "sg:postcode":"5030",
    "sg:province":"Namur",
    "sg:tags":[
        "lady",
        "-",
        "hairdressing"
    ],
    "wof:name":"Jean-claude Biguine",
    "wof:placetype":"venue"
},
  "geometry": {"coordinates":[4.6926398277,50.5604171753],"type":"Point"}
}