{
  "type": "Feature",
  "properties": {
    "iso:country":"BE",
    "sg:address":"Leuvensestraat 1",
    "sg:city":"Vilvoorde",
    "sg:orig_category":"Boucheries",
    "sg:phone":"+32 2 251 00 51",
    "sg:postcode":"1800",
    "sg:province":"Vlaams-Brabant",
    "wof:name":"Seghers-laurent",
    "wof:placetype":"venue"
},
  "geometry": {"coordinates":[4.4361181259,50.9280433655],"type":"Point"}
}