{
  "type": "Feature",
  "properties": {
    "iso:country":"BE",
    "sg:address":"Humont 69",
    "sg:city":"Leuze-en-hainaut (thieulain)",
    "sg:classifiers":[
        {
            "category":"Building & Trades",
            "subcategory":"Landscaping Services",
            "type":"Services"
        }
    ],
    "sg:phone":"+32 69 66 68 76",
    "sg:postcode":"7901",
    "sg:province":"Hainaut",
    "sg:tags":[
        "access",
        "pond",
        "laying-out",
        "-"
    ],
    "wof:name":"Delem J",
    "wof:placetype":"venue"
},
  "geometry": {"coordinates":[3.6070940495,50.628818512],"type":"Point"}
}