{
  "type": "Feature",
  "properties": {
    "addr:full":"Rue Picard 78b1 Bruxelles Bruxelles-Capitale 1080",
    "addr:housenumber":"78b1",
    "addr:postcode":"1080",
    "addr:street":"Rue Picard",
    "iso:country":"BE",
    "sg:address":"Rue Picard 78b1",
    "sg:city":"Bruxelles",
    "sg:orig_category":"Customs Agencies, Declarants",
    "sg:phone":"+32 2 420 66 77",
    "sg:postcode":"1080",
    "sg:province":"Bruxelles-Capitale",
    "wof:name":"Top Communication S.p.r.l.",
    "wof:placetype":"venue"
},
  "geometry": {"coordinates":[4.338973999,50.8650398254],"type":"Point"}
}