{
  "type": "Feature",
  "properties": {
    "iso:country":"BE",
    "sg:address":"Melkvoetstraat 68",
    "sg:city":"Hasselt",
    "sg:orig_category":"Advocaten and juridische adviseurs",
    "sg:phone":"+32 11 23 23 58",
    "sg:postcode":"3500",
    "sg:province":"Limburg",
    "wof:name":"Stephan Vaninbroukx",
    "wof:placetype":"venue"
},
  "geometry": {"coordinates":[5.3314051628,50.9327354431],"type":"Point"}
}