{
  "type": "Feature",
  "properties": {
    "addr:full":"Place De La Constitution 4 Charleroi Hainaut 6001",
    "addr:housenumber":"4",
    "addr:postcode":"6001",
    "addr:street":"Place De La Constitution;Hainaut",
    "iso:country":"BE",
    "sg:address":"Place De La Constitution 4",
    "sg:city":"Charleroi",
    "sg:orig_category":"Instituts de beaut\u00e9",
    "sg:phone":"+32 71 47 66 98",
    "sg:postcode":"6001",
    "sg:province":"Hainaut",
    "wof:name":"Michel Quintelier",
    "wof:placetype":"venue"
},
  "geometry": {"coordinates":[4.42892313,50.3950004578],"type":"Point"}
}