{
  "type": "Feature",
  "properties": {
    "iso:country":"BE",
    "sg:address":"Okegemdorp 24",
    "sg:city":"Ninove",
    "sg:classifiers":[
        {
            "category":"Restaurant",
            "type":"Food & Drink"
        }
    ],
    "sg:phone":"+32 54 32 41 43",
    "sg:postcode":"9400",
    "sg:province":"Oost-Vlaanderen",
    "sg:tags":[
        "\u00c0",
        "domicile",
        "fast",
        "catering",
        "emporter",
        "livraison",
        "restaurants"
    ],
    "wof:name":"Restaurant De Scheerling",
    "wof:placetype":"venue"
},
  "geometry": {"coordinates":[4.033425808,50.8464584351],"type":"Point"}
}