{
  "type": "Feature",
  "properties": {
    "addr:full":"Rue Grande 119 La Louviere Hainaut 7110",
    "addr:housenumber":"119",
    "addr:postcode":"7110",
    "addr:street":"Rue Grande",
    "iso:country":"BE",
    "sg:address":"Rue Grande 119",
    "sg:city":"La Louviere",
    "sg:orig_category":"V\u00e9t\u00e9rinaires",
    "sg:phone":"+32 64 67 82 37",
    "sg:postcode":"7110",
    "sg:province":"Hainaut",
    "wof:name":"Anne Talmat",
    "wof:placetype":"venue"
},
  "geometry": {"coordinates":[4.1505050659,50.4826698303],"type":"Point"}
}