{
  "type": "Feature",
  "properties": {
    "iso:country":"BE",
    "sg:address":"Rue Des Pr\u00e9montr\u00e9s 40",
    "sg:city":"Li\u00e8ge 1",
    "sg:classifiers":[
        {
            "category":"Shopping",
            "subcategory":"Books",
            "type":"Retail Goods"
        }
    ],
    "sg:phone":"+32 4 223 20 55",
    "sg:postcode":"4000",
    "sg:province":"Li\u00e8ge",
    "sg:tags":[
        "bookseller"
    ],
    "wof:name":"C.d.d. Librairie Dioc\u00e9saine Asbl",
    "wof:placetype":"venue"
},
  "geometry": {"coordinates":[5.5746431351,50.6373138428],"type":"Point"}
}