{
  "type": "Feature",
  "properties": {
    "addr:full":"Rue Emile Pirson 10 Sombreffe Namur 5140",
    "addr:housenumber":"10",
    "addr:postcode":"5140",
    "addr:street":"Rue Emile Pirson",
    "iso:country":"BE",
    "sg:address":"Rue Emile Pirson 10",
    "sg:city":"Sombreffe",
    "sg:orig_category":"R\u00e9alisation de programmes and logiciels",
    "sg:phone":"+32 71 88 88 49",
    "sg:postcode":"5140",
    "sg:province":"Namur",
    "wof:name":"A.r.i.",
    "wof:placetype":"venue"
},
  "geometry": {"coordinates":[4.616590023,50.5404853821],"type":"Point"}
}