{
  "type": "Feature",
  "properties": {
    "iso:country":"BE",
    "sg:address":"Chauss\u00e9e De Waterloo 1008",
    "sg:city":"Bruxelles (uccle)",
    "sg:classifiers":[
        {
            "category":"Professional",
            "subcategory":"Art Services",
            "type":"Services"
        }
    ],
    "sg:phone":"+32 2 538 21 30",
    "sg:postcode":"1180",
    "sg:province":"Bruxelles-Capitale",
    "sg:tags":[
        "-",
        "painter",
        "artist"
    ],
    "wof:name":"Tirou'art",
    "wof:placetype":"venue"
},
  "geometry": {"coordinates":[4.374642849,50.8006744385],"type":"Point"}
}