{
  "type": "Feature",
  "properties": {
    "addr:full":"Barri\u00e8re De Fer 22b Espierres-helchin (espierres) West-Vlaanderen 8587",
    "addr:housenumber":"22b",
    "addr:postcode":"8587",
    "addr:street":"Barrie\u0300Re;Fer",
    "iso:country":"BE",
    "sg:address":"Barri\u00e8re De Fer 22b",
    "sg:city":"Espierres-helchin (espierres)",
    "sg:classifiers":[
        {
            "category":"Freight",
            "type":"Transportation"
        }
    ],
    "sg:phone":"+32 56 45 73 73",
    "sg:postcode":"8587",
    "sg:province":"West-Vlaanderen",
    "sg:tags":[
        "-",
        "transport"
    ],
    "wof:name":"Eggermont & Turpyn Nv",
    "wof:placetype":"venue"
},
  "geometry": {"coordinates":[3.3299839497,50.7268981934],"type":"Point"}
}