{
  "type": "Feature",
  "properties": {
    "addr:full":"Kleine Reesdijk 96 Turnhout Antwerpen 2300",
    "addr:housenumber":"96",
    "addr:postcode":"2300",
    "addr:street":"Kleine Reesdijk",
    "iso:country":"BE",
    "sg:address":"Kleine Reesdijk 96",
    "sg:city":"Turnhout",
    "sg:orig_category":"Herstellingen and onderhoud van auto's",
    "sg:phone":"+32 14 42 11 02",
    "sg:postcode":"2300",
    "sg:province":"Antwerpen",
    "wof:name":"Kempens Autoglas",
    "wof:placetype":"venue"
},
  "geometry": {"coordinates":[4.9550061226,51.2832832336],"type":"Point"}
}