{
  "type": "Feature",
  "properties": {
    "addr:full":"Caverstraat 10ba Jabbeke West-Vlaanderen 8490",
    "addr:housenumber":"10ba",
    "addr:postcode":"8490",
    "addr:street":"Caverstraat",
    "iso:country":"BE",
    "sg:address":"Caverstraat 10ba",
    "sg:city":"Jabbeke",
    "sg:orig_category":"Tuinen",
    "sg:phone":"+32 50 81 16 06",
    "sg:postcode":"8490",
    "sg:province":"West-Vlaanderen",
    "wof:name":"Dominique Eeman",
    "wof:placetype":"venue"
},
  "geometry": {"coordinates":[3.0923969746,51.1834220886],"type":"Point"}
}