{
  "type": "Feature",
  "properties": {
    "addr:full":"Nieuwstraat 130 Genk Limburg 3600",
    "addr:housenumber":"130",
    "addr:postcode":"3600",
    "addr:street":"Nieuwstraat",
    "iso:country":"BE",
    "sg:address":"Nieuwstraat 130",
    "sg:city":"Genk",
    "sg:classifiers":[
        {
            "category":"Building & Trades",
            "subcategory":"Electrical",
            "type":"Services"
        }
    ],
    "sg:phone":"+32 485 68 16 94",
    "sg:postcode":"3600",
    "sg:province":"Limburg",
    "sg:tags":[
        "industrial",
        "-",
        "electric",
        "contractor"
    ],
    "wof:name":"Alay Bvba",
    "wof:placetype":"venue"
},
  "geometry": {"coordinates":[5.497759819,50.9617195129],"type":"Point"}
}