{
  "type": "Feature",
  "properties": {
    "addr:full":"Stuurstraat 121 Beveren Oost-Vlaanderen 9120",
    "addr:housenumber":"121",
    "addr:postcode":"9120",
    "addr:street":"Stuurstraat",
    "iso:country":"BE",
    "sg:address":"Stuurstraat 121",
    "sg:city":"Beveren",
    "sg:classifiers":[
        {
            "category":"Arena",
            "subcategory":"Sports Club",
            "type":"Entertainment"
        }
    ],
    "sg:phone":"+32 3 775 81 80",
    "sg:postcode":"9120",
    "sg:province":"Oost-Vlaanderen",
    "sg:tags":[
        "de"
    ],
    "wof:name":"B.c. Ambassadors",
    "wof:placetype":"venue"
},
  "geometry": {"coordinates":[4.211356163,51.1768035889],"type":"Point"}
}