{
  "type": "Feature",
  "properties": {
    "addr:full":"Groenstraat 6 Diepenbeek Limburg 3590",
    "addr:housenumber":"6",
    "addr:postcode":"3590",
    "addr:street":"Groenstraat",
    "iso:country":"BE",
    "sg:address":"Groenstraat 6",
    "sg:city":"Diepenbeek",
    "sg:orig_category":"Installation de menuiserie en bois and plastique",
    "sg:phone":"+32 11 32 47 65",
    "sg:postcode":"3590",
    "sg:province":"Limburg",
    "wof:name":"Peter Freson",
    "wof:placetype":"venue"
},
  "geometry": {"coordinates":[5.4403591156,50.9319648743],"type":"Point"}
}