{
  "type": "Feature",
  "properties": {
    "addr:full":"Oude Baan 617 Maasmechelen Limburg 3630",
    "addr:housenumber":"617",
    "addr:postcode":"3630",
    "addr:street":"Oude Baan",
    "iso:country":"BE",
    "sg:address":"Oude Baan 617",
    "sg:city":"Maasmechelen",
    "sg:orig_category":"Caf\u00e9s Sportclubs Sportterreinen and installaties behalve sportcentra",
    "sg:phone":"+32 89 76 06 94",
    "sg:postcode":"3630",
    "sg:province":"Limburg",
    "wof:name":"Isaekshoef",
    "wof:placetype":"venue"
},
  "geometry": {"coordinates":[5.6638431549,50.9405174255],"type":"Point"}
}