{
  "type": "Feature",
  "properties": {
    "iso:country":"BE",
    "sg:address":"Krekelstraat 77",
    "sg:city":"Ingelmunster",
    "sg:orig_category":"P\u00e9pini\u00e9ristes",
    "sg:phone":"+32 51 48 97 65",
    "sg:postcode":"8770",
    "sg:province":"West-Vlaanderen",
    "wof:name":"Boomkwekerij Dewulf",
    "wof:placetype":"venue"
},
  "geometry": {"coordinates":[3.2764389515,50.9350852966],"type":"Point"}
}