{
  "type": "Feature",
  "properties": {
    "iso:country":"BE",
    "sg:address":"Rijkmakerlaan 37",
    "sg:city":"Essen",
    "sg:classifiers":[
        {
            "category":"Manufacturing",
            "subcategory":"Metals",
            "type":"Manufacturing & Wholesale Goods"
        }
    ],
    "sg:phone":"+32 3 677 38 15",
    "sg:postcode":"2910",
    "sg:province":"Antwerpen",
    "sg:tags":[
        "work",
        "sheet"
    ],
    "wof:name":"De Rooy Bvba",
    "wof:placetype":"venue"
},
  "geometry": {"coordinates":[4.5004620552,51.4475364685],"type":"Point"}
}