{
  "type": "Feature",
  "properties": {
    "addr:full":"Maasveldweg 2 Kinrooi Limburg 3640",
    "addr:housenumber":"2",
    "addr:postcode":"3640",
    "addr:street":"Maasveldweg",
    "iso:country":"BE",
    "sg:address":"Maasveldweg 2",
    "sg:city":"Kinrooi",
    "sg:orig_category":"Producteurs de l\u00e9gumes",
    "sg:phone":"+32 89 56 43 73",
    "sg:postcode":"3640",
    "sg:province":"Limburg",
    "wof:name":"E.g.s.",
    "wof:placetype":"venue"
},
  "geometry": {"coordinates":[5.7974700928,51.1314506531],"type":"Point"}
}