{
  "type": "Feature",
  "properties": {
    "iso:country":"BE",
    "sg:address":"Centrumstraat 7",
    "sg:city":"Zulte (olsene)",
    "sg:classifiers":[
        {
            "category":"Shopping",
            "subcategory":"Optician",
            "type":"Retail Goods"
        }
    ],
    "sg:phone":"+32 9 388 68 50",
    "sg:postcode":"9870",
    "sg:province":"Oost-Vlaanderen",
    "sg:tags":[
        "-"
    ],
    "wof:name":"Optiek Jo Nys Bvba",
    "wof:placetype":"venue"
},
  "geometry": {"coordinates":[3.4665930271,50.9356803894],"type":"Point"}
}