{
  "type": "Feature",
  "properties": {
    "addr:full":"Rue Saint-l\u00e9onard 250 Li\u00e8ge 1 Li\u00e8ge 4000",
    "addr:housenumber":"250;1",
    "addr:postcode":"4000",
    "addr:street":"Rue Saint-Le\u0301Onard",
    "iso:country":"BE",
    "sg:address":"Rue Saint-l\u00e9onard 250",
    "sg:city":"Li\u00e8ge 1",
    "sg:classifiers":[
        {
            "category":"Insurance",
            "subcategory":"Insurance Agent",
            "type":"Services"
        }
    ],
    "sg:phone":"+32 4 227 51 23",
    "sg:postcode":"4000",
    "sg:province":"Li\u00e8ge",
    "sg:tags":[
        "broker"
    ],
    "wof:name":"Brundseaux Bureau D'assurances",
    "wof:placetype":"venue"
},
  "geometry": {"coordinates":[5.5925021172,50.6496162415],"type":"Point"}
}