{
  "type": "Feature",
  "properties": {
    "iso:country":"BE",
    "sg:address":"Rue Laplace 1",
    "sg:city":"Seraing",
    "sg:classifiers":[
        {
            "category":"Professional",
            "subcategory":"Testing Lab",
            "type":"Services"
        }
    ],
    "sg:phone":"+32 4 338 79 30",
    "sg:postcode":"4100",
    "sg:province":"Li\u00e8ge",
    "sg:tags":[
        "laboratory",
        "medical"
    ],
    "wof:name":"C.a.r.a.d.",
    "wof:placetype":"venue"
},
  "geometry": {"coordinates":[5.4959201813,50.5802268982],"type":"Point"}
}