{
  "type": "Feature",
  "properties": {
    "addr:full":"Zelemseweg 0 Diest Vlaams-Brabant 3290",
    "addr:housenumber":"0",
    "addr:postcode":"3290",
    "addr:street":"Zelemseweg",
    "iso:country":"BE",
    "sg:address":"Zelemseweg 0",
    "sg:city":"Diest",
    "sg:orig_category":"Enseignement maternel and primaire",
    "sg:phone":"+32 13 31 48 83",
    "sg:postcode":"3290",
    "sg:province":"Vlaams-Brabant",
    "wof:name":"Vrije Kleuterschool",
    "wof:placetype":"venue"
},
  "geometry": {"coordinates":[5.0712280273,50.995639801],"type":"Point"}
}