{
  "type": "Feature",
  "properties": {
    "iso:country":"BE",
    "sg:address":"Snaggaardstraat 15",
    "sg:city":"Brugge",
    "sg:classifiers":[
        {
            "category":"Education",
            "subcategory":"University",
            "type":"Public Place"
        }
    ],
    "sg:phone":"+32 50 33 52 19",
    "sg:postcode":"8000",
    "sg:province":"West-Vlaanderen",
    "sg:tags":[
        "adult"
    ],
    "wof:name":"Hotel- & Toerismeschool Spermalie",
    "wof:placetype":"venue"
},
  "geometry": {"coordinates":[3.2333381176,51.2155227661],"type":"Point"}
}