{
  "type": "Feature",
  "properties": {
    "iso:country":"BE",
    "sg:address":"Kaudenaardestraat 13",
    "sg:city":"Dilbeek",
    "sg:orig_category":"S\u00e9lection de personnel and placement",
    "sg:phone":"+32 2 267 09 97",
    "sg:postcode":"1700",
    "sg:province":"Vlaams-Brabant",
    "wof:name":"Ulysses Consulting",
    "wof:placetype":"venue"
},
  "geometry": {"coordinates":[4.269659996,50.8439865112],"type":"Point"}
}