{
  "type": "Feature",
  "properties": {
    "iso:country":"BE",
    "sg:address":"Markt 14",
    "sg:city":"Borgloon",
    "sg:orig_category":"Newspapers, magazines, periodicals - Distribution",
    "sg:phone":"+32 12 67 27 93",
    "sg:postcode":"3840",
    "sg:province":"Limburg",
    "wof:name":"Aline Dagbladhandel",
    "wof:placetype":"venue"
},
  "geometry": {"coordinates":[5.3430490494,50.8013305664],"type":"Point"}
}