{
  "type": "Feature",
  "properties": {
    "iso:country":"BE",
    "sg:address":"Rue Du Pont 5",
    "sg:city":"Tournai",
    "sg:classifiers":[
        {
            "category":"Personal",
            "subcategory":"Beauty Salon",
            "type":"Services"
        }
    ],
    "sg:phone":"+32 69 23 30 98",
    "sg:postcode":"7500",
    "sg:province":"Hainaut",
    "sg:tags":[
        "de",
        "coiffure"
    ],
    "wof:name":"Coiffure Recto-verso",
    "wof:placetype":"venue"
},
  "geometry": {"coordinates":[3.393709898,50.6070098877],"type":"Point"}
}