{
  "type": "Feature",
  "properties": {
    "addr:full":"Terne Des Vaches 8 Chimay Hainaut 6460",
    "addr:housenumber":"8",
    "addr:postcode":"6460",
    "iso:country":"BE",
    "sg:address":"Terne Des Vaches 8",
    "sg:city":"Chimay",
    "sg:orig_category":"Rundveehouders",
    "sg:phone":"+32 60 21 33 28",
    "sg:postcode":"6460",
    "sg:province":"Hainaut",
    "wof:name":"Raphael Cornelis",
    "wof:placetype":"venue"
},
  "geometry": {"coordinates":[4.3073348999,50.0382537842],"type":"Point"}
}