{
  "type": "Feature",
  "properties": {
    "addr:full":"Weertstraat 91 Bornem Antwerpen 2880",
    "addr:housenumber":"91",
    "addr:postcode":"2880",
    "addr:street":"Weertstraat",
    "iso:country":"BE",
    "sg:address":"Weertstraat 91",
    "sg:city":"Bornem",
    "sg:classifiers":[
        {
            "category":"Arena",
            "subcategory":"Sports Club",
            "type":"Entertainment"
        }
    ],
    "sg:phone":"+32 52 33 45 67",
    "sg:postcode":"2880",
    "sg:province":"Antwerpen",
    "sg:tags":[
        "de"
    ],
    "wof:name":"T.c. Mariekerke",
    "wof:placetype":"venue"
},
  "geometry": {"coordinates":[4.2007360458,51.0680007935],"type":"Point"}
}