{
  "type": "Feature",
  "properties": {
    "addr:full":"Ooikeplein 1 Wortegem-petegem Oost-Vlaanderen 9790",
    "addr:housenumber":"1",
    "addr:postcode":"9790",
    "addr:street":"Ooikeplein",
    "iso:country":"BE",
    "sg:address":"Ooikeplein 1",
    "sg:city":"Wortegem-petegem",
    "sg:orig_category":"R\u00e9cup\u00e9ration de mati\u00e8res m\u00e9talliques recyclables and d\u00e9molisseurs de voitures. Stations-service and ",
    "sg:phone":"+32 9 383 53 79",
    "sg:postcode":"9790",
    "sg:province":"Oost-Vlaanderen",
    "wof:name":"Garage Vanheulenberghe A.",
    "wof:placetype":"venue"
},
  "geometry": {"coordinates":[3.551459074,50.8701477051],"type":"Point"}
}