{
  "type": "Feature",
  "properties": {
    "addr:full":"Rue Du Predesipe 24 Orp-jauche Brabant Wallon 1350",
    "addr:housenumber":"24",
    "addr:postcode":"1350",
    "addr:street":"Rue Du Predesipe",
    "iso:country":"BE",
    "sg:address":"Rue Du Predesipe 24",
    "sg:city":"Orp-jauche",
    "sg:orig_category":"Goederenvervoer over de weg",
    "sg:phone":"+32 496 25 25 05",
    "sg:postcode":"1350",
    "sg:province":"Brabant Wallon",
    "wof:name":"Ben Transports",
    "wof:placetype":"venue"
},
  "geometry": {"coordinates":[4.97920084,50.6738891602],"type":"Point"}
}