{
  "type": "Feature",
  "properties": {
    "iso:country":"BE",
    "sg:address":"Groenstraat 22",
    "sg:city":"Ternat",
    "sg:classifiers":[
        {
            "category":"Freight",
            "type":"Transportation"
        }
    ],
    "sg:phone":"+32 2 582 73 72",
    "sg:postcode":"1740",
    "sg:province":"Vlaams-Brabant",
    "sg:tags":[
        "express",
        "transport"
    ],
    "wof:name":"Brikens",
    "wof:placetype":"venue"
},
  "geometry": {"coordinates":[4.1811571121,50.8758201599],"type":"Point"}
}