{
  "type": "Feature",
  "properties": {
    "iso:country":"BE",
    "sg:address":"Beukenlaan 12",
    "sg:city":"Boom",
    "sg:orig_category":"M\u00e9decines alternatives",
    "sg:phone":"+32 3 844 55 66",
    "sg:postcode":"2850",
    "sg:province":"Antwerpen",
    "wof:name":"Osteopaat Van Geet H.",
    "wof:placetype":"venue"
},
  "geometry": {"coordinates":[4.3674621582,51.0962524414],"type":"Point"}
}