{
  "type": "Feature",
  "properties": {
    "iso:country":"BE",
    "sg:address":"Deerlijkseweg 116-118",
    "sg:city":"Waregem",
    "sg:classifiers":[
        {
            "category":"Transit Center",
            "subcategory":"Freight",
            "type":"Transportation"
        }
    ],
    "sg:phone":"+32 56 60 69 47",
    "sg:postcode":"8790",
    "sg:province":"West-Vlaanderen",
    "sg:tags":[
        "metallurgy",
        "pipe",
        "metalworking",
        "sheet"
    ],
    "wof:name":"De Bo Bvba",
    "wof:placetype":"venue"
},
  "geometry": {"coordinates":[3.4023430347,50.8688812256],"type":"Point"}
}