{
  "type": "Feature",
  "properties": {
    "addr:full":"Wetstraat 2 Meulebeke West-Vlaanderen 8760",
    "addr:housenumber":"2",
    "addr:postcode":"8760",
    "addr:street":"Wetstraat",
    "iso:country":"BE",
    "sg:address":"Wetstraat 2",
    "sg:city":"Meulebeke",
    "sg:orig_category":"Hypotheken and hypotheekbanken Verbruikerskredietinstellingen",
    "sg:phone":"+32 51 40 13 46",
    "sg:postcode":"8760",
    "sg:province":"West-Vlaanderen",
    "wof:name":"Voor Ons Volk",
    "wof:placetype":"venue"
},
  "geometry": {"coordinates":[3.2872099876,50.9524765015],"type":"Point"}
}