{
  "type": "Feature",
  "properties": {
    "addr:full":"9450 Haaltert (groot) Oost-Vlaanderen 9450",
    "addr:postcode":"9450;9450",
    "addr:street":"Groot Oost-Vlaanderen",
    "iso:country":"BE",
    "sg:address":"9450",
    "sg:city":"Haaltert (groot)",
    "sg:orig_category":"Pharmaciens",
    "sg:phone":"+32 900 10 500",
    "sg:postcode":"9450",
    "sg:province":"Oost-Vlaanderen",
    "wof:name":"Pharmacies De Garde",
    "wof:placetype":"venue"
},
  "geometry": {"coordinates":[4.017660141,50.8874015808],"type":"Point"}
}