{
  "type": "Feature",
  "properties": {
    "iso:country":"BE",
    "sg:address":"Rue Du Marche 53",
    "sg:city":"Huy",
    "sg:classifiers":[
        {
            "category":"Personal",
            "subcategory":"Hair Removal",
            "type":"Services"
        }
    ],
    "sg:phone":"+32 85 25 04 29",
    "sg:postcode":"4500",
    "sg:province":"Li\u00e8ge",
    "sg:tags":[
        "cap",
        "hat"
    ],
    "wof:name":"Reliprint Pp",
    "wof:placetype":"venue"
},
  "geometry": {"coordinates":[5.2442798615,50.5181388855],"type":"Point"}
}