{
  "type": "Feature",
  "properties": {
    "addr:full":"Antwerpsestraat 90 Niel Antwerpen 2845",
    "addr:housenumber":"90",
    "addr:postcode":"2845",
    "addr:street":"Antwerpsestraat",
    "iso:country":"BE",
    "sg:address":"Antwerpsestraat 90",
    "sg:city":"Niel",
    "sg:orig_category":"Kapsalons",
    "sg:phone":"+32 3 888 26 40",
    "sg:postcode":"2845",
    "sg:province":"Antwerpen",
    "wof:name":"Coiffure Simonne",
    "wof:placetype":"venue"
},
  "geometry": {"coordinates":[4.3317189217,51.1097946167],"type":"Point"}
}