{
  "type": "Feature",
  "properties": {
    "addr:full":"Rue De Weert St. Georges 83 Grez-doiceau Brabant Wallon 1390",
    "addr:housenumber":"83",
    "addr:postcode":"1390",
    "addr:street":"Rue De Weert St. Georges",
    "iso:country":"BE",
    "sg:address":"Rue De Weert St. Georges 83",
    "sg:city":"Grez-doiceau",
    "sg:orig_category":"Traducteurs and interpr\u00e8tes",
    "sg:phone":"+32 10 86 14 56",
    "sg:postcode":"1390",
    "sg:province":"Brabant Wallon",
    "wof:name":"Becu A. Cbtip/bkvtf",
    "wof:placetype":"venue"
},
  "geometry": {"coordinates":[4.6659340858,50.7909011841],"type":"Point"}
}