{
  "type": "Feature",
  "properties": {
    "addr:full":"Steenweg Op Mol 187 Oud-turnhout Antwerpen 2360",
    "addr:housenumber":"187",
    "addr:postcode":"2360",
    "addr:street":"Steenweg Op Mol",
    "iso:country":"BE",
    "sg:address":"Steenweg Op Mol 187",
    "sg:city":"Oud-turnhout",
    "sg:orig_category":"Warenhuizen",
    "sg:phone":"+32 14 45 48 84",
    "sg:postcode":"2360",
    "sg:province":"Antwerpen",
    "wof:name":"Intraco",
    "wof:placetype":"venue"
},
  "geometry": {"coordinates":[5.0000801086,51.3108787537],"type":"Point"}
}