{
  "type": "Feature",
  "properties": {
    "addr:full":"Jean Not\u00e9straat 2 Edegem Antwerpen 2650",
    "addr:housenumber":"2",
    "addr:postcode":"2650",
    "addr:street":"Jean Note\u0301Straat",
    "iso:country":"BE",
    "sg:address":"Jean Not\u00e9straat 2",
    "sg:city":"Edegem",
    "sg:classifiers":[
        {
            "category":"Social Services",
            "subcategory":"Retirement Home",
            "type":"Services"
        }
    ],
    "sg:phone":"+32 3 457 19 60",
    "sg:postcode":"2650",
    "sg:province":"Antwerpen",
    "sg:tags":[
        "society",
        "protection",
        "animal"
    ],
    "wof:name":"Den Dierenvriend Vzw",
    "wof:placetype":"venue"
},
  "geometry": {"coordinates":[4.4468359947,51.1479873657],"type":"Point"}
}