{
  "type": "Feature",
  "properties": {
    "addr:full":"Courte Rue Du B\u00c9guinage 3 Wavre Brabant Wallon 1300",
    "addr:housenumber":"3;1300",
    "addr:street":"Rue Du Be\u0301Guinage",
    "iso:country":"BE",
    "sg:address":"Courte Rue Du B\u00c9guinage 3",
    "sg:city":"Wavre",
    "sg:orig_category":"Immobili\u00ebnkantoren",
    "sg:phone":"+32 10 24 54 30",
    "sg:postcode":"1300",
    "sg:province":"Brabant Wallon",
    "wof:name":"Comimas",
    "wof:placetype":"venue"
},
  "geometry": {"coordinates":[4.6094331741,50.7168312073],"type":"Point"}
}