{
  "type": "Feature",
  "properties": {
    "addr:full":"Velle 86 Temse Oost-Vlaanderen 9140",
    "addr:housenumber":"86",
    "addr:postcode":"9140",
    "addr:street":"Velle",
    "iso:country":"BE",
    "sg:address":"Velle 86",
    "sg:city":"Temse",
    "sg:orig_category":"Brood, gebak and snoepgoed",
    "sg:phone":"+32 3 771 00 98",
    "sg:postcode":"9140",
    "sg:province":"Oost-Vlaanderen",
    "wof:name":"Bakkerij Wim Vermeulen",
    "wof:placetype":"venue"
},
  "geometry": {"coordinates":[4.205684185,51.1596832275],"type":"Point"}
}