{
  "type": "Feature",
  "properties": {
    "iso:country":"BE",
    "sg:address":"Holt 12",
    "sg:city":"Bilzen",
    "sg:orig_category":"Electrom\u00e9nager, t\u00e9l\u00e9visions and radios. R\u00e9parations d'appareils \u00e9lectrom\u00e9nagers",
    "sg:phone":"+32 89 41 78 73",
    "sg:postcode":"3740",
    "sg:province":"Limburg",
    "wof:name":"Elektro 2000",
    "wof:placetype":"venue"
},
  "geometry": {"coordinates":[5.4850311279,50.8844451904],"type":"Point"}
}