{
  "type": "Feature",
  "properties": {
    "addr:full":"Hertenstraat 28 Wellen Limburg 3830",
    "addr:housenumber":"28",
    "addr:postcode":"3830",
    "addr:street":"Hertenstraat",
    "iso:country":"BE",
    "sg:address":"Hertenstraat 28",
    "sg:city":"Wellen",
    "sg:classifiers":[
        {
            "category":"Farming",
            "subcategory":"Crops",
            "type":"Manufacturing & Wholesale Goods"
        }
    ],
    "sg:phone":"+32 12 74 10 34",
    "sg:postcode":"3830",
    "sg:province":"Limburg",
    "sg:tags":[
        "vegetable",
        "fruit",
        "-",
        "grower"
    ],
    "wof:name":"Tournel R",
    "wof:placetype":"venue"
},
  "geometry": {"coordinates":[5.3372302055,50.8350105286],"type":"Point"}
}