{
  "type": "Feature",
  "properties": {
    "addr:full":"Holsbeeksesteenweg 133 Leuven Vlaams-Brabant 3010",
    "addr:housenumber":"133",
    "addr:postcode":"3010",
    "addr:street":"Holsbeeksesteenweg",
    "iso:country":"BE",
    "sg:address":"Holsbeeksesteenweg 133",
    "sg:city":"Leuven",
    "sg:orig_category":"Banken and kredietinstellingen",
    "sg:phone":"+32 16 26 02 23",
    "sg:postcode":"3010",
    "sg:province":"Vlaams-Brabant",
    "wof:name":"Kbc",
    "wof:placetype":"venue"
},
  "geometry": {"coordinates":[4.7304501534,50.889755249],"type":"Point"}
}