{
  "type": "Feature",
  "properties": {
    "iso:country":"BE",
    "sg:address":"Avenue Du Bosquet 15",
    "sg:city":"Rixensart",
    "sg:orig_category":"Verlichting and huishoudartikelen",
    "sg:phone":"+32 2 652 01 03",
    "sg:postcode":"1332",
    "sg:province":"Brabant Wallon",
    "wof:name":"Dujardin",
    "wof:placetype":"venue"
},
  "geometry": {"coordinates":[4.4919691086,50.7256278992],"type":"Point"}
}