{
  "type": "Feature",
  "properties": {
    "addr:full":"Breidelstraat 2 Oostende West-Vlaanderen 8400",
    "addr:housenumber":"2",
    "addr:postcode":"8400",
    "addr:street":"Breidelstraat",
    "iso:country":"BE",
    "sg:address":"Breidelstraat 2",
    "sg:city":"Oostende",
    "sg:orig_category":"Pain, p\u00e2tisseries and confiseries",
    "sg:phone":"+32 59 80 21 61",
    "sg:postcode":"8400",
    "sg:province":"West-Vlaanderen",
    "wof:name":"Bakkerij Gheysen I.",
    "wof:placetype":"venue"
},
  "geometry": {"coordinates":[2.9184861183,51.2320899963],"type":"Point"}
}