{
  "type": "Feature",
  "properties": {
    "addr:full":"Rue Albert Ier 25 Mettet Namur 5640",
    "addr:housenumber":"25",
    "addr:postcode":"5640",
    "addr:street":"Rue Albert Ier",
    "iso:country":"BE",
    "sg:address":"Rue Albert Ier 25",
    "sg:city":"Mettet",
    "sg:classifiers":[
        {
            "category":"Cafe",
            "type":"Food & Drink"
        }
    ],
    "sg:phone":"+32 71 72 78 56",
    "sg:postcode":"5640",
    "sg:province":"Namur",
    "sg:tags":[
        "caf\u00e9s"
    ],
    "wof:name":"Caf\u00c9 De La Jeunesse",
    "wof:placetype":"venue"
},
  "geometry": {"coordinates":[4.6583838463,50.3223724365],"type":"Point"}
}