{
  "type": "Feature",
  "properties": {
    "addr:full":"Martelarenplaats Lubbeek Vlaams-Brabant 3210",
    "addr:postcode":"3210",
    "addr:street":"Martelarenplaats",
    "iso:country":"BE",
    "sg:address":"Martelarenplaats",
    "sg:city":"Lubbeek",
    "sg:orig_category":"Enseignement maternel and primaire",
    "sg:phone":"+32 16 62 13 43",
    "sg:postcode":"3210",
    "sg:province":"Vlaams-Brabant",
    "wof:name":"Gemeentelijke Basisschool",
    "wof:placetype":"venue"
},
  "geometry": {"coordinates":[4.7681088448,50.8953018188],"type":"Point"}
}