{
  "type": "Feature",
  "properties": {
    "iso:country":"BE",
    "sg:address":"Rue Puits-en-sock 99",
    "sg:city":"Li\u00e8ge 1 (li\u00e8ge 2)",
    "sg:classifiers":[
        {
            "category":"Food & Beverages",
            "subcategory":"Meat & Fish",
            "type":"Retail Goods"
        }
    ],
    "sg:phone":"+32 4 343 97 70",
    "sg:postcode":"4020",
    "sg:province":"Li\u00e8ge",
    "sg:tags":[
        "poultry",
        "whol",
        "game",
        "-"
    ],
    "wof:name":"Dekeyser (maison)",
    "wof:placetype":"venue"
},
  "geometry": {"coordinates":[5.5852909088,50.6392936707],"type":"Point"}
}