{
  "type": "Feature",
  "properties": {
    "iso:country":"BE",
    "sg:address":"Baalsebaan 324ba",
    "sg:city":"Tremelo",
    "sg:orig_category":"Epiceries",
    "sg:phone":"+32 16 53 05 86",
    "sg:postcode":"3128",
    "sg:province":"Vlaams-Brabant",
    "wof:name":"Marie-jos\u00c9e Neefs",
    "wof:placetype":"venue"
},
  "geometry": {"coordinates":[4.7508821487,50.9948234558],"type":"Point"}
}