{
  "type": "Feature",
  "properties": {
    "addr:full":"Vrieskaai 25 Antwerpen Antwerpen 2030",
    "addr:housenumber":"25",
    "addr:postcode":"2030",
    "addr:street":"Vrieskaai",
    "iso:country":"BE",
    "sg:address":"Vrieskaai 25",
    "sg:city":"Antwerpen",
    "sg:classifiers":[
        {
            "category":"Harbor",
            "type":"Transportation"
        }
    ],
    "sg:phone":"+32 3 544 34 60",
    "sg:postcode":"2030",
    "sg:province":"Antwerpen",
    "sg:tags":[
        "port",
        "facility"
    ],
    "wof:name":"Waeslantnatie Nv",
    "wof:placetype":"venue"
},
  "geometry": {"coordinates":[4.3982839584,51.2541847229],"type":"Point"}
}