{
  "type": "Feature",
  "properties": {
    "iso:country":"BE",
    "sg:address":"Brugstraat 101",
    "sg:city":"Bilzen",
    "sg:classifiers":[
        {
            "category":"Real Estate",
            "subcategory":"Architect",
            "type":"Services"
        }
    ],
    "sg:phone":"+32 89 50 20 22",
    "sg:postcode":"3740",
    "sg:province":"Limburg",
    "wof:name":"Slegers M",
    "wof:placetype":"venue"
},
  "geometry": {"coordinates":[5.5216708183,50.8660125732],"type":"Point"}
}