{
  "type": "Feature",
  "properties": {
    "iso:country":"BE",
    "sg:address":"Rue De La Fontaine Saint-pierre 27",
    "sg:city":"Rochefort (wavreille)",
    "sg:classifiers":[
        {
            "category":"Fast Food",
            "type":"Food & Drink"
        }
    ],
    "sg:phone":"+32 84 21 43 96",
    "sg:postcode":"5580",
    "sg:province":"Namur",
    "sg:tags":[
        "fried",
        "stand",
        "potato"
    ],
    "wof:name":"Brasseur Friterie",
    "wof:placetype":"venue"
},
  "geometry": {"coordinates":[5.2554311752,50.1207962036],"type":"Point"}
}