{
  "type": "Feature",
  "properties": {
    "addr:full":"Aachener Strasse 39 Sankt Vith Li\u00e8ge 4780",
    "addr:housenumber":"39",
    "addr:postcode":"4780",
    "addr:street":"Aachener Strasse",
    "iso:country":"BE",
    "sg:address":"Aachener Strasse 39",
    "sg:city":"Sankt Vith",
    "sg:classifiers":[
        {
            "category":"Utilities",
            "subcategory":"Fuel Oil & Lpg",
            "type":"Services"
        }
    ],
    "sg:phone":"+32 80 22 80 49",
    "sg:postcode":"4780",
    "sg:province":"Li\u00e8ge",
    "wof:name":"Jacobs C",
    "wof:placetype":"venue"
},
  "geometry": {"coordinates":[6.1272859573,50.2848205566],"type":"Point"}
}