{
  "type": "Feature",
  "properties": {
    "iso:country":"BE",
    "sg:address":"Elzeelsesteenweg 236",
    "sg:city":"Ronse/renaix",
    "sg:orig_category":"Kapsalons",
    "sg:phone":"+32 55 21 12 54",
    "sg:postcode":"9600",
    "sg:province":"Oost-Vlaanderen",
    "wof:name":"Coiffure Bilitis",
    "wof:placetype":"venue"
},
  "geometry": {"coordinates":[3.6188619137,50.740650177],"type":"Point"}
}