{
  "type": "Feature",
  "properties": {
    "iso:country":"BE",
    "sg:address":"Boulevard Dolez 24",
    "sg:city":"Mons",
    "sg:classifiers":[
        {
            "category":"Real Estate",
            "subcategory":"Architect",
            "type":"Services"
        }
    ],
    "sg:phone":"+32 65 35 51 26",
    "sg:postcode":"7000",
    "sg:province":"Hainaut",
    "wof:name":"Fasseaux C",
    "wof:placetype":"venue"
},
  "geometry": {"coordinates":[3.9582700729,50.4518356323],"type":"Point"}
}