{
  "type": "Feature",
  "properties": {
    "iso:country":"BE",
    "sg:address":"Rue Murebure",
    "sg:city":"St Nicolas",
    "sg:orig_category":"RESTAURANTS: RESTAURANTS FAST FOOD AND \u00c0 EMPORTER. RESTAURANTS. RESTAURANTS LIVRAISON \u00c0 DOMICILE",
    "sg:phone":"+32 4 233 13 81",
    "sg:postcode":"4420",
    "sg:province":"Li\u00e8ge",
    "wof:name":"Expresso",
    "wof:placetype":"venue"
},
  "geometry": {"coordinates":[5.5185480118,50.6323699951],"type":"Point"}
}