{
  "type": "Feature",
  "properties": {
    "iso:country":"BE",
    "sg:address":"Lesagestraat 16",
    "sg:city":"Steenokkerzeel",
    "sg:classifiers":[
        {
            "category":"Professional",
            "subcategory":"Engineering",
            "type":"Services"
        }
    ],
    "sg:phone":"+32 2 751 39 45",
    "sg:postcode":"1820",
    "sg:province":"Vlaams-Brabant",
    "sg:tags":[
        "-"
    ],
    "wof:name":"Thp Engineering And Software",
    "wof:placetype":"venue"
},
  "geometry": {"coordinates":[4.5131387711,50.9209976196],"type":"Point"}
}