{
  "type": "Feature",
  "properties": {
    "iso:country":"BE",
    "sg:address":"Desguinlei 42",
    "sg:city":"Antwerpen",
    "sg:orig_category":"Geluidsopnames",
    "sg:phone":"+32 3 238 70 77",
    "sg:postcode":"2018",
    "sg:province":"Antwerpen",
    "wof:name":"Little Major Productions",
    "wof:placetype":"venue"
},
  "geometry": {"coordinates":[4.3936300278,51.1978988647],"type":"Point"}
}