{
  "type": "Feature",
  "properties": {
    "addr:full":"La Forge 8 Thimister-clermont Li\u00e8ge 4890",
    "addr:housenumber":"8",
    "addr:postcode":"4890",
    "addr:street":"La Forge",
    "iso:country":"BE",
    "sg:address":"La Forge 8",
    "sg:city":"Thimister-clermont",
    "sg:classifiers":[
        {
            "category":"Food & Beverages",
            "subcategory":"Fruits & Vegetables",
            "type":"Retail Goods"
        }
    ],
    "sg:phone":"+32 87 44 51 62",
    "sg:postcode":"4890",
    "sg:province":"Li\u00e8ge",
    "sg:tags":[
        "l\u00e9gumes"
    ],
    "wof:name":"M.jobkenne Et Fils",
    "wof:placetype":"venue"
},
  "geometry": {"coordinates":[5.8811740875,50.6450538635],"type":"Point"}
}