{
  "type": "Feature",
  "properties": {
    "addr:full":"Place D'herchies 8 Jurbise Hainaut 7050",
    "addr:housenumber":"8",
    "addr:postcode":"7050",
    "addr:street":"Place D'Herchies",
    "iso:country":"BE",
    "sg:address":"Place D'herchies 8",
    "sg:city":"Jurbise",
    "sg:orig_category":"Epiceries. Jeux de hasard",
    "sg:phone":"+32 65 22 57 19",
    "sg:postcode":"7050",
    "sg:province":"Hainaut",
    "wof:name":"Tierc\u00c9 Vincennes",
    "wof:placetype":"venue"
},
  "geometry": {"coordinates":[3.8854579926,50.505317688],"type":"Point"}
}