{
  "type": "Feature",
  "properties": {
    "iso:country":"BE",
    "sg:address":"Edmond Laponstraat 1",
    "sg:city":"Oostende",
    "sg:classifiers":[
        {
            "category":"Food & Beverages",
            "subcategory":"Fruits & Vegetables",
            "type":"Retail Goods"
        }
    ],
    "sg:phone":"+32 59 50 86 53",
    "sg:postcode":"8400",
    "sg:province":"West-Vlaanderen",
    "sg:tags":[
        "l\u00e9gumes"
    ],
    "wof:name":"Rudy Bogaert",
    "wof:placetype":"venue"
},
  "geometry": {"coordinates":[2.9091119766,51.2251815796],"type":"Point"}
}