{
  "type": "Feature",
  "properties": {
    "iso:country":"BE",
    "sg:address":"Exschoor 8",
    "sg:city":"Neerpelt",
    "sg:orig_category":"Maatschappelijke dienstverlening",
    "sg:phone":"+32 11 64 66 58",
    "sg:postcode":"3910",
    "sg:province":"Limburg",
    "wof:name":"Rode Kruis St. Huibrechts Lille",
    "wof:placetype":"venue"
},
  "geometry": {"coordinates":[5.490213871,51.2172851562],"type":"Point"}
}