{
  "type": "Feature",
  "properties": {
    "iso:country":"BE",
    "sg:address":"Chauss\u00c9e Charlemagne 113",
    "sg:city":"Thimister",
    "sg:orig_category":"Installatie van houten of kunststof schrijnwerk",
    "sg:phone":"+32 87 44 52 74",
    "sg:postcode":"4890",
    "sg:province":"Li\u00e8ge",
    "wof:name":"Jacquet Francis",
    "wof:placetype":"venue"
},
  "geometry": {"coordinates":[5.8640837669,50.6541099548],"type":"Point"}
}