{
  "type": "Feature",
  "properties": {
    "addr:full":"Wezenstraat 11 Melle Oost-Vlaanderen 9090",
    "addr:housenumber":"11",
    "addr:postcode":"9090",
    "addr:street":"Wezenstraat",
    "iso:country":"BE",
    "sg:address":"Wezenstraat 11",
    "sg:city":"Melle",
    "sg:classifiers":[
        {
            "category":"Health Services",
            "subcategory":"Health Practitioner",
            "type":"Services"
        }
    ],
    "sg:phone":"+32 9 272 60 72",
    "sg:postcode":"9090",
    "sg:province":"Oost-Vlaanderen",
    "sg:tags":[
        "physiotherapist"
    ],
    "wof:name":"Lavers Carine",
    "wof:placetype":"venue"
},
  "geometry": {"coordinates":[3.8002409935,51.0047569275],"type":"Point"}
}