{
  "type": "Feature",
  "properties": {
    "addr:full":"Rue Rodenbach 69 Bruxelles Bruxelles-Capitale 1190",
    "addr:housenumber":"69",
    "addr:postcode":"1190",
    "addr:street":"Rue Rodenbach",
    "iso:country":"BE",
    "sg:address":"Rue Rodenbach 69",
    "sg:city":"Bruxelles",
    "sg:orig_category":"Mat\u00e9riel \u00e9lectrique and \u00e9lectronique Gr",
    "sg:phone":"+32 2 345 54 67",
    "sg:postcode":"1190",
    "sg:province":"Bruxelles-Capitale",
    "wof:name":"Gosselin",
    "wof:placetype":"venue"
},
  "geometry": {"coordinates":[4.3440170288,50.8184356689],"type":"Point"}
}