{
  "type": "Feature",
  "properties": {
    "iso:country":"BE",
    "sg:address":"Nieuwebrugstraat 15",
    "sg:city":"Ronse/renaix",
    "sg:orig_category":"Bouwmaterialen Gh",
    "sg:phone":"+32 55 20 78 02",
    "sg:postcode":"9600",
    "sg:province":"Oost-Vlaanderen",
    "wof:name":"Delange Dirk",
    "wof:placetype":"venue"
},
  "geometry": {"coordinates":[3.6070721149,50.7441596985],"type":"Point"}
}