{
  "type": "Feature",
  "properties": {
    "iso:country":"BE",
    "sg:address":"Waalse Kaai 18",
    "sg:city":"Antwerpen",
    "sg:classifiers":[
        {
            "category":"Restaurant",
            "type":"Food & Drink"
        }
    ],
    "sg:phone":"+32 3 248 36 86",
    "sg:postcode":"2000",
    "sg:province":"Antwerpen",
    "sg:tags":[
        "caf\u00e9s"
    ],
    "wof:name":"Nick's Cafe",
    "wof:placetype":"venue"
},
  "geometry": {"coordinates":[4.3907141685,51.2113494873],"type":"Point"}
}