{
  "type": "Feature",
  "properties": {
    "addr:full":"Ravenshout Tessenderlo Limburg 3980",
    "addr:postcode":"3980",
    "addr:street":"Limburg",
    "iso:country":"BE",
    "sg:address":"Ravenshout",
    "sg:city":"Tessenderlo",
    "sg:classifiers":[
        {
            "category":"Manufacturing",
            "subcategory":"Rubber & Plastics",
            "type":"Manufacturing & Wholesale Goods"
        }
    ],
    "sg:phone":"+32 13 67 02 90",
    "sg:postcode":"3980",
    "sg:province":"Limburg",
    "sg:tags":[
        "foam"
    ],
    "wof:name":"Fehrer Benelux Nv",
    "wof:placetype":"venue"
},
  "geometry": {"coordinates":[5.1427550316,51.0713005066],"type":"Point"}
}