{
  "type": "Feature",
  "properties": {
    "addr:full":"Rysselhofstraat 23 Kaprijke Oost-Vlaanderen 9970",
    "addr:housenumber":"23",
    "addr:postcode":"9970",
    "addr:street":"Rysselhofstraat",
    "iso:country":"BE",
    "sg:address":"Rysselhofstraat 23",
    "sg:city":"Kaprijke",
    "sg:classifiers":[
        {
            "category":"Real Estate",
            "subcategory":"Surveying",
            "type":"Services"
        }
    ],
    "sg:phone":"+32 9 373 44 37",
    "sg:postcode":"9970",
    "sg:province":"Oost-Vlaanderen",
    "sg:tags":[
        "surveyor",
        "land"
    ],
    "wof:name":"De Pauw F",
    "wof:placetype":"venue"
},
  "geometry": {"coordinates":[3.6058580875,51.2287712097],"type":"Point"}
}