{
  "type": "Feature",
  "properties": {
    "iso:country":"BE",
    "sg:address":"Rue Des Ap\u00f4tres 46",
    "sg:city":"Mons",
    "sg:classifiers":[
        {
            "category":"Organizations",
            "subcategory":"Community Association",
            "type":"Services"
        }
    ],
    "sg:phone":"+32 65 84 49 07",
    "sg:postcode":"7000",
    "sg:province":"Hainaut",
    "sg:tags":[
        "cultural"
    ],
    "wof:name":"Education Sans Frontieres",
    "wof:placetype":"venue"
},
  "geometry": {"coordinates":[3.9646139145,50.4572601318],"type":"Point"}
}