{
  "type": "Feature",
  "properties": {
    "iso:country":"BE",
    "sg:address":"Hille 148",
    "sg:city":"Wingene (zwevezele)",
    "sg:classifiers":[
        {
            "category":"Professional",
            "subcategory":"Lawyer & Legal Services",
            "type":"Services"
        }
    ],
    "sg:phone":"+32 51 61 11 30",
    "sg:postcode":"8750",
    "sg:province":"West-Vlaanderen",
    "wof:name":"Vande Walle Koen",
    "wof:placetype":"venue"
},
  "geometry": {"coordinates":[3.2259221077,51.0461006165],"type":"Point"}
}