{
  "type": "Feature",
  "properties": {
    "addr:full":"Scheihagenstraat 34 Kontich Antwerpen 2550",
    "addr:housenumber":"34",
    "addr:postcode":"2550",
    "addr:street":"Scheihagenstraat",
    "iso:country":"BE",
    "sg:address":"Scheihagenstraat 34",
    "sg:city":"Kontich",
    "sg:orig_category":"Studios photographiques",
    "sg:phone":"+32 3 457 23 45",
    "sg:postcode":"2550",
    "sg:province":"Antwerpen",
    "wof:name":"Annick De Wandeleir",
    "wof:placetype":"venue"
},
  "geometry": {"coordinates":[4.4672789574,51.1247787476],"type":"Point"}
}