{
  "type": "Feature",
  "properties": {
    "addr:full":"Geerstraat 2 Hechtel-eksel Limburg 3941",
    "addr:housenumber":"2",
    "addr:postcode":"3941",
    "addr:street":"Geerstraat",
    "iso:country":"BE",
    "sg:address":"Geerstraat 2",
    "sg:city":"Hechtel-eksel",
    "sg:orig_category":"M\u00e9decins and sp\u00e9cialistes",
    "sg:phone":"+32 11 73 43 60",
    "sg:postcode":"3941",
    "sg:province":"Limburg",
    "wof:name":"Jo Linmans",
    "wof:placetype":"venue"
},
  "geometry": {"coordinates":[5.3950948715,51.1551971436],"type":"Point"}
}