{
  "type": "Feature",
  "properties": {
    "iso:country":"BE",
    "sg:address":"Place Saint-denis 29-30",
    "sg:city":"Bruxelles (forest)",
    "sg:orig_category":"Non-Classified Establishments",
    "sg:phone":"+32 2 376 01 06",
    "sg:postcode":"1190",
    "sg:province":"Bruxelles-Capitale",
    "wof:name":"I.d.e.a. Sprl",
    "wof:placetype":"venue"
},
  "geometry": {"coordinates":[4.3190498352,50.8127975464],"type":"Point"}
}