{
  "type": "Feature",
  "properties": {
    "iso:country":"BE",
    "sg:address":"De Theuxstraat 113",
    "sg:city":"Elsene/ixelles",
    "sg:orig_category":"Advocaten and juridische adviseurs",
    "sg:phone":"+32 2 646 32 17",
    "sg:postcode":"1050",
    "sg:province":"Bruxelles-Capitale",
    "wof:name":"W. Dumoulin",
    "wof:placetype":"venue"
},
  "geometry": {"coordinates":[4.3810768127,50.831615448],"type":"Point"}
}