{
  "type": "Feature",
  "properties": {
    "iso:country":"BE",
    "sg:address":"Boulevard Charles-vanp\u00c9e 51",
    "sg:city":"Nivelles",
    "sg:orig_category":"Catering and organisation de f\u00eates",
    "sg:phone":"+32 67 84 15 11",
    "sg:postcode":"1400",
    "sg:province":"Brabant Wallon",
    "wof:name":"Patrick De Huisser",
    "wof:placetype":"venue"
},
  "geometry": {"coordinates":[4.3287792206,50.5963020325],"type":"Point"}
}