{
  "type": "Feature",
  "properties": {
    "addr:full":"Rue Reine Astrid 1 Engis Li\u00e8ge 4480",
    "addr:housenumber":"1",
    "addr:postcode":"4480",
    "addr:street":"Rue Reine Astrid",
    "iso:country":"BE",
    "sg:address":"Rue Reine Astrid 1",
    "sg:city":"Engis",
    "sg:classifiers":[
        {
            "category":"Fast Food",
            "type":"Food & Drink"
        }
    ],
    "sg:phone":"+32 4 275 25 75",
    "sg:postcode":"4480",
    "sg:province":"Li\u00e8ge",
    "sg:tags":[
        "fried",
        "stand",
        "potato"
    ],
    "wof:name":"Cactus (le)",
    "wof:placetype":"venue"
},
  "geometry": {"coordinates":[5.4048700333,50.5821800232],"type":"Point"}
}