{
  "type": "Feature",
  "properties": {
    "iso:country":"BE",
    "sg:address":"Eksaardedorp 90-92",
    "sg:city":"Lokeren",
    "sg:orig_category":"Bloemen and planten",
    "sg:phone":"+32 9 346 59 20",
    "sg:postcode":"9160",
    "sg:province":"Oost-Vlaanderen",
    "wof:name":"Bloembinderij Oxalis",
    "wof:placetype":"venue"
},
  "geometry": {"coordinates":[3.9631440639,51.1220664978],"type":"Point"}
}