{
  "type": "Feature",
  "properties": {
    "addr:full":"Mechelbaan 446 Putte Antwerpen 2580",
    "addr:housenumber":"446",
    "addr:postcode":"2580",
    "addr:street":"Mechelbaan",
    "iso:country":"BE",
    "sg:address":"Mechelbaan 446",
    "sg:city":"Putte",
    "sg:orig_category":"S\u00e9curit\u00e9 sociale",
    "sg:phone":"+32 15 75 25 88",
    "sg:postcode":"2580",
    "sg:province":"Antwerpen",
    "wof:name":"Socialist. Mutualiteit",
    "wof:placetype":"venue"
},
  "geometry": {"coordinates":[4.6416621208,51.0595436096],"type":"Point"}
}