{
  "type": "Feature",
  "properties": {
    "iso:country":"BE",
    "sg:address":"Lutticher Strasse 232",
    "sg:city":"Kelmis/la Calamine",
    "sg:classifiers":[
        {
            "category":"Restaurant",
            "type":"Food & Drink"
        }
    ],
    "sg:phone":"+32 87 63 15 85",
    "sg:postcode":"4720",
    "sg:province":"Li\u00e8ge",
    "wof:name":"Salons Alt Keris",
    "wof:placetype":"venue"
},
  "geometry": {"coordinates":[6.0133099556,50.7142181396],"type":"Point"}
}