{
  "type": "Feature",
  "properties": {
    "addr:full":"Rue Lloyd Georges 15 Chatelet Hainaut 6200",
    "addr:housenumber":"15",
    "addr:postcode":"6200",
    "addr:street":"Rue Lloyd Georges;Hainaut",
    "iso:country":"BE",
    "sg:address":"Rue Lloyd Georges 15",
    "sg:city":"Chatelet",
    "sg:orig_category":"Algemeen secundair onderwijs Technisch and beroeps secundair onderwijs",
    "sg:phone":"+32 71 38 38 48",
    "sg:postcode":"6200",
    "sg:province":"Hainaut",
    "wof:name":"Coll\u00c8ge St.pie X",
    "wof:placetype":"venue"
},
  "geometry": {"coordinates":[4.5193638802,50.4123344421],"type":"Point"}
}