{
  "type": "Feature",
  "properties": {
    "iso:country":"BE",
    "sg:address":"Rue Longuebourse 48",
    "sg:city":"Charleroi",
    "sg:orig_category":"Installation \u00e9lectrique r\u00e9sidentielle",
    "sg:phone":"+32 71 41 37 42",
    "sg:postcode":"6061",
    "sg:province":"Hainaut",
    "wof:name":"Di Prata",
    "wof:placetype":"venue"
},
  "geometry": {"coordinates":[4.466299057,50.4137687683],"type":"Point"}
}