{
  "type": "Feature",
  "properties": {
    "addr:full":"Rue Du Commerce 91 Ciney Namur 5590",
    "addr:housenumber":"91",
    "addr:postcode":"5590",
    "addr:street":"Rue Du Commerce",
    "iso:country":"BE",
    "sg:address":"Rue Du Commerce 91",
    "sg:city":"Ciney",
    "sg:orig_category":"Boekhouders",
    "sg:postcode":"5590",
    "sg:province":"Namur",
    "wof:name":"Dominique Leger",
    "wof:placetype":"venue"
},
  "geometry": {"coordinates":[5.0957717896,50.2918739319],"type":"Point"}
}