{
  "type": "Feature",
  "properties": {
    "addr:full":"Stationstraat 96a Lommel Limburg 3920",
    "addr:housenumber":"96a",
    "addr:postcode":"3920",
    "addr:street":"Stationstraat",
    "iso:country":"BE",
    "sg:address":"Stationstraat 96a",
    "sg:city":"Lommel",
    "sg:orig_category":"Equipement divers pour commerces Epiceries. Produits surgel\u00e9s Gr",
    "sg:phone":"+32 11 55 34 46",
    "sg:postcode":"3920",
    "sg:province":"Limburg",
    "wof:name":"Ricosnacks",
    "wof:placetype":"venue"
},
  "geometry": {"coordinates":[5.31376791,51.2234687805],"type":"Point"}
}