{
  "type": "Feature",
  "properties": {
    "addr:full":"Rue Thier D'ohet 7 Rochefort Namur 5580",
    "addr:housenumber":"7",
    "addr:postcode":"5580",
    "addr:street":"Rue Thier D'Ohet",
    "iso:country":"BE",
    "sg:address":"Rue Thier D'ohet 7",
    "sg:city":"Rochefort",
    "sg:classifiers":[
        {
            "category":"Mining & Drilling",
            "type":"Manufacturing & Wholesale Goods"
        }
    ],
    "sg:phone":"+32 84 21 12 87",
    "sg:postcode":"5580",
    "sg:province":"Namur",
    "sg:tags":[
        "boring",
        "well"
    ],
    "wof:name":"Marichal Forage Sprl",
    "wof:placetype":"venue"
},
  "geometry": {"coordinates":[5.2162070274,50.163684845],"type":"Point"}
}