{
  "type": "Feature",
  "properties": {
    "iso:country":"BE",
    "sg:address":"Processieweg 7",
    "sg:city":"Torhout",
    "sg:orig_category":"Textiel",
    "sg:phone":"+32 50 22 28 02",
    "sg:postcode":"8820",
    "sg:province":"West-Vlaanderen",
    "wof:name":"Wolshop Nele",
    "wof:placetype":"venue"
},
  "geometry": {"coordinates":[3.0686941147,51.0992584229],"type":"Point"}
}