{
  "type": "Feature",
  "properties": {
    "addr:full":"Avenue Jupiter 7 Bruxelles (forest) Bruxelles-Capitale 1190",
    "addr:housenumber":"7",
    "addr:postcode":"1190",
    "addr:street":"Avenue Jupiter",
    "iso:country":"BE",
    "sg:address":"Avenue Jupiter 7",
    "sg:city":"Bruxelles (forest)",
    "sg:classifiers":[
        {
            "category":"Health Services",
            "subcategory":"Doctor",
            "type":"Services"
        }
    ],
    "sg:phone":"+32 2 343 55 11",
    "sg:postcode":"1190",
    "sg:province":"Bruxelles-Capitale",
    "sg:tags":[
        "medicinephysicians",
        "surgeon"
    ],
    "wof:name":"Berge Lydie",
    "wof:placetype":"venue"
},
  "geometry": {"coordinates":[4.3339281082,50.8156547546],"type":"Point"}
}