{
  "type": "Feature",
  "properties": {
    "addr:full":"Oude Baan 43 Bertem Vlaams-Brabant 3060",
    "addr:housenumber":"43",
    "addr:postcode":"3060",
    "addr:street":"Oude Baan",
    "iso:country":"BE",
    "sg:address":"Oude Baan 43",
    "sg:city":"Bertem",
    "sg:orig_category":"Sportclubs",
    "sg:phone":"+32 16 48 90 29",
    "sg:postcode":"3060",
    "sg:province":"Vlaams-Brabant",
    "wof:name":"Bertem Ac",
    "wof:placetype":"venue"
},
  "geometry": {"coordinates":[4.6353502274,50.8703575134],"type":"Point"}
}