{
  "type": "Feature",
  "properties": {
    "addr:full":"Chauss\u00e9e De Waterloo 1190 Bruxelles (uccle) Bruxelles-Capitale 1180",
    "addr:postcode":"1190;1180",
    "addr:street":"Chausse\u0301E De Waterloo",
    "iso:country":"BE",
    "sg:address":"Chauss\u00e9e De Waterloo 1190",
    "sg:city":"Bruxelles (uccle)",
    "sg:classifiers":[
        {
            "category":"Sports & Exercise",
            "subcategory":"Gym",
            "type":"Entertainment"
        }
    ],
    "sg:phone":"+32 475 59 62 35",
    "sg:postcode":"1180",
    "sg:province":"Bruxelles-Capitale",
    "sg:tags":[
        "fitness"
    ],
    "wof:name":"Gym Contact Asbl",
    "wof:placetype":"venue"
},
  "geometry": {"coordinates":[4.3738012314,50.7951431274],"type":"Point"}
}