{
  "type": "Feature",
  "properties": {
    "addr:full":"Schorvoortstraat 38 Turnhout Antwerpen 2300",
    "addr:housenumber":"38",
    "addr:postcode":"2300",
    "addr:street":"Schorvoortstraat",
    "iso:country":"BE",
    "sg:address":"Schorvoortstraat 38",
    "sg:city":"Turnhout",
    "sg:orig_category":"Pain, p\u00e2tisseries and confiseries",
    "sg:phone":"+32 14 41 55 93",
    "sg:postcode":"2300",
    "sg:province":"Antwerpen",
    "wof:name":"Bakkerij Vandeweyer P.-i.",
    "wof:placetype":"venue"
},
  "geometry": {"coordinates":[4.9524669647,51.3070220947],"type":"Point"}
}