{
  "type": "Feature",
  "properties": {
    "iso:country":"BE",
    "sg:address":"Hasseltsesteenweg 121",
    "sg:city":"Sint-truiden",
    "sg:orig_category":"Newspapers, magazines, periodicals - Distribution",
    "sg:phone":"+32 11 68 33 11",
    "sg:postcode":"3800",
    "sg:province":"Limburg",
    "wof:name":"Di Malgo Balloons",
    "wof:placetype":"venue"
},
  "geometry": {"coordinates":[5.2025399208,50.8290252686],"type":"Point"}
}