{
  "type": "Feature",
  "properties": {
    "iso:country":"BE",
    "sg:address":"Tragel 7",
    "sg:city":"Aalst",
    "sg:orig_category":"Salles de spectacles",
    "sg:phone":"+32 53 70 02 17",
    "sg:postcode":"9300",
    "sg:province":"Oost-Vlaanderen",
    "wof:name":"Galerij S 65",
    "wof:placetype":"venue"
},
  "geometry": {"coordinates":[4.0364379883,50.9476966858],"type":"Point"}
}