{
  "type": "Feature",
  "properties": {
    "addr:full":"Route D\u00b4ohain 3 Lasne Brabant Wallon 1380",
    "addr:housenumber":"3",
    "addr:postcode":"1380",
    "addr:street":"Route D\u00b4Ohain",
    "iso:country":"BE",
    "sg:address":"Route D\u00b4ohain 3",
    "sg:city":"Lasne",
    "sg:orig_category":"Diverse kredietdiensten",
    "sg:postcode":"1380",
    "sg:province":"Brabant Wallon",
    "wof:name":"Bancontact-mister Cash",
    "wof:placetype":"venue"
},
  "geometry": {"coordinates":[4.482530117,50.6870117188],"type":"Point"}
}