{
  "type": "Feature",
  "properties": {
    "iso:country":"BE",
    "sg:address":"Blauwkasteelweg 12",
    "sg:city":"Brugge",
    "sg:orig_category":"M\u00e9decins and sp\u00e9cialistes",
    "sg:phone":"+32 50 37 37 47",
    "sg:postcode":"8310",
    "sg:province":"West-Vlaanderen",
    "wof:name":"Frank De Groote",
    "wof:placetype":"venue"
},
  "geometry": {"coordinates":[3.2434248924,51.2161636353],"type":"Point"}
}