{
  "type": "Feature",
  "properties": {
    "addr:full":"Jules Lagaelaan 25 Box 1 Roeselare West-Vlaanderen 8800",
    "addr:housenumber":"25;1",
    "addr:postcode":"8800",
    "addr:street":"Jules Lagaelaan;Box",
    "iso:country":"BE",
    "sg:address":"Jules Lagaelaan 25 Box 1",
    "sg:city":"Roeselare",
    "sg:classifiers":[
        {
            "category":"Bars & Pubs",
            "type":"Food & Drink"
        }
    ],
    "sg:phone":"+32 51 69 64 02",
    "sg:postcode":"8800",
    "sg:province":"West-Vlaanderen",
    "wof:name":"Netcenter",
    "wof:placetype":"venue"
},
  "geometry": {"coordinates":[3.1311929226,50.9484519958],"type":"Point"}
}