{
  "type": "Feature",
  "properties": {
    "iso:country":"BE",
    "sg:address":"Rue De Pilzen 15",
    "sg:city":"Li\u00e8ge 1 (jupille-sur-meuse)",
    "sg:classifiers":[
        {
            "category":"Professional",
            "subcategory":"Management & Consulting",
            "type":"Services"
        }
    ],
    "sg:phone":"+32 475 45 02 01",
    "sg:postcode":"4020",
    "sg:province":"Li\u00e8ge",
    "sg:tags":[
        "tax-consultants"
    ],
    "wof:name":"Romano A",
    "wof:placetype":"venue"
},
  "geometry": {"coordinates":[5.6157050133,50.63722229],"type":"Point"}
}