{
  "type": "Feature",
  "properties": {
    "iso:country":"BE",
    "sg:address":"Berlingmolenstraat 64",
    "sg:city":"Ardooie",
    "sg:classifiers":[
        {
            "category":"Retail",
            "subcategory":"Veterinary Services",
            "type":"Services"
        }
    ],
    "sg:phone":"+32 51 74 71 81",
    "sg:postcode":"8850",
    "sg:province":"West-Vlaanderen",
    "sg:tags":[
        "veterinarian"
    ],
    "wof:name":"Callewaert H",
    "wof:placetype":"venue"
},
  "geometry": {"coordinates":[3.2060709,50.9835166931],"type":"Point"}
}