{
  "type": "Feature",
  "properties": {
    "iso:country":"BE",
    "sg:address":"Zilverbeeklaan 58",
    "sg:city":"Mortsel",
    "sg:classifiers":[
        {
            "category":"Shopping",
            "subcategory":"Computers & Home Electronics",
            "type":"Retail Goods"
        }
    ],
    "sg:phone":"+32 3 449 84 16",
    "sg:postcode":"2640",
    "sg:province":"Antwerpen",
    "sg:tags":[
        "-",
        "television",
        "radio"
    ],
    "wof:name":"Elektro Ruggeveld Bvba",
    "wof:placetype":"venue"
},
  "geometry": {"coordinates":[4.4452672005,51.1872596741],"type":"Point"}
}