{
  "type": "Feature",
  "properties": {
    "iso:country":"BE",
    "sg:address":"Kouterbaan 46",
    "sg:city":"Aalst",
    "sg:orig_category":"V\u00e9hicules automobiles",
    "sg:phone":"+32 53 71 02 50",
    "sg:postcode":"9310",
    "sg:province":"Oost-Vlaanderen",
    "wof:name":"Garage Esperanza",
    "wof:placetype":"venue"
},
  "geometry": {"coordinates":[4.0670819283,50.9665298462],"type":"Point"}
}