{
  "type": "Feature",
  "properties": {
    "addr:full":"Hondsmertjesstraat 69 Izegem West-Vlaanderen 8870",
    "addr:housenumber":"69",
    "addr:postcode":"8870",
    "addr:street":"Hondsmertjesstraat",
    "iso:country":"BE",
    "sg:address":"Hondsmertjesstraat 69",
    "sg:city":"Izegem",
    "sg:orig_category":"Peinture. Rev\u00eatements pour sols and murs",
    "sg:phone":"+32 51 30 34 83",
    "sg:postcode":"8870",
    "sg:province":"West-Vlaanderen",
    "wof:name":"Maurits De Deygere",
    "wof:placetype":"venue"
},
  "geometry": {"coordinates":[3.1886260509,50.9375228882],"type":"Point"}
}