{
  "type": "Feature",
  "properties": {
    "iso:country":"BE",
    "sg:address":"Square Fran\u00e7ois Riga 24",
    "sg:city":"Bruxelles (schaerbeek)",
    "sg:classifiers":[
        {
            "category":"Health Services",
            "subcategory":"Health Practitioner",
            "type":"Services"
        }
    ],
    "sg:phone":"+32 2 216 62 61",
    "sg:postcode":"1030",
    "sg:province":"Bruxelles-Capitale",
    "sg:tags":[
        "physiotherapist"
    ],
    "wof:name":"Rucquoy J M",
    "wof:placetype":"venue"
},
  "geometry": {"coordinates":[4.3852910995,50.873714447],"type":"Point"}
}