{
  "type": "Feature",
  "properties": {
    "addr:full":"Urselseweg 63 Knesselare (groot) Oost-Vlaanderen 9910",
    "addr:housenumber":"63",
    "addr:postcode":"9910",
    "addr:street":"Urselseweg;Groot Oost-Vlaanderen",
    "iso:country":"BE",
    "sg:address":"Urselseweg 63",
    "sg:city":"Knesselare (groot)",
    "sg:orig_category":"Advocaten and juridische adviseurs Balie van Gent",
    "sg:phone":"+32 9 374 38 03",
    "sg:postcode":"9910",
    "sg:province":"Oost-Vlaanderen",
    "wof:name":"De Bree Nathalie",
    "wof:placetype":"venue"
},
  "geometry": {"coordinates":[3.4261949062,51.1347885132],"type":"Point"}
}