{
  "type": "Feature",
  "properties": {
    "addr:full":"Emile Bockstaellaan 247 Brussel/bruxelles Bruxelles-Capitale 1020",
    "addr:housenumber":"247",
    "addr:postcode":"1020",
    "addr:street":"Emile Bockstaellaan;/",
    "iso:country":"BE",
    "sg:address":"Emile Bockstaellaan 247",
    "sg:city":"Brussel/bruxelles",
    "sg:orig_category":"Artsen and specialisten Medische and orthopedische apparaten",
    "sg:phone":"+32 2 426 11 83",
    "sg:postcode":"1020",
    "sg:province":"Bruxelles-Capitale",
    "wof:name":"Henri Balck",
    "wof:placetype":"venue"
},
  "geometry": {"coordinates":[4.3480839729,50.8788604736],"type":"Point"}
}