{
  "type": "Feature",
  "properties": {
    "iso:country":"BE",
    "sg:address":"Louis Paul Boonstraat 24",
    "sg:city":"Ichtegem",
    "sg:orig_category":"Woningbouw",
    "sg:phone":"+32 59 29 08 11",
    "sg:postcode":"8480",
    "sg:province":"West-Vlaanderen",
    "wof:name":"Cattrysse M.",
    "wof:placetype":"venue"
},
  "geometry": {"coordinates":[3.021392107,51.1336708069],"type":"Point"}
}