{
  "type": "Feature",
  "properties": {
    "addr:full":"Begijnenstraat 18b5 Mechelen Antwerpen 2800",
    "addr:housenumber":"18b5",
    "addr:postcode":"2800",
    "addr:street":"Begijnenstraat",
    "iso:country":"BE",
    "sg:address":"Begijnenstraat 18b5",
    "sg:city":"Mechelen",
    "sg:orig_category":"Paramedische behandelingen",
    "sg:phone":"+32 15 29 25 88",
    "sg:postcode":"2800",
    "sg:province":"Antwerpen",
    "wof:name":"Thuiszorgcentrum",
    "wof:placetype":"venue"
},
  "geometry": {"coordinates":[4.4776511192,51.0280418396],"type":"Point"}
}