{
  "type": "Feature",
  "properties": {
    "addr:full":"Van Iseghemlaan 384 Oostende West-Vlaanderen 8400",
    "addr:housenumber":"384",
    "addr:postcode":"8400",
    "addr:street":"Iseghemlaan",
    "iso:country":"BE",
    "sg:address":"Van Iseghemlaan 384",
    "sg:city":"Oostende",
    "sg:classifiers":[
        {
            "category":"Restaurant",
            "type":"Food & Drink"
        }
    ],
    "sg:phone":"+32 59 80 84 75",
    "sg:postcode":"8400",
    "sg:province":"West-Vlaanderen",
    "sg:tags":[
        "caf\u00e9s"
    ],
    "wof:name":"Caf\u00c9 Feniks",
    "wof:placetype":"venue"
},
  "geometry": {"coordinates":[2.9105501175,51.2281913757],"type":"Point"}
}