{
  "type": "Feature",
  "properties": {
    "addr:full":"Graanmarkt 2 Antwerpen Antwerpen 2000",
    "addr:housenumber":"2",
    "addr:postcode":"2000",
    "addr:street":"Graanmarkt",
    "iso:country":"BE",
    "sg:address":"Graanmarkt 2",
    "sg:city":"Antwerpen",
    "sg:orig_category":"Avocats and conseillers juridiques",
    "sg:phone":"+32 3 203 62 62",
    "sg:postcode":"2000",
    "sg:province":"Antwerpen",
    "wof:name":"Olivier Van Causenbroeck",
    "wof:placetype":"venue"
},
  "geometry": {"coordinates":[4.4082159996,51.2161712646],"type":"Point"}
}