{
  "type": "Feature",
  "properties": {
    "iso:country":"BE",
    "sg:address":"Kapelstraat 136",
    "sg:city":"Schelle",
    "sg:orig_category":"Elektrische installaties voor woningen HERSTELLING ELEKTRISCHE HUISHOUDAPPARATEN Huishoudapparaten, ",
    "sg:phone":"+32 3 887 23 63",
    "sg:postcode":"2627",
    "sg:province":"Antwerpen",
    "wof:name":"Mylle Electro",
    "wof:placetype":"venue"
},
  "geometry": {"coordinates":[4.3265810013,51.1217384338],"type":"Point"}
}