{
  "type": "Feature",
  "properties": {
    "addr:full":"Hoogstraat 35a Willebroek Antwerpen 2830",
    "addr:housenumber":"35a",
    "addr:postcode":"2830",
    "addr:street":"Hoogstraat",
    "iso:country":"BE",
    "sg:address":"Hoogstraat 35a",
    "sg:city":"Willebroek",
    "sg:orig_category":"Tweedehandsgoederen",
    "sg:phone":"+32 3 866 19 17",
    "sg:postcode":"2830",
    "sg:province":"Antwerpen",
    "wof:name":"De Koopjeshoek",
    "wof:placetype":"venue"
},
  "geometry": {"coordinates":[4.3603191376,51.0326538086],"type":"Point"}
}