{
  "type": "Feature",
  "properties": {
    "addr:full":"Elisabeth Willemslaan 43 Haacht (wespelaar) Vlaams-Brabant 3150",
    "addr:housenumber":"43",
    "addr:postcode":"3150",
    "addr:street":"Elisabeth Willemslaan",
    "iso:country":"BE",
    "sg:address":"Elisabeth Willemslaan 43",
    "sg:city":"Haacht (wespelaar)",
    "sg:classifiers":[
        {
            "category":"Health Services",
            "subcategory":"Health Practitioner",
            "type":"Services"
        }
    ],
    "sg:phone":"+32 16 60 55 02",
    "sg:postcode":"3150",
    "sg:province":"Vlaams-Brabant",
    "sg:tags":[
        "physiotherapist"
    ],
    "wof:name":"Deroey Dirk",
    "wof:placetype":"venue"
},
  "geometry": {"coordinates":[4.6380391121,50.9567146301],"type":"Point"}
}