{
  "type": "Feature",
  "properties": {
    "addr:full":"Rue De Brabant 162 Schaarbeek/schaerbeek Bruxelles-Capitale 1030",
    "addr:housenumber":"162",
    "addr:postcode":"1030",
    "addr:street":"Rue De Brabant",
    "iso:country":"BE",
    "sg:address":"Rue De Brabant 162",
    "sg:city":"Schaarbeek/schaerbeek",
    "sg:orig_category":"Pharmaciens",
    "sg:phone":"+32 2 217 94 49",
    "sg:postcode":"1030",
    "sg:province":"Bruxelles-Capitale",
    "wof:name":"Roland Houben",
    "wof:placetype":"venue"
},
  "geometry": {"coordinates":[4.363547802,50.8604431152],"type":"Point"}
}