{
  "type": "Feature",
  "properties": {
    "addr:full":"Rue Des Clos Fleuris 22 Beauraing Namur 5570",
    "addr:housenumber":"22",
    "addr:postcode":"5570",
    "addr:street":"Rue Des Clos Fleuris",
    "iso:country":"BE",
    "sg:address":"Rue Des Clos Fleuris 22",
    "sg:city":"Beauraing",
    "sg:classifiers":[
        {
            "category":"Food & Beverages",
            "subcategory":"Liquor & Beverages",
            "type":"Retail Goods"
        }
    ],
    "sg:phone":"+32 82 74 46 42",
    "sg:postcode":"5570",
    "sg:province":"Namur",
    "sg:tags":[
        "-",
        "spirit",
        "wine"
    ],
    "wof:name":"Cave De Batisse (la) Sc",
    "wof:placetype":"venue"
},
  "geometry": {"coordinates":[4.9495201111,50.1119308472],"type":"Point"}
}