{
  "type": "Feature",
  "properties": {
    "addr:full":"Riddersstraat 1 Tongeren Limburg 3700",
    "addr:housenumber":"1",
    "addr:postcode":"3700",
    "addr:street":"Riddersstraat",
    "iso:country":"BE",
    "sg:address":"Riddersstraat 1",
    "sg:city":"Tongeren",
    "sg:classifiers":[
        {
            "category":"Wholesale",
            "subcategory":"Meat",
            "type":"Manufacturing & Wholesale Goods"
        }
    ],
    "sg:phone":"+32 12 23 23 41",
    "sg:postcode":"3700",
    "sg:province":"Limburg",
    "sg:tags":[
        "machine",
        "product",
        "-",
        "supply"
    ],
    "wof:name":"Berkel-jans-spako",
    "wof:placetype":"venue"
},
  "geometry": {"coordinates":[5.4660801888,50.780216217],"type":"Point"}
}