{
  "type": "Feature",
  "properties": {
    "iso:country":"BE",
    "sg:address":"Kapelstraat 156a",
    "sg:city":"Boom",
    "sg:classifiers":[
        {
            "category":"Manufacturing",
            "subcategory":"Wood Products",
            "type":"Manufacturing & Wholesale Goods"
        }
    ],
    "sg:phone":"+32 71 37 49 54",
    "sg:postcode":"2850",
    "sg:province":"Antwerpen",
    "sg:tags":[
        "pallet",
        "repair"
    ],
    "wof:name":"C.s.d. Palettes Sa",
    "wof:placetype":"venue"
},
  "geometry": {"coordinates":[4.4245052338,50.4448814392],"type":"Point"}
}