{
  "type": "Feature",
  "properties": {
    "addr:full":"Kloosterstraat 109 Antwerpen Antwerpen 2180",
    "addr:housenumber":"109",
    "addr:postcode":"2180",
    "addr:street":"Kloosterstraat",
    "iso:country":"BE",
    "sg:address":"Kloosterstraat 109",
    "sg:city":"Antwerpen",
    "sg:orig_category":"Verplichte sociale verzekeringen",
    "sg:phone":"+32 3 541 07 34",
    "sg:postcode":"2180",
    "sg:province":"Antwerpen",
    "wof:name":"Onafhankelijk Ziekenfonds",
    "wof:placetype":"venue"
},
  "geometry": {"coordinates":[4.3945679665,51.2149124146],"type":"Point"}
}