{
  "type": "Feature",
  "properties": {
    "addr:full":"Leopold I Straat 373 Jette/jette Bruxelles-Capitale 1090",
    "addr:housenumber":"373",
    "addr:postcode":"1090",
    "addr:street":"Leopold I Straat",
    "iso:country":"BE",
    "sg:address":"Leopold I Straat 373",
    "sg:city":"Jette/jette",
    "sg:orig_category":"Schoonmaakbedrijven and ongediertebestrijding",
    "sg:phone":"+32 2 426 03 08",
    "sg:postcode":"1090",
    "sg:province":"Bruxelles-Capitale",
    "wof:name":"Jette Clean",
    "wof:placetype":"venue"
},
  "geometry": {"coordinates":[4.334654808,50.8752822876],"type":"Point"}
}