{
  "type": "Feature",
  "properties": {
    "addr:full":"Rue Des Combattants 17 Brunehaut (bl\u00e9haries) Hainaut 7620",
    "addr:housenumber":"17",
    "addr:postcode":"7620",
    "addr:street":"Rue Des Combattants;Ble\u0301Haries Hainaut",
    "iso:country":"BE",
    "sg:address":"Rue Des Combattants 17",
    "sg:city":"Brunehaut (bl\u00e9haries)",
    "sg:classifiers":[
        {
            "category":"Home & Garden",
            "subcategory":"Hardware",
            "type":"Retail Goods"
        }
    ],
    "sg:phone":"+32 69 34 40 52",
    "sg:postcode":"7620",
    "sg:province":"Hainaut",
    "sg:tags":[
        "machine",
        "horticultural"
    ],
    "wof:name":"A.g.d. Services Sprl",
    "wof:placetype":"venue"
},
  "geometry": {"coordinates":[3.4211881161,50.5149002075],"type":"Point"}
}