{
  "type": "Feature",
  "properties": {
    "iso:country":"BE",
    "sg:address":"Koning Albertstraat 47",
    "sg:city":"Eeklo",
    "sg:classifiers":[
        {
            "category":"Farming",
            "subcategory":"Fish & Marine Products",
            "type":"Manufacturing & Wholesale Goods"
        }
    ],
    "sg:phone":"+32 9 377 90 93",
    "sg:postcode":"9900",
    "sg:province":"Oost-Vlaanderen",
    "sg:tags":[
        "retail",
        "-",
        "shellfish"
    ],
    "wof:name":"Zeester (de)",
    "wof:placetype":"venue"
},
  "geometry": {"coordinates":[3.5617830753,51.1851921082],"type":"Point"}
}