{
  "type": "Feature",
  "properties": {
    "addr:full":"Av Louise 27 Bruxelles Bruxelles-Capitale 1050",
    "addr:housenumber":"27",
    "addr:postcode":"1050",
    "addr:street":"Av Louise",
    "iso:country":"BE",
    "sg:address":"Av Louise 27",
    "sg:city":"Bruxelles",
    "sg:classifiers":[
        {
            "category":"Manufacturing",
            "subcategory":"Leather Goods",
            "type":"Manufacturing & Wholesale Goods"
        }
    ],
    "sg:phone":"+32 2 534 70 41",
    "sg:postcode":"1050",
    "sg:province":"Bruxelles-Capitale",
    "sg:tags":[
        "shoe"
    ],
    "wof:name":"St Dupont Benelux Sa",
    "wof:placetype":"venue"
},
  "geometry": {"coordinates":[4.3563280106,50.8344841003],"type":"Point"}
}