{
  "type": "Feature",
  "properties": {
    "iso:country":"BE",
    "sg:address":"Postbus 58",
    "sg:city":"Antwerpen5",
    "sg:classifiers":[
        {
            "category":"Arena",
            "subcategory":"Sports Club",
            "type":"Entertainment"
        }
    ],
    "sg:phone":"+32 3 235 67 20",
    "sg:postcode":"2050",
    "sg:province":"Antwerpen",
    "wof:name":"K.b.y.v.",
    "wof:placetype":"venue"
},
  "geometry": {"coordinates":[4.3689899445,51.2226295471],"type":"Point"}
}