{
  "type": "Feature",
  "properties": {
    "addr:full":"Steenweg Op Beerse 163 Merksplas Antwerpen 2330",
    "addr:housenumber":"163",
    "addr:postcode":"2330",
    "addr:street":"Steenweg Op Beerse",
    "iso:country":"BE",
    "sg:address":"Steenweg Op Beerse 163",
    "sg:city":"Merksplas",
    "sg:orig_category":"Eleveurs and marchands de porcs. Eleveurs de volaille",
    "sg:phone":"+32 14 63 36 16",
    "sg:postcode":"2330",
    "sg:province":"Antwerpen",
    "wof:name":"Jozef Verheyen",
    "wof:placetype":"venue"
},
  "geometry": {"coordinates":[4.8597640991,51.3409385681],"type":"Point"}
}