{
  "type": "Feature",
  "properties": {
    "iso:country":"BE",
    "sg:address":"Grand'route 20a",
    "sg:city":"Qu\u00e9vy (qu\u00e9vy-le-grand)",
    "sg:classifiers":[
        {
            "category":"Shopping",
            "subcategory":"Florist",
            "type":"Retail Goods"
        }
    ],
    "sg:phone":"+32 65 32 01 78",
    "sg:postcode":"7040",
    "sg:province":"Hainaut",
    "wof:name":"O Eden",
    "wof:placetype":"venue"
},
  "geometry": {"coordinates":[3.8975090981,50.3569107056],"type":"Point"}
}