{
  "type": "Feature",
  "properties": {
    "iso:country":"BE",
    "sg:address":"Avenue Louise 15",
    "sg:city":"Bruxelles (ixelles)",
    "sg:classifiers":[
        {
            "category":"Home & Garden",
            "subcategory":"Home Furnishings",
            "type":"Retail Goods"
        }
    ],
    "sg:phone":"+32 2 534 13 44",
    "sg:postcode":"1050",
    "sg:province":"Bruxelles-Capitale",
    "sg:tags":[
        "linen",
        "household",
        "-"
    ],
    "wof:name":"Descamps",
    "wof:placetype":"venue"
},
  "geometry": {"coordinates":[4.3559851646,50.8347511292],"type":"Point"}
}