{
  "type": "Feature",
  "properties": {
    "addr:full":"Bredabaan 375 Brasschaat Antwerpen 2930",
    "addr:housenumber":"375",
    "addr:postcode":"2930",
    "addr:street":"Bredabaan",
    "iso:country":"BE",
    "sg:address":"Bredabaan 375",
    "sg:city":"Brasschaat",
    "sg:orig_category":"S\u00e9curit\u00e9 sociale",
    "sg:phone":"+32 3 651 87 66",
    "sg:postcode":"2930",
    "sg:province":"Antwerpen",
    "wof:name":"Christelijk Ziekenfonds",
    "wof:placetype":"venue"
},
  "geometry": {"coordinates":[4.4914221764,51.2898254395],"type":"Point"}
}