{
  "type": "Feature",
  "properties": {
    "iso:country":"BE",
    "sg:address":"Rue De Mexico 16",
    "sg:city":"Sint-jans-molenbeek/molenbeek-saint-jean",
    "sg:orig_category":"Installation de serres, double vitrage and fen\u00eatres",
    "sg:phone":"+32 2 426 37 24",
    "sg:postcode":"1080",
    "sg:province":"Bruxelles-Capitale",
    "wof:name":"Fe. Bombaver",
    "wof:placetype":"venue"
},
  "geometry": {"coordinates":[4.3411288261,50.8607215881],"type":"Point"}
}