{
  "type": "Feature",
  "properties": {
    "iso:country":"BE",
    "sg:address":"Paleizenstraat 342",
    "sg:city":"Bruxelles",
    "sg:classifiers":[
        {
            "category":"Banks & Credit Unions",
            "subcategory":"Investment Brokerage",
            "type":"Services"
        }
    ],
    "sg:phone":"+32 2 203 31 36",
    "sg:postcode":"1000",
    "sg:province":"Bruxelles-Capitale",
    "sg:tags":[
        "-",
        "plastic"
    ],
    "wof:name":"Manuplex Sprl",
    "wof:placetype":"venue"
},
  "geometry": {"coordinates":[4.3622221947,50.8718795776],"type":"Point"}
}