{
  "type": "Feature",
  "properties": {
    "addr:full":"Hauptstrasse 69 Sankt Vith Li\u00e8ge 4780",
    "addr:housenumber":"69",
    "addr:postcode":"4780",
    "addr:street":"Hauptstrasse",
    "iso:country":"BE",
    "sg:address":"Hauptstrasse 69",
    "sg:city":"Sankt Vith",
    "sg:classifiers":[
        {
            "category":"Shopping",
            "subcategory":"Books",
            "type":"Retail Goods"
        }
    ],
    "sg:phone":"+32 80 22 85 97",
    "sg:postcode":"4780",
    "sg:province":"Li\u00e8ge",
    "sg:tags":[
        "bookseller"
    ],
    "wof:name":"Mausen M",
    "wof:placetype":"venue"
},
  "geometry": {"coordinates":[6.1254491806,50.2812004089],"type":"Point"}
}