{
  "type": "Feature",
  "properties": {
    "addr:full":"Canadezenstraat 135 Brugge West-Vlaanderen 8380",
    "addr:housenumber":"135",
    "addr:postcode":"8380",
    "addr:street":"Canadezenstraat",
    "iso:country":"BE",
    "sg:address":"Canadezenstraat 135",
    "sg:city":"Brugge",
    "sg:orig_category":"Bijouteries and horlogeries",
    "sg:phone":"+32 50 41 96 99",
    "sg:postcode":"8380",
    "sg:province":"West-Vlaanderen",
    "wof:name":"Delaro",
    "wof:placetype":"venue"
},
  "geometry": {"coordinates":[3.2288448811,51.2742958069],"type":"Point"}
}