{
  "type": "Feature",
  "properties": {
    "iso:country":"BE",
    "sg:address":"Victor Allardstraat 165",
    "sg:city":"Ukkel/uccle",
    "sg:orig_category":"Artsen and specialisten",
    "sg:phone":"+32 2 376 42 94",
    "sg:postcode":"1180",
    "sg:province":"Bruxelles-Capitale",
    "wof:name":"E. Stoupel",
    "wof:placetype":"venue"
},
  "geometry": {"coordinates":[4.3296260834,50.8010444641],"type":"Point"}
}