{
  "type": "Feature",
  "properties": {
    "addr:full":"Rue Des Li\u00c8geois 8 Aywaille Li\u00e8ge 4920",
    "addr:housenumber":"8",
    "addr:postcode":"4920",
    "addr:street":"Rue Des Lie\u0300Geois",
    "iso:country":"BE",
    "sg:address":"Rue Des Li\u00c8geois 8",
    "sg:city":"Aywaille",
    "sg:orig_category":"Woningbouw",
    "sg:phone":"+32 4 384 69 47",
    "sg:postcode":"4920",
    "sg:province":"Li\u00e8ge",
    "wof:name":"Didier Ehlen",
    "wof:placetype":"venue"
},
  "geometry": {"coordinates":[5.6599640846,50.4620780945],"type":"Point"}
}