{
  "type": "Feature",
  "properties": {
    "addr:full":"Schoverikstraat 8 Zutendaal Limburg 3690",
    "addr:housenumber":"8",
    "addr:postcode":"3690",
    "addr:street":"Schoverikstraat",
    "iso:country":"BE",
    "sg:address":"Schoverikstraat 8",
    "sg:city":"Zutendaal",
    "sg:classifiers":[
        {
            "category":"Health Services",
            "subcategory":"Health Practitioner",
            "type":"Services"
        }
    ],
    "sg:phone":"+32 89 61 18 47",
    "sg:postcode":"3690",
    "sg:province":"Limburg",
    "sg:tags":[
        "physiotherapist"
    ],
    "wof:name":"Aerts Els",
    "wof:placetype":"venue"
},
  "geometry": {"coordinates":[5.5524740219,50.9361114502],"type":"Point"}
}