{
  "type": "Feature",
  "properties": {
    "iso:country":"BE",
    "sg:address":"Koningin Astridlaan 193",
    "sg:city":"Mechelen",
    "sg:orig_category":"Paramedische behandelingen",
    "sg:phone":"+32 15 33 14 41",
    "sg:postcode":"2800",
    "sg:province":"Antwerpen",
    "wof:name":"T. Forrier",
    "wof:placetype":"venue"
},
  "geometry": {"coordinates":[4.4734458923,51.0222816467],"type":"Point"}
}