{
  "type": "Feature",
  "properties": {
    "addr:full":"Rue Chapelle Dieu 35 Gembloux-sur-orneau (gembloux) Namur 5030",
    "addr:housenumber":"35",
    "addr:postcode":"5030",
    "addr:street":"Rue Chapelle Dieu;Namur",
    "iso:country":"BE",
    "sg:address":"Rue Chapelle Dieu 35",
    "sg:city":"Gembloux-sur-orneau (gembloux)",
    "sg:classifiers":[
        {
            "category":"Health Services",
            "subcategory":"Dentist",
            "type":"Services"
        }
    ],
    "sg:phone":"+32 81 60 10 85",
    "sg:postcode":"5030",
    "sg:province":"Namur",
    "wof:name":"Determe Marie-sophie",
    "wof:placetype":"venue"
},
  "geometry": {"coordinates":[4.6984291077,50.5584144592],"type":"Point"}
}