{
  "type": "Feature",
  "properties": {
    "addr:full":"Clos Gouyasse 7 Ottignies-louvain-la-neuve Brabant Wallon 1348",
    "addr:housenumber":"7",
    "addr:postcode":"1348",
    "addr:street":"Clos Gouyasse",
    "iso:country":"BE",
    "sg:address":"Clos Gouyasse 7",
    "sg:city":"Ottignies-louvain-la-neuve",
    "sg:orig_category":"Instituts pour adultes moins valides",
    "sg:phone":"+32 10 45 10 87",
    "sg:postcode":"1348",
    "sg:province":"Brabant Wallon",
    "wof:name":"Centre Educatif La Cogn\u00c9e",
    "wof:placetype":"venue"
},
  "geometry": {"coordinates":[4.6080698967,50.6730041504],"type":"Point"}
}