{
  "type": "Feature",
  "properties": {
    "addr:full":"Lavendelstraat 22ba Ninove Oost-Vlaanderen 9400",
    "addr:housenumber":"22ba",
    "addr:postcode":"9400",
    "addr:street":"Lavendelstraat",
    "iso:country":"BE",
    "sg:address":"Lavendelstraat 22ba",
    "sg:city":"Ninove",
    "sg:orig_category":"Chaussures",
    "sg:phone":"+32 54 33 79 86",
    "sg:postcode":"9400",
    "sg:province":"Oost-Vlaanderen",
    "wof:name":"Huis Kwebbels",
    "wof:placetype":"venue"
},
  "geometry": {"coordinates":[4.0201821327,50.8366088867],"type":"Point"}
}