{
  "type": "Feature",
  "properties": {
    "addr:full":"Mechelsesteenweg 84/104 Vilvoorde Vlaams-Brabant 1800",
    "addr:housenumber":"84 / 104",
    "addr:postcode":"1800",
    "addr:street":"Mechelsesteenweg",
    "iso:country":"BE",
    "sg:address":"Mechelsesteenweg 84/104",
    "sg:city":"Vilvoorde",
    "sg:orig_category":"Quincailleries. Magasins sp\u00e9cialis\u00e9s",
    "sg:phone":"+32 78 71 89 97",
    "sg:postcode":"1800",
    "sg:province":"Vlaams-Brabant",
    "wof:name":"Adms Van Boxem",
    "wof:placetype":"venue"
},
  "geometry": {"coordinates":[4.4253401756,50.9329833984],"type":"Point"}
}