{
  "type": "Feature",
  "properties": {
    "iso:country":"BE",
    "sg:address":"Brusselsesteenweg 244",
    "sg:city":"Lebbeke",
    "sg:orig_category":"Non-foodwinkels",
    "sg:phone":"+32 52 35 60 42",
    "sg:postcode":"9280",
    "sg:province":"Oost-Vlaanderen",
    "wof:name":"Holbrecht",
    "wof:placetype":"venue"
},
  "geometry": {"coordinates":[4.1394791603,50.9845123291],"type":"Point"}
}