{
  "type": "Feature",
  "properties": {
    "iso:country":"BE",
    "sg:address":"Oude Straat 28",
    "sg:city":"Stekene",
    "sg:orig_category":"Experts-comptables",
    "sg:phone":"+32 3 779 53 96",
    "sg:postcode":"9190",
    "sg:province":"Oost-Vlaanderen",
    "wof:name":"Firmin Bauters",
    "wof:placetype":"venue"
},
  "geometry": {"coordinates":[3.9997050762,51.2261161804],"type":"Point"}
}