{
  "type": "Feature",
  "properties": {
    "addr:full":"Fran\u00c7ois Rigasquare 6 Schaarbeek/schaerbeek Bruxelles-Capitale 1030",
    "addr:housenumber":"6",
    "addr:postcode":"1030",
    "addr:street":"Franc\u0327Ois Rigasquare",
    "iso:country":"BE",
    "sg:address":"Fran\u00c7ois Rigasquare 6",
    "sg:city":"Schaarbeek/schaerbeek",
    "sg:orig_category":"Artiesten and kunstenaars",
    "sg:phone":"+32 2 215 46 96",
    "sg:postcode":"1030",
    "sg:province":"Bruxelles-Capitale",
    "wof:name":"Taf Wallet",
    "wof:placetype":"venue"
},
  "geometry": {"coordinates":[4.3846912384,50.8743400574],"type":"Point"}
}