{
  "type": "Feature",
  "properties": {
    "iso:country":"BE",
    "sg:address":"Rue Bonne Esp\u00e9rance 2",
    "sg:city":"Mettet",
    "sg:classifiers":[
        {
            "category":"Health Services",
            "subcategory":"Health Practitioner",
            "type":"Services"
        }
    ],
    "sg:phone":"+32 71 72 74 75",
    "sg:postcode":"5640",
    "sg:province":"Namur",
    "sg:tags":[
        "physiotherapist"
    ],
    "wof:name":"Hubot E",
    "wof:placetype":"venue"
},
  "geometry": {"coordinates":[4.6667089462,50.3214454651],"type":"Point"}
}