{
  "type": "Feature",
  "properties": {
    "addr:full":"Pastorijstraat 12 Buggenhout Oost-Vlaanderen 9255",
    "addr:housenumber":"12",
    "addr:postcode":"9255",
    "addr:street":"Pastorijstraat",
    "iso:country":"BE",
    "sg:address":"Pastorijstraat 12",
    "sg:city":"Buggenhout",
    "sg:orig_category":"M\u00e9decins and sp\u00e9cialistes",
    "sg:phone":"+32 52 34 56 10",
    "sg:postcode":"9255",
    "sg:province":"Oost-Vlaanderen",
    "wof:name":"Didier Oosterlynck",
    "wof:placetype":"venue"
},
  "geometry": {"coordinates":[4.2040047646,51.0149765015],"type":"Point"}
}