{
  "type": "Feature",
  "properties": {
    "addr:full":"Brusselsesteenweg 68 Asse (groot) Vlaams-Brabant 1730",
    "addr:housenumber":"68",
    "addr:postcode":"1730",
    "addr:street":"Brusselsesteenweg;Groot Vlaams-Brabant",
    "iso:country":"BE",
    "sg:address":"Brusselsesteenweg 68",
    "sg:city":"Asse (groot)",
    "sg:orig_category":"Articles de jardin. Fleurs and plantes",
    "sg:phone":"+32 2 452 28 40",
    "sg:postcode":"1730",
    "sg:province":"Vlaams-Brabant",
    "wof:name":"Vincent",
    "wof:placetype":"venue"
},
  "geometry": {"coordinates":[4.2116441727,50.9037780762],"type":"Point"}
}