{
  "type": "Feature",
  "properties": {
    "iso:country":"BE",
    "sg:address":"Kempstraat 7",
    "sg:city":"Waregem",
    "sg:orig_category":"Artistes ind\u00e9pendants",
    "sg:phone":"+32 56 60 76 07",
    "sg:postcode":"8790",
    "sg:province":"West-Vlaanderen",
    "wof:name":"Luc Vandenberghe",
    "wof:placetype":"venue"
},
  "geometry": {"coordinates":[3.4363129139,50.8950843811],"type":"Point"}
}