{
  "type": "Feature",
  "properties": {
    "addr:full":"Dorpsstraat 125 Brecht Antwerpen 2960",
    "addr:housenumber":"125",
    "addr:postcode":"2960",
    "addr:street":"Dorpsstraat",
    "iso:country":"BE",
    "sg:address":"Dorpsstraat 125",
    "sg:city":"Brecht",
    "sg:classifiers":[
        {
            "category":"Personal",
            "subcategory":"Beauty Salon",
            "type":"Services"
        }
    ],
    "sg:phone":"+32 3 313 80 23",
    "sg:postcode":"2960",
    "sg:province":"Antwerpen",
    "sg:tags":[
        "de",
        "coiffure"
    ],
    "wof:name":"Coiffure May",
    "wof:placetype":"venue"
},
  "geometry": {"coordinates":[4.6415200233,51.3512115479],"type":"Point"}
}