{
  "type": "Feature",
  "properties": {
    "addr:full":"Rue Jacquet 41c Rochefort Namur 5580",
    "addr:housenumber":"41c",
    "addr:postcode":"5580",
    "addr:street":"Rue Jacquet",
    "iso:country":"BE",
    "sg:address":"Rue Jacquet 41c",
    "sg:city":"Rochefort",
    "sg:classifiers":[
        {
            "category":"Real Estate",
            "subcategory":"Surveying",
            "type":"Services"
        }
    ],
    "sg:phone":"+32 84 22 26 40",
    "sg:postcode":"5580",
    "sg:province":"Namur",
    "sg:tags":[
        "surveyor",
        "land"
    ],
    "wof:name":"Blariaux O",
    "wof:placetype":"venue"
},
  "geometry": {"coordinates":[5.2224521637,50.1556777954],"type":"Point"}
}