{
  "type": "Feature",
  "properties": {
    "iso:country":"BE",
    "sg:address":"Stationsstraat 48",
    "sg:city":"Nazareth (eke)",
    "sg:classifiers":[
        {
            "category":"Utilities",
            "subcategory":"Mobile Phone",
            "type":"Services"
        }
    ],
    "sg:phone":"+32 9 385 56 04",
    "sg:postcode":"9810",
    "sg:province":"Oost-Vlaanderen",
    "sg:tags":[
        "access",
        "gsm",
        "-",
        "apparatus"
    ],
    "wof:name":"Go Tech Vanmerhaeghe Marc",
    "wof:placetype":"venue"
},
  "geometry": {"coordinates":[3.6365399361,50.9580993652],"type":"Point"}
}