{
  "type": "Feature",
  "properties": {
    "iso:country":"BE",
    "sg:address":"Noordstraat 88",
    "sg:city":"Roeselare",
    "sg:orig_category":"V\u00eatements",
    "sg:phone":"+32 51 22 56 24",
    "sg:postcode":"8800",
    "sg:province":"West-Vlaanderen",
    "wof:name":"Isabelle",
    "wof:placetype":"venue"
},
  "geometry": {"coordinates":[3.1220541,50.9477386475],"type":"Point"}
}