{
  "type": "Feature",
  "properties": {
    "iso:country":"BE",
    "sg:address":"Belgi\u00cblei 91",
    "sg:city":"Antwerpen",
    "sg:orig_category":"Musea and historische gebouwen",
    "sg:phone":"+32 3 239 06 52",
    "sg:postcode":"2018",
    "sg:province":"Antwerpen",
    "wof:name":"Museum Ridder Smidt Van Gelder",
    "wof:placetype":"venue"
},
  "geometry": {"coordinates":[4.418943882,51.2060775757],"type":"Point"}
}