{
  "type": "Feature",
  "properties": {
    "iso:country":"BE",
    "sg:address":"Avenue Du Houyoux 5",
    "sg:city":"Huy",
    "sg:orig_category":"Keukens and Keukenapparatuur MEUBELONTWERP AND -INSTALLATIE Meubelzaken, woning- and keukeninrichtin",
    "sg:phone":"+32 85 21 26 96",
    "sg:postcode":"4500",
    "sg:province":"Li\u00e8ge",
    "wof:name":"Ilwa - Les Ateliers Andre Lakaye",
    "wof:placetype":"venue"
},
  "geometry": {"coordinates":[5.2388701439,50.5154495239],"type":"Point"}
}