{
  "type": "Feature",
  "properties": {
    "iso:country":"BE",
    "sg:address":"Plagne 2",
    "sg:city":"Grandrieu",
    "sg:classifiers":[
        {
            "category":"Wholesale",
            "subcategory":"Farm Supplies",
            "type":"Manufacturing & Wholesale Goods"
        }
    ],
    "sg:phone":"+32 60 45 55 25",
    "sg:postcode":"6470",
    "sg:province":"Hainaut",
    "sg:tags":[
        "-",
        "machine",
        "equipment",
        "engineering",
        "machinery",
        "mechanical",
        "agriculture"
    ],
    "wof:name":"Rafhay Andre Sprl",
    "wof:placetype":"venue"
},
  "geometry": {"coordinates":[4.2715301514,50.1426696777],"type":"Point"}
}