{
  "type": "Feature",
  "properties": {
    "iso:country":"BE",
    "sg:address":"De Wandelaar 13",
    "sg:city":"Blankenberge (uitkerke)",
    "sg:classifiers":[
        {
            "category":"Health Services",
            "subcategory":"Doctor",
            "type":"Services"
        }
    ],
    "sg:phone":"+32 50 41 35 21",
    "sg:postcode":"8370",
    "sg:province":"West-Vlaanderen",
    "sg:tags":[
        "medicinephysicians",
        "surgeon"
    ],
    "wof:name":"Lauweryns A",
    "wof:placetype":"venue"
},
  "geometry": {"coordinates":[3.1451339722,51.3137283325],"type":"Point"}
}