{
  "type": "Feature",
  "properties": {
    "addr:full":"Rooigemlaan 532 Gent Oost-Vlaanderen 9000",
    "addr:housenumber":"532",
    "addr:postcode":"9000",
    "addr:street":"Rooigemlaan;Oost-Vlaanderen",
    "iso:country":"BE",
    "sg:address":"Rooigemlaan 532",
    "sg:city":"Gent",
    "sg:orig_category":"Ordinateurs and \u00e9quipement informatique",
    "sg:phone":"+32 9 236 16 36",
    "sg:postcode":"9000",
    "sg:province":"Oost-Vlaanderen",
    "wof:name":"Intentia Belux",
    "wof:placetype":"venue"
},
  "geometry": {"coordinates":[3.6969320774,51.0647163391],"type":"Point"}
}