{
  "type": "Feature",
  "properties": {
    "iso:country":"BE",
    "sg:address":"Quai Des Ardennes 117",
    "sg:city":"Li\u00e8ge 1 (angleur)",
    "sg:classifiers":[
        {
            "category":"Retail",
            "subcategory":"Auto Repair",
            "type":"Services"
        }
    ],
    "sg:phone":"+32 4 254 15 51",
    "sg:postcode":"4031",
    "sg:province":"Li\u00e8ge",
    "sg:tags":[
        "garage"
    ],
    "wof:name":"E.v.s.",
    "wof:placetype":"venue"
},
  "geometry": {"coordinates":[5.6059060097,50.6153755188],"type":"Point"}
}