{
  "type": "Feature",
  "properties": {
    "iso:country":"BE",
    "sg:address":"Veurnestraat 89",
    "sg:city":"De Panne",
    "sg:orig_category":"Quincailleries",
    "sg:phone":"+32 58 41 20 14",
    "sg:postcode":"8660",
    "sg:province":"West-Vlaanderen",
    "wof:name":"Dakwerken Woestijn",
    "wof:placetype":"venue"
},
  "geometry": {"coordinates":[2.5938000679,51.0955162048],"type":"Point"}
}