{
  "type": "Feature",
  "properties": {
    "addr:full":"Rue De Sosoye 6 Onhaye Namur 5522",
    "addr:housenumber":"6",
    "addr:postcode":"5522",
    "addr:street":"Rue De Sosoye",
    "iso:country":"BE",
    "sg:address":"Rue De Sosoye 6",
    "sg:city":"Onhaye",
    "sg:classifiers":[
        {
            "category":"Travel",
            "subcategory":"Hotels & Motels",
            "type":"Entertainment"
        }
    ],
    "sg:phone":"+32 82 69 92 51",
    "sg:postcode":"5522",
    "sg:province":"Namur",
    "sg:tags":[
        "kampeerterreinen",
        "restaurant"
    ],
    "wof:name":"Camping Cobut",
    "wof:placetype":"venue"
},
  "geometry": {"coordinates":[4.7955570221,50.2918663025],"type":"Point"}
}