{
  "type": "Feature",
  "properties": {
    "addr:full":"Zeilstraat 12 Hasselt Limburg 3500",
    "addr:housenumber":"12",
    "addr:postcode":"3500",
    "addr:street":"Zeilstraat",
    "iso:country":"BE",
    "sg:address":"Zeilstraat 12",
    "sg:city":"Hasselt",
    "sg:orig_category":"Production de films, t\u00e9l\u00e9films and vid\u00e9os. Studios photographiques",
    "sg:phone":"+32 11 26 10 16",
    "sg:postcode":"3500",
    "sg:province":"Limburg",
    "wof:name":"Inter Unit Interior",
    "wof:placetype":"venue"
},
  "geometry": {"coordinates":[5.3535089493,50.9397583008],"type":"Point"}
}