{
  "type": "Feature",
  "properties": {
    "iso:country":"BE",
    "sg:address":"Rue De La Croix 64",
    "sg:city":"Charleroi (lodelinsart)",
    "sg:classifiers":[
        {
            "category":"Health Services",
            "subcategory":"Health Practitioner",
            "type":"Services"
        }
    ],
    "sg:phone":"+32 71 41 05 71",
    "sg:postcode":"6042",
    "sg:province":"Hainaut",
    "sg:tags":[
        "physiotherapist"
    ],
    "wof:name":"Detournay Andr\u00e9",
    "wof:placetype":"venue"
},
  "geometry": {"coordinates":[4.4480080605,50.4370422363],"type":"Point"}
}