{
  "type": "Feature",
  "properties": {
    "iso:country":"BE",
    "sg:address":"Rue De Familleureux 64",
    "sg:city":"Ecaussinnes",
    "sg:orig_category":"Dranken Gh",
    "sg:phone":"+32 67 44 22 07",
    "sg:postcode":"7190",
    "sg:province":"Hainaut",
    "wof:name":"Claude Waroquier",
    "wof:placetype":"venue"
},
  "geometry": {"coordinates":[4.1840600967,50.5449333191],"type":"Point"}
}