{
  "type": "Feature",
  "properties": {
    "addr:full":"Oudenaardseweg 14 Wortegem-petegem Oost-Vlaanderen 9790",
    "addr:housenumber":"14",
    "addr:postcode":"9790",
    "addr:street":"Oudenaardseweg",
    "iso:country":"BE",
    "sg:address":"Oudenaardseweg 14",
    "sg:city":"Wortegem-petegem",
    "sg:orig_category":"Salles de spectacles",
    "sg:phone":"+32 56 68 77 99",
    "sg:postcode":"9790",
    "sg:province":"Oost-Vlaanderen",
    "wof:name":"Art Gallery",
    "wof:placetype":"venue"
},
  "geometry": {"coordinates":[3.5114879608,50.8532905579],"type":"Point"}
}