{
  "type": "Feature",
  "properties": {
    "addr:full":"Rue Du Ruisseau 31 Oupeye Li\u00e8ge 4684",
    "addr:housenumber":"31",
    "addr:postcode":"4684",
    "addr:street":"Rue Du Ruisseau",
    "iso:country":"BE",
    "sg:address":"Rue Du Ruisseau 31",
    "sg:city":"Oupeye",
    "sg:orig_category":"Gespecialiseerde niet-residenti\u00eble bouw Installatie van metalen schrijnwerk SMEEDWERK, METAALBEWERKI",
    "sg:phone":"+32 4 379 16 53",
    "sg:postcode":"4684",
    "sg:province":"Li\u00e8ge",
    "wof:name":"Defroidmont",
    "wof:placetype":"venue"
},
  "geometry": {"coordinates":[5.6637458801,50.7396354675],"type":"Point"}
}