{
  "type": "Feature",
  "properties": {
    "addr:full":"Tiensesteenweg 96 Sint-truiden Limburg 3800",
    "addr:housenumber":"96",
    "addr:postcode":"3800",
    "addr:street":"Tiensesteenweg",
    "iso:country":"BE",
    "sg:address":"Tiensesteenweg 96",
    "sg:city":"Sint-truiden",
    "sg:orig_category":"Artsen and specialisten",
    "sg:phone":"+32 11 68 88 85",
    "sg:postcode":"3800",
    "sg:province":"Limburg",
    "wof:name":"Paul Steels",
    "wof:placetype":"venue"
},
  "geometry": {"coordinates":[5.1748280525,50.8149299622],"type":"Point"}
}