{
  "type": "Feature",
  "properties": {
    "addr:full":"Thijskensstraat 64b Maldegem Oost-Vlaanderen 9990",
    "addr:housenumber":"64b",
    "addr:postcode":"9990",
    "addr:street":"Thijskensstraat",
    "iso:country":"BE",
    "sg:address":"Thijskensstraat 64b",
    "sg:city":"Maldegem",
    "sg:classifiers":[
        {
            "category":"Food & Beverages",
            "subcategory":"Meat & Fish",
            "type":"Retail Goods"
        }
    ],
    "sg:phone":"+32 50 71 51 20",
    "sg:postcode":"9990",
    "sg:province":"Oost-Vlaanderen",
    "sg:tags":[
        "-",
        "livestock"
    ],
    "wof:name":"Van Landschoot W",
    "wof:placetype":"venue"
},
  "geometry": {"coordinates":[3.4423260689,51.1854667664],"type":"Point"}
}