{
  "type": "Feature",
  "properties": {
    "addr:full":"Eikevelden 84 Geel Antwerpen 2440",
    "addr:housenumber":"84",
    "addr:postcode":"2440",
    "addr:street":"Eikevelden",
    "iso:country":"BE",
    "sg:address":"Eikevelden 84",
    "sg:city":"Geel",
    "sg:classifiers":[
        {
            "category":"Wholesale",
            "subcategory":"Construction Materials",
            "type":"Manufacturing & Wholesale Goods"
        }
    ],
    "sg:phone":"+32 14 58 76 10",
    "sg:postcode":"2440",
    "sg:province":"Antwerpen",
    "sg:tags":[
        "civil",
        "engineering",
        "-"
    ],
    "wof:name":"S K V Bvba",
    "wof:placetype":"venue"
},
  "geometry": {"coordinates":[5.0013670921,51.1568450928],"type":"Point"}
}