{
  "type": "Feature",
  "properties": {
    "addr:full":"Rue Des Briqueteries 32 Eghez\u00e9e (leuze) Namur 5310",
    "addr:housenumber":"32",
    "addr:postcode":"5310",
    "addr:street":"Rue Des Briqueteries",
    "iso:country":"BE",
    "sg:address":"Rue Des Briqueteries 32",
    "sg:city":"Eghez\u00e9e (leuze)",
    "sg:classifiers":[
        {
            "category":"Government",
            "subcategory":"Fire Station",
            "type":"Public Place"
        }
    ],
    "sg:phone":"+32 81 51 29 91",
    "sg:postcode":"5310",
    "sg:province":"Namur",
    "sg:tags":[
        "installation",
        "-",
        "air conditioning"
    ],
    "wof:name":"Atbr",
    "wof:placetype":"venue"
},
  "geometry": {"coordinates":[4.9105381966,50.5566864014],"type":"Point"}
}