{
  "type": "Feature",
  "properties": {
    "iso:country":"BE",
    "sg:address":"Maria Theresiastraat 96",
    "sg:city":"Leuven",
    "sg:orig_category":"Activit\u00e9s diverses d'imprimerie",
    "sg:phone":"+32 16 20 77 01",
    "sg:postcode":"3000",
    "sg:province":"Vlaams-Brabant",
    "wof:name":"Alto Alto",
    "wof:placetype":"venue"
},
  "geometry": {"coordinates":[4.7138528824,50.8796424866],"type":"Point"}
}