{
  "type": "Feature",
  "properties": {
    "iso:country":"BE",
    "sg:address":"Rue Wattelar Maximilien 94",
    "sg:city":"Charleroi (jumet)",
    "sg:classifiers":[
        {
            "category":"Home & Garden",
            "subcategory":"Household Appliances",
            "type":"Retail Goods"
        }
    ],
    "sg:phone":"+32 71 35 08 86",
    "sg:postcode":"6040",
    "sg:province":"Hainaut",
    "sg:tags":[
        "heating",
        "apparatus"
    ],
    "wof:name":"Jordan",
    "wof:placetype":"venue"
},
  "geometry": {"coordinates":[4.416041851,50.4439849854],"type":"Point"}
}