{
  "type": "Feature",
  "properties": {
    "addr:full":"Rue Arthur Bredat 31 Charleroi Hainaut 6030",
    "addr:housenumber":"31",
    "addr:postcode":"6030",
    "addr:street":"Rue Arthur Bredat;Hainaut",
    "iso:country":"BE",
    "sg:address":"Rue Arthur Bredat 31",
    "sg:city":"Charleroi",
    "sg:classifiers":[
        {
            "category":"Cafe",
            "type":"Food & Drink"
        }
    ],
    "sg:phone":"+32 71 56 15 03",
    "sg:postcode":"6030",
    "sg:province":"Hainaut",
    "sg:tags":[
        "caf\u00e9s"
    ],
    "wof:name":"Caf\u00c9 L'oasis",
    "wof:placetype":"venue"
},
  "geometry": {"coordinates":[4.3906111717,50.3932571411],"type":"Point"}
}