{
  "type": "Feature",
  "properties": {
    "addr:full":"Pont De Marcourt 5 Rendeux (marcourt) Luxembourg 6987",
    "addr:housenumber":"5",
    "addr:postcode":"6987",
    "addr:street":"Pont De Marcourt",
    "iso:country":"BE",
    "sg:address":"Pont De Marcourt 5",
    "sg:city":"Rendeux (marcourt)",
    "sg:classifiers":[
        {
            "category":"Travel",
            "subcategory":"Hotels & Motels",
            "type":"Entertainment"
        }
    ],
    "sg:phone":"+32 84 47 71 79",
    "sg:postcode":"6987",
    "sg:province":"Luxembourg",
    "wof:name":"Ermitage (h\u00f4tel)",
    "wof:placetype":"venue"
},
  "geometry": {"coordinates":[5.503636837,50.2335166931],"type":"Point"}
}