{
  "type": "Feature",
  "properties": {
    "addr:full":"Beversesteenweg 6 Roeselare West-Vlaanderen 8800",
    "addr:housenumber":"6",
    "addr:postcode":"8800",
    "addr:street":"Beversesteenweg",
    "iso:country":"BE",
    "sg:address":"Beversesteenweg 6",
    "sg:city":"Roeselare",
    "sg:classifiers":[
        {
            "category":"Professional",
            "subcategory":"Management & Consulting",
            "type":"Services"
        }
    ],
    "sg:phone":"+32 51 22 43 24",
    "sg:postcode":"8800",
    "sg:province":"West-Vlaanderen",
    "sg:tags":[
        "tax-consultants"
    ],
    "wof:name":"Denys J",
    "wof:placetype":"venue"
},
  "geometry": {"coordinates":[3.1316308975,50.9492340088],"type":"Point"}
}