{
  "type": "Feature",
  "properties": {
    "iso:country":"BE",
    "sg:address":"Frans Vandersteenstraat 86",
    "sg:city":"Lennik",
    "sg:orig_category":"Gespecialiseerde residenti\u00eble bouw Installatie van metalen schrijnwerk Pleisterwerk",
    "sg:phone":"+32 2 532 06 26",
    "sg:postcode":"1750",
    "sg:province":"Vlaams-Brabant",
    "wof:name":"Van Eeckhout Frans & Zoon",
    "wof:placetype":"venue"
},
  "geometry": {"coordinates":[4.1552639008,50.8017349243],"type":"Point"}
}