{
  "type": "Feature",
  "properties": {
    "iso:country":"BE",
    "sg:address":"Hoekskensstraat 5",
    "sg:city":"Lochristi",
    "sg:orig_category":"Traitements param\u00e9dicaux",
    "sg:phone":"+32 9 355 09 56",
    "sg:postcode":"9080",
    "sg:province":"Oost-Vlaanderen",
    "wof:name":"I. Lason",
    "wof:placetype":"venue"
},
  "geometry": {"coordinates":[3.8439309597,51.099647522],"type":"Point"}
}