{
  "type": "Feature",
  "properties": {
    "iso:country":"BE",
    "sg:address":"Hoogstraat 13",
    "sg:city":"Berlare",
    "sg:classifiers":[
        {
            "category":"Building & Trades",
            "subcategory":"Plumbing",
            "type":"Services"
        }
    ],
    "sg:phone":"+32 52 42 70 49",
    "sg:postcode":"9290",
    "sg:province":"Oost-Vlaanderen",
    "sg:tags":[
        "contractor"
    ],
    "wof:name":"Tackaert P",
    "wof:placetype":"venue"
},
  "geometry": {"coordinates":[3.9960548878,51.0229301453],"type":"Point"}
}