{
  "type": "Feature",
  "properties": {
    "addr:full":"Pastoor Mellaertsstraat 4 Heist-op-den-berg Antwerpen 2220",
    "addr:housenumber":"4",
    "addr:postcode":"2220",
    "addr:street":"Pastoor Mellaertsstraat",
    "iso:country":"BE",
    "sg:address":"Pastoor Mellaertsstraat 4",
    "sg:city":"Heist-op-den-berg",
    "sg:classifiers":[
        {
            "category":"Cafe",
            "type":"Food & Drink"
        }
    ],
    "sg:phone":"+32 15 25 18 72",
    "sg:postcode":"2220",
    "sg:province":"Antwerpen",
    "sg:tags":[
        "caf\u00e9s"
    ],
    "wof:name":"Barkeep",
    "wof:placetype":"venue"
},
  "geometry": {"coordinates":[4.7192502022,51.0442085266],"type":"Point"}
}