{
  "type": "Feature",
  "properties": {
    "iso:country":"BE",
    "sg:address":"Antwerpsesteenweg 427",
    "sg:city":"Lier",
    "sg:orig_category":"Industri\u00eble and commerci\u00eble bouw Woningbouw",
    "sg:phone":"+32 3 480 62 01",
    "sg:postcode":"2500",
    "sg:province":"Antwerpen",
    "wof:name":"Van Rymenant W.",
    "wof:placetype":"venue"
},
  "geometry": {"coordinates":[4.5419778824,51.1453742981],"type":"Point"}
}