{
  "type": "Feature",
  "properties": {
    "addr:full":"Hameau De Mer 3 Braine-le-comte Hainaut 7090",
    "addr:housenumber":"3",
    "addr:postcode":"7090",
    "addr:street":"Hameau De Mer",
    "iso:country":"BE",
    "sg:address":"Hameau De Mer 3",
    "sg:city":"Braine-le-comte",
    "sg:orig_category":"Rundveehouders",
    "sg:phone":"+32 67 67 06 11",
    "sg:postcode":"7090",
    "sg:province":"Hainaut",
    "wof:name":"Fernand Devel",
    "wof:placetype":"venue"
},
  "geometry": {"coordinates":[4.0872960091,50.6341323853],"type":"Point"}
}