{
  "type": "Feature",
  "properties": {
    "addr:full":"Rijmenamseweg 2 Bonheiden Antwerpen 2820",
    "addr:housenumber":"2",
    "addr:postcode":"2820",
    "addr:street":"Rijmenamseweg",
    "iso:country":"BE",
    "sg:address":"Rijmenamseweg 2",
    "sg:city":"Bonheiden",
    "sg:orig_category":"Banken and kredietinstellingen",
    "sg:phone":"+32 15 51 17 15",
    "sg:postcode":"2820",
    "sg:province":"Antwerpen",
    "wof:name":"Fortis",
    "wof:placetype":"venue"
},
  "geometry": {"coordinates":[4.5509281158,51.0214614868],"type":"Point"}
}