{
  "type": "Feature",
  "properties": {
    "iso:country":"BE",
    "sg:address":"Hulstbaan 233a",
    "sg:city":"Sint-niklaas (sinaai)",
    "sg:classifiers":[
        {
            "category":"Professional",
            "subcategory":"Lawyer & Legal Services",
            "type":"Services"
        }
    ],
    "sg:phone":"+32 3 735 07 70",
    "sg:postcode":"9112",
    "sg:province":"Oost-Vlaanderen",
    "wof:name":"Colpaert Johan",
    "wof:placetype":"venue"
},
  "geometry": {"coordinates":[4.0300807953,51.1412849426],"type":"Point"}
}