{
  "type": "Feature",
  "properties": {
    "addr:full":"Eikstraat 31 Pepingen Vlaams-Brabant 1673",
    "addr:housenumber":"31",
    "addr:postcode":"1673",
    "addr:street":"Eikstraat",
    "iso:country":"BE",
    "sg:address":"Eikstraat 31",
    "sg:city":"Pepingen",
    "sg:orig_category":"Platenmaatschappijen",
    "sg:phone":"+32 2 356 18 78",
    "sg:postcode":"1673",
    "sg:province":"Vlaams-Brabant",
    "wof:name":"Accent",
    "wof:placetype":"venue"
},
  "geometry": {"coordinates":[4.1817932129,50.741558075],"type":"Point"}
}