{
  "type": "Feature",
  "properties": {
    "addr:full":"Nijverheidsln 1540 Opglabbeek Limburg 3660",
    "addr:postcode":"1540 opglabbeek;3660",
    "iso:country":"BE",
    "sg:address":"Nijverheidsln 1540",
    "sg:city":"Opglabbeek",
    "sg:classifiers":[
        {
            "category":"Professional",
            "subcategory":"Engineering",
            "type":"Services"
        }
    ],
    "sg:phone":"+32 89 85 38 91",
    "sg:postcode":"3660",
    "sg:province":"Limburg",
    "sg:tags":[
        "machine",
        "-",
        "mechanical"
    ],
    "wof:name":"Inventec Nv",
    "wof:placetype":"venue"
},
  "geometry": {"coordinates":[5.5481171608,51.0427436829],"type":"Point"}
}