{
  "type": "Feature",
  "properties": {
    "addr:full":"Bosstraat 23 Drogenbos Vlaams-Brabant 1620",
    "addr:housenumber":"23",
    "addr:postcode":"1620",
    "addr:street":"Bosstraat",
    "iso:country":"BE",
    "sg:address":"Bosstraat 23",
    "sg:city":"Drogenbos",
    "sg:orig_category":"Landmeters",
    "sg:phone":"+32 2 377 30 98",
    "sg:postcode":"1620",
    "sg:province":"Vlaams-Brabant",
    "wof:name":"Bureau Toposat",
    "wof:placetype":"venue"
},
  "geometry": {"coordinates":[4.3208851814,50.7821960449],"type":"Point"}
}