{
  "type": "Feature",
  "properties": {
    "addr:full":"Avenue De Fr\u00e9 3 Bruxelles (uccle) Bruxelles-Capitale 1180",
    "addr:housenumber":"3",
    "addr:postcode":"1180",
    "addr:street":"Avenue De Fre\u0301",
    "iso:country":"BE",
    "sg:address":"Avenue De Fr\u00e9 3",
    "sg:city":"Bruxelles (uccle)",
    "sg:classifiers":[
        {
            "category":"Professional",
            "subcategory":"Accounting & Tax Preparation",
            "type":"Services"
        }
    ],
    "sg:phone":"+32 2 375 17 52",
    "sg:postcode":"1180",
    "sg:province":"Bruxelles-Capitale",
    "sg:tags":[
        "bookkeeper"
    ],
    "wof:name":"Havelange E",
    "wof:placetype":"venue"
},
  "geometry": {"coordinates":[4.3412370682,50.8027076721],"type":"Point"}
}