{
  "type": "Feature",
  "properties": {
    "addr:full":"Rue Du Pont Alsort 1-3 Froidchapelle Hainaut 6440",
    "addr:housenumber":"1-3",
    "addr:postcode":"6440",
    "addr:street":"Rue Du Pont Alsort",
    "iso:country":"BE",
    "sg:address":"Rue Du Pont Alsort 1-3",
    "sg:city":"Froidchapelle",
    "sg:classifiers":[
        {
            "category":"Shopping",
            "subcategory":"Jewelry",
            "type":"Retail Goods"
        }
    ],
    "sg:phone":"+32 60 41 13 13",
    "sg:postcode":"6440",
    "sg:province":"Hainaut",
    "sg:tags":[
        "jeweller",
        "-"
    ],
    "wof:name":"Pestiaux (maison)",
    "wof:placetype":"venue"
},
  "geometry": {"coordinates":[4.3318200111,50.1517181396],"type":"Point"}
}