{
  "type": "Feature",
  "properties": {
    "addr:full":"Rue De La Station 216 Waterloo Brabant Wallon 1410",
    "addr:housenumber":"216",
    "addr:postcode":"1410",
    "addr:street":"Rue De La Station",
    "iso:country":"BE",
    "sg:address":"Rue De La Station 216",
    "sg:city":"Waterloo",
    "sg:classifiers":[
        {
            "category":"Personal",
            "subcategory":"Beauty Salon",
            "type":"Services"
        }
    ],
    "sg:phone":"+32 2 354 13 79",
    "sg:postcode":"1410",
    "sg:province":"Brabant Wallon",
    "sg:tags":[
        "lady",
        "-",
        "hairdressing"
    ],
    "wof:name":"Lady Hair",
    "wof:placetype":"venue"
},
  "geometry": {"coordinates":[4.3893399239,50.7159805298],"type":"Point"}
}