{
  "type": "Feature",
  "properties": {
    "addr:full":"Kruisheide 11 Keerbergen Vlaams-Brabant 3140",
    "addr:housenumber":"11",
    "addr:postcode":"3140",
    "addr:street":"Kruisheide",
    "iso:country":"BE",
    "sg:address":"Kruisheide 11",
    "sg:city":"Keerbergen",
    "sg:classifiers":[
        {
            "category":"Transit Center",
            "subcategory":"Freight",
            "type":"Transportation"
        }
    ],
    "sg:phone":"+32 16 53 98 39",
    "sg:postcode":"3140",
    "sg:province":"Vlaams-Brabant",
    "sg:tags":[
        "import",
        "export",
        "-"
    ],
    "wof:name":"Gain Services And Business Bvba",
    "wof:placetype":"venue"
},
  "geometry": {"coordinates":[4.6906452179,50.9961967468],"type":"Point"}
}