{
  "type": "Feature",
  "properties": {
    "addr:full":"Monnikstraat 13 Tremelo Vlaams-Brabant 3128",
    "addr:housenumber":"13",
    "addr:postcode":"3128",
    "addr:street":"Monnikstraat",
    "iso:country":"BE",
    "sg:address":"Monnikstraat 13",
    "sg:city":"Tremelo",
    "sg:orig_category":"Installation de menuiserie en bois and plastique",
    "sg:phone":"+32 16 53 23 34",
    "sg:postcode":"3128",
    "sg:province":"Vlaams-Brabant",
    "wof:name":"Van Vlasselaer Gebrs",
    "wof:placetype":"venue"
},
  "geometry": {"coordinates":[4.7441830635,50.9964637756],"type":"Point"}
}