{
  "type": "Feature",
  "properties": {
    "iso:country":"BE",
    "sg:address":"Avenue Des Chataigniers 30",
    "sg:city":"Rhode-saint-gen\u00e8se",
    "sg:classifiers":[
        {
            "category":"Sports & Exercise",
            "subcategory":"Gym",
            "type":"Entertainment"
        }
    ],
    "sg:phone":"+32 2 520 47 95",
    "sg:postcode":"1640",
    "sg:province":"Vlaams-Brabant",
    "sg:tags":[
        "access",
        "gymnastics",
        "-",
        "apparatus",
        "fitness"
    ],
    "wof:name":"Dynamic Classic Europe",
    "wof:placetype":"venue"
},
  "geometry": {"coordinates":[4.3791871071,50.7523574829],"type":"Point"}
}