{
  "type": "Feature",
  "properties": {
    "addr:full":"Noorderlaan 97 Antwerpen Antwerpen 2030",
    "addr:housenumber":"97",
    "addr:postcode":"2030",
    "addr:street":"Noorderlaan",
    "iso:country":"BE",
    "sg:address":"Noorderlaan 97",
    "sg:city":"Antwerpen",
    "sg:orig_category":"Autoverhuur",
    "sg:phone":"+32 3 542 05 42",
    "sg:postcode":"2030",
    "sg:province":"Antwerpen",
    "wof:name":"Interleasing Belgium",
    "wof:placetype":"venue"
},
  "geometry": {"coordinates":[4.4196639061,51.2598381042],"type":"Point"}
}