{
  "type": "Feature",
  "properties": {
    "addr:full":"Rue Des Aulnois 2a Le Roeulx (thieu) Hainaut 7070",
    "addr:housenumber":"2a",
    "addr:postcode":"7070",
    "addr:street":"Rue Des Aulnois",
    "iso:country":"BE",
    "sg:address":"Rue Des Aulnois 2a",
    "sg:city":"Le Roeulx (thieu)",
    "sg:classifiers":[
        {
            "category":"Shopping",
            "subcategory":"Bicycles & Sporting Goods",
            "type":"Retail Goods"
        }
    ],
    "sg:phone":"+32 64 67 60 09",
    "sg:postcode":"7070",
    "sg:province":"Hainaut",
    "sg:tags":[
        "-"
    ],
    "wof:name":"Bertrand Cycles",
    "wof:placetype":"venue"
},
  "geometry": {"coordinates":[4.0961427689,50.4755935669],"type":"Point"}
}