{
  "type": "Feature",
  "properties": {
    "addr:full":"Jozef De Vleminckstraat 26 Grimbergen (strombeek-bever) Vlaams-Brabant 1853",
    "addr:housenumber":"26",
    "addr:postcode":"1853",
    "addr:street":"Jozef De Vleminckstraat",
    "iso:country":"BE",
    "sg:address":"Jozef De Vleminckstraat 26",
    "sg:city":"Grimbergen (strombeek-bever)",
    "sg:classifiers":[
        {
            "category":"Real Estate",
            "subcategory":"Real Estate Services",
            "type":"Services"
        }
    ],
    "sg:phone":"+32 2 267 57 10",
    "sg:postcode":"1853",
    "sg:province":"Vlaams-Brabant",
    "wof:name":"Hipo Nv",
    "wof:placetype":"venue"
},
  "geometry": {"coordinates":[4.3481822014,50.9126815796],"type":"Point"}
}