{
  "type": "Feature",
  "properties": {
    "iso:country":"BE",
    "sg:address":"Kerkstraat 26",
    "sg:city":"Hamme",
    "sg:classifiers":[
        {
            "category":"Insurance",
            "subcategory":"Insurance Agent",
            "type":"Services"
        }
    ],
    "sg:phone":"+32 52 48 05 35",
    "sg:postcode":"9220",
    "sg:province":"Oost-Vlaanderen",
    "sg:tags":[
        "broker"
    ],
    "wof:name":"Zakenkantoor Luc Smet",
    "wof:placetype":"venue"
},
  "geometry": {"coordinates":[4.1353840828,51.0983886719],"type":"Point"}
}