{
  "type": "Feature",
  "properties": {
    "iso:country":"BE",
    "sg:address":"Theresiastraat 19",
    "sg:city":"Hasselt",
    "sg:classifiers":[
        {
            "category":"Real Estate",
            "subcategory":"Architect",
            "type":"Services"
        }
    ],
    "sg:phone":"+32 11 22 58 91",
    "sg:postcode":"3500",
    "sg:province":"Limburg",
    "wof:name":"Delbare P",
    "wof:placetype":"venue"
},
  "geometry": {"coordinates":[5.348762989,50.9307861328],"type":"Point"}
}