{
  "type": "Feature",
  "properties": {
    "addr:full":"Rue Britannique 28b13 Braine-le-comte Hainaut 7090",
    "addr:housenumber":"28b13",
    "addr:postcode":"7090",
    "addr:street":"Rue Britannique",
    "iso:country":"BE",
    "sg:address":"Rue Britannique 28b13",
    "sg:city":"Braine-le-comte",
    "sg:orig_category":"Artsen and specialisten",
    "sg:phone":"+32 67 55 55 67",
    "sg:postcode":"7090",
    "sg:province":"Hainaut",
    "wof:name":"P. Oger",
    "wof:placetype":"venue"
},
  "geometry": {"coordinates":[4.1346621513,50.6072158813],"type":"Point"}
}