{
  "type": "Feature",
  "properties": {
    "iso:country":"BE",
    "sg:address":"Drevendaal 26",
    "sg:city":"Sint-katelijne-waver",
    "sg:orig_category":"Non-Classified Establishments",
    "sg:phone":"+32 15 32 09 55",
    "sg:postcode":"2860",
    "sg:province":"Antwerpen",
    "wof:name":"Sorrentina (la)",
    "wof:placetype":"venue"
},
  "geometry": {"coordinates":[4.513220787,51.0680885315],"type":"Point"}
}