{
  "type": "Feature",
  "properties": {
    "iso:country":"BE",
    "sg:address":"Potakker 20",
    "sg:city":"Ieper",
    "sg:classifiers":[
        {
            "category":"Personal",
            "subcategory":"Beauty Salon",
            "type":"Services"
        }
    ],
    "sg:phone":"+32 57 20 89 58",
    "sg:postcode":"8900",
    "sg:province":"West-Vlaanderen",
    "sg:tags":[
        "de",
        "coiffure"
    ],
    "wof:name":"Fabienne Collie",
    "wof:placetype":"venue"
},
  "geometry": {"coordinates":[2.8964760303,50.8613471985],"type":"Point"}
}