{
  "type": "Feature",
  "properties": {
    "addr:full":"Sentier De La Ferme 27 Charleroi Hainaut 6060",
    "addr:housenumber":"27",
    "addr:postcode":"6060",
    "addr:street":"Sentier De La Ferme;Hainaut",
    "iso:country":"BE",
    "sg:address":"Sentier De La Ferme 27",
    "sg:city":"Charleroi",
    "sg:orig_category":"Artiesten and kunstenaars",
    "sg:phone":"+32 71 41 32 86",
    "sg:postcode":"6060",
    "sg:province":"Hainaut",
    "wof:name":"L. De Leeuw",
    "wof:placetype":"venue"
},
  "geometry": {"coordinates":[4.4880981445,50.4251937866],"type":"Point"}
}