{
  "type": "Feature",
  "properties": {
    "iso:country":"BE",
    "sg:address":"Schoolstraat 2c",
    "sg:city":"Schilde",
    "sg:classifiers":[
        {
            "category":"Personal",
            "subcategory":"Beauty Salon",
            "type":"Services"
        }
    ],
    "sg:phone":"+32 3 383 25 79",
    "sg:postcode":"2970",
    "sg:province":"Antwerpen",
    "sg:tags":[
        "de",
        "coiffure"
    ],
    "wof:name":"Hair Styling",
    "wof:placetype":"venue"
},
  "geometry": {"coordinates":[4.5790491104,51.2385368347],"type":"Point"}
}