{
  "type": "Feature",
  "properties": {
    "addr:full":"Vijverdamstraat 17 Meulebeke West-Vlaanderen 8760",
    "addr:housenumber":"17",
    "addr:postcode":"8760",
    "addr:street":"Vijverdamstraat",
    "iso:country":"BE",
    "sg:address":"Vijverdamstraat 17",
    "sg:city":"Meulebeke",
    "sg:orig_category":"Woningbouw",
    "sg:phone":"+32 51 48 91 48",
    "sg:postcode":"8760",
    "sg:province":"West-Vlaanderen",
    "wof:name":"Lucien Roose",
    "wof:placetype":"venue"
},
  "geometry": {"coordinates":[3.2414329052,50.9611244202],"type":"Point"}
}