{
  "type": "Feature",
  "properties": {
    "addr:full":"Rue Oscar Thimus 1 Limbourg Li\u00e8ge 4830",
    "addr:housenumber":"1",
    "addr:postcode":"4830",
    "addr:street":"Rue Oscar Thimus",
    "iso:country":"BE",
    "sg:address":"Rue Oscar Thimus 1",
    "sg:city":"Limbourg",
    "sg:orig_category":"Banques and organismes de cr\u00e9dit",
    "sg:phone":"+32 87 76 20 66",
    "sg:postcode":"4830",
    "sg:province":"Li\u00e8ge",
    "wof:name":"Fortis",
    "wof:placetype":"venue"
},
  "geometry": {"coordinates":[5.9407401085,50.6112518311],"type":"Point"}
}