{
  "type": "Feature",
  "properties": {
    "addr:full":"Boulevard Louis Mettewie 77b22 Sint-jans-molenbeek/molenbeek-saint-jean Bruxelles-Capitale 1080",
    "addr:housenumber":"77b22",
    "addr:postcode":"1080",
    "addr:street":"Boulevard Louis Mettewie",
    "iso:country":"BE",
    "sg:address":"Boulevard Louis Mettewie 77b22",
    "sg:city":"Sint-jans-molenbeek/molenbeek-saint-jean",
    "sg:orig_category":"M\u00e9decins and sp\u00e9cialistes",
    "sg:phone":"+32 2 469 21 24",
    "sg:postcode":"1080",
    "sg:province":"Bruxelles-Capitale",
    "wof:name":"Peter Clement",
    "wof:placetype":"venue"
},
  "geometry": {"coordinates":[4.3042030334,50.8544502258],"type":"Point"}
}