{
  "type": "Feature",
  "properties": {
    "addr:full":"Rue Stijn Streuvels 41 Ronse/renaix Oost-Vlaanderen 9600",
    "addr:housenumber":"41",
    "addr:postcode":"9600",
    "addr:street":"Rue Stijn Streuvels",
    "iso:country":"BE",
    "sg:address":"Rue Stijn Streuvels 41",
    "sg:city":"Ronse/renaix",
    "sg:orig_category":"Pain, p\u00e2tisseries and confiseries",
    "sg:phone":"+32 55 21 54 40",
    "sg:postcode":"9600",
    "sg:province":"Oost-Vlaanderen",
    "wof:name":"Roger Uyttenhove",
    "wof:placetype":"venue"
},
  "geometry": {"coordinates":[3.626101017,50.751247406],"type":"Point"}
}