{
  "type": "Feature",
  "properties": {
    "addr:full":"Nieuwe Baan 58 Sint-niklaas Oost-Vlaanderen 9111",
    "addr:housenumber":"58",
    "addr:postcode":"9111",
    "addr:street":"Nieuwe Baan",
    "iso:country":"BE",
    "sg:address":"Nieuwe Baan 58",
    "sg:city":"Sint-niklaas",
    "sg:orig_category":"Koerierbedrijven",
    "sg:phone":"+32 3 772 18 96",
    "sg:postcode":"9111",
    "sg:province":"Oost-Vlaanderen",
    "wof:name":"Kurt Van Broeck",
    "wof:placetype":"venue"
},
  "geometry": {"coordinates":[4.0903148651,51.1430282593],"type":"Point"}
}