{
  "type": "Feature",
  "properties": {
    "iso:country":"BE",
    "sg:address":"Meersbloemstraat 44",
    "sg:city":"Roeselare",
    "sg:orig_category":"Loodgieterij, verwarming and sanitaire installaties Woningbouw",
    "sg:phone":"+32 51 22 35 47",
    "sg:postcode":"8800",
    "sg:province":"West-Vlaanderen",
    "wof:name":"Johny Beele",
    "wof:placetype":"venue"
},
  "geometry": {"coordinates":[3.1340069771,50.9733886719],"type":"Point"}
}