{
  "type": "Feature",
  "properties": {
    "addr:full":"Rue Neuve 73a Libin (redu) Luxembourg 6890",
    "addr:housenumber":"73a",
    "addr:postcode":"6890",
    "addr:street":"Rue Neuve",
    "iso:country":"BE",
    "sg:address":"Rue Neuve 73a",
    "sg:city":"Libin (redu)",
    "sg:classifiers":[
        {
            "category":"Shopping",
            "subcategory":"Books",
            "type":"Retail Goods"
        }
    ],
    "sg:phone":"+32 61 65 81 49",
    "sg:postcode":"6890",
    "sg:province":"Luxembourg",
    "sg:tags":[
        "bookseller"
    ],
    "wof:name":"Librairie Yves De Prins",
    "wof:placetype":"venue"
},
  "geometry": {"coordinates":[5.2562999725,49.9827537537],"type":"Point"}
}