{
  "type": "Feature",
  "properties": {
    "addr:full":"Rue Grande 44 Tellin Luxembourg 6927",
    "addr:housenumber":"44",
    "addr:postcode":"6927",
    "addr:street":"Rue Grande",
    "iso:country":"BE",
    "sg:address":"Rue Grande 44",
    "sg:city":"Tellin",
    "sg:classifiers":[
        {
            "category":"Health Services",
            "subcategory":"Nursing And Care Facility",
            "type":"Services"
        }
    ],
    "sg:phone":"+32 84 36 68 35",
    "sg:postcode":"6927",
    "sg:province":"Luxembourg",
    "sg:tags":[
        "home"
    ],
    "wof:name":"Perpete M",
    "wof:placetype":"venue"
},
  "geometry": {"coordinates":[5.2212867737,50.0821990967],"type":"Point"}
}