{
  "type": "Feature",
  "properties": {
    "addr:full":"Dieplaan 2 Genk Limburg 3600",
    "addr:housenumber":"2",
    "addr:postcode":"3600",
    "addr:street":"Dieplaan",
    "iso:country":"BE",
    "sg:address":"Dieplaan 2",
    "sg:city":"Genk",
    "sg:orig_category":"Zalen voor culturele evenementen",
    "sg:phone":"+32 89 30 93 11",
    "sg:postcode":"3600",
    "sg:province":"Limburg",
    "wof:name":"Cultureel Centrum",
    "wof:placetype":"venue"
},
  "geometry": {"coordinates":[5.4946689606,50.9645271301],"type":"Point"}
}