{
  "type": "Feature",
  "properties": {
    "iso:country":"BE",
    "sg:address":"Kleine Brede Straat 2ba",
    "sg:city":"Antwerpen",
    "sg:orig_category":"Enseignement secondaire technique and professionnel",
    "sg:phone":"+32 3 568 73 31",
    "sg:postcode":"2040",
    "sg:province":"Antwerpen",
    "wof:name":"Stedelijke Middenschool",
    "wof:placetype":"venue"
},
  "geometry": {"coordinates":[4.4021129608,51.215171814],"type":"Point"}
}