{
  "type": "Feature",
  "properties": {
    "addr:full":"Rue De Saintes 16 Box 3 Nivelles Brabant Wallon 1400",
    "addr:housenumber":"16;3",
    "addr:postcode":"1400",
    "addr:street":"Rue De Saintes;Box",
    "iso:country":"BE",
    "sg:address":"Rue De Saintes 16 Box 3",
    "sg:city":"Nivelles",
    "sg:orig_category":"Ergotherapists",
    "sg:phone":"+32 67 21 51 67",
    "sg:postcode":"1400",
    "sg:province":"Brabant Wallon",
    "wof:name":"Paps D",
    "wof:placetype":"venue"
},
  "geometry": {"coordinates":[4.3249959946,50.5965270996],"type":"Point"}
}