{
  "type": "Feature",
  "properties": {
    "addr:full":"Desguinlei 6b3 Antwerpen Antwerpen 2018",
    "addr:housenumber":"6b3",
    "addr:postcode":"2018",
    "addr:street":"Desguinlei",
    "iso:country":"BE",
    "sg:address":"Desguinlei 6b3",
    "sg:city":"Antwerpen",
    "sg:classifiers":[
        {
            "category":"Insurance",
            "subcategory":"Life Insurance",
            "type":"Services"
        }
    ],
    "sg:phone":"+32 3 241 04 90",
    "sg:postcode":"2018",
    "sg:province":"Antwerpen",
    "sg:tags":[
        "assurance"
    ],
    "wof:name":"Bureau Zao",
    "wof:placetype":"venue"
},
  "geometry": {"coordinates":[4.3948168755,51.1976661682],"type":"Point"}
}