{
  "type": "Feature",
  "properties": {
    "addr:full":"Avenue Georges Speeckaert 24 Villers-la-ville Brabant Wallon 1495",
    "addr:housenumber":"24",
    "addr:postcode":"1495",
    "addr:street":"Avenue Georges Speeckaert",
    "iso:country":"BE",
    "sg:address":"Avenue Georges Speeckaert 24",
    "sg:city":"Villers-la-ville",
    "sg:classifiers":[
        {
            "category":"Organizations",
            "subcategory":"Community Association",
            "type":"Services"
        }
    ],
    "sg:phone":"+32 71 87 71 01",
    "sg:postcode":"1495",
    "sg:province":"Brabant Wallon",
    "sg:tags":[
        "environment",
        "organisation",
        "-"
    ],
    "wof:name":"Nature Et Loisirs",
    "wof:placetype":"venue"
},
  "geometry": {"coordinates":[4.5303859711,50.5885429382],"type":"Point"}
}