{
  "type": "Feature",
  "properties": {
    "iso:country":"BE",
    "sg:address":"Hoekskensstraat 116",
    "sg:city":"Lochristi",
    "sg:orig_category":"Plantes and fleurs Gr",
    "sg:phone":"+32 9 353 88 88",
    "sg:postcode":"9080",
    "sg:province":"Oost-Vlaanderen",
    "wof:name":"De Bruyne",
    "wof:placetype":"venue"
},
  "geometry": {"coordinates":[3.8377330303,51.1111526489],"type":"Point"}
}