{
  "type": "Feature",
  "properties": {
    "addr:full":"Rue Des Vierges 34 Renaix Oost-Vlaanderen 9600",
    "addr:housenumber":"34",
    "addr:postcode":"9600",
    "addr:street":"Rue Des Vierges",
    "iso:country":"BE",
    "sg:address":"Rue Des Vierges 34",
    "sg:city":"Renaix",
    "sg:classifiers":[
        {
            "category":"Building & Trades",
            "subcategory":"Pest Control",
            "type":"Services"
        }
    ],
    "sg:phone":"+32 55 21 98 21",
    "sg:postcode":"9600",
    "sg:province":"Oost-Vlaanderen",
    "sg:tags":[
        "painting",
        "contractor"
    ],
    "wof:name":"Tuybens L",
    "wof:placetype":"venue"
},
  "geometry": {"coordinates":[3.6374690533,50.74842453],"type":"Point"}
}