{
  "type": "Feature",
  "properties": {
    "addr:full":"Rue Redoute 25 Aywaille Li\u00e8ge 4920",
    "addr:housenumber":"25",
    "addr:postcode":"4920",
    "addr:street":"Rue Redoute",
    "iso:country":"BE",
    "sg:address":"Rue Redoute 25",
    "sg:city":"Aywaille",
    "sg:classifiers":[
        {
            "category":"Arena",
            "subcategory":"Sports Club",
            "type":"Entertainment"
        }
    ],
    "sg:phone":"+32 4 384 41 60",
    "sg:postcode":"4920",
    "sg:province":"Li\u00e8ge",
    "sg:tags":[
        "terrain",
        "hors",
        "de",
        "installation",
        "sportifs"
    ],
    "wof:name":"R. Sougne-remouch. Sp.",
    "wof:placetype":"venue"
},
  "geometry": {"coordinates":[5.6782069206,50.4738540649],"type":"Point"}
}