{
  "type": "Feature",
  "properties": {
    "iso:country":"BE",
    "sg:address":"Brugsesteenweg 131",
    "sg:city":"Roeselare",
    "sg:orig_category":"Eclairage et \u00e9quipements du foyer. Epiceries",
    "sg:phone":"+32 51 24 76 24",
    "sg:postcode":"8800",
    "sg:province":"West-Vlaanderen",
    "wof:name":"Kado-shop",
    "wof:placetype":"venue"
},
  "geometry": {"coordinates":[3.1218070984,50.9544334412],"type":"Point"}
}