{
  "type": "Feature",
  "properties": {
    "iso:country":"BE",
    "sg:address":"Kattendansstraat 68",
    "sg:city":"Hasselt",
    "sg:orig_category":"G\u00e9om\u00e8tres",
    "sg:phone":"+32 11 27 02 63",
    "sg:postcode":"3500",
    "sg:province":"Limburg",
    "wof:name":"Hendrik Appeltans",
    "wof:placetype":"venue"
},
  "geometry": {"coordinates":[5.32726717,50.9030723572],"type":"Point"}
}