{
  "type": "Feature",
  "properties": {
    "iso:country":"BE",
    "sg:address":"Torenstraat 122",
    "sg:city":"Rotselaar",
    "sg:classifiers":[
        {
            "category":"Home & Garden",
            "subcategory":"Kitchen Supply",
            "type":"Retail Goods"
        }
    ],
    "sg:phone":"+32 16 44 78 55",
    "sg:postcode":"3110",
    "sg:province":"Vlaams-Brabant",
    "sg:tags":[
        "equipment",
        "baker",
        "-"
    ],
    "wof:name":"Ooms Products Nv",
    "wof:placetype":"venue"
},
  "geometry": {"coordinates":[4.7242698669,50.9555091858],"type":"Point"}
}