{
  "type": "Feature",
  "properties": {
    "iso:country":"BE",
    "sg:address":"Rue Des Faubourgs 83",
    "sg:city":"Arlon",
    "sg:classifiers":[
        {
            "category":"Bars & Pubs",
            "type":"Food & Drink"
        }
    ],
    "sg:phone":"+32 63 23 67 36",
    "sg:postcode":"6700",
    "sg:province":"Luxembourg",
    "wof:name":"Wapiti",
    "wof:placetype":"venue"
},
  "geometry": {"coordinates":[5.8106379509,49.6849403381],"type":"Point"}
}