{
  "type": "Feature",
  "properties": {
    "addr:full":"Paul Jansonlaan 76 Anderlecht/anderlecht Bruxelles-Capitale 1070",
    "addr:housenumber":"76",
    "addr:postcode":"1070",
    "addr:street":"Paul Jansonlaan",
    "iso:country":"BE",
    "sg:address":"Paul Jansonlaan 76",
    "sg:city":"Anderlecht/anderlecht",
    "sg:orig_category":"Artsen and specialisten",
    "sg:phone":"+32 2 521 74 92",
    "sg:postcode":"1070",
    "sg:province":"Bruxelles-Capitale",
    "wof:name":"Henri Heymans",
    "wof:placetype":"venue"
},
  "geometry": {"coordinates":[4.3038430214,50.8334083557],"type":"Point"}
}