{
  "type": "Feature",
  "properties": {
    "iso:country":"BE",
    "sg:address":"Nijverheidsweg 5",
    "sg:city":"Rijkevorsel",
    "sg:orig_category":"Quincailleries. Bois Gr",
    "sg:phone":"+32 3 311 76 54",
    "sg:postcode":"2310",
    "sg:province":"Antwerpen",
    "wof:name":"Immo Aerts",
    "wof:placetype":"venue"
},
  "geometry": {"coordinates":[4.7350511551,51.3326950073],"type":"Point"}
}