{
  "type": "Feature",
  "properties": {
    "addr:full":"Solwaster 62 Jalhay (sart) Li\u00e8ge 4845",
    "addr:housenumber":"62",
    "addr:postcode":"4845",
    "addr:street":"Solwaster;Sart Lie\u0300Ge",
    "iso:country":"BE",
    "sg:address":"Solwaster 62",
    "sg:city":"Jalhay (sart)",
    "sg:classifiers":[
        {
            "category":"Food & Beverages",
            "subcategory":"Meat & Fish",
            "type":"Retail Goods"
        }
    ],
    "sg:phone":"+32 87 47 41 01",
    "sg:postcode":"4845",
    "sg:province":"Li\u00e8ge",
    "sg:tags":[
        "-",
        "livestock"
    ],
    "wof:name":"Orban P",
    "wof:placetype":"venue"
},
  "geometry": {"coordinates":[5.967151165,50.5330314636],"type":"Point"}
}