{
  "type": "Feature",
  "properties": {
    "addr:full":"Ave Chazal 30 Schaarbeek Bruxelles-Capitale 1030",
    "addr:housenumber":"30",
    "addr:postcode":"1030",
    "addr:street":"Ave Chazal",
    "iso:country":"BE",
    "sg:address":"Ave Chazal 30",
    "sg:city":"Schaarbeek",
    "sg:classifiers":[
        {
            "category":"Banks & Credit Unions",
            "subcategory":"Bank",
            "type":"Services"
        }
    ],
    "sg:phone":"+32 2 732 10 18",
    "sg:postcode":"1030",
    "sg:province":"Bruxelles-Capitale",
    "wof:name":"G\u00e9n\u00e9rale De Banque Sa",
    "wof:placetype":"venue"
},
  "geometry": {"coordinates":[4.3882060051,50.8537216187],"type":"Point"}
}