{
  "type": "Feature",
  "properties": {
    "iso:country":"BE",
    "sg:address":"Merksplassesteenweg 104",
    "sg:city":"Rijkevorsel",
    "sg:classifiers":[
        {
            "category":"Autos & Motor Vehicles",
            "subcategory":"Automobile Sales",
            "type":"Retail Goods"
        }
    ],
    "sg:phone":"+32 3 340 49 49",
    "sg:postcode":"2310",
    "sg:province":"Antwerpen",
    "sg:tags":[
        "car",
        "used",
        "-"
    ],
    "wof:name":"Necadis",
    "wof:placetype":"venue"
},
  "geometry": {"coordinates":[4.7773098946,51.3453598022],"type":"Point"}
}