{
  "type": "Feature",
  "properties": {
    "iso:country":"BE",
    "sg:address":"Eksterdreef 8",
    "sg:city":"Schoten",
    "sg:classifiers":[
        {
            "category":"Arena",
            "subcategory":"Sports Club",
            "type":"Entertainment"
        }
    ],
    "sg:phone":"+32 3 685 68 66",
    "sg:postcode":"2900",
    "sg:province":"Antwerpen",
    "sg:tags":[
        "de"
    ],
    "wof:name":"Artemis Schoten Korfbal Club",
    "wof:placetype":"venue"
},
  "geometry": {"coordinates":[4.505095005,51.2643508911],"type":"Point"}
}