{
  "type": "Feature",
  "properties": {
    "addr:full":"Konijnenpad 14 Brugge West-Vlaanderen 8310",
    "addr:housenumber":"14",
    "addr:postcode":"8310",
    "addr:street":"Konijnenpad",
    "iso:country":"BE",
    "sg:address":"Konijnenpad 14",
    "sg:city":"Brugge",
    "sg:classifiers":[
        {
            "category":"Building & Trades",
            "subcategory":"Plumbing",
            "type":"Services"
        }
    ],
    "sg:phone":"+32 50 36 15 34",
    "sg:postcode":"8310",
    "sg:province":"West-Vlaanderen",
    "sg:tags":[
        "diver",
        "commerce",
        "gr",
        "pour",
        "equipement"
    ],
    "wof:name":"Vens",
    "wof:placetype":"venue"
},
  "geometry": {"coordinates":[3.2504398823,51.189250946],"type":"Point"}
}