{
  "type": "Feature",
  "properties": {
    "iso:country":"BE",
    "sg:address":"Stapelstraat 26",
    "sg:city":"Sint-truiden",
    "sg:orig_category":"Schoenen",
    "sg:phone":"+32 11 67 37 68",
    "sg:postcode":"3800",
    "sg:province":"Limburg",
    "wof:name":"Raffaello",
    "wof:placetype":"venue"
},
  "geometry": {"coordinates":[5.1834278107,50.8150177002],"type":"Point"}
}