{
  "type": "Feature",
  "properties": {
    "iso:country":"BE",
    "sg:address":"Pikkeleerstraat 14",
    "sg:city":"Herk-de-stad",
    "sg:orig_category":"Musea and historische gebouwen",
    "sg:phone":"+32 13 55 38 11",
    "sg:postcode":"3540",
    "sg:province":"Limburg",
    "wof:name":"Kasteel de Pierpont",
    "wof:placetype":"venue"
},
  "geometry": {"coordinates":[5.1661472321,50.9366455078],"type":"Point"}
}