{
  "type": "Feature",
  "properties": {
    "addr:full":"Dumortierlaan 155 Knokke-heist (knokke) West-Vlaanderen 8300",
    "addr:housenumber":"155",
    "addr:postcode":"8300",
    "addr:street":"Dumortierlaan",
    "iso:country":"BE",
    "sg:address":"Dumortierlaan 155",
    "sg:city":"Knokke-heist (knokke)",
    "sg:classifiers":[
        {
            "category":"Home & Garden",
            "subcategory":"Home Furnishings",
            "type":"Retail Goods"
        }
    ],
    "sg:phone":"+32 50 61 57 76",
    "sg:postcode":"8300",
    "sg:province":"West-Vlaanderen",
    "sg:tags":[
        "-",
        "bed",
        "mattress"
    ],
    "wof:name":"Vi Spring-debbaut Nv Chark",
    "wof:placetype":"venue"
},
  "geometry": {"coordinates":[3.287694931,51.3467254639],"type":"Point"}
}