{
  "type": "Feature",
  "properties": {
    "iso:country":"BE",
    "sg:address":"Westkapellestraat 400",
    "sg:city":"Knokke-heist (westkapelle)",
    "sg:classifiers":[
        {
            "category":"Retail",
            "subcategory":"Auto Repair",
            "type":"Services"
        }
    ],
    "sg:phone":"+32 50 60 35 27",
    "sg:postcode":"8300",
    "sg:province":"West-Vlaanderen",
    "sg:tags":[
        "breakdown",
        "automobile",
        "-",
        "recovery"
    ],
    "wof:name":"Auto's Lierman",
    "wof:placetype":"venue"
},
  "geometry": {"coordinates":[3.273706913,51.32447052],"type":"Point"}
}