{
  "type": "Feature",
  "properties": {
    "addr:full":"Zuidzandstraat 19 Brugge West-Vlaanderen 8000",
    "addr:housenumber":"19",
    "addr:postcode":"8000",
    "addr:street":"Zuidzandstraat",
    "iso:country":"BE",
    "sg:address":"Zuidzandstraat 19",
    "sg:city":"Brugge",
    "sg:classifiers":[
        {
            "category":"Shopping",
            "subcategory":"Beauty & Cosmetics",
            "type":"Retail Goods"
        }
    ],
    "sg:phone":"+32 50 33 77 28",
    "sg:postcode":"8000",
    "sg:province":"West-Vlaanderen",
    "sg:tags":[
        "-",
        "perfumery"
    ],
    "wof:name":"Body Shop (the)",
    "wof:placetype":"venue"
},
  "geometry": {"coordinates":[3.2195100784,51.2052841187],"type":"Point"}
}