{
  "type": "Feature",
  "properties": {
    "addr:full":"Zuster Van Onze Lieve Vrouwstraat 51 Antwerpen Antwerpen 2170",
    "addr:housenumber":"51",
    "addr:postcode":"2170",
    "addr:street":"Zuster Van Onze Lieve Vrouwstraat",
    "iso:country":"BE",
    "sg:address":"Zuster Van Onze Lieve Vrouwstraat 51",
    "sg:city":"Antwerpen",
    "sg:orig_category":"Boekhouders",
    "sg:phone":"+32 3 644 25 07",
    "sg:postcode":"2170",
    "sg:province":"Antwerpen",
    "wof:name":"Van Den Broeck Nadia",
    "wof:placetype":"venue"
},
  "geometry": {"coordinates":[4.4505147934,51.246723175],"type":"Point"}
}