{
  "type": "Feature",
  "properties": {
    "iso:country":"BE",
    "sg:address":"Brugstraat 59",
    "sg:city":"Turnhout",
    "sg:orig_category":"Secr\u00e9tariats. Activit\u00e9s diverses d'imprimerie. Studios photographiques. Agences de publicit\u00e9. Compos",
    "sg:phone":"+32 14 43 50 68",
    "sg:postcode":"2300",
    "sg:province":"Antwerpen",
    "wof:name":"Outline Graphics",
    "wof:placetype":"venue"
},
  "geometry": {"coordinates":[4.9280138016,51.3264465332],"type":"Point"}
}