{
  "type": "Feature",
  "properties": {
    "iso:country":"BE",
    "sg:address":"Zone Artisanale Des Carri\u00c8res 20",
    "sg:city":"Seneffe",
    "sg:orig_category":"Installation de menuiserie en bois and plastique",
    "sg:phone":"+32 67 87 93 35",
    "sg:postcode":"7181",
    "sg:province":"Hainaut",
    "wof:name":"Guillaume",
    "wof:placetype":"venue"
},
  "geometry": {"coordinates":[4.2732601166,50.565662384],"type":"Point"}
}