{
  "type": "Feature",
  "properties": {
    "addr:full":"Kapellestraat 3 Oostende West-Vlaanderen 8400",
    "addr:housenumber":"3",
    "addr:postcode":"8400",
    "addr:street":"Kapellestraat",
    "iso:country":"BE",
    "sg:address":"Kapellestraat 3",
    "sg:city":"Oostende",
    "sg:orig_category":"Cr\u00e9dits divers",
    "sg:postcode":"8400",
    "sg:province":"West-Vlaanderen",
    "wof:name":"Bancontact-mister Cash",
    "wof:placetype":"venue"
},
  "geometry": {"coordinates":[2.9174349308,51.2314605713],"type":"Point"}
}