{
  "type": "Feature",
  "properties": {
    "addr:full":"Dorpsstraat 118 Stekene Oost-Vlaanderen 9190",
    "addr:housenumber":"118",
    "addr:postcode":"9190",
    "addr:street":"Dorpsstraat",
    "iso:country":"BE",
    "sg:address":"Dorpsstraat 118",
    "sg:city":"Stekene",
    "sg:orig_category":"Brood, gebak and snoepgoed",
    "sg:phone":"+32 3 779 73 64",
    "sg:postcode":"9190",
    "sg:province":"Oost-Vlaanderen",
    "wof:name":"Wim Van Laere",
    "wof:placetype":"venue"
},
  "geometry": {"coordinates":[4.038670063,51.2035903931],"type":"Point"}
}