{
  "type": "Feature",
  "properties": {
    "iso:country":"BE",
    "sg:address":"Dr.f. De Wachterlaan 33",
    "sg:city":"Puurs",
    "sg:orig_category":"Traitements param\u00e9dicaux",
    "sg:phone":"+32 3 886 86 23",
    "sg:postcode":"2870",
    "sg:province":"Antwerpen",
    "wof:name":"Nancy Peeters",
    "wof:placetype":"venue"
},
  "geometry": {"coordinates":[4.3319020271,51.0806236267],"type":"Point"}
}