{
  "type": "Feature",
  "properties": {
    "iso:country":"BE",
    "sg:address":"Route De Wiltz 4a",
    "sg:city":"Bastogne",
    "sg:classifiers":[
        {
            "category":"Real Estate",
            "subcategory":"Architect",
            "type":"Services"
        }
    ],
    "sg:phone":"+32 61 28 75 79",
    "sg:postcode":"6600",
    "sg:province":"Luxembourg",
    "wof:name":"Fretz S",
    "wof:placetype":"venue"
},
  "geometry": {"coordinates":[5.724656105,49.9955444336],"type":"Point"}
}