{
  "type": "Feature",
  "properties": {
    "addr:full":"Rue Haute 19 Hannut Li\u00e8ge 4280",
    "addr:housenumber":"19",
    "addr:postcode":"4280",
    "addr:street":"Rue Haute",
    "iso:country":"BE",
    "sg:address":"Rue Haute 19",
    "sg:city":"Hannut",
    "sg:orig_category":"Elektrische installaties voor woningen",
    "sg:phone":"+32 19 51 08 32",
    "sg:postcode":"4280",
    "sg:province":"Li\u00e8ge",
    "wof:name":"Alain Volon",
    "wof:placetype":"venue"
},
  "geometry": {"coordinates":[5.1179041862,50.6630096436],"type":"Point"}
}