{
  "type": "Feature",
  "properties": {
    "addr:full":"Molenstraat 20 Herenthout Antwerpen 2270",
    "addr:housenumber":"20",
    "addr:postcode":"2270",
    "addr:street":"Molenstraat",
    "iso:country":"BE",
    "sg:address":"Molenstraat 20",
    "sg:city":"Herenthout",
    "sg:classifiers":[
        {
            "category":"Health Services",
            "subcategory":"Dentist",
            "type":"Services"
        }
    ],
    "sg:phone":"+32 14 21 05 04",
    "sg:postcode":"2270",
    "sg:province":"Antwerpen",
    "wof:name":"Roelants Paul",
    "wof:placetype":"venue"
},
  "geometry": {"coordinates":[4.758207798,51.1396408081],"type":"Point"}
}