{
  "type": "Feature",
  "properties": {
    "iso:country":"BE",
    "sg:address":"Gemeenteplein 20",
    "sg:city":"Lummen",
    "sg:classifiers":[
        {
            "category":"Fast Food",
            "type":"Food & Drink"
        }
    ],
    "sg:phone":"+32 13 53 13 12",
    "sg:postcode":"3560",
    "sg:province":"Limburg",
    "sg:tags":[
        "fried",
        "stand",
        "potato"
    ],
    "wof:name":"Dikke Eik",
    "wof:placetype":"venue"
},
  "geometry": {"coordinates":[5.1912589073,50.9860038757],"type":"Point"}
}