{
  "type": "Feature",
  "properties": {
    "addr:full":"Brugsesteenweg 175 Pittem West-Vlaanderen 8740",
    "addr:housenumber":"175",
    "addr:postcode":"8740",
    "addr:street":"Brugsesteenweg",
    "iso:country":"BE",
    "sg:address":"Brugsesteenweg 175",
    "sg:city":"Pittem",
    "sg:orig_category":"Epiceries",
    "sg:phone":"+32 51 46 62 22",
    "sg:postcode":"8740",
    "sg:province":"West-Vlaanderen",
    "wof:name":"M Vandaele",
    "wof:placetype":"venue"
},
  "geometry": {"coordinates":[3.2359199524,51.004699707],"type":"Point"}
}