{
  "type": "Feature",
  "properties": {
    "iso:country":"BE",
    "sg:address":"Gaverse Steenweg 53",
    "sg:city":"Oosterzele (scheldewindeke)",
    "sg:classifiers":[
        {
            "category":"Farming",
            "subcategory":"Livestock Farm",
            "type":"Manufacturing & Wholesale Goods"
        }
    ],
    "sg:phone":"+32 9 362 71 49",
    "sg:postcode":"9860",
    "sg:province":"Oost-Vlaanderen",
    "sg:tags":[
        "poultry",
        "rabbit"
    ],
    "wof:name":"Hofman M",
    "wof:placetype":"venue"
},
  "geometry": {"coordinates":[3.7588310242,50.9361534119],"type":"Point"}
}