{
  "type": "Feature",
  "properties": {
    "addr:full":"Brusselsestraat 52 Dendermonde Oost-Vlaanderen 9200",
    "addr:housenumber":"52",
    "addr:postcode":"9200",
    "addr:street":"Brusselsestraat;Oost-Vlaanderen",
    "iso:country":"BE",
    "sg:address":"Brusselsestraat 52",
    "sg:city":"Dendermonde",
    "sg:orig_category":"Grands magasins. Supermarch\u00e9s",
    "sg:postcode":"9200",
    "sg:province":"Oost-Vlaanderen",
    "wof:name":"Unic",
    "wof:placetype":"venue"
},
  "geometry": {"coordinates":[4.099919796,51.0272483826],"type":"Point"}
}