{
  "type": "Feature",
  "properties": {
    "iso:country":"BE",
    "sg:address":"Rodter Strasse 39a",
    "sg:city":"Sankt Vith",
    "sg:classifiers":[
        {
            "category":"Retail",
            "subcategory":"Driving School",
            "type":"Services"
        }
    ],
    "sg:phone":"+32 80 22 86 88",
    "sg:postcode":"4780",
    "sg:province":"Li\u00e8ge",
    "sg:tags":[
        "automobile",
        "officially",
        "-",
        "recognized"
    ],
    "wof:name":"Fahrschule Theis Sc",
    "wof:placetype":"venue"
},
  "geometry": {"coordinates":[6.1151409149,50.2808990479],"type":"Point"}
}