{
  "type": "Feature",
  "properties": {
    "iso:country":"BE",
    "sg:address":"Isabella Brantstraat 26",
    "sg:city":"Antwerpen",
    "sg:classifiers":[
        {
            "category":"Social Services",
            "subcategory":"Job Training",
            "type":"Services"
        }
    ],
    "sg:phone":"+32 3 257 04 86",
    "sg:postcode":"2018",
    "sg:province":"Antwerpen",
    "sg:tags":[
        "personnel",
        "-selection",
        "recruitment"
    ],
    "wof:name":"Topconsult Bvba",
    "wof:placetype":"venue"
},
  "geometry": {"coordinates":[4.4059081078,51.2055511475],"type":"Point"}
}