{
  "type": "Feature",
  "properties": {
    "addr:full":"Astridplein 8 Koksijde (oostduinkerke) West-Vlaanderen 8670",
    "addr:housenumber":"8",
    "addr:postcode":"8670",
    "addr:street":"Astridplein",
    "iso:country":"BE",
    "sg:address":"Astridplein 8",
    "sg:city":"Koksijde (oostduinkerke)",
    "sg:classifiers":[
        {
            "category":"Manufacturing",
            "subcategory":"Textiles",
            "type":"Manufacturing & Wholesale Goods"
        }
    ],
    "sg:phone":"+32 58 51 29 86",
    "sg:postcode":"8670",
    "sg:province":"West-Vlaanderen",
    "sg:tags":[
        "retail",
        "-"
    ],
    "wof:name":"Vazir",
    "wof:placetype":"venue"
},
  "geometry": {"coordinates":[2.6717669964,51.1325035095],"type":"Point"}
}