{
  "type": "Feature",
  "properties": {
    "iso:country":"BE",
    "sg:address":"Plantinkaai 1",
    "sg:city":"Antwerpen",
    "sg:classifiers":[
        {
            "category":"Utilities",
            "subcategory":"Telephone",
            "type":"Services"
        }
    ],
    "sg:phone":"+32 3 233 40 46",
    "sg:postcode":"2000",
    "sg:province":"Antwerpen",
    "sg:tags":[
        "telecommunication"
    ],
    "wof:name":"Rtc Europe Bvba",
    "wof:placetype":"venue"
},
  "geometry": {"coordinates":[4.3953900337,51.2184638977],"type":"Point"}
}