{
  "type": "Feature",
  "properties": {
    "iso:country":"BE",
    "sg:address":"Terkamerenlaan 42b10",
    "sg:city":"Brussel/bruxelles",
    "sg:orig_category":"Boekhouders",
    "sg:phone":"+32 2 648 40 65",
    "sg:postcode":"1000",
    "sg:province":"Bruxelles-Capitale",
    "wof:name":"Ivan Rymenhaut",
    "wof:placetype":"venue"
},
  "geometry": {"coordinates":[4.3746099472,50.8159217834],"type":"Point"}
}