{
  "type": "Feature",
  "properties": {
    "addr:full":"Chauss\u00e9e Paul Houtart 274 La Louvi\u00e8re (houdeng-goegnies) Hainaut 7110",
    "addr:housenumber":"274",
    "addr:postcode":"7110",
    "addr:street":"Chausse\u0301E Paul Houtart",
    "iso:country":"BE",
    "sg:address":"Chauss\u00e9e Paul Houtart 274",
    "sg:city":"La Louvi\u00e8re (houdeng-goegnies)",
    "sg:classifiers":[
        {
            "category":"Shopping",
            "subcategory":"Florist",
            "type":"Retail Goods"
        }
    ],
    "sg:phone":"+32 64 22 15 94",
    "sg:postcode":"7110",
    "sg:province":"Hainaut",
    "wof:name":"Nadyflor",
    "wof:placetype":"venue"
},
  "geometry": {"coordinates":[4.15792799,50.4866104126],"type":"Point"}
}