{
  "type": "Feature",
  "properties": {
    "addr:full":"Bosdreef 78 Lochristi Oost-Vlaanderen 9080",
    "addr:housenumber":"78",
    "addr:postcode":"9080",
    "addr:street":"Bosdreef",
    "iso:country":"BE",
    "sg:address":"Bosdreef 78",
    "sg:city":"Lochristi",
    "sg:classifiers":[
        {
            "category":"Home & Garden",
            "subcategory":"Carpets & Floor Coverings",
            "type":"Retail Goods"
        }
    ],
    "sg:phone":"+32 9 355 13 56",
    "sg:postcode":"9080",
    "sg:province":"Oost-Vlaanderen",
    "sg:tags":[
        "industrial",
        "-"
    ],
    "wof:name":"Bogaert Kunststofvloeren Nv",
    "wof:placetype":"venue"
},
  "geometry": {"coordinates":[3.8432929516,51.0895957947],"type":"Point"}
}