{
  "type": "Feature",
  "properties": {
    "iso:country":"BE",
    "sg:address":"Stationsstraat 54b",
    "sg:city":"Oudenburg",
    "sg:classifiers":[
        {
            "category":"Retail",
            "subcategory":"Car Wash",
            "type":"Services"
        }
    ],
    "sg:phone":"+32 59 43 32 70",
    "sg:postcode":"8460",
    "sg:province":"West-Vlaanderen",
    "sg:tags":[
        "automobile",
        "washing",
        "-",
        "truck"
    ],
    "wof:name":"Planet Carwash Cvba",
    "wof:placetype":"venue"
},
  "geometry": {"coordinates":[3.0073950291,51.1997871399],"type":"Point"}
}