{
  "type": "Feature",
  "properties": {
    "addr:full":"Veldstraat 40 Zandhoven Antwerpen 2240",
    "addr:housenumber":"40",
    "addr:postcode":"2240",
    "addr:street":"Veldstraat",
    "iso:country":"BE",
    "sg:address":"Veldstraat 40",
    "sg:city":"Zandhoven",
    "sg:orig_category":"Boekhouders",
    "sg:phone":"+32 3 484 32 34",
    "sg:postcode":"2240",
    "sg:province":"Antwerpen",
    "wof:name":"Jozef Poulussen",
    "wof:placetype":"venue"
},
  "geometry": {"coordinates":[4.6546387672,51.2178535461],"type":"Point"}
}