{
  "type": "Feature",
  "properties": {
    "addr:full":"Rue De La Dodane 12 Namur Namur 5000",
    "addr:housenumber":"12",
    "addr:postcode":"5000",
    "addr:street":"Rue De La Dodane",
    "iso:country":"BE",
    "sg:address":"Rue De La Dodane 12",
    "sg:city":"Namur",
    "sg:orig_category":"Artsen and specialisten",
    "sg:phone":"+32 81 73 07 31",
    "sg:postcode":"5000",
    "sg:province":"Namur",
    "wof:name":"Christine Le Boulenge",
    "wof:placetype":"venue"
},
  "geometry": {"coordinates":[4.8550748825,50.4686279297],"type":"Point"}
}