{
  "type": "Feature",
  "properties": {
    "addr:full":"Haute Chaineux 32 Herve (chaineux) Li\u00e8ge 4650",
    "addr:housenumber":"32",
    "addr:postcode":"4650",
    "addr:street":"Haute Chaineux",
    "iso:country":"BE",
    "sg:address":"Haute Chaineux 32",
    "sg:city":"Herve (chaineux)",
    "sg:orig_category":"Non-Classified Establishments",
    "sg:phone":"+32 87 67 92 72",
    "sg:postcode":"4650",
    "sg:province":"Li\u00e8ge",
    "wof:name":"Grifn\u00e9e L",
    "wof:placetype":"venue"
},
  "geometry": {"coordinates":[5.8341169357,50.6319541931],"type":"Point"}
}