{
  "type": "Feature",
  "properties": {
    "iso:country":"BE",
    "sg:address":"Schaens 25a",
    "sg:city":"Aubel",
    "sg:classifiers":[
        {
            "category":"Utilities",
            "subcategory":"Fuel Oil & Lpg",
            "type":"Services"
        }
    ],
    "sg:phone":"+32 87 68 67 67",
    "sg:postcode":"4880",
    "sg:province":"Li\u00e8ge",
    "wof:name":"Hupperts Freddy Sprl",
    "wof:placetype":"venue"
},
  "geometry": {"coordinates":[5.8583078384,50.7041244507],"type":"Point"}
}