{
  "type": "Feature",
  "properties": {
    "iso:country":"BE",
    "sg:address":"Louizalaan 306b16",
    "sg:city":"Elsene/ixelles",
    "sg:classifiers":[
        {
            "category":"Insurance",
            "subcategory":"Insurance Agent",
            "type":"Services"
        }
    ],
    "sg:phone":"+32 2 643 12 11",
    "sg:postcode":"1050",
    "sg:province":"Bruxelles-Capitale",
    "sg:tags":[
        "verzekeringsmakelaars",
        "expert"
    ],
    "wof:name":"Arag",
    "wof:placetype":"venue"
},
  "geometry": {"coordinates":[4.3573069572,50.8343505859],"type":"Point"}
}