{
  "type": "Feature",
  "properties": {
    "iso:country":"BE",
    "sg:address":"Lage Kaart 187",
    "sg:city":"Brasschaat",
    "sg:classifiers":[
        {
            "category":"Home & Garden",
            "subcategory":"Home Furnishings",
            "type":"Retail Goods"
        }
    ],
    "sg:phone":"+32 475 61 56 85",
    "sg:postcode":"2930",
    "sg:province":"Antwerpen",
    "sg:tags":[
        "interior",
        "decoration"
    ],
    "wof:name":"Calander D",
    "wof:placetype":"venue"
},
  "geometry": {"coordinates":[4.4774222374,51.2984352112],"type":"Point"}
}