{
  "type": "Feature",
  "properties": {
    "iso:country":"BE",
    "sg:address":"Voldersstraat 305",
    "sg:city":"Geraardsbergen (onkerzele)",
    "sg:classifiers":[
        {
            "category":"Building & Trades",
            "subcategory":"Electrical",
            "type":"Services"
        }
    ],
    "sg:phone":"+32 54 41 11 32",
    "sg:postcode":"9500",
    "sg:province":"Oost-Vlaanderen",
    "sg:tags":[
        "electric",
        "-",
        "housewiring",
        "contractor"
    ],
    "wof:name":"De Smedt J",
    "wof:placetype":"venue"
},
  "geometry": {"coordinates":[3.8828001022,50.7776184082],"type":"Point"}
}