{
  "type": "Feature",
  "properties": {
    "addr:full":"De Spoelberchstraat 9 Londerzeel Vlaams-Brabant 1840",
    "addr:housenumber":"9",
    "addr:postcode":"1840",
    "addr:street":"De Spoelberchstraat",
    "iso:country":"BE",
    "sg:address":"De Spoelberchstraat 9",
    "sg:city":"Londerzeel",
    "sg:orig_category":"M\u00e9decins and sp\u00e9cialistes",
    "sg:phone":"+32 52 30 14 84",
    "sg:postcode":"1840",
    "sg:province":"Vlaams-Brabant",
    "wof:name":"J. Verhulst",
    "wof:placetype":"venue"
},
  "geometry": {"coordinates":[4.2988810539,51.0112419128],"type":"Point"}
}