{
  "type": "Feature",
  "properties": {
    "iso:country":"BE",
    "sg:address":"Nispert 33",
    "sg:city":"Eupen",
    "sg:orig_category":"Plomberie, chauffage and installations sanitaires",
    "sg:phone":"+32 87 74 01 89",
    "sg:postcode":"4700",
    "sg:province":"Li\u00e8ge",
    "wof:name":"Jung",
    "wof:placetype":"venue"
},
  "geometry": {"coordinates":[6.047826767,50.6328430176],"type":"Point"}
}