{
  "type": "Feature",
  "properties": {
    "addr:full":"E.goossensstraat 17 Heist-op-den-berg Antwerpen 2223",
    "addr:housenumber":"17",
    "addr:postcode":"2223",
    "addr:street":"E.Goossensstraat",
    "iso:country":"BE",
    "sg:address":"E.goossensstraat 17",
    "sg:city":"Heist-op-den-berg",
    "sg:orig_category":"Enseignement maternel and primaire",
    "sg:phone":"+32 15 73 05 07",
    "sg:postcode":"2223",
    "sg:province":"Antwerpen",
    "wof:name":"Vrije Kleuterschool",
    "wof:placetype":"venue"
},
  "geometry": {"coordinates":[4.6935648918,51.0282707214],"type":"Point"}
}