{
  "type": "Feature",
  "properties": {
    "addr:full":"Rue De L\u00b4enseignement 1 Sprimont Li\u00e8ge 4140",
    "addr:housenumber":"1",
    "addr:postcode":"4140",
    "addr:street":"Rue De L\u00b4Enseignement",
    "iso:country":"BE",
    "sg:address":"Rue De L\u00b4enseignement 1",
    "sg:city":"Sprimont",
    "sg:orig_category":"Woningbouw",
    "sg:phone":"+32 4 382 25 66",
    "sg:postcode":"4140",
    "sg:province":"Li\u00e8ge",
    "wof:name":"Tony Thise",
    "wof:placetype":"venue"
},
  "geometry": {"coordinates":[5.6318001747,50.513961792],"type":"Point"}
}