{
  "type": "Feature",
  "properties": {
    "iso:country":"BE",
    "sg:address":"Beekstraat 118",
    "sg:city":"Beernem",
    "sg:orig_category":"Rundveehouders",
    "sg:phone":"+32 50 78 93 21",
    "sg:postcode":"8730",
    "sg:province":"West-Vlaanderen",
    "wof:name":"Roger Sierens",
    "wof:placetype":"venue"
},
  "geometry": {"coordinates":[3.3216888905,51.1651115417],"type":"Point"}
}