{
  "type": "Feature",
  "properties": {
    "addr:full":"Coenraedt Keynslaan 39 Herent (winksele) Vlaams-Brabant 3020",
    "addr:housenumber":"39",
    "addr:postcode":"3020",
    "addr:street":"Coenraedt Keynslaan",
    "iso:country":"BE",
    "sg:address":"Coenraedt Keynslaan 39",
    "sg:city":"Herent (winksele)",
    "sg:classifiers":[
        {
            "category":"Health Services",
            "subcategory":"Doctor",
            "type":"Services"
        }
    ],
    "sg:phone":"+32 16 23 77 21",
    "sg:postcode":"3020",
    "sg:province":"Vlaams-Brabant",
    "sg:tags":[
        "medicinephysicians",
        "surgeon"
    ],
    "wof:name":"De Raeymaecker L",
    "wof:placetype":"venue"
},
  "geometry": {"coordinates":[4.6600699425,50.8858604431],"type":"Point"}
}