{
  "type": "Feature",
  "properties": {
    "iso:country":"BE",
    "sg:address":"Steenovenstraat 6",
    "sg:city":"Stekene",
    "sg:classifiers":[
        {
            "category":"Building & Trades",
            "subcategory":"Electrical",
            "type":"Services"
        }
    ],
    "sg:phone":"+32 3 779 67 71",
    "sg:postcode":"9190",
    "sg:province":"Oost-Vlaanderen",
    "sg:tags":[
        "electric",
        "-",
        "housewiring",
        "contractor"
    ],
    "wof:name":"Wenselaers P",
    "wof:placetype":"venue"
},
  "geometry": {"coordinates":[4.0447440147,51.2007293701],"type":"Point"}
}