{
  "type": "Feature",
  "properties": {
    "addr:full":"Rue De Mons 151 Mons (ghlin) Hainaut 7011",
    "addr:housenumber":"151",
    "addr:postcode":"7011",
    "addr:street":"Rue De Mons",
    "iso:country":"BE",
    "sg:address":"Rue De Mons 151",
    "sg:city":"Mons (ghlin)",
    "sg:classifiers":[
        {
            "category":"Personal",
            "subcategory":"Beauty Salon",
            "type":"Services"
        }
    ],
    "sg:phone":"+32 65 33 46 56",
    "sg:postcode":"7011",
    "sg:province":"Hainaut",
    "sg:tags":[
        "lady",
        "-",
        "hairdressing"
    ],
    "wof:name":"Coiffure Alain",
    "wof:placetype":"venue"
},
  "geometry": {"coordinates":[3.8567180634,50.4755744934],"type":"Point"}
}