{
  "type": "Feature",
  "properties": {
    "iso:country":"BE",
    "sg:address":"Za Sentier Du Br\u00fbl\u00e9 22",
    "sg:city":"Quaregnon",
    "sg:classifiers":[
        {
            "category":"Professional",
            "subcategory":"Engineering",
            "type":"Services"
        }
    ],
    "sg:phone":"+32 65 78 56 20",
    "sg:postcode":"7390",
    "sg:province":"Hainaut",
    "sg:tags":[
        "machine",
        "-",
        "mechanical"
    ],
    "wof:name":"Erbain Sprl",
    "wof:placetype":"venue"
},
  "geometry": {"coordinates":[3.8639008999,50.446937561],"type":"Point"}
}