{
  "type": "Feature",
  "properties": {
    "iso:country":"BE",
    "sg:address":"Rue Andr\u00c9 Renard 3b15",
    "sg:city":"Oupeye",
    "sg:orig_category":"Jardinage",
    "sg:phone":"+32 495 32 90 00",
    "sg:postcode":"4680",
    "sg:province":"Li\u00e8ge",
    "wof:name":"Laurent Joly",
    "wof:placetype":"venue"
},
  "geometry": {"coordinates":[5.6495079994,50.702747345],"type":"Point"}
}