{
  "type": "Feature",
  "properties": {
    "iso:country":"BE",
    "sg:address":"Verbondstraat 19",
    "sg:city":"Antwerpen",
    "sg:classifiers":[
        {
            "category":"Building & Trades",
            "subcategory":"Cleaning & Sanitation",
            "type":"Services"
        }
    ],
    "sg:phone":"+32 3 248 18 97",
    "sg:postcode":"2000",
    "sg:province":"Antwerpen",
    "sg:tags":[
        "janitor"
    ],
    "wof:name":"Keep It Clean Bvba",
    "wof:placetype":"venue"
},
  "geometry": {"coordinates":[4.4009189606,51.2106246948],"type":"Point"}
}