{
  "type": "Feature",
  "properties": {
    "addr:full":"Krekelmuit 1 Eeklo Oost-Vlaanderen 9900",
    "addr:housenumber":"1",
    "addr:postcode":"9900",
    "addr:street":"Krekelmuit",
    "iso:country":"BE",
    "sg:address":"Krekelmuit 1",
    "sg:city":"Eeklo",
    "sg:classifiers":[
        {
            "category":"Bars & Pubs",
            "type":"Food & Drink"
        }
    ],
    "sg:phone":"+32 9 378 20 12",
    "sg:postcode":"9900",
    "sg:province":"Oost-Vlaanderen",
    "wof:name":"Parking",
    "wof:placetype":"venue"
},
  "geometry": {"coordinates":[3.5297238827,51.1992340088],"type":"Point"}
}