{
  "type": "Feature",
  "properties": {
    "iso:country":"BE",
    "sg:address":"Rue E. Cattoir 4",
    "sg:city":"Elsene/ixelles",
    "sg:orig_category":"Studios photographiques",
    "sg:phone":"+32 2 640 17 67",
    "sg:postcode":"1050",
    "sg:province":"Bruxelles-Capitale",
    "wof:name":"A. Javor Internat",
    "wof:placetype":"venue"
},
  "geometry": {"coordinates":[4.3872270584,50.820892334],"type":"Point"}
}