{
  "type": "Feature",
  "properties": {
    "addr:full":"Westerring 69 Oudenaarde Oost-Vlaanderen 9700",
    "addr:housenumber":"69",
    "addr:postcode":"9700",
    "addr:street":"Westerring",
    "iso:country":"BE",
    "sg:address":"Westerring 69",
    "sg:city":"Oudenaarde",
    "sg:classifiers":[
        {
            "category":"Restaurant",
            "type":"Food & Drink"
        }
    ],
    "sg:phone":"+32 9 384 90 25",
    "sg:postcode":"9700",
    "sg:province":"Oost-Vlaanderen",
    "sg:tags":[
        "caf\u00e9s"
    ],
    "wof:name":"Hendrik Snoeck",
    "wof:placetype":"venue"
},
  "geometry": {"coordinates":[3.616216898,50.8909912109],"type":"Point"}
}