{
  "type": "Feature",
  "properties": {
    "addr:full":"Rue Des Eburons 33 Brussel/bruxelles Bruxelles-Capitale 1000",
    "addr:housenumber":"33",
    "addr:postcode":"1000",
    "addr:street":"Rue Des Eburons;/",
    "iso:country":"BE",
    "sg:address":"Rue Des Eburons 33",
    "sg:city":"Brussel/bruxelles",
    "sg:orig_category":"Salles de spectacles",
    "sg:phone":"+32 2 230 37 73",
    "sg:postcode":"1000",
    "sg:province":"Bruxelles-Capitale",
    "wof:name":"Lib.vl.ver.st.vanderpoor.",
    "wof:placetype":"venue"
},
  "geometry": {"coordinates":[4.3794169426,50.8482284546],"type":"Point"}
}