{
  "type": "Feature",
  "properties": {
    "addr:full":"Belhuttebaan 83 Koekelare West-Vlaanderen 8680",
    "addr:housenumber":"83",
    "addr:postcode":"8680",
    "addr:street":"Belhuttebaan",
    "iso:country":"BE",
    "sg:address":"Belhuttebaan 83",
    "sg:city":"Koekelare",
    "sg:classifiers":[
        {
            "category":"Food & Beverages",
            "subcategory":"Liquor & Beverages",
            "type":"Retail Goods"
        }
    ],
    "sg:phone":"+32 51 58 14 14",
    "sg:postcode":"8680",
    "sg:province":"West-Vlaanderen",
    "sg:tags":[
        "-",
        "spirit",
        "wine"
    ],
    "wof:name":"Desmedt Wijnhuis Bvba",
    "wof:placetype":"venue"
},
  "geometry": {"coordinates":[2.9843270779,51.0847129822],"type":"Point"}
}