{
  "type": "Feature",
  "properties": {
    "addr:full":"Rue Des Combattants 62 La Hulpe Brabant Wallon 1310",
    "addr:housenumber":"62",
    "addr:postcode":"1310",
    "addr:street":"Rue Des Combattants",
    "iso:country":"BE",
    "sg:address":"Rue Des Combattants 62",
    "sg:city":"La Hulpe",
    "sg:orig_category":"Dameskledingzaken",
    "sg:phone":"+32 2 652 27 57",
    "sg:postcode":"1310",
    "sg:province":"Brabant Wallon",
    "wof:name":"Maison Actuelle",
    "wof:placetype":"venue"
},
  "geometry": {"coordinates":[4.4881711006,50.7312927246],"type":"Point"}
}