{
  "type": "Feature",
  "properties": {
    "iso:country":"BE",
    "sg:address":"Fran\u00c7ois Benardstraat 2",
    "sg:city":"Gent",
    "sg:orig_category":"Brood, gebak and snoepgoed",
    "sg:phone":"+32 9 225 37 25",
    "sg:postcode":"9000",
    "sg:province":"Oost-Vlaanderen",
    "wof:name":"Sandra Spittael",
    "wof:placetype":"venue"
},
  "geometry": {"coordinates":[3.7295880318,51.0414123535],"type":"Point"}
}