{
  "type": "Feature",
  "properties": {
    "addr:full":"Terhulpensesteenweg 663 Overijse Vlaams-Brabant 3090",
    "addr:housenumber":"663",
    "addr:postcode":"3090",
    "addr:street":"Terhulpensesteenweg",
    "iso:country":"BE",
    "sg:address":"Terhulpensesteenweg 663",
    "sg:city":"Overijse",
    "sg:orig_category":"Sportclubs",
    "sg:phone":"+32 2 688 04 60",
    "sg:postcode":"3090",
    "sg:province":"Vlaams-Brabant",
    "wof:name":"H.c. Zaid",
    "wof:placetype":"venue"
},
  "geometry": {"coordinates":[4.5366621017,50.7620811462],"type":"Point"}
}