{
  "type": "Feature",
  "properties": {
    "iso:country":"BE",
    "sg:address":"Potaardestraat 1",
    "sg:city":"Izegem",
    "sg:classifiers":[
        {
            "category":"Structure",
            "subcategory":"Office Building",
            "type":"Public Place"
        }
    ],
    "sg:phone":"+32 51 30 50 60",
    "sg:postcode":"8870",
    "sg:province":"West-Vlaanderen",
    "sg:tags":[
        "-",
        "type",
        "door",
        "sliding",
        "overhead"
    ],
    "wof:name":"L. Vroman Nv",
    "wof:placetype":"venue"
},
  "geometry": {"coordinates":[3.2146790028,50.9205284119],"type":"Point"}
}