{
  "type": "Feature",
  "properties": {
    "addr:full":"Petite Place 5 Peruwelz Hainaut 7600",
    "addr:housenumber":"5",
    "addr:postcode":"7600",
    "addr:street":"Petite Place;Hainaut",
    "iso:country":"BE",
    "sg:address":"Petite Place 5",
    "sg:city":"Peruwelz",
    "sg:orig_category":"Banken and kredietinstellingen",
    "sg:phone":"+32 69 77 21 16",
    "sg:postcode":"7600",
    "sg:province":"Hainaut",
    "wof:name":"Fortis",
    "wof:placetype":"venue"
},
  "geometry": {"coordinates":[3.5908699036,50.5080947876],"type":"Point"}
}