{
  "type": "Feature",
  "properties": {
    "addr:full":"Rue De La Montagne 69 Charleroi Hainaut 6000",
    "addr:housenumber":"69",
    "addr:postcode":"6000",
    "addr:street":"Rue De La Montagne;Hainaut",
    "iso:country":"BE",
    "sg:address":"Rue De La Montagne 69",
    "sg:city":"Charleroi",
    "sg:classifiers":[
        {
            "category":"Building & Trades",
            "subcategory":"Cleaning & Sanitation",
            "type":"Services"
        }
    ],
    "sg:phone":"+32 71 32 19 74",
    "sg:postcode":"6000",
    "sg:province":"Hainaut",
    "sg:tags":[
        "industrial",
        "-"
    ],
    "wof:name":"Neuf-\u00e0-sec Sprl",
    "wof:placetype":"venue"
},
  "geometry": {"coordinates":[4.4439668655,50.4108772278],"type":"Point"}
}