{
  "type": "Feature",
  "properties": {
    "addr:full":"Vrouwstraat 5-9 Kaprijke Oost-Vlaanderen 9970",
    "addr:housenumber":"5-9",
    "addr:postcode":"9970",
    "addr:street":"Vrouwstraat",
    "iso:country":"BE",
    "sg:address":"Vrouwstraat 5-9",
    "sg:city":"Kaprijke",
    "sg:classifiers":[
        {
            "category":"Building & Trades",
            "subcategory":"Cleaning & Sanitation",
            "type":"Services"
        }
    ],
    "sg:phone":"+32 9 373 87 82",
    "sg:postcode":"9970",
    "sg:province":"Oost-Vlaanderen",
    "sg:tags":[
        "fa\u00e7ade",
        "maintenance"
    ],
    "wof:name":"Aquaprotect",
    "wof:placetype":"venue"
},
  "geometry": {"coordinates":[3.6214420795,51.2194786072],"type":"Point"}
}