{
  "type": "Feature",
  "properties": {
    "iso:country":"BE",
    "sg:address":"Kronenhoekstraat 21",
    "sg:city":"Sint-gillis-waas",
    "sg:orig_category":"R\u00e9parations d'appareils \u00e9lectrom\u00e9nagers. Electrom\u00e9nager, t\u00e9l\u00e9visions and radios",
    "sg:phone":"+32 3 770 57 61",
    "sg:postcode":"9170",
    "sg:province":"Oost-Vlaanderen",
    "wof:name":"Huis Goedemont-baert",
    "wof:placetype":"venue"
},
  "geometry": {"coordinates":[4.123401165,51.2210273743],"type":"Point"}
}