{
  "type": "Feature",
  "properties": {
    "addr:full":"Houtemsestraat Zemst Vlaams-Brabant 1980",
    "addr:postcode":"1980",
    "addr:street":"Houtemsestraat;Vlaams-Brabant",
    "iso:country":"BE",
    "sg:address":"Houtemsestraat",
    "sg:city":"Zemst",
    "sg:orig_category":"Beheer van afvalopslag- and stortplaatsen",
    "sg:phone":"+32 15 62 01 75",
    "sg:postcode":"1980",
    "sg:province":"Vlaams-Brabant",
    "wof:name":"Containerpark Zemst",
    "wof:placetype":"venue"
},
  "geometry": {"coordinates":[4.4593682289,50.9571762085],"type":"Point"}
}