{
  "type": "Feature",
  "properties": {
    "iso:country":"BE",
    "sg:address":"Frankrijkstraat 38",
    "sg:city":"Moeskroen/mouscron",
    "sg:orig_category":"Dierenartsen",
    "sg:phone":"+32 56 48 89 83",
    "sg:postcode":"7711",
    "sg:province":"Hainaut",
    "wof:name":"J. De Rudder/joseph Derudder",
    "wof:placetype":"venue"
},
  "geometry": {"coordinates":[3.3016269207,50.7269287109],"type":"Point"}
}