{
  "type": "Feature",
  "properties": {
    "iso:country":"BE",
    "sg:address":"Koningin Astridlaan 408",
    "sg:city":"Kraainem/kraainem",
    "sg:orig_category":"Sportclubs",
    "sg:phone":"+32 2 731 97 89",
    "sg:postcode":"1950",
    "sg:province":"Vlaams-Brabant",
    "wof:name":"R. White Star A.c.",
    "wof:placetype":"venue"
},
  "geometry": {"coordinates":[4.4690618515,50.8409881592],"type":"Point"}
}