{
  "type": "Feature",
  "properties": {
    "addr:full":"Markt/ Winterslagstraat 31 Genk Limburg 3600",
    "addr:housenumber":"31",
    "addr:postcode":"3600",
    "addr:street":"Winterslagstraat",
    "iso:country":"BE",
    "sg:address":"Markt/ Winterslagstraat 31",
    "sg:city":"Genk",
    "sg:orig_category":"Chaussures",
    "sg:phone":"+32 89 35 54 65",
    "sg:postcode":"3600",
    "sg:province":"Limburg",
    "wof:name":"Remans Schoenmode",
    "wof:placetype":"venue"
},
  "geometry": {"coordinates":[5.4983539581,50.9647521973],"type":"Point"}
}