{
  "type": "Feature",
  "properties": {
    "addr:full":"Rue De Wavre 59 Sombreffe Namur 5140",
    "addr:housenumber":"59",
    "addr:postcode":"5140",
    "addr:street":"Rue De Wavre",
    "iso:country":"BE",
    "sg:address":"Rue De Wavre 59",
    "sg:city":"Sombreffe",
    "sg:orig_category":"Hypotheken and hypotheekbanken Immobili\u00ebnkantoren Verzekeringsmakelaars and experts",
    "sg:phone":"+32 71 88 89 26",
    "sg:postcode":"5140",
    "sg:province":"Namur",
    "wof:name":"Jean-claude Linet",
    "wof:placetype":"venue"
},
  "geometry": {"coordinates":[4.606637001,50.5302200317],"type":"Point"}
}