{
  "type": "Feature",
  "properties": {
    "addr:full":"Markt 2 Tervuren Vlaams-Brabant 3080",
    "addr:housenumber":"2",
    "addr:postcode":"3080",
    "addr:street":"Markt",
    "iso:country":"BE",
    "sg:address":"Markt 2",
    "sg:city":"Tervuren",
    "sg:orig_category":"Banques and organismes de cr\u00e9dit",
    "sg:phone":"+32 2 767 75 95",
    "sg:postcode":"3080",
    "sg:province":"Vlaams-Brabant",
    "wof:name":"Kbc",
    "wof:placetype":"venue"
},
  "geometry": {"coordinates":[4.5145378113,50.8242721558],"type":"Point"}
}