{
  "type": "Feature",
  "properties": {
    "iso:country":"BE",
    "sg:address":"Schoolstraat 11ba",
    "sg:city":"Olen",
    "sg:orig_category":"Mat\u00e9riel m\u00e9dical and orthop\u00e9dique and proth\u00e8ses Fab",
    "sg:phone":"+32 14 22 33 16",
    "sg:postcode":"2250",
    "sg:province":"Antwerpen",
    "wof:name":"Koen Mertens",
    "wof:placetype":"venue"
},
  "geometry": {"coordinates":[4.8986430168,51.1658058167],"type":"Point"}
}