{
  "type": "Feature",
  "properties": {
    "addr:full":"Pieter Coomansstraat 36 Bornem Antwerpen 2880",
    "addr:housenumber":"36",
    "addr:postcode":"2880",
    "addr:street":"Pieter Coomansstraat",
    "iso:country":"BE",
    "sg:address":"Pieter Coomansstraat 36",
    "sg:city":"Bornem",
    "sg:orig_category":"Sportclubs Sportterreinen and installaties behalve sportcentra",
    "sg:phone":"+32 3 889 33 73",
    "sg:postcode":"2880",
    "sg:province":"Antwerpen",
    "wof:name":"K.v.k. Hingene",
    "wof:placetype":"venue"
},
  "geometry": {"coordinates":[4.242205143,51.0998497009],"type":"Point"}
}