{
  "type": "Feature",
  "properties": {
    "addr:full":"Tieltseweg 66 Dentergem West-Vlaanderen 8720",
    "addr:housenumber":"66",
    "addr:postcode":"8720",
    "addr:street":"Tieltseweg",
    "iso:country":"BE",
    "sg:address":"Tieltseweg 66",
    "sg:city":"Dentergem",
    "sg:orig_category":"Enseignement maternel and primaire",
    "sg:phone":"+32 51 40 49 61",
    "sg:postcode":"8720",
    "sg:province":"West-Vlaanderen",
    "wof:name":"Gemeentelijke Basisschool",
    "wof:placetype":"venue"
},
  "geometry": {"coordinates":[3.3729250431,50.9704170227],"type":"Point"}
}