{
  "type": "Feature",
  "properties": {
    "iso:country":"BE",
    "sg:address":"Zegelaan 6",
    "sg:city":"Bredene",
    "sg:classifiers":[
        {
            "category":"Marine",
            "type":"Transportation"
        }
    ],
    "sg:phone":"+32 59 32 06 89",
    "sg:postcode":"8450",
    "sg:province":"West-Vlaanderen",
    "sg:tags":[
        "fishery",
        "-",
        "shipping"
    ],
    "wof:name":"Wilmar Bvba",
    "wof:placetype":"venue"
},
  "geometry": {"coordinates":[2.9585199356,51.2438964844],"type":"Point"}
}