{
  "type": "Feature",
  "properties": {
    "addr:full":"Rue Auguste Hainaut 7 Jette Bruxelles-Capitale 1090",
    "addr:housenumber":"7",
    "addr:postcode":"1090",
    "addr:street":"Rue Auguste Hainaut",
    "iso:country":"BE",
    "sg:address":"Rue Auguste Hainaut 7",
    "sg:city":"Jette",
    "sg:orig_category":"Ordinateurs and \u00e9quipement informatique",
    "sg:phone":"+32 2 420 03 67",
    "sg:postcode":"1090",
    "sg:province":"Bruxelles-Capitale",
    "wof:name":"Omar Taoufik",
    "wof:placetype":"venue"
},
  "geometry": {"coordinates":[4.3355507851,50.8683204651],"type":"Point"}
}