{
  "type": "Feature",
  "properties": {
    "iso:country":"BE",
    "sg:address":"Wolfstraat 68",
    "sg:city":"Alken",
    "sg:classifiers":[
        {
            "category":"Building & Trades",
            "subcategory":"Landscaping Services",
            "type":"Services"
        }
    ],
    "sg:phone":"+32 11 31 12 52",
    "sg:postcode":"3570",
    "sg:province":"Limburg",
    "sg:tags":[
        "access",
        "pond",
        "laying-out",
        "-"
    ],
    "wof:name":"Automatic Spraying Syst Bvba",
    "wof:placetype":"venue"
},
  "geometry": {"coordinates":[5.2617301941,50.8672218323],"type":"Point"}
}