{
  "type": "Feature",
  "properties": {
    "iso:country":"BE",
    "sg:address":"Rollebeekstraat 38",
    "sg:city":"Wommelgem",
    "sg:classifiers":[
        {
            "category":"Communications",
            "subcategory":"Television Station",
            "type":"Services"
        }
    ],
    "sg:phone":"+32 3 353 16 31",
    "sg:postcode":"2160",
    "sg:province":"Antwerpen",
    "sg:tags":[
        "antenna"
    ],
    "wof:name":"Meca Bvba-mertens Guy",
    "wof:placetype":"venue"
},
  "geometry": {"coordinates":[4.5056262016,51.204624176],"type":"Point"}
}