{
  "type": "Feature",
  "properties": {
    "iso:country":"BE",
    "sg:address":"Koningin Astridstraat 33",
    "sg:city":"Sint-truiden",
    "sg:classifiers":[
        {
            "category":"Professional",
            "subcategory":"Accounting & Tax Preparation",
            "type":"Services"
        }
    ],
    "sg:phone":"+32 11 68 94 96",
    "sg:postcode":"3800",
    "sg:province":"Limburg",
    "sg:tags":[
        "accountant"
    ],
    "wof:name":"Claes M",
    "wof:placetype":"venue"
},
  "geometry": {"coordinates":[5.1777358055,50.8175544739],"type":"Point"}
}