{
  "type": "Feature",
  "properties": {
    "iso:country":"BE",
    "sg:address":"Victor Bocqu\u00e9straat 7",
    "sg:city":"Aalst",
    "sg:classifiers":[
        {
            "category":"Professional",
            "subcategory":"Advertising",
            "type":"Services"
        }
    ],
    "sg:phone":"+32 53 80 21 91",
    "sg:postcode":"9300",
    "sg:province":"Oost-Vlaanderen",
    "sg:tags":[
        "advertising-vans"
    ],
    "wof:name":"G.d.a. Mobile Publi And Promotion Cars Sound And Light Equipment",
    "wof:placetype":"venue"
},
  "geometry": {"coordinates":[4.0381407738,50.9530601501],"type":"Point"}
}