{
  "type": "Feature",
  "properties": {
    "iso:country":"BE",
    "sg:address":"Rue Du Croupet 63",
    "sg:city":"Bassenge",
    "sg:orig_category":"Brood, gebak and snoepgoed",
    "sg:phone":"+32 4 286 50 18",
    "sg:postcode":"4690",
    "sg:province":"Li\u00e8ge",
    "wof:name":"Schipers-noben",
    "wof:placetype":"venue"
},
  "geometry": {"coordinates":[5.577466011,50.7550811768],"type":"Point"}
}