{
  "type": "Feature",
  "properties": {
    "iso:country":"BE",
    "sg:address":"Avenue Jean Mermoz 29",
    "sg:city":"Charleroi",
    "sg:classifiers":[
        {
            "category":"Autos & Motor Vehicles",
            "subcategory":"Fuel & Gas Station",
            "type":"Retail Goods"
        }
    ],
    "sg:phone":"+32 71 35 00 80",
    "sg:postcode":"6041",
    "sg:province":"Hainaut",
    "sg:tags":[
        "stations-service",
        "carburants"
    ],
    "wof:name":"Fe. Wagner",
    "wof:placetype":"venue"
},
  "geometry": {"coordinates":[4.4754152298,50.4759292603],"type":"Point"}
}