{
  "type": "Feature",
  "properties": {
    "iso:country":"BE",
    "sg:address":"Veldekens-vaart 9",
    "sg:city":"Eeklo",
    "sg:orig_category":"Rundveehouders Varkenskwekers",
    "sg:phone":"+32 9 377 72 90",
    "sg:postcode":"9900",
    "sg:province":"Oost-Vlaanderen",
    "wof:name":"Paul Vermeulen",
    "wof:placetype":"venue"
},
  "geometry": {"coordinates":[3.5432679653,51.1661987305],"type":"Point"}
}