{
  "type": "Feature",
  "properties": {
    "addr:full":"Avenue De Schiphol 6 Bruxelles (evere) Bruxelles-Capitale 1140",
    "addr:housenumber":"6",
    "addr:postcode":"1140",
    "addr:street":"Avenue De Schiphol",
    "iso:country":"BE",
    "sg:address":"Avenue De Schiphol 6",
    "sg:city":"Bruxelles (evere)",
    "sg:classifiers":[
        {
            "category":"Professional",
            "subcategory":"Management & Consulting",
            "type":"Services"
        }
    ],
    "sg:phone":"+32 2 702 55 33",
    "sg:postcode":"1140",
    "sg:province":"Bruxelles-Capitale",
    "sg:tags":[
        "-",
        "processing",
        "data",
        "consultant"
    ],
    "wof:name":"Atoseuronext Belgium Sa",
    "wof:placetype":"venue"
},
  "geometry": {"coordinates":[4.4162697792,50.8755111694],"type":"Point"}
}