{
  "type": "Feature",
  "properties": {
    "iso:country":"BE",
    "sg:address":"Abtsdreef 84",
    "sg:city":"Stabroek",
    "sg:orig_category":"Dierenartsen",
    "sg:phone":"+32 3 568 76 97",
    "sg:postcode":"2940",
    "sg:province":"Antwerpen",
    "wof:name":"Sofie Van Dyck",
    "wof:placetype":"venue"
},
  "geometry": {"coordinates":[4.3525857925,51.3394775391],"type":"Point"}
}