{
  "type": "Feature",
  "properties": {
    "addr:full":"Van Frachenlaan 44 Steenokkerzeel Vlaams-Brabant 1820",
    "addr:housenumber":"44",
    "addr:postcode":"1820",
    "addr:street":"Van Frachenlaan",
    "iso:country":"BE",
    "sg:address":"Van Frachenlaan 44",
    "sg:city":"Steenokkerzeel",
    "sg:orig_category":"V\u00eatements. V\u00eatements pour Dames",
    "sg:phone":"+32 2 757 08 15",
    "sg:postcode":"1820",
    "sg:province":"Vlaams-Brabant",
    "wof:name":"Mode Deanna",
    "wof:placetype":"venue"
},
  "geometry": {"coordinates":[4.5094127655,50.9130744934],"type":"Point"}
}