{
  "type": "Feature",
  "properties": {
    "addr:full":"Ninoofsesteenweg 533 Dilbeek Vlaams-Brabant 1700",
    "addr:housenumber":"533",
    "addr:postcode":"1700",
    "addr:street":"Ninoofsesteenweg",
    "iso:country":"BE",
    "sg:address":"Ninoofsesteenweg 533",
    "sg:city":"Dilbeek",
    "sg:classifiers":[
        {
            "category":"Shopping",
            "subcategory":"Crafts & Fabrics",
            "type":"Retail Goods"
        }
    ],
    "sg:phone":"+32 2 569 01 22",
    "sg:postcode":"1700",
    "sg:province":"Vlaams-Brabant",
    "sg:tags":[
        "plant",
        "flower",
        "artificial"
    ],
    "wof:name":"Deco-flor",
    "wof:placetype":"venue"
},
  "geometry": {"coordinates":[4.2509860992,50.8430137634],"type":"Point"}
}