{
  "type": "Feature",
  "properties": {
    "iso:country":"BE",
    "sg:address":"Palingstraat 58",
    "sg:city":"Puurs",
    "sg:orig_category":"Activit\u00e9s d\u00b4action sociale sans h\u00e9bergement",
    "sg:phone":"+32 3 889 67 61",
    "sg:postcode":"2870",
    "sg:province":"Antwerpen",
    "wof:name":"Rode Kruis Puurs",
    "wof:placetype":"venue"
},
  "geometry": {"coordinates":[4.2790999413,51.0720787048],"type":"Point"}
}