{
  "type": "Feature",
  "properties": {
    "iso:country":"BE",
    "sg:address":"Bareelstraat 67",
    "sg:city":"Putte (beerzel)",
    "sg:classifiers":[
        {
            "category":"Professional",
            "subcategory":"Accounting & Tax Preparation",
            "type":"Services"
        }
    ],
    "sg:phone":"+32 15 75 81 18",
    "sg:postcode":"2580",
    "sg:province":"Antwerpen",
    "sg:tags":[
        "accountant"
    ],
    "wof:name":"Swenden J",
    "wof:placetype":"venue"
},
  "geometry": {"coordinates":[4.6667041779,51.0524291992],"type":"Point"}
}