{
  "type": "Feature",
  "properties": {
    "addr:full":"Burmstraat 46 Sint-niklaas (sinaai) Oost-Vlaanderen 9112",
    "addr:housenumber":"46",
    "addr:postcode":"9112",
    "addr:street":"Burmstraat",
    "iso:country":"BE",
    "sg:address":"Burmstraat 46",
    "sg:city":"Sint-niklaas (sinaai)",
    "sg:classifiers":[
        {
            "category":"Retail",
            "subcategory":"Veterinary Services",
            "type":"Services"
        }
    ],
    "sg:phone":"+32 3 772 28 75",
    "sg:postcode":"9112",
    "sg:province":"Oost-Vlaanderen",
    "sg:tags":[
        "veterinarian"
    ],
    "wof:name":"Bulteel N",
    "wof:placetype":"venue"
},
  "geometry": {"coordinates":[4.0607600212,51.1604003906],"type":"Point"}
}