{
  "type": "Feature",
  "properties": {
    "iso:country":"BE",
    "sg:address":"Hoogstraat 41",
    "sg:city":"Assenede",
    "sg:classifiers":[
        {
            "category":"Health Services",
            "subcategory":"Health Practitioner",
            "type":"Services"
        }
    ],
    "sg:phone":"+32 9 343 04 99",
    "sg:postcode":"9960",
    "sg:province":"Oost-Vlaanderen",
    "sg:tags":[
        "physiotherapist"
    ],
    "wof:name":"Van De Velde Tonny",
    "wof:placetype":"venue"
},
  "geometry": {"coordinates":[3.7554268837,51.2288742065],"type":"Point"}
}