{
  "type": "Feature",
  "properties": {
    "addr:full":"Rue De Ciney 90 Rochefort Namur 5580",
    "addr:housenumber":"90",
    "addr:postcode":"5580",
    "addr:street":"Rue De Ciney",
    "iso:country":"BE",
    "sg:address":"Rue De Ciney 90",
    "sg:city":"Rochefort",
    "sg:orig_category":"Elektrische installaties voor woningen",
    "sg:phone":"+32 84 21 39 54",
    "sg:postcode":"5580",
    "sg:province":"Namur",
    "wof:name":"Jean-luc Pierard",
    "wof:placetype":"venue"
},
  "geometry": {"coordinates":[5.2114458084,50.1709785461],"type":"Point"}
}