{
  "type": "Feature",
  "properties": {
    "addr:full":"Dorpsstraat 15 Stabroek Antwerpen 2940",
    "addr:housenumber":"15",
    "addr:postcode":"2940",
    "addr:street":"Dorpsstraat",
    "iso:country":"BE",
    "sg:address":"Dorpsstraat 15",
    "sg:city":"Stabroek",
    "sg:orig_category":"Cr\u00e9dits divers",
    "sg:postcode":"2940",
    "sg:province":"Antwerpen",
    "wof:name":"Bancontact-mister Cash",
    "wof:placetype":"venue"
},
  "geometry": {"coordinates":[4.3633060455,51.3314323425],"type":"Point"}
}