{
  "type": "Feature",
  "properties": {
    "addr:full":"Oude Molenstraat 3 Oostende West-Vlaanderen 8400",
    "addr:housenumber":"3",
    "addr:postcode":"8400",
    "addr:street":"Oude Molenstraat",
    "iso:country":"BE",
    "sg:address":"Oude Molenstraat 3",
    "sg:city":"Oostende",
    "sg:classifiers":[
        {
            "category":"Professional",
            "subcategory":"Employment Agencies",
            "type":"Services"
        }
    ],
    "sg:phone":"+32 50 33 00 91",
    "sg:postcode":"8400",
    "sg:province":"West-Vlaanderen",
    "sg:tags":[
        "matrimonial"
    ],
    "wof:name":"Ag Eureka-carine Hamelryck",
    "wof:placetype":"venue"
},
  "geometry": {"coordinates":[2.908274889,51.222820282],"type":"Point"}
}