{
  "type": "Feature",
  "properties": {
    "iso:country":"BE",
    "sg:address":"De Warande 122",
    "sg:city":"Ham",
    "sg:orig_category":"Gespecialiseerde residenti\u00eble bouw",
    "sg:phone":"+32 11 34 31 42",
    "sg:postcode":"3945",
    "sg:province":"Limburg",
    "wof:name":"Robert Leeten",
    "wof:placetype":"venue"
},
  "geometry": {"coordinates":[5.1959171295,51.1069107056],"type":"Point"}
}