{
  "type": "Feature",
  "properties": {
    "iso:country":"BE",
    "sg:address":"Hollezijp 11",
    "sg:city":"Boom",
    "sg:classifiers":[
        {
            "category":"Education",
            "subcategory":"School",
            "type":"Public Place"
        }
    ],
    "sg:phone":"+32 3 888 15 99",
    "sg:postcode":"2850",
    "sg:province":"Antwerpen",
    "sg:tags":[
        "secondary"
    ],
    "wof:name":"Gemeenschapsmiddenschool den Brandt",
    "wof:placetype":"venue"
},
  "geometry": {"coordinates":[4.3716487885,51.0915336609],"type":"Point"}
}