{
  "type": "Feature",
  "properties": {
    "iso:country":"BE",
    "sg:address":"Mechelsesteenweg 45",
    "sg:city":"Kontich",
    "sg:classifiers":[
        {
            "category":"Personal",
            "subcategory":"Beauty Salon",
            "type":"Services"
        }
    ],
    "sg:phone":"+32 3 458 00 37",
    "sg:postcode":"2550",
    "sg:province":"Antwerpen",
    "sg:tags":[
        "de",
        "coiffure"
    ],
    "wof:name":"De Weerdt",
    "wof:placetype":"venue"
},
  "geometry": {"coordinates":[4.4460968971,51.1331977844],"type":"Point"}
}