{
  "type": "Feature",
  "properties": {
    "iso:country":"BE",
    "sg:address":"Malsemstraat 14",
    "sg:city":"Aalter",
    "sg:orig_category":"Rundveehouders",
    "sg:phone":"+32 9 371 51 55",
    "sg:postcode":"9880",
    "sg:province":"Oost-Vlaanderen",
    "wof:name":"Leon Mouton",
    "wof:placetype":"venue"
},
  "geometry": {"coordinates":[3.4841461182,51.0575294495],"type":"Point"}
}