{
  "type": "Feature",
  "properties": {
    "iso:country":"BE",
    "sg:address":"Palingstraat 11",
    "sg:city":"Oostrozebeke",
    "sg:classifiers":[
        {
            "category":"Airport",
            "subcategory":"International",
            "type":"Transportation"
        }
    ],
    "sg:phone":"+32 56 66 62 33",
    "sg:postcode":"8780",
    "sg:province":"West-Vlaanderen",
    "sg:tags":[
        "-",
        "transport"
    ],
    "wof:name":"Polfliet Vervoer Bvba",
    "wof:placetype":"venue"
},
  "geometry": {"coordinates":[3.335308075,50.9176483154],"type":"Point"}
}