{
  "type": "Feature",
  "properties": {
    "iso:country":"BE",
    "sg:address":"Rue H\u00d4tel Communal 130",
    "sg:city":"Saint-nicolas",
    "sg:orig_category":"Goederenvervoer over de weg",
    "sg:phone":"+32 4 252 51 21",
    "sg:postcode":"4420",
    "sg:province":"Li\u00e8ge",
    "wof:name":"Gilissen Transports",
    "wof:placetype":"venue"
},
  "geometry": {"coordinates":[5.5387787819,50.6338348389],"type":"Point"}
}