{
  "type": "Feature",
  "properties": {
    "addr:full":"Oscar Verschuerestraat 36 Waregem West-Vlaanderen 8790",
    "addr:housenumber":"36",
    "addr:postcode":"8790",
    "addr:street":"Verschuerestraat",
    "iso:country":"BE",
    "sg:address":"Oscar Verschuerestraat 36",
    "sg:city":"Waregem",
    "sg:classifiers":[
        {
            "category":"Bars & Pubs",
            "type":"Food & Drink"
        }
    ],
    "sg:phone":"+32 56 60 30 98",
    "sg:postcode":"8790",
    "sg:province":"West-Vlaanderen",
    "wof:name":"Rembrandt",
    "wof:placetype":"venue"
},
  "geometry": {"coordinates":[3.4293460846,50.8868675232],"type":"Point"}
}