{
  "type": "Feature",
  "properties": {
    "addr:full":"Rue De La Costale 4 Waremme Li\u00e8ge 4300",
    "addr:housenumber":"4",
    "addr:postcode":"4300",
    "addr:street":"Rue De La Costale",
    "iso:country":"BE",
    "sg:address":"Rue De La Costale 4",
    "sg:city":"Waremme",
    "sg:classifiers":[
        {
            "category":"Education",
            "subcategory":"Special Training",
            "type":"Public Place"
        }
    ],
    "sg:phone":"+32 19 32 53 40",
    "sg:postcode":"4300",
    "sg:province":"Li\u00e8ge",
    "sg:tags":[
        "professional"
    ],
    "wof:name":"Tart'inn (eft) Asbl",
    "wof:placetype":"venue"
},
  "geometry": {"coordinates":[5.2537579536,50.7010917664],"type":"Point"}
}