{
  "type": "Feature",
  "properties": {
    "addr:full":"Rue Clair Champs 128 Ohey (haillot) Namur 5351",
    "addr:housenumber":"128",
    "addr:postcode":"5351",
    "addr:street":"Rue Clair Champs;Haillot",
    "iso:country":"BE",
    "sg:address":"Rue Clair Champs 128",
    "sg:city":"Ohey (haillot)",
    "sg:classifiers":[
        {
            "category":"Building & Trades",
            "subcategory":"Construction",
            "type":"Services"
        }
    ],
    "sg:phone":"+32 85 61 17 62",
    "sg:postcode":"5351",
    "sg:province":"Namur",
    "sg:tags":[
        "installation",
        "-",
        "central",
        "heating"
    ],
    "wof:name":"Henrytherm Sa",
    "wof:placetype":"venue"
},
  "geometry": {"coordinates":[5.1502351761,50.4461326599],"type":"Point"}
}