{
  "type": "Feature",
  "properties": {
    "iso:country":"BE",
    "sg:address":"Vredestraat 12",
    "sg:city":"Beerse",
    "sg:classifiers":[
        {
            "category":"Health Services",
            "subcategory":"Health Practitioner",
            "type":"Services"
        }
    ],
    "sg:phone":"+32 14 61 26 56",
    "sg:postcode":"2340",
    "sg:province":"Antwerpen",
    "sg:tags":[
        "physiotherapist"
    ],
    "wof:name":"Bolckmans Dirk",
    "wof:placetype":"venue"
},
  "geometry": {"coordinates":[4.8570561409,51.3197097778],"type":"Point"}
}