{
  "type": "Feature",
  "properties": {
    "addr:full":"Laar 2 Mol Antwerpen 2400",
    "addr:housenumber":"2",
    "addr:postcode":"2400",
    "addr:street":"Laar",
    "iso:country":"BE",
    "sg:address":"Laar 2",
    "sg:city":"Mol",
    "sg:classifiers":[
        {
            "category":"Shopping",
            "subcategory":"Shoes",
            "type":"Retail Goods"
        }
    ],
    "sg:phone":"+32 14 31 01 72",
    "sg:postcode":"2400",
    "sg:province":"Antwerpen",
    "sg:tags":[
        "slipper",
        "-"
    ],
    "wof:name":"Sjoosur",
    "wof:placetype":"venue"
},
  "geometry": {"coordinates":[5.1191000938,51.1867790222],"type":"Point"}
}