{
  "type": "Feature",
  "properties": {
    "addr:full":"Dr\u00c8ve Des Br\u00dbl\u00c9s 1 Sint-pieters-woluwe/woluwe-saint-pierre Bruxelles-Capitale 1150",
    "addr:housenumber":"1",
    "addr:postcode":"1150",
    "addr:street":"Dre\u0300Ve Des Bru\u0302Le\u0301S;/",
    "iso:country":"BE",
    "sg:address":"Dr\u00c8ve Des Br\u00dbl\u00c9s 1",
    "sg:city":"Sint-pieters-woluwe/woluwe-saint-pierre",
    "sg:orig_category":"Avocats and conseillers juridiques",
    "sg:phone":"+32 2 770 12 93",
    "sg:postcode":"1150",
    "sg:province":"Bruxelles-Capitale",
    "wof:name":"J.e. Beernaert",
    "wof:placetype":"venue"
},
  "geometry": {"coordinates":[4.4577240944,50.8239173889],"type":"Point"}
}