{
  "type": "Feature",
  "properties": {
    "iso:country":"BE",
    "sg:address":"Rue Saint-martin 85",
    "sg:city":"L\u00e9glise",
    "sg:classifiers":[
        {
            "category":"Insurance",
            "subcategory":"Insurance Agent",
            "type":"Services"
        }
    ],
    "sg:phone":"+32 63 43 39 09",
    "sg:postcode":"6860",
    "sg:province":"Luxembourg",
    "sg:tags":[
        "broker"
    ],
    "wof:name":"Fisco Rulles Scris Sprl",
    "wof:placetype":"venue"
},
  "geometry": {"coordinates":[5.5390300751,49.8527336121],"type":"Point"}
}