{
  "type": "Feature",
  "properties": {
    "addr:full":"Staatsbaan 2b4 Zulte Oost-Vlaanderen 9870",
    "addr:housenumber":"2b4",
    "addr:postcode":"9870",
    "addr:street":"Staatsbaan",
    "iso:country":"BE",
    "sg:address":"Staatsbaan 2b4",
    "sg:city":"Zulte",
    "sg:orig_category":"Meubles D\u00e9taillants, Am\u00e9nagement de B\u00e2timents et de Cuisines",
    "sg:phone":"+32 9 388 98 71",
    "sg:postcode":"9870",
    "sg:province":"Oost-Vlaanderen",
    "wof:name":"Bovijn Meubelland",
    "wof:placetype":"venue"
},
  "geometry": {"coordinates":[3.4517199993,50.9269294739],"type":"Point"}
}