{
  "type": "Feature",
  "properties": {
    "addr:full":"Capitein Trippstraat 38 Willebroek Antwerpen 2830",
    "addr:housenumber":"38",
    "addr:postcode":"2830",
    "addr:street":"Trippstraat",
    "iso:country":"BE",
    "sg:address":"Capitein Trippstraat 38",
    "sg:city":"Willebroek",
    "sg:orig_category":"Sportclubs",
    "sg:phone":"+32 3 886 53 00",
    "sg:postcode":"2830",
    "sg:province":"Antwerpen",
    "wof:name":"Vrije Zwemmers Willebroek",
    "wof:placetype":"venue"
},
  "geometry": {"coordinates":[4.3580589294,51.0587310791],"type":"Point"}
}