{
  "type": "Feature",
  "properties": {
    "iso:country":"BE",
    "sg:address":"Brusselsesteenweg 277",
    "sg:city":"Merchtem",
    "sg:classifiers":[
        {
            "category":"Bars & Pubs",
            "type":"Food & Drink"
        }
    ],
    "sg:phone":"+32 2 460 05 71",
    "sg:postcode":"1785",
    "sg:province":"Vlaams-Brabant",
    "wof:name":"De Volle Pot",
    "wof:placetype":"venue"
},
  "geometry": {"coordinates":[4.2473049164,50.9445457458],"type":"Point"}
}