{
  "type": "Feature",
  "properties": {
    "iso:country":"BE",
    "sg:address":"Rue Boveroth 17",
    "sg:city":"Baelen (membach)",
    "sg:classifiers":[
        {
            "category":"Insurance",
            "subcategory":"Insurance Agent",
            "type":"Services"
        }
    ],
    "sg:phone":"+32 87 56 91 57",
    "sg:postcode":"4837",
    "sg:province":"Li\u00e8ge",
    "sg:tags":[
        "broker"
    ],
    "wof:name":"Pirard J & Fils Assurances",
    "wof:placetype":"venue"
},
  "geometry": {"coordinates":[5.997355938,50.6170539856],"type":"Point"}
}