{
  "type": "Feature",
  "properties": {
    "addr:full":"Rue De Fontenelle 27 Chaumont-gistoux Brabant Wallon 1325",
    "addr:housenumber":"27",
    "addr:postcode":"1325",
    "addr:street":"Rue De Fontenelle",
    "iso:country":"BE",
    "sg:address":"Rue De Fontenelle 27",
    "sg:city":"Chaumont-gistoux",
    "sg:orig_category":"Catering and organisatie van feesten",
    "sg:phone":"+32 10 68 05 57",
    "sg:postcode":"1325",
    "sg:province":"Brabant Wallon",
    "wof:name":"Durieux Communication",
    "wof:placetype":"venue"
},
  "geometry": {"coordinates":[4.6678628922,50.7078742981],"type":"Point"}
}