{
  "type": "Feature",
  "properties": {
    "iso:country":"BE",
    "sg:address":"Antwerpsestraat 382",
    "sg:city":"Boom",
    "sg:classifiers":[
        {
            "category":"Social Services",
            "subcategory":"Child Care",
            "type":"Services"
        }
    ],
    "sg:phone":"+32 3 888 85 15",
    "sg:postcode":"2850",
    "sg:province":"Antwerpen",
    "sg:tags":[
        "baby",
        "nursery",
        "day",
        "sitting"
    ],
    "wof:name":"Harlekino",
    "wof:placetype":"venue"
},
  "geometry": {"coordinates":[4.3684048653,51.1002655029],"type":"Point"}
}