{
  "type": "Feature",
  "properties": {
    "iso:country":"BE",
    "sg:address":"Avenue Georges Henri 180",
    "sg:city":"Bruxelles (woluwe-saint-lambert)",
    "sg:classifiers":[
        {
            "category":"Professional",
            "subcategory":"Testing Lab",
            "type":"Services"
        }
    ],
    "sg:phone":"+32 2 770 45 20",
    "sg:postcode":"1200",
    "sg:province":"Bruxelles-Capitale",
    "sg:tags":[
        "chemist"
    ],
    "wof:name":"Collin G",
    "wof:placetype":"venue"
},
  "geometry": {"coordinates":[4.416821003,50.8449745178],"type":"Point"}
}