{
  "type": "Feature",
  "properties": {
    "addr:full":"Park Tremeland 52 Tremelo Vlaams-Brabant 3120",
    "addr:housenumber":"52",
    "addr:postcode":"3120",
    "addr:street":"Park Tremeland",
    "iso:country":"BE",
    "sg:address":"Park Tremeland 52",
    "sg:city":"Tremelo",
    "sg:classifiers":[
        {
            "category":"Professional",
            "subcategory":"Management & Consulting",
            "type":"Services"
        }
    ],
    "sg:phone":"+32 16 53 22 19",
    "sg:postcode":"3120",
    "sg:province":"Vlaams-Brabant",
    "sg:tags":[
        "-",
        "processing",
        "data",
        "consultant"
    ],
    "wof:name":"R.m.r. Computing Bvba",
    "wof:placetype":"venue"
},
  "geometry": {"coordinates":[4.7268261909,51.0037155151],"type":"Point"}
}