{
  "type": "Feature",
  "properties": {
    "iso:country":"BE",
    "sg:address":"Rue Des Sources 12",
    "sg:city":"La Bruyere",
    "sg:orig_category":"Rev\u00eatements pour sols and murs. Peinture",
    "sg:phone":"+32 81 21 56 90",
    "sg:postcode":"5080",
    "sg:province":"Namur",
    "wof:name":"Philippe Chiliade",
    "wof:placetype":"venue"
},
  "geometry": {"coordinates":[4.8418979645,50.5159111023],"type":"Point"}
}