{
  "type": "Feature",
  "properties": {
    "addr:full":"Karnemelkstraat 2 Oudenaarde Oost-Vlaanderen 9700",
    "addr:housenumber":"2",
    "addr:postcode":"9700",
    "addr:street":"Karnemelkstraat",
    "iso:country":"BE",
    "sg:address":"Karnemelkstraat 2",
    "sg:city":"Oudenaarde",
    "sg:orig_category":"Eleveurs de bovins",
    "sg:phone":"+32 55 31 17 08",
    "sg:postcode":"9700",
    "sg:province":"Oost-Vlaanderen",
    "wof:name":"Lieven Vandeputte",
    "wof:placetype":"venue"
},
  "geometry": {"coordinates":[3.5776839256,50.8622398376],"type":"Point"}
}