{
  "type": "Feature",
  "properties": {
    "iso:country":"BE",
    "sg:address":"Oostendebaan 41-49",
    "sg:city":"Gistel",
    "sg:orig_category":"Elektrische installaties voor woningen Huishoudapparaten, televisies and radio's Loodgieterij and ce",
    "sg:phone":"+32 59 27 74 40",
    "sg:postcode":"8470",
    "sg:province":"West-Vlaanderen",
    "wof:name":"Tavernier Joost",
    "wof:placetype":"venue"
},
  "geometry": {"coordinates":[2.95084095,51.1512260437],"type":"Point"}
}