{
  "type": "Feature",
  "properties": {
    "addr:full":"Rue Albert I 14 La Louvi\u00e8re Hainaut 7100",
    "addr:housenumber":"14",
    "addr:postcode":"7100",
    "addr:street":"Rue Albert I",
    "iso:country":"BE",
    "sg:address":"Rue Albert I 14",
    "sg:city":"La Louvi\u00e8re",
    "sg:classifiers":[
        {
            "category":"Retail",
            "subcategory":"Repair Shop",
            "type":"Services"
        }
    ],
    "sg:phone":"+32 64 23 84 83",
    "sg:postcode":"7100",
    "sg:province":"Hainaut",
    "sg:tags":[
        "photographic",
        "equipment",
        "-",
        "accessory"
    ],
    "wof:name":"Mailleux Photo-cine",
    "wof:placetype":"venue"
},
  "geometry": {"coordinates":[4.2111902237,50.4707374573],"type":"Point"}
}