{
  "type": "Feature",
  "properties": {
    "addr:full":"Industrielaan 22 Eeklo Oost-Vlaanderen 9900",
    "addr:housenumber":"22",
    "addr:postcode":"9900",
    "addr:street":"Industrielaan",
    "iso:country":"BE",
    "sg:address":"Industrielaan 22",
    "sg:city":"Eeklo",
    "sg:classifiers":[
        {
            "category":"Food & Beverages",
            "subcategory":"Groceries & Convenience Stores",
            "type":"Retail Goods"
        }
    ],
    "sg:phone":"+32 9 377 10 70",
    "sg:postcode":"9900",
    "sg:province":"Oost-Vlaanderen",
    "sg:tags":[
        "baker",
        "-",
        "ingredient"
    ],
    "wof:name":"Vernaet W En Zn",
    "wof:placetype":"venue"
},
  "geometry": {"coordinates":[3.5417580605,51.1823272705],"type":"Point"}
}