{
  "type": "Feature",
  "properties": {
    "addr:full":"Rue Yvan Gils 34 Meix-devant-virton (villers-la-loue) Luxembourg 6769",
    "addr:housenumber":"34",
    "addr:postcode":"6769",
    "addr:street":"Rue Yvan Gils",
    "iso:country":"BE",
    "sg:address":"Rue Yvan Gils 34",
    "sg:city":"Meix-devant-virton (villers-la-loue)",
    "sg:classifiers":[
        {
            "category":"Home & Garden",
            "subcategory":"Home Furnishings",
            "type":"Retail Goods"
        }
    ],
    "sg:phone":"+32 63 57 83 39",
    "sg:postcode":"6769",
    "sg:province":"Luxembourg",
    "sg:tags":[
        "-",
        "bed",
        "mattress"
    ],
    "wof:name":"Baulard Literie",
    "wof:placetype":"venue"
},
  "geometry": {"coordinates":[5.49665308,49.5736351013],"type":"Point"}
}