{
  "type": "Feature",
  "properties": {
    "addr:full":"Avenue Des Alli\u00c9s 30 Waterloo Brabant Wallon 1410",
    "addr:housenumber":"30",
    "addr:postcode":"1410",
    "addr:street":"Avenue Des Allie\u0301S",
    "iso:country":"BE",
    "sg:address":"Avenue Des Alli\u00c9s 30",
    "sg:city":"Waterloo",
    "sg:orig_category":"Sportclubs Sportterreinen and installaties behalve sportcentra",
    "sg:phone":"+32 2 354 35 42",
    "sg:postcode":"1410",
    "sg:province":"Brabant Wallon",
    "wof:name":"R. Racing Club Waterloo",
    "wof:placetype":"venue"
},
  "geometry": {"coordinates":[4.4100599289,50.6978492737],"type":"Point"}
}