{
  "type": "Feature",
  "properties": {
    "iso:country":"BE",
    "sg:address":"Oude Noordlaan 2",
    "sg:city":"Roeselare",
    "sg:orig_category":"Benzinestations and brandstoffen",
    "sg:phone":"+32 51 22 72 62",
    "sg:postcode":"8800",
    "sg:province":"West-Vlaanderen",
    "wof:name":"Diana Decappelle",
    "wof:placetype":"venue"
},
  "geometry": {"coordinates":[3.1195049286,50.9564056396],"type":"Point"}
}