{
  "type": "Feature",
  "properties": {
    "iso:country":"BE",
    "sg:address":"Hekkenhoek 32a",
    "sg:city":"Dendermonde (grembergen)",
    "sg:classifiers":[
        {
            "category":"Real Estate",
            "subcategory":"Architect",
            "type":"Services"
        }
    ],
    "sg:phone":"+32 52 20 27 61",
    "sg:postcode":"9200",
    "sg:province":"Oost-Vlaanderen",
    "wof:name":"Lermytte E",
    "wof:placetype":"venue"
},
  "geometry": {"coordinates":[4.0859189034,51.0567817688],"type":"Point"}
}