{
  "type": "Feature",
  "properties": {
    "iso:country":"BE",
    "sg:address":"Av. Gloires Nationales 51",
    "sg:city":"Ganshoren/ganshoren",
    "sg:orig_category":"Salles de spectacles",
    "sg:phone":"+32 2 425 36 55",
    "sg:postcode":"1083",
    "sg:province":"Bruxelles-Capitale",
    "wof:name":"Praxis Th\u00c9\u00c2tre",
    "wof:placetype":"venue"
},
  "geometry": {"coordinates":[4.3226909637,50.8666152954],"type":"Point"}
}