{
  "type": "Feature",
  "properties": {
    "addr:full":"Antwerpsestraat 75 Niel Antwerpen 2845",
    "addr:housenumber":"75",
    "addr:postcode":"2845",
    "addr:street":"Antwerpsestraat",
    "iso:country":"BE",
    "sg:address":"Antwerpsestraat 75",
    "sg:city":"Niel",
    "sg:classifiers":[
        {
            "category":"Professional",
            "subcategory":"Testing Lab",
            "type":"Services"
        }
    ],
    "sg:phone":"+32 3 888 10 30",
    "sg:postcode":"2845",
    "sg:province":"Antwerpen",
    "sg:tags":[
        "chemist"
    ],
    "wof:name":"Modern Nv",
    "wof:placetype":"venue"
},
  "geometry": {"coordinates":[4.3301329613,51.108959198],"type":"Point"}
}