{
  "type": "Feature",
  "properties": {
    "addr:full":"Rue Henri Massange 17 Stavelot Li\u00e8ge 4970",
    "addr:housenumber":"17",
    "addr:postcode":"4970",
    "addr:street":"Rue Henri Massange",
    "iso:country":"BE",
    "sg:address":"Rue Henri Massange 17",
    "sg:city":"Stavelot",
    "sg:orig_category":"Traitements param\u00e9dicaux",
    "sg:phone":"+32 80 88 09 88",
    "sg:postcode":"4970",
    "sg:province":"Li\u00e8ge",
    "wof:name":"Podoline-rentmeister",
    "wof:placetype":"venue"
},
  "geometry": {"coordinates":[5.9289269447,50.3935661316],"type":"Point"}
}