{
  "type": "Feature",
  "properties": {
    "iso:country":"BE",
    "sg:address":"Rue De Tivoli 1",
    "sg:city":"Walcourt",
    "sg:classifiers":[
        {
            "category":"Bars & Pubs",
            "subcategory":"Nightclub",
            "type":"Food & Drink"
        }
    ],
    "sg:phone":"+32 71 61 17 38",
    "sg:postcode":"5650",
    "sg:province":"Namur",
    "sg:tags":[
        "nachtclubs",
        "dancing"
    ],
    "wof:name":"Cocoon Club",
    "wof:placetype":"venue"
},
  "geometry": {"coordinates":[4.425260067,50.2465591431],"type":"Point"}
}