{
  "type": "Feature",
  "properties": {
    "addr:full":"Baronstraat 163 Izegem West-Vlaanderen 8870",
    "addr:housenumber":"163",
    "addr:postcode":"8870",
    "addr:street":"Baronstraat",
    "iso:country":"BE",
    "sg:address":"Baronstraat 163",
    "sg:city":"Izegem",
    "sg:classifiers":[
        {
            "category":"Autos & Motor Vehicles",
            "subcategory":"Motorcycle Sales",
            "type":"Retail Goods"
        }
    ],
    "sg:phone":"+32 51 30 78 20",
    "sg:postcode":"8870",
    "sg:province":"West-Vlaanderen",
    "sg:tags":[
        "scooter",
        "-",
        "moped"
    ],
    "wof:name":"Pruvoost Motorcenter",
    "wof:placetype":"venue"
},
  "geometry": {"coordinates":[3.2172911167,50.9271736145],"type":"Point"}
}