{
  "type": "Feature",
  "properties": {
    "iso:country":"BE",
    "sg:address":"Rue Winston-churchill 3",
    "sg:city":"Li\u00c8ge",
    "sg:orig_category":"Avocats and conseillers juridiques",
    "sg:phone":"+32 4 342 34 19",
    "sg:postcode":"4020",
    "sg:province":"Li\u00e8ge",
    "wof:name":"Chantal Lourtie",
    "wof:placetype":"venue"
},
  "geometry": {"coordinates":[5.6149902344,50.6427307129],"type":"Point"}
}