{
  "type": "Feature",
  "properties": {
    "iso:country":"BE",
    "sg:address":"Konijnenboslaan 28",
    "sg:city":"Gistel",
    "sg:orig_category":"V\u00e9los Fab",
    "sg:phone":"+32 59 27 66 89",
    "sg:postcode":"8470",
    "sg:province":"West-Vlaanderen",
    "wof:name":"Main D'or",
    "wof:placetype":"venue"
},
  "geometry": {"coordinates":[2.9472560883,51.1513633728],"type":"Point"}
}