{
  "type": "Feature",
  "properties": {
    "addr:full":"Rue Du Vallon 6ba Rixensart Brabant Wallon 1332",
    "addr:postcode":"6ba;1332",
    "addr:street":"Rue Du Vallon;Wallon",
    "iso:country":"BE",
    "sg:address":"Rue Du Vallon 6ba",
    "sg:city":"Rixensart",
    "sg:orig_category":"Wasserijen, Reiniging and Droogkuis",
    "sg:phone":"+32 2 657 50 03",
    "sg:postcode":"1332",
    "sg:province":"Brabant Wallon",
    "wof:name":"Clair & Net",
    "wof:placetype":"venue"
},
  "geometry": {"coordinates":[4.4983711243,50.7170639038],"type":"Point"}
}