{
  "type": "Feature",
  "properties": {
    "addr:full":"Varenblok 12b6 Edegem Antwerpen 2650",
    "addr:housenumber":"12b6",
    "addr:postcode":"2650",
    "addr:street":"Varenblok",
    "iso:country":"BE",
    "sg:address":"Varenblok 12b6",
    "sg:city":"Edegem",
    "sg:orig_category":"Editeurs de revues and p\u00e9riodiques. Editeurs de journaux",
    "sg:phone":"+32 3 449 28 69",
    "sg:postcode":"2650",
    "sg:province":"Antwerpen",
    "wof:name":"Fotografiek",
    "wof:placetype":"venue"
},
  "geometry": {"coordinates":[4.4195132256,51.1650428772],"type":"Point"}
}