{
  "type": "Feature",
  "properties": {
    "iso:country":"BE",
    "sg:address":"All\u00c9e Du Petit Paris 39",
    "sg:city":"Waterloo",
    "sg:orig_category":"Jardinage. Machines and mat\u00e9riel agricoles Gr",
    "sg:phone":"+32 2 353 16 40",
    "sg:postcode":"1410",
    "sg:province":"Brabant Wallon",
    "wof:name":"Arbelag",
    "wof:placetype":"venue"
},
  "geometry": {"coordinates":[4.4062509537,50.7137069702],"type":"Point"}
}