{
  "type": "Feature",
  "properties": {
    "iso:country":"BE",
    "sg:address":"Aldestraat 14",
    "sg:city":"Hasselt",
    "sg:classifiers":[
        {
            "category":"Shopping",
            "subcategory":"Clothing, Apparel, & Fashions",
            "type":"Retail Goods"
        }
    ],
    "sg:phone":"+32 11 22 22 70",
    "sg:postcode":"3500",
    "sg:province":"Limburg",
    "sg:tags":[
        "underwear",
        "lingerie",
        "-"
    ],
    "wof:name":"Lingerie Perfecta",
    "wof:placetype":"venue"
},
  "geometry": {"coordinates":[5.3367109299,50.9302062988],"type":"Point"}
}