{
  "type": "Feature",
  "properties": {
    "iso:country":"BE",
    "sg:address":"Rue Du Ch\u00c2teau 13",
    "sg:city":"Tournai",
    "sg:orig_category":"Eleveurs de bovins",
    "sg:phone":"+32 69 85 92 02",
    "sg:postcode":"7543",
    "sg:province":"Hainaut",
    "wof:name":"Jacques Bauziere",
    "wof:placetype":"venue"
},
  "geometry": {"coordinates":[3.4523839951,50.6474266052],"type":"Point"}
}