{
  "type": "Feature",
  "properties": {
    "iso:country":"BE",
    "sg:address":"De Merodelei 112",
    "sg:city":"Turnhout",
    "sg:orig_category":"Advocaten and juridische adviseurs",
    "sg:phone":"+32 14 43 77 18",
    "sg:postcode":"2300",
    "sg:province":"Antwerpen",
    "wof:name":"E. Kersemans",
    "wof:placetype":"venue"
},
  "geometry": {"coordinates":[4.9365530014,51.3215560913],"type":"Point"}
}