{
  "type": "Feature",
  "properties": {
    "addr:full":"Avenue Charles Woeste 180a Bruxelles (jette) Bruxelles-Capitale 1090",
    "addr:housenumber":"180a",
    "addr:postcode":"1090",
    "addr:street":"Avenue Charles Woeste",
    "iso:country":"BE",
    "sg:address":"Avenue Charles Woeste 180a",
    "sg:city":"Bruxelles (jette)",
    "sg:classifiers":[
        {
            "category":"Food & Beverages",
            "subcategory":"Groceries & Convenience Stores",
            "type":"Retail Goods"
        }
    ],
    "sg:phone":"+32 2 425 15 46",
    "sg:postcode":"1090",
    "sg:province":"Bruxelles-Capitale",
    "sg:tags":[
        "grocer"
    ],
    "wof:name":"Pic-nic",
    "wof:placetype":"venue"
},
  "geometry": {"coordinates":[4.3345417976,50.8724784851],"type":"Point"}
}