{
  "type": "Feature",
  "properties": {
    "iso:country":"BE",
    "sg:address":"Sch\u00f6nefelderweg 167",
    "sg:city":"Eupen",
    "sg:classifiers":[
        {
            "category":"Professional",
            "subcategory":"Management & Consulting",
            "type":"Services"
        }
    ],
    "sg:phone":"+32 87 74 03 87",
    "sg:postcode":"4700",
    "sg:province":"Li\u00e8ge",
    "sg:tags":[
        "consultant",
        "agency",
        "advertising"
    ],
    "wof:name":"Ge Be We",
    "wof:placetype":"venue"
},
  "geometry": {"coordinates":[6.0648088455,50.6301460266],"type":"Point"}
}