{
  "type": "Feature",
  "properties": {
    "addr:full":"Sint-hubertuslaan 19 Balen Antwerpen 2490",
    "addr:housenumber":"19",
    "addr:postcode":"2490",
    "addr:street":"Sint-Hubertuslaan",
    "iso:country":"BE",
    "sg:address":"Sint-hubertuslaan 19",
    "sg:city":"Balen",
    "sg:orig_category":"Dakwerken Loodgieterij, verwarming and sanitaire installaties",
    "sg:phone":"+32 14 30 09 42",
    "sg:postcode":"2490",
    "sg:province":"Antwerpen",
    "wof:name":"Aerts & Zoon",
    "wof:placetype":"venue"
},
  "geometry": {"coordinates":[5.131934166,51.1521644592],"type":"Point"}
}