{
  "type": "Feature",
  "properties": {
    "iso:country":"BE",
    "sg:address":"Avenue Des Eglantines 32",
    "sg:city":"Sint-pieters-woluwe/woluwe-saint-pierre",
    "sg:orig_category":"Epuration des eaux",
    "sg:phone":"+32 2 771 02 54",
    "sg:postcode":"1150",
    "sg:province":"Bruxelles-Capitale",
    "wof:name":"O.f.e.p.",
    "wof:placetype":"venue"
},
  "geometry": {"coordinates":[4.4161782265,50.827747345],"type":"Point"}
}