{
  "type": "Feature",
  "properties": {
    "addr:full":"Rue De La Rive 99 Bruxelles (woluwe-saint-lambert) Bruxelles-Capitale 1200",
    "addr:housenumber":"99",
    "addr:postcode":"1200",
    "addr:street":"Rue De La Rive",
    "iso:country":"BE",
    "sg:address":"Rue De La Rive 99",
    "sg:city":"Bruxelles (woluwe-saint-lambert)",
    "sg:classifiers":[
        {
            "category":"Education",
            "subcategory":"School",
            "type":"Public Place"
        }
    ],
    "sg:phone":"+32 2 771 75 11",
    "sg:postcode":"1200",
    "sg:province":"Bruxelles-Capitale",
    "sg:tags":[
        "secondary"
    ],
    "wof:name":"Ecole Integr\u00e9e",
    "wof:placetype":"venue"
},
  "geometry": {"coordinates":[4.4444580078,50.8497581482],"type":"Point"}
}