{
  "type": "Feature",
  "properties": {
    "addr:full":"Zevenhoek 5 Ninove (voorde) Oost-Vlaanderen 9400",
    "addr:housenumber":"5",
    "addr:postcode":"9400",
    "addr:street":"Zevenhoek;Voorde Oost-Vlaanderen",
    "iso:country":"BE",
    "sg:address":"Zevenhoek 5",
    "sg:city":"Ninove (voorde)",
    "sg:classifiers":[
        {
            "category":"Shopping",
            "subcategory":"Hobbies, Toys, & Games",
            "type":"Retail Goods"
        }
    ],
    "sg:phone":"+32 54 51 82 03",
    "sg:postcode":"9400",
    "sg:province":"Oost-Vlaanderen",
    "sg:tags":[
        "toy",
        "-"
    ],
    "wof:name":"Janibejan Belgi\u00eb",
    "wof:placetype":"venue"
},
  "geometry": {"coordinates":[3.9558160305,50.8188171387],"type":"Point"}
}