{
  "type": "Feature",
  "properties": {
    "addr:full":"Baalsebaan 154 Tremelo Vlaams-Brabant 3210",
    "addr:housenumber":"154",
    "addr:postcode":"3210",
    "addr:street":"Baalsebaan",
    "iso:country":"BE",
    "sg:address":"Baalsebaan 154",
    "sg:city":"Tremelo",
    "sg:orig_category":"Pain, p\u00e2tisseries and confiseries",
    "sg:phone":"+32 16 53 25 43",
    "sg:postcode":"3210",
    "sg:province":"Vlaams-Brabant",
    "wof:name":"Brood & Banket Smolders",
    "wof:placetype":"venue"
},
  "geometry": {"coordinates":[4.724298954,50.9942245483],"type":"Point"}
}