{
  "type": "Feature",
  "properties": {
    "addr:full":"Polderstraat 59 Zwijndrecht Antwerpen 2070",
    "addr:housenumber":"59",
    "addr:postcode":"2070",
    "addr:street":"Polderstraat",
    "iso:country":"BE",
    "sg:address":"Polderstraat 59",
    "sg:city":"Zwijndrecht",
    "sg:orig_category":"Dranken",
    "sg:phone":"+32 3 252 70 70",
    "sg:postcode":"2070",
    "sg:province":"Antwerpen",
    "wof:name":"Carpentier",
    "wof:placetype":"venue"
},
  "geometry": {"coordinates":[4.3320889473,51.220489502],"type":"Point"}
}