{
  "type": "Feature",
  "properties": {
    "addr:full":"Lage Meers 10a Wervik (geluwe) West-Vlaanderen 8940",
    "addr:housenumber":"10a",
    "addr:postcode":"8940",
    "addr:street":"Lage Meers",
    "iso:country":"BE",
    "sg:address":"Lage Meers 10a",
    "sg:city":"Wervik (geluwe)",
    "sg:classifiers":[
        {
            "category":"Building & Trades",
            "subcategory":"Landscaping Services",
            "type":"Services"
        }
    ],
    "sg:phone":"+32 56 51 31 07",
    "sg:postcode":"8940",
    "sg:province":"West-Vlaanderen",
    "sg:tags":[
        "gardening",
        "garden",
        "maintenance"
    ],
    "wof:name":"Serlet-ghesqui\u00e8re",
    "wof:placetype":"venue"
},
  "geometry": {"coordinates":[3.082752943,50.804851532],"type":"Point"}
}