{
  "type": "Feature",
  "properties": {
    "addr:full":"Rue Duydelle 10 Bruxelles (molenbeek-saint-jean) Bruxelles-Capitale 1080",
    "addr:housenumber":"10",
    "addr:postcode":"1080",
    "addr:street":"Rue Duydelle",
    "iso:country":"BE",
    "sg:address":"Rue Duydelle 10",
    "sg:city":"Bruxelles (molenbeek-saint-jean)",
    "sg:classifiers":[
        {
            "category":"Real Estate",
            "subcategory":"Architect",
            "type":"Services"
        }
    ],
    "sg:phone":"+32 2 410 68 76",
    "sg:postcode":"1080",
    "sg:province":"Bruxelles-Capitale",
    "wof:name":"Snoeck Pascal",
    "wof:placetype":"venue"
},
  "geometry": {"coordinates":[4.3176817894,50.8537559509],"type":"Point"}
}