{
  "type": "Feature",
  "properties": {
    "iso:country":"BE",
    "sg:address":"Vilvoordsesteenweg 17",
    "sg:city":"Brussel/bruxelles",
    "sg:orig_category":"Benzinestations and brandstoffen",
    "sg:phone":"+32 2 245 41 82",
    "sg:postcode":"1020",
    "sg:province":"Bruxelles-Capitale",
    "wof:name":"Texaco",
    "wof:placetype":"venue"
},
  "geometry": {"coordinates":[4.375,50.8826255798],"type":"Point"}
}