{
  "type": "Feature",
  "properties": {
    "addr:full":"Gasmeterlaan 207 Gent Oost-Vlaanderen 9000",
    "addr:housenumber":"207",
    "addr:postcode":"9000",
    "addr:street":"Gasmeterlaan;Oost-Vlaanderen",
    "iso:country":"BE",
    "sg:address":"Gasmeterlaan 207",
    "sg:city":"Gent",
    "sg:orig_category":"Mat\u00e9riel \u00e9lectrique and \u00e9lectronique Gr",
    "sg:phone":"+32 9 223 49 53",
    "sg:postcode":"9000",
    "sg:province":"Oost-Vlaanderen",
    "wof:name":"Serelec",
    "wof:placetype":"venue"
},
  "geometry": {"coordinates":[3.7239758968,51.067440033],"type":"Point"}
}