{
  "type": "Feature",
  "properties": {
    "addr:full":"Noordhoekstraat 1 Heuvelland West-Vlaanderen 8950",
    "addr:housenumber":"1",
    "addr:postcode":"8950",
    "addr:street":"Noordhoekstraat",
    "iso:country":"BE",
    "sg:address":"Noordhoekstraat 1",
    "sg:city":"Heuvelland",
    "sg:orig_category":"Eleveurs de bovins. Eleveurs and marchands de porcs",
    "sg:phone":"+32 57 44 51 39",
    "sg:postcode":"8950",
    "sg:province":"West-Vlaanderen",
    "wof:name":"Noel Verraes",
    "wof:placetype":"venue"
},
  "geometry": {"coordinates":[2.8143680096,50.7593193054],"type":"Point"}
}