{
  "type": "Feature",
  "properties": {
    "addr:full":"Carri\u00e8re Des Allumoirs 10 Mouscron Hainaut 7700",
    "addr:housenumber":"10",
    "addr:postcode":"7700",
    "iso:country":"BE",
    "sg:address":"Carri\u00e8re Des Allumoirs 10",
    "sg:city":"Mouscron",
    "sg:classifiers":[
        {
            "category":"Retail",
            "subcategory":"Event Space",
            "type":"Services"
        }
    ],
    "sg:phone":"+32 56 85 93 93",
    "sg:postcode":"7700",
    "sg:province":"Hainaut",
    "sg:tags":[
        "wire",
        "fine"
    ],
    "wof:name":"Drafil S.a.",
    "wof:placetype":"venue"
},
  "geometry": {"coordinates":[3.2145800591,50.7437934875],"type":"Point"}
}