{
  "type": "Feature",
  "properties": {
    "iso:country":"BE",
    "sg:address":"Rue Du Postil 13",
    "sg:city":"Fosses-la-ville",
    "sg:classifiers":[
        {
            "category":"Health Services",
            "subcategory":"Dentist",
            "type":"Services"
        }
    ],
    "sg:phone":"+32 71 71 34 23",
    "sg:postcode":"5070",
    "sg:province":"Namur",
    "wof:name":"Fabry Isabelle",
    "wof:placetype":"venue"
},
  "geometry": {"coordinates":[4.6963157654,50.3949127197],"type":"Point"}
}