{
  "type": "Feature",
  "properties": {
    "addr:full":"Rue Des Croisiers 7 Huy Li\u00e8ge 4500",
    "addr:housenumber":"7",
    "addr:postcode":"4500",
    "addr:street":"Rue Des Croisiers",
    "iso:country":"BE",
    "sg:address":"Rue Des Croisiers 7",
    "sg:city":"Huy",
    "sg:classifiers":[
        {
            "category":"Insurance",
            "subcategory":"Insurance Agent",
            "type":"Services"
        }
    ],
    "sg:phone":"+32 85 84 47 77",
    "sg:postcode":"4500",
    "sg:province":"Li\u00e8ge",
    "sg:tags":[
        "broker"
    ],
    "wof:name":"Closset Assurances",
    "wof:placetype":"venue"
},
  "geometry": {"coordinates":[5.2428689003,50.5168991089],"type":"Point"}
}