{
  "type": "Feature",
  "properties": {
    "addr:full":"Rue Joseph Hamels 15 Crisnee Li\u00e8ge 4367",
    "addr:housenumber":"15",
    "addr:postcode":"4367",
    "addr:street":"Rue Joseph Hamels",
    "iso:country":"BE",
    "sg:address":"Rue Joseph Hamels 15",
    "sg:city":"Crisnee",
    "sg:orig_category":"Sportterreinen and installaties behalve sportcentra",
    "sg:phone":"+32 4 257 51 89",
    "sg:postcode":"4367",
    "sg:province":"Li\u00e8ge",
    "wof:name":"Le Haras De Shannon",
    "wof:placetype":"venue"
},
  "geometry": {"coordinates":[5.4145789146,50.7055854797],"type":"Point"}
}