{
  "type": "Feature",
  "properties": {
    "iso:country":"BE",
    "sg:address":"De Gravestraat 20 Box 2",
    "sg:city":"Sint-niklaas",
    "sg:classifiers":[
        {
            "category":"Professional",
            "subcategory":"Management & Consulting",
            "type":"Services"
        }
    ],
    "sg:phone":"+32 3 778 02 78",
    "sg:postcode":"9100",
    "sg:province":"Oost-Vlaanderen",
    "sg:tags":[
        "-",
        "processing",
        "data",
        "consultant"
    ],
    "wof:name":"Peconsys",
    "wof:placetype":"venue"
},
  "geometry": {"coordinates":[4.1468858719,51.1707191467],"type":"Point"}
}