{
  "type": "Feature",
  "properties": {
    "addr:full":"Rue Armand Bury 11 Thuin Hainaut 6534",
    "addr:housenumber":"11",
    "addr:postcode":"6534",
    "addr:street":"Rue Armand Bury",
    "iso:country":"BE",
    "sg:address":"Rue Armand Bury 11",
    "sg:city":"Thuin",
    "sg:orig_category":"Schoonheidssalons",
    "sg:phone":"+32 71 51 18 59",
    "sg:postcode":"6534",
    "sg:province":"Hainaut",
    "wof:name":"Claude Duterme",
    "wof:placetype":"venue"
},
  "geometry": {"coordinates":[4.3486819267,50.3366127014],"type":"Point"}
}