{
  "type": "Feature",
  "properties": {
    "iso:country":"BE",
    "sg:address":"Chauss\u00c9e De Lasne 32 A",
    "sg:city":"Rixensart",
    "sg:orig_category":"Plomberie, chauffage and installations sanitaires",
    "sg:phone":"+32 477 33 66 52",
    "sg:postcode":"1330",
    "sg:province":"Brabant Wallon",
    "wof:name":"Ventair",
    "wof:placetype":"venue"
},
  "geometry": {"coordinates":[4.5082650185,50.7062034607],"type":"Point"}
}