{
  "type": "Feature",
  "properties": {
    "iso:country":"BE",
    "sg:address":"Generaal Jacqueslaan 90",
    "sg:city":"Elsene/ixelles",
    "sg:orig_category":"Meubelzaken, woning- and keukeninrichting",
    "sg:phone":"+32 2 640 48 56",
    "sg:postcode":"1050",
    "sg:province":"Bruxelles-Capitale",
    "wof:name":"Het Huis V.d. Boekkasten/maison Des Biblioth\u00c8ques",
    "wof:placetype":"venue"
},
  "geometry": {"coordinates":[4.3805961609,50.8194923401],"type":"Point"}
}