{
  "type": "Feature",
  "properties": {
    "addr:full":"Poperingseweg 377 Ieper (vlamertinge) West-Vlaanderen 8908",
    "addr:housenumber":"377",
    "addr:postcode":"8908",
    "addr:street":"Poperingseweg",
    "iso:country":"BE",
    "sg:address":"Poperingseweg 377",
    "sg:city":"Ieper (vlamertinge)",
    "sg:classifiers":[
        {
            "category":"Personal",
            "subcategory":"Beauty Salon",
            "type":"Services"
        }
    ],
    "sg:phone":"+32 57 20 42 60",
    "sg:postcode":"8908",
    "sg:province":"West-Vlaanderen",
    "wof:name":"Gokelaere M",
    "wof:placetype":"venue"
},
  "geometry": {"coordinates":[2.8227689266,50.8540077209],"type":"Point"}
}