{
  "type": "Feature",
  "properties": {
    "addr:full":"Place L\u00e9opold Arlon Luxembourg 6700",
    "addr:postcode":"6700",
    "addr:street":"Place Le\u0301Opold",
    "iso:country":"BE",
    "sg:address":"Place L\u00e9opold",
    "sg:city":"Arlon",
    "sg:classifiers":[
        {
            "category":"Organizations",
            "subcategory":"Professional Association",
            "type":"Services"
        }
    ],
    "sg:phone":"+32 63 21 96 03",
    "sg:postcode":"6700",
    "sg:province":"Luxembourg",
    "sg:tags":[
        "trade-union",
        "federation"
    ],
    "wof:name":"Ordre Des Avocats",
    "wof:placetype":"venue"
},
  "geometry": {"coordinates":[5.8126449585,49.6829948425],"type":"Point"}
}