{
  "type": "Feature",
  "properties": {
    "iso:country":"BE",
    "sg:address":"Moerenstraat 89",
    "sg:city":"Arendonk",
    "sg:classifiers":[
        {
            "category":"Bars & Pubs",
            "subcategory":"Biergarten",
            "type":"Food & Drink"
        }
    ],
    "sg:phone":"+32 14 67 81 79",
    "sg:postcode":"2370",
    "sg:province":"Antwerpen",
    "sg:tags":[
        "foil",
        "polyethylene"
    ],
    "wof:name":"Lentrex Nv",
    "wof:placetype":"venue"
},
  "geometry": {"coordinates":[5.1137099266,51.3194503784],"type":"Point"}
}