{
  "type": "Feature",
  "properties": {
    "iso:country":"BE",
    "sg:address":"Baarledorpstraat 83",
    "sg:city":"Gent",
    "sg:orig_category":"Landmeters",
    "sg:phone":"+32 9 282 55 14",
    "sg:postcode":"9031",
    "sg:province":"Oost-Vlaanderen",
    "wof:name":"Paul Van Hoorebeke",
    "wof:placetype":"venue"
},
  "geometry": {"coordinates":[3.6630249023,51.0503692627],"type":"Point"}
}