{
  "type": "Feature",
  "properties": {
    "iso:country":"BE",
    "sg:address":"Gennepstraat 41",
    "sg:city":"Halen",
    "sg:orig_category":"Eleveurs de bovins",
    "sg:phone":"+32 13 33 66 71",
    "sg:postcode":"3545",
    "sg:province":"Limburg",
    "wof:name":"Jozef Farasyn",
    "wof:placetype":"venue"
},
  "geometry": {"coordinates":[5.0833787918,50.9847640991],"type":"Point"}
}