{
  "type": "Feature",
  "properties": {
    "iso:country":"BE",
    "sg:address":"Rue Sur Les Heids 17a",
    "sg:city":"Bl\u00e9gny (saive)",
    "sg:classifiers":[
        {
            "category":"Building & Trades",
            "subcategory":"Construction",
            "type":"Services"
        }
    ],
    "sg:phone":"+32 4 362 57 88",
    "sg:postcode":"4671",
    "sg:province":"Li\u00e8ge",
    "sg:tags":[
        "carpenter"
    ],
    "wof:name":"Hoeters P Sprl",
    "wof:placetype":"venue"
},
  "geometry": {"coordinates":[5.6820588112,50.6480712891],"type":"Point"}
}