{
  "type": "Feature",
  "properties": {
    "addr:full":"Wijnheuvelenstraat 285 Schaarbeek/schaerbeek Bruxelles-Capitale 1030",
    "addr:housenumber":"285",
    "addr:postcode":"1030",
    "addr:street":"Wijnheuvelenstraat",
    "iso:country":"BE",
    "sg:address":"Wijnheuvelenstraat 285",
    "sg:city":"Schaarbeek/schaerbeek",
    "sg:orig_category":"Schoonmaakbedrijven and ongediertebestrijding",
    "sg:phone":"+32 2 245 86 52",
    "sg:postcode":"1030",
    "sg:province":"Bruxelles-Capitale",
    "wof:name":"Ucar Mesut",
    "wof:placetype":"venue"
},
  "geometry": {"coordinates":[4.3786268234,50.8616676331],"type":"Point"}
}