{
  "type": "Feature",
  "properties": {
    "iso:country":"BE",
    "sg:address":"Kruinstraat 9",
    "sg:city":"Lokeren",
    "sg:classifiers":[
        {
            "category":"Banks & Credit Unions",
            "subcategory":"Bureau De Change",
            "type":"Services"
        }
    ],
    "sg:phone":"+32 9 349 03 79",
    "sg:postcode":"9160",
    "sg:province":"Oost-Vlaanderen",
    "sg:tags":[
        "measuring",
        "control",
        "apparatus"
    ],
    "wof:name":"Analyse Service & Engineering",
    "wof:placetype":"venue"
},
  "geometry": {"coordinates":[4.0172491074,51.0950737],"type":"Point"}
}