{
  "type": "Feature",
  "properties": {
    "addr:full":"Rue Saint-pierre 47 Huy Li\u00e8ge 4500",
    "addr:housenumber":"47",
    "addr:postcode":"4500",
    "addr:street":"Rue Saint-Pierre",
    "iso:country":"BE",
    "sg:address":"Rue Saint-pierre 47",
    "sg:city":"Huy",
    "sg:classifiers":[
        {
            "category":"Home & Garden",
            "subcategory":"Home Furnishings",
            "type":"Retail Goods"
        }
    ],
    "sg:phone":"+32 85 21 16 32",
    "sg:postcode":"4500",
    "sg:province":"Li\u00e8ge",
    "sg:tags":[
        "interior",
        "decoration"
    ],
    "wof:name":"Michel Decoration Sprl",
    "wof:placetype":"venue"
},
  "geometry": {"coordinates":[5.2355761528,50.5228004456],"type":"Point"}
}