{
  "type": "Feature",
  "properties": {
    "iso:country":"BE",
    "sg:address":"Rue Verte Voie 34",
    "sg:city":"Mont-de-l'enclus (amougies)",
    "sg:classifiers":[
        {
            "category":"Professional",
            "subcategory":"Accounting & Tax Preparation",
            "type":"Services"
        }
    ],
    "sg:phone":"+32 69 76 71 67",
    "sg:postcode":"7750",
    "sg:province":"Hainaut",
    "sg:tags":[
        "accountant"
    ],
    "wof:name":"Masygran Sprl",
    "wof:placetype":"venue"
},
  "geometry": {"coordinates":[5.703608036,48.3600578308],"type":"Point"}
}