{
  "type": "Feature",
  "properties": {
    "addr:full":"Hogenhovestraat 35a Tielt (aarsele) West-Vlaanderen 8700",
    "addr:housenumber":"35a",
    "addr:postcode":"8700",
    "addr:street":"Hogenhovestraat",
    "iso:country":"BE",
    "sg:address":"Hogenhovestraat 35a",
    "sg:city":"Tielt (aarsele)",
    "sg:classifiers":[
        {
            "category":"Building & Trades",
            "subcategory":"Construction",
            "type":"Services"
        }
    ],
    "sg:phone":"+32 51 63 43 45",
    "sg:postcode":"8700",
    "sg:province":"West-Vlaanderen",
    "sg:tags":[
        "stucco",
        "contractor"
    ],
    "wof:name":"Everaert Plafonneerwerken Bvba",
    "wof:placetype":"venue"
},
  "geometry": {"coordinates":[3.4194059372,50.9878578186],"type":"Point"}
}