{
  "type": "Feature",
  "properties": {
    "iso:country":"BE",
    "sg:address":"Avenue De Forest 32",
    "sg:city":"Rochefort",
    "sg:orig_category":"Baby- and kinderkleding Babyspullen Dameskledingzaken",
    "sg:phone":"+32 84 21 29 02",
    "sg:postcode":"5580",
    "sg:province":"Namur",
    "wof:name":"Pr\u00c9maman",
    "wof:placetype":"venue"
},
  "geometry": {"coordinates":[5.2213602066,50.1582717896],"type":"Point"}
}