{
  "type": "Feature",
  "properties": {
    "addr:full":"Kerkplein 5 De Pinte Oost-Vlaanderen 9840",
    "addr:housenumber":"5",
    "addr:postcode":"9840",
    "addr:street":"Kerkplein",
    "iso:country":"BE",
    "sg:address":"Kerkplein 5",
    "sg:city":"De Pinte",
    "sg:orig_category":"Verplichte sociale verzekeringen",
    "sg:phone":"+32 9 282 87 73",
    "sg:postcode":"9840",
    "sg:province":"Oost-Vlaanderen",
    "wof:name":"Christelijke Mutualiteit",
    "wof:placetype":"venue"
},
  "geometry": {"coordinates":[3.6492860317,50.9919166565],"type":"Point"}
}