{
  "type": "Feature",
  "properties": {
    "iso:country":"BE",
    "sg:address":"Loenhoutseweg 141",
    "sg:city":"Hoogstraten",
    "sg:orig_category":"Afbraak- and draineerwerken Rundveehouders",
    "sg:phone":"+32 3 314 61 54",
    "sg:postcode":"2320",
    "sg:province":"Antwerpen",
    "wof:name":"Sprangers",
    "wof:placetype":"venue"
},
  "geometry": {"coordinates":[4.7170419693,51.3933753967],"type":"Point"}
}