{
  "type": "Feature",
  "properties": {
    "iso:country":"BE",
    "sg:address":"Stationsstraat 3",
    "sg:city":"Geel",
    "sg:classifiers":[
        {
            "category":"Home & Garden",
            "subcategory":"Home Furnishings",
            "type":"Retail Goods"
        }
    ],
    "sg:phone":"+32 14 58 84 03",
    "sg:postcode":"2440",
    "sg:province":"Antwerpen",
    "sg:tags":[
        "linen",
        "household",
        "-"
    ],
    "wof:name":"Boels Raamdecoratie",
    "wof:placetype":"venue"
},
  "geometry": {"coordinates":[4.9908890724,51.1628761292],"type":"Point"}
}