{
  "type": "Feature",
  "properties": {
    "addr:full":"Gemeenteplein 1 Beveren Oost-Vlaanderen 9120",
    "addr:housenumber":"1",
    "addr:postcode":"9120",
    "addr:street":"Gemeenteplein",
    "iso:country":"BE",
    "sg:address":"Gemeenteplein 1",
    "sg:city":"Beveren",
    "sg:orig_category":"Openbare bibliotheken and archieven",
    "sg:phone":"+32 3 575 04 80",
    "sg:postcode":"9120",
    "sg:province":"Oost-Vlaanderen",
    "wof:name":"Gemeentelijke Openbare Bibliotheek",
    "wof:placetype":"venue"
},
  "geometry": {"coordinates":[4.2788619995,51.2526473999],"type":"Point"}
}