{
  "type": "Feature",
  "properties": {
    "addr:full":"Gasmeterlaan 60 Gent Oost-Vlaanderen 9000",
    "addr:housenumber":"60",
    "addr:postcode":"9000",
    "addr:street":"Gasmeterlaan;Oost-Vlaanderen",
    "iso:country":"BE",
    "sg:address":"Gasmeterlaan 60",
    "sg:city":"Gent",
    "sg:orig_category":"M\u00e9decins and sp\u00e9cialistes",
    "sg:phone":"+32 9 225 60 08",
    "sg:postcode":"9000",
    "sg:province":"Oost-Vlaanderen",
    "wof:name":"Dirk Bourgois",
    "wof:placetype":"venue"
},
  "geometry": {"coordinates":[3.7096199989,51.0652313232],"type":"Point"}
}