{
  "type": "Feature",
  "properties": {
    "addr:full":"Avenue Constant Montald 78 Bruxelles (woluwe-saint-lambert) Bruxelles-Capitale 1200",
    "addr:housenumber":"78",
    "addr:postcode":"1200",
    "addr:street":"Avenue Constant Montald",
    "iso:country":"BE",
    "sg:address":"Avenue Constant Montald 78",
    "sg:city":"Bruxelles (woluwe-saint-lambert)",
    "sg:classifiers":[
        {
            "category":"Health Services",
            "subcategory":"Dentist",
            "type":"Services"
        }
    ],
    "sg:phone":"+32 2 771 62 21",
    "sg:postcode":"1200",
    "sg:province":"Bruxelles-Capitale",
    "wof:name":"Ivens E",
    "wof:placetype":"venue"
},
  "geometry": {"coordinates":[4.4207510948,50.8422737122],"type":"Point"}
}