{
  "type": "Feature",
  "properties": {
    "iso:country":"BE",
    "sg:address":"Hippodroomlaan 20",
    "sg:city":"Bredene",
    "sg:classifiers":[
        {
            "category":"Home & Garden",
            "subcategory":"Kitchen Supply",
            "type":"Retail Goods"
        }
    ],
    "sg:phone":"+32 59 33 12 97",
    "sg:postcode":"8450",
    "sg:province":"West-Vlaanderen",
    "sg:tags":[
        "installation"
    ],
    "wof:name":"Bartan Electro",
    "wof:placetype":"venue"
},
  "geometry": {"coordinates":[2.993710041,51.252620697],"type":"Point"}
}