{
  "type": "Feature",
  "properties": {
    "iso:country":"BE",
    "sg:address":"Jozef De Hasquestraat 7",
    "sg:city":"Antwerpen",
    "sg:classifiers":[
        {
            "category":"Manufacturing",
            "subcategory":"Glass & Minerals",
            "type":"Manufacturing & Wholesale Goods"
        }
    ],
    "sg:phone":"+32 3 233 39 87",
    "sg:postcode":"2000",
    "sg:province":"Antwerpen",
    "sg:tags":[
        "precious",
        "stone"
    ],
    "wof:name":"Seashell Nv",
    "wof:placetype":"venue"
},
  "geometry": {"coordinates":[4.407845974,51.2245025635],"type":"Point"}
}