{
  "type": "Feature",
  "properties": {
    "iso:country":"BE",
    "sg:address":"Gasthuisstraat 20",
    "sg:city":"Turnhout",
    "sg:orig_category":"Banques and organismes de cr\u00e9dit",
    "sg:phone":"+32 14 42 15 51",
    "sg:postcode":"2300",
    "sg:province":"Antwerpen",
    "wof:name":"Bacob",
    "wof:placetype":"venue"
},
  "geometry": {"coordinates":[4.9466309547,51.3225135803],"type":"Point"}
}