{
  "type": "Feature",
  "properties": {
    "addr:full":"August De Boeckstraat 19 Merchtem Vlaams-Brabant 1785",
    "addr:housenumber":"19",
    "addr:postcode":"1785",
    "addr:street":"August De Boeckstraat",
    "iso:country":"BE",
    "sg:address":"August De Boeckstraat 19",
    "sg:city":"Merchtem",
    "sg:orig_category":"Cr\u00e9dits divers",
    "sg:postcode":"1785",
    "sg:province":"Vlaams-Brabant",
    "wof:name":"Bancontact-mister Cash",
    "wof:placetype":"venue"
},
  "geometry": {"coordinates":[4.2278847694,50.9598731995],"type":"Point"}
}