{
  "type": "Feature",
  "properties": {
    "addr:full":"Winterslagstraat 207 Genk Limburg 3600",
    "addr:housenumber":"207",
    "addr:postcode":"3600",
    "addr:street":"Winterslagstraat",
    "iso:country":"BE",
    "sg:address":"Winterslagstraat 207",
    "sg:city":"Genk",
    "sg:orig_category":"Brood, gebak and snoepgoed",
    "sg:phone":"+32 89 35 21 10",
    "sg:postcode":"3600",
    "sg:province":"Limburg",
    "wof:name":"Bakkerij Houben",
    "wof:placetype":"venue"
},
  "geometry": {"coordinates":[5.5011591911,50.9769744873],"type":"Point"}
}