{
  "type": "Feature",
  "properties": {
    "addr:full":"Markt 21 Scherpenheuvel-zichem Vlaams-Brabant 3271",
    "addr:housenumber":"21",
    "addr:postcode":"3271",
    "addr:street":"Markt",
    "iso:country":"BE",
    "sg:address":"Markt 21",
    "sg:city":"Scherpenheuvel-zichem",
    "sg:orig_category":"S\u00e9lection de personnel and placement",
    "sg:phone":"+32 13 77 14 25",
    "sg:postcode":"3271",
    "sg:province":"Vlaams-Brabant",
    "wof:name":"Pwa Scherpenheuvel-zichem",
    "wof:placetype":"venue"
},
  "geometry": {"coordinates":[4.9867010117,51.0010414124],"type":"Point"}
}