{
  "type": "Feature",
  "properties": {
    "iso:country":"BE",
    "sg:address":"Rue De Gembloux 500",
    "sg:city":"Namur",
    "sg:orig_category":"Instellingen voor probleemkinderen Kindertehuizen",
    "sg:phone":"+32 81 73 32 57",
    "sg:postcode":"5002",
    "sg:province":"Namur",
    "wof:name":"Centre Nouveau St.servais",
    "wof:placetype":"venue"
},
  "geometry": {"coordinates":[4.8462319374,50.4782791138],"type":"Point"}
}