{
  "type": "Feature",
  "properties": {
    "iso:country":"BE",
    "sg:address":"Larumseweg 51",
    "sg:city":"Geel",
    "sg:orig_category":"Meubelzaken, woning- and keukeninrichting",
    "sg:phone":"+32 14 59 27 55",
    "sg:postcode":"2440",
    "sg:province":"Antwerpen",
    "wof:name":"Meubelen Pro-deco",
    "wof:placetype":"venue"
},
  "geometry": {"coordinates":[4.9678092003,51.1648902893],"type":"Point"}
}