{
  "type": "Feature",
  "properties": {
    "iso:country":"BE",
    "sg:address":"Heirweg 35",
    "sg:city":"Roeselare",
    "sg:orig_category":"Boucheries",
    "sg:phone":"+32 51 20 11 98",
    "sg:postcode":"8800",
    "sg:province":"West-Vlaanderen",
    "wof:name":"De Kiekeboer",
    "wof:placetype":"venue"
},
  "geometry": {"coordinates":[3.1495449543,50.9790611267],"type":"Point"}
}