{
  "type": "Feature",
  "properties": {
    "iso:country":"BE",
    "sg:address":"Rue De Gembloux 0",
    "sg:city":"La Bruyere",
    "sg:orig_category":"Gestion des d\u00e9charges and sites d\u00e9finitifs de stockage",
    "sg:phone":"+32 81 56 83 74",
    "sg:postcode":"5080",
    "sg:province":"Namur",
    "wof:name":"Parcs A Conteneurs Bruy\u00c8re",
    "wof:placetype":"venue"
},
  "geometry": {"coordinates":[4.7900700569,50.5032234192],"type":"Point"}
}