{
  "type": "Feature",
  "properties": {
    "iso:country":"BE",
    "sg:address":"Schotstraat 2",
    "sg:city":"Herent",
    "sg:classifiers":[
        {
            "category":"Professional",
            "subcategory":"Management & Consulting",
            "type":"Services"
        }
    ],
    "sg:phone":"+32 16 29 03 59",
    "sg:postcode":"3020",
    "sg:province":"Vlaams-Brabant",
    "sg:tags":[
        "consultant"
    ],
    "wof:name":"Dr Management Nv",
    "wof:placetype":"venue"
},
  "geometry": {"coordinates":[4.6643052101,50.8987846375],"type":"Point"}
}