{
  "type": "Feature",
  "properties": {
    "iso:country":"BE",
    "sg:address":"Avenue De Haveskercke 66",
    "sg:city":"Bruxelles (forest)",
    "sg:orig_category":"Newspapers, magazines, periodicals - Publishers",
    "sg:phone":"+32 2 376 03 80",
    "sg:postcode":"1190",
    "sg:province":"Bruxelles-Capitale",
    "wof:name":"Publica Promotion",
    "wof:placetype":"venue"
},
  "geometry": {"coordinates":[4.3233938217,50.8040809631],"type":"Point"}
}