{
  "type": "Feature",
  "properties": {
    "addr:full":"Vichtseweg 171 Waregem West-Vlaanderen 8790",
    "addr:housenumber":"171",
    "addr:postcode":"8790",
    "iso:country":"BE",
    "sg:address":"Vichtseweg 171",
    "sg:city":"Waregem",
    "sg:orig_category":"Souvenirs and objets artisanaux. Fleurs and plantes",
    "sg:phone":"+32 56 77 76 17",
    "sg:postcode":"8790",
    "sg:province":"West-Vlaanderen",
    "wof:name":"Devos-d' Haene",
    "wof:placetype":"venue"
},
  "geometry": {"coordinates":[3.4083230495,50.8522186279],"type":"Point"}
}