{
  "type": "Feature",
  "properties": {
    "addr:full":"Rue De La G\u00c2te 34 Chimay Hainaut 6464",
    "addr:housenumber":"34",
    "addr:postcode":"6464",
    "addr:street":"Rue De La Ga\u0302Te",
    "iso:country":"BE",
    "sg:address":"Rue De La G\u00c2te 34",
    "sg:city":"Chimay",
    "sg:orig_category":"Eleveurs de bovins",
    "sg:phone":"+32 60 21 40 92",
    "sg:postcode":"6464",
    "sg:province":"Hainaut",
    "wof:name":"Moreaux L. & Vincent M.",
    "wof:placetype":"venue"
},
  "geometry": {"coordinates":[4.369866848,50.0226821899],"type":"Point"}
}