{
  "type": "Feature",
  "properties": {
    "addr:full":"Dumortierlaan 121 Knokke-heist (knokke) West-Vlaanderen 8300",
    "addr:housenumber":"121",
    "addr:postcode":"8300",
    "addr:street":"Dumortierlaan",
    "iso:country":"BE",
    "sg:address":"Dumortierlaan 121",
    "sg:city":"Knokke-heist (knokke)",
    "sg:classifiers":[
        {
            "category":"Personal",
            "subcategory":"Beauty Salon",
            "type":"Services"
        }
    ],
    "sg:phone":"+32 50 61 57 55",
    "sg:postcode":"8300",
    "sg:province":"West-Vlaanderen",
    "wof:name":"Tiffany's",
    "wof:placetype":"venue"
},
  "geometry": {"coordinates":[3.287694931,51.3467254639],"type":"Point"}
}