{
  "type": "Feature",
  "properties": {
    "iso:country":"BE",
    "sg:address":"Stationstraat 60",
    "sg:city":"Ardooie",
    "sg:classifiers":[
        {
            "category":"Cafe",
            "type":"Food & Drink"
        }
    ],
    "sg:postcode":"8850",
    "sg:province":"West-Vlaanderen",
    "sg:tags":[
        "caf\u00e9s"
    ],
    "wof:name":"Ons Huis",
    "wof:placetype":"venue"
},
  "geometry": {"coordinates":[3.2001490593,50.980846405],"type":"Point"}
}