{
  "type": "Feature",
  "properties": {
    "addr:full":"Rue A. Billy 42 Daverdisse Namur 5370",
    "addr:housenumber":"42",
    "addr:postcode":"5370",
    "addr:street":"Rue A. Billy",
    "iso:country":"BE",
    "sg:address":"Rue A. Billy 42",
    "sg:city":"Daverdisse",
    "sg:orig_category":"Pensions Vakantiehuizen",
    "sg:phone":"+32 83 63 35 20",
    "sg:postcode":"5370",
    "sg:province":"Namur",
    "wof:name":"La Vieille Forge",
    "wof:placetype":"venue"
},
  "geometry": {"coordinates":[5.2412161827,50.387878418],"type":"Point"}
}