{
  "type": "Feature",
  "properties": {
    "addr:full":"Stingstreuvelslaan 13 Hoeilaart Vlaams-Brabant 1560",
    "addr:housenumber":"13",
    "addr:postcode":"1560",
    "addr:street":"Stingstreuvelslaan",
    "iso:country":"BE",
    "sg:address":"Stingstreuvelslaan 13",
    "sg:city":"Hoeilaart",
    "sg:classifiers":[
        {
            "category":"Professional",
            "subcategory":"Engineering",
            "type":"Services"
        }
    ],
    "sg:phone":"+32 2 268 12 26",
    "sg:postcode":"1560",
    "sg:province":"Vlaams-Brabant",
    "sg:tags":[
        "machine",
        "-",
        "mechanical"
    ],
    "wof:name":"Cheminees Peters Sa",
    "wof:placetype":"venue"
},
  "geometry": {"coordinates":[4.4761118889,50.7717666626],"type":"Point"}
}