{
  "type": "Feature",
  "properties": {
    "addr:full":"Karel De Grotelaan 26 Brussel/bruxelles Bruxelles-Capitale 1000",
    "addr:housenumber":"26",
    "addr:postcode":"1000",
    "addr:street":"Karel De Grotelaan;/",
    "iso:country":"BE",
    "sg:address":"Karel De Grotelaan 26",
    "sg:city":"Brussel/bruxelles",
    "sg:orig_category":"Persagentschappen",
    "sg:phone":"+32 2 640 94 34",
    "sg:postcode":"1000",
    "sg:province":"Bruxelles-Capitale",
    "wof:name":"Heide Newson",
    "wof:placetype":"venue"
},
  "geometry": {"coordinates":[4.3812432289,50.8439979553],"type":"Point"}
}