{
  "type": "Feature",
  "properties": {
    "addr:full":"Broodstraat 21 Oudenaarde Oost-Vlaanderen 9700",
    "addr:housenumber":"21",
    "addr:postcode":"9700",
    "addr:street":"Broodstraat",
    "iso:country":"BE",
    "sg:address":"Broodstraat 21",
    "sg:city":"Oudenaarde",
    "sg:classifiers":[
        {
            "category":"Shopping",
            "subcategory":"Clothing, Apparel, & Fashions",
            "type":"Retail Goods"
        }
    ],
    "sg:phone":"+32 55 31 21 70",
    "sg:postcode":"9700",
    "sg:province":"Oost-Vlaanderen",
    "sg:tags":[
        "clothing",
        "-",
        "gentleman"
    ],
    "wof:name":"Elebaut",
    "wof:placetype":"venue"
},
  "geometry": {"coordinates":[3.6059229374,50.8428840637],"type":"Point"}
}