{
  "type": "Feature",
  "properties": {
    "iso:country":"BE",
    "sg:address":"Gapaard 4",
    "sg:city":"Lo-reninge",
    "sg:classifiers":[
        {
            "category":"Cafe",
            "type":"Food & Drink"
        }
    ],
    "sg:phone":"+32 58 28 80 06",
    "sg:postcode":"8647",
    "sg:province":"West-Vlaanderen",
    "sg:tags":[
        "caf\u00e9s"
    ],
    "wof:name":"Andre Dewaele",
    "wof:placetype":"venue"
},
  "geometry": {"coordinates":[2.6988620758,50.970790863],"type":"Point"}
}