{
  "type": "Feature",
  "properties": {
    "addr:full":"Zeebruggelaan 67 Blankenberge (uitkerke) West-Vlaanderen 8370",
    "addr:housenumber":"67",
    "addr:postcode":"8370",
    "addr:street":"Zeebruggelaan",
    "iso:country":"BE",
    "sg:address":"Zeebruggelaan 67",
    "sg:city":"Blankenberge (uitkerke)",
    "sg:classifiers":[
        {
            "category":"Health Services",
            "subcategory":"Doctor",
            "type":"Services"
        }
    ],
    "sg:phone":"+32 50 41 48 77",
    "sg:postcode":"8370",
    "sg:province":"West-Vlaanderen",
    "sg:tags":[
        "medicinephysicians",
        "surgeon"
    ],
    "wof:name":"Claeys R",
    "wof:placetype":"venue"
},
  "geometry": {"coordinates":[3.1447479725,51.3067016602],"type":"Point"}
}