{
  "type": "Feature",
  "properties": {
    "iso:country":"BE",
    "sg:address":"Rue Edgard Doneux 23",
    "sg:city":"Fl\u00e9malle",
    "sg:classifiers":[
        {
            "category":"Professional",
            "subcategory":"Computer Services",
            "type":"Services"
        }
    ],
    "sg:phone":"+32 4 233 95 77",
    "sg:postcode":"4400",
    "sg:province":"Li\u00e8ge",
    "sg:tags":[
        "-",
        "processing",
        "data"
    ],
    "wof:name":"G M I",
    "wof:placetype":"venue"
},
  "geometry": {"coordinates":[5.4667887688,50.5990066528],"type":"Point"}
}