{
  "type": "Feature",
  "properties": {
    "addr:full":"Rue De La Laiterie 21 Bruxelles (anderlecht) Bruxelles-Capitale 1070",
    "addr:housenumber":"21",
    "addr:postcode":"1070",
    "addr:street":"Rue De La Laiterie",
    "iso:country":"BE",
    "sg:address":"Rue De La Laiterie 21",
    "sg:city":"Bruxelles (anderlecht)",
    "sg:classifiers":[
        {
            "category":"Building & Trades",
            "subcategory":"Pest Control",
            "type":"Services"
        }
    ],
    "sg:phone":"+32 2 411 66 40",
    "sg:postcode":"1070",
    "sg:province":"Bruxelles-Capitale",
    "sg:tags":[
        "painting",
        "contractor"
    ],
    "wof:name":"Sadoine J-m",
    "wof:placetype":"venue"
},
  "geometry": {"coordinates":[4.3088951111,50.8486747742],"type":"Point"}
}