{
  "type": "Feature",
  "properties": {
    "iso:country":"BE",
    "sg:address":"Place Communale 54",
    "sg:city":"Rixensart (genval)",
    "sg:classifiers":[
        {
            "category":"Bakery",
            "type":"Food & Drink"
        }
    ],
    "sg:phone":"+32 2 653 66 76",
    "sg:postcode":"1332",
    "sg:province":"Brabant Wallon",
    "sg:tags":[
        "confectioner",
        "baker"
    ],
    "wof:name":"Kirsch P",
    "wof:placetype":"venue"
},
  "geometry": {"coordinates":[4.4980459213,50.717010498],"type":"Point"}
}