{
  "type": "Feature",
  "properties": {
    "addr:full":"Passage De La Gare 3 Namur Namur 5000",
    "addr:housenumber":"3",
    "addr:postcode":"5000",
    "addr:street":"Passage De La Gare",
    "iso:country":"BE",
    "sg:address":"Passage De La Gare 3",
    "sg:city":"Namur",
    "sg:classifiers":[
        {
            "category":"Cafe",
            "type":"Food & Drink"
        }
    ],
    "sg:phone":"+32 81 26 02 99",
    "sg:postcode":"5000",
    "sg:province":"Namur",
    "sg:tags":[
        "snack-bars"
    ],
    "wof:name":"Roi Dagobert (le)",
    "wof:placetype":"venue"
},
  "geometry": {"coordinates":[4.8648600578,50.4680328369],"type":"Point"}
}