{
  "type": "Feature",
  "properties": {
    "addr:full":"Rue Verte 210 Schaarbeek/schaerbeek Bruxelles-Capitale 1030",
    "addr:housenumber":"210",
    "addr:postcode":"1030",
    "addr:street":"Rue Verte",
    "iso:country":"BE",
    "sg:address":"Rue Verte 210",
    "sg:city":"Schaarbeek/schaerbeek",
    "sg:classifiers":[
        {
            "category":"Organizations",
            "subcategory":"Community Association",
            "type":"Services"
        }
    ],
    "sg:phone":"+32 2 242 20 83",
    "sg:postcode":"1030",
    "sg:province":"Bruxelles-Capitale",
    "sg:tags":[
        "organisation"
    ],
    "wof:name":"C.e.d.a.s.",
    "wof:placetype":"venue"
},
  "geometry": {"coordinates":[4.3662910461,50.8623008728],"type":"Point"}
}