{
  "type": "Feature",
  "properties": {
    "addr:full":"Rue De Nivelles 43 Genappe (houtain-le-val) Brabant Wallon 1476",
    "addr:housenumber":"43",
    "addr:postcode":"1476",
    "addr:street":"Rue De Nivelles;Wallon",
    "iso:country":"BE",
    "sg:address":"Rue De Nivelles 43",
    "sg:city":"Genappe (houtain-le-val)",
    "sg:classifiers":[
        {
            "category":"Juice Bar",
            "subcategory":"None",
            "type":"Food & Drink"
        }
    ],
    "sg:phone":"+32 67 77 13 69",
    "sg:postcode":"1476",
    "sg:province":"Brabant Wallon",
    "sg:tags":[
        "water",
        "soft"
    ],
    "wof:name":"D.b.c.t. Sprl",
    "wof:placetype":"venue"
},
  "geometry": {"coordinates":[4.4069862366,50.5837974548],"type":"Point"}
}