{
  "type": "Feature",
  "properties": {
    "addr:full":"Boulevard Landrieu 8 Beloeil Hainaut 7971",
    "addr:housenumber":"8",
    "addr:postcode":"7971",
    "addr:street":"Boulevard Landrieu",
    "iso:country":"BE",
    "sg:address":"Boulevard Landrieu 8",
    "sg:city":"Beloeil",
    "sg:orig_category":"Voedingsspeciaalzaken",
    "sg:phone":"+32 69 57 85 21",
    "sg:postcode":"7971",
    "sg:province":"Hainaut",
    "wof:name":"Traiteur Christian",
    "wof:placetype":"venue"
},
  "geometry": {"coordinates":[3.6526200771,50.5247077942],"type":"Point"}
}