{
  "type": "Feature",
  "properties": {
    "addr:full":"Rue De L'ange 6 Charleroi (marcinelle) Hainaut 6001",
    "addr:housenumber":"6",
    "addr:postcode":"6001",
    "addr:street":"Rue De L'Ange",
    "iso:country":"BE",
    "sg:address":"Rue De L'ange 6",
    "sg:city":"Charleroi (marcinelle)",
    "sg:classifiers":[
        {
            "category":"Retail",
            "subcategory":"Repair Shop",
            "type":"Services"
        }
    ],
    "sg:phone":"+32 71 36 73 06",
    "sg:postcode":"6001",
    "sg:province":"Hainaut",
    "sg:tags":[
        "radio",
        "television",
        "-",
        "maintenance"
    ],
    "wof:name":"Demanet",
    "wof:placetype":"venue"
},
  "geometry": {"coordinates":[4.4479317665,50.3999176025],"type":"Point"}
}