{
  "type": "Feature",
  "properties": {
    "addr:full":"Rue Des Combattants 37 Jemeppe-sur-sambre (mornimont) Namur 5190",
    "addr:housenumber":"37",
    "addr:postcode":"5190",
    "addr:street":"Rue Des Combattants",
    "iso:country":"BE",
    "sg:address":"Rue Des Combattants 37",
    "sg:city":"Jemeppe-sur-sambre (mornimont)",
    "sg:classifiers":[
        {
            "category":"Banks & Credit Unions",
            "subcategory":"Financial Services",
            "type":"Services"
        }
    ],
    "sg:phone":"+32 71 78 10 68",
    "sg:postcode":"5190",
    "sg:province":"Namur",
    "sg:tags":[
        "loan",
        "mortgage"
    ],
    "wof:name":"Falier P",
    "wof:placetype":"venue"
},
  "geometry": {"coordinates":[4.6703448296,50.4645042419],"type":"Point"}
}