{
  "type": "Feature",
  "properties": {
    "addr:full":"Chauss\u00c9e De Waterloo 711 Ukkel/uccle Bruxelles-Capitale 1180",
    "addr:housenumber":"711",
    "addr:postcode":"1180",
    "addr:street":"Chausse\u0301E De Waterloo;/",
    "iso:country":"BE",
    "sg:address":"Chauss\u00c9e De Waterloo 711",
    "sg:city":"Ukkel/uccle",
    "sg:orig_category":"Chaussures",
    "sg:phone":"+32 2 343 57 48",
    "sg:postcode":"1180",
    "sg:province":"Bruxelles-Capitale",
    "wof:name":"Manfield",
    "wof:placetype":"venue"
},
  "geometry": {"coordinates":[4.3668951988,50.8157424927],"type":"Point"}
}