{
  "type": "Feature",
  "properties": {
    "addr:full":"Schansstraat 39 Lommel Limburg 3920",
    "addr:housenumber":"39",
    "addr:postcode":"3920",
    "addr:street":"Schansstraat",
    "iso:country":"BE",
    "sg:address":"Schansstraat 39",
    "sg:city":"Lommel",
    "sg:classifiers":[
        {
            "category":"Shopping",
            "subcategory":"Crafts & Fabrics",
            "type":"Retail Goods"
        }
    ],
    "sg:postcode":"3920",
    "sg:province":"Limburg",
    "sg:tags":[
        "pleating",
        "embroidery"
    ],
    "wof:name":"Keva Borduurtechniek",
    "wof:placetype":"venue"
},
  "geometry": {"coordinates":[5.3504300117,51.2278289795],"type":"Point"}
}