{
  "type": "Feature",
  "properties": {
    "iso:country":"BE",
    "sg:address":"Avelgemstraat 1",
    "sg:city":"Spiere-helkijn/espierres-helchin",
    "sg:classifiers":[
        {
            "category":"Cafe",
            "type":"Food & Drink"
        }
    ],
    "sg:phone":"+32 56 45 63 63",
    "sg:postcode":"8587",
    "sg:province":"West-Vlaanderen",
    "sg:tags":[
        "caf\u00e9s"
    ],
    "wof:name":"Caf\u00c9 Au Relais",
    "wof:placetype":"venue"
},
  "geometry": {"coordinates":[3.3817150593,50.7325706482],"type":"Point"}
}