{
  "type": "Feature",
  "properties": {
    "iso:country":"BE",
    "sg:address":"Rochelinval 20",
    "sg:city":"Trois-ponts - Fosse (trois-ponts Wanne)",
    "sg:classifiers":[
        {
            "category":"Professional",
            "subcategory":"Management & Consulting",
            "type":"Services"
        }
    ],
    "sg:phone":"+32 80 21 69 94",
    "sg:postcode":"4980",
    "sg:province":"Li\u00e8ge",
    "sg:tags":[
        "consultant"
    ],
    "wof:name":"Added Value Management Sa",
    "wof:placetype":"venue"
},
  "geometry": {"coordinates":[5.9202442169,50.3550033569],"type":"Point"}
}