{
  "type": "Feature",
  "properties": {
    "addr:full":"Boekhoutstraat 2 Gingelom Limburg 3890",
    "addr:housenumber":"2",
    "addr:postcode":"3890",
    "addr:street":"Boekhoutstraat",
    "iso:country":"BE",
    "sg:address":"Boekhoutstraat 2",
    "sg:city":"Gingelom",
    "sg:orig_category":"Rundveehouders",
    "sg:phone":"+32 11 48 27 76",
    "sg:postcode":"3890",
    "sg:province":"Limburg",
    "wof:name":"Jozef Vranken",
    "wof:placetype":"venue"
},
  "geometry": {"coordinates":[5.2364139557,50.7504196167],"type":"Point"}
}