{
  "type": "Feature",
  "properties": {
    "addr:full":"Rue De Tenbosch 96 Bruxelles (ixelles) Bruxelles-Capitale 1050",
    "addr:housenumber":"96",
    "addr:postcode":"1050",
    "addr:street":"Rue De Tenbosch",
    "iso:country":"BE",
    "sg:address":"Rue De Tenbosch 96",
    "sg:city":"Bruxelles (ixelles)",
    "sg:classifiers":[
        {
            "category":"Professional",
            "subcategory":"Computer Services",
            "type":"Services"
        }
    ],
    "sg:phone":"+32 2 347 41 72",
    "sg:postcode":"1050",
    "sg:province":"Bruxelles-Capitale",
    "sg:tags":[
        "-",
        "processing",
        "data",
        "software"
    ],
    "wof:name":"Bookman Software Nv",
    "wof:placetype":"venue"
},
  "geometry": {"coordinates":[4.3618140221,50.8211631775],"type":"Point"}
}