{
  "type": "Feature",
  "properties": {
    "addr:full":"Duinenstraat 225 Bredene West-Vlaanderen 8450",
    "addr:housenumber":"225",
    "addr:postcode":"8450",
    "addr:street":"Duinenstraat",
    "iso:country":"BE",
    "sg:address":"Duinenstraat 225",
    "sg:city":"Bredene",
    "sg:orig_category":"Agences de voyages",
    "sg:phone":"+32 59 32 60 07",
    "sg:postcode":"8450",
    "sg:province":"West-Vlaanderen",
    "wof:name":"Guliana Travel",
    "wof:placetype":"venue"
},
  "geometry": {"coordinates":[2.965200901,51.2429237366],"type":"Point"}
}