{
  "type": "Feature",
  "properties": {
    "addr:full":"Grand-place 0 Ronse/renaix Oost-Vlaanderen 9600",
    "addr:housenumber":"0",
    "addr:postcode":"9600",
    "addr:street":"Grand-Place",
    "iso:country":"BE",
    "sg:address":"Grand-place 0",
    "sg:city":"Ronse/renaix",
    "sg:classifiers":[
        {
            "category":"Government",
            "subcategory":"Police Station",
            "type":"Public Place"
        }
    ],
    "sg:phone":"+32 55 23 28 50",
    "sg:postcode":"9600",
    "sg:province":"Oost-Vlaanderen",
    "sg:tags":[
        "gendarmerie"
    ],
    "wof:name":"Federale Politie",
    "wof:placetype":"venue"
},
  "geometry": {"coordinates":[3.5992999077,50.7470397949],"type":"Point"}
}