{
  "type": "Feature",
  "properties": {
    "iso:country":"BE",
    "sg:address":"Hoogblokstraat 5",
    "sg:city":"Ham (kwaadmechelen)",
    "sg:classifiers":[
        {
            "category":"Professional",
            "subcategory":"Accounting & Tax Preparation",
            "type":"Services"
        }
    ],
    "sg:phone":"+32 13 67 65 00",
    "sg:postcode":"3945",
    "sg:province":"Limburg",
    "sg:tags":[
        "bookkeeper"
    ],
    "wof:name":"Stevens Jean Bvba",
    "wof:placetype":"venue"
},
  "geometry": {"coordinates":[5.1776199341,51.1046104431],"type":"Point"}
}