{
  "type": "Feature",
  "properties": {
    "addr:full":"Rue De Trazegnies 150 Courcelles Hainaut 6180",
    "addr:housenumber":"150",
    "addr:postcode":"6180",
    "addr:street":"Rue De Trazegnies",
    "iso:country":"BE",
    "sg:address":"Rue De Trazegnies 150",
    "sg:city":"Courcelles",
    "sg:orig_category":"Supermarkten",
    "sg:phone":"+32 71 46 32 58",
    "sg:postcode":"6180",
    "sg:province":"Hainaut",
    "wof:name":"Intermarch\u00c9",
    "wof:placetype":"venue"
},
  "geometry": {"coordinates":[4.3528661728,50.4628486633],"type":"Point"}
}