{
  "type": "Feature",
  "properties": {
    "iso:country":"BE",
    "sg:address":"Rue Neuve 81",
    "sg:city":"Gerpinnes",
    "sg:classifiers":[
        {
            "category":"Shopping",
            "subcategory":"Clothing, Apparel, & Fashions",
            "type":"Retail Goods"
        }
    ],
    "sg:phone":"+32 71 22 16 53",
    "sg:postcode":"6280",
    "sg:province":"Hainaut",
    "sg:tags":[
        "-",
        "clothing",
        "child"
    ],
    "wof:name":"Cabriole",
    "wof:placetype":"venue"
},
  "geometry": {"coordinates":[4.4712200165,50.3459815979],"type":"Point"}
}