{
  "type": "Feature",
  "properties": {
    "iso:country":"BE",
    "sg:address":"Kwadestraat 151b",
    "sg:city":"Roeselare",
    "sg:classifiers":[
        {
            "category":"Communications",
            "subcategory":"Television Station",
            "type":"Services"
        }
    ],
    "sg:phone":"+32 51 25 95 25",
    "sg:postcode":"8800",
    "sg:province":"West-Vlaanderen",
    "sg:tags":[
        "consulting",
        "medium"
    ],
    "wof:name":"Wtv V.z.w.",
    "wof:placetype":"venue"
},
  "geometry": {"coordinates":[3.1710109711,50.9198532104],"type":"Point"}
}