{
  "type": "Feature",
  "properties": {
    "addr:full":"Zuidlaan 317 Wetteren Oost-Vlaanderen 9230",
    "addr:housenumber":"317",
    "addr:postcode":"9230",
    "addr:street":"Zuidlaan",
    "iso:country":"BE",
    "sg:address":"Zuidlaan 317",
    "sg:city":"Wetteren",
    "sg:classifiers":[
        {
            "category":"Recreation",
            "type":"Entertainment"
        }
    ],
    "sg:phone":"+32 9 369 24 45",
    "sg:postcode":"9230",
    "sg:province":"Oost-Vlaanderen",
    "sg:tags":[
        "diver",
        "amusement"
    ],
    "wof:name":"'t Kapoentje",
    "wof:placetype":"venue"
},
  "geometry": {"coordinates":[3.85145998,50.9911499023],"type":"Point"}
}