{
  "type": "Feature",
  "properties": {
    "addr:full":"Lange Gasthuisstraat 15 Antwerpen Antwerpen 2000",
    "addr:housenumber":"15",
    "addr:postcode":"2000",
    "addr:street":"Lange Gasthuisstraat",
    "iso:country":"BE",
    "sg:address":"Lange Gasthuisstraat 15",
    "sg:city":"Antwerpen",
    "sg:orig_category":"Banken and kredietinstellingen",
    "sg:phone":"+32 3 223 02 71",
    "sg:postcode":"2000",
    "sg:province":"Antwerpen",
    "wof:name":"Centea",
    "wof:placetype":"venue"
},
  "geometry": {"coordinates":[4.4051737785,51.2155647278],"type":"Point"}
}