{
  "type": "Feature",
  "properties": {
    "iso:country":"BE",
    "sg:address":"Boulevard D'anvers 12",
    "sg:city":"Bruxelles",
    "sg:classifiers":[
        {
            "category":"Travel",
            "subcategory":"Travel Agent",
            "type":"Entertainment"
        }
    ],
    "sg:phone":"+32 2 250 55 55",
    "sg:postcode":"1000",
    "sg:province":"Bruxelles-Capitale",
    "sg:tags":[
        "agency"
    ],
    "wof:name":"Sunjets Direct",
    "wof:placetype":"venue"
},
  "geometry": {"coordinates":[4.3538250923,50.8562698364],"type":"Point"}
}