{
  "type": "Feature",
  "properties": {
    "addr:full":"Graaf De Brigodestraat 33 Hasselt Limburg 3500",
    "addr:housenumber":"33",
    "addr:postcode":"3500",
    "addr:street":"Graaf De Brigodestraat",
    "iso:country":"BE",
    "sg:address":"Graaf De Brigodestraat 33",
    "sg:city":"Hasselt",
    "sg:orig_category":"Avocats and conseillers juridiques",
    "sg:phone":"+32 11 59 26 23",
    "sg:postcode":"3500",
    "sg:province":"Limburg",
    "wof:name":"Luc Vandeputte",
    "wof:placetype":"venue"
},
  "geometry": {"coordinates":[5.3087592125,50.9022789001],"type":"Point"}
}