{
  "type": "Feature",
  "properties": {
    "addr:full":"Ringlaan Noord 84 De Haan (klemskerke) West-Vlaanderen 8420",
    "addr:housenumber":"84",
    "addr:postcode":"8420",
    "addr:street":"Ringlaan Noord",
    "iso:country":"BE",
    "sg:address":"Ringlaan Noord 84",
    "sg:city":"De Haan (klemskerke)",
    "sg:classifiers":[
        {
            "category":"Health Services",
            "subcategory":"Health Practitioner",
            "type":"Services"
        }
    ],
    "sg:phone":"+32 59 23 99 80",
    "sg:postcode":"8420",
    "sg:province":"West-Vlaanderen",
    "sg:tags":[
        "therapist",
        "speech"
    ],
    "wof:name":"Pauwels W",
    "wof:placetype":"venue"
},
  "geometry": {"coordinates":[3.0200469494,51.2662963867],"type":"Point"}
}