{
  "type": "Feature",
  "properties": {
    "iso:country":"BE",
    "sg:address":"Route De Wallonie 33",
    "sg:city":"Mons (ghlin)",
    "sg:classifiers":[
        {
            "category":"Manufacturing",
            "subcategory":"Pottery",
            "type":"Manufacturing & Wholesale Goods"
        }
    ],
    "sg:phone":"+32 65 35 38 85",
    "sg:postcode":"7011",
    "sg:province":"Hainaut",
    "sg:tags":[
        "facing",
        "brick"
    ],
    "wof:name":"Terca Ghlin",
    "wof:placetype":"venue"
},
  "geometry": {"coordinates":[3.8731050491,50.477394104],"type":"Point"}
}