{
  "type": "Feature",
  "properties": {
    "addr:full":"Zeedijk 133 Oostende West-Vlaanderen 8400",
    "addr:housenumber":"133",
    "addr:postcode":"8400",
    "addr:street":"Zeedijk",
    "iso:country":"BE",
    "sg:address":"Zeedijk 133",
    "sg:city":"Oostende",
    "sg:orig_category":"Newspapers, magazines, periodicals - Distribution",
    "sg:phone":"+32 59 50 93 41",
    "sg:postcode":"8400",
    "sg:province":"West-Vlaanderen",
    "wof:name":"Dagbladhandel Bruno",
    "wof:placetype":"venue"
},
  "geometry": {"coordinates":[2.8881390095,51.2204246521],"type":"Point"}
}