{
  "type": "Feature",
  "properties": {
    "addr:full":"Knaptandstraat 70 Sint-niklaas Oost-Vlaanderen 9100",
    "addr:housenumber":"70",
    "addr:postcode":"9100",
    "addr:street":"Knaptandstraat",
    "iso:country":"BE",
    "sg:address":"Knaptandstraat 70",
    "sg:city":"Sint-niklaas",
    "sg:classifiers":[
        {
            "category":"Cafe",
            "type":"Food & Drink"
        }
    ],
    "sg:phone":"+32 3 777 62 53",
    "sg:postcode":"9100",
    "sg:province":"Oost-Vlaanderen",
    "sg:tags":[
        "caf\u00e9s"
    ],
    "wof:name":"Caf\u00c9 In \u00b4t Voske",
    "wof:placetype":"venue"
},
  "geometry": {"coordinates":[4.1442332268,51.1592025757],"type":"Point"}
}