{
  "type": "Feature",
  "properties": {
    "addr:full":"Rue De L'ath\u00e9n\u00e9e 24 Soumagne Li\u00e8ge 4630",
    "addr:housenumber":"24",
    "addr:postcode":"4630",
    "addr:street":"Rue De L'Athe \u0301Ne\u0301E",
    "iso:country":"BE",
    "sg:address":"Rue De L'ath\u00e9n\u00e9e 24",
    "sg:city":"Soumagne",
    "sg:classifiers":[
        {
            "category":"Health Services",
            "subcategory":"Health Practitioner",
            "type":"Services"
        }
    ],
    "sg:phone":"+32 4 377 39 68",
    "sg:postcode":"4630",
    "sg:province":"Li\u00e8ge",
    "sg:tags":[
        "dietitian"
    ],
    "wof:name":"Lacroix I",
    "wof:placetype":"venue"
},
  "geometry": {"coordinates":[5.7337608337,50.6276397705],"type":"Point"}
}