{
  "type": "Feature",
  "properties": {
    "addr:full":"Strandlaan 283-285 Koksijde West-Vlaanderen 8670",
    "addr:housenumber":"283-285",
    "addr:postcode":"8670",
    "addr:street":"Strandlaan",
    "iso:country":"BE",
    "sg:address":"Strandlaan 283-285",
    "sg:city":"Koksijde",
    "sg:classifiers":[
        {
            "category":"Travel",
            "subcategory":"Hotels & Motels",
            "type":"Entertainment"
        }
    ],
    "sg:phone":"+32 58 51 35 58",
    "sg:postcode":"8670",
    "sg:province":"West-Vlaanderen",
    "wof:name":"Ruytingen (hotel)",
    "wof:placetype":"venue"
},
  "geometry": {"coordinates":[2.6121819019,51.1094970703],"type":"Point"}
}