{
  "type": "Feature",
  "properties": {
    "addr:full":"Rue Baillet-latour 9 Virton (latour) Luxembourg 6761",
    "addr:housenumber":"9",
    "addr:postcode":"6761",
    "addr:street":"Rue Baillet-Latour;Latour",
    "iso:country":"BE",
    "sg:address":"Rue Baillet-latour 9",
    "sg:city":"Virton (latour)",
    "sg:orig_category":"Oldtimers",
    "sg:phone":"+32 63 57 06 45",
    "sg:postcode":"6761",
    "sg:province":"Luxembourg",
    "wof:name":"Labbe J",
    "wof:placetype":"venue"
},
  "geometry": {"coordinates":[5.5698151588,49.5577392578],"type":"Point"}
}