{
  "type": "Feature",
  "properties": {
    "addr:full":"Chauss\u00c9e De Waterloo 1253 Ukkel/uccle Bruxelles-Capitale 1180",
    "addr:postcode":"1253;1180",
    "addr:street":"Chausse\u0301E De Waterloo",
    "iso:country":"BE",
    "sg:address":"Chauss\u00c9e De Waterloo 1253",
    "sg:city":"Ukkel/uccle",
    "sg:orig_category":"Blanchisseries and teintureries",
    "sg:phone":"+32 2 374 44 01",
    "sg:postcode":"1180",
    "sg:province":"Bruxelles-Capitale",
    "wof:name":"Laverie La Fra\u00cecheur",
    "wof:placetype":"venue"
},
  "geometry": {"coordinates":[4.373729229,50.7934303284],"type":"Point"}
}