{
  "type": "Feature",
  "properties": {
    "addr:full":"Schoonderbeukenweg 135 Aarschot Vlaams-Brabant 3202",
    "addr:housenumber":"135",
    "addr:postcode":"3202",
    "iso:country":"BE",
    "sg:address":"Schoonderbeukenweg 135",
    "sg:city":"Aarschot",
    "sg:classifiers":[
        {
            "category":"Personal",
            "subcategory":"Beauty Salon",
            "type":"Services"
        }
    ],
    "sg:phone":"+32 16 50 08 66",
    "sg:postcode":"3202",
    "sg:province":"Vlaams-Brabant",
    "sg:tags":[
        "de",
        "coiffure"
    ],
    "wof:name":"Jose Mattheus",
    "wof:placetype":"venue"
},
  "geometry": {"coordinates":[4.9089751244,50.9710273743],"type":"Point"}
}