{
  "type": "Feature",
  "properties": {
    "addr:full":"Industrieterrein peerderbaan 1310 Bree Limburg 3960",
    "addr:housenumber":"1310",
    "addr:postcode":"3960",
    "addr:street":"Industrieterrein Peerderbaan",
    "iso:country":"BE",
    "sg:address":"Industrieterrein peerderbaan 1310",
    "sg:city":"Bree",
    "sg:classifiers":[
        {
            "category":"Manufacturing",
            "subcategory":"Metals",
            "type":"Manufacturing & Wholesale Goods"
        }
    ],
    "sg:phone":"+32 89 46 36 36",
    "sg:postcode":"3960",
    "sg:province":"Limburg",
    "sg:tags":[
        "working"
    ],
    "wof:name":"Heka Nv",
    "wof:placetype":"venue"
},
  "geometry": {"coordinates":[5.5733389854,51.1394691467],"type":"Point"}
}