{
  "type": "Feature",
  "properties": {
    "addr:full":"T'hoge 52 Kortrijk West-Vlaanderen 8500",
    "addr:housenumber":"52",
    "addr:postcode":"8500",
    "addr:street":"T'Hoge",
    "iso:country":"BE",
    "sg:address":"T'hoge 52",
    "sg:city":"Kortrijk",
    "sg:classifiers":[
        {
            "category":"Manufacturing",
            "subcategory":"Rubber & Plastics",
            "type":"Manufacturing & Wholesale Goods"
        }
    ],
    "sg:phone":"+32 56 20 39 74",
    "sg:postcode":"8500",
    "sg:province":"West-Vlaanderen",
    "sg:tags":[
        "packaging",
        "material",
        "-"
    ],
    "wof:name":"Visalux Nv",
    "wof:placetype":"venue"
},
  "geometry": {"coordinates":[3.2800600529,50.817741394],"type":"Point"}
}