{
  "type": "Feature",
  "properties": {
    "iso:country":"BE",
    "sg:address":"All\u00c9e Des Alouettes 2",
    "sg:city":"Namur",
    "sg:orig_category":"V\u00e9hicules automobiles",
    "sg:phone":"+32 81 30 35 50",
    "sg:postcode":"5101",
    "sg:province":"Namur",
    "wof:name":"Belartal",
    "wof:placetype":"venue"
},
  "geometry": {"coordinates":[4.9020981789,50.4372215271],"type":"Point"}
}