{
  "type": "Feature",
  "properties": {
    "addr:full":"Breydelstraat 31 Antwerpen Antwerpen 2018",
    "addr:housenumber":"31",
    "addr:postcode":"2018",
    "addr:street":"Breydelstraat",
    "iso:country":"BE",
    "sg:address":"Breydelstraat 31",
    "sg:city":"Antwerpen",
    "sg:classifiers":[
        {
            "category":"Cafe",
            "type":"Food & Drink"
        }
    ],
    "sg:phone":"+32 3 231 44 38",
    "sg:postcode":"2018",
    "sg:province":"Antwerpen",
    "sg:tags":[
        "caf\u00e9s"
    ],
    "wof:name":"Caf\u00c9 Italia 90",
    "wof:placetype":"venue"
},
  "geometry": {"coordinates":[4.4193468094,51.2175598145],"type":"Point"}
}