{
  "type": "Feature",
  "properties": {
    "iso:country":"BE",
    "sg:address":"Tempelstraat 11",
    "sg:city":"Beerse",
    "sg:orig_category":"Installation de menuiserie en bois and plastique",
    "sg:phone":"+32 14 61 32 04",
    "sg:postcode":"2340",
    "sg:province":"Antwerpen",
    "wof:name":"L.m.v.",
    "wof:placetype":"venue"
},
  "geometry": {"coordinates":[4.8546199799,51.3163566589],"type":"Point"}
}