{
  "type": "Feature",
  "properties": {
    "addr:full":"Rue Lucien Nam\u00c8che 44 Namur Namur 5000",
    "addr:housenumber":"44",
    "addr:postcode":"5000",
    "addr:street":"Rue Lucien Name\u0300Che",
    "iso:country":"BE",
    "sg:address":"Rue Lucien Nam\u00c8che 44",
    "sg:city":"Namur",
    "sg:classifiers":[
        {
            "category":"Fast Food",
            "type":"Food & Drink"
        }
    ],
    "sg:phone":"+32 81 25 04 04",
    "sg:postcode":"5000",
    "sg:province":"Namur",
    "sg:tags":[
        "huis",
        "aan",
        "levering",
        "meeneem",
        "restaurant"
    ],
    "wof:name":"Arrivero Namur",
    "wof:placetype":"venue"
},
  "geometry": {"coordinates":[4.8684711456,50.4680557251],"type":"Point"}
}