{
  "type": "Feature",
  "properties": {
    "iso:country":"BE",
    "sg:address":"Avenue Broustin 7",
    "sg:city":"Jette/jette",
    "sg:orig_category":"Agences de publicit\u00e9",
    "sg:phone":"+32 2 428 29 86",
    "sg:postcode":"1090",
    "sg:province":"Bruxelles-Capitale",
    "wof:name":"Ideealen Copyright",
    "wof:placetype":"venue"
},
  "geometry": {"coordinates":[4.3261752129,50.8678207397],"type":"Point"}
}