{
  "type": "Feature",
  "properties": {
    "addr:full":"Rue Emile Henricot 55 Court-saint-etienne Brabant Wallon 1490",
    "addr:housenumber":"55;1490",
    "addr:street":"Rue Emile Henricot",
    "iso:country":"BE",
    "sg:address":"Rue Emile Henricot 55",
    "sg:city":"Court-saint-etienne",
    "sg:classifiers":[
        {
            "category":"Shopping",
            "subcategory":"Jewelry",
            "type":"Retail Goods"
        }
    ],
    "sg:phone":"+32 10 61 16 66",
    "sg:postcode":"1490",
    "sg:province":"Brabant Wallon",
    "sg:tags":[
        "jeweller",
        "-"
    ],
    "wof:name":"Clerbois Bijouterie Sprl",
    "wof:placetype":"venue"
},
  "geometry": {"coordinates":[4.5661530495,50.6457824707],"type":"Point"}
}