{
  "type": "Feature",
  "properties": {
    "addr:full":"Grand\u00b4place 53 Saint-ghislain Hainaut 7330",
    "addr:housenumber":"53",
    "addr:postcode":"7330",
    "addr:street":"Grand\u00b4Place;Hainaut",
    "iso:country":"BE",
    "sg:address":"Grand\u00b4place 53",
    "sg:city":"Saint-ghislain",
    "sg:orig_category":"Pharmaciens",
    "sg:phone":"+32 65 78 38 51",
    "sg:postcode":"7330",
    "sg:province":"Hainaut",
    "wof:name":"Pharmacie Cherain-durez",
    "wof:placetype":"venue"
},
  "geometry": {"coordinates":[3.8201899529,50.448059082],"type":"Point"}
}