{
  "type": "Feature",
  "properties": {
    "addr:full":"Bemelstraat 159 Sint-pieters-woluwe/woluwe-saint-pierre Bruxelles-Capitale 1150",
    "addr:housenumber":"159",
    "addr:postcode":"1150",
    "addr:street":"Bemelstraat;/",
    "iso:country":"BE",
    "sg:address":"Bemelstraat 159",
    "sg:city":"Sint-pieters-woluwe/woluwe-saint-pierre",
    "sg:orig_category":"Kapsalons",
    "sg:phone":"+32 2 771 07 73",
    "sg:postcode":"1150",
    "sg:province":"Bruxelles-Capitale",
    "wof:name":"Willy (coiffure)",
    "wof:placetype":"venue"
},
  "geometry": {"coordinates":[4.4143548012,50.8306999207],"type":"Point"}
}