{
  "type": "Feature",
  "properties": {
    "addr:full":"Astridlaan 1 Overpelt Limburg 3900",
    "addr:housenumber":"1",
    "addr:postcode":"3900",
    "addr:street":"Astridlaan",
    "iso:country":"BE",
    "sg:address":"Astridlaan 1",
    "sg:city":"Overpelt",
    "sg:classifiers":[
        {
            "category":"Professional",
            "subcategory":"Art Services",
            "type":"Services"
        }
    ],
    "sg:phone":"+32 11 80 18 79",
    "sg:postcode":"3900",
    "sg:province":"Limburg",
    "sg:tags":[
        "photographer"
    ],
    "wof:name":"Schutters P",
    "wof:placetype":"venue"
},
  "geometry": {"coordinates":[5.4176101685,51.2091140747],"type":"Point"}
}