{
  "type": "Feature",
  "properties": {
    "iso:country":"BE",
    "sg:address":"Rue Rogier 7",
    "sg:city":"Chimay",
    "sg:classifiers":[
        {
            "category":"Shopping",
            "subcategory":"Jewelry",
            "type":"Retail Goods"
        }
    ],
    "sg:phone":"+32 60 21 20 82",
    "sg:postcode":"6460",
    "sg:province":"Hainaut",
    "sg:tags":[
        "jeweller",
        "-"
    ],
    "wof:name":"Anastasia",
    "wof:placetype":"venue"
},
  "geometry": {"coordinates":[4.3167390823,50.0495109558],"type":"Point"}
}