{
  "type": "Feature",
  "properties": {
    "iso:country":"BE",
    "sg:address":"Eendrachtstraat 25",
    "sg:city":"Elsene/ixelles",
    "sg:orig_category":"Boekhouders",
    "sg:phone":"+32 2 513 16 60",
    "sg:postcode":"1050",
    "sg:province":"Bruxelles-Capitale",
    "wof:name":"Fran\u00c7oise Lebrun",
    "wof:placetype":"venue"
},
  "geometry": {"coordinates":[4.3610949516,50.8334922791],"type":"Point"}
}