{
  "type": "Feature",
  "properties": {
    "iso:country":"BE",
    "sg:address":"Avenue Gisseleire Vers\u00c9 20",
    "sg:city":"Sint-agatha-berchem/berchem-sainte-agathe",
    "sg:orig_category":"Notaires",
    "sg:phone":"+32 2 465 67 89",
    "sg:postcode":"1082",
    "sg:province":"Bruxelles-Capitale",
    "wof:name":"J. Verelst/j.p. Verelst",
    "wof:placetype":"venue"
},
  "geometry": {"coordinates":[4.3009867668,50.8613052368],"type":"Point"}
}