{
  "type": "Feature",
  "properties": {
    "addr:full":"Lakense Laan 10 Jette/jette Bruxelles-Capitale 1090",
    "addr:housenumber":"10",
    "addr:postcode":"1090",
    "addr:street":"Laan",
    "iso:country":"BE",
    "sg:address":"Lakense Laan 10",
    "sg:city":"Jette/jette",
    "sg:orig_category":"Dameskledingzaken",
    "sg:phone":"+32 2 428 20 75",
    "sg:postcode":"1090",
    "sg:province":"Bruxelles-Capitale",
    "wof:name":"Maison Actu-elle",
    "wof:placetype":"venue"
},
  "geometry": {"coordinates":[4.3254961967,50.8715820312],"type":"Point"}
}