{
  "type": "Feature",
  "properties": {
    "addr:full":"Wolfgang D'urselstraat 2 Bornem (hingene) Antwerpen 2880",
    "addr:housenumber":"2",
    "addr:postcode":"2880",
    "addr:street":"Wolfgang D'Urselstraat",
    "iso:country":"BE",
    "sg:address":"Wolfgang D'urselstraat 2",
    "sg:city":"Bornem (hingene)",
    "sg:classifiers":[
        {
            "category":"Bars & Pubs",
            "type":"Food & Drink"
        }
    ],
    "sg:phone":"+32 3 899 13 63",
    "sg:postcode":"2880",
    "sg:province":"Antwerpen",
    "wof:name":"Zwaan (de)",
    "wof:placetype":"venue"
},
  "geometry": {"coordinates":[4.2690291405,51.1031761169],"type":"Point"}
}