{
  "type": "Feature",
  "properties": {
    "iso:country":"BE",
    "sg:address":"Parklaan 4",
    "sg:city":"Hove",
    "sg:classifiers":[
        {
            "category":"Real Estate",
            "subcategory":"Architect",
            "type":"Services"
        }
    ],
    "sg:phone":"+32 3 288 65 58",
    "sg:postcode":"2540",
    "sg:province":"Antwerpen",
    "wof:name":"Lernout J",
    "wof:placetype":"venue"
},
  "geometry": {"coordinates":[4.4731550217,51.1470069885],"type":"Point"}
}