{
  "type": "Feature",
  "properties": {
    "addr:full":"Eeckhoutstraat 2 Gavere Oost-Vlaanderen 9890",
    "addr:housenumber":"2",
    "addr:postcode":"9890",
    "addr:street":"Eeckhoutstraat",
    "iso:country":"BE",
    "sg:address":"Eeckhoutstraat 2",
    "sg:city":"Gavere",
    "sg:orig_category":"M\u00e9decins and sp\u00e9cialistes",
    "sg:phone":"+32 9 384 36 20",
    "sg:postcode":"9890",
    "sg:province":"Oost-Vlaanderen",
    "wof:name":"G. Mahy",
    "wof:placetype":"venue"
},
  "geometry": {"coordinates":[3.6707000732,50.9309692383],"type":"Point"}
}