{
  "type": "Feature",
  "properties": {
    "addr:full":"Leopoldstraat 1 Merksplas Antwerpen 2330",
    "addr:housenumber":"1",
    "addr:postcode":"2330",
    "addr:street":"Leopoldstraat",
    "iso:country":"BE",
    "sg:address":"Leopoldstraat 1",
    "sg:city":"Merksplas",
    "sg:classifiers":[
        {
            "category":"Cafe",
            "type":"Food & Drink"
        }
    ],
    "sg:phone":"+32 14 55 28 72",
    "sg:postcode":"2330",
    "sg:province":"Antwerpen",
    "sg:tags":[
        "snack-bars"
    ],
    "wof:name":"Frietketel",
    "wof:placetype":"venue"
},
  "geometry": {"coordinates":[4.8638210297,51.3579292297],"type":"Point"}
}