{
  "type": "Feature",
  "properties": {
    "addr:full":"Heerweg-noord 29 Gent Oost-Vlaanderen 9052",
    "addr:housenumber":"29",
    "addr:postcode":"9052",
    "addr:street":"Heerweg-Noord;Oost-Vlaanderen",
    "iso:country":"BE",
    "sg:address":"Heerweg-noord 29",
    "sg:city":"Gent",
    "sg:orig_category":"Slagers",
    "sg:phone":"+32 9 222 47 92",
    "sg:postcode":"9052",
    "sg:province":"Oost-Vlaanderen",
    "wof:name":"Meerschaut Chris",
    "wof:placetype":"venue"
},
  "geometry": {"coordinates":[3.7080481052,51.0573768616],"type":"Point"}
}