{
  "type": "Feature",
  "properties": {
    "addr:full":"Solwaster 118bb Jalhay Li\u00e8ge 4845",
    "addr:housenumber":"118bb",
    "addr:postcode":"4845",
    "addr:street":"Solwaster",
    "iso:country":"BE",
    "sg:address":"Solwaster 118bb",
    "sg:city":"Jalhay",
    "sg:orig_category":"V\u00e9hicules automobiles",
    "sg:phone":"+32 87 47 47 88",
    "sg:postcode":"4845",
    "sg:province":"Li\u00e8ge",
    "wof:name":"Garage Taton",
    "wof:placetype":"venue"
},
  "geometry": {"coordinates":[5.9650998116,50.5235290527],"type":"Point"}
}