{
  "type": "Feature",
  "properties": {
    "iso:country":"BE",
    "sg:address":"Rerum Novarumlei 4",
    "sg:city":"Brasschaat",
    "sg:orig_category":"Schoonheidssalons",
    "sg:phone":"+32 3 653 30 11",
    "sg:postcode":"2930",
    "sg:province":"Antwerpen",
    "wof:name":"Studio Little Eagle",
    "wof:placetype":"venue"
},
  "geometry": {"coordinates":[4.504805088,51.3044281006],"type":"Point"}
}