{
  "type": "Feature",
  "properties": {
    "addr:full":"Veldstraat 95a Oostrozebeke West-Vlaanderen 8780",
    "addr:housenumber":"95a",
    "addr:postcode":"8780",
    "addr:street":"Veldstraat",
    "iso:country":"BE",
    "sg:address":"Veldstraat 95a",
    "sg:city":"Oostrozebeke",
    "sg:orig_category":"Centres de relaxation and bien-\u00eatre. M\u00e9decines alternatives. Instituts de beaut\u00e9",
    "sg:phone":"+32 56 66 47 60",
    "sg:postcode":"8780",
    "sg:province":"West-Vlaanderen",
    "wof:name":"Instituut Arves",
    "wof:placetype":"venue"
},
  "geometry": {"coordinates":[3.3471739292,50.9227981567],"type":"Point"}
}