{
  "type": "Feature",
  "properties": {
    "addr:full":"Chemin Des Guin\u00c9es 6 Soignies Hainaut 7063",
    "addr:housenumber":"6",
    "addr:postcode":"7063",
    "addr:street":"Chemin Des Guine\u0301Es",
    "iso:country":"BE",
    "sg:address":"Chemin Des Guin\u00c9es 6",
    "sg:city":"Soignies",
    "sg:orig_category":"G\u00e9om\u00e8tres",
    "sg:phone":"+32 67 33 39 90",
    "sg:postcode":"7063",
    "sg:province":"Hainaut",
    "wof:name":"Henri Deladriere",
    "wof:placetype":"venue"
},
  "geometry": {"coordinates":[3.9769420624,50.5565605164],"type":"Point"}
}