{
  "type": "Feature",
  "properties": {
    "iso:country":"BE",
    "sg:address":"Pol De Montstraat 11",
    "sg:city":"Ternat (wambeek)",
    "sg:classifiers":[
        {
            "category":"Bars & Pubs",
            "type":"Food & Drink"
        }
    ],
    "sg:phone":"+32 2 581 02 11",
    "sg:postcode":"1741",
    "sg:province":"Vlaams-Brabant",
    "wof:name":"Pol De Mont",
    "wof:placetype":"venue"
},
  "geometry": {"coordinates":[4.1619181633,50.8522567749],"type":"Point"}
}