{
  "type": "Feature",
  "properties": {
    "addr:full":"Rue De La Station 116 Fleurus Hainaut 6220",
    "addr:housenumber":"116",
    "addr:postcode":"6220",
    "addr:street":"Rue De La Station",
    "iso:country":"BE",
    "sg:address":"Rue De La Station 116",
    "sg:city":"Fleurus",
    "sg:orig_category":"Cafetarias and selfservice restaurants",
    "sg:phone":"+32 71 81 18 66",
    "sg:postcode":"6220",
    "sg:province":"Hainaut",
    "wof:name":"Lido (le)",
    "wof:placetype":"venue"
},
  "geometry": {"coordinates":[4.5459361076,50.4835128784],"type":"Point"}
}