{
  "type": "Feature",
  "properties": {
    "addr:full":"Bd Du Textile 2 Mouscron Hainaut 7700",
    "addr:housenumber":"2",
    "addr:postcode":"7700",
    "addr:street":"Bd Du Textile",
    "iso:country":"BE",
    "sg:address":"Bd Du Textile 2",
    "sg:city":"Mouscron",
    "sg:classifiers":[
        {
            "category":"Manufacturing",
            "subcategory":"Chemicals & Compounds",
            "type":"Manufacturing & Wholesale Goods"
        }
    ],
    "sg:phone":"+32 56 34 25 16",
    "sg:postcode":"7700",
    "sg:province":"Hainaut",
    "sg:tags":[
        "pharmaceutical",
        "chemistry"
    ],
    "wof:name":"Brenntag Nv",
    "wof:placetype":"venue"
},
  "geometry": {"coordinates":[3.2469499111,50.7523117065],"type":"Point"}
}