{
  "type": "Feature",
  "properties": {
    "iso:country":"BE",
    "sg:address":"Claude De Clerckstraat 18",
    "sg:city":"Ieper",
    "sg:classifiers":[
        {
            "category":"Banks & Credit Unions",
            "subcategory":"Investment Brokerage",
            "type":"Services"
        }
    ],
    "sg:phone":"+32 57 21 81 81",
    "sg:postcode":"8900",
    "sg:province":"West-Vlaanderen",
    "sg:tags":[
        "diver",
        "aux",
        "animation",
        "entreprises",
        "diverses"
    ],
    "wof:name":"Koen Bossuyt",
    "wof:placetype":"venue"
},
  "geometry": {"coordinates":[2.8690519333,50.852771759],"type":"Point"}
}