{
  "type": "Feature",
  "properties": {
    "addr:full":"Botermarkt 2 Hasselt Limburg 3500",
    "addr:housenumber":"2",
    "addr:postcode":"3500",
    "addr:street":"Botermarkt",
    "iso:country":"BE",
    "sg:address":"Botermarkt 2",
    "sg:city":"Hasselt",
    "sg:classifiers":[
        {
            "category":"Shopping",
            "subcategory":"Clothing, Apparel, & Fashions",
            "type":"Retail Goods"
        }
    ],
    "sg:phone":"+32 11 22 71 15",
    "sg:postcode":"3500",
    "sg:province":"Limburg",
    "sg:tags":[
        "underwear",
        "lingerie",
        "-"
    ],
    "wof:name":"Maldoy",
    "wof:placetype":"venue"
},
  "geometry": {"coordinates":[5.337677002,50.9307098389],"type":"Point"}
}