{
  "type": "Feature",
  "properties": {
    "addr:full":"Kliniekstraat 12 Gent (gentbrugge) Oost-Vlaanderen 9050",
    "addr:housenumber":"12",
    "addr:postcode":"9050",
    "addr:street":"Kliniekstraat",
    "iso:country":"BE",
    "sg:address":"Kliniekstraat 12",
    "sg:city":"Gent (gentbrugge)",
    "sg:classifiers":[
        {
            "category":"Bakery",
            "type":"Food & Drink"
        }
    ],
    "sg:phone":"+32 9 211 10 68",
    "sg:postcode":"9050",
    "sg:province":"Oost-Vlaanderen",
    "sg:tags":[
        "confectioner",
        "baker"
    ],
    "wof:name":"De Baets",
    "wof:placetype":"venue"
},
  "geometry": {"coordinates":[3.755480051,51.0434303284],"type":"Point"}
}