{
  "type": "Feature",
  "properties": {
    "addr:full":"Turnhoutsebaan 310 Schilde Antwerpen 2970",
    "addr:housenumber":"310",
    "addr:postcode":"2970",
    "addr:street":"Turnhoutsebaan",
    "iso:country":"BE",
    "sg:address":"Turnhoutsebaan 310",
    "sg:city":"Schilde",
    "sg:classifiers":[
        {
            "category":"Restaurant",
            "type":"Food & Drink"
        }
    ],
    "sg:phone":"+32 3 385 33 72",
    "sg:postcode":"2970",
    "sg:province":"Antwerpen",
    "wof:name":"Parelhof",
    "wof:placetype":"venue"
},
  "geometry": {"coordinates":[4.5842108727,51.2410392761],"type":"Point"}
}