{
  "type": "Feature",
  "properties": {
    "iso:country":"BE",
    "sg:address":"Rue Des Fran\u00e7ais 58",
    "sg:city":"Aiseau-presles (roselies)",
    "sg:classifiers":[
        {
            "category":"Personal",
            "subcategory":"Beauty Salon",
            "type":"Services"
        }
    ],
    "sg:phone":"+32 71 76 02 52",
    "sg:postcode":"6250",
    "sg:province":"Hainaut",
    "sg:tags":[
        "lady",
        "-",
        "hairdressing"
    ],
    "wof:name":"Myriam",
    "wof:placetype":"venue"
},
  "geometry": {"coordinates":[4.5760707855,50.4269180298],"type":"Point"}
}