{
  "type": "Feature",
  "properties": {
    "iso:country":"BE",
    "sg:address":"Vollezelestraat 6",
    "sg:city":"Galmaarden",
    "sg:orig_category":"M\u00e9decins and sp\u00e9cialistes",
    "sg:phone":"+32 54 58 07 77",
    "sg:postcode":"1570",
    "sg:province":"Vlaams-Brabant",
    "wof:name":"Guy Niels",
    "wof:placetype":"venue"
},
  "geometry": {"coordinates":[4.0136108398,50.7462844849],"type":"Point"}
}