{
  "type": "Feature",
  "properties": {
    "addr:full":"Ieperstraat 222 Staden West-Vlaanderen 8840",
    "addr:housenumber":"222",
    "addr:postcode":"8840",
    "addr:street":"Ieperstraat",
    "iso:country":"BE",
    "sg:address":"Ieperstraat 222",
    "sg:city":"Staden",
    "sg:orig_category":"Installation \u00e9lectrique r\u00e9sidentielle",
    "sg:phone":"+32 51 70 23 50",
    "sg:postcode":"8840",
    "sg:province":"West-Vlaanderen",
    "wof:name":"Martin Notable",
    "wof:placetype":"venue"
},
  "geometry": {"coordinates":[2.9869909286,50.9535713196],"type":"Point"}
}