{
  "type": "Feature",
  "properties": {
    "iso:country":"BE",
    "sg:address":"Bossuytlaan 17",
    "sg:city":"Brugge",
    "sg:orig_category":"Avocats and conseillers juridiques",
    "sg:phone":"+32 50 37 14 40",
    "sg:postcode":"8310",
    "sg:province":"West-Vlaanderen",
    "wof:name":"Els Seghers",
    "wof:placetype":"venue"
},
  "geometry": {"coordinates":[3.248431921,51.2012367249],"type":"Point"}
}