{
  "type": "Feature",
  "properties": {
    "iso:country":"BE",
    "sg:address":"Imperiastraat 8",
    "sg:city":"Zaventem",
    "sg:classifiers":[
        {
            "category":"Farming",
            "subcategory":"Livestock Farm",
            "type":"Manufacturing & Wholesale Goods"
        }
    ],
    "sg:phone":"+32 2 720 97 66",
    "sg:postcode":"1930",
    "sg:province":"Vlaams-Brabant",
    "sg:tags":[
        "breeding"
    ],
    "wof:name":"Fomeva Belgi\u00eb Nv",
    "wof:placetype":"venue"
},
  "geometry": {"coordinates":[4.4539341927,50.8796806335],"type":"Point"}
}