{
  "type": "Feature",
  "properties": {
    "addr:full":"Chauss\u00e9e De Nivelles 52 Manage Hainaut 7170",
    "addr:housenumber":"52",
    "addr:postcode":"7170",
    "addr:street":"Chausse\u0301E De Nivelles",
    "iso:country":"BE",
    "sg:address":"Chauss\u00e9e De Nivelles 52",
    "sg:city":"Manage",
    "sg:classifiers":[
        {
            "category":"Health Services",
            "subcategory":"Health Practitioner",
            "type":"Services"
        }
    ],
    "sg:phone":"+32 64 55 55 57",
    "sg:postcode":"7170",
    "sg:province":"Hainaut",
    "sg:tags":[
        "physiotherapist"
    ],
    "wof:name":"Van Trimpont Albert",
    "wof:placetype":"venue"
},
  "geometry": {"coordinates":[4.2451682091,50.4795951843],"type":"Point"}
}