{
  "type": "Feature",
  "properties": {
    "iso:country":"BE",
    "sg:address":"Brialmontlei 66",
    "sg:city":"Antwerpen",
    "sg:classifiers":[
        {
            "category":"Professional",
            "subcategory":"Computer Services",
            "type":"Services"
        }
    ],
    "sg:phone":"+32 3 230 19 25",
    "sg:postcode":"2018",
    "sg:province":"Antwerpen",
    "sg:tags":[
        "-",
        "processing",
        "data",
        "software"
    ],
    "wof:name":"Ortec Nv",
    "wof:placetype":"venue"
},
  "geometry": {"coordinates":[4.4220957756,51.2092704773],"type":"Point"}
}