{
  "type": "Feature",
  "properties": {
    "iso:country":"BE",
    "sg:address":"Mercelisstraat 74",
    "sg:city":"Brussel/bruxelles",
    "sg:orig_category":"Meubelzaken, woning- and keukeninrichting",
    "sg:phone":"+32 2 649 70 29",
    "sg:postcode":"1000",
    "sg:province":"Bruxelles-Capitale",
    "wof:name":"Ayrton Belgium",
    "wof:placetype":"venue"
},
  "geometry": {"coordinates":[4.3628191948,50.830039978],"type":"Point"}
}