{
  "type": "Feature",
  "properties": {
    "addr:full":"Lumenstraat 7 Vloesberg/flobecq Hainaut 7880",
    "addr:housenumber":"7",
    "addr:postcode":"7880",
    "addr:street":"Lumenstraat",
    "iso:country":"BE",
    "sg:address":"Lumenstraat 7",
    "sg:city":"Vloesberg/flobecq",
    "sg:orig_category":"Artsen and specialisten",
    "sg:phone":"+32 68 44 75 56",
    "sg:postcode":"7880",
    "sg:province":"Hainaut",
    "wof:name":"Francine Risselin",
    "wof:placetype":"venue"
},
  "geometry": {"coordinates":[3.7266190052,50.7651062012],"type":"Point"}
}