{
  "type": "Feature",
  "properties": {
    "iso:country":"BE",
    "sg:address":"Rue Modeste Cornil 15",
    "sg:city":"Charleroi",
    "sg:orig_category":"Geschenken and souvenirs Verlichting and huishoudartikelen",
    "sg:phone":"+32 71 37 06 10",
    "sg:postcode":"6041",
    "sg:province":"Hainaut",
    "wof:name":"Gadgetcard",
    "wof:placetype":"venue"
},
  "geometry": {"coordinates":[4.4314317703,50.4685935974],"type":"Point"}
}