{
  "type": "Feature",
  "properties": {
    "iso:country":"BE",
    "sg:address":"Leiestraat 111",
    "sg:city":"Kuurne",
    "sg:orig_category":"Installatie van houten of kunststof schrijnwerk",
    "sg:phone":"+32 56 71 89 02",
    "sg:postcode":"8520",
    "sg:province":"West-Vlaanderen",
    "wof:name":"R. & D.",
    "wof:placetype":"venue"
},
  "geometry": {"coordinates":[3.2880930901,50.8531303406],"type":"Point"}
}