{
  "type": "Feature",
  "properties": {
    "addr:full":"Chauss\u00c9e Brunehaut 291 Beloeil Hainaut 7972",
    "addr:housenumber":"291",
    "addr:postcode":"7972",
    "addr:street":"Chausse\u0301E Brunehaut",
    "iso:country":"BE",
    "sg:address":"Chauss\u00c9e Brunehaut 291",
    "sg:city":"Beloeil",
    "sg:orig_category":"Eleveurs de bovins",
    "sg:phone":"+32 69 68 98 38",
    "sg:postcode":"7972",
    "sg:province":"Hainaut",
    "wof:name":"Patrick Libbrecht",
    "wof:placetype":"venue"
},
  "geometry": {"coordinates":[3.6905479431,50.5450057983],"type":"Point"}
}