{
  "type": "Feature",
  "properties": {
    "iso:country":"BE",
    "sg:address":"Strobrugge 17b",
    "sg:city":"Maldegem",
    "sg:orig_category":"Tweedehandsgoederen",
    "sg:phone":"+32 50 71 59 45",
    "sg:postcode":"9990",
    "sg:province":"Oost-Vlaanderen",
    "wof:name":"Roeland Borgonjon",
    "wof:placetype":"venue"
},
  "geometry": {"coordinates":[3.4466290474,51.236038208],"type":"Point"}
}