{
  "type": "Feature",
  "properties": {
    "addr:full":"Biezeweg 13 Wetteren Oost-Vlaanderen 9230",
    "addr:housenumber":"13",
    "addr:postcode":"9230",
    "addr:street":"Biezeweg",
    "iso:country":"BE",
    "sg:address":"Biezeweg 13",
    "sg:city":"Wetteren",
    "sg:orig_category":"Miscellaneous Products",
    "sg:phone":"+32 81 21 65 78",
    "sg:postcode":"9230",
    "sg:province":"Oost-Vlaanderen",
    "wof:name":"A 4 Services Sa",
    "wof:placetype":"venue"
},
  "geometry": {"coordinates":[4.8477449417,50.4748916626],"type":"Point"}
}