{
  "type": "Feature",
  "properties": {
    "addr:full":"Hoogstraat 60 Wichelen Oost-Vlaanderen 9260",
    "addr:housenumber":"60",
    "addr:postcode":"9260",
    "addr:street":"Hoogstraat",
    "iso:country":"BE",
    "sg:address":"Hoogstraat 60",
    "sg:city":"Wichelen",
    "sg:orig_category":"HUISBRANDOLIE",
    "sg:phone":"+32 9 369 04 76",
    "sg:postcode":"9260",
    "sg:province":"Oost-Vlaanderen",
    "wof:name":"Luc Lammens",
    "wof:placetype":"venue"
},
  "geometry": {"coordinates":[3.9318680763,51.011631012],"type":"Point"}
}