{
  "type": "Feature",
  "properties": {
    "addr:full":"Rue Des Choraux 12 Tournai Hainaut 7500",
    "addr:housenumber":"12",
    "addr:postcode":"7500",
    "addr:street":"Rue Des Choraux",
    "iso:country":"BE",
    "sg:address":"Rue Des Choraux 12",
    "sg:city":"Tournai",
    "sg:orig_category":"Sportcentra Sportclubs Sportterreinen and installaties behalve sportcentra",
    "sg:phone":"+32 69 22 40 92",
    "sg:postcode":"7500",
    "sg:province":"Hainaut",
    "wof:name":"Salle Sports Ecole Fr\u00c8res",
    "wof:placetype":"venue"
},
  "geometry": {"coordinates":[3.3871591091,50.6075553894],"type":"Point"}
}