{
  "type": "Feature",
  "properties": {
    "addr:full":"Rue Defacqz 131 Sint-gillis/saint-gilles Bruxelles-Capitale 1060",
    "addr:housenumber":"131",
    "addr:postcode":"1060",
    "addr:street":"Rue Defacqz",
    "iso:country":"BE",
    "sg:address":"Rue Defacqz 131",
    "sg:city":"Sint-gillis/saint-gilles",
    "sg:orig_category":"Location de voitures",
    "sg:phone":"+32 2 538 33 21",
    "sg:postcode":"1060",
    "sg:province":"Bruxelles-Capitale",
    "wof:name":"Luxauto",
    "wof:placetype":"venue"
},
  "geometry": {"coordinates":[4.3553919792,50.8260307312],"type":"Point"}
}