{
  "type": "Feature",
  "properties": {
    "iso:country":"BE",
    "sg:address":"Kerkstraat 44",
    "sg:city":"Spiere-helkijn/espierres-helchin",
    "sg:classifiers":[
        {
            "category":"Cafe",
            "type":"Food & Drink"
        }
    ],
    "sg:phone":"+32 56 45 53 19",
    "sg:postcode":"8587",
    "sg:province":"West-Vlaanderen",
    "sg:tags":[
        "caf\u00e9s"
    ],
    "wof:name":"Nadine Denhaerynck",
    "wof:placetype":"venue"
},
  "geometry": {"coordinates":[3.3827440739,50.7302589417],"type":"Point"}
}