{
  "type": "Feature",
  "properties": {
    "addr:full":"Place Emile Vandervelde 32 Charleroi (montignies-sur-sambre) Hainaut 6061",
    "addr:housenumber":"32",
    "addr:postcode":"6061",
    "addr:street":"Place Emile Vandervelde",
    "iso:country":"BE",
    "sg:address":"Place Emile Vandervelde 32",
    "sg:city":"Charleroi (montignies-sur-sambre)",
    "sg:classifiers":[
        {
            "category":"Shopping",
            "subcategory":"Crafts & Fabrics",
            "type":"Retail Goods"
        }
    ],
    "sg:phone":"+32 71 41 96 03",
    "sg:postcode":"6061",
    "sg:province":"Hainaut",
    "sg:tags":[
        "plant",
        "flower",
        "artificial"
    ],
    "wof:name":"A. Bertinchamps",
    "wof:placetype":"venue"
},
  "geometry": {"coordinates":[4.4610748291,50.4148864746],"type":"Point"}
}