{
  "type": "Feature",
  "properties": {
    "addr:full":"Eekhoornstraat 24 Kortenberg Vlaams-Brabant 3070",
    "addr:housenumber":"24",
    "addr:postcode":"3070",
    "addr:street":"Eekhoornstraat;Vlaams-Brabant",
    "iso:country":"BE",
    "sg:address":"Eekhoornstraat 24",
    "sg:city":"Kortenberg",
    "sg:classifiers":[
        {
            "category":"Banks & Credit Unions",
            "subcategory":"Investment Brokerage",
            "type":"Services"
        }
    ],
    "sg:phone":"+32 2 759 47 78",
    "sg:postcode":"3070",
    "sg:province":"Vlaams-Brabant",
    "sg:tags":[
        "repair",
        "-",
        "installation",
        "sanitary",
        "article"
    ],
    "wof:name":"Bilterest M",
    "wof:placetype":"venue"
},
  "geometry": {"coordinates":[4.5376219749,50.8798141479],"type":"Point"}
}