{
  "type": "Feature",
  "properties": {
    "iso:country":"BE",
    "sg:address":"Rue Roosevelt 18",
    "sg:city":"Fl\u00e9ron (roms\u00e9e)",
    "sg:classifiers":[
        {
            "category":"Professional",
            "subcategory":"Accounting & Tax Preparation",
            "type":"Services"
        }
    ],
    "sg:phone":"+32 4 355 15 95",
    "sg:postcode":"4624",
    "sg:province":"Li\u00e8ge",
    "sg:tags":[
        "accountant"
    ],
    "wof:name":"Secoges Sprl",
    "wof:placetype":"venue"
},
  "geometry": {"coordinates":[5.6635279655,50.6105194092],"type":"Point"}
}