{
  "type": "Feature",
  "properties": {
    "addr:full":"Avenue Des Bouvreuils 6bb Wavre Brabant Wallon 1301",
    "addr:housenumber":"1301",
    "addr:postcode":"6bb",
    "addr:street":"Avenue Des Bouvreuils",
    "iso:country":"BE",
    "sg:address":"Avenue Des Bouvreuils 6bb",
    "sg:city":"Wavre",
    "sg:orig_category":"Artsen and specialisten",
    "sg:phone":"+32 10 41 48 26",
    "sg:postcode":"1301",
    "sg:province":"Brabant Wallon",
    "wof:name":"Vincent Malvaux",
    "wof:placetype":"venue"
},
  "geometry": {"coordinates":[4.5705327988,50.7222900391],"type":"Point"}
}