{
  "type": "Feature",
  "properties": {
    "addr:full":"Avenue D'auderghem 277 Bruxelles (etterbeek) Bruxelles-Capitale 1040",
    "addr:housenumber":"277",
    "addr:postcode":"1040",
    "addr:street":"Avenue D'Auderghem",
    "iso:country":"BE",
    "sg:address":"Avenue D'auderghem 277",
    "sg:city":"Bruxelles (etterbeek)",
    "sg:classifiers":[
        {
            "category":"Building & Trades",
            "subcategory":"Plumbing",
            "type":"Services"
        }
    ],
    "sg:phone":"+32 2 743 03 80",
    "sg:postcode":"1040",
    "sg:province":"Bruxelles-Capitale",
    "sg:tags":[
        "relocation"
    ],
    "wof:name":"Intercontinental Brussels Properties",
    "wof:placetype":"venue"
},
  "geometry": {"coordinates":[4.3891367912,50.8321037292],"type":"Point"}
}