{
  "type": "Feature",
  "properties": {
    "addr:full":"Rue Charles Quint 29 Brussel/bruxelles Bruxelles-Capitale 1000",
    "addr:housenumber":"29",
    "addr:postcode":"1000",
    "addr:street":"Rue Charles Quint;/",
    "iso:country":"BE",
    "sg:address":"Rue Charles Quint 29",
    "sg:city":"Brussel/bruxelles",
    "sg:orig_category":"Enseignement maternel and primaire",
    "sg:phone":"+32 2 736 11 99",
    "sg:postcode":"1000",
    "sg:province":"Bruxelles-Capitale",
    "wof:name":"Ecole Fond. Communale",
    "wof:placetype":"venue"
},
  "geometry": {"coordinates":[4.3826961517,50.8500213623],"type":"Point"}
}