{
  "type": "Feature",
  "properties": {
    "iso:country":"BE",
    "sg:address":"Vital Decosterstraat 81b2",
    "sg:city":"Leuven",
    "sg:orig_category":"Deurwaarders",
    "sg:phone":"+32 16 23 83 30",
    "sg:postcode":"3000",
    "sg:province":"Vlaams-Brabant",
    "wof:name":"Johan Van Deun",
    "wof:placetype":"venue"
},
  "geometry": {"coordinates":[4.7022438049,50.8824996948],"type":"Point"}
}