{
  "type": "Feature",
  "properties": {
    "iso:country":"BE",
    "sg:address":"Smalle Weg Z/n",
    "sg:city":"Hoevenen",
    "sg:classifiers":[
        {
            "category":"Food & Beverages",
            "subcategory":"Meat & Fish",
            "type":"Retail Goods"
        }
    ],
    "sg:phone":"+32 3 664 69 05",
    "sg:postcode":"2940",
    "sg:province":"Antwerpen",
    "sg:tags":[
        "oil",
        "fat",
        "animal"
    ],
    "wof:name":"V.e.d. B.v.b.a.",
    "wof:placetype":"venue"
},
  "geometry": {"coordinates":[4.3887329102,51.3117828369],"type":"Point"}
}