{
  "type": "Feature",
  "properties": {
    "iso:country":"BE",
    "sg:address":"Place Emile Vinck 3-2",
    "sg:city":"Fl\u00e9malle",
    "sg:classifiers":[
        {
            "category":"Health Services",
            "subcategory":"Health Practitioner",
            "type":"Services"
        }
    ],
    "sg:phone":"+32 4 275 52 43",
    "sg:postcode":"4400",
    "sg:province":"Li\u00e8ge",
    "sg:tags":[
        "physiotherapist"
    ],
    "wof:name":"Hupperts Michele",
    "wof:placetype":"venue"
},
  "geometry": {"coordinates":[5.4455399513,50.6015701294],"type":"Point"}
}