{
  "type": "Feature",
  "properties": {
    "iso:country":"BE",
    "sg:address":"Molenkouterslag 19",
    "sg:city":"Nevele",
    "sg:classifiers":[
        {
            "category":"Insurance",
            "subcategory":"Life Insurance",
            "type":"Services"
        }
    ],
    "sg:phone":"+32 9 371 81 50",
    "sg:postcode":"9850",
    "sg:province":"Oost-Vlaanderen",
    "sg:tags":[
        "assurance"
    ],
    "wof:name":"Ansemma Insur.& Expert.",
    "wof:placetype":"venue"
},
  "geometry": {"coordinates":[3.5701019764,51.0793190002],"type":"Point"}
}