{
  "type": "Feature",
  "properties": {
    "addr:full":"Turnhoutseweg 69 Beerse Antwerpen 2340",
    "addr:housenumber":"69",
    "addr:postcode":"2340",
    "addr:street":"Turnhoutseweg",
    "iso:country":"BE",
    "sg:address":"Turnhoutseweg 69",
    "sg:city":"Beerse",
    "sg:classifiers":[
        {
            "category":"Autos & Motor Vehicles",
            "subcategory":"Motorcycle Sales",
            "type":"Retail Goods"
        }
    ],
    "sg:phone":"+32 14 61 52 52",
    "sg:postcode":"2340",
    "sg:province":"Antwerpen",
    "sg:tags":[
        "automobile",
        "brake",
        "-",
        "truck"
    ],
    "wof:name":"Auto-service U.s.t. Nv",
    "wof:placetype":"venue"
},
  "geometry": {"coordinates":[4.8660769463,51.3118553162],"type":"Point"}
}