{
  "type": "Feature",
  "properties": {
    "addr:full":"Dr Charles Leemansstraat 28 Sint-agatha-berchem/berchem-sainte-agathe Bruxelles-Capitale 1082",
    "addr:housenumber":"28",
    "addr:postcode":"1082",
    "addr:street":"Leemansstraat",
    "iso:country":"BE",
    "sg:address":"Dr Charles Leemansstraat 28",
    "sg:city":"Sint-agatha-berchem/berchem-sainte-agathe",
    "sg:orig_category":"Artsen and specialisten",
    "sg:phone":"+32 2 465 55 66",
    "sg:postcode":"1082",
    "sg:province":"Bruxelles-Capitale",
    "wof:name":"Yves De Vroey",
    "wof:placetype":"venue"
},
  "geometry": {"coordinates":[4.2947459221,50.8616828918],"type":"Point"}
}