{
  "type": "Feature",
  "properties": {
    "iso:country":"BE",
    "sg:address":"Hendrik Consciencestraat 16-18",
    "sg:city":"Sint-niklaas",
    "sg:classifiers":[
        {
            "category":"Building & Trades",
            "subcategory":"Equipment Rental",
            "type":"Services"
        }
    ],
    "sg:postcode":"9100",
    "sg:province":"Oost-Vlaanderen",
    "sg:tags":[
        "tableware",
        "-"
    ],
    "wof:name":"Goethals-baert",
    "wof:placetype":"venue"
},
  "geometry": {"coordinates":[4.1283750534,51.1669654846],"type":"Point"}
}