{
  "type": "Feature",
  "properties": {
    "addr:full":"Hoogstraat 18 Gistel West-Vlaanderen 8470",
    "addr:housenumber":"18",
    "addr:postcode":"8470",
    "addr:street":"Hoogstraat",
    "iso:country":"BE",
    "sg:address":"Hoogstraat 18",
    "sg:city":"Gistel",
    "sg:classifiers":[
        {
            "category":"Cafe",
            "type":"Food & Drink"
        }
    ],
    "sg:phone":"+32 59 27 45 65",
    "sg:postcode":"8470",
    "sg:province":"West-Vlaanderen",
    "sg:tags":[
        "snack-bars"
    ],
    "wof:name":"'t Kruimeltje",
    "wof:placetype":"venue"
},
  "geometry": {"coordinates":[2.9656128883,51.1564292908],"type":"Point"}
}