{
  "type": "Feature",
  "properties": {
    "iso:country":"BE",
    "sg:address":"Stalenstraat 88",
    "sg:city":"Genk (waterschei)",
    "sg:classifiers":[
        {
            "category":"Cafe",
            "type":"Food & Drink"
        }
    ],
    "sg:phone":"+32 89 84 13 93",
    "sg:postcode":"3600",
    "sg:province":"Limburg",
    "sg:tags":[
        "snack-bars"
    ],
    "wof:name":"Orient Iii",
    "wof:placetype":"venue"
},
  "geometry": {"coordinates":[5.5174012184,50.9930877686],"type":"Point"}
}