{
  "type": "Feature",
  "properties": {
    "iso:country":"BE",
    "sg:address":"Frans Beirenslaan 224",
    "sg:city":"Borsbeek",
    "sg:classifiers":[
        {
            "category":"Arena",
            "subcategory":"Sports Club",
            "type":"Entertainment"
        }
    ],
    "sg:phone":"+32 3 322 21 29",
    "sg:postcode":"2150",
    "sg:province":"Antwerpen",
    "wof:name":"Skydive Malle",
    "wof:placetype":"venue"
},
  "geometry": {"coordinates":[4.484005928,51.2003555298],"type":"Point"}
}