{
  "type": "Feature",
  "properties": {
    "iso:country":"BE",
    "sg:address":"Rue Sainte-barbe 49 Box 6",
    "sg:city":"Nivelles",
    "sg:classifiers":[
        {
            "category":"Arts & Performance",
            "subcategory":"Music",
            "type":"Entertainment"
        }
    ],
    "sg:phone":"+32 67 21 26 37",
    "sg:postcode":"1400",
    "sg:province":"Brabant Wallon",
    "sg:tags":[
        "disc-jockeys"
    ],
    "wof:name":"Sonoca",
    "wof:placetype":"venue"
},
  "geometry": {"coordinates":[4.3140149117,50.5933151245],"type":"Point"}
}