{
  "type": "Feature",
  "properties": {
    "addr:full":"Meerstraat 148 Hamme Oost-Vlaanderen 9220",
    "addr:housenumber":"148",
    "addr:postcode":"9220",
    "addr:street":"Meerstraat",
    "iso:country":"BE",
    "sg:address":"Meerstraat 148",
    "sg:city":"Hamme",
    "sg:orig_category":"Rundveehouders Varkenskwekers",
    "sg:phone":"+32 52 47 84 74",
    "sg:postcode":"9220",
    "sg:province":"Oost-Vlaanderen",
    "wof:name":"Georges Van Den Bossche",
    "wof:placetype":"venue"
},
  "geometry": {"coordinates":[4.1120638847,51.0738639832],"type":"Point"}
}