{
  "type": "Feature",
  "properties": {
    "iso:country":"BE",
    "sg:address":"Stokerijstraat 9",
    "sg:city":"Roeselare",
    "sg:classifiers":[
        {
            "category":"Education",
            "subcategory":"School",
            "type":"Public Place"
        }
    ],
    "sg:phone":"+32 51 20 04 87",
    "sg:postcode":"8800",
    "sg:province":"West-Vlaanderen",
    "sg:tags":[
        "secondary"
    ],
    "wof:name":"Bisschop Lyceum Grauwe Zusters",
    "wof:placetype":"venue"
},
  "geometry": {"coordinates":[3.1259219646,50.954826355],"type":"Point"}
}