{
  "type": "Feature",
  "properties": {
    "iso:country":"BE",
    "sg:address":"Rue Joseph Wauters 19",
    "sg:city":"Fleurus",
    "sg:orig_category":"Installatie van houten of kunststof schrijnwerk",
    "sg:phone":"+32 71 81 63 70",
    "sg:postcode":"6224",
    "sg:province":"Hainaut",
    "wof:name":"Willy Carpent",
    "wof:placetype":"venue"
},
  "geometry": {"coordinates":[4.5849947929,50.4642944336],"type":"Point"}
}