{
  "type": "Feature",
  "properties": {
    "iso:country":"BE",
    "sg:address":"A Catriestraat 20bb",
    "sg:city":"Gent",
    "sg:orig_category":"Kunststofrecipi\u00ebnten and -verpakkingen Fab",
    "sg:phone":"+32 9 226 01 65",
    "sg:postcode":"9031",
    "sg:province":"Oost-Vlaanderen",
    "wof:name":"Delafilm",
    "wof:placetype":"venue"
},
  "geometry": {"coordinates":[3.6630249023,51.0503692627],"type":"Point"}
}