{
  "type": "Feature",
  "properties": {
    "addr:full":"Heegstraat 48 Dessel Antwerpen 2480",
    "addr:housenumber":"48",
    "addr:postcode":"2480",
    "addr:street":"Heegstraat",
    "iso:country":"BE",
    "sg:address":"Heegstraat 48",
    "sg:city":"Dessel",
    "sg:orig_category":"Non-Classified Establishments",
    "sg:phone":"+32 14 37 06 00",
    "sg:postcode":"2480",
    "sg:province":"Antwerpen",
    "wof:name":"Jacobs Evenementen Service Bvba",
    "wof:placetype":"venue"
},
  "geometry": {"coordinates":[5.12003088,51.2459030151],"type":"Point"}
}