{
  "type": "Feature",
  "properties": {
    "addr:full":"Vlasmarkt 6 Gent Oost-Vlaanderen 9000",
    "addr:housenumber":"6",
    "addr:postcode":"9000",
    "addr:street":"Vlasmarkt;Oost-Vlaanderen",
    "iso:country":"BE",
    "sg:address":"Vlasmarkt 6",
    "sg:city":"Gent",
    "sg:classifiers":[
        {
            "category":"Bars & Pubs",
            "type":"Food & Drink"
        }
    ],
    "sg:phone":"+32 9 224 23 11",
    "sg:postcode":"9000",
    "sg:province":"Oost-Vlaanderen",
    "sg:tags":[
        "bars",
        "caf\u00e9s"
    ],
    "wof:name":"Charlatan",
    "wof:placetype":"venue"
},
  "geometry": {"coordinates":[3.728358984,51.0560264587],"type":"Point"}
}