{
  "type": "Feature",
  "properties": {
    "addr:full":"Grote Markt 26 Sint-niklaas Oost-Vlaanderen 9100",
    "addr:housenumber":"26",
    "addr:postcode":"9100",
    "addr:street":"Grote Markt",
    "iso:country":"BE",
    "sg:address":"Grote Markt 26",
    "sg:city":"Sint-niklaas",
    "sg:orig_category":"Editeurs de journaux. Editeurs de revues and p\u00e9riodiques",
    "sg:phone":"+32 3 776 34 64",
    "sg:postcode":"9100",
    "sg:province":"Oost-Vlaanderen",
    "wof:name":"Kamer Handel & Nijverheid",
    "wof:placetype":"venue"
},
  "geometry": {"coordinates":[4.1403188705,51.163433075],"type":"Point"}
}