{
  "type": "Feature",
  "properties": {
    "addr:full":"Sint-janslaan 29 Kortrijk West-Vlaanderen 8500",
    "addr:housenumber":"29",
    "addr:postcode":"8500",
    "addr:street":"Sint-Janslaan",
    "iso:country":"BE",
    "sg:address":"Sint-janslaan 29",
    "sg:city":"Kortrijk",
    "sg:orig_category":"Quincailleries",
    "sg:phone":"+32 56 21 71 32",
    "sg:postcode":"8500",
    "sg:province":"West-Vlaanderen",
    "wof:name":"Hobby Center",
    "wof:placetype":"venue"
},
  "geometry": {"coordinates":[3.2713260651,50.8249130249],"type":"Point"}
}