{
  "type": "Feature",
  "properties": {
    "iso:country":"BE",
    "sg:address":"Mimosalaan 18",
    "sg:city":"Sint-pieters-woluwe/woluwe-saint-pierre",
    "sg:orig_category":"Artsen and specialisten",
    "sg:phone":"+32 2 734 47 18",
    "sg:postcode":"1150",
    "sg:province":"Bruxelles-Capitale",
    "wof:name":"J.l. Noel",
    "wof:placetype":"venue"
},
  "geometry": {"coordinates":[4.4077539444,50.8276824951],"type":"Point"}
}