{
  "type": "Feature",
  "properties": {
    "addr:full":"Brusselsesteenweg 753 Gent (gentbrugge) Oost-Vlaanderen 9050",
    "addr:housenumber":"753",
    "addr:postcode":"9050",
    "addr:street":"Brusselsesteenweg",
    "iso:country":"BE",
    "sg:address":"Brusselsesteenweg 753",
    "sg:city":"Gent (gentbrugge)",
    "sg:classifiers":[
        {
            "category":"Shopping",
            "subcategory":"Florist",
            "type":"Retail Goods"
        }
    ],
    "sg:phone":"+32 9 230 38 26",
    "sg:postcode":"9050",
    "sg:province":"Oost-Vlaanderen",
    "wof:name":"Jacques",
    "wof:placetype":"venue"
},
  "geometry": {"coordinates":[3.7685990334,51.0281219482],"type":"Point"}
}