{
  "type": "Feature",
  "properties": {
    "iso:country":"BE",
    "sg:address":"Maalstedestraat 24",
    "sg:city":"Ieper",
    "sg:orig_category":"Bloemen and planten",
    "sg:phone":"+32 57 20 71 94",
    "sg:postcode":"8902",
    "sg:province":"West-Vlaanderen",
    "wof:name":"Rosa",
    "wof:placetype":"venue"
},
  "geometry": {"coordinates":[2.9219059944,50.8384170532],"type":"Point"}
}