{
  "type": "Feature",
  "properties": {
    "iso:country":"BE",
    "sg:address":"Torhoutsestraat 53",
    "sg:city":"Oostkamp (ruddervoorde)",
    "sg:orig_category":"Newspapers, magazines, periodicals - Distribution",
    "sg:phone":"+32 50 28 13 65",
    "sg:postcode":"8020",
    "sg:province":"West-Vlaanderen",
    "wof:name":"Kroniekske (het)",
    "wof:placetype":"venue"
},
  "geometry": {"coordinates":[3.2051529884,51.0929908752],"type":"Point"}
}