{
  "type": "Feature",
  "properties": {
    "iso:country":"BE",
    "sg:address":"Brusselstraat 266",
    "sg:city":"Dilbeek (groot - Bijgaarden)",
    "sg:classifiers":[
        {
            "category":"Autos & Motor Vehicles",
            "subcategory":"Boat Sales",
            "type":"Retail Goods"
        }
    ],
    "sg:phone":"+32 495 54 40 40",
    "sg:postcode":"1702",
    "sg:province":"Vlaams-Brabant",
    "sg:tags":[
        "balloon"
    ],
    "wof:name":"Deebis Bvba-pipo Balloons",
    "wof:placetype":"venue"
},
  "geometry": {"coordinates":[4.2621369362,50.871421814],"type":"Point"}
}