{
  "type": "Feature",
  "properties": {
    "iso:country":"BE",
    "sg:address":"Rue De Houtain 94",
    "sg:city":"Juprelle (fexhe-slins)",
    "sg:classifiers":[
        {
            "category":"Personal",
            "subcategory":"Beauty Salon",
            "type":"Services"
        }
    ],
    "sg:phone":"+32 4 286 45 85",
    "sg:postcode":"4458",
    "sg:province":"Li\u00e8ge",
    "wof:name":"Mireille Institut",
    "wof:placetype":"venue"
},
  "geometry": {"coordinates":[5.569712162,50.7215194702],"type":"Point"}
}