{
  "type": "Feature",
  "properties": {
    "addr:full":"Rue Du Bas-w\u00e9richet 45 Jemeppe-sur-sambre Namur 5190",
    "addr:housenumber":"45",
    "addr:postcode":"5190",
    "addr:street":"Rue Du Bas-We\u0301Richet",
    "iso:country":"BE",
    "sg:address":"Rue Du Bas-w\u00e9richet 45",
    "sg:city":"Jemeppe-sur-sambre",
    "sg:classifiers":[
        {
            "category":"Landmark",
            "subcategory":"Memorial",
            "type":"Public Place"
        }
    ],
    "sg:phone":"+32 71 78 65 20",
    "sg:postcode":"5190",
    "sg:province":"Namur",
    "sg:tags":[
        "-",
        "monument"
    ],
    "wof:name":"Chantier Devilez Denis",
    "wof:placetype":"venue"
},
  "geometry": {"coordinates":[4.6611509323,50.4677314758],"type":"Point"}
}