{
  "type": "Feature",
  "properties": {
    "iso:country":"BE",
    "sg:address":"Rue Du Ch\u00canois 75",
    "sg:city":"Charleroi",
    "sg:orig_category":"Schoonmaakbedrijven and ongediertebestrijding",
    "sg:phone":"+32 71 32 46 67",
    "sg:postcode":"6030",
    "sg:province":"Hainaut",
    "wof:name":"Bati-clean",
    "wof:placetype":"venue"
},
  "geometry": {"coordinates":[4.3949289322,50.4065132141],"type":"Point"}
}