{
  "type": "Feature",
  "properties": {
    "addr:full":"Rue Petit Plain 3 Aywaille Li\u00e8ge 4920",
    "addr:housenumber":"3",
    "addr:postcode":"4920",
    "addr:street":"Rue Petit Plain",
    "iso:country":"BE",
    "sg:address":"Rue Petit Plain 3",
    "sg:city":"Aywaille",
    "sg:orig_category":"Schoonheidssalons",
    "sg:phone":"+32 4 384 61 23",
    "sg:postcode":"4920",
    "sg:province":"Li\u00e8ge",
    "wof:name":"Nathalie Deckers",
    "wof:placetype":"venue"
},
  "geometry": {"coordinates":[5.6782069206,50.4738540649],"type":"Point"}
}