{
  "type": "Feature",
  "properties": {
    "addr:full":"Koningin Astridlaan 31 Mechelen Antwerpen 2800",
    "addr:housenumber":"31",
    "addr:postcode":"2800",
    "addr:street":"Koningin Astridlaan",
    "iso:country":"BE",
    "sg:address":"Koningin Astridlaan 31",
    "sg:city":"Mechelen",
    "sg:classifiers":[
        {
            "category":"Shopping",
            "subcategory":"Bicycles & Sporting Goods",
            "type":"Retail Goods"
        }
    ],
    "sg:phone":"+32 15 28 48 88",
    "sg:postcode":"2800",
    "sg:province":"Antwerpen",
    "sg:tags":[
        "sport",
        "-"
    ],
    "wof:name":"Sport Socks Co",
    "wof:placetype":"venue"
},
  "geometry": {"coordinates":[4.4702582359,51.0265045166],"type":"Point"}
}