{
  "type": "Feature",
  "properties": {
    "iso:country":"BE",
    "sg:address":"Fortbaan 72c",
    "sg:city":"Wommelgem",
    "sg:classifiers":[
        {
            "category":"Home & Garden",
            "subcategory":"Building Materials",
            "type":"Retail Goods"
        }
    ],
    "sg:phone":"+32 3 320 80 80",
    "sg:postcode":"2160",
    "sg:province":"Antwerpen",
    "sg:tags":[
        "window"
    ],
    "wof:name":"Adr Construct Bvba",
    "wof:placetype":"venue"
},
  "geometry": {"coordinates":[4.498819828,51.2025413513],"type":"Point"}
}