{
  "type": "Feature",
  "properties": {
    "iso:country":"BE",
    "sg:address":"Rue Des Primev\u00c8res 2",
    "sg:city":"Binche",
    "sg:orig_category":"Enseignement maternel and primaire",
    "sg:phone":"+32 64 33 46 03",
    "sg:postcode":"7134",
    "sg:province":"Hainaut",
    "wof:name":"Ecole Fondamentale Libre",
    "wof:placetype":"venue"
},
  "geometry": {"coordinates":[4.2175779343,50.4159622192],"type":"Point"}
}