{
  "type": "Feature",
  "properties": {
    "addr:full":"Industrielaan 36 Brakel (nederbrakel) Oost-Vlaanderen 9660",
    "addr:housenumber":"36",
    "addr:postcode":"9660",
    "addr:street":"Industrielaan",
    "iso:country":"BE",
    "sg:address":"Industrielaan 36",
    "sg:city":"Brakel (nederbrakel)",
    "sg:classifiers":[
        {
            "category":"Manufacturing",
            "subcategory":"Tools & Machinery",
            "type":"Manufacturing & Wholesale Goods"
        }
    ],
    "sg:phone":"+32 55 42 01 90",
    "sg:postcode":"9660",
    "sg:province":"Oost-Vlaanderen",
    "sg:tags":[
        "builder"
    ],
    "wof:name":"Chevalier F",
    "wof:placetype":"venue"
},
  "geometry": {"coordinates":[3.7608599663,50.7957229614],"type":"Point"}
}