{
  "type": "Feature",
  "properties": {
    "addr:full":"Avenue De L'emeraude 60b1 Schaarbeek/schaerbeek Bruxelles-Capitale 1030",
    "addr:housenumber":"60b1",
    "addr:postcode":"1030",
    "addr:street":"Avenue De L'Emeraude",
    "iso:country":"BE",
    "sg:address":"Avenue De L'emeraude 60b1",
    "sg:city":"Schaarbeek/schaerbeek",
    "sg:orig_category":"Activit\u00e9s r\u00e9cr\u00e9atives diverses",
    "sg:phone":"+32 2 735 87 33",
    "sg:postcode":"1030",
    "sg:province":"Bruxelles-Capitale",
    "wof:name":"C.b. L'union Europ\u00c9enne",
    "wof:placetype":"venue"
},
  "geometry": {"coordinates":[4.3742771149,50.8617973328],"type":"Point"}
}