{
  "type": "Feature",
  "properties": {
    "iso:country":"BE",
    "sg:address":"Mechelsesteenweg 65",
    "sg:city":"Heist-op-den-berg",
    "sg:orig_category":"Pleisterwerk",
    "sg:phone":"+32 15 24 58 95",
    "sg:postcode":"2220",
    "sg:province":"Antwerpen",
    "wof:name":"Patrick Van Dessel",
    "wof:placetype":"venue"
},
  "geometry": {"coordinates":[4.7027587891,51.0717697144],"type":"Point"}
}