{
  "type": "Feature",
  "properties": {
    "iso:country":"BE",
    "sg:address":"Oudestrijderslaan 7",
    "sg:city":"De Pinte",
    "sg:orig_category":"Ordinateurs and \u00e9quipement informatique",
    "sg:phone":"+32 9 281 15 91",
    "sg:postcode":"9840",
    "sg:province":"Oost-Vlaanderen",
    "wof:name":"Cd I.d.",
    "wof:placetype":"venue"
},
  "geometry": {"coordinates":[3.6569530964,50.9893341064],"type":"Point"}
}