{
  "type": "Feature",
  "properties": {
    "iso:country":"BE",
    "sg:address":"Zandbergstraat 7",
    "sg:city":"Kortenaken (hoeleden)",
    "sg:classifiers":[
        {
            "category":"Health Services",
            "subcategory":"Doctor",
            "type":"Services"
        }
    ],
    "sg:phone":"+32 16 77 93 90",
    "sg:postcode":"3471",
    "sg:province":"Vlaams-Brabant",
    "sg:tags":[
        "medicinephysicians",
        "surgeon"
    ],
    "wof:name":"Lochy G",
    "wof:placetype":"venue"
},
  "geometry": {"coordinates":[4.984046936,50.8630142212],"type":"Point"}
}