{
  "type": "Feature",
  "properties": {
    "addr:full":"Georges Henrilaan 393 Sint-lambrechts-woluwe/woluwe-saint-lambert Bruxelles-Capitale 1200",
    "addr:housenumber":"393;/",
    "addr:postcode":"1200",
    "addr:street":"Henrilaan;Sint-Lambrechts-Woluwe",
    "iso:country":"BE",
    "sg:address":"Georges Henrilaan 393",
    "sg:city":"Sint-lambrechts-woluwe/woluwe-saint-lambert",
    "sg:orig_category":"IJzerwaren, bouw- and verfmaterialen Meubelzaken, woning- and keukeninrichting",
    "sg:phone":"+32 2 734 73 38",
    "sg:postcode":"1200",
    "sg:province":"Bruxelles-Capitale",
    "wof:name":"Plastimo",
    "wof:placetype":"venue"
},
  "geometry": {"coordinates":[4.4077968597,50.8425331116],"type":"Point"}
}