{
  "type": "Feature",
  "properties": {
    "addr:full":"Rue Puits-en-sock Li\u00e8ge 1 (li\u00e8ge 2) Li\u00e8ge 4020",
    "addr:housenumber":"1;2",
    "addr:postcode":"4020",
    "addr:street":"Rue Puits-En-Sock Lie\u0300Ge",
    "iso:country":"BE",
    "sg:address":"Rue Puits-en-sock",
    "sg:city":"Li\u00e8ge 1 (li\u00e8ge 2)",
    "sg:classifiers":[
        {
            "category":"Shopping",
            "subcategory":"Clothing, Apparel, & Fashions",
            "type":"Retail Goods"
        }
    ],
    "sg:phone":"+32 4 342 63 67",
    "sg:postcode":"4020",
    "sg:province":"Li\u00e8ge",
    "sg:tags":[
        "boutique"
    ],
    "wof:name":"Must (le)",
    "wof:placetype":"venue"
},
  "geometry": {"coordinates":[5.5865950584,50.6384086609],"type":"Point"}
}