{
  "type": "Feature",
  "properties": {
    "addr:full":"Klijtstraat 116 Deerlijk West-Vlaanderen 8540",
    "addr:housenumber":"116",
    "addr:postcode":"8540",
    "addr:street":"Klijtstraat",
    "iso:country":"BE",
    "sg:address":"Klijtstraat 116",
    "sg:city":"Deerlijk",
    "sg:orig_category":"Producteurs de l\u00e9gumes",
    "sg:phone":"+32 56 77 31 69",
    "sg:postcode":"8540",
    "sg:province":"West-Vlaanderen",
    "wof:name":"Kurt Chanterie",
    "wof:placetype":"venue"
},
  "geometry": {"coordinates":[3.3771810532,50.8367424011],"type":"Point"}
}