{
  "type": "Feature",
  "properties": {
    "addr:full":"Gustaaf Peetersstraat 48 Ranst Antwerpen 2520",
    "addr:housenumber":"48",
    "addr:postcode":"2520",
    "addr:street":"Gustaaf Peetersstraat",
    "iso:country":"BE",
    "sg:address":"Gustaaf Peetersstraat 48",
    "sg:city":"Ranst",
    "sg:classifiers":[
        {
            "category":"Food & Beverages",
            "subcategory":"Fruits & Vegetables",
            "type":"Retail Goods"
        }
    ],
    "sg:phone":"+32 3 485 57 43",
    "sg:postcode":"2520",
    "sg:province":"Antwerpen",
    "sg:tags":[
        "l\u00e9gumes"
    ],
    "wof:name":"Pittoors - De Wit",
    "wof:placetype":"venue"
},
  "geometry": {"coordinates":[4.6051030159,51.180065155],"type":"Point"}
}