{
  "type": "Feature",
  "properties": {
    "addr:full":"Voshoekstraat 2a Torhout West-Vlaanderen 8820",
    "addr:housenumber":"2a",
    "addr:postcode":"8820",
    "addr:street":"Voshoekstraat",
    "iso:country":"BE",
    "sg:address":"Voshoekstraat 2a",
    "sg:city":"Torhout",
    "sg:orig_category":"Woningbouw",
    "sg:phone":"+32 50 21 74 91",
    "sg:postcode":"8820",
    "sg:province":"West-Vlaanderen",
    "wof:name":"Pollet Kris & Marc",
    "wof:placetype":"venue"
},
  "geometry": {"coordinates":[3.0771679878,51.0584716797],"type":"Point"}
}