{
  "type": "Feature",
  "properties": {
    "iso:country":"BE",
    "sg:address":"Lamorinierestraat 150",
    "sg:city":"Antwerpen",
    "sg:orig_category":"Algemeen secundair onderwijs",
    "sg:phone":"+32 3 281 25 35",
    "sg:postcode":"2018",
    "sg:province":"Antwerpen",
    "wof:name":"Vrije Israel.school Yavne",
    "wof:placetype":"venue"
},
  "geometry": {"coordinates":[4.4205079079,51.2037162781],"type":"Point"}
}