{
  "type": "Feature",
  "properties": {
    "iso:country":"BE",
    "sg:address":"Rue De L\u00b4et\u00c9 79ba",
    "sg:city":"Elsene/ixelles",
    "sg:orig_category":"M\u00e9decins and sp\u00e9cialistes",
    "sg:phone":"+32 2 649 36 46",
    "sg:postcode":"1050",
    "sg:province":"Bruxelles-Capitale",
    "wof:name":"Mich\u00c8le Quintin",
    "wof:placetype":"venue"
},
  "geometry": {"coordinates":[4.3891620636,50.8183708191],"type":"Point"}
}