{
  "type": "Feature",
  "properties": {
    "iso:country":"BE",
    "sg:address":"Poelstraat 10",
    "sg:city":"Merelbeke",
    "sg:orig_category":"Imprimeries and copyshops",
    "sg:phone":"+32 9 230 06 03",
    "sg:postcode":"9820",
    "sg:province":"Oost-Vlaanderen",
    "wof:name":"Drukkerij Andr\u00c9",
    "wof:placetype":"venue"
},
  "geometry": {"coordinates":[3.7473380566,50.989112854],"type":"Point"}
}