{
  "type": "Feature",
  "properties": {
    "iso:country":"BE",
    "sg:address":"Rue Capitaine Hubart 4ba",
    "sg:city":"Mettet",
    "sg:orig_category":"Artsen and specialisten",
    "sg:phone":"+32 71 72 79 97",
    "sg:postcode":"5646",
    "sg:province":"Namur",
    "wof:name":"Jean Pirson",
    "wof:placetype":"venue"
},
  "geometry": {"coordinates":[4.6496372223,50.27602005],"type":"Point"}
}