{
  "type": "Feature",
  "properties": {
    "addr:full":"Rue Grande 85 Philippeville Namur 5600",
    "addr:housenumber":"85",
    "addr:postcode":"5600",
    "addr:street":"Rue Grande",
    "iso:country":"BE",
    "sg:address":"Rue Grande 85",
    "sg:city":"Philippeville",
    "sg:orig_category":"R\u00e9cup\u00e9ration de mati\u00e8res m\u00e9talliques recyclables and d\u00e9molisseurs de voitures. Entretien et r\u00e9parati",
    "sg:phone":"+32 82 67 74 14",
    "sg:postcode":"5600",
    "sg:province":"Namur",
    "wof:name":"De Winter D\u00c9pannage",
    "wof:placetype":"venue"
},
  "geometry": {"coordinates":[4.695084095,50.1668968201],"type":"Point"}
}