{
  "type": "Feature",
  "properties": {
    "addr:full":"Chauss\u00c9e De Dinant 8 Profondeville Namur 5170",
    "addr:housenumber":"8",
    "addr:postcode":"5170",
    "addr:street":"Chausse\u0301E De Dinant",
    "iso:country":"BE",
    "sg:address":"Chauss\u00c9e De Dinant 8",
    "sg:city":"Profondeville",
    "sg:orig_category":"Diverse kredietdiensten",
    "sg:postcode":"5170",
    "sg:province":"Namur",
    "wof:name":"Bancontact-mister Cash",
    "wof:placetype":"venue"
},
  "geometry": {"coordinates":[4.8696961403,50.3775215149],"type":"Point"}
}