{
  "type": "Feature",
  "properties": {
    "iso:country":"BE",
    "sg:address":"Demerstraat 95",
    "sg:city":"Hasselt",
    "sg:classifiers":[
        {
            "category":"Cafe",
            "type":"Food & Drink"
        }
    ],
    "sg:phone":"+32 11 22 68 68",
    "sg:postcode":"3500",
    "sg:province":"Limburg",
    "sg:tags":[
        "snack-bars"
    ],
    "wof:name":"Panachee",
    "wof:placetype":"venue"
},
  "geometry": {"coordinates":[5.3391780853,50.9333190918],"type":"Point"}
}