{
  "type": "Feature",
  "properties": {
    "iso:country":"BE",
    "sg:address":"Rue Joseph Wauters 65",
    "sg:city":"Wavre",
    "sg:orig_category":"Voertuigen",
    "sg:phone":"+32 10 22 56 13",
    "sg:postcode":"1300",
    "sg:province":"Brabant Wallon",
    "wof:name":"Olivares",
    "wof:placetype":"venue"
},
  "geometry": {"coordinates":[4.6093101501,50.7114028931],"type":"Point"}
}