{
  "type": "Feature",
  "properties": {
    "iso:country":"BE",
    "sg:address":"Rue Du Cerisier 40b11",
    "sg:city":"Mons",
    "sg:orig_category":"Traitements param\u00e9dicaux",
    "sg:phone":"+32 65 31 64 02",
    "sg:postcode":"7033",
    "sg:province":"Hainaut",
    "wof:name":"Ch. Gloire",
    "wof:placetype":"venue"
},
  "geometry": {"coordinates":[3.9253261089,50.4366378784],"type":"Point"}
}