{
  "type": "Feature",
  "properties": {
    "addr:full":"Rue Fraikin 36 Bruxelles (schaerbeek) Bruxelles-Capitale 1030",
    "addr:housenumber":"36",
    "addr:postcode":"1030",
    "addr:street":"Rue Fraikin",
    "iso:country":"BE",
    "sg:address":"Rue Fraikin 36",
    "sg:city":"Bruxelles (schaerbeek)",
    "sg:classifiers":[
        {
            "category":"Freight",
            "type":"Transportation"
        }
    ],
    "sg:phone":"+32 2 248 08 51",
    "sg:postcode":"1030",
    "sg:province":"Bruxelles-Capitale",
    "sg:tags":[
        "-",
        "transport"
    ],
    "wof:name":"Teuta Sprl",
    "wof:placetype":"venue"
},
  "geometry": {"coordinates":[4.3744568825,50.8699989319],"type":"Point"}
}