{
  "type": "Feature",
  "properties": {
    "addr:full":"Archimedeslaan 13 Edegem Antwerpen 2650",
    "addr:housenumber":"13",
    "addr:postcode":"2650",
    "addr:street":"Archimedeslaan",
    "iso:country":"BE",
    "sg:address":"Archimedeslaan 13",
    "sg:city":"Edegem",
    "sg:orig_category":"Traitements param\u00e9dicaux",
    "sg:phone":"+32 3 289 01 72",
    "sg:postcode":"2650",
    "sg:province":"Antwerpen",
    "wof:name":"Sabine Verhemeldonck",
    "wof:placetype":"venue"
},
  "geometry": {"coordinates":[4.4408349991,51.1514053345],"type":"Point"}
}