{
  "type": "Feature",
  "properties": {
    "addr:full":"Ch De Tirlemont 48 Gembloux Namur 5030",
    "addr:housenumber":"48",
    "addr:postcode":"5030",
    "addr:street":"Ch De Tirlemont;Namur",
    "iso:country":"BE",
    "sg:address":"Ch De Tirlemont 48",
    "sg:city":"Gembloux",
    "sg:classifiers":[
        {
            "category":"Home & Garden",
            "subcategory":"Furniture",
            "type":"Retail Goods"
        }
    ],
    "sg:phone":"+32 81 61 14 53",
    "sg:postcode":"5030",
    "sg:province":"Namur",
    "sg:tags":[
        "household",
        "wood"
    ],
    "wof:name":"H Socquet Sa",
    "wof:placetype":"venue"
},
  "geometry": {"coordinates":[4.7008938789,50.574672699],"type":"Point"}
}