{
  "type": "Feature",
  "properties": {
    "addr:full":"Industrielaan 4 Menen West-Vlaanderen 8930",
    "addr:housenumber":"4",
    "addr:postcode":"8930",
    "addr:street":"Industrielaan",
    "iso:country":"BE",
    "sg:address":"Industrielaan 4",
    "sg:city":"Menen",
    "sg:classifiers":[
        {
            "category":"Coffee & Tea",
            "type":"Food & Drink"
        }
    ],
    "sg:phone":"+32 56 52 77 77",
    "sg:postcode":"8930",
    "sg:province":"West-Vlaanderen",
    "sg:tags":[
        "gardening",
        "seedling"
    ],
    "wof:name":"Allflor Nv",
    "wof:placetype":"venue"
},
  "geometry": {"coordinates":[3.1049599648,50.7933006287],"type":"Point"}
}