{
  "type": "Feature",
  "properties": {
    "addr:full":"Oudenaardsesteenweg 36 Kruishoutem Oost-Vlaanderen 9770",
    "addr:housenumber":"36",
    "addr:postcode":"9770",
    "addr:street":"Oudenaardsesteenweg",
    "iso:country":"BE",
    "sg:address":"Oudenaardsesteenweg 36",
    "sg:city":"Kruishoutem",
    "sg:classifiers":[
        {
            "category":"Shopping",
            "subcategory":"Florist",
            "type":"Retail Goods"
        }
    ],
    "sg:phone":"+32 9 383 61 19",
    "sg:postcode":"9770",
    "sg:province":"Oost-Vlaanderen",
    "wof:name":"Mieke",
    "wof:placetype":"venue"
},
  "geometry": {"coordinates":[3.5295300484,50.8999595642],"type":"Point"}
}