{
  "type": "Feature",
  "properties": {
    "addr:full":"Keizersplein 39 Aalst Oost-Vlaanderen 9300",
    "addr:housenumber":"39",
    "addr:postcode":"9300",
    "addr:street":"Keizersplein",
    "iso:country":"BE",
    "sg:address":"Keizersplein 39",
    "sg:city":"Aalst",
    "sg:orig_category":"Verbruikerskredietinstellingen",
    "sg:phone":"+32 53 70 41 55",
    "sg:postcode":"9300",
    "sg:province":"Oost-Vlaanderen",
    "wof:name":"J. De Nil",
    "wof:placetype":"venue"
},
  "geometry": {"coordinates":[4.0362901688,50.9362220764],"type":"Point"}
}