{
  "type": "Feature",
  "properties": {
    "iso:country":"BE",
    "sg:address":"Voie De Li\u00c8ge 18",
    "sg:city":"Welkenraedt",
    "sg:orig_category":"D\u00e9m\u00e9nagements",
    "sg:phone":"+32 87 89 05 93",
    "sg:postcode":"4840",
    "sg:province":"Li\u00e8ge",
    "wof:name":"Maurice Gutmann",
    "wof:placetype":"venue"
},
  "geometry": {"coordinates":[5.9789099693,50.6507110596],"type":"Point"}
}