{
  "type": "Feature",
  "properties": {
    "iso:country":"BE",
    "sg:address":"Grand' Rue 115",
    "sg:city":"Saint-l\u00e9ger (ch\u00e2tillon)",
    "sg:classifiers":[
        {
            "category":"Food & Beverages",
            "subcategory":"Groceries & Convenience Stores",
            "type":"Retail Goods"
        }
    ],
    "sg:phone":"+32 63 22 18 83",
    "sg:postcode":"6747",
    "sg:province":"Luxembourg",
    "sg:tags":[
        "grocer"
    ],
    "wof:name":"Soleil De La Gaume",
    "wof:placetype":"venue"
},
  "geometry": {"coordinates":[5.6567749977,49.6120567322],"type":"Point"}
}