{
  "type": "Feature",
  "properties": {
    "iso:country":"BE",
    "sg:address":"Groenestraat 100",
    "sg:city":"Zedelgem",
    "sg:classifiers":[
        {
            "category":"Health Services",
            "subcategory":"Health Practitioner",
            "type":"Services"
        }
    ],
    "sg:phone":"+32 50 20 97 95",
    "sg:postcode":"8210",
    "sg:province":"West-Vlaanderen",
    "sg:tags":[
        "physiotherapist"
    ],
    "wof:name":"Detavernier-verfaillie Christine",
    "wof:placetype":"venue"
},
  "geometry": {"coordinates":[3.1462628841,51.1372032166],"type":"Point"}
}