{
  "type": "Feature",
  "properties": {
    "iso:country":"BE",
    "sg:address":"Puursesteenweg",
    "sg:city":"Bornem",
    "sg:classifiers":[
        {
            "category":"Freight",
            "type":"Transportation"
        }
    ],
    "sg:phone":"+32 3 899 15 01",
    "sg:postcode":"2880",
    "sg:province":"Antwerpen",
    "sg:tags":[
        "-",
        "transport"
    ],
    "wof:name":"Verzele D",
    "wof:placetype":"venue"
},
  "geometry": {"coordinates":[4.2327880859,51.0959205627],"type":"Point"}
}