{
  "type": "Feature",
  "properties": {
    "addr:full":"Rue Du Fonteneau 7 Nivelles Brabant Wallon 1400",
    "addr:housenumber":"7",
    "addr:postcode":"1400",
    "addr:street":"Rue Du Fonteneau",
    "iso:country":"BE",
    "sg:address":"Rue Du Fonteneau 7",
    "sg:city":"Nivelles",
    "sg:classifiers":[
        {
            "category":"Transit Center",
            "subcategory":"Freight",
            "type":"Transportation"
        }
    ],
    "sg:phone":"+32 67 84 25 84",
    "sg:postcode":"1400",
    "sg:province":"Brabant Wallon",
    "sg:tags":[
        "tackle"
    ],
    "wof:name":"Demag Products Sprl",
    "wof:placetype":"venue"
},
  "geometry": {"coordinates":[4.323679924,50.6099014282],"type":"Point"}
}