{
  "type": "Feature",
  "properties": {
    "iso:country":"BE",
    "sg:address":"Antwerpsestraat 22",
    "sg:city":"Rumst",
    "sg:orig_category":"Rev\u00eatements de sols and murs",
    "sg:phone":"+32 3 844 71 04",
    "sg:postcode":"2840",
    "sg:province":"Antwerpen",
    "wof:name":"Santana",
    "wof:placetype":"venue"
},
  "geometry": {"coordinates":[4.4521842003,51.0870780945],"type":"Point"}
}