{
  "type": "Feature",
  "properties": {
    "addr:full":"De Paallanden 11 Brugge West-Vlaanderen 8310",
    "addr:housenumber":"11",
    "addr:postcode":"8310",
    "iso:country":"BE",
    "sg:address":"De Paallanden 11",
    "sg:city":"Brugge",
    "sg:orig_category":"Installatie van houten of kunststof schrijnwerk Woningbouw",
    "sg:phone":"+32 50 35 16 03",
    "sg:postcode":"8310",
    "sg:province":"West-Vlaanderen",
    "wof:name":"Guido Lanszweert",
    "wof:placetype":"venue"
},
  "geometry": {"coordinates":[3.2598979473,51.215259552],"type":"Point"}
}