{
  "type": "Feature",
  "properties": {
    "iso:country":"BE",
    "sg:address":"Rembert Dodoensstraat 95",
    "sg:city":"Mechelen",
    "sg:classifiers":[
        {
            "category":"Real Estate",
            "subcategory":"Surveying",
            "type":"Services"
        }
    ],
    "sg:phone":"+32 15 41 03 20",
    "sg:postcode":"2800",
    "sg:province":"Antwerpen",
    "sg:tags":[
        "surveyor",
        "land"
    ],
    "wof:name":"Van De Put E",
    "wof:placetype":"venue"
},
  "geometry": {"coordinates":[4.4673838615,51.0218429565],"type":"Point"}
}