{
  "type": "Feature",
  "properties": {
    "addr:full":"Doorniksesteenweg 55 Avelgem West-Vlaanderen 8580",
    "addr:housenumber":"55",
    "addr:postcode":"8580",
    "addr:street":"Doorniksesteenweg",
    "iso:country":"BE",
    "sg:address":"Doorniksesteenweg 55",
    "sg:city":"Avelgem",
    "sg:orig_category":"Catering and organisatie van feesten Voedingsspeciaalzaken",
    "sg:phone":"+32 56 64 66 77",
    "sg:postcode":"8580",
    "sg:province":"West-Vlaanderen",
    "wof:name":"'t Keukentje",
    "wof:placetype":"venue"
},
  "geometry": {"coordinates":[3.4442620277,50.7740364075],"type":"Point"}
}