{
  "type": "Feature",
  "properties": {
    "addr:full":"Oude Ieperstraat 14b48 Wevelgem West-Vlaanderen 8560",
    "addr:housenumber":"14b48",
    "addr:postcode":"8560",
    "addr:street":"Oude Ieperstraat",
    "iso:country":"BE",
    "sg:address":"Oude Ieperstraat 14b48",
    "sg:city":"Wevelgem",
    "sg:orig_category":"Elektrische installaties voor woningen Informaticaconsulenten Loodgieterij, verwarming and sanitaire",
    "sg:phone":"+32 56 41 27 42",
    "sg:postcode":"8560",
    "sg:province":"West-Vlaanderen",
    "wof:name":"Vandoorne",
    "wof:placetype":"venue"
},
  "geometry": {"coordinates":[3.2135419846,50.8357124329],"type":"Point"}
}