{
  "type": "Feature",
  "properties": {
    "addr:full":"Place De L'accueil 3 Ottignies-louvain-la-neuve (louvain-la-neuve) Brabant Wallon 1348",
    "addr:housenumber":"3",
    "addr:postcode":"1348",
    "addr:street":"Place De L'Accueil",
    "iso:country":"BE",
    "sg:address":"Place De L'accueil 3",
    "sg:city":"Ottignies-louvain-la-neuve (louvain-la-neuve)",
    "sg:classifiers":[
        {
            "category":"Banks & Credit Unions",
            "subcategory":"Investment Brokerage",
            "type":"Services"
        }
    ],
    "sg:phone":"+32 10 45 17 09",
    "sg:postcode":"1348",
    "sg:province":"Brabant Wallon",
    "sg:tags":[
        "jean",
        "casual",
        "wear"
    ],
    "wof:name":"Jean's Fizz",
    "wof:placetype":"venue"
},
  "geometry": {"coordinates":[4.6152071953,50.670627594],"type":"Point"}
}