{
  "type": "Feature",
  "properties": {
    "addr:full":"Hospitaalstraat 16 A Temse Oost-Vlaanderen 9140",
    "addr:housenumber":"16 a",
    "addr:postcode":"9140",
    "addr:street":"Hospitaalstraat",
    "iso:country":"BE",
    "sg:address":"Hospitaalstraat 16 A",
    "sg:city":"Temse",
    "sg:orig_category":"Plaatsen van vloer- and muurbekleding Speciaalzaken Woningbouw",
    "sg:phone":"+32 3 744 10 19",
    "sg:postcode":"9140",
    "sg:province":"Oost-Vlaanderen",
    "wof:name":"Rudi Wuytack",
    "wof:placetype":"venue"
},
  "geometry": {"coordinates":[4.269425869,51.1307525635],"type":"Point"}
}