{
  "type": "Feature",
  "properties": {
    "iso:country":"BE",
    "sg:address":"Vosselarestraat 19",
    "sg:city":"Nevele",
    "sg:orig_category":"Fotografen and fotostudio's",
    "sg:phone":"+32 9 371 61 94",
    "sg:postcode":"9850",
    "sg:province":"Oost-Vlaanderen",
    "wof:name":"Fotoburo",
    "wof:placetype":"venue"
},
  "geometry": {"coordinates":[3.5719280243,51.0549354553],"type":"Point"}
}