{
  "type": "Feature",
  "properties": {
    "iso:country":"BE",
    "sg:address":"Vrijheidsplein 1",
    "sg:city":"Lokeren",
    "sg:classifiers":[
        {
            "category":"Shopping",
            "subcategory":"Antiques",
            "type":"Retail Goods"
        }
    ],
    "sg:phone":"+32 9 348 06 42",
    "sg:postcode":"9160",
    "sg:province":"Oost-Vlaanderen",
    "wof:name":"Di Art",
    "wof:placetype":"venue"
},
  "geometry": {"coordinates":[3.9875109196,51.1020545959],"type":"Point"}
}