{
  "type": "Feature",
  "properties": {
    "addr:full":"Rue Francois-lefebvre 136 Li\u00c8ge Li\u00e8ge 4000",
    "addr:housenumber":"136",
    "addr:postcode":"4000",
    "addr:street":"Rue Francois-Lefebvre",
    "iso:country":"BE",
    "sg:address":"Rue Francois-lefebvre 136",
    "sg:city":"Li\u00c8ge",
    "sg:orig_category":"Herstelling and restauratie van meubelen Installatie van houten of kunststof schrijnwerk",
    "sg:phone":"+32 4 263 61 05",
    "sg:postcode":"4000",
    "sg:province":"Li\u00e8ge",
    "wof:name":"Lorguet Et Fils",
    "wof:placetype":"venue"
},
  "geometry": {"coordinates":[5.5489530563,50.6825485229],"type":"Point"}
}