{
  "type": "Feature",
  "properties": {
    "iso:country":"BE",
    "sg:address":"Avenue Guillaume Van Leeuw 47",
    "sg:city":"Bruxelles (evere)",
    "sg:classifiers":[
        {
            "category":"Retail",
            "subcategory":"Auto Repair",
            "type":"Services"
        }
    ],
    "sg:phone":"+32 2 216 38 48",
    "sg:postcode":"1140",
    "sg:province":"Bruxelles-Capitale",
    "sg:tags":[
        "garage"
    ],
    "wof:name":"Noel Garage",
    "wof:placetype":"venue"
},
  "geometry": {"coordinates":[4.4056711197,50.8770141602],"type":"Point"}
}