{
  "type": "Feature",
  "properties": {
    "addr:full":"Rue Haute-saive 45 Blegny Li\u00e8ge 4671",
    "addr:housenumber":"45",
    "addr:postcode":"4671",
    "addr:street":"Rue Haute-Saive",
    "iso:country":"BE",
    "sg:address":"Rue Haute-saive 45",
    "sg:city":"Blegny",
    "sg:orig_category":"Diensten voor huisdieren Huisdieren and benodigdheden",
    "sg:phone":"+32 4 362 06 60",
    "sg:postcode":"4671",
    "sg:province":"Li\u00e8ge",
    "wof:name":"La Bouclerie",
    "wof:placetype":"venue"
},
  "geometry": {"coordinates":[5.6760540009,50.6560211182],"type":"Point"}
}