{
  "type": "Feature",
  "properties": {
    "iso:country":"BE",
    "sg:address":"Frontlaan 8",
    "sg:city":"Etterbeek/etterbeek",
    "sg:orig_category":"Landmeters",
    "sg:phone":"+32 2 734 66 93",
    "sg:postcode":"1040",
    "sg:province":"Bruxelles-Capitale",
    "wof:name":"Daniel Oppeel",
    "wof:placetype":"venue"
},
  "geometry": {"coordinates":[4.400616169,50.8322563171],"type":"Point"}
}