{
  "type": "Feature",
  "properties": {
    "iso:country":"BE",
    "sg:address":"Bloempotstraat 3bb",
    "sg:city":"Beveren",
    "sg:orig_category":"Fruitteelt",
    "sg:phone":"+32 3 773 41 12",
    "sg:postcode":"9130",
    "sg:province":"Oost-Vlaanderen",
    "wof:name":"Willy Bogaert",
    "wof:placetype":"venue"
},
  "geometry": {"coordinates":[4.1647992134,51.2628631592],"type":"Point"}
}