{
  "type": "Feature",
  "properties": {
    "addr:full":"Weverstraat 28 Boechout Antwerpen 2531",
    "addr:housenumber":"28",
    "addr:postcode":"2531",
    "addr:street":"Weverstraat",
    "iso:country":"BE",
    "sg:address":"Weverstraat 28",
    "sg:city":"Boechout",
    "sg:classifiers":[
        {
            "category":"Arena",
            "subcategory":"Sports Club",
            "type":"Entertainment"
        }
    ],
    "sg:phone":"+32 3 455 58 83",
    "sg:postcode":"2531",
    "sg:province":"Antwerpen",
    "sg:tags":[
        "de"
    ],
    "wof:name":"W.s.c. Moed & Volharding",
    "wof:placetype":"venue"
},
  "geometry": {"coordinates":[4.5215559006,51.176071167],"type":"Point"}
}