{
  "type": "Feature",
  "properties": {
    "iso:country":"BE",
    "sg:address":"Engerstraat 140",
    "sg:city":"Kortenberg",
    "sg:orig_category":"Artsen and specialisten",
    "sg:phone":"+32 477 22 62 40",
    "sg:postcode":"3071",
    "sg:province":"Vlaams-Brabant",
    "wof:name":"Mirjam Lindemann",
    "wof:placetype":"venue"
},
  "geometry": {"coordinates":[4.5486187935,50.8964805603],"type":"Point"}
}