{
  "type": "Feature",
  "properties": {
    "iso:country":"BE",
    "sg:address":"Onderstraat 15",
    "sg:city":"Gavere",
    "sg:orig_category":"S\u00e9curit\u00e9 sociale",
    "sg:phone":"+32 9 384 26 83",
    "sg:postcode":"9890",
    "sg:province":"Oost-Vlaanderen",
    "wof:name":"Bond Moyson",
    "wof:placetype":"venue"
},
  "geometry": {"coordinates":[3.6622519493,50.9300994873],"type":"Point"}
}