{
  "type": "Feature",
  "properties": {
    "addr:full":"Zandberg 6 Westerlo Antwerpen 2260",
    "addr:housenumber":"6",
    "addr:postcode":"2260",
    "addr:street":"Zandberg",
    "iso:country":"BE",
    "sg:address":"Zandberg 6",
    "sg:city":"Westerlo",
    "sg:classifiers":[
        {
            "category":"Real Estate",
            "subcategory":"Architect",
            "type":"Services"
        }
    ],
    "sg:phone":"+32 14 54 49 61",
    "sg:postcode":"2260",
    "sg:province":"Antwerpen",
    "wof:name":"Vander Laenen W",
    "wof:placetype":"venue"
},
  "geometry": {"coordinates":[4.9312300682,51.0933418274],"type":"Point"}
}