{
  "type": "Feature",
  "properties": {
    "iso:country":"BE",
    "sg:address":"Generaal Lotzstraat 17",
    "sg:city":"Ieper",
    "sg:orig_category":"Fruits and l\u00e9gumes Produits \u00e0 base de pommes de terre Gr",
    "sg:phone":"+32 57 42 25 35",
    "sg:postcode":"8904",
    "sg:province":"West-Vlaanderen",
    "wof:name":"Fa. Antheunes",
    "wof:placetype":"venue"
},
  "geometry": {"coordinates":[2.83553195,50.9172744751],"type":"Point"}
}