{
  "type": "Feature",
  "properties": {
    "addr:full":"Boulevard Paul Janson 42 Charleroi Hainaut 6000",
    "addr:housenumber":"42",
    "addr:postcode":"6000",
    "addr:street":"Boulevard Paul Janson;Hainaut",
    "iso:country":"BE",
    "sg:address":"Boulevard Paul Janson 42",
    "sg:city":"Charleroi",
    "sg:orig_category":"Artsen and specialisten",
    "sg:phone":"+32 71 31 45 70",
    "sg:postcode":"6000",
    "sg:province":"Hainaut",
    "wof:name":"Etienne Salmin",
    "wof:placetype":"venue"
},
  "geometry": {"coordinates":[4.4473900795,50.4141998291],"type":"Point"}
}