{
  "type": "Feature",
  "properties": {
    "iso:country":"BE",
    "sg:address":"Rue De La Forge 1",
    "sg:city":"Beauraing (honnay)",
    "sg:classifiers":[
        {
            "category":"Parking",
            "subcategory":"Bicycle",
            "type":"Transportation"
        }
    ],
    "sg:phone":"+32 84 38 99 43",
    "sg:postcode":"5570",
    "sg:province":"Namur",
    "sg:tags":[
        "chiropodist"
    ],
    "wof:name":"Genson R",
    "wof:placetype":"venue"
},
  "geometry": {"coordinates":[5.0365757942,50.083732605],"type":"Point"}
}