{
  "type": "Feature",
  "properties": {
    "addr:full":"Osseghemstraat 114 Sint-jans-molenbeek/molenbeek-saint-jean Bruxelles-Capitale 1080",
    "addr:housenumber":"114;/",
    "addr:postcode":"1080",
    "addr:street":"Osseghemstraat;Sint-Jans-Molenbeek",
    "iso:country":"BE",
    "sg:address":"Osseghemstraat 114",
    "sg:city":"Sint-jans-molenbeek/molenbeek-saint-jean",
    "sg:orig_category":"Boekhandels Krantenwinkels Rookartikelen",
    "sg:phone":"+32 2 410 34 57",
    "sg:postcode":"1080",
    "sg:province":"Bruxelles-Capitale",
    "wof:name":"Librairie Des Muses",
    "wof:placetype":"venue"
},
  "geometry": {"coordinates":[4.3182091713,50.8542060852],"type":"Point"}
}