{
  "type": "Feature",
  "properties": {
    "iso:country":"BE",
    "sg:address":"Chauss\u00c9e De Dinant 159",
    "sg:city":"Profondeville",
    "sg:orig_category":"Installation \u00e9lectrique r\u00e9sidentielle",
    "sg:phone":"+32 81 41 23 79",
    "sg:postcode":"5170",
    "sg:province":"Namur",
    "wof:name":"Pierre Delcourt",
    "wof:placetype":"venue"
},
  "geometry": {"coordinates":[4.874838829,50.356552124],"type":"Point"}
}