{
  "type": "Feature",
  "properties": {
    "addr:full":"Sleeckxstraat 9 Antwerpen Antwerpen 2060",
    "addr:housenumber":"9",
    "addr:postcode":"2060",
    "addr:street":"Sleeckxstraat",
    "iso:country":"BE",
    "sg:address":"Sleeckxstraat 9",
    "sg:city":"Antwerpen",
    "sg:classifiers":[
        {
            "category":"Transit Center",
            "subcategory":"Freight",
            "type":"Transportation"
        }
    ],
    "sg:phone":"+32 3 235 23 77",
    "sg:postcode":"2060",
    "sg:province":"Antwerpen",
    "sg:tags":[
        "import",
        "export",
        "-"
    ],
    "wof:name":"Chiwal",
    "wof:placetype":"venue"
},
  "geometry": {"coordinates":[4.4343910217,51.2250747681],"type":"Point"}
}