{
  "type": "Feature",
  "properties": {
    "addr:full":"Kerkstraat 109 Anzegem (grand) West-Vlaanderen 8570",
    "addr:housenumber":"109",
    "addr:postcode":"8570",
    "addr:street":"Kerkstraat;Grand West-Vlaanderen",
    "iso:country":"BE",
    "sg:address":"Kerkstraat 109",
    "sg:city":"Anzegem (grand)",
    "sg:orig_category":"Banques and organismes de cr\u00e9dit",
    "sg:phone":"+32 56 68 92 25",
    "sg:postcode":"8570",
    "sg:province":"West-Vlaanderen",
    "wof:name":"Bacob",
    "wof:placetype":"venue"
},
  "geometry": {"coordinates":[3.4744749069,50.8382034302],"type":"Point"}
}