{
  "type": "Feature",
  "properties": {
    "iso:country":"BE",
    "sg:address":"Rue Des Lattes 29",
    "sg:city":"Cerfontaine",
    "sg:orig_category":"Entretien and r\u00e9parations de voitures",
    "sg:phone":"+32 71 61 31 14",
    "sg:postcode":"5630",
    "sg:province":"Namur",
    "wof:name":"Frans Danneels",
    "wof:placetype":"venue"
},
  "geometry": {"coordinates":[4.4546260834,50.2186203003],"type":"Point"}
}