{
  "type": "Feature",
  "properties": {
    "addr:full":"Avenue De La Gare 49 Arlon Luxembourg 6700",
    "addr:housenumber":"49",
    "addr:postcode":"6700",
    "addr:street":"Avenue De La Gare",
    "iso:country":"BE",
    "sg:address":"Avenue De La Gare 49",
    "sg:city":"Arlon",
    "sg:classifiers":[
        {
            "category":"Bars & Pubs",
            "type":"Food & Drink"
        }
    ],
    "sg:phone":"+32 63 41 25 76",
    "sg:postcode":"6700",
    "sg:province":"Luxembourg",
    "wof:name":"Le Tropical Bantoum",
    "wof:placetype":"venue"
},
  "geometry": {"coordinates":[5.8096752167,49.680644989],"type":"Point"}
}