{
  "type": "Feature",
  "properties": {
    "iso:country":"BE",
    "sg:address":"Bosstraat 8",
    "sg:city":"Onze-lieve-vrouw-waver",
    "sg:orig_category":"Informaticaconsulenten Microsoft Software ontwikkeling and ontwerp",
    "sg:phone":"+32 15 75 30 58",
    "sg:postcode":"2861",
    "sg:province":"Antwerpen",
    "wof:name":"Ata",
    "wof:placetype":"venue"
},
  "geometry": {"coordinates":[4.580807209,51.0635414124],"type":"Point"}
}