{
  "type": "Feature",
  "properties": {
    "iso:country":"BE",
    "sg:address":"Rue Jean Jaur\u00e8s 32",
    "sg:city":"La Louvi\u00e8re",
    "sg:classifiers":[
        {
            "category":"Home & Garden",
            "subcategory":"Kitchen Supply",
            "type":"Retail Goods"
        }
    ],
    "sg:phone":"+32 64 28 53 07",
    "sg:postcode":"7100",
    "sg:province":"Hainaut",
    "sg:tags":[
        "installation"
    ],
    "wof:name":"La Torin\u00e8se",
    "wof:placetype":"venue"
},
  "geometry": {"coordinates":[4.1871438026,50.4802780151],"type":"Point"}
}