{
  "type": "Feature",
  "properties": {
    "iso:country":"BE",
    "sg:address":"Oude-afspanningsplein 2",
    "sg:city":"Jette",
    "sg:classifiers":[
        {
            "category":"Insurance",
            "subcategory":"Insurance Agent",
            "type":"Services"
        }
    ],
    "sg:phone":"+32 2 478 72 43",
    "sg:postcode":"1090",
    "sg:province":"Bruxelles-Capitale",
    "sg:tags":[
        "verzekeringsmakelaars",
        "expert"
    ],
    "wof:name":"S.n.c.i.",
    "wof:placetype":"venue"
},
  "geometry": {"coordinates":[4.317814827,50.8856658936],"type":"Point"}
}