{
  "type": "Feature",
  "properties": {
    "iso:country":"BE",
    "sg:address":"Wipstraat 38",
    "sg:city":"Sint-gillis/saint-gilles",
    "sg:orig_category":"Sportcentra Sportclubs Sportterreinen and installaties behalve sportcentra",
    "sg:phone":"+32 2 539 06 15",
    "sg:postcode":"1060",
    "sg:province":"Bruxelles-Capitale",
    "wof:name":"Piscine Communale & Centre Sportif",
    "wof:placetype":"venue"
},
  "geometry": {"coordinates":[4.3408880234,50.8269424438],"type":"Point"}
}