{
  "type": "Feature",
  "properties": {
    "addr:full":"Kasteelstraat 39 Nieuwerkerken Limburg 3850",
    "addr:housenumber":"39",
    "addr:postcode":"3850",
    "addr:street":"Kasteelstraat",
    "iso:country":"BE",
    "sg:address":"Kasteelstraat 39",
    "sg:city":"Nieuwerkerken",
    "sg:classifiers":[
        {
            "category":"Autos & Motor Vehicles",
            "subcategory":"Motorcycle Sales",
            "type":"Retail Goods"
        }
    ],
    "sg:phone":"+32 11 68 85 64",
    "sg:postcode":"3850",
    "sg:province":"Limburg",
    "sg:tags":[
        "scooter",
        "-",
        "moped"
    ],
    "wof:name":"Vandenryt A",
    "wof:placetype":"venue"
},
  "geometry": {"coordinates":[5.1980619431,50.8660736084],"type":"Point"}
}