{
  "type": "Feature",
  "properties": {
    "iso:country":"BE",
    "sg:address":"Chauss\u00c9e De Mons 5",
    "sg:city":"Nivelles",
    "sg:orig_category":"Diverse bedrijfsbeheeradviesbureaus",
    "sg:phone":"+32 67 21 94 97",
    "sg:postcode":"1400",
    "sg:province":"Brabant Wallon",
    "wof:name":"Financiere Binet",
    "wof:placetype":"venue"
},
  "geometry": {"coordinates":[4.3142609596,50.5899963379],"type":"Point"}
}