{
  "type": "Feature",
  "properties": {
    "addr:full":"Baronstraat 115 Izegem West-Vlaanderen 8870",
    "addr:housenumber":"115",
    "addr:postcode":"8870",
    "addr:street":"Baronstraat",
    "iso:country":"BE",
    "sg:address":"Baronstraat 115",
    "sg:city":"Izegem",
    "sg:orig_category":"Installatie van houten of kunststof schrijnwerk",
    "sg:phone":"+32 51 30 31 10",
    "sg:postcode":"8870",
    "sg:province":"West-Vlaanderen",
    "wof:name":"Devlies & Zoon",
    "wof:placetype":"venue"
},
  "geometry": {"coordinates":[3.2226579189,50.9258956909],"type":"Point"}
}