{
  "type": "Feature",
  "properties": {
    "iso:country":"BE",
    "sg:address":"Chauss\u00e9e Des Forges 119",
    "sg:city":"Huy",
    "sg:classifiers":[
        {
            "category":"Retail",
            "subcategory":"Repair Shop",
            "type":"Services"
        }
    ],
    "sg:phone":"+32 85 25 33 15",
    "sg:postcode":"4500",
    "sg:province":"Li\u00e8ge",
    "sg:tags":[
        "-",
        "clothing",
        "alteration"
    ],
    "wof:name":"Fil D'annik (le)",
    "wof:placetype":"venue"
},
  "geometry": {"coordinates":[5.2392001152,50.5105323792],"type":"Point"}
}