{
  "type": "Feature",
  "properties": {
    "addr:full":"Rue Du Pont-quelin 6 Ath Hainaut 7800",
    "addr:housenumber":"6",
    "addr:postcode":"7800",
    "addr:street":"Rue Du Pont-Quelin",
    "iso:country":"BE",
    "sg:address":"Rue Du Pont-quelin 6",
    "sg:city":"Ath",
    "sg:orig_category":"Meubles D\u00e9taillants, Am\u00e9nagement de B\u00e2timents et de Cuisines",
    "sg:phone":"+32 68 28 20 89",
    "sg:postcode":"7800",
    "sg:province":"Hainaut",
    "wof:name":"Meubles Navez",
    "wof:placetype":"venue"
},
  "geometry": {"coordinates":[3.7778940201,50.6310882568],"type":"Point"}
}