{
  "type": "Feature",
  "properties": {
    "iso:country":"BE",
    "sg:address":"Grote Steenweg 66",
    "sg:city":"Zoutleeuw (dormaal)",
    "sg:classifiers":[
        {
            "category":"Health Services",
            "subcategory":"Doctor",
            "type":"Services"
        }
    ],
    "sg:phone":"+32 11 78 10 41",
    "sg:postcode":"3440",
    "sg:province":"Vlaams-Brabant",
    "sg:tags":[
        "medicinephysicians",
        "surgeon"
    ],
    "wof:name":"Aerts Anne",
    "wof:placetype":"venue"
},
  "geometry": {"coordinates":[5.1006708145,50.8073043823],"type":"Point"}
}