{
  "type": "Feature",
  "properties": {
    "addr:full":"J Van Rijkswijkln 82 Antwerpen Antwerpen 2018",
    "addr:housenumber":"82",
    "addr:postcode":"2018",
    "addr:street":"J;Rijkswijkln",
    "iso:country":"BE",
    "sg:address":"J Van Rijkswijkln 82",
    "sg:city":"Antwerpen",
    "sg:classifiers":[
        {
            "category":"Autos & Motor Vehicles",
            "subcategory":"Automobile Sales",
            "type":"Retail Goods"
        }
    ],
    "sg:phone":"+32 3 216 30 05",
    "sg:postcode":"2018",
    "sg:province":"Antwerpen",
    "sg:tags":[
        "equipment",
        "motor-cars",
        "transport"
    ],
    "wof:name":"Cargo Van International Nv",
    "wof:placetype":"venue"
},
  "geometry": {"coordinates":[4.4059782028,51.19713974],"type":"Point"}
}