{
  "type": "Feature",
  "properties": {
    "iso:country":"BE",
    "sg:address":"Berkenstraat 2",
    "sg:city":"Oostkamp",
    "sg:classifiers":[
        {
            "category":"Banks & Credit Unions",
            "subcategory":"Investment Brokerage",
            "type":"Services"
        }
    ],
    "sg:phone":"+32 50 36 01 96",
    "sg:postcode":"8020",
    "sg:province":"West-Vlaanderen",
    "sg:tags":[
        "repair",
        "-",
        "installation",
        "sanitary",
        "article"
    ],
    "wof:name":"Luickx Rudy Bvba",
    "wof:placetype":"venue"
},
  "geometry": {"coordinates":[3.2411999702,51.1773605347],"type":"Point"}
}