{
  "type": "Feature",
  "properties": {
    "addr:full":"Chauss\u00c9e De Nivelles 41 Gembloux Namur 5032",
    "addr:housenumber":"41",
    "addr:postcode":"5032",
    "addr:street":"Chausse\u0301E De Nivelles;Namur",
    "iso:country":"BE",
    "sg:address":"Chauss\u00c9e De Nivelles 41",
    "sg:city":"Gembloux",
    "sg:classifiers":[
        {
            "category":"Insurance",
            "subcategory":"Insurance Agent",
            "type":"Services"
        }
    ],
    "sg:phone":"+32 81 63 30 77",
    "sg:postcode":"5032",
    "sg:province":"Namur",
    "sg:tags":[
        "verzekeringsmakelaars",
        "expert"
    ],
    "wof:name":"Fe. Lefevre A. & M.",
    "wof:placetype":"venue"
},
  "geometry": {"coordinates":[4.6751971245,50.5128936768],"type":"Point"}
}