{
  "type": "Feature",
  "properties": {
    "iso:country":"BE",
    "sg:address":"Borreweidestraat 266",
    "sg:city":"Halle",
    "sg:orig_category":"Woningbouw",
    "sg:phone":"+32 2 361 24 42",
    "sg:postcode":"1502",
    "sg:province":"Vlaams-Brabant",
    "wof:name":"Cremers R. & Smulders P.",
    "wof:placetype":"venue"
},
  "geometry": {"coordinates":[4.1945672035,50.718132019],"type":"Point"}
}