{
  "type": "Feature",
  "properties": {
    "iso:country":"BE",
    "sg:address":"Sneppestraat 5",
    "sg:city":"Oostrozebeke",
    "sg:orig_category":"Elektrische installaties voor woningen",
    "sg:phone":"+32 51 40 80 50",
    "sg:postcode":"8780",
    "sg:province":"West-Vlaanderen",
    "wof:name":"Alain Thorrez",
    "wof:placetype":"venue"
},
  "geometry": {"coordinates":[3.3525679111,50.9442901611],"type":"Point"}
}