{
  "type": "Feature",
  "properties": {
    "iso:country":"BE",
    "sg:address":"Heirbaan 12",
    "sg:city":"Mortsel",
    "sg:orig_category":"Traitement and rev\u00eatement des m\u00e9taux",
    "sg:phone":"+32 3 440 58 88",
    "sg:postcode":"2640",
    "sg:province":"Antwerpen",
    "wof:name":"Witters",
    "wof:placetype":"venue"
},
  "geometry": {"coordinates":[4.4600491524,51.1773948669],"type":"Point"}
}