{
  "type": "Feature",
  "properties": {
    "iso:country":"BE",
    "sg:address":"Beverlaai 3",
    "sg:city":"Kortrijk",
    "sg:classifiers":[
        {
            "category":"Insurance",
            "subcategory":"Insurance Agent",
            "type":"Services"
        }
    ],
    "sg:phone":"+32 56 22 14 60",
    "sg:postcode":"8500",
    "sg:province":"West-Vlaanderen",
    "sg:tags":[
        "broker"
    ],
    "wof:name":"Atelia Kortrijk",
    "wof:placetype":"venue"
},
  "geometry": {"coordinates":[3.2678821087,50.8223342896],"type":"Point"}
}