{
  "type": "Feature",
  "properties": {
    "addr:full":"Gemeenteplein 44 Knokke-heist West-Vlaanderen 8300",
    "addr:housenumber":"44",
    "addr:postcode":"8300",
    "addr:street":"Gemeenteplein",
    "iso:country":"BE",
    "sg:address":"Gemeenteplein 44",
    "sg:city":"Knokke-heist",
    "sg:orig_category":"Textiel",
    "sg:phone":"+32 50 62 01 86",
    "sg:postcode":"8300",
    "sg:province":"West-Vlaanderen",
    "wof:name":"Gori Decor",
    "wof:placetype":"venue"
},
  "geometry": {"coordinates":[3.2913548946,51.3405761719],"type":"Point"}
}