{
  "type": "Feature",
  "properties": {
    "addr:full":"Clos De La Gibeci\u00e8re 11 Waterloo Brabant Wallon 1410",
    "addr:housenumber":"11",
    "addr:postcode":"1410",
    "addr:street":"Clos De La Gibecie\u0300Re",
    "iso:country":"BE",
    "sg:address":"Clos De La Gibeci\u00e8re 11",
    "sg:city":"Waterloo",
    "sg:classifiers":[
        {
            "category":"Health Services",
            "subcategory":"Health Practitioner",
            "type":"Services"
        }
    ],
    "sg:phone":"+32 2 354 36 72",
    "sg:postcode":"1410",
    "sg:province":"Brabant Wallon",
    "sg:tags":[
        "physiotherapist"
    ],
    "wof:name":"Pinte H",
    "wof:placetype":"venue"
},
  "geometry": {"coordinates":[4.4087052345,50.7267837524],"type":"Point"}
}