{
  "type": "Feature",
  "properties": {
    "addr:full":"Stokstraat 55 Zele Oost-Vlaanderen 9240",
    "addr:housenumber":"55",
    "addr:postcode":"9240",
    "addr:street":"Stokstraat",
    "iso:country":"BE",
    "sg:address":"Stokstraat 55",
    "sg:city":"Zele",
    "sg:orig_category":"Eleveurs de bovins",
    "sg:phone":"+32 52 44 68 94",
    "sg:postcode":"9240",
    "sg:province":"Oost-Vlaanderen",
    "wof:name":"Jan Certijn",
    "wof:placetype":"venue"
},
  "geometry": {"coordinates":[4.0260190964,51.0708045959],"type":"Point"}
}