{
  "type": "Feature",
  "properties": {
    "addr:full":"Rue Lombi\u00c8ry 14 Burdinne Li\u00e8ge 4210",
    "addr:housenumber":"14",
    "addr:postcode":"4210",
    "addr:street":"Rue Lombie\u0300Ry",
    "iso:country":"BE",
    "sg:address":"Rue Lombi\u00c8ry 14",
    "sg:city":"Burdinne",
    "sg:orig_category":"Rundveehouders",
    "sg:phone":"+32 85 71 28 76",
    "sg:postcode":"4210",
    "sg:province":"Li\u00e8ge",
    "wof:name":"Leon Leloup",
    "wof:placetype":"venue"
},
  "geometry": {"coordinates":[5.0699720383,50.5800018311],"type":"Point"}
}