{
  "type": "Feature",
  "properties": {
    "iso:country":"BE",
    "sg:address":"Frans Blanckaertdreef 2n",
    "sg:city":"Aalst",
    "sg:orig_category":"Cafetarias and selfservice restaurants",
    "sg:phone":"+32 53 78 37 47",
    "sg:postcode":"9300",
    "sg:province":"Oost-Vlaanderen",
    "wof:name":"Osbroeck",
    "wof:placetype":"venue"
},
  "geometry": {"coordinates":[4.0440759659,50.92760849],"type":"Point"}
}