{
  "type": "Feature",
  "properties": {
    "iso:country":"BE",
    "sg:address":"Gaverstraat 69",
    "sg:city":"Laarne (kalken)",
    "sg:classifiers":[
        {
            "category":"Food & Beverages",
            "subcategory":"Liquor & Beverages",
            "type":"Retail Goods"
        }
    ],
    "sg:phone":"+32 9 367 54 21",
    "sg:postcode":"9270",
    "sg:province":"Oost-Vlaanderen",
    "sg:tags":[
        "-",
        "spirit",
        "wine"
    ],
    "wof:name":"De Lausnay M",
    "wof:placetype":"venue"
},
  "geometry": {"coordinates":[3.9220199585,51.0414581299],"type":"Point"}
}