{
  "type": "Feature",
  "properties": {
    "iso:country":"BE",
    "sg:address":"Tuinwijk 28",
    "sg:city":"Mol",
    "sg:classifiers":[
        {
            "category":"Banks & Credit Unions",
            "subcategory":"Investment Brokerage",
            "type":"Services"
        }
    ],
    "sg:phone":"+32 14 32 45 45",
    "sg:postcode":"2400",
    "sg:province":"Antwerpen",
    "sg:tags":[
        "repair",
        "-",
        "installation",
        "sanitary",
        "article"
    ],
    "wof:name":"De Sleuvenkapper",
    "wof:placetype":"venue"
},
  "geometry": {"coordinates":[5.1442251205,51.2021636963],"type":"Point"}
}