{
  "type": "Feature",
  "properties": {
    "iso:country":"BE",
    "sg:address":"Rue Du Huit 1",
    "sg:city":"Fontaine-l'ev\u00caque",
    "sg:orig_category":"Boekhouders",
    "sg:phone":"+32 71 52 22 65",
    "sg:postcode":"6141",
    "sg:province":"Hainaut",
    "wof:name":"Thierry Cavrot",
    "wof:placetype":"venue"
},
  "geometry": {"coordinates":[4.325428009,50.4335136414],"type":"Point"}
}