{
  "type": "Feature",
  "properties": {
    "addr:full":"Wetterensteenweg 15 Wichelen (serskamp) Oost-Vlaanderen 9260",
    "addr:housenumber":"15",
    "addr:postcode":"9260",
    "addr:street":"Wetterensteenweg",
    "iso:country":"BE",
    "sg:address":"Wetterensteenweg 15",
    "sg:city":"Wichelen (serskamp)",
    "sg:classifiers":[
        {
            "category":"Shopping",
            "subcategory":"Clothing, Apparel, & Fashions",
            "type":"Retail Goods"
        }
    ],
    "sg:phone":"+32 9 369 15 69",
    "sg:postcode":"9260",
    "sg:province":"Oost-Vlaanderen",
    "sg:tags":[
        "clothing",
        "-",
        "gentleman"
    ],
    "wof:name":"Broeken Van Den Broecke",
    "wof:placetype":"venue"
},
  "geometry": {"coordinates":[3.920265913,50.9932746887],"type":"Point"}
}