{
  "type": "Feature",
  "properties": {
    "addr:full":"Boulevard De Smet De Naeyer 592 Bruxelles Bruxelles-Capitale 1020",
    "addr:housenumber":"592",
    "addr:postcode":"1020",
    "addr:street":"Boulevard De Smet De Naeyer",
    "iso:country":"BE",
    "sg:address":"Boulevard De Smet De Naeyer 592",
    "sg:city":"Bruxelles",
    "sg:classifiers":[
        {
            "category":"Wholesale",
            "subcategory":"Fruits & Vegetables",
            "type":"Manufacturing & Wholesale Goods"
        }
    ],
    "sg:phone":"+32 2 478 62 01",
    "sg:postcode":"1020",
    "sg:province":"Bruxelles-Capitale",
    "sg:tags":[
        "whol",
        "-"
    ],
    "wof:name":"Junius",
    "wof:placetype":"venue"
},
  "geometry": {"coordinates":[4.3425397873,50.8861961365],"type":"Point"}
}