{
  "type": "Feature",
  "properties": {
    "addr:full":"Avenue Huart Hamoir 115 Bruxelles (schaerbeek) Bruxelles-Capitale 1030",
    "addr:housenumber":"115",
    "addr:postcode":"1030",
    "addr:street":"Avenue Huart Hamoir",
    "iso:country":"BE",
    "sg:address":"Avenue Huart Hamoir 115",
    "sg:city":"Bruxelles (schaerbeek)",
    "sg:classifiers":[
        {
            "category":"Home & Garden",
            "subcategory":"Home Furnishings",
            "type":"Retail Goods"
        }
    ],
    "sg:phone":"+32 2 248 22 20",
    "sg:postcode":"1030",
    "sg:province":"Bruxelles-Capitale",
    "sg:tags":[
        "interior",
        "decoration"
    ],
    "wof:name":"Une Maison En Ville",
    "wof:placetype":"venue"
},
  "geometry": {"coordinates":[4.3847570419,50.8745918274],"type":"Point"}
}