{
  "type": "Feature",
  "properties": {
    "iso:country":"BE",
    "sg:address":"Ingelmunstersteenweg 58",
    "sg:city":"Oostrozebeke",
    "sg:orig_category":"Tankcleaning",
    "sg:phone":"+32 56 66 65 09",
    "sg:postcode":"8780",
    "sg:province":"West-Vlaanderen",
    "wof:name":"Truck & Tank Cleaning Tack Nv",
    "wof:placetype":"venue"
},
  "geometry": {"coordinates":[3.3162689209,50.9192771912],"type":"Point"}
}