{
  "type": "Feature",
  "properties": {
    "iso:country":"BE",
    "sg:address":"Rue De L'ecuelle 25",
    "sg:city":"Bruxelles",
    "sg:classifiers":[
        {
            "category":"Organizations",
            "subcategory":"Professional Association",
            "type":"Services"
        }
    ],
    "sg:phone":"+32 475 59 60 28",
    "sg:postcode":"1000",
    "sg:province":"Bruxelles-Capitale",
    "sg:tags":[
        "trade-union",
        "federation"
    ],
    "wof:name":"Association Nationale Des Accident\u00e9s De La Route Asbl",
    "wof:placetype":"venue"
},
  "geometry": {"coordinates":[4.3909392357,50.8481483459],"type":"Point"}
}