{
  "type": "Feature",
  "properties": {
    "addr:full":"Chauss\u00c9e De Tongres 85 Li\u00c8ge Li\u00e8ge 4000",
    "addr:housenumber":"85",
    "addr:postcode":"4000",
    "addr:street":"Chausse\u0301E De Tongres",
    "iso:country":"BE",
    "sg:address":"Chauss\u00c9e De Tongres 85",
    "sg:city":"Li\u00c8ge",
    "sg:classifiers":[
        {
            "category":"Restaurant",
            "type":"Food & Drink"
        }
    ],
    "sg:phone":"+32 4 226 67 68",
    "sg:postcode":"4000",
    "sg:province":"Li\u00e8ge",
    "sg:tags":[
        "caf\u00e9s"
    ],
    "wof:name":"Taverne G.b.",
    "wof:placetype":"venue"
},
  "geometry": {"coordinates":[5.5585308075,50.6661605835],"type":"Point"}
}