{
  "type": "Feature",
  "properties": {
    "addr:full":"Sint-christianastraat 25 Dendermonde Oost-Vlaanderen 9200",
    "addr:housenumber":"25",
    "addr:postcode":"9200",
    "addr:street":"Sint-Christianastraat;Oost-Vlaanderen",
    "iso:country":"BE",
    "sg:address":"Sint-christianastraat 25",
    "sg:city":"Dendermonde",
    "sg:classifiers":[
        {
            "category":"Professional",
            "subcategory":"Engineering",
            "type":"Services"
        }
    ],
    "sg:phone":"+32 52 21 37 23",
    "sg:postcode":"9200",
    "sg:province":"Oost-Vlaanderen",
    "sg:tags":[
        "environmental",
        "technique",
        "-"
    ],
    "wof:name":"S W B O Bvba",
    "wof:placetype":"venue"
},
  "geometry": {"coordinates":[4.0900101662,51.0324783325],"type":"Point"}
}