{
  "type": "Feature",
  "properties": {
    "iso:country":"BE",
    "sg:address":"Wijnveld 167",
    "sg:city":"Sinaai",
    "sg:orig_category":"Royal Canin. Animaux domestiques and accessoires",
    "sg:phone":"+32 3 772 35 00",
    "sg:postcode":"9112",
    "sg:province":"Oost-Vlaanderen",
    "wof:name":"Sylvester",
    "wof:placetype":"venue"
},
  "geometry": {"coordinates":[4.0549321175,51.1475334167],"type":"Point"}
}