{
  "type": "Feature",
  "properties": {
    "iso:country":"BE",
    "sg:address":"Heuvelstraat 44",
    "sg:city":"Leopoldsburg",
    "sg:orig_category":"Newspapers, magazines, periodicals - Distribution",
    "sg:phone":"+32 11 40 29 71",
    "sg:postcode":"3970",
    "sg:province":"Limburg",
    "wof:name":"Press-debo Cv",
    "wof:placetype":"venue"
},
  "geometry": {"coordinates":[5.2510547638,51.1186065674],"type":"Point"}
}