{
  "type": "Feature",
  "properties": {
    "addr:full":"Rue L'apleit 7 Huy Li\u00e8ge 4500",
    "addr:housenumber":"7",
    "addr:postcode":"4500",
    "addr:street":"Rue L'Apleit",
    "iso:country":"BE",
    "sg:address":"Rue L'apleit 7",
    "sg:city":"Huy",
    "sg:classifiers":[
        {
            "category":"Professional",
            "subcategory":"Art Services",
            "type":"Services"
        }
    ],
    "sg:phone":"+32 85 24 01 24",
    "sg:postcode":"4500",
    "sg:province":"Li\u00e8ge",
    "sg:tags":[
        "picture",
        "framer"
    ],
    "wof:name":"Cadr'apleit",
    "wof:placetype":"venue"
},
  "geometry": {"coordinates":[5.2401909828,50.5195999146],"type":"Point"}
}