{
  "type": "Feature",
  "properties": {
    "addr:full":"Rue De Havay 41 Binche Hainaut 7130",
    "addr:housenumber":"41",
    "addr:postcode":"7130",
    "addr:street":"Rue De Havay",
    "iso:country":"BE",
    "sg:address":"Rue De Havay 41",
    "sg:city":"Binche",
    "sg:orig_category":"Fleurs and plantes",
    "sg:phone":"+32 64 36 66 14",
    "sg:postcode":"7130",
    "sg:province":"Hainaut",
    "wof:name":"J.m.d Flor",
    "wof:placetype":"venue"
},
  "geometry": {"coordinates":[4.1819272041,50.4110336304],"type":"Point"}
}