{
  "type": "Feature",
  "properties": {
    "addr:full":"Rue Des Croisons 9 Mont-de-l'enclus (amougies) Hainaut 7750",
    "addr:housenumber":"9",
    "addr:postcode":"7750",
    "addr:street":"Rue Des Croisons;Amougies Hainaut",
    "iso:country":"BE",
    "sg:address":"Rue Des Croisons 9",
    "sg:city":"Mont-de-l'enclus (amougies)",
    "sg:classifiers":[
        {
            "category":"Social Services",
            "type":"Services"
        }
    ],
    "sg:phone":"+32 69 76 61 68",
    "sg:postcode":"7750",
    "sg:province":"Hainaut",
    "wof:name":"B.a.s.e.",
    "wof:placetype":"venue"
},
  "geometry": {"coordinates":[5.0023469925,50.3222923279],"type":"Point"}
}