{
  "type": "Feature",
  "properties": {
    "addr:full":"Rue St Sebastien 91 Herseaux Hainaut 7712",
    "addr:housenumber":"91",
    "addr:postcode":"7712",
    "addr:street":"Rue St Sebastien;Hainaut",
    "iso:country":"BE",
    "sg:address":"Rue St Sebastien 91",
    "sg:city":"Herseaux",
    "sg:orig_category":"Yamaha. R\u00e9parations and entretien de motos. Motos",
    "sg:phone":"+32 56 34 97 07",
    "sg:postcode":"7712",
    "sg:province":"Hainaut",
    "wof:name":"Top Bike S.a.",
    "wof:placetype":"venue"
},
  "geometry": {"coordinates":[3.2304179668,50.7261657715],"type":"Point"}
}