{
  "type": "Feature",
  "properties": {
    "addr:full":"Av. De For\u00cat De Soignes 371 Sint-genesius-rode/rhode-saint-genese Vlaams-Brabant 1640",
    "addr:housenumber":"371",
    "addr:postcode":"1640",
    "addr:street":"Av. De Fore\u0302T De Soignes",
    "iso:country":"BE",
    "sg:address":"Av. De For\u00cat De Soignes 371",
    "sg:city":"Sint-genesius-rode/rhode-saint-genese",
    "sg:orig_category":"Banques and organismes de cr\u00e9dit",
    "sg:phone":"+32 2 358 36 00",
    "sg:postcode":"1640",
    "sg:province":"Vlaams-Brabant",
    "wof:name":"Bbl",
    "wof:placetype":"venue"
},
  "geometry": {"coordinates":[4.3812241554,50.7580451965],"type":"Point"}
}