{
  "type": "Feature",
  "properties": {
    "iso:country":"BE",
    "sg:address":"Rue De Taillis-pr\u00c9 12",
    "sg:city":"Chatelet",
    "sg:orig_category":"Artsen and specialisten",
    "sg:phone":"+32 71 41 80 18",
    "sg:postcode":"6200",
    "sg:province":"Hainaut",
    "wof:name":"Rosa Costa",
    "wof:placetype":"venue"
},
  "geometry": {"coordinates":[4.506002903,50.4319953918],"type":"Point"}
}