{
  "type": "Feature",
  "properties": {
    "addr:full":"Langestraat 94 Kruibeke Oost-Vlaanderen 9150",
    "addr:housenumber":"94",
    "addr:postcode":"9150",
    "addr:street":"Langestraat",
    "iso:country":"BE",
    "sg:address":"Langestraat 94",
    "sg:city":"Kruibeke",
    "sg:orig_category":"Banques and organismes de cr\u00e9dit",
    "sg:phone":"+32 3 774 43 32",
    "sg:postcode":"9150",
    "sg:province":"Oost-Vlaanderen",
    "wof:name":"Kbc",
    "wof:placetype":"venue"
},
  "geometry": {"coordinates":[4.3150482178,51.1751861572],"type":"Point"}
}