{
  "type": "Feature",
  "properties": {
    "addr:full":"Rue Des Ecoles 107 Mons (obourg) Hainaut 7034",
    "addr:housenumber":"107",
    "addr:postcode":"7034",
    "addr:street":"Rue Des Ecoles",
    "iso:country":"BE",
    "sg:address":"Rue Des Ecoles 107",
    "sg:city":"Mons (obourg)",
    "sg:classifiers":[
        {
            "category":"Professional",
            "subcategory":"Management & Consulting",
            "type":"Services"
        }
    ],
    "sg:phone":"+32 65 34 97 06",
    "sg:postcode":"7034",
    "sg:province":"Hainaut",
    "sg:tags":[
        "consultant",
        "agency",
        "advertising"
    ],
    "wof:name":"Ac Pub Obourg",
    "wof:placetype":"venue"
},
  "geometry": {"coordinates":[4.0086159706,50.4765396118],"type":"Point"}
}