{
  "type": "Feature",
  "properties": {
    "iso:country":"BE",
    "sg:address":"Rue De L'ecole 2",
    "sg:city":"Lontzen/lontzen",
    "sg:classifiers":[
        {
            "category":"Cafe",
            "type":"Food & Drink"
        }
    ],
    "sg:phone":"+32 87 65 94 06",
    "sg:postcode":"4710",
    "sg:province":"Li\u00e8ge",
    "sg:tags":[
        "caf\u00e9s"
    ],
    "wof:name":"Maria Pons",
    "wof:placetype":"venue"
},
  "geometry": {"coordinates":[5.99229002,50.6763191223],"type":"Point"}
}