{
  "type": "Feature",
  "properties": {
    "addr:full":"Sint-jansplein 54 Antwerpen Antwerpen 2060",
    "addr:housenumber":"54",
    "addr:postcode":"2060",
    "addr:street":"Sint-Jansplein",
    "iso:country":"BE",
    "sg:address":"Sint-jansplein 54",
    "sg:city":"Antwerpen",
    "sg:classifiers":[
        {
            "category":"Cafe",
            "type":"Food & Drink"
        }
    ],
    "sg:phone":"+32 3 232 84 15",
    "sg:postcode":"2060",
    "sg:province":"Antwerpen",
    "sg:tags":[
        "caf\u00e9s"
    ],
    "wof:name":"Caf\u00c9 Den Beer",
    "wof:placetype":"venue"
},
  "geometry": {"coordinates":[4.4166941643,51.2252197266],"type":"Point"}
}