{
  "type": "Feature",
  "properties": {
    "addr:full":"Achter De Hoven 30 Bilzen Limburg 3740",
    "addr:housenumber":"30",
    "addr:postcode":"3740",
    "addr:street":"Achter De Hoven",
    "iso:country":"BE",
    "sg:address":"Achter De Hoven 30",
    "sg:city":"Bilzen",
    "sg:orig_category":"Kapsalons",
    "sg:phone":"+32 89 50 18 48",
    "sg:postcode":"3740",
    "sg:province":"Limburg",
    "wof:name":"Coiffure Carina",
    "wof:placetype":"venue"
},
  "geometry": {"coordinates":[5.4850311279,50.8844451904],"type":"Point"}
}