{
  "type": "Feature",
  "properties": {
    "iso:country":"BE",
    "sg:address":"Rue Du Laboratoire 43b17",
    "sg:city":"Charleroi",
    "sg:orig_category":"Advocaten and juridische adviseurs",
    "sg:phone":"+32 71 30 45 25",
    "sg:postcode":"6000",
    "sg:province":"Hainaut",
    "wof:name":"A. Pedalino",
    "wof:placetype":"venue"
},
  "geometry": {"coordinates":[4.4471960068,50.4124412537],"type":"Point"}
}