{
  "type": "Feature",
  "properties": {
    "iso:country":"BE",
    "sg:address":"Hamstraat 52",
    "sg:city":"Wetteren",
    "sg:orig_category":"Fotografen and fotostudio's",
    "sg:phone":"+32 9 369 31 27",
    "sg:postcode":"9230",
    "sg:province":"Oost-Vlaanderen",
    "wof:name":"Dirk De Pauw",
    "wof:placetype":"venue"
},
  "geometry": {"coordinates":[3.8684589863,51.0010566711],"type":"Point"}
}