{
  "type": "Feature",
  "properties": {
    "iso:country":"BE",
    "sg:address":"Lindestr. 121",
    "sg:city":"Alken",
    "sg:classifiers":[
        {
            "category":"Food & Beverages",
            "subcategory":"Groceries & Convenience Stores",
            "type":"Retail Goods"
        }
    ],
    "sg:phone":"+32 11 31 27 07",
    "sg:postcode":"3570",
    "sg:province":"Limburg",
    "sg:tags":[
        "product",
        "grain",
        "cereal",
        "related"
    ],
    "wof:name":"Vanco Bvba",
    "wof:placetype":"venue"
},
  "geometry": {"coordinates":[5.2657461166,50.8942871094],"type":"Point"}
}