{
  "type": "Feature",
  "properties": {
    "addr:full":"Bloemenstraat 18 Brugge West-Vlaanderen 8310",
    "addr:housenumber":"18",
    "addr:postcode":"8310",
    "addr:street":"Bloemenstraat",
    "iso:country":"BE",
    "sg:address":"Bloemenstraat 18",
    "sg:city":"Brugge",
    "sg:orig_category":"Meubles D\u00e9taillants, Am\u00e9nagement de B\u00e2timents et de Cuisines",
    "sg:phone":"+32 50 36 19 24",
    "sg:postcode":"8310",
    "sg:province":"West-Vlaanderen",
    "wof:name":"Marc Rosseel",
    "wof:placetype":"venue"
},
  "geometry": {"coordinates":[3.2394680977,51.1981582642],"type":"Point"}
}