{
  "type": "Feature",
  "properties": {
    "addr:full":"Emile Idiersstraat 37 Oudergem/auderghem Bruxelles-Capitale 1160",
    "addr:housenumber":"37",
    "addr:postcode":"1160",
    "addr:street":"Emile Idiersstraat;/",
    "iso:country":"BE",
    "sg:address":"Emile Idiersstraat 37",
    "sg:city":"Oudergem/auderghem",
    "sg:orig_category":"Overheidsdiensten",
    "sg:phone":"+32 2 676 49 01",
    "sg:postcode":"1160",
    "sg:province":"Bruxelles-Capitale",
    "wof:name":"C.p.a.s.",
    "wof:placetype":"venue"
},
  "geometry": {"coordinates":[4.4286608696,50.8172988892],"type":"Point"}
}