{
  "type": "Feature",
  "properties": {
    "addr:full":"Avenue Georges Henri 309 Bruxelles (woluwe-saint-lambert) Bruxelles-Capitale 1200",
    "addr:housenumber":"309",
    "addr:postcode":"1200",
    "addr:street":"Avenue Georges Henri",
    "iso:country":"BE",
    "sg:address":"Avenue Georges Henri 309",
    "sg:city":"Bruxelles (woluwe-saint-lambert)",
    "sg:classifiers":[
        {
            "category":"Retail",
            "subcategory":"Repair Shop",
            "type":"Services"
        }
    ],
    "sg:phone":"+32 2 733 57 69",
    "sg:postcode":"1200",
    "sg:province":"Bruxelles-Capitale",
    "sg:tags":[
        "-",
        "mainten",
        "watch",
        "clock"
    ],
    "wof:name":"Au Fil De L'heure",
    "wof:placetype":"venue"
},
  "geometry": {"coordinates":[4.4111981392,50.8433532715],"type":"Point"}
}