{
  "type": "Feature",
  "properties": {
    "iso:country":"BE",
    "sg:address":"Rue Jacques D\u00c9sira 2",
    "sg:city":"Awans",
    "sg:orig_category":"Varkenskwekers",
    "sg:phone":"+32 4 257 41 56",
    "sg:postcode":"4340",
    "sg:province":"Li\u00e8ge",
    "wof:name":"Vilenne Fran\u00c7ois & Fils",
    "wof:placetype":"venue"
},
  "geometry": {"coordinates":[5.4467720985,50.7022819519],"type":"Point"}
}