{
  "type": "Feature",
  "properties": {
    "addr:full":"Markgravestraat 10 Antwerpen Antwerpen 2000",
    "addr:housenumber":"10",
    "addr:postcode":"2000",
    "addr:street":"Markgravestraat",
    "iso:country":"BE",
    "sg:address":"Markgravestraat 10",
    "sg:city":"Antwerpen",
    "sg:orig_category":"Art and fournitures artistiques",
    "sg:phone":"+32 3 226 79 70",
    "sg:postcode":"2000",
    "sg:province":"Antwerpen",
    "wof:name":"Asian European Company",
    "wof:placetype":"venue"
},
  "geometry": {"coordinates":[4.4074721336,51.2205429077],"type":"Point"}
}