{
  "type": "Feature",
  "properties": {
    "addr:full":"Chaussee De Mons 55 Seneffe Hainaut 7180",
    "addr:housenumber":"55",
    "addr:postcode":"7180",
    "addr:street":"Chaussee De Mons",
    "iso:country":"BE",
    "sg:address":"Chaussee De Mons 55",
    "sg:city":"Seneffe",
    "sg:classifiers":[
        {
            "category":"Autos & Motor Vehicles",
            "subcategory":"Automobile Sales",
            "type":"Retail Goods"
        }
    ],
    "sg:phone":"+32 64 52 11 20",
    "sg:postcode":"7180",
    "sg:province":"Hainaut",
    "sg:tags":[
        "disabled",
        "aid",
        "persons'",
        "car"
    ],
    "wof:name":"Ardoullie S.a.",
    "wof:placetype":"venue"
},
  "geometry": {"coordinates":[4.2482089996,50.5175285339],"type":"Point"}
}