{
  "type": "Feature",
  "properties": {
    "iso:country":"BE",
    "sg:address":"Gistelsteenweg 382a",
    "sg:city":"Jabbeke",
    "sg:classifiers":[
        {
            "category":"Building & Trades",
            "subcategory":"Construction",
            "type":"Services"
        }
    ],
    "sg:phone":"+32 50 81 43 94",
    "sg:postcode":"8490",
    "sg:province":"West-Vlaanderen",
    "sg:tags":[
        "carpenter"
    ],
    "wof:name":"Denys Andy Bvba",
    "wof:placetype":"venue"
},
  "geometry": {"coordinates":[3.0791730881,51.1781082153],"type":"Point"}
}