{
  "type": "Feature",
  "properties": {
    "iso:country":"BE",
    "sg:address":"Slangenstraat 62",
    "sg:city":"Lubbeek",
    "sg:orig_category":"Installation \u00e9lectrique r\u00e9sidentielle",
    "sg:phone":"+32 16 25 32 74",
    "sg:postcode":"3210",
    "sg:province":"Vlaams-Brabant",
    "wof:name":"Bulinckx Motor Control",
    "wof:placetype":"venue"
},
  "geometry": {"coordinates":[4.7575631142,50.9032287598],"type":"Point"}
}