{
  "type": "Feature",
  "properties": {
    "iso:country":"BE",
    "sg:address":"R.emmanuel Van Driessche 74",
    "sg:city":"Elsene/ixelles",
    "sg:orig_category":"M\u00e9decins and sp\u00e9cialistes",
    "sg:phone":"+32 2 345 54 36",
    "sg:postcode":"1050",
    "sg:province":"Bruxelles-Capitale",
    "wof:name":"Z. Hecht",
    "wof:placetype":"venue"
},
  "geometry": {"coordinates":[4.3574490547,50.819355011],"type":"Point"}
}