{
  "type": "Feature",
  "properties": {
    "addr:full":"Weg Naar Zwartberg 187 Houthalen-helchteren (houthalen) Limburg 3530",
    "addr:housenumber":"187",
    "addr:postcode":"3530",
    "addr:street":"Weg Naar Zwartberg",
    "iso:country":"BE",
    "sg:address":"Weg Naar Zwartberg 187",
    "sg:city":"Houthalen-helchteren (houthalen)",
    "sg:classifiers":[
        {
            "category":"Military Area",
            "subcategory":"Air Force Base",
            "type":"Public Place"
        }
    ],
    "sg:phone":"+32 89 38 61 73",
    "sg:postcode":"3530",
    "sg:province":"Limburg",
    "sg:tags":[
        "fire",
        "protection"
    ],
    "wof:name":"Amcs Nv",
    "wof:placetype":"venue"
},
  "geometry": {"coordinates":[5.4786100388,51.018661499],"type":"Point"}
}