{
  "type": "Feature",
  "properties": {
    "addr:full":"Rue G\u00e9rardrie 37 Li\u00e8ge 1 Li\u00e8ge 4000",
    "addr:housenumber":"37;1",
    "addr:postcode":"4000",
    "addr:street":"Rue Ge\u0301Rardrie",
    "iso:country":"BE",
    "sg:address":"Rue G\u00e9rardrie 37",
    "sg:city":"Li\u00e8ge 1",
    "sg:classifiers":[
        {
            "category":"Cafe",
            "type":"Food & Drink"
        }
    ],
    "sg:phone":"+32 4 223 00 03",
    "sg:postcode":"4000",
    "sg:province":"Li\u00e8ge",
    "sg:tags":[
        "snack-bars"
    ],
    "wof:name":"Andr\u00e9 (maison)",
    "wof:placetype":"venue"
},
  "geometry": {"coordinates":[5.5742602348,50.6440734863],"type":"Point"}
}