{
  "type": "Feature",
  "properties": {
    "addr:full":"Assesteenweg 15 Zi Mollem Mollem Vlaams-Brabant 1730",
    "addr:housenumber":"15",
    "addr:postcode":"1730",
    "addr:street":"Assesteenweg;Mollem",
    "iso:country":"BE",
    "sg:address":"Assesteenweg 15 Zi Mollem",
    "sg:city":"Mollem",
    "sg:classifiers":[
        {
            "category":"Manufacturing",
            "subcategory":"Tools & Machinery",
            "type":"Manufacturing & Wholesale Goods"
        }
    ],
    "sg:phone":"+32 2 454 01 20",
    "sg:postcode":"1730",
    "sg:province":"Vlaams-Brabant",
    "sg:tags":[
        "metallurgy",
        "metalworking"
    ],
    "wof:name":"Beluma Nv",
    "wof:placetype":"venue"
},
  "geometry": {"coordinates":[4.2281098366,50.9326400757],"type":"Point"}
}