{
  "type": "Feature",
  "properties": {
    "addr:full":"Centrum 3 Herne Vlaams-Brabant 1540",
    "addr:housenumber":"3",
    "addr:postcode":"1540",
    "addr:street":"Centrum",
    "iso:country":"BE",
    "sg:address":"Centrum 3",
    "sg:city":"Herne",
    "sg:classifiers":[
        {
            "category":"Shopping",
            "subcategory":"Florist",
            "type":"Retail Goods"
        }
    ],
    "sg:phone":"+32 2 396 31 71",
    "sg:postcode":"1540",
    "sg:province":"Vlaams-Brabant",
    "wof:name":"Helianthus",
    "wof:placetype":"venue"
},
  "geometry": {"coordinates":[4.0279040337,50.7247848511],"type":"Point"}
}