{
  "type": "Feature",
  "properties": {
    "iso:country":"BE",
    "sg:address":"Overleiestraat 29",
    "sg:city":"Kortrijk",
    "sg:orig_category":"Non-Classified Establishments",
    "sg:phone":"+32 56 35 11 82",
    "sg:postcode":"8500",
    "sg:province":"West-Vlaanderen",
    "wof:name":"Bloeze (de)/dewerchin Noella",
    "wof:placetype":"venue"
},
  "geometry": {"coordinates":[3.2603559494,50.8325538635],"type":"Point"}
}