{
  "type": "Feature",
  "properties": {
    "addr:full":"Chauss\u00c9e De Ninove 621 Anderlecht/anderlecht Bruxelles-Capitale 1070",
    "addr:housenumber":"621",
    "addr:postcode":"1070",
    "addr:street":"Chausse\u0301E De Ninove",
    "iso:country":"BE",
    "sg:address":"Chauss\u00c9e De Ninove 621",
    "sg:city":"Anderlecht/anderlecht",
    "sg:orig_category":"Instituts de beaut\u00e9. Centres de relaxation and bien-\u00eatre",
    "sg:phone":"+32 2 414 18 68",
    "sg:postcode":"1070",
    "sg:province":"Bruxelles-Capitale",
    "wof:name":"Exotic Sun",
    "wof:placetype":"venue"
},
  "geometry": {"coordinates":[4.2984671593,50.8469963074],"type":"Point"}
}