{
  "type": "Feature",
  "properties": {
    "addr:full":"Dr\u00c8ve Du Bois Neuville 44 Neupre Li\u00e8ge 4121",
    "addr:housenumber":"44",
    "addr:postcode":"4121",
    "addr:street":"Dre\u0300Ve Du Bois Neuville",
    "iso:country":"BE",
    "sg:address":"Dr\u00c8ve Du Bois Neuville 44",
    "sg:city":"Neupre",
    "sg:orig_category":"Gespecialiseerde residenti\u00eble bouw Woningbouw",
    "sg:phone":"+32 4 371 90 88",
    "sg:postcode":"4121",
    "sg:province":"Li\u00e8ge",
    "wof:name":"Serge Derua",
    "wof:placetype":"venue"
},
  "geometry": {"coordinates":[5.4725022316,50.5505065918],"type":"Point"}
}