{
  "type": "Feature",
  "properties": {
    "addr:full":"Varentstraat 20 Rotselaar Vlaams-Brabant 3118",
    "addr:housenumber":"20",
    "addr:postcode":"3118",
    "addr:street":"Varentstraat",
    "iso:country":"BE",
    "sg:address":"Varentstraat 20",
    "sg:city":"Rotselaar",
    "sg:classifiers":[
        {
            "category":"Food & Beverages",
            "subcategory":"Fruits & Vegetables",
            "type":"Retail Goods"
        }
    ],
    "sg:phone":"+32 16 53 35 88",
    "sg:postcode":"3118",
    "sg:province":"Vlaams-Brabant",
    "sg:tags":[
        "groenten"
    ],
    "wof:name":"A. Van Cleynenbreugel",
    "wof:placetype":"venue"
},
  "geometry": {"coordinates":[4.6940898895,50.970489502],"type":"Point"}
}