{
  "type": "Feature",
  "properties": {
    "iso:country":"BE",
    "sg:address":"Rankenlaan 16",
    "sg:city":"Lanaken",
    "sg:classifiers":[
        {
            "category":"Health Services",
            "subcategory":"Health Practitioner",
            "type":"Services"
        }
    ],
    "sg:phone":"+32 89 72 29 58",
    "sg:postcode":"3620",
    "sg:province":"Limburg",
    "sg:tags":[
        "physiotherapist"
    ],
    "wof:name":"Verjans Patrick",
    "wof:placetype":"venue"
},
  "geometry": {"coordinates":[5.6554231644,50.89635849],"type":"Point"}
}