{
  "type": "Feature",
  "properties": {
    "addr:full":"Pannestraat 231a Veurne West-Vlaanderen 8630",
    "addr:housenumber":"231a",
    "addr:postcode":"8630",
    "addr:street":"Pannestraat",
    "iso:country":"BE",
    "sg:address":"Pannestraat 231a",
    "sg:city":"Veurne",
    "sg:orig_category":"Autombile concessionaires",
    "sg:phone":"+32 58 31 10 06",
    "sg:postcode":"8630",
    "sg:province":"West-Vlaanderen",
    "wof:name":"Hancke Cars Nv",
    "wof:placetype":"venue"
},
  "geometry": {"coordinates":[2.6404719353,51.0818061829],"type":"Point"}
}