{
  "type": "Feature",
  "properties": {
    "iso:country":"BE",
    "sg:address":"Lindestraat 50",
    "sg:city":"Oudenaarde",
    "sg:classifiers":[
        {
            "category":"Banks & Credit Unions",
            "subcategory":"Investment Brokerage",
            "type":"Services"
        }
    ],
    "sg:phone":"+32 55 31 12 11",
    "sg:postcode":"9700",
    "sg:province":"Oost-Vlaanderen",
    "sg:tags":[
        "repair",
        "-",
        "installation",
        "sanitary",
        "article"
    ],
    "wof:name":"Maes Warmte Nv",
    "wof:placetype":"venue"
},
  "geometry": {"coordinates":[3.6060099602,50.8566474915],"type":"Point"}
}