{
  "type": "Feature",
  "properties": {
    "addr:full":"Harten 19 Turnhout Antwerpen 2300",
    "addr:housenumber":"19",
    "addr:postcode":"2300",
    "addr:street":"Harten",
    "iso:country":"BE",
    "sg:address":"Harten 19",
    "sg:city":"Turnhout",
    "sg:orig_category":"Studios photographiques",
    "sg:phone":"+32 14 41 32 19",
    "sg:postcode":"2300",
    "sg:province":"Antwerpen",
    "wof:name":"Carolus Jongeneelen",
    "wof:placetype":"venue"
},
  "geometry": {"coordinates":[4.9187221527,51.3102340698],"type":"Point"}
}