{
  "type": "Feature",
  "properties": {
    "addr:full":"Antwerpsesteenweg 360 Sint-amandsberg Oost-Vlaanderen 9040",
    "addr:housenumber":"360",
    "addr:postcode":"9040",
    "addr:street":"Antwerpsesteenweg",
    "iso:country":"BE",
    "sg:address":"Antwerpsesteenweg 360",
    "sg:city":"Sint-amandsberg",
    "sg:orig_category":"Advocaten and juridische adviseurs Balie van Gent",
    "sg:phone":"+32 9 229 30 85",
    "sg:postcode":"9040",
    "sg:province":"Oost-Vlaanderen",
    "wof:name":"Bernaert Godelieve",
    "wof:placetype":"venue"
},
  "geometry": {"coordinates":[3.7489459515,51.0614051819],"type":"Point"}
}