{
  "type": "Feature",
  "properties": {
    "iso:country":"BE",
    "sg:address":"Vrijheidslaan 23",
    "sg:city":"Bree",
    "sg:orig_category":"Installatie van houten of kunststof schrijnwerk",
    "sg:phone":"+32 89 48 15 69",
    "sg:postcode":"3960",
    "sg:province":"Limburg",
    "wof:name":"Clijsters Arnold",
    "wof:placetype":"venue"
},
  "geometry": {"coordinates":[5.6015949249,51.1495056152],"type":"Point"}
}