{
  "type": "Feature",
  "properties": {
    "iso:country":"BE",
    "sg:address":"Lange Haag 3",
    "sg:city":"Aalst",
    "sg:orig_category":"Fleurs and plantes",
    "sg:phone":"+32 53 70 33 44",
    "sg:postcode":"9310",
    "sg:province":"Oost-Vlaanderen",
    "wof:name":"Willems Bart",
    "wof:placetype":"venue"
},
  "geometry": {"coordinates":[4.0589661598,50.9414710999],"type":"Point"}
}