{
  "type": "Feature",
  "properties": {
    "addr:full":"Nieuwpoortse Steenweg 73 Gistel West-Vlaanderen 8470",
    "addr:housenumber":"73",
    "addr:postcode":"8470",
    "addr:street":"Nieuwpoortse Steenweg",
    "iso:country":"BE",
    "sg:address":"Nieuwpoortse Steenweg 73",
    "sg:city":"Gistel",
    "sg:classifiers":[
        {
            "category":"Home & Garden",
            "subcategory":"Hardware",
            "type":"Retail Goods"
        }
    ],
    "sg:phone":"+32 59 80 00 03",
    "sg:postcode":"8470",
    "sg:province":"West-Vlaanderen",
    "sg:tags":[
        "gate",
        "opener",
        "door",
        "automatic"
    ],
    "wof:name":"Telegroup Bvba",
    "wof:placetype":"venue"
},
  "geometry": {"coordinates":[2.9578390121,51.1515541077],"type":"Point"}
}