{
  "type": "Feature",
  "properties": {
    "addr:full":"Rue De Lambusart 40 Farciennes Hainaut 6240",
    "addr:housenumber":"40",
    "addr:postcode":"6240",
    "addr:street":"Rue De Lambusart",
    "iso:country":"BE",
    "sg:address":"Rue De Lambusart 40",
    "sg:city":"Farciennes",
    "sg:classifiers":[
        {
            "category":"Bars & Pubs",
            "type":"Food & Drink"
        }
    ],
    "sg:phone":"+32 71 39 12 49",
    "sg:postcode":"6240",
    "sg:province":"Hainaut",
    "wof:name":"Elmas",
    "wof:placetype":"venue"
},
  "geometry": {"coordinates":[4.5368709564,50.4461364746],"type":"Point"}
}