{
  "type": "Feature",
  "properties": {
    "addr:full":"Kempischesteenweg 159 Hasselt Limburg 3500",
    "addr:housenumber":"159",
    "addr:postcode":"3500",
    "addr:street":"Kempischesteenweg",
    "iso:country":"BE",
    "sg:address":"Kempischesteenweg 159",
    "sg:city":"Hasselt",
    "sg:orig_category":"Voertuigen",
    "sg:phone":"+32 11 72 78 28",
    "sg:postcode":"3500",
    "sg:province":"Limburg",
    "wof:name":"Autoexpo",
    "wof:placetype":"venue"
},
  "geometry": {"coordinates":[5.3410100937,50.9384231567],"type":"Point"}
}