{
  "type": "Feature",
  "properties": {
    "addr:full":"Nestor De Ti\u00e8restraat 47-49 Aalst Oost-Vlaanderen 9300",
    "addr:postcode":"47-49;9300",
    "addr:street":"Nestor De Tie\u0300Restraat",
    "iso:country":"BE",
    "sg:address":"Nestor De Ti\u00e8restraat 47-49",
    "sg:city":"Aalst",
    "sg:classifiers":[
        {
            "category":"Shopping",
            "subcategory":"Clothing, Apparel, & Fashions",
            "type":"Retail Goods"
        }
    ],
    "sg:phone":"+32 53 77 44 87",
    "sg:postcode":"9300",
    "sg:province":"Oost-Vlaanderen",
    "sg:tags":[
        "-",
        "fur"
    ],
    "wof:name":"Van Nieuwenberg",
    "wof:placetype":"venue"
},
  "geometry": {"coordinates":[4.0319690704,50.9402542114],"type":"Point"}
}