{
  "type": "Feature",
  "properties": {
    "addr:full":"Rue Dohet 30 Walcourt (tarcienne) Namur 5651",
    "addr:housenumber":"30",
    "addr:postcode":"5651",
    "addr:street":"Rue Dohet",
    "iso:country":"BE",
    "sg:address":"Rue Dohet 30",
    "sg:city":"Walcourt (tarcienne)",
    "sg:classifiers":[
        {
            "category":"Health Services",
            "subcategory":"Nursing And Care Facility",
            "type":"Services"
        }
    ],
    "sg:phone":"+32 71 22 04 52",
    "sg:postcode":"5651",
    "sg:province":"Namur",
    "sg:tags":[
        "home",
        "rest"
    ],
    "wof:name":"Gestihome",
    "wof:placetype":"venue"
},
  "geometry": {"coordinates":[4.4792308807,50.3078231812],"type":"Point"}
}