{
  "type": "Feature",
  "properties": {
    "iso:country":"BE",
    "sg:address":"Schansstraat 66e",
    "sg:city":"Kortenaken",
    "sg:classifiers":[
        {
            "category":"Building & Trades",
            "subcategory":"Construction",
            "type":"Services"
        }
    ],
    "sg:phone":"+32 11 58 26 38",
    "sg:postcode":"3470",
    "sg:province":"Vlaams-Brabant",
    "sg:tags":[
        "stucco",
        "contractor"
    ],
    "wof:name":"Onbelet Gerry",
    "wof:placetype":"venue"
},
  "geometry": {"coordinates":[5.0716218948,50.9069900513],"type":"Point"}
}