{
  "type": "Feature",
  "properties": {
    "addr:full":"Tennisstraat 42 Beringen (koersel) Limburg 3582",
    "addr:housenumber":"42",
    "addr:postcode":"3582",
    "addr:street":"Tennisstraat",
    "iso:country":"BE",
    "sg:address":"Tennisstraat 42",
    "sg:city":"Beringen (koersel)",
    "sg:classifiers":[
        {
            "category":"Personal",
            "subcategory":"Beauty Salon",
            "type":"Services"
        }
    ],
    "sg:phone":"+32 11 42 63 85",
    "sg:postcode":"3582",
    "sg:province":"Limburg",
    "sg:tags":[
        "lady",
        "-",
        "hairdressing"
    ],
    "wof:name":"Therese",
    "wof:placetype":"venue"
},
  "geometry": {"coordinates":[5.215321064,51.0715560913],"type":"Point"}
}