{
  "type": "Feature",
  "properties": {
    "addr:full":"Rue Des Archives 124 Watermaal-bosvoorde/watermael-boitsfort Bruxelles-Capitale 1170",
    "addr:housenumber":"124",
    "addr:postcode":"1170",
    "addr:street":"Rue Des Archives",
    "iso:country":"BE",
    "sg:address":"Rue Des Archives 124",
    "sg:city":"Watermaal-bosvoorde/watermael-boitsfort",
    "sg:orig_category":"Agences de publicit\u00e9",
    "sg:phone":"+32 2 675 37 85",
    "sg:postcode":"1170",
    "sg:province":"Bruxelles-Capitale",
    "wof:name":"Corinne Legrand",
    "wof:placetype":"venue"
},
  "geometry": {"coordinates":[4.4022789001,50.8018722534],"type":"Point"}
}