{
  "type": "Feature",
  "properties": {
    "iso:country":"BE",
    "sg:address":"Lembekedorp 27",
    "sg:city":"Kaprijke",
    "sg:classifiers":[
        {
            "category":"Cafe",
            "type":"Food & Drink"
        }
    ],
    "sg:phone":"+32 9 377 90 03",
    "sg:postcode":"9971",
    "sg:province":"Oost-Vlaanderen",
    "sg:tags":[
        "caf\u00e9s"
    ],
    "wof:name":"Georgette Vanden Abeele",
    "wof:placetype":"venue"
},
  "geometry": {"coordinates":[3.6315310001,51.1950378418],"type":"Point"}
}