{
  "type": "Feature",
  "properties": {
    "iso:country":"BE",
    "sg:address":"Smalleheerweg 31",
    "sg:city":"Gent",
    "sg:classifiers":[
        {
            "category":"Autos & Motor Vehicles",
            "subcategory":"Automobile Sales",
            "type":"Retail Goods"
        }
    ],
    "sg:phone":"+32 9 250 42 11",
    "sg:postcode":"9041",
    "sg:province":"Oost-Vlaanderen",
    "sg:tags":[
        "equipment",
        "industrial",
        "transport"
    ],
    "wof:name":"Volvo Europa Truck Nv",
    "wof:placetype":"venue"
},
  "geometry": {"coordinates":[3.7917098999,51.0868797302],"type":"Point"}
}