{
  "type": "Feature",
  "properties": {
    "addr:full":"Quai De Gaulle 18 Li\u00c8ge Li\u00e8ge 4020",
    "addr:housenumber":"18",
    "addr:postcode":"4020",
    "addr:street":"Quai De Gaulle",
    "iso:country":"BE",
    "sg:address":"Quai De Gaulle 18",
    "sg:city":"Li\u00c8ge",
    "sg:orig_category":"M\u00e9decins and sp\u00e9cialistes",
    "sg:phone":"+32 4 344 19 81",
    "sg:postcode":"4020",
    "sg:province":"Li\u00e8ge",
    "wof:name":"Yves Rausin",
    "wof:placetype":"venue"
},
  "geometry": {"coordinates":[5.579228878,50.6417121887],"type":"Point"}
}