{
  "type": "Feature",
  "properties": {
    "iso:country":"BE",
    "sg:address":"Av Du Pont De Luttre 19-21",
    "sg:city":"Bruxelles",
    "sg:classifiers":[
        {
            "category":"Professional",
            "subcategory":"Business Services",
            "type":"Services"
        }
    ],
    "sg:phone":"+32 2 344 96 02",
    "sg:postcode":"1190",
    "sg:province":"Bruxelles-Capitale",
    "sg:tags":[
        "high-precision",
        "mechanic"
    ],
    "wof:name":"Tool And Record Industry S.p.r.l.",
    "wof:placetype":"venue"
},
  "geometry": {"coordinates":[4.3216161728,50.8208122253],"type":"Point"}
}