{
  "type": "Feature",
  "properties": {
    "addr:full":"Avenue Du Panth\u00e9on 103 Bruxelles (koekelberg) Bruxelles-Capitale 1081",
    "addr:housenumber":"103",
    "addr:postcode":"1081",
    "addr:street":"Avenue Du Panthe\u0301On",
    "iso:country":"BE",
    "sg:address":"Avenue Du Panth\u00e9on 103",
    "sg:city":"Bruxelles (koekelberg)",
    "sg:classifiers":[
        {
            "category":"Food & Beverages",
            "subcategory":"Specialty",
            "type":"Retail Goods"
        }
    ],
    "sg:phone":"+32 2 427 92 45",
    "sg:postcode":"1081",
    "sg:province":"Bruxelles-Capitale",
    "sg:tags":[
        "health",
        "dietary",
        "-",
        "biological"
    ],
    "wof:name":"Bl\u00e9 Germ\u00e9 (le)",
    "wof:placetype":"venue"
},
  "geometry": {"coordinates":[4.3145828247,50.8666381836],"type":"Point"}
}