{
  "type": "Feature",
  "properties": {
    "addr:full":"Oude Keerbergsebaan 14 Bonheiden (rijmenam) Antwerpen 2820",
    "addr:housenumber":"14",
    "addr:postcode":"2820",
    "addr:street":"Oude Keerbergsebaan",
    "iso:country":"BE",
    "sg:address":"Oude Keerbergsebaan 14",
    "sg:city":"Bonheiden (rijmenam)",
    "sg:classifiers":[
        {
            "category":"Communications",
            "subcategory":"Film & Video Production",
            "type":"Services"
        }
    ],
    "sg:phone":"+32 495 10 23 78",
    "sg:postcode":"2820",
    "sg:province":"Antwerpen",
    "sg:tags":[
        "multimedia",
        "-",
        "system"
    ],
    "wof:name":"Case Interactive Belgi\u00eb",
    "wof:placetype":"venue"
},
  "geometry": {"coordinates":[4.6018538475,51.0042991638],"type":"Point"}
}