{
  "type": "Feature",
  "properties": {
    "addr:full":"Duinenstraat 225b2 Bredene West-Vlaanderen 8450",
    "addr:housenumber":"225b2",
    "addr:postcode":"8450",
    "addr:street":"Duinenstraat",
    "iso:country":"BE",
    "sg:address":"Duinenstraat 225b2",
    "sg:city":"Bredene",
    "sg:classifiers":[
        {
            "category":"Taxi",
            "type":"Transportation"
        }
    ],
    "sg:phone":"+32 59 70 27 27",
    "sg:postcode":"8450",
    "sg:province":"West-Vlaanderen",
    "wof:name":"Johnny Barbe",
    "wof:placetype":"venue"
},
  "geometry": {"coordinates":[2.965200901,51.2429237366],"type":"Point"}
}