{
  "type": "Feature",
  "properties": {
    "iso:country":"BE",
    "sg:address":"Steenweg Op Jette 396",
    "sg:city":"Koekelberg/koekelberg",
    "sg:orig_category":"Industri\u00eble and commerci\u00eble bouw Woningbouw",
    "sg:phone":"+32 2 428 95 41",
    "sg:postcode":"1081",
    "sg:province":"Bruxelles-Capitale",
    "wof:name":"Balcaen & Fils",
    "wof:placetype":"venue"
},
  "geometry": {"coordinates":[4.3299951553,50.866985321],"type":"Point"}
}