{
  "type": "Feature",
  "properties": {
    "iso:country":"BE",
    "sg:address":"Bruulstraat 128",
    "sg:city":"Haaltert",
    "sg:orig_category":"Rundveehouders",
    "sg:phone":"+32 53 83 50 85",
    "sg:postcode":"9450",
    "sg:province":"Oost-Vlaanderen",
    "wof:name":"Roger Cautaert",
    "wof:placetype":"venue"
},
  "geometry": {"coordinates":[4.0008797646,50.9057884216],"type":"Point"}
}