{
  "type": "Feature",
  "properties": {
    "addr:full":"Chauss\u00e9e De Watermael 43 Bruxelles (auderghem) Bruxelles-Capitale 1160",
    "addr:housenumber":"43",
    "addr:postcode":"1160",
    "addr:street":"Chausse\u0301E De Watermael",
    "iso:country":"BE",
    "sg:address":"Chauss\u00e9e De Watermael 43",
    "sg:city":"Bruxelles (auderghem)",
    "sg:classifiers":[
        {
            "category":"Travel",
            "subcategory":"Travel Agent",
            "type":"Entertainment"
        }
    ],
    "sg:phone":"+32 2 672 16 64",
    "sg:postcode":"1160",
    "sg:province":"Bruxelles-Capitale",
    "sg:tags":[
        "agency"
    ],
    "wof:name":"P.n.y. Travel International Sa",
    "wof:placetype":"venue"
},
  "geometry": {"coordinates":[4.4190349579,50.817035675],"type":"Point"}
}