{
  "type": "Feature",
  "properties": {
    "addr:full":"Sint-genovevastraat 15 Riemst Limburg 3770",
    "addr:housenumber":"15",
    "addr:postcode":"3770",
    "addr:street":"Sint-Genovevastraat",
    "iso:country":"BE",
    "sg:address":"Sint-genovevastraat 15",
    "sg:city":"Riemst",
    "sg:orig_category":"Groententeelt",
    "sg:phone":"+32 12 45 77 72",
    "sg:postcode":"3770",
    "sg:province":"Limburg",
    "wof:name":"Johannes Geven",
    "wof:placetype":"venue"
},
  "geometry": {"coordinates":[5.6385540962,50.8017234802],"type":"Point"}
}