{
  "type": "Feature",
  "properties": {
    "iso:country":"BE",
    "sg:address":"Guido Gezellestraat 25",
    "sg:city":"Leopoldsburg",
    "sg:classifiers":[
        {
            "category":"Building & Trades",
            "subcategory":"Landscaping Services",
            "type":"Services"
        }
    ],
    "sg:phone":"+32 11 34 13 92",
    "sg:postcode":"3970",
    "sg:province":"Limburg",
    "sg:tags":[
        "gardening",
        "garden",
        "maintenance"
    ],
    "wof:name":"Diepvens & Zn",
    "wof:placetype":"venue"
},
  "geometry": {"coordinates":[5.2529587746,51.1407699585],"type":"Point"}
}