{
  "type": "Feature",
  "properties": {
    "iso:country":"BE",
    "sg:address":"Bosstraat 41",
    "sg:city":"Lummen (groot)",
    "sg:orig_category":"Onderdelen and accessoires voertuigen Gh",
    "sg:phone":"+32 13 53 91 60",
    "sg:postcode":"3560",
    "sg:province":"Limburg",
    "wof:name":"Hyundai Mobis",
    "wof:placetype":"venue"
},
  "geometry": {"coordinates":[5.2067251205,50.9955215454],"type":"Point"}
}