{
  "type": "Feature",
  "properties": {
    "addr:full":"Iepersestraat 16a Moorslede West-Vlaanderen 8890",
    "addr:housenumber":"16a",
    "addr:postcode":"8890",
    "addr:street":"Iepersestraat",
    "iso:country":"BE",
    "sg:address":"Iepersestraat 16a",
    "sg:city":"Moorslede",
    "sg:classifiers":[
        {
            "category":"Insurance",
            "subcategory":"Insurance Agent",
            "type":"Services"
        }
    ],
    "sg:phone":"+32 51 77 83 14",
    "sg:postcode":"8890",
    "sg:province":"West-Vlaanderen",
    "sg:tags":[
        "-",
        "representative"
    ],
    "wof:name":"Labaere Zakenkantoor",
    "wof:placetype":"venue"
},
  "geometry": {"coordinates":[3.0571630001,50.8890953064],"type":"Point"}
}