{
  "type": "Feature",
  "properties": {
    "addr:full":"Steenweg 109 Lanaken (rekem) Limburg 3621",
    "addr:housenumber":"109",
    "addr:postcode":"3621",
    "addr:street":"Steenweg",
    "iso:country":"BE",
    "sg:address":"Steenweg 109",
    "sg:city":"Lanaken (rekem)",
    "sg:classifiers":[
        {
            "category":"Bakery",
            "type":"Food & Drink"
        }
    ],
    "sg:phone":"+32 89 71 45 49",
    "sg:postcode":"3621",
    "sg:province":"Limburg",
    "sg:tags":[
        "confectioner",
        "baker"
    ],
    "wof:name":"Kusters O",
    "wof:placetype":"venue"
},
  "geometry": {"coordinates":[5.6846580505,50.9199790955],"type":"Point"}
}