{
  "type": "Feature",
  "properties": {
    "addr:full":"De Meerkens 13 Ravels Antwerpen 2382",
    "addr:housenumber":"13",
    "addr:postcode":"2382",
    "addr:street":"De Meerkens",
    "iso:country":"BE",
    "sg:address":"De Meerkens 13",
    "sg:city":"Ravels",
    "sg:orig_category":"D\u00e9chets and d\u00e9bris Gr",
    "sg:phone":"+32 14 65 83 22",
    "sg:postcode":"2382",
    "sg:province":"Antwerpen",
    "wof:name":"Fa. Mauritsz",
    "wof:placetype":"venue"
},
  "geometry": {"coordinates":[5.041768074,51.4469108582],"type":"Point"}
}