{
  "type": "Feature",
  "properties": {
    "iso:country":"BE",
    "sg:address":"Rue De Jolimont 146",
    "sg:city":"Manage (la Hestre)",
    "sg:classifiers":[
        {
            "category":"Home & Garden",
            "subcategory":"Hardware",
            "type":"Retail Goods"
        }
    ],
    "sg:phone":"+32 64 22 54 03",
    "sg:postcode":"7170",
    "sg:province":"Hainaut",
    "sg:tags":[
        "soldering",
        "equipment",
        "welding",
        "-",
        "supply"
    ],
    "wof:name":"Soudures & D\u00e9coupes Sprl",
    "wof:placetype":"venue"
},
  "geometry": {"coordinates":[4.2300848961,50.4769477844],"type":"Point"}
}