{
  "type": "Feature",
  "properties": {
    "iso:country":"BE",
    "sg:address":"Rue Ren\u00c9 M\u00c9nada 53",
    "sg:city":"Beauvechain",
    "sg:orig_category":"Location de voitures",
    "sg:phone":"+32 10 86 01 00",
    "sg:postcode":"1320",
    "sg:province":"Brabant Wallon",
    "wof:name":"De Troyer Guido",
    "wof:placetype":"venue"
},
  "geometry": {"coordinates":[4.7088079453,50.7791557312],"type":"Point"}
}