{
  "type": "Feature",
  "properties": {
    "addr:full":"Sint-jakobsstraat 15-17 Brugge West-Vlaanderen 8000",
    "addr:postcode":"15-17;8000",
    "addr:street":"Sint-Jakobsstraat",
    "iso:country":"BE",
    "sg:address":"Sint-jakobsstraat 15-17",
    "sg:city":"Brugge",
    "sg:classifiers":[
        {
            "category":"Health Services",
            "subcategory":"Health Practitioner",
            "type":"Services"
        }
    ],
    "sg:phone":"+32 50 33 93 88",
    "sg:postcode":"8000",
    "sg:province":"West-Vlaanderen",
    "sg:tags":[
        "physiotherapist"
    ],
    "wof:name":"Priem Herman",
    "wof:placetype":"venue"
},
  "geometry": {"coordinates":[3.222069025,51.2094345093],"type":"Point"}
}