{
  "type": "Feature",
  "properties": {
    "addr:full":"Rue Rempart Saint-joseph 34 Edingen/enghien Hainaut 7850",
    "addr:housenumber":"34",
    "addr:postcode":"7850",
    "addr:street":"Rue Rempart Saint-Joseph",
    "iso:country":"BE",
    "sg:address":"Rue Rempart Saint-joseph 34",
    "sg:city":"Edingen/enghien",
    "sg:orig_category":"IJzerwaren, bouw- and verfmaterialen Installatie van metalen schrijnwerk",
    "sg:phone":"+32 2 395 56 06",
    "sg:postcode":"7850",
    "sg:province":"Hainaut",
    "wof:name":"Hobby Wielant",
    "wof:placetype":"venue"
},
  "geometry": {"coordinates":[4.0376210213,50.6966781616],"type":"Point"}
}