{
  "type": "Feature",
  "properties": {
    "iso:country":"BE",
    "sg:address":"Avenue Monbijou 15",
    "sg:city":"Malmedy/malmedy",
    "sg:orig_category":"V\u00e9t\u00e9rinaires",
    "sg:phone":"+32 80 33 01 80",
    "sg:postcode":"4960",
    "sg:province":"Li\u00e8ge",
    "wof:name":"Robert Denis",
    "wof:placetype":"venue"
},
  "geometry": {"coordinates":[6.0551772118,50.37657547],"type":"Point"}
}