{
  "type": "Feature",
  "properties": {
    "iso:country":"BE",
    "sg:address":"Sanderusstraat 36",
    "sg:city":"Antwerpen",
    "sg:orig_category":"Artistes ind\u00e9pendants",
    "sg:phone":"+32 3 216 27 76",
    "sg:postcode":"2018",
    "sg:province":"Antwerpen",
    "wof:name":"Mia Grijp",
    "wof:placetype":"venue"
},
  "geometry": {"coordinates":[4.4049887657,51.2080001831],"type":"Point"}
}