{
  "type": "Feature",
  "properties": {
    "iso:country":"BE",
    "sg:address":"Tapstraat 12",
    "sg:city":"Kortessem",
    "sg:classifiers":[
        {
            "category":"Education",
            "subcategory":"School",
            "type":"Public Place"
        }
    ],
    "sg:phone":"+32 11 37 92 16",
    "sg:postcode":"3720",
    "sg:province":"Limburg",
    "sg:tags":[
        "secondary"
    ],
    "wof:name":"Secundaire School Voor Onderwijs De Dageraad",
    "wof:placetype":"venue"
},
  "geometry": {"coordinates":[5.3894309998,50.8619537354],"type":"Point"}
}