{
  "type": "Feature",
  "properties": {
    "iso:country":"BE",
    "sg:address":"Museumstraat 2",
    "sg:city":"Antwerpen",
    "sg:classifiers":[
        {
            "category":"Professional",
            "subcategory":"Engineering",
            "type":"Services"
        }
    ],
    "sg:phone":"+32 3 270 75 50",
    "sg:postcode":"2000",
    "sg:province":"Antwerpen",
    "sg:tags":[
        "-"
    ],
    "wof:name":"Instaumat",
    "wof:placetype":"venue"
},
  "geometry": {"coordinates":[4.3914680481,51.209941864],"type":"Point"}
}