{
  "type": "Feature",
  "properties": {
    "addr:full":"Rue Du Wainage 117 Fleurus (lambusart) Hainaut 6220",
    "addr:housenumber":"117",
    "addr:postcode":"6220",
    "addr:street":"Rue Du Wainage",
    "iso:country":"BE",
    "sg:address":"Rue Du Wainage 117",
    "sg:city":"Fleurus (lambusart)",
    "sg:classifiers":[
        {
            "category":"Professional",
            "subcategory":"Art Services",
            "type":"Services"
        }
    ],
    "sg:phone":"+32 71 88 80 88",
    "sg:postcode":"6220",
    "sg:province":"Hainaut",
    "sg:tags":[
        "automobile",
        "transit",
        "-",
        "export",
        "import"
    ],
    "wof:name":"Belgian Golden Car",
    "wof:placetype":"venue"
},
  "geometry": {"coordinates":[4.5596108437,50.4570999146],"type":"Point"}
}