{
  "type": "Feature",
  "properties": {
    "iso:country":"BE",
    "sg:address":"Rue Sainte-barbe 49",
    "sg:city":"Ch\u00c2telet",
    "sg:orig_category":"Mat\u00e9riel m\u00e9dical and orthop\u00e9dique and proth\u00e8ses Fab",
    "sg:phone":"+32 71 38 89 91",
    "sg:postcode":"6200",
    "sg:province":"Hainaut",
    "wof:name":"Francois Bourtembourg",
    "wof:placetype":"venue"
},
  "geometry": {"coordinates":[4.5247321129,50.402179718],"type":"Point"}
}