{
  "type": "Feature",
  "properties": {
    "iso:country":"BE",
    "sg:address":"Chauss\u00e9e De Gand 637",
    "sg:city":"Bruxelles (molenbeek-saint-jean)",
    "sg:classifiers":[
        {
            "category":"Banks & Credit Unions",
            "subcategory":"Investment Brokerage",
            "type":"Services"
        }
    ],
    "sg:phone":"+32 2 468 13 60",
    "sg:postcode":"1080",
    "sg:province":"Bruxelles-Capitale",
    "sg:tags":[
        "pump",
        "industrial",
        "-"
    ],
    "wof:name":"Hibon International Sa",
    "wof:placetype":"venue"
},
  "geometry": {"coordinates":[4.305164814,50.8609313965],"type":"Point"}
}