{
  "type": "Feature",
  "properties": {
    "iso:country":"BE",
    "sg:address":"Boulevard Industriel 14",
    "sg:city":"Anderlecht",
    "sg:orig_category":"Messageries. Agences d'exp\u00e9dition",
    "sg:phone":"+32 2 556 62 11",
    "sg:postcode":"1070",
    "sg:province":"Bruxelles-Capitale",
    "wof:name":"A.b.x. Logistics",
    "wof:placetype":"venue"
},
  "geometry": {"coordinates":[4.3150200844,50.827709198],"type":"Point"}
}