{
  "type": "Feature",
  "properties": {
    "addr:full":"Erasmuslaan 30 Kortrijk West-Vlaanderen 8500",
    "addr:housenumber":"30",
    "addr:postcode":"8500",
    "addr:street":"Erasmuslaan",
    "iso:country":"BE",
    "sg:address":"Erasmuslaan 30",
    "sg:city":"Kortrijk",
    "sg:orig_category":"Produits pharmaceutiques Gr",
    "sg:phone":"+32 56 22 32 27",
    "sg:postcode":"8500",
    "sg:province":"West-Vlaanderen",
    "wof:name":"Visiodata",
    "wof:placetype":"venue"
},
  "geometry": {"coordinates":[3.2839310169,50.8101119995],"type":"Point"}
}