{
  "type": "Feature",
  "properties": {
    "addr:full":"Nachtegaalstraat 37 Herk-de-stad (berbroek) Limburg 3540",
    "addr:housenumber":"37",
    "addr:postcode":"3540",
    "addr:street":"Nachtegaalstraat",
    "iso:country":"BE",
    "sg:address":"Nachtegaalstraat 37",
    "sg:city":"Herk-de-stad (berbroek)",
    "sg:classifiers":[
        {
            "category":"Retail",
            "subcategory":"Storage",
            "type":"Services"
        }
    ],
    "sg:phone":"+32 13 55 37 20",
    "sg:postcode":"3540",
    "sg:province":"Limburg",
    "sg:tags":[
        "rack",
        "system"
    ],
    "wof:name":"Metal Rek System Bvba",
    "wof:placetype":"venue"
},
  "geometry": {"coordinates":[5.1659698486,50.9407691956],"type":"Point"}
}