{
  "type": "Feature",
  "properties": {
    "addr:full":"Beukheuvel 48 Lier Antwerpen 2500",
    "addr:housenumber":"48",
    "addr:postcode":"2500",
    "addr:street":"Beukheuvel",
    "iso:country":"BE",
    "sg:address":"Beukheuvel 48",
    "sg:city":"Lier",
    "sg:orig_category":"Entretien and r\u00e9parations de voitures. Stations-service and carburants. V\u00e9hicules automobiles",
    "sg:phone":"+32 15 31 21 55",
    "sg:postcode":"2500",
    "sg:province":"Antwerpen",
    "wof:name":"Garage Germaine",
    "wof:placetype":"venue"
},
  "geometry": {"coordinates":[4.5788440704,51.0855674744],"type":"Point"}
}