{
  "type": "Feature",
  "properties": {
    "iso:country":"BE",
    "sg:address":"Avenue Du Diamant",
    "sg:city":"Brussel/bruxelles",
    "sg:orig_category":"Radioproductie and uitzendingen",
    "sg:phone":"+32 2 732 40 71",
    "sg:postcode":"1030",
    "sg:province":"Bruxelles-Capitale",
    "wof:name":"T\u00c9l\u00c9vision 2 Suedoise Svt2",
    "wof:placetype":"venue"
},
  "geometry": {"coordinates":[4.3914952278,50.8532295227],"type":"Point"}
}