{
  "type": "Feature",
  "properties": {
    "addr:full":"Sint-adriaanstraat 137 Haacht Vlaams-Brabant 3150",
    "addr:housenumber":"137",
    "addr:postcode":"3150",
    "addr:street":"Sint-Adriaanstraat",
    "iso:country":"BE",
    "sg:address":"Sint-adriaanstraat 137",
    "sg:city":"Haacht",
    "sg:orig_category":"Zuivelproducten",
    "sg:phone":"+32 16 60 20 85",
    "sg:postcode":"3150",
    "sg:province":"Vlaams-Brabant",
    "wof:name":"Huis Bosmans",
    "wof:placetype":"venue"
},
  "geometry": {"coordinates":[4.6215457916,50.9825897217],"type":"Point"}
}