{
  "type": "Feature",
  "properties": {
    "addr:full":"Langenbend 3 Raeren Li\u00e8ge 4730",
    "addr:housenumber":"3",
    "addr:postcode":"4730",
    "addr:street":"Langenbend",
    "iso:country":"BE",
    "sg:address":"Langenbend 3",
    "sg:city":"Raeren",
    "sg:classifiers":[
        {
            "category":"Building & Trades",
            "subcategory":"Construction",
            "type":"Services"
        }
    ],
    "sg:phone":"+32 87 85 15 76",
    "sg:postcode":"4730",
    "sg:province":"Li\u00e8ge",
    "sg:tags":[
        "carpenter"
    ],
    "wof:name":"Klinkenberg W",
    "wof:placetype":"venue"
},
  "geometry": {"coordinates":[6.1256871223,50.667930603],"type":"Point"}
}