{
  "type": "Feature",
  "properties": {
    "iso:country":"BE",
    "sg:address":"Kroonstraat 20",
    "sg:city":"Kalmthout",
    "sg:orig_category":"Etablissements Erotiques",
    "sg:phone":"+32 3 667 34 86",
    "sg:postcode":"2920",
    "sg:province":"Antwerpen",
    "wof:name":"Achiel Oerlemans",
    "wof:placetype":"venue"
},
  "geometry": {"coordinates":[4.5150351524,51.4292221069],"type":"Point"}
}