{
  "type": "Feature",
  "properties": {
    "addr:full":"Tramstraat 2a Aalst Oost-Vlaanderen 9300",
    "addr:housenumber":"2a",
    "addr:postcode":"9300",
    "addr:street":"Tramstraat",
    "iso:country":"BE",
    "sg:address":"Tramstraat 2a",
    "sg:city":"Aalst",
    "sg:classifiers":[
        {
            "category":"Sports & Exercise",
            "subcategory":"Sports Center",
            "type":"Entertainment"
        }
    ],
    "sg:phone":"+32 53 77 86 86",
    "sg:postcode":"9300",
    "sg:province":"Oost-Vlaanderen",
    "sg:tags":[
        "club",
        "article",
        "de",
        "camping"
    ],
    "wof:name":"Duikcentrum Padi-vvw",
    "wof:placetype":"venue"
},
  "geometry": {"coordinates":[4.0401978493,50.9458351135],"type":"Point"}
}