{
  "type": "Feature",
  "properties": {
    "iso:country":"BE",
    "sg:address":"Rue Des Tendeurs 48",
    "sg:city":"Li\u00c8ge",
    "sg:orig_category":"Artistes ind\u00e9pendants",
    "sg:phone":"+32 4 227 40 43",
    "sg:postcode":"4000",
    "sg:province":"Li\u00e8ge",
    "wof:name":"Serge Swysen",
    "wof:placetype":"venue"
},
  "geometry": {"coordinates":[5.5685768127,50.6658210754],"type":"Point"}
}