{
  "type": "Feature",
  "properties": {
    "iso:country":"BE",
    "sg:address":"Grasmarkt 7",
    "sg:city":"Brussel/bruxelles",
    "sg:orig_category":"Diverse intermediaire producten Gh Juwelen and horloges",
    "sg:phone":"+32 2 512 02 20",
    "sg:postcode":"1000",
    "sg:province":"Bruxelles-Capitale",
    "wof:name":"Joaillier Bourgeois",
    "wof:placetype":"venue"
},
  "geometry": {"coordinates":[4.3521580696,50.8480758667],"type":"Point"}
}