{
  "type": "Feature",
  "properties": {
    "addr:full":"Beukenlaan 4b4 Hoeselt Limburg 3730",
    "addr:housenumber":"4b4",
    "addr:postcode":"3730",
    "addr:street":"Beukenlaan",
    "iso:country":"BE",
    "sg:address":"Beukenlaan 4b4",
    "sg:city":"Hoeselt",
    "sg:classifiers":[
        {
            "category":"Food & Beverages",
            "subcategory":"Fruits & Vegetables",
            "type":"Retail Goods"
        }
    ],
    "sg:phone":"+32 89 51 14 80",
    "sg:postcode":"3730",
    "sg:province":"Limburg",
    "sg:tags":[
        "l\u00e9gumes"
    ],
    "wof:name":"Kurt Briers",
    "wof:placetype":"venue"
},
  "geometry": {"coordinates":[5.4850702286,50.8490104675],"type":"Point"}
}