{
  "type": "Feature",
  "properties": {
    "iso:country":"BE",
    "sg:address":"Kasteellaan 63",
    "sg:city":"Dilbeek",
    "sg:classifiers":[
        {
            "category":"Arena",
            "subcategory":"Sports Club",
            "type":"Entertainment"
        }
    ],
    "sg:phone":"+32 2 466 69 55",
    "sg:postcode":"1702",
    "sg:province":"Vlaams-Brabant",
    "sg:tags":[
        "de"
    ],
    "wof:name":"W.c. Het Vliegend Wiel",
    "wof:placetype":"venue"
},
  "geometry": {"coordinates":[4.2542791367,50.8731384277],"type":"Point"}
}