{
  "type": "Feature",
  "properties": {
    "addr:full":"Rue De Pont 11 Brunehaut Hainaut 7620",
    "addr:housenumber":"11",
    "addr:postcode":"7620",
    "addr:street":"Rue De Pont",
    "iso:country":"BE",
    "sg:address":"Rue De Pont 11",
    "sg:city":"Brunehaut",
    "sg:orig_category":"P\u00e9pini\u00e9ristes",
    "sg:phone":"+32 69 34 60 41",
    "sg:postcode":"7620",
    "sg:province":"Hainaut",
    "wof:name":"Freddy Delannoy",
    "wof:placetype":"venue"
},
  "geometry": {"coordinates":[3.3896329403,50.5341835022],"type":"Point"}
}