{
  "type": "Feature",
  "properties": {
    "iso:country":"BE",
    "sg:address":"F\u00e9ronstr\u00e9e 110",
    "sg:city":"Li\u00e8ge 1",
    "sg:classifiers":[
        {
            "category":"Food & Beverages",
            "subcategory":"Groceries & Convenience Stores",
            "type":"Retail Goods"
        }
    ],
    "sg:phone":"+32 4 221 36 20",
    "sg:postcode":"4000",
    "sg:province":"Li\u00e8ge",
    "sg:tags":[
        "grocer"
    ],
    "wof:name":"Nazna Store",
    "wof:placetype":"venue"
},
  "geometry": {"coordinates":[5.5816087723,50.6468734741],"type":"Point"}
}