{
  "type": "Feature",
  "properties": {
    "addr:full":"Zoning Industriel Perwez Brabant Wallon 1360",
    "addr:postcode":"1360",
    "addr:street":"Zoning Industriel",
    "iso:country":"BE",
    "sg:address":"Zoning Industriel",
    "sg:city":"Perwez",
    "sg:classifiers":[
        {
            "category":"Banks & Credit Unions",
            "subcategory":"Investment Brokerage",
            "type":"Services"
        }
    ],
    "sg:phone":"+32 81 56 80 07",
    "sg:postcode":"1360",
    "sg:province":"Brabant Wallon",
    "sg:tags":[
        "coil",
        "electric",
        "winding"
    ],
    "wof:name":"Atelec",
    "wof:placetype":"venue"
},
  "geometry": {"coordinates":[4.8146052361,50.6239395142],"type":"Point"}
}