{
  "type": "Feature",
  "properties": {
    "iso:country":"BE",
    "sg:address":"Sprietstraat 7",
    "sg:city":"Ardooie",
    "sg:classifiers":[
        {
            "category":"Real Estate",
            "subcategory":"Surveying",
            "type":"Services"
        }
    ],
    "sg:phone":"+32 476 98 54 22",
    "sg:postcode":"8850",
    "sg:province":"West-Vlaanderen",
    "sg:tags":[
        "surveyor",
        "land"
    ],
    "wof:name":"Vanhaverbeke K",
    "wof:placetype":"venue"
},
  "geometry": {"coordinates":[3.1904489994,50.9777107239],"type":"Point"}
}