{
  "type": "Feature",
  "properties": {
    "iso:country":"BE",
    "sg:address":"Haachtse Steenweg 48-50",
    "sg:city":"Diegem",
    "sg:orig_category":"Microsoft. Ordinateurs and \u00e9quipement informatique",
    "sg:phone":"+32 2 725 60 43",
    "sg:postcode":"1831",
    "sg:province":"Vlaams-Brabant",
    "wof:name":"Everaert",
    "wof:placetype":"venue"
},
  "geometry": {"coordinates":[4.4376878738,50.8989257812],"type":"Point"}
}