{
  "type": "Feature",
  "properties": {
    "iso:country":"BE",
    "sg:address":"Paddeschootdreef 49",
    "sg:city":"Sint-niklaas",
    "sg:classifiers":[
        {
            "category":"Shopping",
            "subcategory":"Clothing, Apparel, & Fashions",
            "type":"Retail Goods"
        }
    ],
    "sg:phone":"+32 3 777 66 06",
    "sg:postcode":"9100",
    "sg:province":"Oost-Vlaanderen",
    "sg:tags":[
        "textile",
        "clothing",
        "clothes"
    ],
    "wof:name":"De Flo-mesot J. Bvba",
    "wof:placetype":"venue"
},
  "geometry": {"coordinates":[4.1297659874,51.1690254211],"type":"Point"}
}