{
  "type": "Feature",
  "properties": {
    "iso:country":"BE",
    "sg:address":"Reningheersdijk 5",
    "sg:city":"Alveringem",
    "sg:orig_category":"Eleveurs de bovins. Eleveurs and marchands de porcs",
    "sg:phone":"+32 58 29 94 17",
    "sg:postcode":"8691",
    "sg:province":"West-Vlaanderen",
    "wof:name":"Michael Selschotter",
    "wof:placetype":"venue"
},
  "geometry": {"coordinates":[2.638710022,50.9423332214],"type":"Point"}
}