{
  "type": "Feature",
  "properties": {
    "iso:country":"BE",
    "sg:address":"Constantin Meunierstraat 107b101",
    "sg:city":"Leuven",
    "sg:orig_category":"Binnenhuisarchitecten",
    "sg:phone":"+32 16 23 11 75",
    "sg:postcode":"3000",
    "sg:province":"Vlaams-Brabant",
    "wof:name":"Joris Van Ermen",
    "wof:placetype":"venue"
},
  "geometry": {"coordinates":[4.7016701698,50.8704071045],"type":"Point"}
}