{
  "type": "Feature",
  "properties": {
    "addr:full":"Sint-truidensesteenweg 252 Tienen Vlaams-Brabant 3300",
    "addr:housenumber":"252",
    "addr:postcode":"3300",
    "addr:street":"Sint-Truidensesteenweg",
    "iso:country":"BE",
    "sg:address":"Sint-truidensesteenweg 252",
    "sg:city":"Tienen",
    "sg:classifiers":[
        {
            "category":"Wholesale",
            "subcategory":"Farm Supplies",
            "type":"Manufacturing & Wholesale Goods"
        }
    ],
    "sg:phone":"+32 16 80 54 32",
    "sg:postcode":"3300",
    "sg:province":"Vlaams-Brabant",
    "sg:tags":[
        "-",
        "machine",
        "equipment",
        "engineering",
        "machinery",
        "mechanical",
        "agriculture"
    ],
    "wof:name":"Eurogarden Nv",
    "wof:placetype":"venue"
},
  "geometry": {"coordinates":[4.9668111801,50.7999076843],"type":"Point"}
}