{
  "type": "Feature",
  "properties": {
    "addr:full":"Sint-pietersaalststraat 17 Gent Oost-Vlaanderen 9000",
    "addr:housenumber":"17",
    "addr:postcode":"9000",
    "addr:street":"Sint-Pietersaalststraat;Oost-Vlaanderen",
    "iso:country":"BE",
    "sg:address":"Sint-pietersaalststraat 17",
    "sg:city":"Gent",
    "sg:orig_category":"Schoonheidssalons",
    "sg:phone":"+32 9 222 18 43",
    "sg:postcode":"9000",
    "sg:province":"Oost-Vlaanderen",
    "wof:name":"De Groote",
    "wof:placetype":"venue"
},
  "geometry": {"coordinates":[3.7144379616,51.0310440063],"type":"Point"}
}