{
  "type": "Feature",
  "properties": {
    "iso:country":"BE",
    "sg:address":"Bosstraat 28",
    "sg:city":"Sint-katelijne-waver",
    "sg:classifiers":[
        {
            "category":"Restaurant",
            "type":"Food & Drink"
        }
    ],
    "sg:phone":"+32 15 75 58 10",
    "sg:postcode":"2861",
    "sg:province":"Antwerpen",
    "wof:name":"Ijs Margo",
    "wof:placetype":"venue"
},
  "geometry": {"coordinates":[4.580491066,51.0644187927],"type":"Point"}
}