{
  "type": "Feature",
  "properties": {
    "addr:full":"Grensstraat 32 Hechtel-eksel (eksel) Limburg 3941",
    "addr:housenumber":"32",
    "addr:postcode":"3941",
    "addr:street":"Grensstraat",
    "iso:country":"BE",
    "sg:address":"Grensstraat 32",
    "sg:city":"Hechtel-eksel (eksel)",
    "sg:classifiers":[
        {
            "category":"Professional",
            "subcategory":"Management & Consulting",
            "type":"Services"
        }
    ],
    "sg:phone":"+32 11 80 95 61",
    "sg:postcode":"3941",
    "sg:province":"Limburg",
    "sg:tags":[
        "tax-consultants"
    ],
    "wof:name":"Agten S",
    "wof:placetype":"venue"
},
  "geometry": {"coordinates":[5.4021282196,51.1625137329],"type":"Point"}
}