{
  "type": "Feature",
  "properties": {
    "iso:country":"BE",
    "sg:address":"Bergstraat 18",
    "sg:city":"Meeuwen-gruitrode",
    "sg:orig_category":"Artsen and specialisten",
    "sg:phone":"+32 11 79 18 77",
    "sg:postcode":"3670",
    "sg:province":"Limburg",
    "wof:name":"Gilbert Vandervoort",
    "wof:placetype":"venue"
},
  "geometry": {"coordinates":[5.518889904,51.1006774902],"type":"Point"}
}