{
  "type": "Feature",
  "properties": {
    "addr:full":"Aalstersestraat 65c Lebbeke (wieze) Oost-Vlaanderen 9280",
    "addr:housenumber":"65c",
    "addr:postcode":"9280",
    "addr:street":"Aalstersestraat",
    "iso:country":"BE",
    "sg:address":"Aalstersestraat 65c",
    "sg:city":"Lebbeke (wieze)",
    "sg:classifiers":[
        {
            "category":"Building & Trades",
            "subcategory":"Pest Control",
            "type":"Services"
        }
    ],
    "sg:phone":"+32 53 70 46 09",
    "sg:postcode":"9280",
    "sg:province":"Oost-Vlaanderen",
    "sg:tags":[
        "painting",
        "contractor"
    ],
    "wof:name":"Hiel B",
    "wof:placetype":"venue"
},
  "geometry": {"coordinates":[4.1099300385,50.987159729],"type":"Point"}
}