{
  "type": "Feature",
  "properties": {
    "iso:country":"BE",
    "sg:address":"Rittenweg 51",
    "sg:city":"Opglabbeek",
    "sg:classifiers":[
        {
            "category":"Retail",
            "subcategory":"Auto Repair",
            "type":"Services"
        }
    ],
    "sg:phone":"+32 89 85 68 73",
    "sg:postcode":"3660",
    "sg:province":"Limburg",
    "sg:tags":[
        "garage"
    ],
    "wof:name":"Baeten J",
    "wof:placetype":"venue"
},
  "geometry": {"coordinates":[5.6101350784,51.046913147],"type":"Point"}
}