{
  "type": "Feature",
  "properties": {
    "iso:country":"BE",
    "sg:address":"Oude Dorpsweg 72",
    "sg:city":"Jabbeke (varsenare)",
    "sg:classifiers":[
        {
            "category":"Bakery",
            "type":"Food & Drink"
        }
    ],
    "sg:phone":"+32 50 38 84 61",
    "sg:postcode":"8490",
    "sg:province":"West-Vlaanderen",
    "sg:tags":[
        "confectioner",
        "baker"
    ],
    "wof:name":"Tavernier H",
    "wof:placetype":"venue"
},
  "geometry": {"coordinates":[3.0896129608,51.1819725037],"type":"Point"}
}