{
  "type": "Feature",
  "properties": {
    "iso:country":"BE",
    "sg:address":"Rue Du Chemin De Fer 14",
    "sg:city":"Wavre",
    "sg:orig_category":"Alimentation sp\u00e9cialis\u00e9e",
    "sg:phone":"+32 10 22 28 80",
    "sg:postcode":"1300",
    "sg:province":"Brabant Wallon",
    "wof:name":"Comptoir Des Caf\u00c9s",
    "wof:placetype":"venue"
},
  "geometry": {"coordinates":[4.6078619957,50.7165527344],"type":"Point"}
}