{
  "type": "Feature",
  "properties": {
    "addr:full":"Ieperstraat 83 Poperinge West-Vlaanderen 8970",
    "addr:housenumber":"83",
    "addr:postcode":"8970",
    "addr:street":"Ieperstraat",
    "iso:country":"BE",
    "sg:address":"Ieperstraat 83",
    "sg:city":"Poperinge",
    "sg:classifiers":[
        {
            "category":"Professional",
            "subcategory":"Testing Lab",
            "type":"Services"
        }
    ],
    "sg:phone":"+32 57 33 32 17",
    "sg:postcode":"8970",
    "sg:province":"West-Vlaanderen",
    "sg:tags":[
        "chemist"
    ],
    "wof:name":"Van Acker P",
    "wof:placetype":"venue"
},
  "geometry": {"coordinates":[2.7314488888,50.8543128967],"type":"Point"}
}