{
  "type": "Feature",
  "properties": {
    "iso:country":"BE",
    "sg:address":"Rue Du Vieux Puits 4",
    "sg:city":"Hamois",
    "sg:orig_category":"Installatie van houten of kunststof schrijnwerk",
    "sg:phone":"+32 83 61 25 14",
    "sg:postcode":"5364",
    "sg:province":"Namur",
    "wof:name":"Jean-luc Dryon",
    "wof:placetype":"venue"
},
  "geometry": {"coordinates":[5.1297922134,50.3757896423],"type":"Point"}
}