{
  "type": "Feature",
  "properties": {
    "addr:full":"Village 52 Stoumont Li\u00e8ge 4987",
    "addr:housenumber":"52",
    "addr:postcode":"4987",
    "iso:country":"BE",
    "sg:address":"Village 52",
    "sg:city":"Stoumont",
    "sg:classifiers":[
        {
            "category":"Wholesale",
            "subcategory":"Fruits & Vegetables",
            "type":"Manufacturing & Wholesale Goods"
        }
    ],
    "sg:phone":"+32 80 78 54 56",
    "sg:postcode":"4987",
    "sg:province":"Li\u00e8ge",
    "sg:tags":[
        "whol",
        "-"
    ],
    "wof:name":"Goffin",
    "wof:placetype":"venue"
},
  "geometry": {"coordinates":[5.805729866,50.4068183899],"type":"Point"}
}