{
  "type": "Feature",
  "properties": {
    "iso:country":"BE",
    "sg:address":"Kattestraat 72",
    "sg:city":"Kruibeke",
    "sg:classifiers":[
        {
            "category":"Community Center",
            "subcategory":"Youth",
            "type":"Public Place"
        }
    ],
    "sg:phone":"+32 3 774 58 67",
    "sg:postcode":"9150",
    "sg:province":"Oost-Vlaanderen",
    "sg:tags":[
        "club"
    ],
    "wof:name":"Jeugdhuis Ter Walle Vzw",
    "wof:placetype":"venue"
},
  "geometry": {"coordinates":[4.3066430092,51.1720428467],"type":"Point"}
}