{
  "type": "Feature",
  "properties": {
    "addr:full":"Rue De Waltzing 19 Arlon Luxembourg 6700",
    "addr:housenumber":"19",
    "addr:postcode":"6700",
    "addr:street":"Rue De Waltzing",
    "iso:country":"BE",
    "sg:address":"Rue De Waltzing 19",
    "sg:city":"Arlon",
    "sg:orig_category":"Fa\u00e7ade covering",
    "sg:phone":"+32 63 22 81 79",
    "sg:postcode":"6700",
    "sg:province":"Luxembourg",
    "wof:name":"Angonese J-m",
    "wof:placetype":"venue"
},
  "geometry": {"coordinates":[5.8253211975,49.684803009],"type":"Point"}
}