{
  "type": "Feature",
  "properties": {
    "iso:country":"BE",
    "sg:address":"Rue Des Meuniers 5",
    "sg:city":"La Louvi\u00e8re (haine-saint-pierre)",
    "sg:classifiers":[
        {
            "category":"Sports & Exercise",
            "subcategory":"Stables",
            "type":"Entertainment"
        }
    ],
    "sg:phone":"+32 64 46 08 79",
    "sg:postcode":"7100",
    "sg:province":"Hainaut",
    "sg:tags":[
        "riding",
        "school"
    ],
    "wof:name":"Ecurie Des Oliviers",
    "wof:placetype":"venue"
},
  "geometry": {"coordinates":[4.2155280113,50.4732437134],"type":"Point"}
}