{
  "type": "Feature",
  "properties": {
    "iso:country":"BE",
    "sg:address":"7",
    "sg:city":"Grandplace 1400 Nivelles",
    "sg:classifiers":[
        {
            "category":"Travel",
            "subcategory":"Hotels & Motels",
            "type":"Entertainment"
        }
    ],
    "sg:phone":"+32 67 21 12 41",
    "sg:postcode":"7",
    "sg:tags":[
        "hotels",
        "business",
        "restaurant"
    ],
    "wof:name":"Arcoma Sprl (hotel Du Commerce)",
    "wof:placetype":"venue"
},
  "geometry": {"coordinates":[4.3228898048,50.5969848633],"type":"Point"}
}