{
  "type": "Feature",
  "properties": {
    "iso:country":"BE",
    "sg:address":"Rue Notre-dame Du Sommeil 83",
    "sg:city":"Bruxelles",
    "sg:classifiers":[
        {
            "category":"Arts & Performance",
            "subcategory":"Theater",
            "type":"Entertainment"
        }
    ],
    "sg:phone":"+32 2 502 24 42",
    "sg:postcode":"1000",
    "sg:province":"Bruxelles-Capitale",
    "sg:tags":[
        "group",
        "theatre"
    ],
    "wof:name":"Dito'dito Vzw",
    "wof:placetype":"venue"
},
  "geometry": {"coordinates":[4.3399572372,50.8503913879],"type":"Point"}
}