{
  "type": "Feature",
  "properties": {
    "addr:full":"Tongerlostraat 10 Westerlo (oevel) Antwerpen 2260",
    "addr:housenumber":"10",
    "addr:postcode":"2260",
    "addr:street":"Tongerlostraat",
    "iso:country":"BE",
    "sg:address":"Tongerlostraat 10",
    "sg:city":"Westerlo (oevel)",
    "sg:classifiers":[
        {
            "category":"Professional",
            "subcategory":"Lawyer & Legal Services",
            "type":"Services"
        }
    ],
    "sg:phone":"+32 14 23 45 64",
    "sg:postcode":"2260",
    "sg:province":"Antwerpen",
    "wof:name":"Buts W",
    "wof:placetype":"venue"
},
  "geometry": {"coordinates":[4.9038491249,51.1353797913],"type":"Point"}
}