{
  "type": "Feature",
  "properties": {
    "addr:full":"Rue De La Mairie 4 Huy Li\u00e8ge 4500",
    "addr:housenumber":"4",
    "addr:postcode":"4500",
    "addr:street":"Rue De La Mairie",
    "iso:country":"BE",
    "sg:address":"Rue De La Mairie 4",
    "sg:city":"Huy",
    "sg:classifiers":[
        {
            "category":"Building & Trades",
            "subcategory":"Landscaping Services",
            "type":"Services"
        }
    ],
    "sg:phone":"+32 85 23 21 27",
    "sg:postcode":"4500",
    "sg:province":"Li\u00e8ge",
    "sg:tags":[
        "etude",
        "technique",
        "ing\u00e9nierie"
    ],
    "wof:name":"Paul Lefebvre",
    "wof:placetype":"venue"
},
  "geometry": {"coordinates":[5.2604541779,50.5283241272],"type":"Point"}
}