{
  "type": "Feature",
  "properties": {
    "addr:full":"Avenue Des Foug\u00e8res 21 Wezembeek-oppem Vlaams-Brabant 1970",
    "addr:housenumber":"21",
    "addr:postcode":"1970",
    "addr:street":"Avenue Des Fouge\u0300Res",
    "iso:country":"BE",
    "sg:address":"Avenue Des Foug\u00e8res 21",
    "sg:city":"Wezembeek-oppem",
    "sg:classifiers":[
        {
            "category":"Health Services",
            "subcategory":"Dentist",
            "type":"Services"
        }
    ],
    "sg:phone":"+32 2 784 22 22",
    "sg:postcode":"1970",
    "sg:province":"Vlaams-Brabant",
    "wof:name":"Spaens Ilona",
    "wof:placetype":"venue"
},
  "geometry": {"coordinates":[4.4855699539,50.8341941833],"type":"Point"}
}