{
  "type": "Feature",
  "properties": {
    "iso:country":"BE",
    "sg:address":"Nolimpark 2403",
    "sg:city":"Overpelt",
    "sg:orig_category":"Magasins de r\u00e9parations d'articles personnels et m\u00e9nagers divers",
    "sg:phone":"+32 11 80 15 16",
    "sg:postcode":"3900",
    "sg:province":"Limburg",
    "wof:name":"Key-guard Morse Watchman",
    "wof:placetype":"venue"
},
  "geometry": {"coordinates":[5.4235649109,51.2117614746],"type":"Point"}
}