{
  "type": "Feature",
  "properties": {
    "addr:full":"Winterslagstraat 40b5 Genk Limburg 3600",
    "addr:housenumber":"40b5",
    "addr:postcode":"3600",
    "addr:street":"Winterslagstraat",
    "iso:country":"BE",
    "sg:address":"Winterslagstraat 40b5",
    "sg:city":"Genk",
    "sg:orig_category":"Chaussures",
    "sg:phone":"+32 89 35 90 03",
    "sg:postcode":"3600",
    "sg:province":"Limburg",
    "wof:name":"Poels",
    "wof:placetype":"venue"
},
  "geometry": {"coordinates":[5.4990701675,50.9659118652],"type":"Point"}
}