{
  "type": "Feature",
  "properties": {
    "addr:full":"Chemin De L\u00b4ecasse/ City Nord Gosselies Hainaut 6041",
    "addr:postcode":"6041",
    "addr:street":"Chemin De L\u00b4Ecasse / City Nord;Hainaut",
    "iso:country":"BE",
    "sg:address":"Chemin De L\u00b4ecasse/ City Nord",
    "sg:city":"Gosselies",
    "sg:orig_category":"Rev\u00eatements de sols and murs. Eclairage et \u00e9quipements du foyer. Articles de jardin",
    "sg:phone":"+32 71 35 55 50",
    "sg:postcode":"6041",
    "sg:province":"Hainaut",
    "wof:name":"Kwantum",
    "wof:placetype":"venue"
},
  "geometry": {"coordinates":[4.4314317703,50.4685935974],"type":"Point"}
}