{
  "type": "Feature",
  "properties": {
    "addr:full":"Chemin-rue 9 Malmedy Li\u00e8ge 4960",
    "addr:housenumber":"9",
    "addr:postcode":"4960",
    "addr:street":"Chemin-Rue",
    "iso:country":"BE",
    "sg:address":"Chemin-rue 9",
    "sg:city":"Malmedy",
    "sg:orig_category":"RESTAURANTS: LIVRAISON \u00c0 DOMICILE. RESTAURANTS",
    "sg:phone":"+32 80 77 04 65",
    "sg:postcode":"4960",
    "sg:province":"Li\u00e8ge",
    "wof:name":"Maison De Charlotte",
    "wof:placetype":"venue"
},
  "geometry": {"coordinates":[6.0277352333,50.4251174927],"type":"Point"}
}