{
  "type": "Feature",
  "properties": {
    "addr:full":"Kruisstraat 12 Kampenhout Vlaams-Brabant 1910",
    "addr:housenumber":"12",
    "addr:postcode":"1910",
    "addr:street":"Kruisstraat",
    "iso:country":"BE",
    "sg:address":"Kruisstraat 12",
    "sg:city":"Kampenhout",
    "sg:orig_category":"V\u00e9hicules automobiles",
    "sg:phone":"+32 16 65 57 52",
    "sg:postcode":"1910",
    "sg:province":"Vlaams-Brabant",
    "wof:name":"Boghemans",
    "wof:placetype":"venue"
},
  "geometry": {"coordinates":[4.5544838905,50.924911499],"type":"Point"}
}