{
  "type": "Feature",
  "properties": {
    "iso:country":"BE",
    "sg:address":"Quai De Rome 1",
    "sg:city":"Li\u00e8ge 1",
    "sg:classifiers":[
        {
            "category":"Industrial Area",
            "type":"Public Place"
        }
    ],
    "sg:phone":"+32 2 202 41 11",
    "sg:postcode":"4000",
    "sg:province":"Li\u00e8ge",
    "sg:tags":[
        "large",
        "private"
    ],
    "wof:name":"Belgacom Sa",
    "wof:placetype":"venue"
},
  "geometry": {"coordinates":[4.3573651314,50.8603782654],"type":"Point"}
}