{
  "type": "Feature",
  "properties": {
    "addr:full":"Esenweg 72 Diksmuide West-Vlaanderen 8600",
    "addr:housenumber":"72",
    "addr:postcode":"8600",
    "addr:street":"Esenweg",
    "iso:country":"BE",
    "sg:address":"Esenweg 72",
    "sg:city":"Diksmuide",
    "sg:classifiers":[
        {
            "category":"Retail",
            "subcategory":"Auto Repair",
            "type":"Services"
        }
    ],
    "sg:phone":"+32 51 50 25 01",
    "sg:postcode":"8600",
    "sg:province":"West-Vlaanderen",
    "sg:tags":[
        "breakdown",
        "automobile",
        "-",
        "recovery"
    ],
    "wof:name":"Durie Fernand Bvba Depannage",
    "wof:placetype":"venue"
},
  "geometry": {"coordinates":[2.8752219677,51.0320892334],"type":"Point"}
}