{
  "type": "Feature",
  "properties": {
    "iso:country":"BE",
    "sg:address":"Fijfelweg 9",
    "sg:city":"Aalst",
    "sg:classifiers":[
        {
            "category":"Cafe",
            "type":"Food & Drink"
        }
    ],
    "sg:phone":"+32 53 21 19 32",
    "sg:postcode":"9310",
    "sg:province":"Oost-Vlaanderen",
    "sg:tags":[
        "caf\u00e9s"
    ],
    "wof:name":"Hans Corthals",
    "wof:placetype":"venue"
},
  "geometry": {"coordinates":[4.0975861549,50.9523735046],"type":"Point"}
}