{
  "type": "Feature",
  "properties": {
    "addr:full":"Ieperstraat 207 Menen West-Vlaanderen 8930",
    "addr:housenumber":"207",
    "addr:postcode":"8930",
    "addr:street":"Ieperstraat",
    "iso:country":"BE",
    "sg:address":"Ieperstraat 207",
    "sg:city":"Menen",
    "sg:orig_category":"G\u00e9om\u00e8tres",
    "sg:phone":"+32 475 59 88 69",
    "sg:postcode":"8930",
    "sg:province":"West-Vlaanderen",
    "wof:name":"Virginie Debuck",
    "wof:placetype":"venue"
},
  "geometry": {"coordinates":[3.1097700596,50.7998313904],"type":"Point"}
}