{
  "type": "Feature",
  "properties": {
    "addr:full":"Vinkenstraat 14 Kasterlee Antwerpen 2460",
    "addr:housenumber":"14",
    "addr:postcode":"2460",
    "addr:street":"Vinkenstraat",
    "iso:country":"BE",
    "sg:address":"Vinkenstraat 14",
    "sg:city":"Kasterlee",
    "sg:classifiers":[
        {
            "category":"Restaurant",
            "type":"Food & Drink"
        }
    ],
    "sg:phone":"+32 14 55 64 28",
    "sg:postcode":"2460",
    "sg:province":"Antwerpen",
    "sg:tags":[
        "caf\u00e9s"
    ],
    "wof:name":"Sint Rochushoeve",
    "wof:placetype":"venue"
},
  "geometry": {"coordinates":[4.9017000198,51.2060585022],"type":"Point"}
}