{
  "type": "Feature",
  "properties": {
    "addr:full":"Louis De Naeyerplein 23 Willebroek Antwerpen 2830",
    "addr:housenumber":"23",
    "addr:postcode":"2830",
    "addr:street":"Louis De Naeyerplein",
    "iso:country":"BE",
    "sg:address":"Louis De Naeyerplein 23",
    "sg:city":"Willebroek",
    "sg:classifiers":[
        {
            "category":"Cafe",
            "type":"Food & Drink"
        }
    ],
    "sg:phone":"+32 3 886 31 99",
    "sg:postcode":"2830",
    "sg:province":"Antwerpen",
    "sg:tags":[
        "caf\u00e9s"
    ],
    "wof:name":"Filleke's Taverne",
    "wof:placetype":"venue"
},
  "geometry": {"coordinates":[4.3610458374,51.0612030029],"type":"Point"}
}