{
  "type": "Feature",
  "properties": {
    "addr:full":"Centrumlaan 36-38 Genk Limburg 3600",
    "addr:postcode":"36-38 genk;3600",
    "addr:street":"Centrumlaan",
    "iso:country":"BE",
    "sg:address":"Centrumlaan 36-38",
    "sg:city":"Genk",
    "sg:classifiers":[
        {
            "category":"Restaurant",
            "type":"Food & Drink"
        }
    ],
    "sg:phone":"+32 89 65 07 50",
    "sg:postcode":"3600",
    "sg:province":"Limburg",
    "wof:name":"Troje",
    "wof:placetype":"venue"
},
  "geometry": {"coordinates":[5.4972219467,50.9647903442],"type":"Point"}
}