{
  "type": "Feature",
  "properties": {
    "iso:country":"BE",
    "sg:address":"Brusselsesteenweg 191",
    "sg:city":"Mechelen",
    "sg:orig_category":"Newspapers, magazines, periodicals - Distribution",
    "sg:phone":"+32 15 41 27 16",
    "sg:postcode":"2800",
    "sg:province":"Antwerpen",
    "wof:name":"Sonja Cvoha",
    "wof:placetype":"venue"
},
  "geometry": {"coordinates":[4.4730668068,51.0152931213],"type":"Point"}
}