{
  "type": "Feature",
  "properties": {
    "iso:country":"BE",
    "sg:address":"Koning Leopold I-straat 7",
    "sg:city":"Leuven",
    "sg:classifiers":[
        {
            "category":"Professional",
            "subcategory":"Lawyer & Legal Services",
            "type":"Services"
        }
    ],
    "sg:phone":"+32 16 22 39 38",
    "sg:postcode":"3000",
    "sg:province":"Vlaams-Brabant",
    "wof:name":"De Raeymaeker L",
    "wof:placetype":"venue"
},
  "geometry": {"coordinates":[4.7082152367,50.8791847229],"type":"Point"}
}