{
  "type": "Feature",
  "properties": {
    "iso:country":"BE",
    "sg:address":"Kapellestraat 24",
    "sg:city":"Oostende",
    "sg:orig_category":"Maroquinerie and articles de voyage. Chaussures",
    "sg:phone":"+32 59 70 66 73",
    "sg:postcode":"8400",
    "sg:province":"West-Vlaanderen",
    "wof:name":"Huis Torfs",
    "wof:placetype":"venue"
},
  "geometry": {"coordinates":[2.9186279774,51.2307434082],"type":"Point"}
}