{
  "type": "Feature",
  "properties": {
    "iso:country":"BE",
    "sg:address":"Klokkestraat 33",
    "sg:city":"Duffel",
    "sg:classifiers":[
        {
            "category":"Sports & Exercise",
            "subcategory":"Stables",
            "type":"Entertainment"
        }
    ],
    "sg:phone":"+32 15 32 03 71",
    "sg:postcode":"2570",
    "sg:province":"Antwerpen",
    "sg:tags":[
        "riding",
        "school"
    ],
    "wof:name":"Stallen Mavalo",
    "wof:placetype":"venue"
},
  "geometry": {"coordinates":[4.4899578094,51.1091156006],"type":"Point"}
}