{
  "type": "Feature",
  "properties": {
    "addr:full":"Zwaaikomstraat 72 Roeselare West-Vlaanderen 8800",
    "addr:housenumber":"72",
    "addr:postcode":"8800",
    "addr:street":"Zwaaikomstraat",
    "iso:country":"BE",
    "sg:address":"Zwaaikomstraat 72",
    "sg:city":"Roeselare",
    "sg:classifiers":[
        {
            "category":"Ferry",
            "type":"Transportation"
        }
    ],
    "sg:phone":"+32 51 24 05 08",
    "sg:postcode":"8800",
    "sg:province":"West-Vlaanderen",
    "sg:tags":[
        "whirlpool"
    ],
    "wof:name":"Belhydro",
    "wof:placetype":"venue"
},
  "geometry": {"coordinates":[3.1500511169,50.9531593323],"type":"Point"}
}