{
  "type": "Feature",
  "properties": {
    "addr:full":"Molenstraat 74 Londerzeel Vlaams-Brabant 1840",
    "addr:housenumber":"74",
    "addr:postcode":"1840",
    "addr:street":"Molenstraat",
    "iso:country":"BE",
    "sg:address":"Molenstraat 74",
    "sg:city":"Londerzeel",
    "sg:orig_category":"M\u00e9decins and sp\u00e9cialistes",
    "sg:phone":"+32 52 30 58 55",
    "sg:postcode":"1840",
    "sg:province":"Vlaams-Brabant",
    "wof:name":"L. Hellemans",
    "wof:placetype":"venue"
},
  "geometry": {"coordinates":[4.2986569405,51.0037765503],"type":"Point"}
}