{
  "type": "Feature",
  "properties": {
    "addr:full":"Kortrijksesteenweg 271 Gent Oost-Vlaanderen 9000",
    "addr:housenumber":"271",
    "addr:postcode":"9000",
    "addr:street":"Kortrijksesteenweg;Oost-Vlaanderen",
    "iso:country":"BE",
    "sg:address":"Kortrijksesteenweg 271",
    "sg:city":"Gent",
    "sg:orig_category":"M\u00e9decins and sp\u00e9cialistes",
    "sg:phone":"+32 9 221 99 68",
    "sg:postcode":"9000",
    "sg:province":"Oost-Vlaanderen",
    "wof:name":"H. Cools",
    "wof:placetype":"venue"
},
  "geometry": {"coordinates":[3.7159090042,51.0383453369],"type":"Point"}
}