{
  "type": "Feature",
  "properties": {
    "iso:country":"BE",
    "sg:address":"Grote Markt 22",
    "sg:city":"Tongeren",
    "sg:classifiers":[
        {
            "category":"Shopping",
            "subcategory":"Musical Instruments",
            "type":"Retail Goods"
        }
    ],
    "sg:phone":"+32 12 23 99 81",
    "sg:postcode":"3700",
    "sg:province":"Limburg",
    "sg:tags":[
        "-"
    ],
    "wof:name":"Drums Express",
    "wof:placetype":"venue"
},
  "geometry": {"coordinates":[5.4631757736,50.7805290222],"type":"Point"}
}