{
  "type": "Feature",
  "properties": {
    "iso:country":"BE",
    "sg:address":"Stationsstraat 41",
    "sg:city":"Sint-truiden",
    "sg:orig_category":"Reisbureaus",
    "sg:phone":"+32 11 68 90 09",
    "sg:postcode":"3800",
    "sg:province":"Limburg",
    "wof:name":"Reizen Hermans",
    "wof:placetype":"venue"
},
  "geometry": {"coordinates":[5.1781258583,50.8167762756],"type":"Point"}
}