{
  "type": "Feature",
  "properties": {
    "addr:full":"Antwerpsestraat 204 Boom Antwerpen 2850",
    "addr:housenumber":"204",
    "addr:postcode":"2850",
    "addr:street":"Antwerpsestraat",
    "iso:country":"BE",
    "sg:address":"Antwerpsestraat 204",
    "sg:city":"Boom",
    "sg:classifiers":[
        {
            "category":"Autos & Motor Vehicles",
            "subcategory":"Motorcycle Sales",
            "type":"Retail Goods"
        }
    ],
    "sg:phone":"+32 3 888 03 46",
    "sg:postcode":"2850",
    "sg:province":"Antwerpen",
    "sg:tags":[
        "scooter",
        "-",
        "moped"
    ],
    "wof:name":"R.m.b. Mampaey Bvba",
    "wof:placetype":"venue"
},
  "geometry": {"coordinates":[4.3666582108,51.0951271057],"type":"Point"}
}