{
  "type": "Feature",
  "properties": {
    "addr:full":"Kortrijksestr. 142 Izegem West-Vlaanderen 8870",
    "addr:housenumber":"142",
    "addr:postcode":"8870",
    "iso:country":"BE",
    "sg:address":"Kortrijksestr. 142",
    "sg:city":"Izegem",
    "sg:classifiers":[
        {
            "category":"Manufacturing",
            "subcategory":"Metals",
            "type":"Manufacturing & Wholesale Goods"
        }
    ],
    "sg:phone":"+32 51 74 40 68",
    "sg:postcode":"8870",
    "sg:province":"West-Vlaanderen",
    "sg:tags":[
        "processing",
        "-",
        "metalworking",
        "metallic",
        "metallurgy",
        "finished"
    ],
    "wof:name":"Art Ferro Design Bvba",
    "wof:placetype":"venue"
},
  "geometry": {"coordinates":[3.216917038,50.9108581543],"type":"Point"}
}