{
  "type": "Feature",
  "properties": {
    "iso:country":"BE",
    "sg:address":"Rue De Mons 13",
    "sg:city":"Soignies",
    "sg:classifiers":[
        {
            "category":"Manufacturing",
            "subcategory":"Textiles",
            "type":"Manufacturing & Wholesale Goods"
        }
    ],
    "sg:phone":"+32 67 33 46 88",
    "sg:postcode":"7060",
    "sg:province":"Hainaut",
    "sg:tags":[
        "retail",
        "-"
    ],
    "wof:name":"Damart",
    "wof:placetype":"venue"
},
  "geometry": {"coordinates":[4.0708642006,50.5784378052],"type":"Point"}
}