{
  "type": "Feature",
  "properties": {
    "addr:full":"Rue Louis De Brouck\u00c8re 10 Waregem Li\u00e8ge 4300",
    "addr:housenumber":"10",
    "addr:postcode":"4300",
    "addr:street":"Rue Louis De Broucke\u0300Re",
    "iso:country":"BE",
    "sg:address":"Rue Louis De Brouck\u00c8re 10",
    "sg:city":"Waregem",
    "sg:orig_category":"Tuinen",
    "sg:phone":"+32 19 32 77 00",
    "sg:postcode":"4300",
    "sg:province":"Li\u00e8ge",
    "wof:name":"Jardin-clean",
    "wof:placetype":"venue"
},
  "geometry": {"coordinates":[5.2565498352,50.6982498169],"type":"Point"}
}