{
  "type": "Feature",
  "properties": {
    "addr:full":"Rue De Tib\u00eat\u00eame 18 Libramont-chevigny (libramont) Luxembourg 6800",
    "addr:housenumber":"18",
    "addr:postcode":"6800",
    "addr:street":"Rue De Tibe\u0302Te\u0302Me",
    "iso:country":"BE",
    "sg:address":"Rue De Tib\u00eat\u00eame 18",
    "sg:city":"Libramont-chevigny (libramont)",
    "sg:classifiers":[
        {
            "category":"Health Services",
            "subcategory":"Health Practitioner",
            "type":"Services"
        }
    ],
    "sg:phone":"+32 61 22 37 62",
    "sg:postcode":"6800",
    "sg:province":"Luxembourg",
    "sg:tags":[
        "physiotherapist"
    ],
    "wof:name":"Guissard J-m",
    "wof:placetype":"venue"
},
  "geometry": {"coordinates":[5.3681368828,49.918132782],"type":"Point"}
}