{
  "type": "Feature",
  "properties": {
    "iso:country":"BE",
    "sg:address":"Vierwegstraat 111",
    "sg:city":"Roeselare",
    "sg:classifiers":[
        {
            "category":"Home & Garden",
            "subcategory":"Home Furnishings",
            "type":"Retail Goods"
        }
    ],
    "sg:phone":"+32 51 22 23 90",
    "sg:postcode":"8800",
    "sg:province":"West-Vlaanderen",
    "sg:tags":[
        "lighting",
        "fixture",
        "-"
    ],
    "wof:name":"Compernolle J",
    "wof:placetype":"venue"
},
  "geometry": {"coordinates":[3.1454780102,50.9479904175],"type":"Point"}
}