{
  "type": "Feature",
  "properties": {
    "iso:country":"BE",
    "sg:address":"Rue Seutin 20",
    "sg:city":"Nivelles",
    "sg:orig_category":"Beautyfarms, relaxatie and lichamelijk welzijn Sportcentra",
    "sg:phone":"+32 67 21 64 71",
    "sg:postcode":"1400",
    "sg:province":"Brabant Wallon",
    "wof:name":"Dyotis",
    "wof:placetype":"venue"
},
  "geometry": {"coordinates":[4.3209252357,50.5968360901],"type":"Point"}
}