{
  "type": "Feature",
  "properties": {
    "addr:full":"Rue De L\u00b4ange Gardien 10 Bouillon Luxembourg 6830",
    "addr:housenumber":"10",
    "addr:postcode":"6830",
    "addr:street":"Rue De L\u00b4Ange Gardien",
    "iso:country":"BE",
    "sg:address":"Rue De L\u00b4ange Gardien 10",
    "sg:city":"Bouillon",
    "sg:orig_category":"S\u00e9curit\u00e9 sociale",
    "sg:phone":"+32 61 46 65 35",
    "sg:postcode":"6830",
    "sg:province":"Luxembourg",
    "wof:name":"Mutualit\u00c9 Socialiste",
    "wof:placetype":"venue"
},
  "geometry": {"coordinates":[5.0741271973,49.7976303101],"type":"Point"}
}