{
  "type": "Feature",
  "properties": {
    "iso:country":"BE",
    "sg:address":"Rue E. De Selys-longch. 36",
    "sg:city":"Waremme",
    "sg:orig_category":"Eclairage et \u00e9quipements du foyer. Mat\u00e9riel \u00e9lectrique and \u00e9lectronique Gr",
    "sg:phone":"+32 19 32 95 95",
    "sg:postcode":"4300",
    "sg:province":"Li\u00e8ge",
    "wof:name":"Rolans",
    "wof:placetype":"venue"
},
  "geometry": {"coordinates":[5.2455067635,50.6931991577],"type":"Point"}
}