{
  "type": "Feature",
  "properties": {
    "addr:full":"Rue Du March\u00e9 42 Li\u00e8ge 1 (li\u00e8ge 2) Li\u00e8ge 4020",
    "addr:housenumber":"42;1;2",
    "addr:postcode":"4020",
    "addr:street":"Rue Du Marche\u0301",
    "iso:country":"BE",
    "sg:address":"Rue Du March\u00e9 42",
    "sg:city":"Li\u00e8ge 1 (li\u00e8ge 2)",
    "sg:classifiers":[
        {
            "category":"Professional",
            "subcategory":"Advertising",
            "type":"Services"
        }
    ],
    "sg:phone":"+32 4 343 96 72",
    "sg:postcode":"4020",
    "sg:province":"Li\u00e8ge",
    "sg:tags":[
        "clothes"
    ],
    "wof:name":"Brod'in",
    "wof:placetype":"venue"
},
  "geometry": {"coordinates":[5.5930438042,50.6408233643],"type":"Point"}
}