{
  "type": "Feature",
  "properties": {
    "addr:full":"Korenstraat 10 Nijlen Antwerpen 2560",
    "addr:housenumber":"10",
    "addr:postcode":"2560",
    "addr:street":"Korenstraat",
    "iso:country":"BE",
    "sg:address":"Korenstraat 10",
    "sg:city":"Nijlen",
    "sg:orig_category":"Schoonheidssalons",
    "sg:phone":"+32 3 411 26 45",
    "sg:postcode":"2560",
    "sg:province":"Antwerpen",
    "wof:name":"Christina Crockaerts",
    "wof:placetype":"venue"
},
  "geometry": {"coordinates":[4.6518650055,51.1660041809],"type":"Point"}
}