{
  "type": "Feature",
  "properties": {
    "iso:country":"BE",
    "sg:address":"Chauss\u00c9e De Wavre 41",
    "sg:city":"Perwez",
    "sg:orig_category":"Artsen and specialisten",
    "sg:phone":"+32 81 65 54 00",
    "sg:postcode":"1360",
    "sg:province":"Brabant Wallon",
    "wof:name":"F. Bucquoye",
    "wof:placetype":"venue"
},
  "geometry": {"coordinates":[4.8065271378,50.6268844604],"type":"Point"}
}