{
  "type": "Feature",
  "properties": {
    "iso:country":"BE",
    "sg:address":"Bosstraat 89",
    "sg:city":"Buggenhout",
    "sg:orig_category":"Installation de menuiserie en bois and plastique",
    "sg:phone":"+32 52 34 11 33",
    "sg:postcode":"9255",
    "sg:province":"Oost-Vlaanderen",
    "wof:name":"Hedwig Aelbrecht",
    "wof:placetype":"venue"
},
  "geometry": {"coordinates":[4.2135062218,51.0111274719],"type":"Point"}
}