{
  "type": "Feature",
  "properties": {
    "addr:full":"Stadsestraat 4f Olen Antwerpen 2250",
    "addr:housenumber":"4f",
    "addr:postcode":"2250",
    "addr:street":"Stadsestraat",
    "iso:country":"BE",
    "sg:address":"Stadsestraat 4f",
    "sg:city":"Olen",
    "sg:classifiers":[
        {
            "category":"Real Estate",
            "subcategory":"Architect",
            "type":"Services"
        }
    ],
    "sg:phone":"+32 14 26 73 43",
    "sg:postcode":"2250",
    "sg:province":"Antwerpen",
    "wof:name":"Goris M",
    "wof:placetype":"venue"
},
  "geometry": {"coordinates":[4.8568549156,51.1468582153],"type":"Point"}
}