{
  "type": "Feature",
  "properties": {
    "addr:full":"Rue Des Rabots 76 Fleurus Hainaut 6220",
    "addr:housenumber":"76",
    "addr:postcode":"6220",
    "addr:street":"Rue Des Rabots",
    "iso:country":"BE",
    "sg:address":"Rue Des Rabots 76",
    "sg:city":"Fleurus",
    "sg:classifiers":[
        {
            "category":"Personal",
            "subcategory":"Nail Salon",
            "type":"Services"
        }
    ],
    "sg:phone":"+32 71 81 59 44",
    "sg:postcode":"6220",
    "sg:province":"Hainaut",
    "sg:tags":[
        "pedicure"
    ],
    "wof:name":"Antoine J",
    "wof:placetype":"venue"
},
  "geometry": {"coordinates":[4.5458321571,50.4814414978],"type":"Point"}
}