{
  "type": "Feature",
  "properties": {
    "iso:country":"BE",
    "sg:address":"Werkstraat 6",
    "sg:city":"Gent",
    "sg:classifiers":[
        {
            "category":"Communications",
            "type":"Services"
        }
    ],
    "sg:phone":"+32 9 233 65 86",
    "sg:postcode":"9000",
    "sg:province":"Oost-Vlaanderen",
    "sg:tags":[
        "translator"
    ],
    "wof:name":"Blesi Vertaaldiensten Bvba",
    "wof:placetype":"venue"
},
  "geometry": {"coordinates":[3.6896901131,51.068359375],"type":"Point"}
}