{
  "type": "Feature",
  "properties": {
    "addr:full":"Rue De La Motte 4 Couvin (boussu-en-fagne) Namur 5660",
    "addr:housenumber":"4",
    "addr:postcode":"5660",
    "addr:street":"Rue De La Motte",
    "iso:country":"BE",
    "sg:address":"Rue De La Motte 4",
    "sg:city":"Couvin (boussu-en-fagne)",
    "sg:classifiers":[
        {
            "category":"Banks & Credit Unions",
            "subcategory":"Bureau De Change",
            "type":"Services"
        }
    ],
    "sg:phone":"+32 60 34 48 37",
    "sg:postcode":"5660",
    "sg:province":"Namur",
    "sg:tags":[
        "measuring",
        "control",
        "apparatus"
    ],
    "wof:name":"Atelier Delchambre",
    "wof:placetype":"venue"
},
  "geometry": {"coordinates":[4.4966731071,50.0532150269],"type":"Point"}
}