{
  "type": "Feature",
  "properties": {
    "iso:country":"BE",
    "sg:address":"Atlantische Oceaanlaan 38",
    "sg:city":"Sint-pieters-woluwe/woluwe-saint-pierre",
    "sg:orig_category":"Artsen and specialisten",
    "sg:phone":"+32 2 779 01 31",
    "sg:postcode":"1150",
    "sg:province":"Bruxelles-Capitale",
    "wof:name":"B\u00c9atrice Follet",
    "wof:placetype":"venue"
},
  "geometry": {"coordinates":[4.418697834,50.8312149048],"type":"Point"}
}