{
  "type": "Feature",
  "properties": {
    "iso:country":"BE",
    "sg:address":"Rue De La Ch\u00can\u00c9e 46",
    "sg:city":"Sambreville",
    "sg:orig_category":"Paramedische behandelingen",
    "sg:phone":"+32 71 81 83 05",
    "sg:postcode":"5060",
    "sg:province":"Namur",
    "wof:name":"Labar",
    "wof:placetype":"venue"
},
  "geometry": {"coordinates":[4.5974202156,50.4723510742],"type":"Point"}
}