{
  "type": "Feature",
  "properties": {
    "iso:country":"BE",
    "sg:address":"Ter Booye 16",
    "sg:city":"Tielt",
    "sg:classifiers":[
        {
            "category":"Building & Trades",
            "subcategory":"Electrical",
            "type":"Services"
        }
    ],
    "sg:phone":"+32 51 40 31 88",
    "sg:postcode":"8700",
    "sg:province":"West-Vlaanderen",
    "sg:tags":[
        "electric",
        "-",
        "housewiring",
        "contractor"
    ],
    "wof:name":"Electro Bm",
    "wof:placetype":"venue"
},
  "geometry": {"coordinates":[3.3141100407,50.9910545349],"type":"Point"}
}