{
  "type": "Feature",
  "properties": {
    "addr:full":"Driesstraat 18 Zwevegem West-Vlaanderen 8554",
    "addr:housenumber":"18",
    "addr:postcode":"8554",
    "addr:street":"Driesstraat",
    "iso:country":"BE",
    "sg:address":"Driesstraat 18",
    "sg:city":"Zwevegem",
    "sg:orig_category":"Artiesten and kunstenaars",
    "sg:phone":"+32 56 45 68 54",
    "sg:postcode":"8554",
    "sg:province":"West-Vlaanderen",
    "wof:name":"Claude Bekaert",
    "wof:placetype":"venue"
},
  "geometry": {"coordinates":[3.3650801182,50.7561302185],"type":"Point"}
}