{
  "type": "Feature",
  "properties": {
    "addr:full":"St. Paulusstraat 15 Mol Antwerpen 2400",
    "addr:housenumber":"15",
    "addr:postcode":"2400",
    "addr:street":"St. Paulusstraat",
    "iso:country":"BE",
    "sg:address":"St. Paulusstraat 15",
    "sg:city":"Mol",
    "sg:orig_category":"M\u00e9decines alternatives",
    "sg:phone":"+32 14 31 69 26",
    "sg:postcode":"2400",
    "sg:province":"Antwerpen",
    "wof:name":"J. Michielsen",
    "wof:placetype":"venue"
},
  "geometry": {"coordinates":[5.1116271019,51.1888961792],"type":"Point"}
}