{
  "type": "Feature",
  "properties": {
    "addr:full":"Rue Huart Chapel 11 Charleroi Hainaut 6000",
    "addr:housenumber":"11",
    "addr:postcode":"6000",
    "addr:street":"Rue Huart;Hainaut",
    "iso:country":"BE",
    "sg:address":"Rue Huart Chapel 11",
    "sg:city":"Charleroi",
    "sg:orig_category":"M\u00e9decins and sp\u00e9cialistes",
    "sg:phone":"+32 71 32 41 11",
    "sg:postcode":"6000",
    "sg:province":"Hainaut",
    "wof:name":"Fran\u00c7oise Quevrin",
    "wof:placetype":"venue"
},
  "geometry": {"coordinates":[4.4486079216,50.4147911072],"type":"Point"}
}