{
  "type": "Feature",
  "properties": {
    "iso:country":"BE",
    "sg:address":"Bastijnstraat 69",
    "sg:city":"Berlaar",
    "sg:orig_category":"Oldtimers",
    "sg:phone":"+32 3 482 01 33",
    "sg:postcode":"2590",
    "sg:province":"Antwerpen",
    "wof:name":"Selection T Bvba",
    "wof:placetype":"venue"
},
  "geometry": {"coordinates":[4.6283378601,51.1144371033],"type":"Point"}
}