{
  "type": "Feature",
  "properties": {
    "addr:full":"Bethovenstraat 62b Brecht Antwerpen 2960",
    "addr:housenumber":"62b",
    "addr:postcode":"2960",
    "addr:street":"Bethovenstraat",
    "iso:country":"BE",
    "sg:address":"Bethovenstraat 62b",
    "sg:city":"Brecht",
    "sg:classifiers":[
        {
            "category":"Home & Garden",
            "subcategory":"Carpets & Floor Coverings",
            "type":"Retail Goods"
        }
    ],
    "sg:phone":"+32 3 313 86 66",
    "sg:postcode":"2960",
    "sg:province":"Antwerpen",
    "sg:tags":[
        "material",
        "waterproofing"
    ],
    "wof:name":"Wulva Nv",
    "wof:placetype":"venue"
},
  "geometry": {"coordinates":[4.6336460114,51.3521842957],"type":"Point"}
}