{
  "type": "Feature",
  "properties": {
    "addr:full":"Warandestraat 9 Liedekerke Vlaams-Brabant 1770",
    "addr:housenumber":"9",
    "addr:postcode":"1770",
    "addr:street":"Warandestraat;Vlaams-Brabant",
    "iso:country":"BE",
    "sg:address":"Warandestraat 9",
    "sg:city":"Liedekerke",
    "sg:classifiers":[
        {
            "category":"Cafe",
            "type":"Food & Drink"
        }
    ],
    "sg:phone":"+32 53 66 79 81",
    "sg:postcode":"1770",
    "sg:province":"Vlaams-Brabant",
    "sg:tags":[
        "caf\u00e9s"
    ],
    "wof:name":"Caf\u00c9 Sportlokaal",
    "wof:placetype":"venue"
},
  "geometry": {"coordinates":[4.0818119049,50.8703079224],"type":"Point"}
}