{
  "type": "Feature",
  "properties": {
    "iso:country":"BE",
    "sg:address":"Rechtestraat 6",
    "sg:city":"Lier",
    "sg:classifiers":[
        {
            "category":"Shopping",
            "subcategory":"Clothing, Apparel, & Fashions",
            "type":"Retail Goods"
        }
    ],
    "sg:phone":"+32 3 480 03 04",
    "sg:postcode":"2500",
    "sg:province":"Antwerpen",
    "sg:tags":[
        "hosiery"
    ],
    "wof:name":"Verwilt",
    "wof:placetype":"venue"
},
  "geometry": {"coordinates":[4.5723662376,51.130065918],"type":"Point"}
}