{
  "type": "Feature",
  "properties": {
    "addr:full":"Cit\u00c9 Wauters 95 Saint-ghislain Hainaut 7333",
    "addr:housenumber":"95",
    "addr:postcode":"7333",
    "addr:street":"Cite\u0301 Wauters;Hainaut",
    "iso:country":"BE",
    "sg:address":"Cit\u00c9 Wauters 95",
    "sg:city":"Saint-ghislain",
    "sg:orig_category":"Kapsalons",
    "sg:phone":"+32 65 64 14 76",
    "sg:postcode":"7333",
    "sg:province":"Hainaut",
    "wof:name":"Coiffure Jocelyne",
    "wof:placetype":"venue"
},
  "geometry": {"coordinates":[3.8111400604,50.4655151367],"type":"Point"}
}