{
  "type": "Feature",
  "properties": {
    "iso:country":"BE",
    "sg:address":"Rue Des Combattants 10",
    "sg:city":"Durbuy (w\u00e9ris)",
    "sg:classifiers":[
        {
            "category":"Professional",
            "subcategory":"Accounting & Tax Preparation",
            "type":"Services"
        }
    ],
    "sg:phone":"+32 86 21 42 78",
    "sg:postcode":"6940",
    "sg:province":"Luxembourg",
    "sg:tags":[
        "bookkeeper"
    ],
    "wof:name":"Monfort B",
    "wof:placetype":"venue"
},
  "geometry": {"coordinates":[5.5309090614,50.3256378174],"type":"Point"}
}