{
  "type": "Feature",
  "properties": {
    "iso:country":"BE",
    "sg:address":"Rue E. Vandervelde 17",
    "sg:city":"Pepinster",
    "sg:orig_category":"D\u00e9molition d\u00b4immeubles and terrassements",
    "sg:phone":"+32 87 46 02 05",
    "sg:postcode":"4860",
    "sg:province":"Li\u00e8ge",
    "wof:name":"Lahaye",
    "wof:placetype":"venue"
},
  "geometry": {"coordinates":[5.8226737976,50.5803146362],"type":"Point"}
}