{
  "type": "Feature",
  "properties": {
    "addr:full":"Rue Du Grand P\u00c9ril 108 Braine-le-comte Hainaut 7090",
    "addr:housenumber":"108",
    "addr:postcode":"7090",
    "addr:street":"Rue Du Grand Pe\u0301Ril",
    "iso:country":"BE",
    "sg:address":"Rue Du Grand P\u00c9ril 108",
    "sg:city":"Braine-le-comte",
    "sg:orig_category":"Entretien and r\u00e9parations de voitures",
    "sg:phone":"+32 67 63 61 74",
    "sg:postcode":"7090",
    "sg:province":"Hainaut",
    "wof:name":"Carrosserie Des Tuileries",
    "wof:placetype":"venue"
},
  "geometry": {"coordinates":[4.1812758446,50.649269104],"type":"Point"}
}