{
  "type": "Feature",
  "properties": {
    "addr:full":"Chemin Du Quesnoy 54 Ath Hainaut 7803",
    "addr:housenumber":"54",
    "addr:postcode":"7803",
    "addr:street":"Chemin Du Quesnoy",
    "iso:country":"BE",
    "sg:address":"Chemin Du Quesnoy 54",
    "sg:city":"Ath",
    "sg:classifiers":[
        {
            "category":"Shopping",
            "subcategory":"Gifts & Souvenirs",
            "type":"Retail Goods"
        }
    ],
    "sg:phone":"+32 68 28 20 90",
    "sg:postcode":"7803",
    "sg:province":"Hainaut",
    "sg:tags":[
        "geschenken"
    ],
    "wof:name":"Provence Passion",
    "wof:placetype":"venue"
},
  "geometry": {"coordinates":[3.7681910992,50.6463928223],"type":"Point"}
}