{
  "type": "Feature",
  "properties": {
    "addr:full":"Rue Janson 25 Andenne Namur 5300",
    "addr:housenumber":"25",
    "addr:postcode":"5300",
    "addr:street":"Rue Janson",
    "iso:country":"BE",
    "sg:address":"Rue Janson 25",
    "sg:city":"Andenne",
    "sg:orig_category":"Paramedische behandelingen",
    "sg:phone":"+32 85 84 16 63",
    "sg:postcode":"5300",
    "sg:province":"Namur",
    "wof:name":"B. Hermanne",
    "wof:placetype":"venue"
},
  "geometry": {"coordinates":[5.0985817909,50.4882202148],"type":"Point"}
}