{
  "type": "Feature",
  "properties": {
    "iso:country":"BE",
    "sg:address":"Frambozenlaan 13",
    "sg:city":"Beveren",
    "sg:orig_category":"Onderdelen and accessoires voor auto's",
    "sg:phone":"+32 3 775 26 87",
    "sg:postcode":"9120",
    "sg:province":"Oost-Vlaanderen",
    "wof:name":"Werner Van Brempt",
    "wof:placetype":"venue"
},
  "geometry": {"coordinates":[4.2862868309,51.2139472961],"type":"Point"}
}