{
  "type": "Feature",
  "properties": {
    "addr:full":"Heiderfeld 31 Amel/ambleve Li\u00e8ge 4770",
    "addr:housenumber":"31",
    "addr:postcode":"4770",
    "addr:street":"Heiderfeld",
    "iso:country":"BE",
    "sg:address":"Heiderfeld 31",
    "sg:city":"Amel/ambleve",
    "sg:orig_category":"Artsen and specialisten",
    "sg:phone":"+32 80 34 96 56",
    "sg:postcode":"4770",
    "sg:province":"Li\u00e8ge",
    "wof:name":"Hildegard Peters",
    "wof:placetype":"venue"
},
  "geometry": {"coordinates":[6.1876211166,50.3251914978],"type":"Point"}
}