{
  "type": "Feature",
  "properties": {
    "addr:full":"Hoekstraat 7 Brecht Antwerpen 2960",
    "addr:housenumber":"7",
    "addr:postcode":"2960",
    "addr:street":"Hoekstraat",
    "iso:country":"BE",
    "sg:address":"Hoekstraat 7",
    "sg:city":"Brecht",
    "sg:orig_category":"Eleveurs de bovins. Eleveurs de volaille",
    "sg:phone":"+32 3 313 99 03",
    "sg:postcode":"2960",
    "sg:province":"Antwerpen",
    "wof:name":"Jozef Meyvis",
    "wof:placetype":"venue"
},
  "geometry": {"coordinates":[4.6213989258,51.3571777344],"type":"Point"}
}