{
  "type": "Feature",
  "properties": {
    "iso:country":"BE",
    "sg:address":"Elsense Steenweg 29b31",
    "sg:city":"Elsene/ixelles",
    "sg:orig_category":"Diverse opleidingen and onderwijs Volwassenenonderwijs",
    "sg:phone":"+32 2 511 01 09",
    "sg:postcode":"1050",
    "sg:province":"Bruxelles-Capitale",
    "wof:name":"C.p.a.b.",
    "wof:placetype":"venue"
},
  "geometry": {"coordinates":[4.362238884,50.8370513916],"type":"Point"}
}