{
  "type": "Feature",
  "properties": {
    "iso:country":"BE",
    "sg:address":"Guido Gezellelaan 41",
    "sg:city":"Deinze",
    "sg:orig_category":"Sportclubs Sportterreinen and installaties behalve sportcentra",
    "sg:phone":"+32 9 386 35 58",
    "sg:postcode":"9800",
    "sg:province":"Oost-Vlaanderen",
    "wof:name":"Fc Corgas",
    "wof:placetype":"venue"
},
  "geometry": {"coordinates":[3.5320730209,50.9837913513],"type":"Point"}
}