{
  "type": "Feature",
  "properties": {
    "addr:full":"Rue De Gembloux 9 La Bruy\u00c8re Namur 5080",
    "addr:housenumber":"9",
    "addr:postcode":"5080",
    "addr:street":"Rue De Gembloux",
    "iso:country":"BE",
    "sg:address":"Rue De Gembloux 9",
    "sg:city":"La Bruy\u00c8re",
    "sg:orig_category":"Belastingconsulenten Diverse juridische dienstverlening",
    "sg:phone":"+32 81 55 95 90",
    "sg:postcode":"5080",
    "sg:province":"Namur",
    "wof:name":"Fiscoburo",
    "wof:placetype":"venue"
},
  "geometry": {"coordinates":[4.7979631424,50.4982337952],"type":"Point"}
}