{
  "type": "Feature",
  "properties": {
    "iso:country":"BE",
    "sg:address":"Rue Albert Ier 107",
    "sg:city":"Hannut",
    "sg:orig_category":"M\u00e9decines alternatives",
    "sg:phone":"+32 19 51 52 76",
    "sg:postcode":"4280",
    "sg:province":"Li\u00e8ge",
    "wof:name":"Di\u00c9t\u00c9ticien Leroy Vincent",
    "wof:placetype":"venue"
},
  "geometry": {"coordinates":[5.0850372314,50.6680259705],"type":"Point"}
}