{
  "type": "Feature",
  "properties": {
    "addr:full":"Ridderhoflaan 17 Sint-genesius-rode Vlaams-Brabant 1640",
    "addr:housenumber":"17",
    "addr:postcode":"1640",
    "addr:street":"Ridderhoflaan",
    "iso:country":"BE",
    "sg:address":"Ridderhoflaan 17",
    "sg:city":"Sint-genesius-rode",
    "sg:orig_category":"D\u00e9corateurs d'int\u00e9rieur",
    "sg:phone":"+32 2 358 23 14",
    "sg:postcode":"1640",
    "sg:province":"Vlaams-Brabant",
    "wof:name":"Pesch Design",
    "wof:placetype":"venue"
},
  "geometry": {"coordinates":[4.3966188431,50.7345962524],"type":"Point"}
}