{
  "type": "Feature",
  "properties": {
    "addr:full":"Cyriel De Grootelaan 5 Middelkerke West-Vlaanderen 8430",
    "addr:housenumber":"5",
    "addr:postcode":"8430",
    "addr:street":"Cyriel De Grootelaan",
    "iso:country":"BE",
    "sg:address":"Cyriel De Grootelaan 5",
    "sg:city":"Middelkerke",
    "sg:orig_category":"M\u00e9decins and sp\u00e9cialistes",
    "sg:phone":"+32 59 30 45 51",
    "sg:postcode":"8430",
    "sg:province":"West-Vlaanderen",
    "wof:name":"Myriam Trypsteen",
    "wof:placetype":"venue"
},
  "geometry": {"coordinates":[2.8197600842,51.1882514954],"type":"Point"}
}