{
  "type": "Feature",
  "properties": {
    "iso:country":"BE",
    "sg:address":"Rue Trieux Des Fr\u00eanes 14",
    "sg:city":"La Bruy\u00e8re (emines)",
    "sg:classifiers":[
        {
            "category":"Building & Trades",
            "subcategory":"Landscaping Services",
            "type":"Services"
        }
    ],
    "sg:phone":"+32 81 56 62 11",
    "sg:postcode":"5080",
    "sg:province":"Namur",
    "sg:tags":[
        "forestry"
    ],
    "wof:name":"Poussiere W",
    "wof:placetype":"venue"
},
  "geometry": {"coordinates":[4.8209319115,50.5162277222],"type":"Point"}
}