{
  "type": "Feature",
  "properties": {
    "iso:country":"BE",
    "sg:address":"Grand'rue 21",
    "sg:city":"Thuin",
    "sg:classifiers":[
        {
            "category":"Professional",
            "subcategory":"Testing Lab",
            "type":"Services"
        }
    ],
    "sg:phone":"+32 71 59 00 89",
    "sg:postcode":"6530",
    "sg:province":"Hainaut",
    "sg:tags":[
        "chemist"
    ],
    "wof:name":"Beffroi (du)",
    "wof:placetype":"venue"
},
  "geometry": {"coordinates":[4.2896828651,50.3388442993],"type":"Point"}
}