{
  "type": "Feature",
  "properties": {
    "iso:country":"BE",
    "sg:address":"Schouteerpark 15",
    "sg:city":"Destelbergen",
    "sg:classifiers":[
        {
            "category":"Professional",
            "subcategory":"Testing Lab",
            "type":"Services"
        }
    ],
    "sg:phone":"+32 9 228 12 99",
    "sg:postcode":"9070",
    "sg:province":"Oost-Vlaanderen",
    "sg:tags":[
        "laboratory",
        "-"
    ],
    "wof:name":"L.v.i. Cv",
    "wof:placetype":"venue"
},
  "geometry": {"coordinates":[3.7749218941,51.0577545166],"type":"Point"}
}