{
  "type": "Feature",
  "properties": {
    "addr:full":"Wolfsdonksesteenweg 160 Herselt Antwerpen 2230",
    "addr:housenumber":"160",
    "addr:postcode":"2230",
    "addr:street":"Wolfsdonksesteenweg",
    "iso:country":"BE",
    "sg:address":"Wolfsdonksesteenweg 160",
    "sg:city":"Herselt",
    "sg:classifiers":[
        {
            "category":"Health Services",
            "subcategory":"Health Practitioner",
            "type":"Services"
        }
    ],
    "sg:phone":"+32 14 54 37 71",
    "sg:postcode":"2230",
    "sg:province":"Antwerpen",
    "sg:tags":[
        "physiotherapist"
    ],
    "wof:name":"Huybs Tom",
    "wof:placetype":"venue"
},
  "geometry": {"coordinates":[4.888449192,51.0350151062],"type":"Point"}
}