{
  "type": "Feature",
  "properties": {
    "iso:country":"BE",
    "sg:address":"Torkonjestraat 21",
    "sg:city":"Kortrijk (marke)",
    "sg:classifiers":[
        {
            "category":"Building & Trades",
            "subcategory":"Cleaning & Sanitation",
            "type":"Services"
        }
    ],
    "sg:phone":"+32 56 25 52 52",
    "sg:postcode":"8510",
    "sg:province":"West-Vlaanderen",
    "sg:tags":[
        "chair-cleaning"
    ],
    "wof:name":"Cleaningboy Bvba",
    "wof:placetype":"venue"
},
  "geometry": {"coordinates":[3.2410149574,50.795501709],"type":"Point"}
}