{
  "type": "Feature",
  "properties": {
    "addr:full":"Pieter Potlaan 29 Kontich Antwerpen 2550",
    "addr:housenumber":"29",
    "addr:postcode":"2550",
    "addr:street":"Pieter Potlaan",
    "iso:country":"BE",
    "sg:address":"Pieter Potlaan 29",
    "sg:city":"Kontich",
    "sg:classifiers":[
        {
            "category":"Building & Trades",
            "subcategory":"Electrical",
            "type":"Services"
        }
    ],
    "sg:phone":"+32 3 457 90 27",
    "sg:postcode":"2550",
    "sg:province":"Antwerpen",
    "sg:tags":[
        "electric",
        "-",
        "housewiring",
        "contractor"
    ],
    "wof:name":"Croket P",
    "wof:placetype":"venue"
},
  "geometry": {"coordinates":[4.4451189041,51.1418685913],"type":"Point"}
}