{
  "type": "Feature",
  "properties": {
    "iso:country":"BE",
    "sg:address":"Hoeksken 4",
    "sg:city":"Oosterzele (scheldewindeke)",
    "sg:classifiers":[
        {
            "category":"Health Services",
            "subcategory":"Health Practitioner",
            "type":"Services"
        }
    ],
    "sg:phone":"+32 9 362 54 00",
    "sg:postcode":"9860",
    "sg:province":"Oost-Vlaanderen",
    "sg:tags":[
        "physiotherapist"
    ],
    "wof:name":"Michiels Paul",
    "wof:placetype":"venue"
},
  "geometry": {"coordinates":[3.7893109322,50.9380645752],"type":"Point"}
}