{
  "type": "Feature",
  "properties": {
    "addr:full":"Lange Minnestraat 59 Lebbeke Oost-Vlaanderen 9280",
    "addr:housenumber":"59",
    "addr:postcode":"9280",
    "addr:street":"Lange Minnestraat",
    "iso:country":"BE",
    "sg:address":"Lange Minnestraat 59",
    "sg:city":"Lebbeke",
    "sg:classifiers":[
        {
            "category":"Education",
            "subcategory":"School",
            "type":"Public Place"
        }
    ],
    "sg:phone":"+32 52 35 84 20",
    "sg:postcode":"9280",
    "sg:province":"Oost-Vlaanderen",
    "sg:tags":[
        "primary"
    ],
    "wof:name":"G.v. Gemengde Basisschool",
    "wof:placetype":"venue"
},
  "geometry": {"coordinates":[4.1437621117,50.9835777283],"type":"Point"}
}