{
  "type": "Feature",
  "properties": {
    "iso:country":"BE",
    "sg:address":"Rue Du Hocquet 229",
    "sg:city":"La Louviere",
    "sg:orig_category":"Apotheken",
    "sg:phone":"+32 64 22 29 23",
    "sg:postcode":"7100",
    "sg:province":"Hainaut",
    "wof:name":"Anne Andre",
    "wof:placetype":"venue"
},
  "geometry": {"coordinates":[4.1918702126,50.4810295105],"type":"Point"}
}