{
  "type": "Feature",
  "properties": {
    "iso:country":"BE",
    "sg:address":"Presseux 15bb",
    "sg:city":"Libramont-chevigny",
    "sg:orig_category":"Rundveehouders Varkenskwekers",
    "sg:phone":"+32 61 22 24 49",
    "sg:postcode":"6800",
    "sg:province":"Luxembourg",
    "wof:name":"Fernand Guebs",
    "wof:placetype":"venue"
},
  "geometry": {"coordinates":[5.400249958,49.9163017273],"type":"Point"}
}