{
  "type": "Feature",
  "properties": {
    "addr:full":"Nieuwstraat 76 Asse Vlaams-Brabant 1730",
    "addr:housenumber":"76",
    "addr:postcode":"1730",
    "addr:street":"Nieuwstraat",
    "iso:country":"BE",
    "sg:address":"Nieuwstraat 76",
    "sg:city":"Asse",
    "sg:orig_category":"Brood, gebak and snoepgoed",
    "sg:phone":"+32 2 452 68 07",
    "sg:postcode":"1730",
    "sg:province":"Vlaams-Brabant",
    "wof:name":"Bakkerij Van Nuffelen",
    "wof:placetype":"venue"
},
  "geometry": {"coordinates":[4.1934480667,50.9096603394],"type":"Point"}
}