{
  "type": "Feature",
  "properties": {
    "addr:full":"Chauss\u00c9e De Wavre 325 Wanze Li\u00e8ge 4520",
    "addr:housenumber":"325",
    "addr:postcode":"4520",
    "addr:street":"Chausse\u0301E De Wavre",
    "iso:country":"BE",
    "sg:address":"Chauss\u00c9e De Wavre 325",
    "sg:city":"Wanze",
    "sg:orig_category":"V\u00e9hicules automobiles",
    "sg:phone":"+32 85 71 16 09",
    "sg:postcode":"4520",
    "sg:province":"Li\u00e8ge",
    "wof:name":"Garage Dave R. & Fils",
    "wof:placetype":"venue"
},
  "geometry": {"coordinates":[5.1466770172,50.5434761047],"type":"Point"}
}