{
  "type": "Feature",
  "properties": {
    "iso:country":"BE",
    "sg:address":"Klingedorp 70a",
    "sg:city":"Sint-gillis-waas (de Klinge)",
    "sg:classifiers":[
        {
            "category":"Bars & Pubs",
            "subcategory":"Nightclub",
            "type":"Food & Drink"
        }
    ],
    "sg:phone":"+32 3 707 06 71",
    "sg:postcode":"9170",
    "sg:province":"Oost-Vlaanderen",
    "wof:name":"Liberties",
    "wof:placetype":"venue"
},
  "geometry": {"coordinates":[4.0908651352,51.2591018677],"type":"Point"}
}