{
  "type": "Feature",
  "properties": {
    "iso:country":"BE",
    "sg:address":"Rue Du Moulin \u00c0 Vent 1",
    "sg:city":"Pont-a-celles",
    "sg:orig_category":"Eleveurs de bovins",
    "sg:phone":"+32 71 84 44 03",
    "sg:postcode":"6230",
    "sg:province":"Hainaut",
    "wof:name":"Frans Oost",
    "wof:placetype":"venue"
},
  "geometry": {"coordinates":[4.3636689186,50.5317420959],"type":"Point"}
}