{
  "type": "Feature",
  "properties": {
    "iso:country":"BE",
    "sg:address":"Rue Solvay 58",
    "sg:city":"Chapelle-lez-herlaimont",
    "sg:classifiers":[
        {
            "category":"Cafe",
            "type":"Food & Drink"
        }
    ],
    "sg:phone":"+32 64 44 76 52",
    "sg:postcode":"7160",
    "sg:province":"Hainaut",
    "sg:tags":[
        "caf\u00e9s"
    ],
    "wof:name":"Caf\u00c9 Le Comte D\u00b4artois",
    "wof:placetype":"venue"
},
  "geometry": {"coordinates":[4.280798912,50.4707832336],"type":"Point"}
}