{
  "type": "Feature",
  "properties": {
    "iso:country":"BE",
    "sg:address":"Veldstraat 307",
    "sg:city":"Brasschaat",
    "sg:classifiers":[
        {
            "category":"Professional",
            "subcategory":"Accounting & Tax Preparation",
            "type":"Services"
        }
    ],
    "sg:phone":"+32 3 651 84 70",
    "sg:postcode":"2930",
    "sg:province":"Antwerpen",
    "sg:tags":[
        "accountant"
    ],
    "wof:name":"De Neef L",
    "wof:placetype":"venue"
},
  "geometry": {"coordinates":[4.4821581841,51.3008232117],"type":"Point"}
}