{
  "type": "Feature",
  "properties": {
    "iso:country":"BE",
    "sg:address":"Rue De Bois-de-breux 122b",
    "sg:city":"Li\u00e8ge 1 (jupille-sur-meuse)",
    "sg:classifiers":[
        {
            "category":"Real Estate",
            "subcategory":"Architect",
            "type":"Services"
        }
    ],
    "sg:phone":"+32 4 362 52 84",
    "sg:postcode":"4020",
    "sg:province":"Li\u00e8ge",
    "wof:name":"Germay J-p",
    "wof:placetype":"venue"
},
  "geometry": {"coordinates":[5.621822834,50.6407623291],"type":"Point"}
}