{
  "type": "Feature",
  "properties": {
    "iso:country":"BE",
    "sg:address":"Avenue De La Briqueterie 25",
    "sg:city":"Wavre",
    "sg:orig_category":"M\u00e9decins and sp\u00e9cialistes",
    "sg:phone":"+32 10 24 14 58",
    "sg:postcode":"1300",
    "sg:province":"Brabant Wallon",
    "wof:name":"Bernadette Hendrickx",
    "wof:placetype":"venue"
},
  "geometry": {"coordinates":[4.629319191,50.7178153992],"type":"Point"}
}