{
  "type": "Feature",
  "properties": {
    "iso:country":"BE",
    "sg:address":"Iers-kruisstraat 25",
    "sg:city":"Riemst",
    "sg:orig_category":"Varkenskwekers",
    "sg:phone":"+32 12 45 27 52",
    "sg:postcode":"3770",
    "sg:province":"Limburg",
    "wof:name":"Jaak Moors",
    "wof:placetype":"venue"
},
  "geometry": {"coordinates":[5.6223487854,50.8285865784],"type":"Point"}
}