{
  "type": "Feature",
  "properties": {
    "addr:full":"Boulevard Emile Jacqmain 151 Sint-joost-ten-node/saint-josse-ten-noode Bruxelles-Capitale 1210",
    "addr:housenumber":"151",
    "addr:postcode":"1210",
    "addr:street":"Boulevard Emile Jacqmain;Sint-Joost-Ten-Node /",
    "iso:country":"BE",
    "sg:address":"Boulevard Emile Jacqmain 151",
    "sg:city":"Sint-joost-ten-node/saint-josse-ten-noode",
    "sg:orig_category":"Cr\u00e9dit \u00e0 la consommation",
    "sg:phone":"+32 2 206 95 11",
    "sg:postcode":"1210",
    "sg:province":"Bruxelles-Capitale",
    "wof:name":"Diners Club International",
    "wof:placetype":"venue"
},
  "geometry": {"coordinates":[4.3556289673,50.8560905457],"type":"Point"}
}