{
  "type": "Feature",
  "properties": {
    "addr:full":"Veldekens 19a Maldegem Oost-Vlaanderen 9991",
    "addr:housenumber":"19a",
    "addr:postcode":"9991",
    "addr:street":"Veldekens",
    "iso:country":"BE",
    "sg:address":"Veldekens 19a",
    "sg:city":"Maldegem",
    "sg:orig_category":"Tuinen",
    "sg:phone":"+32 9 378 34 45",
    "sg:postcode":"9991",
    "sg:province":"Oost-Vlaanderen",
    "wof:name":"Van De Walle F",
    "wof:placetype":"venue"
},
  "geometry": {"coordinates":[3.5227780342,51.1610488892],"type":"Point"}
}