{
  "type": "Feature",
  "properties": {
    "iso:country":"BE",
    "sg:address":"Kleemstraat 13",
    "sg:city":"Halle",
    "sg:orig_category":"Banken and kredietinstellingen",
    "sg:phone":"+32 2 356 15 94",
    "sg:postcode":"1500",
    "sg:province":"Vlaams-Brabant",
    "wof:name":"Kbc",
    "wof:placetype":"venue"
},
  "geometry": {"coordinates":[4.2573308945,50.7197265625],"type":"Point"}
}