{
  "type": "Feature",
  "properties": {
    "iso:country":"BE",
    "sg:address":"Rue De Mazy 69",
    "sg:city":"Gembloux-sur-orneau (gembloux)",
    "sg:classifiers":[
        {
            "category":"Banks & Credit Unions",
            "subcategory":"Investment Brokerage",
            "type":"Services"
        }
    ],
    "sg:phone":"+32 81 61 03 44",
    "sg:postcode":"5030",
    "sg:province":"Namur",
    "wof:name":"Gisele Mortilent Et Cie",
    "wof:placetype":"venue"
},
  "geometry": {"coordinates":[4.696035862,50.5533103943],"type":"Point"}
}