{
  "type": "Feature",
  "properties": {
    "iso:country":"BE",
    "sg:address":"Verlatdreef 5b203",
    "sg:city":"Beveren",
    "sg:orig_category":"Installatie van metalen schrijnwerk Pleisterwerk",
    "sg:phone":"+32 3 755 38 17",
    "sg:postcode":"9120",
    "sg:province":"Oost-Vlaanderen",
    "wof:name":"Patrick Andries",
    "wof:placetype":"venue"
},
  "geometry": {"coordinates":[4.2640218735,51.2105445862],"type":"Point"}
}