{
  "type": "Feature",
  "properties": {
    "addr:full":"Chauss\u00c9e De Louvain 25 Wavre Brabant Wallon 1300",
    "addr:housenumber":"25;1300",
    "addr:street":"Chausse\u0301E De Louvain",
    "iso:country":"BE",
    "sg:address":"Chauss\u00c9e De Louvain 25",
    "sg:city":"Wavre",
    "sg:orig_category":"M\u00e9decines alternatives",
    "sg:phone":"+32 10 22 70 10",
    "sg:postcode":"1300",
    "sg:province":"Brabant Wallon",
    "wof:name":"Jacques Postelmans",
    "wof:placetype":"venue"
},
  "geometry": {"coordinates":[4.6133890152,50.7138328552],"type":"Point"}
}