{
  "type": "Feature",
  "properties": {
    "iso:country":"BE",
    "sg:address":"Zonhoevestraat 5b1",
    "sg:city":"Bilzen",
    "sg:orig_category":"Brood, gebak and snoepgoed",
    "sg:phone":"+32 89 50 17 65",
    "sg:postcode":"3740",
    "sg:province":"Limburg",
    "wof:name":"Marie Hermans",
    "wof:placetype":"venue"
},
  "geometry": {"coordinates":[5.4722700119,50.8915290833],"type":"Point"}
}