{
  "type": "Feature",
  "properties": {
    "addr:full":"Pierlapont 46 Zedelgem West-Vlaanderen 8210",
    "addr:housenumber":"46",
    "addr:postcode":"8210",
    "addr:street":"Pierlapont",
    "iso:country":"BE",
    "sg:address":"Pierlapont 46",
    "sg:city":"Zedelgem",
    "sg:classifiers":[
        {
            "category":"Personal",
            "subcategory":"Beauty Salon",
            "type":"Services"
        }
    ],
    "sg:phone":"+32 50 20 10 50",
    "sg:postcode":"8210",
    "sg:province":"West-Vlaanderen",
    "sg:tags":[
        "de",
        "coiffure"
    ],
    "wof:name":"Anouschka Van Hamme",
    "wof:placetype":"venue"
},
  "geometry": {"coordinates":[3.1458399296,51.1376457214],"type":"Point"}
}