{
  "type": "Feature",
  "properties": {
    "addr:full":"Rue Saint-jean-en-isle 3b28 Li\u00c8ge Li\u00e8ge 4000",
    "addr:housenumber":"3b28",
    "addr:postcode":"4000",
    "addr:street":"Rue Saint-Jean-En-Isle",
    "iso:country":"BE",
    "sg:address":"Rue Saint-jean-en-isle 3b28",
    "sg:city":"Li\u00c8ge",
    "sg:orig_category":"Boekhouders",
    "sg:phone":"+32 4 222 44 47",
    "sg:postcode":"4000",
    "sg:province":"Li\u00e8ge",
    "wof:name":"Marcel Missa",
    "wof:placetype":"venue"
},
  "geometry": {"coordinates":[5.5687208176,50.6422805786],"type":"Point"}
}