{
  "type": "Feature",
  "properties": {
    "iso:country":"BE",
    "sg:address":"Chauss\u00c9e Brunehault 228",
    "sg:city":"Jurbise",
    "sg:orig_category":"Rundveehouders",
    "sg:phone":"+32 65 72 44 91",
    "sg:postcode":"7050",
    "sg:province":"Hainaut",
    "wof:name":"Francis Mouchart",
    "wof:placetype":"venue"
},
  "geometry": {"coordinates":[3.9619019032,50.5192832947],"type":"Point"}
}