{
  "type": "Feature",
  "properties": {
    "iso:country":"BE",
    "sg:address":"Stilleveldstraat 12",
    "sg:city":"Herzele (woubrechtegem)",
    "sg:classifiers":[
        {
            "category":"Building & Trades",
            "subcategory":"Landscaping Services",
            "type":"Services"
        }
    ],
    "sg:phone":"+32 53 62 35 87",
    "sg:postcode":"9550",
    "sg:province":"Oost-Vlaanderen",
    "sg:tags":[
        "-",
        "lopping",
        "work",
        "tree",
        "felling"
    ],
    "wof:name":"Cauwel Geert",
    "wof:placetype":"venue"
},
  "geometry": {"coordinates":[3.9185550213,50.8732261658],"type":"Point"}
}