{
  "type": "Feature",
  "properties": {
    "addr:full":"Pappelweg 13 Lontzen Li\u00e8ge 4710",
    "addr:housenumber":"13",
    "addr:postcode":"4710",
    "addr:street":"Pappelweg",
    "iso:country":"BE",
    "sg:address":"Pappelweg 13",
    "sg:city":"Lontzen",
    "sg:classifiers":[
        {
            "category":"Cafe",
            "type":"Food & Drink"
        }
    ],
    "sg:phone":"+32 87 88 26 02",
    "sg:postcode":"4710",
    "sg:province":"Li\u00e8ge",
    "sg:tags":[
        "caf\u00e9s"
    ],
    "wof:name":"Odette Lauwerier",
    "wof:placetype":"venue"
},
  "geometry": {"coordinates":[5.99330616,50.6585121155],"type":"Point"}
}