{
  "type": "Feature",
  "properties": {
    "addr:full":"Avenue Du Mill\u00e9naire 2 Charleroi (gosselies) Hainaut 6041",
    "addr:housenumber":"2",
    "addr:postcode":"6041",
    "addr:street":"Avenue Du Mille\u0301Naire",
    "iso:country":"BE",
    "sg:address":"Avenue Du Mill\u00e9naire 2",
    "sg:city":"Charleroi (gosselies)",
    "sg:classifiers":[
        {
            "category":"Retail",
            "subcategory":"Auto Repair",
            "type":"Services"
        }
    ],
    "sg:phone":"+32 71 25 60 80",
    "sg:postcode":"6041",
    "sg:province":"Hainaut",
    "sg:tags":[
        "automobile-body"
    ],
    "wof:name":"Centr'auto Charleroi Sa",
    "wof:placetype":"venue"
},
  "geometry": {"coordinates":[4.4314317703,50.4685935974],"type":"Point"}
}