{
  "type": "Feature",
  "properties": {
    "iso:country":"BE",
    "sg:address":"Rue D'arlon 220",
    "sg:city":"Messancy",
    "sg:classifiers":[
        {
            "category":"Home & Garden",
            "subcategory":"Home Furnishings",
            "type":"Retail Goods"
        }
    ],
    "sg:phone":"+32 63 38 09 60",
    "sg:postcode":"6780",
    "sg:province":"Luxembourg",
    "sg:tags":[
        "interior",
        "decoration"
    ],
    "wof:name":"Trendhopper",
    "wof:placetype":"venue"
},
  "geometry": {"coordinates":[5.812169075,49.6142578125],"type":"Point"}
}