{
  "type": "Feature",
  "properties": {
    "iso:country":"BE",
    "sg:address":"4 Rue De Maire",
    "sg:city":"Froyennes",
    "sg:classifiers":[
        {
            "category":"Autos & Motor Vehicles",
            "subcategory":"Boat Sales",
            "type":"Retail Goods"
        }
    ],
    "sg:phone":"+32 69 21 37 95",
    "sg:postcode":"7503",
    "sg:province":"Hainaut",
    "sg:tags":[
        "equipment",
        "transport"
    ],
    "wof:name":"Van Laer Yachting Sprl",
    "wof:placetype":"venue"
},
  "geometry": {"coordinates":[3.369852066,50.6227645874],"type":"Point"}
}