{
  "type": "Feature",
  "properties": {
    "iso:country":"BE",
    "sg:address":"Rue Am\u00e9ricaine 176",
    "sg:city":"Bruxelles (ixelles)",
    "sg:classifiers":[
        {
            "category":"Real Estate",
            "subcategory":"Architect",
            "type":"Services"
        }
    ],
    "sg:phone":"+32 2 646 98 35",
    "sg:postcode":"1050",
    "sg:province":"Bruxelles-Capitale",
    "wof:name":"Brisy-happ\u00e9 Atelier D'architecture Sprl",
    "wof:placetype":"venue"
},
  "geometry": {"coordinates":[4.3641829491,50.8217964172],"type":"Point"}
}