{
  "type": "Feature",
  "properties": {
    "iso:country":"BE",
    "sg:address":"Dendermondesteenweg 923",
    "sg:city":"Destelbergen",
    "sg:orig_category":"Slagers",
    "sg:phone":"+32 9 356 90 30",
    "sg:postcode":"9070",
    "sg:province":"Oost-Vlaanderen",
    "wof:name":"Slagerij Comar",
    "wof:placetype":"venue"
},
  "geometry": {"coordinates":[3.8307459354,51.0611915588],"type":"Point"}
}