{
  "type": "Feature",
  "properties": {
    "iso:country":"BE",
    "sg:address":"Rue Des Cortys 46",
    "sg:city":"Fernelmont",
    "sg:orig_category":"Rundveehouders",
    "sg:phone":"+32 81 85 53 84",
    "sg:postcode":"5380",
    "sg:province":"Namur",
    "wof:name":"Gourdin",
    "wof:placetype":"venue"
},
  "geometry": {"coordinates":[4.9861078262,50.5531463623],"type":"Point"}
}