{
  "type": "Feature",
  "properties": {
    "addr:full":"Bakelaarstraat 78 Mechelen Antwerpen 2800",
    "addr:housenumber":"78",
    "addr:postcode":"2800",
    "addr:street":"Bakelaarstraat",
    "iso:country":"BE",
    "sg:address":"Bakelaarstraat 78",
    "sg:city":"Mechelen",
    "sg:orig_category":"Journaux",
    "sg:phone":"+32 15 20 75 13",
    "sg:postcode":"2800",
    "sg:province":"Antwerpen",
    "wof:name":"Dominique Geers",
    "wof:placetype":"venue"
},
  "geometry": {"coordinates":[4.4892349243,51.0318222046],"type":"Point"}
}