{
  "type": "Feature",
  "properties": {
    "addr:full":"Statielei 26 Mortsel Antwerpen 2640",
    "addr:housenumber":"26",
    "addr:postcode":"2640",
    "addr:street":"Statielei",
    "iso:country":"BE",
    "sg:address":"Statielei 26",
    "sg:city":"Mortsel",
    "sg:classifiers":[
        {
            "category":"Shopping",
            "subcategory":"Clothing, Apparel, & Fashions",
            "type":"Retail Goods"
        }
    ],
    "sg:phone":"+32 3 449 22 84",
    "sg:postcode":"2640",
    "sg:province":"Antwerpen",
    "sg:tags":[
        "boutique"
    ],
    "wof:name":"Samoura\u00ef",
    "wof:placetype":"venue"
},
  "geometry": {"coordinates":[4.452188015,51.1703605652],"type":"Point"}
}