{
  "type": "Feature",
  "properties": {
    "addr:full":"Rue Baron Dhanis 56-58 Bruxelles (etterbeek) Bruxelles-Capitale 1040",
    "addr:housenumber":"56-58",
    "addr:postcode":"1040",
    "addr:street":"Rue Baron Dhanis",
    "iso:country":"BE",
    "sg:address":"Rue Baron Dhanis 56-58",
    "sg:city":"Bruxelles (etterbeek)",
    "sg:classifiers":[
        {
            "category":"Shopping",
            "subcategory":"Stationery & Office Supplies",
            "type":"Retail Goods"
        }
    ],
    "sg:phone":"+32 2 735 43 41",
    "sg:postcode":"1040",
    "sg:province":"Bruxelles-Capitale",
    "sg:tags":[
        "envelope"
    ],
    "wof:name":"A All Pap. Lamot Company Sa",
    "wof:placetype":"venue"
},
  "geometry": {"coordinates":[4.397731781,50.828704834],"type":"Point"}
}