{
  "type": "Feature",
  "properties": {
    "addr:full":"Smedenstraat 142 Knokke-heist West-Vlaanderen 8300",
    "addr:housenumber":"142",
    "addr:postcode":"8300",
    "addr:street":"Smedenstraat",
    "iso:country":"BE",
    "sg:address":"Smedenstraat 142",
    "sg:city":"Knokke-heist",
    "sg:orig_category":"Machines and mat\u00e9riel agricoles Quincailleries. Quincaillerie Constructions non r\u00e9sidentielles sp\u00e9ci",
    "sg:phone":"+32 50 60 13 84",
    "sg:postcode":"8300",
    "sg:province":"West-Vlaanderen",
    "wof:name":"De Bree Walther & Stefaan",
    "wof:placetype":"venue"
},
  "geometry": {"coordinates":[3.2934479713,51.3367462158],"type":"Point"}
}