{
  "type": "Feature",
  "properties": {
    "iso:country":"BE",
    "sg:address":"Diksmuidsesteenweg 333b",
    "sg:city":"Roeselare",
    "sg:classifiers":[
        {
            "category":"Professional",
            "subcategory":"Accounting & Tax Preparation",
            "type":"Services"
        }
    ],
    "sg:phone":"+32 51 22 41 97",
    "sg:postcode":"8800",
    "sg:province":"West-Vlaanderen",
    "sg:tags":[
        "bookkeeper"
    ],
    "wof:name":"Huyghe-veracx Bvba Huverco",
    "wof:placetype":"venue"
},
  "geometry": {"coordinates":[3.1047239304,50.9493942261],"type":"Point"}
}