{
  "type": "Feature",
  "properties": {
    "iso:country":"BE",
    "sg:address":"Rue De Behogne 25",
    "sg:city":"Rochefort",
    "sg:orig_category":"D\u00e9corateurs d'int\u00e9rieur",
    "sg:phone":"+32 84 21 47 87",
    "sg:postcode":"5580",
    "sg:province":"Namur",
    "wof:name":"F. Lardot",
    "wof:placetype":"venue"
},
  "geometry": {"coordinates":[5.2233200073,50.1609306335],"type":"Point"}
}