{
  "type": "Feature",
  "properties": {
    "addr:full":"Amerikalei 30b10 Antwerpen Antwerpen 2000",
    "addr:housenumber":"30b10",
    "addr:postcode":"2000",
    "addr:street":"Amerikalei",
    "iso:country":"BE",
    "sg:address":"Amerikalei 30b10",
    "sg:city":"Antwerpen",
    "sg:orig_category":"Assurances. Administration d'immeubles. Agences immobili\u00e8res",
    "sg:phone":"+32 3 237 18 44",
    "sg:postcode":"2000",
    "sg:province":"Antwerpen",
    "wof:name":"Hevaco",
    "wof:placetype":"venue"
},
  "geometry": {"coordinates":[4.40061903,51.208656311],"type":"Point"}
}