{
  "type": "Feature",
  "properties": {
    "iso:country":"BE",
    "sg:address":"Rue De La Jonchaie 11",
    "sg:city":"Bruxelles (etterbeek)",
    "sg:classifiers":[
        {
            "category":"Shopping",
            "subcategory":"Jewelry",
            "type":"Retail Goods"
        }
    ],
    "sg:phone":"+32 2 736 98 88",
    "sg:postcode":"1040",
    "sg:province":"Bruxelles-Capitale",
    "sg:tags":[
        "jeweller",
        "-"
    ],
    "wof:name":"Della Faille D",
    "wof:placetype":"venue"
},
  "geometry": {"coordinates":[4.3973112106,50.8374671936],"type":"Point"}
}