{
  "type": "Feature",
  "properties": {
    "addr:full":"Planche 8 Vloesberg/flobecq Hainaut 7880",
    "addr:housenumber":"8",
    "addr:postcode":"7880",
    "addr:street":"Planche",
    "iso:country":"BE",
    "sg:address":"Planche 8",
    "sg:city":"Vloesberg/flobecq",
    "sg:classifiers":[
        {
            "category":"Arena",
            "subcategory":"Sports Club",
            "type":"Entertainment"
        }
    ],
    "sg:phone":"+32 68 44 70 67",
    "sg:postcode":"7880",
    "sg:province":"Hainaut",
    "sg:tags":[
        "de"
    ],
    "wof:name":"Les Amis R\u00c9unis",
    "wof:placetype":"venue"
},
  "geometry": {"coordinates":[3.7241990566,50.7410774231],"type":"Point"}
}