{
  "type": "Feature",
  "properties": {
    "iso:country":"BE",
    "sg:address":"Halledorp 116",
    "sg:city":"Zoersel",
    "sg:orig_category":"Enregistrements sonores",
    "sg:phone":"+32 3 385 14 70",
    "sg:postcode":"2980",
    "sg:province":"Antwerpen",
    "wof:name":"Mediamix",
    "wof:placetype":"venue"
},
  "geometry": {"coordinates":[4.642168045,51.240322113],"type":"Point"}
}