{
  "type": "Feature",
  "properties": {
    "iso:country":"BE",
    "sg:address":"Square Des Marronniers 27",
    "sg:city":"Fleurus",
    "sg:orig_category":"Plomberie, chauffage and installations sanitaires",
    "sg:phone":"+32 71 81 38 61",
    "sg:postcode":"6220",
    "sg:province":"Hainaut",
    "wof:name":"Montoisis Vincent",
    "wof:placetype":"venue"
},
  "geometry": {"coordinates":[4.5579581261,50.4613113403],"type":"Point"}
}