{
  "type": "Feature",
  "properties": {
    "iso:country":"BE",
    "sg:address":"Schoolstraat 162",
    "sg:city":"Sint-niklaas",
    "sg:orig_category":"Plomberie, chauffage and installations sanitaires. Charpentes and couvertures",
    "sg:phone":"+32 3 711 27 75",
    "sg:postcode":"9100",
    "sg:province":"Oost-Vlaanderen",
    "wof:name":"Vercauteren Gebrs",
    "wof:placetype":"venue"
},
  "geometry": {"coordinates":[4.1519827843,51.1570243835],"type":"Point"}
}