{
  "type": "Feature",
  "properties": {
    "iso:country":"BE",
    "sg:address":"Rue Ren\u00c9 Delbrouck 103",
    "sg:city":"Seraing",
    "sg:classifiers":[
        {
            "category":"Personal",
            "subcategory":"Beauty Salon",
            "type":"Services"
        }
    ],
    "sg:phone":"+32 4 330 95 66",
    "sg:postcode":"4102",
    "sg:province":"Li\u00e8ge",
    "sg:tags":[
        "de",
        "coiffure"
    ],
    "wof:name":"Les Boucles D\u00b4or",
    "wof:placetype":"venue"
},
  "geometry": {"coordinates":[5.5343599319,50.5988883972],"type":"Point"}
}