{
  "type": "Feature",
  "properties": {
    "addr:full":"Quai Au Foin 23 Brussel/bruxelles Bruxelles-Capitale 1000",
    "addr:housenumber":"23",
    "addr:postcode":"1000",
    "addr:street":"Quai Au Foin;/",
    "iso:country":"BE",
    "sg:address":"Quai Au Foin 23",
    "sg:city":"Brussel/bruxelles",
    "sg:orig_category":"Enseignement maternel and primaire",
    "sg:phone":"+32 2 217 77 99",
    "sg:postcode":"1000",
    "sg:province":"Bruxelles-Capitale",
    "wof:name":"Ecole Fondamentale Libre",
    "wof:placetype":"venue"
},
  "geometry": {"coordinates":[4.3511271477,50.8557662964],"type":"Point"}
}