{
  "type": "Feature",
  "properties": {
    "iso:country":"BE",
    "sg:address":"Dorpsstraat 30",
    "sg:city":"Kapellen",
    "sg:classifiers":[
        {
            "category":"Personal",
            "subcategory":"Beauty Salon",
            "type":"Services"
        }
    ],
    "sg:phone":"+32 3 665 24 66",
    "sg:postcode":"2950",
    "sg:province":"Antwerpen",
    "sg:tags":[
        "lady",
        "-",
        "hairdressing"
    ],
    "wof:name":"Chamar",
    "wof:placetype":"venue"
},
  "geometry": {"coordinates":[4.4288949966,51.3158912659],"type":"Point"}
}