{
  "type": "Feature",
  "properties": {
    "iso:country":"BE",
    "sg:address":"Rue De Soulme 4ba",
    "sg:city":"Hasti\u00c8re",
    "sg:orig_category":"Pluimveekwekers",
    "sg:phone":"+32 82 64 49 26",
    "sg:postcode":"5540",
    "sg:province":"Namur",
    "wof:name":"Delaive",
    "wof:placetype":"venue"
},
  "geometry": {"coordinates":[4.825758934,50.2165184021],"type":"Point"}
}