{
  "type": "Feature",
  "properties": {
    "iso:country":"BE",
    "sg:address":"Lichterveldestraat 35",
    "sg:city":"Kortemark",
    "sg:classifiers":[
        {
            "category":"Retail",
            "subcategory":"Auto Repair",
            "type":"Services"
        }
    ],
    "sg:phone":"+32 51 56 70 66",
    "sg:postcode":"8610",
    "sg:province":"West-Vlaanderen",
    "sg:tags":[
        "garage"
    ],
    "wof:name":"Vandaele D",
    "wof:placetype":"venue"
},
  "geometry": {"coordinates":[3.0474419594,51.0285606384],"type":"Point"}
}