{
  "type": "Feature",
  "properties": {
    "iso:country":"BE",
    "sg:address":"Helmkruidstraat 17",
    "sg:city":"Bierbeek (lovenjoel)",
    "sg:classifiers":[
        {
            "category":"Health Services",
            "subcategory":"Health Practitioner",
            "type":"Services"
        }
    ],
    "sg:phone":"+32 16 46 28 98",
    "sg:postcode":"3360",
    "sg:province":"Vlaams-Brabant",
    "sg:tags":[
        "physiotherapist"
    ],
    "wof:name":"Dejonghe C",
    "wof:placetype":"venue"
},
  "geometry": {"coordinates":[4.7901787758,50.84765625],"type":"Point"}
}