{
  "type": "Feature",
  "properties": {
    "addr:full":"Rue Paul D\u00b4andrimont 107 Soumagne Li\u00e8ge 4630",
    "addr:housenumber":"107",
    "addr:postcode":"4630",
    "addr:street":"Rue Paul D\u00b4Andrimont",
    "iso:country":"BE",
    "sg:address":"Rue Paul D\u00b4andrimont 107",
    "sg:city":"Soumagne",
    "sg:orig_category":"Bouwmaterialen Gh Vloer- and muurbekleding",
    "sg:phone":"+32 4 377 10 58",
    "sg:postcode":"4630",
    "sg:province":"Li\u00e8ge",
    "wof:name":"Hansez - Dalem",
    "wof:placetype":"venue"
},
  "geometry": {"coordinates":[5.7202267647,50.6265411377],"type":"Point"}
}