{
  "type": "Feature",
  "properties": {
    "iso:country":"BE",
    "sg:address":"Torenstraat 92",
    "sg:city":"Zandhoven (pulle)",
    "sg:classifiers":[
        {
            "category":"Parking",
            "subcategory":"Lot",
            "type":"Transportation"
        }
    ],
    "sg:phone":"+32 3 484 55 71",
    "sg:postcode":"2243",
    "sg:province":"Antwerpen",
    "sg:tags":[
        "parking-places",
        "laying-out"
    ],
    "wof:name":"Huybrechts E",
    "wof:placetype":"venue"
},
  "geometry": {"coordinates":[4.7150168419,51.2024841309],"type":"Point"}
}