{
  "type": "Feature",
  "properties": {
    "iso:country":"BE",
    "sg:address":"Rue Joseph Marvel 3",
    "sg:city":"Gembloux-sur-orneau (corroy-le-ch\u00e2teau)",
    "sg:classifiers":[
        {
            "category":"Building & Trades",
            "subcategory":"Cleaning & Sanitation",
            "type":"Services"
        }
    ],
    "sg:phone":"+32 81 63 37 58",
    "sg:postcode":"5032",
    "sg:province":"Namur",
    "sg:tags":[
        "janitor"
    ],
    "wof:name":"Marrant P",
    "wof:placetype":"venue"
},
  "geometry": {"coordinates":[4.6485829353,50.5386314392],"type":"Point"}
}