{
  "type": "Feature",
  "properties": {
    "addr:full":"Molenheide 1 Zandhoven Antwerpen 2242",
    "addr:housenumber":"1",
    "addr:postcode":"2242",
    "addr:street":"Molenheide",
    "iso:country":"BE",
    "sg:address":"Molenheide 1",
    "sg:city":"Zandhoven",
    "sg:orig_category":"Banques and organismes de cr\u00e9dit",
    "sg:phone":"+32 3 466 07 00",
    "sg:postcode":"2242",
    "sg:province":"Antwerpen",
    "wof:name":"Kbc",
    "wof:placetype":"venue"
},
  "geometry": {"coordinates":[4.6932458878,51.220287323],"type":"Point"}
}