{
  "type": "Feature",
  "properties": {
    "addr:full":"Lokerenbaan 220 Zele Oost-Vlaanderen 9240",
    "addr:housenumber":"220",
    "addr:postcode":"9240",
    "iso:country":"BE",
    "sg:address":"Lokerenbaan 220",
    "sg:city":"Zele",
    "sg:classifiers":[
        {
            "category":"Building & Trades",
            "subcategory":"Pest Control",
            "type":"Services"
        }
    ],
    "sg:phone":"+32 52 44 51 39",
    "sg:postcode":"9240",
    "sg:province":"Oost-Vlaanderen",
    "sg:tags":[
        "painting",
        "contractor"
    ],
    "wof:name":"Gijsens A",
    "wof:placetype":"venue"
},
  "geometry": {"coordinates":[4.0369830132,51.0815048218],"type":"Point"}
}