{
  "type": "Feature",
  "properties": {
    "addr:full":"Rue De L'arbre Saint-roch 53 Oupeye (vivegnis) Li\u00e8ge 4683",
    "addr:housenumber":"53",
    "addr:postcode":"4683",
    "addr:street":"Rue De L'Arbre Saint-Roch;Vivegnis",
    "iso:country":"BE",
    "sg:address":"Rue De L'arbre Saint-roch 53",
    "sg:city":"Oupeye (vivegnis)",
    "sg:classifiers":[
        {
            "category":"Professional",
            "subcategory":"Art Services",
            "type":"Services"
        }
    ],
    "sg:phone":"+32 4 264 30 71",
    "sg:postcode":"4683",
    "sg:province":"Li\u00e8ge",
    "sg:tags":[
        "graphic",
        "designer"
    ],
    "wof:name":"Point Jaune",
    "wof:placetype":"venue"
},
  "geometry": {"coordinates":[5.581829071,50.6424331665],"type":"Point"}
}