{
  "type": "Feature",
  "properties": {
    "addr:full":"Offerandestraat 88 Antwerpen Antwerpen 2060",
    "addr:housenumber":"88",
    "addr:postcode":"2060",
    "addr:street":"Offerandestraat",
    "iso:country":"BE",
    "sg:address":"Offerandestraat 88",
    "sg:city":"Antwerpen",
    "sg:classifiers":[
        {
            "category":"Shopping",
            "subcategory":"Clothing, Apparel, & Fashions",
            "type":"Retail Goods"
        }
    ],
    "sg:phone":"+32 3 236 79 69",
    "sg:postcode":"2060",
    "sg:province":"Antwerpen",
    "sg:tags":[
        "boutique"
    ],
    "wof:name":"Samara",
    "wof:placetype":"venue"
},
  "geometry": {"coordinates":[4.4267320633,51.2208404541],"type":"Point"}
}