{
  "type": "Feature",
  "properties": {
    "iso:country":"BE",
    "sg:address":"Grote Markt 47",
    "sg:city":"Lier",
    "sg:classifiers":[
        {
            "category":"Shopping",
            "subcategory":"Clothing, Apparel, & Fashions",
            "type":"Retail Goods"
        }
    ],
    "sg:phone":"+32 3 480 16 86",
    "sg:postcode":"2500",
    "sg:province":"Antwerpen",
    "sg:tags":[
        "lingerie",
        "sous-v\u00eatements"
    ],
    "wof:name":"Maria Van Hoof",
    "wof:placetype":"venue"
},
  "geometry": {"coordinates":[4.5693879128,51.1315727234],"type":"Point"}
}