{
  "type": "Feature",
  "properties": {
    "iso:country":"BE",
    "sg:address":"Gouv. Verwilghensingel 100",
    "sg:city":"Hasselt",
    "sg:orig_category":"Banques and organismes de cr\u00e9dit",
    "sg:phone":"+32 11 24 04 11",
    "sg:postcode":"3500",
    "sg:province":"Limburg",
    "wof:name":"Kbc",
    "wof:placetype":"venue"
},
  "geometry": {"coordinates":[5.3598041534,50.9279327393],"type":"Point"}
}