{
  "type": "Feature",
  "properties": {
    "iso:country":"BE",
    "sg:address":"Haagbeemdenplantsoen 95",
    "sg:city":"Turnhout",
    "sg:orig_category":"Enseignement maternel and primaire",
    "sg:phone":"+32 14 41 59 51",
    "sg:postcode":"2300",
    "sg:province":"Antwerpen",
    "wof:name":"Stedelijke Basisschool",
    "wof:placetype":"venue"
},
  "geometry": {"coordinates":[4.9403867722,51.3068962097],"type":"Point"}
}