{
  "type": "Feature",
  "properties": {
    "addr:full":"Stationsstraat 63 Oosterzele Oost-Vlaanderen 9860",
    "addr:housenumber":"63",
    "addr:postcode":"9860",
    "addr:street":"Stationsstraat;Oost-Vlaanderen",
    "iso:country":"BE",
    "sg:address":"Stationsstraat 63",
    "sg:city":"Oosterzele",
    "sg:orig_category":"Locations de machines and \u00e9quipement pour la construction. Transports routiers de marchandises. Cons",
    "sg:phone":"+32 9 362 76 37",
    "sg:postcode":"9860",
    "sg:province":"Oost-Vlaanderen",
    "wof:name":"Willy De Coene",
    "wof:placetype":"venue"
},
  "geometry": {"coordinates":[3.7805171013,50.9373283386],"type":"Point"}
}