{
  "type": "Feature",
  "properties": {
    "addr:full":"Avenue Du Stade 13 Antoing Hainaut 7640",
    "addr:housenumber":"13",
    "addr:postcode":"7640",
    "addr:street":"Avenue Du Stade",
    "iso:country":"BE",
    "sg:address":"Avenue Du Stade 13",
    "sg:city":"Antoing",
    "sg:orig_category":"Postkantoren Verzekeringsmakelaars and experts",
    "sg:phone":"+32 69 44 22 09",
    "sg:postcode":"7640",
    "sg:province":"Hainaut",
    "wof:name":"La Poste",
    "wof:placetype":"venue"
},
  "geometry": {"coordinates":[3.4480240345,50.5679664612],"type":"Point"}
}