{
  "type": "Feature",
  "properties": {
    "addr:full":"Klotputten 43 Arendonk Antwerpen 2370",
    "addr:housenumber":"43",
    "addr:postcode":"2370",
    "addr:street":"Klotputten",
    "iso:country":"BE",
    "sg:address":"Klotputten 43",
    "sg:city":"Arendonk",
    "sg:classifiers":[
        {
            "category":"Arena",
            "subcategory":"Sports Club",
            "type":"Entertainment"
        }
    ],
    "sg:phone":"+32 14 67 73 09",
    "sg:postcode":"2370",
    "sg:province":"Antwerpen",
    "sg:tags":[
        "de"
    ],
    "wof:name":"De Lusthoven",
    "wof:placetype":"venue"
},
  "geometry": {"coordinates":[5.0950222015,51.2979354858],"type":"Point"}
}