{
  "type": "Feature",
  "properties": {
    "addr:full":"Nieuwstraat 6 Essen Antwerpen 2910",
    "addr:housenumber":"6",
    "addr:postcode":"2910",
    "addr:street":"Nieuwstraat",
    "iso:country":"BE",
    "sg:address":"Nieuwstraat 6",
    "sg:city":"Essen",
    "sg:classifiers":[
        {
            "category":"Health Services",
            "subcategory":"Dentist",
            "type":"Services"
        }
    ],
    "sg:phone":"+32 3 667 60 60",
    "sg:postcode":"2910",
    "sg:province":"Antwerpen",
    "wof:name":"De Bruyn H",
    "wof:placetype":"venue"
},
  "geometry": {"coordinates":[4.4712700844,51.4656906128],"type":"Point"}
}