{
  "type": "Feature",
  "properties": {
    "addr:full":"An Der Follmuhle 2-4 Hauset Li\u00e8ge 4730",
    "addr:housenumber":"2-4",
    "addr:postcode":"4730",
    "addr:street":"An Der Follmuhle",
    "iso:country":"BE",
    "sg:address":"An Der Follmuhle 2-4",
    "sg:city":"Hauset",
    "sg:classifiers":[
        {
            "category":"Building & Trades",
            "subcategory":"Equipment Rental",
            "type":"Services"
        }
    ],
    "sg:phone":"+32 87 65 92 71",
    "sg:postcode":"4730",
    "sg:province":"Li\u00e8ge",
    "sg:tags":[
        "brickwork"
    ],
    "wof:name":"Heutz-homburg S.a.",
    "wof:placetype":"venue"
},
  "geometry": {"coordinates":[6.0729899406,50.7056884766],"type":"Point"}
}