{
  "type": "Feature",
  "properties": {
    "addr:full":"Rue Des Alli\u00c9s 160 Forest Bruxelles-Capitale 1190",
    "addr:housenumber":"160",
    "addr:postcode":"1190",
    "addr:street":"Rue Des Allie\u0301S",
    "iso:country":"BE",
    "sg:address":"Rue Des Alli\u00c9s 160",
    "sg:city":"Forest",
    "sg:orig_category":"Informaticaconsulenten Software ontwikkeling and ontwerp",
    "sg:phone":"+32 2 347 20 21",
    "sg:postcode":"1190",
    "sg:province":"Bruxelles-Capitale",
    "wof:name":"Soft Office",
    "wof:placetype":"venue"
},
  "geometry": {"coordinates":[4.3267989159,50.8190994263],"type":"Point"}
}