{
  "type": "Feature",
  "properties": {
    "iso:country":"BE",
    "sg:address":"Doddelbergstraat 34",
    "sg:city":"Kortenaken (kersbeek-miskom)",
    "sg:classifiers":[
        {
            "category":"Personal",
            "subcategory":"Beauty Salon",
            "type":"Services"
        }
    ],
    "sg:phone":"+32 16 77 91 59",
    "sg:postcode":"3472",
    "sg:province":"Vlaams-Brabant",
    "sg:tags":[
        "lady",
        "-",
        "hairdressing"
    ],
    "wof:name":"Agnes",
    "wof:placetype":"venue"
},
  "geometry": {"coordinates":[4.9815402031,50.8926506042],"type":"Point"}
}