{
  "type": "Feature",
  "properties": {
    "iso:country":"BE",
    "sg:address":"Rue Reper Vreven 116",
    "sg:city":"Brussel/bruxelles",
    "sg:orig_category":"Diverse machines voor de nijverheid Gh",
    "sg:phone":"+32 2 478 68 27",
    "sg:postcode":"1020",
    "sg:province":"Bruxelles-Capitale",
    "wof:name":"Cavignac",
    "wof:placetype":"venue"
},
  "geometry": {"coordinates":[4.3377919197,50.8901062012],"type":"Point"}
}