{
  "type": "Feature",
  "properties": {
    "addr:full":"Avenue Des Eperviers 87 Bruxelles (woluwe-saint-pierre) Bruxelles-Capitale 1150",
    "addr:housenumber":"87",
    "addr:postcode":"1150",
    "addr:street":"Avenue Des Eperviers",
    "iso:country":"BE",
    "sg:address":"Avenue Des Eperviers 87",
    "sg:city":"Bruxelles (woluwe-saint-pierre)",
    "sg:classifiers":[
        {
            "category":"Professional",
            "subcategory":"Accounting & Tax Preparation",
            "type":"Services"
        }
    ],
    "sg:phone":"+32 2 672 73 89",
    "sg:postcode":"1150",
    "sg:province":"Bruxelles-Capitale",
    "sg:tags":[
        "bookkeeper"
    ],
    "wof:name":"Kestemont C",
    "wof:placetype":"venue"
},
  "geometry": {"coordinates":[4.4129571915,50.8247528076],"type":"Point"}
}