{
  "type": "Feature",
  "properties": {
    "addr:full":"Te Boelaarlei 50 Antwerpen (borgerhout) Antwerpen 2140",
    "addr:housenumber":"50",
    "addr:postcode":"2140",
    "iso:country":"BE",
    "sg:address":"Te Boelaarlei 50",
    "sg:city":"Antwerpen (borgerhout)",
    "sg:classifiers":[
        {
            "category":"Personal",
            "subcategory":"Beauty Salon",
            "type":"Services"
        }
    ],
    "sg:phone":"+32 3 236 77 42",
    "sg:postcode":"2140",
    "sg:province":"Antwerpen",
    "sg:tags":[
        "lady",
        "-",
        "hairdressing"
    ],
    "wof:name":"Ingrid",
    "wof:placetype":"venue"
},
  "geometry": {"coordinates":[4.4332199097,51.2137565613],"type":"Point"}
}