{
  "type": "Feature",
  "properties": {
    "addr:full":"Rue Des Bruy\u00c8res 32 Ottignies-louvain-la-neuve Brabant Wallon 1348",
    "addr:housenumber":"32",
    "addr:postcode":"1348",
    "addr:street":"Rue Des Bruye\u0300Res",
    "iso:country":"BE",
    "sg:address":"Rue Des Bruy\u00c8res 32",
    "sg:city":"Ottignies-louvain-la-neuve",
    "sg:orig_category":"Location d'articles de sport, de sport nautique and de camping",
    "sg:phone":"+32 10 45 59 02",
    "sg:postcode":"1348",
    "sg:province":"Brabant Wallon",
    "wof:name":"Maison Kap Course",
    "wof:placetype":"venue"
},
  "geometry": {"coordinates":[4.6112251282,50.6651725769],"type":"Point"}
}