{
  "type": "Feature",
  "properties": {
    "iso:country":"BE",
    "sg:address":"Oude Plaats 48",
    "sg:city":"Komen-waasten/comines-warneton",
    "sg:orig_category":"Kapsalons",
    "sg:phone":"+32 56 55 51 89",
    "sg:postcode":"7784",
    "sg:province":"Hainaut",
    "wof:name":"Sylvie Gruson",
    "wof:placetype":"venue"
},
  "geometry": {"coordinates":[2.964124918,50.7544136047],"type":"Point"}
}