{
  "type": "Feature",
  "properties": {
    "iso:country":"BE",
    "sg:address":"Graaf De M\u00fbelenaerelaan 74",
    "sg:city":"Brugge",
    "sg:classifiers":[
        {
            "category":"Social Services",
            "type":"Services"
        }
    ],
    "sg:phone":"+32 50 31 04 51",
    "sg:postcode":"8000",
    "sg:province":"West-Vlaanderen",
    "wof:name":"Oxfam Solidarit\u00e9 Vzw",
    "wof:placetype":"venue"
},
  "geometry": {"coordinates":[3.2331171036,51.2236824036],"type":"Point"}
}