{
  "type": "Feature",
  "properties": {
    "addr:full":"Rue Rogier 57 Tournai Hainaut 7500",
    "addr:housenumber":"57",
    "addr:postcode":"7500",
    "addr:street":"Rue Rogier",
    "iso:country":"BE",
    "sg:address":"Rue Rogier 57",
    "sg:city":"Tournai",
    "sg:classifiers":[
        {
            "category":"Personal",
            "subcategory":"Psychics & Astrologers",
            "type":"Services"
        }
    ],
    "sg:phone":"+32 69 84 14 44",
    "sg:postcode":"7500",
    "sg:province":"Hainaut",
    "sg:tags":[
        "astrology"
    ],
    "wof:name":"Monsieur M",
    "wof:placetype":"venue"
},
  "geometry": {"coordinates":[3.388559103,50.6013298035],"type":"Point"}
}