{
  "type": "Feature",
  "properties": {
    "iso:country":"BE",
    "sg:address":"Simon Stevinplein 1",
    "sg:city":"Brugge",
    "sg:orig_category":"Maroquinerie and articles de voyage",
    "sg:phone":"+32 50 33 60 95",
    "sg:postcode":"8000",
    "sg:province":"West-Vlaanderen",
    "wof:name":"Art Lux Lederwaren",
    "wof:placetype":"venue"
},
  "geometry": {"coordinates":[3.2228291035,51.2069816589],"type":"Point"}
}