{
  "type": "Feature",
  "properties": {
    "iso:country":"BE",
    "sg:address":"Bassevillestraat 181",
    "sg:city":"Middelkerke (westende)",
    "sg:classifiers":[
        {
            "category":"Ice Cream",
            "type":"Food & Drink"
        }
    ],
    "sg:phone":"+32 58 23 83 76",
    "sg:postcode":"8434",
    "sg:province":"West-Vlaanderen",
    "wof:name":"Retro-ice Bvba",
    "wof:placetype":"venue"
},
  "geometry": {"coordinates":[2.7568869591,51.1495056152],"type":"Point"}
}