{
  "type": "Feature",
  "properties": {
    "addr:full":"Kouterbaan 10 Sint-martens-latem Oost-Vlaanderen 9830",
    "addr:housenumber":"10",
    "addr:postcode":"9830",
    "addr:street":"Kouterbaan",
    "iso:country":"BE",
    "sg:address":"Kouterbaan 10",
    "sg:city":"Sint-martens-latem",
    "sg:orig_category":"Kapsalons",
    "sg:phone":"+32 9 282 35 29",
    "sg:postcode":"9830",
    "sg:province":"Oost-Vlaanderen",
    "wof:name":"Coiffure Trianon",
    "wof:placetype":"venue"
},
  "geometry": {"coordinates":[3.6355519295,51.0165596008],"type":"Point"}
}