{
  "type": "Feature",
  "properties": {
    "addr:full":"Huikstraat 10 Antwerpen Antwerpen 2000",
    "addr:housenumber":"10",
    "addr:postcode":"2000",
    "addr:street":"Huikstraat",
    "iso:country":"BE",
    "sg:address":"Huikstraat 10",
    "sg:city":"Antwerpen",
    "sg:orig_category":"D\u00e9molition d\u00b4immeubles and terrassements",
    "sg:phone":"+32 3 232 52 42",
    "sg:postcode":"2000",
    "sg:province":"Antwerpen",
    "wof:name":"Oude Marktvoerliedennatie",
    "wof:placetype":"venue"
},
  "geometry": {"coordinates":[4.4042429924,51.2249755859],"type":"Point"}
}