{
  "type": "Feature",
  "properties": {
    "iso:country":"BE",
    "sg:address":"Rue Laide-basse 30",
    "sg:city":"Fosses-la-ville",
    "sg:orig_category":"Eleveurs de bovins",
    "sg:phone":"+32 71 71 16 86",
    "sg:postcode":"5070",
    "sg:province":"Namur",
    "wof:name":"Beck Jozef Et Beck Gaston",
    "wof:placetype":"venue"
},
  "geometry": {"coordinates":[4.6833701134,50.3975257874],"type":"Point"}
}