{
  "type": "Feature",
  "properties": {
    "addr:full":"Vieux Chemin De Bruxelles 1 Nivelles Brabant Wallon 1400",
    "addr:housenumber":"1",
    "addr:postcode":"1400",
    "addr:street":"Vieux Chemin De Bruxelles",
    "iso:country":"BE",
    "sg:address":"Vieux Chemin De Bruxelles 1",
    "sg:city":"Nivelles",
    "sg:classifiers":[
        {
            "category":"Food & Beverages",
            "subcategory":"Fruits & Vegetables",
            "type":"Retail Goods"
        }
    ],
    "sg:phone":"+32 67 21 20 96",
    "sg:postcode":"1400",
    "sg:province":"Brabant Wallon",
    "sg:tags":[
        "-"
    ],
    "wof:name":"Binet J",
    "wof:placetype":"venue"
},
  "geometry": {"coordinates":[4.3262071609,50.6004371643],"type":"Point"}
}