{
  "type": "Feature",
  "properties": {
    "iso:country":"BE",
    "sg:address":"Rue Des Naiveux 38",
    "sg:city":"Herstal",
    "sg:classifiers":[
        {
            "category":"Shopping",
            "subcategory":"Baby Store",
            "type":"Retail Goods"
        }
    ],
    "sg:phone":"+32 4 240 46 89",
    "sg:postcode":"4040",
    "sg:province":"Li\u00e8ge",
    "sg:tags":[
        "article",
        "b\u00e9b\u00e9s",
        "pour"
    ],
    "wof:name":"Baby 2000",
    "wof:placetype":"venue"
},
  "geometry": {"coordinates":[5.6478471756,50.6889381409],"type":"Point"}
}