{
  "type": "Feature",
  "properties": {
    "iso:country":"BE",
    "sg:address":"Oostrozebeeksestraat 28",
    "sg:city":"Wielsbeke",
    "sg:orig_category":"Bouwmaterialen Gh",
    "sg:phone":"+32 56 66 67 37",
    "sg:postcode":"8710",
    "sg:province":"West-Vlaanderen",
    "wof:name":"Granimar",
    "wof:placetype":"venue"
},
  "geometry": {"coordinates":[3.335916996,50.894618988],"type":"Point"}
}