{
  "type": "Feature",
  "properties": {
    "iso:country":"BE",
    "sg:address":"Rotselaarsesteenweg 38",
    "sg:city":"Leuven",
    "sg:orig_category":"Sportclubs",
    "sg:phone":"+32 16 44 54 45",
    "sg:postcode":"3018",
    "sg:province":"Vlaams-Brabant",
    "wof:name":"V.c. Kreg Rotselaar",
    "wof:placetype":"venue"
},
  "geometry": {"coordinates":[4.6971678734,50.9333648682],"type":"Point"}
}