{
  "type": "Feature",
  "properties": {
    "addr:full":"Sint-goriksplein 4 Haaltert Oost-Vlaanderen 9450",
    "addr:housenumber":"4",
    "addr:postcode":"9450",
    "addr:street":"Sint-Goriksplein",
    "iso:country":"BE",
    "sg:address":"Sint-goriksplein 4",
    "sg:city":"Haaltert",
    "sg:orig_category":"Brood, gebak and snoepgoed",
    "sg:phone":"+32 53 83 02 43",
    "sg:postcode":"9450",
    "sg:province":"Oost-Vlaanderen",
    "wof:name":"Bakkerij Van Durme",
    "wof:placetype":"venue"
},
  "geometry": {"coordinates":[4.0056090355,50.9014587402],"type":"Point"}
}