{
  "type": "Feature",
  "properties": {
    "addr:full":"Dorp 45 Herselt Antwerpen 2230",
    "addr:housenumber":"45",
    "addr:postcode":"2230",
    "addr:street":"Dorp",
    "iso:country":"BE",
    "sg:address":"Dorp 45",
    "sg:city":"Herselt",
    "sg:classifiers":[
        {
            "category":"Cafe",
            "type":"Food & Drink"
        }
    ],
    "sg:phone":"+32 14 54 13 66",
    "sg:postcode":"2230",
    "sg:province":"Antwerpen",
    "sg:tags":[
        "caf\u00e9s"
    ],
    "wof:name":"Caf\u00c9 't Hoekske",
    "wof:placetype":"venue"
},
  "geometry": {"coordinates":[4.8819890022,51.0529556274],"type":"Point"}
}