{
  "type": "Feature",
  "properties": {
    "addr:full":"Liersesteenweg 191 Mortsel Antwerpen 2640",
    "addr:housenumber":"191",
    "addr:postcode":"2640",
    "addr:street":"Liersesteenweg",
    "iso:country":"BE",
    "sg:address":"Liersesteenweg 191",
    "sg:city":"Mortsel",
    "sg:classifiers":[
        {
            "category":"Professional",
            "subcategory":"Management & Consulting",
            "type":"Services"
        }
    ],
    "sg:phone":"+32 3 454 30 00",
    "sg:postcode":"2640",
    "sg:province":"Antwerpen",
    "sg:tags":[
        "tax-consultants"
    ],
    "wof:name":"Vercammen E",
    "wof:placetype":"venue"
},
  "geometry": {"coordinates":[4.4694399834,51.1690101624],"type":"Point"}
}