{
  "type": "Feature",
  "properties": {
    "addr:full":"Chauss\u00c9e Des Champs 65 Lasne Brabant Wallon 1380",
    "addr:housenumber":"65",
    "addr:postcode":"1380",
    "addr:street":"Chausse\u0301E Des Champs",
    "iso:country":"BE",
    "sg:address":"Chauss\u00c9e Des Champs 65",
    "sg:city":"Lasne",
    "sg:classifiers":[
        {
            "category":"Professional",
            "subcategory":"Business Services",
            "type":"Services"
        }
    ],
    "sg:phone":"+32 2 653 21 44",
    "sg:postcode":"1380",
    "sg:province":"Brabant Wallon",
    "sg:tags":[
        "aux",
        "diver",
        "entreprises"
    ],
    "wof:name":"Remisco",
    "wof:placetype":"venue"
},
  "geometry": {"coordinates":[4.483235836,50.6850166321],"type":"Point"}
}