{
  "type": "Feature",
  "properties": {
    "iso:country":"BE",
    "sg:address":"Meulesteedsesteenweg 7",
    "sg:city":"Gent",
    "sg:classifiers":[
        {
            "category":"Professional",
            "subcategory":"Testing Lab",
            "type":"Services"
        }
    ],
    "sg:phone":"+32 9 251 05 39",
    "sg:postcode":"9000",
    "sg:province":"Oost-Vlaanderen",
    "sg:tags":[
        "chemist"
    ],
    "wof:name":"Depoorter",
    "wof:placetype":"venue"
},
  "geometry": {"coordinates":[3.7308580875,51.0737419128],"type":"Point"}
}