{
  "type": "Feature",
  "properties": {
    "iso:country":"BE",
    "sg:address":"Brieleke 16",
    "sg:city":"Wommelgem",
    "sg:orig_category":"RESTAURANTS: CENTRES DE FITNESS. COURS DE DANSE. ACTIVIT\u00c9S R\u00c9CR\u00c9ATIVES DIVERSES. INSTALLATIONS AND T",
    "sg:phone":"+32 3 354 11 99",
    "sg:postcode":"2160",
    "sg:province":"Antwerpen",
    "wof:name":"Synergie Welness-point",
    "wof:placetype":"venue"
},
  "geometry": {"coordinates":[4.5155038834,51.2021331787],"type":"Point"}
}