{
  "type": "Feature",
  "properties": {
    "iso:country":"BE",
    "sg:address":"Avenue De La Gare 33",
    "sg:city":"Hotton",
    "sg:classifiers":[
        {
            "category":"Health Services",
            "subcategory":"Health Practitioner",
            "type":"Services"
        }
    ],
    "sg:phone":"+32 84 46 66 80",
    "sg:postcode":"6990",
    "sg:province":"Luxembourg",
    "sg:tags":[
        "physiotherapist"
    ],
    "wof:name":"Beyers M",
    "wof:placetype":"venue"
},
  "geometry": {"coordinates":[5.4393901825,50.2735443115],"type":"Point"}
}