{
  "type": "Feature",
  "properties": {
    "addr:full":"Galerie Du Roi 11 Bruxelles Bruxelles-Capitale 1000",
    "addr:housenumber":"11",
    "addr:postcode":"1000",
    "addr:street":"Galerie Du Roi",
    "iso:country":"BE",
    "sg:address":"Galerie Du Roi 11",
    "sg:city":"Bruxelles",
    "sg:orig_category":"Non-Classified Establishments",
    "sg:phone":"+32 2 502 03 12",
    "sg:postcode":"1000",
    "sg:province":"Bruxelles-Capitale",
    "wof:name":"De Keghel A.g.",
    "wof:placetype":"venue"
},
  "geometry": {"coordinates":[4.3330068588,50.8313674927],"type":"Point"}
}