{
  "type": "Feature",
  "properties": {
    "addr:full":"Grote Baan 124 Hulshout Antwerpen 2235",
    "addr:housenumber":"124",
    "addr:postcode":"2235",
    "addr:street":"Grote Baan",
    "iso:country":"BE",
    "sg:address":"Grote Baan 124",
    "sg:city":"Hulshout",
    "sg:classifiers":[
        {
            "category":"Bars & Pubs",
            "type":"Food & Drink"
        }
    ],
    "sg:phone":"+32 15 22 22 35",
    "sg:postcode":"2235",
    "sg:province":"Antwerpen",
    "wof:name":"Onder Den Toren",
    "wof:placetype":"venue"
},
  "geometry": {"coordinates":[4.7913417816,51.0746383667],"type":"Point"}
}