{
  "type": "Feature",
  "properties": {
    "iso:country":"BE",
    "sg:address":"Hogebrugstraat 11",
    "sg:city":"Veurne",
    "sg:classifiers":[
        {
            "category":"Metro Station",
            "type":"Transportation"
        }
    ],
    "sg:phone":"+32 58 31 12 13",
    "sg:postcode":"8630",
    "sg:province":"West-Vlaanderen",
    "sg:tags":[
        "repair",
        "ship",
        "mainten",
        "-"
    ],
    "wof:name":"Vandenbussche A",
    "wof:placetype":"venue"
},
  "geometry": {"coordinates":[2.6582200527,51.0690116882],"type":"Point"}
}