{
  "type": "Feature",
  "properties": {
    "addr:full":"Het Dorlik 16 Hasselt Limburg 3500",
    "addr:housenumber":"16",
    "addr:postcode":"3500",
    "iso:country":"BE",
    "sg:address":"Het Dorlik 16",
    "sg:city":"Hasselt",
    "sg:orig_category":"Imprimeries and copyshops. Agences de publicit\u00e9",
    "sg:phone":"+32 11 22 42 16",
    "sg:postcode":"3500",
    "sg:province":"Limburg",
    "wof:name":"Publi-driesen",
    "wof:placetype":"venue"
},
  "geometry": {"coordinates":[5.3640561104,50.9240875244],"type":"Point"}
}