{
  "type": "Feature",
  "properties": {
    "iso:country":"BE",
    "sg:address":"Dokter Verdurmenstraat 14",
    "sg:city":"Sint-niklaas",
    "sg:classifiers":[
        {
            "category":"Health Services",
            "subcategory":"Doctor",
            "type":"Services"
        }
    ],
    "sg:phone":"+32 3 777 12 93",
    "sg:postcode":"9100",
    "sg:province":"Oost-Vlaanderen",
    "sg:tags":[
        "medicinephysicians",
        "surgeon"
    ],
    "wof:name":"Janssens Marc",
    "wof:placetype":"venue"
},
  "geometry": {"coordinates":[4.1435680389,51.1675071716],"type":"Point"}
}