{
  "type": "Feature",
  "properties": {
    "addr:full":"Industriepark Berkenhoek 10 Onze-lieve-vrouw-waver Antwerpen 2861",
    "addr:housenumber":"10",
    "addr:postcode":"2861",
    "addr:street":"Industriepark Berkenhoek",
    "iso:country":"BE",
    "sg:address":"Industriepark Berkenhoek 10",
    "sg:city":"Onze-lieve-vrouw-waver",
    "sg:orig_category":"Non-Classified Establishments",
    "sg:phone":"+32 15 75 49 59",
    "sg:postcode":"2861",
    "sg:province":"Antwerpen",
    "wof:name":"Verbiest Nv",
    "wof:placetype":"venue"
},
  "geometry": {"coordinates":[4.5678691864,51.0541992188],"type":"Point"}
}