{
  "type": "Feature",
  "properties": {
    "iso:country":"BE",
    "sg:address":"Rue De Tournai 119",
    "sg:city":"Tournai",
    "sg:orig_category":"Entretien and r\u00e9parations de voitures",
    "sg:phone":"+32 69 21 03 00",
    "sg:postcode":"7520",
    "sg:province":"Hainaut",
    "wof:name":"V.d.c. Car",
    "wof:placetype":"venue"
},
  "geometry": {"coordinates":[3.34365201,50.6472702026],"type":"Point"}
}