{
  "type": "Feature",
  "properties": {
    "iso:country":"BE",
    "sg:address":"Bovenhoek 30",
    "sg:city":"Lebbeke",
    "sg:orig_category":"Sportclubs",
    "sg:phone":"+32 53 78 75 26",
    "sg:postcode":"9280",
    "sg:province":"Oost-Vlaanderen",
    "wof:name":"Wandelclub Winsia",
    "wof:placetype":"venue"
},
  "geometry": {"coordinates":[4.086725235,50.9805717468],"type":"Point"}
}