{
  "type": "Feature",
  "properties": {
    "iso:country":"BE",
    "sg:address":"Rue De France 48ba",
    "sg:city":"Verviers",
    "sg:orig_category":"Pr\u00eats hypoth\u00e9caires and cr\u00e9dits immobiliers. Assurances. Cr\u00e9dit \u00e0 la consommation",
    "sg:phone":"+32 87 29 28 80",
    "sg:postcode":"4800",
    "sg:province":"Li\u00e8ge",
    "wof:name":"Groupassur",
    "wof:placetype":"venue"
},
  "geometry": {"coordinates":[5.8603539467,50.587059021],"type":"Point"}
}