{
  "type": "Feature",
  "properties": {
    "iso:country":"BE",
    "sg:address":"Hardenvoort 1",
    "sg:city":"Antwerpen",
    "sg:classifiers":[
        {
            "category":"Professional",
            "subcategory":"Engineering",
            "type":"Services"
        }
    ],
    "sg:phone":"+32 3 225 03 35",
    "sg:postcode":"2060",
    "sg:province":"Antwerpen",
    "sg:tags":[
        "workshop"
    ],
    "wof:name":"Electro Marine Plaatbewerking",
    "wof:placetype":"venue"
},
  "geometry": {"coordinates":[4.4238939285,51.2321243286],"type":"Point"}
}