{
  "type": "Feature",
  "properties": {
    "addr:full":"Hoevenstraat 5 Maaseik Limburg 3680",
    "addr:housenumber":"5",
    "addr:postcode":"3680",
    "addr:street":"Hoevenstraat",
    "iso:country":"BE",
    "sg:address":"Hoevenstraat 5",
    "sg:city":"Maaseik",
    "sg:orig_category":"M\u00e9decins and sp\u00e9cialistes",
    "sg:phone":"+32 89 86 31 68",
    "sg:postcode":"3680",
    "sg:province":"Limburg",
    "wof:name":"Roger Kuipers",
    "wof:placetype":"venue"
},
  "geometry": {"coordinates":[5.791285038,51.0954208374],"type":"Point"}
}