{
  "type": "Feature",
  "properties": {
    "addr:full":"Avenue Georges Truffaut 42 Liege Li\u00e8ge 4020",
    "addr:housenumber":"42",
    "addr:postcode":"4020",
    "addr:street":"Avenue Georges Truffaut",
    "iso:country":"BE",
    "sg:address":"Avenue Georges Truffaut 42",
    "sg:city":"Liege",
    "sg:orig_category":"Winkelinrichting and handelsuitrusting Gh",
    "sg:phone":"+32 4 362 22 23",
    "sg:postcode":"4020",
    "sg:province":"Li\u00e8ge",
    "wof:name":"Karcher-thys",
    "wof:placetype":"venue"
},
  "geometry": {"coordinates":[5.6116957664,50.6498031616],"type":"Point"}
}