{
  "type": "Feature",
  "properties": {
    "addr:full":"Sint-pieterskaai 14b2 Brugge West-Vlaanderen 8000",
    "addr:housenumber":"14b2",
    "addr:postcode":"8000",
    "addr:street":"Sint-Pieterskaai",
    "iso:country":"BE",
    "sg:address":"Sint-pieterskaai 14b2",
    "sg:city":"Brugge",
    "sg:orig_category":"Architecten",
    "sg:phone":"+32 50 31 49 95",
    "sg:postcode":"8000",
    "sg:province":"West-Vlaanderen",
    "wof:name":"Jan Martele",
    "wof:placetype":"venue"
},
  "geometry": {"coordinates":[3.2368268967,51.2163162231],"type":"Point"}
}