{
  "type": "Feature",
  "properties": {
    "iso:country":"BE",
    "sg:address":"Route De La Barri\u00c8re 78",
    "sg:city":"Tenneville",
    "sg:classifiers":[
        {
            "category":"Travel",
            "subcategory":"Hotels & Motels",
            "type":"Entertainment"
        }
    ],
    "sg:phone":"+32 84 45 51 85",
    "sg:postcode":"6971",
    "sg:province":"Luxembourg",
    "sg:tags":[
        "restaurant"
    ],
    "wof:name":"Restaurant Les Bruy\u00c8res",
    "wof:placetype":"venue"
},
  "geometry": {"coordinates":[5.4763689041,50.1050033569],"type":"Point"}
}