{
  "type": "Feature",
  "properties": {
    "addr:full":"Rue Emile Vandervelde 42 Beyne-heusay Li\u00e8ge 4610",
    "addr:housenumber":"42",
    "addr:postcode":"4610",
    "addr:street":"Rue Emile Vandervelde",
    "iso:country":"BE",
    "sg:address":"Rue Emile Vandervelde 42",
    "sg:city":"Beyne-heusay",
    "sg:classifiers":[
        {
            "category":"Restaurant",
            "type":"Food & Drink"
        }
    ],
    "sg:phone":"+32 4 362 66 04",
    "sg:postcode":"4610",
    "sg:province":"Li\u00e8ge",
    "wof:name":"Glacier Chez Marie",
    "wof:placetype":"venue"
},
  "geometry": {"coordinates":[5.6726999283,50.6403388977],"type":"Point"}
}