{
  "type": "Feature",
  "properties": {
    "iso:country":"BE",
    "sg:address":"Guido Gezellestraat 102",
    "sg:city":"Aartselaar",
    "sg:orig_category":"Artsen and specialisten",
    "sg:phone":"+32 3 877 11 57",
    "sg:postcode":"2630",
    "sg:province":"Antwerpen",
    "wof:name":"Philippe Lebrun",
    "wof:placetype":"venue"
},
  "geometry": {"coordinates":[4.3814101219,51.1366577148],"type":"Point"}
}