{
  "type": "Feature",
  "properties": {
    "addr:full":"Rue Des Deux Tilleuls 14a Herve (xhendelesse) Li\u00e8ge 4652",
    "addr:housenumber":"14a",
    "addr:postcode":"4652",
    "addr:street":"Rue Des Deux Tilleuls",
    "iso:country":"BE",
    "sg:address":"Rue Des Deux Tilleuls 14a",
    "sg:city":"Herve (xhendelesse)",
    "sg:classifiers":[
        {
            "category":"Government",
            "subcategory":"Fire Station",
            "type":"Public Place"
        }
    ],
    "sg:phone":"+32 87 66 21 15",
    "sg:postcode":"4652",
    "sg:province":"Li\u00e8ge",
    "sg:tags":[
        "installation",
        "-",
        "air conditioning"
    ],
    "wof:name":"A.c.v. Sprl",
    "wof:placetype":"venue"
},
  "geometry": {"coordinates":[5.7697892189,50.6231575012],"type":"Point"}
}