{
  "type": "Feature",
  "properties": {
    "addr:full":"Rue Octave Mahieu 37 Saint-ghislain (hautrage) Hainaut 7334",
    "addr:housenumber":"37",
    "addr:postcode":"7334",
    "addr:street":"Rue Octave Mahieu",
    "iso:country":"BE",
    "sg:address":"Rue Octave Mahieu 37",
    "sg:city":"Saint-ghislain (hautrage)",
    "sg:classifiers":[
        {
            "category":"Manufacturing",
            "subcategory":"Textiles",
            "type":"Manufacturing & Wholesale Goods"
        }
    ],
    "sg:phone":"+32 65 62 03 71",
    "sg:postcode":"7334",
    "sg:province":"Hainaut",
    "sg:tags":[
        "refractory",
        "material"
    ],
    "wof:name":"Firme Emile Lebailly",
    "wof:placetype":"venue"
},
  "geometry": {"coordinates":[3.7644500732,50.479675293],"type":"Point"}
}