{
  "type": "Feature",
  "properties": {
    "addr:full":"Molenweg 27 Riemst Limburg 3770",
    "addr:housenumber":"27",
    "addr:postcode":"3770",
    "addr:street":"Molenweg",
    "iso:country":"BE",
    "sg:address":"Molenweg 27",
    "sg:city":"Riemst",
    "sg:orig_category":"Charpentes and couvertures",
    "sg:phone":"+32 12 45 52 56",
    "sg:postcode":"3770",
    "sg:province":"Limburg",
    "wof:name":"Duchateau Gebrs",
    "wof:placetype":"venue"
},
  "geometry": {"coordinates":[5.584195137,50.829624176],"type":"Point"}
}