{
  "type": "Feature",
  "properties": {
    "addr:full":"Avenue Brugmann 61 Forest Bruxelles-Capitale 1190",
    "addr:housenumber":"61",
    "addr:postcode":"1190",
    "addr:street":"Avenue Brugmann",
    "iso:country":"BE",
    "sg:address":"Avenue Brugmann 61",
    "sg:city":"Forest",
    "sg:orig_category":"Mutualities",
    "sg:phone":"+32 2 344 41 10",
    "sg:postcode":"1190",
    "sg:province":"Bruxelles-Capitale",
    "wof:name":"Mutuelle Du Coll\u00e8ge Des M\u00e9decins",
    "wof:placetype":"venue"
},
  "geometry": {"coordinates":[4.3520231247,50.8205337524],"type":"Point"}
}