{
  "type": "Feature",
  "properties": {
    "addr:full":"Rue Edison 38 Seraing Li\u00e8ge 4100",
    "addr:housenumber":"38",
    "addr:postcode":"4100",
    "addr:street":"Rue Edison",
    "iso:country":"BE",
    "sg:address":"Rue Edison 38",
    "sg:city":"Seraing",
    "sg:classifiers":[
        {
            "category":"Manufacturing",
            "subcategory":"Tools & Machinery",
            "type":"Manufacturing & Wholesale Goods"
        }
    ],
    "sg:phone":"+32 4 336 81 76",
    "sg:postcode":"4100",
    "sg:province":"Li\u00e8ge",
    "sg:tags":[
        "-"
    ],
    "wof:name":"Gaspari Sa",
    "wof:placetype":"venue"
},
  "geometry": {"coordinates":[5.4949541092,50.5792274475],"type":"Point"}
}