{
  "type": "Feature",
  "properties": {
    "addr:full":"Rozeweideweg 5 Box 1 Rhode-saint-gen\u00e8se Vlaams-Brabant 1640",
    "addr:housenumber":"5;1",
    "addr:postcode":"1640",
    "addr:street":"Rozeweideweg;Box",
    "iso:country":"BE",
    "sg:address":"Rozeweideweg 5 Box 1",
    "sg:city":"Rhode-saint-gen\u00e8se",
    "sg:classifiers":[
        {
            "category":"Communications",
            "type":"Services"
        }
    ],
    "sg:phone":"+32 2 380 59 12",
    "sg:postcode":"1640",
    "sg:province":"Vlaams-Brabant",
    "sg:tags":[
        "translator"
    ],
    "wof:name":"Desmet M",
    "wof:placetype":"venue"
},
  "geometry": {"coordinates":[4.3525099754,50.7440490723],"type":"Point"}
}