{
  "type": "Feature",
  "properties": {
    "iso:country":"BE",
    "sg:address":"Zoning Industriel - Rue De Somtet 9998d",
    "sg:city":"Mettet",
    "sg:orig_category":"Loodgieterij, verwarming and sanitaire installaties",
    "sg:phone":"+32 71 72 71 06",
    "sg:postcode":"5640",
    "sg:province":"Namur",
    "wof:name":"Lefebvre & Fils",
    "wof:placetype":"venue"
},
  "geometry": {"coordinates":[4.652695179,50.3047714233],"type":"Point"}
}