{
  "type": "Feature",
  "properties": {
    "iso:country":"BE",
    "sg:address":"De Stassartstraat 48",
    "sg:city":"Elsene/ixelles",
    "sg:orig_category":"Modellenbureaus",
    "sg:phone":"+32 2 289 11 89",
    "sg:postcode":"1050",
    "sg:province":"Bruxelles-Capitale",
    "wof:name":"Dominique Models Agency",
    "wof:placetype":"venue"
},
  "geometry": {"coordinates":[4.3608751297,50.8364524841],"type":"Point"}
}