{
  "type": "Feature",
  "properties": {
    "addr:full":"Spreet 12-2 Lier Antwerpen 2500",
    "addr:housenumber":"12-2",
    "addr:postcode":"2500",
    "addr:street":"Spreet",
    "iso:country":"BE",
    "sg:address":"Spreet 12-2",
    "sg:city":"Lier",
    "sg:classifiers":[
        {
            "category":"Professional",
            "subcategory":"Management & Consulting",
            "type":"Services"
        }
    ],
    "sg:phone":"+32 3 482 29 39",
    "sg:postcode":"2500",
    "sg:province":"Antwerpen",
    "sg:tags":[
        "-",
        "processing",
        "data",
        "consultant"
    ],
    "wof:name":"Acritec Bvba",
    "wof:placetype":"venue"
},
  "geometry": {"coordinates":[4.6065440178,51.1160888672],"type":"Point"}
}