{
  "type": "Feature",
  "properties": {
    "addr:full":"Destelbergenstraat 64 Gent (sint-amandsberg) Oost-Vlaanderen 9040",
    "addr:housenumber":"64",
    "addr:postcode":"9040",
    "addr:street":"Destelbergenstraat",
    "iso:country":"BE",
    "sg:address":"Destelbergenstraat 64",
    "sg:city":"Gent (sint-amandsberg)",
    "sg:orig_category":"Non-Classified Establishments",
    "sg:phone":"+32 9 218 80 80",
    "sg:postcode":"9040",
    "sg:province":"Oost-Vlaanderen",
    "wof:name":"Vlevy Nv",
    "wof:placetype":"venue"
},
  "geometry": {"coordinates":[3.7557470798,51.050453186],"type":"Point"}
}