{
  "type": "Feature",
  "properties": {
    "addr:full":"Plantinmoretuslei 126 Antwerpen Antwerpen 2018",
    "addr:housenumber":"126",
    "addr:postcode":"2018",
    "iso:country":"BE",
    "sg:address":"Plantinmoretuslei 126",
    "sg:city":"Antwerpen",
    "sg:orig_category":"Epiceries",
    "sg:phone":"+32 3 272 27 36",
    "sg:postcode":"2018",
    "sg:province":"Antwerpen",
    "wof:name":"Flower 2",
    "wof:placetype":"venue"
},
  "geometry": {"coordinates":[4.4295101166,51.2094345093],"type":"Point"}
}