{
  "type": "Feature",
  "properties": {
    "addr:full":"Peperstraat Tienen (groot) Vlaams-Brabant 3300",
    "addr:postcode":"3300",
    "addr:street":"Peperstraat;Groot Vlaams-Brabant",
    "iso:country":"BE",
    "sg:address":"Peperstraat",
    "sg:city":"Tienen (groot)",
    "sg:orig_category":"Bloemen and planten",
    "sg:phone":"+32 16 78 01 05",
    "sg:postcode":"3300",
    "sg:province":"Vlaams-Brabant",
    "wof:name":"De Papaver",
    "wof:placetype":"venue"
},
  "geometry": {"coordinates":[4.9375100136,50.8065109253],"type":"Point"}
}