{
  "type": "Feature",
  "properties": {
    "iso:country":"BE",
    "sg:address":"Churchilllaan 177",
    "sg:city":"Schoten",
    "sg:orig_category":"Schoonheidssalons",
    "sg:phone":"+32 3 658 22 27",
    "sg:postcode":"2900",
    "sg:province":"Antwerpen",
    "wof:name":"N. Lenaerts",
    "wof:placetype":"venue"
},
  "geometry": {"coordinates":[4.4866991043,51.2495880127],"type":"Point"}
}