{
  "type": "Feature",
  "properties": {
    "iso:country":"BE",
    "sg:address":"Rue Bon Air 19",
    "sg:city":"Genappe",
    "sg:orig_category":"Dierenartsen",
    "sg:phone":"+32 67 77 31 15",
    "sg:postcode":"1470",
    "sg:province":"Brabant Wallon",
    "wof:name":"Pierre Dive",
    "wof:placetype":"venue"
},
  "geometry": {"coordinates":[4.4802441597,50.5981140137],"type":"Point"}
}