{
  "type": "Feature",
  "properties": {
    "iso:country":"BE",
    "sg:address":"Rue De La Chapelle 3",
    "sg:city":"Lessines",
    "sg:orig_category":"Eleveurs de bovins",
    "sg:phone":"+32 68 33 27 79",
    "sg:postcode":"7861",
    "sg:province":"Hainaut",
    "wof:name":"Robert Lefevre",
    "wof:placetype":"venue"
},
  "geometry": {"coordinates":[3.7923440933,50.6985359192],"type":"Point"}
}