{
  "type": "Feature",
  "properties": {
    "iso:country":"BE",
    "sg:address":"Overleiestraat 17",
    "sg:city":"Kortrijk",
    "sg:classifiers":[
        {
            "category":"Manufacturing",
            "subcategory":"Textiles",
            "type":"Manufacturing & Wholesale Goods"
        }
    ],
    "sg:phone":"+32 56 35 65 66",
    "sg:postcode":"8500",
    "sg:province":"West-Vlaanderen",
    "sg:tags":[
        "linen",
        "clothing",
        "fabric"
    ],
    "wof:name":"Vanneste Philip Nv",
    "wof:placetype":"venue"
},
  "geometry": {"coordinates":[3.2606639862,50.8321151733],"type":"Point"}
}