{
  "type": "Feature",
  "properties": {
    "iso:country":"BE",
    "sg:address":"Raalbeeklaan 8",
    "sg:city":"Leuven",
    "sg:orig_category":"Diverse bedrijfsbeheeradviesbureaus",
    "sg:phone":"+32 16 40 44 11",
    "sg:postcode":"3001",
    "sg:province":"Vlaams-Brabant",
    "wof:name":"Bruda",
    "wof:placetype":"venue"
},
  "geometry": {"coordinates":[4.6750650406,50.8538475037],"type":"Point"}
}