{
  "type": "Feature",
  "properties": {
    "addr:full":"Grand-rue 15-17 Chimay Hainaut 6460",
    "addr:housenumber":"15-17",
    "addr:postcode":"6460",
    "addr:street":"Grand-Rue",
    "iso:country":"BE",
    "sg:address":"Grand-rue 15-17",
    "sg:city":"Chimay",
    "sg:orig_category":"Baby- and kinderkleding Dameskledingzaken Herenkledingzaken Kleding",
    "sg:phone":"+32 60 21 13 95",
    "sg:postcode":"6460",
    "sg:province":"Hainaut",
    "wof:name":"Coene Michel",
    "wof:placetype":"venue"
},
  "geometry": {"coordinates":[4.3142871857,50.048576355],"type":"Point"}
}