{
  "type": "Feature",
  "properties": {
    "addr:full":"Place Aux Foires 23 Marche-en-famenne Luxembourg 6900",
    "addr:housenumber":"23",
    "addr:postcode":"6900",
    "addr:street":"Place Aux Foires",
    "iso:country":"BE",
    "sg:address":"Place Aux Foires 23",
    "sg:city":"Marche-en-famenne",
    "sg:orig_category":"Juwelen and horloges Opticiens",
    "sg:phone":"+32 84 31 10 94",
    "sg:postcode":"6900",
    "sg:province":"Luxembourg",
    "wof:name":"Ledoux",
    "wof:placetype":"venue"
},
  "geometry": {"coordinates":[5.3449950218,50.225894928],"type":"Point"}
}