{
  "type": "Feature",
  "properties": {
    "addr:full":"Hullekenstraat 19 Kortrijk West-Vlaanderen 8510",
    "addr:housenumber":"19",
    "addr:postcode":"8510",
    "addr:street":"Hullekenstraat",
    "iso:country":"BE",
    "sg:address":"Hullekenstraat 19",
    "sg:city":"Kortrijk",
    "sg:orig_category":"Landmeters and schatters",
    "sg:phone":"+32 56 20 20 77",
    "sg:postcode":"8510",
    "sg:province":"West-Vlaanderen",
    "wof:name":"Verburo",
    "wof:placetype":"venue"
},
  "geometry": {"coordinates":[3.2430689335,50.8081016541],"type":"Point"}
}