{
  "type": "Feature",
  "properties": {
    "addr:full":"Rue Du Midi 6-3 Renaix Oost-Vlaanderen 9600",
    "addr:housenumber":"6-3",
    "addr:postcode":"9600",
    "addr:street":"Rue Du Midi",
    "iso:country":"BE",
    "sg:address":"Rue Du Midi 6-3",
    "sg:city":"Renaix",
    "sg:classifiers":[
        {
            "category":"Shopping",
            "subcategory":"Jewelry",
            "type":"Retail Goods"
        }
    ],
    "sg:phone":"+32 55 21 92 57",
    "sg:postcode":"9600",
    "sg:province":"Oost-Vlaanderen",
    "sg:tags":[
        "purchase",
        "-",
        "sale",
        "gold"
    ],
    "wof:name":"Geldhofshop",
    "wof:placetype":"venue"
},
  "geometry": {"coordinates":[3.6036369801,50.7465438843],"type":"Point"}
}