{
  "type": "Feature",
  "properties": {
    "iso:country":"BE",
    "sg:address":"Diegemstraat 46",
    "sg:city":"Zaventem",
    "sg:classifiers":[
        {
            "category":"Wholesale",
            "subcategory":"Medical Equipment & Supplies",
            "type":"Manufacturing & Wholesale Goods"
        }
    ],
    "sg:phone":"+32 2 721 44 76",
    "sg:postcode":"1930",
    "sg:province":"Vlaams-Brabant",
    "sg:tags":[
        "instrument",
        "apparatus"
    ],
    "wof:name":"Pie Medical Benelux / Esaote Nv",
    "wof:placetype":"venue"
},
  "geometry": {"coordinates":[4.4660611153,50.8881492615],"type":"Point"}
}