{
  "type": "Feature",
  "properties": {
    "addr:full":"Grand'rue 18 Charleroi Hainaut 6000",
    "addr:housenumber":"18",
    "addr:postcode":"6000",
    "addr:street":"Grand'Rue;Hainaut",
    "iso:country":"BE",
    "sg:address":"Grand'rue 18",
    "sg:city":"Charleroi",
    "sg:orig_category":"Entretien and r\u00e9parations de voitures. D\u00e9taillants en pi\u00e8ces and accessoires de voitures",
    "sg:phone":"+32 71 41 79 73",
    "sg:postcode":"6000",
    "sg:province":"Hainaut",
    "wof:name":"Midas",
    "wof:placetype":"venue"
},
  "geometry": {"coordinates":[4.4527988434,50.4181480408],"type":"Point"}
}