{
  "type": "Feature",
  "properties": {
    "addr:full":"Eikelplein 54 Tessenderlo Limburg 3980",
    "addr:housenumber":"54",
    "addr:postcode":"3980",
    "addr:street":"Eikelplein",
    "iso:country":"BE",
    "sg:address":"Eikelplein 54",
    "sg:city":"Tessenderlo",
    "sg:orig_category":"Etablissements Erotiques",
    "sg:phone":"+32 13 66 22 67",
    "sg:postcode":"3980",
    "sg:province":"Limburg",
    "wof:name":"Caf\u00c9 Eikelhof",
    "wof:placetype":"venue"
},
  "geometry": {"coordinates":[5.1278362274,51.0682106018],"type":"Point"}
}