{
  "type": "Feature",
  "properties": {
    "addr:full":"Rue De Montm\u00e9dy 14 Virton Luxembourg 6760",
    "addr:housenumber":"14",
    "addr:postcode":"6760",
    "addr:street":"Rue De Montme\u0301Dy",
    "iso:country":"BE",
    "sg:address":"Rue De Montm\u00e9dy 14",
    "sg:city":"Virton",
    "sg:classifiers":[
        {
            "category":"Retail",
            "subcategory":"Laundry & Dry Cleaning",
            "type":"Services"
        }
    ],
    "sg:phone":"+32 63 57 17 75",
    "sg:postcode":"6760",
    "sg:province":"Luxembourg",
    "sg:tags":[
        "self",
        "-"
    ],
    "wof:name":"Lavoir L'oceane",
    "wof:placetype":"venue"
},
  "geometry": {"coordinates":[5.5182051659,49.5649375916],"type":"Point"}
}