{
  "type": "Feature",
  "properties": {
    "addr:full":"Vrijheid 211 Hoogstraten Antwerpen 2320",
    "addr:housenumber":"211",
    "addr:postcode":"2320",
    "addr:street":"Vrijheid",
    "iso:country":"BE",
    "sg:address":"Vrijheid 211",
    "sg:city":"Hoogstraten",
    "sg:classifiers":[
        {
            "category":"Shopping",
            "subcategory":"Bicycles & Sporting Goods",
            "type":"Retail Goods"
        }
    ],
    "sg:phone":"+32 3 314 44 61",
    "sg:postcode":"2320",
    "sg:province":"Antwerpen",
    "sg:tags":[
        "article",
        "de",
        "sport",
        "camping"
    ],
    "wof:name":"Alma Sport",
    "wof:placetype":"venue"
},
  "geometry": {"coordinates":[4.7600660324,51.3987159729],"type":"Point"}
}