{
  "type": "Feature",
  "properties": {
    "addr:full":"R\u00e9sidence Les Vanneaux 8 Antoing Hainaut 7640",
    "addr:housenumber":"8",
    "addr:postcode":"7640",
    "iso:country":"BE",
    "sg:address":"R\u00e9sidence Les Vanneaux 8",
    "sg:city":"Antoing",
    "sg:classifiers":[
        {
            "category":"Professional",
            "subcategory":"Computer Services",
            "type":"Services"
        }
    ],
    "sg:phone":"+32 69 44 38 84",
    "sg:postcode":"7640",
    "sg:province":"Hainaut",
    "sg:tags":[
        "-",
        "processing",
        "data",
        "software"
    ],
    "wof:name":"Compuwave Sprl",
    "wof:placetype":"venue"
},
  "geometry": {"coordinates":[3.4519898891,50.565738678],"type":"Point"}
}