{
  "type": "Feature",
  "properties": {
    "addr:full":"Gentweg 12 Evergem Oost-Vlaanderen 9940",
    "addr:housenumber":"12",
    "addr:postcode":"9940",
    "addr:street":"Gentweg;Oost-Vlaanderen",
    "iso:country":"BE",
    "sg:address":"Gentweg 12",
    "sg:city":"Evergem",
    "sg:classifiers":[
        {
            "category":"Professional",
            "subcategory":"Lawyer & Legal Services",
            "type":"Services"
        }
    ],
    "sg:phone":"+32 9 253 90 31",
    "sg:postcode":"9940",
    "sg:province":"Oost-Vlaanderen",
    "sg:tags":[
        "notary"
    ],
    "wof:name":"De Sagher T",
    "wof:placetype":"venue"
},
  "geometry": {"coordinates":[3.7422399521,51.1152458191],"type":"Point"}
}