{
  "type": "Feature",
  "properties": {
    "addr:full":"Rue De Souvret 2 Li\u00e8ge 1 (sclessin) Li\u00e8ge 4000",
    "addr:housenumber":"2;1",
    "addr:postcode":"4000",
    "addr:street":"Rue De Souvret;Sclessin Lie\u0300Ge",
    "iso:country":"BE",
    "sg:address":"Rue De Souvret 2",
    "sg:city":"Li\u00e8ge 1 (sclessin)",
    "sg:classifiers":[
        {
            "category":"Wholesale",
            "subcategory":"Painting Supplies",
            "type":"Manufacturing & Wholesale Goods"
        }
    ],
    "sg:phone":"+32 4 231 11 80",
    "sg:postcode":"4000",
    "sg:province":"Li\u00e8ge",
    "sg:tags":[
        "industrial",
        "-"
    ],
    "wof:name":"T.s.n.",
    "wof:placetype":"venue"
},
  "geometry": {"coordinates":[5.5390868187,50.6088142395],"type":"Point"}
}