{
  "type": "Feature",
  "properties": {
    "addr:full":"Sint-michielsestraat 34 Oostkamp West-Vlaanderen 8020",
    "addr:housenumber":"34",
    "addr:postcode":"8020",
    "addr:street":"Sint-Michielsestraat",
    "iso:country":"BE",
    "sg:address":"Sint-michielsestraat 34",
    "sg:city":"Oostkamp",
    "sg:classifiers":[
        {
            "category":"Farming",
            "subcategory":"Fish & Marine Products",
            "type":"Manufacturing & Wholesale Goods"
        }
    ],
    "sg:phone":"+32 50 39 57 51",
    "sg:postcode":"8020",
    "sg:province":"West-Vlaanderen",
    "sg:tags":[
        "retail",
        "-",
        "shellfish"
    ],
    "wof:name":"Markey Bvba",
    "wof:placetype":"venue"
},
  "geometry": {"coordinates":[3.231235981,51.1772079468],"type":"Point"}
}