{
  "type": "Feature",
  "properties": {
    "addr:full":"Jeugdstraat 20 Hamont-achel Limburg 3930",
    "addr:housenumber":"20",
    "addr:postcode":"3930",
    "addr:street":"Jeugdstraat",
    "iso:country":"BE",
    "sg:address":"Jeugdstraat 20",
    "sg:city":"Hamont-achel",
    "sg:orig_category":"Gespecialiseerde residenti\u00eble bouw",
    "sg:phone":"+32 11 44 81 24",
    "sg:postcode":"3930",
    "sg:province":"Limburg",
    "wof:name":"Albert Emmers",
    "wof:placetype":"venue"
},
  "geometry": {"coordinates":[5.5450549126,51.2511863708],"type":"Point"}
}