{
  "type": "Feature",
  "properties": {
    "addr:full":"Bissegemplaats 8 Kortrijk West-Vlaanderen 8501",
    "addr:housenumber":"8",
    "addr:postcode":"8501",
    "addr:street":"Bissegemplaats",
    "iso:country":"BE",
    "sg:address":"Bissegemplaats 8",
    "sg:city":"Kortrijk",
    "sg:classifiers":[
        {
            "category":"Government",
            "subcategory":"Police Station",
            "type":"Public Place"
        }
    ],
    "sg:phone":"+32 56 35 53 95",
    "sg:postcode":"8501",
    "sg:province":"West-Vlaanderen",
    "sg:tags":[
        "gendarmerie"
    ],
    "wof:name":"Federale Politie",
    "wof:placetype":"venue"
},
  "geometry": {"coordinates":[3.2266991138,50.8233604431],"type":"Point"}
}