{
  "type": "Feature",
  "properties": {
    "iso:country":"BE",
    "sg:address":"Avenue De La Galaxie 29",
    "sg:city":"Waterloo",
    "sg:orig_category":"Rev\u00eatements pour sols and murs. Peinture",
    "sg:phone":"+32 2 354 76 40",
    "sg:postcode":"1410",
    "sg:province":"Brabant Wallon",
    "wof:name":"Entreprises Paquet Henri",
    "wof:placetype":"venue"
},
  "geometry": {"coordinates":[4.4210500717,50.6988639832],"type":"Point"}
}