{
  "type": "Feature",
  "properties": {
    "iso:country":"BE",
    "sg:address":"Aannemersstraat 74",
    "sg:city":"Gent (sint-amandsberg)",
    "sg:classifiers":[
        {
            "category":"Organizations",
            "subcategory":"Community Association",
            "type":"Services"
        }
    ],
    "sg:phone":"+32 9 228 52 60",
    "sg:postcode":"9040",
    "sg:province":"Oost-Vlaanderen",
    "sg:tags":[
        "cultural"
    ],
    "wof:name":"Absint Vzw",
    "wof:placetype":"venue"
},
  "geometry": {"coordinates":[3.7479579449,51.0494346619],"type":"Point"}
}