{
  "type": "Feature",
  "properties": {
    "iso:country":"BE",
    "sg:address":"Place Franklin Roosevelt 22b4",
    "sg:city":"Morlanwelz",
    "sg:orig_category":"Evaluation and estimation de biens immobiliers. Administration d'immeubles",
    "sg:phone":"+32 64 44 43 64",
    "sg:postcode":"7140",
    "sg:province":"Hainaut",
    "wof:name":"Immob. Dobbels Bernard",
    "wof:placetype":"venue"
},
  "geometry": {"coordinates":[4.2483000755,50.4520645142],"type":"Point"}
}