{
  "type": "Feature",
  "properties": {
    "iso:country":"BE",
    "sg:address":"Jeruzalemstraat 16",
    "sg:city":"Wervik",
    "sg:orig_category":"Winkelinrichting and handelsuitrusting Gh",
    "sg:phone":"+32 56 35 06 85",
    "sg:postcode":"8940",
    "sg:province":"West-Vlaanderen",
    "wof:name":"Chocolaterie Caveye",
    "wof:placetype":"venue"
},
  "geometry": {"coordinates":[3.0749080181,50.8115959167],"type":"Point"}
}