{
  "type": "Feature",
  "properties": {
    "iso:country":"BE",
    "sg:address":"Avenue Delchambre 6",
    "sg:city":"Huy",
    "sg:orig_category":"Algemeen secundair onderwijs Technisch and beroeps secundair onderwijs",
    "sg:phone":"+32 85 27 31 00",
    "sg:postcode":"4500",
    "sg:province":"Li\u00e8ge",
    "wof:name":"Institut Enseign. Second.",
    "wof:placetype":"venue"
},
  "geometry": {"coordinates":[5.2404899597,50.5214881897],"type":"Point"}
}