{
  "type": "Feature",
  "properties": {
    "addr:full":"Rue Gahy 2 Momignies Hainaut 6590",
    "addr:housenumber":"2",
    "addr:postcode":"6590",
    "addr:street":"Rue Gahy;Hainaut",
    "iso:country":"BE",
    "sg:address":"Rue Gahy 2",
    "sg:city":"Momignies",
    "sg:orig_category":"RESTAURANTS: H\u00d4TELS",
    "sg:phone":"+32 60 51 10 93",
    "sg:postcode":"6590",
    "sg:province":"Hainaut",
    "wof:name":"Hostellerie Du Gahy",
    "wof:placetype":"venue"
},
  "geometry": {"coordinates":[4.1662049294,50.0316047668],"type":"Point"}
}