{
  "type": "Feature",
  "properties": {
    "addr:full":"Tieltsestraat 12 Harelbeke West-Vlaanderen 8531",
    "addr:housenumber":"12",
    "addr:postcode":"8531",
    "addr:street":"Tieltsestraat",
    "iso:country":"BE",
    "sg:address":"Tieltsestraat 12",
    "sg:city":"Harelbeke",
    "sg:classifiers":[
        {
            "category":"Food & Beverages",
            "subcategory":"Fruits & Vegetables",
            "type":"Retail Goods"
        }
    ],
    "sg:phone":"+32 56 71 14 47",
    "sg:postcode":"8531",
    "sg:province":"West-Vlaanderen",
    "sg:tags":[
        "groenten"
    ],
    "wof:name":"Lucien Vinquier",
    "wof:placetype":"venue"
},
  "geometry": {"coordinates":[3.2958090305,50.8827476501],"type":"Point"}
}