{
  "type": "Feature",
  "properties": {
    "iso:country":"BE",
    "sg:address":"Alsembergse Steenweg 59",
    "sg:city":"Sint-gillis/saint-gilles",
    "sg:orig_category":"Opticiens",
    "sg:phone":"+32 2 537 63 20",
    "sg:postcode":"1060",
    "sg:province":"Bruxelles-Capitale",
    "wof:name":"Optique Slotte",
    "wof:placetype":"venue"
},
  "geometry": {"coordinates":[4.3433279991,50.8248252869],"type":"Point"}
}