{
  "type": "Feature",
  "properties": {
    "addr:full":"Driekerkenstraat 74/1 Bissegem West-Vlaanderen 8501",
    "addr:housenumber":"74 / 1",
    "addr:postcode":"8501",
    "addr:street":"Driekerkenstraat",
    "iso:country":"BE",
    "sg:address":"Driekerkenstraat 74/1",
    "sg:city":"Bissegem",
    "sg:classifiers":[
        {
            "category":"Building & Trades",
            "subcategory":"Cleaning & Sanitation",
            "type":"Services"
        }
    ],
    "sg:phone":"+32 56 35 49 37",
    "sg:postcode":"8501",
    "sg:province":"West-Vlaanderen",
    "sg:tags":[
        "plant",
        "machinery",
        "flax",
        "conditioning"
    ],
    "wof:name":"Charle & Co B.v.b.a.",
    "wof:placetype":"venue"
},
  "geometry": {"coordinates":[3.2295999527,50.820110321],"type":"Point"}
}