{
  "type": "Feature",
  "properties": {
    "addr:full":"Route De Mons 65 Quaregnon Hainaut 7390",
    "addr:housenumber":"65",
    "addr:postcode":"7390",
    "addr:street":"Route De Mons",
    "iso:country":"BE",
    "sg:address":"Route De Mons 65",
    "sg:city":"Quaregnon",
    "sg:orig_category":"G\u00e9om\u00e8tres",
    "sg:phone":"+32 65 78 57 70",
    "sg:postcode":"7390",
    "sg:province":"Hainaut",
    "wof:name":"Michel Dufour",
    "wof:placetype":"venue"
},
  "geometry": {"coordinates":[3.8447499275,50.4402198792],"type":"Point"}
}