{
  "type": "Feature",
  "properties": {
    "iso:country":"BE",
    "sg:address":"Stichelendries 85",
    "sg:city":"Lede",
    "sg:orig_category":"Zuivelproducten",
    "sg:phone":"+32 9 366 16 86",
    "sg:postcode":"9340",
    "sg:province":"Oost-Vlaanderen",
    "wof:name":"Patricia De Winter",
    "wof:placetype":"venue"
},
  "geometry": {"coordinates":[3.8861069679,50.9569969177],"type":"Point"}
}