{
  "type": "Feature",
  "properties": {
    "iso:country":"BE",
    "sg:address":"Turnhoutseweg 11b",
    "sg:city":"Baarle-hertog",
    "sg:classifiers":[
        {
            "category":"Banks & Credit Unions",
            "subcategory":"Investment Brokerage",
            "type":"Services"
        }
    ],
    "sg:phone":"+32 14 69 91 25",
    "sg:postcode":"2387",
    "sg:province":"Antwerpen",
    "sg:tags":[
        "repair",
        "-",
        "installation",
        "sanitary",
        "article"
    ],
    "wof:name":"Jespers Frans Bvba",
    "wof:placetype":"venue"
},
  "geometry": {"coordinates":[4.9315218925,51.4343833923],"type":"Point"}
}