{
  "type": "Feature",
  "properties": {
    "iso:country":"BE",
    "sg:address":"Roger Vandendriesscheln 18b3",
    "sg:city":"Sint-pieters-woluwe/woluwe-saint-pierre",
    "sg:orig_category":"Marketingbureaus Marktonderzoekbureaus",
    "sg:phone":"+32 2 775 01 11",
    "sg:postcode":"1150",
    "sg:province":"Bruxelles-Capitale",
    "wof:name":"Inra-european Coord. Off.",
    "wof:placetype":"venue"
},
  "geometry": {"coordinates":[4.4143028259,50.8344230652],"type":"Point"}
}