{
  "type": "Feature",
  "properties": {
    "addr:full":"Bedrijfsstraat 6 Hamont-achel (hamont) Limburg 3930",
    "addr:housenumber":"6",
    "addr:postcode":"3930",
    "addr:street":"Bedrijfsstraat",
    "iso:country":"BE",
    "sg:address":"Bedrijfsstraat 6",
    "sg:city":"Hamont-achel (hamont)",
    "sg:classifiers":[
        {
            "category":"Professional",
            "subcategory":"Accounting & Tax Preparation",
            "type":"Services"
        }
    ],
    "sg:phone":"+32 11 62 17 27",
    "sg:postcode":"3930",
    "sg:province":"Limburg",
    "sg:tags":[
        "bookkeeper"
    ],
    "wof:name":"Pinxten R",
    "wof:placetype":"venue"
},
  "geometry": {"coordinates":[5.5450549126,51.2511863708],"type":"Point"}
}