{
  "type": "Feature",
  "properties": {
    "addr:full":"Zuidstraat 15 Brussel/bruxelles Bruxelles-Capitale 1000",
    "addr:housenumber":"15",
    "addr:postcode":"1000",
    "addr:street":"Zuidstraat;/",
    "iso:country":"BE",
    "sg:address":"Zuidstraat 15",
    "sg:city":"Brussel/bruxelles",
    "sg:orig_category":"Decoratieve kunst and kunstbenodigdheden",
    "sg:phone":"+32 2 511 48 08",
    "sg:postcode":"1000",
    "sg:province":"Bruxelles-Capitale",
    "wof:name":"Maison D'art",
    "wof:placetype":"venue"
},
  "geometry": {"coordinates":[4.3398108482,50.8436737061],"type":"Point"}
}