{
  "type": "Feature",
  "properties": {
    "iso:country":"BE",
    "sg:address":"Zillekesstraat 8",
    "sg:city":"Tessenderlo",
    "sg:classifiers":[
        {
            "category":"Arena",
            "subcategory":"Sports Club",
            "type":"Entertainment"
        }
    ],
    "sg:phone":"+32 13 66 65 53",
    "sg:postcode":"3980",
    "sg:province":"Limburg",
    "sg:tags":[
        "de"
    ],
    "wof:name":"P.c. Zig Zag Ham",
    "wof:placetype":"venue"
},
  "geometry": {"coordinates":[5.1467409134,51.0623817444],"type":"Point"}
}