{
  "type": "Feature",
  "properties": {
    "addr:full":"Oostnieuwkerkestraat 13 Staden West-Vlaanderen 8840",
    "addr:housenumber":"13",
    "addr:postcode":"8840",
    "addr:street":"Oostnieuwkerkestraat",
    "iso:country":"BE",
    "sg:address":"Oostnieuwkerkestraat 13",
    "sg:city":"Staden",
    "sg:orig_category":"Rundveehouders Varkenskwekers",
    "sg:phone":"+32 51 70 18 13",
    "sg:postcode":"8840",
    "sg:province":"West-Vlaanderen",
    "wof:name":"Andre Demeulenaere",
    "wof:placetype":"venue"
},
  "geometry": {"coordinates":[3.0389249325,50.9575500488],"type":"Point"}
}