{
  "type": "Feature",
  "properties": {
    "iso:country":"BE",
    "sg:address":"Gentseweg 537",
    "sg:city":"Waregem",
    "sg:orig_category":"Epiceries",
    "sg:phone":"+32 56 60 26 50",
    "sg:postcode":"8793",
    "sg:province":"West-Vlaanderen",
    "wof:name":"Magda Espeel",
    "wof:placetype":"venue"
},
  "geometry": {"coordinates":[3.3940219879,50.8962059021],"type":"Point"}
}