{
  "type": "Feature",
  "properties": {
    "addr:full":"Grand Rue 173 Charleroi Hainaut 6000",
    "addr:housenumber":"173",
    "addr:postcode":"6000",
    "addr:street":"Grand Rue;Hainaut",
    "iso:country":"BE",
    "sg:address":"Grand Rue 173",
    "sg:city":"Charleroi",
    "sg:orig_category":"Beveiligingsdiensten and bewakingsbedrijven",
    "sg:phone":"+32 71 41 98 18",
    "sg:postcode":"6000",
    "sg:province":"Hainaut",
    "wof:name":"Top Guards Security",
    "wof:placetype":"venue"
},
  "geometry": {"coordinates":[4.4586901665,50.4209289551],"type":"Point"}
}