{
  "type": "Feature",
  "properties": {
    "addr:full":"Chauss\u00e9e De Forest 291 Bruxelles (forest) Bruxelles-Capitale 1190",
    "addr:housenumber":"291",
    "addr:postcode":"1190",
    "addr:street":"Chausse\u0301E De Forest",
    "iso:country":"BE",
    "sg:address":"Chauss\u00e9e De Forest 291",
    "sg:city":"Bruxelles (forest)",
    "sg:classifiers":[
        {
            "category":"Wholesale",
            "subcategory":"Machinery & Supplies",
            "type":"Manufacturing & Wholesale Goods"
        }
    ],
    "sg:phone":"+32 2 537 59 00",
    "sg:postcode":"1190",
    "sg:province":"Bruxelles-Capitale",
    "sg:tags":[
        "packing"
    ],
    "wof:name":"Mc Technic Sprl",
    "wof:placetype":"venue"
},
  "geometry": {"coordinates":[4.3361492157,50.8249549866],"type":"Point"}
}