{
  "type": "Feature",
  "properties": {
    "addr:full":"Esdreef 15 Merelbeke Oost-Vlaanderen 9820",
    "addr:housenumber":"15",
    "addr:postcode":"9820",
    "addr:street":"Esdreef",
    "iso:country":"BE",
    "sg:address":"Esdreef 15",
    "sg:city":"Merelbeke",
    "sg:classifiers":[
        {
            "category":"Professional",
            "subcategory":"Accounting & Tax Preparation",
            "type":"Services"
        }
    ],
    "sg:phone":"+32 9 230 70 57",
    "sg:postcode":"9820",
    "sg:province":"Oost-Vlaanderen",
    "sg:tags":[
        "bookkeeper"
    ],
    "wof:name":"Devoldere R",
    "wof:placetype":"venue"
},
  "geometry": {"coordinates":[3.74187994,50.9817886353],"type":"Point"}
}