{
  "type": "Feature",
  "properties": {
    "iso:country":"BE",
    "sg:address":"Bessemerstraat 563",
    "sg:city":"Lanaken",
    "sg:orig_category":"Sportclubs",
    "sg:phone":"+32 89 71 44 28",
    "sg:postcode":"3620",
    "sg:province":"Limburg",
    "wof:name":"W.s.v. De Sparrentrippers",
    "wof:placetype":"venue"
},
  "geometry": {"coordinates":[5.6085538864,50.9197311401],"type":"Point"}
}