{
  "type": "Feature",
  "properties": {
    "addr:full":"Dekenstraat 80b1 Leuven Vlaams-Brabant 3000",
    "addr:housenumber":"80b1",
    "addr:postcode":"3000",
    "addr:street":"Dekenstraat",
    "iso:country":"BE",
    "sg:address":"Dekenstraat 80b1",
    "sg:city":"Leuven",
    "sg:orig_category":"M\u00e9decins and sp\u00e9cialistes",
    "sg:phone":"+32 16 22 26 77",
    "sg:postcode":"3000",
    "sg:province":"Vlaams-Brabant",
    "wof:name":"S. Maenhout",
    "wof:placetype":"venue"
},
  "geometry": {"coordinates":[4.7121047974,50.872428894],"type":"Point"}
}