{
  "type": "Feature",
  "properties": {
    "addr:full":"Route De Marlagne 13 Sart-saint-laurent Namur 5070",
    "addr:housenumber":"13",
    "addr:postcode":"5070",
    "addr:street":"Route De Marlagne;Namur",
    "iso:country":"BE",
    "sg:address":"Route De Marlagne 13",
    "sg:city":"Sart-saint-laurent",
    "sg:classifiers":[
        {
            "category":"Utilities",
            "subcategory":"Cable",
            "type":"Services"
        }
    ],
    "sg:phone":"+32 71 71 37 74",
    "sg:postcode":"5070",
    "sg:province":"Namur",
    "sg:tags":[
        "forestry"
    ],
    "wof:name":"Sotex-bois S.p.r.l.",
    "wof:placetype":"venue"
},
  "geometry": {"coordinates":[4.7370238304,50.3998184204],"type":"Point"}
}