{
  "type": "Feature",
  "properties": {
    "iso:country":"BE",
    "sg:address":"Hoogpoort 12",
    "sg:city":"Gent",
    "sg:classifiers":[
        {
            "category":"Shopping",
            "subcategory":"Bicycles & Sporting Goods",
            "type":"Retail Goods"
        }
    ],
    "sg:phone":"+32 9 225 98 30",
    "sg:postcode":"9000",
    "sg:province":"Oost-Vlaanderen",
    "sg:tags":[
        "sport",
        "-"
    ],
    "wof:name":"Sport Flash",
    "wof:placetype":"venue"
},
  "geometry": {"coordinates":[3.7227680683,51.0555076599],"type":"Point"}
}