{
  "type": "Feature",
  "properties": {
    "iso:country":"BE",
    "sg:address":"Rue Jean Belli\u00e8re 37-39",
    "sg:city":"Charleroi (marcinelle)",
    "sg:classifiers":[
        {
            "category":"Health Services",
            "subcategory":"Doctor",
            "type":"Services"
        }
    ],
    "sg:phone":"+32 71 36 30 19",
    "sg:postcode":"6001",
    "sg:province":"Hainaut",
    "sg:tags":[
        "medicinephysicians",
        "surgeon"
    ],
    "wof:name":"Laurent Louis",
    "wof:placetype":"venue"
},
  "geometry": {"coordinates":[4.450835228,50.3954086304],"type":"Point"}
}