{
  "type": "Feature",
  "properties": {
    "addr:full":"Guido Gezellestraat 62 Boom Antwerpen 2850",
    "addr:housenumber":"62",
    "addr:postcode":"2850",
    "addr:street":"Guido Gezellestraat",
    "iso:country":"BE",
    "sg:address":"Guido Gezellestraat 62",
    "sg:city":"Boom",
    "sg:orig_category":"Boucheries",
    "sg:phone":"+32 3 888 09 40",
    "sg:postcode":"2850",
    "sg:province":"Antwerpen",
    "wof:name":"Beenhouwerij Bastaens",
    "wof:placetype":"venue"
},
  "geometry": {"coordinates":[4.3726968765,51.0968742371],"type":"Point"}
}