{
  "type": "Feature",
  "properties": {
    "iso:country":"BE",
    "sg:address":"Rue Du Ti\u00e8ge 155",
    "sg:city":"Oupeye",
    "sg:classifiers":[
        {
            "category":"Building & Trades",
            "subcategory":"Construction",
            "type":"Services"
        }
    ],
    "sg:phone":"+32 4 278 70 50",
    "sg:postcode":"4680",
    "sg:province":"Li\u00e8ge",
    "sg:tags":[
        "installation",
        "-",
        "central",
        "heating"
    ],
    "wof:name":"Aquachauffe Scrl",
    "wof:placetype":"venue"
},
  "geometry": {"coordinates":[5.6340827942,50.7121353149],"type":"Point"}
}