{
  "type": "Feature",
  "properties": {
    "addr:full":"Ringstraat 34 Dendermonde Oost-Vlaanderen 9200",
    "addr:housenumber":"34",
    "addr:postcode":"9200",
    "addr:street":"Ringstraat;Oost-Vlaanderen",
    "iso:country":"BE",
    "sg:address":"Ringstraat 34",
    "sg:city":"Dendermonde",
    "sg:orig_category":"Sportclubs Sportterreinen and installaties behalve sportcentra",
    "sg:phone":"+32 52 21 79 69",
    "sg:postcode":"9200",
    "sg:province":"Oost-Vlaanderen",
    "wof:name":"S.k. Grembergen",
    "wof:placetype":"venue"
},
  "geometry": {"coordinates":[4.109650135,51.0520248413],"type":"Point"}
}