{
  "type": "Feature",
  "properties": {
    "addr:full":"Kattenbos 137 Lommel Limburg 3920",
    "addr:housenumber":"137",
    "addr:postcode":"3920",
    "addr:street":"Kattenbos",
    "iso:country":"BE",
    "sg:address":"Kattenbos 137",
    "sg:city":"Lommel",
    "sg:orig_category":"Benzinestations and brandstoffen",
    "sg:phone":"+32 11 54 08 16",
    "sg:postcode":"3920",
    "sg:province":"Limburg",
    "wof:name":"Tankstation Kattenbos",
    "wof:placetype":"venue"
},
  "geometry": {"coordinates":[5.3065648079,51.2024612427],"type":"Point"}
}