{
  "type": "Feature",
  "properties": {
    "addr:full":"Voie De L'air Pur 207 Chaudfontaine (beaufays) Li\u00e8ge 4052",
    "addr:housenumber":"207",
    "addr:postcode":"4052",
    "addr:street":"Voie De L'Air Pur;Beaufays",
    "iso:country":"BE",
    "sg:address":"Voie De L'air Pur 207",
    "sg:city":"Chaudfontaine (beaufays)",
    "sg:classifiers":[
        {
            "category":"Home & Garden",
            "subcategory":"Home Furnishings",
            "type":"Retail Goods"
        }
    ],
    "sg:phone":"+32 4 368 35 45",
    "sg:postcode":"4052",
    "sg:province":"Li\u00e8ge",
    "sg:tags":[
        "-",
        "bed",
        "mattress"
    ],
    "wof:name":"Techno Bedding",
    "wof:placetype":"venue"
},
  "geometry": {"coordinates":[5.5817270279,50.6415977478],"type":"Point"}
}