{
  "type": "Feature",
  "properties": {
    "iso:country":"BE",
    "sg:address":"Rue De Gawday 67",
    "sg:city":"Andenne (maizeret)",
    "sg:classifiers":[
        {
            "category":"Fast Food",
            "type":"Food & Drink"
        }
    ],
    "sg:phone":"+32 81 58 94 71",
    "sg:postcode":"5300",
    "sg:province":"Namur",
    "sg:tags":[
        "fried",
        "stand",
        "potato"
    ],
    "wof:name":"Brumagne (la)",
    "wof:placetype":"venue"
},
  "geometry": {"coordinates":[4.9837799072,50.4705886841],"type":"Point"}
}