{
  "type": "Feature",
  "properties": {
    "iso:country":"BE",
    "sg:address":"Chaussee De Bruxelles 238b28",
    "sg:city":"Waterloo",
    "sg:classifiers":[
        {
            "category":"Organizations",
            "subcategory":"Non-profit Organization",
            "type":"Services"
        }
    ],
    "sg:phone":"+32 2 351 29 00",
    "sg:postcode":"1410",
    "sg:province":"Brabant Wallon",
    "sg:tags":[
        "alarm",
        "system"
    ],
    "wof:name":"Eureca Benelux S.p.r.l.",
    "wof:placetype":"venue"
},
  "geometry": {"coordinates":[4.3982548714,50.7163314819],"type":"Point"}
}