{
  "type": "Feature",
  "properties": {
    "iso:country":"BE",
    "sg:address":"Rue Jean-baptiste Vanp\u00e9 23-25",
    "sg:city":"Bruxelles (forest)",
    "sg:classifiers":[
        {
            "category":"Shopping",
            "subcategory":"Pharmacy",
            "type":"Retail Goods"
        }
    ],
    "sg:phone":"+32 2 376 51 38",
    "sg:postcode":"1190",
    "sg:province":"Bruxelles-Capitale",
    "sg:tags":[
        "store",
        "drug"
    ],
    "wof:name":"Dutrannoit",
    "wof:placetype":"venue"
},
  "geometry": {"coordinates":[4.3183989525,50.8096084595],"type":"Point"}
}