{
  "type": "Feature",
  "properties": {
    "addr:full":"Quai Mativa 43 Li\u00c8ge Li\u00e8ge 4020",
    "addr:housenumber":"43",
    "addr:postcode":"4020",
    "addr:street":"Quai Mativa",
    "iso:country":"BE",
    "sg:address":"Quai Mativa 43",
    "sg:city":"Li\u00c8ge",
    "sg:orig_category":"Artistes ind\u00e9pendants",
    "sg:phone":"+32 4 343 41 51",
    "sg:postcode":"4020",
    "sg:province":"Li\u00e8ge",
    "wof:name":"C. Gilbert",
    "wof:placetype":"venue"
},
  "geometry": {"coordinates":[5.5802369118,50.625],"type":"Point"}
}