{
  "type": "Feature",
  "properties": {
    "iso:country":"BE",
    "sg:address":"Potterierei 46",
    "sg:city":"Brugge",
    "sg:orig_category":"Enseignement secondaire g\u00e9n\u00e9ral",
    "sg:phone":"+32 50 33 33 30",
    "sg:postcode":"8000",
    "sg:province":"West-Vlaanderen",
    "wof:name":"Buso Spermalie-soviag",
    "wof:placetype":"venue"
},
  "geometry": {"coordinates":[3.2289719582,51.2166519165],"type":"Point"}
}