{
  "type": "Feature",
  "properties": {
    "addr:full":"Rue Saint-pierre 91 Dinant Namur 5500",
    "addr:housenumber":"91",
    "addr:postcode":"5500",
    "addr:street":"Rue Saint-Pierre",
    "iso:country":"BE",
    "sg:address":"Rue Saint-pierre 91",
    "sg:city":"Dinant",
    "sg:orig_category":"Boekhouders",
    "sg:phone":"+32 82 22 35 25",
    "sg:postcode":"5500",
    "sg:province":"Namur",
    "wof:name":"Gaston Gilain",
    "wof:placetype":"venue"
},
  "geometry": {"coordinates":[4.9090399742,50.2649040222],"type":"Point"}
}