{
  "type": "Feature",
  "properties": {
    "iso:country":"BE",
    "sg:address":"Markt 8",
    "sg:city":"Tessenderlo",
    "sg:orig_category":"Bagage and lederwaren Schoenen",
    "sg:phone":"+32 13 66 13 17",
    "sg:postcode":"3980",
    "sg:province":"Limburg",
    "wof:name":"Huis Cavinchy",
    "wof:placetype":"venue"
},
  "geometry": {"coordinates":[5.0892529488,51.0672492981],"type":"Point"}
}