{
  "type": "Feature",
  "properties": {
    "iso:country":"BE",
    "sg:address":"Tombroekmolenstraat 6",
    "sg:city":"Kortrijk",
    "sg:classifiers":[
        {
            "category":"Cafe",
            "type":"Food & Drink"
        }
    ],
    "sg:phone":"+32 56 25 54 70",
    "sg:postcode":"8510",
    "sg:province":"West-Vlaanderen",
    "sg:tags":[
        "caf\u00e9s"
    ],
    "wof:name":"Caf\u00c9 St.elooi",
    "wof:placetype":"venue"
},
  "geometry": {"coordinates":[3.2644290924,50.7509307861],"type":"Point"}
}