{
  "type": "Feature",
  "properties": {
    "iso:country":"BE",
    "sg:address":"Rue De La Terre \u00e0 Briques 6",
    "sg:city":"Tournai (blandain - Hertain)",
    "sg:classifiers":[
        {
            "category":"Utilities",
            "subcategory":"Telephone",
            "type":"Services"
        }
    ],
    "sg:phone":"+32 69 89 08 20",
    "sg:postcode":"7522",
    "sg:province":"Hainaut",
    "sg:tags":[
        "-",
        "internet"
    ],
    "wof:name":"Honet Sprl",
    "wof:placetype":"venue"
},
  "geometry": {"coordinates":[3.3341469765,50.6075248718],"type":"Point"}
}