{
  "type": "Feature",
  "properties": {
    "iso:country":"BE",
    "sg:address":"Oude Vaartstraat 50",
    "sg:city":"Turnhout",
    "sg:orig_category":"Avocats and conseillers juridiques",
    "sg:phone":"+32 14 42 82 42",
    "sg:postcode":"2300",
    "sg:province":"Antwerpen",
    "wof:name":"Marc Peeters",
    "wof:placetype":"venue"
},
  "geometry": {"coordinates":[4.9466290474,51.3281173706],"type":"Point"}
}