{
  "type": "Feature",
  "properties": {
    "addr:full":"Heibloemstraat 21 Nijlen Antwerpen 2560",
    "addr:housenumber":"21",
    "addr:postcode":"2560",
    "addr:street":"Heibloemstraat",
    "iso:country":"BE",
    "sg:address":"Heibloemstraat 21",
    "sg:city":"Nijlen",
    "sg:orig_category":"Woningbouw",
    "sg:phone":"+32 3 481 63 08",
    "sg:postcode":"2560",
    "sg:province":"Antwerpen",
    "wof:name":"Vervoort",
    "wof:placetype":"venue"
},
  "geometry": {"coordinates":[4.6609621048,51.1705741882],"type":"Point"}
}