{
  "type": "Feature",
  "properties": {
    "iso:country":"BE",
    "sg:address":"Jozef De Troetselstraat 26",
    "sg:city":"Dendermonde (schoonaarde)",
    "sg:classifiers":[
        {
            "category":"Wholesale",
            "subcategory":"Plants",
            "type":"Manufacturing & Wholesale Goods"
        }
    ],
    "sg:phone":"+32 52 42 35 10",
    "sg:postcode":"9200",
    "sg:province":"Oost-Vlaanderen",
    "sg:tags":[
        "whol",
        "flower",
        "-",
        "grower"
    ],
    "wof:name":"De Clerck P",
    "wof:placetype":"venue"
},
  "geometry": {"coordinates":[4.0152702332,50.998840332],"type":"Point"}
}