{
  "type": "Feature",
  "properties": {
    "addr:full":"Sint-vincentiusstraat 36 Sint-niklaas Oost-Vlaanderen 9100",
    "addr:housenumber":"36",
    "addr:postcode":"9100",
    "addr:street":"Sint-Vincentiusstraat",
    "iso:country":"BE",
    "sg:address":"Sint-vincentiusstraat 36",
    "sg:city":"Sint-niklaas",
    "sg:classifiers":[
        {
            "category":"Farming",
            "subcategory":"Fish & Marine Products",
            "type":"Manufacturing & Wholesale Goods"
        }
    ],
    "sg:phone":"+32 3 766 33 89",
    "sg:postcode":"9100",
    "sg:province":"Oost-Vlaanderen",
    "sg:tags":[
        "retail",
        "-",
        "shellfish"
    ],
    "wof:name":"De Marie-louise",
    "wof:placetype":"venue"
},
  "geometry": {"coordinates":[4.1520190239,51.1637573242],"type":"Point"}
}