{
  "type": "Feature",
  "properties": {
    "addr:full":"Rue Des Dominicains 9 Li\u00e8ge 1 Li\u00e8ge 4000",
    "addr:housenumber":"9;1",
    "addr:postcode":"4000",
    "addr:street":"Rue Des Dominicains",
    "iso:country":"BE",
    "sg:address":"Rue Des Dominicains 9",
    "sg:city":"Li\u00e8ge 1",
    "sg:classifiers":[
        {
            "category":"Shopping",
            "subcategory":"Gifts & Souvenirs",
            "type":"Retail Goods"
        }
    ],
    "sg:phone":"+32 4 237 07 05",
    "sg:postcode":"4000",
    "sg:province":"Li\u00e8ge",
    "sg:tags":[
        "-"
    ],
    "wof:name":"Abstrac",
    "wof:placetype":"venue"
},
  "geometry": {"coordinates":[5.5705809593,50.6426620483],"type":"Point"}
}