{
  "type": "Feature",
  "properties": {
    "addr:full":"Rue De Mont\u00e9n\u00e9gro 19 Bruxelles (saint-gilles) Bruxelles-Capitale 1060",
    "addr:housenumber":"19",
    "addr:postcode":"1060",
    "addr:street":"Rue De Monte\u0301Ne\u0301Gro",
    "iso:country":"BE",
    "sg:address":"Rue De Mont\u00e9n\u00e9gro 19",
    "sg:city":"Bruxelles (saint-gilles)",
    "sg:classifiers":[
        {
            "category":"Health Services",
            "subcategory":"Health Practitioner",
            "type":"Services"
        }
    ],
    "sg:phone":"+32 2 772 94 23",
    "sg:postcode":"1060",
    "sg:province":"Bruxelles-Capitale",
    "sg:tags":[
        "physiotherapist"
    ],
    "wof:name":"Centre De Kin\u00e9sith\u00e9rapie Mont\u00e9n\u00e9gro",
    "wof:placetype":"venue"
},
  "geometry": {"coordinates":[4.3383231163,50.8289031982],"type":"Point"}
}