{
  "type": "Feature",
  "properties": {
    "addr:full":"Zwaluwbeek 3 Melsele Oost-Vlaanderen 9120",
    "addr:housenumber":"3",
    "addr:postcode":"9120",
    "addr:street":"Zwaluwbeek",
    "iso:country":"BE",
    "sg:address":"Zwaluwbeek 3",
    "sg:city":"Melsele",
    "sg:classifiers":[
        {
            "category":"Professional",
            "subcategory":"Advertising",
            "type":"Services"
        }
    ],
    "sg:phone":"+32 3 250 13 20",
    "sg:postcode":"9120",
    "sg:province":"Oost-Vlaanderen",
    "sg:tags":[
        "agency"
    ],
    "wof:name":"De Kie Nv",
    "wof:placetype":"venue"
},
  "geometry": {"coordinates":[4.3181781769,51.1979560852],"type":"Point"}
}