{
  "type": "Feature",
  "properties": {
    "addr:full":"De Breyne Peelaertstraat 25 Diksmuide West-Vlaanderen 8600",
    "addr:housenumber":"25",
    "addr:postcode":"8600",
    "addr:street":"Peelaertstraat",
    "iso:country":"BE",
    "sg:address":"De Breyne Peelaertstraat 25",
    "sg:city":"Diksmuide",
    "sg:classifiers":[
        {
            "category":"Shopping",
            "subcategory":"Pets & Pet Supplies",
            "type":"Retail Goods"
        }
    ],
    "sg:phone":"+32 51 50 42 37",
    "sg:postcode":"8600",
    "sg:province":"West-Vlaanderen",
    "sg:tags":[
        "aquarium",
        "accessory"
    ],
    "wof:name":"Aquaria 't Viske",
    "wof:placetype":"venue"
},
  "geometry": {"coordinates":[2.8655209541,51.0351219177],"type":"Point"}
}