{
  "type": "Feature",
  "properties": {
    "iso:country":"BE",
    "sg:address":"Chemin De Soignies14",
    "sg:city":"Silly",
    "sg:orig_category":"R\u00e9alisation de programmes and logiciels. Formation and enseignement",
    "sg:phone":"+32 2 395 71 46",
    "sg:postcode":"7830",
    "sg:province":"Hainaut",
    "wof:name":"Redwood Sl",
    "wof:placetype":"venue"
},
  "geometry": {"coordinates":[3.9236450195,50.648273468],"type":"Point"}
}