{
  "type": "Feature",
  "properties": {
    "iso:country":"BE",
    "sg:address":"Chauss\u00c9e De Charleroi 229",
    "sg:city":"Gembloux",
    "sg:orig_category":"Herstellingen and onderhoud van auto's",
    "sg:phone":"+32 81 61 22 87",
    "sg:postcode":"5030",
    "sg:province":"Namur",
    "wof:name":"Garage Du Bus De Warnaffe",
    "wof:placetype":"venue"
},
  "geometry": {"coordinates":[4.6829199791,50.5614318848],"type":"Point"}
}