{
  "type": "Feature",
  "properties": {
    "addr:full":"Geraardsbergsestraat 128 Dilbeek Vlaams-Brabant 1703",
    "addr:housenumber":"128",
    "addr:postcode":"1703",
    "addr:street":"Geraardsbergsestraat",
    "iso:country":"BE",
    "sg:address":"Geraardsbergsestraat 128",
    "sg:city":"Dilbeek",
    "sg:orig_category":"Imprimeries and copyshops",
    "sg:phone":"+32 2 569 42 72",
    "sg:postcode":"1703",
    "sg:province":"Vlaams-Brabant",
    "wof:name":"Jan Taelemans",
    "wof:placetype":"venue"
},
  "geometry": {"coordinates":[4.1908578873,50.8331642151],"type":"Point"}
}