{
  "type": "Feature",
  "properties": {
    "iso:country":"BE",
    "sg:address":"Molenstraat 40",
    "sg:city":"Turnhout",
    "sg:orig_category":"Artsen and specialisten",
    "sg:phone":"+32 14 42 16 34",
    "sg:postcode":"2300",
    "sg:province":"Antwerpen",
    "wof:name":"M. Gillis",
    "wof:placetype":"venue"
},
  "geometry": {"coordinates":[4.9404587746,51.3216438293],"type":"Point"}
}