{
  "type": "Feature",
  "properties": {
    "iso:country":"BE",
    "sg:address":"Avenue Des Franciscains 98a",
    "sg:city":"Bruxelles (woluwe-saint-pierre)",
    "sg:classifiers":[
        {
            "category":"Health Services",
            "subcategory":"Doctor",
            "type":"Services"
        }
    ],
    "sg:phone":"+32 2 770 77 56",
    "sg:postcode":"1150",
    "sg:province":"Bruxelles-Capitale",
    "sg:tags":[
        "medicinephysicians",
        "surgeon"
    ],
    "wof:name":"Halama A-r",
    "wof:placetype":"venue"
},
  "geometry": {"coordinates":[4.4229807854,50.8270530701],"type":"Point"}
}