{
  "type": "Feature",
  "properties": {
    "addr:full":"Wijteveldstraat 1b Herzele (borsbeke) Oost-Vlaanderen 9552",
    "addr:housenumber":"1b",
    "addr:postcode":"9552",
    "addr:street":"Wijteveldstraat;Borsbeke Oost-Vlaanderen",
    "iso:country":"BE",
    "sg:address":"Wijteveldstraat 1b",
    "sg:city":"Herzele (borsbeke)",
    "sg:classifiers":[
        {
            "category":"Professional",
            "subcategory":"Computer Services",
            "type":"Services"
        }
    ],
    "sg:phone":"+32 477 53 37 89",
    "sg:postcode":"9552",
    "sg:province":"Oost-Vlaanderen",
    "sg:tags":[
        "webdesign",
        "-",
        "internet"
    ],
    "wof:name":"Phase 2 Phase",
    "wof:placetype":"venue"
},
  "geometry": {"coordinates":[3.8871600628,50.9038009644],"type":"Point"}
}