{
  "type": "Feature",
  "properties": {
    "addr:full":"Maria Teresiastr 11 Brussel Bruxelles-Capitale 1000",
    "addr:housenumber":"11",
    "addr:postcode":"1000",
    "addr:street":"Brussel",
    "iso:country":"BE",
    "sg:address":"Maria Teresiastr 11",
    "sg:city":"Brussel",
    "sg:classifiers":[
        {
            "category":"Banks & Credit Unions",
            "subcategory":"Financial Services",
            "type":"Services"
        }
    ],
    "sg:phone":"+32 2 211 11 11",
    "sg:postcode":"1000",
    "sg:province":"Bruxelles-Capitale",
    "sg:tags":[
        "banking",
        "insurance",
        "institution",
        "finance"
    ],
    "wof:name":"Groupement Europeen Des Caisses Depargne",
    "wof:placetype":"venue"
},
  "geometry": {"coordinates":[4.371942997,50.8463478088],"type":"Point"}
}