{
  "type": "Feature",
  "properties": {
    "iso:country":"BE",
    "sg:address":"Liersebaan 122ba",
    "sg:city":"Zandhoven",
    "sg:orig_category":"V\u00e9hicules automobiles",
    "sg:phone":"+32 3 464 07 83",
    "sg:postcode":"2240",
    "sg:province":"Antwerpen",
    "wof:name":"Devroece Car Business",
    "wof:placetype":"venue"
},
  "geometry": {"coordinates":[4.6523938179,51.2069320679],"type":"Point"}
}