{
  "type": "Feature",
  "properties": {
    "addr:full":"Mont-saint-martin 62b-2 Li\u00e8ge 1 Li\u00e8ge 4000",
    "addr:postcode":"4000",
    "iso:country":"BE",
    "sg:address":"Mont-saint-martin 62b-2",
    "sg:city":"Li\u00e8ge 1",
    "sg:classifiers":[
        {
            "category":"Insurance",
            "subcategory":"Insurance Agent",
            "type":"Services"
        }
    ],
    "sg:phone":"+32 4 223 41 00",
    "sg:postcode":"4000",
    "sg:province":"Li\u00e8ge",
    "sg:tags":[
        "-",
        "representative"
    ],
    "wof:name":"Sirius International Insurance Corporation Belgian Branch",
    "wof:placetype":"venue"
},
  "geometry": {"coordinates":[5.5675158501,50.6449241638],"type":"Point"}
}