{
  "type": "Feature",
  "properties": {
    "addr:full":"Brialmontlei 24 Antwerpen Antwerpen 2018",
    "addr:housenumber":"24",
    "addr:postcode":"2018",
    "addr:street":"Brialmontlei",
    "iso:country":"BE",
    "sg:address":"Brialmontlei 24",
    "sg:city":"Antwerpen",
    "sg:classifiers":[
        {
            "category":"Shopping",
            "subcategory":"Jewelry",
            "type":"Retail Goods"
        }
    ],
    "sg:phone":"+32 3 239 57 84",
    "sg:postcode":"2018",
    "sg:province":"Antwerpen",
    "sg:tags":[
        "fab",
        "bijou"
    ],
    "wof:name":"Judas Wochenmarkt",
    "wof:placetype":"venue"
},
  "geometry": {"coordinates":[4.4200501442,51.2095603943],"type":"Point"}
}