{
  "type": "Feature",
  "properties": {
    "iso:country":"BE",
    "sg:address":"Rechtestraat 64",
    "sg:city":"Beringen (koersel)",
    "sg:classifiers":[
        {
            "category":"Building & Trades",
            "subcategory":"Pest Control",
            "type":"Services"
        }
    ],
    "sg:phone":"+32 11 43 68 46",
    "sg:postcode":"3582",
    "sg:province":"Limburg",
    "sg:tags":[
        "painting",
        "contractor"
    ],
    "wof:name":"Kewa",
    "wof:placetype":"venue"
},
  "geometry": {"coordinates":[5.2708749771,51.0595359802],"type":"Point"}
}