{
  "type": "Feature",
  "properties": {
    "addr:full":"Gentsestraat 152 Erpe-mere (burst) Oost-Vlaanderen 9420",
    "addr:housenumber":"152",
    "addr:postcode":"9420",
    "addr:street":"Gentsestraat",
    "iso:country":"BE",
    "sg:address":"Gentsestraat 152",
    "sg:city":"Erpe-mere (burst)",
    "sg:classifiers":[
        {
            "category":"Professional",
            "subcategory":"Engineering",
            "type":"Services"
        }
    ],
    "sg:phone":"+32 53 62 40 87",
    "sg:postcode":"9420",
    "sg:province":"Oost-Vlaanderen",
    "sg:tags":[
        "technical",
        "industrial",
        "-",
        "subcontracting"
    ],
    "wof:name":"Vatis",
    "wof:placetype":"venue"
},
  "geometry": {"coordinates":[3.90969491,50.9204330444],"type":"Point"}
}