{
  "type": "Feature",
  "properties": {
    "iso:country":"BE",
    "sg:address":"Arendsstraat 163",
    "sg:city":"Harelbeke",
    "sg:classifiers":[
        {
            "category":"Wholesale",
            "subcategory":"Meat",
            "type":"Manufacturing & Wholesale Goods"
        }
    ],
    "sg:phone":"+32 56 71 51 95",
    "sg:postcode":"8530",
    "sg:province":"West-Vlaanderen",
    "sg:tags":[
        "whol",
        "-"
    ],
    "wof:name":"Dezutter G",
    "wof:placetype":"venue"
},
  "geometry": {"coordinates":[3.3253500462,50.8509788513],"type":"Point"}
}