{
  "type": "Feature",
  "properties": {
    "addr:full":"Rue Jules Mononk 50 Thimister-clermont Li\u00e8ge 4890",
    "addr:housenumber":"50",
    "addr:postcode":"4890",
    "addr:street":"Rue Jules Mononk",
    "iso:country":"BE",
    "sg:address":"Rue Jules Mononk 50",
    "sg:city":"Thimister-clermont",
    "sg:classifiers":[
        {
            "category":"Arena",
            "subcategory":"Sports Club",
            "type":"Entertainment"
        }
    ],
    "sg:phone":"+32 87 44 61 79",
    "sg:postcode":"4890",
    "sg:province":"Li\u00e8ge",
    "sg:tags":[
        "terrain",
        "hors",
        "de",
        "installation",
        "sportifs"
    ],
    "wof:name":"Espoir Minerois",
    "wof:placetype":"venue"
},
  "geometry": {"coordinates":[5.8840408325,50.6593093872],"type":"Point"}
}