{
  "type": "Feature",
  "properties": {
    "iso:country":"BE",
    "sg:address":"Dendermondestraat 51",
    "sg:city":"Schelle",
    "sg:classifiers":[
        {
            "category":"Food & Beverages",
            "subcategory":"Groceries & Convenience Stores",
            "type":"Retail Goods"
        }
    ],
    "sg:phone":"+32 3 877 36 12",
    "sg:postcode":"2627",
    "sg:province":"Antwerpen",
    "sg:tags":[
        "grocer"
    ],
    "wof:name":"Salamike ('t)",
    "wof:placetype":"venue"
},
  "geometry": {"coordinates":[4.332649231,51.1276168823],"type":"Point"}
}