{
  "type": "Feature",
  "properties": {
    "addr:full":"Boulevard Industriel 16 Anderlecht Bruxelles-Capitale 1070",
    "addr:housenumber":"16",
    "addr:postcode":"1070",
    "addr:street":"Boulevard Industriel",
    "iso:country":"BE",
    "sg:address":"Boulevard Industriel 16",
    "sg:city":"Anderlecht",
    "sg:orig_category":"Assurances. Bureaux de poste",
    "sg:phone":"+32 2 526 04 19",
    "sg:postcode":"1070",
    "sg:province":"Bruxelles-Capitale",
    "wof:name":"La Poste",
    "wof:placetype":"venue"
},
  "geometry": {"coordinates":[4.3150200844,50.827709198],"type":"Point"}
}