{
  "type": "Feature",
  "properties": {
    "iso:country":"BE",
    "sg:address":"Leuvensesteenweg 125",
    "sg:city":"Kampenhout",
    "sg:classifiers":[
        {
            "category":"Shopping",
            "subcategory":"Clothing, Apparel, & Fashions",
            "type":"Retail Goods"
        }
    ],
    "sg:phone":"+32 16 65 75 02",
    "sg:postcode":"1910",
    "sg:province":"Vlaams-Brabant",
    "sg:tags":[
        "-",
        "clothing",
        "child"
    ],
    "wof:name":"Koko-sinel",
    "wof:placetype":"venue"
},
  "geometry": {"coordinates":[4.6032691002,50.9492759705],"type":"Point"}
}