{
  "type": "Feature",
  "properties": {
    "iso:country":"BE",
    "sg:address":"Rue Francisco Ferrer 15",
    "sg:city":"Farciennes",
    "sg:orig_category":"M\u00e9decines alternatives",
    "sg:phone":"+32 71 38 21 11",
    "sg:postcode":"6240",
    "sg:province":"Hainaut",
    "wof:name":"D. Himmer",
    "wof:placetype":"venue"
},
  "geometry": {"coordinates":[4.5539779663,50.4252319336],"type":"Point"}
}