{
  "type": "Feature",
  "properties": {
    "addr:full":"Chauss\u00c9e De Waterloo 276 Sint-gillis/saint-gilles Bruxelles-Capitale 1060",
    "addr:housenumber":"276",
    "addr:postcode":"1060",
    "addr:street":"Chausse\u0301E De Waterloo",
    "iso:country":"BE",
    "sg:address":"Chauss\u00c9e De Waterloo 276",
    "sg:city":"Sint-gillis/saint-gilles",
    "sg:orig_category":"Boucheries",
    "sg:phone":"+32 2 534 35 06",
    "sg:postcode":"1060",
    "sg:province":"Bruxelles-Capitale",
    "wof:name":"Jean-claude Van Trimpont/jean Van Trimpont",
    "wof:placetype":"venue"
},
  "geometry": {"coordinates":[4.3479561806,50.8255805969],"type":"Point"}
}