{
  "type": "Feature",
  "properties": {
    "iso:country":"BE",
    "sg:address":"Carri\u00c8re Du Mar\u00c9chal 342",
    "sg:city":"Pecq",
    "sg:orig_category":"Herstellingen and onderhoud van auto's",
    "sg:phone":"+32 69 55 66 41",
    "sg:postcode":"7742",
    "sg:province":"Hainaut",
    "wof:name":"Edouard Busschaert",
    "wof:placetype":"venue"
},
  "geometry": {"coordinates":[3.3629090786,50.7024917603],"type":"Point"}
}