{
  "type": "Feature",
  "properties": {
    "iso:country":"BE",
    "sg:address":"Rue Du Perron 30",
    "sg:city":"Oupeye",
    "sg:orig_category":"Journaux. Tabac",
    "sg:phone":"+32 4 379 18 24",
    "sg:postcode":"4681",
    "sg:province":"Li\u00e8ge",
    "wof:name":"Le Par Chemin",
    "wof:placetype":"venue"
},
  "geometry": {"coordinates":[5.6808180809,50.7120170593],"type":"Point"}
}