{
  "type": "Feature",
  "properties": {
    "addr:full":"Deinzestraat 50 Wortegem-petergem Oost-Vlaanderen 9790",
    "addr:housenumber":"50",
    "addr:postcode":"9790",
    "addr:street":"Deinzestraat;Oost-Vlaanderen",
    "iso:country":"BE",
    "sg:address":"Deinzestraat 50",
    "sg:city":"Wortegem-petergem",
    "sg:classifiers":[
        {
            "category":"Manufacturing",
            "subcategory":"Metals",
            "type":"Manufacturing & Wholesale Goods"
        }
    ],
    "sg:phone":"+32 9 383 58 03",
    "sg:postcode":"9790",
    "sg:province":"Oost-Vlaanderen",
    "sg:tags":[
        "metallurgy",
        "steel",
        "metalworking"
    ],
    "wof:name":"Dhr Andr\u00c9 Vindevogel",
    "wof:placetype":"venue"
},
  "geometry": {"coordinates":[3.5603640079,50.8712043762],"type":"Point"}
}