{
  "type": "Feature",
  "properties": {
    "addr:full":"Rue Du Village 21 Seneffe (petit-roeulx-lez-nivelles) Hainaut 7181",
    "addr:housenumber":"21",
    "addr:postcode":"7181",
    "addr:street":"Rue Du Village",
    "iso:country":"BE",
    "sg:address":"Rue Du Village 21",
    "sg:city":"Seneffe (petit-roeulx-lez-nivelles)",
    "sg:classifiers":[
        {
            "category":"Professional",
            "subcategory":"Management & Consulting",
            "type":"Services"
        }
    ],
    "sg:phone":"+32 67 87 87 31",
    "sg:postcode":"7181",
    "sg:province":"Hainaut",
    "sg:tags":[
        "consultant"
    ],
    "wof:name":"Mardin Sprl",
    "wof:placetype":"venue"
},
  "geometry": {"coordinates":[4.2589969635,50.5626296997],"type":"Point"}
}