{
  "type": "Feature",
  "properties": {
    "addr:full":"Sint-truidersteenweg 110 Borgloon Limburg 3840",
    "addr:housenumber":"110",
    "addr:postcode":"3840",
    "addr:street":"Sint-Truidersteenweg",
    "iso:country":"BE",
    "sg:address":"Sint-truidersteenweg 110",
    "sg:city":"Borgloon",
    "sg:orig_category":"Producteurs de fruits",
    "sg:phone":"+32 12 74 17 66",
    "sg:postcode":"3840",
    "sg:province":"Limburg",
    "wof:name":"Derwael Fruitbedrijf",
    "wof:placetype":"venue"
},
  "geometry": {"coordinates":[5.3298039436,50.8044052124],"type":"Point"}
}