{
  "type": "Feature",
  "properties": {
    "addr:full":"Brugstraat 31 Beveren (vrasene) Oost-Vlaanderen 9120",
    "addr:housenumber":"31",
    "addr:postcode":"9120",
    "addr:street":"Brugstraat",
    "iso:country":"BE",
    "sg:address":"Brugstraat 31",
    "sg:city":"Beveren (vrasene)",
    "sg:classifiers":[
        {
            "category":"Shopping",
            "subcategory":"Clothing, Apparel, & Fashions",
            "type":"Retail Goods"
        }
    ],
    "sg:phone":"+32 3 755 25 53",
    "sg:postcode":"9120",
    "sg:province":"Oost-Vlaanderen",
    "sg:tags":[
        "lady",
        "clothing",
        "-"
    ],
    "wof:name":"Grossi Mode",
    "wof:placetype":"venue"
},
  "geometry": {"coordinates":[4.1960988045,51.2197532654],"type":"Point"}
}