{
  "type": "Feature",
  "properties": {
    "iso:country":"BE",
    "sg:address":"Van Breestraat 17",
    "sg:city":"Antwerpen",
    "sg:orig_category":"Rusthuizen and serviceflats",
    "sg:phone":"+32 3 233 03 43",
    "sg:postcode":"2018",
    "sg:province":"Antwerpen",
    "wof:name":"Pension Luyckx",
    "wof:placetype":"venue"
},
  "geometry": {"coordinates":[4.4094848633,51.2102546692],"type":"Point"}
}