{
  "type": "Feature",
  "properties": {
    "addr:full":"Rue Du Comte 33 Mons (nouvelles) Hainaut 7022",
    "addr:housenumber":"33",
    "addr:postcode":"7022",
    "addr:street":"Rue Du Comte",
    "iso:country":"BE",
    "sg:address":"Rue Du Comte 33",
    "sg:city":"Mons (nouvelles)",
    "sg:classifiers":[
        {
            "category":"Arts & Performance",
            "subcategory":"Theater",
            "type":"Entertainment"
        }
    ],
    "sg:phone":"+32 65 33 99 63",
    "sg:postcode":"7022",
    "sg:province":"Hainaut",
    "sg:tags":[
        "group",
        "theatre"
    ],
    "wof:name":"Compagnie Barbiana",
    "wof:placetype":"venue"
},
  "geometry": {"coordinates":[4.0181078911,50.4045410156],"type":"Point"}
}