{
  "type": "Feature",
  "properties": {
    "iso:country":"BE",
    "sg:address":"Rue De Frameries 21bb",
    "sg:city":"Qu\u00c9vy",
    "sg:orig_category":"M\u00e9decins and sp\u00e9cialistes",
    "sg:phone":"+32 65 56 84 40",
    "sg:postcode":"7040",
    "sg:province":"Hainaut",
    "wof:name":"Zohra Nezar",
    "wof:placetype":"venue"
},
  "geometry": {"coordinates":[3.936175108,50.3675727844],"type":"Point"}
}