{
  "type": "Feature",
  "properties": {
    "addr:full":"Rue Du Canal 57 Bruxelles Bruxelles-Capitale 1000",
    "addr:housenumber":"57",
    "addr:postcode":"1000",
    "addr:street":"Rue Du Canal",
    "iso:country":"BE",
    "sg:address":"Rue Du Canal 57",
    "sg:city":"Bruxelles",
    "sg:classifiers":[
        {
            "category":"Education",
            "subcategory":"School",
            "type":"Public Place"
        }
    ],
    "sg:phone":"+32 2 218 01 98",
    "sg:postcode":"1000",
    "sg:province":"Bruxelles-Capitale",
    "sg:tags":[
        "primary"
    ],
    "wof:name":"Ecole Du Canal",
    "wof:placetype":"venue"
},
  "geometry": {"coordinates":[4.3490190506,50.8549156189],"type":"Point"}
}