{
  "type": "Feature",
  "properties": {
    "addr:full":"Vlamingstraat 33 Wevelgem West-Vlaanderen 8560",
    "addr:housenumber":"33",
    "addr:postcode":"8560",
    "addr:street":"Vlamingstraat",
    "iso:country":"BE",
    "sg:address":"Vlamingstraat 33",
    "sg:city":"Wevelgem",
    "sg:orig_category":"Benzinestations and brandstoffen",
    "sg:phone":"+32 56 41 69 11",
    "sg:postcode":"8560",
    "sg:province":"West-Vlaanderen",
    "wof:name":"Dewulf Daniel",
    "wof:placetype":"venue"
},
  "geometry": {"coordinates":[3.2146549225,50.8089332581],"type":"Point"}
}