{
  "type": "Feature",
  "properties": {
    "addr:full":"Rue Du Pont 20 Mons Hainaut 7011",
    "addr:housenumber":"20",
    "addr:postcode":"7011",
    "addr:street":"Rue Du Pont;Hainaut",
    "iso:country":"BE",
    "sg:address":"Rue Du Pont 20",
    "sg:city":"Mons",
    "sg:orig_category":"Woningbouw",
    "sg:phone":"+32 65 35 13 62",
    "sg:postcode":"7011",
    "sg:province":"Hainaut",
    "wof:name":"Ponchant",
    "wof:placetype":"venue"
},
  "geometry": {"coordinates":[3.912539959,50.4712982178],"type":"Point"}
}