{
  "type": "Feature",
  "properties": {
    "iso:country":"BE",
    "sg:address":"Morellestraat 4",
    "sg:city":"Wingene",
    "sg:orig_category":"Entretien and r\u00e9parations de voitures",
    "sg:phone":"+32 51 65 57 60",
    "sg:postcode":"8750",
    "sg:province":"West-Vlaanderen",
    "wof:name":"Willy Van Colen",
    "wof:placetype":"venue"
},
  "geometry": {"coordinates":[3.2907369137,51.069065094],"type":"Point"}
}