{
  "type": "Feature",
  "properties": {
    "addr:full":"Groenstraat 39a Hoeselt Limburg 3730",
    "addr:housenumber":"39a",
    "addr:postcode":"3730",
    "addr:street":"Groenstraat",
    "iso:country":"BE",
    "sg:address":"Groenstraat 39a",
    "sg:city":"Hoeselt",
    "sg:orig_category":"Kapsalons",
    "sg:phone":"+32 89 41 63 70",
    "sg:postcode":"3730",
    "sg:province":"Limburg",
    "wof:name":"Hairstudio Anita",
    "wof:placetype":"venue"
},
  "geometry": {"coordinates":[5.4794359207,50.8624763489],"type":"Point"}
}