{
  "type": "Feature",
  "properties": {
    "addr:full":"Rue De La-roche 6 Rendeux Luxembourg 6987",
    "addr:housenumber":"6",
    "addr:postcode":"6987",
    "addr:street":"Rue De La-Roche",
    "iso:country":"BE",
    "sg:address":"Rue De La-roche 6",
    "sg:city":"Rendeux",
    "sg:classifiers":[
        {
            "category":"Shopping",
            "subcategory":"Clothing, Apparel, & Fashions",
            "type":"Retail Goods"
        }
    ],
    "sg:phone":"+32 84 47 74 20",
    "sg:postcode":"6987",
    "sg:province":"Luxembourg",
    "sg:tags":[
        "ondergoed",
        "lingerie"
    ],
    "wof:name":"Marie-line Poirrier",
    "wof:placetype":"venue"
},
  "geometry": {"coordinates":[5.5101900101,50.2343101501],"type":"Point"}
}