{
  "type": "Feature",
  "properties": {
    "iso:country":"BE",
    "sg:address":"G Gezellestraat 12",
    "sg:city":"Boom",
    "sg:orig_category":"Secr\u00e9tariats",
    "sg:phone":"+32 3 844 19 63",
    "sg:postcode":"2850",
    "sg:province":"Antwerpen",
    "wof:name":"Van De Velde",
    "wof:placetype":"venue"
},
  "geometry": {"coordinates":[4.3729162216,51.0950813293],"type":"Point"}
}