{
  "type": "Feature",
  "properties": {
    "addr:full":"Koning Albertlaan 73 Lanaken Limburg 3620",
    "addr:housenumber":"73",
    "addr:postcode":"3620",
    "addr:street":"Koning Albertlaan",
    "iso:country":"BE",
    "sg:address":"Koning Albertlaan 73",
    "sg:city":"Lanaken",
    "sg:orig_category":"Avocats and conseillers juridiques",
    "sg:phone":"+32 89 71 51 65",
    "sg:postcode":"3620",
    "sg:province":"Limburg",
    "wof:name":"Marc Fraussen",
    "wof:placetype":"venue"
},
  "geometry": {"coordinates":[5.6547532082,50.8912315369],"type":"Point"}
}