{
  "type": "Feature",
  "properties": {
    "iso:country":"BE",
    "sg:address":"Rietorchisstraat 10",
    "sg:city":"Gent (oostakker)",
    "sg:classifiers":[
        {
            "category":"Arts & Performance",
            "subcategory":"Music",
            "type":"Entertainment"
        }
    ],
    "sg:phone":"+32 9 355 99 31",
    "sg:postcode":"9041",
    "sg:province":"Oost-Vlaanderen",
    "sg:tags":[
        "disc-jockeys"
    ],
    "wof:name":"Drill-box Dj Jos Van Limburg",
    "wof:placetype":"venue"
},
  "geometry": {"coordinates":[3.7947609425,51.0759887695],"type":"Point"}
}