{
  "type": "Feature",
  "properties": {
    "addr:full":"Maastrichtersteenweg 88b10 Riemst Limburg 3770",
    "addr:housenumber":"88b10",
    "addr:postcode":"3770",
    "addr:street":"Maastrichtersteenweg",
    "iso:country":"BE",
    "sg:address":"Maastrichtersteenweg 88b10",
    "sg:city":"Riemst",
    "sg:orig_category":"Pleisterwerk",
    "sg:phone":"+32 12 45 14 20",
    "sg:postcode":"3770",
    "sg:province":"Limburg",
    "wof:name":"Lambertus Kerkhofs",
    "wof:placetype":"venue"
},
  "geometry": {"coordinates":[5.612569809,50.8188209534],"type":"Point"}
}