{
  "type": "Feature",
  "properties": {
    "iso:country":"BE",
    "sg:address":"Rue Du Bois De Linthout 42-44",
    "sg:city":"Bruxelles (woluwe-saint-lambert)",
    "sg:classifiers":[
        {
            "category":"Professional",
            "subcategory":"Advertising",
            "type":"Services"
        }
    ],
    "sg:phone":"+32 2 736 17 62",
    "sg:postcode":"1200",
    "sg:province":"Bruxelles-Capitale",
    "sg:tags":[
        "photography"
    ],
    "wof:name":"M\u00e9dia Photography",
    "wof:placetype":"venue"
},
  "geometry": {"coordinates":[4.4124121666,50.8452301025],"type":"Point"}
}