{
  "type": "Feature",
  "properties": {
    "iso:country":"BE",
    "sg:address":"Route De Florennes 95",
    "sg:city":"Gerpinnes",
    "sg:classifiers":[
        {
            "category":"Autos & Motor Vehicles",
            "subcategory":"Automobile Sales",
            "type":"Retail Goods"
        }
    ],
    "sg:phone":"+32 71 50 42 21",
    "sg:postcode":"6280",
    "sg:province":"Hainaut",
    "sg:tags":[
        "-",
        "truck"
    ],
    "wof:name":"Daf-piraux & Fils",
    "wof:placetype":"venue"
},
  "geometry": {"coordinates":[4.5363798141,50.3169212341],"type":"Point"}
}