{
  "type": "Feature",
  "properties": {
    "addr:full":"Francisco Ferrerlaan 445 Gent Oost-Vlaanderen 9000",
    "addr:housenumber":"445",
    "addr:postcode":"9000",
    "addr:street":"Francisco Ferrerlaan;Oost-Vlaanderen",
    "iso:country":"BE",
    "sg:address":"Francisco Ferrerlaan 445",
    "sg:city":"Gent",
    "sg:orig_category":"Cr\u00e9dits divers",
    "sg:postcode":"9000",
    "sg:province":"Oost-Vlaanderen",
    "wof:name":"Bancontact-mister Cash",
    "wof:placetype":"venue"
},
  "geometry": {"coordinates":[3.7044270039,51.0707206726],"type":"Point"}
}