{
  "type": "Feature",
  "properties": {
    "iso:country":"BE",
    "sg:address":"Riddersstraat 175",
    "sg:city":"Leuven",
    "sg:orig_category":"Artistes ind\u00e9pendants",
    "sg:phone":"+32 16 23 15 95",
    "sg:postcode":"3000",
    "sg:province":"Vlaams-Brabant",
    "wof:name":"Alfred Bellefroid",
    "wof:placetype":"venue"
},
  "geometry": {"coordinates":[4.695089817,50.8869934082],"type":"Point"}
}