{
  "type": "Feature",
  "properties": {
    "addr:full":"Kerkstraat 43-45 Blankenberge West-Vlaanderen 8370",
    "addr:housenumber":"43-45",
    "addr:postcode":"8370",
    "addr:street":"Kerkstraat",
    "iso:country":"BE",
    "sg:address":"Kerkstraat 43-45",
    "sg:city":"Blankenberge",
    "sg:orig_category":"Banques and organismes de cr\u00e9dit",
    "sg:phone":"+32 50 41 10 79",
    "sg:postcode":"8370",
    "sg:province":"West-Vlaanderen",
    "wof:name":"Fortis",
    "wof:placetype":"venue"
},
  "geometry": {"coordinates":[3.1291639805,51.3150978088],"type":"Point"}
}