{
  "type": "Feature",
  "properties": {
    "addr:full":"Avenue Marcel Thiry 208 Brussels Bruxelles-Capitale 1200",
    "addr:housenumber":"208",
    "addr:postcode":"1200",
    "addr:street":"Avenue Marcel Thiry",
    "iso:country":"BE",
    "sg:address":"Avenue Marcel Thiry 208",
    "sg:city":"Brussels",
    "sg:classifiers":[
        {
            "category":"Banks & Credit Unions",
            "subcategory":"Bank",
            "type":"Services"
        }
    ],
    "sg:postcode":"1200",
    "sg:province":"Bruxelles-Capitale",
    "wof:name":"Vande Maele & Co Nv",
    "wof:placetype":"venue"
},
  "geometry": {"coordinates":[4.0232000351,50.8349113464],"type":"Point"}
}