{
  "type": "Feature",
  "properties": {
    "iso:country":"BE",
    "sg:address":"Weg Naar Bree 23",
    "sg:city":"Opglabbeek",
    "sg:orig_category":"Fietsen Motorfietsen Watersport-, Sport- and Kampeerbenodigdheden Verhuur",
    "sg:phone":"+32 89 85 43 42",
    "sg:postcode":"3660",
    "sg:province":"Limburg",
    "wof:name":"Fietshandel Stals",
    "wof:placetype":"venue"
},
  "geometry": {"coordinates":[5.5854420662,51.0479888916],"type":"Point"}
}