{
  "type": "Feature",
  "properties": {
    "iso:country":"BE",
    "sg:address":"Schootsheidestraat 1",
    "sg:city":"Maaseik",
    "sg:classifiers":[
        {
            "category":"Personal",
            "subcategory":"Beauty Salon",
            "type":"Services"
        }
    ],
    "sg:phone":"+32 89 86 71 52",
    "sg:postcode":"3680",
    "sg:province":"Limburg",
    "sg:tags":[
        "de",
        "coiffure"
    ],
    "wof:name":"Coiffure Irene",
    "wof:placetype":"venue"
},
  "geometry": {"coordinates":[5.791285038,51.0954208374],"type":"Point"}
}