{
  "type": "Feature",
  "properties": {
    "addr:full":"Rue De L'abreuvoir 1 Grez-doiceau Brabant Wallon 1390",
    "addr:housenumber":"1",
    "addr:postcode":"1390",
    "addr:street":"Rue De L'Abreuvoir",
    "iso:country":"BE",
    "sg:address":"Rue De L'abreuvoir 1",
    "sg:city":"Grez-doiceau",
    "sg:orig_category":"Eleveurs de bovins",
    "sg:phone":"+32 10 84 46 24",
    "sg:postcode":"1390",
    "sg:province":"Brabant Wallon",
    "wof:name":"Marcel Godefroid",
    "wof:placetype":"venue"
},
  "geometry": {"coordinates":[4.7167949677,50.734539032],"type":"Point"}
}