{
  "type": "Feature",
  "properties": {
    "addr:full":"It De Blauwe Toren Monnikenwerve 4 Brugge West-Vlaanderen 8000",
    "addr:housenumber":"4",
    "addr:postcode":"8000",
    "addr:street":"It De Blauwe Toren Monnikenwerve",
    "iso:country":"BE",
    "sg:address":"It De Blauwe Toren Monnikenwerve 4",
    "sg:city":"Brugge",
    "sg:orig_category":"Blast Hole Drilling Machines And Equipment",
    "sg:phone":"+32 50 45 01 70",
    "sg:postcode":"8000",
    "sg:province":"West-Vlaanderen",
    "wof:name":"Fabory Centre Brugge Nv",
    "wof:placetype":"venue"
},
  "geometry": {"coordinates":[3.2019898891,51.2452392578],"type":"Point"}
}