{
  "type": "Feature",
  "properties": {
    "iso:country":"BE",
    "sg:address":"Belgi\u00cblei 14",
    "sg:city":"Antwerpen",
    "sg:orig_category":"Juwelen and edelstenen Fab",
    "sg:phone":"+32 3 230 13 04",
    "sg:postcode":"2018",
    "sg:province":"Antwerpen",
    "wof:name":"Tomas Kikin",
    "wof:placetype":"venue"
},
  "geometry": {"coordinates":[4.4218978882,51.20885849],"type":"Point"}
}