{
  "type": "Feature",
  "properties": {
    "addr:full":"Wespelaarsebaan 15 Boortmeerbeek Vlaams-Brabant 3190",
    "addr:housenumber":"15",
    "addr:postcode":"3190",
    "addr:street":"Wespelaarsebaan",
    "iso:country":"BE",
    "sg:address":"Wespelaarsebaan 15",
    "sg:city":"Boortmeerbeek",
    "sg:classifiers":[
        {
            "category":"Cafe",
            "type":"Food & Drink"
        }
    ],
    "sg:phone":"+32 15 52 90 57",
    "sg:postcode":"3190",
    "sg:province":"Vlaams-Brabant",
    "sg:tags":[
        "caf\u00e9s"
    ],
    "wof:name":"Caf\u00c9 De Donkere Wolk",
    "wof:placetype":"venue"
},
  "geometry": {"coordinates":[4.5762610435,50.9793586731],"type":"Point"}
}