{
  "type": "Feature",
  "properties": {
    "addr:full":"Chauss\u00c9e D'ixelles 297 Elsene/ixelles Bruxelles-Capitale 1050",
    "addr:housenumber":"297",
    "addr:postcode":"1050",
    "addr:street":"Chausse\u0301E D'Ixelles",
    "iso:country":"BE",
    "sg:address":"Chauss\u00c9e D'ixelles 297",
    "sg:city":"Elsene/ixelles",
    "sg:orig_category":"Epiceries",
    "sg:phone":"+32 2 646 50 16",
    "sg:postcode":"1050",
    "sg:province":"Bruxelles-Capitale",
    "wof:name":"Komar",
    "wof:placetype":"venue"
},
  "geometry": {"coordinates":[4.3695960045,50.8297386169],"type":"Point"}
}