{
  "type": "Feature",
  "properties": {
    "addr:full":"Tomt 6 Sint-lievens-houtem Oost-Vlaanderen 9520",
    "addr:housenumber":"6",
    "addr:postcode":"9520",
    "addr:street":"Tomt;Oost-Vlaanderen",
    "iso:country":"BE",
    "sg:address":"Tomt 6",
    "sg:city":"Sint-lievens-houtem",
    "sg:orig_category":"Ruimtes voor conferenties, recepties and feesten",
    "sg:phone":"+32 53 62 31 87",
    "sg:postcode":"9520",
    "sg:province":"Oost-Vlaanderen",
    "wof:name":"Feestzaal Cary",
    "wof:placetype":"venue"
},
  "geometry": {"coordinates":[3.9014389515,50.9316864014],"type":"Point"}
}