{
  "type": "Feature",
  "properties": {
    "addr:full":"Witteweg 65 Komen-waasten/comines-warneton Hainaut 7782",
    "addr:housenumber":"65",
    "addr:postcode":"7782",
    "addr:street":"Witteweg",
    "iso:country":"BE",
    "sg:address":"Witteweg 65",
    "sg:city":"Komen-waasten/comines-warneton",
    "sg:orig_category":"Sportclubs",
    "sg:phone":"+32 56 58 73 55",
    "sg:postcode":"7782",
    "sg:province":"Hainaut",
    "wof:name":"V.c. La Roue D'or",
    "wof:placetype":"venue"
},
  "geometry": {"coordinates":[2.8795371056,50.7278747559],"type":"Point"}
}