{
  "type": "Feature",
  "properties": {
    "addr:full":"Hofstraat 55 Mol Antwerpen 2400",
    "addr:housenumber":"55",
    "addr:postcode":"2400",
    "addr:street":"Hofstraat",
    "iso:country":"BE",
    "sg:address":"Hofstraat 55",
    "sg:city":"Mol",
    "sg:classifiers":[
        {
            "category":"Wholesale",
            "subcategory":"Books, Periodicals, & Newspapers",
            "type":"Manufacturing & Wholesale Goods"
        }
    ],
    "sg:phone":"+32 14 31 57 80",
    "sg:postcode":"2400",
    "sg:province":"Antwerpen",
    "sg:tags":[
        "publisher"
    ],
    "wof:name":"Libertas Bvba",
    "wof:placetype":"venue"
},
  "geometry": {"coordinates":[5.1204352379,51.1846542358],"type":"Point"}
}