{
  "type": "Feature",
  "properties": {
    "iso:country":"BE",
    "sg:address":"Avenue De Spa 30",
    "sg:city":"Verviers",
    "sg:classifiers":[
        {
            "category":"Health Services",
            "subcategory":"Dentist",
            "type":"Services"
        }
    ],
    "sg:phone":"+32 87 22 14 44",
    "sg:postcode":"4800",
    "sg:province":"Li\u00e8ge",
    "wof:name":"Comp\u00e8re E",
    "wof:placetype":"venue"
},
  "geometry": {"coordinates":[5.8628778458,50.5829238892],"type":"Point"}
}