{
  "type": "Feature",
  "properties": {
    "iso:country":"BE",
    "sg:address":"Langendonkstraat 1bb",
    "sg:city":"Beernem",
    "sg:orig_category":"Instituts de beaut\u00e9",
    "sg:phone":"+32 50 79 01 77",
    "sg:postcode":"8730",
    "sg:province":"West-Vlaanderen",
    "wof:name":"Catherine Bourgeois",
    "wof:placetype":"venue"
},
  "geometry": {"coordinates":[3.377204895,51.1392021179],"type":"Point"}
}