{
  "type": "Feature",
  "properties": {
    "iso:country":"BE",
    "sg:address":"Turnhoutsebaan 189",
    "sg:city":"Diest (molenstede)",
    "sg:classifiers":[
        {
            "category":"Personal",
            "subcategory":"Beauty Salon",
            "type":"Services"
        }
    ],
    "sg:phone":"+32 13 32 20 09",
    "sg:postcode":"3294",
    "sg:province":"Vlaams-Brabant",
    "sg:tags":[
        "lady",
        "-",
        "hairdressing"
    ],
    "wof:name":"Smolders K",
    "wof:placetype":"venue"
},
  "geometry": {"coordinates":[5.0239157677,51.0108184814],"type":"Point"}
}