{
  "type": "Feature",
  "properties": {
    "iso:country":"BE",
    "sg:address":"Rue Marcel Niessen 29a",
    "sg:city":"Musson",
    "sg:orig_category":"Kapsalons",
    "sg:phone":"+32 63 67 53 60",
    "sg:postcode":"6750",
    "sg:province":"Luxembourg",
    "wof:name":"Magic Coiffure",
    "wof:placetype":"venue"
},
  "geometry": {"coordinates":[5.6846899986,49.5567512512],"type":"Point"}
}