{
  "type": "Feature",
  "properties": {
    "addr:full":"Hoogstraat 22 Zottegem Oost-Vlaanderen 9620",
    "addr:housenumber":"22",
    "addr:postcode":"9620",
    "addr:street":"Hoogstraat",
    "iso:country":"BE",
    "sg:address":"Hoogstraat 22",
    "sg:city":"Zottegem",
    "sg:orig_category":"R\u00e9parations d'horloges, montres and bijoux. Bijouteries and horlogeries",
    "sg:phone":"+32 9 360 41 65",
    "sg:postcode":"9620",
    "sg:province":"Oost-Vlaanderen",
    "wof:name":"Bosmans",
    "wof:placetype":"venue"
},
  "geometry": {"coordinates":[3.8097190857,50.8687896729],"type":"Point"}
}