{
  "type": "Feature",
  "properties": {
    "iso:country":"BE",
    "sg:address":"Kerkstraat 55",
    "sg:city":"De Haan",
    "sg:classifiers":[
        {
            "category":"Restaurant",
            "type":"Food & Drink"
        }
    ],
    "sg:phone":"+32 50 41 41 39",
    "sg:postcode":"8420",
    "sg:province":"West-Vlaanderen",
    "wof:name":"Trios",
    "wof:placetype":"venue"
},
  "geometry": {"coordinates":[3.0811340809,51.2994117737],"type":"Point"}
}