{
  "type": "Feature",
  "properties": {
    "iso:country":"BE",
    "sg:address":"Ch De Tubize 455",
    "sg:city":"Braine-l'alleud",
    "sg:classifiers":[
        {
            "category":"Utilities",
            "subcategory":"Electric",
            "type":"Services"
        }
    ],
    "sg:phone":"+32 2 384 36 61",
    "sg:postcode":"1420",
    "sg:province":"Brabant Wallon",
    "sg:tags":[
        "electricity",
        "electronic",
        "electrical",
        "equipment"
    ],
    "wof:name":"Braintronic Sa",
    "wof:placetype":"venue"
},
  "geometry": {"coordinates":[4.1567811966,50.7084236145],"type":"Point"}
}