{
  "type": "Feature",
  "properties": {
    "addr:full":"Weligerveld 1 Lubbeek Vlaams-Brabant 3212",
    "addr:housenumber":"1",
    "addr:postcode":"3212",
    "addr:street":"Weligerveld",
    "iso:country":"BE",
    "sg:address":"Weligerveld 1",
    "sg:city":"Lubbeek",
    "sg:orig_category":"Enseignement maternel and primaire",
    "sg:phone":"+32 16 46 22 82",
    "sg:postcode":"3212",
    "sg:province":"Vlaams-Brabant",
    "wof:name":"Bubao",
    "wof:placetype":"venue"
},
  "geometry": {"coordinates":[4.7985239029,50.860584259],"type":"Point"}
}