{
  "type": "Feature",
  "properties": {
    "iso:country":"BE",
    "sg:address":"Rue De Bomel 3",
    "sg:city":"Namur",
    "sg:orig_category":"Brood, gebak and snoepgoed",
    "sg:phone":"+32 81 22 95 32",
    "sg:postcode":"5000",
    "sg:province":"Namur",
    "wof:name":"Jules Glinne",
    "wof:placetype":"venue"
},
  "geometry": {"coordinates":[4.8658561707,50.4708328247],"type":"Point"}
}