{
  "type": "Feature",
  "properties": {
    "addr:full":"Gasthuisvest 50 Lier Antwerpen 2500",
    "addr:housenumber":"50",
    "addr:postcode":"2500",
    "addr:street":"Gasthuisvest",
    "iso:country":"BE",
    "sg:address":"Gasthuisvest 50",
    "sg:city":"Lier",
    "sg:orig_category":"Enseignement artistique",
    "sg:phone":"+32 3 480 45 79",
    "sg:postcode":"2500",
    "sg:province":"Antwerpen",
    "wof:name":"Academie Voor Muziek, Woord En Dans",
    "wof:placetype":"venue"
},
  "geometry": {"coordinates":[4.574368,51.1287651062],"type":"Point"}
}