{
  "type": "Feature",
  "properties": {
    "addr:full":"Abelendreef 2 Moerbeke Oost-Vlaanderen 9180",
    "addr:housenumber":"2",
    "addr:postcode":"9180",
    "addr:street":"Abelendreef",
    "iso:country":"BE",
    "sg:address":"Abelendreef 2",
    "sg:city":"Moerbeke",
    "sg:orig_category":"Rundveehouders",
    "sg:phone":"+32 3 779 91 80",
    "sg:postcode":"9180",
    "sg:province":"Oost-Vlaanderen",
    "wof:name":"Freddy Van Gijsel",
    "wof:placetype":"venue"
},
  "geometry": {"coordinates":[3.9776699543,51.2216072083],"type":"Point"}
}