{
  "type": "Feature",
  "properties": {
    "addr:full":"Beervelde-dorp 46 Lochristi (beervelde) Oost-Vlaanderen 9080",
    "addr:housenumber":"46",
    "addr:postcode":"9080",
    "addr:street":"Beervelde-Dorp",
    "iso:country":"BE",
    "sg:address":"Beervelde-dorp 46",
    "sg:city":"Lochristi (beervelde)",
    "sg:classifiers":[
        {
            "category":"Home & Garden",
            "subcategory":"Household Appliances",
            "type":"Retail Goods"
        }
    ],
    "sg:phone":"+32 9 355 99 21",
    "sg:postcode":"9080",
    "sg:province":"Oost-Vlaanderen",
    "sg:tags":[
        "repair",
        "mainten",
        "-",
        "electric"
    ],
    "wof:name":"Van Schoote W-electro-computer Nv",
    "wof:placetype":"venue"
},
  "geometry": {"coordinates":[3.8324189186,51.1015472412],"type":"Point"}
}