{
  "type": "Feature",
  "properties": {
    "iso:country":"BE",
    "sg:address":"Moerkantsebaan 146",
    "sg:city":"Essen",
    "sg:orig_category":"Eleveurs and marchands de porcs",
    "sg:phone":"+32 3 667 55 95",
    "sg:postcode":"2910",
    "sg:province":"Antwerpen",
    "wof:name":"Constant Sanders",
    "wof:placetype":"venue"
},
  "geometry": {"coordinates":[4.4225997925,51.4489746094],"type":"Point"}
}