{
  "type": "Feature",
  "properties": {
    "iso:country":"BE",
    "sg:address":"Rue Des Bruy\u00e8res 4",
    "sg:city":"Ham-sur-heure-nalinnes (jamioulx)",
    "sg:classifiers":[
        {
            "category":"Bakery",
            "type":"Food & Drink"
        }
    ],
    "sg:phone":"+32 71 21 34 22",
    "sg:postcode":"6120",
    "sg:province":"Hainaut",
    "sg:tags":[
        "confectioner",
        "baker"
    ],
    "wof:name":"Ma Campagne",
    "wof:placetype":"venue"
},
  "geometry": {"coordinates":[4.4152369499,50.3559455872],"type":"Point"}
}