{
  "type": "Feature",
  "properties": {
    "iso:country":"BE",
    "sg:address":"Rue Henri Bles 78",
    "sg:city":"Namur",
    "sg:classifiers":[
        {
            "category":"Wholesale",
            "subcategory":"Plants",
            "type":"Manufacturing & Wholesale Goods"
        }
    ],
    "sg:phone":"+32 81 73 69 09",
    "sg:postcode":"5000",
    "sg:province":"Namur",
    "sg:tags":[
        "machine",
        "industrial",
        "automation"
    ],
    "wof:name":"Georges Dassy Et Fils S.a.",
    "wof:placetype":"venue"
},
  "geometry": {"coordinates":[4.8438091278,50.4651794434],"type":"Point"}
}