{
  "type": "Feature",
  "properties": {
    "iso:country":"BE",
    "sg:address":"Parijsstraat 108",
    "sg:city":"Evere/evere",
    "sg:orig_category":"Diverse organisaties and verenigingen Zalen voor culturele evenementen",
    "sg:phone":"+32 2 241 15 83",
    "sg:postcode":"1140",
    "sg:province":"Bruxelles-Capitale",
    "wof:name":"Foyer Culturel",
    "wof:placetype":"venue"
},
  "geometry": {"coordinates":[4.4030427933,50.8751449585],"type":"Point"}
}