{
  "type": "Feature",
  "properties": {
    "addr:full":"Moorselbaan 129 Aalst Oost-Vlaanderen 9300",
    "addr:housenumber":"129",
    "addr:postcode":"9300",
    "addr:street":"Moorselbaan",
    "iso:country":"BE",
    "sg:address":"Moorselbaan 129",
    "sg:city":"Aalst",
    "sg:orig_category":"Verlichting and huishoudartikelen",
    "sg:phone":"+32 53 21 24 51",
    "sg:postcode":"9300",
    "sg:province":"Oost-Vlaanderen",
    "wof:name":"Geschenken Eronda-willems",
    "wof:placetype":"venue"
},
  "geometry": {"coordinates":[4.050347805,50.9415473938],"type":"Point"}
}