{
  "type": "Feature",
  "properties": {
    "iso:country":"BE",
    "sg:address":"Obere Rottergasse 24",
    "sg:city":"Eupen",
    "sg:orig_category":"P\u00e9pini\u00e9ristes",
    "sg:phone":"+32 87 55 33 72",
    "sg:postcode":"4700",
    "sg:province":"Li\u00e8ge",
    "wof:name":"Christophe Klubert",
    "wof:placetype":"venue"
},
  "geometry": {"coordinates":[6.0488858223,50.6159896851],"type":"Point"}
}