{
  "type": "Feature",
  "properties": {
    "addr:full":"Paul Krugerstraat 3 Lier Antwerpen 2500",
    "addr:housenumber":"3",
    "addr:postcode":"2500",
    "addr:street":"Paul Krugerstraat",
    "iso:country":"BE",
    "sg:address":"Paul Krugerstraat 3",
    "sg:city":"Lier",
    "sg:orig_category":"M\u00e9decins and sp\u00e9cialistes",
    "sg:phone":"+32 3 488 01 19",
    "sg:postcode":"2500",
    "sg:province":"Antwerpen",
    "wof:name":"Johan Coussee",
    "wof:placetype":"venue"
},
  "geometry": {"coordinates":[4.5825529099,51.1277503967],"type":"Point"}
}