{
  "type": "Feature",
  "properties": {
    "addr:full":"Bevrijdingslaan 88 Gent Oost-Vlaanderen 9000",
    "addr:housenumber":"88",
    "addr:postcode":"9000",
    "addr:street":"Bevrijdingslaan;Oost-Vlaanderen",
    "iso:country":"BE",
    "sg:address":"Bevrijdingslaan 88",
    "sg:city":"Gent",
    "sg:classifiers":[
        {
            "category":"Social Services",
            "type":"Services"
        }
    ],
    "sg:phone":"+32 9 226 38 98",
    "sg:postcode":"9000",
    "sg:province":"Oost-Vlaanderen",
    "wof:name":"Consultatiebureau Voor Het Jonge Kind",
    "wof:placetype":"venue"
},
  "geometry": {"coordinates":[3.6961109638,51.0635795593],"type":"Point"}
}