{
  "type": "Feature",
  "properties": {
    "addr:full":"Leynseelstraat 75 Avelgem West-Vlaanderen 8580",
    "addr:housenumber":"75",
    "addr:postcode":"8580",
    "addr:street":"Leynseelstraat",
    "iso:country":"BE",
    "sg:address":"Leynseelstraat 75",
    "sg:city":"Avelgem",
    "sg:classifiers":[
        {
            "category":"Home & Garden",
            "subcategory":"Hardware",
            "type":"Retail Goods"
        }
    ],
    "sg:phone":"+32 56 64 42 04",
    "sg:postcode":"8580",
    "sg:province":"West-Vlaanderen",
    "sg:tags":[
        "gate",
        "opener",
        "door",
        "automatic"
    ],
    "wof:name":"Vercruysse K Nv",
    "wof:placetype":"venue"
},
  "geometry": {"coordinates":[3.4300680161,50.775604248],"type":"Point"}
}