{
  "type": "Feature",
  "properties": {
    "addr:full":"Polenstraat 17 Evergem Oost-Vlaanderen 9940",
    "addr:housenumber":"17",
    "addr:postcode":"9940",
    "addr:street":"Polenstraat;Oost-Vlaanderen",
    "iso:country":"BE",
    "sg:address":"Polenstraat 17",
    "sg:city":"Evergem",
    "sg:orig_category":"Maatschappelijke dienstverlening",
    "sg:phone":"+32 9 358 20 03",
    "sg:postcode":"9940",
    "sg:province":"Oost-Vlaanderen",
    "wof:name":"Rode Kruis Sleidinge",
    "wof:placetype":"venue"
},
  "geometry": {"coordinates":[3.6791110039,51.1305122375],"type":"Point"}
}