{
  "type": "Feature",
  "properties": {
    "iso:country":"BE",
    "sg:address":"Leopold I Straat 419ba",
    "sg:city":"Jette/jette",
    "sg:orig_category":"Woningbouw",
    "sg:phone":"+32 2 426 27 54",
    "sg:postcode":"1090",
    "sg:province":"Bruxelles-Capitale",
    "wof:name":"Daniel Van De Velde",
    "wof:placetype":"venue"
},
  "geometry": {"coordinates":[4.3324580193,50.8745880127],"type":"Point"}
}