{
  "type": "Feature",
  "properties": {
    "addr:full":"Stationsplein 21 Lokeren Oost-Vlaanderen 9160",
    "addr:housenumber":"21",
    "addr:postcode":"9160",
    "addr:street":"Stationsplein",
    "iso:country":"BE",
    "sg:address":"Stationsplein 21",
    "sg:city":"Lokeren",
    "sg:orig_category":"Banken and kredietinstellingen",
    "sg:phone":"+32 9 348 48 58",
    "sg:postcode":"9160",
    "sg:province":"Oost-Vlaanderen",
    "wof:name":"Fortis",
    "wof:placetype":"venue"
},
  "geometry": {"coordinates":[3.9887259007,51.1078643799],"type":"Point"}
}