{
  "type": "Feature",
  "properties": {
    "addr:full":"Steenweg 239 Alken Limburg 3570",
    "addr:housenumber":"239",
    "addr:postcode":"3570",
    "addr:street":"Steenweg",
    "iso:country":"BE",
    "sg:address":"Steenweg 239",
    "sg:city":"Alken",
    "sg:classifiers":[
        {
            "category":"Professional",
            "subcategory":"Art Services",
            "type":"Services"
        }
    ],
    "sg:phone":"+32 11 31 21 90",
    "sg:postcode":"3570",
    "sg:province":"Limburg",
    "sg:tags":[
        "picture",
        "framer"
    ],
    "wof:name":"Du R\u00e9au",
    "wof:placetype":"venue"
},
  "geometry": {"coordinates":[5.2745299339,50.8805732727],"type":"Point"}
}