{
  "type": "Feature",
  "properties": {
    "addr:full":"Duinenweg 509 Middelkerke West-Vlaanderen 8430",
    "addr:housenumber":"509",
    "addr:postcode":"8430",
    "addr:street":"Duinenweg",
    "iso:country":"BE",
    "sg:address":"Duinenweg 509",
    "sg:city":"Middelkerke",
    "sg:classifiers":[
        {
            "category":"Social Services",
            "subcategory":"Job Training",
            "type":"Services"
        }
    ],
    "sg:phone":"+32 59 30 09 56",
    "sg:postcode":"8430",
    "sg:province":"West-Vlaanderen",
    "sg:tags":[
        "de",
        "terrain",
        "camping"
    ],
    "wof:name":"Marva I",
    "wof:placetype":"venue"
},
  "geometry": {"coordinates":[2.7916100025,51.1751289368],"type":"Point"}
}