{
  "type": "Feature",
  "properties": {
    "addr:full":"Rue Berkendael 96 Elsene/ixelles Bruxelles-Capitale 1050",
    "addr:housenumber":"96",
    "addr:postcode":"1050",
    "addr:street":"Rue Berkendael",
    "iso:country":"BE",
    "sg:address":"Rue Berkendael 96",
    "sg:city":"Elsene/ixelles",
    "sg:orig_category":"Ordinateurs Fab. R\u00e9alisation de programmes and logiciels. Machines and mat\u00e9riel de bureau Secr\u00e9taria",
    "sg:phone":"+32 2 344 17 38",
    "sg:postcode":"1050",
    "sg:province":"Bruxelles-Capitale",
    "wof:name":"D.m. & S.",
    "wof:placetype":"venue"
},
  "geometry": {"coordinates":[4.3512988091,50.8170661926],"type":"Point"}
}