{
  "type": "Feature",
  "properties": {
    "addr:full":"Tiensesteenweg 319 Leuven (kessel-lo) Vlaams-Brabant 3010",
    "addr:housenumber":"319",
    "addr:postcode":"3010",
    "addr:street":"Tiensesteenweg",
    "iso:country":"BE",
    "sg:address":"Tiensesteenweg 319",
    "sg:city":"Leuven (kessel-lo)",
    "sg:classifiers":[
        {
            "category":"Health Services",
            "subcategory":"Doctor",
            "type":"Services"
        }
    ],
    "sg:phone":"+32 16 26 07 76",
    "sg:postcode":"3010",
    "sg:province":"Vlaams-Brabant",
    "sg:tags":[
        "medicinephysicians",
        "surgeon"
    ],
    "wof:name":"Maes L",
    "wof:placetype":"venue"
},
  "geometry": {"coordinates":[4.7355918884,50.8688087463],"type":"Point"}
}