{
  "type": "Feature",
  "properties": {
    "iso:country":"BE",
    "sg:address":"Laarstraat 8",
    "sg:city":"Kampenhout (nederokkerzeel)",
    "sg:classifiers":[
        {
            "category":"Health Services",
            "subcategory":"Dentist",
            "type":"Services"
        }
    ],
    "sg:phone":"+32 16 65 74 75",
    "sg:postcode":"1910",
    "sg:province":"Vlaams-Brabant",
    "wof:name":"Moriau L",
    "wof:placetype":"venue"
},
  "geometry": {"coordinates":[4.5513768196,50.9222068787],"type":"Point"}
}