{
  "type": "Feature",
  "properties": {
    "addr:full":"Chemin De La Fontaine 43 Jalhay Li\u00e8ge 4845",
    "addr:housenumber":"43",
    "addr:postcode":"4845",
    "addr:street":"Chemin De La Fontaine",
    "iso:country":"BE",
    "sg:address":"Chemin De La Fontaine 43",
    "sg:city":"Jalhay",
    "sg:classifiers":[
        {
            "category":"Home & Garden",
            "subcategory":"Kitchen Supply",
            "type":"Retail Goods"
        }
    ],
    "sg:phone":"+32 87 77 08 98",
    "sg:postcode":"4845",
    "sg:province":"Li\u00e8ge",
    "sg:tags":[
        "installation"
    ],
    "wof:name":"Peters J-m",
    "wof:placetype":"venue"
},
  "geometry": {"coordinates":[5.8951740265,50.5003356934],"type":"Point"}
}