{
  "type": "Feature",
  "properties": {
    "addr:full":"Rue Gr\u00c9goire-bodart 1ba Huy Li\u00e8ge 4500",
    "addr:housenumber":"1ba",
    "addr:postcode":"4500",
    "addr:street":"Rue Gre\u0301Goire-Bodart",
    "iso:country":"BE",
    "sg:address":"Rue Gr\u00c9goire-bodart 1ba",
    "sg:city":"Huy",
    "sg:orig_category":"Enseignement sup\u00e9rieur",
    "sg:phone":"+32 85 21 11 92",
    "sg:postcode":"4500",
    "sg:province":"Li\u00e8ge",
    "wof:name":"I.e.s.p.p.e.c.f.",
    "wof:placetype":"venue"
},
  "geometry": {"coordinates":[5.2416968346,50.5207443237],"type":"Point"}
}