{
  "type": "Feature",
  "properties": {
    "iso:country":"BE",
    "sg:address":"Kerkeveld 25",
    "sg:city":"Boutersem (honsem)",
    "sg:classifiers":[
        {
            "category":"Professional",
            "subcategory":"Management & Consulting",
            "type":"Services"
        }
    ],
    "sg:phone":"+32 16 73 58 48",
    "sg:postcode":"3370",
    "sg:province":"Vlaams-Brabant",
    "sg:tags":[
        "-",
        "processing",
        "data",
        "consultant"
    ],
    "wof:name":"Informatica Advies Bureau Bvba",
    "wof:placetype":"venue"
},
  "geometry": {"coordinates":[4.8123641014,50.8218460083],"type":"Point"}
}