{
  "type": "Feature",
  "properties": {
    "addr:full":"Casterhovenstraat 63 Hasselt Limburg 3500",
    "addr:housenumber":"63",
    "addr:postcode":"3500",
    "addr:street":"Casterhovenstraat",
    "iso:country":"BE",
    "sg:address":"Casterhovenstraat 63",
    "sg:city":"Hasselt",
    "sg:orig_category":"M\u00e9decins and sp\u00e9cialistes",
    "sg:phone":"+32 11 23 28 44",
    "sg:postcode":"3500",
    "sg:province":"Limburg",
    "wof:name":"Marleen Loenders",
    "wof:placetype":"venue"
},
  "geometry": {"coordinates":[5.3557081223,50.9303512573],"type":"Point"}
}