{
  "type": "Feature",
  "properties": {
    "addr:full":"Kiezelvoort 65 Heusden-zolder (heusden) Limburg 3550",
    "addr:housenumber":"65",
    "addr:postcode":"3550",
    "addr:street":"Kiezelvoort",
    "iso:country":"BE",
    "sg:address":"Kiezelvoort 65",
    "sg:city":"Heusden-zolder (heusden)",
    "sg:orig_category":"Leisure articles",
    "sg:phone":"+32 11 42 97 96",
    "sg:postcode":"3550",
    "sg:province":"Limburg",
    "wof:name":"Krealand Hobby",
    "wof:placetype":"venue"
},
  "geometry": {"coordinates":[5.2532248497,51.0384025574],"type":"Point"}
}