{
  "type": "Feature",
  "properties": {
    "addr:full":"Nieuwstraat 1b9a Borgloon Limburg 3840",
    "addr:housenumber":"1b9a",
    "addr:postcode":"3840",
    "addr:street":"Nieuwstraat",
    "iso:country":"BE",
    "sg:address":"Nieuwstraat 1b9a",
    "sg:city":"Borgloon",
    "sg:orig_category":"Production de films, t\u00e9l\u00e9films and vid\u00e9os. Agences de presse",
    "sg:phone":"+32 12 74 54 69",
    "sg:postcode":"3840",
    "sg:province":"Limburg",
    "wof:name":"Frank Toppets",
    "wof:placetype":"venue"
},
  "geometry": {"coordinates":[5.3404049873,50.8034172058],"type":"Point"}
}