{
  "type": "Feature",
  "properties": {
    "addr:full":"Huidevetterijstraat 4 Koekelberg/koekelberg Bruxelles-Capitale 1081",
    "addr:housenumber":"4",
    "addr:postcode":"1081",
    "addr:street":"Huidevetterijstraat",
    "iso:country":"BE",
    "sg:address":"Huidevetterijstraat 4",
    "sg:city":"Koekelberg/koekelberg",
    "sg:orig_category":"Kinderopvang",
    "sg:phone":"+32 2 411 30 56",
    "sg:postcode":"1081",
    "sg:province":"Bruxelles-Capitale",
    "wof:name":"Garderie Prelude",
    "wof:placetype":"venue"
},
  "geometry": {"coordinates":[4.3309121132,50.860710144],"type":"Point"}
}