{
  "type": "Feature",
  "properties": {
    "iso:country":"BE",
    "sg:address":"A Sauwenin 23",
    "sg:city":"Dilsen-stokkem",
    "sg:orig_category":"Fleurs and plantes",
    "sg:phone":"+32 89 75 51 06",
    "sg:postcode":"3650",
    "sg:province":"Limburg",
    "wof:name":"Bloemenweelde",
    "wof:placetype":"venue"
},
  "geometry": {"coordinates":[5.727396965,51.0364189148],"type":"Point"}
}