{
  "type": "Feature",
  "properties": {
    "addr:full":"August Van Putlei 72 Borsbeek Antwerpen 2150",
    "addr:housenumber":"72",
    "addr:postcode":"2150",
    "addr:street":"August;Putlei",
    "iso:country":"BE",
    "sg:address":"August Van Putlei 72",
    "sg:city":"Borsbeek",
    "sg:orig_category":"Banques and organismes de cr\u00e9dit",
    "sg:phone":"+32 3 321 80 04",
    "sg:postcode":"2150",
    "sg:province":"Antwerpen",
    "wof:name":"Kbc",
    "wof:placetype":"venue"
},
  "geometry": {"coordinates":[4.4758648872,51.1967887878],"type":"Point"}
}