{
  "type": "Feature",
  "properties": {
    "addr:full":"Avenue Wanderpepen 70 Binche Hainaut 7130",
    "addr:housenumber":"70",
    "addr:postcode":"7130",
    "addr:street":"Avenue Wanderpepen",
    "iso:country":"BE",
    "sg:address":"Avenue Wanderpepen 70",
    "sg:city":"Binche",
    "sg:orig_category":"Deurwaarders",
    "sg:phone":"+32 64 36 66 00",
    "sg:postcode":"7130",
    "sg:province":"Hainaut",
    "wof:name":"Jacques Lachapelle",
    "wof:placetype":"venue"
},
  "geometry": {"coordinates":[4.1713929176,50.4120254517],"type":"Point"}
}