{
  "type": "Feature",
  "properties": {
    "iso:country":"BE",
    "sg:address":"Alsembergse Steenweg 100-104",
    "sg:city":"Sint-gillis/saint-gilles",
    "sg:orig_category":"Benzinestations and brandstoffen Herstellingen and onderhoud van auto's Voertuigen",
    "sg:phone":"+32 2 537 74 04",
    "sg:postcode":"1060",
    "sg:province":"Bruxelles-Capitale",
    "wof:name":"Garage Devos",
    "wof:placetype":"venue"
},
  "geometry": {"coordinates":[4.343307972,50.8234291077],"type":"Point"}
}