{
  "type": "Feature",
  "properties": {
    "iso:country":"BE",
    "sg:address":"Galgenberg 15",
    "sg:city":"Gent",
    "sg:classifiers":[
        {
            "category":"Communications",
            "subcategory":"Film & Video Production",
            "type":"Services"
        }
    ],
    "sg:phone":"+32 9 233 31 33",
    "sg:postcode":"9000",
    "sg:province":"Oost-Vlaanderen",
    "sg:tags":[
        "sound",
        "recording",
        "studio"
    ],
    "wof:name":"Digi Classics Bvba",
    "wof:placetype":"venue"
},
  "geometry": {"coordinates":[3.713960886,51.0511550903],"type":"Point"}
}