{
  "type": "Feature",
  "properties": {
    "addr:full":"Heidebloemstraat 14 Zonhoven Limburg 3520",
    "addr:housenumber":"14",
    "addr:postcode":"3520",
    "addr:street":"Heidebloemstraat",
    "iso:country":"BE",
    "sg:address":"Heidebloemstraat 14",
    "sg:city":"Zonhoven",
    "sg:orig_category":"Woningbouw",
    "sg:phone":"+32 11 81 54 05",
    "sg:postcode":"3520",
    "sg:province":"Limburg",
    "wof:name":"L.b.c.",
    "wof:placetype":"venue"
},
  "geometry": {"coordinates":[5.3662571907,50.9732017517],"type":"Point"}
}