{
  "type": "Feature",
  "properties": {
    "addr:full":"Chauss\u00c9e De La Hulpe 166 Watermaal-bosvoorde/watermael-boitsfort Bruxelles-Capitale 1170",
    "addr:housenumber":"166",
    "addr:postcode":"1170",
    "addr:street":"Chausse\u0301E De La Hulpe",
    "iso:country":"BE",
    "sg:address":"Chauss\u00c9e De La Hulpe 166",
    "sg:city":"Watermaal-bosvoorde/watermael-boitsfort",
    "sg:orig_category":"Cr\u00e9dit \u00e0 la consommation",
    "sg:phone":"+32 2 663 80 90",
    "sg:postcode":"1170",
    "sg:province":"Bruxelles-Capitale",
    "wof:name":"Capital Partners Belgium",
    "wof:placetype":"venue"
},
  "geometry": {"coordinates":[4.4065299034,50.7955703735],"type":"Point"}
}