{
  "type": "Feature",
  "properties": {
    "addr:full":"Hoefijzerstraat 21 Ichtegem West-Vlaanderen 8480",
    "addr:housenumber":"21",
    "addr:postcode":"8480",
    "addr:street":"Hoefijzerstraat",
    "iso:country":"BE",
    "sg:address":"Hoefijzerstraat 21",
    "sg:city":"Ichtegem",
    "sg:orig_category":"Epiceries",
    "sg:phone":"+32 50 22 06 35",
    "sg:postcode":"8480",
    "sg:province":"West-Vlaanderen",
    "wof:name":"Katrien Decherf",
    "wof:placetype":"venue"
},
  "geometry": {"coordinates":[3.0444829464,51.0890274048],"type":"Point"}
}