{
  "type": "Feature",
  "properties": {
    "addr:full":"Grensstraat 36 Putte Antwerpen 2580",
    "addr:housenumber":"36",
    "addr:postcode":"2580",
    "addr:street":"Grensstraat",
    "iso:country":"BE",
    "sg:address":"Grensstraat 36",
    "sg:city":"Putte",
    "sg:orig_category":"Slagers",
    "sg:phone":"+32 15 23 41 92",
    "sg:postcode":"2580",
    "sg:province":"Antwerpen",
    "wof:name":"Haegeman",
    "wof:placetype":"venue"
},
  "geometry": {"coordinates":[4.658012867,51.0193328857],"type":"Point"}
}