{
  "type": "Feature",
  "properties": {
    "iso:country":"BE",
    "sg:address":"Weggevoerdenstraat 16",
    "sg:city":"Tessenderlo",
    "sg:orig_category":"Openbare veiligheid",
    "sg:phone":"+32 13 66 10 18",
    "sg:postcode":"3980",
    "sg:province":"Limburg",
    "wof:name":"Federale Politie/police F\u00c9d\u00c9rale",
    "wof:placetype":"venue"
},
  "geometry": {"coordinates":[5.0912051201,51.0658988953],"type":"Point"}
}