{
  "type": "Feature",
  "properties": {
    "iso:country":"BE",
    "sg:address":"Bloemenstraat 53",
    "sg:city":"Wellen",
    "sg:classifiers":[
        {
            "category":"Bars & Pubs",
            "type":"Food & Drink"
        }
    ],
    "sg:phone":"+32 12 74 52 30",
    "sg:postcode":"3830",
    "sg:province":"Limburg",
    "wof:name":"Bloemenhof",
    "wof:placetype":"venue"
},
  "geometry": {"coordinates":[5.3396701813,50.8444404602],"type":"Point"}
}