{
  "type": "Feature",
  "properties": {
    "addr:full":"Van Overbekelaan 161b12 Ganshoren/ganshoren Bruxelles-Capitale 1083",
    "addr:housenumber":"161b12",
    "addr:postcode":"1083",
    "addr:street":"Van Overbekelaan",
    "iso:country":"BE",
    "sg:address":"Van Overbekelaan 161b12",
    "sg:city":"Ganshoren/ganshoren",
    "sg:orig_category":"Beheer onroerend goed",
    "sg:phone":"+32 2 427 39 77",
    "sg:postcode":"1083",
    "sg:province":"Bruxelles-Capitale",
    "wof:name":"Bastin Stevens",
    "wof:placetype":"venue"
},
  "geometry": {"coordinates":[4.31148386,50.8731956482],"type":"Point"}
}