{
  "type": "Feature",
  "properties": {
    "iso:country":"BE",
    "sg:address":"Dokter Dumortierlaan 15",
    "sg:city":"Kortrijk",
    "sg:orig_category":"DIVERSE RECREATIEVE ACTIVITEITEN",
    "sg:phone":"+32 56 35 67 59",
    "sg:postcode":"8501",
    "sg:province":"West-Vlaanderen",
    "wof:name":"Postzegelclub Leiestreek",
    "wof:placetype":"venue"
},
  "geometry": {"coordinates":[3.2287740707,50.8318328857],"type":"Point"}
}