{
  "type": "Feature",
  "properties": {
    "iso:country":"BE",
    "sg:address":"Rue Des Bonniers 91",
    "sg:city":"Lobbes",
    "sg:orig_category":"Installation \u00e9lectrique r\u00e9sidentielle",
    "sg:phone":"+32 71 59 38 13",
    "sg:postcode":"6540",
    "sg:province":"Hainaut",
    "wof:name":"Lobbelec",
    "wof:placetype":"venue"
},
  "geometry": {"coordinates":[4.2744789124,50.3684921265],"type":"Point"}
}