{
  "type": "Feature",
  "properties": {
    "iso:country":"BE",
    "sg:address":"Ster 53",
    "sg:city":"Sint-niklaas",
    "sg:orig_category":"Agences d'exp\u00e9dition",
    "sg:phone":"+32 3 766 69 29",
    "sg:postcode":"9100",
    "sg:province":"Oost-Vlaanderen",
    "wof:name":"Salocin",
    "wof:placetype":"venue"
},
  "geometry": {"coordinates":[4.1912851334,51.1779251099],"type":"Point"}
}