{
  "type": "Feature",
  "properties": {
    "iso:country":"BE",
    "sg:address":"Rue Adelin Colon 56",
    "sg:city":"Wavre",
    "sg:orig_category":"Loodgieterij, verwarming and sanitaire installaties",
    "sg:phone":"+32 10 22 48 31",
    "sg:postcode":"1300",
    "sg:province":"Brabant Wallon",
    "wof:name":"Michel Lebrun",
    "wof:placetype":"venue"
},
  "geometry": {"coordinates":[4.6138310432,50.7209510803],"type":"Point"}
}