{
  "type": "Feature",
  "properties": {
    "addr:full":"Rue De La Marcelle 72 Couvin Namur 5660",
    "addr:housenumber":"72",
    "addr:postcode":"5660",
    "addr:street":"Rue De La Marcelle",
    "iso:country":"BE",
    "sg:address":"Rue De La Marcelle 72",
    "sg:city":"Couvin",
    "sg:classifiers":[
        {
            "category":"Social Services",
            "type":"Services"
        }
    ],
    "sg:phone":"+32 60 34 48 84",
    "sg:postcode":"5660",
    "sg:province":"Namur",
    "wof:name":"C I A C",
    "wof:placetype":"venue"
},
  "geometry": {"coordinates":[4.496969223,50.048915863],"type":"Point"}
}