{
  "type": "Feature",
  "properties": {
    "iso:country":"BE",
    "sg:address":"Rue A. Diderich 32",
    "sg:city":"Sint-gillis/saint-gilles",
    "sg:orig_category":"Maisons de repos and r\u00e9sidences",
    "sg:phone":"+32 2 348 57 61",
    "sg:postcode":"1060",
    "sg:province":"Bruxelles-Capitale",
    "wof:name":"Home Les Tilleuls",
    "wof:placetype":"venue"
},
  "geometry": {"coordinates":[4.3442649841,50.8227539062],"type":"Point"}
}