{
  "type": "Feature",
  "properties": {
    "iso:country":"BE",
    "sg:address":"Grote Bergen 15b",
    "sg:city":"Willebroek",
    "sg:classifiers":[
        {
            "category":"Arena",
            "subcategory":"Sports Club",
            "type":"Entertainment"
        }
    ],
    "sg:phone":"+32 3 886 40 15",
    "sg:postcode":"2830",
    "sg:province":"Antwerpen",
    "sg:tags":[
        "de"
    ],
    "wof:name":"Supportersclub 't Vliegend Wiel",
    "wof:placetype":"venue"
},
  "geometry": {"coordinates":[4.3949680328,51.0683135986],"type":"Point"}
}