{
  "type": "Feature",
  "properties": {
    "addr:full":"Keverslaan 11 Brussel/bruxelles Bruxelles-Capitale 1000",
    "addr:housenumber":"11",
    "addr:postcode":"1000",
    "addr:street":"Keverslaan;/",
    "iso:country":"BE",
    "sg:address":"Keverslaan 11",
    "sg:city":"Brussel/bruxelles",
    "sg:orig_category":"Advocaten and juridische adviseurs",
    "sg:phone":"+32 2 644 48 00",
    "sg:postcode":"1000",
    "sg:province":"Bruxelles-Capitale",
    "wof:name":"M. Van Lierde",
    "wof:placetype":"venue"
},
  "geometry": {"coordinates":[4.3867001534,50.8072471619],"type":"Point"}
}