{
  "type": "Feature",
  "properties": {
    "addr:full":"Stoktevijver 13 Zomergem (ronsele) Oost-Vlaanderen 9932",
    "addr:housenumber":"13",
    "addr:postcode":"9932",
    "addr:street":"Stoktevijver",
    "iso:country":"BE",
    "sg:address":"Stoktevijver 13",
    "sg:city":"Zomergem (ronsele)",
    "sg:orig_category":"Non-Classified Establishments",
    "sg:phone":"+32 9 372 70 10",
    "sg:postcode":"9932",
    "sg:province":"Oost-Vlaanderen",
    "wof:name":"Rijckaert L",
    "wof:placetype":"venue"
},
  "geometry": {"coordinates":[3.5610489845,51.1304130554],"type":"Point"}
}