{
  "type": "Feature",
  "properties": {
    "addr:full":"Route Provinciale 83 Tournai Hainaut 7543",
    "addr:housenumber":"83",
    "addr:postcode":"7543",
    "addr:street":"Route Provinciale",
    "iso:country":"BE",
    "sg:address":"Route Provinciale 83",
    "sg:city":"Tournai",
    "sg:orig_category":"Fantasieartikelen Verhuur cateringmateriaal and evenementuitrusting",
    "sg:phone":"+32 69 85 99 39",
    "sg:postcode":"7543",
    "sg:province":"Hainaut",
    "wof:name":"Cath\u00c9rine Tentes",
    "wof:placetype":"venue"
},
  "geometry": {"coordinates":[3.4349970818,50.657371521],"type":"Point"}
}