{
  "type": "Feature",
  "properties": {
    "iso:country":"BE",
    "sg:address":"Honsemsestraat 17",
    "sg:city":"Boutersem",
    "sg:classifiers":[
        {
            "category":"Wholesale",
            "subcategory":"Meat",
            "type":"Manufacturing & Wholesale Goods"
        }
    ],
    "sg:phone":"+32 16 73 47 20",
    "sg:postcode":"3370",
    "sg:province":"Vlaams-Brabant",
    "sg:tags":[
        "machine",
        "product",
        "-",
        "supply"
    ],
    "wof:name":"Demco",
    "wof:placetype":"venue"
},
  "geometry": {"coordinates":[4.8333587646,50.8283233643],"type":"Point"}
}