{
  "type": "Feature",
  "properties": {
    "iso:country":"BE",
    "sg:address":"Hagedoornlaan 3-2a",
    "sg:city":"Schilde",
    "sg:classifiers":[
        {
            "category":"Professional",
            "subcategory":"Accounting & Tax Preparation",
            "type":"Services"
        }
    ],
    "sg:phone":"+32 3 383 17 73",
    "sg:postcode":"2970",
    "sg:province":"Antwerpen",
    "sg:tags":[
        "bookkeeper"
    ],
    "wof:name":"Arsim Bvba",
    "wof:placetype":"venue"
},
  "geometry": {"coordinates":[4.5749077797,51.235004425],"type":"Point"}
}