{
  "type": "Feature",
  "properties": {
    "iso:country":"BE",
    "sg:address":"Marialoopsteenweg 90",
    "sg:city":"Meulebeke",
    "sg:orig_category":"Installatie van houten of kunststof schrijnwerk Pleisterwerk Woningbouw",
    "sg:phone":"+32 51 40 41 42",
    "sg:postcode":"8760",
    "sg:province":"West-Vlaanderen",
    "wof:name":"Tytgat",
    "wof:placetype":"venue"
},
  "geometry": {"coordinates":[3.323980093,50.9630889893],"type":"Point"}
}