{
  "type": "Feature",
  "properties": {
    "iso:country":"BE",
    "sg:address":"Rue L\u00e9on Lef\u00e8vre 34",
    "sg:city":"Namur (champion - Cognel\u00e9e)",
    "sg:classifiers":[
        {
            "category":"Professional",
            "subcategory":"Accounting & Tax Preparation",
            "type":"Services"
        }
    ],
    "sg:phone":"+32 81 21 28 97",
    "sg:postcode":"5020",
    "sg:province":"Namur",
    "sg:tags":[
        "accountant"
    ],
    "wof:name":"Govaerts A",
    "wof:placetype":"venue"
},
  "geometry": {"coordinates":[4.9044661522,50.4987297058],"type":"Point"}
}