{
  "type": "Feature",
  "properties": {
    "iso:country":"BE",
    "sg:address":"Rue Des Bourreliers 1",
    "sg:city":"Gesves",
    "sg:orig_category":"V\u00e9t\u00e9rinaires",
    "sg:phone":"+32 83 67 74 06",
    "sg:postcode":"5340",
    "sg:province":"Namur",
    "wof:name":"Mathias Vrancken",
    "wof:placetype":"venue"
},
  "geometry": {"coordinates":[5.1205677986,50.3963623047],"type":"Point"}
}