{
  "type": "Feature",
  "properties": {
    "addr:full":"Ertsenrijkstraat 153 Halen Limburg 3545",
    "addr:housenumber":"153",
    "addr:postcode":"3545",
    "addr:street":"Ertsenrijkstraat",
    "iso:country":"BE",
    "sg:address":"Ertsenrijkstraat 153",
    "sg:city":"Halen",
    "sg:orig_category":"Eleveurs and marchands de porcs",
    "sg:phone":"+32 13 44 11 13",
    "sg:postcode":"3545",
    "sg:province":"Limburg",
    "wof:name":"Knaepen Bedrijven",
    "wof:placetype":"venue"
},
  "geometry": {"coordinates":[5.1232428551,50.9211845398],"type":"Point"}
}