{
  "type": "Feature",
  "properties": {
    "addr:full":"Stokveldelaan 30 Brugge West-Vlaanderen 8200",
    "addr:housenumber":"30",
    "addr:postcode":"8200",
    "addr:street":"Stokveldelaan",
    "iso:country":"BE",
    "sg:address":"Stokveldelaan 30",
    "sg:city":"Brugge",
    "sg:orig_category":"Apotheken",
    "sg:phone":"+32 50 38 50 17",
    "sg:postcode":"8200",
    "sg:province":"West-Vlaanderen",
    "wof:name":"Marianne Vercruysse",
    "wof:placetype":"venue"
},
  "geometry": {"coordinates":[3.1904699802,51.1992111206],"type":"Point"}
}