{
  "type": "Feature",
  "properties": {
    "iso:country":"BE",
    "sg:address":"Sijsjesweg 61",
    "sg:city":"Keerbergen",
    "sg:classifiers":[
        {
            "category":"Professional",
            "subcategory":"Management & Consulting",
            "type":"Services"
        }
    ],
    "sg:phone":"+32 15 23 51 53",
    "sg:postcode":"3140",
    "sg:province":"Vlaams-Brabant",
    "sg:tags":[
        "tax-consultants"
    ],
    "wof:name":"Van Dael J",
    "wof:placetype":"venue"
},
  "geometry": {"coordinates":[4.644329071,51.0183296204],"type":"Point"}
}