{
  "type": "Feature",
  "properties": {
    "addr:full":"Peperstraat 27 Kampenhout Vlaams-Brabant 1910",
    "addr:housenumber":"27",
    "addr:postcode":"1910",
    "addr:street":"Peperstraat",
    "iso:country":"BE",
    "sg:address":"Peperstraat 27",
    "sg:city":"Kampenhout",
    "sg:orig_category":"Cr\u00e9meries",
    "sg:phone":"+32 16 65 11 67",
    "sg:postcode":"1910",
    "sg:province":"Vlaams-Brabant",
    "wof:name":"Patrick Herremans",
    "wof:placetype":"venue"
},
  "geometry": {"coordinates":[4.5653829575,50.9227256775],"type":"Point"}
}