{
  "type": "Feature",
  "properties": {
    "addr:full":"Rue De Huy 2 Fernelmont Namur 5380",
    "addr:housenumber":"2",
    "addr:postcode":"5380",
    "addr:street":"Rue De Huy",
    "iso:country":"BE",
    "sg:address":"Rue De Huy 2",
    "sg:city":"Fernelmont",
    "sg:classifiers":[
        {
            "category":"Restaurant",
            "type":"Food & Drink"
        }
    ],
    "sg:phone":"+32 81 83 37 72",
    "sg:postcode":"5380",
    "sg:province":"Namur",
    "sg:tags":[
        "caf\u00e9s"
    ],
    "wof:name":"Taverne Le Poteau",
    "wof:placetype":"venue"
},
  "geometry": {"coordinates":[5.0460247993,50.5512008667],"type":"Point"}
}