{
  "type": "Feature",
  "properties": {
    "addr:full":"Rue Alban-poulet 18 Li\u00c8ge Li\u00e8ge 4032",
    "addr:housenumber":"18",
    "addr:postcode":"4032",
    "addr:street":"Rue Alban-Poulet",
    "iso:country":"BE",
    "sg:address":"Rue Alban-poulet 18",
    "sg:city":"Li\u00c8ge",
    "sg:orig_category":"Woningbouw",
    "sg:phone":"+32 4 365 70 57",
    "sg:postcode":"4032",
    "sg:province":"Li\u00e8ge",
    "wof:name":"Jean-claude Sougnez",
    "wof:placetype":"venue"
},
  "geometry": {"coordinates":[5.5801558495,50.6474151611],"type":"Point"}
}