{
  "type": "Feature",
  "properties": {
    "iso:country":"BE",
    "sg:address":"Rue Des Quatre Maisons 262",
    "sg:city":"Chimay",
    "sg:orig_category":"Installation de menuiserie en bois and plastique",
    "sg:phone":"+32 60 21 47 10",
    "sg:postcode":"6464",
    "sg:province":"Hainaut",
    "wof:name":"Andre Auvray",
    "wof:placetype":"venue"
},
  "geometry": {"coordinates":[4.3209447861,50.0234336853],"type":"Point"}
}