{
  "type": "Feature",
  "properties": {
    "addr:full":"Luxemburgstraat 7 Box 9 Oostende West-Vlaanderen 8400",
    "addr:housenumber":"7;9",
    "addr:postcode":"8400",
    "addr:street":"Luxemburgstraat;Box",
    "iso:country":"BE",
    "sg:address":"Luxemburgstraat 7 Box 9",
    "sg:city":"Oostende",
    "sg:classifiers":[
        {
            "category":"Real Estate",
            "subcategory":"Architect",
            "type":"Services"
        }
    ],
    "sg:phone":"+32 59 51 30 58",
    "sg:postcode":"8400",
    "sg:province":"West-Vlaanderen",
    "wof:name":"Verborgh Johan Architectuurstudio Bvba",
    "wof:placetype":"venue"
},
  "geometry": {"coordinates":[2.888833046,51.2202262878],"type":"Point"}
}