{
  "type": "Feature",
  "properties": {
    "addr:full":"Goethestraat 3 Antwerpen Antwerpen 2050",
    "addr:housenumber":"3",
    "addr:postcode":"2050",
    "addr:street":"Goethestraat",
    "iso:country":"BE",
    "sg:address":"Goethestraat 3",
    "sg:city":"Antwerpen",
    "sg:orig_category":"Zalen voor culturele evenementen",
    "sg:phone":"+32 3 219 40 61",
    "sg:postcode":"2050",
    "sg:province":"Antwerpen",
    "wof:name":"Theater Gloriant",
    "wof:placetype":"venue"
},
  "geometry": {"coordinates":[4.3900690079,51.2313842773],"type":"Point"}
}