{
  "type": "Feature",
  "properties": {
    "iso:country":"BE",
    "sg:address":"Faliestraat 6",
    "sg:city":"Zottegem (sint-maria-oudenhove)",
    "sg:classifiers":[
        {
            "category":"Banks & Credit Unions",
            "subcategory":"Investment Brokerage",
            "type":"Services"
        }
    ],
    "sg:phone":"+32 9 360 18 06",
    "sg:postcode":"9620",
    "sg:province":"Oost-Vlaanderen",
    "sg:tags":[
        "repair",
        "-",
        "installation",
        "sanitary",
        "article"
    ],
    "wof:name":"Wattez F",
    "wof:placetype":"venue"
},
  "geometry": {"coordinates":[3.7978599072,50.8327636719],"type":"Point"}
}