{
  "type": "Feature",
  "properties": {
    "addr:full":"Marktstraat 53 Kortrijk (marke) West-Vlaanderen 8510",
    "addr:housenumber":"53",
    "addr:postcode":"8510",
    "addr:street":"Marktstraat",
    "iso:country":"BE",
    "sg:address":"Marktstraat 53",
    "sg:city":"Kortrijk (marke)",
    "sg:classifiers":[
        {
            "category":"Health Services",
            "subcategory":"Dentist",
            "type":"Services"
        }
    ],
    "sg:phone":"+32 56 21 26 83",
    "sg:postcode":"8510",
    "sg:province":"West-Vlaanderen",
    "wof:name":"Wyseur V\u00e9ronique",
    "wof:placetype":"venue"
},
  "geometry": {"coordinates":[3.234926939,50.8092956543],"type":"Point"}
}