{
  "type": "Feature",
  "properties": {
    "addr:full":"Rue Basse 24 Lessines (bois-de-lessines) Hainaut 7866",
    "addr:housenumber":"24",
    "addr:postcode":"7866",
    "addr:street":"Rue Basse",
    "iso:country":"BE",
    "sg:address":"Rue Basse 24",
    "sg:city":"Lessines (bois-de-lessines)",
    "sg:classifiers":[
        {
            "category":"Utilities",
            "subcategory":"Refuse",
            "type":"Services"
        }
    ],
    "sg:phone":"+32 2 466 13 67",
    "sg:postcode":"7866",
    "sg:province":"Hainaut",
    "sg:tags":[
        "removal"
    ],
    "wof:name":"Minten",
    "wof:placetype":"venue"
},
  "geometry": {"coordinates":[3.9054219723,50.7045059204],"type":"Point"}
}