{
  "type": "Feature",
  "properties": {
    "iso:country":"BE",
    "sg:address":"Belseledorp 117 Box 1",
    "sg:city":"Sint-niklaas (belsele)",
    "sg:classifiers":[
        {
            "category":"Health Services",
            "subcategory":"Health Practitioner",
            "type":"Services"
        }
    ],
    "sg:phone":"+32 3 772 39 82",
    "sg:postcode":"9111",
    "sg:province":"Oost-Vlaanderen",
    "sg:tags":[
        "physiotherapist"
    ],
    "wof:name":"Baetens Evi",
    "wof:placetype":"venue"
},
  "geometry": {"coordinates":[4.0897397995,51.1463394165],"type":"Point"}
}