{
  "type": "Feature",
  "properties": {
    "addr:full":"Rue Pairois 10 Dour Hainaut 7370",
    "addr:housenumber":"10",
    "addr:postcode":"7370",
    "addr:street":"Rue Pairois;Hainaut",
    "iso:country":"BE",
    "sg:address":"Rue Pairois 10",
    "sg:city":"Dour",
    "sg:classifiers":[
        {
            "category":"Professional",
            "subcategory":"Lawyer & Legal Services",
            "type":"Services"
        }
    ],
    "sg:phone":"+32 65 65 28 65",
    "sg:postcode":"7370",
    "sg:province":"Hainaut",
    "wof:name":"Bronsart Y",
    "wof:placetype":"venue"
},
  "geometry": {"coordinates":[3.7806220055,50.3971061707],"type":"Point"}
}