{
  "type": "Feature",
  "properties": {
    "addr:full":"Antwerpsesteenweg 15 Kapellen Antwerpen 2950",
    "addr:housenumber":"15",
    "addr:postcode":"2950",
    "addr:street":"Antwerpsesteenweg",
    "iso:country":"BE",
    "sg:address":"Antwerpsesteenweg 15",
    "sg:city":"Kapellen",
    "sg:orig_category":"Mobistar Centres. Mat\u00e9riel de T\u00e9l\u00e9communication",
    "sg:phone":"+32 3 605 41 41",
    "sg:postcode":"2950",
    "sg:province":"Antwerpen",
    "wof:name":"Mobistar Center A.m.s.",
    "wof:placetype":"venue"
},
  "geometry": {"coordinates":[4.4293050766,51.31407547],"type":"Point"}
}