{
  "type": "Feature",
  "properties": {
    "iso:country":"BE",
    "sg:address":"Rue Des Trieux 21",
    "sg:city":"Cerfontaine (daussois)",
    "sg:classifiers":[
        {
            "category":"Parking",
            "subcategory":"Garage",
            "type":"Transportation"
        }
    ],
    "sg:phone":"+32 71 61 14 11",
    "sg:postcode":"5630",
    "sg:province":"Namur",
    "sg:tags":[
        "truck",
        "-",
        "dump",
        "transport"
    ],
    "wof:name":"Delforge Ch",
    "wof:placetype":"venue"
},
  "geometry": {"coordinates":[4.4586629868,50.2192420959],"type":"Point"}
}