{
  "type": "Feature",
  "properties": {
    "iso:country":"BE",
    "sg:address":"Stationsstraat 81",
    "sg:city":"Geel",
    "sg:classifiers":[
        {
            "category":"Cinema",
            "subcategory":"Movie Rental",
            "type":"Entertainment"
        }
    ],
    "sg:phone":"+32 14 59 37 79",
    "sg:postcode":"2440",
    "sg:province":"Antwerpen",
    "sg:tags":[
        "de",
        "cassette",
        "location",
        "vid\u00e9o",
        "audio"
    ],
    "wof:name":"Beverly Hills",
    "wof:placetype":"venue"
},
  "geometry": {"coordinates":[4.98954916,51.1657180786],"type":"Point"}
}