{
  "type": "Feature",
  "properties": {
    "addr:full":"Waterloolaan 57b Brussel/bruxelles Bruxelles-Capitale 1000",
    "addr:housenumber":"57b",
    "addr:postcode":"1000",
    "addr:street":"Waterloolaan;/",
    "iso:country":"BE",
    "sg:address":"Waterloolaan 57b",
    "sg:city":"Brussel/bruxelles",
    "sg:orig_category":"Herstelling horloges and juwelen Juwelen and horloges",
    "sg:phone":"+32 2 513 49 44",
    "sg:postcode":"1000",
    "sg:province":"Bruxelles-Capitale",
    "wof:name":"M. Lascar",
    "wof:placetype":"venue"
},
  "geometry": {"coordinates":[4.3559970856,50.8366355896],"type":"Point"}
}