{
  "type": "Feature",
  "properties": {
    "addr:full":"J. Vanzeerstraat 81 Diest Vlaams-Brabant 3290",
    "addr:housenumber":"81",
    "addr:postcode":"3290",
    "addr:street":"J. Vanzeerstraat",
    "iso:country":"BE",
    "sg:address":"J. Vanzeerstraat 81",
    "sg:city":"Diest",
    "sg:classifiers":[
        {
            "category":"Insurance",
            "subcategory":"Insurance Agent",
            "type":"Services"
        }
    ],
    "sg:phone":"+32 13 66 13 81",
    "sg:postcode":"3290",
    "sg:province":"Vlaams-Brabant",
    "sg:tags":[
        "verzekeringsmakelaars",
        "expert"
    ],
    "wof:name":"Zakenkantoor Beckers",
    "wof:placetype":"venue"
},
  "geometry": {"coordinates":[5.0949931145,51.0381698608],"type":"Point"}
}