{
  "type": "Feature",
  "properties": {
    "iso:country":"BE",
    "sg:address":"Brandestraat 6 Box 1",
    "sg:city":"Lier (koningshooikt)",
    "sg:classifiers":[
        {
            "category":"Shopping",
            "subcategory":"Florist",
            "type":"Retail Goods"
        }
    ],
    "sg:phone":"+32 3 422 56 46",
    "sg:postcode":"2500",
    "sg:province":"Antwerpen",
    "wof:name":"Golie Bloemen & Planten Bvba",
    "wof:placetype":"venue"
},
  "geometry": {"coordinates":[4.6337032318,51.0886497498],"type":"Point"}
}