{
  "type": "Feature",
  "properties": {
    "addr:full":"Rue De Stambruges 32 Beloeil Hainaut 7972",
    "addr:housenumber":"32",
    "addr:postcode":"7972",
    "addr:street":"Rue De Stambruges",
    "iso:country":"BE",
    "sg:address":"Rue De Stambruges 32",
    "sg:city":"Beloeil",
    "sg:orig_category":"Alternatieve geneeskunde",
    "sg:phone":"+32 69 57 62 68",
    "sg:postcode":"7972",
    "sg:province":"Hainaut",
    "wof:name":"Simon Moiny",
    "wof:placetype":"venue"
},
  "geometry": {"coordinates":[3.6921050549,50.5274238586],"type":"Point"}
}