{
  "type": "Feature",
  "properties": {
    "iso:country":"BE",
    "sg:address":"Route D'etalle 114",
    "sg:city":"Arlon",
    "sg:orig_category":"Produits chimiques Gr",
    "sg:phone":"+32 63 23 73 88",
    "sg:postcode":"6700",
    "sg:province":"Luxembourg",
    "wof:name":"Schmit-contor",
    "wof:placetype":"venue"
},
  "geometry": {"coordinates":[5.7107458115,49.6818466187],"type":"Point"}
}