{
  "type": "Feature",
  "properties": {
    "iso:country":"BE",
    "sg:address":"Kapitein Piretlaan 36",
    "sg:city":"Sint-pieters-woluwe/woluwe-saint-pierre",
    "sg:classifiers":[
        {
            "category":"Cafe",
            "type":"Food & Drink"
        }
    ],
    "sg:phone":"+32 2 762 12 40",
    "sg:postcode":"1150",
    "sg:province":"Bruxelles-Capitale",
    "sg:tags":[
        "caf\u00e9s"
    ],
    "wof:name":"Marc Jambers",
    "wof:placetype":"venue"
},
  "geometry": {"coordinates":[4.4216480255,50.837928772],"type":"Point"}
}