{
  "type": "Feature",
  "properties": {
    "iso:country":"BE",
    "sg:address":"Am Wolfshof 11",
    "sg:city":"Eupen (kettenis)",
    "sg:classifiers":[
        {
            "category":"Airport",
            "subcategory":"International",
            "type":"Transportation"
        }
    ],
    "sg:phone":"+32 87 74 03 59",
    "sg:postcode":"4701",
    "sg:province":"Li\u00e8ge",
    "sg:tags":[
        "-",
        "transport"
    ],
    "wof:name":"Kubben Cormann G Sprl",
    "wof:placetype":"venue"
},
  "geometry": {"coordinates":[6.0461649895,50.6460838318],"type":"Point"}
}