{
  "type": "Feature",
  "properties": {
    "iso:country":"BE",
    "sg:address":"Vijfhoek 14",
    "sg:city":"Mechelen",
    "sg:orig_category":"Apotheken",
    "sg:phone":"+32 15 41 16 97",
    "sg:postcode":"2800",
    "sg:province":"Antwerpen",
    "wof:name":"Apotheek Beele",
    "wof:placetype":"venue"
},
  "geometry": {"coordinates":[4.48204422,51.0225563049],"type":"Point"}
}