{
  "type": "Feature",
  "properties": {
    "iso:country":"BE",
    "sg:address":"Boulevard Heynen 16",
    "sg:city":"Bouillon",
    "sg:classifiers":[
        {
            "category":"Social Services",
            "type":"Services"
        }
    ],
    "sg:phone":"+32 61 46 69 53",
    "sg:postcode":"6830",
    "sg:province":"Luxembourg",
    "wof:name":"Source (la) Maison Des Enfants Asbl",
    "wof:placetype":"venue"
},
  "geometry": {"coordinates":[5.0699400902,49.7964706421],"type":"Point"}
}