{
  "type": "Feature",
  "properties": {
    "addr:full":"Rue Gilles-galler 22-24 Li\u00e8ge Li\u00e8ge 4000",
    "addr:postcode":"22-24;4000",
    "addr:street":"Rue Gilles-Galler",
    "iso:country":"BE",
    "sg:address":"Rue Gilles-galler 22-24",
    "sg:city":"Li\u00e8ge",
    "sg:classifiers":[
        {
            "category":"Government",
            "subcategory":"Police Station",
            "type":"Public Place"
        }
    ],
    "sg:phone":"+32 4 233 79 55",
    "sg:postcode":"4000",
    "sg:province":"Li\u00e8ge",
    "sg:tags":[
        "anodizing"
    ],
    "wof:name":"La Nitruration Moderne S.a.",
    "wof:placetype":"venue"
},
  "geometry": {"coordinates":[5.5672779083,50.6397857666],"type":"Point"}
}