{
  "type": "Feature",
  "properties": {
    "addr:full":"Boulevard Louis Schmidt 4 Bruxelles (etterbeek) Bruxelles-Capitale 1040",
    "addr:housenumber":"4",
    "addr:postcode":"1040",
    "addr:street":"Boulevard Louis Schmidt",
    "iso:country":"BE",
    "sg:address":"Boulevard Louis Schmidt 4",
    "sg:city":"Bruxelles (etterbeek)",
    "sg:classifiers":[
        {
            "category":"Health Services",
            "subcategory":"Doctor",
            "type":"Services"
        }
    ],
    "sg:phone":"+32 2 733 92 15",
    "sg:postcode":"1040",
    "sg:province":"Bruxelles-Capitale",
    "sg:tags":[
        "medicinephysicians",
        "surgeon"
    ],
    "wof:name":"Legrain Ph - Mediophta",
    "wof:placetype":"venue"
},
  "geometry": {"coordinates":[4.3991999626,50.8275909424],"type":"Point"}
}