{
  "type": "Feature",
  "properties": {
    "addr:full":"Molenhoekstraat 2 Mol Antwerpen 2400",
    "addr:housenumber":"2",
    "addr:postcode":"2400",
    "addr:street":"Molenhoekstraat",
    "iso:country":"BE",
    "sg:address":"Molenhoekstraat 2",
    "sg:city":"Mol",
    "sg:classifiers":[
        {
            "category":"Bars & Pubs",
            "type":"Food & Drink"
        }
    ],
    "sg:phone":"+32 14 32 47 77",
    "sg:postcode":"2400",
    "sg:province":"Antwerpen",
    "wof:name":"Passage (de)",
    "wof:placetype":"venue"
},
  "geometry": {"coordinates":[5.1208891869,51.1873321533],"type":"Point"}
}