{
  "type": "Feature",
  "properties": {
    "iso:country":"BE",
    "sg:address":"Berchemstraat 20",
    "sg:city":"Dilbeek",
    "sg:classifiers":[
        {
            "category":"Insurance",
            "subcategory":"Life Insurance",
            "type":"Services"
        }
    ],
    "sg:phone":"+32 2 568 08 68",
    "sg:postcode":"1700",
    "sg:province":"Vlaams-Brabant",
    "sg:tags":[
        "assurance"
    ],
    "wof:name":"Optima Insurance Group",
    "wof:placetype":"venue"
},
  "geometry": {"coordinates":[4.2670068741,50.8453483582],"type":"Point"}
}