{
  "type": "Feature",
  "properties": {
    "addr:full":"Ieperweg 135 Roeselare West-Vlaanderen 8800",
    "addr:housenumber":"135",
    "addr:postcode":"8800",
    "iso:country":"BE",
    "sg:address":"Ieperweg 135",
    "sg:city":"Roeselare",
    "sg:orig_category":"Groententeelt",
    "sg:phone":"+32 51 20 07 57",
    "sg:postcode":"8800",
    "sg:province":"West-Vlaanderen",
    "wof:name":"Marcel Fraeye",
    "wof:placetype":"venue"
},
  "geometry": {"coordinates":[3.1185309887,50.9408683777],"type":"Point"}
}