{
  "type": "Feature",
  "properties": {
    "iso:country":"BE",
    "sg:address":"Diestsestraat 41a",
    "sg:city":"Kortenaken",
    "sg:classifiers":[
        {
            "category":"Health Services",
            "subcategory":"Dentist",
            "type":"Services"
        }
    ],
    "sg:phone":"+32 11 58 84 75",
    "sg:postcode":"3470",
    "sg:province":"Vlaams-Brabant",
    "wof:name":"Van De Velde Katrien",
    "wof:placetype":"venue"
},
  "geometry": {"coordinates":[5.0619769096,50.9126586914],"type":"Point"}
}