{
  "type": "Feature",
  "properties": {
    "addr:full":"Sint-elooistraat 74 Lochristi Oost-Vlaanderen 9080",
    "addr:housenumber":"74",
    "addr:postcode":"9080",
    "addr:street":"Sint-Elooistraat",
    "iso:country":"BE",
    "sg:address":"Sint-elooistraat 74",
    "sg:city":"Lochristi",
    "sg:classifiers":[
        {
            "category":"Autos & Motor Vehicles",
            "subcategory":"Fuel & Gas Station",
            "type":"Retail Goods"
        }
    ],
    "sg:phone":"+32 9 355 13 10",
    "sg:postcode":"9080",
    "sg:province":"Oost-Vlaanderen",
    "sg:tags":[
        "stations-service",
        "carburants"
    ],
    "wof:name":"Peter Maebe",
    "wof:placetype":"venue"
},
  "geometry": {"coordinates":[3.8973491192,51.1024932861],"type":"Point"}
}