{
  "type": "Feature",
  "properties": {
    "iso:country":"BE",
    "sg:address":"Rue G\u00e9n\u00e9ral Lotz 38",
    "sg:city":"Bruxelles (uccle)",
    "sg:classifiers":[
        {
            "category":"Health Services",
            "subcategory":"Dentist",
            "type":"Services"
        }
    ],
    "sg:phone":"+32 2 346 01 02",
    "sg:postcode":"1180",
    "sg:province":"Bruxelles-Capitale",
    "wof:name":"Lauwerys Catherine",
    "wof:placetype":"venue"
},
  "geometry": {"coordinates":[4.3583431244,50.8140602112],"type":"Point"}
}