{
  "type": "Feature",
  "properties": {
    "iso:country":"BE",
    "sg:address":"Hazewindstraat 71",
    "sg:city":"Deerlijk",
    "sg:classifiers":[
        {
            "category":"Manufacturing",
            "subcategory":"Textiles",
            "type":"Manufacturing & Wholesale Goods"
        }
    ],
    "sg:phone":"+32 56 73 56 73",
    "sg:postcode":"8540",
    "sg:province":"West-Vlaanderen",
    "sg:tags":[
        "machinery"
    ],
    "wof:name":"Dewaele Textielmachines Nv",
    "wof:placetype":"venue"
},
  "geometry": {"coordinates":[3.364948988,50.8544006348],"type":"Point"}
}