{
  "type": "Feature",
  "properties": {
    "addr:full":"Rue Marie-henriette 68 Verviers Li\u00e8ge 4800",
    "addr:housenumber":"68",
    "addr:postcode":"4800",
    "addr:street":"Rue Marie-Henriette",
    "iso:country":"BE",
    "sg:address":"Rue Marie-henriette 68",
    "sg:city":"Verviers",
    "sg:classifiers":[
        {
            "category":"Bakery",
            "type":"Food & Drink"
        }
    ],
    "sg:phone":"+32 87 34 01 76",
    "sg:postcode":"4800",
    "sg:province":"Li\u00e8ge",
    "sg:tags":[
        "confectioner",
        "baker"
    ],
    "wof:name":"Dethioux Fres Sprl",
    "wof:placetype":"venue"
},
  "geometry": {"coordinates":[5.8744568825,50.5979804993],"type":"Point"}
}