{
  "type": "Feature",
  "properties": {
    "addr:full":"Roodebeeksteenweg 51 Sint-lambrechts-woluwe/saint-gilles Bruxelles-Capitale 1060",
    "addr:housenumber":"51",
    "addr:postcode":"1060",
    "addr:street":"Roodebeeksteenweg",
    "iso:country":"BE",
    "sg:address":"Roodebeeksteenweg 51",
    "sg:city":"Sint-lambrechts-woluwe/saint-gilles",
    "sg:orig_category":"HERSTELLING ELEKTRISCHE HUISHOUDAPPARATEN Huishoudapparaten, televisies and radio's",
    "sg:phone":"+32 2 538 03 57",
    "sg:postcode":"1060",
    "sg:province":"Bruxelles-Capitale",
    "wof:name":"T\u00c9l\u00c9 Du Parc",
    "wof:placetype":"venue"
},
  "geometry": {"coordinates":[4.3453397751,50.8265914917],"type":"Point"}
}