{
  "type": "Feature",
  "properties": {
    "addr:full":"Kapellestraat 90 Oostende West-Vlaanderen 8400",
    "addr:housenumber":"90",
    "addr:postcode":"8400",
    "addr:street":"Kapellestraat",
    "iso:country":"BE",
    "sg:address":"Kapellestraat 90",
    "sg:city":"Oostende",
    "sg:orig_category":"RESTAURANTS: H\u00d4TELS",
    "sg:phone":"+32 59 70 15 52",
    "sg:postcode":"8400",
    "sg:province":"West-Vlaanderen",
    "wof:name":"Burlington",
    "wof:placetype":"venue"
},
  "geometry": {"coordinates":[2.9210309982,51.2281455994],"type":"Point"}
}