{
  "type": "Feature",
  "properties": {
    "iso:country":"BE",
    "sg:address":"Koningsstoel 40",
    "sg:city":"Brecht",
    "sg:classifiers":[
        {
            "category":"Building & Trades",
            "subcategory":"Plumbing",
            "type":"Services"
        }
    ],
    "sg:phone":"+32 3 313 00 24",
    "sg:postcode":"2960",
    "sg:province":"Antwerpen",
    "sg:tags":[
        "repair",
        "mainten",
        "-",
        "central",
        "heating"
    ],
    "wof:name":"Lauryssen Service",
    "wof:placetype":"venue"
},
  "geometry": {"coordinates":[4.6415200233,51.3512115479],"type":"Point"}
}