{
  "type": "Feature",
  "properties": {
    "addr:full":"Rue De Lodelinsart 91 Charleroi Hainaut 6061",
    "addr:housenumber":"91",
    "addr:postcode":"6061",
    "addr:street":"Rue De Lodelinsart;Hainaut",
    "iso:country":"BE",
    "sg:address":"Rue De Lodelinsart 91",
    "sg:city":"Charleroi",
    "sg:orig_category":"Slagers",
    "sg:phone":"+32 71 41 30 16",
    "sg:postcode":"6061",
    "sg:province":"Hainaut",
    "wof:name":"Boucherie Romain",
    "wof:placetype":"venue"
},
  "geometry": {"coordinates":[4.4659528732,50.4142036438],"type":"Point"}
}