{
  "type": "Feature",
  "properties": {
    "addr:full":"2290 Vorselaar Antwerpen 2290",
    "addr:housenumber":"2290",
    "addr:postcode":"2290",
    "addr:street":"Vorselaar Antwerpen",
    "iso:country":"BE",
    "sg:address":"2290",
    "sg:city":"Vorselaar",
    "sg:orig_category":"Pharmaciens",
    "sg:phone":"+32 900 10 500",
    "sg:postcode":"2290",
    "sg:province":"Antwerpen",
    "wof:name":"Pharmacies De Garde",
    "wof:placetype":"venue"
},
  "geometry": {"coordinates":[4.7724981308,51.2003707886],"type":"Point"}
}