{
  "type": "Feature",
  "properties": {
    "addr:full":"Grote Markt 32-33 Mechelen Antwerpen 2800",
    "addr:postcode":"32-33;2800",
    "addr:street":"Grote Markt",
    "iso:country":"BE",
    "sg:address":"Grote Markt 32-33",
    "sg:city":"Mechelen",
    "sg:classifiers":[
        {
            "category":"Restaurant",
            "type":"Food & Drink"
        }
    ],
    "sg:phone":"+32 15 20 97 06",
    "sg:postcode":"2800",
    "sg:province":"Antwerpen",
    "wof:name":"Brasserie Den Beer",
    "wof:placetype":"venue"
},
  "geometry": {"coordinates":[4.4801869392,51.0277175903],"type":"Point"}
}