{
  "type": "Feature",
  "properties": {
    "addr:full":"Place D'obourg 1 Mons (obourg) Hainaut 7034",
    "addr:housenumber":"1",
    "addr:postcode":"7034",
    "addr:street":"Place D'Obourg",
    "iso:country":"BE",
    "sg:address":"Place D'obourg 1",
    "sg:city":"Mons (obourg)",
    "sg:classifiers":[
        {
            "category":"Shopping",
            "subcategory":"Computers & Home Electronics",
            "type":"Retail Goods"
        }
    ],
    "sg:phone":"+32 65 33 88 12",
    "sg:postcode":"7034",
    "sg:province":"Hainaut",
    "sg:tags":[
        "-",
        "television",
        "radio"
    ],
    "wof:name":"Riviere Francis Ets",
    "wof:placetype":"venue"
},
  "geometry": {"coordinates":[4.0080828667,50.4737472534],"type":"Point"}
}