{
  "type": "Feature",
  "properties": {
    "addr:full":"Pr\u00e9 D'alvaux 18 Namur (bouge) Namur 5004",
    "addr:housenumber":"18",
    "addr:postcode":"5004",
    "addr:street":"Pre\u0301 D'Alvaux",
    "iso:country":"BE",
    "sg:address":"Pr\u00e9 D'alvaux 18",
    "sg:city":"Namur (bouge)",
    "sg:classifiers":[
        {
            "category":"Professional",
            "subcategory":"Engineering",
            "type":"Services"
        }
    ],
    "sg:phone":"+32 81 21 57 37",
    "sg:postcode":"5004",
    "sg:province":"Namur",
    "sg:tags":[
        "technical",
        "equipment",
        "offices-"
    ],
    "wof:name":"Technogaz",
    "wof:placetype":"venue"
},
  "geometry": {"coordinates":[4.8884220123,50.4730644226],"type":"Point"}
}