{
  "type": "Feature",
  "properties": {
    "iso:country":"BE",
    "sg:address":"Lozijde 11",
    "sg:city":"Lille",
    "sg:orig_category":"Installation de menuiserie en bois and plastique",
    "sg:phone":"+32 14 55 18 28",
    "sg:postcode":"2275",
    "sg:province":"Antwerpen",
    "wof:name":"Marc Tops",
    "wof:placetype":"venue"
},
  "geometry": {"coordinates":[4.8741159439,51.2726287842],"type":"Point"}
}