{
  "type": "Feature",
  "properties": {
    "addr:full":"Baron Romain Moyersoen Park 16a Aalst Oost-Vlaanderen 9300",
    "addr:housenumber":"16a",
    "addr:postcode":"9300",
    "addr:street":"Baron Romain Moyersoen Park",
    "iso:country":"BE",
    "sg:address":"Baron Romain Moyersoen Park 16a",
    "sg:city":"Aalst",
    "sg:classifiers":[
        {
            "category":"Health Services",
            "subcategory":"Doctor",
            "type":"Services"
        }
    ],
    "sg:phone":"+32 53 70 49 53",
    "sg:postcode":"9300",
    "sg:province":"Oost-Vlaanderen",
    "sg:tags":[
        "medicinephysicians",
        "surgeon"
    ],
    "wof:name":"De Cordier Eric",
    "wof:placetype":"venue"
},
  "geometry": {"coordinates":[4.0567879677,50.9362678528],"type":"Point"}
}