{
  "type": "Feature",
  "properties": {
    "iso:country":"BE",
    "sg:address":"Rue Emile-parfonry 22",
    "sg:city":"Hotton",
    "sg:orig_category":"Banques and organismes de cr\u00e9dit",
    "sg:phone":"+32 84 46 63 19",
    "sg:postcode":"6990",
    "sg:province":"Luxembourg",
    "wof:name":"Fortis",
    "wof:placetype":"venue"
},
  "geometry": {"coordinates":[5.445335865,50.2672920227],"type":"Point"}
}