{
  "type": "Feature",
  "properties": {
    "iso:country":"BE",
    "sg:address":"Rue De L'ecole 27b",
    "sg:city":"Rhode-saint-gen\u00e8se",
    "sg:classifiers":[
        {
            "category":"Building & Trades",
            "subcategory":"Landscaping Services",
            "type":"Services"
        }
    ],
    "sg:phone":"+32 2 358 17 43",
    "sg:postcode":"1640",
    "sg:province":"Vlaams-Brabant",
    "sg:tags":[
        "gardening",
        "garden",
        "maintenance"
    ],
    "wof:name":"Jardins N",
    "wof:placetype":"venue"
},
  "geometry": {"coordinates":[4.3441500664,50.7446784973],"type":"Point"}
}