{
  "type": "Feature",
  "properties": {
    "iso:country":"BE",
    "sg:address":"Wurfeldermolenweg 49",
    "sg:city":"Maaseik",
    "sg:orig_category":"Rundveehouders",
    "sg:phone":"+32 89 56 46 59",
    "sg:postcode":"3680",
    "sg:province":"Limburg",
    "wof:name":"Joannes Vermeulen",
    "wof:placetype":"venue"
},
  "geometry": {"coordinates":[5.753387928,51.0930023193],"type":"Point"}
}