{
  "type": "Feature",
  "properties": {
    "addr:full":"Avenue Marie-louise 59 Waterloo Brabant Wallon 1410",
    "addr:housenumber":"59",
    "addr:postcode":"1410",
    "addr:street":"Avenue Marie-Louise",
    "iso:country":"BE",
    "sg:address":"Avenue Marie-louise 59",
    "sg:city":"Waterloo",
    "sg:classifiers":[
        {
            "category":"Real Estate",
            "subcategory":"Surveying",
            "type":"Services"
        }
    ],
    "sg:phone":"+32 2 351 65 50",
    "sg:postcode":"1410",
    "sg:province":"Brabant Wallon",
    "sg:tags":[
        "surveyor",
        "land"
    ],
    "wof:name":"Dambly O",
    "wof:placetype":"venue"
},
  "geometry": {"coordinates":[4.4033331871,50.7199630737],"type":"Point"}
}