{
  "type": "Feature",
  "properties": {
    "addr:full":"Avenue Eug\u00e8ne Demolder 57 Bruxelles (schaerbeek) Bruxelles-Capitale 1030",
    "addr:housenumber":"57",
    "addr:postcode":"1030",
    "addr:street":"Avenue Euge\u0300Ne Demolder",
    "iso:country":"BE",
    "sg:address":"Avenue Eug\u00e8ne Demolder 57",
    "sg:city":"Bruxelles (schaerbeek)",
    "sg:classifiers":[
        {
            "category":"Communications",
            "subcategory":"Film & Video Production",
            "type":"Services"
        }
    ],
    "sg:phone":"+32 2 245 64 50",
    "sg:postcode":"1030",
    "sg:province":"Bruxelles-Capitale",
    "sg:tags":[
        "producer",
        "realizators"
    ],
    "wof:name":"Key Line Film Sa",
    "wof:placetype":"venue"
},
  "geometry": {"coordinates":[4.3787169456,50.8720474243],"type":"Point"}
}