{
  "type": "Feature",
  "properties": {
    "addr:full":"Square Kennedy 8 Ciney Namur 5590",
    "addr:housenumber":"8",
    "addr:postcode":"5590",
    "addr:street":"Square Kennedy",
    "iso:country":"BE",
    "sg:address":"Square Kennedy 8",
    "sg:city":"Ciney",
    "sg:orig_category":"Sportclubs Sportterreinen and installaties behalve sportcentra",
    "sg:phone":"+32 83 21 20 13",
    "sg:postcode":"5590",
    "sg:province":"Namur",
    "wof:name":"R.u. Wallonne Ciney",
    "wof:placetype":"venue"
},
  "geometry": {"coordinates":[5.1095957756,50.2974967957],"type":"Point"}
}