{
  "type": "Feature",
  "properties": {
    "addr:full":"Oppuurseweg 7 Sint-amands Antwerpen 2890",
    "addr:housenumber":"7",
    "addr:postcode":"2890",
    "addr:street":"Oppuurseweg",
    "iso:country":"BE",
    "sg:address":"Oppuurseweg 7",
    "sg:city":"Sint-amands",
    "sg:orig_category":"Pain, p\u00e2tisseries and confiseries",
    "sg:phone":"+32 52 33 32 65",
    "sg:postcode":"2890",
    "sg:province":"Antwerpen",
    "wof:name":"Antoon Caluwaerts",
    "wof:placetype":"venue"
},
  "geometry": {"coordinates":[4.2541680336,51.0470123291],"type":"Point"}
}