{
  "type": "Feature",
  "properties": {
    "iso:country":"BE",
    "sg:address":"Leopoldstraat 85",
    "sg:city":"Mechelen",
    "sg:orig_category":"Immobili\u00ebnkantoren",
    "sg:phone":"+32 15 43 28 08",
    "sg:postcode":"2800",
    "sg:province":"Antwerpen",
    "wof:name":"De Vos C. & Partners",
    "wof:placetype":"venue"
},
  "geometry": {"coordinates":[4.4804258347,51.0188179016],"type":"Point"}
}