{
  "type": "Feature",
  "properties": {
    "addr:full":"Beekstraat 6 Londerzeel (malderen) Vlaams-Brabant 1840",
    "addr:housenumber":"6",
    "addr:postcode":"1840",
    "addr:street":"Beekstraat",
    "iso:country":"BE",
    "sg:address":"Beekstraat 6",
    "sg:city":"Londerzeel (malderen)",
    "sg:classifiers":[
        {
            "category":"Arts & Performance",
            "subcategory":"Music",
            "type":"Entertainment"
        }
    ],
    "sg:phone":"+32 476 66 82 78",
    "sg:postcode":"1840",
    "sg:province":"Vlaams-Brabant",
    "sg:tags":[
        "disc-jockeys"
    ],
    "wof:name":"D.j. @ Work",
    "wof:placetype":"venue"
},
  "geometry": {"coordinates":[4.2573041916,51.0097427368],"type":"Point"}
}