{
  "type": "Feature",
  "properties": {
    "iso:country":"BE",
    "sg:address":"Rue Du Beau-site 35",
    "sg:city":"Messancy",
    "sg:orig_category":"Installation \u00e9lectrique r\u00e9sidentielle. Rev\u00eatements pour sols and murs",
    "sg:phone":"+32 63 38 77 21",
    "sg:postcode":"6780",
    "sg:province":"Luxembourg",
    "wof:name":"Pol Henrion",
    "wof:placetype":"venue"
},
  "geometry": {"coordinates":[5.827009201,49.5950813293],"type":"Point"}
}