{
  "type": "Feature",
  "properties": {
    "iso:country":"BE",
    "sg:address":"Leiegoeddreef 15",
    "sg:city":"Waregem",
    "sg:orig_category":"Varkenskwekers",
    "sg:phone":"+32 56 60 21 38",
    "sg:postcode":"8793",
    "sg:province":"West-Vlaanderen",
    "wof:name":"Raphael Van Themsche",
    "wof:placetype":"venue"
},
  "geometry": {"coordinates":[3.3825349808,50.8998260498],"type":"Point"}
}