{
  "type": "Feature",
  "properties": {
    "addr:full":"Senator A.jeunissenlaan 1007 Zonhoven Limburg 3520",
    "addr:postcode":"1007 zonhoven;3520",
    "addr:street":"A.Jeunissenlaan",
    "iso:country":"BE",
    "sg:address":"Senator A.jeunissenlaan 1007",
    "sg:city":"Zonhoven",
    "sg:orig_category":"Traitement and rev\u00eatement des m\u00e9taux",
    "sg:phone":"+32 11 81 36 00",
    "sg:postcode":"3520",
    "sg:province":"Limburg",
    "wof:name":"Fraiponts",
    "wof:placetype":"venue"
},
  "geometry": {"coordinates":[5.3818049431,50.997882843],"type":"Point"}
}