{
  "type": "Feature",
  "properties": {
    "iso:country":"BE",
    "sg:address":"Collegelaan 30",
    "sg:city":"Genk",
    "sg:classifiers":[
        {
            "category":"Education",
            "subcategory":"School",
            "type":"Public Place"
        }
    ],
    "sg:phone":"+32 89 35 22 30",
    "sg:postcode":"3600",
    "sg:province":"Limburg",
    "sg:tags":[
        "boarding"
    ],
    "wof:name":"Onze Lieve Vrouw Lyceum Vzw",
    "wof:placetype":"venue"
},
  "geometry": {"coordinates":[5.5172281265,50.9780311584],"type":"Point"}
}