{
  "type": "Feature",
  "properties": {
    "addr:full":"Pastorijlaan 14 Wijnegem Antwerpen 2110",
    "addr:housenumber":"14",
    "addr:postcode":"2110",
    "addr:street":"Pastorijlaan",
    "iso:country":"BE",
    "sg:address":"Pastorijlaan 14",
    "sg:city":"Wijnegem",
    "sg:classifiers":[
        {
            "category":"Professional",
            "subcategory":"Engineering",
            "type":"Services"
        }
    ],
    "sg:phone":"+32 3 353 76 35",
    "sg:postcode":"2110",
    "sg:province":"Antwerpen",
    "sg:tags":[
        "-"
    ],
    "wof:name":"Rusewij Nv",
    "wof:placetype":"venue"
},
  "geometry": {"coordinates":[4.5260238647,51.2270507812],"type":"Point"}
}