{
  "type": "Feature",
  "properties": {
    "addr:full":"Rue Martin Morimont 20 Ciney Namur 5590",
    "addr:housenumber":"20",
    "addr:postcode":"5590",
    "addr:street":"Rue Martin Morimont",
    "iso:country":"BE",
    "sg:address":"Rue Martin Morimont 20",
    "sg:city":"Ciney",
    "sg:orig_category":"Sportclubs",
    "sg:phone":"+32 83 21 30 06",
    "sg:postcode":"5590",
    "sg:province":"Namur",
    "wof:name":"Gym Club La Gaillarde",
    "wof:placetype":"venue"
},
  "geometry": {"coordinates":[5.0876708031,50.2888336182],"type":"Point"}
}