{
  "type": "Feature",
  "properties": {
    "iso:country":"BE",
    "sg:address":"Neeroetersesteenweg 44",
    "sg:city":"Kinrooi",
    "sg:classifiers":[
        {
            "category":"Travel",
            "subcategory":"Travel Agent",
            "type":"Entertainment"
        }
    ],
    "sg:phone":"+32 89 70 18 85",
    "sg:postcode":"3640",
    "sg:province":"Limburg",
    "sg:tags":[
        "agency"
    ],
    "wof:name":"Gazelle World Wave",
    "wof:placetype":"venue"
},
  "geometry": {"coordinates":[5.7404789925,51.1410255432],"type":"Point"}
}