{
  "type": "Feature",
  "properties": {
    "iso:country":"BE",
    "sg:address":"Keerkringenlaan 5b5",
    "sg:city":"Vorst/forest",
    "sg:orig_category":"Drukkerijen and copyshops",
    "sg:phone":"+32 2 343 40 07",
    "sg:postcode":"1190",
    "sg:province":"Bruxelles-Capitale",
    "wof:name":"Imprimerie Cloos Cauchie",
    "wof:placetype":"venue"
},
  "geometry": {"coordinates":[4.3260798454,50.8150367737],"type":"Point"}
}