{
  "type": "Feature",
  "properties": {
    "iso:country":"BE",
    "sg:address":"Tervuursesteenweg 135",
    "sg:city":"Bertem",
    "sg:orig_category":"Banken and kredietinstellingen",
    "sg:phone":"+32 16 49 09 14",
    "sg:postcode":"3060",
    "sg:province":"Vlaams-Brabant",
    "wof:name":"Fortis",
    "wof:placetype":"venue"
},
  "geometry": {"coordinates":[4.6301951408,50.8655853271],"type":"Point"}
}