{
  "type": "Feature",
  "properties": {
    "iso:country":"BE",
    "sg:address":"Berkenlaan 3",
    "sg:city":"Dendermonde",
    "sg:orig_category":"Agences de presse",
    "sg:phone":"+32 52 20 22 88",
    "sg:postcode":"9200",
    "sg:province":"Oost-Vlaanderen",
    "wof:name":"Erik Segers",
    "wof:placetype":"venue"
},
  "geometry": {"coordinates":[4.1131658554,51.0153427124],"type":"Point"}
}