{
  "type": "Feature",
  "properties": {
    "addr:full":"Ilgatlaan 11 Box 1 Hasselt Limburg 3500",
    "addr:housenumber":"11;1",
    "addr:postcode":"3500",
    "addr:street":"Ilgatlaan;Box",
    "iso:country":"BE",
    "sg:address":"Ilgatlaan 11 Box 1",
    "sg:city":"Hasselt",
    "sg:classifiers":[
        {
            "category":"Community Center",
            "type":"Public Place"
        }
    ],
    "sg:phone":"+32 11 28 68 30",
    "sg:postcode":"3500",
    "sg:province":"Limburg",
    "sg:tags":[
        "medical"
    ],
    "wof:name":"Ambulante Revalidatiecentra Voor Psychisch Mindervaliden",
    "wof:placetype":"venue"
},
  "geometry": {"coordinates":[5.3545150757,50.9223442078],"type":"Point"}
}