{
  "type": "Feature",
  "properties": {
    "addr:full":"Rue Du Croupet 90 Bassenge Li\u00e8ge 4690",
    "addr:housenumber":"90",
    "addr:postcode":"4690",
    "addr:street":"Rue Du Croupet",
    "iso:country":"BE",
    "sg:address":"Rue Du Croupet 90",
    "sg:city":"Bassenge",
    "sg:classifiers":[
        {
            "category":"Insurance",
            "subcategory":"Insurance Agent",
            "type":"Services"
        }
    ],
    "sg:phone":"+32 4 286 42 68",
    "sg:postcode":"4690",
    "sg:province":"Li\u00e8ge",
    "sg:tags":[
        "verzekeringsmakelaars",
        "expert"
    ],
    "wof:name":"Euro Geer-assurances 2000",
    "wof:placetype":"venue"
},
  "geometry": {"coordinates":[5.5778398514,50.7550315857],"type":"Point"}
}