{
  "type": "Feature",
  "properties": {
    "addr:full":"Ingelmunstersteenweg 153 Oostrozebeke West-Vlaanderen 8780",
    "addr:housenumber":"153",
    "addr:postcode":"8780",
    "addr:street":"Ingelmunstersteenweg",
    "iso:country":"BE",
    "sg:address":"Ingelmunstersteenweg 153",
    "sg:city":"Oostrozebeke",
    "sg:classifiers":[
        {
            "category":"Wholesale",
            "subcategory":"Meat",
            "type":"Manufacturing & Wholesale Goods"
        }
    ],
    "sg:phone":"+32 56 66 61 28",
    "sg:postcode":"8780",
    "sg:province":"West-Vlaanderen",
    "sg:tags":[
        "abattoir"
    ],
    "wof:name":"Dewulf J",
    "wof:placetype":"venue"
},
  "geometry": {"coordinates":[3.3108799458,50.9181976318],"type":"Point"}
}