{
  "type": "Feature",
  "properties": {
    "addr:full":"Berthelotstraat 61 Vorst/forest Bruxelles-Capitale 1190",
    "addr:housenumber":"61",
    "addr:postcode":"1190",
    "addr:street":"Berthelotstraat;/ Forest",
    "iso:country":"BE",
    "sg:address":"Berthelotstraat 61",
    "sg:city":"Vorst/forest",
    "sg:orig_category":"Advocaten and juridische adviseurs",
    "sg:phone":"+32 2 534 57 44",
    "sg:postcode":"1190",
    "sg:province":"Bruxelles-Capitale",
    "wof:name":"O. Lassoie",
    "wof:placetype":"venue"
},
  "geometry": {"coordinates":[4.3299608231,50.8254852295],"type":"Point"}
}