{
  "type": "Feature",
  "properties": {
    "addr:full":"Pioenstraat 5 Rijkevorsel Antwerpen 2310",
    "addr:housenumber":"5",
    "addr:postcode":"2310",
    "addr:street":"Pioenstraat",
    "iso:country":"BE",
    "sg:address":"Pioenstraat 5",
    "sg:city":"Rijkevorsel",
    "sg:orig_category":"V\u00e9hicules automobiles",
    "sg:phone":"+32 3 311 64 30",
    "sg:postcode":"2310",
    "sg:province":"Antwerpen",
    "wof:name":"Luc Van Geel",
    "wof:placetype":"venue"
},
  "geometry": {"coordinates":[4.7839488983,51.330329895],"type":"Point"}
}