{
  "type": "Feature",
  "properties": {
    "addr:full":"Oudergemselaan 243 Etterbeek Bruxelles-Capitale 1040",
    "addr:housenumber":"243",
    "addr:postcode":"1040",
    "addr:street":"Oudergemselaan",
    "iso:country":"BE",
    "sg:address":"Oudergemselaan 243",
    "sg:city":"Etterbeek",
    "sg:orig_category":"IJzerwaren, bouw- and verfmaterialen MEUBELONTWERP AND -INSTALLATIE",
    "sg:phone":"+32 2 649 55 31",
    "sg:postcode":"1040",
    "sg:province":"Bruxelles-Capitale",
    "wof:name":"Sani-kitchen-prestige",
    "wof:placetype":"venue"
},
  "geometry": {"coordinates":[4.3887720108,50.8330154419],"type":"Point"}
}