{
  "type": "Feature",
  "properties": {
    "iso:country":"BE",
    "sg:address":"Jozef Ii-straat 47",
    "sg:city":"Oostende",
    "sg:classifiers":[
        {
            "category":"Shopping",
            "subcategory":"Bicycles & Sporting Goods",
            "type":"Retail Goods"
        }
    ],
    "sg:phone":"+32 59 50 20 40",
    "sg:postcode":"8400",
    "sg:province":"West-Vlaanderen",
    "sg:tags":[
        "sport",
        "-"
    ],
    "wof:name":"Mario Sport",
    "wof:placetype":"venue"
},
  "geometry": {"coordinates":[2.9211080074,51.2290458679],"type":"Point"}
}