{
  "type": "Feature",
  "properties": {
    "addr:full":"Blijkheerstraat 63 Gooik Vlaams-Brabant 1755",
    "addr:housenumber":"63",
    "addr:postcode":"1755",
    "addr:street":"Blijkheerstraat",
    "iso:country":"BE",
    "sg:address":"Blijkheerstraat 63",
    "sg:city":"Gooik",
    "sg:orig_category":"Rundveehouders",
    "sg:phone":"+32 54 56 60 74",
    "sg:postcode":"1755",
    "sg:province":"Vlaams-Brabant",
    "wof:name":"Raf Borgenon",
    "wof:placetype":"venue"
},
  "geometry": {"coordinates":[4.04666996,50.7739486694],"type":"Point"}
}