{
  "type": "Feature",
  "properties": {
    "addr:full":"Heidestraat Noord 13 Kapellen Antwerpen 2950",
    "addr:housenumber":"13",
    "addr:postcode":"2950",
    "addr:street":"Heidestraat Noord",
    "iso:country":"BE",
    "sg:address":"Heidestraat Noord 13",
    "sg:city":"Kapellen",
    "sg:classifiers":[
        {
            "category":"Shopping",
            "subcategory":"Bicycles & Sporting Goods",
            "type":"Retail Goods"
        }
    ],
    "sg:postcode":"2950",
    "sg:province":"Antwerpen",
    "sg:tags":[
        "-"
    ],
    "wof:name":"Van De Brande",
    "wof:placetype":"venue"
},
  "geometry": {"coordinates":[4.4487628937,51.328918457],"type":"Point"}
}