{
  "type": "Feature",
  "properties": {
    "iso:country":"BE",
    "sg:address":"Langvennestraat 98",
    "sg:city":"Hasselt",
    "sg:orig_category":"Reisbureaus",
    "sg:phone":"+32 11 22 91 77",
    "sg:postcode":"3511",
    "sg:province":"Limburg",
    "wof:name":"De Witte Merel",
    "wof:placetype":"venue"
},
  "geometry": {"coordinates":[5.3119668961,50.9506835938],"type":"Point"}
}