{
  "type": "Feature",
  "properties": {
    "iso:country":"BE",
    "sg:address":"Rue Des Anglais 1",
    "sg:city":"Peruwelz",
    "sg:orig_category":"Slagers",
    "sg:phone":"+32 69 77 08 58",
    "sg:postcode":"7608",
    "sg:province":"Hainaut",
    "wof:name":"Dominique Vandrepotte",
    "wof:placetype":"venue"
},
  "geometry": {"coordinates":[3.5121970177,50.5018615723],"type":"Point"}
}