{
  "type": "Feature",
  "properties": {
    "addr:full":"Avenue Du Centenaire 61 Nivelles Brabant Wallon 1400",
    "addr:housenumber":"61",
    "addr:postcode":"1400",
    "addr:street":"Avenue Du Centenaire",
    "iso:country":"BE",
    "sg:address":"Avenue Du Centenaire 61",
    "sg:city":"Nivelles",
    "sg:classifiers":[
        {
            "category":"Utilities",
            "subcategory":"Mobile Phone",
            "type":"Services"
        }
    ],
    "sg:phone":"+32 67 84 30 69",
    "sg:postcode":"1400",
    "sg:province":"Brabant Wallon",
    "sg:tags":[
        "access",
        "gsm",
        "-",
        "apparatus"
    ],
    "wof:name":"2001 Informatique",
    "wof:placetype":"venue"
},
  "geometry": {"coordinates":[4.341345787,50.5964126587],"type":"Point"}
}