{
  "type": "Feature",
  "properties": {
    "addr:full":"Rue Du Mont 16 Mettet (biesme) Namur 5640",
    "addr:housenumber":"16",
    "addr:postcode":"5640",
    "addr:street":"Rue Du Mont;Biesme",
    "iso:country":"BE",
    "sg:address":"Rue Du Mont 16",
    "sg:city":"Mettet (biesme)",
    "sg:classifiers":[
        {
            "category":"Arts & Performance",
            "subcategory":"Music",
            "type":"Entertainment"
        }
    ],
    "sg:phone":"+32 71 72 92 44",
    "sg:postcode":"5640",
    "sg:province":"Namur",
    "sg:tags":[
        "disc-jockeys"
    ],
    "wof:name":"Live On Stage",
    "wof:placetype":"venue"
},
  "geometry": {"coordinates":[4.7478909492,50.3458824158],"type":"Point"}
}