{
  "type": "Feature",
  "properties": {
    "iso:country":"BE",
    "sg:address":"Suikerrui 25",
    "sg:city":"Antwerpen",
    "sg:classifiers":[
        {
            "category":"Restaurant",
            "type":"Food & Drink"
        }
    ],
    "sg:phone":"+32 3 233 62 30",
    "sg:postcode":"2000",
    "sg:province":"Antwerpen",
    "wof:name":"Fleur De Lys",
    "wof:placetype":"venue"
},
  "geometry": {"coordinates":[4.3984951973,51.2210044861],"type":"Point"}
}