{
  "type": "Feature",
  "properties": {
    "iso:country":"BE",
    "sg:address":"Stasegemdorp 14",
    "sg:city":"Harelbeke",
    "sg:classifiers":[
        {
            "category":"Cafe",
            "type":"Food & Drink"
        }
    ],
    "sg:phone":"+32 56 22 51 80",
    "sg:postcode":"8530",
    "sg:province":"West-Vlaanderen",
    "sg:tags":[
        "caf\u00e9s"
    ],
    "wof:name":"Caf\u00c9 De Gilde",
    "wof:placetype":"venue"
},
  "geometry": {"coordinates":[3.3146219254,50.8320503235],"type":"Point"}
}