{
  "type": "Feature",
  "properties": {
    "iso:country":"BE",
    "sg:address":"Acaciasstraat 45",
    "sg:city":"Kraainem",
    "sg:orig_category":"Computers and computerapparatuur Diverse informatica-activiteiten Informaticaconsulenten Onderhoud v",
    "sg:phone":"+32 2 731 98 58",
    "sg:postcode":"1950",
    "sg:province":"Vlaams-Brabant",
    "wof:name":"F.r. Electronic Systems",
    "wof:placetype":"venue"
},
  "geometry": {"coordinates":[4.4646959305,50.849773407],"type":"Point"}
}