{
  "type": "Feature",
  "properties": {
    "addr:full":"Plaats 22 Moorslede (dadizele) West-Vlaanderen 8890",
    "addr:housenumber":"22",
    "addr:postcode":"8890",
    "addr:street":"Plaats",
    "iso:country":"BE",
    "sg:address":"Plaats 22",
    "sg:city":"Moorslede (dadizele)",
    "sg:classifiers":[
        {
            "category":"Banks & Credit Unions",
            "subcategory":"Investment Brokerage",
            "type":"Services"
        }
    ],
    "sg:phone":"+32 56 50 16 83",
    "sg:postcode":"8890",
    "sg:province":"West-Vlaanderen",
    "sg:tags":[
        "jean",
        "casual",
        "wear"
    ],
    "wof:name":"Ro-time",
    "wof:placetype":"venue"
},
  "geometry": {"coordinates":[3.0969510078,50.8516693115],"type":"Point"}
}