{
  "type": "Feature",
  "properties": {
    "iso:country":"BE",
    "sg:address":"Kuilenstraat 49",
    "sg:city":"Genk",
    "sg:classifiers":[
        {
            "category":"Shopping",
            "subcategory":"Clothing, Apparel, & Fashions",
            "type":"Retail Goods"
        }
    ],
    "sg:phone":"+32 89 30 64 84",
    "sg:postcode":"3600",
    "sg:province":"Limburg",
    "sg:tags":[
        "ondergoed",
        "lingerie"
    ],
    "wof:name":"Lingerie Blanche",
    "wof:placetype":"venue"
},
  "geometry": {"coordinates":[5.4934267998,50.9713783264],"type":"Point"}
}