{
  "type": "Feature",
  "properties": {
    "addr:full":"Rue Lucien Nam\u00eache 42 Namur Namur 5000",
    "addr:housenumber":"42",
    "addr:postcode":"5000",
    "addr:street":"Rue Lucien Name\u0302Che",
    "iso:country":"BE",
    "sg:address":"Rue Lucien Nam\u00eache 42",
    "sg:city":"Namur",
    "sg:classifiers":[
        {
            "category":"Arena",
            "subcategory":"Sports Club",
            "type":"Entertainment"
        }
    ],
    "sg:phone":"+32 81 22 69 50",
    "sg:postcode":"5000",
    "sg:province":"Namur",
    "wof:name":"City Fitness",
    "wof:placetype":"venue"
},
  "geometry": {"coordinates":[4.8684968948,50.4679985046],"type":"Point"}
}