{
  "type": "Feature",
  "properties": {
    "iso:country":"BE",
    "sg:address":"Toevluchtweg 4b",
    "sg:city":"Nieuwpoort (sint-joris)",
    "sg:classifiers":[
        {
            "category":"Retail",
            "subcategory":"Auto Repair",
            "type":"Services"
        }
    ],
    "sg:phone":"+32 58 23 49 40",
    "sg:postcode":"8620",
    "sg:province":"West-Vlaanderen",
    "sg:tags":[
        "garage"
    ],
    "wof:name":"Portello",
    "wof:placetype":"venue"
},
  "geometry": {"coordinates":[2.7622959614,51.1283721924],"type":"Point"}
}