{
  "type": "Feature",
  "properties": {
    "iso:country":"BE",
    "sg:address":"Brasschaatsebaan 3",
    "sg:city":"Schilde (groot)",
    "sg:classifiers":[
        {
            "category":"Professional",
            "subcategory":"Accounting & Tax Preparation",
            "type":"Services"
        }
    ],
    "sg:phone":"+32 3 385 01 39",
    "sg:postcode":"2970",
    "sg:province":"Antwerpen",
    "sg:tags":[
        "accountant"
    ],
    "wof:name":"August Van De Vliet",
    "wof:placetype":"venue"
},
  "geometry": {"coordinates":[4.5783729553,51.2393112183],"type":"Point"}
}