{
  "type": "Feature",
  "properties": {
    "addr:full":"Mortselsesteenweg 54 Hove Antwerpen 2540",
    "addr:housenumber":"54",
    "addr:postcode":"2540",
    "addr:street":"Mortselsesteenweg",
    "iso:country":"BE",
    "sg:address":"Mortselsesteenweg 54",
    "sg:city":"Hove",
    "sg:orig_category":"Enseignement maternel and primaire",
    "sg:phone":"+32 3 455 48 06",
    "sg:postcode":"2540",
    "sg:province":"Antwerpen",
    "wof:name":"Basisschool",
    "wof:placetype":"venue"
},
  "geometry": {"coordinates":[4.4715390205,51.1559066772],"type":"Point"}
}