{
  "type": "Feature",
  "properties": {
    "addr:full":"Avenue Th\u00e9o Jacques 27 Huy Li\u00e8ge 4500",
    "addr:housenumber":"27",
    "addr:postcode":"4500",
    "addr:street":"Avenue The\u0301O Jacques",
    "iso:country":"BE",
    "sg:address":"Avenue Th\u00e9o Jacques 27",
    "sg:city":"Huy",
    "sg:classifiers":[
        {
            "category":"Shopping",
            "subcategory":"Beauty & Cosmetics",
            "type":"Retail Goods"
        }
    ],
    "sg:phone":"+32 85 23 29 76",
    "sg:postcode":"4500",
    "sg:province":"Li\u00e8ge",
    "sg:tags":[
        "-",
        "perfumery"
    ],
    "wof:name":"Pailhe F",
    "wof:placetype":"venue"
},
  "geometry": {"coordinates":[5.2562861443,50.5220680237],"type":"Point"}
}