{
  "type": "Feature",
  "properties": {
    "iso:country":"BE",
    "sg:address":"Rue P\u00e9ry Hameau 20",
    "sg:city":"Trooz (for\u00eat)",
    "sg:classifiers":[
        {
            "category":"Health Services",
            "subcategory":"Health Practitioner",
            "type":"Services"
        }
    ],
    "sg:phone":"+32 4 351 67 03",
    "sg:postcode":"4870",
    "sg:province":"Li\u00e8ge",
    "sg:tags":[
        "psychologist"
    ],
    "wof:name":"Adam Rita-julie - Bureau \u00e0 Li\u00e8ge",
    "wof:placetype":"venue"
},
  "geometry": {"coordinates":[5.6696181297,50.5613021851],"type":"Point"}
}