{
  "type": "Feature",
  "properties": {
    "addr:full":"Gennevaux 8a Musson Luxembourg 6750",
    "addr:housenumber":"8a",
    "addr:postcode":"6750",
    "addr:street":"Gennevaux",
    "iso:country":"BE",
    "sg:address":"Gennevaux 8a",
    "sg:city":"Musson",
    "sg:classifiers":[
        {
            "category":"Autos & Motor Vehicles",
            "subcategory":"Auto Supplies",
            "type":"Retail Goods"
        }
    ],
    "sg:phone":"+32 63 67 85 27",
    "sg:postcode":"6750",
    "sg:province":"Luxembourg",
    "sg:tags":[
        "access",
        "automobile",
        "part",
        "-"
    ],
    "wof:name":"Pereira",
    "wof:placetype":"venue"
},
  "geometry": {"coordinates":[5.7002549171,49.5682029724],"type":"Point"}
}