{
  "type": "Feature",
  "properties": {
    "iso:country":"BE",
    "sg:address":"Kuurnsestraat 48",
    "sg:city":"Lendelede",
    "sg:orig_category":"Chaussures",
    "sg:phone":"+32 51 30 59 96",
    "sg:postcode":"8860",
    "sg:province":"West-Vlaanderen",
    "wof:name":"Schoencenter Christiane",
    "wof:placetype":"venue"
},
  "geometry": {"coordinates":[3.2411360741,50.8818244934],"type":"Point"}
}