{
  "type": "Feature",
  "properties": {
    "addr:full":"Poorterijstraat 65 Zedelgem West-Vlaanderen 8211",
    "addr:housenumber":"65",
    "addr:postcode":"8211",
    "addr:street":"Poorterijstraat",
    "iso:country":"BE",
    "sg:address":"Poorterijstraat 65",
    "sg:city":"Zedelgem",
    "sg:classifiers":[
        {
            "category":"Food & Beverages",
            "subcategory":"Fruits & Vegetables",
            "type":"Retail Goods"
        }
    ],
    "sg:phone":"+32 50 21 37 56",
    "sg:postcode":"8211",
    "sg:province":"West-Vlaanderen",
    "sg:tags":[
        "groenten"
    ],
    "wof:name":"Dorine Sabbe",
    "wof:placetype":"venue"
},
  "geometry": {"coordinates":[3.0889649391,51.1200408936],"type":"Point"}
}