{
  "type": "Feature",
  "properties": {
    "addr:full":"Peerderbaan 64 Hechtel-eksel Limburg 3940",
    "addr:housenumber":"64",
    "addr:postcode":"3940",
    "addr:street":"Peerderbaan",
    "iso:country":"BE",
    "sg:address":"Peerderbaan 64",
    "sg:city":"Hechtel-eksel",
    "sg:orig_category":"Entretien and r\u00e9parations de voitures. V\u00e9hicules automobiles",
    "sg:phone":"+32 11 73 46 32",
    "sg:postcode":"3940",
    "sg:province":"Limburg",
    "wof:name":"Van Duffel",
    "wof:placetype":"venue"
},
  "geometry": {"coordinates":[5.364795208,51.1255340576],"type":"Point"}
}