{
  "type": "Feature",
  "properties": {
    "iso:country":"BE",
    "sg:address":"Meiz 7",
    "sg:city":"Stavelot",
    "sg:orig_category":"Rundveehouders",
    "sg:phone":"+32 80 33 76 95",
    "sg:postcode":"4970",
    "sg:province":"Li\u00e8ge",
    "wof:name":"Charles Dumoulin",
    "wof:placetype":"venue"
},
  "geometry": {"coordinates":[5.9816060066,50.4200973511],"type":"Point"}
}