{
  "type": "Feature",
  "properties": {
    "addr:full":"Rue De La Fontaine 24 Ch\u00c2telet Hainaut 6200",
    "addr:housenumber":"24",
    "addr:postcode":"6200",
    "addr:street":"Rue De La Fontaine",
    "iso:country":"BE",
    "sg:address":"Rue De La Fontaine 24",
    "sg:city":"Ch\u00c2telet",
    "sg:orig_category":"Plomberie, chauffage and installations sanitaires",
    "sg:phone":"+32 71 38 58 86",
    "sg:postcode":"6200",
    "sg:province":"Hainaut",
    "wof:name":"Eggermont F.",
    "wof:placetype":"venue"
},
  "geometry": {"coordinates":[4.5348877907,50.4018211365],"type":"Point"}
}