{
  "type": "Feature",
  "properties": {
    "iso:country":"BE",
    "sg:address":"Rue D\u00b4elouges 23",
    "sg:city":"Dour",
    "sg:orig_category":"Avocats and conseillers juridiques",
    "sg:phone":"+32 65 69 05 40",
    "sg:postcode":"7370",
    "sg:province":"Hainaut",
    "wof:name":"Bruno De Felicis",
    "wof:placetype":"venue"
},
  "geometry": {"coordinates":[3.7736940384,50.3954925537],"type":"Point"}
}