{
  "type": "Feature",
  "properties": {
    "addr:full":"Chauss\u00e9e De Waterloo 544-546 Bruxelles (ixelles) Bruxelles-Capitale 1050",
    "addr:postcode":"544-546;1050",
    "addr:street":"Chausse\u0301E De Waterloo",
    "iso:country":"BE",
    "sg:address":"Chauss\u00e9e De Waterloo 544-546",
    "sg:city":"Bruxelles (ixelles)",
    "sg:classifiers":[
        {
            "category":"Shopping",
            "subcategory":"Books",
            "type":"Retail Goods"
        }
    ],
    "sg:phone":"+32 2 343 18 48",
    "sg:postcode":"1050",
    "sg:province":"Bruxelles-Capitale",
    "sg:tags":[
        "bookseller"
    ],
    "wof:name":"Shoresh Librairie Delicatesses",
    "wof:placetype":"venue"
},
  "geometry": {"coordinates":[4.3612132072,50.819519043],"type":"Point"}
}