{
  "type": "Feature",
  "properties": {
    "addr:full":"Parelserf 1 Diest (webbekom) Vlaams-Brabant 3290",
    "addr:housenumber":"1",
    "addr:postcode":"3290",
    "addr:street":"Parelserf",
    "iso:country":"BE",
    "sg:address":"Parelserf 1",
    "sg:city":"Diest (webbekom)",
    "sg:classifiers":[
        {
            "category":"Professional",
            "subcategory":"Management & Consulting",
            "type":"Services"
        }
    ],
    "sg:phone":"+32 13 33 30 78",
    "sg:postcode":"3290",
    "sg:province":"Vlaams-Brabant",
    "sg:tags":[
        "-",
        "processing",
        "data",
        "consultant"
    ],
    "wof:name":"R.v. Consulting",
    "wof:placetype":"venue"
},
  "geometry": {"coordinates":[5.0623698235,50.9721221924],"type":"Point"}
}