{
  "type": "Feature",
  "properties": {
    "addr:full":"Rue De Marbaix 149b Montigny-le-tilleul Hainaut 6110",
    "addr:housenumber":"149b",
    "addr:postcode":"6110",
    "addr:street":"Rue De Marbaix",
    "iso:country":"BE",
    "sg:address":"Rue De Marbaix 149b",
    "sg:city":"Montigny-le-tilleul",
    "sg:classifiers":[
        {
            "category":"Arena",
            "subcategory":"Sports Club",
            "type":"Entertainment"
        }
    ],
    "sg:phone":"+32 71 51 89 44",
    "sg:postcode":"6110",
    "sg:province":"Hainaut",
    "sg:tags":[
        "de"
    ],
    "wof:name":"F\u00c9d\u00c9ration Royale Belge De Basket",
    "wof:placetype":"venue"
},
  "geometry": {"coordinates":[4.3721761703,50.3667106628],"type":"Point"}
}