{
  "type": "Feature",
  "properties": {
    "iso:country":"BE",
    "sg:address":"Boulevard De Smet De Nayer 168",
    "sg:city":"Jette",
    "sg:classifiers":[
        {
            "category":"Restaurant",
            "type":"Food & Drink"
        }
    ],
    "sg:phone":"+32 2 426 90 93",
    "sg:postcode":"1090",
    "sg:province":"Bruxelles-Capitale",
    "wof:name":"Patagaf",
    "wof:placetype":"venue"
},
  "geometry": {"coordinates":[4.329641819,50.8752250671],"type":"Point"}
}