{
  "type": "Feature",
  "properties": {
    "iso:country":"BE",
    "sg:address":"Strooiheide 18",
    "sg:city":"Maasmechelen",
    "sg:orig_category":"Paramedische behandelingen",
    "sg:phone":"+32 89 76 79 57",
    "sg:postcode":"3630",
    "sg:province":"Limburg",
    "wof:name":"Micha Gijsen",
    "wof:placetype":"venue"
},
  "geometry": {"coordinates":[5.6776027679,50.9827728271],"type":"Point"}
}