{
  "type": "Feature",
  "properties": {
    "iso:country":"BE",
    "sg:address":"Boulevard Joseph Tirou 95",
    "sg:city":"Charleroi",
    "sg:classifiers":[
        {
            "category":"Personal",
            "subcategory":"Beauty Salon",
            "type":"Services"
        }
    ],
    "sg:phone":"+32 71 31 37 71",
    "sg:postcode":"6000",
    "sg:province":"Hainaut",
    "sg:tags":[
        "slimming"
    ],
    "wof:name":"Centre De Beaute Clarins Sprl",
    "wof:placetype":"venue"
},
  "geometry": {"coordinates":[4.4419488907,50.4084854126],"type":"Point"}
}