{
  "type": "Feature",
  "properties": {
    "addr:full":"Rue De Marbais 30 Floreffe (floriffoux) Namur 5150",
    "addr:housenumber":"30",
    "addr:postcode":"5150",
    "addr:street":"Rue De Marbais",
    "iso:country":"BE",
    "sg:address":"Rue De Marbais 30",
    "sg:city":"Floreffe (floriffoux)",
    "sg:classifiers":[
        {
            "category":"Building & Trades",
            "subcategory":"Construction",
            "type":"Services"
        }
    ],
    "sg:phone":"+32 81 44 50 33",
    "sg:postcode":"5150",
    "sg:province":"Namur",
    "sg:tags":[
        "installation",
        "-",
        "central",
        "heating"
    ],
    "wof:name":"Lesire A",
    "wof:placetype":"venue"
},
  "geometry": {"coordinates":[4.7775411606,50.4584541321],"type":"Point"}
}