{
  "type": "Feature",
  "properties": {
    "addr:full":"Turnhoutsebaan 129 Antwerpen (borgerhout) Antwerpen 2140",
    "addr:housenumber":"129",
    "addr:postcode":"2140",
    "addr:street":"Turnhoutsebaan",
    "iso:country":"BE",
    "sg:address":"Turnhoutsebaan 129",
    "sg:city":"Antwerpen (borgerhout)",
    "sg:classifiers":[
        {
            "category":"Shopping",
            "subcategory":"Music",
            "type":"Retail Goods"
        }
    ],
    "sg:phone":"+32 3 235 48 26",
    "sg:postcode":"2140",
    "sg:province":"Antwerpen",
    "sg:tags":[
        "-",
        "cd's",
        "recorded",
        "cassette"
    ],
    "wof:name":"M & R Movie & Record Shop",
    "wof:placetype":"venue"
},
  "geometry": {"coordinates":[4.4332199097,51.2137565613],"type":"Point"}
}