{
  "type": "Feature",
  "properties": {
    "iso:country":"BE",
    "sg:address":"Rue De L' Harmonie 46",
    "sg:city":"Morlanwelz",
    "sg:orig_category":"Installation \u00e9lectrique r\u00e9sidentielle. Installation \u00e9lectrique industrielle",
    "sg:phone":"+32 64 45 02 25",
    "sg:postcode":"7140",
    "sg:province":"Hainaut",
    "wof:name":"Elec-co",
    "wof:placetype":"venue"
},
  "geometry": {"coordinates":[4.2578902245,50.4675712585],"type":"Point"}
}