{
  "type": "Feature",
  "properties": {
    "addr:full":"Rodestraat 123 Zottegem Oost-Vlaanderen 9620",
    "addr:housenumber":"123",
    "addr:postcode":"9620",
    "addr:street":"Rodestraat",
    "iso:country":"BE",
    "sg:address":"Rodestraat 123",
    "sg:city":"Zottegem",
    "sg:orig_category":"Rundveehouders Varkenskwekers",
    "sg:phone":"+32 9 360 30 25",
    "sg:postcode":"9620",
    "sg:province":"Oost-Vlaanderen",
    "wof:name":"Etienne De Paepe",
    "wof:placetype":"venue"
},
  "geometry": {"coordinates":[3.8392899036,50.8553199768],"type":"Point"}
}