{
  "type": "Feature",
  "properties": {
    "iso:country":"BE",
    "sg:address":"Alt Herbesthalerstrasse 23c",
    "sg:city":"Lontzen",
    "sg:classifiers":[
        {
            "category":"Professional",
            "subcategory":"Computer Services",
            "type":"Services"
        }
    ],
    "sg:phone":"+32 87 89 05 89",
    "sg:postcode":"4710",
    "sg:province":"Li\u00e8ge",
    "sg:tags":[
        "webdesign",
        "-",
        "internet"
    ],
    "wof:name":"Nihant D",
    "wof:placetype":"venue"
},
  "geometry": {"coordinates":[5.9914970398,50.6597442627],"type":"Point"}
}