{
  "type": "Feature",
  "properties": {
    "iso:country":"BE",
    "sg:address":"Rue De P\u00c2turages 7",
    "sg:city":"Quevy",
    "sg:orig_category":"Installatie van houten of kunststof schrijnwerk",
    "sg:phone":"+32 65 58 75 90",
    "sg:postcode":"7041",
    "sg:province":"Hainaut",
    "wof:name":"Freddy Catherine",
    "wof:placetype":"venue"
},
  "geometry": {"coordinates":[4.0340800285,50.3788833618],"type":"Point"}
}