{
  "type": "Feature",
  "properties": {
    "addr:full":"Rue Marcel Lespagne 21 Hasti\u00e8re (hasti\u00e8re-lavaux) Namur 5540",
    "addr:housenumber":"21",
    "addr:postcode":"5540",
    "addr:street":"Rue Marcel Lespagne",
    "iso:country":"BE",
    "sg:address":"Rue Marcel Lespagne 21",
    "sg:city":"Hasti\u00e8re (hasti\u00e8re-lavaux)",
    "sg:classifiers":[
        {
            "category":"Food & Beverages",
            "subcategory":"Groceries & Convenience Stores",
            "type":"Retail Goods"
        }
    ],
    "sg:phone":"+32 82 64 42 92",
    "sg:postcode":"5540",
    "sg:province":"Namur",
    "sg:tags":[
        "grocer"
    ],
    "wof:name":"Louis Delhaize",
    "wof:placetype":"venue"
},
  "geometry": {"coordinates":[4.823469162,50.2156219482],"type":"Point"}
}