{
  "type": "Feature",
  "properties": {
    "iso:country":"BE",
    "sg:address":"Rubenslaan 8",
    "sg:city":"Zoersel",
    "sg:classifiers":[
        {
            "category":"Communications",
            "subcategory":"Film & Video Production",
            "type":"Services"
        }
    ],
    "sg:phone":"+32 3 383 21 10",
    "sg:postcode":"2980",
    "sg:province":"Antwerpen",
    "sg:tags":[
        "platen",
        "cassette",
        "cd's"
    ],
    "wof:name":"Robrecht Reyns",
    "wof:placetype":"venue"
},
  "geometry": {"coordinates":[4.6656808853,51.2659225464],"type":"Point"}
}