{
  "type": "Feature",
  "properties": {
    "addr:full":"Chauss\u00c9e De Couvin 1 Chimay Hainaut 6460",
    "addr:housenumber":"1",
    "addr:postcode":"6460",
    "addr:street":"Chausse\u0301E De Couvin",
    "iso:country":"BE",
    "sg:address":"Chauss\u00c9e De Couvin 1",
    "sg:city":"Chimay",
    "sg:orig_category":"Banken and kredietinstellingen",
    "sg:phone":"+32 60 21 92 88",
    "sg:postcode":"6460",
    "sg:province":"Hainaut",
    "wof:name":"Centea",
    "wof:placetype":"venue"
},
  "geometry": {"coordinates":[4.3194761276,50.0473670959],"type":"Point"}
}