{
  "type": "Feature",
  "properties": {
    "iso:country":"BE",
    "sg:address":"Rue De L\u00b4yser 24",
    "sg:city":"Dour",
    "sg:orig_category":"Paramedische behandelingen",
    "sg:phone":"+32 65 65 62 61",
    "sg:postcode":"7370",
    "sg:province":"Hainaut",
    "wof:name":"A. Bultez",
    "wof:placetype":"venue"
},
  "geometry": {"coordinates":[3.777009964,50.4006958008],"type":"Point"}
}