{
  "type": "Feature",
  "properties": {
    "iso:country":"BE",
    "sg:address":"Kloosterstraat 48",
    "sg:city":"Wuustwezel",
    "sg:classifiers":[
        {
            "category":"Health Services",
            "subcategory":"Health Practitioner",
            "type":"Services"
        }
    ],
    "sg:phone":"+32 3 669 75 08",
    "sg:postcode":"2990",
    "sg:province":"Antwerpen",
    "sg:tags":[
        "physiotherapist"
    ],
    "wof:name":"Geysen Andre",
    "wof:placetype":"venue"
},
  "geometry": {"coordinates":[4.5974149704,51.3918952942],"type":"Point"}
}