{
  "type": "Feature",
  "properties": {
    "addr:full":". Putte (groot) Antwerpen 2580",
    "addr:postcode":"2580",
    "addr:street":"Groot Antwerpen",
    "iso:country":"BE",
    "sg:address":".",
    "sg:city":"Putte (groot)",
    "sg:orig_category":"Apotheken",
    "sg:phone":"+32 900 10 500",
    "sg:postcode":"2580",
    "sg:province":"Antwerpen",
    "wof:name":"Apothekers Van Wacht",
    "wof:placetype":"venue"
},
  "geometry": {"coordinates":[4.6288099289,51.0548591614],"type":"Point"}
}