{
  "type": "Feature",
  "properties": {
    "iso:country":"BE",
    "sg:address":"Rue Joseph Wettinck 64",
    "sg:city":"Seraing",
    "sg:orig_category":"Pain, p\u00e2tisseries and confiseries",
    "sg:phone":"+32 4 233 97 95",
    "sg:postcode":"4101",
    "sg:province":"Li\u00e8ge",
    "wof:name":"Frederic Brabant",
    "wof:placetype":"venue"
},
  "geometry": {"coordinates":[5.5013308525,50.6151046753],"type":"Point"}
}