{
  "type": "Feature",
  "properties": {
    "iso:country":"BE",
    "sg:address":"Kreek 58",
    "sg:city":"Beveren",
    "sg:classifiers":[
        {
            "category":"Cafe",
            "type":"Food & Drink"
        }
    ],
    "sg:phone":"+32 3 773 42 64",
    "sg:postcode":"9130",
    "sg:province":"Oost-Vlaanderen",
    "sg:tags":[
        "caf\u00e9s"
    ],
    "wof:name":"Caf\u00c9 Het Buitenleven",
    "wof:placetype":"venue"
},
  "geometry": {"coordinates":[4.1814389229,51.2839660645],"type":"Point"}
}