{
  "type": "Feature",
  "properties": {
    "iso:country":"BE",
    "sg:address":"Rue Du Pont Neuf 2",
    "sg:city":"Pont-\u00c0-celles",
    "sg:orig_category":"Verplichte sociale verzekeringen",
    "sg:phone":"+32 71 31 37 40",
    "sg:postcode":"6238",
    "sg:province":"Hainaut",
    "wof:name":"Mutualit\u00c9 Lib\u00c9rale",
    "wof:placetype":"venue"
},
  "geometry": {"coordinates":[4.3926649094,50.5056724548],"type":"Point"}
}