{
  "type": "Feature",
  "properties": {
    "addr:full":"Beekboshoek 54a Kontich (waarloos) Antwerpen 2550",
    "addr:housenumber":"54a",
    "addr:postcode":"2550",
    "addr:street":"Beekboshoek",
    "iso:country":"BE",
    "sg:address":"Beekboshoek 54a",
    "sg:city":"Kontich (waarloos)",
    "sg:classifiers":[
        {
            "category":"Retail",
            "subcategory":"Auto Repair",
            "type":"Services"
        }
    ],
    "sg:phone":"+32 15 31 38 96",
    "sg:postcode":"2550",
    "sg:province":"Antwerpen",
    "sg:tags":[
        "garage"
    ],
    "wof:name":"Fierens R",
    "wof:placetype":"venue"
},
  "geometry": {"coordinates":[4.4588308334,51.1072883606],"type":"Point"}
}