{
  "type": "Feature",
  "properties": {
    "iso:country":"BE",
    "sg:address":"Su L't\u00eedge 54",
    "sg:city":"Namur (saint-marc)",
    "sg:classifiers":[
        {
            "category":"Professional",
            "subcategory":"Accounting & Tax Preparation",
            "type":"Services"
        }
    ],
    "sg:phone":"+32 81 73 19 10",
    "sg:postcode":"5003",
    "sg:province":"Namur",
    "sg:tags":[
        "accountant"
    ],
    "wof:name":"Hache M",
    "wof:placetype":"venue"
},
  "geometry": {"coordinates":[4.8603792191,50.4967842102],"type":"Point"}
}