{
  "type": "Feature",
  "properties": {
    "iso:country":"BE",
    "sg:address":"Irislaan 16",
    "sg:city":"Bertem",
    "sg:orig_category":"Loodgieterij, verwarming and sanitaire installaties",
    "sg:phone":"+32 2 767 18 09",
    "sg:postcode":"3061",
    "sg:province":"Vlaams-Brabant",
    "wof:name":"Dekelver F.",
    "wof:placetype":"venue"
},
  "geometry": {"coordinates":[4.5928969383,50.8442764282],"type":"Point"}
}