{
  "type": "Feature",
  "properties": {
    "addr:full":"Bonneviestraat 36 Sint-jans-molenbeek/molenbeek-saint-jean Bruxelles-Capitale 1080",
    "addr:housenumber":"36",
    "addr:postcode":"1080",
    "addr:street":"Bonneviestraat",
    "iso:country":"BE",
    "sg:address":"Bonneviestraat 36",
    "sg:city":"Sint-jans-molenbeek/molenbeek-saint-jean",
    "sg:orig_category":"Herstellingen and onderhoud van auto's",
    "sg:phone":"+32 2 411 24 35",
    "sg:postcode":"1080",
    "sg:province":"Bruxelles-Capitale",
    "wof:name":"Garage Bonnevie",
    "wof:placetype":"venue"
},
  "geometry": {"coordinates":[4.3377428055,50.8563041687],"type":"Point"}
}