{
  "type": "Feature",
  "properties": {
    "addr:full":"Rue Des Messes 23 Esneux Li\u00e8ge 4130",
    "addr:housenumber":"23",
    "addr:postcode":"4130",
    "addr:street":"Rue Des Messes",
    "iso:country":"BE",
    "sg:address":"Rue Des Messes 23",
    "sg:city":"Esneux",
    "sg:orig_category":"M\u00e9decins and sp\u00e9cialistes",
    "sg:phone":"+32 4 388 13 28",
    "sg:postcode":"4130",
    "sg:province":"Li\u00e8ge",
    "wof:name":"N. Lecocq-fran\u00c7ois",
    "wof:placetype":"venue"
},
  "geometry": {"coordinates":[5.5904150009,50.5737762451],"type":"Point"}
}