{
  "type": "Feature",
  "properties": {
    "iso:country":"BE",
    "sg:address":"Rue Van Aa 28 Box 5",
    "sg:city":"Bruxelles (ixelles)",
    "sg:classifiers":[
        {
            "category":"Building & Trades",
            "subcategory":"Construction",
            "type":"Services"
        }
    ],
    "sg:phone":"+32 2 646 24 72",
    "sg:postcode":"1050",
    "sg:province":"Bruxelles-Capitale",
    "sg:tags":[
        "ecological"
    ],
    "wof:name":"Groupe Kadhermes",
    "wof:placetype":"venue"
},
  "geometry": {"coordinates":[4.3695020676,50.8334274292],"type":"Point"}
}