{
  "type": "Feature",
  "properties": {
    "addr:full":"Koningin Astridstraat 66 A Zedelgem West-Vlaanderen 8210",
    "addr:housenumber":"66 a",
    "addr:postcode":"8210",
    "addr:street":"Koningin Astridstraat",
    "iso:country":"BE",
    "sg:address":"Koningin Astridstraat 66 A",
    "sg:city":"Zedelgem",
    "sg:orig_category":"Transports routiers de marchandises",
    "sg:phone":"+32 50 28 99 69",
    "sg:postcode":"8210",
    "sg:province":"West-Vlaanderen",
    "wof:name":"Bevertrans",
    "wof:placetype":"venue"
},
  "geometry": {"coordinates":[3.1458399296,51.1376457214],"type":"Point"}
}