{
  "type": "Feature",
  "properties": {
    "iso:country":"BE",
    "sg:address":"Brusselsesteenweg 321",
    "sg:city":"Overijse",
    "sg:classifiers":[
        {
            "category":"Freight",
            "type":"Transportation"
        }
    ],
    "sg:phone":"+32 2 687 99 79",
    "sg:postcode":"3090",
    "sg:province":"Vlaams-Brabant",
    "sg:tags":[
        "-",
        "transport"
    ],
    "wof:name":"Petrens Transbelga Bvba-sprl",
    "wof:placetype":"venue"
},
  "geometry": {"coordinates":[4.5016498566,50.7854309082],"type":"Point"}
}