{
  "type": "Feature",
  "properties": {
    "addr:full":"Chemin De Gabelle 7 Huy Li\u00e8ge 4500",
    "addr:housenumber":"7",
    "addr:postcode":"4500",
    "addr:street":"Chemin De Gabelle",
    "iso:country":"BE",
    "sg:address":"Chemin De Gabelle 7",
    "sg:city":"Huy",
    "sg:classifiers":[
        {
            "category":"Health Services",
            "subcategory":"Doctor",
            "type":"Services"
        }
    ],
    "sg:phone":"+32 85 23 06 41",
    "sg:postcode":"4500",
    "sg:province":"Li\u00e8ge",
    "sg:tags":[
        "medicinephysicians",
        "surgeon"
    ],
    "wof:name":"De Terwangne J",
    "wof:placetype":"venue"
},
  "geometry": {"coordinates":[5.2466268539,50.5135345459],"type":"Point"}
}