{
  "type": "Feature",
  "properties": {
    "addr:full":"Rue De La Taillette 40 Hamois Namur 5362",
    "addr:housenumber":"40",
    "addr:postcode":"5362",
    "addr:street":"Rue De La Taillette",
    "iso:country":"BE",
    "sg:address":"Rue De La Taillette 40",
    "sg:city":"Hamois",
    "sg:orig_category":"Woningbouw",
    "sg:phone":"+32 83 61 14 04",
    "sg:postcode":"5362",
    "sg:province":"Namur",
    "wof:name":"Marc Poulin",
    "wof:placetype":"venue"
},
  "geometry": {"coordinates":[5.1903319359,50.3356552124],"type":"Point"}
}