{
  "type": "Feature",
  "properties": {
    "iso:country":"BE",
    "sg:address":"Rue Hardu\u00e9mont 59",
    "sg:city":"Verlaine",
    "sg:classifiers":[
        {
            "category":"Food & Beverages",
            "subcategory":"Meat & Fish",
            "type":"Retail Goods"
        }
    ],
    "sg:phone":"+32 4 259 52 51",
    "sg:postcode":"4537",
    "sg:province":"Li\u00e8ge",
    "sg:tags":[
        "poultry",
        "whol",
        "game",
        "-"
    ],
    "wof:name":"Poulet Hesbaye Sc-abattoir Bolly Scrl",
    "wof:placetype":"venue"
},
  "geometry": {"coordinates":[5.3262968063,50.6288757324],"type":"Point"}
}