{
  "type": "Feature",
  "properties": {
    "iso:country":"BE",
    "sg:address":"Rue De La Ferme 2",
    "sg:city":"Comblain-au-pont",
    "sg:classifiers":[
        {
            "category":"Wholesale",
            "subcategory":"Hardware",
            "type":"Manufacturing & Wholesale Goods"
        }
    ],
    "sg:phone":"+32 4 369 12 22",
    "sg:postcode":"4170",
    "sg:province":"Li\u00e8ge",
    "sg:tags":[
        "lubricating",
        "compound"
    ],
    "wof:name":"Degrange E",
    "wof:placetype":"venue"
},
  "geometry": {"coordinates":[5.5759501457,50.4744720459],"type":"Point"}
}