{
  "type": "Feature",
  "properties": {
    "iso:country":"BE",
    "sg:address":"Chauss\u00c9e De Louvain 939",
    "sg:city":"Evere/evere",
    "sg:orig_category":"Mat\u00e9riaux de construction Gr",
    "sg:phone":"+32 2 726 56 76",
    "sg:postcode":"1140",
    "sg:province":"Bruxelles-Capitale",
    "wof:name":"C. Vandermosten/claude Vandermosten",
    "wof:placetype":"venue"
},
  "geometry": {"coordinates":[4.4202189445,50.8606414795],"type":"Point"}
}