{
  "type": "Feature",
  "properties": {
    "iso:country":"BE",
    "sg:address":"Driesstraat 78",
    "sg:city":"Meise",
    "sg:orig_category":"Travaux de pl\u00e2trage",
    "sg:phone":"+32 2 269 06 68",
    "sg:postcode":"1861",
    "sg:province":"Vlaams-Brabant",
    "wof:name":"Maurice Goossens",
    "wof:placetype":"venue"
},
  "geometry": {"coordinates":[4.303442955,50.9556846619],"type":"Point"}
}