{
  "type": "Feature",
  "properties": {
    "iso:country":"BE",
    "sg:address":"Goudveld 7",
    "sg:city":"Zoersel",
    "sg:orig_category":"Installation \u00e9lectrique r\u00e9sidentielle",
    "sg:phone":"+32 3 383 40 04",
    "sg:postcode":"2980",
    "sg:province":"Antwerpen",
    "wof:name":"A.l.k.",
    "wof:placetype":"venue"
},
  "geometry": {"coordinates":[4.6746702194,51.2626800537],"type":"Point"}
}