{
  "type": "Feature",
  "properties": {
    "iso:country":"BE",
    "sg:address":"Soenenspark 15",
    "sg:city":"Gent (sint-denijs-westrem - Afsnee)",
    "sg:classifiers":[
        {
            "category":"Building & Trades",
            "subcategory":"Construction",
            "type":"Services"
        }
    ],
    "sg:phone":"+32 9 243 80 50",
    "sg:postcode":"9051",
    "sg:province":"Oost-Vlaanderen",
    "sg:tags":[
        "-",
        "door",
        "folding",
        "sliding"
    ],
    "wof:name":"Scrigno",
    "wof:placetype":"venue"
},
  "geometry": {"coordinates":[3.6737411022,51.0162162781],"type":"Point"}
}