{
  "type": "Feature",
  "properties": {
    "addr:full":"Industrieweg 18 Beerse Antwerpen 2340",
    "addr:housenumber":"18",
    "addr:postcode":"2340",
    "addr:street":"Industrieweg",
    "iso:country":"BE",
    "sg:address":"Industrieweg 18",
    "sg:city":"Beerse",
    "sg:orig_category":"Non-Classified Establishments",
    "sg:phone":"+32 14 61 44 45",
    "sg:postcode":"2340",
    "sg:province":"Antwerpen",
    "wof:name":"Modimex",
    "wof:placetype":"venue"
},
  "geometry": {"coordinates":[4.8318729401,51.2980575562],"type":"Point"}
}