{
  "type": "Feature",
  "properties": {
    "addr:full":"Godfried Devreeselaan 13 Kortrijk West-Vlaanderen 8500",
    "addr:housenumber":"13",
    "addr:postcode":"8500",
    "addr:street":"Devreeselaan",
    "iso:country":"BE",
    "sg:address":"Godfried Devreeselaan 13",
    "sg:city":"Kortrijk",
    "sg:classifiers":[
        {
            "category":"Shopping",
            "subcategory":"Jewelry",
            "type":"Retail Goods"
        }
    ],
    "sg:phone":"+32 56 35 76 92",
    "sg:postcode":"8500",
    "sg:province":"West-Vlaanderen",
    "sg:tags":[
        "jeweller",
        "-"
    ],
    "wof:name":"Haspeslagh G",
    "wof:placetype":"venue"
},
  "geometry": {"coordinates":[3.2652070522,50.8389091492],"type":"Point"}
}