{
  "type": "Feature",
  "properties": {
    "addr:full":"Rue Du Vivier 57 Vielsalm Luxembourg 6690",
    "addr:housenumber":"57",
    "addr:postcode":"6690",
    "addr:street":"Rue Du Vivier",
    "iso:country":"BE",
    "sg:address":"Rue Du Vivier 57",
    "sg:city":"Vielsalm",
    "sg:classifiers":[
        {
            "category":"Arena",
            "subcategory":"Sports Club",
            "type":"Entertainment"
        }
    ],
    "sg:phone":"+32 80 21 54 05",
    "sg:postcode":"6690",
    "sg:province":"Luxembourg",
    "sg:tags":[
        "de"
    ],
    "wof:name":"T.c. Salm",
    "wof:placetype":"venue"
},
  "geometry": {"coordinates":[5.9084529877,50.2775840759],"type":"Point"}
}