{
  "type": "Feature",
  "properties": {
    "addr:full":"Lievevrouwstraat 67 Wommelgem Antwerpen 2160",
    "addr:housenumber":"67",
    "addr:postcode":"2160",
    "addr:street":"Lievevrouwstraat",
    "iso:country":"BE",
    "sg:address":"Lievevrouwstraat 67",
    "sg:city":"Wommelgem",
    "sg:classifiers":[
        {
            "category":"Arena",
            "subcategory":"Sports Club",
            "type":"Entertainment"
        }
    ],
    "sg:phone":"+32 3 353 22 14",
    "sg:postcode":"2160",
    "sg:province":"Antwerpen",
    "sg:tags":[
        "de"
    ],
    "wof:name":"Wo-gym",
    "wof:placetype":"venue"
},
  "geometry": {"coordinates":[4.5283279419,51.2031059265],"type":"Point"}
}