{
  "type": "Feature",
  "properties": {
    "addr:full":"Magdalena Vermeeschlaan 15 Hove Antwerpen 2540",
    "addr:housenumber":"15",
    "addr:postcode":"2540",
    "addr:street":"Magdalena Vermeeschlaan",
    "iso:country":"BE",
    "sg:address":"Magdalena Vermeeschlaan 15",
    "sg:city":"Hove",
    "sg:classifiers":[
        {
            "category":"Professional",
            "subcategory":"Computer Services",
            "type":"Services"
        }
    ],
    "sg:phone":"+32 3 455 17 36",
    "sg:postcode":"2540",
    "sg:province":"Antwerpen",
    "sg:tags":[
        "-",
        "processing",
        "data",
        "software"
    ],
    "wof:name":"Vervliet Bvba",
    "wof:placetype":"venue"
},
  "geometry": {"coordinates":[4.4789228439,51.1434745789],"type":"Point"}
}