{
  "type": "Feature",
  "properties": {
    "addr:full":"Rue Augustin Duvivier 2 Fleurus Hainaut 6220",
    "addr:housenumber":"2",
    "addr:postcode":"6220",
    "addr:street":"Rue Augustin Duvivier",
    "iso:country":"BE",
    "sg:address":"Rue Augustin Duvivier 2",
    "sg:city":"Fleurus",
    "sg:orig_category":"Artsen and specialisten",
    "sg:phone":"+32 71 81 11 25",
    "sg:postcode":"6220",
    "sg:province":"Hainaut",
    "wof:name":"Lucien Delande",
    "wof:placetype":"venue"
},
  "geometry": {"coordinates":[4.5573401451,50.4568748474],"type":"Point"}
}