{
  "type": "Feature",
  "properties": {
    "iso:country":"BE",
    "sg:address":"Weg Op Bree 3ba",
    "sg:city":"Meeuwen-gruitrode",
    "sg:classifiers":[
        {
            "category":"Insurance",
            "subcategory":"Insurance Agent",
            "type":"Services"
        }
    ],
    "sg:phone":"+32 11 79 31 81",
    "sg:postcode":"3670",
    "sg:province":"Limburg",
    "sg:tags":[
        "verzekeringsmakelaars",
        "expert"
    ],
    "wof:name":"Bureau Brebels Stefan",
    "wof:placetype":"venue"
},
  "geometry": {"coordinates":[5.5188398361,51.0983963013],"type":"Point"}
}