{
  "type": "Feature",
  "properties": {
    "iso:country":"BE",
    "sg:address":"Rozestraat 7",
    "sg:city":"Ingelmunster",
    "sg:classifiers":[
        {
            "category":"Home & Garden",
            "subcategory":"Carpets & Floor Coverings",
            "type":"Retail Goods"
        }
    ],
    "sg:phone":"+32 51 30 40 93",
    "sg:postcode":"8770",
    "sg:province":"West-Vlaanderen",
    "sg:tags":[
        "tile"
    ],
    "wof:name":"Mestdagh Vloeren Bvba",
    "wof:placetype":"venue"
},
  "geometry": {"coordinates":[3.2458019257,50.9150810242],"type":"Point"}
}