{
  "type": "Feature",
  "properties": {
    "iso:country":"BE",
    "sg:address":"Damstraat 64",
    "sg:city":"Hamme",
    "sg:orig_category":"Brandweer and civiele bescherming",
    "sg:phone":"+32 52 48 09 21",
    "sg:postcode":"9220",
    "sg:province":"Oost-Vlaanderen",
    "wof:name":"Brandweerkazerne",
    "wof:placetype":"venue"
},
  "geometry": {"coordinates":[4.1357221603,51.0900611877],"type":"Point"}
}