{
  "type": "Feature",
  "properties": {
    "iso:country":"BE",
    "sg:address":"Boterpotstraat 9",
    "sg:city":"Harelbeke",
    "sg:orig_category":"Textiel",
    "sg:phone":"+32 56 70 48 78",
    "sg:postcode":"8530",
    "sg:province":"West-Vlaanderen",
    "wof:name":"Dehitex",
    "wof:placetype":"venue"
},
  "geometry": {"coordinates":[3.3157250881,50.8585891724],"type":"Point"}
}