{
  "type": "Feature",
  "properties": {
    "iso:country":"BE",
    "sg:address":"Oude Barrier 15",
    "sg:city":"Beringen (paal)",
    "sg:classifiers":[
        {
            "category":"Building & Trades",
            "subcategory":"Landscaping Services",
            "type":"Services"
        }
    ],
    "sg:phone":"+32 11 42 56 45",
    "sg:postcode":"3583",
    "sg:province":"Limburg",
    "sg:tags":[
        "equipment",
        "swimming",
        "-",
        "pool",
        "contractor"
    ],
    "wof:name":"Geert Zwembaden",
    "wof:placetype":"venue"
},
  "geometry": {"coordinates":[5.181470871,51.0394554138],"type":"Point"}
}