{
  "type": "Feature",
  "properties": {
    "addr:full":"Grand'rue 24 Durbuy Luxembourg 6940",
    "addr:housenumber":"24",
    "addr:postcode":"6940",
    "addr:street":"Grand'Rue",
    "iso:country":"BE",
    "sg:address":"Grand'rue 24",
    "sg:city":"Durbuy",
    "sg:orig_category":"Overheidsdiensten",
    "sg:phone":"+32 86 21 25 51",
    "sg:postcode":"6940",
    "sg:province":"Luxembourg",
    "wof:name":"Administration Communale",
    "wof:placetype":"venue"
},
  "geometry": {"coordinates":[5.4936060905,50.3504981995],"type":"Point"}
}