{
  "type": "Feature",
  "properties": {
    "iso:country":"BE",
    "sg:address":"Guido Gezellestraat 11",
    "sg:city":"Zomergem",
    "sg:orig_category":"Magasins de r\u00e9parations d'articles personnels et m\u00e9nagers divers",
    "sg:phone":"+32 9 372 60 87",
    "sg:postcode":"9930",
    "sg:province":"Oost-Vlaanderen",
    "wof:name":"Inge Stul",
    "wof:placetype":"venue"
},
  "geometry": {"coordinates":[3.5552949905,51.1157531738],"type":"Point"}
}