{
  "type": "Feature",
  "properties": {
    "iso:country":"BE",
    "sg:address":"Alsembergse Steenweg 352",
    "sg:city":"Vorst/forest",
    "sg:classifiers":[
        {
            "category":"Communications",
            "subcategory":"Television Station",
            "type":"Services"
        }
    ],
    "sg:phone":"+32 2 347 09 03",
    "sg:postcode":"1190",
    "sg:province":"Bruxelles-Capitale",
    "sg:tags":[
        "video",
        "audio",
        "verhuur"
    ],
    "wof:name":"Cin\u00c9bank Vid\u00c9o 24h/24",
    "wof:placetype":"venue"
},
  "geometry": {"coordinates":[4.3399939537,50.8156814575],"type":"Point"}
}