{
  "type": "Feature",
  "properties": {
    "addr:full":"Laageind 7 Stabroek Antwerpen 2940",
    "addr:housenumber":"7",
    "addr:postcode":"2940",
    "addr:street":"Laageind",
    "iso:country":"BE",
    "sg:address":"Laageind 7",
    "sg:city":"Stabroek",
    "sg:orig_category":"Newspapers, magazines, periodicals - Publishers",
    "sg:phone":"+32 3 568 71 72",
    "sg:postcode":"2940",
    "sg:province":"Antwerpen",
    "wof:name":"De Polder",
    "wof:placetype":"venue"
},
  "geometry": {"coordinates":[4.3621239662,51.3306083679],"type":"Point"}
}