{
  "type": "Feature",
  "properties": {
    "addr:full":"Dorpsstraat 12 Londerzeel Vlaams-Brabant 1840",
    "addr:housenumber":"12",
    "addr:postcode":"1840",
    "addr:street":"Dorpsstraat",
    "iso:country":"BE",
    "sg:address":"Dorpsstraat 12",
    "sg:city":"Londerzeel",
    "sg:classifiers":[
        {
            "category":"Restaurant",
            "type":"Food & Drink"
        }
    ],
    "sg:phone":"+32 52 31 22 50",
    "sg:postcode":"1840",
    "sg:province":"Vlaams-Brabant",
    "wof:name":"De Planck",
    "wof:placetype":"venue"
},
  "geometry": {"coordinates":[4.3021669388,51.0034751892],"type":"Point"}
}