{
  "type": "Feature",
  "properties": {
    "addr:full":"Armentierestraat 397 Komen-waasten/comines-warneton Hainaut 7783",
    "addr:housenumber":"397;7783",
    "addr:street":"Armentierestraat",
    "iso:country":"BE",
    "sg:address":"Armentierestraat 397",
    "sg:city":"Komen-waasten/comines-warneton",
    "sg:orig_category":"Banken and kredietinstellingen",
    "sg:phone":"+32 56 58 89 38",
    "sg:postcode":"7783",
    "sg:province":"Hainaut",
    "wof:name":"Bbl",
    "wof:placetype":"venue"
},
  "geometry": {"coordinates":[2.8828949928,50.7069244385],"type":"Point"}
}