{
  "type": "Feature",
  "properties": {
    "addr:full":"Rue De L'h\u00d4tel De Ville 12bb Sprimont Li\u00e8ge 4140",
    "addr:housenumber":"12bb",
    "addr:postcode":"4140",
    "addr:street":"Rue De L'Ho \u0302Tel De Ville",
    "iso:country":"BE",
    "sg:address":"Rue De L'h\u00d4tel De Ville 12bb",
    "sg:city":"Sprimont",
    "sg:orig_category":"Enseignement maternel and primaire",
    "sg:phone":"+32 4 382 24 35",
    "sg:postcode":"4140",
    "sg:province":"Li\u00e8ge",
    "wof:name":"E.f.l. Emmanuel",
    "wof:placetype":"venue"
},
  "geometry": {"coordinates":[5.6512598991,50.5162200928],"type":"Point"}
}