{
  "type": "Feature",
  "properties": {
    "addr:full":"Priemstraat 44 Beveren Oost-Vlaanderen 9120",
    "addr:housenumber":"44",
    "addr:postcode":"9120",
    "addr:street":"Priemstraat",
    "iso:country":"BE",
    "sg:address":"Priemstraat 44",
    "sg:city":"Beveren",
    "sg:orig_category":"Fruitteelt",
    "sg:phone":"+32 3 775 42 24",
    "sg:postcode":"9120",
    "sg:province":"Oost-Vlaanderen",
    "wof:name":"Prosper Van Stappen",
    "wof:placetype":"venue"
},
  "geometry": {"coordinates":[4.2841391563,51.1931800842],"type":"Point"}
}