{
  "type": "Feature",
  "properties": {
    "iso:country":"BE",
    "sg:address":"Rue F\u00e9lix Bernard 82",
    "sg:city":"Saint-nicolas (montegn\u00e9e)",
    "sg:classifiers":[
        {
            "category":"Health Services",
            "subcategory":"Doctor",
            "type":"Services"
        }
    ],
    "sg:phone":"+32 4 247 25 61",
    "sg:postcode":"4420",
    "sg:province":"Li\u00e8ge",
    "sg:tags":[
        "medicinephysicians",
        "surgeon"
    ],
    "wof:name":"Denoiseux C\u00e9cile",
    "wof:placetype":"venue"
},
  "geometry": {"coordinates":[5.5195879936,50.6431999207],"type":"Point"}
}