{
  "type": "Feature",
  "properties": {
    "addr:full":"Groteweg 220 Geraardsbergen Oost-Vlaanderen 9500",
    "addr:housenumber":"220",
    "addr:postcode":"9500",
    "addr:street":"Groteweg",
    "iso:country":"BE",
    "sg:address":"Groteweg 220",
    "sg:city":"Geraardsbergen",
    "sg:classifiers":[
        {
            "category":"Cafe",
            "type":"Food & Drink"
        }
    ],
    "sg:phone":"+32 54 41 75 31",
    "sg:postcode":"9500",
    "sg:province":"Oost-Vlaanderen",
    "sg:tags":[
        "caf\u00e9s"
    ],
    "wof:name":"Koenraad Vanderschueren",
    "wof:placetype":"venue"
},
  "geometry": {"coordinates":[3.8682899475,50.7667388916],"type":"Point"}
}