{
  "type": "Feature",
  "properties": {
    "addr:full":"Sint-annastraat 15 Steenokkerzeel Vlaams-Brabant 1820",
    "addr:housenumber":"15",
    "addr:postcode":"1820",
    "addr:street":"Sint-Annastraat",
    "iso:country":"BE",
    "sg:address":"Sint-annastraat 15",
    "sg:city":"Steenokkerzeel",
    "sg:orig_category":"Kapsalons",
    "sg:phone":"+32 2 751 87 70",
    "sg:postcode":"1820",
    "sg:province":"Vlaams-Brabant",
    "wof:name":"Hairstyling Marc",
    "wof:placetype":"venue"
},
  "geometry": {"coordinates":[4.4938278198,50.9329338074],"type":"Point"}
}