{
  "type": "Feature",
  "properties": {
    "addr:full":"Rue D'asquillies 56 Mons Hainaut 7022",
    "addr:housenumber":"56",
    "addr:postcode":"7022",
    "addr:street":"Rue D'Asquillies;Hainaut",
    "iso:country":"BE",
    "sg:address":"Rue D'asquillies 56",
    "sg:city":"Mons",
    "sg:orig_category":"Artsen and specialisten",
    "sg:phone":"+32 65 33 89 84",
    "sg:postcode":"7022",
    "sg:province":"Hainaut",
    "wof:name":"Marianne Lossignol",
    "wof:placetype":"venue"
},
  "geometry": {"coordinates":[3.9619328976,50.4398155212],"type":"Point"}
}