{
  "type": "Feature",
  "properties": {
    "addr:full":"Lostraat 18 Lo-reninge West-Vlaanderen 8647",
    "addr:housenumber":"18",
    "addr:postcode":"8647",
    "addr:street":"Lostraat",
    "iso:country":"BE",
    "sg:address":"Lostraat 18",
    "sg:city":"Lo-reninge",
    "sg:classifiers":[
        {
            "category":"Personal",
            "subcategory":"Beauty Salon",
            "type":"Services"
        }
    ],
    "sg:phone":"+32 57 40 02 66",
    "sg:postcode":"8647",
    "sg:province":"West-Vlaanderen",
    "sg:tags":[
        "de",
        "coiffure"
    ],
    "wof:name":"Coiffure Simone",
    "wof:placetype":"venue"
},
  "geometry": {"coordinates":[2.7861969471,50.949924469],"type":"Point"}
}