{
  "type": "Feature",
  "properties": {
    "addr:full":"Th\u00c9odore Verhaegenstraat 190 Sint-gillis/saint-gilles Bruxelles-Capitale 1060",
    "addr:housenumber":"190",
    "addr:postcode":"1060",
    "addr:street":"The\u0301Odore Verhaegenstraat",
    "iso:country":"BE",
    "sg:address":"Th\u00c9odore Verhaegenstraat 190",
    "sg:city":"Sint-gillis/saint-gilles",
    "sg:orig_category":"Onderdelen and accessoires voor auto's",
    "sg:phone":"+32 2 537 31 11",
    "sg:postcode":"1060",
    "sg:province":"Bruxelles-Capitale",
    "wof:name":"Autoland Parts",
    "wof:placetype":"venue"
},
  "geometry": {"coordinates":[4.3354849815,50.8308601379],"type":"Point"}
}