{
  "type": "Feature",
  "properties": {
    "iso:country":"BE",
    "sg:address":"Rerum Novarumlaan 3",
    "sg:city":"Wuustwezel",
    "sg:classifiers":[
        {
            "category":"Health Services",
            "subcategory":"Dentist",
            "type":"Services"
        }
    ],
    "sg:phone":"+32 3 663 65 00",
    "sg:postcode":"2990",
    "sg:province":"Antwerpen",
    "wof:name":"Vandeperre C",
    "wof:placetype":"venue"
},
  "geometry": {"coordinates":[4.5424981117,51.3571014404],"type":"Point"}
}