{
  "type": "Feature",
  "properties": {
    "addr:full":"Rue De Fl\u00c9malle 9 Seraing Li\u00e8ge 4101",
    "addr:housenumber":"9",
    "addr:postcode":"4101",
    "addr:street":"Rue De Fle\u0301Malle",
    "iso:country":"BE",
    "sg:address":"Rue De Fl\u00c9malle 9",
    "sg:city":"Seraing",
    "sg:orig_category":"Librairies. Journaux. Tabac",
    "sg:phone":"+32 4 234 35 53",
    "sg:postcode":"4101",
    "sg:province":"Li\u00e8ge",
    "wof:name":"Maison Vercors",
    "wof:placetype":"venue"
},
  "geometry": {"coordinates":[5.4906811714,50.6080818176],"type":"Point"}
}