{
  "type": "Feature",
  "properties": {
    "addr:full":"Kerkstraat 21 Merksplas Antwerpen 2330",
    "addr:housenumber":"21",
    "addr:postcode":"2330",
    "addr:street":"Kerkstraat",
    "iso:country":"BE",
    "sg:address":"Kerkstraat 21",
    "sg:city":"Merksplas",
    "sg:orig_category":"Kapsalons",
    "sg:phone":"+32 14 63 31 99",
    "sg:postcode":"2330",
    "sg:province":"Antwerpen",
    "wof:name":"Karl's Coiffure",
    "wof:placetype":"venue"
},
  "geometry": {"coordinates":[4.8632240295,51.3595542908],"type":"Point"}
}