{
  "type": "Feature",
  "properties": {
    "addr:full":"Rue De La Glacerie 13 Jemeppe-sur-sambre Namur 5190",
    "addr:housenumber":"13",
    "addr:postcode":"5190",
    "addr:street":"Rue De La Glacerie",
    "iso:country":"BE",
    "sg:address":"Rue De La Glacerie 13",
    "sg:city":"Jemeppe-sur-sambre",
    "sg:orig_category":"Jeux de hasard",
    "sg:phone":"+32 71 78 50 38",
    "sg:postcode":"5190",
    "sg:province":"Namur",
    "wof:name":"Tierc\u00c9 Belge",
    "wof:placetype":"venue"
},
  "geometry": {"coordinates":[4.6950302124,50.4523124695],"type":"Point"}
}