{
  "type": "Feature",
  "properties": {
    "iso:country":"BE",
    "sg:address":"Rue Albert I 58",
    "sg:city":"La Louviere",
    "sg:orig_category":"V\u00eatements",
    "sg:phone":"+32 64 28 38 77",
    "sg:postcode":"7100",
    "sg:province":"Hainaut",
    "wof:name":"Tower",
    "wof:placetype":"venue"
},
  "geometry": {"coordinates":[4.2118902206,50.4707603455],"type":"Point"}
}