{
  "type": "Feature",
  "properties": {
    "addr:full":"Pi Taymansstr 12 Overijse Vlaams-Brabant 3090",
    "addr:housenumber":"12",
    "addr:postcode":"3090",
    "iso:country":"BE",
    "sg:address":"Pi Taymansstr 12",
    "sg:city":"Overijse",
    "sg:classifiers":[
        {
            "category":"Shopping",
            "subcategory":"Clothing, Apparel, & Fashions",
            "type":"Retail Goods"
        }
    ],
    "sg:phone":"+32 2 686 15 25",
    "sg:postcode":"3090",
    "sg:province":"Vlaams-Brabant",
    "sg:tags":[
        "textile",
        "clothing",
        "clothes"
    ],
    "wof:name":"Dutra Nv",
    "wof:placetype":"venue"
},
  "geometry": {"coordinates":[4.5375847816,50.7738990784],"type":"Point"}
}