{
  "type": "Feature",
  "properties": {
    "iso:country":"BE",
    "sg:address":"Neuer Weg 1",
    "sg:city":"B\u00fctgenbach",
    "sg:classifiers":[
        {
            "category":"Travel",
            "subcategory":"Hotels & Motels",
            "type":"Entertainment"
        }
    ],
    "sg:phone":"+32 80 44 50 86",
    "sg:postcode":"4750",
    "sg:province":"Li\u00e8ge",
    "wof:name":"Lindenhof",
    "wof:placetype":"venue"
},
  "geometry": {"coordinates":[6.1644659042,50.4332084656],"type":"Point"}
}