{
  "type": "Feature",
  "properties": {
    "addr:full":"Grand-rue 88 Morlanwelz Hainaut 7140",
    "addr:housenumber":"88",
    "addr:postcode":"7140",
    "addr:street":"Grand-Rue",
    "iso:country":"BE",
    "sg:address":"Grand-rue 88",
    "sg:city":"Morlanwelz",
    "sg:orig_category":"Postkantoren Verzekeringsmakelaars and experts",
    "sg:phone":"+32 64 44 23 74",
    "sg:postcode":"7140",
    "sg:province":"Hainaut",
    "wof:name":"La Poste",
    "wof:placetype":"venue"
},
  "geometry": {"coordinates":[4.2467889786,50.4572868347],"type":"Point"}
}