{
  "type": "Feature",
  "properties": {
    "iso:country":"BE",
    "sg:address":"Tiensestraat 77",
    "sg:city":"Kortenaken",
    "sg:classifiers":[
        {
            "category":"Farming",
            "subcategory":"Crops",
            "type":"Manufacturing & Wholesale Goods"
        }
    ],
    "sg:phone":"+32 11 58 74 15",
    "sg:postcode":"3470",
    "sg:province":"Vlaams-Brabant",
    "sg:tags":[
        "vegetable",
        "fruit",
        "-",
        "grower"
    ],
    "wof:name":"Jan",
    "wof:placetype":"venue"
},
  "geometry": {"coordinates":[5.0461978912,50.8977661133],"type":"Point"}
}