{
  "type": "Feature",
  "properties": {
    "addr:full":"Rue De Najauge 51 Viroinval (maz\u00e9e) Namur 5670",
    "addr:housenumber":"51",
    "addr:postcode":"5670",
    "addr:street":"Rue De Najauge",
    "iso:country":"BE",
    "sg:address":"Rue De Najauge 51",
    "sg:city":"Viroinval (maz\u00e9e)",
    "sg:classifiers":[
        {
            "category":"Shopping",
            "subcategory":"Gifts & Souvenirs",
            "type":"Retail Goods"
        }
    ],
    "sg:phone":"+32 60 39 90 67",
    "sg:postcode":"5670",
    "sg:province":"Namur",
    "sg:tags":[
        "-"
    ],
    "wof:name":"Bertrand J",
    "wof:placetype":"venue"
},
  "geometry": {"coordinates":[4.7004728317,50.0936775208],"type":"Point"}
}