{
  "type": "Feature",
  "properties": {
    "addr:full":"Neustrasse 29 Raeren Li\u00e8ge 4730",
    "addr:housenumber":"29",
    "addr:postcode":"4730",
    "addr:street":"Neustrasse",
    "iso:country":"BE",
    "sg:address":"Neustrasse 29",
    "sg:city":"Raeren",
    "sg:orig_category":"Openbare bibliotheken and archieven",
    "sg:phone":"+32 87 85 10 30",
    "sg:postcode":"4730",
    "sg:province":"Li\u00e8ge",
    "wof:name":"Offentliche Bibliothek",
    "wof:placetype":"venue"
},
  "geometry": {"coordinates":[6.1063461304,50.6749572754],"type":"Point"}
}