{
  "type": "Feature",
  "properties": {
    "iso:country":"BE",
    "sg:address":"Rue Des Boutis 35 Box 3",
    "sg:city":"Ham-sur-heure-nalinnes (nalinnes)",
    "sg:orig_category":"Non-Classified Establishments",
    "sg:phone":"+32 475 25 29 51",
    "sg:postcode":"6120",
    "sg:province":"Hainaut",
    "wof:name":"Chimcoat",
    "wof:placetype":"venue"
},
  "geometry": {"coordinates":[4.4692769051,50.3373146057],"type":"Point"}
}