{
  "type": "Feature",
  "properties": {
    "addr:full":"Nieuwdekkenstraat 24 Sint-truiden Limburg 3800",
    "addr:housenumber":"24",
    "addr:postcode":"3800",
    "addr:street":"Nieuwdekkenstraat",
    "iso:country":"BE",
    "sg:address":"Nieuwdekkenstraat 24",
    "sg:city":"Sint-truiden",
    "sg:orig_category":"Woningbouw",
    "sg:phone":"+32 11 68 53 52",
    "sg:postcode":"3800",
    "sg:province":"Limburg",
    "wof:name":"Gijbels",
    "wof:placetype":"venue"
},
  "geometry": {"coordinates":[5.2550048828,50.8360404968],"type":"Point"}
}