{
  "type": "Feature",
  "properties": {
    "iso:country":"BE",
    "sg:address":"Rue Grande 38",
    "sg:city":"Yvoir",
    "sg:orig_category":"Installation \u00e9lectrique industrielle",
    "sg:phone":"+32 82 61 45 98",
    "sg:postcode":"5530",
    "sg:province":"Namur",
    "wof:name":"Inter Service",
    "wof:placetype":"venue"
},
  "geometry": {"coordinates":[4.8747048378,50.3505706787],"type":"Point"}
}