{
  "type": "Feature",
  "properties": {
    "addr:full":"Voortstraat 65 Beringen Limburg 3580",
    "addr:housenumber":"65",
    "addr:postcode":"3580",
    "addr:street":"Voortstraat",
    "iso:country":"BE",
    "sg:address":"Voortstraat 65",
    "sg:city":"Beringen",
    "sg:orig_category":"Herstellingen and onderhoud aan huis voor voertuigen Metaalafval, schrootrecyclage and sloperijen",
    "sg:phone":"+32 11 42 15 95",
    "sg:postcode":"3580",
    "sg:province":"Limburg",
    "wof:name":"T.c.b.",
    "wof:placetype":"venue"
},
  "geometry": {"coordinates":[5.2142457962,51.0570640564],"type":"Point"}
}