{
  "type": "Feature",
  "properties": {
    "addr:full":"Bellestraat 60ba Ieper West-Vlaanderen 8908",
    "addr:housenumber":"60ba",
    "addr:postcode":"8908",
    "addr:street":"Bellestraat",
    "iso:country":"BE",
    "sg:address":"Bellestraat 60ba",
    "sg:city":"Ieper",
    "sg:orig_category":"Stations-service and carburants. Constructions non r\u00e9sidentielles sp\u00e9cifiques",
    "sg:phone":"+32 57 20 04 94",
    "sg:postcode":"8908",
    "sg:province":"West-Vlaanderen",
    "wof:name":"Nestor Vanrobaeys",
    "wof:placetype":"venue"
},
  "geometry": {"coordinates":[2.8215909004,50.8516235352],"type":"Point"}
}