{
  "type": "Feature",
  "properties": {
    "iso:country":"BE",
    "sg:address":"Rue Du Fau Monin 27",
    "sg:city":"Ciney",
    "sg:orig_category":"Entretien and r\u00e9parations de voitures",
    "sg:phone":"+32 83 21 69 12",
    "sg:postcode":"5590",
    "sg:province":"Namur",
    "wof:name":"Agatino Virzi",
    "wof:placetype":"venue"
},
  "geometry": {"coordinates":[5.1383662224,50.3099555969],"type":"Point"}
}