{
  "type": "Feature",
  "properties": {
    "iso:country":"BE",
    "sg:address":"Peter Benoitlaan 58",
    "sg:city":"Veurne",
    "sg:classifiers":[
        {
            "category":"Social Services",
            "type":"Services"
        }
    ],
    "sg:phone":"+32 58 28 00 28",
    "sg:postcode":"8630",
    "sg:province":"West-Vlaanderen",
    "wof:name":"Caw De Papaver",
    "wof:placetype":"venue"
},
  "geometry": {"coordinates":[2.6594419479,51.0702323914],"type":"Point"}
}