{
  "type": "Feature",
  "properties": {
    "addr:full":"Koekoekstraat 1a Grobbendonk Antwerpen 2280",
    "addr:housenumber":"1a",
    "addr:postcode":"2280",
    "addr:street":"Koekoekstraat",
    "iso:country":"BE",
    "sg:address":"Koekoekstraat 1a",
    "sg:city":"Grobbendonk",
    "sg:classifiers":[
        {
            "category":"Home & Garden",
            "subcategory":"Building Materials",
            "type":"Retail Goods"
        }
    ],
    "sg:phone":"+32 14 51 82 26",
    "sg:postcode":"2280",
    "sg:province":"Antwerpen",
    "sg:tags":[
        "wall",
        "cupboard"
    ],
    "wof:name":"Van Laer D",
    "wof:placetype":"venue"
},
  "geometry": {"coordinates":[4.7290000916,51.1988639832],"type":"Point"}
}