{
  "type": "Feature",
  "properties": {
    "addr:full":"Chemin Des Pr\u00e9elles 28a Box 2 Mons Hainaut 7000",
    "addr:housenumber":"28a box 2",
    "addr:postcode":"7000",
    "addr:street":"Chemin Des Pre\u0301Elles;Hainaut",
    "iso:country":"BE",
    "sg:address":"Chemin Des Pr\u00e9elles 28a Box 2",
    "sg:city":"Mons",
    "sg:classifiers":[
        {
            "category":"Health Services",
            "subcategory":"Doctor",
            "type":"Services"
        }
    ],
    "sg:phone":"+32 65 31 41 01",
    "sg:postcode":"7000",
    "sg:province":"Hainaut",
    "sg:tags":[
        "medicinephysicians",
        "surgeon"
    ],
    "wof:name":"De Rooster Catherine",
    "wof:placetype":"venue"
},
  "geometry": {"coordinates":[3.9646320343,50.4500961304],"type":"Point"}
}