{
  "type": "Feature",
  "properties": {
    "addr:full":"Burg 18 Oudenaarde Oost-Vlaanderen 9700",
    "addr:housenumber":"18",
    "addr:postcode":"9700",
    "addr:street":"Burg",
    "iso:country":"BE",
    "sg:address":"Burg 18",
    "sg:city":"Oudenaarde",
    "sg:classifiers":[
        {
            "category":"Insurance",
            "subcategory":"Life Insurance",
            "type":"Services"
        }
    ],
    "sg:phone":"+32 55 31 04 80",
    "sg:postcode":"9700",
    "sg:province":"Oost-Vlaanderen",
    "sg:tags":[
        "assurance"
    ],
    "wof:name":"Van Nieuwenhove",
    "wof:placetype":"venue"
},
  "geometry": {"coordinates":[3.6051580906,50.8421173096],"type":"Point"}
}