{
  "type": "Feature",
  "properties": {
    "addr:full":"Ijzerstraat 14 Oostende West-Vlaanderen 8400",
    "addr:housenumber":"14",
    "addr:postcode":"8400",
    "addr:street":"Ijzerstraat",
    "iso:country":"BE",
    "sg:address":"Ijzerstraat 14",
    "sg:city":"Oostende",
    "sg:orig_category":"DIVERSE RECREATIEVE ACTIVITEITEN",
    "sg:phone":"+32 59 70 03 76",
    "sg:postcode":"8400",
    "sg:province":"West-Vlaanderen",
    "wof:name":"Bridge Club Oostende",
    "wof:placetype":"venue"
},
  "geometry": {"coordinates":[2.9125380516,51.2292976379],"type":"Point"}
}