{
  "type": "Feature",
  "properties": {
    "addr:full":"Kanaalstraat 18 Lokeren Oost-Vlaanderen 9160",
    "addr:housenumber":"18",
    "addr:postcode":"9160",
    "addr:street":"Kanaalstraat",
    "iso:country":"BE",
    "sg:address":"Kanaalstraat 18",
    "sg:city":"Lokeren",
    "sg:classifiers":[
        {
            "category":"Social Services",
            "type":"Services"
        }
    ],
    "sg:phone":"+32 9 349 16 15",
    "sg:postcode":"9160",
    "sg:province":"Oost-Vlaanderen",
    "wof:name":"Vuurwerk",
    "wof:placetype":"venue"
},
  "geometry": {"coordinates":[4.0029230118,51.0971107483],"type":"Point"}
}