{
  "type": "Feature",
  "properties": {
    "iso:country":"BE",
    "sg:address":"Rue Des Martyrs 43",
    "sg:city":"Arlon",
    "sg:classifiers":[
        {
            "category":"Health Services",
            "subcategory":"Dentist",
            "type":"Services"
        }
    ],
    "sg:phone":"+32 63 21 92 45",
    "sg:postcode":"6700",
    "sg:province":"Luxembourg",
    "wof:name":"Doupagne-humblet Martine",
    "wof:placetype":"venue"
},
  "geometry": {"coordinates":[5.8087639809,49.6834373474],"type":"Point"}
}