{
  "type": "Feature",
  "properties": {
    "addr:full":"Turnhoutsebaan 52 Schilde Antwerpen 2970",
    "addr:housenumber":"52",
    "addr:postcode":"2970",
    "addr:street":"Turnhoutsebaan",
    "iso:country":"BE",
    "sg:address":"Turnhoutsebaan 52",
    "sg:city":"Schilde",
    "sg:orig_category":"Slagers",
    "sg:phone":"+32 3 353 60 87",
    "sg:postcode":"2970",
    "sg:province":"Antwerpen",
    "wof:name":"Johannes Van Daele",
    "wof:placetype":"venue"
},
  "geometry": {"coordinates":[4.5561990738,51.2321739197],"type":"Point"}
}