{
  "type": "Feature",
  "properties": {
    "iso:country":"BE",
    "sg:address":"Rue De La Clef 5",
    "sg:city":"Mons",
    "sg:classifiers":[
        {
            "category":"Banks & Credit Unions",
            "subcategory":"Investment Brokerage",
            "type":"Services"
        }
    ],
    "sg:phone":"+32 65 35 14 66",
    "sg:postcode":"7000",
    "sg:province":"Hainaut",
    "sg:tags":[
        "printing",
        "-"
    ],
    "wof:name":"Grasselli Daniel",
    "wof:placetype":"venue"
},
  "geometry": {"coordinates":[3.9528419971,50.4536895752],"type":"Point"}
}