{
  "type": "Feature",
  "properties": {
    "addr:full":"Rue Roosevelt 17 Herve Li\u00e8ge 4650",
    "addr:housenumber":"17",
    "addr:postcode":"4650",
    "addr:street":"Rue Roosevelt",
    "iso:country":"BE",
    "sg:address":"Rue Roosevelt 17",
    "sg:city":"Herve",
    "sg:classifiers":[
        {
            "category":"Professional",
            "subcategory":"Testing Lab",
            "type":"Services"
        }
    ],
    "sg:phone":"+32 87 67 40 48",
    "sg:postcode":"4650",
    "sg:province":"Li\u00e8ge",
    "sg:tags":[
        "chemist"
    ],
    "wof:name":"Stassen A-c",
    "wof:placetype":"venue"
},
  "geometry": {"coordinates":[5.7937169075,50.6388053894],"type":"Point"}
}