{
  "type": "Feature",
  "properties": {
    "addr:full":"Bistweg 80 Ranst (broechem) Antwerpen 2520",
    "addr:housenumber":"80",
    "addr:postcode":"2520",
    "addr:street":"Bistweg",
    "iso:country":"BE",
    "sg:address":"Bistweg 80",
    "sg:city":"Ranst (broechem)",
    "sg:classifiers":[
        {
            "category":"Home & Garden",
            "subcategory":"Building Materials",
            "type":"Retail Goods"
        }
    ],
    "sg:phone":"+32 3 470 12 12",
    "sg:postcode":"2520",
    "sg:province":"Antwerpen",
    "sg:tags":[
        "insulation",
        "thermical"
    ],
    "wof:name":"Albintra Nv",
    "wof:placetype":"venue"
},
  "geometry": {"coordinates":[4.6187791824,51.1878433228],"type":"Point"}
}