{
  "type": "Feature",
  "properties": {
    "addr:full":"Spoorwegstraat 3 Turnhout Antwerpen 2300",
    "addr:housenumber":"3",
    "addr:postcode":"2300",
    "addr:street":"Spoorwegstraat",
    "iso:country":"BE",
    "sg:address":"Spoorwegstraat 3",
    "sg:city":"Turnhout",
    "sg:classifiers":[
        {
            "category":"Shopping",
            "subcategory":"Computers & Home Electronics",
            "type":"Retail Goods"
        }
    ],
    "sg:phone":"+32 14 41 49 12",
    "sg:postcode":"2300",
    "sg:province":"Antwerpen",
    "sg:tags":[
        "-",
        "television",
        "radio"
    ],
    "wof:name":"Hifi Vid\u00e9o Center Nv",
    "wof:placetype":"venue"
},
  "geometry": {"coordinates":[4.9375901222,51.3212966919],"type":"Point"}
}