{
  "type": "Feature",
  "properties": {
    "iso:country":"BE",
    "sg:address":"Rue Grande 12",
    "sg:city":"Florenville",
    "sg:orig_category":"Boucheries",
    "sg:phone":"+32 61 31 16 32",
    "sg:postcode":"6820",
    "sg:province":"Luxembourg",
    "wof:name":"P. Jehenson",
    "wof:placetype":"venue"
},
  "geometry": {"coordinates":[5.1749000549,49.7162094116],"type":"Point"}
}