{
  "type": "Feature",
  "properties": {
    "iso:country":"BE",
    "sg:address":"Vijfseweg 152",
    "sg:city":"Waregem",
    "sg:orig_category":"Immobili\u00ebnkantoren",
    "sg:phone":"+32 56 60 28 98",
    "sg:postcode":"8790",
    "sg:province":"West-Vlaanderen",
    "wof:name":"Ysowe",
    "wof:placetype":"venue"
},
  "geometry": {"coordinates":[3.4166269302,50.8996162415],"type":"Point"}
}