{
  "type": "Feature",
  "properties": {
    "iso:country":"BE",
    "sg:address":"Rue Du Centre 0",
    "sg:city":"Neufchateau",
    "sg:orig_category":"Enseignement maternel and primaire",
    "sg:phone":"+32 61 27 93 32",
    "sg:postcode":"6840",
    "sg:province":"Luxembourg",
    "wof:name":"Ecole Fond. Communale",
    "wof:placetype":"venue"
},
  "geometry": {"coordinates":[5.4346451759,49.8411598206],"type":"Point"}
}