{
  "type": "Feature",
  "properties": {
    "addr:full":"63 G. Demeurslaan 1654 Beersel Huizingen 63",
    "addr:housenumber":"63",
    "addr:postcode":"1654",
    "addr:street":"G. Demeurslaan",
    "iso:country":"BE",
    "sg:address":"63",
    "sg:city":"G. Demeurslaan 1654 Beersel Huizingen",
    "sg:classifiers":[
        {
            "category":"Wholesale",
            "subcategory":"Meat",
            "type":"Manufacturing & Wholesale Goods"
        }
    ],
    "sg:phone":"+32 2 361 35 14",
    "sg:postcode":"63",
    "sg:tags":[
        "food",
        "cooked",
        "product",
        "related"
    ],
    "wof:name":"Blancke Produktie Nv",
    "wof:placetype":"venue"
},
  "geometry": {"coordinates":[4.2667608261,50.7532844543],"type":"Point"}
}