{
  "type": "Feature",
  "properties": {
    "addr:full":"Dr\u00c8ve Du Carmel 24 Waterloo Brabant Wallon 1410",
    "addr:housenumber":"24",
    "addr:postcode":"1410",
    "addr:street":"Dre\u0300Ve Du Carmel",
    "iso:country":"BE",
    "sg:address":"Dr\u00c8ve Du Carmel 24",
    "sg:city":"Waterloo",
    "sg:orig_category":"Boekbinderijen and afwerking",
    "sg:phone":"+32 2 351 12 90",
    "sg:postcode":"1410",
    "sg:province":"Brabant Wallon",
    "wof:name":"Carmelites D'argenteuil",
    "wof:placetype":"venue"
},
  "geometry": {"coordinates":[4.4386510849,50.7137794495],"type":"Point"}
}