{
  "type": "Feature",
  "properties": {
    "addr:full":"1070 Anderlecht (brussel) Bruxelles-Capitale 1070",
    "addr:postcode":"1070;1070",
    "iso:country":"BE",
    "sg:address":"1070",
    "sg:city":"Anderlecht (brussel)",
    "sg:orig_category":"Pharmaciens",
    "sg:phone":"+32 900 10 500",
    "sg:postcode":"1070",
    "sg:province":"Bruxelles-Capitale",
    "wof:name":"Pharmacies De Garde",
    "wof:placetype":"venue"
},
  "geometry": {"coordinates":[4.3296580315,50.8392295837],"type":"Point"}
}