{
  "type": "Feature",
  "properties": {
    "addr:full":"Place Saint-martin 8 Beauvechain Brabant Wallon 1320",
    "addr:housenumber":"8",
    "addr:postcode":"1320",
    "addr:street":"Place Saint-Martin",
    "iso:country":"BE",
    "sg:address":"Place Saint-martin 8",
    "sg:city":"Beauvechain",
    "sg:orig_category":"Woningbouw",
    "sg:phone":"+32 10 86 09 50",
    "sg:postcode":"1320",
    "sg:province":"Brabant Wallon",
    "wof:name":"G. Lenaerts",
    "wof:placetype":"venue"
},
  "geometry": {"coordinates":[4.7097520828,50.7757301331],"type":"Point"}
}