{
  "type": "Feature",
  "properties": {
    "addr:full":"Rue Des D\u00c9port\u00c9s 50 Arlon Luxembourg 6700",
    "addr:housenumber":"50",
    "addr:postcode":"6700",
    "addr:street":"Rue Des De\u0301Porte\u0301S",
    "iso:country":"BE",
    "sg:address":"Rue Des D\u00c9port\u00c9s 50",
    "sg:city":"Arlon",
    "sg:orig_category":"Air conditionn\u00e9 and ventilation. Plomberie, chauffage and installations sanitaires",
    "sg:phone":"+32 63 22 28 36",
    "sg:postcode":"6700",
    "sg:province":"Luxembourg",
    "wof:name":"Montenay",
    "wof:placetype":"venue"
},
  "geometry": {"coordinates":[5.8208508492,49.6791954041],"type":"Point"}
}