{
  "type": "Feature",
  "properties": {
    "addr:full":"Burgemeestersstraat 32a Heers Limburg 3870",
    "addr:housenumber":"32a",
    "addr:postcode":"3870",
    "addr:street":"Burgemeestersstraat",
    "iso:country":"BE",
    "sg:address":"Burgemeestersstraat 32a",
    "sg:city":"Heers",
    "sg:orig_category":"Installation de menuiserie m\u00e9tallique. Quincailleries. Bois Gr",
    "sg:phone":"+32 11 48 18 85",
    "sg:postcode":"3870",
    "sg:province":"Limburg",
    "wof:name":"Houthandel Hebo",
    "wof:placetype":"venue"
},
  "geometry": {"coordinates":[5.2621622086,50.73802948],"type":"Point"}
}