{
  "type": "Feature",
  "properties": {
    "iso:country":"BE",
    "sg:address":"Joseph Vanhellemontln 11b1a",
    "sg:city":"Anderlecht",
    "sg:orig_category":"Artsen and specialisten",
    "sg:phone":"+32 2 523 76 36",
    "sg:postcode":"1070",
    "sg:province":"Bruxelles-Capitale",
    "wof:name":"Mohammed Salah Ouertani",
    "wof:placetype":"venue"
},
  "geometry": {"coordinates":[4.2858738899,50.8304176331],"type":"Point"}
}