{
  "type": "Feature",
  "properties": {
    "addr:full":"Kasteelplein 8 Turnhout Antwerpen 2300",
    "addr:housenumber":"8",
    "addr:postcode":"2300",
    "addr:street":"Kasteelplein",
    "iso:country":"BE",
    "sg:address":"Kasteelplein 8",
    "sg:city":"Turnhout",
    "sg:classifiers":[
        {
            "category":"Cafe",
            "type":"Food & Drink"
        }
    ],
    "sg:phone":"+32 14 42 29 17",
    "sg:postcode":"2300",
    "sg:province":"Antwerpen",
    "sg:tags":[
        "caf\u00e9s"
    ],
    "wof:name":"Caf\u00c9 't Kasteeltje",
    "wof:placetype":"venue"
},
  "geometry": {"coordinates":[4.9450669289,51.3359909058],"type":"Point"}
}