{
  "type": "Feature",
  "properties": {
    "addr:full":"Gentseweg 1 Waregem West-Vlaanderen 8792",
    "addr:housenumber":"1",
    "addr:postcode":"8792",
    "addr:street":"Gentseweg",
    "iso:country":"BE",
    "sg:address":"Gentseweg 1",
    "sg:city":"Waregem",
    "sg:orig_category":"Beheer onroerend goed Immobili\u00ebnkantoren",
    "sg:phone":"+32 56 72 83 38",
    "sg:postcode":"8792",
    "sg:province":"West-Vlaanderen",
    "wof:name":"Immoburo Termote",
    "wof:placetype":"venue"
},
  "geometry": {"coordinates":[3.3594689369,50.8802185059],"type":"Point"}
}