{
  "type": "Feature",
  "properties": {
    "iso:country":"BE",
    "sg:address":"Rue Thi\u00c9fry 66",
    "sg:city":"Schaarbeek/schaerbeek",
    "sg:orig_category":"Epiceries",
    "sg:phone":"+32 2 215 94 41",
    "sg:postcode":"1030",
    "sg:province":"Bruxelles-Capitale",
    "wof:name":"Hasan Yilmaz",
    "wof:placetype":"venue"
},
  "geometry": {"coordinates":[4.3765068054,50.8585624695],"type":"Point"}
}