{
  "type": "Feature",
  "properties": {
    "iso:country":"BE",
    "sg:address":"Rue Les Moux 26",
    "sg:city":"Walcourt",
    "sg:classifiers":[
        {
            "category":"Insurance",
            "subcategory":"Life Insurance",
            "type":"Services"
        }
    ],
    "sg:phone":"+32 71 65 00 29",
    "sg:postcode":"5651",
    "sg:province":"Namur",
    "sg:tags":[
        "assurance"
    ],
    "wof:name":"C. Dandois",
    "wof:placetype":"venue"
},
  "geometry": {"coordinates":[4.4262080193,50.2824401855],"type":"Point"}
}