{
  "type": "Feature",
  "properties": {
    "addr:full":"Grand\u00b4rue 75 Charleroi Hainaut 6061",
    "addr:housenumber":"75",
    "addr:postcode":"6061",
    "addr:street":"Grand\u00b4Rue;Hainaut",
    "iso:country":"BE",
    "sg:address":"Grand\u00b4rue 75",
    "sg:city":"Charleroi",
    "sg:classifiers":[
        {
            "category":"Restaurant",
            "type":"Food & Drink"
        }
    ],
    "sg:phone":"+32 71 70 23 77",
    "sg:postcode":"6061",
    "sg:province":"Hainaut",
    "sg:tags":[
        "caf\u00e9s"
    ],
    "wof:name":"Taverne Tassili",
    "wof:placetype":"venue"
},
  "geometry": {"coordinates":[4.4591808319,50.4133872986],"type":"Point"}
}