{
  "type": "Feature",
  "properties": {
    "iso:country":"BE",
    "sg:address":"Hoogweg 79",
    "sg:city":"Wervik",
    "sg:classifiers":[
        {
            "category":"Personal",
            "subcategory":"Beauty Salon",
            "type":"Services"
        }
    ],
    "sg:phone":"+32 56 31 48 35",
    "sg:postcode":"8940",
    "sg:province":"West-Vlaanderen",
    "sg:tags":[
        "lady",
        "-",
        "hairdressing"
    ],
    "wof:name":"Soenen P",
    "wof:placetype":"venue"
},
  "geometry": {"coordinates":[3.0580079556,50.7897644043],"type":"Point"}
}