{
  "type": "Feature",
  "properties": {
    "iso:country":"BE",
    "sg:address":"Hoogweg 56",
    "sg:city":"Wingene",
    "sg:orig_category":"Eleveurs de volaille. Eleveurs and marchands de porcs. Eleveurs de bovins",
    "sg:phone":"+32 51 65 57 09",
    "sg:postcode":"8750",
    "sg:province":"West-Vlaanderen",
    "wof:name":"Roger Vermeersch",
    "wof:placetype":"venue"
},
  "geometry": {"coordinates":[3.29697299,51.0651741028],"type":"Point"}
}