{
  "type": "Feature",
  "properties": {
    "addr:full":"Industrieweg 18 Lanaken Limburg 3620",
    "addr:housenumber":"18",
    "addr:postcode":"3620",
    "addr:street":"Industrieweg",
    "iso:country":"BE",
    "sg:address":"Industrieweg 18",
    "sg:city":"Lanaken",
    "sg:classifiers":[
        {
            "category":"Autos & Motor Vehicles",
            "subcategory":"Automobile Sales",
            "type":"Retail Goods"
        }
    ],
    "sg:phone":"+32 89 73 16 26",
    "sg:postcode":"3620",
    "sg:province":"Limburg",
    "sg:tags":[
        "motorhomes",
        "accessory"
    ],
    "wof:name":"Vsg Nubri",
    "wof:placetype":"venue"
},
  "geometry": {"coordinates":[5.667828083,50.891418457],"type":"Point"}
}