{
  "type": "Feature",
  "properties": {
    "addr:full":"Place Du Sablon 11a Gembloux Namur 5030",
    "addr:housenumber":"11a",
    "addr:postcode":"5030",
    "addr:street":"Place Du Sablon;Namur",
    "iso:country":"BE",
    "sg:address":"Place Du Sablon 11a",
    "sg:city":"Gembloux",
    "sg:classifiers":[
        {
            "category":"Arena",
            "subcategory":"Sports Club",
            "type":"Entertainment"
        }
    ],
    "sg:phone":"+32 81 61 27 47",
    "sg:postcode":"5030",
    "sg:province":"Namur",
    "sg:tags":[
        "de"
    ],
    "wof:name":"Volley Club Sauveni\u00c8re",
    "wof:placetype":"venue"
},
  "geometry": {"coordinates":[4.7251729965,50.5815620422],"type":"Point"}
}