{
  "type": "Feature",
  "properties": {
    "addr:full":"Keizer Karellaan 77 Ganshoren Bruxelles-Capitale 1083",
    "addr:housenumber":"77",
    "addr:postcode":"1083",
    "addr:street":"Keizer Karellaan",
    "iso:country":"BE",
    "sg:address":"Keizer Karellaan 77",
    "sg:city":"Ganshoren",
    "sg:orig_category":"Woningbouw",
    "sg:phone":"+32 495 43 51 48",
    "sg:postcode":"1083",
    "sg:province":"Bruxelles-Capitale",
    "wof:name":"B. Company Entreprises",
    "wof:placetype":"venue"
},
  "geometry": {"coordinates":[4.3119258881,50.8683776855],"type":"Point"}
}