{
  "type": "Feature",
  "properties": {
    "iso:country":"BE",
    "sg:address":"Diependaele 28",
    "sg:city":"Deerlijk",
    "sg:classifiers":[
        {
            "category":"Manufacturing",
            "subcategory":"Textiles",
            "type":"Manufacturing & Wholesale Goods"
        }
    ],
    "sg:phone":"+32 56 71 26 55",
    "sg:postcode":"8540",
    "sg:province":"West-Vlaanderen",
    "sg:tags":[
        "spinning",
        "weaving",
        "mill"
    ],
    "wof:name":"Markritex Bvba",
    "wof:placetype":"venue"
},
  "geometry": {"coordinates":[3.3685851097,50.8545188904],"type":"Point"}
}