{
  "type": "Feature",
  "properties": {
    "iso:country":"BE",
    "sg:address":"Rue Winston Churchill 156",
    "sg:city":"Courcelles",
    "sg:classifiers":[
        {
            "category":"Personal",
            "subcategory":"Beauty Salon",
            "type":"Services"
        }
    ],
    "sg:phone":"+32 71 46 26 14",
    "sg:postcode":"6180",
    "sg:province":"Hainaut",
    "sg:tags":[
        "lady",
        "-",
        "hairdressing"
    ],
    "wof:name":"Fr\u00e9d\u00e9ric Coiffure Visagist",
    "wof:placetype":"venue"
},
  "geometry": {"coordinates":[4.3918800354,50.462890625],"type":"Point"}
}