{
  "type": "Feature",
  "properties": {
    "addr:full":"Chauss\u00c9e De Marche 659 Namen Namur 5100",
    "addr:housenumber":"659",
    "addr:postcode":"5100",
    "addr:street":"Chausse\u0301E De Marche",
    "iso:country":"BE",
    "sg:address":"Chauss\u00c9e De Marche 659",
    "sg:city":"Namen",
    "sg:orig_category":"Motoren, transformatoren and generatoren Fab Tuinbenodigdheden",
    "sg:phone":"+32 81 40 19 20",
    "sg:postcode":"5100",
    "sg:province":"Namur",
    "wof:name":"Lange Christian",
    "wof:placetype":"venue"
},
  "geometry": {"coordinates":[4.8713750839,50.4566345215],"type":"Point"}
}