{
  "type": "Feature",
  "properties": {
    "iso:country":"BE",
    "sg:address":"Toekomstlaan 22",
    "sg:city":"Schoten",
    "sg:orig_category":"Diverse bouwafwerking and reiniging",
    "sg:phone":"+32 3 647 01 60",
    "sg:postcode":"2900",
    "sg:province":"Antwerpen",
    "wof:name":"Euro Blast Belgie",
    "wof:placetype":"venue"
},
  "geometry": {"coordinates":[4.4601159096,51.2424545288],"type":"Point"}
}