{
  "type": "Feature",
  "properties": {
    "addr:full":"Diepestraat 46 Hove Antwerpen 2540",
    "addr:housenumber":"46",
    "addr:postcode":"2540",
    "addr:street":"Diepestraat",
    "iso:country":"BE",
    "sg:address":"Diepestraat 46",
    "sg:city":"Hove",
    "sg:orig_category":"Film-, tv- and videoproductie",
    "sg:phone":"+32 3 454 14 08",
    "sg:postcode":"2540",
    "sg:province":"Antwerpen",
    "wof:name":"Sigmacam",
    "wof:placetype":"venue"
},
  "geometry": {"coordinates":[4.4831199646,51.1487159729],"type":"Point"}
}