{
  "type": "Feature",
  "properties": {
    "iso:country":"BE",
    "sg:address":"Rue Alfred Cluysenaar 22",
    "sg:city":"Sint-gillis/saint-gilles",
    "sg:orig_category":"Studios photographiques",
    "sg:phone":"+32 2 538 84 97",
    "sg:postcode":"1060",
    "sg:province":"Bruxelles-Capitale",
    "wof:name":"Yves Fonck",
    "wof:placetype":"venue"
},
  "geometry": {"coordinates":[4.3420009613,50.8249435425],"type":"Point"}
}