{
  "type": "Feature",
  "properties": {
    "addr:full":"Steenstraat 20 Box 1 Vilvoorde Vlaams-Brabant 1800",
    "addr:housenumber":"20;1",
    "addr:postcode":"1800",
    "addr:street":"Steenstraat;Box",
    "iso:country":"BE",
    "sg:address":"Steenstraat 20 Box 1",
    "sg:city":"Vilvoorde",
    "sg:classifiers":[
        {
            "category":"Utilities",
            "subcategory":"Refuse",
            "type":"Services"
        }
    ],
    "sg:phone":"+32 2 263 66 11",
    "sg:postcode":"1800",
    "sg:province":"Vlaams-Brabant",
    "sg:tags":[
        "removal"
    ],
    "wof:name":"Iss Facility Services",
    "wof:placetype":"venue"
},
  "geometry": {"coordinates":[4.3804030418,50.9064025879],"type":"Point"}
}