{
  "type": "Feature",
  "properties": {
    "iso:country":"BE",
    "sg:address":"Erikalaan 9",
    "sg:city":"Rotselaar",
    "sg:orig_category":"Services pour animaux domestiques",
    "sg:phone":"+32 16 58 52 24",
    "sg:postcode":"3110",
    "sg:province":"Vlaams-Brabant",
    "wof:name":"Beloningsgerichte Hondentraining Whisper",
    "wof:placetype":"venue"
},
  "geometry": {"coordinates":[4.7107920647,50.9508590698],"type":"Point"}
}