{
  "type": "Feature",
  "properties": {
    "iso:country":"BE",
    "sg:address":"B\u00c9verc\u00c9 43bb",
    "sg:city":"Malmedy/malmedy",
    "sg:orig_category":"Avocats and conseillers juridiques",
    "sg:phone":"+32 80 77 12 26",
    "sg:postcode":"4960",
    "sg:province":"Li\u00e8ge",
    "wof:name":"A. Baumel",
    "wof:placetype":"venue"
},
  "geometry": {"coordinates":[6.0551772118,50.37657547],"type":"Point"}
}