{
  "type": "Feature",
  "properties": {
    "iso:country":"BE",
    "sg:address":"Avenue Batta 12",
    "sg:city":"Huy",
    "sg:orig_category":"Bloemen and planten",
    "sg:phone":"+32 85 25 44 15",
    "sg:postcode":"4500",
    "sg:province":"Li\u00e8ge",
    "wof:name":"Maison Florilys",
    "wof:placetype":"venue"
},
  "geometry": {"coordinates":[5.2353019714,50.519443512],"type":"Point"}
}