{
  "type": "Feature",
  "properties": {
    "iso:country":"BE",
    "sg:address":"Rue Ch\u00c8re-voie 24",
    "sg:city":"Sambreville",
    "sg:orig_category":"Kapsalons",
    "sg:phone":"+32 71 76 03 93",
    "sg:postcode":"5060",
    "sg:province":"Namur",
    "wof:name":"Manipulation",
    "wof:placetype":"venue"
},
  "geometry": {"coordinates":[4.6283512115,50.4363212585],"type":"Point"}
}