{
  "type": "Feature",
  "properties": {
    "iso:country":"BE",
    "sg:address":"200",
    "sg:city":"Rue Du Cerf 1330 Rixensart",
    "sg:classifiers":[
        {
            "category":"Shopping",
            "subcategory":"Stationery & Office Supplies",
            "type":"Retail Goods"
        }
    ],
    "sg:phone":"+32 2 654 08 85",
    "sg:postcode":"200",
    "sg:tags":[
        "information",
        "technology",
        "telecommunication",
        "equipment"
    ],
    "wof:name":"Apx Computer Belgium Sa",
    "wof:placetype":"venue"
},
  "geometry": {"coordinates":[4.5332751274,50.7153015137],"type":"Point"}
}