{
  "type": "Feature",
  "properties": {
    "addr:full":"Rue De Cheratte 27 Vivegnis Li\u00e8ge 4683",
    "addr:housenumber":"27",
    "addr:postcode":"4683",
    "addr:street":"Rue De Cheratte",
    "iso:country":"BE",
    "sg:address":"Rue De Cheratte 27",
    "sg:city":"Vivegnis",
    "sg:classifiers":[
        {
            "category":"Professional",
            "subcategory":"Engineering",
            "type":"Services"
        }
    ],
    "sg:phone":"+32 4 256 90 69",
    "sg:postcode":"4683",
    "sg:province":"Li\u00e8ge",
    "sg:tags":[
        "machine",
        "-",
        "mechanical"
    ],
    "wof:name":"Britte Sa",
    "wof:placetype":"venue"
},
  "geometry": {"coordinates":[5.6540589333,50.6963882446],"type":"Point"}
}