{
  "type": "Feature",
  "properties": {
    "iso:country":"BE",
    "sg:address":"Leopoldslei 99",
    "sg:city":"Brasschaat",
    "sg:orig_category":"Plomberie, chauffage and installations sanitaires",
    "sg:phone":"+32 3 651 88 93",
    "sg:postcode":"2930",
    "sg:province":"Antwerpen",
    "wof:name":"Centrale Verwarm. Select",
    "wof:placetype":"venue"
},
  "geometry": {"coordinates":[4.4851131439,51.2932243347],"type":"Point"}
}