{
  "type": "Feature",
  "properties": {
    "iso:country":"BE",
    "sg:address":"Rue Tiennes Aux Grives 18",
    "sg:city":"Andenne (sclayn)",
    "sg:classifiers":[
        {
            "category":"Retail",
            "subcategory":"Veterinary Services",
            "type":"Services"
        }
    ],
    "sg:phone":"+32 81 58 20 44",
    "sg:postcode":"5300",
    "sg:province":"Namur",
    "sg:tags":[
        "veterinarian"
    ],
    "wof:name":"Houtain J-y",
    "wof:placetype":"venue"
},
  "geometry": {"coordinates":[5.0391130447,50.4903335571],"type":"Point"}
}