{
  "type": "Feature",
  "properties": {
    "addr:full":"Avenue De La Roseraie 28 Rixensart Brabant Wallon 1330",
    "addr:housenumber":"28",
    "addr:postcode":"1330",
    "addr:street":"Avenue De La Roseraie;Wallon",
    "iso:country":"BE",
    "sg:address":"Avenue De La Roseraie 28",
    "sg:city":"Rixensart",
    "sg:classifiers":[
        {
            "category":"Professional",
            "subcategory":"Management & Consulting",
            "type":"Services"
        }
    ],
    "sg:phone":"+32 2 652 44 06",
    "sg:postcode":"1330",
    "sg:province":"Brabant Wallon",
    "sg:tags":[
        "-",
        "processing",
        "data",
        "consultant"
    ],
    "wof:name":"Mediaconsult",
    "wof:placetype":"venue"
},
  "geometry": {"coordinates":[4.5250740051,50.7227363586],"type":"Point"}
}