{
  "type": "Feature",
  "properties": {
    "addr:full":"Oude-vaartplaats 26 Antwerpen Antwerpen 2000",
    "addr:housenumber":"26",
    "addr:postcode":"2000",
    "addr:street":"Oude-Vaartplaats",
    "iso:country":"BE",
    "sg:address":"Oude-vaartplaats 26",
    "sg:city":"Antwerpen",
    "sg:classifiers":[
        {
            "category":"Bars & Pubs",
            "type":"Food & Drink"
        }
    ],
    "sg:phone":"+32 3 226 14 39",
    "sg:postcode":"2000",
    "sg:province":"Antwerpen",
    "sg:tags":[
        "tavern"
    ],
    "wof:name":"Falstaff",
    "wof:placetype":"venue"
},
  "geometry": {"coordinates":[4.4088730812,51.2146682739],"type":"Point"}
}