{
  "type": "Feature",
  "properties": {
    "iso:country":"BE",
    "sg:address":"Baljuwstraat 66",
    "sg:city":"Poperinge",
    "sg:orig_category":"Herstellingen and onderhoud van auto's",
    "sg:phone":"+32 57 33 44 58",
    "sg:postcode":"8970",
    "sg:province":"West-Vlaanderen",
    "wof:name":"Garage Gouwy",
    "wof:placetype":"venue"
},
  "geometry": {"coordinates":[2.7550830841,50.8224868774],"type":"Point"}
}