{
  "type": "Feature",
  "properties": {
    "iso:country":"BE",
    "sg:address":"Avenue Emile Vandervelde 11",
    "sg:city":"Ch\u00e2telet",
    "sg:classifiers":[
        {
            "category":"Building & Trades",
            "subcategory":"Construction",
            "type":"Services"
        }
    ],
    "sg:phone":"+32 71 38 91 70",
    "sg:postcode":"6200",
    "sg:province":"Hainaut",
    "sg:tags":[
        "carpenter"
    ],
    "wof:name":"Di Nardo",
    "wof:placetype":"venue"
},
  "geometry": {"coordinates":[4.5205302238,50.396320343],"type":"Point"}
}