{
  "type": "Feature",
  "properties": {
    "addr:full":"Markt 16 Beringen Limburg 3580",
    "addr:housenumber":"16",
    "addr:postcode":"3580",
    "addr:street":"Markt",
    "iso:country":"BE",
    "sg:address":"Markt 16",
    "sg:city":"Beringen",
    "sg:orig_category":"Blanchisseries and teintureries",
    "sg:phone":"+32 11 42 24 50",
    "sg:postcode":"3580",
    "sg:province":"Limburg",
    "wof:name":"Droogkuis Janssens",
    "wof:placetype":"venue"
},
  "geometry": {"coordinates":[5.2252149582,51.0478439331],"type":"Point"}
}