{
  "type": "Feature",
  "properties": {
    "addr:full":"Sneppestraat 1 Maarkedal Oost-Vlaanderen 9680",
    "addr:housenumber":"1",
    "addr:postcode":"9680",
    "addr:street":"Sneppestraat",
    "iso:country":"BE",
    "sg:address":"Sneppestraat 1",
    "sg:city":"Maarkedal",
    "sg:orig_category":"Eleveurs de bovins",
    "sg:phone":"+32 55 45 55 68",
    "sg:postcode":"9680",
    "sg:province":"Oost-Vlaanderen",
    "wof:name":"Paul Pot",
    "wof:placetype":"venue"
},
  "geometry": {"coordinates":[3.6563661098,50.7949676514],"type":"Point"}
}