{
  "type": "Feature",
  "properties": {
    "addr:full":"Marie-jos\u00c9laan 6 De Haan West-Vlaanderen 8421",
    "addr:housenumber":"6",
    "addr:postcode":"8421",
    "addr:street":"Marie-Jose\u0301Laan",
    "iso:country":"BE",
    "sg:address":"Marie-jos\u00c9laan 6",
    "sg:city":"De Haan",
    "sg:orig_category":"M\u00e9decins and sp\u00e9cialistes",
    "sg:phone":"+32 59 23 50 54",
    "sg:postcode":"8421",
    "sg:province":"West-Vlaanderen",
    "wof:name":"Hilde Franckx",
    "wof:placetype":"venue"
},
  "geometry": {"coordinates":[3.037758112,51.2785263062],"type":"Point"}
}