{
  "type": "Feature",
  "properties": {
    "addr:full":"Parvis Saint-pierre 13ba Wezembeek-oppem Vlaams-Brabant 1970",
    "addr:housenumber":"13ba",
    "addr:postcode":"1970",
    "addr:street":"Parvis Saint-Pierre",
    "iso:country":"BE",
    "sg:address":"Parvis Saint-pierre 13ba",
    "sg:city":"Wezembeek-oppem",
    "sg:classifiers":[
        {
            "category":"Taxi",
            "type":"Transportation"
        }
    ],
    "sg:phone":"+32 2 731 90 00",
    "sg:postcode":"1970",
    "sg:province":"Vlaams-Brabant",
    "sg:tags":[
        "sp\u00e9ciaux"
    ],
    "wof:name":"A.d. Limousine",
    "wof:placetype":"venue"
},
  "geometry": {"coordinates":[4.4947252274,50.8406791687],"type":"Point"}
}