{
  "type": "Feature",
  "properties": {
    "iso:country":"BE",
    "sg:address":"Kehrweg 11",
    "sg:city":"Eupen/eupen",
    "sg:orig_category":"Radioproductie and uitzendingen",
    "sg:phone":"+32 87 59 11 11",
    "sg:postcode":"4700",
    "sg:province":"Li\u00e8ge",
    "wof:name":"B.r.f.",
    "wof:placetype":"venue"
},
  "geometry": {"coordinates":[6.0439100266,50.626121521],"type":"Point"}
}