{
  "type": "Feature",
  "properties": {
    "addr:full":"Zamenhoflaan 5 Schoten Antwerpen 2900",
    "addr:housenumber":"5",
    "addr:postcode":"2900",
    "addr:street":"Zamenhoflaan",
    "iso:country":"BE",
    "sg:address":"Zamenhoflaan 5",
    "sg:city":"Schoten",
    "sg:orig_category":"M\u00e9decines alternatives",
    "sg:phone":"+32 3 658 76 34",
    "sg:postcode":"2900",
    "sg:province":"Antwerpen",
    "wof:name":"Marc Mollekens - Baf",
    "wof:placetype":"venue"
},
  "geometry": {"coordinates":[4.4998679161,51.2532348633],"type":"Point"}
}