{
  "type": "Feature",
  "properties": {
    "addr:full":"Blancefloerlaan 50 Antwerpen Antwerpen 2050",
    "addr:housenumber":"50",
    "addr:postcode":"2050",
    "addr:street":"Blancefloerlaan",
    "iso:country":"BE",
    "sg:address":"Blancefloerlaan 50",
    "sg:city":"Antwerpen",
    "sg:orig_category":"Industri\u00eble and commerci\u00eble bouw",
    "sg:phone":"+32 3 219 68 78",
    "sg:postcode":"2050",
    "sg:province":"Antwerpen",
    "wof:name":"Rivo",
    "wof:placetype":"venue"
},
  "geometry": {"coordinates":[4.3775792122,51.2206344604],"type":"Point"}
}