{
  "type": "Feature",
  "properties": {
    "iso:country":"BE",
    "sg:address":"Martelarenplein 8",
    "sg:city":"Leuven",
    "sg:classifiers":[
        {
            "category":"Bars & Pubs",
            "type":"Food & Drink"
        }
    ],
    "sg:phone":"+32 16 20 03 32",
    "sg:postcode":"3000",
    "sg:province":"Vlaams-Brabant",
    "wof:name":"Brasserie La Vignette",
    "wof:placetype":"venue"
},
  "geometry": {"coordinates":[4.7138929367,50.8812179565],"type":"Point"}
}