{
  "type": "Feature",
  "properties": {
    "addr:full":"Groendalekapelleweg 3 Lichtervelde West-Vlaanderen 8810",
    "addr:housenumber":"3",
    "addr:postcode":"8810",
    "addr:street":"Groendalekapelleweg",
    "iso:country":"BE",
    "sg:address":"Groendalekapelleweg 3",
    "sg:city":"Lichtervelde",
    "sg:orig_category":"Eleveurs and marchands de porcs",
    "sg:phone":"+32 51 72 22 20",
    "sg:postcode":"8810",
    "sg:province":"West-Vlaanderen",
    "wof:name":"Gabriel De Muynck",
    "wof:placetype":"venue"
},
  "geometry": {"coordinates":[3.1730899811,51.0169219971],"type":"Point"}
}