{
  "type": "Feature",
  "properties": {
    "addr:full":"Dijkstraat 42 Haacht Vlaams-Brabant 3150",
    "addr:housenumber":"42",
    "addr:postcode":"3150",
    "addr:street":"Dijkstraat",
    "iso:country":"BE",
    "sg:address":"Dijkstraat 42",
    "sg:city":"Haacht",
    "sg:orig_category":"Supermarkten",
    "sg:phone":"+32 16 60 21 61",
    "sg:postcode":"3150",
    "sg:province":"Vlaams-Brabant",
    "wof:name":"Spar",
    "wof:placetype":"venue"
},
  "geometry": {"coordinates":[4.6380047798,50.9768714905],"type":"Point"}
}