{
  "type": "Feature",
  "properties": {
    "iso:country":"BE",
    "sg:address":"Menenstraat 100",
    "sg:city":"Wervik",
    "sg:orig_category":"V\u00e9hicules automobiles",
    "sg:phone":"+32 56 51 45 18",
    "sg:postcode":"8940",
    "sg:province":"West-Vlaanderen",
    "wof:name":"Garage Dervaux",
    "wof:placetype":"venue"
},
  "geometry": {"coordinates":[3.0864229202,50.8076400757],"type":"Point"}
}