{
  "type": "Feature",
  "properties": {
    "addr:full":"Route De Couvin 5 Walcourt Namur 5651",
    "addr:housenumber":"5",
    "addr:postcode":"5651",
    "addr:street":"Route De Couvin",
    "iso:country":"BE",
    "sg:address":"Route De Couvin 5",
    "sg:city":"Walcourt",
    "sg:orig_category":"Entretien and r\u00e9parations de voitures",
    "sg:phone":"+32 71 22 06 66",
    "sg:postcode":"5651",
    "sg:province":"Namur",
    "wof:name":"Caro 5",
    "wof:placetype":"venue"
},
  "geometry": {"coordinates":[4.4262080193,50.2824401855],"type":"Point"}
}