{
  "type": "Feature",
  "properties": {
    "iso:country":"BE",
    "sg:address":"Waversesteenweg 138",
    "sg:city":"Bierbeek (honsem)",
    "sg:classifiers":[
        {
            "category":"Communications",
            "type":"Services"
        }
    ],
    "sg:phone":"+32 16 72 09 50",
    "sg:postcode":"3360",
    "sg:province":"Vlaams-Brabant",
    "sg:tags":[
        "translator"
    ],
    "wof:name":"Belita-lingua",
    "wof:placetype":"venue"
},
  "geometry": {"coordinates":[4.7997889519,50.8172454834],"type":"Point"}
}