{
  "type": "Feature",
  "properties": {
    "addr:full":"Broekstraat 1 Dessel Antwerpen 2480",
    "addr:housenumber":"1",
    "addr:postcode":"2480",
    "addr:street":"Broekstraat",
    "iso:country":"BE",
    "sg:address":"Broekstraat 1",
    "sg:city":"Dessel",
    "sg:orig_category":"Installation de serres, double vitrage and fen\u00eatres. Art and fournitures artistiques",
    "sg:phone":"+32 14 37 75 18",
    "sg:postcode":"2480",
    "sg:province":"Antwerpen",
    "wof:name":"Rommes-pauwels",
    "wof:placetype":"venue"
},
  "geometry": {"coordinates":[5.1076788902,51.239276886],"type":"Point"}
}