{
  "type": "Feature",
  "properties": {
    "iso:country":"BE",
    "sg:address":"Kegelslei 7a",
    "sg:city":"Sint-katelijne-waver (onze-lieve-vrouw-waver)",
    "sg:classifiers":[
        {
            "category":"Farming",
            "subcategory":"Crops",
            "type":"Manufacturing & Wholesale Goods"
        }
    ],
    "sg:phone":"+32 15 75 23 42",
    "sg:postcode":"2861",
    "sg:province":"Antwerpen",
    "sg:tags":[
        "vegetable",
        "fruit",
        "-",
        "grower"
    ],
    "wof:name":"Vertommen B",
    "wof:placetype":"venue"
},
  "geometry": {"coordinates":[4.5860757828,51.0575447083],"type":"Point"}
}