{
  "type": "Feature",
  "properties": {
    "iso:country":"BE",
    "sg:address":"Rue Antoine N\u00e9lis 36a",
    "sg:city":"Namur (belgrade)",
    "sg:classifiers":[
        {
            "category":"Education",
            "subcategory":"University",
            "type":"Public Place"
        }
    ],
    "sg:phone":"+32 81 74 00 00",
    "sg:postcode":"5001",
    "sg:province":"Namur",
    "sg:tags":[
        "adult"
    ],
    "wof:name":"Institut Belge D'oenologie Asbl",
    "wof:placetype":"venue"
},
  "geometry": {"coordinates":[4.8257050514,50.4722557068],"type":"Point"}
}