{
  "type": "Feature",
  "properties": {
    "addr:full":"Leuvensesteenweg 202 Tielt-winge (sint-joris-winge) Vlaams-Brabant 3390",
    "addr:housenumber":"202",
    "addr:postcode":"3390",
    "addr:street":"Leuvensesteenweg",
    "iso:country":"BE",
    "sg:address":"Leuvensesteenweg 202",
    "sg:city":"Tielt-winge (sint-joris-winge)",
    "sg:classifiers":[
        {
            "category":"Personal",
            "subcategory":"Beauty Salon",
            "type":"Services"
        }
    ],
    "sg:phone":"+32 16 63 56 56",
    "sg:postcode":"3390",
    "sg:province":"Vlaams-Brabant",
    "sg:tags":[
        "lady",
        "-",
        "hairdressing"
    ],
    "wof:name":"Hilde",
    "wof:placetype":"venue"
},
  "geometry": {"coordinates":[4.881731987,50.9088592529],"type":"Point"}
}