{
  "type": "Feature",
  "properties": {
    "iso:country":"BE",
    "sg:address":"Marktplein 61",
    "sg:city":"Herzele",
    "sg:orig_category":"Rev\u00eatements de sols and murs",
    "sg:phone":"+32 53 62 74 11",
    "sg:postcode":"9520",
    "sg:province":"Oost-Vlaanderen",
    "wof:name":"C.&k. Belgica",
    "wof:placetype":"venue"
},
  "geometry": {"coordinates":[3.8592419624,50.9202613831],"type":"Point"}
}