{
  "type": "Feature",
  "properties": {
    "iso:country":"BE",
    "sg:address":"Luipegem 62a",
    "sg:city":"Bornem",
    "sg:classifiers":[
        {
            "category":"Building & Trades",
            "subcategory":"Landscaping Services",
            "type":"Services"
        }
    ],
    "sg:phone":"+32 3 899 12 67",
    "sg:postcode":"2880",
    "sg:province":"Antwerpen",
    "sg:tags":[
        "-",
        "lopping",
        "work",
        "tree",
        "felling"
    ],
    "wof:name":"Van De Veken-verheyden",
    "wof:placetype":"venue"
},
  "geometry": {"coordinates":[4.2048420906,51.0914154053],"type":"Point"}
}