{
  "type": "Feature",
  "properties": {
    "addr:full":"Boulevard Leopold Iii 106 P\u00e9ruwelz Hainaut 7600",
    "addr:housenumber":"106",
    "addr:postcode":"7600",
    "addr:street":"Boulevard Leopold Iii",
    "iso:country":"BE",
    "sg:address":"Boulevard Leopold Iii 106",
    "sg:city":"P\u00e9ruwelz",
    "sg:classifiers":[
        {
            "category":"Social Services",
            "subcategory":"Job Training",
            "type":"Services"
        }
    ],
    "sg:phone":"+32 69 77 12 82",
    "sg:postcode":"7600",
    "sg:province":"Hainaut",
    "sg:tags":[
        "interpreter"
    ],
    "wof:name":"Forster F",
    "wof:placetype":"venue"
},
  "geometry": {"coordinates":[3.5969920158,50.5037078857],"type":"Point"}
}