{
  "type": "Feature",
  "properties": {
    "addr:full":"Sint-elooisweg 15 Ieper (voormezele) West-Vlaanderen 8902",
    "addr:housenumber":"15",
    "addr:postcode":"8902",
    "addr:street":"Sint-Elooisweg",
    "iso:country":"BE",
    "sg:address":"Sint-elooisweg 15",
    "sg:city":"Ieper (voormezele)",
    "sg:classifiers":[
        {
            "category":"Wholesale",
            "subcategory":"Vending Machines",
            "type":"Manufacturing & Wholesale Goods"
        }
    ],
    "sg:phone":"+32 57 20 90 26",
    "sg:postcode":"8902",
    "sg:province":"West-Vlaanderen",
    "sg:tags":[
        "groundwork",
        "material",
        "-"
    ],
    "wof:name":"Cuvelier",
    "wof:placetype":"venue"
},
  "geometry": {"coordinates":[2.8777399063,50.8169555664],"type":"Point"}
}