{
  "type": "Feature",
  "properties": {
    "addr:full":"Place De L'h\u00f4tel De Ville 9 Florennes Namur 5620",
    "addr:housenumber":"9",
    "addr:postcode":"5620",
    "addr:street":"Place De L'Ho \u0302Tel De Ville",
    "iso:country":"BE",
    "sg:address":"Place De L'h\u00f4tel De Ville 9",
    "sg:city":"Florennes",
    "sg:classifiers":[
        {
            "category":"Personal",
            "subcategory":"Beauty Salon",
            "type":"Services"
        }
    ],
    "sg:phone":"+32 71 68 73 68",
    "sg:postcode":"5620",
    "sg:province":"Namur",
    "wof:name":"Lady Chic",
    "wof:placetype":"venue"
},
  "geometry": {"coordinates":[4.6609201431,50.2378807068],"type":"Point"}
}