{
  "type": "Feature",
  "properties": {
    "iso:country":"BE",
    "sg:address":"Rue Du Moulin De Spiennes 11b",
    "sg:city":"Mons (spiennes)",
    "sg:classifiers":[
        {
            "category":"Building & Trades",
            "subcategory":"Landscaping Services",
            "type":"Services"
        }
    ],
    "sg:phone":"+32 65 34 64 54",
    "sg:postcode":"7032",
    "sg:province":"Hainaut",
    "sg:tags":[
        "gardening",
        "garden",
        "maintenance"
    ],
    "wof:name":"Noel Ets",
    "wof:placetype":"venue"
},
  "geometry": {"coordinates":[3.9869709015,50.4255142212],"type":"Point"}
}