{
  "type": "Feature",
  "properties": {
    "iso:country":"BE",
    "sg:address":"Ijzerstraat 29",
    "sg:city":"Alveringem (stavele)",
    "sg:classifiers":[
        {
            "category":"Home & Garden",
            "subcategory":"Garden Supply",
            "type":"Retail Goods"
        }
    ],
    "sg:phone":"+32 57 30 03 70",
    "sg:postcode":"8691",
    "sg:province":"West-Vlaanderen",
    "sg:tags":[
        "seed",
        "-"
    ],
    "wof:name":"Brunet-vandaele",
    "wof:placetype":"venue"
},
  "geometry": {"coordinates":[2.6723051071,50.9429016113],"type":"Point"}
}