{
  "type": "Feature",
  "properties": {
    "addr:full":"Rue Jules Besme 140 Koekelberg/koekelberg Bruxelles-Capitale 1081",
    "addr:housenumber":"140",
    "addr:postcode":"1081",
    "addr:street":"Rue Jules Besme",
    "iso:country":"BE",
    "sg:address":"Rue Jules Besme 140",
    "sg:city":"Koekelberg/koekelberg",
    "sg:orig_category":"Experts-comptables",
    "sg:phone":"+32 2 410 66 60",
    "sg:postcode":"1081",
    "sg:province":"Bruxelles-Capitale",
    "wof:name":"J.m. Van De Sompel",
    "wof:placetype":"venue"
},
  "geometry": {"coordinates":[4.3187298775,50.8622665405],"type":"Point"}
}