{
  "type": "Feature",
  "properties": {
    "addr:full":"Oude Aarschotseweg 7 Leuven (wilsele) Vlaams-Brabant 3012",
    "addr:housenumber":"7",
    "addr:postcode":"3012",
    "addr:street":"Oude Aarschotseweg",
    "iso:country":"BE",
    "sg:address":"Oude Aarschotseweg 7",
    "sg:city":"Leuven (wilsele)",
    "sg:classifiers":[
        {
            "category":"Retail",
            "subcategory":"Veterinary Services",
            "type":"Services"
        }
    ],
    "sg:phone":"+32 16 44 66 22",
    "sg:postcode":"3012",
    "sg:province":"Vlaams-Brabant",
    "sg:tags":[
        "veterinarian"
    ],
    "wof:name":"Vastesaeger J",
    "wof:placetype":"venue"
},
  "geometry": {"coordinates":[4.7155251503,50.9253845215],"type":"Point"}
}