{
  "type": "Feature",
  "properties": {
    "iso:country":"BE",
    "sg:address":"95",
    "sg:city":"Rue De Wand 1020 Bruxelles",
    "sg:classifiers":[
        {
            "category":"Travel",
            "subcategory":"Hotels & Motels",
            "type":"Entertainment"
        }
    ],
    "sg:phone":"+32 2 262 05 10",
    "sg:postcode":"95",
    "sg:tags":[
        "hotels",
        "business",
        "restaurant"
    ],
    "wof:name":"Restaurant Soave",
    "wof:placetype":"venue"
},
  "geometry": {"coordinates":[4.3605628014,50.9009399414],"type":"Point"}
}