{
  "type": "Feature",
  "properties": {
    "addr:full":"Oostveldstraat 239a Eeklo Oost-Vlaanderen 9900",
    "addr:housenumber":"239a",
    "addr:postcode":"9900",
    "addr:street":"Oostveldstraat",
    "iso:country":"BE",
    "sg:address":"Oostveldstraat 239a",
    "sg:city":"Eeklo",
    "sg:classifiers":[
        {
            "category":"Shopping",
            "subcategory":"Jewelry",
            "type":"Retail Goods"
        }
    ],
    "sg:phone":"+32 9 377 99 29",
    "sg:postcode":"9900",
    "sg:province":"Oost-Vlaanderen",
    "sg:tags":[
        "jeweller",
        "-"
    ],
    "wof:name":"Verbeelt-juwelenhandel",
    "wof:placetype":"venue"
},
  "geometry": {"coordinates":[3.6060669422,51.1847686768],"type":"Point"}
}