{
  "type": "Feature",
  "properties": {
    "addr:full":"4970 Stavelot (groot) Li\u00e8ge 4970",
    "addr:postcode":"4970;4970",
    "addr:street":"Groot Lie\u0300Ge",
    "iso:country":"BE",
    "sg:address":"4970",
    "sg:city":"Stavelot (groot)",
    "sg:orig_category":"Pharmaciens",
    "sg:phone":"+32 900 10 500",
    "sg:postcode":"4970",
    "sg:province":"Li\u00e8ge",
    "wof:name":"Pharmacies De Garde",
    "wof:placetype":"venue"
},
  "geometry": {"coordinates":[5.930850029,50.3942909241],"type":"Point"}
}