{
  "type": "Feature",
  "properties": {
    "addr:full":"Apollostraat 184 Antwerpen (berchem) Antwerpen 2600",
    "addr:housenumber":"184",
    "addr:postcode":"2600",
    "addr:street":"Apollostraat;Antwerpen",
    "iso:country":"BE",
    "sg:address":"Apollostraat 184",
    "sg:city":"Antwerpen (berchem)",
    "sg:classifiers":[
        {
            "category":"Wholesale",
            "subcategory":"Computers",
            "type":"Manufacturing & Wholesale Goods"
        }
    ],
    "sg:phone":"+32 3 321 97 98",
    "sg:postcode":"2600",
    "sg:province":"Antwerpen",
    "sg:tags":[
        "cabling",
        "processing",
        "-",
        "data"
    ],
    "wof:name":"Cuypers & Co",
    "wof:placetype":"venue"
},
  "geometry": {"coordinates":[4.4174151421,51.1974411011],"type":"Point"}
}