{
  "type": "Feature",
  "properties": {
    "addr:full":"Mersenhovenstraat 61 Kortessem Limburg 3720",
    "addr:housenumber":"61",
    "addr:postcode":"3720",
    "addr:street":"Mersenhovenstraat",
    "iso:country":"BE",
    "sg:address":"Mersenhovenstraat 61",
    "sg:city":"Kortessem",
    "sg:classifiers":[
        {
            "category":"Wholesale",
            "subcategory":"Machinery & Supplies",
            "type":"Manufacturing & Wholesale Goods"
        }
    ],
    "sg:phone":"+32 11 37 53 65",
    "sg:postcode":"3720",
    "sg:province":"Limburg",
    "sg:tags":[
        "refrigeration",
        "-",
        "industrial",
        "commercial",
        "equipment"
    ],
    "wof:name":"A-aircool Bvba",
    "wof:placetype":"venue"
},
  "geometry": {"coordinates":[5.3931899071,50.8558502197],"type":"Point"}
}