{
  "type": "Feature",
  "properties": {
    "iso:country":"BE",
    "sg:address":"Stationsstraat 97",
    "sg:city":"Machelen (diegem)",
    "sg:classifiers":[
        {
            "category":"Bars & Pubs",
            "type":"Food & Drink"
        }
    ],
    "sg:phone":"+32 2 721 46 81",
    "sg:postcode":"1831",
    "sg:province":"Vlaams-Brabant",
    "wof:name":"Arbiter (den)",
    "wof:placetype":"venue"
},
  "geometry": {"coordinates":[4.4422011375,50.890914917],"type":"Point"}
}