{
  "type": "Feature",
  "properties": {
    "iso:country":"BE",
    "sg:address":"Steenweg Op Aalst 110",
    "sg:city":"Wevelgem",
    "sg:orig_category":"Souvenirs and objets artisanaux",
    "sg:phone":"+32 53 78 84 92",
    "sg:postcode":"9310",
    "sg:province":"Oost-Vlaanderen",
    "wof:name":"Vandewoude Y",
    "wof:placetype":"venue"
},
  "geometry": {"coordinates":[4.098400116,50.9477767944],"type":"Point"}
}