{
  "type": "Feature",
  "properties": {
    "addr:full":"Zwaantje 50 Evergem (sleidinge) Oost-Vlaanderen 9940",
    "addr:housenumber":"50",
    "addr:postcode":"9940",
    "addr:street":"Zwaantje",
    "iso:country":"BE",
    "sg:address":"Zwaantje 50",
    "sg:city":"Evergem (sleidinge)",
    "sg:classifiers":[
        {
            "category":"Building & Trades",
            "subcategory":"Landscaping Services",
            "type":"Services"
        }
    ],
    "sg:phone":"+32 9 357 30 58",
    "sg:postcode":"9940",
    "sg:province":"Oost-Vlaanderen",
    "sg:tags":[
        "moss",
        "removal"
    ],
    "wof:name":"Byl A",
    "wof:placetype":"venue"
},
  "geometry": {"coordinates":[3.6749379635,51.1514053345],"type":"Point"}
}