{
  "type": "Feature",
  "properties": {
    "addr:full":"Kludweg 7 Zonhoven Limburg 3520",
    "addr:housenumber":"7",
    "addr:postcode":"3520",
    "addr:street":"Kludweg",
    "iso:country":"BE",
    "sg:address":"Kludweg 7",
    "sg:city":"Zonhoven",
    "sg:orig_category":"Ordinateurs and \u00e9quipement informatique",
    "sg:phone":"+32 11 82 19 67",
    "sg:postcode":"3520",
    "sg:province":"Limburg",
    "wof:name":"P.c.p. Printers",
    "wof:placetype":"venue"
},
  "geometry": {"coordinates":[5.3833899498,50.9906997681],"type":"Point"}
}