{
  "type": "Feature",
  "properties": {
    "addr:full":"Noordscheldeweg 1 Antwerpen Antwerpen 2050",
    "addr:housenumber":"1",
    "addr:postcode":"2050",
    "addr:street":"Noordscheldeweg",
    "iso:country":"BE",
    "sg:address":"Noordscheldeweg 1",
    "sg:city":"Antwerpen",
    "sg:classifiers":[
        {
            "category":"Food & Beverages",
            "subcategory":"Fruits & Vegetables",
            "type":"Retail Goods"
        }
    ],
    "sg:phone":"+32 3 219 52 02",
    "sg:postcode":"2050",
    "sg:province":"Antwerpen",
    "sg:tags":[
        "l\u00e9gumes",
        "gr"
    ],
    "wof:name":"Dani\u00cbl Louagie",
    "wof:placetype":"venue"
},
  "geometry": {"coordinates":[4.3769049644,51.2346916199],"type":"Point"}
}