{
  "type": "Feature",
  "properties": {
    "iso:country":"BE",
    "sg:address":"Rue De L\u00b4aun\u00c9e 2",
    "sg:city":"Nassogne",
    "sg:orig_category":"M\u00e9decins and sp\u00e9cialistes",
    "sg:phone":"+32 84 22 31 34",
    "sg:postcode":"6953",
    "sg:province":"Luxembourg",
    "wof:name":"B\u00c9n\u00c9dicte Defoin",
    "wof:placetype":"venue"
},
  "geometry": {"coordinates":[5.2774748802,50.1315689087],"type":"Point"}
}