{
  "type": "Feature",
  "properties": {
    "iso:country":"BE",
    "sg:address":"Dr\u00e8ve Des Dominicains 11",
    "sg:city":"Gerpinnes (loverval)",
    "sg:classifiers":[
        {
            "category":"Health Services",
            "subcategory":"Doctor",
            "type":"Services"
        }
    ],
    "sg:phone":"+32 71 47 06 06",
    "sg:postcode":"6280",
    "sg:province":"Hainaut",
    "sg:tags":[
        "medicinephysicians",
        "surgeon"
    ],
    "wof:name":"Larvor Laurence",
    "wof:placetype":"venue"
},
  "geometry": {"coordinates":[4.4679098129,50.3651390076],"type":"Point"}
}