{
  "type": "Feature",
  "properties": {
    "addr:full":"Rue Chienrue 48 Bl\u00e9gny (trembleur) Li\u00e8ge 4670",
    "addr:housenumber":"48",
    "addr:postcode":"4670",
    "addr:street":"Rue Chienrue;Trembleur",
    "iso:country":"BE",
    "sg:address":"Rue Chienrue 48",
    "sg:city":"Bl\u00e9gny (trembleur)",
    "sg:classifiers":[
        {
            "category":"Home & Garden",
            "subcategory":"Kitchen Supply",
            "type":"Retail Goods"
        }
    ],
    "sg:phone":"+32 4 387 44 95",
    "sg:postcode":"4670",
    "sg:province":"Li\u00e8ge",
    "sg:tags":[
        "installation"
    ],
    "wof:name":"Simon D",
    "wof:placetype":"venue"
},
  "geometry": {"coordinates":[5.7188949585,50.6693077087],"type":"Point"}
}