{
  "type": "Feature",
  "properties": {
    "addr:full":"Plein 2ba Zwevegem West-Vlaanderen 8551",
    "addr:postcode":"8551",
    "addr:street":"Plein 2Ba",
    "iso:country":"BE",
    "sg:address":"Plein 2ba",
    "sg:city":"Zwevegem",
    "sg:orig_category":"Pharmaciens",
    "sg:phone":"+32 56 45 52 45",
    "sg:postcode":"8551",
    "sg:province":"West-Vlaanderen",
    "wof:name":"K. De Maeyer",
    "wof:placetype":"venue"
},
  "geometry": {"coordinates":[3.4109840393,50.782283783],"type":"Point"}
}