{
  "type": "Feature",
  "properties": {
    "iso:country":"BE",
    "sg:address":"Hendrik Heymanplein 10",
    "sg:city":"Sint-niklaas",
    "sg:classifiers":[
        {
            "category":"Travel",
            "subcategory":"Travel Agent",
            "type":"Entertainment"
        }
    ],
    "sg:phone":"+32 3 766 21 61",
    "sg:postcode":"9100",
    "sg:province":"Oost-Vlaanderen",
    "sg:tags":[
        "agency"
    ],
    "wof:name":"Happy Holidays Nv",
    "wof:placetype":"venue"
},
  "geometry": {"coordinates":[4.1414499283,51.1630897522],"type":"Point"}
}