{
  "type": "Feature",
  "properties": {
    "addr:full":"Corsendonk 14 Oud-turnhout Antwerpen 2360",
    "addr:housenumber":"14",
    "addr:postcode":"2360",
    "addr:street":"Corsendonk",
    "iso:country":"BE",
    "sg:address":"Corsendonk 14",
    "sg:city":"Oud-turnhout",
    "sg:orig_category":"Rundveehouders",
    "sg:phone":"+32 14 45 06 15",
    "sg:postcode":"2360",
    "sg:province":"Antwerpen",
    "wof:name":"Frans Herijgers",
    "wof:placetype":"venue"
},
  "geometry": {"coordinates":[5.016438961,51.2861061096],"type":"Point"}
}