{
  "type": "Feature",
  "properties": {
    "addr:full":"Avenue Charles Gilisquet 93 Bruxelles (schaerbeek) Bruxelles-Capitale 1030",
    "addr:housenumber":"93",
    "addr:postcode":"1030",
    "addr:street":"Avenue Charles Gilisquet",
    "iso:country":"BE",
    "sg:address":"Avenue Charles Gilisquet 93",
    "sg:city":"Bruxelles (schaerbeek)",
    "sg:classifiers":[
        {
            "category":"Food & Beverages",
            "subcategory":"Liquor & Beverages",
            "type":"Retail Goods"
        }
    ],
    "sg:phone":"+32 2 215 07 78",
    "sg:postcode":"1030",
    "sg:province":"Bruxelles-Capitale",
    "sg:tags":[
        "-",
        "spirit",
        "wine"
    ],
    "wof:name":"Covipro",
    "wof:placetype":"venue"
},
  "geometry": {"coordinates":[4.3956770897,50.8649864197],"type":"Point"}
}