{
  "type": "Feature",
  "properties": {
    "addr:full":"Vlaamsekunstlaan 60 Antwerpen Antwerpen 2020",
    "addr:housenumber":"60",
    "addr:postcode":"2020",
    "addr:street":"Vlaamsekunstlaan",
    "iso:country":"BE",
    "sg:address":"Vlaamsekunstlaan 60",
    "sg:city":"Antwerpen",
    "sg:classifiers":[
        {
            "category":"Health Services",
            "subcategory":"Doctor",
            "type":"Services"
        }
    ],
    "sg:phone":"+32 3 238 62 66",
    "sg:postcode":"2020",
    "sg:province":"Antwerpen",
    "sg:tags":[
        "medicinephysicians",
        "surgeon"
    ],
    "wof:name":"Dr Peters Bvba",
    "wof:placetype":"venue"
},
  "geometry": {"coordinates":[4.3903989792,51.1900939941],"type":"Point"}
}