{
  "type": "Feature",
  "properties": {
    "addr:full":"Grand-place 63 Wellin Luxembourg 6920",
    "addr:housenumber":"63",
    "addr:postcode":"6920",
    "addr:street":"Grand-Place",
    "iso:country":"BE",
    "sg:address":"Grand-place 63",
    "sg:city":"Wellin",
    "sg:orig_category":"Banken and kredietinstellingen",
    "sg:phone":"+32 84 38 99 10",
    "sg:postcode":"6920",
    "sg:province":"Luxembourg",
    "wof:name":"Fortis",
    "wof:placetype":"venue"
},
  "geometry": {"coordinates":[5.1158399582,50.0816917419],"type":"Point"}
}