{
  "type": "Feature",
  "properties": {
    "addr:full":"Zandvoordedorpstraat 166 Oostende West-Vlaanderen 8400",
    "addr:housenumber":"166",
    "addr:postcode":"8400",
    "addr:street":"Zandvoordedorpstraat",
    "iso:country":"BE",
    "sg:address":"Zandvoordedorpstraat 166",
    "sg:city":"Oostende",
    "sg:orig_category":"Imprimeries and copyshops",
    "sg:phone":"+32 59 25 06 50",
    "sg:postcode":"8400",
    "sg:province":"West-Vlaanderen",
    "wof:name":"Serigrafiek Meseure",
    "wof:placetype":"venue"
},
  "geometry": {"coordinates":[2.9420111179,51.2146377563],"type":"Point"}
}