{
  "type": "Feature",
  "properties": {
    "iso:country":"BE",
    "sg:address":"15 Augustusstraat 12ba",
    "sg:city":"Zutendaal",
    "sg:orig_category":"Epiceries",
    "sg:phone":"+32 89 61 16 61",
    "sg:postcode":"3690",
    "sg:province":"Limburg",
    "wof:name":"In De Markt",
    "wof:placetype":"venue"
},
  "geometry": {"coordinates":[5.5751690865,50.9308433533],"type":"Point"}
}