{
  "type": "Feature",
  "properties": {
    "addr:full":"Kazernelaan 96 Houthalen-helchteren (helchteren) Limburg 3530",
    "addr:housenumber":"96",
    "addr:postcode":"3530",
    "addr:street":"Kazernelaan",
    "iso:country":"BE",
    "sg:address":"Kazernelaan 96",
    "sg:city":"Houthalen-helchteren (helchteren)",
    "sg:classifiers":[
        {
            "category":"Home & Garden",
            "subcategory":"Home Furnishings",
            "type":"Retail Goods"
        }
    ],
    "sg:phone":"+32 11 52 19 79",
    "sg:postcode":"3530",
    "sg:province":"Limburg",
    "sg:tags":[
        "-",
        "furniture"
    ],
    "wof:name":"Meco Meubel-thijs",
    "wof:placetype":"venue"
},
  "geometry": {"coordinates":[5.3719201088,51.0310020447],"type":"Point"}
}