{
  "type": "Feature",
  "properties": {
    "addr:full":"Rijksweg 51 Kuurne West-Vlaanderen 8520",
    "addr:housenumber":"51",
    "addr:postcode":"8520",
    "addr:street":"Rijksweg",
    "iso:country":"BE",
    "sg:address":"Rijksweg 51",
    "sg:city":"Kuurne",
    "sg:orig_category":"RESTAURANTS: CAF\u00c9S",
    "sg:phone":"+32 56 70 60 13",
    "sg:postcode":"8520",
    "sg:province":"West-Vlaanderen",
    "wof:name":"Taverne Oase",
    "wof:placetype":"venue"
},
  "geometry": {"coordinates":[3.2771840096,50.8692703247],"type":"Point"}
}