{
  "type": "Feature",
  "properties": {
    "addr:full":"Zeelaan 104 De Panne West-Vlaanderen 8660",
    "addr:housenumber":"104",
    "addr:postcode":"8660",
    "addr:street":"Zeelaan",
    "iso:country":"BE",
    "sg:address":"Zeelaan 104",
    "sg:city":"De Panne",
    "sg:orig_category":"Supermarkten Warenhuizen",
    "sg:phone":"+32 58 41 31 33",
    "sg:postcode":"8660",
    "sg:province":"West-Vlaanderen",
    "wof:name":"Gb Contact",
    "wof:placetype":"venue"
},
  "geometry": {"coordinates":[2.5922060013,51.0991363525],"type":"Point"}
}