{
  "type": "Feature",
  "properties": {
    "addr:full":"Avenue De L'informatique 9b Ans (alleur) Li\u00e8ge 4432",
    "addr:housenumber":"9b",
    "addr:postcode":"4432",
    "addr:street":"Avenue De L'Informatique",
    "iso:country":"BE",
    "sg:address":"Avenue De L'informatique 9b",
    "sg:city":"Ans (alleur)",
    "sg:classifiers":[
        {
            "category":"Professional",
            "subcategory":"Computer Services",
            "type":"Services"
        }
    ],
    "sg:phone":"+32 4 239 91 50",
    "sg:postcode":"4432",
    "sg:province":"Li\u00e8ge",
    "sg:tags":[
        "-",
        "processing",
        "data",
        "software"
    ],
    "wof:name":"N.s.i. Sa",
    "wof:placetype":"venue"
},
  "geometry": {"coordinates":[5.5242800713,50.6659317017],"type":"Point"}
}