{
  "type": "Feature",
  "properties": {
    "addr:full":"Route De Beaufays 102 Chaudfontaine Li\u00e8ge 4052",
    "addr:housenumber":"102",
    "addr:postcode":"4052",
    "addr:street":"Route De Beaufays",
    "iso:country":"BE",
    "sg:address":"Route De Beaufays 102",
    "sg:city":"Chaudfontaine",
    "sg:orig_category":"Schoonheidssalons",
    "sg:phone":"+32 4 368 85 37",
    "sg:postcode":"4052",
    "sg:province":"Li\u00e8ge",
    "wof:name":"V\u00c9ronique Lejeune",
    "wof:placetype":"venue"
},
  "geometry": {"coordinates":[5.6392202377,50.5586051941],"type":"Point"}
}