{
  "type": "Feature",
  "properties": {
    "addr:full":"Wandebourcy 13 Houffalize Luxembourg 6662",
    "addr:housenumber":"13",
    "addr:postcode":"6662",
    "addr:street":"Wandebourcy",
    "iso:country":"BE",
    "sg:address":"Wandebourcy 13",
    "sg:city":"Houffalize",
    "sg:orig_category":"Location de machines-outils and de mat\u00e9riel de bricolage. Locations de machines and \u00e9quipement pour ",
    "sg:phone":"+32 61 28 85 07",
    "sg:postcode":"6662",
    "sg:province":"Luxembourg",
    "wof:name":"Location Annet",
    "wof:placetype":"venue"
},
  "geometry": {"coordinates":[5.8380899429,50.108253479],"type":"Point"}
}