{
  "type": "Feature",
  "properties": {
    "addr:full":"Alsembergse Steenweg 484 Ukkel/uccle Bruxelles-Capitale 1180",
    "addr:housenumber":"484",
    "addr:postcode":"1180",
    "addr:street":"Alsembergse Steenweg;/",
    "iso:country":"BE",
    "sg:address":"Alsembergse Steenweg 484",
    "sg:city":"Ukkel/uccle",
    "sg:orig_category":"Krantenwinkels Rookartikelen",
    "sg:phone":"+32 2 343 43 58",
    "sg:postcode":"1180",
    "sg:province":"Bruxelles-Capitale",
    "wof:name":"Michel Troost",
    "wof:placetype":"venue"
},
  "geometry": {"coordinates":[4.3377127647,50.8099708557],"type":"Point"}
}