{
  "type": "Feature",
  "properties": {
    "addr:full":"Brigantijnenstraat 2 Oostende West-Vlaanderen 8400",
    "addr:housenumber":"2",
    "addr:postcode":"8400",
    "addr:street":"Brigantijnenstraat",
    "iso:country":"BE",
    "sg:address":"Brigantijnenstraat 2",
    "sg:city":"Oostende",
    "sg:orig_category":"Werk and personeelsselectie",
    "sg:phone":"+32 59 55 65 53",
    "sg:postcode":"8400",
    "sg:province":"West-Vlaanderen",
    "wof:name":"Vdab Consult",
    "wof:placetype":"venue"
},
  "geometry": {"coordinates":[2.9217009544,51.2258071899],"type":"Point"}
}