{
  "type": "Feature",
  "properties": {
    "addr:full":"Neerveldlaan 5 Ternat Vlaams-Brabant 1740",
    "addr:housenumber":"5",
    "addr:postcode":"1740",
    "addr:street":"Neerveldlaan",
    "iso:country":"BE",
    "sg:address":"Neerveldlaan 5",
    "sg:city":"Ternat",
    "sg:orig_category":"Traitements param\u00e9dicaux",
    "sg:phone":"+32 2 582 05 70",
    "sg:postcode":"1740",
    "sg:province":"Vlaams-Brabant",
    "wof:name":"S. Wachtelaer",
    "wof:placetype":"venue"
},
  "geometry": {"coordinates":[4.1674470901,50.8732948303],"type":"Point"}
}