{
  "type": "Feature",
  "properties": {
    "addr:full":"Rue De La Colonne 48 Bruxelles (molenbeek-saint-jean) Bruxelles-Capitale 1080",
    "addr:housenumber":"48",
    "addr:postcode":"1080",
    "addr:street":"Rue De La Colonne",
    "iso:country":"BE",
    "sg:address":"Rue De La Colonne 48",
    "sg:city":"Bruxelles (molenbeek-saint-jean)",
    "sg:classifiers":[
        {
            "category":"Health Services",
            "subcategory":"Health Practitioner",
            "type":"Services"
        }
    ],
    "sg:phone":"+32 2 479 45 35",
    "sg:postcode":"1080",
    "sg:province":"Bruxelles-Capitale",
    "sg:tags":[
        "physiotherapist"
    ],
    "wof:name":"Oukili Hayat",
    "wof:placetype":"venue"
},
  "geometry": {"coordinates":[4.3346400261,50.8537712097],"type":"Point"}
}