{
  "type": "Feature",
  "properties": {
    "iso:country":"BE",
    "sg:address":"Krinkelstraat 18",
    "sg:city":"Meulebeke",
    "sg:orig_category":"Groententeelt",
    "sg:phone":"+32 51 48 71 48",
    "sg:postcode":"8760",
    "sg:province":"West-Vlaanderen",
    "wof:name":"Joost Goethals",
    "wof:placetype":"venue"
},
  "geometry": {"coordinates":[3.2666499615,50.9633293152],"type":"Point"}
}