{
  "type": "Feature",
  "properties": {
    "addr:full":"Oostkade 15 Zelzate Oost-Vlaanderen 9060",
    "addr:housenumber":"15",
    "addr:postcode":"9060",
    "addr:street":"Oostkade",
    "iso:country":"BE",
    "sg:address":"Oostkade 15",
    "sg:city":"Zelzate",
    "sg:orig_category":"Dierenartsen",
    "sg:phone":"+32 9 345 50 30",
    "sg:postcode":"9060",
    "sg:province":"Oost-Vlaanderen",
    "wof:name":"Frieda Erven",
    "wof:placetype":"venue"
},
  "geometry": {"coordinates":[3.8097629547,51.2004051208],"type":"Point"}
}