{
  "type": "Feature",
  "properties": {
    "iso:country":"BE",
    "sg:address":"Rue Du Ch\u00c2teau 1b3",
    "sg:city":"Hannut",
    "sg:classifiers":[
        {
            "category":"Professional",
            "subcategory":"Accounting & Tax Preparation",
            "type":"Services"
        }
    ],
    "sg:phone":"+32 19 51 23 20",
    "sg:postcode":"4280",
    "sg:province":"Li\u00e8ge",
    "sg:tags":[
        "accountant"
    ],
    "wof:name":"Ivo-jean De Vlamynck",
    "wof:placetype":"venue"
},
  "geometry": {"coordinates":[5.1252298355,50.6634140015],"type":"Point"}
}