{
  "type": "Feature",
  "properties": {
    "iso:country":"BE",
    "sg:address":"Abeelstraat 13-15",
    "sg:city":"Ronse",
    "sg:orig_category":"Herstelling horloges and juwelen Juwelen and horloges Swatch",
    "sg:phone":"+32 55 21 47 01",
    "sg:postcode":"9600",
    "sg:province":"Oost-Vlaanderen",
    "wof:name":"Bauwens Ignace",
    "wof:placetype":"venue"
},
  "geometry": {"coordinates":[3.6000161171,50.7450904846],"type":"Point"}
}