{
  "type": "Feature",
  "properties": {
    "iso:country":"BE",
    "sg:address":"Brabantdam 113",
    "sg:city":"Gent",
    "sg:classifiers":[
        {
            "category":"Fast Food",
            "type":"Food & Drink"
        }
    ],
    "sg:phone":"+32 9 233 12 55",
    "sg:postcode":"9000",
    "sg:province":"Oost-Vlaanderen",
    "sg:tags":[
        "meeneem",
        "restaurant"
    ],
    "wof:name":"Frituur Bjorn",
    "wof:placetype":"venue"
},
  "geometry": {"coordinates":[3.7314651012,51.0499458313],"type":"Point"}
}