{
  "type": "Feature",
  "properties": {
    "iso:country":"BE",
    "sg:address":"Grand'route 335",
    "sg:city":"Braine L'alleud (lillois-witterz\u00e9e)",
    "sg:classifiers":[
        {
            "category":"Retail",
            "subcategory":"Veterinary Services",
            "type":"Services"
        }
    ],
    "sg:phone":"+32 2 387 16 69",
    "sg:postcode":"1428",
    "sg:province":"Brabant Wallon",
    "sg:tags":[
        "veterinarian"
    ],
    "wof:name":"Claes I",
    "wof:placetype":"venue"
},
  "geometry": {"coordinates":[-0.6584389806,47.4034957886],"type":"Point"}
}