{
  "type": "Feature",
  "properties": {
    "iso:country":"BE",
    "sg:address":"Pittemsesteenweg 11",
    "sg:city":"Tielt",
    "sg:classifiers":[
        {
            "category":"Arena",
            "subcategory":"Sports Club",
            "type":"Entertainment"
        }
    ],
    "sg:phone":"+32 51 40 56 58",
    "sg:postcode":"8700",
    "sg:province":"West-Vlaanderen",
    "wof:name":"The Lion Snooker Bvba",
    "wof:placetype":"venue"
},
  "geometry": {"coordinates":[3.3120119572,50.9983634949],"type":"Point"}
}