{
  "type": "Feature",
  "properties": {
    "addr:full":"Square Larousse 16 Bruxelles (forest) Bruxelles-Capitale 1190",
    "addr:housenumber":"16",
    "addr:postcode":"1190",
    "addr:street":"Square Larousse",
    "iso:country":"BE",
    "sg:address":"Square Larousse 16",
    "sg:city":"Bruxelles (forest)",
    "sg:classifiers":[
        {
            "category":"Health Services",
            "subcategory":"Dentist",
            "type":"Services"
        }
    ],
    "sg:phone":"+32 2 343 22 62",
    "sg:postcode":"1190",
    "sg:province":"Bruxelles-Capitale",
    "wof:name":"Coryn Anne",
    "wof:placetype":"venue"
},
  "geometry": {"coordinates":[4.3507452011,50.8202629089],"type":"Point"}
}