{
  "type": "Feature",
  "properties": {
    "iso:country":"BE",
    "sg:address":"Mechelse Steenweg 134-136",
    "sg:city":"Antwerpen",
    "sg:classifiers":[
        {
            "category":"Professional",
            "subcategory":"Management & Consulting",
            "type":"Services"
        }
    ],
    "sg:phone":"+32 3 257 12 54",
    "sg:postcode":"2018",
    "sg:province":"Antwerpen",
    "sg:tags":[
        "marketing",
        "-",
        "consultant"
    ],
    "wof:name":"Marketing Services Belgium Bvba",
    "wof:placetype":"venue"
},
  "geometry": {"coordinates":[4.409719944,51.2069702148],"type":"Point"}
}