{
  "type": "Feature",
  "properties": {
    "iso:country":"BE",
    "sg:address":"Fel. Bergiersstraat 141",
    "sg:city":"Overijse",
    "sg:orig_category":"Catering and organisatie van feesten Voedingsspeciaalzaken",
    "sg:phone":"+32 2 687 41 00",
    "sg:postcode":"3090",
    "sg:province":"Vlaams-Brabant",
    "wof:name":"Stefaan Vannerom",
    "wof:placetype":"venue"
},
  "geometry": {"coordinates":[4.4988298416,50.7463493347],"type":"Point"}
}