{
  "type": "Feature",
  "properties": {
    "addr:full":"Neerhofweg 3 Staden West-Vlaanderen 8840",
    "addr:housenumber":"3",
    "addr:postcode":"8840",
    "addr:street":"Neerhofweg",
    "iso:country":"BE",
    "sg:address":"Neerhofweg 3",
    "sg:city":"Staden",
    "sg:orig_category":"Woningbouw",
    "sg:phone":"+32 51 77 05 27",
    "sg:postcode":"8840",
    "sg:province":"West-Vlaanderen",
    "wof:name":"Freddy Lamaire",
    "wof:placetype":"venue"
},
  "geometry": {"coordinates":[3.0048060417,50.935634613],"type":"Point"}
}