{
  "type": "Feature",
  "properties": {
    "iso:country":"BE",
    "sg:address":"Stokstraat 1",
    "sg:city":"Wervik",
    "sg:orig_category":"Advocaten and juridische adviseurs",
    "sg:phone":"+32 475 32 01 87",
    "sg:postcode":"8940",
    "sg:province":"West-Vlaanderen",
    "wof:name":"B. Jorion",
    "wof:placetype":"venue"
},
  "geometry": {"coordinates":[3.0702600479,50.795955658],"type":"Point"}
}