{
  "type": "Feature",
  "properties": {
    "addr:full":"Grand'rue 30 Mettet (saint-g\u00e9rard) Namur 5640",
    "addr:housenumber":"30",
    "addr:postcode":"5640",
    "addr:street":"Grand'Rue;Saint-Ge\u0301Rard",
    "iso:country":"BE",
    "sg:address":"Grand'rue 30",
    "sg:city":"Mettet (saint-g\u00e9rard)",
    "sg:classifiers":[
        {
            "category":"Banks & Credit Unions",
            "subcategory":"Financial Services",
            "type":"Services"
        }
    ],
    "sg:phone":"+32 71 79 88 97",
    "sg:postcode":"5640",
    "sg:province":"Namur",
    "sg:tags":[
        "loan",
        "mortgage"
    ],
    "wof:name":"Smits A-m",
    "wof:placetype":"venue"
},
  "geometry": {"coordinates":[4.7364120483,50.3446502686],"type":"Point"}
}