{
  "type": "Feature",
  "properties": {
    "addr:full":"Dorpsstraat 164 Erpe-mere Oost-Vlaanderen 9420",
    "addr:housenumber":"164",
    "addr:postcode":"9420",
    "addr:street":"Dorpsstraat",
    "iso:country":"BE",
    "sg:address":"Dorpsstraat 164",
    "sg:city":"Erpe-mere",
    "sg:orig_category":"M\u00e9decins and sp\u00e9cialistes",
    "sg:phone":"+32 53 80 61 38",
    "sg:postcode":"9420",
    "sg:province":"Oost-Vlaanderen",
    "wof:name":"Consultatiebur.jonge Kind",
    "wof:placetype":"venue"
},
  "geometry": {"coordinates":[3.9819378853,50.9363021851],"type":"Point"}
}