{
  "type": "Feature",
  "properties": {
    "addr:full":"Broechemsesteenweg 44 Nijlen Antwerpen 2560",
    "addr:housenumber":"44",
    "addr:postcode":"2560",
    "addr:street":"Broechemsesteenweg",
    "iso:country":"BE",
    "sg:address":"Broechemsesteenweg 44",
    "sg:city":"Nijlen",
    "sg:classifiers":[
        {
            "category":"Bars & Pubs",
            "type":"Food & Drink"
        }
    ],
    "sg:phone":"+32 3 411 02 32",
    "sg:postcode":"2560",
    "sg:province":"Antwerpen",
    "sg:tags":[
        "tavern"
    ],
    "wof:name":"Wanneshof ('t)",
    "wof:placetype":"venue"
},
  "geometry": {"coordinates":[4.6652212143,51.1631011963],"type":"Point"}
}