{
  "type": "Feature",
  "properties": {
    "addr:full":"Rue Du Camp 91 Mons (obourg) Hainaut 7034",
    "addr:housenumber":"91",
    "addr:postcode":"7034",
    "addr:street":"Rue Du Camp",
    "iso:country":"BE",
    "sg:address":"Rue Du Camp 91",
    "sg:city":"Mons (obourg)",
    "sg:classifiers":[
        {
            "category":"Shopping",
            "subcategory":"Crafts & Fabrics",
            "type":"Retail Goods"
        }
    ],
    "sg:phone":"+32 65 32 01 00",
    "sg:postcode":"7034",
    "sg:province":"Hainaut",
    "sg:tags":[
        "ceramic"
    ],
    "wof:name":"M L Technologies Sprl",
    "wof:placetype":"venue"
},
  "geometry": {"coordinates":[4.0086159706,50.4765396118],"type":"Point"}
}