{
  "type": "Feature",
  "properties": {
    "iso:country":"BE",
    "sg:address":"Gentsesteenweg 49",
    "sg:city":"Kortrijk",
    "sg:orig_category":"Newspapers, magazines, periodicals - Distribution",
    "sg:phone":"+32 56 21 75 73",
    "sg:postcode":"8500",
    "sg:province":"West-Vlaanderen",
    "wof:name":"Lodrioor",
    "wof:placetype":"venue"
},
  "geometry": {"coordinates":[3.2766211033,50.8329162598],"type":"Point"}
}