{
  "type": "Feature",
  "properties": {
    "iso:country":"BE",
    "sg:address":"Grovermansdreef 32",
    "sg:city":"Evergem",
    "sg:orig_category":"Sportclubs",
    "sg:phone":"+32 9 253 58 09",
    "sg:postcode":"9940",
    "sg:province":"Oost-Vlaanderen",
    "wof:name":"Petanqueclub Meetjesland",
    "wof:placetype":"venue"
},
  "geometry": {"coordinates":[3.7417500019,51.117389679],"type":"Point"}
}