{
  "type": "Feature",
  "properties": {
    "addr:full":"Bld De La Sauveni\u00c8re 24 Li\u00c8ge Li\u00e8ge 4000",
    "addr:housenumber":"24",
    "addr:postcode":"4000",
    "addr:street":"Bld De La Sauvenie\u0300Re",
    "iso:country":"BE",
    "sg:address":"Bld De La Sauveni\u00c8re 24",
    "sg:city":"Li\u00c8ge",
    "sg:orig_category":"Boekenuitgeverijen Public-relationsbureaus Reclamebureaus",
    "sg:phone":"+32 4 223 53 86",
    "sg:postcode":"4000",
    "sg:province":"Li\u00e8ge",
    "wof:name":"Bureau I.p.e.p.",
    "wof:placetype":"venue"
},
  "geometry": {"coordinates":[5.5690851212,50.6444625854],"type":"Point"}
}