{
  "type": "Feature",
  "properties": {
    "iso:country":"BE",
    "sg:address":"Chaussee De Spa 36",
    "sg:city":"Theux",
    "sg:classifiers":[
        {
            "category":"Manufacturing",
            "subcategory":"Metals",
            "type":"Manufacturing & Wholesale Goods"
        }
    ],
    "sg:phone":"+32 87 54 13 42",
    "sg:postcode":"4910",
    "sg:province":"Li\u00e8ge",
    "sg:tags":[
        "ironmongery"
    ],
    "wof:name":"Forges Et Platineries E. Gille S.p.r.l.",
    "wof:placetype":"venue"
},
  "geometry": {"coordinates":[5.8199501038,50.5231590271],"type":"Point"}
}