{
  "type": "Feature",
  "properties": {
    "iso:country":"BE",
    "sg:address":"Koopvaardijlaan 26",
    "sg:city":"Gent",
    "sg:classifiers":[
        {
            "category":"Cafe",
            "type":"Food & Drink"
        }
    ],
    "sg:phone":"+32 9 225 90 70",
    "sg:postcode":"9000",
    "sg:province":"Oost-Vlaanderen",
    "sg:tags":[
        "caf\u00e9s"
    ],
    "wof:name":"Noella Van Bever",
    "wof:placetype":"venue"
},
  "geometry": {"coordinates":[3.7396559715,51.0587882996],"type":"Point"}
}