{
  "type": "Feature",
  "properties": {
    "addr:full":"Ossestraat 15 Moeskroen/mouscron Hainaut 7700",
    "addr:housenumber":"15",
    "addr:postcode":"7700",
    "addr:street":"Ossestraat",
    "iso:country":"BE",
    "sg:address":"Ossestraat 15",
    "sg:city":"Moeskroen/mouscron",
    "sg:orig_category":"Rundveehouders",
    "sg:phone":"+32 56 33 09 12",
    "sg:postcode":"7700",
    "sg:province":"Hainaut",
    "wof:name":"Frans Deconinck",
    "wof:placetype":"venue"
},
  "geometry": {"coordinates":[3.2692329884,50.7466773987],"type":"Point"}
}