{
  "type": "Feature",
  "properties": {
    "addr:full":"Rue Alphonse Gravis 61 Binche Hainaut 7134",
    "addr:housenumber":"61",
    "addr:postcode":"7134",
    "addr:street":"Rue Alphonse Gravis",
    "iso:country":"BE",
    "sg:address":"Rue Alphonse Gravis 61",
    "sg:city":"Binche",
    "sg:orig_category":"Slagers",
    "sg:phone":"+32 64 33 21 00",
    "sg:postcode":"7134",
    "sg:province":"Hainaut",
    "wof:name":"Luc Tricote",
    "wof:placetype":"venue"
},
  "geometry": {"coordinates":[4.2175779343,50.4159622192],"type":"Point"}
}