{
  "type": "Feature",
  "properties": {
    "addr:full":"Lindenstraat 30 Keerbergen Vlaams-Brabant 3140",
    "addr:housenumber":"30",
    "addr:postcode":"3140",
    "addr:street":"Lindenstraat",
    "iso:country":"BE",
    "sg:address":"Lindenstraat 30",
    "sg:city":"Keerbergen",
    "sg:classifiers":[
        {
            "category":"Professional",
            "subcategory":"Computer Services",
            "type":"Services"
        }
    ],
    "sg:phone":"+32 477 54 98 46",
    "sg:postcode":"3140",
    "sg:province":"Vlaams-Brabant",
    "sg:tags":[
        "webdesign",
        "-",
        "internet"
    ],
    "wof:name":"Dream Designs",
    "wof:placetype":"venue"
},
  "geometry": {"coordinates":[4.6343541145,51.0017585754],"type":"Point"}
}