{
  "type": "Feature",
  "properties": {
    "iso:country":"BE",
    "sg:address":"Geraardsbergsestraat 135",
    "sg:city":"Ninove",
    "sg:orig_category":"Pain, p\u00e2tisseries and confiseries",
    "sg:phone":"+32 54 33 26 27",
    "sg:postcode":"9400",
    "sg:province":"Oost-Vlaanderen",
    "wof:name":"Gino Sonck",
    "wof:placetype":"venue"
},
  "geometry": {"coordinates":[4.0149288177,50.8364982605],"type":"Point"}
}