{
  "type": "Feature",
  "properties": {
    "iso:country":"BE",
    "sg:address":"Wazenaarstraat 13",
    "sg:city":"Gent (ledeberg)",
    "sg:classifiers":[
        {
            "category":"Building & Trades",
            "subcategory":"Pest Control",
            "type":"Services"
        }
    ],
    "sg:phone":"+32 9 231 05 85",
    "sg:postcode":"9050",
    "sg:province":"Oost-Vlaanderen",
    "sg:tags":[
        "painting",
        "contractor"
    ],
    "wof:name":"Peeters G",
    "wof:placetype":"venue"
},
  "geometry": {"coordinates":[3.7452208996,51.0410461426],"type":"Point"}
}