{
  "type": "Feature",
  "properties": {
    "addr:full":"Lammekensstraat 15 Oudenaarde Oost-Vlaanderen 9700",
    "addr:housenumber":"15",
    "addr:postcode":"9700",
    "addr:street":"Lammekensstraat",
    "iso:country":"BE",
    "sg:address":"Lammekensstraat 15",
    "sg:city":"Oudenaarde",
    "sg:orig_category":"Parfumeries",
    "sg:phone":"+32 55 31 02 77",
    "sg:postcode":"9700",
    "sg:province":"Oost-Vlaanderen",
    "wof:name":"Johan Vindevogel",
    "wof:placetype":"venue"
},
  "geometry": {"coordinates":[3.6052238941,50.8248214722],"type":"Point"}
}