{
  "type": "Feature",
  "properties": {
    "iso:country":"BE",
    "sg:address":"Rue Joseph Stallaert 79",
    "sg:city":"Bruxelles (uccle)",
    "sg:classifiers":[
        {
            "category":"Real Estate",
            "subcategory":"Architect",
            "type":"Services"
        }
    ],
    "sg:phone":"+32 2 346 15 10",
    "sg:postcode":"1180",
    "sg:province":"Bruxelles-Capitale",
    "wof:name":"Degrune V",
    "wof:placetype":"venue"
},
  "geometry": {"coordinates":[4.3559269905,50.8144111633],"type":"Point"}
}