{
  "type": "Feature",
  "properties": {
    "addr:full":"Boulevard Mairaux 4 La Louviere Hainaut 7100",
    "addr:housenumber":"4",
    "addr:postcode":"7100",
    "addr:street":"Boulevard Mairaux",
    "iso:country":"BE",
    "sg:address":"Boulevard Mairaux 4",
    "sg:city":"La Louviere",
    "sg:classifiers":[
        {
            "category":"Fast Food",
            "type":"Food & Drink"
        }
    ],
    "sg:phone":"+32 64 21 43 27",
    "sg:postcode":"7100",
    "sg:province":"Hainaut",
    "sg:tags":[
        "\u00c0",
        "restaurants",
        "emporter",
        "restaurant"
    ],
    "wof:name":"Le Xalkis",
    "wof:placetype":"venue"
},
  "geometry": {"coordinates":[4.1868457794,50.479057312],"type":"Point"}
}