{
  "type": "Feature",
  "properties": {
    "iso:country":"BE",
    "sg:address":"Av De La Concorde 227",
    "sg:city":"Seraing",
    "sg:classifiers":[
        {
            "category":"Restaurant",
            "type":"Food & Drink"
        }
    ],
    "sg:phone":"+32 4 337 18 52",
    "sg:postcode":"4100",
    "sg:province":"Li\u00e8ge",
    "wof:name":"Aris",
    "wof:placetype":"venue"
},
  "geometry": {"coordinates":[5.501180172,50.5961303711],"type":"Point"}
}