{
  "type": "Feature",
  "properties": {
    "iso:country":"BE",
    "sg:address":"Rue Des Combattants 66",
    "sg:city":"La Hulpe",
    "sg:classifiers":[
        {
            "category":"Shopping",
            "subcategory":"Optician",
            "type":"Retail Goods"
        }
    ],
    "sg:phone":"+32 2 652 25 57",
    "sg:postcode":"1310",
    "sg:province":"Brabant Wallon",
    "sg:tags":[
        "-"
    ],
    "wof:name":"Optique Daenen",
    "wof:placetype":"venue"
},
  "geometry": {"coordinates":[4.4880127907,50.7312431335],"type":"Point"}
}