{
  "type": "Feature",
  "properties": {
    "iso:country":"BE",
    "sg:address":"Geraardsbergsesteenweg 258",
    "sg:city":"Nederhasselt",
    "sg:classifiers":[
        {
            "category":"Home & Garden",
            "subcategory":"Furniture",
            "type":"Retail Goods"
        }
    ],
    "sg:phone":"+32 54 33 53 70",
    "sg:postcode":"9400",
    "sg:province":"Oost-Vlaanderen",
    "sg:tags":[
        "household",
        "wood"
    ],
    "wof:name":"Ver De Braeckeleer M & C",
    "wof:placetype":"venue"
},
  "geometry": {"coordinates":[3.9588270187,50.8503112793],"type":"Point"}
}