{
  "type": "Feature",
  "properties": {
    "addr:full":"Rue De Marchienne 37 Box 4 Thuin (goz\u00e9e) Hainaut 6534",
    "addr:housenumber":"37;4",
    "addr:postcode":"6534",
    "addr:street":"Rue De Marchienne;Box",
    "iso:country":"BE",
    "sg:address":"Rue De Marchienne 37 Box 4",
    "sg:city":"Thuin (goz\u00e9e)",
    "sg:classifiers":[
        {
            "category":"Retail",
            "subcategory":"Animal Services",
            "type":"Services"
        }
    ],
    "sg:phone":"+32 71 56 20 17",
    "sg:postcode":"6534",
    "sg:province":"Hainaut",
    "sg:tags":[
        "grooming",
        "-",
        "dog"
    ],
    "wof:name":"Jolis Dogs",
    "wof:placetype":"venue"
},
  "geometry": {"coordinates":[4.354282856,50.3364830017],"type":"Point"}
}