{
  "type": "Feature",
  "properties": {
    "addr:full":"Avenue Albert 10a Bruxelles (forest) Bruxelles-Capitale 1190",
    "addr:housenumber":"10a",
    "addr:postcode":"1190",
    "addr:street":"Avenue Albert",
    "iso:country":"BE",
    "sg:address":"Avenue Albert 10a",
    "sg:city":"Bruxelles (forest)",
    "sg:classifiers":[
        {
            "category":"Health Services",
            "subcategory":"Doctor",
            "type":"Services"
        }
    ],
    "sg:phone":"+32 2 345 99 59",
    "sg:postcode":"1190",
    "sg:province":"Bruxelles-Capitale",
    "sg:tags":[
        "medicinephysicians",
        "surgeon"
    ],
    "wof:name":"Grynberg H",
    "wof:placetype":"venue"
},
  "geometry": {"coordinates":[4.3433270454,50.8214874268],"type":"Point"}
}