{
  "type": "Feature",
  "properties": {
    "addr:full":"Processiestraat 2 Lennik (sint-martens-lennik) Vlaams-Brabant 1750",
    "addr:housenumber":"2",
    "addr:postcode":"1750",
    "addr:street":"Processiestraat",
    "iso:country":"BE",
    "sg:address":"Processiestraat 2",
    "sg:city":"Lennik (sint-martens-lennik)",
    "sg:classifiers":[
        {
            "category":"Banks & Credit Unions",
            "subcategory":"Bureau De Change",
            "type":"Services"
        }
    ],
    "sg:phone":"+32 2 532 17 74",
    "sg:postcode":"1750",
    "sg:province":"Vlaams-Brabant",
    "sg:tags":[
        "measuring",
        "control",
        "apparatus"
    ],
    "wof:name":"Sensors Belgium Nv",
    "wof:placetype":"venue"
},
  "geometry": {"coordinates":[4.1760931015,50.8138771057],"type":"Point"}
}