{
  "type": "Feature",
  "properties": {
    "iso:country":"BE",
    "sg:address":"Aven Ackers 17",
    "sg:city":"Beveren (verrebroek)",
    "sg:classifiers":[
        {
            "category":"Freight",
            "type":"Transportation"
        }
    ],
    "sg:phone":"+32 3 773 27 03",
    "sg:postcode":"9130",
    "sg:province":"Oost-Vlaanderen",
    "sg:tags":[
        "-",
        "transport"
    ],
    "wof:name":"Franssens W Nv",
    "wof:placetype":"venue"
},
  "geometry": {"coordinates":[4.1916561127,51.2499694824],"type":"Point"}
}