{
  "type": "Feature",
  "properties": {
    "iso:country":"BE",
    "sg:address":"Blankenbergsedijk 138",
    "sg:city":"Blankenberge",
    "sg:orig_category":"Animaux domestiques and accessoires. Articles de jardin",
    "sg:phone":"+32 50 41 16 43",
    "sg:postcode":"8370",
    "sg:province":"West-Vlaanderen",
    "wof:name":"Aveve",
    "wof:placetype":"venue"
},
  "geometry": {"coordinates":[3.1377799511,51.3041305542],"type":"Point"}
}