{
  "type": "Feature",
  "properties": {
    "iso:country":"BE",
    "sg:address":"Wingerstraat 59",
    "sg:city":"Tielt-winge (sint-joris-winge)",
    "sg:classifiers":[
        {
            "category":"Professional",
            "subcategory":"Accounting & Tax Preparation",
            "type":"Services"
        }
    ],
    "sg:phone":"+32 16 63 32 50",
    "sg:postcode":"3390",
    "sg:province":"Vlaams-Brabant",
    "sg:tags":[
        "bookkeeper"
    ],
    "wof:name":"Fiduca Nv",
    "wof:placetype":"venue"
},
  "geometry": {"coordinates":[4.8766617775,50.919090271],"type":"Point"}
}