{
  "type": "Feature",
  "properties": {
    "addr:full":"Avenue De L'id\u00e9al 35 Bruxelles (woluwe-saint-lambert) Bruxelles-Capitale 1200",
    "addr:housenumber":"35",
    "addr:postcode":"1200",
    "addr:street":"Avenue De L'Ide \u0301Al",
    "iso:country":"BE",
    "sg:address":"Avenue De L'id\u00e9al 35",
    "sg:city":"Bruxelles (woluwe-saint-lambert)",
    "sg:classifiers":[
        {
            "category":"Health Services",
            "subcategory":"Health Practitioner",
            "type":"Services"
        }
    ],
    "sg:phone":"+32 2 538 73 17",
    "sg:postcode":"1200",
    "sg:province":"Bruxelles-Capitale",
    "sg:tags":[
        "physiotherapist"
    ],
    "wof:name":"Delecluse V",
    "wof:placetype":"venue"
},
  "geometry": {"coordinates":[4.4567861557,50.8484687805],"type":"Point"}
}