{
  "type": "Feature",
  "properties": {
    "addr:full":"Z/n Kaai Nieuwpoort West-Vlaanderen 8620",
    "addr:housenumber":"z / n",
    "addr:postcode":"8620",
    "addr:street":"Kaai",
    "iso:country":"BE",
    "sg:address":"Z/n Kaai",
    "sg:city":"Nieuwpoort",
    "sg:orig_category":"Diverse voedingsmiddelen Gh",
    "sg:phone":"+32 58 23 33 64",
    "sg:postcode":"8620",
    "sg:province":"West-Vlaanderen",
    "wof:name":"Nieuwpoortse Vismijn",
    "wof:placetype":"venue"
},
  "geometry": {"coordinates":[2.748208046,51.1331939697],"type":"Point"}
}