{
  "type": "Feature",
  "properties": {
    "addr:full":"Rue De Cambron 47 Lens Hainaut 7870",
    "addr:housenumber":"47",
    "addr:postcode":"7870",
    "addr:street":"Rue De Cambron",
    "iso:country":"BE",
    "sg:address":"Rue De Cambron 47",
    "sg:city":"Lens",
    "sg:orig_category":"Rundveehouders",
    "sg:phone":"+32 68 45 46 41",
    "sg:postcode":"7870",
    "sg:province":"Hainaut",
    "wof:name":"Fourez Daniel Et Pascal",
    "wof:placetype":"venue"
},
  "geometry": {"coordinates":[3.9038419724,50.5634231567],"type":"Point"}
}