{
  "type": "Feature",
  "properties": {
    "iso:country":"BE",
    "sg:address":"A Bliecklaan 17",
    "sg:city":"Koksijde",
    "sg:orig_category":"Animations diverses",
    "sg:phone":"+32 58 52 18 90",
    "sg:postcode":"8670",
    "sg:province":"West-Vlaanderen",
    "wof:name":"Discobar Starlight",
    "wof:placetype":"venue"
},
  "geometry": {"coordinates":[2.6366040707,51.1154747009],"type":"Point"}
}