{
  "type": "Feature",
  "properties": {
    "iso:country":"BE",
    "sg:address":"Frijselstraat 10",
    "sg:city":"Kampenhout",
    "sg:orig_category":"Groententeelt Rundveehouders",
    "sg:phone":"+32 16 65 50 69",
    "sg:postcode":"1910",
    "sg:province":"Vlaams-Brabant",
    "wof:name":"Omer Vandenbalck",
    "wof:placetype":"venue"
},
  "geometry": {"coordinates":[4.5438189507,50.9548187256],"type":"Point"}
}