{
  "type": "Feature",
  "properties": {
    "addr:full":"Fr. D. Rooseveltstraat 1 Niel Antwerpen 2845",
    "addr:housenumber":"1",
    "addr:postcode":"2845",
    "addr:street":"Fr. D. Rooseveltstraat",
    "iso:country":"BE",
    "sg:address":"Fr. D. Rooseveltstraat 1",
    "sg:city":"Niel",
    "sg:orig_category":"Herstellingen and onderhoud van auto's",
    "sg:phone":"+32 3 844 24 45",
    "sg:postcode":"2845",
    "sg:province":"Antwerpen",
    "wof:name":"L. Faucompret",
    "wof:placetype":"venue"
},
  "geometry": {"coordinates":[4.3393058777,51.1100578308],"type":"Point"}
}