{
  "type": "Feature",
  "properties": {
    "iso:country":"BE",
    "sg:address":"Rue De Bouvy 18",
    "sg:city":"La Louviere",
    "sg:orig_category":"Slagers",
    "sg:phone":"+32 64 22 40 21",
    "sg:postcode":"7100",
    "sg:province":"Hainaut",
    "wof:name":"Boucherie Michel",
    "wof:placetype":"venue"
},
  "geometry": {"coordinates":[4.1857328415,50.4739952087],"type":"Point"}
}