{
  "type": "Feature",
  "properties": {
    "addr:full":"Boulevard Sylvain Dupuis 243 Bruxelles (anderlecht) Bruxelles-Capitale 1070",
    "addr:housenumber":"243",
    "addr:postcode":"1070",
    "addr:street":"Boulevard Sylvain Dupuis",
    "iso:country":"BE",
    "sg:address":"Boulevard Sylvain Dupuis 243",
    "sg:city":"Bruxelles (anderlecht)",
    "sg:classifiers":[
        {
            "category":"Banks & Credit Unions",
            "subcategory":"Investment Brokerage",
            "type":"Services"
        }
    ],
    "sg:phone":"+32 2 559 08 90",
    "sg:postcode":"1070",
    "sg:province":"Bruxelles-Capitale",
    "sg:tags":[
        "auditor"
    ],
    "wof:name":"Salustro Triest Vleck",
    "wof:placetype":"venue"
},
  "geometry": {"coordinates":[4.2907037735,50.8376426697],"type":"Point"}
}