{
  "type": "Feature",
  "properties": {
    "addr:full":"Sint-jozefstraat 5 Hechtel-eksel Limburg 3941",
    "addr:housenumber":"5",
    "addr:postcode":"3941",
    "addr:street":"Sint-Jozefstraat",
    "iso:country":"BE",
    "sg:address":"Sint-jozefstraat 5",
    "sg:city":"Hechtel-eksel",
    "sg:orig_category":"Cr\u00e8ches and garderies d'enfants",
    "sg:phone":"+32 11 73 13 88",
    "sg:postcode":"3941",
    "sg:province":"Limburg",
    "wof:name":"Kribbe De Speelvogel",
    "wof:placetype":"venue"
},
  "geometry": {"coordinates":[5.38854599,51.155040741],"type":"Point"}
}