{
  "type": "Feature",
  "properties": {
    "addr:full":"Koolmijnlaan 350 Heusden-zolder (zolder) Limburg 3550",
    "addr:housenumber":"350",
    "addr:postcode":"3550",
    "addr:street":"Koolmijnlaan",
    "iso:country":"BE",
    "sg:address":"Koolmijnlaan 350",
    "sg:city":"Heusden-zolder (zolder)",
    "sg:classifiers":[
        {
            "category":"Social Services",
            "type":"Services"
        }
    ],
    "sg:phone":"+32 11 57 49 94",
    "sg:postcode":"3550",
    "sg:province":"Limburg",
    "wof:name":"Vormingscentra Agora",
    "wof:placetype":"venue"
},
  "geometry": {"coordinates":[5.3253960609,51.038848877],"type":"Point"}
}