{
  "type": "Feature",
  "properties": {
    "addr:full":"Louisegalerij 109-117 Elsene/ixelles Bruxelles-Capitale 1050",
    "addr:housenumber":"109-117",
    "addr:postcode":"1050",
    "iso:country":"BE",
    "sg:address":"Louisegalerij 109-117",
    "sg:city":"Elsene/ixelles",
    "sg:orig_category":"Verlichting and huishoudartikelen",
    "sg:phone":"+32 2 512 45 97",
    "sg:postcode":"1050",
    "sg:province":"Bruxelles-Capitale",
    "wof:name":"Maison Forrest",
    "wof:placetype":"venue"
},
  "geometry": {"coordinates":[4.355919838,50.8357810974],"type":"Point"}
}