{
  "type": "Feature",
  "properties": {
    "addr:full":"Dagsterrestraat 6 Sint-gillis-waas Oost-Vlaanderen 9170",
    "addr:housenumber":"6",
    "addr:postcode":"9170",
    "addr:street":"Dagsterrestraat",
    "iso:country":"BE",
    "sg:address":"Dagsterrestraat 6",
    "sg:city":"Sint-gillis-waas",
    "sg:classifiers":[
        {
            "category":"Retail",
            "subcategory":"Repair Shop",
            "type":"Services"
        }
    ],
    "sg:phone":"+32 3 707 01 22",
    "sg:postcode":"9170",
    "sg:province":"Oost-Vlaanderen",
    "sg:tags":[
        "radio",
        "television",
        "-",
        "maintenance"
    ],
    "wof:name":"Beeld En Klank 't Hoeveke",
    "wof:placetype":"venue"
},
  "geometry": {"coordinates":[4.1477332115,51.2054328918],"type":"Point"}
}