{
  "type": "Feature",
  "properties": {
    "addr:full":"Moorselestraat 116 Wevelgem West-Vlaanderen 8560",
    "addr:housenumber":"116",
    "addr:postcode":"8560",
    "addr:street":"Moorselestraat",
    "iso:country":"BE",
    "sg:address":"Moorselestraat 116",
    "sg:city":"Wevelgem",
    "sg:orig_category":"V\u00eatements",
    "sg:phone":"+32 56 41 93 03",
    "sg:postcode":"8560",
    "sg:province":"West-Vlaanderen",
    "wof:name":"Nathalie France",
    "wof:placetype":"venue"
},
  "geometry": {"coordinates":[3.1705839634,50.8128089905],"type":"Point"}
}