{
  "type": "Feature",
  "properties": {
    "iso:country":"BE",
    "sg:address":"Rue Du Miroir 6",
    "sg:city":"Mons",
    "sg:orig_category":"Kapsalons",
    "sg:phone":"+32 65 35 20 84",
    "sg:postcode":"7000",
    "sg:province":"Hainaut",
    "wof:name":"Rene Gondry",
    "wof:placetype":"venue"
},
  "geometry": {"coordinates":[3.9529869556,50.4547615051],"type":"Point"}
}