{
  "type": "Feature",
  "properties": {
    "addr:full":"Rue De Formanoir 13 Bruxelles (anderlecht) Bruxelles-Capitale 1070",
    "addr:housenumber":"13",
    "addr:postcode":"1070",
    "addr:street":"Rue De Formanoir",
    "iso:country":"BE",
    "sg:address":"Rue De Formanoir 13",
    "sg:city":"Bruxelles (anderlecht)",
    "sg:classifiers":[
        {
            "category":"Retail",
            "subcategory":"Animal Services",
            "type":"Services"
        }
    ],
    "sg:phone":"+32 2 523 19 28",
    "sg:postcode":"1070",
    "sg:province":"Bruxelles-Capitale",
    "sg:tags":[
        "grooming",
        "-",
        "dog"
    ],
    "wof:name":"Pretty Dog",
    "wof:placetype":"venue"
},
  "geometry": {"coordinates":[4.3079299927,50.8356132507],"type":"Point"}
}