{
  "type": "Feature",
  "properties": {
    "iso:country":"BE",
    "sg:address":"Aalbeeksesteenweg 13",
    "sg:city":"Kortrijk",
    "sg:classifiers":[
        {
            "category":"Social Services",
            "type":"Services"
        }
    ],
    "sg:phone":"+32 497 53 43 19",
    "sg:postcode":"8500",
    "sg:province":"West-Vlaanderen",
    "wof:name":"Damiaan Vormingscentrum Vzw",
    "wof:placetype":"venue"
},
  "geometry": {"coordinates":[3.258713007,50.8219490051],"type":"Point"}
}