{
  "type": "Feature",
  "properties": {
    "addr:full":"Acacialaan 28 Beringen Limburg 3583",
    "addr:housenumber":"28",
    "addr:postcode":"3583",
    "addr:street":"Acacialaan",
    "iso:country":"BE",
    "sg:address":"Acacialaan 28",
    "sg:city":"Beringen",
    "sg:orig_category":"Dierenartsen",
    "sg:phone":"+32 11 45 41 28",
    "sg:postcode":"3583",
    "sg:province":"Limburg",
    "wof:name":"I. Rediers",
    "wof:placetype":"venue"
},
  "geometry": {"coordinates":[5.1706700325,51.0389442444],"type":"Point"}
}