{
  "type": "Feature",
  "properties": {
    "addr:full":"Chauss\u00c9e De Boondael 92 Elsene/ixelles Bruxelles-Capitale 1050",
    "addr:housenumber":"92",
    "addr:postcode":"1050",
    "addr:street":"Chausse\u0301E De Boondael",
    "iso:country":"BE",
    "sg:address":"Chauss\u00c9e De Boondael 92",
    "sg:city":"Elsene/ixelles",
    "sg:classifiers":[
        {
            "category":"Health Services",
            "subcategory":"Nursing And Care Facility",
            "type":"Services"
        }
    ],
    "sg:phone":"+32 2 641 54 11",
    "sg:postcode":"1050",
    "sg:province":"Bruxelles-Capitale",
    "sg:tags":[
        "public"
    ],
    "wof:name":"O.c.m.w.",
    "wof:placetype":"venue"
},
  "geometry": {"coordinates":[4.3767528534,50.8251647949],"type":"Point"}
}