{
  "type": "Feature",
  "properties": {
    "addr:full":"Generaal Baron Jacquesstraat 30 Diksmuide West-Vlaanderen 8600",
    "addr:housenumber":"30",
    "addr:postcode":"8600",
    "addr:street":"Generaal Baron Jacquesstraat",
    "iso:country":"BE",
    "sg:address":"Generaal Baron Jacquesstraat 30",
    "sg:city":"Diksmuide",
    "sg:classifiers":[
        {
            "category":"Home & Garden",
            "subcategory":"Home Furnishings",
            "type":"Retail Goods"
        }
    ],
    "sg:phone":"+32 51 50 02 30",
    "sg:postcode":"8600",
    "sg:province":"West-Vlaanderen",
    "sg:tags":[
        "linen",
        "household",
        "-"
    ],
    "wof:name":"Travers A",
    "wof:placetype":"venue"
},
  "geometry": {"coordinates":[2.862030983,51.0333366394],"type":"Point"}
}