{
  "type": "Feature",
  "properties": {
    "addr:full":"Diestsestraat 62 Scherpenheuvel-zichem Vlaams-Brabant 3270",
    "addr:housenumber":"62",
    "addr:postcode":"3270",
    "addr:street":"Diestsestraat",
    "iso:country":"BE",
    "sg:address":"Diestsestraat 62",
    "sg:city":"Scherpenheuvel-zichem",
    "sg:orig_category":"Fietsen Herstellingen motorfietsen Motorfietsen",
    "sg:phone":"+32 13 77 32 07",
    "sg:postcode":"3270",
    "sg:province":"Vlaams-Brabant",
    "wof:name":"Mesens",
    "wof:placetype":"venue"
},
  "geometry": {"coordinates":[4.9882497787,50.978679657],"type":"Point"}
}