{
  "type": "Feature",
  "properties": {
    "addr:full":"Demetskaai (fernand) 211 Brussel Bruxelles-Capitale 1070",
    "addr:housenumber":"211",
    "addr:postcode":"1070",
    "addr:street":"Fernand",
    "iso:country":"BE",
    "sg:address":"Demetskaai (fernand) 211",
    "sg:city":"Brussel",
    "sg:orig_category":"Chromating",
    "sg:phone":"+32 3 645 35 47",
    "sg:postcode":"1070",
    "sg:province":"Bruxelles-Capitale",
    "wof:name":"Werkhuizen Taeymans - Lysen B.v.b.a.",
    "wof:placetype":"venue"
},
  "geometry": {"coordinates":[4.4370279312,51.2378997803],"type":"Point"}
}