{
  "type": "Feature",
  "properties": {
    "addr:full":"Louizalaan 149b11 Brussel/bruxelles Bruxelles-Capitale 1150",
    "addr:housenumber":"149b11",
    "addr:postcode":"1150",
    "addr:street":"Louizalaan;/",
    "iso:country":"BE",
    "sg:address":"Louizalaan 149b11",
    "sg:city":"Brussel/bruxelles",
    "sg:orig_category":"Marktonderzoekbureaus Reclamebureaus Software ontwikkeling and ontwerp",
    "sg:phone":"+32 2 761 19 00",
    "sg:postcode":"1150",
    "sg:province":"Bruxelles-Capitale",
    "wof:name":"Marketing Power",
    "wof:placetype":"venue"
},
  "geometry": {"coordinates":[4.4469199181,50.8315811157],"type":"Point"}
}