{
  "type": "Feature",
  "properties": {
    "addr:full":"Schuiferskapelsesteenweg 80 Tielt West-Vlaanderen 8700",
    "addr:housenumber":"80",
    "addr:postcode":"8700",
    "addr:street":"Schuiferskapelsesteenweg",
    "iso:country":"BE",
    "sg:address":"Schuiferskapelsesteenweg 80",
    "sg:city":"Tielt",
    "sg:orig_category":"Eleveurs de bovins. Eleveurs and marchands de porcs",
    "sg:phone":"+32 51 40 07 23",
    "sg:postcode":"8700",
    "sg:province":"West-Vlaanderen",
    "wof:name":"Verhulst & Vanvruwaene",
    "wof:placetype":"venue"
},
  "geometry": {"coordinates":[3.3349719048,51.0226974487],"type":"Point"}
}