{
  "type": "Feature",
  "properties": {
    "addr:full":"Meensesteenweg 303 Kortrijk (bissegem) West-Vlaanderen 8501",
    "addr:housenumber":"303",
    "addr:postcode":"8501",
    "addr:street":"Meensesteenweg",
    "iso:country":"BE",
    "sg:address":"Meensesteenweg 303",
    "sg:city":"Kortrijk (bissegem)",
    "sg:orig_category":"Non-Classified Establishments",
    "sg:phone":"+32 56 35 30 73",
    "sg:postcode":"8501",
    "sg:province":"West-Vlaanderen",
    "wof:name":"Vermandele W",
    "wof:placetype":"venue"
},
  "geometry": {"coordinates":[3.2318210602,50.824546814],"type":"Point"}
}