{
  "type": "Feature",
  "properties": {
    "iso:country":"BE",
    "sg:address":"Lamstraat 40",
    "sg:city":"Stekene",
    "sg:classifiers":[
        {
            "category":"Farming",
            "subcategory":"Livestock Farm",
            "type":"Manufacturing & Wholesale Goods"
        }
    ],
    "sg:phone":"+32 3 789 11 72",
    "sg:postcode":"9190",
    "sg:province":"Oost-Vlaanderen",
    "sg:tags":[
        "horse"
    ],
    "wof:name":"Foubert Gebr",
    "wof:placetype":"venue"
},
  "geometry": {"coordinates":[4.0687761307,51.2149009705],"type":"Point"}
}