{
  "type": "Feature",
  "properties": {
    "iso:country":"BE",
    "sg:address":"Borgerhoutsendijk 400",
    "sg:city":"Mol",
    "sg:orig_category":"Rundveehouders",
    "sg:phone":"+32 14 31 05 78",
    "sg:postcode":"2400",
    "sg:province":"Antwerpen",
    "wof:name":"Lommelen J. & G.-tormans",
    "wof:placetype":"venue"
},
  "geometry": {"coordinates":[5.1043429375,51.163772583],"type":"Point"}
}