{
  "type": "Feature",
  "properties": {
    "addr:full":"Kouterstraat 111 Laarne Oost-Vlaanderen 9270",
    "addr:housenumber":"111",
    "addr:postcode":"9270",
    "addr:street":"Kouterstraat",
    "iso:country":"BE",
    "sg:address":"Kouterstraat 111",
    "sg:city":"Laarne",
    "sg:classifiers":[
        {
            "category":"Manufacturing",
            "subcategory":"Textiles",
            "type":"Manufacturing & Wholesale Goods"
        }
    ],
    "sg:phone":"+32 9 367 63 34",
    "sg:postcode":"9270",
    "sg:province":"Oost-Vlaanderen",
    "wof:name":"Vandendriessche Textiel",
    "wof:placetype":"venue"
},
  "geometry": {"coordinates":[3.8522200584,51.0269813538],"type":"Point"}
}