{
  "type": "Feature",
  "properties": {
    "iso:country":"BE",
    "sg:address":"Passage De La Bourse 22",
    "sg:city":"Charleroi",
    "sg:classifiers":[
        {
            "category":"Professional",
            "subcategory":"Computer Services",
            "type":"Services"
        }
    ],
    "sg:phone":"+32 71 79 68 96",
    "sg:postcode":"6000",
    "sg:province":"Hainaut",
    "sg:tags":[
        "-",
        "processing",
        "data"
    ],
    "wof:name":"Neuronics",
    "wof:placetype":"venue"
},
  "geometry": {"coordinates":[4.4405870438,50.4069786072],"type":"Point"}
}