{
  "type": "Feature",
  "properties": {
    "addr:full":"Voorhavenlaan 98 Oostende West-Vlaanderen 8400",
    "addr:housenumber":"98",
    "addr:postcode":"8400",
    "addr:street":"Voorhavenlaan",
    "iso:country":"BE",
    "sg:address":"Voorhavenlaan 98",
    "sg:city":"Oostende",
    "sg:classifiers":[
        {
            "category":"Health Services",
            "subcategory":"Health Practitioner",
            "type":"Services"
        }
    ],
    "sg:phone":"+32 477 62 68 64",
    "sg:postcode":"8400",
    "sg:province":"West-Vlaanderen",
    "sg:tags":[
        "physiotherapist"
    ],
    "wof:name":"Decorte Tom",
    "wof:placetype":"venue"
},
  "geometry": {"coordinates":[2.9126999378,51.2312583923],"type":"Point"}
}