{
  "type": "Feature",
  "properties": {
    "addr:full":"Baeckelmansstraat 50 Willebroek Antwerpen 2830",
    "addr:housenumber":"50",
    "addr:postcode":"2830",
    "addr:street":"Baeckelmansstraat",
    "iso:country":"BE",
    "sg:address":"Baeckelmansstraat 50",
    "sg:city":"Willebroek",
    "sg:orig_category":"Bloemen and planten",
    "sg:phone":"+32 3 886 67 04",
    "sg:postcode":"2830",
    "sg:province":"Antwerpen",
    "wof:name":"Edelnelken",
    "wof:placetype":"venue"
},
  "geometry": {"coordinates":[4.3540167809,51.0353622437],"type":"Point"}
}