{
  "type": "Feature",
  "properties": {
    "iso:country":"BE",
    "sg:address":"Columbiastraat 4",
    "sg:city":"Antwerpen",
    "sg:orig_category":"Instellingen voor probleemkinderen Kindertehuizen",
    "sg:phone":"+32 3 541 11 89",
    "sg:postcode":"2030",
    "sg:province":"Antwerpen",
    "wof:name":"Home Zon En Hei",
    "wof:placetype":"venue"
},
  "geometry": {"coordinates":[4.4239940643,51.2457466125],"type":"Point"}
}