{
  "type": "Feature",
  "properties": {
    "addr:full":"Koning Albertstraat 13 Assenede Oost-Vlaanderen 9968",
    "addr:housenumber":"13",
    "addr:postcode":"9968",
    "addr:street":"Koning Albertstraat",
    "iso:country":"BE",
    "sg:address":"Koning Albertstraat 13",
    "sg:city":"Assenede",
    "sg:classifiers":[
        {
            "category":"Communications",
            "subcategory":"Radio Station",
            "type":"Services"
        }
    ],
    "sg:phone":"+32 9 373 83 93",
    "sg:postcode":"9968",
    "sg:province":"Oost-Vlaanderen",
    "sg:tags":[
        "diffusion",
        "production",
        "de",
        "programme"
    ],
    "wof:name":"Radio Aktief Oosteeklo",
    "wof:placetype":"venue"
},
  "geometry": {"coordinates":[3.684014082,51.1929092407],"type":"Point"}
}