{
  "type": "Feature",
  "properties": {
    "addr:full":"Van Peborghlei 15bbis Mortsel Antwerpen 2640",
    "addr:postcode":"2640",
    "iso:country":"BE",
    "sg:address":"Van Peborghlei 15bbis",
    "sg:city":"Mortsel",
    "sg:orig_category":"Agences de publicit\u00e9",
    "sg:phone":"+32 3 449 59 28",
    "sg:postcode":"2640",
    "sg:province":"Antwerpen",
    "wof:name":"Intersticker",
    "wof:placetype":"venue"
},
  "geometry": {"coordinates":[4.44475317,51.1723175049],"type":"Point"}
}