{
  "type": "Feature",
  "properties": {
    "addr:full":"Groenestraat 5 Alveringem West-Vlaanderen 8691",
    "addr:housenumber":"5",
    "addr:postcode":"8691",
    "addr:street":"Groenestraat",
    "iso:country":"BE",
    "sg:address":"Groenestraat 5",
    "sg:city":"Alveringem",
    "sg:orig_category":"Slagers",
    "sg:phone":"+32 58 29 92 18",
    "sg:postcode":"8691",
    "sg:province":"West-Vlaanderen",
    "wof:name":"Denis Secq",
    "wof:placetype":"venue"
},
  "geometry": {"coordinates":[2.6652519703,50.9701004028],"type":"Point"}
}