{
  "type": "Feature",
  "properties": {
    "addr:full":"Kasteelstraat 120 Lichtervelde West-Vlaanderen 8810",
    "addr:housenumber":"120",
    "addr:postcode":"8810",
    "addr:street":"Kasteelstraat",
    "iso:country":"BE",
    "sg:address":"Kasteelstraat 120",
    "sg:city":"Lichtervelde",
    "sg:orig_category":"Slagers",
    "sg:phone":"+32 51 72 62 56",
    "sg:postcode":"8810",
    "sg:province":"West-Vlaanderen",
    "wof:name":"Frans Moutton",
    "wof:placetype":"venue"
},
  "geometry": {"coordinates":[3.129545927,51.0502090454],"type":"Point"}
}