{
  "type": "Feature",
  "properties": {
    "addr:full":"R. Stroobants 48a Bruxelles Bruxelles-Capitale 1140",
    "addr:housenumber":"48a",
    "addr:postcode":"1140",
    "addr:street":"Stroobants",
    "iso:country":"BE",
    "sg:address":"R. Stroobants 48a",
    "sg:city":"Bruxelles",
    "sg:classifiers":[
        {
            "category":"Shopping",
            "subcategory":"Computers & Home Electronics",
            "type":"Retail Goods"
        }
    ],
    "sg:phone":"+32 2 247 99 00",
    "sg:postcode":"1140",
    "sg:province":"Bruxelles-Capitale",
    "sg:tags":[
        "electric",
        "electricity",
        "component",
        "equipment",
        "electrical",
        "electronic"
    ],
    "wof:name":"Fci Belgium Sa",
    "wof:placetype":"venue"
},
  "geometry": {"coordinates":[4.3971171379,50.8794517517],"type":"Point"}
}