{
  "type": "Feature",
  "properties": {
    "addr:full":"Kleuterweg 25 Heusden-zolder Limburg 3550",
    "addr:housenumber":"25",
    "addr:postcode":"3550",
    "addr:street":"Kleuterweg",
    "iso:country":"BE",
    "sg:address":"Kleuterweg 25",
    "sg:city":"Heusden-zolder",
    "sg:classifiers":[
        {
            "category":"Shopping",
            "subcategory":"Clothing, Apparel, & Fashions",
            "type":"Retail Goods"
        }
    ],
    "sg:phone":"+32 11 57 23 29",
    "sg:postcode":"3550",
    "sg:province":"Limburg",
    "sg:tags":[
        "ondergoed",
        "lingerie"
    ],
    "wof:name":"Lingerie Inella",
    "wof:placetype":"venue"
},
  "geometry": {"coordinates":[5.3008618355,51.0410995483],"type":"Point"}
}