{
  "type": "Feature",
  "properties": {
    "iso:country":"BE",
    "sg:address":"Fabriekstraat 109",
    "sg:city":"Overpelt",
    "sg:orig_category":"Antiek Installatie van houten of kunststof schrijnwerk",
    "sg:phone":"+32 11 66 41 45",
    "sg:postcode":"3900",
    "sg:province":"Limburg",
    "wof:name":"Theo Schildermans",
    "wof:placetype":"venue"
},
  "geometry": {"coordinates":[5.3931899071,51.2336997986],"type":"Point"}
}