{
  "type": "Feature",
  "properties": {
    "addr:full":"Steenweg 185a Lierde (sint-martens-lierde) Oost-Vlaanderen 9572",
    "addr:housenumber":"185a",
    "addr:postcode":"9572",
    "addr:street":"Steenweg",
    "iso:country":"BE",
    "sg:address":"Steenweg 185a",
    "sg:city":"Lierde (sint-martens-lierde)",
    "sg:classifiers":[
        {
            "category":"Building & Trades",
            "subcategory":"Landscaping Services",
            "type":"Services"
        }
    ],
    "sg:phone":"+32 55 42 77 24",
    "sg:postcode":"9572",
    "sg:province":"Oost-Vlaanderen",
    "sg:tags":[
        "access",
        "pond",
        "laying-out",
        "-"
    ],
    "wof:name":"Mega Vijvercenter",
    "wof:placetype":"venue"
},
  "geometry": {"coordinates":[3.8081998825,50.8127212524],"type":"Point"}
}