{
  "type": "Feature",
  "properties": {
    "addr:full":"Stalenstraat 97 Genk Limburg 3600",
    "addr:housenumber":"97",
    "addr:postcode":"3600",
    "addr:street":"Stalenstraat",
    "iso:country":"BE",
    "sg:address":"Stalenstraat 97",
    "sg:city":"Genk",
    "sg:orig_category":"Boucheries",
    "sg:phone":"+32 89 38 25 73",
    "sg:postcode":"3600",
    "sg:province":"Limburg",
    "wof:name":"Bethlen's Delicatessen",
    "wof:placetype":"venue"
},
  "geometry": {"coordinates":[5.5201840401,50.9946174622],"type":"Point"}
}