{
  "type": "Feature",
  "properties": {
    "addr:full":"Lascheid 16 Burg-reuland Li\u00e8ge 4790",
    "addr:housenumber":"16",
    "addr:postcode":"4790",
    "addr:street":"Lascheid",
    "iso:country":"BE",
    "sg:address":"Lascheid 16",
    "sg:city":"Burg-reuland",
    "sg:orig_category":"Enseignement maternel and primaire",
    "sg:phone":"+32 80 42 01 29",
    "sg:postcode":"4790",
    "sg:province":"Li\u00e8ge",
    "wof:name":"Offizielle Grundschule",
    "wof:placetype":"venue"
},
  "geometry": {"coordinates":[6.1315770149,50.1943702698],"type":"Point"}
}