{
  "type": "Feature",
  "properties": {
    "iso:country":"BE",
    "sg:address":"Bloemendale 31",
    "sg:city":"Ieper (boezinge)",
    "sg:classifiers":[
        {
            "category":"Insurance",
            "subcategory":"Insurance Agent",
            "type":"Services"
        }
    ],
    "sg:phone":"+32 57 42 28 29",
    "sg:postcode":"8904",
    "sg:province":"West-Vlaanderen",
    "sg:tags":[
        "broker"
    ],
    "wof:name":"Wittevrongel E",
    "wof:placetype":"venue"
},
  "geometry": {"coordinates":[2.8510661125,50.8972854614],"type":"Point"}
}