{
  "type": "Feature",
  "properties": {
    "addr:full":"Krekelmotestraat 109 Izegem West-Vlaanderen 8870",
    "addr:housenumber":"109",
    "addr:postcode":"8870",
    "addr:street":"Krekelmotestraat",
    "iso:country":"BE",
    "sg:address":"Krekelmotestraat 109",
    "sg:city":"Izegem",
    "sg:classifiers":[
        {
            "category":"Professional",
            "subcategory":"Computer Services",
            "type":"Services"
        }
    ],
    "sg:phone":"+32 51 31 64 16",
    "sg:postcode":"8870",
    "sg:province":"West-Vlaanderen",
    "sg:tags":[
        "webdesign",
        "-",
        "internet"
    ],
    "wof:name":"Tales Systems",
    "wof:placetype":"venue"
},
  "geometry": {"coordinates":[3.1986899376,50.9171257019],"type":"Point"}
}