{
  "type": "Feature",
  "properties": {
    "addr:full":"Zwartkloosterstraat 60 Mechelen Antwerpen 2800",
    "addr:housenumber":"60",
    "addr:postcode":"2800",
    "addr:street":"Zwartkloosterstraat",
    "iso:country":"BE",
    "sg:address":"Zwartkloosterstraat 60",
    "sg:city":"Mechelen",
    "sg:classifiers":[
        {
            "category":"Health Services",
            "subcategory":"Dentist",
            "type":"Services"
        }
    ],
    "sg:phone":"+32 15 42 40 22",
    "sg:postcode":"2800",
    "sg:province":"Antwerpen",
    "wof:name":"Driesens Katrien",
    "wof:placetype":"venue"
},
  "geometry": {"coordinates":[4.4720749855,51.0062675476],"type":"Point"}
}