{
  "type": "Feature",
  "properties": {
    "addr:full":"Joseph Genotstraat 10 Bruxelles (berchem-sainte-agathe) Bruxelles-Capitale 1082",
    "addr:housenumber":"10",
    "addr:postcode":"1082",
    "addr:street":"Joseph Genotstraat",
    "iso:country":"BE",
    "sg:address":"Joseph Genotstraat 10",
    "sg:city":"Bruxelles (berchem-sainte-agathe)",
    "sg:classifiers":[
        {
            "category":"Health Services",
            "subcategory":"Health Practitioner",
            "type":"Services"
        }
    ],
    "sg:phone":"+32 2 465 51 53",
    "sg:postcode":"1082",
    "sg:province":"Bruxelles-Capitale",
    "sg:tags":[
        "physiotherapist"
    ],
    "wof:name":"Larock S",
    "wof:placetype":"venue"
},
  "geometry": {"coordinates":[4.3039021492,50.8614311218],"type":"Point"}
}