{
  "type": "Feature",
  "properties": {
    "addr:full":"Place Du Busteau 9 Mons Hainaut 7011",
    "addr:housenumber":"9",
    "addr:postcode":"7011",
    "addr:street":"Place Du Busteau;Hainaut",
    "iso:country":"BE",
    "sg:address":"Place Du Busteau 9",
    "sg:city":"Mons",
    "sg:orig_category":"Woningbouw",
    "sg:phone":"+32 65 35 62 70",
    "sg:postcode":"7011",
    "sg:province":"Hainaut",
    "wof:name":"Fe. Troisi\u00c8me Souffle",
    "wof:placetype":"venue"
},
  "geometry": {"coordinates":[3.912539959,50.4712982178],"type":"Point"}
}