{
  "type": "Feature",
  "properties": {
    "addr:full":"Grote Steenweg 216 Zulte Oost-Vlaanderen 9870",
    "addr:housenumber":"216",
    "addr:postcode":"9870",
    "addr:street":"Grote Steenweg",
    "iso:country":"BE",
    "sg:address":"Grote Steenweg 216",
    "sg:city":"Zulte",
    "sg:orig_category":"Slagers",
    "sg:phone":"+32 9 388 40 55",
    "sg:postcode":"9870",
    "sg:province":"Oost-Vlaanderen",
    "wof:name":"Renmans",
    "wof:placetype":"venue"
},
  "geometry": {"coordinates":[3.4599399567,50.9325294495],"type":"Point"}
}