{
  "type": "Feature",
  "properties": {
    "iso:country":"BE",
    "sg:address":"Heerbaan 7",
    "sg:city":"Maaseik",
    "sg:classifiers":[
        {
            "category":"Arena",
            "subcategory":"Sports Club",
            "type":"Entertainment"
        }
    ],
    "sg:phone":"+32 89 86 49 88",
    "sg:postcode":"3680",
    "sg:province":"Limburg",
    "sg:tags":[
        "de"
    ],
    "wof:name":"Maaslandse B.a.",
    "wof:placetype":"venue"
},
  "geometry": {"coordinates":[5.697822094,51.0940895081],"type":"Point"}
}