{
  "type": "Feature",
  "properties": {
    "addr:full":"Avenue Arthur Dezangr\u00e9 76 Kraainem Vlaams-Brabant 1950",
    "addr:housenumber":"76",
    "addr:postcode":"1950",
    "addr:street":"Avenue Arthur Dezangre\u0301",
    "iso:country":"BE",
    "sg:address":"Avenue Arthur Dezangr\u00e9 76",
    "sg:city":"Kraainem",
    "sg:classifiers":[
        {
            "category":"Shopping",
            "subcategory":"Books",
            "type":"Retail Goods"
        }
    ],
    "sg:phone":"+32 2 720 38 51",
    "sg:postcode":"1950",
    "sg:province":"Vlaams-Brabant",
    "sg:tags":[
        "bookseller"
    ],
    "wof:name":"Dekeyzer",
    "wof:placetype":"venue"
},
  "geometry": {"coordinates":[4.47128582,50.861038208],"type":"Point"}
}