{
  "type": "Feature",
  "properties": {
    "addr:full":"Patersstraat 134 Turnhout Antwerpen 2300",
    "addr:housenumber":"134",
    "addr:postcode":"2300",
    "addr:street":"Patersstraat",
    "iso:country":"BE",
    "sg:address":"Patersstraat 134",
    "sg:city":"Turnhout",
    "sg:classifiers":[
        {
            "category":"Food & Beverages",
            "subcategory":"Groceries & Convenience Stores",
            "type":"Retail Goods"
        }
    ],
    "sg:phone":"+32 14 41 16 69",
    "sg:postcode":"2300",
    "sg:province":"Antwerpen",
    "sg:tags":[
        "grocer"
    ],
    "wof:name":"Appels J",
    "wof:placetype":"venue"
},
  "geometry": {"coordinates":[4.9498109818,51.3276367188],"type":"Point"}
}