{
  "type": "Feature",
  "properties": {
    "addr:full":"Scheeplosserstraat 24 Gent Oost-Vlaanderen 9000",
    "addr:housenumber":"24",
    "addr:postcode":"9000",
    "addr:street":"Scheeplosserstraat;Oost-Vlaanderen",
    "iso:country":"BE",
    "sg:address":"Scheeplosserstraat 24",
    "sg:city":"Gent",
    "sg:classifiers":[
        {
            "category":"Professional",
            "subcategory":"Art Services",
            "type":"Services"
        }
    ],
    "sg:phone":"+32 9 251 13 33",
    "sg:postcode":"9000",
    "sg:province":"Oost-Vlaanderen",
    "sg:tags":[
        "graphic",
        "designer"
    ],
    "wof:name":"Caesart",
    "wof:placetype":"venue"
},
  "geometry": {"coordinates":[3.7478621006,51.0749168396],"type":"Point"}
}