{
  "type": "Feature",
  "properties": {
    "addr:full":"Kouter 9 Deinze Oost-Vlaanderen 9800",
    "addr:housenumber":"9",
    "addr:postcode":"9800",
    "addr:street":"Kouter",
    "iso:country":"BE",
    "sg:address":"Kouter 9",
    "sg:city":"Deinze",
    "sg:orig_category":"Benzinestations and brandstoffen",
    "sg:phone":"+32 9 380 49 37",
    "sg:postcode":"9800",
    "sg:province":"Oost-Vlaanderen",
    "wof:name":"T.g.t.",
    "wof:placetype":"venue"
},
  "geometry": {"coordinates":[3.514580965,50.991569519],"type":"Point"}
}