{
  "type": "Feature",
  "properties": {
    "addr:full":"Heerle 11 Minderhout Antwerpen 2322",
    "addr:housenumber":"11",
    "addr:postcode":"2322",
    "addr:street":"Heerle",
    "iso:country":"BE",
    "sg:address":"Heerle 11",
    "sg:city":"Minderhout",
    "sg:orig_category":"Fa\u00e7ade Bricks",
    "sg:phone":"+32 3 315 70 99",
    "sg:postcode":"2322",
    "sg:province":"Antwerpen",
    "wof:name":"Desta Nv",
    "wof:placetype":"venue"
},
  "geometry": {"coordinates":[4.8058729172,51.4443511963],"type":"Point"}
}