{
  "type": "Feature",
  "properties": {
    "addr:full":"Hoogledestraat 2 Kortemark West-Vlaanderen 8610",
    "addr:housenumber":"2",
    "addr:postcode":"8610",
    "addr:street":"Hoogledestraat",
    "iso:country":"BE",
    "sg:address":"Hoogledestraat 2",
    "sg:city":"Kortemark",
    "sg:classifiers":[
        {
            "category":"Shopping",
            "subcategory":"Hobbies, Toys, & Games",
            "type":"Retail Goods"
        }
    ],
    "sg:phone":"+32 51 56 65 88",
    "sg:postcode":"8610",
    "sg:province":"West-Vlaanderen",
    "sg:tags":[
        "toy",
        "-"
    ],
    "wof:name":"Trybou's",
    "wof:placetype":"venue"
},
  "geometry": {"coordinates":[3.0425200462,51.0248718262],"type":"Point"}
}