{
  "type": "Feature",
  "properties": {
    "iso:country":"BE",
    "sg:address":"Ambachtenlaan 29",
    "sg:city":"Leuven",
    "sg:orig_category":"Plomberie, chauffage and installations sanitaires. Air conditionn\u00e9 and ventilation",
    "sg:phone":"+32 16 40 30 00",
    "sg:postcode":"3001",
    "sg:province":"Vlaams-Brabant",
    "wof:name":"Dalkia",
    "wof:placetype":"venue"
},
  "geometry": {"coordinates":[4.716791153,50.8470649719],"type":"Point"}
}