{
  "type": "Feature",
  "properties": {
    "iso:country":"BE",
    "sg:address":"Strijlandstraat 86",
    "sg:city":"Gooik",
    "sg:orig_category":"G\u00e9om\u00e8tres",
    "sg:phone":"+32 54 56 66 19",
    "sg:postcode":"1755",
    "sg:province":"Vlaams-Brabant",
    "wof:name":"Urbain Jamaels",
    "wof:placetype":"venue"
},
  "geometry": {"coordinates":[4.0779309273,50.7925987244],"type":"Point"}
}