{
  "type": "Feature",
  "properties": {
    "iso:country":"BE",
    "sg:address":"Ter Eikestraat 3",
    "sg:city":"Aalter (poeke)",
    "sg:classifiers":[
        {
            "category":"Autos & Motor Vehicles",
            "subcategory":"Fuel & Gas Station",
            "type":"Retail Goods"
        }
    ],
    "sg:phone":"+32 51 68 92 91",
    "sg:postcode":"9880",
    "sg:province":"Oost-Vlaanderen",
    "sg:tags":[
        "filter",
        "-",
        "air"
    ],
    "wof:name":"Aichi E",
    "wof:placetype":"venue"
},
  "geometry": {"coordinates":[3.4614229202,51.0522575378],"type":"Point"}
}