{
  "type": "Feature",
  "properties": {
    "iso:country":"BE",
    "sg:address":"Kwakkelhoekstraat 45",
    "sg:city":"Sint-niklaas (nieuwkerken-waas)",
    "sg:classifiers":[
        {
            "category":"Professional",
            "subcategory":"Art Services",
            "type":"Services"
        }
    ],
    "sg:phone":"+32 3 776 41 81",
    "sg:postcode":"9100",
    "sg:province":"Oost-Vlaanderen",
    "sg:tags":[
        "photographer"
    ],
    "wof:name":"Aelbrecht P",
    "wof:placetype":"venue"
},
  "geometry": {"coordinates":[4.1886591911,51.1931610107],"type":"Point"}
}