{
  "type": "Feature",
  "properties": {
    "iso:country":"BE",
    "sg:address":"Chauss\u00c9e De Wavre 1145",
    "sg:city":"Oudergem/auderghem",
    "sg:classifiers":[
        {
            "category":"Personal",
            "subcategory":"Beauty Salon",
            "type":"Services"
        }
    ],
    "sg:phone":"+32 2 647 10 88",
    "sg:postcode":"1160",
    "sg:province":"Bruxelles-Capitale",
    "sg:tags":[
        "de",
        "coiffure"
    ],
    "wof:name":"Coiffure Charly & Ray",
    "wof:placetype":"venue"
},
  "geometry": {"coordinates":[4.4016919136,50.8232650757],"type":"Point"}
}