{
  "type": "Feature",
  "properties": {
    "addr:full":"Lierbaan 112b Putte Antwerpen 2580",
    "addr:housenumber":"112b",
    "addr:postcode":"2580",
    "addr:street":"Lierbaan",
    "iso:country":"BE",
    "sg:address":"Lierbaan 112b",
    "sg:city":"Putte",
    "sg:orig_category":"Kapsalons",
    "sg:phone":"+32 15 75 67 42",
    "sg:postcode":"2580",
    "sg:province":"Antwerpen",
    "wof:name":"Coiffure Yolande",
    "wof:placetype":"venue"
},
  "geometry": {"coordinates":[4.6288552284,51.0628395081],"type":"Point"}
}