{
  "type": "Feature",
  "properties": {
    "addr:full":"Galerie St-hubert Ottignies-louvain-la-neuve (louvain-la-neuve) Brabant Wallon 1348",
    "addr:postcode":"1348",
    "addr:street":"Brabant",
    "iso:country":"BE",
    "sg:address":"Galerie St-hubert",
    "sg:city":"Ottignies-louvain-la-neuve (louvain-la-neuve)",
    "sg:classifiers":[
        {
            "category":"Shopping",
            "subcategory":"Shoes",
            "type":"Retail Goods"
        }
    ],
    "sg:phone":"+32 10 45 24 39",
    "sg:postcode":"1348",
    "sg:province":"Brabant Wallon",
    "sg:tags":[
        "slipper",
        "-"
    ],
    "wof:name":"Marche \u00e0 Vue",
    "wof:placetype":"venue"
},
  "geometry": {"coordinates":[4.567553997,50.6661262512],"type":"Point"}
}