{
  "type": "Feature",
  "properties": {
    "iso:country":"BE",
    "sg:address":"Leopoldstadplein 9",
    "sg:city":"Etterbeek",
    "sg:orig_category":"Verhuur immobili\u00ebn eigen bezit",
    "sg:phone":"+32 2 734 23 20",
    "sg:postcode":"1040",
    "sg:province":"Bruxelles-Capitale",
    "wof:name":"Lio House",
    "wof:placetype":"venue"
},
  "geometry": {"coordinates":[4.3825178146,50.8287773132],"type":"Point"}
}