{
  "type": "Feature",
  "properties": {
    "addr:full":"Rue Des Fontaines 48a Wavre Brabant Wallon 1300",
    "addr:housenumber":"48a;1300",
    "addr:street":"Rue Des Fontaines",
    "iso:country":"BE",
    "sg:address":"Rue Des Fontaines 48a",
    "sg:city":"Wavre",
    "sg:classifiers":[
        {
            "category":"Personal",
            "subcategory":"Beauty Salon",
            "type":"Services"
        }
    ],
    "sg:phone":"+32 10 22 59 40",
    "sg:postcode":"1300",
    "sg:province":"Brabant Wallon",
    "sg:tags":[
        "de",
        "coiffure"
    ],
    "wof:name":"Coiffure Crescend'o",
    "wof:placetype":"venue"
},
  "geometry": {"coordinates":[4.6092000008,50.7144775391],"type":"Point"}
}