{
  "type": "Feature",
  "properties": {
    "iso:country":"BE",
    "sg:address":"Kielse Vest 44",
    "sg:city":"Antwerpen",
    "sg:classifiers":[
        {
            "category":"Freight",
            "type":"Transportation"
        }
    ],
    "sg:phone":"+32 3 230 20 30",
    "sg:postcode":"2018",
    "sg:province":"Antwerpen",
    "sg:tags":[
        "express",
        "transport"
    ],
    "wof:name":"Antwerp City Express",
    "wof:placetype":"venue"
},
  "geometry": {"coordinates":[4.393239975,51.1978111267],"type":"Point"}
}