{
  "type": "Feature",
  "properties": {
    "addr:full":"Rue Gilmont 1 Chastre Brabant Wallon 1450",
    "addr:housenumber":"1",
    "addr:postcode":"1450",
    "addr:street":"Rue Gilmont",
    "iso:country":"BE",
    "sg:address":"Rue Gilmont 1",
    "sg:city":"Chastre",
    "sg:orig_category":"M\u00e9decins and sp\u00e9cialistes",
    "sg:phone":"+32 10 65 69 41",
    "sg:postcode":"1450",
    "sg:province":"Brabant Wallon",
    "wof:name":"B. Geets",
    "wof:placetype":"venue"
},
  "geometry": {"coordinates":[4.6070261002,50.6030311584],"type":"Point"}
}