{
  "type": "Feature",
  "properties": {
    "iso:country":"BE",
    "sg:address":"Rue De L'industrie 5",
    "sg:city":"Harchies",
    "sg:classifiers":[
        {
            "category":"Train Station",
            "subcategory":"Light Rail",
            "type":"Transportation"
        }
    ],
    "sg:phone":"+32 69 56 23 20",
    "sg:postcode":"7321",
    "sg:province":"Hainaut",
    "sg:tags":[
        "traffic"
    ],
    "wof:name":"Signallight S.a.",
    "wof:placetype":"venue"
},
  "geometry": {"coordinates":[3.7092180252,50.4819526672],"type":"Point"}
}