{
  "type": "Feature",
  "properties": {
    "addr:full":"Stationsplein 6 Kasterlee (tielen) Antwerpen 2460",
    "addr:housenumber":"6",
    "addr:postcode":"2460",
    "addr:street":"Stationsplein",
    "iso:country":"BE",
    "sg:address":"Stationsplein 6",
    "sg:city":"Kasterlee (tielen)",
    "sg:classifiers":[
        {
            "category":"Professional",
            "subcategory":"Art Services",
            "type":"Services"
        }
    ],
    "sg:phone":"+32 14 55 53 62",
    "sg:postcode":"2460",
    "sg:province":"Antwerpen",
    "sg:tags":[
        "interior",
        "designer"
    ],
    "wof:name":"De Seranno",
    "wof:placetype":"venue"
},
  "geometry": {"coordinates":[4.8942232132,51.2414588928],"type":"Point"}
}