{
  "type": "Feature",
  "properties": {
    "iso:country":"BE",
    "sg:address":"Route De Val Dieu 86",
    "sg:city":"Aubel",
    "sg:classifiers":[
        {
            "category":"Professional",
            "subcategory":"Management & Consulting",
            "type":"Services"
        }
    ],
    "sg:phone":"+32 87 68 64 63",
    "sg:postcode":"4880",
    "sg:province":"Li\u00e8ge",
    "sg:tags":[
        "tax-consultants"
    ],
    "wof:name":"Denoel F",
    "wof:placetype":"venue"
},
  "geometry": {"coordinates":[5.84354496,50.7097244263],"type":"Point"}
}