{
  "type": "Feature",
  "properties": {
    "iso:country":"BE",
    "sg:address":"Edward Vlietinckstraat 27",
    "sg:city":"Oostende (stene)",
    "sg:classifiers":[
        {
            "category":"Manufacturing",
            "subcategory":"Furniture",
            "type":"Manufacturing & Wholesale Goods"
        }
    ],
    "sg:phone":"+32 59 70 99 08",
    "sg:postcode":"8400",
    "sg:province":"West-Vlaanderen",
    "sg:tags":[
        "made",
        "-",
        "custom"
    ],
    "wof:name":"Veryser Interieurbouw",
    "wof:placetype":"venue"
},
  "geometry": {"coordinates":[2.9391300678,51.2082672119],"type":"Point"}
}