{
  "type": "Feature",
  "properties": {
    "iso:country":"BE",
    "sg:address":"Avenue Heydenberg 80",
    "sg:city":"Bruxelles (woluwe-saint-lambert)",
    "sg:classifiers":[
        {
            "category":"Wholesale",
            "subcategory":"Books, Periodicals, & Newspapers",
            "type":"Manufacturing & Wholesale Goods"
        }
    ],
    "sg:phone":"+32 2 770 50 71",
    "sg:postcode":"1200",
    "sg:province":"Bruxelles-Capitale",
    "sg:tags":[
        "hygiene",
        "paper",
        "-"
    ],
    "wof:name":"Belgopap Sprl",
    "wof:placetype":"venue"
},
  "geometry": {"coordinates":[4.4174461365,50.8482551575],"type":"Point"}
}