{
  "type": "Feature",
  "properties": {
    "iso:country":"BE",
    "sg:address":"Chauss\u00c9e De Soignies 55",
    "sg:city":"Silly",
    "sg:orig_category":"Huisdierenkwekers",
    "sg:phone":"+32 2 395 51 79",
    "sg:postcode":"7830",
    "sg:province":"Hainaut",
    "wof:name":"Chenil Del Trinitad",
    "wof:placetype":"venue"
},
  "geometry": {"coordinates":[3.9024889469,50.6475601196],"type":"Point"}
}