{
  "type": "Feature",
  "properties": {
    "iso:country":"BE",
    "sg:address":"Karmenhoekstraat 29",
    "sg:city":"Nevele",
    "sg:orig_category":"Installation de menuiserie en bois and plastique",
    "sg:phone":"+32 9 371 50 46",
    "sg:postcode":"9850",
    "sg:province":"Oost-Vlaanderen",
    "wof:name":"Raoul Van De Voorde",
    "wof:placetype":"venue"
},
  "geometry": {"coordinates":[3.5180261135,51.0701789856],"type":"Point"}
}