{
  "type": "Feature",
  "properties": {
    "addr:full":"Rue De Le Mesnil 34 Viroinval (oignies-en-thi\u00e9rache) Namur 5670",
    "addr:housenumber":"34",
    "addr:postcode":"5670",
    "addr:street":"Rue De Le Mesnil",
    "iso:country":"BE",
    "sg:address":"Rue De Le Mesnil 34",
    "sg:city":"Viroinval (oignies-en-thi\u00e9rache)",
    "sg:classifiers":[
        {
            "category":"Real Estate",
            "subcategory":"Real Estate Services",
            "type":"Services"
        }
    ],
    "sg:phone":"+32 475 39 15 01",
    "sg:postcode":"5670",
    "sg:province":"Namur",
    "wof:name":"Cabinet De La Thi\u00e9rache",
    "wof:placetype":"venue"
},
  "geometry": {"coordinates":[4.6436247826,50.0243263245],"type":"Point"}
}