{
  "type": "Feature",
  "properties": {
    "addr:full":"Iepenlaan 11 Temse Oost-Vlaanderen 9140",
    "addr:housenumber":"11",
    "addr:postcode":"9140",
    "addr:street":"Iepenlaan",
    "iso:country":"BE",
    "sg:address":"Iepenlaan 11",
    "sg:city":"Temse",
    "sg:orig_category":"Travaux de finition and nettoyage de b\u00e2timents",
    "sg:phone":"+32 3 771 53 17",
    "sg:postcode":"9140",
    "sg:province":"Oost-Vlaanderen",
    "wof:name":"A.s.m.",
    "wof:placetype":"venue"
},
  "geometry": {"coordinates":[4.186645031,51.1203994751],"type":"Point"}
}