{
  "type": "Feature",
  "properties": {
    "addr:full":"Route De Namur 24 Braives Li\u00e8ge 4260",
    "addr:housenumber":"24",
    "addr:postcode":"4260",
    "addr:street":"Route De Namur",
    "iso:country":"BE",
    "sg:address":"Route De Namur 24",
    "sg:city":"Braives",
    "sg:classifiers":[
        {
            "category":"Autos & Motor Vehicles",
            "subcategory":"Fuel & Gas Station",
            "type":"Retail Goods"
        }
    ],
    "sg:phone":"+32 19 69 91 76",
    "sg:postcode":"4260",
    "sg:province":"Li\u00e8ge",
    "sg:tags":[
        "stations-service",
        "carburants"
    ],
    "wof:name":"Car-services",
    "wof:placetype":"venue"
},
  "geometry": {"coordinates":[5.0830101967,50.6243591309],"type":"Point"}
}