{
  "type": "Feature",
  "properties": {
    "addr:full":"Draaiboom 20 Oud-turnhout Antwerpen 2360",
    "addr:housenumber":"20",
    "addr:postcode":"2360",
    "addr:street":"Draaiboom",
    "iso:country":"BE",
    "sg:address":"Draaiboom 20",
    "sg:city":"Oud-turnhout",
    "sg:orig_category":"Non-Classified Establishments",
    "sg:phone":"+32 14 45 23 88",
    "sg:postcode":"2360",
    "sg:province":"Antwerpen",
    "wof:name":"Nuyts H",
    "wof:placetype":"venue"
},
  "geometry": {"coordinates":[4.9877338409,51.3222885132],"type":"Point"}
}