{
  "type": "Feature",
  "properties": {
    "addr:full":"Chauss\u00c9e De Mons 286 Soignies Hainaut 7060",
    "addr:housenumber":"286",
    "addr:postcode":"7060",
    "addr:street":"Chausse\u0301E De Mons",
    "iso:country":"BE",
    "sg:address":"Chauss\u00c9e De Mons 286",
    "sg:city":"Soignies",
    "sg:orig_category":"Elektrische installaties voor woningen Loodgieterij, verwarming and sanitaire installaties",
    "sg:phone":"+32 67 33 64 28",
    "sg:postcode":"7060",
    "sg:province":"Hainaut",
    "wof:name":"Ets Dehoux Eddy",
    "wof:placetype":"venue"
},
  "geometry": {"coordinates":[4.0516810417,50.5510444641],"type":"Point"}
}