{
  "type": "Feature",
  "properties": {
    "iso:country":"BE",
    "sg:address":"Rue Lecomte 176",
    "sg:city":"Namur",
    "sg:classifiers":[
        {
            "category":"Professional",
            "subcategory":"Management & Consulting",
            "type":"Services"
        }
    ],
    "sg:phone":"+32 81 47 03 84",
    "sg:postcode":"5000",
    "sg:province":"Namur",
    "sg:tags":[
        "consultant"
    ],
    "wof:name":"Bpmc Sprl",
    "wof:placetype":"venue"
},
  "geometry": {"coordinates":[4.8427810669,50.4385032654],"type":"Point"}
}