{
  "type": "Feature",
  "properties": {
    "addr:full":"Staalijzer 3 Maldegem (adegem) Oost-Vlaanderen 9991",
    "addr:housenumber":"3",
    "addr:postcode":"9991",
    "addr:street":"Staalijzer",
    "iso:country":"BE",
    "sg:address":"Staalijzer 3",
    "sg:city":"Maldegem (adegem)",
    "sg:classifiers":[
        {
            "category":"Professional",
            "subcategory":"Accounting & Tax Preparation",
            "type":"Services"
        }
    ],
    "sg:phone":"+32 9 378 61 94",
    "sg:postcode":"9991",
    "sg:province":"Oost-Vlaanderen",
    "sg:tags":[
        "bookkeeper"
    ],
    "wof:name":"Decock A",
    "wof:placetype":"venue"
},
  "geometry": {"coordinates":[3.5064280033,51.1863822937],"type":"Point"}
}