{
  "type": "Feature",
  "properties": {
    "addr:full":"Place De La Coll\u00e9giale 8b Vis\u00e9 Li\u00e8ge 4600",
    "addr:housenumber":"8b",
    "addr:postcode":"4600",
    "addr:street":"Place De La Colle\u0301Giale",
    "iso:country":"BE",
    "sg:address":"Place De La Coll\u00e9giale 8b",
    "sg:city":"Vis\u00e9",
    "sg:classifiers":[
        {
            "category":"Retail",
            "subcategory":"Veterinary Services",
            "type":"Services"
        }
    ],
    "sg:phone":"+32 4 379 56 52",
    "sg:postcode":"4600",
    "sg:province":"Li\u00e8ge",
    "sg:tags":[
        "veterinarian"
    ],
    "wof:name":"Purnode J",
    "wof:placetype":"venue"
},
  "geometry": {"coordinates":[5.6955251694,50.7335929871],"type":"Point"}
}