{
  "type": "Feature",
  "properties": {
    "addr:full":"Hemelrijkstraat 8 Gent (sint-denijs-westrem - Afsnee) Oost-Vlaanderen 9051",
    "addr:housenumber":"8",
    "addr:postcode":"9051",
    "addr:street":"Hemelrijkstraat;Oost-Vlaanderen",
    "iso:country":"BE",
    "sg:address":"Hemelrijkstraat 8",
    "sg:city":"Gent (sint-denijs-westrem - Afsnee)",
    "sg:classifiers":[
        {
            "category":"Real Estate",
            "subcategory":"Real Estate Services",
            "type":"Services"
        }
    ],
    "sg:phone":"+32 9 220 34 40",
    "sg:postcode":"9051",
    "sg:province":"Oost-Vlaanderen",
    "wof:name":"Logist M",
    "wof:placetype":"venue"
},
  "geometry": {"coordinates":[3.6635830402,51.0157585144],"type":"Point"}
}