{
  "type": "Feature",
  "properties": {
    "iso:country":"BE",
    "sg:address":"Rue Commandant Chuillet 28",
    "sg:city":"Chastre",
    "sg:orig_category":"Jardinage",
    "sg:phone":"+32 81 61 13 15",
    "sg:postcode":"1450",
    "sg:province":"Brabant Wallon",
    "wof:name":"Davister",
    "wof:placetype":"venue"
},
  "geometry": {"coordinates":[4.6412091255,50.5921020508],"type":"Point"}
}