{
  "type": "Feature",
  "properties": {
    "addr:full":"Rue De La Brasserie 2 Eghez\u00e9e (saint-germain) Namur 5310",
    "addr:housenumber":"2",
    "addr:postcode":"5310",
    "addr:street":"Rue De La Brasserie",
    "iso:country":"BE",
    "sg:address":"Rue De La Brasserie 2",
    "sg:city":"Eghez\u00e9e (saint-germain)",
    "sg:classifiers":[
        {
            "category":"Professional",
            "subcategory":"Management & Consulting",
            "type":"Services"
        }
    ],
    "sg:phone":"+32 81 51 33 38",
    "sg:postcode":"5310",
    "sg:province":"Namur",
    "sg:tags":[
        "marketing",
        "-",
        "consultant"
    ],
    "wof:name":"Djs Buroservices",
    "wof:placetype":"venue"
},
  "geometry": {"coordinates":[4.8405818939,50.5755386353],"type":"Point"}
}