{
  "type": "Feature",
  "properties": {
    "iso:country":"BE",
    "sg:address":"Rue Du Saiwiat 5",
    "sg:city":"Eghez\u00e9e",
    "sg:classifiers":[
        {
            "category":"Banks & Credit Unions",
            "subcategory":"Investment Brokerage",
            "type":"Services"
        }
    ],
    "sg:phone":"+32 81 81 10 96",
    "sg:postcode":"5310",
    "sg:province":"Namur",
    "sg:tags":[
        "transfusion",
        "blood"
    ],
    "wof:name":"Maison Croix Rouge (la)",
    "wof:placetype":"venue"
},
  "geometry": {"coordinates":[4.9085707664,50.5941085815],"type":"Point"}
}