{
  "type": "Feature",
  "properties": {
    "iso:country":"BE",
    "sg:address":"Rollegemkapelsestraat 109",
    "sg:city":"Ledegem (sint-eloois-winkel)",
    "sg:classifiers":[
        {
            "category":"Shopping",
            "subcategory":"Clothing, Apparel, & Fashions",
            "type":"Retail Goods"
        }
    ],
    "sg:phone":"+32 56 50 95 80",
    "sg:postcode":"8880",
    "sg:province":"West-Vlaanderen",
    "sg:tags":[
        "-",
        "clothing",
        "child"
    ],
    "wof:name":"Leroma Nv",
    "wof:placetype":"venue"
},
  "geometry": {"coordinates":[3.150249958,50.8689804077],"type":"Point"}
}