{
  "type": "Feature",
  "properties": {
    "addr:full":"Rue De La Procession 106 Anderlecht Bruxelles-Capitale 1070",
    "addr:housenumber":"106",
    "addr:postcode":"1070",
    "addr:street":"Rue De La Procession",
    "iso:country":"BE",
    "sg:address":"Rue De La Procession 106",
    "sg:city":"Anderlecht",
    "sg:classifiers":[
        {
            "category":"Cafe",
            "type":"Food & Drink"
        }
    ],
    "sg:phone":"+32 2 521 09 00",
    "sg:postcode":"1070",
    "sg:province":"Bruxelles-Capitale",
    "sg:tags":[
        "caf\u00e9s"
    ],
    "wof:name":"Babs",
    "wof:placetype":"venue"
},
  "geometry": {"coordinates":[4.301035881,50.8350563049],"type":"Point"}
}