{
  "type": "Feature",
  "properties": {
    "iso:country":"BE",
    "sg:address":"Schepen Beckersstraat 11",
    "sg:city":"Gingelom",
    "sg:classifiers":[
        {
            "category":"Health Services",
            "subcategory":"Dentist",
            "type":"Services"
        }
    ],
    "sg:phone":"+32 11 88 48 10",
    "sg:postcode":"3890",
    "sg:province":"Limburg",
    "wof:name":"Deprez Guido",
    "wof:placetype":"venue"
},
  "geometry": {"coordinates":[5.1330718994,50.7491950989],"type":"Point"}
}