{
  "type": "Feature",
  "properties": {
    "addr:full":"Chav\u00c9e Des Vignobles 3 Jodoigne Brabant Wallon 1370",
    "addr:housenumber":"3",
    "addr:postcode":"1370",
    "iso:country":"BE",
    "sg:address":"Chav\u00c9e Des Vignobles 3",
    "sg:city":"Jodoigne",
    "sg:orig_category":"Artsen and specialisten",
    "sg:phone":"+32 10 81 17 42",
    "sg:postcode":"1370",
    "sg:province":"Brabant Wallon",
    "wof:name":"Jean-pierre Szikora",
    "wof:placetype":"venue"
},
  "geometry": {"coordinates":[4.8984599113,50.739692688],"type":"Point"}
}