{
  "type": "Feature",
  "properties": {
    "iso:country":"BE",
    "sg:address":"Place Nestor Outer 15",
    "sg:city":"Virton",
    "sg:classifiers":[
        {
            "category":"Communications",
            "subcategory":"Film & Video Production",
            "type":"Services"
        }
    ],
    "sg:phone":"+32 63 58 21 43",
    "sg:postcode":"6760",
    "sg:province":"Luxembourg",
    "sg:tags":[
        "platen",
        "cassette",
        "cd's"
    ],
    "wof:name":"Music Box",
    "wof:placetype":"venue"
},
  "geometry": {"coordinates":[5.532269001,49.5675697327],"type":"Point"}
}