{
  "type": "Feature",
  "properties": {
    "iso:country":"BE",
    "sg:address":"Route De Saint-g\u00e9rard 205",
    "sg:city":"Namur (w\u00e9pion)",
    "sg:classifiers":[
        {
            "category":"Real Estate",
            "subcategory":"Architect",
            "type":"Services"
        }
    ],
    "sg:phone":"+32 81 47 03 48",
    "sg:postcode":"5100",
    "sg:province":"Namur",
    "wof:name":"Beckers J-m",
    "wof:placetype":"venue"
},
  "geometry": {"coordinates":[4.8548297882,50.4183006287],"type":"Point"}
}