{
  "type": "Feature",
  "properties": {
    "iso:country":"BE",
    "sg:address":"Rue Du Trieu \u00e0 Vall\u00e9e 14",
    "sg:city":"La Louvi\u00e8re (houdeng-goegnies)",
    "sg:classifiers":[
        {
            "category":"Shopping",
            "subcategory":"Gifts & Souvenirs",
            "type":"Retail Goods"
        }
    ],
    "sg:phone":"+32 64 21 11 65",
    "sg:postcode":"7110",
    "sg:province":"Hainaut",
    "sg:tags":[
        "postcard",
        "picture",
        "greeting",
        "card"
    ],
    "wof:name":"Knockaert L",
    "wof:placetype":"venue"
},
  "geometry": {"coordinates":[4.1505050659,50.4826698303],"type":"Point"}
}