{
  "type": "Feature",
  "properties": {
    "addr:full":"Rue Filias Capouillet 29 Charleroi Hainaut 6030",
    "addr:housenumber":"29",
    "addr:postcode":"6030",
    "addr:street":"Rue Filias Capouillet;Hainaut",
    "iso:country":"BE",
    "sg:address":"Rue Filias Capouillet 29",
    "sg:city":"Charleroi",
    "sg:orig_category":"Voertuigen",
    "sg:phone":"+32 71 54 07 61",
    "sg:postcode":"6030",
    "sg:province":"Hainaut",
    "wof:name":"Pascal Blekic",
    "wof:placetype":"venue"
},
  "geometry": {"coordinates":[4.3646411896,50.4127197266],"type":"Point"}
}