{
  "type": "Feature",
  "properties": {
    "addr:full":"H. Consciencelaan 1 Waarschoot Oost-Vlaanderen 9950",
    "addr:housenumber":"1",
    "addr:postcode":"9950",
    "addr:street":"Consciencelaan",
    "iso:country":"BE",
    "sg:address":"H. Consciencelaan 1",
    "sg:city":"Waarschoot",
    "sg:orig_category":"Catering and organisatie van feesten Voedingsspeciaalzaken",
    "sg:phone":"+32 9 378 39 54",
    "sg:postcode":"9950",
    "sg:province":"Oost-Vlaanderen",
    "wof:name":"Vladimir's",
    "wof:placetype":"venue"
},
  "geometry": {"coordinates":[3.5988500118,51.1541481018],"type":"Point"}
}