{
  "type": "Feature",
  "properties": {
    "addr:full":"Elshoutstraat 7 Oostrozebeke West-Vlaanderen 8780",
    "addr:housenumber":"7",
    "addr:postcode":"8780",
    "addr:street":"Elshoutstraat",
    "iso:country":"BE",
    "sg:address":"Elshoutstraat 7",
    "sg:city":"Oostrozebeke",
    "sg:orig_category":"Boekhouders",
    "sg:phone":"+32 56 66 48 18",
    "sg:postcode":"8780",
    "sg:province":"West-Vlaanderen",
    "wof:name":"Devoldere Bart",
    "wof:placetype":"venue"
},
  "geometry": {"coordinates":[3.3336389065,50.9149703979],"type":"Point"}
}