{
  "type": "Feature",
  "properties": {
    "addr:full":"Dekenijstraat 27 Zomergem Oost-Vlaanderen 9930",
    "addr:housenumber":"27",
    "addr:postcode":"9930",
    "addr:street":"Dekenijstraat",
    "iso:country":"BE",
    "sg:address":"Dekenijstraat 27",
    "sg:city":"Zomergem",
    "sg:classifiers":[
        {
            "category":"Personal",
            "subcategory":"Beauty Salon",
            "type":"Services"
        }
    ],
    "sg:phone":"+32 9 372 01 99",
    "sg:postcode":"9930",
    "sg:province":"Oost-Vlaanderen",
    "sg:tags":[
        "de",
        "coiffure"
    ],
    "wof:name":"Hairstudio New Fashion",
    "wof:placetype":"venue"
},
  "geometry": {"coordinates":[3.5609250069,51.1162414551],"type":"Point"}
}