{
  "type": "Feature",
  "properties": {
    "addr:full":"Veeweidestraat 161 Anderlecht/anderlecht Bruxelles-Capitale 1070",
    "addr:housenumber":"161",
    "addr:postcode":"1070",
    "addr:street":"Veeweidestraat",
    "iso:country":"BE",
    "sg:address":"Veeweidestraat 161",
    "sg:city":"Anderlecht/anderlecht",
    "sg:classifiers":[
        {
            "category":"Fast Food",
            "type":"Food & Drink"
        }
    ],
    "sg:phone":"+32 2 523 15 26",
    "sg:postcode":"1070",
    "sg:province":"Bruxelles-Capitale",
    "sg:tags":[
        "meeneem",
        "restaurant"
    ],
    "wof:name":"A La Frite Dor\u00c9e",
    "wof:placetype":"venue"
},
  "geometry": {"coordinates":[4.3041172028,50.8291893005],"type":"Point"}
}