{
  "type": "Feature",
  "properties": {
    "iso:country":"BE",
    "sg:address":"Magermanse Heide 7",
    "sg:city":"Kalmthout",
    "sg:classifiers":[
        {
            "category":"Retail",
            "subcategory":"Auto Repair",
            "type":"Services"
        }
    ],
    "sg:phone":"+32 3 667 71 85",
    "sg:postcode":"2920",
    "sg:province":"Antwerpen",
    "sg:tags":[
        "recapping",
        "-",
        "retreading",
        "tyre"
    ],
    "wof:name":"Tyre Plan Europe Bvba",
    "wof:placetype":"venue"
},
  "geometry": {"coordinates":[4.5051660538,51.4406471252],"type":"Point"}
}