{
  "type": "Feature",
  "properties": {
    "addr:full":"Heirbaan 208 Zwijndrecht (burcht) Antwerpen 2070",
    "addr:housenumber":"208",
    "addr:postcode":"2070",
    "addr:street":"Heirbaan;Burcht",
    "iso:country":"BE",
    "sg:address":"Heirbaan 208",
    "sg:city":"Zwijndrecht (burcht)",
    "sg:orig_category":"Solariums",
    "sg:phone":"+32 3 252 52 01",
    "sg:postcode":"2070",
    "sg:province":"Antwerpen",
    "wof:name":"Kim Zonnen-atelier",
    "wof:placetype":"venue"
},
  "geometry": {"coordinates":[4.3301539421,51.198425293],"type":"Point"}
}