{
  "type": "Feature",
  "properties": {
    "addr:full":"Pellemanstraat 78 Kasterlee Antwerpen 2460",
    "addr:housenumber":"78",
    "addr:postcode":"2460",
    "addr:street":"Pellemanstraat",
    "iso:country":"BE",
    "sg:address":"Pellemanstraat 78",
    "sg:city":"Kasterlee",
    "sg:orig_category":"Fabrication and montage de mobilier",
    "sg:phone":"+32 14 85 19 65",
    "sg:postcode":"2460",
    "sg:province":"Antwerpen",
    "wof:name":"Guido Leysen",
    "wof:placetype":"venue"
},
  "geometry": {"coordinates":[4.9570841789,51.2433128357],"type":"Point"}
}