{
  "type": "Feature",
  "properties": {
    "iso:country":"BE",
    "sg:address":"Rue De L'avenir 3",
    "sg:city":"Namur (saint-servais)",
    "sg:classifiers":[
        {
            "category":"Home & Garden",
            "subcategory":"Building Materials",
            "type":"Retail Goods"
        }
    ],
    "sg:phone":"+32 81 73 11 00",
    "sg:postcode":"5002",
    "sg:province":"Namur",
    "sg:tags":[
        "granite",
        "stone",
        "natural",
        "marble"
    ],
    "wof:name":"Cema-maes Noel Et Cie Sprl",
    "wof:placetype":"venue"
},
  "geometry": {"coordinates":[4.8562779427,50.4734191895],"type":"Point"}
}