{
  "type": "Feature",
  "properties": {
    "iso:country":"BE",
    "sg:address":"Wijnegemsteenweg 48",
    "sg:city":"Wommelgem",
    "sg:classifiers":[
        {
            "category":"Shopping",
            "subcategory":"Baby Store",
            "type":"Retail Goods"
        }
    ],
    "sg:phone":"+32 3 353 93 57",
    "sg:postcode":"2160",
    "sg:province":"Antwerpen",
    "sg:tags":[
        "-",
        "accessory"
    ],
    "wof:name":"Memoria",
    "wof:placetype":"venue"
},
  "geometry": {"coordinates":[4.5291547775,51.2104606628],"type":"Point"}
}