{
  "type": "Feature",
  "properties": {
    "addr:full":"Avenue Rogier 32 Bruxelles (schaerbeek) Bruxelles-Capitale 1030",
    "addr:housenumber":"32",
    "addr:postcode":"1030",
    "addr:street":"Avenue Rogier",
    "iso:country":"BE",
    "sg:address":"Avenue Rogier 32",
    "sg:city":"Bruxelles (schaerbeek)",
    "sg:classifiers":[
        {
            "category":"Professional",
            "subcategory":"Art Services",
            "type":"Services"
        }
    ],
    "sg:phone":"+32 2 242 57 93",
    "sg:postcode":"1030",
    "sg:province":"Bruxelles-Capitale",
    "sg:tags":[
        "realization",
        "audio-visual"
    ],
    "wof:name":"Media Animation Asbl",
    "wof:placetype":"venue"
},
  "geometry": {"coordinates":[4.3734087944,50.8604888916],"type":"Point"}
}