{
  "type": "Feature",
  "properties": {
    "iso:country":"BE",
    "sg:address":"Rue De L'ypr\u00c9au 26",
    "sg:city":"Ronse/renaix",
    "sg:orig_category":"Administration d'immeubles. Agences immobili\u00e8res",
    "sg:phone":"+32 55 21 48 08",
    "sg:postcode":"9600",
    "sg:province":"Oost-Vlaanderen",
    "wof:name":"A.d. Immo",
    "wof:placetype":"venue"
},
  "geometry": {"coordinates":[3.5999140739,50.7458534241],"type":"Point"}
}