{
  "type": "Feature",
  "properties": {
    "iso:country":"BE",
    "sg:address":"Grote Stoppelbergen 1-3",
    "sg:city":"Antwerpen",
    "sg:classifiers":[
        {
            "category":"Building & Trades",
            "subcategory":"Construction",
            "type":"Services"
        }
    ],
    "sg:phone":"+32 476 25 68 09",
    "sg:postcode":"2040",
    "sg:province":"Antwerpen",
    "sg:tags":[
        "carpenter"
    ],
    "wof:name":"Maes Schrijnwerkerij",
    "wof:placetype":"venue"
},
  "geometry": {"coordinates":[4.3314437866,51.3689231873],"type":"Point"}
}