{
  "type": "Feature",
  "properties": {
    "iso:country":"BE",
    "sg:address":"Rue Plaine D'aviation 24",
    "sg:city":"Bruxelles (evere)",
    "sg:classifiers":[
        {
            "category":"Real Estate",
            "subcategory":"Architect",
            "type":"Services"
        }
    ],
    "sg:phone":"+32 2 242 10 35",
    "sg:postcode":"1140",
    "sg:province":"Bruxelles-Capitale",
    "wof:name":"Dassargues C",
    "wof:placetype":"venue"
},
  "geometry": {"coordinates":[4.4032759666,50.8763961792],"type":"Point"}
}