{
  "type": "Feature",
  "properties": {
    "addr:full":"Rue Du Faubourg 299 Montigny-le-tilleul Hainaut 6110",
    "addr:housenumber":"299",
    "addr:postcode":"6110",
    "addr:street":"Rue Du Faubourg",
    "iso:country":"BE",
    "sg:address":"Rue Du Faubourg 299",
    "sg:city":"Montigny-le-tilleul",
    "sg:orig_category":"Onderdelen and accessoires voor auto's",
    "sg:phone":"+32 71 56 00 20",
    "sg:postcode":"6110",
    "sg:province":"Hainaut",
    "wof:name":"Car Styling",
    "wof:placetype":"venue"
},
  "geometry": {"coordinates":[4.3904800415,50.3634033203],"type":"Point"}
}