{
  "type": "Feature",
  "properties": {
    "iso:country":"BE",
    "sg:address":"Ter Eecken 20",
    "sg:city":"Oudenaarde",
    "sg:orig_category":"M\u00e9decins and sp\u00e9cialistes",
    "sg:phone":"+32 55 31 32 33",
    "sg:postcode":"9700",
    "sg:province":"Oost-Vlaanderen",
    "wof:name":"Labo Janssens Henri",
    "wof:placetype":"venue"
},
  "geometry": {"coordinates":[3.6106050014,50.8535842896],"type":"Point"}
}