{
  "type": "Feature",
  "properties": {
    "addr:full":"Avenue De La For\u00eat 176 Bruxelles Bruxelles-Capitale 1000",
    "addr:housenumber":"176",
    "addr:postcode":"1000",
    "addr:street":"Avenue De La Fore\u0302T",
    "iso:country":"BE",
    "sg:address":"Avenue De La For\u00eat 176",
    "sg:city":"Bruxelles",
    "sg:classifiers":[
        {
            "category":"Real Estate",
            "subcategory":"Architect",
            "type":"Services"
        }
    ],
    "sg:phone":"+32 2 673 68 05",
    "sg:postcode":"1000",
    "sg:province":"Bruxelles-Capitale",
    "wof:name":"Wettlin-papalli K",
    "wof:placetype":"venue"
},
  "geometry": {"coordinates":[4.395758152,50.7986717224],"type":"Point"}
}