{
  "type": "Feature",
  "properties": {
    "addr:full":"Havendoklaan 14 Vilvoorde - Cargovil 1804",
    "addr:housenumber":"14",
    "addr:postcode":"1804",
    "addr:street":"Havendoklaan;Cargovil",
    "iso:country":"BE",
    "sg:address":"Havendoklaan 14",
    "sg:city":"Vilvoorde - Cargovil",
    "sg:classifiers":[
        {
            "category":"Conference Center",
            "type":"Public Place"
        }
    ],
    "sg:phone":"+32 2 756 54 90",
    "sg:postcode":"1804",
    "sg:tags":[
        "terrain",
        "vehicle"
    ],
    "wof:name":"Ssangyong Belgium Nv",
    "wof:placetype":"venue"
},
  "geometry": {"coordinates":[4.4258599281,50.9269218445],"type":"Point"}
}