{
  "type": "Feature",
  "properties": {
    "iso:country":"BE",
    "sg:address":"Bisschopsdreef 45",
    "sg:city":"Brugge",
    "sg:orig_category":"M\u00e9decins and sp\u00e9cialistes",
    "sg:phone":"+32 50 36 03 63",
    "sg:postcode":"8310",
    "sg:province":"West-Vlaanderen",
    "wof:name":"Th\u00c9r\u00c8se Devolder",
    "wof:placetype":"venue"
},
  "geometry": {"coordinates":[3.2597949505,51.2165718079],"type":"Point"}
}