{
  "type": "Feature",
  "properties": {
    "addr:full":"Fabriekstraat 10 Dendermonde (baasrode) Oost-Vlaanderen 9200",
    "addr:housenumber":"10",
    "addr:postcode":"9200",
    "addr:street":"Fabriekstraat",
    "iso:country":"BE",
    "sg:address":"Fabriekstraat 10",
    "sg:city":"Dendermonde (baasrode)",
    "sg:classifiers":[
        {
            "category":"Utilities",
            "subcategory":"Cable",
            "type":"Services"
        }
    ],
    "sg:phone":"+32 52 34 23 24",
    "sg:postcode":"9200",
    "sg:province":"Oost-Vlaanderen",
    "sg:tags":[
        "steel",
        "wire",
        "-"
    ],
    "wof:name":"Van Praet-dansaert Nv",
    "wof:placetype":"venue"
},
  "geometry": {"coordinates":[4.0983099937,51.0315208435],"type":"Point"}
}