{
  "type": "Feature",
  "properties": {
    "addr:full":"Wolfrot 1 Asse Vlaams-Brabant 1730",
    "addr:housenumber":"1",
    "addr:postcode":"1730",
    "addr:street":"Wolfrot",
    "iso:country":"BE",
    "sg:address":"Wolfrot 1",
    "sg:city":"Asse",
    "sg:orig_category":"Assurances. Evaluation and estimation de biens immobiliers",
    "sg:phone":"+32 2 452 95 51",
    "sg:postcode":"1730",
    "sg:province":"Vlaams-Brabant",
    "wof:name":"Bureau De Maght & Sablon",
    "wof:placetype":"venue"
},
  "geometry": {"coordinates":[4.2205171585,50.904964447],"type":"Point"}
}