{
  "type": "Feature",
  "properties": {
    "addr:full":"Chauss\u00c9e De Jodoigne 71 Grez-doiceau Brabant Wallon 1390",
    "addr:housenumber":"71",
    "addr:postcode":"1390",
    "addr:street":"Chausse\u0301E De Jodoigne",
    "iso:country":"BE",
    "sg:address":"Chauss\u00c9e De Jodoigne 71",
    "sg:city":"Grez-doiceau",
    "sg:orig_category":"Belastingconsulenten Diverse juridische dienstverlening",
    "sg:phone":"+32 10 84 24 95",
    "sg:postcode":"1390",
    "sg:province":"Brabant Wallon",
    "wof:name":"Accounting Consult. Serv.",
    "wof:placetype":"venue"
},
  "geometry": {"coordinates":[4.7041220665,50.7361831665],"type":"Point"}
}