{
  "type": "Feature",
  "properties": {
    "iso:country":"BE",
    "sg:address":"Rijsbrugge 16",
    "sg:city":"Gent (sint-denijs-westrem - Afsnee)",
    "sg:classifiers":[
        {
            "category":"Communications",
            "type":"Services"
        }
    ],
    "sg:phone":"+32 9 220 56 29",
    "sg:postcode":"9051",
    "sg:province":"Oost-Vlaanderen",
    "sg:tags":[
        "translator"
    ],
    "wof:name":"Alexandre Vertalingen Bvba",
    "wof:placetype":"venue"
},
  "geometry": {"coordinates":[3.6683819294,51.020690918],"type":"Point"}
}