{
  "type": "Feature",
  "properties": {
    "iso:country":"BE",
    "sg:address":"Avenue Esplanade 57",
    "sg:city":"Wezembeek-oppem",
    "sg:orig_category":"M\u00e9decins and sp\u00e9cialistes. M\u00e9decines alternatives",
    "sg:phone":"+32 2 731 55 99",
    "sg:postcode":"1970",
    "sg:province":"Vlaams-Brabant",
    "wof:name":"Dokter Deruyck Christian",
    "wof:placetype":"venue"
},
  "geometry": {"coordinates":[4.4762120247,50.8406333923],"type":"Point"}
}