{
  "type": "Feature",
  "properties": {
    "addr:full":"Ringlaan 6 Kortrijk West-Vlaanderen 8501",
    "addr:housenumber":"6",
    "addr:postcode":"8501",
    "addr:street":"Ringlaan",
    "iso:country":"BE",
    "sg:address":"Ringlaan 6",
    "sg:city":"Kortrijk",
    "sg:orig_category":"Voertuigen",
    "sg:phone":"+32 56 35 45 85",
    "sg:postcode":"8501",
    "sg:province":"West-Vlaanderen",
    "wof:name":"Garage Flandria",
    "wof:placetype":"venue"
},
  "geometry": {"coordinates":[3.2425029278,50.8528747559],"type":"Point"}
}