{
  "type": "Feature",
  "properties": {
    "addr:full":"Leenheerstraat 8 Evergem Oost-Vlaanderen 9940",
    "addr:housenumber":"8",
    "addr:postcode":"9940",
    "addr:street":"Leenheerstraat;Oost-Vlaanderen",
    "iso:country":"BE",
    "sg:address":"Leenheerstraat 8",
    "sg:city":"Evergem",
    "sg:orig_category":"Plomberie, chauffage and installations sanitaires. Installation \u00e9lectrique r\u00e9sidentielle",
    "sg:phone":"+32 9 344 70 06",
    "sg:postcode":"9940",
    "sg:province":"Oost-Vlaanderen",
    "wof:name":"Johan Van Landschoot",
    "wof:placetype":"venue"
},
  "geometry": {"coordinates":[3.736593008,51.1726264954],"type":"Point"}
}