{
  "type": "Feature",
  "properties": {
    "iso:country":"BE",
    "sg:address":"Gentsestraat 44",
    "sg:city":"Harelbeke",
    "sg:classifiers":[
        {
            "category":"Insurance",
            "subcategory":"Life Insurance",
            "type":"Services"
        }
    ],
    "sg:phone":"+32 56 72 93 93",
    "sg:postcode":"8530",
    "sg:province":"West-Vlaanderen",
    "sg:tags":[
        "assurance"
    ],
    "wof:name":"F. Dispersyn",
    "wof:placetype":"venue"
},
  "geometry": {"coordinates":[3.3146979809,50.8583068848],"type":"Point"}
}