{
  "type": "Feature",
  "properties": {
    "addr:full":"Camp Et Haie 28 Ellezelles Hainaut 7890",
    "addr:housenumber":"28",
    "addr:postcode":"7890",
    "iso:country":"BE",
    "sg:address":"Camp Et Haie 28",
    "sg:city":"Ellezelles",
    "sg:orig_category":"Eleveurs de bovins",
    "sg:phone":"+32 68 54 25 65",
    "sg:postcode":"7890",
    "sg:province":"Hainaut",
    "wof:name":"Emile Jouret",
    "wof:placetype":"venue"
},
  "geometry": {"coordinates":[3.6658279896,50.7243766785],"type":"Point"}
}