{
  "type": "Feature",
  "properties": {
    "addr:full":"Avenue De Jette 376 Bruxelles (jette) Bruxelles-Capitale 1090",
    "addr:housenumber":"376",
    "addr:postcode":"1090",
    "addr:street":"Avenue De Jette",
    "iso:country":"BE",
    "sg:address":"Avenue De Jette 376",
    "sg:city":"Bruxelles (jette)",
    "sg:classifiers":[
        {
            "category":"Health Services",
            "subcategory":"Dentist",
            "type":"Services"
        }
    ],
    "sg:phone":"+32 2 425 40 17",
    "sg:postcode":"1090",
    "sg:province":"Bruxelles-Capitale",
    "wof:name":"Derriks Paulette",
    "wof:placetype":"venue"
},
  "geometry": {"coordinates":[4.3303728104,50.8665466309],"type":"Point"}
}