{
  "type": "Feature",
  "properties": {
    "addr:full":"Rue De La Station 34 Beyne-heusay Li\u00e8ge 4610",
    "addr:housenumber":"34",
    "addr:postcode":"4610",
    "addr:street":"Rue De La Station",
    "iso:country":"BE",
    "sg:address":"Rue De La Station 34",
    "sg:city":"Beyne-heusay",
    "sg:classifiers":[
        {
            "category":"Building & Trades",
            "subcategory":"Plumbing",
            "type":"Services"
        }
    ],
    "sg:phone":"+32 4 358 26 97",
    "sg:postcode":"4610",
    "sg:province":"Li\u00e8ge",
    "sg:tags":[
        "contractor"
    ],
    "wof:name":"Polizzi A",
    "wof:placetype":"venue"
},
  "geometry": {"coordinates":[5.6590261459,50.6178474426],"type":"Point"}
}