{
  "type": "Feature",
  "properties": {
    "addr:full":"Rue De La D\u00eeme 15 Braives (ciplet) Li\u00e8ge 4260",
    "addr:housenumber":"15",
    "addr:postcode":"4260",
    "addr:street":"Rue De La Di\u0302Me;Ciplet",
    "iso:country":"BE",
    "sg:address":"Rue De La D\u00eeme 15",
    "sg:city":"Braives (ciplet)",
    "sg:classifiers":[
        {
            "category":"Shopping",
            "subcategory":"Antiques",
            "type":"Retail Goods"
        }
    ],
    "sg:phone":"+32 19 69 71 41",
    "sg:postcode":"4260",
    "sg:province":"Li\u00e8ge",
    "wof:name":"Meubles & Objets",
    "wof:placetype":"venue"
},
  "geometry": {"coordinates":[5.0962719917,50.6198425293],"type":"Point"}
}