{
  "type": "Feature",
  "properties": {
    "addr:full":"Rue Ferrer 47 Boussu Hainaut 7300",
    "addr:housenumber":"47",
    "addr:postcode":"7300",
    "addr:street":"Rue Ferrer",
    "iso:country":"BE",
    "sg:address":"Rue Ferrer 47",
    "sg:city":"Boussu",
    "sg:orig_category":"Epiceries",
    "sg:phone":"+32 65 78 18 41",
    "sg:postcode":"7300",
    "sg:province":"Hainaut",
    "wof:name":"Shop 24",
    "wof:placetype":"venue"
},
  "geometry": {"coordinates":[3.7955698967,50.4115142822],"type":"Point"}
}