{
  "type": "Feature",
  "properties": {
    "addr:full":"Hoogleedsesteenweg 3 Roeselare West-Vlaanderen 8800",
    "addr:housenumber":"3",
    "addr:postcode":"8800",
    "addr:street":"Hoogleedsesteenweg",
    "iso:country":"BE",
    "sg:address":"Hoogleedsesteenweg 3",
    "sg:city":"Roeselare",
    "sg:classifiers":[
        {
            "category":"Professional",
            "subcategory":"Testing Lab",
            "type":"Services"
        }
    ],
    "sg:phone":"+32 51 20 66 62",
    "sg:postcode":"8800",
    "sg:province":"West-Vlaanderen",
    "sg:tags":[
        "chemist"
    ],
    "wof:name":"Matthys A M",
    "wof:placetype":"venue"
},
  "geometry": {"coordinates":[3.1196210384,50.9511489868],"type":"Point"}
}