{
  "type": "Feature",
  "properties": {
    "iso:country":"BE",
    "sg:address":"Industriezone 8",
    "sg:city":"Kruishoutem",
    "sg:classifiers":[
        {
            "category":"Train Station",
            "subcategory":"Light Rail",
            "type":"Transportation"
        }
    ],
    "sg:phone":"+32 9 388 64 18",
    "sg:postcode":"9770",
    "sg:province":"Oost-Vlaanderen",
    "sg:tags":[
        "beam",
        "yarn",
        "flange",
        "warp",
        "sectional"
    ],
    "wof:name":"Demtex B.v.b.a.",
    "wof:placetype":"venue"
},
  "geometry": {"coordinates":[3.4813399315,50.9083747864],"type":"Point"}
}