{
  "type": "Feature",
  "properties": {
    "iso:country":"BE",
    "sg:address":"Boschelstraat 54",
    "sg:city":"Kortessem",
    "sg:orig_category":"Rundveehouders",
    "sg:phone":"+32 12 23 19 56",
    "sg:postcode":"3724",
    "sg:province":"Limburg",
    "wof:name":"Wilhelmus Coeimans",
    "wof:placetype":"venue"
},
  "geometry": {"coordinates":[5.4274802208,50.8472595215],"type":"Point"}
}