{
  "type": "Feature",
  "properties": {
    "addr:full":"Molenstraat 5 Genk Limburg 3600",
    "addr:housenumber":"5",
    "addr:postcode":"3600",
    "addr:street":"Molenstraat",
    "iso:country":"BE",
    "sg:address":"Molenstraat 5",
    "sg:city":"Genk",
    "sg:orig_category":"Pain, p\u00e2tisseries and confiseries",
    "sg:phone":"+32 89 35 24 35",
    "sg:postcode":"3600",
    "sg:province":"Limburg",
    "wof:name":"Bakkerij Bijnens",
    "wof:placetype":"venue"
},
  "geometry": {"coordinates":[5.5007529259,50.9645614624],"type":"Point"}
}