{
  "type": "Feature",
  "properties": {
    "iso:country":"BE",
    "sg:address":"Michielsplein 4",
    "sg:city":"Hamont-achel",
    "sg:classifiers":[
        {
            "category":"Travel",
            "subcategory":"Hotels & Motels",
            "type":"Entertainment"
        }
    ],
    "sg:phone":"+32 11 64 31 81",
    "sg:postcode":"3930",
    "sg:province":"Limburg",
    "sg:tags":[
        "restaurant"
    ],
    "wof:name":"Koeckshof",
    "wof:placetype":"venue"
},
  "geometry": {"coordinates":[5.4798817635,51.2536392212],"type":"Point"}
}