{
  "type": "Feature",
  "properties": {
    "addr:full":"Torhoutsesteenweg 519 Oostende West-Vlaanderen 8400",
    "addr:housenumber":"519",
    "addr:postcode":"8400",
    "addr:street":"Torhoutsesteenweg",
    "iso:country":"BE",
    "sg:address":"Torhoutsesteenweg 519",
    "sg:city":"Oostende",
    "sg:orig_category":"Verlichting and huishoudartikelen",
    "sg:phone":"+32 59 50 28 68",
    "sg:postcode":"8400",
    "sg:province":"West-Vlaanderen",
    "wof:name":"Home Market",
    "wof:placetype":"venue"
},
  "geometry": {"coordinates":[2.9048330784,51.2084617615],"type":"Point"}
}