{
  "type": "Feature",
  "properties": {
    "iso:country":"BE",
    "sg:address":"Amerikalei 133",
    "sg:city":"Antwerpen",
    "sg:orig_category":"Ambassades and consulaten",
    "sg:phone":"+32 3 248 43 96",
    "sg:postcode":"2000",
    "sg:province":"Antwerpen",
    "wof:name":"Consulaat Van Litouwen",
    "wof:placetype":"venue"
},
  "geometry": {"coordinates":[4.3952560425,51.2061653137],"type":"Point"}
}