{
  "type": "Feature",
  "properties": {
    "addr:full":"Tiensesteenweg 13 Leuven Vlaams-Brabant 3000",
    "addr:housenumber":"13",
    "addr:postcode":"3000",
    "addr:street":"Tiensesteenweg",
    "iso:country":"BE",
    "sg:address":"Tiensesteenweg 13",
    "sg:city":"Leuven",
    "sg:orig_category":"Equipement photographique. Mat\u00e9riel de T\u00e9l\u00e9communication. Electrom\u00e9nager, t\u00e9l\u00e9visions and radios",
    "sg:phone":"+32 16 22 63 44",
    "sg:postcode":"3000",
    "sg:province":"Vlaams-Brabant",
    "wof:name":"Foto Vanbergen",
    "wof:placetype":"venue"
},
  "geometry": {"coordinates":[4.7034320831,50.8785858154],"type":"Point"}
}