{
  "type": "Feature",
  "properties": {
    "addr:full":"Rue Wilmotte-dupont 8 Huy Li\u00e8ge 4500",
    "addr:housenumber":"8",
    "addr:postcode":"4500",
    "addr:street":"Rue Wilmotte-Dupont",
    "iso:country":"BE",
    "sg:address":"Rue Wilmotte-dupont 8",
    "sg:city":"Huy",
    "sg:orig_category":"Boissons",
    "sg:phone":"+32 85 21 22 88",
    "sg:postcode":"4500",
    "sg:province":"Li\u00e8ge",
    "wof:name":"Comptoir Des Boissons",
    "wof:placetype":"venue"
},
  "geometry": {"coordinates":[5.2444448471,50.5224990845],"type":"Point"}
}