{
  "type": "Feature",
  "properties": {
    "iso:country":"BE",
    "sg:address":"Ronkenburgstraat 16",
    "sg:city":"Lede",
    "sg:classifiers":[
        {
            "category":"Health Services",
            "subcategory":"Dentist",
            "type":"Services"
        }
    ],
    "sg:phone":"+32 53 80 63 92",
    "sg:postcode":"9340",
    "sg:province":"Oost-Vlaanderen",
    "wof:name":"De Vooght Sandra",
    "wof:placetype":"venue"
},
  "geometry": {"coordinates":[3.9925079346,50.9740829468],"type":"Point"}
}