{
  "type": "Feature",
  "properties": {
    "iso:country":"BE",
    "sg:address":"Hoge Bokstraat 214",
    "sg:city":"Sint-niklaas",
    "sg:orig_category":"Herstellingen and onderhoud van auto's Voertuigen",
    "sg:phone":"+32 3 776 95 17",
    "sg:postcode":"9111",
    "sg:province":"Oost-Vlaanderen",
    "wof:name":"Autohof Vydt",
    "wof:placetype":"venue"
},
  "geometry": {"coordinates":[4.112224102,51.1685562134],"type":"Point"}
}