{
  "type": "Feature",
  "properties": {
    "iso:country":"BE",
    "sg:address":"Wippelgem Dorp 89",
    "sg:city":"Evergem",
    "sg:classifiers":[
        {
            "category":"Personal",
            "subcategory":"Beauty Salon",
            "type":"Services"
        }
    ],
    "sg:phone":"+32 9 357 60 11",
    "sg:postcode":"9940",
    "sg:province":"Oost-Vlaanderen",
    "sg:tags":[
        "lady",
        "-",
        "hairdressing"
    ],
    "wof:name":"Lut's Kapsalon",
    "wof:placetype":"venue"
},
  "geometry": {"coordinates":[3.7312009335,51.14270401],"type":"Point"}
}