{
  "type": "Feature",
  "properties": {
    "addr:full":"Rue Grande 16 Quievrain Hainaut 7380",
    "addr:housenumber":"16",
    "addr:postcode":"7380",
    "addr:street":"Rue Grande;Hainaut",
    "iso:country":"BE",
    "sg:address":"Rue Grande 16",
    "sg:city":"Quievrain",
    "sg:orig_category":"M\u00e9decins and sp\u00e9cialistes",
    "sg:phone":"+32 65 43 09 33",
    "sg:postcode":"7380",
    "sg:province":"Hainaut",
    "wof:name":"Michel Amand",
    "wof:placetype":"venue"
},
  "geometry": {"coordinates":[3.6824810505,50.4071655273],"type":"Point"}
}