{
  "type": "Feature",
  "properties": {
    "iso:country":"BE",
    "sg:address":"Rue Jules Tison 14",
    "sg:city":"La Louvi\u00c8re",
    "sg:orig_category":"Boekhouders",
    "sg:phone":"+32 64 21 62 70",
    "sg:postcode":"7100",
    "sg:province":"Hainaut",
    "wof:name":"Cristina Bellini",
    "wof:placetype":"venue"
},
  "geometry": {"coordinates":[4.1825819016,50.4696540833],"type":"Point"}
}