{
  "type": "Feature",
  "properties": {
    "addr:full":"Magdalenastraat 38 Antwerpen Antwerpen 2018",
    "addr:housenumber":"38",
    "addr:postcode":"2018",
    "addr:street":"Magdalenastraat",
    "iso:country":"BE",
    "sg:address":"Magdalenastraat 38",
    "sg:city":"Antwerpen",
    "sg:orig_category":"Sportclubs",
    "sg:phone":"+32 3 235 33 10",
    "sg:postcode":"2018",
    "sg:province":"Antwerpen",
    "wof:name":"K.c. Loenhout",
    "wof:placetype":"venue"
},
  "geometry": {"coordinates":[4.4284520149,51.2091064453],"type":"Point"}
}