{
  "type": "Feature",
  "properties": {
    "iso:country":"BE",
    "sg:address":"Lippenslaan 14",
    "sg:city":"Beersel",
    "sg:classifiers":[
        {
            "category":"Health Services",
            "subcategory":"Doctor",
            "type":"Services"
        }
    ],
    "sg:phone":"+32 2 377 21 37",
    "sg:postcode":"1650",
    "sg:province":"Vlaams-Brabant",
    "sg:tags":[
        "medicinephysicians",
        "surgeon"
    ],
    "wof:name":"Klein L",
    "wof:placetype":"venue"
},
  "geometry": {"coordinates":[4.3130612373,50.7762641907],"type":"Point"}
}