{
  "type": "Feature",
  "properties": {
    "iso:country":"BE",
    "sg:address":"Groenstraat 19",
    "sg:city":"Sint-laureins (sint-margriete)",
    "sg:classifiers":[
        {
            "category":"Professional",
            "subcategory":"Management & Consulting",
            "type":"Services"
        }
    ],
    "sg:phone":"+32 9 379 81 24",
    "sg:postcode":"9981",
    "sg:province":"Oost-Vlaanderen",
    "sg:tags":[
        "marketing",
        "-",
        "direct",
        "consultant"
    ],
    "wof:name":"Crown Top Invest Cvoha",
    "wof:placetype":"venue"
},
  "geometry": {"coordinates":[3.5431408882,51.2730369568],"type":"Point"}
}