{
  "type": "Feature",
  "properties": {
    "addr:full":"Ancienne Abbaye Stavelot Li\u00e8ge 4970",
    "addr:postcode":"4970",
    "iso:country":"BE",
    "sg:address":"Ancienne Abbaye",
    "sg:city":"Stavelot",
    "sg:classifiers":[
        {
            "category":"Museum",
            "type":"Entertainment"
        }
    ],
    "sg:phone":"+32 80 88 08 78",
    "sg:postcode":"4970",
    "sg:province":"Li\u00e8ge",
    "wof:name":"Mus\u00e9e Du Circuit De Spa-francorchamps",
    "wof:placetype":"venue"
},
  "geometry": {"coordinates":[5.9325051308,50.3940734863],"type":"Point"}
}