{
  "type": "Feature",
  "properties": {
    "iso:country":"BE",
    "sg:address":"Houtbriel 28",
    "sg:city":"Sint-niklaas",
    "sg:classifiers":[
        {
            "category":"Restaurant",
            "type":"Food & Drink"
        }
    ],
    "sg:phone":"+32 3 777 03 10",
    "sg:postcode":"9100",
    "sg:province":"Oost-Vlaanderen",
    "sg:tags":[
        "caf\u00e9s"
    ],
    "wof:name":"Taverne Kopenhagen",
    "wof:placetype":"venue"
},
  "geometry": {"coordinates":[4.1423220634,51.1647987366],"type":"Point"}
}