{
  "type": "Feature",
  "properties": {
    "addr:full":"Oude Bruglaan 100 Lokeren Oost-Vlaanderen 9160",
    "addr:housenumber":"100",
    "addr:postcode":"9160",
    "addr:street":"Oude Bruglaan",
    "iso:country":"BE",
    "sg:address":"Oude Bruglaan 100",
    "sg:city":"Lokeren",
    "sg:classifiers":[
        {
            "category":"Bakery",
            "type":"Food & Drink"
        }
    ],
    "sg:phone":"+32 9 348 88 62",
    "sg:postcode":"9160",
    "sg:province":"Oost-Vlaanderen",
    "sg:tags":[
        "confectioner",
        "baker"
    ],
    "wof:name":"Lybaert",
    "wof:placetype":"venue"
},
  "geometry": {"coordinates":[4.0036878586,51.10521698],"type":"Point"}
}