{
  "type": "Feature",
  "properties": {
    "iso:country":"BE",
    "sg:address":"Avenue Du Golf 11",
    "sg:city":"Evere/evere",
    "sg:orig_category":"Installation \u00e9lectrique r\u00e9sidentielle",
    "sg:phone":"+32 2 242 55 42",
    "sg:postcode":"1140",
    "sg:province":"Bruxelles-Capitale",
    "wof:name":"Alain Schepens",
    "wof:placetype":"venue"
},
  "geometry": {"coordinates":[4.40538311,50.8777275085],"type":"Point"}
}