{
  "type": "Feature",
  "properties": {
    "iso:country":"BE",
    "sg:address":"Rue Du Tilleul 14",
    "sg:city":"Bruxelles (schaerbeek)",
    "sg:classifiers":[
        {
            "category":"Arts & Performance",
            "subcategory":"Theater",
            "type":"Entertainment"
        }
    ],
    "sg:phone":"+32 2 245 83 34",
    "sg:postcode":"1030",
    "sg:province":"Bruxelles-Capitale",
    "sg:tags":[
        "theatrical",
        "agency"
    ],
    "wof:name":"Gombert Y",
    "wof:placetype":"venue"
},
  "geometry": {"coordinates":[4.3902311325,50.8779678345],"type":"Point"}
}