{
  "type": "Feature",
  "properties": {
    "addr:full":"Rue Lesbroussart 97 Elsene/ixelles Bruxelles-Capitale 1050",
    "addr:housenumber":"97",
    "addr:postcode":"1050",
    "addr:street":"Rue Lesbroussart",
    "iso:country":"BE",
    "sg:address":"Rue Lesbroussart 97",
    "sg:city":"Elsene/ixelles",
    "sg:orig_category":"Kapsalons",
    "sg:phone":"+32 2 647 68 32",
    "sg:postcode":"1050",
    "sg:province":"Bruxelles-Capitale",
    "wof:name":"Fran\u00c7oise",
    "wof:placetype":"venue"
},
  "geometry": {"coordinates":[4.365899086,50.8277397156],"type":"Point"}
}