{
  "type": "Feature",
  "properties": {
    "addr:full":"Grufflange 31ba Burg-reuland/burg-reuland Li\u00e8ge 4791",
    "addr:housenumber":"31ba",
    "addr:postcode":"4791",
    "addr:street":"Grufflange",
    "iso:country":"BE",
    "sg:address":"Grufflange 31ba",
    "sg:city":"Burg-reuland/burg-reuland",
    "sg:orig_category":"Eleveurs de bovins",
    "sg:phone":"+32 80 32 92 66",
    "sg:postcode":"4791",
    "sg:province":"Li\u00e8ge",
    "wof:name":"Kurt Feyen",
    "wof:placetype":"venue"
},
  "geometry": {"coordinates":[6.0841197968,50.2279701233],"type":"Point"}
}