{
  "type": "Feature",
  "properties": {
    "iso:country":"BE",
    "sg:address":"Rue De L'eglise 39",
    "sg:city":"Saint-gilles (bruxelles)",
    "sg:classifiers":[
        {
            "category":"Personal",
            "subcategory":"Beauty Salon",
            "type":"Services"
        }
    ],
    "sg:phone":"+32 2 537 36 65",
    "sg:postcode":"1060",
    "sg:province":"Bruxelles-Capitale",
    "sg:tags":[
        "de",
        "coiffure"
    ],
    "wof:name":"Maria Coiffure",
    "wof:placetype":"venue"
},
  "geometry": {"coordinates":[5.6159930229,50.6115684509],"type":"Point"}
}