{
  "type": "Feature",
  "properties": {
    "addr:full":"Mallebergplaats 17 Brugge West-Vlaanderen 8000",
    "addr:housenumber":"17",
    "addr:postcode":"8000",
    "addr:street":"Mallebergplaats",
    "iso:country":"BE",
    "sg:address":"Mallebergplaats 17",
    "sg:city":"Brugge",
    "sg:classifiers":[
        {
            "category":"Restaurant",
            "type":"Food & Drink"
        }
    ],
    "sg:phone":"+32 50 33 47 09",
    "sg:postcode":"8000",
    "sg:province":"West-Vlaanderen",
    "wof:name":"De Gulden Vlies",
    "wof:placetype":"venue"
},
  "geometry": {"coordinates":[3.2278850079,51.2092208862],"type":"Point"}
}