{
  "type": "Feature",
  "properties": {
    "iso:country":"BE",
    "sg:address":"Absheide 28",
    "sg:city":"Beerse",
    "sg:classifiers":[
        {
            "category":"Manufacturing",
            "subcategory":"Pottery",
            "type":"Manufacturing & Wholesale Goods"
        }
    ],
    "sg:phone":"+32 14 61 19 75",
    "sg:postcode":"2340",
    "sg:province":"Antwerpen",
    "sg:tags":[
        "facing",
        "brick"
    ],
    "wof:name":"Terca Beerse",
    "wof:placetype":"venue"
},
  "geometry": {"coordinates":[4.8116679192,51.3239707947],"type":"Point"}
}