{
  "type": "Feature",
  "properties": {
    "iso:country":"BE",
    "sg:address":"Voie Des Cocars 46",
    "sg:city":"Dour",
    "sg:classifiers":[
        {
            "category":"Juice Bar",
            "subcategory":"None",
            "type":"Food & Drink"
        }
    ],
    "sg:phone":"+32 65 65 13 12",
    "sg:postcode":"7370",
    "sg:province":"Hainaut",
    "sg:tags":[
        "water",
        "soft"
    ],
    "wof:name":"Namuroise (caf\u00e9terie)",
    "wof:placetype":"venue"
},
  "geometry": {"coordinates":[3.7686400414,50.3956413269],"type":"Point"}
}