{
  "type": "Feature",
  "properties": {
    "iso:country":"BE",
    "sg:address":"Xavier Buissetstraat 37",
    "sg:city":"Vilvoorde",
    "sg:orig_category":"M\u00e9decins and sp\u00e9cialistes. M\u00e9decines alternatives",
    "sg:phone":"+32 2 251 14 29",
    "sg:postcode":"1800",
    "sg:province":"Vlaams-Brabant",
    "wof:name":"Dokter Maertens Claude-herman Katelyne",
    "wof:placetype":"venue"
},
  "geometry": {"coordinates":[4.4319248199,50.925693512],"type":"Point"}
}