{
  "type": "Feature",
  "properties": {
    "addr:full":"Verbindingsweg 84 Riemst (valmeer) Limburg 3770",
    "addr:housenumber":"84",
    "addr:postcode":"3770",
    "addr:street":"Verbindingsweg",
    "iso:country":"BE",
    "sg:address":"Verbindingsweg 84",
    "sg:city":"Riemst (valmeer)",
    "sg:classifiers":[
        {
            "category":"Communications",
            "type":"Services"
        }
    ],
    "sg:phone":"+32 12 39 53 14",
    "sg:postcode":"3770",
    "sg:province":"Limburg",
    "sg:tags":[
        "telecommunication"
    ],
    "wof:name":"Hermans J",
    "wof:placetype":"venue"
},
  "geometry": {"coordinates":[5.5969901085,50.8109016418],"type":"Point"}
}