{
  "type": "Feature",
  "properties": {
    "addr:full":"Mercatorstraat 172 Sint-niklaas Oost-Vlaanderen 9100",
    "addr:housenumber":"172",
    "addr:postcode":"9100",
    "addr:street":"Mercatorstraat",
    "iso:country":"BE",
    "sg:address":"Mercatorstraat 172",
    "sg:city":"Sint-niklaas",
    "sg:orig_category":"Ramassage and traitement des d\u00e9chets m\u00e9nagers",
    "sg:phone":"+32 3 776 07 73",
    "sg:postcode":"9100",
    "sg:province":"Oost-Vlaanderen",
    "wof:name":"Aufderhaar Belgium",
    "wof:placetype":"venue"
},
  "geometry": {"coordinates":[4.1513872147,51.1685791016],"type":"Point"}
}