{
  "type": "Feature",
  "properties": {
    "addr:full":"Waterloose Steenweg 609 Elsene/ixelles Bruxelles-Capitale 1050",
    "addr:housenumber":"609",
    "addr:postcode":"1050",
    "addr:street":"Waterloose Steenweg",
    "iso:country":"BE",
    "sg:address":"Waterloose Steenweg 609",
    "sg:city":"Elsene/ixelles",
    "sg:orig_category":"Supermarkten",
    "sg:phone":"+32 2 349 66 11",
    "sg:postcode":"1050",
    "sg:province":"Bruxelles-Capitale",
    "wof:name":"Super G.b.",
    "wof:placetype":"venue"
},
  "geometry": {"coordinates":[4.3642950058,50.8178253174],"type":"Point"}
}