{
  "type": "Feature",
  "properties": {
    "iso:country":"BE",
    "sg:address":"Rue De La Station De La Sambre 6",
    "sg:city":"Charleroi",
    "sg:orig_category":"Mat\u00e9riaux de construction Quincailleries. Bois Gr",
    "sg:phone":"+32 71 36 00 90",
    "sg:postcode":"6032",
    "sg:province":"Hainaut",
    "wof:name":"Imperisol",
    "wof:placetype":"venue"
},
  "geometry": {"coordinates":[4.4066061974,50.4059944153],"type":"Point"}
}