{
  "type": "Feature",
  "properties": {
    "addr:full":"Rietveldstraat 22 Melle Oost-Vlaanderen 9090",
    "addr:housenumber":"22",
    "addr:postcode":"9090",
    "addr:street":"Rietveldstraat",
    "iso:country":"BE",
    "sg:address":"Rietveldstraat 22",
    "sg:city":"Melle",
    "sg:classifiers":[
        {
            "category":"Building & Trades",
            "subcategory":"Pest Control",
            "type":"Services"
        }
    ],
    "sg:phone":"+32 9 231 76 57",
    "sg:postcode":"9090",
    "sg:province":"Oost-Vlaanderen",
    "sg:tags":[
        "machine",
        "vending"
    ],
    "wof:name":"Automaten Service",
    "wof:placetype":"venue"
},
  "geometry": {"coordinates":[3.7761700153,51.0125236511],"type":"Point"}
}