{
  "type": "Feature",
  "properties": {
    "addr:full":"Graaf Boudewijn Ix-laan 28 Kortrijk West-Vlaanderen 8500",
    "addr:housenumber":"28",
    "addr:postcode":"8500",
    "addr:street":"Graaf Boudewijn Ix-Laan",
    "iso:country":"BE",
    "sg:address":"Graaf Boudewijn Ix-laan 28",
    "sg:city":"Kortrijk",
    "sg:classifiers":[
        {
            "category":"Personal",
            "subcategory":"Beauty Salon",
            "type":"Services"
        }
    ],
    "sg:phone":"+32 56 21 46 45",
    "sg:postcode":"8500",
    "sg:province":"West-Vlaanderen",
    "sg:tags":[
        "lady",
        "-",
        "hairdressing"
    ],
    "wof:name":"Christa",
    "wof:placetype":"venue"
},
  "geometry": {"coordinates":[3.2780120373,50.8234443665],"type":"Point"}
}