{
  "type": "Feature",
  "properties": {
    "iso:country":"BE",
    "sg:address":"Waterloose Steenweg 1613",
    "sg:city":"Ukkel/uccle",
    "sg:orig_category":"Elektrische installaties voor woningen Verlichting and huishoudartikelen",
    "sg:phone":"+32 2 375 66 19",
    "sg:postcode":"1180",
    "sg:province":"Bruxelles-Capitale",
    "wof:name":"Deltaplus Lighting",
    "wof:placetype":"venue"
},
  "geometry": {"coordinates":[4.3825531006,50.7688941956],"type":"Point"}
}