{
  "type": "Feature",
  "properties": {
    "iso:country":"BE",
    "sg:address":"Rue De La Station 23",
    "sg:city":"Houyet",
    "sg:orig_category":"Treinen and spoorwegen",
    "sg:phone":"+32 82 66 64 19",
    "sg:postcode":"5560",
    "sg:province":"Namur",
    "wof:name":"Gare De Houyet",
    "wof:placetype":"venue"
},
  "geometry": {"coordinates":[5.0061001778,50.1895065308],"type":"Point"}
}