{
  "type": "Feature",
  "properties": {
    "iso:country":"BE",
    "sg:address":"Sint-genovevaplein 26",
    "sg:city":"Tienen",
    "sg:orig_category":"Fabrication and montage de mobilier. Installation de menuiserie en bois and plastique",
    "sg:phone":"+32 474 84 22 17",
    "sg:postcode":"3300",
    "sg:province":"Vlaams-Brabant",
    "wof:name":"Keukens Hupko G.",
    "wof:placetype":"venue"
},
  "geometry": {"coordinates":[4.9893260002,50.8295593262],"type":"Point"}
}