{
  "type": "Feature",
  "properties": {
    "addr:full":"Rue De La Station 4 Soignies Hainaut 7060",
    "addr:housenumber":"4",
    "addr:postcode":"7060",
    "addr:street":"Rue De La Station",
    "iso:country":"BE",
    "sg:address":"Rue De La Station 4",
    "sg:city":"Soignies",
    "sg:orig_category":"Opticiens",
    "sg:phone":"+32 67 33 43 94",
    "sg:postcode":"7060",
    "sg:province":"Hainaut",
    "wof:name":"Optique Delatte R.",
    "wof:placetype":"venue"
},
  "geometry": {"coordinates":[4.0718789101,50.5772361755],"type":"Point"}
}