{
  "type": "Feature",
  "properties": {
    "iso:country":"BE",
    "sg:address":"Kerkeweg 46",
    "sg:city":"Jabbeke",
    "sg:orig_category":"Plaatsen van vloer- and muurbekleding Schilders",
    "sg:phone":"+32 50 81 29 59",
    "sg:postcode":"8490",
    "sg:province":"West-Vlaanderen",
    "wof:name":"Jan Doom",
    "wof:placetype":"venue"
},
  "geometry": {"coordinates":[3.1241459846,51.1729850769],"type":"Point"}
}