{
  "type": "Feature",
  "properties": {
    "addr:full":"Avenue Saint-augustin 16 Vorst/forest Bruxelles-Capitale 1190",
    "addr:housenumber":"16",
    "addr:postcode":"1190",
    "addr:street":"Avenue Saint-Augustin;/ Forest",
    "iso:country":"BE",
    "sg:address":"Avenue Saint-augustin 16",
    "sg:city":"Vorst/forest",
    "sg:orig_category":"Enseignement maternel and primaire",
    "sg:phone":"+32 2 345 82 94",
    "sg:postcode":"1190",
    "sg:province":"Bruxelles-Capitale",
    "wof:name":"Vrije Basisschool/ecole Prim. & Gard. Libre",
    "wof:placetype":"venue"
},
  "geometry": {"coordinates":[4.3384399414,50.8167648315],"type":"Point"}
}