{
  "type": "Feature",
  "properties": {
    "addr:full":"Torhoutsesteenweg 629 Oostende West-Vlaanderen 8400",
    "addr:housenumber":"629",
    "addr:postcode":"8400",
    "addr:street":"Torhoutsesteenweg",
    "iso:country":"BE",
    "sg:address":"Torhoutsesteenweg 629",
    "sg:city":"Oostende",
    "sg:classifiers":[
        {
            "category":"Retail",
            "subcategory":"Repair Shop",
            "type":"Services"
        }
    ],
    "sg:phone":"+32 59 80 26 58",
    "sg:postcode":"8400",
    "sg:province":"West-Vlaanderen",
    "sg:tags":[
        "upholsterer"
    ],
    "wof:name":"Marco Leer",
    "wof:placetype":"venue"
},
  "geometry": {"coordinates":[2.9048330784,51.2084617615],"type":"Point"}
}