{
  "type": "Feature",
  "properties": {
    "iso:country":"BE",
    "sg:address":"Chauss\u00c9e De Jolimont 49",
    "sg:city":"La Louviere",
    "sg:classifiers":[
        {
            "category":"Personal",
            "subcategory":"Beauty Salon",
            "type":"Services"
        }
    ],
    "sg:phone":"+32 64 28 22 41",
    "sg:postcode":"7100",
    "sg:province":"Hainaut",
    "sg:tags":[
        "de",
        "coiffure"
    ],
    "wof:name":"Coiffure Marie Bonelli",
    "wof:placetype":"venue"
},
  "geometry": {"coordinates":[4.2157001495,50.4721488953],"type":"Point"}
}