{
  "type": "Feature",
  "properties": {
    "iso:country":"BE",
    "sg:address":"Sint-jozefsplein 3",
    "sg:city":"Oudenaarde",
    "sg:orig_category":"Apotheken",
    "sg:phone":"+32 55 31 27 05",
    "sg:postcode":"9700",
    "sg:province":"Oost-Vlaanderen",
    "wof:name":"Volksapotheek",
    "wof:placetype":"venue"
},
  "geometry": {"coordinates":[3.610229969,50.8520812988],"type":"Point"}
}