{
  "type": "Feature",
  "properties": {
    "addr:full":"Heirweg 20 Laarne (kalken) Oost-Vlaanderen 9270",
    "addr:housenumber":"20",
    "addr:postcode":"9270",
    "addr:street":"Heirweg",
    "iso:country":"BE",
    "sg:address":"Heirweg 20",
    "sg:city":"Laarne (kalken)",
    "sg:classifiers":[
        {
            "category":"Building & Trades",
            "subcategory":"Construction",
            "type":"Services"
        }
    ],
    "sg:phone":"+32 9 367 97 64",
    "sg:postcode":"9270",
    "sg:province":"Oost-Vlaanderen",
    "sg:tags":[
        "stucco",
        "contractor"
    ],
    "wof:name":"Van Damme T",
    "wof:placetype":"venue"
},
  "geometry": {"coordinates":[3.8829510212,51.0423202515],"type":"Point"}
}