{
  "type": "Feature",
  "properties": {
    "iso:country":"BE",
    "sg:address":"Sikkelstraat 57",
    "sg:city":"Brugge",
    "sg:orig_category":"Fleurs and plantes",
    "sg:phone":"+32 50 59 95 83",
    "sg:postcode":"8000",
    "sg:province":"West-Vlaanderen",
    "wof:name":"Marcel Feys",
    "wof:placetype":"venue"
},
  "geometry": {"coordinates":[3.2284030914,51.2454605103],"type":"Point"}
}