{
  "type": "Feature",
  "properties": {
    "iso:country":"BE",
    "sg:address":"Kerkstraat 44",
    "sg:city":"Oostende",
    "sg:classifiers":[
        {
            "category":"Professional",
            "subcategory":"Art Services",
            "type":"Services"
        }
    ],
    "sg:phone":"+32 59 80 04 27",
    "sg:postcode":"8400",
    "sg:province":"West-Vlaanderen",
    "sg:tags":[
        "picture",
        "framer"
    ],
    "wof:name":"Kunst & Ambacht",
    "wof:placetype":"venue"
},
  "geometry": {"coordinates":[2.920156002,51.230266571],"type":"Point"}
}