{
  "type": "Feature",
  "properties": {
    "iso:country":"BE",
    "sg:address":"Rue Joseph Hinnisdaels 29",
    "sg:city":"Berloz",
    "sg:orig_category":"Installation \u00e9lectrique r\u00e9sidentielle",
    "sg:phone":"+32 19 32 76 00",
    "sg:postcode":"4257",
    "sg:province":"Li\u00e8ge",
    "wof:name":"Luc Mathei",
    "wof:placetype":"venue"
},
  "geometry": {"coordinates":[5.2142047882,50.704750061],"type":"Point"}
}