{
  "type": "Feature",
  "properties": {
    "addr:full":"Rue Des Pierres \u00e0 Fusil 1 Jurbise (masnuy-saint-jean) Hainaut 7050",
    "addr:housenumber":"1",
    "addr:postcode":"7050",
    "addr:street":"Rue Des Pierres A\u0300 Fusil",
    "iso:country":"BE",
    "sg:address":"Rue Des Pierres \u00e0 Fusil 1",
    "sg:city":"Jurbise (masnuy-saint-jean)",
    "sg:classifiers":[
        {
            "category":"Professional",
            "subcategory":"Detective & Security Services",
            "type":"Services"
        }
    ],
    "sg:phone":"+32 65 84 29 93",
    "sg:postcode":"7050",
    "sg:province":"Hainaut",
    "sg:tags":[
        "consultant"
    ],
    "wof:name":"S\u00e9curiteam Sprl",
    "wof:placetype":"venue"
},
  "geometry": {"coordinates":[3.9314661026,50.5037765503],"type":"Point"}
}