{
  "type": "Feature",
  "properties": {
    "addr:full":"Rue De Haerne 216 Bruxelles (etterbeek) Bruxelles-Capitale 1040",
    "addr:housenumber":"216",
    "addr:postcode":"1040",
    "addr:street":"Rue De Haerne",
    "iso:country":"BE",
    "sg:address":"Rue De Haerne 216",
    "sg:city":"Bruxelles (etterbeek)",
    "sg:classifiers":[
        {
            "category":"Social Services",
            "type":"Services"
        }
    ],
    "sg:phone":"+32 2 647 36 00",
    "sg:postcode":"1040",
    "sg:province":"Bruxelles-Capitale",
    "sg:tags":[
        "handicapped",
        "-"
    ],
    "wof:name":"Centre D'aide \u00e0 L'enfance-war M\u00e9morial Asbl",
    "wof:placetype":"venue"
},
  "geometry": {"coordinates":[4.3885231018,50.8271217346],"type":"Point"}
}