{
  "type": "Feature",
  "properties": {
    "iso:country":"BE",
    "sg:address":"Paul Devauxstraat 33",
    "sg:city":"Brugge",
    "sg:classifiers":[
        {
            "category":"Retail",
            "subcategory":"Animal Services",
            "type":"Services"
        }
    ],
    "sg:phone":"+32 50 33 77 35",
    "sg:postcode":"8000",
    "sg:province":"West-Vlaanderen",
    "sg:tags":[
        "grooming",
        "-",
        "dog"
    ],
    "wof:name":"Idee-fix",
    "wof:placetype":"venue"
},
  "geometry": {"coordinates":[3.2379789352,51.2262649536],"type":"Point"}
}