{
  "type": "Feature",
  "properties": {
    "iso:country":"BE",
    "sg:address":"Rue Du Camp 42",
    "sg:city":"Waimes",
    "sg:orig_category":"Charpentes and couvertures. Construction de maisons",
    "sg:phone":"+32 80 44 00 00",
    "sg:postcode":"4950",
    "sg:province":"Li\u00e8ge",
    "wof:name":"Dani\u00cbl Stoffels",
    "wof:placetype":"venue"
},
  "geometry": {"coordinates":[6.1110301018,50.4149055481],"type":"Point"}
}