{
  "type": "Feature",
  "properties": {
    "iso:country":"BE",
    "sg:address":"Weg Naar Zwartberg 177",
    "sg:city":"Opglabbeek",
    "sg:classifiers":[
        {
            "category":"Real Estate",
            "subcategory":"Architect",
            "type":"Services"
        }
    ],
    "sg:phone":"+32 89 85 37 17",
    "sg:postcode":"3660",
    "sg:province":"Limburg",
    "wof:name":"Gielen D",
    "wof:placetype":"venue"
},
  "geometry": {"coordinates":[5.5664138794,51.039264679],"type":"Point"}
}