{
  "type": "Feature",
  "properties": {
    "iso:country":"BE",
    "sg:address":"Rue Des P\u00e2quis 4",
    "sg:city":"Rouvroy (lamorteau)",
    "sg:classifiers":[
        {
            "category":"Retail",
            "subcategory":"Auto Repair",
            "type":"Services"
        }
    ],
    "sg:phone":"+32 63 57 00 57",
    "sg:postcode":"6767",
    "sg:province":"Luxembourg",
    "sg:tags":[
        "garage"
    ],
    "wof:name":"Orens P",
    "wof:placetype":"venue"
},
  "geometry": {"coordinates":[5.4786930084,49.5273513794],"type":"Point"}
}