{
  "type": "Feature",
  "properties": {
    "addr:full":"Waelhemstraat 81-87 Brussel/bruxelles Bruxelles-Capitale 1030",
    "addr:postcode":"81-87;/ bruxelles;1030",
    "addr:street":"Waelhemstraat",
    "iso:country":"BE",
    "sg:address":"Waelhemstraat 81-87",
    "sg:city":"Brussel/bruxelles",
    "sg:orig_category":"Boekhouders",
    "sg:phone":"+32 2 216 88 95",
    "sg:postcode":"1030",
    "sg:province":"Bruxelles-Capitale",
    "wof:name":"Theys Guido",
    "wof:placetype":"venue"
},
  "geometry": {"coordinates":[4.3800301552,50.8703346252],"type":"Point"}
}