{
  "type": "Feature",
  "properties": {
    "iso:country":"BE",
    "sg:address":"Dr. Roosensplein 13",
    "sg:city":"Brasschaat",
    "sg:orig_category":"Bijouteries and horlogeries. R\u00e9parations d'horloges, montres and bijoux",
    "sg:phone":"+32 3 651 80 15",
    "sg:postcode":"2930",
    "sg:province":"Antwerpen",
    "wof:name":"Paul De Beenhouwer",
    "wof:placetype":"venue"
},
  "geometry": {"coordinates":[4.4863052368,51.287940979],"type":"Point"}
}