{
  "type": "Feature",
  "properties": {
    "addr:full":"Rue Du V\u00c9lodr\u00d4me 15 Dinant Namur 5500",
    "addr:housenumber":"15",
    "addr:postcode":"5500",
    "addr:street":"Rue Du Ve\u0301Lodro\u0302Me",
    "iso:country":"BE",
    "sg:address":"Rue Du V\u00c9lodr\u00d4me 15",
    "sg:city":"Dinant",
    "sg:orig_category":"Brandweer and civiele bescherming",
    "sg:phone":"+32 82 22 90 18",
    "sg:postcode":"5500",
    "sg:province":"Namur",
    "wof:name":"Protection Civile",
    "wof:placetype":"venue"
},
  "geometry": {"coordinates":[4.9053311348,50.2366981506],"type":"Point"}
}