{
  "type": "Feature",
  "properties": {
    "iso:country":"BE",
    "sg:address":"Brusselstraat 14",
    "sg:city":"Ternat",
    "sg:orig_category":"Non-Classified Establishments",
    "sg:phone":"+32 2 582 06 18",
    "sg:postcode":"1740",
    "sg:province":"Vlaams-Brabant",
    "wof:name":"Apc Supplies Belgium",
    "wof:placetype":"venue"
},
  "geometry": {"coordinates":[4.1791400909,50.8720436096],"type":"Point"}
}