{
  "type": "Feature",
  "properties": {
    "addr:full":"Hemelrijkstraat 105 Mol Antwerpen 2400",
    "addr:housenumber":"105",
    "addr:postcode":"2400",
    "addr:street":"Hemelrijkstraat",
    "iso:country":"BE",
    "sg:address":"Hemelrijkstraat 105",
    "sg:city":"Mol",
    "sg:classifiers":[
        {
            "category":"Personal",
            "subcategory":"Beauty Salon",
            "type":"Services"
        }
    ],
    "sg:phone":"+32 14 32 03 32",
    "sg:postcode":"2400",
    "sg:province":"Antwerpen",
    "wof:name":"Luka Schoonheidsinstituut",
    "wof:placetype":"venue"
},
  "geometry": {"coordinates":[5.1165041924,51.1748962402],"type":"Point"}
}