{
  "type": "Feature",
  "properties": {
    "iso:country":"BE",
    "sg:address":"Sterstr. 32",
    "sg:city":"Antwerpen",
    "sg:classifiers":[
        {
            "category":"Wholesale",
            "subcategory":"Machinery & Supplies",
            "type":"Manufacturing & Wholesale Goods"
        }
    ],
    "sg:phone":"+32 3 236 18 75",
    "sg:postcode":"2018",
    "sg:province":"Antwerpen",
    "sg:tags":[
        "handling",
        "material",
        "-",
        "machine",
        "equipment",
        "engineering",
        "mechanical"
    ],
    "wof:name":"Liften Ethiery Nv",
    "wof:placetype":"venue"
},
  "geometry": {"coordinates":[4.41370821,51.2032585144],"type":"Point"}
}