{
  "type": "Feature",
  "properties": {
    "iso:country":"BE",
    "sg:address":"Rue Emile Vandervelde 2",
    "sg:city":"Farciennes (pironchamps)",
    "sg:classifiers":[
        {
            "category":"Bakery",
            "type":"Food & Drink"
        }
    ],
    "sg:phone":"+32 71 38 40 62",
    "sg:postcode":"6240",
    "sg:province":"Hainaut",
    "sg:tags":[
        "confectioner",
        "baker"
    ],
    "wof:name":"Heughens",
    "wof:placetype":"venue"
},
  "geometry": {"coordinates":[4.5324888229,50.4238777161],"type":"Point"}
}