{
  "type": "Feature",
  "properties": {
    "addr:full":"Varentstraat 8 Waregem West-Vlaanderen 8791",
    "addr:housenumber":"8",
    "addr:postcode":"8791",
    "addr:street":"Varentstraat",
    "iso:country":"BE",
    "sg:address":"Varentstraat 8",
    "sg:city":"Waregem",
    "sg:classifiers":[
        {
            "category":"Personal",
            "subcategory":"Beauty Salon",
            "type":"Services"
        }
    ],
    "sg:phone":"+32 56 71 44 99",
    "sg:postcode":"8791",
    "sg:province":"West-Vlaanderen",
    "sg:tags":[
        "de",
        "coiffure"
    ],
    "wof:name":"Carmen Desmet",
    "wof:placetype":"venue"
},
  "geometry": {"coordinates":[3.3475260735,50.864074707],"type":"Point"}
}