{
  "type": "Feature",
  "properties": {
    "iso:country":"BE",
    "sg:address":"Keistraat 28",
    "sg:city":"Sint-martens-latem",
    "sg:classifiers":[
        {
            "category":"Professional",
            "subcategory":"Art Services",
            "type":"Services"
        }
    ],
    "sg:phone":"+32 9 281 06 09",
    "sg:postcode":"9830",
    "sg:province":"Oost-Vlaanderen",
    "sg:tags":[
        "interior",
        "designer"
    ],
    "wof:name":"Nachtergaele M",
    "wof:placetype":"venue"
},
  "geometry": {"coordinates":[3.6431980133,51.0021820068],"type":"Point"}
}