{
  "type": "Feature",
  "properties": {
    "addr:full":"Verenigingstraat 2 Brussel/bruxelles Bruxelles-Capitale 1000",
    "addr:housenumber":"2",
    "addr:postcode":"1000",
    "addr:street":"Verenigingstraat;/",
    "iso:country":"BE",
    "sg:address":"Verenigingstraat 2",
    "sg:city":"Brussel/bruxelles",
    "sg:classifiers":[
        {
            "category":"Restaurant",
            "type":"Food & Drink"
        }
    ],
    "sg:phone":"+32 2 217 16 91",
    "sg:postcode":"1000",
    "sg:province":"Bruxelles-Capitale",
    "wof:name":"Taverne Tie Break",
    "wof:placetype":"venue"
},
  "geometry": {"coordinates":[4.3656768799,50.8522949219],"type":"Point"}
}