{
  "type": "Feature",
  "properties": {
    "addr:full":"Boomstraat 35 Bornem Antwerpen 2880",
    "addr:housenumber":"35",
    "addr:postcode":"2880",
    "addr:street":"Boomstraat",
    "iso:country":"BE",
    "sg:address":"Boomstraat 35",
    "sg:city":"Bornem",
    "sg:classifiers":[
        {
            "category":"Shopping",
            "subcategory":"Clothing, Apparel, & Fashions",
            "type":"Retail Goods"
        }
    ],
    "sg:phone":"+32 3 889 38 30",
    "sg:postcode":"2880",
    "sg:province":"Antwerpen",
    "sg:tags":[
        "lingerie",
        "sous-v\u00eatements"
    ],
    "wof:name":"Huis Madame Michiamo",
    "wof:placetype":"venue"
},
  "geometry": {"coordinates":[4.2336702347,51.0977859497],"type":"Point"}
}