{
  "type": "Feature",
  "properties": {
    "addr:full":"Avenue Leopold Iii 22 Binche (p\u00e9ronnes-lez-binche) Hainaut 7134",
    "addr:housenumber":"22",
    "addr:postcode":"7134",
    "addr:street":"Avenue Leopold Iii",
    "iso:country":"BE",
    "sg:address":"Avenue Leopold Iii 22",
    "sg:city":"Binche (p\u00e9ronnes-lez-binche)",
    "sg:classifiers":[
        {
            "category":"Manufacturing",
            "subcategory":"Building Materials",
            "type":"Manufacturing & Wholesale Goods"
        }
    ],
    "sg:phone":"+32 64 27 87 87",
    "sg:postcode":"7134",
    "sg:province":"Hainaut",
    "sg:tags":[
        "fixture",
        "store"
    ],
    "wof:name":"Actual Deco Sa",
    "wof:placetype":"venue"
},
  "geometry": {"coordinates":[4.2175779343,50.4159622192],"type":"Point"}
}