{
  "type": "Feature",
  "properties": {
    "iso:country":"BE",
    "sg:address":"Schransdreef 51",
    "sg:city":"Overijse",
    "sg:classifiers":[
        {
            "category":"Retail",
            "subcategory":"Auto Repair",
            "type":"Services"
        }
    ],
    "sg:phone":"+32 2 687 37 81",
    "sg:postcode":"3090",
    "sg:province":"Vlaams-Brabant",
    "sg:tags":[
        "automobile-body"
    ],
    "wof:name":"Sperling R",
    "wof:placetype":"venue"
},
  "geometry": {"coordinates":[4.5065059662,50.7940483093],"type":"Point"}
}