{
  "type": "Feature",
  "properties": {
    "iso:country":"BE",
    "sg:address":"Industriezone 32",
    "sg:city":"Kruishoutem",
    "sg:classifiers":[
        {
            "category":"Home & Garden",
            "subcategory":"Carpets & Floor Coverings",
            "type":"Retail Goods"
        }
    ],
    "sg:phone":"+32 9 388 62 20",
    "sg:postcode":"9770",
    "sg:province":"Oost-Vlaanderen",
    "sg:tags":[
        "tile"
    ],
    "wof:name":"Bouwcenter Vanhulle Nv",
    "wof:placetype":"venue"
},
  "geometry": {"coordinates":[3.4730679989,50.9027252197],"type":"Point"}
}