{
  "type": "Feature",
  "properties": {
    "iso:country":"BE",
    "sg:address":"Claesplein 16",
    "sg:city":"Halle",
    "sg:orig_category":"Artsen and specialisten",
    "sg:phone":"+32 2 360 20 80",
    "sg:postcode":"1502",
    "sg:province":"Vlaams-Brabant",
    "wof:name":"Carina Bonnewyn",
    "wof:placetype":"venue"
},
  "geometry": {"coordinates":[4.2231202126,50.7136192322],"type":"Point"}
}