{
  "type": "Feature",
  "properties": {
    "iso:country":"BE",
    "sg:address":"Banmolenweg 45",
    "sg:city":"Rijkevorsel",
    "sg:classifiers":[
        {
            "category":"Home & Garden",
            "subcategory":"Carpets & Floor Coverings",
            "type":"Retail Goods"
        }
    ],
    "sg:phone":"+32 3 314 10 04",
    "sg:postcode":"2310",
    "sg:province":"Antwerpen",
    "sg:tags":[
        "layer",
        "mosaicists"
    ],
    "wof:name":"Van Dijck Rudi",
    "wof:placetype":"venue"
},
  "geometry": {"coordinates":[4.7555341721,51.3526306152],"type":"Point"}
}