{
  "type": "Feature",
  "properties": {
    "iso:country":"BE",
    "sg:address":"Kaaistraat 11",
    "sg:city":"Avelgem",
    "sg:orig_category":"Woningbouw",
    "sg:phone":"+32 55 38 86 94",
    "sg:postcode":"8581",
    "sg:province":"West-Vlaanderen",
    "wof:name":"Bouwwerken Desseyn",
    "wof:placetype":"venue"
},
  "geometry": {"coordinates":[3.5000200272,50.7991867065],"type":"Point"}
}