{
  "type": "Feature",
  "properties": {
    "addr:full":"Steentjestraat 81b Laarne Oost-Vlaanderen 9270",
    "addr:housenumber":"81b",
    "addr:postcode":"9270",
    "addr:street":"Steentjestraat",
    "iso:country":"BE",
    "sg:address":"Steentjestraat 81b",
    "sg:city":"Laarne",
    "sg:classifiers":[
        {
            "category":"Wholesale",
            "subcategory":"Plants",
            "type":"Manufacturing & Wholesale Goods"
        }
    ],
    "sg:phone":"+32 9 366 17 90",
    "sg:postcode":"9270",
    "sg:province":"Oost-Vlaanderen",
    "sg:tags":[
        "whol",
        "flower",
        "-",
        "grower"
    ],
    "wof:name":"Hollevoet Bvba",
    "wof:placetype":"venue"
},
  "geometry": {"coordinates":[3.8808600903,51.0410614014],"type":"Point"}
}