{
  "type": "Feature",
  "properties": {
    "addr:full":"Spreeuwweg 19 Keerbergen Vlaams-Brabant 3140",
    "addr:housenumber":"19",
    "addr:postcode":"3140",
    "addr:street":"Spreeuwweg",
    "iso:country":"BE",
    "sg:address":"Spreeuwweg 19",
    "sg:city":"Keerbergen",
    "sg:orig_category":"Maroquinerie Fab",
    "sg:phone":"+32 16 60 17 17",
    "sg:postcode":"3140",
    "sg:province":"Vlaams-Brabant",
    "wof:name":"Toro International",
    "wof:placetype":"venue"
},
  "geometry": {"coordinates":[4.6489801407,50.9887313843],"type":"Point"}
}