{
  "type": "Feature",
  "properties": {
    "addr:full":"Avenue Reine Astrid 430 Kraainem Vlaams-Brabant 1950",
    "addr:housenumber":"430",
    "addr:postcode":"1950",
    "addr:street":"Avenue Reine Astrid",
    "iso:country":"BE",
    "sg:address":"Avenue Reine Astrid 430",
    "sg:city":"Kraainem",
    "sg:classifiers":[
        {
            "category":"Retail",
            "subcategory":"Event Space",
            "type":"Services"
        }
    ],
    "sg:phone":"+32 2 731 35 07",
    "sg:postcode":"1950",
    "sg:province":"Vlaams-Brabant",
    "sg:tags":[
        "rental",
        "-",
        "hall"
    ],
    "wof:name":"Al Pronto",
    "wof:placetype":"venue"
},
  "geometry": {"coordinates":[4.4686689377,50.8397102356],"type":"Point"}
}