{
  "type": "Feature",
  "properties": {
    "addr:full":"Singel 16 Grimbergen Vlaams-Brabant 1853",
    "addr:housenumber":"16",
    "addr:postcode":"1853",
    "addr:street":"Singel",
    "iso:country":"BE",
    "sg:address":"Singel 16",
    "sg:city":"Grimbergen",
    "sg:orig_category":"Articles de jardin",
    "sg:phone":"+32 2 267 36 09",
    "sg:postcode":"1853",
    "sg:province":"Vlaams-Brabant",
    "wof:name":"Scheerlinck",
    "wof:placetype":"venue"
},
  "geometry": {"coordinates":[4.354183197,50.9118309021],"type":"Point"}
}