{
  "type": "Feature",
  "properties": {
    "addr:full":"Chauss\u00c9e De Tongres 269 Fleron Li\u00e8ge 4620",
    "addr:housenumber":"269",
    "addr:postcode":"4620",
    "addr:street":"Chausse\u0301E De Tongres",
    "iso:country":"BE",
    "sg:address":"Chauss\u00c9e De Tongres 269",
    "sg:city":"Fleron",
    "sg:classifiers":[
        {
            "category":"Fast Food",
            "type":"Food & Drink"
        }
    ],
    "sg:phone":"+32 4 246 49 14",
    "sg:postcode":"4620",
    "sg:province":"Li\u00e8ge",
    "sg:tags":[
        "\u00c0",
        "emporter",
        "restaurants"
    ],
    "wof:name":"Quick",
    "wof:placetype":"venue"
},
  "geometry": {"coordinates":[5.6854658127,50.6180953979],"type":"Point"}
}