{
  "type": "Feature",
  "properties": {
    "addr:full":"Avenue Du Bois De La Cambre 101 Elsene/ixelles Bruxelles-Capitale 1050",
    "addr:housenumber":"101",
    "addr:postcode":"1050",
    "addr:street":"Avenue Du Bois De La Cambre",
    "iso:country":"BE",
    "sg:address":"Avenue Du Bois De La Cambre 101",
    "sg:city":"Elsene/ixelles",
    "sg:orig_category":"M\u00e9decins and sp\u00e9cialistes",
    "sg:phone":"+32 2 653 78 26",
    "sg:postcode":"1050",
    "sg:province":"Bruxelles-Capitale",
    "wof:name":"Jejeune V\u00c9ronique",
    "wof:placetype":"venue"
},
  "geometry": {"coordinates":[4.3935627937,50.8084831238],"type":"Point"}
}