{
  "type": "Feature",
  "properties": {
    "addr:full":"Avenue Des Rok\u00c8tes 9 Rebecq Brabant Wallon 1430",
    "addr:housenumber":"9",
    "addr:postcode":"1430",
    "addr:street":"Avenue Des Roke\u0300Tes",
    "iso:country":"BE",
    "sg:address":"Avenue Des Rok\u00c8tes 9",
    "sg:city":"Rebecq",
    "sg:orig_category":"Sportclubs",
    "sg:phone":"+32 67 67 00 82",
    "sg:postcode":"1430",
    "sg:province":"Brabant Wallon",
    "wof:name":"J.c. Rebecq",
    "wof:placetype":"venue"
},
  "geometry": {"coordinates":[4.1368250847,50.6654205322],"type":"Point"}
}