{
  "type": "Feature",
  "properties": {
    "iso:country":"BE",
    "sg:address":"Rue G\u00e9ologue M. Robert 39",
    "sg:city":"Beloeil (stambruges)",
    "sg:classifiers":[
        {
            "category":"Professional",
            "subcategory":"Accounting & Tax Preparation",
            "type":"Services"
        }
    ],
    "sg:phone":"+32 69 58 04 70",
    "sg:postcode":"7973",
    "sg:province":"Hainaut",
    "sg:tags":[
        "accountant"
    ],
    "wof:name":"Galand D",
    "wof:placetype":"venue"
},
  "geometry": {"coordinates":[3.7230789661,50.5090179443],"type":"Point"}
}