{
  "type": "Feature",
  "properties": {
    "iso:country":"BE",
    "sg:address":"Harentstraat 39",
    "sg:city":"Bonheiden (rijmenam)",
    "sg:classifiers":[
        {
            "category":"Bars & Pubs",
            "type":"Food & Drink"
        }
    ],
    "sg:phone":"+32 15 33 14 39",
    "sg:postcode":"2820",
    "sg:province":"Antwerpen",
    "wof:name":"Bromfiets",
    "wof:placetype":"venue"
},
  "geometry": {"coordinates":[4.576002121,51.020160675],"type":"Point"}
}