{
  "type": "Feature",
  "properties": {
    "iso:country":"BE",
    "sg:address":"Avenue Des Cerisiers 128",
    "sg:city":"Bruxelles (woluwe-saint-lambert)",
    "sg:classifiers":[
        {
            "category":"Education",
            "subcategory":"University",
            "type":"Public Place"
        }
    ],
    "sg:phone":"+32 2 734 06 99",
    "sg:postcode":"1200",
    "sg:province":"Bruxelles-Capitale",
    "sg:tags":[
        "higher"
    ],
    "wof:name":"Centre De Formation \u00e0 La Culture Europ\u00e9enne En Belgique",
    "wof:placetype":"venue"
},
  "geometry": {"coordinates":[4.4103579521,50.8475265503],"type":"Point"}
}