{
  "type": "Feature",
  "properties": {
    "addr:full":"Dr. A.rubbensstraat 33 Zele Oost-Vlaanderen 9240",
    "addr:housenumber":"33",
    "addr:postcode":"9240",
    "addr:street":"A.Rubbensstraat",
    "iso:country":"BE",
    "sg:address":"Dr. A.rubbensstraat 33",
    "sg:city":"Zele",
    "sg:orig_category":"Diverse bedrijfsbeheeradviesbureaus",
    "sg:phone":"+32 52 44 99 31",
    "sg:postcode":"9240",
    "sg:province":"Oost-Vlaanderen",
    "wof:name":"Change Management Institute",
    "wof:placetype":"venue"
},
  "geometry": {"coordinates":[4.0423297882,51.0681991577],"type":"Point"}
}