{
  "type": "Feature",
  "properties": {
    "addr:full":"Voornlaan 20 Oudergem/auderghem Bruxelles-Capitale 1160",
    "addr:housenumber":"20",
    "addr:postcode":"1160",
    "addr:street":"Voornlaan;/",
    "iso:country":"BE",
    "sg:address":"Voornlaan 20",
    "sg:city":"Oudergem/auderghem",
    "sg:orig_category":"Architecten",
    "sg:phone":"+32 2 673 31 11",
    "sg:postcode":"1160",
    "sg:province":"Bruxelles-Capitale",
    "wof:name":"Marc De Wasseige",
    "wof:placetype":"venue"
},
  "geometry": {"coordinates":[4.409183979,50.8134689331],"type":"Point"}
}