{
  "type": "Feature",
  "properties": {
    "iso:country":"BE",
    "sg:address":"Cellebroersstraat 97",
    "sg:city":"Brussel/bruxelles",
    "sg:classifiers":[
        {
            "category":"Restaurant",
            "type":"Food & Drink"
        }
    ],
    "sg:phone":"+32 2 513 58 54",
    "sg:postcode":"1000",
    "sg:province":"Bruxelles-Capitale",
    "wof:name":"L'amalgamme",
    "wof:placetype":"venue"
},
  "geometry": {"coordinates":[4.3520541191,50.8421783447],"type":"Point"}
}