{
  "type": "Feature",
  "properties": {
    "iso:country":"BE",
    "sg:address":"Dorp-oost 3",
    "sg:city":"Lochristi",
    "sg:classifiers":[
        {
            "category":"Shopping",
            "subcategory":"Crafts & Fabrics",
            "type":"Retail Goods"
        }
    ],
    "sg:phone":"+32 9 355 60 55",
    "sg:postcode":"9080",
    "sg:province":"Oost-Vlaanderen",
    "sg:tags":[
        "textile",
        "lingerie",
        "sous-v\u00eatements"
    ],
    "wof:name":"Martine's Naaiboetiek",
    "wof:placetype":"venue"
},
  "geometry": {"coordinates":[3.8332519531,51.0964279175],"type":"Point"}
}