{
  "type": "Feature",
  "properties": {
    "iso:country":"BE",
    "sg:address":"Rue Du Ban-de-villers 6",
    "sg:city":"Etalle",
    "sg:classifiers":[
        {
            "category":"Personal",
            "subcategory":"Beauty Salon",
            "type":"Services"
        }
    ],
    "sg:phone":"+32 63 45 52 70",
    "sg:postcode":"6741",
    "sg:province":"Luxembourg",
    "sg:tags":[
        "de",
        "coiffure"
    ],
    "wof:name":"Marie Braconnier",
    "wof:placetype":"venue"
},
  "geometry": {"coordinates":[5.6673212051,49.6705703735],"type":"Point"}
}