{
  "type": "Feature",
  "properties": {
    "iso:country":"BE",
    "sg:address":"Diepestraat 8",
    "sg:city":"Bertem",
    "sg:orig_category":"Slagers",
    "sg:phone":"+32 2 767 85 60",
    "sg:postcode":"3061",
    "sg:province":"Vlaams-Brabant",
    "wof:name":"Frank Bruyninckx",
    "wof:placetype":"venue"
},
  "geometry": {"coordinates":[4.5684070587,50.8551521301],"type":"Point"}
}