{
  "type": "Feature",
  "properties": {
    "addr:full":"Rue Du Beau Site 65 Charleroi (marcinelle) Hainaut 6001",
    "addr:housenumber":"65",
    "addr:postcode":"6001",
    "addr:street":"Rue Du Beau Site",
    "iso:country":"BE",
    "sg:address":"Rue Du Beau Site 65",
    "sg:city":"Charleroi (marcinelle)",
    "sg:classifiers":[
        {
            "category":"Professional",
            "subcategory":"Lawyer & Legal Services",
            "type":"Services"
        }
    ],
    "sg:phone":"+32 71 47 82 78",
    "sg:postcode":"6001",
    "sg:province":"Hainaut",
    "wof:name":"Merveille Dominique",
    "wof:placetype":"venue"
},
  "geometry": {"coordinates":[4.4256181717,50.3956756592],"type":"Point"}
}