{
  "type": "Feature",
  "properties": {
    "addr:full":"Route De Radar 2 Manhay Luxembourg 6960",
    "addr:housenumber":"2",
    "addr:postcode":"6960",
    "addr:street":"Route De Radar",
    "iso:country":"BE",
    "sg:address":"Route De Radar 2",
    "sg:city":"Manhay",
    "sg:orig_category":"Loodgieterij, verwarming and sanitaire installaties",
    "sg:phone":"+32 86 45 54 17",
    "sg:postcode":"6960",
    "sg:province":"Luxembourg",
    "wof:name":"Marc Evrard",
    "wof:placetype":"venue"
},
  "geometry": {"coordinates":[5.6399898529,50.2792205811],"type":"Point"}
}