{
  "type": "Feature",
  "properties": {
    "addr:full":"Avenue Demolder 106 Ottignies-louvain-la-neuve (limelette) Brabant Wallon 1342",
    "addr:housenumber":"106",
    "addr:postcode":"1342",
    "addr:street":"Avenue Demolder",
    "iso:country":"BE",
    "sg:address":"Avenue Demolder 106",
    "sg:city":"Ottignies-louvain-la-neuve (limelette)",
    "sg:classifiers":[
        {
            "category":"Home & Garden",
            "subcategory":"Building Materials",
            "type":"Retail Goods"
        }
    ],
    "sg:phone":"+32 10 41 40 90",
    "sg:postcode":"1342",
    "sg:province":"Brabant Wallon",
    "sg:tags":[
        "shutter"
    ],
    "wof:name":"Godecharles Sprl",
    "wof:placetype":"venue"
},
  "geometry": {"coordinates":[4.5653572083,50.6753005981],"type":"Point"}
}