{
  "type": "Feature",
  "properties": {
    "addr:full":"Pl Reine Astrid 18 Rocourt Li\u00e8ge 4420",
    "addr:housenumber":"18",
    "addr:postcode":"4420",
    "addr:street":"Pl Reine Astrid",
    "iso:country":"BE",
    "sg:address":"Pl Reine Astrid 18",
    "sg:city":"Rocourt",
    "sg:classifiers":[
        {
            "category":"Banks & Credit Unions",
            "subcategory":"Bank",
            "type":"Services"
        }
    ],
    "sg:phone":"+32 41638832",
    "sg:postcode":"4420",
    "sg:province":"Li\u00e8ge",
    "wof:name":"Cr\u00e9dit G\u00e9n\u00e9ral Sa",
    "wof:placetype":"venue"
},
  "geometry": {"coordinates":[5.5459651947,50.6312713623],"type":"Point"}
}