{
  "type": "Feature",
  "properties": {
    "addr:full":"Zeedijk Wenduine 26 De Haan (wenduine) West-Vlaanderen 8420",
    "addr:housenumber":"26",
    "addr:postcode":"8420",
    "addr:street":"Zeedijk Wenduine",
    "iso:country":"BE",
    "sg:address":"Zeedijk Wenduine 26",
    "sg:city":"De Haan (wenduine)",
    "sg:classifiers":[
        {
            "category":"Tea Room",
            "subcategory":"None",
            "type":"Food & Drink"
        }
    ],
    "sg:phone":"+32 50 41 06 10",
    "sg:postcode":"8420",
    "sg:province":"West-Vlaanderen",
    "wof:name":"William's",
    "wof:placetype":"venue"
},
  "geometry": {"coordinates":[3.0799219608,51.301864624],"type":"Point"}
}