{
  "type": "Feature",
  "properties": {
    "iso:country":"BE",
    "sg:address":"Traverse De L'escope 12",
    "sg:city":"Ottignies-louvain-la-neuve",
    "sg:classifiers":[
        {
            "category":"Restaurant",
            "type":"Food & Drink"
        }
    ],
    "sg:phone":"+32 10 45 01 28",
    "sg:postcode":"1348",
    "sg:province":"Brabant Wallon",
    "wof:name":"Restaurant Roma",
    "wof:placetype":"venue"
},
  "geometry": {"coordinates":[4.614387989,50.6690254211],"type":"Point"}
}