{
  "type": "Feature",
  "properties": {
    "addr:full":"Rue Godfroid Kurth 65 Bruxelles (evere) Bruxelles-Capitale 1140",
    "addr:housenumber":"65",
    "addr:postcode":"1140",
    "addr:street":"Rue Godfroid Kurth",
    "iso:country":"BE",
    "sg:address":"Rue Godfroid Kurth 65",
    "sg:city":"Bruxelles (evere)",
    "sg:classifiers":[
        {
            "category":"Health Services",
            "subcategory":"Health Practitioner",
            "type":"Services"
        }
    ],
    "sg:phone":"+32 2 215 77 72",
    "sg:postcode":"1140",
    "sg:province":"Bruxelles-Capitale",
    "sg:tags":[
        "physiotherapist"
    ],
    "wof:name":"Berckmans Val\u00e9rie",
    "wof:placetype":"venue"
},
  "geometry": {"coordinates":[4.3985729218,50.8689994812],"type":"Point"}
}