{
  "type": "Feature",
  "properties": {
    "addr:full":"Chauss\u00c9e De Wavre 184 Wanze Li\u00e8ge 4520",
    "addr:housenumber":"184",
    "addr:postcode":"4520",
    "addr:street":"Chausse\u0301E De Wavre",
    "iso:country":"BE",
    "sg:address":"Chauss\u00c9e De Wavre 184",
    "sg:city":"Wanze",
    "sg:classifiers":[
        {
            "category":"Government",
            "subcategory":"Department Of Motor Vehicles",
            "type":"Public Place"
        }
    ],
    "sg:phone":"+32 85 21 49 77",
    "sg:postcode":"4520",
    "sg:province":"Li\u00e8ge",
    "sg:tags":[
        "mat\u00e9riel",
        "de",
        "location",
        "diver"
    ],
    "wof:name":"Lovema",
    "wof:placetype":"venue"
},
  "geometry": {"coordinates":[5.2008600235,50.5371627808],"type":"Point"}
}