{
  "type": "Feature",
  "properties": {
    "iso:country":"BE",
    "sg:address":"Koninginneoord 3",
    "sg:city":"Wezembeek-oppem/wezembeek-oppem",
    "sg:orig_category":"Landmeters",
    "sg:phone":"+32 2 782 08 10",
    "sg:postcode":"1970",
    "sg:province":"Vlaams-Brabant",
    "wof:name":"Bernard Maryns",
    "wof:placetype":"venue"
},
  "geometry": {"coordinates":[4.4854650497,50.8393516541],"type":"Point"}
}