{
  "type": "Feature",
  "properties": {
    "addr:full":"Molenweg 53 Willebroek Antwerpen 2830",
    "addr:housenumber":"53",
    "addr:postcode":"2830",
    "addr:street":"Molenweg",
    "iso:country":"BE",
    "sg:address":"Molenweg 53",
    "sg:city":"Willebroek",
    "sg:classifiers":[
        {
            "category":"Restaurant",
            "type":"Food & Drink"
        }
    ],
    "sg:phone":"+32 3 866 39 62",
    "sg:postcode":"2830",
    "sg:province":"Antwerpen",
    "wof:name":"Berlinda Roelants",
    "wof:placetype":"venue"
},
  "geometry": {"coordinates":[4.3679609299,51.0529251099],"type":"Point"}
}