{
  "type": "Feature",
  "properties": {
    "iso:country":"BE",
    "sg:address":"Fazantendreef 2",
    "sg:city":"Wingene",
    "sg:orig_category":"Eleveurs de bovins. Eleveurs and marchands de porcs",
    "sg:phone":"+32 50 78 89 92",
    "sg:postcode":"8750",
    "sg:province":"West-Vlaanderen",
    "wof:name":"Robert Vandewiele",
    "wof:placetype":"venue"
},
  "geometry": {"coordinates":[3.3079149723,51.0979919434],"type":"Point"}
}