{
  "type": "Feature",
  "properties": {
    "addr:full":"Rue Des Pinsons 1 Namur (jambes) Namur 5100",
    "addr:housenumber":"1",
    "addr:postcode":"5100",
    "addr:street":"Rue Des Pinsons",
    "iso:country":"BE",
    "sg:address":"Rue Des Pinsons 1",
    "sg:city":"Namur (jambes)",
    "sg:classifiers":[
        {
            "category":"Military Area",
            "subcategory":"Air Force Base",
            "type":"Public Place"
        }
    ],
    "sg:phone":"+32 81 73 80 24",
    "sg:postcode":"5100",
    "sg:province":"Namur",
    "sg:tags":[
        "fire",
        "protection"
    ],
    "wof:name":"Bister (entr)",
    "wof:placetype":"venue"
},
  "geometry": {"coordinates":[4.8713750839,50.4566345215],"type":"Point"}
}