{
  "type": "Feature",
  "properties": {
    "iso:country":"BE",
    "sg:address":"K. Boomstraat 78b",
    "sg:city":"Hoogstraten",
    "sg:orig_category":"Schoonheidssalons",
    "sg:phone":"+32 3 314 93 66",
    "sg:postcode":"2320",
    "sg:province":"Antwerpen",
    "wof:name":"Instituut Cocon",
    "wof:placetype":"venue"
},
  "geometry": {"coordinates":[4.7517590523,51.4039306641],"type":"Point"}
}