{
  "type": "Feature",
  "properties": {
    "addr:full":"Rue Hanroux 35 Remicourt Li\u00e8ge 4350",
    "addr:housenumber":"35",
    "addr:postcode":"4350",
    "addr:street":"Rue Hanroux",
    "iso:country":"BE",
    "sg:address":"Rue Hanroux 35",
    "sg:city":"Remicourt",
    "sg:orig_category":"M\u00e9decins and sp\u00e9cialistes",
    "sg:phone":"+32 4 250 15 51",
    "sg:postcode":"4350",
    "sg:province":"Li\u00e8ge",
    "wof:name":"Willy Kefer",
    "wof:placetype":"venue"
},
  "geometry": {"coordinates":[5.3793730736,50.6829032898],"type":"Point"}
}