{
  "type": "Feature",
  "properties": {
    "addr:full":"Le-buisson-des-cailleschas. 10 Chassepierre Luxembourg 6824",
    "addr:housenumber":"10",
    "addr:postcode":"6824",
    "addr:street":"Le-Buisson-Des-Cailleschas.",
    "iso:country":"BE",
    "sg:address":"Le-buisson-des-cailleschas. 10",
    "sg:city":"Chassepierre",
    "sg:classifiers":[
        {
            "category":"Mining & Drilling",
            "type":"Manufacturing & Wholesale Goods"
        }
    ],
    "sg:phone":"+32 61 31 30 32",
    "sg:postcode":"6824",
    "sg:province":"Luxembourg",
    "sg:tags":[
        "quarry"
    ],
    "wof:name":"Remy Emond S.a.",
    "wof:placetype":"venue"
},
  "geometry": {"coordinates":[5.25897789,49.7073478699],"type":"Point"}
}