{
  "type": "Feature",
  "properties": {
    "addr:full":"E. Eylenboschstraat 18 Dilbeek Vlaams-Brabant 1703",
    "addr:housenumber":"18",
    "addr:postcode":"1703",
    "addr:street":"E. Eylenboschstraat",
    "iso:country":"BE",
    "sg:address":"E. Eylenboschstraat 18",
    "sg:city":"Dilbeek",
    "sg:orig_category":"Banken and kredietinstellingen",
    "sg:phone":"+32 2 569 76 53",
    "sg:postcode":"1703",
    "sg:province":"Vlaams-Brabant",
    "wof:name":"Kbc",
    "wof:placetype":"venue"
},
  "geometry": {"coordinates":[4.1935248375,50.8355064392],"type":"Point"}
}