{
  "type": "Feature",
  "properties": {
    "addr:full":"Ezaart 113 Mol Antwerpen 2400",
    "addr:housenumber":"113",
    "addr:postcode":"2400",
    "addr:street":"Ezaart",
    "iso:country":"BE",
    "sg:address":"Ezaart 113",
    "sg:city":"Mol",
    "sg:classifiers":[
        {
            "category":"Travel",
            "subcategory":"Travel Agent",
            "type":"Entertainment"
        }
    ],
    "sg:phone":"+32 14 32 04 04",
    "sg:postcode":"2400",
    "sg:province":"Antwerpen",
    "sg:tags":[
        "agency"
    ],
    "wof:name":"Cocon Reizen",
    "wof:placetype":"venue"
},
  "geometry": {"coordinates":[5.0978899002,51.1795806885],"type":"Point"}
}