{
  "type": "Feature",
  "properties": {
    "iso:country":"BE",
    "sg:address":"Zeelsebaaan 83e",
    "sg:city":"Dendermonde",
    "sg:orig_category":"Syst\u00e8mes de t\u00e9l\u00e9communications. Mat\u00e9riel de T\u00e9l\u00e9communication",
    "sg:phone":"+32 52 20 20 40",
    "sg:postcode":"9200",
    "sg:province":"Oost-Vlaanderen",
    "wof:name":"Ecotel Bvba",
    "wof:placetype":"venue"
},
  "geometry": {"coordinates":[4.0983099937,51.0315208435],"type":"Point"}
}