{
  "type": "Feature",
  "properties": {
    "iso:country":"BE",
    "sg:address":"Torhoutsestr 224",
    "sg:city":"Oostkamp",
    "sg:classifiers":[
        {
            "category":"Professional",
            "type":"Services"
        }
    ],
    "sg:phone":"+32 50 27 77 83",
    "sg:postcode":"8020",
    "sg:province":"West-Vlaanderen",
    "sg:tags":[
        "transport",
        "road"
    ],
    "wof:name":"Lambert Bvba",
    "wof:placetype":"venue"
},
  "geometry": {"coordinates":[3.1832649708,51.0803604126],"type":"Point"}
}