{
  "type": "Feature",
  "properties": {
    "addr:full":"Verrebroekstraat 2 Beveren (verrebroek) Oost-Vlaanderen 9130",
    "addr:housenumber":"2",
    "addr:postcode":"9130",
    "addr:street":"Verrebroekstraat",
    "iso:country":"BE",
    "sg:address":"Verrebroekstraat 2",
    "sg:city":"Beveren (verrebroek)",
    "sg:classifiers":[
        {
            "category":"Bars & Pubs",
            "type":"Food & Drink"
        }
    ],
    "sg:phone":"+32 3 773 40 85",
    "sg:postcode":"9130",
    "sg:province":"Oost-Vlaanderen",
    "wof:name":"Terminus",
    "wof:placetype":"venue"
},
  "geometry": {"coordinates":[4.1892290115,51.2552185059],"type":"Point"}
}