{
  "type": "Feature",
  "properties": {
    "addr:full":"Rue Sainte-v\u00c9ronique 10 Li\u00c8ge Li\u00e8ge 4000",
    "addr:housenumber":"10",
    "addr:postcode":"4000",
    "addr:street":"Rue Sainte-Ve\u0301Ronique",
    "iso:country":"BE",
    "sg:address":"Rue Sainte-v\u00c9ronique 10",
    "sg:city":"Li\u00c8ge",
    "sg:classifiers":[
        {
            "category":"Cafe",
            "type":"Food & Drink"
        }
    ],
    "sg:phone":"+32 4 253 30 36",
    "sg:postcode":"4000",
    "sg:province":"Li\u00e8ge",
    "sg:tags":[
        "caf\u00e9s"
    ],
    "wof:name":"Giuliano Bizzozero",
    "wof:placetype":"venue"
},
  "geometry": {"coordinates":[5.5666880608,50.6319122314],"type":"Point"}
}