{
  "type": "Feature",
  "properties": {
    "addr:full":"Brederodestraat 148 Antwerpen Antwerpen 2018",
    "addr:housenumber":"148",
    "addr:postcode":"2018",
    "addr:street":"Brederodestraat",
    "iso:country":"BE",
    "sg:address":"Brederodestraat 148",
    "sg:city":"Antwerpen",
    "sg:classifiers":[
        {
            "category":"Bars & Pubs",
            "type":"Food & Drink"
        }
    ],
    "sg:phone":"+32 3 237 11 05",
    "sg:postcode":"2018",
    "sg:province":"Antwerpen",
    "wof:name":"Must",
    "wof:placetype":"venue"
},
  "geometry": {"coordinates":[4.3923940659,51.2021522522],"type":"Point"}
}