{
  "type": "Feature",
  "properties": {
    "iso:country":"BE",
    "sg:address":"Rue David Van Bever 25",
    "sg:city":"Bruxelles (woluwe-saint-pierre)",
    "sg:classifiers":[
        {
            "category":"Health Services",
            "subcategory":"Health Practitioner",
            "type":"Services"
        }
    ],
    "sg:phone":"+32 2 771 35 28",
    "sg:postcode":"1150",
    "sg:province":"Bruxelles-Capitale",
    "sg:tags":[
        "physiotherapist"
    ],
    "wof:name":"Daw E",
    "wof:placetype":"venue"
},
  "geometry": {"coordinates":[4.4398617744,50.8330574036],"type":"Point"}
}