{
  "type": "Feature",
  "properties": {
    "addr:full":"Chauss\u00c9e De Beaumont 99 Froidchapelle Hainaut 6440",
    "addr:housenumber":"99",
    "addr:postcode":"6440",
    "addr:street":"Chausse\u0301E De Beaumont",
    "iso:country":"BE",
    "sg:address":"Chauss\u00c9e De Beaumont 99",
    "sg:city":"Froidchapelle",
    "sg:orig_category":"Elektrische installaties voor woningen",
    "sg:phone":"+32 71 63 38 71",
    "sg:postcode":"6440",
    "sg:province":"Hainaut",
    "wof:name":"Ignas Dhaene",
    "wof:placetype":"venue"
},
  "geometry": {"coordinates":[4.3772997856,50.2285232544],"type":"Point"}
}