{
  "type": "Feature",
  "properties": {
    "iso:country":"BE",
    "sg:address":"Meiz 1",
    "sg:city":"Stavelot",
    "sg:classifiers":[
        {
            "category":"Building & Trades",
            "subcategory":"Construction",
            "type":"Services"
        }
    ],
    "sg:phone":"+32 80 86 32 06",
    "sg:postcode":"4970",
    "sg:province":"Li\u00e8ge",
    "sg:tags":[
        "carpenter"
    ],
    "wof:name":"Mar\u00e9chal G",
    "wof:placetype":"venue"
},
  "geometry": {"coordinates":[5.9816060066,50.4200973511],"type":"Point"}
}