{
  "type": "Feature",
  "properties": {
    "iso:country":"BE",
    "sg:address":"Bennesteeg 19",
    "sg:city":"Gent",
    "sg:orig_category":"V\u00eatements pour Dames. V\u00eatements",
    "sg:phone":"+32 9 233 79 47",
    "sg:postcode":"9000",
    "sg:province":"Oost-Vlaanderen",
    "wof:name":"Huis Lena-lena",
    "wof:placetype":"venue"
},
  "geometry": {"coordinates":[3.7235920429,51.052444458],"type":"Point"}
}