{
  "type": "Feature",
  "properties": {
    "iso:country":"BE",
    "sg:address":"Noord-brabantlaan 6",
    "sg:city":"Turnhout",
    "sg:classifiers":[
        {
            "category":"Shopping",
            "subcategory":"Books",
            "type":"Retail Goods"
        }
    ],
    "sg:phone":"+32 14 45 00 51",
    "sg:postcode":"2300",
    "sg:province":"Antwerpen",
    "sg:tags":[
        "bookseller"
    ],
    "wof:name":"Boekbedrijf Uitg Standing Nv",
    "wof:placetype":"venue"
},
  "geometry": {"coordinates":[4.9673089981,51.3250656128],"type":"Point"}
}