{
  "type": "Feature",
  "properties": {
    "iso:country":"BE",
    "sg:address":"Westrodestraat 75",
    "sg:city":"Meise",
    "sg:orig_category":"Eleveurs de bovins",
    "sg:phone":"+32 15 71 17 46",
    "sg:postcode":"1861",
    "sg:province":"Vlaams-Brabant",
    "wof:name":"Willy Pinnock",
    "wof:placetype":"venue"
},
  "geometry": {"coordinates":[4.3334932327,50.9966049194],"type":"Point"}
}