{
  "type": "Feature",
  "properties": {
    "addr:full":"Elewijtsesteenweg 114 Zemst (eppegem) Vlaams-Brabant 1980",
    "addr:housenumber":"114",
    "addr:postcode":"1980",
    "addr:street":"Elewijtsesteenweg",
    "iso:country":"BE",
    "sg:address":"Elewijtsesteenweg 114",
    "sg:city":"Zemst (eppegem)",
    "sg:classifiers":[
        {
            "category":"Home & Garden",
            "subcategory":"Building Materials",
            "type":"Retail Goods"
        }
    ],
    "sg:phone":"+32 15 61 72 72",
    "sg:postcode":"1980",
    "sg:province":"Vlaams-Brabant",
    "sg:tags":[
        "window"
    ],
    "wof:name":"Thomas Veranda Bvba",
    "wof:placetype":"venue"
},
  "geometry": {"coordinates":[4.4658660889,50.9601516724],"type":"Point"}
}