{
  "type": "Feature",
  "properties": {
    "iso:country":"BE",
    "sg:address":"Edegemsestraat 7",
    "sg:city":"Hove",
    "sg:classifiers":[
        {
            "category":"Shopping",
            "subcategory":"Jewelry",
            "type":"Retail Goods"
        }
    ],
    "sg:phone":"+32 3 455 99 56",
    "sg:postcode":"2540",
    "sg:province":"Antwerpen",
    "sg:tags":[
        "jeweller",
        "-"
    ],
    "wof:name":"Ocket P",
    "wof:placetype":"venue"
},
  "geometry": {"coordinates":[4.4635128975,51.155166626],"type":"Point"}
}