{
  "type": "Feature",
  "properties": {
    "iso:country":"BE",
    "sg:address":"Dijkzijde 38",
    "sg:city":"Oud-turnhout",
    "sg:orig_category":"Jardins botaniques, zoologiques, observatoires and r\u00e9serves naturelles",
    "sg:phone":"+32 14 45 43 79",
    "sg:postcode":"2360",
    "sg:province":"Antwerpen",
    "wof:name":"Turnhouts Vennengebied",
    "wof:placetype":"venue"
},
  "geometry": {"coordinates":[4.9733510017,51.3187866211],"type":"Point"}
}