{
  "type": "Feature",
  "properties": {
    "addr:full":"Erfstraat 12 Lommel Limburg 3920",
    "addr:housenumber":"12",
    "addr:postcode":"3920",
    "addr:street":"Erfstraat",
    "iso:country":"BE",
    "sg:address":"Erfstraat 12",
    "sg:city":"Lommel",
    "sg:classifiers":[
        {
            "category":"Personal",
            "type":"Services"
        }
    ],
    "sg:phone":"+32 11 54 08 34",
    "sg:postcode":"3920",
    "sg:province":"Limburg",
    "sg:tags":[
        "clothing",
        "men's",
        "tailor",
        "-"
    ],
    "wof:name":"Mannaerts J",
    "wof:placetype":"venue"
},
  "geometry": {"coordinates":[5.3020758629,51.2343444824],"type":"Point"}
}