{
  "type": "Feature",
  "properties": {
    "iso:country":"BE",
    "sg:address":"Rue Grande 89",
    "sg:city":"Dinant",
    "sg:orig_category":"Rev\u00eatements pour sols and murs. Eclairage et \u00e9quipements du foyer. Peinture",
    "sg:phone":"+32 82 22 40 77",
    "sg:postcode":"5500",
    "sg:province":"Namur",
    "wof:name":"D\u00c9coration Paquay H\u00c9l\u00c8ne",
    "wof:placetype":"venue"
},
  "geometry": {"coordinates":[4.9141459465,50.2584152222],"type":"Point"}
}