{
  "type": "Feature",
  "properties": {
    "addr:full":"Rue Du Maquis 132 Bruxelles (evere) Bruxelles-Capitale 1140",
    "addr:housenumber":"132",
    "addr:postcode":"1140",
    "addr:street":"Rue Du Maquis",
    "iso:country":"BE",
    "sg:address":"Rue Du Maquis 132",
    "sg:city":"Bruxelles (evere)",
    "sg:classifiers":[
        {
            "category":"Health Services",
            "subcategory":"Doctor",
            "type":"Services"
        }
    ],
    "sg:phone":"+32 2 726 64 34",
    "sg:postcode":"1140",
    "sg:province":"Bruxelles-Capitale",
    "sg:tags":[
        "medicinephysicians",
        "surgeon"
    ],
    "wof:name":"De Greef Jean",
    "wof:placetype":"venue"
},
  "geometry": {"coordinates":[4.4142370224,50.8570556641],"type":"Point"}
}