{
  "type": "Feature",
  "properties": {
    "iso:country":"BE",
    "sg:address":"Lage Kaart 65",
    "sg:city":"Brasschaat",
    "sg:orig_category":"Artsen and specialisten",
    "sg:phone":"+32 3 652 01 02",
    "sg:postcode":"2930",
    "sg:province":"Antwerpen",
    "wof:name":"Anna-maria Van Cauwenberge",
    "wof:placetype":"venue"
},
  "geometry": {"coordinates":[4.4631662369,51.2952804565],"type":"Point"}
}