{
  "type": "Feature",
  "properties": {
    "addr:full":"Durmen 101-103 Zele Oost-Vlaanderen 9240",
    "addr:postcode":"101-103;9240",
    "iso:country":"BE",
    "sg:address":"Durmen 101-103",
    "sg:city":"Zele",
    "sg:classifiers":[
        {
            "category":"Health Services",
            "subcategory":"Medical Lab",
            "type":"Services"
        }
    ],
    "sg:phone":"+32 52 44 56 86",
    "sg:postcode":"9240",
    "sg:province":"Oost-Vlaanderen",
    "sg:tags":[
        "laboratory",
        "dental"
    ],
    "wof:name":"De Gelder Bvba",
    "wof:placetype":"venue"
},
  "geometry": {"coordinates":[4.0473752022,51.0829620361],"type":"Point"}
}