{
  "type": "Feature",
  "properties": {
    "addr:full":"Torhoutse Steenweg 58 Brugge West-Vlaanderen 8200",
    "addr:housenumber":"58",
    "addr:postcode":"8200",
    "addr:street":"Torhoutse Steenweg",
    "iso:country":"BE",
    "sg:address":"Torhoutse Steenweg 58",
    "sg:city":"Brugge",
    "sg:orig_category":"Avocats and conseillers juridiques",
    "sg:phone":"+32 50 38 62 25",
    "sg:postcode":"8200",
    "sg:province":"West-Vlaanderen",
    "wof:name":"Timothy Lanssens",
    "wof:placetype":"venue"
},
  "geometry": {"coordinates":[3.2060918808,51.2022171021],"type":"Point"}
}