{
  "type": "Feature",
  "properties": {
    "iso:country":"BE",
    "sg:address":"Avenue Nestor-martin 2",
    "sg:city":"Saint-hubert",
    "sg:orig_category":"Pain, p\u00e2tisseries and confiseries",
    "sg:phone":"+32 61 61 30 05",
    "sg:postcode":"6870",
    "sg:province":"Luxembourg",
    "wof:name":"Guy Stoz",
    "wof:placetype":"venue"
},
  "geometry": {"coordinates":[5.3701958656,50.0258522034],"type":"Point"}
}