{
  "type": "Feature",
  "properties": {
    "addr:full":"Rue De La Bellefleur 98 Blegny Li\u00e8ge 4672",
    "addr:housenumber":"98",
    "addr:postcode":"4672",
    "addr:street":"Rue De La Bellefleur",
    "iso:country":"BE",
    "sg:address":"Rue De La Bellefleur 98",
    "sg:city":"Blegny",
    "sg:orig_category":"Landbouwmachines Gh",
    "sg:phone":"+32 4 387 42 20",
    "sg:postcode":"4672",
    "sg:province":"Li\u00e8ge",
    "wof:name":"Ateliers Andr\u00c9",
    "wof:placetype":"venue"
},
  "geometry": {"coordinates":[5.7018008232,50.6961021423],"type":"Point"}
}