{
  "type": "Feature",
  "properties": {
    "addr:full":"Steenweg 190 Lanaken Limburg 3621",
    "addr:housenumber":"190",
    "addr:postcode":"3621",
    "addr:street":"Steenweg",
    "iso:country":"BE",
    "sg:address":"Steenweg 190",
    "sg:city":"Lanaken",
    "sg:classifiers":[
        {
            "category":"Insurance",
            "subcategory":"Insurance Agent",
            "type":"Services"
        }
    ],
    "sg:phone":"+32 89 71 56 56",
    "sg:postcode":"3621",
    "sg:province":"Limburg",
    "sg:tags":[
        "verzekeringsmakelaars",
        "expert"
    ],
    "wof:name":"Autostock Rekem",
    "wof:placetype":"venue"
},
  "geometry": {"coordinates":[5.6870179176,50.9250984192],"type":"Point"}
}