{
  "type": "Feature",
  "properties": {
    "addr:full":"Renbaanlaan 6 Kuurne West-Vlaanderen 8520",
    "addr:housenumber":"6",
    "addr:postcode":"8520",
    "addr:street":"Renbaanlaan",
    "iso:country":"BE",
    "sg:address":"Renbaanlaan 6",
    "sg:city":"Kuurne",
    "sg:orig_category":"Sportclubs",
    "sg:phone":"+32 56 70 05 09",
    "sg:postcode":"8520",
    "sg:province":"West-Vlaanderen",
    "wof:name":"Kuurnse Zwemclub Albatros",
    "wof:placetype":"venue"
},
  "geometry": {"coordinates":[3.2755520344,50.8577537537],"type":"Point"}
}