{
  "type": "Feature",
  "properties": {
    "addr:full":"Montenakenweg 80 Sint-truiden Limburg 3800",
    "addr:housenumber":"80",
    "addr:postcode":"3800",
    "addr:street":"Montenakenweg",
    "iso:country":"BE",
    "sg:address":"Montenakenweg 80",
    "sg:city":"Sint-truiden",
    "sg:classifiers":[
        {
            "category":"Restaurant",
            "type":"Food & Drink"
        }
    ],
    "sg:phone":"+32 11 68 97 06",
    "sg:postcode":"3800",
    "sg:province":"Limburg",
    "sg:tags":[
        "caf\u00e9s"
    ],
    "wof:name":"B.f.v. Cafetaria",
    "wof:placetype":"venue"
},
  "geometry": {"coordinates":[5.1763448715,50.8074226379],"type":"Point"}
}