{
  "type": "Feature",
  "properties": {
    "addr:full":"Rue De L' Abbaye 8 Rochefort (groot) Namur 5580",
    "addr:housenumber":"8",
    "addr:postcode":"5580",
    "addr:street":"Rue De L ' Abbaye;Groot Namur",
    "iso:country":"BE",
    "sg:address":"Rue De L' Abbaye 8",
    "sg:city":"Rochefort (groot)",
    "sg:classifiers":[
        {
            "category":"Restaurant",
            "type":"Food & Drink"
        }
    ],
    "sg:phone":"+32 84 21 31 81",
    "sg:postcode":"5580",
    "sg:province":"Namur",
    "sg:tags":[
        "brasserie"
    ],
    "wof:name":"Abbaye Notre Dame St.r\u00c9my",
    "wof:placetype":"venue"
},
  "geometry": {"coordinates":[5.2278199196,50.1997756958],"type":"Point"}
}