{
  "type": "Feature",
  "properties": {
    "addr:full":"Charleroise Steenweg 15 Sint-gillis/saint-gilles Bruxelles-Capitale 1060",
    "addr:housenumber":"15",
    "addr:postcode":"1060",
    "addr:street":"Charleroise Steenweg",
    "iso:country":"BE",
    "sg:address":"Charleroise Steenweg 15",
    "sg:city":"Sint-gillis/saint-gilles",
    "sg:orig_category":"Meubelzaken, woning- and keukeninrichting Verlichting and huishoudartikelen Vloer- and muurbekleding",
    "sg:phone":"+32 2 537 13 90",
    "sg:postcode":"1060",
    "sg:province":"Bruxelles-Capitale",
    "wof:name":"Creyel D\u00c9corateur",
    "wof:placetype":"venue"
},
  "geometry": {"coordinates":[4.3569121361,50.8331756592],"type":"Point"}
}