{
  "type": "Feature",
  "properties": {
    "iso:country":"BE",
    "sg:address":"Val De Pierreux 6",
    "sg:city":"La Roche-en-ardenne",
    "sg:orig_category":"Installation de menuiserie en bois and plastique",
    "sg:phone":"+32 84 41 10 87",
    "sg:postcode":"6980",
    "sg:province":"Luxembourg",
    "wof:name":"Michel Fraselle",
    "wof:placetype":"venue"
},
  "geometry": {"coordinates":[5.5883078575,50.1798706055],"type":"Point"}
}