{
  "type": "Feature",
  "properties": {
    "iso:country":"BE",
    "sg:address":"Heuveneindeweg 1",
    "sg:city":"Zonhoven",
    "sg:classifiers":[
        {
            "category":"Insurance",
            "subcategory":"Life Insurance",
            "type":"Services"
        }
    ],
    "sg:phone":"+32 11 81 88 82",
    "sg:postcode":"3520",
    "sg:province":"Limburg",
    "sg:tags":[
        "assurance"
    ],
    "wof:name":"Kantoor G.m.",
    "wof:placetype":"venue"
},
  "geometry": {"coordinates":[5.3667201996,50.9832038879],"type":"Point"}
}