{
  "type": "Feature",
  "properties": {
    "iso:country":"BE",
    "sg:address":"Jachthuislaan 9",
    "sg:city":"Lubbeek (linden)",
    "sg:classifiers":[
        {
            "category":"Wholesale",
            "subcategory":"Machinery & Supplies",
            "type":"Manufacturing & Wholesale Goods"
        }
    ],
    "sg:phone":"+32 16 62 27 44",
    "sg:postcode":"3210",
    "sg:province":"Vlaams-Brabant",
    "sg:tags":[
        "dry",
        "cleaner",
        "-",
        "dyer",
        "equipment"
    ],
    "wof:name":"Elgetex",
    "wof:placetype":"venue"
},
  "geometry": {"coordinates":[4.7801771164,50.9033851624],"type":"Point"}
}