{
  "type": "Feature",
  "properties": {
    "iso:country":"BE",
    "sg:address":"Westerlosesteenweg 64",
    "sg:city":"Heist-op-den-berg",
    "sg:classifiers":[
        {
            "category":"Retail",
            "subcategory":"Auto Repair",
            "type":"Services"
        }
    ],
    "sg:phone":"+32 15 25 04 32",
    "sg:postcode":"2220",
    "sg:province":"Antwerpen",
    "sg:tags":[
        "automobile-body"
    ],
    "wof:name":"Vervloet P",
    "wof:placetype":"venue"
},
  "geometry": {"coordinates":[4.7459712029,51.0697174072],"type":"Point"}
}