{
  "type": "Feature",
  "properties": {
    "iso:country":"BE",
    "sg:address":"Hoofdstraat 26",
    "sg:city":"Dendermonde",
    "sg:orig_category":"V\u00eatements pour Hommes. V\u00eatements pour Dames. V\u00eatements pour b\u00e9b\u00e9s and enfants",
    "sg:phone":"+32 52 21 11 73",
    "sg:postcode":"9200",
    "sg:province":"Oost-Vlaanderen",
    "wof:name":"Yolanda Scholliers",
    "wof:placetype":"venue"
},
  "geometry": {"coordinates":[4.0531859398,51.0290718079],"type":"Point"}
}