{
  "type": "Feature",
  "properties": {
    "addr:full":"Astridlaan 150 Brugge (assebroek) West-Vlaanderen 8310",
    "addr:housenumber":"150",
    "addr:postcode":"8310",
    "addr:street":"Astridlaan",
    "iso:country":"BE",
    "sg:address":"Astridlaan 150",
    "sg:city":"Brugge (assebroek)",
    "sg:classifiers":[
        {
            "category":"Personal",
            "subcategory":"Beauty Salon",
            "type":"Services"
        }
    ],
    "sg:phone":"+32 50 35 28 37",
    "sg:postcode":"8310",
    "sg:province":"West-Vlaanderen",
    "sg:tags":[
        "lady",
        "-",
        "hairdressing"
    ],
    "wof:name":"Ghislaine",
    "wof:placetype":"venue"
},
  "geometry": {"coordinates":[3.2530200481,51.1965942383],"type":"Point"}
}