{
  "type": "Feature",
  "properties": {
    "addr:full":"Waversesteenweg 94a Hoeilaart Vlaams-Brabant 1560",
    "addr:housenumber":"94a",
    "addr:postcode":"1560",
    "addr:street":"Waversesteenweg",
    "iso:country":"BE",
    "sg:address":"Waversesteenweg 94a",
    "sg:city":"Hoeilaart",
    "sg:classifiers":[
        {
            "category":"Home & Garden",
            "subcategory":"Building Materials",
            "type":"Retail Goods"
        }
    ],
    "sg:phone":"+32 2 657 79 72",
    "sg:postcode":"1560",
    "sg:province":"Vlaams-Brabant",
    "sg:tags":[
        "window"
    ],
    "wof:name":"Raes J-c",
    "wof:placetype":"venue"
},
  "geometry": {"coordinates":[4.479932785,50.7566490173],"type":"Point"}
}