{
  "type": "Feature",
  "properties": {
    "addr:full":"Rue Joseph Wauters 7 Engis Li\u00e8ge 4480",
    "addr:housenumber":"7",
    "addr:postcode":"4480",
    "addr:street":"Rue Joseph Wauters",
    "iso:country":"BE",
    "sg:address":"Rue Joseph Wauters 7",
    "sg:city":"Engis",
    "sg:orig_category":"Jeux de hasard",
    "sg:phone":"+32 4 275 33 50",
    "sg:postcode":"4480",
    "sg:province":"Li\u00e8ge",
    "wof:name":"Tierc\u00c9 Franco Belge",
    "wof:placetype":"venue"
},
  "geometry": {"coordinates":[5.4042038918,50.5809364319],"type":"Point"}
}