{
  "type": "Feature",
  "properties": {
    "addr:full":"Rue Des D\u00c9port\u00c9s 13 Floreffe Namur 5150",
    "addr:housenumber":"13",
    "addr:postcode":"5150",
    "addr:street":"Rue Des De\u0301Porte\u0301S",
    "iso:country":"BE",
    "sg:address":"Rue Des D\u00c9port\u00c9s 13",
    "sg:city":"Floreffe",
    "sg:orig_category":"Artsen and specialisten",
    "sg:phone":"+32 81 44 10 22",
    "sg:postcode":"5150",
    "sg:province":"Namur",
    "wof:name":"E. Dubois",
    "wof:placetype":"venue"
},
  "geometry": {"coordinates":[4.7578229904,50.434803009],"type":"Point"}
}