{
  "type": "Feature",
  "properties": {
    "iso:country":"BE",
    "sg:address":"Schaluin 31",
    "sg:city":"Aarschot",
    "sg:orig_category":"V\u00eatements pour Dames. V\u00eatements",
    "sg:phone":"+32 16 56 40 27",
    "sg:postcode":"3200",
    "sg:province":"Vlaams-Brabant",
    "wof:name":"Pocoline",
    "wof:placetype":"venue"
},
  "geometry": {"coordinates":[4.8391900063,50.9890403748],"type":"Point"}
}