{
  "type": "Feature",
  "properties": {
    "addr:full":"Rue De La Caserne 68 Brussel/bruxelles Bruxelles-Capitale 1000",
    "addr:housenumber":"68",
    "addr:postcode":"1000",
    "addr:street":"Rue De La Caserne;/",
    "iso:country":"BE",
    "sg:address":"Rue De La Caserne 68",
    "sg:city":"Brussel/bruxelles",
    "sg:classifiers":[
        {
            "category":"Organizations",
            "subcategory":"Community Association",
            "type":"Services"
        }
    ],
    "sg:phone":"+32 2 513 33 93",
    "sg:postcode":"1000",
    "sg:province":"Bruxelles-Capitale",
    "sg:tags":[
        "organisation"
    ],
    "wof:name":"Jongeren Aan Bod",
    "wof:placetype":"venue"
},
  "geometry": {"coordinates":[4.3421759605,50.8419113159],"type":"Point"}
}