{
  "type": "Feature",
  "properties": {
    "addr:full":"Rue De L\u00b4eglise 123 Spa Li\u00e8ge 4900",
    "addr:housenumber":"123",
    "addr:postcode":"4900",
    "addr:street":"Rue De L\u00b4Eglise",
    "iso:country":"BE",
    "sg:address":"Rue De L\u00b4eglise 123",
    "sg:city":"Spa",
    "sg:orig_category":"Dierenartsen",
    "sg:phone":"+32 87 77 57 38",
    "sg:postcode":"4900",
    "sg:province":"Li\u00e8ge",
    "wof:name":"K. Van Den Abeele",
    "wof:placetype":"venue"
},
  "geometry": {"coordinates":[5.8495202065,50.4773216248],"type":"Point"}
}