{
  "type": "Feature",
  "properties": {
    "addr:full":"David Teniersstraat 20 Ronse/renaix Oost-Vlaanderen 9600",
    "addr:housenumber":"20",
    "addr:postcode":"9600",
    "addr:street":"David Teniersstraat",
    "iso:country":"BE",
    "sg:address":"David Teniersstraat 20",
    "sg:city":"Ronse/renaix",
    "sg:orig_category":"Boekhouders",
    "sg:phone":"+32 55 20 90 44",
    "sg:postcode":"9600",
    "sg:province":"Oost-Vlaanderen",
    "wof:name":"Brigitte Tonneau",
    "wof:placetype":"venue"
},
  "geometry": {"coordinates":[3.6011109352,50.7406921387],"type":"Point"}
}