{
  "type": "Feature",
  "properties": {
    "addr:full":"Guido Gezellestraat 53 Willebroek Antwerpen 2830",
    "addr:housenumber":"53",
    "addr:postcode":"2830",
    "addr:street":"Guido Gezellestraat",
    "iso:country":"BE",
    "sg:address":"Guido Gezellestraat 53",
    "sg:city":"Willebroek",
    "sg:classifiers":[
        {
            "category":"Bars & Pubs",
            "type":"Food & Drink"
        }
    ],
    "sg:phone":"+32 3 293 32 82",
    "sg:postcode":"2830",
    "sg:province":"Antwerpen",
    "wof:name":"Molenhuis",
    "wof:placetype":"venue"
},
  "geometry": {"coordinates":[4.3580698967,51.0650901794],"type":"Point"}
}