{
  "type": "Feature",
  "properties": {
    "addr:full":"Rue J. Destree 10 Anderlues Hainaut 6150",
    "addr:housenumber":"10",
    "addr:postcode":"6150",
    "addr:street":"Rue J. Destree",
    "iso:country":"BE",
    "sg:address":"Rue J. Destree 10",
    "sg:city":"Anderlues",
    "sg:orig_category":"Huishoudapparaten, televisies and radio's Telecommunicatieapparaten",
    "sg:phone":"+32 71 52 42 79",
    "sg:postcode":"6150",
    "sg:province":"Hainaut",
    "wof:name":"Dutron",
    "wof:placetype":"venue"
},
  "geometry": {"coordinates":[4.2644381523,50.4146881104],"type":"Point"}
}