{
  "type": "Feature",
  "properties": {
    "addr:full":"Boomse Steenweg 14 Schelle Antwerpen 2627",
    "addr:housenumber":"14",
    "addr:postcode":"2627",
    "addr:street":"Steenweg",
    "iso:country":"BE",
    "sg:address":"Boomse Steenweg 14",
    "sg:city":"Schelle",
    "sg:orig_category":"Bagage and lederwaren",
    "sg:phone":"+32 3 844 47 04",
    "sg:postcode":"2627",
    "sg:province":"Antwerpen",
    "wof:name":"Ayline",
    "wof:placetype":"venue"
},
  "geometry": {"coordinates":[4.371819973,51.117225647],"type":"Point"}
}