{
  "type": "Feature",
  "properties": {
    "addr:full":"Rue De La Corderie 29 Wavre Brabant Wallon 1300",
    "addr:housenumber":"29;1300",
    "addr:street":"Rue De La Corderie",
    "iso:country":"BE",
    "sg:address":"Rue De La Corderie 29",
    "sg:city":"Wavre",
    "sg:orig_category":"Non-Classified Establishments",
    "sg:phone":"+32 10 24 25 87",
    "sg:postcode":"1300",
    "sg:province":"Brabant Wallon",
    "wof:name":"Active Line Lingerie Sprl",
    "wof:placetype":"venue"
},
  "geometry": {"coordinates":[4.6128401756,50.710319519],"type":"Point"}
}