{
  "type": "Feature",
  "properties": {
    "iso:country":"BE",
    "sg:address":"Kapelstraat 37",
    "sg:city":"Rotselaar",
    "sg:orig_category":"Film-, tv- and videoproductie Informaticaconsulenten",
    "sg:phone":"+32 16 44 68 76",
    "sg:postcode":"3110",
    "sg:province":"Vlaams-Brabant",
    "wof:name":"Laburo",
    "wof:placetype":"venue"
},
  "geometry": {"coordinates":[4.7108821869,50.953918457],"type":"Point"}
}