{
  "type": "Feature",
  "properties": {
    "addr:full":"Chauss\u00e9e De Helmet 65 Bruxelles (schaerbeek) Bruxelles-Capitale 1030",
    "addr:housenumber":"65",
    "addr:postcode":"1030",
    "addr:street":"Chausse\u0301E De Helmet",
    "iso:country":"BE",
    "sg:address":"Chauss\u00e9e De Helmet 65",
    "sg:city":"Bruxelles (schaerbeek)",
    "sg:classifiers":[
        {
            "category":"Bars & Pubs",
            "type":"Food & Drink"
        }
    ],
    "sg:phone":"+32 2 215 65 79",
    "sg:postcode":"1030",
    "sg:province":"Bruxelles-Capitale",
    "wof:name":"Sapeur (au)",
    "wof:placetype":"venue"
},
  "geometry": {"coordinates":[4.3818211555,50.8701515198],"type":"Point"}
}