{
  "type": "Feature",
  "properties": {
    "addr:full":"Rue L\u00c9on Save 48 Mons Hainaut 7000",
    "addr:housenumber":"48",
    "addr:postcode":"7000",
    "addr:street":"Rue Le\u0301On Save;Hainaut",
    "iso:country":"BE",
    "sg:address":"Rue L\u00c9on Save 48",
    "sg:city":"Mons",
    "sg:classifiers":[
        {
            "category":"Restaurant",
            "type":"Food & Drink"
        }
    ],
    "sg:phone":"+32 65 36 01 77",
    "sg:postcode":"7000",
    "sg:province":"Hainaut",
    "wof:name":"Taverne Restaurant Le Vieux Puits",
    "wof:placetype":"venue"
},
  "geometry": {"coordinates":[3.971339941,50.4477310181],"type":"Point"}
}