{
  "type": "Feature",
  "properties": {
    "addr:full":"Rue Fr\u00c8re Michel 21 Liege Li\u00e8ge 4000",
    "addr:housenumber":"21",
    "addr:postcode":"4000",
    "addr:street":"Rue Fre\u0300Re Michel",
    "iso:country":"BE",
    "sg:address":"Rue Fr\u00c8re Michel 21",
    "sg:city":"Liege",
    "sg:classifiers":[
        {
            "category":"Restaurant",
            "type":"Food & Drink"
        }
    ],
    "sg:phone":"+32 475 73 36 85",
    "sg:postcode":"4000",
    "sg:province":"Li\u00e8ge",
    "wof:name":"Le Numidie",
    "wof:placetype":"venue"
},
  "geometry": {"coordinates":[5.5645909309,50.6403541565],"type":"Point"}
}