{
  "type": "Feature",
  "properties": {
    "iso:country":"BE",
    "sg:address":"Benaetsstraat 9a",
    "sg:city":"Borgloon (voort)",
    "sg:classifiers":[
        {
            "category":"Personal",
            "subcategory":"Beauty Salon",
            "type":"Services"
        }
    ],
    "sg:phone":"+32 12 74 69 74",
    "sg:postcode":"3840",
    "sg:province":"Limburg",
    "sg:tags":[
        "lady",
        "-",
        "hairdressing"
    ],
    "wof:name":"Patrice",
    "wof:placetype":"venue"
},
  "geometry": {"coordinates":[5.3196520805,50.79429245],"type":"Point"}
}