{
  "type": "Feature",
  "properties": {
    "addr:full":"Sloordelle 47 Oudergem/auderghem Bruxelles-Capitale 1160",
    "addr:housenumber":"47",
    "addr:postcode":"1160",
    "addr:street":"Sloordelle;/",
    "iso:country":"BE",
    "sg:address":"Sloordelle 47",
    "sg:city":"Oudergem/auderghem",
    "sg:orig_category":"Artsen and specialisten",
    "sg:phone":"+32 2 672 70 74",
    "sg:postcode":"1160",
    "sg:province":"Bruxelles-Capitale",
    "wof:name":"Jean Thiry",
    "wof:placetype":"venue"
},
  "geometry": {"coordinates":[4.4131989479,50.8186836243],"type":"Point"}
}