{
  "type": "Feature",
  "properties": {
    "iso:country":"BE",
    "sg:address":"Rue Grande 77",
    "sg:city":"Saint-ghislain",
    "sg:orig_category":"Parfumeries",
    "sg:phone":"+32 65 78 79 87",
    "sg:postcode":"7330",
    "sg:province":"Hainaut",
    "wof:name":"Gallea Parfumerie",
    "wof:placetype":"venue"
},
  "geometry": {"coordinates":[3.820827961,50.4446754456],"type":"Point"}
}