{
  "type": "Feature",
  "properties": {
    "iso:country":"BE",
    "sg:address":"Route De Rixensart 18",
    "sg:city":"Limal",
    "sg:classifiers":[
        {
            "category":"Retail",
            "subcategory":"Laundry & Dry Cleaning",
            "type":"Services"
        }
    ],
    "sg:phone":"+32 10 43 51 70",
    "sg:postcode":"1300",
    "sg:province":"Brabant Wallon",
    "sg:tags":[
        "fleece"
    ],
    "wof:name":"Ahlstrom Fibercomposites",
    "wof:placetype":"venue"
},
  "geometry": {"coordinates":[4.5556750298,50.7071533203],"type":"Point"}
}