{
  "type": "Feature",
  "properties": {
    "iso:country":"BE",
    "sg:address":"Beversebaan 40",
    "sg:city":"Zwijndrecht",
    "sg:classifiers":[
        {
            "category":"Professional",
            "subcategory":"Management & Consulting",
            "type":"Services"
        }
    ],
    "sg:phone":"+32 3 252 72 18",
    "sg:postcode":"2070",
    "sg:province":"Antwerpen",
    "sg:tags":[
        "consultant"
    ],
    "wof:name":"Peabean Bvba",
    "wof:placetype":"venue"
},
  "geometry": {"coordinates":[4.312912941,51.2190971375],"type":"Point"}
}