{
  "type": "Feature",
  "properties": {
    "addr:full":"Kloosterweg 16 Oud-heverlee (blanden) Vlaams-Brabant 3052",
    "addr:housenumber":"16",
    "addr:postcode":"3052",
    "addr:street":"Kloosterweg",
    "iso:country":"BE",
    "sg:address":"Kloosterweg 16",
    "sg:city":"Oud-heverlee (blanden)",
    "sg:classifiers":[
        {
            "category":"Professional",
            "subcategory":"Management & Consulting",
            "type":"Services"
        }
    ],
    "sg:phone":"+32 16 40 82 63",
    "sg:postcode":"3052",
    "sg:province":"Vlaams-Brabant",
    "sg:tags":[
        "consultant",
        "law"
    ],
    "wof:name":"Thales Advisory Services",
    "wof:placetype":"venue"
},
  "geometry": {"coordinates":[4.6976389885,50.8319168091],"type":"Point"}
}