{
  "type": "Feature",
  "properties": {
    "addr:full":"Waverse Steenweg 1655 Oudergem/auderghem Bruxelles-Capitale 1160",
    "addr:postcode":"1655;1160",
    "addr:street":"Waverse Steenweg",
    "iso:country":"BE",
    "sg:address":"Waverse Steenweg 1655",
    "sg:city":"Oudergem/auderghem",
    "sg:orig_category":"Sportclubs",
    "sg:phone":"+32 2 673 68 86",
    "sg:postcode":"1160",
    "sg:province":"Bruxelles-Capitale",
    "wof:name":"P.c. St.anne",
    "wof:placetype":"venue"
},
  "geometry": {"coordinates":[4.4227819443,50.8170166016],"type":"Point"}
}