{
  "type": "Feature",
  "properties": {
    "addr:full":"Sint-stevensstraat 11 Sint-pieters-leeuw Vlaams-Brabant 1600",
    "addr:housenumber":"11",
    "addr:postcode":"1600",
    "addr:street":"Sint-Stevensstraat",
    "iso:country":"BE",
    "sg:address":"Sint-stevensstraat 11",
    "sg:city":"Sint-pieters-leeuw",
    "sg:classifiers":[
        {
            "category":"Health Services",
            "subcategory":"Health Practitioner",
            "type":"Services"
        }
    ],
    "sg:phone":"+32 2 378 21 16",
    "sg:postcode":"1600",
    "sg:province":"Vlaams-Brabant",
    "sg:tags":[
        "physiotherapist"
    ],
    "wof:name":"Vermet Luc",
    "wof:placetype":"venue"
},
  "geometry": {"coordinates":[4.2879991531,50.8049278259],"type":"Point"}
}