{
  "type": "Feature",
  "properties": {
    "iso:country":"BE",
    "sg:address":"Stationsstraat 6",
    "sg:city":"Zoutleeuw",
    "sg:orig_category":"Maatschappelijke dienstverlening",
    "sg:phone":"+32 11 78 09 62",
    "sg:postcode":"3440",
    "sg:province":"Vlaams-Brabant",
    "wof:name":"Rode Kruis Zoutleeuw-linter",
    "wof:placetype":"venue"
},
  "geometry": {"coordinates":[5.104347229,50.8319206238],"type":"Point"}
}