{
  "type": "Feature",
  "properties": {
    "addr:full":"Dokter Haubenlaan 3 Box 38 Maasmechelen Limburg 3630",
    "addr:housenumber":"3 box 38",
    "addr:postcode":"3630",
    "addr:street":"Dokter Haubenlaan",
    "iso:country":"BE",
    "sg:address":"Dokter Haubenlaan 3 Box 38",
    "sg:city":"Maasmechelen",
    "sg:classifiers":[
        {
            "category":"Home & Garden",
            "subcategory":"Carpets & Floor Coverings",
            "type":"Retail Goods"
        }
    ],
    "sg:phone":"+32 475 45 63 59",
    "sg:postcode":"3630",
    "sg:province":"Limburg",
    "sg:tags":[
        "industrial",
        "-"
    ],
    "wof:name":"D.d.s. Steentapijt",
    "wof:placetype":"venue"
},
  "geometry": {"coordinates":[5.6961631775,50.9640045166],"type":"Point"}
}