{
  "type": "Feature",
  "properties": {
    "iso:country":"BE",
    "sg:address":"Rue Des Trieux 124",
    "sg:city":"Binche",
    "sg:orig_category":"Kinderopvang",
    "sg:phone":"+32 64 34 16 04",
    "sg:postcode":"7134",
    "sg:province":"Hainaut",
    "wof:name":"Chez Snoopy",
    "wof:placetype":"venue"
},
  "geometry": {"coordinates":[4.2285327911,50.4170074463],"type":"Point"}
}