{
  "type": "Feature",
  "properties": {
    "addr:full":"Blauwepoortstraat 61 Ieper (zillebeke) West-Vlaanderen 8902",
    "addr:housenumber":"61",
    "addr:postcode":"8902",
    "addr:street":"Blauwepoortstraat",
    "iso:country":"BE",
    "sg:address":"Blauwepoortstraat 61",
    "sg:city":"Ieper (zillebeke)",
    "sg:classifiers":[
        {
            "category":"Personal",
            "subcategory":"Beauty Salon",
            "type":"Services"
        }
    ],
    "sg:phone":"+32 57 20 16 63",
    "sg:postcode":"8902",
    "sg:province":"West-Vlaanderen",
    "sg:tags":[
        "lady",
        "-",
        "hairdressing"
    ],
    "wof:name":"Kapsalon Anje",
    "wof:placetype":"venue"
},
  "geometry": {"coordinates":[2.9194691181,50.8330841064],"type":"Point"}
}