{
  "type": "Feature",
  "properties": {
    "iso:country":"BE",
    "sg:address":"Rue Des Grands Pr\u00c9s 331",
    "sg:city":"Li\u00c8ge",
    "sg:orig_category":"Kapsalons",
    "sg:phone":"+32 4 365 38 80",
    "sg:postcode":"4032",
    "sg:province":"Li\u00e8ge",
    "wof:name":"Coiffure Univ\u00b4hair",
    "wof:placetype":"venue"
},
  "geometry": {"coordinates":[5.6248002052,50.6046409607],"type":"Point"}
}