{
  "type": "Feature",
  "properties": {
    "iso:country":"BE",
    "sg:address":"Bonekruidstraat 1",
    "sg:city":"Zemst",
    "sg:classifiers":[
        {
            "category":"Personal",
            "subcategory":"Beauty Salon",
            "type":"Services"
        }
    ],
    "sg:phone":"+32 15 62 03 46",
    "sg:postcode":"1982",
    "sg:province":"Vlaams-Brabant",
    "sg:tags":[
        "de",
        "coiffure"
    ],
    "wof:name":"Patricia Buelens",
    "wof:placetype":"venue"
},
  "geometry": {"coordinates":[4.5072197914,50.9662857056],"type":"Point"}
}