{
  "type": "Feature",
  "properties": {
    "addr:full":"Bagattenstraat 39ba Gent Oost-Vlaanderen 9000",
    "addr:housenumber":"39ba",
    "addr:postcode":"9000",
    "addr:street":"Bagattenstraat;Oost-Vlaanderen",
    "iso:country":"BE",
    "sg:address":"Bagattenstraat 39ba",
    "sg:city":"Gent",
    "sg:orig_category":"Artistes ind\u00e9pendants",
    "sg:phone":"+32 9 224 11 42",
    "sg:postcode":"9000",
    "sg:province":"Oost-Vlaanderen",
    "wof:name":"Twiggy Bossuyt",
    "wof:placetype":"venue"
},
  "geometry": {"coordinates":[3.7226409912,51.047580719],"type":"Point"}
}