{
  "type": "Feature",
  "properties": {
    "iso:country":"BE",
    "sg:address":"Mellinetplein 8",
    "sg:city":"Antwerpen",
    "sg:orig_category":"Avocats and conseillers juridiques",
    "sg:phone":"+32 3 239 89 70",
    "sg:postcode":"2600",
    "sg:province":"Antwerpen",
    "wof:name":"Mieke Van Baden",
    "wof:placetype":"venue"
},
  "geometry": {"coordinates":[4.4174151421,51.1974411011],"type":"Point"}
}