{
  "type": "Feature",
  "properties": {
    "addr:full":"Avenue Beau-s\u00c9jour 54 Ukkel/uccle Bruxelles-Capitale 1180",
    "addr:housenumber":"54",
    "addr:postcode":"1180",
    "addr:street":"Avenue Beau-Se\u0301Jour;/",
    "iso:country":"BE",
    "sg:address":"Avenue Beau-s\u00c9jour 54",
    "sg:city":"Ukkel/uccle",
    "sg:orig_category":"R\u00e9alisation de programmes and logiciels. Banques de donn\u00e9es",
    "sg:phone":"+32 2 375 63 07",
    "sg:postcode":"1180",
    "sg:province":"Bruxelles-Capitale",
    "wof:name":"Bureau Biolley",
    "wof:placetype":"venue"
},
  "geometry": {"coordinates":[4.3672652245,50.8084716797],"type":"Point"}
}