{
  "type": "Feature",
  "properties": {
    "iso:country":"BE",
    "sg:address":"Steenweg Op Sevendonk 55",
    "sg:city":"Oud-turnhout",
    "sg:orig_category":"Entretien and r\u00e9parations de voitures",
    "sg:phone":"+32 14 45 39 19",
    "sg:postcode":"2360",
    "sg:province":"Antwerpen",
    "wof:name":"Carrosserie Huybrechts",
    "wof:placetype":"venue"
},
  "geometry": {"coordinates":[4.9801278114,51.3145103455],"type":"Point"}
}