{
  "type": "Feature",
  "properties": {
    "addr:full":"Kapelweg 1ba Hoogstraten Antwerpen 2328",
    "addr:housenumber":"1ba",
    "addr:postcode":"2328",
    "addr:street":"Kapelweg",
    "iso:country":"BE",
    "sg:address":"Kapelweg 1ba",
    "sg:city":"Hoogstraten",
    "sg:orig_category":"Sportterreinen and installaties behalve sportcentra",
    "sg:phone":"+32 3 315 40 41",
    "sg:postcode":"2328",
    "sg:province":"Antwerpen",
    "wof:name":"Merli Flair Ranch",
    "wof:placetype":"venue"
},
  "geometry": {"coordinates":[4.7693929672,51.490978241],"type":"Point"}
}