{
  "type": "Feature",
  "properties": {
    "addr:full":"Villalaan 17 Aalst (erembodegem) Oost-Vlaanderen 9320",
    "addr:housenumber":"17",
    "addr:postcode":"9320",
    "addr:street":"Villalaan",
    "iso:country":"BE",
    "sg:address":"Villalaan 17",
    "sg:city":"Aalst (erembodegem)",
    "sg:classifiers":[
        {
            "category":"Health Services",
            "subcategory":"Health Practitioner",
            "type":"Services"
        }
    ],
    "sg:phone":"+32 53 78 47 30",
    "sg:postcode":"9320",
    "sg:province":"Oost-Vlaanderen",
    "sg:tags":[
        "physiotherapist"
    ],
    "wof:name":"Herwege Jaak",
    "wof:placetype":"venue"
},
  "geometry": {"coordinates":[4.0553851128,50.9209976196],"type":"Point"}
}