{
  "type": "Feature",
  "properties": {
    "iso:country":"BE",
    "sg:address":"Gruuthusestraat 8",
    "sg:city":"Tielt",
    "sg:classifiers":[
        {
            "category":"Banks & Credit Unions",
            "subcategory":"Investment Brokerage",
            "type":"Services"
        }
    ],
    "sg:phone":"+32 51 40 00 36",
    "sg:postcode":"8700",
    "sg:province":"West-Vlaanderen",
    "sg:tags":[
        "fence"
    ],
    "wof:name":"Rosseel Metalen Nv",
    "wof:placetype":"venue"
},
  "geometry": {"coordinates":[3.3320980072,50.990650177],"type":"Point"}
}