{
  "type": "Feature",
  "properties": {
    "addr:full":"Grand Rue 83 Mons Hainaut 7000",
    "addr:housenumber":"83",
    "addr:postcode":"7000",
    "addr:street":"Grand Rue;Hainaut",
    "iso:country":"BE",
    "sg:address":"Grand Rue 83",
    "sg:city":"Mons",
    "sg:classifiers":[
        {
            "category":"Bars & Pubs",
            "type":"Food & Drink"
        }
    ],
    "sg:phone":"+32 65 31 98 61",
    "sg:postcode":"7000",
    "sg:province":"Hainaut",
    "wof:name":"Appero (l')",
    "wof:placetype":"venue"
},
  "geometry": {"coordinates":[3.9496469498,50.4500160217],"type":"Point"}
}