{
  "type": "Feature",
  "properties": {
    "addr:full":"Molenstr 3 Herzele Oost-Vlaanderen 9550",
    "addr:housenumber":"3",
    "addr:postcode":"9550",
    "addr:street":"Molenstr;Oost-Vlaanderen",
    "iso:country":"BE",
    "sg:address":"Molenstr 3",
    "sg:city":"Herzele",
    "sg:classifiers":[
        {
            "category":"Banks & Credit Unions",
            "subcategory":"Bank",
            "type":"Services"
        }
    ],
    "sg:phone":"+32 53 62 20 63",
    "sg:postcode":"9550",
    "sg:province":"Oost-Vlaanderen",
    "wof:name":"Caisse Nationale De, Cr\u00e9dit Professionnel",
    "wof:placetype":"venue"
},
  "geometry": {"coordinates":[3.8947460651,50.8841094971],"type":"Point"}
}