{
  "type": "Feature",
  "properties": {
    "iso:country":"BE",
    "sg:address":"Roomstraat 40",
    "sg:city":"Lokeren",
    "sg:orig_category":"Avocats and conseillers juridiques",
    "sg:phone":"+32 9 348 58 54",
    "sg:postcode":"9160",
    "sg:province":"Oost-Vlaanderen",
    "wof:name":"Anne-marie Laureys",
    "wof:placetype":"venue"
},
  "geometry": {"coordinates":[3.9880390167,51.1031494141],"type":"Point"}
}