{
  "type": "Feature",
  "properties": {
    "addr:full":"Johannes Schrantstraat 1 Gent Oost-Vlaanderen 9000",
    "addr:housenumber":"1",
    "addr:postcode":"9000",
    "addr:street":"Schrantstraat;Oost-Vlaanderen",
    "iso:country":"BE",
    "sg:address":"Johannes Schrantstraat 1",
    "sg:city":"Gent",
    "sg:classifiers":[
        {
            "category":"Health Services",
            "subcategory":"Health Practitioner",
            "type":"Services"
        }
    ],
    "sg:phone":"+32 9 227 72 34",
    "sg:postcode":"9000",
    "sg:province":"Oost-Vlaanderen",
    "sg:tags":[
        "physiotherapist"
    ],
    "wof:name":"Prov\u00e9 J",
    "wof:placetype":"venue"
},
  "geometry": {"coordinates":[3.7015600204,51.0539970398],"type":"Point"}
}