{
  "type": "Feature",
  "properties": {
    "iso:country":"BE",
    "sg:address":"Rue D'angleur 62",
    "sg:city":"Angleur",
    "sg:classifiers":[
        {
            "category":"Home & Garden",
            "subcategory":"Furniture",
            "type":"Retail Goods"
        }
    ],
    "sg:phone":"+32 4 343 83 01",
    "sg:postcode":"4031",
    "sg:province":"Li\u00e8ge",
    "sg:tags":[
        "designer"
    ],
    "wof:name":"Le Beau Meuble Liegeois S.c.r.l.",
    "wof:placetype":"venue"
},
  "geometry": {"coordinates":[5.5821800232,50.6138381958],"type":"Point"}
}