{
  "type": "Feature",
  "properties": {
    "addr:full":"Avenue Du Centenaire 40 Nivelles Brabant Wallon 1400",
    "addr:housenumber":"40",
    "addr:postcode":"1400",
    "addr:street":"Avenue Du Centenaire",
    "iso:country":"BE",
    "sg:address":"Avenue Du Centenaire 40",
    "sg:city":"Nivelles",
    "sg:orig_category":"Quincailleries",
    "sg:phone":"+32 67 84 14 20",
    "sg:postcode":"1400",
    "sg:province":"Brabant Wallon",
    "wof:name":"Brico",
    "wof:placetype":"venue"
},
  "geometry": {"coordinates":[4.3357648849,50.5945549011],"type":"Point"}
}