{
  "type": "Feature",
  "properties": {
    "iso:country":"BE",
    "sg:address":"Rue Crimont 8",
    "sg:city":"Ellezelles",
    "sg:classifiers":[
        {
            "category":"Arts & Performance",
            "subcategory":"Art Gallery",
            "type":"Entertainment"
        }
    ],
    "sg:phone":"+32 68 54 21 94",
    "sg:postcode":"7890",
    "sg:province":"Hainaut",
    "wof:name":"Clos Louis Charles",
    "wof:placetype":"venue"
},
  "geometry": {"coordinates":[3.6666529179,50.7345657349],"type":"Point"}
}