{
  "type": "Feature",
  "properties": {
    "addr:full":"Rue Des Grands Sarts 43 Pont-a-celles Hainaut 6230",
    "addr:housenumber":"43",
    "addr:postcode":"6230",
    "addr:street":"Rue Des Grands Sarts",
    "iso:country":"BE",
    "sg:address":"Rue Des Grands Sarts 43",
    "sg:city":"Pont-a-celles",
    "sg:orig_category":"Pleisterwerk",
    "sg:phone":"+32 71 37 62 20",
    "sg:postcode":"6230",
    "sg:province":"Hainaut",
    "wof:name":"Pierre Cornelis",
    "wof:placetype":"venue"
},
  "geometry": {"coordinates":[4.4030189514,50.4792175293],"type":"Point"}
}