{
  "type": "Feature",
  "properties": {
    "iso:country":"BE",
    "sg:address":"Langerbruggestraat 70",
    "sg:city":"Gent",
    "sg:orig_category":"Installation de menuiserie en bois and plastique",
    "sg:phone":"+32 9 259 11 11",
    "sg:postcode":"9000",
    "sg:province":"Oost-Vlaanderen",
    "wof:name":"Ingo Lassuyt",
    "wof:placetype":"venue"
},
  "geometry": {"coordinates":[3.7556760311,51.1051521301],"type":"Point"}
}