{
  "type": "Feature",
  "properties": {
    "iso:country":"BE",
    "sg:address":"Kaai 20",
    "sg:city":"Nieuwpoort",
    "sg:orig_category":"Supermarkten",
    "sg:phone":"+32 58 23 42 34",
    "sg:postcode":"8620",
    "sg:province":"West-Vlaanderen",
    "wof:name":"Unic",
    "wof:placetype":"venue"
},
  "geometry": {"coordinates":[2.7514970303,51.1333007812],"type":"Point"}
}