{
  "type": "Feature",
  "properties": {
    "iso:country":"BE",
    "sg:address":"Lochtiens 7",
    "sg:city":"Malle (oostmalle)",
    "sg:classifiers":[
        {
            "category":"Professional",
            "type":"Services"
        }
    ],
    "sg:phone":"+32 3 312 45 54",
    "sg:postcode":"2390",
    "sg:province":"Antwerpen",
    "sg:tags":[
        "industrial",
        "automation"
    ],
    "wof:name":"Verstappen B",
    "wof:placetype":"venue"
},
  "geometry": {"coordinates":[4.7352519035,51.3102684021],"type":"Point"}
}