{
  "type": "Feature",
  "properties": {
    "addr:full":"Jan Frans Willemsstraat 67 Boechout Antwerpen 2530",
    "addr:housenumber":"67",
    "addr:postcode":"2530",
    "addr:street":"Jan Frans Willemsstraat",
    "iso:country":"BE",
    "sg:address":"Jan Frans Willemsstraat 67",
    "sg:city":"Boechout",
    "sg:orig_category":"Diverse bedrijfsbeheeradviesbureaus Plaatsen van vloer- and muurbekleding Schilders",
    "sg:phone":"+32 3 455 05 60",
    "sg:postcode":"2530",
    "sg:province":"Antwerpen",
    "wof:name":"Raco",
    "wof:placetype":"venue"
},
  "geometry": {"coordinates":[4.4955229759,51.1609153748],"type":"Point"}
}