{
  "type": "Feature",
  "properties": {
    "addr:full":"Rue Achille Chavee 46 La Louviere Hainaut 7100",
    "addr:housenumber":"46",
    "addr:postcode":"7100",
    "addr:street":"Rue Achille Chavee",
    "iso:country":"BE",
    "sg:address":"Rue Achille Chavee 46",
    "sg:city":"La Louviere",
    "sg:orig_category":"Woningbouw",
    "sg:phone":"+32 64 26 00 37",
    "sg:postcode":"7100",
    "sg:province":"Hainaut",
    "wof:name":"Antonio Gallo",
    "wof:placetype":"venue"
},
  "geometry": {"coordinates":[4.1918520927,50.4795303345],"type":"Point"}
}