{
  "type": "Feature",
  "properties": {
    "addr:full":"Place Des Martyrs 4 Pont-a-celles Hainaut 6238",
    "addr:housenumber":"4",
    "addr:postcode":"6238",
    "addr:street":"Place Des Martyrs",
    "iso:country":"BE",
    "sg:address":"Place Des Martyrs 4",
    "sg:city":"Pont-a-celles",
    "sg:orig_category":"Huisdieren and benodigdheden",
    "sg:phone":"+32 75932791",
    "sg:postcode":"6238",
    "sg:province":"Hainaut",
    "wof:name":"Animoshop",
    "wof:placetype":"venue"
},
  "geometry": {"coordinates":[4.3931069374,50.5095367432],"type":"Point"}
}