{
  "type": "Feature",
  "properties": {
    "addr:full":"Marktplaats 15 Hooglede West-Vlaanderen 8830",
    "addr:housenumber":"15",
    "addr:postcode":"8830",
    "addr:street":"Marktplaats",
    "iso:country":"BE",
    "sg:address":"Marktplaats 15",
    "sg:city":"Hooglede",
    "sg:orig_category":"Banques and organismes de cr\u00e9dit",
    "sg:phone":"+32 51 20 36 49",
    "sg:postcode":"8830",
    "sg:province":"West-Vlaanderen",
    "wof:name":"Bbl",
    "wof:placetype":"venue"
},
  "geometry": {"coordinates":[3.0826339722,50.978603363],"type":"Point"}
}