{
  "type": "Feature",
  "properties": {
    "iso:country":"BE",
    "sg:address":"Grotesteenweg 101",
    "sg:city":"Geel",
    "sg:classifiers":[
        {
            "category":"Autos & Motor Vehicles",
            "subcategory":"Fuel & Gas Station",
            "type":"Retail Goods"
        }
    ],
    "sg:phone":"+32 14 54 49 65",
    "sg:postcode":"2440",
    "sg:province":"Antwerpen",
    "sg:tags":[
        "stations-service",
        "carburants"
    ],
    "wof:name":"Karel Vansant",
    "wof:placetype":"venue"
},
  "geometry": {"coordinates":[4.9444198608,51.1008110046],"type":"Point"}
}