{
  "type": "Feature",
  "properties": {
    "iso:country":"BE",
    "sg:address":"Mechelsesteenweg 569",
    "sg:city":"Willebroek (blaasveld)",
    "sg:classifiers":[
        {
            "category":"Utilities",
            "subcategory":"Fuel Oil & Lpg",
            "type":"Services"
        }
    ],
    "sg:phone":"+32 3 886 68 97",
    "sg:postcode":"2830",
    "sg:province":"Antwerpen",
    "wof:name":"Goovaerts Brandstoffen Vof",
    "wof:placetype":"venue"
},
  "geometry": {"coordinates":[4.3994212151,51.0470962524],"type":"Point"}
}