{
  "type": "Feature",
  "properties": {
    "addr:full":"Markt 14 Tielt West-Vlaanderen 8700",
    "addr:housenumber":"14",
    "addr:postcode":"8700",
    "addr:street":"Markt",
    "iso:country":"BE",
    "sg:address":"Markt 14",
    "sg:city":"Tielt",
    "sg:orig_category":"Verplichte sociale verzekeringen",
    "sg:phone":"+32 51 40 55 55",
    "sg:postcode":"8700",
    "sg:province":"West-Vlaanderen",
    "wof:name":"Westvl. Liberaal Ziekenf.",
    "wof:placetype":"venue"
},
  "geometry": {"coordinates":[3.3273010254,51.0005455017],"type":"Point"}
}