{
  "type": "Feature",
  "properties": {
    "addr:full":"Werkenstraat 49 Kortemark West-Vlaanderen 8610",
    "addr:housenumber":"49",
    "addr:postcode":"8610",
    "addr:street":"Werkenstraat",
    "iso:country":"BE",
    "sg:address":"Werkenstraat 49",
    "sg:city":"Kortemark",
    "sg:orig_category":"Installatie van houten of kunststof schrijnwerk",
    "sg:phone":"+32 51 56 78 56",
    "sg:postcode":"8610",
    "sg:province":"West-Vlaanderen",
    "wof:name":"Michel Vanacker",
    "wof:placetype":"venue"
},
  "geometry": {"coordinates":[2.9949240685,51.0276298523],"type":"Point"}
}