{
  "type": "Feature",
  "properties": {
    "addr:full":"Rue Du Ruisseau 10 Villers-le-bouillet Li\u00e8ge 4530",
    "addr:housenumber":"10",
    "addr:postcode":"4530",
    "addr:street":"Rue Du Ruisseau",
    "iso:country":"BE",
    "sg:address":"Rue Du Ruisseau 10",
    "sg:city":"Villers-le-bouillet",
    "sg:orig_category":"Loodgieterij, verwarming and sanitaire installaties",
    "sg:phone":"+32 85 23 65 79",
    "sg:postcode":"4530",
    "sg:province":"Li\u00e8ge",
    "wof:name":"Jean-marc Pirlet",
    "wof:placetype":"venue"
},
  "geometry": {"coordinates":[5.2677102089,50.5729904175],"type":"Point"}
}