{
  "type": "Feature",
  "properties": {
    "addr:full":"Andr\u00e9 Demedtslaan 20 Kortrijk (marke) West-Vlaanderen 8510",
    "addr:housenumber":"20",
    "addr:postcode":"8510",
    "addr:street":"Demedtslaan",
    "iso:country":"BE",
    "sg:address":"Andr\u00e9 Demedtslaan 20",
    "sg:city":"Kortrijk (marke)",
    "sg:classifiers":[
        {
            "category":"Professional",
            "subcategory":"Management & Consulting",
            "type":"Services"
        }
    ],
    "sg:phone":"+32 56 21 29 71",
    "sg:postcode":"8510",
    "sg:province":"West-Vlaanderen",
    "sg:tags":[
        "consultant"
    ],
    "wof:name":"Pattyn C",
    "wof:placetype":"venue"
},
  "geometry": {"coordinates":[3.2429831028,50.7855606079],"type":"Point"}
}