{
  "type": "Feature",
  "properties": {
    "addr:full":"Hoekstraat 15 Sint-truiden Limburg 3800",
    "addr:housenumber":"15",
    "addr:postcode":"3800",
    "addr:street":"Hoekstraat",
    "iso:country":"BE",
    "sg:address":"Hoekstraat 15",
    "sg:city":"Sint-truiden",
    "sg:orig_category":"Eleveurs and marchands de porcs",
    "sg:phone":"+32 11 69 10 16",
    "sg:postcode":"3800",
    "sg:province":"Limburg",
    "wof:name":"Jean Hoche",
    "wof:placetype":"venue"
},
  "geometry": {"coordinates":[5.182448864,50.7714653015],"type":"Point"}
}