{
  "type": "Feature",
  "properties": {
    "iso:country":"BE",
    "sg:address":"Lazarijstraat 167",
    "sg:city":"Hasselt",
    "sg:orig_category":"Traitements param\u00e9dicaux",
    "sg:phone":"+32 11 87 28 79",
    "sg:postcode":"3500",
    "sg:province":"Limburg",
    "wof:name":"Anne De Meyer",
    "wof:placetype":"venue"
},
  "geometry": {"coordinates":[5.3328099251,50.9368476868],"type":"Point"}
}