{
  "type": "Feature",
  "properties": {
    "addr:full":"Speelhof 10 Borgloon Limburg 3840",
    "addr:housenumber":"10",
    "addr:postcode":"3840",
    "addr:street":"Speelhof",
    "iso:country":"BE",
    "sg:address":"Speelhof 10",
    "sg:city":"Borgloon",
    "sg:orig_category":"Toeristische diensten",
    "sg:phone":"+32 12 67 36 53",
    "sg:postcode":"3840",
    "sg:province":"Limburg",
    "wof:name":"V.v.v. Borgloon",
    "wof:placetype":"venue"
},
  "geometry": {"coordinates":[5.3442721367,50.8015441895],"type":"Point"}
}