{
  "type": "Feature",
  "properties": {
    "iso:country":"BE",
    "sg:address":"Lange Beulestraat 28",
    "sg:city":"Waasmunster",
    "sg:classifiers":[
        {
            "category":"Professional",
            "subcategory":"Art Services",
            "type":"Services"
        }
    ],
    "sg:phone":"+32 9 349 12 33",
    "sg:postcode":"9250",
    "sg:province":"Oost-Vlaanderen",
    "sg:tags":[
        "design",
        "packing",
        "-",
        "realization"
    ],
    "wof:name":"Van Spittael A",
    "wof:placetype":"venue"
},
  "geometry": {"coordinates":[4.0346851349,51.1252632141],"type":"Point"}
}