{
  "type": "Feature",
  "properties": {
    "addr:full":"L. Georgelaan 10 Brussel Bruxelles-Capitale 1000",
    "addr:housenumber":"10",
    "addr:postcode":"1000",
    "addr:street":"L. Georgelaan",
    "iso:country":"BE",
    "sg:address":"L. Georgelaan 10",
    "sg:city":"Brussel",
    "sg:orig_category":"Diverse bedrijfsbeheeradviesbureaus",
    "sg:phone":"+32 2 646 91 22",
    "sg:postcode":"1000",
    "sg:province":"Bruxelles-Capitale",
    "wof:name":"Ad Corporate Psychology",
    "wof:placetype":"venue"
},
  "geometry": {"coordinates":[4.374423027,50.8152313232],"type":"Point"}
}