{
  "type": "Feature",
  "properties": {
    "iso:country":"BE",
    "sg:address":"Chauss\u00c9e De Gand 1007",
    "sg:city":"Sint-agatha-berchem/berchem-sainte-agathe",
    "sg:classifiers":[
        {
            "category":"Personal",
            "subcategory":"Beauty Salon",
            "type":"Services"
        }
    ],
    "sg:phone":"+32 2 468 09 15",
    "sg:postcode":"1082",
    "sg:province":"Bruxelles-Capitale",
    "sg:tags":[
        "de",
        "coiffure"
    ],
    "wof:name":"Coiffure Ino",
    "wof:placetype":"venue"
},
  "geometry": {"coordinates":[4.3033709526,50.8615112305],"type":"Point"}
}