{
  "type": "Feature",
  "properties": {
    "iso:country":"BE",
    "sg:address":"Struisblokstraat 1",
    "sg:city":"Boutersem (kerkom)",
    "sg:classifiers":[
        {
            "category":"Building & Trades",
            "subcategory":"Landscaping Services",
            "type":"Services"
        }
    ],
    "sg:phone":"+32 16 63 17 38",
    "sg:postcode":"3370",
    "sg:province":"Vlaams-Brabant",
    "sg:tags":[
        "gardening",
        "garden",
        "maintenance"
    ],
    "wof:name":"Rudi's Tuin",
    "wof:placetype":"venue"
},
  "geometry": {"coordinates":[4.8585882187,50.8651237488],"type":"Point"}
}