{
  "type": "Feature",
  "properties": {
    "addr:full":"Rue Des Carreurs 42 Beauraing Namur 5570",
    "addr:housenumber":"42",
    "addr:postcode":"5570",
    "addr:street":"Rue Des Carreurs",
    "iso:country":"BE",
    "sg:address":"Rue Des Carreurs 42",
    "sg:city":"Beauraing",
    "sg:orig_category":"Travail and traitement du bois",
    "sg:phone":"+32 82 71 27 06",
    "sg:postcode":"5570",
    "sg:province":"Namur",
    "wof:name":"Von\u00cache-bois",
    "wof:placetype":"venue"
},
  "geometry": {"coordinates":[4.9845662117,50.0533409119],"type":"Point"}
}