{
  "type": "Feature",
  "properties": {
    "iso:country":"BE",
    "sg:address":"Avenue Des Cerisiers 28",
    "sg:city":"Soignies",
    "sg:classifiers":[
        {
            "category":"Autos & Motor Vehicles",
            "subcategory":"Auto Supplies",
            "type":"Retail Goods"
        }
    ],
    "sg:phone":"+32 67 33 57 88",
    "sg:postcode":"7060",
    "sg:province":"Hainaut",
    "sg:tags":[
        "hydraulics"
    ],
    "wof:name":"Verpolhydrau Sprl",
    "wof:placetype":"venue"
},
  "geometry": {"coordinates":[4.0542731285,50.5879631042],"type":"Point"}
}