{
  "type": "Feature",
  "properties": {
    "iso:country":"BE",
    "sg:address":"Gandastraat 27",
    "sg:city":"Gent",
    "sg:orig_category":"Peinture. Rev\u00eatements de sols and murs. Eclairage et \u00e9quipements du foyer. Rev\u00eatements pour sols and",
    "sg:phone":"+32 9 225 30 39",
    "sg:postcode":"9000",
    "sg:province":"Oost-Vlaanderen",
    "wof:name":"Tomanski-deceuninck",
    "wof:placetype":"venue"
},
  "geometry": {"coordinates":[3.7373919487,51.0537033081],"type":"Point"}
}