{
  "type": "Feature",
  "properties": {
    "addr:full":"Rue De La Marsalle 16a Hannut (merdorp) Li\u00e8ge 4280",
    "addr:housenumber":"16a",
    "addr:postcode":"4280",
    "addr:street":"Rue De La Marsalle",
    "iso:country":"BE",
    "sg:address":"Rue De La Marsalle 16a",
    "sg:city":"Hannut (merdorp)",
    "sg:classifiers":[
        {
            "category":"Farming",
            "subcategory":"Crops",
            "type":"Manufacturing & Wholesale Goods"
        }
    ],
    "sg:phone":"+32 81 85 60 07",
    "sg:postcode":"4280",
    "sg:province":"Li\u00e8ge",
    "sg:tags":[
        "vegetable",
        "fruit",
        "-",
        "grower"
    ],
    "wof:name":"Centre Fruitier Wallon Asbl",
    "wof:placetype":"venue"
},
  "geometry": {"coordinates":[5.002327919,50.6439666748],"type":"Point"}
}