{
  "type": "Feature",
  "properties": {
    "iso:country":"BE",
    "sg:address":"Klapperstraat 134",
    "sg:city":"Beveren",
    "sg:classifiers":[
        {
            "category":"Arena",
            "subcategory":"Sports Club",
            "type":"Entertainment"
        }
    ],
    "sg:phone":"+32 3 775 14 12",
    "sg:postcode":"9120",
    "sg:province":"Oost-Vlaanderen",
    "sg:tags":[
        "de"
    ],
    "wof:name":"De Zuiderbond",
    "wof:placetype":"venue"
},
  "geometry": {"coordinates":[4.2455201149,51.2150001526],"type":"Point"}
}