{
  "type": "Feature",
  "properties": {
    "iso:country":"BE",
    "sg:address":"Beatrijslaan 19",
    "sg:city":"Antwerpen",
    "sg:classifiers":[
        {
            "category":"Arena",
            "subcategory":"Sports Club",
            "type":"Entertainment"
        }
    ],
    "sg:phone":"+32 3 219 68 54",
    "sg:postcode":"2050",
    "sg:province":"Antwerpen",
    "wof:name":"Minigolf Linkeroever",
    "wof:placetype":"venue"
},
  "geometry": {"coordinates":[4.3869819641,51.2194480896],"type":"Point"}
}