{
  "type": "Feature",
  "properties": {
    "addr:full":"Onze-lieve-vrouwlaan 38 Tremelo Vlaams-Brabant 3120",
    "addr:housenumber":"38",
    "addr:postcode":"3120",
    "addr:street":"Onze-Lieve-Vrouwlaan",
    "iso:country":"BE",
    "sg:address":"Onze-lieve-vrouwlaan 38",
    "sg:city":"Tremelo",
    "sg:orig_category":"Experts-comptables",
    "sg:phone":"+32 16 52 03 14",
    "sg:postcode":"3120",
    "sg:province":"Vlaams-Brabant",
    "wof:name":"K. Van Camp",
    "wof:placetype":"venue"
},
  "geometry": {"coordinates":[4.7202978134,50.9974594116],"type":"Point"}
}