{
  "type": "Feature",
  "properties": {
    "addr:full":"Rue De Bruxelles 45 Namur Namur 5000",
    "addr:housenumber":"45",
    "addr:postcode":"5000",
    "addr:street":"Rue De Bruxelles",
    "iso:country":"BE",
    "sg:address":"Rue De Bruxelles 45",
    "sg:city":"Namur",
    "sg:orig_category":"Banques and organismes de cr\u00e9dit",
    "sg:phone":"+32 81 24 33 60",
    "sg:postcode":"5000",
    "sg:province":"Namur",
    "wof:name":"Fortis",
    "wof:placetype":"venue"
},
  "geometry": {"coordinates":[4.8618998528,50.4655342102],"type":"Point"}
}