{
  "type": "Feature",
  "properties": {
    "addr:full":"Bergstrasse 57 Eupen Li\u00e8ge 4700",
    "addr:housenumber":"57",
    "addr:postcode":"4700",
    "addr:street":"Bergstrasse",
    "iso:country":"BE",
    "sg:address":"Bergstrasse 57",
    "sg:city":"Eupen",
    "sg:classifiers":[
        {
            "category":"Shopping",
            "subcategory":"Clothing, Apparel, & Fashions",
            "type":"Retail Goods"
        }
    ],
    "sg:phone":"+32 87 55 29 30",
    "sg:postcode":"4700",
    "sg:province":"Li\u00e8ge",
    "sg:tags":[
        "boutique"
    ],
    "wof:name":"Lady Katharina",
    "wof:placetype":"venue"
},
  "geometry": {"coordinates":[6.0331468582,50.6285400391],"type":"Point"}
}