{
  "type": "Feature",
  "properties": {
    "addr:full":"Rue Stevin 38 Bruxelles Bruxelles-Capitale 1000",
    "addr:housenumber":"38",
    "addr:postcode":"1000",
    "addr:street":"Rue Stevin",
    "iso:country":"BE",
    "sg:address":"Rue Stevin 38",
    "sg:city":"Bruxelles",
    "sg:classifiers":[
        {
            "category":"Professional",
            "subcategory":"Printing & Photocopies",
            "type":"Services"
        }
    ],
    "sg:phone":"+32 2 230 47 04",
    "sg:postcode":"1000",
    "sg:province":"Bruxelles-Capitale",
    "sg:tags":[
        "digital"
    ],
    "wof:name":"Ips Sprl",
    "wof:placetype":"venue"
},
  "geometry": {"coordinates":[4.3768539429,50.8457603455],"type":"Point"}
}