{
  "type": "Feature",
  "properties": {
    "iso:country":"BE",
    "sg:address":"Schomhoeveweg 9",
    "sg:city":"Antwerpen",
    "sg:classifiers":[
        {
            "category":"Freight",
            "type":"Transportation"
        }
    ],
    "sg:phone":"+32 3 542 50 25",
    "sg:postcode":"2030",
    "sg:province":"Antwerpen",
    "sg:tags":[
        "container",
        "-",
        "transport"
    ],
    "wof:name":"Van Loon C & Zn Nv",
    "wof:placetype":"venue"
},
  "geometry": {"coordinates":[4.3956098557,51.2693367004],"type":"Point"}
}