{
  "type": "Feature",
  "properties": {
    "iso:country":"BE",
    "sg:address":"Rue Des Coquelicots 48",
    "sg:city":"Charleroi (goutroux)",
    "sg:classifiers":[
        {
            "category":"Landmark",
            "subcategory":"City Walls",
            "type":"Public Place"
        }
    ],
    "sg:phone":"+32 71 54 54 41",
    "sg:postcode":"6030",
    "sg:province":"Hainaut",
    "sg:tags":[
        "shed",
        "open",
        "hangar"
    ],
    "wof:name":"F.d.g.",
    "wof:placetype":"venue"
},
  "geometry": {"coordinates":[4.3601307869,50.4151496887],"type":"Point"}
}