{
  "type": "Feature",
  "properties": {
    "addr:full":"Grand\u00b4rue 9 Louvain-la-neuve Brabant Wallon 1348",
    "addr:housenumber":"9",
    "addr:postcode":"1348",
    "addr:street":"Grand\u00b4Rue",
    "iso:country":"BE",
    "sg:address":"Grand\u00b4rue 9",
    "sg:city":"Louvain-la-neuve",
    "sg:classifiers":[
        {
            "category":"Restaurant",
            "type":"Food & Drink"
        }
    ],
    "sg:phone":"+32 10 45 13 27",
    "sg:postcode":"1348",
    "sg:province":"Brabant Wallon",
    "wof:name":"Nulle Part Ailleurs",
    "wof:placetype":"venue"
},
  "geometry": {"coordinates":[4.6137161255,50.6692733765],"type":"Point"}
}