{
  "type": "Feature",
  "properties": {
    "iso:country":"BE",
    "sg:address":"Kapellestraat 55",
    "sg:city":"Wevelgem",
    "sg:orig_category":"Installation de menuiserie en bois and plastique",
    "sg:phone":"+32 56 42 12 74",
    "sg:postcode":"8560",
    "sg:province":"West-Vlaanderen",
    "wof:name":"D V Construct",
    "wof:placetype":"venue"
},
  "geometry": {"coordinates":[3.1886260509,50.8143768311],"type":"Point"}
}