{
  "type": "Feature",
  "properties": {
    "addr:full":"Venecoweg 10 Nazareth Oost-Vlaanderen 9810",
    "addr:housenumber":"10",
    "addr:postcode":"9810",
    "addr:street":"Venecoweg",
    "iso:country":"BE",
    "sg:address":"Venecoweg 10",
    "sg:city":"Nazareth",
    "sg:classifiers":[
        {
            "category":"Military Area",
            "subcategory":"Air Force Base",
            "type":"Public Place"
        }
    ],
    "sg:phone":"+32 9 387 00 58",
    "sg:postcode":"9810",
    "sg:province":"Oost-Vlaanderen",
    "sg:tags":[
        "fire",
        "protection"
    ],
    "wof:name":"Pyro-protection Bvba",
    "wof:placetype":"venue"
},
  "geometry": {"coordinates":[3.5542340279,50.953338623],"type":"Point"}
}