{
  "type": "Feature",
  "properties": {
    "iso:country":"BE",
    "sg:address":"Rue Grande 112",
    "sg:city":"Dour",
    "sg:classifiers":[
        {
            "category":"Professional",
            "subcategory":"Art Services",
            "type":"Services"
        }
    ],
    "sg:phone":"+32 65 65 02 14",
    "sg:postcode":"7370",
    "sg:province":"Hainaut",
    "sg:tags":[
        "photographer",
        "-",
        "portrait"
    ],
    "wof:name":"Carre Michele",
    "wof:placetype":"venue"
},
  "geometry": {"coordinates":[3.7825078964,50.4000396729],"type":"Point"}
}