{
  "type": "Feature",
  "properties": {
    "addr:full":"Begijnhofkaai 10 Geraardsbergen Oost-Vlaanderen 9500",
    "addr:housenumber":"10",
    "addr:postcode":"9500",
    "addr:street":"Begijnhofkaai",
    "iso:country":"BE",
    "sg:address":"Begijnhofkaai 10",
    "sg:city":"Geraardsbergen",
    "sg:classifiers":[
        {
            "category":"Education",
            "subcategory":"School",
            "type":"Public Place"
        }
    ],
    "sg:phone":"+32 54 41 31 37",
    "sg:postcode":"9500",
    "sg:province":"Oost-Vlaanderen",
    "sg:tags":[
        "secondary"
    ],
    "wof:name":"Middenschool Geraardsbergen",
    "wof:placetype":"venue"
},
  "geometry": {"coordinates":[3.8787999153,50.7729492188],"type":"Point"}
}