{
  "type": "Feature",
  "properties": {
    "addr:full":"Jules Van Ooststraat 24 Tielt (aarsele) West-Vlaanderen 8700",
    "addr:housenumber":"24",
    "addr:postcode":"8700",
    "addr:street":"Jules Van Ooststraat",
    "iso:country":"BE",
    "sg:address":"Jules Van Ooststraat 24",
    "sg:city":"Tielt (aarsele)",
    "sg:classifiers":[
        {
            "category":"Health Services",
            "subcategory":"Doctor",
            "type":"Services"
        }
    ],
    "sg:phone":"+32 51 63 36 68",
    "sg:postcode":"8700",
    "sg:province":"West-Vlaanderen",
    "sg:tags":[
        "medicinephysicians",
        "surgeon"
    ],
    "wof:name":"Clepkens C",
    "wof:placetype":"venue"
},
  "geometry": {"coordinates":[3.4205429554,50.9984054565],"type":"Point"}
}