{
  "type": "Feature",
  "properties": {
    "addr:full":"Chauss\u00e9e De Li\u00e8ge 96a Amay (ampsin) Li\u00e8ge 4540",
    "addr:housenumber":"96a",
    "addr:postcode":"4540",
    "addr:street":"Chausse\u0301E De Lie\u0300Ge;Ampsin",
    "iso:country":"BE",
    "sg:address":"Chauss\u00e9e De Li\u00e8ge 96a",
    "sg:city":"Amay (ampsin)",
    "sg:classifiers":[
        {
            "category":"Personal",
            "subcategory":"Beauty Salon",
            "type":"Services"
        }
    ],
    "sg:phone":"+32 85 31 59 93",
    "sg:postcode":"4540",
    "sg:province":"Li\u00e8ge",
    "sg:tags":[
        "lady",
        "-",
        "hairdressing"
    ],
    "wof:name":"Christine Coiffure",
    "wof:placetype":"venue"
},
  "geometry": {"coordinates":[5.2987098694,50.5410614014],"type":"Point"}
}