{
  "type": "Feature",
  "properties": {
    "iso:country":"BE",
    "sg:address":"Grendelbaan 18",
    "sg:city":"Diepenbeek",
    "sg:classifiers":[
        {
            "category":"Shopping",
            "subcategory":"Clothing, Apparel, & Fashions",
            "type":"Retail Goods"
        }
    ],
    "sg:phone":"+32 11 35 14 30",
    "sg:postcode":"3590",
    "sg:province":"Limburg",
    "sg:tags":[
        "clothing",
        "-",
        "gentleman"
    ],
    "wof:name":"Carnaby Herenmode",
    "wof:placetype":"venue"
},
  "geometry": {"coordinates":[5.4314398766,50.9052696228],"type":"Point"}
}