{
  "type": "Feature",
  "properties": {
    "iso:country":"BE",
    "sg:address":"Filips De Goedestraat 60",
    "sg:city":"Brussel/bruxelles",
    "sg:orig_category":"Artsen and specialisten",
    "sg:phone":"+32 2 230 97 22",
    "sg:postcode":"1000",
    "sg:province":"Bruxelles-Capitale",
    "wof:name":"Michel Bernard",
    "wof:placetype":"venue"
},
  "geometry": {"coordinates":[4.3766942024,50.8473434448],"type":"Point"}
}