{
  "type": "Feature",
  "properties": {
    "addr:full":"Albertlstrasse 24 Kelmis Li\u00e8ge 4720",
    "addr:housenumber":"24",
    "addr:postcode":"4720",
    "addr:street":"Albertlstrasse",
    "iso:country":"BE",
    "sg:address":"Albertlstrasse 24",
    "sg:city":"Kelmis",
    "sg:classifiers":[
        {
            "category":"Health Services",
            "subcategory":"Dentist",
            "type":"Services"
        }
    ],
    "sg:phone":"+32 87 65 77 09",
    "sg:postcode":"4720",
    "sg:province":"Li\u00e8ge",
    "wof:name":"Maurissen Mathieu",
    "wof:placetype":"venue"
},
  "geometry": {"coordinates":[6.0124998093,50.7170333862],"type":"Point"}
}