{
  "type": "Feature",
  "properties": {
    "addr:full":"Dellestraat 55 Heusden-zolder Limburg 3550",
    "addr:housenumber":"55",
    "addr:postcode":"3550",
    "addr:street":"Dellestraat",
    "iso:country":"BE",
    "sg:address":"Dellestraat 55",
    "sg:city":"Heusden-zolder",
    "sg:classifiers":[
        {
            "category":"Utilities",
            "subcategory":"Water",
            "type":"Services"
        }
    ],
    "sg:phone":"+32 13 53 03 03",
    "sg:postcode":"3550",
    "sg:province":"Limburg",
    "sg:tags":[
        "acid",
        "carbonic"
    ],
    "wof:name":"Acp N.v.-s.a.",
    "wof:placetype":"venue"
},
  "geometry": {"coordinates":[5.2434902191,50.9820556641],"type":"Point"}
}