{
  "type": "Feature",
  "properties": {
    "iso:country":"BE",
    "sg:address":"Nijverheidsstraat 18",
    "sg:city":"Londerzeel",
    "sg:orig_category":"Entretien and r\u00e9parations de voitures. V\u00e9hicules automobiles",
    "sg:phone":"+32 52 30 79 11",
    "sg:postcode":"1840",
    "sg:province":"Vlaams-Brabant",
    "wof:name":"Renault",
    "wof:placetype":"venue"
},
  "geometry": {"coordinates":[4.3241419792,51.0117378235],"type":"Point"}
}