{
  "type": "Feature",
  "properties": {
    "iso:country":"BE",
    "sg:address":"Rue Berkendael 33",
    "sg:city":"Forest",
    "sg:classifiers":[
        {
            "category":"Fast Food",
            "type":"Food & Drink"
        }
    ],
    "sg:phone":"+32 2 343 65 21",
    "sg:postcode":"1190",
    "sg:province":"Bruxelles-Capitale",
    "sg:tags":[
        "d",
        "restaurant",
        "organisation",
        "\u00c0",
        "domicile",
        "catering",
        "emporter",
        "livraison",
        "restaurants"
    ],
    "wof:name":"Le Passe-bouillon",
    "wof:placetype":"venue"
},
  "geometry": {"coordinates":[4.3453578949,50.8183784485],"type":"Point"}
}