{
  "type": "Feature",
  "properties": {
    "addr:full":"Rue Chalais 2 Villers-le-bouillet Li\u00e8ge 4530",
    "addr:housenumber":"2",
    "addr:postcode":"4530",
    "addr:street":"Rue Chalais",
    "iso:country":"BE",
    "sg:address":"Rue Chalais 2",
    "sg:city":"Villers-le-bouillet",
    "sg:orig_category":"Pharmaciens",
    "sg:phone":"+32 4 259 75 25",
    "sg:postcode":"4530",
    "sg:province":"Li\u00e8ge",
    "wof:name":"Pharm. Masereel B. & F.",
    "wof:placetype":"venue"
},
  "geometry": {"coordinates":[5.2829470634,50.5808982849],"type":"Point"}
}