{
  "type": "Feature",
  "properties": {
    "iso:country":"BE",
    "sg:address":"Rue G. Fi\u00c9vet 37",
    "sg:city":"Sombreffe",
    "sg:classifiers":[
        {
            "category":"Arena",
            "subcategory":"Sports Club",
            "type":"Entertainment"
        }
    ],
    "sg:phone":"+32 71 88 96 66",
    "sg:postcode":"5140",
    "sg:province":"Namur",
    "sg:tags":[
        "de"
    ],
    "wof:name":"Athletic Club Des 3 Provinces",
    "wof:placetype":"venue"
},
  "geometry": {"coordinates":[4.6049628258,50.5228118896],"type":"Point"}
}