{
  "type": "Feature",
  "properties": {
    "iso:country":"BE",
    "sg:address":"Rue Joseph War\u00e8gne 76",
    "sg:city":"Namur (flawinne)",
    "sg:classifiers":[
        {
            "category":"Professional",
            "subcategory":"Accounting & Tax Preparation",
            "type":"Services"
        }
    ],
    "sg:phone":"+32 81 74 50 60",
    "sg:postcode":"5020",
    "sg:province":"Namur",
    "sg:tags":[
        "bookkeeper"
    ],
    "wof:name":"Kips J-h",
    "wof:placetype":"venue"
},
  "geometry": {"coordinates":[4.8769698143,50.4837303162],"type":"Point"}
}