{
  "type": "Feature",
  "properties": {
    "addr:full":"Bouwelsesteenweg 146 Nijlen Antwerpen 2560",
    "addr:housenumber":"146",
    "addr:postcode":"2560",
    "addr:street":"Bouwelsesteenweg",
    "iso:country":"BE",
    "sg:address":"Bouwelsesteenweg 146",
    "sg:city":"Nijlen",
    "sg:classifiers":[
        {
            "category":"Bars & Pubs",
            "type":"Food & Drink"
        }
    ],
    "sg:phone":"+32 3 481 78 41",
    "sg:postcode":"2560",
    "sg:province":"Antwerpen",
    "sg:tags":[
        "tavern"
    ],
    "wof:name":"De Paddekote Bvba",
    "wof:placetype":"venue"
},
  "geometry": {"coordinates":[4.6881017685,51.1654472351],"type":"Point"}
}