{
  "type": "Feature",
  "properties": {
    "iso:country":"BE",
    "sg:address":"Avenue Hanlet 48",
    "sg:city":"Verviers (heusy)",
    "sg:classifiers":[
        {
            "category":"Real Estate",
            "subcategory":"Real Estate Services",
            "type":"Services"
        }
    ],
    "sg:phone":"+32 87 22 47 22",
    "sg:postcode":"4802",
    "sg:province":"Li\u00e8ge",
    "sg:tags":[
        "-",
        "abroad"
    ],
    "wof:name":"Thalassa Promotion Sa",
    "wof:placetype":"venue"
},
  "geometry": {"coordinates":[5.8640561104,50.5819892883],"type":"Point"}
}