{
  "type": "Feature",
  "properties": {
    "addr:full":"Place Alphonse Bosch 31 Wavre Brabant Wallon 1300",
    "addr:housenumber":"31;1300",
    "addr:street":"Place Alphonse Bosch",
    "iso:country":"BE",
    "sg:address":"Place Alphonse Bosch 31",
    "sg:city":"Wavre",
    "sg:orig_category":"R\u00e9parations de chaussures and articles en cuir",
    "sg:phone":"+32 10 22 85 56",
    "sg:postcode":"1300",
    "sg:province":"Brabant Wallon",
    "wof:name":"Cordonnerie Du Sablon",
    "wof:placetype":"venue"
},
  "geometry": {"coordinates":[4.6109890938,50.7134513855],"type":"Point"}
}