{
  "type": "Feature",
  "properties": {
    "addr:full":"Provinciestraat 61 Antwerpen Antwerpen 2018",
    "addr:housenumber":"61",
    "addr:postcode":"2018",
    "addr:street":"Provinciestraat",
    "iso:country":"BE",
    "sg:address":"Provinciestraat 61",
    "sg:city":"Antwerpen",
    "sg:orig_category":"Persagentschappen",
    "sg:phone":"+32 3 236 34 41",
    "sg:postcode":"2018",
    "sg:province":"Antwerpen",
    "wof:name":"Jan Hertoghs",
    "wof:placetype":"venue"
},
  "geometry": {"coordinates":[4.4265990257,51.2161712646],"type":"Point"}
}