{
  "type": "Feature",
  "properties": {
    "iso:country":"BE",
    "sg:address":"Kareelstraat 3",
    "sg:city":"Sint-denijs-westrem",
    "sg:orig_category":"Advocaten and juridische adviseurs Balie van Gent",
    "sg:phone":"+32 9 223 90 03",
    "sg:postcode":"9051",
    "sg:province":"Oost-Vlaanderen",
    "wof:name":"Defreyne Geert",
    "wof:placetype":"venue"
},
  "geometry": {"coordinates":[3.6852190495,51.0330352783],"type":"Point"}
}