{
  "type": "Feature",
  "properties": {
    "addr:full":"Guido Gezelleplaats 9 Temse Oost-Vlaanderen 9140",
    "addr:housenumber":"9",
    "addr:postcode":"9140",
    "addr:street":"Guido Gezelleplaats",
    "iso:country":"BE",
    "sg:address":"Guido Gezelleplaats 9",
    "sg:city":"Temse",
    "sg:orig_category":"Herstellingen and onderhoud van auto's Voertuigen",
    "sg:phone":"+32 3 771 52 58",
    "sg:postcode":"9140",
    "sg:province":"Oost-Vlaanderen",
    "wof:name":"Garage Bauwelinck",
    "wof:placetype":"venue"
},
  "geometry": {"coordinates":[4.2201862335,51.1278076172],"type":"Point"}
}