{
  "type": "Feature",
  "properties": {
    "addr:full":"Rue De Nalinnes 112 Charleroi (marcinelle) Hainaut 6001",
    "addr:housenumber":"112",
    "addr:postcode":"6001",
    "addr:street":"Rue De Nalinnes",
    "iso:country":"BE",
    "sg:address":"Rue De Nalinnes 112",
    "sg:city":"Charleroi (marcinelle)",
    "sg:classifiers":[
        {
            "category":"Health Services",
            "subcategory":"Doctor",
            "type":"Services"
        }
    ],
    "sg:phone":"+32 71 43 11 66",
    "sg:postcode":"6001",
    "sg:province":"Hainaut",
    "sg:tags":[
        "medicinephysicians",
        "surgeon"
    ],
    "wof:name":"Jennart Laurence",
    "wof:placetype":"venue"
},
  "geometry": {"coordinates":[4.4448251724,50.3973655701],"type":"Point"}
}