{
  "type": "Feature",
  "properties": {
    "iso:country":"BE",
    "sg:address":"Lageweg 146",
    "sg:city":"Menen",
    "sg:orig_category":"Installation de menuiserie en bois and plastique",
    "sg:phone":"+32 56 51 92 38",
    "sg:postcode":"8930",
    "sg:province":"West-Vlaanderen",
    "wof:name":"Christian Maes",
    "wof:placetype":"venue"
},
  "geometry": {"coordinates":[3.0996689796,50.7914619446],"type":"Point"}
}