{
  "type": "Feature",
  "properties": {
    "iso:country":"BE",
    "sg:address":"Graffendonk 56",
    "sg:city":"Zoersel",
    "sg:classifiers":[
        {
            "category":"Professional",
            "subcategory":"Management & Consulting",
            "type":"Services"
        }
    ],
    "sg:phone":"+32 3 312 29 70",
    "sg:postcode":"2980",
    "sg:province":"Antwerpen",
    "sg:tags":[
        "marketing",
        "-",
        "consultant"
    ],
    "wof:name":"B S C Consulting",
    "wof:placetype":"venue"
},
  "geometry": {"coordinates":[4.7212820053,51.2640914917],"type":"Point"}
}