{
  "type": "Feature",
  "properties": {
    "addr:full":"Kerkplein 47 Lubbeek (pellenberg) Vlaams-Brabant 3212",
    "addr:housenumber":"47",
    "addr:postcode":"3212",
    "addr:street":"Kerkplein",
    "iso:country":"BE",
    "sg:address":"Kerkplein 47",
    "sg:city":"Lubbeek (pellenberg)",
    "sg:classifiers":[
        {
            "category":"Real Estate",
            "subcategory":"Architect",
            "type":"Services"
        }
    ],
    "sg:phone":"+32 16 46 13 69",
    "sg:postcode":"3212",
    "sg:province":"Vlaams-Brabant",
    "wof:name":"Kint Peter Interprofessionele Architektenvennootschap",
    "wof:placetype":"venue"
},
  "geometry": {"coordinates":[4.7960591316,50.8701171875],"type":"Point"}
}