{
  "type": "Feature",
  "properties": {
    "addr:full":"Beerstraat 26 Meerhout Antwerpen 2450",
    "addr:housenumber":"26",
    "addr:postcode":"2450",
    "addr:street":"Beerstraat",
    "iso:country":"BE",
    "sg:address":"Beerstraat 26",
    "sg:city":"Meerhout",
    "sg:classifiers":[
        {
            "category":"Banks & Credit Unions",
            "subcategory":"Investment Brokerage",
            "type":"Services"
        }
    ],
    "sg:phone":"+32 14 30 03 53",
    "sg:postcode":"2450",
    "sg:province":"Antwerpen",
    "sg:tags":[
        "printing",
        "-"
    ],
    "wof:name":"Van Genechten Drukservice Nv",
    "wof:placetype":"venue"
},
  "geometry": {"coordinates":[5.0766830444,51.1316184998],"type":"Point"}
}