{
  "type": "Feature",
  "properties": {
    "iso:country":"BE",
    "sg:address":"Kleinhoefstraat 4",
    "sg:city":"Geel",
    "sg:classifiers":[
        {
            "category":"Education",
            "subcategory":"University",
            "type":"Public Place"
        }
    ],
    "sg:phone":"+32 14 56 23 08",
    "sg:postcode":"2440",
    "sg:province":"Antwerpen",
    "sg:tags":[
        "higher"
    ],
    "wof:name":"Kath Hogeschool Kempen (geel)",
    "wof:placetype":"venue"
},
  "geometry": {"coordinates":[4.9644079208,51.1615142822],"type":"Point"}
}