{
  "type": "Feature",
  "properties": {
    "addr:full":"Hompelstraat 37b1 Aarschot Vlaams-Brabant 3202",
    "addr:housenumber":"37b1",
    "addr:postcode":"3202",
    "addr:street":"Hompelstraat",
    "iso:country":"BE",
    "sg:address":"Hompelstraat 37b1",
    "sg:city":"Aarschot",
    "sg:orig_category":"Installation \u00e9lectrique r\u00e9sidentielle. Installation \u00e9lectrique industrielle",
    "sg:phone":"+32 16 50 22 81",
    "sg:postcode":"3202",
    "sg:province":"Vlaams-Brabant",
    "wof:name":"Blockx Jean-marc",
    "wof:placetype":"venue"
},
  "geometry": {"coordinates":[4.9035220146,50.9898262024],"type":"Point"}
}