{
  "type": "Feature",
  "properties": {
    "addr:full":"Ch. Garenne D'audenarde 4 Ath Hainaut 7802",
    "addr:housenumber":"4",
    "addr:postcode":"7802",
    "addr:street":"Ch. Garenne D'Audenarde",
    "iso:country":"BE",
    "sg:address":"Ch. Garenne D'audenarde 4",
    "sg:city":"Ath",
    "sg:orig_category":"Rundveehouders",
    "sg:phone":"+32 69 68 88 91",
    "sg:postcode":"7802",
    "sg:province":"Hainaut",
    "wof:name":"Carlier Tonniau",
    "wof:placetype":"venue"
},
  "geometry": {"coordinates":[3.7300400734,50.5825386047],"type":"Point"}
}