{
  "type": "Feature",
  "properties": {
    "iso:country":"BE",
    "sg:address":"Rue Du Brul\u00e9 45",
    "sg:city":"Jemeppe-sur-sambre",
    "sg:classifiers":[
        {
            "category":"Health Services",
            "subcategory":"Health Practitioner",
            "type":"Services"
        }
    ],
    "sg:phone":"+32 71 78 58 94",
    "sg:postcode":"5190",
    "sg:province":"Namur",
    "sg:tags":[
        "physiotherapist"
    ],
    "wof:name":"Simon Fran\u00e7ois",
    "wof:placetype":"venue"
},
  "geometry": {"coordinates":[4.6571288109,50.4521713257],"type":"Point"}
}