{
  "type": "Feature",
  "properties": {
    "iso:country":"BE",
    "sg:address":"De Burburestraat 16",
    "sg:city":"Antwerpen",
    "sg:classifiers":[
        {
            "category":"Real Estate",
            "subcategory":"Architect",
            "type":"Services"
        }
    ],
    "sg:phone":"+32 3 238 36 33",
    "sg:postcode":"2000",
    "sg:province":"Antwerpen",
    "wof:name":"Bulcke B",
    "wof:placetype":"venue"
},
  "geometry": {"coordinates":[4.3915038109,51.2090759277],"type":"Point"}
}