{
  "type": "Feature",
  "properties": {
    "addr:full":"Rietenstraat 9 Meeuwen-gruitrode Limburg 3670",
    "addr:housenumber":"9",
    "addr:postcode":"3670",
    "addr:street":"Rietenstraat",
    "iso:country":"BE",
    "sg:address":"Rietenstraat 9",
    "sg:city":"Meeuwen-gruitrode",
    "sg:orig_category":"Pleisterwerk",
    "sg:phone":"+32 89 47 18 35",
    "sg:postcode":"3670",
    "sg:province":"Limburg",
    "wof:name":"Fa. Baeten-schroyen",
    "wof:placetype":"venue"
},
  "geometry": {"coordinates":[5.5507259369,51.0972557068],"type":"Point"}
}