{
  "type": "Feature",
  "properties": {
    "addr:full":"Waalbeekstraat 24 Zulte Oost-Vlaanderen 9870",
    "addr:housenumber":"24",
    "addr:postcode":"9870",
    "addr:street":"Waalbeekstraat",
    "iso:country":"BE",
    "sg:address":"Waalbeekstraat 24",
    "sg:city":"Zulte",
    "sg:orig_category":"Eclairage et \u00e9quipements du foyer",
    "sg:phone":"+32 9 388 73 22",
    "sg:postcode":"9870",
    "sg:province":"Oost-Vlaanderen",
    "wof:name":"William Standaert",
    "wof:placetype":"venue"
},
  "geometry": {"coordinates":[3.4636099339,50.9199333191],"type":"Point"}
}