{
  "type": "Feature",
  "properties": {
    "addr:full":"Mulkensstraat 50 Overpelt Limburg 3900",
    "addr:housenumber":"50",
    "addr:postcode":"3900",
    "addr:street":"Mulkensstraat",
    "iso:country":"BE",
    "sg:address":"Mulkensstraat 50",
    "sg:city":"Overpelt",
    "sg:orig_category":"Eleveurs de bovins",
    "sg:phone":"+32 11 64 78 82",
    "sg:postcode":"3900",
    "sg:province":"Limburg",
    "wof:name":"Theo Weckx",
    "wof:placetype":"venue"
},
  "geometry": {"coordinates":[5.4130411148,51.2167625427],"type":"Point"}
}