{
  "type": "Feature",
  "properties": {
    "iso:country":"BE",
    "sg:address":"Rue De Wellin 55-57",
    "sg:city":"Beauraing (pondr\u00f4me)",
    "sg:classifiers":[
        {
            "category":"Health Services",
            "subcategory":"Doctor",
            "type":"Services"
        }
    ],
    "sg:phone":"+32 82 71 32 66",
    "sg:postcode":"5574",
    "sg:province":"Namur",
    "sg:tags":[
        "medicinephysicians",
        "surgeon"
    ],
    "wof:name":"Leclercq P",
    "wof:placetype":"venue"
},
  "geometry": {"coordinates":[5.0029759407,50.0994796753],"type":"Point"}
}