{
  "type": "Feature",
  "properties": {
    "addr:full":"Munkelostraat 38 Wingene West-Vlaanderen 8750",
    "addr:housenumber":"38",
    "addr:postcode":"8750",
    "addr:street":"Munkelostraat",
    "iso:country":"BE",
    "sg:address":"Munkelostraat 38",
    "sg:city":"Wingene",
    "sg:orig_category":"Rundveehouders Varkenskwekers",
    "sg:phone":"+32 50 27 83 27",
    "sg:postcode":"8750",
    "sg:province":"West-Vlaanderen",
    "wof:name":"Devobra",
    "wof:placetype":"venue"
},
  "geometry": {"coordinates":[3.2414500713,51.0801391602],"type":"Point"}
}