{
  "type": "Feature",
  "properties": {
    "addr:full":"Boulevard Louis Mettewie 74-76 Bruxelles (molenbeek-saint-jean) Bruxelles-Capitale 1080",
    "addr:housenumber":"74-76",
    "addr:postcode":"1080",
    "addr:street":"Boulevard Louis Mettewie",
    "iso:country":"BE",
    "sg:address":"Boulevard Louis Mettewie 74-76",
    "sg:city":"Bruxelles (molenbeek-saint-jean)",
    "sg:orig_category":"Mutualities",
    "sg:phone":"+32 2 444 55 33",
    "sg:postcode":"1080",
    "sg:province":"Bruxelles-Capitale",
    "wof:name":"La Caisse Mutuelle",
    "wof:placetype":"venue"
},
  "geometry": {"coordinates":[4.3061728477,50.8546676636],"type":"Point"}
}