{
  "type": "Feature",
  "properties": {
    "addr:full":"Koningin Astridlaan 11 Mechelen Antwerpen 2800",
    "addr:housenumber":"11",
    "addr:postcode":"2800",
    "addr:street":"Koningin Astridlaan",
    "iso:country":"BE",
    "sg:address":"Koningin Astridlaan 11",
    "sg:city":"Mechelen",
    "sg:orig_category":"M\u00e9decins and sp\u00e9cialistes",
    "sg:phone":"+32 15 21 76 56",
    "sg:postcode":"2800",
    "sg:province":"Antwerpen",
    "wof:name":"M. Tange",
    "wof:placetype":"venue"
},
  "geometry": {"coordinates":[4.4704480171,51.0273170471],"type":"Point"}
}