{
  "type": "Feature",
  "properties": {
    "addr:full":"Thier Martin 101 Herve (battice) Li\u00e8ge 4651",
    "addr:housenumber":"101",
    "addr:postcode":"4651",
    "addr:street":"Thier Martin",
    "iso:country":"BE",
    "sg:address":"Thier Martin 101",
    "sg:city":"Herve (battice)",
    "sg:classifiers":[
        {
            "category":"Building & Trades",
            "subcategory":"Electrical",
            "type":"Services"
        }
    ],
    "sg:phone":"+32 87 67 48 58",
    "sg:postcode":"4651",
    "sg:province":"Li\u00e8ge",
    "sg:tags":[
        "electric",
        "-",
        "housewiring",
        "contractor"
    ],
    "wof:name":"Schoonbroodt A Sprl",
    "wof:placetype":"venue"
},
  "geometry": {"coordinates":[5.8121609688,50.6296653748],"type":"Point"}
}