{
  "type": "Feature",
  "properties": {
    "addr:full":"Esdoorndreef 12 Schoten Antwerpen 2900",
    "addr:housenumber":"12",
    "addr:postcode":"2900",
    "addr:street":"Esdoorndreef",
    "iso:country":"BE",
    "sg:address":"Esdoorndreef 12",
    "sg:city":"Schoten",
    "sg:orig_category":"Non-Classified Establishments",
    "sg:phone":"+32 3 236 88 85",
    "sg:postcode":"2900",
    "sg:province":"Antwerpen",
    "wof:name":"Dierckx Jef & Zonen B.v.b.a.",
    "wof:placetype":"venue"
},
  "geometry": {"coordinates":[4.5170178413,51.2786636353],"type":"Point"}
}