{
  "type": "Feature",
  "properties": {
    "addr:full":"Place G\u00e9rard Froidmont 1 Oupeye (hermalle-sous-argenteau) Li\u00e8ge 4681",
    "addr:housenumber":"1",
    "addr:postcode":"4681",
    "addr:street":"Place Ge\u0301Rard Froidmont;Hermalle-Sous-Argenteau",
    "iso:country":"BE",
    "sg:address":"Place G\u00e9rard Froidmont 1",
    "sg:city":"Oupeye (hermalle-sous-argenteau)",
    "sg:classifiers":[
        {
            "category":"Health Services",
            "subcategory":"Nursing And Care Facility",
            "type":"Services"
        }
    ],
    "sg:phone":"+32 4 379 77 57",
    "sg:postcode":"4681",
    "sg:province":"Li\u00e8ge",
    "sg:tags":[
        "home"
    ],
    "wof:name":"Godefroid C",
    "wof:placetype":"venue"
},
  "geometry": {"coordinates":[5.679500103,50.7103004456],"type":"Point"}
}