{
  "type": "Feature",
  "properties": {
    "addr:full":"Rue De Ways 17 Genappe Brabant Wallon 1470",
    "addr:housenumber":"17",
    "addr:postcode":"1470",
    "addr:street":"Rue De Ways;Wallon",
    "iso:country":"BE",
    "sg:address":"Rue De Ways 17",
    "sg:city":"Genappe",
    "sg:classifiers":[
        {
            "category":"Health Services",
            "subcategory":"Health Practitioner",
            "type":"Services"
        }
    ],
    "sg:phone":"+32 67 77 18 54",
    "sg:postcode":"1470",
    "sg:province":"Brabant Wallon",
    "sg:tags":[
        "physiotherapist"
    ],
    "wof:name":"Dekan Isabelle",
    "wof:placetype":"venue"
},
  "geometry": {"coordinates":[4.4520568848,50.6109542847],"type":"Point"}
}