{
  "type": "Feature",
  "properties": {
    "iso:country":"BE",
    "sg:address":"Knesselarestraat 11",
    "sg:city":"Beernem (oedelem)",
    "sg:classifiers":[
        {
            "category":"Personal",
            "subcategory":"Barber",
            "type":"Services"
        }
    ],
    "sg:phone":"+32 50 78 15 88",
    "sg:postcode":"8730",
    "sg:province":"West-Vlaanderen",
    "sg:tags":[
        "gentleman",
        "salon",
        "-",
        "hairdressing"
    ],
    "wof:name":"Kurt",
    "wof:placetype":"venue"
},
  "geometry": {"coordinates":[3.3402040005,51.1686706543],"type":"Point"}
}