{
  "type": "Feature",
  "properties": {
    "addr:full":"Rue Belle Vue 3 Etalle Luxembourg 6740",
    "addr:housenumber":"3",
    "addr:postcode":"6740",
    "addr:street":"Rue Belle Vue",
    "iso:country":"BE",
    "sg:address":"Rue Belle Vue 3",
    "sg:city":"Etalle",
    "sg:orig_category":"D\u00e9molition d\u00b4immeubles and terrassements",
    "sg:phone":"+32 63 45 59 85",
    "sg:postcode":"6740",
    "sg:province":"Luxembourg",
    "wof:name":"Bertrand",
    "wof:placetype":"venue"
},
  "geometry": {"coordinates":[5.6047148705,49.6749992371],"type":"Point"}
}