{
  "type": "Feature",
  "properties": {
    "addr:full":"Rue Grande 48 Gedinne (vencimont) Namur 5575",
    "addr:housenumber":"48",
    "addr:postcode":"5575",
    "addr:street":"Rue Grande",
    "iso:country":"BE",
    "sg:address":"Rue Grande 48",
    "sg:city":"Gedinne (vencimont)",
    "sg:classifiers":[
        {
            "category":"Building & Trades",
            "subcategory":"Landscaping Services",
            "type":"Services"
        }
    ],
    "sg:phone":"+32 61 58 79 17",
    "sg:postcode":"5575",
    "sg:province":"Namur",
    "sg:tags":[
        "gardening",
        "garden",
        "maintenance"
    ],
    "wof:name":"Pisvin M",
    "wof:placetype":"venue"
},
  "geometry": {"coordinates":[4.9225201607,50.032409668],"type":"Point"}
}