{
  "type": "Feature",
  "properties": {
    "addr:full":"Place Du Ballon 28 Charleroi (jumet) Hainaut 6040",
    "addr:housenumber":"28",
    "addr:postcode":"6040",
    "addr:street":"Place Du Ballon",
    "iso:country":"BE",
    "sg:address":"Place Du Ballon 28",
    "sg:city":"Charleroi (jumet)",
    "sg:classifiers":[
        {
            "category":"Shopping",
            "subcategory":"Crafts & Fabrics",
            "type":"Retail Goods"
        }
    ],
    "sg:phone":"+32 71 35 30 24",
    "sg:postcode":"6040",
    "sg:province":"Hainaut",
    "sg:tags":[
        "silk",
        "-"
    ],
    "wof:name":"Dumont M",
    "wof:placetype":"venue"
},
  "geometry": {"coordinates":[4.414206028,50.4350585938],"type":"Point"}
}