{
  "type": "Feature",
  "properties": {
    "addr:full":"Ieperstraat 57 Menen West-Vlaanderen 8930",
    "addr:housenumber":"57",
    "addr:postcode":"8930",
    "addr:street":"Ieperstraat",
    "iso:country":"BE",
    "sg:address":"Ieperstraat 57",
    "sg:city":"Menen",
    "sg:orig_category":"Slagers",
    "sg:phone":"+32 56 51 21 98",
    "sg:postcode":"8930",
    "sg:province":"West-Vlaanderen",
    "wof:name":"Luc Vanmoerkerke",
    "wof:placetype":"venue"
},
  "geometry": {"coordinates":[3.1170339584,50.7970046997],"type":"Point"}
}