{
  "type": "Feature",
  "properties": {
    "addr:full":"Place Saint-pierre 24 Bastogne Luxembourg 6600",
    "addr:housenumber":"24",
    "addr:postcode":"6600",
    "addr:street":"Place Saint-Pierre",
    "iso:country":"BE",
    "sg:address":"Place Saint-pierre 24",
    "sg:city":"Bastogne",
    "sg:classifiers":[
        {
            "category":"Education",
            "subcategory":"School",
            "type":"Public Place"
        }
    ],
    "sg:phone":"+32 61 24 06 30",
    "sg:postcode":"6600",
    "sg:province":"Luxembourg",
    "sg:tags":[
        "secondary"
    ],
    "wof:name":"Institut Notre Dame Seminaire",
    "wof:placetype":"venue"
},
  "geometry": {"coordinates":[5.7198572159,50.0054359436],"type":"Point"}
}