{
  "type": "Feature",
  "properties": {
    "iso:country":"BE",
    "sg:address":"Grote Lindestraat 32",
    "sg:city":"Hasselt",
    "sg:orig_category":"Installatie van metalen schrijnwerk",
    "sg:phone":"+32 11 27 10 25",
    "sg:postcode":"3500",
    "sg:province":"Limburg",
    "wof:name":"Fa. Christens Gebrs",
    "wof:placetype":"venue"
},
  "geometry": {"coordinates":[5.3242020607,50.9181213379],"type":"Point"}
}