{
  "type": "Feature",
  "properties": {
    "iso:country":"BE",
    "sg:address":"Rue Saint-adolphe 4",
    "sg:city":"Manage",
    "sg:orig_category":"Dakwerken",
    "sg:phone":"+32 64 28 10 85",
    "sg:postcode":"7170",
    "sg:province":"Hainaut",
    "wof:name":"Verschueren",
    "wof:placetype":"venue"
},
  "geometry": {"coordinates":[4.2239608765,50.4686737061],"type":"Point"}
}