{
  "type": "Feature",
  "properties": {
    "iso:country":"BE",
    "sg:address":"Rue De Nalinnes 62",
    "sg:city":"Charleroi",
    "sg:orig_category":"Enseignement maternel and primaire",
    "sg:phone":"+32 71 43 82 57",
    "sg:postcode":"6001",
    "sg:province":"Hainaut",
    "wof:name":"E.f.l. Sacr\u00c9-coeur",
    "wof:placetype":"venue"
},
  "geometry": {"coordinates":[4.460100174,50.3844947815],"type":"Point"}
}