{
  "type": "Feature",
  "properties": {
    "addr:full":"Kanunnik Van Hoonackerstraat 22 Box 8 Brugge West-Vlaanderen 8000",
    "addr:housenumber":"22;8",
    "addr:postcode":"8000",
    "addr:street":"Kanunnik Van Hoonackerstraat;Box",
    "iso:country":"BE",
    "sg:address":"Kanunnik Van Hoonackerstraat 22 Box 8",
    "sg:city":"Brugge",
    "sg:classifiers":[
        {
            "category":"Personal",
            "subcategory":"Nail Salon",
            "type":"Services"
        }
    ],
    "sg:phone":"+32 50 31 86 18",
    "sg:postcode":"8000",
    "sg:province":"West-Vlaanderen",
    "sg:tags":[
        "pedicure"
    ],
    "wof:name":"De Laere R-m",
    "wof:placetype":"venue"
},
  "geometry": {"coordinates":[3.2050030231,51.2145500183],"type":"Point"}
}