{
  "type": "Feature",
  "properties": {
    "iso:country":"BE",
    "sg:address":"Paardskerkhof 4",
    "sg:city":"Peer",
    "sg:classifiers":[
        {
            "category":"Professional",
            "subcategory":"Computer Services",
            "type":"Services"
        }
    ],
    "sg:phone":"+32 478 25 31 16",
    "sg:postcode":"3990",
    "sg:province":"Limburg",
    "sg:tags":[
        "-",
        "processing",
        "data",
        "software"
    ],
    "wof:name":"Wipasoft Educatieve Software",
    "wof:placetype":"venue"
},
  "geometry": {"coordinates":[5.471722126,51.1316184998],"type":"Point"}
}