{
  "type": "Feature",
  "properties": {
    "addr:full":"Rue Chav\u00e9e 20 Manage (la Hestre) Hainaut 7170",
    "addr:housenumber":"20",
    "addr:postcode":"7170",
    "addr:street":"Rue Chave\u0301E;La;Hainaut",
    "iso:country":"BE",
    "sg:address":"Rue Chav\u00e9e 20",
    "sg:city":"Manage (la Hestre)",
    "sg:classifiers":[
        {
            "category":"Freight",
            "type":"Transportation"
        }
    ],
    "sg:phone":"+32 495 24 10 94",
    "sg:postcode":"7170",
    "sg:province":"Hainaut",
    "sg:tags":[
        "-",
        "transport"
    ],
    "wof:name":"Yanlaur",
    "wof:placetype":"venue"
},
  "geometry": {"coordinates":[4.2401437759,50.4767875671],"type":"Point"}
}