{
  "type": "Feature",
  "properties": {
    "addr:full":"Rue De Livourne 125 Elsene/ixelles Bruxelles-Capitale 1050",
    "addr:housenumber":"125",
    "addr:postcode":"1050",
    "addr:street":"Rue De Livourne",
    "iso:country":"BE",
    "sg:address":"Rue De Livourne 125",
    "sg:city":"Elsene/ixelles",
    "sg:orig_category":"Antiek",
    "sg:phone":"+32 2 649 69 89",
    "sg:postcode":"1050",
    "sg:province":"Bruxelles-Capitale",
    "wof:name":"Vandendriessche M.",
    "wof:placetype":"venue"
},
  "geometry": {"coordinates":[4.3625001907,50.8265609741],"type":"Point"}
}