{
  "type": "Feature",
  "properties": {
    "addr:full":"Ropsy Chaudronstraat 22bb Anderlecht/anderlecht Bruxelles-Capitale 1070",
    "addr:housenumber":"22bb",
    "addr:postcode":"1070",
    "addr:street":"Ropsy Chaudronstraat",
    "iso:country":"BE",
    "sg:address":"Ropsy Chaudronstraat 22bb",
    "sg:city":"Anderlecht/anderlecht",
    "sg:orig_category":"Postkantoren Verzekeringsmakelaars and experts",
    "sg:phone":"+32 2 520 85 51",
    "sg:postcode":"1070",
    "sg:province":"Bruxelles-Capitale",
    "wof:name":"De Post",
    "wof:placetype":"venue"
},
  "geometry": {"coordinates":[4.2696990967,50.8269844055],"type":"Point"}
}