{
  "type": "Feature",
  "properties": {
    "addr:full":"Bosbesstraat 59 Westerlo Antwerpen 2260",
    "addr:housenumber":"59",
    "addr:postcode":"2260",
    "addr:street":"Bosbesstraat",
    "iso:country":"BE",
    "sg:address":"Bosbesstraat 59",
    "sg:city":"Westerlo",
    "sg:classifiers":[
        {
            "category":"Insurance",
            "subcategory":"Life Insurance",
            "type":"Services"
        }
    ],
    "sg:phone":"+32 14 54 18 97",
    "sg:postcode":"2260",
    "sg:province":"Antwerpen",
    "sg:tags":[
        "assurance"
    ],
    "wof:name":"J. Aerts",
    "wof:placetype":"venue"
},
  "geometry": {"coordinates":[4.9025449753,51.09582901],"type":"Point"}
}