{
  "type": "Feature",
  "properties": {
    "addr:full":"Avenue Jos\u00e9phine-charlotte 54 Rixensart Brabant Wallon 1330",
    "addr:housenumber":"54",
    "addr:postcode":"1330",
    "addr:street":"Avenue Jose\u0301Phine-Charlotte;Wallon",
    "iso:country":"BE",
    "sg:address":"Avenue Jos\u00e9phine-charlotte 54",
    "sg:city":"Rixensart",
    "sg:classifiers":[
        {
            "category":"Banks & Credit Unions",
            "subcategory":"Investment Brokerage",
            "type":"Services"
        }
    ],
    "sg:phone":"+32 2 653 38 50",
    "sg:postcode":"1330",
    "sg:province":"Brabant Wallon",
    "sg:tags":[
        "auditor"
    ],
    "wof:name":"Josse C",
    "wof:placetype":"venue"
},
  "geometry": {"coordinates":[4.5432901382,50.7069511414],"type":"Point"}
}