{
  "type": "Feature",
  "properties": {
    "iso:country":"BE",
    "sg:address":"Heide 33",
    "sg:city":"Puurs",
    "sg:classifiers":[
        {
            "category":"Education",
            "subcategory":"Dance Studio",
            "type":"Public Place"
        }
    ],
    "sg:phone":"+32 3 889 61 46",
    "sg:postcode":"2870",
    "sg:province":"Antwerpen",
    "sg:tags":[
        "school",
        "dancing"
    ],
    "wof:name":"Seghers D",
    "wof:placetype":"venue"
},
  "geometry": {"coordinates":[4.274848938,51.0691947937],"type":"Point"}
}