{
  "type": "Feature",
  "properties": {
    "addr:full":"Godsschalkstraat 23 Sint-niklaas Oost-Vlaanderen 9100",
    "addr:housenumber":"23",
    "addr:postcode":"9100",
    "addr:street":"Godsschalkstraat",
    "iso:country":"BE",
    "sg:address":"Godsschalkstraat 23",
    "sg:city":"Sint-niklaas",
    "sg:orig_category":"Gespecialiseerde residenti\u00eble bouw",
    "sg:phone":"+32 3 776 85 04",
    "sg:postcode":"9100",
    "sg:province":"Oost-Vlaanderen",
    "wof:name":"Raoul De Munck",
    "wof:placetype":"venue"
},
  "geometry": {"coordinates":[4.1482081413,51.188583374],"type":"Point"}
}