{
  "type": "Feature",
  "properties": {
    "iso:country":"BE",
    "sg:address":"Guido Gezellestraat 43",
    "sg:city":"Zwevegem",
    "sg:classifiers":[
        {
            "category":"Building & Trades",
            "subcategory":"Construction",
            "type":"Services"
        }
    ],
    "sg:phone":"+32 56 75 72 14",
    "sg:postcode":"8550",
    "sg:province":"West-Vlaanderen",
    "sg:tags":[
        "asphalt",
        "contractor"
    ],
    "wof:name":"Vandenbulcke B",
    "wof:placetype":"venue"
},
  "geometry": {"coordinates":[3.3385150433,50.8085594177],"type":"Point"}
}