{
  "type": "Feature",
  "properties": {
    "addr:full":"Kiezelweg 235 Lanaken Limburg 3620",
    "addr:housenumber":"235",
    "addr:postcode":"3620",
    "addr:street":"Kiezelweg",
    "iso:country":"BE",
    "sg:address":"Kiezelweg 235",
    "sg:city":"Lanaken",
    "sg:classifiers":[
        {
            "category":"Recreation",
            "subcategory":"Amusement Park",
            "type":"Entertainment"
        }
    ],
    "sg:phone":"+32 89 73 27 33",
    "sg:postcode":"3620",
    "sg:province":"Limburg",
    "sg:tags":[
        "fantasieartikelen",
        "diver"
    ],
    "wof:name":"Renaldo's Wonderland",
    "wof:placetype":"venue"
},
  "geometry": {"coordinates":[5.6303129196,50.8812713623],"type":"Point"}
}