{
  "type": "Feature",
  "properties": {
    "addr:full":"Kouterbaan 44 Lebbeke Oost-Vlaanderen 9280",
    "addr:housenumber":"44",
    "addr:postcode":"9280",
    "addr:street":"Kouterbaan",
    "iso:country":"BE",
    "sg:address":"Kouterbaan 44",
    "sg:city":"Lebbeke",
    "sg:classifiers":[
        {
            "category":"Shopping",
            "subcategory":"Clothing, Apparel, & Fashions",
            "type":"Retail Goods"
        }
    ],
    "sg:phone":"+32 52 41 26 11",
    "sg:postcode":"9280",
    "sg:province":"Oost-Vlaanderen",
    "sg:tags":[
        "lady",
        "clothing",
        "-"
    ],
    "wof:name":"Caroline Nv",
    "wof:placetype":"venue"
},
  "geometry": {"coordinates":[4.119697094,50.9971542358],"type":"Point"}
}