{
  "type": "Feature",
  "properties": {
    "addr:full":"Rue De La Cense Du Roi 1a Le Roeulx (thieu) Hainaut 7070",
    "addr:housenumber":"1a",
    "addr:postcode":"7070",
    "addr:street":"Rue De La Cense Du Roi",
    "iso:country":"BE",
    "sg:address":"Rue De La Cense Du Roi 1a",
    "sg:city":"Le Roeulx (thieu)",
    "sg:classifiers":[
        {
            "category":"Health Services",
            "subcategory":"Health Practitioner",
            "type":"Services"
        }
    ],
    "sg:phone":"+32 64 65 05 50",
    "sg:postcode":"7070",
    "sg:province":"Hainaut",
    "sg:tags":[
        "physiotherapist"
    ],
    "wof:name":"Marin Jean-fran\u00e7ois",
    "wof:placetype":"venue"
},
  "geometry": {"coordinates":[4.0901441574,50.473613739],"type":"Point"}
}