{
  "type": "Feature",
  "properties": {
    "addr:full":"H. De Backerestraat 6 Kortrijk West-Vlaanderen 8501",
    "addr:housenumber":"6",
    "addr:postcode":"8501",
    "addr:street":"H. De Backerestraat",
    "iso:country":"BE",
    "sg:address":"H. De Backerestraat 6",
    "sg:city":"Kortrijk",
    "sg:classifiers":[
        {
            "category":"Cafe",
            "type":"Food & Drink"
        }
    ],
    "sg:phone":"+32 56 35 95 33",
    "sg:postcode":"8501",
    "sg:province":"West-Vlaanderen",
    "sg:tags":[
        "caf\u00e9s"
    ],
    "wof:name":"Marnix Tuytens",
    "wof:placetype":"venue"
},
  "geometry": {"coordinates":[3.2336709499,50.8435592651],"type":"Point"}
}