{
  "type": "Feature",
  "properties": {
    "iso:country":"BE",
    "sg:address":"Kortrijksepoortstraat 252",
    "sg:city":"Gent",
    "sg:orig_category":"Maisons de repos and r\u00e9sidences",
    "sg:phone":"+32 9 225 52 35",
    "sg:postcode":"9000",
    "sg:province":"Oost-Vlaanderen",
    "wof:name":"O.l.vrouw Ten Schreiboom",
    "wof:placetype":"venue"
},
  "geometry": {"coordinates":[3.7196938992,51.0428695679],"type":"Point"}
}