{
  "type": "Feature",
  "properties": {
    "addr:full":"Hulsen 25 Balen Antwerpen 2490",
    "addr:housenumber":"25",
    "addr:postcode":"2490",
    "addr:street":"Hulsen",
    "iso:country":"BE",
    "sg:address":"Hulsen 25",
    "sg:city":"Balen",
    "sg:orig_category":"Diverse bouwafwerking and reiniging",
    "sg:phone":"+32 14 30 94 00",
    "sg:postcode":"2490",
    "sg:province":"Antwerpen",
    "wof:name":"Francois Nijs",
    "wof:placetype":"venue"
},
  "geometry": {"coordinates":[5.1269869804,51.148853302],"type":"Point"}
}