{
  "type": "Feature",
  "properties": {
    "addr:full":"Rue Van Orley 10 Bruxelles Bruxelles-Capitale 1000",
    "addr:housenumber":"10",
    "addr:postcode":"1000",
    "addr:street":"Rue Van Orley",
    "iso:country":"BE",
    "sg:address":"Rue Van Orley 10",
    "sg:city":"Bruxelles",
    "sg:classifiers":[
        {
            "category":"Sports & Exercise",
            "subcategory":"Gym",
            "type":"Entertainment"
        }
    ],
    "sg:phone":"+32 2 218 08 00",
    "sg:postcode":"1000",
    "sg:province":"Bruxelles-Capitale",
    "sg:tags":[
        "fitness"
    ],
    "wof:name":"Oasis",
    "wof:placetype":"venue"
},
  "geometry": {"coordinates":[4.3670902252,50.8521614075],"type":"Point"}
}