{
  "type": "Feature",
  "properties": {
    "iso:country":"BE",
    "sg:address":"Magnolialaan 22",
    "sg:city":"Steenokkerzeel",
    "sg:classifiers":[
        {
            "category":"Professional",
            "subcategory":"Accounting & Tax Preparation",
            "type":"Services"
        }
    ],
    "sg:phone":"+32 2 751 81 32",
    "sg:postcode":"1820",
    "sg:province":"Vlaams-Brabant",
    "sg:tags":[
        "bookkeeper"
    ],
    "wof:name":"Storckel P",
    "wof:placetype":"venue"
},
  "geometry": {"coordinates":[4.5097560883,50.9272918701],"type":"Point"}
}