{
  "type": "Feature",
  "properties": {
    "addr:full":"Dr\u00c8ve Des Equipages 2 Watermaal-bosvoorde/watermael-boitsfort Bruxelles-Capitale 1170",
    "addr:housenumber":"2",
    "addr:postcode":"1170",
    "addr:street":"Dre\u0300Ve Des Equipages",
    "iso:country":"BE",
    "sg:address":"Dr\u00c8ve Des Equipages 2",
    "sg:city":"Watermaal-bosvoorde/watermael-boitsfort",
    "sg:orig_category":"M\u00e9decins and sp\u00e9cialistes",
    "sg:phone":"+32 2 673 12 27",
    "sg:postcode":"1170",
    "sg:province":"Bruxelles-Capitale",
    "wof:name":"Guy Thysman",
    "wof:placetype":"venue"
},
  "geometry": {"coordinates":[4.421628952,50.7889213562],"type":"Point"}
}