{
  "type": "Feature",
  "properties": {
    "iso:country":"BE",
    "sg:address":"Hallesesteenweg 158",
    "sg:city":"Sint-genesius-rode/rhode-saint-gen\u00c8se",
    "sg:orig_category":"Zalen voor culturele evenementen",
    "sg:phone":"+32 2 381 21 81",
    "sg:postcode":"1640",
    "sg:province":"Vlaams-Brabant",
    "wof:name":"Evelyn De Beir Gallery",
    "wof:placetype":"venue"
},
  "geometry": {"coordinates":[4.3305301666,50.7369308472],"type":"Point"}
}