{
  "type": "Feature",
  "properties": {
    "addr:full":"Bevrijdingsstraat 11-13 Diest Vlaams-Brabant 3290",
    "addr:postcode":"11-13;3290",
    "addr:street":"Bevrijdingsstraat",
    "iso:country":"BE",
    "sg:address":"Bevrijdingsstraat 11-13",
    "sg:city":"Diest",
    "sg:classifiers":[
        {
            "category":"Home & Garden",
            "subcategory":"Kitchen Supply",
            "type":"Retail Goods"
        }
    ],
    "sg:phone":"+32 13 33 32 60",
    "sg:postcode":"3290",
    "sg:province":"Vlaams-Brabant",
    "sg:tags":[
        "equipment",
        "baker",
        "-"
    ],
    "wof:name":"Heinz Backtechnik Nv",
    "wof:placetype":"venue"
},
  "geometry": {"coordinates":[5.056456089,50.9783325195],"type":"Point"}
}