{
  "type": "Feature",
  "properties": {
    "iso:country":"BE",
    "sg:address":"Ravenhofstraat 5",
    "sg:city":"Torhout",
    "sg:orig_category":"Notarissen",
    "sg:phone":"+32 50 21 69 81",
    "sg:postcode":"8820",
    "sg:province":"West-Vlaanderen",
    "wof:name":"C. Ryckaert",
    "wof:placetype":"venue"
},
  "geometry": {"coordinates":[3.0998489857,51.0639572144],"type":"Point"}
}