{
  "type": "Feature",
  "properties": {
    "addr:full":"Baksteenkaai 48 Brussel/bruxelles Bruxelles-Capitale 1000",
    "addr:housenumber":"48",
    "addr:postcode":"1000",
    "addr:street":"Baksteenkaai;/",
    "iso:country":"BE",
    "sg:address":"Baksteenkaai 48",
    "sg:city":"Brussel/bruxelles",
    "sg:orig_category":"Diepvriesproducten Gh Diverse voedingsmiddelen Gh",
    "sg:phone":"+32 2 512 85 25",
    "sg:postcode":"1000",
    "sg:province":"Bruxelles-Capitale",
    "wof:name":"Segers-soetens",
    "wof:placetype":"venue"
},
  "geometry": {"coordinates":[4.3472671509,50.8522186279],"type":"Point"}
}