{
  "type": "Feature",
  "properties": {
    "addr:full":"Rue Paul Pastur 106 Ath Hainaut 7800",
    "addr:housenumber":"106",
    "addr:postcode":"7800",
    "addr:street":"Rue Paul Pastur",
    "iso:country":"BE",
    "sg:address":"Rue Paul Pastur 106",
    "sg:city":"Ath",
    "sg:orig_category":"G\u00e9om\u00e8tres",
    "sg:phone":"+32 68 28 47 81",
    "sg:postcode":"7800",
    "sg:province":"Hainaut",
    "wof:name":"Pierre Tagnon",
    "wof:placetype":"venue"
},
  "geometry": {"coordinates":[3.7718861103,50.6203575134],"type":"Point"}
}