{
  "type": "Feature",
  "properties": {
    "addr:full":"Place De L'h\u00f4tel De Ville 3 Florennes Namur 5620",
    "addr:housenumber":"3",
    "addr:postcode":"5620",
    "addr:street":"Place De L'Ho \u0302Tel De Ville",
    "iso:country":"BE",
    "sg:address":"Place De L'h\u00f4tel De Ville 3",
    "sg:city":"Florennes",
    "sg:classifiers":[
        {
            "category":"Health Services",
            "subcategory":"Health Practitioner",
            "type":"Services"
        }
    ],
    "sg:phone":"+32 71 68 75 87",
    "sg:postcode":"5620",
    "sg:province":"Namur",
    "sg:tags":[
        "psychologist"
    ],
    "wof:name":"Centre De Consultations Conjugales & Familiales",
    "wof:placetype":"venue"
},
  "geometry": {"coordinates":[4.6609201431,50.2378807068],"type":"Point"}
}