{
  "type": "Feature",
  "properties": {
    "iso:country":"BE",
    "sg:address":"Grand'rue",
    "sg:city":"Tintigny",
    "sg:classifiers":[
        {
            "category":"Fast Food",
            "type":"Food & Drink"
        }
    ],
    "sg:phone":"+32 63 44 48 04",
    "sg:postcode":"6730",
    "sg:province":"Luxembourg",
    "sg:tags":[
        "fried",
        "stand",
        "potato"
    ],
    "wof:name":"Routiers (les)",
    "wof:placetype":"venue"
},
  "geometry": {"coordinates":[5.526070118,49.6808395386],"type":"Point"}
}