{
  "type": "Feature",
  "properties": {
    "iso:country":"BE",
    "sg:address":"Route De Marche 3",
    "sg:city":"Somme-leuze (baillonville)",
    "sg:classifiers":[
        {
            "category":"Health Services",
            "subcategory":"Nursing And Care Facility",
            "type":"Services"
        }
    ],
    "sg:phone":"+32 84 31 22 27",
    "sg:postcode":"5377",
    "sg:province":"Namur",
    "sg:tags":[
        "home"
    ],
    "wof:name":"Debouck M",
    "wof:placetype":"venue"
},
  "geometry": {"coordinates":[5.3658270836,50.3406219482],"type":"Point"}
}