{
  "type": "Feature",
  "properties": {
    "iso:country":"BE",
    "sg:address":"Avenue De Maire 15",
    "sg:city":"Tournai",
    "sg:classifiers":[
        {
            "category":"Retail",
            "subcategory":"Animal Services",
            "type":"Services"
        }
    ],
    "sg:phone":"+32 69 84 38 76",
    "sg:postcode":"7500",
    "sg:province":"Hainaut",
    "sg:tags":[
        "grooming",
        "-",
        "dog"
    ],
    "wof:name":"Les 101 Dames A Chiens",
    "wof:placetype":"venue"
},
  "geometry": {"coordinates":[3.37789011,50.6130867004],"type":"Point"}
}