{
  "type": "Feature",
  "properties": {
    "addr:full":"Rue De Bovesse 3 La Bruy\u00e8re (bovesse) Namur 5081",
    "addr:housenumber":"3",
    "addr:postcode":"5081",
    "addr:street":"Rue De Bovesse",
    "iso:country":"BE",
    "sg:address":"Rue De Bovesse 3",
    "sg:city":"La Bruy\u00e8re (bovesse)",
    "sg:classifiers":[
        {
            "category":"Personal",
            "subcategory":"Barber",
            "type":"Services"
        }
    ],
    "sg:phone":"+32 81 55 91 52",
    "sg:postcode":"5081",
    "sg:province":"Namur",
    "sg:tags":[
        "gentleman",
        "salon",
        "-",
        "hairdressing"
    ],
    "wof:name":"A L'hair Libre",
    "wof:placetype":"venue"
},
  "geometry": {"coordinates":[4.7772889137,50.5175132751],"type":"Point"}
}