{
  "type": "Feature",
  "properties": {
    "addr:full":"Rue D'ormont 39b Tournai (kain) Hainaut 7540",
    "addr:housenumber":"39b",
    "addr:postcode":"7540",
    "addr:street":"Rue D'Ormont",
    "iso:country":"BE",
    "sg:address":"Rue D'ormont 39b",
    "sg:city":"Tournai (kain)",
    "sg:classifiers":[
        {
            "category":"Building & Trades",
            "subcategory":"Construction",
            "type":"Services"
        }
    ],
    "sg:phone":"+32 476 24 37 52",
    "sg:postcode":"7540",
    "sg:province":"Hainaut",
    "sg:tags":[
        "installation",
        "-",
        "central",
        "heating"
    ],
    "wof:name":"Labie D",
    "wof:placetype":"venue"
},
  "geometry": {"coordinates":[3.3697059155,50.6354827881],"type":"Point"}
}