{
  "type": "Feature",
  "properties": {
    "iso:country":"BE",
    "sg:address":"Rue De Tubize 8",
    "sg:city":"Ittre (virginal-samme)",
    "sg:classifiers":[
        {
            "category":"Home & Garden",
            "subcategory":"Kitchen Supply",
            "type":"Retail Goods"
        }
    ],
    "sg:phone":"+32 67 64 63 16",
    "sg:postcode":"1460",
    "sg:province":"Brabant Wallon",
    "sg:tags":[
        "equipment",
        "baker",
        "-"
    ],
    "wof:name":"Dekeghel J",
    "wof:placetype":"venue"
},
  "geometry": {"coordinates":[4.2171301842,50.653427124],"type":"Point"}
}