{
  "type": "Feature",
  "properties": {
    "iso:country":"BE",
    "sg:address":"Rue Dorzee 23",
    "sg:city":"Boussu",
    "sg:orig_category":"Electrom\u00e9nager, t\u00e9l\u00e9visions and radios. R\u00e9parations d'appareils \u00e9lectrom\u00e9nagers",
    "sg:phone":"+32 65 78 45 63",
    "sg:postcode":"7300",
    "sg:province":"Hainaut",
    "wof:name":"Geerickx-duprez",
    "wof:placetype":"venue"
},
  "geometry": {"coordinates":[3.7976241112,50.4338951111],"type":"Point"}
}