{
  "type": "Feature",
  "properties": {
    "iso:country":"BE",
    "sg:address":"Rue Du G\u00e9n\u00e9ral-molitor 12",
    "sg:city":"Arlon",
    "sg:classifiers":[
        {
            "category":"Food & Beverages",
            "subcategory":"Specialty",
            "type":"Retail Goods"
        }
    ],
    "sg:phone":"+32 63 22 66 02",
    "sg:postcode":"6700",
    "sg:province":"Luxembourg",
    "sg:tags":[
        "health",
        "dietary",
        "-",
        "biological"
    ],
    "wof:name":"Equilor Centre De Nutrion Sprl",
    "wof:placetype":"venue"
},
  "geometry": {"coordinates":[5.8122210503,49.6816177368],"type":"Point"}
}