{
  "type": "Feature",
  "properties": {
    "addr:full":"Molenbergstraat 20 Lede Oost-Vlaanderen 9340",
    "addr:housenumber":"20",
    "addr:postcode":"9340",
    "addr:street":"Molenbergstraat",
    "iso:country":"BE",
    "sg:address":"Molenbergstraat 20",
    "sg:city":"Lede",
    "sg:classifiers":[
        {
            "category":"Restaurant",
            "type":"Food & Drink"
        }
    ],
    "sg:phone":"+32 53 80 47 70",
    "sg:postcode":"9340",
    "sg:province":"Oost-Vlaanderen",
    "wof:name":"Den Bonten Os",
    "wof:placetype":"venue"
},
  "geometry": {"coordinates":[3.9738099575,50.9637413025],"type":"Point"}
}