{
  "type": "Feature",
  "properties": {
    "iso:country":"BE",
    "sg:address":"Kasteelstraat 73",
    "sg:city":"Kuurne",
    "sg:orig_category":"Peinture. Rev\u00eatements pour sols and murs",
    "sg:phone":"+32 56 71 06 45",
    "sg:postcode":"8520",
    "sg:province":"West-Vlaanderen",
    "wof:name":"Verschelde Vhelst & Zo",
    "wof:placetype":"venue"
},
  "geometry": {"coordinates":[3.2769010067,50.8573760986],"type":"Point"}
}