{
  "type": "Feature",
  "properties": {
    "addr:full":"Nijverheidslaan 27 Maasmechelen Limburg 3630",
    "addr:housenumber":"27",
    "addr:postcode":"3630",
    "addr:street":"Nijverheidslaan",
    "iso:country":"BE",
    "sg:address":"Nijverheidslaan 27",
    "sg:city":"Maasmechelen",
    "sg:orig_category":"M\u00e9decins and sp\u00e9cialistes",
    "sg:phone":"+32 89 76 42 11",
    "sg:postcode":"3630",
    "sg:province":"Limburg",
    "wof:name":"G. Mardaga",
    "wof:placetype":"venue"
},
  "geometry": {"coordinates":[5.6961350441,50.963848114],"type":"Point"}
}