{
  "type": "Feature",
  "properties": {
    "iso:country":"BE",
    "sg:address":"Oude Dorpsweg 85",
    "sg:city":"Jabbeke",
    "sg:orig_category":"Pharmaciens",
    "sg:phone":"+32 50 38 86 18",
    "sg:postcode":"8490",
    "sg:province":"West-Vlaanderen",
    "wof:name":"Verbeke",
    "wof:placetype":"venue"
},
  "geometry": {"coordinates":[3.1426930428,51.1882324219],"type":"Point"}
}