{
  "type": "Feature",
  "properties": {
    "iso:country":"BE",
    "sg:address":"Vakenstraat 18",
    "sg:city":"Rotselaar",
    "sg:orig_category":"Recreatie- and lunaparken Restaurants Sportcentra Sportterreinen and installaties behalve sportcentr",
    "sg:phone":"+32 16 44 45 17",
    "sg:postcode":"3110",
    "sg:province":"Vlaams-Brabant",
    "wof:name":"Sportdienst",
    "wof:placetype":"venue"
},
  "geometry": {"coordinates":[4.7227339745,50.9631385803],"type":"Point"}
}