{
  "type": "Feature",
  "properties": {
    "addr:full":"Rue De La Station 26 Havelange Namur 5370",
    "addr:housenumber":"26",
    "addr:postcode":"5370",
    "addr:street":"Rue De La Station",
    "iso:country":"BE",
    "sg:address":"Rue De La Station 26",
    "sg:city":"Havelange",
    "sg:classifiers":[
        {
            "category":"Personal",
            "subcategory":"Beauty Salon",
            "type":"Services"
        }
    ],
    "sg:phone":"+32 83 63 34 37",
    "sg:postcode":"5370",
    "sg:province":"Namur",
    "sg:tags":[
        "lady",
        "-",
        "hairdressing"
    ],
    "wof:name":"Nizet M",
    "wof:placetype":"venue"
},
  "geometry": {"coordinates":[5.2396497726,50.3887290955],"type":"Point"}
}