{
  "type": "Feature",
  "properties": {
    "iso:country":"BE",
    "sg:address":"Nati\u00ebnlaan 291",
    "sg:city":"Knokke-heist (westkapelle)",
    "sg:classifiers":[
        {
            "category":"Real Estate",
            "subcategory":"Surveying",
            "type":"Services"
        }
    ],
    "sg:phone":"+32 50 60 57 05",
    "sg:postcode":"8300",
    "sg:province":"West-Vlaanderen",
    "sg:tags":[
        "lettering",
        "letter"
    ],
    "wof:name":"Ateljee 342",
    "wof:placetype":"venue"
},
  "geometry": {"coordinates":[3.2890501022,51.3361816406],"type":"Point"}
}