{
  "type": "Feature",
  "properties": {
    "iso:country":"BE",
    "sg:address":"Binnenstraat 293",
    "sg:city":"Aalst",
    "sg:classifiers":[
        {
            "category":"Shopping",
            "subcategory":"Music",
            "type":"Retail Goods"
        }
    ],
    "sg:phone":"+32 53 70 31 48",
    "sg:postcode":"9300",
    "sg:province":"Oost-Vlaanderen",
    "sg:tags":[
        "-",
        "cd's",
        "recorded",
        "cassette"
    ],
    "wof:name":"Multi Music",
    "wof:placetype":"venue"
},
  "geometry": {"coordinates":[4.0553479195,50.9498710632],"type":"Point"}
}