{
  "type": "Feature",
  "properties": {
    "addr:full":"Oude Vierschaarstraat 37 Sint-martens-latem Oost-Vlaanderen 9831",
    "addr:housenumber":"37",
    "addr:postcode":"9831",
    "addr:street":"Oude Vierschaarstraat",
    "iso:country":"BE",
    "sg:address":"Oude Vierschaarstraat 37",
    "sg:city":"Sint-martens-latem",
    "sg:classifiers":[
        {
            "category":"Arena",
            "subcategory":"Sports Club",
            "type":"Entertainment"
        }
    ],
    "sg:phone":"+32 9 282 55 34",
    "sg:postcode":"9831",
    "sg:province":"Oost-Vlaanderen",
    "sg:tags":[
        "de"
    ],
    "wof:name":"B.c. Golden River",
    "wof:placetype":"venue"
},
  "geometry": {"coordinates":[3.6142630577,51.004573822],"type":"Point"}
}