{
  "type": "Feature",
  "properties": {
    "iso:country":"BE",
    "sg:address":"Nieuwbeekstraat 35",
    "sg:city":"Aalst",
    "sg:orig_category":"S\u00e9curit\u00e9 sociale",
    "sg:phone":"+32 53 71 13 00",
    "sg:postcode":"9300",
    "sg:province":"Oost-Vlaanderen",
    "wof:name":"Vl. Neutraal Ziekenfonds",
    "wof:placetype":"venue"
},
  "geometry": {"coordinates":[4.0298099518,50.936290741],"type":"Point"}
}