{
  "type": "Feature",
  "properties": {
    "addr:full":"Molenstraat 57 Heist-op-den-berg Antwerpen 2220",
    "addr:housenumber":"57",
    "addr:postcode":"2220",
    "addr:street":"Molenstraat",
    "iso:country":"BE",
    "sg:address":"Molenstraat 57",
    "sg:city":"Heist-op-den-berg",
    "sg:classifiers":[
        {
            "category":"Insurance",
            "subcategory":"Insurance Agent",
            "type":"Services"
        }
    ],
    "sg:phone":"+32 15 24 61 75",
    "sg:postcode":"2220",
    "sg:province":"Antwerpen",
    "sg:tags":[
        "broker"
    ],
    "wof:name":"Broeckx J Verzekeringskantoor",
    "wof:placetype":"venue"
},
  "geometry": {"coordinates":[4.7185029984,51.0795783997],"type":"Point"}
}