{
  "type": "Feature",
  "properties": {
    "iso:country":"BE",
    "sg:address":"Rond-point Du Meir 6",
    "sg:city":"Bruxelles (anderlecht)",
    "sg:classifiers":[
        {
            "category":"Health Services",
            "subcategory":"Doctor",
            "type":"Services"
        }
    ],
    "sg:phone":"+32 2 521 72 63",
    "sg:postcode":"1070",
    "sg:province":"Bruxelles-Capitale",
    "sg:tags":[
        "medicinephysicians",
        "surgeon"
    ],
    "wof:name":"Baeyens Y",
    "wof:placetype":"venue"
},
  "geometry": {"coordinates":[4.3018717766,50.8322563171],"type":"Point"}
}