{
  "type": "Feature",
  "properties": {
    "addr:full":"Route De Spa 9 Havelange Namur 5372",
    "addr:housenumber":"9",
    "addr:postcode":"5372",
    "addr:street":"Route De Spa",
    "iso:country":"BE",
    "sg:address":"Route De Spa 9",
    "sg:city":"Havelange",
    "sg:orig_category":"G\u00e9om\u00e8tres",
    "sg:phone":"+32 86 32 24 65",
    "sg:postcode":"5372",
    "sg:province":"Namur",
    "wof:name":"Hector Kaye",
    "wof:placetype":"venue"
},
  "geometry": {"coordinates":[5.3338909149,50.3618545532],"type":"Point"}
}