{
  "type": "Feature",
  "properties": {
    "iso:country":"BE",
    "sg:address":"Bruggestraat 190",
    "sg:city":"Beernem",
    "sg:orig_category":"Enseignement secondaire technique and professionnel",
    "sg:phone":"+32 50 35 09 84",
    "sg:postcode":"8730",
    "sg:province":"West-Vlaanderen",
    "wof:name":"Instituut 't Brugse Vrije",
    "wof:placetype":"venue"
},
  "geometry": {"coordinates":[3.3020300865,51.1851196289],"type":"Point"}
}