{
  "type": "Feature",
  "properties": {
    "addr:full":"Rue De M\u00e9rivaux 1a Court-saint-etienne Brabant Wallon 1490",
    "addr:housenumber":"1a;1490",
    "addr:street":"Rue De Me\u0301Rivaux",
    "iso:country":"BE",
    "sg:address":"Rue De M\u00e9rivaux 1a",
    "sg:city":"Court-saint-etienne",
    "sg:classifiers":[
        {
            "category":"Manufacturing",
            "subcategory":"Glass & Minerals",
            "type":"Manufacturing & Wholesale Goods"
        }
    ],
    "sg:phone":"+32 10 61 58 57",
    "sg:postcode":"1490",
    "sg:province":"Brabant Wallon",
    "sg:tags":[
        "safety"
    ],
    "wof:name":"Vitrerie V.g.r. 8 Sprl",
    "wof:placetype":"venue"
},
  "geometry": {"coordinates":[4.5499711037,50.6406021118],"type":"Point"}
}