{
  "type": "Feature",
  "properties": {
    "iso:country":"BE",
    "sg:address":"Rue Boucqueau 13",
    "sg:city":"La Louviere",
    "sg:orig_category":"Editeurs de journaux. Agences d'exp\u00e9dition. Banques de donn\u00e9es. Editeurs de revues and p\u00e9riodiques",
    "sg:phone":"+32 64 22 23 49",
    "sg:postcode":"7100",
    "sg:province":"Hainaut",
    "wof:name":"Chambre Commerce & Ind.",
    "wof:placetype":"venue"
},
  "geometry": {"coordinates":[4.1953649521,50.4817352295],"type":"Point"}
}