{
  "type": "Feature",
  "properties": {
    "iso:country":"BE",
    "sg:address":"Gullegemsestraat 59",
    "sg:city":"Ledegem",
    "sg:orig_category":"M\u00e9decines alternatives",
    "sg:phone":"+32 56 50 94 57",
    "sg:postcode":"8880",
    "sg:province":"West-Vlaanderen",
    "wof:name":"Marian Delecluyse-wyffels",
    "wof:placetype":"venue"
},
  "geometry": {"coordinates":[3.1817789078,50.8734092712],"type":"Point"}
}