{
  "type": "Feature",
  "properties": {
    "addr:full":"Grand'rue 22 Virton Luxembourg 6760",
    "addr:housenumber":"22",
    "addr:postcode":"6760",
    "addr:street":"Grand'Rue",
    "iso:country":"BE",
    "sg:address":"Grand'rue 22",
    "sg:city":"Virton",
    "sg:orig_category":"Schoenen",
    "sg:phone":"+32 63 57 80 71",
    "sg:postcode":"6760",
    "sg:province":"Luxembourg",
    "wof:name":"Maison Junior",
    "wof:placetype":"venue"
},
  "geometry": {"coordinates":[5.5965709686,49.5601654053],"type":"Point"}
}