{
  "type": "Feature",
  "properties": {
    "addr:full":"Dageraadplaats 31 Antwerpen Antwerpen 2018",
    "addr:housenumber":"31",
    "addr:postcode":"2018",
    "addr:street":"Dageraadplaats",
    "iso:country":"BE",
    "sg:address":"Dageraadplaats 31",
    "sg:city":"Antwerpen",
    "sg:orig_category":"Banken and kredietinstellingen",
    "sg:phone":"+32 3 218 67 33",
    "sg:postcode":"2018",
    "sg:province":"Antwerpen",
    "wof:name":"Bacob",
    "wof:placetype":"venue"
},
  "geometry": {"coordinates":[4.4299178123,51.2067642212],"type":"Point"}
}