{
  "type": "Feature",
  "properties": {
    "addr:full":"Rue Des Eglantiers 8 Namur Namur 5100",
    "addr:housenumber":"8",
    "addr:postcode":"5100",
    "addr:street":"Rue Des Eglantiers",
    "iso:country":"BE",
    "sg:address":"Rue Des Eglantiers 8",
    "sg:city":"Namur",
    "sg:orig_category":"Experts-comptables",
    "sg:phone":"+32 81 30 07 21",
    "sg:postcode":"5100",
    "sg:province":"Namur",
    "wof:name":"Guy Lemercinier",
    "wof:placetype":"venue"
},
  "geometry": {"coordinates":[4.8713750839,50.4566345215],"type":"Point"}
}