{
  "type": "Feature",
  "properties": {
    "iso:country":"BE",
    "sg:address":"Kapitein Gilsonplein 20",
    "sg:city":"Aarschot",
    "sg:orig_category":"Advocaten and juridische adviseurs",
    "sg:phone":"+32 16 56 45 12",
    "sg:postcode":"3200",
    "sg:province":"Vlaams-Brabant",
    "wof:name":"Eric Halsband",
    "wof:placetype":"venue"
},
  "geometry": {"coordinates":[4.8242268562,50.9815864563],"type":"Point"}
}