{
  "type": "Feature",
  "properties": {
    "iso:country":"BE",
    "sg:address":"Centre Commerc. Longdoz 50bd",
    "sg:city":"Li\u00c8ge",
    "sg:orig_category":"Bijouteries and horlogeries. R\u00e9parations d'horloges, montres and bijoux",
    "sg:phone":"+32 4 343 86 88",
    "sg:postcode":"4020",
    "sg:province":"Li\u00e8ge",
    "wof:name":"Bijouterie Heuse",
    "wof:placetype":"venue"
},
  "geometry": {"coordinates":[5.5832829475,50.636756897],"type":"Point"}
}