{
  "type": "Feature",
  "properties": {
    "addr:full":"Rue De La Loi 16 Li\u00c8ge Li\u00e8ge 4020",
    "addr:housenumber":"16",
    "addr:postcode":"4020",
    "addr:street":"Rue De La Loi",
    "iso:country":"BE",
    "sg:address":"Rue De La Loi 16",
    "sg:city":"Li\u00c8ge",
    "sg:orig_category":"Diverse bouwinstallaties Verlichtingsapparaten and elektrische lampen Fab",
    "sg:phone":"+32 4 342 48 46",
    "sg:postcode":"4020",
    "sg:province":"Li\u00e8ge",
    "wof:name":"Eva Streveler",
    "wof:placetype":"venue"
},
  "geometry": {"coordinates":[5.5854802132,50.6426048279],"type":"Point"}
}