{
  "type": "Feature",
  "properties": {
    "addr:full":"Gravin Elisabethlaan 1b6 Hoogstraten Antwerpen 2320",
    "addr:housenumber":"1b6",
    "addr:postcode":"2320",
    "addr:street":"Gravin Elisabethlaan",
    "iso:country":"BE",
    "sg:address":"Gravin Elisabethlaan 1b6",
    "sg:city":"Hoogstraten",
    "sg:classifiers":[
        {
            "category":"Professional",
            "subcategory":"Accounting & Tax Preparation",
            "type":"Services"
        }
    ],
    "sg:phone":"+32 3 314 34 10",
    "sg:postcode":"2320",
    "sg:province":"Antwerpen",
    "sg:tags":[
        "bookkeeping"
    ],
    "wof:name":"Vervloet & Compagnie B.v.b.a.",
    "wof:placetype":"venue"
},
  "geometry": {"coordinates":[4.760488987,51.4005012512],"type":"Point"}
}