{
  "type": "Feature",
  "properties": {
    "addr:full":"O.-l.-vrouwekruisstraat 18 Poperinge West-Vlaanderen 8970",
    "addr:housenumber":"18",
    "addr:postcode":"8970",
    "addr:street":"O.-L.-Vrouwekruisstraat",
    "iso:country":"BE",
    "sg:address":"O.-l.-vrouwekruisstraat 18",
    "sg:city":"Poperinge",
    "sg:orig_category":"Instituts pour enfants en difficult\u00e9. Orphelinats",
    "sg:phone":"+32 57 33 85 32",
    "sg:postcode":"8970",
    "sg:province":"West-Vlaanderen",
    "wof:name":"Dagcentrum De Keper",
    "wof:placetype":"venue"
},
  "geometry": {"coordinates":[2.7263898849,50.8555984497],"type":"Point"}
}