{
  "type": "Feature",
  "properties": {
    "iso:country":"BE",
    "sg:address":"Rue \u00b4t Serstevens",
    "sg:city":"Thuin",
    "sg:classifiers":[
        {
            "category":"Shopping",
            "subcategory":"Bicycles & Sporting Goods",
            "type":"Retail Goods"
        }
    ],
    "sg:phone":"+32 71 59 08 61",
    "sg:postcode":"6530",
    "sg:province":"Hainaut",
    "sg:tags":[
        "article",
        "de",
        "sport",
        "camping"
    ],
    "wof:name":"Ets Au Gardon",
    "wof:placetype":"venue"
},
  "geometry": {"coordinates":[4.2841000557,50.3412971497],"type":"Point"}
}