{
  "type": "Feature",
  "properties": {
    "addr:full":"Lindenhoekje 7 Wezembeek-oppem/wezembeek-oppem Vlaams-Brabant 1970",
    "addr:housenumber":"7",
    "addr:postcode":"1970",
    "addr:street":"Lindenhoekje",
    "iso:country":"BE",
    "sg:address":"Lindenhoekje 7",
    "sg:city":"Wezembeek-oppem/wezembeek-oppem",
    "sg:orig_category":"Artsen and specialisten",
    "sg:phone":"+32 2 731 22 88",
    "sg:postcode":"1970",
    "sg:province":"Vlaams-Brabant",
    "wof:name":"Paul Magrez",
    "wof:placetype":"venue"
},
  "geometry": {"coordinates":[4.4794340134,50.8383903503],"type":"Point"}
}