{
  "type": "Feature",
  "properties": {
    "addr:full":"Rue De Tenbosch 45 Bruxelles (ixelles) Bruxelles-Capitale 1050",
    "addr:housenumber":"45",
    "addr:postcode":"1050",
    "addr:street":"Rue De Tenbosch",
    "iso:country":"BE",
    "sg:address":"Rue De Tenbosch 45",
    "sg:city":"Bruxelles (ixelles)",
    "sg:classifiers":[
        {
            "category":"Professional",
            "subcategory":"Lawyer & Legal Services",
            "type":"Services"
        }
    ],
    "sg:phone":"+32 2 647 41 86",
    "sg:postcode":"1050",
    "sg:province":"Bruxelles-Capitale",
    "wof:name":"Gronowski Simon",
    "wof:placetype":"venue"
},
  "geometry": {"coordinates":[4.3644299507,50.8229827881],"type":"Point"}
}