{
  "type": "Feature",
  "properties": {
    "iso:country":"BE",
    "sg:address":"Esplanade 8ab1",
    "sg:city":"Ath",
    "sg:orig_category":"Alternatieve geneeskunde Artsen and specialisten",
    "sg:phone":"+32 68 28 06 18",
    "sg:postcode":"7800",
    "sg:province":"Hainaut",
    "wof:name":"Schol Christian",
    "wof:placetype":"venue"
},
  "geometry": {"coordinates":[3.7805249691,50.631072998],"type":"Point"}
}