{
  "type": "Feature",
  "properties": {
    "addr:full":"Woeringenstraat 12a Nijlen Antwerpen 2560",
    "addr:housenumber":"12a",
    "addr:postcode":"2560",
    "addr:street":"Woeringenstraat",
    "iso:country":"BE",
    "sg:address":"Woeringenstraat 12a",
    "sg:city":"Nijlen",
    "sg:classifiers":[
        {
            "category":"Professional",
            "type":"Services"
        }
    ],
    "sg:phone":"+32 3 385 55 38",
    "sg:postcode":"2560",
    "sg:province":"Antwerpen",
    "sg:tags":[
        "industrial",
        "automation"
    ],
    "wof:name":"Acept Bvba",
    "wof:placetype":"venue"
},
  "geometry": {"coordinates":[4.6738610268,51.1612014771],"type":"Point"}
}