{
  "type": "Feature",
  "properties": {
    "iso:country":"BE",
    "sg:address":"Stijn Streuvelsstraat 43",
    "sg:city":"Beerse",
    "sg:classifiers":[
        {
            "category":"Personal",
            "subcategory":"Beauty Salon",
            "type":"Services"
        }
    ],
    "sg:phone":"+32 14 61 23 82",
    "sg:postcode":"2340",
    "sg:province":"Antwerpen",
    "wof:name":"Isis Bvba",
    "wof:placetype":"venue"
},
  "geometry": {"coordinates":[4.8623690605,51.3193664551],"type":"Point"}
}