{
  "type": "Feature",
  "properties": {
    "addr:full":"Tweelingenstraat 2 Antwerpen Antwerpen 2018",
    "addr:housenumber":"2",
    "addr:postcode":"2018",
    "addr:street":"Tweelingenstraat",
    "iso:country":"BE",
    "sg:address":"Tweelingenstraat 2",
    "sg:city":"Antwerpen",
    "sg:classifiers":[
        {
            "category":"Shopping Center",
            "type":"Public Place"
        }
    ],
    "sg:phone":"+32 3 272 43 78",
    "sg:postcode":"2018",
    "sg:province":"Antwerpen",
    "sg:tags":[
        "enseignement",
        "formation"
    ],
    "wof:name":"Studiecentrum Call & T.",
    "wof:placetype":"venue"
},
  "geometry": {"coordinates":[4.4335680008,51.2070808411],"type":"Point"}
}