{
  "type": "Feature",
  "properties": {
    "iso:country":"BE",
    "sg:address":"Bld De La Sauveni\u00c8re 47",
    "sg:city":"Li\u00c8ge",
    "sg:orig_category":"Tijdelijke werkgelegenheid and uitzendkantoren",
    "sg:phone":"+32 4 223 38 23",
    "sg:postcode":"4000",
    "sg:province":"Li\u00e8ge",
    "wof:name":"Manpower",
    "wof:placetype":"venue"
},
  "geometry": {"coordinates":[5.5674757957,50.6438522339],"type":"Point"}
}