{
  "type": "Feature",
  "properties": {
    "iso:country":"BE",
    "sg:address":"Sint-truidersteenweg 305",
    "sg:city":"Borgloon",
    "sg:classifiers":[
        {
            "category":"Freight",
            "type":"Transportation"
        }
    ],
    "sg:phone":"+32 12 74 14 14",
    "sg:postcode":"3840",
    "sg:province":"Limburg",
    "sg:tags":[
        "-",
        "transport"
    ],
    "wof:name":"Lux Transport Nv",
    "wof:placetype":"venue"
},
  "geometry": {"coordinates":[5.300992012,50.8057174683],"type":"Point"}
}