{
  "type": "Feature",
  "properties": {
    "iso:country":"BE",
    "sg:address":"Peter Benoitstraat 20",
    "sg:city":"Roeselare",
    "sg:classifiers":[
        {
            "category":"Health Services",
            "subcategory":"Health Practitioner",
            "type":"Services"
        }
    ],
    "sg:phone":"+32 51 21 04 20",
    "sg:postcode":"8800",
    "sg:province":"West-Vlaanderen",
    "sg:tags":[
        "physiotherapist"
    ],
    "wof:name":"Vanden Bulcke Kristien",
    "wof:placetype":"venue"
},
  "geometry": {"coordinates":[3.1313610077,50.9370727539],"type":"Point"}
}