{
  "type": "Feature",
  "properties": {
    "iso:country":"BE",
    "sg:address":"Peulisbaan 25a",
    "sg:city":"Bonheiden (rijmenam)",
    "sg:classifiers":[
        {
            "category":"Real Estate",
            "subcategory":"Architect",
            "type":"Services"
        }
    ],
    "sg:phone":"+32 15 51 25 68",
    "sg:postcode":"2820",
    "sg:province":"Antwerpen",
    "wof:name":"Muylaert M",
    "wof:placetype":"venue"
},
  "geometry": {"coordinates":[4.582821846,51.0189361572],"type":"Point"}
}