{
  "type": "Feature",
  "properties": {
    "addr:full":"Poststraat 1 Maarkedal Oost-Vlaanderen 9680",
    "addr:housenumber":"1",
    "addr:postcode":"9680",
    "addr:street":"Poststraat",
    "iso:country":"BE",
    "sg:address":"Poststraat 1",
    "sg:city":"Maarkedal",
    "sg:orig_category":"Assurances. Bureaux de poste",
    "sg:phone":"+32 55 31 27 55",
    "sg:postcode":"9680",
    "sg:province":"Oost-Vlaanderen",
    "wof:name":"De Post",
    "wof:placetype":"venue"
},
  "geometry": {"coordinates":[3.6255331039,50.8131141663],"type":"Point"}
}