{
  "type": "Feature",
  "properties": {
    "addr:full":"Rue Provinciale 60 Wavre (bierges) Brabant Wallon 1301",
    "addr:housenumber":"1301",
    "addr:street":"Rue Provinciale 60",
    "iso:country":"BE",
    "sg:address":"Rue Provinciale 60",
    "sg:city":"Wavre (bierges)",
    "sg:classifiers":[
        {
            "category":"Exhibition Hall",
            "type":"Public Place"
        }
    ],
    "sg:phone":"+32 10 22 72 00",
    "sg:postcode":"1301",
    "sg:province":"Brabant Wallon",
    "sg:tags":[
        "stand"
    ],
    "wof:name":"Connexion",
    "wof:placetype":"venue"
},
  "geometry": {"coordinates":[4.600774765,50.7131309509],"type":"Point"}
}