{
  "type": "Feature",
  "properties": {
    "addr:full":"Avenue De L'informatique 9b Ans Li\u00e8ge 4432",
    "addr:housenumber":"9b",
    "addr:postcode":"4432",
    "addr:street":"Avenue De L'Informatique",
    "iso:country":"BE",
    "sg:address":"Avenue De L'informatique 9b",
    "sg:city":"Ans",
    "sg:orig_category":"Meubles D\u00e9taillants, Am\u00e9nagement de B\u00e2timents et de Cuisines",
    "sg:phone":"+32 4 263 50 50",
    "sg:postcode":"4432",
    "sg:province":"Li\u00e8ge",
    "wof:name":"Paradis Du Matelas",
    "wof:placetype":"venue"
},
  "geometry": {"coordinates":[5.5242800713,50.6659317017],"type":"Point"}
}