{
  "type": "Feature",
  "properties": {
    "addr:full":"Rue Tout-y-faut 69 La Louviere Hainaut 7110",
    "addr:housenumber":"69",
    "addr:postcode":"7110",
    "addr:street":"Rue Tout-Y-Faut",
    "iso:country":"BE",
    "sg:address":"Rue Tout-y-faut 69",
    "sg:city":"La Louviere",
    "sg:orig_category":"Instituts de beaut\u00e9",
    "sg:phone":"+32 64 28 59 85",
    "sg:postcode":"7110",
    "sg:province":"Hainaut",
    "wof:name":"Jean-pol Deblende",
    "wof:placetype":"venue"
},
  "geometry": {"coordinates":[4.1505050659,50.4826698303],"type":"Point"}
}