{
  "type": "Feature",
  "properties": {
    "iso:country":"BE",
    "sg:address":"Clos Des M\u00c9sanges 19",
    "sg:city":"Li\u00c8ge",
    "sg:orig_category":"Ordinateurs and \u00e9quipement informatique",
    "sg:phone":"+32 4 370 21 29",
    "sg:postcode":"4020",
    "sg:province":"Li\u00e8ge",
    "wof:name":"Serial",
    "wof:placetype":"venue"
},
  "geometry": {"coordinates":[5.5559258461,50.6214027405],"type":"Point"}
}