{
  "type": "Feature",
  "properties": {
    "iso:country":"BE",
    "sg:address":"Gentweg 32bb",
    "sg:city":"Herzele",
    "sg:orig_category":"Artsen and specialisten",
    "sg:phone":"+32 54 50 12 17",
    "sg:postcode":"9550",
    "sg:province":"Oost-Vlaanderen",
    "wof:name":"Michael De Vos",
    "wof:placetype":"venue"
},
  "geometry": {"coordinates":[3.8601989746,50.8512763977],"type":"Point"}
}