{
  "type": "Feature",
  "properties": {
    "iso:country":"BE",
    "sg:address":"Krakeleweg 14",
    "sg:city":"Brugge",
    "sg:classifiers":[
        {
            "category":"Utilities",
            "subcategory":"Fuel Oil & Lpg",
            "type":"Services"
        }
    ],
    "sg:phone":"+32 50 31 50 46",
    "sg:postcode":"8000",
    "sg:province":"West-Vlaanderen",
    "wof:name":"Tomar Kolen Bvba",
    "wof:placetype":"venue"
},
  "geometry": {"coordinates":[3.2203600407,51.225769043],"type":"Point"}
}