{
  "type": "Feature",
  "properties": {
    "addr:full":"Pl Andr\u00c9 Renard 3 Amay Li\u00e8ge 4540",
    "addr:housenumber":"3",
    "addr:postcode":"4540",
    "addr:street":"Pl Andre\u0301 Renard",
    "iso:country":"BE",
    "sg:address":"Pl Andr\u00c9 Renard 3",
    "sg:city":"Amay",
    "sg:orig_category":"HUISBRANDOLIE",
    "sg:phone":"+32 85 31 40 27",
    "sg:postcode":"4540",
    "sg:province":"Li\u00e8ge",
    "wof:name":"Maison Jean-luc",
    "wof:placetype":"venue"
},
  "geometry": {"coordinates":[5.314781189,50.5575447083],"type":"Point"}
}