{
  "type": "Feature",
  "properties": {
    "iso:country":"BE",
    "sg:address":"Impasse Leclercq 6",
    "sg:city":"Engis",
    "sg:classifiers":[
        {
            "category":"Building & Trades",
            "subcategory":"Landscaping Services",
            "type":"Services"
        }
    ],
    "sg:phone":"+32 495 18 01 38",
    "sg:postcode":"4480",
    "sg:province":"Li\u00e8ge",
    "sg:tags":[
        "-",
        "lopping",
        "work",
        "tree",
        "felling"
    ],
    "wof:name":"Ferette O",
    "wof:placetype":"venue"
},
  "geometry": {"coordinates":[5.4002299309,50.5810241699],"type":"Point"}
}