{
  "type": "Feature",
  "properties": {
    "iso:country":"BE",
    "sg:address":"Brugseweg 57",
    "sg:city":"Langemark-poelkapelle",
    "sg:classifiers":[
        {
            "category":"Cafe",
            "type":"Food & Drink"
        }
    ],
    "sg:phone":"+32 57 48 85 62",
    "sg:postcode":"8920",
    "sg:province":"West-Vlaanderen",
    "sg:tags":[
        "caf\u00e9s"
    ],
    "wof:name":"Caf\u00c9 Het Paard",
    "wof:placetype":"venue"
},
  "geometry": {"coordinates":[2.9367930889,50.8905029297],"type":"Point"}
}