{
  "type": "Feature",
  "properties": {
    "addr:full":"Rodeborgstraat 74 Schoten Antwerpen 2900",
    "addr:housenumber":"74",
    "addr:postcode":"2900",
    "addr:street":"Rodeborgstraat",
    "iso:country":"BE",
    "sg:address":"Rodeborgstraat 74",
    "sg:city":"Schoten",
    "sg:orig_category":"Producteurs de l\u00e9gumes",
    "sg:phone":"+32 3 658 58 05",
    "sg:postcode":"2900",
    "sg:province":"Antwerpen",
    "wof:name":"Patrick Robeyns",
    "wof:placetype":"venue"
},
  "geometry": {"coordinates":[4.5009489059,51.2540512085],"type":"Point"}
}