{
  "type": "Feature",
  "properties": {
    "iso:country":"BE",
    "sg:address":"Gebroeders Goemaerelaan 50bb",
    "sg:city":"Oudergem/auderghem",
    "sg:orig_category":"Slagers",
    "sg:phone":"+32 2 672 32 72",
    "sg:postcode":"1160",
    "sg:province":"Bruxelles-Capitale",
    "wof:name":"Beenhouwerij William",
    "wof:placetype":"venue"
},
  "geometry": {"coordinates":[4.436147213,50.8108444214],"type":"Point"}
}