{
  "type": "Feature",
  "properties": {
    "addr:full":"Rue Du Bien-faire 12 Watermaal-bosvoorde/watermael-boitsfort Bruxelles-Capitale 1170",
    "addr:housenumber":"12",
    "addr:postcode":"1170",
    "addr:street":"Rue Du Bien-Faire",
    "iso:country":"BE",
    "sg:address":"Rue Du Bien-faire 12",
    "sg:city":"Watermaal-bosvoorde/watermael-boitsfort",
    "sg:orig_category":"Cr\u00e8ches and garderies d'enfants",
    "sg:phone":"+32 2 673 60 06",
    "sg:postcode":"1170",
    "sg:province":"Bruxelles-Capitale",
    "wof:name":"Le Berceau",
    "wof:placetype":"venue"
},
  "geometry": {"coordinates":[4.4020719528,50.8067932129],"type":"Point"}
}