{
  "type": "Feature",
  "properties": {
    "iso:country":"BE",
    "sg:address":"Louis De Brouck\u00c8relaan 70",
    "sg:city":"Ganshoren",
    "sg:orig_category":"Banken and kredietinstellingen",
    "sg:phone":"+32 2 428 86 51",
    "sg:postcode":"1083",
    "sg:province":"Bruxelles-Capitale",
    "wof:name":"Dexia",
    "wof:placetype":"venue"
},
  "geometry": {"coordinates":[4.3173561096,50.8745918274],"type":"Point"}
}