{
  "type": "Feature",
  "properties": {
    "addr:full":"Stenenstraat 28 Kasterlee Antwerpen 2460",
    "addr:housenumber":"28",
    "addr:postcode":"2460",
    "addr:street":"Stenenstraat",
    "iso:country":"BE",
    "sg:address":"Stenenstraat 28",
    "sg:city":"Kasterlee",
    "sg:classifiers":[
        {
            "category":"Travel",
            "subcategory":"Hotels & Motels",
            "type":"Entertainment"
        }
    ],
    "sg:phone":"+32 14 55 19 60",
    "sg:postcode":"2460",
    "sg:province":"Antwerpen",
    "wof:name":"Girasol Logies",
    "wof:placetype":"venue"
},
  "geometry": {"coordinates":[4.9230618477,51.2154464722],"type":"Point"}
}