{
  "type": "Feature",
  "properties": {
    "iso:country":"BE",
    "sg:address":"Zandstraat 102",
    "sg:city":"Dendermonde",
    "sg:orig_category":"Pain, p\u00e2tisseries and confiseries",
    "sg:phone":"+32 52 21 46 28",
    "sg:postcode":"9200",
    "sg:province":"Oost-Vlaanderen",
    "wof:name":"Bakkerij Luka",
    "wof:placetype":"venue"
},
  "geometry": {"coordinates":[4.0657858849,51.0293235779],"type":"Point"}
}