{
  "type": "Feature",
  "properties": {
    "iso:country":"BE",
    "sg:address":"Verschansingstraat 48",
    "sg:city":"Antwerpen",
    "sg:classifiers":[
        {
            "category":"Shopping",
            "subcategory":"Bicycles & Sporting Goods",
            "type":"Retail Goods"
        }
    ],
    "sg:phone":"+32 3 237 82 54",
    "sg:postcode":"2000",
    "sg:province":"Antwerpen",
    "sg:tags":[
        "-"
    ],
    "wof:name":"Fietsdokter",
    "wof:placetype":"venue"
},
  "geometry": {"coordinates":[4.389799118,51.208366394],"type":"Point"}
}