{
  "type": "Feature",
  "properties": {
    "iso:country":"BE",
    "sg:address":"Village 20",
    "sg:city":"Stoumont",
    "sg:orig_category":"Centres de relaxation and bien-\u00eatre. Instituts de beaut\u00e9. Salons de coiffure",
    "sg:phone":"+32 80 78 56 06",
    "sg:postcode":"4987",
    "sg:province":"Li\u00e8ge",
    "wof:name":"Institut Gaspard",
    "wof:placetype":"venue"
},
  "geometry": {"coordinates":[5.8077311516,50.4070968628],"type":"Point"}
}