{
  "type": "Feature",
  "properties": {
    "addr:full":"Terlindenstraat 8 Herne (herfelingen) Vlaams-Brabant 1540",
    "addr:housenumber":"8",
    "addr:postcode":"1540",
    "addr:street":"Terlindenstraat",
    "iso:country":"BE",
    "sg:address":"Terlindenstraat 8",
    "sg:city":"Herne (herfelingen)",
    "sg:classifiers":[
        {
            "category":"Freight",
            "type":"Transportation"
        }
    ],
    "sg:phone":"+32 2 396 22 48",
    "sg:postcode":"1540",
    "sg:province":"Vlaams-Brabant",
    "sg:tags":[
        "-",
        "transport"
    ],
    "wof:name":"Franstrans",
    "wof:placetype":"venue"
},
  "geometry": {"coordinates":[4.0908889771,50.728603363],"type":"Point"}
}