{
  "type": "Feature",
  "properties": {
    "iso:country":"BE",
    "sg:address":"Rue Emile Vandervelde 29",
    "sg:city":"Le Roeulx",
    "sg:classifiers":[
        {
            "category":"Bakery",
            "type":"Food & Drink"
        }
    ],
    "sg:phone":"+32 64 66 21 91",
    "sg:postcode":"7070",
    "sg:province":"Hainaut",
    "sg:tags":[
        "confectioner",
        "baker"
    ],
    "wof:name":"Francois",
    "wof:placetype":"venue"
},
  "geometry": {"coordinates":[4.1097478867,50.5036621094],"type":"Point"}
}