{
  "type": "Feature",
  "properties": {
    "addr:full":"Rue Basse 23 Leuze-en-hainaut (tourpes) Hainaut 7904",
    "addr:housenumber":"23",
    "addr:postcode":"7904",
    "addr:street":"Rue Basse",
    "iso:country":"BE",
    "sg:address":"Rue Basse 23",
    "sg:city":"Leuze-en-hainaut (tourpes)",
    "sg:classifiers":[
        {
            "category":"Sports & Exercise",
            "subcategory":"Skate Park",
            "type":"Entertainment"
        }
    ],
    "sg:phone":"+32 69 67 13 74",
    "sg:postcode":"7904",
    "sg:province":"Hainaut",
    "sg:tags":[
        "mushroom"
    ],
    "wof:name":"Degouis Phytos",
    "wof:placetype":"venue"
},
  "geometry": {"coordinates":[3.6472148895,50.5737266541],"type":"Point"}
}