{
  "type": "Feature",
  "properties": {
    "addr:full":"Mechelsebaan 127 Keerbergen Vlaams-Brabant 3140",
    "addr:housenumber":"127",
    "addr:postcode":"3140",
    "addr:street":"Mechelsebaan",
    "iso:country":"BE",
    "sg:address":"Mechelsebaan 127",
    "sg:city":"Keerbergen",
    "sg:classifiers":[
        {
            "category":"Restaurant",
            "type":"Food & Drink"
        }
    ],
    "sg:phone":"+32 15 51 38 37",
    "sg:postcode":"3140",
    "sg:province":"Vlaams-Brabant",
    "wof:name":"Jan De Volksschilder",
    "wof:placetype":"venue"
},
  "geometry": {"coordinates":[4.606441021,51.0088920593],"type":"Point"}
}