{
  "type": "Feature",
  "properties": {
    "addr:full":"Rue De La Fontaine 16 Vis\u00c9 Li\u00e8ge 4600",
    "addr:housenumber":"16",
    "addr:postcode":"4600",
    "addr:street":"Rue De La Fontaine",
    "iso:country":"BE",
    "sg:address":"Rue De La Fontaine 16",
    "sg:city":"Vis\u00c9",
    "sg:orig_category":"Landmeters and schatters",
    "sg:phone":"+32 4 379 12 58",
    "sg:postcode":"4600",
    "sg:province":"Li\u00e8ge",
    "wof:name":"Robert Sprokkel",
    "wof:placetype":"venue"
},
  "geometry": {"coordinates":[5.6983718872,50.7345733643],"type":"Point"}
}