{
  "type": "Feature",
  "properties": {
    "iso:country":"BE",
    "sg:address":"Helftwinning 4",
    "sg:city":"Sint-martens-latem",
    "sg:classifiers":[
        {
            "category":"Health Services",
            "subcategory":"Doctor",
            "type":"Services"
        }
    ],
    "sg:phone":"+32 9 281 01 87",
    "sg:postcode":"9830",
    "sg:province":"Oost-Vlaanderen",
    "sg:tags":[
        "medicinephysicians",
        "surgeon"
    ],
    "wof:name":"Mahy I",
    "wof:placetype":"venue"
},
  "geometry": {"coordinates":[3.6219890118,51.0315437317],"type":"Point"}
}