{
  "type": "Feature",
  "properties": {
    "addr:full":"Berkendreef 10 Kalmthout Antwerpen 2920",
    "addr:housenumber":"10",
    "addr:postcode":"2920",
    "addr:street":"Berkendreef",
    "iso:country":"BE",
    "sg:address":"Berkendreef 10",
    "sg:city":"Kalmthout",
    "sg:classifiers":[
        {
            "category":"Home & Garden",
            "subcategory":"Home Furnishings",
            "type":"Retail Goods"
        }
    ],
    "sg:phone":"+32 3 666 34 23",
    "sg:postcode":"2920",
    "sg:province":"Antwerpen",
    "sg:tags":[
        "-",
        "furniture"
    ],
    "wof:name":"Gravemaker Belgi\u00eb Bvba",
    "wof:placetype":"venue"
},
  "geometry": {"coordinates":[4.4701809883,51.3684120178],"type":"Point"}
}