{
  "type": "Feature",
  "properties": {
    "iso:country":"BE",
    "sg:address":"Kruisstraat 15",
    "sg:city":"Vleteren",
    "sg:orig_category":"Eleveurs and marchands de porcs. Articles de jardin",
    "sg:phone":"+32 57 40 09 24",
    "sg:postcode":"8640",
    "sg:province":"West-Vlaanderen",
    "wof:name":"Varkenskweek M Pillaert",
    "wof:placetype":"venue"
},
  "geometry": {"coordinates":[2.7010629177,50.9049224854],"type":"Point"}
}