{
  "type": "Feature",
  "properties": {
    "iso:country":"BE",
    "sg:address":"Maastrichterstraat 70",
    "sg:city":"Tongeren",
    "sg:classifiers":[
        {
            "category":"Shopping",
            "subcategory":"Clothing, Apparel, & Fashions",
            "type":"Retail Goods"
        }
    ],
    "sg:phone":"+32 12 23 75 24",
    "sg:postcode":"3700",
    "sg:province":"Limburg",
    "sg:tags":[
        "underwear",
        "lingerie",
        "-"
    ],
    "wof:name":"Vanclee Lingerie Nv",
    "wof:placetype":"venue"
},
  "geometry": {"coordinates":[5.4666619301,50.7824325562],"type":"Point"}
}