{
  "type": "Feature",
  "properties": {
    "addr:full":"Belgradestraat 84b1 Mechelen Antwerpen 2800",
    "addr:housenumber":"84b1",
    "addr:postcode":"2800",
    "addr:street":"Belgradestraat",
    "iso:country":"BE",
    "sg:address":"Belgradestraat 84b1",
    "sg:city":"Mechelen",
    "sg:orig_category":"Plaatsen van vloer- and muurbekleding Schilders",
    "sg:phone":"+32 15 43 08 24",
    "sg:postcode":"2800",
    "sg:province":"Antwerpen",
    "wof:name":"Van Gestel",
    "wof:placetype":"venue"
},
  "geometry": {"coordinates":[4.4764099121,51.0147018433],"type":"Point"}
}