{
  "type": "Feature",
  "properties": {
    "iso:country":"BE",
    "sg:address":"Klaverheide 32",
    "sg:city":"Brasschaat",
    "sg:classifiers":[
        {
            "category":"Arena",
            "subcategory":"Sports Club",
            "type":"Entertainment"
        }
    ],
    "sg:phone":"+32 3 663 47 45",
    "sg:postcode":"2930",
    "sg:province":"Antwerpen",
    "sg:tags":[
        "terrain",
        "hors",
        "de",
        "installation",
        "sportifs"
    ],
    "wof:name":"K. C.m.b.",
    "wof:placetype":"venue"
},
  "geometry": {"coordinates":[4.5047011375,51.3128013611],"type":"Point"}
}