{
  "type": "Feature",
  "properties": {
    "iso:country":"BE",
    "sg:address":"Rue Victor Hugo 168",
    "sg:city":"Schaarbeek/schaerbeek",
    "sg:orig_category":"Production de films, t\u00e9l\u00e9films and vid\u00e9os",
    "sg:phone":"+32 2 734 59 05",
    "sg:postcode":"1030",
    "sg:province":"Bruxelles-Capitale",
    "wof:name":"Jungle",
    "wof:placetype":"venue"
},
  "geometry": {"coordinates":[4.3964829445,50.8494415283],"type":"Point"}
}