{
  "type": "Feature",
  "properties": {
    "iso:country":"BE",
    "sg:address":"Overpoortstraat 43",
    "sg:city":"Gent",
    "sg:classifiers":[
        {
            "category":"Cafe",
            "type":"Food & Drink"
        }
    ],
    "sg:phone":"+32 9 220 53 14",
    "sg:postcode":"9000",
    "sg:province":"Oost-Vlaanderen",
    "sg:tags":[
        "caf\u00e9s"
    ],
    "wof:name":"Caf\u00c9 Abou Simbel",
    "wof:placetype":"venue"
},
  "geometry": {"coordinates":[3.7258269787,51.0397911072],"type":"Point"}
}