{
  "type": "Feature",
  "properties": {
    "addr:full":"Rue Du Chabut 22 Beauvechain Brabant Wallon 1320",
    "addr:housenumber":"22",
    "addr:postcode":"1320",
    "addr:street":"Rue Du Chabut",
    "iso:country":"BE",
    "sg:address":"Rue Du Chabut 22",
    "sg:city":"Beauvechain",
    "sg:orig_category":"M\u00e9decins and sp\u00e9cialistes",
    "sg:phone":"+32 10 86 01 55",
    "sg:postcode":"1320",
    "sg:province":"Brabant Wallon",
    "wof:name":"Yasmine Sere",
    "wof:placetype":"venue"
},
  "geometry": {"coordinates":[4.7220602036,50.7743797302],"type":"Point"}
}