{
  "type": "Feature",
  "properties": {
    "addr:full":"Rue De Jehanster 60 Verviers Li\u00e8ge 4800",
    "addr:housenumber":"60",
    "addr:postcode":"4800",
    "addr:street":"Rue De Jehanster",
    "iso:country":"BE",
    "sg:address":"Rue De Jehanster 60",
    "sg:city":"Verviers",
    "sg:orig_category":"Instituts de beaut\u00e9",
    "sg:phone":"+32 87 22 20 85",
    "sg:postcode":"4800",
    "sg:province":"Li\u00e8ge",
    "wof:name":"Colette Petit",
    "wof:placetype":"venue"
},
  "geometry": {"coordinates":[5.8666157722,50.5846290588],"type":"Point"}
}