{
  "type": "Feature",
  "properties": {
    "addr:full":"Moorselbn 152 Aalst Oost-Vlaanderen 9300",
    "addr:housenumber":"152",
    "addr:postcode":"9300",
    "iso:country":"BE",
    "sg:address":"Moorselbn 152",
    "sg:city":"Aalst",
    "sg:classifiers":[
        {
            "category":"Banks & Credit Unions",
            "subcategory":"Bank",
            "type":"Services"
        }
    ],
    "sg:phone":"+32 53 70 16 00",
    "sg:postcode":"9300",
    "sg:province":"Oost-Vlaanderen",
    "wof:name":"Aslk-cger Bank",
    "wof:placetype":"venue"
},
  "geometry": {"coordinates":[4.0429601669,50.9359741211],"type":"Point"}
}