{
  "type": "Feature",
  "properties": {
    "addr:full":"Meulesteedsesteenweg 328 Gent Oost-Vlaanderen 9000",
    "addr:housenumber":"328",
    "addr:postcode":"9000",
    "addr:street":"Meulesteedsesteenweg;Oost-Vlaanderen",
    "iso:country":"BE",
    "sg:address":"Meulesteedsesteenweg 328",
    "sg:city":"Gent",
    "sg:classifiers":[
        {
            "category":"Freight",
            "type":"Transportation"
        }
    ],
    "sg:phone":"+32 9 251 04 93",
    "sg:postcode":"9000",
    "sg:province":"Oost-Vlaanderen",
    "sg:tags":[
        "-",
        "transport"
    ],
    "wof:name":"Schouls Bvba",
    "wof:placetype":"venue"
},
  "geometry": {"coordinates":[3.7288649082,51.0811347961],"type":"Point"}
}