{
  "type": "Feature",
  "properties": {
    "addr:full":"Vredelaan 17 Kortrijk West-Vlaanderen 8500",
    "addr:housenumber":"17",
    "addr:postcode":"8500",
    "addr:street":"Vredelaan",
    "iso:country":"BE",
    "sg:address":"Vredelaan 17",
    "sg:city":"Kortrijk",
    "sg:orig_category":"Parfumeries",
    "sg:phone":"+32 56 21 70 63",
    "sg:postcode":"8500",
    "sg:province":"West-Vlaanderen",
    "wof:name":"Rita Algoet",
    "wof:placetype":"venue"
},
  "geometry": {"coordinates":[3.2871589661,50.8292808533],"type":"Point"}
}