{
  "type": "Feature",
  "properties": {
    "iso:country":"BE",
    "sg:address":"Rue De Bassine 3",
    "sg:city":"Somme-leuze",
    "sg:orig_category":"Voedingsspeciaalzaken",
    "sg:phone":"+32 86 34 47 19",
    "sg:postcode":"5377",
    "sg:province":"Namur",
    "wof:name":"Jean-benoit Attout",
    "wof:placetype":"venue"
},
  "geometry": {"coordinates":[5.3698949814,50.3404350281],"type":"Point"}
}