{
  "type": "Feature",
  "properties": {
    "addr:full":"Eredienststraat 25 Brussel/bruxelles Bruxelles-Capitale 1000",
    "addr:housenumber":"25",
    "addr:postcode":"1000",
    "addr:street":"Eredienststraat;/",
    "iso:country":"BE",
    "sg:address":"Eredienststraat 25",
    "sg:city":"Brussel/bruxelles",
    "sg:orig_category":"Bloemen and planten",
    "sg:phone":"+32 2 218 34 16",
    "sg:postcode":"1000",
    "sg:province":"Bruxelles-Capitale",
    "wof:name":"Michel",
    "wof:placetype":"venue"
},
  "geometry": {"coordinates":[4.367705822,50.8501930237],"type":"Point"}
}