{
  "type": "Feature",
  "properties": {
    "addr:full":"Pleintje 10 Kasterlee (tielen) Antwerpen 2460",
    "addr:housenumber":"10",
    "addr:postcode":"2460",
    "addr:street":"Pleintje",
    "iso:country":"BE",
    "sg:address":"Pleintje 10",
    "sg:city":"Kasterlee (tielen)",
    "sg:classifiers":[
        {
            "category":"Manufacturing",
            "subcategory":"Leather Goods",
            "type":"Manufacturing & Wholesale Goods"
        }
    ],
    "sg:phone":"+32 14 55 65 66",
    "sg:postcode":"2460",
    "sg:province":"Antwerpen",
    "sg:tags":[
        "repair",
        "buckskin",
        "-",
        "fur",
        "cleaning"
    ],
    "wof:name":"Pw Products Bvba",
    "wof:placetype":"venue"
},
  "geometry": {"coordinates":[4.9016551971,51.250087738],"type":"Point"}
}