{
  "type": "Feature",
  "properties": {
    "addr:full":"Rue D'acquegn\u00e9e 36 Silly (fouleng) Hainaut 7830",
    "addr:housenumber":"36",
    "addr:postcode":"7830",
    "addr:street":"Rue D'Acquegne \u0301E",
    "iso:country":"BE",
    "sg:address":"Rue D'acquegn\u00e9e 36",
    "sg:city":"Silly (fouleng)",
    "sg:classifiers":[
        {
            "category":"Professional",
            "subcategory":"Art Services",
            "type":"Services"
        }
    ],
    "sg:phone":"+32 68 55 11 09",
    "sg:postcode":"7830",
    "sg:province":"Hainaut",
    "sg:tags":[
        "-",
        "painter",
        "artist"
    ],
    "wof:name":"Hebrant R",
    "wof:placetype":"venue"
},
  "geometry": {"coordinates":[3.9422869682,50.6217422485],"type":"Point"}
}