{
  "type": "Feature",
  "properties": {
    "iso:country":"BE",
    "sg:address":"Rue Des Combattants 4",
    "sg:city":"Vielsalm",
    "sg:classifiers":[
        {
            "category":"Government",
            "subcategory":"Department Of Motor Vehicles",
            "type":"Public Place"
        }
    ],
    "sg:phone":"+32 80 21 70 36",
    "sg:postcode":"6690",
    "sg:province":"Luxembourg",
    "sg:tags":[
        "planing",
        "wood",
        "sawing"
    ],
    "wof:name":"Fourcon J",
    "wof:placetype":"venue"
},
  "geometry": {"coordinates":[5.9188351631,50.2843284607],"type":"Point"}
}