{
  "type": "Feature",
  "properties": {
    "addr:full":"Zandvoordeplaats 7 Zonnebeke (zandvoorde) West-Vlaanderen 8980",
    "addr:housenumber":"7",
    "addr:postcode":"8980",
    "addr:street":"Zandvoordeplaats",
    "iso:country":"BE",
    "sg:address":"Zandvoordeplaats 7",
    "sg:city":"Zonnebeke (zandvoorde)",
    "sg:classifiers":[
        {
            "category":"Retail",
            "subcategory":"Veterinary Services",
            "type":"Services"
        }
    ],
    "sg:phone":"+32 57 46 66 24",
    "sg:postcode":"8980",
    "sg:province":"West-Vlaanderen",
    "sg:tags":[
        "veterinarian"
    ],
    "wof:name":"Desaele N",
    "wof:placetype":"venue"
},
  "geometry": {"coordinates":[2.9872550964,50.8730812073],"type":"Point"}
}