{
  "type": "Feature",
  "properties": {
    "addr:full":"Avenue Du Pont De Warche 7 Malmedy Li\u00e8ge 4960",
    "addr:housenumber":"7",
    "addr:postcode":"4960",
    "addr:street":"Avenue Du Pont De Warche",
    "iso:country":"BE",
    "sg:address":"Avenue Du Pont De Warche 7",
    "sg:city":"Malmedy",
    "sg:classifiers":[
        {
            "category":"Retail",
            "subcategory":"Auto Repair",
            "type":"Services"
        }
    ],
    "sg:phone":"+32 80 33 82 75",
    "sg:postcode":"4960",
    "sg:province":"Li\u00e8ge",
    "sg:tags":[
        "garage"
    ],
    "wof:name":"Districar Sa",
    "wof:placetype":"venue"
},
  "geometry": {"coordinates":[6.0048971176,50.4185142517],"type":"Point"}
}