{
  "type": "Feature",
  "properties": {
    "addr:full":"Noordlaan 1 Zwalm Oost-Vlaanderen 9630",
    "addr:housenumber":"1",
    "addr:postcode":"9630",
    "addr:street":"Noordlaan;Oost-Vlaanderen",
    "iso:country":"BE",
    "sg:address":"Noordlaan 1",
    "sg:city":"Zwalm",
    "sg:orig_category":"Verhuur bouwmachines Verhuur doe-het-zelf materiaal",
    "sg:phone":"+32 55 49 60 56",
    "sg:postcode":"9630",
    "sg:province":"Oost-Vlaanderen",
    "wof:name":"All-pas",
    "wof:placetype":"venue"
},
  "geometry": {"coordinates":[3.7346909046,50.8812026978],"type":"Point"}
}