{
  "type": "Feature",
  "properties": {
    "addr:full":"Koningin Astridlaan 278 Kraainem/kraainem Vlaams-Brabant 1950",
    "addr:housenumber":"278",
    "addr:postcode":"1950",
    "addr:street":"Koningin Astridlaan",
    "iso:country":"BE",
    "sg:address":"Koningin Astridlaan 278",
    "sg:city":"Kraainem/kraainem",
    "sg:orig_category":"Postkantoren Verzekeringsmakelaars and experts",
    "sg:phone":"+32 2 731 11 02",
    "sg:postcode":"1950",
    "sg:province":"Vlaams-Brabant",
    "wof:name":"De Post",
    "wof:placetype":"venue"
},
  "geometry": {"coordinates":[4.4664011002,50.8481636047],"type":"Point"}
}