{
  "type": "Feature",
  "properties": {
    "iso:country":"BE",
    "sg:address":"Ti\u00e8ge 3b",
    "sg:city":"Jalhay (sart)",
    "sg:classifiers":[
        {
            "category":"Wholesale",
            "subcategory":"Beer",
            "type":"Manufacturing & Wholesale Goods"
        }
    ],
    "sg:phone":"+32 87 47 45 14",
    "sg:postcode":"4845",
    "sg:province":"Li\u00e8ge",
    "sg:tags":[
        "ale",
        "-"
    ],
    "wof:name":"Michel J & Fils Sa",
    "wof:placetype":"venue"
},
  "geometry": {"coordinates":[5.9165430069,50.5176582336],"type":"Point"}
}