{
  "type": "Feature",
  "properties": {
    "iso:country":"BE",
    "sg:address":"Rue Parmentier 5",
    "sg:city":"Rebecq",
    "sg:orig_category":"Kinderopvang",
    "sg:phone":"+32 67 63 74 71",
    "sg:postcode":"1430",
    "sg:province":"Brabant Wallon",
    "wof:name":"Cr\u00c8che Lucr\u00c8ce & Louisa",
    "wof:placetype":"venue"
},
  "geometry": {"coordinates":[4.1341657639,50.6653442383],"type":"Point"}
}