{
  "type": "Feature",
  "properties": {
    "addr:full":"Stroomstraat 60 Assenede Oost-Vlaanderen 9968",
    "addr:housenumber":"60",
    "addr:postcode":"9968",
    "addr:street":"Stroomstraat",
    "iso:country":"BE",
    "sg:address":"Stroomstraat 60",
    "sg:city":"Assenede",
    "sg:classifiers":[
        {
            "category":"Insurance",
            "subcategory":"Life Insurance",
            "type":"Services"
        }
    ],
    "sg:phone":"+32 9 373 77 66",
    "sg:postcode":"9968",
    "sg:province":"Oost-Vlaanderen",
    "sg:tags":[
        "assurance"
    ],
    "wof:name":"H. De Weweire",
    "wof:placetype":"venue"
},
  "geometry": {"coordinates":[3.6885509491,51.197467804],"type":"Point"}
}