{
  "type": "Feature",
  "properties": {
    "iso:country":"BE",
    "sg:address":"Fauvillers-centre 40",
    "sg:city":"Fauvillers",
    "sg:classifiers":[
        {
            "category":"Cafe",
            "type":"Food & Drink"
        }
    ],
    "sg:phone":"+32 63 60 01 93",
    "sg:postcode":"6637",
    "sg:province":"Luxembourg",
    "sg:tags":[
        "caf\u00e9s"
    ],
    "wof:name":"Eldo-club",
    "wof:placetype":"venue"
},
  "geometry": {"coordinates":[5.6688861847,49.8497962952],"type":"Point"}
}