{
  "type": "Feature",
  "properties": {
    "iso:country":"BE",
    "sg:address":"Rue Morboisa 3",
    "sg:city":"Viroinval",
    "sg:orig_category":"Elektrische installaties voor woningen",
    "sg:phone":"+32 60 39 02 07",
    "sg:postcode":"5670",
    "sg:province":"Namur",
    "wof:name":"Jean-paul Michel",
    "wof:placetype":"venue"
},
  "geometry": {"coordinates":[4.6358728409,50.0237503052],"type":"Point"}
}