{
  "type": "Feature",
  "properties": {
    "addr:full":"Molenstraat 3 Zelzate Oost-Vlaanderen 9060",
    "addr:housenumber":"3",
    "addr:postcode":"9060",
    "addr:street":"Molenstraat",
    "iso:country":"BE",
    "sg:address":"Molenstraat 3",
    "sg:city":"Zelzate",
    "sg:classifiers":[
        {
            "category":"Home & Garden",
            "subcategory":"Carpets & Floor Coverings",
            "type":"Retail Goods"
        }
    ],
    "sg:phone":"+32 9 344 80 21",
    "sg:postcode":"9060",
    "sg:province":"Oost-Vlaanderen",
    "sg:tags":[
        "parquet"
    ],
    "wof:name":"Mogensen Steven",
    "wof:placetype":"venue"
},
  "geometry": {"coordinates":[3.7775509357,51.2007217407],"type":"Point"}
}