{
  "type": "Feature",
  "properties": {
    "addr:full":"Vianeplein 0 Geraardsbergen Oost-Vlaanderen 9500",
    "addr:housenumber":"0",
    "addr:postcode":"9500",
    "addr:street":"Vianeplein",
    "iso:country":"BE",
    "sg:address":"Vianeplein 0",
    "sg:city":"Geraardsbergen",
    "sg:orig_category":"Enseignement maternel and primaire",
    "sg:phone":"+32 54 58 02 42",
    "sg:postcode":"9500",
    "sg:province":"Oost-Vlaanderen",
    "wof:name":"Vrije Basisschool",
    "wof:placetype":"venue"
},
  "geometry": {"coordinates":[3.9231600761,50.743686676],"type":"Point"}
}