{
  "type": "Feature",
  "properties": {
    "addr:full":"Rue Des Cotillages 50 Seraing (ougr\u00e9e) Li\u00e8ge 4102",
    "addr:housenumber":"50",
    "addr:postcode":"4102",
    "addr:street":"Rue Des Cotillages",
    "iso:country":"BE",
    "sg:address":"Rue Des Cotillages 50",
    "sg:city":"Seraing (ougr\u00e9e)",
    "sg:classifiers":[
        {
            "category":"Professional",
            "subcategory":"Management & Consulting",
            "type":"Services"
        }
    ],
    "sg:phone":"+32 4 336 09 30",
    "sg:postcode":"4102",
    "sg:province":"Li\u00e8ge",
    "sg:tags":[
        "consultant",
        "law"
    ],
    "wof:name":"C.v.a.",
    "wof:placetype":"venue"
},
  "geometry": {"coordinates":[5.5371379852,50.5968399048],"type":"Point"}
}