{
  "type": "Feature",
  "properties": {
    "addr:full":"F\u00c9ronstr\u00c9e 112 Li\u00c8ge Li\u00e8ge 4000",
    "addr:housenumber":"112",
    "addr:postcode":"4000",
    "addr:street":"Fe\u0301Ronstre\u0301E",
    "iso:country":"BE",
    "sg:address":"F\u00c9ronstr\u00c9e 112",
    "sg:city":"Li\u00c8ge",
    "sg:classifiers":[
        {
            "category":"Cafe",
            "type":"Food & Drink"
        }
    ],
    "sg:phone":"+32 4 223 13 64",
    "sg:postcode":"4000",
    "sg:province":"Li\u00e8ge",
    "sg:tags":[
        "caf\u00e9s"
    ],
    "wof:name":"Caf\u00c9 St.gregory",
    "wof:placetype":"venue"
},
  "geometry": {"coordinates":[5.5817098618,50.6469116211],"type":"Point"}
}