{
  "type": "Feature",
  "properties": {
    "iso:country":"BE",
    "sg:address":"Rue Paye \u00e0 Fait 18",
    "sg:city":"Froidchapelle",
    "sg:classifiers":[
        {
            "category":"Building & Trades",
            "subcategory":"Pest Control",
            "type":"Services"
        }
    ],
    "sg:phone":"+32 60 41 26 81",
    "sg:postcode":"6440",
    "sg:province":"Hainaut",
    "sg:tags":[
        "painting",
        "contractor"
    ],
    "wof:name":"Demat G",
    "wof:placetype":"venue"
},
  "geometry": {"coordinates":[4.3369350433,50.1545028687],"type":"Point"}
}