{
  "type": "Feature",
  "properties": {
    "iso:country":"BE",
    "sg:address":"Place De Helmet 9",
    "sg:city":"Bruxelles (schaerbeek)",
    "sg:classifiers":[
        {
            "category":"Shopping",
            "subcategory":"Books",
            "type":"Retail Goods"
        }
    ],
    "sg:phone":"+32 2 242 01 45",
    "sg:postcode":"1030",
    "sg:province":"Bruxelles-Capitale",
    "sg:tags":[
        "bookseller"
    ],
    "wof:name":"Librairie De Helmet",
    "wof:placetype":"venue"
},
  "geometry": {"coordinates":[4.3895478249,50.8725967407],"type":"Point"}
}