{
  "type": "Feature",
  "properties": {
    "addr:full":"Rue De La Joncqui\u00c8re 19 Courcelles Hainaut 6180",
    "addr:housenumber":"19",
    "addr:postcode":"6180",
    "addr:street":"Rue De La Joncquie\u0300Re",
    "iso:country":"BE",
    "sg:address":"Rue De La Joncqui\u00c8re 19",
    "sg:city":"Courcelles",
    "sg:orig_category":"Epiceries",
    "sg:phone":"+32 71 45 28 32",
    "sg:postcode":"6180",
    "sg:province":"Hainaut",
    "wof:name":"Andre Normant",
    "wof:placetype":"venue"
},
  "geometry": {"coordinates":[4.3702750206,50.4599761963],"type":"Point"}
}