{
  "type": "Feature",
  "properties": {
    "addr:full":"Franklin Rooseveltlaan 106b5 Vilvoorde Vlaams-Brabant 1800",
    "addr:housenumber":"106b5",
    "addr:postcode":"1800",
    "addr:street":"Franklin Rooseveltlaan",
    "iso:country":"BE",
    "sg:address":"Franklin Rooseveltlaan 106b5",
    "sg:city":"Vilvoorde",
    "sg:orig_category":"Supermarkten",
    "sg:postcode":"1800",
    "sg:province":"Vlaams-Brabant",
    "wof:name":"Aldi",
    "wof:placetype":"venue"
},
  "geometry": {"coordinates":[4.4246912003,50.9311637878],"type":"Point"}
}