{
  "type": "Feature",
  "properties": {
    "iso:country":"BE",
    "sg:address":"Kloosterveldstraat 9",
    "sg:city":"Heist-op-den-berg (booischot)",
    "sg:classifiers":[
        {
            "category":"Sports & Exercise",
            "subcategory":"Gym",
            "type":"Entertainment"
        }
    ],
    "sg:phone":"+32 15 22 44 16",
    "sg:postcode":"2221",
    "sg:province":"Antwerpen",
    "sg:tags":[
        "fitness"
    ],
    "wof:name":"Prisma Sport- & Ontspanningscenter Bvba",
    "wof:placetype":"venue"
},
  "geometry": {"coordinates":[4.7739758492,51.0512428284],"type":"Point"}
}