{
  "type": "Feature",
  "properties": {
    "iso:country":"BE",
    "sg:address":"Rue Du R\u00c9servoir 13",
    "sg:city":"Court-saint-etienne",
    "sg:orig_category":"Artsen and specialisten",
    "sg:phone":"+32 10 61 56 09",
    "sg:postcode":"1490",
    "sg:province":"Brabant Wallon",
    "wof:name":"Dani\u00c8le Vermeylen",
    "wof:placetype":"venue"
},
  "geometry": {"coordinates":[4.5612611771,50.615146637],"type":"Point"}
}