{
  "type": "Feature",
  "properties": {
    "iso:country":"BE",
    "sg:address":"Graaf De Smet De Naeyerlaan 11",
    "sg:city":"Oostende",
    "sg:classifiers":[
        {
            "category":"Personal",
            "subcategory":"Beauty Salon",
            "type":"Services"
        }
    ],
    "sg:phone":"+32 59 50 34 81",
    "sg:postcode":"8400",
    "sg:province":"West-Vlaanderen",
    "sg:tags":[
        "lady",
        "-",
        "hairdressing"
    ],
    "wof:name":"Nadine",
    "wof:placetype":"venue"
},
  "geometry": {"coordinates":[2.9233629704,51.2261199951],"type":"Point"}
}