{
  "type": "Feature",
  "properties": {
    "addr:full":"Schouterveld 40a Hasselt (kuringen) Limburg 3511",
    "addr:housenumber":"40a",
    "addr:postcode":"3511",
    "addr:street":"Schouterveld",
    "iso:country":"BE",
    "sg:address":"Schouterveld 40a",
    "sg:city":"Hasselt (kuringen)",
    "sg:classifiers":[
        {
            "category":"Parking",
            "subcategory":"Lot",
            "type":"Transportation"
        }
    ],
    "sg:phone":"+32 11 25 08 87",
    "sg:postcode":"3511",
    "sg:province":"Limburg",
    "sg:tags":[
        "parking-places",
        "laying-out"
    ],
    "wof:name":"Leers Roger",
    "wof:placetype":"venue"
},
  "geometry": {"coordinates":[5.3034238815,50.9432487488],"type":"Point"}
}