{
  "type": "Feature",
  "properties": {
    "iso:country":"BE",
    "sg:address":"Rue Jules Carlier 16",
    "sg:city":"Courcelles (souvret)",
    "sg:classifiers":[
        {
            "category":"Bars & Pubs",
            "type":"Food & Drink"
        }
    ],
    "sg:phone":"+32 71 45 02 83",
    "sg:postcode":"6182",
    "sg:province":"Hainaut",
    "wof:name":"Garage (du)",
    "wof:placetype":"venue"
},
  "geometry": {"coordinates":[4.3510861397,50.4507751465],"type":"Point"}
}