{
  "type": "Feature",
  "properties": {
    "iso:country":"BE",
    "sg:address":"Rue D'elvaux 17",
    "sg:city":"Herve",
    "sg:classifiers":[
        {
            "category":"Education",
            "subcategory":"School",
            "type":"Public Place"
        }
    ],
    "sg:phone":"+32 87 67 41 37",
    "sg:postcode":"4650",
    "sg:province":"Li\u00e8ge",
    "sg:tags":[
        "secondary"
    ],
    "wof:name":"Coll\u00e8ge Royal Marie-th\u00e8r\u00e8se",
    "wof:placetype":"venue"
},
  "geometry": {"coordinates":[5.7948989868,50.6387443542],"type":"Point"}
}