{
  "type": "Feature",
  "properties": {
    "addr:full":"Oude Beurs 3 Antwerpen Antwerpen 2000",
    "addr:housenumber":"3",
    "addr:postcode":"2000",
    "addr:street":"Oude Beurs",
    "iso:country":"BE",
    "sg:address":"Oude Beurs 3",
    "sg:city":"Antwerpen",
    "sg:orig_category":"Tabac. Journaux",
    "sg:phone":"+32 3 232 25 86",
    "sg:postcode":"2000",
    "sg:province":"Antwerpen",
    "wof:name":"Ruckers",
    "wof:placetype":"venue"
},
  "geometry": {"coordinates":[4.3999929428,51.2222328186],"type":"Point"}
}