{
  "type": "Feature",
  "properties": {
    "addr:full":"Rue Du Centre 33 Sprimont Li\u00e8ge 4140",
    "addr:housenumber":"33",
    "addr:postcode":"4140",
    "addr:street":"Rue Du Centre",
    "iso:country":"BE",
    "sg:address":"Rue Du Centre 33",
    "sg:city":"Sprimont",
    "sg:orig_category":"R\u00e9parations d'horloges, montres and bijoux. Bijouteries and horlogeries",
    "sg:phone":"+32 4 382 14 29",
    "sg:postcode":"4140",
    "sg:province":"Li\u00e8ge",
    "wof:name":"Bijouterie - Horlogerie Pierre",
    "wof:placetype":"venue"
},
  "geometry": {"coordinates":[5.6617832184,50.5067253113],"type":"Point"}
}