{
  "type": "Feature",
  "properties": {
    "addr:full":"Glazenleeuwstraat 15 Beveren Oost-Vlaanderen 9120",
    "addr:housenumber":"15",
    "addr:postcode":"9120",
    "addr:street":"Glazenleeuwstraat",
    "iso:country":"BE",
    "sg:address":"Glazenleeuwstraat 15",
    "sg:city":"Beveren",
    "sg:orig_category":"Advocaten and juridische adviseurs",
    "sg:phone":"+32 3 755 35 96",
    "sg:postcode":"9120",
    "sg:province":"Oost-Vlaanderen",
    "wof:name":"Guy Scheers",
    "wof:placetype":"venue"
},
  "geometry": {"coordinates":[4.2491359711,51.2175712585],"type":"Point"}
}