{
  "type": "Feature",
  "properties": {
    "iso:country":"BE",
    "sg:address":"Rue De L'incroyable 122",
    "sg:city":"Colfontaine",
    "sg:orig_category":"Epiceries",
    "sg:phone":"+32 65 66 83 71",
    "sg:postcode":"7340",
    "sg:province":"Hainaut",
    "wof:name":"Louis Delhaize",
    "wof:placetype":"venue"
},
  "geometry": {"coordinates":[3.8547580242,50.4106826782],"type":"Point"}
}