{
  "type": "Feature",
  "properties": {
    "addr:full":"Anspachlaan 67 Brussel/bruxelles Bruxelles-Capitale 1000",
    "addr:housenumber":"67",
    "addr:postcode":"1000",
    "addr:street":"Anspachlaan;/",
    "iso:country":"BE",
    "sg:address":"Anspachlaan 67",
    "sg:city":"Brussel/bruxelles",
    "sg:orig_category":"Krantenwinkels Rookartikelen",
    "sg:phone":"+32 2 511 11 22",
    "sg:postcode":"1000",
    "sg:province":"Bruxelles-Capitale",
    "wof:name":"City Press Center",
    "wof:placetype":"venue"
},
  "geometry": {"coordinates":[4.3498930931,50.8488197327],"type":"Point"}
}