{
  "type": "Feature",
  "properties": {
    "iso:country":"BE",
    "sg:address":"Sandstrasse 82",
    "sg:city":"Lontzen (walhorn)",
    "sg:classifiers":[
        {
            "category":"Personal",
            "subcategory":"Beauty Salon",
            "type":"Services"
        }
    ],
    "sg:phone":"+32 87 85 00 08",
    "sg:postcode":"4711",
    "sg:province":"Li\u00e8ge",
    "wof:name":"Kosmetik Ruth Burtscheidt",
    "wof:placetype":"venue"
},
  "geometry": {"coordinates":[6.0599379539,50.6781463623],"type":"Point"}
}