{
  "type": "Feature",
  "properties": {
    "iso:country":"BE",
    "sg:address":"Chauss\u00e9e D'ath 104",
    "sg:city":"Enghien (marcq)",
    "sg:classifiers":[
        {
            "category":"Home & Garden",
            "subcategory":"Carpets & Floor Coverings",
            "type":"Retail Goods"
        }
    ],
    "sg:phone":"+32 2 395 45 40",
    "sg:postcode":"7850",
    "sg:province":"Hainaut",
    "sg:tags":[
        "tile"
    ],
    "wof:name":"Degreve C",
    "wof:placetype":"venue"
},
  "geometry": {"coordinates":[4.0172281265,50.6876564026],"type":"Point"}
}