{
  "type": "Feature",
  "properties": {
    "addr:full":"Pitantiestraat 74-76 Waregem (desselgem) West-Vlaanderen 8792",
    "addr:postcode":"74-76;8792",
    "addr:street":"Pitantiestraat",
    "iso:country":"BE",
    "sg:address":"Pitantiestraat 74-76",
    "sg:city":"Waregem (desselgem)",
    "sg:classifiers":[
        {
            "category":"Home & Garden",
            "subcategory":"Carpets & Floor Coverings",
            "type":"Retail Goods"
        }
    ],
    "sg:phone":"+32 56 73 94 80",
    "sg:postcode":"8792",
    "sg:province":"West-Vlaanderen",
    "sg:tags":[
        "parquet"
    ],
    "wof:name":"Flexura Nv",
    "wof:placetype":"venue"
},
  "geometry": {"coordinates":[3.3729979992,50.8935699463],"type":"Point"}
}