{
  "type": "Feature",
  "properties": {
    "iso:country":"BE",
    "sg:address":"Poperingseweg 210",
    "sg:city":"Ieper",
    "sg:orig_category":"Banques and organismes de cr\u00e9dit",
    "sg:phone":"+32 57 20 37 98",
    "sg:postcode":"8908",
    "sg:province":"West-Vlaanderen",
    "wof:name":"Kbc",
    "wof:placetype":"venue"
},
  "geometry": {"coordinates":[2.8244519234,50.8537445068],"type":"Point"}
}