{
  "type": "Feature",
  "properties": {
    "addr:full":"Dorp 23 Olen Antwerpen 2250",
    "addr:housenumber":"23",
    "addr:postcode":"2250",
    "addr:street":"Dorp",
    "iso:country":"BE",
    "sg:address":"Dorp 23",
    "sg:city":"Olen",
    "sg:classifiers":[
        {
            "category":"Insurance",
            "subcategory":"Insurance Agent",
            "type":"Services"
        }
    ],
    "sg:phone":"+32 14 26 67 34",
    "sg:postcode":"2250",
    "sg:province":"Antwerpen",
    "sg:tags":[
        "broker"
    ],
    "wof:name":"Gebruers-schroven",
    "wof:placetype":"venue"
},
  "geometry": {"coordinates":[4.8598937988,51.1455612183],"type":"Point"}
}