{
  "type": "Feature",
  "properties": {
    "iso:country":"BE",
    "sg:address":"Peter Benoitstraat 14",
    "sg:city":"Anzegem (vichte)",
    "sg:classifiers":[
        {
            "category":"Autos & Motor Vehicles",
            "subcategory":"Automobile Sales",
            "type":"Retail Goods"
        }
    ],
    "sg:phone":"+32 56 77 82 26",
    "sg:postcode":"8570",
    "sg:province":"West-Vlaanderen",
    "sg:tags":[
        "motorhomes",
        "accessory"
    ],
    "wof:name":"Elvee",
    "wof:placetype":"venue"
},
  "geometry": {"coordinates":[3.4115068913,50.8317451477],"type":"Point"}
}