{
  "type": "Feature",
  "properties": {
    "addr:full":"Spoorstraat 9 Genk Limburg 3600",
    "addr:housenumber":"9",
    "addr:postcode":"3600",
    "addr:street":"Spoorstraat",
    "iso:country":"BE",
    "sg:address":"Spoorstraat 9",
    "sg:city":"Genk",
    "sg:orig_category":"Artiesten and kunstenaars",
    "sg:phone":"+32 89 35 61 81",
    "sg:postcode":"3600",
    "sg:province":"Limburg",
    "wof:name":"Bessemans",
    "wof:placetype":"venue"
},
  "geometry": {"coordinates":[5.4421257973,50.9634056091],"type":"Point"}
}