{
  "type": "Feature",
  "properties": {
    "addr:full":"Kroonstraat 61 Beverlo Limburg 3581",
    "addr:housenumber":"61",
    "addr:postcode":"3581",
    "addr:street":"Kroonstraat",
    "iso:country":"BE",
    "sg:address":"Kroonstraat 61",
    "sg:city":"Beverlo",
    "sg:classifiers":[
        {
            "category":"Organizations",
            "subcategory":"Non-profit Organization",
            "type":"Services"
        }
    ],
    "sg:phone":"+32 11 34 13 91",
    "sg:postcode":"3581",
    "sg:province":"Limburg",
    "sg:tags":[
        "geothermal",
        "heating",
        "system"
    ],
    "wof:name":"Danio & Partners Nv",
    "wof:placetype":"venue"
},
  "geometry": {"coordinates":[5.2514081001,51.0888671875],"type":"Point"}
}