{
  "type": "Feature",
  "properties": {
    "addr:full":"Steenstraat 69 Brugge West-Vlaanderen 8000",
    "addr:housenumber":"69",
    "addr:postcode":"8000",
    "addr:street":"Steenstraat",
    "iso:country":"BE",
    "sg:address":"Steenstraat 69",
    "sg:city":"Brugge",
    "sg:orig_category":"Krantenuitgeverijen Tijdschriftenuitgeverijen",
    "sg:phone":"+32 50 34 57 75",
    "sg:postcode":"8000",
    "sg:province":"West-Vlaanderen",
    "wof:name":"Fa. Tips",
    "wof:placetype":"venue"
},
  "geometry": {"coordinates":[3.2219219208,51.2062950134],"type":"Point"}
}