{
  "type": "Feature",
  "properties": {
    "iso:country":"BE",
    "sg:address":"Vloeiende 136",
    "sg:city":"Kapellen",
    "sg:orig_category":"M\u00e9decins and sp\u00e9cialistes",
    "sg:phone":"+32 3 605 52 50",
    "sg:postcode":"2950",
    "sg:province":"Antwerpen",
    "wof:name":"Dirk Peeters",
    "wof:placetype":"venue"
},
  "geometry": {"coordinates":[4.4260830879,51.2935409546],"type":"Point"}
}