{
  "type": "Feature",
  "properties": {
    "addr:full":"Rue Du Kriekenput 85 Ukkel/uccle Bruxelles-Capitale 1180",
    "addr:housenumber":"85",
    "addr:postcode":"1180",
    "addr:street":"Rue Du Kriekenput;/",
    "iso:country":"BE",
    "sg:address":"Rue Du Kriekenput 85",
    "sg:city":"Ukkel/uccle",
    "sg:orig_category":"Epiceries",
    "sg:phone":"+32 2 374 69 16",
    "sg:postcode":"1180",
    "sg:province":"Bruxelles-Capitale",
    "wof:name":"Fabienne Tock",
    "wof:placetype":"venue"
},
  "geometry": {"coordinates":[4.3440651894,50.7787628174],"type":"Point"}
}