{
  "type": "Feature",
  "properties": {
    "addr:full":"Rue Adolphe Bastin 10 Namur Namur 5000",
    "addr:housenumber":"10",
    "addr:postcode":"5000",
    "addr:street":"Rue Adolphe Bastin",
    "iso:country":"BE",
    "sg:address":"Rue Adolphe Bastin 10",
    "sg:city":"Namur",
    "sg:orig_category":"Advocaten and juridische adviseurs",
    "sg:phone":"+32 81 22 82 73",
    "sg:postcode":"5000",
    "sg:province":"Namur",
    "wof:name":"A. Raisi\u00c8re",
    "wof:placetype":"venue"
},
  "geometry": {"coordinates":[4.8643159866,50.4705314636],"type":"Point"}
}