{
  "type": "Feature",
  "properties": {
    "addr:full":"Dikkebusseweg 494 Ieper (dikkebus) West-Vlaanderen 8900",
    "addr:housenumber":"494",
    "addr:postcode":"8900",
    "iso:country":"BE",
    "sg:address":"Dikkebusseweg 494",
    "sg:city":"Ieper (dikkebus)",
    "sg:classifiers":[
        {
            "category":"Retail",
            "subcategory":"Veterinary Services",
            "type":"Services"
        }
    ],
    "sg:phone":"+32 57 21 97 00",
    "sg:postcode":"8900",
    "sg:province":"West-Vlaanderen",
    "sg:tags":[
        "veterinarian"
    ],
    "wof:name":"Delanote H",
    "wof:placetype":"venue"
},
  "geometry": {"coordinates":[2.8651199341,50.8389701843],"type":"Point"}
}