{
  "type": "Feature",
  "properties": {
    "iso:country":"BE",
    "sg:address":"Woumenweg 161",
    "sg:city":"Diksmuide",
    "sg:orig_category":"Elektrische installaties voor woningen Huishoudapparaten, televisies and radio's",
    "sg:phone":"+32 51 51 02 92",
    "sg:postcode":"8600",
    "sg:province":"West-Vlaanderen",
    "wof:name":"Elektro Debacker",
    "wof:placetype":"venue"
},
  "geometry": {"coordinates":[2.8685619831,51.0125312805],"type":"Point"}
}