{
  "type": "Feature",
  "properties": {
    "addr:full":"Noblehaye 102 Herve Li\u00e8ge 4653",
    "addr:housenumber":"102",
    "addr:postcode":"4653",
    "addr:street":"Noblehaye",
    "iso:country":"BE",
    "sg:address":"Noblehaye 102",
    "sg:city":"Herve",
    "sg:orig_category":"Rundveehouders",
    "sg:phone":"+32 87 67 44 68",
    "sg:postcode":"4653",
    "sg:province":"Li\u00e8ge",
    "wof:name":"Bonhomme A. & J.-claude",
    "wof:placetype":"venue"
},
  "geometry": {"coordinates":[5.759469986,50.6489181519],"type":"Point"}
}