{
  "type": "Feature",
  "properties": {
    "iso:country":"BE",
    "sg:address":"Rue Goffart 82",
    "sg:city":"Bruxelles (ixelles)",
    "sg:classifiers":[
        {
            "category":"Professional",
            "subcategory":"Accounting & Tax Preparation",
            "type":"Services"
        }
    ],
    "sg:phone":"+32 2 523 21 23",
    "sg:postcode":"1050",
    "sg:province":"Bruxelles-Capitale",
    "sg:tags":[
        "bookkeeper"
    ],
    "wof:name":"Corfim Fsg Sprl",
    "wof:placetype":"venue"
},
  "geometry": {"coordinates":[4.372800827,50.8340034485],"type":"Point"}
}