{
  "type": "Feature",
  "properties": {
    "iso:country":"BE",
    "sg:address":"Leenstraat 7",
    "sg:city":"Nazareth",
    "sg:orig_category":"Non-Classified Establishments",
    "sg:phone":"+32 9 384 80 60",
    "sg:postcode":"9810",
    "sg:province":"Oost-Vlaanderen",
    "wof:name":"Copac Nv",
    "wof:placetype":"venue"
},
  "geometry": {"coordinates":[3.6218450069,50.9305305481],"type":"Point"}
}