{
  "type": "Feature",
  "properties": {
    "iso:country":"BE",
    "sg:address":"Brugstraat 37",
    "sg:city":"Stekene",
    "sg:classifiers":[
        {
            "category":"Home & Garden",
            "subcategory":"Garden Supply",
            "type":"Retail Goods"
        }
    ],
    "sg:phone":"+32 3 779 72 70",
    "sg:postcode":"9190",
    "sg:province":"Oost-Vlaanderen",
    "sg:tags":[
        "seed",
        "-"
    ],
    "wof:name":"Dhondt A",
    "wof:placetype":"venue"
},
  "geometry": {"coordinates":[4.0346531868,51.2011032104],"type":"Point"}
}