{
  "type": "Feature",
  "properties": {
    "addr:full":"Rue De Thulin 2 Hensies Hainaut 7350",
    "addr:housenumber":"2",
    "addr:postcode":"7350",
    "addr:street":"Rue De Thulin",
    "iso:country":"BE",
    "sg:address":"Rue De Thulin 2",
    "sg:city":"Hensies",
    "sg:orig_category":"Verplichte sociale verzekeringen",
    "sg:phone":"+32 65 45 74 89",
    "sg:postcode":"7350",
    "sg:province":"Hainaut",
    "wof:name":"Mutualit\u00c9 Socialiste",
    "wof:placetype":"venue"
},
  "geometry": {"coordinates":[3.7065761089,50.42710495],"type":"Point"}
}