{
  "type": "Feature",
  "properties": {
    "addr:full":"Groeneweg 15 Deinze (wontergem) Oost-Vlaanderen 9800",
    "addr:housenumber":"15",
    "addr:postcode":"9800",
    "addr:street":"Groeneweg",
    "iso:country":"BE",
    "sg:address":"Groeneweg 15",
    "sg:city":"Deinze (wontergem)",
    "sg:classifiers":[
        {
            "category":"Farming",
            "subcategory":"Farm & Veterinary Services",
            "type":"Manufacturing & Wholesale Goods"
        }
    ],
    "sg:phone":"+32 51 63 31 66",
    "sg:postcode":"9800",
    "sg:province":"Oost-Vlaanderen",
    "sg:tags":[
        "agricultural",
        "contractor"
    ],
    "wof:name":"Verplancke-campe",
    "wof:placetype":"venue"
},
  "geometry": {"coordinates":[3.4371440411,50.9705619812],"type":"Point"}
}