{
  "type": "Feature",
  "properties": {
    "iso:country":"BE",
    "sg:address":"Rue De Burnaifontaine 79d",
    "sg:city":"Daverdisse (haut-fays)",
    "sg:classifiers":[
        {
            "category":"Home & Garden",
            "subcategory":"Garden Supply",
            "type":"Retail Goods"
        }
    ],
    "sg:phone":"+32 61 58 93 10",
    "sg:postcode":"6929",
    "sg:province":"Luxembourg",
    "sg:tags":[
        "machine",
        "agricultural",
        "-"
    ],
    "wof:name":"Genonceaux L",
    "wof:placetype":"venue"
},
  "geometry": {"coordinates":[5.0247898102,49.9987792969],"type":"Point"}
}