{
  "type": "Feature",
  "properties": {
    "addr:full":"Vanderheydenweg 38 Hechtel-eksel Limburg 3940",
    "addr:housenumber":"38",
    "addr:postcode":"3940",
    "addr:street":"Vanderheydenweg",
    "iso:country":"BE",
    "sg:address":"Vanderheydenweg 38",
    "sg:city":"Hechtel-eksel",
    "sg:orig_category":"Kapsalons",
    "sg:phone":"+32 11 73 31 39",
    "sg:postcode":"3940",
    "sg:province":"Limburg",
    "wof:name":"Coiffure New Wave",
    "wof:placetype":"venue"
},
  "geometry": {"coordinates":[5.364795208,51.1255340576],"type":"Point"}
}