{
  "type": "Feature",
  "properties": {
    "addr:full":"Rue Victor Greyson 53 Elsene/ixelles Bruxelles-Capitale 1050",
    "addr:housenumber":"53",
    "addr:postcode":"1050",
    "addr:street":"Rue Victor Greyson",
    "iso:country":"BE",
    "sg:address":"Rue Victor Greyson 53",
    "sg:city":"Elsene/ixelles",
    "sg:orig_category":"Maisons de repos and r\u00e9sidences",
    "sg:phone":"+32 2 640 69 20",
    "sg:postcode":"1050",
    "sg:province":"Bruxelles-Capitale",
    "wof:name":"Home Les Heures Douces",
    "wof:placetype":"venue"
},
  "geometry": {"coordinates":[4.3779091835,50.822681427],"type":"Point"}
}