{
  "type": "Feature",
  "properties": {
    "iso:country":"BE",
    "sg:address":"Dageraadstraat 5",
    "sg:city":"Zoersel (halle)",
    "sg:classifiers":[
        {
            "category":"Health Services",
            "subcategory":"Health Practitioner",
            "type":"Services"
        }
    ],
    "sg:phone":"+32 3 383 41 68",
    "sg:postcode":"2980",
    "sg:province":"Antwerpen",
    "sg:tags":[
        "psychologist"
    ],
    "wof:name":"Michielsen M",
    "wof:placetype":"venue"
},
  "geometry": {"coordinates":[4.647356987,51.2356987],"type":"Point"}
}