{
  "type": "Feature",
  "properties": {
    "iso:country":"BE",
    "sg:address":"Kuringersteenweg 110",
    "sg:city":"Hasselt",
    "sg:classifiers":[
        {
            "category":"Insurance",
            "subcategory":"Insurance Agent",
            "type":"Services"
        }
    ],
    "sg:phone":"+32 11 87 22 70",
    "sg:postcode":"3500",
    "sg:province":"Limburg",
    "sg:tags":[
        "broker"
    ],
    "wof:name":"Donn\u00e9 Studiebureel Nv",
    "wof:placetype":"venue"
},
  "geometry": {"coordinates":[5.3221411705,50.9344978333],"type":"Point"}
}