{
  "type": "Feature",
  "properties": {
    "iso:country":"BE",
    "sg:address":"Rue Saint-roch 39",
    "sg:city":"Charleroi",
    "sg:orig_category":"Kapsalons",
    "sg:phone":"+32 71 35 32 33",
    "sg:postcode":"6041",
    "sg:province":"Hainaut",
    "wof:name":"Coiffure Myl\u00c8ne",
    "wof:placetype":"venue"
},
  "geometry": {"coordinates":[4.4279260635,50.4685134888],"type":"Point"}
}