{
  "type": "Feature",
  "properties": {
    "addr:full":"Dorpsstraat 33b1 Niel Antwerpen 2845",
    "addr:housenumber":"33b1",
    "addr:postcode":"2845",
    "addr:street":"Dorpsstraat",
    "iso:country":"BE",
    "sg:address":"Dorpsstraat 33b1",
    "sg:city":"Niel",
    "sg:orig_category":"Chaussures. Maroquinerie and articles de voyage",
    "sg:phone":"+32 3 888 10 44",
    "sg:postcode":"2845",
    "sg:province":"Antwerpen",
    "wof:name":"Huis Wilssens",
    "wof:placetype":"venue"
},
  "geometry": {"coordinates":[4.3270721436,51.1081085205],"type":"Point"}
}