{
  "type": "Feature",
  "properties": {
    "addr:full":"Stationsstraat 11 Oosterzele Oost-Vlaanderen 9860",
    "addr:housenumber":"11",
    "addr:postcode":"9860",
    "addr:street":"Stationsstraat;Oost-Vlaanderen",
    "iso:country":"BE",
    "sg:address":"Stationsstraat 11",
    "sg:city":"Oosterzele",
    "sg:orig_category":"Banques and organismes de cr\u00e9dit",
    "sg:phone":"+32 9 362 66 66",
    "sg:postcode":"9860",
    "sg:province":"Oost-Vlaanderen",
    "wof:name":"Fortis",
    "wof:placetype":"venue"
},
  "geometry": {"coordinates":[3.7831349373,50.9379081726],"type":"Point"}
}