{
  "type": "Feature",
  "properties": {
    "iso:country":"BE",
    "sg:address":"Grote Steenweg 19",
    "sg:city":"De Pinte",
    "sg:orig_category":"Entretien and r\u00e9parations de voitures",
    "sg:phone":"+32 9 222 26 94",
    "sg:postcode":"9840",
    "sg:province":"Oost-Vlaanderen",
    "wof:name":"D. De Rycke",
    "wof:placetype":"venue"
},
  "geometry": {"coordinates":[3.6675510406,50.9740638733],"type":"Point"}
}