{
  "type": "Feature",
  "properties": {
    "addr:full":"Kruishoutemstraat 65 Zulte (machelen) Oost-Vlaanderen 9870",
    "addr:housenumber":"65",
    "addr:postcode":"9870",
    "addr:street":"Kruishoutemstraat",
    "iso:country":"BE",
    "sg:address":"Kruishoutemstraat 65",
    "sg:city":"Zulte (machelen)",
    "sg:classifiers":[
        {
            "category":"Farming",
            "subcategory":"Livestock Farm",
            "type":"Manufacturing & Wholesale Goods"
        }
    ],
    "sg:phone":"+32 9 386 23 39",
    "sg:postcode":"9870",
    "sg:province":"Oost-Vlaanderen",
    "sg:tags":[
        "buyer"
    ],
    "wof:name":"Delbaere Gilbert & Zn Bvba",
    "wof:placetype":"venue"
},
  "geometry": {"coordinates":[3.4993150234,50.9474830627],"type":"Point"}
}