{
  "type": "Feature",
  "properties": {
    "addr:full":"Gentsestraat 32 Harelbeke West-Vlaanderen 8530",
    "addr:housenumber":"32",
    "addr:postcode":"8530",
    "addr:street":"Gentsestraat",
    "iso:country":"BE",
    "sg:address":"Gentsestraat 32",
    "sg:city":"Harelbeke",
    "sg:classifiers":[
        {
            "category":"Insurance",
            "subcategory":"Insurance Agent",
            "type":"Services"
        }
    ],
    "sg:phone":"+32 56 70 58 19",
    "sg:postcode":"8530",
    "sg:province":"West-Vlaanderen",
    "sg:tags":[
        "broker"
    ],
    "wof:name":"Zakenkantoor Dirk Castelein Bvba",
    "wof:placetype":"venue"
},
  "geometry": {"coordinates":[3.3141920567,50.857963562],"type":"Point"}
}