{
  "type": "Feature",
  "properties": {
    "addr:full":"Overleiestraat 38 Harelbeke West-Vlaanderen 8530",
    "addr:housenumber":"38",
    "addr:postcode":"8530",
    "addr:street":"Overleiestraat",
    "iso:country":"BE",
    "sg:address":"Overleiestraat 38",
    "sg:city":"Harelbeke",
    "sg:orig_category":"Brood, gebak and snoepgoed",
    "sg:phone":"+32 56 71 33 31",
    "sg:postcode":"8530",
    "sg:province":"West-Vlaanderen",
    "wof:name":"Eric Vanryckeghem",
    "wof:placetype":"venue"
},
  "geometry": {"coordinates":[3.3068399429,50.8594741821],"type":"Point"}
}