{
  "type": "Feature",
  "properties": {
    "iso:country":"BE",
    "sg:address":"Ch. Woestelaan 156",
    "sg:city":"Bruxelles-jette",
    "sg:classifiers":[
        {
            "category":"Building & Trades",
            "subcategory":"Construction",
            "type":"Services"
        }
    ],
    "sg:phone":"+32 2 421 78 78",
    "sg:postcode":"1090",
    "sg:province":"Bruxelles-Capitale",
    "sg:tags":[
        "siemens",
        "fujitsu"
    ],
    "wof:name":"Dwesab Engineering",
    "wof:placetype":"venue"
},
  "geometry": {"coordinates":[4.3295850754,50.8734817505],"type":"Point"}
}