{
  "type": "Feature",
  "properties": {
    "addr:full":"Miksebaan 75 Brasschaat Antwerpen 2930",
    "addr:housenumber":"75",
    "addr:postcode":"2930",
    "addr:street":"Miksebaan",
    "iso:country":"BE",
    "sg:address":"Miksebaan 75",
    "sg:city":"Brasschaat",
    "sg:orig_category":"Woningbouw",
    "sg:phone":"+32 3 651 68 64",
    "sg:postcode":"2930",
    "sg:province":"Antwerpen",
    "wof:name":"Van Der Wildt A.",
    "wof:placetype":"venue"
},
  "geometry": {"coordinates":[4.4984259605,51.2901344299],"type":"Point"}
}