{
  "type": "Feature",
  "properties": {
    "addr:full":"Olympialaan 22 Ledegem West-Vlaanderen 8880",
    "addr:housenumber":"22",
    "addr:postcode":"8880",
    "addr:street":"Olympialaan",
    "iso:country":"BE",
    "sg:address":"Olympialaan 22",
    "sg:city":"Ledegem",
    "sg:orig_category":"Sportclubs",
    "sg:phone":"+32 56 50 93 64",
    "sg:postcode":"8880",
    "sg:province":"West-Vlaanderen",
    "wof:name":"V.c. Kavo",
    "wof:placetype":"venue"
},
  "geometry": {"coordinates":[3.1817600727,50.8704986572],"type":"Point"}
}