{
  "type": "Feature",
  "properties": {
    "iso:country":"BE",
    "sg:address":"Papestraat 11",
    "sg:city":"Wevelgem",
    "sg:orig_category":"Etalage- and showroomontwerpers",
    "sg:phone":"+32 56 40 11 52",
    "sg:postcode":"8560",
    "sg:province":"West-Vlaanderen",
    "wof:name":"Etalages Isabelle",
    "wof:placetype":"venue"
},
  "geometry": {"coordinates":[3.1814770699,50.81224823],"type":"Point"}
}