{
  "type": "Feature",
  "properties": {
    "addr:full":"Keizer Karelstraat 108 Gent Oost-Vlaanderen 9000",
    "addr:housenumber":"108",
    "addr:postcode":"9000",
    "addr:street":"Keizer Karelstraat;Oost-Vlaanderen",
    "iso:country":"BE",
    "sg:address":"Keizer Karelstraat 108",
    "sg:city":"Gent",
    "sg:orig_category":"Salons de coiffure. Instituts de beaut\u00e9",
    "sg:phone":"+32 9 225 21 21",
    "sg:postcode":"9000",
    "sg:province":"Oost-Vlaanderen",
    "wof:name":"Nail Fashion",
    "wof:placetype":"venue"
},
  "geometry": {"coordinates":[3.7320859432,51.0521965027],"type":"Point"}
}