{
  "type": "Feature",
  "properties": {
    "addr:full":"Legeweg 121 Brugge West-Vlaanderen 8200",
    "addr:housenumber":"121",
    "addr:postcode":"8200",
    "addr:street":"Legeweg",
    "iso:country":"BE",
    "sg:address":"Legeweg 121",
    "sg:city":"Brugge",
    "sg:orig_category":"M\u00e9decins and sp\u00e9cialistes",
    "sg:phone":"+32 50 31 94 57",
    "sg:postcode":"8200",
    "sg:province":"West-Vlaanderen",
    "wof:name":"Filip Parmentier",
    "wof:placetype":"venue"
},
  "geometry": {"coordinates":[3.2017149925,51.2045822144],"type":"Point"}
}