{
  "type": "Feature",
  "properties": {
    "iso:country":"BE",
    "sg:address":"Pieter De Coninckstraat 12",
    "sg:city":"Lommel",
    "sg:orig_category":"Kapsalons",
    "sg:phone":"+32 11 55 13 41",
    "sg:postcode":"3920",
    "sg:province":"Limburg",
    "wof:name":"Nancy Huysmans",
    "wof:placetype":"venue"
},
  "geometry": {"coordinates":[5.3299889565,51.2270736694],"type":"Point"}
}