{
  "type": "Feature",
  "properties": {
    "iso:country":"BE",
    "sg:address":"Johannastraat 2",
    "sg:city":"Middelkerke",
    "sg:orig_category":"Autombile concessionaires",
    "sg:phone":"+32 59 30 09 35",
    "sg:postcode":"8430",
    "sg:province":"West-Vlaanderen",
    "wof:name":"Gar Carels W",
    "wof:placetype":"venue"
},
  "geometry": {"coordinates":[2.8031508923,51.182926178],"type":"Point"}
}