{
  "type": "Feature",
  "properties": {
    "addr:full":"Kuilenstraat 3 Genk Limburg 3600",
    "addr:housenumber":"3",
    "addr:postcode":"3600",
    "addr:street":"Kuilenstraat",
    "iso:country":"BE",
    "sg:address":"Kuilenstraat 3",
    "sg:city":"Genk",
    "sg:orig_category":"Pain, p\u00e2tisseries and confiseries",
    "sg:phone":"+32 89 35 87 61",
    "sg:postcode":"3600",
    "sg:province":"Limburg",
    "wof:name":"Huis Chlo\u00cb",
    "wof:placetype":"venue"
},
  "geometry": {"coordinates":[5.4972229004,50.9688148499],"type":"Point"}
}