{
  "type": "Feature",
  "properties": {
    "iso:country":"BE",
    "sg:address":"Sint-gummarusstraat 36",
    "sg:city":"Antwerpen",
    "sg:classifiers":[
        {
            "category":"Personal",
            "subcategory":"Beauty Salon",
            "type":"Services"
        }
    ],
    "sg:phone":"+32 3 232 22 79",
    "sg:postcode":"2060",
    "sg:province":"Antwerpen",
    "wof:name":"Visage Schoonheidsinstituut",
    "wof:placetype":"venue"
},
  "geometry": {"coordinates":[4.420771122,51.2246208191],"type":"Point"}
}