{
  "type": "Feature",
  "properties": {
    "addr:full":"Boonmarkt 8 Heist-op-den-berg Antwerpen 2220",
    "addr:housenumber":"8",
    "addr:postcode":"2220",
    "addr:street":"Boonmarkt",
    "iso:country":"BE",
    "sg:address":"Boonmarkt 8",
    "sg:city":"Heist-op-den-berg",
    "sg:orig_category":"Fotografen and fotostudio's Speelgoed, sport- and kampeermateriaal Gh",
    "sg:phone":"+32 15 24 22 92",
    "sg:postcode":"2220",
    "sg:province":"Antwerpen",
    "wof:name":"J-tech Automation",
    "wof:placetype":"venue"
},
  "geometry": {"coordinates":[4.7193040848,51.0882606506],"type":"Point"}
}