{
  "type": "Feature",
  "properties": {
    "iso:country":"BE",
    "sg:address":"Avenue Marie -jos\u00c9e 35",
    "sg:city":"Binche",
    "sg:orig_category":"Mat\u00e9riel de contr\u00f4le des processus industriels Fab",
    "sg:phone":"+32 64 33 60 31",
    "sg:postcode":"7130",
    "sg:province":"Hainaut",
    "wof:name":"Legros Automation Industrielle",
    "wof:placetype":"venue"
},
  "geometry": {"coordinates":[4.1780200005,50.4133491516],"type":"Point"}
}