{
  "type": "Feature",
  "properties": {
    "iso:country":"BE",
    "sg:address":"Chauss\u00e9e De Tirlemont 53",
    "sg:city":"Wanze",
    "sg:classifiers":[
        {
            "category":"Health Services",
            "subcategory":"Doctor",
            "type":"Services"
        }
    ],
    "sg:phone":"+32 85 21 32 33",
    "sg:postcode":"4520",
    "sg:province":"Li\u00e8ge",
    "sg:tags":[
        "medicinephysicians",
        "surgeon"
    ],
    "wof:name":"Graindorge H",
    "wof:placetype":"venue"
},
  "geometry": {"coordinates":[5.2198519707,50.5362434387],"type":"Point"}
}