{
  "type": "Feature",
  "properties": {
    "addr:full":"Rue Josaphat 52 Bruxelles (schaerbeek) Bruxelles-Capitale 1030",
    "addr:housenumber":"52",
    "addr:postcode":"1030",
    "addr:street":"Rue Josaphat",
    "iso:country":"BE",
    "sg:address":"Rue Josaphat 52",
    "sg:city":"Bruxelles (schaerbeek)",
    "sg:classifiers":[
        {
            "category":"Bakery",
            "type":"Food & Drink"
        }
    ],
    "sg:phone":"+32 2 215 60 03",
    "sg:postcode":"1030",
    "sg:province":"Bruxelles-Capitale",
    "sg:tags":[
        "confectioner",
        "baker"
    ],
    "wof:name":"Ouluan F",
    "wof:placetype":"venue"
},
  "geometry": {"coordinates":[4.3731021881,50.8569717407],"type":"Point"}
}