{
  "type": "Feature",
  "properties": {
    "iso:country":"BE",
    "sg:address":"Moerstraat 14",
    "sg:city":"Eeklo",
    "sg:orig_category":"Eleveurs de bovins. Eleveurs and marchands de porcs",
    "sg:phone":"+32 9 377 38 54",
    "sg:postcode":"9900",
    "sg:province":"Oost-Vlaanderen",
    "wof:name":"Roger Haegeman",
    "wof:placetype":"venue"
},
  "geometry": {"coordinates":[3.5562999249,51.2141418457],"type":"Point"}
}