{
  "type": "Feature",
  "properties": {
    "addr:full":"Avenue Brunard 55 Ukkel/uccle Bruxelles-Capitale 1180",
    "addr:housenumber":"55",
    "addr:postcode":"1180",
    "addr:street":"Avenue Brunard;/",
    "iso:country":"BE",
    "sg:address":"Avenue Brunard 55",
    "sg:city":"Ukkel/uccle",
    "sg:orig_category":"V\u00eatements pour Dames. V\u00eatements",
    "sg:phone":"+32 2 374 17 32",
    "sg:postcode":"1180",
    "sg:province":"Bruxelles-Capitale",
    "wof:name":"Yves Saint-laurent",
    "wof:placetype":"venue"
},
  "geometry": {"coordinates":[4.360077858,50.8089981079],"type":"Point"}
}