{
  "type": "Feature",
  "properties": {
    "addr:full":"Chauss\u00e9e De Valenciennes 20 Ath Hainaut 7800",
    "addr:housenumber":"20",
    "addr:postcode":"7800",
    "addr:street":"Chausse\u0301E De Valenciennes",
    "iso:country":"BE",
    "sg:address":"Chauss\u00e9e De Valenciennes 20",
    "sg:city":"Ath",
    "sg:classifiers":[
        {
            "category":"Real Estate",
            "subcategory":"Architect",
            "type":"Services"
        }
    ],
    "sg:phone":"+32 68 84 05 00",
    "sg:postcode":"7800",
    "sg:province":"Hainaut",
    "wof:name":"Loncheval L",
    "wof:placetype":"venue"
},
  "geometry": {"coordinates":[3.770209074,50.6256561279],"type":"Point"}
}