{
  "type": "Feature",
  "properties": {
    "addr:full":"Vogelenzangstraat 115 Kalmthout Antwerpen 2920",
    "addr:housenumber":"115",
    "addr:postcode":"2920",
    "addr:street":"Vogelenzangstraat",
    "iso:country":"BE",
    "sg:address":"Vogelenzangstraat 115",
    "sg:city":"Kalmthout",
    "sg:classifiers":[
        {
            "category":"Education",
            "subcategory":"School",
            "type":"Public Place"
        }
    ],
    "sg:phone":"+32 3 666 60 24",
    "sg:postcode":"2920",
    "sg:province":"Antwerpen",
    "sg:tags":[
        "primary"
    ],
    "wof:name":"Gemeenschapsonderwijs- Buitengewone Basisscholen",
    "wof:placetype":"venue"
},
  "geometry": {"coordinates":[4.4529099464,51.3808708191],"type":"Point"}
}