{
  "type": "Feature",
  "properties": {
    "iso:country":"BE",
    "sg:address":"Hippoliet Spilleboutdreef 68",
    "sg:city":"Roeselare",
    "sg:classifiers":[
        {
            "category":"Personal",
            "subcategory":"Barber",
            "type":"Services"
        }
    ],
    "sg:phone":"+32 51 22 55 20",
    "sg:postcode":"8800",
    "sg:province":"West-Vlaanderen",
    "sg:tags":[
        "gentleman",
        "salon",
        "-",
        "hairdressing"
    ],
    "wof:name":"Eddy",
    "wof:placetype":"venue"
},
  "geometry": {"coordinates":[3.1218600273,50.9365882874],"type":"Point"}
}