{
  "type": "Feature",
  "properties": {
    "addr:full":"Bankstraat 7 Wevelgem West-Vlaanderen 8560",
    "addr:housenumber":"7",
    "addr:postcode":"8560",
    "addr:street":"Bankstraat",
    "iso:country":"BE",
    "sg:address":"Bankstraat 7",
    "sg:city":"Wevelgem",
    "sg:orig_category":"Banken and kredietinstellingen",
    "sg:phone":"+32 56 41 57 94",
    "sg:postcode":"8560",
    "sg:province":"West-Vlaanderen",
    "wof:name":"Bacob",
    "wof:placetype":"venue"
},
  "geometry": {"coordinates":[3.2034130096,50.844039917],"type":"Point"}
}