{
  "type": "Feature",
  "properties": {
    "iso:country":"BE",
    "sg:address":"Rue De Marbaix 163",
    "sg:city":"Montigny-le-tilleul",
    "sg:orig_category":"Bijouteries and horlogeries",
    "sg:phone":"+32 71 51 70 07",
    "sg:postcode":"6110",
    "sg:province":"Hainaut",
    "wof:name":"Alain Tron",
    "wof:placetype":"venue"
},
  "geometry": {"coordinates":[4.3731079102,50.3661460876],"type":"Point"}
}