{
  "type": "Feature",
  "properties": {
    "iso:country":"BE",
    "sg:address":"Hoogstraat 14",
    "sg:city":"Aalst",
    "sg:orig_category":"Installatie van houten of kunststof schrijnwerk",
    "sg:phone":"+32 53 70 20 51",
    "sg:postcode":"9308",
    "sg:province":"Oost-Vlaanderen",
    "wof:name":"Julien Van Den Bossche",
    "wof:placetype":"venue"
},
  "geometry": {"coordinates":[4.0621848106,50.9487953186],"type":"Point"}
}