{
  "type": "Feature",
  "properties": {
    "addr:full":"Rue Du Moulin 1ba Etalle Luxembourg 6740",
    "addr:postcode":"1ba;6740",
    "addr:street":"Rue Du Moulin",
    "iso:country":"BE",
    "sg:address":"Rue Du Moulin 1ba",
    "sg:city":"Etalle",
    "sg:classifiers":[
        {
            "category":"Fast Food",
            "type":"Food & Drink"
        }
    ],
    "sg:phone":"+32 63 45 62 92",
    "sg:postcode":"6740",
    "sg:province":"Luxembourg",
    "sg:tags":[
        "meeneem",
        "restaurant"
    ],
    "wof:name":"Friterie Vanny",
    "wof:placetype":"venue"
},
  "geometry": {"coordinates":[5.6026911736,49.674041748],"type":"Point"}
}