{
  "type": "Feature",
  "properties": {
    "addr:full":"Ankerstraat 76 Genk Limburg 3600",
    "addr:housenumber":"76",
    "addr:postcode":"3600",
    "addr:street":"Ankerstraat",
    "iso:country":"BE",
    "sg:address":"Ankerstraat 76",
    "sg:city":"Genk",
    "sg:orig_category":"Peinture. Rev\u00eatements pour sols and murs",
    "sg:phone":"+32 89 35 70 67",
    "sg:postcode":"3600",
    "sg:province":"Limburg",
    "wof:name":"Put & Vermeulen",
    "wof:placetype":"venue"
},
  "geometry": {"coordinates":[5.4557580948,50.9653091431],"type":"Point"}
}