{
  "type": "Feature",
  "properties": {
    "addr:full":"Antwerpsestraat 232 Boom Antwerpen 2850",
    "addr:housenumber":"232",
    "addr:postcode":"2850",
    "addr:street":"Antwerpsestraat",
    "iso:country":"BE",
    "sg:address":"Antwerpsestraat 232",
    "sg:city":"Boom",
    "sg:orig_category":"Produits pharmaceutiques Gr",
    "sg:phone":"+32 3 888 07 13",
    "sg:postcode":"2850",
    "sg:province":"Antwerpen",
    "wof:name":"Medical Equipment Trade",
    "wof:placetype":"venue"
},
  "geometry": {"coordinates":[4.3668479919,51.0955810547],"type":"Point"}
}