{
  "type": "Feature",
  "properties": {
    "iso:country":"BE",
    "sg:address":"Dijkstraat",
    "sg:city":"Aartselaar",
    "sg:orig_category":"Gestion des d\u00e9charges and sites d\u00e9finitifs de stockage",
    "sg:phone":"+32 3 870 16 50",
    "sg:postcode":"2630",
    "sg:province":"Antwerpen",
    "wof:name":"Containerpark Aartselaar",
    "wof:placetype":"venue"
},
  "geometry": {"coordinates":[4.3952531815,51.1464881897],"type":"Point"}
}