{
  "type": "Feature",
  "properties": {
    "iso:country":"BE",
    "sg:address":"Halleweg 138",
    "sg:city":"Halle",
    "sg:orig_category":"Newspapers, magazines, periodicals - Distribution",
    "sg:phone":"+32 2 360 06 64",
    "sg:postcode":"1500",
    "sg:province":"Vlaams-Brabant",
    "wof:name":"Halleweg",
    "wof:placetype":"venue"
},
  "geometry": {"coordinates":[4.2471971512,50.7270393372],"type":"Point"}
}