{
  "type": "Feature",
  "properties": {
    "iso:country":"BE",
    "sg:address":"Galgestraat 22",
    "sg:city":"Oudenaarde",
    "sg:classifiers":[
        {
            "category":"Health Services",
            "subcategory":"Health Practitioner",
            "type":"Services"
        }
    ],
    "sg:phone":"+32 55 31 29 18",
    "sg:postcode":"9700",
    "sg:province":"Oost-Vlaanderen",
    "sg:tags":[
        "physiotherapist"
    ],
    "wof:name":"Vander Haegen Pieter",
    "wof:placetype":"venue"
},
  "geometry": {"coordinates":[3.6138761044,50.8518753052],"type":"Point"}
}