{
  "type": "Feature",
  "properties": {
    "iso:country":"BE",
    "sg:address":"Oude Bruggeweg 2",
    "sg:city":"Wingene",
    "sg:orig_category":"Bouwmaterialen Gh Installatie van houten of kunststof schrijnwerk",
    "sg:phone":"+32 50 78 13 64",
    "sg:postcode":"8750",
    "sg:province":"West-Vlaanderen",
    "wof:name":"Alterno",
    "wof:placetype":"venue"
},
  "geometry": {"coordinates":[3.3040859699,51.0987968445],"type":"Point"}
}