{
  "type": "Feature",
  "properties": {
    "iso:country":"BE",
    "sg:address":"Oosthoek 88",
    "sg:city":"Assenede (oosteeklo)",
    "sg:classifiers":[
        {
            "category":"Shopping",
            "subcategory":"Computers & Home Electronics",
            "type":"Retail Goods"
        }
    ],
    "sg:phone":"+32 477 59 41 70",
    "sg:postcode":"9968",
    "sg:province":"Oost-Vlaanderen",
    "sg:tags":[
        "-",
        "peripheral",
        "processing",
        "data",
        "equipment"
    ],
    "wof:name":"A.d.m. Com-systems",
    "wof:placetype":"venue"
},
  "geometry": {"coordinates":[3.7055261135,51.2013244629],"type":"Point"}
}