{
  "type": "Feature",
  "properties": {
    "addr:full":"Brabantstraat 147 Schaarbeek/schaerbeek Bruxelles-Capitale 1030",
    "addr:housenumber":"147",
    "addr:postcode":"1030",
    "addr:street":"Brabantstraat",
    "iso:country":"BE",
    "sg:address":"Brabantstraat 147",
    "sg:city":"Schaarbeek/schaerbeek",
    "sg:orig_category":"Baby- and kinderkleding",
    "sg:phone":"+32 2 242 98 44",
    "sg:postcode":"1030",
    "sg:province":"Bruxelles-Capitale",
    "wof:name":"Maison Mikatex",
    "wof:placetype":"venue"
},
  "geometry": {"coordinates":[4.3649477959,50.8624954224],"type":"Point"}
}