{
  "type": "Feature",
  "properties": {
    "addr:full":"Rue Petite Chenevi\u00e8re 233 Charleroi (marcinelle) Hainaut 6001",
    "addr:housenumber":"233",
    "addr:postcode":"6001",
    "addr:street":"Rue Petite Chenevie\u0300Re",
    "iso:country":"BE",
    "sg:address":"Rue Petite Chenevi\u00e8re 233",
    "sg:city":"Charleroi (marcinelle)",
    "sg:classifiers":[
        {
            "category":"Wholesale",
            "subcategory":"Wine & Distilled Alcoholic Beverages",
            "type":"Manufacturing & Wholesale Goods"
        }
    ],
    "sg:phone":"+32 71 36 16 21",
    "sg:postcode":"6001",
    "sg:province":"Hainaut",
    "sg:tags":[
        "whol",
        "-",
        "spirit",
        "mfg"
    ],
    "wof:name":"Andr\u00e9 Ets Sa",
    "wof:placetype":"venue"
},
  "geometry": {"coordinates":[4.4407601357,50.3828887939],"type":"Point"}
}