{
  "type": "Feature",
  "properties": {
    "iso:country":"BE",
    "sg:address":"Pastoor De Katerstraat 5",
    "sg:city":"Baarle-hertog",
    "sg:orig_category":"Biblioth\u00e8ques and archives publiques",
    "sg:phone":"+32 14 69 94 92",
    "sg:postcode":"2387",
    "sg:province":"Antwerpen",
    "wof:name":"Openbare Bibliotheek",
    "wof:placetype":"venue"
},
  "geometry": {"coordinates":[4.9258198738,51.4415779114],"type":"Point"}
}