{
  "type": "Feature",
  "properties": {
    "iso:country":"BE",
    "sg:address":"Rue Jules M\u00e9lotte 12",
    "sg:city":"Remicourt",
    "sg:classifiers":[
        {
            "category":"Professional",
            "subcategory":"Management & Consulting",
            "type":"Services"
        }
    ],
    "sg:phone":"+32 19 54 40 13",
    "sg:postcode":"4350",
    "sg:province":"Li\u00e8ge",
    "sg:tags":[
        "consultant"
    ],
    "wof:name":"Hesba Sprl",
    "wof:placetype":"venue"
},
  "geometry": {"coordinates":[5.3208379745,50.6797866821],"type":"Point"}
}