{
  "type": "Feature",
  "properties": {
    "iso:country":"BE",
    "sg:address":"Poldrstraat 72",
    "sg:city":"Oud-turnhout",
    "sg:orig_category":"Loodgieterij, verwarming and sanitaire installaties",
    "sg:phone":"+32 14 43 95 01",
    "sg:postcode":"2360",
    "sg:province":"Antwerpen",
    "wof:name":"Mermans Danny",
    "wof:placetype":"venue"
},
  "geometry": {"coordinates":[4.9689669609,51.3361434937],"type":"Point"}
}