{
  "type": "Feature",
  "properties": {
    "iso:country":"BE",
    "sg:address":"Chauss\u00c9e De Hal 122",
    "sg:city":"Sint-genesius-rode/rhode-saint-genese",
    "sg:orig_category":"Artistes ind\u00e9pendants",
    "sg:phone":"+32 2 649 26 10",
    "sg:postcode":"1640",
    "sg:province":"Vlaams-Brabant",
    "wof:name":"H. Beaumont",
    "wof:placetype":"venue"
},
  "geometry": {"coordinates":[4.3325328827,50.7380332947],"type":"Point"}
}