{
  "type": "Feature",
  "properties": {
    "iso:country":"BE",
    "sg:address":"Handelslei 114",
    "sg:city":"Zoersel",
    "sg:classifiers":[
        {
            "category":"Professional",
            "type":"Services"
        }
    ],
    "sg:phone":"+32 3 289 76 38",
    "sg:postcode":"2980",
    "sg:province":"Antwerpen",
    "sg:tags":[
        "entertainer"
    ],
    "wof:name":"Marc Hul",
    "wof:placetype":"venue"
},
  "geometry": {"coordinates":[4.6484470367,51.2730941772],"type":"Point"}
}