{
  "type": "Feature",
  "properties": {
    "addr:full":"Dries 41 Lebbeke Oost-Vlaanderen 9280",
    "addr:housenumber":"41",
    "addr:postcode":"9280",
    "addr:street":"Dries",
    "iso:country":"BE",
    "sg:address":"Dries 41",
    "sg:city":"Lebbeke",
    "sg:orig_category":"Rundveehouders",
    "sg:phone":"+32 52 41 17 22",
    "sg:postcode":"9280",
    "sg:province":"Oost-Vlaanderen",
    "wof:name":"Eddy Van Langenhove",
    "wof:placetype":"venue"
},
  "geometry": {"coordinates":[4.1033291817,51.0033607483],"type":"Point"}
}