{
  "type": "Feature",
  "properties": {
    "addr:full":"Haachtsesteenweg 47 Steenokkerzeel Vlaams-Brabant 1820",
    "addr:housenumber":"47",
    "addr:postcode":"1820",
    "addr:street":"Haachtsesteenweg",
    "iso:country":"BE",
    "sg:address":"Haachtsesteenweg 47",
    "sg:city":"Steenokkerzeel",
    "sg:orig_category":"Non-Classified Establishments",
    "sg:phone":"+32 2 751 83 93",
    "sg:postcode":"1820",
    "sg:province":"Vlaams-Brabant",
    "wof:name":"Kaashandel Albert Bvba",
    "wof:placetype":"venue"
},
  "geometry": {"coordinates":[4.5106658936,50.9223251343],"type":"Point"}
}