{
  "type": "Feature",
  "properties": {
    "addr:full":"Terhulpensesteenweg 524 Overijse Vlaams-Brabant 3090",
    "addr:housenumber":"524",
    "addr:postcode":"3090",
    "addr:street":"Terhulpensesteenweg",
    "iso:country":"BE",
    "sg:address":"Terhulpensesteenweg 524",
    "sg:city":"Overijse",
    "sg:orig_category":"Enseignement maternel and primaire",
    "sg:phone":"+32 2 687 38 75",
    "sg:postcode":"3090",
    "sg:province":"Vlaams-Brabant",
    "wof:name":"Vrije Basisschool",
    "wof:placetype":"venue"
},
  "geometry": {"coordinates":[4.5301628113,50.7591209412],"type":"Point"}
}