{
  "type": "Feature",
  "properties": {
    "iso:country":"BE",
    "sg:address":"Rempart-des-j\u00c9suites 55",
    "sg:city":"Marche-en-famenne",
    "sg:orig_category":"Artsen and specialisten",
    "sg:phone":"+32 84 31 19 06",
    "sg:postcode":"6900",
    "sg:province":"Luxembourg",
    "wof:name":"Jules Gilles",
    "wof:placetype":"venue"
},
  "geometry": {"coordinates":[5.3460841179,50.2280921936],"type":"Point"}
}