{
  "type": "Feature",
  "properties": {
    "addr:full":"Speurstraat 63 Lede Oost-Vlaanderen 9340",
    "addr:housenumber":"63",
    "addr:postcode":"9340",
    "addr:street":"Speurstraat",
    "iso:country":"BE",
    "sg:address":"Speurstraat 63",
    "sg:city":"Lede",
    "sg:orig_category":"Travail and traitement du bois",
    "sg:phone":"+32 9 369 03 09",
    "sg:postcode":"9340",
    "sg:province":"Oost-Vlaanderen",
    "wof:name":"Michel Meuleman",
    "wof:placetype":"venue"
},
  "geometry": {"coordinates":[3.8985960484,50.962387085],"type":"Point"}
}