{
  "type": "Feature",
  "properties": {
    "iso:country":"BE",
    "sg:address":"Riddersstraat 89",
    "sg:city":"Leuven",
    "sg:orig_category":"Enseignement maternel and primaire",
    "sg:phone":"+32 16 23 35 31",
    "sg:postcode":"3000",
    "sg:province":"Vlaams-Brabant",
    "wof:name":"Vrije Kleuterschool",
    "wof:placetype":"venue"
},
  "geometry": {"coordinates":[4.691901207,50.883846283],"type":"Point"}
}