{
  "type": "Feature",
  "properties": {
    "iso:country":"BE",
    "sg:address":"Adelberg 36-40",
    "sg:city":"Lommel",
    "sg:orig_category":"Passagiersvervoer over de weg",
    "sg:phone":"+32 11 54 40 69",
    "sg:postcode":"3920",
    "sg:province":"Limburg",
    "wof:name":"V.b.m.",
    "wof:placetype":"venue"
},
  "geometry": {"coordinates":[5.3063378334,51.2338943481],"type":"Point"}
}