{
  "type": "Feature",
  "properties": {
    "addr:full":"Rue Des Pr\u00e9s Du Roy 2 Ath Hainaut 7800",
    "addr:housenumber":"2",
    "addr:postcode":"7800",
    "addr:street":"Rue Des Pre\u0301S Du Roy",
    "iso:country":"BE",
    "sg:address":"Rue Des Pr\u00e9s Du Roy 2",
    "sg:city":"Ath",
    "sg:classifiers":[
        {
            "category":"Autos & Motor Vehicles",
            "subcategory":"Automobile Sales",
            "type":"Retail Goods"
        }
    ],
    "sg:phone":"+32 68 84 23 00",
    "sg:postcode":"7800",
    "sg:province":"Hainaut",
    "sg:tags":[
        "car",
        "used",
        "-"
    ],
    "wof:name":"Roos B",
    "wof:placetype":"venue"
},
  "geometry": {"coordinates":[3.7836909294,50.638507843],"type":"Point"}
}