{
  "type": "Feature",
  "properties": {
    "addr:full":"Rue Saint-paul 187 Welkenraedt/welkenraedt Li\u00e8ge 4840",
    "addr:housenumber":"187",
    "addr:postcode":"4840",
    "addr:street":"Rue Saint-Paul",
    "iso:country":"BE",
    "sg:address":"Rue Saint-paul 187",
    "sg:city":"Welkenraedt/welkenraedt",
    "sg:orig_category":"Installatie van houten of kunststof schrijnwerk",
    "sg:phone":"+32 87 88 11 03",
    "sg:postcode":"4840",
    "sg:province":"Li\u00e8ge",
    "wof:name":"Guillermo Mendez-becerra",
    "wof:placetype":"venue"
},
  "geometry": {"coordinates":[5.9796700478,50.6616210938],"type":"Point"}
}