{
  "type": "Feature",
  "properties": {
    "addr:full":"Grand'rue 71 Sankt Vith/saint-vith Li\u00e8ge 4780",
    "addr:housenumber":"71",
    "addr:postcode":"4780",
    "addr:street":"Grand'Rue",
    "iso:country":"BE",
    "sg:address":"Grand'rue 71",
    "sg:city":"Sankt Vith/saint-vith",
    "sg:classifiers":[
        {
            "category":"Restaurant",
            "type":"Food & Drink"
        }
    ],
    "sg:phone":"+32 80 22 80 22",
    "sg:postcode":"4780",
    "sg:province":"Li\u00e8ge",
    "wof:name":"Le Luxembourg",
    "wof:placetype":"venue"
},
  "geometry": {"coordinates":[6.1256599426,50.2810783386],"type":"Point"}
}