{
  "type": "Feature",
  "properties": {
    "iso:country":"BE",
    "sg:address":"De Bergen 1a",
    "sg:city":"Zandhoven",
    "sg:classifiers":[
        {
            "category":"Fast Food",
            "type":"Food & Drink"
        }
    ],
    "sg:phone":"+32 3 484 56 96",
    "sg:postcode":"2240",
    "sg:province":"Antwerpen",
    "sg:tags":[
        "fried",
        "stand",
        "potato"
    ],
    "wof:name":"De Bergen",
    "wof:placetype":"venue"
},
  "geometry": {"coordinates":[4.6594018936,51.2143325806],"type":"Point"}
}