{
  "type": "Feature",
  "properties": {
    "iso:country":"BE",
    "sg:address":"Veldhoek 21",
    "sg:city":"Zomergem",
    "sg:orig_category":"P\u00e9pini\u00e9ristes",
    "sg:phone":"+32 9 377 06 65",
    "sg:postcode":"9931",
    "sg:province":"Oost-Vlaanderen",
    "wof:name":"Jan De Dobbelaere",
    "wof:placetype":"venue"
},
  "geometry": {"coordinates":[3.5173480511,51.1479530334],"type":"Point"}
}