{
  "type": "Feature",
  "properties": {
    "iso:country":"BE",
    "sg:address":"Willem Putmanstraat 9",
    "sg:city":"Kortrijk (marke)",
    "sg:classifiers":[
        {
            "category":"Professional",
            "subcategory":"Printing & Photocopies",
            "type":"Services"
        }
    ],
    "sg:phone":"+32 56 21 81 16",
    "sg:postcode":"8510",
    "sg:province":"West-Vlaanderen",
    "sg:tags":[
        "-",
        "plan",
        "reproduction"
    ],
    "wof:name":"Iac-declercq Jan",
    "wof:placetype":"venue"
},
  "geometry": {"coordinates":[3.2385001183,50.7880783081],"type":"Point"}
}