{
  "type": "Feature",
  "properties": {
    "addr:full":"Dentergemstraat 103 Oostrozebeke West-Vlaanderen 8780",
    "addr:housenumber":"103",
    "addr:postcode":"8780",
    "addr:street":"Dentergemstraat",
    "iso:country":"BE",
    "sg:address":"Dentergemstraat 103",
    "sg:city":"Oostrozebeke",
    "sg:classifiers":[
        {
            "category":"Banks & Credit Unions",
            "subcategory":"Investment Brokerage",
            "type":"Services"
        }
    ],
    "sg:phone":"+32 56 66 43 53",
    "sg:postcode":"8780",
    "sg:province":"West-Vlaanderen",
    "sg:tags":[
        "repair",
        "-",
        "installation",
        "sanitary",
        "article"
    ],
    "wof:name":"Naert K",
    "wof:placetype":"venue"
},
  "geometry": {"coordinates":[3.3607699871,50.9357872009],"type":"Point"}
}