{
  "type": "Feature",
  "properties": {
    "addr:full":"Avenue Des Combattants 22b Gembloux Namur 5030",
    "addr:housenumber":"22b",
    "addr:postcode":"5030",
    "addr:street":"Avenue Des Combattants;Namur",
    "iso:country":"BE",
    "sg:address":"Avenue Des Combattants 22b",
    "sg:city":"Gembloux",
    "sg:orig_category":"Meubles Fab. Installation de menuiserie en bois and plastique. Rev\u00eatements de sols and murs",
    "sg:phone":"+32 81 60 02 89",
    "sg:postcode":"5030",
    "sg:province":"Namur",
    "wof:name":"Kelm",
    "wof:placetype":"venue"
},
  "geometry": {"coordinates":[4.6995201111,50.5603256226],"type":"Point"}
}