{
  "type": "Feature",
  "properties": {
    "addr:full":"Vichtesteenweg 34ba Deerlijk West-Vlaanderen 8540",
    "addr:housenumber":"34ba",
    "addr:postcode":"8540",
    "addr:street":"Vichtesteenweg",
    "iso:country":"BE",
    "sg:address":"Vichtesteenweg 34ba",
    "sg:city":"Deerlijk",
    "sg:classifiers":[
        {
            "category":"Cafe",
            "type":"Food & Drink"
        }
    ],
    "sg:phone":"+32 56 72 94 51",
    "sg:postcode":"8540",
    "sg:province":"West-Vlaanderen",
    "sg:tags":[
        "caf\u00e9s"
    ],
    "wof:name":"Geert Moerman",
    "wof:placetype":"venue"
},
  "geometry": {"coordinates":[3.3606369495,50.8525009155],"type":"Point"}
}