{
  "type": "Feature",
  "properties": {
    "iso:country":"BE",
    "sg:address":"Markt 29",
    "sg:city":"Deinze",
    "sg:classifiers":[
        {
            "category":"Professional",
            "subcategory":"Testing Lab",
            "type":"Services"
        }
    ],
    "sg:phone":"+32 9 386 12 01",
    "sg:postcode":"9800",
    "sg:province":"Oost-Vlaanderen",
    "sg:tags":[
        "chemist"
    ],
    "wof:name":"Matthys J-m",
    "wof:placetype":"venue"
},
  "geometry": {"coordinates":[3.5268330574,50.9846458435],"type":"Point"}
}