{
  "type": "Feature",
  "properties": {
    "iso:country":"BE",
    "sg:address":"Leuvensebaan 139",
    "sg:city":"Holsbeek",
    "sg:orig_category":"Belastingconsulenten Diverse juridische dienstverlening",
    "sg:phone":"+32 16 44 58 61",
    "sg:postcode":"3220",
    "sg:province":"Vlaams-Brabant",
    "wof:name":"Buyse-de Vlieger & Co",
    "wof:placetype":"venue"
},
  "geometry": {"coordinates":[4.7402777672,50.9149856567],"type":"Point"}
}