{
  "type": "Feature",
  "properties": {
    "addr:full":"Avenue Des Nerviens 65-12 Bruxelles (etterbeek) Bruxelles-Capitale 1040",
    "addr:housenumber":"65-12",
    "addr:postcode":"1040",
    "addr:street":"Avenue Des Nerviens",
    "iso:country":"BE",
    "sg:address":"Avenue Des Nerviens 65-12",
    "sg:city":"Bruxelles (etterbeek)",
    "sg:classifiers":[
        {
            "category":"Real Estate",
            "subcategory":"Architect",
            "type":"Services"
        }
    ],
    "sg:phone":"+32 2 732 73 67",
    "sg:postcode":"1040",
    "sg:province":"Bruxelles-Capitale",
    "wof:name":"Bonte Ch",
    "wof:placetype":"venue"
},
  "geometry": {"coordinates":[4.3893079758,50.8385925293],"type":"Point"}
}