{
  "type": "Feature",
  "properties": {
    "addr:full":"Esperantolaan 16 Tienen Vlaams-Brabant 3300",
    "addr:housenumber":"16",
    "addr:postcode":"3300",
    "addr:street":"Esperantolaan",
    "iso:country":"BE",
    "sg:address":"Esperantolaan 16",
    "sg:city":"Tienen",
    "sg:classifiers":[
        {
            "category":"Retail",
            "subcategory":"Auto Repair",
            "type":"Services"
        }
    ],
    "sg:phone":"+32 16 82 39 30",
    "sg:postcode":"3300",
    "sg:province":"Vlaams-Brabant",
    "sg:tags":[
        "garage"
    ],
    "wof:name":"Claes & Zn L.a.r.",
    "wof:placetype":"venue"
},
  "geometry": {"coordinates":[4.9177861214,50.8039283752],"type":"Point"}
}