{
  "type": "Feature",
  "properties": {
    "addr:full":"Leopoldslei 74 Brasschaat Antwerpen 2930",
    "addr:housenumber":"74",
    "addr:postcode":"2930",
    "addr:street":"Leopoldslei",
    "iso:country":"BE",
    "sg:address":"Leopoldslei 74",
    "sg:city":"Brasschaat",
    "sg:classifiers":[
        {
            "category":"Health Services",
            "subcategory":"Health Practitioner",
            "type":"Services"
        }
    ],
    "sg:phone":"+32 3 650 00 01",
    "sg:postcode":"2930",
    "sg:province":"Antwerpen",
    "sg:tags":[
        "physiotherapist"
    ],
    "wof:name":"Merckx R",
    "wof:placetype":"venue"
},
  "geometry": {"coordinates":[4.4856128693,51.291557312],"type":"Point"}
}