{
  "type": "Feature",
  "properties": {
    "addr:full":"Sint-gabri\u00eblstraat 23 Boechout Antwerpen 2530",
    "addr:housenumber":"23",
    "addr:postcode":"2530",
    "addr:street":"Sint-Gabrie\u0308Lstraat",
    "iso:country":"BE",
    "sg:address":"Sint-gabri\u00eblstraat 23",
    "sg:city":"Boechout",
    "sg:classifiers":[
        {
            "category":"Building & Trades",
            "subcategory":"Construction",
            "type":"Services"
        }
    ],
    "sg:phone":"+32 3 455 00 39",
    "sg:postcode":"2530",
    "sg:province":"Antwerpen",
    "sg:tags":[
        "surveyor",
        "-"
    ],
    "wof:name":"Jopro Bvba",
    "wof:placetype":"venue"
},
  "geometry": {"coordinates":[4.4849791527,51.1621742249],"type":"Point"}
}