{
  "type": "Feature",
  "properties": {
    "iso:country":"BE",
    "sg:address":"Ry D\u00c8l Vau 2ba",
    "sg:city":"Gesves",
    "sg:orig_category":"M\u00e9decins and sp\u00e9cialistes",
    "sg:phone":"+32 83 67 70 84",
    "sg:postcode":"5340",
    "sg:province":"Namur",
    "wof:name":"Fran\u00c7ois Michel",
    "wof:placetype":"venue"
},
  "geometry": {"coordinates":[5.0653882027,50.4048423767],"type":"Point"}
}