{
  "type": "Feature",
  "properties": {
    "addr:full":"Oude Kantinestraat 1 Roeselare (oekene) West-Vlaanderen 8800",
    "addr:housenumber":"1",
    "addr:postcode":"8800",
    "addr:street":"Oude Kantinestraat",
    "iso:country":"BE",
    "sg:address":"Oude Kantinestraat 1",
    "sg:city":"Roeselare (oekene)",
    "sg:classifiers":[
        {
            "category":"Farming",
            "subcategory":"Farm & Veterinary Services",
            "type":"Manufacturing & Wholesale Goods"
        }
    ],
    "sg:phone":"+32 51 20 21 63",
    "sg:postcode":"8800",
    "sg:province":"West-Vlaanderen",
    "sg:tags":[
        "agricultural",
        "contractor"
    ],
    "wof:name":"Soenen R & R",
    "wof:placetype":"venue"
},
  "geometry": {"coordinates":[3.1564180851,50.9114875793],"type":"Point"}
}