{
  "type": "Feature",
  "properties": {
    "iso:country":"BE",
    "sg:address":"Stationsstraat 98",
    "sg:city":"Damme",
    "sg:orig_category":"Textiles. Souvenirs and objets artisanaux",
    "sg:phone":"+32 50 36 31 71",
    "sg:postcode":"8340",
    "sg:province":"West-Vlaanderen",
    "wof:name":"Huis Naaldeke",
    "wof:placetype":"venue"
},
  "geometry": {"coordinates":[3.3176269531,51.2070503235],"type":"Point"}
}