{
  "type": "Feature",
  "properties": {
    "iso:country":"BE",
    "sg:address":"Place Du Beau-site 4",
    "sg:city":"Rixensart",
    "sg:orig_category":"Epiceries",
    "sg:phone":"+32 2 653 71 18",
    "sg:postcode":"1330",
    "sg:province":"Brabant Wallon",
    "wof:name":"Delhaize",
    "wof:placetype":"venue"
},
  "geometry": {"coordinates":[4.5461168289,50.712223053],"type":"Point"}
}