{
  "type": "Feature",
  "properties": {
    "addr:full":"Lauwstraat 34 Gent Oost-Vlaanderen 9051",
    "addr:housenumber":"34",
    "addr:postcode":"9051",
    "addr:street":"Lauwstraat;Oost-Vlaanderen",
    "iso:country":"BE",
    "sg:address":"Lauwstraat 34",
    "sg:city":"Gent",
    "sg:orig_category":"Bloemen and planten",
    "sg:phone":"+32 9 220 84 97",
    "sg:postcode":"9051",
    "sg:province":"Oost-Vlaanderen",
    "wof:name":"Dorothea",
    "wof:placetype":"venue"
},
  "geometry": {"coordinates":[3.6657710075,51.0232925415],"type":"Point"}
}