{
  "type": "Feature",
  "properties": {
    "addr:full":"Erasme Ruelensvest 193 Leuven Vlaams-Brabant 3001",
    "addr:housenumber":"193",
    "addr:postcode":"3001",
    "addr:street":"Erasme Ruelensvest",
    "iso:country":"BE",
    "sg:address":"Erasme Ruelensvest 193",
    "sg:city":"Leuven",
    "sg:orig_category":"Avocats and conseillers juridiques",
    "sg:phone":"+32 16 29 59 40",
    "sg:postcode":"3001",
    "sg:province":"Vlaams-Brabant",
    "wof:name":"Christine Mathieu",
    "wof:placetype":"venue"
},
  "geometry": {"coordinates":[4.7079529762,50.868976593],"type":"Point"}
}