{
  "type": "Feature",
  "properties": {
    "addr:full":"Rue Des Awirs 1 Clavier (bois - Et - Borsu) Li\u00e8ge 4560",
    "addr:housenumber":"1",
    "addr:postcode":"4560",
    "addr:street":"Rue Des Awirs",
    "iso:country":"BE",
    "sg:address":"Rue Des Awirs 1",
    "sg:city":"Clavier (bois - Et - Borsu)",
    "sg:classifiers":[
        {
            "category":"Health Services",
            "subcategory":"Health Practitioner",
            "type":"Services"
        }
    ],
    "sg:phone":"+32 86 34 40 35",
    "sg:postcode":"4560",
    "sg:province":"Li\u00e8ge",
    "sg:tags":[
        "physiotherapist"
    ],
    "wof:name":"Raiglot Vinciane",
    "wof:placetype":"venue"
},
  "geometry": {"coordinates":[5.3321471214,50.3950843811],"type":"Point"}
}