{
  "type": "Feature",
  "properties": {
    "addr:full":"Heirbaan 159 Dendermonde Oost-Vlaanderen 9200",
    "addr:housenumber":"159",
    "addr:postcode":"9200",
    "addr:street":"Heirbaan;Oost-Vlaanderen",
    "iso:country":"BE",
    "sg:address":"Heirbaan 159",
    "sg:city":"Dendermonde",
    "sg:orig_category":"Supermarch\u00e9s",
    "sg:phone":"+32 52 21 56 60",
    "sg:postcode":"9200",
    "sg:province":"Oost-Vlaanderen",
    "wof:name":"Delhaize",
    "wof:placetype":"venue"
},
  "geometry": {"coordinates":[4.1178889275,51.0099449158],"type":"Point"}
}