{
  "type": "Feature",
  "properties": {
    "iso:country":"BE",
    "sg:address":"Tereken 146",
    "sg:city":"Sint-niklaas",
    "sg:orig_category":"Pain, p\u00e2tisseries and confiseries",
    "sg:phone":"+32 3 766 58 82",
    "sg:postcode":"9100",
    "sg:province":"Oost-Vlaanderen",
    "wof:name":"Bakkerij Thierens",
    "wof:placetype":"venue"
},
  "geometry": {"coordinates":[4.1487588882,51.1503486633],"type":"Point"}
}