{
  "type": "Feature",
  "properties": {
    "addr:full":"Nicolaylaan 105 Leopoldsburg Limburg 3970",
    "addr:housenumber":"105",
    "addr:postcode":"3970",
    "addr:street":"Nicolaylaan",
    "iso:country":"BE",
    "sg:address":"Nicolaylaan 105",
    "sg:city":"Leopoldsburg",
    "sg:orig_category":"Kinderopvang",
    "sg:phone":"+32 11 34 83 91",
    "sg:postcode":"3970",
    "sg:province":"Limburg",
    "wof:name":"Dienst Onthaalgezinnen",
    "wof:placetype":"venue"
},
  "geometry": {"coordinates":[5.2582101822,51.119052887],"type":"Point"}
}