{
  "type": "Feature",
  "properties": {
    "addr:full":"Victor Heylenlei 15 Boechout Antwerpen 2530",
    "addr:housenumber":"15",
    "addr:postcode":"2530",
    "addr:street":"Victor Heylenlei",
    "iso:country":"BE",
    "sg:address":"Victor Heylenlei 15",
    "sg:city":"Boechout",
    "sg:classifiers":[
        {
            "category":"Personal",
            "subcategory":"Beauty Salon",
            "type":"Services"
        }
    ],
    "sg:phone":"+32 3 455 60 16",
    "sg:postcode":"2530",
    "sg:province":"Antwerpen",
    "sg:tags":[
        "de",
        "coiffure"
    ],
    "wof:name":"Robert Patteet",
    "wof:placetype":"venue"
},
  "geometry": {"coordinates":[4.4844107628,51.1679992676],"type":"Point"}
}