{
  "type": "Feature",
  "properties": {
    "addr:full":"Nieuwmolenstraat 1bb Aalst Oost-Vlaanderen 9310",
    "addr:housenumber":"1bb",
    "addr:postcode":"9310",
    "addr:street":"Nieuwmolenstraat",
    "iso:country":"BE",
    "sg:address":"Nieuwmolenstraat 1bb",
    "sg:city":"Aalst",
    "sg:orig_category":"Boucheries",
    "sg:phone":"+32 53 77 49 09",
    "sg:postcode":"9310",
    "sg:province":"Oost-Vlaanderen",
    "wof:name":"Chris Jaspaert",
    "wof:placetype":"venue"
},
  "geometry": {"coordinates":[4.0992040634,50.9552726746],"type":"Point"}
}