{
  "type": "Feature",
  "properties": {
    "iso:country":"BE",
    "sg:address":"Hoogstraat 71",
    "sg:city":"Harelbeke",
    "sg:orig_category":"Agences d'exp\u00e9dition. Fruits and l\u00e9gumes Gr",
    "sg:phone":"+32 56 72 70 85",
    "sg:postcode":"8531",
    "sg:province":"West-Vlaanderen",
    "wof:name":"Fa. Verbepex",
    "wof:placetype":"venue"
},
  "geometry": {"coordinates":[3.3162150383,50.8838157654],"type":"Point"}
}