{
  "type": "Feature",
  "properties": {
    "iso:country":"BE",
    "sg:address":"Driekerkenstraat 47",
    "sg:city":"Kortrijk (bissegem)",
    "sg:classifiers":[
        {
            "category":"Manufacturing",
            "subcategory":"Metals",
            "type":"Manufacturing & Wholesale Goods"
        }
    ],
    "sg:phone":"+32 56 35 18 98",
    "sg:postcode":"8501",
    "sg:province":"West-Vlaanderen",
    "sg:tags":[
        "sheet",
        "machinery",
        "working"
    ],
    "wof:name":"Amada Promecam",
    "wof:placetype":"venue"
},
  "geometry": {"coordinates":[3.2336709499,50.8435592651],"type":"Point"}
}