{
  "type": "Feature",
  "properties": {
    "addr:full":"Rue Lulay 56 Bassenge Li\u00e8ge 4690",
    "addr:housenumber":"56",
    "addr:postcode":"4690",
    "addr:street":"Rue Lulay",
    "iso:country":"BE",
    "sg:address":"Rue Lulay 56",
    "sg:city":"Bassenge",
    "sg:orig_category":"Banken and kredietinstellingen",
    "sg:phone":"+32 4 286 30 81",
    "sg:postcode":"4690",
    "sg:province":"Li\u00e8ge",
    "wof:name":"Dexia",
    "wof:placetype":"venue"
},
  "geometry": {"coordinates":[5.5479559898,50.7489776611],"type":"Point"}
}