{
  "type": "Feature",
  "properties": {
    "addr:full":"Koningin Astridlaan 18bdo Oostende West-Vlaanderen 8400",
    "addr:housenumber":"18bdo",
    "addr:postcode":"8400",
    "addr:street":"Koningin Astridlaan",
    "iso:country":"BE",
    "sg:address":"Koningin Astridlaan 18bdo",
    "sg:city":"Oostende",
    "sg:classifiers":[
        {
            "category":"Real Estate",
            "subcategory":"Real Estate Services",
            "type":"Services"
        }
    ],
    "sg:phone":"+32 59 50 85 65",
    "sg:postcode":"8400",
    "sg:province":"West-Vlaanderen",
    "wof:name":"Agence V.c.b.",
    "wof:placetype":"venue"
},
  "geometry": {"coordinates":[2.8952190876,51.2225570679],"type":"Point"}
}