{
  "type": "Feature",
  "properties": {
    "addr:full":"Passage Champagne Tubize Brabant Wallon 1480",
    "addr:postcode":"1480",
    "addr:street":"Passage Champagne;Wallon",
    "iso:country":"BE",
    "sg:address":"Passage Champagne",
    "sg:city":"Tubize",
    "sg:classifiers":[
        {
            "category":"Building & Trades",
            "subcategory":"Locksmith",
            "type":"Services"
        }
    ],
    "sg:phone":"+32 495 79 84 85",
    "sg:postcode":"1480",
    "sg:province":"Brabant Wallon",
    "sg:tags":[
        "lock",
        "key"
    ],
    "wof:name":"Artisan Express",
    "wof:placetype":"venue"
},
  "geometry": {"coordinates":[4.204308033,50.6932029724],"type":"Point"}
}