{
  "type": "Feature",
  "properties": {
    "addr:full":"Boomgaardstraat 164 Kuurne West-Vlaanderen 8520",
    "addr:housenumber":"164",
    "addr:postcode":"8520",
    "addr:street":"Boomgaardstraat",
    "iso:country":"BE",
    "sg:address":"Boomgaardstraat 164",
    "sg:city":"Kuurne",
    "sg:classifiers":[
        {
            "category":"Cafe",
            "type":"Food & Drink"
        }
    ],
    "sg:phone":"+32 56 36 01 07",
    "sg:postcode":"8520",
    "sg:province":"West-Vlaanderen",
    "sg:tags":[
        "caf\u00e9s"
    ],
    "wof:name":"Christ Soetaert",
    "wof:placetype":"venue"
},
  "geometry": {"coordinates":[3.2729849815,50.8520126343],"type":"Point"}
}