{
  "type": "Feature",
  "properties": {
    "addr:full":"Avenue G\u00e9n\u00e9ral Michel 1a Charleroi Hainaut 6000",
    "addr:housenumber":"1a",
    "addr:postcode":"6000",
    "addr:street":"Avenue Ge\u0301Ne\u0301Ral Michel;Hainaut",
    "iso:country":"BE",
    "sg:address":"Avenue G\u00e9n\u00e9ral Michel 1a",
    "sg:city":"Charleroi",
    "sg:classifiers":[
        {
            "category":"Professional",
            "subcategory":"Management & Consulting",
            "type":"Services"
        }
    ],
    "sg:phone":"+32 71 60 61 00",
    "sg:postcode":"6000",
    "sg:province":"Hainaut",
    "sg:tags":[
        "consultant"
    ],
    "wof:name":"Groupe Central De M\u00e9diation & D'arbitrage",
    "wof:placetype":"venue"
},
  "geometry": {"coordinates":[4.4504227638,50.4104766846],"type":"Point"}
}