{
  "type": "Feature",
  "properties": {
    "iso:country":"BE",
    "sg:address":"Meulemanslaan 32",
    "sg:city":"Westerlo (tongerlo)",
    "sg:classifiers":[
        {
            "category":"Fast Food",
            "type":"Food & Drink"
        }
    ],
    "sg:phone":"+32 14 54 25 74",
    "sg:postcode":"2260",
    "sg:province":"Antwerpen",
    "sg:tags":[
        "fried",
        "stand",
        "potato"
    ],
    "wof:name":"Big Friet",
    "wof:placetype":"venue"
},
  "geometry": {"coordinates":[4.9131140709,51.1036109924],"type":"Point"}
}