{
  "type": "Feature",
  "properties": {
    "addr:full":"Rue Du Cimeti\u00e8re 85 Beyne-heusay Li\u00e8ge 4610",
    "addr:housenumber":"85",
    "addr:postcode":"4610",
    "addr:street":"Rue Du Cimetie\u0300Re",
    "iso:country":"BE",
    "sg:address":"Rue Du Cimeti\u00e8re 85",
    "sg:city":"Beyne-heusay",
    "sg:classifiers":[
        {
            "category":"Retail",
            "subcategory":"Auto Repair",
            "type":"Services"
        }
    ],
    "sg:phone":"+32 4 365 95 89",
    "sg:postcode":"4610",
    "sg:province":"Li\u00e8ge",
    "sg:tags":[
        "automobile-body"
    ],
    "wof:name":"Winand",
    "wof:placetype":"venue"
},
  "geometry": {"coordinates":[5.6486001015,50.6252098083],"type":"Point"}
}