{
  "type": "Feature",
  "properties": {
    "addr:full":"Avenue Fran\u00e7ois Cornesse 21 Aywaille Li\u00e8ge 4920",
    "addr:housenumber":"21",
    "addr:postcode":"4920",
    "addr:street":"Avenue Franc\u0327Ois Cornesse",
    "iso:country":"BE",
    "sg:address":"Avenue Fran\u00e7ois Cornesse 21",
    "sg:city":"Aywaille",
    "sg:classifiers":[
        {
            "category":"Food & Beverages",
            "subcategory":"Chocolate",
            "type":"Retail Goods"
        }
    ],
    "sg:phone":"+32 4 384 75 09",
    "sg:postcode":"4920",
    "sg:province":"Li\u00e8ge",
    "sg:tags":[
        "confectionery",
        "-"
    ],
    "wof:name":"Leonidas",
    "wof:placetype":"venue"
},
  "geometry": {"coordinates":[5.6740517616,50.474407196],"type":"Point"}
}