{
  "type": "Feature",
  "properties": {
    "addr:full":"Rue Du Cimeti\u00c8re 29 Braine-le-chateau Brabant Wallon 1440",
    "addr:housenumber":"29",
    "addr:postcode":"1440",
    "addr:street":"Rue Du Cimetie\u0300Re;Brabant Wallon",
    "iso:country":"BE",
    "sg:address":"Rue Du Cimeti\u00c8re 29",
    "sg:city":"Braine-le-chateau",
    "sg:classifiers":[
        {
            "category":"Professional",
            "subcategory":"Accounting & Tax Preparation",
            "type":"Services"
        }
    ],
    "sg:phone":"+32 2 366 99 38",
    "sg:postcode":"1440",
    "sg:province":"Brabant Wallon",
    "sg:tags":[
        "accountant"
    ],
    "wof:name":"Luc Willems",
    "wof:placetype":"venue"
},
  "geometry": {"coordinates":[4.2686882019,50.673122406],"type":"Point"}
}