{
  "type": "Feature",
  "properties": {
    "iso:country":"BE",
    "sg:address":"Chauss\u00e9e De Charleroi 343",
    "sg:city":"Fosses-la-ville (le Roux)",
    "sg:classifiers":[
        {
            "category":"Shopping",
            "subcategory":"Books",
            "type":"Retail Goods"
        }
    ],
    "sg:phone":"+32 71 71 13 91",
    "sg:postcode":"5070",
    "sg:province":"Namur",
    "sg:tags":[
        "bookseller"
    ],
    "wof:name":"Roveltex Sprl",
    "wof:placetype":"venue"
},
  "geometry": {"coordinates":[4.6720647812,50.3931503296],"type":"Point"}
}