{
  "type": "Feature",
  "properties": {
    "addr:full":"Clos Des M\u00c9sanges 4 Waremme Li\u00e8ge 4300",
    "addr:housenumber":"4",
    "addr:postcode":"4300",
    "addr:street":"Clos Des Me\u0301Sanges",
    "iso:country":"BE",
    "sg:address":"Clos Des M\u00c9sanges 4",
    "sg:city":"Waremme",
    "sg:orig_category":"Dierenartsen",
    "sg:phone":"+32 19 32 27 71",
    "sg:postcode":"4300",
    "sg:province":"Li\u00e8ge",
    "wof:name":"Jean-francois Mercier",
    "wof:placetype":"venue"
},
  "geometry": {"coordinates":[5.2687029839,50.6985855103],"type":"Point"}
}