{
  "type": "Feature",
  "properties": {
    "addr:full":"Rue De Poix 105 Libin Luxembourg 6890",
    "addr:housenumber":"105",
    "addr:postcode":"6890",
    "addr:street":"Rue De Poix",
    "iso:country":"BE",
    "sg:address":"Rue De Poix 105",
    "sg:city":"Libin",
    "sg:orig_category":"Rev\u00eatements pour sols and murs. Construction de maisons",
    "sg:phone":"+32 61 65 59 50",
    "sg:postcode":"6890",
    "sg:province":"Luxembourg",
    "wof:name":"Fe. Norte J. & C.",
    "wof:placetype":"venue"
},
  "geometry": {"coordinates":[5.2572388649,49.9839859009],"type":"Point"}
}