{
  "type": "Feature",
  "properties": {
    "iso:country":"BE",
    "sg:address":"Passage De La Bourse 8",
    "sg:city":"Charleroi",
    "sg:orig_category":"Reisbureaus",
    "sg:phone":"+32 71 32 58 59",
    "sg:postcode":"6000",
    "sg:province":"Hainaut",
    "wof:name":"Voyages Wasteels",
    "wof:placetype":"venue"
},
  "geometry": {"coordinates":[4.4405097961,50.4073829651],"type":"Point"}
}