{
  "type": "Feature",
  "properties": {
    "addr:full":"Meensesteenweg 80 Kortrijk West-Vlaanderen 8500",
    "addr:housenumber":"80",
    "addr:postcode":"8500",
    "addr:street":"Meensesteenweg",
    "iso:country":"BE",
    "sg:address":"Meensesteenweg 80",
    "sg:city":"Kortrijk",
    "sg:classifiers":[
        {
            "category":"Bars & Pubs",
            "type":"Food & Drink"
        }
    ],
    "sg:phone":"+32 56 35 41 13",
    "sg:postcode":"8500",
    "sg:province":"West-Vlaanderen",
    "wof:name":"Vagabond",
    "wof:placetype":"venue"
},
  "geometry": {"coordinates":[3.2503449917,50.829875946],"type":"Point"}
}