{
  "type": "Feature",
  "properties": {
    "addr:full":"8920 Langemark-poelkapelle West-Vlaanderen 8920",
    "addr:postcode":"8920;8920",
    "iso:country":"BE",
    "sg:address":"8920",
    "sg:city":"Langemark-poelkapelle",
    "sg:orig_category":"Pharmaciens",
    "sg:phone":"+32 900 10 500",
    "sg:postcode":"8920",
    "sg:province":"West-Vlaanderen",
    "wof:name":"Pharmacies De Garde",
    "wof:placetype":"venue"
},
  "geometry": {"coordinates":[2.9163000584,50.9127006531],"type":"Point"}
}