{
  "type": "Feature",
  "properties": {
    "iso:country":"BE",
    "sg:address":"Grootkanonplein 5",
    "sg:city":"Gent",
    "sg:classifiers":[
        {
            "category":"Shopping",
            "subcategory":"Books",
            "type":"Retail Goods"
        }
    ],
    "sg:phone":"+32 9 233 22 76",
    "sg:postcode":"9000",
    "sg:province":"Oost-Vlaanderen",
    "sg:tags":[
        "bookseller"
    ],
    "wof:name":"Krokodil",
    "wof:placetype":"venue"
},
  "geometry": {"coordinates":[3.7246670723,51.0572280884],"type":"Point"}
}