{
  "type": "Feature",
  "properties": {
    "iso:country":"BE",
    "sg:address":"Frankrijklei 100b7",
    "sg:city":"Antwerpen",
    "sg:orig_category":"Artistes ind\u00e9pendants",
    "sg:phone":"+32 3 226 64 09",
    "sg:postcode":"2000",
    "sg:province":"Antwerpen",
    "wof:name":"Wil Beckers",
    "wof:placetype":"venue"
},
  "geometry": {"coordinates":[4.4125189781,51.2151069641],"type":"Point"}
}