{
  "type": "Feature",
  "properties": {
    "addr:full":"Rue De La Croix 14-16 Namur Namur 5000",
    "addr:postcode":"14-16;5000",
    "addr:street":"Rue De La Croix",
    "iso:country":"BE",
    "sg:address":"Rue De La Croix 14-16",
    "sg:city":"Namur",
    "sg:classifiers":[
        {
            "category":"Shopping",
            "subcategory":"Clothing, Apparel, & Fashions",
            "type":"Retail Goods"
        }
    ],
    "sg:phone":"+32 81 22 35 32",
    "sg:postcode":"5000",
    "sg:province":"Namur",
    "sg:tags":[
        "lady",
        "clothing",
        "-"
    ],
    "wof:name":"Mondi",
    "wof:placetype":"venue"
},
  "geometry": {"coordinates":[4.8649811745,50.4637756348],"type":"Point"}
}