{
  "type": "Feature",
  "properties": {
    "addr:full":"Sur Le Tombeux 4 Dison Li\u00e8ge 4821",
    "addr:housenumber":"4",
    "addr:postcode":"4821",
    "addr:street":"Le Tombeux",
    "iso:country":"BE",
    "sg:address":"Sur Le Tombeux 4",
    "sg:city":"Dison",
    "sg:orig_category":"Installation de menuiserie en bois and plastique",
    "sg:phone":"+32 87 35 42 45",
    "sg:postcode":"4821",
    "sg:province":"Li\u00e8ge",
    "wof:name":"Hiligsmann Fr\u00c8res",
    "wof:placetype":"venue"
},
  "geometry": {"coordinates":[5.881280899,50.6143875122],"type":"Point"}
}