{
  "type": "Feature",
  "properties": {
    "iso:country":"BE",
    "sg:address":"Gulden Sporenstraat 19",
    "sg:city":"Eeklo",
    "sg:orig_category":"Serres and speciale beglazing",
    "sg:phone":"+32 9 377 41 92",
    "sg:postcode":"9900",
    "sg:province":"Oost-Vlaanderen",
    "wof:name":"Eddy Jonckheere",
    "wof:placetype":"venue"
},
  "geometry": {"coordinates":[3.5730540752,51.1794624329],"type":"Point"}
}