{
  "type": "Feature",
  "properties": {
    "iso:country":"BE",
    "sg:address":"Bemptlaan 28",
    "sg:city":"Vorst/forest",
    "sg:orig_category":"Industri\u00eble wasserijen and droogkuis",
    "sg:phone":"+32 2 332 06 16",
    "sg:postcode":"1190",
    "sg:province":"Bruxelles-Capitale",
    "wof:name":"Speedy-wash",
    "wof:placetype":"venue"
},
  "geometry": {"coordinates":[4.3168101311,50.8024559021],"type":"Point"}
}