{
  "type": "Feature",
  "properties": {
    "addr:full":"Kapelstraat 1 Kontich Antwerpen 2550",
    "addr:housenumber":"1",
    "addr:postcode":"2550",
    "addr:street":"Kapelstraat",
    "iso:country":"BE",
    "sg:address":"Kapelstraat 1",
    "sg:city":"Kontich",
    "sg:classifiers":[
        {
            "category":"Restaurant",
            "type":"Food & Drink"
        }
    ],
    "sg:phone":"+32 3 457 03 62",
    "sg:postcode":"2550",
    "sg:province":"Antwerpen",
    "wof:name":"Ijs Miami",
    "wof:placetype":"venue"
},
  "geometry": {"coordinates":[4.4747209549,51.1289405823],"type":"Point"}
}