{
  "type": "Feature",
  "properties": {
    "addr:full":"Sint-jansstraat 11 Brugge West-Vlaanderen 8000",
    "addr:housenumber":"11",
    "addr:postcode":"8000",
    "addr:street":"Sint-Jansstraat",
    "iso:country":"BE",
    "sg:address":"Sint-jansstraat 11",
    "sg:city":"Brugge",
    "sg:classifiers":[
        {
            "category":"Community Center",
            "type":"Public Place"
        }
    ],
    "sg:phone":"+32 50 44 61 80",
    "sg:postcode":"8000",
    "sg:province":"West-Vlaanderen",
    "sg:tags":[
        "medical"
    ],
    "wof:name":"Inghelburch Centrum Psychische Revalidatie",
    "wof:placetype":"venue"
},
  "geometry": {"coordinates":[3.2271370888,51.2109985352],"type":"Point"}
}