{
  "type": "Feature",
  "properties": {
    "iso:country":"BE",
    "sg:address":"Onze-lieve-vrouwemarkt 2",
    "sg:city":"Roeselare",
    "sg:classifiers":[
        {
            "category":"Professional",
            "subcategory":"Printing & Photocopies",
            "type":"Services"
        }
    ],
    "sg:phone":"+32 51 22 26 66",
    "sg:postcode":"8800",
    "sg:province":"West-Vlaanderen",
    "sg:tags":[
        "-",
        "plan",
        "reproduction"
    ],
    "wof:name":"Alfa-studie-home Bvba",
    "wof:placetype":"venue"
},
  "geometry": {"coordinates":[3.1339919567,50.947517395],"type":"Point"}
}