{
  "type": "Feature",
  "properties": {
    "iso:country":"BE",
    "sg:address":"Route De Frasnes 42",
    "sg:city":"Ath",
    "sg:classifiers":[
        {
            "category":"Building & Trades",
            "subcategory":"Construction",
            "type":"Services"
        }
    ],
    "sg:phone":"+32 68 84 01 19",
    "sg:postcode":"7800",
    "sg:province":"Hainaut",
    "sg:tags":[
        "installation",
        "-",
        "central",
        "heating"
    ],
    "wof:name":"Jadoul Jm Ets",
    "wof:placetype":"venue"
},
  "geometry": {"coordinates":[3.7563040257,50.6373939514],"type":"Point"}
}