{
  "type": "Feature",
  "properties": {
    "addr:full":"Grand'rue 7 Aubange Luxembourg 6791",
    "addr:housenumber":"7",
    "addr:postcode":"6791",
    "addr:street":"Grand'Rue",
    "iso:country":"BE",
    "sg:address":"Grand'rue 7",
    "sg:city":"Aubange",
    "sg:orig_category":"Studios photographiques. Equipement photographique",
    "sg:phone":"+32 63 37 10 54",
    "sg:postcode":"6791",
    "sg:province":"Luxembourg",
    "wof:name":"Central Photo",
    "wof:placetype":"venue"
},
  "geometry": {"coordinates":[5.8356189728,49.5628623962],"type":"Point"}
}