{
  "type": "Feature",
  "properties": {
    "iso:country":"BE",
    "sg:address":"Eeuwfeestplein 9",
    "sg:city":"Overijse",
    "sg:orig_category":"Woningbouw",
    "sg:phone":"+32 2 687 30 14",
    "sg:postcode":"3090",
    "sg:province":"Vlaams-Brabant",
    "wof:name":"Gebroeders Butaye",
    "wof:placetype":"venue"
},
  "geometry": {"coordinates":[4.5299768448,50.7713050842],"type":"Point"}
}