{
  "type": "Feature",
  "properties": {
    "addr:full":"Rue Du Commerce 38 Ciney Namur 5590",
    "addr:housenumber":"38",
    "addr:postcode":"5590",
    "addr:street":"Rue Du Commerce",
    "iso:country":"BE",
    "sg:address":"Rue Du Commerce 38",
    "sg:city":"Ciney",
    "sg:classifiers":[
        {
            "category":"Shopping",
            "subcategory":"Books",
            "type":"Retail Goods"
        }
    ],
    "sg:phone":"+32 83 21 50 77",
    "sg:postcode":"5590",
    "sg:province":"Namur",
    "sg:tags":[
        "bookseller"
    ],
    "wof:name":"Librairie Moderne",
    "wof:placetype":"venue"
},
  "geometry": {"coordinates":[5.0987138748,50.2942619324],"type":"Point"}
}