{
  "type": "Feature",
  "properties": {
    "iso:country":"BE",
    "sg:address":"Heirweg Zuid 20",
    "sg:city":"Ingelmunster",
    "sg:orig_category":"D\u00e9chets and d\u00e9bris Articles non-alimentaires. Ramassage and traitement des d\u00e9chets m\u00e9nagers",
    "sg:phone":"+32 51 33 50 67",
    "sg:postcode":"8770",
    "sg:province":"West-Vlaanderen",
    "wof:name":"Matco",
    "wof:placetype":"venue"
},
  "geometry": {"coordinates":[3.2820060253,50.9053535461],"type":"Point"}
}