{
  "type": "Feature",
  "properties": {
    "iso:country":"BE",
    "sg:address":"Frans Rottiersstraat 3",
    "sg:city":"Bornem (hingene)",
    "sg:classifiers":[
        {
            "category":"Shopping",
            "subcategory":"Gifts & Souvenirs",
            "type":"Retail Goods"
        }
    ],
    "sg:phone":"+32 3 889 88 82",
    "sg:postcode":"2880",
    "sg:province":"Antwerpen",
    "sg:tags":[
        "postcard",
        "picture",
        "greeting",
        "card"
    ],
    "wof:name":"Anders Bvba",
    "wof:placetype":"venue"
},
  "geometry": {"coordinates":[4.3007831573,51.1065368652],"type":"Point"}
}