{
  "type": "Feature",
  "properties": {
    "iso:country":"BE",
    "sg:address":"Eksterlaan 16",
    "sg:city":"Kapellen",
    "sg:classifiers":[
        {
            "category":"Professional",
            "subcategory":"Accounting & Tax Preparation",
            "type":"Services"
        }
    ],
    "sg:phone":"+32 3 666 36 96",
    "sg:postcode":"2950",
    "sg:province":"Antwerpen",
    "sg:tags":[
        "accountant"
    ],
    "wof:name":"Jacobs W",
    "wof:placetype":"venue"
},
  "geometry": {"coordinates":[4.4553089142,51.343788147],"type":"Point"}
}