{
  "type": "Feature",
  "properties": {
    "addr:full":"Wapenplaats 27 Dentergem (wakken) West-Vlaanderen 8720",
    "addr:housenumber":"27",
    "addr:postcode":"8720",
    "addr:street":"Wapenplaats",
    "iso:country":"BE",
    "sg:address":"Wapenplaats 27",
    "sg:city":"Dentergem (wakken)",
    "sg:classifiers":[
        {
            "category":"Bars & Pubs",
            "type":"Food & Drink"
        }
    ],
    "sg:phone":"+32 56 60 60 85",
    "sg:postcode":"8720",
    "sg:province":"West-Vlaanderen",
    "wof:name":"De Haan",
    "wof:placetype":"venue"
},
  "geometry": {"coordinates":[3.3979671001,50.9310035706],"type":"Point"}
}