{
  "type": "Feature",
  "properties": {
    "addr:full":"De Langheplein 8 Blankenberge West-Vlaanderen 8370",
    "addr:housenumber":"8",
    "addr:postcode":"8370",
    "iso:country":"BE",
    "sg:address":"De Langheplein 8",
    "sg:city":"Blankenberge",
    "sg:orig_category":"Slagers",
    "sg:phone":"+32 50 41 33 23",
    "sg:postcode":"8370",
    "sg:province":"West-Vlaanderen",
    "wof:name":"Johan Demeyer",
    "wof:placetype":"venue"
},
  "geometry": {"coordinates":[3.1235818863,51.3096504211],"type":"Point"}
}