{
  "type": "Feature",
  "properties": {
    "addr:full":"Rue De La M\u00c9lop\u00c9e 43 Sint-jans-molenbeek/molenbeek-saint-jean Bruxelles-Capitale 1080",
    "addr:housenumber":"43",
    "addr:postcode":"1080",
    "addr:street":"Rue De La Me\u0301Lope\u0301E",
    "iso:country":"BE",
    "sg:address":"Rue De La M\u00c9lop\u00c9e 43",
    "sg:city":"Sint-jans-molenbeek/molenbeek-saint-jean",
    "sg:orig_category":"Boucheries",
    "sg:phone":"+32 2 410 85 78",
    "sg:postcode":"1080",
    "sg:province":"Bruxelles-Capitale",
    "wof:name":"Beenhouwerij Arnold",
    "wof:placetype":"venue"
},
  "geometry": {"coordinates":[4.315114975,50.8536109924],"type":"Point"}
}