{
  "type": "Feature",
  "properties": {
    "addr:full":"Rue De Namur 29 Philippeville Namur 5600",
    "addr:housenumber":"29",
    "addr:postcode":"5600",
    "addr:street":"Rue De Namur",
    "iso:country":"BE",
    "sg:address":"Rue De Namur 29",
    "sg:city":"Philippeville",
    "sg:classifiers":[
        {
            "category":"Personal",
            "subcategory":"Beauty Salon",
            "type":"Services"
        }
    ],
    "sg:phone":"+32 71 66 76 30",
    "sg:postcode":"5600",
    "sg:province":"Namur",
    "sg:tags":[
        "de",
        "coiffure"
    ],
    "wof:name":"Michel Henry",
    "wof:placetype":"venue"
},
  "geometry": {"coordinates":[4.5455498695,50.197227478],"type":"Point"}
}