{
  "type": "Feature",
  "properties": {
    "iso:country":"BE",
    "sg:address":"March\u00e9 Aux L\u00e9gumes 3",
    "sg:city":"Arlon",
    "sg:classifiers":[
        {
            "category":"Shopping",
            "subcategory":"Books",
            "type":"Retail Goods"
        }
    ],
    "sg:phone":"+32 61 22 27 47",
    "sg:postcode":"6700",
    "sg:province":"Luxembourg",
    "sg:tags":[
        "bookseller"
    ],
    "wof:name":"City Press",
    "wof:placetype":"venue"
},
  "geometry": {"coordinates":[5.8126020432,49.6836738586],"type":"Point"}
}