{
  "type": "Feature",
  "properties": {
    "addr:full":"Rue Du Thier 1 Soumagne Li\u00e8ge 4631",
    "addr:housenumber":"1",
    "addr:postcode":"4631",
    "addr:street":"Rue Du Thier",
    "iso:country":"BE",
    "sg:address":"Rue Du Thier 1",
    "sg:city":"Soumagne",
    "sg:orig_category":"Enseignement maternel and primaire",
    "sg:phone":"+32 4 377 97 82",
    "sg:postcode":"4631",
    "sg:province":"Li\u00e8ge",
    "wof:name":"Ecole Fond. Communale",
    "wof:placetype":"venue"
},
  "geometry": {"coordinates":[5.7086839676,50.6429595947],"type":"Point"}
}