{
  "type": "Feature",
  "properties": {
    "iso:country":"BE",
    "sg:address":"Albertdreef 2",
    "sg:city":"Brecht",
    "sg:orig_category":"Boekhouders",
    "sg:phone":"+32 3 636 31 42",
    "sg:postcode":"2960",
    "sg:province":"Antwerpen",
    "wof:name":"Atreyu",
    "wof:placetype":"venue"
},
  "geometry": {"coordinates":[4.5525598526,51.2908782959],"type":"Point"}
}