{
  "type": "Feature",
  "properties": {
    "iso:country":"BE",
    "sg:address":"Grotestraat 27",
    "sg:city":"Geraardsbergen",
    "sg:orig_category":"Advocaten and juridische adviseurs",
    "sg:phone":"+32 54 41 18 93",
    "sg:postcode":"9500",
    "sg:province":"Oost-Vlaanderen",
    "wof:name":"Fabienne Uylebroeck",
    "wof:placetype":"venue"
},
  "geometry": {"coordinates":[3.8785800934,50.7718696594],"type":"Point"}
}