{
  "type": "Feature",
  "properties": {
    "addr:full":"Hamerstraat 19 Stekene Oost-Vlaanderen 9190",
    "addr:housenumber":"19",
    "addr:postcode":"9190",
    "addr:street":"Hamerstraat",
    "iso:country":"BE",
    "sg:address":"Hamerstraat 19",
    "sg:city":"Stekene",
    "sg:classifiers":[
        {
            "category":"Freight",
            "type":"Transportation"
        }
    ],
    "sg:phone":"+32 3 779 65 64",
    "sg:postcode":"9190",
    "sg:province":"Oost-Vlaanderen",
    "sg:tags":[
        "-",
        "transport"
    ],
    "wof:name":"Esd Trans Bvba",
    "wof:placetype":"venue"
},
  "geometry": {"coordinates":[4.0257692337,51.211894989],"type":"Point"}
}