{
  "type": "Feature",
  "properties": {
    "iso:country":"BE",
    "sg:address":"Rue De Charleroi 40",
    "sg:city":"Genappe",
    "sg:orig_category":"Banken and kredietinstellingen",
    "sg:phone":"+32 67 77 20 55",
    "sg:postcode":"1470",
    "sg:province":"Brabant Wallon",
    "wof:name":"Fortis",
    "wof:placetype":"venue"
},
  "geometry": {"coordinates":[4.4503779411,50.6094779968],"type":"Point"}
}