{
  "type": "Feature",
  "properties": {
    "iso:country":"BE",
    "sg:address":"Kan. Van Hoonackerstraat 22b8",
    "sg:city":"Brugge",
    "sg:orig_category":"Instituts de beaut\u00e9",
    "sg:phone":"+32 50 31 86 18",
    "sg:postcode":"8000",
    "sg:province":"West-Vlaanderen",
    "wof:name":"De Laere R.m.",
    "wof:placetype":"venue"
},
  "geometry": {"coordinates":[3.2050030231,51.2145500183],"type":"Point"}
}