{
  "type": "Feature",
  "properties": {
    "iso:country":"BE",
    "sg:address":"Veemarkt 4",
    "sg:city":"Ronse/renaix",
    "sg:orig_category":"Herstellingen and onderhoud aan huis voor voertuigen",
    "sg:phone":"+32 55 20 77 04",
    "sg:postcode":"9600",
    "sg:province":"Oost-Vlaanderen",
    "wof:name":"D\u00c9pannage Dumortier",
    "wof:placetype":"venue"
},
  "geometry": {"coordinates":[3.6050169468,50.7484550476],"type":"Point"}
}