{
  "type": "Feature",
  "properties": {
    "addr:full":"Hoge Hul 54-56 Brugge West-Vlaanderen 8000",
    "addr:housenumber":"54-56",
    "addr:postcode":"8000",
    "addr:street":"Hoge Hul",
    "iso:country":"BE",
    "sg:address":"Hoge Hul 54-56",
    "sg:city":"Brugge",
    "sg:classifiers":[
        {
            "category":"Home & Garden",
            "subcategory":"Kitchen Supply",
            "type":"Retail Goods"
        }
    ],
    "sg:phone":"+32 50 31 91 41",
    "sg:postcode":"8000",
    "sg:province":"West-Vlaanderen",
    "sg:tags":[
        "installation"
    ],
    "wof:name":"Van Der Jeugt",
    "wof:placetype":"venue"
},
  "geometry": {"coordinates":[3.1991980076,51.2456550598],"type":"Point"}
}