{
  "type": "Feature",
  "properties": {
    "iso:country":"BE",
    "sg:address":"Bruggestraat 22",
    "sg:city":"Staden",
    "sg:orig_category":"Dierenartsen",
    "sg:phone":"+32 51 70 14 20",
    "sg:postcode":"8840",
    "sg:province":"West-Vlaanderen",
    "wof:name":"Roland Anseeuw",
    "wof:placetype":"venue"
},
  "geometry": {"coordinates":[3.0177509785,50.9751014709],"type":"Point"}
}