{
  "type": "Feature",
  "properties": {
    "addr:full":"Jennekensstraat 41b3 Haacht Vlaams-Brabant 3150",
    "addr:housenumber":"41b3",
    "addr:postcode":"3150",
    "addr:street":"Jennekensstraat",
    "iso:country":"BE",
    "sg:address":"Jennekensstraat 41b3",
    "sg:city":"Haacht",
    "sg:orig_category":"M\u00e9decins and sp\u00e9cialistes",
    "sg:phone":"+32 16 60 94 24",
    "sg:postcode":"3150",
    "sg:province":"Vlaams-Brabant",
    "wof:name":"H. Heulens",
    "wof:placetype":"venue"
},
  "geometry": {"coordinates":[4.6295428276,50.9703292847],"type":"Point"}
}