{
  "type": "Feature",
  "properties": {
    "iso:country":"BE",
    "sg:address":"Weg Naar Zwartberg 141",
    "sg:city":"Houthalen-helchteren",
    "sg:orig_category":"Drukkerijen and copyshops",
    "sg:phone":"+32 89 24 01 74",
    "sg:postcode":"3530",
    "sg:province":"Limburg",
    "wof:name":"A.a.p.g.",
    "wof:placetype":"venue"
},
  "geometry": {"coordinates":[5.4711780548,51.0211868286],"type":"Point"}
}