{
  "type": "Feature",
  "properties": {
    "addr:full":"Viaductstraat 97 Elsene/ixelles Bruxelles-Capitale 1050",
    "addr:housenumber":"97",
    "addr:postcode":"1050",
    "addr:street":"Viaductstraat",
    "iso:country":"BE",
    "sg:address":"Viaductstraat 97",
    "sg:city":"Elsene/ixelles",
    "sg:orig_category":"Algemeen secundair onderwijs",
    "sg:phone":"+32 2 515 61 11",
    "sg:postcode":"1050",
    "sg:province":"Bruxelles-Capitale",
    "wof:name":"Ecole Edmond Peeters",
    "wof:placetype":"venue"
},
  "geometry": {"coordinates":[4.3715319633,50.8337898254],"type":"Point"}
}