{
  "type": "Feature",
  "properties": {
    "iso:country":"BE",
    "sg:address":"Baron De Gieylaan 34",
    "sg:city":"De Pinte",
    "sg:orig_category":"Entretien and r\u00e9parations de voitures",
    "sg:phone":"+32 9 282 33 62",
    "sg:postcode":"9840",
    "sg:province":"Oost-Vlaanderen",
    "wof:name":"Garage Delbaere",
    "wof:placetype":"venue"
},
  "geometry": {"coordinates":[3.6539199352,50.9929618835],"type":"Point"}
}