{
  "type": "Feature",
  "properties": {
    "addr:full":"J. Jordaensln 6 Zemst Vlaams-Brabant 1980",
    "addr:housenumber":"6",
    "addr:postcode":"1980",
    "addr:street":"Vlaams-Brabant",
    "iso:country":"BE",
    "sg:address":"J. Jordaensln 6",
    "sg:city":"Zemst",
    "sg:orig_category":"Effectenmakelaars and vermogensbeheer",
    "sg:phone":"+32 15 61 26 94",
    "sg:postcode":"1980",
    "sg:province":"Vlaams-Brabant",
    "wof:name":"Andries F",
    "wof:placetype":"venue"
},
  "geometry": {"coordinates":[4.4628300667,50.9819908142],"type":"Point"}
}