{
  "type": "Feature",
  "properties": {
    "iso:country":"BE",
    "sg:address":"Nielstraat 18",
    "sg:city":"Gingelom",
    "sg:orig_category":"Dranken",
    "sg:phone":"+32 11 88 17 00",
    "sg:postcode":"3890",
    "sg:province":"Limburg",
    "wof:name":"Remi Graindor",
    "wof:placetype":"venue"
},
  "geometry": {"coordinates":[5.1357750893,50.74741745],"type":"Point"}
}