{
  "type": "Feature",
  "properties": {
    "addr:full":"Rekollettenstraat 27bd Kortrijk West-Vlaanderen 8500",
    "addr:housenumber":"27bd",
    "addr:postcode":"8500",
    "addr:street":"Rekollettenstraat",
    "iso:country":"BE",
    "sg:address":"Rekollettenstraat 27bd",
    "sg:city":"Kortrijk",
    "sg:orig_category":"Dranken Gh",
    "sg:phone":"+32 56 35 17 65",
    "sg:postcode":"8500",
    "sg:province":"West-Vlaanderen",
    "wof:name":"Groep De Grijse",
    "wof:placetype":"venue"
},
  "geometry": {"coordinates":[3.2570500374,50.8312721252],"type":"Point"}
}