{
  "type": "Feature",
  "properties": {
    "iso:country":"BE",
    "sg:address":"Abdijstraat 111",
    "sg:city":"Oudenaarde",
    "sg:classifiers":[
        {
            "category":"Cafe",
            "type":"Food & Drink"
        }
    ],
    "sg:phone":"+32 55 31 41 68",
    "sg:postcode":"9700",
    "sg:province":"Oost-Vlaanderen",
    "sg:tags":[
        "caf\u00e9s"
    ],
    "wof:name":"Caf\u00c9 Sportvriend",
    "wof:placetype":"venue"
},
  "geometry": {"coordinates":[3.6339240074,50.8598823547],"type":"Point"}
}