{
  "type": "Feature",
  "properties": {
    "addr:full":"Naamsestraat 150 Leuven Vlaams-Brabant 3000",
    "addr:housenumber":"150",
    "addr:postcode":"3000",
    "addr:street":"Naamsestraat",
    "iso:country":"BE",
    "sg:address":"Naamsestraat 150",
    "sg:city":"Leuven",
    "sg:classifiers":[
        {
            "category":"Fast Food",
            "type":"Food & Drink"
        }
    ],
    "sg:phone":"+32 16 20 73 86",
    "sg:postcode":"3000",
    "sg:province":"Vlaams-Brabant",
    "sg:tags":[
        "\u00c0",
        "emporter",
        "restaurants"
    ],
    "wof:name":"Restaurant Kwai",
    "wof:placetype":"venue"
},
  "geometry": {"coordinates":[4.6991438866,50.8705635071],"type":"Point"}
}