{
  "type": "Feature",
  "properties": {
    "iso:country":"BE",
    "sg:address":"Lindestraat 18",
    "sg:city":"Poperinge",
    "sg:orig_category":"Eleveurs and marchands de porcs. Eleveurs de bovins",
    "sg:phone":"+32 57 30 06 78",
    "sg:postcode":"8972",
    "sg:province":"West-Vlaanderen",
    "wof:name":"Frans Vandevelde",
    "wof:placetype":"venue"
},
  "geometry": {"coordinates":[2.6481308937,50.9274635315],"type":"Point"}
}