{
  "type": "Feature",
  "properties": {
    "addr:full":"Avenue Du Centaure 55 Sint-lambrechts-woluwe/woluwe-saint-lambert Bruxelles-Capitale 1200",
    "addr:housenumber":"55",
    "addr:postcode":"1200",
    "addr:street":"Avenue Du Centaure",
    "iso:country":"BE",
    "sg:address":"Avenue Du Centaure 55",
    "sg:city":"Sint-lambrechts-woluwe/woluwe-saint-lambert",
    "sg:orig_category":"Agences de relations publiques",
    "sg:phone":"+32 2 770 74 65",
    "sg:postcode":"1200",
    "sg:province":"Bruxelles-Capitale",
    "wof:name":"Bureau Espace Communicat.",
    "wof:placetype":"venue"
},
  "geometry": {"coordinates":[4.4146051407,50.8526649475],"type":"Point"}
}