{
  "type": "Feature",
  "properties": {
    "addr:full":"Chauss\u00e9e Brunehault 39 Leuze-en-hainaut (blicquy) Hainaut 7903",
    "addr:housenumber":"39",
    "addr:postcode":"7903",
    "addr:street":"Chausse\u0301E Brunehault",
    "iso:country":"BE",
    "sg:address":"Chauss\u00e9e Brunehault 39",
    "sg:city":"Leuze-en-hainaut (blicquy)",
    "sg:classifiers":[
        {
            "category":"Utilities",
            "subcategory":"Fuel Oil & Lpg",
            "type":"Services"
        }
    ],
    "sg:phone":"+32 69 66 31 11",
    "sg:postcode":"7903",
    "sg:province":"Hainaut",
    "wof:name":"Liegeois Allary Ets",
    "wof:placetype":"venue"
},
  "geometry": {"coordinates":[3.6922059059,50.5891075134],"type":"Point"}
}