{
  "type": "Feature",
  "properties": {
    "iso:country":"BE",
    "sg:address":"Bolk 17",
    "sg:city":"Vosselaar",
    "sg:classifiers":[
        {
            "category":"Health Services",
            "subcategory":"Dentist",
            "type":"Services"
        }
    ],
    "sg:phone":"+32 14 61 49 97",
    "sg:postcode":"2350",
    "sg:province":"Antwerpen",
    "wof:name":"Hendrickx Paul",
    "wof:placetype":"venue"
},
  "geometry": {"coordinates":[4.8873238564,51.310710907],"type":"Point"}
}