{
  "type": "Feature",
  "properties": {
    "iso:country":"BE",
    "sg:address":"Paardestraat 30",
    "sg:city":"Pittem",
    "sg:orig_category":"V\u00e9t\u00e9rinaires",
    "sg:phone":"+32 51 46 75 35",
    "sg:postcode":"8740",
    "sg:province":"West-Vlaanderen",
    "wof:name":"Geert Michels",
    "wof:placetype":"venue"
},
  "geometry": {"coordinates":[3.2618260384,51.0168876648],"type":"Point"}
}