{
  "type": "Feature",
  "properties": {
    "iso:country":"BE",
    "sg:address":"Rue De La Biderie 1",
    "sg:city":"Chi\u00e8vres (grosage)",
    "sg:classifiers":[
        {
            "category":"Freight",
            "type":"Transportation"
        }
    ],
    "sg:phone":"+32 69 68 95 24",
    "sg:postcode":"7950",
    "sg:province":"Hainaut",
    "sg:tags":[
        "-",
        "transport"
    ],
    "wof:name":"Wiseur-rouse",
    "wof:placetype":"venue"
},
  "geometry": {"coordinates":[3.7605159283,50.5425376892],"type":"Point"}
}