{
  "type": "Feature",
  "properties": {
    "addr:full":"Gestelsesteenweg 111 Meerhout Antwerpen 2450",
    "addr:housenumber":"111",
    "addr:postcode":"2450",
    "addr:street":"Gestelsesteenweg",
    "iso:country":"BE",
    "sg:address":"Gestelsesteenweg 111",
    "sg:city":"Meerhout",
    "sg:orig_category":"Artsen and specialisten",
    "sg:phone":"+32 14 30 10 62",
    "sg:postcode":"2450",
    "sg:province":"Antwerpen",
    "wof:name":"Theo Lebon",
    "wof:placetype":"venue"
},
  "geometry": {"coordinates":[5.0917100906,51.1197013855],"type":"Point"}
}