{
  "type": "Feature",
  "properties": {
    "addr:full":"Wezelhof 40 Mol Antwerpen 2400",
    "addr:housenumber":"40",
    "addr:postcode":"2400",
    "addr:street":"Wezelhof",
    "iso:country":"BE",
    "sg:address":"Wezelhof 40",
    "sg:city":"Mol",
    "sg:orig_category":"Woningbouw",
    "sg:phone":"+32 14 81 48 77",
    "sg:postcode":"2400",
    "sg:province":"Antwerpen",
    "wof:name":"Ferdinand J.geenen",
    "wof:placetype":"venue"
},
  "geometry": {"coordinates":[5.2217278481,51.1884689331],"type":"Point"}
}