{
  "type": "Feature",
  "properties": {
    "addr:full":"Schrikheidestraat 13 Beringen (koersel) Limburg 3582",
    "addr:housenumber":"13",
    "addr:postcode":"3582",
    "addr:street":"Schrikheidestraat",
    "iso:country":"BE",
    "sg:address":"Schrikheidestraat 13",
    "sg:city":"Beringen (koersel)",
    "sg:classifiers":[
        {
            "category":"Health Services",
            "subcategory":"Dentist",
            "type":"Services"
        }
    ],
    "sg:phone":"+32 11 42 19 69",
    "sg:postcode":"3582",
    "sg:province":"Limburg",
    "wof:name":"Tijskens Leon",
    "wof:placetype":"venue"
},
  "geometry": {"coordinates":[5.2708749771,51.0595359802],"type":"Point"}
}