{
  "type": "Feature",
  "properties": {
    "iso:country":"BE",
    "sg:address":"Kachtemsestraat 54",
    "sg:city":"Izegem",
    "sg:orig_category":"Instituts de beaut\u00e9",
    "sg:phone":"+32 51 31 43 08",
    "sg:postcode":"8870",
    "sg:province":"West-Vlaanderen",
    "wof:name":"Ann Verschuere",
    "wof:placetype":"venue"
},
  "geometry": {"coordinates":[3.207007885,50.9297790527],"type":"Point"}
}