{
  "type": "Feature",
  "properties": {
    "iso:country":"BE",
    "sg:address":"Rue De Gouy 60",
    "sg:city":"Chapelle-lez-herlaimont",
    "sg:orig_category":"Begrafeniswezen",
    "sg:phone":"+32 64 44 26 28",
    "sg:postcode":"7160",
    "sg:province":"Hainaut",
    "wof:name":"Fun\u00c9railles Duriau",
    "wof:placetype":"venue"
},
  "geometry": {"coordinates":[4.2868847847,50.4712181091],"type":"Point"}
}