{
  "type": "Feature",
  "properties": {
    "addr:full":"Avenue Des Platanes 34 Li\u00e8ge 1 (sclessin) Li\u00e8ge 4000",
    "addr:housenumber":"34;1",
    "addr:postcode":"4000",
    "addr:street":"Avenue Des Platanes;Sclessin Lie\u0300Ge",
    "iso:country":"BE",
    "sg:address":"Avenue Des Platanes 34",
    "sg:city":"Li\u00e8ge 1 (sclessin)",
    "sg:classifiers":[
        {
            "category":"Real Estate",
            "subcategory":"Architect",
            "type":"Services"
        }
    ],
    "sg:phone":"+32 4 254 16 98",
    "sg:postcode":"4000",
    "sg:province":"Li\u00e8ge",
    "wof:name":"Jacques P",
    "wof:placetype":"venue"
},
  "geometry": {"coordinates":[5.5593380928,50.6159477234],"type":"Point"}
}