{
  "type": "Feature",
  "properties": {
    "iso:country":"BE",
    "sg:address":"Van Stralenstraat 40",
    "sg:city":"Antwerpen",
    "sg:classifiers":[
        {
            "category":"Government",
            "subcategory":"Office",
            "type":"Public Place"
        }
    ],
    "sg:phone":"+32 3 232 72 18",
    "sg:postcode":"2060",
    "sg:province":"Antwerpen",
    "sg:tags":[
        "-",
        "tourism",
        "federation"
    ],
    "wof:name":"Vlaamse Jeugdherbergcentrale",
    "wof:placetype":"venue"
},
  "geometry": {"coordinates":[4.4191069603,51.2206764221],"type":"Point"}
}