{
  "type": "Feature",
  "properties": {
    "iso:country":"BE",
    "sg:address":"Sint-bernardse Steenweg 73",
    "sg:city":"Hemiksem",
    "sg:orig_category":"Newspapers, magazines, periodicals - Distribution",
    "sg:phone":"+32 3 887 47 19",
    "sg:postcode":"2620",
    "sg:province":"Antwerpen",
    "wof:name":"Abdy(d')",
    "wof:placetype":"venue"
},
  "geometry": {"coordinates":[4.3355898857,51.1321487427],"type":"Point"}
}