{
  "type": "Feature",
  "properties": {
    "addr:full":"Route De Luxembourg 183 Arlon Luxembourg 6700",
    "addr:housenumber":"183",
    "addr:postcode":"6700",
    "addr:street":"Route De Luxembourg",
    "iso:country":"BE",
    "sg:address":"Route De Luxembourg 183",
    "sg:city":"Arlon",
    "sg:orig_category":"Autombile concessionaires",
    "sg:phone":"+32 63 22 72 69",
    "sg:postcode":"6700",
    "sg:province":"Luxembourg",
    "wof:name":"Gar Eurauto Sprl",
    "wof:placetype":"venue"
},
  "geometry": {"coordinates":[5.8254780769,49.6737632751],"type":"Point"}
}