{
  "type": "Feature",
  "properties": {
    "addr:full":"Chauss\u00e9e De Bruxelles 465 Charleroi (jumet) Hainaut 6040",
    "addr:housenumber":"465",
    "addr:postcode":"6040",
    "addr:street":"Chausse\u0301E De Bruxelles",
    "iso:country":"BE",
    "sg:address":"Chauss\u00e9e De Bruxelles 465",
    "sg:city":"Charleroi (jumet)",
    "sg:classifiers":[
        {
            "category":"Health Services",
            "subcategory":"Dentist",
            "type":"Services"
        }
    ],
    "sg:phone":"+32 71 35 68 02",
    "sg:postcode":"6040",
    "sg:province":"Hainaut",
    "wof:name":"Blase Didier",
    "wof:placetype":"venue"
},
  "geometry": {"coordinates":[4.4308209419,50.4570236206],"type":"Point"}
}