{
  "type": "Feature",
  "properties": {
    "addr:full":"Brandstraat 24 Ruiselede West-Vlaanderen 8755",
    "addr:housenumber":"24",
    "addr:postcode":"8755",
    "addr:street":"Brandstraat",
    "iso:country":"BE",
    "sg:address":"Brandstraat 24",
    "sg:city":"Ruiselede",
    "sg:orig_category":"Enseignement maternel and primaire",
    "sg:phone":"+32 51 68 73 37",
    "sg:postcode":"8755",
    "sg:province":"West-Vlaanderen",
    "wof:name":"Vrije Basisschool",
    "wof:placetype":"venue"
},
  "geometry": {"coordinates":[3.3580789566,51.0680923462],"type":"Point"}
}