{
  "type": "Feature",
  "properties": {
    "iso:country":"BE",
    "sg:address":"Longue-voie 48",
    "sg:city":"Ronse/renaix",
    "sg:orig_category":"Traitements param\u00e9dicaux",
    "sg:phone":"+32 55 20 78 81",
    "sg:postcode":"9600",
    "sg:province":"Oost-Vlaanderen",
    "wof:name":"M. Van Asbroeck",
    "wof:placetype":"venue"
},
  "geometry": {"coordinates":[3.5992999077,50.7470397949],"type":"Point"}
}