{
  "type": "Feature",
  "properties": {
    "iso:country":"BE",
    "sg:address":"Luccastraat 15",
    "sg:city":"Sint-niklaas",
    "sg:classifiers":[
        {
            "category":"Personal",
            "subcategory":"Beauty Salon",
            "type":"Services"
        }
    ],
    "sg:phone":"+32 3 766 57 77",
    "sg:postcode":"9100",
    "sg:province":"Oost-Vlaanderen",
    "sg:tags":[
        "lady",
        "-",
        "hairdressing"
    ],
    "wof:name":"Conny",
    "wof:placetype":"venue"
},
  "geometry": {"coordinates":[4.1368141174,51.152545929],"type":"Point"}
}