{
  "type": "Feature",
  "properties": {
    "iso:country":"BE",
    "sg:address":"Avenue Du Gris Moulin 9",
    "sg:city":"La Hulpe",
    "sg:classifiers":[
        {
            "category":"Building & Trades",
            "subcategory":"Construction",
            "type":"Services"
        }
    ],
    "sg:phone":"+32 2 653 67 47",
    "sg:postcode":"1310",
    "sg:province":"Brabant Wallon",
    "sg:tags":[
        "installation",
        "-",
        "central",
        "heating"
    ],
    "wof:name":"Rayee & Fils",
    "wof:placetype":"venue"
},
  "geometry": {"coordinates":[4.4790878296,50.7310905457],"type":"Point"}
}