{
  "type": "Feature",
  "properties": {
    "iso:country":"BE",
    "sg:address":"Marktstraat 1",
    "sg:city":"Merchtem",
    "sg:orig_category":"Enseignement secondaire technique and professionnel. Enseignement secondaire g\u00e9n\u00e9ral",
    "sg:phone":"+32 52 37 39 67",
    "sg:postcode":"1785",
    "sg:province":"Vlaams-Brabant",
    "wof:name":"St.donatusinstituut",
    "wof:placetype":"venue"
},
  "geometry": {"coordinates":[4.2308621407,50.9588928223],"type":"Point"}
}