{
  "type": "Feature",
  "properties": {
    "addr:full":"Boterstraat 6 Pittem West-Vlaanderen 8740",
    "addr:housenumber":"6",
    "addr:postcode":"8740",
    "addr:street":"Boterstraat",
    "iso:country":"BE",
    "sg:address":"Boterstraat 6",
    "sg:city":"Pittem",
    "sg:orig_category":"Pharmaciens. Cliniques and h\u00f4pitaux",
    "sg:phone":"+32 51 46 70 41",
    "sg:postcode":"8740",
    "sg:province":"West-Vlaanderen",
    "wof:name":"Kliniek St.jozef",
    "wof:placetype":"venue"
},
  "geometry": {"coordinates":[3.2484400272,50.9834289551],"type":"Point"}
}