{
  "type": "Feature",
  "properties": {
    "iso:country":"BE",
    "sg:address":"Brusselsesteenweg 596",
    "sg:city":"Asse (zellik)",
    "sg:classifiers":[
        {
            "category":"Home & Garden",
            "subcategory":"Carpets & Floor Coverings",
            "type":"Retail Goods"
        }
    ],
    "sg:phone":"+32 2 466 36 06",
    "sg:postcode":"1731",
    "sg:province":"Vlaams-Brabant",
    "sg:tags":[
        "-"
    ],
    "wof:name":"Woondecoratie Walravens",
    "wof:placetype":"venue"
},
  "geometry": {"coordinates":[4.2740488052,50.884147644],"type":"Point"}
}