{
  "type": "Feature",
  "properties": {
    "iso:country":"BE",
    "sg:address":"Tongersesteenweg 364",
    "sg:city":"Borgloon",
    "sg:classifiers":[
        {
            "category":"Insurance",
            "subcategory":"Life Insurance",
            "type":"Services"
        }
    ],
    "sg:phone":"+32 12 74 57 15",
    "sg:postcode":"3840",
    "sg:province":"Limburg",
    "sg:tags":[
        "assurance"
    ],
    "wof:name":"Bierwaerts-vreys-goffings",
    "wof:placetype":"venue"
},
  "geometry": {"coordinates":[5.3611898422,50.798210144],"type":"Point"}
}