{
  "type": "Feature",
  "properties": {
    "iso:country":"BE",
    "sg:address":"Stationsstraat 232",
    "sg:city":"Ichtegem",
    "sg:orig_category":"Kapsalons",
    "sg:phone":"+32 59 29 95 00",
    "sg:postcode":"8480",
    "sg:province":"West-Vlaanderen",
    "wof:name":"Coiffure Lena",
    "wof:placetype":"venue"
},
  "geometry": {"coordinates":[3.0115549564,51.1266326904],"type":"Point"}
}