{
  "type": "Feature",
  "properties": {
    "addr:full":"Emanuel Hielstraat 8 Dendermonde Oost-Vlaanderen 9200",
    "addr:housenumber":"8",
    "addr:postcode":"9200",
    "addr:street":"Emanuel Hielstraat;Oost-Vlaanderen",
    "iso:country":"BE",
    "sg:address":"Emanuel Hielstraat 8",
    "sg:city":"Dendermonde",
    "sg:orig_category":"Artsen and specialisten",
    "sg:phone":"+32 52 21 29 52",
    "sg:postcode":"9200",
    "sg:province":"Oost-Vlaanderen",
    "wof:name":"A. Muylaert",
    "wof:placetype":"venue"
},
  "geometry": {"coordinates":[4.1058092117,51.0203781128],"type":"Point"}
}