{
  "type": "Feature",
  "properties": {
    "iso:country":"BE",
    "sg:address":"Rue Des Wallons 23",
    "sg:city":"Ottignies-louvain-la-neuve (louvain-la-neuve)",
    "sg:classifiers":[
        {
            "category":"Food & Beverages",
            "subcategory":"Groceries & Convenience Stores",
            "type":"Retail Goods"
        }
    ],
    "sg:phone":"+32 10 45 08 95",
    "sg:postcode":"1348",
    "sg:province":"Brabant Wallon",
    "sg:tags":[
        "grocer"
    ],
    "wof:name":"Nomade (le)",
    "wof:placetype":"venue"
},
  "geometry": {"coordinates":[4.6165652275,50.6690254211],"type":"Point"}
}