{
  "type": "Feature",
  "properties": {
    "iso:country":"BE",
    "sg:address":"Italielei 2",
    "sg:city":"Antwerpen",
    "sg:orig_category":"Telecommunicatiesystemen",
    "sg:phone":"+32 3 206 71 20",
    "sg:postcode":"2000",
    "sg:province":"Antwerpen",
    "wof:name":"Belgacom Telebusiness",
    "wof:placetype":"venue"
},
  "geometry": {"coordinates":[4.4126749039,51.2299003601],"type":"Point"}
}