{
  "type": "Feature",
  "properties": {
    "iso:country":"BE",
    "sg:address":"Leliestraat 1",
    "sg:city":"Brugge (assebroek)",
    "sg:classifiers":[
        {
            "category":"Food & Beverages",
            "subcategory":"Supermarket",
            "type":"Retail Goods"
        }
    ],
    "sg:phone":"+32 50 35 06 97",
    "sg:postcode":"8310",
    "sg:province":"West-Vlaanderen",
    "sg:tags":[
        "department",
        "store"
    ],
    "wof:name":"Supermarkt Ronse",
    "wof:placetype":"venue"
},
  "geometry": {"coordinates":[3.2401280403,51.1981697083],"type":"Point"}
}