{
  "type": "Feature",
  "properties": {
    "iso:country":"BE",
    "sg:address":"Bruinstraat 62",
    "sg:city":"Zonhoven",
    "sg:classifiers":[
        {
            "category":"Wholesale",
            "subcategory":"Plants",
            "type":"Manufacturing & Wholesale Goods"
        }
    ],
    "sg:phone":"+32 11 81 35 54",
    "sg:postcode":"3520",
    "sg:province":"Limburg",
    "sg:tags":[
        "freezing"
    ],
    "wof:name":"Lfb Bogaerts B.v.b.a.",
    "wof:placetype":"venue"
},
  "geometry": {"coordinates":[5.3529219627,51.0042953491],"type":"Point"}
}