{
  "type": "Feature",
  "properties": {
    "addr:full":"Sterstraat 38 Brussel Bruxelles-Capitale 1180",
    "addr:housenumber":"38",
    "addr:postcode":"1180",
    "addr:street":"Sterstraat",
    "iso:country":"BE",
    "sg:address":"Sterstraat 38",
    "sg:city":"Brussel",
    "sg:classifiers":[
        {
            "category":"Wholesale",
            "subcategory":"Plants",
            "type":"Manufacturing & Wholesale Goods"
        }
    ],
    "sg:phone":"+32 2 376 51 27",
    "sg:postcode":"1180",
    "sg:province":"Bruxelles-Capitale",
    "sg:tags":[
        "electro",
        "appliance",
        "heating"
    ],
    "wof:name":"Dirac B.v.b.a.",
    "wof:placetype":"venue"
},
  "geometry": {"coordinates":[4.3215799332,50.7949714661],"type":"Point"}
}