{
  "type": "Feature",
  "properties": {
    "iso:country":"BE",
    "sg:address":"Rue Arthur Galand 26",
    "sg:city":"Wanze",
    "sg:orig_category":"Rundveehouders",
    "sg:phone":"+32 85 21 32 45",
    "sg:postcode":"4520",
    "sg:province":"Li\u00e8ge",
    "wof:name":"Camille Desseille",
    "wof:placetype":"venue"
},
  "geometry": {"coordinates":[5.2091288567,50.5345954895],"type":"Point"}
}