{
  "type": "Feature",
  "properties": {
    "iso:country":"BE",
    "sg:address":"P De Conincklaan 11",
    "sg:city":"Kortrijk",
    "sg:orig_category":"Jardinage",
    "sg:phone":"+32 56 21 95 05",
    "sg:postcode":"8500",
    "sg:province":"West-Vlaanderen",
    "wof:name":"Beernaert H",
    "wof:placetype":"venue"
},
  "geometry": {"coordinates":[3.279968977,50.8298072815],"type":"Point"}
}