{
  "type": "Feature",
  "properties": {
    "addr:full":"Chauss\u00e9e De Haecht 616 Bruxelles (schaerbeek) Bruxelles-Capitale 1030",
    "addr:housenumber":"616",
    "addr:postcode":"1030",
    "addr:street":"Chausse\u0301E De Haecht",
    "iso:country":"BE",
    "sg:address":"Chauss\u00e9e De Haecht 616",
    "sg:city":"Bruxelles (schaerbeek)",
    "sg:classifiers":[
        {
            "category":"Retail",
            "subcategory":"Auto Repair",
            "type":"Services"
        }
    ],
    "sg:phone":"+32 2 243 04 95",
    "sg:postcode":"1030",
    "sg:province":"Bruxelles-Capitale",
    "sg:tags":[
        "automobile-body"
    ],
    "wof:name":"Maus Garage Sa",
    "wof:placetype":"venue"
},
  "geometry": {"coordinates":[4.389673233,50.8700408936],"type":"Point"}
}