{
  "type": "Feature",
  "properties": {
    "addr:full":"Latemstraat 95 Sint-martens-latem Oost-Vlaanderen 9830",
    "addr:housenumber":"95",
    "addr:postcode":"9830",
    "addr:street":"Latemstraat",
    "iso:country":"BE",
    "sg:address":"Latemstraat 95",
    "sg:city":"Sint-martens-latem",
    "sg:orig_category":"RESTAURANTS: CAF\u00c9S",
    "sg:phone":"+32 9 282 52 27",
    "sg:postcode":"9830",
    "sg:province":"Oost-Vlaanderen",
    "wof:name":"Taverne Den Atelier",
    "wof:placetype":"venue"
},
  "geometry": {"coordinates":[3.6340510845,51.017074585],"type":"Point"}
}