{
  "type": "Feature",
  "properties": {
    "addr:full":"Hoogdorpsstraat 62 Alken Limburg 3570",
    "addr:housenumber":"62",
    "addr:postcode":"3570",
    "addr:street":"Hoogdorpsstraat",
    "iso:country":"BE",
    "sg:address":"Hoogdorpsstraat 62",
    "sg:city":"Alken",
    "sg:orig_category":"Brood, gebak and snoepgoed",
    "sg:phone":"+32 11 59 22 89",
    "sg:postcode":"3570",
    "sg:province":"Limburg",
    "wof:name":"Leonidas",
    "wof:placetype":"venue"
},
  "geometry": {"coordinates":[5.3042798042,50.874370575],"type":"Point"}
}