{
  "type": "Feature",
  "properties": {
    "iso:country":"BE",
    "sg:address":"Rue De Virelles 1",
    "sg:city":"Cerfontaine",
    "sg:orig_category":"Woningbouw",
    "sg:phone":"+32 71 64 39 32",
    "sg:postcode":"5630",
    "sg:province":"Namur",
    "wof:name":"M. Colle",
    "wof:placetype":"venue"
},
  "geometry": {"coordinates":[4.4030599594,50.1677284241],"type":"Point"}
}