{
  "type": "Feature",
  "properties": {
    "iso:country":"BE",
    "sg:address":"Avenue Mar\u00c9chal Joffre 64",
    "sg:city":"Vorst/forest",
    "sg:orig_category":"Agences immobili\u00e8res. Pr\u00eats hypoth\u00e9caires and cr\u00e9dits immobiliers. Assurances",
    "sg:phone":"+32 2 347 25 05",
    "sg:postcode":"1190",
    "sg:province":"Bruxelles-Capitale",
    "wof:name":"Bureau Netimmo-drappa",
    "wof:placetype":"venue"
},
  "geometry": {"coordinates":[4.3344779015,50.8143806458],"type":"Point"}
}