{
  "type": "Feature",
  "properties": {
    "addr:full":"Schutterhofstraat 51b1 Puurs Antwerpen 2870",
    "addr:housenumber":"51b1",
    "addr:postcode":"2870",
    "addr:street":"Schutterhofstraat",
    "iso:country":"BE",
    "sg:address":"Schutterhofstraat 51b1",
    "sg:city":"Puurs",
    "sg:orig_category":"Sportclubs",
    "sg:phone":"+32 3 899 38 68",
    "sg:postcode":"2870",
    "sg:province":"Antwerpen",
    "wof:name":"Ruisbroek",
    "wof:placetype":"venue"
},
  "geometry": {"coordinates":[4.2804918289,51.0769119263],"type":"Point"}
}