{
  "type": "Feature",
  "properties": {
    "iso:country":"BE",
    "sg:address":"Lispersteenweg 305",
    "sg:city":"Lier",
    "sg:classifiers":[
        {
            "category":"Restaurant",
            "type":"Food & Drink"
        }
    ],
    "sg:phone":"+32 3 488 53 73",
    "sg:postcode":"2500",
    "sg:province":"Antwerpen",
    "wof:name":"Kristel Van Dyck",
    "wof:placetype":"venue"
},
  "geometry": {"coordinates":[4.5756502151,51.1459388733],"type":"Point"}
}