{
  "type": "Feature",
  "properties": {
    "addr:full":"Bruggestraat 14 Box 1 Tielt West-Vlaanderen 8700",
    "addr:housenumber":"14;1",
    "addr:postcode":"8700",
    "addr:street":"Bruggestraat;Box",
    "iso:country":"BE",
    "sg:address":"Bruggestraat 14 Box 1",
    "sg:city":"Tielt",
    "sg:classifiers":[
        {
            "category":"Health Services",
            "subcategory":"Nursing And Care Facility",
            "type":"Services"
        }
    ],
    "sg:phone":"+32 51 40 18 34",
    "sg:postcode":"8700",
    "sg:province":"West-Vlaanderen",
    "sg:tags":[
        "home"
    ],
    "wof:name":"Sit Vzw",
    "wof:placetype":"venue"
},
  "geometry": {"coordinates":[3.3258230686,51.0006637573],"type":"Point"}
}