{
  "type": "Feature",
  "properties": {
    "addr:full":"Marli\u00c8restraat 80 Moeskroen/mouscron Hainaut 7700",
    "addr:housenumber":"80",
    "addr:postcode":"7700",
    "addr:street":"Marlie\u0300Restraat",
    "iso:country":"BE",
    "sg:address":"Marli\u00c8restraat 80",
    "sg:city":"Moeskroen/mouscron",
    "sg:orig_category":"Banken and kredietinstellingen",
    "sg:phone":"+32 56 33 06 88",
    "sg:postcode":"7700",
    "sg:province":"Hainaut",
    "wof:name":"Fortis",
    "wof:placetype":"venue"
},
  "geometry": {"coordinates":[3.2323200703,50.7400932312],"type":"Point"}
}