{
  "type": "Feature",
  "properties": {
    "iso:country":"BE",
    "sg:address":"Vaartstraat 2",
    "sg:city":"Wielsbeke",
    "sg:classifiers":[
        {
            "category":"Airport",
            "subcategory":"International",
            "type":"Transportation"
        }
    ],
    "sg:phone":"+32 56 66 24 00",
    "sg:postcode":"8710",
    "sg:province":"West-Vlaanderen",
    "sg:tags":[
        "-",
        "transport"
    ],
    "wof:name":"Maertens Transport Nv",
    "wof:placetype":"venue"
},
  "geometry": {"coordinates":[3.3420300484,50.9027519226],"type":"Point"}
}