{
  "type": "Feature",
  "properties": {
    "iso:country":"BE",
    "sg:address":"Koning Albertstraat 23",
    "sg:city":"Hasselt",
    "sg:orig_category":"Kapsalons",
    "sg:phone":"+32 11 22 34 28",
    "sg:postcode":"3500",
    "sg:province":"Limburg",
    "wof:name":"Hairclub D.w.",
    "wof:placetype":"venue"
},
  "geometry": {"coordinates":[5.3366918564,50.928440094],"type":"Point"}
}