{
  "type": "Feature",
  "properties": {
    "iso:country":"BE",
    "sg:address":"Sint-annastraat 19",
    "sg:city":"Zottegem",
    "sg:orig_category":"Avocats and conseillers juridiques",
    "sg:phone":"+32 9 360 90 46",
    "sg:postcode":"9620",
    "sg:province":"Oost-Vlaanderen",
    "wof:name":"D. Van Herzeele",
    "wof:placetype":"venue"
},
  "geometry": {"coordinates":[3.8120570183,50.8668785095],"type":"Point"}
}