{
  "type": "Feature",
  "properties": {
    "addr:full":"Lispersteenweg 77 Boechout Antwerpen 2530",
    "addr:housenumber":"77",
    "addr:postcode":"2530",
    "addr:street":"Lispersteenweg",
    "iso:country":"BE",
    "sg:address":"Lispersteenweg 77",
    "sg:city":"Boechout",
    "sg:orig_category":"Cr\u00e9meries. Pain, p\u00e2tisseries and confiseries",
    "sg:phone":"+32 3 455 19 29",
    "sg:postcode":"2530",
    "sg:province":"Antwerpen",
    "wof:name":"Atelier Domino",
    "wof:placetype":"venue"
},
  "geometry": {"coordinates":[4.5232582092,51.1606750488],"type":"Point"}
}