{
  "type": "Feature",
  "properties": {
    "iso:country":"BE",
    "sg:address":"Schietboomstraat 18",
    "sg:city":"Genk",
    "sg:classifiers":[
        {
            "category":"Professional",
            "subcategory":"Management & Consulting",
            "type":"Services"
        }
    ],
    "sg:phone":"+32 89 30 36 30",
    "sg:postcode":"3600",
    "sg:province":"Limburg",
    "sg:tags":[
        "consultant",
        "law"
    ],
    "wof:name":"Advanced Business Management",
    "wof:placetype":"venue"
},
  "geometry": {"coordinates":[5.5000700951,50.9662895203],"type":"Point"}
}