{
  "type": "Feature",
  "properties": {
    "iso:country":"BE",
    "sg:address":"Daknamstraat 88",
    "sg:city":"Lokeren",
    "sg:orig_category":"Installatie van houten of kunststof schrijnwerk SMEEDWERK, METAALBEWERKING AND POEDERMETALLURGIE",
    "sg:phone":"+32 9 348 33 29",
    "sg:postcode":"9160",
    "sg:province":"Oost-Vlaanderen",
    "wof:name":"Paelinck Kunstsmederij",
    "wof:placetype":"venue"
},
  "geometry": {"coordinates":[3.9849491119,51.115901947],"type":"Point"}
}