{
  "type": "Feature",
  "properties": {
    "addr:full":"Geraardsbergsestraat 71 Brakel (nederbrakel) Oost-Vlaanderen 9660",
    "addr:housenumber":"71",
    "addr:postcode":"9660",
    "addr:street":"Geraardsbergsestraat",
    "iso:country":"BE",
    "sg:address":"Geraardsbergsestraat 71",
    "sg:city":"Brakel (nederbrakel)",
    "sg:classifiers":[
        {
            "category":"Retail",
            "subcategory":"Auto Repair",
            "type":"Services"
        }
    ],
    "sg:phone":"+32 55 42 58 17",
    "sg:postcode":"9660",
    "sg:province":"Oost-Vlaanderen",
    "sg:tags":[
        "garage"
    ],
    "wof:name":"Herman J",
    "wof:placetype":"venue"
},
  "geometry": {"coordinates":[3.7648799419,50.7949295044],"type":"Point"}
}