{
  "type": "Feature",
  "properties": {
    "addr:full":"Roeselaarsestraat 177 Ardooie West-Vlaanderen 8850",
    "addr:housenumber":"177",
    "addr:postcode":"8850",
    "addr:street":"Roeselaarsestraat",
    "iso:country":"BE",
    "sg:address":"Roeselaarsestraat 177",
    "sg:city":"Ardooie",
    "sg:classifiers":[
        {
            "category":"Real Estate",
            "subcategory":"Architect",
            "type":"Services"
        }
    ],
    "sg:phone":"+32 51 20 03 26",
    "sg:postcode":"8850",
    "sg:province":"West-Vlaanderen",
    "wof:name":"Tytgat H",
    "wof:placetype":"venue"
},
  "geometry": {"coordinates":[3.1826601028,50.9670181274],"type":"Point"}
}