{
  "type": "Feature",
  "properties": {
    "addr:full":"Hoogstraat 258 Zemst Vlaams-Brabant 1980",
    "addr:housenumber":"258",
    "addr:postcode":"1980",
    "addr:street":"Hoogstraat;Vlaams-Brabant",
    "iso:country":"BE",
    "sg:address":"Hoogstraat 258",
    "sg:city":"Zemst",
    "sg:orig_category":"Woningbouw",
    "sg:phone":"+32 15 61 72 49",
    "sg:postcode":"1980",
    "sg:province":"Vlaams-Brabant",
    "wof:name":"Georges Rodet",
    "wof:placetype":"venue"
},
  "geometry": {"coordinates":[4.4442849159,51.0022773743],"type":"Point"}
}