{
  "type": "Feature",
  "properties": {
    "addr:full":"Prins Boudewijnlaan 441 Edegem Antwerpen 2650",
    "addr:housenumber":"441",
    "addr:postcode":"2650",
    "addr:street":"Prins Boudewijnlaan",
    "iso:country":"BE",
    "sg:address":"Prins Boudewijnlaan 441",
    "sg:city":"Edegem",
    "sg:classifiers":[
        {
            "category":"Retail",
            "subcategory":"Repair Shop",
            "type":"Services"
        }
    ],
    "sg:phone":"+32 3 449 10 45",
    "sg:postcode":"2650",
    "sg:province":"Antwerpen",
    "sg:tags":[
        "-",
        "clothing",
        "alteration"
    ],
    "wof:name":"Knip",
    "wof:placetype":"venue"
},
  "geometry": {"coordinates":[4.4263620377,51.1693344116],"type":"Point"}
}