{
  "type": "Feature",
  "properties": {
    "iso:country":"BE",
    "sg:address":"Kerkhoek 7",
    "sg:city":"Veurne",
    "sg:orig_category":"Rundveehouders",
    "sg:phone":"+32 58 29 91 40",
    "sg:postcode":"8630",
    "sg:province":"West-Vlaanderen",
    "wof:name":"Luc Patfoort",
    "wof:placetype":"venue"
},
  "geometry": {"coordinates":[2.6049079895,51.0120697021],"type":"Point"}
}