{
  "type": "Feature",
  "properties": {
    "addr:full":"Dorpsstraat 104 Damme (sijsele) West-Vlaanderen 8340",
    "addr:housenumber":"104",
    "addr:postcode":"8340",
    "addr:street":"Dorpsstraat",
    "iso:country":"BE",
    "sg:address":"Dorpsstraat 104",
    "sg:city":"Damme (sijsele)",
    "sg:classifiers":[
        {
            "category":"Shopping",
            "subcategory":"Pets & Pet Supplies",
            "type":"Retail Goods"
        }
    ],
    "sg:phone":"+32 50 35 59 19",
    "sg:postcode":"8340",
    "sg:province":"West-Vlaanderen",
    "sg:tags":[
        "shop",
        "-"
    ],
    "wof:name":"Van Belleghem P",
    "wof:placetype":"venue"
},
  "geometry": {"coordinates":[3.324021101,51.2011833191],"type":"Point"}
}