{
  "type": "Feature",
  "properties": {
    "addr:full":"Boomstraat 42 Gavere Oost-Vlaanderen 9890",
    "addr:housenumber":"42",
    "addr:postcode":"9890",
    "addr:street":"Boomstraat",
    "iso:country":"BE",
    "sg:address":"Boomstraat 42",
    "sg:city":"Gavere",
    "sg:orig_category":"Installatie van houten of kunststof schrijnwerk",
    "sg:phone":"+32 9 384 30 70",
    "sg:postcode":"9890",
    "sg:province":"Oost-Vlaanderen",
    "wof:name":"Freddy Van Damme",
    "wof:placetype":"venue"
},
  "geometry": {"coordinates":[3.7141671181,50.9185638428],"type":"Point"}
}