{
  "type": "Feature",
  "properties": {
    "iso:country":"BE",
    "sg:address":"Papegaaistraat 41",
    "sg:city":"Oostrozebeke",
    "sg:classifiers":[
        {
            "category":"Freight",
            "type":"Transportation"
        }
    ],
    "sg:phone":"+32 56 66 48 47",
    "sg:postcode":"8780",
    "sg:province":"West-Vlaanderen",
    "sg:tags":[
        "-",
        "transport"
    ],
    "wof:name":"Brueli's (transport)",
    "wof:placetype":"venue"
},
  "geometry": {"coordinates":[3.3557479382,50.9304885864],"type":"Point"}
}