{
  "type": "Feature",
  "properties": {
    "addr:full":"Rue De France 33 Chimay (saint-remy) Hainaut 6460",
    "addr:housenumber":"33",
    "addr:postcode":"6460",
    "addr:street":"Rue De France",
    "iso:country":"BE",
    "sg:address":"Rue De France 33",
    "sg:city":"Chimay (saint-remy)",
    "sg:classifiers":[
        {
            "category":"Banks & Credit Unions",
            "subcategory":"Investment Brokerage",
            "type":"Services"
        }
    ],
    "sg:phone":"+32 60 21 17 85",
    "sg:postcode":"6460",
    "sg:province":"Hainaut",
    "sg:tags":[
        "lottery",
        "pool"
    ],
    "wof:name":"Meurant",
    "wof:placetype":"venue"
},
  "geometry": {"coordinates":[4.3157711029,50.0477104187],"type":"Point"}
}