{
  "type": "Feature",
  "properties": {
    "iso:country":"BE",
    "sg:address":"Rue Van Soust 188",
    "sg:city":"Anderlecht",
    "sg:orig_category":"Installatie van houten of kunststof schrijnwerk",
    "sg:phone":"+32 2 522 29 47",
    "sg:postcode":"1070",
    "sg:province":"Bruxelles-Capitale",
    "wof:name":"Mpf Menuiserie",
    "wof:placetype":"venue"
},
  "geometry": {"coordinates":[4.3043541908,50.8464927673],"type":"Point"}
}