{
  "type": "Feature",
  "properties": {
    "addr:full":"Place Edouard Pinoy 8 Box 2 Bruxelles (auderghem) Bruxelles-Capitale 1160",
    "addr:housenumber":"8;2",
    "addr:postcode":"1160",
    "addr:street":"Place Edouard Pinoy;Box",
    "iso:country":"BE",
    "sg:address":"Place Edouard Pinoy 8 Box 2",
    "sg:city":"Bruxelles (auderghem)",
    "sg:classifiers":[
        {
            "category":"Banks & Credit Unions",
            "subcategory":"Investment Brokerage",
            "type":"Services"
        }
    ],
    "sg:phone":"+32 2 675 94 90",
    "sg:postcode":"1160",
    "sg:province":"Bruxelles-Capitale",
    "sg:tags":[
        "supply",
        "processing",
        "-",
        "access",
        "carrier",
        "data"
    ],
    "wof:name":"Tout-ok Pc Services",
    "wof:placetype":"venue"
},
  "geometry": {"coordinates":[4.4228591919,50.8110351562],"type":"Point"}
}