{
  "type": "Feature",
  "properties": {
    "iso:country":"BE",
    "sg:address":"Steenstraat 29",
    "sg:city":"Halle",
    "sg:orig_category":"Boekhouders",
    "sg:phone":"+32 2 356 42 09",
    "sg:postcode":"1500",
    "sg:province":"Vlaams-Brabant",
    "wof:name":"Wim Bosmans",
    "wof:placetype":"venue"
},
  "geometry": {"coordinates":[4.2610459328,50.715045929],"type":"Point"}
}