{
  "type": "Feature",
  "properties": {
    "addr:full":"Kerkplein 1 Herentals Antwerpen 2200",
    "addr:housenumber":"1",
    "addr:postcode":"2200",
    "addr:street":"Kerkplein",
    "iso:country":"BE",
    "sg:address":"Kerkplein 1",
    "sg:city":"Herentals",
    "sg:classifiers":[
        {
            "category":"Cafe",
            "type":"Food & Drink"
        }
    ],
    "sg:phone":"+32 14 22 18 78",
    "sg:postcode":"2200",
    "sg:province":"Antwerpen",
    "sg:tags":[
        "caf\u00e9s"
    ],
    "wof:name":"Caf\u00c9 't Zonneke",
    "wof:placetype":"venue"
},
  "geometry": {"coordinates":[4.8352088928,51.1740608215],"type":"Point"}
}