{
  "type": "Feature",
  "properties": {
    "iso:country":"BE",
    "sg:address":"Chauss\u00c9e De Li\u00c8ge 200",
    "sg:city":"Nandrin",
    "sg:orig_category":"Bloemen and planten",
    "sg:phone":"+32 85 23 16 00",
    "sg:postcode":"4550",
    "sg:province":"Li\u00e8ge",
    "wof:name":"Gardenia",
    "wof:placetype":"venue"
},
  "geometry": {"coordinates":[5.4204249382,50.5065155029],"type":"Point"}
}