{
  "type": "Feature",
  "properties": {
    "iso:country":"BE",
    "sg:address":"Graaf De Fienneslaan 19",
    "sg:city":"Edegem",
    "sg:classifiers":[
        {
            "category":"Insurance",
            "subcategory":"Life Insurance",
            "type":"Services"
        }
    ],
    "sg:phone":"+32 3 440 36 30",
    "sg:postcode":"2650",
    "sg:province":"Antwerpen",
    "sg:tags":[
        "assurance"
    ],
    "wof:name":"Dominator",
    "wof:placetype":"venue"
},
  "geometry": {"coordinates":[4.4325270653,51.1595649719],"type":"Point"}
}