{
  "type": "Feature",
  "properties": {
    "addr:full":"Koning Albertlaan 17 Landen Vlaams-Brabant 3400",
    "addr:housenumber":"17",
    "addr:postcode":"3400",
    "addr:street":"Koning Albertlaan",
    "iso:country":"BE",
    "sg:address":"Koning Albertlaan 17",
    "sg:city":"Landen",
    "sg:orig_category":"Paramedische behandelingen",
    "sg:phone":"+32 11 88 70 02",
    "sg:postcode":"3400",
    "sg:province":"Vlaams-Brabant",
    "wof:name":"C. Vandepoel",
    "wof:placetype":"venue"
},
  "geometry": {"coordinates":[5.0840578079,50.7568740845],"type":"Point"}
}