{
  "type": "Feature",
  "properties": {
    "iso:country":"BE",
    "sg:address":"Kruisven 64",
    "sg:city":"Mol",
    "sg:orig_category":"Advocaten and juridische adviseurs",
    "sg:phone":"+32 14 31 43 55",
    "sg:postcode":"2400",
    "sg:province":"Antwerpen",
    "wof:name":"S. Verherstraeten",
    "wof:placetype":"venue"
},
  "geometry": {"coordinates":[5.0993800163,51.1960601807],"type":"Point"}
}