{
  "type": "Feature",
  "properties": {
    "addr:full":"Rue De La Praye 29 Chatelet Hainaut 6200",
    "addr:housenumber":"29",
    "addr:postcode":"6200",
    "addr:street":"Rue De La Praye;Hainaut",
    "iso:country":"BE",
    "sg:address":"Rue De La Praye 29",
    "sg:city":"Chatelet",
    "sg:orig_category":"Plaatsen van vloer- and muurbekleding Schilders Verlichting and huishoudartikelen",
    "sg:phone":"+32 71 38 06 91",
    "sg:postcode":"6200",
    "sg:province":"Hainaut",
    "wof:name":"Claude Figue",
    "wof:placetype":"venue"
},
  "geometry": {"coordinates":[4.5278949738,50.4041175842],"type":"Point"}
}