{
  "type": "Feature",
  "properties": {
    "addr:full":"Route D'ath 278 Jurbise Hainaut 7050",
    "addr:housenumber":"278",
    "addr:postcode":"7050",
    "addr:street":"Route D'Ath",
    "iso:country":"BE",
    "sg:address":"Route D'ath 278",
    "sg:city":"Jurbise",
    "sg:classifiers":[
        {
            "category":"Health Services",
            "subcategory":"Nursing And Care Facility",
            "type":"Services"
        }
    ],
    "sg:phone":"+32 65 22 64 82",
    "sg:postcode":"7050",
    "sg:province":"Hainaut",
    "sg:tags":[
        "home"
    ],
    "wof:name":"Depauld J",
    "wof:placetype":"venue"
},
  "geometry": {"coordinates":[3.921448946,50.5166130066],"type":"Point"}
}