{
  "type": "Feature",
  "properties": {
    "addr:full":"Lange Raamstraat 5 Brugge West-Vlaanderen 8000",
    "addr:housenumber":"5",
    "addr:postcode":"8000",
    "addr:street":"Lange Raamstraat",
    "iso:country":"BE",
    "sg:address":"Lange Raamstraat 5",
    "sg:city":"Brugge",
    "sg:classifiers":[
        {
            "category":"Real Estate",
            "subcategory":"Real Estate Services",
            "type":"Services"
        }
    ],
    "sg:phone":"+32 50 34 47 58",
    "sg:postcode":"8000",
    "sg:province":"West-Vlaanderen",
    "wof:name":"Vastgoed Advies Verhaeghe",
    "wof:placetype":"venue"
},
  "geometry": {"coordinates":[3.2267770767,51.2144889832],"type":"Point"}
}