{
  "type": "Feature",
  "properties": {
    "iso:country":"BE",
    "sg:address":"Frankrijklaan 10",
    "sg:city":"Poperinge",
    "sg:orig_category":"Woningbouw",
    "sg:phone":"+32 57 33 46 40",
    "sg:postcode":"8970",
    "sg:province":"West-Vlaanderen",
    "wof:name":"F. Plessiet",
    "wof:placetype":"venue"
},
  "geometry": {"coordinates":[2.7426509857,50.8486366272],"type":"Point"}
}