{
  "type": "Feature",
  "properties": {
    "addr:full":"Rostynedreef 46 Aalter Oost-Vlaanderen 9880",
    "addr:housenumber":"46",
    "addr:postcode":"9880",
    "addr:street":"Rostynedreef",
    "iso:country":"BE",
    "sg:address":"Rostynedreef 46",
    "sg:city":"Aalter",
    "sg:orig_category":"Peinture. Rev\u00eatements de sols and murs. Rev\u00eatements pour sols and murs",
    "sg:phone":"+32 9 374 68 42",
    "sg:postcode":"9880",
    "sg:province":"Oost-Vlaanderen",
    "wof:name":"Markant",
    "wof:placetype":"venue"
},
  "geometry": {"coordinates":[3.4746448994,51.0772171021],"type":"Point"}
}