{
  "type": "Feature",
  "properties": {
    "addr:full":"Trommelstraat 2 Gent Oost-Vlaanderen 9000",
    "addr:housenumber":"2",
    "addr:postcode":"9000",
    "addr:street":"Trommelstraat;Oost-Vlaanderen",
    "iso:country":"BE",
    "sg:address":"Trommelstraat 2",
    "sg:city":"Gent",
    "sg:classifiers":[
        {
            "category":"Shopping",
            "subcategory":"Clothing, Apparel, & Fashions",
            "type":"Retail Goods"
        }
    ],
    "sg:phone":"+32 9 224 36 16",
    "sg:postcode":"9000",
    "sg:province":"Oost-Vlaanderen",
    "sg:tags":[
        "designer",
        "stylist"
    ],
    "wof:name":"Ann Huybens",
    "wof:placetype":"venue"
},
  "geometry": {"coordinates":[3.7230780125,51.0586090088],"type":"Point"}
}