{
  "type": "Feature",
  "properties": {
    "iso:country":"BE",
    "sg:address":"Zi",
    "sg:city":"Virton",
    "sg:classifiers":[
        {
            "category":"Manufacturing",
            "subcategory":"Rubber & Plastics",
            "type":"Manufacturing & Wholesale Goods"
        }
    ],
    "sg:phone":"+32 63 58 87 00",
    "sg:postcode":"6761",
    "sg:province":"Luxembourg",
    "sg:tags":[
        "packaging",
        "material",
        "-"
    ],
    "wof:name":"Mima Films Sca",
    "wof:placetype":"venue"
},
  "geometry": {"coordinates":[5.5711097717,49.5599479675],"type":"Point"}
}