{
  "type": "Feature",
  "properties": {
    "iso:country":"BE",
    "sg:address":"Dr. Armand Rubbensstraat 41",
    "sg:city":"Zele",
    "sg:orig_category":"Pain, p\u00e2tisseries and confiseries",
    "sg:phone":"+32 52 44 51 02",
    "sg:postcode":"9240",
    "sg:province":"Oost-Vlaanderen",
    "wof:name":"Jean Heirman",
    "wof:placetype":"venue"
},
  "geometry": {"coordinates":[4.0434370041,51.0683441162],"type":"Point"}
}