{
  "type": "Feature",
  "properties": {
    "addr:full":"Driesstraat 28 Geraardsbergen (idegem) Oost-Vlaanderen 9506",
    "addr:housenumber":"28",
    "addr:postcode":"9506",
    "addr:street":"Driesstraat",
    "iso:country":"BE",
    "sg:address":"Driesstraat 28",
    "sg:city":"Geraardsbergen (idegem)",
    "sg:classifiers":[
        {
            "category":"Home & Garden",
            "subcategory":"Carpets & Floor Coverings",
            "type":"Retail Goods"
        }
    ],
    "sg:phone":"+32 54 50 45 89",
    "sg:postcode":"9506",
    "sg:province":"Oost-Vlaanderen",
    "sg:tags":[
        "layer",
        "mosaicists"
    ],
    "wof:name":"Mertens F",
    "wof:placetype":"venue"
},
  "geometry": {"coordinates":[3.8985300064,50.7987060547],"type":"Point"}
}