{
  "type": "Feature",
  "properties": {
    "addr:full":"Rue Du Centre 78 Frameries Hainaut 7080",
    "addr:housenumber":"78",
    "addr:postcode":"7080",
    "addr:street":"Rue Du Centre",
    "iso:country":"BE",
    "sg:address":"Rue Du Centre 78",
    "sg:city":"Frameries",
    "sg:orig_category":"M\u00e9decins and sp\u00e9cialistes",
    "sg:phone":"+32 65 66 67 15",
    "sg:postcode":"7080",
    "sg:province":"Hainaut",
    "wof:name":"Patrick Degroote",
    "wof:placetype":"venue"
},
  "geometry": {"coordinates":[3.9013249874,50.4052352905],"type":"Point"}
}