{
  "type": "Feature",
  "properties": {
    "iso:country":"BE",
    "sg:address":"Kattenbos 82",
    "sg:city":"Lennik",
    "sg:orig_category":"Advocaten and juridische adviseurs",
    "sg:phone":"+32 2 581 03 35",
    "sg:postcode":"1750",
    "sg:province":"Vlaams-Brabant",
    "wof:name":"Philippe Van Den Broecke",
    "wof:placetype":"venue"
},
  "geometry": {"coordinates":[4.1521148682,50.832611084],"type":"Point"}
}