{
  "type": "Feature",
  "properties": {
    "addr:full":"Rue Arthur Hardy 55 Wavre (limal) Brabant Wallon 1300",
    "addr:housenumber":"55",
    "addr:postcode":"1300",
    "addr:street":"Rue Arthur Hardy;Wallon",
    "iso:country":"BE",
    "sg:address":"Rue Arthur Hardy 55",
    "sg:city":"Wavre (limal)",
    "sg:classifiers":[
        {
            "category":"Real Estate",
            "subcategory":"Architect",
            "type":"Services"
        }
    ],
    "sg:phone":"+32 10 41 57 02",
    "sg:postcode":"1300",
    "sg:province":"Brabant Wallon",
    "wof:name":"Bogaerts M",
    "wof:placetype":"venue"
},
  "geometry": {"coordinates":[4.6116552353,50.7134132385],"type":"Point"}
}