{
  "type": "Feature",
  "properties": {
    "iso:country":"BE",
    "sg:address":"Rue Les Cours 236bis",
    "sg:city":"Theux (la Reid)",
    "sg:classifiers":[
        {
            "category":"Professional",
            "subcategory":"Accounting & Tax Preparation",
            "type":"Services"
        }
    ],
    "sg:phone":"+32 87 37 67 64",
    "sg:postcode":"4910",
    "sg:province":"Li\u00e8ge",
    "sg:tags":[
        "bookkeeper"
    ],
    "wof:name":"Luca Pinazo L",
    "wof:placetype":"venue"
},
  "geometry": {"coordinates":[5.7979841232,50.4771842957],"type":"Point"}
}