{
  "type": "Feature",
  "properties": {
    "addr:full":"Magnoliaserf 2 Moeskroen/mouscron Hainaut 7711",
    "addr:housenumber":"2",
    "addr:postcode":"7711",
    "addr:street":"Magnoliaserf",
    "iso:country":"BE",
    "sg:address":"Magnoliaserf 2",
    "sg:city":"Moeskroen/mouscron",
    "sg:orig_category":"Meubelzaken, woning- and keukeninrichting",
    "sg:phone":"+32 56 48 93 37",
    "sg:postcode":"7711",
    "sg:province":"Hainaut",
    "wof:name":"Meubles Rust. De Style",
    "wof:placetype":"venue"
},
  "geometry": {"coordinates":[3.2801449299,50.7349281311],"type":"Point"}
}