{
  "type": "Feature",
  "properties": {
    "addr:full":"Rue Saint-roch 23 Charleroi Hainaut 6041",
    "addr:housenumber":"23",
    "addr:postcode":"6041",
    "addr:street":"Rue Saint-Roch;Hainaut",
    "iso:country":"BE",
    "sg:address":"Rue Saint-roch 23",
    "sg:city":"Charleroi",
    "sg:orig_category":"Brood, gebak and snoepgoed",
    "sg:phone":"+32 71 35 31 06",
    "sg:postcode":"6041",
    "sg:province":"Hainaut",
    "wof:name":"Germain Verhoeyen",
    "wof:placetype":"venue"
},
  "geometry": {"coordinates":[4.4279518127,50.4679412842],"type":"Point"}
}