{
  "type": "Feature",
  "properties": {
    "iso:country":"BE",
    "sg:address":"Sparrestraat 4",
    "sg:city":"Moorslede",
    "sg:classifiers":[
        {
            "category":"Insurance",
            "subcategory":"Insurance Agent",
            "type":"Services"
        }
    ],
    "sg:phone":"+32 51 77 70 83",
    "sg:postcode":"8890",
    "sg:province":"West-Vlaanderen",
    "sg:tags":[
        "verzekeringsmakelaars",
        "expert"
    ],
    "wof:name":"Vuylsteke",
    "wof:placetype":"venue"
},
  "geometry": {"coordinates":[3.06498909,50.8901901245],"type":"Point"}
}