{
  "type": "Feature",
  "properties": {
    "addr:full":"Kortvoortbaan 42 Schilde Antwerpen 2970",
    "addr:housenumber":"42",
    "addr:postcode":"2970",
    "addr:street":"Kortvoortbaan",
    "iso:country":"BE",
    "sg:address":"Kortvoortbaan 42",
    "sg:city":"Schilde",
    "sg:orig_category":"Woningbouw",
    "sg:phone":"+32 3 384 34 60",
    "sg:postcode":"2970",
    "sg:province":"Antwerpen",
    "wof:name":"Remifra",
    "wof:placetype":"venue"
},
  "geometry": {"coordinates":[4.556953907,51.2434234619],"type":"Point"}
}