{
  "type": "Feature",
  "properties": {
    "addr:full":"Rue Ferrer 19 Courcelles Hainaut 6181",
    "addr:housenumber":"19",
    "addr:postcode":"6181",
    "addr:street":"Rue Ferrer",
    "iso:country":"BE",
    "sg:address":"Rue Ferrer 19",
    "sg:city":"Courcelles",
    "sg:orig_category":"Ruimtes voor conferenties, recepties and feesten Rusthuizen and serviceflats",
    "sg:phone":"+32 71 84 62 82",
    "sg:postcode":"6181",
    "sg:province":"Hainaut",
    "wof:name":"Salle Du Cercle",
    "wof:placetype":"venue"
},
  "geometry": {"coordinates":[4.3289852142,50.4869117737],"type":"Point"}
}