{
  "type": "Feature",
  "properties": {
    "iso:country":"BE",
    "sg:address":"Hendrik Speecqvest 2b102",
    "sg:city":"Mechelen",
    "sg:classifiers":[
        {
            "category":"Insurance",
            "subcategory":"Life Insurance",
            "type":"Services"
        }
    ],
    "sg:phone":"+32 15 41 19 42",
    "sg:postcode":"2800",
    "sg:province":"Antwerpen",
    "sg:tags":[
        "assurance"
    ],
    "wof:name":"Verzek. Swinnen Egide",
    "wof:placetype":"venue"
},
  "geometry": {"coordinates":[4.4837069511,51.0204544067],"type":"Point"}
}