{
  "type": "Feature",
  "properties": {
    "iso:country":"BE",
    "sg:address":"Rue Bouille 2",
    "sg:city":"Li\u00c8ge",
    "sg:orig_category":"D\u00e9m\u00e9nagements. Transports routiers de marchandises",
    "sg:phone":"+32 4 342 42 42",
    "sg:postcode":"4020",
    "sg:province":"Li\u00e8ge",
    "wof:name":"Transp.rout.& D\u00c9m\u00c9n.samo",
    "wof:placetype":"venue"
},
  "geometry": {"coordinates":[5.5858888626,50.6353263855],"type":"Point"}
}