{
  "type": "Feature",
  "properties": {
    "addr:full":"Oudekerkstraat 28 Kinrooi Limburg 3640",
    "addr:housenumber":"28",
    "addr:postcode":"3640",
    "addr:street":"Oudekerkstraat",
    "iso:country":"BE",
    "sg:address":"Oudekerkstraat 28",
    "sg:city":"Kinrooi",
    "sg:orig_category":"Plomberie, chauffage and installations sanitaires",
    "sg:phone":"+32 89 70 15 28",
    "sg:postcode":"3640",
    "sg:province":"Limburg",
    "wof:name":"Vandendijk Luc",
    "wof:placetype":"venue"
},
  "geometry": {"coordinates":[5.7331857681,51.1685295105],"type":"Point"}
}