{
  "type": "Feature",
  "properties": {
    "addr:full":"Jan Van Der Vorstlaan 36 Huldenberg Vlaams-Brabant 3040",
    "addr:housenumber":"36",
    "addr:postcode":"3040",
    "addr:street":"Jan Van Der Vorstlaan",
    "iso:country":"BE",
    "sg:address":"Jan Van Der Vorstlaan 36",
    "sg:city":"Huldenberg",
    "sg:orig_category":"Boekhouders",
    "sg:phone":"+32 16 47 19 52",
    "sg:postcode":"3040",
    "sg:province":"Vlaams-Brabant",
    "wof:name":"Karin Devijver",
    "wof:placetype":"venue"
},
  "geometry": {"coordinates":[4.6051111221,50.8063735962],"type":"Point"}
}