{
  "type": "Feature",
  "properties": {
    "addr:full":"Rue De La Lib\u00e9ration 50 Braine-le-ch\u00e2teau Brabant Wallon 1440",
    "addr:housenumber":"50",
    "addr:postcode":"1440",
    "addr:street":"Rue De La Libe\u0301Ration",
    "iso:country":"BE",
    "sg:address":"Rue De La Lib\u00e9ration 50",
    "sg:city":"Braine-le-ch\u00e2teau",
    "sg:orig_category":"Non-Classified Establishments",
    "sg:phone":"+32 2 366 07 17",
    "sg:postcode":"1440",
    "sg:province":"Brabant Wallon",
    "wof:name":"Merckx J",
    "wof:placetype":"venue"
},
  "geometry": {"coordinates":[4.2715349197,50.6825294495],"type":"Point"}
}