{
  "type": "Feature",
  "properties": {
    "iso:country":"BE",
    "sg:address":"Rue De La Croix-rouge 18",
    "sg:city":"Tubize",
    "sg:orig_category":"M\u00e9decins and sp\u00e9cialistes",
    "sg:phone":"+32 2 390 96 84",
    "sg:postcode":"1480",
    "sg:province":"Brabant Wallon",
    "wof:name":"Isabelle Limbourg",
    "wof:placetype":"venue"
},
  "geometry": {"coordinates":[4.1983370781,50.6855697632],"type":"Point"}
}