{
  "type": "Feature",
  "properties": {
    "addr:full":"Maalse Steenweg 334 Brugge (sint-kruis) West-Vlaanderen 8310",
    "addr:housenumber":"334",
    "addr:postcode":"8310",
    "addr:street":"Maalse Steenweg",
    "iso:country":"BE",
    "sg:address":"Maalse Steenweg 334",
    "sg:city":"Brugge (sint-kruis)",
    "sg:classifiers":[
        {
            "category":"Banks & Credit Unions",
            "subcategory":"Investment Brokerage",
            "type":"Services"
        }
    ],
    "sg:phone":"+32 50 37 43 89",
    "sg:postcode":"8310",
    "sg:province":"West-Vlaanderen",
    "sg:tags":[
        "lottery",
        "pool"
    ],
    "wof:name":"Lotto Center",
    "wof:placetype":"venue"
},
  "geometry": {"coordinates":[3.2648339272,51.2082290649],"type":"Point"}
}