{
  "type": "Feature",
  "properties": {
    "iso:country":"BE",
    "sg:address":"Hoogstepuntlaan 11",
    "sg:city":"Lubbeek (pellenberg)",
    "sg:classifiers":[
        {
            "category":"Professional",
            "subcategory":"Accounting & Tax Preparation",
            "type":"Services"
        }
    ],
    "sg:phone":"+32 16 46 29 34",
    "sg:postcode":"3212",
    "sg:province":"Vlaams-Brabant",
    "sg:tags":[
        "bookkeeper"
    ],
    "wof:name":"Fiduciaire De Westhoek Bvba",
    "wof:placetype":"venue"
},
  "geometry": {"coordinates":[4.8018012047,50.870136261],"type":"Point"}
}