{
  "type": "Feature",
  "properties": {
    "iso:country":"BE",
    "sg:address":"Bergmolenstraat 4",
    "sg:city":"Tielt",
    "sg:orig_category":"Eleveurs de bovins. Eleveurs and marchands de porcs",
    "sg:phone":"+32 51 65 68 25",
    "sg:postcode":"8700",
    "sg:province":"West-Vlaanderen",
    "wof:name":"Eric Van Slambrouck",
    "wof:placetype":"venue"
},
  "geometry": {"coordinates":[3.3013420105,51.0251083374],"type":"Point"}
}