{
  "type": "Feature",
  "properties": {
    "addr:full":"Iepersestraat 588 Roeselare West-Vlaanderen 8800",
    "addr:housenumber":"588",
    "addr:postcode":"8800",
    "addr:street":"Iepersestraat",
    "iso:country":"BE",
    "sg:address":"Iepersestraat 588",
    "sg:city":"Roeselare",
    "sg:orig_category":"Enseignement maternel and primaire",
    "sg:phone":"+32 51 22 96 40",
    "sg:postcode":"8800",
    "sg:province":"West-Vlaanderen",
    "wof:name":"Vrije Kleuterschool",
    "wof:placetype":"venue"
},
  "geometry": {"coordinates":[3.0943078995,50.9309539795],"type":"Point"}
}