{
  "type": "Feature",
  "properties": {
    "addr:full":"Hollebeekstraat 67 Rumst Antwerpen 2840",
    "addr:housenumber":"67",
    "addr:postcode":"2840",
    "addr:street":"Hollebeekstraat",
    "iso:country":"BE",
    "sg:address":"Hollebeekstraat 67",
    "sg:city":"Rumst",
    "sg:classifiers":[
        {
            "category":"Farming",
            "subcategory":"Fish & Marine Products",
            "type":"Manufacturing & Wholesale Goods"
        }
    ],
    "sg:phone":"+32 3 888 77 01",
    "sg:postcode":"2840",
    "sg:province":"Antwerpen",
    "sg:tags":[
        "surveyor",
        "-"
    ],
    "wof:name":"Viaene Marine Survey",
    "wof:placetype":"venue"
},
  "geometry": {"coordinates":[4.4214701653,51.0834960938],"type":"Point"}
}