{
  "type": "Feature",
  "properties": {
    "addr:full":"Avenue Minerve 56 Chastre Brabant Wallon 1450",
    "addr:housenumber":"56",
    "addr:postcode":"1450",
    "addr:street":"Avenue Minerve",
    "iso:country":"BE",
    "sg:address":"Avenue Minerve 56",
    "sg:city":"Chastre",
    "sg:orig_category":"Schoonheidssalons",
    "sg:phone":"+32 10 65 73 50",
    "sg:postcode":"1450",
    "sg:province":"Brabant Wallon",
    "wof:name":"Marie-louise Jassogne",
    "wof:placetype":"venue"
},
  "geometry": {"coordinates":[4.6439099312,50.6044464111],"type":"Point"}
}