{
  "type": "Feature",
  "properties": {
    "iso:country":"BE",
    "sg:address":"Ouddorp 56",
    "sg:city":"Haaltert",
    "sg:orig_category":"Boissons",
    "sg:phone":"+32 53 62 23 55",
    "sg:postcode":"9450",
    "sg:province":"Oost-Vlaanderen",
    "wof:name":"Vermassen",
    "wof:placetype":"venue"
},
  "geometry": {"coordinates":[3.9474730492,50.8876953125],"type":"Point"}
}