{
  "type": "Feature",
  "properties": {
    "iso:country":"BE",
    "sg:address":"Heggelaan 71",
    "sg:city":"Lille",
    "sg:orig_category":"Woningbouw",
    "sg:phone":"+32 14 88 25 67",
    "sg:postcode":"2275",
    "sg:province":"Antwerpen",
    "wof:name":"Bouwonderneming Stickens",
    "wof:placetype":"venue"
},
  "geometry": {"coordinates":[4.8309721947,51.2211799622],"type":"Point"}
}