{
  "type": "Feature",
  "properties": {
    "iso:country":"BE",
    "sg:address":"Middelveld 26bb",
    "sg:city":"Lille",
    "sg:orig_category":"Varkenskwekers",
    "sg:phone":"+32 14 55 27 79",
    "sg:postcode":"2275",
    "sg:province":"Antwerpen",
    "wof:name":"Peter Vervoort",
    "wof:placetype":"venue"
},
  "geometry": {"coordinates":[4.8794322014,51.2675743103],"type":"Point"}
}