{
  "type": "Feature",
  "properties": {
    "iso:country":"BE",
    "sg:address":"Vestingstraat 79",
    "sg:city":"Brugge (assebroek)",
    "sg:classifiers":[
        {
            "category":"Professional",
            "subcategory":"Accounting & Tax Preparation",
            "type":"Services"
        }
    ],
    "sg:phone":"+32 50 35 39 64",
    "sg:postcode":"8310",
    "sg:province":"West-Vlaanderen",
    "sg:tags":[
        "accountant"
    ],
    "wof:name":"Houdmont J",
    "wof:placetype":"venue"
},
  "geometry": {"coordinates":[3.2313020229,51.1983947754],"type":"Point"}
}