{
  "type": "Feature",
  "properties": {
    "addr:full":"Rue De Vis\u00e9 154 Li\u00e8ge 1 (jupille-sur-meuse) Li\u00e8ge 4020",
    "addr:housenumber":"154;1",
    "addr:postcode":"4020",
    "addr:street":"Rue De Vise\u0301;Jupille-Sur-Meuse Lie\u0300Ge",
    "iso:country":"BE",
    "sg:address":"Rue De Vis\u00e9 154",
    "sg:city":"Li\u00e8ge 1 (jupille-sur-meuse)",
    "sg:classifiers":[
        {
            "category":"Utilities",
            "subcategory":"Natural Gas",
            "type":"Services"
        }
    ],
    "sg:phone":"+32 4 370 10 12",
    "sg:postcode":"4020",
    "sg:province":"Li\u00e8ge",
    "sg:tags":[
        "firework"
    ],
    "wof:name":"Jla Johnny Lonneux Artifice",
    "wof:placetype":"venue"
},
  "geometry": {"coordinates":[5.6320261955,50.647480011],"type":"Point"}
}