{
  "type": "Feature",
  "properties": {
    "iso:country":"BE",
    "sg:address":"Leo De B\u00e9thunelaan 127 Box 5",
    "sg:city":"Aalst",
    "sg:classifiers":[
        {
            "category":"Professional",
            "subcategory":"Accounting & Tax Preparation",
            "type":"Services"
        }
    ],
    "sg:phone":"+32 53 77 94 16",
    "sg:postcode":"9300",
    "sg:province":"Oost-Vlaanderen",
    "sg:tags":[
        "accountant"
    ],
    "wof:name":"Arijs A",
    "wof:placetype":"venue"
},
  "geometry": {"coordinates":[4.031085968,50.932346344],"type":"Point"}
}