{
  "type": "Feature",
  "properties": {
    "iso:country":"BE",
    "sg:address":"Rue De La Planchette 24",
    "sg:city":"Ittre",
    "sg:orig_category":"Artsen and specialisten",
    "sg:phone":"+32 67 64 63 02",
    "sg:postcode":"1460",
    "sg:province":"Brabant Wallon",
    "wof:name":"Emmanuel Farber",
    "wof:placetype":"venue"
},
  "geometry": {"coordinates":[4.2621021271,50.6477928162],"type":"Point"}
}