{
  "type": "Feature",
  "properties": {
    "addr:full":"Gemehret 30 Eupen (kettenis) Li\u00e8ge 4701",
    "addr:housenumber":"30",
    "addr:postcode":"4701",
    "addr:street":"Gemehret",
    "iso:country":"BE",
    "sg:address":"Gemehret 30",
    "sg:city":"Eupen (kettenis)",
    "sg:classifiers":[
        {
            "category":"Home & Garden",
            "subcategory":"Home Furnishings",
            "type":"Retail Goods"
        }
    ],
    "sg:phone":"+32 87 76 67 26",
    "sg:postcode":"4701",
    "sg:province":"Li\u00e8ge",
    "sg:tags":[
        "decoration"
    ],
    "wof:name":"Signum Ets",
    "wof:placetype":"venue"
},
  "geometry": {"coordinates":[6.0176820755,50.6458625793],"type":"Point"}
}