{
  "type": "Feature",
  "properties": {
    "iso:country":"BE",
    "sg:address":"Kaaiplaats 9",
    "sg:city":"Veurne",
    "sg:classifiers":[
        {
            "category":"Retail",
            "subcategory":"Repair Shop",
            "type":"Services"
        }
    ],
    "sg:phone":"+32 58 31 16 08",
    "sg:postcode":"8630",
    "sg:province":"West-Vlaanderen",
    "sg:tags":[
        "denture"
    ],
    "wof:name":"Platevoet W",
    "wof:placetype":"venue"
},
  "geometry": {"coordinates":[2.6665849686,51.0707893372],"type":"Point"}
}