{
  "type": "Feature",
  "properties": {
    "addr:full":"Markegemstraat 9 Dentergem West-Vlaanderen 8720",
    "addr:housenumber":"9",
    "addr:postcode":"8720",
    "addr:street":"Markegemstraat",
    "iso:country":"BE",
    "sg:address":"Markegemstraat 9",
    "sg:city":"Dentergem",
    "sg:orig_category":"Studios photographiques",
    "sg:phone":"+32 56 60 24 21",
    "sg:postcode":"8720",
    "sg:province":"West-Vlaanderen",
    "wof:name":"Fotografie Pieters",
    "wof:placetype":"venue"
},
  "geometry": {"coordinates":[3.3977429867,50.9319953918],"type":"Point"}
}