{
  "type": "Feature",
  "properties": {
    "iso:country":"BE",
    "sg:address":"Mageleinstraat 11",
    "sg:city":"Gent",
    "sg:classifiers":[
        {
            "category":"Juice Bar",
            "subcategory":"None",
            "type":"Food & Drink"
        }
    ],
    "sg:phone":"+32 9 223 85 19",
    "sg:postcode":"9000",
    "sg:province":"Oost-Vlaanderen",
    "sg:tags":[
        "ivory"
    ],
    "wof:name":"De Gouden Mandarijn",
    "wof:placetype":"venue"
},
  "geometry": {"coordinates":[3.7247369289,51.0532531738],"type":"Point"}
}