{
  "type": "Feature",
  "properties": {
    "addr:full":"Rollegembosstraat 13ba Ledegem West-Vlaanderen 8880",
    "addr:housenumber":"13ba",
    "addr:postcode":"8880",
    "addr:street":"Rollegembosstraat",
    "iso:country":"BE",
    "sg:address":"Rollegembosstraat 13ba",
    "sg:city":"Ledegem",
    "sg:orig_category":"Plaatsen van vloer- and muurbekleding",
    "sg:phone":"+32 56 50 67 97",
    "sg:postcode":"8880",
    "sg:province":"West-Vlaanderen",
    "wof:name":"Francky Lycke",
    "wof:placetype":"venue"
},
  "geometry": {"coordinates":[3.1341900826,50.8698577881],"type":"Point"}
}