{
  "type": "Feature",
  "properties": {
    "addr:full":"Place Charles Ii 24 Charleroi Hainaut 6000",
    "addr:housenumber":"24",
    "addr:postcode":"6000",
    "addr:street":"Place Charles Ii;Hainaut",
    "iso:country":"BE",
    "sg:address":"Place Charles Ii 24",
    "sg:city":"Charleroi",
    "sg:classifiers":[
        {
            "category":"Organizations",
            "subcategory":"Professional Association",
            "type":"Services"
        }
    ],
    "sg:phone":"+32 71 32 11 98",
    "sg:postcode":"6000",
    "sg:province":"Hainaut",
    "sg:tags":[
        "trade-union",
        "federation"
    ],
    "wof:name":"Parti Socialiste Federation De Charleroi",
    "wof:placetype":"venue"
},
  "geometry": {"coordinates":[4.4445261955,50.4111251831],"type":"Point"}
}