{
  "type": "Feature",
  "properties": {
    "addr:full":"Avenue Provinciale 49 Ottignies-louvain-la-neuve Brabant Wallon 1341",
    "addr:housenumber":"49",
    "addr:postcode":"1341",
    "addr:street":"Avenue Provinciale",
    "iso:country":"BE",
    "sg:address":"Avenue Provinciale 49",
    "sg:city":"Ottignies-louvain-la-neuve",
    "sg:classifiers":[
        {
            "category":"Cafe",
            "type":"Food & Drink"
        }
    ],
    "sg:phone":"+32 10 61 55 83",
    "sg:postcode":"1341",
    "sg:province":"Brabant Wallon",
    "sg:tags":[
        "caf\u00e9s"
    ],
    "wof:name":"Philippe Janssens",
    "wof:placetype":"venue"
},
  "geometry": {"coordinates":[4.5627598763,50.6583099365],"type":"Point"}
}