{
  "type": "Feature",
  "properties": {
    "iso:country":"BE",
    "sg:address":"Kortrijkstraat 66",
    "sg:city":"Wortegem-petegem (petegem-aan-de-schelde)",
    "sg:classifiers":[
        {
            "category":"Building & Trades",
            "subcategory":"Landscaping Services",
            "type":"Services"
        }
    ],
    "sg:phone":"+32 55 39 03 90",
    "sg:postcode":"9790",
    "sg:province":"Oost-Vlaanderen",
    "sg:tags":[
        "equipment",
        "swimming",
        "-",
        "pool",
        "contractor"
    ],
    "wof:name":"Willy Naessens Nv",
    "wof:placetype":"venue"
},
  "geometry": {"coordinates":[3.5402600765,50.8192100525],"type":"Point"}
}