{
  "type": "Feature",
  "properties": {
    "iso:country":"BE",
    "sg:address":"Veemarkt 4-6",
    "sg:city":"Mechelen",
    "sg:classifiers":[
        {
            "category":"Shopping",
            "subcategory":"Optician",
            "type":"Retail Goods"
        }
    ],
    "sg:phone":"+32 15 20 32 17",
    "sg:postcode":"2800",
    "sg:province":"Antwerpen",
    "sg:tags":[
        "-"
    ],
    "wof:name":"Cede Opticiens (stappers-depoorter)",
    "wof:placetype":"venue"
},
  "geometry": {"coordinates":[4.4834852219,51.0288276672],"type":"Point"}
}