{
  "type": "Feature",
  "properties": {
    "addr:full":"Gounodstraat 2ba11 Antwerpen Antwerpen 2018",
    "addr:housenumber":"2ba11",
    "addr:postcode":"2018",
    "addr:street":"Gounodstraat",
    "iso:country":"BE",
    "sg:address":"Gounodstraat 2ba11",
    "sg:city":"Antwerpen",
    "sg:orig_category":"Persagentschappen",
    "sg:phone":"+32 3 237 23 17",
    "sg:postcode":"2018",
    "sg:province":"Antwerpen",
    "wof:name":"Robert Lefevre",
    "wof:placetype":"venue"
},
  "geometry": {"coordinates":[4.4095540047,51.2060127258],"type":"Point"}
}