{
  "type": "Feature",
  "properties": {
    "iso:country":"BE",
    "sg:address":"Rue Fernand Marchand 1",
    "sg:city":"Flawinne",
    "sg:classifiers":[
        {
            "category":"Manufacturing",
            "subcategory":"Chemicals & Compounds",
            "type":"Manufacturing & Wholesale Goods"
        }
    ],
    "sg:phone":"+32 81 73 71 42",
    "sg:postcode":"5020",
    "sg:province":"Namur",
    "sg:tags":[
        "pharmaceutical",
        "energy",
        "chemistry",
        "-",
        "by-product"
    ],
    "wof:name":"Joassin Ren\u00c9 Sa",
    "wof:placetype":"venue"
},
  "geometry": {"coordinates":[4.7923059464,50.4505882263],"type":"Point"}
}