{
  "type": "Feature",
  "properties": {
    "addr:full":"Avenue Valentin Tondeur 34a Waterloo Brabant Wallon 1410",
    "addr:housenumber":"34a",
    "addr:postcode":"1410",
    "addr:street":"Avenue Valentin Tondeur",
    "iso:country":"BE",
    "sg:address":"Avenue Valentin Tondeur 34a",
    "sg:city":"Waterloo",
    "sg:classifiers":[
        {
            "category":"Professional",
            "subcategory":"Computer Services",
            "type":"Services"
        }
    ],
    "sg:phone":"+32 2 387 28 68",
    "sg:postcode":"1410",
    "sg:province":"Brabant Wallon",
    "sg:tags":[
        "-",
        "processing",
        "data",
        "software"
    ],
    "wof:name":"Assistance & Applications",
    "wof:placetype":"venue"
},
  "geometry": {"coordinates":[4.4057641029,50.6961212158],"type":"Point"}
}