{
  "type": "Feature",
  "properties": {
    "iso:country":"BE",
    "sg:address":"Rostijnenstraat 51",
    "sg:city":"Lochristi",
    "sg:orig_category":"Rundveehouders Varkenskwekers",
    "sg:phone":"+32 9 355 98 52",
    "sg:postcode":"9080",
    "sg:province":"Oost-Vlaanderen",
    "wof:name":"Maurice Bultinck",
    "wof:placetype":"venue"
},
  "geometry": {"coordinates":[3.7941670418,51.1085662842],"type":"Point"}
}