{
  "type": "Feature",
  "properties": {
    "iso:country":"BE",
    "sg:address":"Rue Le Chat 62",
    "sg:city":"Ath",
    "sg:orig_category":"Rundveehouders",
    "sg:phone":"+32 68 64 53 83",
    "sg:postcode":"7812",
    "sg:province":"Hainaut",
    "wof:name":"Jean Bernard",
    "wof:placetype":"venue"
},
  "geometry": {"coordinates":[3.7009339333,50.6268501282],"type":"Point"}
}