{
  "type": "Feature",
  "properties": {
    "addr:full":"Rue De Cond\u00c9 157 Leuze-en-hainaut Hainaut 7900",
    "addr:housenumber":"157",
    "addr:postcode":"7900",
    "addr:street":"Rue De Conde\u0301",
    "iso:country":"BE",
    "sg:address":"Rue De Cond\u00c9 157",
    "sg:city":"Leuze-en-hainaut",
    "sg:orig_category":"Afvalwaterverwerking and ontstoppingsdiensten Huisvuilophaling and -verwerking",
    "sg:phone":"+32 69 66 23 83",
    "sg:postcode":"7900",
    "sg:province":"Hainaut",
    "wof:name":"Marie-christine Boutiau",
    "wof:placetype":"venue"
},
  "geometry": {"coordinates":[3.6175670624,50.5919532776],"type":"Point"}
}