{
  "type": "Feature",
  "properties": {
    "addr:full":"Turnhoutsebaan 334 Wijnegem Antwerpen 2110",
    "addr:housenumber":"334",
    "addr:postcode":"2110",
    "addr:street":"Turnhoutsebaan",
    "iso:country":"BE",
    "sg:address":"Turnhoutsebaan 334",
    "sg:city":"Wijnegem",
    "sg:orig_category":"Kapsalons",
    "sg:phone":"+32 3 353 18 24",
    "sg:postcode":"2110",
    "sg:province":"Antwerpen",
    "wof:name":"Coiffure Lollypop",
    "wof:placetype":"venue"
},
  "geometry": {"coordinates":[4.5181660652,51.2270088196],"type":"Point"}
}