{
  "type": "Feature",
  "properties": {
    "iso:country":"BE",
    "sg:address":"Hasseltweg 176",
    "sg:city":"Genk",
    "sg:classifiers":[
        {
            "category":"Structure",
            "subcategory":"Building",
            "type":"Public Place"
        }
    ],
    "sg:phone":"+32 89 35 16 60",
    "sg:postcode":"3600",
    "sg:province":"Limburg",
    "sg:tags":[
        "door"
    ],
    "wof:name":"America Ramen & Deuren",
    "wof:placetype":"venue"
},
  "geometry": {"coordinates":[5.4571208954,50.961227417],"type":"Point"}
}