{
  "type": "Feature",
  "properties": {
    "addr:full":"Hoppestraat 12 Wevelgem West-Vlaanderen 8560",
    "addr:housenumber":"12",
    "addr:postcode":"8560",
    "addr:street":"Hoppestraat",
    "iso:country":"BE",
    "sg:address":"Hoppestraat 12",
    "sg:city":"Wevelgem",
    "sg:orig_category":"Installation de menuiserie en bois and plastique",
    "sg:phone":"+32 56 41 09 37",
    "sg:postcode":"8560",
    "sg:province":"West-Vlaanderen",
    "wof:name":"Dv Construct",
    "wof:placetype":"venue"
},
  "geometry": {"coordinates":[3.166189909,50.8093910217],"type":"Point"}
}