{
  "type": "Feature",
  "properties": {
    "addr:full":"Herpendaalstraat 47 Oud-heverlee (haasrode) Vlaams-Brabant 3053",
    "addr:housenumber":"47",
    "addr:postcode":"3053",
    "addr:street":"Herpendaalstraat",
    "iso:country":"BE",
    "sg:address":"Herpendaalstraat 47",
    "sg:city":"Oud-heverlee (haasrode)",
    "sg:classifiers":[
        {
            "category":"Professional",
            "subcategory":"Management & Consulting",
            "type":"Services"
        }
    ],
    "sg:phone":"+32 16 40 38 89",
    "sg:postcode":"3053",
    "sg:province":"Vlaams-Brabant",
    "sg:tags":[
        "consultant"
    ],
    "wof:name":"Vandebrouck Pharma Consult Vof",
    "wof:placetype":"venue"
},
  "geometry": {"coordinates":[4.7316727638,50.8388023376],"type":"Point"}
}