{
  "type": "Feature",
  "properties": {
    "addr:full":"Hoevensebaan 36 Kapellen Antwerpen 2950",
    "addr:housenumber":"36",
    "addr:postcode":"2950",
    "addr:street":"Hoevensebaan",
    "iso:country":"BE",
    "sg:address":"Hoevensebaan 36",
    "sg:city":"Kapellen",
    "sg:orig_category":"Centres de relaxation and bien-\u00eatre",
    "sg:phone":"+32 3 605 31 81",
    "sg:postcode":"2950",
    "sg:province":"Antwerpen",
    "wof:name":"Zonnecenter Sunstar",
    "wof:placetype":"venue"
},
  "geometry": {"coordinates":[4.4270601273,51.3142433167],"type":"Point"}
}