{
  "type": "Feature",
  "properties": {
    "addr:full":"Esplanadestraat 7 Menen West-Vlaanderen 8930",
    "addr:housenumber":"7",
    "addr:postcode":"8930",
    "addr:street":"Esplanadestraat",
    "iso:country":"BE",
    "sg:address":"Esplanadestraat 7",
    "sg:city":"Menen",
    "sg:classifiers":[
        {
            "category":"Building & Trades",
            "subcategory":"Equipment Rental",
            "type":"Services"
        }
    ],
    "sg:phone":"+32 56 51 31 47",
    "sg:postcode":"8930",
    "sg:province":"West-Vlaanderen",
    "sg:tags":[
        "tableware",
        "-"
    ],
    "wof:name":"Versailles Bvba",
    "wof:placetype":"venue"
},
  "geometry": {"coordinates":[3.1213629246,50.7970924377],"type":"Point"}
}