{
  "type": "Feature",
  "properties": {
    "addr:full":"Ambachtenlaan 7 Wevelgem (gullegem) West-Vlaanderen 8560",
    "addr:housenumber":"7",
    "addr:postcode":"8560",
    "addr:street":"Ambachtenlaan",
    "iso:country":"BE",
    "sg:address":"Ambachtenlaan 7",
    "sg:city":"Wevelgem (gullegem)",
    "sg:classifiers":[
        {
            "category":"Home & Garden",
            "subcategory":"Building Materials",
            "type":"Retail Goods"
        }
    ],
    "sg:phone":"+32 56 41 91 70",
    "sg:postcode":"8560",
    "sg:province":"West-Vlaanderen",
    "sg:tags":[
        "window"
    ],
    "wof:name":"Matirol Bvba",
    "wof:placetype":"venue"
},
  "geometry": {"coordinates":[3.1810460091,50.85131073],"type":"Point"}
}