{
  "type": "Feature",
  "properties": {
    "iso:country":"BE",
    "sg:address":"Jeugdlaan 3",
    "sg:city":"Sint-amands",
    "sg:classifiers":[
        {
            "category":"Arena",
            "subcategory":"Sports Club",
            "type":"Entertainment"
        }
    ],
    "sg:phone":"+32 52 34 07 31",
    "sg:postcode":"2890",
    "sg:province":"Antwerpen",
    "sg:tags":[
        "de"
    ],
    "wof:name":"Sakk St.amands",
    "wof:placetype":"venue"
},
  "geometry": {"coordinates":[4.2105569839,51.0501098633],"type":"Point"}
}