{
  "type": "Feature",
  "properties": {
    "iso:country":"BE",
    "sg:address":"Garzebekeveldstraat 2",
    "sg:city":"De Panne",
    "sg:orig_category":"Banken and kredietinstellingen",
    "sg:phone":"+32 58 41 22 78",
    "sg:postcode":"8660",
    "sg:province":"West-Vlaanderen",
    "wof:name":"Fortis",
    "wof:placetype":"venue"
},
  "geometry": {"coordinates":[2.5987539291,51.0727767944],"type":"Point"}
}