{
  "type": "Feature",
  "properties": {
    "addr:full":"Chauss\u00e9e De Bruxelles 87 Waterloo Brabant Wallon 1410",
    "addr:housenumber":"87",
    "addr:postcode":"1410",
    "addr:street":"Chausse\u0301E De Bruxelles",
    "iso:country":"BE",
    "sg:address":"Chauss\u00e9e De Bruxelles 87",
    "sg:city":"Waterloo",
    "sg:classifiers":[
        {
            "category":"Retail",
            "subcategory":"Repair Shop",
            "type":"Services"
        }
    ],
    "sg:phone":"+32 2 353 03 47",
    "sg:postcode":"1410",
    "sg:province":"Brabant Wallon",
    "sg:tags":[
        "upholsterer"
    ],
    "wof:name":"Nicholson (les Ateliers De)",
    "wof:placetype":"venue"
},
  "geometry": {"coordinates":[4.3983149529,50.723033905],"type":"Point"}
}