{
  "type": "Feature",
  "properties": {
    "addr:full":"Kasteelstraat 16 Temse Oost-Vlaanderen 9140",
    "addr:housenumber":"16",
    "addr:postcode":"9140",
    "addr:street":"Kasteelstraat",
    "iso:country":"BE",
    "sg:address":"Kasteelstraat 16",
    "sg:city":"Temse",
    "sg:orig_category":"Protection civile",
    "sg:phone":"+32 3 771 13 20",
    "sg:postcode":"9140",
    "sg:province":"Oost-Vlaanderen",
    "wof:name":"Brandweerkazerne",
    "wof:placetype":"venue"
},
  "geometry": {"coordinates":[4.2151141167,51.1247177124],"type":"Point"}
}