{
  "type": "Feature",
  "properties": {
    "addr:full":"Avenue Du Castillon 71 Chastre Brabant Wallon 1450",
    "addr:housenumber":"71",
    "addr:postcode":"1450",
    "addr:street":"Avenue Du Castillon",
    "iso:country":"BE",
    "sg:address":"Avenue Du Castillon 71",
    "sg:city":"Chastre",
    "sg:classifiers":[
        {
            "category":"Government",
            "subcategory":"Police Station",
            "type":"Public Place"
        }
    ],
    "sg:phone":"+32 10 65 84 75",
    "sg:postcode":"1450",
    "sg:province":"Brabant Wallon",
    "sg:tags":[
        "gendarmerie"
    ],
    "wof:name":"Police F\u00c9d\u00c9rale/federale Politie",
    "wof:placetype":"venue"
},
  "geometry": {"coordinates":[4.644382,50.6103401184],"type":"Point"}
}