{
  "type": "Feature",
  "properties": {
    "iso:country":"BE",
    "sg:address":"Kerkstraat 13a",
    "sg:city":"Aarschot",
    "sg:classifiers":[
        {
            "category":"Bakery",
            "type":"Food & Drink"
        }
    ],
    "sg:phone":"+32 16 56 18 52",
    "sg:postcode":"3200",
    "sg:province":"Vlaams-Brabant",
    "sg:tags":[
        "confectioner",
        "baker"
    ],
    "wof:name":"Pleintje('t)",
    "wof:placetype":"venue"
},
  "geometry": {"coordinates":[4.8359441757,51.0059738159],"type":"Point"}
}