{
  "type": "Feature",
  "properties": {
    "addr:full":"Rue Du Pr\u00c9 Aux Oies 114 Brussel/bruxelles Bruxelles-Capitale 1130",
    "addr:housenumber":"114",
    "addr:postcode":"1130",
    "addr:street":"Rue Du Pre\u0301 Aux Oies;/",
    "iso:country":"BE",
    "sg:address":"Rue Du Pr\u00c9 Aux Oies 114",
    "sg:city":"Brussel/bruxelles",
    "sg:orig_category":"Studios photographiques",
    "sg:phone":"+32 2 245 25 37",
    "sg:postcode":"1130",
    "sg:province":"Bruxelles-Capitale",
    "wof:name":"Philippe Delchevalerie",
    "wof:placetype":"venue"
},
  "geometry": {"coordinates":[4.4161739349,50.8929977417],"type":"Point"}
}