{
  "type": "Feature",
  "properties": {
    "addr:full":"Dornernieuwstraat 45a Maaseik Limburg 3680",
    "addr:housenumber":"45a",
    "addr:postcode":"3680",
    "addr:street":"Dornernieuwstraat",
    "iso:country":"BE",
    "sg:address":"Dornernieuwstraat 45a",
    "sg:city":"Maaseik",
    "sg:classifiers":[
        {
            "category":"Personal",
            "subcategory":"Beauty Salon",
            "type":"Services"
        }
    ],
    "sg:phone":"+32 89 85 67 35",
    "sg:postcode":"3680",
    "sg:province":"Limburg",
    "sg:tags":[
        "de",
        "coiffure"
    ],
    "wof:name":"Kapsalon Modo",
    "wof:placetype":"venue"
},
  "geometry": {"coordinates":[5.791285038,51.0954208374],"type":"Point"}
}