{
  "type": "Feature",
  "properties": {
    "addr:full":"Beukenstraat 9 Meeuwen-gruitrode Limburg 3670",
    "addr:housenumber":"9",
    "addr:postcode":"3670",
    "addr:street":"Beukenstraat",
    "iso:country":"BE",
    "sg:address":"Beukenstraat 9",
    "sg:city":"Meeuwen-gruitrode",
    "sg:orig_category":"Varkenskwekers",
    "sg:phone":"+32 11 79 17 43",
    "sg:postcode":"3670",
    "sg:province":"Limburg",
    "wof:name":"Ceyssens Theodoor & Peter",
    "wof:placetype":"venue"
},
  "geometry": {"coordinates":[5.4924120903,51.095287323],"type":"Point"}
}