{
  "type": "Feature",
  "properties": {
    "addr:full":"Dikke Eikstraat 69 Lummen Limburg 3560",
    "addr:housenumber":"69",
    "addr:postcode":"3560",
    "addr:street":"Eikstraat",
    "iso:country":"BE",
    "sg:address":"Dikke Eikstraat 69",
    "sg:city":"Lummen",
    "sg:classifiers":[
        {
            "category":"Professional",
            "subcategory":"Management & Consulting",
            "type":"Services"
        }
    ],
    "sg:phone":"+32 13 31 34 03",
    "sg:postcode":"3560",
    "sg:province":"Limburg",
    "sg:tags":[
        "consultant",
        "agency",
        "advertising"
    ],
    "wof:name":"Vanhove R",
    "wof:placetype":"venue"
},
  "geometry": {"coordinates":[5.1560969353,50.9928703308],"type":"Point"}
}