{
  "type": "Feature",
  "properties": {
    "addr:full":"Rue De Hollande 45 Sint-gillis/saint-gilles Bruxelles-Capitale 1060",
    "addr:housenumber":"45",
    "addr:postcode":"1060",
    "addr:street":"Rue De Hollande",
    "iso:country":"BE",
    "sg:address":"Rue De Hollande 45",
    "sg:city":"Sint-gillis/saint-gilles",
    "sg:orig_category":"D\u00e9corateurs d'int\u00e9rieur",
    "sg:phone":"+32 2 537 21 52",
    "sg:postcode":"1060",
    "sg:province":"Bruxelles-Capitale",
    "wof:name":"Bureau D\u00b4haenens",
    "wof:placetype":"venue"
},
  "geometry": {"coordinates":[4.3394908905,50.8342018127],"type":"Point"}
}