{
  "type": "Feature",
  "properties": {
    "iso:country":"BE",
    "sg:address":"Kapellensteenweg 162",
    "sg:city":"Kalmthout",
    "sg:classifiers":[
        {
            "category":"Shopping",
            "subcategory":"Clothing, Apparel, & Fashions",
            "type":"Retail Goods"
        }
    ],
    "sg:phone":"+32 3 666 51 31",
    "sg:postcode":"2920",
    "sg:province":"Antwerpen",
    "sg:tags":[
        "-",
        "clothing",
        "child"
    ],
    "wof:name":"Vier Seizoenen (de) Bvba",
    "wof:placetype":"venue"
},
  "geometry": {"coordinates":[4.4748039246,51.3833694458],"type":"Point"}
}