{
  "type": "Feature",
  "properties": {
    "iso:country":"BE",
    "sg:address":"Brusselbaan 249",
    "sg:city":"Affligem",
    "sg:orig_category":"V\u00e9los",
    "sg:phone":"+32 53 66 70 79",
    "sg:postcode":"1790",
    "sg:province":"Vlaams-Brabant",
    "wof:name":"Edmond De Vidts",
    "wof:placetype":"venue"
},
  "geometry": {"coordinates":[4.1189451218,50.9122200012],"type":"Point"}
}