{
  "type": "Feature",
  "properties": {
    "iso:country":"BE",
    "sg:address":"Rue De Brantignies 8",
    "sg:city":"Ath",
    "sg:classifiers":[
        {
            "category":"Shopping",
            "subcategory":"Clothing, Apparel, & Fashions",
            "type":"Retail Goods"
        }
    ],
    "sg:phone":"+32 68 28 44 84",
    "sg:postcode":"7800",
    "sg:province":"Hainaut",
    "sg:tags":[
        "v\u00eatements",
        "pour",
        "dame"
    ],
    "wof:name":"Maison Pullover",
    "wof:placetype":"venue"
},
  "geometry": {"coordinates":[3.777025938,50.6316680908],"type":"Point"}
}