{
  "type": "Feature",
  "properties": {
    "addr:full":"Kattestraat 7 Kluisbergen (ruien) Oost-Vlaanderen 9690",
    "addr:housenumber":"7",
    "addr:postcode":"9690",
    "addr:street":"Kattestraat",
    "iso:country":"BE",
    "sg:address":"Kattestraat 7",
    "sg:city":"Kluisbergen (ruien)",
    "sg:classifiers":[
        {
            "category":"Wholesale",
            "subcategory":"Machinery & Supplies",
            "type":"Manufacturing & Wholesale Goods"
        }
    ],
    "sg:phone":"+32 55 38 73 56",
    "sg:postcode":"9690",
    "sg:province":"Oost-Vlaanderen",
    "sg:tags":[
        "agricultural",
        "tractor"
    ],
    "wof:name":"Geiregat E",
    "wof:placetype":"venue"
},
  "geometry": {"coordinates":[3.4659919739,50.765247345],"type":"Point"}
}