{
  "type": "Feature",
  "properties": {
    "addr:full":"Rue Ch\u00c8re Voie 75 Sambreville Namur 5060",
    "addr:housenumber":"75",
    "addr:postcode":"5060",
    "addr:street":"Rue Che\u0300Re Voie",
    "iso:country":"BE",
    "sg:address":"Rue Ch\u00c8re Voie 75",
    "sg:city":"Sambreville",
    "sg:orig_category":"Cliniques and h\u00f4pitaux. Ambulances. M\u00e9decins and sp\u00e9cialistes",
    "sg:phone":"+32 71 26 52 11",
    "sg:postcode":"5060",
    "sg:province":"Namur",
    "wof:name":"Cent. Hosp. R\u00c9gion. Du Val De Sambre",
    "wof:placetype":"venue"
},
  "geometry": {"coordinates":[4.6273322105,50.4359207153],"type":"Point"}
}