{
  "type": "Feature",
  "properties": {
    "addr:full":"Rue Joseph Wauters 10 Amay Li\u00e8ge 4540",
    "addr:housenumber":"10",
    "addr:postcode":"4540",
    "addr:street":"Rue Joseph Wauters",
    "iso:country":"BE",
    "sg:address":"Rue Joseph Wauters 10",
    "sg:city":"Amay",
    "sg:classifiers":[
        {
            "category":"Home & Garden",
            "subcategory":"Household Appliances",
            "type":"Retail Goods"
        }
    ],
    "sg:phone":"+32 85 31 15 86",
    "sg:postcode":"4540",
    "sg:province":"Li\u00e8ge",
    "sg:tags":[
        "repair",
        "stove",
        "-"
    ],
    "wof:name":"Id\u00e9al Confort Sprl",
    "wof:placetype":"venue"
},
  "geometry": {"coordinates":[5.3194599152,50.5475845337],"type":"Point"}
}