{
  "type": "Feature",
  "properties": {
    "addr:full":"Shopping Center I Genk Limburg 3600",
    "addr:postcode":"3600",
    "addr:street":"Shopping;I;Limburg",
    "iso:country":"BE",
    "sg:address":"Shopping Center I",
    "sg:city":"Genk",
    "sg:classifiers":[
        {
            "category":"Shopping",
            "subcategory":"Optician",
            "type":"Retail Goods"
        }
    ],
    "sg:phone":"+32 89 35 31 83",
    "sg:postcode":"3600",
    "sg:province":"Limburg",
    "sg:tags":[
        "-"
    ],
    "wof:name":"Roterman",
    "wof:placetype":"venue"
},
  "geometry": {"coordinates":[5.4931697845,50.9654083252],"type":"Point"}
}