{
  "type": "Feature",
  "properties": {
    "addr:full":"Rue De L' Eglise 14 Hensies Hainaut 7350",
    "addr:housenumber":"14",
    "addr:postcode":"7350",
    "addr:street":"Rue De L ' Eglise",
    "iso:country":"BE",
    "sg:address":"Rue De L' Eglise 14",
    "sg:city":"Hensies",
    "sg:orig_category":"Brood, gebak and snoepgoed",
    "sg:phone":"+32 65 45 83 13",
    "sg:postcode":"7350",
    "sg:province":"Hainaut",
    "wof:name":"Marcel Duchateau",
    "wof:placetype":"venue"
},
  "geometry": {"coordinates":[3.6810429096,50.4355049133],"type":"Point"}
}