{
  "type": "Feature",
  "properties": {
    "iso:country":"BE",
    "sg:address":"Rue De Nivelles 108",
    "sg:city":"Ecaussinnes (marche-lez-ecaussines)",
    "sg:classifiers":[
        {
            "category":"Building & Trades",
            "subcategory":"Landscaping Services",
            "type":"Services"
        }
    ],
    "sg:phone":"+32 67 49 18 85",
    "sg:postcode":"7190",
    "sg:province":"Hainaut",
    "sg:tags":[
        "gardening",
        "garden",
        "maintenance"
    ],
    "wof:name":"Jardins D'olivier (les)",
    "wof:placetype":"venue"
},
  "geometry": {"coordinates":[4.2008061409,50.5523796082],"type":"Point"}
}