{
  "type": "Feature",
  "properties": {
    "addr:full":"Vorstlaan 2 Watermaal-bosvoorde/watermael-boitsfort Bruxelles-Capitale 1170",
    "addr:housenumber":"2",
    "addr:postcode":"1170",
    "addr:street":"Vorstlaan",
    "iso:country":"BE",
    "sg:address":"Vorstlaan 2",
    "sg:city":"Watermaal-bosvoorde/watermael-boitsfort",
    "sg:classifiers":[
        {
            "category":"Insurance",
            "subcategory":"Insurance Agent",
            "type":"Services"
        }
    ],
    "sg:phone":"+32 2 674 98 10",
    "sg:postcode":"1170",
    "sg:province":"Bruxelles-Capitale",
    "sg:tags":[
        "verzekeringsmakelaars",
        "expert"
    ],
    "wof:name":"Carpenter Guy",
    "wof:placetype":"venue"
},
  "geometry": {"coordinates":[4.4197502136,50.7920875549],"type":"Point"}
}