{
  "type": "Feature",
  "properties": {
    "addr:full":"Rue De La Chauss\u00e9e 31 Fontaine-l'ev\u00eaque (forchies-la-marche) Hainaut 6141",
    "addr:housenumber":"31",
    "addr:postcode":"6141",
    "addr:street":"Rue De La Chausse\u0301E;Hainaut",
    "iso:country":"BE",
    "sg:address":"Rue De La Chauss\u00e9e 31",
    "sg:city":"Fontaine-l'ev\u00eaque (forchies-la-marche)",
    "sg:classifiers":[
        {
            "category":"Shopping",
            "subcategory":"Books",
            "type":"Retail Goods"
        }
    ],
    "sg:phone":"+32 71 52 93 76",
    "sg:postcode":"6141",
    "sg:province":"Hainaut",
    "sg:tags":[
        "bookseller"
    ],
    "wof:name":"Trieux (librairie Des)",
    "wof:placetype":"venue"
},
  "geometry": {"coordinates":[-111.9644622803,46.2507972717],"type":"Point"}
}