{
  "type": "Feature",
  "properties": {
    "iso:country":"BE",
    "sg:address":"Rue A Victor 58a",
    "sg:city":"Musson",
    "sg:classifiers":[
        {
            "category":"Personal",
            "subcategory":"Beauty Salon",
            "type":"Services"
        }
    ],
    "sg:phone":"+32 63 67 58 61",
    "sg:postcode":"6750",
    "sg:province":"Luxembourg",
    "sg:tags":[
        "de",
        "coiffure"
    ],
    "wof:name":"Isabelle Ortega",
    "wof:placetype":"venue"
},
  "geometry": {"coordinates":[5.7049531937,49.5571479797],"type":"Point"}
}