{
  "type": "Feature",
  "properties": {
    "addr:full":"Dorpstraat 40 Wellen Limburg 3830",
    "addr:housenumber":"40",
    "addr:postcode":"3830",
    "addr:street":"Dorpstraat",
    "iso:country":"BE",
    "sg:address":"Dorpstraat 40",
    "sg:city":"Wellen",
    "sg:orig_category":"Non-Classified Establishments",
    "sg:phone":"+32 12 74 46 13",
    "sg:postcode":"3830",
    "sg:province":"Limburg",
    "wof:name":"Govaerts",
    "wof:placetype":"venue"
},
  "geometry": {"coordinates":[5.3324079514,50.8406066895],"type":"Point"}
}