{
  "type": "Feature",
  "properties": {
    "iso:country":"BE",
    "sg:address":"Loofblommestraat 93",
    "sg:city":"Gent (sint-denijs-westrem - Afsnee)",
    "sg:classifiers":[
        {
            "category":"Fast Food",
            "type":"Food & Drink"
        }
    ],
    "sg:phone":"+32 9 222 93 76",
    "sg:postcode":"9051",
    "sg:province":"Oost-Vlaanderen",
    "sg:tags":[
        "fried",
        "stand",
        "potato"
    ],
    "wof:name":"Meuleke ('t)",
    "wof:placetype":"venue"
},
  "geometry": {"coordinates":[3.6687328815,51.0237770081],"type":"Point"}
}