{
  "type": "Feature",
  "properties": {
    "iso:country":"BE",
    "sg:address":"Bertogne 177",
    "sg:city":"Bertogne",
    "sg:orig_category":"Pleisterwerk",
    "sg:phone":"+32 61 21 72 59",
    "sg:postcode":"6687",
    "sg:province":"Luxembourg",
    "wof:name":"Roger Vandendyck",
    "wof:placetype":"venue"
},
  "geometry": {"coordinates":[5.6763930321,50.0879707336],"type":"Point"}
}