{
  "type": "Feature",
  "properties": {
    "addr:full":"Brusselbaan 155 Aalst Oost-Vlaanderen 9320",
    "addr:housenumber":"155",
    "addr:postcode":"9320",
    "addr:street":"Brusselbaan",
    "iso:country":"BE",
    "sg:address":"Brusselbaan 155",
    "sg:city":"Aalst",
    "sg:classifiers":[
        {
            "category":"Cafe",
            "type":"Food & Drink"
        }
    ],
    "sg:phone":"+32 53 21 49 05",
    "sg:postcode":"9320",
    "sg:province":"Oost-Vlaanderen",
    "sg:tags":[
        "caf\u00e9s"
    ],
    "wof:name":"Marianne Van Goethem",
    "wof:placetype":"venue"
},
  "geometry": {"coordinates":[4.0553851128,50.9209976196],"type":"Point"}
}