{
  "type": "Feature",
  "properties": {
    "iso:country":"BE",
    "sg:address":"Antwerpsesteenweg 48",
    "sg:city":"Temse",
    "sg:orig_category":"Antiek",
    "sg:phone":"+32 3 711 18 25",
    "sg:postcode":"9140",
    "sg:province":"Oost-Vlaanderen",
    "wof:name":"Antiek-atelier Vincke-weijn",
    "wof:placetype":"venue"
},
  "geometry": {"coordinates":[4.1790881157,51.1129341125],"type":"Point"}
}