{
  "type": "Feature",
  "properties": {
    "iso:country":"BE",
    "sg:address":"Rue De Hussompont 11",
    "sg:city":"Jodoigne",
    "sg:orig_category":"Eclairage et \u00e9quipements du foyer",
    "sg:phone":"+32 10 81 33 80",
    "sg:postcode":"1370",
    "sg:province":"Brabant Wallon",
    "wof:name":"Stephane Dupont",
    "wof:placetype":"venue"
},
  "geometry": {"coordinates":[4.8426551819,50.7416877747],"type":"Point"}
}