{
  "type": "Feature",
  "properties": {
    "iso:country":"BE",
    "sg:address":"Rue De La Tombelle 2",
    "sg:city":"Ch\u00e2telet",
    "sg:classifiers":[
        {
            "category":"Bars & Pubs",
            "type":"Food & Drink"
        }
    ],
    "sg:phone":"+32 71 38 55 41",
    "sg:postcode":"6200",
    "sg:province":"Hainaut",
    "wof:name":"Richelieu (le)",
    "wof:placetype":"venue"
},
  "geometry": {"coordinates":[4.5231747627,50.4048233032],"type":"Point"}
}