{
  "type": "Feature",
  "properties": {
    "iso:country":"BE",
    "sg:address":"Avenue Des Martyrs 234",
    "sg:city":"Fleron",
    "sg:orig_category":"Pharmaciens",
    "sg:phone":"+32 4 358 30 44",
    "sg:postcode":"4620",
    "sg:province":"Li\u00e8ge",
    "wof:name":"J. Iserentant",
    "wof:placetype":"venue"
},
  "geometry": {"coordinates":[5.6831908226,50.6144180298],"type":"Point"}
}