{
  "type": "Feature",
  "properties": {
    "iso:country":"BE",
    "sg:address":"Rue De Corbeau 10",
    "sg:city":"Courcelles",
    "sg:orig_category":"Groenten and fruit Gh",
    "sg:phone":"+32 71 45 70 74",
    "sg:postcode":"6183",
    "sg:province":"Hainaut",
    "wof:name":"Parlapiano",
    "wof:placetype":"venue"
},
  "geometry": {"coordinates":[4.3331460953,50.4700584412],"type":"Point"}
}