{
  "type": "Feature",
  "properties": {
    "iso:country":"BE",
    "sg:address":"Wollestraat 51",
    "sg:city":"Brugge",
    "sg:orig_category":"Parfumeries",
    "sg:phone":"+32 50 33 88 19",
    "sg:postcode":"8000",
    "sg:province":"West-Vlaanderen",
    "wof:name":"Brugs Zeepwinkeltje",
    "wof:placetype":"venue"
},
  "geometry": {"coordinates":[3.2270729542,51.2070732117],"type":"Point"}
}