{
  "type": "Feature",
  "properties": {
    "iso:country":"BE",
    "sg:address":"Rue Pont D'avroy 50",
    "sg:city":"Li\u00e8ge 1",
    "sg:classifiers":[
        {
            "category":"Cafe",
            "type":"Food & Drink"
        }
    ],
    "sg:phone":"+32 4 250 69 19",
    "sg:postcode":"4000",
    "sg:province":"Li\u00e8ge",
    "sg:tags":[
        "snack-bars"
    ],
    "wof:name":"Baragan (le)",
    "wof:placetype":"venue"
},
  "geometry": {"coordinates":[5.5689258575,50.6403503418],"type":"Point"}
}