{
  "type": "Feature",
  "properties": {
    "addr:full":"Stationslaan 44 Zemst Vlaams-Brabant 1980",
    "addr:housenumber":"44",
    "addr:postcode":"1980",
    "addr:street":"Stationslaan;Vlaams-Brabant",
    "iso:country":"BE",
    "sg:address":"Stationslaan 44",
    "sg:city":"Zemst",
    "sg:orig_category":"Peinture. Rev\u00eatements pour sols and murs",
    "sg:phone":"+32 15 61 18 21",
    "sg:postcode":"1980",
    "sg:province":"Vlaams-Brabant",
    "wof:name":"Ivo Pepermans",
    "wof:placetype":"venue"
},
  "geometry": {"coordinates":[4.4664130211,50.9833145142],"type":"Point"}
}