{
  "type": "Feature",
  "properties": {
    "iso:country":"BE",
    "sg:address":"Zwaaikomstraat 22",
    "sg:city":"Roeselare",
    "sg:classifiers":[
        {
            "category":"Manufacturing",
            "subcategory":"Textiles",
            "type":"Manufacturing & Wholesale Goods"
        }
    ],
    "sg:phone":"+32 51 24 81 70",
    "sg:postcode":"8800",
    "sg:province":"West-Vlaanderen",
    "sg:tags":[
        "technical"
    ],
    "wof:name":"Veranneman Technical Textiles Nv",
    "wof:placetype":"venue"
},
  "geometry": {"coordinates":[3.1520709991,50.9497261047],"type":"Point"}
}