{
  "type": "Feature",
  "properties": {
    "addr:full":"Faubourg De Mignault 17 Le Roeulx Hainaut 7070",
    "addr:housenumber":"17",
    "addr:postcode":"7070",
    "addr:street":"Faubourg De Mignault",
    "iso:country":"BE",
    "sg:address":"Faubourg De Mignault 17",
    "sg:city":"Le Roeulx",
    "sg:classifiers":[
        {
            "category":"Real Estate",
            "subcategory":"Developer",
            "type":"Services"
        }
    ],
    "sg:phone":"+32 64 67 55 86",
    "sg:postcode":"7070",
    "sg:province":"Hainaut",
    "sg:tags":[
        "project"
    ],
    "wof:name":"Promotions Y.w. Sa",
    "wof:placetype":"venue"
},
  "geometry": {"coordinates":[4.1205301285,50.5089111328],"type":"Point"}
}