{
  "type": "Feature",
  "properties": {
    "addr:full":"Hasseltweg 341 Genk Limburg 3600",
    "addr:housenumber":"341",
    "addr:postcode":"3600",
    "addr:street":"Hasseltweg",
    "iso:country":"BE",
    "sg:address":"Hasseltweg 341",
    "sg:city":"Genk",
    "sg:orig_category":"Mat\u00e9riaux de construction Jardinage",
    "sg:phone":"+32 89 35 78 90",
    "sg:postcode":"3600",
    "sg:province":"Limburg",
    "wof:name":"L Hollands",
    "wof:placetype":"venue"
},
  "geometry": {"coordinates":[5.4345149994,50.9573249817],"type":"Point"}
}