{
  "type": "Feature",
  "properties": {
    "addr:full":"Hullekenstraat 169 Dendermonde (sint-gillis-bij-dendermonde) Oost-Vlaanderen 9200",
    "addr:housenumber":"169",
    "addr:postcode":"9200",
    "addr:street":"Hullekenstraat",
    "iso:country":"BE",
    "sg:address":"Hullekenstraat 169",
    "sg:city":"Dendermonde (sint-gillis-bij-dendermonde)",
    "sg:classifiers":[
        {
            "category":"Health Services",
            "subcategory":"Dentist",
            "type":"Services"
        }
    ],
    "sg:phone":"+32 52 22 08 57",
    "sg:postcode":"9200",
    "sg:province":"Oost-Vlaanderen",
    "wof:name":"Van Daele M",
    "wof:placetype":"venue"
},
  "geometry": {"coordinates":[4.1197052002,51.0276908875],"type":"Point"}
}