{
  "type": "Feature",
  "properties": {
    "addr:full":"Courtil 104 Gouvy Luxembourg 6671",
    "addr:housenumber":"104",
    "addr:postcode":"6671",
    "addr:street":"Courtil",
    "iso:country":"BE",
    "sg:address":"Courtil 104",
    "sg:city":"Gouvy",
    "sg:orig_category":"Verplichte sociale verzekeringen",
    "sg:phone":"+32 80 21 52 95",
    "sg:postcode":"6671",
    "sg:province":"Luxembourg",
    "wof:name":"La Femada",
    "wof:placetype":"venue"
},
  "geometry": {"coordinates":[5.9153008461,50.2131004333],"type":"Point"}
}