{
  "type": "Feature",
  "properties": {
    "addr:full":"Kruispadstraat 3 Schoten Antwerpen 2900",
    "addr:housenumber":"3",
    "addr:postcode":"2900",
    "addr:street":"Kruispadstraat",
    "iso:country":"BE",
    "sg:address":"Kruispadstraat 3",
    "sg:city":"Schoten",
    "sg:classifiers":[
        {
            "category":"Personal",
            "subcategory":"Barber",
            "type":"Services"
        }
    ],
    "sg:phone":"+32 3 658 82 14",
    "sg:postcode":"2900",
    "sg:province":"Antwerpen",
    "sg:tags":[
        "gentleman",
        "salon",
        "-",
        "hairdressing"
    ],
    "wof:name":"Paul",
    "wof:placetype":"venue"
},
  "geometry": {"coordinates":[4.5036001205,51.2541465759],"type":"Point"}
}