{
  "type": "Feature",
  "properties": {
    "iso:country":"BE",
    "sg:address":"Rue Des Saules 38",
    "sg:city":"Huy",
    "sg:orig_category":"Rusthuizen and serviceflats",
    "sg:phone":"+32 85 24 40 50",
    "sg:postcode":"4500",
    "sg:province":"Li\u00e8ge",
    "wof:name":"R\u00c9sidence Notre Dame",
    "wof:placetype":"venue"
},
  "geometry": {"coordinates":[5.2498102188,50.5323600769],"type":"Point"}
}