{
  "type": "Feature",
  "properties": {
    "iso:country":"BE",
    "sg:address":"Vinkenlei 7a",
    "sg:city":"Schoten",
    "sg:orig_category":"Vertalers and tolken",
    "sg:phone":"+32 3 288 92 10",
    "sg:postcode":"2900",
    "sg:province":"Antwerpen",
    "wof:name":"Bervoets Marleen",
    "wof:placetype":"venue"
},
  "geometry": {"coordinates":[4.5237779617,51.2562332153],"type":"Point"}
}