{
  "type": "Feature",
  "properties": {
    "addr:full":"Rue A Renard 95 Ukkel/uccle Bruxelles-Capitale 1180",
    "addr:housenumber":"95",
    "addr:postcode":"1180",
    "addr:street":"Rue A Renard;/",
    "iso:country":"BE",
    "sg:address":"Rue A Renard 95",
    "sg:city":"Ukkel/uccle",
    "sg:orig_category":"Fer and acier Fab",
    "sg:phone":"+32 2 343 67 04",
    "sg:postcode":"1180",
    "sg:province":"Bruxelles-Capitale",
    "wof:name":"Englebert M",
    "wof:placetype":"venue"
},
  "geometry": {"coordinates":[4.3797769547,50.7913780212],"type":"Point"}
}