{
  "type": "Feature",
  "properties": {
    "iso:country":"BE",
    "sg:address":"Nervi\u00cbrsstraat 67",
    "sg:city":"Asse",
    "sg:orig_category":"Herstellingen and onderhoud van auto's",
    "sg:phone":"+32 2 452 69 44",
    "sg:postcode":"1730",
    "sg:province":"Vlaams-Brabant",
    "wof:name":"Andr\u00c9",
    "wof:placetype":"venue"
},
  "geometry": {"coordinates":[4.1885900497,50.9172592163],"type":"Point"}
}