{
  "type": "Feature",
  "properties": {
    "addr:full":"Rue Saint-martin 91 Tournai Hainaut 7500",
    "addr:housenumber":"91",
    "addr:postcode":"7500",
    "addr:street":"Rue Saint-Martin",
    "iso:country":"BE",
    "sg:address":"Rue Saint-martin 91",
    "sg:city":"Tournai",
    "sg:classifiers":[
        {
            "category":"Food & Beverages",
            "subcategory":"Groceries & Convenience Stores",
            "type":"Retail Goods"
        }
    ],
    "sg:phone":"+32 69 22 87 65",
    "sg:postcode":"7500",
    "sg:province":"Hainaut",
    "sg:tags":[
        "grocer"
    ],
    "wof:name":"Roi Des Primeurs (au)",
    "wof:placetype":"venue"
},
  "geometry": {"coordinates":[3.3860399723,50.6038017273],"type":"Point"}
}