{
  "type": "Feature",
  "properties": {
    "addr:full":"Felix D'hoopstraat 89 Tielt West-Vlaanderen 8700",
    "addr:housenumber":"89",
    "addr:postcode":"8700",
    "addr:street":"D'Hoopstraat",
    "iso:country":"BE",
    "sg:address":"Felix D'hoopstraat 89",
    "sg:city":"Tielt",
    "sg:orig_category":"Assurances. Comptables",
    "sg:phone":"+32 51 40 21 79",
    "sg:postcode":"8700",
    "sg:province":"West-Vlaanderen",
    "wof:name":"Bureau Vansteenkiste",
    "wof:placetype":"venue"
},
  "geometry": {"coordinates":[3.3459730148,50.9976158142],"type":"Point"}
}