{
  "type": "Feature",
  "properties": {
    "iso:country":"BE",
    "sg:address":"Cit\u00e9 De L'abbaye 105",
    "sg:city":"Colfontaine (wasmes)",
    "sg:classifiers":[
        {
            "category":"Social Services",
            "type":"Services"
        }
    ],
    "sg:phone":"+32 65 67 17 88",
    "sg:postcode":"7340",
    "sg:province":"Hainaut",
    "wof:name":"L'accueil",
    "wof:placetype":"venue"
},
  "geometry": {"coordinates":[3.8379540443,50.4177398682],"type":"Point"}
}