{
  "type": "Feature",
  "properties": {
    "addr:full":"Roeselarestraat 121 Diksmuide West-Vlaanderen 8600",
    "addr:housenumber":"121",
    "addr:postcode":"8600",
    "addr:street":"Roeselarestraat",
    "iso:country":"BE",
    "sg:address":"Roeselarestraat 121",
    "sg:city":"Diksmuide",
    "sg:classifiers":[
        {
            "category":"Cafe",
            "type":"Food & Drink"
        }
    ],
    "sg:phone":"+32 51 56 62 80",
    "sg:postcode":"8600",
    "sg:province":"West-Vlaanderen",
    "sg:tags":[
        "caf\u00e9s"
    ],
    "wof:name":"Chantal Huyghebaert",
    "wof:placetype":"venue"
},
  "geometry": {"coordinates":[2.9393439293,51.0195579529],"type":"Point"}
}