{
  "type": "Feature",
  "properties": {
    "addr:full":"Kapellestraat 5 Gavere Oost-Vlaanderen 9890",
    "addr:housenumber":"5",
    "addr:postcode":"9890",
    "addr:street":"Kapellestraat",
    "iso:country":"BE",
    "sg:address":"Kapellestraat 5",
    "sg:city":"Gavere",
    "sg:orig_category":"Treinen and spoorwegen",
    "sg:phone":"+32 9 384 12 99",
    "sg:postcode":"9890",
    "sg:province":"Oost-Vlaanderen",
    "wof:name":"Station Gavere-asper",
    "wof:placetype":"venue"
},
  "geometry": {"coordinates":[3.6403529644,50.9270515442],"type":"Point"}
}