{
  "type": "Feature",
  "properties": {
    "addr:full":"Breendonkstraat 48 Sint-truiden Limburg 3800",
    "addr:housenumber":"48",
    "addr:postcode":"3800",
    "addr:street":"Breendonkstraat",
    "iso:country":"BE",
    "sg:address":"Breendonkstraat 48",
    "sg:city":"Sint-truiden",
    "sg:orig_category":"S\u00e9curit\u00e9 sociale",
    "sg:phone":"+32 11 68 21 61",
    "sg:postcode":"3800",
    "sg:province":"Limburg",
    "wof:name":"De Voorzorg",
    "wof:placetype":"venue"
},
  "geometry": {"coordinates":[5.1833620071,50.8174781799],"type":"Point"}
}