{
  "type": "Feature",
  "properties": {
    "iso:country":"BE",
    "sg:address":"Zum Ohlesief 28",
    "sg:city":"Bullingen",
    "sg:classifiers":[
        {
            "category":"Building & Trades",
            "subcategory":"Landscaping Services",
            "type":"Services"
        }
    ],
    "sg:phone":"+32 80 64 31 33",
    "sg:postcode":"4760",
    "sg:province":"Li\u00e8ge",
    "sg:tags":[
        "forestry"
    ],
    "wof:name":"Sujdak H",
    "wof:placetype":"venue"
},
  "geometry": {"coordinates":[6.2557492256,50.4061813354],"type":"Point"}
}