{
  "type": "Feature",
  "properties": {
    "iso:country":"BE",
    "sg:address":"Grote Markt 2",
    "sg:city":"Tongeren",
    "sg:orig_category":"Opticiens",
    "sg:phone":"+32 12 23 25 91",
    "sg:postcode":"3700",
    "sg:province":"Limburg",
    "wof:name":"Jules Vanheers",
    "wof:placetype":"venue"
},
  "geometry": {"coordinates":[5.4634947777,50.7805557251],"type":"Point"}
}