{
  "type": "Feature",
  "properties": {
    "addr:full":"Rue Du Manypr\u00c9 88 Chaumont-gistoux Brabant Wallon 1325",
    "addr:housenumber":"88",
    "addr:postcode":"1325",
    "addr:street":"Rue Du Manypre\u0301",
    "iso:country":"BE",
    "sg:address":"Rue Du Manypr\u00c9 88",
    "sg:city":"Chaumont-gistoux",
    "sg:orig_category":"Paramedische behandelingen",
    "sg:phone":"+32 10 68 90 63",
    "sg:postcode":"1325",
    "sg:province":"Brabant Wallon",
    "wof:name":"C. Gerbaux",
    "wof:placetype":"venue"
},
  "geometry": {"coordinates":[4.7223548889,50.6729545593],"type":"Point"}
}