{
  "type": "Feature",
  "properties": {
    "addr:full":"Kleine Veldstraat 11 Wingene West-Vlaanderen 8750",
    "addr:housenumber":"11",
    "addr:postcode":"8750",
    "addr:street":"Kleine Veldstraat",
    "iso:country":"BE",
    "sg:address":"Kleine Veldstraat 11",
    "sg:city":"Wingene",
    "sg:orig_category":"Rundveehouders",
    "sg:phone":"+32 51 65 53 70",
    "sg:postcode":"8750",
    "sg:province":"West-Vlaanderen",
    "wof:name":"Martin Duyck",
    "wof:placetype":"venue"
},
  "geometry": {"coordinates":[3.3269329071,51.0642356873],"type":"Point"}
}