{
  "type": "Feature",
  "properties": {
    "addr:full":"Ruyseveltslei 12 Box 2 Kapellen (mariaburg) Antwerpen 2950",
    "addr:housenumber":"12;2",
    "addr:postcode":"2950",
    "addr:street":"Ruyseveltslei;Box",
    "iso:country":"BE",
    "sg:address":"Ruyseveltslei 12 Box 2",
    "sg:city":"Kapellen (mariaburg)",
    "sg:classifiers":[
        {
            "category":"Retail",
            "subcategory":"Auto Rental",
            "type":"Services"
        }
    ],
    "sg:postcode":"2950",
    "sg:province":"Antwerpen",
    "sg:tags":[
        "plant",
        "flower",
        "-"
    ],
    "wof:name":"Hydro Design Bvba",
    "wof:placetype":"venue"
},
  "geometry": {"coordinates":[4.4377388954,51.3103904724],"type":"Point"}
}