{
  "type": "Feature",
  "properties": {
    "addr:full":"Rampe Sainte-waudru 16 Mons Hainaut 7000",
    "addr:housenumber":"16",
    "addr:postcode":"7000",
    "addr:street":"Rampe Sainte-Waudru;Hainaut",
    "iso:country":"BE",
    "sg:address":"Rampe Sainte-waudru 16",
    "sg:city":"Mons",
    "sg:classifiers":[
        {
            "category":"Social Services",
            "type":"Services"
        }
    ],
    "sg:phone":"+32 65 84 43 89",
    "sg:postcode":"7000",
    "sg:province":"Hainaut",
    "sg:tags":[
        "handicapped",
        "-"
    ],
    "wof:name":"Centre De Jour Pour Handicap\u00e9s Mentaux",
    "wof:placetype":"venue"
},
  "geometry": {"coordinates":[3.9475579262,50.4539833069],"type":"Point"}
}