{
  "type": "Feature",
  "properties": {
    "iso:country":"BE",
    "sg:address":"Paterstraat 6",
    "sg:city":"Temse",
    "sg:orig_category":"Avocats and conseillers juridiques",
    "sg:phone":"+32 3 711 01 49",
    "sg:postcode":"9140",
    "sg:province":"Oost-Vlaanderen",
    "wof:name":"Patrick Vermeulen",
    "wof:placetype":"venue"
},
  "geometry": {"coordinates":[4.2119479179,51.1251907349],"type":"Point"}
}