{
  "type": "Feature",
  "properties": {
    "iso:country":"BE",
    "sg:address":"Hei-ende 7",
    "sg:city":"Beerse",
    "sg:orig_category":"Banques and organismes de cr\u00e9dit",
    "sg:phone":"+32 3 312 48 06",
    "sg:postcode":"2340",
    "sg:province":"Antwerpen",
    "wof:name":"De Vaderlandsche",
    "wof:placetype":"venue"
},
  "geometry": {"coordinates":[4.7806768417,51.3022537231],"type":"Point"}
}