{
  "type": "Feature",
  "properties": {
    "iso:country":"BE",
    "sg:address":"Hoevenstraat 43",
    "sg:city":"Herselt",
    "sg:orig_category":"Supermarkten",
    "sg:phone":"+32 16 69 91 10",
    "sg:postcode":"2230",
    "sg:province":"Antwerpen",
    "wof:name":"Drankencenter Pelgrims",
    "wof:placetype":"venue"
},
  "geometry": {"coordinates":[4.8215398788,51.0259361267],"type":"Point"}
}