{
  "type": "Feature",
  "properties": {
    "iso:country":"BE",
    "sg:address":"Kerkelei 9",
    "sg:city":"Kontich (waarloos)",
    "sg:classifiers":[
        {
            "category":"Cafe",
            "type":"Food & Drink"
        }
    ],
    "sg:phone":"+32 15 33 12 00",
    "sg:postcode":"2550",
    "sg:province":"Antwerpen",
    "sg:tags":[
        "snack-bars"
    ],
    "wof:name":"Petit Gourmande",
    "wof:placetype":"venue"
},
  "geometry": {"coordinates":[4.453810215,51.1046447754],"type":"Point"}
}