{
  "type": "Feature",
  "properties": {
    "addr:full":"Sneppenpad 3 Knokke-heist West-Vlaanderen 8301",
    "addr:housenumber":"3",
    "addr:postcode":"8301",
    "addr:street":"Sneppenpad",
    "iso:country":"BE",
    "sg:address":"Sneppenpad 3",
    "sg:city":"Knokke-heist",
    "sg:orig_category":"Artsen and specialisten",
    "sg:phone":"+32 50 61 34 91",
    "sg:postcode":"8301",
    "sg:province":"West-Vlaanderen",
    "wof:name":"Albert-victor De Bevere",
    "wof:placetype":"venue"
},
  "geometry": {"coordinates":[3.2761878967,51.3437309265],"type":"Point"}
}