{
  "type": "Feature",
  "properties": {
    "iso:country":"BE",
    "sg:address":"Rue Eug\u00e8ne-houdret 59",
    "sg:city":"Li\u00e8ge 1 (glain)",
    "sg:classifiers":[
        {
            "category":"Retail",
            "subcategory":"Auto Repair",
            "type":"Services"
        }
    ],
    "sg:phone":"+32 4 226 56 31",
    "sg:postcode":"4000",
    "sg:province":"Li\u00e8ge",
    "sg:tags":[
        "garage"
    ],
    "wof:name":"Saab-daniel Car Garage",
    "wof:placetype":"venue"
},
  "geometry": {"coordinates":[5.5482578278,50.649559021],"type":"Point"}
}