{
  "type": "Feature",
  "properties": {
    "addr:full":"Vieille-route-de-marenne 10 Hotton Luxembourg 6990",
    "addr:housenumber":"10",
    "addr:postcode":"6990",
    "addr:street":"Vieille-Route-De-Marenne",
    "iso:country":"BE",
    "sg:address":"Vieille-route-de-marenne 10",
    "sg:city":"Hotton",
    "sg:orig_category":"V\u00e9t\u00e9rinaires",
    "sg:phone":"+32 84 32 21 86",
    "sg:postcode":"6990",
    "sg:province":"Luxembourg",
    "wof:name":"Philippe Picavet",
    "wof:placetype":"venue"
},
  "geometry": {"coordinates":[5.4036011696,50.247592926],"type":"Point"}
}