{
  "type": "Feature",
  "properties": {
    "addr:full":"Woluwe Shopping Center 284 Bruxelles (woluwe-saint-lambert) Bruxelles-Capitale 1200",
    "addr:housenumber":"284",
    "addr:postcode":"1200",
    "iso:country":"BE",
    "sg:address":"Woluwe Shopping Center 284",
    "sg:city":"Bruxelles (woluwe-saint-lambert)",
    "sg:classifiers":[
        {
            "category":"Shopping",
            "subcategory":"Clothing, Apparel, & Fashions",
            "type":"Retail Goods"
        }
    ],
    "sg:phone":"+32 2 779 14 86",
    "sg:postcode":"1200",
    "sg:province":"Bruxelles-Capitale",
    "sg:tags":[
        "boutique"
    ],
    "wof:name":"La Gaviotta",
    "wof:placetype":"venue"
},
  "geometry": {"coordinates":[4.4252500534,50.8438148499],"type":"Point"}
}