{
  "type": "Feature",
  "properties": {
    "addr:full":"Steenkuilstraat 2 Dilsen-stokkem Limburg 3650",
    "addr:housenumber":"2",
    "addr:postcode":"3650",
    "addr:street":"Steenkuilstraat",
    "iso:country":"BE",
    "sg:address":"Steenkuilstraat 2",
    "sg:city":"Dilsen-stokkem",
    "sg:orig_category":"Banques and organismes de cr\u00e9dit",
    "sg:phone":"+32 89 75 80 18",
    "sg:postcode":"3650",
    "sg:province":"Limburg",
    "wof:name":"Bacob",
    "wof:placetype":"venue"
},
  "geometry": {"coordinates":[5.727396965,51.0364189148],"type":"Point"}
}