{
  "type": "Feature",
  "properties": {
    "iso:country":"BE",
    "sg:address":"Lange Kroonstraat 207",
    "sg:city":"Boechout",
    "sg:classifiers":[
        {
            "category":"Personal",
            "subcategory":"Beauty Salon",
            "type":"Services"
        }
    ],
    "sg:phone":"+32 3 455 33 36",
    "sg:postcode":"2530",
    "sg:province":"Antwerpen",
    "sg:tags":[
        "lady",
        "-",
        "hairdressing"
    ],
    "wof:name":"Patteet R",
    "wof:placetype":"venue"
},
  "geometry": {"coordinates":[4.4849591255,51.1669883728],"type":"Point"}
}