{
  "type": "Feature",
  "properties": {
    "addr:full":"Meensesteenweg 194 Kortrijk West-Vlaanderen 8501",
    "addr:housenumber":"194",
    "addr:postcode":"8501",
    "addr:street":"Meensesteenweg",
    "iso:country":"BE",
    "sg:address":"Meensesteenweg 194",
    "sg:city":"Kortrijk",
    "sg:orig_category":"Entretien and r\u00e9parations de voitures",
    "sg:phone":"+32 56 35 51 17",
    "sg:postcode":"8501",
    "sg:province":"West-Vlaanderen",
    "wof:name":"Garage Dujardyn Serge",
    "wof:placetype":"venue"
},
  "geometry": {"coordinates":[3.2355289459,50.8256111145],"type":"Point"}
}