{
  "type": "Feature",
  "properties": {
    "iso:country":"BE",
    "sg:address":"Denderhoutembaan 139",
    "sg:city":"Ninove",
    "sg:classifiers":[
        {
            "category":"Landmark",
            "subcategory":"Memorial",
            "type":"Public Place"
        }
    ],
    "sg:phone":"+32 54 33 69 92",
    "sg:postcode":"9400",
    "sg:province":"Oost-Vlaanderen",
    "sg:tags":[
        "-",
        "monument"
    ],
    "wof:name":"Robert M",
    "wof:placetype":"venue"
},
  "geometry": {"coordinates":[4.0212879181,50.8451652527],"type":"Point"}
}