{
  "type": "Feature",
  "properties": {
    "addr:full":"Nieuwstraat 54 Denderleeuw Oost-Vlaanderen 9470",
    "addr:housenumber":"54",
    "addr:postcode":"9470",
    "addr:street":"Nieuwstraat",
    "iso:country":"BE",
    "sg:address":"Nieuwstraat 54",
    "sg:city":"Denderleeuw",
    "sg:classifiers":[
        {
            "category":"Professional",
            "subcategory":"Accounting & Tax Preparation",
            "type":"Services"
        }
    ],
    "sg:phone":"+32 53 66 23 51",
    "sg:postcode":"9470",
    "sg:province":"Oost-Vlaanderen",
    "sg:tags":[
        "bookkeeper"
    ],
    "wof:name":"Hanskens J",
    "wof:placetype":"venue"
},
  "geometry": {"coordinates":[4.0732398033,50.8798027039],"type":"Point"}
}