{
  "type": "Feature",
  "properties": {
    "iso:country":"BE",
    "sg:address":"Van Landeghemstraat 52",
    "sg:city":"Sint-niklaas",
    "sg:classifiers":[
        {
            "category":"Professional",
            "subcategory":"Management & Consulting",
            "type":"Services"
        }
    ],
    "sg:phone":"+32 3 766 61 56",
    "sg:postcode":"9100",
    "sg:province":"Oost-Vlaanderen",
    "sg:tags":[
        "tax-consultants"
    ],
    "wof:name":"Rumes F",
    "wof:placetype":"venue"
},
  "geometry": {"coordinates":[4.1808848381,51.167766571],"type":"Point"}
}