{
  "type": "Feature",
  "properties": {
    "iso:country":"BE",
    "sg:address":"Dennenstraat 22",
    "sg:city":"Willebroek",
    "sg:classifiers":[
        {
            "category":"Building & Trades",
            "subcategory":"Cleaning & Sanitation",
            "type":"Services"
        }
    ],
    "sg:phone":"+32 3 289 33 53",
    "sg:postcode":"2830",
    "sg:province":"Antwerpen",
    "sg:tags":[
        "fa\u00e7ade",
        "maintenance"
    ],
    "wof:name":"Lucrima Bvba",
    "wof:placetype":"venue"
},
  "geometry": {"coordinates":[4.3551659584,51.058681488],"type":"Point"}
}