{
  "type": "Feature",
  "properties": {
    "addr:full":"Chauss\u00e9e De Louvain 456 Bruxelles (schaerbeek) Bruxelles-Capitale 1030",
    "addr:housenumber":"456",
    "addr:postcode":"1030",
    "addr:street":"Chausse\u0301E De Louvain",
    "iso:country":"BE",
    "sg:address":"Chauss\u00e9e De Louvain 456",
    "sg:city":"Bruxelles (schaerbeek)",
    "sg:classifiers":[
        {
            "category":"Retail",
            "subcategory":"Repair Shop",
            "type":"Services"
        }
    ],
    "sg:phone":"+32 2 735 95 07",
    "sg:postcode":"1030",
    "sg:province":"Bruxelles-Capitale",
    "sg:tags":[
        "radio",
        "television",
        "-",
        "maintenance"
    ],
    "wof:name":"C.d.e.",
    "wof:placetype":"venue"
},
  "geometry": {"coordinates":[4.3904161453,50.8529052734],"type":"Point"}
}