{
  "type": "Feature",
  "properties": {
    "iso:country":"BE",
    "sg:address":"Rue Du Maka",
    "sg:city":"Yvoir",
    "sg:orig_category":"Sportterreinen and installaties behalve sportcentra",
    "sg:phone":"+32 82 61 03 40",
    "sg:postcode":"5530",
    "sg:province":"Namur",
    "wof:name":"V.c Mosan Yvoir",
    "wof:placetype":"venue"
},
  "geometry": {"coordinates":[4.8794560432,50.3266525269],"type":"Point"}
}