{
  "type": "Feature",
  "properties": {
    "addr:full":"Rue De Bouillon 24 Bi\u00e8vre Namur 5555",
    "addr:housenumber":"24",
    "addr:postcode":"5555",
    "addr:street":"Rue De Bouillon",
    "iso:country":"BE",
    "sg:address":"Rue De Bouillon 24",
    "sg:city":"Bi\u00e8vre",
    "sg:classifiers":[
        {
            "category":"Shopping",
            "subcategory":"Bicycles & Sporting Goods",
            "type":"Retail Goods"
        }
    ],
    "sg:phone":"+32 61 51 18 95",
    "sg:postcode":"5555",
    "sg:province":"Namur",
    "sg:tags":[
        "sport",
        "-"
    ],
    "wof:name":"Sportswear",
    "wof:placetype":"venue"
},
  "geometry": {"coordinates":[5.0216097832,49.9389190674],"type":"Point"}
}