{
  "type": "Feature",
  "properties": {
    "addr:full":"Werthplatz 4 Eupen Li\u00e8ge 4700",
    "addr:housenumber":"4",
    "addr:postcode":"4700",
    "addr:street":"Werthplatz",
    "iso:country":"BE",
    "sg:address":"Werthplatz 4",
    "sg:city":"Eupen",
    "sg:classifiers":[
        {
            "category":"Manufacturing",
            "subcategory":"Textiles",
            "type":"Manufacturing & Wholesale Goods"
        }
    ],
    "sg:phone":"+32 87 76 42 71",
    "sg:postcode":"4700",
    "sg:province":"Li\u00e8ge",
    "sg:tags":[
        "retail",
        "-"
    ],
    "wof:name":"Zeeman",
    "wof:placetype":"venue"
},
  "geometry": {"coordinates":[6.0385270119,50.6328582764],"type":"Point"}
}