{
  "type": "Feature",
  "properties": {
    "iso:country":"BE",
    "sg:address":"Kasteelstraat 9-11",
    "sg:city":"Ruiselede",
    "sg:classifiers":[
        {
            "category":"Professional",
            "subcategory":"Art Services",
            "type":"Services"
        }
    ],
    "sg:phone":"+32 51 68 92 94",
    "sg:postcode":"8755",
    "sg:province":"West-Vlaanderen",
    "sg:tags":[
        "photographer"
    ],
    "wof:name":"Maes N",
    "wof:placetype":"venue"
},
  "geometry": {"coordinates":[3.3955988884,51.0402603149],"type":"Point"}
}