{
  "type": "Feature",
  "properties": {
    "addr:full":"Torhoutsesteenweg 193 Oostende West-Vlaanderen 8400",
    "addr:housenumber":"193",
    "addr:postcode":"8400",
    "addr:street":"Torhoutsesteenweg",
    "iso:country":"BE",
    "sg:address":"Torhoutsesteenweg 193",
    "sg:city":"Oostende",
    "sg:orig_category":"Verhuur textielartikelen and schoenen",
    "sg:phone":"+32 59 50 13 03",
    "sg:postcode":"8400",
    "sg:province":"West-Vlaanderen",
    "wof:name":"Cerenomiekleding My Lady",
    "wof:placetype":"venue"
},
  "geometry": {"coordinates":[2.9076209068,51.2196846008],"type":"Point"}
}