{
  "type": "Feature",
  "properties": {
    "iso:country":"BE",
    "sg:address":"Dokter Eduard Moreauxln 2",
    "sg:city":"Oostende",
    "sg:orig_category":"Sportclubs",
    "sg:phone":"+32 59 32 14 52",
    "sg:postcode":"8400",
    "sg:province":"West-Vlaanderen",
    "wof:name":"Royal Yacht Club",
    "wof:placetype":"venue"
},
  "geometry": {"coordinates":[2.9412519932,51.2245597839],"type":"Point"}
}