{
  "type": "Feature",
  "properties": {
    "addr:full":"Rue De Xhoris 4 Aywaille Li\u00e8ge 4920",
    "addr:housenumber":"4",
    "addr:postcode":"4920",
    "addr:street":"Rue De Xhoris",
    "iso:country":"BE",
    "sg:address":"Rue De Xhoris 4",
    "sg:city":"Aywaille",
    "sg:orig_category":"Maisons de vacances",
    "sg:phone":"+32 4 384 56 08",
    "sg:postcode":"4920",
    "sg:province":"Li\u00e8ge",
    "wof:name":"G\u00cete Rural L'hirondelle",
    "wof:placetype":"venue"
},
  "geometry": {"coordinates":[5.6326341629,50.4457321167],"type":"Point"}
}