{
  "type": "Feature",
  "properties": {
    "iso:country":"BE",
    "sg:address":"Rue Puits-en-sock 145",
    "sg:city":"Li\u00c8ge",
    "sg:orig_category":"Poissonniers and \u00e9caillers",
    "sg:phone":"+32 4 349 00 49",
    "sg:postcode":"4020",
    "sg:province":"Li\u00e8ge",
    "wof:name":"Aquality",
    "wof:placetype":"venue"
},
  "geometry": {"coordinates":[5.5859217644,50.6389389038],"type":"Point"}
}