{
  "type": "Feature",
  "properties": {
    "iso:country":"BE",
    "sg:address":"Boulevard Adolphe Max 41",
    "sg:city":"Brussel/bruxelles",
    "sg:classifiers":[
        {
            "category":"Military Area",
            "subcategory":"Armory",
            "type":"Public Place"
        }
    ],
    "sg:phone":"+32 2 223 16 64",
    "sg:postcode":"1000",
    "sg:province":"Bruxelles-Capitale",
    "sg:tags":[
        "armes",
        "munition"
    ],
    "wof:name":"Armabel",
    "wof:placetype":"venue"
},
  "geometry": {"coordinates":[4.3548269272,50.852771759],"type":"Point"}
}