{
  "type": "Feature",
  "properties": {
    "addr:full":"Tielendorp 15 Kasterlee Antwerpen 2460",
    "addr:housenumber":"15",
    "addr:postcode":"2460",
    "addr:street":"Tielendorp",
    "iso:country":"BE",
    "sg:address":"Tielendorp 15",
    "sg:city":"Kasterlee",
    "sg:orig_category":"Plaatsen van vloer- and muurbekleding Woningbouw",
    "sg:phone":"+32 14 55 61 37",
    "sg:postcode":"2460",
    "sg:province":"Antwerpen",
    "wof:name":"Mertens & Co",
    "wof:placetype":"venue"
},
  "geometry": {"coordinates":[4.8969511986,51.2423973083],"type":"Point"}
}