{
  "type": "Feature",
  "properties": {
    "addr:full":"Klaverstraat 3-1 Veurne West-Vlaanderen 8630",
    "addr:housenumber":"3-1",
    "addr:postcode":"8630",
    "addr:street":"Klaverstraat",
    "iso:country":"BE",
    "sg:address":"Klaverstraat 3-1",
    "sg:city":"Veurne",
    "sg:classifiers":[
        {
            "category":"Transit Center",
            "subcategory":"Freight",
            "type":"Transportation"
        }
    ],
    "sg:phone":"+32 58 31 72 51",
    "sg:postcode":"8630",
    "sg:province":"West-Vlaanderen",
    "sg:tags":[
        "import",
        "export",
        "-"
    ],
    "wof:name":"Rsl Europe",
    "wof:placetype":"venue"
},
  "geometry": {"coordinates":[2.6635050774,51.0711174011],"type":"Point"}
}