{
  "type": "Feature",
  "properties": {
    "iso:country":"BE",
    "sg:address":"Rue Fond M\u00c9an 6",
    "sg:city":"Saint-georges-sur-meuse",
    "sg:orig_category":"Onderdelen and accessoires voor auto's Voertuigen",
    "sg:phone":"+32 4 275 35 77",
    "sg:postcode":"4470",
    "sg:province":"Li\u00e8ge",
    "wof:name":"Garage Angelo",
    "wof:placetype":"venue"
},
  "geometry": {"coordinates":[5.3818497658,50.6012115479],"type":"Point"}
}