{
  "type": "Feature",
  "properties": {
    "addr:full":"Rampe Des Ecoliers 27 Colfontaine Hainaut 7340",
    "addr:housenumber":"27",
    "addr:postcode":"7340",
    "addr:street":"Rampe Des Ecoliers",
    "iso:country":"BE",
    "sg:address":"Rampe Des Ecoliers 27",
    "sg:city":"Colfontaine",
    "sg:orig_category":"Paramedische behandelingen",
    "sg:phone":"+32 65 66 56 74",
    "sg:postcode":"7340",
    "sg:province":"Hainaut",
    "wof:name":"Laurence Remy",
    "wof:placetype":"venue"
},
  "geometry": {"coordinates":[3.8357760906,50.4025993347],"type":"Point"}
}