{
  "type": "Feature",
  "properties": {
    "iso:country":"BE",
    "sg:address":"Kasteleinsplein 28",
    "sg:city":"Elsene/ixelles",
    "sg:orig_category":"Artsen and specialisten",
    "sg:phone":"+32 2 534 39 12",
    "sg:postcode":"1050",
    "sg:province":"Bruxelles-Capitale",
    "wof:name":"Pierre Burghgraeve",
    "wof:placetype":"venue"
},
  "geometry": {"coordinates":[4.3596701622,50.8243026733],"type":"Point"}
}