{
  "type": "Feature",
  "properties": {
    "addr:full":"Chauss\u00e9e De Wavre 763 Bruxelles (etterbeek) Bruxelles-Capitale 1040",
    "addr:housenumber":"763",
    "addr:postcode":"1040",
    "addr:street":"Chausse\u0301E De Wavre",
    "iso:country":"BE",
    "sg:address":"Chauss\u00e9e De Wavre 763",
    "sg:city":"Bruxelles (etterbeek)",
    "sg:classifiers":[
        {
            "category":"Utilities",
            "subcategory":"Mobile Phone",
            "type":"Services"
        }
    ],
    "sg:phone":"+32 2 649 38 65",
    "sg:postcode":"1040",
    "sg:province":"Bruxelles-Capitale",
    "sg:tags":[
        "access",
        "gsm",
        "-",
        "apparatus"
    ],
    "wof:name":"Optovision",
    "wof:placetype":"venue"
},
  "geometry": {"coordinates":[4.3924999237,50.8287887573],"type":"Point"}
}