{
  "type": "Feature",
  "properties": {
    "addr:full":"Avenue Montesquieu 19 Seraing (jemeppe-sur-meuse) Li\u00e8ge 4101",
    "addr:housenumber":"19",
    "addr:postcode":"4101",
    "addr:street":"Avenue Montesquieu;Jemeppe-Sur-Meuse",
    "iso:country":"BE",
    "sg:address":"Avenue Montesquieu 19",
    "sg:city":"Seraing (jemeppe-sur-meuse)",
    "sg:classifiers":[
        {
            "category":"Health Services",
            "subcategory":"Doctor",
            "type":"Services"
        }
    ],
    "sg:phone":"+32 4 233 95 30",
    "sg:postcode":"4101",
    "sg:province":"Li\u00e8ge",
    "sg:tags":[
        "medicinephysicians",
        "surgeon"
    ],
    "wof:name":"Collon H",
    "wof:placetype":"venue"
},
  "geometry": {"coordinates":[5.5147981644,50.6193847656],"type":"Point"}
}