{
  "type": "Feature",
  "properties": {
    "addr:full":"Orquennois 19 Leuze-en-hainaut Hainaut 7904",
    "addr:housenumber":"19",
    "addr:postcode":"7904",
    "addr:street":"Orquennois",
    "iso:country":"BE",
    "sg:address":"Orquennois 19",
    "sg:city":"Leuze-en-hainaut",
    "sg:orig_category":"Rundveehouders",
    "sg:phone":"+32 69 66 64 04",
    "sg:postcode":"7904",
    "sg:province":"Hainaut",
    "wof:name":"Scohiez Andre Et Bernard",
    "wof:placetype":"venue"
},
  "geometry": {"coordinates":[3.5636899471,50.5867004395],"type":"Point"}
}