{
  "type": "Feature",
  "properties": {
    "iso:country":"BE",
    "sg:address":"Merelstraat 5",
    "sg:city":"Meeuwen-gruitrode",
    "sg:orig_category":"Varkenskwekers",
    "sg:phone":"+32 11 79 23 51",
    "sg:postcode":"3670",
    "sg:province":"Limburg",
    "wof:name":"Jacob Berben",
    "wof:placetype":"venue"
},
  "geometry": {"coordinates":[5.504529953,51.0745925903],"type":"Point"}
}