{
  "type": "Feature",
  "properties": {
    "addr:full":"Nijverheidskaai 210 Anderlecht/anderlecht Bruxelles-Capitale 1070",
    "addr:housenumber":"210",
    "addr:postcode":"1070",
    "addr:street":"Nijverheidskaai",
    "iso:country":"BE",
    "sg:address":"Nijverheidskaai 210",
    "sg:city":"Anderlecht/anderlecht",
    "sg:orig_category":"Artsen and specialisten",
    "sg:phone":"+32 2 522 26 61",
    "sg:postcode":"1070",
    "sg:province":"Bruxelles-Capitale",
    "wof:name":"J. Dandoy",
    "wof:placetype":"venue"
},
  "geometry": {"coordinates":[4.3204069138,50.8402137756],"type":"Point"}
}