{
  "type": "Feature",
  "properties": {
    "addr:full":"Schoebroekstraat 50 Beringen Limburg 3583",
    "addr:housenumber":"50",
    "addr:postcode":"3583",
    "addr:street":"Schoebroekstraat",
    "iso:country":"BE",
    "sg:address":"Schoebroekstraat 50",
    "sg:city":"Beringen",
    "sg:orig_category":"Krantenuitgeverijen Tijdschriftenuitgeverijen",
    "sg:phone":"+32 11 45 82 50",
    "sg:postcode":"3583",
    "sg:province":"Limburg",
    "wof:name":"Uitgeverij Greenwich",
    "wof:placetype":"venue"
},
  "geometry": {"coordinates":[5.1706700325,51.0389442444],"type":"Point"}
}