{
  "type": "Feature",
  "properties": {
    "iso:country":"BE",
    "sg:address":"Rue Remy Soetens 30",
    "sg:city":"Jette/jette",
    "sg:orig_category":"Cr\u00e8ches and garderies d'enfants",
    "sg:phone":"+32 2 479 87 70",
    "sg:postcode":"1090",
    "sg:province":"Bruxelles-Capitale",
    "wof:name":"Cr\u00c8che Superclub Des As",
    "wof:placetype":"venue"
},
  "geometry": {"coordinates":[4.3195810318,50.8862113953],"type":"Point"}
}