{
  "type": "Feature",
  "properties": {
    "iso:country":"BE",
    "sg:address":"Boulevard De La Sauveni\u00c8re 141",
    "sg:city":"Liege",
    "sg:classifiers":[
        {
            "category":"Restaurant",
            "type":"Food & Drink"
        }
    ],
    "sg:phone":"+32 4 223 43 57",
    "sg:postcode":"4000",
    "sg:province":"Li\u00e8ge",
    "wof:name":"Zagoura",
    "wof:placetype":"venue"
},
  "geometry": {"coordinates":[5.5685539246,50.6407165527],"type":"Point"}
}