{
  "type": "Feature",
  "properties": {
    "addr:full":"Quai De L'industrie 31 Ciney Namur 5590",
    "addr:housenumber":"31",
    "addr:postcode":"5590",
    "addr:street":"Quai De L'Industrie",
    "iso:country":"BE",
    "sg:address":"Quai De L'industrie 31",
    "sg:city":"Ciney",
    "sg:orig_category":"DIENSTEN VOOR TELECOMMUNICATIE Elektriciteitsproductie and -distributie Gasproductie and -distributi",
    "sg:phone":"+32 78 78 78 78",
    "sg:postcode":"5590",
    "sg:province":"Namur",
    "wof:name":"Electrabel",
    "wof:placetype":"venue"
},
  "geometry": {"coordinates":[5.0893039703,50.295463562],"type":"Point"}
}