{
  "type": "Feature",
  "properties": {
    "addr:full":"Vinkenlaan 19 Leuven Vlaams-Brabant 3001",
    "addr:housenumber":"19",
    "addr:postcode":"3001",
    "addr:street":"Vinkenlaan",
    "iso:country":"BE",
    "sg:address":"Vinkenlaan 19",
    "sg:city":"Leuven",
    "sg:orig_category":"Sportclubs",
    "sg:phone":"+32 16 23 86 61",
    "sg:postcode":"3001",
    "sg:province":"Vlaams-Brabant",
    "wof:name":"Koninkl. Leuv. Zwemclub",
    "wof:placetype":"venue"
},
  "geometry": {"coordinates":[4.7072110176,50.8659286499],"type":"Point"}
}