{
  "type": "Feature",
  "properties": {
    "addr:full":"Sint-amandplein 3 Gent Oost-Vlaanderen 9000",
    "addr:housenumber":"3",
    "addr:postcode":"9000",
    "addr:street":"Sint-Amandplein;Oost-Vlaanderen",
    "iso:country":"BE",
    "sg:address":"Sint-amandplein 3",
    "sg:city":"Gent",
    "sg:orig_category":"Location d'habitations",
    "sg:phone":"+32 9 224 21 70",
    "sg:postcode":"9000",
    "sg:province":"Oost-Vlaanderen",
    "wof:name":"Manor",
    "wof:placetype":"venue"
},
  "geometry": {"coordinates":[3.7249720097,51.0433120728],"type":"Point"}
}