{
  "type": "Feature",
  "properties": {
    "addr:full":"Avenue G\u00e9n\u00e9ral Jacques 8 Nivelles Brabant Wallon 1400",
    "addr:housenumber":"8",
    "addr:postcode":"1400",
    "addr:street":"Avenue Ge\u0301Ne\u0301Ral Jacques",
    "iso:country":"BE",
    "sg:address":"Avenue G\u00e9n\u00e9ral Jacques 8",
    "sg:city":"Nivelles",
    "sg:classifiers":[
        {
            "category":"Health Services",
            "subcategory":"Health Practitioner",
            "type":"Services"
        }
    ],
    "sg:phone":"+32 67 21 75 53",
    "sg:postcode":"1400",
    "sg:province":"Brabant Wallon",
    "sg:tags":[
        "physiotherapist"
    ],
    "wof:name":"Luyckfasseel Herman",
    "wof:placetype":"venue"
},
  "geometry": {"coordinates":[4.3287258148,50.5949745178],"type":"Point"}
}