{
  "type": "Feature",
  "properties": {
    "iso:country":"BE",
    "sg:address":"Liersesteenweg 455",
    "sg:city":"Mechelen",
    "sg:orig_category":"Brood, gebak and snoepgoed",
    "sg:phone":"+32 15 20 04 81",
    "sg:postcode":"2800",
    "sg:province":"Antwerpen",
    "wof:name":"Rita Feremans",
    "wof:placetype":"venue"
},
  "geometry": {"coordinates":[4.4800491333,51.0507850647],"type":"Point"}
}