{
  "type": "Feature",
  "properties": {
    "addr:full":"Sneppestraat 7 Kortemark West-Vlaanderen 8610",
    "addr:housenumber":"7",
    "addr:postcode":"8610",
    "addr:street":"Sneppestraat",
    "iso:country":"BE",
    "sg:address":"Sneppestraat 7",
    "sg:city":"Kortemark",
    "sg:orig_category":"Pleisterwerk",
    "sg:phone":"+32 51 57 04 17",
    "sg:postcode":"8610",
    "sg:province":"West-Vlaanderen",
    "wof:name":"Haelewyn Johnny En Zonen",
    "wof:placetype":"venue"
},
  "geometry": {"coordinates":[3.0340259075,51.0300140381],"type":"Point"}
}