{
  "type": "Feature",
  "properties": {
    "iso:country":"BE",
    "sg:address":"Centrumlaan 179",
    "sg:city":"Ninove",
    "sg:orig_category":"Souvenirs and objets artisanaux",
    "sg:phone":"+32 54 32 29 92",
    "sg:postcode":"9400",
    "sg:province":"Oost-Vlaanderen",
    "wof:name":"Heyvaert",
    "wof:placetype":"venue"
},
  "geometry": {"coordinates":[4.0149941444,50.8328933716],"type":"Point"}
}