{
  "type": "Feature",
  "properties": {
    "addr:full":"Industriepark Rostijne 25-5 Zelzate Oost-Vlaanderen 9060",
    "addr:housenumber":"25-5",
    "addr:postcode":"9060",
    "addr:street":"Industriepark Rostijne",
    "iso:country":"BE",
    "sg:address":"Industriepark Rostijne 25-5",
    "sg:city":"Zelzate",
    "sg:classifiers":[
        {
            "category":"Utilities",
            "subcategory":"Refuse",
            "type":"Services"
        }
    ],
    "sg:phone":"+32 9 342 73 75",
    "sg:postcode":"9060",
    "sg:province":"Oost-Vlaanderen",
    "sg:tags":[
        "removal"
    ],
    "wof:name":"Algemene Verhuizingen Wyttra",
    "wof:placetype":"venue"
},
  "geometry": {"coordinates":[3.828430891,51.1890182495],"type":"Point"}
}