{
  "type": "Feature",
  "properties": {
    "addr:full":"Burgemeester Capellelaan 34 Damme (sijsele) West-Vlaanderen 8340",
    "addr:housenumber":"34",
    "addr:postcode":"8340",
    "addr:street":"Burgemeester Capellelaan",
    "iso:country":"BE",
    "sg:address":"Burgemeester Capellelaan 34",
    "sg:city":"Damme (sijsele)",
    "sg:classifiers":[
        {
            "category":"Professional",
            "subcategory":"Computer Services",
            "type":"Services"
        }
    ],
    "sg:phone":"+32 50 35 82 47",
    "sg:postcode":"8340",
    "sg:province":"West-Vlaanderen",
    "sg:tags":[
        "-",
        "processing",
        "data"
    ],
    "wof:name":"Arad Bvba",
    "wof:placetype":"venue"
},
  "geometry": {"coordinates":[3.3113899231,51.2103233337],"type":"Point"}
}