{
  "type": "Feature",
  "properties": {
    "addr:full":"Arthur Meersmanstraat 10 Temse Oost-Vlaanderen 9140",
    "addr:housenumber":"10",
    "addr:postcode":"9140",
    "addr:street":"Arthur Meersmanstraat",
    "iso:country":"BE",
    "sg:address":"Arthur Meersmanstraat 10",
    "sg:city":"Temse",
    "sg:classifiers":[
        {
            "category":"Professional",
            "subcategory":"Management & Consulting",
            "type":"Services"
        }
    ],
    "sg:phone":"+32 3 710 11 07",
    "sg:postcode":"9140",
    "sg:province":"Oost-Vlaanderen",
    "sg:tags":[
        "-",
        "processing",
        "data",
        "consultant"
    ],
    "wof:name":"Twistfare Ltd.",
    "wof:placetype":"venue"
},
  "geometry": {"coordinates":[4.2292599678,51.1344909668],"type":"Point"}
}