{
  "type": "Feature",
  "properties": {
    "addr:full":"Place Des Chasseurs Ardennais 11 Bruxelles (schaerbeek) Bruxelles-Capitale 1030",
    "addr:housenumber":"11",
    "addr:postcode":"1030",
    "addr:street":"Place Des Chasseurs Ardennais",
    "iso:country":"BE",
    "sg:address":"Place Des Chasseurs Ardennais 11",
    "sg:city":"Bruxelles (schaerbeek)",
    "sg:classifiers":[
        {
            "category":"Health Services",
            "subcategory":"Doctor",
            "type":"Services"
        }
    ],
    "sg:phone":"+32 2 732 55 98",
    "sg:postcode":"1030",
    "sg:province":"Bruxelles-Capitale",
    "sg:tags":[
        "medicinephysicians",
        "surgeon"
    ],
    "wof:name":"Dutron Ph",
    "wof:placetype":"venue"
},
  "geometry": {"coordinates":[4.3906202316,50.8490638733],"type":"Point"}
}