{
  "type": "Feature",
  "properties": {
    "addr:full":"Avenue Des Casernes 20 Etterbeek/etterbeek Bruxelles-Capitale 1040",
    "addr:housenumber":"20",
    "addr:postcode":"1040",
    "addr:street":"Avenue Des Casernes",
    "iso:country":"BE",
    "sg:address":"Avenue Des Casernes 20",
    "sg:city":"Etterbeek/etterbeek",
    "sg:orig_category":"Services fun\u00e9raires",
    "sg:phone":"+32 2 647 49 29",
    "sg:postcode":"1040",
    "sg:province":"Bruxelles-Capitale",
    "wof:name":"Fun\u00c9railles Bouvin & Fils",
    "wof:placetype":"venue"
},
  "geometry": {"coordinates":[4.3906178474,50.8293914795],"type":"Point"}
}