{
  "type": "Feature",
  "properties": {
    "addr:full":"Heistraat 62 Sint-niklaas Oost-Vlaanderen 9100",
    "addr:housenumber":"62",
    "addr:postcode":"9100",
    "addr:street":"Heistraat",
    "iso:country":"BE",
    "sg:address":"Heistraat 62",
    "sg:city":"Sint-niklaas",
    "sg:classifiers":[
        {
            "category":"Communications",
            "type":"Services"
        }
    ],
    "sg:phone":"+32 3 766 24 24",
    "sg:postcode":"9100",
    "sg:province":"Oost-Vlaanderen",
    "sg:tags":[
        "translation"
    ],
    "wof:name":"Redaktie & Revisie Ls",
    "wof:placetype":"venue"
},
  "geometry": {"coordinates":[4.1278119087,51.1737060547],"type":"Point"}
}