{
  "type": "Feature",
  "properties": {
    "iso:country":"BE",
    "sg:address":"Rue Linette 44",
    "sg:city":"Neupr\u00e9 (plainevaux)",
    "sg:classifiers":[
        {
            "category":"Personal",
            "subcategory":"Nail Salon",
            "type":"Services"
        }
    ],
    "sg:phone":"+32 4 371 49 11",
    "sg:postcode":"4122",
    "sg:province":"Li\u00e8ge",
    "sg:tags":[
        "pedicure"
    ],
    "wof:name":"Van Gramberen A",
    "wof:placetype":"venue"
},
  "geometry": {"coordinates":[5.5085740089,50.5421295166],"type":"Point"}
}