{
  "type": "Feature",
  "properties": {
    "addr:full":"Kaudenaardestraat 72 Dilbeek Vlaams-Brabant 1700",
    "addr:housenumber":"72",
    "addr:postcode":"1700",
    "addr:street":"Kaudenaardestraat",
    "iso:country":"BE",
    "sg:address":"Kaudenaardestraat 72",
    "sg:city":"Dilbeek",
    "sg:classifiers":[
        {
            "category":"Insurance",
            "subcategory":"Insurance Agent",
            "type":"Services"
        }
    ],
    "sg:phone":"+32 2 569 29 07",
    "sg:postcode":"1700",
    "sg:province":"Vlaams-Brabant",
    "sg:tags":[
        "verzekeringsmakelaars",
        "expert"
    ],
    "wof:name":"Bureau Pollak G. & B.",
    "wof:placetype":"venue"
},
  "geometry": {"coordinates":[4.2744498253,50.8428535461],"type":"Point"}
}