{
  "type": "Feature",
  "properties": {
    "iso:country":"BE",
    "sg:address":"Puursesteenweg 61",
    "sg:city":"Bornem",
    "sg:orig_category":"HUISBRANDOLIE",
    "sg:phone":"+32 3 889 07 39",
    "sg:postcode":"2880",
    "sg:province":"Antwerpen",
    "wof:name":"Franciscus Van Noten",
    "wof:placetype":"venue"
},
  "geometry": {"coordinates":[4.2369651794,51.0953636169],"type":"Point"}
}