{
  "type": "Feature",
  "properties": {
    "iso:country":"BE",
    "sg:address":"Rue De La Casquette 40",
    "sg:city":"Li\u00e8ge 1",
    "sg:classifiers":[
        {
            "category":"Recreation",
            "subcategory":"Arcade",
            "type":"Entertainment"
        }
    ],
    "sg:postcode":"4000",
    "sg:province":"Li\u00e8ge",
    "sg:tags":[
        "machine",
        "amusement"
    ],
    "wof:name":"Circus London",
    "wof:placetype":"venue"
},
  "geometry": {"coordinates":[5.5672798157,50.6419563293],"type":"Point"}
}