{
  "type": "Feature",
  "properties": {
    "addr:full":"Leo Baekelandstraat 4 Gent Oost-Vlaanderen 9000",
    "addr:housenumber":"4",
    "addr:postcode":"9000",
    "addr:street":"Leo Baekelandstraat;Oost-Vlaanderen",
    "iso:country":"BE",
    "sg:address":"Leo Baekelandstraat 4",
    "sg:city":"Gent",
    "sg:classifiers":[
        {
            "category":"Real Estate",
            "subcategory":"Surveying",
            "type":"Services"
        }
    ],
    "sg:phone":"+32 9 221 29 73",
    "sg:postcode":"9000",
    "sg:province":"Oost-Vlaanderen",
    "sg:tags":[
        "surveyor",
        "land"
    ],
    "wof:name":"De Muynck A",
    "wof:placetype":"venue"
},
  "geometry": {"coordinates":[3.7062458992,51.0249176025],"type":"Point"}
}