{
  "type": "Feature",
  "properties": {
    "iso:country":"BE",
    "sg:address":"Rhoode 93",
    "sg:city":"Oud-turnhout",
    "sg:orig_category":"Afbraak- and draineerwerken",
    "sg:phone":"+32 11 45 14 56",
    "sg:postcode":"2360",
    "sg:province":"Antwerpen",
    "wof:name":"Van Der Veken",
    "wof:placetype":"venue"
},
  "geometry": {"coordinates":[5.0477190018,51.3048324585],"type":"Point"}
}