{
  "type": "Feature",
  "properties": {
    "addr:full":"Rue Saint-jacques 359 Dinant Namur 5500",
    "addr:housenumber":"359",
    "addr:postcode":"5500",
    "addr:street":"Rue Saint-Jacques",
    "iso:country":"BE",
    "sg:address":"Rue Saint-jacques 359",
    "sg:city":"Dinant",
    "sg:orig_category":"Non-Classified Establishments",
    "sg:phone":"+32 82 22 28 76",
    "sg:postcode":"5500",
    "sg:province":"Namur",
    "wof:name":"Prodecor",
    "wof:placetype":"venue"
},
  "geometry": {"coordinates":[4.9394822121,50.2661132812],"type":"Point"}
}