{
  "type": "Feature",
  "properties": {
    "addr:full":"P.p. Rubensstraat 53 Kapelle-op-den-bos Vlaams-Brabant 1880",
    "addr:housenumber":"53",
    "addr:postcode":"1880",
    "addr:street":"P.P. Rubensstraat",
    "iso:country":"BE",
    "sg:address":"P.p. Rubensstraat 53",
    "sg:city":"Kapelle-op-den-bos",
    "sg:orig_category":"Immobili\u00ebnkantoren",
    "sg:phone":"+32 15 71 03 81",
    "sg:postcode":"1880",
    "sg:province":"Vlaams-Brabant",
    "wof:name":"Immo De Wael",
    "wof:placetype":"venue"
},
  "geometry": {"coordinates":[4.364967823,51.0034408569],"type":"Point"}
}