{
  "type": "Feature",
  "properties": {
    "addr:full":"Rue De Wand 15 Bruxelles Bruxelles-Capitale 1020",
    "addr:housenumber":"15",
    "addr:postcode":"1020",
    "addr:street":"Rue De Wand",
    "iso:country":"BE",
    "sg:address":"Rue De Wand 15",
    "sg:city":"Bruxelles",
    "sg:classifiers":[
        {
            "category":"Shopping",
            "subcategory":"Crafts & Fabrics",
            "type":"Retail Goods"
        }
    ],
    "sg:phone":"+32 2 262 00 42",
    "sg:postcode":"1020",
    "sg:province":"Bruxelles-Capitale",
    "sg:tags":[
        "needlework",
        "lady"
    ],
    "wof:name":"Secret Garden",
    "wof:placetype":"venue"
},
  "geometry": {"coordinates":[4.3577427864,50.8963394165],"type":"Point"}
}