{
  "type": "Feature",
  "properties": {
    "addr:full":"Avenue Fonsny 35 Bruxelles (saint-gilles) Bruxelles-Capitale 1060",
    "addr:housenumber":"35",
    "addr:postcode":"1060",
    "addr:street":"Avenue Fonsny",
    "iso:country":"BE",
    "sg:address":"Avenue Fonsny 35",
    "sg:city":"Bruxelles (saint-gilles)",
    "sg:classifiers":[
        {
            "category":"Bars & Pubs",
            "type":"Food & Drink"
        }
    ],
    "sg:phone":"+32 2 538 03 86",
    "sg:postcode":"1060",
    "sg:province":"Bruxelles-Capitale",
    "wof:name":"I C I R",
    "wof:placetype":"venue"
},
  "geometry": {"coordinates":[4.3379678726,50.835395813],"type":"Point"}
}