{
  "type": "Feature",
  "properties": {
    "addr:full":"Brusselsesteenweg 71 Zemst Vlaams-Brabant 1980",
    "addr:housenumber":"71",
    "addr:postcode":"1980",
    "addr:street":"Brusselsesteenweg;Vlaams-Brabant",
    "iso:country":"BE",
    "sg:address":"Brusselsesteenweg 71",
    "sg:city":"Zemst",
    "sg:classifiers":[
        {
            "category":"Wholesale",
            "subcategory":"Beer",
            "type":"Manufacturing & Wholesale Goods"
        }
    ],
    "sg:phone":"+32 15 61 11 22",
    "sg:postcode":"1980",
    "sg:province":"Vlaams-Brabant",
    "sg:tags":[
        "ale",
        "-"
    ],
    "wof:name":"Becq W",
    "wof:placetype":"venue"
},
  "geometry": {"coordinates":[4.4616718292,50.9819068909],"type":"Point"}
}