{
  "type": "Feature",
  "properties": {
    "addr:full":"Rue De L'etang 83 Charleroi Hainaut 6042",
    "addr:housenumber":"83",
    "addr:postcode":"6042",
    "addr:street":"Rue De L'Etang;Hainaut",
    "iso:country":"BE",
    "sg:address":"Rue De L'etang 83",
    "sg:city":"Charleroi",
    "sg:orig_category":"Architecten",
    "sg:phone":"+32 71 30 74 24",
    "sg:postcode":"6042",
    "sg:province":"Hainaut",
    "wof:name":"Michel Bucken",
    "wof:placetype":"venue"
},
  "geometry": {"coordinates":[4.4308400154,50.4648895264],"type":"Point"}
}