{
  "type": "Feature",
  "properties": {
    "addr:full":"Rue Vieille Chaussee 1 Braine-le-comte Hainaut 7090",
    "addr:housenumber":"1",
    "addr:postcode":"7090",
    "addr:street":"Rue Vieille Chaussee",
    "iso:country":"BE",
    "sg:address":"Rue Vieille Chaussee 1",
    "sg:city":"Braine-le-comte",
    "sg:classifiers":[
        {
            "category":"Professional",
            "subcategory":"Engineering",
            "type":"Services"
        }
    ],
    "sg:phone":"+32 67 56 13 85",
    "sg:postcode":"7090",
    "sg:province":"Hainaut",
    "sg:tags":[
        "road",
        "surfacing",
        "asphalt",
        "highway"
    ],
    "wof:name":"La Route S.a.",
    "wof:placetype":"venue"
},
  "geometry": {"coordinates":[4.1360211372,50.6137046814],"type":"Point"}
}