{
  "type": "Feature",
  "properties": {
    "iso:country":"BE",
    "sg:address":"Statiestraat 31",
    "sg:city":"Zwijndrecht",
    "sg:classifiers":[
        {
            "category":"Professional",
            "subcategory":"Computer Services",
            "type":"Services"
        }
    ],
    "sg:phone":"+32 3 296 33 70",
    "sg:postcode":"2070",
    "sg:province":"Antwerpen",
    "sg:tags":[
        "network"
    ],
    "wof:name":"Info-tech",
    "wof:placetype":"venue"
},
  "geometry": {"coordinates":[4.3271369934,51.2178840637],"type":"Point"}
}