{
  "type": "Feature",
  "properties": {
    "addr:full":"Kasteeldreef 20 Lubbeek Vlaams-Brabant 3210",
    "addr:housenumber":"20",
    "addr:postcode":"3210",
    "addr:street":"Kasteeldreef",
    "iso:country":"BE",
    "sg:address":"Kasteeldreef 20",
    "sg:city":"Lubbeek",
    "sg:orig_category":"Kapsalons",
    "sg:phone":"+32 16 26 00 47",
    "sg:postcode":"3210",
    "sg:province":"Vlaams-Brabant",
    "wof:name":"Coiffure Karina",
    "wof:placetype":"venue"
},
  "geometry": {"coordinates":[4.7604398727,50.900642395],"type":"Point"}
}