{
  "type": "Feature",
  "properties": {
    "iso:country":"BE",
    "sg:address":"Blankenbergse Steenweg 31",
    "sg:city":"Brugge",
    "sg:orig_category":"Boucheries",
    "sg:phone":"+32 50 31 41 59",
    "sg:postcode":"8000",
    "sg:province":"West-Vlaanderen",
    "wof:name":"Beenhouwerij Christiaens",
    "wof:placetype":"venue"
},
  "geometry": {"coordinates":[3.2233009338,51.2075653076],"type":"Point"}
}