{
  "type": "Feature",
  "properties": {
    "addr:full":"Neerstraat 156 Ninove Oost-Vlaanderen 9400",
    "addr:housenumber":"156",
    "addr:postcode":"9400",
    "addr:street":"Neerstraat",
    "iso:country":"BE",
    "sg:address":"Neerstraat 156",
    "sg:city":"Ninove",
    "sg:classifiers":[
        {
            "category":"Arena",
            "subcategory":"Sports Club",
            "type":"Entertainment"
        }
    ],
    "sg:phone":"+32 54 33 33 96",
    "sg:postcode":"9400",
    "sg:province":"Oost-Vlaanderen",
    "sg:tags":[
        "terrain",
        "hors",
        "de",
        "installation",
        "sportifs"
    ],
    "wof:name":"K.e. Appelterre-eichem",
    "wof:placetype":"venue"
},
  "geometry": {"coordinates":[4.0232000351,50.8349113464],"type":"Point"}
}