{
  "type": "Feature",
  "properties": {
    "addr:full":"Rue De L'egalit\u00e9 28 Manage (bois-d'haine) Hainaut 7170",
    "addr:housenumber":"28",
    "addr:postcode":"7170",
    "addr:street":"Rue De L'Egalite \u0301;Hainaut",
    "iso:country":"BE",
    "sg:address":"Rue De L'egalit\u00e9 28",
    "sg:city":"Manage (bois-d'haine)",
    "sg:classifiers":[
        {
            "category":"Banks & Credit Unions",
            "subcategory":"Investment Brokerage",
            "type":"Services"
        }
    ],
    "sg:phone":"+32 64 54 14 30",
    "sg:postcode":"7170",
    "sg:province":"Hainaut",
    "sg:tags":[
        "printing",
        "-"
    ],
    "wof:name":"Hupet Printing Sprl",
    "wof:placetype":"venue"
},
  "geometry": {"coordinates":[4.2150540352,50.4932785034],"type":"Point"}
}