{
  "type": "Feature",
  "properties": {
    "iso:country":"BE",
    "sg:address":"Rue Du Feu 55a",
    "sg:city":"Bruxelles (forest)",
    "sg:classifiers":[
        {
            "category":"Professional",
            "subcategory":"Advertising",
            "type":"Services"
        }
    ],
    "sg:postcode":"1190",
    "sg:province":"Bruxelles-Capitale",
    "sg:tags":[
        "clothes"
    ],
    "wof:name":"Aats Production",
    "wof:placetype":"venue"
},
  "geometry": {"coordinates":[4.3233308792,50.8196716309],"type":"Point"}
}