{
  "type": "Feature",
  "properties": {
    "addr:full":"Rue Du Pont Neuf 1a Pont-\u00e0-celles (luttre) Hainaut 6238",
    "addr:housenumber":"1a",
    "addr:postcode":"6238",
    "addr:street":"Rue Du Pont Neuf",
    "iso:country":"BE",
    "sg:address":"Rue Du Pont Neuf 1a",
    "sg:city":"Pont-\u00e0-celles (luttre)",
    "sg:classifiers":[
        {
            "category":"Health Services",
            "subcategory":"Health Practitioner",
            "type":"Services"
        }
    ],
    "sg:phone":"+32 71 84 62 97",
    "sg:postcode":"6238",
    "sg:province":"Hainaut",
    "sg:tags":[
        "physiotherapist"
    ],
    "wof:name":"Lechien F",
    "wof:placetype":"venue"
},
  "geometry": {"coordinates":[4.3916068077,50.5051345825],"type":"Point"}
}