{
  "type": "Feature",
  "properties": {
    "iso:country":"BE",
    "sg:address":"Eupener Strasse 164",
    "sg:city":"Raeren (eynatten)",
    "sg:classifiers":[
        {
            "category":"Animal Shelter",
            "type":"Public Place"
        }
    ],
    "sg:phone":"+32 87 85 34 13",
    "sg:postcode":"4731",
    "sg:province":"Li\u00e8ge",
    "wof:name":"Berger A",
    "wof:placetype":"venue"
},
  "geometry": {"coordinates":[6.0738129616,50.6764450073],"type":"Point"}
}