{
  "type": "Feature",
  "properties": {
    "addr:full":"Lefebvrestraat 13 Nieuwpoort West-Vlaanderen 8620",
    "addr:housenumber":"13",
    "addr:postcode":"8620",
    "addr:street":"Lefebvrestraat",
    "iso:country":"BE",
    "sg:address":"Lefebvrestraat 13",
    "sg:city":"Nieuwpoort",
    "sg:classifiers":[
        {
            "category":"Personal",
            "subcategory":"Beauty Salon",
            "type":"Services"
        }
    ],
    "sg:phone":"+32 58 23 63 59",
    "sg:postcode":"8620",
    "sg:province":"West-Vlaanderen",
    "sg:tags":[
        "lady",
        "-",
        "hairdressing"
    ],
    "wof:name":"Creation V",
    "wof:placetype":"venue"
},
  "geometry": {"coordinates":[2.7162919044,51.1471786499],"type":"Point"}
}