{
  "type": "Feature",
  "properties": {
    "iso:country":"BE",
    "sg:address":"Marcel Windelsstraat 57",
    "sg:city":"Waregem",
    "sg:classifiers":[
        {
            "category":"Communications",
            "subcategory":"Television Station",
            "type":"Services"
        }
    ],
    "sg:phone":"+32 56 60 15 03",
    "sg:postcode":"8790",
    "sg:province":"West-Vlaanderen",
    "sg:tags":[
        "report",
        "video"
    ],
    "wof:name":"Van Herpe L",
    "wof:placetype":"venue"
},
  "geometry": {"coordinates":[3.4319880009,50.8915214539],"type":"Point"}
}