{
  "type": "Feature",
  "properties": {
    "addr:full":"Tier Saint-antoine 28 Durbuy (barvaux-sur-ourthe) Luxembourg 6940",
    "addr:housenumber":"28",
    "addr:postcode":"6940",
    "iso:country":"BE",
    "sg:address":"Tier Saint-antoine 28",
    "sg:city":"Durbuy (barvaux-sur-ourthe)",
    "sg:classifiers":[
        {
            "category":"Building & Trades",
            "subcategory":"Pest Control",
            "type":"Services"
        }
    ],
    "sg:phone":"+32 86 21 10 48",
    "sg:postcode":"6940",
    "sg:province":"Luxembourg",
    "sg:tags":[
        "painting",
        "contractor"
    ],
    "wof:name":"De Groote F",
    "wof:placetype":"venue"
},
  "geometry": {"coordinates":[5.4825558662,50.3507843018],"type":"Point"}
}