{
  "type": "Feature",
  "properties": {
    "addr:full":"Handelsstrasse 14 Eupen Li\u00e8ge 4700",
    "addr:housenumber":"14",
    "addr:postcode":"4700",
    "addr:street":"Handelsstrasse",
    "iso:country":"BE",
    "sg:address":"Handelsstrasse 14",
    "sg:city":"Eupen",
    "sg:classifiers":[
        {
            "category":"Retail",
            "subcategory":"Laundry & Dry Cleaning",
            "type":"Services"
        }
    ],
    "sg:phone":"+32 87 59 89 89",
    "sg:postcode":"4700",
    "sg:province":"Li\u00e8ge",
    "sg:tags":[
        "dyer",
        "cleaner"
    ],
    "wof:name":"Vita-shop Sprl",
    "wof:placetype":"venue"
},
  "geometry": {"coordinates":[6.0130028725,50.6360244751],"type":"Point"}
}