{
  "type": "Feature",
  "properties": {
    "iso:country":"BE",
    "sg:address":"Rue Tourette 59",
    "sg:city":"Charleroi",
    "sg:orig_category":"M\u00e9decins and sp\u00e9cialistes",
    "sg:phone":"+32 71 33 17 89",
    "sg:postcode":"6000",
    "sg:province":"Hainaut",
    "wof:name":"M. Deschamps",
    "wof:placetype":"venue"
},
  "geometry": {"coordinates":[4.4486298561,50.4233703613],"type":"Point"}
}