{
  "type": "Feature",
  "properties": {
    "addr:full":"Madrigaalstraat 6a Herentals Antwerpen 2200",
    "addr:housenumber":"6a",
    "addr:postcode":"2200",
    "addr:street":"Madrigaalstraat",
    "iso:country":"BE",
    "sg:address":"Madrigaalstraat 6a",
    "sg:city":"Herentals",
    "sg:orig_category":"Sportclubs",
    "sg:phone":"+32 14 22 36 49",
    "sg:postcode":"2200",
    "sg:province":"Antwerpen",
    "wof:name":"Herentals Bc Fv",
    "wof:placetype":"venue"
},
  "geometry": {"coordinates":[4.8218212128,51.1765174866],"type":"Point"}
}