{
  "type": "Feature",
  "properties": {
    "addr:full":"Sint-genovevaplein 12 Tienen Vlaams-Brabant 3300",
    "addr:housenumber":"12",
    "addr:postcode":"3300",
    "addr:street":"Sint-Genovevaplein",
    "iso:country":"BE",
    "sg:address":"Sint-genovevaplein 12",
    "sg:city":"Tienen",
    "sg:orig_category":"Brood, gebak and snoepgoed",
    "sg:phone":"+32 16 81 92 97",
    "sg:postcode":"3300",
    "sg:province":"Vlaams-Brabant",
    "wof:name":"Guido Janssens",
    "wof:placetype":"venue"
},
  "geometry": {"coordinates":[4.9884028435,50.8293380737],"type":"Point"}
}