{
  "type": "Feature",
  "properties": {
    "addr:full":"Huidevettersstraat 132 Brussel/bruxelles Bruxelles-Capitale 1000",
    "addr:housenumber":"132",
    "addr:postcode":"1000",
    "addr:street":"Huidevettersstraat;/",
    "iso:country":"BE",
    "sg:address":"Huidevettersstraat 132",
    "sg:city":"Brussel/bruxelles",
    "sg:orig_category":"Plaatsen van vloer- and muurbekleding Schilders",
    "sg:phone":"+32 2 762 64 72",
    "sg:postcode":"1000",
    "sg:province":"Bruxelles-Capitale",
    "wof:name":"Spain Color",
    "wof:placetype":"venue"
},
  "geometry": {"coordinates":[4.3445940018,50.8377113342],"type":"Point"}
}