{
  "type": "Feature",
  "properties": {
    "addr:full":"Rue Tour L'ev\u00eaque 8 Vis\u00e9 Li\u00e8ge 4600",
    "addr:housenumber":"8",
    "addr:postcode":"4600",
    "addr:street":"Rue Tour;\u0302Que",
    "iso:country":"BE",
    "sg:address":"Rue Tour L'ev\u00eaque 8",
    "sg:city":"Vis\u00e9",
    "sg:classifiers":[
        {
            "category":"Building & Trades",
            "subcategory":"Plumbing",
            "type":"Services"
        }
    ],
    "sg:phone":"+32 477 73 79 79",
    "sg:postcode":"4600",
    "sg:province":"Li\u00e8ge",
    "sg:tags":[
        "pipe",
        "drain",
        "unblocking"
    ],
    "wof:name":"Henri",
    "wof:placetype":"venue"
},
  "geometry": {"coordinates":[5.6946620941,50.7384719849],"type":"Point"}
}