{
  "type": "Feature",
  "properties": {
    "iso:country":"BE",
    "sg:address":"Rue Du Baukion 13",
    "sg:city":"Jodoigne (jodoigne-souveraine)",
    "sg:classifiers":[
        {
            "category":"Shopping",
            "subcategory":"Clothing, Apparel, & Fashions",
            "type":"Retail Goods"
        }
    ],
    "sg:phone":"+32 4 366 10 87",
    "sg:postcode":"1370",
    "sg:province":"Brabant Wallon",
    "sg:tags":[
        "-",
        "clothing",
        "child"
    ],
    "wof:name":"Buissonni\u00e8re",
    "wof:placetype":"venue"
},
  "geometry": {"coordinates":[4.8390369415,50.6993789673],"type":"Point"}
}