{
  "type": "Feature",
  "properties": {
    "addr:full":"Place Elie Delferri\u00e8re 24 Charleroi Hainaut 6000",
    "addr:housenumber":"24",
    "addr:postcode":"6000",
    "addr:street":"Place Elie Delferrie\u0300Re;Hainaut",
    "iso:country":"BE",
    "sg:address":"Place Elie Delferri\u00e8re 24",
    "sg:city":"Charleroi",
    "sg:classifiers":[
        {
            "category":"Health Services",
            "subcategory":"Health Practitioner",
            "type":"Services"
        }
    ],
    "sg:phone":"+32 71 41 28 14",
    "sg:postcode":"6000",
    "sg:province":"Hainaut",
    "sg:tags":[
        "physiotherapist"
    ],
    "wof:name":"Azzetti D",
    "wof:placetype":"venue"
},
  "geometry": {"coordinates":[4.4527812004,50.4215660095],"type":"Point"}
}