{
  "type": "Feature",
  "properties": {
    "addr:full":"August De Boeckstraat 5 Sint-niklaas Oost-Vlaanderen 9100",
    "addr:housenumber":"5",
    "addr:postcode":"9100",
    "addr:street":"August De Boeckstraat",
    "iso:country":"BE",
    "sg:address":"August De Boeckstraat 5",
    "sg:city":"Sint-niklaas",
    "sg:orig_category":"Quincailleries. Bois Gr. Location de machines-outils and de mat\u00e9riel de bricolage",
    "sg:phone":"+32 3 766 27 77",
    "sg:postcode":"9100",
    "sg:province":"Oost-Vlaanderen",
    "wof:name":"Gamma",
    "wof:placetype":"venue"
},
  "geometry": {"coordinates":[4.1545758247,51.1571388245],"type":"Point"}
}