{
  "type": "Feature",
  "properties": {
    "addr:full":"Avenue G\u00e9n\u00e9ral Lartigue 27 Bruxelles (woluwe-saint-lambert) Bruxelles-Capitale 1200",
    "addr:housenumber":"27",
    "addr:postcode":"1200",
    "addr:street":"Avenue Ge\u0301Ne\u0301Ral Lartigue",
    "iso:country":"BE",
    "sg:address":"Avenue G\u00e9n\u00e9ral Lartigue 27",
    "sg:city":"Bruxelles (woluwe-saint-lambert)",
    "sg:classifiers":[
        {
            "category":"Health Services",
            "subcategory":"Health Practitioner",
            "type":"Services"
        }
    ],
    "sg:phone":"+32 2 733 24 34",
    "sg:postcode":"1200",
    "sg:province":"Bruxelles-Capitale",
    "sg:tags":[
        "physiotherapist"
    ],
    "wof:name":"Dumoulin Jean-pierre",
    "wof:placetype":"venue"
},
  "geometry": {"coordinates":[4.4103779793,50.8466110229],"type":"Point"}
}