{
  "type": "Feature",
  "properties": {
    "iso:country":"BE",
    "sg:address":"Toekomstlaan 33",
    "sg:city":"Herentals",
    "sg:orig_category":"Autoverhuur Koerierbedrijven Opslagvoorzieningen Verhuisdiensten Verhuur voertuigen behalve auto's",
    "sg:phone":"+32 14 23 21 20",
    "sg:postcode":"2200",
    "sg:province":"Antwerpen",
    "wof:name":"Dockx/horizon",
    "wof:placetype":"venue"
},
  "geometry": {"coordinates":[4.797973156,51.1644172668],"type":"Point"}
}