{
  "type": "Feature",
  "properties": {
    "addr:full":"Zwarbergw 14 Opglabbeek Limburg 3660",
    "addr:housenumber":"14",
    "addr:postcode":"3660",
    "addr:street":"Zwarbergw",
    "iso:country":"BE",
    "sg:address":"Zwarbergw 14",
    "sg:city":"Opglabbeek",
    "sg:classifiers":[
        {
            "category":"Banks & Credit Unions",
            "subcategory":"Bank",
            "type":"Services"
        }
    ],
    "sg:phone":"+32 11 85 72 29",
    "sg:postcode":"3660",
    "sg:province":"Limburg",
    "wof:name":"Gemeentekrediet",
    "wof:placetype":"venue"
},
  "geometry": {"coordinates":[5.581744194,51.0421638489],"type":"Point"}
}