{
  "type": "Feature",
  "properties": {
    "addr:full":"Rue Du Bourrelier 30b Jurbise Hainaut 7050",
    "addr:housenumber":"30b",
    "addr:postcode":"7050",
    "addr:street":"Rue Du Bourrelier",
    "iso:country":"BE",
    "sg:address":"Rue Du Bourrelier 30b",
    "sg:city":"Jurbise",
    "sg:orig_category":"Plomberie, chauffage and installations sanitaires",
    "sg:phone":"+32 65 22 75 11",
    "sg:postcode":"7050",
    "sg:province":"Hainaut",
    "wof:name":"Guy Michez",
    "wof:placetype":"venue"
},
  "geometry": {"coordinates":[3.9219830036,50.5344276428],"type":"Point"}
}