{
  "type": "Feature",
  "properties": {
    "addr:full":"Rue Saint-jacques 15 Tournai Hainaut 7500",
    "addr:housenumber":"15",
    "addr:postcode":"7500",
    "addr:street":"Rue Saint-Jacques",
    "iso:country":"BE",
    "sg:address":"Rue Saint-jacques 15",
    "sg:city":"Tournai",
    "sg:classifiers":[
        {
            "category":"Cafe",
            "type":"Food & Drink"
        }
    ],
    "sg:phone":"+32 69 21 10 79",
    "sg:postcode":"7500",
    "sg:province":"Hainaut",
    "sg:tags":[
        "caf\u00e9s"
    ],
    "wof:name":"Le Relais Du Miroir",
    "wof:placetype":"venue"
},
  "geometry": {"coordinates":[3.3839559555,50.6092338562],"type":"Point"}
}