{
  "type": "Feature",
  "properties": {
    "addr:full":"Chauss\u00c9e De Jolimont 298 La Louviere Hainaut 7100",
    "addr:housenumber":"298",
    "addr:postcode":"7100",
    "addr:street":"Chausse\u0301E De Jolimont",
    "iso:country":"BE",
    "sg:address":"Chauss\u00c9e De Jolimont 298",
    "sg:city":"La Louviere",
    "sg:orig_category":"Plaatsen van vloer- and muurbekleding",
    "sg:phone":"+32 64 26 49 72",
    "sg:postcode":"7100",
    "sg:province":"Hainaut",
    "wof:name":"Ets. Paci Liborio",
    "wof:placetype":"venue"
},
  "geometry": {"coordinates":[4.2121348381,50.4698028564],"type":"Point"}
}