{
  "type": "Feature",
  "properties": {
    "addr:full":"Brusselsestraat 18 Leuven Vlaams-Brabant 3000",
    "addr:housenumber":"18",
    "addr:postcode":"3000",
    "addr:street":"Brusselsestraat",
    "iso:country":"BE",
    "sg:address":"Brusselsestraat 18",
    "sg:city":"Leuven",
    "sg:classifiers":[
        {
            "category":"Food & Beverages",
            "subcategory":"Chocolate",
            "type":"Retail Goods"
        }
    ],
    "sg:phone":"+32 16 22 35 67",
    "sg:postcode":"3000",
    "sg:province":"Vlaams-Brabant",
    "sg:tags":[
        "confectionery",
        "-"
    ],
    "wof:name":"Leonidas-'t Jokolateke",
    "wof:placetype":"venue"
},
  "geometry": {"coordinates":[4.6994919777,50.8796195984],"type":"Point"}
}