{
  "type": "Feature",
  "properties": {
    "iso:country":"BE",
    "sg:address":"Rue Du Crucifix 29",
    "sg:city":"Herstal",
    "sg:orig_category":"Paramedische behandelingen",
    "sg:phone":"+32 4 248 36 43",
    "sg:postcode":"4040",
    "sg:province":"Li\u00e8ge",
    "wof:name":"Sturbois",
    "wof:placetype":"venue"
},
  "geometry": {"coordinates":[5.6395120621,50.6746406555],"type":"Point"}
}