{
  "type": "Feature",
  "properties": {
    "addr:full":"Pottenbrug 3b212 Antwerpen Antwerpen 2000",
    "addr:housenumber":"3b212",
    "addr:postcode":"2000",
    "addr:street":"Pottenbrug",
    "iso:country":"BE",
    "sg:address":"Pottenbrug 3b212",
    "sg:city":"Antwerpen",
    "sg:orig_category":"D\u00e9corateurs d'int\u00e9rieur",
    "sg:phone":"+32 3 290 72 01",
    "sg:postcode":"2000",
    "sg:province":"Antwerpen",
    "wof:name":"Yvo Orso Designs",
    "wof:placetype":"venue"
},
  "geometry": {"coordinates":[4.4038500786,51.2225074768],"type":"Point"}
}