{
  "type": "Feature",
  "properties": {
    "iso:country":"BE",
    "sg:address":"Rue De St. Ghislain 30",
    "sg:city":"Ottignies-louvain-la-neuve",
    "sg:orig_category":"Dansscholen",
    "sg:phone":"+32 475 64 03 92",
    "sg:postcode":"1348",
    "sg:province":"Brabant Wallon",
    "wof:name":"Studio Bala\u00cfrina",
    "wof:placetype":"venue"
},
  "geometry": {"coordinates":[4.6117129326,50.6744918823],"type":"Point"}
}