{
  "type": "Feature",
  "properties": {
    "iso:country":"BE",
    "sg:address":"Rue De La Libert\u00c9 22",
    "sg:city":"Frameries",
    "sg:orig_category":"M\u00e9decines alternatives",
    "sg:phone":"+32 65 66 81 32",
    "sg:postcode":"7080",
    "sg:province":"Hainaut",
    "wof:name":"Sylvie Carriero",
    "wof:placetype":"venue"
},
  "geometry": {"coordinates":[3.9034569263,50.4090309143],"type":"Point"}
}