{
  "type": "Feature",
  "properties": {
    "addr:full":"Koninginnelaan 46 Box 15 Oostende West-Vlaanderen 8400",
    "addr:housenumber":"46 box 15",
    "addr:postcode":"8400",
    "addr:street":"Koninginnelaan",
    "iso:country":"BE",
    "sg:address":"Koninginnelaan 46 Box 15",
    "sg:city":"Oostende",
    "sg:classifiers":[
        {
            "category":"Real Estate",
            "subcategory":"Real Estate Services",
            "type":"Services"
        }
    ],
    "sg:phone":"+32 59 43 30 90",
    "sg:postcode":"8400",
    "sg:province":"West-Vlaanderen",
    "wof:name":"Royal S",
    "wof:placetype":"venue"
},
  "geometry": {"coordinates":[2.9079089165,51.2251014709],"type":"Point"}
}