{
  "type": "Feature",
  "properties": {
    "iso:country":"BE",
    "sg:address":"Rue Wayez 133",
    "sg:city":"Anderlecht/anderlecht",
    "sg:orig_category":"Blanchisseries and teintureries",
    "sg:phone":"+32 2 522 14 22",
    "sg:postcode":"1070",
    "sg:province":"Bruxelles-Capitale",
    "wof:name":"Nettoyage \u00c0 Sec Clean",
    "wof:placetype":"venue"
},
  "geometry": {"coordinates":[4.3102378845,50.8355674744],"type":"Point"}
}