{
  "type": "Feature",
  "properties": {
    "addr:full":"Grufflingen 25 Burg-reuland/burg-reuland Li\u00e8ge 4791",
    "addr:housenumber":"25",
    "addr:postcode":"4791",
    "addr:street":"Grufflingen",
    "iso:country":"BE",
    "sg:address":"Grufflingen 25",
    "sg:city":"Burg-reuland/burg-reuland",
    "sg:orig_category":"Rundveehouders",
    "sg:phone":"+32 80 32 96 06",
    "sg:postcode":"4791",
    "sg:province":"Li\u00e8ge",
    "wof:name":"Bernhard Arens",
    "wof:placetype":"venue"
},
  "geometry": {"coordinates":[6.0771751404,50.2173156738],"type":"Point"}
}