{
  "type": "Feature",
  "properties": {
    "addr:full":"Chauss\u00e9e D'herseaux 6 Estaimpuis Hainaut 7730",
    "addr:housenumber":"6",
    "addr:postcode":"7730",
    "addr:street":"Chausse\u0301E D'Herseaux;Hainaut",
    "iso:country":"BE",
    "sg:address":"Chauss\u00e9e D'herseaux 6",
    "sg:city":"Estaimpuis",
    "sg:classifiers":[
        {
            "category":"Home & Garden",
            "subcategory":"Building Materials",
            "type":"Retail Goods"
        }
    ],
    "sg:phone":"+32 56 48 48 67",
    "sg:postcode":"7730",
    "sg:province":"Hainaut",
    "sg:tags":[
        "synthetic",
        "fibre",
        "weaving",
        "-",
        "spinning",
        "mill"
    ],
    "wof:name":"V.l.t.",
    "wof:placetype":"venue"
},
  "geometry": {"coordinates":[3.2675828934,50.7165908813],"type":"Point"}
}