{
  "type": "Feature",
  "properties": {
    "iso:country":"BE",
    "sg:address":"Rue Lincoln 37",
    "sg:city":"Bruxelles (uccle)",
    "sg:classifiers":[
        {
            "category":"Real Estate",
            "subcategory":"Surveying",
            "type":"Services"
        }
    ],
    "sg:phone":"+32 2 347 33 62",
    "sg:postcode":"1180",
    "sg:province":"Bruxelles-Capitale",
    "sg:tags":[
        "surveyor",
        "land"
    ],
    "wof:name":"Deffense P",
    "wof:placetype":"venue"
},
  "geometry": {"coordinates":[4.3631339073,50.8148612976],"type":"Point"}
}