{
  "type": "Feature",
  "properties": {
    "iso:country":"BE",
    "sg:address":"Paanderstraat 161",
    "sg:city":"Deerlijk",
    "sg:orig_category":"Transports routiers de marchandises",
    "sg:phone":"+32 56 71 20 90",
    "sg:postcode":"8540",
    "sg:province":"West-Vlaanderen",
    "wof:name":"Transport Duchi",
    "wof:placetype":"venue"
},
  "geometry": {"coordinates":[3.3583900928,50.8608970642],"type":"Point"}
}