{
  "type": "Feature",
  "properties": {
    "iso:country":"BE",
    "sg:address":"Hubert Tobbackstraat 29",
    "sg:city":"Kampenhout",
    "sg:classifiers":[
        {
            "category":"Food & Beverages",
            "subcategory":"Liquor & Beverages",
            "type":"Retail Goods"
        }
    ],
    "sg:phone":"+32 16 65 58 80",
    "sg:postcode":"1910",
    "sg:province":"Vlaams-Brabant",
    "sg:tags":[
        "-",
        "spirit",
        "wine"
    ],
    "wof:name":"Van Craenenbroeck Bvba",
    "wof:placetype":"venue"
},
  "geometry": {"coordinates":[4.5792508125,50.9529418945],"type":"Point"}
}