{
  "type": "Feature",
  "properties": {
    "iso:country":"BE",
    "sg:address":"Leopold Wienerlaan 85",
    "sg:city":"Watermaal-bosvoorde/watermael-boitsfort",
    "sg:orig_category":"Artsen and specialisten",
    "sg:phone":"+32 2 662 27 67",
    "sg:postcode":"1170",
    "sg:province":"Bruxelles-Capitale",
    "wof:name":"Martine Duvivier",
    "wof:placetype":"venue"
},
  "geometry": {"coordinates":[4.4077091217,50.8064117432],"type":"Point"}
}