{
  "type": "Feature",
  "properties": {
    "iso:country":"BE",
    "sg:address":"Sint-jozefstraat 53",
    "sg:city":"Londerzeel",
    "sg:classifiers":[
        {
            "category":"Home & Garden",
            "subcategory":"Carpets & Floor Coverings",
            "type":"Retail Goods"
        }
    ],
    "sg:phone":"+32 52 30 99 71",
    "sg:postcode":"1840",
    "sg:province":"Vlaams-Brabant",
    "sg:tags":[
        "tile"
    ],
    "wof:name":"Carleer J",
    "wof:placetype":"venue"
},
  "geometry": {"coordinates":[4.296394825,51.028881073],"type":"Point"}
}