{
  "type": "Feature",
  "properties": {
    "addr:full":"Heiligstraat 17 Hemiksem Antwerpen 2620",
    "addr:housenumber":"17",
    "addr:postcode":"2620",
    "addr:street":"Heiligstraat",
    "iso:country":"BE",
    "sg:address":"Heiligstraat 17",
    "sg:city":"Hemiksem",
    "sg:orig_category":"Kapsalons",
    "sg:phone":"+32 3 887 38 15",
    "sg:postcode":"2620",
    "sg:province":"Antwerpen",
    "wof:name":"Coiffure Mogi",
    "wof:placetype":"venue"
},
  "geometry": {"coordinates":[4.347140789,51.1449127197],"type":"Point"}
}