{
  "type": "Feature",
  "properties": {
    "iso:country":"BE",
    "sg:address":"Rue De La Comtesse 2",
    "sg:city":"Aubange (halanzy)",
    "sg:classifiers":[
        {
            "category":"Retail",
            "subcategory":"Event Space",
            "type":"Services"
        }
    ],
    "sg:phone":"+32 63 38 83 71",
    "sg:postcode":"6792",
    "sg:province":"Luxembourg",
    "sg:tags":[
        "rental",
        "-",
        "hall"
    ],
    "wof:name":"Cafe De La Place",
    "wof:placetype":"venue"
},
  "geometry": {"coordinates":[5.7616510391,49.581111908],"type":"Point"}
}