{
  "type": "Feature",
  "properties": {
    "addr:full":"Avenue Roi Albert 281 Andenne Namur 5300",
    "addr:housenumber":"281",
    "addr:postcode":"5300",
    "addr:street":"Avenue Roi Albert",
    "iso:country":"BE",
    "sg:address":"Avenue Roi Albert 281",
    "sg:city":"Andenne",
    "sg:orig_category":"R\u00e9parations de chaussures and articles en cuir",
    "sg:phone":"+32 85 84 12 71",
    "sg:postcode":"5300",
    "sg:province":"Namur",
    "wof:name":"Yvan Lambert",
    "wof:placetype":"venue"
},
  "geometry": {"coordinates":[5.1137671471,50.4954452515],"type":"Point"}
}