{
  "type": "Feature",
  "properties": {
    "addr:full":"Route De Philippeville 307 Charleroi Hainaut 6010",
    "addr:housenumber":"307",
    "addr:postcode":"6010",
    "addr:street":"Route De Philippeville;Hainaut",
    "iso:country":"BE",
    "sg:address":"Route De Philippeville 307",
    "sg:city":"Charleroi",
    "sg:orig_category":"Articles de jardin",
    "sg:phone":"+32 71 47 02 14",
    "sg:postcode":"6010",
    "sg:province":"Hainaut",
    "wof:name":"Alexandre",
    "wof:placetype":"venue"
},
  "geometry": {"coordinates":[4.4642820358,50.3842544556],"type":"Point"}
}