{
  "type": "Feature",
  "properties": {
    "addr:full":"Rue Du Lavis 9 Paliseul Luxembourg 6856",
    "addr:housenumber":"9",
    "addr:postcode":"6856",
    "addr:street":"Rue Du Lavis",
    "iso:country":"BE",
    "sg:address":"Rue Du Lavis 9",
    "sg:city":"Paliseul",
    "sg:classifiers":[
        {
            "category":"Arena",
            "subcategory":"Sports Club",
            "type":"Entertainment"
        }
    ],
    "sg:phone":"+32 61 53 50 59",
    "sg:postcode":"6856",
    "sg:province":"Luxembourg",
    "sg:tags":[
        "terrain",
        "hors",
        "de",
        "installation",
        "sportifs"
    ],
    "wof:name":"Etoile Sportive Cheminots",
    "wof:placetype":"venue"
},
  "geometry": {"coordinates":[5.1584978104,49.8663215637],"type":"Point"}
}