{
  "type": "Feature",
  "properties": {
    "addr:full":"Rue D'angleterre 56 Vresse-sur-semois (orchimont) Namur 5550",
    "addr:housenumber":"56",
    "addr:postcode":"5550",
    "addr:street":"Rue D'Angleterre",
    "iso:country":"BE",
    "sg:address":"Rue D'angleterre 56",
    "sg:city":"Vresse-sur-semois (orchimont)",
    "sg:classifiers":[
        {
            "category":"Landmark",
            "subcategory":"Tourist Attraction",
            "type":"Public Place"
        }
    ],
    "sg:phone":"+32 61 50 07 08",
    "sg:postcode":"5550",
    "sg:province":"Namur",
    "sg:tags":[
        "-",
        "tourism",
        "interest",
        "sight"
    ],
    "wof:name":"Bison Ranch Orchimont",
    "wof:placetype":"venue"
},
  "geometry": {"coordinates":[4.930603981,49.8955726624],"type":"Point"}
}