{
  "type": "Feature",
  "properties": {
    "addr:full":"Sportlaan 30 Dilsen-stokkem (dilsen) Limburg 3650",
    "addr:housenumber":"30",
    "addr:postcode":"3650",
    "addr:street":"Sportlaan",
    "iso:country":"BE",
    "sg:address":"Sportlaan 30",
    "sg:city":"Dilsen-stokkem (dilsen)",
    "sg:classifiers":[
        {
            "category":"Shopping",
            "subcategory":"Jewelry",
            "type":"Retail Goods"
        }
    ],
    "sg:phone":"+32 89 79 29 57",
    "sg:postcode":"3650",
    "sg:province":"Limburg",
    "sg:tags":[
        "jeweller",
        "-"
    ],
    "wof:name":"Christiane",
    "wof:placetype":"venue"
},
  "geometry": {"coordinates":[5.7096347809,51.0355758667],"type":"Point"}
}