{
  "type": "Feature",
  "properties": {
    "iso:country":"BE",
    "sg:address":"Wipstraat 2",
    "sg:city":"Niel",
    "sg:classifiers":[
        {
            "category":"Home & Garden",
            "subcategory":"Household Appliances",
            "type":"Retail Goods"
        }
    ],
    "sg:phone":"+32 3 888 00 20",
    "sg:postcode":"2845",
    "sg:province":"Antwerpen",
    "sg:tags":[
        "repair",
        "stove",
        "-"
    ],
    "wof:name":"Van Den Berge Louis",
    "wof:placetype":"venue"
},
  "geometry": {"coordinates":[4.3338599205,51.1124687195],"type":"Point"}
}