{
  "type": "Feature",
  "properties": {
    "addr:full":"Steenstraat 124 Lede Oost-Vlaanderen 9340",
    "addr:housenumber":"124",
    "addr:postcode":"9340",
    "addr:street":"Steenstraat",
    "iso:country":"BE",
    "sg:address":"Steenstraat 124",
    "sg:city":"Lede",
    "sg:classifiers":[
        {
            "category":"Manufacturing",
            "subcategory":"Building Materials",
            "type":"Manufacturing & Wholesale Goods"
        }
    ],
    "sg:phone":"+32 53 77 34 33",
    "sg:postcode":"9340",
    "sg:province":"Oost-Vlaanderen",
    "sg:tags":[
        "boiler",
        "manufacturer"
    ],
    "wof:name":"De Groodt Frank",
    "wof:placetype":"venue"
},
  "geometry": {"coordinates":[4.0075950623,50.9624786377],"type":"Point"}
}