{
  "type": "Feature",
  "properties": {
    "addr:full":"Rue Du Chatelet 9 Malmedy Li\u00e8ge 4960",
    "addr:housenumber":"9",
    "addr:postcode":"4960",
    "addr:street":"Rue Du Chatelet",
    "iso:country":"BE",
    "sg:address":"Rue Du Chatelet 9",
    "sg:city":"Malmedy",
    "sg:orig_category":"S\u00e9lection de personnel and placement",
    "sg:phone":"+32 80 79 96 68",
    "sg:postcode":"4960",
    "sg:province":"Li\u00e8ge",
    "wof:name":"Ale Malmedy",
    "wof:placetype":"venue"
},
  "geometry": {"coordinates":[6.0273299217,50.4267883301],"type":"Point"}
}