{
  "type": "Feature",
  "properties": {
    "iso:country":"BE",
    "sg:address":"J.f. Kennedystraat 1",
    "sg:city":"As",
    "sg:classifiers":[
        {
            "category":"Personal",
            "subcategory":"Beauty Salon",
            "type":"Services"
        }
    ],
    "sg:phone":"+32 89 65 73 60",
    "sg:postcode":"3665",
    "sg:province":"Limburg",
    "sg:tags":[
        "lady",
        "-",
        "hairdressing"
    ],
    "wof:name":"Elly",
    "wof:placetype":"venue"
},
  "geometry": {"coordinates":[5.578810215,51.000831604],"type":"Point"}
}