{
  "type": "Feature",
  "properties": {
    "addr:full":"Chemin De Saint-druon 2 Antoing Hainaut 7640",
    "addr:housenumber":"2",
    "addr:postcode":"7640",
    "addr:street":"Chemin De Saint-Druon",
    "iso:country":"BE",
    "sg:address":"Chemin De Saint-druon 2",
    "sg:city":"Antoing",
    "sg:orig_category":"Brandweer and civiele bescherming",
    "sg:phone":"+32 69 44 12 03",
    "sg:postcode":"7640",
    "sg:province":"Hainaut",
    "wof:name":"Corps De Pompiers",
    "wof:placetype":"venue"
},
  "geometry": {"coordinates":[3.454116106,50.5631446838],"type":"Point"}
}