{
  "type": "Feature",
  "properties": {
    "addr:full":"Veldweg 7 Zottegem (leeuwergem) Oost-Vlaanderen 9620",
    "addr:housenumber":"7",
    "addr:postcode":"9620",
    "addr:street":"Veldweg",
    "iso:country":"BE",
    "sg:address":"Veldweg 7",
    "sg:city":"Zottegem (leeuwergem)",
    "sg:classifiers":[
        {
            "category":"Transit Center",
            "subcategory":"Freight",
            "type":"Transportation"
        }
    ],
    "sg:phone":"+32 9 360 80 92",
    "sg:postcode":"9620",
    "sg:province":"Oost-Vlaanderen",
    "sg:tags":[
        "import",
        "export",
        "-"
    ],
    "wof:name":"Gefos",
    "wof:placetype":"venue"
},
  "geometry": {"coordinates":[3.8345439434,50.8870010376],"type":"Point"}
}