{
  "type": "Feature",
  "properties": {
    "iso:country":"BE",
    "sg:address":"Beekstraat 60",
    "sg:city":"Deinze",
    "sg:orig_category":"Ordinateurs and \u00e9quipement informatique",
    "sg:phone":"+32 9 380 07 78",
    "sg:postcode":"9800",
    "sg:province":"Oost-Vlaanderen",
    "wof:name":"Softrain",
    "wof:placetype":"venue"
},
  "geometry": {"coordinates":[3.5810830593,50.9822273254],"type":"Point"}
}