{
  "type": "Feature",
  "properties": {
    "iso:country":"BE",
    "sg:address":"Fonteinebeekdreef 6",
    "sg:city":"Jabbeke",
    "sg:orig_category":"Artistes ind\u00e9pendants",
    "sg:phone":"+32 50 38 60 07",
    "sg:postcode":"8490",
    "sg:province":"West-Vlaanderen",
    "wof:name":"Frans Corneillie",
    "wof:placetype":"venue"
},
  "geometry": {"coordinates":[3.1300840378,51.185092926],"type":"Point"}
}