{
  "type": "Feature",
  "properties": {
    "addr:full":"Maastrichterstraat 63 Hasselt Limburg 3500",
    "addr:housenumber":"63",
    "addr:postcode":"3500",
    "addr:street":"Maastrichterstraat",
    "iso:country":"BE",
    "sg:address":"Maastrichterstraat 63",
    "sg:city":"Hasselt",
    "sg:classifiers":[
        {
            "category":"Retail",
            "subcategory":"Event Space",
            "type":"Services"
        }
    ],
    "sg:phone":"+32 11 21 52 18",
    "sg:postcode":"3500",
    "sg:province":"Limburg",
    "sg:tags":[
        "rental",
        "-",
        "hall"
    ],
    "wof:name":"Huis De Carswaren",
    "wof:placetype":"venue"
},
  "geometry": {"coordinates":[5.3406457901,50.929523468],"type":"Point"}
}