{
  "type": "Feature",
  "properties": {
    "iso:country":"BE",
    "sg:address":"Jan Van Rijswijcklaan 228",
    "sg:city":"Antwerpen",
    "sg:orig_category":"Belastingconsulenten Diverse juridische dienstverlening",
    "sg:phone":"+32 3 244 11 80",
    "sg:postcode":"2020",
    "sg:province":"Antwerpen",
    "wof:name":"Lvc Consult",
    "wof:placetype":"venue"
},
  "geometry": {"coordinates":[4.3931159973,51.1875801086],"type":"Point"}
}