{
  "type": "Feature",
  "properties": {
    "iso:country":"BE",
    "sg:address":"Rue Baudouaine 226",
    "sg:city":"Chimay",
    "sg:orig_category":"Rundveehouders",
    "sg:phone":"+32 60 21 35 24",
    "sg:postcode":"6464",
    "sg:province":"Hainaut",
    "wof:name":"Josee Louette",
    "wof:placetype":"venue"
},
  "geometry": {"coordinates":[4.3132791519,50.0159263611],"type":"Point"}
}