{
  "type": "Feature",
  "properties": {
    "iso:country":"BE",
    "sg:address":"Muurstraat 10",
    "sg:city":"Wortegem-petegem (petegem-aan-de-schelde)",
    "sg:classifiers":[
        {
            "category":"Professional",
            "subcategory":"Management & Consulting",
            "type":"Services"
        }
    ],
    "sg:phone":"+32 55 30 20 31",
    "sg:postcode":"9790",
    "sg:province":"Oost-Vlaanderen",
    "sg:tags":[
        "consultant"
    ],
    "wof:name":"Galun Nv",
    "wof:placetype":"venue"
},
  "geometry": {"coordinates":[3.5625801086,50.8264503479],"type":"Point"}
}