{
  "type": "Feature",
  "properties": {
    "iso:country":"BE",
    "sg:address":"Beverenstraat 14",
    "sg:city":"Alveringem (leisele)",
    "sg:classifiers":[
        {
            "category":"Health Services",
            "subcategory":"Dentist",
            "type":"Services"
        }
    ],
    "sg:phone":"+32 58 29 91 96",
    "sg:postcode":"8691",
    "sg:province":"West-Vlaanderen",
    "wof:name":"Averbeke Katrien",
    "wof:placetype":"venue"
},
  "geometry": {"coordinates":[2.6238811016,50.9838180542],"type":"Point"}
}