{
  "type": "Feature",
  "properties": {
    "addr:full":"Rue Porte De Lorette 15 Vis\u00c9 Li\u00e8ge 4600",
    "addr:housenumber":"15",
    "addr:postcode":"4600",
    "addr:street":"Rue Porte De Lorette",
    "iso:country":"BE",
    "sg:address":"Rue Porte De Lorette 15",
    "sg:city":"Vis\u00c9",
    "sg:classifiers":[
        {
            "category":"Cafe",
            "type":"Food & Drink"
        }
    ],
    "sg:phone":"+32 4 379 33 51",
    "sg:postcode":"4600",
    "sg:province":"Li\u00e8ge",
    "sg:tags":[
        "caf\u00e9s"
    ],
    "wof:name":"Caf\u00c9taria Lorette",
    "wof:placetype":"venue"
},
  "geometry": {"coordinates":[5.69815588,50.7327575684],"type":"Point"}
}