{
  "type": "Feature",
  "properties": {
    "iso:country":"BE",
    "sg:address":"Sur La Carri\u00e8re 23",
    "sg:city":"Vis\u00e9 (richelle)",
    "sg:classifiers":[
        {
            "category":"Professional",
            "subcategory":"Lawyer & Legal Services",
            "type":"Services"
        }
    ],
    "sg:phone":"+32 4 379 53 29",
    "sg:postcode":"4600",
    "sg:province":"Li\u00e8ge",
    "wof:name":"Marion Ph",
    "wof:placetype":"venue"
},
  "geometry": {"coordinates":[5.6937842369,50.7170829773],"type":"Point"}
}