{
  "type": "Feature",
  "properties": {
    "addr:full":"Hoveniersstraat 31 Gent Oost-Vlaanderen 9050",
    "addr:housenumber":"31",
    "addr:postcode":"9050",
    "addr:street":"Hoveniersstraat;Oost-Vlaanderen",
    "iso:country":"BE",
    "sg:address":"Hoveniersstraat 31",
    "sg:city":"Gent",
    "sg:orig_category":"Decoratieve kunst and kunstbenodigdheden Foto-uitrusting",
    "sg:phone":"+32 9 231 01 22",
    "sg:postcode":"9050",
    "sg:province":"Oost-Vlaanderen",
    "wof:name":"Fa. Focilux",
    "wof:placetype":"venue"
},
  "geometry": {"coordinates":[3.7274909019,51.0440979004],"type":"Point"}
}