{
  "type": "Feature",
  "properties": {
    "iso:country":"BE",
    "sg:address":"Triepstraat 6",
    "sg:city":"Lierde (hemelveerdegem)",
    "sg:classifiers":[
        {
            "category":"Bars & Pubs",
            "type":"Food & Drink"
        }
    ],
    "sg:phone":"+32 54 42 29 52",
    "sg:postcode":"9571",
    "sg:province":"Oost-Vlaanderen",
    "wof:name":"Het Karrewiel",
    "wof:placetype":"venue"
},
  "geometry": {"coordinates":[3.8575649261,50.8069763184],"type":"Point"}
}