{
  "type": "Feature",
  "properties": {
    "addr:full":"Oude Mechelse Baan 117 Aarschot Vlaams-Brabant 3200",
    "addr:housenumber":"117",
    "addr:postcode":"3200",
    "addr:street":"Oude Mechelse Baan",
    "iso:country":"BE",
    "sg:address":"Oude Mechelse Baan 117",
    "sg:city":"Aarschot",
    "sg:classifiers":[
        {
            "category":"Professional",
            "subcategory":"Printing & Photocopies",
            "type":"Services"
        }
    ],
    "sg:phone":"+32 16 57 09 60",
    "sg:postcode":"3200",
    "sg:province":"Vlaams-Brabant",
    "sg:tags":[
        "machine",
        "equipment"
    ],
    "wof:name":"Gms-bvba",
    "wof:placetype":"venue"
},
  "geometry": {"coordinates":[4.8315339088,51.0039749146],"type":"Point"}
}