{
  "type": "Feature",
  "properties": {
    "addr:full":"Kruindersweg 43 Box 1 Maasmechelen (eisden) Limburg 3630",
    "addr:housenumber":"43;1",
    "addr:postcode":"3630",
    "addr:street":"Kruindersweg;Box",
    "iso:country":"BE",
    "sg:address":"Kruindersweg 43 Box 1",
    "sg:city":"Maasmechelen (eisden)",
    "sg:classifiers":[
        {
            "category":"Real Estate",
            "subcategory":"Architect",
            "type":"Services"
        }
    ],
    "sg:phone":"+32 89 76 42 40",
    "sg:postcode":"3630",
    "sg:province":"Limburg",
    "wof:name":"Coelmont D",
    "wof:placetype":"venue"
},
  "geometry": {"coordinates":[5.6961350441,50.963848114],"type":"Point"}
}