{
  "type": "Feature",
  "properties": {
    "iso:country":"BE",
    "sg:address":"Rue De La Gare 78",
    "sg:city":"Weismes",
    "sg:classifiers":[
        {
            "category":"Building & Trades",
            "subcategory":"Construction",
            "type":"Services"
        }
    ],
    "sg:phone":"+32 80 67 82 52",
    "sg:postcode":"4950",
    "sg:province":"Li\u00e8ge",
    "sg:tags":[
        "stucco",
        "contractor"
    ],
    "wof:name":"Sarlette F",
    "wof:placetype":"venue"
},
  "geometry": {"coordinates":[6.1196269989,50.4096908569],"type":"Point"}
}