{
  "type": "Feature",
  "properties": {
    "addr:full":"Rue Ernest Vander Aa 22 Bruxelles Bruxelles-Capitale 1020",
    "addr:housenumber":"22",
    "addr:postcode":"1020",
    "addr:street":"Rue Ernest Vander Aa",
    "iso:country":"BE",
    "sg:address":"Rue Ernest Vander Aa 22",
    "sg:city":"Bruxelles",
    "sg:orig_category":"Non-Classified Establishments",
    "sg:phone":"+32 2 478 51 85",
    "sg:postcode":"1020",
    "sg:province":"Bruxelles-Capitale",
    "wof:name":"Maison Goffart Belgium",
    "wof:placetype":"venue"
},
  "geometry": {"coordinates":[4.3462080956,50.8807029724],"type":"Point"}
}