{
  "type": "Feature",
  "properties": {
    "iso:country":"BE",
    "sg:address":"Stationstraat 1",
    "sg:city":"Beringen",
    "sg:orig_category":"Reisbureaus",
    "sg:phone":"+32 11 45 37 01",
    "sg:postcode":"3582",
    "sg:province":"Limburg",
    "wof:name":"Umay Reizen",
    "wof:placetype":"venue"
},
  "geometry": {"coordinates":[5.2205820084,51.072719574],"type":"Point"}
}