{
  "type": "Feature",
  "properties": {
    "iso:country":"BE",
    "sg:address":"Kloosterstraat 25",
    "sg:city":"Gent",
    "sg:orig_category":"Groententeelt",
    "sg:phone":"+32 9 282 73 60",
    "sg:postcode":"9031",
    "sg:province":"Oost-Vlaanderen",
    "wof:name":"Roger Sergeant",
    "wof:placetype":"venue"
},
  "geometry": {"coordinates":[3.6170110703,51.0390586853],"type":"Point"}
}