{
  "type": "Feature",
  "properties": {
    "addr:full":"Guido Gezellestraat 122 Beersel (huizingen) Vlaams-Brabant 1654",
    "addr:housenumber":"122",
    "addr:postcode":"1654",
    "addr:street":"Guido Gezellestraat",
    "iso:country":"BE",
    "sg:address":"Guido Gezellestraat 122",
    "sg:city":"Beersel (huizingen)",
    "sg:classifiers":[
        {
            "category":"Utilities",
            "subcategory":"Natural Gas",
            "type":"Services"
        }
    ],
    "sg:phone":"+32 2 361 46 40",
    "sg:postcode":"1654",
    "sg:province":"Vlaams-Brabant",
    "sg:tags":[
        "welding"
    ],
    "wof:name":"Aludan",
    "wof:placetype":"venue"
},
  "geometry": {"coordinates":[4.2708778381,50.7543067932],"type":"Point"}
}