{
  "type": "Feature",
  "properties": {
    "iso:country":"BE",
    "sg:address":"Stationsstraat 7-9",
    "sg:city":"Brakel (nederbrakel)",
    "sg:classifiers":[
        {
            "category":"Shopping",
            "subcategory":"Gifts & Souvenirs",
            "type":"Retail Goods"
        }
    ],
    "sg:phone":"+32 55 42 47 35",
    "sg:postcode":"9660",
    "sg:province":"Oost-Vlaanderen",
    "sg:tags":[
        "-"
    ],
    "wof:name":"D'haeyer Hilde Bvba",
    "wof:placetype":"venue"
},
  "geometry": {"coordinates":[3.7660989761,50.8008155823],"type":"Point"}
}