{
  "type": "Feature",
  "properties": {
    "addr:full":"Rue Jean-d'outremeuse 57 Li\u00c8ge Li\u00e8ge 4020",
    "addr:housenumber":"57",
    "addr:postcode":"4020",
    "addr:street":"Rue Jean-D'Outremeuse",
    "iso:country":"BE",
    "sg:address":"Rue Jean-d'outremeuse 57",
    "sg:city":"Li\u00c8ge",
    "sg:orig_category":"Enseignement maternel and primaire",
    "sg:phone":"+32 4 342 38 78",
    "sg:postcode":"4020",
    "sg:province":"Li\u00e8ge",
    "wof:name":"Ecole Robert Brasseur",
    "wof:placetype":"venue"
},
  "geometry": {"coordinates":[5.5850148201,50.6405982971],"type":"Point"}
}