{
  "type": "Feature",
  "properties": {
    "iso:country":"BE",
    "sg:address":"Rue Lenoir 10",
    "sg:city":"Louvain-la-neuve",
    "sg:classifiers":[
        {
            "category":"Retail",
            "subcategory":"Event Space",
            "type":"Services"
        }
    ],
    "sg:phone":"+32 10 48 56 00",
    "sg:postcode":"1348",
    "sg:province":"Brabant Wallon",
    "sg:tags":[
        "telecommunication"
    ],
    "wof:name":"Global Telephone And Telecommunication S.a.",
    "wof:placetype":"venue"
},
  "geometry": {"coordinates":[4.6268630028,50.6639862061],"type":"Point"}
}