{
  "type": "Feature",
  "properties": {
    "addr:full":"Rue De Taillis-pr\u00c9 53 Ch\u00c2telet Hainaut 6200",
    "addr:housenumber":"53",
    "addr:postcode":"6200",
    "addr:street":"Rue De Taillis-Pre\u0301",
    "iso:country":"BE",
    "sg:address":"Rue De Taillis-pr\u00c9 53",
    "sg:city":"Ch\u00c2telet",
    "sg:orig_category":"Entretien and r\u00e9parations de voitures. V\u00e9hicules automobiles Gr",
    "sg:phone":"+32 71 40 57 47",
    "sg:postcode":"6200",
    "sg:province":"Hainaut",
    "wof:name":"Garage Du Taillis Pr\u00c9",
    "wof:placetype":"venue"
},
  "geometry": {"coordinates":[4.5067028999,50.4333000183],"type":"Point"}
}