{
  "type": "Feature",
  "properties": {
    "iso:country":"BE",
    "sg:address":"Steentjeslaan 20",
    "sg:city":"Kontich",
    "sg:orig_category":"Traitements param\u00e9dicaux",
    "sg:phone":"+32 3 457 86 38",
    "sg:postcode":"2550",
    "sg:province":"Antwerpen",
    "wof:name":"Van Hemelen-keppens",
    "wof:placetype":"venue"
},
  "geometry": {"coordinates":[4.4503378868,51.1428756714],"type":"Point"}
}