{
  "type": "Feature",
  "properties": {
    "addr:full":"Schaapsven 26 Lommel Limburg 3920",
    "addr:housenumber":"26",
    "addr:postcode":"3920",
    "addr:street":"Schaapsven",
    "iso:country":"BE",
    "sg:address":"Schaapsven 26",
    "sg:city":"Lommel",
    "sg:classifiers":[
        {
            "category":"Health Services",
            "subcategory":"Health Practitioner",
            "type":"Services"
        }
    ],
    "sg:phone":"+32 11 55 39 34",
    "sg:postcode":"3920",
    "sg:province":"Limburg",
    "sg:tags":[
        "physiotherapist"
    ],
    "wof:name":"Rademakers Chris",
    "wof:placetype":"venue"
},
  "geometry": {"coordinates":[5.3278160095,51.2482185364],"type":"Point"}
}