{
  "type": "Feature",
  "properties": {
    "addr:full":"Rue De Marchienne 35 Charleroi Hainaut 6040",
    "addr:housenumber":"35",
    "addr:postcode":"6040",
    "addr:street":"Rue De Marchienne;Hainaut",
    "iso:country":"BE",
    "sg:address":"Rue De Marchienne 35",
    "sg:city":"Charleroi",
    "sg:orig_category":"Grands magasins",
    "sg:phone":"+32 71 37 08 98",
    "sg:postcode":"6040",
    "sg:province":"Hainaut",
    "wof:name":"Les Magasins Point Jaune",
    "wof:placetype":"venue"
},
  "geometry": {"coordinates":[4.4148988724,50.4328727722],"type":"Point"}
}