{
  "type": "Feature",
  "properties": {
    "iso:country":"BE",
    "sg:address":"Rue Haute 9",
    "sg:city":"Bassenge (eben-emael)",
    "sg:classifiers":[
        {
            "category":"Social Services",
            "subcategory":"Job Training",
            "type":"Services"
        }
    ],
    "sg:phone":"+32 4 286 54 53",
    "sg:postcode":"4690",
    "sg:province":"Li\u00e8ge",
    "sg:tags":[
        "personnel"
    ],
    "wof:name":"Fil \u00e0 Plomb (le)-eft",
    "wof:placetype":"venue"
},
  "geometry": {"coordinates":[5.6660060883,50.7934341431],"type":"Point"}
}