{
  "type": "Feature",
  "properties": {
    "iso:country":"BE",
    "sg:address":"Holstraat 53",
    "sg:city":"Londerzeel",
    "sg:orig_category":"Verhuur cateringmateriaal and evenementuitrusting Verhuur diversen",
    "sg:phone":"+32 52 33 79 03",
    "sg:postcode":"1840",
    "sg:province":"Vlaams-Brabant",
    "wof:name":"Luc Steenackers",
    "wof:placetype":"venue"
},
  "geometry": {"coordinates":[4.2369999886,51.0181083679],"type":"Point"}
}