{
  "type": "Feature",
  "properties": {
    "iso:country":"BE",
    "sg:address":"Schulstraat 1",
    "sg:city":"Antwerpen",
    "sg:classifiers":[
        {
            "category":"Professional",
            "subcategory":"Testing Lab",
            "type":"Services"
        }
    ],
    "sg:phone":"+32 3 237 51 43",
    "sg:postcode":"2018",
    "sg:province":"Antwerpen",
    "sg:tags":[
        "chemist"
    ],
    "wof:name":"Van Hoyweghen N",
    "wof:placetype":"venue"
},
  "geometry": {"coordinates":[4.4070301056,51.2021903992],"type":"Point"}
}