{
  "type": "Feature",
  "properties": {
    "iso:country":"BE",
    "sg:address":"Kapelleriestraat 1",
    "sg:city":"Staden",
    "sg:orig_category":"Zuivelproducten",
    "sg:phone":"+32 51 70 32 16",
    "sg:postcode":"8840",
    "sg:province":"West-Vlaanderen",
    "wof:name":"Christel Carette",
    "wof:placetype":"venue"
},
  "geometry": {"coordinates":[3.012775898,50.974571228],"type":"Point"}
}