{
  "type": "Feature",
  "properties": {
    "iso:country":"BE",
    "sg:address":"Rue De La Gare 82",
    "sg:city":"Onhaye (fala\u00ebn)",
    "sg:classifiers":[
        {
            "category":"Landmark",
            "subcategory":"Tourist Attraction",
            "type":"Public Place"
        }
    ],
    "sg:phone":"+32 82 69 90 79",
    "sg:postcode":"5522",
    "sg:province":"Namur",
    "sg:tags":[
        "-",
        "tourism",
        "interest",
        "sight"
    ],
    "wof:name":"Draisines De La Molign\u00e9e",
    "wof:placetype":"venue"
},
  "geometry": {"coordinates":[4.801202774,50.290725708],"type":"Point"}
}