{
  "type": "Feature",
  "properties": {
    "iso:country":"BE",
    "sg:address":"Wolvenstraat 28",
    "sg:city":"Arendonk",
    "sg:classifiers":[
        {
            "category":"Home & Garden",
            "subcategory":"Home Furnishings",
            "type":"Retail Goods"
        }
    ],
    "sg:phone":"+32 14 67 02 66",
    "sg:postcode":"2370",
    "sg:province":"Antwerpen",
    "sg:tags":[
        "decoration"
    ],
    "wof:name":"Allsfeer",
    "wof:placetype":"venue"
},
  "geometry": {"coordinates":[5.0892748833,51.3286895752],"type":"Point"}
}