{
  "type": "Feature",
  "properties": {
    "addr:full":"Place Palais De Justice 4 Tournai Hainaut 7500",
    "addr:housenumber":"4",
    "addr:postcode":"7500",
    "addr:street":"Place Palais De Justice",
    "iso:country":"BE",
    "sg:address":"Place Palais De Justice 4",
    "sg:city":"Tournai",
    "sg:classifiers":[
        {
            "category":"Restaurant",
            "type":"Food & Drink"
        }
    ],
    "sg:phone":"+32 69 22 77 75",
    "sg:postcode":"7500",
    "sg:province":"Hainaut",
    "sg:tags":[
        "caf\u00e9s"
    ],
    "wof:name":"Au Petit Palais",
    "wof:placetype":"venue"
},
  "geometry": {"coordinates":[3.3954041004,50.602191925],"type":"Point"}
}