{
  "type": "Feature",
  "properties": {
    "addr:full":"Chauss\u00e9e De Louvain 17 Eghez\u00e9e Namur 5310",
    "addr:housenumber":"17",
    "addr:postcode":"5310",
    "addr:street":"Chausse\u0301E De Louvain;Namur",
    "iso:country":"BE",
    "sg:address":"Chauss\u00e9e De Louvain 17",
    "sg:city":"Eghez\u00e9e",
    "sg:classifiers":[
        {
            "category":"Bakery",
            "type":"Food & Drink"
        }
    ],
    "sg:phone":"+32 81 81 13 59",
    "sg:postcode":"5310",
    "sg:province":"Namur",
    "sg:tags":[
        "confectioner",
        "baker"
    ],
    "wof:name":"Boxus P",
    "wof:placetype":"venue"
},
  "geometry": {"coordinates":[4.9108428955,50.5929145813],"type":"Point"}
}