{
  "type": "Feature",
  "properties": {
    "iso:country":"BE",
    "sg:address":"C\u00f4te De Hagelstein 7",
    "sg:city":"Aubel",
    "sg:classifiers":[
        {
            "category":"Professional",
            "subcategory":"Accounting & Tax Preparation",
            "type":"Services"
        }
    ],
    "sg:phone":"+32 87 68 67 14",
    "sg:postcode":"4880",
    "sg:province":"Li\u00e8ge",
    "sg:tags":[
        "bookkeeper"
    ],
    "wof:name":"Belleflamme C",
    "wof:placetype":"venue"
},
  "geometry": {"coordinates":[5.8582000732,50.7129211426],"type":"Point"}
}