{
  "type": "Feature",
  "properties": {
    "addr:full":"Diksmuidseweg 113 Ieper West-Vlaanderen 8900",
    "addr:housenumber":"113",
    "addr:postcode":"8900",
    "iso:country":"BE",
    "sg:address":"Diksmuidseweg 113",
    "sg:city":"Ieper",
    "sg:orig_category":"Artsen and specialisten",
    "sg:phone":"+32 57 21 72 12",
    "sg:postcode":"8900",
    "sg:province":"West-Vlaanderen",
    "wof:name":"Griet Stoffels",
    "wof:placetype":"venue"
},
  "geometry": {"coordinates":[2.8765408993,50.8641357422],"type":"Point"}
}