{
  "type": "Feature",
  "properties": {
    "addr:full":"Galerie Op\u00c9ra 9c Li\u00c8ge Li\u00e8ge 4000",
    "addr:housenumber":"9c",
    "addr:postcode":"4000",
    "iso:country":"BE",
    "sg:address":"Galerie Op\u00c9ra 9c",
    "sg:city":"Li\u00c8ge",
    "sg:orig_category":"Chaussures. V\u00eatements pour b\u00e9b\u00e9s and enfants",
    "sg:phone":"+32 4 222 13 65",
    "sg:postcode":"4000",
    "sg:province":"Li\u00e8ge",
    "wof:name":"Maison Bisou",
    "wof:placetype":"venue"
},
  "geometry": {"coordinates":[5.57107687,50.6435165405],"type":"Point"}
}