{
  "type": "Feature",
  "properties": {
    "iso:country":"BE",
    "sg:address":"Zavelstraat 6",
    "sg:city":"Westerlo",
    "sg:classifiers":[
        {
            "category":"Health Services",
            "subcategory":"Health Practitioner",
            "type":"Services"
        }
    ],
    "sg:phone":"+32 14 71 32 04",
    "sg:postcode":"2260",
    "sg:province":"Antwerpen",
    "sg:tags":[
        "dietitian"
    ],
    "wof:name":"De Busser A",
    "wof:placetype":"venue"
},
  "geometry": {"coordinates":[4.9112768173,51.0883636475],"type":"Point"}
}