{
  "type": "Feature",
  "properties": {
    "addr:full":"Grootlostraat 93 Tremelo Vlaams-Brabant 3128",
    "addr:housenumber":"93",
    "addr:postcode":"3128",
    "addr:street":"Grootlostraat",
    "iso:country":"BE",
    "sg:address":"Grootlostraat 93",
    "sg:city":"Tremelo",
    "sg:orig_category":"Boucheries",
    "sg:phone":"+32 16 53 20 43",
    "sg:postcode":"3128",
    "sg:province":"Vlaams-Brabant",
    "wof:name":"Lodewijk Heremans",
    "wof:placetype":"venue"
},
  "geometry": {"coordinates":[4.7394890785,51.0183792114],"type":"Point"}
}