{
  "type": "Feature",
  "properties": {
    "iso:country":"BE",
    "sg:address":"Molenbos 77",
    "sg:city":"Nijlen",
    "sg:orig_category":"Biljart- and snookerzalen Sportcentra Sportclubs Sportterreinen and installaties behalve sportcentra",
    "sg:phone":"+32 3 481 69 77",
    "sg:postcode":"2560",
    "sg:province":"Antwerpen",
    "wof:name":"Sportcenter Molenbos",
    "wof:placetype":"venue"
},
  "geometry": {"coordinates":[4.6786088943,51.1508560181],"type":"Point"}
}