{
  "type": "Feature",
  "properties": {
    "addr:full":"Dani\u00eblsstraat 31 Box 5 Hasselt Limburg 3500",
    "addr:housenumber":"31;5",
    "addr:postcode":"3500",
    "addr:street":"Danie\u0308Lsstraat;Box",
    "iso:country":"BE",
    "sg:address":"Dani\u00eblsstraat 31 Box 5",
    "sg:city":"Hasselt",
    "sg:classifiers":[
        {
            "category":"Structure",
            "subcategory":"Office Building",
            "type":"Public Place"
        }
    ],
    "sg:phone":"+32 11 28 44 78",
    "sg:postcode":"3500",
    "sg:province":"Limburg",
    "sg:tags":[
        "drawing"
    ],
    "wof:name":"Artekto",
    "wof:placetype":"venue"
},
  "geometry": {"coordinates":[5.3480758667,50.9190139771],"type":"Point"}
}