{
  "type": "Feature",
  "properties": {
    "addr:full":"Witte Barier 69 Heusden-zolder (zolder) Limburg 3550",
    "addr:housenumber":"69",
    "addr:postcode":"3550",
    "iso:country":"BE",
    "sg:address":"Witte Barier 69",
    "sg:city":"Heusden-zolder (zolder)",
    "sg:classifiers":[
        {
            "category":"Building & Trades",
            "subcategory":"Landscaping Services",
            "type":"Services"
        }
    ],
    "sg:phone":"+32 13 55 65 33",
    "sg:postcode":"3550",
    "sg:province":"Limburg",
    "sg:tags":[
        "gardening",
        "garden",
        "maintenance"
    ],
    "wof:name":"Corthouts",
    "wof:placetype":"venue"
},
  "geometry": {"coordinates":[5.3109908104,51.0170097351],"type":"Point"}
}