{
  "type": "Feature",
  "properties": {
    "addr:full":"Tongerlostraat 19 Antwerpen Antwerpen 2040",
    "addr:housenumber":"19",
    "addr:postcode":"2040",
    "addr:street":"Tongerlostraat",
    "iso:country":"BE",
    "sg:address":"Tongerlostraat 19",
    "sg:city":"Antwerpen",
    "sg:orig_category":"Ordinateurs and \u00e9quipement informatique",
    "sg:phone":"+32 3 569 17 79",
    "sg:postcode":"2040",
    "sg:province":"Antwerpen",
    "wof:name":"Comweb",
    "wof:placetype":"venue"
},
  "geometry": {"coordinates":[4.3141150475,51.3429756165],"type":"Point"}
}