{
  "type": "Feature",
  "properties": {
    "addr:full":"Meir 24 Antwerpen Antwerpen 2000",
    "addr:housenumber":"24",
    "addr:postcode":"2000",
    "addr:street":"Meir",
    "iso:country":"BE",
    "sg:address":"Meir 24",
    "sg:city":"Antwerpen",
    "sg:orig_category":"Agences immobili\u00e8res",
    "sg:phone":"+32 3 231 26 17",
    "sg:postcode":"2000",
    "sg:province":"Antwerpen",
    "wof:name":"Fidimco",
    "wof:placetype":"venue"
},
  "geometry": {"coordinates":[4.4064750671,51.2180976868],"type":"Point"}
}