{
  "type": "Feature",
  "properties": {
    "iso:country":"BE",
    "sg:address":"Sint-pietersaalststraat 86",
    "sg:city":"Gent",
    "sg:classifiers":[
        {
            "category":"Education",
            "subcategory":"School",
            "type":"Public Place"
        }
    ],
    "sg:phone":"+32 9 221 23 53",
    "sg:postcode":"9000",
    "sg:province":"Oost-Vlaanderen",
    "sg:tags":[
        "primary"
    ],
    "wof:name":"Sint-lievenscollege",
    "wof:placetype":"venue"
},
  "geometry": {"coordinates":[3.716137886,51.0292510986],"type":"Point"}
}