{
  "type": "Feature",
  "properties": {
    "iso:country":"BE",
    "sg:address":"Froidbermont 37",
    "sg:city":"Olne",
    "sg:classifiers":[
        {
            "category":"Building & Trades",
            "subcategory":"Pest Control",
            "type":"Services"
        }
    ],
    "sg:phone":"+32 87 26 88 14",
    "sg:postcode":"4877",
    "sg:province":"Li\u00e8ge",
    "sg:tags":[
        "painting",
        "contractor"
    ],
    "wof:name":"Close Bernard Sc",
    "wof:placetype":"venue"
},
  "geometry": {"coordinates":[5.7549619675,50.5845756531],"type":"Point"}
}