{
  "type": "Feature",
  "properties": {
    "iso:country":"BE",
    "sg:address":"Kortrijksesteenweg 204",
    "sg:city":"Deinze",
    "sg:orig_category":"Agences d'exp\u00e9dition",
    "sg:phone":"+32 9 386 58 30",
    "sg:postcode":"9800",
    "sg:province":"Oost-Vlaanderen",
    "wof:name":"Apt International",
    "wof:placetype":"venue"
},
  "geometry": {"coordinates":[3.5250399113,50.9756698608],"type":"Point"}
}