{
  "type": "Feature",
  "properties": {
    "addr:full":"Rue De La Prairie 24 Grez-doiceau Brabant Wallon 1390",
    "addr:housenumber":"24",
    "addr:postcode":"1390",
    "addr:street":"Rue De La Prairie",
    "iso:country":"BE",
    "sg:address":"Rue De La Prairie 24",
    "sg:city":"Grez-doiceau",
    "sg:orig_category":"Installatie van houten of kunststof schrijnwerk Meubelzaken, woning- and keukeninrichting",
    "sg:phone":"+32 10 86 72 85",
    "sg:postcode":"1390",
    "sg:province":"Brabant Wallon",
    "wof:name":"V.d.z.",
    "wof:placetype":"venue"
},
  "geometry": {"coordinates":[4.6830258369,50.7822647095],"type":"Point"}
}