{
  "type": "Feature",
  "properties": {
    "iso:country":"BE",
    "sg:address":"Rue Ponthi\u00e8re 7 Box 2",
    "sg:city":"Amay",
    "sg:classifiers":[
        {
            "category":"Social Services",
            "type":"Services"
        }
    ],
    "sg:phone":"+32 70 25 10 11",
    "sg:postcode":"4540",
    "sg:province":"Li\u00e8ge",
    "sg:tags":[
        "-",
        "infokiosk"
    ],
    "wof:name":"Moving's Phone Sprl",
    "wof:placetype":"venue"
},
  "geometry": {"coordinates":[5.3230319023,50.5448532104],"type":"Point"}
}