{
  "type": "Feature",
  "properties": {
    "iso:country":"BE",
    "sg:address":"Paddenhoek 14",
    "sg:city":"Sint-martens-latem",
    "sg:classifiers":[
        {
            "category":"Building & Trades",
            "subcategory":"Electrical",
            "type":"Services"
        }
    ],
    "sg:phone":"+32 9 223 71 08",
    "sg:postcode":"9830",
    "sg:province":"Oost-Vlaanderen",
    "sg:tags":[
        "electric",
        "-",
        "housewiring",
        "contractor"
    ],
    "wof:name":"Vandenbroucke A",
    "wof:placetype":"venue"
},
  "geometry": {"coordinates":[3.6364700794,51.0111351013],"type":"Point"}
}