{
  "type": "Feature",
  "properties": {
    "iso:country":"BE",
    "sg:address":"Rue Des Ecoles 13",
    "sg:city":"Charleroi",
    "sg:orig_category":"Installatie van houten of kunststof schrijnwerk Installatie van metalen schrijnwerk",
    "sg:phone":"+32 71 52 87 83",
    "sg:postcode":"6031",
    "sg:province":"Hainaut",
    "wof:name":"Menuiserie Du Hameau",
    "wof:placetype":"venue"
},
  "geometry": {"coordinates":[4.413711071,50.4521598816],"type":"Point"}
}