{
  "type": "Feature",
  "properties": {
    "iso:country":"BE",
    "sg:address":"Rue Du Sartia 12",
    "sg:city":"Fosses-la-ville (sart-eustache)",
    "sg:classifiers":[
        {
            "category":"Health Services",
            "subcategory":"Doctor",
            "type":"Services"
        }
    ],
    "sg:phone":"+32 71 39 80 19",
    "sg:postcode":"5070",
    "sg:province":"Namur",
    "sg:tags":[
        "medicinephysicians",
        "surgeon"
    ],
    "wof:name":"Calicis Benjamin",
    "wof:placetype":"venue"
},
  "geometry": {"coordinates":[4.6015629768,50.3759994507],"type":"Point"}
}