{
  "type": "Feature",
  "properties": {
    "addr:full":"Steenweg Op Ruisbroek 65 St. Pieters Leeuw Vlaams-Brabant 1600",
    "addr:housenumber":"65",
    "addr:postcode":"1600",
    "addr:street":"Steenweg Op Ruisbroek",
    "iso:country":"BE",
    "sg:address":"Steenweg Op Ruisbroek 65",
    "sg:city":"St. Pieters Leeuw",
    "sg:classifiers":[
        {
            "category":"Banks & Credit Unions",
            "subcategory":"Bank",
            "type":"Services"
        }
    ],
    "sg:phone":"+32 2 378 24 65",
    "sg:postcode":"1600",
    "sg:province":"Vlaams-Brabant",
    "wof:name":"Aslk-cger Bank",
    "wof:placetype":"venue"
},
  "geometry": {"coordinates":[4.2848591805,50.788646698],"type":"Point"}
}