{
  "type": "Feature",
  "properties": {
    "iso:country":"BE",
    "sg:address":"Liersesteenweg 107",
    "sg:city":"Sint-katelijne-waver",
    "sg:orig_category":"Medische apparatuur, orthopedische artikelen and prothesen Fab",
    "sg:phone":"+32 15 20 05 96",
    "sg:postcode":"2860",
    "sg:province":"Antwerpen",
    "wof:name":"Huysmans",
    "wof:placetype":"venue"
},
  "geometry": {"coordinates":[4.4804501534,51.0539588928],"type":"Point"}
}