{
  "type": "Feature",
  "properties": {
    "iso:country":"BE",
    "sg:address":"Rue De M\u00c9rode 18",
    "sg:city":"Chatelet",
    "sg:orig_category":"Enseignement maternel and primaire",
    "sg:phone":"+32 71 39 32 70",
    "sg:postcode":"6200",
    "sg:province":"Hainaut",
    "wof:name":"Ecole Matern. Communale",
    "wof:placetype":"venue"
},
  "geometry": {"coordinates":[4.5165882111,50.4107894897],"type":"Point"}
}