{
  "type": "Feature",
  "properties": {
    "addr:full":"Hector Henneaulaan 12 Zaventem Vlaams-Brabant 1930",
    "addr:housenumber":"12",
    "addr:postcode":"1930",
    "addr:street":"Hector Henneaulaan",
    "iso:country":"BE",
    "sg:address":"Hector Henneaulaan 12",
    "sg:city":"Zaventem",
    "sg:classifiers":[
        {
            "category":"Government",
            "subcategory":"Police Station",
            "type":"Public Place"
        }
    ],
    "sg:phone":"+32 2 252 42 80",
    "sg:postcode":"1930",
    "sg:province":"Vlaams-Brabant",
    "sg:tags":[
        "anodizing"
    ],
    "wof:name":"Analu Nv",
    "wof:placetype":"venue"
},
  "geometry": {"coordinates":[4.4506621361,50.9206809998],"type":"Point"}
}