{
  "type": "Feature",
  "properties": {
    "iso:country":"BE",
    "sg:address":"Rue Des Combattants 4bc",
    "sg:city":"Tournai",
    "sg:orig_category":"M\u00e9decins and sp\u00e9cialistes",
    "sg:phone":"+32 69 54 59 04",
    "sg:postcode":"7534",
    "sg:province":"Hainaut",
    "wof:name":"J.l. Locufier",
    "wof:placetype":"venue"
},
  "geometry": {"coordinates":[3.5431890488,50.5878715515],"type":"Point"}
}