{
  "type": "Feature",
  "properties": {
    "iso:country":"BE",
    "sg:address":"Rue Cour-lassus 7",
    "sg:city":"Rouvroy",
    "sg:orig_category":"Rundveehouders",
    "sg:phone":"+32 63 57 76 72",
    "sg:postcode":"6767",
    "sg:province":"Luxembourg",
    "wof:name":"Albin Louis",
    "wof:placetype":"venue"
},
  "geometry": {"coordinates":[5.4747519493,49.5081253052],"type":"Point"}
}