{
  "type": "Feature",
  "properties": {
    "iso:country":"BE",
    "sg:address":"Rue Soeurs-de-hasque 9",
    "sg:city":"Li\u00c8ge",
    "sg:orig_category":"Opvangtehuizen and vluchthuizen",
    "sg:phone":"+32 4 223 42 85",
    "sg:postcode":"4000",
    "sg:province":"Li\u00e8ge",
    "wof:name":"Maison Femmes Battues",
    "wof:placetype":"venue"
},
  "geometry": {"coordinates":[5.5734329224,50.6403808594],"type":"Point"}
}