{
  "type": "Feature",
  "properties": {
    "iso:country":"BE",
    "sg:address":"Rue Des Grand Carmes 33",
    "sg:city":"Brussel/bruxelles",
    "sg:orig_category":"RESTAURANTS: CAF\u00c9S",
    "sg:phone":"+32 2 502 71 45",
    "sg:postcode":"1000",
    "sg:province":"Bruxelles-Capitale",
    "wof:name":"Taverne Manneken Pis",
    "wof:placetype":"venue"
},
  "geometry": {"coordinates":[4.3496260643,50.8449478149],"type":"Point"}
}