{
  "type": "Feature",
  "properties": {
    "addr:full":"Begijnhofdries 42 Gent Oost-Vlaanderen 9000",
    "addr:housenumber":"42",
    "addr:postcode":"9000",
    "addr:street":"Begijnhofdries;Oost-Vlaanderen",
    "iso:country":"BE",
    "sg:address":"Begijnhofdries 42",
    "sg:city":"Gent",
    "sg:orig_category":"Enseignement maternel and primaire",
    "sg:phone":"+32 9 225 14 55",
    "sg:postcode":"9000",
    "sg:province":"Oost-Vlaanderen",
    "wof:name":"Stedelijke Basisschool",
    "wof:placetype":"venue"
},
  "geometry": {"coordinates":[3.7130339146,51.0573730469],"type":"Point"}
}