{
  "type": "Feature",
  "properties": {
    "addr:full":"Hillesteenweg 50 Wingene West-Vlaanderen 8750",
    "addr:housenumber":"50",
    "addr:postcode":"8750",
    "addr:street":"Hillesteenweg",
    "iso:country":"BE",
    "sg:address":"Hillesteenweg 50",
    "sg:city":"Wingene",
    "sg:orig_category":"Non-Classified Establishments",
    "sg:phone":"+32 51 65 55 36",
    "sg:postcode":"8750",
    "sg:province":"West-Vlaanderen",
    "wof:name":"Demeyere Cvba",
    "wof:placetype":"venue"
},
  "geometry": {"coordinates":[3.2611570358,51.0555229187],"type":"Point"}
}