{
  "type": "Feature",
  "properties": {
    "addr:full":"Rue Sualem 40 Jemeppe Li\u00e8ge 4101",
    "addr:housenumber":"40",
    "addr:postcode":"4101",
    "addr:street":"Rue Sualem;Jemeppe",
    "iso:country":"BE",
    "sg:address":"Rue Sualem 40",
    "sg:city":"Jemeppe",
    "sg:classifiers":[
        {
            "category":"Cinema",
            "subcategory":"Movie Rental",
            "type":"Entertainment"
        }
    ],
    "sg:phone":"+32 4 235 96 80",
    "sg:postcode":"4101",
    "sg:province":"Li\u00e8ge",
    "sg:tags":[
        "de",
        "cassette",
        "location",
        "vid\u00e9o",
        "audio"
    ],
    "wof:name":"Star Video",
    "wof:placetype":"venue"
},
  "geometry": {"coordinates":[5.496778965,50.6195220947],"type":"Point"}
}