{
  "type": "Feature",
  "properties": {
    "addr:full":"Laurent Delvauxstraat 8 Gent Oost-Vlaanderen 9000",
    "addr:housenumber":"8",
    "addr:postcode":"9000",
    "addr:street":"Delvauxstraat;Oost-Vlaanderen",
    "iso:country":"BE",
    "sg:address":"Laurent Delvauxstraat 8",
    "sg:city":"Gent",
    "sg:classifiers":[
        {
            "category":"Health Services",
            "subcategory":"Health Practitioner",
            "type":"Services"
        }
    ],
    "sg:phone":"+32 9 225 08 76",
    "sg:postcode":"9000",
    "sg:province":"Oost-Vlaanderen",
    "sg:tags":[
        "physiotherapist"
    ],
    "wof:name":"Marichal I",
    "wof:placetype":"venue"
},
  "geometry": {"coordinates":[3.7201581001,51.0420455933],"type":"Point"}
}