{
  "type": "Feature",
  "properties": {
    "iso:country":"BE",
    "sg:address":"Sint-elooistraat 58",
    "sg:city":"Lochristi",
    "sg:orig_category":"Enseignement maternel and primaire",
    "sg:phone":"+32 9 355 73 20",
    "sg:postcode":"9080",
    "sg:province":"Oost-Vlaanderen",
    "wof:name":"Vrije Basisschool",
    "wof:placetype":"venue"
},
  "geometry": {"coordinates":[3.897480011,51.1036376953],"type":"Point"}
}