{
  "type": "Feature",
  "properties": {
    "addr:full":"Rue De Birmingham 299 Bruxelles (anderlecht) Bruxelles-Capitale 1070",
    "addr:housenumber":"299",
    "addr:postcode":"1070",
    "addr:street":"Rue De Birmingham",
    "iso:country":"BE",
    "sg:address":"Rue De Birmingham 299",
    "sg:city":"Bruxelles (anderlecht)",
    "sg:classifiers":[
        {
            "category":"Shopping",
            "subcategory":"Discount & Variety Stores",
            "type":"Retail Goods"
        }
    ],
    "sg:phone":"+32 2 522 14 97",
    "sg:postcode":"1070",
    "sg:province":"Bruxelles-Capitale",
    "sg:tags":[
        "warehouse",
        "-",
        "merchandise"
    ],
    "wof:name":"Gift In Gift",
    "wof:placetype":"venue"
},
  "geometry": {"coordinates":[4.3150310516,50.8413085938],"type":"Point"}
}