{
  "type": "Feature",
  "properties": {
    "addr:full":"Rue Des Trois-grands 69 Li\u00e8ge 1 (grivegn\u00e9e) Li\u00e8ge 4030",
    "addr:housenumber":"69;1",
    "addr:postcode":"4030",
    "addr:street":"Rue Des Trois-Grands",
    "iso:country":"BE",
    "sg:address":"Rue Des Trois-grands 69",
    "sg:city":"Li\u00e8ge 1 (grivegn\u00e9e)",
    "sg:classifiers":[
        {
            "category":"Professional",
            "subcategory":"Accounting & Tax Preparation",
            "type":"Services"
        }
    ],
    "sg:phone":"+32 4 343 90 36",
    "sg:postcode":"4030",
    "sg:province":"Li\u00e8ge",
    "sg:tags":[
        "bookkeeper"
    ],
    "wof:name":"Perri A",
    "wof:placetype":"venue"
},
  "geometry": {"coordinates":[5.5956740379,50.6220016479],"type":"Point"}
}