{
  "type": "Feature",
  "properties": {
    "iso:country":"BE",
    "sg:address":"Brandestraat 25",
    "sg:city":"Berlaar",
    "sg:classifiers":[
        {
            "category":"Restaurant",
            "type":"Food & Drink"
        }
    ],
    "sg:phone":"+32 3 385 29 56",
    "sg:postcode":"2590",
    "sg:province":"Antwerpen",
    "wof:name":"'t Kruidenboeketje",
    "wof:placetype":"venue"
},
  "geometry": {"coordinates":[4.6339831352,51.0950317383],"type":"Point"}
}