{
  "type": "Feature",
  "properties": {
    "iso:country":"BE",
    "sg:address":"Romeinsesteenweg 324",
    "sg:city":"Vilvorde",
    "sg:orig_category":"Entretien and r\u00e9parations de machines de bureau and ordinateurs. Ordinateurs and \u00e9quipement informat",
    "sg:phone":"+32 2 267 18 06",
    "sg:postcode":"1800",
    "sg:province":"Vlaams-Brabant",
    "wof:name":"Adverbo",
    "wof:placetype":"venue"
},
  "geometry": {"coordinates":[4.371119976,50.9025611877],"type":"Point"}
}