{
  "type": "Feature",
  "properties": {
    "iso:country":"BE",
    "sg:address":"Moretteweg 21",
    "sg:city":"Asse",
    "sg:classifiers":[
        {
            "category":"Health Services",
            "subcategory":"Doctor",
            "type":"Services"
        }
    ],
    "sg:phone":"+32 2 452 78 98",
    "sg:postcode":"1730",
    "sg:province":"Vlaams-Brabant",
    "sg:tags":[
        "medicinephysicians",
        "surgeon"
    ],
    "wof:name":"De Witte Michel",
    "wof:placetype":"venue"
},
  "geometry": {"coordinates":[4.1632452011,50.8970031738],"type":"Point"}
}