{
  "type": "Feature",
  "properties": {
    "iso:country":"BE",
    "sg:address":"La Coulee 55",
    "sg:city":"Lierneux",
    "sg:orig_category":"Eleveurs de bovins",
    "sg:phone":"+32 86 45 55 23",
    "sg:postcode":"4990",
    "sg:province":"Li\u00e8ge",
    "wof:name":"Jose Lecomte",
    "wof:placetype":"venue"
},
  "geometry": {"coordinates":[5.7310271263,50.3241119385],"type":"Point"}
}