{
  "type": "Feature",
  "properties": {
    "iso:country":"BE",
    "sg:address":"Waaienberg 2ba",
    "sg:city":"Ronse/renaix",
    "sg:orig_category":"Formation permanente",
    "sg:phone":"+32 55 21 50 47",
    "sg:postcode":"9600",
    "sg:province":"Oost-Vlaanderen",
    "wof:name":"Techn. Leerg. Elektronica",
    "wof:placetype":"venue"
},
  "geometry": {"coordinates":[3.6436679363,50.7441902161],"type":"Point"}
}