{
  "type": "Feature",
  "properties": {
    "iso:country":"BE",
    "sg:address":"Dikke Linde 11",
    "sg:city":"Kinrooi",
    "sg:orig_category":"Pain, p\u00e2tisseries and confiseries",
    "sg:phone":"+32 89 56 55 89",
    "sg:postcode":"3640",
    "sg:province":"Limburg",
    "wof:name":"Antony Van Esser",
    "wof:placetype":"venue"
},
  "geometry": {"coordinates":[5.7962970734,51.1226234436],"type":"Point"}
}