{
  "type": "Feature",
  "properties": {
    "iso:country":"BE",
    "sg:address":"Sint-gillislaan 125",
    "sg:city":"Dendermonde",
    "sg:orig_category":"Souvenirs and objets artisanaux. Services fun\u00e9raires. Fleurs and plantes. Art and fournitures artist",
    "sg:phone":"+32 52 21 14 72",
    "sg:postcode":"9200",
    "sg:province":"Oost-Vlaanderen",
    "wof:name":"Patrick Cornelis - Blot",
    "wof:placetype":"venue"
},
  "geometry": {"coordinates":[4.1115088463,51.0191268921],"type":"Point"}
}