{
  "type": "Feature",
  "properties": {
    "addr:full":"Quai De Rome 82 Li\u00c8ge Li\u00e8ge 4000",
    "addr:housenumber":"82",
    "addr:postcode":"4000",
    "addr:street":"Quai De Rome",
    "iso:country":"BE",
    "sg:address":"Quai De Rome 82",
    "sg:city":"Li\u00c8ge",
    "sg:orig_category":"Avocats and conseillers juridiques",
    "sg:phone":"+32 4 252 59 05",
    "sg:postcode":"4000",
    "sg:province":"Li\u00e8ge",
    "wof:name":"Yves Bisinella",
    "wof:placetype":"venue"
},
  "geometry": {"coordinates":[5.5777578354,50.6198959351],"type":"Point"}
}