{
  "type": "Feature",
  "properties": {
    "iso:country":"BE",
    "sg:address":"Pontstraat 108",
    "sg:city":"Zwevegem",
    "sg:orig_category":"Eleveurs de bovins. Eleveurs and marchands de porcs",
    "sg:phone":"+32 56 77 75 05",
    "sg:postcode":"8551",
    "sg:province":"West-Vlaanderen",
    "wof:name":"Lanneau",
    "wof:placetype":"venue"
},
  "geometry": {"coordinates":[3.3980000019,50.8092689514],"type":"Point"}
}