{
  "type": "Feature",
  "properties": {
    "addr:full":"Rue Riverre 12 Floreffe Namur 5150",
    "addr:housenumber":"12",
    "addr:postcode":"5150",
    "addr:street":"Rue Riverre",
    "iso:country":"BE",
    "sg:address":"Rue Riverre 12",
    "sg:city":"Floreffe",
    "sg:orig_category":"Dakwerken Loodgieterij, verwarming and sanitaire installaties Woningbouw",
    "sg:phone":"+32 81 44 02 18",
    "sg:postcode":"5150",
    "sg:province":"Namur",
    "wof:name":"Brahy",
    "wof:placetype":"venue"
},
  "geometry": {"coordinates":[4.7786278725,50.4420928955],"type":"Point"}
}