{
  "type": "Feature",
  "properties": {
    "iso:country":"BE",
    "sg:address":"Rue Des Pr\u00c9s Du Roy 17",
    "sg:city":"Ath",
    "sg:orig_category":"Entretien and r\u00e9parations de voitures",
    "sg:phone":"+32 68 26 41 41",
    "sg:postcode":"7800",
    "sg:province":"Hainaut",
    "wof:name":"Avip Sa",
    "wof:placetype":"venue"
},
  "geometry": {"coordinates":[3.7815699577,50.6391296387],"type":"Point"}
}