{
  "type": "Feature",
  "properties": {
    "iso:country":"BE",
    "sg:address":"Burchtdam 39",
    "sg:city":"Ninove",
    "sg:orig_category":"Huisdieren and benodigdheden Royal Canin",
    "sg:phone":"+32 54 34 21 51",
    "sg:postcode":"9400",
    "sg:province":"Oost-Vlaanderen",
    "wof:name":"Cauwenberghs",
    "wof:placetype":"venue"
},
  "geometry": {"coordinates":[4.0234909058,50.8336372375],"type":"Point"}
}