{
  "type": "Feature",
  "properties": {
    "addr:full":"Stationsstraat 46 Aalter Oost-Vlaanderen 9880",
    "addr:housenumber":"46",
    "addr:postcode":"9880",
    "addr:street":"Stationsstraat",
    "iso:country":"BE",
    "sg:address":"Stationsstraat 46",
    "sg:city":"Aalter",
    "sg:classifiers":[
        {
            "category":"Shopping",
            "subcategory":"Clothing, Apparel, & Fashions",
            "type":"Retail Goods"
        }
    ],
    "sg:phone":"+32 9 325 05 50",
    "sg:postcode":"9880",
    "sg:province":"Oost-Vlaanderen",
    "sg:tags":[
        "boutique"
    ],
    "wof:name":"Mady Boetiek",
    "wof:placetype":"venue"
},
  "geometry": {"coordinates":[3.4481730461,51.0855445862],"type":"Point"}
}