{
  "type": "Feature",
  "properties": {
    "iso:country":"BE",
    "sg:address":"Overheet 27",
    "sg:city":"Berlare",
    "sg:orig_category":"Eleveurs de bovins",
    "sg:phone":"+32 52 42 32 73",
    "sg:postcode":"9290",
    "sg:province":"Oost-Vlaanderen",
    "wof:name":"Raymond De Backer",
    "wof:placetype":"venue"
},
  "geometry": {"coordinates":[4.0172657967,51.0144577026],"type":"Point"}
}