{
  "type": "Feature",
  "properties": {
    "iso:country":"BE",
    "sg:address":"Rue Des Arquebusiers",
    "sg:city":"Grace-hollogne",
    "sg:orig_category":"Ordinateurs and \u00e9quipement informatique",
    "sg:phone":"+32 65 40 11 19",
    "sg:postcode":"7000",
    "sg:province":"Hainaut",
    "wof:name":"La Solution Logicielle",
    "wof:placetype":"venue"
},
  "geometry": {"coordinates":[3.9522509575,50.4547271729],"type":"Point"}
}