{
  "type": "Feature",
  "properties": {
    "addr:full":"Chauss\u00e9e De Mons 354 Tubize Brabant Wallon 1480",
    "addr:housenumber":"354",
    "addr:postcode":"1480",
    "addr:street":"Chausse\u0301E De Mons;Wallon",
    "iso:country":"BE",
    "sg:address":"Chauss\u00e9e De Mons 354",
    "sg:city":"Tubize",
    "sg:classifiers":[
        {
            "category":"Health Services",
            "subcategory":"Dentist",
            "type":"Services"
        }
    ],
    "sg:phone":"+32 2 355 92 21",
    "sg:postcode":"1480",
    "sg:province":"Brabant Wallon",
    "wof:name":"Dubois Anne",
    "wof:placetype":"venue"
},
  "geometry": {"coordinates":[4.1934452057,50.6817970276],"type":"Point"}
}