{
  "type": "Feature",
  "properties": {
    "iso:country":"BE",
    "sg:address":"Rue Haute 1",
    "sg:city":"Ath",
    "sg:classifiers":[
        {
            "category":"Shopping",
            "subcategory":"Clothing, Apparel, & Fashions",
            "type":"Retail Goods"
        }
    ],
    "sg:phone":"+32 68 55 32 73",
    "sg:postcode":"7800",
    "sg:province":"Hainaut",
    "sg:tags":[
        "boutique"
    ],
    "wof:name":"Sable Mer",
    "wof:placetype":"venue"
},
  "geometry": {"coordinates":[3.7796800137,50.6299514771],"type":"Point"}
}