{
  "type": "Feature",
  "properties": {
    "addr:full":"Leuvensesteenweg 387 Schaarbeek/schaerbeek Bruxelles-Capitale 1030",
    "addr:housenumber":"387",
    "addr:postcode":"1030",
    "addr:street":"Leuvensesteenweg",
    "iso:country":"BE",
    "sg:address":"Leuvensesteenweg 387",
    "sg:city":"Schaarbeek/schaerbeek",
    "sg:orig_category":"Onderhoud van kantoor- and computeruitrusting",
    "sg:phone":"+32 2 736 60 47",
    "sg:postcode":"1030",
    "sg:province":"Bruxelles-Capitale",
    "wof:name":"Inform. D\u00c9pannage Express",
    "wof:placetype":"venue"
},
  "geometry": {"coordinates":[4.3908491135,50.8533172607],"type":"Point"}
}