{
  "type": "Feature",
  "properties": {
    "iso:country":"BE",
    "sg:address":"Onze-lieve-vrouwstraat 12",
    "sg:city":"Heers",
    "sg:orig_category":"Producteurs de fruits",
    "sg:phone":"+32 12 74 27 98",
    "sg:postcode":"3870",
    "sg:province":"Limburg",
    "wof:name":"Lambie Eric & Eugeen",
    "wof:placetype":"venue"
},
  "geometry": {"coordinates":[5.3731789589,50.7584724426],"type":"Point"}
}