{
  "type": "Feature",
  "properties": {
    "addr:full":"Diestersteenweg 374 Nieuwerkerken Limburg 3850",
    "addr:housenumber":"374",
    "addr:postcode":"3850",
    "addr:street":"Diestersteenweg",
    "iso:country":"BE",
    "sg:address":"Diestersteenweg 374",
    "sg:city":"Nieuwerkerken",
    "sg:orig_category":"Afbraak- and draineerwerken",
    "sg:phone":"+32 11 68 91 40",
    "sg:postcode":"3850",
    "sg:province":"Limburg",
    "wof:name":"Grondwerken Vanderspikken",
    "wof:placetype":"venue"
},
  "geometry": {"coordinates":[5.1844978333,50.8808822632],"type":"Point"}
}