{
  "type": "Feature",
  "properties": {
    "iso:country":"BE",
    "sg:address":"Kolvestraat 4",
    "sg:city":"Brugge",
    "sg:orig_category":"Fish, Frozen",
    "sg:phone":"+32 50 45 85 85",
    "sg:postcode":"8000",
    "sg:province":"West-Vlaanderen",
    "wof:name":"Pieters Visbedrijf Nv",
    "wof:placetype":"venue"
},
  "geometry": {"coordinates":[3.1987900734,51.2418899536],"type":"Point"}
}