{
  "type": "Feature",
  "properties": {
    "addr:full":"Voorzorgsstraat 56 Brussel/bruxelles Bruxelles-Capitale 1000",
    "addr:housenumber":"56",
    "addr:postcode":"1000",
    "addr:street":"Voorzorgsstraat;/",
    "iso:country":"BE",
    "sg:address":"Voorzorgsstraat 56",
    "sg:city":"Brussel/bruxelles",
    "sg:orig_category":"Diverse organisaties and verenigingen Maatschappelijke dienstverlening",
    "sg:phone":"+32 2 512 73 60",
    "sg:postcode":"1000",
    "sg:province":"Bruxelles-Capitale",
    "wof:name":"Foyer Montserrat",
    "wof:placetype":"venue"
},
  "geometry": {"coordinates":[4.3510198593,50.8347206116],"type":"Point"}
}