{
  "type": "Feature",
  "properties": {
    "iso:country":"BE",
    "sg:address":"Gezellenlaan 24",
    "sg:city":"Moorslede",
    "sg:orig_category":"Woningbouw",
    "sg:phone":"+32 56 50 30 67",
    "sg:postcode":"8890",
    "sg:province":"West-Vlaanderen",
    "wof:name":"Marcobouw",
    "wof:placetype":"venue"
},
  "geometry": {"coordinates":[3.0637769699,50.891456604],"type":"Point"}
}