{
  "type": "Feature",
  "properties": {
    "addr:full":"Boulevard D'avroy 96 Li\u00c8ge Li\u00e8ge 4000",
    "addr:housenumber":"96",
    "addr:postcode":"4000",
    "addr:street":"Boulevard D'Avroy",
    "iso:country":"BE",
    "sg:address":"Boulevard D'avroy 96",
    "sg:city":"Li\u00c8ge",
    "sg:orig_category":"Formation permanente",
    "sg:phone":"+32 4 221 37 86",
    "sg:postcode":"4000",
    "sg:province":"Li\u00e8ge",
    "wof:name":"Cours Sciences Commerc.",
    "wof:placetype":"venue"
},
  "geometry": {"coordinates":[5.5671820641,50.636390686],"type":"Point"}
}