{
  "type": "Feature",
  "properties": {
    "addr:full":"Chemin Du Lanternier 12 Lasne (plancenoit) Brabant Wallon 1380",
    "addr:housenumber":"12",
    "addr:postcode":"1380",
    "addr:street":"Chemin Du Lanternier",
    "iso:country":"BE",
    "sg:address":"Chemin Du Lanternier 12",
    "sg:city":"Lasne (plancenoit)",
    "sg:classifiers":[
        {
            "category":"Health Services",
            "subcategory":"Dentist",
            "type":"Services"
        }
    ],
    "sg:phone":"+32 2 354 54 76",
    "sg:postcode":"1380",
    "sg:province":"Brabant Wallon",
    "wof:name":"Bettens Fr\u00e9d\u00e9ric",
    "wof:placetype":"venue"
},
  "geometry": {"coordinates":[4.4286608696,50.6624031067],"type":"Point"}
}