{
  "type": "Feature",
  "properties": {
    "iso:country":"BE",
    "sg:address":"Distelstraat 40a",
    "sg:city":"Dendermonde (baasrode)",
    "sg:classifiers":[
        {
            "category":"Farming",
            "subcategory":"Livestock Farm",
            "type":"Manufacturing & Wholesale Goods"
        }
    ],
    "sg:phone":"+32 52 21 60 56",
    "sg:postcode":"9200",
    "sg:province":"Oost-Vlaanderen",
    "sg:tags":[
        "buyer"
    ],
    "wof:name":"Daelemans",
    "wof:placetype":"venue"
},
  "geometry": {"coordinates":[4.0983099937,51.0315208435],"type":"Point"}
}