{
  "type": "Feature",
  "properties": {
    "addr:full":"Rue Emile Tilman 24 Herstal Li\u00e8ge 4040",
    "addr:housenumber":"24",
    "addr:postcode":"4040",
    "addr:street":"Rue Emile Tilman",
    "iso:country":"BE",
    "sg:address":"Rue Emile Tilman 24",
    "sg:city":"Herstal",
    "sg:classifiers":[
        {
            "category":"Professional",
            "subcategory":"Engineering",
            "type":"Services"
        }
    ],
    "sg:phone":"+32 4 240 33 12",
    "sg:postcode":"4040",
    "sg:province":"Li\u00e8ge",
    "sg:tags":[
        "precision"
    ],
    "wof:name":"Menendez M\u00e9canique",
    "wof:placetype":"venue"
},
  "geometry": {"coordinates":[5.6369409561,50.6695480347],"type":"Point"}
}