{
  "type": "Feature",
  "properties": {
    "iso:country":"BE",
    "sg:address":"Kleine Essestraat 14",
    "sg:city":"Lichtervelde",
    "sg:orig_category":"Rundveehouders",
    "sg:phone":"+32 51 72 25 23",
    "sg:postcode":"8810",
    "sg:province":"West-Vlaanderen",
    "wof:name":"Roger Vanslambrouck",
    "wof:placetype":"venue"
},
  "geometry": {"coordinates":[3.1368041039,51.0297775269],"type":"Point"}
}