{
  "type": "Feature",
  "properties": {
    "iso:country":"BE",
    "sg:address":"Isabellalei 136",
    "sg:city":"Antwerpen",
    "sg:classifiers":[
        {
            "category":"Bars & Pubs",
            "type":"Food & Drink"
        }
    ],
    "sg:phone":"+32 3 281 55 25",
    "sg:postcode":"2018",
    "sg:province":"Antwerpen",
    "wof:name":"Den Yzer-kroeg",
    "wof:placetype":"venue"
},
  "geometry": {"coordinates":[4.4189829826,51.2023582458],"type":"Point"}
}