{
  "type": "Feature",
  "properties": {
    "iso:country":"BE",
    "sg:address":"Markt",
    "sg:city":"Oudenaarde",
    "sg:classifiers":[
        {
            "category":"Fast Food",
            "type":"Food & Drink"
        }
    ],
    "sg:phone":"+32 55 31 01 00",
    "sg:postcode":"9700",
    "sg:province":"Oost-Vlaanderen",
    "sg:tags":[
        "fried",
        "stand",
        "potato"
    ],
    "wof:name":"Louis",
    "wof:placetype":"venue"
},
  "geometry": {"coordinates":[3.6039299965,50.8436508179],"type":"Point"}
}