{
  "type": "Feature",
  "properties": {
    "iso:country":"BE",
    "sg:address":"Bostsestraat 2b2",
    "sg:city":"Tienen",
    "sg:orig_category":"Slagers",
    "sg:phone":"+32 16 81 11 78",
    "sg:postcode":"3300",
    "sg:province":"Vlaams-Brabant",
    "wof:name":"Jean Morren",
    "wof:placetype":"venue"
},
  "geometry": {"coordinates":[4.9403448105,50.8032188416],"type":"Point"}
}