{
  "type": "Feature",
  "properties": {
    "iso:country":"BE",
    "sg:address":"Turnhoutsebaan 142",
    "sg:city":"Schilde",
    "sg:classifiers":[
        {
            "category":"Personal",
            "subcategory":"Beauty Salon",
            "type":"Services"
        }
    ],
    "sg:phone":"+32 3 385 17 77",
    "sg:postcode":"2970",
    "sg:province":"Antwerpen",
    "sg:tags":[
        "de",
        "coiffure"
    ],
    "wof:name":"Coiffure Sank\u00c9",
    "wof:placetype":"venue"
},
  "geometry": {"coordinates":[4.5731987953,51.2368087769],"type":"Point"}
}