{
  "type": "Feature",
  "properties": {
    "addr:full":"Victor Van Paepeghemstr. 1 Sint-pieters-leeuw Vlaams-Brabant 1600",
    "addr:housenumber":"1",
    "addr:postcode":"1600",
    "addr:street":"Victor Van Paepeghemstr.",
    "iso:country":"BE",
    "sg:address":"Victor Van Paepeghemstr. 1",
    "sg:city":"Sint-pieters-leeuw",
    "sg:orig_category":"Mat\u00e9riaux de construction Gr",
    "sg:phone":"+32 2 378 31 96",
    "sg:postcode":"1600",
    "sg:province":"Vlaams-Brabant",
    "wof:name":"Materia",
    "wof:placetype":"venue"
},
  "geometry": {"coordinates":[4.2932128906,50.79945755],"type":"Point"}
}