{
  "type": "Feature",
  "properties": {
    "iso:country":"BE",
    "sg:address":"Rue Barre Saint-brice 4",
    "sg:city":"Tournai",
    "sg:classifiers":[
        {
            "category":"Professional",
            "subcategory":"Lawyer & Legal Services",
            "type":"Services"
        }
    ],
    "sg:phone":"+32 69 84 74 05",
    "sg:postcode":"7500",
    "sg:province":"Hainaut",
    "wof:name":"De Ceuninck Vincent",
    "wof:placetype":"venue"
},
  "geometry": {"coordinates":[3.3944349289,50.6077575684],"type":"Point"}
}