{
  "type": "Feature",
  "properties": {
    "iso:country":"BE",
    "sg:address":"Rue Augustin Berger 105",
    "sg:city":"Chapelle-lez-herlaimont",
    "sg:orig_category":"Artiesten and kunstenaars",
    "sg:phone":"+32 71 54 20 52",
    "sg:postcode":"7160",
    "sg:province":"Hainaut",
    "wof:name":"Maurice Roels",
    "wof:placetype":"venue"
},
  "geometry": {"coordinates":[4.2934608459,50.4363555908],"type":"Point"}
}