{
  "type": "Feature",
  "properties": {
    "addr:full":"Rue Eloy 86 Anderlecht/anderlecht Bruxelles-Capitale 1070",
    "addr:housenumber":"86",
    "addr:postcode":"1070",
    "addr:street":"Rue Eloy",
    "iso:country":"BE",
    "sg:address":"Rue Eloy 86",
    "sg:city":"Anderlecht/anderlecht",
    "sg:orig_category":"M\u00e9decins and sp\u00e9cialistes",
    "sg:phone":"+32 2 523 36 74",
    "sg:postcode":"1070",
    "sg:province":"Bruxelles-Capitale",
    "wof:name":"Basaula Lusinga",
    "wof:placetype":"venue"
},
  "geometry": {"coordinates":[4.3266940117,50.8360786438],"type":"Point"}
}