{
  "type": "Feature",
  "properties": {
    "iso:country":"BE",
    "sg:address":"Rue Hov\u00e9mont 29",
    "sg:city":"Theux",
    "sg:classifiers":[
        {
            "category":"Personal",
            "subcategory":"Barber",
            "type":"Services"
        }
    ],
    "sg:phone":"+32 87 53 07 23",
    "sg:postcode":"4910",
    "sg:province":"Li\u00e8ge",
    "sg:tags":[
        "gentleman",
        "salon",
        "-",
        "hairdressing"
    ],
    "wof:name":"Volume 5",
    "wof:placetype":"venue"
},
  "geometry": {"coordinates":[5.8145670891,50.5338592529],"type":"Point"}
}