{
  "type": "Feature",
  "properties": {
    "iso:country":"BE",
    "sg:address":"Boulevard Du Nord 19",
    "sg:city":"Namur",
    "sg:classifiers":[
        {
            "category":"Restaurant",
            "type":"Food & Drink"
        }
    ],
    "sg:phone":"+32 81 22 32 56",
    "sg:postcode":"5000",
    "sg:province":"Namur",
    "wof:name":"Le Temps Pr\u00c9sent",
    "wof:placetype":"venue"
},
  "geometry": {"coordinates":[4.8634161949,50.4702224731],"type":"Point"}
}