{
  "type": "Feature",
  "properties": {
    "iso:country":"BE",
    "sg:address":"Mangelaarstraat 10",
    "sg:city":"Langemark-poelkapelle",
    "sg:orig_category":"Woningbouw",
    "sg:phone":"+32 57 48 73 11",
    "sg:postcode":"8920",
    "sg:province":"West-Vlaanderen",
    "wof:name":"Georges Vanbecelaere",
    "wof:placetype":"venue"
},
  "geometry": {"coordinates":[2.9088830948,50.9347381592],"type":"Point"}
}