{
  "type": "Feature",
  "properties": {
    "addr:full":"Place Camille Dessart 11 Charleroi Hainaut 6030",
    "addr:housenumber":"11",
    "addr:postcode":"6030",
    "addr:street":"Place Camille Dessart;Hainaut",
    "iso:country":"BE",
    "sg:address":"Place Camille Dessart 11",
    "sg:city":"Charleroi",
    "sg:orig_category":"Supermarch\u00e9s",
    "sg:phone":"+32 71 51 66 91",
    "sg:postcode":"6030",
    "sg:province":"Hainaut",
    "wof:name":"Francesca Piccicuto",
    "wof:placetype":"venue"
},
  "geometry": {"coordinates":[4.3911681175,50.4025154114],"type":"Point"}
}