{
  "type": "Feature",
  "properties": {
    "iso:country":"BE",
    "sg:address":"Avenue Du Luxembourg 62",
    "sg:city":"Li\u00c8ge",
    "sg:orig_category":"Geluidsopnames",
    "sg:phone":"+32 4 341 19 09",
    "sg:postcode":"4020",
    "sg:province":"Li\u00e8ge",
    "wof:name":"Digital Studio Live",
    "wof:placetype":"venue"
},
  "geometry": {"coordinates":[5.5885300636,50.6222076416],"type":"Point"}
}