{
  "type": "Feature",
  "properties": {
    "iso:country":"BE",
    "sg:address":"Bergstraat 8",
    "sg:city":"Lovendegem (vinderhoute)",
    "sg:classifiers":[
        {
            "category":"Health Services",
            "subcategory":"Nursing And Care Facility",
            "type":"Services"
        }
    ],
    "sg:phone":"+32 9 227 85 45",
    "sg:postcode":"9921",
    "sg:province":"Oost-Vlaanderen",
    "sg:tags":[
        "home"
    ],
    "wof:name":"D'hooge",
    "wof:placetype":"venue"
},
  "geometry": {"coordinates":[3.6368219852,51.086769104],"type":"Point"}
}