{
  "type": "Feature",
  "properties": {
    "addr:full":"Chemin De Mons 15 Morlanwelz Hainaut 7140",
    "addr:housenumber":"15",
    "addr:postcode":"7140",
    "addr:street":"Chemin De Mons",
    "iso:country":"BE",
    "sg:address":"Chemin De Mons 15",
    "sg:city":"Morlanwelz",
    "sg:orig_category":"Rundveehouders",
    "sg:phone":"+32 64 44 49 77",
    "sg:postcode":"7140",
    "sg:province":"Hainaut",
    "wof:name":"Marcel Tiels",
    "wof:placetype":"venue"
},
  "geometry": {"coordinates":[4.2304577827,50.4462890625],"type":"Point"}
}