{
  "type": "Feature",
  "properties": {
    "iso:country":"BE",
    "sg:address":"Eksaarde Dorp 75",
    "sg:city":"Lokeren (eksaarde)",
    "sg:classifiers":[
        {
            "category":"Shopping",
            "subcategory":"Clothing, Apparel, & Fashions",
            "type":"Retail Goods"
        }
    ],
    "sg:phone":"+32 9 346 64 18",
    "sg:postcode":"9160",
    "sg:province":"Oost-Vlaanderen",
    "sg:tags":[
        "underwear",
        "lingerie",
        "-"
    ],
    "wof:name":"Liemar",
    "wof:placetype":"venue"
},
  "geometry": {"coordinates":[3.9637210369,51.1180648804],"type":"Point"}
}