{
  "type": "Feature",
  "properties": {
    "addr:full":"Le Petit Val 270 Attert (tontelange) Luxembourg 6717",
    "addr:housenumber":"270",
    "addr:postcode":"6717",
    "addr:street":"Attert Tontelange",
    "iso:country":"BE",
    "sg:address":"Le Petit Val 270",
    "sg:city":"Attert (tontelange)",
    "sg:classifiers":[
        {
            "category":"Health Services",
            "subcategory":"Doctor",
            "type":"Services"
        }
    ],
    "sg:phone":"+32 63 22 26 28",
    "sg:postcode":"6717",
    "sg:province":"Luxembourg",
    "sg:tags":[
        "medicinephysicians",
        "surgeon"
    ],
    "wof:name":"Emonts M",
    "wof:placetype":"venue"
},
  "geometry": {"coordinates":[5.8098068237,49.7270698547],"type":"Point"}
}