{
  "type": "Feature",
  "properties": {
    "iso:country":"BE",
    "sg:address":"Pas 121",
    "sg:city":"Geel",
    "sg:orig_category":"Pain, p\u00e2tisseries and confiseries",
    "sg:phone":"+32 14 58 57 28",
    "sg:postcode":"2440",
    "sg:province":"Antwerpen",
    "wof:name":"Sweat Heart",
    "wof:placetype":"venue"
},
  "geometry": {"coordinates":[4.988134861,51.15832901],"type":"Point"}
}