{
  "type": "Feature",
  "properties": {
    "addr:full":"Rue De Godinry 2 Hamoir (filot) Li\u00e8ge 4181",
    "addr:housenumber":"2",
    "addr:postcode":"4181",
    "addr:street":"Rue De Godinry;Filot",
    "iso:country":"BE",
    "sg:address":"Rue De Godinry 2",
    "sg:city":"Hamoir (filot)",
    "sg:classifiers":[
        {
            "category":"Building & Trades",
            "subcategory":"Pest Control",
            "type":"Services"
        }
    ],
    "sg:phone":"+32 86 38 84 37",
    "sg:postcode":"4181",
    "sg:province":"Li\u00e8ge",
    "sg:tags":[
        "painting",
        "contractor"
    ],
    "wof:name":"Decojiell",
    "wof:placetype":"venue"
},
  "geometry": {"coordinates":[5.5691680908,50.4253540039],"type":"Point"}
}