{
  "type": "Feature",
  "properties": {
    "addr:full":"Hugo Verrieststraat 35 Ichtegem West-Vlaanderen 8480",
    "addr:housenumber":"35",
    "addr:postcode":"8480",
    "addr:street":"Hugo Verrieststraat",
    "iso:country":"BE",
    "sg:address":"Hugo Verrieststraat 35",
    "sg:city":"Ichtegem",
    "sg:orig_category":"Boucheries",
    "sg:phone":"+32 51 58 04 53",
    "sg:postcode":"8480",
    "sg:province":"West-Vlaanderen",
    "wof:name":"Rik Vandendriessche",
    "wof:placetype":"venue"
},
  "geometry": {"coordinates":[3.0131340027,51.0947799683],"type":"Point"}
}