{
  "type": "Feature",
  "properties": {
    "addr:full":"Rijksweg 762 Dilsen-stokkem (dilsen) Limburg 3650",
    "addr:housenumber":"762",
    "addr:postcode":"3650",
    "addr:street":"Rijksweg",
    "iso:country":"BE",
    "sg:address":"Rijksweg 762",
    "sg:city":"Dilsen-stokkem (dilsen)",
    "sg:classifiers":[
        {
            "category":"Retail",
            "subcategory":"Auto Repair",
            "type":"Services"
        }
    ],
    "sg:phone":"+32 89 75 40 60",
    "sg:postcode":"3650",
    "sg:province":"Limburg",
    "sg:tags":[
        "garage"
    ],
    "wof:name":"Willems-nies Nv",
    "wof:placetype":"venue"
},
  "geometry": {"coordinates":[5.7348308563,51.0439147949],"type":"Point"}
}