{
  "type": "Feature",
  "properties": {
    "addr:full":"Chera De La Gombe 28 Esneux Li\u00e8ge 4130",
    "addr:housenumber":"28",
    "addr:postcode":"4130",
    "iso:country":"BE",
    "sg:address":"Chera De La Gombe 28",
    "sg:city":"Esneux",
    "sg:classifiers":[
        {
            "category":"Personal",
            "subcategory":"Beauty Salon",
            "type":"Services"
        }
    ],
    "sg:phone":"+32 4 380 08 39",
    "sg:postcode":"4130",
    "sg:province":"Li\u00e8ge",
    "sg:tags":[
        "de",
        "coiffure"
    ],
    "wof:name":"Martine Berger",
    "wof:placetype":"venue"
},
  "geometry": {"coordinates":[5.5725259781,50.512096405],"type":"Point"}
}