{
  "type": "Feature",
  "properties": {
    "addr:full":"Legen Heirweg 15 Gavere Oost-Vlaanderen 9890",
    "addr:housenumber":"15",
    "addr:postcode":"9890",
    "addr:street":"Legen Heirweg",
    "iso:country":"BE",
    "sg:address":"Legen Heirweg 15",
    "sg:city":"Gavere",
    "sg:orig_category":"Articles de jardin",
    "sg:phone":"+32 9 384 25 89",
    "sg:postcode":"9890",
    "sg:province":"Oost-Vlaanderen",
    "wof:name":"Garden Machinery",
    "wof:placetype":"venue"
},
  "geometry": {"coordinates":[3.6459670067,50.9331588745],"type":"Point"}
}