{
  "type": "Feature",
  "properties": {
    "iso:country":"BE",
    "sg:address":"Deerlijksesteenweg 11",
    "sg:city":"Harelbeke",
    "sg:orig_category":"Alternatieve geneeskunde",
    "sg:phone":"+32 56 70 40 03",
    "sg:postcode":"8530",
    "sg:province":"West-Vlaanderen",
    "wof:name":"Marie-ann Belaen",
    "wof:placetype":"venue"
},
  "geometry": {"coordinates":[3.3214221001,50.8595924377],"type":"Point"}
}