{
  "type": "Feature",
  "properties": {
    "iso:country":"BE",
    "sg:address":"Avenue Des Arts 46",
    "sg:city":"Bruxelles",
    "sg:classifiers":[
        {
            "category":"Real Estate",
            "subcategory":"Developer",
            "type":"Services"
        }
    ],
    "sg:phone":"+32 2 550 00 30",
    "sg:postcode":"1000",
    "sg:province":"Bruxelles-Capitale",
    "sg:tags":[
        "project"
    ],
    "wof:name":"Ing Real Estate Development Belgium Sa",
    "wof:placetype":"venue"
},
  "geometry": {"coordinates":[4.3673357964,50.8423538208],"type":"Point"}
}