{
  "type": "Feature",
  "properties": {
    "iso:country":"BE",
    "sg:address":"Hei-ende 48",
    "sg:city":"Beerse",
    "sg:classifiers":[
        {
            "category":"Professional",
            "subcategory":"Management & Consulting",
            "type":"Services"
        }
    ],
    "sg:phone":"+32 3 311 71 17",
    "sg:postcode":"2340",
    "sg:province":"Antwerpen",
    "sg:tags":[
        "consultant"
    ],
    "wof:name":"Aglae Bvba",
    "wof:placetype":"venue"
},
  "geometry": {"coordinates":[4.7801380157,51.3068008423],"type":"Point"}
}