{
  "type": "Feature",
  "properties": {
    "addr:full":"R. Des Poudreries 160 Engis Li\u00e8ge 4480",
    "addr:housenumber":"160",
    "addr:postcode":"4480",
    "iso:country":"BE",
    "sg:address":"R. Des Poudreries 160",
    "sg:city":"Engis",
    "sg:classifiers":[
        {
            "category":"Manufacturing",
            "subcategory":"Chemicals & Compounds",
            "type":"Manufacturing & Wholesale Goods"
        }
    ],
    "sg:phone":"+32 4 275 10 53",
    "sg:postcode":"4480",
    "sg:province":"Li\u00e8ge",
    "sg:tags":[
        "pharmaceutical",
        "chemistry",
        "-",
        "by-product"
    ],
    "wof:name":"Nobel Explosifs Belgique Sa",
    "wof:placetype":"venue"
},
  "geometry": {"coordinates":[5.3909020424,50.5634002686],"type":"Point"}
}