{
  "type": "Feature",
  "properties": {
    "addr:full":"Groenstraat 5 Rotselaar Vlaams-Brabant 3110",
    "addr:housenumber":"5",
    "addr:postcode":"3110",
    "addr:street":"Groenstraat",
    "iso:country":"BE",
    "sg:address":"Groenstraat 5",
    "sg:city":"Rotselaar",
    "sg:orig_category":"Verplichte sociale verzekeringen",
    "sg:phone":"+32 16 44 00 10",
    "sg:postcode":"3110",
    "sg:province":"Vlaams-Brabant",
    "wof:name":"Socialist. Mutualiteit",
    "wof:placetype":"venue"
},
  "geometry": {"coordinates":[4.7095708847,50.9521713257],"type":"Point"}
}