{
  "type": "Feature",
  "properties": {
    "addr:full":"Golfln 36 Deurle Oost-Vlaanderen 9831",
    "addr:housenumber":"36",
    "addr:postcode":"9831",
    "addr:street":"Golfln;Oost-Vlaanderen",
    "iso:country":"BE",
    "sg:address":"Golfln 36",
    "sg:city":"Deurle",
    "sg:classifiers":[
        {
            "category":"Banks & Credit Unions",
            "subcategory":"Bank",
            "type":"Services"
        }
    ],
    "sg:phone":"+32 54 82 90 44",
    "sg:postcode":"9831",
    "sg:province":"Oost-Vlaanderen",
    "wof:name":"Gemeentekrediet",
    "wof:placetype":"venue"
},
  "geometry": {"coordinates":[3.6009049416,51.0073394775],"type":"Point"}
}