{
  "type": "Feature",
  "properties": {
    "addr:full":"Kriekestraat 109 Ichtegem West-Vlaanderen 8480",
    "addr:housenumber":"109",
    "addr:postcode":"8480",
    "addr:street":"Kriekestraat",
    "iso:country":"BE",
    "sg:address":"Kriekestraat 109",
    "sg:city":"Ichtegem",
    "sg:orig_category":"Rundveehouders Varkenskwekers",
    "sg:phone":"+32 59 29 95 80",
    "sg:postcode":"8480",
    "sg:province":"West-Vlaanderen",
    "wof:name":"Luc Vandaele",
    "wof:placetype":"venue"
},
  "geometry": {"coordinates":[3.0600850582,51.1267738342],"type":"Point"}
}