{
  "type": "Feature",
  "properties": {
    "addr:full":"Heppeneert 34 Maaseik Limburg 3680",
    "addr:housenumber":"34",
    "addr:postcode":"3680",
    "addr:street":"Heppeneert",
    "iso:country":"BE",
    "sg:address":"Heppeneert 34",
    "sg:city":"Maaseik",
    "sg:orig_category":"Fruitteelt",
    "sg:phone":"+32 89 56 46 11",
    "sg:postcode":"3680",
    "sg:province":"Limburg",
    "wof:name":"Michel Schroe",
    "wof:placetype":"venue"
},
  "geometry": {"coordinates":[5.7931461334,51.0718345642],"type":"Point"}
}