{
  "type": "Feature",
  "properties": {
    "addr:full":"Paanderstraat 98 Meulebeke West-Vlaanderen 8760",
    "addr:housenumber":"98",
    "addr:postcode":"8760",
    "addr:street":"Paanderstraat",
    "iso:country":"BE",
    "sg:address":"Paanderstraat 98",
    "sg:city":"Meulebeke",
    "sg:orig_category":"Agences de publicit\u00e9",
    "sg:phone":"+32 51 48 99 33",
    "sg:postcode":"8760",
    "sg:province":"West-Vlaanderen",
    "wof:name":"R.m. Graphix",
    "wof:placetype":"venue"
},
  "geometry": {"coordinates":[3.3204400539,50.9408302307],"type":"Point"}
}