{
  "type": "Feature",
  "properties": {
    "addr:full":"Industrielaan 37 Torhout West-Vlaanderen 8820",
    "addr:housenumber":"37",
    "addr:postcode":"8820",
    "addr:street":"Industrielaan",
    "iso:country":"BE",
    "sg:address":"Industrielaan 37",
    "sg:city":"Torhout",
    "sg:classifiers":[
        {
            "category":"Utilities",
            "subcategory":"Telephone",
            "type":"Services"
        }
    ],
    "sg:phone":"+32 50 21 17 61",
    "sg:postcode":"8820",
    "sg:province":"West-Vlaanderen",
    "sg:tags":[
        "telecommunication"
    ],
    "wof:name":"Anttron Nv",
    "wof:placetype":"venue"
},
  "geometry": {"coordinates":[3.1019830704,51.0760612488],"type":"Point"}
}