{
  "type": "Feature",
  "properties": {
    "iso:country":"BE",
    "sg:address":"Nederstraat 9",
    "sg:city":"Sint-pieters-leeuw (vlezenbeek)",
    "sg:classifiers":[
        {
            "category":"Building & Trades",
            "subcategory":"Landscaping Services",
            "type":"Services"
        }
    ],
    "sg:phone":"+32 2 569 49 35",
    "sg:postcode":"1602",
    "sg:province":"Vlaams-Brabant",
    "sg:tags":[
        "gardening",
        "garden",
        "maintenance"
    ],
    "wof:name":"Rampelberg B",
    "wof:placetype":"venue"
},
  "geometry": {"coordinates":[4.2362761497,50.8081512451],"type":"Point"}
}