{
  "type": "Feature",
  "properties": {
    "addr:full":"Houthoek 83 Laakdal (forest) Antwerpen 2430",
    "addr:housenumber":"83",
    "addr:postcode":"2430",
    "addr:street":"Houthoek",
    "iso:country":"BE",
    "sg:address":"Houthoek 83",
    "sg:city":"Laakdal (forest)",
    "sg:classifiers":[
        {
            "category":"Food & Beverages",
            "subcategory":"Groceries & Convenience Stores",
            "type":"Retail Goods"
        }
    ],
    "sg:phone":"+32 13 66 21 60",
    "sg:postcode":"2430",
    "sg:province":"Antwerpen",
    "sg:tags":[
        "grocer"
    ],
    "wof:name":"Superspar",
    "wof:placetype":"venue"
},
  "geometry": {"coordinates":[5.0294327736,51.0816497803],"type":"Point"}
}