{
  "type": "Feature",
  "properties": {
    "iso:country":"BE",
    "sg:address":"Elsum 133",
    "sg:city":"Geel",
    "sg:classifiers":[
        {
            "category":"Retail",
            "subcategory":"Veterinary Services",
            "type":"Services"
        }
    ],
    "sg:phone":"+32 14 58 89 88",
    "sg:postcode":"2440",
    "sg:province":"Antwerpen",
    "sg:tags":[
        "veterinarian"
    ],
    "wof:name":"Sels L",
    "wof:placetype":"venue"
},
  "geometry": {"coordinates":[4.9780840874,51.1641616821],"type":"Point"}
}