{
  "type": "Feature",
  "properties": {
    "iso:country":"BE",
    "sg:address":"Rue De Mons-lez-li\u00e8ge 376",
    "sg:city":"Fl\u00e9malle (mons-lez-li\u00e8ge)",
    "sg:classifiers":[
        {
            "category":"Professional",
            "subcategory":"Testing Lab",
            "type":"Services"
        }
    ],
    "sg:phone":"+32 4 233 91 32",
    "sg:postcode":"4400",
    "sg:province":"Li\u00e8ge",
    "sg:tags":[
        "chemist"
    ],
    "wof:name":"Brusten F",
    "wof:placetype":"venue"
},
  "geometry": {"coordinates":[5.4555940628,50.6230010986],"type":"Point"}
}