{
  "type": "Feature",
  "properties": {
    "iso:country":"BE",
    "sg:address":"Burg 13",
    "sg:city":"Brugge",
    "sg:orig_category":"Mus\u00e9es and patrimoine culturel",
    "sg:phone":"+32 50 33 71 73",
    "sg:postcode":"8000",
    "sg:province":"West-Vlaanderen",
    "wof:name":"Museum V/h Heilig Bloed",
    "wof:placetype":"venue"
},
  "geometry": {"coordinates":[3.2264978886,51.2082901001],"type":"Point"}
}