{
  "type": "Feature",
  "properties": {
    "addr:full":"Broekstraat 2 Tienen Vlaams-Brabant 3300",
    "addr:housenumber":"2",
    "addr:postcode":"3300",
    "addr:street":"Broekstraat",
    "iso:country":"BE",
    "sg:address":"Broekstraat 2",
    "sg:city":"Tienen",
    "sg:classifiers":[
        {
            "category":"Fast Food",
            "type":"Food & Drink"
        }
    ],
    "sg:phone":"+32 16 82 16 26",
    "sg:postcode":"3300",
    "sg:province":"Vlaams-Brabant",
    "sg:tags":[
        "fried",
        "stand",
        "potato"
    ],
    "wof:name":"Super Hap",
    "wof:placetype":"venue"
},
  "geometry": {"coordinates":[4.937224865,50.8064918518],"type":"Point"}
}