{
  "type": "Feature",
  "properties": {
    "addr:full":"Rue Auguste Donnay 11 Li\u00c8ge Li\u00e8ge 4000",
    "addr:housenumber":"11",
    "addr:postcode":"4000",
    "addr:street":"Rue Auguste Donnay",
    "iso:country":"BE",
    "sg:address":"Rue Auguste Donnay 11",
    "sg:city":"Li\u00c8ge",
    "sg:orig_category":"Studios photographiques",
    "sg:phone":"+32 4 225 00 44",
    "sg:postcode":"4000",
    "sg:province":"Li\u00e8ge",
    "wof:name":"Studio Tilt",
    "wof:placetype":"venue"
},
  "geometry": {"coordinates":[5.5649638176,50.6551017761],"type":"Point"}
}