{
  "type": "Feature",
  "properties": {
    "iso:country":"BE",
    "sg:address":"Rue De Robio 11",
    "sg:city":"Gedinne",
    "sg:orig_category":"Enseignement secondaire technique and professionnel. Enseignement secondaire g\u00e9n\u00e9ral",
    "sg:phone":"+32 61 58 83 52",
    "sg:postcode":"5575",
    "sg:province":"Namur",
    "wof:name":"I.n.d.",
    "wof:placetype":"venue"
},
  "geometry": {"coordinates":[4.9377169609,49.9822845459],"type":"Point"}
}