{
  "type": "Feature",
  "properties": {
    "iso:country":"BE",
    "sg:address":"Sint-jobsteenweg 124",
    "sg:city":"Schilde ('s Gravenwezel)",
    "sg:classifiers":[
        {
            "category":"Personal",
            "subcategory":"Psychics & Astrologers",
            "type":"Services"
        }
    ],
    "sg:phone":"+32 3 383 44 66",
    "sg:postcode":"2970",
    "sg:province":"Antwerpen",
    "sg:tags":[
        "astrology"
    ],
    "wof:name":"Van Hassel P",
    "wof:placetype":"venue"
},
  "geometry": {"coordinates":[4.570704937,51.2846565247],"type":"Point"}
}