{
  "type": "Feature",
  "properties": {
    "addr:full":"Steentjeslaan 25 Kontich Antwerpen 2550",
    "addr:housenumber":"25",
    "addr:postcode":"2550",
    "addr:street":"Steentjeslaan",
    "iso:country":"BE",
    "sg:address":"Steentjeslaan 25",
    "sg:city":"Kontich",
    "sg:orig_category":"Cr\u00e9meries",
    "sg:phone":"+32 3 457 09 70",
    "sg:postcode":"2550",
    "sg:province":"Antwerpen",
    "wof:name":"Jan Verhoeven",
    "wof:placetype":"venue"
},
  "geometry": {"coordinates":[4.4499249458,51.142993927],"type":"Point"}
}