{
  "type": "Feature",
  "properties": {
    "addr:full":"Schoolstraat 19 Oosterzele Oost-Vlaanderen 9860",
    "addr:housenumber":"19",
    "addr:postcode":"9860",
    "addr:street":"Schoolstraat;Oost-Vlaanderen",
    "iso:country":"BE",
    "sg:address":"Schoolstraat 19",
    "sg:city":"Oosterzele",
    "sg:orig_category":"Enseignement maternel and primaire",
    "sg:phone":"+32 9 362 50 70",
    "sg:postcode":"9860",
    "sg:province":"Oost-Vlaanderen",
    "wof:name":"Gemeentel. Lagere School",
    "wof:placetype":"venue"
},
  "geometry": {"coordinates":[3.8163099289,50.9699745178],"type":"Point"}
}