{
  "type": "Feature",
  "properties": {
    "addr:full":"Fonteinstraat 19 Haaltert Oost-Vlaanderen 9450",
    "addr:housenumber":"19",
    "addr:postcode":"9450",
    "addr:street":"Fonteinstraat",
    "iso:country":"BE",
    "sg:address":"Fonteinstraat 19",
    "sg:city":"Haaltert",
    "sg:orig_category":"Instituts de beaut\u00e9",
    "sg:phone":"+32 53 83 65 59",
    "sg:postcode":"9450",
    "sg:province":"Oost-Vlaanderen",
    "wof:name":"Esthetiek Martine",
    "wof:placetype":"venue"
},
  "geometry": {"coordinates":[4.009786129,50.8963241577],"type":"Point"}
}