{
  "type": "Feature",
  "properties": {
    "iso:country":"BE",
    "sg:address":"Lange Munteplein 7b5",
    "sg:city":"Kortrijk",
    "sg:orig_category":"Art and fournitures artistiques",
    "sg:phone":"+32 56 22 39 99",
    "sg:postcode":"8500",
    "sg:province":"West-Vlaanderen",
    "wof:name":"Randolff Rahmen Benelux",
    "wof:placetype":"venue"
},
  "geometry": {"coordinates":[3.2983949184,50.8109283447],"type":"Point"}
}