{
  "type": "Feature",
  "properties": {
    "iso:country":"BE",
    "sg:address":"Zuiderlaan 21",
    "sg:city":"Waregem",
    "sg:classifiers":[
        {
            "category":"Restaurant",
            "type":"Food & Drink"
        }
    ],
    "sg:phone":"+32 56 60 29 09",
    "sg:postcode":"8790",
    "sg:province":"West-Vlaanderen",
    "wof:name":"'t Boothuis",
    "wof:placetype":"venue"
},
  "geometry": {"coordinates":[3.4292840958,50.8815422058],"type":"Point"}
}