{
  "type": "Feature",
  "properties": {
    "iso:country":"BE",
    "sg:address":"Rue Du Commerce 2",
    "sg:city":"Marche-en-famenne",
    "sg:classifiers":[
        {
            "category":"Personal",
            "subcategory":"Beauty Salon",
            "type":"Services"
        }
    ],
    "sg:phone":"+32 84 36 72 22",
    "sg:postcode":"6900",
    "sg:province":"Luxembourg",
    "sg:tags":[
        "lady",
        "-",
        "hairdressing"
    ],
    "wof:name":"Caprice De Femmes",
    "wof:placetype":"venue"
},
  "geometry": {"coordinates":[5.3430018425,50.2273216248],"type":"Point"}
}