{
  "type": "Feature",
  "properties": {
    "addr:full":"Steenweg 587 Denderleeuw Oost-Vlaanderen 9470",
    "addr:housenumber":"587",
    "addr:postcode":"9470",
    "addr:street":"Steenweg",
    "iso:country":"BE",
    "sg:address":"Steenweg 587",
    "sg:city":"Denderleeuw",
    "sg:orig_category":"Non-Classified Establishments",
    "sg:phone":"+32 53 66 73 82",
    "sg:postcode":"9470",
    "sg:province":"Oost-Vlaanderen",
    "wof:name":"Sonck J",
    "wof:placetype":"venue"
},
  "geometry": {"coordinates":[4.0571360588,50.8711509705],"type":"Point"}
}