{
  "type": "Feature",
  "properties": {
    "addr:full":"Molstenstr. 42 Oostrozebeke West-Vlaanderen 8780",
    "addr:housenumber":"42",
    "addr:postcode":"8780",
    "addr:street":"Molstenstr.",
    "iso:country":"BE",
    "sg:address":"Molstenstr. 42",
    "sg:city":"Oostrozebeke",
    "sg:classifiers":[
        {
            "category":"Shopping",
            "subcategory":"Crafts & Fabrics",
            "type":"Retail Goods"
        }
    ],
    "sg:phone":"+32 56 67 46 46",
    "sg:postcode":"8780",
    "sg:province":"West-Vlaanderen",
    "sg:tags":[
        "textile",
        "clothing"
    ],
    "wof:name":"Ter Molst International Nv",
    "wof:placetype":"venue"
},
  "geometry": {"coordinates":[3.3476560116,50.9378318787],"type":"Point"}
}