{
  "type": "Feature",
  "properties": {
    "addr:full":"Rivierstraat 17 Laarne Oost-Vlaanderen 9270",
    "addr:housenumber":"17",
    "addr:postcode":"9270",
    "addr:street":"Rivierstraat",
    "iso:country":"BE",
    "sg:address":"Rivierstraat 17",
    "sg:city":"Laarne",
    "sg:orig_category":"Non-Classified Establishments",
    "sg:phone":"+32 9 369 06 13",
    "sg:postcode":"9270",
    "sg:province":"Oost-Vlaanderen",
    "wof:name":"Navarone Tricots",
    "wof:placetype":"venue"
},
  "geometry": {"coordinates":[3.8810999393,51.0626182556],"type":"Point"}
}