{
  "type": "Feature",
  "properties": {
    "addr:full":"Kloosterstraat 13a Mol Antwerpen 2400",
    "addr:housenumber":"13a",
    "addr:postcode":"2400",
    "addr:street":"Kloosterstraat",
    "iso:country":"BE",
    "sg:address":"Kloosterstraat 13a",
    "sg:city":"Mol",
    "sg:classifiers":[
        {
            "category":"Home & Garden",
            "subcategory":"Home Furnishings",
            "type":"Retail Goods"
        }
    ],
    "sg:phone":"+32 14 32 26 00",
    "sg:postcode":"2400",
    "sg:province":"Antwerpen",
    "sg:tags":[
        "-",
        "furniture"
    ],
    "wof:name":"Home Arts",
    "wof:placetype":"venue"
},
  "geometry": {"coordinates":[5.1196951866,51.1878585815],"type":"Point"}
}