{
  "type": "Feature",
  "properties": {
    "addr:full":"Guldensporenpark 45e Merelbeke Oost-Vlaanderen 9820",
    "addr:housenumber":"45e",
    "addr:postcode":"9820",
    "addr:street":"Guldensporenpark",
    "iso:country":"BE",
    "sg:address":"Guldensporenpark 45e",
    "sg:city":"Merelbeke",
    "sg:classifiers":[
        {
            "category":"Insurance",
            "subcategory":"Insurance Agent",
            "type":"Services"
        }
    ],
    "sg:phone":"+32 9 331 54 00",
    "sg:postcode":"9820",
    "sg:province":"Oost-Vlaanderen",
    "sg:tags":[
        "-",
        "representative"
    ],
    "wof:name":"Almarisk Nv",
    "wof:placetype":"venue"
},
  "geometry": {"coordinates":[3.7540869713,51.0058479309],"type":"Point"}
}