{
  "type": "Feature",
  "properties": {
    "iso:country":"BE",
    "sg:address":"Nati\u00ebnlaan 201",
    "sg:city":"Knokke-heist (westkapelle)",
    "sg:classifiers":[
        {
            "category":"Home & Garden",
            "subcategory":"Carpets & Floor Coverings",
            "type":"Retail Goods"
        }
    ],
    "sg:phone":"+32 50 62 29 19",
    "sg:postcode":"8300",
    "sg:province":"West-Vlaanderen",
    "sg:tags":[
        "tile"
    ],
    "wof:name":"Emex I/s Nv",
    "wof:placetype":"venue"
},
  "geometry": {"coordinates":[3.2890501022,51.3361816406],"type":"Point"}
}