{
  "type": "Feature",
  "properties": {
    "iso:country":"BE",
    "sg:address":"Kerkstraat 6",
    "sg:city":"Blankenberge",
    "sg:classifiers":[
        {
            "category":"Travel",
            "subcategory":"Hotels & Motels",
            "type":"Entertainment"
        }
    ],
    "sg:phone":"+32 50 41 93 76",
    "sg:postcode":"8370",
    "sg:province":"West-Vlaanderen",
    "wof:name":"Corner House",
    "wof:placetype":"venue"
},
  "geometry": {"coordinates":[3.1286768913,51.3157577515],"type":"Point"}
}