{
  "type": "Feature",
  "properties": {
    "addr:full":"Sint-apoloniastraat 60 Aalst Oost-Vlaanderen 9300",
    "addr:housenumber":"60",
    "addr:postcode":"9300",
    "addr:street":"Sint-Apoloniastraat",
    "iso:country":"BE",
    "sg:address":"Sint-apoloniastraat 60",
    "sg:city":"Aalst",
    "sg:classifiers":[
        {
            "category":"Arena",
            "subcategory":"Sports Club",
            "type":"Entertainment"
        }
    ],
    "sg:phone":"+32 53 77 65 42",
    "sg:postcode":"9300",
    "sg:province":"Oost-Vlaanderen",
    "sg:tags":[
        "de"
    ],
    "wof:name":"Wetterse Waterpolo",
    "wof:placetype":"venue"
},
  "geometry": {"coordinates":[4.0065479279,50.945098877],"type":"Point"}
}