{
  "type": "Feature",
  "properties": {
    "iso:country":"BE",
    "sg:address":"Kommenstraat 64",
    "sg:city":"Anderlecht/anderlecht",
    "sg:classifiers":[
        {
            "category":"Cafe",
            "type":"Food & Drink"
        }
    ],
    "sg:phone":"+32 2 523 52 54",
    "sg:postcode":"1070",
    "sg:province":"Bruxelles-Capitale",
    "sg:tags":[
        "caf\u00e9s"
    ],
    "wof:name":"Caf\u00c9 Petit Maes",
    "wof:placetype":"venue"
},
  "geometry": {"coordinates":[4.3210549355,50.8352432251],"type":"Point"}
}