{
  "type": "Feature",
  "properties": {
    "addr:full":"Chemin De Mons 51 Fleurus Hainaut 6220",
    "addr:housenumber":"51",
    "addr:postcode":"6220",
    "addr:street":"Chemin De Mons",
    "iso:country":"BE",
    "sg:address":"Chemin De Mons 51",
    "sg:city":"Fleurus",
    "sg:classifiers":[
        {
            "category":"Personal",
            "subcategory":"Nail Salon",
            "type":"Services"
        }
    ],
    "sg:phone":"+32 71 81 83 95",
    "sg:postcode":"6220",
    "sg:province":"Hainaut",
    "sg:tags":[
        "pedicure"
    ],
    "wof:name":"Vermeulen",
    "wof:placetype":"venue"
},
  "geometry": {"coordinates":[4.5543351173,50.4876365662],"type":"Point"}
}