{
  "type": "Feature",
  "properties": {
    "addr:full":"De Bolle 7 Knokke-heist West-Vlaanderen 8301",
    "addr:housenumber":"7",
    "addr:postcode":"8301",
    "addr:street":"De Bolle",
    "iso:country":"BE",
    "sg:address":"De Bolle 7",
    "sg:city":"Knokke-heist",
    "sg:classifiers":[
        {
            "category":"Restaurant",
            "type":"Food & Drink"
        }
    ],
    "sg:phone":"+32 50 51 53 66",
    "sg:postcode":"8301",
    "sg:province":"West-Vlaanderen",
    "wof:name":"Tearoom Mikado",
    "wof:placetype":"venue"
},
  "geometry": {"coordinates":[3.2639000416,51.3396911621],"type":"Point"}
}