{
  "type": "Feature",
  "properties": {
    "iso:country":"BE",
    "sg:address":"Avenue Arthur Proc\u00c8s 26",
    "sg:city":"Namur",
    "sg:orig_category":"ACCOUNTANTS Belastingconsulenten Diverse juridische dienstverlening",
    "sg:phone":"+32 81 23 10 92",
    "sg:postcode":"5000",
    "sg:province":"Namur",
    "wof:name":"Cec Rottiers & Cie",
    "wof:placetype":"venue"
},
  "geometry": {"coordinates":[4.8707480431,50.4733657837],"type":"Point"}
}