{
  "type": "Feature",
  "properties": {
    "iso:country":"BE",
    "sg:address":"Simpelstraat 2",
    "sg:city":"Kinrooi",
    "sg:orig_category":"Rundveehouders",
    "sg:phone":"+32 89 70 25 17",
    "sg:postcode":"3640",
    "sg:province":"Limburg",
    "wof:name":"Jacobus Drijkoningen",
    "wof:placetype":"venue"
},
  "geometry": {"coordinates":[5.7270560265,51.143371582],"type":"Point"}
}