{
  "type": "Feature",
  "properties": {
    "addr:full":"Boulevard G. Van Haelen 174 Bruxelles (forest) Bruxelles-Capitale 1190",
    "addr:housenumber":"174",
    "addr:postcode":"1190",
    "addr:street":"Boulevard G. Van Haelen",
    "iso:country":"BE",
    "sg:address":"Boulevard G. Van Haelen 174",
    "sg:city":"Bruxelles (forest)",
    "sg:classifiers":[
        {
            "category":"Retail",
            "subcategory":"Event Space",
            "type":"Services"
        }
    ],
    "sg:phone":"+32 475 90 75 86",
    "sg:postcode":"1190",
    "sg:province":"Bruxelles-Capitale",
    "sg:tags":[
        "organisation"
    ],
    "wof:name":"Royal Event",
    "wof:placetype":"venue"
},
  "geometry": {"coordinates":[4.3331561089,50.8235206604],"type":"Point"}
}