{
  "type": "Feature",
  "properties": {
    "addr:full":"Langestraat 72 Asse (kobbegem) Vlaams-Brabant 1730",
    "addr:housenumber":"72",
    "addr:postcode":"1730",
    "addr:street":"Langestraat",
    "iso:country":"BE",
    "sg:address":"Langestraat 72",
    "sg:city":"Asse (kobbegem)",
    "sg:classifiers":[
        {
            "category":"Autos & Motor Vehicles",
            "subcategory":"Auto Supplies",
            "type":"Retail Goods"
        }
    ],
    "sg:phone":"+32 2 453 28 80",
    "sg:postcode":"1730",
    "sg:province":"Vlaams-Brabant",
    "sg:tags":[
        "semi-trailers",
        "industrial",
        "-",
        "trailer"
    ],
    "wof:name":"Devos Transport Nv",
    "wof:placetype":"venue"
},
  "geometry": {"coordinates":[4.2366600037,50.8955802917],"type":"Point"}
}