{
  "type": "Feature",
  "properties": {
    "iso:country":"BE",
    "sg:address":"Chemin Dessus La Haye 9",
    "sg:city":"Florenville",
    "sg:classifiers":[
        {
            "category":"Retail",
            "subcategory":"Veterinary Services",
            "type":"Services"
        }
    ],
    "sg:phone":"+32 61 31 13 54",
    "sg:postcode":"6820",
    "sg:province":"Luxembourg",
    "sg:tags":[
        "veterinarian"
    ],
    "wof:name":"Gregoire C",
    "wof:placetype":"venue"
},
  "geometry": {"coordinates":[5.326417923,49.6973152161],"type":"Point"}
}