{
  "type": "Feature",
  "properties": {
    "iso:country":"BE",
    "sg:address":"Gentsesteenweg 1440",
    "sg:city":"Brussel",
    "sg:classifiers":[
        {
            "category":"Professional",
            "type":"Services"
        }
    ],
    "sg:phone":"+32 2 506 02 11",
    "sg:postcode":"1082",
    "sg:province":"Bruxelles-Capitale",
    "sg:tags":[
        "leasing"
    ],
    "wof:name":"Fortislease S.a.",
    "wof:placetype":"venue"
},
  "geometry": {"coordinates":[4.2896928787,50.8719902039],"type":"Point"}
}