{
  "type": "Feature",
  "properties": {
    "addr:full":"Rozemarijnstraat 7 Aalst Oost-Vlaanderen 9300",
    "addr:housenumber":"7",
    "addr:postcode":"9300",
    "addr:street":"Rozemarijnstraat",
    "iso:country":"BE",
    "sg:address":"Rozemarijnstraat 7",
    "sg:city":"Aalst",
    "sg:classifiers":[
        {
            "category":"Restaurant",
            "type":"Food & Drink"
        }
    ],
    "sg:phone":"+32 53 21 44 01",
    "sg:postcode":"9300",
    "sg:province":"Oost-Vlaanderen",
    "wof:name":"Anny Lenssens",
    "wof:placetype":"venue"
},
  "geometry": {"coordinates":[4.0403599739,50.9383430481],"type":"Point"}
}