{
  "type": "Feature",
  "properties": {
    "iso:country":"BE",
    "sg:address":"Glabbeekstraat 278",
    "sg:city":"Geetbets",
    "sg:classifiers":[
        {
            "category":"Wholesale",
            "subcategory":"Farm Supplies",
            "type":"Manufacturing & Wholesale Goods"
        }
    ],
    "sg:phone":"+32 11 58 74 93",
    "sg:postcode":"3450",
    "sg:province":"Vlaams-Brabant",
    "sg:tags":[
        "machine",
        "agricoles",
        "mat\u00e9riel",
        "gr"
    ],
    "wof:name":"Basile Verlaers",
    "wof:placetype":"venue"
},
  "geometry": {"coordinates":[5.0897698402,50.8750114441],"type":"Point"}
}