{
  "type": "Feature",
  "properties": {
    "addr:full":"Houtstraat 140 Brecht (sint-lenaarts) Antwerpen 2960",
    "addr:housenumber":"140",
    "addr:postcode":"2960",
    "addr:street":"Houtstraat",
    "iso:country":"BE",
    "sg:address":"Houtstraat 140",
    "sg:city":"Brecht (sint-lenaarts)",
    "sg:classifiers":[
        {
            "category":"Shopping",
            "subcategory":"Crafts & Fabrics",
            "type":"Retail Goods"
        }
    ],
    "sg:phone":"+32 3 313 44 44",
    "sg:postcode":"2960",
    "sg:province":"Antwerpen",
    "sg:tags":[
        "-",
        "wool",
        "knitting",
        "yarn"
    ],
    "wof:name":"Lea",
    "wof:placetype":"venue"
},
  "geometry": {"coordinates":[4.6415200233,51.3512115479],"type":"Point"}
}