{
  "type": "Feature",
  "properties": {
    "iso:country":"BE",
    "sg:address":"Hoogstraat 29 Box 17",
    "sg:city":"Antwerpen",
    "sg:classifiers":[
        {
            "category":"Building & Trades",
            "subcategory":"Electrical",
            "type":"Services"
        }
    ],
    "sg:phone":"+32 3 226 59 74",
    "sg:postcode":"2000",
    "sg:province":"Antwerpen",
    "sg:tags":[
        "electric",
        "-",
        "housewiring",
        "contractor"
    ],
    "wof:name":"Stefens K. Elektro",
    "wof:placetype":"venue"
},
  "geometry": {"coordinates":[4.3984270096,51.2196617126],"type":"Point"}
}