{
  "type": "Feature",
  "properties": {
    "iso:country":"BE",
    "sg:address":"Fiertelmeers 59",
    "sg:city":"Ronse/renaix",
    "sg:orig_category":"Begrafeniswezen",
    "sg:phone":"+32 55 21 37 40",
    "sg:postcode":"9600",
    "sg:province":"Oost-Vlaanderen",
    "wof:name":"Begrafenissen Devos",
    "wof:placetype":"venue"
},
  "geometry": {"coordinates":[3.5894699097,50.7541656494],"type":"Point"}
}