{
  "type": "Feature",
  "properties": {
    "addr:full":"Grand Place 13 Brugelette Hainaut 7940",
    "addr:housenumber":"13",
    "addr:postcode":"7940",
    "addr:street":"Grand Place;Hainaut",
    "iso:country":"BE",
    "sg:address":"Grand Place 13",
    "sg:city":"Brugelette",
    "sg:classifiers":[
        {
            "category":"Bars & Pubs",
            "type":"Food & Drink"
        }
    ],
    "sg:phone":"+32 68 45 58 22",
    "sg:postcode":"7940",
    "sg:province":"Hainaut",
    "wof:name":"Union (caf\u00e9 De L')",
    "wof:placetype":"venue"
},
  "geometry": {"coordinates":[3.8524410725,50.5954627991],"type":"Point"}
}