{
  "type": "Feature",
  "properties": {
    "iso:country":"BE",
    "sg:address":"Markt 13",
    "sg:city":"Lokeren",
    "sg:classifiers":[
        {
            "category":"Fast Food",
            "type":"Food & Drink"
        }
    ],
    "sg:phone":"+32 9 348 49 77",
    "sg:postcode":"9160",
    "sg:province":"Oost-Vlaanderen",
    "sg:tags":[
        "\u00c0",
        "restaurants",
        "emporter",
        "restaurant"
    ],
    "wof:name":"Restaurant Het Pleintje",
    "wof:placetype":"venue"
},
  "geometry": {"coordinates":[3.9888370037,51.1048202515],"type":"Point"}
}