{
  "type": "Feature",
  "properties": {
    "iso:country":"BE",
    "sg:address":"Leopold Ii Laan 262",
    "sg:city":"Koekelberg",
    "sg:orig_category":"Reisbureaus",
    "sg:phone":"+32 2 414 97 97",
    "sg:postcode":"1081",
    "sg:province":"Bruxelles-Capitale",
    "wof:name":"Ldk Travel Company",
    "wof:placetype":"venue"
},
  "geometry": {"coordinates":[4.3318362236,50.8625221252],"type":"Point"}
}