{
  "type": "Feature",
  "properties": {
    "addr:full":"Stationsstraat 2 Lendelede West-Vlaanderen 8860",
    "addr:housenumber":"2",
    "addr:postcode":"8860",
    "addr:street":"Stationsstraat",
    "iso:country":"BE",
    "sg:address":"Stationsstraat 2",
    "sg:city":"Lendelede",
    "sg:orig_category":"Pharmaciens",
    "sg:phone":"+32 51 30 37 52",
    "sg:postcode":"8860",
    "sg:province":"West-Vlaanderen",
    "wof:name":"Apoteek Vancoppernolle",
    "wof:placetype":"venue"
},
  "geometry": {"coordinates":[3.2388250828,50.8860321045],"type":"Point"}
}