{
  "type": "Feature",
  "properties": {
    "iso:country":"BE",
    "sg:address":"Rue De La Fraternit\u00c9 9",
    "sg:city":"Charleroi",
    "sg:orig_category":"D\u00e9molition d\u00b4immeubles and terrassements. Rev\u00eatements pour sols and murs. Plomberie, chauffage and i",
    "sg:phone":"+32 71 34 01 37",
    "sg:postcode":"6040",
    "sg:province":"Hainaut",
    "wof:name":"Michel Duliere",
    "wof:placetype":"venue"
},
  "geometry": {"coordinates":[4.4596791267,50.4421844482],"type":"Point"}
}