{
  "type": "Feature",
  "properties": {
    "iso:country":"BE",
    "sg:address":"Jan Frans Gellyncklaan 53",
    "sg:city":"Hove",
    "sg:orig_category":"Loodgieterij, verwarming and sanitaire installaties",
    "sg:phone":"+32 3 455 27 46",
    "sg:postcode":"2540",
    "sg:province":"Antwerpen",
    "wof:name":"Alex Boiy",
    "wof:placetype":"venue"
},
  "geometry": {"coordinates":[4.4649190903,51.150100708],"type":"Point"}
}