{
  "type": "Feature",
  "properties": {
    "iso:country":"BE",
    "sg:address":"Handelskaai 4",
    "sg:city":"Brussel/bruxelles",
    "sg:orig_category":"Groenten and fruit Gh",
    "sg:phone":"+32 2 217 69 58",
    "sg:postcode":"1000",
    "sg:province":"Bruxelles-Capitale",
    "wof:name":"D. Meert",
    "wof:placetype":"venue"
},
  "geometry": {"coordinates":[4.3471221924,50.8559074402],"type":"Point"}
}