{
  "type": "Feature",
  "properties": {
    "iso:country":"BE",
    "sg:address":"Mont 17",
    "sg:city":"Theux",
    "sg:classifiers":[
        {
            "category":"Shopping",
            "subcategory":"Florist",
            "type":"Retail Goods"
        }
    ],
    "sg:phone":"+32 87 53 07 14",
    "sg:postcode":"4910",
    "sg:province":"Li\u00e8ge",
    "wof:name":"Champs Fleury",
    "wof:placetype":"venue"
},
  "geometry": {"coordinates":[5.7910108566,50.5333251953],"type":"Point"}
}