{
  "type": "Feature",
  "properties": {
    "addr:full":"Chauss\u00c9e D'alsemberg 903 Braine-l'alleud Brabant Wallon 1420",
    "addr:housenumber":"903",
    "addr:postcode":"1420",
    "addr:street":"Chausse\u0301E D'Alsemberg",
    "iso:country":"BE",
    "sg:address":"Chauss\u00c9e D'alsemberg 903",
    "sg:city":"Braine-l'alleud",
    "sg:orig_category":"M\u00e9decins and sp\u00e9cialistes",
    "sg:phone":"+32 2 354 00 60",
    "sg:postcode":"1420",
    "sg:province":"Brabant Wallon",
    "wof:name":"M. Lesplingart",
    "wof:placetype":"venue"
},
  "geometry": {"coordinates":[-0.7711730003,47.3931159973],"type":"Point"}
}