{
  "type": "Feature",
  "properties": {
    "addr:full":"Arthur Boelstraat 55 Wuustwezel Antwerpen 2990",
    "addr:housenumber":"55",
    "addr:postcode":"2990",
    "addr:street":"Arthur Boelstraat",
    "iso:country":"BE",
    "sg:address":"Arthur Boelstraat 55",
    "sg:city":"Wuustwezel",
    "sg:classifiers":[
        {
            "category":"Building & Trades",
            "subcategory":"Construction",
            "type":"Services"
        }
    ],
    "sg:phone":"+32 3 633 08 07",
    "sg:postcode":"2990",
    "sg:province":"Antwerpen",
    "sg:tags":[
        "stucco",
        "contractor"
    ],
    "wof:name":"Tant G",
    "wof:placetype":"venue"
},
  "geometry": {"coordinates":[4.5503001213,51.3496818542],"type":"Point"}
}