{
  "type": "Feature",
  "properties": {
    "iso:country":"BE",
    "sg:address":"Koning Albertlaan 97",
    "sg:city":"Lanaken",
    "sg:classifiers":[
        {
            "category":"Insurance",
            "subcategory":"Insurance Agent",
            "type":"Services"
        }
    ],
    "sg:phone":"+32 89 71 65 21",
    "sg:postcode":"3620",
    "sg:province":"Limburg",
    "sg:tags":[
        "verzekeringsmakelaars",
        "expert"
    ],
    "wof:name":"Christoffels",
    "wof:placetype":"venue"
},
  "geometry": {"coordinates":[5.6558551788,50.8916435242],"type":"Point"}
}