{
  "type": "Feature",
  "properties": {
    "addr:full":"Hullestraat 16 Gavere Oost-Vlaanderen 9890",
    "addr:housenumber":"16",
    "addr:postcode":"9890",
    "addr:street":"Hullestraat",
    "iso:country":"BE",
    "sg:address":"Hullestraat 16",
    "sg:city":"Gavere",
    "sg:orig_category":"Bloemen and planten Gh",
    "sg:phone":"+32 9 384 68 99",
    "sg:postcode":"9890",
    "sg:province":"Oost-Vlaanderen",
    "wof:name":"De Baere",
    "wof:placetype":"venue"
},
  "geometry": {"coordinates":[3.6936159134,50.9370613098],"type":"Point"}
}