{
  "type": "Feature",
  "properties": {
    "iso:country":"BE",
    "sg:address":"Rue Des Moulins 9",
    "sg:city":"Gesves",
    "sg:orig_category":"Catering and organisatie van feesten",
    "sg:phone":"+32 83 67 78 34",
    "sg:postcode":"5340",
    "sg:province":"Namur",
    "wof:name":"La F\u00cate Au Palais",
    "wof:placetype":"venue"
},
  "geometry": {"coordinates":[5.0627398491,50.4047050476],"type":"Point"}
}