{
  "type": "Feature",
  "properties": {
    "iso:country":"BE",
    "sg:address":"Leuvensesteenweg 949",
    "sg:city":"Evere/evere",
    "sg:orig_category":"Benzinestations and brandstoffen",
    "sg:phone":"+32 2 726 60 72",
    "sg:postcode":"1140",
    "sg:province":"Bruxelles-Capitale",
    "wof:name":"Bp",
    "wof:placetype":"venue"
},
  "geometry": {"coordinates":[4.4208707809,50.8608016968],"type":"Point"}
}