{
  "type": "Feature",
  "properties": {
    "iso:country":"BE",
    "sg:address":"Chauss\u00c9e Napol\u00c9on 3",
    "sg:city":"Huy",
    "sg:orig_category":"D\u00e9taillants en pi\u00e8ces and accessoires de voitures. Stations-service and carburants. Entretien and r\u00e9",
    "sg:phone":"+32 85 23 09 70",
    "sg:postcode":"4500",
    "sg:province":"Li\u00e8ge",
    "wof:name":"A.c.t.",
    "wof:placetype":"venue"
},
  "geometry": {"coordinates":[5.2354421616,50.5168418884],"type":"Point"}
}