{
  "type": "Feature",
  "properties": {
    "addr:full":"Rue Jean Jacquet 63 Bruxelles (koekelberg) Bruxelles-Capitale 1081",
    "addr:housenumber":"63",
    "addr:postcode":"1081",
    "addr:street":"Rue Jean Jacquet",
    "iso:country":"BE",
    "sg:address":"Rue Jean Jacquet 63",
    "sg:city":"Bruxelles (koekelberg)",
    "sg:classifiers":[
        {
            "category":"Retail",
            "subcategory":"Auto Repair",
            "type":"Services"
        }
    ],
    "sg:phone":"+32 2 411 67 45",
    "sg:postcode":"1081",
    "sg:province":"Bruxelles-Capitale",
    "sg:tags":[
        "garage"
    ],
    "wof:name":"Station Service Goyers",
    "wof:placetype":"venue"
},
  "geometry": {"coordinates":[4.3269600868,50.8572311401],"type":"Point"}
}