{
  "type": "Feature",
  "properties": {
    "iso:country":"BE",
    "sg:address":"Rue Des Cayats 2",
    "sg:city":"Charleroi",
    "sg:orig_category":"Peinture. Rev\u00eatements pour sols and murs",
    "sg:phone":"+32 71 36 75 38",
    "sg:postcode":"6001",
    "sg:province":"Hainaut",
    "wof:name":"Henri Marique",
    "wof:placetype":"venue"
},
  "geometry": {"coordinates":[4.4380521774,50.3909645081],"type":"Point"}
}