{
  "type": "Feature",
  "properties": {
    "iso:country":"BE",
    "sg:address":"Vaartkom 3",
    "sg:city":"Leuven",
    "sg:classifiers":[
        {
            "category":"Airport",
            "subcategory":"International",
            "type":"Transportation"
        }
    ],
    "sg:phone":"+32 16 24 66 20",
    "sg:postcode":"3000",
    "sg:province":"Vlaams-Brabant",
    "sg:tags":[
        "-",
        "transport"
    ],
    "wof:name":"Dava Nv",
    "wof:placetype":"venue"
},
  "geometry": {"coordinates":[4.7008500099,50.8879165649],"type":"Point"}
}