{
  "type": "Feature",
  "properties": {
    "addr:full":"Justitiestraat 2b11 Antwerpen Antwerpen 2018",
    "addr:housenumber":"2b11",
    "addr:postcode":"2018",
    "addr:street":"Justitiestraat",
    "iso:country":"BE",
    "sg:address":"Justitiestraat 2b11",
    "sg:city":"Antwerpen",
    "sg:orig_category":"Services de recherches and bureaux de d\u00e9tectives",
    "sg:phone":"+32 3 248 70 78",
    "sg:postcode":"2018",
    "sg:province":"Antwerpen",
    "wof:name":"A.d.a. Uilenspiegel",
    "wof:placetype":"venue"
},
  "geometry": {"coordinates":[4.4076981544,51.2097625732],"type":"Point"}
}