{
  "type": "Feature",
  "properties": {
    "iso:country":"BE",
    "sg:address":"Passage De La Bourse 15-19",
    "sg:city":"Charleroi",
    "sg:classifiers":[
        {
            "category":"Shopping",
            "subcategory":"Books",
            "type":"Retail Goods"
        }
    ],
    "sg:phone":"+32 71 31 22 94",
    "sg:postcode":"6000",
    "sg:province":"Hainaut",
    "sg:tags":[
        "antiquarian",
        "trade"
    ],
    "wof:name":"Fafouille-grandchamps",
    "wof:placetype":"venue"
},
  "geometry": {"coordinates":[4.4401907921,50.4071083069],"type":"Point"}
}