{
  "type": "Feature",
  "properties": {
    "addr:full":"Zoerselsteenweg 37-39 Zoersel Antwerpen 2980",
    "addr:postcode":"37-39;2980",
    "addr:street":"Zoerselsteenweg",
    "iso:country":"BE",
    "sg:address":"Zoerselsteenweg 37-39",
    "sg:city":"Zoersel",
    "sg:orig_category":"Bois Gr. Quincailleries. Articles de jardin",
    "sg:phone":"+32 3 383 12 13",
    "sg:postcode":"2980",
    "sg:province":"Antwerpen",
    "wof:name":"All-hout",
    "wof:placetype":"venue"
},
  "geometry": {"coordinates":[4.6561508179,51.2617492676],"type":"Point"}
}