{
  "type": "Feature",
  "properties": {
    "addr:full":"Oude Mechelbaan 34bb Heist-op-den-berg Antwerpen 2220",
    "addr:housenumber":"34bb",
    "addr:postcode":"2220",
    "addr:street":"Oude Mechelbaan",
    "iso:country":"BE",
    "sg:address":"Oude Mechelbaan 34bb",
    "sg:city":"Heist-op-den-berg",
    "sg:orig_category":"Travaux de pl\u00e2trage. Quincailleries",
    "sg:phone":"+32 15 24 50 46",
    "sg:postcode":"2220",
    "sg:province":"Antwerpen",
    "wof:name":"Bezettingswerken Ditro",
    "wof:placetype":"venue"
},
  "geometry": {"coordinates":[4.7078380585,51.0770874023],"type":"Point"}
}