{
  "type": "Feature",
  "properties": {
    "iso:country":"BE",
    "sg:address":"Emiel Vermeulenstraat 115bc",
    "sg:city":"Zoersel",
    "sg:orig_category":"D\u00e9corateurs d'int\u00e9rieur",
    "sg:phone":"+32 3 385 87 81",
    "sg:postcode":"2980",
    "sg:province":"Antwerpen",
    "wof:name":"Peter Deelen",
    "wof:placetype":"venue"
},
  "geometry": {"coordinates":[4.6326470375,51.2783126831],"type":"Point"}
}