{
  "type": "Feature",
  "properties": {
    "addr:full":"Oostendelaan 304 Middelkerke West-Vlaanderen 8430",
    "addr:housenumber":"304",
    "addr:postcode":"8430",
    "addr:street":"Oostendelaan",
    "iso:country":"BE",
    "sg:address":"Oostendelaan 304",
    "sg:city":"Middelkerke",
    "sg:classifiers":[
        {
            "category":"Restaurant",
            "type":"Food & Drink"
        }
    ],
    "sg:phone":"+32 59 30 02 96",
    "sg:postcode":"8430",
    "sg:province":"West-Vlaanderen",
    "wof:name":"Cappucino",
    "wof:placetype":"venue"
},
  "geometry": {"coordinates":[2.8405580521,51.1936988831],"type":"Point"}
}