{
  "type": "Feature",
  "properties": {
    "addr:full":"Leuvensesteenweg 49 Boortmeerbeek Vlaams-Brabant 3191",
    "addr:housenumber":"49",
    "addr:postcode":"3191",
    "addr:street":"Leuvensesteenweg",
    "iso:country":"BE",
    "sg:address":"Leuvensesteenweg 49",
    "sg:city":"Boortmeerbeek",
    "sg:classifiers":[
        {
            "category":"Shopping",
            "subcategory":"Clothing, Apparel, & Fashions",
            "type":"Retail Goods"
        }
    ],
    "sg:phone":"+32 15 52 03 33",
    "sg:postcode":"3191",
    "sg:province":"Vlaams-Brabant",
    "sg:tags":[
        "v\u00eatements",
        "pour",
        "dame"
    ],
    "wof:name":"Huis Bilitis",
    "wof:placetype":"venue"
},
  "geometry": {"coordinates":[4.5361299515,50.9921760559],"type":"Point"}
}