{
  "type": "Feature",
  "properties": {
    "iso:country":"BE",
    "sg:address":"Vissersstraat 10",
    "sg:city":"Roeselare",
    "sg:classifiers":[
        {
            "category":"Building & Trades",
            "subcategory":"Landscaping Services",
            "type":"Services"
        }
    ],
    "sg:phone":"+32 51 22 21 42",
    "sg:postcode":"8800",
    "sg:province":"West-Vlaanderen",
    "sg:tags":[
        "moss",
        "removal"
    ],
    "wof:name":"Callewaert R",
    "wof:placetype":"venue"
},
  "geometry": {"coordinates":[3.1478099823,50.9405975342],"type":"Point"}
}