{
  "type": "Feature",
  "properties": {
    "iso:country":"BE",
    "sg:address":"Kraaiwinkelstraat 35",
    "sg:city":"Aalst (nieuwerkerken)",
    "sg:classifiers":[
        {
            "category":"Utilities",
            "subcategory":"Fuel Oil & Lpg",
            "type":"Services"
        }
    ],
    "sg:phone":"+32 53 83 28 43",
    "sg:postcode":"9320",
    "sg:province":"Oost-Vlaanderen",
    "wof:name":"De Rouck P",
    "wof:placetype":"venue"
},
  "geometry": {"coordinates":[4.0553851128,50.9209976196],"type":"Point"}
}