{
  "type": "Feature",
  "properties": {
    "iso:country":"BE",
    "sg:address":"Rue Du Port 106",
    "sg:city":"Saint-ghislain",
    "sg:classifiers":[
        {
            "category":"Health Services",
            "subcategory":"Health Practitioner",
            "type":"Services"
        }
    ],
    "sg:phone":"+32 65 77 72 65",
    "sg:postcode":"7330",
    "sg:province":"Hainaut",
    "sg:tags":[
        "physiotherapist"
    ],
    "wof:name":"Regnard Andr\u00e9",
    "wof:placetype":"venue"
},
  "geometry": {"coordinates":[3.815805912,50.4514694214],"type":"Point"}
}