{
  "type": "Feature",
  "properties": {
    "addr:full":"Place H\u00d4tel De Ville 18 Chatelet Hainaut 6200",
    "addr:housenumber":"18",
    "addr:postcode":"6200",
    "addr:street":"Place;Chatelet Hainaut",
    "iso:country":"BE",
    "sg:address":"Place H\u00d4tel De Ville 18",
    "sg:city":"Chatelet",
    "sg:orig_category":"Pharmaciens",
    "sg:phone":"+32 71 38 10 18",
    "sg:postcode":"6200",
    "sg:province":"Hainaut",
    "wof:name":"Martine Hoyez",
    "wof:placetype":"venue"
},
  "geometry": {"coordinates":[4.5238800049,50.403881073],"type":"Point"}
}