{
  "type": "Feature",
  "properties": {
    "addr:full":"Rue Du Fourneau 61 Florennes Namur 5620",
    "addr:housenumber":"61",
    "addr:postcode":"5620",
    "addr:street":"Rue Du Fourneau",
    "iso:country":"BE",
    "sg:address":"Rue Du Fourneau 61",
    "sg:city":"Florennes",
    "sg:orig_category":"Woningbouw",
    "sg:phone":"+32 71 68 71 83",
    "sg:postcode":"5620",
    "sg:province":"Namur",
    "wof:name":"Didier Hubert",
    "wof:placetype":"venue"
},
  "geometry": {"coordinates":[4.56650877,50.2445487976],"type":"Point"}
}