{
  "type": "Feature",
  "properties": {
    "iso:country":"BE",
    "sg:address":"Bodegemstraat 15",
    "sg:city":"Dilbeek",
    "sg:orig_category":"Metaalbehandeling and -bekleding SMEEDWERK, METAALBEWERKING AND POEDERMETALLURGIE Tuinen",
    "sg:phone":"+32 2 569 24 76",
    "sg:postcode":"1701",
    "sg:province":"Vlaams-Brabant",
    "wof:name":"Filip Notaerts",
    "wof:placetype":"venue"
},
  "geometry": {"coordinates":[4.2406058311,50.8430786133],"type":"Point"}
}