{
  "type": "Feature",
  "properties": {
    "addr:full":"Sint-amandsstraat 84-86 Roeselare West-Vlaanderen 8800",
    "addr:housenumber":"84-86",
    "addr:postcode":"8800",
    "addr:street":"Sint-Amandsstraat",
    "iso:country":"BE",
    "sg:address":"Sint-amandsstraat 84-86",
    "sg:city":"Roeselare",
    "sg:classifiers":[
        {
            "category":"Bakery",
            "type":"Food & Drink"
        }
    ],
    "sg:phone":"+32 51 20 17 54",
    "sg:postcode":"8800",
    "sg:province":"West-Vlaanderen",
    "sg:tags":[
        "confectioner",
        "baker"
    ],
    "wof:name":"Vandenbulcke",
    "wof:placetype":"venue"
},
  "geometry": {"coordinates":[3.1265850067,50.9490470886],"type":"Point"}
}