{
  "type": "Feature",
  "properties": {
    "addr:full":"Godfried Bomansstraat 1 Lommel Limburg 3920",
    "addr:housenumber":"1",
    "addr:postcode":"3920",
    "addr:street":"Godfried Bomansstraat",
    "iso:country":"BE",
    "sg:address":"Godfried Bomansstraat 1",
    "sg:city":"Lommel",
    "sg:orig_category":"Rusthuizen and serviceflats",
    "sg:phone":"+32 11 54 10 17",
    "sg:postcode":"3920",
    "sg:province":"Limburg",
    "wof:name":"Residentie Kopshoeven",
    "wof:placetype":"venue"
},
  "geometry": {"coordinates":[5.286110878,51.2273216248],"type":"Point"}
}