{
  "type": "Feature",
  "properties": {
    "iso:country":"BE",
    "sg:address":"Rue Wilson 104",
    "sg:city":"Colfontaine",
    "sg:orig_category":"Kapsalons",
    "sg:phone":"+32 65 66 51 61",
    "sg:postcode":"7340",
    "sg:province":"Hainaut",
    "wof:name":"Coiffure Ange",
    "wof:placetype":"venue"
},
  "geometry": {"coordinates":[3.8362998962,50.4121818542],"type":"Point"}
}