{
  "type": "Feature",
  "properties": {
    "iso:country":"BE",
    "sg:address":"Rue De Givet 1a",
    "sg:city":"Durbuy",
    "sg:orig_category":"Elektrische installaties voor woningen",
    "sg:phone":"+32 86 21 27 69",
    "sg:postcode":"6940",
    "sg:province":"Luxembourg",
    "wof:name":"Dominique Durdu",
    "wof:placetype":"venue"
},
  "geometry": {"coordinates":[5.4375801086,50.3374710083],"type":"Point"}
}