{
  "type": "Feature",
  "properties": {
    "iso:country":"BE",
    "sg:address":"Chauss\u00c9e Brunehault 351",
    "sg:city":"Estinnes",
    "sg:orig_category":"Architecten",
    "sg:phone":"+32 65 58 75 22",
    "sg:postcode":"7120",
    "sg:province":"Hainaut",
    "wof:name":"Philippe Beaucamp",
    "wof:placetype":"venue"
},
  "geometry": {"coordinates":[4.0733218193,50.3884010315],"type":"Point"}
}