{
  "type": "Feature",
  "properties": {
    "addr:full":"Avenue De Houffalize 25bb Libramont-chevigny Luxembourg 6800",
    "addr:housenumber":"25bb",
    "addr:postcode":"6800",
    "addr:street":"Avenue De Houffalize",
    "iso:country":"BE",
    "sg:address":"Avenue De Houffalize 25bb",
    "sg:city":"Libramont-chevigny",
    "sg:orig_category":"Herstelling leer and schoeisel",
    "sg:phone":"+32 61 23 27 67",
    "sg:postcode":"6800",
    "sg:province":"Luxembourg",
    "wof:name":"Olivier Frenoy",
    "wof:placetype":"venue"
},
  "geometry": {"coordinates":[5.3761348724,49.9199943542],"type":"Point"}
}