{
  "type": "Feature",
  "properties": {
    "addr:full":"Rue De Wand 52 Bruxelles Bruxelles-Capitale 1020",
    "addr:housenumber":"52",
    "addr:postcode":"1020",
    "addr:street":"Rue De Wand",
    "iso:country":"BE",
    "sg:address":"Rue De Wand 52",
    "sg:city":"Bruxelles",
    "sg:classifiers":[
        {
            "category":"Home & Garden",
            "subcategory":"Home Furnishings",
            "type":"Retail Goods"
        }
    ],
    "sg:phone":"+32 2 268 20 92",
    "sg:postcode":"1020",
    "sg:province":"Bruxelles-Capitale",
    "sg:tags":[
        "interior",
        "decoration"
    ],
    "wof:name":"Tout Simplement...",
    "wof:placetype":"venue"
},
  "geometry": {"coordinates":[4.3588809967,50.897983551],"type":"Point"}
}