{
  "type": "Feature",
  "properties": {
    "addr:full":"Maastrichtersteenweg 196 Tongeren Limburg 3700",
    "addr:housenumber":"196",
    "addr:postcode":"3700",
    "addr:street":"Maastrichtersteenweg",
    "iso:country":"BE",
    "sg:address":"Maastrichtersteenweg 196",
    "sg:city":"Tongeren",
    "sg:orig_category":"Drogisterijen",
    "sg:phone":"+32 12 39 40 50",
    "sg:postcode":"3700",
    "sg:province":"Limburg",
    "wof:name":"Pomme J. & Braun E.",
    "wof:placetype":"venue"
},
  "geometry": {"coordinates":[5.470510006,50.7831993103],"type":"Point"}
}