{
  "type": "Feature",
  "properties": {
    "iso:country":"BE",
    "sg:address":"Oude Mechelsebaan 150",
    "sg:city":"Aarschot",
    "sg:classifiers":[
        {
            "category":"Home & Garden",
            "subcategory":"Furniture",
            "type":"Retail Goods"
        }
    ],
    "sg:phone":"+32 16 56 70 80",
    "sg:postcode":"3200",
    "sg:province":"Vlaams-Brabant",
    "sg:tags":[
        "wood"
    ],
    "wof:name":"Schilfineer Wijns Nv",
    "wof:placetype":"venue"
},
  "geometry": {"coordinates":[4.8224868774,50.99659729],"type":"Point"}
}