{
  "type": "Feature",
  "properties": {
    "addr:full":"Steenovenstraat 27 Stekene Oost-Vlaanderen 9190",
    "addr:housenumber":"27",
    "addr:postcode":"9190",
    "addr:street":"Steenovenstraat",
    "iso:country":"BE",
    "sg:address":"Steenovenstraat 27",
    "sg:city":"Stekene",
    "sg:classifiers":[
        {
            "category":"Home & Garden",
            "subcategory":"Carpets & Floor Coverings",
            "type":"Retail Goods"
        }
    ],
    "sg:phone":"+32 3 789 14 24",
    "sg:postcode":"9190",
    "sg:province":"Oost-Vlaanderen",
    "sg:tags":[
        "tile"
    ],
    "wof:name":"De Rijck H",
    "wof:placetype":"venue"
},
  "geometry": {"coordinates":[4.0464639664,51.2007865906],"type":"Point"}
}