{
  "type": "Feature",
  "properties": {
    "iso:country":"BE",
    "sg:address":"Lombardstraat 7",
    "sg:city":"Tienen",
    "sg:classifiers":[
        {
            "category":"Insurance",
            "subcategory":"Insurance Agent",
            "type":"Services"
        }
    ],
    "sg:phone":"+32 16 82 37 94",
    "sg:postcode":"3300",
    "sg:province":"Vlaams-Brabant",
    "sg:tags":[
        "verzekeringsmakelaars",
        "expert"
    ],
    "wof:name":"Verzimmo",
    "wof:placetype":"venue"
},
  "geometry": {"coordinates":[4.9406089783,50.8038215637],"type":"Point"}
}