{
  "type": "Feature",
  "properties": {
    "addr:full":"Cuylitsstraat 64 Antwerpen Antwerpen 2018",
    "addr:housenumber":"64",
    "addr:postcode":"2018",
    "addr:street":"Cuylitsstraat",
    "iso:country":"BE",
    "sg:address":"Cuylitsstraat 64",
    "sg:city":"Antwerpen",
    "sg:classifiers":[
        {
            "category":"Professional",
            "subcategory":"Management & Consulting",
            "type":"Services"
        }
    ],
    "sg:phone":"+32 3 288 56 97",
    "sg:postcode":"2018",
    "sg:province":"Antwerpen",
    "sg:tags":[
        "consultant"
    ],
    "wof:name":"Vamas Nv",
    "wof:placetype":"venue"
},
  "geometry": {"coordinates":[4.3911390305,51.2044487],"type":"Point"}
}