{
  "type": "Feature",
  "properties": {
    "iso:country":"BE",
    "sg:address":"Spinnerslaan 9",
    "sg:city":"Lokeren",
    "sg:classifiers":[
        {
            "category":"Professional",
            "subcategory":"Management & Consulting",
            "type":"Services"
        }
    ],
    "sg:phone":"+32 9 339 13 00",
    "sg:postcode":"9160",
    "sg:province":"Oost-Vlaanderen",
    "sg:tags":[
        "consultant",
        "promotion",
        "-",
        "sale"
    ],
    "wof:name":"Promotica",
    "wof:placetype":"venue"
},
  "geometry": {"coordinates":[4.0172419548,51.1115837097],"type":"Point"}
}