{
  "type": "Feature",
  "properties": {
    "iso:country":"BE",
    "sg:address":"Rue De Sirault 36",
    "sg:city":"Jurbise (herchies)",
    "sg:classifiers":[
        {
            "category":"Building & Trades",
            "subcategory":"Landscaping Services",
            "type":"Services"
        }
    ],
    "sg:phone":"+32 65 22 70 77",
    "sg:postcode":"7050",
    "sg:province":"Hainaut",
    "sg:tags":[
        "gardening",
        "garden",
        "maintenance"
    ],
    "wof:name":"Devos B",
    "wof:placetype":"venue"
},
  "geometry": {"coordinates":[3.8382899761,50.5276298523],"type":"Point"}
}