{
  "type": "Feature",
  "properties": {
    "addr:full":"Grote Steenweg 259 Linter Vlaams-Brabant 3350",
    "addr:housenumber":"259",
    "addr:postcode":"3350",
    "addr:street":"Grote Steenweg;Vlaams-Brabant",
    "iso:country":"BE",
    "sg:address":"Grote Steenweg 259",
    "sg:city":"Linter",
    "sg:orig_category":"Banques and organismes de cr\u00e9dit",
    "sg:phone":"+32 11 78 12 65",
    "sg:postcode":"3350",
    "sg:province":"Vlaams-Brabant",
    "wof:name":"Fortis",
    "wof:placetype":"venue"
},
  "geometry": {"coordinates":[5.0468130112,50.8449363708],"type":"Point"}
}