{
  "type": "Feature",
  "properties": {
    "addr:full":"Oost-eindeken 35 Stekene Oost-Vlaanderen 9190",
    "addr:housenumber":"35",
    "addr:postcode":"9190",
    "addr:street":"Oost-Eindeken",
    "iso:country":"BE",
    "sg:address":"Oost-eindeken 35",
    "sg:city":"Stekene",
    "sg:orig_category":"Advocaten and juridische adviseurs",
    "sg:phone":"+32 3 789 18 06",
    "sg:postcode":"9190",
    "sg:province":"Oost-Vlaanderen",
    "wof:name":"Bie Verbeke",
    "wof:placetype":"venue"
},
  "geometry": {"coordinates":[4.0488939285,51.2139549255],"type":"Point"}
}