{
  "type": "Feature",
  "properties": {
    "iso:country":"BE",
    "sg:address":"Jean-baptiste Nowelei 30",
    "sg:city":"Vilvoorde",
    "sg:orig_category":"Apotheken",
    "sg:phone":"+32 2 251 23 09",
    "sg:postcode":"1800",
    "sg:province":"Vlaams-Brabant",
    "wof:name":"Pieter Van Tongelen",
    "wof:placetype":"venue"
},
  "geometry": {"coordinates":[4.4267978668,50.9291343689],"type":"Point"}
}