{
  "type": "Feature",
  "properties": {
    "addr:full":"Chauss\u00e9e De Bruxelles 412a Waterloo Brabant Wallon 1410",
    "addr:housenumber":"412a",
    "addr:postcode":"1410",
    "addr:street":"Chausse\u0301E De Bruxelles",
    "iso:country":"BE",
    "sg:address":"Chauss\u00e9e De Bruxelles 412a",
    "sg:city":"Waterloo",
    "sg:classifiers":[
        {
            "category":"Shopping",
            "subcategory":"Stationery & Office Supplies",
            "type":"Retail Goods"
        }
    ],
    "sg:phone":"+32 2 354 89 23",
    "sg:postcode":"1410",
    "sg:province":"Brabant Wallon",
    "wof:name":"Artegra Sprl",
    "wof:placetype":"venue"
},
  "geometry": {"coordinates":[4.4010419846,50.7090263367],"type":"Point"}
}