{
  "type": "Feature",
  "properties": {
    "addr:full":"Benedenstraat 5 Asse Vlaams-Brabant 1730",
    "addr:housenumber":"5",
    "addr:postcode":"1730",
    "addr:street":"Benedenstraat",
    "iso:country":"BE",
    "sg:address":"Benedenstraat 5",
    "sg:city":"Asse",
    "sg:classifiers":[
        {
            "category":"Education",
            "subcategory":"Vocational School",
            "type":"Public Place"
        }
    ],
    "sg:phone":"+32 2 453 03 99",
    "sg:postcode":"1730",
    "sg:province":"Vlaams-Brabant",
    "sg:tags":[
        "teaching",
        "material"
    ],
    "wof:name":"Katioucha",
    "wof:placetype":"venue"
},
  "geometry": {"coordinates":[4.2285032272,50.8990211487],"type":"Point"}
}