{
  "type": "Feature",
  "properties": {
    "addr:full":"Vekestraat 13b14 Antwerpen Antwerpen 2000",
    "addr:housenumber":"13b14",
    "addr:postcode":"2000",
    "addr:street":"Vekestraat",
    "iso:country":"BE",
    "sg:address":"Vekestraat 13b14",
    "sg:city":"Antwerpen",
    "sg:orig_category":"Binnenhuisarchitecten",
    "sg:phone":"+32 3 231 35 93",
    "sg:postcode":"2000",
    "sg:province":"Antwerpen",
    "wof:name":"Bureau Bataille & Ibens",
    "wof:placetype":"venue"
},
  "geometry": {"coordinates":[4.4106359482,51.2243995667],"type":"Point"}
}