{
  "type": "Feature",
  "properties": {
    "iso:country":"BE",
    "sg:address":"Donkgoeddreef 22",
    "sg:city":"Berlare",
    "sg:orig_category":"Boekhouders",
    "sg:phone":"+32 52 42 21 86",
    "sg:postcode":"9290",
    "sg:province":"Oost-Vlaanderen",
    "wof:name":"De Wilde Monique",
    "wof:placetype":"venue"
},
  "geometry": {"coordinates":[3.989317894,51.0386581421],"type":"Point"}
}