{
  "type": "Feature",
  "properties": {
    "addr:full":"Verdunstraat 417 Brussel/bruxelles Bruxelles-Capitale 1130",
    "addr:housenumber":"417",
    "addr:postcode":"1130",
    "addr:street":"Verdunstraat;/",
    "iso:country":"BE",
    "sg:address":"Verdunstraat 417",
    "sg:city":"Brussel/bruxelles",
    "sg:orig_category":"Fotografen and fotostudio's",
    "sg:phone":"+32 2 241 38 05",
    "sg:postcode":"1130",
    "sg:province":"Bruxelles-Capitale",
    "wof:name":"R.s.c.",
    "wof:placetype":"venue"
},
  "geometry": {"coordinates":[4.4178228378,50.8919067383],"type":"Point"}
}