{
  "type": "Feature",
  "properties": {
    "addr:full":"Avenue Georges-truffaut 14 Li\u00e8ge 1 (li\u00e8ge 2) Li\u00e8ge 4020",
    "addr:housenumber":"14;1;2",
    "addr:postcode":"4020",
    "addr:street":"Avenue Georges-Truffaut",
    "iso:country":"BE",
    "sg:address":"Avenue Georges-truffaut 14",
    "sg:city":"Li\u00e8ge 1 (li\u00e8ge 2)",
    "sg:classifiers":[
        {
            "category":"Shopping",
            "subcategory":"Crafts & Fabrics",
            "type":"Retail Goods"
        }
    ],
    "sg:phone":"+32 4 343 97 61",
    "sg:postcode":"4020",
    "sg:province":"Li\u00e8ge",
    "sg:tags":[
        "ceramic"
    ],
    "wof:name":"Randaxhe",
    "wof:placetype":"venue"
},
  "geometry": {"coordinates":[5.6243219376,50.6511497498],"type":"Point"}
}