{
  "type": "Feature",
  "properties": {
    "iso:country":"BE",
    "sg:address":"Marktlaan 18",
    "sg:city":"De Panne",
    "sg:classifiers":[
        {
            "category":"Health Services",
            "subcategory":"Doctor",
            "type":"Services"
        }
    ],
    "sg:phone":"+32 58 41 39 39",
    "sg:postcode":"8660",
    "sg:province":"West-Vlaanderen",
    "sg:tags":[
        "medicinephysicians",
        "surgeon"
    ],
    "wof:name":"Houbaert Alain",
    "wof:placetype":"venue"
},
  "geometry": {"coordinates":[2.594340086,51.0992698669],"type":"Point"}
}