{
  "type": "Feature",
  "properties": {
    "iso:country":"BE",
    "sg:address":"Tien Gebodensteeg 9",
    "sg:city":"Antwerpen",
    "sg:classifiers":[
        {
            "category":"Health Services",
            "subcategory":"Doctor",
            "type":"Services"
        }
    ],
    "sg:phone":"+32 486 56 47 68",
    "sg:postcode":"2060",
    "sg:province":"Antwerpen",
    "sg:tags":[
        "psychotherapist",
        "psychoanalyst"
    ],
    "wof:name":"Witpas A",
    "wof:placetype":"venue"
},
  "geometry": {"coordinates":[4.4283900261,51.2288208008],"type":"Point"}
}