{
  "type": "Feature",
  "properties": {
    "iso:country":"BE",
    "sg:address":"Riedekens 51",
    "sg:city":"Oudenaarde",
    "sg:orig_category":"Diverse bouwafwerking and reiniging",
    "sg:phone":"+32 55 31 43 87",
    "sg:postcode":"9700",
    "sg:province":"Oost-Vlaanderen",
    "wof:name":"Cedric Naert",
    "wof:placetype":"venue"
},
  "geometry": {"coordinates":[3.627022028,50.8492279053],"type":"Point"}
}