{
  "type": "Feature",
  "properties": {
    "addr:full":"Place D'isi\u00c8res 21 Ath Hainaut 7822",
    "addr:housenumber":"21",
    "addr:postcode":"7822",
    "addr:street":"Place D'Isie \u0300Res",
    "iso:country":"BE",
    "sg:address":"Place D'isi\u00c8res 21",
    "sg:city":"Ath",
    "sg:orig_category":"Enseignement maternel and primaire",
    "sg:phone":"+32 68 28 10 90",
    "sg:postcode":"7822",
    "sg:province":"Hainaut",
    "wof:name":"E.m.l. St.pierre",
    "wof:placetype":"venue"
},
  "geometry": {"coordinates":[3.8214330673,50.6619949341],"type":"Point"}
}