{
  "type": "Feature",
  "properties": {
    "iso:country":"BE",
    "sg:address":"O-l-vrouwstraat 11",
    "sg:city":"Mechelen",
    "sg:classifiers":[
        {
            "category":"Personal",
            "subcategory":"Piercing",
            "type":"Services"
        }
    ],
    "sg:phone":"+32 15 34 32 34",
    "sg:postcode":"2800",
    "sg:province":"Antwerpen",
    "sg:tags":[
        "piercings",
        "tatouages"
    ],
    "wof:name":"Tattoo-piercing Freedom",
    "wof:placetype":"venue"
},
  "geometry": {"coordinates":[4.4832692146,51.0390357971],"type":"Point"}
}