{
  "type": "Feature",
  "properties": {
    "addr:full":"Boekveldbaan 35 Aalst Oost-Vlaanderen 9310",
    "addr:housenumber":"35",
    "addr:postcode":"9310",
    "addr:street":"Boekveldbaan",
    "iso:country":"BE",
    "sg:address":"Boekveldbaan 35",
    "sg:city":"Aalst",
    "sg:orig_category":"M\u00e9decins and sp\u00e9cialistes",
    "sg:phone":"+32 53 78 14 49",
    "sg:postcode":"9310",
    "sg:province":"Oost-Vlaanderen",
    "wof:name":"M. Aelbrecht",
    "wof:placetype":"venue"
},
  "geometry": {"coordinates":[4.0988459587,50.9547386169],"type":"Point"}
}