{
  "type": "Feature",
  "properties": {
    "addr:full":"Rue Emile Vandervelde 47 Charleroi Hainaut 6032",
    "addr:housenumber":"47",
    "addr:postcode":"6032",
    "addr:street":"Rue Emile Vandervelde;Hainaut",
    "iso:country":"BE",
    "sg:address":"Rue Emile Vandervelde 47",
    "sg:city":"Charleroi",
    "sg:orig_category":"Voertuigen",
    "sg:phone":"+32 71 36 70 20",
    "sg:postcode":"6032",
    "sg:province":"Hainaut",
    "wof:name":"Leon Meurant",
    "wof:placetype":"venue"
},
  "geometry": {"coordinates":[4.4085378647,50.3970794678],"type":"Point"}
}