{
  "type": "Feature",
  "properties": {
    "iso:country":"BE",
    "sg:address":"Rue De L'abattoir 53-59",
    "sg:city":"Moeskroen",
    "sg:orig_category":"Huishoudapparaten, televisies and radio's",
    "sg:phone":"+32 56 33 00 20",
    "sg:postcode":"7700",
    "sg:province":"Hainaut",
    "wof:name":"Envirom",
    "wof:placetype":"venue"
},
  "geometry": {"coordinates":[3.2266499996,50.7569885254],"type":"Point"}
}