{
  "type": "Feature",
  "properties": {
    "addr:full":"Retiesebaan 8 Kasterlee Antwerpen 2460",
    "addr:housenumber":"8",
    "addr:postcode":"2460",
    "addr:street":"Retiesebaan",
    "iso:country":"BE",
    "sg:address":"Retiesebaan 8",
    "sg:city":"Kasterlee",
    "sg:orig_category":"Kapsalons",
    "sg:phone":"+32 14 85 07 53",
    "sg:postcode":"2460",
    "sg:province":"Antwerpen",
    "wof:name":"Maria Slegers",
    "wof:placetype":"venue"
},
  "geometry": {"coordinates":[4.9693760872,51.2408332825],"type":"Point"}
}