{
  "type": "Feature",
  "properties": {
    "addr:full":"Sint-geertruistraat 78 Box 1 Tongeren (riksingen) Limburg 3700",
    "addr:housenumber":"78;1",
    "addr:postcode":"3700",
    "addr:street":"Sint-Geertruistraat;Box",
    "iso:country":"BE",
    "sg:address":"Sint-geertruistraat 78 Box 1",
    "sg:city":"Tongeren (riksingen)",
    "sg:classifiers":[
        {
            "category":"Health Services",
            "subcategory":"Medical Lab",
            "type":"Services"
        }
    ],
    "sg:phone":"+32 12 23 48 34",
    "sg:postcode":"3700",
    "sg:province":"Limburg",
    "sg:tags":[
        "laboratory",
        "dental"
    ],
    "wof:name":"Dtb-simons M",
    "wof:placetype":"venue"
},
  "geometry": {"coordinates":[5.4532599449,50.8100891113],"type":"Point"}
}