{
  "type": "Feature",
  "properties": {
    "iso:country":"BE",
    "sg:address":"Rue De Namur 20",
    "sg:city":"Nivelles",
    "sg:classifiers":[
        {
            "category":"Banks & Credit Unions",
            "subcategory":"Bank",
            "type":"Services"
        }
    ],
    "sg:phone":"+32 67 21 69 33",
    "sg:postcode":"1400",
    "sg:province":"Brabant Wallon",
    "wof:name":"Banque Cr\u00e9dit Commercial",
    "wof:placetype":"venue"
},
  "geometry": {"coordinates":[4.3259749413,50.5982170105],"type":"Point"}
}