{
  "type": "Feature",
  "properties": {
    "iso:country":"BE",
    "sg:address":"Manchesterstraat 25bb",
    "sg:city":"Gent",
    "sg:orig_category":"Assistances juridiques. Comptables. Conseillers fiscaux",
    "sg:phone":"+32 9 251 03 40",
    "sg:postcode":"9000",
    "sg:province":"Oost-Vlaanderen",
    "wof:name":"Ivan Mercier",
    "wof:placetype":"venue"
},
  "geometry": {"coordinates":[3.7306730747,51.0786972046],"type":"Point"}
}