{
  "type": "Feature",
  "properties": {
    "iso:country":"BE",
    "sg:address":"Philippe De Denterghemlaan 14",
    "sg:city":"Sint-martens-latem (deurle)",
    "sg:classifiers":[
        {
            "category":"Health Services",
            "subcategory":"Health Practitioner",
            "type":"Services"
        }
    ],
    "sg:phone":"+32 9 282 74 08",
    "sg:postcode":"9831",
    "sg:province":"Oost-Vlaanderen",
    "sg:tags":[
        "osteopath"
    ],
    "wof:name":"Hellebaut E",
    "wof:placetype":"venue"
},
  "geometry": {"coordinates":[3.6032860279,51.0083999634],"type":"Point"}
}