{
  "type": "Feature",
  "properties": {
    "addr:full":"Rue Du Rivage 16 Ch\u00e2telet (ch\u00e2telineau) Hainaut 6200",
    "addr:housenumber":"16",
    "addr:postcode":"6200",
    "addr:street":"Rue Du Rivage",
    "iso:country":"BE",
    "sg:address":"Rue Du Rivage 16",
    "sg:city":"Ch\u00e2telet (ch\u00e2telineau)",
    "sg:classifiers":[
        {
            "category":"Building & Trades",
            "subcategory":"Construction",
            "type":"Services"
        }
    ],
    "sg:phone":"+32 71 38 29 86",
    "sg:postcode":"6200",
    "sg:province":"Hainaut",
    "sg:tags":[
        "installation",
        "-",
        "central",
        "heating"
    ],
    "wof:name":"Dereumaux P",
    "wof:placetype":"venue"
},
  "geometry": {"coordinates":[4.5217790604,50.4135131836],"type":"Point"}
}