{
  "type": "Feature",
  "properties": {
    "addr:full":"Kasteeldreef 182 Beveren Oost-Vlaanderen 9120",
    "addr:housenumber":"182",
    "addr:postcode":"9120",
    "addr:street":"Kasteeldreef",
    "iso:country":"BE",
    "sg:address":"Kasteeldreef 182",
    "sg:city":"Beveren",
    "sg:orig_category":"Artistes ind\u00e9pendants",
    "sg:phone":"+32 3 775 90 25",
    "sg:postcode":"9120",
    "sg:province":"Oost-Vlaanderen",
    "wof:name":"Ruythoorn",
    "wof:placetype":"venue"
},
  "geometry": {"coordinates":[4.2538847923,51.2212028503],"type":"Point"}
}