{
  "type": "Feature",
  "properties": {
    "addr:full":"Rue Du Chabut 19 Beauvechain Brabant Wallon 1320",
    "addr:housenumber":"19",
    "addr:postcode":"1320",
    "addr:street":"Rue Du Chabut",
    "iso:country":"BE",
    "sg:address":"Rue Du Chabut 19",
    "sg:city":"Beauvechain",
    "sg:orig_category":"Elektrische installaties voor woningen",
    "sg:phone":"+32 10 86 19 42",
    "sg:postcode":"1320",
    "sg:province":"Brabant Wallon",
    "wof:name":"Deregnoncourt",
    "wof:placetype":"venue"
},
  "geometry": {"coordinates":[4.7732748985,50.7803611755],"type":"Point"}
}