{
  "type": "Feature",
  "properties": {
    "addr:full":"Merksplassesteenweg 36 Rijkevorsel Antwerpen 2310",
    "addr:housenumber":"36",
    "addr:postcode":"2310",
    "addr:street":"Merksplassesteenweg",
    "iso:country":"BE",
    "sg:address":"Merksplassesteenweg 36",
    "sg:city":"Rijkevorsel",
    "sg:classifiers":[
        {
            "category":"Farming",
            "subcategory":"Livestock Farm",
            "type":"Manufacturing & Wholesale Goods"
        }
    ],
    "sg:phone":"+32 3 314 58 88",
    "sg:postcode":"2310",
    "sg:province":"Antwerpen",
    "sg:tags":[
        "buyer"
    ],
    "wof:name":"De Meester",
    "wof:placetype":"venue"
},
  "geometry": {"coordinates":[4.7844510078,51.3464050293],"type":"Point"}
}