{
  "type": "Feature",
  "properties": {
    "addr:full":"Bredabaan 90 Antwerpen Antwerpen 2170",
    "addr:housenumber":"90",
    "addr:postcode":"2170",
    "addr:street":"Bredabaan",
    "iso:country":"BE",
    "sg:address":"Bredabaan 90",
    "sg:city":"Antwerpen",
    "sg:orig_category":"Plaatsen van vloer- and muurbekleding Woningbouw",
    "sg:phone":"+32 3 644 35 15",
    "sg:postcode":"2170",
    "sg:province":"Antwerpen",
    "wof:name":"Jozef Merckx",
    "wof:placetype":"venue"
},
  "geometry": {"coordinates":[4.423538208,51.2341461182],"type":"Point"}
}