{
  "type": "Feature",
  "properties": {
    "addr:full":"Avenue Firmin Lecharlier 115 Bruxelles (jette) Bruxelles-Capitale 1090",
    "addr:housenumber":"115",
    "addr:postcode":"1090",
    "addr:street":"Avenue Firmin Lecharlier",
    "iso:country":"BE",
    "sg:address":"Avenue Firmin Lecharlier 115",
    "sg:city":"Bruxelles (jette)",
    "sg:classifiers":[
        {
            "category":"Personal",
            "subcategory":"Beauty Salon",
            "type":"Services"
        }
    ],
    "sg:phone":"+32 2 426 78 59",
    "sg:postcode":"1090",
    "sg:province":"Bruxelles-Capitale",
    "sg:tags":[
        "lady",
        "-",
        "hairdressing"
    ],
    "wof:name":"Clairette",
    "wof:placetype":"venue"
},
  "geometry": {"coordinates":[4.3321461678,50.869972229],"type":"Point"}
}