{
  "type": "Feature",
  "properties": {
    "iso:country":"BE",
    "sg:address":"Proeftuinstraat 6",
    "sg:city":"Gent",
    "sg:classifiers":[
        {
            "category":"Wholesale",
            "subcategory":"Meat",
            "type":"Manufacturing & Wholesale Goods"
        }
    ],
    "sg:phone":"+32 9 222 00 57",
    "sg:postcode":"9000",
    "sg:province":"Oost-Vlaanderen",
    "sg:tags":[
        "whol",
        "-"
    ],
    "wof:name":"Devreese G",
    "wof:placetype":"venue"
},
  "geometry": {"coordinates":[3.7364599705,51.0212211609],"type":"Point"}
}