{
  "type": "Feature",
  "properties": {
    "addr:full":"Rue Christophe 27 Herstal Li\u00e8ge 4040",
    "addr:housenumber":"27",
    "addr:postcode":"4040",
    "addr:street":"Rue Christophe",
    "iso:country":"BE",
    "sg:address":"Rue Christophe 27",
    "sg:city":"Herstal",
    "sg:classifiers":[
        {
            "category":"Professional",
            "subcategory":"Advertising",
            "type":"Services"
        }
    ],
    "sg:phone":"+32 4 343 44 60",
    "sg:postcode":"4040",
    "sg:province":"Li\u00e8ge",
    "sg:tags":[
        "item",
        "-",
        "business",
        "gift",
        "promotional"
    ],
    "wof:name":"General Service",
    "wof:placetype":"venue"
},
  "geometry": {"coordinates":[5.619383812,50.6675109863],"type":"Point"}
}