{
  "type": "Feature",
  "properties": {
    "addr:full":"Lamorinierestraat 236 Antwerpen Antwerpen 2018",
    "addr:housenumber":"236",
    "addr:postcode":"2018",
    "addr:street":"Lamorinierestraat",
    "iso:country":"BE",
    "sg:address":"Lamorinierestraat 236",
    "sg:city":"Antwerpen",
    "sg:orig_category":"Non-Classified Establishments",
    "sg:phone":"+32 3 230 44 32",
    "sg:postcode":"2018",
    "sg:province":"Antwerpen",
    "wof:name":"Gigue",
    "wof:placetype":"venue"
},
  "geometry": {"coordinates":[4.4174537659,51.201587677],"type":"Point"}
}