{
  "type": "Feature",
  "properties": {
    "addr:full":"Victor Govaerslaan 1 Merksem Antwerpen 2170",
    "addr:housenumber":"1",
    "addr:postcode":"2170",
    "addr:street":"Victor Govaerslaan",
    "iso:country":"BE",
    "sg:address":"Victor Govaerslaan 1",
    "sg:city":"Merksem",
    "sg:classifiers":[
        {
            "category":"Social Services",
            "subcategory":"Job Training",
            "type":"Services"
        }
    ],
    "sg:phone":"+32 3 646 42 72",
    "sg:postcode":"2170",
    "sg:province":"Antwerpen",
    "sg:tags":[
        "information",
        "business",
        "advice",
        "-",
        "technology",
        "peripheral"
    ],
    "wof:name":"Business System Team Nv",
    "wof:placetype":"venue"
},
  "geometry": {"coordinates":[4.4353108406,51.2550697327],"type":"Point"}
}