{
  "type": "Feature",
  "properties": {
    "addr:full":"Parijsstraat 51 Leuven Vlaams-Brabant 3000",
    "addr:housenumber":"51",
    "addr:postcode":"3000",
    "addr:street":"Parijsstraat",
    "iso:country":"BE",
    "sg:address":"Parijsstraat 51",
    "sg:city":"Leuven",
    "sg:classifiers":[
        {
            "category":"Restaurant",
            "type":"Food & Drink"
        }
    ],
    "sg:phone":"+32 16 22 63 24",
    "sg:postcode":"3000",
    "sg:province":"Vlaams-Brabant",
    "wof:name":"Peach Pit",
    "wof:placetype":"venue"
},
  "geometry": {"coordinates":[4.698993206,50.8780632019],"type":"Point"}
}