{
  "type": "Feature",
  "properties": {
    "iso:country":"BE",
    "sg:address":"Nijlensesteenweg 60",
    "sg:city":"Nijlen",
    "sg:classifiers":[
        {
            "category":"Arena",
            "subcategory":"Sports Club",
            "type":"Entertainment"
        }
    ],
    "sg:phone":"+32 3 481 73 10",
    "sg:postcode":"2560",
    "sg:province":"Antwerpen",
    "sg:tags":[
        "de"
    ],
    "wof:name":"Vrije Duivenbond",
    "wof:placetype":"venue"
},
  "geometry": {"coordinates":[4.6844792366,51.1403694153],"type":"Point"}
}