{
  "type": "Feature",
  "properties": {
    "iso:country":"BE",
    "sg:address":"De Valken 8",
    "sg:city":"Arendonk",
    "sg:orig_category":"Banques and organismes de cr\u00e9dit",
    "sg:phone":"+32 14 67 76 96",
    "sg:postcode":"2370",
    "sg:province":"Antwerpen",
    "wof:name":"Fortis",
    "wof:placetype":"venue"
},
  "geometry": {"coordinates":[5.0842638016,51.3200416565],"type":"Point"}
}