{
  "type": "Feature",
  "properties": {
    "addr:full":"Stationsstraat 62 Ichtegem West-Vlaanderen 8480",
    "addr:housenumber":"62",
    "addr:postcode":"8480",
    "addr:street":"Stationsstraat",
    "iso:country":"BE",
    "sg:address":"Stationsstraat 62",
    "sg:city":"Ichtegem",
    "sg:orig_category":"Banken and kredietinstellingen",
    "sg:phone":"+32 59 29 90 25",
    "sg:postcode":"8480",
    "sg:province":"West-Vlaanderen",
    "wof:name":"Dexia",
    "wof:placetype":"venue"
},
  "geometry": {"coordinates":[3.0218501091,51.1299705505],"type":"Point"}
}