{
  "type": "Feature",
  "properties": {
    "iso:country":"BE",
    "sg:address":"Kapelstraat 7",
    "sg:city":"Schilde",
    "sg:orig_category":"Salles de conf\u00e9rences and de r\u00e9ceptions",
    "sg:phone":"+32 3 383 44 06",
    "sg:postcode":"2970",
    "sg:province":"Antwerpen",
    "wof:name":"Pomona",
    "wof:placetype":"venue"
},
  "geometry": {"coordinates":[4.5781908035,51.2422523499],"type":"Point"}
}