{
  "type": "Feature",
  "properties": {
    "addr:full":"Rue Anne-croix 46 Rebecq Brabant Wallon 1430",
    "addr:housenumber":"46",
    "addr:postcode":"1430",
    "addr:street":"Rue Anne-Croix",
    "iso:country":"BE",
    "sg:address":"Rue Anne-croix 46",
    "sg:city":"Rebecq",
    "sg:orig_category":"Rundveehouders",
    "sg:phone":"+32 2 395 66 82",
    "sg:postcode":"1430",
    "sg:province":"Brabant Wallon",
    "wof:name":"Jean Dekoninck",
    "wof:placetype":"venue"
},
  "geometry": {"coordinates":[4.119849205,50.7029571533],"type":"Point"}
}