{
  "type": "Feature",
  "properties": {
    "addr:full":"Graaf Jansdijk 41 Knokke-heist West-Vlaanderen 8300",
    "addr:housenumber":"41",
    "addr:postcode":"8300",
    "addr:street":"Graaf Jansdijk",
    "iso:country":"BE",
    "sg:address":"Graaf Jansdijk 41",
    "sg:city":"Knokke-heist",
    "sg:orig_category":"Plomberie, chauffage and installations sanitaires",
    "sg:phone":"+32 50 62 54 35",
    "sg:postcode":"8300",
    "sg:province":"West-Vlaanderen",
    "wof:name":"Peter Breems",
    "wof:placetype":"venue"
},
  "geometry": {"coordinates":[3.2979021072,51.3395652771],"type":"Point"}
}