{
  "type": "Feature",
  "properties": {
    "addr:full":"Rue D'anderlecht 82 Bruxelles Bruxelles-Capitale 1000",
    "addr:housenumber":"82",
    "addr:postcode":"1000",
    "addr:street":"Rue D'Anderlecht",
    "iso:country":"BE",
    "sg:address":"Rue D'anderlecht 82",
    "sg:city":"Bruxelles",
    "sg:classifiers":[
        {
            "category":"Retail",
            "subcategory":"Laundry & Dry Cleaning",
            "type":"Services"
        }
    ],
    "sg:phone":"+32 2 513 57 47",
    "sg:postcode":"1000",
    "sg:province":"Bruxelles-Capitale",
    "sg:tags":[
        "dyer",
        "cleaner"
    ],
    "wof:name":"Spencer-shop",
    "wof:placetype":"venue"
},
  "geometry": {"coordinates":[4.3676638603,50.8506736755],"type":"Point"}
}