{
  "type": "Feature",
  "properties": {
    "iso:country":"BE",
    "sg:address":"Victor Greysonstraat 70",
    "sg:city":"Elsene/ixelles",
    "sg:orig_category":"Elektrische installaties voor woningen",
    "sg:phone":"+32 2 640 70 59",
    "sg:postcode":"1050",
    "sg:province":"Bruxelles-Capitale",
    "wof:name":"Bio-installat. Materelec",
    "wof:placetype":"venue"
},
  "geometry": {"coordinates":[4.3790049553,50.822467804],"type":"Point"}
}