{
  "type": "Feature",
  "properties": {
    "iso:country":"BE",
    "sg:address":"Avenue Georges Henri 345",
    "sg:city":"Sint-lambrechts-woluwe/woluwe-saint-lambert",
    "sg:orig_category":"Meubles D\u00e9taillants, Am\u00e9nagement de B\u00e2timents et de Cuisines. Magasins de r\u00e9parations d'articles per",
    "sg:phone":"+32 2 736 47 02",
    "sg:postcode":"1200",
    "sg:province":"Bruxelles-Capitale",
    "wof:name":"Dynatec",
    "wof:placetype":"venue"
},
  "geometry": {"coordinates":[4.4097681046,50.8429985046],"type":"Point"}
}