{
  "type": "Feature",
  "properties": {
    "iso:country":"BE",
    "sg:address":"Schoon Uitzichtlaan 69",
    "sg:city":"Ukkel/uccle",
    "sg:orig_category":"Artsen and specialisten",
    "sg:phone":"+32 2 347 58 02",
    "sg:postcode":"1180",
    "sg:province":"Bruxelles-Capitale",
    "wof:name":"H. Krutzen",
    "wof:placetype":"venue"
},
  "geometry": {"coordinates":[4.3638510704,50.81300354],"type":"Point"}
}