{
  "type": "Feature",
  "properties": {
    "addr:full":"Sint-jansbergsesteenweg 171 Heverlee Vlaams-Brabant 3001",
    "addr:housenumber":"171",
    "addr:postcode":"3001",
    "addr:street":"Sint-Jansbergsesteenweg",
    "iso:country":"BE",
    "sg:address":"Sint-jansbergsesteenweg 171",
    "sg:city":"Heverlee",
    "sg:classifiers":[
        {
            "category":"Restaurant",
            "type":"Food & Drink"
        }
    ],
    "sg:phone":"+32 16 29 69 79",
    "sg:postcode":"3001",
    "sg:province":"Vlaams-Brabant",
    "wof:name":"Couvert Couvert",
    "wof:placetype":"venue"
},
  "geometry": {"coordinates":[4.6598081589,50.8629951477],"type":"Point"}
}