{
  "type": "Feature",
  "properties": {
    "addr:full":"Ridderstraat 9 Hasselt Limburg 3500",
    "addr:housenumber":"9",
    "addr:postcode":"3500",
    "addr:street":"Ridderstraat",
    "iso:country":"BE",
    "sg:address":"Ridderstraat 9",
    "sg:city":"Hasselt",
    "sg:orig_category":"Dameskledingzaken",
    "sg:phone":"+32 11 21 35 44",
    "sg:postcode":"3500",
    "sg:province":"Limburg",
    "wof:name":"Santolina",
    "wof:placetype":"venue"
},
  "geometry": {"coordinates":[5.3361701965,50.9283752441],"type":"Point"}
}