{
  "type": "Feature",
  "properties": {
    "iso:country":"BE",
    "sg:address":"Rue Du Moulin 1",
    "sg:city":"Wasseiges",
    "sg:orig_category":"Woningbouw",
    "sg:phone":"+32 81 85 53 30",
    "sg:postcode":"4219",
    "sg:province":"Li\u00e8ge",
    "wof:name":"Espace",
    "wof:placetype":"venue"
},
  "geometry": {"coordinates":[5.0056409836,50.6210861206],"type":"Point"}
}