{
  "type": "Feature",
  "properties": {
    "addr:full":"Diksmuidsestraat 52 Ieper West-Vlaanderen 8900",
    "addr:housenumber":"52",
    "addr:postcode":"8900",
    "addr:street":"Diksmuidsestraat",
    "iso:country":"BE",
    "sg:address":"Diksmuidsestraat 52",
    "sg:city":"Ieper",
    "sg:classifiers":[
        {
            "category":"Insurance",
            "subcategory":"Insurance Agent",
            "type":"Services"
        }
    ],
    "sg:phone":"+32 57 21 80 05",
    "sg:postcode":"8900",
    "sg:province":"West-Vlaanderen",
    "sg:tags":[
        "broker"
    ],
    "wof:name":"Robyn Jan / Jrc",
    "wof:placetype":"venue"
},
  "geometry": {"coordinates":[2.8867149353,50.8535842896],"type":"Point"}
}