{
  "type": "Feature",
  "properties": {
    "addr:full":"Stationsplein 9 Tongeren Limburg 3700",
    "addr:housenumber":"9",
    "addr:postcode":"3700",
    "addr:street":"Stationsplein",
    "iso:country":"BE",
    "sg:address":"Stationsplein 9",
    "sg:city":"Tongeren",
    "sg:classifiers":[
        {
            "category":"Fast Food",
            "type":"Food & Drink"
        }
    ],
    "sg:phone":"+32 12 39 18 06",
    "sg:postcode":"3700",
    "sg:province":"Limburg",
    "sg:tags":[
        "meeneem",
        "restaurant"
    ],
    "wof:name":"Everybody",
    "wof:placetype":"venue"
},
  "geometry": {"coordinates":[5.4711661339,50.7832260132],"type":"Point"}
}