{
  "type": "Feature",
  "properties": {
    "iso:country":"BE",
    "sg:address":"Rue De La Corn\u00c9e 4",
    "sg:city":"Bertrix",
    "sg:orig_category":"Jardinage",
    "sg:phone":"+32 61 41 54 81",
    "sg:postcode":"6880",
    "sg:province":"Luxembourg",
    "wof:name":"H.f. Bontemps",
    "wof:placetype":"venue"
},
  "geometry": {"coordinates":[5.2522587776,49.860874176],"type":"Point"}
}