{
  "type": "Feature",
  "properties": {
    "addr:full":"Rue Ferrer 82 Fleurus Hainaut 6224",
    "addr:housenumber":"82",
    "addr:postcode":"6224",
    "addr:street":"Rue Ferrer",
    "iso:country":"BE",
    "sg:address":"Rue Ferrer 82",
    "sg:city":"Fleurus",
    "sg:orig_category":"Dakwerken",
    "sg:phone":"+32 71 81 00 70",
    "sg:postcode":"6224",
    "sg:province":"Hainaut",
    "wof:name":"Huysmans",
    "wof:placetype":"venue"
},
  "geometry": {"coordinates":[4.5868639946,50.4635238647],"type":"Point"}
}