{
  "type": "Feature",
  "properties": {
    "addr:full":"Rue De Wansin 5 Hannut Li\u00e8ge 4280",
    "addr:housenumber":"5",
    "addr:postcode":"4280",
    "addr:street":"Rue De Wansin",
    "iso:country":"BE",
    "sg:address":"Rue De Wansin 5",
    "sg:city":"Hannut",
    "sg:orig_category":"Machines and mat\u00e9riel agricoles Articles de jardin",
    "sg:phone":"+32 19 63 43 74",
    "sg:postcode":"4280",
    "sg:province":"Li\u00e8ge",
    "wof:name":"Green Machine",
    "wof:placetype":"venue"
},
  "geometry": {"coordinates":[5.024315834,50.6806259155],"type":"Point"}
}