{
  "type": "Feature",
  "properties": {
    "addr:full":"Riddersstraat 21 Brugge West-Vlaanderen 8000",
    "addr:housenumber":"21",
    "addr:postcode":"8000",
    "addr:street":"Riddersstraat",
    "iso:country":"BE",
    "sg:address":"Riddersstraat 21",
    "sg:city":"Brugge",
    "sg:classifiers":[
        {
            "category":"Fast Food",
            "type":"Food & Drink"
        }
    ],
    "sg:phone":"+32 50 34 30 96",
    "sg:postcode":"8000",
    "sg:province":"West-Vlaanderen",
    "sg:tags":[
        "\u00c0",
        "emporter",
        "restaurants"
    ],
    "wof:name":"Frituur Memling",
    "wof:placetype":"venue"
},
  "geometry": {"coordinates":[3.2295470238,51.209854126],"type":"Point"}
}