{
  "type": "Feature",
  "properties": {
    "addr:full":"Avenue Kersbeek 62 Vorst/forest Bruxelles-Capitale 1190",
    "addr:housenumber":"62",
    "addr:postcode":"1190",
    "addr:street":"Avenue Kersbeek;/ Forest",
    "iso:country":"BE",
    "sg:address":"Avenue Kersbeek 62",
    "sg:city":"Vorst/forest",
    "sg:orig_category":"Architectes",
    "sg:phone":"+32 2 376 54 86",
    "sg:postcode":"1190",
    "sg:province":"Bruxelles-Capitale",
    "wof:name":"Franchimont Y",
    "wof:placetype":"venue"
},
  "geometry": {"coordinates":[4.3192281723,50.8073348999],"type":"Point"}
}