{
  "type": "Feature",
  "properties": {
    "iso:country":"BE",
    "sg:address":"Weddemer Weg 3",
    "sg:city":"B\u00fctgenbach",
    "sg:classifiers":[
        {
            "category":"Building & Trades",
            "subcategory":"Landscaping Services",
            "type":"Services"
        }
    ],
    "sg:phone":"+32 80 44 42 07",
    "sg:postcode":"4750",
    "sg:province":"Li\u00e8ge",
    "sg:tags":[
        "-",
        "lopping",
        "work",
        "tree",
        "felling"
    ],
    "wof:name":"Piront Rolf Sprlu",
    "wof:placetype":"venue"
},
  "geometry": {"coordinates":[6.1626620293,50.4321937561],"type":"Point"}
}