{
  "type": "Feature",
  "properties": {
    "addr:full":"Brug Noord 25a Aalter Oost-Vlaanderen 9880",
    "addr:housenumber":"25a",
    "addr:postcode":"9880",
    "addr:street":"Brug Noord",
    "iso:country":"BE",
    "sg:address":"Brug Noord 25a",
    "sg:city":"Aalter",
    "sg:classifiers":[
        {
            "category":"Personal",
            "subcategory":"Skin Care",
            "type":"Services"
        }
    ],
    "sg:phone":"+32 9 325 04 02",
    "sg:postcode":"9880",
    "sg:province":"Oost-Vlaanderen",
    "sg:tags":[
        "hair",
        "treatment"
    ],
    "wof:name":"De Ridder M",
    "wof:placetype":"venue"
},
  "geometry": {"coordinates":[3.4442241192,51.0942878723],"type":"Point"}
}