{
  "type": "Feature",
  "properties": {
    "iso:country":"BE",
    "sg:address":"Boomgaardstraat 82",
    "sg:city":"Zwijndrecht (burcht)",
    "sg:classifiers":[
        {
            "category":"Professional",
            "subcategory":"Management & Consulting",
            "type":"Services"
        }
    ],
    "sg:phone":"+32 3 252 88 16",
    "sg:postcode":"2070",
    "sg:province":"Antwerpen",
    "sg:tags":[
        "tax-consultants"
    ],
    "wof:name":"Noeninckx D",
    "wof:placetype":"venue"
},
  "geometry": {"coordinates":[4.325594902,51.2030296326],"type":"Point"}
}