{
  "type": "Feature",
  "properties": {
    "iso:country":"BE",
    "sg:address":"Avenue Du Panth\u00e9on 68",
    "sg:city":"Bruxelles (koekelberg)",
    "sg:classifiers":[
        {
            "category":"Bars & Pubs",
            "type":"Food & Drink"
        }
    ],
    "sg:phone":"+32 2 414 42 81",
    "sg:postcode":"1081",
    "sg:province":"Bruxelles-Capitale",
    "wof:name":"Parc (cafe Du)",
    "wof:placetype":"venue"
},
  "geometry": {"coordinates":[4.3203120232,50.8648719788],"type":"Point"}
}