{
  "type": "Feature",
  "properties": {
    "iso:country":"BE",
    "sg:address":"Stationsstraat 153bb",
    "sg:city":"Sint-genesius-rode/rhode-saint-genese",
    "sg:orig_category":"Schoonheidssalons",
    "sg:phone":"+32 2 380 68 91",
    "sg:postcode":"1640",
    "sg:province":"Vlaams-Brabant",
    "wof:name":"Myriam Vanden Berghen",
    "wof:placetype":"venue"
},
  "geometry": {"coordinates":[4.3581337929,50.7495727539],"type":"Point"}
}