{
  "type": "Feature",
  "properties": {
    "iso:country":"BE",
    "sg:address":"Stampkotstraat 17",
    "sg:city":"Staden",
    "sg:orig_category":"Eleveurs and marchands de porcs",
    "sg:phone":"+32 51 70 19 73",
    "sg:postcode":"8840",
    "sg:province":"West-Vlaanderen",
    "wof:name":"Maria Ghesquiere",
    "wof:placetype":"venue"
},
  "geometry": {"coordinates":[2.9955880642,50.9768486023],"type":"Point"}
}