{
  "type": "Feature",
  "properties": {
    "addr:full":"Ninoofsesteenweg 632 Halle Vlaams-Brabant 1500",
    "addr:housenumber":"632",
    "addr:postcode":"1500",
    "addr:street":"Ninoofsesteenweg",
    "iso:country":"BE",
    "sg:address":"Ninoofsesteenweg 632",
    "sg:city":"Halle",
    "sg:orig_category":"HUISBRANDOLIE",
    "sg:phone":"+32 2 356 65 89",
    "sg:postcode":"1500",
    "sg:province":"Vlaams-Brabant",
    "wof:name":"Geert Coppens",
    "wof:placetype":"venue"
},
  "geometry": {"coordinates":[4.2043452263,50.7438468933],"type":"Point"}
}