{
  "type": "Feature",
  "properties": {
    "iso:country":"BE",
    "sg:address":"Turnhoutsebaan 5b126",
    "sg:city":"Wijnegem",
    "sg:orig_category":"Herenkledingzaken",
    "sg:phone":"+32 3 353 67 10",
    "sg:postcode":"2110",
    "sg:province":"Antwerpen",
    "wof:name":"La Chemiserie",
    "wof:placetype":"venue"
},
  "geometry": {"coordinates":[4.5043401718,51.2240219116],"type":"Point"}
}