{
  "type": "Feature",
  "properties": {
    "iso:country":"BE",
    "sg:address":"Square Georges Marlow 34",
    "sg:city":"Bruxelles (uccle)",
    "sg:classifiers":[
        {
            "category":"Professional",
            "subcategory":"Management & Consulting",
            "type":"Services"
        }
    ],
    "sg:phone":"+32 2 346 77 36",
    "sg:postcode":"1180",
    "sg:province":"Bruxelles-Capitale",
    "sg:tags":[
        "consultant"
    ],
    "wof:name":"A+ Group",
    "wof:placetype":"venue"
},
  "geometry": {"coordinates":[4.3230838776,50.798538208],"type":"Point"}
}