{
  "type": "Feature",
  "properties": {
    "addr:full":"Kruisweg Haven 650 Antwerpen Antwerpen 2040",
    "addr:housenumber":"650",
    "addr:postcode":"2040",
    "addr:street":"Kruisweg Haven",
    "iso:country":"BE",
    "sg:address":"Kruisweg Haven 650",
    "sg:city":"Antwerpen",
    "sg:classifiers":[
        {
            "category":"Professional",
            "subcategory":"Employment Agencies",
            "type":"Services"
        }
    ],
    "sg:phone":"+32 3 560 49 11",
    "sg:postcode":"2040",
    "sg:province":"Antwerpen",
    "sg:tags":[
        "overseas",
        "shipping"
    ],
    "wof:name":"Norexa Nv",
    "wof:placetype":"venue"
},
  "geometry": {"coordinates":[4.3254981041,51.3139648438],"type":"Point"}
}