{
  "type": "Feature",
  "properties": {
    "iso:country":"BE",
    "sg:address":"Terdonkplein 29",
    "sg:city":"Gent (sint-kruis-winkel)",
    "sg:classifiers":[
        {
            "category":"Building & Trades",
            "subcategory":"Electrical",
            "type":"Services"
        }
    ],
    "sg:phone":"+32 475 32 45 88",
    "sg:postcode":"9042",
    "sg:province":"Oost-Vlaanderen",
    "sg:tags":[
        "electric",
        "-",
        "housewiring",
        "contractor"
    ],
    "wof:name":"Verbeecke G",
    "wof:placetype":"venue"
},
  "geometry": {"coordinates":[3.777009964,51.1459197998],"type":"Point"}
}