{
  "type": "Feature",
  "properties": {
    "addr:full":"Rte De Luxembourg 16 Malmedy Li\u00e8ge 4960",
    "addr:housenumber":"16",
    "addr:postcode":"4960",
    "addr:street":"Rte De Luxembourg",
    "iso:country":"BE",
    "sg:address":"Rte De Luxembourg 16",
    "sg:city":"Malmedy",
    "sg:classifiers":[
        {
            "category":"Building & Trades",
            "subcategory":"Construction",
            "type":"Services"
        }
    ],
    "sg:phone":"+32 80 79 91 20",
    "sg:postcode":"4960",
    "sg:province":"Li\u00e8ge",
    "sg:tags":[
        "work",
        "public"
    ],
    "wof:name":"Bodarwe Et Fils & Boreta Sa",
    "wof:placetype":"venue"
},
  "geometry": {"coordinates":[6.0668320656,50.4008712769],"type":"Point"}
}