{
  "type": "Feature",
  "properties": {
    "addr:full":"Rue Salvador Allende 17a Ath (maffle) Hainaut 7810",
    "addr:housenumber":"17a",
    "addr:postcode":"7810",
    "addr:street":"Rue Salvador Allende",
    "iso:country":"BE",
    "sg:address":"Rue Salvador Allende 17a",
    "sg:city":"Ath (maffle)",
    "sg:classifiers":[
        {
            "category":"Autos & Motor Vehicles",
            "subcategory":"Motorcycle Sales",
            "type":"Retail Goods"
        }
    ],
    "sg:phone":"+32 68 84 21 04",
    "sg:postcode":"7810",
    "sg:province":"Hainaut",
    "sg:tags":[
        "scooter",
        "-",
        "moped"
    ],
    "wof:name":"Rs.bikes",
    "wof:placetype":"venue"
},
  "geometry": {"coordinates":[3.8022899628,50.6149749756],"type":"Point"}
}