{
  "type": "Feature",
  "properties": {
    "addr:full":"Chauss\u00c9e De Mons 27-4 Nijvel Brabant Wallon 1400",
    "addr:housenumber":"27-4",
    "addr:postcode":"1400",
    "addr:street":"Chausse\u0301E De Mons;Brabant Wallon",
    "iso:country":"BE",
    "sg:address":"Chauss\u00c9e De Mons 27-4",
    "sg:city":"Nijvel",
    "sg:orig_category":"Sportclubs",
    "sg:phone":"+32 67 84 19 41",
    "sg:postcode":"1400",
    "sg:province":"Brabant Wallon",
    "wof:name":"Shitokai",
    "wof:placetype":"venue"
},
  "geometry": {"coordinates":[4.3105449677,50.5870132446],"type":"Point"}
}