{
  "type": "Feature",
  "properties": {
    "iso:country":"BE",
    "sg:address":"Kreupelveldstraat 38",
    "sg:city":"Aalst",
    "sg:classifiers":[
        {
            "category":"Arena",
            "subcategory":"Sports Club",
            "type":"Entertainment"
        }
    ],
    "sg:phone":"+32 53 78 69 14",
    "sg:postcode":"9300",
    "sg:province":"Oost-Vlaanderen",
    "wof:name":"Petanqueclub Alosta Vzw",
    "wof:placetype":"venue"
},
  "geometry": {"coordinates":[4.0098638535,50.941696167],"type":"Point"}
}