{
  "type": "Feature",
  "properties": {
    "iso:country":"BE",
    "sg:address":"Oosteeklodorp 66",
    "sg:city":"Assenede",
    "sg:orig_category":"V\u00e9t\u00e9rinaires",
    "sg:phone":"+32 9 373 78 94",
    "sg:postcode":"9968",
    "sg:province":"Oost-Vlaanderen",
    "wof:name":"Andre De Kesel",
    "wof:placetype":"venue"
},
  "geometry": {"coordinates":[3.6860558987,51.1902198792],"type":"Point"}
}