{
  "type": "Feature",
  "properties": {
    "addr:full":"Weerstersteenweg 112 Maaseik Limburg 3680",
    "addr:housenumber":"112",
    "addr:postcode":"3680",
    "addr:street":"Weerstersteenweg",
    "iso:country":"BE",
    "sg:address":"Weerstersteenweg 112",
    "sg:city":"Maaseik",
    "sg:orig_category":"Activit\u00e9s d\u00b4action sociale sans h\u00e9bergement",
    "sg:phone":"+32 89 56 80 75",
    "sg:postcode":"3680",
    "sg:province":"Limburg",
    "wof:name":"Rode Kruis Maaseik",
    "wof:placetype":"venue"
},
  "geometry": {"coordinates":[5.791285038,51.0954208374],"type":"Point"}
}