{
  "type": "Feature",
  "properties": {
    "addr:full":"Florastraat 8 De Pinte Oost-Vlaanderen 9840",
    "addr:housenumber":"8",
    "addr:postcode":"9840",
    "addr:street":"Florastraat",
    "iso:country":"BE",
    "sg:address":"Florastraat 8",
    "sg:city":"De Pinte",
    "sg:orig_category":"Alternatieve geneeskunde",
    "sg:phone":"+32 9 282 47 08",
    "sg:postcode":"9840",
    "sg:province":"Oost-Vlaanderen",
    "wof:name":"M. Kielland E.",
    "wof:placetype":"venue"
},
  "geometry": {"coordinates":[3.6572210789,50.9997062683],"type":"Point"}
}