{
  "type": "Feature",
  "properties": {
    "iso:country":"BE",
    "sg:address":"Adriaanbrouwerstraat 2",
    "sg:city":"Oudenaarde",
    "sg:orig_category":"Schoonheidssalons",
    "sg:phone":"+32 55 31 41 92",
    "sg:postcode":"9700",
    "sg:province":"Oost-Vlaanderen",
    "wof:name":"Instituut Nefertete",
    "wof:placetype":"venue"
},
  "geometry": {"coordinates":[3.6108310223,50.8468208313],"type":"Point"}
}