{
  "type": "Feature",
  "properties": {
    "iso:country":"BE",
    "sg:address":"Chauss\u00c9e De Li\u00c8ge 40",
    "sg:city":"Marche-en-famenne",
    "sg:orig_category":"Slagers",
    "sg:phone":"+32 84 31 51 19",
    "sg:postcode":"6900",
    "sg:province":"Luxembourg",
    "wof:name":"Renmans",
    "wof:placetype":"venue"
},
  "geometry": {"coordinates":[5.3442521095,50.2339820862],"type":"Point"}
}