{
  "type": "Feature",
  "properties": {
    "addr:full":"Stapelstraat 58 Sint-truiden Limburg 3800",
    "addr:housenumber":"58",
    "addr:postcode":"3800",
    "addr:street":"Stapelstraat",
    "iso:country":"BE",
    "sg:address":"Stapelstraat 58",
    "sg:city":"Sint-truiden",
    "sg:classifiers":[
        {
            "category":"Shopping",
            "subcategory":"Florist",
            "type":"Retail Goods"
        }
    ],
    "sg:phone":"+32 11 68 34 57",
    "sg:postcode":"3800",
    "sg:province":"Limburg",
    "wof:name":"Flora",
    "wof:placetype":"venue"
},
  "geometry": {"coordinates":[5.1822490692,50.8153038025],"type":"Point"}
}