{
  "type": "Feature",
  "properties": {
    "addr:full":"Zoning Industriel Marche-en-famenne Luxembourg 6900",
    "addr:postcode":"6900",
    "addr:street":"Zoning Industriel",
    "iso:country":"BE",
    "sg:address":"Zoning Industriel",
    "sg:city":"Marche-en-famenne",
    "sg:classifiers":[
        {
            "category":"Communications",
            "subcategory":"Newspaper",
            "type":"Services"
        }
    ],
    "sg:phone":"+32 84 31 01 11",
    "sg:postcode":"6900",
    "sg:province":"Luxembourg",
    "sg:tags":[
        "paper",
        "local",
        "free"
    ],
    "wof:name":"Groupe Plus",
    "wof:placetype":"venue"
},
  "geometry": {"coordinates":[5.3256669044,50.2212715149],"type":"Point"}
}