{
  "type": "Feature",
  "properties": {
    "iso:country":"BE",
    "sg:address":"Rue Saint-martin 13",
    "sg:city":"Hannut (thisnes)",
    "sg:classifiers":[
        {
            "category":"Professional",
            "subcategory":"Accounting & Tax Preparation",
            "type":"Services"
        }
    ],
    "sg:phone":"+32 19 51 06 41",
    "sg:postcode":"4280",
    "sg:province":"Li\u00e8ge",
    "sg:tags":[
        "bookkeeper"
    ],
    "wof:name":"Compt A Dis Sprl",
    "wof:placetype":"venue"
},
  "geometry": {"coordinates":[5.0819830894,50.6693687439],"type":"Point"}
}