{
  "type": "Feature",
  "properties": {
    "addr:full":"Rue Des Fontaines 85 Wavre Brabant Wallon 1300",
    "addr:housenumber":"85;1300",
    "addr:street":"Rue Des Fontaines",
    "iso:country":"BE",
    "sg:address":"Rue Des Fontaines 85",
    "sg:city":"Wavre",
    "sg:classifiers":[
        {
            "category":"Shopping",
            "subcategory":"Jewelry",
            "type":"Retail Goods"
        }
    ],
    "sg:phone":"+32 10 22 82 96",
    "sg:postcode":"1300",
    "sg:province":"Brabant Wallon",
    "sg:tags":[
        "purchase",
        "-",
        "sale",
        "gold"
    ],
    "wof:name":"Dorenavant",
    "wof:placetype":"venue"
},
  "geometry": {"coordinates":[4.6096892357,50.715473175],"type":"Point"}
}