{
  "type": "Feature",
  "properties": {
    "addr:full":"Rodter Strasse 152 Sankt Vith Li\u00e8ge 4780",
    "addr:housenumber":"152",
    "addr:postcode":"4780",
    "addr:street":"Rodter Strasse",
    "iso:country":"BE",
    "sg:address":"Rodter Strasse 152",
    "sg:city":"Sankt Vith",
    "sg:classifiers":[
        {
            "category":"Retail",
            "subcategory":"Veterinary Services",
            "type":"Services"
        }
    ],
    "sg:phone":"+32 80 22 82 58",
    "sg:postcode":"4780",
    "sg:province":"Li\u00e8ge",
    "sg:tags":[
        "veterinarian"
    ],
    "wof:name":"Clohse G",
    "wof:placetype":"venue"
},
  "geometry": {"coordinates":[6.101099968,50.2839698792],"type":"Point"}
}