{
  "type": "Feature",
  "properties": {
    "iso:country":"BE",
    "sg:address":"Kapucijnenvoer 33",
    "sg:city":"Leuven",
    "sg:classifiers":[
        {
            "category":"Social Services",
            "type":"Services"
        }
    ],
    "sg:phone":"+32 496 21 74 24",
    "sg:postcode":"3000",
    "sg:province":"Vlaams-Brabant",
    "wof:name":"Fides-beschut Wonen Leuven Vzw",
    "wof:placetype":"venue"
},
  "geometry": {"coordinates":[4.6925039291,50.8792037964],"type":"Point"}
}