{
  "type": "Feature",
  "properties": {
    "addr:full":"Brusselsesteenweg 297 Wetteren (massemen) Oost-Vlaanderen 9230",
    "addr:housenumber":"297",
    "addr:postcode":"9230",
    "addr:street":"Brusselsesteenweg",
    "iso:country":"BE",
    "sg:address":"Brusselsesteenweg 297",
    "sg:city":"Wetteren (massemen)",
    "sg:classifiers":[
        {
            "category":"Building & Trades",
            "subcategory":"Cleaning & Sanitation",
            "type":"Services"
        }
    ],
    "sg:phone":"+32 9 369 61 37",
    "sg:postcode":"9230",
    "sg:province":"Oost-Vlaanderen",
    "sg:tags":[
        "fa\u00e7ade",
        "maintenance"
    ],
    "wof:name":"De Graeve M",
    "wof:placetype":"venue"
},
  "geometry": {"coordinates":[3.8494958878,50.9822692871],"type":"Point"}
}