{
  "type": "Feature",
  "properties": {
    "iso:country":"BE",
    "sg:address":"Geelseweg 45",
    "sg:city":"Olen",
    "sg:classifiers":[
        {
            "category":"Utilities",
            "subcategory":"Fuel Oil & Lpg",
            "type":"Services"
        }
    ],
    "sg:phone":"+32 14 21 24 03",
    "sg:postcode":"2250",
    "sg:province":"Antwerpen",
    "wof:name":"Van Lierde Nv",
    "wof:placetype":"venue"
},
  "geometry": {"coordinates":[4.8673601151,51.1650695801],"type":"Point"}
}