{
  "type": "Feature",
  "properties": {
    "addr:full":"Koning Ridderdijk 33 Middelkerke (westende) West-Vlaanderen 8434",
    "addr:housenumber":"33",
    "addr:postcode":"8434",
    "addr:street":"Koning Ridderdijk",
    "iso:country":"BE",
    "sg:address":"Koning Ridderdijk 33",
    "sg:city":"Middelkerke (westende)",
    "sg:classifiers":[
        {
            "category":"Shopping",
            "subcategory":"Books",
            "type":"Retail Goods"
        }
    ],
    "sg:phone":"+32 59 30 24 12",
    "sg:postcode":"8434",
    "sg:province":"West-Vlaanderen",
    "sg:tags":[
        "bookseller"
    ],
    "wof:name":"Kompas",
    "wof:placetype":"venue"
},
  "geometry": {"coordinates":[2.7569050789,51.1488685608],"type":"Point"}
}