{
  "type": "Feature",
  "properties": {
    "iso:country":"BE",
    "sg:address":"Chauss\u00e9e De Verviers 94",
    "sg:city":"Theux",
    "sg:classifiers":[
        {
            "category":"Autos & Motor Vehicles",
            "subcategory":"Automobile Sales",
            "type":"Retail Goods"
        }
    ],
    "sg:phone":"+32 87 54 13 52",
    "sg:postcode":"4910",
    "sg:province":"Li\u00e8ge",
    "sg:tags":[
        "car",
        "used",
        "-"
    ],
    "wof:name":"Jaminon J-p",
    "wof:placetype":"venue"
},
  "geometry": {"coordinates":[5.8293170929,50.5422477722],"type":"Point"}
}