{
  "type": "Feature",
  "properties": {
    "iso:country":"BE",
    "sg:address":"Boulevard Du Jubil\u00c9 32",
    "sg:city":"Sint-jans-molenbeek/molenbeek-saint-jean",
    "sg:orig_category":"Avocats and conseillers juridiques",
    "sg:phone":"+32 2 425 65 12",
    "sg:postcode":"1080",
    "sg:province":"Bruxelles-Capitale",
    "wof:name":"J.l. Vankerckhove",
    "wof:placetype":"venue"
},
  "geometry": {"coordinates":[4.3375840187,50.8621635437],"type":"Point"}
}