{
  "type": "Feature",
  "properties": {
    "addr:full":"Lichtaartseweg 169 Herentals Antwerpen 2200",
    "addr:housenumber":"169",
    "addr:postcode":"2200",
    "addr:street":"Lichtaartseweg",
    "iso:country":"BE",
    "sg:address":"Lichtaartseweg 169",
    "sg:city":"Herentals",
    "sg:classifiers":[
        {
            "category":"Bars & Pubs",
            "type":"Food & Drink"
        }
    ],
    "sg:phone":"+32 14 22 58 30",
    "sg:postcode":"2200",
    "sg:province":"Antwerpen",
    "wof:name":"Kluis (de)",
    "wof:placetype":"venue"
},
  "geometry": {"coordinates":[4.8476071358,51.1932945251],"type":"Point"}
}