{
  "type": "Feature",
  "properties": {
    "addr:full":"Leeuwenstraat 1 Zuienkerke West-Vlaanderen 8377",
    "addr:housenumber":"1",
    "addr:postcode":"8377",
    "addr:street":"Leeuwenstraat",
    "iso:country":"BE",
    "sg:address":"Leeuwenstraat 1",
    "sg:city":"Zuienkerke",
    "sg:orig_category":"Eleveurs and marchands de porcs. Eleveurs de bovins",
    "sg:phone":"+32 50 41 30 47",
    "sg:postcode":"8377",
    "sg:province":"West-Vlaanderen",
    "wof:name":"Johan Schouteeten",
    "wof:placetype":"venue"
},
  "geometry": {"coordinates":[3.1134870052,51.2666969299],"type":"Point"}
}