{
  "type": "Feature",
  "properties": {
    "iso:country":"BE",
    "sg:address":"Genkersteenweg 33",
    "sg:city":"Hasselt",
    "sg:classifiers":[
        {
            "category":"Government",
            "subcategory":"Fire Station",
            "type":"Public Place"
        }
    ],
    "sg:phone":"+32 11 30 70 80",
    "sg:postcode":"3500",
    "sg:province":"Limburg",
    "sg:tags":[
        "installation",
        "-",
        "air conditioning"
    ],
    "wof:name":"Knoops Cooling Nv",
    "wof:placetype":"venue"
},
  "geometry": {"coordinates":[5.3801698685,50.9444885254],"type":"Point"}
}