{
  "type": "Feature",
  "properties": {
    "addr:full":"Berkenweg 17 Erpe-mere Oost-Vlaanderen 9420",
    "addr:housenumber":"17",
    "addr:postcode":"9420",
    "addr:street":"Berkenweg",
    "iso:country":"BE",
    "sg:address":"Berkenweg 17",
    "sg:city":"Erpe-mere",
    "sg:orig_category":"Verplichte sociale verzekeringen",
    "sg:phone":"+32 53 62 42 28",
    "sg:postcode":"9420",
    "sg:province":"Oost-Vlaanderen",
    "wof:name":"Bond Moyson",
    "wof:placetype":"venue"
},
  "geometry": {"coordinates":[3.9202420712,50.9094276428],"type":"Point"}
}