{
  "type": "Feature",
  "properties": {
    "iso:country":"BE",
    "sg:address":"Koningsbaan 24",
    "sg:city":"Putte (beerzel)",
    "sg:classifiers":[
        {
            "category":"Retail",
            "subcategory":"Event Space",
            "type":"Services"
        }
    ],
    "sg:phone":"+32 15 76 00 47",
    "sg:postcode":"2580",
    "sg:province":"Antwerpen",
    "sg:tags":[
        "rental",
        "-",
        "hall"
    ],
    "wof:name":"Kennedy",
    "wof:placetype":"venue"
},
  "geometry": {"coordinates":[4.6728720665,51.0570144653],"type":"Point"}
}