{
  "type": "Feature",
  "properties": {
    "iso:country":"BE",
    "sg:address":"Rue De Tr\u00e8ves 30",
    "sg:city":"Bruxelles (ixelles)",
    "sg:classifiers":[
        {
            "category":"Bars & Pubs",
            "type":"Food & Drink"
        }
    ],
    "sg:phone":"+32 2 511 77 31",
    "sg:postcode":"1050",
    "sg:province":"Bruxelles-Capitale",
    "wof:name":"Ville De Dinant (\u00e0 La)",
    "wof:placetype":"venue"
},
  "geometry": {"coordinates":[4.3730068207,50.8388252258],"type":"Point"}
}