{
  "type": "Feature",
  "properties": {
    "addr:full":"Alsembergse Steenweg 706 Ukkel/uccle Bruxelles-Capitale 1180",
    "addr:housenumber":"706",
    "addr:postcode":"1180",
    "addr:street":"Alsembergse Steenweg;/",
    "iso:country":"BE",
    "sg:address":"Alsembergse Steenweg 706",
    "sg:city":"Ukkel/uccle",
    "sg:classifiers":[
        {
            "category":"Food & Beverages",
            "subcategory":"Meat & Fish",
            "type":"Retail Goods"
        }
    ],
    "sg:phone":"+32 2 343 95 47",
    "sg:postcode":"1180",
    "sg:province":"Bruxelles-Capitale",
    "sg:tags":[
        "vi",
        "zeevruchten"
    ],
    "wof:name":"Poissonnerie Centrale",
    "wof:placetype":"venue"
},
  "geometry": {"coordinates":[4.3368811607,50.8022155762],"type":"Point"}
}