{
  "type": "Feature",
  "properties": {
    "addr:full":"Avenue Des Prunelliers 5 Wemmel Vlaams-Brabant 1780",
    "addr:housenumber":"5",
    "addr:postcode":"1780",
    "addr:street":"Avenue Des Prunelliers;Vlaams-Brabant",
    "iso:country":"BE",
    "sg:address":"Avenue Des Prunelliers 5",
    "sg:city":"Wemmel",
    "sg:classifiers":[
        {
            "category":"Shopping",
            "subcategory":"Stationery & Office Supplies",
            "type":"Retail Goods"
        }
    ],
    "sg:phone":"+32 2 460 23 14",
    "sg:postcode":"1780",
    "sg:province":"Vlaams-Brabant",
    "sg:tags":[
        "fab",
        "carton",
        "en",
        "papier",
        "emballages"
    ],
    "wof:name":"Papeteries De La Lienne",
    "wof:placetype":"venue"
},
  "geometry": {"coordinates":[4.3096499443,50.9127731323],"type":"Point"}
}