{
  "type": "Feature",
  "properties": {
    "addr:full":"Lemmeken 16 Londerzeel (malderen) Vlaams-Brabant 1840",
    "addr:housenumber":"16",
    "addr:postcode":"1840",
    "addr:street":"Lemmeken",
    "iso:country":"BE",
    "sg:address":"Lemmeken 16",
    "sg:city":"Londerzeel (malderen)",
    "sg:classifiers":[
        {
            "category":"Building & Trades",
            "subcategory":"Construction",
            "type":"Services"
        }
    ],
    "sg:phone":"+32 52 33 58 92",
    "sg:postcode":"1840",
    "sg:province":"Vlaams-Brabant",
    "sg:tags":[
        "installation",
        "-",
        "central",
        "heating"
    ],
    "wof:name":"Van Laethem W",
    "wof:placetype":"venue"
},
  "geometry": {"coordinates":[4.2416291237,51.0146026611],"type":"Point"}
}