{
  "type": "Feature",
  "properties": {
    "addr:full":"Rue Verte Voie 55 Li\u00c8ge Li\u00e8ge 4000",
    "addr:housenumber":"55",
    "addr:postcode":"4000",
    "addr:street":"Rue Verte Voie",
    "iso:country":"BE",
    "sg:address":"Rue Verte Voie 55",
    "sg:city":"Li\u00c8ge",
    "sg:orig_category":"R\u00e9cup\u00e9ration de mati\u00e8res m\u00e9talliques recyclables and d\u00e9molisseurs de voitures. D\u00e9taillants en pi\u00e8ces",
    "sg:phone":"+32 4 233 55 56",
    "sg:postcode":"4000",
    "sg:province":"Li\u00e8ge",
    "wof:name":"Nucera D\u00c9pannage",
    "wof:placetype":"venue"
},
  "geometry": {"coordinates":[5.5401291847,50.6142463684],"type":"Point"}
}