{
  "type": "Feature",
  "properties": {
    "iso:country":"BE",
    "sg:address":"Chauss\u00e9e De Mons 1135",
    "sg:city":"Bruxelles (anderlecht)",
    "sg:classifiers":[
        {
            "category":"Building & Trades",
            "subcategory":"Cleaning & Sanitation",
            "type":"Services"
        }
    ],
    "sg:phone":"+32 2 526 57 57",
    "sg:postcode":"1070",
    "sg:province":"Bruxelles-Capitale",
    "sg:tags":[
        "cleaner",
        "window"
    ],
    "wof:name":"Clean-up Bruxelles Sa",
    "wof:placetype":"venue"
},
  "geometry": {"coordinates":[4.2944788933,50.8223152161],"type":"Point"}
}