{
  "type": "Feature",
  "properties": {
    "addr:full":"Quai De Brabant 2 Charleroi Hainaut 6000",
    "addr:housenumber":"2",
    "addr:postcode":"6000",
    "addr:street":"Quai De Brabant;Hainaut",
    "iso:country":"BE",
    "sg:address":"Quai De Brabant 2",
    "sg:city":"Charleroi",
    "sg:classifiers":[
        {
            "category":"Bars & Pubs",
            "type":"Food & Drink"
        }
    ],
    "sg:phone":"+32 71 32 77 52",
    "sg:postcode":"6000",
    "sg:province":"Hainaut",
    "wof:name":"Galion (le)",
    "wof:placetype":"venue"
},
  "geometry": {"coordinates":[4.4394841194,50.4062576294],"type":"Point"}
}