{
  "type": "Feature",
  "properties": {
    "iso:country":"BE",
    "sg:address":"Rue De La Station 155",
    "sg:city":"Courcelles",
    "sg:orig_category":"Slagers",
    "sg:phone":"+32 71 84 46 56",
    "sg:postcode":"6181",
    "sg:province":"Hainaut",
    "wof:name":"Lucien Halliez",
    "wof:placetype":"venue"
},
  "geometry": {"coordinates":[4.3269128799,50.4960975647],"type":"Point"}
}