{
  "type": "Feature",
  "properties": {
    "addr:full":"Rue Du March\u00e9 Aux Herbes 49 Bruxelles Bruxelles-Capitale 1000",
    "addr:housenumber":"49",
    "addr:postcode":"1000",
    "addr:street":"Rue Du Marche\u0301 Aux Herbes",
    "iso:country":"BE",
    "sg:address":"Rue Du March\u00e9 Aux Herbes 49",
    "sg:city":"Bruxelles",
    "sg:classifiers":[
        {
            "category":"Shopping",
            "subcategory":"Jewelry",
            "type":"Retail Goods"
        }
    ],
    "sg:phone":"+32 2 513 37 98",
    "sg:postcode":"1000",
    "sg:province":"Bruxelles-Capitale",
    "sg:tags":[
        "jeweller",
        "-"
    ],
    "wof:name":"Rupture",
    "wof:placetype":"venue"
},
  "geometry": {"coordinates":[4.3526911736,50.847442627],"type":"Point"}
}