{
  "type": "Feature",
  "properties": {
    "iso:country":"BE",
    "sg:address":"Steenweg Op Beerse 124",
    "sg:city":"Merksplas",
    "sg:orig_category":"Rundveehouders",
    "sg:phone":"+32 14 63 34 58",
    "sg:postcode":"2330",
    "sg:province":"Antwerpen",
    "wof:name":"Adams-willemse",
    "wof:placetype":"venue"
},
  "geometry": {"coordinates":[4.8610429764,51.3433876038],"type":"Point"}
}