{
  "type": "Feature",
  "properties": {
    "iso:country":"BE",
    "sg:address":"Villerslei 82",
    "sg:city":"Schoten",
    "sg:orig_category":"Banques and organismes de cr\u00e9dit",
    "sg:phone":"+32 3 658 25 52",
    "sg:postcode":"2900",
    "sg:province":"Antwerpen",
    "wof:name":"Fortis",
    "wof:placetype":"venue"
},
  "geometry": {"coordinates":[4.5122032166,51.252155304],"type":"Point"}
}