{
  "type": "Feature",
  "properties": {
    "iso:country":"BE",
    "sg:address":"Immertstraat 11",
    "sg:city":"Leopoldsburg",
    "sg:classifiers":[
        {
            "category":"Shopping Center",
            "type":"Public Place"
        }
    ],
    "sg:phone":"+32 11 40 16 96",
    "sg:postcode":"3971",
    "sg:province":"Limburg",
    "sg:tags":[
        "enseignement",
        "formation"
    ],
    "wof:name":"Motivation",
    "wof:placetype":"venue"
},
  "geometry": {"coordinates":[5.2218151093,51.1218795776],"type":"Point"}
}