{
  "type": "Feature",
  "properties": {
    "addr:full":"Rue Des Dames 8 Gerpinnes (acoz) Hainaut 6280",
    "addr:housenumber":"8",
    "addr:postcode":"6280",
    "addr:street":"Rue Des Dames",
    "iso:country":"BE",
    "sg:address":"Rue Des Dames 8",
    "sg:city":"Gerpinnes (acoz)",
    "sg:classifiers":[
        {
            "category":"Health Services",
            "subcategory":"Health Practitioner",
            "type":"Services"
        }
    ],
    "sg:phone":"+32 71 50 58 35",
    "sg:postcode":"6280",
    "sg:province":"Hainaut",
    "sg:tags":[
        "physiotherapist"
    ],
    "wof:name":"Lema\u00eetre Fabian",
    "wof:placetype":"venue"
},
  "geometry": {"coordinates":[4.5138978958,50.3633728027],"type":"Point"}
}