{
  "type": "Feature",
  "properties": {
    "addr:full":"Rue De L'esplanade 8 Sprimont Li\u00e8ge 4141",
    "addr:housenumber":"8",
    "addr:postcode":"4141",
    "addr:street":"Rue De L'Esplanade",
    "iso:country":"BE",
    "sg:address":"Rue De L'esplanade 8",
    "sg:city":"Sprimont",
    "sg:orig_category":"Orphelinats. Instituts pour enfants en difficult\u00e9",
    "sg:phone":"+32 4 360 80 46",
    "sg:postcode":"4141",
    "sg:province":"Li\u00e8ge",
    "wof:name":"Foyer Les Faons",
    "wof:placetype":"venue"
},
  "geometry": {"coordinates":[5.7383208275,50.5373764038],"type":"Point"}
}