{
  "type": "Feature",
  "properties": {
    "addr:full":"Zuidlaan 90 Brussel/bruxelles Bruxelles-Capitale 1000",
    "addr:housenumber":"90",
    "addr:postcode":"1000",
    "addr:street":"Zuidlaan;/",
    "iso:country":"BE",
    "sg:address":"Zuidlaan 90",
    "sg:city":"Brussel/bruxelles",
    "sg:classifiers":[
        {
            "category":"Cafe",
            "type":"Food & Drink"
        }
    ],
    "sg:phone":"+32 2 511 26 50",
    "sg:postcode":"1000",
    "sg:province":"Bruxelles-Capitale",
    "sg:tags":[
        "caf\u00e9s"
    ],
    "wof:name":"Caf\u00c9 Athoise",
    "wof:placetype":"venue"
},
  "geometry": {"coordinates":[4.3420138359,50.837600708],"type":"Point"}
}