{
  "type": "Feature",
  "properties": {
    "iso:country":"BE",
    "sg:address":"Place Albert Ier 17",
    "sg:city":"Anderlues",
    "sg:orig_category":"Medische apparatuur, orthopedische artikelen and prothesen Fab",
    "sg:phone":"+32 71 54 08 28",
    "sg:postcode":"6150",
    "sg:province":"Hainaut",
    "wof:name":"Labo Lombart",
    "wof:placetype":"venue"
},
  "geometry": {"coordinates":[4.2712101936,50.4070510864],"type":"Point"}
}