{
  "type": "Feature",
  "properties": {
    "addr:full":"Gentstr 288 Oostakker Oost-Vlaanderen 9040",
    "addr:housenumber":"288",
    "addr:postcode":"9040",
    "iso:country":"BE",
    "sg:address":"Gentstr 288",
    "sg:city":"Oostakker",
    "sg:classifiers":[
        {
            "category":"Banks & Credit Unions",
            "subcategory":"Bank",
            "type":"Services"
        }
    ],
    "sg:phone":"+32 54 51 23 24",
    "sg:postcode":"9040",
    "sg:province":"Oost-Vlaanderen",
    "wof:name":"Krediet Nuverheid",
    "wof:placetype":"venue"
},
  "geometry": {"coordinates":[3.7643020153,51.0994186401],"type":"Point"}
}