{
  "type": "Feature",
  "properties": {
    "iso:country":"BE",
    "sg:address":"Horststraat 20",
    "sg:city":"Arendonk",
    "sg:orig_category":"Travaux de pl\u00e2trage",
    "sg:phone":"+32 14 67 14 14",
    "sg:postcode":"2370",
    "sg:province":"Antwerpen",
    "wof:name":"Patrick Wouters",
    "wof:placetype":"venue"
},
  "geometry": {"coordinates":[5.0963730812,51.3189964294],"type":"Point"}
}