{
  "type": "Feature",
  "properties": {
    "iso:country":"BE",
    "sg:address":"Rue D'anderlues 14",
    "sg:city":"Lobbes",
    "sg:orig_category":"Eleveurs de bovins",
    "sg:phone":"+32 71 59 33 68",
    "sg:postcode":"6540",
    "sg:province":"Hainaut",
    "wof:name":"Antonio Dui",
    "wof:placetype":"venue"
},
  "geometry": {"coordinates":[4.2753210068,50.3702316284],"type":"Point"}
}