{
  "type": "Feature",
  "properties": {
    "addr:full":"Pieter Van Aalst 10 Aalst Oost-Vlaanderen 9300",
    "addr:housenumber":"10",
    "addr:postcode":"9300",
    "addr:street":"Pieter Van Aalst",
    "iso:country":"BE",
    "sg:address":"Pieter Van Aalst 10",
    "sg:city":"Aalst",
    "sg:classifiers":[
        {
            "category":"Shopping",
            "subcategory":"Clothing, Apparel, & Fashions",
            "type":"Retail Goods"
        }
    ],
    "sg:phone":"+32 50 70 42 96",
    "sg:postcode":"9300",
    "sg:province":"Oost-Vlaanderen",
    "sg:tags":[
        "v\u00eatements",
        "pour",
        "dame"
    ],
    "wof:name":"Cassis",
    "wof:placetype":"venue"
},
  "geometry": {"coordinates":[4.0311560631,50.9206695557],"type":"Point"}
}