{
  "type": "Feature",
  "properties": {
    "addr:full":"Montgolfierlaan 125 Sint-pieters-woluwe/woluwe-saint-pierre Bruxelles-Capitale 1150",
    "addr:housenumber":"125",
    "addr:postcode":"1150",
    "addr:street":"Montgolfierlaan;/",
    "iso:country":"BE",
    "sg:address":"Montgolfierlaan 125",
    "sg:city":"Sint-pieters-woluwe/woluwe-saint-pierre",
    "sg:orig_category":"Landmeters",
    "sg:phone":"+32 2 771 55 88",
    "sg:postcode":"1150",
    "sg:province":"Bruxelles-Capitale",
    "wof:name":"Guy Servais",
    "wof:placetype":"venue"
},
  "geometry": {"coordinates":[4.4411201477,50.8372993469],"type":"Point"}
}