{
  "type": "Feature",
  "properties": {
    "addr:full":"Rue Des Ourmes 26 Walcourt Namur 5650",
    "addr:housenumber":"26",
    "addr:postcode":"5650",
    "addr:street":"Rue Des Ourmes",
    "iso:country":"BE",
    "sg:address":"Rue Des Ourmes 26",
    "sg:city":"Walcourt",
    "sg:orig_category":"MEUBELONTWERP AND -INSTALLATIE",
    "sg:phone":"+32 71 65 53 08",
    "sg:postcode":"5650",
    "sg:province":"Namur",
    "wof:name":"Nobler",
    "wof:placetype":"venue"
},
  "geometry": {"coordinates":[4.4313349724,50.2514762878],"type":"Point"}
}