{
  "type": "Feature",
  "properties": {
    "addr:full":"Schotelven 149 Arendonk Antwerpen 2370",
    "addr:housenumber":"149",
    "addr:postcode":"2370",
    "addr:street":"Schotelven",
    "iso:country":"BE",
    "sg:address":"Schotelven 149",
    "sg:city":"Arendonk",
    "sg:classifiers":[
        {
            "category":"Utilities",
            "subcategory":"Natural Gas",
            "type":"Services"
        }
    ],
    "sg:phone":"+32 14 67 76 05",
    "sg:postcode":"2370",
    "sg:province":"Antwerpen",
    "sg:tags":[
        "welding"
    ],
    "wof:name":"Y-las",
    "wof:placetype":"venue"
},
  "geometry": {"coordinates":[5.045486927,51.3121261597],"type":"Point"}
}