{
  "type": "Feature",
  "properties": {
    "addr:full":"Rue Du Mohet 7 Donceel Li\u00e8ge 4357",
    "addr:housenumber":"7",
    "addr:postcode":"4357",
    "addr:street":"Rue Du Mohet",
    "iso:country":"BE",
    "sg:address":"Rue Du Mohet 7",
    "sg:city":"Donceel",
    "sg:orig_category":"V\u00e9t\u00e9rinaires",
    "sg:phone":"+32 19 54 48 97",
    "sg:postcode":"4357",
    "sg:province":"Li\u00e8ge",
    "wof:name":"H. Lucas",
    "wof:placetype":"venue"
},
  "geometry": {"coordinates":[5.3086419106,50.6587295532],"type":"Point"}
}