{
  "type": "Feature",
  "properties": {
    "addr:full":"Rue Du Village 88 Gr\u00e2ce-hollogne (velroux) Li\u00e8ge 4460",
    "addr:housenumber":"88",
    "addr:postcode":"4460",
    "addr:street":"Rue Du Village;Velroux",
    "iso:country":"BE",
    "sg:address":"Rue Du Village 88",
    "sg:city":"Gr\u00e2ce-hollogne (velroux)",
    "sg:classifiers":[
        {
            "category":"Professional",
            "subcategory":"Accounting & Tax Preparation",
            "type":"Services"
        }
    ],
    "sg:phone":"+32 4 250 24 66",
    "sg:postcode":"4460",
    "sg:province":"Li\u00e8ge",
    "sg:tags":[
        "accountant"
    ],
    "wof:name":"Piedboeuf R",
    "wof:placetype":"venue"
},
  "geometry": {"coordinates":[5.4266037941,50.6415290833],"type":"Point"}
}