{
  "type": "Feature",
  "properties": {
    "iso:country":"BE",
    "sg:address":"Chemin Du Pr\u00c9 Leftay 15",
    "sg:city":"Spa",
    "sg:orig_category":"Fabrication and montage de mobilier",
    "sg:phone":"+32 87 77 46 20",
    "sg:postcode":"4900",
    "sg:province":"Li\u00e8ge",
    "wof:name":"Paul Gasia",
    "wof:placetype":"venue"
},
  "geometry": {"coordinates":[5.8800311089,50.4954986572],"type":"Point"}
}