{
  "type": "Feature",
  "properties": {
    "iso:country":"BE",
    "sg:address":"Ekeveldstraat 4",
    "sg:city":"Brakel",
    "sg:orig_category":"Plaatsen van vloer- and muurbekleding Schilders",
    "sg:phone":"+32 55 42 55 59",
    "sg:postcode":"9660",
    "sg:province":"Oost-Vlaanderen",
    "wof:name":"Willy Austraete",
    "wof:placetype":"venue"
},
  "geometry": {"coordinates":[3.7539899349,50.7967758179],"type":"Point"}
}