{
  "type": "Feature",
  "properties": {
    "iso:country":"BE",
    "sg:address":"Leeuwerikweg 12",
    "sg:city":"Tienen",
    "sg:orig_category":"Mat\u00e9riaux de construction Gr",
    "sg:phone":"+32 16 82 35 00",
    "sg:postcode":"3300",
    "sg:province":"Vlaams-Brabant",
    "wof:name":"Vicca & Zn.",
    "wof:placetype":"venue"
},
  "geometry": {"coordinates":[4.9554400444,50.7962913513],"type":"Point"}
}