{
  "type": "Feature",
  "properties": {
    "addr:full":"R. De La Basse Charlotte 28 Jodoigne Brabant Wallon 1370",
    "addr:housenumber":"28",
    "addr:postcode":"1370",
    "iso:country":"BE",
    "sg:address":"R. De La Basse Charlotte 28",
    "sg:city":"Jodoigne",
    "sg:orig_category":"Rundveehouders",
    "sg:phone":"+32 10 81 10 48",
    "sg:postcode":"1370",
    "sg:province":"Brabant Wallon",
    "wof:name":"Jacques Haumont",
    "wof:placetype":"venue"
},
  "geometry": {"coordinates":[4.8469028473,50.7106513977],"type":"Point"}
}