{
  "type": "Feature",
  "properties": {
    "iso:country":"BE",
    "sg:address":"Parc Du Bay Bonnet 7-38",
    "sg:city":"Fl\u00e9ron",
    "sg:classifiers":[
        {
            "category":"Building & Trades",
            "subcategory":"Construction",
            "type":"Services"
        }
    ],
    "sg:phone":"+32 4 358 53 23",
    "sg:postcode":"4620",
    "sg:province":"Li\u00e8ge",
    "sg:tags":[
        "scaffolding"
    ],
    "wof:name":"Bruthier J-p",
    "wof:placetype":"venue"
},
  "geometry": {"coordinates":[5.6891207695,50.6131019592],"type":"Point"}
}