{
  "type": "Feature",
  "properties": {
    "addr:full":"Rue De Rodange 22 Aubange Luxembourg 6791",
    "addr:housenumber":"22",
    "addr:postcode":"6791",
    "addr:street":"Rue De Rodange",
    "iso:country":"BE",
    "sg:address":"Rue De Rodange 22",
    "sg:city":"Aubange",
    "sg:orig_category":"D\u00e9taillants en pi\u00e8ces and accessoires de voitures",
    "sg:phone":"+32 63 38 92 86",
    "sg:postcode":"6791",
    "sg:province":"Luxembourg",
    "wof:name":"J.c.s. Marketing",
    "wof:placetype":"venue"
},
  "geometry": {"coordinates":[5.8368301392,49.5627288818],"type":"Point"}
}