{
  "type": "Feature",
  "properties": {
    "addr:full":"Chauss\u00c9e De Namur 56 Hamois Namur 5360",
    "addr:housenumber":"56",
    "addr:postcode":"5360",
    "addr:street":"Chausse\u0301E De Namur",
    "iso:country":"BE",
    "sg:address":"Chauss\u00c9e De Namur 56",
    "sg:city":"Hamois",
    "sg:orig_category":"Artiesten and kunstenaars",
    "sg:phone":"+32 83 21 36 61",
    "sg:postcode":"5360",
    "sg:province":"Namur",
    "wof:name":"Jules Rensonnet",
    "wof:placetype":"venue"
},
  "geometry": {"coordinates":[5.0550451279,50.3438568115],"type":"Point"}
}