{
  "type": "Feature",
  "properties": {
    "iso:country":"BE",
    "sg:address":"Lentewijk 11",
    "sg:city":"Kortrijk",
    "sg:classifiers":[
        {
            "category":"Cafe",
            "type":"Food & Drink"
        }
    ],
    "sg:phone":"+32 56 45 52 78",
    "sg:postcode":"8510",
    "sg:province":"West-Vlaanderen",
    "sg:tags":[
        "caf\u00e9s"
    ],
    "wof:name":"Marcel Bataille",
    "wof:placetype":"venue"
},
  "geometry": {"coordinates":[3.3313090801,50.7418289185],"type":"Point"}
}