{
  "type": "Feature",
  "properties": {
    "addr:full":"Rue De La Chapelleframont 12 Framont Luxembourg 6853",
    "addr:housenumber":"12",
    "addr:postcode":"6853",
    "addr:street":"Rue De La Chapelleframont",
    "iso:country":"BE",
    "sg:address":"Rue De La Chapelleframont 12",
    "sg:city":"Framont",
    "sg:classifiers":[
        {
            "category":"Mining & Drilling",
            "type":"Manufacturing & Wholesale Goods"
        }
    ],
    "sg:phone":"+32 61 53 38 28",
    "sg:postcode":"6853",
    "sg:province":"Luxembourg",
    "sg:tags":[
        "ground"
    ],
    "wof:name":"Arnould Georges",
    "wof:placetype":"venue"
},
  "geometry": {"coordinates":[5.1605811119,49.9196281433],"type":"Point"}
}