{
  "type": "Feature",
  "properties": {
    "iso:country":"BE",
    "sg:address":"Rue E. Picart 20",
    "sg:city":"Ixelles",
    "sg:orig_category":"Diverse bedrijfsbeheeradviesbureaus",
    "sg:phone":"+32 2 345 00 20",
    "sg:postcode":"1050",
    "sg:province":"Bruxelles-Capitale",
    "wof:name":"Seifert M.",
    "wof:placetype":"venue"
},
  "geometry": {"coordinates":[4.3541970253,50.816116333],"type":"Point"}
}