{
  "type": "Feature",
  "properties": {
    "iso:country":"BE",
    "sg:address":"Kortrijksesteenweg 214",
    "sg:city":"St-martens-latem",
    "sg:classifiers":[
        {
            "category":"Travel",
            "subcategory":"Hotels & Motels",
            "type":"Entertainment"
        }
    ],
    "sg:phone":"+32 9 282 31 71",
    "sg:postcode":"9830",
    "sg:province":"Oost-Vlaanderen",
    "sg:tags":[
        "hotels",
        "game",
        "sport",
        "business",
        "restaurant"
    ],
    "wof:name":"T Pompierke Nv",
    "wof:placetype":"venue"
},
  "geometry": {"coordinates":[3.6397531033,51.0196495056],"type":"Point"}
}