{
  "type": "Feature",
  "properties": {
    "iso:country":"BE",
    "sg:address":"Chauss\u00e9e De Bascoup 137a",
    "sg:city":"Anderlues",
    "sg:classifiers":[
        {
            "category":"Home & Garden",
            "subcategory":"Carpets & Floor Coverings",
            "type":"Retail Goods"
        }
    ],
    "sg:phone":"+32 71 52 88 52",
    "sg:postcode":"6150",
    "sg:province":"Hainaut",
    "sg:tags":[
        "automobile",
        "-",
        "upholstering",
        "cover"
    ],
    "wof:name":"Auto Cuir Sanna",
    "wof:placetype":"venue"
},
  "geometry": {"coordinates":[4.2824921608,50.4150886536],"type":"Point"}
}