{
  "type": "Feature",
  "properties": {
    "iso:country":"BE",
    "sg:address":"Dorpsstraat 87",
    "sg:city":"Middelkerke",
    "sg:classifiers":[
        {
            "category":"Restaurant",
            "type":"Food & Drink"
        }
    ],
    "sg:phone":"+32 59 31 14 26",
    "sg:postcode":"8432",
    "sg:province":"West-Vlaanderen",
    "wof:name":"D'halve Maene",
    "wof:placetype":"venue"
},
  "geometry": {"coordinates":[2.876955986,51.1751174927],"type":"Point"}
}