{
  "type": "Feature",
  "properties": {
    "addr:full":"Chemin Du Caillou Qui Bique 19 Honnelles (roisin) Hainaut 7387",
    "addr:housenumber":"19",
    "addr:postcode":"7387",
    "addr:street":"Chemin Du Caillou Qui Bique",
    "iso:country":"BE",
    "sg:address":"Chemin Du Caillou Qui Bique 19",
    "sg:city":"Honnelles (roisin)",
    "sg:classifiers":[
        {
            "category":"Bars & Pubs",
            "type":"Food & Drink"
        }
    ],
    "sg:phone":"+32 65 75 03 52",
    "sg:postcode":"7387",
    "sg:province":"Hainaut",
    "wof:name":"Chant Des Oiseaux (le)",
    "wof:placetype":"venue"
},
  "geometry": {"coordinates":[3.6974899769,50.3631401062],"type":"Point"}
}