{
  "type": "Feature",
  "properties": {
    "addr:full":"Kleine Monnikenwerve 32 Brugge West-Vlaanderen 8000",
    "addr:housenumber":"32",
    "addr:postcode":"8000",
    "addr:street":"Kleine Monnikenwerve",
    "iso:country":"BE",
    "sg:address":"Kleine Monnikenwerve 32",
    "sg:city":"Brugge",
    "sg:classifiers":[
        {
            "category":"Transit Center",
            "subcategory":"Freight",
            "type":"Transportation"
        }
    ],
    "sg:phone":"+32 50 31 11 13",
    "sg:postcode":"8000",
    "sg:province":"West-Vlaanderen",
    "sg:tags":[
        "import",
        "export",
        "-"
    ],
    "wof:name":"Proditel Nv",
    "wof:placetype":"venue"
},
  "geometry": {"coordinates":[3.2020790577,51.2447166443],"type":"Point"}
}