{
  "type": "Feature",
  "properties": {
    "iso:country":"BE",
    "sg:address":"Bergstraat 7ba",
    "sg:city":"Temse",
    "sg:orig_category":"Eleveurs and marchands de porcs",
    "sg:phone":"+32 3 771 18 75",
    "sg:postcode":"9140",
    "sg:province":"Oost-Vlaanderen",
    "wof:name":"Charles Maes",
    "wof:placetype":"venue"
},
  "geometry": {"coordinates":[4.1545348167,51.1237792969],"type":"Point"}
}