{
  "type": "Feature",
  "properties": {
    "iso:country":"BE",
    "sg:address":"Avenue Everard 11",
    "sg:city":"Bruxelles (forest)",
    "sg:classifiers":[
        {
            "category":"Insurance",
            "subcategory":"Insurance Agent",
            "type":"Services"
        }
    ],
    "sg:phone":"+32 2 346 97 57",
    "sg:postcode":"1190",
    "sg:province":"Bruxelles-Capitale",
    "sg:tags":[
        "broker"
    ],
    "wof:name":"Belfor",
    "wof:placetype":"venue"
},
  "geometry": {"coordinates":[4.3376669884,50.8161430359],"type":"Point"}
}