{
  "type": "Feature",
  "properties": {
    "addr:full":"Ninovesteenweg 241 Aalst Oost-Vlaanderen 9320",
    "addr:housenumber":"241",
    "addr:postcode":"9320",
    "addr:street":"Ninovesteenweg",
    "iso:country":"BE",
    "sg:address":"Ninovesteenweg 241",
    "sg:city":"Aalst",
    "sg:classifiers":[
        {
            "category":"Cafe",
            "type":"Food & Drink"
        }
    ],
    "sg:phone":"+32 53 67 00 04",
    "sg:postcode":"9320",
    "sg:province":"Oost-Vlaanderen",
    "sg:tags":[
        "caf\u00e9s"
    ],
    "wof:name":"Caf\u00c9 Industriepark",
    "wof:placetype":"venue"
},
  "geometry": {"coordinates":[4.0351052284,50.9271011353],"type":"Point"}
}