{
  "type": "Feature",
  "properties": {
    "addr:full":"Gentstraat 33 Menen West-Vlaanderen 8930",
    "addr:housenumber":"33",
    "addr:postcode":"8930",
    "addr:street":"Gentstraat",
    "iso:country":"BE",
    "sg:address":"Gentstraat 33",
    "sg:city":"Menen",
    "sg:orig_category":"Slagers",
    "sg:phone":"+32 56 41 36 62",
    "sg:postcode":"8930",
    "sg:province":"West-Vlaanderen",
    "wof:name":"Beenhouwerij David",
    "wof:placetype":"venue"
},
  "geometry": {"coordinates":[3.1921339035,50.7562980652],"type":"Point"}
}