{
  "type": "Feature",
  "properties": {
    "addr:full":"Stationsstraat 45 Haaltert Oost-Vlaanderen 9450",
    "addr:housenumber":"45",
    "addr:postcode":"9450",
    "addr:street":"Stationsstraat",
    "iso:country":"BE",
    "sg:address":"Stationsstraat 45",
    "sg:city":"Haaltert",
    "sg:orig_category":"Syst\u00e8mes de t\u00e9l\u00e9communications. Electrom\u00e9nager, t\u00e9l\u00e9visions and radios",
    "sg:phone":"+32 53 83 22 59",
    "sg:postcode":"9450",
    "sg:province":"Oost-Vlaanderen",
    "wof:name":"Fa. Satelec",
    "wof:placetype":"venue"
},
  "geometry": {"coordinates":[4.0126700401,50.9025382996],"type":"Point"}
}