{
  "type": "Feature",
  "properties": {
    "addr:full":"Leopold Sabbestraat 196 Menen (lauwe) West-Vlaanderen 8930",
    "addr:housenumber":"196",
    "addr:postcode":"8930",
    "addr:street":"Leopold Sabbestraat",
    "iso:country":"BE",
    "sg:address":"Leopold Sabbestraat 196",
    "sg:city":"Menen (lauwe)",
    "sg:classifiers":[
        {
            "category":"Building & Trades",
            "subcategory":"Pest Control",
            "type":"Services"
        }
    ],
    "sg:phone":"+32 56 41 53 95",
    "sg:postcode":"8930",
    "sg:province":"West-Vlaanderen",
    "sg:tags":[
        "painting",
        "contractor"
    ],
    "wof:name":"Lef\u00e8vre J",
    "wof:placetype":"venue"
},
  "geometry": {"coordinates":[3.1282699108,50.7988700867],"type":"Point"}
}