{
  "type": "Feature",
  "properties": {
    "addr:full":"Antwerpsestraat 39 Niel Antwerpen 2845",
    "addr:housenumber":"39",
    "addr:postcode":"2845",
    "addr:street":"Antwerpsestraat",
    "iso:country":"BE",
    "sg:address":"Antwerpsestraat 39",
    "sg:city":"Niel",
    "sg:orig_category":"Beheer onroerend goed Immobili\u00ebnkantoren",
    "sg:phone":"+32 3 888 54 55",
    "sg:postcode":"2845",
    "sg:province":"Antwerpen",
    "wof:name":"Zakenkantoor Serrien",
    "wof:placetype":"venue"
},
  "geometry": {"coordinates":[4.3294801712,51.1078834534],"type":"Point"}
}