{
  "type": "Feature",
  "properties": {
    "iso:country":"BE",
    "sg:address":"Deurnestraat 200b4",
    "sg:city":"Mortsel",
    "sg:classifiers":[
        {
            "category":"Professional",
            "subcategory":"Business Services",
            "type":"Services"
        }
    ],
    "sg:phone":"+32 3 440 61 96",
    "sg:postcode":"2640",
    "sg:province":"Antwerpen",
    "sg:tags":[
        "aux",
        "diver",
        "entreprises"
    ],
    "wof:name":"Bike Organisations",
    "wof:placetype":"venue"
},
  "geometry": {"coordinates":[4.4473252296,51.1812934875],"type":"Point"}
}