{
  "type": "Feature",
  "properties": {
    "iso:country":"BE",
    "sg:address":"Rue De Villance 108",
    "sg:city":"Libin",
    "sg:orig_category":"Entretien and r\u00e9parations de voitures",
    "sg:phone":"+32 61 65 52 86",
    "sg:postcode":"6890",
    "sg:province":"Luxembourg",
    "wof:name":"M. Dom",
    "wof:placetype":"venue"
},
  "geometry": {"coordinates":[5.2549748421,49.9820594788],"type":"Point"}
}