{
  "type": "Feature",
  "properties": {
    "iso:country":"BE",
    "sg:address":"Dr\u00e8ve De Waroux 57",
    "sg:city":"Ans (alleur)",
    "sg:classifiers":[
        {
            "category":"Professional",
            "subcategory":"Accounting & Tax Preparation",
            "type":"Services"
        }
    ],
    "sg:phone":"+32 4 263 37 98",
    "sg:postcode":"4432",
    "sg:province":"Li\u00e8ge",
    "sg:tags":[
        "accountant"
    ],
    "wof:name":"Lambotte C",
    "wof:placetype":"venue"
},
  "geometry": {"coordinates":[5.4930419922,50.6798362732],"type":"Point"}
}