{
  "type": "Feature",
  "properties": {
    "addr:full":"Grensstraat 112b Keerbergen Vlaams-Brabant 3140",
    "addr:housenumber":"112b",
    "addr:postcode":"3140",
    "addr:street":"Grensstraat",
    "iso:country":"BE",
    "sg:address":"Grensstraat 112b",
    "sg:city":"Keerbergen",
    "sg:classifiers":[
        {
            "category":"Professional",
            "subcategory":"Computer Services",
            "type":"Services"
        }
    ],
    "sg:phone":"+32 15 73 02 94",
    "sg:postcode":"3140",
    "sg:province":"Vlaams-Brabant",
    "sg:tags":[
        "-",
        "processing",
        "data",
        "software"
    ],
    "wof:name":"Inforce Bvba",
    "wof:placetype":"venue"
},
  "geometry": {"coordinates":[4.6678729057,51.0196685791],"type":"Point"}
}