{
  "type": "Feature",
  "properties": {
    "iso:country":"BE",
    "sg:address":"Avenue De Spa 26",
    "sg:city":"Verviers",
    "sg:classifiers":[
        {
            "category":"Insurance",
            "subcategory":"Insurance Agent",
            "type":"Services"
        }
    ],
    "sg:phone":"+32 87 22 38 03",
    "sg:postcode":"4800",
    "sg:province":"Li\u00e8ge",
    "sg:tags":[
        "broker"
    ],
    "wof:name":"Taquet Nadine Sa",
    "wof:placetype":"venue"
},
  "geometry": {"coordinates":[5.8626251221,50.5833778381],"type":"Point"}
}