{
  "type": "Feature",
  "properties": {
    "iso:country":"BE",
    "sg:address":"Blarenberglaan 4",
    "sg:city":"Mechelen",
    "sg:orig_category":"DISTRIBUTORS: SYSTEMS",
    "sg:phone":"+32 15 28 93 11",
    "sg:postcode":"2800",
    "sg:province":"Antwerpen",
    "wof:name":"Fleetguard N.v",
    "wof:placetype":"venue"
},
  "geometry": {"coordinates":[4.4494891167,51.0556106567],"type":"Point"}
}