{
  "type": "Feature",
  "properties": {
    "iso:country":"BE",
    "sg:address":"Rijksweg 406",
    "sg:city":"Maasmechelen",
    "sg:classifiers":[
        {
            "category":"Home & Garden",
            "subcategory":"Carpets & Floor Coverings",
            "type":"Retail Goods"
        }
    ],
    "sg:phone":"+32 89 77 18 86",
    "sg:postcode":"3630",
    "sg:province":"Limburg",
    "sg:tags":[
        "parquet"
    ],
    "wof:name":"Dreamline Plafonds Bvba",
    "wof:placetype":"venue"
},
  "geometry": {"coordinates":[5.6958351135,50.9655609131],"type":"Point"}
}