{
  "type": "Feature",
  "properties": {
    "addr:full":"Munthofstraat 135 Sint-gillis/saint-gilles Bruxelles-Capitale 1060",
    "addr:housenumber":"135",
    "addr:postcode":"1060",
    "addr:street":"Munthofstraat",
    "iso:country":"BE",
    "sg:address":"Munthofstraat 135",
    "sg:city":"Sint-gillis/saint-gilles",
    "sg:orig_category":"Advocaten and juridische adviseurs",
    "sg:phone":"+32 2 538 38 08",
    "sg:postcode":"1060",
    "sg:province":"Bruxelles-Capitale",
    "wof:name":"X. Huberland",
    "wof:placetype":"venue"
},
  "geometry": {"coordinates":[4.3458957672,50.8286209106],"type":"Point"}
}