{
  "type": "Feature",
  "properties": {
    "iso:country":"BE",
    "sg:address":"Rue Basse 8",
    "sg:city":"Ittre",
    "sg:orig_category":"Artsen and specialisten",
    "sg:phone":"+32 67 64 94 14",
    "sg:postcode":"1460",
    "sg:province":"Brabant Wallon",
    "wof:name":"Sabine Vliers",
    "wof:placetype":"venue"
},
  "geometry": {"coordinates":[4.2634019852,50.6498146057],"type":"Point"}
}