{
  "type": "Feature",
  "properties": {
    "iso:country":"BE",
    "sg:address":"Turnhoutsebaan 416",
    "sg:city":"Schilde",
    "sg:orig_category":"Slagers",
    "sg:phone":"+32 3 384 26 76",
    "sg:postcode":"2970",
    "sg:province":"Antwerpen",
    "wof:name":"Kwaliteitslagerij Patrick",
    "wof:placetype":"venue"
},
  "geometry": {"coordinates":[4.5913109779,51.2438354492],"type":"Point"}
}