{
  "type": "Feature",
  "properties": {
    "iso:country":"BE",
    "sg:address":"Grand Rue 108",
    "sg:city":"Courcelles (trazegnies)",
    "sg:classifiers":[
        {
            "category":"Insurance",
            "subcategory":"Insurance Agent",
            "type":"Services"
        }
    ],
    "sg:phone":"+32 71 45 15 07",
    "sg:postcode":"6183",
    "sg:province":"Hainaut",
    "sg:tags":[
        "broker"
    ],
    "wof:name":"Druine Jacques",
    "wof:placetype":"venue"
},
  "geometry": {"coordinates":[4.3350520134,50.4609794617],"type":"Point"}
}