{
  "type": "Feature",
  "properties": {
    "addr:full":"Avenue Des Etats-unis 1bb Tournai Hainaut 7500",
    "addr:housenumber":"1bb",
    "addr:postcode":"7500",
    "addr:street":"Avenue Des Etats-Unis",
    "iso:country":"BE",
    "sg:address":"Avenue Des Etats-unis 1bb",
    "sg:city":"Tournai",
    "sg:orig_category":"Herstellingen and onderhoud van auto's",
    "sg:phone":"+32 69 22 25 35",
    "sg:postcode":"7500",
    "sg:province":"Hainaut",
    "wof:name":"Gery Tellin",
    "wof:placetype":"venue"
},
  "geometry": {"coordinates":[3.3970189095,50.601398468],"type":"Point"}
}