{
  "type": "Feature",
  "properties": {
    "iso:country":"BE",
    "sg:address":"Maastrichterstraat 40",
    "sg:city":"Hasselt",
    "sg:classifiers":[
        {
            "category":"Autos & Motor Vehicles",
            "subcategory":"Boat Sales",
            "type":"Retail Goods"
        }
    ],
    "sg:phone":"+32 11 26 12 80",
    "sg:postcode":"3500",
    "sg:province":"Limburg",
    "sg:tags":[
        "balloon"
    ],
    "wof:name":"Bibo Ballon",
    "wof:placetype":"venue"
},
  "geometry": {"coordinates":[5.3395028114,50.9294204712],"type":"Point"}
}