{
  "type": "Feature",
  "properties": {
    "addr:full":"Groeningestraat 6 Poperinge West-Vlaanderen 8970",
    "addr:housenumber":"6",
    "addr:postcode":"8970",
    "addr:street":"Groeningestraat",
    "iso:country":"BE",
    "sg:address":"Groeningestraat 6",
    "sg:city":"Poperinge",
    "sg:orig_category":"Eleveurs and marchands de porcs",
    "sg:phone":"+32 57 33 42 72",
    "sg:postcode":"8970",
    "sg:province":"West-Vlaanderen",
    "wof:name":"Noel Decat",
    "wof:placetype":"venue"
},
  "geometry": {"coordinates":[2.7239789963,50.8735275269],"type":"Point"}
}