{
  "type": "Feature",
  "properties": {
    "iso:country":"BE",
    "sg:address":"Lintkasteelstraat 9",
    "sg:city":"Grimbergen",
    "sg:orig_category":"Producteurs de l\u00e9gumes. Eleveurs de bovins",
    "sg:phone":"+32 2 269 31 55",
    "sg:postcode":"1850",
    "sg:province":"Vlaams-Brabant",
    "wof:name":"Maurice Robberechts",
    "wof:placetype":"venue"
},
  "geometry": {"coordinates":[4.3904380798,50.9534568787],"type":"Point"}
}