{
  "type": "Feature",
  "properties": {
    "iso:country":"BE",
    "sg:address":"Val D'heure 42",
    "sg:city":"Ham-sur-heure-nalinnes (ham-sur-heure)",
    "sg:classifiers":[
        {
            "category":"Arena",
            "subcategory":"Sports Club",
            "type":"Entertainment"
        }
    ],
    "sg:phone":"+32 71 22 12 23",
    "sg:postcode":"6120",
    "sg:province":"Hainaut",
    "wof:name":"Jacquart J",
    "wof:placetype":"venue"
},
  "geometry": {"coordinates":[4.4008197784,50.3463478088],"type":"Point"}
}