{
  "type": "Feature",
  "properties": {
    "addr:full":"Langestraat 148 Aarschot Vlaams-Brabant 3202",
    "addr:housenumber":"148",
    "addr:postcode":"3202",
    "addr:street":"Langestraat",
    "iso:country":"BE",
    "sg:address":"Langestraat 148",
    "sg:city":"Aarschot",
    "sg:orig_category":"Fruitteelt Groententeelt",
    "sg:phone":"+32 16 50 08 45",
    "sg:postcode":"3202",
    "sg:province":"Vlaams-Brabant",
    "wof:name":"Petrus Nijs",
    "wof:placetype":"venue"
},
  "geometry": {"coordinates":[4.9045491219,50.9832077026],"type":"Point"}
}