{
  "type": "Feature",
  "properties": {
    "addr:full":"Jan Van Stopenberghestraat 5 Gent Oost-Vlaanderen 9000",
    "addr:housenumber":"5",
    "addr:postcode":"9000",
    "addr:street":"Jan Van Stopenberghestraat;Oost-Vlaanderen",
    "iso:country":"BE",
    "sg:address":"Jan Van Stopenberghestraat 5",
    "sg:city":"Gent",
    "sg:classifiers":[
        {
            "category":"Cafe",
            "type":"Food & Drink"
        }
    ],
    "sg:phone":"+32 9 225 68 89",
    "sg:postcode":"9000",
    "sg:province":"Oost-Vlaanderen",
    "sg:tags":[
        "caf\u00e9s"
    ],
    "wof:name":"Duke",
    "wof:placetype":"venue"
},
  "geometry": {"coordinates":[3.7220449448,51.0535736084],"type":"Point"}
}