{
  "type": "Feature",
  "properties": {
    "iso:country":"BE",
    "sg:address":"Rue Middelbourg 90",
    "sg:city":"Watermaal-bosvoorde/watermael-boitsfort",
    "sg:orig_category":"Studios photographiques",
    "sg:phone":"+32 2 673 35 25",
    "sg:postcode":"1170",
    "sg:province":"Bruxelles-Capitale",
    "wof:name":"Jacques Vilet",
    "wof:placetype":"venue"
},
  "geometry": {"coordinates":[4.4183468819,50.7949981689],"type":"Point"}
}