{
  "type": "Feature",
  "properties": {
    "iso:country":"BE",
    "sg:address":"Bosstraat 49",
    "sg:city":"Gooik (leerbeek)",
    "sg:classifiers":[
        {
            "category":"Farming",
            "subcategory":"Farm & Veterinary Services",
            "type":"Manufacturing & Wholesale Goods"
        }
    ],
    "sg:phone":"+32 2 532 41 52",
    "sg:postcode":"1755",
    "sg:province":"Vlaams-Brabant",
    "sg:tags":[
        "agricultural",
        "contractor"
    ],
    "wof:name":"Ots Gebrs",
    "wof:placetype":"venue"
},
  "geometry": {"coordinates":[4.1158599854,50.782119751],"type":"Point"}
}