{
  "type": "Feature",
  "properties": {
    "iso:country":"BE",
    "sg:address":"Stationsstraat 119",
    "sg:city":"Tessenderlo",
    "sg:classifiers":[
        {
            "category":"Retail",
            "subcategory":"Repair Shop",
            "type":"Services"
        }
    ],
    "sg:phone":"+32 476 24 88 10",
    "sg:postcode":"3980",
    "sg:province":"Limburg",
    "sg:tags":[
        "mainten",
        "-",
        "parquet"
    ],
    "wof:name":"Almo Design",
    "wof:placetype":"venue"
},
  "geometry": {"coordinates":[5.0987849236,51.0668487549],"type":"Point"}
}