{
  "type": "Feature",
  "properties": {
    "iso:country":"BE",
    "sg:address":"Leuvensestraat 29",
    "sg:city":"Tienen",
    "sg:classifiers":[
        {
            "category":"Utilities",
            "subcategory":"Mobile Phone",
            "type":"Services"
        }
    ],
    "sg:phone":"+32 16 76 84 10",
    "sg:postcode":"3300",
    "sg:province":"Vlaams-Brabant",
    "sg:tags":[
        "access",
        "gsm",
        "-",
        "apparatus"
    ],
    "wof:name":"Phone House (the)",
    "wof:placetype":"venue"
},
  "geometry": {"coordinates":[4.9285850525,50.8101806641],"type":"Point"}
}