{
  "type": "Feature",
  "properties": {
    "addr:full":"Rue Du Culot 13 Perwez Brabant Wallon 1360",
    "addr:housenumber":"13",
    "addr:postcode":"1360",
    "addr:street":"Rue Du Culot",
    "iso:country":"BE",
    "sg:address":"Rue Du Culot 13",
    "sg:city":"Perwez",
    "sg:orig_category":"Herstellingen and onderhoud van auto's",
    "sg:phone":"+32 81 65 60 96",
    "sg:postcode":"1360",
    "sg:province":"Brabant Wallon",
    "wof:name":"Olivier Wiame",
    "wof:placetype":"venue"
},
  "geometry": {"coordinates":[4.7904801369,50.6410140991],"type":"Point"}
}