{
  "type": "Feature",
  "properties": {
    "addr:full":"Blockmansstraat 11 Steenokkerzeel Vlaams-Brabant 1820",
    "addr:housenumber":"11",
    "addr:postcode":"1820",
    "addr:street":"Blockmansstraat",
    "iso:country":"BE",
    "sg:address":"Blockmansstraat 11",
    "sg:city":"Steenokkerzeel",
    "sg:orig_category":"Producteurs de l\u00e9gumes",
    "sg:phone":"+32 2 759 97 78",
    "sg:postcode":"1820",
    "sg:province":"Vlaams-Brabant",
    "wof:name":"Hendrik Charels",
    "wof:placetype":"venue"
},
  "geometry": {"coordinates":[4.5168709755,50.9058532715],"type":"Point"}
}