{
  "type": "Feature",
  "properties": {
    "iso:country":"BE",
    "sg:address":"Wampenberg 88",
    "sg:city":"Arendonk",
    "sg:classifiers":[
        {
            "category":"Health Services",
            "subcategory":"Doctor",
            "type":"Services"
        }
    ],
    "sg:phone":"+32 14 67 83 10",
    "sg:postcode":"2370",
    "sg:province":"Antwerpen",
    "sg:tags":[
        "medicinephysicians",
        "surgeon"
    ],
    "wof:name":"Bovin P",
    "wof:placetype":"venue"
},
  "geometry": {"coordinates":[5.0946822166,51.3288002014],"type":"Point"}
}