{
  "type": "Feature",
  "properties": {
    "addr:full":"Rue Jehoge 1 Ferri\u00e8res (xhoris) Li\u00e8ge 4190",
    "addr:housenumber":"1",
    "addr:postcode":"4190",
    "addr:street":"Rue Jehoge",
    "iso:country":"BE",
    "sg:address":"Rue Jehoge 1",
    "sg:city":"Ferri\u00e8res (xhoris)",
    "sg:classifiers":[
        {
            "category":"Farming",
            "subcategory":"Livestock Farm",
            "type":"Manufacturing & Wholesale Goods"
        }
    ],
    "sg:phone":"+32 4 369 26 94",
    "sg:postcode":"4190",
    "sg:province":"Li\u00e8ge",
    "sg:tags":[
        "stud"
    ],
    "wof:name":"Banneux J-c",
    "wof:placetype":"venue"
},
  "geometry": {"coordinates":[5.6091761589,50.4447097778],"type":"Point"}
}