{
  "type": "Feature",
  "properties": {
    "addr:full":"Rue D'houffalize 24 Gouvy Luxembourg 6670",
    "addr:housenumber":"24",
    "addr:postcode":"6670",
    "addr:street":"Rue D'Houffalize",
    "iso:country":"BE",
    "sg:address":"Rue D'houffalize 24",
    "sg:city":"Gouvy",
    "sg:orig_category":"Huishoudapparaten, televisies and radio's",
    "sg:phone":"+32 80 51 71 63",
    "sg:postcode":"6670",
    "sg:province":"Luxembourg",
    "wof:name":"Mathieu Jacquet",
    "wof:placetype":"venue"
},
  "geometry": {"coordinates":[5.9473948479,50.186630249],"type":"Point"}
}