{
  "type": "Feature",
  "properties": {
    "addr:full":"Solvijnslaan 10 Brecht Antwerpen 2960",
    "addr:housenumber":"10",
    "addr:postcode":"2960",
    "addr:street":"Solvijnslaan",
    "iso:country":"BE",
    "sg:address":"Solvijnslaan 10",
    "sg:city":"Brecht",
    "sg:classifiers":[
        {
            "category":"Home & Garden",
            "subcategory":"Building Materials",
            "type":"Retail Goods"
        }
    ],
    "sg:phone":"+32 3 290 55 83",
    "sg:postcode":"2960",
    "sg:province":"Antwerpen",
    "sg:tags":[
        "window"
    ],
    "wof:name":"Hertogs Jef Com V",
    "wof:placetype":"venue"
},
  "geometry": {"coordinates":[4.6415200233,51.3512115479],"type":"Point"}
}