{
  "type": "Feature",
  "properties": {
    "iso:country":"BE",
    "sg:address":"Helstraat 37",
    "sg:city":"Diepenbeek",
    "sg:orig_category":"Installatie van metalen schrijnwerk",
    "sg:phone":"+32 11 32 29 88",
    "sg:postcode":"3590",
    "sg:province":"Limburg",
    "wof:name":"Crova",
    "wof:placetype":"venue"
},
  "geometry": {"coordinates":[5.4209918976,50.8843994141],"type":"Point"}
}