{
  "type": "Feature",
  "properties": {
    "addr:full":"Lindenstraat 22 Westerlo Antwerpen 2260",
    "addr:housenumber":"22",
    "addr:postcode":"2260",
    "addr:street":"Lindenstraat",
    "iso:country":"BE",
    "sg:address":"Lindenstraat 22",
    "sg:city":"Westerlo",
    "sg:orig_category":"Boucheries",
    "sg:phone":"+32 14 22 24 06",
    "sg:postcode":"2260",
    "sg:province":"Antwerpen",
    "wof:name":"Beenhouwerij Pieter",
    "wof:placetype":"venue"
},
  "geometry": {"coordinates":[4.9037117958,51.1407165527],"type":"Point"}
}