{
  "type": "Feature",
  "properties": {
    "addr:full":"Schipperstraat 50 Maasmechelen Limburg 3631",
    "addr:housenumber":"50",
    "addr:postcode":"3631",
    "addr:street":"Schipperstraat",
    "iso:country":"BE",
    "sg:address":"Schipperstraat 50",
    "sg:city":"Maasmechelen",
    "sg:orig_category":"Bouwmaterialen Gh",
    "sg:phone":"+32 89 76 46 38",
    "sg:postcode":"3631",
    "sg:province":"Limburg",
    "wof:name":"N.g.m.",
    "wof:placetype":"venue"
},
  "geometry": {"coordinates":[5.7239232063,50.9423713684],"type":"Point"}
}