{
  "type": "Feature",
  "properties": {
    "iso:country":"BE",
    "sg:address":"Arendsstraat 49",
    "sg:city":"Harelbeke",
    "sg:orig_category":"Kinderopvang",
    "sg:phone":"+32 56 72 49 37",
    "sg:postcode":"8530",
    "sg:province":"West-Vlaanderen",
    "wof:name":"Ti-ta Tovenaar",
    "wof:placetype":"venue"
},
  "geometry": {"coordinates":[3.3195400238,50.8561592102],"type":"Point"}
}