{
  "type": "Feature",
  "properties": {
    "iso:country":"BE",
    "sg:address":"Oude Gendarmeriestraat 40b2",
    "sg:city":"Heist-op-den-berg",
    "sg:orig_category":"Sportclubs Sportterreinen and installaties behalve sportcentra",
    "sg:phone":"+32 15 24 47 33",
    "sg:postcode":"2220",
    "sg:province":"Antwerpen",
    "wof:name":"K. Sportkring Heist",
    "wof:placetype":"venue"
},
  "geometry": {"coordinates":[4.7177090645,51.0724258423],"type":"Point"}
}