{
  "type": "Feature",
  "properties": {
    "iso:country":"BE",
    "sg:address":"Jenny Montignylaan 2",
    "sg:city":"Sint-martens-latem",
    "sg:orig_category":"Sportclubs",
    "sg:phone":"+32 9 282 80 83",
    "sg:postcode":"9831",
    "sg:province":"Oost-Vlaanderen",
    "wof:name":"V.d.k. Spaarbank",
    "wof:placetype":"venue"
},
  "geometry": {"coordinates":[3.6015079021,51.0085906982],"type":"Point"}
}