{
  "type": "Feature",
  "properties": {
    "iso:country":"BE",
    "sg:address":"Steenstraat 2",
    "sg:city":"Gistel",
    "sg:orig_category":"Rundveehouders",
    "sg:phone":"+32 59 27 84 22",
    "sg:postcode":"8470",
    "sg:province":"West-Vlaanderen",
    "wof:name":"Bertrand Dehaemers",
    "wof:placetype":"venue"
},
  "geometry": {"coordinates":[2.9000549316,51.1408119202],"type":"Point"}
}