{
  "type": "Feature",
  "properties": {
    "addr:full":"Rue Des Moulins 46 Beyne-heusay Li\u00e8ge 4610",
    "addr:housenumber":"46",
    "addr:postcode":"4610",
    "addr:street":"Rue Des Moulins",
    "iso:country":"BE",
    "sg:address":"Rue Des Moulins 46",
    "sg:city":"Beyne-heusay",
    "sg:orig_category":"Sportclubs",
    "sg:phone":"+32 4 370 64 30",
    "sg:postcode":"4610",
    "sg:province":"Li\u00e8ge",
    "wof:name":"Les Gadlis D\u00c8 P\u00c9ron D\u00b4or",
    "wof:placetype":"venue"
},
  "geometry": {"coordinates":[5.6645789146,50.6330451965],"type":"Point"}
}