{
  "type": "Feature",
  "properties": {
    "addr:full":"Koningin Astridlaan 30 Sint-niklaas Oost-Vlaanderen 9100",
    "addr:housenumber":"30",
    "addr:postcode":"9100",
    "addr:street":"Koningin Astridlaan",
    "iso:country":"BE",
    "sg:address":"Koningin Astridlaan 30",
    "sg:city":"Sint-niklaas",
    "sg:orig_category":"M\u00e9decins and sp\u00e9cialistes",
    "sg:phone":"+32 3 776 04 95",
    "sg:postcode":"9100",
    "sg:province":"Oost-Vlaanderen",
    "wof:name":"De Schrijver",
    "wof:placetype":"venue"
},
  "geometry": {"coordinates":[4.1579561234,51.1571311951],"type":"Point"}
}