{
  "type": "Feature",
  "properties": {
    "addr:full":"Rue Ernest Allard 20 Brussel/bruxelles Bruxelles-Capitale 1000",
    "addr:housenumber":"20",
    "addr:postcode":"1000",
    "addr:street":"Rue Ernest Allard;/",
    "iso:country":"BE",
    "sg:address":"Rue Ernest Allard 20",
    "sg:city":"Brussel/bruxelles",
    "sg:orig_category":"Antiquit\u00e9s. R\u00e9paration and restauration de meubles",
    "sg:phone":"+32 2 512 06 58",
    "sg:postcode":"1000",
    "sg:province":"Bruxelles-Capitale",
    "wof:name":"Maison Autegarden",
    "wof:placetype":"venue"
},
  "geometry": {"coordinates":[4.3545417786,50.8398208618],"type":"Point"}
}