{
  "type": "Feature",
  "properties": {
    "addr:full":"Chauss\u00e9e De Jolimont 191 La Louvi\u00e8re (haine-saint-pierre) Hainaut 7100",
    "addr:housenumber":"191",
    "addr:postcode":"7100",
    "addr:street":"Chausse\u0301E De Jolimont",
    "iso:country":"BE",
    "sg:address":"Chauss\u00e9e De Jolimont 191",
    "sg:city":"La Louvi\u00e8re (haine-saint-pierre)",
    "sg:classifiers":[
        {
            "category":"Shopping",
            "subcategory":"Books",
            "type":"Retail Goods"
        }
    ],
    "sg:phone":"+32 64 22 47 21",
    "sg:postcode":"7100",
    "sg:province":"Hainaut",
    "sg:tags":[
        "bookseller"
    ],
    "wof:name":"Tache D'encre (la)",
    "wof:placetype":"venue"
},
  "geometry": {"coordinates":[4.2160367966,50.4726753235],"type":"Point"}
}