{
  "type": "Feature",
  "properties": {
    "iso:country":"BE",
    "sg:address":"Lindenstraat 28",
    "sg:city":"Keerbergen",
    "sg:orig_category":"Advocaten and juridische adviseurs",
    "sg:phone":"+32 15 52 03 70",
    "sg:postcode":"3140",
    "sg:province":"Vlaams-Brabant",
    "wof:name":"Erika Van Looy",
    "wof:placetype":"venue"
},
  "geometry": {"coordinates":[4.6346888542,51.0016746521],"type":"Point"}
}