{
  "type": "Feature",
  "properties": {
    "addr:full":"Dorpsstraat 42 Lochristi Oost-Vlaanderen 9080",
    "addr:housenumber":"42",
    "addr:postcode":"9080",
    "addr:street":"Dorpsstraat",
    "iso:country":"BE",
    "sg:address":"Dorpsstraat 42",
    "sg:city":"Lochristi",
    "sg:classifiers":[
        {
            "category":"Wholesale",
            "subcategory":"Wine & Distilled Alcoholic Beverages",
            "type":"Manufacturing & Wholesale Goods"
        }
    ],
    "sg:phone":"+32 9 356 68 76",
    "sg:postcode":"9080",
    "sg:province":"Oost-Vlaanderen",
    "sg:tags":[
        "whol",
        "-",
        "spirit",
        "mfg"
    ],
    "wof:name":"Mis En Bouteille Bvba",
    "wof:placetype":"venue"
},
  "geometry": {"coordinates":[3.8319830894,51.1013832092],"type":"Point"}
}