{
  "type": "Feature",
  "properties": {
    "iso:country":"BE",
    "sg:address":"Izegemstraat 50",
    "sg:city":"Roeselare",
    "sg:orig_category":"M\u00e9decins and sp\u00e9cialistes",
    "sg:phone":"+32 51 24 99 76",
    "sg:postcode":"8800",
    "sg:province":"West-Vlaanderen",
    "wof:name":"Jan Neirynck",
    "wof:placetype":"venue"
},
  "geometry": {"coordinates":[3.1597409248,50.9318504333],"type":"Point"}
}