{
  "type": "Feature",
  "properties": {
    "iso:country":"BE",
    "sg:address":"Lepelstraat 36",
    "sg:city":"Laarne (groot)",
    "sg:classifiers":[
        {
            "category":"Restaurant",
            "type":"Food & Drink"
        }
    ],
    "sg:phone":"+32 9 369 01 34",
    "sg:postcode":"9270",
    "sg:province":"Oost-Vlaanderen",
    "sg:tags":[
        "brasserie"
    ],
    "wof:name":"Brouwerij Walrave",
    "wof:placetype":"venue"
},
  "geometry": {"coordinates":[3.8531079292,51.0303764343],"type":"Point"}
}