{
  "type": "Feature",
  "properties": {
    "iso:country":"BE",
    "sg:address":"Schuiferskapelsesteenweg 66bc",
    "sg:city":"Tielt",
    "sg:orig_category":"Installatie van houten of kunststof schrijnwerk",
    "sg:phone":"+32 51 40 12 99",
    "sg:postcode":"8700",
    "sg:province":"West-Vlaanderen",
    "wof:name":"Marc Nemegheer",
    "wof:placetype":"venue"
},
  "geometry": {"coordinates":[3.3319580555,51.0195198059],"type":"Point"}
}