{
  "type": "Feature",
  "properties": {
    "iso:country":"BE",
    "sg:address":"Waterpachtgoedstraat 5",
    "sg:city":"Ledegem (rollegem Kapelle)",
    "sg:classifiers":[
        {
            "category":"Health Services",
            "subcategory":"Nursing And Care Facility",
            "type":"Services"
        }
    ],
    "sg:phone":"+32 56 50 99 04",
    "sg:postcode":"8880",
    "sg:province":"West-Vlaanderen",
    "sg:tags":[
        "home"
    ],
    "wof:name":"Rebry G",
    "wof:placetype":"venue"
},
  "geometry": {"coordinates":[3.1604499817,50.8654060364],"type":"Point"}
}