{
  "type": "Feature",
  "properties": {
    "addr:full":"Borghthoevestraat 5 Brecht Antwerpen 2960",
    "addr:housenumber":"5",
    "addr:postcode":"2960",
    "addr:street":"Borghthoevestraat",
    "iso:country":"BE",
    "sg:address":"Borghthoevestraat 5",
    "sg:city":"Brecht",
    "sg:classifiers":[
        {
            "category":"Freight",
            "type":"Transportation"
        }
    ],
    "sg:phone":"+32 3 313 71 11",
    "sg:postcode":"2960",
    "sg:province":"Antwerpen",
    "sg:tags":[
        "-",
        "transport"
    ],
    "wof:name":"Jolitrans",
    "wof:placetype":"venue"
},
  "geometry": {"coordinates":[4.6360092163,51.353603363],"type":"Point"}
}