{
  "type": "Feature",
  "properties": {
    "addr:full":"Rue Grande Pierr\u00c8re 16 Sambreville Namur 5060",
    "addr:housenumber":"16",
    "addr:postcode":"5060",
    "addr:street":"Rue Grande Pierre\u0300Re",
    "iso:country":"BE",
    "sg:address":"Rue Grande Pierr\u00c8re 16",
    "sg:city":"Sambreville",
    "sg:orig_category":"Drogisterijen",
    "sg:phone":"+32 71 77 69 19",
    "sg:postcode":"5060",
    "sg:province":"Namur",
    "wof:name":"Philippe Parmentier",
    "wof:placetype":"venue"
},
  "geometry": {"coordinates":[4.6333961487,50.4245758057],"type":"Point"}
}