{
  "type": "Feature",
  "properties": {
    "addr:full":"Rue Victor Allard 155 Bruxelles (uccle) Bruxelles-Capitale 1180",
    "addr:housenumber":"155",
    "addr:postcode":"1180",
    "addr:street":"Rue Victor Allard",
    "iso:country":"BE",
    "sg:address":"Rue Victor Allard 155",
    "sg:city":"Bruxelles (uccle)",
    "sg:classifiers":[
        {
            "category":"Autos & Motor Vehicles",
            "subcategory":"Automobile Sales",
            "type":"Retail Goods"
        }
    ],
    "sg:phone":"+32 2 347 58 42",
    "sg:postcode":"1180",
    "sg:province":"Bruxelles-Capitale",
    "sg:tags":[
        "car",
        "used",
        "-"
    ],
    "wof:name":"Auto Gazelle",
    "wof:placetype":"venue"
},
  "geometry": {"coordinates":[4.3302631378,50.8012275696],"type":"Point"}
}