{
  "type": "Feature",
  "properties": {
    "addr:full":"Rue De Gembloux 199 Namur Namur 5002",
    "addr:housenumber":"199",
    "addr:postcode":"5002",
    "addr:street":"Rue De Gembloux",
    "iso:country":"BE",
    "sg:address":"Rue De Gembloux 199",
    "sg:city":"Namur",
    "sg:classifiers":[
        {
            "category":"Personal",
            "subcategory":"Beauty Salon",
            "type":"Services"
        }
    ],
    "sg:phone":"+32 81 73 32 38",
    "sg:postcode":"5002",
    "sg:province":"Namur",
    "sg:tags":[
        "de",
        "coiffure"
    ],
    "wof:name":"Epi Rebelle",
    "wof:placetype":"venue"
},
  "geometry": {"coordinates":[4.8462319374,50.4782791138],"type":"Point"}
}