{
  "type": "Feature",
  "properties": {
    "addr:full":"Oelegemsteenweg 3 Schilde Antwerpen 2970",
    "addr:housenumber":"3",
    "addr:postcode":"2970",
    "addr:street":"Oelegemsteenweg",
    "iso:country":"BE",
    "sg:address":"Oelegemsteenweg 3",
    "sg:city":"Schilde",
    "sg:classifiers":[
        {
            "category":"Cafe",
            "type":"Food & Drink"
        }
    ],
    "sg:phone":"+32 3 383 62 28",
    "sg:postcode":"2970",
    "sg:province":"Antwerpen",
    "sg:tags":[
        "caf\u00e9s"
    ],
    "wof:name":"Caf\u00c9 Puttenhof",
    "wof:placetype":"venue"
},
  "geometry": {"coordinates":[4.5883607864,51.2331771851],"type":"Point"}
}