{
  "type": "Feature",
  "properties": {
    "addr:full":"Rue Du Wanroux 14 Genappe Brabant Wallon 1470",
    "addr:housenumber":"14",
    "addr:postcode":"1470",
    "addr:street":"Rue Du Wanroux;Wallon",
    "iso:country":"BE",
    "sg:address":"Rue Du Wanroux 14",
    "sg:city":"Genappe",
    "sg:orig_category":"Installatie van houten of kunststof schrijnwerk Vloer- and muurbekleding",
    "sg:phone":"+32 10 65 81 47",
    "sg:postcode":"1470",
    "sg:province":"Brabant Wallon",
    "wof:name":"Francia-vanosmael",
    "wof:placetype":"venue"
},
  "geometry": {"coordinates":[4.5129032135,50.6421089172],"type":"Point"}
}