{
  "type": "Feature",
  "properties": {
    "addr:full":"Papenvest 78 Brussel/bruxelles Bruxelles-Capitale 1000",
    "addr:housenumber":"78",
    "addr:postcode":"1000",
    "addr:street":"Papenvest;/",
    "iso:country":"BE",
    "sg:address":"Papenvest 78",
    "sg:city":"Brussel/bruxelles",
    "sg:orig_category":"Maatschappelijke dienstverlening",
    "sg:phone":"+32 2 511 33 60",
    "sg:postcode":"1000",
    "sg:province":"Bruxelles-Capitale",
    "wof:name":"Vclb-centrum",
    "wof:placetype":"venue"
},
  "geometry": {"coordinates":[4.343416214,50.8508071899],"type":"Point"}
}