{
  "type": "Feature",
  "properties": {
    "iso:country":"BE",
    "sg:address":"Beemdenstraat 5",
    "sg:city":"Broechem",
    "sg:classifiers":[
        {
            "category":"Shopping",
            "subcategory":"Crafts & Fabrics",
            "type":"Retail Goods"
        }
    ],
    "sg:phone":"+32 3 485 54 33",
    "sg:postcode":"2520",
    "sg:province":"Antwerpen",
    "sg:tags":[
        "trade",
        "timber"
    ],
    "wof:name":"J. Van Den Heurck B.v.b.a.",
    "wof:placetype":"venue"
},
  "geometry": {"coordinates":[4.6199240685,51.1839828491],"type":"Point"}
}