{
  "type": "Feature",
  "properties": {
    "addr:full":"Hoekstraat 23 Sint-amands Antwerpen 2890",
    "addr:housenumber":"23",
    "addr:postcode":"2890",
    "addr:street":"Hoekstraat",
    "iso:country":"BE",
    "sg:address":"Hoekstraat 23",
    "sg:city":"Sint-amands",
    "sg:classifiers":[
        {
            "category":"Home & Garden",
            "subcategory":"Carpets & Floor Coverings",
            "type":"Retail Goods"
        }
    ],
    "sg:phone":"+32 52 33 59 29",
    "sg:postcode":"2890",
    "sg:province":"Antwerpen",
    "sg:tags":[
        "l\u00e9gumes",
        "fruit",
        "gr"
    ],
    "wof:name":"Groenten & Fruit Sarens",
    "wof:placetype":"venue"
},
  "geometry": {"coordinates":[4.2070941925,51.0469017029],"type":"Point"}
}