{
  "type": "Feature",
  "properties": {
    "addr:full":"Rue Des Tanneurs 12ba Soignies Hainaut 7060",
    "addr:housenumber":"12ba",
    "addr:postcode":"7060",
    "addr:street":"Rue Des Tanneurs",
    "iso:country":"BE",
    "sg:address":"Rue Des Tanneurs 12ba",
    "sg:city":"Soignies",
    "sg:orig_category":"Agences d\u00b4interim and personnel temporaire",
    "sg:phone":"+32 67 33 19 06",
    "sg:postcode":"7060",
    "sg:province":"Hainaut",
    "wof:name":"T-int\u00c9rim",
    "wof:placetype":"venue"
},
  "geometry": {"coordinates":[4.0765380859,50.5762863159],"type":"Point"}
}