{
  "type": "Feature",
  "properties": {
    "iso:country":"BE",
    "sg:address":"Westpoeselstraat 1",
    "sg:city":"Lo-reninge (noordschote)",
    "sg:classifiers":[
        {
            "category":"Farming",
            "subcategory":"Livestock Farm",
            "type":"Manufacturing & Wholesale Goods"
        }
    ],
    "sg:phone":"+32 51 54 40 95",
    "sg:postcode":"8647",
    "sg:province":"West-Vlaanderen",
    "sg:tags":[
        "buyer"
    ],
    "wof:name":"Vandenbroele G",
    "wof:placetype":"venue"
},
  "geometry": {"coordinates":[2.8280620575,50.954208374],"type":"Point"}
}