{
  "type": "Feature",
  "properties": {
    "addr:full":"Rue Du Stade 18 Dour Hainaut 7370",
    "addr:housenumber":"18",
    "addr:postcode":"7370",
    "addr:street":"Rue Du Stade;Hainaut",
    "iso:country":"BE",
    "sg:address":"Rue Du Stade 18",
    "sg:city":"Dour",
    "sg:orig_category":"Pain, p\u00e2tisseries and confiseries",
    "sg:phone":"+32 65 65 31 22",
    "sg:postcode":"7370",
    "sg:province":"Hainaut",
    "wof:name":"Mattucci",
    "wof:placetype":"venue"
},
  "geometry": {"coordinates":[3.7785201073,50.39635849],"type":"Point"}
}