{
  "type": "Feature",
  "properties": {
    "addr:full":"Kazernestraat 68 Brussel/bruxelles Bruxelles-Capitale 1000",
    "addr:housenumber":"68",
    "addr:postcode":"1000",
    "addr:street":"Kazernestraat;/",
    "iso:country":"BE",
    "sg:address":"Kazernestraat 68",
    "sg:city":"Brussel/bruxelles",
    "sg:orig_category":"Diverse organisaties and verenigingen",
    "sg:phone":"+32 2 513 56 93",
    "sg:postcode":"1000",
    "sg:province":"Bruxelles-Capitale",
    "wof:name":"Ikove - Cidepe",
    "wof:placetype":"venue"
},
  "geometry": {"coordinates":[4.3421759605,50.8419113159],"type":"Point"}
}