{
  "type": "Feature",
  "properties": {
    "addr:full":"Verbindingslaan 36 Leuven (heverlee) Vlaams-Brabant 3001",
    "addr:housenumber":"36",
    "addr:postcode":"3001",
    "addr:street":"Verbindingslaan",
    "iso:country":"BE",
    "sg:address":"Verbindingslaan 36",
    "sg:city":"Leuven (heverlee)",
    "sg:classifiers":[
        {
            "category":"Building & Trades",
            "subcategory":"Construction",
            "type":"Services"
        }
    ],
    "sg:phone":"+32 16 40 44 89",
    "sg:postcode":"3001",
    "sg:province":"Vlaams-Brabant",
    "sg:tags":[
        "installation",
        "-",
        "central",
        "heating"
    ],
    "wof:name":"Vkc Poot W",
    "wof:placetype":"venue"
},
  "geometry": {"coordinates":[4.7015528679,50.860458374],"type":"Point"}
}