{
  "type": "Feature",
  "properties": {
    "iso:country":"BE",
    "sg:address":"Avenue Bar A D'huart 28",
    "sg:city":"Sint-pieters-woluwe/woluwe-sai",
    "sg:orig_category":"Herstellingen and onderhoud van auto's",
    "sg:phone":"+32 2 779 29 80",
    "sg:postcode":"1150",
    "sg:province":"Bruxelles-Capitale",
    "wof:name":"Etablissement Peugeot Stockel",
    "wof:placetype":"venue"
},
  "geometry": {"coordinates":[4.4663949013,50.8389625549],"type":"Point"}
}