{
  "type": "Feature",
  "properties": {
    "iso:country":"BE",
    "sg:address":"Dampstraat 9",
    "sg:city":"Meeuwen-gruitrode",
    "sg:orig_category":"Varkenskwekers",
    "sg:phone":"+32 11 79 29 35",
    "sg:postcode":"3670",
    "sg:province":"Limburg",
    "wof:name":"Alice Evens",
    "wof:placetype":"venue"
},
  "geometry": {"coordinates":[5.5267400742,51.0694389343],"type":"Point"}
}