{
  "type": "Feature",
  "properties": {
    "iso:country":"BE",
    "sg:address":"Av. Baron De Moreau",
    "sg:city":"Namur",
    "sg:orig_category":"H\u00f4tels",
    "sg:phone":"+32 81 23 00 28",
    "sg:postcode":"5000",
    "sg:province":"Namur",
    "wof:name":"Hotel Beau Regard",
    "wof:placetype":"venue"
},
  "geometry": {"coordinates":[4.8634738922,50.4573020935],"type":"Point"}
}