{
  "type": "Feature",
  "properties": {
    "addr:full":"Brouwerijstraat 33 Halle Vlaams-Brabant 1500",
    "addr:housenumber":"33",
    "addr:postcode":"1500",
    "addr:street":"Brouwerijstraat",
    "iso:country":"BE",
    "sg:address":"Brouwerijstraat 33",
    "sg:city":"Halle",
    "sg:classifiers":[
        {
            "category":"Manufacturing",
            "subcategory":"Metals",
            "type":"Manufacturing & Wholesale Goods"
        }
    ],
    "sg:phone":"+32 2 356 90 24",
    "sg:postcode":"1500",
    "sg:province":"Vlaams-Brabant",
    "sg:tags":[
        "sheet",
        "machinery",
        "working"
    ],
    "wof:name":"Tremac Bvba",
    "wof:placetype":"venue"
},
  "geometry": {"coordinates":[4.2399568558,50.7247276306],"type":"Point"}
}