{
  "type": "Feature",
  "properties": {
    "addr:full":"Kleine Wouwer 29 Box 3 Meise Vlaams-Brabant 1860",
    "addr:housenumber":"29;3",
    "addr:postcode":"1860",
    "addr:street":"Kleine Wouwer;Box",
    "iso:country":"BE",
    "sg:address":"Kleine Wouwer 29 Box 3",
    "sg:city":"Meise",
    "sg:classifiers":[
        {
            "category":"Professional",
            "subcategory":"Management & Consulting",
            "type":"Services"
        }
    ],
    "sg:phone":"+32 2 270 36 05",
    "sg:postcode":"1860",
    "sg:province":"Vlaams-Brabant",
    "sg:tags":[
        "consultant"
    ],
    "wof:name":"Klinkers Public Policy Consultants",
    "wof:placetype":"venue"
},
  "geometry": {"coordinates":[4.3185238838,50.9368362427],"type":"Point"}
}