{
  "type": "Feature",
  "properties": {
    "addr:full":"Goormansdijk 12 Dessel Antwerpen 2480",
    "addr:housenumber":"12",
    "addr:postcode":"2480",
    "addr:street":"Goormansdijk",
    "iso:country":"BE",
    "sg:address":"Goormansdijk 12",
    "sg:city":"Dessel",
    "sg:orig_category":"Meubelzaken, woning- and keukeninrichting",
    "sg:phone":"+32 14 37 31 22",
    "sg:postcode":"2480",
    "sg:province":"Antwerpen",
    "wof:name":"Arte Design Inelli",
    "wof:placetype":"venue"
},
  "geometry": {"coordinates":[5.1176872253,51.2273750305],"type":"Point"}
}