{
  "type": "Feature",
  "properties": {
    "addr:full":"Koning Albertstraat 40 Hasselt Limburg 3500",
    "addr:housenumber":"40",
    "addr:postcode":"3500",
    "addr:street":"Koning Albertstraat",
    "iso:country":"BE",
    "sg:address":"Koning Albertstraat 40",
    "sg:city":"Hasselt",
    "sg:orig_category":"Jeux and jouets",
    "sg:phone":"+32 11 26 32 94",
    "sg:postcode":"3500",
    "sg:province":"Limburg",
    "wof:name":"Broux",
    "wof:placetype":"venue"
},
  "geometry": {"coordinates":[5.3370871544,50.9283294678],"type":"Point"}
}