{
  "type": "Feature",
  "properties": {
    "iso:country":"BE",
    "sg:address":"Bras Baisy Thy",
    "sg:city":"Genappe",
    "sg:classifiers":[
        {
            "category":"Education",
            "subcategory":"Special Training",
            "type":"Public Place"
        }
    ],
    "sg:phone":"+32 2 653 08 32",
    "sg:postcode":"1470",
    "sg:province":"Brabant Wallon",
    "sg:tags":[
        "school",
        "flying"
    ],
    "wof:name":"U.l.m. Centre Baisy-thy",
    "wof:placetype":"venue"
},
  "geometry": {"coordinates":[4.4828839302,50.609828949],"type":"Point"}
}