{
  "type": "Feature",
  "properties": {
    "addr:full":"Place Roi-albert-ier 9 Rochefort Namur 5580",
    "addr:housenumber":"9",
    "addr:postcode":"5580",
    "addr:street":"Place Roi-Albert-Ier",
    "iso:country":"BE",
    "sg:address":"Place Roi-albert-ier 9",
    "sg:city":"Rochefort",
    "sg:orig_category":"Chaussures",
    "sg:phone":"+32 84 21 11 55",
    "sg:postcode":"5580",
    "sg:province":"Namur",
    "wof:name":"Shoes In The Box",
    "wof:placetype":"venue"
},
  "geometry": {"coordinates":[5.2233099937,50.1594200134],"type":"Point"}
}