{
  "type": "Feature",
  "properties": {
    "addr:full":"Heilig-hartplein 5 Herzele (woubrechtegem) Oost-Vlaanderen 9550",
    "addr:housenumber":"5",
    "addr:postcode":"9550",
    "addr:street":"Heilig-Hartplein;Woubrechtegem Oost-Vlaanderen",
    "iso:country":"BE",
    "sg:address":"Heilig-hartplein 5",
    "sg:city":"Herzele (woubrechtegem)",
    "sg:classifiers":[
        {
            "category":"Bars & Pubs",
            "type":"Food & Drink"
        }
    ],
    "sg:phone":"+32 53 62 29 25",
    "sg:postcode":"9550",
    "sg:province":"Oost-Vlaanderen",
    "wof:name":"Hoefijzer ('t)",
    "wof:placetype":"venue"
},
  "geometry": {"coordinates":[3.9153599739,50.8731040955],"type":"Point"}
}