{
  "type": "Feature",
  "properties": {
    "iso:country":"BE",
    "sg:address":"Rue Du Tilleul 52",
    "sg:city":"Ans (alleur)",
    "sg:classifiers":[
        {
            "category":"Professional",
            "subcategory":"Art Services",
            "type":"Services"
        }
    ],
    "sg:phone":"+32 475 84 39 29",
    "sg:postcode":"4432",
    "sg:province":"Li\u00e8ge",
    "sg:tags":[
        "-",
        "painter",
        "artist"
    ],
    "wof:name":"Broeders S",
    "wof:placetype":"venue"
},
  "geometry": {"coordinates":[5.519007206,50.6760292053],"type":"Point"}
}