{
  "type": "Feature",
  "properties": {
    "iso:country":"BE",
    "sg:address":"Gasthuisstraat 30",
    "sg:city":"Turnhout",
    "sg:orig_category":"Baby- and kinderkleding",
    "sg:phone":"+32 14 42 10 36",
    "sg:postcode":"2300",
    "sg:province":"Antwerpen",
    "wof:name":"Mexx",
    "wof:placetype":"venue"
},
  "geometry": {"coordinates":[4.9462471008,51.3223876953],"type":"Point"}
}