{
  "type": "Feature",
  "properties": {
    "iso:country":"BE",
    "sg:address":"Rue Ferrer 1",
    "sg:city":"Mons",
    "sg:orig_category":"Enseignement maternel and primaire",
    "sg:phone":"+32 65 31 62 86",
    "sg:postcode":"7033",
    "sg:province":"Hainaut",
    "wof:name":"Ecole Fond. Communale",
    "wof:placetype":"venue"
},
  "geometry": {"coordinates":[3.9452989101,50.4211616516],"type":"Point"}
}