{
  "type": "Feature",
  "properties": {
    "iso:country":"BE",
    "sg:address":"Edingensesteenweg 764",
    "sg:city":"Halle",
    "sg:orig_category":"Charpentes and couvertures",
    "sg:phone":"+32 2 361 01 18",
    "sg:postcode":"1502",
    "sg:province":"Vlaams-Brabant",
    "wof:name":"Albert Hubert",
    "wof:placetype":"venue"
},
  "geometry": {"coordinates":[4.1921339035,50.7184295654],"type":"Point"}
}