{
  "type": "Feature",
  "properties": {
    "addr:full":"'t Goed 14 Begijnendijk Vlaams-Brabant 3130",
    "addr:housenumber":"14",
    "addr:postcode":"3130",
    "addr:street":"' T Goed",
    "iso:country":"BE",
    "sg:address":"'t Goed 14",
    "sg:city":"Begijnendijk",
    "sg:classifiers":[
        {
            "category":"Personal",
            "subcategory":"Nail Salon",
            "type":"Services"
        }
    ],
    "sg:phone":"+32 16 57 18 16",
    "sg:postcode":"3130",
    "sg:province":"Vlaams-Brabant",
    "sg:tags":[
        "pedicure"
    ],
    "wof:name":"Huysmans S",
    "wof:placetype":"venue"
},
  "geometry": {"coordinates":[4.7874650955,51.0313606262],"type":"Point"}
}