{
  "type": "Feature",
  "properties": {
    "iso:country":"BE",
    "sg:address":"Monteux 15",
    "sg:city":"Lierneux",
    "sg:orig_category":"Rundveehouders",
    "sg:phone":"+32 80 31 97 45",
    "sg:postcode":"4990",
    "sg:province":"Li\u00e8ge",
    "wof:name":"Bruno Lambotte",
    "wof:placetype":"venue"
},
  "geometry": {"coordinates":[5.7571578026,50.3286476135],"type":"Point"}
}