{
  "type": "Feature",
  "properties": {
    "addr:full":"Rue De Bruxelles 19 Wavre Brabant Wallon 1300",
    "addr:housenumber":"19;1300",
    "addr:street":"Rue De Bruxelles",
    "iso:country":"BE",
    "sg:address":"Rue De Bruxelles 19",
    "sg:city":"Wavre",
    "sg:classifiers":[
        {
            "category":"Recreation",
            "subcategory":"Fishing",
            "type":"Entertainment"
        }
    ],
    "sg:phone":"+32 10 22 77 36",
    "sg:postcode":"1300",
    "sg:province":"Brabant Wallon",
    "sg:tags":[
        "tackle"
    ],
    "wof:name":"Relais Du P\u00eacheur",
    "wof:placetype":"venue"
},
  "geometry": {"coordinates":[4.6115131378,50.7178001404],"type":"Point"}
}