{
  "type": "Feature",
  "properties": {
    "iso:country":"BE",
    "sg:address":"Burgemeesterstraat 10",
    "sg:city":"Sint-martens-latem",
    "sg:classifiers":[
        {
            "category":"Insurance",
            "subcategory":"Insurance Agent",
            "type":"Services"
        }
    ],
    "sg:phone":"+32 9 282 87 92",
    "sg:postcode":"9830",
    "sg:province":"Oost-Vlaanderen",
    "sg:tags":[
        "-",
        "representative"
    ],
    "wof:name":"Steyaert J",
    "wof:placetype":"venue"
},
  "geometry": {"coordinates":[3.6305658817,51.0164871216],"type":"Point"}
}