{
  "type": "Feature",
  "properties": {
    "addr:full":"Brakelsesteenweg 210 Ninove Oost-Vlaanderen 9406",
    "addr:housenumber":"210",
    "addr:postcode":"9406",
    "addr:street":"Brakelsesteenweg",
    "iso:country":"BE",
    "sg:address":"Brakelsesteenweg 210",
    "sg:city":"Ninove",
    "sg:orig_category":"M\u00e9decins and sp\u00e9cialistes",
    "sg:phone":"+32 54 32 03 25",
    "sg:postcode":"9406",
    "sg:province":"Oost-Vlaanderen",
    "wof:name":"Peter Coigniez",
    "wof:placetype":"venue"
},
  "geometry": {"coordinates":[3.9948589802,50.8342704773],"type":"Point"}
}