{
  "type": "Feature",
  "properties": {
    "addr:full":"Kraaienstraat 83 Beringen (koersel) Limburg 3582",
    "addr:housenumber":"83",
    "addr:postcode":"3582",
    "addr:street":"Kraaienstraat",
    "iso:country":"BE",
    "sg:address":"Kraaienstraat 83",
    "sg:city":"Beringen (koersel)",
    "sg:classifiers":[
        {
            "category":"Manufacturing",
            "subcategory":"Metals",
            "type":"Manufacturing & Wholesale Goods"
        }
    ],
    "sg:phone":"+32 11 42 49 52",
    "sg:postcode":"3582",
    "sg:province":"Limburg",
    "sg:tags":[
        "ornamental",
        "work",
        "-"
    ],
    "wof:name":"Kerfs J",
    "wof:placetype":"venue"
},
  "geometry": {"coordinates":[5.2708749771,51.0595359802],"type":"Point"}
}