{
  "type": "Feature",
  "properties": {
    "iso:country":"BE",
    "sg:address":"Sint-gillislaan 2",
    "sg:city":"Dendermonde",
    "sg:orig_category":"Electrom\u00e9nager, t\u00e9l\u00e9visions and radios",
    "sg:phone":"+32 52 21 35 81",
    "sg:postcode":"9200",
    "sg:province":"Oost-Vlaanderen",
    "wof:name":"Invicto",
    "wof:placetype":"venue"
},
  "geometry": {"coordinates":[4.1110668182,51.0193367004],"type":"Point"}
}