{
  "type": "Feature",
  "properties": {
    "iso:country":"BE",
    "sg:address":"Kruisweg 8",
    "sg:city":"Anzegem",
    "sg:classifiers":[
        {
            "category":"Shopping",
            "subcategory":"Florist",
            "type":"Retail Goods"
        }
    ],
    "sg:phone":"+32 56 68 13 56",
    "sg:postcode":"8570",
    "sg:province":"West-Vlaanderen",
    "wof:name":"Florini",
    "wof:placetype":"venue"
},
  "geometry": {"coordinates":[3.4714889526,50.8421516418],"type":"Point"}
}