{
  "type": "Feature",
  "properties": {
    "addr:full":"Mechelsesteenweg 5 Heist-op-den-berg Antwerpen 2220",
    "addr:housenumber":"5",
    "addr:postcode":"2220",
    "addr:street":"Mechelsesteenweg",
    "iso:country":"BE",
    "sg:address":"Mechelsesteenweg 5",
    "sg:city":"Heist-op-den-berg",
    "sg:classifiers":[
        {
            "category":"Shopping",
            "subcategory":"Stationery & Office Supplies",
            "type":"Retail Goods"
        }
    ],
    "sg:phone":"+32 15 25 12 11",
    "sg:postcode":"2220",
    "sg:province":"Antwerpen",
    "sg:tags":[
        "-"
    ],
    "wof:name":"Nvh-new Van Heukelom Kantoormachines",
    "wof:placetype":"venue"
},
  "geometry": {"coordinates":[4.707321167,51.0738601685],"type":"Point"}
}