{
  "type": "Feature",
  "properties": {
    "addr:full":"Vorstse Steenweg 93 Sint-gillis/saint-gilles Bruxelles-Capitale 1060",
    "addr:housenumber":"93",
    "addr:postcode":"1060",
    "addr:street":"Vorstse Steenweg",
    "iso:country":"BE",
    "sg:address":"Vorstse Steenweg 93",
    "sg:city":"Sint-gillis/saint-gilles",
    "sg:classifiers":[
        {
            "category":"Cafe",
            "type":"Food & Drink"
        }
    ],
    "sg:phone":"+32 2 538 89 11",
    "sg:postcode":"1060",
    "sg:province":"Bruxelles-Capitale",
    "sg:tags":[
        "caf\u00e9s"
    ],
    "wof:name":"Caf\u00c9 Regoa",
    "wof:placetype":"venue"
},
  "geometry": {"coordinates":[4.3386387825,50.8309898376],"type":"Point"}
}