{
  "type": "Feature",
  "properties": {
    "iso:country":"BE",
    "sg:address":"Martijn Van Torhoutstraat 14bis",
    "sg:city":"Oudenaarde",
    "sg:classifiers":[
        {
            "category":"Professional",
            "type":"Services"
        }
    ],
    "sg:phone":"+32 55 30 10 74",
    "sg:postcode":"9700",
    "sg:province":"Oost-Vlaanderen",
    "sg:tags":[
        "industrial",
        "automation"
    ],
    "wof:name":"Automation & Controls",
    "wof:placetype":"venue"
},
  "geometry": {"coordinates":[3.6215500832,50.8480606079],"type":"Point"}
}