{
  "type": "Feature",
  "properties": {
    "iso:country":"BE",
    "sg:address":"Beernemsteenweg 75ba",
    "sg:city":"Wingene",
    "sg:classifiers":[
        {
            "category":"Personal",
            "subcategory":"Beauty Salon",
            "type":"Services"
        }
    ],
    "sg:phone":"+32 51 65 56 87",
    "sg:postcode":"8750",
    "sg:province":"West-Vlaanderen",
    "sg:tags":[
        "de",
        "coiffure"
    ],
    "wof:name":"Coiffure Mariette",
    "wof:placetype":"venue"
},
  "geometry": {"coordinates":[3.2786650658,51.0635375977],"type":"Point"}
}