{
  "type": "Feature",
  "properties": {
    "iso:country":"BE",
    "sg:address":"Avenue De Selliers De Moranville 86b3",
    "sg:city":"Sint-agatha-berchem/berchem-sainte-agathe",
    "sg:orig_category":"Peinture. Construction de maisons. Rev\u00eatements pour sols and murs",
    "sg:phone":"+32 2 465 55 60",
    "sg:postcode":"1082",
    "sg:province":"Bruxelles-Capitale",
    "wof:name":"Jean Donn\u00c9",
    "wof:placetype":"venue"
},
  "geometry": {"coordinates":[4.291053772,50.8666038513],"type":"Point"}
}