{
  "type": "Feature",
  "properties": {
    "addr:full":"Chauss\u00c9e De Charleroi 45 Sint-gillis/saint-gilles Bruxelles-Capitale 1060",
    "addr:housenumber":"45",
    "addr:postcode":"1060",
    "addr:street":"Chausse\u0301E De Charleroi",
    "iso:country":"BE",
    "sg:address":"Chauss\u00c9e De Charleroi 45",
    "sg:city":"Sint-gillis/saint-gilles",
    "sg:orig_category":"Boucheries",
    "sg:phone":"+32 2 538 65 81",
    "sg:postcode":"1060",
    "sg:province":"Bruxelles-Capitale",
    "wof:name":"Boucherie Chez Dov",
    "wof:placetype":"venue"
},
  "geometry": {"coordinates":[4.3563990593,50.8319854736],"type":"Point"}
}