{
  "type": "Feature",
  "properties": {
    "addr:full":"Michiel Jansplein 28 Box 2b Lommel Limburg 3920",
    "addr:housenumber":"28;2b",
    "addr:postcode":"3920",
    "addr:street":"Michiel Jansplein;Box",
    "iso:country":"BE",
    "sg:address":"Michiel Jansplein 28 Box 2b",
    "sg:city":"Lommel",
    "sg:classifiers":[
        {
            "category":"Travel",
            "subcategory":"Travel Agent",
            "type":"Entertainment"
        }
    ],
    "sg:phone":"+32 11 55 45 74",
    "sg:postcode":"3920",
    "sg:province":"Limburg",
    "sg:tags":[
        "agency"
    ],
    "wof:name":"Vivaldi Reisbureau Selectair",
    "wof:placetype":"venue"
},
  "geometry": {"coordinates":[5.3089981079,51.2305793762],"type":"Point"}
}