{
  "type": "Feature",
  "properties": {
    "addr:full":"Stationsstraat 117 Rotselaar Vlaams-Brabant 3110",
    "addr:housenumber":"117",
    "addr:postcode":"3110",
    "addr:street":"Stationsstraat",
    "iso:country":"BE",
    "sg:address":"Stationsstraat 117",
    "sg:city":"Rotselaar",
    "sg:classifiers":[
        {
            "category":"Home & Garden",
            "subcategory":"Hardware",
            "type":"Retail Goods"
        }
    ],
    "sg:postcode":"3110",
    "sg:province":"Vlaams-Brabant",
    "sg:tags":[
        "tarpaulin"
    ],
    "wof:name":"Vandenbroek Harry",
    "wof:placetype":"venue"
},
  "geometry": {"coordinates":[4.7237820625,50.9465751648],"type":"Point"}
}