{
  "type": "Feature",
  "properties": {
    "iso:country":"BE",
    "sg:address":"Dijk 99 Box 1",
    "sg:city":"Sint-katelijne-waver (onze-lieve-vrouw-waver)",
    "sg:classifiers":[
        {
            "category":"Insurance",
            "subcategory":"Insurance Agent",
            "type":"Services"
        }
    ],
    "sg:phone":"+32 15 23 73 86",
    "sg:postcode":"2861",
    "sg:province":"Antwerpen",
    "sg:tags":[
        "broker"
    ],
    "wof:name":"Hellemans Verzekeringskantoor Bvba",
    "wof:placetype":"venue"
},
  "geometry": {"coordinates":[4.5730400085,51.0555686951],"type":"Point"}
}