{
  "type": "Feature",
  "properties": {
    "addr:full":"Borchtstraat 14 Meise Vlaams-Brabant 1860",
    "addr:housenumber":"14",
    "addr:postcode":"1860",
    "addr:street":"Borchtstraat",
    "iso:country":"BE",
    "sg:address":"Borchtstraat 14",
    "sg:city":"Meise",
    "sg:orig_category":"Sportclubs",
    "sg:phone":"+32 2 269 00 68",
    "sg:postcode":"1860",
    "sg:province":"Vlaams-Brabant",
    "wof:name":"V.c. Knodde Meise",
    "wof:placetype":"venue"
},
  "geometry": {"coordinates":[4.3336601257,50.9585075378],"type":"Point"}
}