{
  "type": "Feature",
  "properties": {
    "addr:full":"Rue Du Centre 50 Sprimont 4060",
    "addr:housenumber":"50",
    "addr:postcode":"4060",
    "addr:street":"Rue Du Centre",
    "iso:country":"BE",
    "sg:address":"Rue Du Centre 50",
    "sg:city":"Sprimont",
    "sg:classifiers":[
        {
            "category":"Banks & Credit Unions",
            "subcategory":"Bank",
            "type":"Services"
        }
    ],
    "sg:phone":"+32 41822030",
    "sg:postcode":"4060",
    "wof:name":"Aslk-cger Bank",
    "wof:placetype":"venue"
},
  "geometry": {"coordinates":[5.6619229317,50.5033187866],"type":"Point"}
}