{
  "type": "Feature",
  "properties": {
    "iso:country":"BE",
    "sg:address":"Industrielaan 32",
    "sg:city":"Kuurne",
    "sg:classifiers":[
        {
            "category":"Shopping",
            "subcategory":"Crafts & Fabrics",
            "type":"Retail Goods"
        }
    ],
    "sg:phone":"+32 56 35 24 92",
    "sg:postcode":"8520",
    "sg:province":"West-Vlaanderen",
    "sg:tags":[
        "textile",
        "clothing"
    ],
    "wof:name":"Distrilin Nv",
    "wof:placetype":"venue"
},
  "geometry": {"coordinates":[3.2594399452,50.8567810059],"type":"Point"}
}