{
  "type": "Feature",
  "properties": {
    "iso:country":"BE",
    "sg:address":"28",
    "sg:city":"Rue Voot 1200 Woluwe St Lambert",
    "sg:classifiers":[
        {
            "category":"Travel",
            "subcategory":"Hotels & Motels",
            "type":"Entertainment"
        }
    ],
    "sg:phone":"+32 2 770 24 40",
    "sg:postcode":"28",
    "sg:tags":[
        "hotels",
        "business",
        "restaurant"
    ],
    "wof:name":"Alliance Cafe",
    "wof:placetype":"venue"
},
  "geometry": {"coordinates":[4.4330558777,50.8416252136],"type":"Point"}
}