{
  "type": "Feature",
  "properties": {
    "addr:full":"Hekslaan 1 Heers Limburg 3870",
    "addr:housenumber":"1",
    "addr:postcode":"3870",
    "addr:street":"Hekslaan",
    "iso:country":"BE",
    "sg:address":"Hekslaan 1",
    "sg:city":"Heers",
    "sg:orig_category":"Eleveurs and marchands de porcs",
    "sg:phone":"+32 12 74 13 13",
    "sg:postcode":"3870",
    "sg:province":"Limburg",
    "wof:name":"Guido Daenen",
    "wof:placetype":"venue"
},
  "geometry": {"coordinates":[5.3732500076,50.7634010315],"type":"Point"}
}