{
  "type": "Feature",
  "properties": {
    "iso:country":"BE",
    "sg:address":"Sint-amandsstraat 8",
    "sg:city":"Brugge",
    "sg:classifiers":[
        {
            "category":"Restaurant",
            "type":"Food & Drink"
        }
    ],
    "sg:phone":"+32 50 33 42 02",
    "sg:postcode":"8000",
    "sg:province":"West-Vlaanderen",
    "wof:name":"Restaurant Hermes",
    "wof:placetype":"venue"
},
  "geometry": {"coordinates":[3.2233519554,51.2086486816],"type":"Point"}
}