{
  "type": "Feature",
  "properties": {
    "iso:country":"BE",
    "sg:address":"Avenue De La Marmotte 101",
    "sg:city":"Wezembeek-oppem",
    "sg:classifiers":[
        {
            "category":"Health Services",
            "subcategory":"Health Practitioner",
            "type":"Services"
        }
    ],
    "sg:phone":"+32 2 767 08 78",
    "sg:postcode":"1970",
    "sg:province":"Vlaams-Brabant",
    "sg:tags":[
        "psychologist"
    ],
    "wof:name":"Le Polain De Waroux A-ch",
    "wof:placetype":"venue"
},
  "geometry": {"coordinates":[4.4974098206,50.8359031677],"type":"Point"}
}