{
  "type": "Feature",
  "properties": {
    "iso:country":"BE",
    "sg:address":"Rue Bois De N\u00e9verl\u00e9e 2",
    "sg:city":"Namur (suarl\u00e9e)",
    "sg:classifiers":[
        {
            "category":"Building & Trades",
            "subcategory":"Landscaping Services",
            "type":"Services"
        }
    ],
    "sg:phone":"+32 81 56 06 00",
    "sg:postcode":"5020",
    "sg:province":"Namur",
    "sg:tags":[
        "forestry"
    ],
    "wof:name":"Neverlest",
    "wof:placetype":"venue"
},
  "geometry": {"coordinates":[4.8148698807,50.4895401001],"type":"Point"}
}