{
  "type": "Feature",
  "properties": {
    "iso:country":"BE",
    "sg:address":"Quai De Rome 2",
    "sg:city":"Li\u00e8ge 1",
    "sg:classifiers":[
        {
            "category":"Professional",
            "subcategory":"Lawyer & Legal Services",
            "type":"Services"
        }
    ],
    "sg:phone":"+32 4 254 11 00",
    "sg:postcode":"4000",
    "sg:province":"Li\u00e8ge",
    "wof:name":"Neuprez Vincent",
    "wof:placetype":"venue"
},
  "geometry": {"coordinates":[5.5734901428,50.6265411377],"type":"Point"}
}