{
  "type": "Feature",
  "properties": {
    "addr:full":"Frederik De Merodestraat 33 Mechelen Antwerpen 2800",
    "addr:housenumber":"33",
    "addr:postcode":"2800",
    "addr:street":"Frederik De Merodestraat",
    "iso:country":"BE",
    "sg:address":"Frederik De Merodestraat 33",
    "sg:city":"Mechelen",
    "sg:classifiers":[
        {
            "category":"Personal",
            "type":"Services"
        }
    ],
    "sg:phone":"+32 15 28 79 50",
    "sg:postcode":"2800",
    "sg:province":"Antwerpen",
    "sg:tags":[
        "party",
        "planning"
    ],
    "wof:name":"Huis Van Dijck Nv",
    "wof:placetype":"venue"
},
  "geometry": {"coordinates":[4.4808921814,51.0296134949],"type":"Point"}
}