{
  "type": "Feature",
  "properties": {
    "addr:full":"Maurits Sacr\u00c9straat 52 Merchtem Vlaams-Brabant 1785",
    "addr:housenumber":"52",
    "addr:postcode":"1785",
    "addr:street":"Sacre\u0301Straat",
    "iso:country":"BE",
    "sg:address":"Maurits Sacr\u00c9straat 52",
    "sg:city":"Merchtem",
    "sg:orig_category":"Plaatsen van vloer- and muurbekleding Schilders",
    "sg:phone":"+32 52 37 30 93",
    "sg:postcode":"1785",
    "sg:province":"Vlaams-Brabant",
    "wof:name":"C Jacquemijn En Zoon",
    "wof:placetype":"venue"
},
  "geometry": {"coordinates":[4.2354550362,50.9531021118],"type":"Point"}
}