{
  "type": "Feature",
  "properties": {
    "iso:country":"BE",
    "sg:address":"Rue De Rochefort 62",
    "sg:city":"Beauraing",
    "sg:classifiers":[
        {
            "category":"Personal",
            "subcategory":"Beauty Salon",
            "type":"Services"
        }
    ],
    "sg:phone":"+32 82 71 41 71",
    "sg:postcode":"5570",
    "sg:province":"Namur",
    "sg:tags":[
        "lady",
        "-",
        "hairdressing"
    ],
    "wof:name":"Symbiose",
    "wof:placetype":"venue"
},
  "geometry": {"coordinates":[4.9605917931,50.1102561951],"type":"Point"}
}