{
  "type": "Feature",
  "properties": {
    "addr:full":"Baron Copp\u00c9elaan 20 Maasmechelen Limburg 3630",
    "addr:housenumber":"20",
    "addr:postcode":"3630",
    "addr:street":"Baron Coppe\u0301Elaan",
    "iso:country":"BE",
    "sg:address":"Baron Copp\u00c9elaan 20",
    "sg:city":"Maasmechelen",
    "sg:orig_category":"Pain, p\u00e2tisseries and confiseries",
    "sg:phone":"+32 89 76 63 50",
    "sg:postcode":"3630",
    "sg:province":"Limburg",
    "wof:name":"Edmond Sponga",
    "wof:placetype":"venue"
},
  "geometry": {"coordinates":[5.698800087,50.9975204468],"type":"Point"}
}