{
  "type": "Feature",
  "properties": {
    "addr:full":"Verbrandhofstraat 41 Roeselare West-Vlaanderen 8800",
    "addr:housenumber":"41",
    "addr:postcode":"8800",
    "addr:street":"Verbrandhofstraat",
    "iso:country":"BE",
    "sg:address":"Verbrandhofstraat 41",
    "sg:city":"Roeselare",
    "sg:classifiers":[
        {
            "category":"Building & Trades",
            "subcategory":"Pest Control",
            "type":"Services"
        }
    ],
    "sg:phone":"+32 3 233 06 46",
    "sg:postcode":"8800",
    "sg:province":"West-Vlaanderen",
    "sg:tags":[
        "disinfectant",
        "insecticide"
    ],
    "wof:name":"Hunt",
    "wof:placetype":"venue"
},
  "geometry": {"coordinates":[3.1151330471,50.9285812378],"type":"Point"}
}