{
  "type": "Feature",
  "properties": {
    "addr:full":"Russelt 96 Wellen Limburg 3830",
    "addr:housenumber":"96",
    "addr:postcode":"3830",
    "addr:street":"Russelt",
    "iso:country":"BE",
    "sg:address":"Russelt 96",
    "sg:city":"Wellen",
    "sg:orig_category":"P\u00e9pini\u00e9ristes",
    "sg:phone":"+32 11 59 65 79",
    "sg:postcode":"3830",
    "sg:province":"Limburg",
    "wof:name":"Marc Mouha",
    "wof:placetype":"venue"
},
  "geometry": {"coordinates":[5.3141860962,50.8569984436],"type":"Point"}
}