{
  "type": "Feature",
  "properties": {
    "addr:full":"Kortewildestraat 3 Diksmuide (vladslo) West-Vlaanderen 8600",
    "addr:housenumber":"3",
    "addr:postcode":"8600",
    "addr:street":"Kortewildestraat",
    "iso:country":"BE",
    "sg:address":"Kortewildestraat 3",
    "sg:city":"Diksmuide (vladslo)",
    "sg:classifiers":[
        {
            "category":"Insurance",
            "subcategory":"Insurance Agent",
            "type":"Services"
        }
    ],
    "sg:phone":"+32 51 50 46 34",
    "sg:postcode":"8600",
    "sg:province":"West-Vlaanderen",
    "sg:tags":[
        "broker"
    ],
    "wof:name":"Decoene En Co Verzekeringsmakelaars",
    "wof:placetype":"venue"
},
  "geometry": {"coordinates":[2.9230940342,51.0461616516],"type":"Point"}
}