{
  "type": "Feature",
  "properties": {
    "addr:full":"Vaartstraat 10ba Laarne Oost-Vlaanderen 9270",
    "addr:housenumber":"10ba",
    "addr:postcode":"9270",
    "addr:street":"Vaartstraat",
    "iso:country":"BE",
    "sg:address":"Vaartstraat 10ba",
    "sg:city":"Laarne",
    "sg:orig_category":"Instellingen voor probleemkinderen Kindertehuizen",
    "sg:phone":"+32 9 367 06 23",
    "sg:postcode":"9270",
    "sg:province":"Oost-Vlaanderen",
    "wof:name":"Home De Steiger",
    "wof:placetype":"venue"
},
  "geometry": {"coordinates":[3.9167129993,51.0358428955],"type":"Point"}
}