{
  "type": "Feature",
  "properties": {
    "iso:country":"BE",
    "sg:address":"Rochesterlaan 12",
    "sg:city":"Gistel",
    "sg:orig_category":"Onderdelen and accessoires voor auto's",
    "sg:phone":"+32 59 27 88 94",
    "sg:postcode":"8470",
    "sg:province":"West-Vlaanderen",
    "wof:name":"V. Decramer",
    "wof:placetype":"venue"
},
  "geometry": {"coordinates":[2.9452021122,51.1487197876],"type":"Point"}
}