{
  "type": "Feature",
  "properties": {
    "addr:full":"Rue De La Croix 16 Clavier Li\u00e8ge 4560",
    "addr:housenumber":"16",
    "addr:postcode":"4560",
    "addr:street":"Rue De La Croix",
    "iso:country":"BE",
    "sg:address":"Rue De La Croix 16",
    "sg:city":"Clavier",
    "sg:orig_category":"Gespecialiseerde residenti\u00eble bouw Woningbouw",
    "sg:phone":"+32 86 34 40 12",
    "sg:postcode":"4560",
    "sg:province":"Li\u00e8ge",
    "wof:name":"Delhez Jacques",
    "wof:placetype":"venue"
},
  "geometry": {"coordinates":[5.3971891403,50.3949394226],"type":"Point"}
}