{
  "type": "Feature",
  "properties": {
    "iso:country":"BE",
    "sg:address":"Merksplassebaan 47",
    "sg:city":"Malle",
    "sg:orig_category":"Installation de menuiserie en bois and plastique",
    "sg:phone":"+32 3 312 56 66",
    "sg:postcode":"2390",
    "sg:province":"Antwerpen",
    "wof:name":"Van Os I",
    "wof:placetype":"venue"
},
  "geometry": {"coordinates":[4.7426609993,51.3072929382],"type":"Point"}
}