{
  "type": "Feature",
  "properties": {
    "addr:full":"Veldstraat 44 Houthulst West-Vlaanderen 8650",
    "addr:housenumber":"44",
    "addr:postcode":"8650",
    "addr:street":"Veldstraat",
    "iso:country":"BE",
    "sg:address":"Veldstraat 44",
    "sg:city":"Houthulst",
    "sg:orig_category":"Afval and schroot Gh",
    "sg:phone":"+32 51 70 08 43",
    "sg:postcode":"8650",
    "sg:province":"West-Vlaanderen",
    "wof:name":"Johny Noyelle",
    "wof:placetype":"venue"
},
  "geometry": {"coordinates":[2.9368619919,50.9791984558],"type":"Point"}
}