{
  "type": "Feature",
  "properties": {
    "addr:full":"Ontmijnersstraat 2 Staden (westrozebeke) West-Vlaanderen 8840",
    "addr:housenumber":"2",
    "addr:postcode":"8840",
    "addr:street":"Ontmijnersstraat",
    "iso:country":"BE",
    "sg:address":"Ontmijnersstraat 2",
    "sg:city":"Staden (westrozebeke)",
    "sg:classifiers":[
        {
            "category":"Bars & Pubs",
            "type":"Food & Drink"
        }
    ],
    "sg:phone":"+32 51 70 10 60",
    "sg:postcode":"8840",
    "sg:province":"West-Vlaanderen",
    "wof:name":"Het Keverke",
    "wof:placetype":"venue"
},
  "geometry": {"coordinates":[2.9742920399,50.9497642517],"type":"Point"}
}