{
  "type": "Feature",
  "properties": {
    "addr:full":"Cuperusstraat 37 Antwerpen Antwerpen 2018",
    "addr:housenumber":"37",
    "addr:postcode":"2018",
    "addr:street":"Cuperusstraat",
    "iso:country":"BE",
    "sg:address":"Cuperusstraat 37",
    "sg:city":"Antwerpen",
    "sg:classifiers":[
        {
            "category":"Real Estate",
            "subcategory":"Architect",
            "type":"Services"
        }
    ],
    "sg:phone":"+32 3 218 55 84",
    "sg:postcode":"2018",
    "sg:province":"Antwerpen",
    "wof:name":"Vleminckx C",
    "wof:placetype":"venue"
},
  "geometry": {"coordinates":[4.4276747704,51.2035827637],"type":"Point"}
}