{
  "type": "Feature",
  "properties": {
    "addr:full":"Koning Albertlaan 51 Box 2 Neerpelt Limburg 3910",
    "addr:housenumber":"51;2",
    "addr:postcode":"3910",
    "addr:street":"Koning Albertlaan;Box",
    "iso:country":"BE",
    "sg:address":"Koning Albertlaan 51 Box 2",
    "sg:city":"Neerpelt",
    "sg:classifiers":[
        {
            "category":"Insurance",
            "subcategory":"Insurance Agent",
            "type":"Services"
        }
    ],
    "sg:phone":"+32 11 66 38 18",
    "sg:postcode":"3910",
    "sg:province":"Limburg",
    "sg:tags":[
        "broker"
    ],
    "wof:name":"Vanvinckenroye Gie",
    "wof:placetype":"venue"
},
  "geometry": {"coordinates":[5.4304699898,51.2262115479],"type":"Point"}
}