{
  "type": "Feature",
  "properties": {
    "iso:country":"BE",
    "sg:address":"Rue D'hamptay 61",
    "sg:city":"Rochefort (han-sur-lesse)",
    "sg:classifiers":[
        {
            "category":"Travel",
            "subcategory":"Hotels & Motels",
            "type":"Entertainment"
        }
    ],
    "sg:phone":"+32 84 34 09 90",
    "sg:postcode":"5580",
    "sg:province":"Namur",
    "wof:name":"Stradella (la)",
    "wof:placetype":"venue"
},
  "geometry": {"coordinates":[5.1892228127,50.1244544983],"type":"Point"}
}