{
  "type": "Feature",
  "properties": {
    "iso:country":"BE",
    "sg:address":"Rue Ropsy Chaudron Straat 22",
    "sg:city":"Bruxelles-brussel",
    "sg:classifiers":[
        {
            "category":"Professional",
            "subcategory":"Accounting & Tax Preparation",
            "type":"Services"
        }
    ],
    "sg:phone":"+32 2 521 25 55",
    "sg:postcode":"1070",
    "sg:province":"Bruxelles-Capitale",
    "sg:tags":[
        "balance"
    ],
    "wof:name":"Albel - Giga S.a./ Nv",
    "wof:placetype":"venue"
},
  "geometry": {"coordinates":[4.3284931183,50.8433113098],"type":"Point"}
}