{
  "type": "Feature",
  "properties": {
    "addr:full":"Zagerijstraat 49 Lille Antwerpen 2275",
    "addr:housenumber":"49",
    "addr:postcode":"2275",
    "addr:street":"Zagerijstraat",
    "iso:country":"BE",
    "sg:address":"Zagerijstraat 49",
    "sg:city":"Lille",
    "sg:orig_category":"Belastingconsulenten Diverse juridische dienstverlening",
    "sg:phone":"+32 14 88 06 10",
    "sg:postcode":"2275",
    "sg:province":"Antwerpen",
    "wof:name":"Accosoft",
    "wof:placetype":"venue"
},
  "geometry": {"coordinates":[4.8176398277,51.2326927185],"type":"Point"}
}