{
  "type": "Feature",
  "properties": {
    "iso:country":"BE",
    "sg:address":"Rue Du Suffrage Universel 45",
    "sg:city":"Sprimont",
    "sg:classifiers":[
        {
            "category":"Building & Trades",
            "subcategory":"Construction",
            "type":"Services"
        }
    ],
    "sg:phone":"+32 4 382 17 78",
    "sg:postcode":"4140",
    "sg:province":"Li\u00e8ge",
    "sg:tags":[
        "roofing",
        "material",
        "-"
    ],
    "wof:name":"Sprimotoit Sc",
    "wof:placetype":"venue"
},
  "geometry": {"coordinates":[5.6552400589,50.5147705078],"type":"Point"}
}