{
  "type": "Feature",
  "properties": {
    "iso:country":"BE",
    "sg:address":"Rue Romaine 19",
    "sg:city":"Comines-warneton (comines)",
    "sg:classifiers":[
        {
            "category":"Home & Garden",
            "subcategory":"Building Materials",
            "type":"Retail Goods"
        }
    ],
    "sg:phone":"+32 56 55 54 19",
    "sg:postcode":"7780",
    "sg:province":"Hainaut",
    "sg:tags":[
        "window"
    ],
    "wof:name":"Ateliers Jean Dujardin Et Fils",
    "wof:placetype":"venue"
},
  "geometry": {"coordinates":[2.9947040081,50.7774963379],"type":"Point"}
}