{
  "type": "Feature",
  "properties": {
    "addr:full":"Visvijverstraat 110 Elsene/ixelles Bruxelles-Capitale 1050",
    "addr:housenumber":"110",
    "addr:postcode":"1050",
    "addr:street":"Visvijverstraat",
    "iso:country":"BE",
    "sg:address":"Visvijverstraat 110",
    "sg:city":"Elsene/ixelles",
    "sg:orig_category":"Fotografen and fotostudio's",
    "sg:phone":"+32 2 646 92 12",
    "sg:postcode":"1050",
    "sg:province":"Bruxelles-Capitale",
    "wof:name":"Michel Clinckemaille",
    "wof:placetype":"venue"
},
  "geometry": {"coordinates":[4.3798298836,50.8328971863],"type":"Point"}
}