{
  "type": "Feature",
  "properties": {
    "iso:country":"BE",
    "sg:address":"Gremelsloweg 6",
    "sg:city":"Maaseik",
    "sg:classifiers":[
        {
            "category":"Building & Trades",
            "subcategory":"Construction",
            "type":"Services"
        }
    ],
    "sg:phone":"+32 89 56 64 01",
    "sg:postcode":"3680",
    "sg:province":"Limburg",
    "sg:tags":[
        "asphalt",
        "contractor"
    ],
    "wof:name":"Peters Leon Dakwerken",
    "wof:placetype":"venue"
},
  "geometry": {"coordinates":[5.7554979324,51.1067008972],"type":"Point"}
}