{
  "type": "Feature",
  "properties": {
    "addr:full":"Sur Les Marli\u00c8res 6 Clavier Li\u00e8ge 4560",
    "addr:housenumber":"6",
    "addr:postcode":"4560",
    "addr:street":"Sur Les Marlie\u0300Res",
    "iso:country":"BE",
    "sg:address":"Sur Les Marli\u00c8res 6",
    "sg:city":"Clavier",
    "sg:orig_category":"Toeristische diensten",
    "sg:phone":"+32 86 34 48 61",
    "sg:postcode":"4560",
    "sg:province":"Li\u00e8ge",
    "wof:name":"Syndicat D'initiative",
    "wof:placetype":"venue"
},
  "geometry": {"coordinates":[5.3975839615,50.3959274292],"type":"Point"}
}