{
  "type": "Feature",
  "properties": {
    "addr:full":"Rue De Rodange 56 Aubange (athus) Luxembourg 6791",
    "addr:housenumber":"56",
    "addr:postcode":"6791",
    "addr:street":"Rue De Rodange",
    "iso:country":"BE",
    "sg:address":"Rue De Rodange 56",
    "sg:city":"Aubange (athus)",
    "sg:classifiers":[
        {
            "category":"Shopping",
            "subcategory":"Florist",
            "type":"Retail Goods"
        }
    ],
    "sg:phone":"+32 63 38 82 00",
    "sg:postcode":"6791",
    "sg:province":"Luxembourg",
    "wof:name":"Bouquet Fleuri (au)",
    "wof:placetype":"venue"
},
  "geometry": {"coordinates":[5.8368301392,49.5627288818],"type":"Point"}
}