{
  "type": "Feature",
  "properties": {
    "addr:full":"Les Arsilli\u00c8res 37 Momignies Hainaut 6590",
    "addr:housenumber":"37",
    "addr:postcode":"6590",
    "addr:street":"Hainaut",
    "iso:country":"BE",
    "sg:address":"Les Arsilli\u00c8res 37",
    "sg:city":"Momignies",
    "sg:orig_category":"M\u00e9decins and sp\u00e9cialistes",
    "sg:phone":"+32 60 51 15 16",
    "sg:postcode":"6590",
    "sg:province":"Hainaut",
    "wof:name":"D. Schoels",
    "wof:placetype":"venue"
},
  "geometry": {"coordinates":[4.1700110435,50.0270500183],"type":"Point"}
}