{
  "type": "Feature",
  "properties": {
    "addr:full":"Schoonzichtstraat 7 Gent Oost-Vlaanderen 9051",
    "addr:housenumber":"7",
    "addr:postcode":"9051",
    "addr:street":"Schoonzichtstraat;Oost-Vlaanderen",
    "iso:country":"BE",
    "sg:address":"Schoonzichtstraat 7",
    "sg:city":"Gent",
    "sg:classifiers":[
        {
            "category":"Fast Food",
            "type":"Food & Drink"
        }
    ],
    "sg:phone":"+32 9 220 46 40",
    "sg:postcode":"9051",
    "sg:province":"Oost-Vlaanderen",
    "sg:tags":[
        "\u00c0",
        "emporter",
        "restaurants"
    ],
    "wof:name":"Pizza Il Paradiso",
    "wof:placetype":"venue"
},
  "geometry": {"coordinates":[3.6712639332,51.0177345276],"type":"Point"}
}