{
  "type": "Feature",
  "properties": {
    "addr:full":"Stationsstraat 35 Lennik Vlaams-Brabant 1750",
    "addr:housenumber":"35;1750",
    "addr:street":"Stationsstraat;Vlaams-Brabant",
    "iso:country":"BE",
    "sg:address":"Stationsstraat 35",
    "sg:city":"Lennik",
    "sg:orig_category":"Maisons de repos and r\u00e9sidences",
    "sg:phone":"+32 2 532 41 45",
    "sg:postcode":"1750",
    "sg:province":"Vlaams-Brabant",
    "wof:name":"Rusthuis Den Bleek",
    "wof:placetype":"venue"
},
  "geometry": {"coordinates":[4.1570591927,50.8096504211],"type":"Point"}
}