{
  "type": "Feature",
  "properties": {
    "iso:country":"BE",
    "sg:address":"Rue De La Libert\u00e9 34",
    "sg:city":"Saint-nicolas",
    "sg:classifiers":[
        {
            "category":"Building & Trades",
            "subcategory":"Construction",
            "type":"Services"
        }
    ],
    "sg:phone":"+32 4 252 63 35",
    "sg:postcode":"4420",
    "sg:province":"Li\u00e8ge",
    "sg:tags":[
        "stucco",
        "contractor"
    ],
    "wof:name":"Riggi Gino Sprl",
    "wof:placetype":"venue"
},
  "geometry": {"coordinates":[5.5402917862,50.6257362366],"type":"Point"}
}