{
  "type": "Feature",
  "properties": {
    "addr:full":"Priester Daensplein 8 Aalst Oost-Vlaanderen 9300",
    "addr:housenumber":"8",
    "addr:postcode":"9300",
    "addr:street":"Priester Daensplein",
    "iso:country":"BE",
    "sg:address":"Priester Daensplein 8",
    "sg:city":"Aalst",
    "sg:orig_category":"Dameskledingzaken",
    "sg:phone":"+32 53 21 10 42",
    "sg:postcode":"9300",
    "sg:province":"Oost-Vlaanderen",
    "wof:name":"Huis Marty",
    "wof:placetype":"venue"
},
  "geometry": {"coordinates":[4.0409421921,50.9373664856],"type":"Point"}
}