{
  "type": "Feature",
  "properties": {
    "addr:full":"Rue De L'aunaie 25 Li\u00c8ge Li\u00e8ge 4031",
    "addr:housenumber":"25",
    "addr:postcode":"4031",
    "addr:street":"Rue De L'Aunaie",
    "iso:country":"BE",
    "sg:address":"Rue De L'aunaie 25",
    "sg:city":"Li\u00c8ge",
    "sg:orig_category":"Assurances. Bureaux de poste",
    "sg:phone":"+32 4 365 86 13",
    "sg:postcode":"4031",
    "sg:province":"Li\u00e8ge",
    "wof:name":"La Poste",
    "wof:placetype":"venue"
},
  "geometry": {"coordinates":[5.5706400871,50.5872116089],"type":"Point"}
}