{
  "type": "Feature",
  "properties": {
    "addr:full":"Nati\u00ebnlaan 43 Knokke West-Vlaanderen 8300",
    "addr:housenumber":"43",
    "addr:postcode":"8300",
    "addr:street":"Natie\u0308Nlaan",
    "iso:country":"BE",
    "sg:address":"Nati\u00ebnlaan 43",
    "sg:city":"Knokke",
    "sg:classifiers":[
        {
            "category":"Food Court",
            "type":"Food & Drink"
        }
    ],
    "sg:phone":"+32 50 60 13 63",
    "sg:postcode":"8300",
    "sg:province":"West-Vlaanderen",
    "sg:tags":[
        "product",
        "related"
    ],
    "wof:name":"Pauwaert Hip Nv",
    "wof:placetype":"venue"
},
  "geometry": {"coordinates":[3.2869091034,51.3386878967],"type":"Point"}
}