{
  "type": "Feature",
  "properties": {
    "iso:country":"BE",
    "sg:address":"Rue J.b. Brabant 30",
    "sg:city":"Namur",
    "sg:orig_category":"Medische apparatuur, orthopedische artikelen and prothesen Fab",
    "sg:phone":"+32 81 22 37 66",
    "sg:postcode":"5000",
    "sg:province":"Namur",
    "wof:name":"J. Thomas",
    "wof:placetype":"venue"
},
  "geometry": {"coordinates":[4.872218132,50.465171814],"type":"Point"}
}