{
  "type": "Feature",
  "properties": {
    "addr:full":"De Keyserlei 58-60 B61 Antwerpen Antwerpen 2018",
    "addr:housenumber":"58-60 b61",
    "addr:postcode":"2018",
    "addr:street":"De Keyserlei",
    "iso:country":"BE",
    "sg:address":"De Keyserlei 58-60 B61",
    "sg:city":"Antwerpen",
    "sg:classifiers":[
        {
            "category":"Marine",
            "type":"Transportation"
        }
    ],
    "sg:phone":"+32 3 203 69 00",
    "sg:postcode":"2018",
    "sg:province":"Antwerpen",
    "sg:tags":[
        "agency",
        "sea",
        "shipping"
    ],
    "wof:name":"Evergreen Belgium Shipping Agency",
    "wof:placetype":"venue"
},
  "geometry": {"coordinates":[4.4141998291,51.2049598694],"type":"Point"}
}