{
  "type": "Feature",
  "properties": {
    "iso:country":"BE",
    "sg:address":"Rue Ruisseau Des Forges 7",
    "sg:city":"Florennes",
    "sg:classifiers":[
        {
            "category":"Professional",
            "subcategory":"Lawyer & Legal Services",
            "type":"Services"
        }
    ],
    "sg:phone":"+32 71 68 93 52",
    "sg:postcode":"5620",
    "sg:province":"Namur",
    "wof:name":"Meunier J Sprl",
    "wof:placetype":"venue"
},
  "geometry": {"coordinates":[4.6009159088,50.2519111633],"type":"Point"}
}