{
  "type": "Feature",
  "properties": {
    "addr:full":"Rue De Ghislenghien 9 Ath Hainaut 7822",
    "addr:housenumber":"9",
    "addr:postcode":"7822",
    "addr:street":"Rue De Ghislenghien",
    "iso:country":"BE",
    "sg:address":"Rue De Ghislenghien 9",
    "sg:city":"Ath",
    "sg:orig_category":"Banken and kredietinstellingen",
    "sg:phone":"+32 68 57 00 30",
    "sg:postcode":"7822",
    "sg:province":"Hainaut",
    "wof:name":"Axa",
    "wof:placetype":"venue"
},
  "geometry": {"coordinates":[3.8736848831,50.6571159363],"type":"Point"}
}