{
  "type": "Feature",
  "properties": {
    "addr:full":"Hertsdeinstraat 4b Antwerpen Antwerpen 2018",
    "addr:housenumber":"4b",
    "addr:postcode":"2018",
    "addr:street":"Hertsdeinstraat",
    "iso:country":"BE",
    "sg:address":"Hertsdeinstraat 4b",
    "sg:city":"Antwerpen",
    "sg:classifiers":[
        {
            "category":"Manufacturing",
            "subcategory":"Metals",
            "type":"Manufacturing & Wholesale Goods"
        }
    ],
    "sg:phone":"+32 486 23 01 30",
    "sg:postcode":"2018",
    "sg:province":"Antwerpen",
    "sg:tags":[
        "ironwork"
    ],
    "wof:name":"Arcana Bvba",
    "wof:placetype":"venue"
},
  "geometry": {"coordinates":[4.3981719017,51.2035446167],"type":"Point"}
}