{
  "type": "Feature",
  "properties": {
    "addr:full":"Rue Du Broux 48 Beauvechain Brabant Wallon 1320",
    "addr:housenumber":"48",
    "addr:postcode":"1320",
    "addr:street":"Rue Du Broux",
    "iso:country":"BE",
    "sg:address":"Rue Du Broux 48",
    "sg:city":"Beauvechain",
    "sg:orig_category":"Rundveehouders",
    "sg:phone":"+32 10 86 68 74",
    "sg:postcode":"1320",
    "sg:province":"Brabant Wallon",
    "wof:name":"Marcel Rowart Dewaersegger",
    "wof:placetype":"venue"
},
  "geometry": {"coordinates":[4.7905731201,50.7810020447],"type":"Point"}
}