{
  "type": "Feature",
  "properties": {
    "addr:full":"Rue Des Forri\u00c8res 11 Gembloux Namur 5032",
    "addr:housenumber":"11",
    "addr:postcode":"5032",
    "addr:street":"Rue Des Forrie\u0300Res;Namur",
    "iso:country":"BE",
    "sg:address":"Rue Des Forri\u00c8res 11",
    "sg:city":"Gembloux",
    "sg:orig_category":"Enseignement maternel and primaire",
    "sg:phone":"+32 81 63 39 47",
    "sg:postcode":"5032",
    "sg:province":"Namur",
    "wof:name":"Ecole Matern. Communale",
    "wof:placetype":"venue"
},
  "geometry": {"coordinates":[4.6956400871,50.5173988342],"type":"Point"}
}