{
  "type": "Feature",
  "properties": {
    "addr:full":"Rue De La Campagne 42 Huy Li\u00e8ge 4500",
    "addr:housenumber":"42",
    "addr:postcode":"4500",
    "addr:street":"Rue De La",
    "iso:country":"BE",
    "sg:address":"Rue De La Campagne 42",
    "sg:city":"Huy",
    "sg:orig_category":"Voedingsspeciaalzaken",
    "sg:phone":"+32 475 55 84 40",
    "sg:postcode":"4500",
    "sg:province":"Li\u00e8ge",
    "wof:name":"Michel Marchand",
    "wof:placetype":"venue"
},
  "geometry": {"coordinates":[5.2557559013,50.5310173035],"type":"Point"}
}