{
  "type": "Feature",
  "properties": {
    "addr:full":"Rue Des Hirondelles 11 Oupeye Li\u00e8ge 4680",
    "addr:housenumber":"11",
    "addr:postcode":"4680",
    "addr:street":"Rue Des Hirondelles",
    "iso:country":"BE",
    "sg:address":"Rue Des Hirondelles 11",
    "sg:city":"Oupeye",
    "sg:classifiers":[
        {
            "category":"Arena",
            "subcategory":"Sports Club",
            "type":"Entertainment"
        }
    ],
    "sg:phone":"+32 4 278 69 16",
    "sg:postcode":"4680",
    "sg:province":"Li\u00e8ge",
    "wof:name":"Tritons (les)",
    "wof:placetype":"venue"
},
  "geometry": {"coordinates":[5.6350288391,50.7111473083],"type":"Point"}
}