{
  "type": "Feature",
  "properties": {
    "iso:country":"BE",
    "sg:address":"Prinsenkouter 17",
    "sg:city":"Destelbergen",
    "sg:orig_category":"Binnenhuisarchitecten",
    "sg:phone":"+32 9 230 55 03",
    "sg:postcode":"9070",
    "sg:province":"Oost-Vlaanderen",
    "wof:name":"Brigitte Demerre",
    "wof:placetype":"venue"
},
  "geometry": {"coordinates":[3.8141028881,51.0402755737],"type":"Point"}
}