{
  "type": "Feature",
  "properties": {
    "iso:country":"BE",
    "sg:address":"Rue Andr\u00c9 Renard 84",
    "sg:city":"Ans",
    "sg:orig_category":"Architecten",
    "sg:phone":"+32 4 263 36 14",
    "sg:postcode":"4430",
    "sg:province":"Li\u00e8ge",
    "wof:name":"Jean-fran\u00c7ois Deblinde",
    "wof:placetype":"venue"
},
  "geometry": {"coordinates":[5.5240211487,50.6615028381],"type":"Point"}
}