{
  "type": "Feature",
  "properties": {
    "iso:country":"BE",
    "sg:address":"Beeklaan 40",
    "sg:city":"Kortrijk",
    "sg:orig_category":"Banques and organismes de cr\u00e9dit",
    "sg:phone":"+32 56 20 17 05",
    "sg:postcode":"8500",
    "sg:province":"West-Vlaanderen",
    "wof:name":"Bacob",
    "wof:placetype":"venue"
},
  "geometry": {"coordinates":[3.2959339619,50.813621521],"type":"Point"}
}