{
  "type": "Feature",
  "properties": {
    "addr:full":"Rue De Li\u00e8ge 100 Durbuy (bomal-sur-ourthe) Luxembourg 6941",
    "addr:housenumber":"100",
    "addr:postcode":"6941",
    "addr:street":"Rue De Lie\u0300Ge",
    "iso:country":"BE",
    "sg:address":"Rue De Li\u00e8ge 100",
    "sg:city":"Durbuy (bomal-sur-ourthe)",
    "sg:classifiers":[
        {
            "category":"Manufacturing",
            "subcategory":"Lumber",
            "type":"Manufacturing & Wholesale Goods"
        }
    ],
    "sg:phone":"+32 86 21 19 19",
    "sg:postcode":"6941",
    "sg:province":"Luxembourg",
    "sg:tags":[
        "timber"
    ],
    "wof:name":"Detrooz Ets",
    "wof:placetype":"venue"
},
  "geometry": {"coordinates":[5.524184227,50.3770332336],"type":"Point"}
}