{
  "type": "Feature",
  "properties": {
    "addr:full":"Chauss\u00e9e De Charleroi 669 Fleurus Hainaut 6220",
    "addr:housenumber":"669",
    "addr:postcode":"6220",
    "addr:street":"Chausse\u0301E De Charleroi",
    "iso:country":"BE",
    "sg:address":"Chauss\u00e9e De Charleroi 669",
    "sg:city":"Fleurus",
    "sg:classifiers":[
        {
            "category":"Home & Garden",
            "subcategory":"Household Appliances",
            "type":"Retail Goods"
        }
    ],
    "sg:phone":"+32 71 85 09 51",
    "sg:postcode":"6220",
    "sg:province":"Hainaut",
    "sg:tags":[
        "repair",
        "mainten",
        "-",
        "electric"
    ],
    "wof:name":"Electro-d\u00e9p\u00f4t",
    "wof:placetype":"venue"
},
  "geometry": {"coordinates":[4.5383300781,50.4679107666],"type":"Point"}
}