{
  "type": "Feature",
  "properties": {
    "addr:full":"Kattebroekstraat 3 Bilzen Limburg 3740",
    "addr:housenumber":"3",
    "addr:postcode":"3740",
    "addr:street":"Kattebroekstraat",
    "iso:country":"BE",
    "sg:address":"Kattebroekstraat 3",
    "sg:city":"Bilzen",
    "sg:classifiers":[
        {
            "category":"Insurance",
            "subcategory":"Insurance Agent",
            "type":"Services"
        }
    ],
    "sg:phone":"+32 89 51 09 70",
    "sg:postcode":"3740",
    "sg:province":"Limburg",
    "sg:tags":[
        "broker"
    ],
    "wof:name":"Vandersanden Alex Zakenkantoor Bvba",
    "wof:placetype":"venue"
},
  "geometry": {"coordinates":[5.5190649033,50.8666877747],"type":"Point"}
}