{
  "type": "Feature",
  "properties": {
    "addr:full":"Schipstraat 33 Nieuwpoort West-Vlaanderen 8620",
    "addr:housenumber":"33",
    "addr:postcode":"8620",
    "addr:street":"Schipstraat",
    "iso:country":"BE",
    "sg:address":"Schipstraat 33",
    "sg:city":"Nieuwpoort",
    "sg:orig_category":"Installation de menuiserie en bois and plastique. Charpentes and couvertures",
    "sg:phone":"+32 58 23 71 93",
    "sg:postcode":"8620",
    "sg:province":"West-Vlaanderen",
    "wof:name":"De Craemer Gebrs",
    "wof:placetype":"venue"
},
  "geometry": {"coordinates":[2.7530219555,51.1310691833],"type":"Point"}
}