{
  "type": "Feature",
  "properties": {
    "iso:country":"BE",
    "sg:address":"Avenue De La Chasse 44",
    "sg:city":"Etterbeek",
    "sg:orig_category":"Epiceries",
    "sg:phone":"+32 2 734 48 56",
    "sg:postcode":"1040",
    "sg:province":"Bruxelles-Capitale",
    "wof:name":"Harun Brothers",
    "wof:placetype":"venue"
},
  "geometry": {"coordinates":[4.3910079002,50.8318901062],"type":"Point"}
}