{
  "type": "Feature",
  "properties": {
    "addr:full":"Place Du Chef-lieu 0 Charleroi Hainaut 6040",
    "addr:housenumber":"0",
    "addr:postcode":"6040",
    "addr:street":"Place Du Chef-Lieu;Hainaut",
    "iso:country":"BE",
    "sg:address":"Place Du Chef-lieu 0",
    "sg:city":"Charleroi",
    "sg:orig_category":"Openbare veiligheid",
    "sg:phone":"+32 71 86 17 06",
    "sg:postcode":"6040",
    "sg:province":"Hainaut",
    "wof:name":"Police F\u00c9d\u00c9rale/federale Politie",
    "wof:placetype":"venue"
},
  "geometry": {"coordinates":[4.4254817963,50.4513206482],"type":"Point"}
}