{
  "type": "Feature",
  "properties": {
    "iso:country":"BE",
    "sg:address":"Magdalenastraat 11",
    "sg:city":"Wervik",
    "sg:orig_category":"Notaires",
    "sg:phone":"+32 56 31 11 49",
    "sg:postcode":"8940",
    "sg:province":"West-Vlaanderen",
    "wof:name":"Th. Devos",
    "wof:placetype":"venue"
},
  "geometry": {"coordinates":[3.0399549007,50.7777519226],"type":"Point"}
}