{
  "type": "Feature",
  "properties": {
    "iso:country":"BE",
    "sg:address":"Rue De Trazegnies 16",
    "sg:city":"Chapelle-lez-herlaimont",
    "sg:orig_category":"Kapsalons",
    "sg:phone":"+32 64 45 17 58",
    "sg:postcode":"7160",
    "sg:province":"Hainaut",
    "wof:name":"Coiffure Gina",
    "wof:placetype":"venue"
},
  "geometry": {"coordinates":[4.2857499123,50.4670639038],"type":"Point"}
}