{
  "type": "Feature",
  "properties": {
    "addr:full":"Tongersesteenweg 137 Riemst Limburg 3770",
    "addr:housenumber":"137",
    "addr:postcode":"3770",
    "addr:street":"Tongersesteenweg",
    "iso:country":"BE",
    "sg:address":"Tongersesteenweg 137",
    "sg:city":"Riemst",
    "sg:orig_category":"Epiceries. Meubles D\u00e9taillants, Am\u00e9nagement de B\u00e2timents et de Cuisines",
    "sg:phone":"+32 12 44 01 00",
    "sg:postcode":"3770",
    "sg:province":"Limburg",
    "wof:name":"Meubelen Eycken",
    "wof:placetype":"venue"
},
  "geometry": {"coordinates":[5.5895900726,50.8097305298],"type":"Point"}
}