{
  "type": "Feature",
  "properties": {
    "iso:country":"BE",
    "sg:address":"Rue Riverre 3",
    "sg:city":"Floreffe",
    "sg:orig_category":"Schoonmaakbedrijven and ongediertebestrijding",
    "sg:phone":"+32 81 44 60 70",
    "sg:postcode":"5150",
    "sg:province":"Namur",
    "wof:name":"Cemstobel",
    "wof:placetype":"venue"
},
  "geometry": {"coordinates":[4.7699871063,50.4444465637],"type":"Point"}
}