{
  "type": "Feature",
  "properties": {
    "addr:full":"Sint-jorisgilde 1 Dendermonde Oost-Vlaanderen 9200",
    "addr:housenumber":"1",
    "addr:postcode":"9200",
    "addr:street":"Sint-Jorisgilde;Oost-Vlaanderen",
    "iso:country":"BE",
    "sg:address":"Sint-jorisgilde 1",
    "sg:city":"Dendermonde",
    "sg:orig_category":"Rev\u00eatements de sols and murs. Textiles",
    "sg:phone":"+32 52 21 15 92",
    "sg:postcode":"9200",
    "sg:province":"Oost-Vlaanderen",
    "wof:name":"Huis Baetens",
    "wof:placetype":"venue"
},
  "geometry": {"coordinates":[4.0986700058,51.028968811],"type":"Point"}
}