{
  "type": "Feature",
  "properties": {
    "addr:full":"Rue Paradis 61a Li\u00e8ge 1 Li\u00e8ge 4000",
    "addr:housenumber":"61a;1",
    "addr:postcode":"4000",
    "addr:street":"Rue Paradis",
    "iso:country":"BE",
    "sg:address":"Rue Paradis 61a",
    "sg:city":"Li\u00e8ge 1",
    "sg:orig_category":"Non-Classified Establishments",
    "sg:phone":"+32 4 253 19 81",
    "sg:postcode":"4000",
    "sg:province":"Li\u00e8ge",
    "wof:name":"Eurafimex Sprl",
    "wof:placetype":"venue"
},
  "geometry": {"coordinates":[5.5691652298,50.6257247925],"type":"Point"}
}