{
  "type": "Feature",
  "properties": {
    "iso:country":"BE",
    "sg:address":"Zultseweg 123",
    "sg:city":"Waregem",
    "sg:classifiers":[
        {
            "category":"Shopping",
            "subcategory":"Bicycles & Sporting Goods",
            "type":"Retail Goods"
        }
    ],
    "sg:phone":"+32 56 61 28 62",
    "sg:postcode":"8790",
    "sg:province":"West-Vlaanderen",
    "sg:tags":[
        "-"
    ],
    "wof:name":"Vancompernolle D",
    "wof:placetype":"venue"
},
  "geometry": {"coordinates":[3.4414570332,50.8976097107],"type":"Point"}
}