{
  "type": "Feature",
  "properties": {
    "addr:full":"Stoofstraat 112a Merchtem Vlaams-Brabant 1785",
    "addr:housenumber":"112a",
    "addr:postcode":"1785",
    "addr:street":"Stoofstraat",
    "iso:country":"BE",
    "sg:address":"Stoofstraat 112a",
    "sg:city":"Merchtem",
    "sg:classifiers":[
        {
            "category":"Exhibition Hall",
            "type":"Public Place"
        }
    ],
    "sg:phone":"+32 52 37 33 75",
    "sg:postcode":"1785",
    "sg:province":"Vlaams-Brabant",
    "sg:tags":[
        "stand"
    ],
    "wof:name":"Stakka Concepts",
    "wof:placetype":"venue"
},
  "geometry": {"coordinates":[4.2359700203,50.9561386108],"type":"Point"}
}