{
  "type": "Feature",
  "properties": {
    "addr:full":"Dorp 90 Wachtebeke Oost-Vlaanderen 9185",
    "addr:housenumber":"90",
    "addr:postcode":"9185",
    "addr:street":"Dorp",
    "iso:country":"BE",
    "sg:address":"Dorp 90",
    "sg:city":"Wachtebeke",
    "sg:orig_category":"Fleurs and plantes",
    "sg:phone":"+32 9 345 95 12",
    "sg:postcode":"9185",
    "sg:province":"Oost-Vlaanderen",
    "wof:name":"Amaryllis",
    "wof:placetype":"venue"
},
  "geometry": {"coordinates":[3.8534700871,51.1651191711],"type":"Point"}
}