{
  "type": "Feature",
  "properties": {
    "addr:full":"Waverse Steenweg 1620 Oudergem/auderghem Bruxelles-Capitale 1160",
    "addr:housenumber":"1620",
    "addr:postcode":"1160",
    "addr:street":"Waverse Steenweg;/",
    "iso:country":"BE",
    "sg:address":"Waverse Steenweg 1620",
    "sg:city":"Oudergem/auderghem",
    "sg:orig_category":"Baby- and kinderkleding Dameskledingzaken Herenkledingzaken Textiel",
    "sg:phone":"+32 2 662 14 48",
    "sg:postcode":"1160",
    "sg:province":"Bruxelles-Capitale",
    "wof:name":"Zeeman",
    "wof:placetype":"venue"
},
  "geometry": {"coordinates":[4.4252028465,50.8168716431],"type":"Point"}
}