{
  "type": "Feature",
  "properties": {
    "iso:country":"BE",
    "sg:address":"Rue De La Procession 64",
    "sg:city":"Silly",
    "sg:orig_category":"Boucheries",
    "sg:phone":"+32 68 55 31 03",
    "sg:postcode":"7830",
    "sg:province":"Hainaut",
    "wof:name":"R. De Deyn",
    "wof:placetype":"venue"
},
  "geometry": {"coordinates":[3.9472620487,50.6727523804],"type":"Point"}
}