{
  "type": "Feature",
  "properties": {
    "addr:full":"Torhoutsesteenweg 222e Zedelgem West-Vlaanderen 8210",
    "addr:housenumber":"222e",
    "addr:postcode":"8210",
    "addr:street":"Torhoutsesteenweg",
    "iso:country":"BE",
    "sg:address":"Torhoutsesteenweg 222e",
    "sg:city":"Zedelgem",
    "sg:orig_category":"V\u00eatements",
    "sg:phone":"+32 50 20 90 89",
    "sg:postcode":"8210",
    "sg:province":"West-Vlaanderen",
    "wof:name":"Modecentrum",
    "wof:placetype":"venue"
},
  "geometry": {"coordinates":[3.1576468945,51.1365127563],"type":"Point"}
}