{
  "type": "Feature",
  "properties": {
    "iso:country":"BE",
    "sg:address":"Rue Peltzer De Clermont 36",
    "sg:city":"Verviers",
    "sg:classifiers":[
        {
            "category":"Social Services",
            "type":"Services"
        }
    ],
    "sg:phone":"+32 87 33 61 75",
    "sg:postcode":"4800",
    "sg:province":"Li\u00e8ge",
    "wof:name":"Esope Asbl Asbl",
    "wof:placetype":"venue"
},
  "geometry": {"coordinates":[5.8532328606,50.59167099],"type":"Point"}
}