{
  "type": "Feature",
  "properties": {
    "addr:full":"Steenstraat 1 Koekelare West-Vlaanderen 8680",
    "addr:housenumber":"1",
    "addr:postcode":"8680",
    "addr:street":"Steenstraat",
    "iso:country":"BE",
    "sg:address":"Steenstraat 1",
    "sg:city":"Koekelare",
    "sg:orig_category":"Gespecialiseerde niet-residenti\u00eble bouw Varkenskwekers",
    "sg:phone":"+32 51 58 14 81",
    "sg:postcode":"8680",
    "sg:province":"West-Vlaanderen",
    "wof:name":"Francky Dehaudt",
    "wof:placetype":"venue"
},
  "geometry": {"coordinates":[3.0125389099,51.0689048767],"type":"Point"}
}