{
  "type": "Feature",
  "properties": {
    "addr:full":"Koning Albertstraat 109 Diest Vlaams-Brabant 3290",
    "addr:housenumber":"109",
    "addr:postcode":"3290",
    "addr:street":"Koning Albertstraat",
    "iso:country":"BE",
    "sg:address":"Koning Albertstraat 109",
    "sg:city":"Diest",
    "sg:orig_category":"Slagers",
    "sg:phone":"+32 13 32 33 30",
    "sg:postcode":"3290",
    "sg:province":"Vlaams-Brabant",
    "wof:name":"Kippenboutikske",
    "wof:placetype":"venue"
},
  "geometry": {"coordinates":[5.0561900139,50.9875221252],"type":"Point"}
}