{
  "type": "Feature",
  "properties": {
    "addr:full":"Avenue Victor Olivier 21 Bruxelles (anderlecht) Bruxelles-Capitale 1070",
    "addr:housenumber":"21",
    "addr:postcode":"1070",
    "addr:street":"Avenue Victor Olivier",
    "iso:country":"BE",
    "sg:address":"Avenue Victor Olivier 21",
    "sg:city":"Bruxelles (anderlecht)",
    "sg:orig_category":"Non-Classified Establishments",
    "sg:phone":"+32 2 520 50 25",
    "sg:postcode":"1070",
    "sg:province":"Bruxelles-Capitale",
    "wof:name":"Vescom Belgium Nv",
    "wof:placetype":"venue"
},
  "geometry": {"coordinates":[4.310008049,50.8298072815],"type":"Point"}
}