{
  "type": "Feature",
  "properties": {
    "addr:full":"Haachtsesteenweg 17 Steenokkerzeel Vlaams-Brabant 1820",
    "addr:housenumber":"17",
    "addr:postcode":"1820",
    "addr:street":"Haachtsesteenweg",
    "iso:country":"BE",
    "sg:address":"Haachtsesteenweg 17",
    "sg:city":"Steenokkerzeel",
    "sg:classifiers":[
        {
            "category":"Building & Trades",
            "subcategory":"Plumbing",
            "type":"Services"
        }
    ],
    "sg:phone":"+32 16 65 66 68",
    "sg:postcode":"1820",
    "sg:province":"Vlaams-Brabant",
    "sg:tags":[
        "repair",
        "mainten",
        "-",
        "central",
        "heating"
    ],
    "wof:name":"Croes",
    "wof:placetype":"venue"
},
  "geometry": {"coordinates":[4.5155768394,50.9242134094],"type":"Point"}
}