{
  "type": "Feature",
  "properties": {
    "addr:full":"Diestseweg 155 Geel Antwerpen 2440",
    "addr:housenumber":"155",
    "addr:postcode":"2440",
    "addr:street":"Diestseweg",
    "iso:country":"BE",
    "sg:address":"Diestseweg 155",
    "sg:city":"Geel",
    "sg:classifiers":[
        {
            "category":"Professional",
            "subcategory":"Lawyer & Legal Services",
            "type":"Services"
        }
    ],
    "sg:phone":"+32 14 58 55 18",
    "sg:postcode":"2440",
    "sg:province":"Antwerpen",
    "wof:name":"Naulaerts Geert",
    "wof:placetype":"venue"
},
  "geometry": {"coordinates":[4.9935560226,51.1529808044],"type":"Point"}
}