{
  "type": "Feature",
  "properties": {
    "addr:full":"Acaciastraat 5 Gent Oost-Vlaanderen 9000",
    "addr:housenumber":"5",
    "addr:postcode":"9000",
    "addr:street":"Acaciastraat;Oost-Vlaanderen",
    "iso:country":"BE",
    "sg:address":"Acaciastraat 5",
    "sg:city":"Gent",
    "sg:classifiers":[
        {
            "category":"Personal",
            "subcategory":"Beauty Salon",
            "type":"Services"
        }
    ],
    "sg:phone":"+32 9 226 67 31",
    "sg:postcode":"9000",
    "sg:province":"Oost-Vlaanderen",
    "sg:tags":[
        "lady",
        "-",
        "hairdressing"
    ],
    "wof:name":"Jiani",
    "wof:placetype":"venue"
},
  "geometry": {"coordinates":[3.7002871037,51.0609016418],"type":"Point"}
}