{
  "type": "Feature",
  "properties": {
    "iso:country":"BE",
    "sg:address":"Rue Du Wayaux 23",
    "sg:city":"Ramillies",
    "sg:orig_category":"Eleveurs and marchands de porcs",
    "sg:phone":"+32 81 87 74 48",
    "sg:postcode":"1367",
    "sg:province":"Brabant Wallon",
    "wof:name":"Jadoul-willem",
    "wof:placetype":"venue"
},
  "geometry": {"coordinates":[4.9335780144,50.64503479],"type":"Point"}
}