{
  "type": "Feature",
  "properties": {
    "iso:country":"BE",
    "sg:address":"Komenseweg 180",
    "sg:city":"Ieper",
    "sg:orig_category":"Slagers",
    "sg:phone":"+32 57 20 30 34",
    "sg:postcode":"8902",
    "sg:province":"West-Vlaanderen",
    "wof:name":"Beenhouwerij Albert",
    "wof:placetype":"venue"
},
  "geometry": {"coordinates":[2.9383881092,50.8060302734],"type":"Point"}
}