{
  "type": "Feature",
  "properties": {
    "addr:full":"Place De Ronqui\u00c8res 16 Braine-le-comte Hainaut 7090",
    "addr:housenumber":"16",
    "addr:postcode":"7090",
    "addr:street":"Place De Ronquie\u0300Res",
    "iso:country":"BE",
    "sg:address":"Place De Ronqui\u00c8res 16",
    "sg:city":"Braine-le-comte",
    "sg:orig_category":"M\u00e9decins and sp\u00e9cialistes",
    "sg:phone":"+32 67 64 92 50",
    "sg:postcode":"7090",
    "sg:province":"Hainaut",
    "wof:name":"J.l. Gallez",
    "wof:placetype":"venue"
},
  "geometry": {"coordinates":[4.1455159187,50.6098175049],"type":"Point"}
}