{
  "type": "Feature",
  "properties": {
    "addr:full":"Edgard Tinelstraat 10 Stekene (klein Sinaai) Oost-Vlaanderen 9190",
    "addr:housenumber":"10",
    "addr:postcode":"9190",
    "addr:street":"Edgard Tinelstraat;Oost-Vlaanderen",
    "iso:country":"BE",
    "sg:address":"Edgard Tinelstraat 10",
    "sg:city":"Stekene (klein Sinaai)",
    "sg:classifiers":[
        {
            "category":"Health Services",
            "subcategory":"Health Practitioner",
            "type":"Services"
        }
    ],
    "sg:phone":"+32 9 346 98 98",
    "sg:postcode":"9190",
    "sg:province":"Oost-Vlaanderen",
    "sg:tags":[
        "physiotherapist"
    ],
    "wof:name":"Naessens H",
    "wof:placetype":"venue"
},
  "geometry": {"coordinates":[3.9848001003,51.1832008362],"type":"Point"}
}