{
  "type": "Feature",
  "properties": {
    "iso:country":"BE",
    "sg:address":"Hoogstraat 64b5",
    "sg:city":"Haaltert",
    "sg:orig_category":"Advocaten and juridische adviseurs",
    "sg:phone":"+32 53 83 25 52",
    "sg:postcode":"9450",
    "sg:province":"Oost-Vlaanderen",
    "wof:name":"Peter Paesen",
    "wof:placetype":"venue"
},
  "geometry": {"coordinates":[4.0031328201,50.8985061646],"type":"Point"}
}