{
  "type": "Feature",
  "properties": {
    "iso:country":"BE",
    "sg:address":"Kerkstraat 26",
    "sg:city":"Lummen",
    "sg:orig_category":"Slagers",
    "sg:phone":"+32 13 52 15 21",
    "sg:postcode":"3560",
    "sg:province":"Limburg",
    "wof:name":"Jaak Vandekerkhof",
    "wof:placetype":"venue"
},
  "geometry": {"coordinates":[5.1881518364,50.9852485657],"type":"Point"}
}