{
  "type": "Feature",
  "properties": {
    "iso:country":"BE",
    "sg:address":"Scheldestraat 19",
    "sg:city":"Antwerpen",
    "sg:classifiers":[
        {
            "category":"Cinema",
            "subcategory":"Movie Rental",
            "type":"Entertainment"
        }
    ],
    "sg:phone":"+32 3 237 42 94",
    "sg:postcode":"2000",
    "sg:province":"Antwerpen",
    "sg:tags":[
        "de",
        "cassette",
        "location",
        "vid\u00e9o",
        "audio"
    ],
    "wof:name":"Paris-texas",
    "wof:placetype":"venue"
},
  "geometry": {"coordinates":[4.3926119804,51.2129058838],"type":"Point"}
}