{
  "type": "Feature",
  "properties": {
    "iso:country":"BE",
    "sg:address":"Grotenbergestraat 111",
    "sg:city":"Zottegem",
    "sg:classifiers":[
        {
            "category":"Bars & Pubs",
            "type":"Food & Drink"
        }
    ],
    "sg:phone":"+32 9 360 44 92",
    "sg:postcode":"9620",
    "sg:province":"Oost-Vlaanderen",
    "wof:name":"Berg (den)",
    "wof:placetype":"venue"
},
  "geometry": {"coordinates":[3.8217060566,50.8719139099],"type":"Point"}
}