{
  "type": "Feature",
  "properties": {
    "iso:country":"BE",
    "sg:address":"Rue Des Pyramides 18",
    "sg:city":"Mouscron",
    "sg:classifiers":[
        {
            "category":"Real Estate",
            "subcategory":"Architect",
            "type":"Services"
        }
    ],
    "sg:phone":"+32 56 33 49 13",
    "sg:postcode":"7700",
    "sg:province":"Hainaut",
    "wof:name":"Simon B",
    "wof:placetype":"venue"
},
  "geometry": {"coordinates":[3.2127399445,50.7402801514],"type":"Point"}
}