{
  "type": "Feature",
  "properties": {
    "addr:full":"Elyzeese Velden 42 Gent Oost-Vlaanderen 9000",
    "addr:housenumber":"42",
    "addr:postcode":"9000",
    "addr:street":"Elyzeese Velden;Oost-Vlaanderen",
    "iso:country":"BE",
    "sg:address":"Elyzeese Velden 42",
    "sg:city":"Gent",
    "sg:orig_category":"Artiesten and kunstenaars",
    "sg:phone":"+32 9 233 83 99",
    "sg:postcode":"9000",
    "sg:province":"Oost-Vlaanderen",
    "wof:name":"Benoit Cooremans",
    "wof:placetype":"venue"
},
  "geometry": {"coordinates":[3.7032549381,51.0632553101],"type":"Point"}
}