{
  "type": "Feature",
  "properties": {
    "iso:country":"BE",
    "sg:address":"Rue De La Scierie 12",
    "sg:city":"Dinant",
    "sg:orig_category":"Travail and traitement du bois",
    "sg:phone":"+32 82 22 24 17",
    "sg:postcode":"5500",
    "sg:province":"Namur",
    "wof:name":"Scierie Leroy",
    "wof:placetype":"venue"
},
  "geometry": {"coordinates":[4.9568719864,50.2648162842],"type":"Point"}
}