{
  "type": "Feature",
  "properties": {
    "addr:full":"Gevaerts-zuid 53 Beernem West-Vlaanderen 8730",
    "addr:housenumber":"53",
    "addr:postcode":"8730",
    "addr:street":"Gevaerts-Zuid",
    "iso:country":"BE",
    "sg:address":"Gevaerts-zuid 53",
    "sg:city":"Beernem",
    "sg:classifiers":[
        {
            "category":"Wholesale",
            "subcategory":"Scrap",
            "type":"Manufacturing & Wholesale Goods"
        }
    ],
    "sg:phone":"+32 50 79 09 28",
    "sg:postcode":"8730",
    "sg:province":"West-Vlaanderen",
    "sg:tags":[
        "metal"
    ],
    "wof:name":"Anthoons",
    "wof:placetype":"venue"
},
  "geometry": {"coordinates":[3.2908320427,51.144367218],"type":"Point"}
}