{
  "type": "Feature",
  "properties": {
    "addr:full":"Weg Naar Zwartberg 289 Opglabbeek Limburg 3660",
    "addr:housenumber":"289",
    "addr:postcode":"3660",
    "addr:street":"Weg Naar Zwartberg",
    "iso:country":"BE",
    "sg:address":"Weg Naar Zwartberg 289",
    "sg:city":"Opglabbeek",
    "sg:classifiers":[
        {
            "category":"Retail",
            "subcategory":"Auto Repair",
            "type":"Services"
        }
    ],
    "sg:phone":"+32 89 85 47 42",
    "sg:postcode":"3660",
    "sg:province":"Limburg",
    "sg:tags":[
        "breakdown",
        "automobile",
        "-",
        "recovery"
    ],
    "wof:name":"Garage Blockken Bvba",
    "wof:placetype":"venue"
},
  "geometry": {"coordinates":[5.5513000488,51.0335998535],"type":"Point"}
}