{
  "type": "Feature",
  "properties": {
    "iso:country":"BE",
    "sg:address":"Nierstrasse 15",
    "sg:city":"Lontzen/lontzen",
    "sg:orig_category":"Rundveehouders",
    "sg:phone":"+32 87 65 96 97",
    "sg:postcode":"4711",
    "sg:province":"Li\u00e8ge",
    "wof:name":"Hubert Goor",
    "wof:placetype":"venue"
},
  "geometry": {"coordinates":[6.0316147804,50.689956665],"type":"Point"}
}