{
  "type": "Feature",
  "properties": {
    "addr:full":"Koolmijnlaan 12 Beringen Limburg 3580",
    "addr:housenumber":"12",
    "addr:postcode":"3580",
    "addr:street":"Koolmijnlaan",
    "iso:country":"BE",
    "sg:address":"Koolmijnlaan 12",
    "sg:city":"Beringen",
    "sg:classifiers":[
        {
            "category":"Fast Food",
            "type":"Food & Drink"
        }
    ],
    "sg:phone":"+32 11 45 30 99",
    "sg:postcode":"3580",
    "sg:province":"Limburg",
    "sg:tags":[
        "\u00c0",
        "emporter",
        "restaurants"
    ],
    "wof:name":"Lezzet",
    "wof:placetype":"venue"
},
  "geometry": {"coordinates":[5.2233481407,51.0499153137],"type":"Point"}
}