{
  "type": "Feature",
  "properties": {
    "iso:country":"BE",
    "sg:address":"Rue De Beaumont 382",
    "sg:city":"Charleroi",
    "sg:orig_category":"Slagers",
    "sg:phone":"+32 71 51 54 84",
    "sg:postcode":"6030",
    "sg:province":"Hainaut",
    "wof:name":"Au Petit Bedon",
    "wof:placetype":"venue"
},
  "geometry": {"coordinates":[4.3902459145,50.3953399658],"type":"Point"}
}