{
  "type": "Feature",
  "properties": {
    "iso:country":"BE",
    "sg:address":"Bremlaan 13",
    "sg:city":"Knokke-heist",
    "sg:orig_category":"Cr\u00e8ches and garderies d'enfants",
    "sg:phone":"+32 50 63 37 00",
    "sg:postcode":"8300",
    "sg:province":"West-Vlaanderen",
    "wof:name":"Kribbe 't Bremhuisje",
    "wof:placetype":"venue"
},
  "geometry": {"coordinates":[3.3043711185,51.3367576599],"type":"Point"}
}