{
  "type": "Feature",
  "properties": {
    "iso:country":"BE",
    "sg:address":"Kunstlaan 53",
    "sg:city":"Brussel/bruxelles",
    "sg:orig_category":"Software ontwikkeling and ontwerp",
    "sg:phone":"+32 2 213 30 00",
    "sg:postcode":"1000",
    "sg:province":"Bruxelles-Capitale",
    "wof:name":"Simcorp Benelux",
    "wof:placetype":"venue"
},
  "geometry": {"coordinates":[4.3668980598,50.8414230347],"type":"Point"}
}