{
  "type": "Feature",
  "properties": {
    "addr:full":"Hoogrokersstraat 7 Pittem West-Vlaanderen 8740",
    "addr:housenumber":"7",
    "addr:postcode":"8740",
    "addr:street":"Hoogrokersstraat",
    "iso:country":"BE",
    "sg:address":"Hoogrokersstraat 7",
    "sg:city":"Pittem",
    "sg:orig_category":"Rundveehouders Varkenskwekers",
    "sg:phone":"+32 51 46 64 47",
    "sg:postcode":"8740",
    "sg:province":"West-Vlaanderen",
    "wof:name":"Gabriel Patteeuw",
    "wof:placetype":"venue"
},
  "geometry": {"coordinates":[3.2420771122,51.0024795532],"type":"Point"}
}