{
  "type": "Feature",
  "properties": {
    "iso:country":"BE",
    "sg:address":"Rubenstraat 13",
    "sg:city":"Grobbendonk",
    "sg:orig_category":"Diverse bedrijfsbeheeradviesbureaus",
    "sg:phone":"+32 14 50 23 70",
    "sg:postcode":"2280",
    "sg:province":"Antwerpen",
    "wof:name":"I.q. Consulting",
    "wof:placetype":"venue"
},
  "geometry": {"coordinates":[4.7204489708,51.1920433044],"type":"Point"}
}