{
  "type": "Feature",
  "properties": {
    "iso:country":"BE",
    "sg:address":"Quai March\u00c9 Au Poisson 3",
    "sg:city":"Tournai",
    "sg:orig_category":"Pharmaciens",
    "sg:phone":"+32 69 22 26 34",
    "sg:postcode":"7500",
    "sg:province":"Hainaut",
    "wof:name":"Pharmacie Marghem",
    "wof:placetype":"venue"
},
  "geometry": {"coordinates":[3.3908369541,50.6079750061],"type":"Point"}
}