{
  "type": "Feature",
  "properties": {
    "addr:full":"Rue Fineau 20 Bruxelles Bruxelles-Capitale 1020",
    "addr:housenumber":"20",
    "addr:postcode":"1020",
    "addr:street":"Rue Fineau",
    "iso:country":"BE",
    "sg:address":"Rue Fineau 20",
    "sg:city":"Bruxelles",
    "sg:orig_category":"Non-Classified Establishments",
    "sg:phone":"+32 2 420 70 65",
    "sg:postcode":"1020",
    "sg:province":"Bruxelles-Capitale",
    "wof:name":"Kezer",
    "wof:placetype":"venue"
},
  "geometry": {"coordinates":[4.344189167,50.8794517517],"type":"Point"}
}