{
  "type": "Feature",
  "properties": {
    "addr:full":"Chauss\u00c9e D'enghien 47 Soignies Hainaut 7060",
    "addr:housenumber":"47",
    "addr:postcode":"7060",
    "addr:street":"Chausse\u0301E D'Enghien",
    "iso:country":"BE",
    "sg:address":"Chauss\u00c9e D'enghien 47",
    "sg:city":"Soignies",
    "sg:orig_category":"Enseignement maternel and primaire",
    "sg:phone":"+32 67 33 39 24",
    "sg:postcode":"7060",
    "sg:province":"Hainaut",
    "wof:name":"Ecole Fondamentale Libre",
    "wof:placetype":"venue"
},
  "geometry": {"coordinates":[4.0671629906,50.5829658508],"type":"Point"}
}