{
  "type": "Feature",
  "properties": {
    "iso:country":"BE",
    "sg:address":"Rue Du Z\u00e8\u00e9 14",
    "sg:city":"Braives",
    "sg:classifiers":[
        {
            "category":"Retail",
            "subcategory":"Auto Repair",
            "type":"Services"
        }
    ],
    "sg:phone":"+32 19 69 84 70",
    "sg:postcode":"4260",
    "sg:province":"Li\u00e8ge",
    "sg:tags":[
        "garage"
    ],
    "wof:name":"De Swart S",
    "wof:placetype":"venue"
},
  "geometry": {"coordinates":[5.1391820908,50.6214904785],"type":"Point"}
}