{
  "type": "Feature",
  "properties": {
    "iso:country":"BE",
    "sg:address":"Breidelstraat 13",
    "sg:city":"Torhout",
    "sg:orig_category":"Herenkledingzaken Kleding",
    "sg:phone":"+32 50 21 37 86",
    "sg:postcode":"8820",
    "sg:province":"West-Vlaanderen",
    "wof:name":"Trio's",
    "wof:placetype":"venue"
},
  "geometry": {"coordinates":[3.1024858952,51.0652732849],"type":"Point"}
}