{
  "type": "Feature",
  "properties": {
    "iso:country":"BE",
    "sg:address":"Av Fleming 2",
    "sg:city":"Wavre",
    "sg:classifiers":[
        {
            "category":"Wholesale",
            "subcategory":"Auto Parts",
            "type":"Manufacturing & Wholesale Goods"
        }
    ],
    "sg:phone":"+32 10 23 15 00",
    "sg:postcode":"1300",
    "sg:province":"Brabant Wallon",
    "sg:tags":[
        "pharmaceutical",
        "-",
        "chemical",
        "engineering",
        "machine",
        "mechanical",
        "chemistry",
        "by-product"
    ],
    "wof:name":"Sun Chemical Services Sa",
    "wof:placetype":"venue"
},
  "geometry": {"coordinates":[4.6024250984,50.7363739014],"type":"Point"}
}