{
  "type": "Feature",
  "properties": {
    "iso:country":"BE",
    "sg:address":"Voie De L'ardenne 108",
    "sg:city":"Chaudfontaine (embourg)",
    "sg:classifiers":[
        {
            "category":"Bakery",
            "type":"Food & Drink"
        }
    ],
    "sg:phone":"+32 4 361 09 90",
    "sg:postcode":"4053",
    "sg:province":"Li\u00e8ge",
    "sg:tags":[
        "confectioner",
        "baker"
    ],
    "wof:name":"Pain Des Champs (au)",
    "wof:placetype":"venue"
},
  "geometry": {"coordinates":[5.6068348885,50.5901451111],"type":"Point"}
}