{
  "type": "Feature",
  "properties": {
    "iso:country":"BE",
    "sg:address":"Rue Des Fran\u00e7ais 431",
    "sg:city":"Ans",
    "sg:classifiers":[
        {
            "category":"Autos & Motor Vehicles",
            "subcategory":"Automobile Sales",
            "type":"Retail Goods"
        }
    ],
    "sg:phone":"+32 4 263 99 34",
    "sg:postcode":"4430",
    "sg:province":"Li\u00e8ge",
    "sg:tags":[
        "-",
        "truck"
    ],
    "wof:name":"B T S",
    "wof:placetype":"venue"
},
  "geometry": {"coordinates":[5.5408802032,50.669418335],"type":"Point"}
}