{
  "type": "Feature",
  "properties": {
    "addr:full":"Avenue Rogier 431 Bruxelles (schaerbeek) Bruxelles-Capitale 1030",
    "addr:housenumber":"431",
    "addr:postcode":"1030",
    "addr:street":"Avenue Rogier",
    "iso:country":"BE",
    "sg:address":"Avenue Rogier 431",
    "sg:city":"Bruxelles (schaerbeek)",
    "sg:classifiers":[
        {
            "category":"Shopping",
            "subcategory":"Books",
            "type":"Retail Goods"
        }
    ],
    "sg:phone":"+32 2 734 74 54",
    "sg:postcode":"1030",
    "sg:province":"Bruxelles-Capitale",
    "sg:tags":[
        "bookseller"
    ],
    "wof:name":"Kuller Sa Ex-libris",
    "wof:placetype":"venue"
},
  "geometry": {"coordinates":[4.3973908424,50.8549385071],"type":"Point"}
}