{
  "type": "Feature",
  "properties": {
    "addr:full":"Groenplaats 7 Gingelom Limburg 3890",
    "addr:housenumber":"7",
    "addr:postcode":"3890",
    "addr:street":"Groenplaats",
    "iso:country":"BE",
    "sg:address":"Groenplaats 7",
    "sg:city":"Gingelom",
    "sg:orig_category":"Producteurs de fruits",
    "sg:phone":"+32 11 83 17 86",
    "sg:postcode":"3890",
    "sg:province":"Limburg",
    "wof:name":"Gerry Gillard",
    "wof:placetype":"venue"
},
  "geometry": {"coordinates":[5.146340847,50.717376709],"type":"Point"}
}