{
  "type": "Feature",
  "properties": {
    "addr:full":"Sint-jozefslaan 68 Mol Antwerpen 2400",
    "addr:housenumber":"68",
    "addr:postcode":"2400",
    "addr:street":"Sint-Jozefslaan",
    "iso:country":"BE",
    "sg:address":"Sint-jozefslaan 68",
    "sg:city":"Mol",
    "sg:orig_category":"Messageries",
    "sg:phone":"+32 14 71 30 03",
    "sg:postcode":"2400",
    "sg:province":"Antwerpen",
    "wof:name":"Bronco's Koerierservice",
    "wof:placetype":"venue"
},
  "geometry": {"coordinates":[5.2138161659,51.1947097778],"type":"Point"}
}