{
  "type": "Feature",
  "properties": {
    "addr:full":"Orkaanstraat 11bb Roeselare West-Vlaanderen 8800",
    "addr:housenumber":"11bb",
    "addr:postcode":"8800",
    "addr:street":"Orkaanstraat",
    "iso:country":"BE",
    "sg:address":"Orkaanstraat 11bb",
    "sg:city":"Roeselare",
    "sg:orig_category":"Drogueries",
    "sg:phone":"+32 51 24 64 51",
    "sg:postcode":"8800",
    "sg:province":"West-Vlaanderen",
    "wof:name":"Ignace De Rudder",
    "wof:placetype":"venue"
},
  "geometry": {"coordinates":[3.1252670288,50.9326248169],"type":"Point"}
}