{
  "type": "Feature",
  "properties": {
    "iso:country":"BE",
    "sg:address":"Rue Gabrielle Petit 31",
    "sg:city":"Mouscron (dottignies)",
    "sg:classifiers":[
        {
            "category":"Building & Trades",
            "subcategory":"Electrical",
            "type":"Services"
        }
    ],
    "sg:phone":"+32 56 48 98 81",
    "sg:postcode":"7711",
    "sg:province":"Hainaut",
    "sg:tags":[
        "industrial",
        "-",
        "electric",
        "contractor"
    ],
    "wof:name":"Der Electro",
    "wof:placetype":"venue"
},
  "geometry": {"coordinates":[3.3090689182,50.7219390869],"type":"Point"}
}