{
  "type": "Feature",
  "properties": {
    "iso:country":"BE",
    "sg:address":"Varkensmarkt 10",
    "sg:city":"Diepenbeek",
    "sg:orig_category":"Banken and kredietinstellingen",
    "sg:phone":"+32 11 32 45 10",
    "sg:postcode":"3590",
    "sg:province":"Limburg",
    "wof:name":"Landbouwkrediet",
    "wof:placetype":"venue"
},
  "geometry": {"coordinates":[5.4190821648,50.9084815979],"type":"Point"}
}