{
  "type": "Feature",
  "properties": {
    "iso:country":"BE",
    "sg:address":"Brusselsesteenweg 7",
    "sg:city":"Wemmel",
    "sg:orig_category":"Restaurants Ruimtes voor conferenties, recepties and feesten",
    "sg:phone":"+32 2 460 03 74",
    "sg:postcode":"1780",
    "sg:province":"Vlaams-Brabant",
    "wof:name":"De Kam",
    "wof:placetype":"venue"
},
  "geometry": {"coordinates":[4.3063421249,50.9074478149],"type":"Point"}
}