{
  "type": "Feature",
  "properties": {
    "addr:full":"Koophandelsplein 20 Gent Oost-Vlaanderen 9000",
    "addr:housenumber":"20",
    "addr:postcode":"9000",
    "addr:street":"Koophandelsplein;Oost-Vlaanderen",
    "iso:country":"BE",
    "sg:address":"Koophandelsplein 20",
    "sg:city":"Gent",
    "sg:orig_category":"Postkantoren Verzekeringsmakelaars and experts",
    "sg:phone":"+32 9 225 21 87",
    "sg:postcode":"9000",
    "sg:province":"Oost-Vlaanderen",
    "wof:name":"De Post",
    "wof:placetype":"venue"
},
  "geometry": {"coordinates":[3.7211689949,51.0494689941],"type":"Point"}
}