{
  "type": "Feature",
  "properties": {
    "iso:country":"BE",
    "sg:address":"Krommebeekstr 14",
    "sg:city":"Menen",
    "sg:classifiers":[
        {
            "category":"Manufacturing",
            "subcategory":"Textiles",
            "type":"Manufacturing & Wholesale Goods"
        }
    ],
    "sg:phone":"+32 56 52 13 80",
    "sg:postcode":"8930",
    "sg:province":"West-Vlaanderen",
    "sg:tags":[
        "clothing",
        "accessory"
    ],
    "wof:name":"Valvan Baling Systems Nv",
    "wof:placetype":"venue"
},
  "geometry": {"coordinates":[3.1293330193,50.8112869263],"type":"Point"}
}