{
  "type": "Feature",
  "properties": {
    "addr:full":"Heirbaan 245 Hamme Oost-Vlaanderen 9220",
    "addr:housenumber":"245",
    "addr:postcode":"9220",
    "addr:street":"Heirbaan",
    "iso:country":"BE",
    "sg:address":"Heirbaan 245",
    "sg:city":"Hamme",
    "sg:orig_category":"V\u00e9los",
    "sg:phone":"+32 52 47 92 17",
    "sg:postcode":"9220",
    "sg:province":"Oost-Vlaanderen",
    "wof:name":"De Blende",
    "wof:placetype":"venue"
},
  "geometry": {"coordinates":[4.0982241631,51.070602417],"type":"Point"}
}