{
  "type": "Feature",
  "properties": {
    "iso:country":"BE",
    "sg:address":"Avenue De Maire 85",
    "sg:city":"Tournai",
    "sg:orig_category":"Sportclubs Sportterreinen and installaties behalve sportcentra",
    "sg:phone":"+32 69 22 38 42",
    "sg:postcode":"7500",
    "sg:province":"Hainaut",
    "wof:name":"Royal Racing Club Tounaisien",
    "wof:placetype":"venue"
},
  "geometry": {"coordinates":[3.3740971088,50.6172523499],"type":"Point"}
}