{
  "type": "Feature",
  "properties": {
    "addr:full":"Rue Gr\u00c9goire Wincqz 270 Soignies Hainaut 7060",
    "addr:housenumber":"270",
    "addr:postcode":"7060",
    "addr:street":"Rue Gre\u0301Goire Wincqz",
    "iso:country":"BE",
    "sg:address":"Rue Gr\u00c9goire Wincqz 270",
    "sg:city":"Soignies",
    "sg:orig_category":"Landmeters",
    "sg:phone":"+32 67 34 06 10",
    "sg:postcode":"7060",
    "sg:province":"Hainaut",
    "wof:name":"J. Van Osta",
    "wof:placetype":"venue"
},
  "geometry": {"coordinates":[4.0780758858,50.5705604553],"type":"Point"}
}