{
  "type": "Feature",
  "properties": {
    "iso:country":"BE",
    "sg:address":"Avenue De La Houssi\u00c8re 194",
    "sg:city":"Braine-le-comte",
    "sg:orig_category":"Drukkerijen and copyshops",
    "sg:phone":"+32 67 56 06 34",
    "sg:postcode":"7090",
    "sg:province":"Hainaut",
    "wof:name":"Ac Bureau Services",
    "wof:placetype":"venue"
},
  "geometry": {"coordinates":[4.1664671898,50.6103096008],"type":"Point"}
}