{
  "type": "Feature",
  "properties": {
    "iso:country":"BE",
    "sg:address":"St Jan Berchmansstraat 10-12",
    "sg:city":"Diest",
    "sg:orig_category":"Mat\u00e9riel de T\u00e9l\u00e9communication",
    "sg:phone":"+32 13 33 87 60",
    "sg:postcode":"3290",
    "sg:province":"Vlaams-Brabant",
    "wof:name":"Photo Hall",
    "wof:placetype":"venue"
},
  "geometry": {"coordinates":[5.0513548851,50.9838905334],"type":"Point"}
}