{
  "type": "Feature",
  "properties": {
    "addr:full":"Rue Oswald Ponette 24 Ronse/renaix Oost-Vlaanderen 9600",
    "addr:housenumber":"24",
    "addr:postcode":"9600",
    "addr:street":"Rue Oswald Ponette",
    "iso:country":"BE",
    "sg:address":"Rue Oswald Ponette 24",
    "sg:city":"Ronse/renaix",
    "sg:orig_category":"M\u00e9decins and sp\u00e9cialistes",
    "sg:phone":"+32 55 21 51 51",
    "sg:postcode":"9600",
    "sg:province":"Oost-Vlaanderen",
    "wof:name":"J. Olemans",
    "wof:placetype":"venue"
},
  "geometry": {"coordinates":[3.5992999077,50.7470397949],"type":"Point"}
}