{
  "type": "Feature",
  "properties": {
    "iso:country":"BE",
    "sg:address":"Rue Masure 34",
    "sg:city":"Charleroi",
    "sg:orig_category":"DIVERSE RECREATIEVE ACTIVITEITEN Diverse opleidingen and onderwijs Kantoormateriaal Verhuur kantoorm",
    "sg:phone":"+32 71 37 26 31",
    "sg:postcode":"6040",
    "sg:province":"Hainaut",
    "wof:name":"D\u00c9filangues",
    "wof:placetype":"venue"
},
  "geometry": {"coordinates":[4.4114851952,50.4427223206],"type":"Point"}
}