{
  "type": "Feature",
  "properties": {
    "iso:country":"BE",
    "sg:address":"34 Rue L\u00e9opold",
    "sg:city":"Charleroi",
    "sg:classifiers":[
        {
            "category":"Government",
            "subcategory":"Department Of Motor Vehicles",
            "type":"Public Place"
        }
    ],
    "sg:phone":"+32 71 31 00 36",
    "sg:postcode":"6000",
    "sg:province":"Hainaut",
    "sg:tags":[
        "equipment",
        "industrial",
        "transport",
        "motor-cars"
    ],
    "wof:name":"D\u00c9sir\u00c9 Pontacq Sprl",
    "wof:placetype":"venue"
},
  "geometry": {"coordinates":[4.4448847771,50.4058151245],"type":"Point"}
}