{
  "type": "Feature",
  "properties": {
    "iso:country":"BE",
    "sg:address":"Speiestraat 23ba",
    "sg:city":"Wervik",
    "sg:orig_category":"Orphelinats. Instituts pour enfants en difficult\u00e9",
    "sg:phone":"+32 56 31 57 33",
    "sg:postcode":"8940",
    "sg:province":"West-Vlaanderen",
    "wof:name":"Centrum De Wijzer",
    "wof:placetype":"venue"
},
  "geometry": {"coordinates":[3.0460970402,50.7790908813],"type":"Point"}
}