{
  "type": "Feature",
  "properties": {
    "iso:country":"BE",
    "sg:address":"Trieux Des Scieurs - Tri Des Soyeux 18",
    "sg:city":"Namur (malonne)",
    "sg:classifiers":[
        {
            "category":"Personal",
            "subcategory":"Nail Salon",
            "type":"Services"
        }
    ],
    "sg:phone":"+32 81 45 00 11",
    "sg:postcode":"5020",
    "sg:province":"Namur",
    "sg:tags":[
        "pedicure"
    ],
    "wof:name":"Massaux M",
    "wof:placetype":"venue"
},
  "geometry": {"coordinates":[4.7952418327,50.4352035522],"type":"Point"}
}