{
  "type": "Feature",
  "properties": {
    "iso:country":"BE",
    "sg:address":"Kattestraat 7",
    "sg:city":"Landen",
    "sg:orig_category":"Cr\u00e8ches and garderies d'enfants",
    "sg:phone":"+32 11 88 33 46",
    "sg:postcode":"3400",
    "sg:province":"Vlaams-Brabant",
    "wof:name":"Mezenestje",
    "wof:placetype":"venue"
},
  "geometry": {"coordinates":[5.0791120529,50.7546539307],"type":"Point"}
}