{
  "type": "Feature",
  "properties": {
    "addr:full":"Stationsstraat 47 Sint-pieters-leeuw Vlaams-Brabant 1601",
    "addr:housenumber":"47",
    "addr:postcode":"1601",
    "addr:street":"Stationsstraat",
    "iso:country":"BE",
    "sg:address":"Stationsstraat 47",
    "sg:city":"Sint-pieters-leeuw",
    "sg:orig_category":"Procesbesturingssystemen Fab",
    "sg:phone":"+32 2 377 68 88",
    "sg:postcode":"1601",
    "sg:province":"Vlaams-Brabant",
    "wof:name":"L T R",
    "wof:placetype":"venue"
},
  "geometry": {"coordinates":[4.2959499359,50.7905387878],"type":"Point"}
}