{
  "type": "Feature",
  "properties": {
    "iso:country":"BE",
    "sg:address":"Rue Winamplanche 776",
    "sg:city":"Theux (la Reid)",
    "sg:classifiers":[
        {
            "category":"Parking",
            "subcategory":"Lot",
            "type":"Transportation"
        }
    ],
    "sg:phone":"+32 87 37 62 02",
    "sg:postcode":"4910",
    "sg:province":"Li\u00e8ge",
    "sg:tags":[
        "parking-places",
        "laying-out"
    ],
    "wof:name":"Boniver Entreprise Sa",
    "wof:placetype":"venue"
},
  "geometry": {"coordinates":[5.8178119659,50.476146698],"type":"Point"}
}