{
  "type": "Feature",
  "properties": {
    "iso:country":"BE",
    "sg:address":"Bergkapelstraat 56",
    "sg:city":"Londerzeel",
    "sg:orig_category":"Voertuigen",
    "sg:phone":"+32 52 30 09 38",
    "sg:postcode":"1840",
    "sg:province":"Vlaams-Brabant",
    "wof:name":"Johan Van Der Perre",
    "wof:placetype":"venue"
},
  "geometry": {"coordinates":[4.3225550652,51.0072441101],"type":"Point"}
}