{
  "type": "Feature",
  "properties": {
    "iso:country":"BE",
    "sg:address":"Route De Huy 47bc",
    "sg:city":"Ohey",
    "sg:orig_category":"Woningbouw",
    "sg:phone":"+32 85 61 18 81",
    "sg:postcode":"5351",
    "sg:province":"Namur",
    "wof:name":"Entreprises Fonteyne",
    "wof:placetype":"venue"
},
  "geometry": {"coordinates":[5.150015831,50.4366760254],"type":"Point"}
}