{
  "type": "Feature",
  "properties": {
    "iso:country":"BE",
    "sg:address":"Au Palo 22",
    "sg:city":"Chaudfontaine",
    "sg:orig_category":"D\u00e9chets and d\u00e9bris Gr",
    "sg:phone":"+32 4 367 49 56",
    "sg:postcode":"4053",
    "sg:province":"Li\u00e8ge",
    "wof:name":"Michel Groenendaels",
    "wof:placetype":"venue"
},
  "geometry": {"coordinates":[5.6067252159,50.5988273621],"type":"Point"}
}