{
  "type": "Feature",
  "properties": {
    "addr:full":"Chauss\u00e9e De Maubeuge 362 Mons (hyon) Hainaut 7022",
    "addr:housenumber":"362",
    "addr:postcode":"7022",
    "addr:street":"Chausse\u0301E De Maubeuge",
    "iso:country":"BE",
    "sg:address":"Chauss\u00e9e De Maubeuge 362",
    "sg:city":"Mons (hyon)",
    "sg:classifiers":[
        {
            "category":"Bakery",
            "type":"Food & Drink"
        }
    ],
    "sg:phone":"+32 65 84 10 10",
    "sg:postcode":"7022",
    "sg:province":"Hainaut",
    "sg:tags":[
        "confectioner",
        "baker"
    ],
    "wof:name":"Croquembouche",
    "wof:placetype":"venue"
},
  "geometry": {"coordinates":[3.9471890926,50.4331016541],"type":"Point"}
}