{
  "type": "Feature",
  "properties": {
    "addr:full":"Steenweg 14 Lierde Oost-Vlaanderen 9570",
    "addr:housenumber":"14",
    "addr:postcode":"9570",
    "addr:street":"Steenweg",
    "iso:country":"BE",
    "sg:address":"Steenweg 14",
    "sg:city":"Lierde",
    "sg:orig_category":"Benzinestations and brandstoffen Herstellingen and onderhoud van auto's",
    "sg:phone":"+32 55 42 22 49",
    "sg:postcode":"9570",
    "sg:province":"Oost-Vlaanderen",
    "wof:name":"Boone Bisschop",
    "wof:placetype":"venue"
},
  "geometry": {"coordinates":[3.8477389812,50.8187637329],"type":"Point"}
}