{
  "type": "Feature",
  "properties": {
    "iso:country":"BE",
    "sg:address":"Schutterijstraat 15",
    "sg:city":"Deinze",
    "sg:classifiers":[
        {
            "category":"Health Services",
            "subcategory":"Dentist",
            "type":"Services"
        }
    ],
    "sg:phone":"+32 9 380 42 96",
    "sg:postcode":"9800",
    "sg:province":"Oost-Vlaanderen",
    "wof:name":"Van Cauwenberghe Nathalie",
    "wof:placetype":"venue"
},
  "geometry": {"coordinates":[3.5282258987,50.9852828979],"type":"Point"}
}