{
  "type": "Feature",
  "properties": {
    "iso:country":"BE",
    "sg:address":"Raketstraat 50",
    "sg:city":"Waterloo",
    "sg:orig_category":"Telecommunicatiesystemen",
    "sg:phone":"+32 2 357 57 57",
    "sg:postcode":"1410",
    "sg:province":"Brabant Wallon",
    "wof:name":"Fe. At & T Europe",
    "wof:placetype":"venue"
},
  "geometry": {"coordinates":[4.3980250359,50.7174263],"type":"Point"}
}