{
  "type": "Feature",
  "properties": {
    "addr:full":"Krekelstraat 17 Roeselare West-Vlaanderen 8800",
    "addr:housenumber":"17",
    "addr:postcode":"8800",
    "addr:street":"Krekelstraat",
    "iso:country":"BE",
    "sg:address":"Krekelstraat 17",
    "sg:city":"Roeselare",
    "sg:classifiers":[
        {
            "category":"Utilities",
            "subcategory":"Telephone",
            "type":"Services"
        }
    ],
    "sg:phone":"+32 51 22 22 06",
    "sg:postcode":"8800",
    "sg:province":"West-Vlaanderen",
    "sg:tags":[
        "-",
        "internet"
    ],
    "wof:name":"Depoorter G",
    "wof:placetype":"venue"
},
  "geometry": {"coordinates":[3.1275420189,50.9386978149],"type":"Point"}
}