{
  "type": "Feature",
  "properties": {
    "iso:country":"BE",
    "sg:address":"Rue De Bertransart 65",
    "sg:city":"Gerpinnes",
    "sg:orig_category":"Experts-comptables",
    "sg:phone":"+32 71 30 74 60",
    "sg:postcode":"6280",
    "sg:province":"Hainaut",
    "wof:name":"Jacques Thibaut",
    "wof:placetype":"venue"
},
  "geometry": {"coordinates":[4.4811639786,50.3321685791],"type":"Point"}
}