{
  "type": "Feature",
  "properties": {
    "iso:country":"BE",
    "sg:address":"Stegelstraat 42",
    "sg:city":"Lichtervelde",
    "sg:classifiers":[
        {
            "category":"Shopping",
            "subcategory":"Clothing, Apparel, & Fashions",
            "type":"Retail Goods"
        }
    ],
    "sg:phone":"+32 51 72 32 06",
    "sg:postcode":"8810",
    "sg:province":"West-Vlaanderen",
    "sg:tags":[
        "textile",
        "clothing",
        "clothes"
    ],
    "wof:name":"Licatex Nv",
    "wof:placetype":"venue"
},
  "geometry": {"coordinates":[3.1332840919,51.020904541],"type":"Point"}
}