{
  "type": "Feature",
  "properties": {
    "addr:full":"Drapstraat 68 Hamme Oost-Vlaanderen 9220",
    "addr:housenumber":"68",
    "addr:postcode":"9220",
    "addr:street":"Drapstraat",
    "iso:country":"BE",
    "sg:address":"Drapstraat 68",
    "sg:city":"Hamme",
    "sg:classifiers":[
        {
            "category":"Home & Garden",
            "subcategory":"Building Materials",
            "type":"Retail Goods"
        }
    ],
    "sg:phone":"+32 52 47 17 78",
    "sg:postcode":"9220",
    "sg:province":"Oost-Vlaanderen",
    "sg:tags":[
        "window"
    ],
    "wof:name":"A.v.m.",
    "wof:placetype":"venue"
},
  "geometry": {"coordinates":[4.1435899734,51.0982513428],"type":"Point"}
}