{
  "type": "Feature",
  "properties": {
    "iso:country":"BE",
    "sg:address":"Beversesteenweg 255b",
    "sg:city":"Roeselare",
    "sg:orig_category":"Assistances juridiques. Conseillers fiscaux",
    "sg:phone":"+32 51 24 24 44",
    "sg:postcode":"8800",
    "sg:province":"West-Vlaanderen",
    "wof:name":"Fiduciaire Omez",
    "wof:placetype":"venue"
},
  "geometry": {"coordinates":[3.1330749989,50.9603233337],"type":"Point"}
}