{
  "type": "Feature",
  "properties": {
    "addr:full":"Peperstraat 1/3 Zingem Oost-Vlaanderen 9750",
    "addr:housenumber":"1 / 3",
    "addr:postcode":"9750",
    "addr:street":"Peperstraat;Zingem Oost-Vlaanderen",
    "iso:country":"BE",
    "sg:address":"Peperstraat 1/3",
    "sg:city":"Zingem",
    "sg:orig_category":"Diverse meubelen Fab Installatie van houten of kunststof schrijnwerk Meubelzaken, woning- and keuken",
    "sg:phone":"+32 9 384 12 03",
    "sg:postcode":"9750",
    "sg:province":"Oost-Vlaanderen",
    "wof:name":"Windels",
    "wof:placetype":"venue"
},
  "geometry": {"coordinates":[3.6538169384,50.9047698975],"type":"Point"}
}