{
  "type": "Feature",
  "properties": {
    "iso:country":"BE",
    "sg:address":"Kleine Koraalberg 8-12",
    "sg:city":"Antwerpen",
    "sg:classifiers":[
        {
            "category":"Bars & Pubs",
            "type":"Food & Drink"
        }
    ],
    "sg:phone":"+32 3 232 59 08",
    "sg:postcode":"2000",
    "sg:province":"Antwerpen",
    "wof:name":"De Gloria",
    "wof:placetype":"venue"
},
  "geometry": {"coordinates":[4.4007902145,51.222820282],"type":"Point"}
}