{
  "type": "Feature",
  "properties": {
    "addr:full":"Rue Weert-saint-georges 31 Grez-doiceau Brabant Wallon 1390",
    "addr:housenumber":"31",
    "addr:postcode":"1390",
    "addr:street":"Rue Weert-Saint-Georges",
    "iso:country":"BE",
    "sg:address":"Rue Weert-saint-georges 31",
    "sg:city":"Grez-doiceau",
    "sg:orig_category":"Plaatsen van vloer- and muurbekleding Schilders",
    "sg:phone":"+32 10 86 73 37",
    "sg:postcode":"1390",
    "sg:province":"Brabant Wallon",
    "wof:name":"Marc Fabry",
    "wof:placetype":"venue"
},
  "geometry": {"coordinates":[4.6704759598,50.7880477905],"type":"Point"}
}