{
  "type": "Feature",
  "properties": {
    "addr:full":"Hoogstraat 30 Bilzen Limburg 3740",
    "addr:housenumber":"30",
    "addr:postcode":"3740",
    "addr:street":"Hoogstraat",
    "iso:country":"BE",
    "sg:address":"Hoogstraat 30",
    "sg:city":"Bilzen",
    "sg:orig_category":"Pain, p\u00e2tisseries and confiseries",
    "sg:phone":"+32 12 45 16 19",
    "sg:postcode":"3740",
    "sg:province":"Limburg",
    "wof:name":"Pieter Janssen",
    "wof:placetype":"venue"
},
  "geometry": {"coordinates":[5.5033512115,50.8867912292],"type":"Point"}
}