{
  "type": "Feature",
  "properties": {
    "addr:full":"Albert I Laan 101-4a Nieuwpoort West-Vlaanderen 8620",
    "addr:housenumber":"101-4a",
    "addr:postcode":"8620",
    "addr:street":"Albert I Laan",
    "iso:country":"BE",
    "sg:address":"Albert I Laan 101-4a",
    "sg:city":"Nieuwpoort",
    "sg:classifiers":[
        {
            "category":"Professional",
            "subcategory":"Accounting & Tax Preparation",
            "type":"Services"
        }
    ],
    "sg:phone":"+32 58 24 18 02",
    "sg:postcode":"8620",
    "sg:province":"West-Vlaanderen",
    "sg:tags":[
        "accountant"
    ],
    "wof:name":"Madou Vandromme Accountancy Bvba",
    "wof:placetype":"venue"
},
  "geometry": {"coordinates":[2.7285749912,51.1452484131],"type":"Point"}
}