{
  "type": "Feature",
  "properties": {
    "iso:country":"BE",
    "sg:address":"Brussel Zuidstation",
    "sg:city":"Bruxelles (saint-gilles)",
    "sg:classifiers":[
        {
            "category":"Building & Trades",
            "subcategory":"Locksmith",
            "type":"Services"
        }
    ],
    "sg:phone":"+32 2 527 22 22",
    "sg:postcode":"1060",
    "sg:province":"Bruxelles-Capitale",
    "sg:tags":[
        "lock",
        "key"
    ],
    "wof:name":"Ab Serrurerie Express",
    "wof:placetype":"venue"
},
  "geometry": {"coordinates":[4.3421602249,50.8302116394],"type":"Point"}
}