{
  "type": "Feature",
  "properties": {
    "iso:country":"BE",
    "sg:address":"Chauss\u00c9e De Mons 771",
    "sg:city":"Tubize",
    "sg:orig_category":"Meubles D\u00e9taillants, Am\u00e9nagement de B\u00e2timents et de Cuisines",
    "sg:phone":"+32 2 390 01 34",
    "sg:postcode":"1480",
    "sg:province":"Brabant Wallon",
    "wof:name":"Center Literie",
    "wof:placetype":"venue"
},
  "geometry": {"coordinates":[4.1956419945,50.6854248047],"type":"Point"}
}