{
  "type": "Feature",
  "properties": {
    "addr:full":"De Ribaucourtplein 3bc Steenokkerzeel Vlaams-Brabant 1820",
    "addr:postcode":"1820",
    "addr:street":"Vlaams-Brabant",
    "iso:country":"BE",
    "sg:address":"De Ribaucourtplein 3bc",
    "sg:city":"Steenokkerzeel",
    "sg:orig_category":"Advocaten and juridische adviseurs",
    "sg:phone":"+32 2 751 61 00",
    "sg:postcode":"1820",
    "sg:province":"Vlaams-Brabant",
    "wof:name":"J. Van Hoof",
    "wof:placetype":"venue"
},
  "geometry": {"coordinates":[4.5141129494,50.9303359985],"type":"Point"}
}