{
  "type": "Feature",
  "properties": {
    "iso:country":"BE",
    "sg:address":"Rue Des Charrons 51",
    "sg:city":"Verviers",
    "sg:orig_category":"Boekhouders",
    "sg:phone":"+32 87 33 72 84",
    "sg:postcode":"4800",
    "sg:province":"Li\u00e8ge",
    "wof:name":"Roger Geelen",
    "wof:placetype":"venue"
},
  "geometry": {"coordinates":[5.8594508171,50.5917663574],"type":"Point"}
}