{
  "type": "Feature",
  "properties": {
    "addr:full":"Rue De Nimy 70 Mons Hainaut 7000",
    "addr:housenumber":"70",
    "addr:postcode":"7000",
    "addr:street":"Rue De Nimy;Hainaut",
    "iso:country":"BE",
    "sg:address":"Rue De Nimy 70",
    "sg:city":"Mons",
    "sg:orig_category":"Tribunaux",
    "sg:phone":"+32 65 34 00 85",
    "sg:postcode":"7000",
    "sg:province":"Hainaut",
    "wof:name":"Tribunal Du Travail",
    "wof:placetype":"venue"
},
  "geometry": {"coordinates":[3.9554340839,50.457359314],"type":"Point"}
}