{
  "type": "Feature",
  "properties": {
    "iso:country":"BE",
    "sg:address":"Avenue De La Station 99",
    "sg:city":"Gembloux-sur-orneau (gembloux)",
    "sg:classifiers":[
        {
            "category":"Utilities",
            "subcategory":"Telephone",
            "type":"Services"
        }
    ],
    "sg:phone":"+32 81 62 04 00",
    "sg:postcode":"5030",
    "sg:province":"Namur",
    "sg:tags":[
        "-",
        "internet"
    ],
    "wof:name":"Kf T\u00e9l\u00e9com Sprl",
    "wof:placetype":"venue"
},
  "geometry": {"coordinates":[4.6926350594,50.5689163208],"type":"Point"}
}