{
  "type": "Feature",
  "properties": {
    "addr:full":"Rue De Marche 16-11 Nandrin Li\u00e8ge 4550",
    "addr:postcode":"16-11;4550",
    "addr:street":"Rue De Marche",
    "iso:country":"BE",
    "sg:address":"Rue De Marche 16-11",
    "sg:city":"Nandrin",
    "sg:classifiers":[
        {
            "category":"Utilities",
            "subcategory":"Mobile Phone",
            "type":"Services"
        }
    ],
    "sg:phone":"+32 85 51 35 78",
    "sg:postcode":"4550",
    "sg:province":"Li\u00e8ge",
    "sg:tags":[
        "access",
        "gsm",
        "-",
        "apparatus"
    ],
    "wof:name":"Photo Nandrin",
    "wof:placetype":"venue"
},
  "geometry": {"coordinates":[5.441010952,50.5418548584],"type":"Point"}
}