{
  "type": "Feature",
  "properties": {
    "addr:full":"Vrijheid 139 Hoogstraten Antwerpen 2320",
    "addr:housenumber":"139",
    "addr:postcode":"2320",
    "addr:street":"Vrijheid",
    "iso:country":"BE",
    "sg:address":"Vrijheid 139",
    "sg:city":"Hoogstraten",
    "sg:classifiers":[
        {
            "category":"Cafe",
            "type":"Food & Drink"
        }
    ],
    "sg:phone":"+32 3 314 17 77",
    "sg:postcode":"2320",
    "sg:province":"Antwerpen",
    "sg:tags":[
        "caf\u00e9s"
    ],
    "wof:name":"Cafe T Verschil",
    "wof:placetype":"venue"
},
  "geometry": {"coordinates":[4.7613801956,51.4013137817],"type":"Point"}
}