{
  "type": "Feature",
  "properties": {
    "addr:full":"Wichelse Steenweg 31 Lede Oost-Vlaanderen 9340",
    "addr:housenumber":"31",
    "addr:postcode":"9340",
    "addr:street":"Steenweg",
    "iso:country":"BE",
    "sg:address":"Wichelse Steenweg 31",
    "sg:city":"Lede",
    "sg:orig_category":"Rev\u00eatements de sols and murs",
    "sg:phone":"+32 53 80 72 15",
    "sg:postcode":"9340",
    "sg:province":"Oost-Vlaanderen",
    "wof:name":"Parket Christiaens",
    "wof:placetype":"venue"
},
  "geometry": {"coordinates":[4.0005898476,50.9635848999],"type":"Point"}
}