{
  "type": "Feature",
  "properties": {
    "iso:country":"BE",
    "sg:address":"Spoorweglaan 2a",
    "sg:city":"Aalter",
    "sg:orig_category":"Kapsalons",
    "sg:phone":"+32 9 374 26 73",
    "sg:postcode":"9880",
    "sg:province":"Oost-Vlaanderen",
    "wof:name":"Coiffure Lujo",
    "wof:placetype":"venue"
},
  "geometry": {"coordinates":[3.4470229149,51.092124939],"type":"Point"}
}