{
  "type": "Feature",
  "properties": {
    "addr:full":"Rue De La Mutualit\u00c9 45b2 Vorst/forest Bruxelles-Capitale 1190",
    "addr:housenumber":"45b2",
    "addr:postcode":"1190",
    "addr:street":"Rue De La Mutualite\u0301;/ Forest",
    "iso:country":"BE",
    "sg:address":"Rue De La Mutualit\u00c9 45b2",
    "sg:city":"Vorst/forest",
    "sg:orig_category":"D\u00e9corateurs d'int\u00e9rieur",
    "sg:phone":"+32 2 346 08 38",
    "sg:postcode":"1190",
    "sg:province":"Bruxelles-Capitale",
    "wof:name":"Fabrice Portois",
    "wof:placetype":"venue"
},
  "geometry": {"coordinates":[4.3446259499,50.8144035339],"type":"Point"}
}