{
  "type": "Feature",
  "properties": {
    "iso:country":"BE",
    "sg:address":"Rue Des Bourgeois 1",
    "sg:city":"Fleurus",
    "sg:classifiers":[
        {
            "category":"Personal",
            "subcategory":"Beauty Salon",
            "type":"Services"
        }
    ],
    "sg:phone":"+32 71 81 15 93",
    "sg:postcode":"6220",
    "sg:province":"Hainaut",
    "sg:tags":[
        "lady",
        "-",
        "hairdressing"
    ],
    "wof:name":"Helene T",
    "wof:placetype":"venue"
},
  "geometry": {"coordinates":[4.5504441261,50.4829406738],"type":"Point"}
}