{
  "type": "Feature",
  "properties": {
    "addr:full":"Liersebaan 235 Massenhoven Antwerpen 2240",
    "addr:housenumber":"235",
    "addr:postcode":"2240",
    "addr:street":"Liersebaan",
    "iso:country":"BE",
    "sg:address":"Liersebaan 235",
    "sg:city":"Massenhoven",
    "sg:classifiers":[
        {
            "category":"Building & Trades",
            "subcategory":"Landscaping Services",
            "type":"Services"
        }
    ],
    "sg:phone":"+32 3 475 17 85",
    "sg:postcode":"2240",
    "sg:province":"Antwerpen",
    "sg:tags":[
        "horticulture",
        "gardening",
        "landscape"
    ],
    "wof:name":"Brasseur & Van Den Bouwhuysen",
    "wof:placetype":"venue"
},
  "geometry": {"coordinates":[4.6286687851,51.1864967346],"type":"Point"}
}