{
  "type": "Feature",
  "properties": {
    "addr:full":"Stationsstraat 122 Ardooie West-Vlaanderen 8850",
    "addr:housenumber":"122",
    "addr:postcode":"8850",
    "addr:street":"Stationsstraat",
    "iso:country":"BE",
    "sg:address":"Stationsstraat 122",
    "sg:city":"Ardooie",
    "sg:classifiers":[
        {
            "category":"Personal",
            "subcategory":"Beauty Salon",
            "type":"Services"
        }
    ],
    "sg:phone":"+32 51 74 47 61",
    "sg:postcode":"8850",
    "sg:province":"West-Vlaanderen",
    "sg:tags":[
        "lady",
        "-",
        "hairdressing"
    ],
    "wof:name":"Kapsalon Stern",
    "wof:placetype":"venue"
},
  "geometry": {"coordinates":[3.2022008896,50.9832725525],"type":"Point"}
}