{
  "type": "Feature",
  "properties": {
    "addr:full":"Chauss\u00c9e De Bruxelles 417ba Charleroi Hainaut 6040",
    "addr:postcode":"6040",
    "addr:street":"Chausse\u0301E De Bruxelles 417Ba;Hainaut",
    "iso:country":"BE",
    "sg:address":"Chauss\u00c9e De Bruxelles 417ba",
    "sg:city":"Charleroi",
    "sg:orig_category":"V\u00e9hicules automobiles",
    "sg:phone":"+32 71 35 75 70",
    "sg:postcode":"6040",
    "sg:province":"Hainaut",
    "wof:name":"Lagaune",
    "wof:placetype":"venue"
},
  "geometry": {"coordinates":[4.4333381653,50.4512214661],"type":"Point"}
}