{
  "type": "Feature",
  "properties": {
    "iso:country":"BE",
    "sg:address":"Deensewyr 10 ( Kmo-zone)",
    "sg:city":"Bilzen",
    "sg:orig_category":"Traitement and rev\u00eatement des m\u00e9taux",
    "sg:phone":"+32 89 51 52 08",
    "sg:postcode":"3740",
    "sg:province":"Limburg",
    "wof:name":"Nelissen L. Laswerken",
    "wof:placetype":"venue"
},
  "geometry": {"coordinates":[5.5133070946,50.8699760437],"type":"Point"}
}