{
  "type": "Feature",
  "properties": {
    "iso:country":"BE",
    "sg:address":"Rue Des Abattis 90",
    "sg:city":"Bouillon",
    "sg:orig_category":"Enseignement maternel and primaire",
    "sg:phone":"+32 61 46 87 26",
    "sg:postcode":"6838",
    "sg:province":"Luxembourg",
    "wof:name":"Ecole Prim. Communale",
    "wof:placetype":"venue"
},
  "geometry": {"coordinates":[5.0071702003,49.7973403931],"type":"Point"}
}