{
  "type": "Feature",
  "properties": {
    "addr:full":"Rue Des Abattis 90 Bouillon Luxembourg 6838",
    "addr:housenumber":"90",
    "addr:postcode":"6838",
    "addr:street":"Rue Des Abattis",
    "iso:country":"BE",
    "sg:address":"Rue Des Abattis 90",
    "sg:city":"Bouillon",
    "sg:orig_category":"Enseignement maternel and primaire",
    "sg:phone":"+32 61 46 87 26",
    "sg:postcode":"6838",
    "sg:province":"Luxembourg",
    "wof:name":"Ecole Prim. Communale",
    "wof:placetype":"venue"
},
  "geometry": {"coordinates":[5.0071702003,49.7973403931],"type":"Point"}
}