{
  "type": "Feature",
  "properties": {
    "iso:country":"BE",
    "sg:address":"Dorenboslaan 2",
    "sg:city":"Wijnegem",
    "sg:classifiers":[
        {
            "category":"Restaurant",
            "type":"Food & Drink"
        }
    ],
    "sg:phone":"+32 3 353 92 76",
    "sg:postcode":"2110",
    "sg:province":"Antwerpen",
    "wof:name":"Lunch Garden",
    "wof:placetype":"venue"
},
  "geometry": {"coordinates":[4.5040102005,51.2217788696],"type":"Point"}
}