{
  "type": "Feature",
  "properties": {
    "iso:country":"BE",
    "sg:address":"Keizershoek 214",
    "sg:city":"Kontich",
    "sg:orig_category":"Eclairage et \u00e9quipements du foyer",
    "sg:phone":"+32 3 457 51 05",
    "sg:postcode":"2550",
    "sg:province":"Antwerpen",
    "wof:name":"Marc Goossens",
    "wof:placetype":"venue"
},
  "geometry": {"coordinates":[4.4383239746,51.1247253418],"type":"Point"}
}