{
  "type": "Feature",
  "properties": {
    "addr:full":"Molenstraat 10 Zottegem Oost-Vlaanderen 9620",
    "addr:housenumber":"10",
    "addr:postcode":"9620",
    "addr:street":"Molenstraat",
    "iso:country":"BE",
    "sg:address":"Molenstraat 10",
    "sg:city":"Zottegem",
    "sg:orig_category":"Kunstonderwijs",
    "sg:phone":"+32 9 364 64 81",
    "sg:postcode":"9620",
    "sg:province":"Oost-Vlaanderen",
    "wof:name":"Acad. Beeldende Kunsten",
    "wof:placetype":"venue"
},
  "geometry": {"coordinates":[3.8091740608,50.8667373657],"type":"Point"}
}