{
  "type": "Feature",
  "properties": {
    "iso:country":"BE",
    "sg:address":"Dorp 1a",
    "sg:city":"Bouwel",
    "sg:classifiers":[
        {
            "category":"Professional",
            "subcategory":"Computer Services",
            "type":"Services"
        }
    ],
    "sg:phone":"+32 14 51 28 65",
    "sg:postcode":"2288",
    "sg:province":"Antwerpen",
    "sg:tags":[
        "microsoft"
    ],
    "wof:name":"Zeb Electronics",
    "wof:placetype":"venue"
},
  "geometry": {"coordinates":[4.7416257858,51.1721839905],"type":"Point"}
}