{
  "type": "Feature",
  "properties": {
    "addr:full":"Rue De Barvaux 6 Durbuy (bomal-sur-ourthe) Luxembourg 6941",
    "addr:housenumber":"6",
    "addr:postcode":"6941",
    "addr:street":"Rue De Barvaux",
    "iso:country":"BE",
    "sg:address":"Rue De Barvaux 6",
    "sg:city":"Durbuy (bomal-sur-ourthe)",
    "sg:classifiers":[
        {
            "category":"Insurance",
            "subcategory":"Insurance Agent",
            "type":"Services"
        }
    ],
    "sg:phone":"+32 86 21 28 17",
    "sg:postcode":"6941",
    "sg:province":"Luxembourg",
    "sg:tags":[
        "broker"
    ],
    "wof:name":"Figass-lamotte Scrl",
    "wof:placetype":"venue"
},
  "geometry": {"coordinates":[5.524184227,50.3770332336],"type":"Point"}
}