{
  "type": "Feature",
  "properties": {
    "iso:country":"BE",
    "sg:address":"Hospitaalstraat 2",
    "sg:city":"Evergem (ertvelde)",
    "sg:classifiers":[
        {
            "category":"Health Services",
            "subcategory":"Nursing And Care Facility",
            "type":"Services"
        }
    ],
    "sg:phone":"+32 9 344 55 84",
    "sg:postcode":"9940",
    "sg:province":"Oost-Vlaanderen",
    "sg:tags":[
        "home",
        "rest"
    ],
    "wof:name":"Rvt Sint-jozef",
    "wof:placetype":"venue"
},
  "geometry": {"coordinates":[3.7470550537,51.179485321],"type":"Point"}
}