{
  "type": "Feature",
  "properties": {
    "iso:country":"BE",
    "sg:address":"Rue Sous-le-ch\u00c2teau 47",
    "sg:city":"Huy",
    "sg:classifiers":[
        {
            "category":"Shopping Center",
            "type":"Public Place"
        }
    ],
    "sg:phone":"+32 85 25 15 86",
    "sg:postcode":"4500",
    "sg:province":"Li\u00e8ge",
    "sg:tags":[
        "enseignement",
        "formation"
    ],
    "wof:name":"Vega Engineering",
    "wof:placetype":"venue"
},
  "geometry": {"coordinates":[5.2389669418,50.5167961121],"type":"Point"}
}