{
  "type": "Feature",
  "properties": {
    "iso:country":"BE",
    "sg:address":"Langendamdreef 11",
    "sg:city":"Aalter",
    "sg:classifiers":[
        {
            "category":"Professional",
            "subcategory":"Management & Consulting",
            "type":"Services"
        }
    ],
    "sg:phone":"+32 9 375 13 73",
    "sg:postcode":"9880",
    "sg:province":"Oost-Vlaanderen",
    "sg:tags":[
        "consultant"
    ],
    "wof:name":"Verhaeghe P",
    "wof:placetype":"venue"
},
  "geometry": {"coordinates":[3.4641869068,51.0737915039],"type":"Point"}
}