{
  "type": "Feature",
  "properties": {
    "iso:country":"BE",
    "sg:address":"Gulden-sporenlaan 8",
    "sg:city":"Elsene/ixelles",
    "sg:orig_category":"Artsen and specialisten",
    "sg:phone":"+32 2 647 26 38",
    "sg:postcode":"1050",
    "sg:province":"Bruxelles-Capitale",
    "wof:name":"Roland Lef\u00c8vre",
    "wof:placetype":"venue"
},
  "geometry": {"coordinates":[4.3731350899,50.824886322],"type":"Point"}
}