{
  "type": "Feature",
  "properties": {
    "iso:country":"BE",
    "sg:address":"Ettelgemsestraat 96",
    "sg:city":"Oudenburg",
    "sg:orig_category":"Bloemen and planten Tuinbenodigdheden",
    "sg:phone":"+32 59 26 69 17",
    "sg:postcode":"8460",
    "sg:province":"West-Vlaanderen",
    "wof:name":"Plantencentrum De Vrijboom",
    "wof:placetype":"venue"
},
  "geometry": {"coordinates":[3.0185899734,51.1831016541],"type":"Point"}
}