{
  "type": "Feature",
  "properties": {
    "addr:full":"Gouverneur Roppesingel 81b4 Hasselt Limburg 3500",
    "addr:housenumber":"81b4",
    "addr:postcode":"3500",
    "addr:street":"Gouverneur Roppesingel",
    "iso:country":"BE",
    "sg:address":"Gouverneur Roppesingel 81b4",
    "sg:city":"Hasselt",
    "sg:orig_category":"Schoonmaakbedrijven and ongediertebestrijding",
    "sg:phone":"+32 11 27 97 10",
    "sg:postcode":"3500",
    "sg:province":"Limburg",
    "wof:name":"Fa. Actief Cleaning",
    "wof:placetype":"venue"
},
  "geometry": {"coordinates":[5.353823185,50.92004776],"type":"Point"}
}