{
  "type": "Feature",
  "properties": {
    "iso:country":"BE",
    "sg:address":"Vrasenestraat 47",
    "sg:city":"Beveren",
    "sg:orig_category":"Brood, gebak and snoepgoed",
    "sg:phone":"+32 3 775 46 29",
    "sg:postcode":"9120",
    "sg:province":"Oost-Vlaanderen",
    "wof:name":"Leonidas",
    "wof:placetype":"venue"
},
  "geometry": {"coordinates":[4.2543039322,51.2135429382],"type":"Point"}
}