{
  "type": "Feature",
  "properties": {
    "addr:full":"Voortkapelseweg 18 Olen Antwerpen 2250",
    "addr:housenumber":"18",
    "addr:postcode":"2250",
    "addr:street":"Voortkapelseweg",
    "iso:country":"BE",
    "sg:address":"Voortkapelseweg 18",
    "sg:city":"Olen",
    "sg:orig_category":"Sportactiviteiten en -evenementen",
    "sg:phone":"+32 14 26 30 50",
    "sg:postcode":"2250",
    "sg:province":"Antwerpen",
    "wof:name":"Rabbits Ballooning-olens Ballonteam",
    "wof:placetype":"venue"
},
  "geometry": {"coordinates":[4.8560771942,51.1414642334],"type":"Point"}
}