{
  "type": "Feature",
  "properties": {
    "addr:full":"Anjerstraat 16b1 Meeuwen-gruitrode Limburg 3670",
    "addr:housenumber":"16b1",
    "addr:postcode":"3670",
    "addr:street":"Anjerstraat",
    "iso:country":"BE",
    "sg:address":"Anjerstraat 16b1",
    "sg:city":"Meeuwen-gruitrode",
    "sg:orig_category":"Installation de menuiserie en bois and plastique. Eclairage et \u00e9quipements du foyer",
    "sg:phone":"+32 11 79 29 56",
    "sg:postcode":"3670",
    "sg:province":"Limburg",
    "wof:name":"Kerkhofs-neyens",
    "wof:placetype":"venue"
},
  "geometry": {"coordinates":[5.5353059769,51.0797615051],"type":"Point"}
}