{
  "type": "Feature",
  "properties": {
    "iso:country":"BE",
    "sg:address":"Rue Des Pages 7",
    "sg:city":"Burdinne",
    "sg:orig_category":"Herstellingen and onderhoud van auto's Onderdelen and accessoires voor auto's",
    "sg:phone":"+32 85 71 14 48",
    "sg:postcode":"4210",
    "sg:province":"Li\u00e8ge",
    "wof:name":"Garage De'ville De Goyet",
    "wof:placetype":"venue"
},
  "geometry": {"coordinates":[5.1265058517,50.5799636841],"type":"Point"}
}