{
  "type": "Feature",
  "properties": {
    "addr:full":"Rue Elisa Dumonceau 58 Herstal Li\u00e8ge 4040",
    "addr:housenumber":"58",
    "addr:postcode":"4040",
    "addr:street":"Rue Elisa Dumonceau",
    "iso:country":"BE",
    "sg:address":"Rue Elisa Dumonceau 58",
    "sg:city":"Herstal",
    "sg:classifiers":[
        {
            "category":"Shopping",
            "subcategory":"Jewelry",
            "type":"Retail Goods"
        }
    ],
    "sg:phone":"+32 4 264 05 35",
    "sg:postcode":"4040",
    "sg:province":"Li\u00e8ge",
    "sg:tags":[
        "jeweller",
        "-"
    ],
    "wof:name":"Collard L",
    "wof:placetype":"venue"
},
  "geometry": {"coordinates":[5.6292748451,50.6636047363],"type":"Point"}
}