{
  "type": "Feature",
  "properties": {
    "addr:full":"St Willebrorduspln 21 Heusden Limburg 3550",
    "addr:housenumber":"21",
    "addr:postcode":"3550",
    "iso:country":"BE",
    "sg:address":"St Willebrorduspln 21",
    "sg:city":"Heusden",
    "sg:classifiers":[
        {
            "category":"Banks & Credit Unions",
            "subcategory":"Bank",
            "type":"Services"
        }
    ],
    "sg:phone":"+32 11 42 33 23",
    "sg:postcode":"3550",
    "sg:province":"Limburg",
    "wof:name":"Gemeentekrediet",
    "wof:placetype":"venue"
},
  "geometry": {"coordinates":[5.2816038132,51.0332450867],"type":"Point"}
}