{
  "type": "Feature",
  "properties": {
    "iso:country":"BE",
    "sg:address":"Grootbroekstraat 28",
    "sg:city":"Dendermonde",
    "sg:classifiers":[
        {
            "category":"Arena",
            "subcategory":"Sports Club",
            "type":"Entertainment"
        }
    ],
    "sg:phone":"+32 52 22 43 89",
    "sg:postcode":"9200",
    "sg:province":"Oost-Vlaanderen",
    "sg:tags":[
        "de"
    ],
    "wof:name":"T.c. Topspin",
    "wof:placetype":"venue"
},
  "geometry": {"coordinates":[4.1087651253,51.0446395874],"type":"Point"}
}