{
  "type": "Feature",
  "properties": {
    "addr:full":"Eindstraat 1 Neerpelt Limburg 3910",
    "addr:housenumber":"1",
    "addr:postcode":"3910",
    "addr:street":"Eindstraat",
    "iso:country":"BE",
    "sg:address":"Eindstraat 1",
    "sg:city":"Neerpelt",
    "sg:classifiers":[
        {
            "category":"Home & Garden",
            "subcategory":"Building Materials",
            "type":"Retail Goods"
        }
    ],
    "sg:phone":"+32 11 66 16 67",
    "sg:postcode":"3910",
    "sg:province":"Limburg",
    "sg:tags":[
        "insect",
        "screen"
    ],
    "wof:name":"H R Vliegenramen & -deuren Bvba",
    "wof:placetype":"venue"
},
  "geometry": {"coordinates":[5.4367799759,51.2402305603],"type":"Point"}
}