{
  "type": "Feature",
  "properties": {
    "iso:country":"BE",
    "sg:address":"Grensstraat 5",
    "sg:city":"Sint-lenaarts",
    "sg:classifiers":[
        {
            "category":"Home & Garden",
            "subcategory":"Carpets & Floor Coverings",
            "type":"Retail Goods"
        }
    ],
    "sg:phone":"+32 3 314 62 23",
    "sg:postcode":"2960",
    "sg:province":"Antwerpen",
    "sg:tags":[
        "supraregional",
        "flooring"
    ],
    "wof:name":"Jochems Gebroeders Nv",
    "wof:placetype":"venue"
},
  "geometry": {"coordinates":[4.7223420143,51.3509597778],"type":"Point"}
}