{
  "type": "Feature",
  "properties": {
    "iso:country":"BE",
    "sg:address":"Rue Des Alli\u00e9s 2",
    "sg:city":"Frameries",
    "sg:classifiers":[
        {
            "category":"Professional",
            "subcategory":"Credit Reporting & Collection",
            "type":"Services"
        }
    ],
    "sg:phone":"+32 65 67 49 20",
    "sg:postcode":"7080",
    "sg:province":"Hainaut",
    "sg:tags":[
        "bailiff"
    ],
    "wof:name":"Pi\u00e9rart Y",
    "wof:placetype":"venue"
},
  "geometry": {"coordinates":[3.8952260017,50.4109039307],"type":"Point"}
}