{
  "type": "Feature",
  "properties": {
    "addr:full":"Rue Du Marais 10 Peruwelz Hainaut 7604",
    "addr:housenumber":"10",
    "addr:postcode":"7604",
    "addr:street":"Rue Du Marais;Hainaut",
    "iso:country":"BE",
    "sg:address":"Rue Du Marais 10",
    "sg:city":"Peruwelz",
    "sg:orig_category":"Rundveehouders",
    "sg:phone":"+32 69 77 25 46",
    "sg:postcode":"7604",
    "sg:province":"Hainaut",
    "wof:name":"Raoul Procureur",
    "wof:placetype":"venue"
},
  "geometry": {"coordinates":[3.5185029507,50.5297698975],"type":"Point"}
}