{
  "type": "Feature",
  "properties": {
    "addr:full":"Kerkhoflei 47 Mechelen Antwerpen 2800",
    "addr:housenumber":"47",
    "addr:postcode":"2800",
    "addr:street":"Kerkhoflei",
    "iso:country":"BE",
    "sg:address":"Kerkhoflei 47",
    "sg:city":"Mechelen",
    "sg:orig_category":"Enseignement maternel and primaire",
    "sg:phone":"+32 15 20 43 40",
    "sg:postcode":"2800",
    "sg:province":"Antwerpen",
    "wof:name":"Vrije Basisschool",
    "wof:placetype":"venue"
},
  "geometry": {"coordinates":[4.4830489159,51.0383796692],"type":"Point"}
}