{
  "type": "Feature",
  "properties": {
    "addr:full":"Rue Du Petit Bois 50 Namur Namur 5020",
    "addr:housenumber":"50",
    "addr:postcode":"5020",
    "addr:street":"Rue Du Petit Bois",
    "iso:country":"BE",
    "sg:address":"Rue Du Petit Bois 50",
    "sg:city":"Namur",
    "sg:orig_category":"Woningbouw",
    "sg:phone":"+32 81 44 03 33",
    "sg:postcode":"5020",
    "sg:province":"Namur",
    "wof:name":"Entreprises Tellier",
    "wof:placetype":"venue"
},
  "geometry": {"coordinates":[4.8014330864,50.4223213196],"type":"Point"}
}