{
  "type": "Feature",
  "properties": {
    "addr:full":"Sint-denijsplaats 30 Zwevegem (sint-denijs) West-Vlaanderen 8554",
    "addr:housenumber":"30",
    "addr:postcode":"8554",
    "addr:street":"Sint-Denijsplaats",
    "iso:country":"BE",
    "sg:address":"Sint-denijsplaats 30",
    "sg:city":"Zwevegem (sint-denijs)",
    "sg:classifiers":[
        {
            "category":"Health Services",
            "subcategory":"Health Practitioner",
            "type":"Services"
        }
    ],
    "sg:phone":"+32 56 45 65 63",
    "sg:postcode":"8554",
    "sg:province":"West-Vlaanderen",
    "sg:tags":[
        "physiotherapist"
    ],
    "wof:name":"Smet Koen",
    "wof:placetype":"venue"
},
  "geometry": {"coordinates":[3.3668088913,50.7520980835],"type":"Point"}
}