{
  "type": "Feature",
  "properties": {
    "addr:full":"Slagmolenlaan 43 Merchtem Vlaams-Brabant 1785",
    "addr:housenumber":"43",
    "addr:postcode":"1785",
    "addr:street":"Slagmolenlaan",
    "iso:country":"BE",
    "sg:address":"Slagmolenlaan 43",
    "sg:city":"Merchtem",
    "sg:classifiers":[
        {
            "category":"Personal",
            "subcategory":"Beauty Salon",
            "type":"Services"
        }
    ],
    "sg:phone":"+32 52 37 21 28",
    "sg:postcode":"1785",
    "sg:province":"Vlaams-Brabant",
    "sg:tags":[
        "lady",
        "-",
        "hairdressing"
    ],
    "wof:name":"Monique",
    "wof:placetype":"venue"
},
  "geometry": {"coordinates":[4.2345738411,50.9500541687],"type":"Point"}
}