{
  "type": "Feature",
  "properties": {
    "iso:country":"BE",
    "sg:address":"Route De Hannut 109",
    "sg:city":"Namur",
    "sg:classifiers":[
        {
            "category":"Personal",
            "subcategory":"Beauty Salon",
            "type":"Services"
        }
    ],
    "sg:phone":"+32 81 21 59 66",
    "sg:postcode":"5004",
    "sg:province":"Namur",
    "sg:tags":[
        "de",
        "coiffure"
    ],
    "wof:name":"Annick Lucas",
    "wof:placetype":"venue"
},
  "geometry": {"coordinates":[4.9062547684,50.475402832],"type":"Point"}
}