{
  "type": "Feature",
  "properties": {
    "addr:full":"'s Graventafelstraat 1 Zonnebeke (passendale) West-Vlaanderen 8980",
    "addr:housenumber":"1",
    "addr:postcode":"8980",
    "addr:street":"' S Graventafelstraat",
    "iso:country":"BE",
    "sg:address":"'s Graventafelstraat 1",
    "sg:city":"Zonnebeke (passendale)",
    "sg:classifiers":[
        {
            "category":"Autos & Motor Vehicles",
            "subcategory":"Automobile Sales",
            "type":"Retail Goods"
        }
    ],
    "sg:phone":"+32 51 77 04 07",
    "sg:postcode":"8980",
    "sg:province":"West-Vlaanderen",
    "sg:tags":[
        "car",
        "used",
        "-"
    ],
    "wof:name":"Degryse Joris Cv",
    "wof:placetype":"venue"
},
  "geometry": {"coordinates":[3.0194449425,50.9081802368],"type":"Point"}
}