{
  "type": "Feature",
  "properties": {
    "iso:country":"BE",
    "sg:address":"Dorpshof 17",
    "sg:city":"Heusden-zolder",
    "sg:orig_category":"Woningbouw",
    "sg:phone":"+32 11 53 76 65",
    "sg:postcode":"3550",
    "sg:province":"Limburg",
    "wof:name":"Romanus Bogaerts",
    "wof:placetype":"venue"
},
  "geometry": {"coordinates":[5.3119649887,51.0191917419],"type":"Point"}
}