{
  "type": "Feature",
  "properties": {
    "addr:full":"Assesteenweg 33 Roosdaal Vlaams-Brabant 1761",
    "addr:housenumber":"33",
    "addr:postcode":"1761",
    "addr:street":"Assesteenweg",
    "iso:country":"BE",
    "sg:address":"Assesteenweg 33",
    "sg:city":"Roosdaal",
    "sg:orig_category":"Advocaten and juridische adviseurs",
    "sg:phone":"+32 2 582 33 96",
    "sg:postcode":"1761",
    "sg:province":"Vlaams-Brabant",
    "wof:name":"Maria Uyttendaele",
    "wof:placetype":"venue"
},
  "geometry": {"coordinates":[4.136548996,50.848526001],"type":"Point"}
}