{
  "type": "Feature",
  "properties": {
    "iso:country":"BE",
    "sg:address":"Varensbos 9",
    "sg:city":"Lovendegem",
    "sg:classifiers":[
        {
            "category":"Building & Trades",
            "subcategory":"Cleaning & Sanitation",
            "type":"Services"
        }
    ],
    "sg:phone":"+32 9 372 70 58",
    "sg:postcode":"9920",
    "sg:province":"Oost-Vlaanderen",
    "sg:tags":[
        "cleaner",
        "window"
    ],
    "wof:name":"Vitro-quick",
    "wof:placetype":"venue"
},
  "geometry": {"coordinates":[3.615530014,51.1176338196],"type":"Point"}
}