{
  "type": "Feature",
  "properties": {
    "iso:country":"BE",
    "sg:address":"Mosselerlaan 115",
    "sg:city":"Genk",
    "sg:classifiers":[
        {
            "category":"Real Estate",
            "subcategory":"Architect",
            "type":"Services"
        }
    ],
    "sg:phone":"+32 89 30 40 20",
    "sg:postcode":"3600",
    "sg:province":"Limburg",
    "wof:name":"Houben Eric",
    "wof:placetype":"venue"
},
  "geometry": {"coordinates":[5.5115671158,50.9766082764],"type":"Point"}
}