{
  "type": "Feature",
  "properties": {
    "iso:country":"BE",
    "sg:address":"Rue De La Grotte 2",
    "sg:city":"Brussel/bruxelles",
    "sg:orig_category":"Travaux de pl\u00e2trage. Peinture. Eclairage et \u00e9quipements du foyer. Rev\u00eatements pour sols and murs. Tr",
    "sg:phone":"+32 2 478 56 43",
    "sg:postcode":"1020",
    "sg:province":"Bruxelles-Capitale",
    "wof:name":"Valcke-decors",
    "wof:placetype":"venue"
},
  "geometry": {"coordinates":[4.3597002029,50.878288269],"type":"Point"}
}