{
  "type": "Feature",
  "properties": {
    "iso:country":"BE",
    "sg:address":"Wezestraat 10",
    "sg:city":"Ardooie",
    "sg:orig_category":"Plomberie, chauffage and installations sanitaires",
    "sg:phone":"+32 51 74 53 47",
    "sg:postcode":"8850",
    "sg:province":"West-Vlaanderen",
    "wof:name":"Kurt Vandenbussche",
    "wof:placetype":"venue"
},
  "geometry": {"coordinates":[3.2045359612,50.973777771],"type":"Point"}
}