{
  "type": "Feature",
  "properties": {
    "addr:full":"Rue Aux Pois 83 Tournai (templeuve) Hainaut 7520",
    "addr:housenumber":"83",
    "addr:postcode":"7520",
    "addr:street":"Rue Aux Pois",
    "iso:country":"BE",
    "sg:address":"Rue Aux Pois 83",
    "sg:city":"Tournai (templeuve)",
    "sg:classifiers":[
        {
            "category":"Building & Trades",
            "subcategory":"Landscaping Services",
            "type":"Services"
        }
    ],
    "sg:postcode":"7520",
    "sg:province":"Hainaut",
    "sg:tags":[
        "handicraft"
    ],
    "wof:name":"Kadoriane",
    "wof:placetype":"venue"
},
  "geometry": {"coordinates":[3.2805891037,50.6400299072],"type":"Point"}
}