{
  "type": "Feature",
  "properties": {
    "addr:full":"Rue Fran\u00c7ois Dive 28 Sambreville Namur 5060",
    "addr:housenumber":"28",
    "addr:postcode":"5060",
    "addr:street":"Rue Franc\u0327Ois Dive",
    "iso:country":"BE",
    "sg:address":"Rue Fran\u00c7ois Dive 28",
    "sg:city":"Sambreville",
    "sg:classifiers":[
        {
            "category":"Restaurant",
            "type":"Food & Drink"
        }
    ],
    "sg:phone":"+32 71 76 10 95",
    "sg:postcode":"5060",
    "sg:province":"Namur",
    "wof:name":"Le Rif",
    "wof:placetype":"venue"
},
  "geometry": {"coordinates":[4.6285200119,50.4448738098],"type":"Point"}
}