{
  "type": "Feature",
  "properties": {
    "addr:full":"Rue Boursoit 8 Onhaye Namur 5524",
    "addr:housenumber":"8",
    "addr:postcode":"5524",
    "addr:street":"Rue Boursoit",
    "iso:country":"BE",
    "sg:address":"Rue Boursoit 8",
    "sg:city":"Onhaye",
    "sg:classifiers":[
        {
            "category":"Arena",
            "subcategory":"Sports Club",
            "type":"Entertainment"
        }
    ],
    "sg:phone":"+32 82 64 64 98",
    "sg:postcode":"5524",
    "sg:province":"Namur",
    "sg:tags":[
        "de"
    ],
    "wof:name":"J.c. Kyo Jyaku",
    "wof:placetype":"venue"
},
  "geometry": {"coordinates":[4.8164858818,50.2454528809],"type":"Point"}
}