{
  "type": "Feature",
  "properties": {
    "addr:full":"Rue Du Calvaire 1 Celles Hainaut 7760",
    "addr:housenumber":"1",
    "addr:postcode":"7760",
    "addr:street":"Rue Du Calvaire",
    "iso:country":"BE",
    "sg:address":"Rue Du Calvaire 1",
    "sg:city":"Celles",
    "sg:orig_category":"Maisons de repos and r\u00e9sidences",
    "sg:phone":"+32 69 45 44 12",
    "sg:postcode":"7760",
    "sg:province":"Hainaut",
    "wof:name":"Institut St.joseph",
    "wof:placetype":"venue"
},
  "geometry": {"coordinates":[3.4545609951,50.7126617432],"type":"Point"}
}