{
  "type": "Feature",
  "properties": {
    "iso:country":"BE",
    "sg:address":"Thommen 53ba",
    "sg:city":"Burg-reuland",
    "sg:orig_category":"Installation de menuiserie m\u00e9tallique",
    "sg:phone":"+32 80 32 98 61",
    "sg:postcode":"4791",
    "sg:province":"Li\u00e8ge",
    "wof:name":"Brever M.",
    "wof:placetype":"venue"
},
  "geometry": {"coordinates":[6.0771698952,50.2173118591],"type":"Point"}
}