{
  "type": "Feature",
  "properties": {
    "addr:full":"Overleistraat 104 Harelbeke (groot) West-Vlaanderen 8530",
    "addr:housenumber":"104",
    "addr:postcode":"8530",
    "addr:street":"Overleistraat;Groot West-Vlaanderen",
    "iso:country":"BE",
    "sg:address":"Overleistraat 104",
    "sg:city":"Harelbeke (groot)",
    "sg:orig_category":"Kapsalons",
    "sg:phone":"+32 56 72 44 27",
    "sg:postcode":"8530",
    "sg:province":"West-Vlaanderen",
    "wof:name":"Catherine Hairstyling",
    "wof:placetype":"venue"
},
  "geometry": {"coordinates":[3.3051159382,50.8606147766],"type":"Point"}
}