{
  "type": "Feature",
  "properties": {
    "addr:full":"Rue Grande 37 Dinant Namur 5500",
    "addr:housenumber":"37",
    "addr:postcode":"5500",
    "addr:street":"Rue Grande",
    "iso:country":"BE",
    "sg:address":"Rue Grande 37",
    "sg:city":"Dinant",
    "sg:orig_category":"Kampeerterreinen",
    "sg:phone":"+32 82 22 28 70",
    "sg:postcode":"5500",
    "sg:province":"Namur",
    "wof:name":"Centre D\u00c9v\u00c8l. Touristique",
    "wof:placetype":"venue"
},
  "geometry": {"coordinates":[4.9153428078,50.2570304871],"type":"Point"}
}