{
  "type": "Feature",
  "properties": {
    "addr:full":"Rue Lens 2 Bruxelles (ixelles) Bruxelles-Capitale 1050",
    "addr:housenumber":"2",
    "addr:postcode":"1050",
    "addr:street":"Rue Lens",
    "iso:country":"BE",
    "sg:address":"Rue Lens 2",
    "sg:city":"Bruxelles (ixelles)",
    "sg:classifiers":[
        {
            "category":"Bars & Pubs",
            "type":"Food & Drink"
        }
    ],
    "sg:phone":"+32 2 647 28 01",
    "sg:postcode":"1050",
    "sg:province":"Bruxelles-Capitale",
    "sg:tags":[
        "tavern"
    ],
    "wof:name":"Victoria",
    "wof:placetype":"venue"
},
  "geometry": {"coordinates":[4.3651108742,50.8275222778],"type":"Point"}
}