{
  "type": "Feature",
  "properties": {
    "iso:country":"BE",
    "sg:address":"Noerether Strasse 156a",
    "sg:city":"Eupen",
    "sg:classifiers":[
        {
            "category":"Health Services",
            "subcategory":"Health Practitioner",
            "type":"Services"
        }
    ],
    "sg:phone":"+32 87 55 34 23",
    "sg:postcode":"4700",
    "sg:province":"Li\u00e8ge",
    "sg:tags":[
        "physiotherapist"
    ],
    "wof:name":"Hick C",
    "wof:placetype":"venue"
},
  "geometry": {"coordinates":[6.023018837,50.6409568787],"type":"Point"}
}