{
  "type": "Feature",
  "properties": {
    "addr:full":"Rue Rogier 3 Charleroi Hainaut 6040",
    "addr:housenumber":"3",
    "addr:postcode":"6040",
    "addr:street":"Rue Rogier;Hainaut",
    "iso:country":"BE",
    "sg:address":"Rue Rogier 3",
    "sg:city":"Charleroi",
    "sg:orig_category":"Traitements param\u00e9dicaux",
    "sg:phone":"+32 71 35 73 44",
    "sg:postcode":"6040",
    "sg:province":"Hainaut",
    "wof:name":"A. Moreau",
    "wof:placetype":"venue"
},
  "geometry": {"coordinates":[4.4344577789,50.420375824],"type":"Point"}
}