{
  "type": "Feature",
  "properties": {
    "iso:country":"BE",
    "sg:address":"Bollestraat 55",
    "sg:city":"Merchtem",
    "sg:orig_category":"Rundveehouders",
    "sg:phone":"+32 2 460 28 73",
    "sg:postcode":"1785",
    "sg:province":"Vlaams-Brabant",
    "wof:name":"Frank De Cock",
    "wof:placetype":"venue"
},
  "geometry": {"coordinates":[4.268884182,50.9443778992],"type":"Point"}
}