{
  "type": "Feature",
  "properties": {
    "iso:country":"BE",
    "sg:address":"Rue Montoyer 28",
    "sg:city":"Bruxelles",
    "sg:classifiers":[
        {
            "category":"Professional",
            "subcategory":"Lawyer & Legal Services",
            "type":"Services"
        }
    ],
    "sg:phone":"+32 2 234 67 10",
    "sg:postcode":"1000",
    "sg:province":"Bruxelles-Capitale",
    "wof:name":"Brault Fran\u00e7ois",
    "wof:placetype":"venue"
},
  "geometry": {"coordinates":[4.3703699112,50.8412742615],"type":"Point"}
}