{
  "type": "Feature",
  "properties": {
    "iso:country":"BE",
    "sg:address":"Europastraat 18",
    "sg:city":"Boom",
    "sg:classifiers":[
        {
            "category":"Personal",
            "subcategory":"Beauty Salon",
            "type":"Services"
        }
    ],
    "sg:phone":"+32 3 844 60 02",
    "sg:postcode":"2850",
    "sg:province":"Antwerpen",
    "sg:tags":[
        "de",
        "coiffure"
    ],
    "wof:name":"Coiffure Wendysign",
    "wof:placetype":"venue"
},
  "geometry": {"coordinates":[4.3771100044,51.1000747681],"type":"Point"}
}