{
  "type": "Feature",
  "properties": {
    "addr:full":"Langemunt 48 Nevele Oost-Vlaanderen 9850",
    "addr:housenumber":"48",
    "addr:postcode":"9850",
    "addr:street":"Langemunt",
    "iso:country":"BE",
    "sg:address":"Langemunt 48",
    "sg:city":"Nevele",
    "sg:orig_category":"Kapsalons",
    "sg:phone":"+32 9 371 54 16",
    "sg:postcode":"9850",
    "sg:province":"Oost-Vlaanderen",
    "wof:name":"Coiffure Helene",
    "wof:placetype":"venue"
},
  "geometry": {"coordinates":[3.5538799763,51.0309295654],"type":"Point"}
}