{
  "type": "Feature",
  "properties": {
    "addr:full":"Rue Fr\u00e8res Bi\u00e9va 174 Namur (vedrin - Daussoulx) Namur 5020",
    "addr:housenumber":"174",
    "addr:postcode":"5020",
    "addr:street":"Rue Fre\u0300Res Bie\u0301Va",
    "iso:country":"BE",
    "sg:address":"Rue Fr\u00e8res Bi\u00e9va 174",
    "sg:city":"Namur (vedrin - Daussoulx)",
    "sg:classifiers":[
        {
            "category":"Real Estate",
            "subcategory":"Real Estate Services",
            "type":"Services"
        }
    ],
    "sg:phone":"+32 81 20 11 99",
    "sg:postcode":"5020",
    "sg:province":"Namur",
    "wof:name":"Roland M",
    "wof:placetype":"venue"
},
  "geometry": {"coordinates":[4.87352705,50.4822540283],"type":"Point"}
}