{
  "type": "Feature",
  "properties": {
    "addr:full":"Avenue Des Chrysanth\u00e8mes 9 Rhode-saint-gen\u00e8se Vlaams-Brabant 1640",
    "addr:housenumber":"9",
    "addr:postcode":"1640",
    "addr:street":"Avenue Des Chrysanthe\u0300Mes",
    "iso:country":"BE",
    "sg:address":"Avenue Des Chrysanth\u00e8mes 9",
    "sg:city":"Rhode-saint-gen\u00e8se",
    "sg:classifiers":[
        {
            "category":"Professional",
            "subcategory":"Management & Consulting",
            "type":"Services"
        }
    ],
    "sg:phone":"+32 2 380 83 34",
    "sg:postcode":"1640",
    "sg:province":"Vlaams-Brabant",
    "sg:tags":[
        "consultant"
    ],
    "wof:name":"G\u00e9n\u00e9ral Management Sprl",
    "wof:placetype":"venue"
},
  "geometry": {"coordinates":[4.3747792244,50.7484016418],"type":"Point"}
}