{
  "type": "Feature",
  "properties": {
    "addr:full":"112 Rue De Marche 6600 Bastogne 112",
    "addr:housenumber":"112",
    "addr:postcode":"6600;112",
    "addr:street":"Rue De Marche",
    "iso:country":"BE",
    "sg:address":"112",
    "sg:city":"Rue De Marche 6600 Bastogne",
    "sg:classifiers":[
        {
            "category":"Travel",
            "subcategory":"Hotels & Motels",
            "type":"Entertainment"
        }
    ],
    "sg:phone":"+32 61 21 70 84",
    "sg:postcode":"112",
    "sg:tags":[
        "hotels",
        "business",
        "restaurant"
    ],
    "wof:name":"Marer Sa",
    "wof:placetype":"venue"
},
  "geometry": {"coordinates":[5.6969451904,50.0022964478],"type":"Point"}
}