{
  "type": "Feature",
  "properties": {
    "addr:full":"Rue De Lodelinsart 15 Charleroi (jumet) Hainaut 6040",
    "addr:housenumber":"15",
    "addr:postcode":"6040",
    "addr:street":"Rue De Lodelinsart",
    "iso:country":"BE",
    "sg:address":"Rue De Lodelinsart 15",
    "sg:city":"Charleroi (jumet)",
    "sg:classifiers":[
        {
            "category":"Retail",
            "subcategory":"Auto Repair",
            "type":"Services"
        }
    ],
    "sg:phone":"+32 71 35 09 25",
    "sg:postcode":"6040",
    "sg:province":"Hainaut",
    "sg:tags":[
        "garage"
    ],
    "wof:name":"Noerens",
    "wof:placetype":"venue"
},
  "geometry": {"coordinates":[4.4442000389,50.4396781921],"type":"Point"}
}