{
  "type": "Feature",
  "properties": {
    "addr:full":"Kouterstraat 146 Overijse Vlaams-Brabant 3090",
    "addr:housenumber":"146",
    "addr:postcode":"3090",
    "addr:street":"Kouterstraat",
    "iso:country":"BE",
    "sg:address":"Kouterstraat 146",
    "sg:city":"Overijse",
    "sg:orig_category":"Sportclubs",
    "sg:phone":"+32 2 687 43 86",
    "sg:postcode":"3090",
    "sg:province":"Vlaams-Brabant",
    "wof:name":"T.c. Panorama",
    "wof:placetype":"venue"
},
  "geometry": {"coordinates":[4.5507731438,50.7804527283],"type":"Point"}
}