{
  "type": "Feature",
  "properties": {
    "iso:country":"BE",
    "sg:address":"Rue Roberts-jones 77",
    "sg:city":"Bruxelles (uccle)",
    "sg:classifiers":[
        {
            "category":"Government",
            "subcategory":"Embassy",
            "type":"Public Place"
        }
    ],
    "sg:phone":"+32 2 343 00 20",
    "sg:postcode":"1180",
    "sg:province":"Bruxelles-Capitale",
    "sg:tags":[
        "consulate"
    ],
    "wof:name":"Cuba",
    "wof:placetype":"venue"
},
  "geometry": {"coordinates":[4.3524651527,50.806224823],"type":"Point"}
}