{
  "type": "Feature",
  "properties": {
    "addr:full":"Koeisteerthofdreef 12 Mortsel Antwerpen 2640",
    "addr:housenumber":"12",
    "addr:postcode":"2640",
    "addr:street":"Koeisteerthofdreef",
    "iso:country":"BE",
    "sg:address":"Koeisteerthofdreef 12",
    "sg:city":"Mortsel",
    "sg:orig_category":"M\u00e9decins and sp\u00e9cialistes",
    "sg:phone":"+32 3 455 09 87",
    "sg:postcode":"2640",
    "sg:province":"Antwerpen",
    "wof:name":"Michel Tersago",
    "wof:placetype":"venue"
},
  "geometry": {"coordinates":[4.4732217789,51.1691665649],"type":"Point"}
}