{
  "type": "Feature",
  "properties": {
    "iso:country":"BE",
    "sg:address":"Wilderstraat 52",
    "sg:city":"Ninove (appelterre-eichem)",
    "sg:orig_category":"Electric transformers, rectifiers, converters",
    "sg:phone":"+32 54 30 04 42",
    "sg:postcode":"9400",
    "sg:province":"Oost-Vlaanderen",
    "wof:name":"Mascot Benelux",
    "wof:placetype":"venue"
},
  "geometry": {"coordinates":[4.0232000351,50.8349113464],"type":"Point"}
}