{
  "type": "Feature",
  "properties": {
    "iso:country":"BE",
    "sg:address":"Avenue Mozart 43",
    "sg:city":"Bruxelles (forest)",
    "sg:classifiers":[
        {
            "category":"Food & Beverages",
            "subcategory":"Groceries & Convenience Stores",
            "type":"Retail Goods"
        }
    ],
    "sg:phone":"+32 2 345 51 22",
    "sg:postcode":"1190",
    "sg:province":"Bruxelles-Capitale",
    "sg:tags":[
        "grocer"
    ],
    "wof:name":"Devaux",
    "wof:placetype":"venue"
},
  "geometry": {"coordinates":[4.3354430199,50.8116645813],"type":"Point"}
}