{
  "type": "Feature",
  "properties": {
    "addr:full":"Gillebroek 8 Borgloon Limburg 3840",
    "addr:housenumber":"8",
    "addr:postcode":"3840",
    "addr:street":"Gillebroek",
    "iso:country":"BE",
    "sg:address":"Gillebroek 8",
    "sg:city":"Borgloon",
    "sg:classifiers":[
        {
            "category":"Utilities",
            "subcategory":"Water",
            "type":"Services"
        }
    ],
    "sg:phone":"+32 12 67 23 70",
    "sg:postcode":"3840",
    "sg:province":"Limburg",
    "sg:tags":[
        "purification"
    ],
    "wof:name":"I.e.p.c",
    "wof:placetype":"venue"
},
  "geometry": {"coordinates":[5.3441700935,50.8012466431],"type":"Point"}
}