{
  "type": "Feature",
  "properties": {
    "addr:full":"Rue De La Fronti\u00c8re 76 Dour Hainaut 7370",
    "addr:housenumber":"76",
    "addr:postcode":"7370",
    "addr:street":"Rue De La Frontie\u0300Re;Hainaut",
    "iso:country":"BE",
    "sg:address":"Rue De La Fronti\u00c8re 76",
    "sg:city":"Dour",
    "sg:orig_category":"Kapsalons",
    "sg:phone":"+32 65 65 40 82",
    "sg:postcode":"7370",
    "sg:province":"Hainaut",
    "wof:name":"Yves Delattre",
    "wof:placetype":"venue"
},
  "geometry": {"coordinates":[3.8079180717,50.3716773987],"type":"Point"}
}