{
  "type": "Feature",
  "properties": {
    "iso:country":"BE",
    "sg:address":"Hoogstraat 14",
    "sg:city":"Gingelom (vorsen)",
    "sg:classifiers":[
        {
            "category":"Insurance",
            "subcategory":"Insurance Agent",
            "type":"Services"
        }
    ],
    "sg:phone":"+32 11 88 57 00",
    "sg:postcode":"3890",
    "sg:province":"Limburg",
    "sg:tags":[
        "broker"
    ],
    "wof:name":"Alfa Consult",
    "wof:placetype":"venue"
},
  "geometry": {"coordinates":[5.1678757668,50.7032470703],"type":"Point"}
}