{
  "type": "Feature",
  "properties": {
    "addr:full":"Pont D'amercoeur 77 Li\u00e8ge 1 (li\u00e8ge 2) Li\u00e8ge 4020",
    "addr:housenumber":"77;1;2",
    "addr:postcode":"4020",
    "addr:street":"Pont D'Amercoeur",
    "iso:country":"BE",
    "sg:address":"Pont D'amercoeur 77",
    "sg:city":"Li\u00e8ge 1 (li\u00e8ge 2)",
    "sg:classifiers":[
        {
            "category":"Retail",
            "subcategory":"Repair Shop",
            "type":"Services"
        }
    ],
    "sg:phone":"+32 4 343 06 13",
    "sg:postcode":"4020",
    "sg:province":"Li\u00e8ge",
    "sg:tags":[
        "-",
        "mainten",
        "watch",
        "clock"
    ],
    "wof:name":"Lekeu & Fils Sprl",
    "wof:placetype":"venue"
},
  "geometry": {"coordinates":[5.5907268524,50.6358909607],"type":"Point"}
}