{
  "type": "Feature",
  "properties": {
    "iso:country":"BE",
    "sg:address":"Tervuursesteenweg 147",
    "sg:city":"Mechelen",
    "sg:orig_category":"Antiquit\u00e9s",
    "sg:phone":"+32 15 43 01 92",
    "sg:postcode":"2800",
    "sg:province":"Antwerpen",
    "wof:name":"Wilfried Goossens",
    "wof:placetype":"venue"
},
  "geometry": {"coordinates":[4.4844532013,51.0105361938],"type":"Point"}
}