{
  "type": "Feature",
  "properties": {
    "iso:country":"BE",
    "sg:address":"Willem Elschotstraat 5",
    "sg:city":"Vilvoorde",
    "sg:orig_category":"Transports routiers de marchandises",
    "sg:phone":"+32 2 253 57 28",
    "sg:postcode":"1800",
    "sg:province":"Vlaams-Brabant",
    "wof:name":"Deluxe International",
    "wof:placetype":"venue"
},
  "geometry": {"coordinates":[4.427341938,50.9393234253],"type":"Point"}
}