{
  "type": "Feature",
  "properties": {
    "addr:full":"Koning Ridderdijk 366 Middelkerke West-Vlaanderen 8434",
    "addr:housenumber":"366",
    "addr:postcode":"8434",
    "addr:street":"Koning Ridderdijk",
    "iso:country":"BE",
    "sg:address":"Koning Ridderdijk 366",
    "sg:city":"Middelkerke",
    "sg:orig_category":"Watersport-, Sport- and Kampeerbenodigdheden Verhuur",
    "sg:phone":"+32 59 30 09 30",
    "sg:postcode":"8434",
    "sg:province":"West-Vlaanderen",
    "wof:name":"Huis Anita",
    "wof:placetype":"venue"
},
  "geometry": {"coordinates":[2.7569050789,51.1488685608],"type":"Point"}
}