{
  "type": "Feature",
  "properties": {
    "iso:country":"BE",
    "sg:address":"Golflaan 47d",
    "sg:city":"Sint-martens-latem",
    "sg:classifiers":[
        {
            "category":"Food & Beverages",
            "subcategory":"Fruits & Vegetables",
            "type":"Retail Goods"
        }
    ],
    "sg:phone":"+32 9 282 98 47",
    "sg:postcode":"9830",
    "sg:province":"Oost-Vlaanderen",
    "sg:tags":[
        "-"
    ],
    "wof:name":"Sterfruit Bvba",
    "wof:placetype":"venue"
},
  "geometry": {"coordinates":[3.6312360764,51.0113525391],"type":"Point"}
}