{
  "type": "Feature",
  "properties": {
    "iso:country":"BE",
    "sg:address":"Zijbaan 6",
    "sg:city":"Dendermonde (schoonaarde)",
    "sg:classifiers":[
        {
            "category":"Communications",
            "subcategory":"Television Station",
            "type":"Services"
        }
    ],
    "sg:phone":"+32 52 42 25 74",
    "sg:postcode":"9200",
    "sg:province":"Oost-Vlaanderen",
    "sg:tags":[
        "report",
        "video"
    ],
    "wof:name":"De Nul J",
    "wof:placetype":"venue"
},
  "geometry": {"coordinates":[4.0163660049,51.0037651062],"type":"Point"}
}