{
  "type": "Feature",
  "properties": {
    "iso:country":"BE",
    "sg:address":"En Roua 5",
    "sg:city":"Clavier",
    "sg:orig_category":"Eleveurs de bovins",
    "sg:phone":"+32 86 34 42 95",
    "sg:postcode":"4560",
    "sg:province":"Li\u00e8ge",
    "wof:name":"Jean Couchard",
    "wof:placetype":"venue"
},
  "geometry": {"coordinates":[5.3925180435,50.4010124207],"type":"Point"}
}