{
  "type": "Feature",
  "properties": {
    "addr:full":"Brielmolenstraat 83 Lokeren (eksaarde) Oost-Vlaanderen 9160",
    "addr:housenumber":"83",
    "addr:postcode":"9160",
    "addr:street":"Brielmolenstraat;Lokeren Eksaarde Oost-Vlaanderen",
    "iso:country":"BE",
    "sg:address":"Brielmolenstraat 83",
    "sg:city":"Lokeren (eksaarde)",
    "sg:classifiers":[
        {
            "category":"Wholesale",
            "subcategory":"Plants",
            "type":"Manufacturing & Wholesale Goods"
        }
    ],
    "sg:phone":"+32 9 348 36 47",
    "sg:postcode":"9160",
    "sg:province":"Oost-Vlaanderen",
    "sg:tags":[
        "whol",
        "flower",
        "-",
        "grower"
    ],
    "wof:name":"Van Rumst L",
    "wof:placetype":"venue"
},
  "geometry": {"coordinates":[3.9864850044,51.1047401428],"type":"Point"}
}