{
  "type": "Feature",
  "properties": {
    "addr:full":"Theo Verellenlaan 86 Wuustwezel Antwerpen 2990",
    "addr:housenumber":"86",
    "addr:postcode":"2990",
    "addr:street":"Theo Verellenlaan",
    "iso:country":"BE",
    "sg:address":"Theo Verellenlaan 86",
    "sg:city":"Wuustwezel",
    "sg:classifiers":[
        {
            "category":"Manufacturing",
            "subcategory":"Wood Products",
            "type":"Manufacturing & Wholesale Goods"
        }
    ],
    "sg:phone":"+32 3 663 03 34",
    "sg:postcode":"2990",
    "sg:province":"Antwerpen",
    "sg:tags":[
        "firewood"
    ],
    "wof:name":"Aernouts Bvba",
    "wof:placetype":"venue"
},
  "geometry": {"coordinates":[4.5428080559,51.3574905396],"type":"Point"}
}