{
  "type": "Feature",
  "properties": {
    "addr:full":"Stationsstraat 128 Geel Antwerpen 2440",
    "addr:housenumber":"128",
    "addr:postcode":"2440",
    "addr:street":"Stationsstraat",
    "iso:country":"BE",
    "sg:address":"Stationsstraat 128",
    "sg:city":"Geel",
    "sg:classifiers":[
        {
            "category":"Wholesale",
            "subcategory":"Plants",
            "type":"Manufacturing & Wholesale Goods"
        }
    ],
    "sg:phone":"+32 14 58 31 54",
    "sg:postcode":"2440",
    "sg:province":"Antwerpen",
    "sg:tags":[
        "decoration",
        "flower",
        "-"
    ],
    "wof:name":"De Gele Legende",
    "wof:placetype":"venue"
},
  "geometry": {"coordinates":[4.9887280464,51.1666946411],"type":"Point"}
}