{
  "type": "Feature",
  "properties": {
    "iso:country":"BE",
    "sg:address":"Rue De La Source 7",
    "sg:city":"Wavre",
    "sg:orig_category":"Librairies. Organisations and associations",
    "sg:phone":"+32 10 24 22 64",
    "sg:postcode":"1300",
    "sg:province":"Brabant Wallon",
    "wof:name":"Le Chat Pitre",
    "wof:placetype":"venue"
},
  "geometry": {"coordinates":[4.6107058525,50.7160377502],"type":"Point"}
}