{
  "type": "Feature",
  "properties": {
    "iso:country":"BE",
    "sg:address":"Chauss\u00c9e De Wavre 148",
    "sg:city":"Grez-doiceau",
    "sg:orig_category":"Quincailleries",
    "sg:phone":"+32 10 84 57 82",
    "sg:postcode":"1390",
    "sg:province":"Brabant Wallon",
    "wof:name":"Capiaux R & R",
    "wof:placetype":"venue"
},
  "geometry": {"coordinates":[4.6873898506,50.7466812134],"type":"Point"}
}