{
  "type": "Feature",
  "properties": {
    "addr:full":"Defacqzstraat 95 Sint-gillis/saint-gilles Bruxelles-Capitale 1060",
    "addr:housenumber":"95",
    "addr:postcode":"1060",
    "addr:street":"Defacqzstraat",
    "iso:country":"BE",
    "sg:address":"Defacqzstraat 95",
    "sg:city":"Sint-gillis/saint-gilles",
    "sg:orig_category":"Diverse bouwafwerking and reiniging",
    "sg:phone":"+32 2 544 01 09",
    "sg:postcode":"1060",
    "sg:province":"Bruxelles-Capitale",
    "wof:name":"Batisse",
    "wof:placetype":"venue"
},
  "geometry": {"coordinates":[4.3566889763,50.826751709],"type":"Point"}
}