{
  "type": "Feature",
  "properties": {
    "addr:full":"Meensesteenweg 122 Roeselare West-Vlaanderen 8800",
    "addr:housenumber":"122",
    "addr:postcode":"8800",
    "addr:street":"Meensesteenweg",
    "iso:country":"BE",
    "sg:address":"Meensesteenweg 122",
    "sg:city":"Roeselare",
    "sg:orig_category":"Assurances. Bureaux de poste",
    "sg:phone":"+32 51 22 64 65",
    "sg:postcode":"8800",
    "sg:province":"West-Vlaanderen",
    "wof:name":"De Post",
    "wof:placetype":"venue"
},
  "geometry": {"coordinates":[3.1213300228,50.9384498596],"type":"Point"}
}