{
  "type": "Feature",
  "properties": {
    "addr:full":"Lambroekstraat 5 Machelen (diegem) Vlaams-Brabant 1831",
    "addr:housenumber":"5",
    "addr:postcode":"1831",
    "addr:street":"Lambroekstraat",
    "iso:country":"BE",
    "sg:address":"Lambroekstraat 5",
    "sg:city":"Machelen (diegem)",
    "sg:classifiers":[
        {
            "category":"Professional",
            "subcategory":"Computer Services",
            "type":"Services"
        }
    ],
    "sg:phone":"+32 2 719 02 71",
    "sg:postcode":"1831",
    "sg:province":"Vlaams-Brabant",
    "sg:tags":[
        "-",
        "processing",
        "data",
        "software"
    ],
    "wof:name":"Scr Europe",
    "wof:placetype":"venue"
},
  "geometry": {"coordinates":[4.4486842155,50.880191803],"type":"Point"}
}