{
  "type": "Feature",
  "properties": {
    "iso:country":"BE",
    "sg:address":"Rue Royale 13",
    "sg:city":"Leuze-en-hainaut (tourpes)",
    "sg:classifiers":[
        {
            "category":"Health Services",
            "subcategory":"Health Practitioner",
            "type":"Services"
        }
    ],
    "sg:phone":"+32 476 49 55 31",
    "sg:postcode":"7904",
    "sg:province":"Hainaut",
    "sg:tags":[
        "physiotherapist"
    ],
    "wof:name":"Gu\u00e9ret Xavier",
    "wof:placetype":"venue"
},
  "geometry": {"coordinates":[3.6561350822,50.5708198547],"type":"Point"}
}