{
  "type": "Feature",
  "properties": {
    "iso:country":"BE",
    "sg:address":"Voochtstraat 7",
    "sg:city":"Mechelen",
    "sg:orig_category":"Rechtbanken",
    "sg:phone":"+32 15 28 83 64",
    "sg:postcode":"2800",
    "sg:province":"Antwerpen",
    "wof:name":"Rechtbank Van Koophandel",
    "wof:placetype":"venue"
},
  "geometry": {"coordinates":[4.486533165,51.0283851624],"type":"Point"}
}