{
  "type": "Feature",
  "properties": {
    "iso:country":"BE",
    "sg:address":"Perche \u00c0 L'oiseau 32",
    "sg:city":"Beloeil",
    "sg:orig_category":"Avocats and conseillers juridiques",
    "sg:phone":"+32 69 56 07 65",
    "sg:postcode":"7971",
    "sg:province":"Hainaut",
    "wof:name":"I. Brasseur",
    "wof:placetype":"venue"
},
  "geometry": {"coordinates":[3.6459169388,50.5286903381],"type":"Point"}
}