{
  "type": "Feature",
  "properties": {
    "iso:country":"BE",
    "sg:address":"Rue Elisa Dumonceau 17",
    "sg:city":"Herstal",
    "sg:orig_category":"Articles m\u00e9dicaux and orthop\u00e9diques. Opticiens",
    "sg:phone":"+32 4 264 07 21",
    "sg:postcode":"4040",
    "sg:province":"Li\u00e8ge",
    "wof:name":"Optique Baudinet Georges",
    "wof:placetype":"venue"
},
  "geometry": {"coordinates":[5.6303310394,50.6645278931],"type":"Point"}
}