{
  "type": "Feature",
  "properties": {
    "iso:country":"BE",
    "sg:address":"Breebijl 13",
    "sg:city":"Lierde",
    "sg:orig_category":"Eleveurs de bovins",
    "sg:phone":"+32 55 42 25 39",
    "sg:postcode":"9570",
    "sg:province":"Oost-Vlaanderen",
    "wof:name":"Roger De Nooze",
    "wof:placetype":"venue"
},
  "geometry": {"coordinates":[3.8223500252,50.7935523987],"type":"Point"}
}