{
  "type": "Feature",
  "properties": {
    "iso:country":"BE",
    "sg:address":"Durentijdlei 111",
    "sg:city":"Brasschaat",
    "sg:classifiers":[
        {
            "category":"Health Services",
            "subcategory":"Doctor",
            "type":"Services"
        }
    ],
    "sg:phone":"+32 3 633 13 14",
    "sg:postcode":"2930",
    "sg:province":"Antwerpen",
    "sg:tags":[
        "medicinephysicians",
        "surgeon"
    ],
    "wof:name":"Coucheir Rene",
    "wof:placetype":"venue"
},
  "geometry": {"coordinates":[4.5284099579,51.3230285645],"type":"Point"}
}