{
  "type": "Feature",
  "properties": {
    "addr:full":"Royestraat 23 Meeuwen-gruitrode (gruitrode) Limburg 3670",
    "addr:housenumber":"23",
    "addr:postcode":"3670",
    "addr:street":"Royestraat",
    "iso:country":"BE",
    "sg:address":"Royestraat 23",
    "sg:city":"Meeuwen-gruitrode (gruitrode)",
    "sg:classifiers":[
        {
            "category":"Health Services",
            "subcategory":"Nursing And Care Facility",
            "type":"Services"
        }
    ],
    "sg:phone":"+32 89 81 26 67",
    "sg:postcode":"3670",
    "sg:province":"Limburg",
    "sg:tags":[
        "home"
    ],
    "wof:name":"Donne-brebels",
    "wof:placetype":"venue"
},
  "geometry": {"coordinates":[5.627491951,51.1123657227],"type":"Point"}
}