{
  "type": "Feature",
  "properties": {
    "iso:country":"BE",
    "sg:address":"Beverlostraat 2",
    "sg:city":"Leopoldsburg",
    "sg:classifiers":[
        {
            "category":"Sports & Exercise",
            "subcategory":"Sports Center",
            "type":"Entertainment"
        }
    ],
    "sg:phone":"+32 11 34 33 80",
    "sg:postcode":"3970",
    "sg:province":"Limburg",
    "sg:tags":[
        "terrain",
        "hors",
        "de",
        "installation",
        "sportifs"
    ],
    "wof:name":"Milit. 't Fonteintje",
    "wof:placetype":"venue"
},
  "geometry": {"coordinates":[5.277130127,51.1038284302],"type":"Point"}
}