{
  "type": "Feature",
  "properties": {
    "iso:country":"BE",
    "sg:address":"Sint-michielsdreef 2ba",
    "sg:city":"Kraainem",
    "sg:classifiers":[
        {
            "category":"Insurance",
            "subcategory":"Insurance Agent",
            "type":"Services"
        }
    ],
    "sg:phone":"+32 2 725 65 47",
    "sg:postcode":"1950",
    "sg:province":"Vlaams-Brabant",
    "sg:tags":[
        "verzekeringsmakelaars",
        "expert"
    ],
    "wof:name":"Uni - Assur/uni-assur",
    "wof:placetype":"venue"
},
  "geometry": {"coordinates":[4.4608812332,50.8617630005],"type":"Point"}
}