{
  "type": "Feature",
  "properties": {
    "iso:country":"BE",
    "sg:address":"Rue C\u00c9sar Franck 44",
    "sg:city":"Li\u00c8ge",
    "sg:orig_category":"Advocaten and juridische adviseurs",
    "sg:phone":"+32 4 223 02 01",
    "sg:postcode":"4000",
    "sg:province":"Li\u00e8ge",
    "wof:name":"M. Teheux",
    "wof:placetype":"venue"
},
  "geometry": {"coordinates":[5.5603289604,50.6387786865],"type":"Point"}
}