{
  "type": "Feature",
  "properties": {
    "addr:full":"Rue De Monsville Quaregnon Hainaut 7390",
    "addr:postcode":"7390",
    "addr:street":"Rue De Monsville;Hainaut",
    "iso:country":"BE",
    "sg:address":"Rue De Monsville",
    "sg:city":"Quaregnon",
    "sg:orig_category":"Huisdieren and benodigdheden Royal Canin",
    "sg:phone":"+32 65 78 59 31",
    "sg:postcode":"7390",
    "sg:province":"Hainaut",
    "wof:name":"Vanderlinden-gossuin Ass.",
    "wof:placetype":"venue"
},
  "geometry": {"coordinates":[3.8663699627,50.4396629333],"type":"Point"}
}