{
  "type": "Feature",
  "properties": {
    "iso:country":"BE",
    "sg:address":"Route De Mons 87",
    "sg:city":"Quaregnon",
    "sg:orig_category":"Quincailleries. Articles non-alimentaires",
    "sg:phone":"+32 65 78 41 78",
    "sg:postcode":"7390",
    "sg:province":"Hainaut",
    "wof:name":"Stock Am\u00c9ricain",
    "wof:placetype":"venue"
},
  "geometry": {"coordinates":[3.8466238976,50.4407653809],"type":"Point"}
}