{
  "type": "Feature",
  "properties": {
    "addr:full":"Av. De La Croix Poncin 17 Braine-l'alleud Brabant Wallon 1428",
    "addr:housenumber":"17",
    "addr:postcode":"1428",
    "addr:street":"Av. De La Croix Poncin",
    "iso:country":"BE",
    "sg:address":"Av. De La Croix Poncin 17",
    "sg:city":"Braine-l'alleud",
    "sg:orig_category":"G\u00e9om\u00e8tres",
    "sg:phone":"+32 2 384 43 13",
    "sg:postcode":"1428",
    "sg:province":"Brabant Wallon",
    "wof:name":"Jacques Decraemer",
    "wof:placetype":"venue"
},
  "geometry": {"coordinates":[-2.3329610825,46.7079162598],"type":"Point"}
}