{
  "type": "Feature",
  "properties": {
    "iso:country":"BE",
    "sg:address":"Tuimelarestraat 10",
    "sg:city":"Moorslede",
    "sg:orig_category":"Installatie van houten of kunststof schrijnwerk",
    "sg:phone":"+32 51 77 93 97",
    "sg:postcode":"8890",
    "sg:province":"West-Vlaanderen",
    "wof:name":"Noel Misplon",
    "wof:placetype":"venue"
},
  "geometry": {"coordinates":[3.0802819729,50.8890914917],"type":"Point"}
}