{
  "type": "Feature",
  "properties": {
    "addr:full":"Hoogstraat 315 Duffel Antwerpen 2570",
    "addr:housenumber":"315",
    "addr:postcode":"2570",
    "addr:street":"Hoogstraat",
    "iso:country":"BE",
    "sg:address":"Hoogstraat 315",
    "sg:city":"Duffel",
    "sg:orig_category":"Stations-service and carburants. V\u00e9hicules automobiles. Entretien and r\u00e9parations de voitures",
    "sg:phone":"+32 15 31 15 68",
    "sg:postcode":"2570",
    "sg:province":"Antwerpen",
    "wof:name":"Garage Verlinden",
    "wof:placetype":"venue"
},
  "geometry": {"coordinates":[4.5391411781,51.0914878845],"type":"Point"}
}