{
  "type": "Feature",
  "properties": {
    "addr:full":"Kaperberg 50 Eupen/eupen Li\u00e8ge 4700",
    "addr:housenumber":"50",
    "addr:postcode":"4700",
    "addr:street":"Kaperberg",
    "iso:country":"BE",
    "sg:address":"Kaperberg 50",
    "sg:city":"Eupen/eupen",
    "sg:orig_category":"Avocats and conseillers juridiques",
    "sg:phone":"+32 87 55 56 56",
    "sg:postcode":"4700",
    "sg:province":"Li\u00e8ge",
    "wof:name":"M. Orban",
    "wof:placetype":"venue"
},
  "geometry": {"coordinates":[6.0422120094,50.6298522949],"type":"Point"}
}