{
  "type": "Feature",
  "properties": {
    "iso:country":"BE",
    "sg:address":"Sint-hendriksvoorplein 34",
    "sg:city":"Sint-lambrechts-woluwe/woluwe-saint-lambert",
    "sg:orig_category":"Slagers",
    "sg:phone":"+32 2 734 15 05",
    "sg:postcode":"1200",
    "sg:province":"Bruxelles-Capitale",
    "wof:name":"Beenhouwerij Ronny",
    "wof:placetype":"venue"
},
  "geometry": {"coordinates":[4.4092550278,50.8421401978],"type":"Point"}
}