{
  "type": "Feature",
  "properties": {
    "addr:full":"De Smet-de Naeyerlaan 30 Wenduine West-Vlaanderen 8420",
    "addr:housenumber":"30",
    "addr:postcode":"8420",
    "addr:street":"Naeyerlaan",
    "iso:country":"BE",
    "sg:address":"De Smet-de Naeyerlaan 30",
    "sg:city":"Wenduine",
    "sg:orig_category":"Herstelling aan huis van huishoudartikelen",
    "sg:phone":"+32 50 41 41 72",
    "sg:postcode":"8420",
    "sg:province":"West-Vlaanderen",
    "wof:name":"Bevi",
    "wof:placetype":"venue"
},
  "geometry": {"coordinates":[3.0851008892,51.3029556274],"type":"Point"}
}