{
  "type": "Feature",
  "properties": {
    "iso:country":"BE",
    "sg:address":"Rue Fond-des-vaux 116",
    "sg:city":"Libin",
    "sg:orig_category":"Installation \u00e9lectrique r\u00e9sidentielle",
    "sg:phone":"+32 61 65 56 28",
    "sg:postcode":"6890",
    "sg:province":"Luxembourg",
    "wof:name":"Gerard Nicolay",
    "wof:placetype":"venue"
},
  "geometry": {"coordinates":[5.2570419312,49.9768104553],"type":"Point"}
}