{
  "type": "Feature",
  "properties": {
    "addr:full":"Liersebaan 166 Zandhoven Antwerpen 2240",
    "addr:housenumber":"166",
    "addr:postcode":"2240",
    "addr:street":"Liersebaan",
    "iso:country":"BE",
    "sg:address":"Liersebaan 166",
    "sg:city":"Zandhoven",
    "sg:classifiers":[
        {
            "category":"Building & Trades",
            "subcategory":"Plumbing",
            "type":"Services"
        }
    ],
    "sg:phone":"+32 3 484 49 68",
    "sg:postcode":"2240",
    "sg:province":"Antwerpen",
    "sg:tags":[
        "pipe",
        "drain",
        "unblocking"
    ],
    "wof:name":"Algemene Ontstoppingsdienst Van Meerbergen",
    "wof:placetype":"venue"
},
  "geometry": {"coordinates":[4.6519298553,51.2068099976],"type":"Point"}
}