{
  "type": "Feature",
  "properties": {
    "iso:country":"BE",
    "sg:address":"Place Marie Jos\u00c9 4",
    "sg:city":"Elsene/ixelles",
    "sg:orig_category":"Brood, gebak and snoepgoed",
    "sg:phone":"+32 2 649 42 73",
    "sg:postcode":"1050",
    "sg:province":"Bruxelles-Capitale",
    "wof:name":"La Provencale",
    "wof:placetype":"venue"
},
  "geometry": {"coordinates":[4.3874821663,50.8064460754],"type":"Point"}
}