{
  "type": "Feature",
  "properties": {
    "iso:country":"BE",
    "sg:address":"Kosterstraat 1",
    "sg:city":"Kluisbergen",
    "sg:orig_category":"Eleveurs and marchands de porcs. Eleveurs de bovins. Eleveurs de volaille",
    "sg:phone":"+32 55 38 83 06",
    "sg:postcode":"9690",
    "sg:province":"Oost-Vlaanderen",
    "wof:name":"Omer Roman",
    "wof:placetype":"venue"
},
  "geometry": {"coordinates":[3.5675110817,50.7833862305],"type":"Point"}
}