{
  "type": "Feature",
  "properties": {
    "iso:country":"BE",
    "sg:address":"Raymond Blyckaertsplein 3",
    "sg:city":"Elsene/ixelles",
    "sg:orig_category":"Brood, gebak and snoepgoed",
    "sg:phone":"+32 2 648 66 06",
    "sg:postcode":"1050",
    "sg:province":"Bruxelles-Capitale",
    "wof:name":"P\u00c2tisserie Walter",
    "wof:placetype":"venue"
},
  "geometry": {"coordinates":[4.3741431236,50.8330078125],"type":"Point"}
}