{
  "type": "Feature",
  "properties": {
    "addr:full":"La Grange 4 Ferrieres Li\u00e8ge 4190",
    "addr:housenumber":"4",
    "addr:postcode":"4190",
    "addr:street":"Ferrieres Lie\u0300Ge",
    "iso:country":"BE",
    "sg:address":"La Grange 4",
    "sg:city":"Ferrieres",
    "sg:classifiers":[
        {
            "category":"Personal",
            "subcategory":"Beauty Salon",
            "type":"Services"
        }
    ],
    "sg:phone":"+32 4 369 20 47",
    "sg:postcode":"4190",
    "sg:province":"Li\u00e8ge",
    "sg:tags":[
        "de",
        "coiffure"
    ],
    "wof:name":"Bernadette Corbesier",
    "wof:placetype":"venue"
},
  "geometry": {"coordinates":[5.6112728119,50.4475479126],"type":"Point"}
}