{
  "type": "Feature",
  "properties": {
    "iso:country":"BE",
    "sg:address":"Middelweg 27",
    "sg:city":"Knesselare",
    "sg:orig_category":"Glaszetten and glaswerk",
    "sg:phone":"+32 9 375 08 39",
    "sg:postcode":"9910",
    "sg:province":"Oost-Vlaanderen",
    "wof:name":"Kurt Mouton",
    "wof:placetype":"venue"
},
  "geometry": {"coordinates":[3.4803431034,51.1268501282],"type":"Point"}
}