{
  "type": "Feature",
  "properties": {
    "addr:full":"Rue De La P\u00eacherie 114 Bruxelles (uccle) Bruxelles-Capitale 1180",
    "addr:housenumber":"114",
    "addr:postcode":"1180",
    "addr:street":"Rue De La Pe\u0302Cherie",
    "iso:country":"BE",
    "sg:address":"Rue De La P\u00eacherie 114",
    "sg:city":"Bruxelles (uccle)",
    "sg:classifiers":[
        {
            "category":"Building & Trades",
            "subcategory":"Landscaping Services",
            "type":"Services"
        }
    ],
    "sg:phone":"+32 478 70 54 00",
    "sg:postcode":"1180",
    "sg:province":"Bruxelles-Capitale",
    "sg:tags":[
        "architect",
        "landscape"
    ],
    "wof:name":"Poncelet C",
    "wof:placetype":"venue"
},
  "geometry": {"coordinates":[4.3579659462,50.7931594849],"type":"Point"}
}