{
  "type": "Feature",
  "properties": {
    "iso:country":"BE",
    "sg:address":"Lengeler 36",
    "sg:city":"Burg-reuland",
    "sg:classifiers":[
        {
            "category":"Personal",
            "subcategory":"Beauty Salon",
            "type":"Services"
        }
    ],
    "sg:phone":"+32 80 32 95 01",
    "sg:postcode":"4790",
    "sg:province":"Li\u00e8ge",
    "sg:tags":[
        "lady",
        "-",
        "hairdressing"
    ],
    "wof:name":"Hoffmann M",
    "wof:placetype":"venue"
},
  "geometry": {"coordinates":[6.1315770149,50.1943702698],"type":"Point"}
}