{
  "type": "Feature",
  "properties": {
    "addr:full":"Quai Godefroid-kurth 30 Li\u00e8ge 1 (li\u00e8ge 2) Li\u00e8ge 4020",
    "addr:housenumber":"30;1;2",
    "addr:postcode":"4020",
    "addr:street":"Quai Godefroid-Kurth",
    "iso:country":"BE",
    "sg:address":"Quai Godefroid-kurth 30",
    "sg:city":"Li\u00e8ge 1 (li\u00e8ge 2)",
    "sg:classifiers":[
        {
            "category":"Banks & Credit Unions",
            "subcategory":"Investment Brokerage",
            "type":"Services"
        }
    ],
    "sg:phone":"+32 4 341 00 31",
    "sg:postcode":"4020",
    "sg:province":"Li\u00e8ge",
    "wof:name":"Foyer Ottaviani & Associes Sa (le) Sa",
    "wof:placetype":"venue"
},
  "geometry": {"coordinates":[5.5901708603,50.6463165283],"type":"Point"}
}