{
  "type": "Feature",
  "properties": {
    "iso:country":"BE",
    "sg:address":"Avenue Albert Ier 28",
    "sg:city":"Charleroi",
    "sg:orig_category":"Bagage and lederwaren",
    "sg:phone":"+32 71 43 66 37",
    "sg:postcode":"6032",
    "sg:province":"Hainaut",
    "wof:name":"Roger Dagnely",
    "wof:placetype":"venue"
},
  "geometry": {"coordinates":[4.425755024,50.3980751038],"type":"Point"}
}