{
  "type": "Feature",
  "properties": {
    "addr:full":"Binnensteenweg 190 Boechout Antwerpen 2530",
    "addr:housenumber":"190",
    "addr:postcode":"2530",
    "addr:street":"Binnensteenweg",
    "iso:country":"BE",
    "sg:address":"Binnensteenweg 190",
    "sg:city":"Boechout",
    "sg:orig_category":"Assistances juridiques",
    "sg:phone":"+32 3 455 17 70",
    "sg:postcode":"2530",
    "sg:province":"Antwerpen",
    "wof:name":"Jordaens",
    "wof:placetype":"venue"
},
  "geometry": {"coordinates":[4.4917488098,51.1665420532],"type":"Point"}
}