{
  "type": "Feature",
  "properties": {
    "iso:country":"BE",
    "sg:address":"Heidestraat 149",
    "sg:city":"Diepenbeek",
    "sg:orig_category":"Kapsalons",
    "sg:phone":"+32 11 32 38 21",
    "sg:postcode":"3590",
    "sg:province":"Limburg",
    "wof:name":"Coiffure Paul",
    "wof:placetype":"venue"
},
  "geometry": {"coordinates":[5.4201397896,50.9327697754],"type":"Point"}
}