{
  "type": "Feature",
  "properties": {
    "iso:country":"BE",
    "sg:address":"Nederstraat 30",
    "sg:city":"Oudenaarde",
    "sg:classifiers":[
        {
            "category":"Shopping",
            "subcategory":"Clothing, Apparel, & Fashions",
            "type":"Retail Goods"
        }
    ],
    "sg:phone":"+32 55 23 93 06",
    "sg:postcode":"9700",
    "sg:province":"Oost-Vlaanderen",
    "sg:tags":[
        "lady",
        "clothing",
        "-"
    ],
    "wof:name":"Sarah Pacini",
    "wof:placetype":"venue"
},
  "geometry": {"coordinates":[3.6030840874,50.8447608948],"type":"Point"}
}