{
  "type": "Feature",
  "properties": {
    "iso:country":"BE",
    "sg:address":"Veldenbergstraat 73b",
    "sg:city":"Merksplas",
    "sg:classifiers":[
        {
            "category":"Shopping",
            "subcategory":"Discount & Variety Stores",
            "type":"Retail Goods"
        }
    ],
    "sg:phone":"+32 14 63 51 28",
    "sg:postcode":"2330",
    "sg:province":"Antwerpen",
    "sg:tags":[
        "warehouse",
        "-",
        "merchandise"
    ],
    "wof:name":"C & I Global Logistics Bvba",
    "wof:placetype":"venue"
},
  "geometry": {"coordinates":[4.8424520493,51.3659133911],"type":"Point"}
}