{
  "type": "Feature",
  "properties": {
    "addr:full":"Bessemstraat 99 Waregem West-Vlaanderen 8790",
    "addr:housenumber":"99",
    "addr:postcode":"8790",
    "addr:street":"Bessemstraat",
    "iso:country":"BE",
    "sg:address":"Bessemstraat 99",
    "sg:city":"Waregem",
    "sg:orig_category":"Traitements param\u00e9dicaux",
    "sg:phone":"+32 56 60 47 52",
    "sg:postcode":"8790",
    "sg:province":"West-Vlaanderen",
    "wof:name":"Ruth Dauwe",
    "wof:placetype":"venue"
},
  "geometry": {"coordinates":[3.4583950043,50.8867111206],"type":"Point"}
}