{
  "type": "Feature",
  "properties": {
    "addr:full":"Rue Des Colonies 56 Bruxelles Bruxelles-Capitale 1000",
    "addr:housenumber":"56",
    "addr:postcode":"1000",
    "addr:street":"Rue Des Colonies",
    "iso:country":"BE",
    "sg:address":"Rue Des Colonies 56",
    "sg:city":"Bruxelles",
    "sg:classifiers":[
        {
            "category":"Banks & Credit Unions",
            "subcategory":"Bank",
            "type":"Services"
        }
    ],
    "sg:postcode":"1000",
    "sg:province":"Bruxelles-Capitale",
    "wof:name":"Bank Van Roeselare Nv",
    "wof:placetype":"venue"
},
  "geometry": {"coordinates":[3.1231050491,50.9462089539],"type":"Point"}
}