{
  "type": "Feature",
  "properties": {
    "iso:country":"BE",
    "sg:address":"Rue De Fize 2",
    "sg:city":"Crisn\u00e9e",
    "sg:classifiers":[
        {
            "category":"Farming",
            "subcategory":"Livestock Farm",
            "type":"Manufacturing & Wholesale Goods"
        }
    ],
    "sg:phone":"+32 19 67 71 79",
    "sg:postcode":"4367",
    "sg:province":"Li\u00e8ge",
    "sg:tags":[
        "buyer"
    ],
    "wof:name":"Depas Sprl",
    "wof:placetype":"venue"
},
  "geometry": {"coordinates":[5.3954458237,50.7136306763],"type":"Point"}
}