{
  "type": "Feature",
  "properties": {
    "addr:full":"Kortrijksesteenweg 682 Gent Oost-Vlaanderen 9000",
    "addr:housenumber":"682",
    "addr:postcode":"9000",
    "addr:street":"Kortrijksesteenweg;Oost-Vlaanderen",
    "iso:country":"BE",
    "sg:address":"Kortrijksesteenweg 682",
    "sg:city":"Gent",
    "sg:classifiers":[
        {
            "category":"Professional",
            "subcategory":"Lawyer & Legal Services",
            "type":"Services"
        }
    ],
    "sg:phone":"+32 9 221 96 29",
    "sg:postcode":"9000",
    "sg:province":"Oost-Vlaanderen",
    "wof:name":"Hofmans Frans",
    "wof:placetype":"venue"
},
  "geometry": {"coordinates":[3.7123320103,51.0297470093],"type":"Point"}
}