{
  "type": "Feature",
  "properties": {
    "addr:full":"Bosdel 26b8-9 Genk Limburg 3600",
    "addr:housenumber":"26b8-9",
    "addr:postcode":"3600",
    "addr:street":"Bosdel",
    "iso:country":"BE",
    "sg:address":"Bosdel 26b8-9",
    "sg:city":"Genk",
    "sg:orig_category":"Mat\u00e9riaux de construction Gr",
    "sg:phone":"+32 89 35 69 54",
    "sg:postcode":"3600",
    "sg:province":"Limburg",
    "wof:name":"Tegelcenter No One",
    "wof:placetype":"venue"
},
  "geometry": {"coordinates":[5.4878950119,50.9496154785],"type":"Point"}
}