{
  "type": "Feature",
  "properties": {
    "addr:full":"Chauss\u00c9e De Haecht 1687 Brussel/bruxelles Bruxelles-Capitale 1130",
    "addr:postcode":"1687;/ bruxelles;1130",
    "addr:street":"Chausse\u0301E De Haecht",
    "iso:country":"BE",
    "sg:address":"Chauss\u00c9e De Haecht 1687",
    "sg:city":"Brussel/bruxelles",
    "sg:orig_category":"RESTAURANTS: CAF\u00c9S",
    "sg:phone":"+32 2 245 53 66",
    "sg:postcode":"1130",
    "sg:province":"Bruxelles-Capitale",
    "wof:name":"Normandie",
    "wof:placetype":"venue"
},
  "geometry": {"coordinates":[4.4244141579,50.8884391785],"type":"Point"}
}