{
  "type": "Feature",
  "properties": {
    "addr:full":"Dorpsstraat 60 Geetbets Vlaams-Brabant 3450",
    "addr:housenumber":"60",
    "addr:postcode":"3450",
    "addr:street":"Dorpsstraat",
    "iso:country":"BE",
    "sg:address":"Dorpsstraat 60",
    "sg:city":"Geetbets",
    "sg:orig_category":"Warenhuizen",
    "sg:phone":"+32 11 58 72 47",
    "sg:postcode":"3450",
    "sg:province":"Vlaams-Brabant",
    "wof:name":"Maria Croes",
    "wof:placetype":"venue"
},
  "geometry": {"coordinates":[5.1156330109,50.8895645142],"type":"Point"}
}