{
  "type": "Feature",
  "properties": {
    "addr:full":"Langeveld 180 Holsbeek Vlaams-Brabant 3220",
    "addr:housenumber":"180",
    "addr:postcode":"3220",
    "addr:street":"Langeveld",
    "iso:country":"BE",
    "sg:address":"Langeveld 180",
    "sg:city":"Holsbeek",
    "sg:orig_category":"Boekhouders",
    "sg:phone":"+32 16 44 91 53",
    "sg:postcode":"3220",
    "sg:province":"Vlaams-Brabant",
    "wof:name":"E. Spruyt",
    "wof:placetype":"venue"
},
  "geometry": {"coordinates":[4.7298579216,50.9137611389],"type":"Point"}
}