{
  "type": "Feature",
  "properties": {
    "addr:full":"Lierse Steenweg 80 Grobbendonk Antwerpen 2280",
    "addr:housenumber":"80",
    "addr:postcode":"2280",
    "addr:street":"Lierse Steenweg",
    "iso:country":"BE",
    "sg:address":"Lierse Steenweg 80",
    "sg:city":"Grobbendonk",
    "sg:orig_category":"M\u00e9decins and sp\u00e9cialistes",
    "sg:phone":"+32 14 51 12 24",
    "sg:postcode":"2280",
    "sg:province":"Antwerpen",
    "wof:name":"Gerrit Carpentier",
    "wof:placetype":"venue"
},
  "geometry": {"coordinates":[4.7214951515,51.1685752869],"type":"Point"}
}