{
  "type": "Feature",
  "properties": {
    "addr:full":"Waterstraat 30 Lille Antwerpen 2275",
    "addr:housenumber":"30",
    "addr:postcode":"2275",
    "addr:street":"Waterstraat",
    "iso:country":"BE",
    "sg:address":"Waterstraat 30",
    "sg:city":"Lille",
    "sg:orig_category":"Eleveurs and marchands de porcs",
    "sg:phone":"+32 14 55 12 58",
    "sg:postcode":"2275",
    "sg:province":"Antwerpen",
    "wof:name":"Dirk Bastiaens",
    "wof:placetype":"venue"
},
  "geometry": {"coordinates":[4.8788399696,51.2552108765],"type":"Point"}
}