{
  "type": "Feature",
  "properties": {
    "addr:full":"Lerenveld 45 Lint Antwerpen 2547",
    "addr:housenumber":"45",
    "addr:postcode":"2547",
    "addr:street":"Lerenveld",
    "iso:country":"BE",
    "sg:address":"Lerenveld 45",
    "sg:city":"Lint",
    "sg:classifiers":[
        {
            "category":"Retail",
            "subcategory":"Auto Repair",
            "type":"Services"
        }
    ],
    "sg:phone":"+32 3 488 27 89",
    "sg:postcode":"2547",
    "sg:province":"Antwerpen",
    "sg:tags":[
        "automobile",
        "-",
        "wrecking"
    ],
    "wof:name":"Jeep Design Nv",
    "wof:placetype":"venue"
},
  "geometry": {"coordinates":[4.5118751526,51.1271781921],"type":"Point"}
}