{
  "type": "Feature",
  "properties": {
    "addr:full":"Rue De Namur 3 Charleroi Hainaut 6041",
    "addr:housenumber":"3",
    "addr:postcode":"6041",
    "addr:street":"Rue De Namur;Hainaut",
    "iso:country":"BE",
    "sg:address":"Rue De Namur 3",
    "sg:city":"Charleroi",
    "sg:classifiers":[
        {
            "category":"Fast Food",
            "type":"Food & Drink"
        }
    ],
    "sg:phone":"+32 71 34 60 39",
    "sg:postcode":"6041",
    "sg:province":"Hainaut",
    "sg:tags":[
        "meeneem",
        "restaurant"
    ],
    "wof:name":"Rapido Pizza",
    "wof:placetype":"venue"
},
  "geometry": {"coordinates":[4.4406380653,50.4215431213],"type":"Point"}
}