{
  "type": "Feature",
  "properties": {
    "iso:country":"BE",
    "sg:address":"Evence Copp\u00e9elaan 21",
    "sg:city":"Genk",
    "sg:classifiers":[
        {
            "category":"Health Services",
            "subcategory":"Doctor",
            "type":"Services"
        }
    ],
    "sg:phone":"+32 89 35 95 90",
    "sg:postcode":"3600",
    "sg:province":"Limburg",
    "sg:tags":[
        "medicinephysicians",
        "surgeon"
    ],
    "wof:name":"Fran\u00e7ois B",
    "wof:placetype":"venue"
},
  "geometry": {"coordinates":[5.4983901978,50.9728660583],"type":"Point"}
}