{
  "type": "Feature",
  "properties": {
    "addr:full":"Hommelheide 12 Genk Limburg 3600",
    "addr:housenumber":"12",
    "addr:postcode":"3600",
    "addr:street":"Hommelheide",
    "iso:country":"BE",
    "sg:address":"Hommelheide 12",
    "sg:city":"Genk",
    "sg:orig_category":"Diverse persoonlijke diensten",
    "sg:phone":"+32 89 35 53 54",
    "sg:postcode":"3600",
    "sg:province":"Limburg",
    "wof:name":"Alg.belg.ceremonien",
    "wof:placetype":"venue"
},
  "geometry": {"coordinates":[5.5006918907,50.9520187378],"type":"Point"}
}