{
  "type": "Feature",
  "properties": {
    "iso:country":"BE",
    "sg:address":"Rue Du Calvaire 65",
    "sg:city":"Chimay",
    "sg:orig_category":"Loodgieterij, verwarming and sanitaire installaties",
    "sg:phone":"+32 60 21 44 18",
    "sg:postcode":"6464",
    "sg:province":"Hainaut",
    "wof:name":"Fe. Le Four",
    "wof:placetype":"venue"
},
  "geometry": {"coordinates":[4.3756861687,50.0240821838],"type":"Point"}
}