{
  "type": "Feature",
  "properties": {
    "addr:full":"Rue Large 70 Li\u00e8ge 1 (ch\u00ean\u00e9e) Li\u00e8ge 4032",
    "addr:housenumber":"70;1",
    "addr:postcode":"4032",
    "addr:street":"Rue Large",
    "iso:country":"BE",
    "sg:address":"Rue Large 70",
    "sg:city":"Li\u00e8ge 1 (ch\u00ean\u00e9e)",
    "sg:orig_category":"Fiduciairies",
    "sg:phone":"+32 4 367 01 42",
    "sg:postcode":"4032",
    "sg:province":"Li\u00e8ge",
    "wof:name":"Renson G",
    "wof:placetype":"venue"
},
  "geometry": {"coordinates":[5.6124219894,50.6150588989],"type":"Point"}
}