{
  "type": "Feature",
  "properties": {
    "addr:full":"Geelsebaan 73 Kasterlee Antwerpen 2460",
    "addr:housenumber":"73",
    "addr:postcode":"2460",
    "addr:street":"Geelsebaan",
    "iso:country":"BE",
    "sg:address":"Geelsebaan 73",
    "sg:city":"Kasterlee",
    "sg:classifiers":[
        {
            "category":"Restaurant",
            "type":"Food & Drink"
        }
    ],
    "sg:phone":"+32 14 85 04 25",
    "sg:postcode":"2460",
    "sg:province":"Antwerpen",
    "wof:name":"Bistro Potiron",
    "wof:placetype":"venue"
},
  "geometry": {"coordinates":[4.9707169533,51.2360801697],"type":"Point"}
}