{
  "type": "Feature",
  "properties": {
    "iso:country":"BE",
    "sg:address":"Rijksweg 215",
    "sg:city":"Maasmechelen",
    "sg:classifiers":[
        {
            "category":"Restaurant",
            "type":"Food & Drink"
        }
    ],
    "sg:phone":"+32 89 76 41 34",
    "sg:postcode":"3630",
    "sg:province":"Limburg",
    "wof:name":"Da Lidia",
    "wof:placetype":"venue"
},
  "geometry": {"coordinates":[5.7003760338,50.9771728516],"type":"Point"}
}