{
  "type": "Feature",
  "properties": {
    "iso:country":"BE",
    "sg:address":"Place Eug\u00e8ne Keym 52",
    "sg:city":"Bruxelles (watermael-boitsfort)",
    "sg:classifiers":[
        {
            "category":"Professional",
            "subcategory":"Testing Lab",
            "type":"Services"
        }
    ],
    "sg:phone":"+32 2 660 19 18",
    "sg:postcode":"1170",
    "sg:province":"Bruxelles-Capitale",
    "sg:tags":[
        "laboratory",
        "photographic",
        "film"
    ],
    "wof:name":"Tele-photo-lab Sprl",
    "wof:placetype":"venue"
},
  "geometry": {"coordinates":[4.4031071663,50.8092041016],"type":"Point"}
}