{
  "type": "Feature",
  "properties": {
    "addr:full":"Gapenberg 18 Geraardsbergen (ophasselt) Oost-Vlaanderen 9500",
    "addr:housenumber":"18",
    "addr:postcode":"9500",
    "addr:street":"Gapenberg",
    "iso:country":"BE",
    "sg:address":"Gapenberg 18",
    "sg:city":"Geraardsbergen (ophasselt)",
    "sg:classifiers":[
        {
            "category":"Home & Garden",
            "subcategory":"Building Materials",
            "type":"Retail Goods"
        }
    ],
    "sg:phone":"+32 54 50 26 87",
    "sg:postcode":"9500",
    "sg:province":"Oost-Vlaanderen",
    "sg:tags":[
        "veranda"
    ],
    "wof:name":"Ds Veranda's",
    "wof:placetype":"venue"
},
  "geometry": {"coordinates":[3.8843801022,50.7716445923],"type":"Point"}
}