{
  "type": "Feature",
  "properties": {
    "addr:full":"Place Du March\u00e9 15 Box 37 La Roche-en-ardenne Luxembourg 6980",
    "addr:housenumber":"15 box 37",
    "addr:postcode":"6980",
    "addr:street":"Place Du Marche\u0301",
    "iso:country":"BE",
    "sg:address":"Place Du March\u00e9 15 Box 37",
    "sg:city":"La Roche-en-ardenne",
    "sg:classifiers":[
        {
            "category":"Government",
            "subcategory":"Office",
            "type":"Public Place"
        }
    ],
    "sg:phone":"+32 84 36 77 36",
    "sg:postcode":"6980",
    "sg:province":"Luxembourg",
    "sg:tags":[
        "-",
        "tourism",
        "federation"
    ],
    "wof:name":"Maison Du Tourisme",
    "wof:placetype":"venue"
},
  "geometry": {"coordinates":[5.5752801895,50.1816101074],"type":"Point"}
}