{
  "type": "Feature",
  "properties": {
    "iso:country":"BE",
    "sg:address":"Place De Rome 15",
    "sg:city":"Malmedy/malmedy",
    "sg:orig_category":"Avocats and conseillers juridiques",
    "sg:phone":"+32 80 33 06 07",
    "sg:postcode":"4960",
    "sg:province":"Li\u00e8ge",
    "wof:name":"Leon Doutrelepont",
    "wof:placetype":"venue"
},
  "geometry": {"coordinates":[6.0551772118,50.37657547],"type":"Point"}
}