{
  "type": "Feature",
  "properties": {
    "iso:country":"BE",
    "sg:address":"Av. Prince De Li\u00e8ge 74 Bte 78",
    "sg:city":"Jambes",
    "sg:classifiers":[
        {
            "category":"Banks & Credit Unions",
            "subcategory":"Financial Services",
            "type":"Services"
        }
    ],
    "sg:phone":"+32 81 32 42 11",
    "sg:postcode":"5100",
    "sg:province":"Namur",
    "sg:tags":[
        "banking",
        "finance",
        "insurance"
    ],
    "wof:name":"Assurances Du Credit Namur",
    "wof:placetype":"venue"
},
  "geometry": {"coordinates":[4.881896019,50.463054657],"type":"Point"}
}