{
  "type": "Feature",
  "properties": {
    "addr:full":"Koning Leopold I Straat 34 Leuven Vlaams-Brabant 3000",
    "addr:housenumber":"34",
    "addr:postcode":"3000",
    "addr:street":"Koning Leopold I Straat",
    "iso:country":"BE",
    "sg:address":"Koning Leopold I Straat 34",
    "sg:city":"Leuven",
    "sg:orig_category":"Opticiens. S\u00e9curit\u00e9 sociale. Articles m\u00e9dicaux and orthop\u00e9diques",
    "sg:phone":"+32 16 23 71 39",
    "sg:postcode":"3000",
    "sg:province":"Vlaams-Brabant",
    "wof:name":"Uitleendienst Mediotheek Leuven",
    "wof:placetype":"venue"
},
  "geometry": {"coordinates":[4.7091999054,50.8794822693],"type":"Point"}
}