{
  "type": "Feature",
  "properties": {
    "iso:country":"BE",
    "sg:address":"Grand Chemin 108",
    "sg:city":"Tournai (havinnes)",
    "sg:classifiers":[
        {
            "category":"Retail",
            "subcategory":"Auto Rental",
            "type":"Services"
        }
    ],
    "sg:phone":"+32 69 54 65 19",
    "sg:postcode":"7531",
    "sg:province":"Hainaut",
    "sg:tags":[
        "milking",
        "machine"
    ],
    "wof:name":"De Witte & Fils",
    "wof:placetype":"venue"
},
  "geometry": {"coordinates":[3.4625511169,50.6155090332],"type":"Point"}
}