{
  "type": "Feature",
  "properties": {
    "addr:full":"Olenseweg 150 Geel Antwerpen 2440",
    "addr:housenumber":"150",
    "addr:postcode":"2440",
    "addr:street":"Olenseweg",
    "iso:country":"BE",
    "sg:address":"Olenseweg 150",
    "sg:city":"Geel",
    "sg:classifiers":[
        {
            "category":"Home & Garden",
            "subcategory":"Home Furnishings",
            "type":"Retail Goods"
        }
    ],
    "sg:phone":"+32 14 58 97 20",
    "sg:postcode":"2440",
    "sg:province":"Antwerpen",
    "sg:tags":[
        "-",
        "furniture"
    ],
    "wof:name":"Horemans Nv",
    "wof:placetype":"venue"
},
  "geometry": {"coordinates":[4.9292469025,51.1642227173],"type":"Point"}
}