{
  "type": "Feature",
  "properties": {
    "addr:full":"1 Pontembeek Bever Vlaams-Brabant 1547",
    "addr:housenumber":"1",
    "addr:postcode":"1547",
    "addr:street":"Pontembeek;Vlaams-Brabant",
    "iso:country":"BE",
    "sg:address":"1 Pontembeek",
    "sg:city":"Bever",
    "sg:classifiers":[
        {
            "category":"Travel",
            "subcategory":"Hotels & Motels",
            "type":"Entertainment"
        }
    ],
    "sg:phone":"+32 54 58 68 80",
    "sg:postcode":"1547",
    "sg:province":"Vlaams-Brabant",
    "sg:tags":[
        "hotels",
        "business",
        "restaurant"
    ],
    "wof:name":"Malesteni Bvba",
    "wof:placetype":"venue"
},
  "geometry": {"coordinates":[3.9423089027,50.7065963745],"type":"Point"}
}