{
  "type": "Feature",
  "properties": {
    "addr:full":"Ville-du-bois 71 Vielsalm Luxembourg 6690",
    "addr:housenumber":"71",
    "addr:postcode":"6690",
    "addr:street":"Ville-Du-Bois",
    "iso:country":"BE",
    "sg:address":"Ville-du-bois 71",
    "sg:city":"Vielsalm",
    "sg:orig_category":"Epiceries",
    "sg:phone":"+32 80 21 64 38",
    "sg:postcode":"6690",
    "sg:province":"Luxembourg",
    "wof:name":"Uma",
    "wof:placetype":"venue"
},
  "geometry": {"coordinates":[5.9359297752,50.2912483215],"type":"Point"}
}