{
  "type": "Feature",
  "properties": {
    "iso:country":"BE",
    "sg:address":"Rue Fr. Robbrechts 69",
    "sg:city":"Wemmel",
    "sg:classifiers":[
        {
            "category":"Health Services",
            "subcategory":"Health Practitioner",
            "type":"Services"
        }
    ],
    "sg:phone":"+32 2 460 34 91",
    "sg:postcode":"1780",
    "sg:province":"Vlaams-Brabant",
    "sg:tags":[
        "physiotherapist"
    ],
    "wof:name":"Laurent M-f",
    "wof:placetype":"venue"
},
  "geometry": {"coordinates":[4.3072228432,50.9121322632],"type":"Point"}
}