{
  "type": "Feature",
  "properties": {
    "iso:country":"BE",
    "sg:address":"Bouwelse Steenweg 68",
    "sg:city":"Herenthout",
    "sg:classifiers":[
        {
            "category":"Wholesale",
            "subcategory":"Meat",
            "type":"Manufacturing & Wholesale Goods"
        }
    ],
    "sg:phone":"+32 14 51 17 08",
    "sg:postcode":"2270",
    "sg:province":"Antwerpen",
    "sg:tags":[
        "whol",
        "-"
    ],
    "wof:name":"Van Den Broeck P",
    "wof:placetype":"venue"
},
  "geometry": {"coordinates":[4.7541007996,51.1437034607],"type":"Point"}
}