{
  "type": "Feature",
  "properties": {
    "addr:full":"Ooststraat 74b Veurne West-Vlaanderen 8630",
    "addr:housenumber":"74b",
    "addr:postcode":"8630",
    "addr:street":"Ooststraat",
    "iso:country":"BE",
    "sg:address":"Ooststraat 74b",
    "sg:city":"Veurne",
    "sg:classifiers":[
        {
            "category":"Manufacturing",
            "subcategory":"Textiles",
            "type":"Manufacturing & Wholesale Goods"
        }
    ],
    "sg:phone":"+32 58 29 88 38",
    "sg:postcode":"8630",
    "sg:province":"West-Vlaanderen",
    "sg:tags":[
        "retail",
        "-"
    ],
    "wof:name":"Zeeman Textiel Supers",
    "wof:placetype":"venue"
},
  "geometry": {"coordinates":[2.6670429707,51.0731201172],"type":"Point"}
}