{
  "type": "Feature",
  "properties": {
    "addr:full":"Rue Des Marais 29 Perwez Brabant Wallon 1360",
    "addr:housenumber":"29",
    "addr:postcode":"1360",
    "addr:street":"Rue Des Marais",
    "iso:country":"BE",
    "sg:address":"Rue Des Marais 29",
    "sg:city":"Perwez",
    "sg:orig_category":"M\u00e9decins and sp\u00e9cialistes",
    "sg:phone":"+32 10 88 02 80",
    "sg:postcode":"1360",
    "sg:province":"Brabant Wallon",
    "wof:name":"Fabienne De Browne De Ti\u00c8ge",
    "wof:placetype":"venue"
},
  "geometry": {"coordinates":[4.8180580139,50.6611328125],"type":"Point"}
}