{
  "type": "Feature",
  "properties": {
    "iso:country":"BE",
    "sg:address":"Polderstraat 79",
    "sg:city":"Knokke-heist",
    "sg:orig_category":"Herstelling leer and schoeisel Herstellingswinkels voor diverse persoonlijke and huishoudartikelen I",
    "sg:phone":"+32 50 51 26 17",
    "sg:postcode":"8301",
    "sg:province":"West-Vlaanderen",
    "wof:name":"Multi Key",
    "wof:placetype":"venue"
},
  "geometry": {"coordinates":[3.2639000416,51.3396911621],"type":"Point"}
}