{
  "type": "Feature",
  "properties": {
    "iso:country":"BE",
    "sg:address":"Hompr\u00c9 28",
    "sg:city":"Vaux-sur-sure",
    "sg:orig_category":"Woningbouw",
    "sg:phone":"+32 61 26 69 44",
    "sg:postcode":"6640",
    "sg:province":"Luxembourg",
    "wof:name":"Rene Warg\u00c9",
    "wof:placetype":"venue"
},
  "geometry": {"coordinates":[5.5671000481,49.91065979],"type":"Point"}
}