{
  "type": "Feature",
  "properties": {
    "iso:country":"BE",
    "sg:address":"Villerslei 226",
    "sg:city":"Schoten",
    "sg:classifiers":[
        {
            "category":"Food & Beverages",
            "subcategory":"Meat & Fish",
            "type":"Retail Goods"
        }
    ],
    "sg:phone":"+32 3 789 93 66",
    "sg:postcode":"2900",
    "sg:province":"Antwerpen",
    "sg:tags":[
        "poultry",
        "whol",
        "game",
        "-"
    ],
    "wof:name":"C.t.o.",
    "wof:placetype":"venue"
},
  "geometry": {"coordinates":[4.524189949,51.2504692078],"type":"Point"}
}