{
  "type": "Feature",
  "properties": {
    "addr:full":"Elsense Steenweg 310 Elsene/ixelles Bruxelles-Capitale 1050",
    "addr:housenumber":"310",
    "addr:postcode":"1050",
    "addr:street":"Elsense Steenweg",
    "iso:country":"BE",
    "sg:address":"Elsense Steenweg 310",
    "sg:city":"Elsene/ixelles",
    "sg:orig_category":"Voedingsspeciaalzaken",
    "sg:phone":"+32 2 640 05 72",
    "sg:postcode":"1050",
    "sg:province":"Bruxelles-Capitale",
    "wof:name":"Spiga D'oro",
    "wof:placetype":"venue"
},
  "geometry": {"coordinates":[4.3712291718,50.8284034729],"type":"Point"}
}