{
  "type": "Feature",
  "properties": {
    "addr:full":"Halensebaan 148 Tielt-winge Vlaams-Brabant 3390",
    "addr:housenumber":"148",
    "addr:postcode":"3390",
    "addr:street":"Halensebaan",
    "iso:country":"BE",
    "sg:address":"Halensebaan 148",
    "sg:city":"Tielt-winge",
    "sg:orig_category":"Entretien and r\u00e9parations de voitures",
    "sg:phone":"+32 16 63 41 18",
    "sg:postcode":"3390",
    "sg:province":"Vlaams-Brabant",
    "wof:name":"Garage Lemmens",
    "wof:placetype":"venue"
},
  "geometry": {"coordinates":[4.9194598198,50.9137191772],"type":"Point"}
}