{
  "type": "Feature",
  "properties": {
    "addr:full":"Kantonsweg 89 Dilsen-stokkem Limburg 3650",
    "addr:housenumber":"89",
    "addr:postcode":"3650",
    "addr:street":"Kantonsweg",
    "iso:country":"BE",
    "sg:address":"Kantonsweg 89",
    "sg:city":"Dilsen-stokkem",
    "sg:orig_category":"Pain, p\u00e2tisseries and confiseries",
    "sg:phone":"+32 89 79 23 63",
    "sg:postcode":"3650",
    "sg:province":"Limburg",
    "wof:name":"Bakkerij Dirkx",
    "wof:placetype":"venue"
},
  "geometry": {"coordinates":[5.7184801102,51.0470466614],"type":"Point"}
}