{
  "type": "Feature",
  "properties": {
    "addr:full":"Statiestraat 1 Lichtervelde West-Vlaanderen 8810",
    "addr:housenumber":"1",
    "addr:postcode":"8810",
    "addr:street":"Statiestraat",
    "iso:country":"BE",
    "sg:address":"Statiestraat 1",
    "sg:city":"Lichtervelde",
    "sg:orig_category":"Brood, gebak and snoepgoed",
    "sg:phone":"+32 51 72 61 65",
    "sg:postcode":"8810",
    "sg:province":"West-Vlaanderen",
    "wof:name":"Chocolaterie Huyghe",
    "wof:placetype":"venue"
},
  "geometry": {"coordinates":[3.141201973,51.0261497498],"type":"Point"}
}