{
  "type": "Feature",
  "properties": {
    "iso:country":"BE",
    "sg:address":"Shopping Center Nivelles",
    "sg:city":"Nivelles",
    "sg:classifiers":[
        {
            "category":"Shopping",
            "subcategory":"Clothing, Apparel, & Fashions",
            "type":"Retail Goods"
        }
    ],
    "sg:phone":"+32 67 21 39 65",
    "sg:postcode":"1400",
    "sg:province":"Brabant Wallon",
    "sg:tags":[
        "-",
        "clothing",
        "child"
    ],
    "wof:name":"Saute Mouton",
    "wof:placetype":"venue"
},
  "geometry": {"coordinates":[4.3036298752,50.5899467468],"type":"Point"}
}