{
  "type": "Feature",
  "properties": {
    "addr:full":"Vleurgatsesteenweg 55 Elsene/ixelles Bruxelles-Capitale 1050",
    "addr:housenumber":"55",
    "addr:postcode":"1050",
    "addr:street":"Vleurgatsesteenweg",
    "iso:country":"BE",
    "sg:address":"Vleurgatsesteenweg 55",
    "sg:city":"Elsene/ixelles",
    "sg:orig_category":"Technisch and beroeps secundair onderwijs",
    "sg:phone":"+32 2 648 10 70",
    "sg:postcode":"1050",
    "sg:province":"Bruxelles-Capitale",
    "wof:name":"C.e.s. St.vincent Paul",
    "wof:placetype":"venue"
},
  "geometry": {"coordinates":[4.369852066,50.8260154724],"type":"Point"}
}