{
  "type": "Feature",
  "properties": {
    "iso:country":"BE",
    "sg:address":"Rue Provinciale (wavre) 58",
    "sg:city":"Bierges",
    "sg:classifiers":[
        {
            "category":"Coffee & Tea",
            "type":"Food & Drink"
        }
    ],
    "sg:phone":"+32 10 22 67 81",
    "sg:postcode":"1301",
    "sg:province":"Brabant Wallon",
    "sg:tags":[
        "mustard"
    ],
    "wof:name":"L'etoile Vinaigrerie S.a.",
    "wof:placetype":"venue"
},
  "geometry": {"coordinates":[4.6010808945,50.7132911682],"type":"Point"}
}