{
  "type": "Feature",
  "properties": {
    "iso:country":"BE",
    "sg:address":"Cataloniestraat 4",
    "sg:city":"Gent",
    "sg:orig_category":"V\u00eatements",
    "sg:phone":"+32 9 225 36 45",
    "sg:postcode":"9000",
    "sg:province":"Oost-Vlaanderen",
    "wof:name":"Company Store",
    "wof:placetype":"venue"
},
  "geometry": {"coordinates":[3.7230379581,51.0536575317],"type":"Point"}
}