{
  "type": "Feature",
  "properties": {
    "addr:full":"Oppendorpgang Leuven Vlaams-Brabant 3000",
    "addr:postcode":"3000",
    "addr:street":"Oppendorpgang",
    "iso:country":"BE",
    "sg:address":"Oppendorpgang",
    "sg:city":"Leuven",
    "sg:classifiers":[
        {
            "category":"Shopping",
            "subcategory":"Party Supplies",
            "type":"Retail Goods"
        }
    ],
    "sg:phone":"+32 16 20 20 70",
    "sg:postcode":"3000",
    "sg:province":"Vlaams-Brabant",
    "sg:tags":[
        "rental",
        "-"
    ],
    "wof:name":"Party-service I.s.m. Terclavers",
    "wof:placetype":"venue"
},
  "geometry": {"coordinates":[4.7120199203,50.8816452026],"type":"Point"}
}