{
  "type": "Feature",
  "properties": {
    "iso:country":"BE",
    "sg:address":"Dendermondebaan 75",
    "sg:city":"Zele",
    "sg:classifiers":[
        {
            "category":"Health Services",
            "subcategory":"Health Practitioner",
            "type":"Services"
        }
    ],
    "sg:phone":"+32 52 45 27 19",
    "sg:postcode":"9240",
    "sg:province":"Oost-Vlaanderen",
    "sg:tags":[
        "physiotherapist"
    ],
    "wof:name":"Fiers Katrien",
    "wof:placetype":"venue"
},
  "geometry": {"coordinates":[4.049685955,51.0663146973],"type":"Point"}
}