{
  "type": "Feature",
  "properties": {
    "addr:full":"Nationalestraat 96-98 Antwerpen Antwerpen 2000",
    "addr:postcode":"96-98;2000",
    "addr:street":"Nationalestraat",
    "iso:country":"BE",
    "sg:address":"Nationalestraat 96-98",
    "sg:city":"Antwerpen",
    "sg:classifiers":[
        {
            "category":"Personal",
            "subcategory":"Beauty Salon",
            "type":"Services"
        }
    ],
    "sg:phone":"+32 3 233 07 96",
    "sg:postcode":"2000",
    "sg:province":"Antwerpen",
    "sg:tags":[
        "de",
        "coiffure"
    ],
    "wof:name":"Coiffure Heidi",
    "wof:placetype":"venue"
},
  "geometry": {"coordinates":[4.3982729912,51.2147712708],"type":"Point"}
}