{
  "type": "Feature",
  "properties": {
    "addr:full":"Rue Bois D'ohey 291 Ohey Namur 5350",
    "addr:housenumber":"291",
    "addr:postcode":"5350",
    "addr:street":"Rue Bois D'Ohey",
    "iso:country":"BE",
    "sg:address":"Rue Bois D'ohey 291",
    "sg:city":"Ohey",
    "sg:orig_category":"Brood, gebak and snoepgoed",
    "sg:phone":"+32 85 61 16 90",
    "sg:postcode":"5350",
    "sg:province":"Namur",
    "wof:name":"Boulangerie Lamborelle",
    "wof:placetype":"venue"
},
  "geometry": {"coordinates":[5.1113190651,50.4400672913],"type":"Point"}
}