{
  "type": "Feature",
  "properties": {
    "iso:country":"BE",
    "sg:address":"Damkaai 6bc2",
    "sg:city":"Kortrijk",
    "sg:classifiers":[
        {
            "category":"Insurance",
            "subcategory":"Life Insurance",
            "type":"Services"
        }
    ],
    "sg:phone":"+32 56 20 50 86",
    "sg:postcode":"8500",
    "sg:province":"West-Vlaanderen",
    "sg:tags":[
        "assurance"
    ],
    "wof:name":"De Clerck T.",
    "wof:placetype":"venue"
},
  "geometry": {"coordinates":[3.2668199539,50.831489563],"type":"Point"}
}