{
  "type": "Feature",
  "properties": {
    "iso:country":"BE",
    "sg:address":"Alphonse Franskinlaan 24",
    "sg:city":"De Haan",
    "sg:orig_category":"Hout and afgeleiden Gh IJzerwaren, bouw- and verfmaterialen",
    "sg:phone":"+32 59 23 89 24",
    "sg:postcode":"8420",
    "sg:province":"West-Vlaanderen",
    "wof:name":"Imexbois",
    "wof:placetype":"venue"
},
  "geometry": {"coordinates":[3.0278930664,51.2665748596],"type":"Point"}
}