{
  "type": "Feature",
  "properties": {
    "iso:country":"BE",
    "sg:address":"Place Du Tr\u00f4ne 1",
    "sg:city":"Bruxelles",
    "sg:classifiers":[
        {
            "category":"Utilities",
            "subcategory":"Water",
            "type":"Services"
        }
    ],
    "sg:phone":"+32 78 35 35 00",
    "sg:postcode":"1000",
    "sg:province":"Bruxelles-Capitale",
    "sg:tags":[
        "distribution"
    ],
    "wof:name":"Aquinter",
    "wof:placetype":"venue"
},
  "geometry": {"coordinates":[4.3635129929,50.8400535583],"type":"Point"}
}