{
  "type": "Feature",
  "properties": {
    "addr:full":"Eeckhoutstraat 22 Aalst Oost-Vlaanderen 9308",
    "addr:housenumber":"22",
    "addr:postcode":"9308",
    "addr:street":"Eeckhoutstraat",
    "iso:country":"BE",
    "sg:address":"Eeckhoutstraat 22",
    "sg:city":"Aalst",
    "sg:classifiers":[
        {
            "category":"Personal",
            "subcategory":"Beauty Salon",
            "type":"Services"
        }
    ],
    "sg:phone":"+32 53 78 58 89",
    "sg:postcode":"9308",
    "sg:province":"Oost-Vlaanderen",
    "sg:tags":[
        "de",
        "coiffure"
    ],
    "wof:name":"Karine De Winne",
    "wof:placetype":"venue"
},
  "geometry": {"coordinates":[4.1321310997,50.9293937683],"type":"Point"}
}