{
  "type": "Feature",
  "properties": {
    "addr:full":"Markt 1 Kruishoutem Oost-Vlaanderen 9770",
    "addr:housenumber":"1",
    "addr:postcode":"9770",
    "addr:street":"Markt",
    "iso:country":"BE",
    "sg:address":"Markt 1",
    "sg:city":"Kruishoutem",
    "sg:orig_category":"Biblioth\u00e8ques and archives publiques",
    "sg:phone":"+32 9 383 69 78",
    "sg:postcode":"9770",
    "sg:province":"Oost-Vlaanderen",
    "wof:name":"Openbare Bibliotheek",
    "wof:placetype":"venue"
},
  "geometry": {"coordinates":[3.5280380249,50.9042739868],"type":"Point"}
}