{
  "type": "Feature",
  "properties": {
    "iso:country":"BE",
    "sg:address":"Antwerpsesteenweg 78",
    "sg:city":"Kapellen",
    "sg:classifiers":[
        {
            "category":"Health Services",
            "subcategory":"Doctor",
            "type":"Services"
        }
    ],
    "sg:phone":"+32 3 665 07 08",
    "sg:postcode":"2950",
    "sg:province":"Antwerpen",
    "sg:tags":[
        "medicinephysicians",
        "surgeon"
    ],
    "wof:name":"Eekhaut M",
    "wof:placetype":"venue"
},
  "geometry": {"coordinates":[4.4303088188,51.3107795715],"type":"Point"}
}