{
  "type": "Feature",
  "properties": {
    "iso:country":"BE",
    "sg:address":"Rue Lagasse 30",
    "sg:city":"Nivelles",
    "sg:orig_category":"Mat\u00e9riel m\u00e9dical and orthop\u00e9dique and proth\u00e8ses Fab",
    "sg:phone":"+32 67 21 27 58",
    "sg:postcode":"1400",
    "sg:province":"Brabant Wallon",
    "wof:name":"Durieux",
    "wof:placetype":"venue"
},
  "geometry": {"coordinates":[4.3334040642,50.5985908508],"type":"Point"}
}