{
  "type": "Feature",
  "properties": {
    "addr:full":"De Panestraat 5 Heusden-zolder Limburg 3550",
    "addr:housenumber":"5",
    "addr:postcode":"3550",
    "addr:street":"Panestraat",
    "iso:country":"BE",
    "sg:address":"De Panestraat 5",
    "sg:city":"Heusden-zolder",
    "sg:orig_category":"Woningbouw",
    "sg:phone":"+32 11 53 84 36",
    "sg:postcode":"3550",
    "sg:province":"Limburg",
    "wof:name":"Willy Moons",
    "wof:placetype":"venue"
},
  "geometry": {"coordinates":[5.2852067947,51.0123138428],"type":"Point"}
}