{
  "type": "Feature",
  "properties": {
    "addr:full":"Rue Albert Ier 60 Dison Li\u00e8ge 4820",
    "addr:housenumber":"60",
    "addr:postcode":"4820",
    "addr:street":"Rue Albert Ier",
    "iso:country":"BE",
    "sg:address":"Rue Albert Ier 60",
    "sg:city":"Dison",
    "sg:orig_category":"Banken and kredietinstellingen",
    "sg:phone":"+32 87 33 44 24",
    "sg:postcode":"4820",
    "sg:province":"Li\u00e8ge",
    "wof:name":"Bbl",
    "wof:placetype":"venue"
},
  "geometry": {"coordinates":[5.8546080589,50.6083145142],"type":"Point"}
}