{
  "type": "Feature",
  "properties": {
    "iso:country":"BE",
    "sg:address":"Chauss\u00e9e De Lille 18b",
    "sg:city":"Tournai",
    "sg:classifiers":[
        {
            "category":"Retail",
            "subcategory":"Auto Repair",
            "type":"Services"
        }
    ],
    "sg:phone":"+32 69 21 30 57",
    "sg:postcode":"7500",
    "sg:province":"Hainaut",
    "sg:tags":[
        "garage"
    ],
    "wof:name":"Garage Desnerck",
    "wof:placetype":"venue"
},
  "geometry": {"coordinates":[3.3739550114,50.6048965454],"type":"Point"}
}