{
  "type": "Feature",
  "properties": {
    "iso:country":"BE",
    "sg:address":"Brusselsesteenweg 150",
    "sg:city":"Merchtem",
    "sg:orig_category":"Non-Classified Establishments",
    "sg:phone":"+32 52 37 05 70",
    "sg:postcode":"1785",
    "sg:province":"Vlaams-Brabant",
    "wof:name":"Marc Reigel Bvba",
    "wof:placetype":"venue"
},
  "geometry": {"coordinates":[4.2458219528,50.9467086792],"type":"Point"}
}