{
  "type": "Feature",
  "properties": {
    "addr:full":"Menenstraat 340 Wevelgem West-Vlaanderen 8560",
    "addr:housenumber":"340",
    "addr:postcode":"8560",
    "addr:street":"Menenstraat",
    "iso:country":"BE",
    "sg:address":"Menenstraat 340",
    "sg:city":"Wevelgem",
    "sg:classifiers":[
        {
            "category":"Cafe",
            "type":"Food & Drink"
        }
    ],
    "sg:phone":"+32 56 41 22 79",
    "sg:postcode":"8560",
    "sg:province":"West-Vlaanderen",
    "sg:tags":[
        "caf\u00e9s"
    ],
    "wof:name":"Monique Verstraete",
    "wof:placetype":"venue"
},
  "geometry": {"coordinates":[3.1598420143,50.8034667969],"type":"Point"}
}