{
  "type": "Feature",
  "properties": {
    "iso:country":"BE",
    "sg:address":"Rijksweg 263a",
    "sg:city":"Maasmechelen",
    "sg:classifiers":[
        {
            "category":"Retail",
            "subcategory":"Event Space",
            "type":"Services"
        }
    ],
    "sg:phone":"+32 89 76 53 78",
    "sg:postcode":"3630",
    "sg:province":"Limburg",
    "sg:tags":[
        "rental",
        "-",
        "hall"
    ],
    "wof:name":"Henri F",
    "wof:placetype":"venue"
},
  "geometry": {"coordinates":[5.6985521317,50.9724845886],"type":"Point"}
}