{
  "type": "Feature",
  "properties": {
    "iso:country":"BE",
    "sg:address":"Rue D'hurtebise 10",
    "sg:city":"Binche",
    "sg:classifiers":[
        {
            "category":"Real Estate",
            "subcategory":"Real Estate Services",
            "type":"Services"
        }
    ],
    "sg:phone":"+32 64 34 04 34",
    "sg:postcode":"7130",
    "sg:province":"Hainaut",
    "wof:name":"Immo 7 Sc",
    "wof:placetype":"venue"
},
  "geometry": {"coordinates":[4.1702399254,50.4074554443],"type":"Point"}
}