{
  "type": "Feature",
  "properties": {
    "addr:full":"Galgeveldstraat 13 Diest Vlaams-Brabant 3293",
    "addr:housenumber":"13",
    "addr:postcode":"3293",
    "addr:street":"Galgeveldstraat",
    "iso:country":"BE",
    "sg:address":"Galgeveldstraat 13",
    "sg:city":"Diest",
    "sg:orig_category":"Installation \u00e9lectrique r\u00e9sidentielle",
    "sg:phone":"+32 13 33 30 23",
    "sg:postcode":"3293",
    "sg:province":"Vlaams-Brabant",
    "wof:name":"Roland Dekkers",
    "wof:placetype":"venue"
},
  "geometry": {"coordinates":[5.0415558815,50.9791297913],"type":"Point"}
}