{
  "type": "Feature",
  "properties": {
    "addr:full":"Olmenstraat 34 Oostkamp West-Vlaanderen 8020",
    "addr:housenumber":"34",
    "addr:postcode":"8020",
    "addr:street":"Olmenstraat",
    "iso:country":"BE",
    "sg:address":"Olmenstraat 34",
    "sg:city":"Oostkamp",
    "sg:classifiers":[
        {
            "category":"Home & Garden",
            "subcategory":"Carpets & Floor Coverings",
            "type":"Retail Goods"
        }
    ],
    "sg:phone":"+32 50 36 15 30",
    "sg:postcode":"8020",
    "sg:province":"West-Vlaanderen",
    "sg:tags":[
        "layer",
        "mosaicists"
    ],
    "wof:name":"Roelandts R",
    "wof:placetype":"venue"
},
  "geometry": {"coordinates":[3.2429249287,51.1783218384],"type":"Point"}
}