{
  "type": "Feature",
  "properties": {
    "iso:country":"BE",
    "sg:address":"Leopoldlaan 12",
    "sg:city":"De Haan (klemskerke)",
    "sg:classifiers":[
        {
            "category":"Travel",
            "subcategory":"Hotels & Motels",
            "type":"Entertainment"
        }
    ],
    "sg:phone":"+32 59 23 35 79",
    "sg:postcode":"8420",
    "sg:province":"West-Vlaanderen",
    "wof:name":"Internos",
    "wof:placetype":"venue"
},
  "geometry": {"coordinates":[3.0320560932,51.2734985352],"type":"Point"}
}