{
  "type": "Feature",
  "properties": {
    "addr:full":"Dijk 67 Sint-katelijne-waver (onze-lieve-vrouw-waver) Antwerpen 2861",
    "addr:housenumber":"67",
    "addr:postcode":"2861",
    "addr:street":"Dijk",
    "iso:country":"BE",
    "sg:address":"Dijk 67",
    "sg:city":"Sint-katelijne-waver (onze-lieve-vrouw-waver)",
    "sg:classifiers":[
        {
            "category":"Health Services",
            "subcategory":"Health Practitioner",
            "type":"Services"
        }
    ],
    "sg:phone":"+32 15 75 45 36",
    "sg:postcode":"2861",
    "sg:province":"Antwerpen",
    "sg:tags":[
        "physiotherapist"
    ],
    "wof:name":"Cluydts M-c",
    "wof:placetype":"venue"
},
  "geometry": {"coordinates":[4.5750169754,51.0575942993],"type":"Point"}
}