{
  "type": "Feature",
  "properties": {
    "addr:full":"Elderenweg 16 Riemst Limburg 3770",
    "addr:housenumber":"16",
    "addr:postcode":"3770",
    "addr:street":"Elderenweg",
    "iso:country":"BE",
    "sg:address":"Elderenweg 16",
    "sg:city":"Riemst",
    "sg:orig_category":"Landbouwmachines Gh",
    "sg:phone":"+32 12 23 20 97",
    "sg:postcode":"3770",
    "sg:province":"Limburg",
    "wof:name":"Landbouwmachines Ulrix",
    "wof:placetype":"venue"
},
  "geometry": {"coordinates":[5.5536699295,50.7926940918],"type":"Point"}
}