{
  "type": "Feature",
  "properties": {
    "addr:full":"Hoogstraat 58 Wichelen (schellebelle) Oost-Vlaanderen 9260",
    "addr:housenumber":"58",
    "addr:postcode":"9260",
    "addr:street":"Hoogstraat",
    "iso:country":"BE",
    "sg:address":"Hoogstraat 58",
    "sg:city":"Wichelen (schellebelle)",
    "sg:classifiers":[
        {
            "category":"Manufacturing",
            "subcategory":"Textiles",
            "type":"Manufacturing & Wholesale Goods"
        }
    ],
    "sg:phone":"+32 9 369 27 96",
    "sg:postcode":"9260",
    "sg:province":"Oost-Vlaanderen",
    "sg:tags":[
        "retail",
        "-"
    ],
    "wof:name":"Huylebroeck A",
    "wof:placetype":"venue"
},
  "geometry": {"coordinates":[3.9318079948,51.0116729736],"type":"Point"}
}