{
  "type": "Feature",
  "properties": {
    "addr:full":"Place Marcellis 2 Aywaille Li\u00e8ge 4920",
    "addr:housenumber":"2",
    "addr:postcode":"4920",
    "addr:street":"Place Marcellis",
    "iso:country":"BE",
    "sg:address":"Place Marcellis 2",
    "sg:city":"Aywaille",
    "sg:classifiers":[
        {
            "category":"Cafe",
            "type":"Food & Drink"
        }
    ],
    "sg:phone":"+32 4 384 72 84",
    "sg:postcode":"4920",
    "sg:province":"Li\u00e8ge",
    "sg:tags":[
        "caf\u00e9s"
    ],
    "wof:name":"Caf\u00c9 Le Grillon",
    "wof:placetype":"venue"
},
  "geometry": {"coordinates":[5.6727471352,50.4731941223],"type":"Point"}
}