{
  "type": "Feature",
  "properties": {
    "addr:full":"Bilksken 36 Lovendegem Oost-Vlaanderen 9920",
    "addr:housenumber":"36",
    "addr:postcode":"9920",
    "addr:street":"Bilksken",
    "iso:country":"BE",
    "sg:address":"Bilksken 36",
    "sg:city":"Lovendegem",
    "sg:classifiers":[
        {
            "category":"Professional",
            "type":"Services"
        }
    ],
    "sg:phone":"+32 9 370 55 55",
    "sg:postcode":"9920",
    "sg:province":"Oost-Vlaanderen",
    "sg:tags":[
        "industrial",
        "automation"
    ],
    "wof:name":"Automotion Nv",
    "wof:placetype":"venue"
},
  "geometry": {"coordinates":[3.6374700069,51.0945091248],"type":"Point"}
}