{
  "type": "Feature",
  "properties": {
    "iso:country":"BE",
    "sg:address":"Bonestraat 102",
    "sg:city":"Meulebeke",
    "sg:classifiers":[
        {
            "category":"Transit Center",
            "subcategory":"Freight",
            "type":"Transportation"
        }
    ],
    "sg:phone":"+32 51 48 02 05",
    "sg:postcode":"8760",
    "sg:province":"West-Vlaanderen",
    "sg:tags":[
        "handtrucks",
        "barrow"
    ],
    "wof:name":"Avero Handling",
    "wof:placetype":"venue"
},
  "geometry": {"coordinates":[3.3253700733,50.9560585022],"type":"Point"}
}