{
  "type": "Feature",
  "properties": {
    "iso:country":"BE",
    "sg:address":"L. Lambrechtsstraat 20",
    "sg:city":"Hoeselt",
    "sg:orig_category":"Dansscholen",
    "sg:phone":"+32 475 64 76 09",
    "sg:postcode":"3730",
    "sg:province":"Limburg",
    "wof:name":"Future Dance",
    "wof:placetype":"venue"
},
  "geometry": {"coordinates":[5.4903078079,50.84998703],"type":"Point"}
}