{
  "type": "Feature",
  "properties": {
    "addr:full":"Brusselse Steenweg 148 Vorst/forest Bruxelles-Capitale 1190",
    "addr:housenumber":"148",
    "addr:postcode":"1190",
    "addr:street":"Brusselse Steenweg;/ Forest",
    "iso:country":"BE",
    "sg:address":"Brusselse Steenweg 148",
    "sg:city":"Vorst/forest",
    "sg:orig_category":"Dierenartsen",
    "sg:phone":"+32 2 343 41 83",
    "sg:postcode":"1190",
    "sg:province":"Bruxelles-Capitale",
    "wof:name":"Philippe Swaelus",
    "wof:placetype":"venue"
},
  "geometry": {"coordinates":[4.3243031502,50.8133239746],"type":"Point"}
}