{
  "type": "Feature",
  "properties": {
    "iso:country":"BE",
    "sg:address":"Rue De Ten-brielen 46",
    "sg:city":"Komen-waasten/comines-warneton",
    "sg:classifiers":[
        {
            "category":"Personal",
            "subcategory":"Beauty Salon",
            "type":"Services"
        }
    ],
    "sg:phone":"+32 56 55 64 88",
    "sg:postcode":"7780",
    "sg:province":"Hainaut",
    "sg:tags":[
        "de",
        "coiffure"
    ],
    "wof:name":"Jean-luc Hairdressing",
    "wof:placetype":"venue"
},
  "geometry": {"coordinates":[2.9967899323,50.7743797302],"type":"Point"}
}