{
  "type": "Feature",
  "properties": {
    "iso:country":"BE",
    "sg:address":"Meistraat 16",
    "sg:city":"Hasselt",
    "sg:orig_category":"Boissons Gr",
    "sg:phone":"+32 11 87 24 28",
    "sg:postcode":"3510",
    "sg:province":"Limburg",
    "wof:name":"D.d.s.",
    "wof:placetype":"venue"
},
  "geometry": {"coordinates":[5.2531552315,50.9474906921],"type":"Point"}
}