{
  "type": "Feature",
  "properties": {
    "addr:full":"Rue Du Noyer 281 Bruxelles Bruxelles-Capitale 1000",
    "addr:housenumber":"281",
    "addr:postcode":"1000",
    "addr:street":"Rue Du Noyer",
    "iso:country":"BE",
    "sg:address":"Rue Du Noyer 281",
    "sg:city":"Bruxelles",
    "sg:classifiers":[
        {
            "category":"Shopping",
            "subcategory":"Discount & Variety Stores",
            "type":"Retail Goods"
        }
    ],
    "sg:phone":"+32 2 735 60 57",
    "sg:postcode":"1000",
    "sg:province":"Bruxelles-Capitale",
    "sg:tags":[
        "shop",
        "clearers",
        "curiosity",
        "furniture"
    ],
    "wof:name":"The English House",
    "wof:placetype":"venue"
},
  "geometry": {"coordinates":[4.3956050873,50.8440361023],"type":"Point"}
}