{
  "type": "Feature",
  "properties": {
    "iso:country":"BE",
    "sg:address":"Av De L'artisanat 10",
    "sg:city":"Braine-l'alleud",
    "sg:classifiers":[
        {
            "category":"Utilities",
            "subcategory":"Electric",
            "type":"Services"
        }
    ],
    "sg:phone":"+32 2 385 00 35",
    "sg:postcode":"1420",
    "sg:province":"Brabant Wallon",
    "sg:tags":[
        "electricity",
        "electronic",
        "electrical",
        "equipment"
    ],
    "wof:name":"Michel Descamp Sa",
    "wof:placetype":"venue"
},
  "geometry": {"coordinates":[15.2195005417,40.783657074],"type":"Point"}
}