{
  "type": "Feature",
  "properties": {
    "addr:full":"Lange Violettestraat 49 Gent-centrum Oost-Vlaanderen 9000",
    "addr:housenumber":"49",
    "addr:postcode":"9000",
    "addr:street":"Lange Violettestraat;Oost-Vlaanderen",
    "iso:country":"BE",
    "sg:address":"Lange Violettestraat 49",
    "sg:city":"Gent-centrum",
    "sg:orig_category":"Fietsen",
    "sg:phone":"+32 9 223 44 96",
    "sg:postcode":"9000",
    "sg:province":"Oost-Vlaanderen",
    "wof:name":"De Ligfiets",
    "wof:placetype":"venue"
},
  "geometry": {"coordinates":[3.7342970371,51.0478210449],"type":"Point"}
}