{
  "type": "Feature",
  "properties": {
    "iso:country":"BE",
    "sg:address":"Essensteenweg 78",
    "sg:city":"Kalmthout",
    "sg:classifiers":[
        {
            "category":"Utilities",
            "subcategory":"Recycling",
            "type":"Services"
        }
    ],
    "sg:phone":"+32 3 667 22 76",
    "sg:postcode":"2920",
    "sg:province":"Antwerpen",
    "sg:tags":[
        "rubbish",
        "removal"
    ],
    "wof:name":"Peeters & Zn",
    "wof:placetype":"venue"
},
  "geometry": {"coordinates":[4.5054402351,51.4387207031],"type":"Point"}
}