{
  "type": "Feature",
  "properties": {
    "addr:full":"Rue Mar\u00e9chal Foch 28a Charleroi (roux) Hainaut 6044",
    "addr:housenumber":"28a;6044",
    "addr:street":"Rue Mare\u0301Chal Foch",
    "iso:country":"BE",
    "sg:address":"Rue Mar\u00e9chal Foch 28a",
    "sg:city":"Charleroi (roux)",
    "sg:classifiers":[
        {
            "category":"Fast Food",
            "type":"Food & Drink"
        }
    ],
    "sg:phone":"+32 71 46 12 41",
    "sg:postcode":"6044",
    "sg:province":"Hainaut",
    "sg:tags":[
        "fried",
        "stand",
        "potato"
    ],
    "wof:name":"Carlo",
    "wof:placetype":"venue"
},
  "geometry": {"coordinates":[4.3942418098,50.441822052],"type":"Point"}
}