{
  "type": "Feature",
  "properties": {
    "iso:country":"BE",
    "sg:address":"Poiel 16",
    "sg:city":"Geel",
    "sg:classifiers":[
        {
            "category":"Health Services",
            "subcategory":"Health Practitioner",
            "type":"Services"
        }
    ],
    "sg:phone":"+32 14 58 65 78",
    "sg:postcode":"2440",
    "sg:province":"Antwerpen",
    "sg:tags":[
        "physiotherapist"
    ],
    "wof:name":"Mols Roger",
    "wof:placetype":"venue"
},
  "geometry": {"coordinates":[4.9751429558,51.157623291],"type":"Point"}
}