{
  "type": "Feature",
  "properties": {
    "addr:full":"Rue Gustave Fuss 35 Schaarbeek/schaerbeek Bruxelles-Capitale 1030",
    "addr:housenumber":"35",
    "addr:postcode":"1030",
    "addr:street":"Rue Gustave Fuss",
    "iso:country":"BE",
    "sg:address":"Rue Gustave Fuss 35",
    "sg:city":"Schaarbeek/schaerbeek",
    "sg:orig_category":"Salles de spectacles",
    "sg:phone":"+32 2 736 95 77",
    "sg:postcode":"1030",
    "sg:province":"Bruxelles-Capitale",
    "wof:name":"Compagnie Iks",
    "wof:placetype":"venue"
},
  "geometry": {"coordinates":[4.3800301552,50.8530044556],"type":"Point"}
}