{
  "type": "Feature",
  "properties": {
    "iso:country":"BE",
    "sg:address":"Rue Du Vieux Moulin 6",
    "sg:city":"Huy",
    "sg:orig_category":"Instellingen voor mindervalide volwassenen",
    "sg:phone":"+32 85 61 26 70",
    "sg:postcode":"4500",
    "sg:province":"Li\u00e8ge",
    "wof:name":"I.m.p. Le Ch\u00c2teau Vert",
    "wof:placetype":"venue"
},
  "geometry": {"coordinates":[5.17689991,50.4784812927],"type":"Point"}
}