{
  "type": "Feature",
  "properties": {
    "iso:country":"BE",
    "sg:address":"Rue Sigebert 7",
    "sg:city":"Gembloux",
    "sg:orig_category":"M\u00e9decins and sp\u00e9cialistes",
    "sg:phone":"+32 81 61 39 38",
    "sg:postcode":"5030",
    "sg:province":"Namur",
    "wof:name":"Jean-paul Hardy",
    "wof:placetype":"venue"
},
  "geometry": {"coordinates":[4.6982607841,50.5617103577],"type":"Point"}
}