{
  "type": "Feature",
  "properties": {
    "addr:full":"Tervuursesteenweg 379 Bertem Vlaams-Brabant 3061",
    "addr:housenumber":"379",
    "addr:postcode":"3061",
    "addr:street":"Tervuursesteenweg",
    "iso:country":"BE",
    "sg:address":"Tervuursesteenweg 379",
    "sg:city":"Bertem",
    "sg:orig_category":"Installatie van houten of kunststof schrijnwerk",
    "sg:phone":"+32 2 767 21 20",
    "sg:postcode":"3061",
    "sg:province":"Vlaams-Brabant",
    "wof:name":"Wim Smets",
    "wof:placetype":"venue"
},
  "geometry": {"coordinates":[4.5941410065,50.8558311462],"type":"Point"}
}