{
  "type": "Feature",
  "properties": {
    "addr:full":"Rue Egide Van Ophem 16 Ukkel/uccle Bruxelles-Capitale 1180",
    "addr:housenumber":"16",
    "addr:postcode":"1180",
    "addr:street":"Rue Egide Van Ophem;/",
    "iso:country":"BE",
    "sg:address":"Rue Egide Van Ophem 16",
    "sg:city":"Ukkel/uccle",
    "sg:orig_category":"Artistes ind\u00e9pendants",
    "sg:phone":"+32 2 332 02 30",
    "sg:postcode":"1180",
    "sg:province":"Bruxelles-Capitale",
    "wof:name":"Danielle De Fays",
    "wof:placetype":"venue"
},
  "geometry": {"coordinates":[4.3317489624,50.7914543152],"type":"Point"}
}