{
  "type": "Feature",
  "properties": {
    "addr:full":"Rue Des Brasseurs 21 Huy Li\u00e8ge 4500",
    "addr:housenumber":"21",
    "addr:postcode":"4500",
    "addr:street":"Rue Des Brasseurs",
    "iso:country":"BE",
    "sg:address":"Rue Des Brasseurs 21",
    "sg:city":"Huy",
    "sg:classifiers":[
        {
            "category":"Professional",
            "subcategory":"Art Services",
            "type":"Services"
        }
    ],
    "sg:phone":"+32 85 31 89 03",
    "sg:postcode":"4500",
    "sg:province":"Li\u00e8ge",
    "sg:tags":[
        "picture",
        "framer"
    ],
    "wof:name":"Galerie Neteora",
    "wof:placetype":"venue"
},
  "geometry": {"coordinates":[5.2410497665,50.5172386169],"type":"Point"}
}