{
  "type": "Feature",
  "properties": {
    "iso:country":"BE",
    "sg:address":"Chauss\u00e9e Montgomery 1",
    "sg:city":"Rumes",
    "sg:classifiers":[
        {
            "category":"Retail",
            "subcategory":"Auto Repair",
            "type":"Services"
        }
    ],
    "sg:postcode":"7610",
    "sg:province":"Hainaut",
    "sg:tags":[
        "garage"
    ],
    "wof:name":"Vanden-broeck & Fils",
    "wof:placetype":"venue"
},
  "geometry": {"coordinates":[3.2968211174,50.5425453186],"type":"Point"}
}