{
  "type": "Feature",
  "properties": {
    "addr:full":"Volksverheffingsstraat 95 Aalst Oost-Vlaanderen 9300",
    "addr:housenumber":"95",
    "addr:postcode":"9300",
    "addr:street":"Volksverheffingsstraat",
    "iso:country":"BE",
    "sg:address":"Volksverheffingsstraat 95",
    "sg:city":"Aalst",
    "sg:orig_category":"Sportcentra",
    "sg:phone":"+32 53 77 74 90",
    "sg:postcode":"9300",
    "sg:province":"Oost-Vlaanderen",
    "wof:name":"Yoga Vendata",
    "wof:placetype":"venue"
},
  "geometry": {"coordinates":[4.0249319077,50.9422531128],"type":"Point"}
}