{
  "type": "Feature",
  "properties": {
    "addr:full":"Toleindestraat 23a Lochristi (beervelde) Oost-Vlaanderen 9080",
    "addr:housenumber":"23a",
    "addr:postcode":"9080",
    "addr:street":"Toleindestraat",
    "iso:country":"BE",
    "sg:address":"Toleindestraat 23a",
    "sg:city":"Lochristi (beervelde)",
    "sg:classifiers":[
        {
            "category":"Health Services",
            "subcategory":"Health Practitioner",
            "type":"Services"
        }
    ],
    "sg:phone":"+32 9 356 63 46",
    "sg:postcode":"9080",
    "sg:province":"Oost-Vlaanderen",
    "sg:tags":[
        "physiotherapist"
    ],
    "wof:name":"Van De Sompel Gunter",
    "wof:placetype":"venue"
},
  "geometry": {"coordinates":[3.8828830719,51.0803413391],"type":"Point"}
}