{
  "type": "Feature",
  "properties": {
    "iso:country":"BE",
    "sg:address":"Ferdinand Maesstraat 50",
    "sg:city":"Kontich (waarloos)",
    "sg:orig_category":"Newspapers, magazines, periodicals - Distribution",
    "sg:phone":"+32 15 31 16 27",
    "sg:postcode":"2550",
    "sg:province":"Antwerpen",
    "wof:name":"Jusha Bvba",
    "wof:placetype":"venue"
},
  "geometry": {"coordinates":[4.4536561966,51.1058959961],"type":"Point"}
}