{
  "type": "Feature",
  "properties": {
    "iso:country":"BE",
    "sg:address":"Herdelijkestraat 26",
    "sg:city":"Moeskroen/mouscron",
    "sg:orig_category":"Sociale huisvestingsmaatschappijen",
    "sg:phone":"+32 56 48 73 33",
    "sg:postcode":"7711",
    "sg:province":"Hainaut",
    "wof:name":"Le Foyer Dottignien",
    "wof:placetype":"venue"
},
  "geometry": {"coordinates":[3.3035650253,50.7287254333],"type":"Point"}
}