{
  "type": "Feature",
  "properties": {
    "iso:country":"BE",
    "sg:address":"Route De Neufchateau 512",
    "sg:city":"Arlon",
    "sg:orig_category":"Dierenartsen",
    "sg:phone":"+32 63 23 45 55",
    "sg:postcode":"6700",
    "sg:province":"Luxembourg",
    "wof:name":"Muriel Jamotton",
    "wof:placetype":"venue"
},
  "geometry": {"coordinates":[5.8042387962,49.689666748],"type":"Point"}
}