{
  "type": "Feature",
  "properties": {
    "addr:full":"Avenue Du Parc 126 Bruxelles (forest) Bruxelles-Capitale 1190",
    "addr:housenumber":"126",
    "addr:postcode":"1190",
    "addr:street":"Avenue Du Parc",
    "iso:country":"BE",
    "sg:address":"Avenue Du Parc 126",
    "sg:city":"Bruxelles (forest)",
    "sg:classifiers":[
        {
            "category":"Transit Center",
            "subcategory":"Freight",
            "type":"Transportation"
        }
    ],
    "sg:phone":"+32 2 537 22 33",
    "sg:postcode":"1190",
    "sg:province":"Bruxelles-Capitale",
    "sg:tags":[
        "import",
        "export",
        "-"
    ],
    "wof:name":"Sopromat Sa",
    "wof:placetype":"venue"
},
  "geometry": {"coordinates":[4.3384509087,50.8250007629],"type":"Point"}
}