{
  "type": "Feature",
  "properties": {
    "addr:full":"Zakstraat 42 Sint-niklaas Oost-Vlaanderen 9112",
    "addr:housenumber":"42",
    "addr:postcode":"9112",
    "addr:street":"Zakstraat",
    "iso:country":"BE",
    "sg:address":"Zakstraat 42",
    "sg:city":"Sint-niklaas",
    "sg:orig_category":"Meubles D\u00e9taillants, Am\u00e9nagement de B\u00e2timents et de Cuisines",
    "sg:phone":"+32 3 772 45 98",
    "sg:postcode":"9112",
    "sg:province":"Oost-Vlaanderen",
    "wof:name":"Van Krinkelen",
    "wof:placetype":"venue"
},
  "geometry": {"coordinates":[4.032749176,51.1492271423],"type":"Point"}
}