{
  "type": "Feature",
  "properties": {
    "iso:country":"BE",
    "sg:address":"Beelbroekstraat 40",
    "sg:city":"Gent",
    "sg:orig_category":"Afbraak- and draineerwerken",
    "sg:phone":"+32 9 228 40 24",
    "sg:postcode":"9040",
    "sg:province":"Oost-Vlaanderen",
    "wof:name":"De Neve R",
    "wof:placetype":"venue"
},
  "geometry": {"coordinates":[3.7845768929,51.0700263977],"type":"Point"}
}