{
  "type": "Feature",
  "properties": {
    "iso:country":"BE",
    "sg:address":"Sint-willebrordusstraat 63",
    "sg:city":"Brecht",
    "sg:classifiers":[
        {
            "category":"Autos & Motor Vehicles",
            "subcategory":"Auto Supplies",
            "type":"Retail Goods"
        }
    ],
    "sg:phone":"+32 3 663 22 00",
    "sg:postcode":"2960",
    "sg:province":"Antwerpen",
    "sg:tags":[
        "automobile",
        "-",
        "enamel"
    ],
    "wof:name":"Overbroekse Verfcentrale",
    "wof:placetype":"venue"
},
  "geometry": {"coordinates":[4.5997247696,51.342754364],"type":"Point"}
}