{
  "type": "Feature",
  "properties": {
    "addr:full":"Esenstr 48 Zarren West-Vlaanderen 8610",
    "addr:housenumber":"48",
    "addr:postcode":"8610",
    "addr:street":"Esenstr;West-Vlaanderen",
    "iso:country":"BE",
    "sg:address":"Esenstr 48",
    "sg:city":"Zarren",
    "sg:classifiers":[
        {
            "category":"Food & Beverages",
            "subcategory":"Meat & Fish",
            "type":"Retail Goods"
        }
    ],
    "sg:phone":"+32 51 56 60 74",
    "sg:postcode":"8610",
    "sg:province":"West-Vlaanderen",
    "sg:tags":[
        "preserve",
        "cooked",
        "product",
        "related"
    ],
    "wof:name":"Vannieuwenhuyse Nv",
    "wof:placetype":"venue"
},
  "geometry": {"coordinates":[2.9546821117,51.0173683167],"type":"Point"}
}