{
  "type": "Feature",
  "properties": {
    "addr:full":"Staakstraat 85ba Assenede Oost-Vlaanderen 9960",
    "addr:housenumber":"85ba",
    "addr:postcode":"9960",
    "addr:street":"Staakstraat",
    "iso:country":"BE",
    "sg:address":"Staakstraat 85ba",
    "sg:city":"Assenede",
    "sg:orig_category":"Enseignement maternel and primaire",
    "sg:phone":"+32 9 344 68 27",
    "sg:postcode":"9960",
    "sg:province":"Oost-Vlaanderen",
    "wof:name":"Vrije Kleuterschool",
    "wof:placetype":"venue"
},
  "geometry": {"coordinates":[3.7785899639,51.2252578735],"type":"Point"}
}