{
  "type": "Feature",
  "properties": {
    "iso:country":"BE",
    "sg:address":"Zoning Du Pont De Warche 1",
    "sg:city":"Malmedy",
    "sg:orig_category":"Onderdelen and accessoires voor auto's",
    "sg:phone":"+32 80 33 92 05",
    "sg:postcode":"4960",
    "sg:province":"Li\u00e8ge",
    "wof:name":"V.p.pneus",
    "wof:placetype":"venue"
},
  "geometry": {"coordinates":[6.0085859299,50.4198074341],"type":"Point"}
}