{
  "type": "Feature",
  "properties": {
    "addr:full":"Rue Des Deux Rys 33 Manhay (harre) Luxembourg 6960",
    "addr:housenumber":"33",
    "addr:postcode":"6960",
    "addr:street":"Rue Des Deux Rys",
    "iso:country":"BE",
    "sg:address":"Rue Des Deux Rys 33",
    "sg:city":"Manhay (harre)",
    "sg:classifiers":[
        {
            "category":"Manufacturing",
            "subcategory":"Furniture",
            "type":"Manufacturing & Wholesale Goods"
        }
    ],
    "sg:phone":"+32 86 49 90 00",
    "sg:postcode":"6960",
    "sg:province":"Luxembourg",
    "sg:tags":[
        "made",
        "-",
        "custom"
    ],
    "wof:name":"Mar\u00e9chal P",
    "wof:placetype":"venue"
},
  "geometry": {"coordinates":[5.6754698753,50.291759491],"type":"Point"}
}