{
  "type": "Feature",
  "properties": {
    "iso:country":"BE",
    "sg:address":"Winterkoninkjestraat 22",
    "sg:city":"Watermaal-bosvoorde/watermael-boitsfort",
    "sg:orig_category":"Industri\u00eble wasserijen and droogkuis",
    "sg:phone":"+32 2 673 97 75",
    "sg:postcode":"1170",
    "sg:province":"Bruxelles-Capitale",
    "wof:name":"Dust Carpet Clean. Mahaut",
    "wof:placetype":"venue"
},
  "geometry": {"coordinates":[4.4013152122,50.8092384338],"type":"Point"}
}