{
  "type": "Feature",
  "properties": {
    "addr:full":"Plaanstraat 1 Nazareth Oost-Vlaanderen 9810",
    "addr:housenumber":"1",
    "addr:postcode":"9810",
    "addr:street":"Plaanstraat",
    "iso:country":"BE",
    "sg:address":"Plaanstraat 1",
    "sg:city":"Nazareth",
    "sg:orig_category":"Travaux d\u00b4installation divers. Forages and sondages. Constructions non r\u00e9sidentielles sp\u00e9cifiques",
    "sg:phone":"+32 9 385 84 00",
    "sg:postcode":"9810",
    "sg:province":"Oost-Vlaanderen",
    "wof:name":"Geolab",
    "wof:placetype":"venue"
},
  "geometry": {"coordinates":[3.642070055,50.9606895447],"type":"Point"}
}