{
  "type": "Feature",
  "properties": {
    "iso:country":"BE",
    "sg:address":"Faubourg De Mons 1",
    "sg:city":"Nivelles",
    "sg:orig_category":"Sportterreinen and installaties behalve sportcentra",
    "sg:phone":"+32 67 21 91 67",
    "sg:postcode":"1400",
    "sg:province":"Brabant Wallon",
    "wof:name":"Sal.sport.col.st.gertrude",
    "wof:placetype":"venue"
},
  "geometry": {"coordinates":[4.3147611618,50.5904388428],"type":"Point"}
}