{
  "type": "Feature",
  "properties": {
    "addr:full":"Minimenstraat 17 Brussel/bruxelles Bruxelles-Capitale 1000",
    "addr:housenumber":"17",
    "addr:postcode":"1000",
    "addr:street":"Minimenstraat;/",
    "iso:country":"BE",
    "sg:address":"Minimenstraat 17",
    "sg:city":"Brussel/bruxelles",
    "sg:orig_category":"Antiek Diverse zakelijke dienstverlening",
    "sg:phone":"+32 2 511 65 39",
    "sg:postcode":"1000",
    "sg:province":"Bruxelles-Capitale",
    "wof:name":"Galerie Harmakhis",
    "wof:placetype":"venue"
},
  "geometry": {"coordinates":[4.3533987999,50.8408927917],"type":"Point"}
}