{
  "type": "Feature",
  "properties": {
    "addr:full":"Rue Paul Pastur 9b Quaregnon Hainaut 7390",
    "addr:housenumber":"9b",
    "addr:postcode":"7390",
    "addr:street":"Rue Paul Pastur",
    "iso:country":"BE",
    "sg:address":"Rue Paul Pastur 9b",
    "sg:city":"Quaregnon",
    "sg:classifiers":[
        {
            "category":"Military Area",
            "subcategory":"Air Force Base",
            "type":"Public Place"
        }
    ],
    "sg:phone":"+32 65 78 70 06",
    "sg:postcode":"7390",
    "sg:province":"Hainaut",
    "sg:tags":[
        "herb",
        "-",
        "medicinal"
    ],
    "wof:name":"Maison Des Plantes",
    "wof:placetype":"venue"
},
  "geometry": {"coordinates":[3.8645200729,50.4450302124],"type":"Point"}
}