{
  "type": "Feature",
  "properties": {
    "iso:country":"BE",
    "sg:address":"Ter Stratenweg 40",
    "sg:city":"Ranst",
    "sg:orig_category":"Installatie van houten of kunststof schrijnwerk Installatie van metalen schrijnwerk",
    "sg:phone":"+32 3 475 20 49",
    "sg:postcode":"2520",
    "sg:province":"Antwerpen",
    "wof:name":"Antwerp Window Line",
    "wof:placetype":"venue"
},
  "geometry": {"coordinates":[4.5822367668,51.2095870972],"type":"Point"}
}