{
  "type": "Feature",
  "properties": {
    "iso:country":"BE",
    "sg:address":"Kerkstraat 310",
    "sg:city":"Blankenberge",
    "sg:orig_category":"Dameskledingzaken Herenkledingzaken Industri\u00eble wasserijen and droogkuis",
    "sg:phone":"+32 50 41 76 63",
    "sg:postcode":"8370",
    "sg:province":"West-Vlaanderen",
    "wof:name":"Droogkuis Aneca-st.andr\u00c9",
    "wof:placetype":"venue"
},
  "geometry": {"coordinates":[3.1399669647,51.3064155579],"type":"Point"}
}