{
  "type": "Feature",
  "properties": {
    "addr:full":"Roerdomplei 32 Kapellen Antwerpen 2950",
    "addr:housenumber":"32",
    "addr:postcode":"2950",
    "addr:street":"Roerdomplei",
    "iso:country":"BE",
    "sg:address":"Roerdomplei 32",
    "sg:city":"Kapellen",
    "sg:orig_category":"Diensten voor huisdieren Diverse organisaties and verenigingen",
    "sg:phone":"+32 3 666 96 18",
    "sg:postcode":"2950",
    "sg:province":"Antwerpen",
    "wof:name":"\u00b4t Poezennestje",
    "wof:placetype":"venue"
},
  "geometry": {"coordinates":[4.4806261063,51.3407096863],"type":"Point"}
}