{
  "type": "Feature",
  "properties": {
    "iso:country":"BE",
    "sg:address":"Maria Pypelinxstraat 19",
    "sg:city":"Hasselt",
    "sg:orig_category":"Services pour animaux domestiques",
    "sg:phone":"+32 11 25 00 15",
    "sg:postcode":"3511",
    "sg:province":"Limburg",
    "wof:name":"Babeth",
    "wof:placetype":"venue"
},
  "geometry": {"coordinates":[5.3013930321,50.9428520203],"type":"Point"}
}