{
  "type": "Feature",
  "properties": {
    "addr:full":"Place Peter Benoit 34c Brussel/bruxelles Bruxelles-Capitale 1120",
    "addr:housenumber":"34c",
    "addr:postcode":"1120",
    "addr:street":"Place Peter Benoit;/",
    "iso:country":"BE",
    "sg:address":"Place Peter Benoit 34c",
    "sg:city":"Brussel/bruxelles",
    "sg:orig_category":"Banques and organismes de cr\u00e9dit",
    "sg:phone":"+32 2 268 58 81",
    "sg:postcode":"1120",
    "sg:province":"Bruxelles-Capitale",
    "wof:name":"Bacob",
    "wof:placetype":"venue"
},
  "geometry": {"coordinates":[4.3887848854,50.8958358765],"type":"Point"}
}