{
  "type": "Feature",
  "properties": {
    "addr:full":"Brabantsebaan 373 Sint-pieters-leeuw Vlaams-Brabant 1600",
    "addr:housenumber":"373",
    "addr:postcode":"1600",
    "addr:street":"Brabantsebaan",
    "iso:country":"BE",
    "sg:address":"Brabantsebaan 373",
    "sg:city":"Sint-pieters-leeuw",
    "sg:classifiers":[
        {
            "category":"Social Services",
            "subcategory":"Job Training",
            "type":"Services"
        }
    ],
    "sg:phone":"+32 2 532 35 81",
    "sg:postcode":"1600",
    "sg:province":"Vlaams-Brabant",
    "sg:tags":[
        "personnel"
    ],
    "wof:name":"Telecoaching",
    "wof:placetype":"venue"
},
  "geometry": {"coordinates":[4.2103099823,50.7826805115],"type":"Point"}
}