{
  "type": "Feature",
  "properties": {
    "addr:full":"Rue Des B\u00e9guines 2 Vis\u00e9 Li\u00e8ge 4600",
    "addr:housenumber":"2",
    "addr:postcode":"4600",
    "addr:street":"Rue Des Be\u0301Guines",
    "iso:country":"BE",
    "sg:address":"Rue Des B\u00e9guines 2",
    "sg:city":"Vis\u00e9",
    "sg:classifiers":[
        {
            "category":"Professional",
            "subcategory":"Computer Services",
            "type":"Services"
        }
    ],
    "sg:phone":"+32 4 379 79 41",
    "sg:postcode":"4600",
    "sg:province":"Li\u00e8ge",
    "sg:tags":[
        "-",
        "processing",
        "data",
        "software"
    ],
    "wof:name":"Ibex",
    "wof:placetype":"venue"
},
  "geometry": {"coordinates":[5.6940631866,50.7358703613],"type":"Point"}
}