{
  "type": "Feature",
  "properties": {
    "addr:full":"Rue Montavaux 155 Frameries Hainaut 7080",
    "addr:housenumber":"155",
    "addr:postcode":"7080",
    "addr:street":"Rue Montavaux",
    "iso:country":"BE",
    "sg:address":"Rue Montavaux 155",
    "sg:city":"Frameries",
    "sg:classifiers":[
        {
            "category":"Real Estate",
            "subcategory":"Real Estate Services",
            "type":"Services"
        }
    ],
    "sg:phone":"+32 65 66 29 00",
    "sg:postcode":"7080",
    "sg:province":"Hainaut",
    "wof:name":"Immobiliere Des Quatre Seigneux",
    "wof:placetype":"venue"
},
  "geometry": {"coordinates":[3.9116399288,50.4075508118],"type":"Point"}
}