{
  "type": "Feature",
  "properties": {
    "addr:full":"Stationsstraat Neerpelt Limburg 3910",
    "addr:postcode":"3910",
    "addr:street":"Stationsstraat",
    "iso:country":"BE",
    "sg:address":"Stationsstraat",
    "sg:city":"Neerpelt",
    "sg:classifiers":[
        {
            "category":"Fast Food",
            "type":"Food & Drink"
        }
    ],
    "sg:phone":"+32 11 64 26 53",
    "sg:postcode":"3910",
    "sg:province":"Limburg",
    "sg:tags":[
        "fried",
        "stand",
        "potato"
    ],
    "wof:name":"Guy Frituur",
    "wof:placetype":"venue"
},
  "geometry": {"coordinates":[5.434899807,51.2277908325],"type":"Point"}
}