{
  "type": "Feature",
  "properties": {
    "addr:full":"Rollegemstraat 8 Ledegem West-Vlaanderen 8880",
    "addr:housenumber":"8",
    "addr:postcode":"8880",
    "addr:street":"Rollegemstraat",
    "iso:country":"BE",
    "sg:address":"Rollegemstraat 8",
    "sg:city":"Ledegem",
    "sg:classifiers":[
        {
            "category":"Cafe",
            "type":"Food & Drink"
        }
    ],
    "sg:phone":"+32 56 50 28 21",
    "sg:postcode":"8880",
    "sg:province":"West-Vlaanderen",
    "sg:tags":[
        "caf\u00e9s"
    ],
    "wof:name":"Corneillie & Goddeeris",
    "wof:placetype":"venue"
},
  "geometry": {"coordinates":[3.1272609234,50.8547706604],"type":"Point"}
}