{
  "type": "Feature",
  "properties": {
    "iso:country":"BE",
    "sg:address":"Avenue D'hyon 105",
    "sg:city":"Mons",
    "sg:classifiers":[
        {
            "category":"Personal",
            "subcategory":"Beauty Salon",
            "type":"Services"
        }
    ],
    "sg:phone":"+32 65 34 61 81",
    "sg:postcode":"7000",
    "sg:province":"Hainaut",
    "sg:tags":[
        "de",
        "coiffure"
    ],
    "wof:name":"Coiffure Cr\u00c9a-style",
    "wof:placetype":"venue"
},
  "geometry": {"coordinates":[3.9553821087,50.4447135925],"type":"Point"}
}