{
  "type": "Feature",
  "properties": {
    "iso:country":"BE",
    "sg:address":"Charleroise Steenweg 258ba",
    "sg:city":"Sint-gillis/saint-gilles",
    "sg:orig_category":"Diverse kredietdiensten",
    "sg:postcode":"1060",
    "sg:province":"Bruxelles-Capitale",
    "wof:name":"Bancontact-mister Cash",
    "wof:placetype":"venue"
},
  "geometry": {"coordinates":[4.3539609909,50.8229141235],"type":"Point"}
}