{
  "type": "Feature",
  "properties": {
    "addr:full":"Bavelstraat 35 Rijkevorsel Antwerpen 2310",
    "addr:housenumber":"35",
    "addr:postcode":"2310",
    "addr:street":"Bavelstraat",
    "iso:country":"BE",
    "sg:address":"Bavelstraat 35",
    "sg:city":"Rijkevorsel",
    "sg:orig_category":"Non-Classified Establishments",
    "sg:phone":"+32 3 314 93 48",
    "sg:postcode":"2310",
    "sg:province":"Antwerpen",
    "wof:name":"Lady Bird",
    "wof:placetype":"venue"
},
  "geometry": {"coordinates":[4.7624697685,51.351436615],"type":"Point"}
}