{
  "type": "Feature",
  "properties": {
    "addr:full":"Hombeeksesteenweg 225 Mechelen Antwerpen 2800",
    "addr:housenumber":"225",
    "addr:postcode":"2800",
    "addr:street":"Hombeeksesteenweg",
    "iso:country":"BE",
    "sg:address":"Hombeeksesteenweg 225",
    "sg:city":"Mechelen",
    "sg:orig_category":"Voedingsspeciaalzaken",
    "sg:phone":"+32 15 41 59 56",
    "sg:postcode":"2800",
    "sg:province":"Antwerpen",
    "wof:name":"Herman Dockx",
    "wof:placetype":"venue"
},
  "geometry": {"coordinates":[4.4659070969,51.0167732239],"type":"Point"}
}