{
  "type": "Feature",
  "properties": {
    "iso:country":"BE",
    "sg:address":"Roterijstraat 18",
    "sg:city":"Deerlijk",
    "sg:orig_category":"Boomkwekerijen",
    "sg:phone":"+32 56 71 78 76",
    "sg:postcode":"8540",
    "sg:province":"West-Vlaanderen",
    "wof:name":"Dirk Benoit",
    "wof:placetype":"venue"
},
  "geometry": {"coordinates":[3.3469099998,50.8507118225],"type":"Point"}
}