{
  "type": "Feature",
  "properties": {
    "iso:country":"BE",
    "sg:address":"Rue De Robiano 23",
    "sg:city":"Binche",
    "sg:orig_category":"Opticiens",
    "sg:phone":"+32 64 33 15 64",
    "sg:postcode":"7130",
    "sg:province":"Hainaut",
    "wof:name":"Jean-marie Vervaeren",
    "wof:placetype":"venue"
},
  "geometry": {"coordinates":[4.1679987907,50.4108047485],"type":"Point"}
}