{
  "type": "Feature",
  "properties": {
    "addr:full":"Rue De L'amiti\u00c9 152 Herstal Li\u00e8ge 4041",
    "addr:housenumber":"152",
    "addr:postcode":"4041",
    "addr:street":"Rue De L'Amitie \u0301",
    "iso:country":"BE",
    "sg:address":"Rue De L'amiti\u00c9 152",
    "sg:city":"Herstal",
    "sg:classifiers":[
        {
            "category":"Food & Beverages",
            "subcategory":"Fruits & Vegetables",
            "type":"Retail Goods"
        }
    ],
    "sg:phone":"+32 4 278 52 64",
    "sg:postcode":"4041",
    "sg:province":"Li\u00e8ge",
    "sg:tags":[
        "groenten"
    ],
    "wof:name":"Jean-marie Talbot",
    "wof:placetype":"venue"
},
  "geometry": {"coordinates":[5.598405838,50.6825408936],"type":"Point"}
}