{
  "type": "Feature",
  "properties": {
    "addr:full":"Rue Des Arbalestriers 8 Mons Hainaut 7000",
    "addr:housenumber":"8",
    "addr:postcode":"7000",
    "addr:street":"Rue Des Arbalestriers;Hainaut",
    "iso:country":"BE",
    "sg:address":"Rue Des Arbalestriers 8",
    "sg:city":"Mons",
    "sg:classifiers":[
        {
            "category":"Arts & Performance",
            "subcategory":"Theater",
            "type":"Entertainment"
        }
    ],
    "sg:phone":"+32 65 35 56 64",
    "sg:postcode":"7000",
    "sg:province":"Hainaut",
    "sg:tags":[
        "group",
        "theatre"
    ],
    "wof:name":"As Palavras Cie Claudio Bernardo",
    "wof:placetype":"venue"
},
  "geometry": {"coordinates":[3.9594600201,50.455493927],"type":"Point"}
}