{
  "type": "Feature",
  "properties": {
    "iso:country":"BE",
    "sg:address":"Gouv. A. Galopinstraat 46",
    "sg:city":"Genk",
    "sg:orig_category":"Huishoudapparaten, televisies and radio's",
    "sg:phone":"+32 89 38 46 43",
    "sg:postcode":"3600",
    "sg:province":"Limburg",
    "wof:name":"Ahmet Kelleci",
    "wof:placetype":"venue"
},
  "geometry": {"coordinates":[5.5024781227,51.0060005188],"type":"Point"}
}