{
  "type": "Feature",
  "properties": {
    "iso:country":"BE",
    "sg:address":"Merksplasseweg 1",
    "sg:city":"Beerse",
    "sg:classifiers":[
        {
            "category":"Arts & Performance",
            "subcategory":"Art Gallery",
            "type":"Entertainment"
        }
    ],
    "sg:phone":"+32 14 61 56 09",
    "sg:postcode":"2340",
    "sg:province":"Antwerpen",
    "wof:name":"Marmerhuis",
    "wof:placetype":"venue"
},
  "geometry": {"coordinates":[4.855246067,51.3286819458],"type":"Point"}
}