{
  "type": "Feature",
  "properties": {
    "addr:full":"Lippenslaan 81 Knokke-heist West-Vlaanderen 8300",
    "addr:housenumber":"81",
    "addr:postcode":"8300",
    "addr:street":"Lippenslaan",
    "iso:country":"BE",
    "sg:address":"Lippenslaan 81",
    "sg:city":"Knokke-heist",
    "sg:orig_category":"Agences d\u00b4interim and personnel temporaire",
    "sg:phone":"+32 50 62 71 17",
    "sg:postcode":"8300",
    "sg:province":"West-Vlaanderen",
    "wof:name":"Daoust Interim",
    "wof:placetype":"venue"
},
  "geometry": {"coordinates":[3.2878201008,51.3439064026],"type":"Point"}
}