{
  "type": "Feature",
  "properties": {
    "iso:country":"BE",
    "sg:address":"Stoppelveld 27",
    "sg:city":"Zoersel",
    "sg:classifiers":[
        {
            "category":"Personal",
            "subcategory":"Beauty Salon",
            "type":"Services"
        }
    ],
    "sg:phone":"+32 495 24 07 80",
    "sg:postcode":"2980",
    "sg:province":"Antwerpen",
    "wof:name":"Vanhoey T",
    "wof:placetype":"venue"
},
  "geometry": {"coordinates":[4.713435173,51.269985199],"type":"Point"}
}