{
  "type": "Feature",
  "properties": {
    "addr:full":"Groenestraat 10 Kortemark West-Vlaanderen 8610",
    "addr:housenumber":"10",
    "addr:postcode":"8610",
    "addr:street":"Groenestraat",
    "iso:country":"BE",
    "sg:address":"Groenestraat 10",
    "sg:city":"Kortemark",
    "sg:classifiers":[
        {
            "category":"Personal",
            "subcategory":"Beauty Salon",
            "type":"Services"
        }
    ],
    "sg:phone":"+32 51 56 83 61",
    "sg:postcode":"8610",
    "sg:province":"West-Vlaanderen",
    "sg:tags":[
        "lady",
        "-",
        "hairdressing"
    ],
    "wof:name":"Johan",
    "wof:placetype":"venue"
},
  "geometry": {"coordinates":[3.004308939,51.0177993774],"type":"Point"}
}