{
  "type": "Feature",
  "properties": {
    "addr:full":"Magdalena Vermeeschlaan 27 Hove Antwerpen 2540",
    "addr:housenumber":"27",
    "addr:postcode":"2540",
    "addr:street":"Magdalena Vermeeschlaan",
    "iso:country":"BE",
    "sg:address":"Magdalena Vermeeschlaan 27",
    "sg:city":"Hove",
    "sg:orig_category":"Apotheken",
    "sg:phone":"+32 3 455 99 24",
    "sg:postcode":"2540",
    "sg:province":"Antwerpen",
    "wof:name":"Godelieve Embrechts",
    "wof:placetype":"venue"
},
  "geometry": {"coordinates":[4.4811449051,51.1440620422],"type":"Point"}
}