{
  "type": "Feature",
  "properties": {
    "addr:full":"Oude Brugstraat 7 Dendermonde Oost-Vlaanderen 9200",
    "addr:housenumber":"7",
    "addr:postcode":"9200",
    "addr:street":"Oude Brugstraat;Oost-Vlaanderen",
    "iso:country":"BE",
    "sg:address":"Oude Brugstraat 7",
    "sg:city":"Dendermonde",
    "sg:orig_category":"Landbouwmachines Gh",
    "sg:phone":"+32 52 43 29 43",
    "sg:postcode":"9200",
    "sg:province":"Oost-Vlaanderen",
    "wof:name":"Multiplast",
    "wof:placetype":"venue"
},
  "geometry": {"coordinates":[4.0751438141,51.0173454285],"type":"Point"}
}