{
  "type": "Feature",
  "properties": {
    "iso:country":"BE",
    "sg:address":"Rue Emile Vandervelde 2",
    "sg:city":"Charleroi",
    "sg:orig_category":"HERSTELLING ELEKTRISCHE HUISHOUDAPPARATEN Herstelling aan huis van elektrische huishoudapparaten Hui",
    "sg:phone":"+32 71 43 77 87",
    "sg:postcode":"6010",
    "sg:province":"Hainaut",
    "wof:name":"Jaumain Tiercet",
    "wof:placetype":"venue"
},
  "geometry": {"coordinates":[4.4689741135,50.3915901184],"type":"Point"}
}