{
  "type": "Feature",
  "properties": {
    "addr:full":"Bosdam 61 Lochristi (zaffelare) Oost-Vlaanderen 9080",
    "addr:housenumber":"61",
    "addr:postcode":"9080",
    "addr:street":"Bosdam",
    "iso:country":"BE",
    "sg:address":"Bosdam 61",
    "sg:city":"Lochristi (zaffelare)",
    "sg:classifiers":[
        {
            "category":"Health Services",
            "subcategory":"Health Practitioner",
            "type":"Services"
        }
    ],
    "sg:phone":"+32 9 355 20 01",
    "sg:postcode":"9080",
    "sg:province":"Oost-Vlaanderen",
    "sg:tags":[
        "physiotherapist"
    ],
    "wof:name":"Praet Katrien",
    "wof:placetype":"venue"
},
  "geometry": {"coordinates":[3.844014883,51.0891990662],"type":"Point"}
}