{
  "type": "Feature",
  "properties": {
    "addr:full":"L\u00c9on Scheurvest 7 Leuven Vlaams-Brabant 3001",
    "addr:housenumber":"7",
    "addr:postcode":"3001",
    "iso:country":"BE",
    "sg:address":"L\u00c9on Scheurvest 7",
    "sg:city":"Leuven",
    "sg:orig_category":"Evaluation and estimation de biens immobiliers",
    "sg:phone":"+32 16 31 93 93",
    "sg:postcode":"3001",
    "sg:province":"Vlaams-Brabant",
    "wof:name":"Dynamic Invest",
    "wof:placetype":"venue"
},
  "geometry": {"coordinates":[4.714577198,50.8731117249],"type":"Point"}
}