{
  "type": "Feature",
  "properties": {
    "addr:full":"Brusselsesteenweg 258 Melle Oost-Vlaanderen 9090",
    "addr:housenumber":"258",
    "addr:postcode":"9090",
    "addr:street":"Brusselsesteenweg",
    "iso:country":"BE",
    "sg:address":"Brusselsesteenweg 258",
    "sg:city":"Melle",
    "sg:classifiers":[
        {
            "category":"Wholesale",
            "subcategory":"Plants",
            "type":"Manufacturing & Wholesale Goods"
        }
    ],
    "sg:phone":"+32 9 252 13 65",
    "sg:postcode":"9090",
    "sg:province":"Oost-Vlaanderen",
    "sg:tags":[
        "whol",
        "flower",
        "-",
        "grower"
    ],
    "wof:name":"Langerock L",
    "wof:placetype":"venue"
},
  "geometry": {"coordinates":[3.8037409782,51.0016174316],"type":"Point"}
}