{
  "type": "Feature",
  "properties": {
    "addr:full":"Berkenlaan 39 Grimbergen Vlaams-Brabant 1850",
    "addr:housenumber":"39",
    "addr:postcode":"1850",
    "addr:street":"Berkenlaan",
    "iso:country":"BE",
    "sg:address":"Berkenlaan 39",
    "sg:city":"Grimbergen",
    "sg:orig_category":"Artsen and specialisten",
    "sg:phone":"+32 2 253 37 83",
    "sg:postcode":"1850",
    "sg:province":"Vlaams-Brabant",
    "wof:name":"M. Kazemien",
    "wof:placetype":"venue"
},
  "geometry": {"coordinates":[4.3837971687,50.9201049805],"type":"Point"}
}