{
  "type": "Feature",
  "properties": {
    "iso:country":"BE",
    "sg:address":"Avenue Reine Astrid 71 Box 11",
    "sg:city":"Namur",
    "sg:classifiers":[
        {
            "category":"Shopping",
            "subcategory":"Baby Store",
            "type":"Retail Goods"
        }
    ],
    "sg:phone":"+32 81 43 59 91",
    "sg:postcode":"5000",
    "sg:province":"Namur",
    "sg:tags":[
        "midwife"
    ],
    "wof:name":"Roger C",
    "wof:placetype":"venue"
},
  "geometry": {"coordinates":[4.8540000916,50.462688446],"type":"Point"}
}