{
  "type": "Feature",
  "properties": {
    "addr:full":"Kruisveld 30 Londerzeel Vlaams-Brabant 1840",
    "addr:housenumber":"30",
    "addr:postcode":"1840",
    "addr:street":"Kruisveld",
    "iso:country":"BE",
    "sg:address":"Kruisveld 30",
    "sg:city":"Londerzeel",
    "sg:orig_category":"Bouwmaterialen Gh",
    "sg:phone":"+32 52 30 10 19",
    "sg:postcode":"1840",
    "sg:province":"Vlaams-Brabant",
    "wof:name":"Technicas",
    "wof:placetype":"venue"
},
  "geometry": {"coordinates":[4.2903580666,51.0102653503],"type":"Point"}
}