{
  "type": "Feature",
  "properties": {
    "addr:full":"Ijzerlaan 6 Antwerpen Antwerpen 2060",
    "addr:housenumber":"6",
    "addr:postcode":"2060",
    "addr:street":"Ijzerlaan",
    "iso:country":"BE",
    "sg:address":"Ijzerlaan 6",
    "sg:city":"Antwerpen",
    "sg:orig_category":"Entretien and r\u00e9parations de voitures. D\u00e9taillants en pi\u00e8ces and accessoires de voitures",
    "sg:phone":"+32 3 231 12 50",
    "sg:postcode":"2060",
    "sg:province":"Antwerpen",
    "wof:name":"Midas",
    "wof:placetype":"venue"
},
  "geometry": {"coordinates":[4.4228739738,51.2355728149],"type":"Point"}
}