{
  "type": "Feature",
  "properties": {
    "iso:country":"BE",
    "sg:address":"Donkerstraat 48",
    "sg:city":"Lennik",
    "sg:orig_category":"V\u00e9t\u00e9rinaires",
    "sg:phone":"+32 2 532 27 65",
    "sg:postcode":"1750",
    "sg:province":"Vlaams-Brabant",
    "wof:name":"P. De Meuter",
    "wof:placetype":"venue"
},
  "geometry": {"coordinates":[4.1868700981,50.7983398438],"type":"Point"}
}