{
  "type": "Feature",
  "properties": {
    "iso:country":"BE",
    "sg:address":"Ahornlaan 24",
    "sg:city":"Gent (mariakerke)",
    "sg:classifiers":[
        {
            "category":"Health Services",
            "subcategory":"Doctor",
            "type":"Services"
        }
    ],
    "sg:phone":"+32 9 226 28 90",
    "sg:postcode":"9030",
    "sg:province":"Oost-Vlaanderen",
    "sg:tags":[
        "medicinephysicians",
        "surgeon"
    ],
    "wof:name":"De Paepe Peter",
    "wof:placetype":"venue"
},
  "geometry": {"coordinates":[3.6904690266,51.0751647949],"type":"Point"}
}