{
  "type": "Feature",
  "properties": {
    "addr:full":"Rue De L'incroyable 109 Colfontaine (wasmes) Hainaut 7340",
    "addr:housenumber":"109",
    "addr:postcode":"7340",
    "addr:street":"Rue De L'Incroyable",
    "iso:country":"BE",
    "sg:address":"Rue De L'incroyable 109",
    "sg:city":"Colfontaine (wasmes)",
    "sg:classifiers":[
        {
            "category":"Building & Trades",
            "subcategory":"Construction",
            "type":"Services"
        }
    ],
    "sg:phone":"+32 65 67 30 15",
    "sg:postcode":"7340",
    "sg:province":"Hainaut",
    "sg:tags":[
        "installation",
        "-",
        "central",
        "heating"
    ],
    "wof:name":"Alyxel Sprl",
    "wof:placetype":"venue"
},
  "geometry": {"coordinates":[3.8542408943,50.4101371765],"type":"Point"}
}