{
  "type": "Feature",
  "properties": {
    "addr:full":"Hoge Beemdstraat 12 Oud-turnhout Antwerpen 2360",
    "addr:housenumber":"12",
    "addr:postcode":"2360",
    "addr:street":"Hoge Beemdstraat",
    "iso:country":"BE",
    "sg:address":"Hoge Beemdstraat 12",
    "sg:city":"Oud-turnhout",
    "sg:orig_category":"Groententeelt",
    "sg:phone":"+32 14 43 66 35",
    "sg:postcode":"2360",
    "sg:province":"Antwerpen",
    "wof:name":"Paul Renders",
    "wof:placetype":"venue"
},
  "geometry": {"coordinates":[4.9840331078,51.3254852295],"type":"Point"}
}