{
  "type": "Feature",
  "properties": {
    "addr:full":"Rue De L'auberge 17 Doische (matagne-la-petite) Namur 5680",
    "addr:housenumber":"17",
    "addr:postcode":"5680",
    "addr:street":"Rue De L'Auberge",
    "iso:country":"BE",
    "sg:address":"Rue De L'auberge 17",
    "sg:city":"Doische (matagne-la-petite)",
    "sg:classifiers":[
        {
            "category":"Bars & Pubs",
            "type":"Food & Drink"
        }
    ],
    "sg:phone":"+32 60 39 18 47",
    "sg:postcode":"5680",
    "sg:province":"Namur",
    "wof:name":"Petit Rustique (le)",
    "wof:placetype":"venue"
},
  "geometry": {"coordinates":[4.6471600533,50.1169967651],"type":"Point"}
}