{
  "type": "Feature",
  "properties": {
    "addr:full":"Chauss\u00e9e De Waterloo 292 Bruxelles (saint-gilles) Bruxelles-Capitale 1060",
    "addr:housenumber":"292",
    "addr:postcode":"1060",
    "addr:street":"Chausse\u0301E De Waterloo",
    "iso:country":"BE",
    "sg:address":"Chauss\u00e9e De Waterloo 292",
    "sg:city":"Bruxelles (saint-gilles)",
    "sg:classifiers":[
        {
            "category":"Professional",
            "subcategory":"Computer Services",
            "type":"Services"
        }
    ],
    "sg:phone":"+32 495 21 38 93",
    "sg:postcode":"1060",
    "sg:province":"Bruxelles-Capitale",
    "sg:tags":[
        "-",
        "processing",
        "data",
        "software"
    ],
    "wof:name":"Data-concept",
    "wof:placetype":"venue"
},
  "geometry": {"coordinates":[4.3486452103,50.8252716064],"type":"Point"}
}