{
  "type": "Feature",
  "properties": {
    "iso:country":"BE",
    "sg:address":"Place Eug\u00e8ne Keym 31",
    "sg:city":"Bruxelles (watermael-boitsfort)",
    "sg:classifiers":[
        {
            "category":"Bars & Pubs",
            "type":"Food & Drink"
        }
    ],
    "sg:phone":"+32 2 675 43 36",
    "sg:postcode":"1170",
    "sg:province":"Bruxelles-Capitale",
    "wof:name":"Keym Taverne",
    "wof:placetype":"venue"
},
  "geometry": {"coordinates":[4.4036960602,50.8093757629],"type":"Point"}
}