{
  "type": "Feature",
  "properties": {
    "addr:full":"Lode De Boningestraat 21 Wevelgem West-Vlaanderen 8560",
    "addr:housenumber":"21",
    "addr:postcode":"8560",
    "addr:street":"Lode De Boningestraat",
    "iso:country":"BE",
    "sg:address":"Lode De Boningestraat 21",
    "sg:city":"Wevelgem",
    "sg:orig_category":"Brood, gebak and snoepgoed",
    "sg:phone":"+32 56 41 34 32",
    "sg:postcode":"8560",
    "sg:province":"West-Vlaanderen",
    "wof:name":"Noel Craeynest",
    "wof:placetype":"venue"
},
  "geometry": {"coordinates":[3.1829319,50.8096122742],"type":"Point"}
}