{
  "type": "Feature",
  "properties": {
    "iso:country":"BE",
    "sg:address":"Heestertstraat 14",
    "sg:city":"Maasmechelen",
    "sg:orig_category":"Tuinen",
    "sg:phone":"+32 89 77 22 84",
    "sg:postcode":"3630",
    "sg:province":"Limburg",
    "wof:name":"Kusters Peter",
    "wof:placetype":"venue"
},
  "geometry": {"coordinates":[5.6915960312,50.96824646],"type":"Point"}
}