{
  "type": "Feature",
  "properties": {
    "iso:country":"BE",
    "sg:address":"Hoogkamerstraat 5",
    "sg:city":"Temse",
    "sg:orig_category":"Sportclubs Sportterreinen and installaties behalve sportcentra",
    "sg:phone":"+32 3 771 02 72",
    "sg:postcode":"9140",
    "sg:province":"Oost-Vlaanderen",
    "wof:name":"Tennisclub Ter Poorter-temse",
    "wof:placetype":"venue"
},
  "geometry": {"coordinates":[4.2030172348,51.1267776489],"type":"Point"}
}