{
  "type": "Feature",
  "properties": {
    "iso:country":"BE",
    "sg:address":"Brusselsestraat 23",
    "sg:city":"Dendermonde",
    "sg:orig_category":"Dameskledingzaken",
    "sg:phone":"+32 52 21 17 14",
    "sg:postcode":"9200",
    "sg:province":"Oost-Vlaanderen",
    "wof:name":"Huis Belladonna",
    "wof:placetype":"venue"
},
  "geometry": {"coordinates":[4.0990839005,51.0284309387],"type":"Point"}
}