{
  "type": "Feature",
  "properties": {
    "iso:country":"BE",
    "sg:address":"Rue Gustave Joaris 32",
    "sg:city":"Chimay",
    "sg:orig_category":"Eleveurs de bovins",
    "sg:phone":"+32 60 21 10 19",
    "sg:postcode":"6463",
    "sg:province":"Hainaut",
    "wof:name":"Isaac Derzelle",
    "wof:placetype":"venue"
},
  "geometry": {"coordinates":[4.3773050308,50.0631065369],"type":"Point"}
}