{
  "type": "Feature",
  "properties": {
    "iso:country":"BE",
    "sg:address":"Haenestraat 14",
    "sg:city":"Veurne (steenkerke)",
    "sg:classifiers":[
        {
            "category":"Farming",
            "subcategory":"Livestock Farm",
            "type":"Manufacturing & Wholesale Goods"
        }
    ],
    "sg:phone":"+32 58 31 17 39",
    "sg:postcode":"8630",
    "sg:province":"West-Vlaanderen",
    "sg:tags":[
        "buyer"
    ],
    "wof:name":"Vandenbroucke J T",
    "wof:placetype":"venue"
},
  "geometry": {"coordinates":[2.6753799915,51.0777893066],"type":"Point"}
}