{
  "type": "Feature",
  "properties": {
    "iso:country":"BE",
    "sg:address":"Rue Des Ecoles 34",
    "sg:city":"Aiseau-presles",
    "sg:classifiers":[
        {
            "category":"Personal",
            "subcategory":"Beauty Salon",
            "type":"Services"
        }
    ],
    "sg:phone":"+32 71 76 05 48",
    "sg:postcode":"6250",
    "sg:province":"Hainaut",
    "sg:tags":[
        "de",
        "coiffure"
    ],
    "wof:name":"L'atelier Du Rotang",
    "wof:placetype":"venue"
},
  "geometry": {"coordinates":[4.6012787819,50.4227333069],"type":"Point"}
}