{
  "type": "Feature",
  "properties": {
    "addr:full":"Quai Du Brabant 39 Charleroi Hainaut 6000",
    "addr:housenumber":"39",
    "addr:postcode":"6000",
    "addr:street":"Quai Du Brabant;Hainaut",
    "iso:country":"BE",
    "sg:address":"Quai Du Brabant 39",
    "sg:city":"Charleroi",
    "sg:orig_category":"Lampes and appareils \u00e9lectriques Fab. Travaux d\u00b4installation divers",
    "sg:phone":"+32 71 33 35 80",
    "sg:postcode":"6000",
    "sg:province":"Hainaut",
    "wof:name":"Petrus",
    "wof:placetype":"venue"
},
  "geometry": {"coordinates":[4.445663929,50.4053115845],"type":"Point"}
}