{
  "type": "Feature",
  "properties": {
    "addr:full":"Arendsstraat 101 Harelbeke West-Vlaanderen 8530",
    "addr:housenumber":"101",
    "addr:postcode":"8530",
    "addr:street":"Arendsstraat",
    "iso:country":"BE",
    "sg:address":"Arendsstraat 101",
    "sg:city":"Harelbeke",
    "sg:classifiers":[
        {
            "category":"Professional",
            "subcategory":"Computer Services",
            "type":"Services"
        }
    ],
    "sg:phone":"+32 56 32 73 20",
    "sg:postcode":"8530",
    "sg:province":"West-Vlaanderen",
    "sg:tags":[
        "-",
        "processing",
        "data"
    ],
    "wof:name":"Rolin Computing",
    "wof:placetype":"venue"
},
  "geometry": {"coordinates":[3.3223910332,50.8543014526],"type":"Point"}
}