{
  "type": "Feature",
  "properties": {
    "addr:full":"Rue Des Carmes 202 Soumagne Li\u00e8ge 4630",
    "addr:housenumber":"202",
    "addr:postcode":"4630",
    "addr:street":"Rue Des Carmes",
    "iso:country":"BE",
    "sg:address":"Rue Des Carmes 202",
    "sg:city":"Soumagne",
    "sg:orig_category":"Catering and organisation de f\u00eates",
    "sg:phone":"+32 4 377 12 67",
    "sg:postcode":"4630",
    "sg:province":"Li\u00e8ge",
    "wof:name":"Michel Willot",
    "wof:placetype":"venue"
},
  "geometry": {"coordinates":[5.7337207794,50.6115264893],"type":"Point"}
}