{
  "type": "Feature",
  "properties": {
    "iso:country":"BE",
    "sg:address":"Broekstraat 41",
    "sg:city":"Sint-martens-latem",
    "sg:orig_category":"Artiesten and kunstenaars",
    "sg:phone":"+32 9 282 45 58",
    "sg:postcode":"9831",
    "sg:province":"Oost-Vlaanderen",
    "wof:name":"Alfons Roggeman",
    "wof:placetype":"venue"
},
  "geometry": {"coordinates":[3.6186540127,50.9959411621],"type":"Point"}
}