{
  "type": "Feature",
  "properties": {
    "addr:full":"Meester Van Wijnsberghelaan 7 Harelbeke (hulste) West-Vlaanderen 8531",
    "addr:housenumber":"7",
    "addr:postcode":"8531",
    "addr:street":"Meester Van Wijnsberghelaan",
    "iso:country":"BE",
    "sg:address":"Meester Van Wijnsberghelaan 7",
    "sg:city":"Harelbeke (hulste)",
    "sg:classifiers":[
        {
            "category":"Home & Garden",
            "subcategory":"Building Materials",
            "type":"Retail Goods"
        }
    ],
    "sg:phone":"+32 56 25 77 07",
    "sg:postcode":"8531",
    "sg:province":"West-Vlaanderen",
    "sg:tags":[
        "house"
    ],
    "wof:name":"Summer Chalet",
    "wof:placetype":"venue"
},
  "geometry": {"coordinates":[3.2948870659,50.8839836121],"type":"Point"}
}