{
  "type": "Feature",
  "properties": {
    "iso:country":"BE",
    "sg:address":"Sint-jorisstraat 4",
    "sg:city":"Elsene/ixelles",
    "sg:orig_category":"Dameskledingzaken Herenkledingzaken",
    "sg:phone":"+32 2 649 23 00",
    "sg:postcode":"1050",
    "sg:province":"Bruxelles-Capitale",
    "wof:name":"Maison Degand",
    "wof:placetype":"venue"
},
  "geometry": {"coordinates":[4.3695659637,50.8190040588],"type":"Point"}
}