{
  "type": "Feature",
  "properties": {
    "iso:country":"BE",
    "sg:address":"Rue Fran\u00c7ois Bossaerts 35",
    "sg:city":"Schaarbeek/schaerbeek",
    "sg:orig_category":"Epiceries",
    "sg:phone":"+32 2 736 41 04",
    "sg:postcode":"1030",
    "sg:province":"Bruxelles-Capitale",
    "wof:name":"Shiqbal And Co",
    "wof:placetype":"venue"
},
  "geometry": {"coordinates":[4.3850030899,50.8543891907],"type":"Point"}
}