{
  "type": "Feature",
  "properties": {
    "addr:full":"Wilfordkaai 37 Temse Oost-Vlaanderen 9140",
    "addr:housenumber":"37",
    "addr:postcode":"9140",
    "addr:street":"Wilfordkaai",
    "iso:country":"BE",
    "sg:address":"Wilfordkaai 37",
    "sg:city":"Temse",
    "sg:orig_category":"H\u00f4tels. Restaurants",
    "sg:phone":"+32 3 771 08 08",
    "sg:postcode":"9140",
    "sg:province":"Oost-Vlaanderen",
    "wof:name":"Belle-vue",
    "wof:placetype":"venue"
},
  "geometry": {"coordinates":[4.218298912,51.1232872009],"type":"Point"}
}