{
  "type": "Feature",
  "properties": {
    "iso:country":"BE",
    "sg:address":"Galopstraat 5",
    "sg:city":"Waregem",
    "sg:classifiers":[
        {
            "category":"Recreation",
            "subcategory":"Amusement Park",
            "type":"Entertainment"
        }
    ],
    "sg:phone":"+32 56 61 40 66",
    "sg:postcode":"8790",
    "sg:province":"West-Vlaanderen",
    "sg:tags":[
        "attraction",
        "-",
        "sale",
        "fair",
        "hiring"
    ],
    "wof:name":"Attracties Joy Bouncer",
    "wof:placetype":"venue"
},
  "geometry": {"coordinates":[3.4339458942,50.8797988892],"type":"Point"}
}