{
  "type": "Feature",
  "properties": {
    "addr:full":"Oude Heerweg 6 Lokeren Oost-Vlaanderen 9160",
    "addr:housenumber":"6",
    "addr:postcode":"9160",
    "addr:street":"Oude Heerweg",
    "iso:country":"BE",
    "sg:address":"Oude Heerweg 6",
    "sg:city":"Lokeren",
    "sg:classifiers":[
        {
            "category":"Parking",
            "subcategory":"Lot",
            "type":"Transportation"
        }
    ],
    "sg:phone":"+32 9 348 64 21",
    "sg:postcode":"9160",
    "sg:province":"Oost-Vlaanderen",
    "sg:tags":[
        "parking-places",
        "laying-out"
    ],
    "wof:name":"Van Sleyken",
    "wof:placetype":"venue"
},
  "geometry": {"coordinates":[3.9912691116,51.1135368347],"type":"Point"}
}