{
  "type": "Feature",
  "properties": {
    "iso:country":"BE",
    "sg:address":"Kolonel Begaultlaan 15 Box 18",
    "sg:city":"Leuven (wilsele)",
    "sg:classifiers":[
        {
            "category":"Professional",
            "subcategory":"Art Services",
            "type":"Services"
        }
    ],
    "sg:phone":"+32 16 29 29 01",
    "sg:postcode":"3012",
    "sg:province":"Vlaams-Brabant",
    "sg:tags":[
        "realization",
        "audio-visual"
    ],
    "wof:name":"Btm Productions Nv",
    "wof:placetype":"venue"
},
  "geometry": {"coordinates":[4.7059540749,50.8914337158],"type":"Point"}
}