{
  "type": "Feature",
  "properties": {
    "addr:full":"Rue Des Epingliers 9 Mons Hainaut 7000",
    "addr:housenumber":"9",
    "addr:postcode":"7000",
    "addr:street":"Rue Des Epingliers;Hainaut",
    "iso:country":"BE",
    "sg:address":"Rue Des Epingliers 9",
    "sg:city":"Mons",
    "sg:classifiers":[
        {
            "category":"Personal",
            "type":"Services"
        }
    ],
    "sg:phone":"+32 65 33 94 70",
    "sg:postcode":"7000",
    "sg:province":"Hainaut",
    "sg:tags":[
        "clothing",
        "men's",
        "tailor",
        "-"
    ],
    "wof:name":"Grotta Daurea S",
    "wof:placetype":"venue"
},
  "geometry": {"coordinates":[3.9548380375,50.4533042908],"type":"Point"}
}