{
  "type": "Feature",
  "properties": {
    "iso:country":"BE",
    "sg:address":"Rue Gr\u00e9goire Wincqz 245",
    "sg:city":"Soignies",
    "sg:classifiers":[
        {
            "category":"Shopping",
            "subcategory":"Bridal",
            "type":"Retail Goods"
        }
    ],
    "sg:phone":"+32 67 33 30 36",
    "sg:postcode":"7060",
    "sg:province":"Hainaut",
    "sg:tags":[
        "list",
        "-",
        "present",
        "wedding"
    ],
    "wof:name":"Deltenre Y",
    "wof:placetype":"venue"
},
  "geometry": {"coordinates":[4.0775141716,50.5708885193],"type":"Point"}
}