{
  "type": "Feature",
  "properties": {
    "addr:full":"Rue Des D\u00c9port\u00c9s 140 Aarlen Luxembourg 6700",
    "addr:housenumber":"140",
    "addr:postcode":"6700",
    "addr:street":"Rue Des De\u0301Porte\u0301S",
    "iso:country":"BE",
    "sg:address":"Rue Des D\u00c9port\u00c9s 140",
    "sg:city":"Aarlen",
    "sg:orig_category":"Diverse bedrijfsbeheeradviesbureaus",
    "sg:phone":"+32 63 23 50 50",
    "sg:postcode":"6700",
    "sg:province":"Luxembourg",
    "wof:name":"Creaction",
    "wof:placetype":"venue"
},
  "geometry": {"coordinates":[5.8208508492,49.6791954041],"type":"Point"}
}