{
  "type": "Feature",
  "properties": {
    "addr:full":"Avenue Saint-hubert 71 Braine-le-comte (hennuy\u00e8res) Hainaut 7090",
    "addr:housenumber":"71",
    "addr:postcode":"7090",
    "addr:street":"Avenue Saint-Hubert",
    "iso:country":"BE",
    "sg:address":"Avenue Saint-hubert 71",
    "sg:city":"Braine-le-comte (hennuy\u00e8res)",
    "sg:classifiers":[
        {
            "category":"Shopping",
            "subcategory":"Pets & Pet Supplies",
            "type":"Retail Goods"
        }
    ],
    "sg:phone":"+32 475 64 00 33",
    "sg:postcode":"7090",
    "sg:province":"Hainaut",
    "sg:tags":[
        "shop",
        "-"
    ],
    "wof:name":"Druet Ph",
    "wof:placetype":"venue"
},
  "geometry": {"coordinates":[4.1741118431,50.6370010376],"type":"Point"}
}