{
  "type": "Feature",
  "properties": {
    "addr:full":"Boulevard Du Nord 30 Namur Namur 5000",
    "addr:housenumber":"30",
    "addr:postcode":"5000",
    "addr:street":"Boulevard Du Nord",
    "iso:country":"BE",
    "sg:address":"Boulevard Du Nord 30",
    "sg:city":"Namur",
    "sg:classifiers":[
        {
            "category":"Autos & Motor Vehicles",
            "subcategory":"Auto Supplies",
            "type":"Retail Goods"
        }
    ],
    "sg:phone":"+32 81 22 48 60",
    "sg:postcode":"5000",
    "sg:province":"Namur",
    "sg:tags":[
        "automobile",
        "-",
        "radio"
    ],
    "wof:name":"Dufeys",
    "wof:placetype":"venue"
},
  "geometry": {"coordinates":[4.8645558357,50.4702644348],"type":"Point"}
}