{
  "type": "Feature",
  "properties": {
    "addr:full":"Speurtstraat 104 Lede Oost-Vlaanderen 9340",
    "addr:housenumber":"104",
    "addr:postcode":"9340",
    "addr:street":"Speurtstraat",
    "iso:country":"BE",
    "sg:address":"Speurtstraat 104",
    "sg:city":"Lede",
    "sg:orig_category":"Artsen and specialisten",
    "sg:phone":"+32 9 369 91 43",
    "sg:postcode":"9340",
    "sg:province":"Oost-Vlaanderen",
    "wof:name":"Bernadette Van De Vijver",
    "wof:placetype":"venue"
},
  "geometry": {"coordinates":[3.9020218849,50.9646263123],"type":"Point"}
}