{
  "type": "Feature",
  "properties": {
    "iso:country":"BE",
    "sg:address":"Bistseveldenstraat 11",
    "sg:city":"Mechelen",
    "sg:orig_category":"Epiceries",
    "sg:phone":"+32 15 33 18 40",
    "sg:postcode":"2811",
    "sg:province":"Antwerpen",
    "wof:name":"De Thuiswinkel",
    "wof:placetype":"venue"
},
  "geometry": {"coordinates":[4.3809299469,51.0153465271],"type":"Point"}
}