{
  "type": "Feature",
  "properties": {
    "addr:full":"Am Rurbusch Butgenbach Li\u00e8ge 4750",
    "addr:postcode":"4750",
    "addr:street":"Am Rurbusch",
    "iso:country":"BE",
    "sg:address":"Am Rurbusch",
    "sg:city":"Butgenbach",
    "sg:classifiers":[
        {
            "category":"Home & Garden",
            "subcategory":"Furniture",
            "type":"Retail Goods"
        }
    ],
    "sg:phone":"+32 80 44 48 19",
    "sg:postcode":"4750",
    "sg:province":"Li\u00e8ge",
    "sg:tags":[
        "wood"
    ],
    "wof:name":"Peterges Compagnie Scierie Sprl",
    "wof:placetype":"venue"
},
  "geometry": {"coordinates":[6.1461467743,50.4827728271],"type":"Point"}
}