{
  "type": "Feature",
  "properties": {
    "addr:full":"Zone Lion D'or Noord 4 Aalst Oost-Vlaanderen 9300",
    "addr:housenumber":"4",
    "addr:postcode":"9300",
    "addr:street":"Noord",
    "iso:country":"BE",
    "sg:address":"Zone Lion D'or Noord 4",
    "sg:city":"Aalst",
    "sg:classifiers":[
        {
            "category":"Shopping",
            "subcategory":"Clothing, Apparel, & Fashions",
            "type":"Retail Goods"
        }
    ],
    "sg:phone":"+32 53 78 36 36",
    "sg:postcode":"9300",
    "sg:province":"Oost-Vlaanderen",
    "sg:tags":[
        "clothing",
        "protective",
        "disposable"
    ],
    "wof:name":"Smekens Nv",
    "wof:placetype":"venue"
},
  "geometry": {"coordinates":[4.0653629303,50.8305854797],"type":"Point"}
}