{
  "type": "Feature",
  "properties": {
    "addr:full":"Appelmansstraat 1 Antwerpen Antwerpen 2018",
    "addr:housenumber":"1",
    "addr:postcode":"2018",
    "addr:street":"Appelmansstraat",
    "iso:country":"BE",
    "sg:address":"Appelmansstraat 1",
    "sg:city":"Antwerpen",
    "sg:classifiers":[
        {
            "category":"Shopping",
            "subcategory":"Jewelry",
            "type":"Retail Goods"
        }
    ],
    "sg:phone":"+32 3 231 25 63",
    "sg:postcode":"2018",
    "sg:province":"Antwerpen",
    "sg:tags":[
        "jeweller",
        "-"
    ],
    "wof:name":"Geussens R",
    "wof:placetype":"venue"
},
  "geometry": {"coordinates":[4.4178371429,51.2175178528],"type":"Point"}
}