{
  "type": "Feature",
  "properties": {
    "iso:country":"BE",
    "sg:address":"Rue Pierre Hap Lemaitre 22",
    "sg:city":"Etterbeek",
    "sg:orig_category":"Artiesten and kunstenaars Divers amusement",
    "sg:phone":"+32 2 648 25 79",
    "sg:postcode":"1040",
    "sg:province":"Bruxelles-Capitale",
    "wof:name":"Baye N",
    "wof:placetype":"venue"
},
  "geometry": {"coordinates":[4.3866429329,50.8265991211],"type":"Point"}
}