{
  "type": "Feature",
  "properties": {
    "addr:full":"Hazehoekstraat Bekkevoort Vlaams-Brabant 3460",
    "addr:postcode":"3460",
    "addr:street":"Hazehoekstraat",
    "iso:country":"BE",
    "sg:address":"Hazehoekstraat",
    "sg:city":"Bekkevoort",
    "sg:orig_category":"Paardenfokkers",
    "sg:phone":"+32 13 32 15 68",
    "sg:postcode":"3460",
    "sg:province":"Vlaams-Brabant",
    "wof:name":"De Hulst",
    "wof:placetype":"venue"
},
  "geometry": {"coordinates":[4.975605011,50.9449462891],"type":"Point"}
}