{
  "type": "Feature",
  "properties": {
    "iso:country":"BE",
    "sg:address":"Kazernestraat 74a",
    "sg:city":"Lokeren",
    "sg:classifiers":[
        {
            "category":"School Buses",
            "type":"Transportation"
        }
    ],
    "sg:phone":"+32 9 348 84 19",
    "sg:postcode":"9160",
    "sg:province":"Oost-Vlaanderen",
    "sg:tags":[
        "homeopathy"
    ],
    "wof:name":"Baetens E",
    "wof:placetype":"venue"
},
  "geometry": {"coordinates":[3.9903259277,51.0997543335],"type":"Point"}
}