{
  "type": "Feature",
  "properties": {
    "iso:country":"BE",
    "sg:address":"Voetbalstraat 5",
    "sg:city":"Izegem",
    "sg:orig_category":"Voertuigen",
    "sg:phone":"+32 51 30 71 85",
    "sg:postcode":"8870",
    "sg:province":"West-Vlaanderen",
    "wof:name":"Quadrifoglio Verde Motors",
    "wof:placetype":"venue"
},
  "geometry": {"coordinates":[3.2174899578,50.9281234741],"type":"Point"}
}