{
  "type": "Feature",
  "properties": {
    "addr:full":"Edegemsestraat 80 Mortsel Antwerpen 2640",
    "addr:housenumber":"80",
    "addr:postcode":"2640",
    "addr:street":"Edegemsestraat",
    "iso:country":"BE",
    "sg:address":"Edegemsestraat 80",
    "sg:city":"Mortsel",
    "sg:classifiers":[
        {
            "category":"Insurance",
            "subcategory":"Insurance Agent",
            "type":"Services"
        }
    ],
    "sg:phone":"+32 3 440 20 02",
    "sg:postcode":"2640",
    "sg:province":"Antwerpen",
    "sg:tags":[
        "-",
        "representative"
    ],
    "wof:name":"Verzekeringskantoor Vanderispaillie",
    "wof:placetype":"venue"
},
  "geometry": {"coordinates":[4.4460420609,51.1683006287],"type":"Point"}
}