{
  "type": "Feature",
  "properties": {
    "addr:full":"Rue D'esneux 57 Comblain-au-pont Li\u00e8ge 4171",
    "addr:housenumber":"57",
    "addr:postcode":"4171",
    "addr:street":"Rue D'Esneux",
    "iso:country":"BE",
    "sg:address":"Rue D'esneux 57",
    "sg:city":"Comblain-au-pont",
    "sg:orig_category":"D\u00e9taillants en pi\u00e8ces and accessoires de voitures. R\u00e9cup\u00e9ration de mati\u00e8res m\u00e9talliques recyclables ",
    "sg:phone":"+32 4 380 47 81",
    "sg:postcode":"4171",
    "sg:province":"Li\u00e8ge",
    "wof:name":"Demopel",
    "wof:placetype":"venue"
},
  "geometry": {"coordinates":[5.5695338249,50.5060272217],"type":"Point"}
}