{
  "type": "Feature",
  "properties": {
    "addr:full":"Leuvenseweg 93 Aarschot (rillaar) Vlaams-Brabant 3202",
    "addr:housenumber":"93",
    "addr:postcode":"3202",
    "addr:street":"Leuvenseweg",
    "iso:country":"BE",
    "sg:address":"Leuvenseweg 93",
    "sg:city":"Aarschot (rillaar)",
    "sg:classifiers":[
        {
            "category":"Building & Trades",
            "subcategory":"Landscaping Services",
            "type":"Services"
        }
    ],
    "sg:phone":"+32 498 76 36 50",
    "sg:postcode":"3202",
    "sg:province":"Vlaams-Brabant",
    "sg:tags":[
        "gardening",
        "garden",
        "maintenance"
    ],
    "wof:name":"Luykx B",
    "wof:placetype":"venue"
},
  "geometry": {"coordinates":[4.8795790672,50.9673881531],"type":"Point"}
}