{
  "type": "Feature",
  "properties": {
    "iso:country":"BE",
    "sg:address":"Bruulstraat 31a",
    "sg:city":"Hulshout",
    "sg:orig_category":"Jardinage",
    "sg:phone":"+32 15 22 44 22",
    "sg:postcode":"2235",
    "sg:province":"Antwerpen",
    "wof:name":"Eko-flora",
    "wof:placetype":"venue"
},
  "geometry": {"coordinates":[4.7998437881,51.0696411133],"type":"Point"}
}