{
  "type": "Feature",
  "properties": {
    "addr:full":"Binkomstraat 1 Lubbeek Vlaams-Brabant 3210",
    "addr:housenumber":"1",
    "addr:postcode":"3210",
    "addr:street":"Binkomstraat",
    "iso:country":"BE",
    "sg:address":"Binkomstraat 1",
    "sg:city":"Lubbeek",
    "sg:orig_category":"Assurances. Bureaux de poste",
    "sg:phone":"+32 16 63 42 16",
    "sg:postcode":"3210",
    "sg:province":"Vlaams-Brabant",
    "wof:name":"De Post",
    "wof:placetype":"venue"
},
  "geometry": {"coordinates":[4.8427519798,50.8817634583],"type":"Point"}
}