{
  "type": "Feature",
  "properties": {
    "iso:country":"BE",
    "sg:address":"Rue De Houtain 50",
    "sg:city":"Juprelle",
    "sg:orig_category":"Groenten and fruit Gh",
    "sg:phone":"+32 4 278 53 27",
    "sg:postcode":"4458",
    "sg:province":"Li\u00e8ge",
    "wof:name":"Maison Doris",
    "wof:placetype":"venue"
},
  "geometry": {"coordinates":[5.569712162,50.7215194702],"type":"Point"}
}