{
  "type": "Feature",
  "properties": {
    "iso:country":"BE",
    "sg:address":"Hortensiastraat 12",
    "sg:city":"Antwerpen",
    "sg:classifiers":[
        {
            "category":"Professional",
            "subcategory":"Accounting & Tax Preparation",
            "type":"Services"
        }
    ],
    "sg:phone":"+32 3 216 99 58",
    "sg:postcode":"2020",
    "sg:province":"Antwerpen",
    "sg:tags":[
        "accountant"
    ],
    "wof:name":"Van Looy D",
    "wof:placetype":"venue"
},
  "geometry": {"coordinates":[4.3929491043,51.1849403381],"type":"Point"}
}