{
  "type": "Feature",
  "properties": {
    "iso:country":"BE",
    "sg:address":"Boekweitstraat 30",
    "sg:city":"Jabbeke",
    "sg:orig_category":"Elektrische installaties voor woningen",
    "sg:phone":"+32 50 81 55 51",
    "sg:postcode":"8490",
    "sg:province":"West-Vlaanderen",
    "wof:name":"Elcon",
    "wof:placetype":"venue"
},
  "geometry": {"coordinates":[3.0862410069,51.175819397],"type":"Point"}
}