{
  "type": "Feature",
  "properties": {
    "iso:country":"BE",
    "sg:address":"Grobbendonkseweg 128",
    "sg:city":"Nijlen",
    "sg:orig_category":"Rev\u00eatements pour sols and murs. Peinture",
    "sg:phone":"+32 3 481 95 69",
    "sg:postcode":"2560",
    "sg:province":"Antwerpen",
    "wof:name":"A.s.p.",
    "wof:placetype":"venue"
},
  "geometry": {"coordinates":[4.6997389793,51.1687927246],"type":"Point"}
}