{
  "type": "Feature",
  "properties": {
    "iso:country":"BE",
    "sg:address":"Chauss\u00c9e Du Roeulx 173",
    "sg:city":"Mons",
    "sg:orig_category":"Kinderopvang",
    "sg:phone":"+32 65 31 34 45",
    "sg:postcode":"7000",
    "sg:province":"Hainaut",
    "wof:name":"La Maison De Snoopy",
    "wof:placetype":"venue"
},
  "geometry": {"coordinates":[3.9744699001,50.4566612244],"type":"Point"}
}