{
  "type": "Feature",
  "properties": {
    "addr:full":"Rue Haut Cortil 1 Jemeppe 5790",
    "addr:housenumber":"1",
    "addr:postcode":"5790",
    "addr:street":"Rue Haut Cortil;Jemeppe",
    "iso:country":"BE",
    "sg:address":"Rue Haut Cortil 1",
    "sg:city":"Jemeppe",
    "sg:classifiers":[
        {
            "category":"Banks & Credit Unions",
            "subcategory":"Bank",
            "type":"Services"
        }
    ],
    "sg:phone":"+32 19 78 61 82",
    "sg:postcode":"5790",
    "wof:name":"Banque Bruxelles Lambert Sa",
    "wof:placetype":"venue"
},
  "geometry": {"coordinates":[24.2972507477,43.1057510376],"type":"Point"}
}