{
  "type": "Feature",
  "properties": {
    "iso:country":"BE",
    "sg:address":"Rue Piervenne 149",
    "sg:city":"Ciney",
    "sg:orig_category":"Artsen and specialisten",
    "sg:phone":"+32 83 21 17 43",
    "sg:postcode":"5590",
    "sg:province":"Namur",
    "wof:name":"Ets. Nyssen-dehaye",
    "wof:placetype":"venue"
},
  "geometry": {"coordinates":[5.0918779373,50.2915534973],"type":"Point"}
}