{
  "type": "Feature",
  "properties": {
    "addr:full":"Grote Baan 560 Houthalen-helchteren Limburg 3530",
    "addr:housenumber":"560",
    "addr:postcode":"3530",
    "addr:street":"Grote Baan",
    "iso:country":"BE",
    "sg:address":"Grote Baan 560",
    "sg:city":"Houthalen-helchteren",
    "sg:orig_category":"Industri\u00eble and commerci\u00eble bouw Woningbouw",
    "sg:phone":"+32 11 52 10 55",
    "sg:postcode":"3530",
    "sg:province":"Limburg",
    "wof:name":"Awouters Bouw En Beton",
    "wof:placetype":"venue"
},
  "geometry": {"coordinates":[5.3802499771,51.0446510315],"type":"Point"}
}