{
  "type": "Feature",
  "properties": {
    "addr:full":"Rue Fran\u00e7ois Bekaert 13 Bruxelles (auderghem) Bruxelles-Capitale 1160",
    "addr:housenumber":"13",
    "addr:postcode":"1160",
    "addr:street":"Rue Franc\u0327Ois Bekaert",
    "iso:country":"BE",
    "sg:address":"Rue Fran\u00e7ois Bekaert 13",
    "sg:city":"Bruxelles (auderghem)",
    "sg:classifiers":[
        {
            "category":"Food & Beverages",
            "subcategory":"Groceries & Convenience Stores",
            "type":"Retail Goods"
        }
    ],
    "sg:phone":"+32 2 672 04 87",
    "sg:postcode":"1160",
    "sg:province":"Bruxelles-Capitale",
    "sg:tags":[
        "grocer"
    ],
    "wof:name":"Le Petit Delhaize",
    "wof:placetype":"venue"
},
  "geometry": {"coordinates":[4.4311981201,50.8090438843],"type":"Point"}
}