{
  "type": "Feature",
  "properties": {
    "addr:full":"Dendermondesteenweg 449 Destelbergen Oost-Vlaanderen 9070",
    "addr:housenumber":"449",
    "addr:postcode":"9070",
    "addr:street":"Dendermondesteenweg",
    "iso:country":"BE",
    "sg:address":"Dendermondesteenweg 449",
    "sg:city":"Destelbergen",
    "sg:classifiers":[
        {
            "category":"Social Services",
            "type":"Services"
        }
    ],
    "sg:phone":"+32 9 228 28 08",
    "sg:postcode":"9070",
    "sg:province":"Oost-Vlaanderen",
    "sg:tags":[
        "handicapped",
        "-"
    ],
    "wof:name":"Doventolkendienst-cab",
    "wof:placetype":"venue"
},
  "geometry": {"coordinates":[3.7970449924,51.0560913086],"type":"Point"}
}