{
  "type": "Feature",
  "properties": {
    "iso:country":"BE",
    "sg:address":"Merksemsebaan 98",
    "sg:city":"Wijnegem",
    "sg:classifiers":[
        {
            "category":"Health Services",
            "subcategory":"Health Practitioner",
            "type":"Services"
        }
    ],
    "sg:phone":"+32 3 353 05 01",
    "sg:postcode":"2110",
    "sg:province":"Antwerpen",
    "sg:tags":[
        "physiotherapist"
    ],
    "wof:name":"Gios P",
    "wof:placetype":"venue"
},
  "geometry": {"coordinates":[4.5153188705,51.2289657593],"type":"Point"}
}