{
  "type": "Feature",
  "properties": {
    "iso:country":"BE",
    "sg:address":"Gulledelle 96",
    "sg:city":"Sint-lambrechts-woluwe/woluwe-saint-lambert",
    "sg:classifiers":[
        {
            "category":"Shopping Center",
            "type":"Public Place"
        }
    ],
    "sg:phone":"+32 2 777 70 20",
    "sg:postcode":"1200",
    "sg:province":"Bruxelles-Capitale",
    "sg:tags":[
        "enseignement",
        "formation"
    ],
    "wof:name":"Personnel Decisions Inc.",
    "wof:placetype":"venue"
},
  "geometry": {"coordinates":[4.4248809814,50.8559036255],"type":"Point"}
}