{
  "type": "Feature",
  "properties": {
    "addr:full":"Guido Gezellelaan 15 Zonnebeke West-Vlaanderen 8980",
    "addr:housenumber":"15",
    "addr:postcode":"8980",
    "addr:street":"Guido Gezellelaan",
    "iso:country":"BE",
    "sg:address":"Guido Gezellelaan 15",
    "sg:city":"Zonnebeke",
    "sg:orig_category":"Banken and kredietinstellingen",
    "sg:phone":"+32 51 77 83 10",
    "sg:postcode":"8980",
    "sg:province":"West-Vlaanderen",
    "wof:name":"Centea",
    "wof:placetype":"venue"
},
  "geometry": {"coordinates":[2.9845530987,50.8689804077],"type":"Point"}
}