{
  "type": "Feature",
  "properties": {
    "iso:country":"BE",
    "sg:address":"Rue De La Croix 14",
    "sg:city":"Welkenraedt/welkenraedt",
    "sg:orig_category":"Artsen and specialisten",
    "sg:phone":"+32 87 88 17 44",
    "sg:postcode":"4840",
    "sg:province":"Li\u00e8ge",
    "wof:name":"Beno\u00cet Joskin",
    "wof:placetype":"venue"
},
  "geometry": {"coordinates":[5.9796700478,50.6616210938],"type":"Point"}
}