{
  "type": "Feature",
  "properties": {
    "addr:full":"Rue Surmont 32 Sambreville (auvelais) Namur 5060",
    "addr:housenumber":"32",
    "addr:postcode":"5060",
    "addr:street":"Rue Surmont",
    "iso:country":"BE",
    "sg:address":"Rue Surmont 32",
    "sg:city":"Sambreville (auvelais)",
    "sg:classifiers":[
        {
            "category":"Utilities",
            "subcategory":"Fuel Oil & Lpg",
            "type":"Services"
        }
    ],
    "sg:phone":"+32 71 78 86 30",
    "sg:postcode":"5060",
    "sg:province":"Namur",
    "wof:name":"Bertrand-tourneur",
    "wof:placetype":"venue"
},
  "geometry": {"coordinates":[4.6285200119,50.4448738098],"type":"Point"}
}