{
  "type": "Feature",
  "properties": {
    "iso:country":"BE",
    "sg:address":"Machelsesteenweg 25",
    "sg:city":"Steenokkerzeel",
    "sg:orig_category":"Agences de publicit\u00e9. R\u00e9alisation de programmes and logiciels. Imprimeries and copyshops",
    "sg:phone":"+32 2 751 31 61",
    "sg:postcode":"1820",
    "sg:province":"Vlaams-Brabant",
    "wof:name":"Tamis",
    "wof:placetype":"venue"
},
  "geometry": {"coordinates":[4.4709892273,50.9117088318],"type":"Point"}
}