{
  "type": "Feature",
  "properties": {
    "iso:country":"BE",
    "sg:address":"Ch De Boondael 467",
    "sg:city":"Bruxelles",
    "sg:classifiers":[
        {
            "category":"Travel",
            "subcategory":"Hotels & Motels",
            "type":"Entertainment"
        }
    ],
    "sg:phone":"+32 2 640 45 11",
    "sg:postcode":"1050",
    "sg:province":"Bruxelles-Capitale",
    "sg:tags":[
        "hotels",
        "business",
        "restaurant"
    ],
    "wof:name":"Petite Planete (la) Sprl",
    "wof:placetype":"venue"
},
  "geometry": {"coordinates":[4.3893318176,50.8161239624],"type":"Point"}
}