{
  "type": "Feature",
  "properties": {
    "addr:full":"Rijkenhoekstraat 80 Grimbergen Vlaams-Brabant 1850",
    "addr:housenumber":"80",
    "addr:postcode":"1850",
    "addr:street":"Rijkenhoekstraat",
    "iso:country":"BE",
    "sg:address":"Rijkenhoekstraat 80",
    "sg:city":"Grimbergen",
    "sg:classifiers":[
        {
            "category":"Social Services",
            "type":"Services"
        }
    ],
    "sg:phone":"+32 2 270 09 30",
    "sg:postcode":"1850",
    "sg:province":"Vlaams-Brabant",
    "wof:name":"Diepen Boomgaard",
    "wof:placetype":"venue"
},
  "geometry": {"coordinates":[4.3735399246,50.938041687],"type":"Point"}
}