{
  "type": "Feature",
  "properties": {
    "iso:country":"BE",
    "sg:address":"Kapelstraat 1",
    "sg:city":"Boom",
    "sg:classifiers":[
        {
            "category":"Health Services",
            "subcategory":"Nursing And Care Facility",
            "type":"Services"
        }
    ],
    "sg:phone":"+32 3 888 63 13",
    "sg:postcode":"2850",
    "sg:province":"Antwerpen",
    "sg:tags":[
        "public"
    ],
    "wof:name":"R.v.a.",
    "wof:placetype":"venue"
},
  "geometry": {"coordinates":[4.3704648018,51.0868682861],"type":"Point"}
}