{
  "type": "Feature",
  "properties": {
    "iso:country":"BE",
    "sg:address":"Akrenbos 85",
    "sg:city":"Bever/bievene",
    "sg:orig_category":"Rundveehouders",
    "sg:phone":"+32 54 58 88 25",
    "sg:postcode":"1547",
    "sg:province":"Vlaams-Brabant",
    "wof:name":"Camille Goorickx",
    "wof:placetype":"venue"
},
  "geometry": {"coordinates":[3.9079580307,50.7230949402],"type":"Point"}
}