{
  "type": "Feature",
  "properties": {
    "iso:country":"BE",
    "sg:address":"Rue Des Buissons 57b",
    "sg:city":"Li\u00e8ge 1",
    "sg:classifiers":[
        {
            "category":"Building & Trades",
            "subcategory":"Pest Control",
            "type":"Services"
        }
    ],
    "sg:phone":"+32 4 224 01 98",
    "sg:postcode":"4000",
    "sg:province":"Li\u00e8ge",
    "sg:tags":[
        "painting",
        "contractor"
    ],
    "wof:name":"Dullens (les Entreprises) Sprl",
    "wof:placetype":"venue"
},
  "geometry": {"coordinates":[5.5665040016,50.6515350342],"type":"Point"}
}