{
  "type": "Feature",
  "properties": {
    "iso:country":"BE",
    "sg:address":"Rue Hayette 47",
    "sg:city":"Esneux",
    "sg:orig_category":"R\u00e9parations d'appareils \u00e9lectrom\u00e9nagers",
    "sg:phone":"+32 4 380 00 21",
    "sg:postcode":"4130",
    "sg:province":"Li\u00e8ge",
    "wof:name":"Alain Laffut",
    "wof:placetype":"venue"
},
  "geometry": {"coordinates":[5.570540905,50.5572471619],"type":"Point"}
}