{
  "type": "Feature",
  "properties": {
    "addr:full":"Rue Willems 64 Bruxelles (saint-josse-ten-noode) Bruxelles-Capitale 1210",
    "addr:housenumber":"64",
    "addr:postcode":"1210",
    "addr:street":"Rue Willems",
    "iso:country":"BE",
    "sg:address":"Rue Willems 64",
    "sg:city":"Bruxelles (saint-josse-ten-noode)",
    "sg:classifiers":[
        {
            "category":"Bakery",
            "type":"Food & Drink"
        }
    ],
    "sg:phone":"+32 2 230 61 76",
    "sg:postcode":"1210",
    "sg:province":"Bruxelles-Capitale",
    "sg:tags":[
        "confectioner",
        "baker"
    ],
    "wof:name":"Marie-jose",
    "wof:placetype":"venue"
},
  "geometry": {"coordinates":[4.3777399063,50.8489189148],"type":"Point"}
}