{
  "type": "Feature",
  "properties": {
    "addr:full":"Rue Jules Mattez 34b2 Courcelles Hainaut 6182",
    "addr:housenumber":"34b2",
    "addr:postcode":"6182",
    "addr:street":"Rue Jules Mattez",
    "iso:country":"BE",
    "sg:address":"Rue Jules Mattez 34b2",
    "sg:city":"Courcelles",
    "sg:orig_category":"Woningbouw",
    "sg:phone":"+32 71 46 01 91",
    "sg:postcode":"6182",
    "sg:province":"Hainaut",
    "wof:name":"Gianmarino Fidelino",
    "wof:placetype":"venue"
},
  "geometry": {"coordinates":[4.351334095,50.4485321045],"type":"Point"}
}