{
  "type": "Feature",
  "properties": {
    "iso:country":"BE",
    "sg:address":"Rue Bayard 3",
    "sg:city":"Couvin",
    "sg:orig_category":"Apotheken",
    "sg:phone":"+32 60 34 53 38",
    "sg:postcode":"5660",
    "sg:province":"Namur",
    "wof:name":"Henry Gravy",
    "wof:placetype":"venue"
},
  "geometry": {"coordinates":[4.4252390862,50.0382881165],"type":"Point"}
}