{
  "type": "Feature",
  "properties": {
    "iso:country":"BE",
    "sg:address":"Lisperstraat 3-5",
    "sg:city":"Lier",
    "sg:classifiers":[
        {
            "category":"Shopping",
            "subcategory":"Clothing, Apparel, & Fashions",
            "type":"Retail Goods"
        }
    ],
    "sg:phone":"+32 3 480 06 14",
    "sg:postcode":"2500",
    "sg:province":"Antwerpen",
    "sg:tags":[
        "boutique"
    ],
    "wof:name":"Van Oosterwijck",
    "wof:placetype":"venue"
},
  "geometry": {"coordinates":[4.5694060326,51.131652832],"type":"Point"}
}