{
  "type": "Feature",
  "properties": {
    "iso:country":"BE",
    "sg:address":"Avenue Des Rouge-gorges 14",
    "sg:city":"Kraainem/kraainem",
    "sg:orig_category":"Installation \u00e9lectrique r\u00e9sidentielle",
    "sg:phone":"+32 2 731 74 54",
    "sg:postcode":"1950",
    "sg:province":"Vlaams-Brabant",
    "wof:name":"Pascal Hacquin",
    "wof:placetype":"venue"
},
  "geometry": {"coordinates":[4.472383976,50.8576660156],"type":"Point"}
}