{
  "type": "Feature",
  "properties": {
    "iso:country":"BE",
    "sg:address":"Hyacintenlaan 7",
    "sg:city":"Heusden-zolder",
    "sg:orig_category":"Plomberie, chauffage and installations sanitaires",
    "sg:phone":"+32 11 25 46 10",
    "sg:postcode":"3550",
    "sg:province":"Limburg",
    "wof:name":"Pagroco",
    "wof:placetype":"venue"
},
  "geometry": {"coordinates":[5.2964987755,50.9838409424],"type":"Point"}
}