{
  "type": "Feature",
  "properties": {
    "iso:country":"BE",
    "sg:address":"Gustave Latinislaan 15",
    "sg:city":"Schaarbeek/schaerbeek",
    "sg:orig_category":"Reclamebureaus",
    "sg:phone":"+32 2 242 47 11",
    "sg:postcode":"1030",
    "sg:province":"Bruxelles-Capitale",
    "wof:name":"Alin\u00c9a Communication",
    "wof:placetype":"venue"
},
  "geometry": {"coordinates":[4.3867788315,50.8671455383],"type":"Point"}
}