{
  "type": "Feature",
  "properties": {
    "iso:country":"BE",
    "sg:address":"Langstraat 118",
    "sg:city":"Herenthout",
    "sg:orig_category":"Schoenen",
    "sg:phone":"+32 14 50 03 53",
    "sg:postcode":"2270",
    "sg:province":"Antwerpen",
    "wof:name":"Huis Stippels",
    "wof:placetype":"venue"
},
  "geometry": {"coordinates":[4.747713089,51.1348953247],"type":"Point"}
}