{
  "type": "Feature",
  "properties": {
    "addr:full":"Gentsestraat 45 Harelbeke West-Vlaanderen 8530",
    "addr:housenumber":"45",
    "addr:postcode":"8530",
    "addr:street":"Gentsestraat",
    "iso:country":"BE",
    "sg:address":"Gentsestraat 45",
    "sg:city":"Harelbeke",
    "sg:classifiers":[
        {
            "category":"Health Services",
            "subcategory":"Chiropractor",
            "type":"Services"
        }
    ],
    "sg:phone":"+32 56 75 57 54",
    "sg:postcode":"8530",
    "sg:province":"West-Vlaanderen",
    "wof:name":"Desimpele H",
    "wof:placetype":"venue"
},
  "geometry": {"coordinates":[3.3154699802,50.8590545654],"type":"Point"}
}