{
  "type": "Feature",
  "properties": {
    "iso:country":"BE",
    "sg:address":"Boterbergstraat 71",
    "sg:city":"Kortenaken (waanrode)",
    "sg:classifiers":[
        {
            "category":"Insurance",
            "subcategory":"Insurance Agent",
            "type":"Services"
        }
    ],
    "sg:phone":"+32 16 77 04 25",
    "sg:postcode":"3473",
    "sg:province":"Vlaams-Brabant",
    "sg:tags":[
        "broker"
    ],
    "wof:name":"Vandelook-centea Zakenkantoor",
    "wof:placetype":"venue"
},
  "geometry": {"coordinates":[4.9916009903,50.9172668457],"type":"Point"}
}