{
  "type": "Feature",
  "properties": {
    "iso:country":"BE",
    "sg:address":"Kloosterstraat 10",
    "sg:city":"Herzele",
    "sg:classifiers":[
        {
            "category":"Real Estate",
            "subcategory":"Architect",
            "type":"Services"
        }
    ],
    "sg:phone":"+32 53 62 38 21",
    "sg:postcode":"9550",
    "sg:province":"Oost-Vlaanderen",
    "wof:name":"Devogeleer L",
    "wof:placetype":"venue"
},
  "geometry": {"coordinates":[3.893335104,50.8864593506],"type":"Point"}
}