{
  "type": "Feature",
  "properties": {
    "iso:country":"BE",
    "sg:address":"Sint-jan Vianneystraat 33",
    "sg:city":"Antwerpen (wilrijk)",
    "sg:classifiers":[
        {
            "category":"Shopping",
            "subcategory":"Party Supplies",
            "type":"Retail Goods"
        }
    ],
    "sg:phone":"+32 3 830 23 79",
    "sg:postcode":"2610",
    "sg:province":"Antwerpen",
    "sg:tags":[
        "rental",
        "-"
    ],
    "wof:name":"Schoeters Rental Services Bvba",
    "wof:placetype":"venue"
},
  "geometry": {"coordinates":[4.3946051598,51.1691131592],"type":"Point"}
}