{
  "type": "Feature",
  "properties": {
    "iso:country":"BE",
    "sg:address":"Bp 1149",
    "sg:city":"Charleroi",
    "sg:orig_category":"Springstoffen Fab",
    "sg:phone":"+32 71 56 07 58",
    "sg:postcode":"6000",
    "sg:province":"Hainaut",
    "wof:name":"Pyrowallonie",
    "wof:placetype":"venue"
},
  "geometry": {"coordinates":[4.4434351921,50.41015625],"type":"Point"}
}