{
  "type": "Feature",
  "properties": {
    "iso:country":"BE",
    "sg:address":"Burgemeester Voetslaan 6b1",
    "sg:city":"Peer",
    "sg:classifiers":[
        {
            "category":"Cafe",
            "type":"Food & Drink"
        }
    ],
    "sg:phone":"+32 11 63 25 74",
    "sg:postcode":"3990",
    "sg:province":"Limburg",
    "sg:tags":[
        "caf\u00e9s"
    ],
    "wof:name":"Caf\u00c9 Run Inn",
    "wof:placetype":"venue"
},
  "geometry": {"coordinates":[5.448925972,51.1365203857],"type":"Point"}
}