{
  "type": "Feature",
  "properties": {
    "addr:full":"Groot Begijnhof 29 Gent (sint-amandsberg) Oost-Vlaanderen 9040",
    "addr:housenumber":"29",
    "addr:postcode":"9040",
    "addr:street":"Groot Begijnhof",
    "iso:country":"BE",
    "sg:address":"Groot Begijnhof 29",
    "sg:city":"Gent (sint-amandsberg)",
    "sg:classifiers":[
        {
            "category":"Shopping",
            "subcategory":"Musical Instruments",
            "type":"Retail Goods"
        }
    ],
    "sg:phone":"+32 9 228 15 11",
    "sg:postcode":"9040",
    "sg:province":"Oost-Vlaanderen",
    "sg:tags":[
        "piano",
        "-",
        "tuning"
    ],
    "wof:name":"Reynaert",
    "wof:placetype":"venue"
},
  "geometry": {"coordinates":[3.7124900818,51.0594902039],"type":"Point"}
}