{
  "type": "Feature",
  "properties": {
    "addr:full":"Vezerlaan 1b1 Herk-de-stad Limburg 3540",
    "addr:housenumber":"1b1",
    "addr:postcode":"3540",
    "addr:street":"Vezerlaan",
    "iso:country":"BE",
    "sg:address":"Vezerlaan 1b1",
    "sg:city":"Herk-de-stad",
    "sg:orig_category":"Avocats and conseillers juridiques",
    "sg:phone":"+32 13 55 31 84",
    "sg:postcode":"3540",
    "sg:province":"Limburg",
    "wof:name":"Raskin",
    "wof:placetype":"venue"
},
  "geometry": {"coordinates":[5.1692562103,50.9422073364],"type":"Point"}
}