{
  "type": "Feature",
  "properties": {
    "iso:country":"BE",
    "sg:address":"Rue Alphonse Robert 63",
    "sg:city":"Incourt (opprebais)",
    "sg:classifiers":[
        {
            "category":"Building & Trades",
            "subcategory":"Construction",
            "type":"Services"
        }
    ],
    "sg:phone":"+32 10 88 98 73",
    "sg:postcode":"1315",
    "sg:province":"Brabant Wallon",
    "sg:tags":[
        "carpenter"
    ],
    "wof:name":"Lambrechts",
    "wof:placetype":"venue"
},
  "geometry": {"coordinates":[4.7624502182,50.6798591614],"type":"Point"}
}