{
  "type": "Feature",
  "properties": {
    "addr:full":"Rue D'asneux 12 Hamois Namur 5360",
    "addr:housenumber":"12",
    "addr:postcode":"5360",
    "addr:street":"Rue D'Asneux",
    "iso:country":"BE",
    "sg:address":"Rue D'asneux 12",
    "sg:city":"Hamois",
    "sg:orig_category":"Installatie van houten of kunststof schrijnwerk",
    "sg:phone":"+32 83 61 26 39",
    "sg:postcode":"5360",
    "sg:province":"Namur",
    "wof:name":"Menuiserie D'asneux",
    "wof:placetype":"venue"
},
  "geometry": {"coordinates":[5.1660761833,50.3451919556],"type":"Point"}
}