{
  "type": "Feature",
  "properties": {
    "addr:full":"Rue Entre-deux-villes 98 Blegny Li\u00e8ge 4670",
    "addr:housenumber":"98",
    "addr:postcode":"4670",
    "addr:street":"Rue Entre-Deux-Villes",
    "iso:country":"BE",
    "sg:address":"Rue Entre-deux-villes 98",
    "sg:city":"Blegny",
    "sg:orig_category":"V\u00e9hicules automobiles",
    "sg:phone":"+32 4 387 41 01",
    "sg:postcode":"4670",
    "sg:province":"Li\u00e8ge",
    "wof:name":"Spirlet - Blegny",
    "wof:placetype":"venue"
},
  "geometry": {"coordinates":[5.7196130753,50.6697616577],"type":"Point"}
}