{
  "type": "Feature",
  "properties": {
    "addr:full":"Rue De Marchienne 173a Thuin Hainaut 6534",
    "addr:housenumber":"173a",
    "addr:postcode":"6534",
    "addr:street":"Rue De Marchienne",
    "iso:country":"BE",
    "sg:address":"Rue De Marchienne 173a",
    "sg:city":"Thuin",
    "sg:orig_category":"D\u00e9taillants en pi\u00e8ces and accessoires de voitures",
    "sg:phone":"+32 71 51 87 62",
    "sg:postcode":"6534",
    "sg:province":"Hainaut",
    "wof:name":"Lekeu M.p.s.",
    "wof:placetype":"venue"
},
  "geometry": {"coordinates":[4.363902092,50.355255127],"type":"Point"}
}