{
  "type": "Feature",
  "properties": {
    "addr:full":"Diestsesteenweg 409 Aarschot (rillaar) Vlaams-Brabant 3202",
    "addr:housenumber":"409",
    "addr:postcode":"3202",
    "addr:street":"Diestsesteenweg",
    "iso:country":"BE",
    "sg:address":"Diestsesteenweg 409",
    "sg:city":"Aarschot (rillaar)",
    "sg:classifiers":[
        {
            "category":"Retail",
            "subcategory":"Auto Rental",
            "type":"Services"
        }
    ],
    "sg:phone":"+32 16 50 15 73",
    "sg:postcode":"3202",
    "sg:province":"Vlaams-Brabant",
    "sg:tags":[
        "plant",
        "flower",
        "-"
    ],
    "wof:name":"Vos",
    "wof:placetype":"venue"
},
  "geometry": {"coordinates":[4.9003520012,50.9745368958],"type":"Point"}
}