{
  "type": "Feature",
  "properties": {
    "iso:country":"BE",
    "sg:address":"En Hayeneux 103",
    "sg:city":"Herstal",
    "sg:classifiers":[
        {
            "category":"Professional",
            "subcategory":"Lawyer & Legal Services",
            "type":"Services"
        }
    ],
    "sg:phone":"+32 4 264 07 78",
    "sg:postcode":"4040",
    "sg:province":"Li\u00e8ge",
    "sg:tags":[
        "notary"
    ],
    "wof:name":"Gauthy J-m",
    "wof:placetype":"venue"
},
  "geometry": {"coordinates":[5.6191000938,50.6572799683],"type":"Point"}
}