{
  "type": "Feature",
  "properties": {
    "iso:country":"BE",
    "sg:address":"Rue Capitaine Crespel 6",
    "sg:city":"Bruxelles (ixelles)",
    "sg:classifiers":[
        {
            "category":"Travel",
            "subcategory":"Hotels & Motels",
            "type":"Entertainment"
        }
    ],
    "sg:phone":"+32 2 514 07 70",
    "sg:postcode":"1050",
    "sg:province":"Bruxelles-Capitale",
    "wof:name":"Argus",
    "wof:placetype":"venue"
},
  "geometry": {"coordinates":[4.3581171036,50.8360519409],"type":"Point"}
}