{
  "type": "Feature",
  "properties": {
    "addr:full":"Cit\u00e9 Georges Cornez 21 Colfontaine (wasmes) Hainaut 7340",
    "addr:housenumber":"21",
    "addr:postcode":"7340",
    "addr:street":"Cite\u0301 Georges Cornez",
    "iso:country":"BE",
    "sg:address":"Cit\u00e9 Georges Cornez 21",
    "sg:city":"Colfontaine (wasmes)",
    "sg:classifiers":[
        {
            "category":"Real Estate",
            "subcategory":"Architect",
            "type":"Services"
        }
    ],
    "sg:phone":"+32 479 30 80 27",
    "sg:postcode":"7340",
    "sg:province":"Hainaut",
    "wof:name":"Bessalah S",
    "wof:placetype":"venue"
},
  "geometry": {"coordinates":[3.840086937,50.4185256958],"type":"Point"}
}