{
  "type": "Feature",
  "properties": {
    "addr:full":"Potievre 9 Herve Li\u00e8ge 4650",
    "addr:housenumber":"9",
    "addr:postcode":"4650",
    "addr:street":"Potievre",
    "iso:country":"BE",
    "sg:address":"Potievre 9",
    "sg:city":"Herve",
    "sg:orig_category":"Kapsalons",
    "sg:phone":"+32 87 66 01 94",
    "sg:postcode":"4650",
    "sg:province":"Li\u00e8ge",
    "wof:name":"Coiffure Ana\u00cfs",
    "wof:placetype":"venue"
},
  "geometry": {"coordinates":[5.7943401337,50.6393814087],"type":"Point"}
}