{
  "type": "Feature",
  "properties": {
    "iso:country":"BE",
    "sg:address":"Rue Alphonse Helsen 21",
    "sg:city":"Les Bons Villers",
    "sg:orig_category":"Brood, gebak and snoepgoed",
    "sg:phone":"+32 71 85 12 13",
    "sg:postcode":"6211",
    "sg:province":"Hainaut",
    "wof:name":"Boulangerie Bourgeois",
    "wof:placetype":"venue"
},
  "geometry": {"coordinates":[4.4791898727,50.5055961609],"type":"Point"}
}