{
  "type": "Feature",
  "properties": {
    "addr:full":"Dijkstraat 23 Ham Limburg 3945",
    "addr:housenumber":"23",
    "addr:postcode":"3945",
    "addr:street":"Dijkstraat",
    "iso:country":"BE",
    "sg:address":"Dijkstraat 23",
    "sg:city":"Ham",
    "sg:classifiers":[
        {
            "category":"Arena",
            "subcategory":"Sports Club",
            "type":"Entertainment"
        }
    ],
    "sg:phone":"+32 13 66 37 83",
    "sg:postcode":"3945",
    "sg:province":"Limburg",
    "sg:tags":[
        "de"
    ],
    "wof:name":"Blijf Jong Genebos",
    "wof:placetype":"venue"
},
  "geometry": {"coordinates":[5.1776199341,51.1046104431],"type":"Point"}
}