{
  "type": "Feature",
  "properties": {
    "addr:full":"Avenue Alfred Madoux 11 Box 5 Bruxelles (woluwe-saint-pierre) Bruxelles-Capitale 1150",
    "addr:housenumber":"11;5",
    "addr:postcode":"1150",
    "addr:street":"Avenue Alfred Madoux;Box",
    "iso:country":"BE",
    "sg:address":"Avenue Alfred Madoux 11 Box 5",
    "sg:city":"Bruxelles (woluwe-saint-pierre)",
    "sg:classifiers":[
        {
            "category":"Manufacturing",
            "subcategory":"Paper Products",
            "type":"Manufacturing & Wholesale Goods"
        }
    ],
    "sg:phone":"+32 2 770 81 40",
    "sg:postcode":"1150",
    "sg:province":"Bruxelles-Capitale",
    "sg:tags":[
        "-"
    ],
    "wof:name":"Bourg Jean P Ets Sa",
    "wof:placetype":"venue"
},
  "geometry": {"coordinates":[4.4477381706,50.828666687],"type":"Point"}
}