{
  "type": "Feature",
  "properties": {
    "addr:full":"Graatakker 54 Turnhout Antwerpen 2300",
    "addr:housenumber":"54",
    "addr:postcode":"2300",
    "addr:street":"Graatakker",
    "iso:country":"BE",
    "sg:address":"Graatakker 54",
    "sg:city":"Turnhout",
    "sg:classifiers":[
        {
            "category":"Personal",
            "subcategory":"Beauty Salon",
            "type":"Services"
        }
    ],
    "sg:phone":"+32 14 42 60 49",
    "sg:postcode":"2300",
    "sg:province":"Antwerpen",
    "wof:name":"Atrium",
    "wof:placetype":"venue"
},
  "geometry": {"coordinates":[4.9502701759,51.3176193237],"type":"Point"}
}