{
  "type": "Feature",
  "properties": {
    "addr:full":"Esdoornlaan 5 Oostende West-Vlaanderen 8400",
    "addr:housenumber":"5",
    "addr:postcode":"8400",
    "addr:street":"Esdoornlaan",
    "iso:country":"BE",
    "sg:address":"Esdoornlaan 5",
    "sg:city":"Oostende",
    "sg:orig_category":"Architectes",
    "sg:phone":"+32 59 50 12 40",
    "sg:postcode":"8400",
    "sg:province":"West-Vlaanderen",
    "wof:name":"Tom Van Mieghem",
    "wof:placetype":"venue"
},
  "geometry": {"coordinates":[2.9126999378,51.2312583923],"type":"Point"}
}