{
  "type": "Feature",
  "properties": {
    "addr:full":"Paniswijerstraat 44 Genk Limburg 3600",
    "addr:housenumber":"44",
    "addr:postcode":"3600",
    "addr:street":"Paniswijerstraat",
    "iso:country":"BE",
    "sg:address":"Paniswijerstraat 44",
    "sg:city":"Genk",
    "sg:classifiers":[
        {
            "category":"Autos & Motor Vehicles",
            "subcategory":"Automobile Sales",
            "type":"Retail Goods"
        }
    ],
    "sg:phone":"+32 89 35 11 17",
    "sg:postcode":"3600",
    "sg:province":"Limburg",
    "sg:tags":[
        "equipment",
        "motor-cars",
        "transport"
    ],
    "wof:name":"Da Motors Nv",
    "wof:placetype":"venue"
},
  "geometry": {"coordinates":[5.4758758545,50.9455032349],"type":"Point"}
}