{
  "type": "Feature",
  "properties": {
    "iso:country":"BE",
    "sg:address":"Rue De La Filature 1ba",
    "sg:city":"Sint-gillis/saint-gilles",
    "sg:orig_category":"Agences de publicit\u00e9",
    "sg:phone":"+32 2 537 72 26",
    "sg:postcode":"1060",
    "sg:province":"Bruxelles-Capitale",
    "wof:name":"Bureau A.v.-comm.",
    "wof:placetype":"venue"
},
  "geometry": {"coordinates":[4.344979763,50.8317146301],"type":"Point"}
}