{
  "type": "Feature",
  "properties": {
    "addr:full":"Grote Markt 54 Kortrijk West-Vlaanderen 8500",
    "addr:housenumber":"54",
    "addr:postcode":"8500",
    "addr:street":"Grote Markt",
    "iso:country":"BE",
    "sg:address":"Grote Markt 54",
    "sg:city":"Kortrijk",
    "sg:classifiers":[
        {
            "category":"Restaurant",
            "type":"Food & Drink"
        }
    ],
    "sg:phone":"+32 56 21 91 87",
    "sg:postcode":"8500",
    "sg:province":"West-Vlaanderen",
    "sg:tags":[
        "caf\u00e9s"
    ],
    "wof:name":"De Raadskelder",
    "wof:placetype":"venue"
},
  "geometry": {"coordinates":[3.2648100853,50.8279762268],"type":"Point"}
}