{
  "type": "Feature",
  "properties": {
    "iso:country":"BE",
    "sg:address":"Amelscheid 23",
    "sg:city":"Sankt Vith (sch\u00f6nberg)",
    "sg:classifiers":[
        {
            "category":"Building & Trades",
            "subcategory":"Construction",
            "type":"Services"
        }
    ],
    "sg:phone":"+32 80 54 82 91",
    "sg:postcode":"4782",
    "sg:province":"Li\u00e8ge",
    "sg:tags":[
        "carpenter"
    ],
    "wof:name":"Hans-martiny M",
    "wof:placetype":"venue"
},
  "geometry": {"coordinates":[6.2570099831,50.2879943848],"type":"Point"}
}