{
  "type": "Feature",
  "properties": {
    "iso:country":"BE",
    "sg:address":"Rue De Namur 12",
    "sg:city":"Nivelles",
    "sg:orig_category":"Agences de voyages",
    "sg:phone":"+32 67 22 03 72",
    "sg:postcode":"1400",
    "sg:province":"Brabant Wallon",
    "wof:name":"Neckermann",
    "wof:placetype":"venue"
},
  "geometry": {"coordinates":[4.3255329132,50.5979042053],"type":"Point"}
}