{
  "type": "Feature",
  "properties": {
    "iso:country":"BE",
    "sg:address":"Hoge Buizemont 247",
    "sg:city":"Geraardsbergen",
    "sg:orig_category":"Maisons de repos and r\u00e9sidences",
    "sg:phone":"+32 54 43 28 25",
    "sg:postcode":"9500",
    "sg:province":"Oost-Vlaanderen",
    "wof:name":"Rusthuis Denderoord",
    "wof:placetype":"venue"
},
  "geometry": {"coordinates":[3.8815090656,50.7656326294],"type":"Point"}
}