{
  "type": "Feature",
  "properties": {
    "iso:country":"BE",
    "sg:address":"Rue Du Vieux Fr\u00cane 9",
    "sg:city":"Angleur",
    "sg:orig_category":"Centres de fitness. Clubs de sport. Centres de fitness. Centres sportifs",
    "sg:phone":"+32 4 338 44 44",
    "sg:postcode":"4031",
    "sg:province":"Li\u00e8ge",
    "wof:name":"Holiday Fitness Club",
    "wof:placetype":"venue"
},
  "geometry": {"coordinates":[5.5537519455,50.5669059753],"type":"Point"}
}