{
  "type": "Feature",
  "properties": {
    "iso:country":"BE",
    "sg:address":"Baronielaan 29",
    "sg:city":"Meulebeke",
    "sg:orig_category":"Enseignement secondaire g\u00e9n\u00e9ral. Enseignement secondaire technique and professionnel",
    "sg:phone":"+32 51 48 88 91",
    "sg:postcode":"8760",
    "sg:province":"West-Vlaanderen",
    "wof:name":"Instituut Ter Borcht",
    "wof:placetype":"venue"
},
  "geometry": {"coordinates":[3.2779829502,50.9475135803],"type":"Point"}
}