{
  "type": "Feature",
  "properties": {
    "iso:country":"BE",
    "sg:address":"Van Iseghemlaan 76a",
    "sg:city":"Oostende",
    "sg:classifiers":[
        {
            "category":"Shopping",
            "subcategory":"Gifts & Souvenirs",
            "type":"Retail Goods"
        }
    ],
    "sg:phone":"+32 59 43 43 13",
    "sg:postcode":"8400",
    "sg:province":"West-Vlaanderen",
    "sg:tags":[
        "-"
    ],
    "wof:name":"Cabientje ('t)",
    "wof:placetype":"venue"
},
  "geometry": {"coordinates":[2.912375927,51.2306976318],"type":"Point"}
}