{
  "type": "Feature",
  "properties": {
    "iso:country":"BE",
    "sg:address":"Leiestraat 26",
    "sg:city":"Menen",
    "sg:orig_category":"Zuivelproducten",
    "sg:phone":"+32 56 41 28 67",
    "sg:postcode":"8930",
    "sg:province":"West-Vlaanderen",
    "wof:name":"Huis Deleu-deboosere",
    "wof:placetype":"venue"
},
  "geometry": {"coordinates":[3.121336937,50.7925796509],"type":"Point"}
}