{
  "type": "Feature",
  "properties": {
    "addr:full":"Toleindestraat 35 Lochristi Oost-Vlaanderen 9080",
    "addr:housenumber":"35",
    "addr:postcode":"9080",
    "addr:street":"Toleindestraat",
    "iso:country":"BE",
    "sg:address":"Toleindestraat 35",
    "sg:city":"Lochristi",
    "sg:orig_category":"Banken and kredietinstellingen",
    "sg:phone":"+32 9 355 24 00",
    "sg:postcode":"9080",
    "sg:province":"Oost-Vlaanderen",
    "wof:name":"V.d.k. Spaarbank",
    "wof:placetype":"venue"
},
  "geometry": {"coordinates":[3.883975029,51.0804290771],"type":"Point"}
}