{
  "type": "Feature",
  "properties": {
    "addr:full":"Industrieweg 2 Balen Antwerpen 2490",
    "addr:housenumber":"2",
    "addr:postcode":"2490",
    "addr:street":"Industrieweg",
    "iso:country":"BE",
    "sg:address":"Industrieweg 2",
    "sg:city":"Balen",
    "sg:orig_category":"Bouwmaterialen Gh",
    "sg:phone":"+32 14 82 03 14",
    "sg:postcode":"2490",
    "sg:province":"Antwerpen",
    "wof:name":"Van Der Kooij",
    "wof:placetype":"venue"
},
  "geometry": {"coordinates":[5.1644201279,51.1993103027],"type":"Point"}
}