{
  "type": "Feature",
  "properties": {
    "addr:full":"Rue Es Fays 37 Namur Namur 5101",
    "addr:housenumber":"37",
    "addr:postcode":"5101",
    "addr:street":"Rue Es Fays",
    "iso:country":"BE",
    "sg:address":"Rue Es Fays 37",
    "sg:city":"Namur",
    "sg:orig_category":"Dranken Slagers Zuivelproducten",
    "sg:phone":"+32 81 58 82 95",
    "sg:postcode":"5101",
    "sg:province":"Namur",
    "wof:name":"Gaston Gorane",
    "wof:placetype":"venue"
},
  "geometry": {"coordinates":[4.904815197,50.4481887817],"type":"Point"}
}