{
  "type": "Feature",
  "properties": {
    "iso:country":"BE",
    "sg:address":"Simonsestraat 4-2",
    "sg:city":"Mol",
    "sg:classifiers":[
        {
            "category":"Banks & Credit Unions",
            "subcategory":"Investment Brokerage",
            "type":"Services"
        }
    ],
    "sg:phone":"+32 14 43 57 18",
    "sg:postcode":"2400",
    "sg:province":"Antwerpen",
    "sg:tags":[
        "-",
        "plastic"
    ],
    "wof:name":"Multidop Plastics Nv",
    "wof:placetype":"venue"
},
  "geometry": {"coordinates":[5.160378933,51.2053756714],"type":"Point"}
}