{
  "type": "Feature",
  "properties": {
    "addr:full":"Pintestraat 65 De Pinte Oost-Vlaanderen 9840",
    "addr:housenumber":"65",
    "addr:postcode":"9840",
    "addr:street":"Pintestraat",
    "iso:country":"BE",
    "sg:address":"Pintestraat 65",
    "sg:city":"De Pinte",
    "sg:orig_category":"Banken and kredietinstellingen",
    "sg:phone":"+32 9 282 66 40",
    "sg:postcode":"9840",
    "sg:province":"Oost-Vlaanderen",
    "wof:name":"Kbc",
    "wof:placetype":"venue"
},
  "geometry": {"coordinates":[3.6453630924,50.9899559021],"type":"Point"}
}