{
  "type": "Feature",
  "properties": {
    "addr:full":"Rue Grande 129 Beloeil (bas\u00e8cles) Hainaut 7971",
    "addr:housenumber":"129",
    "addr:postcode":"7971",
    "addr:street":"Rue Grande",
    "iso:country":"BE",
    "sg:address":"Rue Grande 129",
    "sg:city":"Beloeil (bas\u00e8cles)",
    "sg:classifiers":[
        {
            "category":"Personal",
            "subcategory":"Beauty Salon",
            "type":"Services"
        }
    ],
    "sg:phone":"+32 69 57 75 37",
    "sg:postcode":"7971",
    "sg:province":"Hainaut",
    "wof:name":"Jardin De Beaut\u00e9 (au)",
    "wof:placetype":"venue"
},
  "geometry": {"coordinates":[3.6543691158,50.5234603882],"type":"Point"}
}