{
  "type": "Feature",
  "properties": {
    "addr:full":"Clarastraat 10 Tongeren Limburg 3700",
    "addr:housenumber":"10",
    "addr:postcode":"3700",
    "addr:street":"Clarastraat",
    "iso:country":"BE",
    "sg:address":"Clarastraat 10",
    "sg:city":"Tongeren",
    "sg:classifiers":[
        {
            "category":"Shopping",
            "subcategory":"Jewelry",
            "type":"Retail Goods"
        }
    ],
    "sg:phone":"+32 12 23 79 05",
    "sg:postcode":"3700",
    "sg:province":"Limburg",
    "sg:tags":[
        "jeweller",
        "-"
    ],
    "wof:name":"Lenaers D",
    "wof:placetype":"venue"
},
  "geometry": {"coordinates":[5.4697260857,50.7731323242],"type":"Point"}
}