{
  "type": "Feature",
  "properties": {
    "iso:country":"BE",
    "sg:address":"Thomas Van Loostraat 25",
    "sg:city":"Oostende",
    "sg:orig_category":"Slagers",
    "sg:phone":"+32 59 32 12 19",
    "sg:postcode":"8400",
    "sg:province":"West-Vlaanderen",
    "wof:name":"Mireille Bogaert",
    "wof:placetype":"venue"
},
  "geometry": {"coordinates":[2.9426081181,51.2305221558],"type":"Point"}
}