{
  "type": "Feature",
  "properties": {
    "iso:country":"BE",
    "sg:address":"Elshouterbosstraat 2",
    "sg:city":"Diepenbeek",
    "sg:classifiers":[
        {
            "category":"Building & Trades",
            "subcategory":"Plumbing",
            "type":"Services"
        }
    ],
    "sg:phone":"+32 11 32 25 02",
    "sg:postcode":"3590",
    "sg:province":"Limburg",
    "sg:tags":[
        "repair",
        "mainten",
        "-",
        "central",
        "heating"
    ],
    "wof:name":"Jacobs F",
    "wof:placetype":"venue"
},
  "geometry": {"coordinates":[5.4362511635,50.8955345154],"type":"Point"}
}