{
  "type": "Feature",
  "properties": {
    "iso:country":"BE",
    "sg:address":"Chauss\u00c9e Du Roeulx 484",
    "sg:city":"Mons",
    "sg:orig_category":"Instituts de beaut\u00e9",
    "sg:phone":"+32 65 36 21 02",
    "sg:postcode":"7000",
    "sg:province":"Hainaut",
    "wof:name":"Marie-paule Glaneur",
    "wof:placetype":"venue"
},
  "geometry": {"coordinates":[3.9959740639,50.4583473206],"type":"Point"}
}