{
  "type": "Feature",
  "properties": {
    "addr:full":"Dennestraat 2 Geel Antwerpen 2440",
    "addr:housenumber":"2",
    "addr:postcode":"2440",
    "addr:street":"Dennestraat",
    "iso:country":"BE",
    "sg:address":"Dennestraat 2",
    "sg:city":"Geel",
    "sg:classifiers":[
        {
            "category":"Professional",
            "subcategory":"Computer Services",
            "type":"Services"
        }
    ],
    "sg:phone":"+32 14 58 05 80",
    "sg:postcode":"2440",
    "sg:province":"Antwerpen",
    "sg:tags":[
        "-",
        "processing",
        "data",
        "software"
    ],
    "wof:name":"Jocofi Services",
    "wof:placetype":"venue"
},
  "geometry": {"coordinates":[5.008409977,51.1236381531],"type":"Point"}
}