{
  "type": "Feature",
  "properties": {
    "addr:full":"Rue Entre Deux Portes 5 Huy Li\u00e8ge 4500",
    "addr:housenumber":"5",
    "addr:postcode":"4500",
    "addr:street":"Rue Entre Deux Portes",
    "iso:country":"BE",
    "sg:address":"Rue Entre Deux Portes 5",
    "sg:city":"Huy",
    "sg:orig_category":"Electrom\u00e9nager, t\u00e9l\u00e9visions and radios. Mat\u00e9riel de T\u00e9l\u00e9communication",
    "sg:phone":"+32 85 21 11 80",
    "sg:postcode":"4500",
    "sg:province":"Li\u00e8ge",
    "wof:name":"Eldi",
    "wof:placetype":"venue"
},
  "geometry": {"coordinates":[5.2301588058,50.5251464844],"type":"Point"}
}