{
  "type": "Feature",
  "properties": {
    "addr:full":"Deuzeldlaan 87 Schoten Antwerpen 2900",
    "addr:housenumber":"87",
    "addr:postcode":"2900",
    "addr:street":"Deuzeldlaan",
    "iso:country":"BE",
    "sg:address":"Deuzeldlaan 87",
    "sg:city":"Schoten",
    "sg:orig_category":"V\u00e9t\u00e9rinaires",
    "sg:phone":"+32 3 645 26 43",
    "sg:postcode":"2900",
    "sg:province":"Antwerpen",
    "wof:name":"Elsy Leysen",
    "wof:placetype":"venue"
},
  "geometry": {"coordinates":[4.4651927948,51.2448272705],"type":"Point"}
}