{
  "type": "Feature",
  "properties": {
    "iso:country":"BE",
    "sg:address":"Avenue Du B\u00e9lian 30",
    "sg:city":"Mons",
    "sg:classifiers":[
        {
            "category":"Professional",
            "subcategory":"Testing Lab",
            "type":"Services"
        }
    ],
    "sg:phone":"+32 65 33 59 07",
    "sg:postcode":"7000",
    "sg:province":"Hainaut",
    "sg:tags":[
        "chemist"
    ],
    "wof:name":"Familia",
    "wof:placetype":"venue"
},
  "geometry": {"coordinates":[3.945982933,50.4390258789],"type":"Point"}
}