{
  "type": "Feature",
  "properties": {
    "addr:full":"R De La Liberte 3 Beauvechain Brabant Wallon 1320",
    "addr:housenumber":"3",
    "addr:postcode":"1320",
    "addr:street":"La Liberte",
    "iso:country":"BE",
    "sg:address":"R De La Liberte 3",
    "sg:city":"Beauvechain",
    "sg:classifiers":[
        {
            "category":"Professional",
            "subcategory":"Management & Consulting",
            "type":"Services"
        }
    ],
    "sg:phone":"+32 10 86 06 67",
    "sg:postcode":"1320",
    "sg:province":"Brabant Wallon",
    "sg:tags":[
        "consultant"
    ],
    "wof:name":"Agri Immo Management & Invest",
    "wof:placetype":"venue"
},
  "geometry": {"coordinates":[4.7441210747,50.7774810791],"type":"Point"}
}