{
  "type": "Feature",
  "properties": {
    "addr:full":"Geelsebaan 74 Retie Antwerpen 2470",
    "addr:housenumber":"74",
    "addr:postcode":"2470",
    "addr:street":"Geelsebaan",
    "iso:country":"BE",
    "sg:address":"Geelsebaan 74",
    "sg:city":"Retie",
    "sg:classifiers":[
        {
            "category":"Professional",
            "subcategory":"Engineering",
            "type":"Services"
        }
    ],
    "sg:phone":"+32 14 37 54 45",
    "sg:postcode":"2470",
    "sg:province":"Antwerpen",
    "sg:tags":[
        "environmental",
        "technique",
        "-"
    ],
    "wof:name":"Eco2",
    "wof:placetype":"venue"
},
  "geometry": {"coordinates":[5.0763912201,51.2555809021],"type":"Point"}
}