{
  "type": "Feature",
  "properties": {
    "addr:full":"Kasteelstraat 35 Kruishoutem Oost-Vlaanderen 9770",
    "addr:housenumber":"35",
    "addr:postcode":"9770",
    "addr:street":"Kasteelstraat",
    "iso:country":"BE",
    "sg:address":"Kasteelstraat 35",
    "sg:city":"Kruishoutem",
    "sg:orig_category":"Installation \u00e9lectrique r\u00e9sidentielle",
    "sg:phone":"+32 9 383 50 09",
    "sg:postcode":"9770",
    "sg:province":"Oost-Vlaanderen",
    "wof:name":"Dirk Bauters",
    "wof:placetype":"venue"
},
  "geometry": {"coordinates":[3.5411200523,50.9136161804],"type":"Point"}
}