{
  "type": "Feature",
  "properties": {
    "iso:country":"BE",
    "sg:address":"Rue De Willemeau 22",
    "sg:city":"Tournai (saint-maur-ere)",
    "sg:classifiers":[
        {
            "category":"Professional",
            "subcategory":"Management & Consulting",
            "type":"Services"
        }
    ],
    "sg:phone":"+32 69 64 12 19",
    "sg:postcode":"7500",
    "sg:province":"Hainaut",
    "sg:tags":[
        "consultant",
        "agency",
        "advertising"
    ],
    "wof:name":"Visualpub-posterit",
    "wof:placetype":"venue"
},
  "geometry": {"coordinates":[3.3813350201,50.5982894897],"type":"Point"}
}