{
  "type": "Feature",
  "properties": {
    "iso:country":"BE",
    "sg:address":"Neerveldstraat 109",
    "sg:city":"Sint-lambrechts-woluwe/woluwe-saint-lambert",
    "sg:orig_category":"Krantenuitgeverijen Tijdschriftenuitgeverijen",
    "sg:phone":"+32 2 776 22 11",
    "sg:postcode":"1200",
    "sg:province":"Bruxelles-Capitale",
    "wof:name":"Mediaxis",
    "wof:placetype":"venue"
},
  "geometry": {"coordinates":[4.4424629211,50.8534355164],"type":"Point"}
}