{
  "type": "Feature",
  "properties": {
    "iso:country":"BE",
    "sg:address":"Industrieweg 166",
    "sg:city":"Gent",
    "sg:orig_category":"Industri\u00eble and commerci\u00eble bouw",
    "sg:phone":"+32 9 226 79 11",
    "sg:postcode":"9030",
    "sg:province":"Oost-Vlaanderen",
    "wof:name":"Van Autryve Bouwbedrijf",
    "wof:placetype":"venue"
},
  "geometry": {"coordinates":[3.679158926,51.0880470276],"type":"Point"}
}