{
  "type": "Feature",
  "properties": {
    "addr:full":"Murringen 4 B\u00dcllingen/bullange Li\u00e8ge 4760",
    "addr:housenumber":"4",
    "addr:postcode":"4760",
    "addr:street":"Murringen",
    "iso:country":"BE",
    "sg:address":"Murringen 4",
    "sg:city":"B\u00dcllingen/bullange",
    "sg:orig_category":"Rundveehouders",
    "sg:phone":"+32 80 64 75 64",
    "sg:postcode":"4760",
    "sg:province":"Li\u00e8ge",
    "wof:name":"Edith Roehl",
    "wof:placetype":"venue"
},
  "geometry": {"coordinates":[6.304910183,50.4083137512],"type":"Point"}
}