{
  "type": "Feature",
  "properties": {
    "addr:full":"Avenue Victor Jacobs 69 Box 7 Bruxelles (etterbeek) Bruxelles-Capitale 1040",
    "addr:housenumber":"69;7",
    "addr:postcode":"1040",
    "addr:street":"Avenue Victor Jacobs;Box",
    "iso:country":"BE",
    "sg:address":"Avenue Victor Jacobs 69 Box 7",
    "sg:city":"Bruxelles (etterbeek)",
    "sg:classifiers":[
        {
            "category":"Health Services",
            "subcategory":"Health Practitioner",
            "type":"Services"
        }
    ],
    "sg:phone":"+32 2 733 28 64",
    "sg:postcode":"1040",
    "sg:province":"Bruxelles-Capitale",
    "sg:tags":[
        "therapist",
        "speech"
    ],
    "wof:name":"Strebelle D",
    "wof:placetype":"venue"
},
  "geometry": {"coordinates":[4.3820619583,50.8302650452],"type":"Point"}
}