{
  "type": "Feature",
  "properties": {
    "addr:full":"Dorp 13 Rijkevorsel Antwerpen 2310",
    "addr:housenumber":"13",
    "addr:postcode":"2310",
    "addr:street":"Dorp",
    "iso:country":"BE",
    "sg:address":"Dorp 13",
    "sg:city":"Rijkevorsel",
    "sg:orig_category":"Slagers",
    "sg:phone":"+32 3 314 60 96",
    "sg:postcode":"2310",
    "sg:province":"Antwerpen",
    "wof:name":"Marc Hofkens",
    "wof:placetype":"venue"
},
  "geometry": {"coordinates":[4.7598648071,51.3502197266],"type":"Point"}
}