{
  "type": "Feature",
  "properties": {
    "iso:country":"BE",
    "sg:address":"Potaerdegatstr 18a",
    "sg:city":"Brussel",
    "sg:classifiers":[
        {
            "category":"Professional",
            "subcategory":"Advertising",
            "type":"Services"
        }
    ],
    "sg:phone":"+32 2 469 17 00",
    "sg:postcode":"1080",
    "sg:province":"Bruxelles-Capitale",
    "sg:tags":[
        "information",
        "medium",
        "communication"
    ],
    "wof:name":"Mmp-filmproduktie Cv",
    "wof:placetype":"venue"
},
  "geometry": {"coordinates":[4.3058581352,50.8596115112],"type":"Point"}
}