{
  "type": "Feature",
  "properties": {
    "addr:full":"F\u00c9ronstr\u00c9e 16 Li\u00c8ge Li\u00e8ge 4000",
    "addr:housenumber":"16",
    "addr:postcode":"4000",
    "addr:street":"Fe\u0301Ronstre\u0301E",
    "iso:country":"BE",
    "sg:address":"F\u00c9ronstr\u00c9e 16",
    "sg:city":"Li\u00c8ge",
    "sg:orig_category":"R\u00e9parations de chaussures and articles en cuir",
    "sg:phone":"+32 4 358 63 69",
    "sg:postcode":"4000",
    "sg:province":"Li\u00e8ge",
    "wof:name":"Cordonnerie Mario",
    "wof:placetype":"venue"
},
  "geometry": {"coordinates":[5.5776910782,50.6458969116],"type":"Point"}
}