{
  "type": "Feature",
  "properties": {
    "iso:country":"BE",
    "sg:address":"Stationstraat 15",
    "sg:city":"Dilbeek (groot)",
    "sg:orig_category":"Goederenvervoer over de weg Koerierbedrijven Verhuisdiensten",
    "sg:phone":"+32 497 37 73 27",
    "sg:postcode":"1702",
    "sg:province":"Vlaams-Brabant",
    "wof:name":"All Delivery Transport",
    "wof:placetype":"venue"
},
  "geometry": {"coordinates":[4.2732892036,50.869354248],"type":"Point"}
}