{
  "type": "Feature",
  "properties": {
    "addr:full":"Route D'eghez\u00c9e 79 Jemeppe-sur-sambre Namur 5190",
    "addr:housenumber":"79",
    "addr:postcode":"5190",
    "addr:street":"Route D'Egheze \u0301E",
    "iso:country":"BE",
    "sg:address":"Route D'eghez\u00c9e 79",
    "sg:city":"Jemeppe-sur-sambre",
    "sg:orig_category":"Paramedische behandelingen",
    "sg:phone":"+32 71 78 46 16",
    "sg:postcode":"5190",
    "sg:province":"Namur",
    "wof:name":"A. Lesire",
    "wof:placetype":"venue"
},
  "geometry": {"coordinates":[4.670788765,50.4641075134],"type":"Point"}
}