{
  "type": "Feature",
  "properties": {
    "iso:country":"BE",
    "sg:address":"Baljuwstraat 51c",
    "sg:city":"Poperinge (reningelst)",
    "sg:orig_category":"Non-Classified Establishments",
    "sg:phone":"+32 57 33 85 88",
    "sg:postcode":"8970",
    "sg:province":"West-Vlaanderen",
    "wof:name":"Dimabel Bvba",
    "wof:placetype":"venue"
},
  "geometry": {"coordinates":[2.7577850819,50.8196868896],"type":"Point"}
}