{
  "type": "Feature",
  "properties": {
    "addr:full":"Avenue De Voroux 7 Li\u00c8ge Li\u00e8ge 4000",
    "addr:housenumber":"7",
    "addr:postcode":"4000",
    "addr:street":"Avenue De Voroux",
    "iso:country":"BE",
    "sg:address":"Avenue De Voroux 7",
    "sg:city":"Li\u00c8ge",
    "sg:classifiers":[
        {
            "category":"Food & Beverages",
            "subcategory":"Meat & Fish",
            "type":"Retail Goods"
        }
    ],
    "sg:phone":"+32 4 246 44 97",
    "sg:postcode":"4000",
    "sg:province":"Li\u00e8ge",
    "sg:tags":[
        "vi",
        "zeevruchten"
    ],
    "wof:name":"Marc Devillers",
    "wof:placetype":"venue"
},
  "geometry": {"coordinates":[5.5594229698,50.680355072],"type":"Point"}
}