{
  "type": "Feature",
  "properties": {
    "addr:full":"Boncquetstraat 17 Ardooie West-Vlaanderen 8850",
    "addr:housenumber":"17",
    "addr:postcode":"8850",
    "addr:street":"Boncquetstraat",
    "iso:country":"BE",
    "sg:address":"Boncquetstraat 17",
    "sg:city":"Ardooie",
    "sg:orig_category":"Installation de menuiserie en bois and plastique",
    "sg:phone":"+32 51 74 56 76",
    "sg:postcode":"8850",
    "sg:province":"West-Vlaanderen",
    "wof:name":"Eddy Van Acker",
    "wof:placetype":"venue"
},
  "geometry": {"coordinates":[3.201488018,50.9856834412],"type":"Point"}
}