{
  "type": "Feature",
  "properties": {
    "addr:full":"Avenue Du Front 11 Bruxelles (etterbeek) Bruxelles-Capitale 1040",
    "addr:housenumber":"11",
    "addr:postcode":"1040",
    "addr:street":"Avenue Du Front",
    "iso:country":"BE",
    "sg:address":"Avenue Du Front 11",
    "sg:city":"Bruxelles (etterbeek)",
    "sg:classifiers":[
        {
            "category":"Professional",
            "subcategory":"Testing Lab",
            "type":"Services"
        }
    ],
    "sg:phone":"+32 2 736 12 53",
    "sg:postcode":"1040",
    "sg:province":"Bruxelles-Capitale",
    "sg:tags":[
        "laboratory",
        "medical"
    ],
    "wof:name":"Shi Yu",
    "wof:placetype":"venue"
},
  "geometry": {"coordinates":[4.4003491402,50.8328018188],"type":"Point"}
}