{
  "type": "Feature",
  "properties": {
    "iso:country":"BE",
    "sg:address":"Achterbroeksteenweg 25",
    "sg:city":"Kalmthout",
    "sg:classifiers":[
        {
            "category":"Health Services",
            "subcategory":"Health Practitioner",
            "type":"Services"
        }
    ],
    "sg:phone":"+32 3 666 90 80",
    "sg:postcode":"2920",
    "sg:province":"Antwerpen",
    "sg:tags":[
        "physiotherapist"
    ],
    "wof:name":"Adriaensen P",
    "wof:placetype":"venue"
},
  "geometry": {"coordinates":[4.4772357941,51.394367218],"type":"Point"}
}