{
  "type": "Feature",
  "properties": {
    "iso:country":"BE",
    "sg:address":"Steenvoordestraat 155",
    "sg:city":"Destelbergen",
    "sg:orig_category":"Bloemen and planten Gh",
    "sg:phone":"+32 9 252 37 40",
    "sg:postcode":"9070",
    "sg:province":"Oost-Vlaanderen",
    "wof:name":"Roggeman H",
    "wof:placetype":"venue"
},
  "geometry": {"coordinates":[3.8121509552,51.0158843994],"type":"Point"}
}