{
  "type": "Feature",
  "properties": {
    "addr:full":"Blekerijstraat 75 Gent Oost-Vlaanderen 9000",
    "addr:housenumber":"75",
    "addr:postcode":"9000",
    "addr:street":"Blekerijstraat;Oost-Vlaanderen",
    "iso:country":"BE",
    "sg:address":"Blekerijstraat 75",
    "sg:city":"Gent",
    "sg:classifiers":[
        {
            "category":"Professional",
            "subcategory":"Art Services",
            "type":"Services"
        }
    ],
    "sg:phone":"+32 9 224 30 37",
    "sg:postcode":"9000",
    "sg:province":"Oost-Vlaanderen",
    "sg:tags":[
        "graphic",
        "designer"
    ],
    "wof:name":"Kenens Hub",
    "wof:placetype":"venue"
},
  "geometry": {"coordinates":[3.7326099873,51.0597686768],"type":"Point"}
}