{
  "type": "Feature",
  "properties": {
    "addr:full":"Square Ambiorix 30 Bruxelles Bruxelles-Capitale 1000",
    "addr:housenumber":"30",
    "addr:postcode":"1000",
    "addr:street":"Square Ambiorix",
    "iso:country":"BE",
    "sg:address":"Square Ambiorix 30",
    "sg:city":"Bruxelles",
    "sg:classifiers":[
        {
            "category":"Health Services",
            "subcategory":"Dentist",
            "type":"Services"
        }
    ],
    "sg:phone":"+32 2 735 12 39",
    "sg:postcode":"1000",
    "sg:province":"Bruxelles-Capitale",
    "wof:name":"Verheyen B",
    "wof:placetype":"venue"
},
  "geometry": {"coordinates":[4.3840718269,50.846157074],"type":"Point"}
}