{
  "type": "Feature",
  "properties": {
    "addr:full":"Molenbergstraat 133 Stekene Oost-Vlaanderen 9190",
    "addr:housenumber":"133",
    "addr:postcode":"9190",
    "addr:street":"Molenbergstraat",
    "iso:country":"BE",
    "sg:address":"Molenbergstraat 133",
    "sg:city":"Stekene",
    "sg:classifiers":[
        {
            "category":"Home & Garden",
            "subcategory":"Hardware",
            "type":"Retail Goods"
        }
    ],
    "sg:phone":"+32 3 790 12 12",
    "sg:postcode":"9190",
    "sg:province":"Oost-Vlaanderen",
    "sg:tags":[
        "gate",
        "opener",
        "door",
        "automatic"
    ],
    "wof:name":"B.d.l. Bvba",
    "wof:placetype":"venue"
},
  "geometry": {"coordinates":[4.0303969383,51.2123222351],"type":"Point"}
}