{
  "type": "Feature",
  "properties": {
    "addr:full":"Stationstraat 36 Tielt West-Vlaanderen 8700",
    "addr:housenumber":"36",
    "addr:postcode":"8700",
    "addr:street":"Stationstraat",
    "iso:country":"BE",
    "sg:address":"Stationstraat 36",
    "sg:city":"Tielt",
    "sg:orig_category":"Imprimeries and copyshops",
    "sg:phone":"+32 51 40 02 08",
    "sg:postcode":"8700",
    "sg:province":"West-Vlaanderen",
    "wof:name":"Drukkerij E Baert",
    "wof:placetype":"venue"
},
  "geometry": {"coordinates":[3.3272941113,50.9928741455],"type":"Point"}
}