{
  "type": "Feature",
  "properties": {
    "addr:full":"Warandestraat 4 Oostkamp West-Vlaanderen 8020",
    "addr:housenumber":"4",
    "addr:postcode":"8020",
    "addr:street":"Warandestraat",
    "iso:country":"BE",
    "sg:address":"Warandestraat 4",
    "sg:city":"Oostkamp",
    "sg:classifiers":[
        {
            "category":"Personal",
            "subcategory":"Nail Salon",
            "type":"Services"
        }
    ],
    "sg:phone":"+32 50 38 62 66",
    "sg:postcode":"8020",
    "sg:province":"West-Vlaanderen",
    "sg:tags":[
        "pedicure"
    ],
    "wof:name":"Dossche N",
    "wof:placetype":"venue"
},
  "geometry": {"coordinates":[3.235047102,51.1701660156],"type":"Point"}
}