{
  "type": "Feature",
  "properties": {
    "iso:country":"BE",
    "sg:address":"Djepstraat 8",
    "sg:city":"Geel",
    "sg:orig_category":"Advocaten and juridische adviseurs",
    "sg:phone":"+32 14 58 99 71",
    "sg:postcode":"2440",
    "sg:province":"Antwerpen",
    "wof:name":"Steven Hooyberghs",
    "wof:placetype":"venue"
},
  "geometry": {"coordinates":[5.0214300156,51.1342658997],"type":"Point"}
}