{
  "type": "Feature",
  "properties": {
    "addr:full":"Tramstraat 10ba Tielt West-Vlaanderen 8700",
    "addr:housenumber":"10ba",
    "addr:postcode":"8700",
    "addr:street":"Tramstraat",
    "iso:country":"BE",
    "sg:address":"Tramstraat 10ba",
    "sg:city":"Tielt",
    "sg:classifiers":[
        {
            "category":"Cafe",
            "type":"Food & Drink"
        }
    ],
    "sg:phone":"+32 51 40 97 59",
    "sg:postcode":"8700",
    "sg:province":"West-Vlaanderen",
    "sg:tags":[
        "caf\u00e9s"
    ],
    "wof:name":"Caf\u00c9 Amiticia",
    "wof:placetype":"venue"
},
  "geometry": {"coordinates":[3.3278689384,51.0013313293],"type":"Point"}
}