{
  "type": "Feature",
  "properties": {
    "iso:country":"BE",
    "sg:address":"Herent 104a",
    "sg:city":"Neerpelt",
    "sg:classifiers":[
        {
            "category":"Building & Trades",
            "subcategory":"Construction",
            "type":"Services"
        }
    ],
    "sg:phone":"+32 11 66 51 38",
    "sg:postcode":"3910",
    "sg:province":"Limburg",
    "sg:tags":[
        "stucco",
        "contractor"
    ],
    "wof:name":"Dewitz K",
    "wof:placetype":"venue"
},
  "geometry": {"coordinates":[5.4440088272,51.2055702209],"type":"Point"}
}