{
  "type": "Feature",
  "properties": {
    "addr:full":"Rue Du Falchena 10 Li\u00e8ge 1 (grivegn\u00e9e) Li\u00e8ge 4030",
    "addr:housenumber":"10;1",
    "addr:postcode":"4030",
    "addr:street":"Rue Du Falchena",
    "iso:country":"BE",
    "sg:address":"Rue Du Falchena 10",
    "sg:city":"Li\u00e8ge 1 (grivegn\u00e9e)",
    "sg:classifiers":[
        {
            "category":"Professional",
            "subcategory":"Accounting & Tax Preparation",
            "type":"Services"
        }
    ],
    "sg:phone":"+32 4 342 29 87",
    "sg:postcode":"4030",
    "sg:province":"Li\u00e8ge",
    "sg:tags":[
        "accountant"
    ],
    "wof:name":"Hougardy J-p",
    "wof:placetype":"venue"
},
  "geometry": {"coordinates":[5.5939412117,50.6235198975],"type":"Point"}
}