{
  "type": "Feature",
  "properties": {
    "iso:country":"BE",
    "sg:address":"Rue Boden 29",
    "sg:city":"Waremme",
    "sg:orig_category":"Rundveehouders Varkenskwekers",
    "sg:phone":"+32 19 32 27 48",
    "sg:postcode":"4300",
    "sg:province":"Li\u00e8ge",
    "wof:name":"Philippe Henrioulle",
    "wof:placetype":"venue"
},
  "geometry": {"coordinates":[5.2337398529,50.7104911804],"type":"Point"}
}