{
  "type": "Feature",
  "properties": {
    "addr:full":"Nieuwbaan 29a Sint-katherina-lombeek Vlaams-Brabant 1742",
    "addr:housenumber":"29a",
    "addr:postcode":"1742",
    "addr:street":"Nieuwbaan",
    "iso:country":"BE",
    "sg:address":"Nieuwbaan 29a",
    "sg:city":"Sint-katherina-lombeek",
    "sg:orig_category":"Tubes, Collapsible",
    "sg:phone":"+32 53 64 70 20",
    "sg:postcode":"1742",
    "sg:province":"Vlaams-Brabant",
    "wof:name":"Tubes Souples Nv",
    "wof:placetype":"venue"
},
  "geometry": {"coordinates":[4.1238517761,50.880065918],"type":"Point"}
}