{
  "type": "Feature",
  "properties": {
    "addr:full":"Zoning Mongaveau 1 Str\u00e9py-bracquegnies Hainaut 7110",
    "addr:housenumber":"1",
    "addr:postcode":"7110",
    "addr:street":"Mongaveau;Hainaut",
    "iso:country":"BE",
    "sg:address":"Zoning Mongaveau 1",
    "sg:city":"Str\u00e9py-bracquegnies",
    "sg:classifiers":[
        {
            "category":"Manufacturing",
            "subcategory":"Rubber & Plastics",
            "type":"Manufacturing & Wholesale Goods"
        }
    ],
    "sg:phone":"+32 64 67 70 51",
    "sg:postcode":"7110",
    "sg:province":"Hainaut",
    "sg:tags":[
        "foam",
        "processing",
        "polyurethane"
    ],
    "wof:name":"Foam-tec S.a.",
    "wof:placetype":"venue"
},
  "geometry": {"coordinates":[4.1295051575,50.4733352661],"type":"Point"}
}