{
  "type": "Feature",
  "properties": {
    "addr:full":"Onledemolenstraat 2ba Roeselare West-Vlaanderen 8800",
    "addr:housenumber":"2ba",
    "addr:postcode":"8800",
    "addr:street":"Onledemolenstraat",
    "iso:country":"BE",
    "sg:address":"Onledemolenstraat 2ba",
    "sg:city":"Roeselare",
    "sg:orig_category":"Machines \u00e0 coudre and tricoter",
    "sg:phone":"+32 51 22 52 42",
    "sg:postcode":"8800",
    "sg:province":"West-Vlaanderen",
    "wof:name":"Freddy Decadt",
    "wof:placetype":"venue"
},
  "geometry": {"coordinates":[3.142136097,50.9745864868],"type":"Point"}
}