{
  "type": "Feature",
  "properties": {
    "addr:full":"Brouwerijstraat 1b1 Aarschot Vlaams-Brabant 3200",
    "addr:housenumber":"1b1",
    "addr:postcode":"3200",
    "addr:street":"Brouwerijstraat",
    "iso:country":"BE",
    "sg:address":"Brouwerijstraat 1b1",
    "sg:city":"Aarschot",
    "sg:orig_category":"Avocats and conseillers juridiques",
    "sg:phone":"+32 16 56 07 54",
    "sg:postcode":"3200",
    "sg:province":"Vlaams-Brabant",
    "wof:name":"L. Dehond",
    "wof:placetype":"venue"
},
  "geometry": {"coordinates":[4.8368411064,50.9853515625],"type":"Point"}
}