{
  "type": "Feature",
  "properties": {
    "iso:country":"BE",
    "sg:address":"Rue De La Goulette 85",
    "sg:city":"Chatelet",
    "sg:orig_category":"Huisdierenkwekers",
    "sg:phone":"+32 71 38 37 33",
    "sg:postcode":"6200",
    "sg:province":"Hainaut",
    "wof:name":"Chenil Cockers Boisi\u00c8re",
    "wof:placetype":"venue"
},
  "geometry": {"coordinates":[4.5255651474,50.3866195679],"type":"Point"}
}