{
  "type": "Feature",
  "properties": {
    "iso:country":"BE",
    "sg:address":"Rue De Roucourt 66",
    "sg:city":"Peruwelz",
    "sg:orig_category":"Herstelling leer and schoeisel",
    "sg:phone":"+32 69 77 18 51",
    "sg:postcode":"7600",
    "sg:province":"Hainaut",
    "wof:name":"Roger Antoine",
    "wof:placetype":"venue"
},
  "geometry": {"coordinates":[3.5890769958,50.5110092163],"type":"Point"}
}