{
  "type": "Feature",
  "properties": {
    "addr:full":"Hoge Barrierestr. 8 Rumbeke West-Vlaanderen 8800",
    "addr:housenumber":"8",
    "addr:postcode":"8800",
    "addr:street":"Hoge Barrierestr.",
    "iso:country":"BE",
    "sg:address":"Hoge Barrierestr. 8",
    "sg:city":"Rumbeke",
    "sg:classifiers":[
        {
            "category":"Banks & Credit Unions",
            "subcategory":"Investment Brokerage",
            "type":"Services"
        }
    ],
    "sg:phone":"+32 51 22 49 42",
    "sg:postcode":"8800",
    "sg:province":"West-Vlaanderen",
    "sg:tags":[
        "rubber",
        "good",
        "-",
        "metalworking",
        "metallic",
        "metallurgy",
        "finished",
        "plastic"
    ],
    "wof:name":"Defrancq Bouwspec Nv",
    "wof:placetype":"venue"
},
  "geometry": {"coordinates":[3.1158230305,50.9279174805],"type":"Point"}
}