{
  "type": "Feature",
  "properties": {
    "addr:full":"Clement D\u00b4hooghestraat 23 Beveren Oost-Vlaanderen 9120",
    "addr:housenumber":"23",
    "addr:postcode":"9120",
    "addr:street":"D\u00b4Hooghestraat",
    "iso:country":"BE",
    "sg:address":"Clement D\u00b4hooghestraat 23",
    "sg:city":"Beveren",
    "sg:orig_category":"Schoonmaakbedrijven and ongediertebestrijding",
    "sg:phone":"+32 3 775 97 70",
    "sg:postcode":"9120",
    "sg:province":"Oost-Vlaanderen",
    "wof:name":"Serge Deck Service",
    "wof:placetype":"venue"
},
  "geometry": {"coordinates":[4.2259640694,51.2056388855],"type":"Point"}
}