{
  "type": "Feature",
  "properties": {
    "addr:full":"Rue Devant Sauveni\u00e8re 12 Rochefort Namur 5580",
    "addr:housenumber":"12",
    "addr:postcode":"5580",
    "addr:street":"Rue Devant Sauvenie\u0300Re",
    "iso:country":"BE",
    "sg:address":"Rue Devant Sauveni\u00e8re 12",
    "sg:city":"Rochefort",
    "sg:classifiers":[
        {
            "category":"Professional",
            "subcategory":"Lawyer & Legal Services",
            "type":"Services"
        }
    ],
    "sg:phone":"+32 84 21 12 89",
    "sg:postcode":"5580",
    "sg:province":"Namur",
    "sg:tags":[
        "notary"
    ],
    "wof:name":"Maus De Rolley J M",
    "wof:placetype":"venue"
},
  "geometry": {"coordinates":[5.221353054,50.1607780457],"type":"Point"}
}