{
  "type": "Feature",
  "properties": {
    "iso:country":"BE",
    "sg:address":"Brusselheerweg 23",
    "sg:city":"Ninove",
    "sg:orig_category":"Woningbouw",
    "sg:phone":"+32 54 33 62 68",
    "sg:postcode":"9400",
    "sg:province":"Oost-Vlaanderen",
    "wof:name":"Viaene",
    "wof:placetype":"venue"
},
  "geometry": {"coordinates":[4.0274062157,50.8281822205],"type":"Point"}
}