{
  "type": "Feature",
  "properties": {
    "addr:full":"Avenue Louise 427 Bruxelles (ixelles) Bruxelles-Capitale 1050",
    "addr:housenumber":"427",
    "addr:postcode":"1050",
    "addr:street":"Avenue Louise",
    "iso:country":"BE",
    "sg:address":"Avenue Louise 427",
    "sg:city":"Bruxelles (ixelles)",
    "sg:classifiers":[
        {
            "category":"Shopping",
            "subcategory":"Clothing, Apparel, & Fashions",
            "type":"Retail Goods"
        }
    ],
    "sg:phone":"+32 2 648 85 46",
    "sg:postcode":"1050",
    "sg:province":"Bruxelles-Capitale",
    "sg:tags":[
        "designer",
        "stylist"
    ],
    "wof:name":"La Cambre-mode(s) Show.be",
    "wof:placetype":"venue"
},
  "geometry": {"coordinates":[4.3707752228,50.8187103271],"type":"Point"}
}