{
  "type": "Feature",
  "properties": {
    "addr:full":"Rue De La Banque 8 Verviers Li\u00e8ge 4800",
    "addr:housenumber":"8",
    "addr:postcode":"4800",
    "addr:street":"Rue De La Banque",
    "iso:country":"BE",
    "sg:address":"Rue De La Banque 8",
    "sg:city":"Verviers",
    "sg:classifiers":[
        {
            "category":"Health Services",
            "subcategory":"Nursing And Care Facility",
            "type":"Services"
        }
    ],
    "sg:phone":"+32 4 342 84 28",
    "sg:postcode":"4800",
    "sg:province":"Li\u00e8ge",
    "sg:tags":[
        "home"
    ],
    "wof:name":"A.s.d.",
    "wof:placetype":"venue"
},
  "geometry": {"coordinates":[5.8648018837,50.5911331177],"type":"Point"}
}