{
  "type": "Feature",
  "properties": {
    "addr:full":"Rue De La Station 65 Walcourt Namur 5650",
    "addr:housenumber":"65",
    "addr:postcode":"5650",
    "addr:street":"Rue De La Station",
    "iso:country":"BE",
    "sg:address":"Rue De La Station 65",
    "sg:city":"Walcourt",
    "sg:classifiers":[
        {
            "category":"Personal",
            "subcategory":"Beauty Salon",
            "type":"Services"
        }
    ],
    "sg:phone":"+32 71 61 18 31",
    "sg:postcode":"5650",
    "sg:province":"Namur",
    "sg:tags":[
        "lady",
        "-",
        "hairdressing"
    ],
    "wof:name":"Claudine",
    "wof:placetype":"venue"
},
  "geometry": {"coordinates":[4.4377207756,50.2566757202],"type":"Point"}
}