{
  "type": "Feature",
  "properties": {
    "iso:country":"BE",
    "sg:address":"Werf 16",
    "sg:city":"Lier",
    "sg:orig_category":"Pain, p\u00e2tisseries and confiseries",
    "sg:phone":"+32 3 480 17 75",
    "sg:postcode":"2500",
    "sg:province":"Antwerpen",
    "wof:name":"Bakkerij De Vocht P.",
    "wof:placetype":"venue"
},
  "geometry": {"coordinates":[4.5713100433,51.1291236877],"type":"Point"}
}