{
  "type": "Feature",
  "properties": {
    "iso:country":"BE",
    "sg:address":"Chauss\u00e9e De Chastre 153",
    "sg:city":"Sombreffe",
    "sg:classifiers":[
        {
            "category":"Health Services",
            "subcategory":"Doctor",
            "type":"Services"
        }
    ],
    "sg:phone":"+32 71 76 16 74",
    "sg:postcode":"5140",
    "sg:province":"Namur",
    "sg:tags":[
        "medicinephysicians",
        "surgeon"
    ],
    "wof:name":"Chaumont D",
    "wof:placetype":"venue"
},
  "geometry": {"coordinates":[4.5969491005,50.5389671326],"type":"Point"}
}