{
  "type": "Feature",
  "properties": {
    "iso:country":"BE",
    "sg:address":"Chauss\u00e9e De Braine 76a",
    "sg:city":"Ecaussinnes (ecaussinnes-d'enghien)",
    "sg:classifiers":[
        {
            "category":"Farming",
            "subcategory":"Livestock Farm",
            "type":"Manufacturing & Wholesale Goods"
        }
    ],
    "sg:phone":"+32 67 44 21 72",
    "sg:postcode":"7190",
    "sg:province":"Hainaut",
    "sg:tags":[
        "breeding"
    ],
    "wof:name":"Branquart R",
    "wof:placetype":"venue"
},
  "geometry": {"coordinates":[4.1486530304,50.5771942139],"type":"Point"}
}