{
  "type": "Feature",
  "properties": {
    "addr:full":"Avenue Frans Van Kalken 6 Bruxelles (anderlecht) Bruxelles-Capitale 1070",
    "addr:housenumber":"6",
    "addr:postcode":"1070",
    "addr:street":"Avenue Frans Van Kalken",
    "iso:country":"BE",
    "sg:address":"Avenue Frans Van Kalken 6",
    "sg:city":"Bruxelles (anderlecht)",
    "sg:classifiers":[
        {
            "category":"Professional",
            "subcategory":"Testing Lab",
            "type":"Services"
        }
    ],
    "sg:phone":"+32 2 523 68 47",
    "sg:postcode":"1070",
    "sg:province":"Bruxelles-Capitale",
    "sg:tags":[
        "chemist"
    ],
    "wof:name":"Grenez-seeuws Sprl",
    "wof:placetype":"venue"
},
  "geometry": {"coordinates":[4.3053598404,50.8260879517],"type":"Point"}
}