{
  "type": "Feature",
  "properties": {
    "iso:country":"BE",
    "sg:address":"Sint-geertruistraat 135",
    "sg:city":"Tongeren",
    "sg:orig_category":"Producteurs de l\u00e9gumes",
    "sg:phone":"+32 12 23 78 68",
    "sg:postcode":"3700",
    "sg:province":"Limburg",
    "wof:name":"Rene Roubben",
    "wof:placetype":"venue"
},
  "geometry": {"coordinates":[5.4477090836,50.8114242554],"type":"Point"}
}