{
  "type": "Feature",
  "properties": {
    "addr:full":"Lange Koepoortstraat 42-44 Antwerpen Antwerpen 2000",
    "addr:postcode":"42-44;2000",
    "addr:street":"Lange Koepoortstraat",
    "iso:country":"BE",
    "sg:address":"Lange Koepoortstraat 42-44",
    "sg:city":"Antwerpen",
    "sg:orig_category":"Newspapers, magazines, periodicals - Distribution",
    "sg:phone":"+32 3 233 02 82",
    "sg:postcode":"2000",
    "sg:province":"Antwerpen",
    "wof:name":"D & B",
    "wof:placetype":"venue"
},
  "geometry": {"coordinates":[4.4021391869,51.2225494385],"type":"Point"}
}