{
  "type": "Feature",
  "properties": {
    "addr:full":"Torhoutse Steenweg 315 Brugge (sint-andries) West-Vlaanderen 8200",
    "addr:housenumber":"315",
    "addr:postcode":"8200",
    "addr:street":"Torhoutse Steenweg",
    "iso:country":"BE",
    "sg:address":"Torhoutse Steenweg 315",
    "sg:city":"Brugge (sint-andries)",
    "sg:classifiers":[
        {
            "category":"Professional",
            "subcategory":"Accounting & Tax Preparation",
            "type":"Services"
        }
    ],
    "sg:phone":"+32 50 39 17 20",
    "sg:postcode":"8200",
    "sg:province":"West-Vlaanderen",
    "sg:tags":[
        "bookkeeper"
    ],
    "wof:name":"Missinne H",
    "wof:placetype":"venue"
},
  "geometry": {"coordinates":[3.1983458996,51.1939506531],"type":"Point"}
}