{
  "type": "Feature",
  "properties": {
    "addr:full":"Jozef Nellenslaan 229 Knokke-heist West-Vlaanderen 8300",
    "addr:housenumber":"229",
    "addr:postcode":"8300",
    "addr:street":"Jozef Nellenslaan",
    "iso:country":"BE",
    "sg:address":"Jozef Nellenslaan 229",
    "sg:city":"Knokke-heist",
    "sg:classifiers":[
        {
            "category":"Restaurant",
            "type":"Food & Drink"
        }
    ],
    "sg:phone":"+32 50 62 25 61",
    "sg:postcode":"8300",
    "sg:province":"West-Vlaanderen",
    "wof:name":"Restaurant Thornhill",
    "wof:placetype":"venue"
},
  "geometry": {"coordinates":[3.287694931,51.3467254639],"type":"Point"}
}