{
  "type": "Feature",
  "properties": {
    "iso:country":"BE",
    "sg:address":"Clos Roger Lap\u00e9bie 1",
    "sg:city":"Mouscron",
    "sg:classifiers":[
        {
            "category":"Fast Food",
            "type":"Food & Drink"
        }
    ],
    "sg:phone":"+32 56 34 90 36",
    "sg:postcode":"7700",
    "sg:province":"Hainaut",
    "sg:tags":[
        "fried",
        "stand",
        "potato"
    ],
    "wof:name":"Bonne Bouffe Sprl",
    "wof:placetype":"venue"
},
  "geometry": {"coordinates":[3.2112309933,50.7323913574],"type":"Point"}
}