{
  "type": "Feature",
  "properties": {
    "iso:country":"BE",
    "sg:address":"Avenue De La R\u00e9sistance 253",
    "sg:city":"Soumagne",
    "sg:classifiers":[
        {
            "category":"Parking",
            "subcategory":"Bicycle",
            "type":"Transportation"
        }
    ],
    "sg:phone":"+32 4 377 48 12",
    "sg:postcode":"4630",
    "sg:province":"Li\u00e8ge",
    "sg:tags":[
        "chiropodist"
    ],
    "wof:name":"Id\u00e9al Beaut\u00e9",
    "wof:placetype":"venue"
},
  "geometry": {"coordinates":[5.7349281311,50.6308059692],"type":"Point"}
}