{
  "type": "Feature",
  "properties": {
    "addr:full":"Markt 12 Zele Oost-Vlaanderen 9240",
    "addr:housenumber":"12",
    "addr:postcode":"9240",
    "addr:street":"Markt",
    "iso:country":"BE",
    "sg:address":"Markt 12",
    "sg:city":"Zele",
    "sg:orig_category":"Imprimeries and copyshops. Fournitures de bureau",
    "sg:phone":"+32 52 44 41 69",
    "sg:postcode":"9240",
    "sg:province":"Oost-Vlaanderen",
    "wof:name":"Drukkerij De Geest",
    "wof:placetype":"venue"
},
  "geometry": {"coordinates":[4.0395698547,51.0680885315],"type":"Point"}
}