{
  "type": "Feature",
  "properties": {
    "addr:full":"Kuilstraat 79 Erpe-mere Oost-Vlaanderen 9420",
    "addr:housenumber":"79",
    "addr:postcode":"9420",
    "addr:street":"Kuilstraat",
    "iso:country":"BE",
    "sg:address":"Kuilstraat 79",
    "sg:city":"Erpe-mere",
    "sg:classifiers":[
        {
            "category":"Health Services",
            "subcategory":"Hospital",
            "type":"Services"
        }
    ],
    "sg:phone":"+32 53 80 52 32",
    "sg:postcode":"9420",
    "sg:province":"Oost-Vlaanderen",
    "sg:tags":[
        "ambulance"
    ],
    "wof:name":"Guy Otte",
    "wof:placetype":"venue"
},
  "geometry": {"coordinates":[3.9478530884,50.9437522888],"type":"Point"}
}