{
  "type": "Feature",
  "properties": {
    "iso:country":"BE",
    "sg:address":"Waterloose Steenweg 1354",
    "sg:city":"Ukkel/uccle",
    "sg:classifiers":[
        {
            "category":"Communications",
            "subcategory":"Television Station",
            "type":"Services"
        }
    ],
    "sg:phone":"+32 2 375 19 36",
    "sg:postcode":"1180",
    "sg:province":"Bruxelles-Capitale",
    "sg:tags":[
        "televisies",
        "platen",
        "radio's",
        "huishoudapparaten",
        "cassette",
        "cd's"
    ],
    "wof:name":"Music Inn",
    "wof:placetype":"venue"
},
  "geometry": {"coordinates":[4.3751158714,50.7895011902],"type":"Point"}
}