{
  "type": "Feature",
  "properties": {
    "iso:country":"BE",
    "sg:address":"Korenstraat 20",
    "sg:city":"Bilzen",
    "sg:orig_category":"Drogisterijen Textiel Verlichting and huishoudartikelen",
    "sg:phone":"+32 89 41 18 07",
    "sg:postcode":"3740",
    "sg:province":"Limburg",
    "wof:name":"Huis Mouchaers",
    "wof:placetype":"venue"
},
  "geometry": {"coordinates":[5.5142469406,50.8702507019],"type":"Point"}
}