{
  "type": "Feature",
  "properties": {
    "iso:country":"BE",
    "sg:address":"Beerveldse Baan 20",
    "sg:city":"Lochristi",
    "sg:orig_category":"Eleveurs de bovins",
    "sg:phone":"+32 9 355 54 80",
    "sg:postcode":"9080",
    "sg:province":"Oost-Vlaanderen",
    "wof:name":"Omer Boghaert",
    "wof:placetype":"venue"
},
  "geometry": {"coordinates":[3.8761720657,51.0955696106],"type":"Point"}
}