{
  "type": "Feature",
  "properties": {
    "addr:full":"Rue De La Tombette 12 P\u00e9ruwelz (wiers) Hainaut 7608",
    "addr:housenumber":"12",
    "addr:postcode":"7608",
    "addr:street":"Rue De La Tombette",
    "iso:country":"BE",
    "sg:address":"Rue De La Tombette 12",
    "sg:city":"P\u00e9ruwelz (wiers)",
    "sg:classifiers":[
        {
            "category":"Real Estate",
            "subcategory":"Architect",
            "type":"Services"
        }
    ],
    "sg:phone":"+32 69 77 46 80",
    "sg:postcode":"7608",
    "sg:province":"Hainaut",
    "wof:name":"Lenglez C",
    "wof:placetype":"venue"
},
  "geometry": {"coordinates":[3.5416181087,50.4977149963],"type":"Point"}
}