{
  "type": "Feature",
  "properties": {
    "iso:country":"BE",
    "sg:address":"Rue Bois Du Bosquet 3",
    "sg:city":"Rixensart",
    "sg:orig_category":"Huisvuilophaling and -verwerking",
    "sg:phone":"+32 2 654 07 31",
    "sg:postcode":"1331",
    "sg:province":"Brabant Wallon",
    "wof:name":"Deva",
    "wof:placetype":"venue"
},
  "geometry": {"coordinates":[4.5516710281,50.734287262],"type":"Point"}
}