{
  "type": "Feature",
  "properties": {
    "iso:country":"BE",
    "sg:address":"Rue Des D\u00c9port\u00c9s 3",
    "sg:city":"Tubize",
    "sg:orig_category":"Pain, p\u00e2tisseries and confiseries",
    "sg:phone":"+32 2 355 73 65",
    "sg:postcode":"1480",
    "sg:province":"Brabant Wallon",
    "wof:name":"Smagge Boulangerie",
    "wof:placetype":"venue"
},
  "geometry": {"coordinates":[4.2224788666,50.6906166077],"type":"Point"}
}