{
  "type": "Feature",
  "properties": {
    "iso:country":"BE",
    "sg:address":"Leuvensesteenweg 334",
    "sg:city":"Boutersem",
    "sg:orig_category":"Chaussures",
    "sg:phone":"+32 16 73 43 65",
    "sg:postcode":"3370",
    "sg:province":"Vlaams-Brabant",
    "wof:name":"Huis Vandeweyer",
    "wof:placetype":"venue"
},
  "geometry": {"coordinates":[4.8324480057,50.842010498],"type":"Point"}
}