{
  "type": "Feature",
  "properties": {
    "iso:country":"BE",
    "sg:address":"Elshoutbaan 19",
    "sg:city":"Brasschaat",
    "sg:orig_category":"Salles de conf\u00e9rences and de r\u00e9ceptions",
    "sg:phone":"+32 3 653 10 77",
    "sg:postcode":"2930",
    "sg:province":"Antwerpen",
    "wof:name":"Den Duiktoren",
    "wof:placetype":"venue"
},
  "geometry": {"coordinates":[4.5039968491,51.2851905823],"type":"Point"}
}