{
  "type": "Feature",
  "properties": {
    "iso:country":"BE",
    "sg:address":"Kempenaarweg 12",
    "sg:city":"Antwerpen",
    "sg:classifiers":[
        {
            "category":"Wholesale",
            "subcategory":"Construction Materials",
            "type":"Manufacturing & Wholesale Goods"
        }
    ],
    "sg:phone":"+32 3 541 03 01",
    "sg:postcode":"2030",
    "sg:province":"Antwerpen",
    "sg:tags":[
        "tubing",
        "industrial"
    ],
    "wof:name":"Dijksman",
    "wof:placetype":"venue"
},
  "geometry": {"coordinates":[4.4127898216,51.2510414124],"type":"Point"}
}