{
  "type": "Feature",
  "properties": {
    "addr:full":"Rue Joseph Wauters 72 Pont-a-celles Hainaut 6230",
    "addr:housenumber":"72",
    "addr:postcode":"6230",
    "addr:street":"Rue Joseph Wauters",
    "iso:country":"BE",
    "sg:address":"Rue Joseph Wauters 72",
    "sg:city":"Pont-a-celles",
    "sg:orig_category":"Banques and organismes de cr\u00e9dit",
    "sg:phone":"+32 71 84 41 29",
    "sg:postcode":"6230",
    "sg:province":"Hainaut",
    "wof:name":"Fortis",
    "wof:placetype":"venue"
},
  "geometry": {"coordinates":[4.3864989281,50.5048370361],"type":"Point"}
}