{
  "type": "Feature",
  "properties": {
    "addr:full":"Puitvoetstraat 39 Sint-niklaas Oost-Vlaanderen 9100",
    "addr:housenumber":"39",
    "addr:postcode":"9100",
    "addr:street":"Puitvoetstraat",
    "iso:country":"BE",
    "sg:address":"Puitvoetstraat 39",
    "sg:city":"Sint-niklaas",
    "sg:classifiers":[
        {
            "category":"Arena",
            "subcategory":"Sports Club",
            "type":"Entertainment"
        }
    ],
    "sg:phone":"+32 3 776 78 49",
    "sg:postcode":"9100",
    "sg:province":"Oost-Vlaanderen",
    "wof:name":"White Boys",
    "wof:placetype":"venue"
},
  "geometry": {"coordinates":[4.1603589058,51.1491661072],"type":"Point"}
}