{
  "type": "Feature",
  "properties": {
    "addr:full":"Rue Emile Vandervelde 2 Fleurus Hainaut 6220",
    "addr:housenumber":"2",
    "addr:postcode":"6220",
    "addr:street":"Rue Emile Vandervelde",
    "iso:country":"BE",
    "sg:address":"Rue Emile Vandervelde 2",
    "sg:city":"Fleurus",
    "sg:orig_category":"Dameskledingzaken Herenkledingzaken",
    "sg:phone":"+32 71 81 77 33",
    "sg:postcode":"6220",
    "sg:province":"Hainaut",
    "wof:name":"Lady Gentlemen Junior",
    "wof:placetype":"venue"
},
  "geometry": {"coordinates":[4.549680233,50.4823455811],"type":"Point"}
}