{
  "type": "Feature",
  "properties": {
    "iso:country":"BE",
    "sg:address":"Sint-niklaasstraat 8",
    "sg:city":"Oostende",
    "sg:classifiers":[
        {
            "category":"Organizations",
            "subcategory":"Professional Association",
            "type":"Services"
        }
    ],
    "sg:phone":"+32 59 80 27 69",
    "sg:postcode":"8400",
    "sg:province":"West-Vlaanderen",
    "sg:tags":[
        "trade-union",
        "federation"
    ],
    "wof:name":"A C O D",
    "wof:placetype":"venue"
},
  "geometry": {"coordinates":[2.916754961,51.2312850952],"type":"Point"}
}