{
  "type": "Feature",
  "properties": {
    "addr:full":"Leuvensesteenweg 159b1 Tielt-winge Vlaams-Brabant 3390",
    "addr:housenumber":"159b1",
    "addr:postcode":"3390",
    "addr:street":"Leuvensesteenweg",
    "iso:country":"BE",
    "sg:address":"Leuvensesteenweg 159b1",
    "sg:city":"Tielt-winge",
    "sg:orig_category":"Schoonheidssalons",
    "sg:phone":"+32 16 46 80 99",
    "sg:postcode":"3390",
    "sg:province":"Vlaams-Brabant",
    "wof:name":"Instituut Tina",
    "wof:placetype":"venue"
},
  "geometry": {"coordinates":[4.8809151649,50.90832901],"type":"Point"}
}