{
  "type": "Feature",
  "properties": {
    "iso:country":"BE",
    "sg:address":"Oordegemdorp 54",
    "sg:city":"Lede",
    "sg:classifiers":[
        {
            "category":"Insurance",
            "subcategory":"Life Insurance",
            "type":"Services"
        }
    ],
    "sg:phone":"+32 9 369 05 67",
    "sg:postcode":"9340",
    "sg:province":"Oost-Vlaanderen",
    "sg:tags":[
        "assurance"
    ],
    "wof:name":"Hassur",
    "wof:placetype":"venue"
},
  "geometry": {"coordinates":[3.9029641151,50.9568634033],"type":"Point"}
}