{
  "type": "Feature",
  "properties": {
    "addr:full":"Rue De La Basse Marihaye 1 Seraing Li\u00e8ge 4100",
    "addr:housenumber":"1",
    "addr:postcode":"4100",
    "addr:street":"Rue De La Basse Marihaye",
    "iso:country":"BE",
    "sg:address":"Rue De La Basse Marihaye 1",
    "sg:city":"Seraing",
    "sg:classifiers":[
        {
            "category":"Retail",
            "subcategory":"Car Wash",
            "type":"Services"
        }
    ],
    "sg:phone":"+32 4 336 85 36",
    "sg:postcode":"4100",
    "sg:province":"Li\u00e8ge",
    "sg:tags":[
        "automobile",
        "product",
        "-",
        "cleaning",
        "maintenance"
    ],
    "wof:name":"Zulav Sa",
    "wof:placetype":"venue"
},
  "geometry": {"coordinates":[5.4972100258,50.6047706604],"type":"Point"}
}