{
  "type": "Feature",
  "properties": {
    "addr:full":"Rue De Bruxelles 10 Enghien Hainaut 7850",
    "addr:housenumber":"10",
    "addr:postcode":"7850",
    "addr:street":"Rue De Bruxelles",
    "iso:country":"BE",
    "sg:address":"Rue De Bruxelles 10",
    "sg:city":"Enghien",
    "sg:classifiers":[
        {
            "category":"Shopping",
            "subcategory":"Luggage & Leather Goods",
            "type":"Retail Goods"
        }
    ],
    "sg:phone":"+32 2 395 45 14",
    "sg:postcode":"7850",
    "sg:province":"Hainaut",
    "sg:tags":[
        "-"
    ],
    "wof:name":"Malbrecq R",
    "wof:placetype":"venue"
},
  "geometry": {"coordinates":[4.0397748947,50.6938362122],"type":"Point"}
}