{
  "type": "Feature",
  "properties": {
    "iso:country":"BE",
    "sg:address":"Chauss\u00e9e De Couvin 17-21",
    "sg:city":"Chimay",
    "sg:classifiers":[
        {
            "category":"Retail",
            "subcategory":"Auto Repair",
            "type":"Services"
        }
    ],
    "sg:phone":"+32 60 21 38 38",
    "sg:postcode":"6460",
    "sg:province":"Hainaut",
    "sg:tags":[
        "garage"
    ],
    "wof:name":"Chimay Auto Service",
    "wof:placetype":"venue"
},
  "geometry": {"coordinates":[4.3203468323,50.0472602844],"type":"Point"}
}