{
  "type": "Feature",
  "properties": {
    "iso:country":"BE",
    "sg:address":"Waregemstraat 366",
    "sg:city":"Deerlijk",
    "sg:orig_category":"Bloemen and planten",
    "sg:phone":"+32 56 71 78 91",
    "sg:postcode":"8540",
    "sg:province":"West-Vlaanderen",
    "wof:name":"Huis Floralia",
    "wof:placetype":"venue"
},
  "geometry": {"coordinates":[3.3782570362,50.8595504761],"type":"Point"}
}