{
  "type": "Feature",
  "properties": {
    "addr:full":"Place Maurice Servais 8 Namur Namur 5000",
    "addr:housenumber":"8",
    "addr:postcode":"5000",
    "addr:street":"Place Maurice Servais",
    "iso:country":"BE",
    "sg:address":"Place Maurice Servais 8",
    "sg:city":"Namur",
    "sg:orig_category":"Dameskledingzaken Kleding",
    "sg:phone":"+32 81 26 12 04",
    "sg:postcode":"5000",
    "sg:province":"Namur",
    "wof:name":"Enigma",
    "wof:placetype":"venue"
},
  "geometry": {"coordinates":[4.8647351265,50.4622840881],"type":"Point"}
}