{
  "type": "Feature",
  "properties": {
    "iso:country":"BE",
    "sg:address":"Zandstraat 44",
    "sg:city":"Herentals",
    "sg:classifiers":[
        {
            "category":"Cafe",
            "type":"Food & Drink"
        }
    ],
    "sg:phone":"+32 14 21 43 04",
    "sg:postcode":"2200",
    "sg:province":"Antwerpen",
    "sg:tags":[
        "snack-bars"
    ],
    "wof:name":"Ori\u00ebnt",
    "wof:placetype":"venue"
},
  "geometry": {"coordinates":[4.8336138725,51.1769180298],"type":"Point"}
}