{
  "type": "Feature",
  "properties": {
    "addr:full":"Avenue Louis Gribaumont 99 Bruxelles (woluwe-saint-lambert) Bruxelles-Capitale 1200",
    "addr:housenumber":"99",
    "addr:postcode":"1200",
    "addr:street":"Avenue Louis Gribaumont",
    "iso:country":"BE",
    "sg:address":"Avenue Louis Gribaumont 99",
    "sg:city":"Bruxelles (woluwe-saint-lambert)",
    "sg:orig_category":"Non-Classified Establishments",
    "sg:phone":"+32 2 775 89 90",
    "sg:postcode":"1200",
    "sg:province":"Bruxelles-Capitale",
    "wof:name":"A.m. Company Sprl Protidiet",
    "wof:placetype":"venue"
},
  "geometry": {"coordinates":[4.4170160294,50.8394088745],"type":"Point"}
}