{
  "type": "Feature",
  "properties": {
    "addr:full":"Rue Adrien Victor 58a Musson Luxembourg 6750",
    "addr:housenumber":"58a",
    "addr:postcode":"6750",
    "addr:street":"Rue Adrien Victor",
    "iso:country":"BE",
    "sg:address":"Rue Adrien Victor 58a",
    "sg:city":"Musson",
    "sg:classifiers":[
        {
            "category":"Personal",
            "subcategory":"Beauty Salon",
            "type":"Services"
        }
    ],
    "sg:phone":"+32 63 67 58 61",
    "sg:postcode":"6750",
    "sg:province":"Luxembourg",
    "sg:tags":[
        "lady",
        "-",
        "hairdressing"
    ],
    "wof:name":"Antares Coiffure",
    "wof:placetype":"venue"
},
  "geometry": {"coordinates":[5.7049531937,49.5571479797],"type":"Point"}
}