{
  "type": "Feature",
  "properties": {
    "addr:full":"Chauss\u00c9e De Charleroi 77 Sint-gillis/saint-gilles Bruxelles-Capitale 1060",
    "addr:housenumber":"77",
    "addr:postcode":"1060",
    "addr:street":"Chausse\u0301E De Charleroi",
    "iso:country":"BE",
    "sg:address":"Chauss\u00c9e De Charleroi 77",
    "sg:city":"Sint-gillis/saint-gilles",
    "sg:classifiers":[
        {
            "category":"Personal",
            "subcategory":"Beauty Salon",
            "type":"Services"
        }
    ],
    "sg:phone":"+32 2 539 41 05",
    "sg:postcode":"1060",
    "sg:province":"Bruxelles-Capitale",
    "sg:tags":[
        "de",
        "coiffure"
    ],
    "wof:name":"Celini C.n.",
    "wof:placetype":"venue"
},
  "geometry": {"coordinates":[4.3560109138,50.830821991],"type":"Point"}
}