{
  "type": "Feature",
  "properties": {
    "addr:full":"Morgenlandstraat 125 Etterbeek Bruxelles-Capitale 1040",
    "addr:housenumber":"125",
    "addr:postcode":"1040",
    "addr:street":"Morgenlandstraat",
    "iso:country":"BE",
    "sg:address":"Morgenlandstraat 125",
    "sg:city":"Etterbeek",
    "sg:orig_category":"Woningbouw",
    "sg:phone":"+32 2 640 13 64",
    "sg:postcode":"1040",
    "sg:province":"Bruxelles-Capitale",
    "wof:name":"H C R\u00c9novation",
    "wof:placetype":"venue"
},
  "geometry": {"coordinates":[4.3840842247,50.8326797485],"type":"Point"}
}