{
  "type": "Feature",
  "properties": {
    "iso:country":"BE",
    "sg:address":"Stationsstraat 2b11",
    "sg:city":"Sint-truiden",
    "sg:classifiers":[
        {
            "category":"Communications",
            "subcategory":"Television Station",
            "type":"Services"
        }
    ],
    "sg:phone":"+32 11 68 97 25",
    "sg:postcode":"3800",
    "sg:province":"Limburg",
    "sg:tags":[
        "video",
        "audio",
        "verhuur"
    ],
    "wof:name":"Videotheek Hollywood",
    "wof:placetype":"venue"
},
  "geometry": {"coordinates":[5.1800251007,50.8156280518],"type":"Point"}
}