{
  "type": "Feature",
  "properties": {
    "addr:full":"Torhoutsestraat 3 Oostkamp (ruddervoorde) West-Vlaanderen 8020",
    "addr:housenumber":"3",
    "addr:postcode":"8020",
    "addr:street":"Torhoutsestraat",
    "iso:country":"BE",
    "sg:address":"Torhoutsestraat 3",
    "sg:city":"Oostkamp (ruddervoorde)",
    "sg:orig_category":"Non-Classified Establishments",
    "sg:phone":"+32 50 27 78 88",
    "sg:postcode":"8020",
    "sg:province":"West-Vlaanderen",
    "wof:name":"Firma Stubbe",
    "wof:placetype":"venue"
},
  "geometry": {"coordinates":[3.2066869736,51.0957336426],"type":"Point"}
}