{
  "type": "Feature",
  "properties": {
    "iso:country":"BE",
    "sg:address":"Sint-michielsstraat 16",
    "sg:city":"Sint-katelijne-waver",
    "sg:classifiers":[
        {
            "category":"Landmark",
            "subcategory":"Marketplace",
            "type":"Public Place"
        }
    ],
    "sg:phone":"+32 15 20 31 16",
    "sg:postcode":"2860",
    "sg:province":"Antwerpen",
    "sg:tags":[
        "commerce",
        "gr",
        "equipement",
        "de",
        "pour",
        "divers",
        "biens",
        "location",
        "diver"
    ],
    "wof:name":"Verlinden Jan & Dirk",
    "wof:placetype":"venue"
},
  "geometry": {"coordinates":[4.4850888252,51.0582733154],"type":"Point"}
}