{
  "type": "Feature",
  "properties": {
    "addr:full":"Ringstraat 47 Dendermonde Oost-Vlaanderen 9200",
    "addr:housenumber":"47",
    "addr:postcode":"9200",
    "addr:street":"Ringstraat;Oost-Vlaanderen",
    "iso:country":"BE",
    "sg:address":"Ringstraat 47",
    "sg:city":"Dendermonde",
    "sg:classifiers":[
        {
            "category":"Cafe",
            "type":"Food & Drink"
        }
    ],
    "sg:phone":"+32 52 21 77 95",
    "sg:postcode":"9200",
    "sg:province":"Oost-Vlaanderen",
    "sg:tags":[
        "caf\u00e9s"
    ],
    "wof:name":"Koninkl.atl.ver.denderm.",
    "wof:placetype":"venue"
},
  "geometry": {"coordinates":[4.1076478958,51.0525131226],"type":"Point"}
}