{
  "type": "Feature",
  "properties": {
    "addr:full":"Rue Ville-basse 32 Houffalize Luxembourg 6660",
    "addr:housenumber":"32",
    "addr:postcode":"6660",
    "addr:street":"Rue Ville-Basse",
    "iso:country":"BE",
    "sg:address":"Rue Ville-basse 32",
    "sg:city":"Houffalize",
    "sg:orig_category":"Artsen and specialisten",
    "sg:phone":"+32 61 28 97 90",
    "sg:postcode":"6660",
    "sg:province":"Luxembourg",
    "wof:name":"B\u00c9atrice Marenne",
    "wof:placetype":"venue"
},
  "geometry": {"coordinates":[5.7909240723,50.1306037903],"type":"Point"}
}