{
  "type": "Feature",
  "properties": {
    "iso:country":"BE",
    "sg:address":"Rue Emile Vandervelde 59",
    "sg:city":"Charleroi",
    "sg:orig_category":"Boekhouders",
    "sg:phone":"+32 71 32 80 24",
    "sg:postcode":"6042",
    "sg:province":"Hainaut",
    "wof:name":"Christian Tahon",
    "wof:placetype":"venue"
},
  "geometry": {"coordinates":[4.4541320801,50.4220733643],"type":"Point"}
}