{
  "type": "Feature",
  "properties": {
    "iso:country":"BE",
    "sg:address":"Avenue De La Gare 7 Box 2",
    "sg:city":"Namur",
    "sg:classifiers":[
        {
            "category":"Education",
            "subcategory":"School",
            "type":"Public Place"
        }
    ],
    "sg:phone":"+32 81 26 27 66",
    "sg:postcode":"5000",
    "sg:province":"Namur",
    "sg:tags":[
        "-",
        "private"
    ],
    "wof:name":"Methode Travail Performance Asbl",
    "wof:placetype":"venue"
},
  "geometry": {"coordinates":[4.8646659851,50.4680023193],"type":"Point"}
}