{
  "type": "Feature",
  "properties": {
    "addr:full":"Albert I Laan 113bb Koksijde West-Vlaanderen 8670",
    "addr:postcode":"8670",
    "addr:street":"Albert I Laan 113Bb",
    "iso:country":"BE",
    "sg:address":"Albert I Laan 113bb",
    "sg:city":"Koksijde",
    "sg:classifiers":[
        {
            "category":"Restaurant",
            "type":"Food & Drink"
        }
    ],
    "sg:phone":"+32 58 52 18 53",
    "sg:postcode":"8670",
    "sg:province":"West-Vlaanderen",
    "wof:name":"Bretoens Pannenkoekenhuis",
    "wof:placetype":"venue"
},
  "geometry": {"coordinates":[2.6985449791,51.1398544312],"type":"Point"}
}