{
  "type": "Feature",
  "properties": {
    "iso:country":"BE",
    "sg:address":"Avenue De L\u00b4or\u00c9e 2",
    "sg:city":"Brussel/bruxelles",
    "sg:orig_category":"Administration d'immeubles",
    "sg:phone":"+32 2 649 32 26",
    "sg:postcode":"1000",
    "sg:province":"Bruxelles-Capitale",
    "wof:name":"Finec",
    "wof:placetype":"venue"
},
  "geometry": {"coordinates":[4.3826518059,50.8090248108],"type":"Point"}
}