{
  "type": "Feature",
  "properties": {
    "iso:country":"BE",
    "sg:address":"Rue Des Thiers 89",
    "sg:city":"Stavelot",
    "sg:orig_category":"Eleveurs de bovins",
    "sg:phone":"+32 87 27 50 75",
    "sg:postcode":"4970",
    "sg:province":"Li\u00e8ge",
    "wof:name":"Andre Legrand",
    "wof:placetype":"venue"
},
  "geometry": {"coordinates":[5.952559948,50.4485397339],"type":"Point"}
}