{
  "type": "Feature",
  "properties": {
    "iso:country":"BE",
    "sg:address":"Stationsstraat 114",
    "sg:city":"Halen",
    "sg:orig_category":"Installation \u00e9lectrique r\u00e9sidentielle. Electrom\u00e9nager, t\u00e9l\u00e9visions and radios. R\u00e9parations d'apparei",
    "sg:phone":"+32 13 44 16 43",
    "sg:postcode":"3545",
    "sg:province":"Limburg",
    "wof:name":"Marc Das",
    "wof:placetype":"venue"
},
  "geometry": {"coordinates":[5.1212120056,50.9778823853],"type":"Point"}
}