{
  "type": "Feature",
  "properties": {
    "addr:full":"Parklaan 98-100 Sint-niklaas Oost-Vlaanderen 9100",
    "addr:housenumber":"98-100",
    "addr:postcode":"9100",
    "addr:street":"Parklaan",
    "iso:country":"BE",
    "sg:address":"Parklaan 98-100",
    "sg:city":"Sint-niklaas",
    "sg:orig_category":"Siematic. Meubles D\u00e9taillants, Am\u00e9nagement de B\u00e2timents et de Cuisines. Fabrication and montage de m",
    "sg:phone":"+32 3 766 38 35",
    "sg:postcode":"9100",
    "sg:province":"Oost-Vlaanderen",
    "wof:name":"Keukenhome",
    "wof:placetype":"venue"
},
  "geometry": {"coordinates":[4.1540942192,51.1566314697],"type":"Point"}
}