{
  "type": "Feature",
  "properties": {
    "addr:full":"Gentsesteenweg 8d Aalst Oost-Vlaanderen 9300",
    "addr:housenumber":"8d",
    "addr:postcode":"9300",
    "addr:street":"Gentsesteenweg",
    "iso:country":"BE",
    "sg:address":"Gentsesteenweg 8d",
    "sg:city":"Aalst",
    "sg:classifiers":[
        {
            "category":"Banks & Credit Unions",
            "subcategory":"Financial Services",
            "type":"Services"
        }
    ],
    "sg:phone":"+32 53 70 43 86",
    "sg:postcode":"9300",
    "sg:province":"Oost-Vlaanderen",
    "sg:tags":[
        "loan",
        "mortgage"
    ],
    "wof:name":"Assuco Bvba",
    "wof:placetype":"venue"
},
  "geometry": {"coordinates":[4.0269317627,50.9373016357],"type":"Point"}
}