{
  "type": "Feature",
  "properties": {
    "addr:full":"Dennenbosstraat 3 Geetbets Vlaams-Brabant 3450",
    "addr:housenumber":"3",
    "addr:postcode":"3450",
    "addr:street":"Dennenbosstraat",
    "iso:country":"BE",
    "sg:address":"Dennenbosstraat 3",
    "sg:city":"Geetbets",
    "sg:orig_category":"Eleveurs de bovins. Producteurs de fruits",
    "sg:phone":"+32 11 58 78 54",
    "sg:postcode":"3450",
    "sg:province":"Vlaams-Brabant",
    "wof:name":"Ivo Langen",
    "wof:placetype":"venue"
},
  "geometry": {"coordinates":[5.0830068588,50.8779563904],"type":"Point"}
}