{
  "type": "Feature",
  "properties": {
    "iso:country":"BE",
    "sg:address":"Rue De Dampremy 14b1",
    "sg:city":"Charleroi",
    "sg:orig_category":"Avocats and conseillers juridiques",
    "sg:phone":"+32 71 30 90 67",
    "sg:postcode":"6000",
    "sg:province":"Hainaut",
    "wof:name":"J.ph. Defechereux",
    "wof:placetype":"venue"
},
  "geometry": {"coordinates":[4.4419388771,50.4086990356],"type":"Point"}
}