{
  "type": "Feature",
  "properties": {
    "iso:country":"BE",
    "sg:address":"Rue De Cond\u00e9 29",
    "sg:city":"Leuze-en-hainaut",
    "sg:classifiers":[
        {
            "category":"Bakery",
            "type":"Food & Drink"
        }
    ],
    "sg:phone":"+32 69 66 26 20",
    "sg:postcode":"7900",
    "sg:province":"Hainaut",
    "sg:tags":[
        "confectioner",
        "baker"
    ],
    "wof:name":"Gateau D'hawai (au)",
    "wof:placetype":"venue"
},
  "geometry": {"coordinates":[3.6176199913,50.596736908],"type":"Point"}
}