{
  "type": "Feature",
  "properties": {
    "iso:country":"BE",
    "sg:address":"Vaartkant Links 26",
    "sg:city":"Brecht (sint-lenaarts)",
    "sg:classifiers":[
        {
            "category":"Freight",
            "type":"Transportation"
        }
    ],
    "sg:phone":"+32 3 313 55 00",
    "sg:postcode":"2960",
    "sg:province":"Antwerpen",
    "sg:tags":[
        "-",
        "transport"
    ],
    "wof:name":"Petag Nv",
    "wof:placetype":"venue"
},
  "geometry": {"coordinates":[4.6415200233,51.3512115479],"type":"Point"}
}