{
  "type": "Feature",
  "properties": {
    "iso:country":"BE",
    "sg:address":"Rue Du Bois D'arche 21",
    "sg:city":"Profondeville",
    "sg:orig_category":"Catering and organisation de f\u00eates",
    "sg:phone":"+32 81 41 20 64",
    "sg:postcode":"5170",
    "sg:province":"Namur",
    "wof:name":"Eric Massaux",
    "wof:placetype":"venue"
},
  "geometry": {"coordinates":[4.9162287712,50.3850631714],"type":"Point"}
}