{
  "type": "Feature",
  "properties": {
    "addr:full":"Rue Clarisse 65 Nivelles Brabant Wallon 1400",
    "addr:housenumber":"65",
    "addr:postcode":"1400",
    "addr:street":"Rue Clarisse",
    "iso:country":"BE",
    "sg:address":"Rue Clarisse 65",
    "sg:city":"Nivelles",
    "sg:classifiers":[
        {
            "category":"Insurance",
            "subcategory":"Insurance Agent",
            "type":"Services"
        }
    ],
    "sg:phone":"+32 67 21 54 05",
    "sg:postcode":"1400",
    "sg:province":"Brabant Wallon",
    "sg:tags":[
        "broker"
    ],
    "wof:name":"Colpaert Pulinx Et Associ\u00e9s",
    "wof:placetype":"venue"
},
  "geometry": {"coordinates":[4.3406758308,50.597946167],"type":"Point"}
}