{
  "type": "Feature",
  "properties": {
    "iso:country":"BE",
    "sg:address":"Avenue Des Artisans 45",
    "sg:city":"Ath",
    "sg:orig_category":"Autokeuringen",
    "sg:phone":"+32 68 25 06 60",
    "sg:postcode":"7822",
    "sg:province":"Hainaut",
    "wof:name":"Contr\u00d4le Technique Automobile",
    "wof:placetype":"venue"
},
  "geometry": {"coordinates":[3.8683750629,50.6687698364],"type":"Point"}
}