{
  "type": "Feature",
  "properties": {
    "iso:country":"BE",
    "sg:address":"Rue Pj Delcloche 16",
    "sg:city":"Li\u00e8ge",
    "sg:orig_category":"Software For The Chemical Industry",
    "sg:phone":"+32 2 701 94 50",
    "sg:postcode":"4020",
    "sg:province":"Li\u00e8ge",
    "wof:name":"Aspentech Europe S.a.",
    "wof:placetype":"venue"
},
  "geometry": {"coordinates":[4.4723620415,50.7271842957],"type":"Point"}
}