{
  "type": "Feature",
  "properties": {
    "addr:full":"Place Verte 25 Dour Hainaut 7370",
    "addr:housenumber":"25",
    "addr:postcode":"7370",
    "addr:street":"Place Verte;Hainaut",
    "iso:country":"BE",
    "sg:address":"Place Verte 25",
    "sg:city":"Dour",
    "sg:orig_category":"Banques and organismes de cr\u00e9dit",
    "sg:phone":"+32 65 65 35 09",
    "sg:postcode":"7370",
    "sg:province":"Hainaut",
    "wof:name":"Anhyp",
    "wof:placetype":"venue"
},
  "geometry": {"coordinates":[3.7883229256,50.3987197876],"type":"Point"}
}