{
  "type": "Feature",
  "properties": {
    "addr:full":"Zanddijk 70 Dessel Antwerpen 2480",
    "addr:housenumber":"70",
    "addr:postcode":"2480",
    "addr:street":"Zanddijk",
    "iso:country":"BE",
    "sg:address":"Zanddijk 70",
    "sg:city":"Dessel",
    "sg:classifiers":[
        {
            "category":"Real Estate",
            "subcategory":"Architect",
            "type":"Services"
        }
    ],
    "sg:phone":"+32 14 37 50 85",
    "sg:postcode":"2480",
    "sg:province":"Antwerpen",
    "wof:name":"Cuylen J",
    "wof:placetype":"venue"
},
  "geometry": {"coordinates":[5.1396150589,51.2638816833],"type":"Point"}
}