{
  "type": "Feature",
  "properties": {
    "addr:full":"8540 Deerlijk West-Vlaanderen 8540",
    "addr:postcode":"8540;8540",
    "iso:country":"BE",
    "sg:address":"8540",
    "sg:city":"Deerlijk",
    "sg:orig_category":"Pharmaciens",
    "sg:phone":"+32 900 10 500",
    "sg:postcode":"8540",
    "sg:province":"West-Vlaanderen",
    "wof:name":"Pharmacies De Garde",
    "wof:placetype":"venue"
},
  "geometry": {"coordinates":[3.3521909714,50.8535194397],"type":"Point"}
}