{
  "type": "Feature",
  "properties": {
    "addr:full":"Doornlaarstraat 47 Bonheiden Antwerpen 2820",
    "addr:housenumber":"47",
    "addr:postcode":"2820",
    "addr:street":"Doornlaarstraat",
    "iso:country":"BE",
    "sg:address":"Doornlaarstraat 47",
    "sg:city":"Bonheiden",
    "sg:orig_category":"Producteurs de l\u00e9gumes",
    "sg:phone":"+32 15 51 18 01",
    "sg:postcode":"2820",
    "sg:province":"Antwerpen",
    "wof:name":"Albert De Preter",
    "wof:placetype":"venue"
},
  "geometry": {"coordinates":[4.6324548721,51.0157661438],"type":"Point"}
}