{
  "type": "Feature",
  "properties": {
    "addr:full":"Mechelsesteenweg 366 Vilvoorde Vlaams-Brabant 1800",
    "addr:housenumber":"366",
    "addr:postcode":"1800",
    "addr:street":"Mechelsesteenweg",
    "iso:country":"BE",
    "sg:address":"Mechelsesteenweg 366",
    "sg:city":"Vilvoorde",
    "sg:classifiers":[
        {
            "category":"Retail",
            "subcategory":"Auto Repair",
            "type":"Services"
        }
    ],
    "sg:phone":"+32 2 252 18 03",
    "sg:postcode":"1800",
    "sg:province":"Vlaams-Brabant",
    "sg:tags":[
        "garage"
    ],
    "wof:name":"Jacobs",
    "wof:placetype":"venue"
},
  "geometry": {"coordinates":[4.4314317703,50.937587738],"type":"Point"}
}