{
  "type": "Feature",
  "properties": {
    "iso:country":"BE",
    "sg:address":"Steenweg Op Deinze 51",
    "sg:city":"Aalter",
    "sg:classifiers":[
        {
            "category":"Farming",
            "subcategory":"Poultry Farm",
            "type":"Manufacturing & Wholesale Goods"
        }
    ],
    "sg:phone":"+32 9 375 33 75",
    "sg:postcode":"9880",
    "sg:province":"Oost-Vlaanderen",
    "sg:tags":[
        "rabbit",
        "slaughterhouse"
    ],
    "wof:name":"Van Der Eecken Nv",
    "wof:placetype":"venue"
},
  "geometry": {"coordinates":[3.4572329521,51.0629425049],"type":"Point"}
}