{
  "type": "Feature",
  "properties": {
    "iso:country":"BE",
    "sg:address":"Rue Saint-vincent 1",
    "sg:city":"Walhain",
    "sg:orig_category":"V\u00e9t\u00e9rinaires",
    "sg:phone":"+32 10 65 05 16",
    "sg:postcode":"1457",
    "sg:province":"Brabant Wallon",
    "wof:name":"C. Diederich",
    "wof:placetype":"venue"
},
  "geometry": {"coordinates":[4.6736240387,50.6406326294],"type":"Point"}
}