{
  "type": "Feature",
  "properties": {
    "iso:country":"BE",
    "sg:address":"Rue D'ougr\u00c9e 65",
    "sg:city":"Li\u00c8ge",
    "sg:orig_category":"Algemeen secundair onderwijs Technisch and beroeps secundair onderwijs",
    "sg:phone":"+32 4 365 01 18",
    "sg:postcode":"4031",
    "sg:province":"Li\u00e8ge",
    "wof:name":"Ath\u00c9n\u00c9e Royal",
    "wof:placetype":"venue"
},
  "geometry": {"coordinates":[5.5843200684,50.611240387],"type":"Point"}
}