{
  "type": "Feature",
  "properties": {
    "iso:country":"BE",
    "sg:address":"Oostmeers 92",
    "sg:city":"Brugge",
    "sg:classifiers":[
        {
            "category":"Professional",
            "subcategory":"Accounting & Tax Preparation",
            "type":"Services"
        }
    ],
    "sg:phone":"+32 50 34 20 03",
    "sg:postcode":"8000",
    "sg:province":"West-Vlaanderen",
    "sg:tags":[
        "bookkeeper"
    ],
    "wof:name":"Knockaert L",
    "wof:placetype":"venue"
},
  "geometry": {"coordinates":[3.220664978,51.2014732361],"type":"Point"}
}