{
  "type": "Feature",
  "properties": {
    "addr:full":"E Hielstraat 19 Knokke-heist West-Vlaanderen 8301",
    "addr:housenumber":"19",
    "addr:postcode":"8301",
    "addr:street":"E Hielstraat",
    "iso:country":"BE",
    "sg:address":"E Hielstraat 19",
    "sg:city":"Knokke-heist",
    "sg:orig_category":"Sportclubs",
    "sg:phone":"+32 50 51 86 06",
    "sg:postcode":"8301",
    "sg:province":"West-Vlaanderen",
    "wof:name":"Nippon Karate Knokke-heist",
    "wof:placetype":"venue"
},
  "geometry": {"coordinates":[3.2639000416,51.3396911621],"type":"Point"}
}