{
  "type": "Feature",
  "properties": {
    "iso:country":"BE",
    "sg:address":"Ninoofsesteenweg 136",
    "sg:city":"Dilbeek",
    "sg:orig_category":"Studios photographiques. Equipement photographique. Mat\u00e9riel de T\u00e9l\u00e9communication",
    "sg:phone":"+32 2 569 35 09",
    "sg:postcode":"1700",
    "sg:province":"Vlaams-Brabant",
    "wof:name":"Top Camera Studio Woudec",
    "wof:placetype":"venue"
},
  "geometry": {"coordinates":[4.2750577927,50.8447685242],"type":"Point"}
}