{
  "type": "Feature",
  "properties": {
    "iso:country":"BE",
    "sg:address":"Steenweg 77",
    "sg:city":"Herk-de-stad",
    "sg:classifiers":[
        {
            "category":"Travel",
            "subcategory":"Bed & Breakfast",
            "type":"Entertainment"
        }
    ],
    "sg:phone":"+32 13 55 15 25",
    "sg:postcode":"3540",
    "sg:province":"Limburg",
    "sg:tags":[
        "ladder"
    ],
    "wof:name":"Comal",
    "wof:placetype":"venue"
},
  "geometry": {"coordinates":[5.2051520348,50.9473114014],"type":"Point"}
}