{
  "type": "Feature",
  "properties": {
    "addr:full":"Rue Neuve 99 Gerpinnes Hainaut 6280",
    "addr:housenumber":"99",
    "addr:postcode":"6280",
    "addr:street":"Rue Neuve;Hainaut",
    "iso:country":"BE",
    "sg:address":"Rue Neuve 99",
    "sg:city":"Gerpinnes",
    "sg:orig_category":"Verlichting and huishoudartikelen",
    "sg:phone":"+32 71 22 11 16",
    "sg:postcode":"6280",
    "sg:province":"Hainaut",
    "wof:name":"La Maison",
    "wof:placetype":"venue"
},
  "geometry": {"coordinates":[4.4712200165,50.3459815979],"type":"Point"}
}