{
  "type": "Feature",
  "properties": {
    "addr:full":"Schavei 1 Overijse Vlaams-Brabant 3090",
    "addr:housenumber":"1",
    "addr:postcode":"3090",
    "addr:street":"Schavei",
    "iso:country":"BE",
    "sg:address":"Schavei 1",
    "sg:city":"Overijse",
    "sg:classifiers":[
        {
            "category":"Professional",
            "subcategory":"Management & Consulting",
            "type":"Services"
        }
    ],
    "sg:phone":"+32 2 687 91 77",
    "sg:postcode":"3090",
    "sg:province":"Vlaams-Brabant",
    "sg:tags":[
        "-",
        "processing",
        "data",
        "consultant"
    ],
    "wof:name":"Danckaarts Bvba",
    "wof:placetype":"venue"
},
  "geometry": {"coordinates":[4.5331377983,50.772644043],"type":"Point"}
}