{
  "type": "Feature",
  "properties": {
    "iso:country":"BE",
    "sg:address":"Boulevard De L\u00b4empereur 24",
    "sg:city":"Brussel/bruxelles",
    "sg:orig_category":"Avocats and conseillers juridiques",
    "sg:phone":"+32 2 513 37 23",
    "sg:postcode":"1000",
    "sg:province":"Bruxelles-Capitale",
    "wof:name":"Et. Boniver",
    "wof:placetype":"venue"
},
  "geometry": {"coordinates":[4.3533649445,50.8426933289],"type":"Point"}
}