{
  "type": "Feature",
  "properties": {
    "addr:full":"Avenue Des Perdrix 20 Kraainem/kraainem Vlaams-Brabant 1950",
    "addr:housenumber":"20",
    "addr:postcode":"1950",
    "addr:street":"Avenue Des Perdrix",
    "iso:country":"BE",
    "sg:address":"Avenue Des Perdrix 20",
    "sg:city":"Kraainem/kraainem",
    "sg:orig_category":"M\u00e9decins and sp\u00e9cialistes",
    "sg:phone":"+32 2 731 63 93",
    "sg:postcode":"1950",
    "sg:province":"Vlaams-Brabant",
    "wof:name":"Philippe Lauwers",
    "wof:placetype":"venue"
},
  "geometry": {"coordinates":[4.4811701775,50.8321418762],"type":"Point"}
}