{
  "type": "Feature",
  "properties": {
    "iso:country":"BE",
    "sg:address":"All\u00c9e Du Ch\u00c2teau 15",
    "sg:city":"Theux",
    "sg:classifiers":[
        {
            "category":"Cafe",
            "type":"Food & Drink"
        }
    ],
    "sg:phone":"+32 87 54 10 27",
    "sg:postcode":"4910",
    "sg:province":"Li\u00e8ge",
    "sg:tags":[
        "caf\u00e9s"
    ],
    "wof:name":"Chalet Des Ruines",
    "wof:placetype":"venue"
},
  "geometry": {"coordinates":[5.8248529434,50.5282592773],"type":"Point"}
}