{
  "type": "Feature",
  "properties": {
    "iso:country":"BE",
    "sg:address":"Bieststraat 166",
    "sg:city":"Boortmeerbeek",
    "sg:orig_category":"Entretien and r\u00e9parations de voitures",
    "sg:phone":"+32 15 51 84 98",
    "sg:postcode":"3191",
    "sg:province":"Vlaams-Brabant",
    "wof:name":"Dietmar's Car Cleaning",
    "wof:placetype":"venue"
},
  "geometry": {"coordinates":[4.5477199554,50.9829063416],"type":"Point"}
}