{
  "type": "Feature",
  "properties": {
    "iso:country":"BE",
    "sg:address":"Lekkensstraat 55",
    "sg:city":"Roeselare",
    "sg:orig_category":"D\u00e9taillants en pi\u00e8ces and accessoires de voitures. R\u00e9cup\u00e9ration de mati\u00e8res m\u00e9talliques recyclables ",
    "sg:phone":"+32 51 20 25 44",
    "sg:postcode":"8800",
    "sg:province":"West-Vlaanderen",
    "wof:name":"Labeeuw",
    "wof:placetype":"venue"
},
  "geometry": {"coordinates":[3.1594760418,50.9348335266],"type":"Point"}
}