{
  "type": "Feature",
  "properties": {
    "iso:country":"BE",
    "sg:address":"Stoepestraat 15",
    "sg:city":"Evergem (ertvelde)",
    "sg:classifiers":[
        {
            "category":"Retail",
            "subcategory":"Veterinary Services",
            "type":"Services"
        }
    ],
    "sg:phone":"+32 9 344 21 05",
    "sg:postcode":"9940",
    "sg:province":"Oost-Vlaanderen",
    "sg:tags":[
        "veterinarian"
    ],
    "wof:name":"Van Hoye Kathleen",
    "wof:placetype":"venue"
},
  "geometry": {"coordinates":[3.7524180412,51.1865272522],"type":"Point"}
}