{
  "type": "Feature",
  "properties": {
    "iso:country":"BE",
    "sg:address":"Rue De Limoges 67",
    "sg:city":"Esneux",
    "sg:orig_category":"Textiel Verlichting and huishoudartikelen",
    "sg:phone":"+32 4 388 31 08",
    "sg:postcode":"4130",
    "sg:province":"Li\u00e8ge",
    "wof:name":"Martine Champagne",
    "wof:placetype":"venue"
},
  "geometry": {"coordinates":[5.5717477798,50.566608429],"type":"Point"}
}