{
  "type": "Feature",
  "properties": {
    "iso:country":"BE",
    "sg:address":"Belgi\u00cblei 134",
    "sg:city":"Antwerpen",
    "sg:orig_category":"Imprimeries and copyshops",
    "sg:phone":"+32 3 239 11 51",
    "sg:postcode":"2018",
    "sg:province":"Antwerpen",
    "wof:name":"De Kopiant",
    "wof:placetype":"venue"
},
  "geometry": {"coordinates":[4.4161667824,51.2048034668],"type":"Point"}
}