{
  "type": "Feature",
  "properties": {
    "addr:full":"Kloosterstraat 1 Izegem West-Vlaanderen 8870",
    "addr:housenumber":"1",
    "addr:postcode":"8870",
    "addr:street":"Kloosterstraat",
    "iso:country":"BE",
    "sg:address":"Kloosterstraat 1",
    "sg:city":"Izegem",
    "sg:classifiers":[
        {
            "category":"Food & Beverages",
            "subcategory":"Specialty",
            "type":"Retail Goods"
        }
    ],
    "sg:phone":"+32 51 30 44 12",
    "sg:postcode":"8870",
    "sg:province":"West-Vlaanderen",
    "sg:tags":[
        "health",
        "dietary",
        "-",
        "biological"
    ],
    "wof:name":"De Hoeve",
    "wof:placetype":"venue"
},
  "geometry": {"coordinates":[3.2141010761,50.9176712036],"type":"Point"}
}