{
  "type": "Feature",
  "properties": {
    "addr:full":"Rue Emile Sergijsels 23 Bruxelles (koekelberg) Bruxelles-Capitale 1081",
    "addr:housenumber":"23",
    "addr:postcode":"1081",
    "addr:street":"Rue Emile Sergijsels",
    "iso:country":"BE",
    "sg:address":"Rue Emile Sergijsels 23",
    "sg:city":"Bruxelles (koekelberg)",
    "sg:classifiers":[
        {
            "category":"Food & Beverages",
            "subcategory":"Groceries & Convenience Stores",
            "type":"Retail Goods"
        }
    ],
    "sg:phone":"+32 2 414 92 70",
    "sg:postcode":"1081",
    "sg:province":"Bruxelles-Capitale",
    "sg:tags":[
        "grocer"
    ],
    "wof:name":"Fami Prix",
    "wof:placetype":"venue"
},
  "geometry": {"coordinates":[4.3337907791,50.8598670959],"type":"Point"}
}