{
  "type": "Feature",
  "properties": {
    "addr:full":"All\u00e9e Du Broc \u00e0 L'aye 21 Nivelles Brabant Wallon 1400",
    "addr:housenumber":"21",
    "addr:postcode":"1400",
    "addr:street":"Alle\u0301E Du Broc A\u0300 L'Aye",
    "iso:country":"BE",
    "sg:address":"All\u00e9e Du Broc \u00e0 L'aye 21",
    "sg:city":"Nivelles",
    "sg:classifiers":[
        {
            "category":"Professional",
            "subcategory":"Accounting & Tax Preparation",
            "type":"Services"
        }
    ],
    "sg:phone":"+32 67 84 21 84",
    "sg:postcode":"1400",
    "sg:province":"Brabant Wallon",
    "sg:tags":[
        "bookkeeper"
    ],
    "wof:name":"Dufond H",
    "wof:placetype":"venue"
},
  "geometry": {"coordinates":[4.3188781738,50.6074829102],"type":"Point"}
}