{
  "type": "Feature",
  "properties": {
    "addr:full":"Grootveldlaan 233 Sint-pieters-woluwe/woluwe-saint-pierre Bruxelles-Capitale 1150",
    "addr:housenumber":"233",
    "addr:postcode":"1150",
    "addr:street":"Grootveldlaan;/",
    "iso:country":"BE",
    "sg:address":"Grootveldlaan 233",
    "sg:city":"Sint-pieters-woluwe/woluwe-saint-pierre",
    "sg:orig_category":"Artsen and specialisten",
    "sg:phone":"+32 2 772 98 47",
    "sg:postcode":"1150",
    "sg:province":"Bruxelles-Capitale",
    "wof:name":"J. Gueibe",
    "wof:placetype":"venue"
},
  "geometry": {"coordinates":[4.4585080147,50.8405532837],"type":"Point"}
}