{
  "type": "Feature",
  "properties": {
    "addr:full":"Kopkapelstraat 42 Lokeren Oost-Vlaanderen 9160",
    "addr:housenumber":"42",
    "addr:postcode":"9160",
    "addr:street":"Kopkapelstraat",
    "iso:country":"BE",
    "sg:address":"Kopkapelstraat 42",
    "sg:city":"Lokeren",
    "sg:classifiers":[
        {
            "category":"Communications",
            "type":"Services"
        }
    ],
    "sg:phone":"+32 9 328 94 74",
    "sg:postcode":"9160",
    "sg:province":"Oost-Vlaanderen",
    "sg:tags":[
        "translator"
    ],
    "wof:name":"Neumann S",
    "wof:placetype":"venue"
},
  "geometry": {"coordinates":[4.002395153,51.1182174683],"type":"Point"}
}