{
  "type": "Feature",
  "properties": {
    "addr:full":"Bevrijdingslaan 109 Gent Oost-Vlaanderen 9000",
    "addr:housenumber":"109",
    "addr:postcode":"9000",
    "addr:street":"Bevrijdingslaan;Oost-Vlaanderen",
    "iso:country":"BE",
    "sg:address":"Bevrijdingslaan 109",
    "sg:city":"Gent",
    "sg:classifiers":[
        {
            "category":"Shopping",
            "subcategory":"Discount & Variety Stores",
            "type":"Retail Goods"
        }
    ],
    "sg:phone":"+32 9 236 18 69",
    "sg:postcode":"9000",
    "sg:province":"Oost-Vlaanderen",
    "sg:tags":[
        "shop",
        "night"
    ],
    "wof:name":"Usman",
    "wof:placetype":"venue"
},
  "geometry": {"coordinates":[3.6993501186,51.0620994568],"type":"Point"}
}