{
  "type": "Feature",
  "properties": {
    "addr:full":"Land Van Waaslaan 74 Gent Oost-Vlaanderen 9040",
    "addr:housenumber":"74",
    "addr:postcode":"9040",
    "addr:street":"Land Van Waaslaan;Oost-Vlaanderen",
    "iso:country":"BE",
    "sg:address":"Land Van Waaslaan 74",
    "sg:city":"Gent",
    "sg:orig_category":"Imprimeries and copyshops",
    "sg:phone":"+32 9 238 13 76",
    "sg:postcode":"9040",
    "sg:province":"Oost-Vlaanderen",
    "wof:name":"Practico",
    "wof:placetype":"venue"
},
  "geometry": {"coordinates":[3.7460319996,51.0580787659],"type":"Point"}
}