{
  "type": "Feature",
  "properties": {
    "iso:country":"BE",
    "sg:address":"Kwakkelenberg 1",
    "sg:city":"Duffel",
    "sg:orig_category":"Maisons de repos and r\u00e9sidences",
    "sg:phone":"+32 15 30 99 80",
    "sg:postcode":"2570",
    "sg:province":"Antwerpen",
    "wof:name":"Rusthuis De Craene",
    "wof:placetype":"venue"
},
  "geometry": {"coordinates":[4.5106630325,51.0952072144],"type":"Point"}
}