{
  "type": "Feature",
  "properties": {
    "iso:country":"BE",
    "sg:address":"Rue Neerveld 51",
    "sg:city":"Bruxelles (woluwe-saint-lambert)",
    "sg:classifiers":[
        {
            "category":"Home & Garden",
            "subcategory":"Hardware",
            "type":"Retail Goods"
        }
    ],
    "sg:phone":"+32 2 771 57 21",
    "sg:postcode":"1200",
    "sg:province":"Bruxelles-Capitale",
    "sg:tags":[
        "builders'",
        "-",
        "furniture"
    ],
    "wof:name":"Horion",
    "wof:placetype":"venue"
},
  "geometry": {"coordinates":[4.4405770302,50.8498344421],"type":"Point"}
}