{
  "type": "Feature",
  "properties": {
    "iso:country":"BE",
    "sg:address":"Varendonk 61",
    "sg:city":"Evergem",
    "sg:orig_category":"Zuivelproducten",
    "sg:phone":"+32 9 357 30 17",
    "sg:postcode":"9940",
    "sg:province":"Oost-Vlaanderen",
    "wof:name":"Hilaire Schauvliege",
    "wof:placetype":"venue"
},
  "geometry": {"coordinates":[3.6724159718,51.1328086853],"type":"Point"}
}