{
  "type": "Feature",
  "properties": {
    "iso:country":"BE",
    "sg:address":"Pastorijstraat 26",
    "sg:city":"Evergem",
    "sg:orig_category":"Radioproductie and uitzendingen",
    "sg:phone":"+32 75857979",
    "sg:postcode":"075857979",
    "wof:name":"Radio Contact Evergem",
    "wof:placetype":"venue"
},
  "geometry": {"coordinates":[3.7486109734,51.1787338257],"type":"Point"}
}