{
  "type": "Feature",
  "properties": {
    "iso:country":"BE",
    "sg:address":"Oostendebaan 114",
    "sg:city":"Gistel",
    "sg:orig_category":"Articles m\u00e9talliques ouvr\u00e9s divers Fab",
    "sg:phone":"+32 59 27 85 96",
    "sg:postcode":"8470",
    "sg:province":"West-Vlaanderen",
    "wof:name":"Ameel H",
    "wof:placetype":"venue"
},
  "geometry": {"coordinates":[2.9438400269,51.1559028625],"type":"Point"}
}