{
  "type": "Feature",
  "properties": {
    "iso:country":"BE",
    "sg:address":"Eikestraat 33-35",
    "sg:city":"Herzele (steenhuize-wijnhuize)",
    "sg:classifiers":[
        {
            "category":"Home & Garden",
            "subcategory":"Garden Supply",
            "type":"Retail Goods"
        }
    ],
    "sg:phone":"+32 54 50 03 66",
    "sg:postcode":"9550",
    "sg:province":"Oost-Vlaanderen",
    "sg:tags":[
        "lawn",
        "mower"
    ],
    "wof:name":"Schotte W",
    "wof:placetype":"venue"
},
  "geometry": {"coordinates":[3.8919329643,50.8376693726],"type":"Point"}
}