{
  "type": "Feature",
  "properties": {
    "addr:full":"Rue De La Forge 28 Beauraing Namur 5570",
    "addr:housenumber":"28",
    "addr:postcode":"5570",
    "addr:street":"Rue De La Forge",
    "iso:country":"BE",
    "sg:address":"Rue De La Forge 28",
    "sg:city":"Beauraing",
    "sg:orig_category":"Woningbouw",
    "sg:phone":"+32 84 38 84 62",
    "sg:postcode":"5570",
    "sg:province":"Namur",
    "wof:name":"Capelle & Fils",
    "wof:placetype":"venue"
},
  "geometry": {"coordinates":[5.0379328728,50.0821685791],"type":"Point"}
}