{
  "type": "Feature",
  "properties": {
    "addr:full":"Gentbruggestraat 28 Gent (sint-amandsberg) Oost-Vlaanderen 9040",
    "addr:housenumber":"28",
    "addr:postcode":"9040",
    "addr:street":"Gentbruggestraat",
    "iso:country":"BE",
    "sg:address":"Gentbruggestraat 28",
    "sg:city":"Gent (sint-amandsberg)",
    "sg:classifiers":[
        {
            "category":"Professional",
            "subcategory":"Art Services",
            "type":"Services"
        }
    ],
    "sg:phone":"+32 478 28 88 50",
    "sg:postcode":"9040",
    "sg:province":"Oost-Vlaanderen",
    "sg:tags":[
        "graphic",
        "designer"
    ],
    "wof:name":"Gee! Graphics & Art Direction",
    "wof:placetype":"venue"
},
  "geometry": {"coordinates":[3.7520740032,51.0515937805],"type":"Point"}
}