{
  "type": "Feature",
  "properties": {
    "addr:full":"Avenue De L'ind\u00c9pendance 19 Bastogne Luxembourg 6600",
    "addr:housenumber":"19",
    "addr:postcode":"6600",
    "addr:street":"Avenue De;\u0301Pendance",
    "iso:country":"BE",
    "sg:address":"Avenue De L'ind\u00c9pendance 19",
    "sg:city":"Bastogne",
    "sg:orig_category":"Peinture. Rev\u00eatements pour sols and murs",
    "sg:phone":"+32 61 21 46 54",
    "sg:postcode":"6600",
    "sg:province":"Luxembourg",
    "wof:name":"Alain Teise",
    "wof:placetype":"venue"
},
  "geometry": {"coordinates":[5.7249770164,50.0122680664],"type":"Point"}
}