{
  "type": "Feature",
  "properties": {
    "addr:full":"Mechelsesteenweg 681 Herent Vlaams-Brabant 3020",
    "addr:housenumber":"681",
    "addr:postcode":"3020",
    "addr:street":"Mechelsesteenweg",
    "iso:country":"BE",
    "sg:address":"Mechelsesteenweg 681",
    "sg:city":"Herent",
    "sg:orig_category":"Voertuigen",
    "sg:phone":"+32 16 22 79 89",
    "sg:postcode":"3020",
    "sg:province":"Vlaams-Brabant",
    "wof:name":"Daniel Vandenheuvel",
    "wof:placetype":"venue"
},
  "geometry": {"coordinates":[4.6872601509,50.8951911926],"type":"Point"}
}