{
  "type": "Feature",
  "properties": {
    "addr:full":"Melkerijstraat 66/3 Halle Vlaams-Brabant 1500",
    "addr:housenumber":"66 / 3",
    "addr:postcode":"1500",
    "addr:street":"Melkerijstraat",
    "iso:country":"BE",
    "sg:address":"Melkerijstraat 66/3",
    "sg:city":"Halle",
    "sg:orig_category":"Sportclubs",
    "sg:phone":"+32 2 356 59 46",
    "sg:postcode":"1500",
    "sg:province":"Vlaams-Brabant",
    "wof:name":"Buizingen Sportief",
    "wof:placetype":"venue"
},
  "geometry": {"coordinates":[4.2420158386,50.7314453125],"type":"Point"}
}