{
  "type": "Feature",
  "properties": {
    "addr:full":"Heirweg 45 De Pinte Oost-Vlaanderen 9840",
    "addr:housenumber":"45",
    "addr:postcode":"9840",
    "addr:street":"Heirweg",
    "iso:country":"BE",
    "sg:address":"Heirweg 45",
    "sg:city":"De Pinte",
    "sg:classifiers":[
        {
            "category":"Professional",
            "subcategory":"Credit Reporting & Collection",
            "type":"Services"
        }
    ],
    "sg:phone":"+32 9 385 89 90",
    "sg:postcode":"9840",
    "sg:province":"Oost-Vlaanderen",
    "sg:tags":[
        "bailiff"
    ],
    "wof:name":"Matthys J",
    "wof:placetype":"venue"
},
  "geometry": {"coordinates":[3.6490449905,50.9758110046],"type":"Point"}
}