{
  "type": "Feature",
  "properties": {
    "iso:country":"BE",
    "sg:address":"Entrepotstraat 5",
    "sg:city":"Sint-niklaas",
    "sg:classifiers":[
        {
            "category":"Home & Garden",
            "subcategory":"Building Materials",
            "type":"Retail Goods"
        }
    ],
    "sg:phone":"+32 3 777 23 69",
    "sg:postcode":"9100",
    "sg:province":"Oost-Vlaanderen",
    "sg:tags":[
        "aluminium",
        "construction",
        "-"
    ],
    "wof:name":"Ricka Nv",
    "wof:placetype":"venue"
},
  "geometry": {"coordinates":[4.1672339439,51.174987793],"type":"Point"}
}