{
  "type": "Feature",
  "properties": {
    "iso:country":"BE",
    "sg:address":"Chauss\u00e9e De Louvain 81",
    "sg:city":"Eghez\u00e9e",
    "sg:classifiers":[
        {
            "category":"Shopping",
            "subcategory":"Antiques",
            "type":"Retail Goods"
        }
    ],
    "sg:phone":"+32 81 81 15 66",
    "sg:postcode":"5310",
    "sg:province":"Namur",
    "wof:name":"Maison Vande Ryse Sa",
    "wof:placetype":"venue"
},
  "geometry": {"coordinates":[4.9062800407,50.5970687866],"type":"Point"}
}