{
  "type": "Feature",
  "properties": {
    "addr:full":"Sint-annastraat 15 Waasmunster Oost-Vlaanderen 9250",
    "addr:housenumber":"15",
    "addr:postcode":"9250",
    "addr:street":"Sint-Annastraat",
    "iso:country":"BE",
    "sg:address":"Sint-annastraat 15",
    "sg:city":"Waasmunster",
    "sg:orig_category":"Agences de presse",
    "sg:phone":"+32 52 47 80 16",
    "sg:postcode":"9250",
    "sg:province":"Oost-Vlaanderen",
    "wof:name":"Roland Rentmeesters",
    "wof:placetype":"venue"
},
  "geometry": {"coordinates":[4.087003231,51.0954818726],"type":"Point"}
}