{
  "type": "Feature",
  "properties": {
    "addr:full":"Rue De Neufch\u00e2teau 72 Libramont-chevigny (recogne) Luxembourg 6800",
    "addr:housenumber":"72",
    "addr:postcode":"6800",
    "addr:street":"Rue De Neufcha\u0302Teau",
    "iso:country":"BE",
    "sg:address":"Rue De Neufch\u00e2teau 72",
    "sg:city":"Libramont-chevigny (recogne)",
    "sg:classifiers":[
        {
            "category":"Professional",
            "subcategory":"Detective & Security Services",
            "type":"Services"
        }
    ],
    "sg:phone":"+32 61 22 50 36",
    "sg:postcode":"6800",
    "sg:province":"Luxembourg",
    "sg:tags":[
        "installation",
        "alarm",
        "-",
        "system"
    ],
    "wof:name":"Atmr S\u00e9curit\u00e9",
    "wof:placetype":"venue"
},
  "geometry": {"coordinates":[5.3761348724,49.9199943542],"type":"Point"}
}