{
  "type": "Feature",
  "properties": {
    "iso:country":"BE",
    "sg:address":"9300",
    "sg:city":"Aalst",
    "sg:orig_category":"Etablissements Erotiques",
    "sg:phone":"+32 53 77 97 54",
    "sg:postcode":"9300",
    "sg:province":"Oost-Vlaanderen",
    "wof:name":"Vanessa",
    "wof:placetype":"venue"
},
  "geometry": {"coordinates":[4.0454001427,50.9429397583],"type":"Point"}
}