{
  "type": "Feature",
  "properties": {
    "addr:full":"Rue Gr\u00e9try 150 Li\u00e8ge 1 (li\u00e8ge 2) Li\u00e8ge 4020",
    "addr:housenumber":"150;1;2",
    "addr:postcode":"4020",
    "addr:street":"Rue Gre\u0301Try",
    "iso:country":"BE",
    "sg:address":"Rue Gr\u00e9try 150",
    "sg:city":"Li\u00e8ge 1 (li\u00e8ge 2)",
    "sg:classifiers":[
        {
            "category":"Professional",
            "subcategory":"Computer Services",
            "type":"Services"
        }
    ],
    "sg:phone":"+32 4 340 42 60",
    "sg:postcode":"4020",
    "sg:province":"Li\u00e8ge",
    "sg:tags":[
        "webdesign",
        "-",
        "internet"
    ],
    "wof:name":"Web Consult",
    "wof:placetype":"venue"
},
  "geometry": {"coordinates":[5.5839190483,50.6321754456],"type":"Point"}
}