{
  "type": "Feature",
  "properties": {
    "addr:full":"Rue De Forges 51 Chimay Hainaut 6460",
    "addr:housenumber":"51",
    "addr:postcode":"6460",
    "addr:street":"Rue De Forges",
    "iso:country":"BE",
    "sg:address":"Rue De Forges 51",
    "sg:city":"Chimay",
    "sg:orig_category":"Plaatsen van vloer- and muurbekleding Schilders Vloer- and muurbekleding",
    "sg:phone":"+32 60 21 11 65",
    "sg:postcode":"6460",
    "sg:province":"Hainaut",
    "wof:name":"Canivet",
    "wof:placetype":"venue"
},
  "geometry": {"coordinates":[4.3191719055,50.0415992737],"type":"Point"}
}