{
  "type": "Feature",
  "properties": {
    "iso:country":"BE",
    "sg:address":"Dorp 78",
    "sg:city":"Herselt",
    "sg:classifiers":[
        {
            "category":"Home & Garden",
            "subcategory":"Home Furnishings",
            "type":"Retail Goods"
        }
    ],
    "sg:phone":"+32 14 54 55 11",
    "sg:postcode":"2230",
    "sg:province":"Antwerpen",
    "sg:tags":[
        "-",
        "furniture"
    ],
    "wof:name":"Vi-spring/de Bedstee",
    "wof:placetype":"venue"
},
  "geometry": {"coordinates":[4.8839588165,51.054649353],"type":"Point"}
}