{
  "type": "Feature",
  "properties": {
    "iso:country":"BE",
    "sg:address":"Rue De La Tasni\u00c8re 60",
    "sg:city":"Rixensart",
    "sg:orig_category":"Herstellingen and onderhoud van auto's Voertuigen",
    "sg:phone":"+32 2 653 56 95",
    "sg:postcode":"1332",
    "sg:province":"Brabant Wallon",
    "wof:name":"Schmitz",
    "wof:placetype":"venue"
},
  "geometry": {"coordinates":[4.5050902367,50.7263908386],"type":"Point"}
}