{
  "type": "Feature",
  "properties": {
    "iso:country":"BE",
    "sg:address":"Hasseltweg 487",
    "sg:city":"Genk",
    "sg:orig_category":"Industri\u00eble wasserijen and droogkuis",
    "sg:phone":"+32 11 21 12 58",
    "sg:postcode":"3600",
    "sg:province":"Limburg",
    "wof:name":"Mireno Schizzarotto",
    "wof:placetype":"venue"
},
  "geometry": {"coordinates":[5.4345149994,50.9573249817],"type":"Point"}
}