{
  "type": "Feature",
  "properties": {
    "addr:full":"Rue Vaudr\u00e9e 226 Li\u00e8ge 1 (angleur) Li\u00e8ge 4031",
    "addr:housenumber":"226;1",
    "addr:postcode":"4031",
    "addr:street":"Rue Vaudre\u0301E",
    "iso:country":"BE",
    "sg:address":"Rue Vaudr\u00e9e 226",
    "sg:city":"Li\u00e8ge 1 (angleur)",
    "sg:classifiers":[
        {
            "category":"Personal",
            "subcategory":"Nail Salon",
            "type":"Services"
        }
    ],
    "sg:phone":"+32 4 365 07 68",
    "sg:postcode":"4031",
    "sg:province":"Li\u00e8ge",
    "sg:tags":[
        "pedicure"
    ],
    "wof:name":"G\u00e9rard J",
    "wof:placetype":"venue"
},
  "geometry": {"coordinates":[5.5878181458,50.6136322021],"type":"Point"}
}