{
  "type": "Feature",
  "properties": {
    "iso:country":"BE",
    "sg:address":"Merrenhofstraat 11",
    "sg:city":"Kinrooi",
    "sg:classifiers":[
        {
            "category":"Personal",
            "subcategory":"Beauty Salon",
            "type":"Services"
        }
    ],
    "sg:phone":"+32 89 56 41 75",
    "sg:postcode":"3640",
    "sg:province":"Limburg",
    "sg:tags":[
        "de",
        "coiffure"
    ],
    "wof:name":"Jozefina Sybers",
    "wof:placetype":"venue"
},
  "geometry": {"coordinates":[5.7972202301,51.1296768188],"type":"Point"}
}