{
  "type": "Feature",
  "properties": {
    "addr:full":"Pont Des Bayards 79 Li\u00e8ge 1 Li\u00e8ge 4000",
    "addr:housenumber":"79;1",
    "addr:postcode":"4000",
    "addr:street":"Pont Des Bayards",
    "iso:country":"BE",
    "sg:address":"Pont Des Bayards 79",
    "sg:city":"Li\u00e8ge 1",
    "sg:classifiers":[
        {
            "category":"Food & Beverages",
            "subcategory":"Groceries & Convenience Stores",
            "type":"Retail Goods"
        }
    ],
    "sg:phone":"+32 4 227 40 68",
    "sg:postcode":"4000",
    "sg:province":"Li\u00e8ge",
    "sg:tags":[
        "grocer"
    ],
    "wof:name":"Calahorro",
    "wof:placetype":"venue"
},
  "geometry": {"coordinates":[5.5977940559,50.6557998657],"type":"Point"}
}