{
  "type": "Feature",
  "properties": {
    "addr:full":"Turnhoutsebaan 274 Schilde Antwerpen 2970",
    "addr:housenumber":"274",
    "addr:postcode":"2970",
    "addr:street":"Turnhoutsebaan",
    "iso:country":"BE",
    "sg:address":"Turnhoutsebaan 274",
    "sg:city":"Schilde",
    "sg:classifiers":[
        {
            "category":"Fast Food",
            "type":"Food & Drink"
        }
    ],
    "sg:phone":"+32 3 385 08 94",
    "sg:postcode":"2970",
    "sg:province":"Antwerpen",
    "sg:tags":[
        "\u00c0",
        "emporter",
        "restaurants"
    ],
    "wof:name":"La Dolce Pitta",
    "wof:placetype":"venue"
},
  "geometry": {"coordinates":[4.581715107,51.2400131226],"type":"Point"}
}