{
  "type": "Feature",
  "properties": {
    "iso:country":"BE",
    "sg:address":"Pav\u00c9 Bayart 12",
    "sg:city":"Estaimpuis",
    "sg:orig_category":"Rundveehouders",
    "sg:phone":"+32 56 48 82 60",
    "sg:postcode":"7730",
    "sg:province":"Hainaut",
    "wof:name":"Marceau Michels",
    "wof:placetype":"venue"
},
  "geometry": {"coordinates":[3.2755610943,50.711933136],"type":"Point"}
}