{
  "type": "Feature",
  "properties": {
    "iso:country":"BE",
    "sg:address":"Polderstraat 47",
    "sg:city":"Sint-gillis-waas",
    "sg:orig_category":"Boekhouders",
    "sg:phone":"+32 3 773 36 03",
    "sg:postcode":"9170",
    "sg:province":"Oost-Vlaanderen",
    "wof:name":"Patrick Verschooren",
    "wof:placetype":"venue"
},
  "geometry": {"coordinates":[4.1437001228,51.2626800537],"type":"Point"}
}