{
  "type": "Feature",
  "properties": {
    "addr:full":"Chauss\u00e9e De Bruxelles 394a Braine-le-comte (hennuy\u00e8res) Hainaut 7090",
    "addr:housenumber":"394a",
    "addr:postcode":"7090",
    "addr:street":"Chausse\u0301E De Bruxelles",
    "iso:country":"BE",
    "sg:address":"Chauss\u00e9e De Bruxelles 394a",
    "sg:city":"Braine-le-comte (hennuy\u00e8res)",
    "sg:classifiers":[
        {
            "category":"Home & Garden",
            "subcategory":"Carpets & Floor Coverings",
            "type":"Retail Goods"
        }
    ],
    "sg:phone":"+32 67 21 09 00",
    "sg:postcode":"7090",
    "sg:province":"Hainaut",
    "sg:tags":[
        "merchant",
        "iron"
    ],
    "wof:name":"G Metal",
    "wof:placetype":"venue"
},
  "geometry": {"coordinates":[4.1448898315,50.6265335083],"type":"Point"}
}