{
  "type": "Feature",
  "properties": {
    "iso:country":"BE",
    "sg:address":"Chauss\u00c9e Solvay 8",
    "sg:city":"Charleroi",
    "sg:classifiers":[
        {
            "category":"Restaurant",
            "type":"Food & Drink"
        }
    ],
    "sg:phone":"+32 71 33 01 41",
    "sg:postcode":"6061",
    "sg:province":"Hainaut",
    "sg:tags":[
        "caf\u00e9s"
    ],
    "wof:name":"Taverne H\u00d4tel De Ville",
    "wof:placetype":"venue"
},
  "geometry": {"coordinates":[4.4810137749,50.3995475769],"type":"Point"}
}