{
  "type": "Feature",
  "properties": {
    "iso:country":"BE",
    "sg:address":"Monschauer Strasse 102",
    "sg:city":"Eupen",
    "sg:classifiers":[
        {
            "category":"Restaurant",
            "type":"Food & Drink"
        }
    ],
    "sg:phone":"+32 87 55 67 49",
    "sg:postcode":"4700",
    "sg:province":"Li\u00e8ge",
    "wof:name":"Domino Im Rotterwaldchen",
    "wof:placetype":"venue"
},
  "geometry": {"coordinates":[6.0637359619,50.6107597351],"type":"Point"}
}