{
  "type": "Feature",
  "properties": {
    "iso:country":"BE",
    "sg:address":"Bergstraat 131",
    "sg:city":"Heist-op-den-berg",
    "sg:orig_category":"Herenkledingzaken",
    "sg:phone":"+32 15 24 70 25",
    "sg:postcode":"2220",
    "sg:province":"Antwerpen",
    "wof:name":"\u00b4t Saloon Country",
    "wof:placetype":"venue"
},
  "geometry": {"coordinates":[4.7186050415,51.0767250061],"type":"Point"}
}