{
  "type": "Feature",
  "properties": {
    "addr:full":"Smidsestraat 2 Gent Oost-Vlaanderen 9000",
    "addr:housenumber":"2",
    "addr:postcode":"9000",
    "addr:street":"Smidsestraat;Oost-Vlaanderen",
    "iso:country":"BE",
    "sg:address":"Smidsestraat 2",
    "sg:city":"Gent",
    "sg:classifiers":[
        {
            "category":"Professional",
            "subcategory":"Lawyer & Legal Services",
            "type":"Services"
        }
    ],
    "sg:phone":"+32 9 225 60 60",
    "sg:postcode":"9000",
    "sg:province":"Oost-Vlaanderen",
    "sg:tags":[
        "notary"
    ],
    "wof:name":"Van Belle C",
    "wof:placetype":"venue"
},
  "geometry": {"coordinates":[3.7166149616,51.0401573181],"type":"Point"}
}