{
  "type": "Feature",
  "properties": {
    "iso:country":"BE",
    "sg:address":"Fincentlaan 41",
    "sg:city":"Knokke-heist (knokke)",
    "sg:classifiers":[
        {
            "category":"Professional",
            "subcategory":"Lawyer & Legal Services",
            "type":"Services"
        }
    ],
    "sg:phone":"+32 50 62 47 60",
    "sg:postcode":"8300",
    "sg:province":"West-Vlaanderen",
    "wof:name":"Bouche H",
    "wof:placetype":"venue"
},
  "geometry": {"coordinates":[3.2858800888,51.3427963257],"type":"Point"}
}