{
  "type": "Feature",
  "properties": {
    "addr:full":"Willekensmolenstraat 135 Hasselt Limburg 3500",
    "addr:housenumber":"135",
    "addr:postcode":"3500",
    "addr:street":"Willekensmolenstraat",
    "iso:country":"BE",
    "sg:address":"Willekensmolenstraat 135",
    "sg:city":"Hasselt",
    "sg:orig_category":"M\u00e9decins and sp\u00e9cialistes",
    "sg:phone":"+32 11 22 51 52",
    "sg:postcode":"3500",
    "sg:province":"Limburg",
    "wof:name":"P. Decoutere",
    "wof:placetype":"venue"
},
  "geometry": {"coordinates":[5.3517198563,50.9323577881],"type":"Point"}
}