{
  "type": "Feature",
  "properties": {
    "iso:country":"BE",
    "sg:address":"Marktplein 9",
    "sg:city":"Hamme",
    "sg:orig_category":"Cr\u00e9dits divers",
    "sg:postcode":"9220",
    "sg:province":"Oost-Vlaanderen",
    "wof:name":"Bancontact-mister Cash",
    "wof:placetype":"venue"
},
  "geometry": {"coordinates":[4.136906147,51.0977287292],"type":"Point"}
}