{
  "type": "Feature",
  "properties": {
    "addr:full":"Pastorijstraat 19 Hasselt Limburg 3500",
    "addr:housenumber":"19",
    "addr:postcode":"3500",
    "addr:street":"Pastorijstraat",
    "iso:country":"BE",
    "sg:address":"Pastorijstraat 19",
    "sg:city":"Hasselt",
    "sg:orig_category":"Restaurants Ruimtes voor conferenties, recepties and feesten",
    "sg:phone":"+32 11 31 30 38",
    "sg:postcode":"3500",
    "sg:province":"Limburg",
    "wof:name":"De Vuurdoorn",
    "wof:placetype":"venue"
},
  "geometry": {"coordinates":[5.3046188354,50.8997039795],"type":"Point"}
}