{
  "type": "Feature",
  "properties": {
    "addr:full":"Ravenstraat 15 Leuven Vlaams-Brabant 3000",
    "addr:housenumber":"15",
    "addr:postcode":"3000",
    "addr:street":"Ravenstraat",
    "iso:country":"BE",
    "sg:address":"Ravenstraat 15",
    "sg:city":"Leuven",
    "sg:classifiers":[
        {
            "category":"Restaurant",
            "type":"Food & Drink"
        }
    ],
    "sg:phone":"+32 16 20 18 94",
    "sg:postcode":"3000",
    "sg:province":"Vlaams-Brabant",
    "wof:name":"De Appel",
    "wof:placetype":"venue"
},
  "geometry": {"coordinates":[4.7070770264,50.8774681091],"type":"Point"}
}