{
  "type": "Feature",
  "properties": {
    "addr:full":"Kloosterstraat 93 Antwerpen Antwerpen 2180",
    "addr:housenumber":"93",
    "addr:postcode":"2180",
    "addr:street":"Kloosterstraat",
    "iso:country":"BE",
    "sg:address":"Kloosterstraat 93",
    "sg:city":"Antwerpen",
    "sg:orig_category":"Disquaires",
    "sg:phone":"+32 3 542 62 66",
    "sg:postcode":"2180",
    "sg:province":"Antwerpen",
    "wof:name":"Huis Cadodisc",
    "wof:placetype":"venue"
},
  "geometry": {"coordinates":[4.3946399689,51.2150344849],"type":"Point"}
}