{
  "type": "Feature",
  "properties": {
    "iso:country":"BE",
    "sg:address":"Avenue Du Haut-pays 5",
    "sg:city":"Honnelles",
    "sg:orig_category":"Eleveurs de bovins",
    "sg:phone":"+32 65 75 93 62",
    "sg:postcode":"7387",
    "sg:province":"Hainaut",
    "wof:name":"Georges Druart",
    "wof:placetype":"venue"
},
  "geometry": {"coordinates":[3.7538750172,50.3538131714],"type":"Point"}
}