{
  "type": "Feature",
  "properties": {
    "addr:full":"Lange Meire 51 Laarne Oost-Vlaanderen 9270",
    "addr:housenumber":"51",
    "addr:postcode":"9270",
    "addr:street":"Lange Meire",
    "iso:country":"BE",
    "sg:address":"Lange Meire 51",
    "sg:city":"Laarne",
    "sg:orig_category":"Installatie van houten of kunststof schrijnwerk",
    "sg:phone":"+32 9 369 45 62",
    "sg:postcode":"9270",
    "sg:province":"Oost-Vlaanderen",
    "wof:name":"Peter Mareels",
    "wof:placetype":"venue"
},
  "geometry": {"coordinates":[3.8626511097,51.0300941467],"type":"Point"}
}