{
  "type": "Feature",
  "properties": {
    "iso:country":"BE",
    "sg:address":"Rue De La Clef 1",
    "sg:city":"Fl\u00c9ron (grand)",
    "sg:orig_category":"IJzerwaren, bouw- and verfmaterialen Plaatsen van vloer- and muurbekleding Schilders Textiel Verlich",
    "sg:phone":"+32 4 358 88 10",
    "sg:postcode":"4621",
    "sg:province":"Li\u00e8ge",
    "wof:name":"Heytens",
    "wof:placetype":"venue"
},
  "geometry": {"coordinates":[5.6880822182,50.6147499084],"type":"Point"}
}