{
  "type": "Feature",
  "properties": {
    "addr:full":"Hoogstraat 314 Brussel/bruxelles Bruxelles-Capitale 1000",
    "addr:housenumber":"314",
    "addr:postcode":"1000",
    "addr:street":"Hoogstraat;/",
    "iso:country":"BE",
    "sg:address":"Hoogstraat 314",
    "sg:city":"Brussel/bruxelles",
    "sg:orig_category":"Krantenwinkels Rookartikelen",
    "sg:phone":"+32 2 534 28 17",
    "sg:postcode":"1000",
    "sg:province":"Bruxelles-Capitale",
    "wof:name":"Librairie Anny",
    "wof:placetype":"venue"
},
  "geometry": {"coordinates":[4.3461608887,50.8345451355],"type":"Point"}
}