{
  "type": "Feature",
  "properties": {
    "addr:full":"Stationsstraat 168 Gavere Oost-Vlaanderen 9890",
    "addr:housenumber":"168",
    "addr:postcode":"9890",
    "addr:street":"Stationsstraat",
    "iso:country":"BE",
    "sg:address":"Stationsstraat 168",
    "sg:city":"Gavere",
    "sg:classifiers":[
        {
            "category":"Shopping",
            "subcategory":"Bicycles & Sporting Goods",
            "type":"Retail Goods"
        }
    ],
    "sg:phone":"+32 9 390 82 71",
    "sg:postcode":"9890",
    "sg:province":"Oost-Vlaanderen",
    "sg:tags":[
        "-"
    ],
    "wof:name":"Freewheels",
    "wof:placetype":"venue"
},
  "geometry": {"coordinates":[3.6481471062,50.9294776917],"type":"Point"}
}