{
  "type": "Feature",
  "properties": {
    "addr:full":"Victoriestraat 2 Beveren Oost-Vlaanderen 9120",
    "addr:housenumber":"2",
    "addr:postcode":"9120",
    "addr:street":"Victoriestraat",
    "iso:country":"BE",
    "sg:address":"Victoriestraat 2",
    "sg:city":"Beveren",
    "sg:classifiers":[
        {
            "category":"Recreation",
            "type":"Entertainment"
        }
    ],
    "sg:phone":"+32 3 575 03 35",
    "sg:postcode":"9120",
    "sg:province":"Oost-Vlaanderen",
    "sg:tags":[
        "diver",
        "amusement"
    ],
    "wof:name":"Disco-show Enjoy",
    "wof:placetype":"venue"
},
  "geometry": {"coordinates":[4.2783999443,51.2529144287],"type":"Point"}
}