{
  "type": "Feature",
  "properties": {
    "iso:country":"BE",
    "sg:address":"Westkapellestraat 474",
    "sg:city":"Knokke-heist",
    "sg:orig_category":"HUISBRANDOLIE",
    "sg:phone":"+32 50 60 30 97",
    "sg:postcode":"8300",
    "sg:province":"West-Vlaanderen",
    "wof:name":"Marc Broucke",
    "wof:placetype":"venue"
},
  "geometry": {"coordinates":[3.287694931,51.3467254639],"type":"Point"}
}