{
  "type": "Feature",
  "properties": {
    "addr:full":"Rue Du Joncquoy 63 Peruwelz Hainaut 7602",
    "addr:housenumber":"63",
    "addr:postcode":"7602",
    "addr:street":"Rue Du Joncquoy;Hainaut",
    "iso:country":"BE",
    "sg:address":"Rue Du Joncquoy 63",
    "sg:city":"Peruwelz",
    "sg:orig_category":"Installation \u00e9lectrique industrielle",
    "sg:phone":"+32 69 77 37 81",
    "sg:postcode":"7602",
    "sg:province":"Hainaut",
    "wof:name":"Alsec Alarme Et Securite",
    "wof:placetype":"venue"
},
  "geometry": {"coordinates":[3.5908200741,50.5430603027],"type":"Point"}
}