{
  "type": "Feature",
  "properties": {
    "iso:country":"BE",
    "sg:address":"Rue Saint-jacques 20",
    "sg:city":"Binche",
    "sg:classifiers":[
        {
            "category":"Personal",
            "subcategory":"Beauty Salon",
            "type":"Services"
        }
    ],
    "sg:phone":"+32 64 36 73 91",
    "sg:postcode":"7130",
    "sg:province":"Hainaut",
    "sg:tags":[
        "lady",
        "-",
        "hairdressing"
    ],
    "wof:name":"Patrick",
    "wof:placetype":"venue"
},
  "geometry": {"coordinates":[4.1640357971,50.4108924866],"type":"Point"}
}