{
  "type": "Feature",
  "properties": {
    "iso:country":"BE",
    "sg:address":"Comansweg 42",
    "sg:city":"Hechtel-eksel (hechtel)",
    "sg:classifiers":[
        {
            "category":"Autos & Motor Vehicles",
            "subcategory":"Motorcycle Sales",
            "type":"Retail Goods"
        }
    ],
    "sg:phone":"+32 11 73 35 76",
    "sg:postcode":"3940",
    "sg:province":"Limburg",
    "sg:tags":[
        "motorbike"
    ],
    "wof:name":"Stappers Danny",
    "wof:placetype":"venue"
},
  "geometry": {"coordinates":[5.364795208,51.1255340576],"type":"Point"}
}