{
  "type": "Feature",
  "properties": {
    "iso:country":"BE",
    "sg:address":"Antoon De Pesseroeylaan 58",
    "sg:city":"Sint-martens-latem (deurle)",
    "sg:classifiers":[
        {
            "category":"Professional",
            "subcategory":"Management & Consulting",
            "type":"Services"
        }
    ],
    "sg:phone":"+32 9 245 68 01",
    "sg:postcode":"9831",
    "sg:province":"Oost-Vlaanderen",
    "sg:tags":[
        "consultant"
    ],
    "wof:name":"B & M Consulting",
    "wof:placetype":"venue"
},
  "geometry": {"coordinates":[3.6088070869,51.0002632141],"type":"Point"}
}