{
  "type": "Feature",
  "properties": {
    "addr:full":"Rue Des Forges 46a Leglise Luxembourg 6860",
    "addr:housenumber":"46a",
    "addr:postcode":"6860",
    "addr:street":"Rue Des Forges",
    "iso:country":"BE",
    "sg:address":"Rue Des Forges 46a",
    "sg:city":"Leglise",
    "sg:orig_category":"Rev\u00eatements de sols and murs. Meubles Fab. Installation de menuiserie en bois and plastique. Install",
    "sg:phone":"+32 63 43 38 37",
    "sg:postcode":"6860",
    "sg:province":"Luxembourg",
    "wof:name":"Hubert Fr\u00c8res Menuiserie",
    "wof:placetype":"venue"
},
  "geometry": {"coordinates":[5.5349779129,49.7996826172],"type":"Point"}
}