{
  "type": "Feature",
  "properties": {
    "addr:full":"Stationstraat 142 Haacht Vlaams-Brabant 3150",
    "addr:housenumber":"142",
    "addr:postcode":"3150",
    "addr:street":"Stationstraat",
    "iso:country":"BE",
    "sg:address":"Stationstraat 142",
    "sg:city":"Haacht",
    "sg:orig_category":"Herstellingen and onderhoud aan huis voor voertuigen Metaalafval, schrootrecyclage and sloperijen",
    "sg:phone":"+32 16 60 13 76",
    "sg:postcode":"3150",
    "sg:province":"Vlaams-Brabant",
    "wof:name":"Autohandel Depannage Rb-trucks",
    "wof:placetype":"venue"
},
  "geometry": {"coordinates":[4.6249980927,50.9728355408],"type":"Point"}
}