{
  "type": "Feature",
  "properties": {
    "addr:full":"Torhoutsesteenweg 234 Oostende West-Vlaanderen 8400",
    "addr:housenumber":"234",
    "addr:postcode":"8400",
    "addr:street":"Torhoutsesteenweg",
    "iso:country":"BE",
    "sg:address":"Torhoutsesteenweg 234",
    "sg:city":"Oostende",
    "sg:orig_category":"Administration d'immeubles",
    "sg:phone":"+32 59 70 29 33",
    "sg:postcode":"8400",
    "sg:province":"West-Vlaanderen",
    "wof:name":"Karel Vanden Broecke",
    "wof:placetype":"venue"
},
  "geometry": {"coordinates":[2.9075078964,51.2175064087],"type":"Point"}
}