{
  "type": "Feature",
  "properties": {
    "iso:country":"BE",
    "sg:address":"Arteveldestraat 159a",
    "sg:city":"Brussel/bruxelles",
    "sg:orig_category":"Juwelen and horloges",
    "sg:phone":"+32 2 511 85 63",
    "sg:postcode":"1000",
    "sg:province":"Bruxelles-Capitale",
    "wof:name":"Maison Baudot",
    "wof:placetype":"venue"
},
  "geometry": {"coordinates":[4.3429751396,50.8463745117],"type":"Point"}
}