{
  "type": "Feature",
  "properties": {
    "addr:full":"Rue Charles Moncousin 0 Wanze Li\u00e8ge 4520",
    "addr:housenumber":"0",
    "addr:postcode":"4520",
    "addr:street":"Rue Charles Moncousin",
    "iso:country":"BE",
    "sg:address":"Rue Charles Moncousin 0",
    "sg:city":"Wanze",
    "sg:orig_category":"Sportclubs Sportterreinen and installaties behalve sportcentra",
    "sg:phone":"+32 85 23 17 21",
    "sg:postcode":"4520",
    "sg:province":"Li\u00e8ge",
    "wof:name":"Piscine Communale",
    "wof:placetype":"venue"
},
  "geometry": {"coordinates":[5.212911129,50.5337104797],"type":"Point"}
}