{
  "type": "Feature",
  "properties": {
    "iso:country":"BE",
    "sg:address":"Bukenstraat 16bb",
    "sg:city":"Kampenhout",
    "sg:orig_category":"Loodgieterij, verwarming and sanitaire installaties",
    "sg:phone":"+32 16 73 48 42",
    "sg:postcode":"1910",
    "sg:province":"Vlaams-Brabant",
    "wof:name":"Fa. Roberechts-nackaerts",
    "wof:placetype":"venue"
},
  "geometry": {"coordinates":[4.6174449921,50.9366798401],"type":"Point"}
}