{
  "type": "Feature",
  "properties": {
    "addr:full":"Groenstraat 15a Hoeselt Limburg 3730",
    "addr:housenumber":"15a",
    "addr:postcode":"3730",
    "addr:street":"Groenstraat",
    "iso:country":"BE",
    "sg:address":"Groenstraat 15a",
    "sg:city":"Hoeselt",
    "sg:classifiers":[
        {
            "category":"Building & Trades",
            "subcategory":"Landscaping Services",
            "type":"Services"
        }
    ],
    "sg:phone":"+32 89 41 22 26",
    "sg:postcode":"3730",
    "sg:province":"Limburg",
    "sg:tags":[
        "nurseryman"
    ],
    "wof:name":"Claesen K & W",
    "wof:placetype":"venue"
},
  "geometry": {"coordinates":[5.4811282158,50.8593254089],"type":"Point"}
}