{
  "type": "Feature",
  "properties": {
    "iso:country":"BE",
    "sg:address":"Vroenhoek 7",
    "sg:city":"Kaprijke",
    "sg:orig_category":"Voedingsspeciaalzaken",
    "sg:phone":"+32 9 373 83 69",
    "sg:postcode":"9971",
    "sg:province":"Oost-Vlaanderen",
    "wof:name":"Bart Van Damme",
    "wof:placetype":"venue"
},
  "geometry": {"coordinates":[3.6582698822,51.2066993713],"type":"Point"}
}