{
  "type": "Feature",
  "properties": {
    "iso:country":"BE",
    "sg:address":"Elverdingseweg 3",
    "sg:city":"Poperinge",
    "sg:orig_category":"Eleveurs de bovins",
    "sg:phone":"+32 57 33 43 84",
    "sg:postcode":"8970",
    "sg:province":"West-Vlaanderen",
    "wof:name":"Cuvelier Raoul En Stephan",
    "wof:placetype":"venue"
},
  "geometry": {"coordinates":[2.7481710911,50.8606643677],"type":"Point"}
}