{
  "type": "Feature",
  "properties": {
    "iso:country":"BE",
    "sg:address":"Avenue Brugmann 404",
    "sg:city":"Bruxelles (uccle)",
    "sg:classifiers":[
        {
            "category":"Professional",
            "subcategory":"Lawyer & Legal Services",
            "type":"Services"
        }
    ],
    "sg:phone":"+32 2 346 64 40",
    "sg:postcode":"1180",
    "sg:province":"Bruxelles-Capitale",
    "wof:name":"Fink Arnaud",
    "wof:placetype":"venue"
},
  "geometry": {"coordinates":[4.3427391052,50.8050727844],"type":"Point"}
}