{
  "type": "Feature",
  "properties": {
    "iso:country":"BE",
    "sg:address":"Rue De La Fontaine Dieu 23",
    "sg:city":"Eghezee",
    "sg:orig_category":"Installation \u00e9lectrique r\u00e9sidentielle. Plomberie, chauffage and installations sanitaires",
    "sg:phone":"+32 81 81 19 58",
    "sg:postcode":"5310",
    "sg:province":"Namur",
    "wof:name":"Michaux & Fils",
    "wof:placetype":"venue"
},
  "geometry": {"coordinates":[4.8763489723,50.5972366333],"type":"Point"}
}