{
  "type": "Feature",
  "properties": {
    "addr:full":"Antwerpsesteenweg 845 Gent Oost-Vlaanderen 9040",
    "addr:housenumber":"845",
    "addr:postcode":"9040",
    "addr:street":"Antwerpsesteenweg;Oost-Vlaanderen",
    "iso:country":"BE",
    "sg:address":"Antwerpsesteenweg 845",
    "sg:city":"Gent",
    "sg:classifiers":[
        {
            "category":"Cafe",
            "type":"Food & Drink"
        }
    ],
    "sg:phone":"+32 9 228 25 16",
    "sg:postcode":"9040",
    "sg:province":"Oost-Vlaanderen",
    "sg:tags":[
        "caf\u00e9s"
    ],
    "wof:name":"Caf\u00c9 Meerakker",
    "wof:placetype":"venue"
},
  "geometry": {"coordinates":[3.7812480927,51.0771827698],"type":"Point"}
}