{
  "type": "Feature",
  "properties": {
    "iso:country":"BE",
    "sg:address":"Singel 17a",
    "sg:city":"Gand",
    "sg:orig_category":"Metalen constructies Fab",
    "sg:phone":"+32 9 259 14 48",
    "sg:postcode":"9000",
    "sg:province":"Oost-Vlaanderen",
    "wof:name":"Monta-mega",
    "wof:placetype":"venue"
},
  "geometry": {"coordinates":[3.748085022,51.0823707581],"type":"Point"}
}