{
  "type": "Feature",
  "properties": {
    "iso:country":"BE",
    "sg:address":"Damse Vaart-zuid 66",
    "sg:city":"Brugge (sint-kruis)",
    "sg:classifiers":[
        {
            "category":"Shopping",
            "subcategory":"Florist",
            "type":"Retail Goods"
        }
    ],
    "sg:phone":"+32 497 17 02 28",
    "sg:postcode":"8310",
    "sg:province":"West-Vlaanderen",
    "wof:name":"Didier A",
    "wof:placetype":"venue"
},
  "geometry": {"coordinates":[3.2406320572,51.2243766785],"type":"Point"}
}