{
  "type": "Feature",
  "properties": {
    "addr:full":"Kleine Steenweg 38 Heist-op-den-berg (booischot) Antwerpen 2221",
    "addr:housenumber":"38",
    "addr:postcode":"2221",
    "addr:street":"Kleine Steenweg",
    "iso:country":"BE",
    "sg:address":"Kleine Steenweg 38",
    "sg:city":"Heist-op-den-berg (booischot)",
    "sg:classifiers":[
        {
            "category":"Building & Trades",
            "subcategory":"Electrical",
            "type":"Services"
        }
    ],
    "sg:phone":"+32 15 22 30 92",
    "sg:postcode":"2221",
    "sg:province":"Antwerpen",
    "sg:tags":[
        "electric",
        "-",
        "housewiring",
        "contractor"
    ],
    "wof:name":"Elektro T & D Danny Van Gehuchten",
    "wof:placetype":"venue"
},
  "geometry": {"coordinates":[4.7745690346,51.0475654602],"type":"Point"}
}