{
  "type": "Feature",
  "properties": {
    "iso:country":"BE",
    "sg:address":"Beentjesstraat 2a",
    "sg:city":"Nevele",
    "sg:classifiers":[
        {
            "category":"Wholesale",
            "subcategory":"Meat",
            "type":"Manufacturing & Wholesale Goods"
        }
    ],
    "sg:phone":"+32 9 371 43 91",
    "sg:postcode":"9850",
    "sg:province":"Oost-Vlaanderen",
    "sg:tags":[
        "whol",
        "-"
    ],
    "wof:name":"D & D Vleeshandel Bvba",
    "wof:placetype":"venue"
},
  "geometry": {"coordinates":[3.5162870884,51.034576416],"type":"Point"}
}