{
  "type": "Feature",
  "properties": {
    "addr:full":"Place De La Sauge 3 Ottignies-louvain-la-neuve Brabant Wallon 1348",
    "addr:housenumber":"3",
    "addr:postcode":"1348",
    "addr:street":"Place De La Sauge",
    "iso:country":"BE",
    "sg:address":"Place De La Sauge 3",
    "sg:city":"Ottignies-louvain-la-neuve",
    "sg:orig_category":"Reclamebureaus",
    "sg:phone":"+32 10 45 30 79",
    "sg:postcode":"1348",
    "sg:province":"Brabant Wallon",
    "wof:name":"Joanses-communication",
    "wof:placetype":"venue"
},
  "geometry": {"coordinates":[4.6172609329,50.6622772217],"type":"Point"}
}