{
  "type": "Feature",
  "properties": {
    "addr:full":"Rue Ambiorix 90 Li\u00c8ge Li\u00e8ge 4000",
    "addr:housenumber":"90",
    "addr:postcode":"4000",
    "addr:street":"Rue Ambiorix",
    "iso:country":"BE",
    "sg:address":"Rue Ambiorix 90",
    "sg:city":"Li\u00c8ge",
    "sg:orig_category":"Artsen and specialisten",
    "sg:phone":"+32 4 252 98 57",
    "sg:postcode":"4000",
    "sg:province":"Li\u00e8ge",
    "wof:name":"Catherine Kestens",
    "wof:placetype":"venue"
},
  "geometry": {"coordinates":[5.5604200363,50.6294631958],"type":"Point"}
}