{
  "type": "Feature",
  "properties": {
    "addr:full":"Bd Du Bois Jacquet 5 Mouscron Hainaut 7711",
    "addr:housenumber":"5",
    "addr:postcode":"7711",
    "addr:street":"Bd Du Bois Jacquet",
    "iso:country":"BE",
    "sg:address":"Bd Du Bois Jacquet 5",
    "sg:city":"Mouscron",
    "sg:classifiers":[
        {
            "category":"Shopping",
            "subcategory":"Hobbies, Toys, & Games",
            "type":"Retail Goods"
        }
    ],
    "sg:phone":"+32 56 48 51 91",
    "sg:postcode":"7711",
    "sg:province":"Hainaut",
    "sg:tags":[
        "product",
        "miscellaneous",
        "entertainment"
    ],
    "wof:name":"Bougies Craeymeersch Kaarsen Sprl",
    "wof:placetype":"venue"
},
  "geometry": {"coordinates":[3.3080399036,50.7282752991],"type":"Point"}
}