{
  "type": "Feature",
  "properties": {
    "addr:full":"Beverstraat 15-17 Ninove Oost-Vlaanderen 9400",
    "addr:housenumber":"15-17",
    "addr:postcode":"9400",
    "addr:street":"Beverstraat",
    "iso:country":"BE",
    "sg:address":"Beverstraat 15-17",
    "sg:city":"Ninove",
    "sg:classifiers":[
        {
            "category":"Retail",
            "subcategory":"Repair Shop",
            "type":"Services"
        }
    ],
    "sg:phone":"+32 54 33 21 68",
    "sg:postcode":"9400",
    "sg:province":"Oost-Vlaanderen",
    "sg:tags":[
        "-",
        "mainten",
        "watch",
        "clock"
    ],
    "wof:name":"Paul Juweliers Nv",
    "wof:placetype":"venue"
},
  "geometry": {"coordinates":[4.0221309662,50.836139679],"type":"Point"}
}