{
  "type": "Feature",
  "properties": {
    "addr:full":"Vanderkinderestraat 160 Ukkel/uccle Bruxelles-Capitale 1180",
    "addr:housenumber":"160",
    "addr:postcode":"1180",
    "addr:street":"Vanderkinderestraat;/",
    "iso:country":"BE",
    "sg:address":"Vanderkinderestraat 160",
    "sg:city":"Ukkel/uccle",
    "sg:classifiers":[
        {
            "category":"Restaurant",
            "type":"Food & Drink"
        }
    ],
    "sg:phone":"+32 2 344 02 61",
    "sg:postcode":"1180",
    "sg:province":"Bruxelles-Capitale",
    "sg:tags":[
        "caf\u00e9s"
    ],
    "wof:name":"Taverne Mistinguett",
    "wof:placetype":"venue"
},
  "geometry": {"coordinates":[4.3459529877,50.8139457703],"type":"Point"}
}