{
  "type": "Feature",
  "properties": {
    "iso:country":"BE",
    "sg:address":"Rue Du Plan Inclin\u00c9 105",
    "sg:city":"Li\u00c8ge",
    "sg:orig_category":"Goederenvervoer over de weg Koerierbedrijven Taxi's Taxi's speciale diensten Verhuisdiensten",
    "sg:phone":"+32 4 252 20 20",
    "sg:postcode":"4000",
    "sg:province":"Li\u00e8ge",
    "wof:name":"Melkior",
    "wof:placetype":"venue"
},
  "geometry": {"coordinates":[5.565114975,50.627494812],"type":"Point"}
}