{
  "type": "Feature",
  "properties": {
    "iso:country":"BE",
    "sg:address":"Rue De La Station 38",
    "sg:city":"Charleroi",
    "sg:orig_category":"Instituts de beaut\u00e9",
    "sg:phone":"+32 71 41 02 12",
    "sg:postcode":"6060",
    "sg:province":"Hainaut",
    "wof:name":"Luigi Di Cintio",
    "wof:placetype":"venue"
},
  "geometry": {"coordinates":[4.4881749153,50.4239692688],"type":"Point"}
}