{
  "type": "Feature",
  "properties": {
    "iso:country":"BE",
    "sg:address":"Tongersesteenweg 149",
    "sg:city":"Hoeselt",
    "sg:classifiers":[
        {
            "category":"Cafe",
            "type":"Food & Drink"
        }
    ],
    "sg:phone":"+32 12 23 16 91",
    "sg:postcode":"3730",
    "sg:province":"Limburg",
    "sg:tags":[
        "caf\u00e9s"
    ],
    "wof:name":"Rudi Pellaers",
    "wof:placetype":"venue"
},
  "geometry": {"coordinates":[5.4675598145,50.8247718811],"type":"Point"}
}