{
  "type": "Feature",
  "properties": {
    "addr:full":"Heiveld 11 Opwijk Vlaams-Brabant 1745",
    "addr:housenumber":"11",
    "addr:postcode":"1745",
    "addr:street":"Heiveld",
    "iso:country":"BE",
    "sg:address":"Heiveld 11",
    "sg:city":"Opwijk",
    "sg:classifiers":[
        {
            "category":"Personal",
            "subcategory":"Beauty Salon",
            "type":"Services"
        }
    ],
    "sg:phone":"+32 52 35 06 39",
    "sg:postcode":"1745",
    "sg:province":"Vlaams-Brabant",
    "wof:name":"Athena",
    "wof:placetype":"venue"
},
  "geometry": {"coordinates":[4.1862812042,50.9711036682],"type":"Point"}
}