{
  "type": "Feature",
  "properties": {
    "addr:full":"Boulevard De Froidmont 57 Li\u00c8ge Li\u00e8ge 4030",
    "addr:housenumber":"57",
    "addr:postcode":"4030",
    "addr:street":"Boulevard De Froidmont",
    "iso:country":"BE",
    "sg:address":"Boulevard De Froidmont 57",
    "sg:city":"Li\u00c8ge",
    "sg:orig_category":"Diepvriesproducten Gh",
    "sg:phone":"+32 4 341 24 45",
    "sg:postcode":"4030",
    "sg:province":"Li\u00e8ge",
    "wof:name":"Covee",
    "wof:placetype":"venue"
},
  "geometry": {"coordinates":[5.6046648026,50.6188240051],"type":"Point"}
}