{
  "type": "Feature",
  "properties": {
    "addr:full":"Rijselsteenweg 284 Moeskroen/mouscron Hainaut 7700",
    "addr:housenumber":"284",
    "addr:postcode":"7700",
    "addr:street":"Rijselsteenweg",
    "iso:country":"BE",
    "sg:address":"Rijselsteenweg 284",
    "sg:city":"Moeskroen/mouscron",
    "sg:orig_category":"Banken and kredietinstellingen",
    "sg:phone":"+32 56 34 20 87",
    "sg:postcode":"7700",
    "sg:province":"Hainaut",
    "wof:name":"Fortis",
    "wof:placetype":"venue"
},
  "geometry": {"coordinates":[3.2323200703,50.7400932312],"type":"Point"}
}