{
  "type": "Feature",
  "properties": {
    "iso:country":"BE",
    "sg:address":"Dorpsstraat 48",
    "sg:city":"Stekene",
    "sg:classifiers":[
        {
            "category":"Personal",
            "subcategory":"Beauty Salon",
            "type":"Services"
        }
    ],
    "sg:phone":"+32 3 779 73 26",
    "sg:postcode":"9190",
    "sg:province":"Oost-Vlaanderen",
    "sg:tags":[
        "de",
        "coiffure"
    ],
    "wof:name":"Freddy Dullaert",
    "wof:placetype":"venue"
},
  "geometry": {"coordinates":[4.039249897,51.2047576904],"type":"Point"}
}