{
  "type": "Feature",
  "properties": {
    "addr:full":"Spinnerijkaai 37 Kortrijk West-Vlaanderen 8500",
    "addr:housenumber":"37",
    "addr:postcode":"8500",
    "addr:street":"Spinnerijkaai",
    "iso:country":"BE",
    "sg:address":"Spinnerijkaai 37",
    "sg:city":"Kortrijk",
    "sg:classifiers":[
        {
            "category":"Building & Trades",
            "subcategory":"Pest Control",
            "type":"Services"
        }
    ],
    "sg:phone":"+32 475 45 87 02",
    "sg:postcode":"8500",
    "sg:province":"West-Vlaanderen",
    "sg:tags":[
        "painting",
        "contractor"
    ],
    "wof:name":"Action Paint",
    "wof:placetype":"venue"
},
  "geometry": {"coordinates":[3.2813770771,50.8323478699],"type":"Point"}
}