{
  "type": "Feature",
  "properties": {
    "addr:full":"Mottaart 20 Herselt Antwerpen 2230",
    "addr:housenumber":"20",
    "addr:postcode":"2230",
    "addr:street":"Mottaart",
    "iso:country":"BE",
    "sg:address":"Mottaart 20",
    "sg:city":"Herselt",
    "sg:classifiers":[
        {
            "category":"Professional",
            "subcategory":"Computer Services",
            "type":"Services"
        }
    ],
    "sg:phone":"+32 14 54 59 74",
    "sg:postcode":"2230",
    "sg:province":"Antwerpen",
    "sg:tags":[
        "-",
        "processing",
        "data",
        "software"
    ],
    "wof:name":"Dianamic Vzw",
    "wof:placetype":"venue"
},
  "geometry": {"coordinates":[4.8908071518,51.0412902832],"type":"Point"}
}