{
  "type": "Feature",
  "properties": {
    "addr:full":"Deinsesteenweg 19 Tielt West-Vlaanderen 8700",
    "addr:housenumber":"19",
    "addr:postcode":"8700",
    "addr:street":"Deinsesteenweg",
    "iso:country":"BE",
    "sg:address":"Deinsesteenweg 19",
    "sg:city":"Tielt",
    "sg:orig_category":"Eleveurs and marchands de porcs",
    "sg:phone":"+32 51 40 10 77",
    "sg:postcode":"8700",
    "sg:province":"West-Vlaanderen",
    "wof:name":"Andre Voet",
    "wof:placetype":"venue"
},
  "geometry": {"coordinates":[3.3553850651,50.9967460632],"type":"Point"}
}