{
  "type": "Feature",
  "properties": {
    "addr:full":"Steenberg 26 Ninove Oost-Vlaanderen 9401",
    "addr:housenumber":"26",
    "addr:postcode":"9401",
    "addr:street":"Steenberg",
    "iso:country":"BE",
    "sg:address":"Steenberg 26",
    "sg:city":"Ninove",
    "sg:orig_category":"R\u00e9paration and restauration de meubles",
    "sg:phone":"+32 54 33 51 85",
    "sg:postcode":"9401",
    "sg:province":"Oost-Vlaanderen",
    "wof:name":"Fa. Van Grimbergen",
    "wof:placetype":"venue"
},
  "geometry": {"coordinates":[4.0016198158,50.8126487732],"type":"Point"}
}