{
  "type": "Feature",
  "properties": {
    "iso:country":"BE",
    "sg:address":"Ommegangstraat 88",
    "sg:city":"Izegem",
    "sg:classifiers":[
        {
            "category":"Building & Trades",
            "subcategory":"Construction",
            "type":"Services"
        }
    ],
    "sg:phone":"+32 477 42 62 06",
    "sg:postcode":"8870",
    "sg:province":"West-Vlaanderen",
    "sg:tags":[
        "installation",
        "-",
        "central",
        "heating"
    ],
    "wof:name":"Baekelandt-corneillie Bvba",
    "wof:placetype":"venue"
},
  "geometry": {"coordinates":[3.2088780403,50.9163360596],"type":"Point"}
}