{
  "type": "Feature",
  "properties": {
    "iso:country":"BE",
    "sg:address":"Rue De La Station 12a",
    "sg:city":"Hamoir",
    "sg:classifiers":[
        {
            "category":"Bakery",
            "type":"Food & Drink"
        }
    ],
    "sg:phone":"+32 86 38 85 32",
    "sg:postcode":"4180",
    "sg:province":"Li\u00e8ge",
    "sg:tags":[
        "confectioner",
        "baker"
    ],
    "wof:name":"Debraz R & Fils Sprl",
    "wof:placetype":"venue"
},
  "geometry": {"coordinates":[5.5341601372,50.4280090332],"type":"Point"}
}