{
  "type": "Feature",
  "properties": {
    "addr:full":"Luikerstraat 8 Sint-truiden Limburg 3800",
    "addr:housenumber":"8",
    "addr:postcode":"3800",
    "addr:street":"Luikerstraat",
    "iso:country":"BE",
    "sg:address":"Luikerstraat 8",
    "sg:city":"Sint-truiden",
    "sg:orig_category":"Pain, p\u00e2tisseries and confiseries",
    "sg:phone":"+32 11 68 27 40",
    "sg:postcode":"3800",
    "sg:province":"Limburg",
    "wof:name":"Bakkerij Verboven",
    "wof:placetype":"venue"
},
  "geometry": {"coordinates":[5.1873269081,50.8150558472],"type":"Point"}
}