{
  "type": "Feature",
  "properties": {
    "addr:full":"Chemin Du Hallage 13 Ittre Brabant Wallon 1460",
    "addr:housenumber":"13;1460",
    "addr:street":"Chemin Du Hallage",
    "iso:country":"BE",
    "sg:address":"Chemin Du Hallage 13",
    "sg:city":"Ittre",
    "sg:classifiers":[
        {
            "category":"Home & Garden",
            "subcategory":"Mobile Homes",
            "type":"Retail Goods"
        }
    ],
    "sg:phone":"+32 67 64 80 80",
    "sg:postcode":"1460",
    "sg:province":"Brabant Wallon",
    "sg:tags":[
        "tent",
        "marquee"
    ],
    "wof:name":"Pierre Boon International S.p.r.l.",
    "wof:placetype":"venue"
},
  "geometry": {"coordinates":[4.2297677994,50.6259994507],"type":"Point"}
}