{
  "type": "Feature",
  "properties": {
    "iso:country":"BE",
    "sg:address":"Rue Des Fusill\u00c9s 6",
    "sg:city":"Mont-de-l'enclus",
    "sg:orig_category":"Eleveurs de bovins",
    "sg:phone":"+32 69 45 43 42",
    "sg:postcode":"7750",
    "sg:province":"Hainaut",
    "wof:name":"Michel Hernould",
    "wof:placetype":"venue"
},
  "geometry": {"coordinates":[5.9272909164,50.328918457],"type":"Point"}
}