{
  "type": "Feature",
  "properties": {
    "addr:full":"Neerpoortenstraat 116 Huldenberg Vlaams-Brabant 3040",
    "addr:housenumber":"116",
    "addr:postcode":"3040",
    "addr:street":"Neerpoortenstraat",
    "iso:country":"BE",
    "sg:address":"Neerpoortenstraat 116",
    "sg:city":"Huldenberg",
    "sg:orig_category":"Afbraak- and draineerwerken Bouwmaterialen Gh Hout and afgeleiden Gh Houtbewerking and -behandeling ",
    "sg:phone":"+32 16 47 17 27",
    "sg:postcode":"3040",
    "sg:province":"Vlaams-Brabant",
    "wof:name":"Olislaegers Roland",
    "wof:placetype":"venue"
},
  "geometry": {"coordinates":[4.6064858437,50.7641868591],"type":"Point"}
}