{
  "type": "Feature",
  "properties": {
    "iso:country":"BE",
    "sg:address":"Gijmelsesteenweg 339",
    "sg:city":"Aarschot",
    "sg:classifiers":[
        {
            "category":"Food & Beverages",
            "subcategory":"Groceries & Convenience Stores",
            "type":"Retail Goods"
        }
    ],
    "sg:phone":"+32 16 56 83 21",
    "sg:postcode":"3200",
    "sg:province":"Vlaams-Brabant",
    "sg:tags":[
        "grocer"
    ],
    "wof:name":"Vanhelmont A",
    "wof:placetype":"venue"
},
  "geometry": {"coordinates":[4.8495268822,50.9992446899],"type":"Point"}
}