{
  "type": "Feature",
  "properties": {
    "iso:country":"BE",
    "sg:address":"Rue Du Moulin 11",
    "sg:city":"Li\u00e8ge 1 (bressoux)",
    "sg:classifiers":[
        {
            "category":"Bakery",
            "type":"Food & Drink"
        }
    ],
    "sg:phone":"+32 4 343 72 95",
    "sg:postcode":"4020",
    "sg:province":"Li\u00e8ge",
    "sg:tags":[
        "confectioner",
        "baker"
    ],
    "wof:name":"Gaspari S",
    "wof:placetype":"venue"
},
  "geometry": {"coordinates":[5.5938878059,50.6407165527],"type":"Point"}
}