{
  "type": "Feature",
  "properties": {
    "addr:full":"Doornappelstraat 5 Meeuwen-gruitrode Limburg 3670",
    "addr:housenumber":"5",
    "addr:postcode":"3670",
    "addr:street":"Doornappelstraat",
    "iso:country":"BE",
    "sg:address":"Doornappelstraat 5",
    "sg:city":"Meeuwen-gruitrode",
    "sg:orig_category":"Herstellingen and onderhoud van auto's",
    "sg:phone":"+32 11 79 19 28",
    "sg:postcode":"3670",
    "sg:province":"Limburg",
    "wof:name":"Ren\u00c9 Blockken",
    "wof:placetype":"venue"
},
  "geometry": {"coordinates":[5.5203242302,51.1040534973],"type":"Point"}
}