{
  "type": "Feature",
  "properties": {
    "addr:full":"Rue De La Villa Romaine 27 Houffalize (nadrin) Luxembourg 6660",
    "addr:housenumber":"27",
    "addr:postcode":"6660",
    "addr:street":"Rue De La Villa Romaine",
    "iso:country":"BE",
    "sg:address":"Rue De La Villa Romaine 27",
    "sg:city":"Houffalize (nadrin)",
    "sg:classifiers":[
        {
            "category":"Retail",
            "subcategory":"Veterinary Services",
            "type":"Services"
        }
    ],
    "sg:phone":"+32 84 44 40 90",
    "sg:postcode":"6660",
    "sg:province":"Luxembourg",
    "sg:tags":[
        "veterinarian"
    ],
    "wof:name":"Thys B",
    "wof:placetype":"venue"
},
  "geometry": {"coordinates":[5.6793789864,50.1625366211],"type":"Point"}
}