{
  "type": "Feature",
  "properties": {
    "iso:country":"BE",
    "sg:address":"Rue Colonel Van Gele 119",
    "sg:city":"Bruxelles (etterbeek)",
    "sg:classifiers":[
        {
            "category":"Communications",
            "type":"Services"
        }
    ],
    "sg:phone":"+32 2 736 30 13",
    "sg:postcode":"1040",
    "sg:province":"Bruxelles-Capitale",
    "sg:tags":[
        "translator"
    ],
    "wof:name":"Colin P",
    "wof:placetype":"venue"
},
  "geometry": {"coordinates":[4.3925890923,50.834022522],"type":"Point"}
}