{
  "type": "Feature",
  "properties": {
    "iso:country":"BE",
    "sg:address":"Zuidschotestraat 9",
    "sg:city":"Lo-reninge",
    "sg:orig_category":"Elektrische installaties voor woningen Herstelling aan huis van huishoudartikelen Industri\u00eble elektr",
    "sg:phone":"+32 57 40 03 02",
    "sg:postcode":"8647",
    "sg:province":"West-Vlaanderen",
    "wof:name":"Dirk Huyghe",
    "wof:placetype":"venue"
},
  "geometry": {"coordinates":[2.7917299271,50.9431724548],"type":"Point"}
}