{
  "type": "Feature",
  "properties": {
    "addr:full":"Kerkeveldstraat 68 Brussel/bruxelles Bruxelles-Capitale 1020",
    "addr:housenumber":"68",
    "addr:postcode":"1020",
    "addr:street":"Kerkeveldstraat;/",
    "iso:country":"BE",
    "sg:address":"Kerkeveldstraat 68",
    "sg:city":"Brussel/bruxelles",
    "sg:orig_category":"Dranken",
    "sg:phone":"+32 2 426 15 24",
    "sg:postcode":"1020",
    "sg:province":"Bruxelles-Capitale",
    "wof:name":"Brasserie St.remi",
    "wof:placetype":"venue"
},
  "geometry": {"coordinates":[4.3538460732,50.8748588562],"type":"Point"}
}