{
  "type": "Feature",
  "properties": {
    "addr:full":"Aarselestraat 40 Tielt West-Vlaanderen 8700",
    "addr:housenumber":"40",
    "addr:postcode":"8700",
    "addr:street":"Aarselestraat",
    "iso:country":"BE",
    "sg:address":"Aarselestraat 40",
    "sg:city":"Tielt",
    "sg:orig_category":"Banken and kredietinstellingen",
    "sg:phone":"+32 51 63 33 68",
    "sg:postcode":"8700",
    "sg:province":"West-Vlaanderen",
    "wof:name":"Bbl",
    "wof:placetype":"venue"
},
  "geometry": {"coordinates":[3.4212350845,50.993183136],"type":"Point"}
}