{
  "type": "Feature",
  "properties": {
    "addr:full":"Stuivenbergbaan 235 Mechelen Antwerpen 2800",
    "addr:housenumber":"235",
    "addr:postcode":"2800",
    "addr:street":"Stuivenbergbaan",
    "iso:country":"BE",
    "sg:address":"Stuivenbergbaan 235",
    "sg:city":"Mechelen",
    "sg:classifiers":[
        {
            "category":"Shopping",
            "subcategory":"Florist",
            "type":"Retail Goods"
        }
    ],
    "sg:phone":"+32 15 42 36 83",
    "sg:postcode":"2800",
    "sg:province":"Antwerpen",
    "wof:name":"Diane",
    "wof:placetype":"venue"
},
  "geometry": {"coordinates":[4.4389538765,51.028427124],"type":"Point"}
}