{
  "type": "Feature",
  "properties": {
    "iso:country":"BE",
    "sg:address":"Langestraat 99",
    "sg:city":"Aarschot",
    "sg:orig_category":"Instituts de beaut\u00e9",
    "sg:phone":"+32 16 50 22 42",
    "sg:postcode":"3202",
    "sg:province":"Vlaams-Brabant",
    "wof:name":"R. Esthetiek",
    "wof:placetype":"venue"
},
  "geometry": {"coordinates":[4.9038820267,50.9831504822],"type":"Point"}
}