{
  "type": "Feature",
  "properties": {
    "addr:full":"Kokkelbeekplein 113 Sint-niklaas Oost-Vlaanderen 9100",
    "addr:housenumber":"113",
    "addr:postcode":"9100",
    "iso:country":"BE",
    "sg:address":"Kokkelbeekplein 113",
    "sg:city":"Sint-niklaas",
    "sg:classifiers":[
        {
            "category":"Personal",
            "subcategory":"Beauty Salon",
            "type":"Services"
        }
    ],
    "sg:phone":"+32 3 776 17 59",
    "sg:postcode":"9100",
    "sg:province":"Oost-Vlaanderen",
    "sg:tags":[
        "lady",
        "-",
        "hairdressing"
    ],
    "wof:name":"Carthier",
    "wof:placetype":"venue"
},
  "geometry": {"coordinates":[4.1447610855,51.1608085632],"type":"Point"}
}