{
  "type": "Feature",
  "properties": {
    "addr:full":"Rue Georges C\u00c9sar 12 Waremme Li\u00e8ge 4300",
    "addr:housenumber":"12",
    "addr:postcode":"4300",
    "addr:street":"Rue Georges Ce\u0301Sar",
    "iso:country":"BE",
    "sg:address":"Rue Georges C\u00c9sar 12",
    "sg:city":"Waremme",
    "sg:orig_category":"Maatkleding Fab",
    "sg:phone":"+32 19 32 45 88",
    "sg:postcode":"4300",
    "sg:province":"Li\u00e8ge",
    "wof:name":"Claudine Douette",
    "wof:placetype":"venue"
},
  "geometry": {"coordinates":[5.2270150185,50.6770973206],"type":"Point"}
}