{
  "type": "Feature",
  "properties": {
    "iso:country":"BE",
    "sg:address":"Sint-bernardusstraat 34",
    "sg:city":"Lier",
    "sg:orig_category":"Boissons",
    "sg:phone":"+32 3 480 51 55",
    "sg:postcode":"2500",
    "sg:province":"Antwerpen",
    "wof:name":"Fa. Bogaerts",
    "wof:placetype":"venue"
},
  "geometry": {"coordinates":[4.5751838684,51.1473045349],"type":"Point"}
}