{
  "type": "Feature",
  "properties": {
    "addr:full":"Rue Des Ecoles 2bb Tournai Hainaut 7532",
    "addr:housenumber":"2bb",
    "addr:postcode":"7532",
    "addr:street":"Rue Des Ecoles",
    "iso:country":"BE",
    "sg:address":"Rue Des Ecoles 2bb",
    "sg:city":"Tournai",
    "sg:orig_category":"Epiceries",
    "sg:phone":"+32 69 54 73 10",
    "sg:postcode":"7532",
    "sg:province":"Hainaut",
    "wof:name":"Francis Fontaine",
    "wof:placetype":"venue"
},
  "geometry": {"coordinates":[3.3913080692,50.6240119934],"type":"Point"}
}