{
  "type": "Feature",
  "properties": {
    "addr:full":"Grand Rue 70 Mons Hainaut 7000",
    "addr:housenumber":"70",
    "addr:postcode":"7000",
    "addr:street":"Grand Rue;Hainaut",
    "iso:country":"BE",
    "sg:address":"Grand Rue 70",
    "sg:city":"Mons",
    "sg:classifiers":[
        {
            "category":"Real Estate",
            "subcategory":"Real Estate Services",
            "type":"Services"
        }
    ],
    "sg:phone":"+32 65 33 92 01",
    "sg:postcode":"7000",
    "sg:province":"Hainaut",
    "wof:name":"Immo Theodorou",
    "wof:placetype":"venue"
},
  "geometry": {"coordinates":[3.9492108822,50.4505004883],"type":"Point"}
}