{
  "type": "Feature",
  "properties": {
    "iso:country":"BE",
    "sg:address":"Rue De Lonz\u00c9e 129",
    "sg:city":"Gembloux",
    "sg:orig_category":"Woningbouw",
    "sg:phone":"+32 81 61 50 86",
    "sg:postcode":"5030",
    "sg:province":"Namur",
    "wof:name":"Dumont J",
    "wof:placetype":"venue"
},
  "geometry": {"coordinates":[4.7348327637,50.5562973022],"type":"Point"}
}