{
  "type": "Feature",
  "properties": {
    "addr:full":"Avenue Wolvendael 1 Box 16 Bruxelles (uccle) Bruxelles-Capitale 1180",
    "addr:housenumber":"1 box 16",
    "addr:postcode":"1180",
    "addr:street":"Avenue Wolvendael",
    "iso:country":"BE",
    "sg:address":"Avenue Wolvendael 1 Box 16",
    "sg:city":"Bruxelles (uccle)",
    "sg:classifiers":[
        {
            "category":"Personal",
            "subcategory":"Beauty Salon",
            "type":"Services"
        }
    ],
    "sg:phone":"+32 2 345 54 13",
    "sg:postcode":"1180",
    "sg:province":"Bruxelles-Capitale",
    "wof:name":"Vannier G",
    "wof:placetype":"venue"
},
  "geometry": {"coordinates":[4.3406910896,50.8010101318],"type":"Point"}
}