{
  "type": "Feature",
  "properties": {
    "addr:full":"Hippocrateslaan 7 Kraainem Vlaams-Brabant 1950",
    "addr:housenumber":"7",
    "addr:postcode":"1950",
    "addr:street":"Hippocrateslaan",
    "iso:country":"BE",
    "sg:address":"Hippocrateslaan 7",
    "sg:city":"Kraainem",
    "sg:orig_category":"Diverse bedrijfsbeheeradviesbureaus",
    "sg:phone":"+32 2 721 59 09",
    "sg:postcode":"1950",
    "sg:province":"Vlaams-Brabant",
    "wof:name":"Van Triel",
    "wof:placetype":"venue"
},
  "geometry": {"coordinates":[4.4612870216,50.8519973755],"type":"Point"}
}