{
  "type": "Feature",
  "properties": {
    "iso:country":"BE",
    "sg:address":"Rue Fontaine De Spa 14",
    "sg:city":"Morlanwelz (morlanwelz-mariemont)",
    "sg:classifiers":[
        {
            "category":"Building & Trades",
            "subcategory":"Landscaping Services",
            "type":"Services"
        }
    ],
    "sg:phone":"+32 64 84 79 10",
    "sg:postcode":"7140",
    "sg:province":"Hainaut",
    "sg:tags":[
        "access",
        "pond",
        "laying-out",
        "-"
    ],
    "wof:name":"Aquaphil",
    "wof:placetype":"venue"
},
  "geometry": {"coordinates":[4.2200689316,50.4643592834],"type":"Point"}
}