{
  "type": "Feature",
  "properties": {
    "addr:full":"Sint-lambertusstraat 116 Sint-lambrechts-woluwe/woluwe-saint-lambert Bruxelles-Capitale 1200",
    "addr:housenumber":"116",
    "addr:postcode":"1200",
    "addr:street":"Sint-Lambertusstraat",
    "iso:country":"BE",
    "sg:address":"Sint-lambertusstraat 116",
    "sg:city":"Sint-lambrechts-woluwe/woluwe-saint-lambert",
    "sg:orig_category":"Boekhandels",
    "sg:phone":"+32 2 762 66 69",
    "sg:postcode":"1200",
    "sg:province":"Bruxelles-Capitale",
    "wof:name":"Librairie Le Rat Conteur",
    "wof:placetype":"venue"
},
  "geometry": {"coordinates":[4.4358057976,50.8438148499],"type":"Point"}
}