{
  "type": "Feature",
  "properties": {
    "iso:country":"BE",
    "sg:address":"Monceau 10",
    "sg:city":"Blegny",
    "sg:orig_category":"Rundveehouders",
    "sg:phone":"+32 4 387 41 37",
    "sg:postcode":"4670",
    "sg:province":"Li\u00e8ge",
    "wof:name":"Pierre Cloes",
    "wof:placetype":"venue"
},
  "geometry": {"coordinates":[5.724919796,50.6725769043],"type":"Point"}
}