{
  "type": "Feature",
  "properties": {
    "addr:full":"Rue De La Briqueterie 24 Gerpinnes (gougnies) Hainaut 6280",
    "addr:housenumber":"24",
    "addr:postcode":"6280",
    "addr:street":"Rue De La Briqueterie",
    "iso:country":"BE",
    "sg:address":"Rue De La Briqueterie 24",
    "sg:city":"Gerpinnes (gougnies)",
    "sg:classifiers":[
        {
            "category":"Health Services",
            "subcategory":"Health Practitioner",
            "type":"Services"
        }
    ],
    "sg:phone":"+32 71 50 42 36",
    "sg:postcode":"6280",
    "sg:province":"Hainaut",
    "sg:tags":[
        "physiotherapist"
    ],
    "wof:name":"Giot V",
    "wof:placetype":"venue"
},
  "geometry": {"coordinates":[4.5684928894,50.3588218689],"type":"Point"}
}