{
  "type": "Feature",
  "properties": {
    "iso:country":"BE",
    "sg:address":"Rue Guillaume Lekeu 2",
    "sg:city":"Verviers",
    "sg:orig_category":"Drukkerijen and copyshops Kleding, schoenen and accessoires Gh",
    "sg:phone":"+32 87 23 27 27",
    "sg:postcode":"4800",
    "sg:province":"Li\u00e8ge",
    "wof:name":"I.t.s. Marot",
    "wof:placetype":"venue"
},
  "geometry": {"coordinates":[5.8594508171,50.5917663574],"type":"Point"}
}