{
  "type": "Feature",
  "properties": {
    "iso:country":"BE",
    "sg:address":"Vogelheide 26",
    "sg:city":"Zwijnaarde",
    "sg:orig_category":"Avocats and conseillers juridiques. Balie van Gent. Avocats and conseillers juridiques",
    "sg:phone":"+32 9 221 53 44",
    "sg:postcode":"9052",
    "sg:province":"Oost-Vlaanderen",
    "wof:name":"Van Quickenborne Marc",
    "wof:placetype":"venue"
},
  "geometry": {"coordinates":[3.6800639629,51.000415802],"type":"Point"}
}