{
  "type": "Feature",
  "properties": {
    "addr:full":"Rue Des Renards 17 Brussel/bruxelles Bruxelles-Capitale 1000",
    "addr:housenumber":"17",
    "addr:postcode":"1000",
    "addr:street":"Rue Des Renards;/",
    "iso:country":"BE",
    "sg:address":"Rue Des Renards 17",
    "sg:city":"Brussel/bruxelles",
    "sg:orig_category":"Forge, Moulage and Profilage des M\u00e9taux",
    "sg:phone":"+32 475 61 01 97",
    "sg:postcode":"1000",
    "sg:province":"Bruxelles-Capitale",
    "wof:name":"Le Dimanche Matin",
    "wof:placetype":"venue"
},
  "geometry": {"coordinates":[4.3476161957,50.8368835449],"type":"Point"}
}