{
  "type": "Feature",
  "properties": {
    "iso:country":"BE",
    "sg:address":"Vermeulenstraat 42",
    "sg:city":"Lokeren",
    "sg:orig_category":"M\u00e9decines alternatives",
    "sg:phone":"+32 9 349 63 83",
    "sg:postcode":"9160",
    "sg:province":"Oost-Vlaanderen",
    "wof:name":"Anja Troubleyn",
    "wof:placetype":"venue"
},
  "geometry": {"coordinates":[3.9955461025,51.0999565125],"type":"Point"}
}