{
  "type": "Feature",
  "properties": {
    "iso:country":"BE",
    "sg:address":"Sint-ermelindisstraat 11",
    "sg:city":"Hoegaarden (honsem)",
    "sg:classifiers":[
        {
            "category":"Home & Garden",
            "subcategory":"Garden Supply",
            "type":"Retail Goods"
        }
    ],
    "sg:phone":"+32 16 76 77 44",
    "sg:postcode":"3320",
    "sg:province":"Vlaams-Brabant",
    "wof:name":"Natuurlijk",
    "wof:placetype":"venue"
},
  "geometry": {"coordinates":[4.837928772,50.7883682251],"type":"Point"}
}