{
  "type": "Feature",
  "properties": {
    "addr:full":"J. Creytensstraat 38 Beernem (oedelem) West-Vlaanderen 8730",
    "addr:housenumber":"38",
    "addr:postcode":"8730",
    "addr:street":"Creytensstraat",
    "iso:country":"BE",
    "sg:address":"J. Creytensstraat 38",
    "sg:city":"Beernem (oedelem)",
    "sg:classifiers":[
        {
            "category":"Building & Trades",
            "subcategory":"Pest Control",
            "type":"Services"
        }
    ],
    "sg:phone":"+32 50 78 93 04",
    "sg:postcode":"8730",
    "sg:province":"West-Vlaanderen",
    "sg:tags":[
        "painting",
        "contractor"
    ],
    "wof:name":"Detra Paint",
    "wof:placetype":"venue"
},
  "geometry": {"coordinates":[3.335119009,51.1700210571],"type":"Point"}
}