{
  "type": "Feature",
  "properties": {
    "iso:country":"BE",
    "sg:address":"Dennenlaan 20",
    "sg:city":"Steenokkerzeel",
    "sg:classifiers":[
        {
            "category":"Professional",
            "subcategory":"Art Services",
            "type":"Services"
        }
    ],
    "sg:phone":"+32 486 70 63 43",
    "sg:postcode":"1820",
    "sg:province":"Vlaams-Brabant",
    "sg:tags":[
        "graphic",
        "designer"
    ],
    "wof:name":"Patry F",
    "wof:placetype":"venue"
},
  "geometry": {"coordinates":[4.5117897987,50.9259567261],"type":"Point"}
}