{
  "type": "Feature",
  "properties": {
    "addr:full":"Arthur Maesstraat 75 Brussel Bruxelles-Capitale 1130",
    "addr:housenumber":"75",
    "addr:postcode":"1130",
    "addr:street":"Arthur Maesstraat",
    "iso:country":"BE",
    "sg:address":"Arthur Maesstraat 75",
    "sg:city":"Brussel",
    "sg:classifiers":[
        {
            "category":"Building & Trades",
            "subcategory":"Electrical",
            "type":"Services"
        }
    ],
    "sg:phone":"+32 2 705 02 62",
    "sg:postcode":"1130",
    "sg:province":"Bruxelles-Capitale",
    "sg:tags":[
        "electronic",
        "lighting",
        "equipment"
    ],
    "wof:name":"Technitole Nv",
    "wof:placetype":"venue"
},
  "geometry": {"coordinates":[4.372344017,50.8307151794],"type":"Point"}
}