{
  "type": "Feature",
  "properties": {
    "addr:full":"Gyselstraat 23 Sint-niklaas Oost-Vlaanderen 9100",
    "addr:housenumber":"23",
    "addr:postcode":"9100",
    "addr:street":"Gyselstraat",
    "iso:country":"BE",
    "sg:address":"Gyselstraat 23",
    "sg:city":"Sint-niklaas",
    "sg:orig_category":"Artistes ind\u00e9pendants",
    "sg:phone":"+32 3 776 38 16",
    "sg:postcode":"9100",
    "sg:province":"Oost-Vlaanderen",
    "wof:name":"Grumiau",
    "wof:placetype":"venue"
},
  "geometry": {"coordinates":[4.1773319244,51.1944961548],"type":"Point"}
}