{
  "type": "Feature",
  "properties": {
    "iso:country":"BE",
    "sg:address":"Romboutstraat 28",
    "sg:city":"Bilzen",
    "sg:classifiers":[
        {
            "category":"Real Estate",
            "subcategory":"Architect",
            "type":"Services"
        }
    ],
    "sg:phone":"+32 89 50 10 75",
    "sg:postcode":"3740",
    "sg:province":"Limburg",
    "wof:name":"Menten Karla",
    "wof:placetype":"venue"
},
  "geometry": {"coordinates":[5.5144639015,50.8701705933],"type":"Point"}
}