{
  "type": "Feature",
  "properties": {
    "iso:country":"BE",
    "sg:address":"Oude Tramweg 37",
    "sg:city":"Wevelgem",
    "sg:orig_category":"Bouwmaterialen Gh",
    "sg:phone":"+32 56 41 86 61",
    "sg:postcode":"8560",
    "sg:province":"West-Vlaanderen",
    "wof:name":"Gadeyne",
    "wof:placetype":"venue"
},
  "geometry": {"coordinates":[3.1605610847,50.838722229],"type":"Point"}
}