{
  "type": "Feature",
  "properties": {
    "iso:country":"BE",
    "sg:address":"Houppestraat 97",
    "sg:city":"Vloesberg/flobecq",
    "sg:classifiers":[
        {
            "category":"Insurance",
            "subcategory":"Insurance Agent",
            "type":"Services"
        }
    ],
    "sg:phone":"+32 68 44 72 85",
    "sg:postcode":"7880",
    "sg:province":"Hainaut",
    "sg:tags":[
        "verzekeringsmakelaars",
        "expert"
    ],
    "wof:name":"T\u00b4sas",
    "wof:placetype":"venue"
},
  "geometry": {"coordinates":[3.7384300232,50.7368011475],"type":"Point"}
}