{
  "type": "Feature",
  "properties": {
    "iso:country":"BE",
    "sg:address":"Rue Du Champ Saint-nicolas 16",
    "sg:city":"Genappe (bousval)",
    "sg:classifiers":[
        {
            "category":"Building & Trades",
            "subcategory":"Landscaping Services",
            "type":"Services"
        }
    ],
    "sg:phone":"+32 10 61 12 78",
    "sg:postcode":"1470",
    "sg:province":"Brabant Wallon",
    "sg:tags":[
        "gardening",
        "garden",
        "maintenance"
    ],
    "wof:name":"Nolf Gardens Service",
    "wof:placetype":"venue"
},
  "geometry": {"coordinates":[4.5255317688,50.6430244446],"type":"Point"}
}