{
  "type": "Feature",
  "properties": {
    "addr:full":"Nieuwstraat 33bb Westerlo Antwerpen 2260",
    "addr:housenumber":"33bb",
    "addr:postcode":"2260",
    "addr:street":"Nieuwstraat",
    "iso:country":"BE",
    "sg:address":"Nieuwstraat 33bb",
    "sg:city":"Westerlo",
    "sg:orig_category":"Blanchisseries and teintureries",
    "sg:phone":"+32 14 54 88 65",
    "sg:postcode":"2260",
    "sg:province":"Antwerpen",
    "wof:name":"Prima",
    "wof:placetype":"venue"
},
  "geometry": {"coordinates":[4.9142308235,51.0860977173],"type":"Point"}
}