{
  "type": "Feature",
  "properties": {
    "iso:country":"BE",
    "sg:address":"Rue Colonel Bourg 1",
    "sg:city":"Profondeville",
    "sg:classifiers":[
        {
            "category":"Shopping",
            "subcategory":"Clothing, Apparel, & Fashions",
            "type":"Retail Goods"
        }
    ],
    "sg:phone":"+32 81 41 37 85",
    "sg:postcode":"5170",
    "sg:province":"Namur",
    "sg:tags":[
        "lady",
        "clothing",
        "-"
    ],
    "wof:name":"Verdicci",
    "wof:placetype":"venue"
},
  "geometry": {"coordinates":[4.8695111275,50.3779144287],"type":"Point"}
}