{
  "type": "Feature",
  "properties": {
    "addr:full":"Avenue Adolphe Buyl 196b5 Elsene/ixelles Bruxelles-Capitale 1050",
    "addr:housenumber":"196b5",
    "addr:postcode":"1050",
    "addr:street":"Avenue Adolphe Buyl",
    "iso:country":"BE",
    "sg:address":"Avenue Adolphe Buyl 196b5",
    "sg:city":"Elsene/ixelles",
    "sg:orig_category":"Artistes ind\u00e9pendants. Animations diverses",
    "sg:phone":"+32 2 640 87 66",
    "sg:postcode":"1050",
    "sg:province":"Bruxelles-Capitale",
    "wof:name":"C. Acmen",
    "wof:placetype":"venue"
},
  "geometry": {"coordinates":[4.3860268593,50.8116188049],"type":"Point"}
}