{
  "type": "Feature",
  "properties": {
    "iso:country":"BE",
    "sg:address":"Rue De La Grande Triperie 3",
    "sg:city":"Mons",
    "sg:classifiers":[
        {
            "category":"Professional",
            "subcategory":"Lawyer & Legal Services",
            "type":"Services"
        }
    ],
    "sg:phone":"+32 65 33 98 09",
    "sg:postcode":"7000",
    "sg:province":"Hainaut",
    "wof:name":"Belle G",
    "wof:placetype":"venue"
},
  "geometry": {"coordinates":[3.9521260262,50.4517745972],"type":"Point"}
}