{
  "type": "Feature",
  "properties": {
    "addr:full":"Cauwerburg 115ba Temse Oost-Vlaanderen 9140",
    "addr:postcode":"9140",
    "addr:street":"Oost-Vlaanderen",
    "iso:country":"BE",
    "sg:address":"Cauwerburg 115ba",
    "sg:city":"Temse",
    "sg:orig_category":"Articles de camping and de sport. V\u00e9hicules automobiles",
    "sg:phone":"+32 3 771 93 04",
    "sg:postcode":"9140",
    "sg:province":"Oost-Vlaanderen",
    "wof:name":"Marine Shine",
    "wof:placetype":"venue"
},
  "geometry": {"coordinates":[4.1951098442,51.1200180054],"type":"Point"}
}