{
  "type": "Feature",
  "properties": {
    "addr:full":"Rue De Courcelles 2e Charleroi (roux) Hainaut 6044",
    "addr:housenumber":"2e;6044",
    "addr:street":"Rue De Courcelles",
    "iso:country":"BE",
    "sg:address":"Rue De Courcelles 2e",
    "sg:city":"Charleroi (roux)",
    "sg:classifiers":[
        {
            "category":"Retail",
            "subcategory":"Auto Rental",
            "type":"Services"
        }
    ],
    "sg:phone":"+32 475 62 57 57",
    "sg:postcode":"6044",
    "sg:province":"Hainaut",
    "sg:tags":[
        "van",
        "hire",
        "-",
        "truck"
    ],
    "wof:name":"Fontenelle Ph",
    "wof:placetype":"venue"
},
  "geometry": {"coordinates":[4.3860769272,50.4403457642],"type":"Point"}
}