{
  "type": "Feature",
  "properties": {
    "addr:full":"Rue Des Ardennes 6 Braine-le-comte Hainaut 7090",
    "addr:housenumber":"6",
    "addr:postcode":"7090",
    "addr:street":"Rue Des Ardennes",
    "iso:country":"BE",
    "sg:address":"Rue Des Ardennes 6",
    "sg:city":"Braine-le-comte",
    "sg:orig_category":"Woningbouw",
    "sg:phone":"+32 67 56 10 54",
    "sg:postcode":"7090",
    "sg:province":"Hainaut",
    "wof:name":"Binnemans",
    "wof:placetype":"venue"
},
  "geometry": {"coordinates":[4.1851148605,50.6418418884],"type":"Point"}
}