{
  "type": "Feature",
  "properties": {
    "addr:full":"Vakebuurtstraat 278a Maldegem Oost-Vlaanderen 9990",
    "addr:housenumber":"278a",
    "addr:postcode":"9990",
    "addr:street":"Vakebuurtstraat",
    "iso:country":"BE",
    "sg:address":"Vakebuurtstraat 278a",
    "sg:city":"Maldegem",
    "sg:orig_category":"Computers and computerapparatuur Software ontwikkeling and ontwerp",
    "sg:phone":"+32 50 71 93 14",
    "sg:postcode":"9990",
    "sg:province":"Oost-Vlaanderen",
    "wof:name":"Procom Software-hardware",
    "wof:placetype":"venue"
},
  "geometry": {"coordinates":[3.4257509708,51.2250823975],"type":"Point"}
}