{
  "type": "Feature",
  "properties": {
    "iso:country":"BE",
    "sg:address":"Spoorwegstraat 104",
    "sg:city":"Menen",
    "sg:orig_category":"Boucheries",
    "sg:phone":"+32 56 41 19 66",
    "sg:postcode":"8930",
    "sg:province":"West-Vlaanderen",
    "wof:name":"Gerard Malfait",
    "wof:placetype":"venue"
},
  "geometry": {"coordinates":[3.1209149361,50.7961845398],"type":"Point"}
}