{
  "type": "Feature",
  "properties": {
    "addr:full":"Keerstraatje 13 Waarschoot Oost-Vlaanderen 9950",
    "addr:housenumber":"13",
    "addr:postcode":"9950",
    "addr:street":"Keerstraatje",
    "iso:country":"BE",
    "sg:address":"Keerstraatje 13",
    "sg:city":"Waarschoot",
    "sg:classifiers":[
        {
            "category":"Arena",
            "subcategory":"Sports Club",
            "type":"Entertainment"
        }
    ],
    "sg:phone":"+32 9 377 26 79",
    "sg:postcode":"9950",
    "sg:province":"Oost-Vlaanderen",
    "sg:tags":[
        "de"
    ],
    "wof:name":"T.c. Orbis",
    "wof:placetype":"venue"
},
  "geometry": {"coordinates":[3.5943799019,51.1532363892],"type":"Point"}
}