{
  "type": "Feature",
  "properties": {
    "addr:full":"Schoolstraat 3 Schilde Antwerpen 2970",
    "addr:housenumber":"3",
    "addr:postcode":"2970",
    "addr:street":"Schoolstraat",
    "iso:country":"BE",
    "sg:address":"Schoolstraat 3",
    "sg:city":"Schilde",
    "sg:orig_category":"Postkantoren Verzekeringsmakelaars and experts",
    "sg:phone":"+32 3 383 00 02",
    "sg:postcode":"2970",
    "sg:province":"Antwerpen",
    "wof:name":"De Post",
    "wof:placetype":"venue"
},
  "geometry": {"coordinates":[4.5795998573,51.2383575439],"type":"Point"}
}