{
  "type": "Feature",
  "properties": {
    "iso:country":"BE",
    "sg:address":"Tinnenpotstraat 20",
    "sg:city":"Gent",
    "sg:classifiers":[
        {
            "category":"Professional",
            "subcategory":"Advertising",
            "type":"Services"
        }
    ],
    "sg:phone":"+32 9 233 14 68",
    "sg:postcode":"9000",
    "sg:province":"Oost-Vlaanderen",
    "sg:tags":[
        "bill",
        "-",
        "posting"
    ],
    "wof:name":"Aanp Bvba",
    "wof:placetype":"venue"
},
  "geometry": {"coordinates":[3.7184770107,51.05834198],"type":"Point"}
}