{
  "type": "Feature",
  "properties": {
    "iso:country":"BE",
    "sg:address":"Borrensstraat 11",
    "sg:city":"Elsene/ixelles",
    "sg:orig_category":"Benzinestations and brandstoffen Herstellingen and onderhoud van auto's",
    "sg:phone":"+32 2 649 11 97",
    "sg:postcode":"1050",
    "sg:province":"Bruxelles-Capitale",
    "wof:name":"Garage G.p.",
    "wof:placetype":"venue"
},
  "geometry": {"coordinates":[4.376721859,50.8258247375],"type":"Point"}
}