{
  "type": "Feature",
  "properties": {
    "iso:country":"BE",
    "sg:address":"Chauss\u00e9e De France 10",
    "sg:city":"Neufch\u00e2teau",
    "sg:classifiers":[
        {
            "category":"Professional",
            "subcategory":"Lawyer & Legal Services",
            "type":"Services"
        }
    ],
    "sg:phone":"+32 61 27 75 89",
    "sg:postcode":"6840",
    "sg:province":"Luxembourg",
    "wof:name":"Laurent J-m",
    "wof:placetype":"venue"
},
  "geometry": {"coordinates":[5.4286909103,49.840259552],"type":"Point"}
}