{
  "type": "Feature",
  "properties": {
    "iso:country":"BE",
    "sg:address":"Muizendries 15",
    "sg:city":"Destelbergen",
    "sg:orig_category":"Studios photographiques",
    "sg:phone":"+32 9 230 98 58",
    "sg:postcode":"9070",
    "sg:province":"Oost-Vlaanderen",
    "wof:name":"Anne-sofie De Lembre",
    "wof:placetype":"venue"
},
  "geometry": {"coordinates":[3.8207879066,51.0311088562],"type":"Point"}
}