{
  "type": "Feature",
  "properties": {
    "iso:country":"BE",
    "sg:address":"Dorp-west 52",
    "sg:city":"Lochristi",
    "sg:classifiers":[
        {
            "category":"Health Services",
            "subcategory":"Nursing And Care Facility",
            "type":"Services"
        }
    ],
    "sg:phone":"+32 9 355 51 51",
    "sg:postcode":"9080",
    "sg:province":"Oost-Vlaanderen",
    "sg:tags":[
        "public"
    ],
    "wof:name":"Gemeentebestuur",
    "wof:placetype":"venue"
},
  "geometry": {"coordinates":[3.8305289745,51.0958023071],"type":"Point"}
}