{
  "type": "Feature",
  "properties": {
    "addr:full":"Hundelgemsesteenweg 457 Merelbeke Oost-Vlaanderen 9820",
    "addr:housenumber":"457",
    "addr:postcode":"9820",
    "addr:street":"Hundelgemsesteenweg",
    "iso:country":"BE",
    "sg:address":"Hundelgemsesteenweg 457",
    "sg:city":"Merelbeke",
    "sg:orig_category":"V\u00eatements sur mesure Fab",
    "sg:phone":"+32 9 230 78 54",
    "sg:postcode":"9820",
    "sg:province":"Oost-Vlaanderen",
    "wof:name":"Rene De Mulder",
    "wof:placetype":"venue"
},
  "geometry": {"coordinates":[3.7464931011,50.9891281128],"type":"Point"}
}