{
  "type": "Feature",
  "properties": {
    "addr:full":"Impulsstraat 15 Heist-op-den-berg Antwerpen 2220",
    "addr:housenumber":"15",
    "addr:postcode":"2220",
    "addr:street":"Impulsstraat",
    "iso:country":"BE",
    "sg:address":"Impulsstraat 15",
    "sg:city":"Heist-op-den-berg",
    "sg:classifiers":[
        {
            "category":"Professional",
            "subcategory":"Printing & Photocopies",
            "type":"Services"
        }
    ],
    "sg:phone":"+32 15 25 75 25",
    "sg:postcode":"2220",
    "sg:province":"Antwerpen",
    "sg:tags":[
        "-",
        "offset"
    ],
    "wof:name":"Scheers & Loos Graf.bedrijf",
    "wof:placetype":"venue"
},
  "geometry": {"coordinates":[4.7022137642,51.0642471313],"type":"Point"}
}