{
  "type": "Feature",
  "properties": {
    "addr:full":"Avenue Des Gen\u00cats 13 Court-saint-etienne Brabant Wallon 1490",
    "addr:housenumber":"13;1490",
    "addr:street":"Avenue Des Gene\u0302Ts",
    "iso:country":"BE",
    "sg:address":"Avenue Des Gen\u00cats 13",
    "sg:city":"Court-saint-etienne",
    "sg:orig_category":"Woningbouw",
    "sg:phone":"+32 10 61 35 75",
    "sg:postcode":"1490",
    "sg:province":"Brabant Wallon",
    "wof:name":"Vito De Luca",
    "wof:placetype":"venue"
},
  "geometry": {"coordinates":[4.5562667847,50.6512184143],"type":"Point"}
}