{
  "type": "Feature",
  "properties": {
    "addr:full":"Meensesteenweg 608b Roeselare West-Vlaanderen 8800",
    "addr:housenumber":"608b",
    "addr:postcode":"8800",
    "addr:street":"Meensesteenweg",
    "iso:country":"BE",
    "sg:address":"Meensesteenweg 608b",
    "sg:city":"Roeselare",
    "sg:classifiers":[
        {
            "category":"Food & Beverages",
            "subcategory":"Supermarket",
            "type":"Retail Goods"
        }
    ],
    "sg:phone":"+32 51 25 11 74",
    "sg:postcode":"8800",
    "sg:province":"West-Vlaanderen",
    "sg:tags":[
        "department",
        "store"
    ],
    "wof:name":"Intermarch\u00e9 Bvba",
    "wof:placetype":"venue"
},
  "geometry": {"coordinates":[3.1183900833,50.9258003235],"type":"Point"}
}