{
  "type": "Feature",
  "properties": {
    "iso:country":"BE",
    "sg:address":"Doelhaagstraat 50",
    "sg:city":"Rumst",
    "sg:orig_category":"Diverse bouwafwerking and reiniging",
    "sg:phone":"+32 3 844 76 79",
    "sg:postcode":"2840",
    "sg:province":"Antwerpen",
    "wof:name":"All-fix",
    "wof:placetype":"venue"
},
  "geometry": {"coordinates":[4.4288759232,51.0810165405],"type":"Point"}
}