{
  "type": "Feature",
  "properties": {
    "iso:country":"BE",
    "sg:address":"Grand-rue 1",
    "sg:city":"Moeskroen/mouscron",
    "sg:classifiers":[
        {
            "category":"Cafe",
            "type":"Food & Drink"
        }
    ],
    "sg:phone":"+32 56 34 22 36",
    "sg:postcode":"7700",
    "sg:province":"Hainaut",
    "sg:tags":[
        "caf\u00e9s"
    ],
    "wof:name":"Caf\u00c9 Le Bon Accueil",
    "wof:placetype":"venue"
},
  "geometry": {"coordinates":[3.2358698845,50.7423286438],"type":"Point"}
}