{
  "type": "Feature",
  "properties": {
    "iso:country":"BE",
    "sg:address":"Hendrik Consciencestraat 36b2",
    "sg:city":"Kortrijk",
    "sg:orig_category":"Pi\u00e8ces and accessoires de v\u00e9hicules automobiles Gr",
    "sg:phone":"+32 56 22 63 99",
    "sg:postcode":"8500",
    "sg:province":"West-Vlaanderen",
    "wof:name":"Car En Cycle Equipment",
    "wof:placetype":"venue"
},
  "geometry": {"coordinates":[3.2587931156,50.8261184692],"type":"Point"}
}