{
  "type": "Feature",
  "properties": {
    "iso:country":"BE",
    "sg:address":"Bree\u00ebrsteenweg 303",
    "sg:city":"Kinrooi",
    "sg:classifiers":[
        {
            "category":"Home & Garden",
            "subcategory":"Building Materials",
            "type":"Retail Goods"
        }
    ],
    "sg:phone":"+32 89 70 24 86",
    "sg:postcode":"3640",
    "sg:province":"Limburg",
    "sg:tags":[
        "window"
    ],
    "wof:name":"Christis",
    "wof:placetype":"venue"
},
  "geometry": {"coordinates":[5.7369289398,51.145450592],"type":"Point"}
}