{
  "type": "Feature",
  "properties": {
    "addr:full":"Kruisstraat 18 Tremelo Vlaams-Brabant 3120",
    "addr:housenumber":"18",
    "addr:postcode":"3120",
    "addr:street":"Kruisstraat",
    "iso:country":"BE",
    "sg:address":"Kruisstraat 18",
    "sg:city":"Tremelo",
    "sg:classifiers":[
        {
            "category":"Shopping",
            "subcategory":"Clothing, Apparel, & Fashions",
            "type":"Retail Goods"
        }
    ],
    "sg:phone":"+32 16 53 11 06",
    "sg:postcode":"3120",
    "sg:province":"Vlaams-Brabant",
    "sg:tags":[
        "boutique"
    ],
    "wof:name":"Mix-shop",
    "wof:placetype":"venue"
},
  "geometry": {"coordinates":[4.7030282021,50.9927062988],"type":"Point"}
}