{
  "type": "Feature",
  "properties": {
    "iso:country":"BE",
    "sg:address":"Belgenlaan 10",
    "sg:city":"Balen",
    "sg:orig_category":"Entretien and r\u00e9parations de voitures",
    "sg:phone":"+32 11 34 58 52",
    "sg:postcode":"2490",
    "sg:province":"Antwerpen",
    "wof:name":"Jozef De Groote",
    "wof:placetype":"venue"
},
  "geometry": {"coordinates":[5.2345099449,51.1416511536],"type":"Point"}
}