{
  "type": "Feature",
  "properties": {
    "addr:full":"Place L Wauthier 15 Fl\u00e9malle (ivoz-ramet) Li\u00e8ge 4400",
    "addr:housenumber":"15",
    "addr:postcode":"4400",
    "addr:street":"Place;Wauthier;Ivoz-Ramet",
    "iso:country":"BE",
    "sg:address":"Place L Wauthier 15",
    "sg:city":"Fl\u00e9malle (ivoz-ramet)",
    "sg:classifiers":[
        {
            "category":"Bars & Pubs",
            "type":"Food & Drink"
        }
    ],
    "sg:phone":"+32 497 80 74 14",
    "sg:postcode":"4400",
    "sg:province":"Li\u00e8ge",
    "wof:name":"Bourse (la)",
    "wof:placetype":"venue"
},
  "geometry": {"coordinates":[5.4576430321,50.5693130493],"type":"Point"}
}