{
  "type": "Feature",
  "properties": {
    "addr:full":"Pastoor De Conincklaan 18 Antwerpen (wilrijk) Antwerpen 2610",
    "addr:housenumber":"18",
    "addr:postcode":"2610",
    "addr:street":"Pastoor De Conincklaan;Antwerpen",
    "iso:country":"BE",
    "sg:address":"Pastoor De Conincklaan 18",
    "sg:city":"Antwerpen (wilrijk)",
    "sg:classifiers":[
        {
            "category":"Farming",
            "subcategory":"Fish & Marine Products",
            "type":"Manufacturing & Wholesale Goods"
        }
    ],
    "sg:phone":"+32 3 828 67 52",
    "sg:postcode":"2610",
    "sg:province":"Antwerpen",
    "sg:tags":[
        "photographer",
        "fashion",
        "-"
    ],
    "wof:name":"Alja Foto Produkties",
    "wof:placetype":"venue"
},
  "geometry": {"coordinates":[4.4201860428,51.2217636108],"type":"Point"}
}