{
  "type": "Feature",
  "properties": {
    "iso:country":"BE",
    "sg:address":"Grotstr 40",
    "sg:city":"Kapelle-op-den-bos (groot)",
    "sg:orig_category":"Kapsalons",
    "sg:phone":"+32 15 71 46 89",
    "sg:postcode":"1880",
    "sg:province":"Vlaams-Brabant",
    "wof:name":"D'hollander E",
    "wof:placetype":"venue"
},
  "geometry": {"coordinates":[4.3344068527,51.0122032166],"type":"Point"}
}