{
  "type": "Feature",
  "properties": {
    "addr:full":"Rue De Tilff 123 Li\u00c8ge Li\u00e8ge 4031",
    "addr:housenumber":"123",
    "addr:postcode":"4031",
    "addr:street":"Rue De Tilff",
    "iso:country":"BE",
    "sg:address":"Rue De Tilff 123",
    "sg:city":"Li\u00c8ge",
    "sg:orig_category":"Sportclubs",
    "sg:phone":"+32 4 366 08 09",
    "sg:postcode":"4031",
    "sg:province":"Li\u00e8ge",
    "wof:name":"V.b.c. Tilff",
    "wof:placetype":"venue"
},
  "geometry": {"coordinates":[5.6042361259,50.6075935364],"type":"Point"}
}