{
  "type": "Feature",
  "properties": {
    "addr:full":"Chauss\u00c9e De Monstreux 34 Seneffe Hainaut 7181",
    "addr:housenumber":"34",
    "addr:postcode":"7181",
    "addr:street":"Chausse\u0301E De Monstreux",
    "iso:country":"BE",
    "sg:address":"Chauss\u00c9e De Monstreux 34",
    "sg:city":"Seneffe",
    "sg:classifiers":[
        {
            "category":"Wholesale",
            "subcategory":"Sporting Goods",
            "type":"Manufacturing & Wholesale Goods"
        }
    ],
    "sg:phone":"+32 67 87 92 92",
    "sg:postcode":"7181",
    "sg:province":"Hainaut",
    "sg:tags":[
        "sport-",
        "kampeermateriaal"
    ],
    "wof:name":"Binsdi Horse",
    "wof:placetype":"venue"
},
  "geometry": {"coordinates":[4.2589969635,50.5626296997],"type":"Point"}
}