{
  "type": "Feature",
  "properties": {
    "addr:full":"Schooldreef 10 Gent Oost-Vlaanderen 9050",
    "addr:housenumber":"10",
    "addr:postcode":"9050",
    "addr:street":"Schooldreef;Oost-Vlaanderen",
    "iso:country":"BE",
    "sg:address":"Schooldreef 10",
    "sg:city":"Gent",
    "sg:orig_category":"Banques and organismes de cr\u00e9dit",
    "sg:phone":"+32 9 231 05 34",
    "sg:postcode":"9050",
    "sg:province":"Oost-Vlaanderen",
    "wof:name":"V.d.k. Spaarbank",
    "wof:placetype":"venue"
},
  "geometry": {"coordinates":[3.7614779472,51.0323066711],"type":"Point"}
}