{
  "type": "Feature",
  "properties": {
    "addr:full":"Doelstraat 162 Ingelmunster West-Vlaanderen 8770",
    "addr:housenumber":"162",
    "addr:postcode":"8770",
    "addr:street":"Doelstraat",
    "iso:country":"BE",
    "sg:address":"Doelstraat 162",
    "sg:city":"Ingelmunster",
    "sg:classifiers":[
        {
            "category":"Home & Garden",
            "subcategory":"Building Materials",
            "type":"Retail Goods"
        }
    ],
    "sg:phone":"+32 51 30 82 60",
    "sg:postcode":"8770",
    "sg:province":"West-Vlaanderen",
    "sg:tags":[
        "window"
    ],
    "wof:name":"Verschaete",
    "wof:placetype":"venue"
},
  "geometry": {"coordinates":[3.2406458855,50.9349365234],"type":"Point"}
}