{
  "type": "Feature",
  "properties": {
    "addr:full":"Schoolstraat 14ba Zulte Oost-Vlaanderen 9870",
    "addr:housenumber":"14ba",
    "addr:postcode":"9870",
    "addr:street":"Schoolstraat",
    "iso:country":"BE",
    "sg:address":"Schoolstraat 14ba",
    "sg:city":"Zulte",
    "sg:orig_category":"Articles de camping and de sport. Textiles. V\u00eatements",
    "sg:phone":"+32 9 386 82 86",
    "sg:postcode":"9870",
    "sg:province":"Oost-Vlaanderen",
    "wof:name":"Tennisland",
    "wof:placetype":"venue"
},
  "geometry": {"coordinates":[3.4917020798,50.9586791992],"type":"Point"}
}