{
  "type": "Feature",
  "properties": {
    "addr:full":"Tuinwijk 42 Kortemark West-Vlaanderen 8610",
    "addr:housenumber":"42",
    "addr:postcode":"8610",
    "addr:street":"Tuinwijk",
    "iso:country":"BE",
    "sg:address":"Tuinwijk 42",
    "sg:city":"Kortemark",
    "sg:classifiers":[
        {
            "category":"Arena",
            "subcategory":"Sports Club",
            "type":"Entertainment"
        }
    ],
    "sg:phone":"+32 51 56 94 48",
    "sg:postcode":"8610",
    "sg:province":"West-Vlaanderen",
    "sg:tags":[
        "terrain",
        "hors",
        "de",
        "installation",
        "sportifs"
    ],
    "wof:name":"V.v. Kortemark",
    "wof:placetype":"venue"
},
  "geometry": {"coordinates":[3.0491631031,51.030960083],"type":"Point"}
}