{
  "type": "Feature",
  "properties": {
    "addr:full":"Banneuxstr 17 Hasselt Limburg 3500",
    "addr:housenumber":"17",
    "addr:postcode":"3500",
    "addr:street":"Banneuxstr",
    "iso:country":"BE",
    "sg:address":"Banneuxstr 17",
    "sg:city":"Hasselt",
    "sg:classifiers":[
        {
            "category":"Banks & Credit Unions",
            "subcategory":"Bank",
            "type":"Services"
        }
    ],
    "sg:phone":"+32 11 21 12 12",
    "sg:postcode":"3500",
    "sg:province":"Limburg",
    "wof:name":"G\u00e9n\u00e9rale De Banque Sa",
    "wof:placetype":"venue"
},
  "geometry": {"coordinates":[5.3359251022,50.9270362854],"type":"Point"}
}