{
  "type": "Feature",
  "properties": {
    "addr:full":"Offerlaan 3 Gent Oost-Vlaanderen 9000",
    "addr:housenumber":"3",
    "addr:postcode":"9000",
    "addr:street":"Offerlaan;Oost-Vlaanderen",
    "iso:country":"BE",
    "sg:address":"Offerlaan 3",
    "sg:city":"Gent",
    "sg:orig_category":"Volwassenenonderwijs",
    "sg:phone":"+32 9 225 04 36",
    "sg:postcode":"9000",
    "sg:province":"Oost-Vlaanderen",
    "wof:name":"Centrum Permanente Vorm.",
    "wof:placetype":"venue"
},
  "geometry": {"coordinates":[3.7086849213,51.0436820984],"type":"Point"}
}