{
  "type": "Feature",
  "properties": {
    "addr:full":"De Merodestraat 6 Grimbergen Vlaams-Brabant 1850",
    "addr:housenumber":"6",
    "addr:postcode":"1850",
    "addr:street":"De Merodestraat",
    "iso:country":"BE",
    "sg:address":"De Merodestraat 6",
    "sg:city":"Grimbergen",
    "sg:orig_category":"Dierenartsen",
    "sg:phone":"+32 2 270 96 50",
    "sg:postcode":"1850",
    "sg:province":"Vlaams-Brabant",
    "wof:name":"Lode Cornelissen",
    "wof:placetype":"venue"
},
  "geometry": {"coordinates":[4.3737149239,50.9256286621],"type":"Point"}
}