{
  "type": "Feature",
  "properties": {
    "iso:country":"BE",
    "sg:address":"Parc Ind. Des Hauts Sarts 1e 215",
    "sg:city":"Herstal",
    "sg:classifiers":[
        {
            "category":"Autos & Motor Vehicles",
            "subcategory":"Auto Supplies",
            "type":"Retail Goods"
        }
    ],
    "sg:phone":"+32 4 248 24 79",
    "sg:postcode":"4040",
    "sg:province":"Li\u00e8ge",
    "sg:tags":[
        "electric"
    ],
    "wof:name":"Travelec S.a.",
    "wof:placetype":"venue"
},
  "geometry": {"coordinates":[5.6154317856,50.6897239685],"type":"Point"}
}