{
  "type": "Feature",
  "properties": {
    "addr:full":"Boezingestraat 1 Ieper West-Vlaanderen 8900",
    "addr:housenumber":"1",
    "addr:postcode":"8900",
    "addr:street":"Boezingestraat",
    "iso:country":"BE",
    "sg:address":"Boezingestraat 1",
    "sg:city":"Ieper",
    "sg:orig_category":"Postkantoren Verzekeringsmakelaars and experts",
    "sg:phone":"+32 57 42 20 42",
    "sg:postcode":"8900",
    "sg:province":"West-Vlaanderen",
    "wof:name":"De Post",
    "wof:placetype":"venue"
},
  "geometry": {"coordinates":[2.8833069801,50.8524742126],"type":"Point"}
}