{
  "type": "Feature",
  "properties": {
    "iso:country":"BE",
    "sg:address":"Rue D'arenberg 18",
    "sg:city":"Brussel/bruxelles",
    "sg:orig_category":"H\u00f4tels. Restaurants",
    "sg:phone":"+32 2 548 18 11",
    "sg:postcode":"1000",
    "sg:province":"Bruxelles-Capitale",
    "wof:name":"Arctia Hotel Brussels",
    "wof:placetype":"venue"
},
  "geometry": {"coordinates":[4.3564281464,50.8484573364],"type":"Point"}
}