{
  "type": "Feature",
  "properties": {
    "addr:full":"Steenkouter 51 Wichelen (serskamp) Oost-Vlaanderen 9260",
    "addr:housenumber":"51",
    "addr:postcode":"9260",
    "addr:street":"Steenkouter",
    "iso:country":"BE",
    "sg:address":"Steenkouter 51",
    "sg:city":"Wichelen (serskamp)",
    "sg:classifiers":[
        {
            "category":"Communications",
            "type":"Services"
        }
    ],
    "sg:phone":"+32 9 369 67 78",
    "sg:postcode":"9260",
    "sg:province":"Oost-Vlaanderen",
    "sg:tags":[
        "translator"
    ],
    "wof:name":"Gertner-lauenstein",
    "wof:placetype":"venue"
},
  "geometry": {"coordinates":[3.9317789078,50.9846572876],"type":"Point"}
}