{
  "type": "Feature",
  "properties": {
    "addr:full":"Tweekerkenstraat 134 Zottegem (godveerdegem) Oost-Vlaanderen 9620",
    "addr:housenumber":"134",
    "addr:postcode":"9620",
    "addr:street":"Tweekerkenstraat",
    "iso:country":"BE",
    "sg:address":"Tweekerkenstraat 134",
    "sg:city":"Zottegem (godveerdegem)",
    "sg:classifiers":[
        {
            "category":"Shopping",
            "subcategory":"Florist",
            "type":"Retail Goods"
        }
    ],
    "sg:phone":"+32 9 360 12 55",
    "sg:postcode":"9620",
    "sg:province":"Oost-Vlaanderen",
    "wof:name":"Vlasschaert R",
    "wof:placetype":"venue"
},
  "geometry": {"coordinates":[3.8112111092,50.871181488],"type":"Point"}
}