{
  "type": "Feature",
  "properties": {
    "addr:full":"Rue De Bonne Esp\u00e9rance 56 La Louvi\u00e8re Hainaut 7100",
    "addr:housenumber":"56",
    "addr:postcode":"7100",
    "addr:street":"Rue De Bonne Espe\u0301Rance",
    "iso:country":"BE",
    "sg:address":"Rue De Bonne Esp\u00e9rance 56",
    "sg:city":"La Louvi\u00e8re",
    "sg:classifiers":[
        {
            "category":"Health Services",
            "subcategory":"Health Practitioner",
            "type":"Services"
        }
    ],
    "sg:phone":"+32 64 28 13 66",
    "sg:postcode":"7100",
    "sg:province":"Hainaut",
    "sg:tags":[
        "physiotherapist"
    ],
    "wof:name":"Vermeersch A-c",
    "wof:placetype":"venue"
},
  "geometry": {"coordinates":[4.1847281456,50.4696617126],"type":"Point"}
}