{
  "type": "Feature",
  "properties": {
    "iso:country":"BE",
    "sg:address":"Oudenaardestraat 33",
    "sg:city":"Anzegem (vichte)",
    "sg:orig_category":"Newspapers, magazines, periodicals - Distribution",
    "sg:phone":"+32 56 77 30 05",
    "sg:postcode":"8570",
    "sg:province":"West-Vlaanderen",
    "wof:name":"Media Press Shop",
    "wof:placetype":"venue"
},
  "geometry": {"coordinates":[3.4065999985,50.8388633728],"type":"Point"}
}