{
  "type": "Feature",
  "properties": {
    "addr:full":"Rue Des Carm\u00e9lites 4 Lens Hainaut 7870",
    "addr:housenumber":"4",
    "addr:postcode":"7870",
    "addr:street":"Rue Des Carme\u0301Lites",
    "iso:country":"BE",
    "sg:address":"Rue Des Carm\u00e9lites 4",
    "sg:city":"Lens",
    "sg:classifiers":[
        {
            "category":"Health Services",
            "subcategory":"Health Practitioner",
            "type":"Services"
        }
    ],
    "sg:phone":"+32 65 23 55 67",
    "sg:postcode":"7870",
    "sg:province":"Hainaut",
    "sg:tags":[
        "physiotherapist"
    ],
    "wof:name":"Manandise E",
    "wof:placetype":"venue"
},
  "geometry": {"coordinates":[3.8966610432,50.5563163757],"type":"Point"}
}