{
  "type": "Feature",
  "properties": {
    "addr:full":"Kortrijksestraat 23 Oostkamp West-Vlaanderen 8020",
    "addr:housenumber":"23",
    "addr:postcode":"8020",
    "addr:street":"Kortrijksestraat",
    "iso:country":"BE",
    "sg:address":"Kortrijksestraat 23",
    "sg:city":"Oostkamp",
    "sg:classifiers":[
        {
            "category":"Retail",
            "subcategory":"Repair Shop",
            "type":"Services"
        }
    ],
    "sg:phone":"+32 50 82 73 73",
    "sg:postcode":"8020",
    "sg:province":"West-Vlaanderen",
    "sg:tags":[
        "-",
        "mainten",
        "watch",
        "clock"
    ],
    "wof:name":"Vanquaethem",
    "wof:placetype":"venue"
},
  "geometry": {"coordinates":[3.2352950573,51.1534919739],"type":"Point"}
}