{
  "type": "Feature",
  "properties": {
    "addr:full":"Chauss\u00c9e D'audenarde 42ba Pecq Hainaut 7742",
    "addr:housenumber":"42ba",
    "addr:postcode":"7742",
    "addr:street":"Chausse\u0301E D'Audenarde",
    "iso:country":"BE",
    "sg:address":"Chauss\u00c9e D'audenarde 42ba",
    "sg:city":"Pecq",
    "sg:orig_category":"Rundveehouders",
    "sg:phone":"+32 69 55 77 17",
    "sg:postcode":"7742",
    "sg:province":"Hainaut",
    "wof:name":"Willy Vandeputte",
    "wof:placetype":"venue"
},
  "geometry": {"coordinates":[3.358850956,50.6783866882],"type":"Point"}
}