{
  "type": "Feature",
  "properties": {
    "addr:full":"Molenveld 19 Zemst Vlaams-Brabant 1982",
    "addr:housenumber":"19",
    "addr:postcode":"1982",
    "addr:street":"Molenveld;Vlaams-Brabant",
    "iso:country":"BE",
    "sg:address":"Molenveld 19",
    "sg:city":"Zemst",
    "sg:orig_category":"Pain, p\u00e2tisseries and confiseries",
    "sg:phone":"+32 15 61 17 01",
    "sg:postcode":"1982",
    "sg:province":"Vlaams-Brabant",
    "wof:name":"Merckx En Co",
    "wof:placetype":"venue"
},
  "geometry": {"coordinates":[4.5011520386,50.9606971741],"type":"Point"}
}