{
  "type": "Feature",
  "properties": {
    "iso:country":"BE",
    "sg:address":"Astridlaan 28",
    "sg:city":"Heusden-zolder",
    "sg:classifiers":[
        {
            "category":"Cafe",
            "type":"Food & Drink"
        }
    ],
    "sg:phone":"+32 11 53 67 25",
    "sg:postcode":"3550",
    "sg:province":"Limburg",
    "sg:tags":[
        "caf\u00e9s"
    ],
    "wof:name":"Giovanni Campus",
    "wof:placetype":"venue"
},
  "geometry": {"coordinates":[5.2849698067,51.0141296387],"type":"Point"}
}