{
  "type": "Feature",
  "properties": {
    "addr:full":"Avenue Du Petit Sart 86 Namur Namur 5100",
    "addr:housenumber":"86",
    "addr:postcode":"5100",
    "addr:street":"Avenue Du Petit Sart",
    "iso:country":"BE",
    "sg:address":"Avenue Du Petit Sart 86",
    "sg:city":"Namur",
    "sg:orig_category":"Mat\u00e9riaux de construction Gr",
    "sg:phone":"+32 81 30 37 73",
    "sg:postcode":"5100",
    "sg:province":"Namur",
    "wof:name":"Gautot Brothers Industrie",
    "wof:placetype":"venue"
},
  "geometry": {"coordinates":[4.8899769783,50.4425354004],"type":"Point"}
}