{
  "type": "Feature",
  "properties": {
    "addr:full":"Markt 21 Lokeren Oost-Vlaanderen 9160",
    "addr:housenumber":"21",
    "addr:postcode":"9160",
    "addr:street":"Markt",
    "iso:country":"BE",
    "sg:address":"Markt 21",
    "sg:city":"Lokeren",
    "sg:classifiers":[
        {
            "category":"Cafe",
            "type":"Food & Drink"
        }
    ],
    "sg:phone":"+32 9 348 36 72",
    "sg:postcode":"9160",
    "sg:province":"Oost-Vlaanderen",
    "sg:tags":[
        "caf\u00e9s"
    ],
    "wof:name":"Caf\u00c9 Prior",
    "wof:placetype":"venue"
},
  "geometry": {"coordinates":[3.9899199009,51.1048851013],"type":"Point"}
}