{
  "type": "Feature",
  "properties": {
    "iso:country":"BE",
    "sg:address":"Rue Du Cimeti\u00c8re 31",
    "sg:city":"Charleroi",
    "sg:orig_category":"Instellingen voor probleemkinderen Kindertehuizen",
    "sg:phone":"+32 71 31 28 75",
    "sg:postcode":"6030",
    "sg:province":"Hainaut",
    "wof:name":"A.c.i.s.",
    "wof:placetype":"venue"
},
  "geometry": {"coordinates":[4.4069390297,50.4254455566],"type":"Point"}
}