{
  "type": "Feature",
  "properties": {
    "iso:country":"BE",
    "sg:address":"Lange Brilstraat 14",
    "sg:city":"Antwerpen",
    "sg:orig_category":"Bouwmaterialen Gh",
    "sg:phone":"+32 3 231 08 21",
    "sg:postcode":"2000",
    "sg:province":"Antwerpen",
    "wof:name":"De Saegher J. Steenhandel",
    "wof:placetype":"venue"
},
  "geometry": {"coordinates":[4.4083352089,51.2237930298],"type":"Point"}
}