{
  "type": "Feature",
  "properties": {
    "iso:country":"BE",
    "sg:address":"Negende Linielaan 22",
    "sg:city":"Middelkerke",
    "sg:classifiers":[
        {
            "category":"Insurance",
            "subcategory":"Life Insurance",
            "type":"Services"
        }
    ],
    "sg:phone":"+32 58 23 63 03",
    "sg:postcode":"8434",
    "sg:province":"West-Vlaanderen",
    "sg:tags":[
        "assurance"
    ],
    "wof:name":"N. Coulier",
    "wof:placetype":"venue"
},
  "geometry": {"coordinates":[2.7591300011,51.1481704712],"type":"Point"}
}