{
  "type": "Feature",
  "properties": {
    "addr:full":"Rue Nazareth 11 Herve (battice) Li\u00e8ge 4651",
    "addr:housenumber":"11",
    "addr:postcode":"4651",
    "addr:street":"Rue Nazareth",
    "iso:country":"BE",
    "sg:address":"Rue Nazareth 11",
    "sg:city":"Herve (battice)",
    "sg:classifiers":[
        {
            "category":"Manufacturing",
            "subcategory":"Tools & Machinery",
            "type":"Manufacturing & Wholesale Goods"
        }
    ],
    "sg:phone":"+32 87 67 42 07",
    "sg:postcode":"4651",
    "sg:province":"Li\u00e8ge",
    "sg:tags":[
        "-"
    ],
    "wof:name":"Technovit Sprl",
    "wof:placetype":"venue"
},
  "geometry": {"coordinates":[5.8010401726,50.6468582153],"type":"Point"}
}