{
  "type": "Feature",
  "properties": {
    "iso:country":"BE",
    "sg:address":"Route De Lennik 238",
    "sg:city":"Bruxelles (anderlecht)",
    "sg:classifiers":[
        {
            "category":"Shopping",
            "subcategory":"Musical Instruments",
            "type":"Retail Goods"
        }
    ],
    "sg:phone":"+32 2 522 19 13",
    "sg:postcode":"1070",
    "sg:province":"Bruxelles-Capitale",
    "sg:tags":[
        "piano",
        "-",
        "tuning"
    ],
    "wof:name":"Michiels (maison)",
    "wof:placetype":"venue"
},
  "geometry": {"coordinates":[4.287209034,50.8195800781],"type":"Point"}
}