{
  "type": "Feature",
  "properties": {
    "addr:full":"Rotterij 146 Ronse/renaix Oost-Vlaanderen 9600",
    "addr:housenumber":"146",
    "addr:postcode":"9600",
    "iso:country":"BE",
    "sg:address":"Rotterij 146",
    "sg:city":"Ronse/renaix",
    "sg:orig_category":"M\u00e9decins and sp\u00e9cialistes",
    "sg:phone":"+32 55 20 89 14",
    "sg:postcode":"9600",
    "sg:province":"Oost-Vlaanderen",
    "wof:name":"Monique Vreugde",
    "wof:placetype":"venue"
},
  "geometry": {"coordinates":[3.6251211166,50.7443771362],"type":"Point"}
}