{
  "type": "Feature",
  "properties": {
    "iso:country":"BE",
    "sg:address":"Wisselstraat 5",
    "sg:city":"Antwerpen",
    "sg:classifiers":[
        {
            "category":"Restaurant",
            "type":"Food & Drink"
        }
    ],
    "sg:phone":"+32 3 776 88 63",
    "sg:postcode":"2000",
    "sg:province":"Antwerpen",
    "wof:name":"Sattwa",
    "wof:placetype":"venue"
},
  "geometry": {"coordinates":[-102.4115524292,38.0852584839],"type":"Point"}
}