{
  "type": "Feature",
  "properties": {
    "iso:country":"BE",
    "sg:address":"Rue Du Merlo 16",
    "sg:city":"Ukkel/uccle",
    "sg:orig_category":"Enseignement maternel and primaire",
    "sg:phone":"+32 2 348 68 41",
    "sg:postcode":"1180",
    "sg:province":"Bruxelles-Capitale",
    "wof:name":"Ecole Le Merlo",
    "wof:placetype":"venue"
},
  "geometry": {"coordinates":[4.3210282326,50.7988357544],"type":"Point"}
}