{
  "type": "Feature",
  "properties": {
    "addr:full":"Avenue Champion - Aubange 1 Aubange Luxembourg 6790",
    "addr:housenumber":"1",
    "addr:postcode":"6790",
    "addr:street":"Avenue Champion Aubange",
    "iso:country":"BE",
    "sg:address":"Avenue Champion - Aubange 1",
    "sg:city":"Aubange",
    "sg:classifiers":[
        {
            "category":"Wholesale",
            "subcategory":"Auto Parts",
            "type":"Manufacturing & Wholesale Goods"
        }
    ],
    "sg:phone":"+32 63 38 22 11",
    "sg:postcode":"6790",
    "sg:province":"Luxembourg",
    "sg:tags":[
        "car",
        "electronic",
        "systems",
        "ignition"
    ],
    "wof:name":"Cooper Automative S.a.",
    "wof:placetype":"venue"
},
  "geometry": {"coordinates":[5.8105821609,49.5559082031],"type":"Point"}
}