{
  "type": "Feature",
  "properties": {
    "iso:country":"BE",
    "sg:address":"Vrijhem 10bb",
    "sg:city":"Oosterzele",
    "sg:orig_category":"Artsen and specialisten",
    "sg:phone":"+32 9 362 64 50",
    "sg:postcode":"9860",
    "sg:province":"Oost-Vlaanderen",
    "wof:name":"Joost De Maeseneer",
    "wof:placetype":"venue"
},
  "geometry": {"coordinates":[3.7868709564,50.9294319153],"type":"Point"}
}