{
  "type": "Feature",
  "properties": {
    "addr:full":"Kapel Ter Rustestraat 4 Deerlijk West-Vlaanderen 8540",
    "addr:housenumber":"4",
    "addr:postcode":"8540",
    "addr:street":"Rustestraat",
    "iso:country":"BE",
    "sg:address":"Kapel Ter Rustestraat 4",
    "sg:city":"Deerlijk",
    "sg:orig_category":"Quincailleries",
    "sg:phone":"+32 56 71 34 58",
    "sg:postcode":"8540",
    "sg:province":"West-Vlaanderen",
    "wof:name":"Deprez",
    "wof:placetype":"venue"
},
  "geometry": {"coordinates":[3.3546819687,50.8513946533],"type":"Point"}
}