{
  "type": "Feature",
  "properties": {
    "addr:full":"Rue \u00c0 La Barre 12bb Tournai Hainaut 7530",
    "addr:housenumber":"12bb",
    "addr:postcode":"7530",
    "addr:street":"Rue A\u0300 La Barre",
    "iso:country":"BE",
    "sg:address":"Rue \u00c0 La Barre 12bb",
    "sg:city":"Tournai",
    "sg:orig_category":"Medische apparatuur, orthopedische artikelen and prothesen Fab",
    "sg:phone":"+32 69 54 76 73",
    "sg:postcode":"7530",
    "sg:province":"Hainaut",
    "wof:name":"Michel Detournay",
    "wof:placetype":"venue"
},
  "geometry": {"coordinates":[3.4995861053,50.5990257263],"type":"Point"}
}