{
  "type": "Feature",
  "properties": {
    "addr:full":"Europalaan 124b2 Genk Limburg 3600",
    "addr:housenumber":"124b2",
    "addr:postcode":"3600",
    "addr:street":"Europalaan",
    "iso:country":"BE",
    "sg:address":"Europalaan 124b2",
    "sg:city":"Genk",
    "sg:orig_category":"Souvenirs and objets artisanaux. Eclairage et \u00e9quipements du foyer",
    "sg:phone":"+32 89 35 43 49",
    "sg:postcode":"3600",
    "sg:province":"Limburg",
    "wof:name":"Cervantes",
    "wof:placetype":"venue"
},
  "geometry": {"coordinates":[5.5027008057,50.965713501],"type":"Point"}
}