{
  "type": "Feature",
  "properties": {
    "iso:country":"BE",
    "sg:address":"Kiezelstraat 18",
    "sg:city":"Kortenberg",
    "sg:classifiers":[
        {
            "category":"Arena",
            "subcategory":"Sports Club",
            "type":"Entertainment"
        }
    ],
    "sg:phone":"+32 16 48 09 47",
    "sg:postcode":"3078",
    "sg:province":"Vlaams-Brabant",
    "sg:tags":[
        "de"
    ],
    "wof:name":"C.c.b.",
    "wof:placetype":"venue"
},
  "geometry": {"coordinates":[4.6051878929,50.8713912964],"type":"Point"}
}