{
  "type": "Feature",
  "properties": {
    "addr:full":"Rue Marie-henriette 52-54 Elsene Bruxelles-Capitale 1050",
    "addr:housenumber":"52-54",
    "addr:postcode":"1050",
    "addr:street":"Rue Marie-Henriette",
    "iso:country":"BE",
    "sg:address":"Rue Marie-henriette 52-54",
    "sg:city":"Elsene",
    "sg:orig_category":"Begrafeniswezen",
    "sg:phone":"+32 475 46 07 06",
    "sg:postcode":"1050",
    "sg:province":"Bruxelles-Capitale",
    "wof:name":"Animatrans",
    "wof:placetype":"venue"
},
  "geometry": {"coordinates":[4.3748898506,50.8298606873],"type":"Point"}
}