{
  "type": "Feature",
  "properties": {
    "addr:full":"Grand Route 4 Antoing (maubray) Hainaut 7640",
    "addr:postcode":"7640",
    "addr:street":"Grand Route 4",
    "iso:country":"BE",
    "sg:address":"Grand Route 4",
    "sg:city":"Antoing (maubray)",
    "sg:classifiers":[
        {
            "category":"Building & Trades",
            "subcategory":"Plumbing",
            "type":"Services"
        }
    ],
    "sg:phone":"+32 69 44 28 72",
    "sg:postcode":"7640",
    "sg:province":"Hainaut",
    "sg:tags":[
        "contractor"
    ],
    "wof:name":"Geerens G",
    "wof:placetype":"venue"
},
  "geometry": {"coordinates":[3.4779069424,50.5521888733],"type":"Point"}
}