{
  "type": "Feature",
  "properties": {
    "iso:country":"BE",
    "sg:address":"Les Taillisses 10",
    "sg:city":"Fl\u00e9malle",
    "sg:classifiers":[
        {
            "category":"Real Estate",
            "subcategory":"Surveying",
            "type":"Services"
        }
    ],
    "sg:phone":"+32 4 275 65 65",
    "sg:postcode":"4400",
    "sg:province":"Li\u00e8ge",
    "sg:tags":[
        "surveyor",
        "land"
    ],
    "wof:name":"B.e.s Topom\u00e9trie Sprl",
    "wof:placetype":"venue"
},
  "geometry": {"coordinates":[5.4446229935,50.5969963074],"type":"Point"}
}