{
  "type": "Feature",
  "properties": {
    "iso:country":"BE",
    "sg:address":"Bergstraat 103",
    "sg:city":"Heist-op-den-berg",
    "sg:classifiers":[
        {
            "category":"Cafe",
            "type":"Food & Drink"
        }
    ],
    "sg:phone":"+32 15 25 07 73",
    "sg:postcode":"2220",
    "sg:province":"Antwerpen",
    "sg:tags":[
        "caf\u00e9s"
    ],
    "wof:name":"De Rotonde",
    "wof:placetype":"venue"
},
  "geometry": {"coordinates":[4.7206020355,51.0763015747],"type":"Point"}
}