{
  "type": "Feature",
  "properties": {
    "addr:full":"Rud De Sedan 92 Vresse-sur-semois Namur 5550",
    "addr:housenumber":"92",
    "addr:postcode":"5550",
    "iso:country":"BE",
    "sg:address":"Rud De Sedan 92",
    "sg:city":"Vresse-sur-semois",
    "sg:orig_category":"Houtbewerking and -behandeling",
    "sg:phone":"+32 61 50 80 00",
    "sg:postcode":"5550",
    "sg:province":"Namur",
    "wof:name":"Leplang Fr\u00c8res",
    "wof:placetype":"venue"
},
  "geometry": {"coordinates":[4.9682350159,49.801448822],"type":"Point"}
}