{
  "type": "Feature",
  "properties": {
    "addr:full":"Tieltstraat 68ba Wingene West-Vlaanderen 8750",
    "addr:housenumber":"68ba",
    "addr:postcode":"8750",
    "addr:street":"Tieltstraat",
    "iso:country":"BE",
    "sg:address":"Tieltstraat 68ba",
    "sg:city":"Wingene",
    "sg:orig_category":"Quincailleries",
    "sg:phone":"+32 51 65 57 76",
    "sg:postcode":"8750",
    "sg:province":"West-Vlaanderen",
    "wof:name":"Luc Vanhoutte",
    "wof:placetype":"venue"
},
  "geometry": {"coordinates":[3.2847568989,51.0553627014],"type":"Point"}
}