{
  "type": "Feature",
  "properties": {
    "iso:country":"BE",
    "sg:address":"Avenue J. B. Nothomb 14",
    "sg:city":"Arlon",
    "sg:orig_category":"Artsen and specialisten",
    "sg:phone":"+32 63 22 19 84",
    "sg:postcode":"6700",
    "sg:province":"Luxembourg",
    "wof:name":"Mich\u00c8le Lippert",
    "wof:placetype":"venue"
},
  "geometry": {"coordinates":[5.8111371994,49.6821746826],"type":"Point"}
}