{
  "type": "Feature",
  "properties": {
    "iso:country":"BE",
    "sg:address":"Gemechenne 79",
    "sg:city":"Dinant",
    "sg:classifiers":[
        {
            "category":"Farming",
            "subcategory":"Farm & Veterinary Services",
            "type":"Manufacturing & Wholesale Goods"
        }
    ],
    "sg:phone":"+32 82 22 22 25",
    "sg:postcode":"5500",
    "sg:province":"Namur",
    "sg:tags":[
        "agricultural",
        "contractor"
    ],
    "wof:name":"Agrigem",
    "wof:placetype":"venue"
},
  "geometry": {"coordinates":[4.9494328499,50.2659645081],"type":"Point"}
}