{
  "type": "Feature",
  "properties": {
    "addr:full":"M. Van Bourgondi\u00cblaan 42 Torhout West-Vlaanderen 8820",
    "addr:housenumber":"42",
    "addr:postcode":"8820",
    "addr:street":"M. Van Bourgondie\u0308Laan",
    "iso:country":"BE",
    "sg:address":"M. Van Bourgondi\u00cblaan 42",
    "sg:city":"Torhout",
    "sg:orig_category":"M\u00e9decins and sp\u00e9cialistes",
    "sg:phone":"+32 50 21 51 11",
    "sg:postcode":"8820",
    "sg:province":"West-Vlaanderen",
    "wof:name":"Jean-pierre Kerckhoven",
    "wof:placetype":"venue"
},
  "geometry": {"coordinates":[3.0971260071,51.0688514709],"type":"Point"}
}