{
  "type": "Feature",
  "properties": {
    "addr:full":"Rue Paloke 175 Sint-jans-molenbeek/molenbeek-saint-jean Bruxelles-Capitale 1080",
    "addr:housenumber":"175",
    "addr:postcode":"1080",
    "addr:street":"Rue Paloke",
    "iso:country":"BE",
    "sg:address":"Rue Paloke 175",
    "sg:city":"Sint-jans-molenbeek/molenbeek-saint-jean",
    "sg:orig_category":"Installation \u00e9lectrique r\u00e9sidentielle",
    "sg:phone":"+32 2 469 33 03",
    "sg:postcode":"1080",
    "sg:province":"Bruxelles-Capitale",
    "wof:name":"Electric 2000",
    "wof:placetype":"venue"
},
  "geometry": {"coordinates":[4.2849941254,50.8524780273],"type":"Point"}
}