{
  "type": "Feature",
  "properties": {
    "iso:country":"BE",
    "sg:address":"Chauss\u00c9e De Waterloo 849",
    "sg:city":"Ukkel/uccle",
    "sg:orig_category":"Telecommunicatieapparaten",
    "sg:phone":"+32 2 375 39 07",
    "sg:postcode":"1180",
    "sg:province":"Bruxelles-Capitale",
    "wof:name":"Barphone",
    "wof:placetype":"venue"
},
  "geometry": {"coordinates":[4.3693470955,50.8094940186],"type":"Point"}
}