{
  "type": "Feature",
  "properties": {
    "iso:country":"BE",
    "sg:address":"R Des Clercs 19",
    "sg:city":"Mons",
    "sg:classifiers":[
        {
            "category":"Real Estate",
            "subcategory":"Architect",
            "type":"Services"
        }
    ],
    "sg:phone":"+32 65 84 16 81",
    "sg:postcode":"7000",
    "sg:province":"Hainaut",
    "wof:name":"Delaisse P",
    "wof:placetype":"venue"
},
  "geometry": {"coordinates":[3.9506030083,50.4535636902],"type":"Point"}
}