{
  "type": "Feature",
  "properties": {
    "addr:full":"Sippelberglaan 1 Ganshoren Bruxelles-Capitale 1083",
    "addr:housenumber":"1",
    "addr:postcode":"1083",
    "addr:street":"Sippelberglaan",
    "iso:country":"BE",
    "sg:address":"Sippelberglaan 1",
    "sg:city":"Ganshoren",
    "sg:orig_category":"Fitnesscentra",
    "sg:phone":"+32 2 414 41 55",
    "sg:postcode":"1083",
    "sg:province":"Bruxelles-Capitale",
    "wof:name":"Centre Fyzixs",
    "wof:placetype":"venue"
},
  "geometry": {"coordinates":[4.3144011497,50.8697166443],"type":"Point"}
}