{
  "type": "Feature",
  "properties": {
    "addr:full":"Kleinesteenweg 1a Antwerpen Antwerpen 2610",
    "addr:housenumber":"1a",
    "addr:postcode":"2610",
    "addr:street":"Kleinesteenweg",
    "iso:country":"BE",
    "sg:address":"Kleinesteenweg 1a",
    "sg:city":"Antwerpen",
    "sg:orig_category":"Levering aan huis restaurants",
    "sg:phone":"+32 3 828 22 08",
    "sg:postcode":"2610",
    "sg:province":"Antwerpen",
    "wof:name":"Levoni",
    "wof:placetype":"venue"
},
  "geometry": {"coordinates":[4.402244091,51.2156181335],"type":"Point"}
}