{
  "type": "Feature",
  "properties": {
    "iso:country":"BE",
    "sg:address":"Rue Du Rouge-bouton 43ba",
    "sg:city":"Ittre",
    "sg:orig_category":"Dansscholen",
    "sg:phone":"+32 67 64 66 60",
    "sg:postcode":"1460",
    "sg:province":"Brabant Wallon",
    "wof:name":"Les Jeunes Talents",
    "wof:placetype":"venue"
},
  "geometry": {"coordinates":[4.2057452202,50.6459388733],"type":"Point"}
}