{
  "type": "Feature",
  "properties": {
    "addr:full":"Sint-truidersteenweg 130 Hasselt Limburg 3500",
    "addr:housenumber":"130",
    "addr:postcode":"3500",
    "addr:street":"Sint-Truidersteenweg",
    "iso:country":"BE",
    "sg:address":"Sint-truidersteenweg 130",
    "sg:city":"Hasselt",
    "sg:orig_category":"Kapsalons",
    "sg:phone":"+32 11 22 78 38",
    "sg:postcode":"3500",
    "sg:province":"Limburg",
    "wof:name":"Mod\u00b4s Hair Desmet",
    "wof:placetype":"venue"
},
  "geometry": {"coordinates":[5.3319611549,50.9227523804],"type":"Point"}
}