{
  "type": "Feature",
  "properties": {
    "addr:full":"Bois D'hazy 205 Bastogne Luxembourg 6600",
    "addr:housenumber":"205",
    "addr:postcode":"6600",
    "iso:country":"BE",
    "sg:address":"Bois D'hazy 205",
    "sg:city":"Bastogne",
    "sg:classifiers":[
        {
            "category":"Farming",
            "subcategory":"Livestock Farm",
            "type":"Manufacturing & Wholesale Goods"
        }
    ],
    "sg:phone":"+32 61 21 62 23",
    "sg:postcode":"6600",
    "sg:province":"Luxembourg",
    "sg:tags":[
        "buyer"
    ],
    "wof:name":"Nisen D Sa",
    "wof:placetype":"venue"
},
  "geometry": {"coordinates":[5.7171049118,49.9879150391],"type":"Point"}
}