{
  "type": "Feature",
  "properties": {
    "addr:full":"Voie De Li\u00e8ge 86 Chaudfontaine (embourg) Li\u00e8ge 4053",
    "addr:housenumber":"86",
    "addr:postcode":"4053",
    "addr:street":"Voie De Lie\u0300Ge",
    "iso:country":"BE",
    "sg:address":"Voie De Li\u00e8ge 86",
    "sg:city":"Chaudfontaine (embourg)",
    "sg:classifiers":[
        {
            "category":"Health Services",
            "subcategory":"Health Practitioner",
            "type":"Services"
        }
    ],
    "sg:phone":"+32 4 365 31 97",
    "sg:postcode":"4053",
    "sg:province":"Li\u00e8ge",
    "sg:tags":[
        "physiotherapist"
    ],
    "wof:name":"Bader J-l",
    "wof:placetype":"venue"
},
  "geometry": {"coordinates":[5.6160440445,50.5937004089],"type":"Point"}
}