{
  "type": "Feature",
  "properties": {
    "iso:country":"BE",
    "sg:address":"Rue D'en Dessous 67",
    "sg:city":"Les Bons Villers (mellet)",
    "sg:classifiers":[
        {
            "category":"Shopping",
            "subcategory":"Antiques",
            "type":"Retail Goods"
        }
    ],
    "sg:phone":"+32 71 87 63 76",
    "sg:postcode":"6211",
    "sg:province":"Hainaut",
    "sg:tags":[
        "restoration"
    ],
    "wof:name":"Lifting Du Meuble",
    "wof:placetype":"venue"
},
  "geometry": {"coordinates":[4.4603381157,50.4977836609],"type":"Point"}
}