{
  "type": "Feature",
  "properties": {
    "addr:full":"Meersbloem Melden 20 Oudenaarde (melden) Oost-Vlaanderen 9700",
    "addr:housenumber":"20",
    "addr:postcode":"9700",
    "addr:street":"Melden",
    "iso:country":"BE",
    "sg:address":"Meersbloem Melden 20",
    "sg:city":"Oudenaarde (melden)",
    "sg:classifiers":[
        {
            "category":"Transit Center",
            "subcategory":"Passenger",
            "type":"Transportation"
        }
    ],
    "sg:phone":"+32 55 33 48 11",
    "sg:postcode":"9700",
    "sg:province":"Oost-Vlaanderen",
    "sg:tags":[
        "sand",
        "gravel"
    ],
    "wof:name":"Ottevaere Firmin & Co Nv O.b.c. Oudenaardse Betoncentrale",
    "wof:placetype":"venue"
},
  "geometry": {"coordinates":[3.57385993,50.8169593811],"type":"Point"}
}