{
  "type": "Feature",
  "properties": {
    "addr:full":"Rue Bovesse 45 Aubange Luxembourg 6791",
    "addr:housenumber":"45",
    "addr:postcode":"6791",
    "addr:street":"Rue Bovesse",
    "iso:country":"BE",
    "sg:address":"Rue Bovesse 45",
    "sg:city":"Aubange",
    "sg:orig_category":"Immobili\u00ebnkantoren Landmeters",
    "sg:phone":"+32 63 38 98 60",
    "sg:postcode":"6791",
    "sg:province":"Luxembourg",
    "wof:name":"Imtop",
    "wof:placetype":"venue"
},
  "geometry": {"coordinates":[5.8368301392,49.5627288818],"type":"Point"}
}