{
  "type": "Feature",
  "properties": {
    "addr:full":"Kleine Eggestraat 1 Zonhoven Limburg 3520",
    "addr:housenumber":"1",
    "addr:postcode":"3520",
    "addr:street":"Kleine Eggestraat",
    "iso:country":"BE",
    "sg:address":"Kleine Eggestraat 1",
    "sg:city":"Zonhoven",
    "sg:classifiers":[
        {
            "category":"Health Services",
            "subcategory":"Dentist",
            "type":"Services"
        }
    ],
    "sg:phone":"+32 11 81 57 57",
    "sg:postcode":"3520",
    "sg:province":"Limburg",
    "wof:name":"Bielen E",
    "wof:placetype":"venue"
},
  "geometry": {"coordinates":[5.3678722382,50.9875411987],"type":"Point"}
}