{
  "type": "Feature",
  "properties": {
    "addr:full":"Avenue Jules Henin 28 Charleroi Hainaut 6000",
    "addr:housenumber":"28",
    "addr:postcode":"6000",
    "addr:street":"Avenue Jules Henin;Hainaut",
    "iso:country":"BE",
    "sg:address":"Avenue Jules Henin 28",
    "sg:city":"Charleroi",
    "sg:classifiers":[
        {
            "category":"Cafe",
            "type":"Food & Drink"
        }
    ],
    "sg:phone":"+32 71 30 41 03",
    "sg:postcode":"6000",
    "sg:province":"Hainaut",
    "sg:tags":[
        "snack-bars"
    ],
    "wof:name":"Lulu Et Natha (chez)",
    "wof:placetype":"venue"
},
  "geometry": {"coordinates":[4.4500641823,50.4169540405],"type":"Point"}
}