{
  "type": "Feature",
  "properties": {
    "iso:country":"BE",
    "sg:address":"Fritz Vinckelaan 192",
    "sg:city":"Bredene",
    "sg:orig_category":"Diensten voor huisdieren",
    "sg:phone":"+32 59 32 52 97",
    "sg:postcode":"8450",
    "sg:province":"West-Vlaanderen",
    "wof:name":"Trimca",
    "wof:placetype":"venue"
},
  "geometry": {"coordinates":[2.9694180489,51.2322807312],"type":"Point"}
}