{
  "type": "Feature",
  "properties": {
    "iso:country":"BE",
    "sg:address":"Venstraat 85",
    "sg:city":"Tongeren",
    "sg:orig_category":"Postkantoren Verzekeringsmakelaars and experts",
    "sg:phone":"+32 12 23 26 34",
    "sg:postcode":"3700",
    "sg:province":"Limburg",
    "wof:name":"De Post",
    "wof:placetype":"venue"
},
  "geometry": {"coordinates":[5.4955677986,50.7549629211],"type":"Point"}
}