{
  "type": "Feature",
  "properties": {
    "addr:full":"Vijverstraat 18 Sint-niklaas Oost-Vlaanderen 9111",
    "addr:housenumber":"18",
    "addr:postcode":"9111",
    "addr:street":"Vijverstraat",
    "iso:country":"BE",
    "sg:address":"Vijverstraat 18",
    "sg:city":"Sint-niklaas",
    "sg:classifiers":[
        {
            "category":"Cafe",
            "type":"Food & Drink"
        }
    ],
    "sg:phone":"+32 3 722 04 34",
    "sg:postcode":"9111",
    "sg:province":"Oost-Vlaanderen",
    "sg:tags":[
        "caf\u00e9s"
    ],
    "wof:name":"Ria Vereecken",
    "wof:placetype":"venue"
},
  "geometry": {"coordinates":[4.0836291313,51.1436042786],"type":"Point"}
}