{
  "type": "Feature",
  "properties": {
    "iso:country":"BE",
    "sg:address":"Spaanshoflaan 2",
    "sg:city":"Herentals",
    "sg:classifiers":[
        {
            "category":"Arena",
            "subcategory":"Sports Club",
            "type":"Entertainment"
        }
    ],
    "sg:phone":"+32 14 21 70 49",
    "sg:postcode":"2200",
    "sg:province":"Antwerpen",
    "sg:tags":[
        "de"
    ],
    "wof:name":"V.c. De Snepkens",
    "wof:placetype":"venue"
},
  "geometry": {"coordinates":[4.8412661552,51.186214447],"type":"Point"}
}