{
  "type": "Feature",
  "properties": {
    "addr:full":"Groendreef 99 Lokeren Oost-Vlaanderen 9160",
    "addr:housenumber":"99",
    "addr:postcode":"9160",
    "addr:street":"Groendreef",
    "iso:country":"BE",
    "sg:address":"Groendreef 99",
    "sg:city":"Lokeren",
    "sg:orig_category":"Huisdieren and benodigdheden Royal Canin",
    "sg:phone":"+32 9 348 00 04",
    "sg:postcode":"9160",
    "sg:province":"Oost-Vlaanderen",
    "wof:name":"Van Der Maelen",
    "wof:placetype":"venue"
},
  "geometry": {"coordinates":[3.9839639664,51.1104812622],"type":"Point"}
}