{
  "type": "Feature",
  "properties": {
    "addr:full":"Leuvenselaan 467 Tienen Vlaams-Brabant 3300",
    "addr:housenumber":"467",
    "addr:postcode":"3300",
    "addr:street":"Leuvenselaan",
    "iso:country":"BE",
    "sg:address":"Leuvenselaan 467",
    "sg:city":"Tienen",
    "sg:classifiers":[
        {
            "category":"Building & Trades",
            "subcategory":"Electrical",
            "type":"Services"
        }
    ],
    "sg:phone":"+32 16 82 46 31",
    "sg:postcode":"3300",
    "sg:province":"Vlaams-Brabant",
    "sg:tags":[
        "industrial",
        "-",
        "electric",
        "contractor"
    ],
    "wof:name":"Industrolek",
    "wof:placetype":"venue"
},
  "geometry": {"coordinates":[4.9088587761,50.8166351318],"type":"Point"}
}