{
  "type": "Feature",
  "properties": {
    "addr:full":"Antwerpsestraat 73 Lier Antwerpen 2500",
    "addr:housenumber":"73",
    "addr:postcode":"2500",
    "addr:street":"Antwerpsestraat",
    "iso:country":"BE",
    "sg:address":"Antwerpsestraat 73",
    "sg:city":"Lier",
    "sg:classifiers":[
        {
            "category":"Shopping",
            "subcategory":"Clothing, Apparel, & Fashions",
            "type":"Retail Goods"
        }
    ],
    "sg:phone":"+32 3 480 24 88",
    "sg:postcode":"2500",
    "sg:province":"Antwerpen",
    "sg:tags":[
        "-",
        "clothing",
        "child"
    ],
    "wof:name":"Pirouette",
    "wof:placetype":"venue"
},
  "geometry": {"coordinates":[4.5670747757,51.1335601807],"type":"Point"}
}