{
  "type": "Feature",
  "properties": {
    "iso:country":"BE",
    "sg:address":"Moorseelsestraat 144",
    "sg:city":"Kortrijk",
    "sg:classifiers":[
        {
            "category":"Cafe",
            "type":"Food & Drink"
        }
    ],
    "sg:phone":"+32 56 37 48 57",
    "sg:postcode":"8501",
    "sg:province":"West-Vlaanderen",
    "sg:tags":[
        "caf\u00e9s"
    ],
    "wof:name":"Wembley",
    "wof:placetype":"venue"
},
  "geometry": {"coordinates":[3.2458729744,50.8318138123],"type":"Point"}
}