{
  "type": "Feature",
  "properties": {
    "iso:country":"BE",
    "sg:address":"Chauss\u00e9e De Douai 11",
    "sg:city":"Rumes",
    "sg:classifiers":[
        {
            "category":"Retail",
            "subcategory":"Veterinary Services",
            "type":"Services"
        }
    ],
    "sg:phone":"+32 69 64 91 29",
    "sg:postcode":"7610",
    "sg:province":"Hainaut",
    "sg:tags":[
        "veterinarian"
    ],
    "wof:name":"Demortier J",
    "wof:placetype":"venue"
},
  "geometry": {"coordinates":[3.3112750053,50.556312561],"type":"Point"}
}