{
  "type": "Feature",
  "properties": {
    "addr:full":"Voskenslaan 450 Gent Oost-Vlaanderen 9000",
    "addr:housenumber":"450",
    "addr:postcode":"9000",
    "addr:street":"Voskenslaan;Oost-Vlaanderen",
    "iso:country":"BE",
    "sg:address":"Voskenslaan 450",
    "sg:city":"Gent",
    "sg:classifiers":[
        {
            "category":"Health Services",
            "subcategory":"Dentist",
            "type":"Services"
        }
    ],
    "sg:phone":"+32 9 222 66 17",
    "sg:postcode":"9000",
    "sg:province":"Oost-Vlaanderen",
    "wof:name":"Vuylsteek P",
    "wof:placetype":"venue"
},
  "geometry": {"coordinates":[3.7096180916,51.0266418457],"type":"Point"}
}