{
  "type": "Feature",
  "properties": {
    "addr:full":"Sint-jozefsstraat 41 Heusden-zolder Limburg 3550",
    "addr:housenumber":"41",
    "addr:postcode":"3550",
    "addr:street":"Sint-Jozefsstraat",
    "iso:country":"BE",
    "sg:address":"Sint-jozefsstraat 41",
    "sg:city":"Heusden-zolder",
    "sg:orig_category":"Gespecialiseerde residenti\u00eble bouw",
    "sg:phone":"+32 11 53 88 81",
    "sg:postcode":"3550",
    "sg:province":"Limburg",
    "wof:name":"Roger Vaes",
    "wof:placetype":"venue"
},
  "geometry": {"coordinates":[5.3188171387,51.0211524963],"type":"Point"}
}