{
  "type": "Feature",
  "properties": {
    "iso:country":"BE",
    "sg:address":"Brugsestr 1",
    "sg:city":"Oostkamp",
    "sg:classifiers":[
        {
            "category":"Banks & Credit Unions",
            "subcategory":"Bank",
            "type":"Services"
        }
    ],
    "sg:phone":"+32 50 82 37 71",
    "sg:postcode":"8020",
    "sg:province":"West-Vlaanderen",
    "wof:name":"Aslk-cger Bank",
    "wof:placetype":"venue"
},
  "geometry": {"coordinates":[3.2358300686,51.1553001404],"type":"Point"}
}