{
  "type": "Feature",
  "properties": {
    "addr:full":"Rue Hanoteau 18 Sombreffe Namur 5140",
    "addr:housenumber":"18",
    "addr:postcode":"5140",
    "addr:street":"Rue Hanoteau",
    "iso:country":"BE",
    "sg:address":"Rue Hanoteau 18",
    "sg:city":"Sombreffe",
    "sg:classifiers":[
        {
            "category":"Banks & Credit Unions",
            "subcategory":"Investment Brokerage",
            "type":"Services"
        }
    ],
    "sg:phone":"+32 71 88 87 05",
    "sg:postcode":"5140",
    "sg:province":"Namur",
    "sg:tags":[
        "-",
        "plastic"
    ],
    "wof:name":"Dubois Fr\u00e8res Sa",
    "wof:placetype":"venue"
},
  "geometry": {"coordinates":[4.6122050285,50.5253562927],"type":"Point"}
}