{
  "type": "Feature",
  "properties": {
    "addr:full":"Avenue Henri De Brouck\u00e8re 86 Bruxelles (auderghem) Bruxelles-Capitale 1160",
    "addr:housenumber":"86",
    "addr:postcode":"1160",
    "addr:street":"Avenue Henri De Broucke\u0300Re",
    "iso:country":"BE",
    "sg:address":"Avenue Henri De Brouck\u00e8re 86",
    "sg:city":"Bruxelles (auderghem)",
    "sg:classifiers":[
        {
            "category":"Building & Trades",
            "subcategory":"Plumbing",
            "type":"Services"
        }
    ],
    "sg:phone":"+32 2 672 80 81",
    "sg:postcode":"1160",
    "sg:province":"Bruxelles-Capitale",
    "sg:tags":[
        "contractor"
    ],
    "wof:name":"Steenacker P Sprl",
    "wof:placetype":"venue"
},
  "geometry": {"coordinates":[4.425465107,50.8187026978],"type":"Point"}
}