{
  "type": "Feature",
  "properties": {
    "iso:country":"BE",
    "sg:address":"Betekomsesteenweg 14 Box 2",
    "sg:city":"Begijnendijk",
    "sg:classifiers":[
        {
            "category":"Cafe",
            "type":"Food & Drink"
        }
    ],
    "sg:phone":"+32 16 52 04 08",
    "sg:postcode":"3130",
    "sg:province":"Vlaams-Brabant",
    "sg:tags":[
        "snack-bars"
    ],
    "wof:name":"Unal Snacks",
    "wof:placetype":"venue"
},
  "geometry": {"coordinates":[4.7832322121,51.0185317993],"type":"Point"}
}