{
  "type": "Feature",
  "properties": {
    "iso:country":"BE",
    "sg:address":"Zolderstraat 27",
    "sg:city":"Zwevegem (otegem)",
    "sg:classifiers":[
        {
            "category":"Building & Trades",
            "subcategory":"Landscaping Services",
            "type":"Services"
        }
    ],
    "sg:phone":"+32 56 77 51 50",
    "sg:postcode":"8553",
    "sg:province":"West-Vlaanderen",
    "sg:tags":[
        "gardening",
        "garden",
        "maintenance"
    ],
    "wof:name":"Destoop Frederic Bvba",
    "wof:placetype":"venue"
},
  "geometry": {"coordinates":[3.4145309925,50.8119354248],"type":"Point"}
}