{
  "type": "Feature",
  "properties": {
    "iso:country":"BE",
    "sg:address":"Rue De Wand 249",
    "sg:city":"Brussel/bruxelles",
    "sg:orig_category":"Instituts de beaut\u00e9. Parfumeries. Centres de relaxation and bien-\u00eatre",
    "sg:phone":"+32 2 262 12 59",
    "sg:postcode":"1020",
    "sg:province":"Bruxelles-Capitale",
    "wof:name":"Yves Rocher",
    "wof:placetype":"venue"
},
  "geometry": {"coordinates":[4.3606281281,50.90076828],"type":"Point"}
}