{
  "type": "Feature",
  "properties": {
    "addr:full":"Banierstraat 2 Gent Oost-Vlaanderen 9000",
    "addr:housenumber":"2",
    "addr:postcode":"9000",
    "addr:street":"Banierstraat;Oost-Vlaanderen",
    "iso:country":"BE",
    "sg:address":"Banierstraat 2",
    "sg:city":"Gent",
    "sg:orig_category":"Entretien and r\u00e9parations de voitures",
    "sg:phone":"+32 9 228 71 99",
    "sg:postcode":"9000",
    "sg:province":"Oost-Vlaanderen",
    "wof:name":"De Mobiele Garagist",
    "wof:placetype":"venue"
},
  "geometry": {"coordinates":[3.7448740005,51.0549278259],"type":"Point"}
}