{
  "type": "Feature",
  "properties": {
    "iso:country":"BE",
    "sg:address":"Kasteellaan",
    "sg:city":"Veurne (de Moeren)",
    "sg:classifiers":[
        {
            "category":"Professional",
            "subcategory":"Art Services",
            "type":"Services"
        }
    ],
    "sg:phone":"+32 58 31 27 02",
    "sg:postcode":"8630",
    "sg:province":"West-Vlaanderen",
    "sg:tags":[
        "-",
        "furniture"
    ],
    "wof:name":"Ardies Import Nv",
    "wof:placetype":"venue"
},
  "geometry": {"coordinates":[2.6049950123,51.0369949341],"type":"Point"}
}