{
  "type": "Feature",
  "properties": {
    "addr:full":"Rue Du Mail 50 Ixelles Bruxelles-Capitale 1050",
    "addr:housenumber":"50",
    "addr:postcode":"1050",
    "addr:street":"Rue Du Mail",
    "iso:country":"BE",
    "sg:address":"Rue Du Mail 50",
    "sg:city":"Ixelles",
    "sg:orig_category":"V\u00e9hicules automobiles",
    "sg:phone":"+32 2 756 82 11",
    "sg:postcode":"1050",
    "sg:province":"Bruxelles-Capitale",
    "wof:name":"Importateur D'ieteren",
    "wof:placetype":"venue"
},
  "geometry": {"coordinates":[4.3595142365,50.8218078613],"type":"Point"}
}