{
  "type": "Feature",
  "properties": {
    "iso:country":"BE",
    "sg:address":"Vredebaan 36",
    "sg:city":"Mortsel",
    "sg:orig_category":"Modellenbureaus",
    "sg:phone":"+32 3 440 68 64",
    "sg:postcode":"2640",
    "sg:province":"Antwerpen",
    "wof:name":"Fly Look",
    "wof:placetype":"venue"
},
  "geometry": {"coordinates":[4.4415378571,51.1725082397],"type":"Point"}
}