{
  "type": "Feature",
  "properties": {
    "addr:full":"Avenue Adolphe Buyl 56 Bruxelles (ixelles) Bruxelles-Capitale 1050",
    "addr:housenumber":"56",
    "addr:postcode":"1050",
    "addr:street":"Avenue Adolphe Buyl",
    "iso:country":"BE",
    "sg:address":"Avenue Adolphe Buyl 56",
    "sg:city":"Bruxelles (ixelles)",
    "sg:classifiers":[
        {
            "category":"Home & Garden",
            "subcategory":"Building Materials",
            "type":"Retail Goods"
        }
    ],
    "sg:postcode":"1050",
    "sg:province":"Bruxelles-Capitale",
    "sg:tags":[
        "water",
        "heater"
    ],
    "wof:name":"Michel Vandendriessche",
    "wof:placetype":"venue"
},
  "geometry": {"coordinates":[4.3813180923,50.8172225952],"type":"Point"}
}