{
  "type": "Feature",
  "properties": {
    "addr:full":"Rue Du Tirogne 56 Grace-hollogne Li\u00e8ge 4460",
    "addr:housenumber":"56",
    "addr:postcode":"4460",
    "addr:street":"Rue Du Tirogne",
    "iso:country":"BE",
    "sg:address":"Rue Du Tirogne 56",
    "sg:city":"Grace-hollogne",
    "sg:orig_category":"Services de Nettoyage and de D\u00e9sinfection. Plomberie, chauffage and installations sanitaires",
    "sg:phone":"+32 4 233 42 91",
    "sg:postcode":"4460",
    "sg:province":"Li\u00e8ge",
    "wof:name":"Marc Basile",
    "wof:placetype":"venue"
},
  "geometry": {"coordinates":[5.4728741646,50.6322479248],"type":"Point"}
}