{
  "type": "Feature",
  "properties": {
    "addr:full":"Rue Haute 21 Vise Li\u00e8ge 4600",
    "addr:housenumber":"21",
    "addr:postcode":"4600",
    "addr:street":"Rue Haute",
    "iso:country":"BE",
    "sg:address":"Rue Haute 21",
    "sg:city":"Vise",
    "sg:orig_category":"Diverse voedingsmiddelen Gh",
    "sg:phone":"+32 4 379 18 81",
    "sg:postcode":"4600",
    "sg:province":"Li\u00e8ge",
    "wof:name":"Humblet F.",
    "wof:placetype":"venue"
},
  "geometry": {"coordinates":[5.6959109306,50.7345619202],"type":"Point"}
}