{
  "type": "Feature",
  "properties": {
    "addr:full":"Avenue De L'h\u00e9lice 8 Bruxelles (woluwe-saint-pierre) Bruxelles-Capitale 1150",
    "addr:housenumber":"8",
    "addr:postcode":"1150",
    "addr:street":"Avenue De L'He \u0301Lice",
    "iso:country":"BE",
    "sg:address":"Avenue De L'h\u00e9lice 8",
    "sg:city":"Bruxelles (woluwe-saint-pierre)",
    "sg:classifiers":[
        {
            "category":"Utilities",
            "subcategory":"Natural Gas",
            "type":"Services"
        }
    ],
    "sg:phone":"+32 2 772 02 09",
    "sg:postcode":"1150",
    "sg:province":"Bruxelles-Capitale",
    "sg:tags":[
        "filter",
        "-",
        "liquid"
    ],
    "wof:name":"Anthena Sa",
    "wof:placetype":"venue"
},
  "geometry": {"coordinates":[4.4521298409,50.8340377808],"type":"Point"}
}