{
  "type": "Feature",
  "properties": {
    "iso:country":"BE",
    "sg:address":"Abelenlaan 22",
    "sg:city":"Kontich",
    "sg:orig_category":"Entretien and r\u00e9parations de machines de bureau and ordinateurs",
    "sg:phone":"+32 3 457 95 78",
    "sg:postcode":"2550",
    "sg:province":"Antwerpen",
    "wof:name":"Herdis",
    "wof:placetype":"venue"
},
  "geometry": {"coordinates":[4.4484438896,51.1426620483],"type":"Point"}
}