{
  "type": "Feature",
  "properties": {
    "addr:full":"Eeuwfeestlaan 54 De Pinte Oost-Vlaanderen 9840",
    "addr:housenumber":"54",
    "addr:postcode":"9840",
    "addr:street":"Eeuwfeestlaan",
    "iso:country":"BE",
    "sg:address":"Eeuwfeestlaan 54",
    "sg:city":"De Pinte",
    "sg:classifiers":[
        {
            "category":"Health Services",
            "subcategory":"Doctor",
            "type":"Services"
        }
    ],
    "sg:phone":"+32 9 282 61 20",
    "sg:postcode":"9840",
    "sg:province":"Oost-Vlaanderen",
    "sg:tags":[
        "medicinephysicians",
        "surgeon"
    ],
    "wof:name":"Lontie A-m",
    "wof:placetype":"venue"
},
  "geometry": {"coordinates":[3.6503789425,50.9903831482],"type":"Point"}
}