{
  "type": "Feature",
  "properties": {
    "iso:country":"BE",
    "sg:address":"Grevensmolenw 28",
    "sg:city":"St. Truiden",
    "sg:classifiers":[
        {
            "category":"Banks & Credit Unions",
            "subcategory":"Bank",
            "type":"Services"
        }
    ],
    "sg:phone":"+32 11 68 33 90",
    "sg:postcode":"3800",
    "sg:province":"Limburg",
    "wof:name":"Caisse Nationale De, Cr\u00e9dit Professionnel",
    "wof:placetype":"venue"
},
  "geometry": {"coordinates":[5.17497015,50.8218193054],"type":"Point"}
}