{
  "type": "Feature",
  "properties": {
    "iso:country":"BE",
    "sg:address":"Doornveld 1",
    "sg:city":"Zellik",
    "sg:classifiers":[
        {
            "category":"Home & Garden",
            "subcategory":"Carpets & Floor Coverings",
            "type":"Retail Goods"
        }
    ],
    "sg:phone":"+32 2 467 60 50",
    "sg:postcode":"1731",
    "sg:province":"Vlaams-Brabant",
    "sg:tags":[
        "appliance",
        "cleaning"
    ],
    "wof:name":"Nilfisk S.a.",
    "wof:placetype":"venue"
},
  "geometry": {"coordinates":[4.2581400871,50.8911552429],"type":"Point"}
}