{
  "type": "Feature",
  "properties": {
    "addr:full":"Alfred Algoetstraat 67a Lennik Vlaams-Brabant 1750",
    "addr:housenumber":"67a;1750",
    "addr:street":"Algoetstraat;Vlaams-Brabant",
    "iso:country":"BE",
    "sg:address":"Alfred Algoetstraat 67a",
    "sg:city":"Lennik",
    "sg:orig_category":"Herstellingen and onderhoud van auto's Voertuigen",
    "sg:phone":"+32 2 532 41 17",
    "sg:postcode":"1750",
    "sg:province":"Vlaams-Brabant",
    "wof:name":"Garage De Schuyffelleer",
    "wof:placetype":"venue"
},
  "geometry": {"coordinates":[4.1609268188,50.806892395],"type":"Point"}
}