{
  "type": "Feature",
  "properties": {
    "iso:country":"BE",
    "sg:address":"Rue De La Loi 59",
    "sg:city":"Chatelet",
    "sg:classifiers":[
        {
            "category":"Personal",
            "subcategory":"Beauty Salon",
            "type":"Services"
        }
    ],
    "sg:phone":"+32 71 38 08 19",
    "sg:postcode":"6200",
    "sg:province":"Hainaut",
    "sg:tags":[
        "de",
        "coiffure"
    ],
    "wof:name":"Magali",
    "wof:placetype":"venue"
},
  "geometry": {"coordinates":[4.5123620033,50.4138755798],"type":"Point"}
}