{
  "type": "Feature",
  "properties": {
    "iso:country":"BE",
    "sg:address":"Route De Frasnes 102",
    "sg:city":"Ath",
    "sg:orig_category":"Rundveehouders",
    "sg:phone":"+32 68 28 23 90",
    "sg:postcode":"7812",
    "sg:province":"Hainaut",
    "wof:name":"Andre Scops",
    "wof:placetype":"venue"
},
  "geometry": {"coordinates":[3.6734309196,50.6524047852],"type":"Point"}
}