{
  "type": "Feature",
  "properties": {
    "addr:full":"Mieregemstraat 74 Merchtem Vlaams-Brabant 1785",
    "addr:housenumber":"74",
    "addr:postcode":"1785",
    "addr:street":"Mieregemstraat",
    "iso:country":"BE",
    "sg:address":"Mieregemstraat 74",
    "sg:city":"Merchtem",
    "sg:classifiers":[
        {
            "category":"Bars & Pubs",
            "type":"Food & Drink"
        }
    ],
    "sg:phone":"+32 52 37 41 30",
    "sg:postcode":"1785",
    "sg:province":"Vlaams-Brabant",
    "wof:name":"Eendracht (den)",
    "wof:placetype":"venue"
},
  "geometry": {"coordinates":[4.2313089371,50.9532241821],"type":"Point"}
}