{
  "type": "Feature",
  "properties": {
    "addr:full":"Bosstraat 112 Boom Antwerpen 2850",
    "addr:housenumber":"112",
    "addr:postcode":"2850",
    "addr:street":"Bosstraat",
    "iso:country":"BE",
    "sg:address":"Bosstraat 112",
    "sg:city":"Boom",
    "sg:orig_category":"Catering and organisation de f\u00eates",
    "sg:phone":"+32 3 844 33 40",
    "sg:postcode":"2850",
    "sg:province":"Antwerpen",
    "wof:name":"Traiteur Terberghe",
    "wof:placetype":"venue"
},
  "geometry": {"coordinates":[4.3875842094,51.0862121582],"type":"Point"}
}