{
  "type": "Feature",
  "properties": {
    "iso:country":"BE",
    "sg:address":"Rue Victor Libert 8",
    "sg:city":"Marche-en-famenne",
    "sg:classifiers":[
        {
            "category":"Professional",
            "subcategory":"Lawyer & Legal Services",
            "type":"Services"
        }
    ],
    "sg:phone":"+32 84 31 20 13",
    "sg:postcode":"6900",
    "sg:province":"Luxembourg",
    "wof:name":"Picard F",
    "wof:placetype":"venue"
},
  "geometry": {"coordinates":[5.3407678604,50.2276611328],"type":"Point"}
}