{
  "type": "Feature",
  "properties": {
    "iso:country":"BE",
    "sg:address":"Rue Du Longtry 51",
    "sg:city":"Charleroi (mont-sur-marchienne)",
    "sg:classifiers":[
        {
            "category":"Health Services",
            "subcategory":"Health Practitioner",
            "type":"Services"
        }
    ],
    "sg:phone":"+32 71 43 31 97",
    "sg:postcode":"6032",
    "sg:province":"Hainaut",
    "sg:tags":[
        "physiotherapist"
    ],
    "wof:name":"Ruelle Henri-eric",
    "wof:placetype":"venue"
},
  "geometry": {"coordinates":[4.4068617821,50.3728866577],"type":"Point"}
}