{
  "type": "Feature",
  "properties": {
    "addr:full":"Chauss\u00e9e De Ninove 503 Bruxelles (anderlecht) Bruxelles-Capitale 1070",
    "addr:housenumber":"503",
    "addr:postcode":"1070",
    "addr:street":"Chausse\u0301E De Ninove",
    "iso:country":"BE",
    "sg:address":"Chauss\u00e9e De Ninove 503",
    "sg:city":"Bruxelles (anderlecht)",
    "sg:classifiers":[
        {
            "category":"Bars & Pubs",
            "type":"Food & Drink"
        }
    ],
    "sg:phone":"+32 2 411 31 79",
    "sg:postcode":"1070",
    "sg:province":"Bruxelles-Capitale",
    "sg:tags":[
        "tavern"
    ],
    "wof:name":"Terminus (le)",
    "wof:placetype":"venue"
},
  "geometry": {"coordinates":[4.3149647713,50.8482666016],"type":"Point"}
}