{
  "type": "Feature",
  "properties": {
    "addr:full":"Stationsstraat 62 Wichelen Oost-Vlaanderen 9260",
    "addr:housenumber":"62",
    "addr:postcode":"9260",
    "addr:street":"Stationsstraat",
    "iso:country":"BE",
    "sg:address":"Stationsstraat 62",
    "sg:city":"Wichelen",
    "sg:orig_category":"Boekhouders Verzekeringsmakelaars and experts",
    "sg:phone":"+32 9 369 33 76",
    "sg:postcode":"9260",
    "sg:province":"Oost-Vlaanderen",
    "wof:name":"Arnold Stroobant",
    "wof:placetype":"venue"
},
  "geometry": {"coordinates":[3.9255440235,51.00963974],"type":"Point"}
}