{
  "type": "Feature",
  "properties": {
    "iso:country":"BE",
    "sg:address":"Rue De Fierlant 5",
    "sg:city":"Bruxelles (forest)",
    "sg:classifiers":[
        {
            "category":"Bars & Pubs",
            "type":"Food & Drink"
        }
    ],
    "sg:phone":"+32 2 538 61 97",
    "sg:postcode":"1190",
    "sg:province":"Bruxelles-Capitale",
    "wof:name":"Tout Va Bien",
    "wof:placetype":"venue"
},
  "geometry": {"coordinates":[4.3307180405,50.8279495239],"type":"Point"}
}