{
  "type": "Feature",
  "properties": {
    "iso:country":"BE",
    "sg:address":"Helstraat 58",
    "sg:city":"Kortessem",
    "sg:orig_category":"Equipement divers pour commerces Eclairage et \u00e9quipements du foyer",
    "sg:phone":"+32 11 37 78 46",
    "sg:postcode":"3721",
    "sg:province":"Limburg",
    "wof:name":"Josse Meekers",
    "wof:placetype":"venue"
},
  "geometry": {"coordinates":[5.4254732132,50.8735122681],"type":"Point"}
}