{
  "type": "Feature",
  "properties": {
    "addr:full":"Van Roystraat 7 Lint Antwerpen 2547",
    "addr:housenumber":"7",
    "addr:postcode":"2547",
    "addr:street":"Roystraat",
    "iso:country":"BE",
    "sg:address":"Van Roystraat 7",
    "sg:city":"Lint",
    "sg:orig_category":"Sportclubs",
    "sg:phone":"+32 3 454 07 85",
    "sg:postcode":"2547",
    "sg:province":"Antwerpen",
    "wof:name":"T.c. A.c.w. 62",
    "wof:placetype":"venue"
},
  "geometry": {"coordinates":[4.4831790924,51.1337585449],"type":"Point"}
}