{
  "type": "Feature",
  "properties": {
    "addr:full":"Sint-jansstraat 54 Sint-laureins Oost-Vlaanderen 9982",
    "addr:housenumber":"54",
    "addr:postcode":"9982",
    "addr:street":"Sint-Jansstraat",
    "iso:country":"BE",
    "sg:address":"Sint-jansstraat 54",
    "sg:city":"Sint-laureins",
    "sg:classifiers":[
        {
            "category":"Insurance",
            "subcategory":"Insurance Agent",
            "type":"Services"
        }
    ],
    "sg:phone":"+32 9 379 94 40",
    "sg:postcode":"9982",
    "sg:province":"Oost-Vlaanderen",
    "sg:tags":[
        "verzekeringsmakelaars",
        "expert"
    ],
    "wof:name":"Johan Francque",
    "wof:placetype":"venue"
},
  "geometry": {"coordinates":[3.5959920883,51.2484054565],"type":"Point"}
}