{
  "type": "Feature",
  "properties": {
    "iso:country":"BE",
    "sg:address":"Rue Wilson 189",
    "sg:city":"Colfontaine (wasmes)",
    "sg:classifiers":[
        {
            "category":"Bars & Pubs",
            "type":"Food & Drink"
        }
    ],
    "sg:phone":"+32 65 67 61 48",
    "sg:postcode":"7340",
    "sg:province":"Hainaut",
    "wof:name":"Cercle Ouvrier (le)",
    "wof:placetype":"venue"
},
  "geometry": {"coordinates":[3.8333649635,50.4082717896],"type":"Point"}
}