{
  "type": "Feature",
  "properties": {
    "addr:full":"Rue De Damr\u00e9 36 Sprimont Li\u00e8ge 4140",
    "addr:housenumber":"36",
    "addr:postcode":"4140",
    "addr:street":"Rue De Damre\u0301",
    "iso:country":"BE",
    "sg:address":"Rue De Damr\u00e9 36",
    "sg:city":"Sprimont",
    "sg:classifiers":[
        {
            "category":"Retail",
            "subcategory":"Veterinary Services",
            "type":"Services"
        }
    ],
    "sg:phone":"+32 4 382 16 43",
    "sg:postcode":"4140",
    "sg:province":"Li\u00e8ge",
    "sg:tags":[
        "veterinarian"
    ],
    "wof:name":"Pirard M",
    "wof:placetype":"venue"
},
  "geometry": {"coordinates":[5.6687088013,50.5043716431],"type":"Point"}
}