{
  "type": "Feature",
  "properties": {
    "iso:country":"BE",
    "sg:address":"Brugsestraat 70",
    "sg:city":"Zedelgem",
    "sg:orig_category":"Bagage and lederwaren Herstelling leer and schoeisel Schoenen",
    "sg:phone":"+32 50 24 04 70",
    "sg:postcode":"8211",
    "sg:province":"West-Vlaanderen",
    "wof:name":"Huis Van De Populiere",
    "wof:placetype":"venue"
},
  "geometry": {"coordinates":[3.0889649391,51.1200408936],"type":"Point"}
}