{
  "type": "Feature",
  "properties": {
    "iso:country":"BE",
    "sg:address":"Dorpstraat 135",
    "sg:city":"Zwijndrecht (burcht)",
    "sg:classifiers":[
        {
            "category":"Education",
            "subcategory":"School",
            "type":"Public Place"
        }
    ],
    "sg:phone":"+32 3 253 19 20",
    "sg:postcode":"2070",
    "sg:province":"Antwerpen",
    "sg:tags":[
        "-",
        "furniture"
    ],
    "wof:name":"Van Gastel Bvba",
    "wof:placetype":"venue"
},
  "geometry": {"coordinates":[4.3424091339,51.2022590637],"type":"Point"}
}