{
  "type": "Feature",
  "properties": {
    "addr:full":"Rue Du Ch\u00c2telain 40 Elsene/ixelles Bruxelles-Capitale 1050",
    "addr:housenumber":"40",
    "addr:postcode":"1050",
    "addr:street":"Rue Du Cha\u0302Telain",
    "iso:country":"BE",
    "sg:address":"Rue Du Ch\u00c2telain 40",
    "sg:city":"Elsene/ixelles",
    "sg:orig_category":"Antiquit\u00e9s",
    "sg:phone":"+32 2 647 48 80",
    "sg:postcode":"1050",
    "sg:province":"Bruxelles-Capitale",
    "wof:name":"Maison Cassandre",
    "wof:placetype":"venue"
},
  "geometry": {"coordinates":[4.3619179726,50.8253135681],"type":"Point"}
}