{
  "type": "Feature",
  "properties": {
    "iso:country":"BE",
    "sg:address":"Lieven De Winnestraat 44",
    "sg:city":"Gent",
    "sg:orig_category":"Instruments de musique. Enseignement artistique",
    "sg:phone":"+32 9 233 26 35",
    "sg:postcode":"9000",
    "sg:province":"Oost-Vlaanderen",
    "wof:name":"F.ketels",
    "wof:placetype":"venue"
},
  "geometry": {"coordinates":[3.7141780853,51.0489273071],"type":"Point"}
}