{
  "type": "Feature",
  "properties": {
    "iso:country":"BE",
    "sg:address":"Hageveldstraat 11",
    "sg:city":"Denderleeuw",
    "sg:orig_category":"Ordinateurs and \u00e9quipement informatique",
    "sg:phone":"+32 53 66 23 50",
    "sg:postcode":"9470",
    "sg:province":"Oost-Vlaanderen",
    "wof:name":"C.s.a.",
    "wof:placetype":"venue"
},
  "geometry": {"coordinates":[4.0760121346,50.8745994568],"type":"Point"}
}