{
  "type": "Feature",
  "properties": {
    "addr:full":"Het Blok 6 Wuustwezel Antwerpen 2990",
    "addr:housenumber":"6",
    "addr:postcode":"2990",
    "addr:street":"Het Blok",
    "iso:country":"BE",
    "sg:address":"Het Blok 6",
    "sg:city":"Wuustwezel",
    "sg:orig_category":"M\u00e9decins and sp\u00e9cialistes",
    "sg:phone":"+32 3 669 77 06",
    "sg:postcode":"2990",
    "sg:province":"Antwerpen",
    "wof:name":"E. Voet",
    "wof:placetype":"venue"
},
  "geometry": {"coordinates":[4.599755764,51.3912582397],"type":"Point"}
}