{
  "type": "Feature",
  "properties": {
    "addr:full":"Ferme Des Douze Bonniers 1 Grez-doiceau Brabant Wallon 1390",
    "addr:housenumber":"1",
    "addr:postcode":"1390",
    "addr:street":"Bonniers",
    "iso:country":"BE",
    "sg:address":"Ferme Des Douze Bonniers 1",
    "sg:city":"Grez-doiceau",
    "sg:orig_category":"Zuivelproducten",
    "sg:phone":"+32 10 86 64 11",
    "sg:postcode":"1390",
    "sg:province":"Brabant Wallon",
    "wof:name":"Ferme Des 12 Bonniers",
    "wof:placetype":"venue"
},
  "geometry": {"coordinates":[4.6916098595,50.7895011902],"type":"Point"}
}