{
  "type": "Feature",
  "properties": {
    "iso:country":"BE",
    "sg:address":"Vrijheidslaan 18",
    "sg:city":"Gent",
    "sg:orig_category":"Artsen and specialisten",
    "sg:phone":"+32 9 220 79 69",
    "sg:postcode":"9000",
    "sg:province":"Oost-Vlaanderen",
    "wof:name":"M. Geerts",
    "wof:placetype":"venue"
},
  "geometry": {"coordinates":[3.7210609913,51.0297851562],"type":"Point"}
}