{
  "type": "Feature",
  "properties": {
    "iso:country":"BE",
    "sg:address":"Jacques Callaertslaan 6",
    "sg:city":"Meise",
    "sg:classifiers":[
        {
            "category":"Insurance",
            "subcategory":"Insurance Agent",
            "type":"Services"
        }
    ],
    "sg:phone":"+32 2 269 29 37",
    "sg:postcode":"1860",
    "sg:province":"Vlaams-Brabant",
    "sg:tags":[
        "verzekeringsmakelaars",
        "expert"
    ],
    "wof:name":"H. Vervaecke",
    "wof:placetype":"venue"
},
  "geometry": {"coordinates":[4.315554142,50.9376564026],"type":"Point"}
}