{
  "type": "Feature",
  "properties": {
    "iso:country":"BE",
    "sg:address":"Statielei 39",
    "sg:city":"Mortsel",
    "sg:orig_category":"Herenkledingzaken",
    "sg:phone":"+32 3 449 13 31",
    "sg:postcode":"2640",
    "sg:province":"Antwerpen",
    "wof:name":"Daveli",
    "wof:placetype":"venue"
},
  "geometry": {"coordinates":[4.4513077736,51.1707801819],"type":"Point"}
}