{
  "type": "Feature",
  "properties": {
    "addr:full":"Rue De Stassart 119 Bruxelles (ixelles) Bruxelles-Capitale 1050",
    "addr:housenumber":"119",
    "addr:postcode":"1050",
    "addr:street":"Rue De Stassart",
    "iso:country":"BE",
    "sg:address":"Rue De Stassart 119",
    "sg:city":"Bruxelles (ixelles)",
    "sg:classifiers":[
        {
            "category":"Education",
            "subcategory":"University",
            "type":"Public Place"
        }
    ],
    "sg:phone":"+32 2 513 83 32",
    "sg:postcode":"1050",
    "sg:province":"Bruxelles-Capitale",
    "sg:tags":[
        "higher"
    ],
    "wof:name":"Coimbra Group",
    "wof:placetype":"venue"
},
  "geometry": {"coordinates":[4.3585238457,50.8342132568],"type":"Point"}
}