{
  "type": "Feature",
  "properties": {
    "iso:country":"BE",
    "sg:address":"Henri Jansseunestraat 10",
    "sg:city":"Middelkerke",
    "sg:orig_category":"Etalage- and showroomontwerpers",
    "sg:phone":"+32 59 30 35 94",
    "sg:postcode":"8433",
    "sg:province":"West-Vlaanderen",
    "wof:name":"Marleen Willaert",
    "wof:placetype":"venue"
},
  "geometry": {"coordinates":[2.8452999592,51.1544189453],"type":"Point"}
}