{
  "type": "Feature",
  "properties": {
    "iso:country":"BE",
    "sg:address":"39 Rte De Li\u00e8ge",
    "sg:city":"Terwagne",
    "sg:classifiers":[
        {
            "category":"Manufacturing",
            "subcategory":"Chemicals & Compounds",
            "type":"Manufacturing & Wholesale Goods"
        }
    ],
    "sg:phone":"+32 85 41 11 62",
    "sg:postcode":"4560",
    "sg:province":"Li\u00e8ge",
    "sg:tags":[
        "pharmaceutical",
        "chemistry",
        "-",
        "by-product"
    ],
    "wof:name":"Ets Blockx Fils Sa",
    "wof:placetype":"venue"
},
  "geometry": {"coordinates":[5.3525500298,50.4493598938],"type":"Point"}
}