{
  "type": "Feature",
  "properties": {
    "iso:country":"BE",
    "sg:address":"Clos De Kilmarnock 12",
    "sg:city":"Herstal",
    "sg:orig_category":"Boekhouders",
    "sg:phone":"+32 4 248 21 67",
    "sg:postcode":"4040",
    "sg:province":"Li\u00e8ge",
    "wof:name":"Georges Smets",
    "wof:placetype":"venue"
},
  "geometry": {"coordinates":[5.6238350868,50.6789207458],"type":"Point"}
}