{
  "type": "Feature",
  "properties": {
    "iso:country":"BE",
    "sg:address":"De Ribaucourtstraat 56",
    "sg:city":"Sint-jans-molenbeek/molenbeek-saint-jean",
    "sg:orig_category":"HERSTELLING ELEKTRISCHE HUISHOUDAPPARATEN Huishoudapparaten, televisies and radio's",
    "sg:phone":"+32 2 414 16 08",
    "sg:postcode":"1080",
    "sg:province":"Bruxelles-Capitale",
    "wof:name":"Daniel Duwyn/d. Duwyn",
    "wof:placetype":"venue"
},
  "geometry": {"coordinates":[4.3398098946,50.8585205078],"type":"Point"}
}