{
  "type": "Feature",
  "properties": {
    "addr:full":"Dorpsstraat 64 F Booischot Vlaams-Brabant 3150",
    "addr:housenumber":"64 f",
    "addr:postcode":"3150",
    "addr:street":"Dorpsstraat",
    "iso:country":"BE",
    "sg:address":"Dorpsstraat 64 F",
    "sg:city":"Booischot",
    "sg:classifiers":[
        {
            "category":"Banks & Credit Unions",
            "subcategory":"Bank",
            "type":"Services"
        }
    ],
    "sg:phone":"+32 15 22 33 28",
    "sg:postcode":"3150",
    "sg:province":"Vlaams-Brabant",
    "wof:name":"Aslk-cger Bank",
    "wof:placetype":"venue"
},
  "geometry": {"coordinates":[4.6434550285,50.9456558228],"type":"Point"}
}