{
  "type": "Feature",
  "properties": {
    "addr:full":"Breendonkstraat 116 Willebroek Antwerpen 2830",
    "addr:housenumber":"116",
    "addr:postcode":"2830",
    "addr:street":"Breendonkstraat",
    "iso:country":"BE",
    "sg:address":"Breendonkstraat 116",
    "sg:city":"Willebroek",
    "sg:classifiers":[
        {
            "category":"Building & Trades",
            "subcategory":"Construction",
            "type":"Services"
        }
    ],
    "sg:phone":"+32 3 886 21 51",
    "sg:postcode":"2830",
    "sg:province":"Antwerpen",
    "sg:tags":[
        "ceiling"
    ],
    "wof:name":"Van Kerchove Bvba",
    "wof:placetype":"venue"
},
  "geometry": {"coordinates":[4.3490071297,51.0527076721],"type":"Point"}
}