{
  "type": "Feature",
  "properties": {
    "addr:full":"Slaveweg 3 Zottegem (strijpen) Oost-Vlaanderen 9620",
    "addr:housenumber":"3",
    "addr:postcode":"9620",
    "addr:street":"Slaveweg",
    "iso:country":"BE",
    "sg:address":"Slaveweg 3",
    "sg:city":"Zottegem (strijpen)",
    "sg:classifiers":[
        {
            "category":"Farming",
            "subcategory":"Crops",
            "type":"Manufacturing & Wholesale Goods"
        }
    ],
    "sg:phone":"+32 9 361 11 46",
    "sg:postcode":"9620",
    "sg:province":"Oost-Vlaanderen",
    "sg:tags":[
        "vegetable",
        "fruit",
        "-",
        "grower"
    ],
    "wof:name":"Coppens J",
    "wof:placetype":"venue"
},
  "geometry": {"coordinates":[3.8012890816,50.8756065369],"type":"Point"}
}