{
  "type": "Feature",
  "properties": {
    "iso:country":"BE",
    "sg:address":"Collemansbrug 15",
    "sg:city":"Moerbeke",
    "sg:orig_category":"Rundveehouders",
    "sg:phone":"+32 9 346 61 85",
    "sg:postcode":"9180",
    "sg:province":"Oost-Vlaanderen",
    "wof:name":"Johan Van Damme",
    "wof:placetype":"venue"
},
  "geometry": {"coordinates":[3.9277009964,51.1793823242],"type":"Point"}
}