{
  "type": "Feature",
  "properties": {
    "iso:country":"BE",
    "sg:address":"Rue Saint-gilles 46",
    "sg:city":"Saint-hubert",
    "sg:orig_category":"Foto-uitrusting Fotografen and fotostudio's",
    "sg:phone":"+32 61 61 17 28",
    "sg:postcode":"6870",
    "sg:province":"Luxembourg",
    "wof:name":"Studio Philippe",
    "wof:placetype":"venue"
},
  "geometry": {"coordinates":[5.3714118004,50.0259132385],"type":"Point"}
}