{
  "type": "Feature",
  "properties": {
    "addr:full":"Rue Henri Van Zuylen 13 Ukkel/uccle Bruxelles-Capitale 1180",
    "addr:housenumber":"13",
    "addr:postcode":"1180",
    "addr:street":"Rue Henri Van Zuylen;/",
    "iso:country":"BE",
    "sg:address":"Rue Henri Van Zuylen 13",
    "sg:city":"Ukkel/uccle",
    "sg:classifiers":[
        {
            "category":"Arena",
            "subcategory":"Sports Club",
            "type":"Entertainment"
        }
    ],
    "sg:phone":"+32 2 332 45 26",
    "sg:postcode":"1180",
    "sg:province":"Bruxelles-Capitale",
    "sg:tags":[
        "de"
    ],
    "wof:name":"Claes Olivier",
    "wof:placetype":"venue"
},
  "geometry": {"coordinates":[4.3368887901,50.7978210449],"type":"Point"}
}