{
  "type": "Feature",
  "properties": {
    "iso:country":"BE",
    "sg:address":"Bormanstraat 40",
    "sg:city":"Bocholt",
    "sg:orig_category":"Installation \u00e9lectrique r\u00e9sidentielle",
    "sg:phone":"+32 89 46 62 83",
    "sg:postcode":"3950",
    "sg:province":"Limburg",
    "wof:name":"Stijn Geunis",
    "wof:placetype":"venue"
},
  "geometry": {"coordinates":[5.5708031654,51.1528701782],"type":"Point"}
}