{
  "type": "Feature",
  "properties": {
    "addr:full":"Leopoldlaan 10 Mol Antwerpen 2400",
    "addr:housenumber":"10",
    "addr:postcode":"2400",
    "addr:street":"Leopoldlaan",
    "iso:country":"BE",
    "sg:address":"Leopoldlaan 10",
    "sg:city":"Mol",
    "sg:orig_category":"Artsen and specialisten",
    "sg:phone":"+32 14 58 94 18",
    "sg:postcode":"2400",
    "sg:province":"Antwerpen",
    "wof:name":"Johan Van Hove",
    "wof:placetype":"venue"
},
  "geometry": {"coordinates":[5.0413107872,51.2094116211],"type":"Point"}
}