{
  "type": "Feature",
  "properties": {
    "iso:country":"BE",
    "sg:address":"Groenestraat 58",
    "sg:city":"Ieper (sint-jan)",
    "sg:classifiers":[
        {
            "category":"Real Estate",
            "subcategory":"Real Estate Services",
            "type":"Services"
        }
    ],
    "sg:phone":"+32 57 21 74 28",
    "sg:postcode":"8900",
    "sg:province":"West-Vlaanderen",
    "wof:name":"Sudeco",
    "wof:placetype":"venue"
},
  "geometry": {"coordinates":[2.8988258839,50.8673820496],"type":"Point"}
}