{
  "type": "Feature",
  "properties": {
    "addr:full":"Rue Emile Tumelaire 65 Charleroi Hainaut 6000",
    "addr:housenumber":"65",
    "addr:postcode":"6000",
    "addr:street":"Rue Emile Tumelaire;Hainaut",
    "iso:country":"BE",
    "sg:address":"Rue Emile Tumelaire 65",
    "sg:city":"Charleroi",
    "sg:orig_category":"Avocats and conseillers juridiques",
    "sg:phone":"+32 71 32 48 08",
    "sg:postcode":"6000",
    "sg:province":"Hainaut",
    "wof:name":"P. Lemaire",
    "wof:placetype":"venue"
},
  "geometry": {"coordinates":[4.4501919746,50.4096794128],"type":"Point"}
}