{
  "type": "Feature",
  "properties": {
    "iso:country":"BE",
    "sg:address":"Chaussee De Namur 146",
    "sg:city":"Gembloux",
    "sg:classifiers":[
        {
            "category":"Home & Garden",
            "subcategory":"Hardware",
            "type":"Retail Goods"
        }
    ],
    "sg:phone":"+32 81 61 25 01",
    "sg:postcode":"5030",
    "sg:province":"Namur",
    "sg:tags":[
        "agricultural",
        "implement"
    ],
    "wof:name":"Cra Station De Genie",
    "wof:placetype":"venue"
},
  "geometry": {"coordinates":[4.7088198662,50.5527381897],"type":"Point"}
}