{
  "type": "Feature",
  "properties": {
    "addr:full":"Kluisstraat 42 Mechelen Antwerpen 2800",
    "addr:housenumber":"42",
    "addr:postcode":"2800",
    "addr:street":"Kluisstraat",
    "iso:country":"BE",
    "sg:address":"Kluisstraat 42",
    "sg:city":"Mechelen",
    "sg:orig_category":"Voedingsspeciaalzaken",
    "sg:phone":"+32 15 55 77 54",
    "sg:postcode":"2800",
    "sg:province":"Antwerpen",
    "wof:name":"Patrick Verdonck",
    "wof:placetype":"venue"
},
  "geometry": {"coordinates":[4.4919071198,51.0327148438],"type":"Point"}
}