{
  "type": "Feature",
  "properties": {
    "addr:full":"Koolmijnlaan 365 Beringen Limburg 3581",
    "addr:housenumber":"365",
    "addr:postcode":"3581",
    "addr:street":"Koolmijnlaan",
    "iso:country":"BE",
    "sg:address":"Koolmijnlaan 365",
    "sg:city":"Beringen",
    "sg:orig_category":"Meubelzaken, woning- and keukeninrichting Verlichting and huishoudartikelen",
    "sg:phone":"+32 11 43 19 06",
    "sg:postcode":"3581",
    "sg:province":"Limburg",
    "wof:name":"Rotan Palace",
    "wof:placetype":"venue"
},
  "geometry": {"coordinates":[5.2194008827,51.0787811279],"type":"Point"}
}