{
  "type": "Feature",
  "properties": {
    "addr:full":"Stationsstraat 60 Wachtebeke Oost-Vlaanderen 9185",
    "addr:housenumber":"60",
    "addr:postcode":"9185",
    "addr:street":"Stationsstraat",
    "iso:country":"BE",
    "sg:address":"Stationsstraat 60",
    "sg:city":"Wachtebeke",
    "sg:classifiers":[
        {
            "category":"Retail",
            "subcategory":"Funeral Services",
            "type":"Services"
        }
    ],
    "sg:phone":"+32 9 345 02 05",
    "sg:postcode":"9185",
    "sg:province":"Oost-Vlaanderen",
    "sg:tags":[
        "director"
    ],
    "wof:name":"Ongena Bvba",
    "wof:placetype":"venue"
},
  "geometry": {"coordinates":[3.8626520634,51.1739234924],"type":"Point"}
}