{
  "type": "Feature",
  "properties": {
    "addr:full":"Rue De Tourcoing 43 Mouscron Hainaut 7700",
    "addr:housenumber":"43",
    "addr:postcode":"7700",
    "addr:street":"Rue De Tourcoing",
    "iso:country":"BE",
    "sg:address":"Rue De Tourcoing 43",
    "sg:city":"Mouscron",
    "sg:classifiers":[
        {
            "category":"Shopping",
            "subcategory":"Clothing, Apparel, & Fashions",
            "type":"Retail Goods"
        }
    ],
    "sg:phone":"+32 56 34 43 63",
    "sg:postcode":"7700",
    "sg:province":"Hainaut",
    "sg:tags":[
        "lady",
        "clothing",
        "-"
    ],
    "wof:name":"Joyce",
    "wof:placetype":"venue"
},
  "geometry": {"coordinates":[3.211591959,50.7443504333],"type":"Point"}
}