{
  "type": "Feature",
  "properties": {
    "iso:country":"BE",
    "sg:address":"Vrouweneekhoek 122",
    "sg:city":"Sint-niklaas",
    "sg:orig_category":"Jardinage",
    "sg:phone":"+32 3 777 61 05",
    "sg:postcode":"9100",
    "sg:province":"Oost-Vlaanderen",
    "wof:name":"Jan Den Tuinman",
    "wof:placetype":"venue"
},
  "geometry": {"coordinates":[4.1450161934,51.1888999939],"type":"Point"}
}