{
  "type": "Feature",
  "properties": {
    "addr:full":"Laarstraat 45 Boortmeerbeek Vlaams-Brabant 3190",
    "addr:housenumber":"45",
    "addr:postcode":"3190",
    "addr:street":"Laarstraat",
    "iso:country":"BE",
    "sg:address":"Laarstraat 45",
    "sg:city":"Boortmeerbeek",
    "sg:classifiers":[
        {
            "category":"Building & Trades",
            "subcategory":"Construction",
            "type":"Services"
        }
    ],
    "sg:phone":"+32 16 60 56 69",
    "sg:postcode":"3190",
    "sg:province":"Vlaams-Brabant",
    "sg:tags":[
        "carpenter"
    ],
    "wof:name":"Van Rillaer",
    "wof:placetype":"venue"
},
  "geometry": {"coordinates":[4.5786027908,50.9679222107],"type":"Point"}
}