{
  "type": "Feature",
  "properties": {
    "addr:full":"Tennislaan 0 Tienen Vlaams-Brabant 3300",
    "addr:housenumber":"0",
    "addr:postcode":"3300",
    "addr:street":"Tennislaan",
    "iso:country":"BE",
    "sg:address":"Tennislaan 0",
    "sg:city":"Tienen",
    "sg:classifiers":[
        {
            "category":"Sports & Exercise",
            "subcategory":"Sports Center",
            "type":"Entertainment"
        }
    ],
    "sg:phone":"+32 16 81 19 11",
    "sg:postcode":"3300",
    "sg:province":"Vlaams-Brabant",
    "sg:tags":[
        "de",
        "fitness"
    ],
    "wof:name":"Tennis Club Thuinas",
    "wof:placetype":"venue"
},
  "geometry": {"coordinates":[4.9408650398,50.8176498413],"type":"Point"}
}