{
  "type": "Feature",
  "properties": {
    "iso:country":"BE",
    "sg:address":"Edward De Denestraat 17 Box 2",
    "sg:city":"Brugge (assebroek)",
    "sg:classifiers":[
        {
            "category":"Building & Trades",
            "subcategory":"Construction",
            "type":"Services"
        }
    ],
    "sg:phone":"+32 475 36 17 64",
    "sg:postcode":"8310",
    "sg:province":"West-Vlaanderen",
    "sg:tags":[
        "installation",
        "-",
        "central",
        "heating"
    ],
    "wof:name":"Oltec Bvba",
    "wof:placetype":"venue"
},
  "geometry": {"coordinates":[3.2336199284,51.1989364624],"type":"Point"}
}