{
  "type": "Feature",
  "properties": {
    "iso:country":"BE",
    "sg:address":"Rue Albert 1er 63",
    "sg:city":"Leval-trahegnies",
    "sg:classifiers":[
        {
            "category":"Manufacturing",
            "subcategory":"Lumber",
            "type":"Manufacturing & Wholesale Goods"
        }
    ],
    "sg:phone":"+32 64 33 39 21",
    "sg:postcode":"7134",
    "sg:province":"Hainaut",
    "sg:tags":[
        "hardwood",
        "sawmill"
    ],
    "wof:name":"Stiernon Et Fils S.a.",
    "wof:placetype":"venue"
},
  "geometry": {"coordinates":[4.2097220421,50.430305481],"type":"Point"}
}