{
  "type": "Feature",
  "properties": {
    "addr:full":"Sint-pieterskaai 73 Brugge West-Vlaanderen 8000",
    "addr:housenumber":"73",
    "addr:postcode":"8000",
    "addr:street":"Sint-Pieterskaai",
    "iso:country":"BE",
    "sg:address":"Sint-pieterskaai 73",
    "sg:city":"Brugge",
    "sg:orig_category":"Editeurs de journaux. Editeurs de revues and p\u00e9riodiques",
    "sg:phone":"+32 50 55 17 53",
    "sg:postcode":"8000",
    "sg:province":"West-Vlaanderen",
    "wof:name":"Cartacarta",
    "wof:placetype":"venue"
},
  "geometry": {"coordinates":[3.2259209156,51.2227058411],"type":"Point"}
}