{
  "type": "Feature",
  "properties": {
    "addr:full":"Rn 5 191 Gosselies Hainaut 6041",
    "addr:housenumber":"191",
    "addr:postcode":"6041",
    "addr:street":"Rn 5",
    "iso:country":"BE",
    "sg:address":"Rn 5 191",
    "sg:city":"Gosselies",
    "sg:classifiers":[
        {
            "category":"Professional",
            "subcategory":"Advertising",
            "type":"Services"
        }
    ],
    "sg:phone":"+32 71 25 75 50",
    "sg:postcode":"6041",
    "sg:province":"Hainaut",
    "sg:tags":[
        "information",
        "medium",
        "business",
        "communication",
        "advice",
        "technology"
    ],
    "wof:name":"Intern Cr\u00c9ative Digital Sa",
    "wof:placetype":"venue"
},
  "geometry": {"coordinates":[4.4314317703,50.4685935974],"type":"Point"}
}