{
  "type": "Feature",
  "properties": {
    "iso:country":"BE",
    "sg:address":"Rue De L\u00b4ath\u00c9n\u00c9e 12",
    "sg:city":"Tournai",
    "sg:orig_category":"Advocaten and juridische adviseurs",
    "sg:phone":"+32 69 84 16 91",
    "sg:postcode":"7500",
    "sg:province":"Hainaut",
    "wof:name":"Pascaline Foucart",
    "wof:placetype":"venue"
},
  "geometry": {"coordinates":[3.3952660561,50.6090240479],"type":"Point"}
}