{
  "type": "Feature",
  "properties": {
    "iso:country":"BE",
    "sg:address":"Jaak Lemmenslaan 50",
    "sg:city":"Zemst",
    "sg:classifiers":[
        {
            "category":"Professional",
            "subcategory":"Management & Consulting",
            "type":"Services"
        }
    ],
    "sg:phone":"+32 15 61 07 91",
    "sg:postcode":"1980",
    "sg:province":"Vlaams-Brabant",
    "sg:tags":[
        "consultant"
    ],
    "wof:name":"I.c.t.s. Nv",
    "wof:placetype":"venue"
},
  "geometry": {"coordinates":[4.4619231224,50.9796676636],"type":"Point"}
}