{
  "type": "Feature",
  "properties": {
    "addr:full":"Rue Du Stade 1 Bl\u00e9gny (housse) Li\u00e8ge 4671",
    "addr:housenumber":"1",
    "addr:postcode":"4671",
    "addr:street":"Rue Du Stade;Housse",
    "iso:country":"BE",
    "sg:address":"Rue Du Stade 1",
    "sg:city":"Bl\u00e9gny (housse)",
    "sg:classifiers":[
        {
            "category":"Health Services",
            "subcategory":"Nursing And Care Facility",
            "type":"Services"
        }
    ],
    "sg:phone":"+32 4 387 65 56",
    "sg:postcode":"4671",
    "sg:province":"Li\u00e8ge",
    "sg:tags":[
        "home"
    ],
    "wof:name":"Letesson C",
    "wof:placetype":"venue"
},
  "geometry": {"coordinates":[5.698996067,50.6806564331],"type":"Point"}
}