{
  "type": "Feature",
  "properties": {
    "iso:country":"BE",
    "sg:address":"Rue Vanderveken 52",
    "sg:city":"Ganshoren/ganshoren",
    "sg:orig_category":"Epiceries",
    "sg:phone":"+32 2 465 65 71",
    "sg:postcode":"1083",
    "sg:province":"Bruxelles-Capitale",
    "wof:name":"Shopwell",
    "wof:placetype":"venue"
},
  "geometry": {"coordinates":[4.3045358658,50.8745880127],"type":"Point"}
}