{
  "type": "Feature",
  "properties": {
    "iso:country":"BE",
    "sg:address":"Jan Mahieustraat 26",
    "sg:city":"Roeselare",
    "sg:classifiers":[
        {
            "category":"Health Services",
            "subcategory":"Dentist",
            "type":"Services"
        }
    ],
    "sg:phone":"+32 51 24 25 60",
    "sg:postcode":"8800",
    "sg:province":"West-Vlaanderen",
    "wof:name":"Rommel Benedikte",
    "wof:placetype":"venue"
},
  "geometry": {"coordinates":[3.1269419193,50.9476547241],"type":"Point"}
}