{
  "type": "Feature",
  "properties": {
    "addr:full":"Rue C\u00c9lestin Demblon 86 Herstal Li\u00e8ge 4040",
    "addr:housenumber":"86",
    "addr:postcode":"4040",
    "addr:street":"Rue Ce\u0301Lestin Demblon",
    "iso:country":"BE",
    "sg:address":"Rue C\u00c9lestin Demblon 86",
    "sg:city":"Herstal",
    "sg:classifiers":[
        {
            "category":"Restaurant",
            "type":"Food & Drink"
        }
    ],
    "sg:phone":"+32 4 248 09 97",
    "sg:postcode":"4040",
    "sg:province":"Li\u00e8ge",
    "wof:name":"Glacier Le Mambo",
    "wof:placetype":"venue"
},
  "geometry": {"coordinates":[5.6298680305,50.6736412048],"type":"Point"}
}