{
  "type": "Feature",
  "properties": {
    "iso:country":"BE",
    "sg:address":"Rue Mitoyenne 130",
    "sg:city":"Lontzen",
    "sg:orig_category":"Antiquit\u00e9s",
    "sg:phone":"+32 87 34 07 26",
    "sg:postcode":"4710",
    "sg:province":"Li\u00e8ge",
    "wof:name":"J. Masset",
    "wof:placetype":"venue"
},
  "geometry": {"coordinates":[5.9620499611,50.6794281006],"type":"Point"}
}