{
  "type": "Feature",
  "properties": {
    "addr:full":"Avenue Paul Dejaer 29 Bruxelles (saint-gilles) Bruxelles-Capitale 1060",
    "addr:housenumber":"29",
    "addr:postcode":"1060",
    "addr:street":"Avenue Paul Dejaer",
    "iso:country":"BE",
    "sg:address":"Avenue Paul Dejaer 29",
    "sg:city":"Bruxelles (saint-gilles)",
    "sg:classifiers":[
        {
            "category":"Personal",
            "subcategory":"Beauty Salon",
            "type":"Services"
        }
    ],
    "sg:phone":"+32 2 534 42 29",
    "sg:postcode":"1060",
    "sg:province":"Bruxelles-Capitale",
    "wof:name":"Esth\u00e9tique Santi's (l')",
    "wof:placetype":"venue"
},
  "geometry": {"coordinates":[4.3448271751,50.8257369995],"type":"Point"}
}