{
  "type": "Feature",
  "properties": {
    "iso:country":"BE",
    "sg:address":"August Leyweg 14",
    "sg:city":"Antwerpen",
    "sg:orig_category":"Enseignement maternel and primaire",
    "sg:phone":"+32 3 216 28 80",
    "sg:postcode":"2020",
    "sg:province":"Antwerpen",
    "wof:name":"Bulo",
    "wof:placetype":"venue"
},
  "geometry": {"coordinates":[4.3785529137,51.1959266663],"type":"Point"}
}