{
  "type": "Feature",
  "properties": {
    "addr:full":"Rue Britannique 22 Braine-le-comte Hainaut 7090",
    "addr:housenumber":"22",
    "addr:postcode":"7090",
    "addr:street":"Rue Britannique",
    "iso:country":"BE",
    "sg:address":"Rue Britannique 22",
    "sg:city":"Braine-le-comte",
    "sg:classifiers":[
        {
            "category":"Shopping",
            "subcategory":"Computers & Home Electronics",
            "type":"Retail Goods"
        }
    ],
    "sg:phone":"+32 67 55 28 74",
    "sg:postcode":"7090",
    "sg:province":"Hainaut",
    "sg:tags":[
        "personal",
        "-",
        "processing",
        "data"
    ],
    "wof:name":"Guevar Informatique",
    "wof:placetype":"venue"
},
  "geometry": {"coordinates":[4.1348347664,50.6074028015],"type":"Point"}
}