{
  "type": "Feature",
  "properties": {
    "addr:full":"Rue De La Vall\u00c9e 9 Ottignies-louvain-la-neuve Brabant Wallon 1340",
    "addr:housenumber":"9",
    "addr:postcode":"1340",
    "addr:street":"Rue De La Valle\u0301E",
    "iso:country":"BE",
    "sg:address":"Rue De La Vall\u00c9e 9",
    "sg:city":"Ottignies-louvain-la-neuve",
    "sg:orig_category":"Installation de menuiserie en bois and plastique",
    "sg:phone":"+32 10 41 05 66",
    "sg:postcode":"1340",
    "sg:province":"Brabant Wallon",
    "wof:name":"Henri Ruelle",
    "wof:placetype":"venue"
},
  "geometry": {"coordinates":[4.5774888992,50.6724014282],"type":"Point"}
}