{
  "type": "Feature",
  "properties": {
    "addr:full":"Rue De Courtrai 3 Pecq Hainaut 7740",
    "addr:housenumber":"3",
    "addr:postcode":"7740",
    "addr:street":"Rue De Courtrai",
    "iso:country":"BE",
    "sg:address":"Rue De Courtrai 3",
    "sg:city":"Pecq",
    "sg:classifiers":[
        {
            "category":"Professional",
            "subcategory":"Testing Lab",
            "type":"Services"
        }
    ],
    "sg:phone":"+32 69 55 64 74",
    "sg:postcode":"7740",
    "sg:province":"Hainaut",
    "sg:tags":[
        "chemist"
    ],
    "wof:name":"Pharmacie De La Place",
    "wof:placetype":"venue"
},
  "geometry": {"coordinates":[3.3388030529,50.6856193542],"type":"Point"}
}