{
  "type": "Feature",
  "properties": {
    "addr:full":"Torhoutsestraat 224 Oostkamp West-Vlaanderen 8020",
    "addr:housenumber":"224",
    "addr:postcode":"8020",
    "addr:street":"Torhoutsestraat",
    "iso:country":"BE",
    "sg:address":"Torhoutsestraat 224",
    "sg:city":"Oostkamp",
    "sg:orig_category":"Autoverhuur",
    "sg:phone":"+32 50 27 82 85",
    "sg:postcode":"8020",
    "sg:province":"West-Vlaanderen",
    "wof:name":"Lambert",
    "wof:placetype":"venue"
},
  "geometry": {"coordinates":[3.1832649708,51.0803604126],"type":"Point"}
}