{
  "type": "Feature",
  "properties": {
    "addr:full":"Slijkenhoefstraat 34 Rumst Antwerpen 2840",
    "addr:housenumber":"34",
    "addr:postcode":"2840",
    "addr:street":"Slijkenhoefstraat",
    "iso:country":"BE",
    "sg:address":"Slijkenhoefstraat 34",
    "sg:city":"Rumst",
    "sg:orig_category":"Sportclubs",
    "sg:phone":"+32 15 32 96 82",
    "sg:postcode":"2840",
    "sg:province":"Antwerpen",
    "wof:name":"J.c. Sandokan Mechelen",
    "wof:placetype":"venue"
},
  "geometry": {"coordinates":[4.4501700401,51.0938911438],"type":"Point"}
}