{
  "type": "Feature",
  "properties": {
    "iso:country":"BE",
    "sg:address":"Hortensiastraat 45",
    "sg:city":"Houthalen-helchteren (houthalen)",
    "sg:classifiers":[
        {
            "category":"Personal",
            "subcategory":"Nail Salon",
            "type":"Services"
        }
    ],
    "sg:phone":"+32 89 38 19 51",
    "sg:postcode":"3530",
    "sg:province":"Limburg",
    "sg:tags":[
        "pedicure"
    ],
    "wof:name":"Fraiponts L",
    "wof:placetype":"venue"
},
  "geometry": {"coordinates":[5.4913811684,51.0226974487],"type":"Point"}
}