{
  "type": "Feature",
  "properties": {
    "addr:full":"Leuvenstraat 48 Box 1 Kortenberg (erps-kwerps) Vlaams-Brabant 3071",
    "addr:housenumber":"48;1",
    "addr:postcode":"3071",
    "addr:street":"Leuvenstraat;Box",
    "iso:country":"BE",
    "sg:address":"Leuvenstraat 48 Box 1",
    "sg:city":"Kortenberg (erps-kwerps)",
    "sg:classifiers":[
        {
            "category":"Building & Trades",
            "subcategory":"Equipment Rental",
            "type":"Services"
        }
    ],
    "sg:phone":"+32 16 23 03 78",
    "sg:postcode":"3071",
    "sg:province":"Vlaams-Brabant",
    "sg:tags":[
        "sound",
        "-",
        "system"
    ],
    "wof:name":"Ssls",
    "wof:placetype":"venue"
},
  "geometry": {"coordinates":[4.6044998169,50.91796875],"type":"Point"}
}