{
  "type": "Feature",
  "properties": {
    "iso:country":"BE",
    "sg:address":"Akkerstraat 7",
    "sg:city":"Wachtebeke",
    "sg:orig_category":"Varkenskwekers",
    "sg:phone":"+32 9 345 08 35",
    "sg:postcode":"9185",
    "sg:province":"Oost-Vlaanderen",
    "wof:name":"Roger De Maesschalck",
    "wof:placetype":"venue"
},
  "geometry": {"coordinates":[3.85115695,51.1915893555],"type":"Point"}
}