{
  "type": "Feature",
  "properties": {
    "addr:full":"Valkenweg 10 Oud-turnhout Antwerpen 2360",
    "addr:housenumber":"10",
    "addr:postcode":"2360",
    "addr:street":"Valkenweg",
    "iso:country":"BE",
    "sg:address":"Valkenweg 10",
    "sg:city":"Oud-turnhout",
    "sg:classifiers":[
        {
            "category":"Real Estate",
            "subcategory":"Real Estate Services",
            "type":"Services"
        }
    ],
    "sg:phone":"+32 14 45 04 18",
    "sg:postcode":"2360",
    "sg:province":"Antwerpen",
    "wof:name":"Touber Bedrijfshuisvesting",
    "wof:placetype":"venue"
},
  "geometry": {"coordinates":[5.0240631104,51.3211593628],"type":"Point"}
}