{
  "type": "Feature",
  "properties": {
    "iso:country":"BE",
    "sg:address":"Groeningenlei 44",
    "sg:city":"Kontich",
    "sg:classifiers":[
        {
            "category":"Building & Trades",
            "subcategory":"Construction",
            "type":"Services"
        }
    ],
    "sg:phone":"+32 3 457 21 57",
    "sg:postcode":"2550",
    "sg:province":"Antwerpen",
    "sg:tags":[
        "residential",
        "masonry"
    ],
    "wof:name":"Quackels Woningbouw Nv",
    "wof:placetype":"venue"
},
  "geometry": {"coordinates":[4.434440136,51.1388931274],"type":"Point"}
}