{
  "type": "Feature",
  "properties": {
    "addr:full":"Rue Du Grand Air 39 Chaudfontaine Li\u00e8ge 4052",
    "addr:housenumber":"39",
    "addr:postcode":"4052",
    "addr:street":"Rue Du Grand Air",
    "iso:country":"BE",
    "sg:address":"Rue Du Grand Air 39",
    "sg:city":"Chaudfontaine",
    "sg:orig_category":"Installation de menuiserie en bois and plastique",
    "sg:phone":"+32 4 368 82 91",
    "sg:postcode":"4052",
    "sg:province":"Li\u00e8ge",
    "wof:name":"Franz Banken",
    "wof:placetype":"venue"
},
  "geometry": {"coordinates":[5.6186790466,50.564868927],"type":"Point"}
}