{
  "type": "Feature",
  "properties": {
    "addr:full":"Wijnendalestraat 189 Roeselare West-Vlaanderen 8800",
    "addr:housenumber":"189",
    "addr:postcode":"8800",
    "addr:street":"Wijnendalestraat",
    "iso:country":"BE",
    "sg:address":"Wijnendalestraat 189",
    "sg:city":"Roeselare",
    "sg:classifiers":[
        {
            "category":"Banks & Credit Unions",
            "subcategory":"Investment Brokerage",
            "type":"Services"
        }
    ],
    "sg:phone":"+32 51 22 72 00",
    "sg:postcode":"8800",
    "sg:province":"West-Vlaanderen",
    "sg:tags":[
        "pipe",
        "-"
    ],
    "wof:name":"Verhoestraete Metalen Nv",
    "wof:placetype":"venue"
},
  "geometry": {"coordinates":[3.1250810623,50.9721183777],"type":"Point"}
}