{
  "type": "Feature",
  "properties": {
    "iso:country":"BE",
    "sg:address":"Rue Du Calvaire 23",
    "sg:city":"Fernelmont",
    "sg:orig_category":"Herstellingen and onderhoud van auto's",
    "sg:phone":"+32 81 21 13 80",
    "sg:postcode":"5380",
    "sg:province":"Namur",
    "wof:name":"Albert Gustin",
    "wof:placetype":"venue"
},
  "geometry": {"coordinates":[4.9433250427,50.5250854492],"type":"Point"}
}