{
  "type": "Feature",
  "properties": {
    "addr:full":"Rue E. Bonehill 121 Sint-jans-molenbeek Bruxelles-Capitale 1080",
    "addr:housenumber":"121",
    "addr:postcode":"1080",
    "addr:street":"Rue E. Bonehill",
    "iso:country":"BE",
    "sg:address":"Rue E. Bonehill 121",
    "sg:city":"Sint-jans-molenbeek",
    "sg:orig_category":"Gespecialiseerde niet-residenti\u00eble bouw Metaalbehandeling and -bekleding",
    "sg:phone":"+32 2 410 16 19",
    "sg:postcode":"1080",
    "sg:province":"Bruxelles-Capitale",
    "wof:name":"Alvarez",
    "wof:placetype":"venue"
},
  "geometry": {"coordinates":[4.3246049881,50.8500785828],"type":"Point"}
}