{
  "type": "Feature",
  "properties": {
    "iso:country":"BE",
    "sg:address":"Avenue Jette 333",
    "sg:city":"Ganshoren",
    "sg:classifiers":[
        {
            "category":"Structure",
            "subcategory":"Factory",
            "type":"Public Place"
        }
    ],
    "sg:phone":"+32 2 428 35 26",
    "sg:postcode":"1083",
    "sg:province":"Bruxelles-Capitale",
    "sg:tags":[
        "metaalwaren",
        "fab",
        "diverse"
    ],
    "wof:name":"Go-bel-houss",
    "wof:placetype":"venue"
},
  "geometry": {"coordinates":[4.3195829391,50.8753356934],"type":"Point"}
}