{
  "type": "Feature",
  "properties": {
    "addr:full":"Rue Joseph Merlot 39 Fl\u00e9ron (roms\u00e9e) Li\u00e8ge 4624",
    "addr:housenumber":"39",
    "addr:postcode":"4624",
    "addr:street":"Rue Joseph Merlot",
    "iso:country":"BE",
    "sg:address":"Rue Joseph Merlot 39",
    "sg:city":"Fl\u00e9ron (roms\u00e9e)",
    "sg:classifiers":[
        {
            "category":"Arts & Performance",
            "subcategory":"Music",
            "type":"Entertainment"
        }
    ],
    "sg:phone":"+32 496 08 69 25",
    "sg:postcode":"4624",
    "sg:province":"Li\u00e8ge",
    "sg:tags":[
        "disc-jockeys"
    ],
    "wof:name":"Absolute Freeline Int.",
    "wof:placetype":"venue"
},
  "geometry": {"coordinates":[5.6599798203,50.6104545593],"type":"Point"}
}