{
  "type": "Feature",
  "properties": {
    "addr:full":"Rue Joseph Muller 11bb Dalhem Li\u00e8ge 4608",
    "addr:housenumber":"11bb",
    "addr:postcode":"4608",
    "addr:street":"Rue Joseph Muller",
    "iso:country":"BE",
    "sg:address":"Rue Joseph Muller 11bb",
    "sg:city":"Dalhem",
    "sg:orig_category":"Salles de conf\u00e9rences and de r\u00e9ceptions",
    "sg:phone":"+32 4 376 72 81",
    "sg:postcode":"4608",
    "sg:province":"Li\u00e8ge",
    "wof:name":"Salons Amon Nos Otes",
    "wof:placetype":"venue"
},
  "geometry": {"coordinates":[5.7665410042,50.7354812622],"type":"Point"}
}