{
  "type": "Feature",
  "properties": {
    "iso:country":"BE",
    "sg:address":"Rue De Merbes 225",
    "sg:city":"Binche (waudrez)",
    "sg:classifiers":[
        {
            "category":"Professional",
            "subcategory":"Lawyer & Legal Services",
            "type":"Services"
        }
    ],
    "sg:phone":"+32 64 36 68 06",
    "sg:postcode":"7131",
    "sg:province":"Hainaut",
    "wof:name":"Tombal Laurence",
    "wof:placetype":"venue"
},
  "geometry": {"coordinates":[4.1724901199,50.4012145996],"type":"Point"}
}