{
  "type": "Feature",
  "properties": {
    "addr:full":"Avenue Du Roi Albert 85 Bruxelles (berchem-sainte-agathe) Bruxelles-Capitale 1082",
    "addr:housenumber":"85",
    "addr:postcode":"1082",
    "addr:street":"Avenue Du Roi Albert",
    "iso:country":"BE",
    "sg:address":"Avenue Du Roi Albert 85",
    "sg:city":"Bruxelles (berchem-sainte-agathe)",
    "sg:classifiers":[
        {
            "category":"Health Services",
            "subcategory":"Doctor",
            "type":"Services"
        }
    ],
    "sg:phone":"+32 2 465 07 32",
    "sg:postcode":"1082",
    "sg:province":"Bruxelles-Capitale",
    "sg:tags":[
        "medicinephysicians",
        "surgeon"
    ],
    "wof:name":"Berghmans Beno\u00eet",
    "wof:placetype":"venue"
},
  "geometry": {"coordinates":[4.2926101685,50.8655128479],"type":"Point"}
}