{
  "type": "Feature",
  "properties": {
    "addr:full":"Rue Des Pirailles 21 Namur (vedrin - Daussoulx) Namur 5020",
    "addr:housenumber":"21",
    "addr:postcode":"5020",
    "addr:street":"Rue Des Pirailles",
    "iso:country":"BE",
    "sg:address":"Rue Des Pirailles 21",
    "sg:city":"Namur (vedrin - Daussoulx)",
    "sg:classifiers":[
        {
            "category":"Health Services",
            "subcategory":"Doctor",
            "type":"Services"
        }
    ],
    "sg:phone":"+32 81 21 23 86",
    "sg:postcode":"5020",
    "sg:province":"Namur",
    "sg:tags":[
        "medicinephysicians",
        "surgeon"
    ],
    "wof:name":"Etienne J",
    "wof:placetype":"venue"
},
  "geometry": {"coordinates":[4.7952418327,50.4352035522],"type":"Point"}
}