{
  "type": "Feature",
  "properties": {
    "addr:full":"Albert I Laan 101c Nieuwpoort West-Vlaanderen 8620",
    "addr:housenumber":"101c",
    "addr:postcode":"8620",
    "addr:street":"Albert I Laan",
    "iso:country":"BE",
    "sg:address":"Albert I Laan 101c",
    "sg:city":"Nieuwpoort",
    "sg:classifiers":[
        {
            "category":"Tea Room",
            "subcategory":"None",
            "type":"Food & Drink"
        }
    ],
    "sg:phone":"+32 58 23 01 11",
    "sg:postcode":"8620",
    "sg:province":"West-Vlaanderen",
    "wof:name":"Plaza Rodriguez",
    "wof:placetype":"venue"
},
  "geometry": {"coordinates":[2.7285749912,51.1452484131],"type":"Point"}
}