{
  "type": "Feature",
  "properties": {
    "addr:full":"Hofbouwstraat 5 Zomergem Oost-Vlaanderen 9930",
    "addr:housenumber":"5",
    "addr:postcode":"9930",
    "addr:street":"Hofbouwstraat",
    "iso:country":"BE",
    "sg:address":"Hofbouwstraat 5",
    "sg:city":"Zomergem",
    "sg:orig_category":"Loodgieterij, verwarming and sanitaire installaties",
    "sg:phone":"+32 9 372 07 34",
    "sg:postcode":"9930",
    "sg:province":"Oost-Vlaanderen",
    "wof:name":"Thermako",
    "wof:placetype":"venue"
},
  "geometry": {"coordinates":[3.5631399155,51.1212348938],"type":"Point"}
}