{
  "type": "Feature",
  "properties": {
    "addr:full":"Rue Saint-michel Bruxelles Bruxelles-Capitale 1000",
    "addr:postcode":"1000",
    "addr:street":"Rue Saint-Michel",
    "iso:country":"BE",
    "sg:address":"Rue Saint-michel",
    "sg:city":"Bruxelles",
    "sg:classifiers":[
        {
            "category":"Sports & Exercise",
            "subcategory":"Gym",
            "type":"Entertainment"
        }
    ],
    "sg:phone":"+32 70 22 54 25",
    "sg:postcode":"1000",
    "sg:province":"Bruxelles-Capitale",
    "sg:tags":[
        "fitness"
    ],
    "wof:name":"Passage Fitness",
    "wof:placetype":"venue"
},
  "geometry": {"coordinates":[4.3538351059,50.8526382446],"type":"Point"}
}