{
  "type": "Feature",
  "properties": {
    "addr:full":"Rue Destriveaux 28 Li\u00e8ge 1 Li\u00e8ge 4000",
    "addr:housenumber":"28;1",
    "addr:postcode":"4000",
    "addr:street":"Rue Destriveaux",
    "iso:country":"BE",
    "sg:address":"Rue Destriveaux 28",
    "sg:city":"Li\u00e8ge 1",
    "sg:classifiers":[
        {
            "category":"Health Services",
            "subcategory":"Doctor",
            "type":"Services"
        }
    ],
    "sg:phone":"+32 4 252 29 10",
    "sg:postcode":"4000",
    "sg:province":"Li\u00e8ge",
    "sg:tags":[
        "medicinephysicians",
        "surgeon"
    ],
    "wof:name":"Cinna Benoit",
    "wof:placetype":"venue"
},
  "geometry": {"coordinates":[5.5567440987,50.634349823],"type":"Point"}
}