{
  "type": "Feature",
  "properties": {
    "addr:full":"Driesstraat 107 Geraardsbergen Oost-Vlaanderen 9506",
    "addr:housenumber":"107",
    "addr:postcode":"9506",
    "addr:street":"Driesstraat",
    "iso:country":"BE",
    "sg:address":"Driesstraat 107",
    "sg:city":"Geraardsbergen",
    "sg:orig_category":"Afval and schroot Gh",
    "sg:phone":"+32 54 50 15 26",
    "sg:postcode":"9506",
    "sg:province":"Oost-Vlaanderen",
    "wof:name":"Luc Eeckhout",
    "wof:placetype":"venue"
},
  "geometry": {"coordinates":[3.8985300064,50.7987060547],"type":"Point"}
}