{
  "type": "Feature",
  "properties": {
    "addr:full":"Rue De Velupont 9 Braives (ville-en-hesbaye) Li\u00e8ge 4260",
    "addr:housenumber":"9",
    "addr:postcode":"4260",
    "addr:street":"Rue De Velupont;Ville-En-Hesbaye",
    "iso:country":"BE",
    "sg:address":"Rue De Velupont 9",
    "sg:city":"Braives (ville-en-hesbaye)",
    "sg:classifiers":[
        {
            "category":"Health Services",
            "subcategory":"Health Practitioner",
            "type":"Services"
        }
    ],
    "sg:phone":"+32 19 69 86 93",
    "sg:postcode":"4260",
    "sg:province":"Li\u00e8ge",
    "sg:tags":[
        "physiotherapist"
    ],
    "wof:name":"Viatour Maryline",
    "wof:placetype":"venue"
},
  "geometry": {"coordinates":[5.1167092323,50.6218833923],"type":"Point"}
}