{
  "type": "Feature",
  "properties": {
    "iso:country":"BE",
    "sg:address":"Galgestraat 3",
    "sg:city":"Lichtervelde",
    "sg:orig_category":"HUISBRANDOLIE",
    "sg:phone":"+32 51 72 22 09",
    "sg:postcode":"8810",
    "sg:province":"West-Vlaanderen",
    "wof:name":"Willy Labens",
    "wof:placetype":"venue"
},
  "geometry": {"coordinates":[3.1750900745,51.0137672424],"type":"Point"}
}