{
  "type": "Feature",
  "properties": {
    "iso:country":"BE",
    "sg:address":"Rue Hautes Golettes 235",
    "sg:city":"Ohey",
    "sg:orig_category":"Woningbouw",
    "sg:phone":"+32 85 61 18 89",
    "sg:postcode":"5351",
    "sg:province":"Namur",
    "wof:name":"Marcel Malherbe",
    "wof:placetype":"venue"
},
  "geometry": {"coordinates":[5.1492128372,50.4539108276],"type":"Point"}
}