{
  "type": "Feature",
  "properties": {
    "iso:country":"BE",
    "sg:address":"Maastrichterstraat 1b24",
    "sg:city":"Hasselt",
    "sg:orig_category":"Timbres, monnaies and troph\u00e9es",
    "sg:phone":"+32 11 22 58 10",
    "sg:postcode":"3500",
    "sg:province":"Limburg",
    "wof:name":"Dezittere",
    "wof:placetype":"venue"
},
  "geometry": {"coordinates":[5.3379402161,50.9291534424],"type":"Point"}
}