{
  "type": "Feature",
  "properties": {
    "iso:country":"BE",
    "sg:address":"Route De Souxhon 266",
    "sg:city":"Fl\u00e9malle",
    "sg:classifiers":[
        {
            "category":"Retail",
            "subcategory":"Event Space",
            "type":"Services"
        }
    ],
    "sg:phone":"+32 4 234 45 46",
    "sg:postcode":"4400",
    "sg:province":"Li\u00e8ge",
    "sg:tags":[
        "rental",
        "-",
        "hall"
    ],
    "wof:name":"Au Vieux Souxhon",
    "wof:placetype":"venue"
},
  "geometry": {"coordinates":[5.4554281235,50.608505249],"type":"Point"}
}