{
  "type": "Feature",
  "properties": {
    "iso:country":"BE",
    "sg:address":"Rue Saint-mort 255",
    "sg:city":"Ohey (haillot)",
    "sg:classifiers":[
        {
            "category":"Shopping",
            "subcategory":"Hobbies, Toys, & Games",
            "type":"Retail Goods"
        }
    ],
    "sg:phone":"+32 85 61 19 75",
    "sg:postcode":"5351",
    "sg:province":"Namur",
    "sg:tags":[
        "toy",
        "-"
    ],
    "wof:name":"Bilboquet (le)",
    "wof:placetype":"venue"
},
  "geometry": {"coordinates":[5.143901825,50.4593048096],"type":"Point"}
}