{
  "type": "Feature",
  "properties": {
    "addr:full":"Boulevard De La Sauveni\u00c8re 138 Luik (groot) Li\u00e8ge 4000",
    "addr:housenumber":"138",
    "addr:postcode":"4000",
    "addr:street":"Boulevard De La Sauvenie\u0300Re;Luik Groot Lie\u0300Ge",
    "iso:country":"BE",
    "sg:address":"Boulevard De La Sauveni\u00c8re 138",
    "sg:city":"Luik (groot)",
    "sg:classifiers":[
        {
            "category":"Personal",
            "subcategory":"Beauty Salon",
            "type":"Services"
        }
    ],
    "sg:phone":"+32 4 223 00 14",
    "sg:postcode":"4000",
    "sg:province":"Li\u00e8ge",
    "sg:tags":[
        "de",
        "coiffure"
    ],
    "wof:name":"Serge",
    "wof:placetype":"venue"
},
  "geometry": {"coordinates":[5.5669789314,50.6413116455],"type":"Point"}
}