{
  "type": "Feature",
  "properties": {
    "addr:full":"August Van Landeghemstraat 9 Willebroek Antwerpen 2830",
    "addr:housenumber":"9",
    "addr:postcode":"2830",
    "addr:street":"August Van Landeghemstraat",
    "iso:country":"BE",
    "sg:address":"August Van Landeghemstraat 9",
    "sg:city":"Willebroek",
    "sg:orig_category":"Solariums",
    "sg:phone":"+32 3 866 58 59",
    "sg:postcode":"2830",
    "sg:province":"Antwerpen",
    "wof:name":"Sunlife",
    "wof:placetype":"venue"
},
  "geometry": {"coordinates":[4.3602671623,51.0609970093],"type":"Point"}
}