{
  "type": "Feature",
  "properties": {
    "addr:full":"Grand Route 120 Hotton (marenne) Luxembourg 6990",
    "addr:postcode":"6990",
    "addr:street":"Grand Route 120",
    "iso:country":"BE",
    "sg:address":"Grand Route 120",
    "sg:city":"Hotton (marenne)",
    "sg:classifiers":[
        {
            "category":"Conference Center",
            "type":"Public Place"
        }
    ],
    "sg:phone":"+32 84 31 16 11",
    "sg:postcode":"6990",
    "sg:province":"Luxembourg",
    "sg:tags":[
        "terrain",
        "vehicle"
    ],
    "wof:name":"Hanciaux",
    "wof:placetype":"venue"
},
  "geometry": {"coordinates":[5.3847260475,50.2432899475],"type":"Point"}
}