{
  "type": "Feature",
  "properties": {
    "iso:country":"BE",
    "sg:address":"Laarstraat 24",
    "sg:city":"Kampenhout",
    "sg:classifiers":[
        {
            "category":"Cafe",
            "type":"Food & Drink"
        }
    ],
    "sg:phone":"+32 16 65 53 62",
    "sg:postcode":"1910",
    "sg:province":"Vlaams-Brabant",
    "sg:tags":[
        "caf\u00e9s"
    ],
    "wof:name":"Beire Fluit",
    "wof:placetype":"venue"
},
  "geometry": {"coordinates":[4.5487699509,50.9223632812],"type":"Point"}
}