{
  "type": "Feature",
  "properties": {
    "iso:country":"BE",
    "sg:address":"Rue Saint-bruno 20",
    "sg:city":"Tournai",
    "sg:classifiers":[
        {
            "category":"Organizations",
            "subcategory":"Professional Association",
            "type":"Services"
        }
    ],
    "sg:phone":"+32 69 23 56 05",
    "sg:postcode":"7500",
    "sg:province":"Hainaut",
    "sg:tags":[
        "organisation",
        "seminar"
    ],
    "wof:name":"Le Chateau De Cartes",
    "wof:placetype":"venue"
},
  "geometry": {"coordinates":[3.3890259266,50.6114845276],"type":"Point"}
}