{
  "type": "Feature",
  "properties": {
    "iso:country":"BE",
    "sg:address":"Neerstalse Steenweg 88",
    "sg:city":"Vorst/forest",
    "sg:orig_category":"HUISBRANDOLIE",
    "sg:phone":"+32 2 376 07 85",
    "sg:postcode":"1190",
    "sg:province":"Bruxelles-Capitale",
    "wof:name":"Fe. Slagmulder",
    "wof:placetype":"venue"
},
  "geometry": {"coordinates":[4.3154449463,50.8071556091],"type":"Point"}
}