{
  "type": "Feature",
  "properties": {
    "addr:full":"Satenrozen 10 Kontich Antwerpen 2550",
    "addr:housenumber":"10",
    "addr:postcode":"2550",
    "addr:street":"Satenrozen",
    "iso:country":"BE",
    "sg:address":"Satenrozen 10",
    "sg:city":"Kontich",
    "sg:classifiers":[
        {
            "category":"Home & Garden",
            "subcategory":"Carpets & Floor Coverings",
            "type":"Retail Goods"
        }
    ],
    "sg:phone":"+32 3 457 69 42",
    "sg:postcode":"2550",
    "sg:province":"Antwerpen",
    "sg:tags":[
        "parquet"
    ],
    "wof:name":"Ado Parketvloeren Nv",
    "wof:placetype":"venue"
},
  "geometry": {"coordinates":[4.4137301445,51.1232795715],"type":"Point"}
}