{
  "type": "Feature",
  "properties": {
    "addr:full":"Thonetlaan 133 Antwerpen Antwerpen 2050",
    "addr:housenumber":"133",
    "addr:postcode":"2050",
    "addr:street":"Thonetlaan",
    "iso:country":"BE",
    "sg:address":"Thonetlaan 133",
    "sg:city":"Antwerpen",
    "sg:classifiers":[
        {
            "category":"Banks & Credit Unions",
            "subcategory":"Investment Brokerage",
            "type":"Services"
        }
    ],
    "sg:phone":"+32 3 219 36 22",
    "sg:postcode":"2050",
    "sg:province":"Antwerpen",
    "sg:tags":[
        "-",
        "sale",
        "yachts",
        "accessory",
        "pleasure",
        "boat"
    ],
    "wof:name":"Batoo",
    "wof:placetype":"venue"
},
  "geometry": {"coordinates":[4.3919348717,51.2290725708],"type":"Point"}
}