{
  "type": "Feature",
  "properties": {
    "iso:country":"BE",
    "sg:address":"Place Du G\u00c9n\u00c9ral Leman 33",
    "sg:city":"Li\u00c8ge",
    "sg:orig_category":"Industri\u00eble wasserijen and droogkuis",
    "sg:phone":"+32 4 229 33 63",
    "sg:postcode":"4000",
    "sg:province":"Li\u00e8ge",
    "wof:name":"Nettoyage Sec Aigle Noir",
    "wof:placetype":"venue"
},
  "geometry": {"coordinates":[5.5741591454,50.6203346252],"type":"Point"}
}