{
  "type": "Feature",
  "properties": {
    "addr:full":"Route De La Marache 4 Lasne (ohain) Brabant Wallon 1380",
    "addr:housenumber":"4",
    "addr:postcode":"1380",
    "addr:street":"Route De La Marache;Wallon",
    "iso:country":"BE",
    "sg:address":"Route De La Marache 4",
    "sg:city":"Lasne (ohain)",
    "sg:classifiers":[
        {
            "category":"Real Estate",
            "subcategory":"Real Estate Services",
            "type":"Services"
        }
    ],
    "sg:phone":"+32 2 351 19 60",
    "sg:postcode":"1380",
    "sg:province":"Brabant Wallon",
    "wof:name":"Nanouche Immo Sa",
    "wof:placetype":"venue"
},
  "geometry": {"coordinates":[4.483235836,50.6850166321],"type":"Point"}
}