{
  "type": "Feature",
  "properties": {
    "addr:full":"Stenaertberg 3 Sint-truiden Limburg 3800",
    "addr:housenumber":"3",
    "addr:postcode":"3800",
    "addr:street":"Stenaertberg",
    "iso:country":"BE",
    "sg:address":"Stenaertberg 3",
    "sg:city":"Sint-truiden",
    "sg:classifiers":[
        {
            "category":"Health Services",
            "subcategory":"Health Practitioner",
            "type":"Services"
        }
    ],
    "sg:phone":"+32 11 69 47 38",
    "sg:postcode":"3800",
    "sg:province":"Limburg",
    "sg:tags":[
        "therapist",
        "speech"
    ],
    "wof:name":"Morrhaye N",
    "wof:placetype":"venue"
},
  "geometry": {"coordinates":[5.1880779266,50.8181114197],"type":"Point"}
}