{
  "type": "Feature",
  "properties": {
    "addr:full":"Rue De La Mairie 20 Huy Li\u00e8ge 4500",
    "addr:housenumber":"20",
    "addr:postcode":"4500",
    "addr:street":"Rue De La Mairie",
    "iso:country":"BE",
    "sg:address":"Rue De La Mairie 20",
    "sg:city":"Huy",
    "sg:orig_category":"Entretien and r\u00e9parations de voitures",
    "sg:phone":"+32 85 21 42 68",
    "sg:postcode":"4500",
    "sg:province":"Li\u00e8ge",
    "wof:name":"Garage Watelet",
    "wof:placetype":"venue"
},
  "geometry": {"coordinates":[5.2637648582,50.5299835205],"type":"Point"}
}