{
  "type": "Feature",
  "properties": {
    "addr:full":"Paulusstraat 42 Herck-la-ville Limburg 3540",
    "addr:housenumber":"42",
    "addr:postcode":"3540",
    "addr:street":"Paulusstraat",
    "iso:country":"BE",
    "sg:address":"Paulusstraat 42",
    "sg:city":"Herck-la-ville",
    "sg:orig_category":"R\u00e9alisation de programmes and logiciels",
    "sg:phone":"+32 13 55 49 11",
    "sg:postcode":"3540",
    "sg:province":"Limburg",
    "wof:name":"Technosoft Belgi\u00cb",
    "wof:placetype":"venue"
},
  "geometry": {"coordinates":[5.1659698486,50.9407691956],"type":"Point"}
}