{
  "type": "Feature",
  "properties": {
    "addr:full":"Ring 25 Herentals (noorderwijk) Antwerpen 2200",
    "addr:housenumber":"25",
    "addr:postcode":"2200",
    "addr:street":"Ring",
    "iso:country":"BE",
    "sg:address":"Ring 25",
    "sg:city":"Herentals (noorderwijk)",
    "sg:classifiers":[
        {
            "category":"Insurance",
            "subcategory":"Insurance Agent",
            "type":"Services"
        }
    ],
    "sg:phone":"+32 14 26 21 11",
    "sg:postcode":"2200",
    "sg:province":"Antwerpen",
    "sg:tags":[
        "broker"
    ],
    "wof:name":"N & W Kantoor Claes Bvba",
    "wof:placetype":"venue"
},
  "geometry": {"coordinates":[4.8394799232,51.1399726868],"type":"Point"}
}