{
  "type": "Feature",
  "properties": {
    "iso:country":"BE",
    "sg:address":"Rue De Marchienne 17",
    "sg:city":"Charleroi",
    "sg:classifiers":[
        {
            "category":"Shopping",
            "subcategory":"Books",
            "type":"Retail Goods"
        }
    ],
    "sg:phone":"+32 71 33 28 27",
    "sg:postcode":"6000",
    "sg:province":"Hainaut",
    "sg:tags":[
        "bookseller"
    ],
    "wof:name":"Librair Universit De Charleroi",
    "wof:placetype":"venue"
},
  "geometry": {"coordinates":[4.4398388863,50.407749176],"type":"Point"}
}