{
  "type": "Feature",
  "properties": {
    "addr:full":"Rue Baille-cariotte 58 Colfontaine Hainaut 7340",
    "addr:housenumber":"58",
    "addr:postcode":"7340",
    "addr:street":"Rue Baille-Cariotte",
    "iso:country":"BE",
    "sg:address":"Rue Baille-cariotte 58",
    "sg:city":"Colfontaine",
    "sg:orig_category":"Vakantiehuizen",
    "sg:phone":"+32 65 67 34 83",
    "sg:postcode":"7340",
    "sg:province":"Hainaut",
    "wof:name":"Gillez",
    "wof:placetype":"venue"
},
  "geometry": {"coordinates":[3.8248078823,50.4003829956],"type":"Point"}
}