{
  "type": "Feature",
  "properties": {
    "iso:country":"BE",
    "sg:address":"Elisabethwal 15",
    "sg:city":"Tongeren",
    "sg:classifiers":[
        {
            "category":"Health Services",
            "subcategory":"Doctor",
            "type":"Services"
        }
    ],
    "sg:phone":"+32 12 23 49 50",
    "sg:postcode":"3700",
    "sg:province":"Limburg",
    "sg:tags":[
        "medicinephysicians",
        "surgeon"
    ],
    "wof:name":"Marguillier A",
    "wof:placetype":"venue"
},
  "geometry": {"coordinates":[5.4598789215,50.7791404724],"type":"Point"}
}