{
  "type": "Feature",
  "properties": {
    "addr:full":"Tieltsteenweg 28ba Wingene West-Vlaanderen 8750",
    "addr:housenumber":"28ba",
    "addr:postcode":"8750",
    "addr:street":"Tieltsteenweg",
    "iso:country":"BE",
    "sg:address":"Tieltsteenweg 28ba",
    "sg:city":"Wingene",
    "sg:orig_category":"Herstellingen and onderhoud van auto's",
    "sg:phone":"+32 51 65 57 55",
    "sg:postcode":"8750",
    "sg:province":"West-Vlaanderen",
    "wof:name":"Garage Nemegeer",
    "wof:placetype":"venue"
},
  "geometry": {"coordinates":[3.3023369312,51.0417060852],"type":"Point"}
}