{
  "type": "Feature",
  "properties": {
    "iso:country":"BE",
    "sg:address":"Brugsesteenweg 387",
    "sg:city":"Kuurne",
    "sg:classifiers":[
        {
            "category":"Personal",
            "subcategory":"Sauna",
            "type":"Services"
        }
    ],
    "sg:phone":"+32 56 72 65 18",
    "sg:postcode":"8520",
    "sg:province":"West-Vlaanderen",
    "sg:tags":[
        "installation",
        "-"
    ],
    "wof:name":"Saunashop (de)",
    "wof:placetype":"venue"
},
  "geometry": {"coordinates":[3.270950079,50.8673171997],"type":"Point"}
}