{
  "type": "Feature",
  "properties": {
    "iso:country":"BE",
    "sg:address":"Galerie Ravenstein 42",
    "sg:city":"Bruxelles",
    "sg:classifiers":[
        {
            "category":"Bars & Pubs",
            "type":"Food & Drink"
        }
    ],
    "sg:phone":"+32 2 511 49 09",
    "sg:postcode":"1000",
    "sg:province":"Bruxelles-Capitale",
    "wof:name":"Mont Des Arts",
    "wof:placetype":"venue"
},
  "geometry": {"coordinates":[4.3594450951,50.8449363708],"type":"Point"}
}