{
  "type": "Feature",
  "properties": {
    "addr:full":"Woestijnstraat 31 Bornem Antwerpen 2880",
    "addr:housenumber":"31",
    "addr:postcode":"2880",
    "addr:street":"Woestijnstraat",
    "iso:country":"BE",
    "sg:address":"Woestijnstraat 31",
    "sg:city":"Bornem",
    "sg:classifiers":[
        {
            "category":"Home & Garden",
            "subcategory":"Building Materials",
            "type":"Retail Goods"
        }
    ],
    "sg:phone":"+32 3 899 56 62",
    "sg:postcode":"2880",
    "sg:province":"Antwerpen",
    "sg:tags":[
        "window"
    ],
    "wof:name":"Decsys Nv",
    "wof:placetype":"venue"
},
  "geometry": {"coordinates":[4.2706918716,51.0937194824],"type":"Point"}
}