{
  "type": "Feature",
  "properties": {
    "iso:country":"BE",
    "sg:address":"Westerring 58",
    "sg:city":"Oudenaarde",
    "sg:classifiers":[
        {
            "category":"Transit Center",
            "subcategory":"Passenger",
            "type":"Transportation"
        }
    ],
    "sg:phone":"+32 477 34 76 20",
    "sg:postcode":"9700",
    "sg:province":"Oost-Vlaanderen",
    "sg:tags":[
        "car",
        "trailer"
    ],
    "wof:name":"Van De Putte D",
    "wof:placetype":"venue"
},
  "geometry": {"coordinates":[3.6155838966,50.8913116455],"type":"Point"}
}