{
  "type": "Feature",
  "properties": {
    "iso:country":"BE",
    "sg:address":"Rue Fonds De For\u00cat 20",
    "sg:city":"Fleron",
    "sg:classifiers":[
        {
            "category":"Cafe",
            "type":"Food & Drink"
        }
    ],
    "sg:phone":"+32 4 358 62 61",
    "sg:postcode":"4623",
    "sg:province":"Li\u00e8ge",
    "sg:tags":[
        "caf\u00e9s"
    ],
    "wof:name":"Fafchamps",
    "wof:placetype":"venue"
},
  "geometry": {"coordinates":[5.6843161583,50.6018600464],"type":"Point"}
}