{
  "type": "Feature",
  "properties": {
    "addr:full":"Varkensmarkt 14 Diepenbeek Limburg 3590",
    "addr:housenumber":"14",
    "addr:postcode":"3590",
    "addr:street":"Varkensmarkt",
    "iso:country":"BE",
    "sg:address":"Varkensmarkt 14",
    "sg:city":"Diepenbeek",
    "sg:classifiers":[
        {
            "category":"Shopping",
            "subcategory":"Florist",
            "type":"Retail Goods"
        }
    ],
    "sg:phone":"+32 11 22 86 98",
    "sg:postcode":"3590",
    "sg:province":"Limburg",
    "wof:name":"Bloemen Peter",
    "wof:placetype":"venue"
},
  "geometry": {"coordinates":[5.4188132286,50.9083099365],"type":"Point"}
}