{
  "type": "Feature",
  "properties": {
    "addr:full":"Heirbaan 75bb Beveren Oost-Vlaanderen 9120",
    "addr:housenumber":"75bb",
    "addr:postcode":"9120",
    "addr:street":"Heirbaan",
    "iso:country":"BE",
    "sg:address":"Heirbaan 75bb",
    "sg:city":"Beveren",
    "sg:orig_category":"Epiceries. Producteurs de l\u00e9gumes",
    "sg:phone":"+32 3 775 89 33",
    "sg:postcode":"9120",
    "sg:province":"Oost-Vlaanderen",
    "wof:name":"Marc De Grave",
    "wof:placetype":"venue"
},
  "geometry": {"coordinates":[4.2808489799,51.1861114502],"type":"Point"}
}