{
  "type": "Feature",
  "properties": {
    "addr:full":"Gratiebossen 4 Berlare Oost-Vlaanderen 9290",
    "addr:housenumber":"4",
    "addr:postcode":"9290",
    "addr:street":"Gratiebossen",
    "iso:country":"BE",
    "sg:address":"Gratiebossen 4",
    "sg:city":"Berlare",
    "sg:classifiers":[
        {
            "category":"Building & Trades",
            "subcategory":"Construction",
            "type":"Services"
        }
    ],
    "sg:phone":"+32 52 44 81 87",
    "sg:postcode":"9290",
    "sg:province":"Oost-Vlaanderen",
    "sg:tags":[
        "carpenter"
    ],
    "wof:name":"Pennewaert F",
    "wof:placetype":"venue"
},
  "geometry": {"coordinates":[4.0107278824,51.0504455566],"type":"Point"}
}