{
  "type": "Feature",
  "properties": {
    "addr:full":"Place De La Station 7 Namur Namur 5000",
    "addr:housenumber":"7",
    "addr:postcode":"5000",
    "addr:street":"Place De La Station",
    "iso:country":"BE",
    "sg:address":"Place De La Station 7",
    "sg:city":"Namur",
    "sg:classifiers":[
        {
            "category":"Bars & Pubs",
            "type":"Food & Drink"
        }
    ],
    "sg:phone":"+32 81 23 14 33",
    "sg:postcode":"5000",
    "sg:province":"Namur",
    "wof:name":"Copenhagen Taverne (le)",
    "wof:placetype":"venue"
},
  "geometry": {"coordinates":[4.8634328842,50.4683151245],"type":"Point"}
}