{
  "type": "Feature",
  "properties": {
    "iso:country":"BE",
    "sg:address":"Aarschotsesteenweg 604",
    "sg:city":"Leuven (wilsele)",
    "sg:classifiers":[
        {
            "category":"Professional",
            "subcategory":"Testing Lab",
            "type":"Services"
        }
    ],
    "sg:phone":"+32 16 44 53 15",
    "sg:postcode":"3012",
    "sg:province":"Vlaams-Brabant",
    "sg:tags":[
        "chemist"
    ],
    "wof:name":"Laevers",
    "wof:placetype":"venue"
},
  "geometry": {"coordinates":[4.7207231522,50.9229927063],"type":"Point"}
}