{
  "type": "Feature",
  "properties": {
    "addr:full":"Place Rouppe 4 Bruxelles Bruxelles-Capitale 1000",
    "addr:housenumber":"4",
    "addr:postcode":"1000",
    "addr:street":"Place Rouppe",
    "iso:country":"BE",
    "sg:address":"Place Rouppe 4",
    "sg:city":"Bruxelles",
    "sg:classifiers":[
        {
            "category":"Building & Trades",
            "subcategory":"Construction",
            "type":"Services"
        }
    ],
    "sg:phone":"+32 2 513 19 00",
    "sg:postcode":"1000",
    "sg:province":"Bruxelles-Capitale",
    "sg:tags":[
        "glazier"
    ],
    "wof:name":"Ok Service Sprl-bvba",
    "wof:placetype":"venue"
},
  "geometry": {"coordinates":[4.3455162048,50.8431282043],"type":"Point"}
}