{
  "type": "Feature",
  "properties": {
    "iso:country":"BE",
    "sg:address":"Sijselestraat 10",
    "sg:city":"Beernem",
    "sg:orig_category":"Boucheries",
    "sg:phone":"+32 50 78 86 25",
    "sg:postcode":"8730",
    "sg:province":"West-Vlaanderen",
    "wof:name":"Marc Desoete",
    "wof:placetype":"venue"
},
  "geometry": {"coordinates":[3.3391969204,51.170501709],"type":"Point"}
}