{
  "type": "Feature",
  "properties": {
    "iso:country":"BE",
    "sg:address":"Kapelstraat 15",
    "sg:city":"Sint-truiden",
    "sg:orig_category":"Herstellingen and onderhoud van auto's",
    "sg:phone":"+32 11 68 62 83",
    "sg:postcode":"3800",
    "sg:province":"Limburg",
    "wof:name":"Michel Plevoets",
    "wof:placetype":"venue"
},
  "geometry": {"coordinates":[5.181499958,50.8010826111],"type":"Point"}
}