{
  "type": "Feature",
  "properties": {
    "addr:full":"Roosbeekstraat 52 Sint-truiden (zepperen) Limburg 3800",
    "addr:housenumber":"52",
    "addr:postcode":"3800",
    "addr:street":"Roosbeekstraat",
    "iso:country":"BE",
    "sg:address":"Roosbeekstraat 52",
    "sg:city":"Sint-truiden (zepperen)",
    "sg:classifiers":[
        {
            "category":"Wholesale",
            "subcategory":"Machinery & Supplies",
            "type":"Manufacturing & Wholesale Goods"
        }
    ],
    "sg:phone":"+32 11 68 44 10",
    "sg:postcode":"3800",
    "sg:province":"Limburg",
    "sg:tags":[
        "agricultural",
        "tractor"
    ],
    "wof:name":"Nicola\u00ef",
    "wof:placetype":"venue"
},
  "geometry": {"coordinates":[5.2644920349,50.8347320557],"type":"Point"}
}