{
  "type": "Feature",
  "properties": {
    "addr:full":"Rue De La Station 66 Andenne (seilles) Namur 5300",
    "addr:housenumber":"66",
    "addr:postcode":"5300",
    "addr:street":"Rue De La Station",
    "iso:country":"BE",
    "sg:address":"Rue De La Station 66",
    "sg:city":"Andenne (seilles)",
    "sg:classifiers":[
        {
            "category":"Shopping",
            "subcategory":"Baby Store",
            "type":"Retail Goods"
        }
    ],
    "sg:phone":"+32 85 82 61 98",
    "sg:postcode":"5300",
    "sg:province":"Namur",
    "sg:tags":[
        "-",
        "accessory"
    ],
    "wof:name":"Bambino",
    "wof:placetype":"venue"
},
  "geometry": {"coordinates":[5.0982642174,50.4863739014],"type":"Point"}
}