{
  "type": "Feature",
  "properties": {
    "iso:country":"BE",
    "sg:address":"Goorstraat 58",
    "sg:city":"Nijlen",
    "sg:orig_category":"Non-Classified Establishments",
    "sg:phone":"+32 3 481 71 36",
    "sg:postcode":"2560",
    "sg:province":"Antwerpen",
    "wof:name":"Scheers Diamonds Cv",
    "wof:placetype":"venue"
},
  "geometry": {"coordinates":[4.6537971497,51.1560211182],"type":"Point"}
}