{
  "type": "Feature",
  "properties": {
    "iso:country":"BE",
    "sg:address":"Mechelsesteenweg 15-17",
    "sg:city":"Mortsel",
    "sg:classifiers":[
        {
            "category":"Restaurant",
            "type":"Food & Drink"
        }
    ],
    "sg:phone":"+32 3 440 78 17",
    "sg:postcode":"2640",
    "sg:province":"Antwerpen",
    "wof:name":"'t Barokske",
    "wof:placetype":"venue"
},
  "geometry": {"coordinates":[4.4509949684,51.1695137024],"type":"Point"}
}