{
  "type": "Feature",
  "properties": {
    "iso:country":"BE",
    "sg:address":"Leiweg 23",
    "sg:city":"Zemst (eppegem)",
    "sg:classifiers":[
        {
            "category":"Building & Trades",
            "subcategory":"Pest Control",
            "type":"Services"
        }
    ],
    "sg:phone":"+32 15 62 31 78",
    "sg:postcode":"1980",
    "sg:province":"Vlaams-Brabant",
    "sg:tags":[
        "remote",
        "system"
    ],
    "wof:name":"Seme",
    "wof:placetype":"venue"
},
  "geometry": {"coordinates":[4.4403848648,50.9625282288],"type":"Point"}
}