{
  "type": "Feature",
  "properties": {
    "iso:country":"BE",
    "sg:address":"Woeker 12",
    "sg:city":"Oudenaarde",
    "sg:orig_category":"Bouwmaterialen Gh",
    "sg:phone":"+32 55 31 58 56",
    "sg:postcode":"9700",
    "sg:province":"Oost-Vlaanderen",
    "wof:name":"Geeraert",
    "wof:placetype":"venue"
},
  "geometry": {"coordinates":[3.606306076,50.8451004028],"type":"Point"}
}