{
  "type": "Feature",
  "properties": {
    "addr:full":"Venecoweg 37 Nazareth Oost-Vlaanderen 9810",
    "addr:housenumber":"37",
    "addr:postcode":"9810",
    "addr:street":"Venecoweg",
    "iso:country":"BE",
    "sg:address":"Venecoweg 37",
    "sg:city":"Nazareth",
    "sg:orig_category":"Fa\u00e7ade Renovation",
    "sg:phone":"+32 9 381 65 00",
    "sg:postcode":"9810",
    "sg:province":"Oost-Vlaanderen",
    "wof:name":"Pentagon Plastics Nv",
    "wof:placetype":"venue"
},
  "geometry": {"coordinates":[3.5542340279,50.953338623],"type":"Point"}
}