{
  "type": "Feature",
  "properties": {
    "iso:country":"BE",
    "sg:address":"Albertvest 15",
    "sg:city":"Tienen",
    "sg:orig_category":"Hypermarch\u00e9s. Supermarch\u00e9s. Mat\u00e9riel de T\u00e9l\u00e9communication",
    "sg:phone":"+32 16 80 86 11",
    "sg:postcode":"3300",
    "sg:province":"Vlaams-Brabant",
    "wof:name":"Carrefour - Maxitec",
    "wof:placetype":"venue"
},
  "geometry": {"coordinates":[4.9284071922,50.8124809265],"type":"Point"}
}