{
  "type": "Feature",
  "properties": {
    "addr:full":"Londerzeelsesteenweg 28 Meise Vlaams-Brabant 1861",
    "addr:housenumber":"28",
    "addr:postcode":"1861",
    "addr:street":"Londerzeelsesteenweg",
    "iso:country":"BE",
    "sg:address":"Londerzeelsesteenweg 28",
    "sg:city":"Meise",
    "sg:orig_category":"Producteurs de l\u00e9gumes",
    "sg:phone":"+32 52 30 07 44",
    "sg:postcode":"1861",
    "sg:province":"Vlaams-Brabant",
    "wof:name":"Pierre Mertens",
    "wof:placetype":"venue"
},
  "geometry": {"coordinates":[4.3212008476,50.9961280823],"type":"Point"}
}