{
  "type": "Feature",
  "properties": {
    "addr:full":"Rue O. Dupuis 44 Manage Hainaut 7170",
    "addr:housenumber":"44",
    "addr:postcode":"7170",
    "addr:street":"Rue O. Dupuis",
    "iso:country":"BE",
    "sg:address":"Rue O. Dupuis 44",
    "sg:city":"Manage",
    "sg:orig_category":"Fotogravure and zetwerk Secretariaatsdiensten",
    "sg:phone":"+32 64 26 54 61",
    "sg:postcode":"7170",
    "sg:province":"Hainaut",
    "wof:name":"Laurent Jaunart",
    "wof:placetype":"venue"
},
  "geometry": {"coordinates":[4.2254772186,50.468208313],"type":"Point"}
}