{
  "type": "Feature",
  "properties": {
    "addr:full":"Rue De Steenkerque 49a Soignies Hainaut 7060",
    "addr:housenumber":"49a",
    "addr:postcode":"7060",
    "addr:street":"Rue De Steenkerque",
    "iso:country":"BE",
    "sg:address":"Rue De Steenkerque 49a",
    "sg:city":"Soignies",
    "sg:classifiers":[
        {
            "category":"Food & Beverages",
            "subcategory":"Liquor & Beverages",
            "type":"Retail Goods"
        }
    ],
    "sg:phone":"+32 67 34 17 37",
    "sg:postcode":"7060",
    "sg:province":"Hainaut",
    "sg:tags":[
        "-",
        "spirit",
        "wine"
    ],
    "wof:name":"Bacchus Sc",
    "wof:placetype":"venue"
},
  "geometry": {"coordinates":[4.072042942,50.5817222595],"type":"Point"}
}