{
  "type": "Feature",
  "properties": {
    "addr:full":"Brugstraat 43 Wevelgem West-Vlaanderen 8560",
    "addr:housenumber":"43",
    "addr:postcode":"8560",
    "addr:street":"Brugstraat",
    "iso:country":"BE",
    "sg:address":"Brugstraat 43",
    "sg:city":"Wevelgem",
    "sg:classifiers":[
        {
            "category":"Brewery",
            "type":"Food & Drink"
        }
    ],
    "sg:phone":"+32 56 41 82 41",
    "sg:postcode":"8560",
    "sg:province":"West-Vlaanderen",
    "wof:name":"Brouwerij De Ranke Bvba",
    "wof:placetype":"venue"
},
  "geometry": {"coordinates":[3.1854939461,50.8106575012],"type":"Point"}
}