{
  "type": "Feature",
  "properties": {
    "addr:full":"Schoolstraat 14 Deerlijk West-Vlaanderen 8540",
    "addr:housenumber":"14",
    "addr:postcode":"8540",
    "addr:street":"Schoolstraat",
    "iso:country":"BE",
    "sg:address":"Schoolstraat 14",
    "sg:city":"Deerlijk",
    "sg:classifiers":[
        {
            "category":"Shopping",
            "subcategory":"Beauty & Cosmetics",
            "type":"Retail Goods"
        }
    ],
    "sg:phone":"+32 56 71 17 96",
    "sg:postcode":"8540",
    "sg:province":"West-Vlaanderen",
    "sg:tags":[
        "-",
        "perfumery"
    ],
    "wof:name":"Vandendriessche Marguerit",
    "wof:placetype":"venue"
},
  "geometry": {"coordinates":[3.3560459614,50.8528518677],"type":"Point"}
}