{
  "type": "Feature",
  "properties": {
    "addr:full":"Hasseltsebaan 17 Diest Vlaams-Brabant 3290",
    "addr:housenumber":"17",
    "addr:postcode":"3290",
    "addr:street":"Hasseltsebaan",
    "iso:country":"BE",
    "sg:address":"Hasseltsebaan 17",
    "sg:city":"Diest",
    "sg:orig_category":"Kapsalons",
    "sg:phone":"+32 13 66 89 06",
    "sg:postcode":"3290",
    "sg:province":"Vlaams-Brabant",
    "wof:name":"Martina Severijns",
    "wof:placetype":"venue"
},
  "geometry": {"coordinates":[5.0528011322,50.9820976257],"type":"Point"}
}