{
  "type": "Feature",
  "properties": {
    "addr:full":"Rue De L'orjo 19b Namur (jambes) Namur 5100",
    "addr:housenumber":"19b",
    "addr:postcode":"5100",
    "addr:street":"Rue De L'Orjo",
    "iso:country":"BE",
    "sg:address":"Rue De L'orjo 19b",
    "sg:city":"Namur (jambes)",
    "sg:classifiers":[
        {
            "category":"Communications",
            "subcategory":"Film & Video Production",
            "type":"Services"
        }
    ],
    "sg:phone":"+32 81 30 93 98",
    "sg:postcode":"5100",
    "sg:province":"Namur",
    "sg:tags":[
        "realisation",
        "-"
    ],
    "wof:name":"Jendot P",
    "wof:placetype":"venue"
},
  "geometry": {"coordinates":[4.8831691742,50.4606323242],"type":"Point"}
}