{
  "type": "Feature",
  "properties": {
    "addr:full":"Bredabaan 617b4 Brasschaat Antwerpen 2930",
    "addr:housenumber":"617b4",
    "addr:postcode":"2930",
    "addr:street":"Bredabaan",
    "iso:country":"BE",
    "sg:address":"Bredabaan 617b4",
    "sg:city":"Brasschaat",
    "sg:classifiers":[
        {
            "category":"Cafe",
            "type":"Food & Drink"
        }
    ],
    "sg:phone":"+32 3 651 95 41",
    "sg:postcode":"2930",
    "sg:province":"Antwerpen",
    "sg:tags":[
        "caf\u00e9s"
    ],
    "wof:name":"F. Van Den Broek",
    "wof:placetype":"venue"
},
  "geometry": {"coordinates":[4.5008068085,51.2998313904],"type":"Point"}
}