{
  "type": "Feature",
  "properties": {
    "addr:full":"Vaartdijk-zuid 32 Middelkerke (leffinge) West-Vlaanderen 8432",
    "addr:housenumber":"32",
    "addr:postcode":"8432",
    "addr:street":"Vaartdijk-Zuid",
    "iso:country":"BE",
    "sg:address":"Vaartdijk-zuid 32",
    "sg:city":"Middelkerke (leffinge)",
    "sg:classifiers":[
        {
            "category":"Health Services",
            "subcategory":"Health Practitioner",
            "type":"Services"
        }
    ],
    "sg:phone":"+32 59 80 67 83",
    "sg:postcode":"8432",
    "sg:province":"West-Vlaanderen",
    "sg:tags":[
        "physiotherapist"
    ],
    "wof:name":"Proot Tim",
    "wof:placetype":"venue"
},
  "geometry": {"coordinates":[2.7594919205,51.146446228],"type":"Point"}
}