{
  "type": "Feature",
  "properties": {
    "addr:full":"Cit\u00c9-du-centenaire 244 Tellin Luxembourg 6927",
    "addr:housenumber":"244",
    "addr:postcode":"6927",
    "iso:country":"BE",
    "sg:address":"Cit\u00c9-du-centenaire 244",
    "sg:city":"Tellin",
    "sg:orig_category":"MEUBELONTWERP AND -INSTALLATIE",
    "sg:phone":"+32 84 36 62 59",
    "sg:postcode":"6927",
    "sg:province":"Luxembourg",
    "wof:name":"Jacques Deom",
    "wof:placetype":"venue"
},
  "geometry": {"coordinates":[5.2186660767,50.0875473022],"type":"Point"}
}