{
  "type": "Feature",
  "properties": {
    "iso:country":"BE",
    "sg:address":"Sint-bavoplein 16",
    "sg:city":"Boechout",
    "sg:classifiers":[
        {
            "category":"Bars & Pubs",
            "type":"Food & Drink"
        }
    ],
    "sg:phone":"+32 3 455 13 45",
    "sg:postcode":"2530",
    "sg:province":"Antwerpen",
    "wof:name":"Falco Snooker",
    "wof:placetype":"venue"
},
  "geometry": {"coordinates":[4.491353035,51.159198761],"type":"Point"}
}