{
  "type": "Feature",
  "properties": {
    "addr:full":"Nieuwpoortkeiweg 31 Veurne West-Vlaanderen 8630",
    "addr:housenumber":"31",
    "addr:postcode":"8630",
    "addr:street":"Nieuwpoortkeiweg",
    "iso:country":"BE",
    "sg:address":"Nieuwpoortkeiweg 31",
    "sg:city":"Veurne",
    "sg:classifiers":[
        {
            "category":"Professional",
            "subcategory":"Art Services",
            "type":"Services"
        }
    ],
    "sg:phone":"+32 58 31 16 87",
    "sg:postcode":"8630",
    "sg:province":"West-Vlaanderen",
    "sg:tags":[
        "photographer"
    ],
    "wof:name":"Schreel F",
    "wof:placetype":"venue"
},
  "geometry": {"coordinates":[2.6694691181,51.076789856],"type":"Point"}
}