{
  "type": "Feature",
  "properties": {
    "iso:country":"BE",
    "sg:address":"Rue Cl\u00e8rue 56",
    "sg:city":"La Roche-en-ardenne",
    "sg:classifiers":[
        {
            "category":"Professional",
            "subcategory":"Computer Services",
            "type":"Services"
        }
    ],
    "sg:phone":"+32 84 41 29 21",
    "sg:postcode":"6980",
    "sg:province":"Luxembourg",
    "sg:tags":[
        "-",
        "processing",
        "data"
    ],
    "wof:name":"Voyager's Technology",
    "wof:placetype":"venue"
},
  "geometry": {"coordinates":[5.5774598122,50.1817893982],"type":"Point"}
}