{
  "type": "Feature",
  "properties": {
    "addr:full":"Rue Peltzer De Clermont 82 Verviers Li\u00e8ge 4800",
    "addr:housenumber":"82",
    "addr:postcode":"4800",
    "addr:street":"Rue Peltzer De Clermont",
    "iso:country":"BE",
    "sg:address":"Rue Peltzer De Clermont 82",
    "sg:city":"Verviers",
    "sg:classifiers":[
        {
            "category":"Personal",
            "subcategory":"Barber",
            "type":"Services"
        }
    ],
    "sg:phone":"+32 495 89 73 78",
    "sg:postcode":"4800",
    "sg:province":"Li\u00e8ge",
    "sg:tags":[
        "gentleman",
        "salon",
        "-",
        "hairdressing"
    ],
    "wof:name":"Hom'air",
    "wof:placetype":"venue"
},
  "geometry": {"coordinates":[5.8516402245,50.5914497375],"type":"Point"}
}