{
  "type": "Feature",
  "properties": {
    "iso:country":"BE",
    "sg:address":"Sint-alenalaan 89",
    "sg:city":"Dilbeek",
    "sg:classifiers":[
        {
            "category":"Health Services",
            "subcategory":"Dentist",
            "type":"Services"
        }
    ],
    "sg:phone":"+32 2 466 34 31",
    "sg:postcode":"1700",
    "sg:province":"Vlaams-Brabant",
    "wof:name":"D'hoe Brigitte",
    "wof:placetype":"venue"
},
  "geometry": {"coordinates":[4.2657709122,50.8481216431],"type":"Point"}
}