{
  "type": "Feature",
  "properties": {
    "addr:full":"Provincielaan 65 Puurs (breendonk) Antwerpen 2870",
    "addr:housenumber":"65",
    "addr:postcode":"2870",
    "addr:street":"Provincielaan",
    "iso:country":"BE",
    "sg:address":"Provincielaan 65",
    "sg:city":"Puurs (breendonk)",
    "sg:classifiers":[
        {
            "category":"Professional",
            "subcategory":"Computer Services",
            "type":"Services"
        }
    ],
    "sg:phone":"+32 3 298 00 42",
    "sg:postcode":"2870",
    "sg:province":"Antwerpen",
    "sg:tags":[
        "webdesign",
        "-",
        "internet"
    ],
    "wof:name":"Digiworks Bvba",
    "wof:placetype":"venue"
},
  "geometry": {"coordinates":[4.3000788689,51.0426025391],"type":"Point"}
}