{
  "type": "Feature",
  "properties": {
    "addr:full":"Chauss\u00e9e De Wervicq 313 Comines-warneton (comines) Hainaut 7780",
    "addr:housenumber":"313",
    "addr:postcode":"7780",
    "addr:street":"Chausse\u0301E De Wervicq",
    "iso:country":"BE",
    "sg:address":"Chauss\u00e9e De Wervicq 313",
    "sg:city":"Comines-warneton (comines)",
    "sg:classifiers":[
        {
            "category":"Autos & Motor Vehicles",
            "subcategory":"Fuel & Gas Station",
            "type":"Retail Goods"
        }
    ],
    "sg:phone":"+32 56 55 67 55",
    "sg:postcode":"7780",
    "sg:province":"Hainaut",
    "wof:name":"Power Station",
    "wof:placetype":"venue"
},
  "geometry": {"coordinates":[3.0177650452,50.7766265869],"type":"Point"}
}