{
  "type": "Feature",
  "properties": {
    "addr:full":"Dr\u00c8ve De La Charte 11 Ganshoren Bruxelles-Capitale 1083",
    "addr:housenumber":"11",
    "addr:postcode":"1083",
    "addr:street":"Dre\u0300Ve De La Charte",
    "iso:country":"BE",
    "sg:address":"Dr\u00c8ve De La Charte 11",
    "sg:city":"Ganshoren",
    "sg:orig_category":"Artistes ind\u00e9pendants",
    "sg:phone":"+32 2 426 86 73",
    "sg:postcode":"1083",
    "sg:province":"Bruxelles-Capitale",
    "wof:name":"Gosse",
    "wof:placetype":"venue"
},
  "geometry": {"coordinates":[4.3174152374,50.8784255981],"type":"Point"}
}