{
  "type": "Feature",
  "properties": {
    "addr:full":"Rue Du Mayeuri 30 Marche-en-famenne Hainaut 6032",
    "addr:housenumber":"30",
    "addr:postcode":"6032",
    "addr:street":"Rue Du Mayeuri",
    "iso:country":"BE",
    "sg:address":"Rue Du Mayeuri 30",
    "sg:city":"Marche-en-famenne",
    "sg:orig_category":"Ziekenhuizen and zorginstellingen",
    "sg:phone":"+32 71 43 03 87",
    "sg:postcode":"6032",
    "sg:province":"Hainaut",
    "wof:name":"Centre Orthog\u00c9nique",
    "wof:placetype":"venue"
},
  "geometry": {"coordinates":[4.4175691605,50.3973808289],"type":"Point"}
}