{
  "type": "Feature",
  "properties": {
    "iso:country":"BE",
    "sg:address":"Chauss\u00e9e Du Luxembourg 39",
    "sg:city":"Neufch\u00e2teau (hamipr\u00e9)",
    "sg:classifiers":[
        {
            "category":"Structure",
            "subcategory":"Office Building",
            "type":"Public Place"
        }
    ],
    "sg:phone":"+32 61 27 82 77",
    "sg:postcode":"6840",
    "sg:province":"Luxembourg",
    "sg:tags":[
        "roofing",
        "slate"
    ],
    "wof:name":"Klepper Pascal Sprl",
    "wof:placetype":"venue"
},
  "geometry": {"coordinates":[5.4346451759,49.8411598206],"type":"Point"}
}