{
  "type": "Feature",
  "properties": {
    "addr:full":"Hoeven 1 Lille (poederlee) Antwerpen 2275",
    "addr:housenumber":"1",
    "addr:postcode":"2275",
    "addr:street":"Hoeven",
    "iso:country":"BE",
    "sg:address":"Hoeven 1",
    "sg:city":"Lille (poederlee)",
    "sg:classifiers":[
        {
            "category":"Sports & Exercise",
            "subcategory":"Gym",
            "type":"Entertainment"
        }
    ],
    "sg:phone":"+32 14 65 26 37",
    "sg:postcode":"2275",
    "sg:province":"Antwerpen",
    "sg:tags":[
        "access",
        "gymnastics",
        "-",
        "apparatus",
        "fitness"
    ],
    "wof:name":"Power Plate Belgium Bvba",
    "wof:placetype":"venue"
},
  "geometry": {"coordinates":[4.8395109177,51.2182350159],"type":"Point"}
}