{
  "type": "Feature",
  "properties": {
    "addr:full":"Molenkouterbaan 4 Aalst (moorsel) Oost-Vlaanderen 9310",
    "addr:housenumber":"4",
    "addr:postcode":"9310",
    "addr:street":"Molenkouterbaan;Moorsel Oost-Vlaanderen",
    "iso:country":"BE",
    "sg:address":"Molenkouterbaan 4",
    "sg:city":"Aalst (moorsel)",
    "sg:classifiers":[
        {
            "category":"Wholesale",
            "subcategory":"Plants",
            "type":"Manufacturing & Wholesale Goods"
        }
    ],
    "sg:phone":"+32 53 77 88 55",
    "sg:postcode":"9310",
    "sg:province":"Oost-Vlaanderen",
    "sg:tags":[
        "whol",
        "flower",
        "-",
        "grower"
    ],
    "wof:name":"Vermoesen K",
    "wof:placetype":"venue"
},
  "geometry": {"coordinates":[4.098400116,50.9477767944],"type":"Point"}
}