{
  "type": "Feature",
  "properties": {
    "addr:full":"Rue Bureau 83 Fleron Li\u00e8ge 4621",
    "addr:housenumber":"83",
    "addr:postcode":"4621",
    "addr:street":"Rue Bureau",
    "iso:country":"BE",
    "sg:address":"Rue Bureau 83",
    "sg:city":"Fleron",
    "sg:orig_category":"M\u00e9decins and sp\u00e9cialistes",
    "sg:phone":"+32 4 358 39 75",
    "sg:postcode":"4621",
    "sg:province":"Li\u00e8ge",
    "wof:name":"Eric Englebert",
    "wof:placetype":"venue"
},
  "geometry": {"coordinates":[5.6962609291,50.6133613586],"type":"Point"}
}