{
  "type": "Feature",
  "properties": {
    "iso:country":"BE",
    "sg:address":"Brugstraat 35",
    "sg:city":"Bocholt",
    "sg:classifiers":[
        {
            "category":"Professional",
            "subcategory":"Management & Consulting",
            "type":"Services"
        }
    ],
    "sg:phone":"+32 89 46 48 51",
    "sg:postcode":"3950",
    "sg:province":"Limburg",
    "sg:tags":[
        "consultant"
    ],
    "wof:name":"Bakos Annelies Bvba",
    "wof:placetype":"venue"
},
  "geometry": {"coordinates":[5.583990097,51.1762084961],"type":"Point"}
}