{
  "type": "Feature",
  "properties": {
    "addr:full":"Joseph Bensstraat 73 Ukkel/uccle Bruxelles-Capitale 1180",
    "addr:housenumber":"73",
    "addr:postcode":"1180",
    "addr:street":"Bensstraat;/",
    "iso:country":"BE",
    "sg:address":"Joseph Bensstraat 73",
    "sg:city":"Ukkel/uccle",
    "sg:orig_category":"Artsen and specialisten",
    "sg:phone":"+32 2 344 38 32",
    "sg:postcode":"1180",
    "sg:province":"Bruxelles-Capitale",
    "wof:name":"Paul Depr\u00c9",
    "wof:placetype":"venue"
},
  "geometry": {"coordinates":[4.3333859444,50.8071022034],"type":"Point"}
}