{
  "type": "Feature",
  "properties": {
    "iso:country":"BE",
    "sg:address":"Cours D'orval 5",
    "sg:city":"Ottignies-louvain-la-neuve (louvain-la-neuve)",
    "sg:classifiers":[
        {
            "category":"Health Services",
            "subcategory":"Doctor",
            "type":"Services"
        }
    ],
    "sg:phone":"+32 10 45 97 22",
    "sg:postcode":"1348",
    "sg:province":"Brabant Wallon",
    "sg:tags":[
        "psychotherapist",
        "psychoanalyst"
    ],
    "wof:name":"Alpedrinha J.",
    "wof:placetype":"venue"
},
  "geometry": {"coordinates":[4.6152129173,50.6743469238],"type":"Point"}
}