{
  "type": "Feature",
  "properties": {
    "iso:country":"BE",
    "sg:address":"Kloosterdam 19",
    "sg:city":"Grimbergen",
    "sg:classifiers":[
        {
            "category":"Professional",
            "subcategory":"Art Services",
            "type":"Services"
        }
    ],
    "sg:phone":"+32 2 269 53 83",
    "sg:postcode":"1850",
    "sg:province":"Vlaams-Brabant",
    "sg:tags":[
        "sculptor"
    ],
    "wof:name":"Dubois D'enghien R",
    "wof:placetype":"venue"
},
  "geometry": {"coordinates":[4.3722500801,50.9366798401],"type":"Point"}
}