{
  "type": "Feature",
  "properties": {
    "iso:country":"BE",
    "sg:address":"Generaal Lemanstraat 114",
    "sg:city":"Etterbeek/etterbeek",
    "sg:orig_category":"Artiesten and kunstenaars",
    "sg:phone":"+32 2 230 46 14",
    "sg:postcode":"1040",
    "sg:province":"Bruxelles-Capitale",
    "wof:name":"Anne Carpriaux",
    "wof:placetype":"venue"
},
  "geometry": {"coordinates":[4.3863492012,50.8368911743],"type":"Point"}
}