{
  "type": "Feature",
  "properties": {
    "iso:country":"BE",
    "sg:address":"Boerenkrijglaan 191",
    "sg:city":"Westerlo",
    "sg:classifiers":[
        {
            "category":"Cafe",
            "type":"Food & Drink"
        }
    ],
    "sg:phone":"+32 14 54 42 34",
    "sg:postcode":"2260",
    "sg:province":"Antwerpen",
    "sg:tags":[
        "caf\u00e9s"
    ],
    "wof:name":"Caf\u00c9 Sooi Van 't Hof",
    "wof:placetype":"venue"
},
  "geometry": {"coordinates":[4.9085288048,51.0990638733],"type":"Point"}
}