{
  "type": "Feature",
  "properties": {
    "addr:full":"Rue De La Vaulx 58 Fl\u00e9ron (retinne) Li\u00e8ge 4621",
    "addr:housenumber":"58",
    "addr:postcode":"4621",
    "addr:street":"Rue De La Vaulx",
    "iso:country":"BE",
    "sg:address":"Rue De La Vaulx 58",
    "sg:city":"Fl\u00e9ron (retinne)",
    "sg:classifiers":[
        {
            "category":"Health Services",
            "subcategory":"Dentist",
            "type":"Services"
        }
    ],
    "sg:phone":"+32 4 358 18 06",
    "sg:postcode":"4621",
    "sg:province":"Li\u00e8ge",
    "wof:name":"Schyns Monique",
    "wof:placetype":"venue"
},
  "geometry": {"coordinates":[5.7027587891,50.6277275085],"type":"Point"}
}