{
  "type": "Feature",
  "properties": {
    "addr:full":"Rue De Fontaine 5 Grace-hollogne Li\u00e8ge 4460",
    "addr:housenumber":"5",
    "addr:postcode":"4460",
    "addr:street":"Rue De Fontaine",
    "iso:country":"BE",
    "sg:address":"Rue De Fontaine 5",
    "sg:city":"Grace-hollogne",
    "sg:orig_category":"Enseignement maternel and primaire",
    "sg:phone":"+32 4 250 13 19",
    "sg:postcode":"4460",
    "sg:province":"Li\u00e8ge",
    "wof:name":"Ecole Fondamentale Libre",
    "wof:placetype":"venue"
},
  "geometry": {"coordinates":[5.4154901505,50.6256904602],"type":"Point"}
}