{
  "type": "Feature",
  "properties": {
    "addr:full":"Rue De Haerne 51 Bruxelles (etterbeek) Bruxelles-Capitale 1040",
    "addr:housenumber":"51",
    "addr:postcode":"1040",
    "addr:street":"Rue De Haerne",
    "iso:country":"BE",
    "sg:address":"Rue De Haerne 51",
    "sg:city":"Bruxelles (etterbeek)",
    "sg:classifiers":[
        {
            "category":"Social Services",
            "type":"Services"
        }
    ],
    "sg:phone":"+32 2 644 22 00",
    "sg:postcode":"1040",
    "sg:province":"Bruxelles-Capitale",
    "wof:name":"Modus Vivendi",
    "wof:placetype":"venue"
},
  "geometry": {"coordinates":[4.3822860718,50.8314361572],"type":"Point"}
}