{
  "type": "Feature",
  "properties": {
    "addr:full":"Bezelaervelden 11 Willebroek (blaasveld) Antwerpen 2830",
    "addr:housenumber":"11",
    "addr:postcode":"2830",
    "addr:street":"Bezelaervelden",
    "iso:country":"BE",
    "sg:address":"Bezelaervelden 11",
    "sg:city":"Willebroek (blaasveld)",
    "sg:classifiers":[
        {
            "category":"Building & Trades",
            "subcategory":"Construction",
            "type":"Services"
        }
    ],
    "sg:phone":"+32 3 866 00 25",
    "sg:postcode":"2830",
    "sg:province":"Antwerpen",
    "sg:tags":[
        "installation",
        "-",
        "central",
        "heating"
    ],
    "wof:name":"Van Loock Bvba",
    "wof:placetype":"venue"
},
  "geometry": {"coordinates":[4.3755760193,51.0549583435],"type":"Point"}
}