{
  "type": "Feature",
  "properties": {
    "addr:full":"Vaesstraat 3 Bree Limburg 3960",
    "addr:housenumber":"3",
    "addr:postcode":"3960",
    "addr:street":"Vaesstraat",
    "iso:country":"BE",
    "sg:address":"Vaesstraat 3",
    "sg:city":"Bree",
    "sg:orig_category":"Reclamebureaus",
    "sg:phone":"+32 89 47 36 57",
    "sg:postcode":"3960",
    "sg:province":"Limburg",
    "wof:name":"Kaat Vrancken",
    "wof:placetype":"venue"
},
  "geometry": {"coordinates":[5.5990691185,51.1407012939],"type":"Point"}
}