{
  "type": "Feature",
  "properties": {
    "iso:country":"BE",
    "sg:address":"Rue Pecquereau 18",
    "sg:city":"Tournai",
    "sg:orig_category":"Ruimtes voor conferenties, recepties and feesten",
    "sg:phone":"+32 69 54 89 54",
    "sg:postcode":"7530",
    "sg:province":"Hainaut",
    "wof:name":"Le Pelerin",
    "wof:placetype":"venue"
},
  "geometry": {"coordinates":[3.4877018929,50.5929870605],"type":"Point"}
}