{
  "type": "Feature",
  "properties": {
    "addr:full":"Rue Du Fosse-aux-loups 48 B Brussels Bruxelles-Capitale 1000",
    "addr:housenumber":"48 b",
    "addr:postcode":"1000",
    "addr:street":"Rue Du Fosse-Aux-Loups",
    "iso:country":"BE",
    "sg:address":"Rue Du Fosse-aux-loups 48 B",
    "sg:city":"Brussels",
    "sg:classifiers":[
        {
            "category":"Banks & Credit Unions",
            "subcategory":"Bank",
            "type":"Services"
        }
    ],
    "sg:postcode":"1000",
    "sg:province":"Bruxelles-Capitale",
    "wof:name":"Astridim",
    "wof:placetype":"venue"
},
  "geometry": {"coordinates":[4.356523037,50.8498725891],"type":"Point"}
}