{
  "type": "Feature",
  "properties": {
    "iso:country":"BE",
    "sg:address":"Route De Bouillon 2",
    "sg:city":"Gedinne",
    "sg:classifiers":[
        {
            "category":"Social Services",
            "subcategory":"Job Training",
            "type":"Services"
        }
    ],
    "sg:phone":"+32 61 58 85 60",
    "sg:postcode":"5575",
    "sg:province":"Namur",
    "sg:tags":[
        "de",
        "terrain",
        "camping"
    ],
    "wof:name":"Les Melezes",
    "wof:placetype":"venue"
},
  "geometry": {"coordinates":[4.9710659981,50.0287742615],"type":"Point"}
}