{
  "type": "Feature",
  "properties": {
    "addr:full":"Rue Fran\u00c7ois-dache 10 Floreffe Namur 5150",
    "addr:housenumber":"10",
    "addr:postcode":"5150",
    "addr:street":"Rue Franc\u0327Ois-Dache",
    "iso:country":"BE",
    "sg:address":"Rue Fran\u00c7ois-dache 10",
    "sg:city":"Floreffe",
    "sg:orig_category":"Diensten voor huisdieren",
    "sg:phone":"+32 81 44 11 71",
    "sg:postcode":"5150",
    "sg:province":"Namur",
    "wof:name":"La Main Du Ma\u00cetre",
    "wof:placetype":"venue"
},
  "geometry": {"coordinates":[4.7647600174,50.4562950134],"type":"Point"}
}