{
  "type": "Feature",
  "properties": {
    "addr:full":"Oppuursdorp 6 Sint-amands (oppuurs) Antwerpen 2890",
    "addr:housenumber":"6",
    "addr:postcode":"2890",
    "addr:street":"Oppuursdorp",
    "iso:country":"BE",
    "sg:address":"Oppuursdorp 6",
    "sg:city":"Sint-amands (oppuurs)",
    "sg:classifiers":[
        {
            "category":"Bakery",
            "type":"Food & Drink"
        }
    ],
    "sg:phone":"+32 3 889 08 64",
    "sg:postcode":"2890",
    "sg:province":"Antwerpen",
    "sg:tags":[
        "confectioner",
        "baker"
    ],
    "wof:name":"De Wit L",
    "wof:placetype":"venue"
},
  "geometry": {"coordinates":[4.2453308105,51.0665588379],"type":"Point"}
}