{
  "type": "Feature",
  "properties": {
    "iso:country":"BE",
    "sg:address":"Hazeschransstraat 37",
    "sg:city":"Edegem",
    "sg:orig_category":"Postkantoren Verzekeringsmakelaars and experts",
    "sg:phone":"+32 3 449 55 09",
    "sg:postcode":"2650",
    "sg:province":"Antwerpen",
    "wof:name":"De Post",
    "wof:placetype":"venue"
},
  "geometry": {"coordinates":[4.4234352112,51.1651229858],"type":"Point"}
}