{
  "type": "Feature",
  "properties": {
    "iso:country":"BE",
    "sg:address":"Rue Fransman 62",
    "sg:city":"Bruxelles",
    "sg:classifiers":[
        {
            "category":"Home & Garden",
            "subcategory":"Kitchen Supply",
            "type":"Retail Goods"
        }
    ],
    "sg:phone":"+32 2 425 19 99",
    "sg:postcode":"1020",
    "sg:province":"Bruxelles-Capitale",
    "sg:tags":[
        "equipment",
        "baker",
        "-"
    ],
    "wof:name":"Maison Awouters Sprl",
    "wof:placetype":"venue"
},
  "geometry": {"coordinates":[4.3450479507,50.8788642883],"type":"Point"}
}