{
  "type": "Feature",
  "properties": {
    "iso:country":"BE",
    "sg:address":"Massestraat 15",
    "sg:city":"Ternat",
    "sg:orig_category":"M\u00e9decins and sp\u00e9cialistes",
    "sg:phone":"+32 2 582 46 67",
    "sg:postcode":"1741",
    "sg:province":"Vlaams-Brabant",
    "wof:name":"S. De Schryver",
    "wof:placetype":"venue"
},
  "geometry": {"coordinates":[4.1697511673,50.850982666],"type":"Point"}
}