{
  "type": "Feature",
  "properties": {
    "addr:full":"Rue De Villers 72 Hensies Hainaut 7350",
    "addr:housenumber":"72",
    "addr:postcode":"7350",
    "addr:street":"Rue De Villers",
    "iso:country":"BE",
    "sg:address":"Rue De Villers 72",
    "sg:city":"Hensies",
    "sg:classifiers":[
        {
            "category":"Arena",
            "subcategory":"Sports Club",
            "type":"Entertainment"
        }
    ],
    "sg:phone":"+32 65 46 01 16",
    "sg:postcode":"7350",
    "sg:province":"Hainaut",
    "sg:tags":[
        "terrain",
        "hors",
        "de",
        "installation",
        "sportifs"
    ],
    "wof:name":"U.s. Hensitoise",
    "wof:placetype":"venue"
},
  "geometry": {"coordinates":[3.6914548874,50.4257392883],"type":"Point"}
}