{
  "type": "Feature",
  "properties": {
    "iso:country":"BE",
    "sg:address":"Bolk 83b1",
    "sg:city":"Vosselaar",
    "sg:orig_category":"Brood, gebak and snoepgoed",
    "sg:phone":"+32 14 61 88 81",
    "sg:postcode":"2350",
    "sg:province":"Antwerpen",
    "wof:name":"Huis Amore",
    "wof:placetype":"venue"
},
  "geometry": {"coordinates":[4.8877949715,51.3070526123],"type":"Point"}
}