{
  "type": "Feature",
  "properties": {
    "addr:full":"Rue Fouleng 3 Brugelette Hainaut 7943",
    "addr:housenumber":"3",
    "addr:postcode":"7943",
    "addr:street":"Rue Fouleng;Hainaut",
    "iso:country":"BE",
    "sg:address":"Rue Fouleng 3",
    "sg:city":"Brugelette",
    "sg:orig_category":"Pain, p\u00e2tisseries and confiseries. Eleveurs de volaille",
    "sg:phone":"+32 68 45 44 44",
    "sg:postcode":"7943",
    "sg:province":"Hainaut",
    "wof:name":"Romain Langhendries",
    "wof:placetype":"venue"
},
  "geometry": {"coordinates":[3.8942649364,50.6068534851],"type":"Point"}
}