{
  "type": "Feature",
  "properties": {
    "addr:full":"Otegemsesteenweg 102 Deerlijk West-Vlaanderen 8540",
    "addr:housenumber":"102",
    "addr:postcode":"8540",
    "addr:street":"Otegemsesteenweg",
    "iso:country":"BE",
    "sg:address":"Otegemsesteenweg 102",
    "sg:city":"Deerlijk",
    "sg:orig_category":"Tuinbenodigdheden",
    "sg:phone":"+32 56 77 31 85",
    "sg:postcode":"8540",
    "sg:province":"West-Vlaanderen",
    "wof:name":"Swing Chairs",
    "wof:placetype":"venue"
},
  "geometry": {"coordinates":[3.3808720112,50.8155937195],"type":"Point"}
}