{
  "type": "Feature",
  "properties": {
    "addr:full":"Mangelbeekstraat 40 Lummen Limburg 3560",
    "addr:housenumber":"40",
    "addr:postcode":"3560",
    "addr:street":"Mangelbeekstraat",
    "iso:country":"BE",
    "sg:address":"Mangelbeekstraat 40",
    "sg:city":"Lummen",
    "sg:orig_category":"Entretien and r\u00e9parations de voitures",
    "sg:phone":"+32 13 52 31 57",
    "sg:postcode":"3560",
    "sg:province":"Limburg",
    "wof:name":"D.cars",
    "wof:placetype":"venue"
},
  "geometry": {"coordinates":[5.1796360016,50.978099823],"type":"Point"}
}