{
  "type": "Feature",
  "properties": {
    "iso:country":"BE",
    "sg:address":"Wallerode 106",
    "sg:city":"Amel (meyerode)",
    "sg:classifiers":[
        {
            "category":"Building & Trades",
            "subcategory":"Landscaping Services",
            "type":"Services"
        }
    ],
    "sg:phone":"+32 80 22 78 99",
    "sg:postcode":"4770",
    "sg:province":"Li\u00e8ge",
    "sg:tags":[
        "-",
        "lopping",
        "work",
        "tree",
        "felling"
    ],
    "wof:name":"Classen L",
    "wof:placetype":"venue"
},
  "geometry": {"coordinates":[6.1689629555,50.3543167114],"type":"Point"}
}