{
  "type": "Feature",
  "properties": {
    "iso:country":"BE",
    "sg:address":"R. Du March\u00c9 Aux Poulets 3",
    "sg:city":"Brussel/bruxelles",
    "sg:orig_category":"Alimentation sp\u00e9cialis\u00e9e",
    "sg:phone":"+32 2 512 39 53",
    "sg:postcode":"1000",
    "sg:province":"Bruxelles-Capitale",
    "wof:name":"Santos Palace/clary-santos Palace",
    "wof:placetype":"venue"
},
  "geometry": {"coordinates":[4.3491458893,50.8494186401],"type":"Point"}
}