{
  "type": "Feature",
  "properties": {
    "iso:country":"BE",
    "sg:address":"Avenue Du Commerce 3",
    "sg:city":"Enghien",
    "sg:orig_category":"Mat\u00e9riaux de construction Gr",
    "sg:phone":"+32 78 71 90 36",
    "sg:postcode":"7850",
    "sg:province":"Hainaut",
    "wof:name":"Kerger",
    "wof:placetype":"venue"
},
  "geometry": {"coordinates":[4.0514431,50.6987380981],"type":"Point"}
}