{
  "type": "Feature",
  "properties": {
    "addr:full":"Rue Henri Gardier 21 Soumagne Li\u00e8ge 4630",
    "addr:housenumber":"21",
    "addr:postcode":"4630",
    "addr:street":"Rue Henri Gardier",
    "iso:country":"BE",
    "sg:address":"Rue Henri Gardier 21",
    "sg:city":"Soumagne",
    "sg:orig_category":"Woningbouw",
    "sg:phone":"+32 4 377 36 89",
    "sg:postcode":"4630",
    "sg:province":"Li\u00e8ge",
    "wof:name":"C.d.f. Construction",
    "wof:placetype":"venue"
},
  "geometry": {"coordinates":[5.7401251793,50.6226501465],"type":"Point"}
}