{
  "type": "Feature",
  "properties": {
    "addr:full":"Kerkstraat 65 Sint-pieters-leeuw (ruisbroek) Vlaams-Brabant 1601",
    "addr:housenumber":"65",
    "addr:postcode":"1601",
    "addr:street":"Kerkstraat",
    "iso:country":"BE",
    "sg:address":"Kerkstraat 65",
    "sg:city":"Sint-pieters-leeuw (ruisbroek)",
    "sg:classifiers":[
        {
            "category":"Real Estate",
            "subcategory":"Architect",
            "type":"Services"
        }
    ],
    "sg:phone":"+32 2 377 81 99",
    "sg:postcode":"1601",
    "sg:province":"Vlaams-Brabant",
    "wof:name":"Breda Karel Architectenbureau",
    "wof:placetype":"venue"
},
  "geometry": {"coordinates":[4.2969641685,50.7875595093],"type":"Point"}
}