{
  "type": "Feature",
  "properties": {
    "addr:full":"3990 Peer (groot) Limburg 3990",
    "addr:postcode":"3990;3990",
    "addr:street":"Groot Limburg",
    "iso:country":"BE",
    "sg:address":"3990",
    "sg:city":"Peer (groot)",
    "sg:orig_category":"Pharmaciens",
    "sg:phone":"+32 900 10 500",
    "sg:postcode":"3990",
    "sg:province":"Limburg",
    "wof:name":"Pharmacies De Garde",
    "wof:placetype":"venue"
},
  "geometry": {"coordinates":[5.4533009529,51.1329536438],"type":"Point"}
}