{
  "type": "Feature",
  "properties": {
    "addr:full":"Minister E. Rubbenslaan 16 Zele Oost-Vlaanderen 9240",
    "addr:housenumber":"16",
    "addr:postcode":"9240",
    "addr:street":"Minister E. Rubbenslaan",
    "iso:country":"BE",
    "sg:address":"Minister E. Rubbenslaan 16",
    "sg:city":"Zele",
    "sg:orig_category":"Artiesten and kunstenaars",
    "sg:phone":"+32 52 44 48 80",
    "sg:postcode":"9240",
    "sg:province":"Oost-Vlaanderen",
    "wof:name":"Arens",
    "wof:placetype":"venue"
},
  "geometry": {"coordinates":[4.0376329422,51.0703849792],"type":"Point"}
}