{
  "type": "Feature",
  "properties": {
    "iso:country":"BE",
    "sg:address":"Peter Benoitstraat 12",
    "sg:city":"Vichte",
    "sg:classifiers":[
        {
            "category":"Shopping",
            "subcategory":"Clothing, Apparel, & Fashions",
            "type":"Retail Goods"
        }
    ],
    "sg:phone":"+32 56 77 48 05",
    "sg:postcode":"8570",
    "sg:province":"West-Vlaanderen",
    "sg:tags":[
        "clothing",
        "fabric"
    ],
    "wof:name":"Degetex B.v.b.a.",
    "wof:placetype":"venue"
},
  "geometry": {"coordinates":[3.4110369682,50.8318367004],"type":"Point"}
}