{
  "type": "Feature",
  "properties": {
    "addr:full":"Rue Covis 8 Profondeville (lustin) Namur 5170",
    "addr:housenumber":"8",
    "addr:postcode":"5170",
    "addr:street":"Rue Covis",
    "iso:country":"BE",
    "sg:address":"Rue Covis 8",
    "sg:city":"Profondeville (lustin)",
    "sg:classifiers":[
        {
            "category":"Health Services",
            "subcategory":"Health Practitioner",
            "type":"Services"
        }
    ],
    "sg:phone":"+32 81 41 30 27",
    "sg:postcode":"5170",
    "sg:province":"Namur",
    "sg:tags":[
        "physiotherapist"
    ],
    "wof:name":"Collart Baudouin",
    "wof:placetype":"venue"
},
  "geometry": {"coordinates":[4.8674049377,50.3786392212],"type":"Point"}
}