{
  "type": "Feature",
  "properties": {
    "iso:country":"BE",
    "sg:address":"Morinnegoed 4",
    "sg:city":"Kortrijk",
    "sg:orig_category":"Travaux de pl\u00e2trage",
    "sg:phone":"+32 56 22 97 86",
    "sg:postcode":"8500",
    "sg:province":"West-Vlaanderen",
    "wof:name":"G. Vandenbussche",
    "wof:placetype":"venue"
},
  "geometry": {"coordinates":[3.3063650131,50.8097496033],"type":"Point"}
}