{
  "type": "Feature",
  "properties": {
    "iso:country":"BE",
    "sg:address":"Chemin Du Champ De La Cour 1",
    "sg:city":"Braine-le-comte (hennuy\u00e8res)",
    "sg:classifiers":[
        {
            "category":"Professional",
            "subcategory":"Computer Services",
            "type":"Services"
        }
    ],
    "sg:phone":"+32 476 79 00 63",
    "sg:postcode":"7090",
    "sg:province":"Hainaut",
    "sg:tags":[
        "webdesign",
        "-",
        "internet"
    ],
    "wof:name":"Declic En Clic",
    "wof:placetype":"venue"
},
  "geometry": {"coordinates":[4.1602721214,50.6456108093],"type":"Point"}
}