{
  "type": "Feature",
  "properties": {
    "addr:full":"Ettelgemstraat 20 Jabbeke West-Vlaanderen 8490",
    "addr:housenumber":"20",
    "addr:postcode":"8490",
    "addr:street":"Ettelgemstraat",
    "iso:country":"BE",
    "sg:address":"Ettelgemstraat 20",
    "sg:city":"Jabbeke",
    "sg:classifiers":[
        {
            "category":"Food & Beverages",
            "subcategory":"Meat & Fish",
            "type":"Retail Goods"
        }
    ],
    "sg:phone":"+32 50 81 11 18",
    "sg:postcode":"8490",
    "sg:province":"West-Vlaanderen",
    "sg:tags":[
        "-",
        "livestock"
    ],
    "wof:name":"Acke F",
    "wof:placetype":"venue"
},
  "geometry": {"coordinates":[3.0825901031,51.1801948547],"type":"Point"}
}