{
  "type": "Feature",
  "properties": {
    "addr:full":"Avenue D'itterbeek 3 Anderlecht/anderlecht Bruxelles-Capitale 1070",
    "addr:housenumber":"3",
    "addr:postcode":"1070",
    "addr:street":"Avenue D'Itterbeek",
    "iso:country":"BE",
    "sg:address":"Avenue D'itterbeek 3",
    "sg:city":"Anderlecht/anderlecht",
    "sg:orig_category":"Fleurs and plantes",
    "sg:phone":"+32 2 523 43 92",
    "sg:postcode":"1070",
    "sg:province":"Bruxelles-Capitale",
    "wof:name":"Chez Berthe",
    "wof:placetype":"venue"
},
  "geometry": {"coordinates":[4.2987470627,50.8355789185],"type":"Point"}
}