{
  "type": "Feature",
  "properties": {
    "iso:country":"BE",
    "sg:address":"Untere B\u00fcchelstrasse 36",
    "sg:city":"Sankt Vith",
    "sg:classifiers":[
        {
            "category":"Building & Trades",
            "subcategory":"Landscaping Services",
            "type":"Services"
        }
    ],
    "sg:phone":"+32 80 22 85 82",
    "sg:postcode":"4780",
    "sg:province":"Li\u00e8ge",
    "sg:tags":[
        "forestry"
    ],
    "wof:name":"Neissen Pgmbh",
    "wof:placetype":"venue"
},
  "geometry": {"coordinates":[6.1223778725,50.2771224976],"type":"Point"}
}