{
  "type": "Feature",
  "properties": {
    "iso:country":"BE",
    "sg:address":"Veldstraat 11",
    "sg:city":"Kapelle-op-den-bos",
    "sg:orig_category":"Enseignement maternel and primaire",
    "sg:phone":"+32 15 71 13 80",
    "sg:postcode":"1880",
    "sg:province":"Vlaams-Brabant",
    "wof:name":"Vrije Lagere School",
    "wof:placetype":"venue"
},
  "geometry": {"coordinates":[4.3550758362,51.0068664551],"type":"Point"}
}