{
  "type": "Feature",
  "properties": {
    "addr:full":"Torenplein 1 Box 18 Hasselt Limburg 3500",
    "addr:housenumber":"1 box 18",
    "addr:postcode":"3500",
    "addr:street":"Torenplein",
    "iso:country":"BE",
    "sg:address":"Torenplein 1 Box 18",
    "sg:city":"Hasselt",
    "sg:classifiers":[
        {
            "category":"Autos & Motor Vehicles",
            "subcategory":"Automobile Sales",
            "type":"Retail Goods"
        }
    ],
    "sg:postcode":"3500",
    "sg:province":"Limburg",
    "sg:tags":[
        "ceremony",
        "car"
    ],
    "wof:name":"Exclusief Invest Nv",
    "wof:placetype":"venue"
},
  "geometry": {"coordinates":[5.3408169746,50.9289245605],"type":"Point"}
}