{
  "type": "Feature",
  "properties": {
    "iso:country":"BE",
    "sg:address":"Mandellaan 172",
    "sg:city":"Roeselare",
    "sg:classifiers":[
        {
            "category":"Health Services",
            "subcategory":"Dentist",
            "type":"Services"
        }
    ],
    "sg:phone":"+32 51 22 48 66",
    "sg:postcode":"8800",
    "sg:province":"West-Vlaanderen",
    "wof:name":"Moerman Jan",
    "wof:placetype":"venue"
},
  "geometry": {"coordinates":[3.1373040676,50.9517631531],"type":"Point"}
}