{
  "type": "Feature",
  "properties": {
    "iso:country":"BE",
    "sg:address":"Senator A Jeurissenlaan 1120",
    "sg:city":"Zonhoven",
    "sg:orig_category":"Non-Classified Establishments",
    "sg:phone":"+32 11 81 75 75",
    "sg:postcode":"3520",
    "sg:province":"Limburg",
    "wof:name":"Sedeo Bvba",
    "wof:placetype":"venue"
},
  "geometry": {"coordinates":[5.389538765,50.998008728],"type":"Point"}
}