{
  "type": "Feature",
  "properties": {
    "addr:full":"Oosteeklo-dorp 32 Oosteeklo Oost-Vlaanderen 9968",
    "addr:housenumber":"32",
    "addr:postcode":"9968",
    "addr:street":"Oosteeklo-Dorp",
    "iso:country":"BE",
    "sg:address":"Oosteeklo-dorp 32",
    "sg:city":"Oosteeklo",
    "sg:orig_category":"Herstelling horloges and juwelen Juwelen and horloges",
    "sg:phone":"+32 9 373 72 82",
    "sg:postcode":"9968",
    "sg:province":"Oost-Vlaanderen",
    "wof:name":"Wauters",
    "wof:placetype":"venue"
},
  "geometry": {"coordinates":[3.6877789497,51.1916694641],"type":"Point"}
}