{
  "type": "Feature",
  "properties": {
    "iso:country":"BE",
    "sg:address":"Industriestrasse 16",
    "sg:city":"Eupen",
    "sg:orig_category":"Non-Classified Establishments",
    "sg:phone":"+32 87 59 29 11",
    "sg:postcode":"4700",
    "sg:province":"Li\u00e8ge",
    "wof:name":"Jacques (chocolaterie Et Mus\u00e9e)",
    "wof:placetype":"venue"
},
  "geometry": {"coordinates":[6.0075001717,50.6406707764],"type":"Point"}
}