{
  "type": "Feature",
  "properties": {
    "iso:country":"BE",
    "sg:address":"Lange Beeldekensstraat 17",
    "sg:city":"Antwerpen",
    "sg:orig_category":"Activit\u00e9s d\u00b4action sociale sans h\u00e9bergement",
    "sg:phone":"+32 3 232 40 90",
    "sg:postcode":"2060",
    "sg:province":"Antwerpen",
    "wof:name":"Vclb-centrum",
    "wof:placetype":"venue"
},
  "geometry": {"coordinates":[4.4222288132,51.221446991],"type":"Point"}
}