{
  "type": "Feature",
  "properties": {
    "iso:country":"BE",
    "sg:address":"Boechoutselei 97",
    "sg:city":"Mortsel",
    "sg:orig_category":"Artiesten and kunstenaars",
    "sg:phone":"+32 3 455 21 40",
    "sg:postcode":"2640",
    "sg:province":"Antwerpen",
    "wof:name":"Ludovicus Bosmans",
    "wof:placetype":"venue"
},
  "geometry": {"coordinates":[4.4774122238,51.1627922058],"type":"Point"}
}