{
  "type": "Feature",
  "properties": {
    "addr:full":"Place Philippe Werrie 25 Bruxelles (jette) Bruxelles-Capitale 1090",
    "addr:housenumber":"25",
    "addr:postcode":"1090",
    "addr:street":"Place Philippe Werrie",
    "iso:country":"BE",
    "sg:address":"Place Philippe Werrie 25",
    "sg:city":"Bruxelles (jette)",
    "sg:classifiers":[
        {
            "category":"Building & Trades",
            "subcategory":"Landscaping Services",
            "type":"Services"
        }
    ],
    "sg:phone":"+32 2 428 49 22",
    "sg:postcode":"1090",
    "sg:province":"Bruxelles-Capitale",
    "sg:tags":[
        "gardening",
        "garden",
        "maintenance"
    ],
    "wof:name":"Area & Garden",
    "wof:placetype":"venue"
},
  "geometry": {"coordinates":[4.3349599838,50.8680114746],"type":"Point"}
}