{
  "type": "Feature",
  "properties": {
    "addr:full":"Hemelrijkstraat 26 Maasmechelen Limburg 3630",
    "addr:housenumber":"26",
    "addr:postcode":"3630",
    "addr:street":"Hemelrijkstraat",
    "iso:country":"BE",
    "sg:address":"Hemelrijkstraat 26",
    "sg:city":"Maasmechelen",
    "sg:orig_category":"Dierenartsen",
    "sg:phone":"+32 89 76 47 47",
    "sg:postcode":"3630",
    "sg:province":"Limburg",
    "wof:name":"Ivo Van Herck",
    "wof:placetype":"venue"
},
  "geometry": {"coordinates":[5.7046480179,50.9580917358],"type":"Point"}
}