{
  "type": "Feature",
  "properties": {
    "iso:country":"BE",
    "sg:address":"Mercatorstraat 70",
    "sg:city":"Antwerpen",
    "sg:orig_category":"Eclairage et \u00e9quipements du foyer. Installation de menuiserie m\u00e9tallique. Installation de menuiserie",
    "sg:phone":"+32 3 667 70 30",
    "sg:postcode":"2018",
    "sg:province":"Antwerpen",
    "wof:name":"Bam-interieur",
    "wof:placetype":"venue"
},
  "geometry": {"coordinates":[4.4240398407,51.207901001],"type":"Point"}
}