{
  "type": "Feature",
  "properties": {
    "addr:full":"Rue Du Wainage 90 Farciennes Hainaut 6240",
    "addr:housenumber":"90",
    "addr:postcode":"6240",
    "addr:street":"Rue Du Wainage",
    "iso:country":"BE",
    "sg:address":"Rue Du Wainage 90",
    "sg:city":"Farciennes",
    "sg:orig_category":"Postkantoren Verzekeringsmakelaars and experts",
    "sg:phone":"+32 71 38 26 23",
    "sg:postcode":"6240",
    "sg:province":"Hainaut",
    "wof:name":"La Poste",
    "wof:placetype":"venue"
},
  "geometry": {"coordinates":[4.5295009613,50.4406166077],"type":"Point"}
}