{
  "type": "Feature",
  "properties": {
    "iso:country":"BE",
    "sg:address":"Graafjansdijk 32",
    "sg:city":"Sint-laureins",
    "sg:orig_category":"Kapsalons",
    "sg:phone":"+32 9 379 89 77",
    "sg:postcode":"9982",
    "sg:province":"Oost-Vlaanderen",
    "wof:name":"Greta Goethals",
    "wof:placetype":"venue"
},
  "geometry": {"coordinates":[3.5940489769,51.2468757629],"type":"Point"}
}