{
  "type": "Feature",
  "properties": {
    "iso:country":"BE",
    "sg:address":"Gitsbergstraat 21",
    "sg:city":"Hooglede (gits)",
    "sg:classifiers":[
        {
            "category":"Retail",
            "subcategory":"Repair Shop",
            "type":"Services"
        }
    ],
    "sg:phone":"+32 51 20 25 91",
    "sg:postcode":"8830",
    "sg:province":"West-Vlaanderen",
    "sg:tags":[
        "jobbing",
        "tailoring",
        "-"
    ],
    "wof:name":"Grymonpon Confectie Bvba",
    "wof:placetype":"venue"
},
  "geometry": {"coordinates":[3.0967860222,50.9952926636],"type":"Point"}
}