{
  "type": "Feature",
  "properties": {
    "addr:full":"Lauwershoek 8 Temse Oost-Vlaanderen 9140",
    "addr:housenumber":"8",
    "addr:postcode":"9140",
    "addr:street":"Lauwershoek",
    "iso:country":"BE",
    "sg:address":"Lauwershoek 8",
    "sg:city":"Temse",
    "sg:orig_category":"Eleveurs and marchands de porcs. Eleveurs de bovins",
    "sg:phone":"+32 3 771 21 47",
    "sg:postcode":"9140",
    "sg:province":"Oost-Vlaanderen",
    "wof:name":"Willy Speelman",
    "wof:placetype":"venue"
},
  "geometry": {"coordinates":[4.23458004,51.1423912048],"type":"Point"}
}