{
  "type": "Feature",
  "properties": {
    "iso:country":"BE",
    "sg:address":"Mechelseweg 272",
    "sg:city":"Kapelle-op-den-bos",
    "sg:orig_category":"Rev\u00eatements pour sols and murs. Peinture",
    "sg:phone":"+32 15 71 36 51",
    "sg:postcode":"1880",
    "sg:province":"Vlaams-Brabant",
    "wof:name":"Karel Van De Ven",
    "wof:placetype":"venue"
},
  "geometry": {"coordinates":[4.3679280281,51.0119476318],"type":"Point"}
}