{
  "type": "Feature",
  "properties": {
    "iso:country":"BE",
    "sg:address":"Vert Chemin 26",
    "sg:city":"Mouscron (dottignies)",
    "sg:classifiers":[
        {
            "category":"Farming",
            "subcategory":"Livestock Farm",
            "type":"Manufacturing & Wholesale Goods"
        }
    ],
    "sg:phone":"+32 56 48 82 73",
    "sg:postcode":"7711",
    "sg:province":"Hainaut",
    "sg:tags":[
        "buyer"
    ],
    "wof:name":"Lefebvre Ch",
    "wof:placetype":"venue"
},
  "geometry": {"coordinates":[3.2756130695,50.7397613525],"type":"Point"}
}