{
  "type": "Feature",
  "properties": {
    "addr:full":"Rue Franz Merjay 123 Elsene/ixelles Bruxelles-Capitale 1050",
    "addr:housenumber":"123",
    "addr:postcode":"1050",
    "addr:street":"Rue Franz Merjay",
    "iso:country":"BE",
    "sg:address":"Rue Franz Merjay 123",
    "sg:city":"Elsene/ixelles",
    "sg:orig_category":"M\u00e9decins and sp\u00e9cialistes",
    "sg:phone":"+32 2 344 41 64",
    "sg:postcode":"1050",
    "sg:province":"Bruxelles-Capitale",
    "wof:name":"I. Libert",
    "wof:placetype":"venue"
},
  "geometry": {"coordinates":[4.3528351784,50.8184127808],"type":"Point"}
}