{
  "type": "Feature",
  "properties": {
    "addr:full":"Rue Imbette 9 Oupeye Li\u00e8ge 4684",
    "addr:housenumber":"9",
    "addr:postcode":"4684",
    "addr:street":"Rue Imbette",
    "iso:country":"BE",
    "sg:address":"Rue Imbette 9",
    "sg:city":"Oupeye",
    "sg:orig_category":"Benzinestations and brandstoffen",
    "sg:phone":"+32 4 379 89 27",
    "sg:postcode":"4684",
    "sg:province":"Li\u00e8ge",
    "wof:name":"Serge Thys",
    "wof:placetype":"venue"
},
  "geometry": {"coordinates":[5.668129921,50.7341194153],"type":"Point"}
}