{
  "type": "Feature",
  "properties": {
    "addr:full":"Molendreef 54 Aarschot Vlaams-Brabant 3202",
    "addr:housenumber":"54",
    "addr:postcode":"3202",
    "addr:street":"Molendreef",
    "iso:country":"BE",
    "sg:address":"Molendreef 54",
    "sg:city":"Aarschot",
    "sg:orig_category":"Sportclubs",
    "sg:phone":"+32 16 50 17 41",
    "sg:postcode":"3202",
    "sg:province":"Vlaams-Brabant",
    "wof:name":"Karate Club Messelbroek",
    "wof:placetype":"venue"
},
  "geometry": {"coordinates":[4.8999648094,50.9797973633],"type":"Point"}
}