{
  "type": "Feature",
  "properties": {
    "addr:full":"Rue Fond Des Tawes 91 Li\u00e8ge 1 Li\u00e8ge 4000",
    "addr:housenumber":"91;1",
    "addr:postcode":"4000",
    "addr:street":"Rue Fond Des Tawes",
    "iso:country":"BE",
    "sg:address":"Rue Fond Des Tawes 91",
    "sg:city":"Li\u00e8ge 1",
    "sg:orig_category":"Tankcleaning",
    "sg:phone":"+32 4 240 14 07",
    "sg:postcode":"4000",
    "sg:province":"Li\u00e8ge",
    "wof:name":"Atelier Lhoest Freres",
    "wof:placetype":"venue"
},
  "geometry": {"coordinates":[5.5865731239,50.6566886902],"type":"Point"}
}