{
  "type": "Feature",
  "properties": {
    "iso:country":"BE",
    "sg:address":"Werchtersesteenweg 14",
    "sg:city":"Haacht",
    "sg:classifiers":[
        {
            "category":"Shopping",
            "subcategory":"Clothing, Apparel, & Fashions",
            "type":"Retail Goods"
        }
    ],
    "sg:phone":"+32 16 60 13 56",
    "sg:postcode":"3150",
    "sg:province":"Vlaams-Brabant",
    "sg:tags":[
        "-",
        "clothing",
        "child"
    ],
    "wof:name":"Chloe",
    "wof:placetype":"venue"
},
  "geometry": {"coordinates":[4.6385369301,50.9759407043],"type":"Point"}
}