{
  "type": "Feature",
  "properties": {
    "iso:country":"BE",
    "sg:address":"Pl. La Chapelle Au Puits 19",
    "sg:city":"La Louvi\u00c8re",
    "sg:orig_category":"S\u00e9curit\u00e9 sociale",
    "sg:phone":"+32 64 22 45 56",
    "sg:postcode":"7100",
    "sg:province":"Hainaut",
    "wof:name":"Mutualit\u00c9 Socialiste",
    "wof:placetype":"venue"
},
  "geometry": {"coordinates":[4.1850848198,50.4748649597],"type":"Point"}
}