{
  "type": "Feature",
  "properties": {
    "iso:country":"BE",
    "sg:address":"Strandlaan 324",
    "sg:city":"Koksijde",
    "sg:orig_category":"Warenhuizen",
    "sg:phone":"+32 58 51 79 49",
    "sg:postcode":"8670",
    "sg:province":"West-Vlaanderen",
    "wof:name":"Els Hilderson",
    "wof:placetype":"venue"
},
  "geometry": {"coordinates":[2.6110489368,51.1113204956],"type":"Point"}
}