{
  "type": "Feature",
  "properties": {
    "addr:full":"Jozef Ginisstraat 39 Bertem Vlaams-Brabant 3060",
    "addr:housenumber":"39",
    "addr:postcode":"3060",
    "addr:street":"Jozef Ginisstraat",
    "iso:country":"BE",
    "sg:address":"Jozef Ginisstraat 39",
    "sg:city":"Bertem",
    "sg:orig_category":"Ordinateurs and \u00e9quipement informatique",
    "sg:phone":"+32 16 48 03 31",
    "sg:postcode":"3060",
    "sg:province":"Vlaams-Brabant",
    "wof:name":"Reneldis Software",
    "wof:placetype":"venue"
},
  "geometry": {"coordinates":[4.6406202316,50.8672370911],"type":"Point"}
}