{
  "type": "Feature",
  "properties": {
    "iso:country":"BE",
    "sg:address":"Strijdersstraat 25",
    "sg:city":"Edingen/enghien",
    "sg:orig_category":"Loodgieterij, verwarming and sanitaire installaties",
    "sg:phone":"+32 2 395 62 43",
    "sg:postcode":"7850",
    "sg:province":"Hainaut",
    "wof:name":"Gilbert Scohy",
    "wof:placetype":"venue"
},
  "geometry": {"coordinates":[4.0836877823,50.6899147034],"type":"Point"}
}