{
  "type": "Feature",
  "properties": {
    "addr:full":"Molenblookstraat 63bb Zutendaal Limburg 3690",
    "addr:housenumber":"63bb",
    "addr:postcode":"3690",
    "addr:street":"Molenblookstraat",
    "iso:country":"BE",
    "sg:address":"Molenblookstraat 63bb",
    "sg:city":"Zutendaal",
    "sg:orig_category":"Voertuigen",
    "sg:phone":"+32 89 61 48 91",
    "sg:postcode":"3690",
    "sg:province":"Limburg",
    "wof:name":"Auto S Jeuris",
    "wof:placetype":"venue"
},
  "geometry": {"coordinates":[5.5519018173,50.9244499207],"type":"Point"}
}