{
  "type": "Feature",
  "properties": {
    "iso:country":"BE",
    "sg:address":"Gulden-vlieslaan 60bc",
    "sg:city":"Sint-gillis/saint-gilles",
    "sg:orig_category":"Advocaten and juridische adviseurs",
    "sg:phone":"+32 2 544 11 99",
    "sg:postcode":"1060",
    "sg:province":"Bruxelles-Capitale",
    "wof:name":"Donatienne Maes",
    "wof:placetype":"venue"
},
  "geometry": {"coordinates":[4.3538928032,50.8347587585],"type":"Point"}
}