{
  "type": "Feature",
  "properties": {
    "addr:full":"Lozenberg 17 Zaventem (sint-stevens-woluwe) Vlaams-Brabant 1932",
    "addr:housenumber":"17",
    "addr:postcode":"1932",
    "addr:street":"Lozenberg",
    "iso:country":"BE",
    "sg:address":"Lozenberg 17",
    "sg:city":"Zaventem (sint-stevens-woluwe)",
    "sg:classifiers":[
        {
            "category":"Professional",
            "subcategory":"Management & Consulting",
            "type":"Services"
        }
    ],
    "sg:phone":"+32 2 723 19 80",
    "sg:postcode":"1932",
    "sg:province":"Vlaams-Brabant",
    "sg:tags":[
        "-",
        "processing",
        "data",
        "consultant"
    ],
    "wof:name":"Cognita",
    "wof:placetype":"venue"
},
  "geometry": {"coordinates":[4.4597158432,50.8680801392],"type":"Point"}
}