{
  "type": "Feature",
  "properties": {
    "addr:full":"Abeelstraat 2 Ronse/renaix Oost-Vlaanderen 9600",
    "addr:housenumber":"2",
    "addr:postcode":"9600",
    "addr:street":"Abeelstraat",
    "iso:country":"BE",
    "sg:address":"Abeelstraat 2",
    "sg:city":"Ronse/renaix",
    "sg:orig_category":"Banken and kredietinstellingen",
    "sg:phone":"+32 55 21 56 71",
    "sg:postcode":"9600",
    "sg:province":"Oost-Vlaanderen",
    "wof:name":"Kbc",
    "wof:placetype":"venue"
},
  "geometry": {"coordinates":[3.6005549431,50.7447891235],"type":"Point"}
}