{
  "type": "Feature",
  "properties": {
    "addr:full":"Tieltsesteenweg 167 Aalter Oost-Vlaanderen 9880",
    "addr:housenumber":"167",
    "addr:postcode":"9880",
    "addr:street":"Tieltsesteenweg",
    "iso:country":"BE",
    "sg:address":"Tieltsesteenweg 167",
    "sg:city":"Aalter",
    "sg:orig_category":"Royal Canin. Animaux domestiques and accessoires",
    "sg:phone":"+32 51 68 66 60",
    "sg:postcode":"9880",
    "sg:province":"Oost-Vlaanderen",
    "wof:name":"May Flower",
    "wof:placetype":"venue"
},
  "geometry": {"coordinates":[3.4247500896,51.0602493286],"type":"Point"}
}