{
  "type": "Feature",
  "properties": {
    "iso:country":"BE",
    "sg:address":"Chauss\u00c9e De Tournai 38",
    "sg:city":"Tournai",
    "sg:orig_category":"Voertuigen",
    "sg:phone":"+32 69 22 14 46",
    "sg:postcode":"7520",
    "sg:province":"Hainaut",
    "wof:name":"Autolux",
    "wof:placetype":"venue"
},
  "geometry": {"coordinates":[3.354227066,50.6343650818],"type":"Point"}
}