{
  "type": "Feature",
  "properties": {
    "addr:full":"Turnhoutsebaan 204 Schilde Antwerpen 2970",
    "addr:housenumber":"204",
    "addr:postcode":"2970",
    "addr:street":"Turnhoutsebaan",
    "iso:country":"BE",
    "sg:address":"Turnhoutsebaan 204",
    "sg:city":"Schilde",
    "sg:orig_category":"Kunstonderwijs",
    "sg:phone":"+32 3 385 36 93",
    "sg:postcode":"2970",
    "sg:province":"Antwerpen",
    "wof:name":"Gemeentelijke Muziek En Woordacademie",
    "wof:placetype":"venue"
},
  "geometry": {"coordinates":[4.5775370598,51.2383499146],"type":"Point"}
}