{
  "type": "Feature",
  "properties": {
    "addr:full":"De Schaaf 34 Malle (oostmalle) Antwerpen 2390",
    "addr:housenumber":"34",
    "addr:postcode":"2390",
    "addr:street":"De Schaaf",
    "iso:country":"BE",
    "sg:address":"De Schaaf 34",
    "sg:city":"Malle (oostmalle)",
    "sg:classifiers":[
        {
            "category":"Home & Garden",
            "subcategory":"Carpets & Floor Coverings",
            "type":"Retail Goods"
        }
    ],
    "sg:phone":"+32 3 311 54 34",
    "sg:postcode":"2390",
    "sg:province":"Antwerpen",
    "sg:tags":[
        "layer",
        "mosaicists"
    ],
    "wof:name":"Keysers R",
    "wof:placetype":"venue"
},
  "geometry": {"coordinates":[4.7182130814,51.2852325439],"type":"Point"}
}