{
  "type": "Feature",
  "properties": {
    "iso:country":"BE",
    "sg:address":"Vennestraat 258",
    "sg:city":"Genk",
    "sg:orig_category":"Entretien and r\u00e9parations de voitures",
    "sg:phone":"+32 89 35 49 24",
    "sg:postcode":"3600",
    "sg:province":"Limburg",
    "wof:name":"Express Car Wash",
    "wof:placetype":"venue"
},
  "geometry": {"coordinates":[5.4796481133,50.9660949707],"type":"Point"}
}