{
  "type": "Feature",
  "properties": {
    "addr:full":"Rue Du Garceau 12 Frasnes-lez-anvaing Hainaut 7912",
    "addr:housenumber":"12",
    "addr:postcode":"7912",
    "addr:street":"Rue Du Garceau",
    "iso:country":"BE",
    "sg:address":"Rue Du Garceau 12",
    "sg:city":"Frasnes-lez-anvaing",
    "sg:orig_category":"Rundveehouders",
    "sg:phone":"+32 69 76 93 98",
    "sg:postcode":"7912",
    "sg:province":"Hainaut",
    "wof:name":"Leopold Dupret",
    "wof:placetype":"venue"
},
  "geometry": {"coordinates":[3.5919909477,50.7055664062],"type":"Point"}
}