{
  "type": "Feature",
  "properties": {
    "addr:full":"Rue De L'arbre B\u00e9nit 129 Bruxelles (ixelles) Bruxelles-Capitale 1050",
    "addr:housenumber":"129",
    "addr:postcode":"1050",
    "addr:street":"Rue De L'Arbre Be\u0301Nit",
    "iso:country":"BE",
    "sg:address":"Rue De L'arbre B\u00e9nit 129",
    "sg:city":"Bruxelles (ixelles)",
    "sg:classifiers":[
        {
            "category":"Professional",
            "subcategory":"Art Services",
            "type":"Services"
        }
    ],
    "sg:phone":"+32 2 647 47 26",
    "sg:postcode":"1050",
    "sg:province":"Bruxelles-Capitale",
    "sg:tags":[
        "-",
        "painter",
        "artist"
    ],
    "wof:name":"Gomila Solar A",
    "wof:placetype":"venue"
},
  "geometry": {"coordinates":[4.3638682365,50.8302383423],"type":"Point"}
}