{
  "type": "Feature",
  "properties": {
    "addr:full":"Priorijlaan 32 Middelkerke West-Vlaanderen 8434",
    "addr:housenumber":"32",
    "addr:postcode":"8434",
    "addr:street":"Priorijlaan",
    "iso:country":"BE",
    "sg:address":"Priorijlaan 32",
    "sg:city":"Middelkerke",
    "sg:classifiers":[
        {
            "category":"Restaurant",
            "type":"Food & Drink"
        }
    ],
    "sg:phone":"+32 59 30 40 65",
    "sg:postcode":"8434",
    "sg:province":"West-Vlaanderen",
    "wof:name":"Tea-room Le Go\u00c9land",
    "wof:placetype":"venue"
},
  "geometry": {"coordinates":[2.7569050789,51.1488685608],"type":"Point"}
}