{
  "type": "Feature",
  "properties": {
    "iso:country":"BE",
    "sg:address":"Watertorenlaan 13",
    "sg:city":"Zaventem",
    "sg:classifiers":[
        {
            "category":"Insurance",
            "subcategory":"Insurance Agent",
            "type":"Services"
        }
    ],
    "sg:phone":"+32 496 16 19 06",
    "sg:postcode":"1930",
    "sg:province":"Vlaams-Brabant",
    "sg:tags":[
        "-",
        "representative"
    ],
    "wof:name":"Alpascha Bvba",
    "wof:placetype":"venue"
},
  "geometry": {"coordinates":[4.4718780518,50.8861541748],"type":"Point"}
}