{
  "type": "Feature",
  "properties": {
    "addr:full":"Chemin Fourneau 2 Nivelles (monstreux) Brabant Wallon 1400",
    "addr:housenumber":"2",
    "addr:postcode":"1400",
    "addr:street":"Chemin Fourneau;Wallon",
    "iso:country":"BE",
    "sg:address":"Chemin Fourneau 2",
    "sg:city":"Nivelles (monstreux)",
    "sg:classifiers":[
        {
            "category":"Health Services",
            "subcategory":"Health Practitioner",
            "type":"Services"
        }
    ],
    "sg:phone":"+32 67 84 19 05",
    "sg:postcode":"1400",
    "sg:province":"Brabant Wallon",
    "sg:tags":[
        "physiotherapist"
    ],
    "wof:name":"Kersten Brigitte",
    "wof:placetype":"venue"
},
  "geometry": {"coordinates":[4.2913861275,50.600189209],"type":"Point"}
}