{
  "type": "Feature",
  "properties": {
    "addr:full":"Roeselaarsestraat 527 Izegem West-Vlaanderen 8870",
    "addr:housenumber":"527",
    "addr:postcode":"8870",
    "addr:street":"Roeselaarsestraat",
    "iso:country":"BE",
    "sg:address":"Roeselaarsestraat 527",
    "sg:city":"Izegem",
    "sg:orig_category":"Eleveurs and marchands de porcs",
    "sg:phone":"+32 51 30 27 74",
    "sg:postcode":"8870",
    "sg:province":"West-Vlaanderen",
    "wof:name":"Pol Roelens",
    "wof:placetype":"venue"
},
  "geometry": {"coordinates":[3.1821100712,50.9282798767],"type":"Point"}
}