{
  "type": "Feature",
  "properties": {
    "addr:full":"Rue Neuve 7 Nivelles Brabant Wallon 1400",
    "addr:housenumber":"7",
    "addr:postcode":"1400",
    "addr:street":"Rue Neuve",
    "iso:country":"BE",
    "sg:address":"Rue Neuve 7",
    "sg:city":"Nivelles",
    "sg:classifiers":[
        {
            "category":"Government",
            "subcategory":"Post Office",
            "type":"Public Place"
        }
    ],
    "sg:phone":"+32 67 34 25 39",
    "sg:postcode":"1400",
    "sg:province":"Brabant Wallon",
    "sg:tags":[
        "picture",
        "restoring"
    ],
    "wof:name":"De Meyer A",
    "wof:placetype":"venue"
},
  "geometry": {"coordinates":[4.3270320892,50.5977897644],"type":"Point"}
}