{
  "type": "Feature",
  "properties": {
    "addr:full":"Krijgsbaan 51 Mortsel Antwerpen 2640",
    "addr:housenumber":"51",
    "addr:postcode":"2640",
    "addr:street":"Krijgsbaan",
    "iso:country":"BE",
    "sg:address":"Krijgsbaan 51",
    "sg:city":"Mortsel",
    "sg:orig_category":"V\u00e9hicules automobiles",
    "sg:phone":"+32 3 440 32 36",
    "sg:postcode":"2640",
    "sg:province":"Antwerpen",
    "wof:name":"Autohandel Van Dessel",
    "wof:placetype":"venue"
},
  "geometry": {"coordinates":[4.4573721886,51.1758384705],"type":"Point"}
}