{
  "type": "Feature",
  "properties": {
    "addr:full":"Rue Du Petit Ch\u00eane 3 Li\u00e8ge 1 Li\u00e8ge 4000",
    "addr:housenumber":"3;1",
    "addr:postcode":"4000",
    "addr:street":"Rue Du Petit Che\u0302Ne",
    "iso:country":"BE",
    "sg:address":"Rue Du Petit Ch\u00eane 3",
    "sg:city":"Li\u00e8ge 1",
    "sg:classifiers":[
        {
            "category":"Shopping",
            "subcategory":"Books",
            "type":"Retail Goods"
        }
    ],
    "sg:phone":"+32 4 227 82 72",
    "sg:postcode":"4000",
    "sg:province":"Li\u00e8ge",
    "sg:tags":[
        "bookseller"
    ],
    "wof:name":"Feuille De Ch\u00eane (a La)",
    "wof:placetype":"venue"
},
  "geometry": {"coordinates":[5.605743885,50.6554031372],"type":"Point"}
}