{
  "type": "Feature",
  "properties": {
    "addr:full":"Rue De Li\u00e8ge 30 Durbuy (bomal-sur-ourthe) Luxembourg 6941",
    "addr:housenumber":"30",
    "addr:postcode":"6941",
    "addr:street":"Rue De Lie\u0300Ge",
    "iso:country":"BE",
    "sg:address":"Rue De Li\u00e8ge 30",
    "sg:city":"Durbuy (bomal-sur-ourthe)",
    "sg:classifiers":[
        {
            "category":"Personal",
            "subcategory":"Beauty Salon",
            "type":"Services"
        }
    ],
    "sg:phone":"+32 86 21 23 52",
    "sg:postcode":"6941",
    "sg:province":"Luxembourg",
    "sg:tags":[
        "lady",
        "-",
        "hairdressing"
    ],
    "wof:name":"B\u00e9atrice Coiffure",
    "wof:placetype":"venue"
},
  "geometry": {"coordinates":[5.524184227,50.3770332336],"type":"Point"}
}