{
  "type": "Feature",
  "properties": {
    "iso:country":"BE",
    "sg:address":"Rue La Brouck Campagne 22",
    "sg:city":"Trooz (for\u00eat)",
    "sg:classifiers":[
        {
            "category":"Home & Garden",
            "subcategory":"Building Materials",
            "type":"Retail Goods"
        }
    ],
    "sg:phone":"+32 4 351 73 40",
    "sg:postcode":"4870",
    "sg:province":"Li\u00e8ge",
    "sg:tags":[
        "window"
    ],
    "wof:name":"Chassis Trooz",
    "wof:placetype":"venue"
},
  "geometry": {"coordinates":[5.6648879051,50.5775909424],"type":"Point"}
}