{
  "type": "Feature",
  "properties": {
    "addr:full":"Spelverstraat 36 Bilzen Limburg 3740",
    "addr:housenumber":"36",
    "addr:postcode":"3740",
    "addr:street":"Spelverstraat",
    "iso:country":"BE",
    "sg:address":"Spelverstraat 36",
    "sg:city":"Bilzen",
    "sg:orig_category":"Equipements divers pour l\u00b4industrie Gr. Quincailleries. Location de mat\u00e9riel divers",
    "sg:phone":"+32 89 41 35 92",
    "sg:postcode":"3740",
    "sg:province":"Limburg",
    "wof:name":"Oben Building Machines",
    "wof:placetype":"venue"
},
  "geometry": {"coordinates":[5.5276007652,50.8705940247],"type":"Point"}
}