{
  "type": "Feature",
  "properties": {
    "addr:full":"Rue De L'ype 14 Soumagne Li\u00e8ge 4630",
    "addr:housenumber":"14",
    "addr:postcode":"4630",
    "addr:street":"Rue De L'Ype",
    "iso:country":"BE",
    "sg:address":"Rue De L'ype 14",
    "sg:city":"Soumagne",
    "sg:orig_category":"Produits surgel\u00e9s Gr",
    "sg:phone":"+32 4 377 46 87",
    "sg:postcode":"4630",
    "sg:province":"Li\u00e8ge",
    "wof:name":"Daniel Loos",
    "wof:placetype":"venue"
},
  "geometry": {"coordinates":[5.7229528427,50.6336784363],"type":"Point"}
}