{
  "type": "Feature",
  "properties": {
    "iso:country":"BE",
    "sg:address":"Kolonel Dusartplein 31",
    "sg:city":"Hasselt",
    "sg:orig_category":"Huishoudapparaten, televisies and radio's",
    "sg:phone":"+32 11 22 34 17",
    "sg:postcode":"3500",
    "sg:province":"Limburg",
    "wof:name":"Sirocco",
    "wof:placetype":"venue"
},
  "geometry": {"coordinates":[5.3448438644,50.931728363],"type":"Point"}
}