{
  "type": "Feature",
  "properties": {
    "addr:full":"Huombois 13 Etalle Luxembourg 6740",
    "addr:housenumber":"13",
    "addr:postcode":"6740",
    "addr:street":"Huombois",
    "iso:country":"BE",
    "sg:address":"Huombois 13",
    "sg:city":"Etalle",
    "sg:orig_category":"Eleveurs de bovins",
    "sg:phone":"+32 63 45 53 36",
    "sg:postcode":"6740",
    "sg:province":"Luxembourg",
    "wof:name":"Jose Henuset",
    "wof:placetype":"venue"
},
  "geometry": {"coordinates":[5.6007847786,49.6738510132],"type":"Point"}
}