{
  "type": "Feature",
  "properties": {
    "iso:country":"BE",
    "sg:address":"Oude Kerkstraat 96",
    "sg:city":"Antwerpen",
    "sg:classifiers":[
        {
            "category":"Retail",
            "subcategory":"Event Space",
            "type":"Services"
        }
    ],
    "sg:phone":"+32 3 259 06 80",
    "sg:postcode":"2018",
    "sg:province":"Antwerpen",
    "sg:tags":[
        "organisation"
    ],
    "wof:name":"Accent Events Bvba",
    "wof:placetype":"venue"
},
  "geometry": {"coordinates":[4.3948149681,51.1989746094],"type":"Point"}
}