{
  "type": "Feature",
  "properties": {
    "addr:full":"Rue Paul Pastur 42 Charleroi Hainaut 6040",
    "addr:housenumber":"42",
    "addr:postcode":"6040",
    "addr:street":"Rue Paul Pastur;Hainaut",
    "iso:country":"BE",
    "sg:address":"Rue Paul Pastur 42",
    "sg:city":"Charleroi",
    "sg:orig_category":"Ordinateurs and \u00e9quipement informatique",
    "sg:phone":"+32 71 37 03 38",
    "sg:postcode":"6040",
    "sg:province":"Hainaut",
    "wof:name":"Claude Taburiaux",
    "wof:placetype":"venue"
},
  "geometry": {"coordinates":[4.4171290398,50.4414710999],"type":"Point"}
}