{
  "type": "Feature",
  "properties": {
    "iso:country":"BE",
    "sg:address":"Steenweg Op Asse 23",
    "sg:city":"Merchtem (brussegem)",
    "sg:classifiers":[
        {
            "category":"Professional",
            "subcategory":"Management & Consulting",
            "type":"Services"
        }
    ],
    "sg:phone":"+32 2 460 24 38",
    "sg:postcode":"1785",
    "sg:province":"Vlaams-Brabant",
    "sg:tags":[
        "tax-consultants"
    ],
    "wof:name":"Meysman E",
    "wof:placetype":"venue"
},
  "geometry": {"coordinates":[4.2609071732,50.9269638062],"type":"Point"}
}