{
  "type": "Feature",
  "properties": {
    "addr:full":"Leopold Ii-laan 25 Oostende West-Vlaanderen 8400",
    "addr:housenumber":"25",
    "addr:postcode":"8400",
    "addr:street":"Leopold Ii-Laan",
    "iso:country":"BE",
    "sg:address":"Leopold Ii-laan 25",
    "sg:city":"Oostende",
    "sg:classifiers":[
        {
            "category":"Shopping",
            "subcategory":"Clothing, Apparel, & Fashions",
            "type":"Retail Goods"
        }
    ],
    "sg:phone":"+32 59 80 80 55",
    "sg:postcode":"8400",
    "sg:province":"West-Vlaanderen",
    "sg:tags":[
        "leather",
        "-",
        "buckskin",
        "clothing"
    ],
    "wof:name":"Velter",
    "wof:placetype":"venue"
},
  "geometry": {"coordinates":[2.9133150578,51.231136322],"type":"Point"}
}