{
  "type": "Feature",
  "properties": {
    "iso:country":"BE",
    "sg:address":"Broekstraat 15",
    "sg:city":"Oud-heverlee",
    "sg:classifiers":[
        {
            "category":"Professional",
            "subcategory":"Management & Consulting",
            "type":"Services"
        }
    ],
    "sg:phone":"+32 16 40 47 06",
    "sg:postcode":"3050",
    "sg:province":"Vlaams-Brabant",
    "sg:tags":[
        "consultant"
    ],
    "wof:name":"First Consult Bvba",
    "wof:placetype":"venue"
},
  "geometry": {"coordinates":[4.6622929573,50.8390312195],"type":"Point"}
}