{
  "type": "Feature",
  "properties": {
    "iso:country":"BE",
    "sg:address":"Route De Ch\u00e2telet",
    "sg:city":"Charleroi (couillet)",
    "sg:classifiers":[
        {
            "category":"Health Services",
            "subcategory":"Nursing And Care Facility",
            "type":"Services"
        }
    ],
    "sg:phone":"+32 71 21 48 74",
    "sg:postcode":"6010",
    "sg:province":"Hainaut",
    "sg:tags":[
        "home"
    ],
    "wof:name":"Giuliani M-h",
    "wof:placetype":"venue"
},
  "geometry": {"coordinates":[4.45622015,50.3920135498],"type":"Point"}
}