{
  "type": "Feature",
  "properties": {
    "addr:full":"Rue De Nivelles 16 `s Gravenbrakel Hainaut 7090",
    "addr:housenumber":"16",
    "addr:postcode":"7090",
    "addr:street":"Rue De Nivelles;Hainaut",
    "iso:country":"BE",
    "sg:address":"Rue De Nivelles 16",
    "sg:city":"`s Gravenbrakel",
    "sg:orig_category":"Bloemen and planten",
    "sg:phone":"+32 67 64 85 62",
    "sg:postcode":"7090",
    "sg:province":"Hainaut",
    "wof:name":"Euroflor",
    "wof:placetype":"venue"
},
  "geometry": {"coordinates":[4.2274641991,50.6066360474],"type":"Point"}
}