{
  "type": "Feature",
  "properties": {
    "addr:full":"Place Saint-job 31 Uccle Bruxelles-Capitale 1180",
    "addr:housenumber":"31",
    "addr:postcode":"1180",
    "addr:street":"Place Saint-Job",
    "iso:country":"BE",
    "sg:address":"Place Saint-job 31",
    "sg:city":"Uccle",
    "sg:orig_category":"Boucheries",
    "sg:phone":"+32 2 374 19 68",
    "sg:postcode":"1180",
    "sg:province":"Bruxelles-Capitale",
    "wof:name":"L\u00c9on",
    "wof:placetype":"venue"
},
  "geometry": {"coordinates":[4.365459919,50.7940597534],"type":"Point"}
}