{
  "type": "Feature",
  "properties": {
    "addr:full":"Hofstraat 80 Sint-niklaas Oost-Vlaanderen 9100",
    "addr:housenumber":"80",
    "addr:postcode":"9100",
    "addr:street":"Hofstraat",
    "iso:country":"BE",
    "sg:address":"Hofstraat 80",
    "sg:city":"Sint-niklaas",
    "sg:orig_category":"Agences de voyages",
    "sg:phone":"+32 3 760 16 16",
    "sg:postcode":"9100",
    "sg:province":"Oost-Vlaanderen",
    "wof:name":"Reizen Van Laere",
    "wof:placetype":"venue"
},
  "geometry": {"coordinates":[4.1370038986,51.1671981812],"type":"Point"}
}