{
  "type": "Feature",
  "properties": {
    "iso:country":"BE",
    "sg:address":"Molendreef 49",
    "sg:city":"Sint-niklaas (belsele)",
    "sg:classifiers":[
        {
            "category":"Banks & Credit Unions",
            "subcategory":"Investment Brokerage",
            "type":"Services"
        }
    ],
    "sg:phone":"+32 3 777 46 45",
    "sg:postcode":"9111",
    "sg:province":"Oost-Vlaanderen",
    "sg:tags":[
        "pump",
        "industrial",
        "-"
    ],
    "wof:name":"A & M Industrial Pumps Nv",
    "wof:placetype":"venue"
},
  "geometry": {"coordinates":[4.0928149223,51.1482696533],"type":"Point"}
}