{
  "type": "Feature",
  "properties": {
    "iso:country":"BE",
    "sg:address":"Rue De La Station 16",
    "sg:city":"Waterloo",
    "sg:classifiers":[
        {
            "category":"Tea Room",
            "subcategory":"None",
            "type":"Food & Drink"
        }
    ],
    "sg:phone":"+32 2 351 21 90",
    "sg:postcode":"1410",
    "sg:province":"Brabant Wallon",
    "wof:name":"Salade Tournesol (la)",
    "wof:placetype":"venue"
},
  "geometry": {"coordinates":[4.395512104,50.7177848816],"type":"Point"}
}