{
  "type": "Feature",
  "properties": {
    "iso:country":"BE",
    "sg:address":"Grensstraat 17",
    "sg:city":"Sint-joost-ten-node/saint-josse-ten-noode",
    "sg:classifiers":[
        {
            "category":"Insurance",
            "subcategory":"Insurance Agent",
            "type":"Services"
        }
    ],
    "sg:phone":"+32 2 217 59 19",
    "sg:postcode":"1210",
    "sg:province":"Bruxelles-Capitale",
    "sg:tags":[
        "verzekeringsmakelaars",
        "expert"
    ],
    "wof:name":"Verheyen Jean",
    "wof:placetype":"venue"
},
  "geometry": {"coordinates":[4.3700652122,50.8531494141],"type":"Point"}
}