{
  "type": "Feature",
  "properties": {
    "iso:country":"BE",
    "sg:address":"Beestenmarkt 6",
    "sg:city":"Halle",
    "sg:orig_category":"Huishoudapparaten, televisies and radio's",
    "sg:phone":"+32 2 356 82 41",
    "sg:postcode":"1500",
    "sg:province":"Vlaams-Brabant",
    "wof:name":"Constant Van Hemelrijck",
    "wof:placetype":"venue"
},
  "geometry": {"coordinates":[4.2362599373,50.7361450195],"type":"Point"}
}