{
  "type": "Feature",
  "properties": {
    "addr:full":"Mechelsestraat 21 Leuven Vlaams-Brabant 3000",
    "addr:housenumber":"21",
    "addr:postcode":"3000",
    "addr:street":"Mechelsestraat",
    "iso:country":"BE",
    "sg:address":"Mechelsestraat 21",
    "sg:city":"Leuven",
    "sg:classifiers":[
        {
            "category":"Home & Garden",
            "subcategory":"Home Furnishings",
            "type":"Retail Goods"
        }
    ],
    "sg:phone":"+32 16 23 29 79",
    "sg:postcode":"3000",
    "sg:province":"Vlaams-Brabant",
    "sg:tags":[
        "linen",
        "household",
        "-"
    ],
    "wof:name":"Singel",
    "wof:placetype":"venue"
},
  "geometry": {"coordinates":[4.6999278069,50.8805160522],"type":"Point"}
}