{
  "type": "Feature",
  "properties": {
    "iso:country":"BE",
    "sg:address":"Place Georges Brugmann 14",
    "sg:city":"Bruxelles (ixelles)",
    "sg:classifiers":[
        {
            "category":"Shopping",
            "subcategory":"Clothing, Apparel, & Fashions",
            "type":"Retail Goods"
        }
    ],
    "sg:phone":"+32 2 346 59 47",
    "sg:postcode":"1050",
    "sg:province":"Bruxelles-Capitale",
    "sg:tags":[
        "-",
        "clothing",
        "child"
    ],
    "wof:name":"Hontoir C",
    "wof:placetype":"venue"
},
  "geometry": {"coordinates":[4.353785038,50.8173027039],"type":"Point"}
}