{
  "type": "Feature",
  "properties": {
    "iso:country":"BE",
    "sg:address":"Christinastraat 129",
    "sg:city":"Oostende",
    "sg:orig_category":"Alternatieve geneeskunde Artsen and specialisten",
    "sg:phone":"+32 59 50 29 37",
    "sg:postcode":"8400",
    "sg:province":"West-Vlaanderen",
    "wof:name":"Erwin Doeuvre",
    "wof:placetype":"venue"
},
  "geometry": {"coordinates":[2.9193780422,51.2286148071],"type":"Point"}
}