{
  "type": "Feature",
  "properties": {
    "addr:full":"Rue De L\u00b4eglise 96 - Bte 6 Woluwe-saint-pierre Bruxelles-Capitale 1150",
    "addr:housenumber":"96 bte 6",
    "addr:postcode":"1150",
    "addr:street":"Rue De L\u00b4Eglise",
    "iso:country":"BE",
    "sg:address":"Rue De L\u00b4eglise 96 - Bte 6",
    "sg:city":"Woluwe-saint-pierre",
    "sg:orig_category":"Huisdieren and benodigdheden",
    "sg:phone":"+32 2 770 24 60",
    "sg:postcode":"1150",
    "sg:province":"Bruxelles-Capitale",
    "wof:name":"Tom & Co",
    "wof:placetype":"venue"
},
  "geometry": {"coordinates":[4.4639568329,50.8406906128],"type":"Point"}
}