{
  "type": "Feature",
  "properties": {
    "addr:full":"Avenue Dailly 164-166 Bruxelles (schaerbeek) Bruxelles-Capitale 1030",
    "addr:postcode":"164-166;1030",
    "addr:street":"Avenue Dailly",
    "iso:country":"BE",
    "sg:address":"Avenue Dailly 164-166",
    "sg:city":"Bruxelles (schaerbeek)",
    "sg:classifiers":[
        {
            "category":"Retail",
            "subcategory":"Laundry & Dry Cleaning",
            "type":"Services"
        }
    ],
    "sg:phone":"+32 2 735 30 93",
    "sg:postcode":"1030",
    "sg:province":"Bruxelles-Capitale",
    "sg:tags":[
        "dyer",
        "cleaner"
    ],
    "wof:name":"Blue Wash",
    "wof:placetype":"venue"
},
  "geometry": {"coordinates":[4.385653019,50.8543548584],"type":"Point"}
}