{
  "type": "Feature",
  "properties": {
    "addr:full":"Ruisledestweg 71 Wingene West-Vlaanderen 8750",
    "addr:housenumber":"71",
    "addr:postcode":"8750",
    "addr:street":"Ruisledestweg",
    "iso:country":"BE",
    "sg:address":"Ruisledestweg 71",
    "sg:city":"Wingene",
    "sg:orig_category":"Metaalbehandeling and -bekleding",
    "sg:phone":"+32 51 65 54 93",
    "sg:postcode":"8750",
    "sg:province":"West-Vlaanderen",
    "wof:name":"Depestel",
    "wof:placetype":"venue"
},
  "geometry": {"coordinates":[3.2787899971,51.0574951172],"type":"Point"}
}