{
  "type": "Feature",
  "properties": {
    "addr:full":"Naamsesteenweg 90 Oud-heverlee Vlaams-Brabant 3052",
    "addr:housenumber":"90",
    "addr:postcode":"3052",
    "addr:street":"Naamsesteenweg",
    "iso:country":"BE",
    "sg:address":"Naamsesteenweg 90",
    "sg:city":"Oud-heverlee",
    "sg:classifiers":[
        {
            "category":"Restaurant",
            "type":"Food & Drink"
        }
    ],
    "sg:phone":"+32 16 40 24 02",
    "sg:postcode":"3052",
    "sg:province":"Vlaams-Brabant",
    "wof:name":"Meerdael",
    "wof:placetype":"venue"
},
  "geometry": {"coordinates":[4.7026410103,50.8215904236],"type":"Point"}
}