{
  "type": "Feature",
  "properties": {
    "iso:country":"BE",
    "sg:address":"Molenstraat 40",
    "sg:city":"Belgium",
    "sg:orig_category":"Boucheries",
    "sg:phone":"+32 14 81 24 15",
    "sg:postcode":"2490",
    "sg:province":"Antwerpen",
    "wof:name":"Beenhouwerij Van Der Auwera",
    "wof:placetype":"venue"
},
  "geometry": {"coordinates":[5.1736087799,51.172290802],"type":"Point"}
}