{
  "type": "Feature",
  "properties": {
    "iso:country":"BE",
    "sg:address":"Rue Village 1",
    "sg:city":"Olne",
    "sg:classifiers":[
        {
            "category":"Home & Garden",
            "subcategory":"Garden Supply",
            "type":"Retail Goods"
        }
    ],
    "sg:phone":"+32 87 26 80 44",
    "sg:postcode":"4877",
    "sg:province":"Li\u00e8ge",
    "sg:tags":[
        "lawn",
        "mower"
    ],
    "wof:name":"Coeme J-m",
    "wof:placetype":"venue"
},
  "geometry": {"coordinates":[5.7445950508,50.5898704529],"type":"Point"}
}