{
  "type": "Feature",
  "properties": {
    "addr:full":"Rue De Jace 32 Seraing Li\u00e8ge 4101",
    "addr:housenumber":"32",
    "addr:postcode":"4101",
    "addr:street":"Rue De Jace",
    "iso:country":"BE",
    "sg:address":"Rue De Jace 32",
    "sg:city":"Seraing",
    "sg:orig_category":"Industri\u00eble and commerci\u00eble bouw Woningbouw",
    "sg:phone":"+32 4 235 71 40",
    "sg:postcode":"4101",
    "sg:province":"Li\u00e8ge",
    "wof:name":"Casa",
    "wof:placetype":"venue"
},
  "geometry": {"coordinates":[5.4892668724,50.6244087219],"type":"Point"}
}