{
  "type": "Feature",
  "properties": {
    "addr:full":"Kapellestraat 4 Ledegem West-Vlaanderen 8880",
    "addr:housenumber":"4",
    "addr:postcode":"8880",
    "addr:street":"Kapellestraat",
    "iso:country":"BE",
    "sg:address":"Kapellestraat 4",
    "sg:city":"Ledegem",
    "sg:orig_category":"Cr\u00e9meries",
    "sg:phone":"+32 56 50 96 67",
    "sg:postcode":"8880",
    "sg:province":"West-Vlaanderen",
    "wof:name":"Vandecasteele",
    "wof:placetype":"venue"
},
  "geometry": {"coordinates":[3.1766328812,50.8733711243],"type":"Point"}
}