{
  "type": "Feature",
  "properties": {
    "addr:full":"Rue Basse 32 Ittre Brabant Wallon 1460",
    "addr:housenumber":"32;1460",
    "addr:street":"Rue Basse",
    "iso:country":"BE",
    "sg:address":"Rue Basse 32",
    "sg:city":"Ittre",
    "sg:orig_category":"Boucheries",
    "sg:phone":"+32 67 64 61 06",
    "sg:postcode":"1460",
    "sg:province":"Brabant Wallon",
    "wof:name":"Boucherie Michel",
    "wof:placetype":"venue"
},
  "geometry": {"coordinates":[4.2633609772,50.6483154297],"type":"Point"}
}