{
  "type": "Feature",
  "properties": {
    "addr:full":"Weg Naar Helchteren 33 Meeuwen-gruitrode Limburg 3670",
    "addr:housenumber":"33",
    "addr:postcode":"3670",
    "addr:street":"Weg Naar Helchteren",
    "iso:country":"BE",
    "sg:address":"Weg Naar Helchteren 33",
    "sg:city":"Meeuwen-gruitrode",
    "sg:classifiers":[
        {
            "category":"Fast Food",
            "type":"Food & Drink"
        }
    ],
    "sg:phone":"+32 11 79 22 70",
    "sg:postcode":"3670",
    "sg:province":"Limburg",
    "sg:tags":[
        "\u00c0",
        "emporter",
        "restaurants"
    ],
    "wof:name":"Frituur Quatre-bras",
    "wof:placetype":"venue"
},
  "geometry": {"coordinates":[5.5156230927,51.0973815918],"type":"Point"}
}