{
  "type": "Feature",
  "properties": {
    "iso:country":"BE",
    "sg:address":"Veemarkt 32",
    "sg:city":"Ieper",
    "sg:classifiers":[
        {
            "category":"Cafe",
            "type":"Food & Drink"
        }
    ],
    "sg:phone":"+32 57 21 63 85",
    "sg:postcode":"8900",
    "sg:province":"West-Vlaanderen",
    "sg:tags":[
        "caf\u00e9s"
    ],
    "wof:name":"Stefaan De Crock",
    "wof:placetype":"venue"
},
  "geometry": {"coordinates":[2.883341074,50.854259491],"type":"Point"}
}