{
  "type": "Feature",
  "properties": {
    "addr:full":"Kerkmansstraat 53 Houthalen-helchteren (houthalen) Limburg 3530",
    "addr:housenumber":"53",
    "addr:postcode":"3530",
    "addr:street":"Kerkmansstraat",
    "iso:country":"BE",
    "sg:address":"Kerkmansstraat 53",
    "sg:city":"Houthalen-helchteren (houthalen)",
    "sg:classifiers":[
        {
            "category":"Professional",
            "subcategory":"Computer Services",
            "type":"Services"
        }
    ],
    "sg:phone":"+32 12 21 04 43",
    "sg:postcode":"3530",
    "sg:province":"Limburg",
    "sg:tags":[
        "-",
        "security",
        "processing",
        "data"
    ],
    "wof:name":"Secur-it",
    "wof:placetype":"venue"
},
  "geometry": {"coordinates":[5.3921589851,51.0279312134],"type":"Point"}
}