{
  "type": "Feature",
  "properties": {
    "addr:full":"Rue Xavier De Bue 40 Bruxelles (uccle) Bruxelles-Capitale 1180",
    "addr:housenumber":"40",
    "addr:postcode":"1180",
    "addr:street":"Rue Xavier De Bue",
    "iso:country":"BE",
    "sg:address":"Rue Xavier De Bue 40",
    "sg:city":"Bruxelles (uccle)",
    "sg:classifiers":[
        {
            "category":"Shopping",
            "subcategory":"Optician",
            "type":"Retail Goods"
        }
    ],
    "sg:phone":"+32 2 346 09 57",
    "sg:postcode":"1180",
    "sg:province":"Bruxelles-Capitale",
    "sg:tags":[
        "-"
    ],
    "wof:name":"Thiele Optique",
    "wof:placetype":"venue"
},
  "geometry": {"coordinates":[4.3374209404,50.8035621643],"type":"Point"}
}