{
  "type": "Feature",
  "properties": {
    "addr:full":"Rue De Pont-\u00c0-celles 70a Courcelles Hainaut 6180",
    "addr:housenumber":"70a",
    "addr:postcode":"6180",
    "addr:street":"Rue De Pont-A\u0300-Celles",
    "iso:country":"BE",
    "sg:address":"Rue De Pont-\u00c0-celles 70a",
    "sg:city":"Courcelles",
    "sg:orig_category":"Installation \u00e9lectrique r\u00e9sidentielle. Construction de maisons",
    "sg:phone":"+32 71 45 61 95",
    "sg:postcode":"6180",
    "sg:province":"Hainaut",
    "wof:name":"Gargaro",
    "wof:placetype":"venue"
},
  "geometry": {"coordinates":[4.3743700981,50.4565086365],"type":"Point"}
}