{
  "type": "Feature",
  "properties": {
    "addr:full":"Dekkenstraat 113 Sint-truiden (zepperen) Limburg 3800",
    "addr:housenumber":"113",
    "addr:postcode":"3800",
    "addr:street":"Dekkenstraat",
    "iso:country":"BE",
    "sg:address":"Dekkenstraat 113",
    "sg:city":"Sint-truiden (zepperen)",
    "sg:classifiers":[
        {
            "category":"Autos & Motor Vehicles",
            "subcategory":"Automobile Sales",
            "type":"Retail Goods"
        }
    ],
    "sg:phone":"+32 11 31 41 31",
    "sg:postcode":"3800",
    "sg:province":"Limburg",
    "sg:tags":[
        "car",
        "used",
        "-"
    ],
    "wof:name":"Schils R",
    "wof:placetype":"venue"
},
  "geometry": {"coordinates":[5.2599468231,50.8394584656],"type":"Point"}
}