{
  "type": "Feature",
  "properties": {
    "iso:country":"BE",
    "sg:address":"Vrankrijk 14",
    "sg:city":"Bilzen",
    "sg:classifiers":[
        {
            "category":"Sports & Exercise",
            "subcategory":"Gym",
            "type":"Entertainment"
        }
    ],
    "sg:phone":"+32 89 81 99 70",
    "sg:postcode":"3740",
    "sg:province":"Limburg",
    "sg:tags":[
        "fitness"
    ],
    "wof:name":"Sportopolis Bilzen",
    "wof:placetype":"venue"
},
  "geometry": {"coordinates":[5.50872612,50.8606910706],"type":"Point"}
}