{
  "type": "Feature",
  "properties": {
    "iso:country":"BE",
    "sg:address":"Kruisstraat 2",
    "sg:city":"Heist-op-den-berg (wiekevorst)",
    "sg:classifiers":[
        {
            "category":"Health Services",
            "subcategory":"Nursing And Care Facility",
            "type":"Services"
        }
    ],
    "sg:phone":"+32 14 26 06 44",
    "sg:postcode":"2222",
    "sg:province":"Antwerpen",
    "sg:tags":[
        "home"
    ],
    "wof:name":"Caes - Goetschalckx",
    "wof:placetype":"venue"
},
  "geometry": {"coordinates":[4.7862200737,51.1026420593],"type":"Point"}
}