{
  "type": "Feature",
  "properties": {
    "addr:full":"Oude Baan 96 Maasmechelen Limburg 3630",
    "addr:housenumber":"96",
    "addr:postcode":"3630",
    "addr:street":"Oude Baan",
    "iso:country":"BE",
    "sg:address":"Oude Baan 96",
    "sg:city":"Maasmechelen",
    "sg:orig_category":"Supermarkten",
    "sg:phone":"+32 89 76 42 35",
    "sg:postcode":"3630",
    "sg:province":"Limburg",
    "wof:name":"Ad Delhaize",
    "wof:placetype":"venue"
},
  "geometry": {"coordinates":[5.6929421425,50.9854507446],"type":"Point"}
}