{
  "type": "Feature",
  "properties": {
    "iso:country":"BE",
    "sg:address":"Route De Bolland 16",
    "sg:city":"Herve",
    "sg:classifiers":[
        {
            "category":"Building & Trades",
            "subcategory":"Electrical",
            "type":"Services"
        }
    ],
    "sg:phone":"+32 87 69 27 90",
    "sg:postcode":"4650",
    "sg:province":"Li\u00e8ge",
    "sg:tags":[
        "industrial",
        "-",
        "electric",
        "contractor"
    ],
    "wof:name":"Ferrara & Fils",
    "wof:placetype":"venue"
},
  "geometry": {"coordinates":[5.7919669151,50.6446800232],"type":"Point"}
}