{
  "type": "Feature",
  "properties": {
    "iso:country":"BE",
    "sg:address":"Bell Telephonelaan 2",
    "sg:city":"Westerlo (oevel)",
    "sg:classifiers":[
        {
            "category":"Professional",
            "subcategory":"Engineering",
            "type":"Services"
        }
    ],
    "sg:phone":"+32 14 59 16 69",
    "sg:postcode":"2260",
    "sg:province":"Antwerpen",
    "sg:tags":[
        "-"
    ],
    "wof:name":"Carlier Bvba",
    "wof:placetype":"venue"
},
  "geometry": {"coordinates":[4.9408049583,51.1327934265],"type":"Point"}
}