{
  "type": "Feature",
  "properties": {
    "addr:full":"Generaal Lemanstraat 34 Etterbeek/etterbeek Bruxelles-Capitale 1040",
    "addr:housenumber":"34",
    "addr:postcode":"1040",
    "addr:street":"Generaal Lemanstraat",
    "iso:country":"BE",
    "sg:address":"Generaal Lemanstraat 34",
    "sg:city":"Etterbeek/etterbeek",
    "sg:orig_category":"Tweedehandsgoederen",
    "sg:phone":"+32 2 230 84 82",
    "sg:postcode":"1040",
    "sg:province":"Bruxelles-Capitale",
    "wof:name":"Apostrophe",
    "wof:placetype":"venue"
},
  "geometry": {"coordinates":[4.3828449249,50.8368186951],"type":"Point"}
}