{
  "type": "Feature",
  "properties": {
    "addr:full":"Rue Lackman 20 Saint-l\u00c9ger Luxembourg 6747",
    "addr:housenumber":"20",
    "addr:postcode":"6747",
    "addr:street":"Rue Lackman",
    "iso:country":"BE",
    "sg:address":"Rue Lackman 20",
    "sg:city":"Saint-l\u00c9ger",
    "sg:orig_category":"Sportclubs Sportterreinen and installaties behalve sportcentra",
    "sg:phone":"+32 63 23 91 52",
    "sg:postcode":"6747",
    "sg:province":"Luxembourg",
    "wof:name":"Union St.louis St.leger",
    "wof:placetype":"venue"
},
  "geometry": {"coordinates":[5.6609902382,49.6144714355],"type":"Point"}
}