{
  "type": "Feature",
  "properties": {
    "iso:country":"BE",
    "sg:address":"Rue Du Commerce 39",
    "sg:city":"Libin",
    "sg:classifiers":[
        {
            "category":"Fast Food",
            "type":"Food & Drink"
        }
    ],
    "sg:phone":"+32 61 65 56 25",
    "sg:postcode":"6890",
    "sg:province":"Luxembourg",
    "sg:tags":[
        "restaurant",
        "\u00c0",
        "domicile",
        "o",
        "catering",
        "emporter",
        "livraison",
        "restaurants"
    ],
    "wof:name":"Le Petit Bedon",
    "wof:placetype":"venue"
},
  "geometry": {"coordinates":[5.2563281059,49.9831924438],"type":"Point"}
}