{
  "type": "Feature",
  "properties": {
    "iso:country":"BE",
    "sg:address":"Jonkershovestraat 144d",
    "sg:city":"Houthulst",
    "sg:classifiers":[
        {
            "category":"Building & Trades",
            "subcategory":"Construction",
            "type":"Services"
        }
    ],
    "sg:phone":"+32 51 70 59 19",
    "sg:postcode":"8650",
    "sg:province":"West-Vlaanderen",
    "sg:tags":[
        "stucco",
        "contractor"
    ],
    "wof:name":"Joseph Bjorn",
    "wof:placetype":"venue"
},
  "geometry": {"coordinates":[2.9326860905,50.9730186462],"type":"Point"}
}