{
  "type": "Feature",
  "properties": {
    "iso:country":"BE",
    "sg:address":"Nieuwstraat 31",
    "sg:city":"Deinze",
    "sg:orig_category":"Electrom\u00e9nager, t\u00e9l\u00e9visions and radios. R\u00e9parations d'appareils \u00e9lectrom\u00e9nagers",
    "sg:phone":"+32 9 386 18 49",
    "sg:postcode":"9800",
    "sg:province":"Oost-Vlaanderen",
    "wof:name":"Luc's Electro Service",
    "wof:placetype":"venue"
},
  "geometry": {"coordinates":[3.56259799,50.9831466675],"type":"Point"}
}