{
  "type": "Feature",
  "properties": {
    "iso:country":"BE",
    "sg:address":"Rue Du Midi 125",
    "sg:city":"Brussel/bruxelles",
    "sg:orig_category":"RESTAURANTS: CAF\u00c9S",
    "sg:phone":"+32 2 513 53 82",
    "sg:postcode":"1000",
    "sg:province":"Bruxelles-Capitale",
    "wof:name":"Taverne Aca",
    "wof:placetype":"venue"
},
  "geometry": {"coordinates":[4.3479480743,50.8445701599],"type":"Point"}
}