{
  "type": "Feature",
  "properties": {
    "addr:full":"Rue Try Des M\u00c2les 25 Jemeppe-sur-sambre Namur 5190",
    "addr:housenumber":"25",
    "addr:postcode":"5190",
    "addr:street":"Rue Try Des Ma\u0302Les",
    "iso:country":"BE",
    "sg:address":"Rue Try Des M\u00c2les 25",
    "sg:city":"Jemeppe-sur-sambre",
    "sg:orig_category":"Kapsalons",
    "sg:phone":"+32 71 78 11 81",
    "sg:postcode":"5190",
    "sg:province":"Namur",
    "wof:name":"Ex\u00c9cutif Scs",
    "wof:placetype":"venue"
},
  "geometry": {"coordinates":[4.6431488991,50.464931488],"type":"Point"}
}