{
  "type": "Feature",
  "properties": {
    "iso:country":"BE",
    "sg:address":"Goudenkruispunt 32",
    "sg:city":"Tielt-winge",
    "sg:orig_category":"Dameskledingzaken Herenkledingzaken Lingerie and ondergoed",
    "sg:phone":"+32 16 64 08 82",
    "sg:postcode":"3390",
    "sg:province":"Vlaams-Brabant",
    "wof:name":"Noba Mode",
    "wof:placetype":"venue"
},
  "geometry": {"coordinates":[4.8718619347,50.9042701721],"type":"Point"}
}