{
  "type": "Feature",
  "properties": {
    "iso:country":"BE",
    "sg:address":"Rijakker 1",
    "sg:city":"Gent (mariakerke)",
    "sg:classifiers":[
        {
            "category":"Professional",
            "subcategory":"Accounting & Tax Preparation",
            "type":"Services"
        }
    ],
    "sg:phone":"+32 9 227 02 85",
    "sg:postcode":"9030",
    "sg:province":"Oost-Vlaanderen",
    "sg:tags":[
        "bookkeeper"
    ],
    "wof:name":"Knops M",
    "wof:placetype":"venue"
},
  "geometry": {"coordinates":[3.6737179756,51.0728416443],"type":"Point"}
}