{
  "type": "Feature",
  "properties": {
    "addr:full":"Baljuwstraat 48 Elsene/ixelles Bruxelles-Capitale 1050",
    "addr:housenumber":"48",
    "addr:postcode":"1050",
    "addr:street":"Baljuwstraat",
    "iso:country":"BE",
    "sg:address":"Baljuwstraat 48",
    "sg:city":"Elsene/ixelles",
    "sg:orig_category":"Dameskledingzaken",
    "sg:phone":"+32 2 646 56 55",
    "sg:postcode":"1050",
    "sg:province":"Bruxelles-Capitale",
    "wof:name":"Maison L\u00b4edelweis",
    "wof:placetype":"venue"
},
  "geometry": {"coordinates":[4.3615231514,50.8262252808],"type":"Point"}
}