{
  "type": "Feature",
  "properties": {
    "iso:country":"BE",
    "sg:address":"Langestraat 94",
    "sg:city":"Ternat",
    "sg:orig_category":"Rundveehouders",
    "sg:phone":"+32 2 582 21 77",
    "sg:postcode":"1741",
    "sg:province":"Vlaams-Brabant",
    "wof:name":"Cl Van Laethem",
    "wof:placetype":"venue"
},
  "geometry": {"coordinates":[4.1742949486,50.8513641357],"type":"Point"}
}