{
  "type": "Feature",
  "properties": {
    "addr:full":"Rue Du Progr\u00c8s 4 Bievre Namur 5555",
    "addr:housenumber":"4",
    "addr:postcode":"5555",
    "addr:street":"Rue Du Progre\u0300S",
    "iso:country":"BE",
    "sg:address":"Rue Du Progr\u00c8s 4",
    "sg:city":"Bievre",
    "sg:classifiers":[
        {
            "category":"Fast Food",
            "type":"Food & Drink"
        }
    ],
    "sg:phone":"+32 61 51 25 12",
    "sg:postcode":"5555",
    "sg:province":"Namur",
    "sg:tags":[
        "meeneem",
        "restaurant"
    ],
    "wof:name":"Le Matefaim",
    "wof:placetype":"venue"
},
  "geometry": {"coordinates":[5.0451998711,49.9357414246],"type":"Point"}
}