{
  "type": "Feature",
  "properties": {
    "iso:country":"BE",
    "sg:address":"Heidestraat 47",
    "sg:city":"Diepenbeek",
    "sg:orig_category":"Paramedische behandelingen",
    "sg:phone":"+32 11 32 38 69",
    "sg:postcode":"3590",
    "sg:province":"Limburg",
    "wof:name":"Sofie Lambert",
    "wof:placetype":"venue"
},
  "geometry": {"coordinates":[5.431385994,50.9242248535],"type":"Point"}
}