{
  "type": "Feature",
  "properties": {
    "addr:full":"Rue Saint-jean 29 Tournai Hainaut 7500",
    "addr:housenumber":"29",
    "addr:postcode":"7500",
    "addr:street":"Rue Saint-Jean",
    "iso:country":"BE",
    "sg:address":"Rue Saint-jean 29",
    "sg:city":"Tournai",
    "sg:classifiers":[
        {
            "category":"Cafe",
            "type":"Food & Drink"
        }
    ],
    "sg:phone":"+32 69 21 09 71",
    "sg:postcode":"7500",
    "sg:province":"Hainaut",
    "sg:tags":[
        "caf\u00e9s"
    ],
    "wof:name":"Liliane Vancoppenolle",
    "wof:placetype":"venue"
},
  "geometry": {"coordinates":[3.3987081051,50.6052360535],"type":"Point"}
}