{
  "type": "Feature",
  "properties": {
    "iso:country":"BE",
    "sg:address":"Paalstraat 67",
    "sg:city":"Schoten",
    "sg:classifiers":[
        {
            "category":"Professional",
            "subcategory":"Printing & Photocopies",
            "type":"Services"
        }
    ],
    "sg:phone":"+32 3 658 74 63",
    "sg:postcode":"2900",
    "sg:province":"Antwerpen",
    "sg:tags":[
        "trophy",
        "medal"
    ],
    "wof:name":"Proost",
    "wof:placetype":"venue"
},
  "geometry": {"coordinates":[4.5006041527,51.2523727417],"type":"Point"}
}