{
  "type": "Feature",
  "properties": {
    "iso:country":"BE",
    "sg:address":"Knodbaan 1",
    "sg:city":"Ranst",
    "sg:orig_category":"Rundveehouders",
    "sg:phone":"+32 3 383 02 78",
    "sg:postcode":"2520",
    "sg:province":"Antwerpen",
    "wof:name":"Ludovicus Couwels",
    "wof:placetype":"venue"
},
  "geometry": {"coordinates":[4.5912499428,51.2178192139],"type":"Point"}
}