{
  "type": "Feature",
  "properties": {
    "iso:country":"BE",
    "sg:address":"Felix Verhaeghestraat 8ba",
    "sg:city":"Waregem",
    "sg:classifiers":[
        {
            "category":"Restaurant",
            "type":"Food & Drink"
        }
    ],
    "sg:phone":"+32 56 60 82 39",
    "sg:postcode":"8790",
    "sg:province":"West-Vlaanderen",
    "wof:name":"Ter Doest",
    "wof:placetype":"venue"
},
  "geometry": {"coordinates":[3.4409370422,50.882610321],"type":"Point"}
}