{
  "type": "Feature",
  "properties": {
    "addr:full":"Woluwelaan 22 Sint-pieters-woluwe/woluwe-saint-pierre Bruxelles-Capitale 1150",
    "addr:housenumber":"22",
    "addr:postcode":"1150",
    "addr:street":"Woluwelaan;/",
    "iso:country":"BE",
    "sg:address":"Woluwelaan 22",
    "sg:city":"Sint-pieters-woluwe/woluwe-saint-pierre",
    "sg:orig_category":"Algemeen secundair onderwijs Technisch and beroeps secundair onderwijs",
    "sg:phone":"+32 2 771 01 78",
    "sg:postcode":"1150",
    "sg:province":"Bruxelles-Capitale",
    "wof:name":"St.jozefcollege",
    "wof:placetype":"venue"
},
  "geometry": {"coordinates":[4.43419981,50.8364868164],"type":"Point"}
}