{
  "type": "Feature",
  "properties": {
    "addr:full":"Bevelsesteenweg 9 Nijlen Antwerpen 2560",
    "addr:housenumber":"9",
    "addr:postcode":"2560",
    "addr:street":"Bevelsesteenweg",
    "iso:country":"BE",
    "sg:address":"Bevelsesteenweg 9",
    "sg:city":"Nijlen",
    "sg:orig_category":"Binnenhuisarchitecten Meubelzaken, woning- and keukeninrichting",
    "sg:phone":"+32 3 411 06 06",
    "sg:postcode":"2560",
    "sg:province":"Antwerpen",
    "wof:name":"Office Design Belgium",
    "wof:placetype":"venue"
},
  "geometry": {"coordinates":[4.6711239815,51.1596755981],"type":"Point"}
}