{
  "type": "Feature",
  "properties": {
    "addr:full":"Rue Charlemagne 148 Li\u00e8ge 1 (jupille-sur-meuse) Li\u00e8ge 4020",
    "addr:housenumber":"148;1",
    "addr:postcode":"4020",
    "addr:street":"Rue Charlemagne;Jupille-Sur-Meuse Lie\u0300Ge",
    "iso:country":"BE",
    "sg:address":"Rue Charlemagne 148",
    "sg:city":"Li\u00e8ge 1 (jupille-sur-meuse)",
    "sg:classifiers":[
        {
            "category":"Health Services",
            "subcategory":"Health Practitioner",
            "type":"Services"
        }
    ],
    "sg:phone":"+32 4 362 44 12",
    "sg:postcode":"4020",
    "sg:province":"Li\u00e8ge",
    "sg:tags":[
        "therapist",
        "speech"
    ],
    "wof:name":"Lemaire Y",
    "wof:placetype":"venue"
},
  "geometry": {"coordinates":[5.6264247894,50.6437683105],"type":"Point"}
}