{
  "type": "Feature",
  "properties": {
    "addr:full":"Libomont 1 Weismes/waimes Li\u00e8ge 4950",
    "addr:housenumber":"1",
    "addr:postcode":"4950",
    "addr:street":"Libomont",
    "iso:country":"BE",
    "sg:address":"Libomont 1",
    "sg:city":"Weismes/waimes",
    "sg:orig_category":"Binnenhuisarchitecten",
    "sg:phone":"+32 80 67 84 68",
    "sg:postcode":"4950",
    "sg:province":"Li\u00e8ge",
    "wof:name":"Bureau Rosen-wey",
    "wof:placetype":"venue"
},
  "geometry": {"coordinates":[6.1406908035,50.4036178589],"type":"Point"}
}