{
  "type": "Feature",
  "properties": {
    "iso:country":"BE",
    "sg:address":"Steenpoelweg 1",
    "sg:city":"Affligem (hekelgem)",
    "sg:classifiers":[
        {
            "category":"Shopping",
            "subcategory":"Florist",
            "type":"Retail Goods"
        }
    ],
    "sg:phone":"+32 53 70 23 29",
    "sg:postcode":"1790",
    "sg:province":"Vlaams-Brabant",
    "wof:name":"Cooreman-bruyland",
    "wof:placetype":"venue"
},
  "geometry": {"coordinates":[4.0952401161,50.9173202515],"type":"Point"}
}