{
  "type": "Feature",
  "properties": {
    "addr:full":"Route D'herbesthal 132bb Eupen/eupen Li\u00e8ge 4700",
    "addr:housenumber":"132bb",
    "addr:postcode":"4700",
    "addr:street":"Route D'Herbesthal",
    "iso:country":"BE",
    "sg:address":"Route D'herbesthal 132bb",
    "sg:city":"Eupen/eupen",
    "sg:orig_category":"Chaussures",
    "sg:phone":"+32 87 56 01 97",
    "sg:postcode":"4700",
    "sg:province":"Li\u00e8ge",
    "wof:name":"Shoe Discount",
    "wof:placetype":"venue"
},
  "geometry": {"coordinates":[6.0259408951,50.6333389282],"type":"Point"}
}