{
  "type": "Feature",
  "properties": {
    "addr:full":"Grote Markt 32b33 Mechelen Antwerpen 2800",
    "addr:housenumber":"32b33",
    "addr:postcode":"2800",
    "addr:street":"Grote Markt",
    "iso:country":"BE",
    "sg:address":"Grote Markt 32b33",
    "sg:city":"Mechelen",
    "sg:classifiers":[
        {
            "category":"Cafe",
            "type":"Food & Drink"
        }
    ],
    "sg:phone":"+32 15 20 35 67",
    "sg:postcode":"2800",
    "sg:province":"Antwerpen",
    "sg:tags":[
        "caf\u00e9s"
    ],
    "wof:name":"Den Beer",
    "wof:placetype":"venue"
},
  "geometry": {"coordinates":[4.4801869392,51.0277175903],"type":"Point"}
}