{
  "type": "Feature",
  "properties": {
    "addr:full":"Korhoenstraat 18 Dilsen-stokkem Limburg 3650",
    "addr:housenumber":"18",
    "addr:postcode":"3650",
    "addr:street":"Korhoenstraat",
    "iso:country":"BE",
    "sg:address":"Korhoenstraat 18",
    "sg:city":"Dilsen-stokkem",
    "sg:classifiers":[
        {
            "category":"Arena",
            "subcategory":"Sports Club",
            "type":"Entertainment"
        }
    ],
    "sg:phone":"+32 89 65 89 20",
    "sg:postcode":"3650",
    "sg:province":"Limburg",
    "sg:tags":[
        "de"
    ],
    "wof:name":"Buggy Team",
    "wof:placetype":"venue"
},
  "geometry": {"coordinates":[5.727396965,51.0364189148],"type":"Point"}
}