{
  "type": "Feature",
  "properties": {
    "addr:full":"Poststraat 142 Lokeren Oost-Vlaanderen 9160",
    "addr:housenumber":"142",
    "addr:postcode":"9160",
    "addr:street":"Poststraat",
    "iso:country":"BE",
    "sg:address":"Poststraat 142",
    "sg:city":"Lokeren",
    "sg:orig_category":"Fleurs and plantes",
    "sg:phone":"+32 9 348 84 04",
    "sg:postcode":"9160",
    "sg:province":"Oost-Vlaanderen",
    "wof:name":"M Verstraeten",
    "wof:placetype":"venue"
},
  "geometry": {"coordinates":[3.9974579811,51.1056098938],"type":"Point"}
}