{
  "type": "Feature",
  "properties": {
    "iso:country":"BE",
    "sg:address":"Korenbloemstraat 0",
    "sg:city":"Torhout",
    "sg:orig_category":"Enseignement maternel and primaire",
    "sg:phone":"+32 50 21 15 65",
    "sg:postcode":"8820",
    "sg:province":"West-Vlaanderen",
    "wof:name":"Vrije Basisschool",
    "wof:placetype":"venue"
},
  "geometry": {"coordinates":[3.1421790123,51.0816993713],"type":"Point"}
}