{
  "type": "Feature",
  "properties": {
    "addr:full":"Tiensestweg 38 Glabbeek Vlaams-Brabant 3380",
    "addr:housenumber":"38",
    "addr:postcode":"3380",
    "addr:street":"Tiensestweg",
    "iso:country":"BE",
    "sg:address":"Tiensestweg 38",
    "sg:city":"Glabbeek",
    "sg:orig_category":"Agences de marketing",
    "sg:phone":"+32 16 77 00 21",
    "sg:postcode":"3380",
    "sg:province":"Vlaams-Brabant",
    "wof:name":"Jd & Phil's",
    "wof:placetype":"venue"
},
  "geometry": {"coordinates":[4.9449119568,50.839214325],"type":"Point"}
}