{
  "type": "Feature",
  "properties": {
    "iso:country":"BE",
    "sg:address":"Rijselsestraat 130",
    "sg:city":"Ieper",
    "sg:orig_category":"Boucheries",
    "sg:phone":"+32 57 20 91 18",
    "sg:postcode":"8900",
    "sg:province":"West-Vlaanderen",
    "wof:name":"Dirk Verhille",
    "wof:placetype":"venue"
},
  "geometry": {"coordinates":[2.8889410496,50.8468437195],"type":"Point"}
}