{
  "type": "Feature",
  "properties": {
    "addr:full":"Goormansdijk 9 Dessel Antwerpen 2480",
    "addr:housenumber":"9",
    "addr:postcode":"2480",
    "addr:street":"Goormansdijk",
    "iso:country":"BE",
    "sg:address":"Goormansdijk 9",
    "sg:city":"Dessel",
    "sg:classifiers":[
        {
            "category":"Professional",
            "subcategory":"Engineering",
            "type":"Services"
        }
    ],
    "sg:phone":"+32 14 37 79 84",
    "sg:postcode":"2480",
    "sg:province":"Antwerpen",
    "sg:tags":[
        "road",
        "surfacing",
        "asphalt",
        "highway"
    ],
    "wof:name":"Kembo Kempische Bouw- En Wegenwerken Nv",
    "wof:placetype":"venue"
},
  "geometry": {"coordinates":[5.1195130348,51.2270545959],"type":"Point"}
}