{
  "type": "Feature",
  "properties": {
    "addr:full":"Rue De La Clawenne 12 Herstal Li\u00e8ge 4040",
    "addr:housenumber":"12",
    "addr:postcode":"4040",
    "addr:street":"Rue De La Clawenne",
    "iso:country":"BE",
    "sg:address":"Rue De La Clawenne 12",
    "sg:city":"Herstal",
    "sg:orig_category":"Banques and organismes de cr\u00e9dit",
    "sg:phone":"+32 4 264 40 48",
    "sg:postcode":"4040",
    "sg:province":"Li\u00e8ge",
    "wof:name":"Fortis",
    "wof:placetype":"venue"
},
  "geometry": {"coordinates":[5.6392011642,50.6742362976],"type":"Point"}
}