{
  "type": "Feature",
  "properties": {
    "iso:country":"BE",
    "sg:address":"Rue De La Grotte 28",
    "sg:city":"La Hulpe",
    "sg:orig_category":"M\u00e9decins and sp\u00e9cialistes",
    "sg:phone":"+32 2 653 92 62",
    "sg:postcode":"1310",
    "sg:province":"Brabant Wallon",
    "wof:name":"Didier Huart",
    "wof:placetype":"venue"
},
  "geometry": {"coordinates":[4.4884438515,50.7297325134],"type":"Point"}
}