{
  "type": "Feature",
  "properties": {
    "iso:country":"BE",
    "sg:address":"Rue De Hognoul 99",
    "sg:city":"Awans (hognoul)",
    "sg:classifiers":[
        {
            "category":"Professional",
            "subcategory":"Management & Consulting",
            "type":"Services"
        }
    ],
    "sg:phone":"+32 4 257 73 39",
    "sg:postcode":"4342",
    "sg:province":"Li\u00e8ge",
    "sg:tags":[
        "marketing",
        "-",
        "consultant"
    ],
    "wof:name":"Display Courrier",
    "wof:placetype":"venue"
},
  "geometry": {"coordinates":[5.4536561966,50.6769104004],"type":"Point"}
}