{
  "type": "Feature",
  "properties": {
    "addr:full":"Koolaerdstraat 132 Gistel West-Vlaanderen 8470",
    "addr:housenumber":"132",
    "addr:postcode":"8470",
    "addr:street":"Koolaerdstraat",
    "iso:country":"BE",
    "sg:address":"Koolaerdstraat 132",
    "sg:city":"Gistel",
    "sg:orig_category":"Installatie van houten of kunststof schrijnwerk",
    "sg:phone":"+32 59 27 68 12",
    "sg:postcode":"8470",
    "sg:province":"West-Vlaanderen",
    "wof:name":"Bienstman",
    "wof:placetype":"venue"
},
  "geometry": {"coordinates":[2.9505250454,51.1538505554],"type":"Point"}
}