{
  "type": "Feature",
  "properties": {
    "iso:country":"BE",
    "sg:address":"Kielsbroek 1",
    "sg:city":"Antwerpen",
    "sg:classifiers":[
        {
            "category":"Utilities",
            "subcategory":"Recycling",
            "type":"Services"
        }
    ],
    "sg:phone":"+32 3 238 63 55",
    "sg:postcode":"2020",
    "sg:province":"Antwerpen",
    "wof:name":"Stedelijke Recyclage Centra",
    "wof:placetype":"venue"
},
  "geometry": {"coordinates":[4.3705830574,51.1929550171],"type":"Point"}
}