{
  "type": "Feature",
  "properties": {
    "iso:country":"BE",
    "sg:address":"Rue De Bruxelles 7",
    "sg:city":"Namur",
    "sg:orig_category":"Traitements param\u00e9dicaux",
    "sg:phone":"+32 81 22 57 45",
    "sg:postcode":"5000",
    "sg:province":"Namur",
    "wof:name":"Rouffiange",
    "wof:placetype":"venue"
},
  "geometry": {"coordinates":[4.8632287979,50.4651870728],"type":"Point"}
}