{
  "type": "Feature",
  "properties": {
    "iso:country":"BE",
    "sg:address":"Voldersstraat 74b76",
    "sg:city":"Gent",
    "sg:orig_category":"V\u00eatements. V\u00eatements de mariage and c\u00e9r\u00e9monies",
    "sg:phone":"+32 9 225 53 28",
    "sg:postcode":"9000",
    "sg:province":"Oost-Vlaanderen",
    "wof:name":"Huis Decotex",
    "wof:placetype":"venue"
},
  "geometry": {"coordinates":[3.7224149704,51.0524330139],"type":"Point"}
}