{
  "type": "Feature",
  "properties": {
    "addr:full":"Ertbrandstraat 185 Kapellen Antwerpen 2950",
    "addr:housenumber":"185",
    "addr:postcode":"2950",
    "addr:street":"Ertbrandstraat",
    "iso:country":"BE",
    "sg:address":"Ertbrandstraat 185",
    "sg:city":"Kapellen",
    "sg:classifiers":[
        {
            "category":"Cafe",
            "type":"Food & Drink"
        }
    ],
    "sg:phone":"+32 3 605 44 58",
    "sg:postcode":"2950",
    "sg:province":"Antwerpen",
    "sg:tags":[
        "caf\u00e9s"
    ],
    "wof:name":"Caf\u00c9 Kruisbaan",
    "wof:placetype":"venue"
},
  "geometry": {"coordinates":[4.3994898796,51.3480873108],"type":"Point"}
}