{
  "type": "Feature",
  "properties": {
    "addr:full":"Rue De L'industrie 31 Namur (saint-servais) Namur 5002",
    "addr:housenumber":"31",
    "addr:postcode":"5002",
    "addr:street":"Rue De L'Industrie",
    "iso:country":"BE",
    "sg:address":"Rue De L'industrie 31",
    "sg:city":"Namur (saint-servais)",
    "sg:classifiers":[
        {
            "category":"Shopping",
            "type":"Retail Goods"
        }
    ],
    "sg:phone":"+32 81 43 44 14",
    "sg:postcode":"5002",
    "sg:province":"Namur",
    "sg:tags":[
        "product",
        "cleaning",
        "maintenance"
    ],
    "wof:name":"Anp Product Int",
    "wof:placetype":"venue"
},
  "geometry": {"coordinates":[4.8536629677,50.4745368958],"type":"Point"}
}