{
  "type": "Feature",
  "properties": {
    "iso:country":"BE",
    "sg:address":"Rue Du Village 33",
    "sg:city":"Ouffet",
    "sg:orig_category":"Pain, p\u00e2tisseries and confiseries",
    "sg:phone":"+32 86 36 70 59",
    "sg:postcode":"4590",
    "sg:province":"Li\u00e8ge",
    "wof:name":"La Gourmandine",
    "wof:placetype":"venue"
},
  "geometry": {"coordinates":[5.4700098038,50.4396324158],"type":"Point"}
}