{
  "type": "Feature",
  "properties": {
    "addr:full":"Frans Beirenslaan 125 Borsbeek Antwerpen 2150",
    "addr:housenumber":"125",
    "addr:postcode":"2150",
    "addr:street":"Frans Beirenslaan",
    "iso:country":"BE",
    "sg:address":"Frans Beirenslaan 125",
    "sg:city":"Borsbeek",
    "sg:classifiers":[
        {
            "category":"Shopping",
            "subcategory":"Pets & Pet Supplies",
            "type":"Retail Goods"
        }
    ],
    "sg:phone":"+32 3 320 27 60",
    "sg:postcode":"2150",
    "sg:province":"Antwerpen",
    "sg:tags":[
        "bird"
    ],
    "wof:name":"Orni-mondo Nv",
    "wof:placetype":"venue"
},
  "geometry": {"coordinates":[4.4806990623,51.19688797],"type":"Point"}
}