{
  "type": "Feature",
  "properties": {
    "iso:country":"BE",
    "sg:address":"Dorpsplein 3",
    "sg:city":"Wellen",
    "sg:classifiers":[
        {
            "category":"Food & Beverages",
            "subcategory":"Fruits & Vegetables",
            "type":"Retail Goods"
        }
    ],
    "sg:phone":"+32 12 74 58 65",
    "sg:postcode":"3830",
    "sg:province":"Limburg",
    "sg:tags":[
        "groenten"
    ],
    "wof:name":"Huis 't Vitamientje",
    "wof:placetype":"venue"
},
  "geometry": {"coordinates":[5.3384242058,50.841003418],"type":"Point"}
}