{
  "type": "Feature",
  "properties": {
    "addr:full":"Hazelaarkouter 35 Tielt West-Vlaanderen 8700",
    "addr:housenumber":"35",
    "addr:postcode":"8700",
    "addr:street":"Hazelaarkouter",
    "iso:country":"BE",
    "sg:address":"Hazelaarkouter 35",
    "sg:city":"Tielt",
    "sg:classifiers":[
        {
            "category":"Building & Trades",
            "subcategory":"Electrical",
            "type":"Services"
        }
    ],
    "sg:phone":"+32 51 40 50 31",
    "sg:postcode":"8700",
    "sg:province":"West-Vlaanderen",
    "sg:tags":[
        "electric",
        "-",
        "housewiring",
        "contractor"
    ],
    "wof:name":"Van Parys Koen Bvba",
    "wof:placetype":"venue"
},
  "geometry": {"coordinates":[3.3132820129,50.9947052002],"type":"Point"}
}