{
  "type": "Feature",
  "properties": {
    "addr:full":"Rue Batonnier Braffort 9 Etterbeek/etterbeek Bruxelles-Capitale 1040",
    "addr:housenumber":"9",
    "addr:postcode":"1040",
    "addr:street":"Rue Batonnier Braffort",
    "iso:country":"BE",
    "sg:address":"Rue Batonnier Braffort 9",
    "sg:city":"Etterbeek/etterbeek",
    "sg:orig_category":"Epiceries",
    "sg:phone":"+32 2 736 26 01",
    "sg:postcode":"1040",
    "sg:province":"Bruxelles-Capitale",
    "wof:name":"Coffee House",
    "wof:placetype":"venue"
},
  "geometry": {"coordinates":[4.4020190239,50.840385437],"type":"Point"}
}