{
  "type": "Feature",
  "properties": {
    "iso:country":"BE",
    "sg:address":"Oude Geelsebaan 100",
    "sg:city":"Laakdal (veerle)",
    "sg:classifiers":[
        {
            "category":"Home & Garden",
            "subcategory":"Home Furnishings",
            "type":"Retail Goods"
        }
    ],
    "sg:phone":"+32 14 84 03 19",
    "sg:postcode":"2431",
    "sg:province":"Antwerpen",
    "sg:tags":[
        "-",
        "furniture"
    ],
    "wof:name":"Meubelen Bvba Peeters Van Leeu Bvba",
    "wof:placetype":"venue"
},
  "geometry": {"coordinates":[4.9642901421,51.0722885132],"type":"Point"}
}