{
  "type": "Feature",
  "properties": {
    "iso:country":"BE",
    "sg:address":"Rue Des Resedas 9",
    "sg:city":"Bruxelles",
    "sg:orig_category":"Metal Roof-Top Mountings For Advertising Panels",
    "sg:phone":"+32 2 521 27 35",
    "sg:postcode":"1070",
    "sg:province":"Bruxelles-Capitale",
    "wof:name":"Lichtert Industrie S.a.",
    "wof:placetype":"venue"
},
  "geometry": {"coordinates":[4.302549839,50.8252410889],"type":"Point"}
}