{
  "type": "Feature",
  "properties": {
    "iso:country":"BE",
    "sg:address":"Rijksweg 186",
    "sg:city":"Maasmechelen",
    "sg:classifiers":[
        {
            "category":"Banks & Credit Unions",
            "subcategory":"Bank",
            "type":"Services"
        }
    ],
    "sg:phone":"+32 89 77 29 99",
    "sg:postcode":"3630",
    "sg:province":"Limburg",
    "sg:tags":[
        "savings-banks"
    ],
    "wof:name":"Mercator Bank En Verzekeringen",
    "wof:placetype":"venue"
},
  "geometry": {"coordinates":[5.7007632256,50.9780769348],"type":"Point"}
}