{
  "type": "Feature",
  "properties": {
    "iso:country":"BE",
    "sg:address":"Oranjerielaan 4",
    "sg:city":"Gent",
    "sg:orig_category":"V\u00eatements sur mesure Fab",
    "sg:phone":"+32 9 226 28 46",
    "sg:postcode":"9030",
    "sg:province":"Oost-Vlaanderen",
    "wof:name":"Ann Goormachtigh",
    "wof:placetype":"venue"
},
  "geometry": {"coordinates":[3.6805028915,51.0710754395],"type":"Point"}
}