{
  "type": "Feature",
  "properties": {
    "addr:full":"Dokter De Drijverestraat 45 Brakel (nederbrakel) Oost-Vlaanderen 9660",
    "addr:housenumber":"45",
    "addr:postcode":"9660",
    "addr:street":"Dokter De Drijverestraat",
    "iso:country":"BE",
    "sg:address":"Dokter De Drijverestraat 45",
    "sg:city":"Brakel (nederbrakel)",
    "sg:classifiers":[
        {
            "category":"Professional",
            "subcategory":"Engineering",
            "type":"Services"
        }
    ],
    "sg:phone":"+32 55 42 48 47",
    "sg:postcode":"9660",
    "sg:province":"Oost-Vlaanderen",
    "sg:tags":[
        "-"
    ],
    "wof:name":"Codeco Cooman Bvba",
    "wof:placetype":"venue"
},
  "geometry": {"coordinates":[3.7683959007,50.801109314],"type":"Point"}
}