{
  "type": "Feature",
  "properties": {
    "addr:full":"Diepmeersstraat 53 Buggenhout Oost-Vlaanderen 9255",
    "addr:housenumber":"53",
    "addr:postcode":"9255",
    "addr:street":"Diepmeersstraat",
    "iso:country":"BE",
    "sg:address":"Diepmeersstraat 53",
    "sg:city":"Buggenhout",
    "sg:orig_category":"Informaticaconsulenten",
    "sg:phone":"+32 52 34 17 97",
    "sg:postcode":"9255",
    "sg:province":"Oost-Vlaanderen",
    "wof:name":"Van Evercooren F",
    "wof:placetype":"venue"
},
  "geometry": {"coordinates":[4.1887688637,51.0270233154],"type":"Point"}
}