{
  "type": "Feature",
  "properties": {
    "iso:country":"BE",
    "sg:address":"Van Haelenstraat 14",
    "sg:city":"Koksijde",
    "sg:classifiers":[
        {
            "category":"Cafe",
            "type":"Food & Drink"
        }
    ],
    "sg:phone":"+32 58 52 28 02",
    "sg:postcode":"8670",
    "sg:province":"West-Vlaanderen",
    "sg:tags":[
        "caf\u00e9s"
    ],
    "wof:name":"Richard Bourgois",
    "wof:placetype":"venue"
},
  "geometry": {"coordinates":[2.6379289627,51.1222457886],"type":"Point"}
}