{
  "type": "Feature",
  "properties": {
    "iso:country":"BE",
    "sg:address":"Rue Werner Wilquet 16",
    "sg:city":"Genappe",
    "sg:orig_category":"Rundveehouders",
    "sg:phone":"+32 2 633 15 50",
    "sg:postcode":"1473",
    "sg:province":"Brabant Wallon",
    "wof:name":"Frans Balduyck",
    "wof:placetype":"venue"
},
  "geometry": {"coordinates":[4.4565930367,50.6417427063],"type":"Point"}
}