{
  "type": "Feature",
  "properties": {
    "addr:full":"Avenue Milieu Du Monde 3 Namur Namur 5000",
    "addr:housenumber":"3",
    "addr:postcode":"5000",
    "addr:street":"Avenue Milieu Du Monde",
    "iso:country":"BE",
    "sg:address":"Avenue Milieu Du Monde 3",
    "sg:city":"Namur",
    "sg:classifiers":[
        {
            "category":"Arena",
            "subcategory":"Sports Club",
            "type":"Entertainment"
        }
    ],
    "sg:phone":"+32 81 74 03 74",
    "sg:postcode":"5000",
    "sg:province":"Namur",
    "sg:tags":[
        "de"
    ],
    "wof:name":"Tennis De La Citadelle",
    "wof:placetype":"venue"
},
  "geometry": {"coordinates":[4.8525118828,50.4558906555],"type":"Point"}
}