{
  "type": "Feature",
  "properties": {
    "addr:full":"Place Albert Ier 47 Malmedy/malmedy Li\u00e8ge 4960",
    "addr:housenumber":"47",
    "addr:postcode":"4960",
    "addr:street":"Place Albert Ier",
    "iso:country":"BE",
    "sg:address":"Place Albert Ier 47",
    "sg:city":"Malmedy/malmedy",
    "sg:orig_category":"Banken and kredietinstellingen",
    "sg:phone":"+32 80 33 85 61",
    "sg:postcode":"4960",
    "sg:province":"Li\u00e8ge",
    "wof:name":"Fortis",
    "wof:placetype":"venue"
},
  "geometry": {"coordinates":[6.0551772118,50.37657547],"type":"Point"}
}