{
  "type": "Feature",
  "properties": {
    "iso:country":"BE",
    "sg:address":"Dorpsstraat 109b1",
    "sg:city":"Damme",
    "sg:orig_category":"Banken and kredietinstellingen",
    "sg:phone":"+32 50 35 83 42",
    "sg:postcode":"8340",
    "sg:province":"West-Vlaanderen",
    "wof:name":"Dexia",
    "wof:placetype":"venue"
},
  "geometry": {"coordinates":[3.3232650757,51.2015533447],"type":"Point"}
}