{
  "type": "Feature",
  "properties": {
    "iso:country":"BE",
    "sg:address":"Smidstraat 196",
    "sg:city":"Berlaar",
    "sg:orig_category":"Fleurs and plantes",
    "sg:phone":"+32 3 422 56 90",
    "sg:postcode":"2590",
    "sg:province":"Antwerpen",
    "wof:name":"Natuurverschijnselen",
    "wof:placetype":"venue"
},
  "geometry": {"coordinates":[4.6528978348,51.1101760864],"type":"Point"}
}