{
  "type": "Feature",
  "properties": {
    "iso:country":"BE",
    "sg:address":"Route De La Vall\u00c9e 28",
    "sg:city":"Bouillon",
    "sg:orig_category":"Installation de menuiserie en bois and plastique",
    "sg:phone":"+32 61 46 82 56",
    "sg:postcode":"6833",
    "sg:province":"Luxembourg",
    "wof:name":"Danny Collard",
    "wof:placetype":"venue"
},
  "geometry": {"coordinates":[5.0664200783,49.8508300781],"type":"Point"}
}