{
  "type": "Feature",
  "properties": {
    "iso:country":"BE",
    "sg:address":"Gentseweg 536",
    "sg:city":"Beveren",
    "sg:classifiers":[
        {
            "category":"Restaurant",
            "type":"Food & Drink"
        }
    ],
    "sg:phone":"+32 3 775 47 88",
    "sg:postcode":"9120",
    "sg:province":"Oost-Vlaanderen",
    "wof:name":"Sint-maarten",
    "wof:placetype":"venue"
},
  "geometry": {"coordinates":[4.2185897827,51.1951789856],"type":"Point"}
}