{
  "type": "Feature",
  "properties": {
    "iso:country":"BE",
    "sg:address":"Chauss\u00e9e De Namur 14",
    "sg:city":"Profondeville",
    "sg:classifiers":[
        {
            "category":"Autos & Motor Vehicles",
            "subcategory":"Motorcycle Sales",
            "type":"Retail Goods"
        }
    ],
    "sg:phone":"+32 81 41 37 30",
    "sg:postcode":"5170",
    "sg:province":"Namur",
    "sg:tags":[
        "scooter",
        "-",
        "moped"
    ],
    "wof:name":"Bill'bike",
    "wof:placetype":"venue"
},
  "geometry": {"coordinates":[4.8685297966,50.378036499],"type":"Point"}
}