{
  "type": "Feature",
  "properties": {
    "addr:full":"Harelbekestraat 63 Deerlijk West-Vlaanderen 8540",
    "addr:housenumber":"63",
    "addr:postcode":"8540",
    "addr:street":"Harelbekestraat",
    "iso:country":"BE",
    "sg:address":"Harelbekestraat 63",
    "sg:city":"Deerlijk",
    "sg:orig_category":"Avocats and conseillers juridiques",
    "sg:phone":"+32 56 71 63 44",
    "sg:postcode":"8540",
    "sg:province":"West-Vlaanderen",
    "wof:name":"Jan Deleersnyder",
    "wof:placetype":"venue"
},
  "geometry": {"coordinates":[3.3506169319,50.8521537781],"type":"Point"}
}