{
  "type": "Feature",
  "properties": {
    "addr:full":"Place Du Luxembourg 12 Bruxelles (ixelles) Bruxelles-Capitale 1050",
    "addr:housenumber":"12",
    "addr:postcode":"1050",
    "addr:street":"Place Du Luxembourg",
    "iso:country":"BE",
    "sg:address":"Place Du Luxembourg 12",
    "sg:city":"Bruxelles (ixelles)",
    "sg:classifiers":[
        {
            "category":"Bars & Pubs",
            "type":"Food & Drink"
        }
    ],
    "sg:phone":"+32 2 230 15 82",
    "sg:postcode":"1050",
    "sg:province":"Bruxelles-Capitale",
    "wof:name":"Pullman (le)",
    "wof:placetype":"venue"
},
  "geometry": {"coordinates":[4.3726921082,50.8395576477],"type":"Point"}
}