{
  "type": "Feature",
  "properties": {
    "addr:full":"Rue Geleytsbeek 59 Ukkel/uccle Bruxelles-Capitale 1180",
    "addr:housenumber":"59",
    "addr:postcode":"1180",
    "addr:street":"Rue Geleytsbeek;/",
    "iso:country":"BE",
    "sg:address":"Rue Geleytsbeek 59",
    "sg:city":"Ukkel/uccle",
    "sg:orig_category":"M\u00e9decins and sp\u00e9cialistes",
    "sg:phone":"+32 2 374 61 36",
    "sg:postcode":"1180",
    "sg:province":"Bruxelles-Capitale",
    "wof:name":"Kristel Vandenbosch",
    "wof:placetype":"venue"
},
  "geometry": {"coordinates":[4.3460788727,50.7919464111],"type":"Point"}
}