{
  "type": "Feature",
  "properties": {
    "iso:country":"BE",
    "sg:address":"Franklin Rooseveltlaan 1",
    "sg:city":"Gent",
    "sg:orig_category":"Production and distribution d'\u00e9lectricit\u00e9. Services de t\u00e9l\u00e9communications. Compagnies de distributio",
    "sg:phone":"+32 78 35 35 35",
    "sg:postcode":"9000",
    "sg:province":"Oost-Vlaanderen",
    "wof:name":"Electrabel",
    "wof:placetype":"venue"
},
  "geometry": {"coordinates":[3.7299399376,51.0474281311],"type":"Point"}
}