{
  "type": "Feature",
  "properties": {
    "addr:full":"Rue Sainte-anne 5 Fleurus Hainaut 6220",
    "addr:housenumber":"5",
    "addr:postcode":"6220",
    "addr:street":"Rue Sainte-Anne",
    "iso:country":"BE",
    "sg:address":"Rue Sainte-anne 5",
    "sg:city":"Fleurus",
    "sg:orig_category":"Formation permanente",
    "sg:phone":"+32 71 30 22 17",
    "sg:postcode":"6220",
    "sg:province":"Hainaut",
    "wof:name":"Prom.soc. Inst. St.anne",
    "wof:placetype":"venue"
},
  "geometry": {"coordinates":[4.5515980721,50.4820747375],"type":"Point"}
}