{
  "type": "Feature",
  "properties": {
    "iso:country":"BE",
    "sg:address":"Avenue De La Basilique 17",
    "sg:city":"Peruwelz",
    "sg:classifiers":[
        {
            "category":"Cafe",
            "type":"Food & Drink"
        }
    ],
    "sg:phone":"+32 69 77 44 18",
    "sg:postcode":"7603",
    "sg:province":"Hainaut",
    "sg:tags":[
        "caf\u00e9s"
    ],
    "wof:name":"Philippe Debuys",
    "wof:placetype":"venue"
},
  "geometry": {"coordinates":[3.6059529781,50.4979858398],"type":"Point"}
}