{
  "type": "Feature",
  "properties": {
    "iso:country":"BE",
    "sg:address":"Quai De La D\u00e9rivation 2",
    "sg:city":"Li\u00e8ge 1 (li\u00e8ge 2)",
    "sg:classifiers":[
        {
            "category":"Manufacturing",
            "subcategory":"Rubber & Plastics",
            "type":"Manufacturing & Wholesale Goods"
        }
    ],
    "sg:phone":"+32 4 343 07 99",
    "sg:postcode":"4020",
    "sg:province":"Li\u00e8ge",
    "sg:tags":[
        "foam"
    ],
    "wof:name":"Les Ateliers Revor",
    "wof:placetype":"venue"
},
  "geometry": {"coordinates":[5.586783886,50.6383361816],"type":"Point"}
}