{
  "type": "Feature",
  "properties": {
    "iso:country":"BE",
    "sg:address":"Kalkendorp 28",
    "sg:city":"Laarne (kalken)",
    "sg:classifiers":[
        {
            "category":"Bars & Pubs",
            "type":"Food & Drink"
        }
    ],
    "sg:phone":"+32 9 367 67 68",
    "sg:postcode":"9270",
    "sg:province":"Oost-Vlaanderen",
    "wof:name":"Breughel",
    "wof:placetype":"venue"
},
  "geometry": {"coordinates":[3.9175400734,51.0364494324],"type":"Point"}
}