{
  "type": "Feature",
  "properties": {
    "iso:country":"BE",
    "sg:address":"Vervierser Strasse 26",
    "sg:city":"Eupen/eupen",
    "sg:orig_category":"Binnenhuisarchitecten Immobili\u00ebnkantoren",
    "sg:phone":"+32 87 55 68 41",
    "sg:postcode":"4700",
    "sg:province":"Li\u00e8ge",
    "wof:name":"Euroconsult",
    "wof:placetype":"venue"
},
  "geometry": {"coordinates":[6.0258049965,50.631565094],"type":"Point"}
}