{
  "type": "Feature",
  "properties": {
    "addr:full":"Rue Le Campinaire 95 Farciennes Hainaut 6240",
    "addr:housenumber":"95",
    "addr:postcode":"6240",
    "addr:street":"Rue Le Campinaire",
    "iso:country":"BE",
    "sg:address":"Rue Le Campinaire 95",
    "sg:city":"Farciennes",
    "sg:classifiers":[
        {
            "category":"Arena",
            "subcategory":"Sports Club",
            "type":"Entertainment"
        }
    ],
    "sg:phone":"+32 71 39 52 70",
    "sg:postcode":"6240",
    "sg:province":"Hainaut",
    "sg:tags":[
        "de"
    ],
    "wof:name":"La Bande \u00c0 Bodart",
    "wof:placetype":"venue"
},
  "geometry": {"coordinates":[4.5418100357,50.4288253784],"type":"Point"}
}