{
  "type": "Feature",
  "properties": {
    "iso:country":"BE",
    "sg:address":"Ettelgemsestraat 68",
    "sg:city":"Oudenburg",
    "sg:classifiers":[
        {
            "category":"Food & Beverages",
            "subcategory":"Meat & Fish",
            "type":"Retail Goods"
        }
    ],
    "sg:phone":"+32 59 26 60 14",
    "sg:postcode":"8460",
    "sg:province":"West-Vlaanderen",
    "sg:tags":[
        "-",
        "livestock"
    ],
    "wof:name":"Souvagie R",
    "wof:placetype":"venue"
},
  "geometry": {"coordinates":[3.0141899586,51.1836662292],"type":"Point"}
}