{
  "type": "Feature",
  "properties": {
    "iso:country":"BE",
    "sg:address":"Frans Van Der Steenstraat 69",
    "sg:city":"Lennik (sint-kwintens-lennik)",
    "sg:classifiers":[
        {
            "category":"Food & Beverages",
            "subcategory":"Groceries & Convenience Stores",
            "type":"Retail Goods"
        }
    ],
    "sg:phone":"+32 2 532 13 82",
    "sg:postcode":"1750",
    "sg:province":"Vlaams-Brabant",
    "sg:tags":[
        "grocer"
    ],
    "wof:name":"De Boeck C",
    "wof:placetype":"venue"
},
  "geometry": {"coordinates":[4.1548509598,50.8022117615],"type":"Point"}
}