{
  "type": "Feature",
  "properties": {
    "iso:country":"BE",
    "sg:address":"Moerlandstraat 4",
    "sg:city":"Sint-niklaas",
    "sg:classifiers":[
        {
            "category":"Personal",
            "subcategory":"Beauty Salon",
            "type":"Services"
        }
    ],
    "sg:phone":"+32 3 777 75 48",
    "sg:postcode":"9100",
    "sg:province":"Oost-Vlaanderen",
    "sg:tags":[
        "lady",
        "-",
        "hairdressing"
    ],
    "wof:name":"Kapper Aan Huis (de)",
    "wof:placetype":"venue"
},
  "geometry": {"coordinates":[4.1523990631,51.1613273621],"type":"Point"}
}