{
  "type": "Feature",
  "properties": {
    "addr:full":"Koning - Albertstraat 109 Geel Antwerpen 2440",
    "addr:housenumber":"109",
    "addr:postcode":"2440",
    "addr:street":"Koning Albertstraat",
    "iso:country":"BE",
    "sg:address":"Koning - Albertstraat 109",
    "sg:city":"Geel",
    "sg:classifiers":[
        {
            "category":"Food & Beverages",
            "subcategory":"Meat & Fish",
            "type":"Retail Goods"
        }
    ],
    "sg:phone":"+32 14 58 91 82",
    "sg:postcode":"2440",
    "sg:province":"Antwerpen",
    "sg:tags":[
        "-",
        "livestock"
    ],
    "wof:name":"Hobbyvoeders Wim",
    "wof:placetype":"venue"
},
  "geometry": {"coordinates":[4.9791312218,51.1353683472],"type":"Point"}
}