{
  "type": "Feature",
  "properties": {
    "addr:full":"Duquesnoystraat 45 Brussel/bruxelles Bruxelles-Capitale 1000",
    "addr:housenumber":"45",
    "addr:postcode":"1000",
    "addr:street":"Duquesnoystraat;/",
    "iso:country":"BE",
    "sg:address":"Duquesnoystraat 45",
    "sg:city":"Brussel/bruxelles",
    "sg:classifiers":[
        {
            "category":"Restaurant",
            "type":"Food & Drink"
        }
    ],
    "sg:phone":"+32 2 502 46 39",
    "sg:postcode":"1000",
    "sg:province":"Bruxelles-Capitale",
    "wof:name":"Taverne Le Go-go",
    "wof:placetype":"venue"
},
  "geometry": {"coordinates":[4.3532972336,50.8448600769],"type":"Point"}
}