{
  "type": "Feature",
  "properties": {
    "iso:country":"BE",
    "sg:address":"Vredestraat 36",
    "sg:city":"Oostende",
    "sg:orig_category":"Woningbouw",
    "sg:phone":"+32 59 70 09 50",
    "sg:postcode":"8400",
    "sg:province":"West-Vlaanderen",
    "wof:name":"Baeteman En Zonen",
    "wof:placetype":"venue"
},
  "geometry": {"coordinates":[2.8905930519,51.2151603699],"type":"Point"}
}