{
  "type": "Feature",
  "properties": {
    "iso:country":"BE",
    "sg:address":"Dorp 24",
    "sg:city":"Lille (poederlee)",
    "sg:classifiers":[
        {
            "category":"Health Services",
            "subcategory":"Health Practitioner",
            "type":"Services"
        }
    ],
    "sg:phone":"+32 14 88 28 18",
    "sg:postcode":"2275",
    "sg:province":"Antwerpen",
    "sg:tags":[
        "physiotherapist"
    ],
    "wof:name":"Asselman Hugo",
    "wof:placetype":"venue"
},
  "geometry": {"coordinates":[4.835723877,51.2280693054],"type":"Point"}
}