{
  "type": "Feature",
  "properties": {
    "iso:country":"BE",
    "sg:address":"Wettersestraat 4",
    "sg:city":"Wichelen",
    "sg:orig_category":"Opticiens",
    "sg:phone":"+32 9 366 00 31",
    "sg:postcode":"9260",
    "sg:province":"Oost-Vlaanderen",
    "wof:name":"Optiek Geertrui",
    "wof:placetype":"venue"
},
  "geometry": {"coordinates":[3.9267590046,51.0129928589],"type":"Point"}
}