{
  "type": "Feature",
  "properties": {
    "addr:full":"Winterslagstraat 11 Genk Limburg 3600",
    "addr:housenumber":"11",
    "addr:postcode":"3600",
    "addr:street":"Winterslagstraat",
    "iso:country":"BE",
    "sg:address":"Winterslagstraat 11",
    "sg:city":"Genk",
    "sg:classifiers":[
        {
            "category":"Travel",
            "subcategory":"Hotels & Motels",
            "type":"Entertainment"
        }
    ],
    "sg:phone":"+32 89 35 27 69",
    "sg:postcode":"3600",
    "sg:province":"Limburg",
    "sg:tags":[
        "van",
        "restaurant",
        "food",
        "aan",
        "fast",
        "feesten",
        "levering",
        "meeneem",
        "organisatie",
        "rest",
        "catering",
        "huis"
    ],
    "wof:name":"Hotel 't Hert",
    "wof:placetype":"venue"
},
  "geometry": {"coordinates":[5.4989600182,50.9667243958],"type":"Point"}
}