{
  "type": "Feature",
  "properties": {
    "iso:country":"BE",
    "sg:address":"Bekersveldstraat 4b",
    "sg:city":"Sint-pieters-leeuw (vlezenbeek)",
    "sg:classifiers":[
        {
            "category":"Freight",
            "type":"Transportation"
        }
    ],
    "sg:phone":"+32 2 532 10 46",
    "sg:postcode":"1602",
    "sg:province":"Vlaams-Brabant",
    "sg:tags":[
        "-",
        "transport"
    ],
    "wof:name":"De Ridder P",
    "wof:placetype":"venue"
},
  "geometry": {"coordinates":[4.22651577,50.7939338684],"type":"Point"}
}