{
  "type": "Feature",
  "properties": {
    "iso:country":"BE",
    "sg:address":"Ekkelenbergstraat 7",
    "sg:city":"Herne",
    "sg:classifiers":[
        {
            "category":"Social Services",
            "subcategory":"Job Training",
            "type":"Services"
        }
    ],
    "sg:phone":"+32 2 396 27 38",
    "sg:postcode":"1540",
    "sg:province":"Vlaams-Brabant",
    "sg:tags":[
        "personnel"
    ],
    "wof:name":"Rhe'a Consult Bvba",
    "wof:placetype":"venue"
},
  "geometry": {"coordinates":[4.0508871078,50.7337303162],"type":"Point"}
}