{
  "type": "Feature",
  "properties": {
    "iso:country":"BE",
    "sg:address":"Sint-denijsstraat 18",
    "sg:city":"Zwevegem",
    "sg:orig_category":"Dierenartsen",
    "sg:phone":"+32 56 75 93 21",
    "sg:postcode":"8550",
    "sg:province":"West-Vlaanderen",
    "wof:name":"Bernard Vangheluwe",
    "wof:placetype":"venue"
},
  "geometry": {"coordinates":[3.3374860287,50.7963600159],"type":"Point"}
}