{
  "type": "Feature",
  "properties": {
    "addr:full":"Boerenstraat 12 Zelzate Oost-Vlaanderen 9060",
    "addr:housenumber":"12",
    "addr:postcode":"9060",
    "addr:street":"Boerenstraat",
    "iso:country":"BE",
    "sg:address":"Boerenstraat 12",
    "sg:city":"Zelzate",
    "sg:classifiers":[
        {
            "category":"Professional",
            "subcategory":"Accounting & Tax Preparation",
            "type":"Services"
        }
    ],
    "sg:phone":"+32 9 345 50 88",
    "sg:postcode":"9060",
    "sg:province":"Oost-Vlaanderen",
    "sg:tags":[
        "bookkeeper"
    ],
    "wof:name":"Verhegge J.p.",
    "wof:placetype":"venue"
},
  "geometry": {"coordinates":[3.8121469021,51.1967315674],"type":"Point"}
}