{
  "type": "Feature",
  "properties": {
    "addr:full":"Rue De Li\u00c8ge 39 Verviers Li\u00e8ge 4800",
    "addr:housenumber":"39",
    "addr:postcode":"4800",
    "addr:street":"Rue De Lie\u0300Ge",
    "iso:country":"BE",
    "sg:address":"Rue De Li\u00c8ge 39",
    "sg:city":"Verviers",
    "sg:classifiers":[
        {
            "category":"Insurance",
            "subcategory":"Life Insurance",
            "type":"Services"
        }
    ],
    "sg:phone":"+32 87 22 41 31",
    "sg:postcode":"4800",
    "sg:province":"Li\u00e8ge",
    "sg:tags":[
        "assurance"
    ],
    "wof:name":"M\u00c9nage & Jowa Gras Savoye",
    "wof:placetype":"venue"
},
  "geometry": {"coordinates":[5.8563342094,50.5861587524],"type":"Point"}
}