{
  "type": "Feature",
  "properties": {
    "addr:full":"Gen Lemansstraat Antwerpen (groot) Antwerpen 2018",
    "addr:postcode":"2018",
    "addr:street":"Gen Lemansstraat;Groot Antwerpen",
    "iso:country":"BE",
    "sg:address":"Gen Lemansstraat",
    "sg:city":"Antwerpen (groot)",
    "sg:orig_category":"Banques and organismes de cr\u00e9dit",
    "sg:phone":"+32 3 240 02 11",
    "sg:postcode":"2018",
    "sg:province":"Antwerpen",
    "wof:name":"Bacob",
    "wof:placetype":"venue"
},
  "geometry": {"coordinates":[4.4119811058,51.1935348511],"type":"Point"}
}