{
  "type": "Feature",
  "properties": {
    "addr:full":"Heikantstraat 48 Laakdal (eindhout) Antwerpen 2430",
    "addr:housenumber":"48",
    "addr:postcode":"2430",
    "addr:street":"Heikantstraat",
    "iso:country":"BE",
    "sg:address":"Heikantstraat 48",
    "sg:city":"Laakdal (eindhout)",
    "sg:classifiers":[
        {
            "category":"Wholesale",
            "subcategory":"Vending Machines",
            "type":"Manufacturing & Wholesale Goods"
        }
    ],
    "sg:phone":"+32 478 93 87 14",
    "sg:postcode":"2430",
    "sg:province":"Antwerpen",
    "sg:tags":[
        "groundwork",
        "material",
        "-"
    ],
    "wof:name":"Barrezeele & Vanuytsel Bvba",
    "wof:placetype":"venue"
},
  "geometry": {"coordinates":[5.0687851906,51.0857543945],"type":"Point"}
}