{
  "type": "Feature",
  "properties": {
    "addr:full":"Vliegveld 37 Wevelgem West-Vlaanderen 8560",
    "addr:housenumber":"37",
    "addr:postcode":"8560",
    "addr:street":"Vliegveld",
    "iso:country":"BE",
    "sg:address":"Vliegveld 37",
    "sg:city":"Wevelgem",
    "sg:classifiers":[
        {
            "category":"Utilities",
            "subcategory":"Telephone",
            "type":"Services"
        }
    ],
    "sg:phone":"+32 56 43 98 43",
    "sg:postcode":"8560",
    "sg:province":"West-Vlaanderen",
    "sg:tags":[
        "karting",
        "accessory"
    ],
    "wof:name":"Karting Concept Company Bvba",
    "wof:placetype":"venue"
},
  "geometry": {"coordinates":[3.2045440674,50.8184356689],"type":"Point"}
}