{
  "type": "Feature",
  "properties": {
    "addr:full":"Zeelaan 138 De Panne West-Vlaanderen 8660",
    "addr:housenumber":"138",
    "addr:postcode":"8660",
    "addr:street":"Zeelaan",
    "iso:country":"BE",
    "sg:address":"Zeelaan 138",
    "sg:city":"De Panne",
    "sg:classifiers":[
        {
            "category":"Shopping",
            "subcategory":"Clothing, Apparel, & Fashions",
            "type":"Retail Goods"
        }
    ],
    "sg:phone":"+32 58 41 11 47",
    "sg:postcode":"8660",
    "sg:province":"West-Vlaanderen",
    "sg:tags":[
        "lady",
        "clothing",
        "-"
    ],
    "wof:name":"Gaston (maison)",
    "wof:placetype":"venue"
},
  "geometry": {"coordinates":[2.5923418999,51.1011123657],"type":"Point"}
}