{
  "type": "Feature",
  "properties": {
    "addr:full":"Avenue Albert I 93 Namur Namur 5000",
    "addr:housenumber":"93",
    "addr:postcode":"5000",
    "addr:street":"Avenue Albert I",
    "iso:country":"BE",
    "sg:address":"Avenue Albert I 93",
    "sg:city":"Namur",
    "sg:classifiers":[
        {
            "category":"Insurance",
            "subcategory":"Insurance Agent",
            "type":"Services"
        }
    ],
    "sg:phone":"+32 81 22 37 41",
    "sg:postcode":"5000",
    "sg:province":"Namur",
    "sg:tags":[
        "broker"
    ],
    "wof:name":"Cooperative Luxembourgeoise",
    "wof:placetype":"venue"
},
  "geometry": {"coordinates":[4.8823208809,50.4670219421],"type":"Point"}
}