{
  "type": "Feature",
  "properties": {
    "iso:country":"BE",
    "sg:address":"Rue Des Pr\u00e9s Fleuris 24",
    "sg:city":"Verviers (ensival)",
    "sg:classifiers":[
        {
            "category":"Personal",
            "subcategory":"Barber",
            "type":"Services"
        }
    ],
    "sg:phone":"+32 87 35 21 06",
    "sg:postcode":"4800",
    "sg:province":"Li\u00e8ge",
    "sg:tags":[
        "gentleman",
        "salon",
        "-",
        "hairdressing"
    ],
    "wof:name":"Ciseaux Volants (les)",
    "wof:placetype":"venue"
},
  "geometry": {"coordinates":[5.8396501541,50.586101532],"type":"Point"}
}