{
  "type": "Feature",
  "properties": {
    "addr:full":"Route Du Condroz 464 Li\u00c8ge Li\u00e8ge 4031",
    "addr:housenumber":"464",
    "addr:postcode":"4031",
    "addr:street":"Route Du Condroz",
    "iso:country":"BE",
    "sg:address":"Route Du Condroz 464",
    "sg:city":"Li\u00c8ge",
    "sg:classifiers":[
        {
            "category":"Fast Food",
            "type":"Food & Drink"
        }
    ],
    "sg:phone":"+32 4 227 56 76",
    "sg:postcode":"4031",
    "sg:province":"Li\u00e8ge",
    "sg:tags":[
        "\u00c0",
        "emporter",
        "restaurants"
    ],
    "wof:name":"Somorest",
    "wof:placetype":"venue"
},
  "geometry": {"coordinates":[5.5761699677,50.5973396301],"type":"Point"}
}