{
  "type": "Feature",
  "properties": {
    "addr:full":"Rue Grand Piersoulx 1 Charleroi (gosselies) Hainaut 6041",
    "addr:housenumber":"1",
    "addr:postcode":"6041",
    "addr:street":"Rue Grand Piersoulx",
    "iso:country":"BE",
    "sg:address":"Rue Grand Piersoulx 1",
    "sg:city":"Charleroi (gosselies)",
    "sg:classifiers":[
        {
            "category":"Utilities",
            "subcategory":"Fuel Oil & Lpg",
            "type":"Services"
        }
    ],
    "sg:phone":"+32 71 35 16 15",
    "sg:postcode":"6041",
    "sg:province":"Hainaut",
    "wof:name":"Vdv Mazout Sprl",
    "wof:placetype":"venue"
},
  "geometry": {"coordinates":[4.4314317703,50.4685935974],"type":"Point"}
}