{
  "type": "Feature",
  "properties": {
    "iso:country":"BE",
    "sg:address":"Van Haeftenlaan 33",
    "sg:city":"Kapellen",
    "sg:orig_category":"Woningbouw",
    "sg:phone":"+32 3 664 86 56",
    "sg:postcode":"2950",
    "sg:province":"Antwerpen",
    "wof:name":"Frans Koninckx",
    "wof:placetype":"venue"
},
  "geometry": {"coordinates":[4.440885067,51.3243484497],"type":"Point"}
}