{
  "type": "Feature",
  "properties": {
    "iso:country":"BE",
    "sg:address":"Avenue De La Wallonie 125",
    "sg:city":"Leuze-en-hainaut",
    "sg:orig_category":"Installation \u00e9lectrique r\u00e9sidentielle",
    "sg:phone":"+32 69 66 20 56",
    "sg:postcode":"7900",
    "sg:province":"Hainaut",
    "wof:name":"Bernard Durand",
    "wof:placetype":"venue"
},
  "geometry": {"coordinates":[3.6323668957,50.5837059021],"type":"Point"}
}