{
  "type": "Feature",
  "properties": {
    "iso:country":"BE",
    "sg:address":"Rue De L'argili\u00c8re 121",
    "sg:city":"Mons",
    "sg:orig_category":"Verhuur textielartikelen and schoenen",
    "sg:phone":"+32 65 88 43 40",
    "sg:postcode":"7012",
    "sg:province":"Hainaut",
    "wof:name":"Au Prince Carnaval",
    "wof:placetype":"venue"
},
  "geometry": {"coordinates":[3.8922801018,50.4416313171],"type":"Point"}
}