{
  "type": "Feature",
  "properties": {
    "addr:full":"Ortolanenlaan 7 Watermaal-bosvoorde/watermael-boitsfort Bruxelles-Capitale 1170",
    "addr:housenumber":"7",
    "addr:postcode":"1170",
    "addr:street":"Ortolanenlaan",
    "iso:country":"BE",
    "sg:address":"Ortolanenlaan 7",
    "sg:city":"Watermaal-bosvoorde/watermael-boitsfort",
    "sg:orig_category":"Artsen and specialisten",
    "sg:phone":"+32 2 660 62 33",
    "sg:postcode":"1170",
    "sg:province":"Bruxelles-Capitale",
    "wof:name":"Pierre Debehogne",
    "wof:placetype":"venue"
},
  "geometry": {"coordinates":[4.4123902321,50.8027954102],"type":"Point"}
}