{
  "type": "Feature",
  "properties": {
    "addr:full":"Franklin Rooseveltlaan 186b1 Brussel/bruxelles Bruxelles-Capitale 1050",
    "addr:housenumber":"186b1",
    "addr:postcode":"1050",
    "addr:street":"Franklin Rooseveltlaan;/",
    "iso:country":"BE",
    "sg:address":"Franklin Rooseveltlaan 186b1",
    "sg:city":"Brussel/bruxelles",
    "sg:orig_category":"Advocaten and juridische adviseurs",
    "sg:phone":"+32 2 672 27 02",
    "sg:postcode":"1050",
    "sg:province":"Bruxelles-Capitale",
    "wof:name":"Renaud Goossens",
    "wof:placetype":"venue"
},
  "geometry": {"coordinates":[4.3886198997,50.802936554],"type":"Point"}
}