{
  "type": "Feature",
  "properties": {
    "addr:full":"Dr.-van De Perrestraat 395 Geel Antwerpen 2440",
    "addr:housenumber":"395",
    "addr:postcode":"2440",
    "addr:street":"Dr.-Van De Perrestraat",
    "iso:country":"BE",
    "sg:address":"Dr.-van De Perrestraat 395",
    "sg:city":"Geel",
    "sg:orig_category":"R\u00e9parations de chaussures and articles en cuir",
    "sg:phone":"+32 14 58 59 26",
    "sg:postcode":"2440",
    "sg:province":"Antwerpen",
    "wof:name":"Raymond Gebruers",
    "wof:placetype":"venue"
},
  "geometry": {"coordinates":[4.9834728241,51.1882705688],"type":"Point"}
}