{
  "type": "Feature",
  "properties": {
    "addr:full":"Rue De Binche 2 Merbes-le-ch\u00c2teau Hainaut 6567",
    "addr:housenumber":"2",
    "addr:postcode":"6567",
    "addr:street":"Rue De Binche",
    "iso:country":"BE",
    "sg:address":"Rue De Binche 2",
    "sg:city":"Merbes-le-ch\u00c2teau",
    "sg:orig_category":"Eleveurs de bovins",
    "sg:phone":"+32 71 55 50 82",
    "sg:postcode":"6567",
    "sg:province":"Hainaut",
    "wof:name":"Bernard Leblanc",
    "wof:placetype":"venue"
},
  "geometry": {"coordinates":[4.1672229767,50.3258895874],"type":"Point"}
}