{
  "type": "Feature",
  "properties": {
    "addr:full":"Rue De Rechain 168 Dison Li\u00e8ge 4820",
    "addr:housenumber":"168",
    "addr:postcode":"4820",
    "addr:street":"Rue De Rechain",
    "iso:country":"BE",
    "sg:address":"Rue De Rechain 168",
    "sg:city":"Dison",
    "sg:classifiers":[
        {
            "category":"Insurance",
            "subcategory":"Insurance Agent",
            "type":"Services"
        }
    ],
    "sg:phone":"+32 87 35 21 16",
    "sg:postcode":"4820",
    "sg:province":"Li\u00e8ge",
    "sg:tags":[
        "verzekeringsmakelaars",
        "expert"
    ],
    "wof:name":"Fafchamps",
    "wof:placetype":"venue"
},
  "geometry": {"coordinates":[5.8438692093,50.6127891541],"type":"Point"}
}