{
  "type": "Feature",
  "properties": {
    "iso:country":"BE",
    "sg:address":"R. Vander Bruggenlaan 100b12",
    "sg:city":"Anderlecht",
    "sg:orig_category":"Artsen and specialisten",
    "sg:phone":"+32 2 523 98 07",
    "sg:postcode":"1070",
    "sg:province":"Bruxelles-Capitale",
    "wof:name":"Isabelle Vanherle",
    "wof:placetype":"venue"
},
  "geometry": {"coordinates":[4.3130831718,50.8384666443],"type":"Point"}
}