{
  "type": "Feature",
  "properties": {
    "iso:country":"BE",
    "sg:address":"Rue Royale 147",
    "sg:city":"Florennes",
    "sg:orig_category":"Installation de menuiserie en bois and plastique",
    "sg:phone":"+32 71 68 82 44",
    "sg:postcode":"5621",
    "sg:province":"Namur",
    "wof:name":"Franquet G. & Helu M.",
    "wof:placetype":"venue"
},
  "geometry": {"coordinates":[4.565653801,50.2752952576],"type":"Point"}
}