{
  "type": "Feature",
  "properties": {
    "addr:full":"Pastoor Bontestraat 90 Eeklo Oost-Vlaanderen 9900",
    "addr:housenumber":"90",
    "addr:postcode":"9900",
    "addr:street":"Pastoor Bontestraat",
    "iso:country":"BE",
    "sg:address":"Pastoor Bontestraat 90",
    "sg:city":"Eeklo",
    "sg:classifiers":[
        {
            "category":"Insurance",
            "subcategory":"Life Insurance",
            "type":"Services"
        }
    ],
    "sg:phone":"+32 9 377 48 11",
    "sg:postcode":"9900",
    "sg:province":"Oost-Vlaanderen",
    "sg:tags":[
        "assurance"
    ],
    "wof:name":"Kantoor Declercq",
    "wof:placetype":"venue"
},
  "geometry": {"coordinates":[3.5276310444,51.2035255432],"type":"Point"}
}