{
  "type": "Feature",
  "properties": {
    "iso:country":"BE",
    "sg:address":"Olmstraat 77",
    "sg:city":"Waregem",
    "sg:classifiers":[
        {
            "category":"Arena",
            "subcategory":"Sports Club",
            "type":"Entertainment"
        }
    ],
    "sg:phone":"+32 56 60 95 86",
    "sg:postcode":"8790",
    "sg:province":"West-Vlaanderen",
    "sg:tags":[
        "de"
    ],
    "wof:name":"B.c. Pitbulls",
    "wof:placetype":"venue"
},
  "geometry": {"coordinates":[3.4249908924,50.8902816772],"type":"Point"}
}