{
  "type": "Feature",
  "properties": {
    "iso:country":"BE",
    "sg:address":"Avenue Joseph Wauters 8",
    "sg:city":"Colfontaine (p\u00e2turages)",
    "sg:classifiers":[
        {
            "category":"Personal",
            "subcategory":"Beauty Salon",
            "type":"Services"
        }
    ],
    "sg:phone":"+32 65 66 82 59",
    "sg:postcode":"7340",
    "sg:province":"Hainaut",
    "sg:tags":[
        "lady",
        "-",
        "hairdressing"
    ],
    "wof:name":"Maria Coiffure",
    "wof:placetype":"venue"
},
  "geometry": {"coordinates":[3.8574750423,50.4018630981],"type":"Point"}
}