{
  "type": "Feature",
  "properties": {
    "addr:full":"Steenweg Op Heindonk 9 Mechelen Antwerpen 2801",
    "addr:housenumber":"9",
    "addr:postcode":"2801",
    "addr:street":"Steenweg Op Heindonk",
    "iso:country":"BE",
    "sg:address":"Steenweg Op Heindonk 9",
    "sg:city":"Mechelen",
    "sg:orig_category":"Slagers",
    "sg:phone":"+32 15 21 89 80",
    "sg:postcode":"2801",
    "sg:province":"Antwerpen",
    "wof:name":"Elvira Switsers",
    "wof:placetype":"venue"
},
  "geometry": {"coordinates":[4.4223451614,51.0472068787],"type":"Point"}
}