{
  "type": "Feature",
  "properties": {
    "iso:country":"BE",
    "sg:address":"Avenue Du Chemin De Fer 59",
    "sg:city":"Zinnik",
    "sg:orig_category":"Rev\u00eatements de sols and murs",
    "sg:phone":"+32 67 34 03 08",
    "sg:postcode":"7062",
    "sg:province":"Hainaut",
    "wof:name":"Distripierres P\u00c2ques Et Cie",
    "wof:placetype":"venue"
},
  "geometry": {"coordinates":[4.0996851921,50.5541000366],"type":"Point"}
}