{
  "type": "Feature",
  "properties": {
    "addr:full":"Mechelsesteenweg 87 Kampenhout Vlaams-Brabant 1910",
    "addr:housenumber":"87",
    "addr:postcode":"1910",
    "addr:street":"Mechelsesteenweg",
    "iso:country":"BE",
    "sg:address":"Mechelsesteenweg 87",
    "sg:city":"Kampenhout",
    "sg:classifiers":[
        {
            "category":"Banks & Credit Unions",
            "subcategory":"Investment Brokerage",
            "type":"Services"
        }
    ],
    "sg:phone":"+32 16 60 72 60",
    "sg:postcode":"1910",
    "sg:province":"Vlaams-Brabant",
    "sg:tags":[
        "distributor",
        "-",
        "distributors",
        "physical"
    ],
    "wof:name":"Hessenatie Logistics Nv",
    "wof:placetype":"venue"
},
  "geometry": {"coordinates":[4.5843667984,50.9611282349],"type":"Point"}
}