{
  "type": "Feature",
  "properties": {
    "addr:full":"Jan De Voslei 31b6 Antwerpen Antwerpen 2020",
    "addr:housenumber":"31b6",
    "addr:postcode":"2020",
    "addr:street":"Jan De Voslei",
    "iso:country":"BE",
    "sg:address":"Jan De Voslei 31b6",
    "sg:city":"Antwerpen",
    "sg:classifiers":[
        {
            "category":"Insurance",
            "subcategory":"Life Insurance",
            "type":"Services"
        }
    ],
    "sg:phone":"+32 3 237 63 01",
    "sg:postcode":"2020",
    "sg:province":"Antwerpen",
    "sg:tags":[
        "assurance"
    ],
    "wof:name":"Assemper",
    "wof:placetype":"venue"
},
  "geometry": {"coordinates":[4.3885569572,51.1893119812],"type":"Point"}
}