{
  "type": "Feature",
  "properties": {
    "iso:country":"BE",
    "sg:address":"Torenstraat 5",
    "sg:city":"Rotselaar",
    "sg:classifiers":[
        {
            "category":"Retail",
            "subcategory":"Auto Repair",
            "type":"Services"
        }
    ],
    "sg:phone":"+32 16 44 31 02",
    "sg:postcode":"3110",
    "sg:province":"Vlaams-Brabant",
    "sg:tags":[
        "automobile-body"
    ],
    "wof:name":"Vanderborght Bvba",
    "wof:placetype":"venue"
},
  "geometry": {"coordinates":[4.7121691704,50.9508934021],"type":"Point"}
}