{
  "type": "Feature",
  "properties": {
    "iso:country":"BE",
    "sg:address":"Gentsesteenweg 1026",
    "sg:city":"Brussel",
    "sg:orig_category":"Finished goods - metallic Health - equipments and instruments Metallurgy and Metalworking Precision ",
    "sg:phone":"+32 2 465 69 10",
    "sg:postcode":"1082",
    "sg:province":"Bruxelles-Capitale",
    "wof:name":"De Clerck Sa",
    "wof:placetype":"venue"
},
  "geometry": {"coordinates":[4.3038930893,50.8610420227],"type":"Point"}
}