{
  "type": "Feature",
  "properties": {
    "addr:full":"Sleutelbloemlaan 11 Zaventem Vlaams-Brabant 1933",
    "addr:housenumber":"11",
    "addr:postcode":"1933",
    "addr:street":"Sleutelbloemlaan",
    "iso:country":"BE",
    "sg:address":"Sleutelbloemlaan 11",
    "sg:city":"Zaventem",
    "sg:orig_category":"Medische apparatuur, orthopedische artikelen and prothesen Fab",
    "sg:phone":"+32 2 731 70 37",
    "sg:postcode":"1933",
    "sg:province":"Vlaams-Brabant",
    "wof:name":"Henri Pappaert",
    "wof:placetype":"venue"
},
  "geometry": {"coordinates":[4.4965910912,50.8590011597],"type":"Point"}
}