{
  "type": "Feature",
  "properties": {
    "addr:full":"Rue De La Croix 7 Lens Hainaut 7870",
    "addr:housenumber":"7",
    "addr:postcode":"7870",
    "addr:street":"Rue De La Croix",
    "iso:country":"BE",
    "sg:address":"Rue De La Croix 7",
    "sg:city":"Lens",
    "sg:orig_category":"Alimentation sp\u00e9cialis\u00e9e",
    "sg:phone":"+32 68 65 75 67",
    "sg:postcode":"7870",
    "sg:province":"Hainaut",
    "wof:name":"Traiteur Damien Boulet",
    "wof:placetype":"venue"
},
  "geometry": {"coordinates":[3.8563098907,50.5701026917],"type":"Point"}
}