{
  "type": "Feature",
  "properties": {
    "iso:country":"BE",
    "sg:address":"Oudenaardebaan 8",
    "sg:city":"Kluisbergen",
    "sg:orig_category":"Installatie van houten of kunststof schrijnwerk",
    "sg:phone":"+32 55 38 56 65",
    "sg:postcode":"9690",
    "sg:province":"Oost-Vlaanderen",
    "wof:name":"Dominique De Meester",
    "wof:placetype":"venue"
},
  "geometry": {"coordinates":[3.5176010132,50.7943229675],"type":"Point"}
}