{
  "type": "Feature",
  "properties": {
    "addr:full":"Rue De L'institut Louis Marie 33 Walcourt (thy-le-ch\u00e2teau) Namur 5651",
    "addr:housenumber":"33",
    "addr:postcode":"5651",
    "addr:street":"Rue De L'Institut Louis Marie",
    "iso:country":"BE",
    "sg:address":"Rue De L'institut Louis Marie 33",
    "sg:city":"Walcourt (thy-le-ch\u00e2teau)",
    "sg:classifiers":[
        {
            "category":"Social Services",
            "subcategory":"Child Care",
            "type":"Services"
        }
    ],
    "sg:phone":"+32 71 61 18 17",
    "sg:postcode":"5651",
    "sg:province":"Namur",
    "sg:tags":[
        "home"
    ],
    "wof:name":"Louis Marie Institut",
    "wof:placetype":"venue"
},
  "geometry": {"coordinates":[4.4273400307,50.2856216431],"type":"Point"}
}