{
  "type": "Feature",
  "properties": {
    "iso:country":"BE",
    "sg:address":"Onderbergen 1",
    "sg:city":"Gent",
    "sg:classifiers":[
        {
            "category":"Education",
            "subcategory":"Library",
            "type":"Public Place"
        }
    ],
    "sg:phone":"+32 9 224 36 66",
    "sg:postcode":"9000",
    "sg:province":"Oost-Vlaanderen",
    "sg:tags":[
        "medium"
    ],
    "wof:name":"Agentschap Belga",
    "wof:placetype":"venue"
},
  "geometry": {"coordinates":[3.7198979855,51.0530891418],"type":"Point"}
}