{
  "type": "Feature",
  "properties": {
    "iso:country":"BE",
    "sg:address":"Boomgaardstraat 29",
    "sg:city":"Kalmthout",
    "sg:classifiers":[
        {
            "category":"Personal",
            "subcategory":"Beauty Salon",
            "type":"Services"
        }
    ],
    "sg:phone":"+32 3 677 09 89",
    "sg:postcode":"2920",
    "sg:province":"Antwerpen",
    "sg:tags":[
        "lady",
        "-",
        "hairdressing"
    ],
    "wof:name":"Vicky",
    "wof:placetype":"venue"
},
  "geometry": {"coordinates":[4.5207500458,51.4365501404],"type":"Point"}
}