{
  "type": "Feature",
  "properties": {
    "addr:full":"Rue De La Station 3 Hamoir Li\u00e8ge 4180",
    "addr:housenumber":"3",
    "addr:postcode":"4180",
    "addr:street":"Rue De La Station",
    "iso:country":"BE",
    "sg:address":"Rue De La Station 3",
    "sg:city":"Hamoir",
    "sg:classifiers":[
        {
            "category":"Health Services",
            "subcategory":"Dentist",
            "type":"Services"
        }
    ],
    "sg:phone":"+32 86 38 90 30",
    "sg:postcode":"4180",
    "sg:province":"Li\u00e8ge",
    "wof:name":"Marechal V",
    "wof:placetype":"venue"
},
  "geometry": {"coordinates":[5.5335488319,50.4270172119],"type":"Point"}
}