{
  "type": "Feature",
  "properties": {
    "iso:country":"BE",
    "sg:address":"Sinte Apoloniastraat 7",
    "sg:city":"Aalst",
    "sg:classifiers":[
        {
            "category":"Insurance",
            "subcategory":"Insurance Agent",
            "type":"Services"
        }
    ],
    "sg:phone":"+32 53 77 67 50",
    "sg:postcode":"9300",
    "sg:province":"Oost-Vlaanderen",
    "sg:tags":[
        "broker"
    ],
    "wof:name":"Cis R",
    "wof:placetype":"venue"
},
  "geometry": {"coordinates":[4.0029840469,50.9420814514],"type":"Point"}
}