{
  "type": "Feature",
  "properties": {
    "addr:full":"Borgersstraat 10 Lummen Limburg 3560",
    "addr:housenumber":"10",
    "addr:postcode":"3560",
    "addr:street":"Borgersstraat",
    "iso:country":"BE",
    "sg:address":"Borgersstraat 10",
    "sg:city":"Lummen",
    "sg:orig_category":"Installatie van houten of kunststof schrijnwerk",
    "sg:phone":"+32 13 33 36 13",
    "sg:postcode":"3560",
    "sg:province":"Limburg",
    "wof:name":"Vandereycken J.",
    "wof:placetype":"venue"
},
  "geometry": {"coordinates":[5.1236658096,51.0110092163],"type":"Point"}
}