{
  "type": "Feature",
  "properties": {
    "iso:country":"BE",
    "sg:address":"Noordlaan 21",
    "sg:city":"Dendermonde",
    "sg:orig_category":"Verplichte sociale verzekeringen",
    "sg:phone":"+32 52 20 00 30",
    "sg:postcode":"9200",
    "sg:province":"Oost-Vlaanderen",
    "wof:name":"Bond Moyson",
    "wof:placetype":"venue"
},
  "geometry": {"coordinates":[4.1011018753,51.0330352783],"type":"Point"}
}