{
  "type": "Feature",
  "properties": {
    "addr:full":"Rue De La Lib\u00c9ration 9 Braine-le-chateau Brabant Wallon 1440",
    "addr:housenumber":"9",
    "addr:postcode":"1440",
    "addr:street":"Rue De La Libe\u0301Ration;Brabant Wallon",
    "iso:country":"BE",
    "sg:address":"Rue De La Lib\u00c9ration 9",
    "sg:city":"Braine-le-chateau",
    "sg:classifiers":[
        {
            "category":"Health Services",
            "subcategory":"Nursing And Care Facility",
            "type":"Services"
        }
    ],
    "sg:phone":"+32 2 366 90 93",
    "sg:postcode":"1440",
    "sg:province":"Brabant Wallon",
    "sg:tags":[
        "public"
    ],
    "wof:name":"Administration Communale",
    "wof:placetype":"venue"
},
  "geometry": {"coordinates":[4.2693338394,50.6824684143],"type":"Point"}
}