{
  "type": "Feature",
  "properties": {
    "addr:full":"Rue Nestor Martin 315 Bruxelles (berchem-sainte-agathe) Bruxelles-Capitale 1082",
    "addr:housenumber":"315",
    "addr:postcode":"1082",
    "addr:street":"Rue Nestor Martin",
    "iso:country":"BE",
    "sg:address":"Rue Nestor Martin 315",
    "sg:city":"Bruxelles (berchem-sainte-agathe)",
    "sg:classifiers":[
        {
            "category":"Parking",
            "subcategory":"Lot",
            "type":"Transportation"
        }
    ],
    "sg:phone":"+32 2 482 07 40",
    "sg:postcode":"1082",
    "sg:province":"Bruxelles-Capitale",
    "sg:tags":[
        "parking-places",
        "laying-out"
    ],
    "wof:name":"Wegebo Nv",
    "wof:placetype":"venue"
},
  "geometry": {"coordinates":[4.2957210541,50.873085022],"type":"Point"}
}