{
  "type": "Feature",
  "properties": {
    "iso:country":"BE",
    "sg:address":"Avenue Du Grand Jardin 13a",
    "sg:city":"Courcelles (trazegnies)",
    "sg:classifiers":[
        {
            "category":"Parking",
            "subcategory":"Bicycle",
            "type":"Transportation"
        }
    ],
    "sg:phone":"+32 71 45 64 88",
    "sg:postcode":"6183",
    "sg:province":"Hainaut",
    "sg:tags":[
        "chiropodist"
    ],
    "wof:name":"Chapelle M",
    "wof:placetype":"venue"
},
  "geometry": {"coordinates":[4.3325839043,50.4599380493],"type":"Point"}
}