{
  "type": "Feature",
  "properties": {
    "addr:full":"Rue De Mons 25b Charleroi Hainaut 6000",
    "addr:housenumber":"25b",
    "addr:postcode":"6000",
    "addr:street":"Rue De Mons;Hainaut",
    "iso:country":"BE",
    "sg:address":"Rue De Mons 25b",
    "sg:city":"Charleroi",
    "sg:classifiers":[
        {
            "category":"Insurance",
            "subcategory":"Insurance Agent",
            "type":"Services"
        }
    ],
    "sg:phone":"+32 71 30 46 37",
    "sg:postcode":"6000",
    "sg:province":"Hainaut",
    "sg:tags":[
        "broker"
    ],
    "wof:name":"Segers D",
    "wof:placetype":"venue"
},
  "geometry": {"coordinates":[4.4352698326,50.4122581482],"type":"Point"}
}