{
  "type": "Feature",
  "properties": {
    "iso:country":"BE",
    "sg:address":"Willem Geetsstraat 9",
    "sg:city":"Mechelen",
    "sg:orig_category":"Advocaten and juridische adviseurs",
    "sg:phone":"+32 15 41 86 66",
    "sg:postcode":"2800",
    "sg:province":"Antwerpen",
    "wof:name":"Inge Verhulst",
    "wof:placetype":"venue"
},
  "geometry": {"coordinates":[4.4793047905,51.0187568665],"type":"Point"}
}