{
  "type": "Feature",
  "properties": {
    "iso:country":"BE",
    "sg:address":"Rue De La Station 148",
    "sg:city":"Jemeppe-sur-sambre",
    "sg:orig_category":"Avocats and conseillers juridiques",
    "sg:phone":"+32 71 78 84 80",
    "sg:postcode":"5190",
    "sg:province":"Namur",
    "wof:name":"Daniel Dartois",
    "wof:placetype":"venue"
},
  "geometry": {"coordinates":[4.6949481964,50.45495224],"type":"Point"}
}