{
  "type": "Feature",
  "properties": {
    "iso:country":"BE",
    "sg:address":"Rue Des Francais 373bte 13",
    "sg:city":"Ans",
    "sg:classifiers":[
        {
            "category":"Wholesale",
            "subcategory":"Furniture",
            "type":"Manufacturing & Wholesale Goods"
        }
    ],
    "sg:phone":"+32 4 246 13 02",
    "sg:postcode":"4430",
    "sg:province":"Li\u00e8ge",
    "sg:tags":[
        "school"
    ],
    "wof:name":"Gai Savoir (le) S.a.",
    "wof:placetype":"venue"
},
  "geometry": {"coordinates":[5.5381097794,50.6659011841],"type":"Point"}
}