{
  "type": "Feature",
  "properties": {
    "addr:full":"Begijnhof 5a Arendonk Antwerpen 2370",
    "addr:housenumber":"5a",
    "addr:postcode":"2370",
    "addr:street":"Begijnhof",
    "iso:country":"BE",
    "sg:address":"Begijnhof 5a",
    "sg:city":"Arendonk",
    "sg:classifiers":[
        {
            "category":"Health Services",
            "subcategory":"Health Practitioner",
            "type":"Services"
        }
    ],
    "sg:phone":"+32 14 67 82 82",
    "sg:postcode":"2370",
    "sg:province":"Antwerpen",
    "sg:tags":[
        "physiotherapist"
    ],
    "wof:name":"Cantryn G",
    "wof:placetype":"venue"
},
  "geometry": {"coordinates":[5.0914759636,51.3222923279],"type":"Point"}
}