{
  "type": "Feature",
  "properties": {
    "addr:full":"Fochelstraat 6 Lebbeke Oost-Vlaanderen 9280",
    "addr:housenumber":"6",
    "addr:postcode":"9280",
    "addr:street":"Fochelstraat",
    "iso:country":"BE",
    "sg:address":"Fochelstraat 6",
    "sg:city":"Lebbeke",
    "sg:classifiers":[
        {
            "category":"Utilities",
            "subcategory":"Natural Gas",
            "type":"Services"
        }
    ],
    "sg:phone":"+32 52 35 81 45",
    "sg:postcode":"9280",
    "sg:province":"Oost-Vlaanderen",
    "sg:tags":[
        "blacksmith"
    ],
    "wof:name":"Cooremans R",
    "wof:placetype":"venue"
},
  "geometry": {"coordinates":[4.1472420692,50.9887123108],"type":"Point"}
}