{
  "type": "Feature",
  "properties": {
    "addr:full":"Rue Paul Pastur 2 Box 9 Charleroi (gosselies) Hainaut 6041",
    "addr:housenumber":"2;9",
    "addr:postcode":"6041",
    "addr:street":"Rue Paul Pastur;Box",
    "iso:country":"BE",
    "sg:address":"Rue Paul Pastur 2 Box 9",
    "sg:city":"Charleroi (gosselies)",
    "sg:classifiers":[
        {
            "category":"Health Services",
            "subcategory":"Health Practitioner",
            "type":"Services"
        }
    ],
    "sg:phone":"+32 71 35 40 79",
    "sg:postcode":"6041",
    "sg:province":"Hainaut",
    "sg:tags":[
        "physiotherapist"
    ],
    "wof:name":"Mascart Albert",
    "wof:placetype":"venue"
},
  "geometry": {"coordinates":[4.4636101723,50.3808135986],"type":"Point"}
}