{
  "type": "Feature",
  "properties": {
    "iso:country":"BE",
    "sg:address":"Botermijnstraat 2",
    "sg:city":"Beringen",
    "sg:orig_category":"Avocats and conseillers juridiques",
    "sg:phone":"+32 11 45 10 67",
    "sg:postcode":"3580",
    "sg:province":"Limburg",
    "wof:name":"C. Cox",
    "wof:placetype":"venue"
},
  "geometry": {"coordinates":[5.2225980759,51.0486602783],"type":"Point"}
}