{
  "type": "Feature",
  "properties": {
    "iso:country":"BE",
    "sg:address":"Entrepotstraat 35",
    "sg:city":"Sint-niklaas",
    "sg:classifiers":[
        {
            "category":"Shopping",
            "type":"Retail Goods"
        }
    ],
    "sg:phone":"+32 3 780 54 54",
    "sg:postcode":"9100",
    "sg:province":"Oost-Vlaanderen",
    "sg:tags":[
        "product",
        "cleaning",
        "maintenance"
    ],
    "wof:name":"Valma Bv",
    "wof:placetype":"venue"
},
  "geometry": {"coordinates":[4.1672339439,51.174987793],"type":"Point"}
}