{
  "type": "Feature",
  "properties": {
    "iso:country":"BE",
    "sg:address":"Steenveldlaan 65",
    "sg:city":"Denderleeuw",
    "sg:orig_category":"M\u00e9decins and sp\u00e9cialistes",
    "sg:phone":"+32 53 66 92 44",
    "sg:postcode":"9470",
    "sg:province":"Oost-Vlaanderen",
    "wof:name":"Marc De Vuyst",
    "wof:placetype":"venue"
},
  "geometry": {"coordinates":[4.0516119003,50.8910713196],"type":"Point"}
}