{
  "type": "Feature",
  "properties": {
    "addr:full":"Donklaan 241 Berlare (overmere) Oost-Vlaanderen 9290",
    "addr:housenumber":"241",
    "addr:postcode":"9290",
    "addr:street":"Donklaan",
    "iso:country":"BE",
    "sg:address":"Donklaan 241",
    "sg:city":"Berlare (overmere)",
    "sg:classifiers":[
        {
            "category":"Sports & Exercise",
            "subcategory":"Gym",
            "type":"Entertainment"
        }
    ],
    "sg:phone":"+32 9 367 00 05",
    "sg:postcode":"9290",
    "sg:province":"Oost-Vlaanderen",
    "sg:tags":[
        "fitness"
    ],
    "wof:name":"Topform Gym",
    "wof:placetype":"venue"
},
  "geometry": {"coordinates":[3.9795000553,51.0246582031],"type":"Point"}
}