{
  "type": "Feature",
  "properties": {
    "addr:full":"Lesbroussartstraat 96 Elsene/ixelles Bruxelles-Capitale 1050",
    "addr:housenumber":"96",
    "addr:postcode":"1050",
    "addr:street":"Lesbroussartstraat",
    "iso:country":"BE",
    "sg:address":"Lesbroussartstraat 96",
    "sg:city":"Elsene/ixelles",
    "sg:orig_category":"Plaatsen van vloer- and muurbekleding Schilders Verlichting and huishoudartikelen",
    "sg:phone":"+32 2 648 84 98",
    "sg:postcode":"1050",
    "sg:province":"Bruxelles-Capitale",
    "wof:name":"Marie-louise Lannoy",
    "wof:placetype":"venue"
},
  "geometry": {"coordinates":[4.3666028976,50.8275299072],"type":"Point"}
}