{
  "type": "Feature",
  "properties": {
    "addr:full":"Zerkingen 20 Sint-truiden Limburg 3800",
    "addr:housenumber":"20",
    "addr:postcode":"3800",
    "addr:street":"Zerkingen",
    "iso:country":"BE",
    "sg:address":"Zerkingen 20",
    "sg:city":"Sint-truiden",
    "sg:orig_category":"DIVERSE RECREATIEVE ACTIVITEITEN",
    "sg:phone":"+32 11 68 77 02",
    "sg:postcode":"3800",
    "sg:province":"Limburg",
    "wof:name":"B.c. Sint-truiden",
    "wof:placetype":"venue"
},
  "geometry": {"coordinates":[5.1789360046,50.810092926],"type":"Point"}
}