{
  "type": "Feature",
  "properties": {
    "iso:country":"BE",
    "sg:address":"Kanaalweg 58",
    "sg:city":"Tessenderlo",
    "sg:classifiers":[
        {
            "category":"Banks & Credit Unions",
            "subcategory":"Bureau De Change",
            "type":"Services"
        }
    ],
    "sg:phone":"+32 13 66 35 11",
    "sg:postcode":"3980",
    "sg:province":"Limburg",
    "sg:tags":[
        "tank",
        "cleaning"
    ],
    "wof:name":"Tessenderlo Cleaning Center Nv",
    "wof:placetype":"venue"
},
  "geometry": {"coordinates":[5.1566419601,51.0753059387],"type":"Point"}
}