{
  "type": "Feature",
  "properties": {
    "iso:country":"BE",
    "sg:address":"Ninovestraat 5",
    "sg:city":"Ronse/renaix",
    "sg:classifiers":[
        {
            "category":"Cafe",
            "type":"Food & Drink"
        }
    ],
    "sg:phone":"+32 55 21 00 39",
    "sg:postcode":"9600",
    "sg:province":"Oost-Vlaanderen",
    "sg:tags":[
        "caf\u00e9s"
    ],
    "wof:name":"Taverne Park Side",
    "wof:placetype":"venue"
},
  "geometry": {"coordinates":[3.6046040058,50.7498054504],"type":"Point"}
}