{
  "type": "Feature",
  "properties": {
    "iso:country":"BE",
    "sg:address":"Kraanberg 12",
    "sg:city":"Peer",
    "sg:orig_category":"Sportclubs",
    "sg:phone":"+32 11 63 17 21",
    "sg:postcode":"3990",
    "sg:province":"Limburg",
    "wof:name":"W.s.v. De Anjertrippers",
    "wof:placetype":"venue"
},
  "geometry": {"coordinates":[5.4604649544,51.1262359619],"type":"Point"}
}