{
  "type": "Feature",
  "properties": {
    "addr:full":"Lerenveld 26 Lint Antwerpen 2547",
    "addr:housenumber":"26",
    "addr:postcode":"2547",
    "addr:street":"Lerenveld",
    "iso:country":"BE",
    "sg:address":"Lerenveld 26",
    "sg:city":"Lint",
    "sg:classifiers":[
        {
            "category":"Retail",
            "subcategory":"Auto Repair",
            "type":"Services"
        }
    ],
    "sg:phone":"+32 3 488 53 43",
    "sg:postcode":"2547",
    "sg:province":"Antwerpen",
    "sg:tags":[
        "automobile-body"
    ],
    "wof:name":"Carrosserie Guy Cars Bvba",
    "wof:placetype":"venue"
},
  "geometry": {"coordinates":[4.5134778023,51.1276130676],"type":"Point"}
}