{
  "type": "Feature",
  "properties": {
    "addr:full":"Grande Foxhalle 160-162 Herstal Li\u00e8ge 4040",
    "addr:postcode":"160-162;4040",
    "iso:country":"BE",
    "sg:address":"Grande Foxhalle 160-162",
    "sg:city":"Herstal",
    "sg:classifiers":[
        {
            "category":"Wholesale",
            "subcategory":"Machinery & Supplies",
            "type":"Manufacturing & Wholesale Goods"
        }
    ],
    "sg:phone":"+32 4 264 04 38",
    "sg:postcode":"4040",
    "sg:province":"Li\u00e8ge",
    "sg:tags":[
        "handling",
        "material",
        "-",
        "machine",
        "equipment",
        "engineering",
        "mechanical"
    ],
    "wof:name":"Marganne Sa",
    "wof:placetype":"venue"
},
  "geometry": {"coordinates":[5.6192851067,50.6643371582],"type":"Point"}
}