{
  "type": "Feature",
  "properties": {
    "addr:full":"Handelsstraat 17 Londerzeel (malderen) Vlaams-Brabant 1840",
    "addr:housenumber":"17",
    "addr:postcode":"1840",
    "addr:street":"Handelsstraat",
    "iso:country":"BE",
    "sg:address":"Handelsstraat 17",
    "sg:city":"Londerzeel (malderen)",
    "sg:classifiers":[
        {
            "category":"Personal",
            "subcategory":"Beauty Salon",
            "type":"Services"
        }
    ],
    "sg:phone":"+32 52 33 59 17",
    "sg:postcode":"1840",
    "sg:province":"Vlaams-Brabant",
    "wof:name":"Friedl",
    "wof:placetype":"venue"
},
  "geometry": {"coordinates":[4.2372589111,51.0150756836],"type":"Point"}
}