{
  "type": "Feature",
  "properties": {
    "addr:full":"Sint-denijsstraat 117 Vorst/forest Bruxelles-Capitale 1190",
    "addr:housenumber":"117",
    "addr:postcode":"1190",
    "addr:street":"Sint-Denijsstraat;/ Forest",
    "iso:country":"BE",
    "sg:address":"Sint-denijsstraat 117",
    "sg:city":"Vorst/forest",
    "sg:orig_category":"Autoverhuur",
    "sg:phone":"+32 2 348 92 20",
    "sg:postcode":"1190",
    "sg:province":"Bruxelles-Capitale",
    "wof:name":"Europcar",
    "wof:placetype":"venue"
},
  "geometry": {"coordinates":[4.3189740181,50.8148880005],"type":"Point"}
}