{
  "type": "Feature",
  "properties": {
    "addr:full":"Rue De La Clinique 70 Anderlecht/anderlecht Bruxelles-Capitale 1070",
    "addr:housenumber":"70",
    "addr:postcode":"1070",
    "addr:street":"Rue De La Clinique",
    "iso:country":"BE",
    "sg:address":"Rue De La Clinique 70",
    "sg:city":"Anderlecht/anderlecht",
    "sg:orig_category":"Maroquinerie Fab",
    "sg:phone":"+32 2 521 02 24",
    "sg:postcode":"1070",
    "sg:province":"Bruxelles-Capitale",
    "wof:name":"Sellerie De Brie",
    "wof:placetype":"venue"
},
  "geometry": {"coordinates":[4.3319988251,50.8404541016],"type":"Point"}
}