{
  "type": "Feature",
  "properties": {
    "addr:full":"Lerenveld 2ba Lint Antwerpen 2547",
    "addr:postcode":"2ba;2547",
    "addr:street":"Lerenveld",
    "iso:country":"BE",
    "sg:address":"Lerenveld 2ba",
    "sg:city":"Lint",
    "sg:orig_category":"Traitement and rev\u00eatement des m\u00e9taux",
    "sg:phone":"+32 3 488 00 88",
    "sg:postcode":"2547",
    "sg:province":"Antwerpen",
    "wof:name":"Bacovo",
    "wof:placetype":"venue"
},
  "geometry": {"coordinates":[4.5160970688,51.1270751953],"type":"Point"}
}