{
  "type": "Feature",
  "properties": {
    "addr:full":"Tijllaan 25 Schoten Antwerpen 2900",
    "addr:housenumber":"25",
    "addr:postcode":"2900",
    "addr:street":"Tijllaan",
    "iso:country":"BE",
    "sg:address":"Tijllaan 25",
    "sg:city":"Schoten",
    "sg:orig_category":"Fotografen and fotostudio's",
    "sg:phone":"+32 3 658 01 94",
    "sg:postcode":"2900",
    "sg:province":"Antwerpen",
    "wof:name":"Studio Van Cleemput",
    "wof:placetype":"venue"
},
  "geometry": {"coordinates":[4.5140480995,51.2638778687],"type":"Point"}
}