{
  "type": "Feature",
  "properties": {
    "addr:full":"R. Van Der Weydenstraat 29b2 Edegem Antwerpen 2650",
    "addr:housenumber":"29b2",
    "addr:postcode":"2650",
    "addr:street":"R. Van Der Weydenstraat",
    "iso:country":"BE",
    "sg:address":"R. Van Der Weydenstraat 29b2",
    "sg:city":"Edegem",
    "sg:orig_category":"Plaatsen van vloer- and muurbekleding Schilders",
    "sg:phone":"+32 3 448 08 92",
    "sg:postcode":"2650",
    "sg:province":"Antwerpen",
    "wof:name":"Fa. Pentura",
    "wof:placetype":"venue"
},
  "geometry": {"coordinates":[4.438680172,51.1676292419],"type":"Point"}
}