{
  "type": "Feature",
  "properties": {
    "iso:country":"BE",
    "sg:address":"Rue De La T\u00eate D'or 7",
    "sg:city":"Tournai",
    "sg:classifiers":[
        {
            "category":"Retail",
            "subcategory":"Animal Services",
            "type":"Services"
        }
    ],
    "sg:phone":"+32 69 84 08 27",
    "sg:postcode":"7500",
    "sg:province":"Hainaut",
    "sg:tags":[
        "grooming",
        "-",
        "dog"
    ],
    "wof:name":"Academie (l')",
    "wof:placetype":"venue"
},
  "geometry": {"coordinates":[3.3932800293,50.5892715454],"type":"Point"}
}