{
  "type": "Feature",
  "properties": {
    "iso:country":"BE",
    "sg:address":"Rue De Fosses 17",
    "sg:city":"Jemeppe-sur-sambre (ham-sur-sambre)",
    "sg:classifiers":[
        {
            "category":"Shopping",
            "subcategory":"Pets & Pet Supplies",
            "type":"Retail Goods"
        }
    ],
    "sg:phone":"+32 71 78 56 45",
    "sg:postcode":"5190",
    "sg:province":"Namur",
    "sg:tags":[
        "equipment",
        "plumber",
        "-"
    ],
    "wof:name":"Honnay Zinc Sprl",
    "wof:placetype":"venue"
},
  "geometry": {"coordinates":[4.6703448296,50.4645042419],"type":"Point"}
}