{
  "type": "Feature",
  "properties": {
    "addr:full":"Bien 28 Hamont-achel Limburg 3930",
    "addr:housenumber":"28",
    "addr:postcode":"3930",
    "addr:street":"Bien",
    "iso:country":"BE",
    "sg:address":"Bien 28",
    "sg:city":"Hamont-achel",
    "sg:orig_category":"Eleveurs de bovins",
    "sg:phone":"+32 11 64 38 84",
    "sg:postcode":"3930",
    "sg:province":"Limburg",
    "wof:name":"Mauritius Schuurmans",
    "wof:placetype":"venue"
},
  "geometry": {"coordinates":[5.4718689919,51.2516136169],"type":"Point"}
}