{
  "type": "Feature",
  "properties": {
    "addr:full":"Route De La G\u00e9ronst\u00e8re 119 Spa Li\u00e8ge 4900",
    "addr:housenumber":"119",
    "addr:postcode":"4900",
    "addr:street":"Route De La Ge\u0301Ronste\u0300Re",
    "iso:country":"BE",
    "sg:address":"Route De La G\u00e9ronst\u00e8re 119",
    "sg:city":"Spa",
    "sg:classifiers":[
        {
            "category":"Travel",
            "subcategory":"Hotels & Motels",
            "type":"Entertainment"
        }
    ],
    "sg:phone":"+32 87 77 03 72",
    "sg:postcode":"4900",
    "sg:province":"Li\u00e8ge",
    "wof:name":"Source De La G\u00e9ronst\u00e8re (la)",
    "wof:placetype":"venue"
},
  "geometry": {"coordinates":[5.8733201027,50.4767494202],"type":"Point"}
}