{
  "type": "Feature",
  "properties": {
    "addr:full":"Rue Albert Bernard 12 Gerpinnes Hainaut 6280",
    "addr:housenumber":"12",
    "addr:postcode":"6280",
    "addr:street":"Rue Albert Bernard;Hainaut",
    "iso:country":"BE",
    "sg:address":"Rue Albert Bernard 12",
    "sg:city":"Gerpinnes",
    "sg:classifiers":[
        {
            "category":"Professional",
            "subcategory":"Secretarial Services",
            "type":"Services"
        }
    ],
    "sg:phone":"+32 71 50 52 77",
    "sg:postcode":"6280",
    "sg:province":"Hainaut",
    "sg:tags":[
        "firm"
    ],
    "wof:name":"Type Perfect",
    "wof:placetype":"venue"
},
  "geometry": {"coordinates":[4.5265479088,50.3370437622],"type":"Point"}
}