{
  "type": "Feature",
  "properties": {
    "addr:full":"Veldstraat 58 Lochristi Oost-Vlaanderen 9080",
    "addr:housenumber":"58",
    "addr:postcode":"9080",
    "addr:street":"Veldstraat",
    "iso:country":"BE",
    "sg:address":"Veldstraat 58",
    "sg:city":"Lochristi",
    "sg:orig_category":"Diensten voor huisdieren Huisdieren and benodigdheden Royal Canin",
    "sg:phone":"+32 9 355 84 24",
    "sg:postcode":"9080",
    "sg:province":"Oost-Vlaanderen",
    "wof:name":"Watteeuw",
    "wof:placetype":"venue"
},
  "geometry": {"coordinates":[3.7979779243,51.1022644043],"type":"Point"}
}