{
  "type": "Feature",
  "properties": {
    "addr:full":"Heesdijk 10 Ravels Antwerpen 2382",
    "addr:housenumber":"10",
    "addr:postcode":"2382",
    "addr:street":"Heesdijk",
    "iso:country":"BE",
    "sg:address":"Heesdijk 10",
    "sg:city":"Ravels",
    "sg:orig_category":"Diverse bouwinstallaties Verlichtingsapparaten and elektrische lampen Fab",
    "sg:phone":"+32 14 65 00 66",
    "sg:postcode":"2382",
    "sg:province":"Antwerpen",
    "wof:name":"Glaifa Neon",
    "wof:placetype":"venue"
},
  "geometry": {"coordinates":[5.0324120522,51.4339675903],"type":"Point"}
}