{
  "type": "Feature",
  "properties": {
    "iso:country":"BE",
    "sg:address":"Lampernisbeekstraat 4",
    "sg:city":"Lendelede",
    "sg:orig_category":"Producteurs de l\u00e9gumes",
    "sg:phone":"+32 51 30 44 55",
    "sg:postcode":"8860",
    "sg:province":"West-Vlaanderen",
    "wof:name":"Monsere Gebroeders",
    "wof:placetype":"venue"
},
  "geometry": {"coordinates":[3.2678220272,50.8881721497],"type":"Point"}
}