{
  "type": "Feature",
  "properties": {
    "addr:full":"Dennenstraat 29 Genk (waterschei) Limburg 3600",
    "addr:housenumber":"29",
    "addr:postcode":"3600",
    "addr:street":"Dennenstraat",
    "iso:country":"BE",
    "sg:address":"Dennenstraat 29",
    "sg:city":"Genk (waterschei)",
    "sg:classifiers":[
        {
            "category":"Health Services",
            "subcategory":"Health Practitioner",
            "type":"Services"
        }
    ],
    "sg:phone":"+32 89 35 09 61",
    "sg:postcode":"3600",
    "sg:province":"Limburg",
    "sg:tags":[
        "physiotherapist"
    ],
    "wof:name":"Stragier Greta",
    "wof:placetype":"venue"
},
  "geometry": {"coordinates":[5.5241260529,50.9971351624],"type":"Point"}
}