{
  "type": "Feature",
  "properties": {
    "iso:country":"BE",
    "sg:address":"Rue De La Roche 9",
    "sg:city":"Mons",
    "sg:orig_category":"Boissons",
    "sg:phone":"+32 65 58 74 12",
    "sg:postcode":"7022",
    "sg:province":"Hainaut",
    "wof:name":"Crus & Sauveurs Languedoc",
    "wof:placetype":"venue"
},
  "geometry": {"coordinates":[3.9901769161,50.3930435181],"type":"Point"}
}