{
  "type": "Feature",
  "properties": {
    "iso:country":"BE",
    "sg:address":"Genthof 18",
    "sg:city":"Brugge",
    "sg:classifiers":[
        {
            "category":"Personal",
            "subcategory":"Beauty Salon",
            "type":"Services"
        }
    ],
    "sg:phone":"+32 50 33 08 13",
    "sg:postcode":"8000",
    "sg:province":"West-Vlaanderen",
    "sg:tags":[
        "de",
        "coiffure"
    ],
    "wof:name":"A. Kerckhove",
    "wof:placetype":"venue"
},
  "geometry": {"coordinates":[3.2269690037,51.2124137878],"type":"Point"}
}