{
  "type": "Feature",
  "properties": {
    "addr:full":"Visserskaai 35 Oostende West-Vlaanderen 8400",
    "addr:housenumber":"35",
    "addr:postcode":"8400",
    "addr:street":"Visserskaai",
    "iso:country":"BE",
    "sg:address":"Visserskaai 35",
    "sg:city":"Oostende",
    "sg:classifiers":[
        {
            "category":"Restaurant",
            "type":"Food & Drink"
        }
    ],
    "sg:phone":"+32 59 70 17 65",
    "sg:postcode":"8400",
    "sg:province":"West-Vlaanderen",
    "wof:name":"Lusitania",
    "wof:placetype":"venue"
},
  "geometry": {"coordinates":[2.9217529297,51.2333145142],"type":"Point"}
}