{
  "type": "Feature",
  "properties": {
    "addr:full":"Grand Place 0 La Louviere Hainaut 7100",
    "addr:housenumber":"0",
    "addr:postcode":"7100",
    "addr:street":"Grand Place",
    "iso:country":"BE",
    "sg:address":"Grand Place 0",
    "sg:city":"La Louviere",
    "sg:orig_category":"Biblioth\u00e8ques and archives publiques",
    "sg:phone":"+32 64 26 01 41",
    "sg:postcode":"7100",
    "sg:province":"Hainaut",
    "wof:name":"Biblioth\u00c8que Publique",
    "wof:placetype":"venue"
},
  "geometry": {"coordinates":[4.1850848198,50.4748649597],"type":"Point"}
}