{
  "type": "Feature",
  "properties": {
    "addr:full":"Lange Ambachtstraat 17 Oosterzele Oost-Vlaanderen 9860",
    "addr:housenumber":"17",
    "addr:postcode":"9860",
    "addr:street":"Lange Ambachtstraat;Oost-Vlaanderen",
    "iso:country":"BE",
    "sg:address":"Lange Ambachtstraat 17",
    "sg:city":"Oosterzele",
    "sg:classifiers":[
        {
            "category":"Retail",
            "subcategory":"Auto Repair",
            "type":"Services"
        }
    ],
    "sg:phone":"+32 9 362 81 10",
    "sg:postcode":"9860",
    "sg:province":"Oost-Vlaanderen",
    "sg:tags":[
        "garage"
    ],
    "wof:name":"Leboeuf F",
    "wof:placetype":"venue"
},
  "geometry": {"coordinates":[3.8170640469,50.9488449097],"type":"Point"}
}