{
  "type": "Feature",
  "properties": {
    "iso:country":"BE",
    "sg:address":"Zeedijk 107",
    "sg:city":"De Panne",
    "sg:classifiers":[
        {
            "category":"Tea Room",
            "subcategory":"None",
            "type":"Food & Drink"
        }
    ],
    "sg:phone":"+32 58 42 21 23",
    "sg:postcode":"8660",
    "sg:province":"West-Vlaanderen",
    "wof:name":"Miro",
    "wof:placetype":"venue"
},
  "geometry": {"coordinates":[2.5920679569,51.1002388],"type":"Point"}
}