{
  "type": "Feature",
  "properties": {
    "iso:country":"BE",
    "sg:address":"Steenvoordestraat 157",
    "sg:city":"Destelbergen",
    "sg:orig_category":"Traitements param\u00e9dicaux",
    "sg:phone":"+32 9 252 27 77",
    "sg:postcode":"9070",
    "sg:province":"Oost-Vlaanderen",
    "wof:name":"Tania Dhaenens",
    "wof:placetype":"venue"
},
  "geometry": {"coordinates":[3.8122820854,51.0157699585],"type":"Point"}
}