{
  "type": "Feature",
  "properties": {
    "iso:country":"BE",
    "sg:address":"H Horriestr 9",
    "sg:city":"Roeselare",
    "sg:classifiers":[
        {
            "category":"Banks & Credit Unions",
            "subcategory":"Bank",
            "type":"Services"
        }
    ],
    "sg:phone":"+32 51 22 88 63",
    "sg:postcode":"8800",
    "sg:province":"West-Vlaanderen",
    "wof:name":"G\u00e9n\u00e9rale De Banque Sa",
    "wof:placetype":"venue"
},
  "geometry": {"coordinates":[3.1252639294,50.9465560913],"type":"Point"}
}