{
  "type": "Feature",
  "properties": {
    "iso:country":"BE",
    "sg:address":"Keistraat 39",
    "sg:city":"Antwerpen",
    "sg:orig_category":"Activit\u00e9s diverses d'imprimerie",
    "sg:phone":"+32 3 233 55 16",
    "sg:postcode":"2000",
    "sg:province":"Antwerpen",
    "wof:name":"T. Jacobs",
    "wof:placetype":"venue"
},
  "geometry": {"coordinates":[4.4036297798,51.2249031067],"type":"Point"}
}