{
  "type": "Feature",
  "properties": {
    "addr:full":"Avenue Reine Astrid 40 La Hulpe Brabant Wallon 1310",
    "addr:housenumber":"40",
    "addr:postcode":"1310",
    "addr:street":"Avenue Reine Astrid",
    "iso:country":"BE",
    "sg:address":"Avenue Reine Astrid 40",
    "sg:city":"La Hulpe",
    "sg:orig_category":"Bouwmaterialen Gh Dakwerken",
    "sg:phone":"+32 2 653 68 16",
    "sg:postcode":"1310",
    "sg:province":"Brabant Wallon",
    "wof:name":"Marcel David",
    "wof:placetype":"venue"
},
  "geometry": {"coordinates":[4.4763979912,50.7290649414],"type":"Point"}
}