{
  "type": "Feature",
  "properties": {
    "addr:full":"Sint-paulusstraat 40 Oostende West-Vlaanderen 8400",
    "addr:housenumber":"40",
    "addr:postcode":"8400",
    "addr:street":"Sint-Paulusstraat",
    "iso:country":"BE",
    "sg:address":"Sint-paulusstraat 40",
    "sg:city":"Oostende",
    "sg:orig_category":"Paramedische behandelingen",
    "sg:phone":"+32 59 51 54 95",
    "sg:postcode":"8400",
    "sg:province":"West-Vlaanderen",
    "wof:name":"G. Maertens",
    "wof:placetype":"venue"
},
  "geometry": {"coordinates":[2.9199140072,51.2301368713],"type":"Point"}
}