{
  "type": "Feature",
  "properties": {
    "iso:country":"BE",
    "sg:address":"Burgemeester Lemmensstraat 54",
    "sg:city":"Hamme (moerzeke)",
    "sg:classifiers":[
        {
            "category":"Personal",
            "subcategory":"Massage",
            "type":"Services"
        }
    ],
    "sg:phone":"+32 52 48 13 94",
    "sg:postcode":"9220",
    "sg:province":"Oost-Vlaanderen",
    "wof:name":"Heirweg A",
    "wof:placetype":"venue"
},
  "geometry": {"coordinates":[4.1559500694,51.0663299561],"type":"Point"}
}