{
  "type": "Feature",
  "properties": {
    "iso:country":"BE",
    "sg:address":"Stationsstraat 227",
    "sg:city":"Herzele",
    "sg:orig_category":"Passagiersvervoer over de weg Reisbureaus",
    "sg:phone":"+32 53 63 00 88",
    "sg:postcode":"9550",
    "sg:province":"Oost-Vlaanderen",
    "wof:name":"Sylvae Tours",
    "wof:placetype":"venue"
},
  "geometry": {"coordinates":[3.8817009926,50.8968887329],"type":"Point"}
}