{
  "type": "Feature",
  "properties": {
    "addr:full":"Bredabaan 460 Brasschaat Antwerpen 2930",
    "addr:housenumber":"460",
    "addr:postcode":"2930",
    "addr:street":"Bredabaan",
    "iso:country":"BE",
    "sg:address":"Bredabaan 460",
    "sg:city":"Brasschaat",
    "sg:orig_category":"Artistes ind\u00e9pendants",
    "sg:phone":"+32 3 651 48 33",
    "sg:postcode":"2930",
    "sg:province":"Antwerpen",
    "wof:name":"Van Beeumen",
    "wof:placetype":"venue"
},
  "geometry": {"coordinates":[4.4971451759,51.2961044312],"type":"Point"}
}