{
  "type": "Feature",
  "properties": {
    "iso:country":"BE",
    "sg:address":"Rue Du Vert Galant 5bb",
    "sg:city":"Tournai",
    "sg:orig_category":"Eleveurs de bovins",
    "sg:phone":"+32 69 64 86 80",
    "sg:postcode":"7500",
    "sg:province":"Hainaut",
    "wof:name":"Roger Delneste",
    "wof:placetype":"venue"
},
  "geometry": {"coordinates":[3.3621621132,50.5772819519],"type":"Point"}
}