{
  "type": "Feature",
  "properties": {
    "addr:full":"Rue Des Viaducs 73a Mons Hainaut 7020",
    "addr:housenumber":"73a",
    "addr:postcode":"7020",
    "addr:street":"Rue Des Viaducs;Hainaut",
    "iso:country":"BE",
    "sg:address":"Rue Des Viaducs 73a",
    "sg:city":"Mons",
    "sg:orig_category":"Kapsalons",
    "sg:phone":"+32 65 31 12 60",
    "sg:postcode":"7020",
    "sg:province":"Hainaut",
    "wof:name":"Coiffure Chantal",
    "wof:placetype":"venue"
},
  "geometry": {"coordinates":[3.9553449154,50.4761772156],"type":"Point"}
}