{
  "type": "Feature",
  "properties": {
    "addr:full":"Rue Sainte-croix 48 Arlon Luxembourg 6700",
    "addr:housenumber":"48",
    "addr:postcode":"6700",
    "addr:street":"Rue Sainte-Croix",
    "iso:country":"BE",
    "sg:address":"Rue Sainte-croix 48",
    "sg:city":"Arlon",
    "sg:classifiers":[
        {
            "category":"Personal",
            "subcategory":"Beauty Salon",
            "type":"Services"
        }
    ],
    "sg:phone":"+32 63 21 96 18",
    "sg:postcode":"6700",
    "sg:province":"Luxembourg",
    "sg:tags":[
        "de",
        "coiffure"
    ],
    "wof:name":"Bernadette Van De Kerckhove",
    "wof:placetype":"venue"
},
  "geometry": {"coordinates":[5.8071708679,49.6893386841],"type":"Point"}
}