{
  "type": "Feature",
  "properties": {
    "iso:country":"BE",
    "sg:address":"Quai Saint-l\u00e9onard 10",
    "sg:city":"Li\u00e8ge 1",
    "sg:classifiers":[
        {
            "category":"Health Services",
            "subcategory":"Doctor",
            "type":"Services"
        }
    ],
    "sg:phone":"+32 4 227 00 51",
    "sg:postcode":"4000",
    "sg:province":"Li\u00e8ge",
    "sg:tags":[
        "medicinephysicians",
        "surgeon"
    ],
    "wof:name":"Gob Daniel",
    "wof:placetype":"venue"
},
  "geometry": {"coordinates":[5.5871968269,50.6472702026],"type":"Point"}
}