{
  "type": "Feature",
  "properties": {
    "addr:full":"Windmolenstraat 25 Sint-truiden Limburg 3800",
    "addr:housenumber":"25",
    "addr:postcode":"3800",
    "addr:street":"Windmolenstraat",
    "iso:country":"BE",
    "sg:address":"Windmolenstraat 25",
    "sg:city":"Sint-truiden",
    "sg:orig_category":"Producteurs de fruits",
    "sg:phone":"+32 11 69 16 08",
    "sg:postcode":"3800",
    "sg:province":"Limburg",
    "wof:name":"Gilbert Roosen",
    "wof:placetype":"venue"
},
  "geometry": {"coordinates":[5.2129459381,50.8048019409],"type":"Point"}
}