{
  "type": "Feature",
  "properties": {
    "addr:full":"Rue Lavalle 72 Ham-sur-heure-nalinnes (nalinnes) Hainaut 6120",
    "addr:housenumber":"72",
    "addr:postcode":"6120",
    "addr:street":"Rue Lavalle",
    "iso:country":"BE",
    "sg:address":"Rue Lavalle 72",
    "sg:city":"Ham-sur-heure-nalinnes (nalinnes)",
    "sg:classifiers":[
        {
            "category":"Retail",
            "subcategory":"Auto Repair",
            "type":"Services"
        }
    ],
    "sg:phone":"+32 71 21 75 53",
    "sg:postcode":"6120",
    "sg:province":"Hainaut",
    "sg:tags":[
        "garage"
    ],
    "wof:name":"Garage Lavalle",
    "wof:placetype":"venue"
},
  "geometry": {"coordinates":[4.4385237694,50.3176994324],"type":"Point"}
}