{
  "type": "Feature",
  "properties": {
    "addr:full":"Boulevard Du Roi Albert 114 Tournai Hainaut 7500",
    "addr:housenumber":"114",
    "addr:postcode":"7500",
    "addr:street":"Boulevard Du Roi Albert",
    "iso:country":"BE",
    "sg:address":"Boulevard Du Roi Albert 114",
    "sg:city":"Tournai",
    "sg:classifiers":[
        {
            "category":"Health Services",
            "subcategory":"Doctor",
            "type":"Services"
        }
    ],
    "sg:phone":"+32 69 84 04 64",
    "sg:postcode":"7500",
    "sg:province":"Hainaut",
    "sg:tags":[
        "medicinephysicians",
        "surgeon"
    ],
    "wof:name":"Delvoye A",
    "wof:placetype":"venue"
},
  "geometry": {"coordinates":[3.3910079002,50.6006202698],"type":"Point"}
}