{
  "type": "Feature",
  "properties": {
    "iso:country":"BE",
    "sg:address":"Rue Joseph Wauters 46",
    "sg:city":"Charleroi (couillet)",
    "sg:classifiers":[
        {
            "category":"Insurance",
            "subcategory":"Insurance Agent",
            "type":"Services"
        }
    ],
    "sg:phone":"+32 71 43 80 81",
    "sg:postcode":"6010",
    "sg:province":"Hainaut",
    "sg:tags":[
        "broker"
    ],
    "wof:name":"Euro Pr\u00eats & Finances",
    "wof:placetype":"venue"
},
  "geometry": {"coordinates":[4.4719691277,50.3851165771],"type":"Point"}
}