{
  "type": "Feature",
  "properties": {
    "iso:country":"BE",
    "sg:address":"Stalingradlaan 11",
    "sg:city":"Brussel/bruxelles",
    "sg:orig_category":"Maatschappelijke dienstverlening",
    "sg:phone":"+32 2 513 23 90",
    "sg:postcode":"1000",
    "sg:province":"Bruxelles-Capitale",
    "wof:name":"Blindenzorg Licht &liefde",
    "wof:placetype":"venue"
},
  "geometry": {"coordinates":[4.3450331688,50.8424873352],"type":"Point"}
}