{
  "type": "Feature",
  "properties": {
    "addr:full":"Heemstraat 14 Gent (wondelgem) Oost-Vlaanderen 9032",
    "addr:housenumber":"14",
    "addr:postcode":"9032",
    "addr:street":"Heemstraat",
    "iso:country":"BE",
    "sg:address":"Heemstraat 14",
    "sg:city":"Gent (wondelgem)",
    "sg:classifiers":[
        {
            "category":"Home & Garden",
            "subcategory":"Carpets & Floor Coverings",
            "type":"Retail Goods"
        }
    ],
    "sg:phone":"+32 9 253 12 10",
    "sg:postcode":"9032",
    "sg:province":"Oost-Vlaanderen",
    "sg:tags":[
        "layer",
        "mosaicists"
    ],
    "wof:name":"Dossche Jan",
    "wof:placetype":"venue"
},
  "geometry": {"coordinates":[3.7162549496,51.0900535583],"type":"Point"}
}