{
  "type": "Feature",
  "properties": {
    "addr:full":"Heikantstraat 31 Laakdal Antwerpen 2430",
    "addr:housenumber":"31",
    "addr:postcode":"2430",
    "addr:street":"Heikantstraat",
    "iso:country":"BE",
    "sg:address":"Heikantstraat 31",
    "sg:city":"Laakdal",
    "sg:orig_category":"Diensten voor huisdieren",
    "sg:phone":"+32 14 86 68 26",
    "sg:postcode":"2430",
    "sg:province":"Antwerpen",
    "wof:name":"Toilettage Sterckx",
    "wof:placetype":"venue"
},
  "geometry": {"coordinates":[5.0687851906,51.0857543945],"type":"Point"}
}