{
  "type": "Feature",
  "properties": {
    "addr:full":"Chauss\u00c9e De Dinant 15 Profondeville Namur 5170",
    "addr:housenumber":"15",
    "addr:postcode":"5170",
    "addr:street":"Chausse\u0301E De Dinant",
    "iso:country":"BE",
    "sg:address":"Chauss\u00c9e De Dinant 15",
    "sg:city":"Profondeville",
    "sg:orig_category":"Tweedehandsgoederen",
    "sg:phone":"+32 81 41 42 60",
    "sg:postcode":"5170",
    "sg:province":"Namur",
    "wof:name":"Maison L\u00b4et\u00c9 Indien",
    "wof:placetype":"venue"
},
  "geometry": {"coordinates":[4.8716101646,50.3773994446],"type":"Point"}
}