{
  "type": "Feature",
  "properties": {
    "iso:country":"BE",
    "sg:address":"Rue Amas 2",
    "sg:city":"Clavier",
    "sg:orig_category":"Eleveurs de bovins",
    "sg:phone":"+32 86 34 40 46",
    "sg:postcode":"4560",
    "sg:province":"Li\u00e8ge",
    "wof:name":"Pierre Baudoin",
    "wof:placetype":"venue"
},
  "geometry": {"coordinates":[5.4191389084,50.3988952637],"type":"Point"}
}