{
  "type": "Feature",
  "properties": {
    "iso:country":"BE",
    "sg:address":"Ooststatiestraat 147",
    "sg:city":"Kontich",
    "sg:classifiers":[
        {
            "category":"Health Services",
            "subcategory":"Health Practitioner",
            "type":"Services"
        }
    ],
    "sg:phone":"+32 3 459 80 63",
    "sg:postcode":"2550",
    "sg:province":"Antwerpen",
    "sg:tags":[
        "physiotherapist"
    ],
    "wof:name":"Smets Greet",
    "wof:placetype":"venue"
},
  "geometry": {"coordinates":[4.4547629356,51.1348190308],"type":"Point"}
}