{
  "type": "Feature",
  "properties": {
    "addr:full":"Godshuizenlaan 159 Gent Oost-Vlaanderen 9000",
    "addr:housenumber":"159",
    "addr:postcode":"9000",
    "addr:street":"Godshuizenlaan;Oost-Vlaanderen",
    "iso:country":"BE",
    "sg:address":"Godshuizenlaan 159",
    "sg:city":"Gent",
    "sg:classifiers":[
        {
            "category":"Insurance",
            "subcategory":"Insurance Agent",
            "type":"Services"
        }
    ],
    "sg:phone":"+32 9 223 23 08",
    "sg:postcode":"9000",
    "sg:province":"Oost-Vlaanderen",
    "sg:tags":[
        "broker"
    ],
    "wof:name":"Wylleman & Torfs(zakenkantoor)",
    "wof:placetype":"venue"
},
  "geometry": {"coordinates":[3.7139310837,51.0449104309],"type":"Point"}
}