{
  "type": "Feature",
  "properties": {
    "addr:full":"Oedelemsestraat 118 Oostkamp West-Vlaanderen 8020",
    "addr:housenumber":"118",
    "addr:postcode":"8020",
    "addr:street":"Oedelemsestraat",
    "iso:country":"BE",
    "sg:address":"Oedelemsestraat 118",
    "sg:city":"Oostkamp",
    "sg:orig_category":"Eleveurs de bovins",
    "sg:phone":"+32 50 82 25 07",
    "sg:postcode":"8020",
    "sg:province":"West-Vlaanderen",
    "wof:name":"Leopold Van Meenen",
    "wof:placetype":"venue"
},
  "geometry": {"coordinates":[3.2706999779,51.1583900452],"type":"Point"}
}