{
  "type": "Feature",
  "properties": {
    "iso:country":"BE",
    "sg:address":"Zandstraat 34",
    "sg:city":"Grobbendonk",
    "sg:classifiers":[
        {
            "category":"Airport",
            "subcategory":"International",
            "type":"Transportation"
        }
    ],
    "sg:phone":"+32 14 51 47 84",
    "sg:postcode":"2280",
    "sg:province":"Antwerpen",
    "sg:tags":[
        "-",
        "transport"
    ],
    "wof:name":"Jadeko Trans Bvba",
    "wof:placetype":"venue"
},
  "geometry": {"coordinates":[4.7199568748,51.1972618103],"type":"Point"}
}