{
  "type": "Feature",
  "properties": {
    "addr:full":"Wayenborgstraat 19 Mechelen Antwerpen 2800",
    "addr:housenumber":"19",
    "addr:postcode":"2800",
    "addr:street":"Wayenborgstraat",
    "iso:country":"BE",
    "sg:address":"Wayenborgstraat 19",
    "sg:city":"Mechelen",
    "sg:classifiers":[
        {
            "category":"Manufacturing",
            "subcategory":"Electronics",
            "type":"Manufacturing & Wholesale Goods"
        }
    ],
    "sg:phone":"+32 15 20 74 78",
    "sg:postcode":"2800",
    "sg:province":"Antwerpen",
    "sg:tags":[
        "oven",
        "microwave"
    ],
    "wof:name":"Daewoo Electronics Benelux",
    "wof:placetype":"venue"
},
  "geometry": {"coordinates":[4.4436440468,51.0497398376],"type":"Point"}
}