{
  "type": "Feature",
  "properties": {
    "addr:full":"Karreweg 54 Kruishoutem Oost-Vlaanderen 9770",
    "addr:housenumber":"54",
    "addr:postcode":"9770",
    "addr:street":"Karreweg",
    "iso:country":"BE",
    "sg:address":"Karreweg 54",
    "sg:city":"Kruishoutem",
    "sg:orig_category":"Catering and organisatie van feesten",
    "sg:phone":"+32 9 386 66 90",
    "sg:postcode":"9770",
    "sg:province":"Oost-Vlaanderen",
    "wof:name":"Van Thuyne",
    "wof:placetype":"venue"
},
  "geometry": {"coordinates":[3.5190489292,50.9403114319],"type":"Point"}
}