{
  "type": "Feature",
  "properties": {
    "iso:country":"BE",
    "sg:address":"Rue Village 67",
    "sg:city":"Herve (chaineux)",
    "sg:classifiers":[
        {
            "category":"Food & Beverages",
            "subcategory":"Groceries & Convenience Stores",
            "type":"Retail Goods"
        }
    ],
    "sg:phone":"+32 87 67 43 89",
    "sg:postcode":"4650",
    "sg:province":"Li\u00e8ge",
    "sg:tags":[
        "grocer"
    ],
    "wof:name":"Hac",
    "wof:placetype":"venue"
},
  "geometry": {"coordinates":[5.834400177,50.6317214966],"type":"Point"}
}