{
  "type": "Feature",
  "properties": {
    "iso:country":"BE",
    "sg:address":"Kortrijksesteenweg 1160",
    "sg:city":"Gent (sint-denijs-westrem - Afsnee)",
    "sg:classifiers":[
        {
            "category":"Organizations",
            "subcategory":"Professional Association",
            "type":"Services"
        }
    ],
    "sg:phone":"+32 9 222 88 82",
    "sg:postcode":"9051",
    "sg:province":"Oost-Vlaanderen",
    "sg:tags":[
        "trade-union",
        "federation"
    ],
    "wof:name":"Onafhankelijk Verbond Voor Zelfstandigen",
    "wof:placetype":"venue"
},
  "geometry": {"coordinates":[3.6514649391,51.0148277283],"type":"Point"}
}