{
  "type": "Feature",
  "properties": {
    "addr:full":"Gallaitstraat 86 Schaarbeek/schaerbeek Bruxelles-Capitale 1030",
    "addr:housenumber":"86",
    "addr:postcode":"1030",
    "addr:street":"Gallaitstraat",
    "iso:country":"BE",
    "sg:address":"Gallaitstraat 86",
    "sg:city":"Schaarbeek/schaerbeek",
    "sg:orig_category":"Krantenuitgeverijen Tijdschriftenuitgeverijen Zalen voor culturele evenementen",
    "sg:phone":"+32 2 215 27 08",
    "sg:postcode":"1030",
    "sg:province":"Bruxelles-Capitale",
    "wof:name":"Vlaams Centrum Volks Ontwikkeling",
    "wof:placetype":"venue"
},
  "geometry": {"coordinates":[4.3686380386,50.8668022156],"type":"Point"}
}