{
  "type": "Feature",
  "properties": {
    "addr:full":"Rue De L\u00b4institut 5 Namur Namur 5004",
    "addr:housenumber":"5",
    "addr:postcode":"5004",
    "addr:street":"Rue De L\u00b4Institut",
    "iso:country":"BE",
    "sg:address":"Rue De L\u00b4institut 5",
    "sg:city":"Namur",
    "sg:orig_category":"M\u00e9decins and sp\u00e9cialistes",
    "sg:phone":"+32 81 20 78 33",
    "sg:postcode":"5004",
    "sg:province":"Namur",
    "wof:name":"Daniel Goffin",
    "wof:placetype":"venue"
},
  "geometry": {"coordinates":[4.8855490685,50.4737701416],"type":"Point"}
}