{
  "type": "Feature",
  "properties": {
    "addr:full":"Drengel 28 Zoersel Antwerpen 2980",
    "addr:housenumber":"28",
    "addr:postcode":"2980",
    "addr:street":"Drengel",
    "iso:country":"BE",
    "sg:address":"Drengel 28",
    "sg:city":"Zoersel",
    "sg:orig_category":"Eleveurs de bovins",
    "sg:phone":"+32 3 312 36 75",
    "sg:postcode":"2980",
    "sg:province":"Antwerpen",
    "wof:name":"Jozef Meeusen",
    "wof:placetype":"venue"
},
  "geometry": {"coordinates":[4.7140870094,51.2562942505],"type":"Point"}
}