{
  "type": "Feature",
  "properties": {
    "iso:country":"BE",
    "sg:address":"Brugmannlaan 288",
    "sg:city":"Ukkel/uccle",
    "sg:orig_category":"Marktonderzoekbureaus Reclamebureaus",
    "sg:phone":"+32 2 347 46 33",
    "sg:postcode":"1180",
    "sg:province":"Bruxelles-Capitale",
    "wof:name":"Bureau Nord-sud",
    "wof:placetype":"venue"
},
  "geometry": {"coordinates":[4.3472270966,50.8122253418],"type":"Point"}
}