{
  "type": "Feature",
  "properties": {
    "addr:full":"Kruipuit 29 Maldegem Oost-Vlaanderen 9991",
    "addr:housenumber":"29",
    "addr:postcode":"9991",
    "addr:street":"Kruipuit",
    "iso:country":"BE",
    "sg:address":"Kruipuit 29",
    "sg:city":"Maldegem",
    "sg:orig_category":"Elektrische installaties voor woningen",
    "sg:phone":"+32 9 377 13 18",
    "sg:postcode":"9991",
    "sg:province":"Oost-Vlaanderen",
    "wof:name":"Gelaude G",
    "wof:placetype":"venue"
},
  "geometry": {"coordinates":[3.5164139271,51.1570281982],"type":"Point"}
}