{
  "type": "Feature",
  "properties": {
    "iso:country":"BE",
    "sg:address":"Westkade 14",
    "sg:city":"Zelzate",
    "sg:classifiers":[
        {
            "category":"Bars & Pubs",
            "type":"Food & Drink"
        }
    ],
    "sg:phone":"+32 9 342 84 70",
    "sg:postcode":"9060",
    "sg:province":"Oost-Vlaanderen",
    "wof:name":"De Boom",
    "wof:placetype":"venue"
},
  "geometry": {"coordinates":[3.8083109856,51.2000541687],"type":"Point"}
}