{
  "type": "Feature",
  "properties": {
    "iso:country":"BE",
    "sg:address":"Hundelgemsesteenweg 584a",
    "sg:city":"Merelbeke",
    "sg:orig_category":"Goederenvervoer over de weg",
    "sg:phone":"+32 9 210 50 30",
    "sg:postcode":"9820",
    "sg:province":"Oost-Vlaanderen",
    "wof:name":"Van Poucke",
    "wof:placetype":"venue"
},
  "geometry": {"coordinates":[3.7469460964,50.9968452454],"type":"Point"}
}