{
  "type": "Feature",
  "properties": {
    "iso:country":"BE",
    "sg:address":"Boerenkrijglaan 1",
    "sg:city":"Westerlo",
    "sg:orig_category":"Solariums",
    "sg:phone":"+32 14 54 45 01",
    "sg:postcode":"2260",
    "sg:province":"Antwerpen",
    "wof:name":"Van Dessel D",
    "wof:placetype":"venue"
},
  "geometry": {"coordinates":[4.915389061,51.0866355896],"type":"Point"}
}