{
  "type": "Feature",
  "properties": {
    "addr:full":"Rumbeeksegravier 152-154 Roeselare West-Vlaanderen 8800",
    "addr:housenumber":"152-154",
    "addr:postcode":"8800",
    "addr:street":"Rumbeeksegravier",
    "iso:country":"BE",
    "sg:address":"Rumbeeksegravier 152-154",
    "sg:city":"Roeselare",
    "sg:classifiers":[
        {
            "category":"Autos & Motor Vehicles",
            "subcategory":"Auto Supplies",
            "type":"Retail Goods"
        }
    ],
    "sg:phone":"+32 51 24 01 00",
    "sg:postcode":"8800",
    "sg:province":"West-Vlaanderen",
    "sg:tags":[
        "car",
        "mat"
    ],
    "wof:name":"Jadi B.v.b.a.",
    "wof:placetype":"venue"
},
  "geometry": {"coordinates":[3.1631510258,50.9446220398],"type":"Point"}
}