{
  "type": "Feature",
  "properties": {
    "addr:full":"Pasbrug 18 Westerlo Antwerpen 2260",
    "addr:housenumber":"18",
    "addr:postcode":"2260",
    "addr:street":"Pasbrug",
    "iso:country":"BE",
    "sg:address":"Pasbrug 18",
    "sg:city":"Westerlo",
    "sg:orig_category":"Producteurs de l\u00e9gumes",
    "sg:phone":"+32 14 26 59 65",
    "sg:postcode":"2260",
    "sg:province":"Antwerpen",
    "wof:name":"Marcus Naets",
    "wof:placetype":"venue"
},
  "geometry": {"coordinates":[4.8552589417,51.1055641174],"type":"Point"}
}