{
  "type": "Feature",
  "properties": {
    "iso:country":"BE",
    "sg:address":"Koning Albert I Straat 5",
    "sg:city":"Lebbeke",
    "sg:classifiers":[
        {
            "category":"Personal",
            "subcategory":"Barber",
            "type":"Services"
        }
    ],
    "sg:phone":"+32 52 41 10 86",
    "sg:postcode":"9280",
    "sg:province":"Oost-Vlaanderen",
    "sg:tags":[
        "gentleman",
        "salon",
        "-",
        "hairdressing"
    ],
    "wof:name":"Dany",
    "wof:placetype":"venue"
},
  "geometry": {"coordinates":[4.1281151772,51.0004501343],"type":"Point"}
}