{
  "type": "Feature",
  "properties": {
    "addr:full":"Rue Royale 330 Bruxelles (schaerbeek) Bruxelles-Capitale 1030",
    "addr:housenumber":"330",
    "addr:postcode":"1030",
    "addr:street":"Rue Royale",
    "iso:country":"BE",
    "sg:address":"Rue Royale 330",
    "sg:city":"Bruxelles (schaerbeek)",
    "sg:classifiers":[
        {
            "category":"Communications",
            "subcategory":"Film & Video Production",
            "type":"Services"
        }
    ],
    "sg:phone":"+32 2 217 08 67",
    "sg:postcode":"1030",
    "sg:province":"Bruxelles-Capitale",
    "sg:tags":[
        "material",
        "audio-visual"
    ],
    "wof:name":"Eiki Video/data Projector",
    "wof:placetype":"venue"
},
  "geometry": {"coordinates":[4.3680157661,50.8579292297],"type":"Point"}
}