{
  "type": "Feature",
  "properties": {
    "addr:full":"Rue Du Onze Novembre 4ba Manage Hainaut 7170",
    "addr:postcode":"7170",
    "addr:street":"Rue Du Onze Novembre 4Ba;Hainaut",
    "iso:country":"BE",
    "sg:address":"Rue Du Onze Novembre 4ba",
    "sg:city":"Manage",
    "sg:orig_category":"Elektrische installaties voor woningen",
    "sg:phone":"+32 64 55 72 00",
    "sg:postcode":"7170",
    "sg:province":"Hainaut",
    "wof:name":"Nothag",
    "wof:placetype":"venue"
},
  "geometry": {"coordinates":[4.2327899933,50.5008239746],"type":"Point"}
}