{
  "type": "Feature",
  "properties": {
    "addr:full":"Rue De Bouillon 34 Beauraing Namur 5570",
    "addr:housenumber":"34",
    "addr:postcode":"5570",
    "addr:street":"Rue De Bouillon",
    "iso:country":"BE",
    "sg:address":"Rue De Bouillon 34",
    "sg:city":"Beauraing",
    "sg:classifiers":[
        {
            "category":"Bakery",
            "type":"Food & Drink"
        }
    ],
    "sg:phone":"+32 82 71 15 52",
    "sg:postcode":"5570",
    "sg:province":"Namur",
    "sg:tags":[
        "confectioner",
        "baker"
    ],
    "wof:name":"Francois-duvivier",
    "wof:placetype":"venue"
},
  "geometry": {"coordinates":[4.9563589096,50.1093025208],"type":"Point"}
}