{
  "type": "Feature",
  "properties": {
    "iso:country":"BE",
    "sg:address":"Ezelstraat 19-21",
    "sg:city":"Brugge",
    "sg:classifiers":[
        {
            "category":"Restaurant",
            "type":"Food & Drink"
        }
    ],
    "sg:phone":"+32 50 33 95 21",
    "sg:postcode":"8000",
    "sg:province":"West-Vlaanderen",
    "wof:name":"'t Presidentje",
    "wof:placetype":"venue"
},
  "geometry": {"coordinates":[3.2193551064,51.2122306824],"type":"Point"}
}