{
  "type": "Feature",
  "properties": {
    "addr:full":"Rue Jules Destr\u00e9e 98 Charleroi (ransart) Hainaut 6043",
    "addr:housenumber":"98",
    "addr:postcode":"6043",
    "addr:street":"Rue Jules Destre\u0301E",
    "iso:country":"BE",
    "sg:address":"Rue Jules Destr\u00e9e 98",
    "sg:city":"Charleroi (ransart)",
    "sg:classifiers":[
        {
            "category":"Health Services",
            "subcategory":"Health Practitioner",
            "type":"Services"
        }
    ],
    "sg:phone":"+32 71 37 37 04",
    "sg:postcode":"6043",
    "sg:province":"Hainaut",
    "sg:tags":[
        "therapist",
        "speech"
    ],
    "wof:name":"Verbanck N",
    "wof:placetype":"venue"
},
  "geometry": {"coordinates":[4.4517412186,50.4210090637],"type":"Point"}
}