{
  "type": "Feature",
  "properties": {
    "addr:full":"Desmedtstraat 73 Zaventem Vlaams-Brabant 1930",
    "addr:housenumber":"73",
    "addr:postcode":"1930",
    "addr:street":"Desmedtstraat",
    "iso:country":"BE",
    "sg:address":"Desmedtstraat 73",
    "sg:city":"Zaventem",
    "sg:classifiers":[
        {
            "category":"Health Services",
            "subcategory":"Dentist",
            "type":"Services"
        }
    ],
    "sg:phone":"+32 2 720 26 32",
    "sg:postcode":"1930",
    "sg:province":"Vlaams-Brabant",
    "wof:name":"Knockaert Koen",
    "wof:placetype":"venue"
},
  "geometry": {"coordinates":[4.4673271179,50.8899154663],"type":"Point"}
}