{
  "type": "Feature",
  "properties": {
    "addr:full":"Rue De La Station 73 Charleroi Hainaut 6043",
    "addr:housenumber":"73",
    "addr:postcode":"6043",
    "addr:street":"Rue De La Station;Hainaut",
    "iso:country":"BE",
    "sg:address":"Rue De La Station 73",
    "sg:city":"Charleroi",
    "sg:orig_category":"Apotheken",
    "sg:phone":"+32 71 35 21 30",
    "sg:postcode":"6043",
    "sg:province":"Hainaut",
    "wof:name":"Jacques Cowez",
    "wof:placetype":"venue"
},
  "geometry": {"coordinates":[4.4864211082,50.4566268921],"type":"Point"}
}