{
  "type": "Feature",
  "properties": {
    "iso:country":"BE",
    "sg:address":"Rue De La Foire 2",
    "sg:city":"Sprimont",
    "sg:classifiers":[
        {
            "category":"Health Services",
            "subcategory":"Dentist",
            "type":"Services"
        }
    ],
    "sg:phone":"+32 4 382 24 26",
    "sg:postcode":"4140",
    "sg:province":"Li\u00e8ge",
    "wof:name":"Pirard Beno\u00eet",
    "wof:placetype":"venue"
},
  "geometry": {"coordinates":[5.6586709023,50.5039291382],"type":"Point"}
}