{
  "type": "Feature",
  "properties": {
    "addr:full":"Eugeen Meeusstraat 126 Merksem Antwerpen 2170",
    "addr:housenumber":"126",
    "addr:postcode":"2170",
    "addr:street":"Eugeen Meeusstraat",
    "iso:country":"BE",
    "sg:address":"Eugeen Meeusstraat 126",
    "sg:city":"Merksem",
    "sg:orig_category":"Messageries. Stockage and entreposage",
    "sg:phone":"+32 3 646 94 18",
    "sg:postcode":"2170",
    "sg:province":"Antwerpen",
    "wof:name":"Abc Service",
    "wof:placetype":"venue"
},
  "geometry": {"coordinates":[4.4421300888,51.2369194031],"type":"Point"}
}