{
  "type": "Feature",
  "properties": {
    "addr:full":"Chauss\u00c9e De Charleroi 160 Fleurus Hainaut 6220",
    "addr:housenumber":"160",
    "addr:postcode":"6220",
    "addr:street":"Chausse\u0301E De Charleroi",
    "iso:country":"BE",
    "sg:address":"Chauss\u00c9e De Charleroi 160",
    "sg:city":"Fleurus",
    "sg:orig_category":"M\u00e9decins and sp\u00e9cialistes",
    "sg:phone":"+32 71 81 18 44",
    "sg:postcode":"6220",
    "sg:province":"Hainaut",
    "wof:name":"Michel Tournay",
    "wof:placetype":"venue"
},
  "geometry": {"coordinates":[4.5530319214,50.4837036133],"type":"Point"}
}