{
  "type": "Feature",
  "properties": {
    "iso:country":"BE",
    "sg:address":"Boomse Steenweg 353",
    "sg:city":"Antwerpen",
    "sg:classifiers":[
        {
            "category":"Retail",
            "subcategory":"Driving School",
            "type":"Services"
        }
    ],
    "sg:phone":"+32 3 780 64 00",
    "sg:postcode":"2020",
    "sg:province":"Antwerpen",
    "sg:tags":[
        "automobile",
        "officially",
        "-",
        "recognized"
    ],
    "wof:name":"Select",
    "wof:placetype":"venue"
},
  "geometry": {"coordinates":[4.3884849548,51.1862297058],"type":"Point"}
}