{
  "type": "Feature",
  "properties": {
    "iso:country":"BE",
    "sg:address":"Waregemsestraat 15",
    "sg:city":"Kruishoutem",
    "sg:orig_category":"Pluimveekwekers",
    "sg:phone":"+32 9 383 55 38",
    "sg:postcode":"9771",
    "sg:province":"Oost-Vlaanderen",
    "wof:name":"Frans Dhuyvetter",
    "wof:placetype":"venue"
},
  "geometry": {"coordinates":[3.5099229813,50.8865203857],"type":"Point"}
}