{
  "type": "Feature",
  "properties": {
    "iso:country":"BE",
    "sg:address":"Sombekedries 9",
    "sg:city":"Waasmunster",
    "sg:orig_category":"Epiceries",
    "sg:phone":"+32 52 46 01 41",
    "sg:postcode":"9250",
    "sg:province":"Oost-Vlaanderen",
    "wof:name":"Spar",
    "wof:placetype":"venue"
},
  "geometry": {"coordinates":[4.1239671707,51.1138191223],"type":"Point"}
}