{
  "type": "Feature",
  "properties": {
    "addr:full":"Ekkelenbergstraat 9 Herne Vlaams-Brabant 1540",
    "addr:housenumber":"9",
    "addr:postcode":"1540",
    "addr:street":"Ekkelenbergstraat",
    "iso:country":"BE",
    "sg:address":"Ekkelenbergstraat 9",
    "sg:city":"Herne",
    "sg:orig_category":"Eleveurs de bovins",
    "sg:phone":"+32 2 396 22 33",
    "sg:postcode":"1540",
    "sg:province":"Vlaams-Brabant",
    "wof:name":"Luc Van Hove",
    "wof:placetype":"venue"
},
  "geometry": {"coordinates":[4.052421093,50.7317848206],"type":"Point"}
}