{
  "type": "Feature",
  "properties": {
    "addr:full":"Rue Alfred Brasseur 29 Namur (vedrin - Daussoulx) Namur 5020",
    "addr:housenumber":"29",
    "addr:postcode":"5020",
    "addr:street":"Rue Alfred Brasseur",
    "iso:country":"BE",
    "sg:address":"Rue Alfred Brasseur 29",
    "sg:city":"Namur (vedrin - Daussoulx)",
    "sg:classifiers":[
        {
            "category":"Home & Garden",
            "subcategory":"Garden Supply",
            "type":"Retail Goods"
        }
    ],
    "sg:phone":"+32 81 21 22 39",
    "sg:postcode":"5020",
    "sg:province":"Namur",
    "sg:tags":[
        "lawn",
        "mower"
    ],
    "wof:name":"Corriat Ets",
    "wof:placetype":"venue"
},
  "geometry": {"coordinates":[4.8665599823,50.4621086121],"type":"Point"}
}