{
  "type": "Feature",
  "properties": {
    "addr:full":"Rue Du Parc 4 Manage Hainaut 7170",
    "addr:housenumber":"4",
    "addr:postcode":"7170",
    "addr:street":"Rue Du Parc",
    "iso:country":"BE",
    "sg:address":"Rue Du Parc 4",
    "sg:city":"Manage",
    "sg:orig_category":"M\u00e9decins and sp\u00e9cialistes",
    "sg:phone":"+32 64 22 07 61",
    "sg:postcode":"7170",
    "sg:province":"Hainaut",
    "wof:name":"J. Trinteler",
    "wof:placetype":"venue"
},
  "geometry": {"coordinates":[4.2340512276,50.4720497131],"type":"Point"}
}