{
  "type": "Feature",
  "properties": {
    "iso:country":"BE",
    "sg:address":"Wijnveld 16",
    "sg:city":"Sint-niklaas (sinaai)",
    "sg:classifiers":[
        {
            "category":"Professional",
            "subcategory":"Management & Consulting",
            "type":"Services"
        }
    ],
    "sg:phone":"+32 3 722 05 43",
    "sg:postcode":"9112",
    "sg:province":"Oost-Vlaanderen",
    "sg:tags":[
        "consultant"
    ],
    "wof:name":"Forces Consulting Bvba",
    "wof:placetype":"venue"
},
  "geometry": {"coordinates":[4.0442728996,51.1534118652],"type":"Point"}
}