{
  "type": "Feature",
  "properties": {
    "iso:country":"BE",
    "sg:address":"Mutsaertstraat 23",
    "sg:city":"Vilvoorde",
    "sg:classifiers":[
        {
            "category":"Professional",
            "subcategory":"Accounting & Tax Preparation",
            "type":"Services"
        }
    ],
    "sg:phone":"+32 2 305 83 41",
    "sg:postcode":"1800",
    "sg:province":"Vlaams-Brabant",
    "sg:tags":[
        "bookkeeper"
    ],
    "wof:name":"Herten E",
    "wof:placetype":"venue"
},
  "geometry": {"coordinates":[4.3629751205,50.9019126892],"type":"Point"}
}