{
  "type": "Feature",
  "properties": {
    "iso:country":"BE",
    "sg:address":"Rue De La Station 35",
    "sg:city":"Waimes",
    "sg:orig_category":"Bouwmaterialen Gh Installatie van metalen schrijnwerk",
    "sg:phone":"+32 80 44 69 64",
    "sg:postcode":"4950",
    "sg:province":"Li\u00e8ge",
    "wof:name":"Georges Bronlet",
    "wof:placetype":"venue"
},
  "geometry": {"coordinates":[6.1328001022,50.4750595093],"type":"Point"}
}