{
  "type": "Feature",
  "properties": {
    "addr:full":"Zwaanhofweg 21 Ieper West-Vlaanderen 8900",
    "addr:housenumber":"21",
    "addr:postcode":"8900",
    "addr:street":"Zwaanhofweg",
    "iso:country":"BE",
    "sg:address":"Zwaanhofweg 21",
    "sg:city":"Ieper",
    "sg:orig_category":"Hout and afgeleiden Gh IJzerwaren, bouw- and verfmaterialen Verhuur doe-het-zelf materiaal",
    "sg:phone":"+32 57 20 64 65",
    "sg:postcode":"8900",
    "sg:province":"West-Vlaanderen",
    "wof:name":"Gamma",
    "wof:placetype":"venue"
},
  "geometry": {"coordinates":[2.8861179352,50.8741950989],"type":"Point"}
}