{
  "type": "Feature",
  "properties": {
    "iso:country":"BE",
    "sg:address":"Bree\u00cbrweg 70",
    "sg:city":"Maaseik",
    "sg:classifiers":[
        {
            "category":"Personal",
            "subcategory":"Beauty Salon",
            "type":"Services"
        }
    ],
    "sg:phone":"+32 89 86 40 56",
    "sg:postcode":"3680",
    "sg:province":"Limburg",
    "sg:tags":[
        "de",
        "coiffure"
    ],
    "wof:name":"Coiffure Suzy",
    "wof:placetype":"venue"
},
  "geometry": {"coordinates":[5.6675000191,51.1143035889],"type":"Point"}
}