{
  "type": "Feature",
  "properties": {
    "iso:country":"BE",
    "sg:address":"Sint-jansstraat 11",
    "sg:city":"Herk-de-stad",
    "sg:orig_category":"Kapsalons",
    "sg:phone":"+32 13 55 15 83",
    "sg:postcode":"3540",
    "sg:province":"Limburg",
    "wof:name":"Coiffure Lea",
    "wof:placetype":"venue"
},
  "geometry": {"coordinates":[5.1678152084,50.9398994446],"type":"Point"}
}