{
  "type": "Feature",
  "properties": {
    "iso:country":"BE",
    "sg:address":"Kortrijksesteenweg 1182a",
    "sg:city":"Gent",
    "sg:orig_category":"V\u00eatements. V\u00eatements pour Hommes. V\u00eatements pour Dames. V\u00eatements pour b\u00e9b\u00e9s and enfants",
    "sg:phone":"+32 9 220 55 74",
    "sg:postcode":"9051",
    "sg:province":"Oost-Vlaanderen",
    "wof:name":"Jbc Mode",
    "wof:placetype":"venue"
},
  "geometry": {"coordinates":[3.6514649391,51.0148277283],"type":"Point"}
}