{
  "type": "Feature",
  "properties": {
    "addr:full":"Hertevoetweg 14 Zemst (weerde) Vlaams-Brabant 1982",
    "addr:housenumber":"14",
    "addr:postcode":"1982",
    "addr:street":"Hertevoetweg",
    "iso:country":"BE",
    "sg:address":"Hertevoetweg 14",
    "sg:city":"Zemst (weerde)",
    "sg:classifiers":[
        {
            "category":"Real Estate",
            "subcategory":"Architect",
            "type":"Services"
        }
    ],
    "sg:phone":"+32 15 61 19 45",
    "sg:postcode":"1982",
    "sg:province":"Vlaams-Brabant",
    "wof:name":"Van Welden Paul",
    "wof:placetype":"venue"
},
  "geometry": {"coordinates":[4.4760408401,50.9732437134],"type":"Point"}
}