{
  "type": "Feature",
  "properties": {
    "addr:full":"Houw 10 Herzele Oost-Vlaanderen 9550",
    "addr:housenumber":"10",
    "addr:postcode":"9550",
    "addr:street":"Houw;Oost-Vlaanderen",
    "iso:country":"BE",
    "sg:address":"Houw 10",
    "sg:city":"Herzele",
    "sg:orig_category":"Travaux de pl\u00e2trage",
    "sg:phone":"+32 53 63 16 01",
    "sg:postcode":"9550",
    "sg:province":"Oost-Vlaanderen",
    "wof:name":"Stefan Roos",
    "wof:placetype":"venue"
},
  "geometry": {"coordinates":[3.8699901104,50.9011497498],"type":"Point"}
}