{
  "type": "Feature",
  "properties": {
    "addr:full":"Chauss\u00e9e De Gand 1204 Bruxelles (berchem-sainte-agathe) Bruxelles-Capitale 1082",
    "addr:postcode":"1204;berchem-sainte-agathe;1082",
    "addr:street":"Chausse\u0301E De Gand",
    "iso:country":"BE",
    "sg:address":"Chauss\u00e9e De Gand 1204",
    "sg:city":"Bruxelles (berchem-sainte-agathe)",
    "sg:classifiers":[
        {
            "category":"Health Services",
            "subcategory":"Health Practitioner",
            "type":"Services"
        }
    ],
    "sg:phone":"+32 2 465 47 82",
    "sg:postcode":"1082",
    "sg:province":"Bruxelles-Capitale",
    "sg:tags":[
        "physiotherapist"
    ],
    "wof:name":"Van Damme Bernadette",
    "wof:placetype":"venue"
},
  "geometry": {"coordinates":[4.2959141731,50.865436554],"type":"Point"}
}