{
  "type": "Feature",
  "properties": {
    "iso:country":"BE",
    "sg:address":"Diksmuidsesteenweg 141",
    "sg:city":"Ieper",
    "sg:orig_category":"Eclairage et \u00e9quipements du foyer",
    "sg:phone":"+32 57 21 94 19",
    "sg:postcode":"8900",
    "sg:province":"West-Vlaanderen",
    "wof:name":"Desmyter Marc Interieur",
    "wof:placetype":"venue"
},
  "geometry": {"coordinates":[2.8750059605,50.866607666],"type":"Point"}
}