{
  "type": "Feature",
  "properties": {
    "addr:full":"Koning Leopold Iii-laan 5 Kortrijk West-Vlaanderen 8500",
    "addr:housenumber":"5",
    "addr:postcode":"8500",
    "addr:street":"Koning Leopold Iii-Laan",
    "iso:country":"BE",
    "sg:address":"Koning Leopold Iii-laan 5",
    "sg:city":"Kortrijk",
    "sg:orig_category":"Benzinestations and brandstoffen Herstellingen and onderhoud van auto's",
    "sg:phone":"+32 56 35 48 40",
    "sg:postcode":"8500",
    "sg:province":"West-Vlaanderen",
    "wof:name":"Q8",
    "wof:placetype":"venue"
},
  "geometry": {"coordinates":[3.2692129612,50.8364448547],"type":"Point"}
}