{
  "type": "Feature",
  "properties": {
    "iso:country":"BE",
    "sg:address":"Gasthuisbosdreef 1",
    "sg:city":"Tongeren",
    "sg:orig_category":"Boekhouders",
    "sg:phone":"+32 12 23 89 06",
    "sg:postcode":"3700",
    "sg:province":"Limburg",
    "wof:name":"Danny Jans",
    "wof:placetype":"venue"
},
  "geometry": {"coordinates":[5.451294899,50.7907829285],"type":"Point"}
}