{
  "type": "Feature",
  "properties": {
    "addr:full":"Rue Joseph Wettinck 60 Seraing Li\u00e8ge 4101",
    "addr:housenumber":"60",
    "addr:postcode":"4101",
    "addr:street":"Rue Joseph Wettinck",
    "iso:country":"BE",
    "sg:address":"Rue Joseph Wettinck 60",
    "sg:city":"Seraing",
    "sg:classifiers":[
        {
            "category":"Wholesale",
            "subcategory":"Vending Machines",
            "type":"Manufacturing & Wholesale Goods"
        }
    ],
    "sg:phone":"+32 4 233 35 27",
    "sg:postcode":"4101",
    "sg:province":"Li\u00e8ge",
    "sg:tags":[
        "mat\u00e9riel",
        "de",
        "bureau",
        "gr",
        "fournitures"
    ],
    "wof:name":"Trois Fontaines",
    "wof:placetype":"venue"
},
  "geometry": {"coordinates":[5.5014438629,50.6151695251],"type":"Point"}
}