{
  "type": "Feature",
  "properties": {
    "addr:full":"Gross Geraulaan 7 Tielt West-Vlaanderen 8700",
    "addr:housenumber":"7",
    "addr:postcode":"8700",
    "addr:street":"Geraulaan",
    "iso:country":"BE",
    "sg:address":"Gross Geraulaan 7",
    "sg:city":"Tielt",
    "sg:classifiers":[
        {
            "category":"Professional",
            "subcategory":"Art Services",
            "type":"Services"
        }
    ],
    "sg:phone":"+32 51 40 31 54",
    "sg:postcode":"8700",
    "sg:province":"West-Vlaanderen",
    "sg:tags":[
        "interior",
        "designer"
    ],
    "wof:name":"Dierckens & Pauwels",
    "wof:placetype":"venue"
},
  "geometry": {"coordinates":[3.3363780975,51.0019073486],"type":"Point"}
}