{
  "type": "Feature",
  "properties": {
    "addr:full":"Herseltsesteenweg 162 Aarschot Vlaams-Brabant 3200",
    "addr:housenumber":"162",
    "addr:postcode":"3200",
    "addr:street":"Herseltsesteenweg",
    "iso:country":"BE",
    "sg:address":"Herseltsesteenweg 162",
    "sg:city":"Aarschot",
    "sg:classifiers":[
        {
            "category":"Restaurant",
            "type":"Food & Drink"
        }
    ],
    "sg:phone":"+32 16 56 11 26",
    "sg:postcode":"3200",
    "sg:province":"Vlaams-Brabant",
    "wof:name":"Caf\u00c9 De Witte Molen",
    "wof:placetype":"venue"
},
  "geometry": {"coordinates":[4.8356261253,51.0026130676],"type":"Point"}
}