{
  "type": "Feature",
  "properties": {
    "iso:country":"BE",
    "sg:address":"Noorderlaan 123",
    "sg:city":"Antwerpen",
    "sg:classifiers":[
        {
            "category":"Train Station",
            "subcategory":"Rail",
            "type":"Transportation"
        }
    ],
    "sg:phone":"+32 50 54 69 81",
    "sg:postcode":"2030",
    "sg:province":"Antwerpen",
    "sg:tags":[
        "ship",
        "chandler"
    ],
    "wof:name":"Wells & Mommaerts Nv",
    "wof:placetype":"venue"
},
  "geometry": {"coordinates":[4.4130687714,51.2640914917],"type":"Point"}
}