{
  "type": "Feature",
  "properties": {
    "addr:full":"Vagevuurstraat 16a Zuienkerke West-Vlaanderen 8377",
    "addr:housenumber":"16a",
    "addr:postcode":"8377",
    "addr:street":"Vagevuurstraat",
    "iso:country":"BE",
    "sg:address":"Vagevuurstraat 16a",
    "sg:city":"Zuienkerke",
    "sg:classifiers":[
        {
            "category":"Retail",
            "subcategory":"Event Space",
            "type":"Services"
        }
    ],
    "sg:phone":"+32 50 67 00 44",
    "sg:postcode":"8377",
    "sg:province":"West-Vlaanderen",
    "sg:tags":[
        "organisation"
    ],
    "wof:name":"Sculpta",
    "wof:placetype":"venue"
},
  "geometry": {"coordinates":[3.1833798885,51.2577209473],"type":"Point"}
}