{
  "type": "Feature",
  "properties": {
    "iso:country":"BE",
    "sg:address":"Trommelstraat 9",
    "sg:city":"Heist-op-den-berg (schriek)",
    "sg:classifiers":[
        {
            "category":"Shopping",
            "subcategory":"Computers & Home Electronics",
            "type":"Retail Goods"
        }
    ],
    "sg:phone":"+32 15 23 68 69",
    "sg:postcode":"2223",
    "sg:province":"Antwerpen",
    "sg:tags":[
        "-",
        "television",
        "radio"
    ],
    "wof:name":"Patrick Sales Bvba",
    "wof:placetype":"venue"
},
  "geometry": {"coordinates":[4.6935648918,51.0282707214],"type":"Point"}
}