{
  "type": "Feature",
  "properties": {
    "addr:full":"Poederleeseweg 83 Lille Antwerpen 2275",
    "addr:housenumber":"83",
    "addr:postcode":"2275",
    "addr:street":"Poederleeseweg",
    "iso:country":"BE",
    "sg:address":"Poederleeseweg 83",
    "sg:city":"Lille",
    "sg:orig_category":"Kapsalons",
    "sg:phone":"+32 14 88 02 69",
    "sg:postcode":"2275",
    "sg:province":"Antwerpen",
    "wof:name":"Haarstudio Michel",
    "wof:placetype":"venue"
},
  "geometry": {"coordinates":[4.8295907974,51.2337760925],"type":"Point"}
}