{
  "type": "Feature",
  "properties": {
    "iso:country":"BE",
    "sg:address":"Stationsstraat 98",
    "sg:city":"Eeklo",
    "sg:orig_category":"Meubles D\u00e9taillants, Am\u00e9nagement de B\u00e2timents et de Cuisines",
    "sg:phone":"+32 9 377 90 34",
    "sg:postcode":"9900",
    "sg:province":"Oost-Vlaanderen",
    "wof:name":"Sleepy Eeklo",
    "wof:placetype":"venue"
},
  "geometry": {"coordinates":[3.5727849007,51.1819267273],"type":"Point"}
}