{
  "type": "Feature",
  "properties": {
    "addr:full":"Prinsenveld 20 Aalst Oost-Vlaanderen 9300",
    "addr:housenumber":"20",
    "addr:postcode":"9300",
    "addr:street":"Prinsenveld",
    "iso:country":"BE",
    "sg:address":"Prinsenveld 20",
    "sg:city":"Aalst",
    "sg:classifiers":[
        {
            "category":"Personal",
            "subcategory":"Beauty Salon",
            "type":"Services"
        }
    ],
    "sg:phone":"+32 53 77 13 83",
    "sg:postcode":"9300",
    "sg:province":"Oost-Vlaanderen",
    "sg:tags":[
        "lady",
        "-",
        "hairdressing"
    ],
    "wof:name":"Arlette",
    "wof:placetype":"venue"
},
  "geometry": {"coordinates":[4.0462298393,50.9519081116],"type":"Point"}
}