{
  "type": "Feature",
  "properties": {
    "addr:full":"Rue Namur Perwez 64 La Bruy\u00e8re (villers-lez-heest) Namur 5080",
    "addr:housenumber":"64",
    "addr:postcode":"5080",
    "addr:street":"Rue Namur Perwez;Bruye\u0300Re Villers-Lez-Heest",
    "iso:country":"BE",
    "sg:address":"Rue Namur Perwez 64",
    "sg:city":"La Bruy\u00e8re (villers-lez-heest)",
    "sg:classifiers":[
        {
            "category":"Food & Beverages",
            "subcategory":"Liquor & Beverages",
            "type":"Retail Goods"
        }
    ],
    "sg:phone":"+32 81 51 19 41",
    "sg:postcode":"5080",
    "sg:province":"Namur",
    "sg:tags":[
        "-",
        "spirit",
        "wine"
    ],
    "wof:name":"Au Bon C\u00e9page",
    "wof:placetype":"venue"
},
  "geometry": {"coordinates":[4.8439478874,50.5330047607],"type":"Point"}
}