{
  "type": "Feature",
  "properties": {
    "addr:full":"Grand'place 38 Jodoigne Brabant Wallon 1370",
    "addr:housenumber":"38",
    "addr:postcode":"1370",
    "addr:street":"Grand'Place",
    "iso:country":"BE",
    "sg:address":"Grand'place 38",
    "sg:city":"Jodoigne",
    "sg:orig_category":"Apotheken",
    "sg:phone":"+32 10 81 34 58",
    "sg:postcode":"1370",
    "sg:province":"Brabant Wallon",
    "wof:name":"Pharmacie Geldof",
    "wof:placetype":"venue"
},
  "geometry": {"coordinates":[4.8666749001,50.7255744934],"type":"Point"}
}