{
  "type": "Feature",
  "properties": {
    "addr:full":"Emiel Hertecantlaan 56 Berlare Oost-Vlaanderen 9290",
    "addr:housenumber":"56",
    "addr:postcode":"9290",
    "addr:street":"Emiel Hertecantlaan",
    "iso:country":"BE",
    "sg:address":"Emiel Hertecantlaan 56",
    "sg:city":"Berlare",
    "sg:orig_category":"Opticiens",
    "sg:phone":"+32 52 42 72 80",
    "sg:postcode":"9290",
    "sg:province":"Oost-Vlaanderen",
    "wof:name":"Optiek Patrick Pieters",
    "wof:placetype":"venue"
},
  "geometry": {"coordinates":[4.0052838326,51.0149688721],"type":"Point"}
}