{
  "type": "Feature",
  "properties": {
    "iso:country":"BE",
    "sg:address":"Nervi\u00ebrsstraat 68",
    "sg:city":"Leuven",
    "sg:classifiers":[
        {
            "category":"Building & Trades",
            "subcategory":"Electrical",
            "type":"Services"
        }
    ],
    "sg:phone":"+32 16 22 34 91",
    "sg:postcode":"3000",
    "sg:province":"Vlaams-Brabant",
    "sg:tags":[
        "heating"
    ],
    "wof:name":"Carlens P",
    "wof:placetype":"venue"
},
  "geometry": {"coordinates":[4.7097878456,50.8826522827],"type":"Point"}
}