{
  "type": "Feature",
  "properties": {
    "iso:country":"BE",
    "sg:address":"Boulevard Sylvain Dupuis 112",
    "sg:city":"Anderlecht",
    "sg:orig_category":"Enseignement maternel and primaire",
    "sg:phone":"+32 2 523 68 01",
    "sg:postcode":"1070",
    "sg:province":"Bruxelles-Capitale",
    "wof:name":"Ecole Les Sureaux",
    "wof:placetype":"venue"
},
  "geometry": {"coordinates":[4.3007669449,50.8371124268],"type":"Point"}
}