{
  "type": "Feature",
  "properties": {
    "addr:full":"Lostraat 49 Heist-op-den-berg Antwerpen 2220",
    "addr:housenumber":"49",
    "addr:postcode":"2220",
    "addr:street":"Lostraat",
    "iso:country":"BE",
    "sg:address":"Lostraat 49",
    "sg:city":"Heist-op-den-berg",
    "sg:orig_category":"Centres de fitness. Centres de relaxation and bien-\u00eatre. Clubs de sport. Centres de fitness",
    "sg:phone":"+32 15 24 87 49",
    "sg:postcode":"2220",
    "sg:province":"Antwerpen",
    "wof:name":"Heistse Gym",
    "wof:placetype":"venue"
},
  "geometry": {"coordinates":[4.7362599373,51.067653656],"type":"Point"}
}