{
  "type": "Feature",
  "properties": {
    "iso:country":"BE",
    "sg:address":"Hoogstraat 175",
    "sg:city":"Brussel/bruxelles",
    "sg:orig_category":"Kapsalons",
    "sg:phone":"+32 2 513 16 36",
    "sg:postcode":"1000",
    "sg:province":"Bruxelles-Capitale",
    "wof:name":"Coiffure Francine",
    "wof:placetype":"venue"
},
  "geometry": {"coordinates":[4.3492441177,50.8379211426],"type":"Point"}
}