{
  "type": "Feature",
  "properties": {
    "addr:full":"De Vis 20 Brasschaat Antwerpen 2930",
    "addr:housenumber":"20",
    "addr:postcode":"2930",
    "iso:country":"BE",
    "sg:address":"De Vis 20",
    "sg:city":"Brasschaat",
    "sg:orig_category":"Fleurs and plantes",
    "sg:phone":"+32 3 653 18 20",
    "sg:postcode":"2930",
    "sg:province":"Antwerpen",
    "wof:name":"\u00b4t Sfeerhuis",
    "wof:placetype":"venue"
},
  "geometry": {"coordinates":[4.5113930702,51.293838501],"type":"Point"}
}