{
  "type": "Feature",
  "properties": {
    "iso:country":"BE",
    "sg:address":"Rue De La Giloterie 37",
    "sg:city":"Fosses-la-ville",
    "sg:orig_category":"Traitements param\u00e9dicaux",
    "sg:phone":"+32 71 71 21 65",
    "sg:postcode":"5070",
    "sg:province":"Namur",
    "wof:name":"C. Godart",
    "wof:placetype":"venue"
},
  "geometry": {"coordinates":[4.6381192207,50.3920326233],"type":"Point"}
}