{
  "type": "Feature",
  "properties": {
    "addr:full":"Rue D\u00b4emptinne 3 Hamois Namur 5363",
    "addr:housenumber":"3",
    "addr:postcode":"5363",
    "addr:street":"Rue D\u00b4Emptinne",
    "iso:country":"BE",
    "sg:address":"Rue D\u00b4emptinne 3",
    "sg:city":"Hamois",
    "sg:orig_category":"D\u00e9molition d\u00b4immeubles and terrassements",
    "sg:phone":"+32 83 61 24 69",
    "sg:postcode":"5363",
    "sg:province":"Namur",
    "wof:name":"Thierry Lurot",
    "wof:placetype":"venue"
},
  "geometry": {"coordinates":[5.1216220856,50.326915741],"type":"Point"}
}