{
  "type": "Feature",
  "properties": {
    "addr:full":"Torenplein 2 Ranst (oelegem) Antwerpen 2520",
    "addr:housenumber":"2",
    "addr:postcode":"2520",
    "addr:street":"Torenplein",
    "iso:country":"BE",
    "sg:address":"Torenplein 2",
    "sg:city":"Ranst (oelegem)",
    "sg:classifiers":[
        {
            "category":"Health Services",
            "subcategory":"Health Practitioner",
            "type":"Services"
        }
    ],
    "sg:phone":"+32 3 383 51 95",
    "sg:postcode":"2520",
    "sg:province":"Antwerpen",
    "sg:tags":[
        "physiotherapist"
    ],
    "wof:name":"Heyrman Annette",
    "wof:placetype":"venue"
},
  "geometry": {"coordinates":[4.5983281136,51.2108230591],"type":"Point"}
}