{
  "type": "Feature",
  "properties": {
    "iso:country":"BE",
    "sg:address":"Rue Des C\u00c9lestines 6",
    "sg:city":"Li\u00c8ge",
    "sg:classifiers":[
        {
            "category":"Restaurant",
            "type":"Food & Drink"
        }
    ],
    "sg:phone":"+32 4 221 39 51",
    "sg:postcode":"4000",
    "sg:province":"Li\u00e8ge",
    "wof:name":"Restaurant La Cueca",
    "wof:placetype":"venue"
},
  "geometry": {"coordinates":[5.5680551529,50.6417388916],"type":"Point"}
}