{
  "type": "Feature",
  "properties": {
    "addr:full":"Voorstadstraat 18 Komen-waasten/comines-warneton Hainaut 7780",
    "addr:housenumber":"18;7780",
    "addr:street":"Voorstadstraat",
    "iso:country":"BE",
    "sg:address":"Voorstadstraat 18",
    "sg:city":"Komen-waasten/comines-warneton",
    "sg:orig_category":"Herstelling horloges and juwelen Juwelen and horloges",
    "sg:phone":"+32 56 55 52 01",
    "sg:postcode":"7780",
    "sg:province":"Hainaut",
    "wof:name":"Maison De Potter-leroy",
    "wof:placetype":"venue"
},
  "geometry": {"coordinates":[2.9984300137,50.7863311768],"type":"Point"}
}