{
  "type": "Feature",
  "properties": {
    "addr:full":"Leuvensestraat 6 Aarschot Vlaams-Brabant 3200",
    "addr:housenumber":"6",
    "addr:postcode":"3200",
    "addr:street":"Leuvensestraat",
    "iso:country":"BE",
    "sg:address":"Leuvensestraat 6",
    "sg:city":"Aarschot",
    "sg:classifiers":[
        {
            "category":"Shopping",
            "subcategory":"Clothing, Apparel, & Fashions",
            "type":"Retail Goods"
        }
    ],
    "sg:phone":"+32 16 56 29 39",
    "sg:postcode":"3200",
    "sg:province":"Vlaams-Brabant",
    "sg:tags":[
        "-",
        "clothing",
        "child"
    ],
    "wof:name":"Babeloe",
    "wof:placetype":"venue"
},
  "geometry": {"coordinates":[4.8322401047,50.9837989807],"type":"Point"}
}