{
  "type": "Feature",
  "properties": {
    "iso:country":"BE",
    "sg:address":"Abeelstraat 37",
    "sg:city":"Ruiselede",
    "sg:orig_category":"Dierenartsen",
    "sg:phone":"+32 51 68 64 30",
    "sg:postcode":"8755",
    "sg:province":"West-Vlaanderen",
    "wof:name":"Filip De Jaeger",
    "wof:placetype":"venue"
},
  "geometry": {"coordinates":[3.3609740734,51.0404396057],"type":"Point"}
}