{
  "type": "Feature",
  "properties": {
    "iso:country":"BE",
    "sg:address":"Rue Neuve 101",
    "sg:city":"Boussu",
    "sg:orig_category":"Supermarch\u00e9s",
    "sg:postcode":"7300",
    "sg:province":"Hainaut",
    "wof:name":"Aldi",
    "wof:placetype":"venue"
},
  "geometry": {"coordinates":[3.7927570343,50.4302215576],"type":"Point"}
}