{
  "type": "Feature",
  "properties": {
    "addr:full":"Place Saint-walh\u00e8re 2 Walcourt (gourdinne) Namur 5651",
    "addr:housenumber":"2",
    "addr:postcode":"5651",
    "addr:street":"Place Saint-Walhe\u0300Re",
    "iso:country":"BE",
    "sg:address":"Place Saint-walh\u00e8re 2",
    "sg:city":"Walcourt (gourdinne)",
    "sg:classifiers":[
        {
            "category":"Health Services",
            "subcategory":"Medical Lab",
            "type":"Services"
        }
    ],
    "sg:phone":"+32 71 61 30 85",
    "sg:postcode":"5651",
    "sg:province":"Namur",
    "sg:tags":[
        "laboratory",
        "dental"
    ],
    "wof:name":"Bailey S",
    "wof:placetype":"venue"
},
  "geometry": {"coordinates":[4.4536619186,50.2892036438],"type":"Point"}
}