{
  "type": "Feature",
  "properties": {
    "addr:full":"Minister E. Rubbenslaan 1 Zele Oost-Vlaanderen 9240",
    "addr:housenumber":"1",
    "addr:postcode":"9240",
    "addr:street":"Minister E. Rubbenslaan",
    "iso:country":"BE",
    "sg:address":"Minister E. Rubbenslaan 1",
    "sg:city":"Zele",
    "sg:classifiers":[
        {
            "category":"Personal",
            "subcategory":"Beauty Salon",
            "type":"Services"
        }
    ],
    "sg:phone":"+32 52 45 06 75",
    "sg:postcode":"9240",
    "sg:province":"Oost-Vlaanderen",
    "sg:tags":[
        "lady",
        "-",
        "hairdressing"
    ],
    "wof:name":"Kristien",
    "wof:placetype":"venue"
},
  "geometry": {"coordinates":[4.0362939835,51.0702934265],"type":"Point"}
}