{
  "type": "Feature",
  "properties": {
    "addr:full":"Dorpsstraat 52 Aalst (baardegem) Oost-Vlaanderen 9310",
    "addr:housenumber":"52",
    "addr:postcode":"9310",
    "addr:street":"Dorpsstraat",
    "iso:country":"BE",
    "sg:address":"Dorpsstraat 52",
    "sg:city":"Aalst (baardegem)",
    "sg:classifiers":[
        {
            "category":"Wholesale",
            "subcategory":"Fruits & Vegetables",
            "type":"Manufacturing & Wholesale Goods"
        }
    ],
    "sg:phone":"+32 52 35 89 30",
    "sg:postcode":"9310",
    "sg:province":"Oost-Vlaanderen",
    "sg:tags":[
        "whol",
        "-",
        "potato"
    ],
    "wof:name":"Roggeman R",
    "wof:placetype":"venue"
},
  "geometry": {"coordinates":[4.098400116,50.9477767944],"type":"Point"}
}