{
  "type": "Feature",
  "properties": {
    "addr:full":"Quartier Du Petit Culot 18bb Doische Namur 5680",
    "addr:housenumber":"18bb",
    "addr:postcode":"5680",
    "addr:street":"Quartier Du Petit Culot",
    "iso:country":"BE",
    "sg:address":"Quartier Du Petit Culot 18bb",
    "sg:city":"Doische",
    "sg:orig_category":"Kapsalons",
    "sg:phone":"+32 60 39 91 78",
    "sg:postcode":"5680",
    "sg:province":"Namur",
    "wof:name":"Coiffure Brigitte",
    "wof:placetype":"venue"
},
  "geometry": {"coordinates":[4.6447811127,50.1181983948],"type":"Point"}
}