{
  "type": "Feature",
  "properties": {
    "iso:country":"BE",
    "sg:address":"Boerenkrijgsingel 26",
    "sg:city":"Hasselt",
    "sg:orig_category":"Paramedische behandelingen",
    "sg:phone":"+32 11 28 19 65",
    "sg:postcode":"3500",
    "sg:province":"Limburg",
    "wof:name":"Isabella Piquet",
    "wof:placetype":"venue"
},
  "geometry": {"coordinates":[5.318005085,50.9244499207],"type":"Point"}
}