{
  "type": "Feature",
  "properties": {
    "iso:country":"BE",
    "sg:address":"Rue Laurent Vandenhoven 47a",
    "sg:city":"Bruxelles (evere)",
    "sg:classifiers":[
        {
            "category":"Autos & Motor Vehicles",
            "subcategory":"Automobile Sales",
            "type":"Retail Goods"
        }
    ],
    "sg:phone":"+32 2 242 33 25",
    "sg:postcode":"1140",
    "sg:province":"Bruxelles-Capitale",
    "sg:tags":[
        "car",
        "used",
        "-"
    ],
    "wof:name":"Busi - Ness.car Sprl",
    "wof:placetype":"venue"
},
  "geometry": {"coordinates":[4.4053440094,50.8824996948],"type":"Point"}
}