{
  "type": "Feature",
  "properties": {
    "iso:country":"BE",
    "sg:address":"Kapellestraat 78",
    "sg:city":"Aartselaar",
    "sg:classifiers":[
        {
            "category":"Shopping",
            "subcategory":"Florist",
            "type":"Retail Goods"
        }
    ],
    "sg:phone":"+32 3 887 17 42",
    "sg:postcode":"2630",
    "sg:province":"Antwerpen",
    "wof:name":"Beukeleers Bloemen",
    "wof:placetype":"venue"
},
  "geometry": {"coordinates":[4.3891911507,51.1307258606],"type":"Point"}
}