{
  "type": "Feature",
  "properties": {
    "iso:country":"BE",
    "sg:address":"Prinsstraat 18",
    "sg:city":"Antwerpen",
    "sg:orig_category":"Architecten",
    "sg:phone":"+32 3 203 08 74",
    "sg:postcode":"2000",
    "sg:province":"Antwerpen",
    "wof:name":"Lucien Kahane",
    "wof:placetype":"venue"
},
  "geometry": {"coordinates":[4.4108710289,51.2222938538],"type":"Point"}
}