{
  "type": "Feature",
  "properties": {
    "addr:full":"Rue De La Lib\u00c9ration 11 La Louviere Hainaut 7100",
    "addr:housenumber":"11",
    "addr:postcode":"7100",
    "addr:street":"Rue De La Libe\u0301Ration",
    "iso:country":"BE",
    "sg:address":"Rue De La Lib\u00c9ration 11",
    "sg:city":"La Louviere",
    "sg:orig_category":"Traitements param\u00e9dicaux",
    "sg:phone":"+32 64 28 30 97",
    "sg:postcode":"7100",
    "sg:province":"Hainaut",
    "wof:name":"A. Taquin",
    "wof:placetype":"venue"
},
  "geometry": {"coordinates":[4.2152137756,50.4743385315],"type":"Point"}
}