{
  "type": "Feature",
  "properties": {
    "iso:country":"BE",
    "sg:address":"Rue De L'usine 1",
    "sg:city":"Charleroi (couillet)",
    "sg:classifiers":[
        {
            "category":"Utilities",
            "subcategory":"Refuse",
            "type":"Services"
        }
    ],
    "sg:phone":"+32 71 60 57 19",
    "sg:postcode":"6010",
    "sg:province":"Hainaut",
    "sg:tags":[
        "management",
        "waste"
    ],
    "wof:name":"Retrival",
    "wof:placetype":"venue"
},
  "geometry": {"coordinates":[4.4674019814,50.3930740356],"type":"Point"}
}