{
  "type": "Feature",
  "properties": {
    "addr:full":"Marktstraat 15-17 Izegem West-Vlaanderen 8870",
    "addr:postcode":"15-17;8870",
    "addr:street":"Marktstraat",
    "iso:country":"BE",
    "sg:address":"Marktstraat 15-17",
    "sg:city":"Izegem",
    "sg:classifiers":[
        {
            "category":"Health Services",
            "subcategory":"Optometrist",
            "type":"Services"
        }
    ],
    "sg:phone":"+32 51 31 01 59",
    "sg:postcode":"8870",
    "sg:province":"West-Vlaanderen",
    "wof:name":"Optiek Marrannes Bvba",
    "wof:placetype":"venue"
},
  "geometry": {"coordinates":[3.2148039341,50.9182395935],"type":"Point"}
}