{
  "type": "Feature",
  "properties": {
    "iso:country":"BE",
    "sg:address":"Oude Kerkstraat 50",
    "sg:city":"Oudenburg",
    "sg:orig_category":"Eleveurs and marchands de porcs. Eleveurs de bovins",
    "sg:phone":"+32 59 26 66 95",
    "sg:postcode":"8460",
    "sg:province":"West-Vlaanderen",
    "wof:name":"Valere De Klerck",
    "wof:placetype":"venue"
},
  "geometry": {"coordinates":[3.0323109627,51.1749801636],"type":"Point"}
}