{
  "type": "Feature",
  "properties": {
    "iso:country":"BE",
    "sg:address":"Ouden Heirweg 76",
    "sg:city":"Lede",
    "sg:orig_category":"Pain, p\u00e2tisseries and confiseries",
    "sg:phone":"+32 9 369 49 57",
    "sg:postcode":"9340",
    "sg:province":"Oost-Vlaanderen",
    "wof:name":"Gilbert Uyttendaele",
    "wof:placetype":"venue"
},
  "geometry": {"coordinates":[3.8916509151,50.9549674988],"type":"Point"}
}