{
  "type": "Feature",
  "properties": {
    "iso:country":"BE",
    "sg:address":"Grote Baan 341",
    "sg:city":"Waasmunster",
    "sg:orig_category":"Meubelzaken, woning- and keukeninrichting",
    "sg:phone":"+32 9 348 15 49",
    "sg:postcode":"9250",
    "sg:province":"Oost-Vlaanderen",
    "wof:name":"Van Goethem",
    "wof:placetype":"venue"
},
  "geometry": {"coordinates":[4.02871418,51.1225662231],"type":"Point"}
}