{
  "type": "Feature",
  "properties": {
    "addr:full":"Avenue Des Martyrs 208 Fleron Li\u00e8ge 4620",
    "addr:housenumber":"208",
    "addr:postcode":"4620",
    "addr:street":"Avenue Des Martyrs",
    "iso:country":"BE",
    "sg:address":"Avenue Des Martyrs 208",
    "sg:city":"Fleron",
    "sg:orig_category":"Eclairage et \u00e9quipements du foyer. Textiles",
    "sg:phone":"+32 4 358 74 14",
    "sg:postcode":"4620",
    "sg:province":"Li\u00e8ge",
    "wof:name":"Autrement D\u00c9coration",
    "wof:placetype":"venue"
},
  "geometry": {"coordinates":[5.6805119514,50.6144943237],"type":"Point"}
}