{
  "type": "Feature",
  "properties": {
    "iso:country":"BE",
    "sg:address":"Rue Saint-nicolas 1",
    "sg:city":"Ramillies",
    "sg:orig_category":"Verplichte sociale verzekeringen",
    "sg:phone":"+32 81 87 82 74",
    "sg:postcode":"1367",
    "sg:province":"Brabant Wallon",
    "wof:name":"Mutualit\u00c9 Socialiste",
    "wof:placetype":"venue"
},
  "geometry": {"coordinates":[4.8547987938,50.6411476135],"type":"Point"}
}