{
  "type": "Feature",
  "properties": {
    "iso:country":"BE",
    "sg:address":"Kapittelstraat 20",
    "sg:city":"Aalst (moorsel)",
    "sg:classifiers":[
        {
            "category":"Building & Trades",
            "subcategory":"Construction",
            "type":"Services"
        }
    ],
    "sg:phone":"+32 53 78 12 30",
    "sg:postcode":"9310",
    "sg:province":"Oost-Vlaanderen",
    "sg:tags":[
        "installation",
        "-",
        "central",
        "heating"
    ],
    "wof:name":"Bornauw J",
    "wof:placetype":"venue"
},
  "geometry": {"coordinates":[4.0967822075,50.9395523071],"type":"Point"}
}