{
  "type": "Feature",
  "properties": {
    "iso:country":"BE",
    "sg:address":"Rue Des Andrieux 120",
    "sg:city":"Dour",
    "sg:orig_category":"Antiek",
    "sg:phone":"+32 65 65 20 63",
    "sg:postcode":"7370",
    "sg:province":"Hainaut",
    "wof:name":"Daniel Traube",
    "wof:placetype":"venue"
},
  "geometry": {"coordinates":[3.7697930336,50.3970031738],"type":"Point"}
}