{
  "type": "Feature",
  "properties": {
    "addr:full":"Winkelomseheide 144 Geel Antwerpen 2440",
    "addr:housenumber":"144",
    "addr:postcode":"2440",
    "addr:street":"Winkelomseheide",
    "iso:country":"BE",
    "sg:address":"Winkelomseheide 144",
    "sg:city":"Geel",
    "sg:orig_category":"Epiceries",
    "sg:phone":"+32 14 58 02 47",
    "sg:postcode":"2440",
    "sg:province":"Antwerpen",
    "wof:name":"Imke Verwimp",
    "wof:placetype":"venue"
},
  "geometry": {"coordinates":[5.0124402046,51.1230392456],"type":"Point"}
}