{
  "type": "Feature",
  "properties": {
    "addr:full":"Promenade Hippolyte Rolin 14 Box 8 Bruxelles (etterbeek) Bruxelles-Capitale 1040",
    "addr:housenumber":"14;8",
    "addr:postcode":"1040",
    "addr:street":"Promenade Hippolyte Rolin;Box",
    "iso:country":"BE",
    "sg:address":"Promenade Hippolyte Rolin 14 Box 8",
    "sg:city":"Bruxelles (etterbeek)",
    "sg:classifiers":[
        {
            "category":"Professional",
            "subcategory":"Computer Services",
            "type":"Services"
        }
    ],
    "sg:phone":"+32 475 82 43 10",
    "sg:postcode":"1040",
    "sg:province":"Bruxelles-Capitale",
    "sg:tags":[
        "-",
        "processing",
        "data",
        "software"
    ],
    "wof:name":"Digisoft Bvba",
    "wof:placetype":"venue"
},
  "geometry": {"coordinates":[4.3970890045,50.827331543],"type":"Point"}
}