{
  "type": "Feature",
  "properties": {
    "iso:country":"BE",
    "sg:address":"Ter Couter 9",
    "sg:city":"Menen",
    "sg:classifiers":[
        {
            "category":"Personal",
            "subcategory":"Beauty Salon",
            "type":"Services"
        }
    ],
    "sg:phone":"+32 56 51 28 29",
    "sg:postcode":"8930",
    "sg:province":"West-Vlaanderen",
    "sg:tags":[
        "de",
        "coiffure"
    ],
    "wof:name":"Salon Henk",
    "wof:placetype":"venue"
},
  "geometry": {"coordinates":[3.0993459225,50.7951698303],"type":"Point"}
}