{
  "type": "Feature",
  "properties": {
    "addr:full":"Busstraat 20 Lochristi Oost-Vlaanderen 9080",
    "addr:housenumber":"20",
    "addr:postcode":"9080",
    "addr:street":"Busstraat",
    "iso:country":"BE",
    "sg:address":"Busstraat 20",
    "sg:city":"Lochristi",
    "sg:orig_category":"Eleveurs de bovins",
    "sg:phone":"+32 9 355 78 64",
    "sg:postcode":"9080",
    "sg:province":"Oost-Vlaanderen",
    "wof:name":"Roger Van De Velde",
    "wof:placetype":"venue"
},
  "geometry": {"coordinates":[3.8313500881,51.1342582703],"type":"Point"}
}