{
  "type": "Feature",
  "properties": {
    "addr:full":"Sint-apolloniastraat 8 Erpe-mere (erpe) Oost-Vlaanderen 9420",
    "addr:housenumber":"8",
    "addr:postcode":"9420",
    "addr:street":"Sint-Apolloniastraat",
    "iso:country":"BE",
    "sg:address":"Sint-apolloniastraat 8",
    "sg:city":"Erpe-mere (erpe)",
    "sg:classifiers":[
        {
            "category":"Real Estate",
            "subcategory":"Surveying",
            "type":"Services"
        }
    ],
    "sg:phone":"+32 475 71 52 97",
    "sg:postcode":"9420",
    "sg:province":"Oost-Vlaanderen",
    "sg:tags":[
        "lettering",
        "letter"
    ],
    "wof:name":"W.s. Lettering",
    "wof:placetype":"venue"
},
  "geometry": {"coordinates":[3.998226881,50.94373703],"type":"Point"}
}