{
  "type": "Feature",
  "properties": {
    "addr:full":"Lange Beeldekensstraat 119 Antwerpen Antwerpen 2060",
    "addr:housenumber":"119",
    "addr:postcode":"2060",
    "addr:street":"Lange Beeldekensstraat",
    "iso:country":"BE",
    "sg:address":"Lange Beeldekensstraat 119",
    "sg:city":"Antwerpen",
    "sg:classifiers":[
        {
            "category":"Communications",
            "subcategory":"Film & Video Production",
            "type":"Services"
        }
    ],
    "sg:phone":"+32 3 272 13 32",
    "sg:postcode":"2060",
    "sg:province":"Antwerpen",
    "sg:tags":[
        "platen",
        "cassette",
        "cd's"
    ],
    "wof:name":"Fassiphone Belgium",
    "wof:placetype":"venue"
},
  "geometry": {"coordinates":[4.4272770882,51.2216033936],"type":"Point"}
}