{
  "type": "Feature",
  "properties": {
    "addr:full":"Scheldedijk 20 Zwijndrecht Antwerpen 2070",
    "addr:housenumber":"20",
    "addr:postcode":"2070",
    "addr:street":"Scheldedijk",
    "iso:country":"BE",
    "sg:address":"Scheldedijk 20",
    "sg:city":"Zwijndrecht",
    "sg:classifiers":[
        {
            "category":"Education",
            "subcategory":"School",
            "type":"Public Place"
        }
    ],
    "sg:phone":"+32 3 575 04 46",
    "sg:postcode":"2070",
    "sg:province":"Antwerpen",
    "sg:tags":[
        "secondary"
    ],
    "wof:name":"Kta Zwijndrecht-cenflumarin",
    "wof:placetype":"venue"
},
  "geometry": {"coordinates":[4.3302612305,51.2464179993],"type":"Point"}
}