{
  "type": "Feature",
  "properties": {
    "addr:full":"Rue Des Deux Chauss\u00e9es 25 Bruxelles (auderghem) Bruxelles-Capitale 1160",
    "addr:housenumber":"25",
    "addr:postcode":"1160",
    "addr:street":"Rue Des Deux Chausse\u0301Es",
    "iso:country":"BE",
    "sg:address":"Rue Des Deux Chauss\u00e9es 25",
    "sg:city":"Bruxelles (auderghem)",
    "sg:classifiers":[
        {
            "category":"Retail",
            "subcategory":"Auto Repair",
            "type":"Services"
        }
    ],
    "sg:phone":"+32 2 672 53 41",
    "sg:postcode":"1160",
    "sg:province":"Bruxelles-Capitale",
    "sg:tags":[
        "automobile-body"
    ],
    "wof:name":"Vanbellinghen Sprl",
    "wof:placetype":"venue"
},
  "geometry": {"coordinates":[4.4338650703,50.8145103455],"type":"Point"}
}