{
  "type": "Feature",
  "properties": {
    "addr:full":"Rue De L'hublinbu 30 Charleroi (couillet) Hainaut 6010",
    "addr:housenumber":"30",
    "addr:postcode":"6010",
    "addr:street":"Rue De L'Hublinbu",
    "iso:country":"BE",
    "sg:address":"Rue De L'hublinbu 30",
    "sg:city":"Charleroi (couillet)",
    "sg:classifiers":[
        {
            "category":"Manufacturing",
            "subcategory":"Chemicals & Compounds",
            "type":"Manufacturing & Wholesale Goods"
        }
    ],
    "sg:phone":"+32 71 30 92 09",
    "sg:postcode":"6010",
    "sg:province":"Hainaut",
    "sg:tags":[
        "pharmaceutical",
        "product"
    ],
    "wof:name":"Jacquiez Ets",
    "wof:placetype":"venue"
},
  "geometry": {"coordinates":[4.4581489563,50.3833808899],"type":"Point"}
}