{
  "type": "Feature",
  "properties": {
    "iso:country":"BE",
    "sg:address":"Rue Des Deux Eglises 55",
    "sg:city":"Neupr\u00e9 (rotheux-rimi\u00e8re)",
    "sg:classifiers":[
        {
            "category":"Shopping",
            "subcategory":"Florist",
            "type":"Retail Goods"
        }
    ],
    "sg:phone":"+32 4 372 01 32",
    "sg:postcode":"4120",
    "sg:province":"Li\u00e8ge",
    "wof:name":"Myosotis (le)",
    "wof:placetype":"venue"
},
  "geometry": {"coordinates":[5.479388237,50.5387992859],"type":"Point"}
}