{
  "type": "Feature",
  "properties": {
    "addr:full":"Dageraadplaats 23 Antwerpen Antwerpen 2018",
    "addr:housenumber":"23",
    "addr:postcode":"2018",
    "addr:street":"Dageraadplaats",
    "iso:country":"BE",
    "sg:address":"Dageraadplaats 23",
    "sg:city":"Antwerpen",
    "sg:orig_category":"Rev\u00eatements pour sols and murs. Peinture",
    "sg:phone":"+32 3 236 17 17",
    "sg:postcode":"2018",
    "sg:province":"Antwerpen",
    "wof:name":"Ronald Van Den Belt",
    "wof:placetype":"venue"
},
  "geometry": {"coordinates":[4.429599762,51.2073402405],"type":"Point"}
}