{
  "type": "Feature",
  "properties": {
    "iso:country":"BE",
    "sg:address":"Rue Rys De Mosbeux 9",
    "sg:city":"Sprimont",
    "sg:orig_category":"Afbraak- and draineerwerken Benzinestations and brandstoffen",
    "sg:phone":"+32 4 360 86 11",
    "sg:postcode":"4140",
    "sg:province":"Li\u00e8ge",
    "wof:name":"Thierry Lami",
    "wof:placetype":"venue"
},
  "geometry": {"coordinates":[5.6903400421,50.5456314087],"type":"Point"}
}