{
  "type": "Feature",
  "properties": {
    "addr:full":"Avenue Demolder 104 Ottignies-louvain-la-neuve (limelette) Brabant Wallon 1342",
    "addr:housenumber":"104",
    "addr:postcode":"1342",
    "addr:street":"Avenue Demolder",
    "iso:country":"BE",
    "sg:address":"Avenue Demolder 104",
    "sg:city":"Ottignies-louvain-la-neuve (limelette)",
    "sg:classifiers":[
        {
            "category":"Shopping",
            "type":"Retail Goods"
        }
    ],
    "sg:phone":"+32 10 41 52 88",
    "sg:postcode":"1342",
    "sg:province":"Brabant Wallon",
    "sg:tags":[
        "product",
        "cleaning",
        "maintenance"
    ],
    "wof:name":"Bg Distribution Sprl",
    "wof:placetype":"venue"
},
  "geometry": {"coordinates":[4.5653619766,50.6753959656],"type":"Point"}
}