{
  "type": "Feature",
  "properties": {
    "iso:country":"BE",
    "sg:address":"Dorpstraat 48",
    "sg:city":"Wichelen",
    "sg:classifiers":[
        {
            "category":"Cafe",
            "type":"Food & Drink"
        }
    ],
    "sg:phone":"+32 9 369 01 31",
    "sg:postcode":"9260",
    "sg:province":"Oost-Vlaanderen",
    "sg:tags":[
        "caf\u00e9s"
    ],
    "wof:name":"Caf\u00c9 Eendracht Serskamp",
    "wof:placetype":"venue"
},
  "geometry": {"coordinates":[3.9716010094,51.013130188],"type":"Point"}
}