{
  "type": "Feature",
  "properties": {
    "addr:full":"Corbeelsstraat 1 Turnhout Antwerpen 2300",
    "addr:housenumber":"1",
    "addr:postcode":"2300",
    "addr:street":"Corbeelsstraat",
    "iso:country":"BE",
    "sg:address":"Corbeelsstraat 1",
    "sg:city":"Turnhout",
    "sg:orig_category":"Elektrische installaties voor woningen Industri\u00eble elektrische installaties",
    "sg:phone":"+32 14 42 92 84",
    "sg:postcode":"2300",
    "sg:province":"Antwerpen",
    "wof:name":"Van Oprooy",
    "wof:placetype":"venue"
},
  "geometry": {"coordinates":[4.9410247803,51.3210716248],"type":"Point"}
}