{
  "type": "Feature",
  "properties": {
    "iso:country":"BE",
    "sg:address":"Rue Des Combattants 63",
    "sg:city":"La Hulpe",
    "sg:classifiers":[
        {
            "category":"Home & Garden",
            "subcategory":"Home Furnishings",
            "type":"Retail Goods"
        }
    ],
    "sg:phone":"+32 2 652 59 57",
    "sg:postcode":"1310",
    "sg:province":"Brabant Wallon",
    "sg:tags":[
        "lampshade",
        "chandelier",
        "-"
    ],
    "wof:name":"Jeu D'ombre",
    "wof:placetype":"venue"
},
  "geometry": {"coordinates":[4.4888081551,50.7311935425],"type":"Point"}
}