{
  "type": "Feature",
  "properties": {
    "iso:country":"BE",
    "sg:address":"Eug. De Grootelaan 46a",
    "sg:city":"Houthulst",
    "sg:classifiers":[
        {
            "category":"Health Services",
            "subcategory":"Health Practitioner",
            "type":"Services"
        }
    ],
    "sg:phone":"+32 51 70 03 53",
    "sg:postcode":"8650",
    "sg:province":"West-Vlaanderen",
    "sg:tags":[
        "physiotherapist"
    ],
    "wof:name":"Claus Katrien",
    "wof:placetype":"venue"
},
  "geometry": {"coordinates":[2.9535090923,50.9759140015],"type":"Point"}
}