{
  "type": "Feature",
  "properties": {
    "iso:country":"BE",
    "sg:address":"Zavelstraat 23",
    "sg:city":"Retie",
    "sg:classifiers":[
        {
            "category":"Building & Trades",
            "subcategory":"Plumbing",
            "type":"Services"
        }
    ],
    "sg:phone":"+32 14 37 98 17",
    "sg:postcode":"2470",
    "sg:province":"Antwerpen",
    "sg:tags":[
        "diver",
        "commerce",
        "gr",
        "pour",
        "equipement"
    ],
    "wof:name":"Mertens En Hertoghs",
    "wof:placetype":"venue"
},
  "geometry": {"coordinates":[5.06229496,51.2541351318],"type":"Point"}
}