{
  "type": "Feature",
  "properties": {
    "addr:full":"Rue Des Ecoles 1 Pont-a-celles Hainaut 6230",
    "addr:housenumber":"1",
    "addr:postcode":"6230",
    "addr:street":"Rue Des Ecoles",
    "iso:country":"BE",
    "sg:address":"Rue Des Ecoles 1",
    "sg:city":"Pont-a-celles",
    "sg:orig_category":"S\u00e9lection de personnel and placement",
    "sg:phone":"+32 71 84 91 91",
    "sg:postcode":"6230",
    "sg:province":"Hainaut",
    "wof:name":"S.l.a.i.e. Pont-\u00c0-celles",
    "wof:placetype":"venue"
},
  "geometry": {"coordinates":[4.3618497849,50.5119895935],"type":"Point"}
}