{
  "type": "Feature",
  "properties": {
    "addr:full":"Rue Nicolas Simonon 1a Herstal Li\u00e8ge 4040",
    "addr:housenumber":"1a",
    "addr:postcode":"4040",
    "addr:street":"Rue Nicolas Simonon",
    "iso:country":"BE",
    "sg:address":"Rue Nicolas Simonon 1a",
    "sg:city":"Herstal",
    "sg:classifiers":[
        {
            "category":"Home & Garden",
            "subcategory":"Home Furnishings",
            "type":"Retail Goods"
        }
    ],
    "sg:phone":"+32 4 248 30 32",
    "sg:postcode":"4040",
    "sg:province":"Li\u00e8ge",
    "sg:tags":[
        "-",
        "furniture"
    ],
    "wof:name":"Cds Product",
    "wof:placetype":"venue"
},
  "geometry": {"coordinates":[5.6214199066,50.6665992737],"type":"Point"}
}