{
  "type": "Feature",
  "properties": {
    "iso:country":"BE",
    "sg:address":"Place De Belle-maison 17",
    "sg:city":"Marchin",
    "sg:classifiers":[
        {
            "category":"Bars & Pubs",
            "type":"Food & Drink"
        }
    ],
    "sg:phone":"+32 85 21 31 04",
    "sg:postcode":"4570",
    "sg:province":"Li\u00e8ge",
    "wof:name":"Ruelle J.p.",
    "wof:placetype":"venue"
},
  "geometry": {"coordinates":[5.224366188,50.4815444946],"type":"Point"}
}