{
  "type": "Feature",
  "properties": {
    "addr:full":"Moerstraat 30 Gent Oost-Vlaanderen 9031",
    "addr:housenumber":"30",
    "addr:postcode":"9031",
    "addr:street":"Moerstraat;Oost-Vlaanderen",
    "iso:country":"BE",
    "sg:address":"Moerstraat 30",
    "sg:city":"Gent",
    "sg:orig_category":"Clubs de sport. Transports fluviaux",
    "sg:phone":"+32 9 282 26 27",
    "sg:postcode":"9031",
    "sg:province":"Oost-Vlaanderen",
    "wof:name":"Vaarcentrum Drongen",
    "wof:placetype":"venue"
},
  "geometry": {"coordinates":[3.6630249023,51.0503692627],"type":"Point"}
}