{
  "type": "Feature",
  "properties": {
    "iso:country":"BE",
    "sg:address":"Halve Stepsteenweg 6",
    "sg:city":"Gistel",
    "sg:orig_category":"Eleveurs and marchands de porcs. Eleveurs de bovins",
    "sg:phone":"+32 59 27 81 53",
    "sg:postcode":"8470",
    "sg:province":"West-Vlaanderen",
    "wof:name":"Herman Dehaemers",
    "wof:placetype":"venue"
},
  "geometry": {"coordinates":[2.9543480873,51.1416168213],"type":"Point"}
}