{
  "type": "Feature",
  "properties": {
    "iso:country":"BE",
    "sg:address":"Rue D\u00b4anthisnes 31",
    "sg:city":"Hamoir",
    "sg:orig_category":"Brood, gebak and snoepgoed",
    "sg:phone":"+32 86 38 81 62",
    "sg:postcode":"4180",
    "sg:province":"Li\u00e8ge",
    "wof:name":"Fr\u00c9d\u00c9ric Gilis",
    "wof:placetype":"venue"
},
  "geometry": {"coordinates":[5.538146019,50.4487495422],"type":"Point"}
}