{
  "type": "Feature",
  "properties": {
    "iso:country":"BE",
    "sg:address":"Longchamps 597",
    "sg:city":"Longchamps",
    "sg:classifiers":[
        {
            "category":"Retail",
            "subcategory":"Veterinary Services",
            "type":"Services"
        }
    ],
    "sg:phone":"+32 61 21 71 08",
    "sg:postcode":"6688",
    "sg:province":"Luxembourg",
    "sg:tags":[
        "veterinarian"
    ],
    "wof:name":"Aubry J",
    "wof:placetype":"venue"
},
  "geometry": {"coordinates":[5.6940789223,50.0549201965],"type":"Point"}
}