{
  "type": "Feature",
  "properties": {
    "addr:full":"Menenstraat 20 Moeskroen/mouscron Hainaut 7700",
    "addr:housenumber":"20",
    "addr:postcode":"7700",
    "addr:street":"Menenstraat",
    "iso:country":"BE",
    "sg:address":"Menenstraat 20",
    "sg:city":"Moeskroen/mouscron",
    "sg:orig_category":"Artsen and specialisten",
    "sg:phone":"+32 56 33 44 64",
    "sg:postcode":"7700",
    "sg:province":"Hainaut",
    "wof:name":"Joseph Leterme",
    "wof:placetype":"venue"
},
  "geometry": {"coordinates":[3.2323200703,50.7400932312],"type":"Point"}
}