{
  "type": "Feature",
  "properties": {
    "addr:full":"Steenweg Op Oosthoven 245 Turnhout Antwerpen 2300",
    "addr:housenumber":"245",
    "addr:postcode":"2300",
    "addr:street":"Steenweg Op Oosthoven",
    "iso:country":"BE",
    "sg:address":"Steenweg Op Oosthoven 245",
    "sg:city":"Turnhout",
    "sg:classifiers":[
        {
            "category":"Cafe",
            "type":"Food & Drink"
        }
    ],
    "sg:phone":"+32 14 42 61 79",
    "sg:postcode":"2300",
    "sg:province":"Antwerpen",
    "sg:tags":[
        "caf\u00e9s"
    ],
    "wof:name":"Cafe Oude Molen",
    "wof:placetype":"venue"
},
  "geometry": {"coordinates":[4.9590902328,51.3324928284],"type":"Point"}
}