{
  "type": "Feature",
  "properties": {
    "iso:country":"BE",
    "sg:address":"Eduard Dompasstraat 38-40",
    "sg:city":"Alken",
    "sg:orig_category":"Non-Classified Establishments",
    "sg:phone":"+32 11 59 10 37",
    "sg:postcode":"3570",
    "sg:province":"Limburg",
    "wof:name":"Vip-design Bvba",
    "wof:placetype":"venue"
},
  "geometry": {"coordinates":[5.2775998116,50.8718910217],"type":"Point"}
}