{
  "type": "Feature",
  "properties": {
    "addr:full":"Kapelstraat 3 Gooik Vlaams-Brabant 1755",
    "addr:housenumber":"3",
    "addr:postcode":"1755",
    "addr:street":"Kapelstraat",
    "iso:country":"BE",
    "sg:address":"Kapelstraat 3",
    "sg:city":"Gooik",
    "sg:orig_category":"Mat\u00e9riaux de construction Bois Gr. Quincailleries",
    "sg:phone":"+32 54 56 60 06",
    "sg:postcode":"1755",
    "sg:province":"Vlaams-Brabant",
    "wof:name":"Bouwmat D Dehandschutter",
    "wof:placetype":"venue"
},
  "geometry": {"coordinates":[4.0691051483,50.7756271362],"type":"Point"}
}