{
  "type": "Feature",
  "properties": {
    "iso:country":"BE",
    "sg:address":"En Hayeneux 173",
    "sg:city":"Herstal",
    "sg:classifiers":[
        {
            "category":"Manufacturing",
            "subcategory":"Metals",
            "type":"Manufacturing & Wholesale Goods"
        }
    ],
    "sg:phone":"+32 4 264 50 86",
    "sg:postcode":"4040",
    "sg:province":"Li\u00e8ge",
    "sg:tags":[
        "ironwork"
    ],
    "wof:name":"Fusaro & Piette Scrl",
    "wof:placetype":"venue"
},
  "geometry": {"coordinates":[5.6159009933,50.6561584473],"type":"Point"}
}