{
  "type": "Feature",
  "properties": {
    "iso:country":"BE",
    "sg:address":"Lovinfossestraat 8 H",
    "sg:city":"Waasmunster",
    "sg:orig_category":"Equipement divers pour commerces Installation de menuiserie en bois and plastique",
    "sg:phone":"+32 52 46 16 61",
    "sg:postcode":"9250",
    "sg:province":"Oost-Vlaanderen",
    "wof:name":"Rudy De Smet",
    "wof:placetype":"venue"
},
  "geometry": {"coordinates":[4.0877051353,51.1107292175],"type":"Point"}
}