{
  "type": "Feature",
  "properties": {
    "addr:full":"Ninoofsesteenweg 98a Pepingen Vlaams-Brabant 1670",
    "addr:housenumber":"98a",
    "addr:postcode":"1670",
    "addr:street":"Ninoofsesteenweg",
    "iso:country":"BE",
    "sg:address":"Ninoofsesteenweg 98a",
    "sg:city":"Pepingen",
    "sg:classifiers":[
        {
            "category":"Banks & Credit Unions",
            "subcategory":"Bank",
            "type":"Services"
        }
    ],
    "sg:phone":"+32 2 356 64 71",
    "sg:postcode":"1670",
    "sg:province":"Vlaams-Brabant",
    "sg:tags":[
        "savings-banks"
    ],
    "wof:name":"Cornelis Martine Bvba",
    "wof:placetype":"venue"
},
  "geometry": {"coordinates":[4.1613130569,50.7594337463],"type":"Point"}
}