{
  "type": "Feature",
  "properties": {
    "addr:full":"Rue Tillieux 43 Namur (jambes) Namur 5100",
    "addr:housenumber":"43",
    "addr:postcode":"5100",
    "addr:street":"Rue Tillieux",
    "iso:country":"BE",
    "sg:address":"Rue Tillieux 43",
    "sg:city":"Namur (jambes)",
    "sg:orig_category":"Newspapers, magazines, periodicals - Publishers",
    "sg:phone":"+32 81 30 28 35",
    "sg:postcode":"5100",
    "sg:province":"Namur",
    "wof:name":"Editions Du Confluent (edico) Sc",
    "wof:placetype":"venue"
},
  "geometry": {"coordinates":[4.8713750839,50.4566345215],"type":"Point"}
}