{
  "type": "Feature",
  "properties": {
    "addr:full":"Rue G\u00c9n\u00c9ral Michel 1 Namur Namur 5000",
    "addr:housenumber":"1",
    "addr:postcode":"5000",
    "addr:street":"Rue Ge\u0301Ne\u0301Ral Michel",
    "iso:country":"BE",
    "sg:address":"Rue G\u00c9n\u00c9ral Michel 1",
    "sg:city":"Namur",
    "sg:orig_category":"Verbruikerskredietinstellingen",
    "sg:phone":"+32 81 22 30 52",
    "sg:postcode":"5000",
    "sg:province":"Namur",
    "wof:name":"Agence Dujardin",
    "wof:placetype":"venue"
},
  "geometry": {"coordinates":[4.8706841469,50.4669189453],"type":"Point"}
}