{
  "type": "Feature",
  "properties": {
    "addr:full":"Rue Le Campinaire 353 Farciennes Hainaut 6240",
    "addr:housenumber":"353",
    "addr:postcode":"6240",
    "addr:street":"Rue Le Campinaire",
    "iso:country":"BE",
    "sg:address":"Rue Le Campinaire 353",
    "sg:city":"Farciennes",
    "sg:orig_category":"Benzinestations and brandstoffen HUISBRANDOLIE",
    "sg:phone":"+32 71 38 28 96",
    "sg:postcode":"6240",
    "sg:province":"Hainaut",
    "wof:name":"Esso",
    "wof:placetype":"venue"
},
  "geometry": {"coordinates":[4.5316309929,50.4424285889],"type":"Point"}
}