{
  "type": "Feature",
  "properties": {
    "iso:country":"BE",
    "sg:address":"Friedensstrasse 8",
    "sg:city":"Sankt Vith",
    "sg:classifiers":[
        {
            "category":"Professional",
            "subcategory":"Printing & Photocopies",
            "type":"Services"
        }
    ],
    "sg:phone":"+32 80 28 01 80",
    "sg:postcode":"4780",
    "sg:province":"Li\u00e8ge",
    "sg:tags":[
        "-",
        "offset"
    ],
    "wof:name":"Pro D & P Grafische Betriebe A.g.",
    "wof:placetype":"venue"
},
  "geometry": {"coordinates":[6.1235060692,50.2850570679],"type":"Point"}
}