{
  "type": "Feature",
  "properties": {
    "addr:full":"Karmelietenstraat 58 Ukkel/uccle Bruxelles-Capitale 1180",
    "addr:housenumber":"58",
    "addr:postcode":"1180",
    "addr:street":"Karmelietenstraat;/",
    "iso:country":"BE",
    "sg:address":"Karmelietenstraat 58",
    "sg:city":"Ukkel/uccle",
    "sg:orig_category":"Diverse producten Gh",
    "sg:phone":"+32 2 344 70 00",
    "sg:postcode":"1180",
    "sg:province":"Bruxelles-Capitale",
    "wof:name":"Ci Vandervelde & Co",
    "wof:placetype":"venue"
},
  "geometry": {"coordinates":[4.3410792351,50.8124961853],"type":"Point"}
}