{
  "type": "Feature",
  "properties": {
    "iso:country":"BE",
    "sg:address":"Onderwijsstraat 26",
    "sg:city":"Lommel",
    "sg:classifiers":[
        {
            "category":"Health Services",
            "subcategory":"Dentist",
            "type":"Services"
        }
    ],
    "sg:phone":"+32 11 54 46 69",
    "sg:postcode":"3920",
    "sg:province":"Limburg",
    "wof:name":"Jansen F",
    "wof:placetype":"venue"
},
  "geometry": {"coordinates":[5.3186411858,51.2264137268],"type":"Point"}
}