{
  "type": "Feature",
  "properties": {
    "addr:full":"Rue Hamoir 131 La Louvi\u00e8re Hainaut 7100",
    "addr:housenumber":"131",
    "addr:postcode":"7100",
    "addr:street":"Rue Hamoir",
    "iso:country":"BE",
    "sg:address":"Rue Hamoir 131",
    "sg:city":"La Louvi\u00e8re",
    "sg:classifiers":[
        {
            "category":"Retail",
            "subcategory":"Auto Repair",
            "type":"Services"
        }
    ],
    "sg:phone":"+32 64 22 51 74",
    "sg:postcode":"7100",
    "sg:province":"Hainaut",
    "sg:tags":[
        "garage"
    ],
    "wof:name":"Auto Jacky",
    "wof:placetype":"venue"
},
  "geometry": {"coordinates":[4.1946392059,50.47473526],"type":"Point"}
}