{
  "type": "Feature",
  "properties": {
    "iso:country":"BE",
    "sg:address":"Negenbunderdtraat 35",
    "sg:city":"Lennik",
    "sg:orig_category":"D\u00e9corateurs d'int\u00e9rieur",
    "sg:phone":"+32 2 532 22 29",
    "sg:postcode":"1750",
    "sg:province":"Vlaams-Brabant",
    "wof:name":"Heremans V.",
    "wof:placetype":"venue"
},
  "geometry": {"coordinates":[4.154654026,50.8054275513],"type":"Point"}
}