{
  "type": "Feature",
  "properties": {
    "addr:full":"Noordlaan 19 Zutendaal Limburg 3690",
    "addr:housenumber":"19",
    "addr:postcode":"3690",
    "addr:street":"Noordlaan",
    "iso:country":"BE",
    "sg:address":"Noordlaan 19",
    "sg:city":"Zutendaal",
    "sg:classifiers":[
        {
            "category":"Health Services",
            "subcategory":"Health Practitioner",
            "type":"Services"
        }
    ],
    "sg:phone":"+32 89 61 28 36",
    "sg:postcode":"3690",
    "sg:province":"Limburg",
    "sg:tags":[
        "physiotherapist"
    ],
    "wof:name":"Hubrechts Karin",
    "wof:placetype":"venue"
},
  "geometry": {"coordinates":[5.5564398766,50.954990387],"type":"Point"}
}