{
  "type": "Feature",
  "properties": {
    "addr:full":"Beke 159 Waarschoot Oost-Vlaanderen 9950",
    "addr:housenumber":"159",
    "addr:postcode":"9950",
    "addr:street":"Beke",
    "iso:country":"BE",
    "sg:address":"Beke 159",
    "sg:city":"Waarschoot",
    "sg:orig_category":"Benzinestations and brandstoffen Herstellingen and onderhoud aan huis voor voertuigen Herstellingen ",
    "sg:phone":"+32 9 372 54 03",
    "sg:postcode":"9950",
    "sg:province":"Oost-Vlaanderen",
    "wof:name":"Fa. Vlaeminck R.",
    "wof:placetype":"venue"
},
  "geometry": {"coordinates":[3.6049799919,51.1305389404],"type":"Point"}
}