{
  "type": "Feature",
  "properties": {
    "iso:country":"BE",
    "sg:address":"Beukenootjesstraat 25",
    "sg:city":"Brussel/bruxelles",
    "sg:orig_category":"Foto-uitrusting Fotografen and fotostudio's",
    "sg:phone":"+32 2 268 41 28",
    "sg:postcode":"1120",
    "sg:province":"Bruxelles-Capitale",
    "wof:name":"Roger Coulon",
    "wof:placetype":"venue"
},
  "geometry": {"coordinates":[4.3936729431,50.8945083618],"type":"Point"}
}