{
  "type": "Feature",
  "properties": {
    "iso:country":"BE",
    "sg:address":"Zwevegemstraat 69",
    "sg:city":"Zwevegem",
    "sg:orig_category":"Sportclubs",
    "sg:phone":"+32 56 77 92 71",
    "sg:postcode":"8553",
    "sg:province":"West-Vlaanderen",
    "wof:name":"W.c. Otegem Boven",
    "wof:placetype":"venue"
},
  "geometry": {"coordinates":[3.4159889221,50.8094558716],"type":"Point"}
}