{
  "type": "Feature",
  "properties": {
    "iso:country":"BE",
    "sg:address":"Livornostraat 59",
    "sg:city":"Elsene/ixelles",
    "sg:classifiers":[
        {
            "category":"Cafe",
            "type":"Food & Drink"
        }
    ],
    "sg:phone":"+32 2 538 64 29",
    "sg:postcode":"1050",
    "sg:province":"Bruxelles-Capitale",
    "sg:tags":[
        "caf\u00e9s"
    ],
    "wof:name":"Le Livourne",
    "wof:placetype":"venue"
},
  "geometry": {"coordinates":[4.3597230911,50.8290481567],"type":"Point"}
}