{
  "type": "Feature",
  "properties": {
    "addr:full":"Rue Fran\u00c7ois Lapierre 2b6 Fleron Li\u00e8ge 4620",
    "addr:housenumber":"2b6",
    "addr:postcode":"4620",
    "addr:street":"Rue Franc\u0327Ois Lapierre",
    "iso:country":"BE",
    "sg:address":"Rue Fran\u00c7ois Lapierre 2b6",
    "sg:city":"Fleron",
    "sg:orig_category":"Kapsalons",
    "sg:phone":"+32 4 358 50 66",
    "sg:postcode":"4620",
    "sg:province":"Li\u00e8ge",
    "wof:name":"Coiffure Creastyl",
    "wof:placetype":"venue"
},
  "geometry": {"coordinates":[5.6820878983,50.6148719788],"type":"Point"}
}