{
  "type": "Feature",
  "properties": {
    "addr:full":"Heirbaan 120 Beveren Oost-Vlaanderen 9120",
    "addr:housenumber":"120",
    "addr:postcode":"9120",
    "addr:street":"Heirbaan",
    "iso:country":"BE",
    "sg:address":"Heirbaan 120",
    "sg:city":"Beveren",
    "sg:orig_category":"Producteurs de fruits",
    "sg:phone":"+32 3 755 18 22",
    "sg:postcode":"9120",
    "sg:province":"Oost-Vlaanderen",
    "wof:name":"Johan Hens",
    "wof:placetype":"venue"
},
  "geometry": {"coordinates":[4.280272007,51.1862716675],"type":"Point"}
}