{
  "type": "Feature",
  "properties": {
    "addr:full":"Rue De La Briqueterie 87 Bruxelles Bruxelles-Capitale 1020",
    "addr:housenumber":"87",
    "addr:postcode":"1020",
    "addr:street":"Rue De La Briqueterie",
    "iso:country":"BE",
    "sg:address":"Rue De La Briqueterie 87",
    "sg:city":"Bruxelles",
    "sg:classifiers":[
        {
            "category":"Building & Trades",
            "subcategory":"Pest Control",
            "type":"Services"
        }
    ],
    "sg:phone":"+32 2 426 16 41",
    "sg:postcode":"1020",
    "sg:province":"Bruxelles-Capitale",
    "sg:tags":[
        "painting",
        "contractor"
    ],
    "wof:name":"Marquez & Cuelvas",
    "wof:placetype":"venue"
},
  "geometry": {"coordinates":[4.3491530418,50.873210907],"type":"Point"}
}