{
  "type": "Feature",
  "properties": {
    "iso:country":"BE",
    "sg:address":"Woudweg Naar Zedelgem 3",
    "sg:city":"Jabbeke (snellegem)",
    "sg:classifiers":[
        {
            "category":"Building & Trades",
            "subcategory":"Construction",
            "type":"Services"
        }
    ],
    "sg:phone":"+32 50 81 21 26",
    "sg:postcode":"8490",
    "sg:province":"West-Vlaanderen",
    "sg:tags":[
        "carpenter"
    ],
    "wof:name":"Becue A",
    "wof:placetype":"venue"
},
  "geometry": {"coordinates":[3.1132640839,51.1656837463],"type":"Point"}
}