{
  "type": "Feature",
  "properties": {
    "addr:full":"Rue De Coubry 12 Gedinne (willerzie) Namur 5575",
    "addr:housenumber":"12",
    "addr:postcode":"5575",
    "addr:street":"Rue De Coubry",
    "iso:country":"BE",
    "sg:address":"Rue De Coubry 12",
    "sg:city":"Gedinne (willerzie)",
    "sg:classifiers":[
        {
            "category":"Government",
            "subcategory":"Department Of Motor Vehicles",
            "type":"Public Place"
        }
    ],
    "sg:phone":"+32 61 58 85 23",
    "sg:postcode":"5575",
    "sg:province":"Namur",
    "sg:tags":[
        "planing",
        "wood",
        "sawing"
    ],
    "wof:name":"Scierie De Willerzie",
    "wof:placetype":"venue"
},
  "geometry": {"coordinates":[4.8498411179,49.9874038696],"type":"Point"}
}