{
  "type": "Feature",
  "properties": {
    "addr:full":"Rue Fran\u00e7ois Lapierre 25 Fl\u00e9ron Li\u00e8ge 4620",
    "addr:housenumber":"25",
    "addr:postcode":"4620",
    "addr:street":"Rue Franc\u0327Ois Lapierre",
    "iso:country":"BE",
    "sg:address":"Rue Fran\u00e7ois Lapierre 25",
    "sg:city":"Fl\u00e9ron",
    "sg:classifiers":[
        {
            "category":"Structure",
            "subcategory":"Office Building",
            "type":"Public Place"
        }
    ],
    "sg:phone":"+32 4 358 88 29",
    "sg:postcode":"4620",
    "sg:province":"Li\u00e8ge",
    "sg:tags":[
        "roofing",
        "slate"
    ],
    "wof:name":"Hanquet C",
    "wof:placetype":"venue"
},
  "geometry": {"coordinates":[5.681330204,50.6178207397],"type":"Point"}
}