{
  "type": "Feature",
  "properties": {
    "addr:full":"Vinave D'ile 21 Li\u00c8ge Li\u00e8ge 4000",
    "addr:housenumber":"21",
    "addr:postcode":"4000",
    "addr:street":"Vinave D'Ile",
    "iso:country":"BE",
    "sg:address":"Vinave D'ile 21",
    "sg:city":"Li\u00c8ge",
    "sg:classifiers":[
        {
            "category":"Shopping",
            "subcategory":"Clothing, Apparel, & Fashions",
            "type":"Retail Goods"
        }
    ],
    "sg:phone":"+32 4 223 08 12",
    "sg:postcode":"4000",
    "sg:province":"Li\u00e8ge",
    "sg:tags":[
        "v\u00eatements",
        "pour",
        "dame"
    ],
    "wof:name":"M&s Mode",
    "wof:placetype":"venue"
},
  "geometry": {"coordinates":[5.5714139938,50.6415901184],"type":"Point"}
}