{
  "type": "Feature",
  "properties": {
    "iso:country":"BE",
    "sg:address":"Wijnbergstraat 9",
    "sg:city":"Wevelgem",
    "sg:orig_category":"Artiesten and kunstenaars",
    "sg:phone":"+32 56 41 39 89",
    "sg:postcode":"8560",
    "sg:province":"West-Vlaanderen",
    "wof:name":"Vandendriessche",
    "wof:placetype":"venue"
},
  "geometry": {"coordinates":[3.1757850647,50.8183631897],"type":"Point"}
}