{
  "type": "Feature",
  "properties": {
    "iso:country":"BE",
    "sg:address":"Rue Du Seize Pieds 4",
    "sg:city":"Profondeville",
    "sg:orig_category":"Traitements param\u00e9dicaux",
    "sg:phone":"+32 81 43 48 49",
    "sg:postcode":"5170",
    "sg:province":"Namur",
    "wof:name":"Anne Lecomte",
    "wof:placetype":"venue"
},
  "geometry": {"coordinates":[4.8045477867,50.3861618042],"type":"Point"}
}