{
  "type": "Feature",
  "properties": {
    "addr:full":"Assenedestraat 18 Assenede Oost-Vlaanderen 9968",
    "addr:housenumber":"18",
    "addr:postcode":"9968",
    "addr:street":"Assenedestraat",
    "iso:country":"BE",
    "sg:address":"Assenedestraat 18",
    "sg:city":"Assenede",
    "sg:orig_category":"Enseignement maternel and primaire",
    "sg:phone":"+32 9 323 92 36",
    "sg:postcode":"9968",
    "sg:province":"Oost-Vlaanderen",
    "wof:name":"Vrije Basisschool",
    "wof:placetype":"venue"
},
  "geometry": {"coordinates":[3.6887938976,51.1923027039],"type":"Point"}
}