{
  "type": "Feature",
  "properties": {
    "iso:country":"BE",
    "sg:address":"Rue Tasiaux 83b2",
    "sg:city":"Bastogne",
    "sg:orig_category":"Woningbouw",
    "sg:phone":"+32 61 21 92 89",
    "sg:postcode":"6600",
    "sg:province":"Luxembourg",
    "wof:name":"William Collard",
    "wof:placetype":"venue"
},
  "geometry": {"coordinates":[5.7086119652,49.999961853],"type":"Point"}
}