{
  "type": "Feature",
  "properties": {
    "iso:country":"BE",
    "sg:address":"Vaubanstraat 66",
    "sg:city":"Ieper",
    "sg:orig_category":"Experts-comptables",
    "sg:phone":"+32 57 20 78 71",
    "sg:postcode":"8900",
    "sg:province":"West-Vlaanderen",
    "wof:name":"Leonnel Couwet",
    "wof:placetype":"venue"
},
  "geometry": {"coordinates":[2.898250103,50.8490219116],"type":"Point"}
}