{
  "type": "Feature",
  "properties": {
    "iso:country":"BE",
    "sg:address":"Chauss\u00c9e De Bruxelles 211",
    "sg:city":"Nivelles",
    "sg:orig_category":"Eleveurs de bovins",
    "sg:phone":"+32 67 21 36 54",
    "sg:postcode":"1401",
    "sg:province":"Brabant Wallon",
    "wof:name":"Louis Piret",
    "wof:placetype":"venue"
},
  "geometry": {"coordinates":[4.34395504,50.6202888489],"type":"Point"}
}