{
  "type": "Feature",
  "properties": {
    "addr:full":"Wittestraat 25 Tielt West-Vlaanderen 8700",
    "addr:housenumber":"25",
    "addr:postcode":"8700",
    "addr:street":"Wittestraat",
    "iso:country":"BE",
    "sg:address":"Wittestraat 25",
    "sg:city":"Tielt",
    "sg:orig_category":"Woningbouw",
    "sg:phone":"+32 51 40 54 50",
    "sg:postcode":"8700",
    "sg:province":"West-Vlaanderen",
    "wof:name":"Andy Demeyere",
    "wof:placetype":"venue"
},
  "geometry": {"coordinates":[3.3234379292,50.9906463623],"type":"Point"}
}