{
  "type": "Feature",
  "properties": {
    "addr:full":"Bondgenotenlaan 117 Leuven Vlaams-Brabant 3000",
    "addr:housenumber":"117",
    "addr:postcode":"3000",
    "addr:street":"Bondgenotenlaan",
    "iso:country":"BE",
    "sg:address":"Bondgenotenlaan 117",
    "sg:city":"Leuven",
    "sg:orig_category":"Agences immobili\u00e8res. Administration d'immeubles. G\u00e9om\u00e8tres",
    "sg:phone":"+32 16 22 31 72",
    "sg:postcode":"3000",
    "sg:province":"Vlaams-Brabant",
    "wof:name":"Studiebureel Soetewey",
    "wof:placetype":"venue"
},
  "geometry": {"coordinates":[4.710714817,50.8806762695],"type":"Point"}
}