{
  "type": "Feature",
  "properties": {
    "iso:country":"BE",
    "sg:address":"Wiekevorstseweg 37",
    "sg:city":"Herentals",
    "sg:orig_category":"Rundveehouders",
    "sg:phone":"+32 14 26 10 90",
    "sg:postcode":"2200",
    "sg:province":"Antwerpen",
    "wof:name":"Dominicus Biermans",
    "wof:placetype":"venue"
},
  "geometry": {"coordinates":[4.8104810715,51.1134910583],"type":"Point"}
}