{
  "type": "Feature",
  "properties": {
    "addr:full":"Zuidleiestraat 10ba Knesselare Oost-Vlaanderen 9910",
    "addr:housenumber":"10ba",
    "addr:postcode":"9910",
    "addr:street":"Zuidleiestraat;Oost-Vlaanderen",
    "iso:country":"BE",
    "sg:address":"Zuidleiestraat 10ba",
    "sg:city":"Knesselare",
    "sg:orig_category":"Eleveurs de bovins",
    "sg:phone":"+32 9 374 19 44",
    "sg:postcode":"9910",
    "sg:province":"Oost-Vlaanderen",
    "wof:name":"Robert Wittevrongel",
    "wof:placetype":"venue"
},
  "geometry": {"coordinates":[3.3921809196,51.1177482605],"type":"Point"}
}