{
  "type": "Feature",
  "properties": {
    "iso:country":"BE",
    "sg:address":"Rue De L' Esplanade 54",
    "sg:city":"Banneux",
    "sg:orig_category":"Kleding, schoenen and accessoires Gh Postzegels, munten and trofee\u00ebn Sport- and kampeermateriaal",
    "sg:phone":"+32 4 360 81 44",
    "sg:postcode":"4141",
    "sg:province":"Li\u00e8ge",
    "wof:name":"Marksports",
    "wof:placetype":"venue"
},
  "geometry": {"coordinates":[5.7438211441,50.5385971069],"type":"Point"}
}