{
  "type": "Feature",
  "properties": {
    "addr:full":"Galerie Du Centre 57 Bruxelles Bruxelles-Capitale 1000",
    "addr:housenumber":"57",
    "addr:postcode":"1000",
    "addr:street":"Galerie Du Centre",
    "iso:country":"BE",
    "sg:address":"Galerie Du Centre 57",
    "sg:city":"Bruxelles",
    "sg:classifiers":[
        {
            "category":"Cinema",
            "subcategory":"Movie Theater",
            "type":"Entertainment"
        }
    ],
    "sg:phone":"+32 2 219 17 48",
    "sg:postcode":"1000",
    "sg:province":"Bruxelles-Capitale",
    "wof:name":"Aventure",
    "wof:placetype":"venue"
},
  "geometry": {"coordinates":[4.3531398773,50.8482093811],"type":"Point"}
}