{
  "type": "Feature",
  "properties": {
    "addr:full":"Karel Coggelaan 6 Veurne West-Vlaanderen 8630",
    "addr:housenumber":"6",
    "addr:postcode":"8630",
    "addr:street":"Karel Coggelaan",
    "iso:country":"BE",
    "sg:address":"Karel Coggelaan 6",
    "sg:city":"Veurne",
    "sg:classifiers":[
        {
            "category":"Home & Garden",
            "subcategory":"Building Materials",
            "type":"Retail Goods"
        }
    ],
    "sg:phone":"+32 58 31 13 93",
    "sg:postcode":"8630",
    "sg:province":"West-Vlaanderen",
    "sg:tags":[
        "granite",
        "stone",
        "natural",
        "marble"
    ],
    "wof:name":"Bailleul",
    "wof:placetype":"venue"
},
  "geometry": {"coordinates":[2.666426897,51.072353363],"type":"Point"}
}