{
  "type": "Feature",
  "properties": {
    "iso:country":"BE",
    "sg:address":"Lissewegestraat 19",
    "sg:city":"Blankenberge (uitkerke)",
    "sg:classifiers":[
        {
            "category":"Farming",
            "subcategory":"Farm & Veterinary Services",
            "type":"Manufacturing & Wholesale Goods"
        }
    ],
    "sg:phone":"+32 50 41 57 80",
    "sg:postcode":"8370",
    "sg:province":"West-Vlaanderen",
    "sg:tags":[
        "agricultural",
        "contractor"
    ],
    "wof:name":"Witgeers G",
    "wof:placetype":"venue"
},
  "geometry": {"coordinates":[3.1468889713,51.3055381775],"type":"Point"}
}