{
  "type": "Feature",
  "properties": {
    "addr:full":"Rue De L'eglise 31 Montigny-le-tilleul Hainaut 6110",
    "addr:housenumber":"31",
    "addr:postcode":"6110",
    "addr:street":"Rue De L'Eglise",
    "iso:country":"BE",
    "sg:address":"Rue De L'eglise 31",
    "sg:city":"Montigny-le-tilleul",
    "sg:classifiers":[
        {
            "category":"Professional",
            "subcategory":"Management & Consulting",
            "type":"Services"
        }
    ],
    "sg:phone":"+32 71 56 24 51",
    "sg:postcode":"6110",
    "sg:province":"Hainaut",
    "sg:tags":[
        "consultant",
        "agency",
        "advertising"
    ],
    "wof:name":"Business Advices",
    "wof:placetype":"venue"
},
  "geometry": {"coordinates":[4.3794469833,50.3786010742],"type":"Point"}
}