{
  "type": "Feature",
  "properties": {
    "addr:full":"Rue De Clairefontaine 1 Arlon Luxembourg 6700",
    "addr:housenumber":"1",
    "addr:postcode":"6700",
    "addr:street":"Rue De Clairefontaine",
    "iso:country":"BE",
    "sg:address":"Rue De Clairefontaine 1",
    "sg:city":"Arlon",
    "sg:orig_category":"Supermarkten Telecommunicatieapparaten",
    "sg:phone":"+32 63 23 06 11",
    "sg:postcode":"6700",
    "sg:province":"Luxembourg",
    "wof:name":"Carrefour - Maxitec",
    "wof:placetype":"venue"
},
  "geometry": {"coordinates":[5.8227000237,49.6778907776],"type":"Point"}
}