{
  "type": "Feature",
  "properties": {
    "iso:country":"BE",
    "sg:address":"Rue Du Grand Jour 62",
    "sg:city":"Jurbise",
    "sg:orig_category":"Jardinage",
    "sg:phone":"+32 65 22 80 55",
    "sg:postcode":"7050",
    "sg:province":"Hainaut",
    "wof:name":"Anrys",
    "wof:placetype":"venue"
},
  "geometry": {"coordinates":[3.9346199036,50.5057411194],"type":"Point"}
}