{
  "type": "Feature",
  "properties": {
    "addr:full":"Rue Zeecrabbe 85b5 Ukkel/uccle Bruxelles-Capitale 1180",
    "addr:housenumber":"85b5",
    "addr:postcode":"1180",
    "addr:street":"Rue Zeecrabbe;/",
    "iso:country":"BE",
    "sg:address":"Rue Zeecrabbe 85b5",
    "sg:city":"Ukkel/uccle",
    "sg:orig_category":"Location d'appareils audio-visuels",
    "sg:phone":"+32 475 70 16 27",
    "sg:postcode":"1180",
    "sg:province":"Bruxelles-Capitale",
    "wof:name":"Audio Light System",
    "wof:placetype":"venue"
},
  "geometry": {"coordinates":[4.3574681282,50.8061447144],"type":"Point"}
}