{
  "type": "Feature",
  "properties": {
    "iso:country":"BE",
    "sg:address":"Oude Bruggestraat 27",
    "sg:city":"Wingene",
    "sg:classifiers":[
        {
            "category":"Personal",
            "subcategory":"Beauty Salon",
            "type":"Services"
        }
    ],
    "sg:phone":"+32 51 65 52 31",
    "sg:postcode":"8750",
    "sg:province":"West-Vlaanderen",
    "sg:tags":[
        "de",
        "coiffure"
    ],
    "wof:name":"Marc Vanseveren",
    "wof:placetype":"venue"
},
  "geometry": {"coordinates":[3.2766749859,51.0581245422],"type":"Point"}
}