{
  "type": "Feature",
  "properties": {
    "iso:country":"BE",
    "sg:address":"Nieuwstraat 64b5",
    "sg:city":"Wevelgem",
    "sg:classifiers":[
        {
            "category":"Manufacturing",
            "subcategory":"Textiles",
            "type":"Manufacturing & Wholesale Goods"
        }
    ],
    "sg:phone":"+32 56 42 43 51",
    "sg:postcode":"8560",
    "sg:province":"West-Vlaanderen",
    "wof:name":"Fa. Textilux",
    "wof:placetype":"venue"
},
  "geometry": {"coordinates":[3.177834034,50.8113555908],"type":"Point"}
}