{
  "type": "Feature",
  "properties": {
    "iso:country":"BE",
    "sg:address":"Waterkasteelstraat 2",
    "sg:city":"Blankenberge",
    "sg:orig_category":"DIVERSE RECREATIEVE ACTIVITEITEN",
    "sg:phone":"+32 50 41 46 26",
    "sg:postcode":"8370",
    "sg:province":"West-Vlaanderen",
    "wof:name":"Bridge Club",
    "wof:placetype":"venue"
},
  "geometry": {"coordinates":[3.1216609478,51.3117218018],"type":"Point"}
}