{
  "type": "Feature",
  "properties": {
    "addr:full":"Willem Huveneersstraat 5 Hasselt Limburg 3500",
    "addr:housenumber":"5",
    "addr:postcode":"3500",
    "addr:street":"Willem Huveneersstraat",
    "iso:country":"BE",
    "sg:address":"Willem Huveneersstraat 5",
    "sg:city":"Hasselt",
    "sg:orig_category":"Tankcleaning",
    "sg:phone":"+32 11 27 58 92",
    "sg:postcode":"3500",
    "sg:province":"Limburg",
    "wof:name":"Euro Cleaning",
    "wof:placetype":"venue"
},
  "geometry": {"coordinates":[5.3244562149,50.9119491577],"type":"Point"}
}