{
  "type": "Feature",
  "properties": {
    "iso:country":"BE",
    "sg:address":"Boulevard G\u00c9n\u00c9ral Jacques 116",
    "sg:city":"Elsene/ixelles",
    "sg:classifiers":[
        {
            "category":"Restaurant",
            "type":"Food & Drink"
        }
    ],
    "sg:phone":"+32 2 646 10 98",
    "sg:postcode":"1050",
    "sg:province":"Bruxelles-Capitale",
    "wof:name":"Fougeres",
    "wof:placetype":"venue"
},
  "geometry": {"coordinates":[4.3816127777,50.8198013306],"type":"Point"}
}