{
  "type": "Feature",
  "properties": {
    "addr:full":"Avenue Des Combattants 68 Court-saint-etienne Brabant Wallon 1490",
    "addr:housenumber":"68;1490",
    "addr:street":"Avenue Des Combattants",
    "iso:country":"BE",
    "sg:address":"Avenue Des Combattants 68",
    "sg:city":"Court-saint-etienne",
    "sg:classifiers":[
        {
            "category":"Fast Food",
            "type":"Food & Drink"
        }
    ],
    "sg:phone":"+32 10 61 37 19",
    "sg:postcode":"1490",
    "sg:province":"Brabant Wallon",
    "sg:tags":[
        "meeneem",
        "restaurant"
    ],
    "wof:name":"La Primavera",
    "wof:placetype":"venue"
},
  "geometry": {"coordinates":[4.5626320839,50.6477127075],"type":"Point"}
}