{
  "type": "Feature",
  "properties": {
    "iso:country":"BE",
    "sg:address":"Tervuursesteenweg 148",
    "sg:city":"Steenokkerzeel",
    "sg:classifiers":[
        {
            "category":"Insurance",
            "subcategory":"Life Insurance",
            "type":"Services"
        }
    ],
    "sg:phone":"+32 2 751 94 60",
    "sg:postcode":"1820",
    "sg:province":"Vlaams-Brabant",
    "sg:tags":[
        "assurance"
    ],
    "wof:name":"Vervloet",
    "wof:placetype":"venue"
},
  "geometry": {"coordinates":[4.4991898537,50.9219589233],"type":"Point"}
}