{
  "type": "Feature",
  "properties": {
    "iso:country":"BE",
    "sg:address":"Hoedenmakersstraat 12",
    "sg:city":"Brugge",
    "sg:orig_category":"Woningbouw",
    "sg:phone":"+32 50 34 06 89",
    "sg:postcode":"8000",
    "sg:province":"West-Vlaanderen",
    "wof:name":"Jan Roels",
    "wof:placetype":"venue"
},
  "geometry": {"coordinates":[3.2250699997,51.2143173218],"type":"Point"}
}