{
  "type": "Feature",
  "properties": {
    "addr:full":"Rue Albert Ier 60 Jemeppe-sur-sambre (ham-sur-sambre) Namur 5190",
    "addr:housenumber":"60",
    "addr:postcode":"5190",
    "addr:street":"Rue Albert Ier;Ham-Sur-Sambre",
    "iso:country":"BE",
    "sg:address":"Rue Albert Ier 60",
    "sg:city":"Jemeppe-sur-sambre (ham-sur-sambre)",
    "sg:classifiers":[
        {
            "category":"Banks & Credit Unions",
            "subcategory":"Investment Brokerage",
            "type":"Services"
        }
    ],
    "sg:phone":"+32 71 78 85 30",
    "sg:postcode":"5190",
    "sg:province":"Namur",
    "sg:tags":[
        "repair",
        "-",
        "installation",
        "sanitary",
        "article"
    ],
    "wof:name":"Gafob Sprl-gaye Eric",
    "wof:placetype":"venue"
},
  "geometry": {"coordinates":[4.6703448296,50.4645042419],"type":"Point"}
}