{
  "type": "Feature",
  "properties": {
    "iso:country":"BE",
    "sg:address":"Burg. J. Van Aperenstr. 20",
    "sg:city":"Hoogstraten",
    "sg:orig_category":"Experts-comptables",
    "sg:phone":"+32 3 314 86 65",
    "sg:postcode":"2320",
    "sg:province":"Antwerpen",
    "wof:name":"Guy Ansoms",
    "wof:placetype":"venue"
},
  "geometry": {"coordinates":[4.7574038506,51.4000816345],"type":"Point"}
}