{
  "type": "Feature",
  "properties": {
    "addr:full":"Rue De La Papeterie 13 Andenne Namur 5300",
    "addr:housenumber":"13",
    "addr:postcode":"5300",
    "addr:street":"Rue De La Papeterie",
    "iso:country":"BE",
    "sg:address":"Rue De La Papeterie 13",
    "sg:city":"Andenne",
    "sg:orig_category":"HERSTELLING ELEKTRISCHE HUISHOUDAPPARATEN Huishoudapparaten, televisies and radio's",
    "sg:phone":"+32 85 84 65 31",
    "sg:postcode":"5300",
    "sg:province":"Namur",
    "wof:name":"Kr\u00cbfel",
    "wof:placetype":"venue"
},
  "geometry": {"coordinates":[5.0924301147,50.4915122986],"type":"Point"}
}