{
  "type": "Feature",
  "properties": {
    "addr:full":"Lammerdries 32 Olen Antwerpen 2250",
    "addr:housenumber":"32",
    "addr:postcode":"2250",
    "addr:street":"Lammerdries",
    "iso:country":"BE",
    "sg:address":"Lammerdries 32",
    "sg:city":"Olen",
    "sg:orig_category":"Agences en douane",
    "sg:phone":"+32 14 25 81 29",
    "sg:postcode":"2250",
    "sg:province":"Antwerpen",
    "wof:name":"T.i.r. Services",
    "wof:placetype":"venue"
},
  "geometry": {"coordinates":[4.911948204,51.1497344971],"type":"Point"}
}