{
  "type": "Feature",
  "properties": {
    "addr:full":"Rue Kessels 77 Bruxelles (schaerbeek) Bruxelles-Capitale 1030",
    "addr:housenumber":"77",
    "addr:postcode":"1030",
    "addr:street":"Rue Kessels",
    "iso:country":"BE",
    "sg:address":"Rue Kessels 77",
    "sg:city":"Bruxelles (schaerbeek)",
    "sg:classifiers":[
        {
            "category":"Food & Beverages",
            "subcategory":"Groceries & Convenience Stores",
            "type":"Retail Goods"
        }
    ],
    "sg:phone":"+32 2 215 33 63",
    "sg:postcode":"1030",
    "sg:province":"Bruxelles-Capitale",
    "sg:tags":[
        "grocer"
    ],
    "wof:name":"Abimed Bvba",
    "wof:placetype":"venue"
},
  "geometry": {"coordinates":[4.377093792,50.863243103],"type":"Point"}
}