{
  "type": "Feature",
  "properties": {
    "addr:full":"Burchtstraat 1 Aalst Oost-Vlaanderen 9300",
    "addr:housenumber":"1",
    "addr:postcode":"9300",
    "addr:street":"Burchtstraat",
    "iso:country":"BE",
    "sg:address":"Burchtstraat 1",
    "sg:city":"Aalst",
    "sg:classifiers":[
        {
            "category":"Real Estate",
            "subcategory":"Developer",
            "type":"Services"
        }
    ],
    "sg:phone":"+32 53 21 22 47",
    "sg:postcode":"9300",
    "sg:province":"Oost-Vlaanderen",
    "sg:tags":[
        "project"
    ],
    "wof:name":"Hbc",
    "wof:placetype":"venue"
},
  "geometry": {"coordinates":[4.0437579155,50.9397201538],"type":"Point"}
}