{
  "type": "Feature",
  "properties": {
    "addr:full":"Rue Des Bruy\u00c8res 199 Eghezee Namur 5310",
    "addr:housenumber":"199",
    "addr:postcode":"5310",
    "addr:street":"Rue Des Bruye\u0300Res;Namur",
    "iso:country":"BE",
    "sg:address":"Rue Des Bruy\u00c8res 199",
    "sg:city":"Eghezee",
    "sg:orig_category":"Diverse meubelen Fab MEUBELONTWERP AND -INSTALLATIE",
    "sg:phone":"+32 81 51 37 67",
    "sg:postcode":"5310",
    "sg:province":"Namur",
    "wof:name":"Dupont",
    "wof:placetype":"venue"
},
  "geometry": {"coordinates":[4.8972501755,50.5377616882],"type":"Point"}
}