{
  "type": "Feature",
  "properties": {
    "addr:full":"Gr. De Smet De Naeyerln 19 Oostende West-Vlaanderen 8400",
    "addr:housenumber":"19",
    "addr:postcode":"8400",
    "addr:street":"Gr. De Smet De Naeyerln",
    "iso:country":"BE",
    "sg:address":"Gr. De Smet De Naeyerln 19",
    "sg:city":"Oostende",
    "sg:classifiers":[
        {
            "category":"Cafe",
            "type":"Food & Drink"
        }
    ],
    "sg:phone":"+32 59 51 31 51",
    "sg:postcode":"8400",
    "sg:province":"West-Vlaanderen",
    "sg:tags":[
        "caf\u00e9s"
    ],
    "wof:name":"Theatercaf\u00c9 De Illusie",
    "wof:placetype":"venue"
},
  "geometry": {"coordinates":[2.92374897,51.2256584167],"type":"Point"}
}