{
  "type": "Feature",
  "properties": {
    "addr:full":"Kerkhofstraat 16 Kinrooi Limburg 3640",
    "addr:housenumber":"16",
    "addr:postcode":"3640",
    "addr:street":"Kerkhofstraat",
    "iso:country":"BE",
    "sg:address":"Kerkhofstraat 16",
    "sg:city":"Kinrooi",
    "sg:classifiers":[
        {
            "category":"Building & Trades",
            "subcategory":"Construction",
            "type":"Services"
        }
    ],
    "sg:phone":"+32 89 70 22 65",
    "sg:postcode":"3640",
    "sg:province":"Limburg",
    "sg:tags":[
        "stucco",
        "contractor"
    ],
    "wof:name":"Houben L",
    "wof:placetype":"venue"
},
  "geometry": {"coordinates":[5.7359499931,51.1472206116],"type":"Point"}
}