{
  "type": "Feature",
  "properties": {
    "iso:country":"BE",
    "sg:address":"Dr. Haubenlaan 19",
    "sg:city":"Maasmechelen",
    "sg:orig_category":"Cr\u00e9dits divers",
    "sg:postcode":"3630",
    "sg:province":"Limburg",
    "wof:name":"Postomat Maasmechelen",
    "wof:placetype":"venue"
},
  "geometry": {"coordinates":[5.6977601051,50.9632301331],"type":"Point"}
}