{
  "type": "Feature",
  "properties": {
    "addr:full":"Assesteenweg 115 Ternat Vlaams-Brabant 1740",
    "addr:housenumber":"115",
    "addr:postcode":"1740",
    "addr:street":"Assesteenweg",
    "iso:country":"BE",
    "sg:address":"Assesteenweg 115",
    "sg:city":"Ternat",
    "sg:classifiers":[
        {
            "category":"Farming",
            "subcategory":"Livestock Farm",
            "type":"Manufacturing & Wholesale Goods"
        }
    ],
    "sg:phone":"+32 71 84 41 97",
    "sg:postcode":"1740",
    "sg:province":"Vlaams-Brabant",
    "sg:tags":[
        "horticulture",
        "product",
        "food",
        "related",
        "animal",
        "breeding",
        "agriculture"
    ],
    "wof:name":"Sibille Sa",
    "wof:placetype":"venue"
},
  "geometry": {"coordinates":[4.3552980423,50.5144042969],"type":"Point"}
}