{
  "type": "Feature",
  "properties": {
    "addr:full":"Chauss\u00c9e De Dieleghem 18 Jette Bruxelles-Capitale 1090",
    "addr:housenumber":"18",
    "addr:postcode":"1090",
    "addr:street":"Chausse\u0301E De Dieleghem",
    "iso:country":"BE",
    "sg:address":"Chauss\u00c9e De Dieleghem 18",
    "sg:city":"Jette",
    "sg:orig_category":"Agences de publicit\u00e9",
    "sg:phone":"+32 2 479 98 73",
    "sg:postcode":"1090",
    "sg:province":"Bruxelles-Capitale",
    "wof:name":"Monudor",
    "wof:placetype":"venue"
},
  "geometry": {"coordinates":[4.3212451935,50.8826675415],"type":"Point"}
}