{
  "type": "Feature",
  "properties": {
    "iso:country":"BE",
    "sg:address":"Rue De Profondsart 20",
    "sg:city":"Ottignies-louvain-la-neuve",
    "sg:orig_category":"Services de Nettoyage and de D\u00e9sinfection. Jardinage",
    "sg:phone":"+32 10 41 06 08",
    "sg:postcode":"1342",
    "sg:province":"Brabant Wallon",
    "wof:name":"Marc Hoebeke",
    "wof:placetype":"venue"
},
  "geometry": {"coordinates":[4.5461320877,50.6905441284],"type":"Point"}
}