{
  "type": "Feature",
  "properties": {
    "addr:full":"Aarschotsesteenweg 115 Lier Antwerpen 2500",
    "addr:housenumber":"115",
    "addr:postcode":"2500",
    "addr:street":"Aarschotsesteenweg",
    "iso:country":"BE",
    "sg:address":"Aarschotsesteenweg 115",
    "sg:city":"Lier",
    "sg:classifiers":[
        {
            "category":"Shopping",
            "subcategory":"Shoes",
            "type":"Retail Goods"
        }
    ],
    "sg:phone":"+32 3 480 10 99",
    "sg:postcode":"2500",
    "sg:province":"Antwerpen",
    "sg:tags":[
        "slipper",
        "-"
    ],
    "wof:name":"Deckers Kinderen Bvba",
    "wof:placetype":"venue"
},
  "geometry": {"coordinates":[4.587015152,51.115398407],"type":"Point"}
}