{
  "type": "Feature",
  "properties": {
    "addr:full":"Avenue Reine Astrid 71 Box 1 Namur Namur 5000",
    "addr:housenumber":"71;1",
    "addr:postcode":"5000",
    "addr:street":"Avenue Reine Astrid;Box",
    "iso:country":"BE",
    "sg:address":"Avenue Reine Astrid 71 Box 1",
    "sg:city":"Namur",
    "sg:classifiers":[
        {
            "category":"Professional",
            "subcategory":"Lawyer & Legal Services",
            "type":"Services"
        }
    ],
    "sg:phone":"+32 81 74 45 90",
    "sg:postcode":"5000",
    "sg:province":"Namur",
    "wof:name":"Moinil Isabelle",
    "wof:placetype":"venue"
},
  "geometry": {"coordinates":[4.8540000916,50.462688446],"type":"Point"}
}