{
  "type": "Feature",
  "properties": {
    "iso:country":"BE",
    "sg:address":"Baasrodestraat 194",
    "sg:city":"Lebbeke",
    "sg:orig_category":"Fleurs and plantes",
    "sg:phone":"+32 52 34 27 27",
    "sg:postcode":"9280",
    "sg:province":"Oost-Vlaanderen",
    "wof:name":"Koen Van Malderen",
    "wof:placetype":"venue"
},
  "geometry": {"coordinates":[4.1513562202,51.0189056396],"type":"Point"}
}