{
  "type": "Feature",
  "properties": {
    "addr:full":"Bergense Steenweg 260 Anderlecht/anderlecht Bruxelles-Capitale 1070",
    "addr:housenumber":"260",
    "addr:postcode":"1070",
    "addr:street":"Bergense Steenweg",
    "iso:country":"BE",
    "sg:address":"Bergense Steenweg 260",
    "sg:city":"Anderlecht/anderlecht",
    "sg:orig_category":"Apotheken",
    "sg:phone":"+32 2 521 57 07",
    "sg:postcode":"1070",
    "sg:province":"Bruxelles-Capitale",
    "wof:name":"Pharmacie De Mey-fifils",
    "wof:placetype":"venue"
},
  "geometry": {"coordinates":[4.3256959915,50.839931488],"type":"Point"}
}