{
  "type": "Feature",
  "properties": {
    "iso:country":"BE",
    "sg:address":"Esdoornstraat 40",
    "sg:city":"Izegem",
    "sg:orig_category":"Herstellingen and onderhoud van auto's",
    "sg:phone":"+32 51 31 22 80",
    "sg:postcode":"8870",
    "sg:province":"West-Vlaanderen",
    "wof:name":"Dirk Vandewalle",
    "wof:placetype":"venue"
},
  "geometry": {"coordinates":[3.1891520023,50.9143753052],"type":"Point"}
}