{
  "type": "Feature",
  "properties": {
    "iso:country":"BE",
    "sg:address":"Albert Meunierstraat 86",
    "sg:city":"Oudergem/auderghem",
    "sg:orig_category":"Schoonmaakbedrijven and ongediertebestrijding",
    "sg:phone":"+32 2 673 58 40",
    "sg:postcode":"1160",
    "sg:province":"Bruxelles-Capitale",
    "wof:name":"Fabrice Van Bellingen",
    "wof:placetype":"venue"
},
  "geometry": {"coordinates":[4.437265873,50.810131073],"type":"Point"}
}