{
  "type": "Feature",
  "properties": {
    "iso:country":"BE",
    "sg:address":"Corbion 41",
    "sg:city":"Ciney",
    "sg:classifiers":[
        {
            "category":"Building & Trades",
            "subcategory":"Construction",
            "type":"Services"
        }
    ],
    "sg:phone":"+32 83 21 62 26",
    "sg:postcode":"5590",
    "sg:province":"Namur",
    "sg:tags":[
        "ventilation",
        "conditionn\u00e9",
        "air"
    ],
    "wof:name":"Christian Daiwaille",
    "wof:placetype":"venue"
},
  "geometry": {"coordinates":[5.1022520065,50.297088623],"type":"Point"}
}