{
  "type": "Feature",
  "properties": {
    "iso:country":"BE",
    "sg:address":"Nachtegalendreef 8",
    "sg:city":"Grobbendonk",
    "sg:classifiers":[
        {
            "category":"Professional",
            "subcategory":"Accounting & Tax Preparation",
            "type":"Services"
        }
    ],
    "sg:phone":"+32 14 51 24 71",
    "sg:postcode":"2280",
    "sg:province":"Antwerpen",
    "sg:tags":[
        "bookkeeper"
    ],
    "wof:name":"Van Den Bulck S",
    "wof:placetype":"venue"
},
  "geometry": {"coordinates":[4.7232909203,51.1707992554],"type":"Point"}
}