{
  "type": "Feature",
  "properties": {
    "addr:full":"Astridlaan 276 Brugge West-Vlaanderen 8310",
    "addr:housenumber":"276",
    "addr:postcode":"8310",
    "addr:street":"Astridlaan",
    "iso:country":"BE",
    "sg:address":"Astridlaan 276",
    "sg:city":"Brugge",
    "sg:orig_category":"Alimentation sp\u00e9cialis\u00e9e. Boucheries",
    "sg:phone":"+32 50 35 03 58",
    "sg:postcode":"8310",
    "sg:province":"West-Vlaanderen",
    "wof:name":"Slagerij Finesse",
    "wof:placetype":"venue"
},
  "geometry": {"coordinates":[3.2573299408,51.1949081421],"type":"Point"}
}