{
  "type": "Feature",
  "properties": {
    "iso:country":"BE",
    "sg:address":"Rijksweg 428",
    "sg:city":"Maasmechelen",
    "sg:orig_category":"Traitements param\u00e9dicaux",
    "sg:phone":"+32 89 76 58 61",
    "sg:postcode":"3630",
    "sg:province":"Limburg",
    "wof:name":"Thuiszorg",
    "wof:placetype":"venue"
},
  "geometry": {"coordinates":[5.6953721046,50.9643211365],"type":"Point"}
}