{
  "type": "Feature",
  "properties": {
    "addr:full":"Merelstraat 19 Londerzeel Vlaams-Brabant 1840",
    "addr:housenumber":"19",
    "addr:postcode":"1840",
    "addr:street":"Merelstraat",
    "iso:country":"BE",
    "sg:address":"Merelstraat 19",
    "sg:city":"Londerzeel",
    "sg:orig_category":"Location de biens divers",
    "sg:phone":"+32 52 30 23 27",
    "sg:postcode":"1840",
    "sg:province":"Vlaams-Brabant",
    "wof:name":"Bart Van De Voorde",
    "wof:placetype":"venue"
},
  "geometry": {"coordinates":[4.3011779785,51.0127296448],"type":"Point"}
}