{
  "type": "Feature",
  "properties": {
    "addr:full":"Industriepark 33 Tienen (groot) Vlaams-Brabant 3300",
    "addr:housenumber":"33",
    "addr:postcode":"3300",
    "addr:street":"Industriepark;Groot Vlaams-Brabant",
    "iso:country":"BE",
    "sg:address":"Industriepark 33",
    "sg:city":"Tienen (groot)",
    "sg:orig_category":"Herstellingen and onderhoud van auto's",
    "sg:phone":"+32 16 82 01 01",
    "sg:postcode":"3300",
    "sg:province":"Vlaams-Brabant",
    "wof:name":"Van Wezel Autoparts",
    "wof:placetype":"venue"
},
  "geometry": {"coordinates":[4.961868763,50.8090019226],"type":"Point"}
}