{
  "type": "Feature",
  "properties": {
    "iso:country":"BE",
    "sg:address":"Gorislaan 49",
    "sg:city":"Steenokkerzeel",
    "sg:classifiers":[
        {
            "category":"Professional",
            "subcategory":"Engineering",
            "type":"Services"
        }
    ],
    "sg:phone":"+32 2 759 59 30",
    "sg:postcode":"1820",
    "sg:province":"Vlaams-Brabant",
    "sg:tags":[
        "environmental",
        "technique",
        "-"
    ],
    "wof:name":"Mava Bodemonderzoek/ Milieu-advies Nv",
    "wof:placetype":"venue"
},
  "geometry": {"coordinates":[4.5133662224,50.9021186829],"type":"Point"}
}