{
  "type": "Feature",
  "properties": {
    "addr:full":"Rue De L'eglise 13 Waterloo Brabant Wallon 1410",
    "addr:housenumber":"13",
    "addr:postcode":"1410",
    "addr:street":"Rue De L'Eglise",
    "iso:country":"BE",
    "sg:address":"Rue De L'eglise 13",
    "sg:city":"Waterloo",
    "sg:classifiers":[
        {
            "category":"Building & Trades",
            "subcategory":"Plumbing",
            "type":"Services"
        }
    ],
    "sg:phone":"+32 2 351 44 96",
    "sg:postcode":"1410",
    "sg:province":"Brabant Wallon",
    "sg:tags":[
        "contractor"
    ],
    "wof:name":"Duchateau Christophe",
    "wof:placetype":"venue"
},
  "geometry": {"coordinates":[4.3748488426,50.7083854675],"type":"Point"}
}