{
  "type": "Feature",
  "properties": {
    "iso:country":"BE",
    "sg:address":"Waterstraat 11",
    "sg:city":"Bilzen (munsterbilzen)",
    "sg:classifiers":[
        {
            "category":"Shopping",
            "subcategory":"Clothing, Apparel, & Fashions",
            "type":"Retail Goods"
        }
    ],
    "sg:phone":"+32 89 41 46 88",
    "sg:postcode":"3740",
    "sg:province":"Limburg",
    "sg:tags":[
        "leather",
        "-",
        "buckskin",
        "clothing"
    ],
    "wof:name":"Eldoliro",
    "wof:placetype":"venue"
},
  "geometry": {"coordinates":[5.5252008438,50.8914794922],"type":"Point"}
}