{
  "type": "Feature",
  "properties": {
    "iso:country":"BE",
    "sg:address":"Kortemarkstraat 174",
    "sg:city":"Torhout",
    "sg:orig_category":"HUISBRANDOLIE",
    "sg:phone":"+32 50 21 26 67",
    "sg:postcode":"8820",
    "sg:province":"West-Vlaanderen",
    "wof:name":"Dirk Vansevenant",
    "wof:placetype":"venue"
},
  "geometry": {"coordinates":[3.0866119862,51.0572395325],"type":"Point"}
}