{
  "type": "Feature",
  "properties": {
    "addr:full":"Bieststraat 13b Grimbergen Vlaams-Brabant 1850",
    "addr:housenumber":"13b",
    "addr:postcode":"1850",
    "addr:street":"Bieststraat",
    "iso:country":"BE",
    "sg:address":"Bieststraat 13b",
    "sg:city":"Grimbergen",
    "sg:classifiers":[
        {
            "category":"Professional",
            "subcategory":"Accounting & Tax Preparation",
            "type":"Services"
        }
    ],
    "sg:phone":"+32 2 269 39 69",
    "sg:postcode":"1850",
    "sg:province":"Vlaams-Brabant",
    "sg:tags":[
        "bookkeeper"
    ],
    "wof:name":"Claessens E",
    "wof:placetype":"venue"
},
  "geometry": {"coordinates":[4.3568491936,50.9364891052],"type":"Point"}
}