{
  "type": "Feature",
  "properties": {
    "iso:country":"BE",
    "sg:address":"Rue Puits-en-sock 133",
    "sg:city":"Li\u00e8ge 1 (li\u00e8ge 2)",
    "sg:classifiers":[
        {
            "category":"Real Estate",
            "subcategory":"Real Estate Services",
            "type":"Services"
        }
    ],
    "sg:phone":"+32 4 369 42 69",
    "sg:postcode":"4020",
    "sg:province":"Li\u00e8ge",
    "wof:name":"Bureau Inform. Construct. Espagnols",
    "wof:placetype":"venue"
},
  "geometry": {"coordinates":[5.5857720375,50.6390380859],"type":"Point"}
}