{
  "type": "Feature",
  "properties": {
    "addr:full":"Ridder Walter Van Havrelaan 163 Schoten Antwerpen 2900",
    "addr:housenumber":"163",
    "addr:postcode":"2900",
    "addr:street":"Ridder Walter Van Havrelaan",
    "iso:country":"BE",
    "sg:address":"Ridder Walter Van Havrelaan 163",
    "sg:city":"Schoten",
    "sg:classifiers":[
        {
            "category":"Personal",
            "subcategory":"Barber",
            "type":"Services"
        }
    ],
    "sg:phone":"+32 3 658 32 15",
    "sg:postcode":"2900",
    "sg:province":"Antwerpen",
    "sg:tags":[
        "gentleman",
        "salon",
        "-",
        "hairdressing"
    ],
    "wof:name":"Goolaerts",
    "wof:placetype":"venue"
},
  "geometry": {"coordinates":[4.4909229279,51.2536087036],"type":"Point"}
}