{
  "type": "Feature",
  "properties": {
    "iso:country":"BE",
    "sg:address":"Quai Saint-leonard 21",
    "sg:city":"Liege",
    "sg:orig_category":"Mat\u00e9riel de T\u00e9l\u00e9communication",
    "sg:phone":"+32 4 227 61 66",
    "sg:postcode":"4000",
    "sg:province":"Li\u00e8ge",
    "wof:name":"International Communication And",
    "wof:placetype":"venue"
},
  "geometry": {"coordinates":[5.5891442299,50.6476402283],"type":"Point"}
}