{
  "type": "Feature",
  "properties": {
    "addr:full":"Krombeekweg 13 Heist-op-den-berg Antwerpen 2222",
    "addr:housenumber":"13",
    "addr:postcode":"2222",
    "addr:street":"Krombeekweg",
    "iso:country":"BE",
    "sg:address":"Krombeekweg 13",
    "sg:city":"Heist-op-den-berg",
    "sg:orig_category":"Herstellingen and onderhoud van auto's",
    "sg:phone":"+32 15 24 17 60",
    "sg:postcode":"2222",
    "sg:province":"Antwerpen",
    "wof:name":"Garage Van Herck",
    "wof:placetype":"venue"
},
  "geometry": {"coordinates":[4.7292399406,51.1032218933],"type":"Point"}
}