{
  "type": "Feature",
  "properties": {
    "addr:full":"Zwevezelestraat 48 Torhout West-Vlaanderen 8820",
    "addr:housenumber":"48",
    "addr:postcode":"8820",
    "addr:street":"Zwevezelestraat",
    "iso:country":"BE",
    "sg:address":"Zwevezelestraat 48",
    "sg:city":"Torhout",
    "sg:orig_category":"Pharmaciens",
    "sg:phone":"+32 50 21 67 44",
    "sg:postcode":"8820",
    "sg:province":"West-Vlaanderen",
    "wof:name":"Helene Vandaele",
    "wof:placetype":"venue"
},
  "geometry": {"coordinates":[3.1120250225,51.0591697693],"type":"Point"}
}