{
  "type": "Feature",
  "properties": {
    "addr:full":"Hooistraat 70 Destelbergen Oost-Vlaanderen 9070",
    "addr:housenumber":"70",
    "addr:postcode":"9070",
    "addr:street":"Hooistraat",
    "iso:country":"BE",
    "sg:address":"Hooistraat 70",
    "sg:city":"Destelbergen",
    "sg:orig_category":"Rev\u00eatements pour sols and murs. Peinture",
    "sg:phone":"+32 9 239 90 30",
    "sg:postcode":"9070",
    "sg:province":"Oost-Vlaanderen",
    "wof:name":"Marnix Bracke",
    "wof:placetype":"venue"
},
  "geometry": {"coordinates":[3.8064200878,51.04164505],"type":"Point"}
}