{
  "type": "Feature",
  "properties": {
    "iso:country":"BE",
    "sg:address":"Rue Yerpen 17",
    "sg:city":"Huy",
    "sg:orig_category":"Plomberie, chauffage and installations sanitaires",
    "sg:phone":"+32 85 23 37 82",
    "sg:postcode":"4500",
    "sg:province":"Li\u00e8ge",
    "wof:name":"Alain Ambroise",
    "wof:placetype":"venue"
},
  "geometry": {"coordinates":[5.2266740799,50.5262565613],"type":"Point"}
}