{
  "type": "Feature",
  "properties": {
    "addr:full":"Oude Vest 59 Dendermonde Oost-Vlaanderen 9200",
    "addr:housenumber":"59",
    "addr:postcode":"9200",
    "addr:street":"Oude Vest;Oost-Vlaanderen",
    "iso:country":"BE",
    "sg:address":"Oude Vest 59",
    "sg:city":"Dendermonde",
    "sg:classifiers":[
        {
            "category":"Bars & Pubs",
            "type":"Food & Drink"
        }
    ],
    "sg:phone":"+32 52 21 71 73",
    "sg:postcode":"9200",
    "sg:province":"Oost-Vlaanderen",
    "sg:tags":[
        "tavern"
    ],
    "wof:name":"Hamilton",
    "wof:placetype":"venue"
},
  "geometry": {"coordinates":[4.1011900902,51.0291519165],"type":"Point"}
}