{
  "type": "Feature",
  "properties": {
    "iso:country":"BE",
    "sg:address":"Ch. De Wavre 295",
    "sg:city":"Etterbeek",
    "sg:orig_category":"Mat\u00e9riel de T\u00e9l\u00e9communication. Machines and mat\u00e9riel de bureau Syst\u00e8mes de t\u00e9l\u00e9communications",
    "sg:phone":"+32 2 646 57 10",
    "sg:postcode":"1040",
    "sg:province":"Bruxelles-Capitale",
    "wof:name":"Globalcom",
    "wof:placetype":"venue"
},
  "geometry": {"coordinates":[4.3801398277,50.8363571167],"type":"Point"}
}