{
  "type": "Feature",
  "properties": {
    "iso:country":"BE",
    "sg:address":"Breydelstraat 2",
    "sg:city":"Antwerpen",
    "sg:classifiers":[
        {
            "category":"Cafe",
            "type":"Food & Drink"
        }
    ],
    "sg:phone":"+32 3 233 04 72",
    "sg:postcode":"2018",
    "sg:province":"Antwerpen",
    "sg:tags":[
        "caf\u00e9s"
    ],
    "wof:name":"Sidonia Van Buggenhout",
    "wof:placetype":"venue"
},
  "geometry": {"coordinates":[4.419219017,51.2181091309],"type":"Point"}
}