{
  "type": "Feature",
  "properties": {
    "iso:country":"BE",
    "sg:address":"Langestraat 52",
    "sg:city":"Zandhoven",
    "sg:orig_category":"Dranken Fotogravure and zetwerk Herstellingswinkels voor diverse persoonlijke and huishoudartikelen ",
    "sg:phone":"+32 3 484 59 11",
    "sg:postcode":"2240",
    "sg:province":"Antwerpen",
    "wof:name":"Casa Diana",
    "wof:placetype":"venue"
},
  "geometry": {"coordinates":[4.6744980812,51.2246208191],"type":"Point"}
}