{
  "type": "Feature",
  "properties": {
    "addr:full":"Krokussenlaan 9 Kuurne West-Vlaanderen 8520",
    "addr:housenumber":"9",
    "addr:postcode":"8520",
    "addr:street":"Krokussenlaan",
    "iso:country":"BE",
    "sg:address":"Krokussenlaan 9",
    "sg:city":"Kuurne",
    "sg:classifiers":[
        {
            "category":"Personal",
            "subcategory":"Beauty Salon",
            "type":"Services"
        }
    ],
    "sg:phone":"+32 56 37 00 18",
    "sg:postcode":"8520",
    "sg:province":"West-Vlaanderen",
    "sg:tags":[
        "equipment",
        "hairdressing",
        "-",
        "supply"
    ],
    "wof:name":"Eeckhout M",
    "wof:placetype":"venue"
},
  "geometry": {"coordinates":[3.2742080688,50.8509788513],"type":"Point"}
}