{
  "type": "Feature",
  "properties": {
    "iso:country":"BE",
    "sg:address":"Rue De Li\u00c8ge 21",
    "sg:city":"Esneux",
    "sg:orig_category":"Artsen and specialisten",
    "sg:phone":"+32 4 380 40 80",
    "sg:postcode":"4130",
    "sg:province":"Li\u00e8ge",
    "wof:name":"C. Smets",
    "wof:placetype":"venue"
},
  "geometry": {"coordinates":[5.5763449669,50.5368537903],"type":"Point"}
}