{
  "type": "Feature",
  "properties": {
    "addr:full":"Jules Vandenbemptlaan 16 Leuven Vlaams-Brabant 3001",
    "addr:housenumber":"16",
    "addr:postcode":"3001",
    "addr:street":"Jules Vandenbemptlaan",
    "iso:country":"BE",
    "sg:address":"Jules Vandenbemptlaan 16",
    "sg:city":"Leuven",
    "sg:orig_category":"Artsen and specialisten",
    "sg:phone":"+32 16 22 16 91",
    "sg:postcode":"3001",
    "sg:province":"Vlaams-Brabant",
    "wof:name":"M. Van Der Auwera",
    "wof:placetype":"venue"
},
  "geometry": {"coordinates":[4.6896238327,50.8626556396],"type":"Point"}
}