{
  "type": "Feature",
  "properties": {
    "iso:country":"BE",
    "sg:address":"Rue De Pont \u00e0 Celles 3",
    "sg:city":"Courcelles (trazegnies)",
    "sg:classifiers":[
        {
            "category":"Health Services",
            "subcategory":"Doctor",
            "type":"Services"
        }
    ],
    "sg:phone":"+32 71 45 19 84",
    "sg:postcode":"6183",
    "sg:province":"Hainaut",
    "sg:tags":[
        "medicinephysicians",
        "surgeon"
    ],
    "wof:name":"Lemaire P",
    "wof:placetype":"venue"
},
  "geometry": {"coordinates":[4.3360800743,50.4682197571],"type":"Point"}
}