{
  "type": "Feature",
  "properties": {
    "addr:full":"Torrezeel 19 Bever/bievene Vlaams-Brabant 1547",
    "addr:housenumber":"19;1547",
    "addr:street":"Torrezeel;Vlaams-Brabant",
    "iso:country":"BE",
    "sg:address":"Torrezeel 19",
    "sg:city":"Bever/bievene",
    "sg:orig_category":"Rundveehouders",
    "sg:phone":"+32 54 58 89 55",
    "sg:postcode":"1547",
    "sg:province":"Vlaams-Brabant",
    "wof:name":"Omer Van De Reeckt",
    "wof:placetype":"venue"
},
  "geometry": {"coordinates":[3.9403600693,50.7166404724],"type":"Point"}
}