{
  "type": "Feature",
  "properties": {
    "addr:full":"Lindestraat 3 Melle Oost-Vlaanderen 9090",
    "addr:housenumber":"3",
    "addr:postcode":"9090",
    "addr:street":"Lindestraat",
    "iso:country":"BE",
    "sg:address":"Lindestraat 3",
    "sg:city":"Melle",
    "sg:classifiers":[
        {
            "category":"Food & Beverages",
            "subcategory":"Groceries & Convenience Stores",
            "type":"Retail Goods"
        }
    ],
    "sg:phone":"+32 9 252 20 17",
    "sg:postcode":"9090",
    "sg:province":"Oost-Vlaanderen",
    "sg:tags":[
        "grocer"
    ],
    "wof:name":"Sabine",
    "wof:placetype":"venue"
},
  "geometry": {"coordinates":[3.7957489491,51.0030212402],"type":"Point"}
}