{
  "type": "Feature",
  "properties": {
    "addr:full":"Antwerpsestraat 41 Lier Antwerpen 2500",
    "addr:housenumber":"41",
    "addr:postcode":"2500",
    "addr:street":"Antwerpsestraat",
    "iso:country":"BE",
    "sg:address":"Antwerpsestraat 41",
    "sg:city":"Lier",
    "sg:classifiers":[
        {
            "category":"Tea Room",
            "subcategory":"None",
            "type":"Food & Drink"
        }
    ],
    "sg:phone":"+32 3 488 40 60",
    "sg:postcode":"2500",
    "sg:province":"Antwerpen",
    "wof:name":"De Lierse Coffeeschop",
    "wof:placetype":"venue"
},
  "geometry": {"coordinates":[4.5681262016,51.1327285767],"type":"Point"}
}