{
  "type": "Feature",
  "properties": {
    "addr:full":"Rue Roi Albert 20 Hannut Li\u00e8ge 4280",
    "addr:housenumber":"20",
    "addr:postcode":"4280",
    "addr:street":"Rue Roi Albert",
    "iso:country":"BE",
    "sg:address":"Rue Roi Albert 20",
    "sg:city":"Hannut",
    "sg:classifiers":[
        {
            "category":"Structure",
            "subcategory":"Building",
            "type":"Public Place"
        }
    ],
    "sg:phone":"+32 19 51 15 46",
    "sg:postcode":"4280",
    "sg:province":"Li\u00e8ge",
    "sg:tags":[
        "apartment"
    ],
    "wof:name":"Gabriel S.a.",
    "wof:placetype":"venue"
},
  "geometry": {"coordinates":[5.080406189,50.6708984375],"type":"Point"}
}