{
  "type": "Feature",
  "properties": {
    "addr:full":"Kruisbaan 10 Grobbendonk Antwerpen 2280",
    "addr:housenumber":"10",
    "addr:postcode":"2280",
    "addr:street":"Kruisbaan",
    "iso:country":"BE",
    "sg:address":"Kruisbaan 10",
    "sg:city":"Grobbendonk",
    "sg:orig_category":"Eleveurs de volaille",
    "sg:phone":"+32 14 51 17 59",
    "sg:postcode":"2280",
    "sg:province":"Antwerpen",
    "wof:name":"Ruddy Duck",
    "wof:placetype":"venue"
},
  "geometry": {"coordinates":[4.7177000046,51.1983222961],"type":"Point"}
}