{
  "type": "Feature",
  "properties": {
    "iso:country":"BE",
    "sg:address":"Hameau De Xhignesse 5",
    "sg:city":"Hamoir",
    "sg:classifiers":[
        {
            "category":"Wholesale",
            "subcategory":"Meat",
            "type":"Manufacturing & Wholesale Goods"
        }
    ],
    "sg:phone":"+32 86 38 80 53",
    "sg:postcode":"4180",
    "sg:province":"Li\u00e8ge",
    "sg:tags":[
        "abattoir"
    ],
    "wof:name":"Hamoir (abattoir De)",
    "wof:placetype":"venue"
},
  "geometry": {"coordinates":[5.5409421921,50.4278526306],"type":"Point"}
}