{
  "type": "Feature",
  "properties": {
    "addr:full":"Maalse Steenweg 25 Brugge (sint-kruis) West-Vlaanderen 8310",
    "addr:housenumber":"25",
    "addr:postcode":"8310",
    "addr:street":"Maalse Steenweg",
    "iso:country":"BE",
    "sg:address":"Maalse Steenweg 25",
    "sg:city":"Brugge (sint-kruis)",
    "sg:classifiers":[
        {
            "category":"Shopping",
            "subcategory":"Pets & Pet Supplies",
            "type":"Retail Goods"
        }
    ],
    "sg:phone":"+32 50 35 15 87",
    "sg:postcode":"8310",
    "sg:province":"West-Vlaanderen",
    "sg:tags":[
        "shop",
        "-"
    ],
    "wof:name":"Dierengilde Bostoen",
    "wof:placetype":"venue"
},
  "geometry": {"coordinates":[3.2431840897,51.2106933594],"type":"Point"}
}