{
  "type": "Feature",
  "properties": {
    "iso:country":"BE",
    "sg:address":"Slinkerstraat 95",
    "sg:city":"Lommel",
    "sg:classifiers":[
        {
            "category":"Fast Food",
            "type":"Food & Drink"
        }
    ],
    "sg:phone":"+32 11 55 13 06",
    "sg:postcode":"3920",
    "sg:province":"Limburg",
    "sg:tags":[
        "fried",
        "stand",
        "potato"
    ],
    "wof:name":"Brug 11",
    "wof:placetype":"venue"
},
  "geometry": {"coordinates":[5.3355998993,51.2460403442],"type":"Point"}
}