{
  "type": "Feature",
  "properties": {
    "addr:full":"Vogelkerslaan 40 Brecht Antwerpen 2960",
    "addr:housenumber":"40",
    "addr:postcode":"2960",
    "addr:street":"Vogelkerslaan",
    "iso:country":"BE",
    "sg:address":"Vogelkerslaan 40",
    "sg:city":"Brecht",
    "sg:classifiers":[
        {
            "category":"Personal",
            "subcategory":"Beauty Salon",
            "type":"Services"
        }
    ],
    "sg:phone":"+32 3 636 35 82",
    "sg:postcode":"2960",
    "sg:province":"Antwerpen",
    "sg:tags":[
        "slimming"
    ],
    "wof:name":"Hendrickx Briggitte",
    "wof:placetype":"venue"
},
  "geometry": {"coordinates":[4.6415200233,51.3512115479],"type":"Point"}
}