{
  "type": "Feature",
  "properties": {
    "addr:full":"Oude Meirstraat 48 Malle Antwerpen 2390",
    "addr:housenumber":"48",
    "addr:postcode":"2390",
    "addr:street":"Oude Meirstraat",
    "iso:country":"BE",
    "sg:address":"Oude Meirstraat 48",
    "sg:city":"Malle",
    "sg:orig_category":"Entretien and r\u00e9parations de voitures",
    "sg:phone":"+32 3 312 47 23",
    "sg:postcode":"2390",
    "sg:province":"Antwerpen",
    "wof:name":"Robert Van Dyck",
    "wof:placetype":"venue"
},
  "geometry": {"coordinates":[4.7428569794,51.2992248535],"type":"Point"}
}