{
  "type": "Feature",
  "properties": {
    "iso:country":"BE",
    "sg:address":"Marktweg 186",
    "sg:city":"Aalst",
    "sg:classifiers":[
        {
            "category":"Banks & Credit Unions",
            "subcategory":"Investment Brokerage",
            "type":"Services"
        }
    ],
    "sg:phone":"+32 53 77 03 16",
    "sg:postcode":"9300",
    "sg:province":"Oost-Vlaanderen",
    "sg:tags":[
        "repair",
        "-",
        "installation",
        "sanitary",
        "article"
    ],
    "wof:name":"De Vidts J Bvba",
    "wof:placetype":"venue"
},
  "geometry": {"coordinates":[4.0264701843,50.9344902039],"type":"Point"}
}