{
  "type": "Feature",
  "properties": {
    "iso:country":"BE",
    "sg:address":"Sijslostraat 115",
    "sg:city":"Oostkamp",
    "sg:classifiers":[
        {
            "category":"Cafe",
            "type":"Food & Drink"
        }
    ],
    "sg:phone":"+32 50 27 99 84",
    "sg:postcode":"8020",
    "sg:province":"West-Vlaanderen",
    "sg:tags":[
        "caf\u00e9s"
    ],
    "wof:name":"Johan Bonte",
    "wof:placetype":"venue"
},
  "geometry": {"coordinates":[3.1919109821,51.1005744934],"type":"Point"}
}