{
  "type": "Feature",
  "properties": {
    "addr:full":"Jan Mioenstraat 12 Kortemark West-Vlaanderen 8610",
    "addr:housenumber":"12",
    "addr:postcode":"8610",
    "addr:street":"Mioenstraat",
    "iso:country":"BE",
    "sg:address":"Jan Mioenstraat 12",
    "sg:city":"Kortemark",
    "sg:classifiers":[
        {
            "category":"Retail",
            "subcategory":"Auto Repair",
            "type":"Services"
        }
    ],
    "sg:phone":"+32 51 57 00 14",
    "sg:postcode":"8610",
    "sg:province":"West-Vlaanderen",
    "sg:tags":[
        "automobile-body"
    ],
    "wof:name":"Peire D",
    "wof:placetype":"venue"
},
  "geometry": {"coordinates":[3.0285000801,51.0176696777],"type":"Point"}
}