{
  "type": "Feature",
  "properties": {
    "addr:full":"Rue De L'echauffour\u00c9e 41 Mouscron Hainaut 7700",
    "addr:housenumber":"41",
    "addr:postcode":"7700",
    "addr:street":"Rue De L'Echauffoure \u0301E",
    "iso:country":"BE",
    "sg:address":"Rue De L'echauffour\u00c9e 41",
    "sg:city":"Mouscron",
    "sg:orig_category":"Ordinateurs and \u00e9quipement informatique",
    "sg:phone":"+32 56 34 62 40",
    "sg:postcode":"7700",
    "sg:province":"Hainaut",
    "wof:name":"Eco Lazer",
    "wof:placetype":"venue"
},
  "geometry": {"coordinates":[3.1822490692,50.7528762817],"type":"Point"}
}