{
  "type": "Feature",
  "properties": {
    "iso:country":"BE",
    "sg:address":"Mantelstraat 2",
    "sg:city":"Kruishoutem",
    "sg:classifiers":[
        {
            "category":"Restaurant",
            "type":"Food & Drink"
        }
    ],
    "sg:phone":"+32 9 380 35 34",
    "sg:postcode":"9770",
    "sg:province":"Oost-Vlaanderen",
    "wof:name":"Het Boerenhuis",
    "wof:placetype":"venue"
},
  "geometry": {"coordinates":[3.5465090275,50.940738678],"type":"Point"}
}