{
  "type": "Feature",
  "properties": {
    "addr:full":"Ardooisesteenweg 78 Roeselare West-Vlaanderen 8800",
    "addr:housenumber":"78",
    "addr:postcode":"8800",
    "addr:street":"Ardooisesteenweg",
    "iso:country":"BE",
    "sg:address":"Ardooisesteenweg 78",
    "sg:city":"Roeselare",
    "sg:orig_category":"Non-Classified Establishments",
    "sg:phone":"+32 51 20 19 01",
    "sg:postcode":"8800",
    "sg:province":"West-Vlaanderen",
    "wof:name":"Bijoulux",
    "wof:placetype":"venue"
},
  "geometry": {"coordinates":[3.1336739063,50.9499740601],"type":"Point"}
}