{
  "type": "Feature",
  "properties": {
    "iso:country":"BE",
    "sg:address":"Corneel Vissenaekensplein 6",
    "sg:city":"Begijnendijk (groot)",
    "sg:orig_category":"Banken and kredietinstellingen",
    "sg:phone":"+32 16 56 73 33",
    "sg:postcode":"3130",
    "sg:province":"Vlaams-Brabant",
    "wof:name":"Dexia",
    "wof:placetype":"venue"
},
  "geometry": {"coordinates":[4.7829737663,50.9856758118],"type":"Point"}
}