{
  "type": "Feature",
  "properties": {
    "iso:country":"BE",
    "sg:address":"Wolvenstraat 16",
    "sg:city":"Diest",
    "sg:orig_category":"Activit\u00e9s diverses d'imprimerie",
    "sg:phone":"+32 13 33 32 15",
    "sg:postcode":"3290",
    "sg:province":"Vlaams-Brabant",
    "wof:name":"Anita Laureys",
    "wof:placetype":"venue"
},
  "geometry": {"coordinates":[5.0533490181,50.983039856],"type":"Point"}
}