{
  "type": "Feature",
  "properties": {
    "iso:country":"BE",
    "sg:address":"Churchilllaan 280",
    "sg:city":"Schoten",
    "sg:classifiers":[
        {
            "category":"Insurance",
            "subcategory":"Life Insurance",
            "type":"Services"
        }
    ],
    "sg:phone":"+32 3 685 25 85",
    "sg:postcode":"2900",
    "sg:province":"Antwerpen",
    "sg:tags":[
        "assurance"
    ],
    "wof:name":"Triple A",
    "wof:placetype":"venue"
},
  "geometry": {"coordinates":[4.4832639694,51.2496032715],"type":"Point"}
}