{
  "type": "Feature",
  "properties": {
    "iso:country":"BE",
    "sg:address":"Chauss\u00e9e De Bruxelles 21",
    "sg:city":"Sombreffe",
    "sg:classifiers":[
        {
            "category":"Retail",
            "subcategory":"Auto Repair",
            "type":"Services"
        }
    ],
    "sg:phone":"+32 71 88 63 22",
    "sg:postcode":"5140",
    "sg:province":"Namur",
    "sg:tags":[
        "garage"
    ],
    "wof:name":"Pgm Garage",
    "wof:placetype":"venue"
},
  "geometry": {"coordinates":[4.6159057617,50.5244483948],"type":"Point"}
}