{
  "type": "Feature",
  "properties": {
    "addr:full":"Rue Du Brou 79 Verviers Li\u00e8ge 4800",
    "addr:housenumber":"79",
    "addr:postcode":"4800",
    "addr:street":"Rue Du Brou",
    "iso:country":"BE",
    "sg:address":"Rue Du Brou 79",
    "sg:city":"Verviers",
    "sg:classifiers":[
        {
            "category":"Retail",
            "subcategory":"Repair Shop",
            "type":"Services"
        }
    ],
    "sg:phone":"+32 87 33 15 55",
    "sg:postcode":"4800",
    "sg:province":"Li\u00e8ge",
    "sg:tags":[
        "machine",
        "sewing",
        "-"
    ],
    "wof:name":"Schmitz-mernier",
    "wof:placetype":"venue"
},
  "geometry": {"coordinates":[5.8576331139,50.5919914246],"type":"Point"}
}