{
  "type": "Feature",
  "properties": {
    "addr:full":"Rue Albert I 22 Dison Li\u00e8ge 4820",
    "addr:housenumber":"22",
    "addr:postcode":"4820",
    "addr:street":"Rue Albert I",
    "iso:country":"BE",
    "sg:address":"Rue Albert I 22",
    "sg:city":"Dison",
    "sg:classifiers":[
        {
            "category":"Autos & Motor Vehicles",
            "subcategory":"Fuel & Gas Station",
            "type":"Retail Goods"
        }
    ],
    "sg:phone":"+32 87 35 15 31",
    "sg:postcode":"4820",
    "sg:province":"Li\u00e8ge",
    "wof:name":"Burton Sprl",
    "wof:placetype":"venue"
},
  "geometry": {"coordinates":[5.8557357788,50.6095237732],"type":"Point"}
}