{
  "type": "Feature",
  "properties": {
    "addr:full":"Alfons Van De Maelestr. 23ba Aalst Oost-Vlaanderen 9320",
    "addr:housenumber":"23ba",
    "addr:postcode":"9320",
    "addr:street":"Alfons Van De Maelestr.",
    "iso:country":"BE",
    "sg:address":"Alfons Van De Maelestr. 23ba",
    "sg:city":"Aalst",
    "sg:orig_category":"Artsen and specialisten",
    "sg:phone":"+32 53 78 54 46",
    "sg:postcode":"9320",
    "sg:province":"Oost-Vlaanderen",
    "wof:name":"B. De Sadeleer",
    "wof:placetype":"venue"
},
  "geometry": {"coordinates":[4.0516247749,50.9192123413],"type":"Point"}
}