{
  "type": "Feature",
  "properties": {
    "addr:full":"Schoolstraat 17 Temse Oost-Vlaanderen 9140",
    "addr:housenumber":"17",
    "addr:postcode":"9140",
    "addr:street":"Schoolstraat",
    "iso:country":"BE",
    "sg:address":"Schoolstraat 17",
    "sg:city":"Temse",
    "sg:orig_category":"Kunstonderwijs",
    "sg:phone":"+32 3 771 10 03",
    "sg:postcode":"9140",
    "sg:province":"Oost-Vlaanderen",
    "wof:name":"Academie & Vaktekenschool",
    "wof:placetype":"venue"
},
  "geometry": {"coordinates":[4.209564209,51.1272583008],"type":"Point"}
}