{
  "type": "Feature",
  "properties": {
    "iso:country":"BE",
    "sg:address":"Hannuitsesteenweg 494",
    "sg:city":"Tienen (goetsenhoven)",
    "sg:classifiers":[
        {
            "category":"Home & Garden",
            "subcategory":"Carpets & Floor Coverings",
            "type":"Retail Goods"
        }
    ],
    "sg:phone":"+32 16 81 14 92",
    "sg:postcode":"3300",
    "sg:province":"Vlaams-Brabant",
    "sg:tags":[
        "tile"
    ],
    "wof:name":"Lebegge & Zonen Bvba",
    "wof:placetype":"venue"
},
  "geometry": {"coordinates":[4.930077076,50.8096694946],"type":"Point"}
}