{
  "type": "Feature",
  "properties": {
    "addr:full":"Rue De Binche Courcelles Hainaut 6180",
    "addr:postcode":"6180",
    "addr:street":"Rue De Binche",
    "iso:country":"BE",
    "sg:address":"Rue De Binche",
    "sg:city":"Courcelles",
    "sg:orig_category":"Huisdieren and benodigdheden Royal Canin",
    "sg:phone":"+32 71 45 02 62",
    "sg:postcode":"6180",
    "sg:province":"Hainaut",
    "wof:name":"Ets Henreaux",
    "wof:placetype":"venue"
},
  "geometry": {"coordinates":[4.363339901,50.4660110474],"type":"Point"}
}