{
  "type": "Feature",
  "properties": {
    "addr:full":"Victor Allardstraat 38 Ukkel/uccle Bruxelles-Capitale 1180",
    "addr:housenumber":"38",
    "addr:postcode":"1180",
    "addr:street":"Victor Allardstraat;/",
    "iso:country":"BE",
    "sg:address":"Victor Allardstraat 38",
    "sg:city":"Ukkel/uccle",
    "sg:orig_category":"Artiesten and kunstenaars Diverse grafische activiteiten Plaatsen van vloer- and muurbekleding Schil",
    "sg:phone":"+32 2 332 37 82",
    "sg:postcode":"1180",
    "sg:province":"Bruxelles-Capitale",
    "wof:name":"Philippe Mahillon",
    "wof:placetype":"venue"
},
  "geometry": {"coordinates":[4.3350601196,50.8022575378],"type":"Point"}
}