{
  "type": "Feature",
  "properties": {
    "iso:country":"BE",
    "sg:address":"Rue Du Centre 149",
    "sg:city":"Aiseau-presles (aiseau)",
    "sg:classifiers":[
        {
            "category":"Organizations",
            "subcategory":"Professional Association",
            "type":"Services"
        }
    ],
    "sg:phone":"+32 71 50 27 57",
    "sg:postcode":"6250",
    "sg:province":"Hainaut",
    "sg:tags":[
        "organisation",
        "seminar"
    ],
    "wof:name":"Pirard E",
    "wof:placetype":"venue"
},
  "geometry": {"coordinates":[4.586730957,50.4117355347],"type":"Point"}
}