{
  "type": "Feature",
  "properties": {
    "addr:full":"Rue De Marchienne 100 Thuin Hainaut 6534",
    "addr:housenumber":"100",
    "addr:postcode":"6534",
    "addr:street":"Rue De Marchienne",
    "iso:country":"BE",
    "sg:address":"Rue De Marchienne 100",
    "sg:city":"Thuin",
    "sg:orig_category":"Betonnen bouwelementen Fab Bouwmaterialen Gh Stortklaar beton Fab",
    "sg:phone":"+32 71 51 61 98",
    "sg:postcode":"6534",
    "sg:province":"Hainaut",
    "wof:name":"Betons De Gozee",
    "wof:placetype":"venue"
},
  "geometry": {"coordinates":[4.3579211235,50.3413696289],"type":"Point"}
}