{
  "type": "Feature",
  "properties": {
    "iso:country":"BE",
    "sg:address":"Ertbrandstraat 159",
    "sg:city":"Kapellen",
    "sg:classifiers":[
        {
            "category":"Professional",
            "subcategory":"Engineering",
            "type":"Services"
        }
    ],
    "sg:phone":"+32 475 53 65 60",
    "sg:postcode":"2950",
    "sg:province":"Antwerpen",
    "sg:tags":[
        "industrial",
        "-",
        "automation"
    ],
    "wof:name":"X D B",
    "wof:placetype":"venue"
},
  "geometry": {"coordinates":[4.3995990753,51.3477363586],"type":"Point"}
}