{
  "type": "Feature",
  "properties": {
    "iso:country":"BE",
    "sg:address":"Rue Sainte-gertrude 12",
    "sg:city":"Nivelles",
    "sg:orig_category":"Krantenuitgeverijen Tijdschriftenuitgeverijen",
    "sg:phone":"+32 67 84 32 99",
    "sg:postcode":"1400",
    "sg:province":"Brabant Wallon",
    "wof:name":"Frankie Et Lette",
    "wof:placetype":"venue"
},
  "geometry": {"coordinates":[4.3233089447,50.5962944031],"type":"Point"}
}