{
  "type": "Feature",
  "properties": {
    "addr:full":"Rue De La Terre \u00e0 Briques 29 Tournai (orcq - Marquain - Lamain) Hainaut 7501",
    "addr:housenumber":"29",
    "addr:postcode":"7501",
    "addr:street":"Rue De La Terre A\u0300 Briques;Hainaut",
    "iso:country":"BE",
    "sg:address":"Rue De La Terre \u00e0 Briques 29",
    "sg:city":"Tournai (orcq - Marquain - Lamain)",
    "sg:classifiers":[
        {
            "category":"Professional",
            "subcategory":"Management & Consulting",
            "type":"Services"
        }
    ],
    "sg:phone":"+32 69 54 95 09",
    "sg:postcode":"7501",
    "sg:province":"Hainaut",
    "sg:tags":[
        "consultant"
    ],
    "wof:name":"Korbex",
    "wof:placetype":"venue"
},
  "geometry": {"coordinates":[3.333920002,50.6072616577],"type":"Point"}
}