{
  "type": "Feature",
  "properties": {
    "addr:full":"Spijker 38 Essen Antwerpen 2910",
    "addr:housenumber":"38",
    "addr:postcode":"2910",
    "addr:street":"Spijker",
    "iso:country":"BE",
    "sg:address":"Spijker 38",
    "sg:city":"Essen",
    "sg:classifiers":[
        {
            "category":"Home & Garden",
            "subcategory":"Building Materials",
            "type":"Retail Goods"
        }
    ],
    "sg:phone":"+32 3 667 70 00",
    "sg:postcode":"2910",
    "sg:province":"Antwerpen",
    "sg:tags":[
        "window"
    ],
    "wof:name":"Van Den Bergh H Nv",
    "wof:placetype":"venue"
},
  "geometry": {"coordinates":[4.4745550156,51.4569854736],"type":"Point"}
}