{
  "type": "Feature",
  "properties": {
    "iso:country":"BE",
    "sg:address":"Driesstraat 97",
    "sg:city":"Brussel/bruxelles",
    "sg:orig_category":"Architecten",
    "sg:phone":"+32 2 770 28 60",
    "sg:postcode":"1200",
    "sg:province":"Bruxelles-Capitale",
    "wof:name":"Thierry Berhin",
    "wof:placetype":"venue"
},
  "geometry": {"coordinates":[4.4258599281,50.8465270996],"type":"Point"}
}