{
  "type": "Feature",
  "properties": {
    "iso:country":"BE",
    "sg:address":"Waterloose Steenweg 79",
    "sg:city":"Sint-gillis/saint-gilles",
    "sg:orig_category":"Slagers",
    "sg:phone":"+32 2 534 68 82",
    "sg:postcode":"1060",
    "sg:province":"Bruxelles-Capitale",
    "wof:name":"Zarioh",
    "wof:placetype":"venue"
},
  "geometry": {"coordinates":[4.3442149162,50.8295440674],"type":"Point"}
}