{
  "type": "Feature",
  "properties": {
    "addr:full":"Rue Andr\u00e9 Winands 10 Li\u00e8ge 1 (glain) Li\u00e8ge 4000",
    "addr:housenumber":"10;1",
    "addr:postcode":"4000",
    "addr:street":"Rue Andre\u0301 Winands",
    "iso:country":"BE",
    "sg:address":"Rue Andr\u00e9 Winands 10",
    "sg:city":"Li\u00e8ge 1 (glain)",
    "sg:classifiers":[
        {
            "category":"Retail",
            "subcategory":"Event Space",
            "type":"Services"
        }
    ],
    "sg:phone":"+32 495 51 95 47",
    "sg:postcode":"4000",
    "sg:province":"Li\u00e8ge",
    "sg:tags":[
        "organisation"
    ],
    "wof:name":"Fernandez",
    "wof:placetype":"venue"
},
  "geometry": {"coordinates":[5.5373401642,50.6443023682],"type":"Point"}
}