{
  "type": "Feature",
  "properties": {
    "iso:country":"BE",
    "sg:address":"Boulevard D'herseaux 83",
    "sg:city":"Moeskroen/mouscron",
    "sg:orig_category":"Meubles D\u00e9taillants, Am\u00e9nagement de B\u00e2timents et de Cuisines",
    "sg:phone":"+32 56 48 59 61",
    "sg:postcode":"7711",
    "sg:province":"Hainaut",
    "wof:name":"Meubles Toff",
    "wof:placetype":"venue"
},
  "geometry": {"coordinates":[3.282227993,50.7201118469],"type":"Point"}
}