{
  "type": "Feature",
  "properties": {
    "iso:country":"BE",
    "sg:address":"Grand Rue 20",
    "sg:city":"Sivry-rance",
    "sg:orig_category":"Banques and organismes de cr\u00e9dit",
    "sg:phone":"+32 60 41 22 73",
    "sg:postcode":"6470",
    "sg:province":"Hainaut",
    "wof:name":"Cbc",
    "wof:placetype":"venue"
},
  "geometry": {"coordinates":[4.270149231,50.1428222656],"type":"Point"}
}