{
  "type": "Feature",
  "properties": {
    "addr:full":"Rue G\u00e9n\u00e9ral De Gaulle 5 Courcelles Hainaut 6180",
    "addr:housenumber":"5",
    "addr:postcode":"6180",
    "addr:street":"Rue Ge\u0301Ne\u0301Ral De Gaulle",
    "iso:country":"BE",
    "sg:address":"Rue G\u00e9n\u00e9ral De Gaulle 5",
    "sg:city":"Courcelles",
    "sg:classifiers":[
        {
            "category":"Banks & Credit Unions",
            "subcategory":"Bank",
            "type":"Services"
        }
    ],
    "sg:phone":"+32 71 45 19 12",
    "sg:postcode":"6180",
    "sg:province":"Hainaut",
    "wof:name":"Aslk-cger Bank",
    "wof:placetype":"venue"
},
  "geometry": {"coordinates":[4.3802599907,50.4588394165],"type":"Point"}
}