{
  "type": "Feature",
  "properties": {
    "addr:full":"Sint-martinusstraat 15 Wortegem-petegem Oost-Vlaanderen 9790",
    "addr:housenumber":"15",
    "addr:postcode":"9790",
    "addr:street":"Sint-Martinusstraat",
    "iso:country":"BE",
    "sg:address":"Sint-martinusstraat 15",
    "sg:city":"Wortegem-petegem",
    "sg:orig_category":"Artsen and specialisten",
    "sg:phone":"+32 55 31 38 99",
    "sg:postcode":"9790",
    "sg:province":"Oost-Vlaanderen",
    "wof:name":"Willy Vercamst",
    "wof:placetype":"venue"
},
  "geometry": {"coordinates":[3.5595140457,50.8348770142],"type":"Point"}
}