{
  "type": "Feature",
  "properties": {
    "iso:country":"BE",
    "sg:address":"Hoogdorpsstraat 17a",
    "sg:city":"Alken",
    "sg:classifiers":[
        {
            "category":"Banks & Credit Unions",
            "subcategory":"Financial Services",
            "type":"Services"
        }
    ],
    "sg:phone":"+32 11 59 64 93",
    "sg:postcode":"3570",
    "sg:province":"Limburg",
    "sg:tags":[
        "loan",
        "mortgage"
    ],
    "wof:name":"Ceulemans A",
    "wof:placetype":"venue"
},
  "geometry": {"coordinates":[5.3047418594,50.874294281],"type":"Point"}
}