{
  "type": "Feature",
  "properties": {
    "addr:full":"Paul Jansonlaan 44 Anderlecht Bruxelles-Capitale 1070",
    "addr:housenumber":"44",
    "addr:postcode":"1070",
    "addr:street":"Paul Jansonlaan",
    "iso:country":"BE",
    "sg:address":"Paul Jansonlaan 44",
    "sg:city":"Anderlecht",
    "sg:orig_category":"Sociale secretariaten Verplichte sociale verzekeringen",
    "sg:phone":"+32 2 522 75 53",
    "sg:postcode":"1070",
    "sg:province":"Bruxelles-Capitale",
    "wof:name":"Partena",
    "wof:placetype":"venue"
},
  "geometry": {"coordinates":[4.3048710823,50.834022522],"type":"Point"}
}