{
  "type": "Feature",
  "properties": {
    "addr:full":"Achterstraat 28 Haaltert Oost-Vlaanderen 9450",
    "addr:housenumber":"28",
    "addr:postcode":"9450",
    "addr:street":"Achterstraat",
    "iso:country":"BE",
    "sg:address":"Achterstraat 28",
    "sg:city":"Haaltert",
    "sg:classifiers":[
        {
            "category":"Health Services",
            "subcategory":"Health Practitioner",
            "type":"Services"
        }
    ],
    "sg:phone":"+32 53 83 87 32",
    "sg:postcode":"9450",
    "sg:province":"Oost-Vlaanderen",
    "sg:tags":[
        "physiotherapist"
    ],
    "wof:name":"Van Impe Vera",
    "wof:placetype":"venue"
},
  "geometry": {"coordinates":[4.0007081032,50.9017105103],"type":"Point"}
}