{
  "type": "Feature",
  "properties": {
    "iso:country":"BE",
    "sg:address":"Sint-maurusweg 9",
    "sg:city":"Tienen",
    "sg:classifiers":[
        {
            "category":"Home & Garden",
            "subcategory":"Building Materials",
            "type":"Retail Goods"
        }
    ],
    "sg:phone":"+32 16 81 61 87",
    "sg:postcode":"3300",
    "sg:province":"Vlaams-Brabant",
    "sg:tags":[
        "window"
    ],
    "wof:name":"Andries P",
    "wof:placetype":"venue"
},
  "geometry": {"coordinates":[4.9621601105,50.7970809937],"type":"Point"}
}