{
  "type": "Feature",
  "properties": {
    "iso:country":"BE",
    "sg:address":"Spinnerijkaai 67b",
    "sg:city":"Kortrijk",
    "sg:classifiers":[
        {
            "category":"Sports & Exercise",
            "subcategory":"Sports Center",
            "type":"Entertainment"
        }
    ],
    "sg:phone":"+32 56 21 49 91",
    "sg:postcode":"8500",
    "sg:province":"West-Vlaanderen",
    "sg:tags":[
        "terrain",
        "hors",
        "de",
        "installation",
        "sportifs"
    ],
    "wof:name":"Flanders Indoor Karting",
    "wof:placetype":"venue"
},
  "geometry": {"coordinates":[3.2849171162,50.8315048218],"type":"Point"}
}