{
  "type": "Feature",
  "properties": {
    "addr:full":"Sparrenweg 238 Tessenderlo Limburg 3980",
    "addr:housenumber":"238",
    "addr:postcode":"3980",
    "addr:street":"Sparrenweg",
    "iso:country":"BE",
    "sg:address":"Sparrenweg 238",
    "sg:city":"Tessenderlo",
    "sg:orig_category":"Woningbouw",
    "sg:phone":"+32 13 66 20 69",
    "sg:postcode":"3980",
    "sg:province":"Limburg",
    "wof:name":"Verspreet F",
    "wof:placetype":"venue"
},
  "geometry": {"coordinates":[5.0414481163,51.0644187927],"type":"Point"}
}