{
  "type": "Feature",
  "properties": {
    "addr:full":"Lijnwaadstraat 57 Gent Oost-Vlaanderen 9000",
    "addr:housenumber":"57",
    "addr:postcode":"9000",
    "addr:street":"Lijnwaadstraat;Oost-Vlaanderen",
    "iso:country":"BE",
    "sg:address":"Lijnwaadstraat 57",
    "sg:city":"Gent",
    "sg:classifiers":[
        {
            "category":"Recreation",
            "type":"Entertainment"
        }
    ],
    "sg:phone":"+32 477 47 35 68",
    "sg:postcode":"9000",
    "sg:province":"Oost-Vlaanderen",
    "sg:tags":[
        "diver",
        "amusement"
    ],
    "wof:name":"Fire-music Party Provider",
    "wof:placetype":"venue"
},
  "geometry": {"coordinates":[3.6878249645,51.0689926147],"type":"Point"}
}