{
  "type": "Feature",
  "properties": {
    "addr:full":"Grand Route 56 Verlaine Li\u00e8ge 4537",
    "addr:postcode":"4537",
    "addr:street":"Grand Route 56 Verlaine",
    "iso:country":"BE",
    "sg:address":"Grand Route 56",
    "sg:city":"Verlaine",
    "sg:classifiers":[
        {
            "category":"Wholesale",
            "subcategory":"Fruits & Vegetables",
            "type":"Manufacturing & Wholesale Goods"
        }
    ],
    "sg:phone":"+32 4 259 50 98",
    "sg:postcode":"4537",
    "sg:province":"Li\u00e8ge",
    "sg:tags":[
        "whol",
        "-"
    ],
    "wof:name":"Buttiens Fruits",
    "wof:placetype":"venue"
},
  "geometry": {"coordinates":[5.3064627647,50.61353302],"type":"Point"}
}