{
  "type": "Feature",
  "properties": {
    "iso:country":"BE",
    "sg:address":"Sint-rochusstraat 52",
    "sg:city":"Halle",
    "sg:classifiers":[
        {
            "category":"Personal",
            "subcategory":"Shoe Repair & Shine",
            "type":"Services"
        }
    ],
    "sg:phone":"+32 2 361 04 81",
    "sg:postcode":"1500",
    "sg:province":"Vlaams-Brabant",
    "sg:tags":[
        "shoemaker"
    ],
    "wof:name":"A.r.s.e. Bvba",
    "wof:placetype":"venue"
},
  "geometry": {"coordinates":[4.2396597862,50.7310638428],"type":"Point"}
}