{
  "type": "Feature",
  "properties": {
    "addr:full":"Industriepark 23 Ronse Oost-Vlaanderen 9600",
    "addr:housenumber":"23",
    "addr:postcode":"9600",
    "addr:street":"Industriepark",
    "iso:country":"BE",
    "sg:address":"Industriepark 23",
    "sg:city":"Ronse",
    "sg:classifiers":[
        {
            "category":"Sports & Exercise",
            "subcategory":"Athletic Track",
            "type":"Entertainment"
        }
    ],
    "sg:phone":"+32 2 255 01 00",
    "sg:postcode":"9600",
    "sg:province":"Oost-Vlaanderen",
    "sg:tags":[
        "adhesive",
        "kapton\u00ae",
        "tape"
    ],
    "wof:name":"S.d.s. Benelux N.v. - Nexans Group",
    "wof:placetype":"venue"
},
  "geometry": {"coordinates":[4.2770171165,50.7453041077],"type":"Point"}
}