{
  "type": "Feature",
  "properties": {
    "iso:country":"BE",
    "sg:address":"Steppekestraat 65",
    "sg:city":"Zemst",
    "sg:orig_category":"Beautyfarms, relaxatie and lichamelijk welzijn Diverse voedingsmiddelen Gh Kruideniers Schoonheidssa",
    "sg:phone":"+32 15 61 51 32",
    "sg:postcode":"1981",
    "sg:province":"Vlaams-Brabant",
    "wof:name":"Aadi",
    "wof:placetype":"venue"
},
  "geometry": {"coordinates":[4.4954648018,50.9949989319],"type":"Point"}
}