{
  "type": "Feature",
  "properties": {
    "iso:country":"BE",
    "sg:address":"Brugstraat 64",
    "sg:city":"Boutersem",
    "sg:orig_category":"Tuinen",
    "sg:phone":"+32 16 73 38 83",
    "sg:postcode":"3370",
    "sg:province":"Vlaams-Brabant",
    "wof:name":"Ons Tuinarchitectuur",
    "wof:placetype":"venue"
},
  "geometry": {"coordinates":[4.8317098618,50.8385391235],"type":"Point"}
}