{
  "type": "Feature",
  "properties": {
    "addr:full":"Boomstraat 55 Bornem Antwerpen 2880",
    "addr:housenumber":"55",
    "addr:postcode":"2880",
    "addr:street":"Boomstraat",
    "iso:country":"BE",
    "sg:address":"Boomstraat 55",
    "sg:city":"Bornem",
    "sg:classifiers":[
        {
            "category":"Manufacturing",
            "subcategory":"Textiles",
            "type":"Manufacturing & Wholesale Goods"
        }
    ],
    "sg:phone":"+32 3 899 63 79",
    "sg:postcode":"2880",
    "sg:province":"Antwerpen",
    "sg:tags":[
        "retail",
        "-"
    ],
    "wof:name":"Zeeman Textiel Supers",
    "wof:placetype":"venue"
},
  "geometry": {"coordinates":[4.2334117889,51.097202301],"type":"Point"}
}