{
  "type": "Feature",
  "properties": {
    "iso:country":"BE",
    "sg:address":"Pater Christophestraat 3",
    "sg:city":"Waasmunster",
    "sg:classifiers":[
        {
            "category":"Cafe",
            "type":"Food & Drink"
        }
    ],
    "sg:phone":"+32 3 722 00 97",
    "sg:postcode":"9250",
    "sg:province":"Oost-Vlaanderen",
    "sg:tags":[
        "caf\u00e9s"
    ],
    "wof:name":"Caf\u00c9 De Zwaluw",
    "wof:placetype":"venue"
},
  "geometry": {"coordinates":[4.0634279251,51.1417427063],"type":"Point"}
}