{
  "type": "Feature",
  "properties": {
    "iso:country":"BE",
    "sg:address":"Rue Nouvelle 7",
    "sg:city":"Charleroi",
    "sg:orig_category":"Drukkerijen and copyshops",
    "sg:phone":"+32 71 41 40 37",
    "sg:postcode":"6060",
    "sg:province":"Hainaut",
    "wof:name":"Sibille-bussa",
    "wof:placetype":"venue"
},
  "geometry": {"coordinates":[4.468952179,50.3944892883],"type":"Point"}
}