{
  "type": "Feature",
  "properties": {
    "addr:full":"Rue De Lill\u00c9 10 Sprimont Li\u00e8ge 4140",
    "addr:housenumber":"10",
    "addr:postcode":"4140",
    "addr:street":"Rue De Lille\u0301",
    "iso:country":"BE",
    "sg:address":"Rue De Lill\u00c9 10",
    "sg:city":"Sprimont",
    "sg:orig_category":"Eleveurs and marchands de porcs",
    "sg:phone":"+32 4 382 25 79",
    "sg:postcode":"4140",
    "sg:province":"Li\u00e8ge",
    "wof:name":"Frederic Pirard",
    "wof:placetype":"venue"
},
  "geometry": {"coordinates":[5.6507949829,50.5023918152],"type":"Point"}
}