{
  "type": "Feature",
  "properties": {
    "iso:country":"BE",
    "sg:address":"Anjerstraat 12",
    "sg:city":"Neerpelt",
    "sg:classifiers":[
        {
            "category":"Communications",
            "subcategory":"Television Station",
            "type":"Services"
        }
    ],
    "sg:phone":"+32 11 66 11 50",
    "sg:postcode":"3910",
    "sg:province":"Limburg",
    "sg:tags":[
        "video",
        "audio",
        "verhuur"
    ],
    "wof:name":"Heidi Breemans",
    "wof:placetype":"venue"
},
  "geometry": {"coordinates":[5.4541501999,51.225315094],"type":"Point"}
}