{
  "type": "Feature",
  "properties": {
    "addr:full":"Rue De La Place Du Bois 19 Boussu Hainaut 7300",
    "addr:housenumber":"19",
    "addr:postcode":"7300",
    "addr:street":"Rue De La Place Du Bois",
    "iso:country":"BE",
    "sg:address":"Rue De La Place Du Bois 19",
    "sg:city":"Boussu",
    "sg:classifiers":[
        {
            "category":"Bakery",
            "type":"Food & Drink"
        }
    ],
    "sg:phone":"+32 65 65 49 80",
    "sg:postcode":"7300",
    "sg:province":"Hainaut",
    "sg:tags":[
        "confectioner",
        "baker"
    ],
    "wof:name":"Amand Ch",
    "wof:placetype":"venue"
},
  "geometry": {"coordinates":[3.7830309868,50.4122924805],"type":"Point"}
}