{
  "type": "Feature",
  "properties": {
    "addr:full":"Amerikaanse Straat 52 Elsene/ixelles Bruxelles-Capitale 1050",
    "addr:housenumber":"52",
    "addr:postcode":"1050",
    "addr:street":"Amerikaanse Straat",
    "iso:country":"BE",
    "sg:address":"Amerikaanse Straat 52",
    "sg:city":"Elsene/ixelles",
    "sg:orig_category":"Artsen and specialisten",
    "sg:phone":"+32 2 538 70 69",
    "sg:postcode":"1050",
    "sg:province":"Bruxelles-Capitale",
    "wof:name":"Brigitte Szerer",
    "wof:placetype":"venue"
},
  "geometry": {"coordinates":[4.3569951057,50.824016571],"type":"Point"}
}