{
  "type": "Feature",
  "properties": {
    "iso:country":"BE",
    "sg:address":"Kronenburgstraat 90",
    "sg:city":"Antwerpen",
    "sg:orig_category":"Non-Classified Establishments",
    "sg:phone":"+32 3 238 96 13",
    "sg:postcode":"2000",
    "sg:province":"Antwerpen",
    "wof:name":"De Boeck Bvba",
    "wof:placetype":"venue"
},
  "geometry": {"coordinates":[4.3996357918,51.2116241455],"type":"Point"}
}