{
  "type": "Feature",
  "properties": {
    "iso:country":"BE",
    "sg:address":"Rue Bois Saint-gilles",
    "sg:city":"Saint-nicolas",
    "sg:classifiers":[
        {
            "category":"Social Services",
            "subcategory":"Retirement Home",
            "type":"Services"
        }
    ],
    "sg:phone":"+32 4 252 96 36",
    "sg:postcode":"4420",
    "sg:province":"Li\u00e8ge",
    "sg:tags":[
        "society",
        "protection",
        "animal"
    ],
    "wof:name":"S.p.a.-societe Protectrice Des Animaux Asbl",
    "wof:placetype":"venue"
},
  "geometry": {"coordinates":[5.5467419624,50.6253204346],"type":"Point"}
}