{
  "type": "Feature",
  "properties": {
    "iso:country":"BE",
    "sg:address":"Hoogsteenveld 72",
    "sg:city":"Denderleeuw",
    "sg:orig_category":"Agences immobili\u00e8res",
    "sg:phone":"+32 53 66 13 79",
    "sg:postcode":"9473",
    "sg:province":"Oost-Vlaanderen",
    "wof:name":"Century 21 De Woondienst",
    "wof:placetype":"venue"
},
  "geometry": {"coordinates":[4.0504660606,50.8946762085],"type":"Point"}
}