{
  "type": "Feature",
  "properties": {
    "addr:full":"Rue Omer Houssi\u00e8re 19 La Louvi\u00e8re (str\u00e9py-bracquegnies) Hainaut 7110",
    "addr:housenumber":"19",
    "addr:postcode":"7110",
    "addr:street":"Rue Omer Houssie\u0300Re",
    "iso:country":"BE",
    "sg:address":"Rue Omer Houssi\u00e8re 19",
    "sg:city":"La Louvi\u00e8re (str\u00e9py-bracquegnies)",
    "sg:classifiers":[
        {
            "category":"Shopping",
            "subcategory":"Hobbies, Toys, & Games",
            "type":"Retail Goods"
        }
    ],
    "sg:phone":"+32 64 66 50 66",
    "sg:postcode":"7110",
    "sg:province":"Hainaut",
    "sg:tags":[
        "toy",
        "-"
    ],
    "wof:name":"Amiprix",
    "wof:placetype":"venue"
},
  "geometry": {"coordinates":[4.1505050659,50.4826698303],"type":"Point"}
}