{
  "type": "Feature",
  "properties": {
    "iso:country":"BE",
    "sg:address":"Sint-bernardsesteenweg 505",
    "sg:city":"Antwerpen",
    "sg:orig_category":"Journaux",
    "sg:phone":"+32 3 827 56 06",
    "sg:postcode":"2660",
    "sg:province":"Antwerpen",
    "wof:name":"Evang. Kerk Philadelphia",
    "wof:placetype":"venue"
},
  "geometry": {"coordinates":[4.3397898674,51.1732788086],"type":"Point"}
}