{
  "type": "Feature",
  "properties": {
    "iso:country":"BE",
    "sg:address":"Rue D'oignies 70",
    "sg:city":"Couvin (br\u00fbly)",
    "sg:classifiers":[
        {
            "category":"Manufacturing",
            "subcategory":"Lumber",
            "type":"Manufacturing & Wholesale Goods"
        }
    ],
    "sg:phone":"+32 60 37 85 91",
    "sg:postcode":"5660",
    "sg:province":"Namur",
    "sg:tags":[
        "timber"
    ],
    "wof:name":"Wallybois Sprl",
    "wof:placetype":"venue"
},
  "geometry": {"coordinates":[4.5373010635,49.9678459167],"type":"Point"}
}