{
  "type": "Feature",
  "properties": {
    "iso:country":"BE",
    "sg:address":"Chauss\u00e9e De Bruxelles 192",
    "sg:city":"Enghien (petit-enghien)",
    "sg:classifiers":[
        {
            "category":"Real Estate",
            "subcategory":"Architect",
            "type":"Services"
        }
    ],
    "sg:phone":"+32 2 395 38 53",
    "sg:postcode":"7850",
    "sg:province":"Hainaut",
    "wof:name":"De Smet D",
    "wof:placetype":"venue"
},
  "geometry": {"coordinates":[4.0625700951,50.6890182495],"type":"Point"}
}