{
  "type": "Feature",
  "properties": {
    "addr:full":"Zillebeek 110 Beveren (beveren-waas) Oost-Vlaanderen 9120",
    "addr:housenumber":"110",
    "addr:postcode":"9120",
    "addr:street":"Beveren Beveren-Waas Oost-Vlaanderen",
    "iso:country":"BE",
    "sg:address":"Zillebeek 110",
    "sg:city":"Beveren (beveren-waas)",
    "sg:classifiers":[
        {
            "category":"Food & Beverages",
            "subcategory":"Meat & Fish",
            "type":"Retail Goods"
        }
    ],
    "sg:phone":"+32 3 775 90 15",
    "sg:postcode":"9120",
    "sg:province":"Oost-Vlaanderen",
    "sg:tags":[
        "-",
        "livestock"
    ],
    "wof:name":"Verbraeken Wilfried",
    "wof:placetype":"venue"
},
  "geometry": {"coordinates":[4.2211751938,51.222618103],"type":"Point"}
}