{
  "type": "Feature",
  "properties": {
    "iso:country":"BE",
    "sg:address":"Rue De Saint-donat 22",
    "sg:city":"Mettet",
    "sg:orig_category":"Installation de menuiserie en bois and plastique. Fabrication and montage de mobilier. Construction ",
    "sg:phone":"+32 475 47 08 30",
    "sg:postcode":"5640",
    "sg:province":"Namur",
    "wof:name":"Boc System",
    "wof:placetype":"venue"
},
  "geometry": {"coordinates":[4.646299839,50.3017311096],"type":"Point"}
}