{
  "type": "Feature",
  "properties": {
    "iso:country":"BE",
    "sg:address":"Clos De La Magneroule 8",
    "sg:city":"Charleroi (marcinelle)",
    "sg:classifiers":[
        {
            "category":"Health Services",
            "subcategory":"Health Practitioner",
            "type":"Services"
        }
    ],
    "sg:phone":"+32 71 43 25 49",
    "sg:postcode":"6001",
    "sg:province":"Hainaut",
    "sg:tags":[
        "physiotherapist"
    ],
    "wof:name":"Culot A",
    "wof:placetype":"venue"
},
  "geometry": {"coordinates":[4.4297308922,50.3723907471],"type":"Point"}
}