{
  "type": "Feature",
  "properties": {
    "addr:full":"Steenweg 125 Nazareth (eke) Oost-Vlaanderen 9810",
    "addr:housenumber":"125",
    "addr:postcode":"9810",
    "addr:street":"Steenweg",
    "iso:country":"BE",
    "sg:address":"Steenweg 125",
    "sg:city":"Nazareth (eke)",
    "sg:classifiers":[
        {
            "category":"Shopping",
            "subcategory":"Shoes",
            "type":"Retail Goods"
        }
    ],
    "sg:phone":"+32 9 385 57 29",
    "sg:postcode":"9810",
    "sg:province":"Oost-Vlaanderen",
    "sg:tags":[
        "slipper",
        "-"
    ],
    "wof:name":"Dhondt",
    "wof:placetype":"venue"
},
  "geometry": {"coordinates":[3.6421039104,50.9574203491],"type":"Point"}
}