{
  "type": "Feature",
  "properties": {
    "iso:country":"BE",
    "sg:address":"Aarschotsesteenweg 48",
    "sg:city":"Wilsele",
    "sg:orig_category":"Royal Canin. Animaux domestiques and accessoires",
    "sg:phone":"+32 16 24 27 64",
    "sg:postcode":"3012",
    "sg:province":"Vlaams-Brabant",
    "wof:name":"Aveve Wilsele",
    "wof:placetype":"venue"
},
  "geometry": {"coordinates":[4.7071628571,50.892124176],"type":"Point"}
}