{
  "type": "Feature",
  "properties": {
    "iso:country":"BE",
    "sg:address":"Bld Emile De Laveleye 132b",
    "sg:city":"Li\u00c8ge",
    "sg:classifiers":[
        {
            "category":"Personal",
            "subcategory":"Beauty Salon",
            "type":"Services"
        }
    ],
    "sg:phone":"+32 4 344 45 47",
    "sg:postcode":"4020",
    "sg:province":"Li\u00e8ge",
    "sg:tags":[
        "de",
        "coiffure"
    ],
    "wof:name":"Coiffure Animatiff",
    "wof:placetype":"venue"
},
  "geometry": {"coordinates":[5.5910000801,50.6199302673],"type":"Point"}
}