{
  "type": "Feature",
  "properties": {
    "addr:full":"Rue Du Commerce 37 Libin 6910",
    "addr:housenumber":"37",
    "addr:postcode":"6910",
    "addr:street":"Rue Du Commerce",
    "iso:country":"BE",
    "sg:address":"Rue Du Commerce 37",
    "sg:city":"Libin",
    "sg:classifiers":[
        {
            "category":"Banks & Credit Unions",
            "subcategory":"Bank",
            "type":"Services"
        }
    ],
    "sg:phone":"+32 61 65 56 14",
    "sg:postcode":"6910",
    "wof:name":"Aslk-cger Bank",
    "wof:placetype":"venue"
},
  "geometry": {"coordinates":[116.01313018800001,-32.1562004089],"type":"Point"}
}