{
  "type": "Feature",
  "properties": {
    "addr:full":"Steenweg Op Mol 34 Turnhout Antwerpen 2300",
    "addr:housenumber":"34",
    "addr:postcode":"2300",
    "addr:street":"Steenweg Op Mol",
    "iso:country":"BE",
    "sg:address":"Steenweg Op Mol 34",
    "sg:city":"Turnhout",
    "sg:classifiers":[
        {
            "category":"Military Area",
            "subcategory":"Army Base",
            "type":"Public Place"
        }
    ],
    "sg:phone":"+32 14 41 40 66",
    "sg:postcode":"2300",
    "sg:province":"Antwerpen",
    "sg:tags":[
        "equipment",
        "machinery",
        "vacuum"
    ],
    "wof:name":"D'heldt",
    "wof:placetype":"venue"
},
  "geometry": {"coordinates":[4.9604759216,51.3212966919],"type":"Point"}
}