{
  "type": "Feature",
  "properties": {
    "iso:country":"BE",
    "sg:address":"Albertstrasse 28",
    "sg:city":"Kelmis/la Calamine",
    "sg:classifiers":[
        {
            "category":"Cafe",
            "type":"Food & Drink"
        }
    ],
    "sg:phone":"+32 87 65 26 10",
    "sg:postcode":"4720",
    "sg:province":"Li\u00e8ge",
    "sg:tags":[
        "caf\u00e9s"
    ],
    "wof:name":"Caf\u00c9 Chez Parrain",
    "wof:placetype":"venue"
},
  "geometry": {"coordinates":[6.0124201775,50.7172737122],"type":"Point"}
}