{
  "type": "Feature",
  "properties": {
    "addr:full":"Interleuvenstraat 32 Oud-heverlee (blanden) Vlaams-Brabant 3052",
    "addr:housenumber":"32",
    "addr:postcode":"3052",
    "addr:street":"Interleuvenstraat",
    "iso:country":"BE",
    "sg:address":"Interleuvenstraat 32",
    "sg:city":"Oud-heverlee (blanden)",
    "sg:classifiers":[
        {
            "category":"Education",
            "subcategory":"Special Training",
            "type":"Public Place"
        }
    ],
    "sg:phone":"+32 16 40 31 87",
    "sg:postcode":"3052",
    "sg:province":"Vlaams-Brabant",
    "sg:tags":[
        "-",
        "processing",
        "data"
    ],
    "wof:name":"Smets P Consultancy",
    "wof:placetype":"venue"
},
  "geometry": {"coordinates":[4.7169270515,50.8229827881],"type":"Point"}
}