{
  "type": "Feature",
  "properties": {
    "addr:full":"Veldhoekstraat 10 Herzele Oost-Vlaanderen 9551",
    "addr:housenumber":"10",
    "addr:postcode":"9551",
    "addr:street":"Veldhoekstraat;Oost-Vlaanderen",
    "iso:country":"BE",
    "sg:address":"Veldhoekstraat 10",
    "sg:city":"Herzele",
    "sg:orig_category":"Opticiens",
    "sg:phone":"+32 53 62 54 18",
    "sg:postcode":"9551",
    "sg:province":"Oost-Vlaanderen",
    "wof:name":"Kristof De Landsheer",
    "wof:placetype":"venue"
},
  "geometry": {"coordinates":[3.9146649837,50.8958511353],"type":"Point"}
}