{
  "type": "Feature",
  "properties": {
    "addr:full":"Pl. Des Wallons 37 Ottignies-louvain-la-neuve Brabant Wallon 1348",
    "addr:housenumber":"37",
    "addr:postcode":"1348",
    "addr:street":"Pl. Des Wallons",
    "iso:country":"BE",
    "sg:address":"Pl. Des Wallons 37",
    "sg:city":"Ottignies-louvain-la-neuve",
    "sg:classifiers":[
        {
            "category":"Restaurant",
            "type":"Food & Drink"
        }
    ],
    "sg:phone":"+32 10 45 03 61",
    "sg:postcode":"1348",
    "sg:province":"Brabant Wallon",
    "wof:name":"Only Wood",
    "wof:placetype":"venue"
},
  "geometry": {"coordinates":[4.6171569824,50.6685676575],"type":"Point"}
}