{
  "type": "Feature",
  "properties": {
    "addr:full":"Rue Du Ham 447 Moeskroen/mouscron Hainaut 7712",
    "addr:housenumber":"447",
    "addr:postcode":"7712",
    "addr:street":"Rue Du Ham",
    "iso:country":"BE",
    "sg:address":"Rue Du Ham 447",
    "sg:city":"Moeskroen/mouscron",
    "sg:classifiers":[
        {
            "category":"Personal",
            "subcategory":"Beauty Salon",
            "type":"Services"
        }
    ],
    "sg:phone":"+32 56 34 18 47",
    "sg:postcode":"7712",
    "sg:province":"Hainaut",
    "sg:tags":[
        "de",
        "coiffure"
    ],
    "wof:name":"Maurice Spiessens",
    "wof:placetype":"venue"
},
  "geometry": {"coordinates":[3.2186160088,50.7136154175],"type":"Point"}
}