{
  "type": "Feature",
  "properties": {
    "iso:country":"BE",
    "sg:address":"Rue De Baume 62",
    "sg:city":"La Louvi\u00c8re",
    "sg:orig_category":"Herstellingen and onderhoud van auto's",
    "sg:phone":"+32 64 28 00 26",
    "sg:postcode":"7100",
    "sg:province":"Hainaut",
    "wof:name":"Garage Free Pump",
    "wof:placetype":"venue"
},
  "geometry": {"coordinates":[4.1942000389,50.4719314575],"type":"Point"}
}