{
  "type": "Feature",
  "properties": {
    "iso:country":"BE",
    "sg:address":"Idevoordelaan 43",
    "sg:city":"Ninove",
    "sg:orig_category":"Installation \u00e9lectrique r\u00e9sidentielle. Installation \u00e9lectrique industrielle",
    "sg:phone":"+32 54 33 41 10",
    "sg:postcode":"9400",
    "sg:province":"Oost-Vlaanderen",
    "wof:name":"Domomatic",
    "wof:placetype":"venue"
},
  "geometry": {"coordinates":[4.0232000351,50.8349113464],"type":"Point"}
}