{
  "type": "Feature",
  "properties": {
    "iso:country":"BE",
    "sg:address":"Rue Henri Fays 18",
    "sg:city":"Anthisnes",
    "sg:orig_category":"Gespecialiseerde residenti\u00eble bouw Woningbouw",
    "sg:phone":"+32 4 383 69 23",
    "sg:postcode":"4160",
    "sg:province":"Li\u00e8ge",
    "wof:name":"Dallo Silvano",
    "wof:placetype":"venue"
},
  "geometry": {"coordinates":[5.5144729614,50.4829139709],"type":"Point"}
}