{
  "type": "Feature",
  "properties": {
    "iso:country":"BE",
    "sg:address":"Diestersteenweg 2a",
    "sg:city":"Leopoldsburg",
    "sg:classifiers":[
        {
            "category":"Professional",
            "subcategory":"Testing Lab",
            "type":"Services"
        }
    ],
    "sg:phone":"+32 11 34 88 38",
    "sg:postcode":"3970",
    "sg:province":"Limburg",
    "sg:tags":[
        "chemist"
    ],
    "wof:name":"Meysen C",
    "wof:placetype":"venue"
},
  "geometry": {"coordinates":[5.2565970421,51.1160583496],"type":"Point"}
}