{
  "type": "Feature",
  "properties": {
    "addr:full":"Rue Grande 94 Tintigny Luxembourg 6730",
    "addr:housenumber":"94",
    "addr:postcode":"6730",
    "addr:street":"Rue Grande",
    "iso:country":"BE",
    "sg:address":"Rue Grande 94",
    "sg:city":"Tintigny",
    "sg:classifiers":[
        {
            "category":"Recreation",
            "subcategory":"Arcade",
            "type":"Entertainment"
        }
    ],
    "sg:phone":"+32 63 44 48 98",
    "sg:postcode":"6730",
    "sg:province":"Luxembourg",
    "sg:tags":[
        "machine",
        "amusement"
    ],
    "wof:name":"Gestion & Loisirs",
    "wof:placetype":"venue"
},
  "geometry": {"coordinates":[5.5131521225,49.6832771301],"type":"Point"}
}