{
  "type": "Feature",
  "properties": {
    "iso:country":"BE",
    "sg:address":"Vakenleiestraat 3a",
    "sg:city":"Maldegem",
    "sg:orig_category":"Traitements param\u00e9dicaux",
    "sg:phone":"+32 50 71 03 11",
    "sg:postcode":"9990",
    "sg:province":"Oost-Vlaanderen",
    "wof:name":"K. Cornelis",
    "wof:placetype":"venue"
},
  "geometry": {"coordinates":[3.4483320713,51.2094421387],"type":"Point"}
}