{
  "type": "Feature",
  "properties": {
    "addr:full":"Avenue Henry Dunant 4 Box 3 Bruxelles (evere) Bruxelles-Capitale 1140",
    "addr:housenumber":"4;3",
    "addr:postcode":"1140",
    "addr:street":"Avenue Henry Dunant;Box",
    "iso:country":"BE",
    "sg:address":"Avenue Henry Dunant 4 Box 3",
    "sg:city":"Bruxelles (evere)",
    "sg:classifiers":[
        {
            "category":"Shopping",
            "subcategory":"Stationery & Office Supplies",
            "type":"Retail Goods"
        }
    ],
    "sg:phone":"+32 2 201 49 59",
    "sg:postcode":"1140",
    "sg:province":"Bruxelles-Capitale",
    "sg:tags":[
        "partition"
    ],
    "wof:name":"Zajac J",
    "wof:placetype":"venue"
},
  "geometry": {"coordinates":[4.4058990479,50.860660553],"type":"Point"}
}