{
  "type": "Feature",
  "properties": {
    "iso:country":"BE",
    "sg:address":"Echelveldstraat 14",
    "sg:city":"Wommelgem",
    "sg:orig_category":"Fleurs and plantes",
    "sg:phone":"+32 3 353 19 82",
    "sg:postcode":"2160",
    "sg:province":"Antwerpen",
    "wof:name":"Blom",
    "wof:placetype":"venue"
},
  "geometry": {"coordinates":[4.5181121826,51.203918457],"type":"Point"}
}