{
  "type": "Feature",
  "properties": {
    "addr:full":"Voortstraat 2 Sint-amands Antwerpen 2890",
    "addr:housenumber":"2",
    "addr:postcode":"2890",
    "addr:street":"Voortstraat",
    "iso:country":"BE",
    "sg:address":"Voortstraat 2",
    "sg:city":"Sint-amands",
    "sg:orig_category":"Entretien and r\u00e9parations de voitures",
    "sg:phone":"+32 3 889 80 13",
    "sg:postcode":"2890",
    "sg:province":"Antwerpen",
    "wof:name":"Danny Tierens",
    "wof:placetype":"venue"
},
  "geometry": {"coordinates":[4.2453651428,51.066078186],"type":"Point"}
}