{
  "type": "Feature",
  "properties": {
    "addr:full":"Kasteeldreef 2 Turnhout Antwerpen 2300",
    "addr:housenumber":"2",
    "addr:postcode":"2300",
    "addr:street":"Kasteeldreef",
    "iso:country":"BE",
    "sg:address":"Kasteeldreef 2",
    "sg:city":"Turnhout",
    "sg:orig_category":"Enseignement maternel and primaire. Enseignement secondaire g\u00e9n\u00e9ral",
    "sg:phone":"+32 14 41 71 48",
    "sg:postcode":"2300",
    "sg:province":"Antwerpen",
    "wof:name":"Vrije Lagere School",
    "wof:placetype":"venue"
},
  "geometry": {"coordinates":[4.9471030235,51.3244781494],"type":"Point"}
}