{
  "type": "Feature",
  "properties": {
    "addr:full":"Aalbeeksestraat 51 Kortrijk West-Vlaanderen 8510",
    "addr:housenumber":"51",
    "addr:postcode":"8510",
    "addr:street":"Aalbeeksestraat",
    "iso:country":"BE",
    "sg:address":"Aalbeeksestraat 51",
    "sg:city":"Kortrijk",
    "sg:orig_category":"Meubles D\u00e9taillants, Am\u00e9nagement de B\u00e2timents et de Cuisines",
    "sg:phone":"+32 56 21 53 81",
    "sg:postcode":"8510",
    "sg:province":"West-Vlaanderen",
    "wof:name":"Budget Meubel",
    "wof:placetype":"venue"
},
  "geometry": {"coordinates":[3.2586500645,50.7694740295],"type":"Point"}
}