{
  "type": "Feature",
  "properties": {
    "iso:country":"BE",
    "sg:address":"Jozef Reusenslei 154",
    "sg:city":"Borsbeek",
    "sg:classifiers":[
        {
            "category":"Health Services",
            "subcategory":"Dentist",
            "type":"Services"
        }
    ],
    "sg:phone":"+32 3 321 52 66",
    "sg:postcode":"2150",
    "sg:province":"Antwerpen",
    "wof:name":"Bontinck Katrien",
    "wof:placetype":"venue"
},
  "geometry": {"coordinates":[4.4900689125,51.19789505],"type":"Point"}
}