{
  "type": "Feature",
  "properties": {
    "addr:full":"Fabriekstraat 16 Bocholt Limburg 3950",
    "addr:housenumber":"16",
    "addr:postcode":"3950",
    "addr:street":"Fabriekstraat",
    "iso:country":"BE",
    "sg:address":"Fabriekstraat 16",
    "sg:city":"Bocholt",
    "sg:orig_category":"Banques and organismes de cr\u00e9dit",
    "sg:phone":"+32 89 44 57 24",
    "sg:postcode":"3950",
    "sg:province":"Limburg",
    "wof:name":"Kbc",
    "wof:placetype":"venue"
},
  "geometry": {"coordinates":[5.5510821342,51.2064437866],"type":"Point"}
}