{
  "type": "Feature",
  "properties": {
    "addr:full":"Desselgemseweg 10 Waregem West-Vlaanderen 8790",
    "addr:housenumber":"10",
    "addr:postcode":"8790",
    "addr:street":"Desselgemseweg",
    "iso:country":"BE",
    "sg:address":"Desselgemseweg 10",
    "sg:city":"Waregem",
    "sg:orig_category":"Catering and organisatie van feesten Slagers Voedingsspeciaalzaken",
    "sg:phone":"+32 56 60 13 10",
    "sg:postcode":"8790",
    "sg:province":"West-Vlaanderen",
    "wof:name":"Traiteur Kurt & Els",
    "wof:placetype":"venue"
},
  "geometry": {"coordinates":[3.4148800373,50.8816642761],"type":"Point"}
}