{
  "type": "Feature",
  "properties": {
    "addr:full":"Goudbloemstraat 23bc Herentals Antwerpen 2200",
    "addr:housenumber":"23bc",
    "addr:postcode":"2200",
    "addr:street":"Goudbloemstraat",
    "iso:country":"BE",
    "sg:address":"Goudbloemstraat 23bc",
    "sg:city":"Herentals",
    "sg:orig_category":"Advocaten and juridische adviseurs",
    "sg:phone":"+32 14 21 30 53",
    "sg:postcode":"2200",
    "sg:province":"Antwerpen",
    "wof:name":"Ph. Somers",
    "wof:placetype":"venue"
},
  "geometry": {"coordinates":[4.8331642151,51.1798439026],"type":"Point"}
}