{
  "type": "Feature",
  "properties": {
    "addr:full":"Nieuwstraat 32 Deinze Oost-Vlaanderen 9800",
    "addr:housenumber":"32",
    "addr:postcode":"9800",
    "addr:street":"Nieuwstraat",
    "iso:country":"BE",
    "sg:address":"Nieuwstraat 32",
    "sg:city":"Deinze",
    "sg:orig_category":"Artsen and specialisten",
    "sg:phone":"+32 9 386 89 70",
    "sg:postcode":"9800",
    "sg:province":"Oost-Vlaanderen",
    "wof:name":"Geert Clauwaert",
    "wof:placetype":"venue"
},
  "geometry": {"coordinates":[3.5634770393,50.9835472107],"type":"Point"}
}