{
  "type": "Feature",
  "properties": {
    "addr:full":"Lindestraat 20 Zele Oost-Vlaanderen 9240",
    "addr:housenumber":"20",
    "addr:postcode":"9240",
    "addr:street":"Lindestraat",
    "iso:country":"BE",
    "sg:address":"Lindestraat 20",
    "sg:city":"Zele",
    "sg:orig_category":"Imprimeries and copyshops. Travaux d\u00b4installation divers. Ordinateurs and \u00e9quipement informatique",
    "sg:phone":"+32 52 45 78 11",
    "sg:postcode":"9240",
    "sg:province":"Oost-Vlaanderen",
    "wof:name":"W H Brady",
    "wof:placetype":"venue"
},
  "geometry": {"coordinates":[4.0232357979,51.0658950806],"type":"Point"}
}