{
  "type": "Feature",
  "properties": {
    "iso:country":"BE",
    "sg:address":"Rue Ernest Milcamps 13bb",
    "sg:city":"La Louviere",
    "sg:orig_category":"Algemeen secundair onderwijs Technisch and beroeps secundair onderwijs",
    "sg:phone":"+32 64 26 31 91",
    "sg:postcode":"7100",
    "sg:province":"Hainaut",
    "wof:name":"Inst. Prov. De Nursing",
    "wof:placetype":"venue"
},
  "geometry": {"coordinates":[4.1914010048,50.4789276123],"type":"Point"}
}