{
  "type": "Feature",
  "properties": {
    "iso:country":"BE",
    "sg:address":"Avenue De Waterloo 12",
    "sg:city":"Charleroi",
    "sg:orig_category":"Non-foodwinkels",
    "sg:phone":"+32 71 30 39 74",
    "sg:postcode":"6000",
    "sg:province":"Hainaut",
    "wof:name":"Gauvain",
    "wof:placetype":"venue"
},
  "geometry": {"coordinates":[4.4471678734,50.4147415161],"type":"Point"}
}