{
  "type": "Feature",
  "properties": {
    "addr:full":"Monshofstraat 32 Bocholt Limburg 3950",
    "addr:housenumber":"32",
    "addr:postcode":"3950",
    "addr:street":"Monshofstraat",
    "iso:country":"BE",
    "sg:address":"Monshofstraat 32",
    "sg:city":"Bocholt",
    "sg:orig_category":"Diverse bedrijfsbeheeradviesbureaus",
    "sg:phone":"+32 89 47 13 29",
    "sg:postcode":"3950",
    "sg:province":"Limburg",
    "wof:name":"C E M Consulting Services",
    "wof:placetype":"venue"
},
  "geometry": {"coordinates":[5.5487308502,51.1527671814],"type":"Point"}
}