{
  "type": "Feature",
  "properties": {
    "iso:country":"BE",
    "sg:address":"Borgstraat 141",
    "sg:city":"Sint-amands",
    "sg:orig_category":"HUISBRANDOLIE",
    "sg:phone":"+32 52 34 38 94",
    "sg:postcode":"2890",
    "sg:province":"Antwerpen",
    "wof:name":"Koek",
    "wof:placetype":"venue"
},
  "geometry": {"coordinates":[4.2057909966,51.0521965027],"type":"Point"}
}