{
  "type": "Feature",
  "properties": {
    "addr:full":"Termstraat 21 Laarne Oost-Vlaanderen 9270",
    "addr:housenumber":"21",
    "addr:postcode":"9270",
    "addr:street":"Termstraat",
    "iso:country":"BE",
    "sg:address":"Termstraat 21",
    "sg:city":"Laarne",
    "sg:classifiers":[
        {
            "category":"Home & Garden",
            "subcategory":"Building Materials",
            "type":"Retail Goods"
        }
    ],
    "sg:phone":"+32 9 368 18 17",
    "sg:postcode":"9270",
    "sg:province":"Oost-Vlaanderen",
    "sg:tags":[
        "window"
    ],
    "wof:name":"De Vijlder Marcel Bvba",
    "wof:placetype":"venue"
},
  "geometry": {"coordinates":[3.8589029312,51.0264854431],"type":"Point"}
}