{
  "type": "Feature",
  "properties": {
    "addr:full":"Berkenhagestraat 7 Zedelgem West-Vlaanderen 8210",
    "addr:housenumber":"7",
    "addr:postcode":"8210",
    "addr:street":"Berkenhagestraat",
    "iso:country":"BE",
    "sg:address":"Berkenhagestraat 7",
    "sg:city":"Zedelgem",
    "sg:classifiers":[
        {
            "category":"Banks & Credit Unions",
            "subcategory":"Investment Brokerage",
            "type":"Services"
        }
    ],
    "sg:phone":"+32 50 20 00 67",
    "sg:postcode":"8210",
    "sg:province":"West-Vlaanderen",
    "wof:name":"Vanroose Bvba",
    "wof:placetype":"venue"
},
  "geometry": {"coordinates":[3.1375639439,51.1406173706],"type":"Point"}
}