{
  "type": "Feature",
  "properties": {
    "iso:country":"BE",
    "sg:address":"Stuiverstraat 191",
    "sg:city":"Oostende",
    "sg:orig_category":"Services fun\u00e9raires",
    "sg:phone":"+32 59 70 23 88",
    "sg:postcode":"8400",
    "sg:province":"West-Vlaanderen",
    "wof:name":"Leo Raes",
    "wof:placetype":"venue"
},
  "geometry": {"coordinates":[2.9075500965,51.2152671814],"type":"Point"}
}