{
  "type": "Feature",
  "properties": {
    "addr:full":"Rue Cardinal Mercier 206a Mouscron (dottignies) Hainaut 7711",
    "addr:housenumber":"206a",
    "addr:postcode":"7711",
    "addr:street":"Rue Cardinal Mercier",
    "iso:country":"BE",
    "sg:address":"Rue Cardinal Mercier 206a",
    "sg:city":"Mouscron (dottignies)",
    "sg:classifiers":[
        {
            "category":"Freight",
            "type":"Transportation"
        }
    ],
    "sg:phone":"+32 56 48 12 09",
    "sg:postcode":"7711",
    "sg:province":"Hainaut",
    "sg:tags":[
        "-",
        "transport"
    ],
    "wof:name":"Somotex",
    "wof:placetype":"venue"
},
  "geometry": {"coordinates":[3.3077158928,50.7210121155],"type":"Point"}
}