{
  "type": "Feature",
  "properties": {
    "addr:full":"Goudbloemstraat 9 Neerpelt Limburg 3910",
    "addr:housenumber":"9",
    "addr:postcode":"3910",
    "addr:street":"Goudbloemstraat",
    "iso:country":"BE",
    "sg:address":"Goudbloemstraat 9",
    "sg:city":"Neerpelt",
    "sg:classifiers":[
        {
            "category":"Cafe",
            "type":"Food & Drink"
        }
    ],
    "sg:phone":"+32 11 64 98 21",
    "sg:postcode":"3910",
    "sg:province":"Limburg",
    "sg:tags":[
        "caf\u00e9s"
    ],
    "wof:name":"Catharina Vanherck",
    "wof:placetype":"venue"
},
  "geometry": {"coordinates":[5.4524669647,51.2273445129],"type":"Point"}
}