{
  "type": "Feature",
  "properties": {
    "addr:full":"Rue Debast 73 Quievrain Hainaut 7380",
    "addr:housenumber":"73",
    "addr:postcode":"7380",
    "addr:street":"Rue Debast;Hainaut",
    "iso:country":"BE",
    "sg:address":"Rue Debast 73",
    "sg:city":"Quievrain",
    "sg:orig_category":"Jeux de hasard",
    "sg:phone":"+32 65 45 74 43",
    "sg:postcode":"7380",
    "sg:province":"Hainaut",
    "wof:name":"Ladbroke",
    "wof:placetype":"venue"
},
  "geometry": {"coordinates":[3.6867530346,50.4070892334],"type":"Point"}
}