{
  "type": "Feature",
  "properties": {
    "iso:country":"BE",
    "sg:address":"Iepersestraat 57",
    "sg:city":"Roeselare",
    "sg:orig_category":"Magasins de r\u00e9parations d'articles personnels et m\u00e9nagers divers",
    "sg:phone":"+32 51 22 02 21",
    "sg:postcode":"8800",
    "sg:province":"West-Vlaanderen",
    "wof:name":"Huis Retouche",
    "wof:placetype":"venue"
},
  "geometry": {"coordinates":[3.1214880943,50.9419975281],"type":"Point"}
}