{
  "type": "Feature",
  "properties": {
    "iso:country":"BE",
    "sg:address":"Rue Du Chapelet 7",
    "sg:city":"Hotton",
    "sg:classifiers":[
        {
            "category":"Shopping",
            "subcategory":"Florist",
            "type":"Retail Goods"
        }
    ],
    "sg:phone":"+32 84 46 70 97",
    "sg:postcode":"6990",
    "sg:province":"Luxembourg",
    "wof:name":"Ryon A-m",
    "wof:placetype":"venue"
},
  "geometry": {"coordinates":[5.44105196,50.2784347534],"type":"Point"}
}