{
  "type": "Feature",
  "properties": {
    "iso:country":"BE",
    "sg:address":"Rue Joseph Guilleaume 22",
    "sg:city":"Ramillies",
    "sg:orig_category":"Elektrische installaties voor woningen",
    "sg:phone":"+32 81 87 70 12",
    "sg:postcode":"1367",
    "sg:province":"Brabant Wallon",
    "wof:name":"Guy Minnoye",
    "wof:placetype":"venue"
},
  "geometry": {"coordinates":[4.9168682098,50.6427116394],"type":"Point"}
}