{
  "type": "Feature",
  "properties": {
    "addr:full":"Rue De La Plate Pierre 3 Chimay (saint-remy) Hainaut 6460",
    "addr:housenumber":"3",
    "addr:postcode":"6460",
    "addr:street":"Rue De La Plate Pierre",
    "iso:country":"BE",
    "sg:address":"Rue De La Plate Pierre 3",
    "sg:city":"Chimay (saint-remy)",
    "sg:classifiers":[
        {
            "category":"Recreation",
            "subcategory":"Gun Range",
            "type":"Entertainment"
        }
    ],
    "sg:phone":"+32 60 21 43 34",
    "sg:postcode":"6460",
    "sg:province":"Hainaut",
    "sg:tags":[
        "ammunition",
        "-",
        "retail"
    ],
    "wof:name":"Corman F",
    "wof:placetype":"venue"
},
  "geometry": {"coordinates":[4.2899880409,50.0534820557],"type":"Point"}
}