{
  "type": "Feature",
  "properties": {
    "iso:country":"BE",
    "sg:address":"Ambachtsstraat 1",
    "sg:city":"Balen",
    "sg:classifiers":[
        {
            "category":"Retail",
            "subcategory":"Auto Repair",
            "type":"Services"
        }
    ],
    "sg:phone":"+32 14 81 41 00",
    "sg:postcode":"2490",
    "sg:province":"Antwerpen",
    "sg:tags":[
        "automobile-body"
    ],
    "wof:name":"Carrosserie Jos Cools Bvba",
    "wof:placetype":"venue"
},
  "geometry": {"coordinates":[5.1530880928,51.1580085754],"type":"Point"}
}