{
  "type": "Feature",
  "properties": {
    "iso:country":"BE",
    "sg:address":"Terlostraat 29a",
    "sg:city":"Gooik",
    "sg:classifiers":[
        {
            "category":"Health Services",
            "subcategory":"Nursing And Care Facility",
            "type":"Services"
        }
    ],
    "sg:phone":"+32 54 56 80 23",
    "sg:postcode":"1755",
    "sg:province":"Vlaams-Brabant",
    "sg:tags":[
        "home"
    ],
    "wof:name":"Du Bois N",
    "wof:placetype":"venue"
},
  "geometry": {"coordinates":[4.1063051224,50.7917251587],"type":"Point"}
}