{
  "type": "Feature",
  "properties": {
    "iso:country":"BE",
    "sg:address":"Grand Route 54",
    "sg:city":"Antoing",
    "sg:orig_category":"Jeux de hasard",
    "sg:phone":"+32 69 44 20 61",
    "sg:postcode":"7640",
    "sg:province":"Hainaut",
    "wof:name":"Ladbroke",
    "wof:placetype":"venue"
},
  "geometry": {"coordinates":[3.4483299255,50.5668716431],"type":"Point"}
}