{
  "type": "Feature",
  "properties": {
    "addr:full":"Rue Du Ch\u00c2teau D'eau 31 Ukkel/uccle Bruxelles-Capitale 1180",
    "addr:housenumber":"31",
    "addr:postcode":"1180",
    "addr:street":"Rue Du Cha\u0302Teau D'Eau;/",
    "iso:country":"BE",
    "sg:address":"Rue Du Ch\u00c2teau D'eau 31",
    "sg:city":"Ukkel/uccle",
    "sg:orig_category":"Installation de menuiserie en bois and plastique",
    "sg:phone":"+32 2 376 47 62",
    "sg:postcode":"1180",
    "sg:province":"Bruxelles-Capitale",
    "wof:name":"Menuiserie Linkebeekoise",
    "wof:placetype":"venue"
},
  "geometry": {"coordinates":[4.3369321823,50.7962684631],"type":"Point"}
}