{
  "type": "Feature",
  "properties": {
    "iso:country":"BE",
    "sg:address":"Rue Des Arcis 58",
    "sg:city":"Marchin",
    "sg:orig_category":"Quincailleries. Charpentes and couvertures. R\u00e9parations \u00e0 domicile d'articles divers. Plomberie, cha",
    "sg:phone":"+32 85 41 22 59",
    "sg:postcode":"4570",
    "sg:province":"Li\u00e8ge",
    "wof:name":"Claude Vandenrijt",
    "wof:placetype":"venue"
},
  "geometry": {"coordinates":[5.2750248909,50.4462089539],"type":"Point"}
}