{
  "type": "Feature",
  "properties": {
    "iso:country":"BE",
    "sg:address":"Rue De La Gendarmerie 9",
    "sg:city":"Assesse",
    "sg:orig_category":"Boucheries",
    "sg:phone":"+32 83 65 51 72",
    "sg:postcode":"5330",
    "sg:province":"Namur",
    "wof:name":"Boucherie Servotte",
    "wof:placetype":"venue"
},
  "geometry": {"coordinates":[5.0215930939,50.3710708618],"type":"Point"}
}