{
  "type": "Feature",
  "properties": {
    "iso:country":"BE",
    "sg:address":"Rue Jules Hoebeke 2",
    "sg:city":"Les Bons Villers",
    "sg:classifiers":[
        {
            "category":"Cafe",
            "type":"Food & Drink"
        }
    ],
    "sg:phone":"+32 71 85 15 63",
    "sg:postcode":"6210",
    "sg:province":"Hainaut",
    "sg:tags":[
        "caf\u00e9s"
    ],
    "wof:name":"Jean Leclercq",
    "wof:placetype":"venue"
},
  "geometry": {"coordinates":[4.4511561394,50.5378227234],"type":"Point"}
}