{
  "type": "Feature",
  "properties": {
    "iso:country":"BE",
    "sg:address":"Limburgerstrasse 91",
    "sg:city":"Lontzen",
    "sg:classifiers":[
        {
            "category":"Freight",
            "type":"Transportation"
        }
    ],
    "sg:phone":"+32 87 39 45 20",
    "sg:postcode":"4710",
    "sg:province":"Li\u00e8ge",
    "sg:tags":[
        "-",
        "transport"
    ],
    "wof:name":"G & G E-logistics",
    "wof:placetype":"venue"
},
  "geometry": {"coordinates":[6.0046401024,50.6704711914],"type":"Point"}
}