{
  "type": "Feature",
  "properties": {
    "iso:country":"BE",
    "sg:address":"Hoge Mauw 3a",
    "sg:city":"Arendonk",
    "sg:classifiers":[
        {
            "category":"Structure",
            "subcategory":"Building",
            "type":"Public Place"
        }
    ],
    "sg:phone":"+32 14 68 90 68",
    "sg:postcode":"2370",
    "sg:province":"Antwerpen",
    "sg:tags":[
        "door"
    ],
    "wof:name":"A.t.a. Bvba",
    "wof:placetype":"venue"
},
  "geometry": {"coordinates":[5.1123580933,51.3021621704],"type":"Point"}
}