{
  "type": "Feature",
  "properties": {
    "addr:full":"Rue Hubert-d\u00e9samor\u00e9 1 Li\u00e8ge 1 (li\u00e8ge 2) Li\u00e8ge 4020",
    "addr:housenumber":"1;1;2",
    "addr:postcode":"4020",
    "addr:street":"Rue Hubert-De\u0301Samore\u0301",
    "iso:country":"BE",
    "sg:address":"Rue Hubert-d\u00e9samor\u00e9 1",
    "sg:city":"Li\u00e8ge 1 (li\u00e8ge 2)",
    "sg:classifiers":[
        {
            "category":"Education",
            "subcategory":"Dance Studio",
            "type":"Public Place"
        }
    ],
    "sg:phone":"+32 4 388 20 05",
    "sg:postcode":"4020",
    "sg:province":"Li\u00e8ge",
    "sg:tags":[
        "school",
        "dancing"
    ],
    "wof:name":"F\u00e9d\u00e9ration Sportive De Danse Old Time",
    "wof:placetype":"venue"
},
  "geometry": {"coordinates":[5.5954608917,50.6186294556],"type":"Point"}
}