{
  "type": "Feature",
  "properties": {
    "iso:country":"BE",
    "sg:address":"Postbus 32",
    "sg:city":"Beveren1",
    "sg:classifiers":[
        {
            "category":"Arts & Performance",
            "subcategory":"Theater",
            "type":"Entertainment"
        }
    ],
    "sg:phone":"+32 3 755 24 45",
    "sg:postcode":"9120",
    "sg:province":"Oost-Vlaanderen",
    "sg:tags":[
        "group",
        "theatre"
    ],
    "wof:name":"Figurentheater Vlinders & Co Vzw",
    "wof:placetype":"venue"
},
  "geometry": {"coordinates":[4.2574100494,51.213180542],"type":"Point"}
}