{
  "type": "Feature",
  "properties": {
    "iso:country":"BE",
    "sg:address":"Chauss\u00e9e De Ghlin 162",
    "sg:city":"Mons",
    "sg:classifiers":[
        {
            "category":"Personal",
            "subcategory":"Psychics & Astrologers",
            "type":"Services"
        }
    ],
    "sg:phone":"+32 65 84 01 65",
    "sg:postcode":"7000",
    "sg:province":"Hainaut",
    "sg:tags":[
        "astrology"
    ],
    "wof:name":"Chrystina",
    "wof:placetype":"venue"
},
  "geometry": {"coordinates":[3.9336700439,50.4646606445],"type":"Point"}
}