{
  "type": "Feature",
  "properties": {
    "addr:full":"Engelstraat 89 Ichtegem West-Vlaanderen 8480",
    "addr:housenumber":"89",
    "addr:postcode":"8480",
    "addr:street":"Engelstraat",
    "iso:country":"BE",
    "sg:address":"Engelstraat 89",
    "sg:city":"Ichtegem",
    "sg:orig_category":"Avocats and conseillers juridiques",
    "sg:phone":"+32 51 58 82 00",
    "sg:postcode":"8480",
    "sg:province":"West-Vlaanderen",
    "wof:name":"Antoon Luca",
    "wof:placetype":"venue"
},
  "geometry": {"coordinates":[3.0181128979,51.094379425],"type":"Point"}
}