{
  "type": "Feature",
  "properties": {
    "addr:full":"Gaverstraat 222 Geraardsbergen Oost-Vlaanderen 9500",
    "addr:housenumber":"222",
    "addr:postcode":"9500",
    "addr:street":"Gaverstraat",
    "iso:country":"BE",
    "sg:address":"Gaverstraat 222",
    "sg:city":"Geraardsbergen",
    "sg:orig_category":"Installation \u00e9lectrique r\u00e9sidentielle",
    "sg:phone":"+32 54 41 82 61",
    "sg:postcode":"9500",
    "sg:province":"Oost-Vlaanderen",
    "wof:name":"Rudy Van Ruyskensvelde",
    "wof:placetype":"venue"
},
  "geometry": {"coordinates":[3.8769099712,50.7616996765],"type":"Point"}
}