{
  "type": "Feature",
  "properties": {
    "addr:full":"Lil 51 Meerhout Antwerpen 2450",
    "addr:housenumber":"51",
    "addr:postcode":"2450",
    "addr:street":"Lil",
    "iso:country":"BE",
    "sg:address":"Lil 51",
    "sg:city":"Meerhout",
    "sg:classifiers":[
        {
            "category":"Wholesale",
            "subcategory":"Books, Periodicals, & Newspapers",
            "type":"Manufacturing & Wholesale Goods"
        }
    ],
    "sg:phone":"+32 14 36 92 92",
    "sg:postcode":"2450",
    "sg:province":"Antwerpen",
    "sg:tags":[
        "publisher"
    ],
    "wof:name":"Zwijsen-infoboek",
    "wof:placetype":"venue"
},
  "geometry": {"coordinates":[5.0893630981,51.1410331726],"type":"Point"}
}