{
  "type": "Feature",
  "properties": {
    "addr:full":"Avenue De La R\u00e9sistance 354 Soumagne Li\u00e8ge 4630",
    "addr:housenumber":"354",
    "addr:postcode":"4630",
    "addr:street":"Avenue De La Re\u0301Sistance",
    "iso:country":"BE",
    "sg:address":"Avenue De La R\u00e9sistance 354",
    "sg:city":"Soumagne",
    "sg:classifiers":[
        {
            "category":"Professional",
            "subcategory":"Lawyer & Legal Services",
            "type":"Services"
        }
    ],
    "sg:phone":"+32 4 377 14 49",
    "sg:postcode":"4630",
    "sg:province":"Li\u00e8ge",
    "wof:name":"Pierlot Genevi\u00e8ve",
    "wof:placetype":"venue"
},
  "geometry": {"coordinates":[5.740404129,50.6326942444],"type":"Point"}
}