{
  "type": "Feature",
  "properties": {
    "iso:country":"BE",
    "sg:address":"Pater Gerard Defeverstr. 7",
    "sg:city":"Bredene",
    "sg:orig_category":"Pleisterwerk",
    "sg:phone":"+32 59 33 17 61",
    "sg:postcode":"8450",
    "sg:province":"West-Vlaanderen",
    "wof:name":"Jan Parasie",
    "wof:placetype":"venue"
},
  "geometry": {"coordinates":[2.9673318863,51.2281570435],"type":"Point"}
}