{
  "type": "Feature",
  "properties": {
    "addr:full":"Sousbeekstraat 88 Waasmunster Oost-Vlaanderen 9250",
    "addr:housenumber":"88",
    "addr:postcode":"9250",
    "addr:street":"Sousbeekstraat",
    "iso:country":"BE",
    "sg:address":"Sousbeekstraat 88",
    "sg:city":"Waasmunster",
    "sg:orig_category":"Banken and kredietinstellingen",
    "sg:phone":"+32 9 349 02 60",
    "sg:postcode":"9250",
    "sg:province":"Oost-Vlaanderen",
    "wof:name":"Centea",
    "wof:placetype":"venue"
},
  "geometry": {"coordinates":[4.0433797836,51.1135597229],"type":"Point"}
}