{
  "type": "Feature",
  "properties": {
    "addr:full":"Avenue Reine Astrid 26 Mouscron Hainaut 7700",
    "addr:housenumber":"26",
    "addr:postcode":"7700",
    "addr:street":"Avenue Reine Astrid",
    "iso:country":"BE",
    "sg:address":"Avenue Reine Astrid 26",
    "sg:city":"Mouscron",
    "sg:classifiers":[
        {
            "category":"Health Services",
            "subcategory":"Doctor",
            "type":"Services"
        }
    ],
    "sg:phone":"+32 56 33 30 16",
    "sg:postcode":"7700",
    "sg:province":"Hainaut",
    "sg:tags":[
        "medicinephysicians",
        "surgeon"
    ],
    "wof:name":"Decantere P",
    "wof:placetype":"venue"
},
  "geometry": {"coordinates":[3.2226059437,50.7493591309],"type":"Point"}
}