{
  "type": "Feature",
  "properties": {
    "addr:full":"Rue De Birken 30 Plombieres/plombieres Li\u00e8ge 4850",
    "addr:housenumber":"30",
    "addr:postcode":"4850",
    "addr:street":"Rue De Birken",
    "iso:country":"BE",
    "sg:address":"Rue De Birken 30",
    "sg:city":"Plombieres/plombieres",
    "sg:orig_category":"Rev\u00eatements pour sols and murs",
    "sg:phone":"+32 87 78 52 20",
    "sg:postcode":"4850",
    "sg:province":"Li\u00e8ge",
    "wof:name":"Jose Hardy",
    "wof:placetype":"venue"
},
  "geometry": {"coordinates":[5.9626002312,50.7068138123],"type":"Point"}
}