{
  "type": "Feature",
  "properties": {
    "addr:full":"Grote Baan 12 Houthalen-helchteren Limburg 3530",
    "addr:housenumber":"12",
    "addr:postcode":"3530",
    "addr:street":"Grote Baan",
    "iso:country":"BE",
    "sg:address":"Grote Baan 12",
    "sg:city":"Houthalen-helchteren",
    "sg:orig_category":"Autoverhuur",
    "sg:phone":"+32 11 52 39 90",
    "sg:postcode":"3530",
    "sg:province":"Limburg",
    "wof:name":"Mols Huurwagens",
    "wof:placetype":"venue"
},
  "geometry": {"coordinates":[5.3739228249,51.0200080872],"type":"Point"}
}