{
  "type": "Feature",
  "properties": {
    "iso:country":"BE",
    "sg:address":"Weststraat 14",
    "sg:city":"Kaprijke",
    "sg:orig_category":"Rundveehouders Varkenskwekers",
    "sg:phone":"+32 9 377 13 78",
    "sg:postcode":"9971",
    "sg:province":"Oost-Vlaanderen",
    "wof:name":"Martin Wauters",
    "wof:placetype":"venue"
},
  "geometry": {"coordinates":[3.6615390778,51.1953125],"type":"Point"}
}