{
  "type": "Feature",
  "properties": {
    "addr:full":"Wijgmaalsesteenweg 168 Herent Vlaams-Brabant 3020",
    "addr:housenumber":"168",
    "addr:postcode":"3020",
    "addr:street":"Wijgmaalsesteenweg",
    "iso:country":"BE",
    "sg:address":"Wijgmaalsesteenweg 168",
    "sg:city":"Herent",
    "sg:classifiers":[
        {
            "category":"Manufacturing",
            "subcategory":"Furniture",
            "type":"Manufacturing & Wholesale Goods"
        }
    ],
    "sg:phone":"+32 16 20 78 93",
    "sg:postcode":"3020",
    "sg:province":"Vlaams-Brabant",
    "sg:tags":[
        "made",
        "-",
        "custom"
    ],
    "wof:name":"Atelier (den)",
    "wof:placetype":"venue"
},
  "geometry": {"coordinates":[4.6844949722,50.916015625],"type":"Point"}
}