{
  "type": "Feature",
  "properties": {
    "addr:full":"Muidepoort 17 Gent Oost-Vlaanderen 9000",
    "addr:housenumber":"17",
    "addr:postcode":"9000",
    "addr:street":"Muidepoort;Oost-Vlaanderen",
    "iso:country":"BE",
    "sg:address":"Muidepoort 17",
    "sg:city":"Gent",
    "sg:orig_category":"Banken and kredietinstellingen",
    "sg:phone":"+32 9 251 58 45",
    "sg:postcode":"9000",
    "sg:province":"Oost-Vlaanderen",
    "wof:name":"Dexia",
    "wof:placetype":"venue"
},
  "geometry": {"coordinates":[3.7304310799,51.071056366],"type":"Point"}
}