{
  "type": "Feature",
  "properties": {
    "addr:full":"Rue De L'industrie 31 Namur Namur 5002",
    "addr:housenumber":"31",
    "addr:postcode":"5002",
    "addr:street":"Rue De L'Industrie",
    "iso:country":"BE",
    "sg:address":"Rue De L'industrie 31",
    "sg:city":"Namur",
    "sg:orig_category":"Travaux d'isolation. Installation de menuiserie en bois and plastique. Eclairage et \u00e9quipements du f",
    "sg:phone":"+32 81 74 06 63",
    "sg:postcode":"5002",
    "sg:province":"Namur",
    "wof:name":"A-climaver",
    "wof:placetype":"venue"
},
  "geometry": {"coordinates":[4.8536629677,50.4745368958],"type":"Point"}
}