{
  "type": "Feature",
  "properties": {
    "addr:full":"Kontichstraat 177 Edegem Antwerpen 2650",
    "addr:housenumber":"177",
    "addr:postcode":"2650",
    "addr:street":"Kontichstraat",
    "iso:country":"BE",
    "sg:address":"Kontichstraat 177",
    "sg:city":"Edegem",
    "sg:classifiers":[
        {
            "category":"Shopping",
            "subcategory":"Computers & Home Electronics",
            "type":"Retail Goods"
        }
    ],
    "sg:phone":"+32 3 457 57 77",
    "sg:postcode":"2650",
    "sg:province":"Antwerpen",
    "sg:tags":[
        "computerapparatuur",
        "microsoft"
    ],
    "wof:name":"Faxcom (aurelium)",
    "wof:placetype":"venue"
},
  "geometry": {"coordinates":[4.4464440346,51.1484489441],"type":"Point"}
}