{
  "type": "Feature",
  "properties": {
    "addr:full":"Rue Maurice Duesberg 114 Dison (andrimont) Li\u00e8ge 4821",
    "addr:housenumber":"114",
    "addr:postcode":"4821",
    "addr:street":"Rue Maurice Duesberg",
    "iso:country":"BE",
    "sg:address":"Rue Maurice Duesberg 114",
    "sg:city":"Dison (andrimont)",
    "sg:classifiers":[
        {
            "category":"Professional",
            "subcategory":"Management & Consulting",
            "type":"Services"
        }
    ],
    "sg:phone":"+32 87 35 35 15",
    "sg:postcode":"4821",
    "sg:province":"Li\u00e8ge",
    "sg:tags":[
        "-",
        "processing",
        "data",
        "consultant"
    ],
    "wof:name":"Nihoul Bureau",
    "wof:placetype":"venue"
},
  "geometry": {"coordinates":[5.8643097878,50.6037979126],"type":"Point"}
}