{
  "type": "Feature",
  "properties": {
    "addr:full":"Rue De La Brasserie 52 Bruxelles (ixelles) Bruxelles-Capitale 1050",
    "addr:housenumber":"52",
    "addr:postcode":"1050",
    "addr:street":"Rue De La Brasserie",
    "iso:country":"BE",
    "sg:address":"Rue De La Brasserie 52",
    "sg:city":"Bruxelles (ixelles)",
    "sg:classifiers":[
        {
            "category":"Real Estate",
            "subcategory":"Architect",
            "type":"Services"
        }
    ],
    "sg:phone":"+32 2 640 65 68",
    "sg:postcode":"1050",
    "sg:province":"Bruxelles-Capitale",
    "wof:name":"Provoost O",
    "wof:placetype":"venue"
},
  "geometry": {"coordinates":[4.3773598671,50.8290748596],"type":"Point"}
}