{
  "type": "Feature",
  "properties": {
    "addr:full":"Marktstraat 23 Izegem West-Vlaanderen 8870",
    "addr:housenumber":"23",
    "addr:postcode":"8870",
    "addr:street":"Marktstraat",
    "iso:country":"BE",
    "sg:address":"Marktstraat 23",
    "sg:city":"Izegem",
    "sg:orig_category":"Tijdelijke werkgelegenheid and uitzendkantoren",
    "sg:phone":"+32 51 33 50 50",
    "sg:postcode":"8870",
    "sg:province":"West-Vlaanderen",
    "wof:name":"Forum Interim",
    "wof:placetype":"venue"
},
  "geometry": {"coordinates":[3.21489501,50.9184341431],"type":"Point"}
}