{
  "type": "Feature",
  "properties": {
    "iso:country":"BE",
    "sg:address":"Visserijstraat 35",
    "sg:city":"Diepenbeek",
    "sg:orig_category":"Producteurs de fruits",
    "sg:phone":"+32 11 32 39 66",
    "sg:postcode":"3590",
    "sg:province":"Limburg",
    "wof:name":"Eric Vandenholt",
    "wof:placetype":"venue"
},
  "geometry": {"coordinates":[5.4538822174,50.9192390442],"type":"Point"}
}