{
  "type": "Feature",
  "properties": {
    "iso:country":"BE",
    "sg:address":"Windstraat 18",
    "sg:city":"Roeselare (rumbeke)",
    "sg:classifiers":[
        {
            "category":"Retail",
            "subcategory":"Repair Shop",
            "type":"Services"
        }
    ],
    "sg:phone":"+32 51 22 45 40",
    "sg:postcode":"8800",
    "sg:province":"West-Vlaanderen",
    "sg:tags":[
        "radio",
        "television",
        "-",
        "maintenance"
    ],
    "wof:name":"Muylle J",
    "wof:placetype":"venue"
},
  "geometry": {"coordinates":[3.1252999306,50.9314956665],"type":"Point"}
}