{
  "type": "Feature",
  "properties": {
    "addr:full":"Rue Cervant\u00e8s 64 Bruxelles (forest) Bruxelles-Capitale 1190",
    "addr:housenumber":"64",
    "addr:postcode":"1190",
    "addr:street":"Rue Cervante\u0300S",
    "iso:country":"BE",
    "sg:address":"Rue Cervant\u00e8s 64",
    "sg:city":"Bruxelles (forest)",
    "sg:classifiers":[
        {
            "category":"Arts & Performance",
            "subcategory":"Theater",
            "type":"Entertainment"
        }
    ],
    "sg:phone":"+32 2 345 21 73",
    "sg:postcode":"1190",
    "sg:province":"Bruxelles-Capitale",
    "sg:tags":[
        "group",
        "theatre"
    ],
    "wof:name":"Th\u00e9atre Jacques Gueux Asbl",
    "wof:placetype":"venue"
},
  "geometry": {"coordinates":[4.3391690254,50.8181800842],"type":"Point"}
}