{
  "type": "Feature",
  "properties": {
    "iso:country":"BE",
    "sg:address":"Hullekenstraat 17",
    "sg:city":"Dendermonde (sint-gillis-bij-dendermonde)",
    "sg:classifiers":[
        {
            "category":"Building & Trades",
            "subcategory":"Electrical",
            "type":"Services"
        }
    ],
    "sg:phone":"+32 52 21 86 34",
    "sg:postcode":"9200",
    "sg:province":"Oost-Vlaanderen",
    "sg:tags":[
        "electric",
        "-",
        "housewiring",
        "contractor"
    ],
    "wof:name":"Helon E",
    "wof:placetype":"venue"
},
  "geometry": {"coordinates":[4.1143097878,51.0228118896],"type":"Point"}
}