{
  "type": "Feature",
  "properties": {
    "iso:country":"BE",
    "sg:address":"Rue De La Barge 16",
    "sg:city":"Li\u00e8ge 1 (sclessin)",
    "sg:classifiers":[
        {
            "category":"Professional",
            "subcategory":"Advertising",
            "type":"Services"
        }
    ],
    "sg:phone":"+32 4 234 74 75",
    "sg:postcode":"4000",
    "sg:province":"Li\u00e8ge",
    "sg:tags":[
        "advertising-vans"
    ],
    "wof:name":"Publi Belgium",
    "wof:placetype":"venue"
},
  "geometry": {"coordinates":[5.5369300842,50.6094665527],"type":"Point"}
}