{
  "type": "Feature",
  "properties": {
    "iso:country":"BE",
    "sg:address":"Ravelingenstraat 15",
    "sg:city":"Oostende",
    "sg:classifiers":[
        {
            "category":"Marine",
            "type":"Transportation"
        }
    ],
    "sg:phone":"+32 59 32 16 94",
    "sg:postcode":"8400",
    "sg:province":"West-Vlaanderen",
    "sg:tags":[
        "fishery",
        "-",
        "shipping"
    ],
    "wof:name":"De Viertorre",
    "wof:placetype":"venue"
},
  "geometry": {"coordinates":[2.9126999378,51.2312583923],"type":"Point"}
}