{
  "type": "Feature",
  "properties": {
    "iso:country":"BE",
    "sg:address":"Chauss\u00e9e De Recogne 22",
    "sg:city":"Neufch\u00e2teau",
    "sg:classifiers":[
        {
            "category":"Retail",
            "subcategory":"Auto Repair",
            "type":"Services"
        }
    ],
    "sg:phone":"+32 61 27 98 27",
    "sg:postcode":"6840",
    "sg:province":"Luxembourg",
    "sg:tags":[
        "garage"
    ],
    "wof:name":"Chenot D",
    "wof:placetype":"venue"
},
  "geometry": {"coordinates":[5.4343428612,49.8546218872],"type":"Point"}
}