{
  "type": "Feature",
  "properties": {
    "iso:country":"BE",
    "sg:address":"Esplanade Du Heyzel 126bb4",
    "sg:city":"Brussel/bruxelles",
    "sg:orig_category":"Diverse opleidingen and onderwijs",
    "sg:phone":"+32 2 475 20 00",
    "sg:postcode":"1020",
    "sg:province":"Bruxelles-Capitale",
    "wof:name":"Teleport Brussel/t\u00c9l\u00c9port Bruxelles",
    "wof:placetype":"venue"
},
  "geometry": {"coordinates":[4.3462300301,50.8855514526],"type":"Point"}
}