{
  "type": "Feature",
  "properties": {
    "iso:country":"BE",
    "sg:address":"Baanstknokstraat 32",
    "sg:city":"Waregem",
    "sg:orig_category":"Woningbouw",
    "sg:phone":"+32 56 60 79 95",
    "sg:postcode":"8790",
    "sg:province":"West-Vlaanderen",
    "wof:name":"Mi-casa",
    "wof:placetype":"venue"
},
  "geometry": {"coordinates":[3.415405035,50.8919029236],"type":"Point"}
}