{
  "type": "Feature",
  "properties": {
    "addr:full":"Rue Gr\u00c9goire Chermanne 34 Ch\u00c2telet Hainaut 6200",
    "addr:housenumber":"34",
    "addr:postcode":"6200",
    "addr:street":"Rue Gre\u0301Goire Chermanne",
    "iso:country":"BE",
    "sg:address":"Rue Gr\u00c9goire Chermanne 34",
    "sg:city":"Ch\u00c2telet",
    "sg:orig_category":"M\u00e9decins and sp\u00e9cialistes",
    "sg:phone":"+32 71 38 48 54",
    "sg:postcode":"6200",
    "sg:province":"Hainaut",
    "wof:name":"Sophie Coulon",
    "wof:placetype":"venue"
},
  "geometry": {"coordinates":[4.5225038528,50.4019775391],"type":"Point"}
}