{
  "type": "Feature",
  "properties": {
    "iso:country":"BE",
    "sg:address":"Velmerlaan 125",
    "sg:city":"Sint-truiden",
    "sg:orig_category":"Biljart- and snookerzalen",
    "sg:phone":"+32 11 68 57 56",
    "sg:postcode":"3806",
    "sg:province":"Limburg",
    "wof:name":"Bc De Smis Velm",
    "wof:placetype":"venue"
},
  "geometry": {"coordinates":[5.1390790939,50.7869338989],"type":"Point"}
}