{
  "type": "Feature",
  "properties": {
    "addr:full":"Chauss\u00e9e De Fleurus 114 Charleroi (jumet) Hainaut 6040",
    "addr:housenumber":"114",
    "addr:postcode":"6040",
    "addr:street":"Chausse\u0301E De Fleurus",
    "iso:country":"BE",
    "sg:address":"Chauss\u00e9e De Fleurus 114",
    "sg:city":"Charleroi (jumet)",
    "sg:classifiers":[
        {
            "category":"Banks & Credit Unions",
            "subcategory":"Investment Brokerage",
            "type":"Services"
        }
    ],
    "sg:phone":"+32 71 42 24 47",
    "sg:postcode":"6040",
    "sg:province":"Hainaut",
    "sg:tags":[
        "printing",
        "-"
    ],
    "wof:name":"Van Hasselt Imprimerie Sa",
    "wof:placetype":"venue"
},
  "geometry": {"coordinates":[4.4735770226,50.4392814636],"type":"Point"}
}