{
  "type": "Feature",
  "properties": {
    "addr:full":"Rue Des D\u00c9port\u00c9s 26 Estinnes Hainaut 7120",
    "addr:housenumber":"26",
    "addr:postcode":"7120",
    "addr:street":"Rue Des De\u0301Porte\u0301S",
    "iso:country":"BE",
    "sg:address":"Rue Des D\u00c9port\u00c9s 26",
    "sg:city":"Estinnes",
    "sg:orig_category":"Eleveurs de bovins",
    "sg:phone":"+32 64 77 13 93",
    "sg:postcode":"7120",
    "sg:province":"Hainaut",
    "wof:name":"Vera Delaere",
    "wof:placetype":"venue"
},
  "geometry": {"coordinates":[4.1012029648,50.3701210022],"type":"Point"}
}