{
  "type": "Feature",
  "properties": {
    "iso:country":"BE",
    "sg:address":"Van Beethovenlaan 4",
    "sg:city":"Kampenhout",
    "sg:classifiers":[
        {
            "category":"Personal",
            "subcategory":"Beauty Salon",
            "type":"Services"
        }
    ],
    "sg:phone":"+32 16 65 50 89",
    "sg:postcode":"1910",
    "sg:province":"Vlaams-Brabant",
    "sg:tags":[
        "de",
        "coiffure"
    ],
    "wof:name":"Nelly Pardon",
    "wof:placetype":"venue"
},
  "geometry": {"coordinates":[4.5533690453,50.9420776367],"type":"Point"}
}