{
  "type": "Feature",
  "properties": {
    "addr:full":"Grand Rue 14 Namur (gelbress\u00e9e) Namur 5024",
    "addr:housenumber":"14",
    "addr:postcode":"5024",
    "addr:street":"Grand Rue",
    "iso:country":"BE",
    "sg:address":"Grand Rue 14",
    "sg:city":"Namur (gelbress\u00e9e)",
    "sg:classifiers":[
        {
            "category":"Retail",
            "subcategory":"Event Space",
            "type":"Services"
        }
    ],
    "sg:phone":"+32 81 58 95 08",
    "sg:postcode":"5024",
    "sg:province":"Namur",
    "sg:tags":[
        "rental",
        "-",
        "hall"
    ],
    "wof:name":"Bourguignonne",
    "wof:placetype":"venue"
},
  "geometry": {"coordinates":[4.9733657837,50.4914627075],"type":"Point"}
}