{
  "type": "Feature",
  "properties": {
    "iso:country":"BE",
    "sg:address":"Brusselsesteenweg 174",
    "sg:city":"Mechelen",
    "sg:orig_category":"Postkantoren Verzekeringsmakelaars and experts",
    "sg:phone":"+32 15 41 50 02",
    "sg:postcode":"2800",
    "sg:province":"Antwerpen",
    "wof:name":"De Post",
    "wof:placetype":"venue"
},
  "geometry": {"coordinates":[4.4726138115,51.0154647827],"type":"Point"}
}