{
  "type": "Feature",
  "properties": {
    "iso:country":"BE",
    "sg:address":"Stalenstraat 9",
    "sg:city":"Genk (waterschei)",
    "sg:classifiers":[
        {
            "category":"Bakery",
            "type":"Food & Drink"
        }
    ],
    "sg:phone":"+32 89 38 26 57",
    "sg:postcode":"3600",
    "sg:province":"Limburg",
    "sg:tags":[
        "confectioner",
        "baker"
    ],
    "wof:name":"Colson G",
    "wof:placetype":"venue"
},
  "geometry": {"coordinates":[5.523086071,50.9970054626],"type":"Point"}
}