{
  "type": "Feature",
  "properties": {
    "iso:country":"BE",
    "sg:address":"Sprietstraat 14",
    "sg:city":"Wingene (zwevezele)",
    "sg:classifiers":[
        {
            "category":"Farming",
            "subcategory":"Livestock Farm",
            "type":"Manufacturing & Wholesale Goods"
        }
    ],
    "sg:phone":"+32 51 61 10 85",
    "sg:postcode":"8750",
    "sg:province":"West-Vlaanderen",
    "sg:tags":[
        "horse"
    ],
    "wof:name":"Blontia A",
    "wof:placetype":"venue"
},
  "geometry": {"coordinates":[3.1717400551,51.037979126],"type":"Point"}
}