{
  "type": "Feature",
  "properties": {
    "iso:country":"BE",
    "sg:address":"Rue De Steppes 22",
    "sg:city":"Li\u00c8ge",
    "sg:orig_category":"Dakwerken Plaatsen van vloer- and muurbekleding Schilders Woningbouw",
    "sg:phone":"+32 4 227 80 00",
    "sg:postcode":"4000",
    "sg:province":"Li\u00e8ge",
    "wof:name":"1000 Et 1 Choses \u00c0 Faire",
    "wof:placetype":"venue"
},
  "geometry": {"coordinates":[5.6014838219,50.6548652649],"type":"Point"}
}