{
  "type": "Feature",
  "properties": {
    "iso:country":"BE",
    "sg:address":"Rue Du Palais 55",
    "sg:city":"Verviers",
    "sg:orig_category":"Eclairage et \u00e9quipements du foyer. R\u00e9paration and restauration de meubles",
    "sg:phone":"+32 87 22 64 50",
    "sg:postcode":"4800",
    "sg:province":"Li\u00e8ge",
    "wof:name":"A. Thelen",
    "wof:placetype":"venue"
},
  "geometry": {"coordinates":[5.8615398407,50.5901603699],"type":"Point"}
}