{
  "type": "Feature",
  "properties": {
    "addr:full":"Steenrijen 36 Lille Antwerpen 2275",
    "addr:housenumber":"36",
    "addr:postcode":"2275",
    "addr:street":"Steenrijen",
    "iso:country":"BE",
    "sg:address":"Steenrijen 36",
    "sg:city":"Lille",
    "sg:orig_category":"Loodgieterij, verwarming and sanitaire installaties",
    "sg:phone":"+32 14 88 15 25",
    "sg:postcode":"2275",
    "sg:province":"Antwerpen",
    "wof:name":"G. Borrey",
    "wof:placetype":"venue"
},
  "geometry": {"coordinates":[4.8456459045,51.2479553223],"type":"Point"}
}