{
  "type": "Feature",
  "properties": {
    "addr:full":"Rue Beeckman 92 Ukkel/uccle Bruxelles-Capitale 1180",
    "addr:housenumber":"92",
    "addr:postcode":"1180",
    "addr:street":"Rue Beeckman;/",
    "iso:country":"BE",
    "sg:address":"Rue Beeckman 92",
    "sg:city":"Ukkel/uccle",
    "sg:orig_category":"Instituts de beaut\u00e9",
    "sg:phone":"+32 2 347 08 20",
    "sg:postcode":"1180",
    "sg:province":"Bruxelles-Capitale",
    "wof:name":"Francoise De Geyter",
    "wof:placetype":"venue"
},
  "geometry": {"coordinates":[4.3349308968,50.8041229248],"type":"Point"}
}