{
  "type": "Feature",
  "properties": {
    "iso:country":"BE",
    "sg:address":"Meerhoutstraat 55",
    "sg:city":"Gent",
    "sg:orig_category":"Enseignement maternel and primaire",
    "sg:phone":"+32 9 255 92 20",
    "sg:postcode":"9041",
    "sg:province":"Oost-Vlaanderen",
    "wof:name":"Bulo",
    "wof:placetype":"venue"
},
  "geometry": {"coordinates":[3.770097971,51.0933532715],"type":"Point"}
}