{
  "type": "Feature",
  "properties": {
    "addr:full":"Les Marleres 6 Namur Namur 5020",
    "addr:housenumber":"6",
    "addr:postcode":"5020",
    "iso:country":"BE",
    "sg:address":"Les Marleres 6",
    "sg:city":"Namur",
    "sg:orig_category":"Antiek",
    "sg:phone":"+32 81 44 43 95",
    "sg:postcode":"5020",
    "sg:province":"Namur",
    "wof:name":"J.m. Gregoire",
    "wof:placetype":"venue"
},
  "geometry": {"coordinates":[4.7952418327,50.4352035522],"type":"Point"}
}