{
  "type": "Feature",
  "properties": {
    "iso:country":"BE",
    "sg:address":"Hille 177",
    "sg:city":"Wingene",
    "sg:orig_category":"Installation \u00e9lectrique r\u00e9sidentielle",
    "sg:phone":"+32 51 61 23 57",
    "sg:postcode":"8750",
    "sg:province":"West-Vlaanderen",
    "wof:name":"Elektro-tech V.v.v.",
    "wof:placetype":"venue"
},
  "geometry": {"coordinates":[3.2270650864,51.0420837402],"type":"Point"}
}