{
  "type": "Feature",
  "properties": {
    "iso:country":"BE",
    "sg:address":"Rue Joseph Wauters 8",
    "sg:city":"Charleroi (gosselies)",
    "sg:classifiers":[
        {
            "category":"Health Services",
            "subcategory":"Doctor",
            "type":"Services"
        }
    ],
    "sg:phone":"+32 71 34 08 98",
    "sg:postcode":"6041",
    "sg:province":"Hainaut",
    "sg:tags":[
        "medicinephysicians",
        "surgeon"
    ],
    "wof:name":"Holzapfel Dieter",
    "wof:placetype":"venue"
},
  "geometry": {"coordinates":[4.4577198029,50.4243164062],"type":"Point"}
}