{
  "type": "Feature",
  "properties": {
    "addr:full":"Bloemkerslaan 33 Grimbergen Vlaams-Brabant 1851",
    "addr:housenumber":"33",
    "addr:postcode":"1851",
    "addr:street":"Bloemkerslaan",
    "iso:country":"BE",
    "sg:address":"Bloemkerslaan 33",
    "sg:city":"Grimbergen",
    "sg:orig_category":"Artsen and specialisten",
    "sg:phone":"+32 2 269 34 61",
    "sg:postcode":"1851",
    "sg:province":"Vlaams-Brabant",
    "wof:name":"Wim Van Paesschen",
    "wof:placetype":"venue"
},
  "geometry": {"coordinates":[4.3756051064,50.9614906311],"type":"Point"}
}