{
  "type": "Feature",
  "properties": {
    "iso:country":"BE",
    "sg:address":"La Cl\u00e9 Des Champs 49",
    "sg:city":"Wezembeek-oppem",
    "sg:classifiers":[
        {
            "category":"Health Services",
            "subcategory":"Doctor",
            "type":"Services"
        }
    ],
    "sg:phone":"+32 2 731 86 17",
    "sg:postcode":"1970",
    "sg:province":"Vlaams-Brabant",
    "sg:tags":[
        "medicinephysicians",
        "surgeon"
    ],
    "wof:name":"Appelmans Y",
    "wof:placetype":"venue"
},
  "geometry": {"coordinates":[4.4877390862,50.8463478088],"type":"Point"}
}