{
  "type": "Feature",
  "properties": {
    "addr:full":"Place Aux Foires 7 Durbuy Luxembourg 6940",
    "addr:housenumber":"7",
    "addr:postcode":"6940",
    "addr:street":"Place Aux Foires",
    "iso:country":"BE",
    "sg:address":"Place Aux Foires 7",
    "sg:city":"Durbuy",
    "sg:orig_category":"H\u00f4tels",
    "sg:phone":"+32 86 21 30 32",
    "sg:postcode":"6940",
    "sg:province":"Luxembourg",
    "wof:name":"H\u00d4tel C\u00d4t\u00c9 Jardin - Cour",
    "wof:placetype":"venue"
},
  "geometry": {"coordinates":[5.4564990997,50.3511276245],"type":"Point"}
}