{
  "type": "Feature",
  "properties": {
    "iso:country":"BE",
    "sg:address":"Arendsstraat 21a",
    "sg:city":"Harelbeke",
    "sg:classifiers":[
        {
            "category":"Shopping",
            "subcategory":"Florist",
            "type":"Retail Goods"
        }
    ],
    "sg:phone":"+32 56 70 46 84",
    "sg:postcode":"8530",
    "sg:province":"West-Vlaanderen",
    "wof:name":"Hortensis",
    "wof:placetype":"venue"
},
  "geometry": {"coordinates":[3.3183529377,50.8570671082],"type":"Point"}
}