{
  "type": "Feature",
  "properties": {
    "iso:country":"BE",
    "sg:address":"Rue Du Chimiste 26",
    "sg:city":"Anderlecht",
    "sg:orig_category":"Agences d'exp\u00e9dition",
    "sg:phone":"+32 2 520 37 43",
    "sg:postcode":"1070",
    "sg:province":"Bruxelles-Capitale",
    "wof:name":"W S B Export",
    "wof:placetype":"venue"
},
  "geometry": {"coordinates":[4.333384037,50.8459739685],"type":"Point"}
}