{
  "type": "Feature",
  "properties": {
    "addr:full":"Peperstraat 39 Herzele Oost-Vlaanderen 9550",
    "addr:housenumber":"39",
    "addr:postcode":"9550",
    "addr:street":"Peperstraat;Oost-Vlaanderen",
    "iso:country":"BE",
    "sg:address":"Peperstraat 39",
    "sg:city":"Herzele",
    "sg:classifiers":[
        {
            "category":"Personal",
            "subcategory":"Skin Care",
            "type":"Services"
        }
    ],
    "sg:phone":"+32 53 62 20 34",
    "sg:postcode":"9550",
    "sg:province":"Oost-Vlaanderen",
    "sg:tags":[
        "shaver"
    ],
    "wof:name":"De Raeve L",
    "wof:placetype":"venue"
},
  "geometry": {"coordinates":[3.8954570293,50.885181427],"type":"Point"}
}