{
  "type": "Feature",
  "properties": {
    "addr:full":"Europaplein 4 Maasmechelen (eisden) Limburg 3630",
    "addr:housenumber":"4",
    "addr:postcode":"3630",
    "addr:street":"Europaplein",
    "iso:country":"BE",
    "sg:address":"Europaplein 4",
    "sg:city":"Maasmechelen (eisden)",
    "sg:classifiers":[
        {
            "category":"Cafe",
            "type":"Food & Drink"
        }
    ],
    "sg:phone":"+32 89 77 41 58",
    "sg:postcode":"3630",
    "sg:province":"Limburg",
    "sg:tags":[
        "snack-bars"
    ],
    "wof:name":"Efes",
    "wof:placetype":"venue"
},
  "geometry": {"coordinates":[5.6961350441,50.963848114],"type":"Point"}
}