{
  "type": "Feature",
  "properties": {
    "addr:full":"Rue Bertinchamps 12 Sombreffe Namur 5140",
    "addr:housenumber":"12",
    "addr:postcode":"5140",
    "addr:street":"Rue Bertinchamps",
    "iso:country":"BE",
    "sg:address":"Rue Bertinchamps 12",
    "sg:city":"Sombreffe",
    "sg:classifiers":[
        {
            "category":"Professional",
            "subcategory":"Lawyer & Legal Services",
            "type":"Services"
        }
    ],
    "sg:phone":"+32 71 88 81 22",
    "sg:postcode":"5140",
    "sg:province":"Namur",
    "sg:tags":[
        "notary"
    ],
    "wof:name":"Charpentier A",
    "wof:placetype":"venue"
},
  "geometry": {"coordinates":[4.6041259766,50.5270996094],"type":"Point"}
}