{
  "type": "Feature",
  "properties": {
    "iso:country":"BE",
    "sg:address":"Generaal Lartiguelaan 45",
    "sg:city":"Sint-lambrechts-woluwe/woluwe-saint-lambert",
    "sg:orig_category":"Artsen and specialisten",
    "sg:phone":"+32 2 736 90 89",
    "sg:postcode":"1200",
    "sg:province":"Bruxelles-Capitale",
    "wof:name":"St\u00c9phane Van Rooijen",
    "wof:placetype":"venue"
},
  "geometry": {"coordinates":[4.4093689919,50.8463172913],"type":"Point"}
}