{
  "type": "Feature",
  "properties": {
    "addr:full":"Kortrijkstraat 66 Wortegem-petegem Oost-Vlaanderen 9790",
    "addr:housenumber":"66",
    "addr:postcode":"9790",
    "addr:street":"Kortrijkstraat",
    "iso:country":"BE",
    "sg:address":"Kortrijkstraat 66",
    "sg:city":"Wortegem-petegem",
    "sg:orig_category":"Huishoudapparaten, televisies and radio's",
    "sg:phone":"+32 55 38 82 84",
    "sg:postcode":"9790",
    "sg:province":"Oost-Vlaanderen",
    "wof:name":"Anex",
    "wof:placetype":"venue"
},
  "geometry": {"coordinates":[3.5402600765,50.8192100525],"type":"Point"}
}