{
  "type": "Feature",
  "properties": {
    "addr:full":"Avenue Georges Henry 390 Brussel/bruxelles Bruxelles-Capitale 1200",
    "addr:housenumber":"390",
    "addr:postcode":"1200",
    "addr:street":"Avenue Georges Henry;/",
    "iso:country":"BE",
    "sg:address":"Avenue Georges Henry 390",
    "sg:city":"Brussel/bruxelles",
    "sg:orig_category":"Librairies",
    "sg:phone":"+32 2 736 86 46",
    "sg:postcode":"1200",
    "sg:province":"Bruxelles-Capitale",
    "wof:name":"Boutique Bedephage",
    "wof:placetype":"venue"
},
  "geometry": {"coordinates":[4.4068188667,50.8426017761],"type":"Point"}
}