{
  "type": "Feature",
  "properties": {
    "iso:country":"BE",
    "sg:address":"Boulevard Du Midi 52",
    "sg:city":"Bruxelles",
    "sg:orig_category":"Non-Classified Establishments",
    "sg:phone":"+32 2 511 77 11",
    "sg:postcode":"1000",
    "sg:province":"Bruxelles-Capitale",
    "wof:name":"De Coster Uniformier",
    "wof:placetype":"venue"
},
  "geometry": {"coordinates":[4.3407049179,50.8409461975],"type":"Point"}
}