{
  "type": "Feature",
  "properties": {
    "addr:full":"Gen. Baron Jacquesstraat 60 Diksmuide West-Vlaanderen 8600",
    "addr:housenumber":"60",
    "addr:postcode":"8600",
    "addr:street":"Gen. Baron Jacquesstraat",
    "iso:country":"BE",
    "sg:address":"Gen. Baron Jacquesstraat 60",
    "sg:city":"Diksmuide",
    "sg:orig_category":"HERSTELLING ELEKTRISCHE HUISHOUDAPPARATEN Huishoudapparaten, televisies and radio's",
    "sg:phone":"+32 51 50 03 84",
    "sg:postcode":"8600",
    "sg:province":"West-Vlaanderen",
    "wof:name":"Elektro Sansen",
    "wof:placetype":"venue"
},
  "geometry": {"coordinates":[2.8605771065,51.0332717896],"type":"Point"}
}