{
  "type": "Feature",
  "properties": {
    "addr:full":"Gasthuisstraat 10 Box 7 Lanaken Limburg 3620",
    "addr:housenumber":"10;7",
    "addr:postcode":"3620",
    "addr:street":"Gasthuisstraat;Box",
    "iso:country":"BE",
    "sg:address":"Gasthuisstraat 10 Box 7",
    "sg:city":"Lanaken",
    "sg:classifiers":[
        {
            "category":"Communications",
            "subcategory":"Television Station",
            "type":"Services"
        }
    ],
    "sg:phone":"+32 477 23 27 32",
    "sg:postcode":"3620",
    "sg:province":"Limburg",
    "sg:tags":[
        "report",
        "video"
    ],
    "wof:name":"Jeandarme M",
    "wof:placetype":"venue"
},
  "geometry": {"coordinates":[5.6528501511,50.8881263733],"type":"Point"}
}