{
  "type": "Feature",
  "properties": {
    "addr:full":"Boulevard Du Souverain 146 Bruxelles (auderghem) Bruxelles-Capitale 1160",
    "addr:housenumber":"146",
    "addr:postcode":"1160",
    "addr:street":"Boulevard Du Souverain",
    "iso:country":"BE",
    "sg:address":"Boulevard Du Souverain 146",
    "sg:city":"Bruxelles (auderghem)",
    "sg:classifiers":[
        {
            "category":"Professional",
            "subcategory":"Computer Services",
            "type":"Services"
        }
    ],
    "sg:phone":"+32 2 673 06 74",
    "sg:postcode":"1160",
    "sg:province":"Bruxelles-Capitale",
    "sg:tags":[
        "webdesign",
        "-",
        "internet"
    ],
    "wof:name":"Callibra Sprl",
    "wof:placetype":"venue"
},
  "geometry": {"coordinates":[4.4274029732,50.8109321594],"type":"Point"}
}