{
  "type": "Feature",
  "properties": {
    "iso:country":"BE",
    "sg:address":"Euphrosina Beernaertstraat 58 Box 1",
    "sg:city":"Oostende",
    "sg:classifiers":[
        {
            "category":"Professional",
            "subcategory":"Lawyer & Legal Services",
            "type":"Services"
        }
    ],
    "sg:phone":"+32 59 56 50 30",
    "sg:postcode":"8400",
    "sg:province":"West-Vlaanderen",
    "wof:name":"Coucke Antoon",
    "wof:placetype":"venue"
},
  "geometry": {"coordinates":[2.9146289825,51.2272758484],"type":"Point"}
}