{
  "type": "Feature",
  "properties": {
    "addr:full":"Avenue F\u00e9n\u00e9lon 108 Colfontaine (p\u00e2turages) Hainaut 7340",
    "addr:housenumber":"108",
    "addr:postcode":"7340",
    "addr:street":"Avenue Fe\u0301Ne\u0301Lon",
    "iso:country":"BE",
    "sg:address":"Avenue F\u00e9n\u00e9lon 108",
    "sg:city":"Colfontaine (p\u00e2turages)",
    "sg:classifiers":[
        {
            "category":"Home & Garden",
            "subcategory":"Garden Supply",
            "type":"Retail Goods"
        }
    ],
    "sg:phone":"+32 65 66 15 88",
    "sg:postcode":"7340",
    "sg:province":"Hainaut",
    "sg:tags":[
        "director",
        "funeral",
        "-"
    ],
    "wof:name":"Urbain Alain",
    "wof:placetype":"venue"
},
  "geometry": {"coordinates":[3.8631579876,50.4052276611],"type":"Point"}
}