{
  "type": "Feature",
  "properties": {
    "addr:full":"Waverse Steenweg 1130 Oudergem/auderghem Bruxelles-Capitale 1160",
    "addr:postcode":"1130;1160",
    "addr:street":"Waverse Steenweg",
    "iso:country":"BE",
    "sg:address":"Waverse Steenweg 1130",
    "sg:city":"Oudergem/auderghem",
    "sg:orig_category":"Herstellingen and onderhoud aan huis voor voertuigen Metaalafval, schrootrecyclage and sloperijen",
    "sg:phone":"+32 2 736 40 44",
    "sg:postcode":"1160",
    "sg:province":"Bruxelles-Capitale",
    "wof:name":"B.b.m. Recup",
    "wof:placetype":"venue"
},
  "geometry": {"coordinates":[4.4036140442,50.8224868774],"type":"Point"}
}