{
  "type": "Feature",
  "properties": {
    "addr:full":"Koningin Astridlaan 7 Landen Vlaams-Brabant 3400",
    "addr:housenumber":"7",
    "addr:postcode":"3400",
    "addr:street":"Koningin Astridlaan",
    "iso:country":"BE",
    "sg:address":"Koningin Astridlaan 7",
    "sg:city":"Landen",
    "sg:classifiers":[
        {
            "category":"Health Services",
            "subcategory":"Doctor",
            "type":"Services"
        }
    ],
    "sg:phone":"+32 11 88 11 31",
    "sg:postcode":"3400",
    "sg:province":"Vlaams-Brabant",
    "sg:tags":[
        "medicinephysicians",
        "surgeon"
    ],
    "wof:name":"De Backere Y",
    "wof:placetype":"venue"
},
  "geometry": {"coordinates":[5.0777049065,50.7427406311],"type":"Point"}
}