{
  "type": "Feature",
  "properties": {
    "addr:full":"Chemin De L'alloux 8 Ciney Namur 5590",
    "addr:housenumber":"8",
    "addr:postcode":"5590",
    "addr:street":"Chemin De L'Alloux",
    "iso:country":"BE",
    "sg:address":"Chemin De L'alloux 8",
    "sg:city":"Ciney",
    "sg:classifiers":[
        {
            "category":"Autos & Motor Vehicles",
            "subcategory":"Automobile Sales",
            "type":"Retail Goods"
        }
    ],
    "sg:phone":"+32 83 21 20 02",
    "sg:postcode":"5590",
    "sg:province":"Namur",
    "sg:tags":[
        "car",
        "used",
        "-"
    ],
    "wof:name":"Miler R",
    "wof:placetype":"venue"
},
  "geometry": {"coordinates":[5.1171360016,50.2988853455],"type":"Point"}
}