{
  "type": "Feature",
  "properties": {
    "addr:full":"Avenue Charles Michiels 174 Watermaal-bosvoorde/watermael-boitsfort Bruxelles-Capitale 1170",
    "addr:housenumber":"174;/",
    "addr:postcode":"1170",
    "addr:street":"Avenue Charles Michiels;Watermaal-Bosvoorde",
    "iso:country":"BE",
    "sg:address":"Avenue Charles Michiels 174",
    "sg:city":"Watermaal-bosvoorde/watermael-boitsfort",
    "sg:orig_category":"S\u00e9lection de personnel and placement",
    "sg:phone":"+32 2 673 78 50",
    "sg:postcode":"1170",
    "sg:province":"Bruxelles-Capitale",
    "wof:name":"C.m.c.",
    "wof:placetype":"venue"
},
  "geometry": {"coordinates":[4.4031748772,50.8146247864],"type":"Point"}
}