{
  "type": "Feature",
  "properties": {
    "iso:country":"BE",
    "sg:address":"Frans Gasthuislaan 2",
    "sg:city":"Ganshoren/ganshoren",
    "sg:orig_category":"Apotheken",
    "sg:phone":"+32 2 426 55 12",
    "sg:postcode":"1083",
    "sg:province":"Bruxelles-Capitale",
    "wof:name":"Pharmacie Tielen",
    "wof:placetype":"venue"
},
  "geometry": {"coordinates":[4.3145489693,50.8671760559],"type":"Point"}
}