{
  "type": "Feature",
  "properties": {
    "iso:country":"BE",
    "sg:address":"Rue Croisette 76",
    "sg:city":"Mons (jemappes)",
    "sg:classifiers":[
        {
            "category":"Communications",
            "subcategory":"Film & Video Production",
            "type":"Services"
        }
    ],
    "sg:phone":"+32 65 82 59 29",
    "sg:postcode":"7012",
    "sg:province":"Hainaut",
    "sg:tags":[
        "videotape",
        "duplication",
        "-"
    ],
    "wof:name":"Studio Vid\u00e9o S",
    "wof:placetype":"venue"
},
  "geometry": {"coordinates":[3.8894600868,50.4481964111],"type":"Point"}
}