{
  "type": "Feature",
  "properties": {
    "iso:country":"BE",
    "sg:address":"Rue De Mortagne 44ba",
    "sg:city":"Peruwelz",
    "sg:orig_category":"V\u00e9t\u00e9rinaires",
    "sg:phone":"+32 69 77 55 22",
    "sg:postcode":"7604",
    "sg:province":"Hainaut",
    "wof:name":"Alex Debailleul",
    "wof:placetype":"venue"
},
  "geometry": {"coordinates":[3.5557479858,50.5643234253],"type":"Point"}
}