{
  "type": "Feature",
  "properties": {
    "addr:full":"Ramboutstraat 27 Diksmuide (vladslo) West-Vlaanderen 8600",
    "addr:housenumber":"27",
    "addr:postcode":"8600",
    "addr:street":"Ramboutstraat",
    "iso:country":"BE",
    "sg:address":"Ramboutstraat 27",
    "sg:city":"Diksmuide (vladslo)",
    "sg:classifiers":[
        {
            "category":"Wholesale",
            "subcategory":"Machinery & Supplies",
            "type":"Manufacturing & Wholesale Goods"
        }
    ],
    "sg:phone":"+32 51 50 31 96",
    "sg:postcode":"8600",
    "sg:province":"West-Vlaanderen",
    "sg:tags":[
        "agricultural",
        "tractor"
    ],
    "wof:name":"Depauw L",
    "wof:placetype":"venue"
},
  "geometry": {"coordinates":[2.9126050472,51.077545166],"type":"Point"}
}