{
  "type": "Feature",
  "properties": {
    "iso:country":"BE",
    "sg:address":"Stwg Naar Neeroeteren 21ba",
    "sg:city":"Dilsen-stokkem",
    "sg:classifiers":[
        {
            "category":"Cafe",
            "type":"Food & Drink"
        }
    ],
    "sg:phone":"+32 89 86 14 54",
    "sg:postcode":"3650",
    "sg:province":"Limburg",
    "sg:tags":[
        "caf\u00e9s"
    ],
    "wof:name":"Caf\u00c9 De Zwarte Kat",
    "wof:placetype":"venue"
},
  "geometry": {"coordinates":[5.7261199951,51.0690307617],"type":"Point"}
}