{
  "type": "Feature",
  "properties": {
    "addr:full":"Rue De Trooz 37 Chaudfontaine Li\u00e8ge 4052",
    "addr:housenumber":"37",
    "addr:postcode":"4052",
    "addr:street":"Rue De Trooz",
    "iso:country":"BE",
    "sg:address":"Rue De Trooz 37",
    "sg:city":"Chaudfontaine",
    "sg:orig_category":"Zalen voor culturele evenementen",
    "sg:phone":"+32 4 368 30 06",
    "sg:postcode":"4052",
    "sg:province":"Li\u00e8ge",
    "wof:name":"Val-des-pres",
    "wof:placetype":"venue"
},
  "geometry": {"coordinates":[5.6392202377,50.5586051941],"type":"Point"}
}