{
  "type": "Feature",
  "properties": {
    "addr:full":"Houtestraat 46 Mechelen (hombeek) Antwerpen 2811",
    "addr:housenumber":"46",
    "addr:postcode":"2811",
    "addr:street":"Houtestraat",
    "iso:country":"BE",
    "sg:address":"Houtestraat 46",
    "sg:city":"Mechelen (hombeek)",
    "sg:classifiers":[
        {
            "category":"Professional",
            "subcategory":"Art Services",
            "type":"Services"
        }
    ],
    "sg:phone":"+32 15 42 13 27",
    "sg:postcode":"2811",
    "sg:province":"Antwerpen",
    "sg:tags":[
        "photographer"
    ],
    "wof:name":"Collier J",
    "wof:placetype":"venue"
},
  "geometry": {"coordinates":[4.4388670921,51.0037765503],"type":"Point"}
}