{
  "type": "Feature",
  "properties": {
    "addr:full":"Rue De Bruxelles 43 Namur Namur 5000",
    "addr:housenumber":"43",
    "addr:postcode":"5000",
    "addr:street":"Rue De Bruxelles",
    "iso:country":"BE",
    "sg:address":"Rue De Bruxelles 43",
    "sg:city":"Namur",
    "sg:orig_category":"Levensverzekeringsmaatschappijen Verzekeringen vastgoed",
    "sg:phone":"+32 81 24 32 11",
    "sg:postcode":"5000",
    "sg:province":"Namur",
    "wof:name":"Fortis",
    "wof:placetype":"venue"
},
  "geometry": {"coordinates":[4.8620138168,50.4654998779],"type":"Point"}
}