{
  "type": "Feature",
  "properties": {
    "addr:full":"Leeuwerikstraat 4 Vosselaar Antwerpen 2350",
    "addr:housenumber":"4",
    "addr:postcode":"2350",
    "addr:street":"Leeuwerikstraat",
    "iso:country":"BE",
    "sg:address":"Leeuwerikstraat 4",
    "sg:city":"Vosselaar",
    "sg:orig_category":"Loodgieterij, verwarming and sanitaire installaties",
    "sg:phone":"+32 14 61 70 02",
    "sg:postcode":"2350",
    "sg:province":"Antwerpen",
    "wof:name":"Fa. Verdisan",
    "wof:placetype":"venue"
},
  "geometry": {"coordinates":[4.8852620125,51.3081970215],"type":"Point"}
}