{
  "type": "Feature",
  "properties": {
    "iso:country":"BE",
    "sg:address":"Hubert Fr\u00c8re-orbanlaan 228",
    "sg:city":"Gent",
    "sg:orig_category":"Deurwaarders",
    "sg:phone":"+32 9 265 76 51",
    "sg:postcode":"9000",
    "sg:province":"Oost-Vlaanderen",
    "wof:name":"K. De Knibber",
    "wof:placetype":"venue"
},
  "geometry": {"coordinates":[3.7351999283,51.0425491333],"type":"Point"}
}