{
  "type": "Feature",
  "properties": {
    "addr:full":"Op Den Hamel 9 Wellen Limburg 3832",
    "addr:housenumber":"9",
    "addr:postcode":"3832",
    "addr:street":"Op Den Hamel",
    "iso:country":"BE",
    "sg:address":"Op Den Hamel 9",
    "sg:city":"Wellen",
    "sg:orig_category":"Fruitteelt",
    "sg:phone":"+32 11 31 56 40",
    "sg:postcode":"3832",
    "sg:province":"Limburg",
    "wof:name":"Joseph Vaesen",
    "wof:placetype":"venue"
},
  "geometry": {"coordinates":[5.3002128601,50.8468017578],"type":"Point"}
}