{
  "type": "Feature",
  "properties": {
    "addr:full":"Pronkenbergstraat 53 Kontich Antwerpen 2550",
    "addr:housenumber":"53",
    "addr:postcode":"2550",
    "addr:street":"Pronkenbergstraat",
    "iso:country":"BE",
    "sg:address":"Pronkenbergstraat 53",
    "sg:city":"Kontich",
    "sg:classifiers":[
        {
            "category":"Taxi",
            "type":"Transportation"
        }
    ],
    "sg:phone":"+32 3 457 68 78",
    "sg:postcode":"2550",
    "sg:province":"Antwerpen",
    "sg:tags":[
        "taxicab"
    ],
    "wof:name":"Taxi Crauwels Willy Kontich",
    "wof:placetype":"venue"
},
  "geometry": {"coordinates":[4.4653811455,51.1269187927],"type":"Point"}
}