{
  "type": "Feature",
  "properties": {
    "iso:country":"BE",
    "sg:address":"Ketenstraat 12",
    "sg:city":"Moorslede",
    "sg:orig_category":"Pain, p\u00e2tisseries and confiseries",
    "sg:phone":"+32 56 50 53 32",
    "sg:postcode":"8890",
    "sg:province":"West-Vlaanderen",
    "wof:name":"Jurgen Todts",
    "wof:placetype":"venue"
},
  "geometry": {"coordinates":[3.0939800739,50.8504180908],"type":"Point"}
}