{
  "type": "Feature",
  "properties": {
    "iso:country":"BE",
    "sg:address":"Kardinaal Mercierlaan 22 Box 7",
    "sg:city":"De Haan (klemskerke)",
    "sg:classifiers":[
        {
            "category":"Banks & Credit Unions",
            "subcategory":"Investment Brokerage",
            "type":"Services"
        }
    ],
    "sg:phone":"+32 59 29 81 12",
    "sg:postcode":"8420",
    "sg:province":"West-Vlaanderen",
    "sg:tags":[
        "fence"
    ],
    "wof:name":"Croes G",
    "wof:placetype":"venue"
},
  "geometry": {"coordinates":[3.0328929424,51.2701644897],"type":"Point"}
}