{
  "type": "Feature",
  "properties": {
    "addr:full":"Hoogstadestraat 62 Alveringem West-Vlaanderen 8690",
    "addr:housenumber":"62",
    "addr:postcode":"8690",
    "addr:street":"Hoogstadestraat",
    "iso:country":"BE",
    "sg:address":"Hoogstadestraat 62",
    "sg:city":"Alveringem",
    "sg:orig_category":"Installatie van houten of kunststof schrijnwerk",
    "sg:phone":"+32 58 28 87 96",
    "sg:postcode":"8690",
    "sg:province":"West-Vlaanderen",
    "wof:name":"Hugo Vanhee",
    "wof:placetype":"venue"
},
  "geometry": {"coordinates":[2.6850340366,51.0017242432],"type":"Point"}
}