{
  "type": "Feature",
  "properties": {
    "addr:full":"Ravelsbrug Oud-turnhout Antwerpen 2360",
    "addr:postcode":"2360",
    "addr:street":"Ravelsbrug",
    "iso:country":"BE",
    "sg:address":"Ravelsbrug",
    "sg:city":"Oud-turnhout",
    "sg:orig_category":"Bouwmaterialen Gh",
    "sg:phone":"+32 14 42 44 61",
    "sg:postcode":"2360",
    "sg:province":"Antwerpen",
    "wof:name":"Ttr Dakpannenfabriek",
    "wof:placetype":"venue"
},
  "geometry": {"coordinates":[4.9856901169,51.34815979],"type":"Point"}
}