{
  "type": "Feature",
  "properties": {
    "iso:country":"BE",
    "sg:address":"Alkenstraat 134",
    "sg:city":"Hasselt (stevoort)",
    "sg:classifiers":[
        {
            "category":"Retail",
            "subcategory":"Auto Repair",
            "type":"Services"
        }
    ],
    "sg:phone":"+32 11 59 15 16",
    "sg:postcode":"3512",
    "sg:province":"Limburg",
    "sg:tags":[
        "garage"
    ],
    "wof:name":"Megaband",
    "wof:placetype":"venue"
},
  "geometry": {"coordinates":[5.2610349655,50.9071350098],"type":"Point"}
}