{
  "type": "Feature",
  "properties": {
    "addr:full":"Rue Louis Delhove 2 Bruxelles (ganshoren) Bruxelles-Capitale 1083",
    "addr:housenumber":"2",
    "addr:postcode":"1083",
    "addr:street":"Rue Louis Delhove",
    "iso:country":"BE",
    "sg:address":"Rue Louis Delhove 2",
    "sg:city":"Bruxelles (ganshoren)",
    "sg:classifiers":[
        {
            "category":"Bars & Pubs",
            "type":"Food & Drink"
        }
    ],
    "sg:phone":"+32 2 425 25 40",
    "sg:postcode":"1083",
    "sg:province":"Bruxelles-Capitale",
    "sg:tags":[
        "tavern"
    ],
    "wof:name":"The Game's",
    "wof:placetype":"venue"
},
  "geometry": {"coordinates":[4.3180608749,50.8706169128],"type":"Point"}
}