{
  "type": "Feature",
  "properties": {
    "addr:full":"Boulevard D\u00b4avroy 77 Li\u00c8ge Li\u00e8ge 4000",
    "addr:housenumber":"77",
    "addr:postcode":"4000",
    "addr:street":"Boulevard D\u00b4Avroy",
    "iso:country":"BE",
    "sg:address":"Boulevard D\u00b4avroy 77",
    "sg:city":"Li\u00c8ge",
    "sg:orig_category":"Antiquit\u00e9s",
    "sg:phone":"+32 4 223 52 35",
    "sg:postcode":"4000",
    "sg:province":"Li\u00e8ge",
    "wof:name":"Paulypin",
    "wof:placetype":"venue"
},
  "geometry": {"coordinates":[5.5687570572,50.6362991333],"type":"Point"}
}