{
  "type": "Feature",
  "properties": {
    "addr:full":"Place De L'h\u00f4tel De Ville 28 Wavre Brabant Wallon 1300",
    "addr:housenumber":"28;1300",
    "addr:street":"Place De L'Ho \u0302Tel De Ville",
    "iso:country":"BE",
    "sg:address":"Place De L'h\u00f4tel De Ville 28",
    "sg:city":"Wavre",
    "sg:classifiers":[
        {
            "category":"Shopping",
            "subcategory":"Clothing, Apparel, & Fashions",
            "type":"Retail Goods"
        }
    ],
    "sg:phone":"+32 71 31 82 68",
    "sg:postcode":"1300",
    "sg:province":"Brabant Wallon",
    "sg:tags":[
        "underwear",
        "lingerie",
        "-"
    ],
    "wof:name":"Damart",
    "wof:placetype":"venue"
},
  "geometry": {"coordinates":[4.6109271049,50.7185287476],"type":"Point"}
}