{
  "type": "Feature",
  "properties": {
    "addr:full":"Avenue Reine Astrid 345 Kraainem Vlaams-Brabant 1950",
    "addr:housenumber":"345",
    "addr:postcode":"1950",
    "addr:street":"Avenue Reine Astrid",
    "iso:country":"BE",
    "sg:address":"Avenue Reine Astrid 345",
    "sg:city":"Kraainem",
    "sg:classifiers":[
        {
            "category":"Personal",
            "subcategory":"Nail Salon",
            "type":"Services"
        }
    ],
    "sg:phone":"+32 2 782 18 61",
    "sg:postcode":"1950",
    "sg:province":"Vlaams-Brabant",
    "sg:tags":[
        "pedicure"
    ],
    "wof:name":"Scheers H",
    "wof:placetype":"venue"
},
  "geometry": {"coordinates":[4.4686260223,50.8424453735],"type":"Point"}
}