{
  "type": "Feature",
  "properties": {
    "addr:full":"Rue Meyerbeer 7 Bruxelles (forest) Bruxelles-Capitale 1190",
    "addr:housenumber":"7",
    "addr:postcode":"1190",
    "addr:street":"Rue Meyerbeer",
    "iso:country":"BE",
    "sg:address":"Rue Meyerbeer 7",
    "sg:city":"Bruxelles (forest)",
    "sg:classifiers":[
        {
            "category":"Freight",
            "type":"Transportation"
        }
    ],
    "sg:phone":"+32 2 387 28 21",
    "sg:postcode":"1190",
    "sg:province":"Bruxelles-Capitale",
    "sg:tags":[
        "-",
        "transport"
    ],
    "wof:name":"Bebede Transport",
    "wof:placetype":"venue"
},
  "geometry": {"coordinates":[4.3464121819,50.8150939941],"type":"Point"}
}