{
  "type": "Feature",
  "properties": {
    "addr:full":"Venecoweg 9 Nazareth Oost-Vlaanderen 9810",
    "addr:housenumber":"9",
    "addr:postcode":"9810",
    "addr:street":"Venecoweg",
    "iso:country":"BE",
    "sg:address":"Venecoweg 9",
    "sg:city":"Nazareth",
    "sg:classifiers":[
        {
            "category":"Shopping",
            "subcategory":"Clothing, Apparel, & Fashions",
            "type":"Retail Goods"
        }
    ],
    "sg:phone":"+32 9 384 91 43",
    "sg:postcode":"9810",
    "sg:province":"Oost-Vlaanderen",
    "sg:tags":[
        "lining",
        "clothing",
        "-"
    ],
    "wof:name":"Jdc Nv",
    "wof:placetype":"venue"
},
  "geometry": {"coordinates":[3.5542340279,50.953338623],"type":"Point"}
}