{
  "type": "Feature",
  "properties": {
    "iso:country":"BE",
    "sg:address":"Struykstraat 93",
    "sg:city":"Bekkevoort",
    "sg:classifiers":[
        {
            "category":"Health Services",
            "subcategory":"Doctor",
            "type":"Services"
        }
    ],
    "sg:phone":"+32 13 33 45 71",
    "sg:postcode":"3460",
    "sg:province":"Vlaams-Brabant",
    "sg:tags":[
        "medicinephysicians",
        "surgeon"
    ],
    "wof:name":"Laenen Kristel",
    "wof:placetype":"venue"
},
  "geometry": {"coordinates":[5.0028448105,50.936164856],"type":"Point"}
}