{
  "type": "Feature",
  "properties": {
    "addr:full":"Brusselstraat 68 Roosdaal Vlaams-Brabant 1761",
    "addr:housenumber":"68",
    "addr:postcode":"1761",
    "addr:street":"Brusselstraat",
    "iso:country":"BE",
    "sg:address":"Brusselstraat 68",
    "sg:city":"Roosdaal",
    "sg:classifiers":[
        {
            "category":"Taxi",
            "type":"Transportation"
        }
    ],
    "sg:phone":"+32 475 64 79 31",
    "sg:postcode":"1761",
    "sg:province":"Vlaams-Brabant",
    "sg:tags":[
        "taxi's"
    ],
    "wof:name":"Taxi Marc",
    "wof:placetype":"venue"
},
  "geometry": {"coordinates":[4.136548996,50.848526001],"type":"Point"}
}