{
  "type": "Feature",
  "properties": {
    "addr:full":"Rue Des Etangs Noirs 1ba Sint-jans-molenbeek/molenbeek-saint-jean Bruxelles-Capitale 1080",
    "addr:postcode":"1080",
    "addr:street":"Rue Des Etangs Noirs",
    "iso:country":"BE",
    "sg:address":"Rue Des Etangs Noirs 1ba",
    "sg:city":"Sint-jans-molenbeek/molenbeek-saint-jean",
    "sg:orig_category":"Pharmaciens",
    "sg:phone":"+32 2 411 20 82",
    "sg:postcode":"1080",
    "sg:province":"Bruxelles-Capitale",
    "wof:name":"M. Lambrechts",
    "wof:placetype":"venue"
},
  "geometry": {"coordinates":[4.3325400352,50.8570823669],"type":"Point"}
}