{
  "type": "Feature",
  "properties": {
    "addr:full":"Rue Emile Wittmann 51 Bruxelles (schaerbeek) Bruxelles-Capitale 1030",
    "addr:housenumber":"51",
    "addr:postcode":"1030",
    "addr:street":"Rue Emile Wittmann",
    "iso:country":"BE",
    "sg:address":"Rue Emile Wittmann 51",
    "sg:city":"Bruxelles (schaerbeek)",
    "sg:classifiers":[
        {
            "category":"Structure",
            "subcategory":"Building",
            "type":"Public Place"
        }
    ],
    "sg:phone":"+32 2 732 27 44",
    "sg:postcode":"1030",
    "sg:province":"Bruxelles-Capitale",
    "sg:tags":[
        "door"
    ],
    "wof:name":"Europa Wittmann Sprl",
    "wof:placetype":"venue"
},
  "geometry": {"coordinates":[4.3915529251,50.8553352356],"type":"Point"}
}