{
  "type": "Feature",
  "properties": {
    "addr:full":"Waterloose Steenweg 1488 Ukkel/uccle Bruxelles-Capitale 1180",
    "addr:postcode":"1488;1180",
    "addr:street":"Waterloose Steenweg",
    "iso:country":"BE",
    "sg:address":"Waterloose Steenweg 1488",
    "sg:city":"Ukkel/uccle",
    "sg:orig_category":"Herstellingen and onderhoud van auto's",
    "sg:phone":"+32 2 375 66 93",
    "sg:postcode":"1180",
    "sg:province":"Bruxelles-Capitale",
    "wof:name":"Carglass",
    "wof:placetype":"venue"
},
  "geometry": {"coordinates":[4.3787579536,50.7841262817],"type":"Point"}
}