{
  "type": "Feature",
  "properties": {
    "iso:country":"BE",
    "sg:address":"Naastveldstraat 155",
    "sg:city":"Lokeren",
    "sg:orig_category":"Produits c\u00e9r\u00e9aliers Fab",
    "sg:phone":"+32 9 348 18 97",
    "sg:postcode":"9160",
    "sg:province":"Oost-Vlaanderen",
    "wof:name":"Buydens",
    "wof:placetype":"venue"
},
  "geometry": {"coordinates":[3.978276968,51.0900726318],"type":"Point"}
}