{
  "type": "Feature",
  "properties": {
    "addr:full":"Rue Hameau De Barzin 120 Wellin Luxembourg 6924",
    "addr:housenumber":"120",
    "addr:postcode":"6924",
    "addr:street":"Rue Hameau De Barzin",
    "iso:country":"BE",
    "sg:address":"Rue Hameau De Barzin 120",
    "sg:city":"Wellin",
    "sg:orig_category":"Eclairage et \u00e9quipements du foyer",
    "sg:phone":"+32 2 657 74 02",
    "sg:postcode":"6924",
    "sg:province":"Luxembourg",
    "wof:name":"Table in",
    "wof:placetype":"venue"
},
  "geometry": {"coordinates":[5.0906729698,50.0760726929],"type":"Point"}
}