{
  "type": "Feature",
  "properties": {
    "iso:country":"BE",
    "sg:address":"Onze-lieve-vrouwstraat 110",
    "sg:city":"Mol",
    "sg:classifiers":[
        {
            "category":"Communications",
            "subcategory":"Radio Station",
            "type":"Services"
        }
    ],
    "sg:phone":"+32 14 31 49 61",
    "sg:postcode":"2400",
    "sg:province":"Antwerpen",
    "sg:tags":[
        "diffusion",
        "production",
        "de",
        "programme"
    ],
    "wof:name":"Lokale Radio Gompel",
    "wof:placetype":"venue"
},
  "geometry": {"coordinates":[5.1519579887,51.1932868958],"type":"Point"}
}