{
  "type": "Feature",
  "properties": {
    "addr:full":"Beverestraat 28a Oudenaarde Oost-Vlaanderen 9700",
    "addr:housenumber":"28a",
    "addr:postcode":"9700",
    "addr:street":"Beverestraat",
    "iso:country":"BE",
    "sg:address":"Beverestraat 28a",
    "sg:city":"Oudenaarde",
    "sg:classifiers":[
        {
            "category":"Retail",
            "subcategory":"Auto Repair",
            "type":"Services"
        }
    ],
    "sg:phone":"+32 55 31 48 05",
    "sg:postcode":"9700",
    "sg:province":"Oost-Vlaanderen",
    "sg:tags":[
        "automobile",
        "servic",
        "electrical",
        "-"
    ],
    "wof:name":"Auto-service Nv",
    "wof:placetype":"venue"
},
  "geometry": {"coordinates":[3.6010029316,50.8470535278],"type":"Point"}
}