{
  "type": "Feature",
  "properties": {
    "iso:country":"BE",
    "sg:address":"Oude Brusselsestraat 36",
    "sg:city":"Mechelen",
    "sg:orig_category":"Rev\u00eatements de sols and murs",
    "sg:phone":"+32 15 42 14 47",
    "sg:postcode":"2800",
    "sg:province":"Antwerpen",
    "wof:name":"Westwood-interiors",
    "wof:placetype":"venue"
},
  "geometry": {"coordinates":[4.4814009666,51.0215606689],"type":"Point"}
}