{
  "type": "Feature",
  "properties": {
    "iso:country":"BE",
    "sg:address":"Oostmoer Tuinwijk 13",
    "sg:city":"Waarschoot",
    "sg:orig_category":"Rev\u00eatements pour sols and murs",
    "sg:phone":"+32 9 377 86 62",
    "sg:postcode":"9950",
    "sg:province":"Oost-Vlaanderen",
    "wof:name":"Fa. Van Den Bossche",
    "wof:placetype":"venue"
},
  "geometry": {"coordinates":[3.6229009628,51.156627655],"type":"Point"}
}