{
  "type": "Feature",
  "properties": {
    "addr:full":"Rue Haute-sauveni\u00c8re 3 Li\u00c8ge Li\u00e8ge 4000",
    "addr:housenumber":"3",
    "addr:postcode":"4000",
    "addr:street":"Rue Haute-Sauvenie\u0300Re",
    "iso:country":"BE",
    "sg:address":"Rue Haute-sauveni\u00c8re 3",
    "sg:city":"Li\u00c8ge",
    "sg:orig_category":"Epiceries",
    "sg:phone":"+32 4 232 14 73",
    "sg:postcode":"4000",
    "sg:province":"Li\u00e8ge",
    "wof:name":"Abid Kebir",
    "wof:placetype":"venue"
},
  "geometry": {"coordinates":[5.5706977844,50.6443519592],"type":"Point"}
}