{
  "type": "Feature",
  "properties": {
    "addr:full":"Stationspl 7 Roeselare West-Vlaanderen 8800",
    "addr:housenumber":"7",
    "addr:postcode":"8800",
    "addr:street":"Stationspl",
    "iso:country":"BE",
    "sg:address":"Stationspl 7",
    "sg:city":"Roeselare",
    "sg:classifiers":[
        {
            "category":"Travel",
            "subcategory":"Hotels & Motels",
            "type":"Entertainment"
        }
    ],
    "sg:phone":"+32 51 26 31 31",
    "sg:postcode":"8800",
    "sg:province":"West-Vlaanderen",
    "sg:tags":[
        "professional",
        "hotels",
        "fair",
        "business",
        "restaurant"
    ],
    "wof:name":"Parkhotel Nv",
    "wof:placetype":"venue"
},
  "geometry": {"coordinates":[3.1297030449,50.9484024048],"type":"Point"}
}