{
  "type": "Feature",
  "properties": {
    "addr:full":"Rue Du Centre 13 Weismes Li\u00e8ge 4950",
    "addr:housenumber":"13",
    "addr:postcode":"4950",
    "addr:street":"Rue Du Centre",
    "iso:country":"BE",
    "sg:address":"Rue Du Centre 13",
    "sg:city":"Weismes",
    "sg:classifiers":[
        {
            "category":"Fast Food",
            "type":"Food & Drink"
        }
    ],
    "sg:phone":"+32 80 67 88 61",
    "sg:postcode":"4950",
    "sg:province":"Li\u00e8ge",
    "sg:tags":[
        "fried",
        "stand",
        "potato"
    ],
    "wof:name":"Coco-fri",
    "wof:placetype":"venue"
},
  "geometry": {"coordinates":[6.1114001274,50.4151992798],"type":"Point"}
}