{
  "type": "Feature",
  "properties": {
    "iso:country":"BE",
    "sg:address":"Bloemendalestraat 46 Box 2",
    "sg:city":"Beernem",
    "sg:classifiers":[
        {
            "category":"Professional",
            "subcategory":"Art Services",
            "type":"Services"
        }
    ],
    "sg:phone":"+32 50 79 11 87",
    "sg:postcode":"8730",
    "sg:province":"West-Vlaanderen",
    "sg:tags":[
        "photographer"
    ],
    "wof:name":"Cyclope Photographies",
    "wof:placetype":"venue"
},
  "geometry": {"coordinates":[3.3386850357,51.1409797668],"type":"Point"}
}