{
  "type": "Feature",
  "properties": {
    "iso:country":"BE",
    "sg:address":"Kortrijkstraat 82",
    "sg:city":"Wevelgem",
    "sg:orig_category":"Fleurs and plantes",
    "sg:phone":"+32 56 42 46 96",
    "sg:postcode":"8560",
    "sg:province":"West-Vlaanderen",
    "wof:name":"Verde",
    "wof:placetype":"venue"
},
  "geometry": {"coordinates":[3.1892819405,50.8103790283],"type":"Point"}
}