{
  "type": "Feature",
  "properties": {
    "iso:country":"BE",
    "sg:address":"Poti\u00c9rue 4",
    "sg:city":"Herve",
    "sg:orig_category":"V\u00eatements. V\u00eatements pour b\u00e9b\u00e9s and enfants. V\u00eatements pour Dames",
    "sg:phone":"+32 87 67 91 17",
    "sg:postcode":"4650",
    "sg:province":"Li\u00e8ge",
    "wof:name":"La Boutique D'odile",
    "wof:placetype":"venue"
},
  "geometry": {"coordinates":[5.7943129539,50.6396217346],"type":"Point"}
}