{
  "type": "Feature",
  "properties": {
    "iso:country":"BE",
    "sg:address":"Rue Des Combattants 94",
    "sg:city":"La Hulpe",
    "sg:orig_category":"Souvenirs and objets artisanaux. Eclairage et \u00e9quipements du foyer",
    "sg:phone":"+32 2 652 19 07",
    "sg:postcode":"1310",
    "sg:province":"Brabant Wallon",
    "wof:name":"D'un Soleil \u00c0 L'autre",
    "wof:placetype":"venue"
},
  "geometry": {"coordinates":[4.4868898392,50.7309837341],"type":"Point"}
}