{
  "type": "Feature",
  "properties": {
    "iso:country":"BE",
    "sg:address":"Sint-elisabethstraat 44",
    "sg:city":"Beveren (melsele)",
    "sg:classifiers":[
        {
            "category":"Food & Beverages",
            "subcategory":"Groceries & Convenience Stores",
            "type":"Retail Goods"
        }
    ],
    "sg:phone":"+32 3 775 90 89",
    "sg:postcode":"9120",
    "sg:province":"Oost-Vlaanderen",
    "sg:tags":[
        "grocer"
    ],
    "wof:name":"Ivens E",
    "wof:placetype":"venue"
},
  "geometry": {"coordinates":[4.2839770317,51.2213783264],"type":"Point"}
}