{
  "type": "Feature",
  "properties": {
    "addr:full":"Avenue De La Gare 1 Waver Brabant Wallon 1300",
    "addr:housenumber":"1",
    "addr:postcode":"1300",
    "addr:street":"Avenue De La Gare;Wallon",
    "iso:country":"BE",
    "sg:address":"Avenue De La Gare 1",
    "sg:city":"Waver",
    "sg:orig_category":"Treinen and spoorwegen",
    "sg:phone":"+32 10 24 30 54",
    "sg:postcode":"1300",
    "sg:province":"Brabant Wallon",
    "wof:name":"Gare De Limal",
    "wof:placetype":"venue"
},
  "geometry": {"coordinates":[4.6116552353,50.7134132385],"type":"Point"}
}