{
  "type": "Feature",
  "properties": {
    "addr:full":"Geraardsbergsesteenweg 151ba Melle Oost-Vlaanderen 9090",
    "addr:housenumber":"151ba",
    "addr:postcode":"9090",
    "addr:street":"Geraardsbergsesteenweg",
    "iso:country":"BE",
    "sg:address":"Geraardsbergsesteenweg 151ba",
    "sg:city":"Melle",
    "sg:orig_category":"Enseignement maternel and primaire",
    "sg:phone":"+32 9 252 52 50",
    "sg:postcode":"9090",
    "sg:province":"Oost-Vlaanderen",
    "wof:name":"Vrije Basisschool",
    "wof:placetype":"venue"
},
  "geometry": {"coordinates":[3.7989499569,50.9907608032],"type":"Point"}
}