{
  "type": "Feature",
  "properties": {
    "iso:country":"BE",
    "sg:address":"Rue Du Chaffour 17",
    "sg:city":"Nassogne",
    "sg:orig_category":"Rundveehouders",
    "sg:phone":"+32 84 21 23 04",
    "sg:postcode":"6953",
    "sg:province":"Luxembourg",
    "wof:name":"Charles Weron",
    "wof:placetype":"venue"
},
  "geometry": {"coordinates":[5.2774748802,50.1315689087],"type":"Point"}
}