{
  "type": "Feature",
  "properties": {
    "iso:country":"BE",
    "sg:address":"Rue Saint-paul 47",
    "sg:city":"Binche",
    "sg:orig_category":"Kapsalons",
    "sg:phone":"+32 64 33 86 19",
    "sg:postcode":"7130",
    "sg:province":"Hainaut",
    "wof:name":"Yves Groise",
    "wof:placetype":"venue"
},
  "geometry": {"coordinates":[4.168656826,50.4094848633],"type":"Point"}
}