{
  "type": "Feature",
  "properties": {
    "iso:country":"BE",
    "sg:address":"Haltbaan 23",
    "sg:city":"Lierde",
    "sg:classifiers":[
        {
            "category":"Personal",
            "subcategory":"Beauty Salon",
            "type":"Services"
        }
    ],
    "sg:phone":"+32 54 41 30 94",
    "sg:postcode":"9572",
    "sg:province":"Oost-Vlaanderen",
    "sg:tags":[
        "de",
        "coiffure"
    ],
    "wof:name":"Coiffure Lucienne",
    "wof:placetype":"venue"
},
  "geometry": {"coordinates":[3.847383976,50.8016815186],"type":"Point"}
}