{
  "type": "Feature",
  "properties": {
    "iso:country":"BE",
    "sg:address":"Alfred Algoetstraat 75",
    "sg:city":"Lennik",
    "sg:orig_category":"Openbare veiligheid",
    "sg:phone":"+32 2 532 41 13",
    "sg:postcode":"1750",
    "sg:province":"Vlaams-Brabant",
    "wof:name":"Federale Politie/police F\u00c9d\u00c9rale",
    "wof:placetype":"venue"
},
  "geometry": {"coordinates":[4.1623010635,50.8074417114],"type":"Point"}
}