{
  "type": "Feature",
  "properties": {
    "addr:full":"Rue D'assenois 77 Bastogne Luxembourg 6600",
    "addr:housenumber":"77",
    "addr:postcode":"6600",
    "addr:street":"Rue D'Assenois",
    "iso:country":"BE",
    "sg:address":"Rue D'assenois 77",
    "sg:city":"Bastogne",
    "sg:classifiers":[
        {
            "category":"Building & Trades",
            "subcategory":"Construction",
            "type":"Services"
        }
    ],
    "sg:phone":"+32 61 21 55 13",
    "sg:postcode":"6600",
    "sg:province":"Luxembourg",
    "sg:tags":[
        "installation",
        "-",
        "central",
        "heating"
    ],
    "wof:name":"Dasnoy B",
    "wof:placetype":"venue"
},
  "geometry": {"coordinates":[5.7085900307,49.99376297],"type":"Point"}
}