{
  "type": "Feature",
  "properties": {
    "addr:full":"Route De Perwez 91 Eghez\u00e9e (liernu) Namur 5310",
    "addr:housenumber":"91",
    "addr:postcode":"5310",
    "addr:street":"Route De Perwez;Liernu",
    "iso:country":"BE",
    "sg:address":"Route De Perwez 91",
    "sg:city":"Eghez\u00e9e (liernu)",
    "sg:classifiers":[
        {
            "category":"Personal",
            "subcategory":"Beauty Salon",
            "type":"Services"
        }
    ],
    "sg:phone":"+32 81 65 52 58",
    "sg:postcode":"5310",
    "sg:province":"Namur",
    "sg:tags":[
        "lady",
        "-",
        "hairdressing"
    ],
    "wof:name":"Roger",
    "wof:placetype":"venue"
},
  "geometry": {"coordinates":[4.8308649063,50.5831871033],"type":"Point"}
}