{
  "type": "Feature",
  "properties": {
    "addr:full":"Rue Des Ep\u00e9rires 63 Florenville Luxembourg 6820",
    "addr:housenumber":"63",
    "addr:postcode":"6820",
    "addr:street":"Rue Des Epe\u0301Rires",
    "iso:country":"BE",
    "sg:address":"Rue Des Ep\u00e9rires 63",
    "sg:city":"Florenville",
    "sg:classifiers":[
        {
            "category":"Professional",
            "subcategory":"Business Services",
            "type":"Services"
        }
    ],
    "sg:phone":"+32 61 31 46 59",
    "sg:postcode":"6820",
    "sg:province":"Luxembourg",
    "sg:tags":[
        "automobile",
        "-",
        "assessor"
    ],
    "wof:name":"Legrand Ing\u00e9nierie Scrl",
    "wof:placetype":"venue"
},
  "geometry": {"coordinates":[5.3016891479,49.7012825012],"type":"Point"}
}