{
  "type": "Feature",
  "properties": {
    "addr:full":"Keizersplein 56 Aalst Oost-Vlaanderen 9300",
    "addr:housenumber":"56",
    "addr:postcode":"9300",
    "addr:street":"Keizersplein",
    "iso:country":"BE",
    "sg:address":"Keizersplein 56",
    "sg:city":"Aalst",
    "sg:orig_category":"Avocats and conseillers juridiques",
    "sg:phone":"+32 53 70 59 27",
    "sg:postcode":"9300",
    "sg:province":"Oost-Vlaanderen",
    "wof:name":"Wouters Koen",
    "wof:placetype":"venue"
},
  "geometry": {"coordinates":[4.0375747681,50.9361457825],"type":"Point"}
}