{
  "type": "Feature",
  "properties": {
    "addr:full":"Rue Du Parnasse 2 Thuin Hainaut 6530",
    "addr:housenumber":"2",
    "addr:postcode":"6530",
    "addr:street":"Rue Du Parnasse",
    "iso:country":"BE",
    "sg:address":"Rue Du Parnasse 2",
    "sg:city":"Thuin",
    "sg:orig_category":"Huisdierenkwekers",
    "sg:phone":"+32 71 59 17 78",
    "sg:postcode":"6530",
    "sg:province":"Hainaut",
    "wof:name":"Jack Russell-pattyn",
    "wof:placetype":"venue"
},
  "geometry": {"coordinates":[4.2851338387,50.3351554871],"type":"Point"}
}