{
  "type": "Feature",
  "properties": {
    "addr:full":"Rue Haut-doux 3 Frasnes-lez-anvaing Hainaut 7911",
    "addr:housenumber":"3",
    "addr:postcode":"7911",
    "addr:street":"Rue Haut-Doux",
    "iso:country":"BE",
    "sg:address":"Rue Haut-doux 3",
    "sg:city":"Frasnes-lez-anvaing",
    "sg:orig_category":"Eleveurs de bovins",
    "sg:phone":"+32 69 86 62 91",
    "sg:postcode":"7911",
    "sg:province":"Hainaut",
    "wof:name":"Guy Delaunoy",
    "wof:placetype":"venue"
},
  "geometry": {"coordinates":[3.5945780277,50.6367721558],"type":"Point"}
}