{
  "type": "Feature",
  "properties": {
    "addr:full":"Molenstraat 16 Linkebeek Vlaams-Brabant 1630",
    "addr:housenumber":"16",
    "addr:postcode":"1630",
    "addr:street":"Molenstraat",
    "iso:country":"BE",
    "sg:address":"Molenstraat 16",
    "sg:city":"Linkebeek",
    "sg:orig_category":"Drukkerijen and copyshops",
    "sg:phone":"+32 2 380 92 68",
    "sg:postcode":"1630",
    "sg:province":"Vlaams-Brabant",
    "wof:name":"Pat Productions/pat Production",
    "wof:placetype":"venue"
},
  "geometry": {"coordinates":[4.3294301033,50.7763404846],"type":"Point"}
}