{
  "type": "Feature",
  "properties": {
    "iso:country":"BE",
    "sg:address":"Moerkantsebaan 49",
    "sg:city":"Essen",
    "sg:orig_category":"Pharmaciens",
    "sg:phone":"+32 3 667 49 42",
    "sg:postcode":"2910",
    "sg:province":"Antwerpen",
    "wof:name":"Apotheek Kerstens E.",
    "wof:placetype":"venue"
},
  "geometry": {"coordinates":[4.431499958,51.4531288147],"type":"Point"}
}