{
  "type": "Feature",
  "properties": {
    "addr:full":"Rue Du Godiassau 1 Gerpinnes Hainaut 6280",
    "addr:housenumber":"1",
    "addr:postcode":"6280",
    "addr:street":"Rue Du Godiassau;Hainaut",
    "iso:country":"BE",
    "sg:address":"Rue Du Godiassau 1",
    "sg:city":"Gerpinnes",
    "sg:orig_category":"Eleveurs de bovins",
    "sg:phone":"+32 71 50 13 42",
    "sg:postcode":"6280",
    "sg:province":"Hainaut",
    "wof:name":"Ernest Stroobants",
    "wof:placetype":"venue"
},
  "geometry": {"coordinates":[4.5026707649,50.352596283],"type":"Point"}
}