{
  "type": "Feature",
  "properties": {
    "iso:country":"BE",
    "sg:address":"Cyriel Prie\u00eblsstraat 197",
    "sg:city":"Ninove (aspelare)",
    "sg:classifiers":[
        {
            "category":"Freight",
            "type":"Transportation"
        }
    ],
    "sg:phone":"+32 54 50 37 35",
    "sg:postcode":"9404",
    "sg:province":"Oost-Vlaanderen",
    "sg:tags":[
        "-",
        "transport"
    ],
    "wof:name":"Hagrytrans Bvba",
    "wof:placetype":"venue"
},
  "geometry": {"coordinates":[3.956870079,50.843788147],"type":"Point"}
}