{
  "type": "Feature",
  "properties": {
    "addr:full":"Kaai 52 Nieuwpoort West-Vlaanderen 8620",
    "addr:housenumber":"52",
    "addr:postcode":"8620",
    "addr:street":"Kaai",
    "iso:country":"BE",
    "sg:address":"Kaai 52",
    "sg:city":"Nieuwpoort",
    "sg:orig_category":"Benzinestations and brandstoffen",
    "sg:phone":"+32 58 23 36 45",
    "sg:postcode":"8620",
    "sg:province":"West-Vlaanderen",
    "wof:name":"Garage Sarrazijn Michel",
    "wof:placetype":"venue"
},
  "geometry": {"coordinates":[2.744961977,51.1333656311],"type":"Point"}
}