{
  "type": "Feature",
  "properties": {
    "iso:country":"BE",
    "sg:address":"Rue Jean Martin 7",
    "sg:city":"Chaumont-gistoux",
    "sg:orig_category":"Isolatiewerk",
    "sg:phone":"+32 10 68 02 36",
    "sg:postcode":"1325",
    "sg:province":"Brabant Wallon",
    "wof:name":"Serge Brohee",
    "wof:placetype":"venue"
},
  "geometry": {"coordinates":[4.7150421143,50.6759414673],"type":"Point"}
}