{
  "type": "Feature",
  "properties": {
    "iso:country":"BE",
    "sg:address":"Sonvalwijk 26",
    "sg:city":"Landen (walshoutem)",
    "sg:classifiers":[
        {
            "category":"Building & Trades",
            "subcategory":"Equipment Rental",
            "type":"Services"
        }
    ],
    "sg:phone":"+32 11 83 28 24",
    "sg:postcode":"3401",
    "sg:province":"Vlaams-Brabant",
    "sg:tags":[
        "safety",
        "collective",
        "individual",
        "-"
    ],
    "wof:name":"Dcl",
    "wof:placetype":"venue"
},
  "geometry": {"coordinates":[5.0683751106,50.7348365784],"type":"Point"}
}