{
  "type": "Feature",
  "properties": {
    "addr:full":"Rue De Bavay 96 Boussu (hornu) Hainaut 7301",
    "addr:housenumber":"96",
    "addr:postcode":"7301",
    "addr:street":"Rue De Bavay",
    "iso:country":"BE",
    "sg:address":"Rue De Bavay 96",
    "sg:city":"Boussu (hornu)",
    "sg:classifiers":[
        {
            "category":"Personal",
            "subcategory":"Nail Salon",
            "type":"Services"
        }
    ],
    "sg:phone":"+32 65 65 91 45",
    "sg:postcode":"7301",
    "sg:province":"Hainaut",
    "sg:tags":[
        "pedicure"
    ],
    "wof:name":"Schietse M",
    "wof:placetype":"venue"
},
  "geometry": {"coordinates":[3.805052042,50.4058456421],"type":"Point"}
}