{
  "type": "Feature",
  "properties": {
    "iso:country":"BE",
    "sg:address":"Zandbergstraat 4",
    "sg:city":"Kortenaken (hoeleden)",
    "sg:classifiers":[
        {
            "category":"Autos & Motor Vehicles",
            "subcategory":"Automobile Sales",
            "type":"Retail Goods"
        }
    ],
    "sg:phone":"+32 16 77 81 19",
    "sg:postcode":"3471",
    "sg:province":"Vlaams-Brabant",
    "sg:tags":[
        "car",
        "used",
        "-"
    ],
    "wof:name":"Car World International Bvba",
    "wof:placetype":"venue"
},
  "geometry": {"coordinates":[4.9843320847,50.8622970581],"type":"Point"}
}