{
  "type": "Feature",
  "properties": {
    "addr:full":"Zur Dom\u00c4ne 31 B\u00dctgenbach/b\u00dctgenbach Li\u00e8ge 4750",
    "addr:housenumber":"31",
    "addr:postcode":"4750",
    "iso:country":"BE",
    "sg:address":"Zur Dom\u00c4ne 31",
    "sg:city":"B\u00dctgenbach/b\u00dctgenbach",
    "sg:orig_category":"D\u00e9taillants en pi\u00e8ces and accessoires de voitures. Stations-service and carburants",
    "sg:phone":"+32 80 64 79 71",
    "sg:postcode":"4750",
    "sg:province":"Li\u00e8ge",
    "wof:name":"Heinen B.",
    "wof:placetype":"venue"
},
  "geometry": {"coordinates":[6.2206501961,50.457408905],"type":"Point"}
}