{
  "type": "Feature",
  "properties": {
    "iso:country":"BE",
    "sg:address":"Rue De La Limite 89",
    "sg:city":"Wezembeek-oppem/wezembeek-oppem",
    "sg:orig_category":"M\u00e9decins and sp\u00e9cialistes",
    "sg:phone":"+32 2 767 80 82",
    "sg:postcode":"1970",
    "sg:province":"Vlaams-Brabant",
    "wof:name":"Liliane Dorthu",
    "wof:placetype":"venue"
},
  "geometry": {"coordinates":[4.5115218163,50.8351020813],"type":"Point"}
}