{
  "type": "Feature",
  "properties": {
    "addr:full":"Louis Verweestraat 2 Kortrijk West-Vlaanderen 8500",
    "addr:housenumber":"2",
    "addr:postcode":"8500",
    "addr:street":"Verweestraat",
    "iso:country":"BE",
    "sg:address":"Louis Verweestraat 2",
    "sg:city":"Kortrijk",
    "sg:orig_category":"Avocats and conseillers juridiques",
    "sg:phone":"+32 56 22 44 75",
    "sg:postcode":"8500",
    "sg:province":"West-Vlaanderen",
    "wof:name":"A. De Gryse",
    "wof:placetype":"venue"
},
  "geometry": {"coordinates":[3.2617309093,50.8273887634],"type":"Point"}
}