{
  "type": "Feature",
  "properties": {
    "addr:full":"Kemeldijk 20 Geel Antwerpen 2440",
    "addr:housenumber":"20",
    "addr:postcode":"2440",
    "addr:street":"Kemeldijk",
    "iso:country":"BE",
    "sg:address":"Kemeldijk 20",
    "sg:city":"Geel",
    "sg:classifiers":[
        {
            "category":"Cafe",
            "type":"Food & Drink"
        }
    ],
    "sg:phone":"+32 14 58 21 93",
    "sg:postcode":"2440",
    "sg:province":"Antwerpen",
    "sg:tags":[
        "caf\u00e9s"
    ],
    "wof:name":"Caf\u00c9 Beiaard",
    "wof:placetype":"venue"
},
  "geometry": {"coordinates":[5.0090708733,51.1273193359],"type":"Point"}
}