{
  "type": "Feature",
  "properties": {
    "addr:full":"Wittestraat 12 Kortrijk (heule) West-Vlaanderen 8501",
    "addr:housenumber":"12",
    "addr:postcode":"8501",
    "addr:street":"Wittestraat",
    "iso:country":"BE",
    "sg:address":"Wittestraat 12",
    "sg:city":"Kortrijk (heule)",
    "sg:classifiers":[
        {
            "category":"Manufacturing",
            "subcategory":"Rubber & Plastics",
            "type":"Manufacturing & Wholesale Goods"
        }
    ],
    "sg:phone":"+32 56 36 01 64",
    "sg:postcode":"8501",
    "sg:province":"West-Vlaanderen",
    "sg:tags":[
        "industrial",
        "-"
    ],
    "wof:name":"Alcaplast Plastics Technology",
    "wof:placetype":"venue"
},
  "geometry": {"coordinates":[3.237981081,50.8509254456],"type":"Point"}
}