{
  "type": "Feature",
  "properties": {
    "addr:full":"Voorhavenlaan 86 Gent Oost-Vlaanderen 9000",
    "addr:housenumber":"86",
    "addr:postcode":"9000",
    "addr:street":"Voorhavenlaan;Oost-Vlaanderen",
    "iso:country":"BE",
    "sg:address":"Voorhavenlaan 86",
    "sg:city":"Gent",
    "sg:orig_category":"Salles de spectacles",
    "sg:phone":"+32 9 259 01 01",
    "sg:postcode":"9000",
    "sg:province":"Oost-Vlaanderen",
    "wof:name":"Waterfront Galerie",
    "wof:placetype":"venue"
},
  "geometry": {"coordinates":[3.7281599045,51.0797195435],"type":"Point"}
}