{
  "type": "Feature",
  "properties": {
    "addr:full":"Boulevard Georges Deryck 26 Tubize Brabant Wallon 1480",
    "addr:housenumber":"26",
    "addr:postcode":"1480",
    "addr:street":"Boulevard Georges Deryck;Wallon",
    "iso:country":"BE",
    "sg:address":"Boulevard Georges Deryck 26",
    "sg:city":"Tubize",
    "sg:classifiers":[
        {
            "category":"Banks & Credit Unions",
            "subcategory":"Investment Brokerage",
            "type":"Services"
        }
    ],
    "sg:phone":"+32 2 355 22 16",
    "sg:postcode":"1480",
    "sg:province":"Brabant Wallon",
    "sg:tags":[
        "auditor"
    ],
    "wof:name":"Deschamps A Sa",
    "wof:placetype":"venue"
},
  "geometry": {"coordinates":[4.2024950981,50.6939201355],"type":"Point"}
}