{
  "type": "Feature",
  "properties": {
    "iso:country":"BE",
    "sg:address":"Avenue De L'yser 35",
    "sg:city":"Etterbeek/etterbeek",
    "sg:orig_category":"Cr\u00e8ches and garderies d'enfants",
    "sg:phone":"+32 2 735 56 69",
    "sg:postcode":"1040",
    "sg:province":"Bruxelles-Capitale",
    "wof:name":"Het Jubeltuintje",
    "wof:placetype":"venue"
},
  "geometry": {"coordinates":[4.3958330154,50.8422584534],"type":"Point"}
}