{
  "type": "Feature",
  "properties": {
    "addr:full":"Rue Du P\u00c9rr\u00c9on 83bb Sprimont Li\u00e8ge 4141",
    "addr:housenumber":"83bb",
    "addr:postcode":"4141",
    "addr:street":"Rue Du Pe\u0301Rre\u0301On",
    "iso:country":"BE",
    "sg:address":"Rue Du P\u00c9rr\u00c9on 83bb",
    "sg:city":"Sprimont",
    "sg:orig_category":"Enseignement maternel and primaire",
    "sg:phone":"+32 4 360 85 13",
    "sg:postcode":"4141",
    "sg:province":"Li\u00e8ge",
    "wof:name":"Ecole Fond. Communale",
    "wof:placetype":"venue"
},
  "geometry": {"coordinates":[5.7135300636,50.530254364],"type":"Point"}
}