{
  "type": "Feature",
  "properties": {
    "addr:full":"Rue Charlemagne 83 Li\u00e8ge 1 (jupille-sur-meuse) Li\u00e8ge 4020",
    "addr:housenumber":"83;1",
    "addr:postcode":"4020",
    "addr:street":"Rue Charlemagne;Jupille-Sur-Meuse Lie\u0300Ge",
    "iso:country":"BE",
    "sg:address":"Rue Charlemagne 83",
    "sg:city":"Li\u00e8ge 1 (jupille-sur-meuse)",
    "sg:classifiers":[
        {
            "category":"Health Services",
            "subcategory":"Dentist",
            "type":"Services"
        }
    ],
    "sg:phone":"+32 4 362 76 93",
    "sg:postcode":"4020",
    "sg:province":"Li\u00e8ge",
    "wof:name":"Gilson Gabriel",
    "wof:placetype":"venue"
},
  "geometry": {"coordinates":[5.628800869,50.6439704895],"type":"Point"}
}