{
  "type": "Feature",
  "properties": {
    "addr:full":"Bruggestraat 120ba2 Beernem West-Vlaanderen 8730",
    "addr:housenumber":"120ba2",
    "addr:postcode":"8730",
    "addr:street":"Bruggestraat",
    "iso:country":"BE",
    "sg:address":"Bruggestraat 120ba2",
    "sg:city":"Beernem",
    "sg:classifiers":[
        {
            "category":"Food & Beverages",
            "subcategory":"Meat & Fish",
            "type":"Retail Goods"
        }
    ],
    "sg:phone":"+32 50 79 10 58",
    "sg:postcode":"8730",
    "sg:province":"West-Vlaanderen",
    "sg:tags":[
        "vi",
        "zeevruchten"
    ],
    "wof:name":"Huis Jolika",
    "wof:placetype":"venue"
},
  "geometry": {"coordinates":[3.3203289509,51.1744995117],"type":"Point"}
}