{
  "type": "Feature",
  "properties": {
    "addr:full":"Lindenstraat 33 Tessenderlo Limburg 3980",
    "addr:housenumber":"33",
    "addr:postcode":"3980",
    "addr:street":"Lindenstraat",
    "iso:country":"BE",
    "sg:address":"Lindenstraat 33",
    "sg:city":"Tessenderlo",
    "sg:orig_category":"Landmeters",
    "sg:phone":"+32 13 31 52 57",
    "sg:postcode":"3980",
    "sg:province":"Limburg",
    "wof:name":"S. Verspreet",
    "wof:placetype":"venue"
},
  "geometry": {"coordinates":[5.0491862297,51.0332145691],"type":"Point"}
}