{
  "type": "Feature",
  "properties": {
    "addr:full":"Brugstraat 49 Heusden-zolder Limburg 3550",
    "addr:housenumber":"49",
    "addr:postcode":"3550",
    "addr:street":"Brugstraat",
    "iso:country":"BE",
    "sg:address":"Brugstraat 49",
    "sg:city":"Heusden-zolder",
    "sg:orig_category":"Paramedische behandelingen",
    "sg:phone":"+32 11 42 37 30",
    "sg:postcode":"3550",
    "sg:province":"Limburg",
    "wof:name":"Els Coenen",
    "wof:placetype":"venue"
},
  "geometry": {"coordinates":[5.2852740288,51.0349349976],"type":"Point"}
}