{
  "type": "Feature",
  "properties": {
    "addr:full":"Mudaeusstraat 3 Brecht Antwerpen 2960",
    "addr:housenumber":"3",
    "addr:postcode":"2960",
    "addr:street":"Mudaeusstraat",
    "iso:country":"BE",
    "sg:address":"Mudaeusstraat 3",
    "sg:city":"Brecht",
    "sg:classifiers":[
        {
            "category":"Shopping",
            "subcategory":"Gifts & Souvenirs",
            "type":"Retail Goods"
        }
    ],
    "sg:phone":"+32 3 313 43 96",
    "sg:postcode":"2960",
    "sg:province":"Antwerpen",
    "sg:tags":[
        "geschenken"
    ],
    "wof:name":"Het Kunstatelier",
    "wof:placetype":"venue"
},
  "geometry": {"coordinates":[4.6422381401,51.3487739563],"type":"Point"}
}