{
  "type": "Feature",
  "properties": {
    "addr:full":"Veldstraat 40 Wevelgem West-Vlaanderen 8560",
    "addr:housenumber":"40",
    "addr:postcode":"8560",
    "addr:street":"Veldstraat",
    "iso:country":"BE",
    "sg:address":"Veldstraat 40",
    "sg:city":"Wevelgem",
    "sg:classifiers":[
        {
            "category":"Building & Trades",
            "subcategory":"Construction",
            "type":"Services"
        }
    ],
    "sg:phone":"+32 56 41 27 84",
    "sg:postcode":"8560",
    "sg:province":"West-Vlaanderen",
    "sg:tags":[
        "carpenter"
    ],
    "wof:name":"Profithome Bvba",
    "wof:placetype":"venue"
},
  "geometry": {"coordinates":[3.1867771149,50.8201141357],"type":"Point"}
}