{
  "type": "Feature",
  "properties": {
    "addr:full":"Gentstraat 199 Meulebeke West-Vlaanderen 8760",
    "addr:housenumber":"199",
    "addr:postcode":"8760",
    "addr:street":"Gentstraat",
    "iso:country":"BE",
    "sg:address":"Gentstraat 199",
    "sg:city":"Meulebeke",
    "sg:orig_category":"V\u00eatements",
    "sg:phone":"+32 51 48 93 30",
    "sg:postcode":"8760",
    "sg:province":"West-Vlaanderen",
    "wof:name":"Germain L",
    "wof:placetype":"venue"
},
  "geometry": {"coordinates":[3.3055570126,50.9491043091],"type":"Point"}
}