{
  "type": "Feature",
  "properties": {
    "iso:country":"BE",
    "sg:address":"Vakenstraat 27",
    "sg:city":"Rotselaar",
    "sg:orig_category":"Woningbouw",
    "sg:phone":"+32 16 44 00 26",
    "sg:postcode":"3110",
    "sg:province":"Vlaams-Brabant",
    "wof:name":"Salien Pascal",
    "wof:placetype":"venue"
},
  "geometry": {"coordinates":[4.7243180275,50.9636154175],"type":"Point"}
}