{
  "type": "Feature",
  "properties": {
    "iso:country":"BE",
    "sg:address":"Rue Bassidaine 5",
    "sg:city":"Viroinval",
    "sg:orig_category":"Pain, p\u00e2tisseries and confiseries",
    "sg:phone":"+32 60 31 14 61",
    "sg:postcode":"5670",
    "sg:province":"Namur",
    "wof:name":"Boulangerie Keymolen",
    "wof:placetype":"venue"
},
  "geometry": {"coordinates":[4.5479259491,50.0750083923],"type":"Point"}
}