{
  "type": "Feature",
  "properties": {
    "iso:country":"BE",
    "sg:address":"Mercatordok 0",
    "sg:city":"Oostende",
    "sg:orig_category":"Mus\u00e9es and patrimoine culturel",
    "sg:phone":"+32 59 70 56 54",
    "sg:postcode":"8400",
    "sg:province":"West-Vlaanderen",
    "wof:name":"Museum Mercator",
    "wof:placetype":"venue"
},
  "geometry": {"coordinates":[2.9202589989,51.225151062],"type":"Point"}
}