{
  "type": "Feature",
  "properties": {
    "iso:country":"BE",
    "sg:address":"Garenstraat 17",
    "sg:city":"Evergem",
    "sg:orig_category":"Herstellingen and onderhoud van auto's",
    "sg:phone":"+32 9 344 58 72",
    "sg:postcode":"9940",
    "sg:province":"Oost-Vlaanderen",
    "wof:name":"Garage Segers",
    "wof:placetype":"venue"
},
  "geometry": {"coordinates":[3.7443509102,51.1779441833],"type":"Point"}
}