{
  "type": "Feature",
  "properties": {
    "iso:country":"BE",
    "sg:address":"Rue Du Commerce 3-5",
    "sg:city":"Wavre",
    "sg:classifiers":[
        {
            "category":"Shopping",
            "subcategory":"Clothing, Apparel, & Fashions",
            "type":"Retail Goods"
        }
    ],
    "sg:phone":"+32 10 24 33 54",
    "sg:postcode":"1300",
    "sg:province":"Brabant Wallon",
    "sg:tags":[
        "lady",
        "clothing",
        "-"
    ],
    "wof:name":"Inn (boutique)",
    "wof:placetype":"venue"
},
  "geometry": {"coordinates":[4.6102461815,50.7166366577],"type":"Point"}
}