{
  "type": "Feature",
  "properties": {
    "iso:country":"BE",
    "sg:address":"Linkhoutstraat 277",
    "sg:city":"Lummen (linkhout)",
    "sg:classifiers":[
        {
            "category":"Health Services",
            "subcategory":"Doctor",
            "type":"Services"
        }
    ],
    "sg:phone":"+32 13 44 41 74",
    "sg:postcode":"3560",
    "sg:province":"Limburg",
    "sg:tags":[
        "medicinephysicians",
        "surgeon"
    ],
    "wof:name":"Goris C",
    "wof:placetype":"venue"
},
  "geometry": {"coordinates":[5.1277360916,50.9629020691],"type":"Point"}
}