{
  "type": "Feature",
  "properties": {
    "addr:full":"Krabos 32 Halle (buizingen) Vlaams-Brabant 1501",
    "addr:housenumber":"32",
    "addr:postcode":"1501",
    "addr:street":"Krabos",
    "iso:country":"BE",
    "sg:address":"Krabos 32",
    "sg:city":"Halle (buizingen)",
    "sg:classifiers":[
        {
            "category":"Building & Trades",
            "subcategory":"Plumbing",
            "type":"Services"
        }
    ],
    "sg:phone":"+32 2 380 13 74",
    "sg:postcode":"1501",
    "sg:province":"Vlaams-Brabant",
    "sg:tags":[
        "repair",
        "mainten",
        "-",
        "central",
        "heating"
    ],
    "wof:name":"Leunens A",
    "wof:placetype":"venue"
},
  "geometry": {"coordinates":[4.2732601166,50.7244682312],"type":"Point"}
}