{
  "type": "Feature",
  "properties": {
    "iso:country":"BE",
    "sg:address":"Vrouweneekhoekstraat 122",
    "sg:city":"Sint-niklaas",
    "sg:classifiers":[
        {
            "category":"Building & Trades",
            "subcategory":"Landscaping Services",
            "type":"Services"
        }
    ],
    "sg:phone":"+32 3 296 90 70",
    "sg:postcode":"9100",
    "sg:province":"Oost-Vlaanderen",
    "sg:tags":[
        "architect",
        "landscape"
    ],
    "wof:name":"Jan Den Tuinman",
    "wof:placetype":"venue"
},
  "geometry": {"coordinates":[4.1450161934,51.1888999939],"type":"Point"}
}