{
  "type": "Feature",
  "properties": {
    "iso:country":"BE",
    "sg:address":"D\u00c9s. Van Monckhovenstr. 24",
    "sg:city":"Gent",
    "sg:orig_category":"Avocats and conseillers juridiques",
    "sg:phone":"+32 9 222 71 84",
    "sg:postcode":"9000",
    "sg:province":"Oost-Vlaanderen",
    "wof:name":"Anne Martens",
    "wof:placetype":"venue"
},
  "geometry": {"coordinates":[3.7146010399,51.0382194519],"type":"Point"}
}