{
  "type": "Feature",
  "properties": {
    "iso:country":"BE",
    "sg:address":"Vredeplein 27",
    "sg:city":"Evere",
    "sg:orig_category":"Foto-uitrusting Fotografen and fotostudio's",
    "sg:phone":"+32 2 216 45 53",
    "sg:postcode":"1140",
    "sg:province":"Bruxelles-Capitale",
    "wof:name":"Zoom Photo",
    "wof:placetype":"venue"
},
  "geometry": {"coordinates":[4.4009618759,50.8767318726],"type":"Point"}
}