{
  "type": "Feature",
  "properties": {
    "addr:full":"Quai Du Halage 12 Flemalle Li\u00e8ge 4400",
    "addr:housenumber":"12",
    "addr:postcode":"4400",
    "addr:street":"Quai Du Halage",
    "iso:country":"BE",
    "sg:address":"Quai Du Halage 12",
    "sg:city":"Flemalle",
    "sg:orig_category":"Stations-service and carburants. V\u00e9hicules automobiles. Entretien and r\u00e9parations de voitures",
    "sg:phone":"+32 4 233 40 59",
    "sg:postcode":"4400",
    "sg:province":"Li\u00e8ge",
    "wof:name":"Bp",
    "wof:placetype":"venue"
},
  "geometry": {"coordinates":[5.4785251617,50.5973167419],"type":"Point"}
}