{
  "type": "Feature",
  "properties": {
    "addr:full":"Milseweg 61 Leuven (heverlee) Vlaams-Brabant 3001",
    "addr:housenumber":"61",
    "addr:postcode":"3001",
    "addr:street":"Milseweg",
    "iso:country":"BE",
    "sg:address":"Milseweg 61",
    "sg:city":"Leuven (heverlee)",
    "sg:classifiers":[
        {
            "category":"Real Estate",
            "subcategory":"Architect",
            "type":"Services"
        }
    ],
    "sg:phone":"+32 16 40 41 39",
    "sg:postcode":"3001",
    "sg:province":"Vlaams-Brabant",
    "wof:name":"Wuytack P",
    "wof:placetype":"venue"
},
  "geometry": {"coordinates":[4.7126021385,50.8574981689],"type":"Point"}
}