{
  "type": "Feature",
  "properties": {
    "iso:country":"BE",
    "sg:address":"Dokter Spitaelslaan 245",
    "sg:city":"Halle",
    "sg:orig_category":"Artsen and specialisten",
    "sg:phone":"+32 2 361 50 38",
    "sg:postcode":"1502",
    "sg:province":"Vlaams-Brabant",
    "wof:name":"S. Marblie",
    "wof:placetype":"venue"
},
  "geometry": {"coordinates":[4.240901947,50.7089691162],"type":"Point"}
}