{
  "type": "Feature",
  "properties": {
    "addr:full":"Rue De L'ypr\u00e9au 6 Renaix Oost-Vlaanderen 9600",
    "addr:housenumber":"6",
    "addr:postcode":"9600",
    "addr:street":"Rue De L'Ypre \u0301Au",
    "iso:country":"BE",
    "sg:address":"Rue De L'ypr\u00e9au 6",
    "sg:city":"Renaix",
    "sg:classifiers":[
        {
            "category":"Shopping",
            "subcategory":"Beauty & Cosmetics",
            "type":"Retail Goods"
        }
    ],
    "sg:phone":"+32 55 21 56 80",
    "sg:postcode":"9600",
    "sg:province":"Oost-Vlaanderen",
    "sg:tags":[
        "-",
        "perfumery"
    ],
    "wof:name":"Gutmann",
    "wof:placetype":"venue"
},
  "geometry": {"coordinates":[3.5992999077,50.7470397949],"type":"Point"}
}