{
  "type": "Feature",
  "properties": {
    "iso:country":"BE",
    "sg:address":"Avenue Adolphe Lacombl\u00c9 40b12",
    "sg:city":"Schaarbeek/schaerbeek",
    "sg:orig_category":"V\u00e9t\u00e9rinaires",
    "sg:phone":"+32 2 734 32 32",
    "sg:postcode":"1030",
    "sg:province":"Bruxelles-Capitale",
    "wof:name":"Andre Marchal",
    "wof:placetype":"venue"
},
  "geometry": {"coordinates":[4.3996100426,50.8494415283],"type":"Point"}
}