{
  "type": "Feature",
  "properties": {
    "addr:full":"Koophandelsplein 18 Gent Oost-Vlaanderen 9000",
    "addr:housenumber":"18",
    "addr:postcode":"9000",
    "addr:street":"Koophandelsplein;Oost-Vlaanderen",
    "iso:country":"BE",
    "sg:address":"Koophandelsplein 18",
    "sg:city":"Gent",
    "sg:classifiers":[
        {
            "category":"Shopping",
            "subcategory":"Jewelry",
            "type":"Retail Goods"
        }
    ],
    "sg:phone":"+32 9 225 27 23",
    "sg:postcode":"9000",
    "sg:province":"Oost-Vlaanderen",
    "sg:tags":[
        "jeweller",
        "-"
    ],
    "wof:name":"Lefebvre",
    "wof:placetype":"venue"
},
  "geometry": {"coordinates":[3.7211689949,51.0494689941],"type":"Point"}
}