{
  "type": "Feature",
  "properties": {
    "addr:full":"Mechelsesteenweg 204 Herent Vlaams-Brabant 3020",
    "addr:housenumber":"204",
    "addr:postcode":"3020",
    "addr:street":"Mechelsesteenweg",
    "iso:country":"BE",
    "sg:address":"Mechelsesteenweg 204",
    "sg:city":"Herent",
    "sg:orig_category":"R\u00e9parations de chaussures and articles en cuir",
    "sg:phone":"+32 16 23 02 82",
    "sg:postcode":"3020",
    "sg:province":"Vlaams-Brabant",
    "wof:name":"Schoenmakerij Patrick",
    "wof:placetype":"venue"
},
  "geometry": {"coordinates":[4.681137085,50.8990631104],"type":"Point"}
}