{
  "type": "Feature",
  "properties": {
    "addr:full":"Werthplatz 4b8 Eupen Li\u00e8ge 4700",
    "addr:housenumber":"4b8",
    "addr:postcode":"4700",
    "addr:street":"Werthplatz",
    "iso:country":"BE",
    "sg:address":"Werthplatz 4b8",
    "sg:city":"Eupen",
    "sg:orig_category":"Kapsalons",
    "sg:phone":"+32 87 55 32 29",
    "sg:postcode":"4700",
    "sg:province":"Li\u00e8ge",
    "wof:name":"Coiffure Shampoo",
    "wof:placetype":"venue"
},
  "geometry": {"coordinates":[6.0385270119,50.6328582764],"type":"Point"}
}