{
  "type": "Feature",
  "properties": {
    "iso:country":"BE",
    "sg:address":"Florivalstraat 32",
    "sg:city":"Huldenberg",
    "sg:classifiers":[
        {
            "category":"Fast Food",
            "type":"Food & Drink"
        }
    ],
    "sg:phone":"+32 16 47 16 08",
    "sg:postcode":"3040",
    "sg:province":"Vlaams-Brabant",
    "sg:tags":[
        "\u00c0",
        "emporter",
        "restaurants"
    ],
    "wof:name":"Frituur Richard",
    "wof:placetype":"venue"
},
  "geometry": {"coordinates":[4.635160923,50.7585372925],"type":"Point"}
}