{
  "type": "Feature",
  "properties": {
    "addr:full":"Rue Waraxhe 23 Flemalle Li\u00e8ge 4400",
    "addr:housenumber":"23",
    "addr:postcode":"4400",
    "addr:street":"Rue Waraxhe",
    "iso:country":"BE",
    "sg:address":"Rue Waraxhe 23",
    "sg:city":"Flemalle",
    "sg:orig_category":"Peinture. Rev\u00eatements pour sols and murs",
    "sg:phone":"+32 4 337 18 34",
    "sg:postcode":"4400",
    "sg:province":"Li\u00e8ge",
    "wof:name":"Jean-pierre Reynders",
    "wof:placetype":"venue"
},
  "geometry": {"coordinates":[5.4576430321,50.5693130493],"type":"Point"}
}