{
  "type": "Feature",
  "properties": {
    "iso:country":"BE",
    "sg:address":"Sart D'avette 33",
    "sg:city":"Flemalle",
    "sg:orig_category":"Avocats and conseillers juridiques",
    "sg:phone":"+32 4 275 04 05",
    "sg:postcode":"4400",
    "sg:province":"Li\u00e8ge",
    "wof:name":"Marie-h\u00c9l\u00c8ne Swinnen",
    "wof:placetype":"venue"
},
  "geometry": {"coordinates":[5.4127960205,50.6009483337],"type":"Point"}
}