{
  "type": "Feature",
  "properties": {
    "addr:full":"Kristinastraat 8 Brussel/bruxelles Bruxelles-Capitale 1000",
    "addr:housenumber":"8",
    "addr:postcode":"1000",
    "addr:street":"Kristinastraat;/",
    "iso:country":"BE",
    "sg:address":"Kristinastraat 8",
    "sg:city":"Brussel/bruxelles",
    "sg:classifiers":[
        {
            "category":"Cafe",
            "type":"Food & Drink"
        }
    ],
    "sg:phone":"+32 2 512 03 41",
    "sg:postcode":"1000",
    "sg:province":"Bruxelles-Capitale",
    "sg:tags":[
        "caf\u00e9s"
    ],
    "wof:name":"Beata Krynska",
    "wof:placetype":"venue"
},
  "geometry": {"coordinates":[4.3515300751,50.8393669128],"type":"Point"}
}