{
  "type": "Feature",
  "properties": {
    "iso:country":"BE",
    "sg:address":"Hille 144be",
    "sg:city":"Wingene",
    "sg:orig_category":"Installation de menuiserie en bois and plastique",
    "sg:phone":"+32 51 61 19 23",
    "sg:postcode":"8750",
    "sg:province":"West-Vlaanderen",
    "wof:name":"Dirk Pollet",
    "wof:placetype":"venue"
},
  "geometry": {"coordinates":[3.2259390354,51.0463485718],"type":"Point"}
}