{
  "type": "Feature",
  "properties": {
    "iso:country":"BE",
    "sg:address":"Wijnegemsteenweg 32",
    "sg:city":"Schilde ('s Gravenwezel)",
    "sg:classifiers":[
        {
            "category":"Bakery",
            "type":"Food & Drink"
        }
    ],
    "sg:phone":"+32 3 658 85 98",
    "sg:postcode":"2970",
    "sg:province":"Antwerpen",
    "sg:tags":[
        "confectioner",
        "baker"
    ],
    "wof:name":"Micha\u00ebl",
    "wof:placetype":"venue"
},
  "geometry": {"coordinates":[4.550658226,51.2621765137],"type":"Point"}
}