{
  "type": "Feature",
  "properties": {
    "addr:full":"Philippe Werrieplein 10 Jette/jette Bruxelles-Capitale 1090",
    "addr:housenumber":"10",
    "addr:postcode":"1090",
    "addr:street":"Werrieplein",
    "iso:country":"BE",
    "sg:address":"Philippe Werrieplein 10",
    "sg:city":"Jette/jette",
    "sg:orig_category":"Artiesten and kunstenaars",
    "sg:phone":"+32 2 426 50 78",
    "sg:postcode":"1090",
    "sg:province":"Bruxelles-Capitale",
    "wof:name":"D. Lammers",
    "wof:placetype":"venue"
},
  "geometry": {"coordinates":[4.3355579376,50.8678665161],"type":"Point"}
}