{
  "type": "Feature",
  "properties": {
    "iso:country":"BE",
    "sg:address":"Vhauss\u00c9e De Vilvorde 1",
    "sg:city":"Brussel/bruxelles",
    "sg:classifiers":[
        {
            "category":"Arena",
            "subcategory":"Sports Club",
            "type":"Entertainment"
        }
    ],
    "sg:phone":"+32 2 216 48 28",
    "sg:postcode":"1020",
    "sg:province":"Bruxelles-Capitale",
    "sg:tags":[
        "de"
    ],
    "wof:name":"B.r.y.c.",
    "wof:placetype":"venue"
},
  "geometry": {"coordinates":[4.3738889694,50.8817405701],"type":"Point"}
}