{
  "type": "Feature",
  "properties": {
    "addr:full":"Chemin Du Stocquoy 1-3 Wavre Brabant Wallon 1300",
    "addr:housenumber":"1-3;1300",
    "addr:street":"Chemin Du Stocquoy",
    "iso:country":"BE",
    "sg:address":"Chemin Du Stocquoy 1-3",
    "sg:city":"Wavre",
    "sg:classifiers":[
        {
            "category":"Organizations",
            "subcategory":"Professional Association",
            "type":"Services"
        }
    ],
    "sg:phone":"+32 10 45 11 41",
    "sg:postcode":"1300",
    "sg:province":"Brabant Wallon",
    "sg:tags":[
        "trade-union",
        "federation"
    ],
    "wof:name":"Union Wallonne Des Entreprises",
    "wof:placetype":"venue"
},
  "geometry": {"coordinates":[4.6157569885,50.6898498535],"type":"Point"}
}