{
  "type": "Feature",
  "properties": {
    "iso:country":"BE",
    "sg:address":"Woumenweg 175",
    "sg:city":"Diksmuide",
    "sg:orig_category":"Rundveehouders Varkenskwekers",
    "sg:phone":"+32 51 50 15 65",
    "sg:postcode":"8600",
    "sg:province":"West-Vlaanderen",
    "wof:name":"Jozef Roose",
    "wof:placetype":"venue"
},
  "geometry": {"coordinates":[2.8685619831,51.0125312805],"type":"Point"}
}