{
  "type": "Feature",
  "properties": {
    "addr:full":"Rue Cervant\u00c8s 65 Vorst/forest Bruxelles-Capitale 1190",
    "addr:housenumber":"65",
    "addr:postcode":"1190",
    "addr:street":"Rue Cervante\u0300S;/ Forest",
    "iso:country":"BE",
    "sg:address":"Rue Cervant\u00c8s 65",
    "sg:city":"Vorst/forest",
    "sg:orig_category":"M\u00e9decins and sp\u00e9cialistes",
    "sg:phone":"+32 2 345 76 53",
    "sg:postcode":"1190",
    "sg:province":"Bruxelles-Capitale",
    "wof:name":"Anne Michele De Clerck/anne De Clerck",
    "wof:placetype":"venue"
},
  "geometry": {"coordinates":[4.3390240669,50.8179244995],"type":"Point"}
}