{
  "type": "Feature",
  "properties": {
    "iso:country":"BE",
    "sg:address":"Rue Du Bois 2a",
    "sg:city":"Braine-le-ch\u00e2teau (wauthier-braine)",
    "sg:classifiers":[
        {
            "category":"Professional",
            "subcategory":"Advertising",
            "type":"Services"
        }
    ],
    "sg:phone":"+32 2 366 25 86",
    "sg:postcode":"1440",
    "sg:province":"Brabant Wallon",
    "sg:tags":[
        "photography"
    ],
    "wof:name":"Chevalier F",
    "wof:placetype":"venue"
},
  "geometry": {"coordinates":[4.324338913,50.685749054],"type":"Point"}
}