{
  "type": "Feature",
  "properties": {
    "addr:full":"Roggelaan 2 Kortrijk West-Vlaanderen 8500",
    "addr:housenumber":"2",
    "addr:postcode":"8500",
    "addr:street":"Roggelaan",
    "iso:country":"BE",
    "sg:address":"Roggelaan 2",
    "sg:city":"Kortrijk",
    "sg:orig_category":"Watermaatschappijen and -distributie",
    "sg:phone":"+32 56 23 17 11",
    "sg:postcode":"8500",
    "sg:province":"West-Vlaanderen",
    "wof:name":"Vlaamse Maatschappij Voor Watervoorzienin",
    "wof:placetype":"venue"
},
  "geometry": {"coordinates":[3.298525095,50.8171081543],"type":"Point"}
}