{
  "type": "Feature",
  "properties": {
    "iso:country":"BE",
    "sg:address":"Berlaarbaan 169",
    "sg:city":"Sint-katelijne-waver",
    "sg:orig_category":"Groententeelt",
    "sg:phone":"+32 15 55 17 49",
    "sg:postcode":"2860",
    "sg:province":"Antwerpen",
    "wof:name":"Edward Van Reeth",
    "wof:placetype":"venue"
},
  "geometry": {"coordinates":[4.535200119,51.0489692688],"type":"Point"}
}