{
  "type": "Feature",
  "properties": {
    "iso:country":"BE",
    "sg:address":"Houtstraat 3",
    "sg:city":"Sint-truiden",
    "sg:classifiers":[
        {
            "category":"Cafe",
            "type":"Food & Drink"
        }
    ],
    "sg:phone":"+32 11 68 43 91",
    "sg:postcode":"3800",
    "sg:province":"Limburg",
    "sg:tags":[
        "caf\u00e9s"
    ],
    "wof:name":"Caf\u00c9 De Witte",
    "wof:placetype":"venue"
},
  "geometry": {"coordinates":[5.1768898964,50.8235054016],"type":"Point"}
}