{
  "type": "Feature",
  "properties": {
    "addr:full":"Avenue Du Canal 6 Komen-waasten/comines-warneton Hainaut 7780",
    "addr:housenumber":"6;7780",
    "addr:street":"Avenue Du Canal",
    "iso:country":"BE",
    "sg:address":"Avenue Du Canal 6",
    "sg:city":"Komen-waasten/comines-warneton",
    "sg:orig_category":"Activit\u00e9s diverses d'imprimerie",
    "sg:phone":"+32 56 55 62 20",
    "sg:postcode":"7780",
    "sg:province":"Hainaut",
    "wof:name":"Bureau Indigo",
    "wof:placetype":"venue"
},
  "geometry": {"coordinates":[2.996434927,50.765953064],"type":"Point"}
}