{
  "type": "Feature",
  "properties": {
    "iso:country":"BE",
    "sg:address":"Rue Du Monty 11",
    "sg:city":"Somme-leuze",
    "sg:orig_category":"Rundveehouders",
    "sg:phone":"+32 83 68 83 12",
    "sg:postcode":"5377",
    "sg:province":"Namur",
    "wof:name":"Leboutte",
    "wof:placetype":"venue"
},
  "geometry": {"coordinates":[5.3698949814,50.3404350281],"type":"Point"}
}