{
  "type": "Feature",
  "properties": {
    "addr:full":"Velodroomstraat 299-301 Boom Antwerpen 2850",
    "addr:housenumber":"299-301",
    "addr:postcode":"2850",
    "addr:street":"Velodroomstraat",
    "iso:country":"BE",
    "sg:address":"Velodroomstraat 299-301",
    "sg:city":"Boom",
    "sg:orig_category":"Non-Classified Establishments",
    "sg:phone":"+32 3 888 04 42",
    "sg:postcode":"2850",
    "sg:province":"Antwerpen",
    "wof:name":"Maes M",
    "wof:placetype":"venue"
},
  "geometry": {"coordinates":[4.3744769096,51.0917778015],"type":"Point"}
}