{
  "type": "Feature",
  "properties": {
    "addr:full":"Henri Torleylaan 53 Beersel Vlaams-Brabant 1654",
    "addr:housenumber":"53",
    "addr:postcode":"1654",
    "addr:street":"Henri Torleylaan",
    "iso:country":"BE",
    "sg:address":"Henri Torleylaan 53",
    "sg:city":"Beersel",
    "sg:orig_category":"Banques and organismes de cr\u00e9dit",
    "sg:phone":"+32 2 356 97 28",
    "sg:postcode":"1654",
    "sg:province":"Vlaams-Brabant",
    "wof:name":"Dexia",
    "wof:placetype":"venue"
},
  "geometry": {"coordinates":[4.2761712074,50.7457122803],"type":"Point"}
}