{
  "type": "Feature",
  "properties": {
    "iso:country":"BE",
    "sg:address":"Mansteen 21",
    "sg:city":"Opwijk",
    "sg:classifiers":[
        {
            "category":"Health Services",
            "subcategory":"Health Practitioner",
            "type":"Services"
        }
    ],
    "sg:phone":"+32 52 37 35 10",
    "sg:postcode":"1745",
    "sg:province":"Vlaams-Brabant",
    "sg:tags":[
        "physiotherapist"
    ],
    "wof:name":"Baetens Mir\u00e8se",
    "wof:placetype":"venue"
},
  "geometry": {"coordinates":[4.2016267776,50.9578552246],"type":"Point"}
}