{
  "type": "Feature",
  "properties": {
    "addr:full":"Rue Notre-dame 39 Sint-lambrechts-woluwe/woluwe-saint-lambert Bruxelles-Capitale 1200",
    "addr:housenumber":"39",
    "addr:postcode":"1200",
    "addr:street":"Rue Notre-Dame",
    "iso:country":"BE",
    "sg:address":"Rue Notre-dame 39",
    "sg:city":"Sint-lambrechts-woluwe/woluwe-saint-lambert",
    "sg:orig_category":"Peinture. Eclairage et \u00e9quipements du foyer. Rev\u00eatements pour sols and murs",
    "sg:phone":"+32 2 762 32 69",
    "sg:postcode":"1200",
    "sg:province":"Bruxelles-Capitale",
    "wof:name":"J.m. Bogaert",
    "wof:placetype":"venue"
},
  "geometry": {"coordinates":[4.4443001747,50.8445129395],"type":"Point"}
}