{
  "type": "Feature",
  "properties": {
    "addr:full":"Diesterstraat 16 Hasselt Limburg 3500",
    "addr:housenumber":"16",
    "addr:postcode":"3500",
    "addr:street":"Diesterstraat",
    "iso:country":"BE",
    "sg:address":"Diesterstraat 16",
    "sg:city":"Hasselt",
    "sg:classifiers":[
        {
            "category":"Shopping",
            "subcategory":"Optician",
            "type":"Retail Goods"
        }
    ],
    "sg:phone":"+32 11 22 72 52",
    "sg:postcode":"3500",
    "sg:province":"Limburg",
    "sg:tags":[
        "-"
    ],
    "wof:name":"Peeters M",
    "wof:placetype":"venue"
},
  "geometry": {"coordinates":[5.3330287933,50.9302444458],"type":"Point"}
}