{
  "type": "Feature",
  "properties": {
    "iso:country":"BE",
    "sg:address":"Esplanadestraat 7",
    "sg:city":"Aalst",
    "sg:orig_category":"Artiesten and kunstenaars",
    "sg:phone":"+32 53 77 02 31",
    "sg:postcode":"9300",
    "sg:province":"Oost-Vlaanderen",
    "wof:name":"Maria-helena Siau",
    "wof:placetype":"venue"
},
  "geometry": {"coordinates":[4.0372438431,50.9408378601],"type":"Point"}
}