{
  "type": "Feature",
  "properties": {
    "addr:full":"Rue Aim\u00e9 Smekens 75 Bruxelles (schaerbeek) Bruxelles-Capitale 1030",
    "addr:housenumber":"75",
    "addr:postcode":"1030",
    "addr:street":"Rue Aime\u0301 Smekens",
    "iso:country":"BE",
    "sg:address":"Rue Aim\u00e9 Smekens 75",
    "sg:city":"Bruxelles (schaerbeek)",
    "sg:classifiers":[
        {
            "category":"Health Services",
            "subcategory":"Dentist",
            "type":"Services"
        }
    ],
    "sg:phone":"+32 2 732 19 84",
    "sg:postcode":"1030",
    "sg:province":"Bruxelles-Capitale",
    "wof:name":"No\u00ebl Anne",
    "wof:placetype":"venue"
},
  "geometry": {"coordinates":[4.4092359543,50.8493385315],"type":"Point"}
}