{
  "type": "Feature",
  "properties": {
    "addr:full":"Moorselestraat 9 Wevelgem West-Vlaanderen 8560",
    "addr:housenumber":"9",
    "addr:postcode":"8560",
    "addr:street":"Moorselestraat",
    "iso:country":"BE",
    "sg:address":"Moorselestraat 9",
    "sg:city":"Wevelgem",
    "sg:orig_category":"Diverse grafische activiteiten Secretariaatsdiensten",
    "sg:phone":"+32 56 41 84 20",
    "sg:postcode":"8560",
    "sg:province":"West-Vlaanderen",
    "wof:name":"V.d.s. Graphics",
    "wof:placetype":"venue"
},
  "geometry": {"coordinates":[3.1768989563,50.8076477051],"type":"Point"}
}