{
  "type": "Feature",
  "properties": {
    "addr:full":"Rue Du Commerce 18 Ciney Namur 5590",
    "addr:housenumber":"18",
    "addr:postcode":"5590",
    "addr:street":"Rue Du Commerce",
    "iso:country":"BE",
    "sg:address":"Rue Du Commerce 18",
    "sg:city":"Ciney",
    "sg:orig_category":"Alimentation sp\u00e9cialis\u00e9e",
    "sg:phone":"+32 83 21 14 18",
    "sg:postcode":"5590",
    "sg:province":"Namur",
    "wof:name":"Serge Helman",
    "wof:placetype":"venue"
},
  "geometry": {"coordinates":[5.0994000435,50.2949829102],"type":"Point"}
}