{
  "type": "Feature",
  "properties": {
    "addr:full":"Maastrichterstraat 49 Hasselt Limburg 3500",
    "addr:housenumber":"49",
    "addr:postcode":"3500",
    "addr:street":"Maastrichterstraat",
    "iso:country":"BE",
    "sg:address":"Maastrichterstraat 49",
    "sg:city":"Hasselt",
    "sg:classifiers":[
        {
            "category":"Shopping",
            "subcategory":"Clothing, Apparel, & Fashions",
            "type":"Retail Goods"
        }
    ],
    "sg:phone":"+32 11 22 69 45",
    "sg:postcode":"3500",
    "sg:province":"Limburg",
    "sg:tags":[
        "boutique"
    ],
    "wof:name":"Avenue",
    "wof:placetype":"venue"
},
  "geometry": {"coordinates":[5.3482317924,50.9299850464],"type":"Point"}
}