{
  "type": "Feature",
  "properties": {
    "addr:full":"Lenniksesteenweg 578 Halle Vlaams-Brabant 1500",
    "addr:housenumber":"578",
    "addr:postcode":"1500",
    "addr:street":"Lenniksesteenweg",
    "iso:country":"BE",
    "sg:address":"Lenniksesteenweg 578",
    "sg:city":"Halle",
    "sg:orig_category":"G\u00e2teaux, p\u00e2tisserie and biscuits Fab",
    "sg:phone":"+32 2 381 03 67",
    "sg:postcode":"1500",
    "sg:province":"Vlaams-Brabant",
    "wof:name":"Fa. Hugo",
    "wof:placetype":"venue"
},
  "geometry": {"coordinates":[4.1957950592,50.76612854],"type":"Point"}
}