{
  "type": "Feature",
  "properties": {
    "addr:full":"Rue De L'ecole 19 Rebecq Brabant Wallon 1430",
    "addr:housenumber":"19",
    "addr:postcode":"1430",
    "addr:street":"Rue De L'Ecole",
    "iso:country":"BE",
    "sg:address":"Rue De L'ecole 19",
    "sg:city":"Rebecq",
    "sg:orig_category":"Activit\u00e9s diverses d'imprimerie",
    "sg:phone":"+32 67 67 03 80",
    "sg:postcode":"1430",
    "sg:province":"Brabant Wallon",
    "wof:name":"Kid Graphics",
    "wof:placetype":"venue"
},
  "geometry": {"coordinates":[4.1317100525,50.6643714905],"type":"Point"}
}