{
  "type": "Feature",
  "properties": {
    "addr:full":"Rue Des Le\u00dbps 15 Verviers Li\u00e8ge 4801",
    "addr:housenumber":"15",
    "addr:postcode":"4801",
    "addr:street":"Rue Des Leu\u0302Ps",
    "iso:country":"BE",
    "sg:address":"Rue Des Le\u00dbps 15",
    "sg:city":"Verviers",
    "sg:orig_category":"Gespecialiseerde residenti\u00eble bouw",
    "sg:phone":"+32 87 22 82 57",
    "sg:postcode":"4801",
    "sg:province":"Li\u00e8ge",
    "wof:name":"Fe. Solu-chapes",
    "wof:placetype":"venue"
},
  "geometry": {"coordinates":[5.8930549622,50.5922393799],"type":"Point"}
}