{
  "type": "Feature",
  "properties": {
    "iso:country":"BE",
    "sg:address":"Rue De Diekirch 7",
    "sg:city":"Arlon",
    "sg:orig_category":"Studios photographiques. Equipement photographique",
    "sg:phone":"+32 63 21 79 59",
    "sg:postcode":"6700",
    "sg:province":"Luxembourg",
    "wof:name":"Photo-video L'arc-en-ciel",
    "wof:placetype":"venue"
},
  "geometry": {"coordinates":[5.8122329712,49.6842308044],"type":"Point"}
}