{
  "type": "Feature",
  "properties": {
    "addr:full":"Place De Bossut 2 Grez-doiceau (bossut-gottechain) Brabant Wallon 1390",
    "addr:housenumber":"2",
    "addr:postcode":"1390",
    "addr:street":"Place De Bossut;Wallon",
    "iso:country":"BE",
    "sg:address":"Place De Bossut 2",
    "sg:city":"Grez-doiceau (bossut-gottechain)",
    "sg:classifiers":[
        {
            "category":"Banks & Credit Unions",
            "subcategory":"Investment Brokerage",
            "type":"Services"
        }
    ],
    "sg:phone":"+32 10 84 48 90",
    "sg:postcode":"1390",
    "sg:province":"Brabant Wallon",
    "sg:tags":[
        "fence"
    ],
    "wof:name":"Clabots",
    "wof:placetype":"venue"
},
  "geometry": {"coordinates":[4.6954898834,50.7613258362],"type":"Point"}
}