{
  "type": "Feature",
  "properties": {
    "iso:country":"BE",
    "sg:address":"Rue De Boussu 145",
    "sg:city":"Saint-ghislain",
    "sg:orig_category":"Herstellingen and onderhoud van auto's Voertuigen",
    "sg:phone":"+32 65 62 12 21",
    "sg:postcode":"7333",
    "sg:province":"Hainaut",
    "wof:name":"Garage Dufour",
    "wof:placetype":"venue"
},
  "geometry": {"coordinates":[3.778701067,50.4627838135],"type":"Point"}
}