{
  "type": "Feature",
  "properties": {
    "addr:full":"Vieux Chemin De Louvain 41 Beauvechain Brabant Wallon 1320",
    "addr:housenumber":"41",
    "addr:postcode":"1320",
    "addr:street":"Vieux Chemin De Louvain",
    "iso:country":"BE",
    "sg:address":"Vieux Chemin De Louvain 41",
    "sg:city":"Beauvechain",
    "sg:classifiers":[
        {
            "category":"Fast Food",
            "type":"Food & Drink"
        }
    ],
    "sg:phone":"+32 10 86 07 19",
    "sg:postcode":"1320",
    "sg:province":"Brabant Wallon",
    "sg:tags":[
        "\u00c0",
        "restaurants",
        "emporter",
        "restaurant"
    ],
    "wof:name":"Restaurant Bali",
    "wof:placetype":"venue"
},
  "geometry": {"coordinates":[4.7195358276,50.7825698853],"type":"Point"}
}