{
  "type": "Feature",
  "properties": {
    "addr:full":"Rue Des Alli\u00e9s 35 Bruxelles (forest) Bruxelles-Capitale 1190",
    "addr:housenumber":"35",
    "addr:postcode":"1190",
    "addr:street":"Rue Des Allie\u0301S",
    "iso:country":"BE",
    "sg:address":"Rue Des Alli\u00e9s 35",
    "sg:city":"Bruxelles (forest)",
    "sg:classifiers":[
        {
            "category":"Building & Trades",
            "subcategory":"Electrical",
            "type":"Services"
        }
    ],
    "sg:phone":"+32 2 344 40 57",
    "sg:postcode":"1190",
    "sg:province":"Bruxelles-Capitale",
    "sg:tags":[
        "-",
        "electric",
        "contractor"
    ],
    "wof:name":"Simon C Electricit\u00e9 Sprl",
    "wof:placetype":"venue"
},
  "geometry": {"coordinates":[4.3268728256,50.8161735535],"type":"Point"}
}