{
  "type": "Feature",
  "properties": {
    "addr:full":"Gistelsesteenweg 142 Oostende West-Vlaanderen 8400",
    "addr:housenumber":"142",
    "addr:postcode":"8400",
    "addr:street":"Gistelsesteenweg",
    "iso:country":"BE",
    "sg:address":"Gistelsesteenweg 142",
    "sg:city":"Oostende",
    "sg:classifiers":[
        {
            "category":"Retail",
            "subcategory":"Animal Services",
            "type":"Services"
        }
    ],
    "sg:phone":"+32 59 50 45 23",
    "sg:postcode":"8400",
    "sg:province":"West-Vlaanderen",
    "sg:tags":[
        "training",
        "dog"
    ],
    "wof:name":"Happy Dog Zandvoorde",
    "wof:placetype":"venue"
},
  "geometry": {"coordinates":[2.9266300201,51.2150115967],"type":"Point"}
}