{
  "type": "Feature",
  "properties": {
    "iso:country":"BE",
    "sg:address":"Pierenstraat 3",
    "sg:city":"Geel",
    "sg:classifiers":[
        {
            "category":"Building & Trades",
            "subcategory":"Electrical",
            "type":"Services"
        }
    ],
    "sg:phone":"+32 14 85 10 21",
    "sg:postcode":"2440",
    "sg:province":"Antwerpen",
    "sg:tags":[
        "electric",
        "-",
        "housewiring",
        "contractor"
    ],
    "wof:name":"Van Aerde R",
    "wof:placetype":"venue"
},
  "geometry": {"coordinates":[4.987552166,51.2050552368],"type":"Point"}
}