{
  "type": "Feature",
  "properties": {
    "addr:full":"Rue Duchateau 37 La Louviere Hainaut 7100",
    "addr:housenumber":"37",
    "addr:postcode":"7100",
    "addr:street":"Rue Duchateau",
    "iso:country":"BE",
    "sg:address":"Rue Duchateau 37",
    "sg:city":"La Louviere",
    "sg:orig_category":"Paramedische behandelingen",
    "sg:phone":"+32 64 22 60 09",
    "sg:postcode":"7100",
    "sg:province":"Hainaut",
    "wof:name":"Jocelyne Dizelle",
    "wof:placetype":"venue"
},
  "geometry": {"coordinates":[4.1850848198,50.4748649597],"type":"Point"}
}