{
  "type": "Feature",
  "properties": {
    "iso:country":"BE",
    "sg:address":"Avenue De La R\u00c9sistance 261",
    "sg:city":"Soumagne",
    "sg:orig_category":"Banken and kredietinstellingen",
    "sg:phone":"+32 4 377 12 96",
    "sg:postcode":"4630",
    "sg:province":"Li\u00e8ge",
    "wof:name":"Fortis",
    "wof:placetype":"venue"
},
  "geometry": {"coordinates":[5.7353510857,50.6309165955],"type":"Point"}
}