{
  "type": "Feature",
  "properties": {
    "addr:full":"Rue Du Bac 18 Thimister-clermont (clermont) Li\u00e8ge 4890",
    "addr:housenumber":"18",
    "addr:postcode":"4890",
    "addr:street":"Rue Du Bac",
    "iso:country":"BE",
    "sg:address":"Rue Du Bac 18",
    "sg:city":"Thimister-clermont (clermont)",
    "sg:classifiers":[
        {
            "category":"Professional",
            "subcategory":"Business Services",
            "type":"Services"
        }
    ],
    "sg:phone":"+32 87 44 84 62",
    "sg:postcode":"4890",
    "sg:province":"Li\u00e8ge",
    "sg:tags":[
        "firm"
    ],
    "wof:name":"Bac",
    "wof:placetype":"venue"
},
  "geometry": {"coordinates":[5.8829598427,50.6572036743],"type":"Point"}
}