{
  "type": "Feature",
  "properties": {
    "addr:full":"Rue St Jean 9 Jodoigne 5900",
    "addr:housenumber":"9",
    "addr:postcode":"5900",
    "addr:street":"Rue St Jean",
    "iso:country":"BE",
    "sg:address":"Rue St Jean 9",
    "sg:city":"Jodoigne",
    "sg:classifiers":[
        {
            "category":"Banks & Credit Unions",
            "subcategory":"Bank",
            "type":"Services"
        }
    ],
    "sg:phone":"+32 10 81 24 34",
    "sg:postcode":"5900",
    "wof:name":"Cr\u00e9dit Communal",
    "wof:placetype":"venue"
},
  "geometry": {"coordinates":[4.8701448441,50.724571228],"type":"Point"}
}