{
  "type": "Feature",
  "properties": {
    "addr:full":"Stoofstraat 9 Antwerpen Antwerpen 2000",
    "addr:housenumber":"9",
    "addr:postcode":"2000",
    "addr:street":"Stoofstraat",
    "iso:country":"BE",
    "sg:address":"Stoofstraat 9",
    "sg:city":"Antwerpen",
    "sg:orig_category":"Rev\u00eatements de sols and murs. Antiquit\u00e9s",
    "sg:phone":"+32 3 226 02 12",
    "sg:postcode":"2000",
    "sg:province":"Antwerpen",
    "wof:name":"Keppens",
    "wof:placetype":"venue"
},
  "geometry": {"coordinates":[4.3970360756,51.2192497253],"type":"Point"}
}