{
  "type": "Feature",
  "properties": {
    "addr:full":"Grote Steenweg 138 De Pinte (zevergem) Oost-Vlaanderen 9840",
    "addr:housenumber":"138",
    "addr:postcode":"9840",
    "addr:street":"Grote Steenweg",
    "iso:country":"BE",
    "sg:address":"Grote Steenweg 138",
    "sg:city":"De Pinte (zevergem)",
    "sg:classifiers":[
        {
            "category":"Professional",
            "subcategory":"Secretarial Services",
            "type":"Services"
        }
    ],
    "sg:phone":"+32 9 385 36 87",
    "sg:postcode":"9840",
    "sg:province":"Oost-Vlaanderen",
    "sg:tags":[
        "-",
        "wordprocessing"
    ],
    "wof:name":"Auxilia",
    "wof:placetype":"venue"
},
  "geometry": {"coordinates":[3.6847500801,50.9958305359],"type":"Point"}
}