{
  "type": "Feature",
  "properties": {
    "iso:country":"BE",
    "sg:address":"Putsesteenweg 95",
    "sg:city":"Kalmthout",
    "sg:orig_category":"Imprimeries and copyshops",
    "sg:phone":"+32 3 666 00 94",
    "sg:postcode":"2920",
    "sg:province":"Antwerpen",
    "wof:name":"Jongenelen",
    "wof:placetype":"venue"
},
  "geometry": {"coordinates":[4.4493331909,51.3780174255],"type":"Point"}
}