{
  "type": "Feature",
  "properties": {
    "iso:country":"BE",
    "sg:address":"Boulevard Mairaux 19",
    "sg:city":"La Louvi\u00e8re",
    "sg:classifiers":[
        {
            "category":"Professional",
            "subcategory":"Testing Lab",
            "type":"Services"
        }
    ],
    "sg:phone":"+32 64 22 33 40",
    "sg:postcode":"7100",
    "sg:province":"Hainaut",
    "sg:tags":[
        "chemist"
    ],
    "wof:name":"Mathelart-coquette Sa",
    "wof:placetype":"venue"
},
  "geometry": {"coordinates":[4.1874499321,50.4787788391],"type":"Point"}
}