{
  "type": "Feature",
  "properties": {
    "addr:full":"Van Naemenstraat 35 Sint-niklaas Oost-Vlaanderen 9100",
    "addr:housenumber":"35",
    "addr:postcode":"9100",
    "addr:street":"Naemenstraat",
    "iso:country":"BE",
    "sg:address":"Van Naemenstraat 35",
    "sg:city":"Sint-niklaas",
    "sg:orig_category":"Plaatsen van vloer- and muurbekleding Schilders",
    "sg:phone":"+32 3 776 33 42",
    "sg:postcode":"9100",
    "sg:province":"Oost-Vlaanderen",
    "wof:name":"Nimmegeers",
    "wof:placetype":"venue"
},
  "geometry": {"coordinates":[4.1510272026,51.1697883606],"type":"Point"}
}