{
  "type": "Feature",
  "properties": {
    "addr:full":"Labroyeweg 17 Kortrijk West-Vlaanderen 8510",
    "addr:housenumber":"17",
    "addr:postcode":"8510",
    "addr:street":"Labroyeweg",
    "iso:country":"BE",
    "sg:address":"Labroyeweg 17",
    "sg:city":"Kortrijk",
    "sg:orig_category":"Rundveehouders",
    "sg:phone":"+32 56 22 13 68",
    "sg:postcode":"8510",
    "sg:province":"West-Vlaanderen",
    "wof:name":"Ignaas Duthoo",
    "wof:placetype":"venue"
},
  "geometry": {"coordinates":[3.3146510124,50.766708374],"type":"Point"}
}