{
  "type": "Feature",
  "properties": {
    "iso:country":"BE",
    "sg:address":"Rue Brunehaut 65",
    "sg:city":"Mons",
    "sg:orig_category":"Loodgieterij, verwarming and sanitaire installaties",
    "sg:phone":"+32 65 34 88 75",
    "sg:postcode":"7022",
    "sg:province":"Hainaut",
    "wof:name":"Save Andr\u00c9",
    "wof:placetype":"venue"
},
  "geometry": {"coordinates":[3.9585850239,50.4259757996],"type":"Point"}
}