{
  "type": "Feature",
  "properties": {
    "iso:country":"BE",
    "sg:address":"Bonnert-rte De Bastogne 317",
    "sg:city":"Arlon",
    "sg:orig_category":"Mazda Voertuigen",
    "sg:phone":"+32 63 22 02 74",
    "sg:postcode":"6700",
    "sg:province":"Luxembourg",
    "wof:name":"Garage Lambert Ren\u00c9",
    "wof:placetype":"venue"
},
  "geometry": {"coordinates":[5.8135142326,49.6924438477],"type":"Point"}
}