{
  "type": "Feature",
  "properties": {
    "iso:country":"BE",
    "sg:address":"Molenveld 84b1",
    "sg:city":"Balen",
    "sg:orig_category":"Sportclubs",
    "sg:phone":"+32 14 81 62 52",
    "sg:postcode":"2490",
    "sg:province":"Antwerpen",
    "wof:name":"B.c. Teuten",
    "wof:placetype":"venue"
},
  "geometry": {"coordinates":[5.1808538437,51.1753158569],"type":"Point"}
}