{
  "type": "Feature",
  "properties": {
    "iso:country":"BE",
    "sg:address":"Driehoekstraat 71",
    "sg:city":"Brakel (nederbrakel)",
    "sg:classifiers":[
        {
            "category":"Insurance",
            "subcategory":"Insurance Agent",
            "type":"Services"
        }
    ],
    "sg:phone":"+32 55 42 32 74",
    "sg:postcode":"9660",
    "sg:province":"Oost-Vlaanderen",
    "sg:tags":[
        "broker"
    ],
    "wof:name":"Guns-vanden Branden",
    "wof:placetype":"venue"
},
  "geometry": {"coordinates":[3.766669035,50.8077049255],"type":"Point"}
}