{
  "type": "Feature",
  "properties": {
    "addr:full":"Montenakenweg 8 Sint-truiden Limburg 3800",
    "addr:housenumber":"8",
    "addr:postcode":"3800",
    "addr:street":"Montenakenweg",
    "iso:country":"BE",
    "sg:address":"Montenakenweg 8",
    "sg:city":"Sint-truiden",
    "sg:classifiers":[
        {
            "category":"Personal",
            "subcategory":"Nail Salon",
            "type":"Services"
        }
    ],
    "sg:phone":"+32 11 68 00 49",
    "sg:postcode":"3800",
    "sg:province":"Limburg",
    "sg:tags":[
        "pedicure"
    ],
    "wof:name":"Cindy",
    "wof:placetype":"venue"
},
  "geometry": {"coordinates":[5.1747198105,50.80443573],"type":"Point"}
}