{
  "type": "Feature",
  "properties": {
    "iso:country":"BE",
    "sg:address":"Rue Eeckelaers 45",
    "sg:city":"Bruxelles (saint-josse-ten-noode)",
    "sg:classifiers":[
        {
            "category":"Health Services",
            "subcategory":"Health Practitioner",
            "type":"Services"
        }
    ],
    "sg:phone":"+32 2 733 21 86",
    "sg:postcode":"1210",
    "sg:province":"Bruxelles-Capitale",
    "sg:tags":[
        "physiotherapist"
    ],
    "wof:name":"Faversienne Michel",
    "wof:placetype":"venue"
},
  "geometry": {"coordinates":[4.3804712296,50.8524131775],"type":"Point"}
}