{
  "type": "Feature",
  "properties": {
    "iso:country":"BE",
    "sg:address":"Maalsesteenweg 263",
    "sg:city":"Brugge",
    "sg:orig_category":"Geschenken and souvenirs Verlichting and huishoudartikelen",
    "sg:phone":"+32 50 37 32 99",
    "sg:postcode":"8310",
    "sg:province":"West-Vlaanderen",
    "wof:name":"Casa",
    "wof:placetype":"venue"
},
  "geometry": {"coordinates":[3.2610270977,51.208442688],"type":"Point"}
}