{
  "type": "Feature",
  "properties": {
    "iso:country":"BE",
    "sg:address":"Place Du Sacr\u00c9-coeur 4",
    "sg:city":"Sint-lambrechts-woluwe/woluwe-saint-lambert",
    "sg:orig_category":"M\u00e9decins and sp\u00e9cialistes",
    "sg:phone":"+32 2 770 81 97",
    "sg:postcode":"1200",
    "sg:province":"Bruxelles-Capitale",
    "wof:name":"Jacques Noppen",
    "wof:placetype":"venue"
},
  "geometry": {"coordinates":[4.432284832,50.8415222168],"type":"Point"}
}