{
  "type": "Feature",
  "properties": {
    "iso:country":"BE",
    "sg:address":"Nachtegalenstraat 37",
    "sg:city":"Geel",
    "sg:orig_category":"Alimentation sp\u00e9cialis\u00e9e. Catering and organisation de f\u00eates",
    "sg:phone":"+32 14 58 42 50",
    "sg:postcode":"2440",
    "sg:province":"Antwerpen",
    "wof:name":"Bellinckx",
    "wof:placetype":"venue"
},
  "geometry": {"coordinates":[4.9790410995,51.1730384827],"type":"Point"}
}