{
  "type": "Feature",
  "properties": {
    "addr:full":"Rue Des Mineurs 141 Binche Hainaut 7134",
    "addr:housenumber":"141",
    "addr:postcode":"7134",
    "addr:street":"Rue Des Mineurs",
    "iso:country":"BE",
    "sg:address":"Rue Des Mineurs 141",
    "sg:city":"Binche",
    "sg:classifiers":[
        {
            "category":"Insurance",
            "subcategory":"Life Insurance",
            "type":"Services"
        }
    ],
    "sg:phone":"+32 64 36 85 49",
    "sg:postcode":"7134",
    "sg:province":"Hainaut",
    "sg:tags":[
        "assurance"
    ],
    "wof:name":"Panarisi",
    "wof:placetype":"venue"
},
  "geometry": {"coordinates":[4.2175779343,50.4159622192],"type":"Point"}
}