{
  "type": "Feature",
  "properties": {
    "addr:full":"Harelbekestraat 63 Anzegem (vichte) West-Vlaanderen 8570",
    "addr:housenumber":"63",
    "addr:postcode":"8570",
    "addr:street":"Harelbekestraat",
    "iso:country":"BE",
    "sg:address":"Harelbekestraat 63",
    "sg:city":"Anzegem (vichte)",
    "sg:classifiers":[
        {
            "category":"Personal",
            "subcategory":"Beauty Salon",
            "type":"Services"
        }
    ],
    "sg:phone":"+32 56 77 73 74",
    "sg:postcode":"8570",
    "sg:province":"West-Vlaanderen",
    "wof:name":"Grondwerken Rik Bvba",
    "wof:placetype":"venue"
},
  "geometry": {"coordinates":[3.389786005,50.8424720764],"type":"Point"}
}