{
  "type": "Feature",
  "properties": {
    "iso:country":"BE",
    "sg:address":"Verbrandhofstraat 105",
    "sg:city":"Roeselare",
    "sg:classifiers":[
        {
            "category":"Home & Garden",
            "subcategory":"Building Materials",
            "type":"Retail Goods"
        }
    ],
    "sg:phone":"+32 51 22 17 32",
    "sg:postcode":"8800",
    "sg:province":"West-Vlaanderen",
    "sg:tags":[
        "window"
    ],
    "wof:name":"Ducasteele Gery",
    "wof:placetype":"venue"
},
  "geometry": {"coordinates":[3.1108760834,50.928943634],"type":"Point"}
}