{
  "type": "Feature",
  "properties": {
    "addr:full":"Hamstraat 81 Box 2 Borgloon (hoepertingen) Limburg 3840",
    "addr:housenumber":"81;2",
    "addr:postcode":"3840",
    "addr:street":"Hamstraat;Box",
    "iso:country":"BE",
    "sg:address":"Hamstraat 81 Box 2",
    "sg:city":"Borgloon (hoepertingen)",
    "sg:classifiers":[
        {
            "category":"Building & Trades",
            "subcategory":"Landscaping Services",
            "type":"Services"
        }
    ],
    "sg:phone":"+32 476 59 35 09",
    "sg:postcode":"3840",
    "sg:province":"Limburg",
    "sg:tags":[
        "gardening",
        "garden",
        "maintenance"
    ],
    "wof:name":"D&m Garden",
    "wof:placetype":"venue"
},
  "geometry": {"coordinates":[5.2962942123,50.8080749512],"type":"Point"}
}