{
  "type": "Feature",
  "properties": {
    "addr:full":"Hoogstraat 1 Oudenaarde Oost-Vlaanderen 9700",
    "addr:housenumber":"1",
    "addr:postcode":"9700",
    "addr:street":"Hoogstraat",
    "iso:country":"BE",
    "sg:address":"Hoogstraat 1",
    "sg:city":"Oudenaarde",
    "sg:orig_category":"Traitements param\u00e9dicaux",
    "sg:phone":"+32 55 30 33 21",
    "sg:postcode":"9700",
    "sg:province":"Oost-Vlaanderen",
    "wof:name":"K. Vanrobaeys",
    "wof:placetype":"venue"
},
  "geometry": {"coordinates":[3.6036601067,50.8437423706],"type":"Point"}
}