{
  "type": "Feature",
  "properties": {
    "addr:full":"Schoor 84 Balen Antwerpen 2490",
    "addr:housenumber":"84",
    "addr:postcode":"2490",
    "addr:street":"Schoor",
    "iso:country":"BE",
    "sg:address":"Schoor 84",
    "sg:city":"Balen",
    "sg:orig_category":"Boissons",
    "sg:phone":"+32 14 81 23 27",
    "sg:postcode":"2490",
    "sg:province":"Antwerpen",
    "wof:name":"Drinkhal Geenen",
    "wof:placetype":"venue"
},
  "geometry": {"coordinates":[5.1896481514,51.1601371765],"type":"Point"}
}