{
  "type": "Feature",
  "properties": {
    "addr:full":"Rue Du Fort 50 Bruxelles (saint-gilles) Bruxelles-Capitale 1060",
    "addr:housenumber":"50",
    "addr:postcode":"1060",
    "addr:street":"Rue Du Fort",
    "iso:country":"BE",
    "sg:address":"Rue Du Fort 50",
    "sg:city":"Bruxelles (saint-gilles)",
    "sg:classifiers":[
        {
            "category":"Manufacturing",
            "subcategory":"Tobacco Products",
            "type":"Manufacturing & Wholesale Goods"
        }
    ],
    "sg:phone":"+32 2 538 65 92",
    "sg:postcode":"1060",
    "sg:province":"Bruxelles-Capitale",
    "sg:tags":[
        "leaf",
        "-"
    ],
    "wof:name":"Ben Et Co Cadeaux Sprl",
    "wof:placetype":"venue"
},
  "geometry": {"coordinates":[4.342774868,50.8285522461],"type":"Point"}
}