{
  "type": "Feature",
  "properties": {
    "addr:full":"Place De Carni\u00e8res 39 Morlanwelz (carni\u00e8res) Hainaut 7141",
    "addr:housenumber":"39",
    "addr:postcode":"7141",
    "addr:street":"Place De Carnie\u0300Res",
    "iso:country":"BE",
    "sg:address":"Place De Carni\u00e8res 39",
    "sg:city":"Morlanwelz (carni\u00e8res)",
    "sg:classifiers":[
        {
            "category":"Food & Beverages",
            "subcategory":"Groceries & Convenience Stores",
            "type":"Retail Goods"
        }
    ],
    "sg:phone":"+32 64 44 24 02",
    "sg:postcode":"7141",
    "sg:province":"Hainaut",
    "sg:tags":[
        "grocer"
    ],
    "wof:name":"Fromont G",
    "wof:placetype":"venue"
},
  "geometry": {"coordinates":[4.2546520233,50.4431037903],"type":"Point"}
}