{
  "type": "Feature",
  "properties": {
    "iso:country":"BE",
    "sg:address":"Chauss\u00c9e De Bruxelles 405",
    "sg:city":"Charleroi",
    "sg:classifiers":[
        {
            "category":"Restaurant",
            "type":"Food & Drink"
        }
    ],
    "sg:phone":"+32 71 32 64 79",
    "sg:postcode":"6042",
    "sg:province":"Hainaut",
    "wof:name":"La Luppia",
    "wof:placetype":"venue"
},
  "geometry": {"coordinates":[4.4337282181,50.4501914978],"type":"Point"}
}