{
  "type": "Feature",
  "properties": {
    "iso:country":"BE",
    "sg:address":"Kalmthoutse Steenweg 120a",
    "sg:city":"Wuustwezel",
    "sg:classifiers":[
        {
            "category":"Home & Garden",
            "subcategory":"Building Materials",
            "type":"Retail Goods"
        }
    ],
    "sg:phone":"+32 3 669 99 55",
    "sg:postcode":"2990",
    "sg:province":"Antwerpen",
    "sg:tags":[
        "house"
    ],
    "wof:name":"Garden Lux-raster Blokhutland Bvba",
    "wof:placetype":"venue"
},
  "geometry": {"coordinates":[4.5797848701,51.3904266357],"type":"Point"}
}