{
  "type": "Feature",
  "properties": {
    "addr:full":"Meenselstraat 61a Lubbeek (binkom) Vlaams-Brabant 3211",
    "addr:housenumber":"61a",
    "addr:postcode":"3211",
    "addr:street":"Meenselstraat",
    "iso:country":"BE",
    "sg:address":"Meenselstraat 61a",
    "sg:city":"Lubbeek (binkom)",
    "sg:classifiers":[
        {
            "category":"Building & Trades",
            "subcategory":"Cleaning & Sanitation",
            "type":"Services"
        }
    ],
    "sg:phone":"+32 16 63 56 49",
    "sg:postcode":"3211",
    "sg:province":"Vlaams-Brabant",
    "sg:tags":[
        "cleaner",
        "domestic",
        "vacuum"
    ],
    "wof:name":"Duovac L'aspirateur Central",
    "wof:placetype":"venue"
},
  "geometry": {"coordinates":[4.890376091,50.8773422241],"type":"Point"}
}