{
  "type": "Feature",
  "properties": {
    "iso:country":"BE",
    "sg:address":"Rue Omer Lef\u00e8vre 33",
    "sg:city":"La Louvi\u00e8re",
    "sg:classifiers":[
        {
            "category":"Professional",
            "subcategory":"Lawyer & Legal Services",
            "type":"Services"
        }
    ],
    "sg:phone":"+32 64 22 16 32",
    "sg:postcode":"7100",
    "sg:province":"Hainaut",
    "sg:tags":[
        "notary"
    ],
    "wof:name":"Jacquet A",
    "wof:placetype":"venue"
},
  "geometry": {"coordinates":[4.1938471794,50.4760818481],"type":"Point"}
}