{
  "type": "Feature",
  "properties": {
    "addr:full":"Maastrichtersteenweg 203 Riemst (vroenhoven) Limburg 3770",
    "addr:housenumber":"203",
    "addr:postcode":"3770",
    "addr:street":"Maastrichtersteenweg",
    "iso:country":"BE",
    "sg:address":"Maastrichtersteenweg 203",
    "sg:city":"Riemst (vroenhoven)",
    "sg:classifiers":[
        {
            "category":"Shopping",
            "subcategory":"Antiques",
            "type":"Retail Goods"
        }
    ],
    "sg:phone":"+32 12 21 01 51",
    "sg:postcode":"3770",
    "sg:province":"Limburg",
    "wof:name":"Elisabeth",
    "wof:placetype":"venue"
},
  "geometry": {"coordinates":[5.612569809,50.8188209534],"type":"Point"}
}