{
  "type": "Feature",
  "properties": {
    "addr:full":"Avenue De La Lib\u00c9ration 35 Sambreville Namur 5060",
    "addr:housenumber":"35",
    "addr:postcode":"5060",
    "addr:street":"Avenue De La Libe\u0301Ration",
    "iso:country":"BE",
    "sg:address":"Avenue De La Lib\u00c9ration 35",
    "sg:city":"Sambreville",
    "sg:orig_category":"Diverse kredietdiensten",
    "sg:postcode":"5060",
    "sg:province":"Namur",
    "wof:name":"Bancontact-mister Cash",
    "wof:placetype":"venue"
},
  "geometry": {"coordinates":[4.6285200119,50.4448738098],"type":"Point"}
}