{
  "type": "Feature",
  "properties": {
    "addr:full":"Hazelereik 18 Tongeren Limburg 3700",
    "addr:housenumber":"18",
    "addr:postcode":"3700",
    "addr:street":"Hazelereik",
    "iso:country":"BE",
    "sg:address":"Hazelereik 18",
    "sg:city":"Tongeren",
    "sg:classifiers":[
        {
            "category":"Health Services",
            "subcategory":"Dentist",
            "type":"Services"
        }
    ],
    "sg:phone":"+32 12 23 66 75",
    "sg:postcode":"3700",
    "sg:province":"Limburg",
    "wof:name":"Govaerts M",
    "wof:placetype":"venue"
},
  "geometry": {"coordinates":[5.4838428497,50.7860298157],"type":"Point"}
}