{
  "type": "Feature",
  "properties": {
    "iso:country":"BE",
    "sg:address":"Nazarethsesteenweg 109",
    "sg:city":"Kruishoutem",
    "sg:classifiers":[
        {
            "category":"Home & Garden",
            "subcategory":"Building Materials",
            "type":"Retail Goods"
        }
    ],
    "sg:phone":"+32 9 384 11 72",
    "sg:postcode":"9770",
    "sg:province":"Oost-Vlaanderen",
    "sg:tags":[
        "house"
    ],
    "wof:name":"Van Den Brande F",
    "wof:placetype":"venue"
},
  "geometry": {"coordinates":[3.5846030712,50.928401947],"type":"Point"}
}