{
  "type": "Feature",
  "properties": {
    "addr:full":"Rue Vert Buisson 312 Theux (la Reid) Li\u00e8ge 4910",
    "addr:housenumber":"312",
    "addr:postcode":"4910",
    "addr:street":"Rue Vert Buisson;La Reid",
    "iso:country":"BE",
    "sg:address":"Rue Vert Buisson 312",
    "sg:city":"Theux (la Reid)",
    "sg:classifiers":[
        {
            "category":"Building & Trades",
            "subcategory":"Landscaping Services",
            "type":"Services"
        }
    ],
    "sg:phone":"+32 475 59 29 43",
    "sg:postcode":"4910",
    "sg:province":"Li\u00e8ge",
    "sg:tags":[
        "-",
        "lopping",
        "work",
        "tree",
        "felling"
    ],
    "wof:name":"Geurts Ch",
    "wof:placetype":"venue"
},
  "geometry": {"coordinates":[5.7828202248,50.4637565613],"type":"Point"}
}