{
  "type": "Feature",
  "properties": {
    "addr:full":"Jozef Van Cleemputplein 1 Boom Antwerpen 2850",
    "addr:housenumber":"1",
    "addr:postcode":"2850",
    "addr:street":"Jozef Van Cleemputplein",
    "iso:country":"BE",
    "sg:address":"Jozef Van Cleemputplein 1",
    "sg:city":"Boom",
    "sg:orig_category":"Maisons de repos and r\u00e9sidences",
    "sg:phone":"+32 3 880 27 40",
    "sg:postcode":"2850",
    "sg:province":"Antwerpen",
    "wof:name":"Rusthuis Jan-baptist",
    "wof:placetype":"venue"
},
  "geometry": {"coordinates":[4.3707499504,51.0885314941],"type":"Point"}
}