{
  "type": "Feature",
  "properties": {
    "addr:full":"Avenue De La Paix 26 Koekelberg Bruxelles-Capitale 1081",
    "addr:housenumber":"26",
    "addr:postcode":"1081",
    "addr:street":"Avenue De La Paix",
    "iso:country":"BE",
    "sg:address":"Avenue De La Paix 26",
    "sg:city":"Koekelberg",
    "sg:orig_category":"M\u00e9decins and sp\u00e9cialistes",
    "sg:phone":"+32 2 425 89 51",
    "sg:postcode":"1081",
    "sg:province":"Bruxelles-Capitale",
    "wof:name":"Andr\u00c9 Joris",
    "wof:placetype":"venue"
},
  "geometry": {"coordinates":[4.3165149689,50.8645401001],"type":"Point"}
}