{
  "type": "Feature",
  "properties": {
    "iso:country":"BE",
    "sg:address":"Keiemdorpsstraat 76ba",
    "sg:city":"Diksmuide",
    "sg:orig_category":"Fietsen Watersport-, Sport- and Kampeerbenodigdheden Verhuur",
    "sg:phone":"+32 51 50 49 41",
    "sg:postcode":"8600",
    "sg:province":"West-Vlaanderen",
    "wof:name":"Fietsen Simoens",
    "wof:placetype":"venue"
},
  "geometry": {"coordinates":[2.8817179203,51.0792655945],"type":"Point"}
}