{
  "type": "Feature",
  "properties": {
    "addr:full":"Kruisweg 6 Wuustwezel Antwerpen 2990",
    "addr:housenumber":"6",
    "addr:postcode":"2990",
    "addr:street":"Kruisweg",
    "iso:country":"BE",
    "sg:address":"Kruisweg 6",
    "sg:city":"Wuustwezel",
    "sg:orig_category":"Fujitsu Siemens. R\u00e9alisation de programmes and logiciels. Ordinateurs and \u00e9quipement informatique. E",
    "sg:phone":"+32 3 669 86 48",
    "sg:postcode":"2990",
    "sg:province":"Antwerpen",
    "wof:name":"Baelen Data Design",
    "wof:placetype":"venue"
},
  "geometry": {"coordinates":[4.638961792,51.4002418518],"type":"Point"}
}