{
  "type": "Feature",
  "properties": {
    "iso:country":"BE",
    "sg:address":"Schransstraat 8 Box 2",
    "sg:city":"Herentals (noorderwijk)",
    "sg:classifiers":[
        {
            "category":"Home & Garden",
            "subcategory":"Carpets & Floor Coverings",
            "type":"Retail Goods"
        }
    ],
    "sg:phone":"+32 14 26 13 49",
    "sg:postcode":"2200",
    "sg:province":"Antwerpen",
    "sg:tags":[
        "layer",
        "mosaicists"
    ],
    "wof:name":"Van Den Broeck K",
    "wof:placetype":"venue"
},
  "geometry": {"coordinates":[4.8221869469,51.1240005493],"type":"Point"}
}