{
  "type": "Feature",
  "properties": {
    "addr:full":"Rue Frans Binj\u00c9 8 Schaarbeek/schaerbeek Bruxelles-Capitale 1030",
    "addr:housenumber":"8",
    "addr:postcode":"1030",
    "addr:street":"Rue Frans Binje\u0301",
    "iso:country":"BE",
    "sg:address":"Rue Frans Binj\u00c9 8",
    "sg:city":"Schaarbeek/schaerbeek",
    "sg:orig_category":"M\u00e9decins and sp\u00e9cialistes",
    "sg:phone":"+32 2 216 38 73",
    "sg:postcode":"1030",
    "sg:province":"Bruxelles-Capitale",
    "wof:name":"Fabienne Forton",
    "wof:placetype":"venue"
},
  "geometry": {"coordinates":[4.3848252296,50.8585662842],"type":"Point"}
}