{
  "type": "Feature",
  "properties": {
    "iso:country":"BE",
    "sg:address":"Avenue Albert-mahiels 13b13",
    "sg:city":"Li\u00c8ge",
    "sg:orig_category":"Benzinestations and brandstoffen",
    "sg:phone":"+32 4 344 16 88",
    "sg:postcode":"4020",
    "sg:province":"Li\u00e8ge",
    "wof:name":"Saga",
    "wof:placetype":"venue"
},
  "geometry": {"coordinates":[5.5831332207,50.6221084595],"type":"Point"}
}