{
  "type": "Feature",
  "properties": {
    "iso:country":"BE",
    "sg:address":"Heiveldstraat 285",
    "sg:city":"Gent",
    "sg:orig_category":"Poissonniers and \u00e9caillers",
    "sg:phone":"+32 9 228 35 08",
    "sg:postcode":"9040",
    "sg:province":"Oost-Vlaanderen",
    "wof:name":"Alain Miche",
    "wof:placetype":"venue"
},
  "geometry": {"coordinates":[3.7655379772,51.0661964417],"type":"Point"}
}