{
  "type": "Feature",
  "properties": {
    "addr:full":"Rue Des Ecoles 56ba Hotton Luxembourg 6990",
    "addr:housenumber":"56ba",
    "addr:postcode":"6990",
    "addr:street":"Rue Des Ecoles",
    "iso:country":"BE",
    "sg:address":"Rue Des Ecoles 56ba",
    "sg:city":"Hotton",
    "sg:orig_category":"Travail and traitement du bois",
    "sg:phone":"+32 84 46 61 35",
    "sg:postcode":"6990",
    "sg:province":"Luxembourg",
    "wof:name":"Hotton-bois",
    "wof:placetype":"venue"
},
  "geometry": {"coordinates":[5.4497270584,50.2708969116],"type":"Point"}
}