{
  "type": "Feature",
  "properties": {
    "addr:full":"Rue Le Bas 51 Tournai Hainaut 7533",
    "addr:housenumber":"51",
    "addr:postcode":"7533",
    "addr:street":"Rue Le Bas",
    "iso:country":"BE",
    "sg:address":"Rue Le Bas 51",
    "sg:city":"Tournai",
    "sg:orig_category":"Schoonmaakbedrijven and ongediertebestrijding Woningbouw",
    "sg:phone":"+32 69 54 88 59",
    "sg:postcode":"7533",
    "sg:province":"Hainaut",
    "wof:name":"Patrice Adam",
    "wof:placetype":"venue"
},
  "geometry": {"coordinates":[3.5189330578,50.6369056702],"type":"Point"}
}