{
  "type": "Feature",
  "properties": {
    "addr:full":"Rue De La Foulerie 81 Limbourg Li\u00e8ge 4830",
    "addr:housenumber":"81",
    "addr:postcode":"4830",
    "addr:street":"Rue De La Foulerie",
    "iso:country":"BE",
    "sg:address":"Rue De La Foulerie 81",
    "sg:city":"Limbourg",
    "sg:classifiers":[
        {
            "category":"Utilities",
            "subcategory":"Fuel Oil & Lpg",
            "type":"Services"
        }
    ],
    "sg:phone":"+32 87 76 28 44",
    "sg:postcode":"4830",
    "sg:province":"Li\u00e8ge",
    "wof:name":"Frebel J & Fils",
    "wof:placetype":"venue"
},
  "geometry": {"coordinates":[5.9407401085,50.6112518311],"type":"Point"}
}