{
  "type": "Feature",
  "properties": {
    "addr:full":"Steenbakkerijstraat 8 Kuurne West-Vlaanderen 8520",
    "addr:housenumber":"8",
    "addr:postcode":"8520",
    "addr:street":"Steenbakkerijstraat",
    "iso:country":"BE",
    "sg:address":"Steenbakkerijstraat 8",
    "sg:city":"Kuurne",
    "sg:orig_category":"Elektrische installaties voor woningen",
    "sg:phone":"+32 56 70 38 39",
    "sg:postcode":"8520",
    "sg:province":"West-Vlaanderen",
    "wof:name":"Guy Cobbe",
    "wof:placetype":"venue"
},
  "geometry": {"coordinates":[3.2991371155,50.853805542],"type":"Point"}
}