{
  "type": "Feature",
  "properties": {
    "iso:country":"BE",
    "sg:address":"Mosselstraat 31",
    "sg:city":"Jabbeke",
    "sg:orig_category":"Woningbouw",
    "sg:phone":"+32 50 81 34 34",
    "sg:postcode":"8490",
    "sg:province":"West-Vlaanderen",
    "wof:name":"Ivan Benoot",
    "wof:placetype":"venue"
},
  "geometry": {"coordinates":[3.079914093,51.1538543701],"type":"Point"}
}