{
  "type": "Feature",
  "properties": {
    "iso:country":"BE",
    "sg:address":"Larum 21",
    "sg:city":"Geel",
    "sg:orig_category":"Alimentation sp\u00e9cialis\u00e9e",
    "sg:phone":"+32 14 58 66 40",
    "sg:postcode":"2440",
    "sg:province":"Antwerpen",
    "wof:name":"Fijnkosthoeve",
    "wof:placetype":"venue"
},
  "geometry": {"coordinates":[4.9707651138,51.1648902893],"type":"Point"}
}