{
  "type": "Feature",
  "properties": {
    "iso:country":"BE",
    "sg:address":"Brouwerijstraat 51",
    "sg:city":"Kortenberg",
    "sg:orig_category":"Blanchisseries and teintureries",
    "sg:phone":"+32 2 759 75 59",
    "sg:postcode":"3070",
    "sg:province":"Vlaams-Brabant",
    "wof:name":"H.i.",
    "wof:placetype":"venue"
},
  "geometry": {"coordinates":[4.5428128242,50.886341095],"type":"Point"}
}