{
  "type": "Feature",
  "properties": {
    "addr:full":"Rue Winston Churchill 37 Courcelles Hainaut 6180",
    "addr:housenumber":"37",
    "addr:postcode":"6180",
    "addr:street":"Rue Winston Churchill",
    "iso:country":"BE",
    "sg:address":"Rue Winston Churchill 37",
    "sg:city":"Courcelles",
    "sg:classifiers":[
        {
            "category":"Personal",
            "subcategory":"Beauty Salon",
            "type":"Services"
        }
    ],
    "sg:phone":"+32 71 46 57 62",
    "sg:postcode":"6180",
    "sg:province":"Hainaut",
    "sg:tags":[
        "lady",
        "-",
        "hairdressing"
    ],
    "wof:name":"Intemporel (l')",
    "wof:placetype":"venue"
},
  "geometry": {"coordinates":[4.3822407722,50.460975647],"type":"Point"}
}