{
  "type": "Feature",
  "properties": {
    "addr:full":"Rue Gilles Ghaye 10bb Donceel Li\u00e8ge 4357",
    "addr:housenumber":"10bb",
    "addr:postcode":"4357",
    "addr:street":"Rue Gilles Ghaye",
    "iso:country":"BE",
    "sg:address":"Rue Gilles Ghaye 10bb",
    "sg:city":"Donceel",
    "sg:orig_category":"Voedingsspeciaalzaken",
    "sg:phone":"+32 19 54 48 03",
    "sg:postcode":"4357",
    "sg:province":"Li\u00e8ge",
    "wof:name":"Luc Delvaux",
    "wof:placetype":"venue"
},
  "geometry": {"coordinates":[5.3183188438,50.6569671631],"type":"Point"}
}