{
  "type": "Feature",
  "properties": {
    "addr:full":"Belgi\u00eblei 50 Box 23 Antwerpen Antwerpen 2018",
    "addr:housenumber":"50 box 23",
    "addr:postcode":"2018",
    "addr:street":"Belgie\u0308Lei",
    "iso:country":"BE",
    "sg:address":"Belgi\u00eblei 50 Box 23",
    "sg:city":"Antwerpen",
    "sg:classifiers":[
        {
            "category":"Manufacturing",
            "subcategory":"Jewelry",
            "type":"Manufacturing & Wholesale Goods"
        }
    ],
    "sg:phone":"+32 3 230 29 03",
    "sg:postcode":"2018",
    "sg:province":"Antwerpen",
    "sg:tags":[
        "diamond",
        "broker"
    ],
    "wof:name":"Poonam Gems",
    "wof:placetype":"venue"
},
  "geometry": {"coordinates":[4.4206290245,51.207950592],"type":"Point"}
}