{
  "type": "Feature",
  "properties": {
    "iso:country":"BE",
    "sg:address":"Rue De France",
    "sg:city":"Philippeville",
    "sg:orig_category":"Supermarkten",
    "sg:postcode":"5600",
    "sg:province":"Namur",
    "wof:name":"Aldi",
    "wof:placetype":"venue"
},
  "geometry": {"coordinates":[4.5399699211,50.195980072],"type":"Point"}
}