{
  "type": "Feature",
  "properties": {
    "addr:full":"Rue De Pierrard 24 Virton Luxembourg 6761",
    "addr:housenumber":"24",
    "addr:postcode":"6761",
    "addr:street":"Rue De Pierrard",
    "iso:country":"BE",
    "sg:address":"Rue De Pierrard 24",
    "sg:city":"Virton",
    "sg:orig_category":"Producteurs de fruits. Producteurs de l\u00e9gumes",
    "sg:phone":"+32 63 57 19 07",
    "sg:postcode":"6761",
    "sg:province":"Luxembourg",
    "wof:name":"Robert Munaut",
    "wof:placetype":"venue"
},
  "geometry": {"coordinates":[5.548579216,49.5664329529],"type":"Point"}
}