{
  "type": "Feature",
  "properties": {
    "addr:full":"Habaru 17 Bertrix (assenois) Luxembourg 6860",
    "addr:housenumber":"17",
    "addr:postcode":"6860",
    "addr:street":"Habaru",
    "iso:country":"BE",
    "sg:address":"Habaru 17",
    "sg:city":"Bertrix (assenois)",
    "sg:classifiers":[
        {
            "category":"Building & Trades",
            "subcategory":"Landscaping Services",
            "type":"Services"
        }
    ],
    "sg:phone":"+32 63 43 32 98",
    "sg:postcode":"6860",
    "sg:province":"Luxembourg",
    "sg:tags":[
        "forestry"
    ],
    "wof:name":"Bozet F",
    "wof:placetype":"venue"
},
  "geometry": {"coordinates":[5.5349779129,49.7996826172],"type":"Point"}
}