{
  "type": "Feature",
  "properties": {
    "iso:country":"BE",
    "sg:address":"Chauss\u00e9e De Bruxelles 75",
    "sg:city":"La Hulpe",
    "sg:classifiers":[
        {
            "category":"Shopping",
            "subcategory":"Discount & Variety Stores",
            "type":"Retail Goods"
        }
    ],
    "sg:postcode":"1310",
    "sg:province":"Brabant Wallon",
    "sg:tags":[
        "shop",
        "clearers",
        "curiosity",
        "furniture"
    ],
    "wof:name":"Finet",
    "wof:placetype":"venue"
},
  "geometry": {"coordinates":[4.4757609367,50.7348937988],"type":"Point"}
}