{
  "type": "Feature",
  "properties": {
    "iso:country":"BE",
    "sg:address":"Meensesteenweg 448",
    "sg:city":"Roeselare",
    "sg:orig_category":"V\u00e9hicules automobiles",
    "sg:phone":"+32 51 20 54 62",
    "sg:postcode":"8800",
    "sg:province":"West-Vlaanderen",
    "wof:name":"Virgile Auto\u00b4s",
    "wof:placetype":"venue"
},
  "geometry": {"coordinates":[3.1162970066,50.9185028076],"type":"Point"}
}