{
  "type": "Feature",
  "properties": {
    "addr:full":"Hulshoutsesteenweg 24 Westerlo Antwerpen 2260",
    "addr:housenumber":"24",
    "addr:postcode":"2260",
    "addr:street":"Hulshoutsesteenweg",
    "iso:country":"BE",
    "sg:address":"Hulshoutsesteenweg 24",
    "sg:city":"Westerlo",
    "sg:classifiers":[
        {
            "category":"Wholesale",
            "subcategory":"Books, Periodicals, & Newspapers",
            "type":"Manufacturing & Wholesale Goods"
        }
    ],
    "sg:phone":"+32 16 68 05 87",
    "sg:postcode":"2260",
    "sg:province":"Antwerpen",
    "sg:tags":[
        "publisher"
    ],
    "wof:name":"Kramat",
    "wof:placetype":"venue"
},
  "geometry": {"coordinates":[4.8313789368,51.072517395],"type":"Point"}
}