{
  "type": "Feature",
  "properties": {
    "addr:full":"Hoogstraat 75 Waasmunster Oost-Vlaanderen 9250",
    "addr:housenumber":"75",
    "addr:postcode":"9250",
    "addr:street":"Hoogstraat",
    "iso:country":"BE",
    "sg:address":"Hoogstraat 75",
    "sg:city":"Waasmunster",
    "sg:classifiers":[
        {
            "category":"Building & Trades",
            "subcategory":"Construction",
            "type":"Services"
        }
    ],
    "sg:phone":"+32 52 46 14 14",
    "sg:postcode":"9250",
    "sg:province":"Oost-Vlaanderen",
    "sg:tags":[
        "flue"
    ],
    "wof:name":"Heyninck-verschelden Bvba",
    "wof:placetype":"venue"
},
  "geometry": {"coordinates":[4.0879659653,51.111000061],"type":"Point"}
}