{
  "type": "Feature",
  "properties": {
    "addr:full":"Grote Markt 28 Halle Vlaams-Brabant 1500",
    "addr:housenumber":"28",
    "addr:postcode":"1500",
    "addr:street":"Grote Markt",
    "iso:country":"BE",
    "sg:address":"Grote Markt 28",
    "sg:city":"Halle",
    "sg:classifiers":[
        {
            "category":"Restaurant",
            "type":"Food & Drink"
        }
    ],
    "sg:phone":"+32 2 361 28 08",
    "sg:postcode":"1500",
    "sg:province":"Vlaams-Brabant",
    "wof:name":"Olifant",
    "wof:placetype":"venue"
},
  "geometry": {"coordinates":[4.2375788689,50.7362518311],"type":"Point"}
}