{
  "type": "Feature",
  "properties": {
    "iso:country":"BE",
    "sg:address":"Rudderhove 75",
    "sg:city":"Harelbeke",
    "sg:orig_category":"Eclairage et \u00e9quipements du foyer",
    "sg:phone":"+32 56 72 67 86",
    "sg:postcode":"8530",
    "sg:province":"West-Vlaanderen",
    "wof:name":"Doro Light",
    "wof:placetype":"venue"
},
  "geometry": {"coordinates":[3.3166871071,50.8647766113],"type":"Point"}
}