{
  "type": "Feature",
  "properties": {
    "iso:country":"BE",
    "sg:address":"Strateneinde 8",
    "sg:city":"Vorselaar",
    "sg:orig_category":"Rundveehouders",
    "sg:phone":"+32 14 51 32 76",
    "sg:postcode":"2290",
    "sg:province":"Antwerpen",
    "wof:name":"Leonard Smits",
    "wof:placetype":"venue"
},
  "geometry": {"coordinates":[4.76212883,51.2260437012],"type":"Point"}
}