{
  "type": "Feature",
  "properties": {
    "iso:country":"BE",
    "sg:address":"Molenweg 55",
    "sg:city":"Zonhoven",
    "sg:orig_category":"Newspapers, magazines, periodicals - Distribution",
    "sg:phone":"+32 11 81 38 74",
    "sg:postcode":"3520",
    "sg:province":"Limburg",
    "wof:name":"Peggy",
    "wof:placetype":"venue"
},
  "geometry": {"coordinates":[5.4090561867,50.9874229431],"type":"Point"}
}