{
  "type": "Feature",
  "properties": {
    "iso:country":"BE",
    "sg:address":"Rue De Roubaix 219",
    "sg:city":"Mouscron",
    "sg:classifiers":[
        {
            "category":"Bars & Pubs",
            "type":"Food & Drink"
        }
    ],
    "sg:phone":"+32 56 33 07 45",
    "sg:postcode":"7700",
    "sg:province":"Hainaut",
    "wof:name":"Coin Du Stade (au)",
    "wof:placetype":"venue"
},
  "geometry": {"coordinates":[3.2065460682,50.7349853516],"type":"Point"}
}