{
  "type": "Feature",
  "properties": {
    "addr:full":"Rue De L'automne 58 Elsene/ixelles Bruxelles-Capitale 1050",
    "addr:housenumber":"58",
    "addr:postcode":"1050",
    "addr:street":"Rue De L'Automne",
    "iso:country":"BE",
    "sg:address":"Rue De L'automne 58",
    "sg:city":"Elsene/ixelles",
    "sg:orig_category":"V\u00eatements",
    "sg:phone":"+32 2 647 90 03",
    "sg:postcode":"1050",
    "sg:province":"Bruxelles-Capitale",
    "wof:name":"Vannitsem",
    "wof:placetype":"venue"
},
  "geometry": {"coordinates":[4.3901228905,50.8200340271],"type":"Point"}
}