{
  "type": "Feature",
  "properties": {
    "iso:country":"BE",
    "sg:address":"Rue Es Thier 23",
    "sg:city":"Hamoir",
    "sg:classifiers":[
        {
            "category":"Home & Garden",
            "subcategory":"Building Materials",
            "type":"Retail Goods"
        }
    ],
    "sg:phone":"+32 86 38 90 86",
    "sg:postcode":"4180",
    "sg:province":"Li\u00e8ge",
    "sg:tags":[
        "window"
    ],
    "wof:name":"Bieber Pvc Sa",
    "wof:placetype":"venue"
},
  "geometry": {"coordinates":[5.5287017822,50.4277687073],"type":"Point"}
}