{
  "type": "Feature",
  "properties": {
    "iso:country":"BE",
    "sg:address":"Notelarestraat 34",
    "sg:city":"Wellen",
    "sg:classifiers":[
        {
            "category":"Bars & Pubs",
            "type":"Food & Drink"
        }
    ],
    "sg:phone":"+32 12 74 18 37",
    "sg:postcode":"3830",
    "sg:province":"Limburg",
    "wof:name":"Mariette",
    "wof:placetype":"venue"
},
  "geometry": {"coordinates":[5.3388462067,50.8384628296],"type":"Point"}
}