{
  "type": "Feature",
  "properties": {
    "addr:full":"Avenue Champs Ston\u00e9 57 Fosses-la-ville Namur 5070",
    "addr:housenumber":"57",
    "addr:postcode":"5070",
    "addr:street":"Avenue Champs Stone\u0301",
    "iso:country":"BE",
    "sg:address":"Avenue Champs Ston\u00e9 57",
    "sg:city":"Fosses-la-ville",
    "sg:classifiers":[
        {
            "category":"Health Services",
            "subcategory":"Health Practitioner",
            "type":"Services"
        }
    ],
    "sg:phone":"+32 71 71 20 23",
    "sg:postcode":"5070",
    "sg:province":"Namur",
    "sg:tags":[
        "physiotherapist"
    ],
    "wof:name":"Lorand Philippe",
    "wof:placetype":"venue"
},
  "geometry": {"coordinates":[4.6892728806,50.3935852051],"type":"Point"}
}