{
  "type": "Feature",
  "properties": {
    "iso:country":"BE",
    "sg:address":"Heistraat 52",
    "sg:city":"Wuustwezel",
    "sg:orig_category":"Rundveehouders",
    "sg:phone":"+32 3 669 72 08",
    "sg:postcode":"2990",
    "sg:province":"Antwerpen",
    "wof:name":"Louis Breugelmans",
    "wof:placetype":"venue"
},
  "geometry": {"coordinates":[4.5816230774,51.4163970947],"type":"Point"}
}