{
  "type": "Feature",
  "properties": {
    "iso:country":"BE",
    "sg:address":"Zandgroefweg 7",
    "sg:city":"Brecht (sint-job-in-'t Goor)",
    "sg:classifiers":[
        {
            "category":"Professional",
            "subcategory":"Accounting & Tax Preparation",
            "type":"Services"
        }
    ],
    "sg:phone":"+32 3 663 25 63",
    "sg:postcode":"2960",
    "sg:province":"Antwerpen",
    "sg:tags":[
        "bookkeeper"
    ],
    "wof:name":"Vermeiren F",
    "wof:placetype":"venue"
},
  "geometry": {"coordinates":[4.5616769791,51.302986145],"type":"Point"}
}