{
  "type": "Feature",
  "properties": {
    "iso:country":"BE",
    "sg:address":"Rue Emile Vandervelde 5",
    "sg:city":"Courcelles (souvret)",
    "sg:classifiers":[
        {
            "category":"Education",
            "subcategory":"Library",
            "type":"Public Place"
        }
    ],
    "sg:phone":"+32 71 46 99 55",
    "sg:postcode":"6182",
    "sg:province":"Hainaut",
    "wof:name":"Bibliotheque Communale",
    "wof:placetype":"venue"
},
  "geometry": {"coordinates":[4.3542299271,50.4462013245],"type":"Point"}
}