{
  "type": "Feature",
  "properties": {
    "iso:country":"BE",
    "sg:address":"Kerselarenlaan 33",
    "sg:city":"Schaarbeek/schaerbeek",
    "sg:orig_category":"Huishoudapparaten, televisies and radio's MEUBELONTWERP AND -INSTALLATIE",
    "sg:phone":"+32 2 736 90 94",
    "sg:postcode":"1030",
    "sg:province":"Bruxelles-Capitale",
    "wof:name":"Cuisines American K.",
    "wof:placetype":"venue"
},
  "geometry": {"coordinates":[4.4047670364,50.8483734131],"type":"Point"}
}