{
  "type": "Feature",
  "properties": {
    "addr:full":"Rue Petoumont 13 Vise Li\u00e8ge 4602",
    "addr:housenumber":"13",
    "addr:postcode":"4602",
    "addr:street":"Rue Petoumont",
    "iso:country":"BE",
    "sg:address":"Rue Petoumont 13",
    "sg:city":"Vise",
    "sg:orig_category":"Installatie van houten of kunststof schrijnwerk Verlichting and huishoudartikelen",
    "sg:phone":"+32 4 362 67 31",
    "sg:postcode":"4602",
    "sg:province":"Li\u00e8ge",
    "wof:name":"Roger Georges",
    "wof:placetype":"venue"
},
  "geometry": {"coordinates":[5.6731290817,50.6794929504],"type":"Point"}
}