{
  "type": "Feature",
  "properties": {
    "iso:country":"BE",
    "sg:address":"Komenstraat 77bb",
    "sg:city":"Wervik",
    "sg:orig_category":"Entretien and r\u00e9parations de voitures",
    "sg:phone":"+32 56 31 16 99",
    "sg:postcode":"8940",
    "sg:province":"West-Vlaanderen",
    "wof:name":"Hendrik Debackere",
    "wof:placetype":"venue"
},
  "geometry": {"coordinates":[3.033162117,50.7798423767],"type":"Point"}
}