{
  "type": "Feature",
  "properties": {
    "addr:full":"Handelslei 202 Zoersel Antwerpen 2980",
    "addr:housenumber":"202",
    "addr:postcode":"2980",
    "iso:country":"BE",
    "sg:address":"Handelslei 202",
    "sg:city":"Zoersel",
    "sg:orig_category":"Rev\u00eatements pour sols and murs. Peinture",
    "sg:phone":"+32 3 385 84 10",
    "sg:postcode":"2980",
    "sg:province":"Antwerpen",
    "wof:name":"F. Van Looy",
    "wof:placetype":"venue"
},
  "geometry": {"coordinates":[4.6484470367,51.2730941772],"type":"Point"}
}