{
  "type": "Feature",
  "properties": {
    "addr:full":"Rue De La Chapelle 121 Verviers Li\u00e8ge 4800",
    "addr:housenumber":"121",
    "addr:postcode":"4800",
    "addr:street":"Rue De La Chapelle",
    "iso:country":"BE",
    "sg:address":"Rue De La Chapelle 121",
    "sg:city":"Verviers",
    "sg:orig_category":"Epiceries",
    "sg:phone":"+32 87 33 24 81",
    "sg:postcode":"4800",
    "sg:province":"Li\u00e8ge",
    "wof:name":"Senay Cayir",
    "wof:placetype":"venue"
},
  "geometry": {"coordinates":[5.8594508171,50.5917663574],"type":"Point"}
}