{
  "type": "Feature",
  "properties": {
    "iso:country":"BE",
    "sg:address":"Roeselarestraat 169",
    "sg:city":"Wevelgem",
    "sg:classifiers":[
        {
            "category":"Social Services",
            "subcategory":"Job Training",
            "type":"Services"
        }
    ],
    "sg:phone":"+32 56 40 40 40",
    "sg:postcode":"8560",
    "sg:province":"West-Vlaanderen",
    "sg:tags":[
        "personnel"
    ],
    "wof:name":"Taste And Colours",
    "wof:placetype":"venue"
},
  "geometry": {"coordinates":[3.1793379784,50.8156166077],"type":"Point"}
}