{
  "type": "Feature",
  "properties": {
    "addr:full":"Rue Vivier Le Duc 3 Court-saint-etienne Brabant Wallon 1490",
    "addr:housenumber":"3;1490",
    "addr:street":"Rue Vivier Le Duc",
    "iso:country":"BE",
    "sg:address":"Rue Vivier Le Duc 3",
    "sg:city":"Court-saint-etienne",
    "sg:classifiers":[
        {
            "category":"Taxi",
            "type":"Transportation"
        }
    ],
    "sg:phone":"+32 10 61 15 50",
    "sg:postcode":"1490",
    "sg:province":"Brabant Wallon",
    "sg:tags":[
        "taxi's"
    ],
    "wof:name":"Taxi Rasquart",
    "wof:placetype":"venue"
},
  "geometry": {"coordinates":[4.6001000404,50.6444511414],"type":"Point"}
}