{
  "type": "Feature",
  "properties": {
    "addr:full":"Van Meerstraetenlaan 8 Tremelo Vlaams-Brabant 3120",
    "addr:housenumber":"8",
    "addr:postcode":"3120",
    "addr:street":"Van Meerstraetenlaan",
    "iso:country":"BE",
    "sg:address":"Van Meerstraetenlaan 8",
    "sg:city":"Tremelo",
    "sg:classifiers":[
        {
            "category":"Professional",
            "subcategory":"Management & Consulting",
            "type":"Services"
        }
    ],
    "sg:phone":"+32 15 22 68 66",
    "sg:postcode":"3120",
    "sg:province":"Vlaams-Brabant",
    "sg:tags":[
        "consultant"
    ],
    "wof:name":"Waelbers Bvba",
    "wof:placetype":"venue"
},
  "geometry": {"coordinates":[4.7247519493,51.0156936646],"type":"Point"}
}