{
  "type": "Feature",
  "properties": {
    "addr:full":"Gilainstraat 54 Tienen Vlaams-Brabant 3300",
    "addr:housenumber":"54",
    "addr:postcode":"3300",
    "addr:street":"Gilainstraat",
    "iso:country":"BE",
    "sg:address":"Gilainstraat 54",
    "sg:city":"Tienen",
    "sg:orig_category":"Baby- and kinderkleding Babyspullen Meubelzaken, woning- and keukeninrichting",
    "sg:phone":"+32 16 81 47 98",
    "sg:postcode":"3300",
    "sg:province":"Vlaams-Brabant",
    "wof:name":"Huis Baby Set",
    "wof:placetype":"venue"
},
  "geometry": {"coordinates":[4.9365448952,50.809928894],"type":"Point"}
}