{
  "type": "Feature",
  "properties": {
    "addr:full":"Statiestraat 2 Mol Antwerpen 2400",
    "addr:housenumber":"2",
    "addr:postcode":"2400",
    "addr:street":"Statiestraat",
    "iso:country":"BE",
    "sg:address":"Statiestraat 2",
    "sg:city":"Mol",
    "sg:orig_category":"Krantenwinkels Rookartikelen",
    "sg:phone":"+32 14 31 18 94",
    "sg:postcode":"2400",
    "sg:province":"Antwerpen",
    "wof:name":"Press Shop",
    "wof:placetype":"venue"
},
  "geometry": {"coordinates":[5.1182022095,51.1898498535],"type":"Point"}
}