{
  "type": "Feature",
  "properties": {
    "iso:country":"BE",
    "sg:address":"Rue Astrid 34",
    "sg:city":"P\u00e9ruwelz",
    "sg:classifiers":[
        {
            "category":"Personal",
            "subcategory":"Beauty Salon",
            "type":"Services"
        }
    ],
    "sg:postcode":"7600",
    "sg:province":"Hainaut",
    "sg:tags":[
        "lady",
        "-",
        "hairdressing"
    ],
    "wof:name":"Jacqueline Antkowiak",
    "wof:placetype":"venue"
},
  "geometry": {"coordinates":[3.5924339294,50.5120315552],"type":"Point"}
}