{
  "type": "Feature",
  "properties": {
    "addr:full":"Aartrijkestraat 73 Torhout West-Vlaanderen 8820",
    "addr:housenumber":"73",
    "addr:postcode":"8820",
    "addr:street":"Aartrijkestraat",
    "iso:country":"BE",
    "sg:address":"Aartrijkestraat 73",
    "sg:city":"Torhout",
    "sg:classifiers":[
        {
            "category":"Home & Garden",
            "subcategory":"Hardware",
            "type":"Retail Goods"
        }
    ],
    "sg:phone":"+32 50 21 23 78",
    "sg:postcode":"8820",
    "sg:province":"West-Vlaanderen",
    "sg:tags":[
        "builders'",
        "-",
        "furniture"
    ],
    "wof:name":"Vervisch L",
    "wof:placetype":"venue"
},
  "geometry": {"coordinates":[3.0994160175,51.0737304688],"type":"Point"}
}