{
  "type": "Feature",
  "properties": {
    "iso:country":"BE",
    "sg:address":"Rue Du Chesle 19ba",
    "sg:city":"Florennes",
    "sg:orig_category":"Woningbouw",
    "sg:phone":"+32 71 68 95 77",
    "sg:postcode":"5620",
    "sg:province":"Namur",
    "wof:name":"Ets. Croes Joseph",
    "wof:placetype":"venue"
},
  "geometry": {"coordinates":[4.5971698761,50.2514305115],"type":"Point"}
}