{
  "type": "Feature",
  "properties": {
    "addr:full":"Rue Du Bout De La Haut 259 Quaregnon Hainaut 7390",
    "addr:housenumber":"259",
    "addr:postcode":"7390",
    "addr:street":"Rue Du Bout De La Haut",
    "iso:country":"BE",
    "sg:address":"Rue Du Bout De La Haut 259",
    "sg:city":"Quaregnon",
    "sg:orig_category":"Pain, p\u00e2tisseries and confiseries",
    "sg:phone":"+32 65 67 35 11",
    "sg:postcode":"7390",
    "sg:province":"Hainaut",
    "wof:name":"Au Gourmand Ravi",
    "wof:placetype":"venue"
},
  "geometry": {"coordinates":[3.8704690933,50.4193458557],"type":"Point"}
}