{
  "type": "Feature",
  "properties": {
    "addr:full":"Rue L\u00e9on Fr\u00e9d\u00e9ricq 26 Li\u00e8ge 1 (li\u00e8ge 2) Li\u00e8ge 4020",
    "addr:housenumber":"26;1;2",
    "addr:postcode":"4020",
    "addr:street":"Rue Le\u0301On Fre\u0301De\u0301Ricq",
    "iso:country":"BE",
    "sg:address":"Rue L\u00e9on Fr\u00e9d\u00e9ricq 26",
    "sg:city":"Li\u00e8ge 1 (li\u00e8ge 2)",
    "sg:classifiers":[
        {
            "category":"Health Services",
            "subcategory":"Health Practitioner",
            "type":"Services"
        }
    ],
    "sg:phone":"+32 4 341 51 27",
    "sg:postcode":"4020",
    "sg:province":"Li\u00e8ge",
    "sg:tags":[
        "physiotherapist"
    ],
    "wof:name":"Bockourt Karin",
    "wof:placetype":"venue"
},
  "geometry": {"coordinates":[5.5756931305,50.6338806152],"type":"Point"}
}