{
  "type": "Feature",
  "properties": {
    "iso:country":"BE",
    "sg:address":"Rue Paul Pastur 47",
    "sg:city":"Pont-\u00e0-celles (buzet)",
    "sg:classifiers":[
        {
            "category":"Professional",
            "subcategory":"Accounting & Tax Preparation",
            "type":"Services"
        }
    ],
    "sg:phone":"+32 71 84 61 11",
    "sg:postcode":"6230",
    "sg:province":"Hainaut",
    "sg:tags":[
        "bookkeeper"
    ],
    "wof:name":"Santa Isabel Sprl",
    "wof:placetype":"venue"
},
  "geometry": {"coordinates":[4.3702998161,50.5407714844],"type":"Point"}
}