{
  "type": "Feature",
  "properties": {
    "iso:country":"BE",
    "sg:address":"Rue Du Grand Pr\u00e9 51b",
    "sg:city":"Comblain-au-pont",
    "sg:classifiers":[
        {
            "category":"Health Services",
            "subcategory":"Health Practitioner",
            "type":"Services"
        }
    ],
    "sg:phone":"+32 4 369 29 72",
    "sg:postcode":"4170",
    "sg:province":"Li\u00e8ge",
    "sg:tags":[
        "physiotherapist"
    ],
    "wof:name":"Baczkiewicz D",
    "wof:placetype":"venue"
},
  "geometry": {"coordinates":[5.5808558464,50.4684906006],"type":"Point"}
}