{
  "type": "Feature",
  "properties": {
    "addr:full":"Guido Gezellelaan 3 Lint Antwerpen 2547",
    "addr:housenumber":"3",
    "addr:postcode":"2547",
    "addr:street":"Guido Gezellelaan",
    "iso:country":"BE",
    "sg:address":"Guido Gezellelaan 3",
    "sg:city":"Lint",
    "sg:classifiers":[
        {
            "category":"Freight",
            "type":"Transportation"
        }
    ],
    "sg:phone":"+32 3 489 11 74",
    "sg:postcode":"2547",
    "sg:province":"Antwerpen",
    "sg:tags":[
        "-",
        "transport"
    ],
    "wof:name":"Van Den Bergh Frank Bvba",
    "wof:placetype":"venue"
},
  "geometry": {"coordinates":[4.5122032166,51.1229324341],"type":"Point"}
}