{
  "type": "Feature",
  "properties": {
    "addr:full":"Rue Du Vicinal 27 Hamoir Li\u00e8ge 4180",
    "addr:housenumber":"27",
    "addr:postcode":"4180",
    "addr:street":"Rue Du Vicinal",
    "iso:country":"BE",
    "sg:address":"Rue Du Vicinal 27",
    "sg:city":"Hamoir",
    "sg:orig_category":"Installation \u00e9lectrique r\u00e9sidentielle",
    "sg:phone":"+32 4 369 27 38",
    "sg:postcode":"4180",
    "sg:province":"Li\u00e8ge",
    "wof:name":"Fe. Dethier",
    "wof:placetype":"venue"
},
  "geometry": {"coordinates":[5.5663700104,50.4610214233],"type":"Point"}
}