{
  "type": "Feature",
  "properties": {
    "iso:country":"BE",
    "sg:address":"Chauss\u00c9e De Charleroi 293",
    "sg:city":"Fleurus",
    "sg:orig_category":"Brood, gebak and snoepgoed",
    "sg:phone":"+32 71 81 19 40",
    "sg:postcode":"6220",
    "sg:province":"Hainaut",
    "wof:name":"J. Vanrossomme",
    "wof:placetype":"venue"
},
  "geometry": {"coordinates":[4.5490341187,50.47996521],"type":"Point"}
}