{
  "type": "Feature",
  "properties": {
    "iso:country":"BE",
    "sg:address":"Rue Des Artisants 7",
    "sg:city":"Floreffe",
    "sg:classifiers":[
        {
            "category":"Wholesale",
            "subcategory":"Machinery & Supplies",
            "type":"Manufacturing & Wholesale Goods"
        }
    ],
    "sg:phone":"+32 81 44 09 66",
    "sg:postcode":"5150",
    "sg:province":"Namur",
    "sg:tags":[
        "refrigeration",
        "-",
        "industrial",
        "commercial",
        "equipment"
    ],
    "wof:name":"Pirson-bollet Sprl",
    "wof:placetype":"venue"
},
  "geometry": {"coordinates":[4.7600998878,50.435710907],"type":"Point"}
}