{
  "type": "Feature",
  "properties": {
    "iso:country":"BE",
    "sg:address":"Grand'route 66",
    "sg:city":"Hamoir",
    "sg:orig_category":"Epiceries",
    "sg:phone":"+32 86 38 85 41",
    "sg:postcode":"4181",
    "sg:province":"Li\u00e8ge",
    "wof:name":"Nadine Petitjean",
    "wof:placetype":"venue"
},
  "geometry": {"coordinates":[5.5839800835,50.4247016907],"type":"Point"}
}