{
  "type": "Feature",
  "properties": {
    "addr:full":"Kleine Mierenstraat 7 Mechelen (heffen) Antwerpen 2801",
    "addr:housenumber":"7",
    "addr:postcode":"2801",
    "addr:street":"Kleine Mierenstraat",
    "iso:country":"BE",
    "sg:address":"Kleine Mierenstraat 7",
    "sg:city":"Mechelen (heffen)",
    "sg:classifiers":[
        {
            "category":"Real Estate",
            "subcategory":"Architect",
            "type":"Services"
        }
    ],
    "sg:phone":"+32 15 27 74 46",
    "sg:postcode":"2801",
    "sg:province":"Antwerpen",
    "wof:name":"Van Lysebeth J & Goossens T",
    "wof:placetype":"venue"
},
  "geometry": {"coordinates":[4.418610096,51.052734375],"type":"Point"}
}