{
  "type": "Feature",
  "properties": {
    "addr:full":"Avenue Des Vanneaux 12 Neupr\u00e9 (neuville-en-condroz) Li\u00e8ge 4121",
    "addr:housenumber":"12",
    "addr:postcode":"4121",
    "addr:street":"Avenue Des Vanneaux",
    "iso:country":"BE",
    "sg:address":"Avenue Des Vanneaux 12",
    "sg:city":"Neupr\u00e9 (neuville-en-condroz)",
    "sg:classifiers":[
        {
            "category":"Insurance",
            "subcategory":"Insurance Agent",
            "type":"Services"
        }
    ],
    "sg:phone":"+32 4 371 33 77",
    "sg:postcode":"4121",
    "sg:province":"Li\u00e8ge",
    "sg:tags":[
        "broker"
    ],
    "wof:name":"Lodewyckx R",
    "wof:placetype":"venue"
},
  "geometry": {"coordinates":[5.4544510841,50.544052124],"type":"Point"}
}