{
  "type": "Feature",
  "properties": {
    "addr:full":"Leemanslaan 2a Olen Antwerpen 2250",
    "addr:housenumber":"2a",
    "addr:postcode":"2250",
    "addr:street":"Leemanslaan",
    "iso:country":"BE",
    "sg:address":"Leemanslaan 2a",
    "sg:city":"Olen",
    "sg:classifiers":[
        {
            "category":"Personal",
            "subcategory":"Beauty Salon",
            "type":"Services"
        }
    ],
    "sg:phone":"+32 14 21 67 12",
    "sg:postcode":"2250",
    "sg:province":"Antwerpen",
    "sg:tags":[
        "lady",
        "-",
        "hairdressing"
    ],
    "wof:name":"Elegance Haarstudio",
    "wof:placetype":"venue"
},
  "geometry": {"coordinates":[4.9022750854,51.1744232178],"type":"Point"}
}