{
  "type": "Feature",
  "properties": {
    "addr:full":"Rue De France 66 Philippeville Namur 5600",
    "addr:housenumber":"66",
    "addr:postcode":"5600",
    "addr:street":"Rue De France",
    "iso:country":"BE",
    "sg:address":"Rue De France 66",
    "sg:city":"Philippeville",
    "sg:classifiers":[
        {
            "category":"Building & Trades",
            "subcategory":"Plumbing",
            "type":"Services"
        }
    ],
    "sg:phone":"+32 71 66 78 50",
    "sg:postcode":"5600",
    "sg:province":"Namur",
    "sg:tags":[
        "diver",
        "commerce",
        "gr",
        "pour",
        "equipement"
    ],
    "wof:name":"Comptoir Profes. Coiffeur",
    "wof:placetype":"venue"
},
  "geometry": {"coordinates":[4.5384631157,50.1961517334],"type":"Point"}
}