{
  "type": "Feature",
  "properties": {
    "addr:full":"Kochuytstraat 2 Sint-laureins Oost-Vlaanderen 9980",
    "addr:housenumber":"2",
    "addr:postcode":"9980",
    "addr:street":"Kochuytstraat",
    "iso:country":"BE",
    "sg:address":"Kochuytstraat 2",
    "sg:city":"Sint-laureins",
    "sg:orig_category":"Eleveurs and marchands de porcs",
    "sg:phone":"+32 9 377 31 30",
    "sg:postcode":"9980",
    "sg:province":"Oost-Vlaanderen",
    "wof:name":"Dirk De Geeter",
    "wof:placetype":"venue"
},
  "geometry": {"coordinates":[3.5118069649,51.218788147],"type":"Point"}
}