{
  "type": "Feature",
  "properties": {
    "addr:full":"Hulstraat 6 Avelgem West-Vlaanderen 8581",
    "addr:housenumber":"6",
    "addr:postcode":"8581",
    "addr:street":"Hulstraat",
    "iso:country":"BE",
    "sg:address":"Hulstraat 6",
    "sg:city":"Avelgem",
    "sg:orig_category":"P\u00e9pini\u00e9ristes",
    "sg:phone":"+32 56 64 85 82",
    "sg:postcode":"8581",
    "sg:province":"West-Vlaanderen",
    "wof:name":"Jean-pierre Malfait",
    "wof:placetype":"venue"
},
  "geometry": {"coordinates":[3.4665460587,50.7870521545],"type":"Point"}
}