{
  "type": "Feature",
  "properties": {
    "iso:country":"BE",
    "sg:address":"Zaffelaredorp 17",
    "sg:city":"Lochristi",
    "sg:orig_category":"Etalage- and showroomontwerpers",
    "sg:phone":"+32 9 356 85 88",
    "sg:postcode":"9080",
    "sg:province":"Oost-Vlaanderen",
    "wof:name":"Mark Verbrugge",
    "wof:placetype":"venue"
},
  "geometry": {"coordinates":[3.8633520603,51.1328659058],"type":"Point"}
}