{
  "type": "Feature",
  "properties": {
    "iso:country":"BE",
    "sg:address":"De Wynantsstraat 23",
    "sg:city":"Brussel/bruxelles",
    "sg:orig_category":"Advocaten and juridische adviseurs",
    "sg:phone":"+32 2 548 01 99",
    "sg:postcode":"1000",
    "sg:province":"Bruxelles-Capitale",
    "wof:name":"Damien Dupuis",
    "wof:placetype":"venue"
},
  "geometry": {"coordinates":[4.3507180214,50.8355369568],"type":"Point"}
}