{
  "type": "Feature",
  "properties": {
    "addr:full":"Rue G\u00c9n\u00c9ral Piron 103 Tournai Hainaut 7500",
    "addr:housenumber":"103",
    "addr:postcode":"7500",
    "addr:street":"Rue Ge\u0301Ne\u0301Ral Piron",
    "iso:country":"BE",
    "sg:address":"Rue G\u00c9n\u00c9ral Piron 103",
    "sg:city":"Tournai",
    "sg:classifiers":[
        {
            "category":"Cafe",
            "type":"Food & Drink"
        }
    ],
    "sg:phone":"+32 69 22 21 39",
    "sg:postcode":"7500",
    "sg:province":"Hainaut",
    "sg:tags":[
        "caf\u00e9s"
    ],
    "wof:name":"Caf\u00c9 Musicien",
    "wof:placetype":"venue"
},
  "geometry": {"coordinates":[3.385461092,50.5965423584],"type":"Point"}
}