{
  "type": "Feature",
  "properties": {
    "iso:country":"BE",
    "sg:address":"Sint-pietersplein 54",
    "sg:city":"Gent-centrum",
    "sg:classifiers":[
        {
            "category":"Communications",
            "subcategory":"Film & Video Production",
            "type":"Services"
        }
    ],
    "sg:phone":"+32 9 225 84 60",
    "sg:postcode":"9000",
    "sg:province":"Oost-Vlaanderen",
    "sg:tags":[
        "verhuur",
        "cassette",
        "audio",
        "platen",
        "cd's"
    ],
    "wof:name":"Roxy Center",
    "wof:placetype":"venue"
},
  "geometry": {"coordinates":[3.7252759933,51.0426368713],"type":"Point"}
}