{
  "type": "Feature",
  "properties": {
    "iso:country":"BE",
    "sg:address":"Grotesteenweg Zuid 27",
    "sg:city":"Gent (zwijnaarde)",
    "sg:classifiers":[
        {
            "category":"Manufacturing",
            "subcategory":"Building Materials",
            "type":"Manufacturing & Wholesale Goods"
        }
    ],
    "sg:phone":"+32 9 221 53 11",
    "sg:postcode":"9052",
    "sg:province":"Oost-Vlaanderen",
    "sg:tags":[
        "fixture",
        "store"
    ],
    "wof:name":"Siba Design Bvba",
    "wof:placetype":"venue"
},
  "geometry": {"coordinates":[3.7058780193,51.0591239929],"type":"Point"}
}