{
  "type": "Feature",
  "properties": {
    "addr:full":"Rolliersstraat 20 Sint-niklaas Oost-Vlaanderen 9100",
    "addr:housenumber":"20",
    "addr:postcode":"9100",
    "addr:street":"Rolliersstraat",
    "iso:country":"BE",
    "sg:address":"Rolliersstraat 20",
    "sg:city":"Sint-niklaas",
    "sg:classifiers":[
        {
            "category":"Personal",
            "subcategory":"Beauty Salon",
            "type":"Services"
        }
    ],
    "sg:phone":"+32 3 776 92 89",
    "sg:postcode":"9100",
    "sg:province":"Oost-Vlaanderen",
    "sg:tags":[
        "lady",
        "-",
        "hairdressing"
    ],
    "wof:name":"De Groot A",
    "wof:placetype":"venue"
},
  "geometry": {"coordinates":[4.1321320534,51.165512085],"type":"Point"}
}