{
  "type": "Feature",
  "properties": {
    "addr:full":"Gustaaf Schockaertstraat 68 Zottegem Oost-Vlaanderen 9620",
    "addr:housenumber":"68",
    "addr:postcode":"9620",
    "addr:street":"Gustaaf Schockaertstraat",
    "iso:country":"BE",
    "sg:address":"Gustaaf Schockaertstraat 68",
    "sg:city":"Zottegem",
    "sg:orig_category":"Boekhouders",
    "sg:phone":"+32 9 360 31 02",
    "sg:postcode":"9620",
    "sg:province":"Oost-Vlaanderen",
    "wof:name":"Guido Podevijn",
    "wof:placetype":"venue"
},
  "geometry": {"coordinates":[3.8117330074,50.8654518127],"type":"Point"}
}