{
  "type": "Feature",
  "properties": {
    "iso:country":"BE",
    "sg:address":"Begijnenstraat 43",
    "sg:city":"Sint-niklaas",
    "sg:orig_category":"Elektrische and elektronische apparatuur Gh Elektrische installaties voor woningen Metalen and ertse",
    "sg:phone":"+32 3 777 88 80",
    "sg:postcode":"9100",
    "sg:province":"Oost-Vlaanderen",
    "wof:name":"Piessens Electro Industr.",
    "wof:placetype":"venue"
},
  "geometry": {"coordinates":[4.144466877,51.176399231],"type":"Point"}
}