{
  "type": "Feature",
  "properties": {
    "iso:country":"BE",
    "sg:address":"Sint-hubertusplein 4n",
    "sg:city":"Hasselt",
    "sg:classifiers":[
        {
            "category":"Fast Food",
            "type":"Food & Drink"
        }
    ],
    "sg:phone":"+32 496 10 23 94",
    "sg:postcode":"3500",
    "sg:province":"Limburg",
    "sg:tags":[
        "fried",
        "stand",
        "potato"
    ],
    "wof:name":"Smulbrakske ('t)",
    "wof:placetype":"venue"
},
  "geometry": {"coordinates":[5.3273558617,50.9255523682],"type":"Point"}
}