{
  "type": "Feature",
  "properties": {
    "addr:full":"Tichelrijstraat 25 Sint-truiden Limburg 3800",
    "addr:housenumber":"25",
    "addr:postcode":"3800",
    "addr:street":"Tichelrijstraat",
    "iso:country":"BE",
    "sg:address":"Tichelrijstraat 25",
    "sg:city":"Sint-truiden",
    "sg:classifiers":[
        {
            "category":"Professional",
            "type":"Services"
        }
    ],
    "sg:phone":"+32 11 70 29 10",
    "sg:postcode":"3800",
    "sg:province":"Limburg",
    "sg:tags":[
        "surveyor",
        "-",
        "valuer"
    ],
    "wof:name":"Bouwexperten Moers & Vanoppen Nv",
    "wof:placetype":"venue"
},
  "geometry": {"coordinates":[5.1922521591,50.8168106079],"type":"Point"}
}