{
  "type": "Feature",
  "properties": {
    "iso:country":"BE",
    "sg:address":"Emiel Lossystraat 13",
    "sg:city":"Gent",
    "sg:orig_category":"Boekhouders",
    "sg:phone":"+32 9 228 23 51",
    "sg:postcode":"9040",
    "sg:province":"Oost-Vlaanderen",
    "wof:name":"Peter Van Laere",
    "wof:placetype":"venue"
},
  "geometry": {"coordinates":[3.7592151165,51.0512924194],"type":"Point"}
}