{
  "type": "Feature",
  "properties": {
    "addr:full":"Burchtstraat 30 Ninove Oost-Vlaanderen 9400",
    "addr:housenumber":"30",
    "addr:postcode":"9400",
    "addr:street":"Burchtstraat",
    "iso:country":"BE",
    "sg:address":"Burchtstraat 30",
    "sg:city":"Ninove",
    "sg:classifiers":[
        {
            "category":"Fast Food",
            "type":"Food & Drink"
        }
    ],
    "sg:phone":"+32 54 32 36 91",
    "sg:postcode":"9400",
    "sg:province":"Oost-Vlaanderen",
    "sg:tags":[
        "de",
        "restaurant",
        "organisation",
        "\u00c0",
        "catering",
        "emporter",
        "f\u00cates",
        "restaurants"
    ],
    "wof:name":"El Greco",
    "wof:placetype":"venue"
},
  "geometry": {"coordinates":[4.0234007835,50.8342971802],"type":"Point"}
}