{
  "type": "Feature",
  "properties": {
    "addr:full":"Rue Grande 24 Couvin (br\u00fbly) Namur 5660",
    "addr:housenumber":"24",
    "addr:postcode":"5660",
    "addr:street":"Rue Grande",
    "iso:country":"BE",
    "sg:address":"Rue Grande 24",
    "sg:city":"Couvin (br\u00fbly)",
    "sg:classifiers":[
        {
            "category":"Personal",
            "subcategory":"Beauty Salon",
            "type":"Services"
        }
    ],
    "sg:phone":"+32 60 37 71 15",
    "sg:postcode":"5660",
    "sg:province":"Namur",
    "sg:tags":[
        "lady",
        "-",
        "hairdressing"
    ],
    "wof:name":"Francine",
    "wof:placetype":"venue"
},
  "geometry": {"coordinates":[4.524928093,49.9697113037],"type":"Point"}
}