{
  "type": "Feature",
  "properties": {
    "iso:country":"BE",
    "sg:address":"Chauss\u00e9e De Ruisbroek 290",
    "sg:city":"Drogenbos",
    "sg:classifiers":[
        {
            "category":"Manufacturing",
            "subcategory":"Musical Instruments",
            "type":"Manufacturing & Wholesale Goods"
        }
    ],
    "sg:phone":"+32 2 334 22 70",
    "sg:postcode":"1620",
    "sg:province":"Vlaams-Brabant",
    "sg:tags":[
        "scientific",
        "apparatus"
    ],
    "wof:name":"B.r.s. Bvba",
    "wof:placetype":"venue"
},
  "geometry": {"coordinates":[4.3057198524,50.7974014282],"type":"Point"}
}