{
  "type": "Feature",
  "properties": {
    "addr:full":"Handelsstraat 29 Essen Antwerpen 2910",
    "addr:housenumber":"29",
    "addr:postcode":"2910",
    "addr:street":"Handelsstraat",
    "iso:country":"BE",
    "sg:address":"Handelsstraat 29",
    "sg:city":"Essen",
    "sg:classifiers":[
        {
            "category":"Home & Garden",
            "subcategory":"Carpets & Floor Coverings",
            "type":"Retail Goods"
        }
    ],
    "sg:phone":"+32 3 667 20 47",
    "sg:postcode":"2910",
    "sg:province":"Antwerpen",
    "sg:tags":[
        "layer",
        "mosaicists"
    ],
    "wof:name":"Van Hooydonck Gebr",
    "wof:placetype":"venue"
},
  "geometry": {"coordinates":[4.4504752159,51.466091156],"type":"Point"}
}