{
  "type": "Feature",
  "properties": {
    "addr:full":"Leliestraat 34 Zemst Vlaams-Brabant 1982",
    "addr:housenumber":"34",
    "addr:postcode":"1982",
    "addr:street":"Leliestraat;Vlaams-Brabant",
    "iso:country":"BE",
    "sg:address":"Leliestraat 34",
    "sg:city":"Zemst",
    "sg:orig_category":"Plomberie, chauffage and installations sanitaires",
    "sg:phone":"+32 15 61 49 86",
    "sg:postcode":"1982",
    "sg:province":"Vlaams-Brabant",
    "wof:name":"Fa. Voet",
    "wof:placetype":"venue"
},
  "geometry": {"coordinates":[4.5010271072,50.9657096863],"type":"Point"}
}