{
  "type": "Feature",
  "properties": {
    "addr:full":"Stationsstraat 91 Heist-op-den-berg Antwerpen 2220",
    "addr:housenumber":"91",
    "addr:postcode":"2220",
    "addr:street":"Stationsstraat",
    "iso:country":"BE",
    "sg:address":"Stationsstraat 91",
    "sg:city":"Heist-op-den-berg",
    "sg:orig_category":"Artsen and specialisten",
    "sg:phone":"+32 15 24 15 48",
    "sg:postcode":"2220",
    "sg:province":"Antwerpen",
    "wof:name":"Jos Mertens",
    "wof:placetype":"venue"
},
  "geometry": {"coordinates":[4.7092890739,51.0747833252],"type":"Point"}
}