{
  "type": "Feature",
  "properties": {
    "addr:full":"Kapiteintjesstraat 13 Aalst Oost-Vlaanderen 9300",
    "addr:housenumber":"13",
    "addr:postcode":"9300",
    "addr:street":"Kapiteintjesstraat",
    "iso:country":"BE",
    "sg:address":"Kapiteintjesstraat 13",
    "sg:city":"Aalst",
    "sg:orig_category":"Marca. V\u00eatements pour Dames. V\u00eatements pour Hommes. V\u00eatements pour b\u00e9b\u00e9s and enfants",
    "sg:phone":"+32 53 70 72 98",
    "sg:postcode":"9300",
    "sg:province":"Oost-Vlaanderen",
    "wof:name":"Marca Aalst",
    "wof:placetype":"venue"
},
  "geometry": {"coordinates":[4.0352320671,50.9348106384],"type":"Point"}
}