{
  "type": "Feature",
  "properties": {
    "addr:full":"Priester Daensplein 6 Aalst Oost-Vlaanderen 9300",
    "addr:housenumber":"6",
    "addr:postcode":"9300",
    "addr:street":"Priester Daensplein",
    "iso:country":"BE",
    "sg:address":"Priester Daensplein 6",
    "sg:city":"Aalst",
    "sg:orig_category":"Diverse producten Fab Herstelling aan huis van huishoudartikelen Herstelling leer and schoeisel Hers",
    "sg:phone":"+32 53 71 08 30",
    "sg:postcode":"9300",
    "sg:province":"Oost-Vlaanderen",
    "wof:name":"Jan Minute",
    "wof:placetype":"venue"
},
  "geometry": {"coordinates":[4.0404319763,50.9374084473],"type":"Point"}
}