{
  "type": "Feature",
  "properties": {
    "iso:country":"BE",
    "sg:address":"Steenwagenstraat 11",
    "sg:city":"Steenokkerzeel",
    "sg:classifiers":[
        {
            "category":"Restaurant",
            "type":"Food & Drink"
        }
    ],
    "sg:phone":"+32 2 751 95 56",
    "sg:postcode":"1820",
    "sg:province":"Vlaams-Brabant",
    "wof:name":"Restaurant Cleynhof",
    "wof:placetype":"venue"
},
  "geometry": {"coordinates":[4.4725852013,50.9144592285],"type":"Point"}
}