{
  "type": "Feature",
  "properties": {
    "iso:country":"BE",
    "sg:address":"Gentbruggestraat 3",
    "sg:city":"Gent",
    "sg:classifiers":[
        {
            "category":"Insurance",
            "subcategory":"Insurance Agent",
            "type":"Services"
        }
    ],
    "sg:phone":"+32 9 232 20 43",
    "sg:postcode":"9040",
    "sg:province":"Oost-Vlaanderen",
    "sg:tags":[
        "verzekeringsmakelaars",
        "expert"
    ],
    "wof:name":"Bureau Smet-de Grieve",
    "wof:placetype":"venue"
},
  "geometry": {"coordinates":[3.7524518967,51.0520782471],"type":"Point"}
}