{
  "type": "Feature",
  "properties": {
    "iso:country":"BE",
    "sg:address":"Warande 18",
    "sg:city":"Sint-laureins (sint-jan-in-eremo)",
    "sg:orig_category":"Non-Classified Establishments",
    "sg:phone":"+32 9 379 81 38",
    "sg:postcode":"9982",
    "sg:province":"Oost-Vlaanderen",
    "wof:name":"Engels L",
    "wof:placetype":"venue"
},
  "geometry": {"coordinates":[3.5859649181,51.2472877502],"type":"Point"}
}