{
  "type": "Feature",
  "properties": {
    "iso:country":"BE",
    "sg:address":"Rue Oscar Quertinmont 12",
    "sg:city":"La Louviere",
    "sg:orig_category":"Boucheries",
    "sg:phone":"+32 64 22 51 99",
    "sg:postcode":"7100",
    "sg:province":"Hainaut",
    "wof:name":"Boucherie Stievenart",
    "wof:placetype":"venue"
},
  "geometry": {"coordinates":[4.1850848198,50.4748649597],"type":"Point"}
}