{
  "type": "Feature",
  "properties": {
    "addr:full":"Rue Notre Dame 12 Binche Hainaut 7130",
    "addr:postcode":"12;7130",
    "addr:street":"Rue Notre Dame;Hainaut",
    "iso:country":"BE",
    "sg:address":"Rue Notre Dame 12",
    "sg:city":"Binche",
    "sg:classifiers":[
        {
            "category":"Utilities",
            "subcategory":"Telephone",
            "type":"Services"
        }
    ],
    "sg:phone":"+32 64 36 75 10",
    "sg:postcode":"7130",
    "sg:province":"Hainaut",
    "sg:tags":[
        "house",
        "phone",
        "telecommunicatieapparaten"
    ],
    "wof:name":"The Phone House",
    "wof:placetype":"venue"
},
  "geometry": {"coordinates":[4.1655230522,50.4113578796],"type":"Point"}
}