{
  "type": "Feature",
  "properties": {
    "addr:full":"F\u00e9ronstr\u00e9e 103 Li\u00e8ge 1 Li\u00e8ge 4000",
    "addr:housenumber":"103;1",
    "addr:postcode":"4000",
    "addr:street":"Fe\u0301Ronstre\u0301E",
    "iso:country":"BE",
    "sg:address":"F\u00e9ronstr\u00e9e 103",
    "sg:city":"Li\u00e8ge 1",
    "sg:classifiers":[
        {
            "category":"Shopping",
            "subcategory":"Musical Instruments",
            "type":"Retail Goods"
        }
    ],
    "sg:phone":"+32 4 343 60 14",
    "sg:postcode":"4000",
    "sg:province":"Li\u00e8ge",
    "sg:tags":[
        "-"
    ],
    "wof:name":"Colmant J-y Guitares",
    "wof:placetype":"venue"
},
  "geometry": {"coordinates":[5.5806717873,50.6469459534],"type":"Point"}
}