{
  "type": "Feature",
  "properties": {
    "iso:country":"BE",
    "sg:address":"Gansbroekstraat 48",
    "sg:city":"Puurs",
    "sg:orig_category":"Jardinage",
    "sg:phone":"+32 3 886 73 24",
    "sg:postcode":"2870",
    "sg:province":"Antwerpen",
    "wof:name":"Guy Ponet",
    "wof:placetype":"venue"
},
  "geometry": {"coordinates":[4.3377299309,51.087726593],"type":"Point"}
}