{
  "type": "Feature",
  "properties": {
    "addr:full":"Ebdries 1 Aarschot Vlaams-Brabant 3202",
    "addr:housenumber":"1",
    "addr:postcode":"3202",
    "addr:street":"Ebdries",
    "iso:country":"BE",
    "sg:address":"Ebdries 1",
    "sg:city":"Aarschot",
    "sg:orig_category":"Rev\u00eatements de sols and murs. Eclairage et \u00e9quipements du foyer",
    "sg:phone":"+32 16 50 01 32",
    "sg:postcode":"3202",
    "sg:province":"Vlaams-Brabant",
    "wof:name":"Ceramica Andalucia",
    "wof:placetype":"venue"
},
  "geometry": {"coordinates":[4.8975000381,50.9719810486],"type":"Point"}
}