{
  "type": "Feature",
  "properties": {
    "addr:full":"Ooststraat 38 Roeselare West-Vlaanderen 8800",
    "addr:housenumber":"38",
    "addr:postcode":"8800",
    "addr:street":"Ooststraat",
    "iso:country":"BE",
    "sg:address":"Ooststraat 38",
    "sg:city":"Roeselare",
    "sg:classifiers":[
        {
            "category":"Shopping",
            "subcategory":"Clothing, Apparel, & Fashions",
            "type":"Retail Goods"
        }
    ],
    "sg:phone":"+32 51 24 00 38",
    "sg:postcode":"8800",
    "sg:province":"West-Vlaanderen",
    "sg:tags":[
        "ondergoed",
        "lingerie"
    ],
    "wof:name":"Huis Sofie",
    "wof:placetype":"venue"
},
  "geometry": {"coordinates":[3.1256580353,50.9459266663],"type":"Point"}
}