{
  "type": "Feature",
  "properties": {
    "addr:full":"Kerkstraat 20 Hoogstraten Antwerpen 2328",
    "addr:housenumber":"20",
    "addr:postcode":"2328",
    "addr:street":"Kerkstraat",
    "iso:country":"BE",
    "sg:address":"Kerkstraat 20",
    "sg:city":"Hoogstraten",
    "sg:orig_category":"D\u00e9m\u00e9nagements",
    "sg:phone":"+32 3 315 78 38",
    "sg:postcode":"2328",
    "sg:province":"Antwerpen",
    "wof:name":"Verkooyen",
    "wof:placetype":"venue"
},
  "geometry": {"coordinates":[4.80230093,51.4741744995],"type":"Point"}
}