{
  "type": "Feature",
  "properties": {
    "addr:full":"Vijverstraat 2 Aalst Oost-Vlaanderen 9300",
    "addr:housenumber":"2",
    "addr:postcode":"9300",
    "addr:street":"Vijverstraat",
    "iso:country":"BE",
    "sg:address":"Vijverstraat 2",
    "sg:city":"Aalst",
    "sg:orig_category":"Meubles D\u00e9taillants, Am\u00e9nagement de B\u00e2timents et de Cuisines",
    "sg:phone":"+32 53 21 39 14",
    "sg:postcode":"9300",
    "sg:province":"Oost-Vlaanderen",
    "wof:name":"Sleepy Aalst",
    "wof:placetype":"venue"
},
  "geometry": {"coordinates":[4.0429601669,50.9359741211],"type":"Point"}
}