{
  "type": "Feature",
  "properties": {
    "iso:country":"BE",
    "sg:address":"Dorpstraat 85b",
    "sg:city":"Merchtem (brussegem)",
    "sg:classifiers":[
        {
            "category":"Banks & Credit Unions",
            "subcategory":"Investment Brokerage",
            "type":"Services"
        }
    ],
    "sg:phone":"+32 2 460 29 35",
    "sg:postcode":"1785",
    "sg:province":"Vlaams-Brabant",
    "sg:tags":[
        "printing",
        "-"
    ],
    "wof:name":"Leleu Printing Nv",
    "wof:placetype":"venue"
},
  "geometry": {"coordinates":[4.2317490578,50.9585723877],"type":"Point"}
}