{
  "type": "Feature",
  "properties": {
    "iso:country":"BE",
    "sg:address":"Place Chasseurs Ardennais 5",
    "sg:city":"Gedinne",
    "sg:orig_category":"Notaires",
    "sg:phone":"+32 61 58 80 31",
    "sg:postcode":"5575",
    "sg:province":"Namur",
    "wof:name":"Jacques Castermans",
    "wof:placetype":"venue"
},
  "geometry": {"coordinates":[4.9369850159,49.9804153442],"type":"Point"}
}