{
  "type": "Feature",
  "properties": {
    "addr:full":"Drootbeekstraat 129 Brussel/bruxelles Bruxelles-Capitale 1020",
    "addr:housenumber":"129",
    "addr:postcode":"1020",
    "addr:street":"Drootbeekstraat;/",
    "iso:country":"BE",
    "sg:address":"Drootbeekstraat 129",
    "sg:city":"Brussel/bruxelles",
    "sg:orig_category":"Schoonmaakbedrijven and ongediertebestrijding",
    "sg:phone":"+32 2 425 40 24",
    "sg:postcode":"1020",
    "sg:province":"Bruxelles-Capitale",
    "wof:name":"Mohamed Ghani",
    "wof:placetype":"venue"
},
  "geometry": {"coordinates":[4.3468809128,50.8722763062],"type":"Point"}
}