{
  "type": "Feature",
  "properties": {
    "addr:full":"Beverhoutsveldstraat 33 Beernem (oedelem) West-Vlaanderen 8730",
    "addr:housenumber":"33",
    "addr:postcode":"8730",
    "addr:street":"Beverhoutsveldstraat",
    "iso:country":"BE",
    "sg:address":"Beverhoutsveldstraat 33",
    "sg:city":"Beernem (oedelem)",
    "sg:classifiers":[
        {
            "category":"Manufacturing",
            "subcategory":"Metals",
            "type":"Manufacturing & Wholesale Goods"
        }
    ],
    "sg:phone":"+32 50 82 53 63",
    "sg:postcode":"8730",
    "sg:province":"West-Vlaanderen",
    "sg:tags":[
        "working"
    ],
    "wof:name":"Dewilde Robert",
    "wof:placetype":"venue"
},
  "geometry": {"coordinates":[3.3036060333,51.1763153076],"type":"Point"}
}