{
  "type": "Feature",
  "properties": {
    "iso:country":"BE",
    "sg:address":"Ghistelstraat 5",
    "sg:city":"Izegem",
    "sg:orig_category":"Dakwerken Installatie van houten of kunststof schrijnwerk Installatie van metalen schrijnwerk",
    "sg:phone":"+32 51 31 02 06",
    "sg:postcode":"8870",
    "sg:province":"West-Vlaanderen",
    "wof:name":"Holvoet G H V",
    "wof:placetype":"venue"
},
  "geometry": {"coordinates":[3.2380969524,50.9328689575],"type":"Point"}
}