{
  "type": "Feature",
  "properties": {
    "addr:full":"Oude Beewegstraat 12 Beveren (melsele) Oost-Vlaanderen 9120",
    "addr:housenumber":"12",
    "addr:postcode":"9120",
    "addr:street":"Oude Beewegstraat",
    "iso:country":"BE",
    "sg:address":"Oude Beewegstraat 12",
    "sg:city":"Beveren (melsele)",
    "sg:classifiers":[
        {
            "category":"Bars & Pubs",
            "type":"Food & Drink"
        }
    ],
    "sg:phone":"+32 3 775 08 05",
    "sg:postcode":"9120",
    "sg:province":"Oost-Vlaanderen",
    "wof:name":"Linde (de)",
    "wof:placetype":"venue"
},
  "geometry": {"coordinates":[4.2675151825,51.2250823975],"type":"Point"}
}