{
  "type": "Feature",
  "properties": {
    "iso:country":"BE",
    "sg:address":"Rue Bras 14ba",
    "sg:city":"Bastogne",
    "sg:classifiers":[
        {
            "category":"Fast Food",
            "type":"Food & Drink"
        }
    ],
    "sg:phone":"+32 61 21 38 63",
    "sg:postcode":"6600",
    "sg:province":"Luxembourg",
    "sg:tags":[
        "\u00c0",
        "emporter",
        "restaurants"
    ],
    "wof:name":"Friterie",
    "wof:placetype":"venue"
},
  "geometry": {"coordinates":[5.7182488441,50.0041847229],"type":"Point"}
}