{
  "type": "Feature",
  "properties": {
    "addr:full":"Adolf Baeyensstraat 11 Gent (sint-amandsberg) Oost-Vlaanderen 9040",
    "addr:housenumber":"11",
    "addr:postcode":"9040",
    "addr:street":"Baeyensstraat",
    "iso:country":"BE",
    "sg:address":"Adolf Baeyensstraat 11",
    "sg:city":"Gent (sint-amandsberg)",
    "sg:classifiers":[
        {
            "category":"Professional",
            "subcategory":"Lawyer & Legal Services",
            "type":"Services"
        }
    ],
    "sg:phone":"+32 9 238 26 07",
    "sg:postcode":"9040",
    "sg:province":"Oost-Vlaanderen",
    "wof:name":"Bonne C",
    "wof:placetype":"venue"
},
  "geometry": {"coordinates":[3.7514939308,51.0569572449],"type":"Point"}
}