{
  "type": "Feature",
  "properties": {
    "iso:country":"BE",
    "sg:address":"Rue Du Tr\u00f4ne 236",
    "sg:city":"Bruxelles (ixelles)",
    "sg:classifiers":[
        {
            "category":"Retail",
            "subcategory":"Laundry & Dry Cleaning",
            "type":"Services"
        }
    ],
    "sg:phone":"+32 2 649 40 67",
    "sg:postcode":"1050",
    "sg:province":"Bruxelles-Capitale",
    "sg:tags":[
        "self",
        "-"
    ],
    "wof:name":"Quick Wash Service",
    "wof:placetype":"venue"
},
  "geometry": {"coordinates":[4.3738279343,50.8336601257],"type":"Point"}
}