{
  "type": "Feature",
  "properties": {
    "iso:country":"BE",
    "sg:address":"Rue Du Moulin Romedenne 19",
    "sg:city":"Philippeville",
    "sg:classifiers":[
        {
            "category":"Social Services",
            "subcategory":"Job Training",
            "type":"Services"
        }
    ],
    "sg:phone":"+32 82 67 76 95",
    "sg:postcode":"5600",
    "sg:province":"Namur",
    "sg:tags":[
        "de",
        "terrain",
        "camping"
    ],
    "wof:name":"Camping Moulin Romedenne",
    "wof:placetype":"venue"
},
  "geometry": {"coordinates":[4.6967282295,50.1722412109],"type":"Point"}
}