{
  "type": "Feature",
  "properties": {
    "addr:full":"Kapelstraat 3 Puurs Antwerpen 2870",
    "addr:housenumber":"3",
    "addr:postcode":"2870",
    "addr:street":"Kapelstraat",
    "iso:country":"BE",
    "sg:address":"Kapelstraat 3",
    "sg:city":"Puurs",
    "sg:orig_category":"Pain, p\u00e2tisseries and confiseries",
    "sg:phone":"+32 3 889 83 77",
    "sg:postcode":"2870",
    "sg:province":"Antwerpen",
    "wof:name":"'t Hoeveke",
    "wof:placetype":"venue"
},
  "geometry": {"coordinates":[4.3133468628,51.0823135376],"type":"Point"}
}