{
  "type": "Feature",
  "properties": {
    "addr:full":"Rue Edouard Etienne 13 Braine-le-comte Hainaut 7090",
    "addr:housenumber":"13",
    "addr:postcode":"7090",
    "addr:street":"Rue Edouard Etienne",
    "iso:country":"BE",
    "sg:address":"Rue Edouard Etienne 13",
    "sg:city":"Braine-le-comte",
    "sg:orig_category":"Artsen and specialisten",
    "sg:phone":"+32 67 55 36 24",
    "sg:postcode":"7090",
    "sg:province":"Hainaut",
    "wof:name":"M. Kusnierek",
    "wof:placetype":"venue"
},
  "geometry": {"coordinates":[4.1377511024,50.6105422974],"type":"Point"}
}