{
  "type": "Feature",
  "properties": {
    "addr:full":"Blauwtorenplein 2 Antwerpen Antwerpen 2000",
    "addr:housenumber":"2",
    "addr:postcode":"2000",
    "addr:street":"Blauwtorenplein",
    "iso:country":"BE",
    "sg:address":"Blauwtorenplein 2",
    "sg:city":"Antwerpen",
    "sg:orig_category":"Banques and organismes de cr\u00e9dit",
    "sg:phone":"+32 3 233 78 00",
    "sg:postcode":"2000",
    "sg:province":"Antwerpen",
    "wof:name":"De Maertelaere",
    "wof:placetype":"venue"
},
  "geometry": {"coordinates":[4.4088668823,51.2129096985],"type":"Point"}
}