{
  "type": "Feature",
  "properties": {
    "iso:country":"BE",
    "sg:address":"Eikelberg 52",
    "sg:city":"Aarschot",
    "sg:classifiers":[
        {
            "category":"Professional",
            "subcategory":"Management & Consulting",
            "type":"Services"
        }
    ],
    "sg:phone":"+32 16 56 74 50",
    "sg:postcode":"3200",
    "sg:province":"Vlaams-Brabant",
    "sg:tags":[
        "consultant",
        "law"
    ],
    "wof:name":"Asselberghs R",
    "wof:placetype":"venue"
},
  "geometry": {"coordinates":[4.8044810295,50.9729652405],"type":"Point"}
}