{
  "type": "Feature",
  "properties": {
    "iso:country":"BE",
    "sg:address":"Heet 114",
    "sg:city":"Oosterzele (scheldewindeke)",
    "sg:classifiers":[
        {
            "category":"Farming",
            "subcategory":"Farm & Veterinary Services",
            "type":"Manufacturing & Wholesale Goods"
        }
    ],
    "sg:phone":"+32 9 362 53 63",
    "sg:postcode":"9860",
    "sg:province":"Oost-Vlaanderen",
    "sg:tags":[
        "agricultural",
        "contractor"
    ],
    "wof:name":"Vanderhaegen L",
    "wof:placetype":"venue"
},
  "geometry": {"coordinates":[3.7568199635,50.9358711243],"type":"Point"}
}