{
  "type": "Feature",
  "properties": {
    "addr:full":"Moerenakker 1 Destelbergen (heusden) Oost-Vlaanderen 9070",
    "addr:housenumber":"1",
    "addr:postcode":"9070",
    "addr:street":"Moerenakker",
    "iso:country":"BE",
    "sg:address":"Moerenakker 1",
    "sg:city":"Destelbergen (heusden)",
    "sg:classifiers":[
        {
            "category":"Building & Trades",
            "subcategory":"Landscaping Services",
            "type":"Services"
        }
    ],
    "sg:phone":"+32 9 230 80 46",
    "sg:postcode":"9070",
    "sg:province":"Oost-Vlaanderen",
    "sg:tags":[
        "gardening",
        "garden",
        "maintenance"
    ],
    "wof:name":"Van Renterghem O",
    "wof:placetype":"venue"
},
  "geometry": {"coordinates":[3.8119010925,51.0334625244],"type":"Point"}
}