{
  "type": "Feature",
  "properties": {
    "iso:country":"BE",
    "sg:address":"Opperstraat 143",
    "sg:city":"Liedekerke",
    "sg:orig_category":"Artsen and specialisten",
    "sg:phone":"+32 53 66 74 79",
    "sg:postcode":"1770",
    "sg:province":"Vlaams-Brabant",
    "wof:name":"Leo Luyckx",
    "wof:placetype":"venue"
},
  "geometry": {"coordinates":[4.0905752182,50.8687553406],"type":"Point"}
}