{
  "type": "Feature",
  "properties": {
    "iso:country":"BE",
    "sg:address":"Nieuwstraat 70",
    "sg:city":"Sint-genesius-rode/rhode-saint-genese",
    "sg:orig_category":"Kapsalons",
    "sg:phone":"+32 2 380 80 82",
    "sg:postcode":"1640",
    "sg:province":"Vlaams-Brabant",
    "wof:name":"Val\u00c9rie",
    "wof:placetype":"venue"
},
  "geometry": {"coordinates":[4.3585858345,50.7412376404],"type":"Point"}
}