{
  "type": "Feature",
  "properties": {
    "addr:full":"Ozo 9a Durbuy (izier) Luxembourg 6941",
    "addr:housenumber":"9a",
    "addr:postcode":"6941",
    "addr:street":"Ozo",
    "iso:country":"BE",
    "sg:address":"Ozo 9a",
    "sg:city":"Durbuy (izier)",
    "sg:classifiers":[
        {
            "category":"Building & Trades",
            "subcategory":"Landscaping Services",
            "type":"Services"
        }
    ],
    "sg:phone":"+32 86 40 05 85",
    "sg:postcode":"6941",
    "sg:province":"Luxembourg",
    "sg:tags":[
        "gardening",
        "garden",
        "maintenance"
    ],
    "wof:name":"Contor J-l",
    "wof:placetype":"venue"
},
  "geometry": {"coordinates":[5.524184227,50.3770332336],"type":"Point"}
}