{
  "type": "Feature",
  "properties": {
    "iso:country":"BE",
    "sg:address":"Waterloose Steenweg 1330",
    "sg:city":"Ukkel/uccle",
    "sg:orig_category":"Kapsalons",
    "sg:phone":"+32 2 374 21 15",
    "sg:postcode":"1180",
    "sg:province":"Bruxelles-Capitale",
    "wof:name":"Mitselos Pour Mitselos",
    "wof:placetype":"venue"
},
  "geometry": {"coordinates":[4.3750162125,50.7903938293],"type":"Point"}
}