{
  "type": "Feature",
  "properties": {
    "addr:full":"Kastanjelaan 143 Zulte Oost-Vlaanderen 9870",
    "addr:housenumber":"143",
    "addr:postcode":"9870",
    "addr:street":"Kastanjelaan",
    "iso:country":"BE",
    "sg:address":"Kastanjelaan 143",
    "sg:city":"Zulte",
    "sg:orig_category":"Entretien and r\u00e9parations de voitures",
    "sg:phone":"+32 56 60 55 07",
    "sg:postcode":"9870",
    "sg:province":"Oost-Vlaanderen",
    "wof:name":"Carrosserie Vandaele",
    "wof:placetype":"venue"
},
  "geometry": {"coordinates":[3.4499030113,50.9160499573],"type":"Point"}
}