{
  "type": "Feature",
  "properties": {
    "addr:full":"Minnewater 4 Brugge West-Vlaanderen 8000",
    "addr:housenumber":"4",
    "addr:postcode":"8000",
    "addr:street":"Minnewater",
    "iso:country":"BE",
    "sg:address":"Minnewater 4",
    "sg:city":"Brugge",
    "sg:orig_category":"RESTAURANTS: CAF\u00c9S",
    "sg:phone":"+32 50 33 42 54",
    "sg:postcode":"8000",
    "sg:province":"West-Vlaanderen",
    "wof:name":"Kasteel Minnewater",
    "wof:placetype":"venue"
},
  "geometry": {"coordinates":[3.2246239185,51.200176239],"type":"Point"}
}