{
  "type": "Feature",
  "properties": {
    "addr:full":"Montstraat 8 Vloesberg/flobecq Hainaut 7880",
    "addr:housenumber":"8",
    "addr:postcode":"7880",
    "addr:street":"Montstraat",
    "iso:country":"BE",
    "sg:address":"Montstraat 8",
    "sg:city":"Vloesberg/flobecq",
    "sg:orig_category":"Gedistilleerde dranken and aperitieven Fab Wijnen Fab",
    "sg:phone":"+32 68 44 91 00",
    "sg:postcode":"7880",
    "sg:province":"Hainaut",
    "wof:name":"Karin Descendre",
    "wof:placetype":"venue"
},
  "geometry": {"coordinates":[3.7659370899,50.7487640381],"type":"Point"}
}