{
  "type": "Feature",
  "properties": {
    "addr:full":"Rue Sainte-th\u00e9r\u00e8se 47 Erquelinnes Hainaut 6560",
    "addr:housenumber":"47",
    "addr:postcode":"6560",
    "addr:street":"Rue Sainte-The\u0301Re\u0300Se",
    "iso:country":"BE",
    "sg:address":"Rue Sainte-th\u00e9r\u00e8se 47",
    "sg:city":"Erquelinnes",
    "sg:classifiers":[
        {
            "category":"Education",
            "subcategory":"School",
            "type":"Public Place"
        }
    ],
    "sg:phone":"+32 71 55 68 28",
    "sg:postcode":"6560",
    "sg:province":"Hainaut",
    "sg:tags":[
        "primary"
    ],
    "wof:name":"Ecole Ste-th\u00e9r\u00e8se",
    "wof:placetype":"venue"
},
  "geometry": {"coordinates":[4.1136879921,50.3068847656],"type":"Point"}
}