{
  "type": "Feature",
  "properties": {
    "iso:country":"BE",
    "sg:address":"Borgersteinlei 69",
    "sg:city":"Mechelen",
    "sg:classifiers":[
        {
            "category":"Arena",
            "subcategory":"Sports Club",
            "type":"Entertainment"
        }
    ],
    "sg:phone":"+32 15 55 59 61",
    "sg:postcode":"2800",
    "sg:province":"Antwerpen",
    "sg:tags":[
        "de"
    ],
    "wof:name":"De Gympies Keerbergen",
    "wof:placetype":"venue"
},
  "geometry": {"coordinates":[4.5097551346,51.0377120972],"type":"Point"}
}