{
  "type": "Feature",
  "properties": {
    "iso:country":"BE",
    "sg:address":"Dokter Elie Lambottestr. 189",
    "sg:city":"Schaarbeek/schaerbeek",
    "sg:orig_category":"Diverse zakelijke dienstverlening",
    "sg:phone":"+32 2 245 65 12",
    "sg:postcode":"1030",
    "sg:province":"Bruxelles-Capitale",
    "wof:name":"Sport & Culture Diffusion",
    "wof:placetype":"venue"
},
  "geometry": {"coordinates":[4.3886270523,50.872253418],"type":"Point"}
}