{
  "type": "Feature",
  "properties": {
    "addr:full":"Rue Fouarge 4 Huy Li\u00e8ge 4500",
    "addr:housenumber":"4",
    "addr:postcode":"4500",
    "addr:street":"Rue Fouarge",
    "iso:country":"BE",
    "sg:address":"Rue Fouarge 4",
    "sg:city":"Huy",
    "sg:orig_category":"Maroquinerie and articles de voyage. Chaussures",
    "sg:phone":"+32 85 21 16 60",
    "sg:postcode":"4500",
    "sg:province":"Li\u00e8ge",
    "wof:name":"Ramelot-chaussures",
    "wof:placetype":"venue"
},
  "geometry": {"coordinates":[5.2417221069,50.5187835693],"type":"Point"}
}