{
  "type": "Feature",
  "properties": {
    "iso:country":"BE",
    "sg:address":"Hoeikensstraat 19",
    "sg:city":"Willebroek",
    "sg:orig_category":"Metallizing",
    "sg:phone":"+32 3 886 53 35",
    "sg:postcode":"2830",
    "sg:province":"Antwerpen",
    "wof:name":"E.c.c. 2000 Nv",
    "wof:placetype":"venue"
},
  "geometry": {"coordinates":[4.3516387939,51.076461792],"type":"Point"}
}