{
  "type": "Feature",
  "properties": {
    "iso:country":"BE",
    "sg:address":"Rue D'ambly 14",
    "sg:city":"Marche-en-famenne",
    "sg:classifiers":[
        {
            "category":"Personal",
            "subcategory":"Beauty Salon",
            "type":"Services"
        }
    ],
    "sg:phone":"+32 84 21 15 31",
    "sg:postcode":"6900",
    "sg:province":"Luxembourg",
    "sg:tags":[
        "de",
        "coiffure"
    ],
    "wof:name":"Coiffure Dominique",
    "wof:placetype":"venue"
},
  "geometry": {"coordinates":[5.3919558525,50.1643943787],"type":"Point"}
}