{
  "type": "Feature",
  "properties": {
    "iso:country":"BE",
    "sg:address":"Roeselaarsestraat 85",
    "sg:city":"Ardooie",
    "sg:orig_category":"Transports routiers de marchandises",
    "sg:phone":"+32 51 74 42 18",
    "sg:postcode":"8850",
    "sg:province":"West-Vlaanderen",
    "wof:name":"Vervoer Verdeba",
    "wof:placetype":"venue"
},
  "geometry": {"coordinates":[3.1826601028,50.9670181274],"type":"Point"}
}