{
  "type": "Feature",
  "properties": {
    "iso:country":"BE",
    "sg:address":"Hoekstraat 41",
    "sg:city":"Anzegem (vichte)",
    "sg:orig_category":"Non-Classified Establishments",
    "sg:phone":"+32 56 77 73 52",
    "sg:postcode":"8570",
    "sg:province":"West-Vlaanderen",
    "wof:name":"Maes Romain Nv",
    "wof:placetype":"venue"
},
  "geometry": {"coordinates":[3.408176899,50.8368835449],"type":"Point"}
}