{
  "type": "Feature",
  "properties": {
    "iso:country":"BE",
    "sg:address":"Brusselsesteenweg 83",
    "sg:city":"Asse",
    "sg:orig_category":"Boekhouders",
    "sg:phone":"+32 2 452 54 56",
    "sg:postcode":"1730",
    "sg:province":"Vlaams-Brabant",
    "wof:name":"Willy Van Hoefs",
    "wof:placetype":"venue"
},
  "geometry": {"coordinates":[4.2128801346,50.9034347534],"type":"Point"}
}