{
  "type": "Feature",
  "properties": {
    "iso:country":"BE",
    "sg:address":"Guffenslaan 84",
    "sg:city":"Hasselt",
    "sg:classifiers":[
        {
            "category":"Professional",
            "subcategory":"Lawyer & Legal Services",
            "type":"Services"
        }
    ],
    "sg:phone":"+32 11 23 07 03",
    "sg:postcode":"3500",
    "sg:province":"Limburg",
    "wof:name":"Dewez J",
    "wof:placetype":"venue"
},
  "geometry": {"coordinates":[5.342110157,50.9286155701],"type":"Point"}
}