{
  "type": "Feature",
  "properties": {
    "addr:full":"Sasstraat 20 Ieper West-Vlaanderen 8904",
    "addr:housenumber":"20",
    "addr:postcode":"8904",
    "addr:street":"Sasstraat",
    "iso:country":"BE",
    "sg:address":"Sasstraat 20",
    "sg:city":"Ieper",
    "sg:orig_category":"Diverse bouwafwerking and reiniging Plaatsen van vloer- and muurbekleding Pleisterwerk Schilders Ver",
    "sg:phone":"+32 57 48 62 48",
    "sg:postcode":"8904",
    "sg:province":"West-Vlaanderen",
    "wof:name":"Vandenbriele",
    "wof:placetype":"venue"
},
  "geometry": {"coordinates":[2.8533120155,50.9113731384],"type":"Point"}
}