{
  "type": "Feature",
  "properties": {
    "addr:full":"Leopoldplein 29 Box 1 Hasselt Limburg 3500",
    "addr:housenumber":"29;1",
    "addr:postcode":"3500",
    "addr:street":"Leopoldplein;Box",
    "iso:country":"BE",
    "sg:address":"Leopoldplein 29 Box 1",
    "sg:city":"Hasselt",
    "sg:classifiers":[
        {
            "category":"Banks & Credit Unions",
            "subcategory":"Financial Services",
            "type":"Services"
        }
    ],
    "sg:phone":"+32 11 22 25 55",
    "sg:postcode":"3500",
    "sg:province":"Limburg",
    "sg:tags":[
        "loan",
        "mortgage"
    ],
    "wof:name":"Houben Nv",
    "wof:placetype":"venue"
},
  "geometry": {"coordinates":[5.3348097801,50.9282112122],"type":"Point"}
}