{
  "type": "Feature",
  "properties": {
    "iso:country":"BE",
    "sg:address":"Avenue Jupiter 16",
    "sg:city":"Chastre (chastre-villeroux-blanmont)",
    "sg:classifiers":[
        {
            "category":"Communications",
            "subcategory":"Film & Video Production",
            "type":"Services"
        }
    ],
    "sg:phone":"+32 10 65 41 14",
    "sg:postcode":"1450",
    "sg:province":"Brabant Wallon",
    "sg:tags":[
        "multimedia",
        "-",
        "system"
    ],
    "wof:name":"Krenotec",
    "wof:placetype":"venue"
},
  "geometry": {"coordinates":[4.6402440071,50.6083602905],"type":"Point"}
}