{
  "type": "Feature",
  "properties": {
    "iso:country":"BE",
    "sg:address":"Chemin De Vieux-cond\u00c9 2ba",
    "sg:city":"Peruwelz",
    "sg:orig_category":"HUISBRANDOLIE",
    "sg:phone":"+32 69 77 57 88",
    "sg:postcode":"7600",
    "sg:province":"Hainaut",
    "wof:name":"Hommerin",
    "wof:placetype":"venue"
},
  "geometry": {"coordinates":[3.5916440487,50.4920539856],"type":"Point"}
}