{
  "type": "Feature",
  "properties": {
    "iso:country":"BE",
    "sg:address":"Gentsesteenweg 101",
    "sg:city":"Mechelen",
    "sg:classifiers":[
        {
            "category":"Manufacturing",
            "subcategory":"Furniture",
            "type":"Manufacturing & Wholesale Goods"
        }
    ],
    "sg:phone":"+32 15 27 28 49",
    "sg:postcode":"2800",
    "sg:province":"Antwerpen",
    "sg:tags":[
        "armchair",
        "-"
    ],
    "wof:name":"De Schoenmaeker Nv",
    "wof:placetype":"venue"
},
  "geometry": {"coordinates":[4.434800148,51.0416412354],"type":"Point"}
}