{
  "type": "Feature",
  "properties": {
    "addr:full":"Vyvestraat 24 Staden West-Vlaanderen 8840",
    "addr:housenumber":"24",
    "addr:postcode":"8840",
    "addr:street":"Vyvestraat",
    "iso:country":"BE",
    "sg:address":"Vyvestraat 24",
    "sg:city":"Staden",
    "sg:orig_category":"Producteurs de l\u00e9gumes",
    "sg:phone":"+32 51 21 19 42",
    "sg:postcode":"8840",
    "sg:province":"West-Vlaanderen",
    "wof:name":"Dirk Mylle",
    "wof:placetype":"venue"
},
  "geometry": {"coordinates":[3.0691850185,50.9388885498],"type":"Point"}
}