{
  "type": "Feature",
  "properties": {
    "iso:country":"BE",
    "sg:address":"Sint-dimpnaplein 7",
    "sg:city":"Geel",
    "sg:orig_category":"Installatie van houten of kunststof schrijnwerk",
    "sg:phone":"+32 14 59 24 08",
    "sg:postcode":"2440",
    "sg:province":"Antwerpen",
    "wof:name":"Fa. Horemans-van Hoof",
    "wof:placetype":"venue"
},
  "geometry": {"coordinates":[5.000772953,51.162689209],"type":"Point"}
}