{
  "type": "Feature",
  "properties": {
    "addr:full":"Place Joseph Thiry 8 Aywaille Li\u00e8ge 4920",
    "addr:housenumber":"8",
    "addr:postcode":"4920",
    "addr:street":"Place Joseph Thiry",
    "iso:country":"BE",
    "sg:address":"Place Joseph Thiry 8",
    "sg:city":"Aywaille",
    "sg:classifiers":[
        {
            "category":"Building & Trades",
            "subcategory":"Equipment Rental",
            "type":"Services"
        }
    ],
    "sg:phone":"+32 4 384 51 11",
    "sg:postcode":"4920",
    "sg:province":"Li\u00e8ge",
    "sg:tags":[
        "tableware",
        "-"
    ],
    "wof:name":"Artform",
    "wof:placetype":"venue"
},
  "geometry": {"coordinates":[5.6753058434,50.4738006592],"type":"Point"}
}