{
  "type": "Feature",
  "properties": {
    "iso:country":"BE",
    "sg:address":"Zandstraat 33",
    "sg:city":"Geel",
    "sg:orig_category":"D\u00e9molition d\u00b4immeubles and terrassements. Locations de machines and \u00e9quipement pour la construction",
    "sg:phone":"+32 14 58 00 48",
    "sg:postcode":"2440",
    "sg:province":"Antwerpen",
    "wof:name":"Marc Verborgt",
    "wof:placetype":"venue"
},
  "geometry": {"coordinates":[5.0180969238,51.1550445557],"type":"Point"}
}