{
  "type": "Feature",
  "properties": {
    "addr:full":"Molenstraat 4 Zonnebeke West-Vlaanderen 8980",
    "addr:housenumber":"4",
    "addr:postcode":"8980",
    "addr:street":"Molenstraat",
    "iso:country":"BE",
    "sg:address":"Molenstraat 4",
    "sg:city":"Zonnebeke",
    "sg:orig_category":"Drukkerijen and copyshops Kantoormateriaal Krantenwinkels Rookartikelen",
    "sg:phone":"+32 51 77 09 42",
    "sg:postcode":"8980",
    "sg:province":"West-Vlaanderen",
    "wof:name":"Daisy Derveaux",
    "wof:placetype":"venue"
},
  "geometry": {"coordinates":[3.0215990543,50.9011650085],"type":"Point"}
}