{
  "type": "Feature",
  "properties": {
    "addr:full":"Rue De La Colline 22 Tubize Brabant Wallon 1480",
    "addr:housenumber":"22",
    "addr:postcode":"1480",
    "addr:street":"Rue De La Colline;Wallon",
    "iso:country":"BE",
    "sg:address":"Rue De La Colline 22",
    "sg:city":"Tubize",
    "sg:classifiers":[
        {
            "category":"Home & Garden",
            "subcategory":"Home Furnishings",
            "type":"Retail Goods"
        }
    ],
    "sg:phone":"+32 2 355 29 41",
    "sg:postcode":"1480",
    "sg:province":"Brabant Wallon",
    "sg:tags":[
        "interior",
        "decoration"
    ],
    "wof:name":"Carinelli",
    "wof:placetype":"venue"
},
  "geometry": {"coordinates":[4.210916996,50.6838569641],"type":"Point"}
}