{
  "type": "Feature",
  "properties": {
    "iso:country":"BE",
    "sg:address":"Boulevard D\u00b4avroy 35",
    "sg:city":"Li\u00c8ge",
    "sg:orig_category":"Banken and kredietinstellingen",
    "sg:phone":"+32 4 230 19 63",
    "sg:postcode":"4000",
    "sg:province":"Li\u00e8ge",
    "wof:name":"Axa",
    "wof:placetype":"venue"
},
  "geometry": {"coordinates":[5.5688500404,50.6380119324],"type":"Point"}
}