{
  "type": "Feature",
  "properties": {
    "addr:full":"Edgard Tinelstraat 37 Sint-lievens-houtem Oost-Vlaanderen 9520",
    "addr:housenumber":"37",
    "addr:postcode":"9520",
    "addr:street":"Edgard Tinelstraat",
    "iso:country":"BE",
    "sg:address":"Edgard Tinelstraat 37",
    "sg:city":"Sint-lievens-houtem",
    "sg:classifiers":[
        {
            "category":"Health Services",
            "subcategory":"Health Practitioner",
            "type":"Services"
        }
    ],
    "sg:phone":"+32 53 62 29 83",
    "sg:postcode":"9520",
    "sg:province":"Oost-Vlaanderen",
    "sg:tags":[
        "physiotherapist"
    ],
    "wof:name":"Tas Ann",
    "wof:placetype":"venue"
},
  "geometry": {"coordinates":[3.8600289822,50.9203033447],"type":"Point"}
}