{
  "type": "Feature",
  "properties": {
    "addr:full":"Baronielaan 28 Meulebeke West-Vlaanderen 8760",
    "addr:housenumber":"28",
    "addr:postcode":"8760",
    "addr:street":"Baronielaan",
    "iso:country":"BE",
    "sg:address":"Baronielaan 28",
    "sg:city":"Meulebeke",
    "sg:classifiers":[
        {
            "category":"Fast Food",
            "type":"Food & Drink"
        }
    ],
    "sg:phone":"+32 51 48 76 02",
    "sg:postcode":"8760",
    "sg:province":"West-Vlaanderen",
    "sg:tags":[
        "\u00c0",
        "restaurants",
        "emporter",
        "restaurant"
    ],
    "wof:name":"'t Gisthuis",
    "wof:placetype":"venue"
},
  "geometry": {"coordinates":[3.2762799263,50.9472198486],"type":"Point"}
}