{
  "type": "Feature",
  "properties": {
    "addr:full":"Kattenbroekstraat 22ba Aalst Oost-Vlaanderen 9310",
    "addr:housenumber":"22ba",
    "addr:postcode":"9310",
    "addr:street":"Kattenbroekstraat",
    "iso:country":"BE",
    "sg:address":"Kattenbroekstraat 22ba",
    "sg:city":"Aalst",
    "sg:orig_category":"Alimentation sp\u00e9cialis\u00e9e. Parfumeries",
    "sg:phone":"+32 53 78 50 30",
    "sg:postcode":"9310",
    "sg:province":"Oost-Vlaanderen",
    "wof:name":"All Products",
    "wof:placetype":"venue"
},
  "geometry": {"coordinates":[4.0893378258,50.9553833008],"type":"Point"}
}