{
  "type": "Feature",
  "properties": {
    "addr:full":"Rue Ferdinand Nicolay 136 Herstal Li\u00e8ge 4041",
    "addr:housenumber":"136",
    "addr:postcode":"4041",
    "addr:street":"Rue Ferdinand Nicolay",
    "iso:country":"BE",
    "sg:address":"Rue Ferdinand Nicolay 136",
    "sg:city":"Herstal",
    "sg:classifiers":[
        {
            "category":"Insurance",
            "subcategory":"Life Insurance",
            "type":"Services"
        }
    ],
    "sg:phone":"+32 4 227 95 62",
    "sg:postcode":"4041",
    "sg:province":"Li\u00e8ge",
    "sg:tags":[
        "assurance"
    ],
    "wof:name":"S. Fievez",
    "wof:placetype":"venue"
},
  "geometry": {"coordinates":[5.5849199295,50.6724891663],"type":"Point"}
}