{
  "type": "Feature",
  "properties": {
    "addr:full":"Avenue De La Chevalerie 20 Brussel/bruxelles Bruxelles-Capitale 1000",
    "addr:housenumber":"20",
    "addr:postcode":"1000",
    "addr:street":"Avenue De La Chevalerie;/",
    "iso:country":"BE",
    "sg:address":"Avenue De La Chevalerie 20",
    "sg:city":"Brussel/bruxelles",
    "sg:classifiers":[
        {
            "category":"Insurance",
            "subcategory":"Life Insurance",
            "type":"Services"
        }
    ],
    "sg:phone":"+32 2 735 89 31",
    "sg:postcode":"1000",
    "sg:province":"Bruxelles-Capitale",
    "sg:tags":[
        "assurance"
    ],
    "wof:name":"Istace J. & Co",
    "wof:placetype":"venue"
},
  "geometry": {"coordinates":[4.3957052231,50.8430862427],"type":"Point"}
}