{
  "type": "Feature",
  "properties": {
    "iso:country":"BE",
    "sg:address":"Oostrozebekestraat 279",
    "sg:city":"Meulebeke",
    "sg:orig_category":"Producteurs de l\u00e9gumes",
    "sg:phone":"+32 51 48 85 63",
    "sg:postcode":"8760",
    "sg:province":"West-Vlaanderen",
    "wof:name":"Roland Kerckhof",
    "wof:placetype":"venue"
},
  "geometry": {"coordinates":[3.3140978813,50.9310264587],"type":"Point"}
}