{
  "type": "Feature",
  "properties": {
    "addr:full":"Veldenstraat 4 Putte (beerzel) Antwerpen 2580",
    "addr:housenumber":"4",
    "addr:postcode":"2580",
    "addr:street":"Veldenstraat",
    "iso:country":"BE",
    "sg:address":"Veldenstraat 4",
    "sg:city":"Putte (beerzel)",
    "sg:classifiers":[
        {
            "category":"Health Services",
            "subcategory":"Health Practitioner",
            "type":"Services"
        }
    ],
    "sg:phone":"+32 15 75 71 55",
    "sg:postcode":"2580",
    "sg:province":"Antwerpen",
    "sg:tags":[
        "physiotherapist"
    ],
    "wof:name":"Van Den Meutter Tina",
    "wof:placetype":"venue"
},
  "geometry": {"coordinates":[4.6610980034,51.0591201782],"type":"Point"}
}