{
  "type": "Feature",
  "properties": {
    "addr:full":"Schuurhovenveld 1008 St-truiden Limburg 3800",
    "addr:housenumber":"1008",
    "addr:postcode":"3800",
    "addr:street":"St-Truiden Limburg",
    "iso:country":"BE",
    "sg:address":"Schuurhovenveld 1008",
    "sg:city":"St-truiden",
    "sg:classifiers":[
        {
            "category":"Shopping",
            "subcategory":"Computers & Home Electronics",
            "type":"Retail Goods"
        }
    ],
    "sg:phone":"+32 11 68 21 62",
    "sg:postcode":"3800",
    "sg:province":"Limburg",
    "sg:tags":[
        "information",
        "peripheral",
        "-",
        "technology"
    ],
    "wof:name":"Ijzerwaren Pierard Nv",
    "wof:placetype":"venue"
},
  "geometry": {"coordinates":[5.1863641739,50.8153343201],"type":"Point"}
}