{
  "type": "Feature",
  "properties": {
    "addr:full":"Processiestraat 1 Wingene West-Vlaanderen 8750",
    "addr:housenumber":"1",
    "addr:postcode":"8750",
    "addr:street":"Processiestraat",
    "iso:country":"BE",
    "sg:address":"Processiestraat 1",
    "sg:city":"Wingene",
    "sg:orig_category":"Elektrische installaties voor woningen",
    "sg:phone":"+32 51 61 16 58",
    "sg:postcode":"8750",
    "sg:province":"West-Vlaanderen",
    "wof:name":"Jacques Schotte",
    "wof:placetype":"venue"
},
  "geometry": {"coordinates":[3.2147829533,51.0389595032],"type":"Point"}
}