{
  "type": "Feature",
  "properties": {
    "iso:country":"BE",
    "sg:address":"Cabocheriestraat 9",
    "sg:city":"Moeskroen/mouscron",
    "sg:orig_category":"Plaatsen van vloer- and muurbekleding Schilders Verlichting and huishoudartikelen",
    "sg:phone":"+32 56 48 74 94",
    "sg:postcode":"7711",
    "sg:province":"Hainaut",
    "wof:name":"Pascal Rasson",
    "wof:placetype":"venue"
},
  "geometry": {"coordinates":[3.3099730015,50.7293319702],"type":"Point"}
}