{
  "type": "Feature",
  "properties": {
    "iso:country":"BE",
    "sg:address":"Leon Spilliaertstraat 1",
    "sg:city":"Oostende",
    "sg:classifiers":[
        {
            "category":"Travel",
            "subcategory":"Hotels & Motels",
            "type":"Entertainment"
        }
    ],
    "sg:phone":"+32 59 70 08 06",
    "sg:postcode":"8400",
    "sg:province":"West-Vlaanderen",
    "sg:tags":[
        "restaurant"
    ],
    "wof:name":"Lido 2000",
    "wof:placetype":"venue"
},
  "geometry": {"coordinates":[2.9110629559,51.2290344238],"type":"Point"}
}