{
  "type": "Feature",
  "properties": {
    "addr:full":"Goudenregenstraat 28 Mechelen Antwerpen 2800",
    "addr:housenumber":"28",
    "addr:postcode":"2800",
    "addr:street":"Goudenregenstraat",
    "iso:country":"BE",
    "sg:address":"Goudenregenstraat 28",
    "sg:city":"Mechelen",
    "sg:orig_category":"M\u00e9decins and sp\u00e9cialistes",
    "sg:phone":"+32 15 41 29 48",
    "sg:postcode":"2800",
    "sg:province":"Antwerpen",
    "wof:name":"J. Simons",
    "wof:placetype":"venue"
},
  "geometry": {"coordinates":[4.4797501564,51.0054206848],"type":"Point"}
}