{
  "type": "Feature",
  "properties": {
    "addr:full":"Rue Chantrenne 43 Momignies Hainaut 6590",
    "addr:housenumber":"43",
    "addr:postcode":"6590",
    "addr:street":"Rue Chantrenne;Hainaut",
    "iso:country":"BE",
    "sg:address":"Rue Chantrenne 43",
    "sg:city":"Momignies",
    "sg:classifiers":[
        {
            "category":"Retail",
            "subcategory":"Auto Repair",
            "type":"Services"
        }
    ],
    "sg:phone":"+32 60 51 10 66",
    "sg:postcode":"6590",
    "sg:province":"Hainaut",
    "sg:tags":[
        "garage"
    ],
    "wof:name":"Daubercies M Sa",
    "wof:placetype":"venue"
},
  "geometry": {"coordinates":[4.1603899002,50.0275917053],"type":"Point"}
}