{
  "type": "Feature",
  "properties": {
    "iso:country":"BE",
    "sg:address":"Nieuwlandstraat 3",
    "sg:city":"Nazareth",
    "sg:orig_category":"Dierenartsen",
    "sg:phone":"+32 9 386 55 91",
    "sg:postcode":"9810",
    "sg:province":"Oost-Vlaanderen",
    "wof:name":"Vicky Stevens",
    "wof:placetype":"venue"
},
  "geometry": {"coordinates":[3.5593240261,50.9441108704],"type":"Point"}
}