{
  "type": "Feature",
  "properties": {
    "iso:country":"BE",
    "sg:address":"Hogeleeststraat 2",
    "sg:city":"Brussel/bruxelles",
    "sg:orig_category":"Benzinestations and brandstoffen Herstellingen and onderhoud van auto's",
    "sg:phone":"+32 2 268 08 53",
    "sg:postcode":"1120",
    "sg:province":"Bruxelles-Capitale",
    "wof:name":"Garage Pagodes",
    "wof:placetype":"venue"
},
  "geometry": {"coordinates":[4.3707070351,50.8951911926],"type":"Point"}
}