{
  "type": "Feature",
  "properties": {
    "addr:full":"S Streuvelslaan 30 Tremelo Vlaams-Brabant 3128",
    "addr:housenumber":"30",
    "addr:postcode":"3128",
    "addr:street":"S Streuvelslaan",
    "iso:country":"BE",
    "sg:address":"S Streuvelslaan 30",
    "sg:city":"Tremelo",
    "sg:orig_category":"Secr\u00e9tariats",
    "sg:phone":"+32 16 53 74 63",
    "sg:postcode":"3128",
    "sg:province":"Vlaams-Brabant",
    "wof:name":"Vanden Cruyce",
    "wof:placetype":"venue"
},
  "geometry": {"coordinates":[4.7451748848,51.0169563293],"type":"Point"}
}