{
  "type": "Feature",
  "properties": {
    "iso:country":"BE",
    "sg:address":"Kaaistraat 90",
    "sg:city":"Beringen",
    "sg:classifiers":[
        {
            "category":"Real Estate",
            "subcategory":"Developer",
            "type":"Services"
        }
    ],
    "sg:phone":"+32 11 43 22 38",
    "sg:postcode":"3580",
    "sg:province":"Limburg",
    "sg:tags":[
        "plomberie",
        "chauffage",
        "mat\u00e9riel",
        "gr",
        "pour"
    ],
    "wof:name":"Thermosystems",
    "wof:placetype":"venue"
},
  "geometry": {"coordinates":[5.2175498009,51.0459594727],"type":"Point"}
}