{
  "type": "Feature",
  "properties": {
    "iso:country":"BE",
    "sg:address":"Mispelstraat 81",
    "sg:city":"Sint-niklaas",
    "sg:orig_category":"Installation \u00e9lectrique r\u00e9sidentielle. Location d'appareils audio-visuels",
    "sg:phone":"+32 3 776 70 11",
    "sg:postcode":"9100",
    "sg:province":"Oost-Vlaanderen",
    "wof:name":"Let Schonkeren",
    "wof:placetype":"venue"
},
  "geometry": {"coordinates":[4.1195859909,51.1773757935],"type":"Point"}
}