{
  "type": "Feature",
  "properties": {
    "addr:full":"Boulevard Fosse-crahay 54 Li\u00c8ge Li\u00e8ge 4000",
    "addr:housenumber":"54",
    "addr:postcode":"4000",
    "addr:street":"Boulevard Fosse-Crahay",
    "iso:country":"BE",
    "sg:address":"Boulevard Fosse-crahay 54",
    "sg:city":"Li\u00c8ge",
    "sg:orig_category":"Fleurs and plantes",
    "sg:phone":"+32 4 226 27 10",
    "sg:postcode":"4000",
    "sg:province":"Li\u00e8ge",
    "wof:name":"Bertrand",
    "wof:placetype":"venue"
},
  "geometry": {"coordinates":[5.5706682205,50.6625976562],"type":"Point"}
}