{
  "type": "Feature",
  "properties": {
    "iso:country":"BE",
    "sg:address":"Zoning Industriel",
    "sg:city":"Bertrix",
    "sg:classifiers":[
        {
            "category":"Retail",
            "subcategory":"Auto Repair",
            "type":"Services"
        }
    ],
    "sg:phone":"+32 61 41 23 30",
    "sg:postcode":"6880",
    "sg:province":"Luxembourg",
    "sg:tags":[
        "breakdown",
        "automobile",
        "-",
        "recovery"
    ],
    "wof:name":"Arnould O",
    "wof:placetype":"venue"
},
  "geometry": {"coordinates":[5.2535948753,49.8544845581],"type":"Point"}
}