{
  "type": "Feature",
  "properties": {
    "addr:full":"Rue De L'eglise 42 Havelange Namur 5376",
    "addr:housenumber":"42",
    "addr:postcode":"5376",
    "addr:street":"Rue De L'Eglise",
    "iso:country":"BE",
    "sg:address":"Rue De L'eglise 42",
    "sg:city":"Havelange",
    "sg:orig_category":"Enseignement maternel and primaire",
    "sg:phone":"+32 83 63 31 56",
    "sg:postcode":"5376",
    "sg:province":"Namur",
    "wof:name":"Ecole Prim. Communale",
    "wof:placetype":"venue"
},
  "geometry": {"coordinates":[5.2485098839,50.3657417297],"type":"Point"}
}