{
  "type": "Feature",
  "properties": {
    "addr:full":"Rue Hector Delaiss\u00e9 15 Rumes Hainaut 7610",
    "addr:housenumber":"15",
    "addr:postcode":"7610",
    "addr:street":"Rue Hector Delaisse\u0301",
    "iso:country":"BE",
    "sg:address":"Rue Hector Delaiss\u00e9 15",
    "sg:city":"Rumes",
    "sg:classifiers":[
        {
            "category":"Building & Trades",
            "subcategory":"Pest Control",
            "type":"Services"
        }
    ],
    "sg:phone":"+32 69 64 94 91",
    "sg:postcode":"7610",
    "sg:province":"Hainaut",
    "sg:tags":[
        "painting",
        "contractor"
    ],
    "wof:name":"Henrotte Jean",
    "wof:placetype":"venue"
},
  "geometry": {"coordinates":[3.3054358959,50.5543136597],"type":"Point"}
}