{
  "type": "Feature",
  "properties": {
    "addr:full":"4 Stationsstraat Merchtem Vlaams-Brabant 1785",
    "addr:postcode":"1785",
    "addr:street":"Stationsstraat",
    "iso:country":"BE",
    "sg:address":"4 Stationsstraat",
    "sg:city":"Merchtem",
    "sg:classifiers":[
        {
            "category":"Bakery",
            "type":"Food & Drink"
        }
    ],
    "sg:phone":"+32 52 37 43 65",
    "sg:postcode":"1785",
    "sg:province":"Vlaams-Brabant",
    "sg:tags":[
        "cake",
        "product",
        "related",
        "bread"
    ],
    "wof:name":"Lucas Bvba",
    "wof:placetype":"venue"
},
  "geometry": {"coordinates":[4.2277951241,50.9583587646],"type":"Point"}
}