{
  "type": "Feature",
  "properties": {
    "addr:full":"N\u00e9blon Le Moulin 4 Ouffet Li\u00e8ge 4590",
    "addr:housenumber":"4",
    "addr:postcode":"4590",
    "addr:street":"Le Moulin",
    "iso:country":"BE",
    "sg:address":"N\u00e9blon Le Moulin 4",
    "sg:city":"Ouffet",
    "sg:orig_category":"Non-Classified Establishments",
    "sg:phone":"+32 86 36 60 53",
    "sg:postcode":"4590",
    "sg:province":"Li\u00e8ge",
    "wof:name":"Lm And Co Sprlu",
    "wof:placetype":"venue"
},
  "geometry": {"coordinates":[5.4881229401,50.4179763794],"type":"Point"}
}