{
  "type": "Feature",
  "properties": {
    "iso:country":"BE",
    "sg:address":"Martelaarslaan 264",
    "sg:city":"Gent",
    "sg:orig_category":"Artsen and specialisten",
    "sg:phone":"+32 9 234 15 74",
    "sg:postcode":"9000",
    "sg:province":"Oost-Vlaanderen",
    "wof:name":"Orthopedie Orthovano",
    "wof:placetype":"venue"
},
  "geometry": {"coordinates":[3.7111179829,51.0472373962],"type":"Point"}
}