{
  "type": "Feature",
  "properties": {
    "iso:country":"BE",
    "sg:address":"Rogery 35",
    "sg:city":"Gouvy (bovigny)",
    "sg:classifiers":[
        {
            "category":"Building & Trades",
            "subcategory":"Construction",
            "type":"Services"
        }
    ],
    "sg:phone":"+32 80 21 46 87",
    "sg:postcode":"6671",
    "sg:province":"Luxembourg",
    "sg:tags":[
        "installation",
        "-",
        "central",
        "heating"
    ],
    "wof:name":"Watteau Ch",
    "wof:placetype":"venue"
},
  "geometry": {"coordinates":[5.9487838745,50.2419319153],"type":"Point"}
}