{
  "type": "Feature",
  "properties": {
    "addr:full":"Rue Joseph Mignolet 4 Faimes Li\u00e8ge 4317",
    "addr:housenumber":"4",
    "addr:postcode":"4317",
    "addr:street":"Rue Joseph Mignolet",
    "iso:country":"BE",
    "sg:address":"Rue Joseph Mignolet 4",
    "sg:city":"Faimes",
    "sg:classifiers":[
        {
            "category":"Professional",
            "subcategory":"Computer Services",
            "type":"Services"
        }
    ],
    "sg:phone":"+32 19 32 89 65",
    "sg:postcode":"4317",
    "sg:province":"Li\u00e8ge",
    "sg:tags":[
        "informaticaconsulent",
        "fab",
        "diverse",
        "computerapparatuur",
        "informatica-activiteiten"
    ],
    "wof:name":"Conqueror Computers",
    "wof:placetype":"venue"
},
  "geometry": {"coordinates":[5.2693071365,50.6487388611],"type":"Point"}
}