{
  "type": "Feature",
  "properties": {
    "addr:full":"Kortrijksestraat 96ba Lendelede West-Vlaanderen 8860",
    "addr:housenumber":"96ba",
    "addr:postcode":"8860",
    "addr:street":"Kortrijksestraat",
    "iso:country":"BE",
    "sg:address":"Kortrijksestraat 96ba",
    "sg:city":"Lendelede",
    "sg:orig_category":"Eleveurs and marchands de porcs. Construction de maisons",
    "sg:phone":"+32 51 30 77 48",
    "sg:postcode":"8860",
    "sg:province":"West-Vlaanderen",
    "wof:name":"Bouwwerken Lammertyn",
    "wof:placetype":"venue"
},
  "geometry": {"coordinates":[3.2249031067,50.8901176453],"type":"Point"}
}