{
  "type": "Feature",
  "properties": {
    "iso:country":"BE",
    "sg:address":"Kapittelbossen 22",
    "sg:city":"Herentals",
    "sg:orig_category":"Informaticaconsulenten",
    "sg:phone":"+32 14 22 51 31",
    "sg:postcode":"2200",
    "sg:province":"Antwerpen",
    "wof:name":"V.l.e.c",
    "wof:placetype":"venue"
},
  "geometry": {"coordinates":[4.8349781036,51.1945800781],"type":"Point"}
}