{
  "type": "Feature",
  "properties": {
    "addr:full":"Brammert 24 Dilsen-stokkem Limburg 3650",
    "addr:housenumber":"24",
    "addr:postcode":"3650",
    "addr:street":"Brammert",
    "iso:country":"BE",
    "sg:address":"Brammert 24",
    "sg:city":"Dilsen-stokkem",
    "sg:orig_category":"Eleveurs de bovins",
    "sg:phone":"+32 89 75 64 50",
    "sg:postcode":"3650",
    "sg:province":"Limburg",
    "wof:name":"Joseph Sauwen",
    "wof:placetype":"venue"
},
  "geometry": {"coordinates":[5.727396965,51.0364189148],"type":"Point"}
}