{
  "type": "Feature",
  "properties": {
    "iso:country":"BE",
    "sg:address":"Beekstraat 93",
    "sg:city":"Deinze (astene)",
    "sg:classifiers":[
        {
            "category":"Personal",
            "subcategory":"Nail Salon",
            "type":"Services"
        }
    ],
    "sg:phone":"+32 9 386 50 68",
    "sg:postcode":"9800",
    "sg:province":"Oost-Vlaanderen",
    "sg:tags":[
        "pedicure"
    ],
    "wof:name":"Oosterlynck-roussel L",
    "wof:placetype":"venue"
},
  "geometry": {"coordinates":[3.5879979134,50.9852371216],"type":"Point"}
}