{
  "type": "Feature",
  "properties": {
    "iso:country":"BE",
    "sg:address":"Rue Louis Niemegeers 29",
    "sg:city":"Kraainem",
    "sg:classifiers":[
        {
            "category":"Building & Trades",
            "subcategory":"Cleaning & Sanitation",
            "type":"Services"
        }
    ],
    "sg:phone":"+32 2 720 79 46",
    "sg:postcode":"1950",
    "sg:province":"Vlaams-Brabant",
    "wof:name":"Van Dieren Services",
    "wof:placetype":"venue"
},
  "geometry": {"coordinates":[4.4558000565,50.8618278503],"type":"Point"}
}