{
  "type": "Feature",
  "properties": {
    "addr:full":"Rue Marie-christine 60 Brussel/bruxelles Bruxelles-Capitale 1020",
    "addr:housenumber":"60",
    "addr:postcode":"1020",
    "addr:street":"Rue Marie-Christine;/",
    "iso:country":"BE",
    "sg:address":"Rue Marie-christine 60",
    "sg:city":"Brussel/bruxelles",
    "sg:orig_category":"Epiceries",
    "sg:phone":"+32 2 428 76 00",
    "sg:postcode":"1020",
    "sg:province":"Bruxelles-Capitale",
    "wof:name":"Bousiff",
    "wof:placetype":"venue"
},
  "geometry": {"coordinates":[4.3564100266,50.8742866516],"type":"Point"}
}