{
  "type": "Feature",
  "properties": {
    "addr:full":"Rue De Battice 78b2 Verviers Li\u00e8ge 4800",
    "addr:housenumber":"78b2",
    "addr:postcode":"4800",
    "addr:street":"Rue De Battice",
    "iso:country":"BE",
    "sg:address":"Rue De Battice 78b2",
    "sg:city":"Verviers",
    "sg:orig_category":"Slagers",
    "sg:phone":"+32 87 35 27 24",
    "sg:postcode":"4800",
    "sg:province":"Li\u00e8ge",
    "wof:name":"Renmans",
    "wof:placetype":"venue"
},
  "geometry": {"coordinates":[5.8594508171,50.5917663574],"type":"Point"}
}