{
  "type": "Feature",
  "properties": {
    "iso:country":"BE",
    "sg:address":"Keukelstraat 40",
    "sg:city":"Wingene",
    "sg:orig_category":"Pain, p\u00e2tisseries and confiseries",
    "sg:phone":"+32 51 65 52 85",
    "sg:postcode":"8750",
    "sg:province":"West-Vlaanderen",
    "wof:name":"Bart Claus",
    "wof:placetype":"venue"
},
  "geometry": {"coordinates":[3.3076500893,51.0634498596],"type":"Point"}
}