{
  "type": "Feature",
  "properties": {
    "iso:country":"BE",
    "sg:address":"33",
    "sg:city":"Rue Dassenois 6600 Bastogne",
    "sg:classifiers":[
        {
            "category":"Food Court",
            "type":"Food & Drink"
        }
    ],
    "sg:phone":"+32 61 21 28 45",
    "sg:postcode":"33",
    "sg:tags":[
        "product",
        "related"
    ],
    "wof:name":"Ardennes Boissons",
    "wof:placetype":"venue"
},
  "geometry": {"coordinates":[5.7148199081,50.0007820129],"type":"Point"}
}