{
  "type": "Feature",
  "properties": {
    "iso:country":"BE",
    "sg:address":"Rue De La Ri\u00e8ze 19",
    "sg:city":"Couvin (cul-des-sarts)",
    "sg:classifiers":[
        {
            "category":"Professional",
            "subcategory":"Engineering",
            "type":"Services"
        }
    ],
    "sg:phone":"+32 60 37 83 73",
    "sg:postcode":"5660",
    "sg:province":"Namur",
    "sg:tags":[
        "-"
    ],
    "wof:name":"H.q.e.",
    "wof:placetype":"venue"
},
  "geometry": {"coordinates":[4.4592900276,49.963470459],"type":"Point"}
}