{
  "type": "Feature",
  "properties": {
    "iso:country":"BE",
    "sg:address":"Rodenburgstraat 56",
    "sg:city":"Kortrijk (marke)",
    "sg:classifiers":[
        {
            "category":"Retail",
            "subcategory":"Event Space",
            "type":"Services"
        }
    ],
    "sg:phone":"+32 477 92 45 06",
    "sg:postcode":"8510",
    "sg:province":"West-Vlaanderen",
    "sg:tags":[
        "organisation"
    ],
    "wof:name":"Europconcept Bvba",
    "wof:placetype":"venue"
},
  "geometry": {"coordinates":[3.2467670441,50.8030853271],"type":"Point"}
}