{
  "type": "Feature",
  "properties": {
    "iso:country":"BE",
    "sg:address":"Dorp 30",
    "sg:city":"Rijkevorsel",
    "sg:classifiers":[
        {
            "category":"Banks & Credit Unions",
            "subcategory":"Bank",
            "type":"Services"
        }
    ],
    "sg:phone":"+32 3 314 40 40",
    "sg:postcode":"2310",
    "sg:province":"Antwerpen",
    "sg:tags":[
        "savings-banks"
    ],
    "wof:name":"Vanopstal J",
    "wof:placetype":"venue"
},
  "geometry": {"coordinates":[4.7595419884,51.3500099182],"type":"Point"}
}