{
  "type": "Feature",
  "properties": {
    "iso:country":"BE",
    "sg:address":"Rue Des Religieuses 22",
    "sg:city":"Philippeville",
    "sg:classifiers":[
        {
            "category":"Insurance",
            "subcategory":"Insurance Agent",
            "type":"Services"
        }
    ],
    "sg:phone":"+32 71 66 83 21",
    "sg:postcode":"5600",
    "sg:province":"Namur",
    "sg:tags":[
        "broker"
    ],
    "wof:name":"Ecassurances-emplaincourt",
    "wof:placetype":"venue"
},
  "geometry": {"coordinates":[4.5480389595,50.1977462769],"type":"Point"}
}