{
  "type": "Feature",
  "properties": {
    "addr:full":"Rue Des Alli\u00c9s 72 Frameries Hainaut 7080",
    "addr:housenumber":"72",
    "addr:postcode":"7080",
    "addr:street":"Rue Des Allie\u0301S",
    "iso:country":"BE",
    "sg:address":"Rue Des Alli\u00c9s 72",
    "sg:city":"Frameries",
    "sg:orig_category":"Parfumeries",
    "sg:phone":"+32 65 66 14 14",
    "sg:postcode":"7080",
    "sg:province":"Hainaut",
    "wof:name":"Ici Paris Xl",
    "wof:placetype":"venue"
},
  "geometry": {"coordinates":[3.8941040039,50.4089508057],"type":"Point"}
}