{
  "type": "Feature",
  "properties": {
    "iso:country":"BE",
    "sg:address":"Rue Du Couvent 26",
    "sg:city":"Transinne",
    "sg:orig_category":"Salles de conf\u00e9rences and de r\u00e9ceptions. Restaurants",
    "sg:phone":"+32 61 65 64 92",
    "sg:postcode":"6890",
    "sg:province":"Luxembourg",
    "wof:name":"Chez Melusine",
    "wof:placetype":"venue"
},
  "geometry": {"coordinates":[5.1990289688,49.9991874695],"type":"Point"}
}