{
  "type": "Feature",
  "properties": {
    "iso:country":"BE",
    "sg:address":"Rue Saint-gilles 78",
    "sg:city":"Li\u00c8ge",
    "sg:orig_category":"Imprimeries and copyshops",
    "sg:phone":"+32 4 222 05 53",
    "sg:postcode":"4000",
    "sg:province":"Li\u00e8ge",
    "wof:name":"Intercopy",
    "wof:placetype":"venue"
},
  "geometry": {"coordinates":[5.5634598732,50.6382026672],"type":"Point"}
}