{
  "type": "Feature",
  "properties": {
    "addr:full":"Dekkenstraat 47 Sint-truiden Limburg 3800",
    "addr:housenumber":"47",
    "addr:postcode":"3800",
    "addr:street":"Dekkenstraat",
    "iso:country":"BE",
    "sg:address":"Dekkenstraat 47",
    "sg:city":"Sint-truiden",
    "sg:orig_category":"Schoonheidssalons",
    "sg:phone":"+32 11 67 44 25",
    "sg:postcode":"3800",
    "sg:province":"Limburg",
    "wof:name":"Katrien Sterkendries",
    "wof:placetype":"venue"
},
  "geometry": {"coordinates":[5.2580618858,50.8345451355],"type":"Point"}
}