{
  "type": "Feature",
  "properties": {
    "addr:full":"Virginiastraat 255 Gent Oost-Vlaanderen 9000",
    "addr:housenumber":"255",
    "addr:postcode":"9000",
    "addr:street":"Virginiastraat;Oost-Vlaanderen",
    "iso:country":"BE",
    "sg:address":"Virginiastraat 255",
    "sg:city":"Gent",
    "sg:classifiers":[
        {
            "category":"Social Services",
            "type":"Services"
        }
    ],
    "sg:phone":"+32 9 226 11 21",
    "sg:postcode":"9000",
    "sg:province":"Oost-Vlaanderen",
    "wof:name":"Beschermcomite: Dag Voor Alle Weduwen, Weduwnaars En Wezen",
    "wof:placetype":"venue"
},
  "geometry": {"coordinates":[3.6956980228,51.068195343],"type":"Point"}
}