{
  "type": "Feature",
  "properties": {
    "addr:full":"Nicolaylaan 53 Leopoldsburg Limburg 3970",
    "addr:housenumber":"53",
    "addr:postcode":"3970",
    "addr:street":"Nicolaylaan",
    "iso:country":"BE",
    "sg:address":"Nicolaylaan 53",
    "sg:city":"Leopoldsburg",
    "sg:classifiers":[
        {
            "category":"Cafe",
            "type":"Food & Drink"
        }
    ],
    "sg:phone":"+32 11 39 21 27",
    "sg:postcode":"3970",
    "sg:province":"Limburg",
    "sg:tags":[
        "caf\u00e9s"
    ],
    "wof:name":"Giovanotti's",
    "wof:placetype":"venue"
},
  "geometry": {"coordinates":[5.2586550713,51.1170730591],"type":"Point"}
}