{
  "type": "Feature",
  "properties": {
    "addr:full":"Gentse Steenweg 132 Damme West-Vlaanderen 8340",
    "addr:housenumber":"132",
    "addr:postcode":"8340",
    "addr:street":"Gentse Steenweg",
    "iso:country":"BE",
    "sg:address":"Gentse Steenweg 132",
    "sg:city":"Damme",
    "sg:orig_category":"Ziekenhuizen and zorginstellingen",
    "sg:phone":"+32 50 72 81 11",
    "sg:postcode":"8340",
    "sg:province":"West-Vlaanderen",
    "wof:name":"Elisabethziekenhuis",
    "wof:placetype":"venue"
},
  "geometry": {"coordinates":[3.3796420097,51.2051887512],"type":"Point"}
}