{
  "type": "Feature",
  "properties": {
    "iso:country":"BE",
    "sg:address":"Wijkstraat 22",
    "sg:city":"Diepenbeek",
    "sg:orig_category":"Begrafeniswezen Drukkerijen and copyshops",
    "sg:phone":"+32 11 32 31 56",
    "sg:postcode":"3590",
    "sg:province":"Limburg",
    "wof:name":"Begrafenissen Lambrechts",
    "wof:placetype":"venue"
},
  "geometry": {"coordinates":[5.4269881248,50.9066734314],"type":"Point"}
}