{
  "type": "Feature",
  "properties": {
    "addr:full":"Hasseltweg 400 Genk Limburg 3600",
    "addr:housenumber":"400",
    "addr:postcode":"3600",
    "addr:street":"Hasseltweg",
    "iso:country":"BE",
    "sg:address":"Hasseltweg 400",
    "sg:city":"Genk",
    "sg:orig_category":"Meubles D\u00e9taillants, Am\u00e9nagement de B\u00e2timents et de Cuisines. Textiles. Eclairage et \u00e9quipements du ",
    "sg:phone":"+32 11 21 59 99",
    "sg:postcode":"3600",
    "sg:province":"Limburg",
    "wof:name":"Inter Seer",
    "wof:placetype":"venue"
},
  "geometry": {"coordinates":[5.4362030029,50.9578742981],"type":"Point"}
}