{
  "type": "Feature",
  "properties": {
    "addr:full":"Laarstraat 16bc Antwerpen Antwerpen 2610",
    "addr:housenumber":"16bc",
    "addr:postcode":"2610",
    "addr:street":"Laarstraat",
    "iso:country":"BE",
    "sg:address":"Laarstraat 16bc",
    "sg:city":"Antwerpen",
    "sg:orig_category":"Avocats and conseillers juridiques",
    "sg:phone":"+32 3 825 55 00",
    "sg:postcode":"2610",
    "sg:province":"Antwerpen",
    "wof:name":"Katrien Calcoen",
    "wof:placetype":"venue"
},
  "geometry": {"coordinates":[4.3946051598,51.1691131592],"type":"Point"}
}