{
  "type": "Feature",
  "properties": {
    "addr:full":"Place Larsimont 0 Courcelles Hainaut 6183",
    "addr:housenumber":"0",
    "addr:postcode":"6183",
    "addr:street":"Place Larsimont",
    "iso:country":"BE",
    "sg:address":"Place Larsimont 0",
    "sg:city":"Courcelles",
    "sg:orig_category":"Enseignement maternel and primaire",
    "sg:phone":"+32 71 46 99 38",
    "sg:postcode":"6183",
    "sg:province":"Hainaut",
    "wof:name":"E.p.e.s.c.",
    "wof:placetype":"venue"
},
  "geometry": {"coordinates":[4.3319177628,50.4664459229],"type":"Point"}
}