{
  "type": "Feature",
  "properties": {
    "addr:full":"Slagvelden 14 Heist-op-den-berg Antwerpen 2220",
    "addr:housenumber":"14",
    "addr:postcode":"2220",
    "addr:street":"Slagvelden",
    "iso:country":"BE",
    "sg:address":"Slagvelden 14",
    "sg:city":"Heist-op-den-berg",
    "sg:classifiers":[
        {
            "category":"Health Services",
            "subcategory":"Nursing And Care Facility",
            "type":"Services"
        }
    ],
    "sg:phone":"+32 15 25 03 58",
    "sg:postcode":"2220",
    "sg:province":"Antwerpen",
    "sg:tags":[
        "home"
    ],
    "wof:name":"Knops Kurt",
    "wof:placetype":"venue"
},
  "geometry": {"coordinates":[4.7325248718,51.0803909302],"type":"Point"}
}