{
  "type": "Feature",
  "properties": {
    "addr:full":"Rozenkranslaan 4 Scherpenheuvel-zichem Vlaams-Brabant 3270",
    "addr:housenumber":"4",
    "addr:postcode":"3270",
    "addr:street":"Rozenkranslaan",
    "iso:country":"BE",
    "sg:address":"Rozenkranslaan 4",
    "sg:city":"Scherpenheuvel-zichem",
    "sg:classifiers":[
        {
            "category":"Cafe",
            "type":"Food & Drink"
        }
    ],
    "sg:phone":"+32 13 77 81 03",
    "sg:postcode":"3270",
    "sg:province":"Vlaams-Brabant",
    "sg:tags":[
        "caf\u00e9s"
    ],
    "wof:name":"Duivenlokaal",
    "wof:placetype":"venue"
},
  "geometry": {"coordinates":[4.9782681465,50.984588623],"type":"Point"}
}