{
  "type": "Feature",
  "properties": {
    "addr:full":"Schoonboekestraat Ronse Oost-Vlaanderen 9600",
    "addr:postcode":"9600",
    "addr:street":"Schoonboekestraat",
    "iso:country":"BE",
    "sg:address":"Schoonboekestraat",
    "sg:city":"Ronse",
    "sg:orig_category":"Non-Classified Establishments",
    "sg:phone":"+32 55 21 28 76",
    "sg:postcode":"9600",
    "sg:province":"Oost-Vlaanderen",
    "wof:name":"Lekkerland-ronse",
    "wof:placetype":"venue"
},
  "geometry": {"coordinates":[3.657378912,50.753452301],"type":"Point"}
}