{
  "type": "Feature",
  "properties": {
    "iso:country":"BE",
    "sg:address":"Koningin Fabiolapark 21",
    "sg:city":"Merelbeke",
    "sg:classifiers":[
        {
            "category":"Utilities",
            "subcategory":"Telephone",
            "type":"Services"
        }
    ],
    "sg:phone":"+32 9 232 59 86",
    "sg:postcode":"9820",
    "sg:province":"Oost-Vlaanderen",
    "sg:tags":[
        "-",
        "internet"
    ],
    "wof:name":"Tall Solutions",
    "wof:placetype":"venue"
},
  "geometry": {"coordinates":[3.7606298923,51.0082473755],"type":"Point"}
}