{
  "type": "Feature",
  "properties": {
    "addr:full":"Rue Fran\u00c7ois-boudart 14 Arlon Luxembourg 6700",
    "addr:housenumber":"14",
    "addr:postcode":"6700",
    "addr:street":"Rue Franc\u0327Ois-Boudart",
    "iso:country":"BE",
    "sg:address":"Rue Fran\u00c7ois-boudart 14",
    "sg:city":"Arlon",
    "sg:orig_category":"Experts-comptables",
    "sg:phone":"+32 63 22 30 83",
    "sg:postcode":"6700",
    "sg:province":"Luxembourg",
    "wof:name":"Marie-denise Willemet",
    "wof:placetype":"venue"
},
  "geometry": {"coordinates":[5.8090200424,49.6876983643],"type":"Point"}
}