{
  "type": "Feature",
  "properties": {
    "addr:full":"Schendelbeekhofstraat 27 Aalst Oost-Vlaanderen 9300",
    "addr:housenumber":"27",
    "addr:postcode":"9300",
    "addr:street":"Schendelbeekhofstraat",
    "iso:country":"BE",
    "sg:address":"Schendelbeekhofstraat 27",
    "sg:city":"Aalst",
    "sg:orig_category":"Loodgieterij, verwarming and sanitaire installaties",
    "sg:phone":"+32 53 78 20 75",
    "sg:postcode":"9300",
    "sg:province":"Oost-Vlaanderen",
    "wof:name":"Theofiel Verhulst",
    "wof:placetype":"venue"
},
  "geometry": {"coordinates":[4.0579509735,50.9421806335],"type":"Point"}
}