{
  "type": "Feature",
  "properties": {
    "iso:country":"BE",
    "sg:address":"Diepestraat 123",
    "sg:city":"Antwerpen",
    "sg:orig_category":"Pain, p\u00e2tisseries and confiseries",
    "sg:phone":"+32 3 235 62 14",
    "sg:postcode":"2060",
    "sg:province":"Antwerpen",
    "wof:name":"Panaderia San Juan",
    "wof:placetype":"venue"
},
  "geometry": {"coordinates":[4.4260530472,51.2225761414],"type":"Point"}
}