{
  "type": "Feature",
  "properties": {
    "iso:country":"BE",
    "sg:address":"Rue As Pois 7",
    "sg:city":"Tournai",
    "sg:classifiers":[
        {
            "category":"Community Center",
            "subcategory":"Youth",
            "type":"Public Place"
        }
    ],
    "sg:phone":"+32 69 22 02 76",
    "sg:postcode":"7500",
    "sg:province":"Hainaut",
    "sg:tags":[
        "club"
    ],
    "wof:name":"Masure 14 Asbl",
    "wof:placetype":"venue"
},
  "geometry": {"coordinates":[3.3810949326,50.6061820984],"type":"Point"}
}