{
  "type": "Feature",
  "properties": {
    "addr:full":"Millenstraat 31 Bree Limburg 3960",
    "addr:housenumber":"31",
    "addr:postcode":"3960",
    "addr:street":"Millenstraat",
    "iso:country":"BE",
    "sg:address":"Millenstraat 31",
    "sg:city":"Bree",
    "sg:classifiers":[
        {
            "category":"Insurance",
            "subcategory":"Insurance Agent",
            "type":"Services"
        }
    ],
    "sg:phone":"+32 89 46 57 62",
    "sg:postcode":"3960",
    "sg:province":"Limburg",
    "sg:tags":[
        "verzekeringsmakelaars",
        "expert"
    ],
    "wof:name":"Aegten",
    "wof:placetype":"venue"
},
  "geometry": {"coordinates":[5.6066288948,51.1403160095],"type":"Point"}
}