{
  "type": "Feature",
  "properties": {
    "iso:country":"BE",
    "sg:address":"Rue De L'espinette 36",
    "sg:city":"Ecaussinnes",
    "sg:orig_category":"Rundveehouders",
    "sg:phone":"+32 67 44 46 45",
    "sg:postcode":"7191",
    "sg:province":"Hainaut",
    "wof:name":"Armand Dechief",
    "wof:placetype":"venue"
},
  "geometry": {"coordinates":[4.1872758865,50.5724525452],"type":"Point"}
}