{
  "type": "Feature",
  "properties": {
    "iso:country":"BE",
    "sg:address":"Marktstraat 60",
    "sg:city":"Harelbeke",
    "sg:orig_category":"Banques and organismes de cr\u00e9dit",
    "sg:phone":"+32 56 71 05 07",
    "sg:postcode":"8530",
    "sg:province":"West-Vlaanderen",
    "wof:name":"Fortis",
    "wof:placetype":"venue"
},
  "geometry": {"coordinates":[3.309333086,50.8558998108],"type":"Point"}
}