{
  "type": "Feature",
  "properties": {
    "iso:country":"BE",
    "sg:address":"Pannestraat 43ba",
    "sg:city":"Veurne",
    "sg:orig_category":"Instellingen voor probleemkinderen Kindertehuizen",
    "sg:phone":"+32 58 31 18 89",
    "sg:postcode":"8630",
    "sg:province":"West-Vlaanderen",
    "wof:name":"Home Zonnewende",
    "wof:placetype":"venue"
},
  "geometry": {"coordinates":[2.6579210758,51.0750846863],"type":"Point"}
}