{
  "type": "Feature",
  "properties": {
    "iso:country":"BE",
    "sg:address":"Rue De Wixhou 27",
    "sg:city":"Vis\u00e9 (argenteau)",
    "sg:classifiers":[
        {
            "category":"Building & Trades",
            "subcategory":"Plumbing",
            "type":"Services"
        }
    ],
    "sg:phone":"+32 4 379 13 55",
    "sg:postcode":"4601",
    "sg:province":"Li\u00e8ge",
    "sg:tags":[
        "repair",
        "mainten",
        "-",
        "central",
        "heating"
    ],
    "wof:name":"Bebelman B",
    "wof:placetype":"venue"
},
  "geometry": {"coordinates":[5.6874017715,50.6957092285],"type":"Point"}
}