{
  "type": "Feature",
  "properties": {
    "addr:full":"Boomse Steenweg 1 Schelle Antwerpen 2627",
    "addr:housenumber":"1",
    "addr:postcode":"2627",
    "addr:street":"Steenweg",
    "iso:country":"BE",
    "sg:address":"Boomse Steenweg 1",
    "sg:city":"Schelle",
    "sg:classifiers":[
        {
            "category":"Travel",
            "subcategory":"Travel Agent",
            "type":"Entertainment"
        }
    ],
    "sg:phone":"+32 3 888 02 87",
    "sg:postcode":"2627",
    "sg:province":"Antwerpen",
    "sg:tags":[
        "agency"
    ],
    "wof:name":"Alpina Cars Bvba",
    "wof:placetype":"venue"
},
  "geometry": {"coordinates":[4.3737530708,51.1201057434],"type":"Point"}
}