{
  "type": "Feature",
  "properties": {
    "addr:full":"Rue Du Midi 47 Renaix Oost-Vlaanderen 9600",
    "addr:housenumber":"47",
    "addr:postcode":"9600",
    "addr:street":"Rue Du Midi",
    "iso:country":"BE",
    "sg:address":"Rue Du Midi 47",
    "sg:city":"Renaix",
    "sg:classifiers":[
        {
            "category":"Professional",
            "subcategory":"Art Services",
            "type":"Services"
        }
    ],
    "sg:phone":"+32 55 20 60 72",
    "sg:postcode":"9600",
    "sg:province":"Oost-Vlaanderen",
    "sg:tags":[
        "picture",
        "framer"
    ],
    "wof:name":"Fine Arts",
    "wof:placetype":"venue"
},
  "geometry": {"coordinates":[3.6041519642,50.7447967529],"type":"Point"}
}