{
  "type": "Feature",
  "properties": {
    "iso:country":"BE",
    "sg:address":"Rue Joseph Jeanfils",
    "sg:city":"Soumagne",
    "sg:classifiers":[
        {
            "category":"Retail",
            "subcategory":"Event Space",
            "type":"Services"
        }
    ],
    "sg:phone":"+32 4 377 57 86",
    "sg:postcode":"4630",
    "sg:province":"Li\u00e8ge",
    "sg:tags":[
        "rental",
        "-",
        "hall"
    ],
    "wof:name":"Local 80 Fecher",
    "wof:placetype":"venue"
},
  "geometry": {"coordinates":[5.7455849648,50.6294059753],"type":"Point"}
}