{
  "type": "Feature",
  "properties": {
    "addr:full":"Jachthoorn 12 Lubbeek (linden) Vlaams-Brabant 3210",
    "addr:housenumber":"12",
    "addr:postcode":"3210",
    "addr:street":"Jachthoorn",
    "iso:country":"BE",
    "sg:address":"Jachthoorn 12",
    "sg:city":"Lubbeek (linden)",
    "sg:classifiers":[
        {
            "category":"Retail",
            "subcategory":"Event Space",
            "type":"Services"
        }
    ],
    "sg:phone":"+32 16 62 04 02",
    "sg:postcode":"3210",
    "sg:province":"Vlaams-Brabant",
    "sg:tags":[
        "product",
        "snack",
        "speciality",
        "potato",
        "stand",
        "fried"
    ],
    "wof:name":"Delifood Trading & Consulting",
    "wof:placetype":"venue"
},
  "geometry": {"coordinates":[4.7786641121,50.9027862549],"type":"Point"}
}