{
  "type": "Feature",
  "properties": {
    "addr:full":"Prinsenstraat 13 Grimbergen Vlaams-Brabant 1850",
    "addr:housenumber":"13",
    "addr:postcode":"1850",
    "addr:street":"Prinsenstraat",
    "iso:country":"BE",
    "sg:address":"Prinsenstraat 13",
    "sg:city":"Grimbergen",
    "sg:classifiers":[
        {
            "category":"Health Services",
            "subcategory":"Doctor",
            "type":"Services"
        }
    ],
    "sg:phone":"+32 2 270 85 00",
    "sg:postcode":"1850",
    "sg:province":"Vlaams-Brabant",
    "sg:tags":[
        "medicinephysicians",
        "surgeon"
    ],
    "wof:name":"Duron C",
    "wof:placetype":"venue"
},
  "geometry": {"coordinates":[4.3722500801,50.9315986633],"type":"Point"}
}