{
  "type": "Feature",
  "properties": {
    "iso:country":"BE",
    "sg:address":"Sint-amandstraat 18",
    "sg:city":"Gent",
    "sg:classifiers":[
        {
            "category":"Professional",
            "subcategory":"Art Services",
            "type":"Services"
        }
    ],
    "sg:phone":"+32 9 265 99 00",
    "sg:postcode":"9000",
    "sg:province":"Oost-Vlaanderen",
    "sg:tags":[
        "catalogue"
    ],
    "wof:name":"Impf B.v.b.a.",
    "wof:placetype":"venue"
},
  "geometry": {"coordinates":[3.7243878841,51.0436325073],"type":"Point"}
}