{
  "type": "Feature",
  "properties": {
    "addr:full":"Augustinerinnenstrasse 6 Sankt Vith/saint-vith Li\u00e8ge 4780",
    "addr:housenumber":"6",
    "addr:postcode":"4780",
    "addr:street":"Augustinerinnenstrasse",
    "iso:country":"BE",
    "sg:address":"Augustinerinnenstrasse 6",
    "sg:city":"Sankt Vith/saint-vith",
    "sg:orig_category":"Kampeerterreinen",
    "sg:phone":"+32 80 22 71 23",
    "sg:postcode":"4780",
    "sg:province":"Li\u00e8ge",
    "wof:name":"Almabel",
    "wof:placetype":"venue"
},
  "geometry": {"coordinates":[6.0429549217,50.3349761963],"type":"Point"}
}