{
  "type": "Feature",
  "properties": {
    "addr:full":"Avenue Paul Pastur 117 Charleroi (marcinelle) Hainaut 6001",
    "addr:housenumber":"117",
    "addr:postcode":"6001",
    "addr:street":"Avenue Paul Pastur",
    "iso:country":"BE",
    "sg:address":"Avenue Paul Pastur 117",
    "sg:city":"Charleroi (marcinelle)",
    "sg:classifiers":[
        {
            "category":"Professional",
            "subcategory":"Testing Lab",
            "type":"Services"
        }
    ],
    "sg:phone":"+32 71 36 04 15",
    "sg:postcode":"6001",
    "sg:province":"Hainaut",
    "sg:tags":[
        "chemist"
    ],
    "wof:name":"Doucet D",
    "wof:placetype":"venue"
},
  "geometry": {"coordinates":[4.4289879799,50.4019851685],"type":"Point"}
}