{
  "type": "Feature",
  "properties": {
    "iso:country":"BE",
    "sg:address":"Rue De Bosnie 101",
    "sg:city":"Bruxelles (saint-gilles)",
    "sg:classifiers":[
        {
            "category":"Professional",
            "subcategory":"Computer Services",
            "type":"Services"
        }
    ],
    "sg:phone":"+32 2 534 31 70",
    "sg:postcode":"1060",
    "sg:province":"Bruxelles-Capitale",
    "sg:tags":[
        "webdesign",
        "-",
        "internet"
    ],
    "wof:name":"Full Web Service",
    "wof:placetype":"venue"
},
  "geometry": {"coordinates":[4.3377552032,50.8269004822],"type":"Point"}
}