{
  "type": "Feature",
  "properties": {
    "addr:full":"Rue Du Blanc-ry 29 Ottignies-louvain-la-neuve (ottignies) Brabant Wallon 1340",
    "addr:housenumber":"29",
    "addr:postcode":"1340",
    "addr:street":"Rue Du Blanc-Ry",
    "iso:country":"BE",
    "sg:address":"Rue Du Blanc-ry 29",
    "sg:city":"Ottignies-louvain-la-neuve (ottignies)",
    "sg:classifiers":[
        {
            "category":"Personal",
            "subcategory":"Beauty Salon",
            "type":"Services"
        }
    ],
    "sg:phone":"+32 477 34 05 55",
    "sg:postcode":"1340",
    "sg:province":"Brabant Wallon",
    "wof:name":"Actu Nails",
    "wof:placetype":"venue"
},
  "geometry": {"coordinates":[4.5769138336,50.672832489],"type":"Point"}
}