{
  "type": "Feature",
  "properties": {
    "addr:full":"Zwadderkotstraat 2 Oudenaarde Oost-Vlaanderen 9700",
    "addr:housenumber":"2",
    "addr:postcode":"9700",
    "addr:street":"Zwadderkotstraat",
    "iso:country":"BE",
    "sg:address":"Zwadderkotstraat 2",
    "sg:city":"Oudenaarde",
    "sg:classifiers":[
        {
            "category":"Restaurant",
            "type":"Food & Drink"
        }
    ],
    "sg:phone":"+32 55 49 84 95",
    "sg:postcode":"9700",
    "sg:province":"Oost-Vlaanderen",
    "wof:name":"Zwadderkotmolen",
    "wof:placetype":"venue"
},
  "geometry": {"coordinates":[3.6656990051,50.8562583923],"type":"Point"}
}