{
  "type": "Feature",
  "properties": {
    "iso:country":"BE",
    "sg:address":"La Vaux 14",
    "sg:city":"Trois-ponts - Fosse (basse-bodeux)",
    "sg:classifiers":[
        {
            "category":"Professional",
            "subcategory":"Art Services",
            "type":"Services"
        }
    ],
    "sg:phone":"+32 80 68 45 71",
    "sg:postcode":"4983",
    "sg:province":"Li\u00e8ge",
    "sg:tags":[
        "graphic",
        "designer"
    ],
    "wof:name":"Martin Cl",
    "wof:placetype":"venue"
},
  "geometry": {"coordinates":[5.8048601151,50.3586807251],"type":"Point"}
}