{
  "type": "Feature",
  "properties": {
    "addr:full":"Rue Joseph Wauters 33 Waremme Li\u00e8ge 4300",
    "addr:housenumber":"33",
    "addr:postcode":"4300",
    "addr:street":"Rue Joseph Wauters",
    "iso:country":"BE",
    "sg:address":"Rue Joseph Wauters 33",
    "sg:city":"Waremme",
    "sg:orig_category":"Textiel",
    "sg:phone":"+32 19 32 24 23",
    "sg:postcode":"4300",
    "sg:province":"Li\u00e8ge",
    "wof:name":"Maison Anny",
    "wof:placetype":"venue"
},
  "geometry": {"coordinates":[5.2548179626,50.6971473694],"type":"Point"}
}