{
  "type": "Feature",
  "properties": {
    "addr:full":"Rue Des Briqueteries 1 La Louviere Hainaut 7100",
    "addr:housenumber":"1",
    "addr:postcode":"7100",
    "addr:street":"Rue Des Briqueteries",
    "iso:country":"BE",
    "sg:address":"Rue Des Briqueteries 1",
    "sg:city":"La Louviere",
    "sg:orig_category":"Enseignement maternel and primaire",
    "sg:phone":"+32 64 22 36 65",
    "sg:postcode":"7100",
    "sg:province":"Hainaut",
    "wof:name":"Ecole Fond. Communale",
    "wof:placetype":"venue"
},
  "geometry": {"coordinates":[4.1664648056,50.4670677185],"type":"Point"}
}