{
  "type": "Feature",
  "properties": {
    "addr:full":"Terlinden 237 Merchtem Vlaams-Brabant 1785",
    "addr:housenumber":"237",
    "addr:postcode":"1785",
    "addr:street":"Terlinden",
    "iso:country":"BE",
    "sg:address":"Terlinden 237",
    "sg:city":"Merchtem",
    "sg:classifiers":[
        {
            "category":"Shopping",
            "subcategory":"Bicycles & Sporting Goods",
            "type":"Retail Goods"
        }
    ],
    "sg:phone":"+32 52 37 08 84",
    "sg:postcode":"1785",
    "sg:province":"Vlaams-Brabant",
    "sg:tags":[
        "tyre"
    ],
    "wof:name":"Merchtemse Bandencentrale",
    "wof:placetype":"venue"
},
  "geometry": {"coordinates":[4.2542247772,50.9676704407],"type":"Point"}
}