{
  "type": "Feature",
  "properties": {
    "addr:full":"Ninoofsesteenweg 55 Halle (groot) Vlaams-Brabant 1500",
    "addr:housenumber":"55;1500",
    "addr:street":"Ninoofsesteenweg;Groot Vlaams-Brabant",
    "iso:country":"BE",
    "sg:address":"Ninoofsesteenweg 55",
    "sg:city":"Halle (groot)",
    "sg:classifiers":[
        {
            "category":"Personal",
            "subcategory":"Beauty Salon",
            "type":"Services"
        }
    ],
    "sg:phone":"+32 2 356 68 06",
    "sg:postcode":"1500",
    "sg:province":"Vlaams-Brabant",
    "sg:tags":[
        "de",
        "coiffure"
    ],
    "wof:name":"Alan Paul Hairdressing",
    "wof:placetype":"venue"
},
  "geometry": {"coordinates":[4.2341542244,50.7376556396],"type":"Point"}
}