{
  "type": "Feature",
  "properties": {
    "iso:country":"BE",
    "sg:address":"Boulevard Adolphe Max 108-15",
    "sg:city":"Bruxelles",
    "sg:classifiers":[
        {
            "category":"Organizations",
            "subcategory":"Professional Association",
            "type":"Services"
        }
    ],
    "sg:postcode":"1000",
    "sg:province":"Bruxelles-Capitale",
    "sg:tags":[
        "trade-union",
        "federation"
    ],
    "wof:name":"Liberaal Verbond Voor Zelfstandigen Vzw",
    "wof:placetype":"venue"
},
  "geometry": {"coordinates":[4.3560447693,50.8541564941],"type":"Point"}
}