{
  "type": "Feature",
  "properties": {
    "iso:country":"BE",
    "sg:address":"Rue Octave-lotin 35",
    "sg:city":"Chastre",
    "sg:orig_category":"Dakwerken",
    "sg:phone":"+32 81 61 54 24",
    "sg:postcode":"1450",
    "sg:province":"Brabant Wallon",
    "wof:name":"Eric Michels",
    "wof:placetype":"venue"
},
  "geometry": {"coordinates":[4.636452198,50.6085243225],"type":"Point"}
}