{
  "type": "Feature",
  "properties": {
    "iso:country":"BE",
    "sg:address":"Rue Du Moulin D'en Haut 236",
    "sg:city":"Mons (fl\u00e9nu)",
    "sg:classifiers":[
        {
            "category":"Personal",
            "subcategory":"Beauty Salon",
            "type":"Services"
        }
    ],
    "sg:phone":"+32 65 72 47 47",
    "sg:postcode":"7012",
    "sg:province":"Hainaut",
    "sg:tags":[
        "lady",
        "-",
        "hairdressing"
    ],
    "wof:name":"Id\u00e9al Coiff",
    "wof:placetype":"venue"
},
  "geometry": {"coordinates":[3.8994269371,50.438911438],"type":"Point"}
}