{
  "type": "Feature",
  "properties": {
    "iso:country":"BE",
    "sg:address":"Volksberg 35",
    "sg:city":"Kortrijk",
    "sg:classifiers":[
        {
            "category":"Cafe",
            "type":"Food & Drink"
        }
    ],
    "sg:phone":"+32 56 22 07 70",
    "sg:postcode":"8510",
    "sg:province":"West-Vlaanderen",
    "sg:tags":[
        "caf\u00e9s"
    ],
    "wof:name":"Liliane Putman",
    "wof:placetype":"venue"
},
  "geometry": {"coordinates":[3.2904450893,50.7752342224],"type":"Point"}
}