{
  "type": "Feature",
  "properties": {
    "iso:country":"BE",
    "sg:address":"Avenue De La Toison D'or 15",
    "sg:city":"Bruxelles (ixelles)",
    "sg:classifiers":[
        {
            "category":"Bus Stop",
            "subcategory":"None",
            "type":"Transportation"
        }
    ],
    "sg:phone":"+32 2 515 20 00",
    "sg:postcode":"1050",
    "sg:province":"Bruxelles-Capitale",
    "sg:tags":[
        "public",
        "transport"
    ],
    "wof:name":"Stib",
    "wof:placetype":"venue"
},
  "geometry": {"coordinates":[4.3798799515,50.8206710815],"type":"Point"}
}