{
  "type": "Feature",
  "properties": {
    "addr:full":"Pannestraat 203 Lanaken Limburg 3620",
    "addr:housenumber":"203",
    "addr:postcode":"3620",
    "addr:street":"Pannestraat",
    "iso:country":"BE",
    "sg:address":"Pannestraat 203",
    "sg:city":"Lanaken",
    "sg:orig_category":"Landmeters Woningbouw",
    "sg:phone":"+32 89 71 52 70",
    "sg:postcode":"3620",
    "sg:province":"Limburg",
    "wof:name":"Bouwbedrijf D\u00b4n Heuvel",
    "wof:placetype":"venue"
},
  "geometry": {"coordinates":[5.6321911812,50.8930358887],"type":"Point"}
}