{
  "type": "Feature",
  "properties": {
    "addr:full":"Kattestraat 57 Denderleeuw (welle) Oost-Vlaanderen 9473",
    "addr:housenumber":"57",
    "addr:postcode":"9473",
    "addr:street":"Kattestraat",
    "iso:country":"BE",
    "sg:address":"Kattestraat 57",
    "sg:city":"Denderleeuw (welle)",
    "sg:orig_category":"Non-Classified Establishments",
    "sg:phone":"+32 53 66 04 92",
    "sg:postcode":"9473",
    "sg:province":"Oost-Vlaanderen",
    "wof:name":"Flanders Knitwear",
    "wof:placetype":"venue"
},
  "geometry": {"coordinates":[4.0474190712,50.8961143494],"type":"Point"}
}