{
  "type": "Feature",
  "properties": {
    "iso:country":"BE",
    "sg:address":"Landbouwstraat 40",
    "sg:city":"Niel",
    "sg:classifiers":[
        {
            "category":"Manufacturing",
            "subcategory":"Motor Vehicles & Parts",
            "type":"Manufacturing & Wholesale Goods"
        }
    ],
    "sg:phone":"+32 3 844 54 07",
    "sg:postcode":"2845",
    "sg:province":"Antwerpen",
    "sg:tags":[
        "bearing"
    ],
    "wof:name":"Isorol Bvba",
    "wof:placetype":"venue"
},
  "geometry": {"coordinates":[4.3315348625,51.1075172424],"type":"Point"}
}