{
  "type": "Feature",
  "properties": {
    "iso:country":"BE",
    "sg:address":"Statiestraat 154",
    "sg:city":"Ternat",
    "sg:classifiers":[
        {
            "category":"Cafe",
            "type":"Food & Drink"
        }
    ],
    "sg:phone":"+32 2 582 41 84",
    "sg:postcode":"1740",
    "sg:province":"Vlaams-Brabant",
    "sg:tags":[
        "caf\u00e9s"
    ],
    "wof:name":"Julia De Brandt",
    "wof:placetype":"venue"
},
  "geometry": {"coordinates":[4.1681060791,50.8736724854],"type":"Point"}
}