{
  "type": "Feature",
  "properties": {
    "addr:full":"Boseind 148b3 Neerpelt Limburg 3910",
    "addr:housenumber":"148b3",
    "addr:postcode":"3910",
    "addr:street":"Boseind",
    "iso:country":"BE",
    "sg:address":"Boseind 148b3",
    "sg:city":"Neerpelt",
    "sg:orig_category":"M\u00e9decins and sp\u00e9cialistes",
    "sg:phone":"+32 11 64 35 51",
    "sg:postcode":"3910",
    "sg:province":"Limburg",
    "wof:name":"Marfa Di Pietrantonio",
    "wof:placetype":"venue"
},
  "geometry": {"coordinates":[5.440764904,51.2124443054],"type":"Point"}
}