{
  "type": "Feature",
  "properties": {
    "addr:full":"Quinten Matsijslei 3 Antwerpen Antwerpen 2018",
    "addr:housenumber":"3",
    "addr:postcode":"2018",
    "addr:street":"Matsijslei",
    "iso:country":"BE",
    "sg:address":"Quinten Matsijslei 3",
    "sg:city":"Antwerpen",
    "sg:classifiers":[
        {
            "category":"Food & Beverages",
            "subcategory":"Fruits & Vegetables",
            "type":"Retail Goods"
        }
    ],
    "sg:phone":"+32 3 233 70 33",
    "sg:postcode":"2018",
    "sg:province":"Antwerpen",
    "sg:tags":[
        "groenten"
    ],
    "wof:name":"De Fruitkorf",
    "wof:placetype":"venue"
},
  "geometry": {"coordinates":[4.4160161018,51.2148742676],"type":"Point"}
}