{
  "type": "Feature",
  "properties": {
    "iso:country":"BE",
    "sg:address":"Hoogstraat 64",
    "sg:city":"Herzele",
    "sg:classifiers":[
        {
            "category":"Insurance",
            "subcategory":"Life Insurance",
            "type":"Services"
        }
    ],
    "sg:phone":"+32 53 62 18 11",
    "sg:postcode":"9550",
    "sg:province":"Oost-Vlaanderen",
    "sg:tags":[
        "assurance"
    ],
    "wof:name":"Fa. Van Den Driessche",
    "wof:placetype":"venue"
},
  "geometry": {"coordinates":[3.8809421062,50.8828582764],"type":"Point"}
}