{
  "type": "Feature",
  "properties": {
    "iso:country":"BE",
    "sg:address":"Kalkoven 133",
    "sg:city":"Asse",
    "sg:orig_category":"Catering and organisatie van feesten Voedingsspeciaalzaken",
    "sg:phone":"+32 2 453 00 80",
    "sg:postcode":"1730",
    "sg:province":"Vlaams-Brabant",
    "wof:name":"Traiteur Speedy",
    "wof:placetype":"venue"
},
  "geometry": {"coordinates":[4.1933298111,50.9141082764],"type":"Point"}
}