{
  "type": "Feature",
  "properties": {
    "iso:country":"BE",
    "sg:address":"Rue Des D\u00e9port\u00e9s 2b",
    "sg:city":"Charleroi (gosselies)",
    "sg:classifiers":[
        {
            "category":"Professional",
            "subcategory":"Lawyer & Legal Services",
            "type":"Services"
        }
    ],
    "sg:phone":"+32 71 35 35 15",
    "sg:postcode":"6041",
    "sg:province":"Hainaut",
    "sg:tags":[
        "notary"
    ],
    "wof:name":"Dupuis Ph",
    "wof:placetype":"venue"
},
  "geometry": {"coordinates":[4.4751682281,50.383769989],"type":"Point"}
}