{
  "type": "Feature",
  "properties": {
    "addr:full":"Bosstraat 23 Bree Limburg 3960",
    "addr:housenumber":"23",
    "addr:postcode":"3960",
    "addr:street":"Bosstraat",
    "iso:country":"BE",
    "sg:address":"Bosstraat 23",
    "sg:city":"Bree",
    "sg:orig_category":"Enseignement maternel and primaire",
    "sg:phone":"+32 89 86 69 16",
    "sg:postcode":"3960",
    "sg:province":"Limburg",
    "wof:name":"Vrije Basisschool",
    "wof:placetype":"venue"
},
  "geometry": {"coordinates":[5.6606030464,51.1286239624],"type":"Point"}
}