{
  "type": "Feature",
  "properties": {
    "addr:full":"Diestsevest 50 Leuven Vlaams-Brabant 3000",
    "addr:housenumber":"50",
    "addr:postcode":"3000",
    "addr:street":"Diestsevest",
    "iso:country":"BE",
    "sg:address":"Diestsevest 50",
    "sg:city":"Leuven",
    "sg:orig_category":"Maatschappelijke dienstverlening",
    "sg:phone":"+32 16 22 74 48",
    "sg:postcode":"3000",
    "sg:province":"Vlaams-Brabant",
    "wof:name":"Vclb-centrum",
    "wof:placetype":"venue"
},
  "geometry": {"coordinates":[4.7134752274,50.8832015991],"type":"Point"}
}