{
  "type": "Feature",
  "properties": {
    "iso:country":"BE",
    "sg:address":"Rue Du Culot 28",
    "sg:city":"Eghezee",
    "sg:classifiers":[
        {
            "category":"Military Area",
            "subcategory":"Armory",
            "type":"Public Place"
        }
    ],
    "sg:phone":"+32 81 51 13 27",
    "sg:postcode":"5310",
    "sg:province":"Namur",
    "sg:tags":[
        "armes",
        "munition"
    ],
    "wof:name":"Philippe Kodeck",
    "wof:placetype":"venue"
},
  "geometry": {"coordinates":[4.892551899,50.5749740601],"type":"Point"}
}