{
  "type": "Feature",
  "properties": {
    "iso:country":"BE",
    "sg:address":"Rue Des 14 Verges 361",
    "sg:city":"Liege",
    "sg:orig_category":"Woningbouw",
    "sg:phone":"+32 4 226 68 60",
    "sg:postcode":"4000",
    "sg:province":"Li\u00e8ge",
    "wof:name":"B\u00c9ton Refect",
    "wof:placetype":"venue"
},
  "geometry": {"coordinates":[5.5575499535,50.6627311707],"type":"Point"}
}