{
  "type": "Feature",
  "properties": {
    "addr:full":"Sportlaan 17 Eeklo Oost-Vlaanderen 9900",
    "addr:housenumber":"17",
    "addr:postcode":"9900",
    "addr:street":"Sportlaan",
    "iso:country":"BE",
    "sg:address":"Sportlaan 17",
    "sg:city":"Eeklo",
    "sg:classifiers":[
        {
            "category":"Health Services",
            "subcategory":"Doctor",
            "type":"Services"
        }
    ],
    "sg:phone":"+32 9 376 04 46",
    "sg:postcode":"9900",
    "sg:province":"Oost-Vlaanderen",
    "sg:tags":[
        "medicinephysicians",
        "surgeon"
    ],
    "wof:name":"Maes J-j",
    "wof:placetype":"venue"
},
  "geometry": {"coordinates":[3.5839691162,51.1821784973],"type":"Point"}
}