{
  "type": "Feature",
  "properties": {
    "iso:country":"BE",
    "sg:address":"Sankt-vitherstrasse 99",
    "sg:city":"Amel/ambleve",
    "sg:orig_category":"Boucheries. Eleveurs de bovins",
    "sg:phone":"+32 80 34 96 15",
    "sg:postcode":"4770",
    "sg:province":"Li\u00e8ge",
    "wof:name":"Peters W. & Sohn",
    "wof:placetype":"venue"
},
  "geometry": {"coordinates":[6.1184020042,50.3325119019],"type":"Point"}
}