{
  "type": "Feature",
  "properties": {
    "addr:full":"Rue Eglise Saint-sulpice 9 Beauvechain Brabant Wallon 1320",
    "addr:housenumber":"9",
    "addr:postcode":"1320",
    "addr:street":"Rue Eglise Saint-Sulpice",
    "iso:country":"BE",
    "sg:address":"Rue Eglise Saint-sulpice 9",
    "sg:city":"Beauvechain",
    "sg:orig_category":"Pharmaciens",
    "sg:phone":"+32 10 86 60 48",
    "sg:postcode":"1320",
    "sg:province":"Brabant Wallon",
    "wof:name":"S. Cavalier",
    "wof:placetype":"venue"
},
  "geometry": {"coordinates":[4.7730078697,50.7801704407],"type":"Point"}
}