{
  "type": "Feature",
  "properties": {
    "addr:full":"Dorpsplein 5 Zonhoven Limburg 3520",
    "addr:housenumber":"5",
    "addr:postcode":"3520",
    "addr:street":"Dorpsplein",
    "iso:country":"BE",
    "sg:address":"Dorpsplein 5",
    "sg:city":"Zonhoven",
    "sg:classifiers":[
        {
            "category":"Building & Trades",
            "subcategory":"Construction",
            "type":"Services"
        }
    ],
    "sg:phone":"+32 11 81 87 65",
    "sg:postcode":"3520",
    "sg:province":"Limburg",
    "sg:tags":[
        "surveyor",
        "-"
    ],
    "wof:name":"Decoutere Studiebureau Bvba",
    "wof:placetype":"venue"
},
  "geometry": {"coordinates":[5.3673582077,50.9942817688],"type":"Point"}
}