{
  "type": "Feature",
  "properties": {
    "addr:full":"Halmaal-dorp 1 Sint-truiden (halmaal) Limburg 3800",
    "addr:housenumber":"1",
    "addr:postcode":"3800",
    "addr:street":"Halmaal-Dorp",
    "iso:country":"BE",
    "sg:address":"Halmaal-dorp 1",
    "sg:city":"Sint-truiden (halmaal)",
    "sg:classifiers":[
        {
            "category":"Professional",
            "subcategory":"Accounting & Tax Preparation",
            "type":"Services"
        }
    ],
    "sg:phone":"+32 11 70 72 40",
    "sg:postcode":"3800",
    "sg:province":"Limburg",
    "sg:tags":[
        "accountant"
    ],
    "wof:name":"Elchardus F",
    "wof:placetype":"venue"
},
  "geometry": {"coordinates":[5.1544299126,50.8042488098],"type":"Point"}
}