{
  "type": "Feature",
  "properties": {
    "addr:full":"Witvenstraat 98 Stabroek Antwerpen 2940",
    "addr:housenumber":"98",
    "addr:postcode":"2940",
    "addr:street":"Witvenstraat",
    "iso:country":"BE",
    "sg:address":"Witvenstraat 98",
    "sg:city":"Stabroek",
    "sg:classifiers":[
        {
            "category":"Shopping",
            "subcategory":"Clothing, Apparel, & Fashions",
            "type":"Retail Goods"
        }
    ],
    "sg:phone":"+32 3 605 00 41",
    "sg:postcode":"2940",
    "sg:province":"Antwerpen",
    "sg:tags":[
        "v\u00eatements",
        "pour",
        "dame"
    ],
    "wof:name":"Huis Zora",
    "wof:placetype":"venue"
},
  "geometry": {"coordinates":[4.3649148941,51.331943512],"type":"Point"}
}