{
  "type": "Feature",
  "properties": {
    "iso:country":"BE",
    "sg:address":"Astweg 2",
    "sg:city":"Wuustwezel",
    "sg:orig_category":"Eleveurs de bovins. Eleveurs and marchands de porcs",
    "sg:phone":"+32 3 313 89 72",
    "sg:postcode":"2990",
    "sg:province":"Antwerpen",
    "wof:name":"Jan Van Looveren",
    "wof:placetype":"venue"
},
  "geometry": {"coordinates":[4.6698269844,51.3897018433],"type":"Point"}
}