{
  "type": "Feature",
  "properties": {
    "iso:country":"BE",
    "sg:address":"Spoorwegstraat 9",
    "sg:city":"Genk",
    "sg:classifiers":[
        {
            "category":"Bakery",
            "type":"Food & Drink"
        }
    ],
    "sg:phone":"+32 89 36 18 94",
    "sg:postcode":"3600",
    "sg:province":"Limburg",
    "sg:tags":[
        "confectioner",
        "baker"
    ],
    "wof:name":"Tomassen-cops",
    "wof:placetype":"venue"
},
  "geometry": {"coordinates":[5.4700450897,50.9750595093],"type":"Point"}
}