{
  "type": "Feature",
  "properties": {
    "iso:country":"BE",
    "sg:address":"Kerselarenlaan 8",
    "sg:city":"Brussel",
    "sg:classifiers":[
        {
            "category":"Organizations",
            "subcategory":"Community Association",
            "type":"Services"
        }
    ],
    "sg:phone":"+32 2 736 90 81",
    "sg:postcode":"1030",
    "sg:province":"Bruxelles-Capitale",
    "sg:tags":[
        "assembly",
        "system"
    ],
    "wof:name":"A.c.i. Eau Pure S.a.",
    "wof:placetype":"venue"
},
  "geometry": {"coordinates":[4.4036102295,50.8489341736],"type":"Point"}
}