{
  "type": "Feature",
  "properties": {
    "addr:full":"Cijnsstraat 32 Aalter Oost-Vlaanderen 9880",
    "addr:housenumber":"32",
    "addr:postcode":"9880",
    "addr:street":"Cijnsstraat",
    "iso:country":"BE",
    "sg:address":"Cijnsstraat 32",
    "sg:city":"Aalter",
    "sg:orig_category":"Eleveurs de bovins",
    "sg:phone":"+32 9 374 23 89",
    "sg:postcode":"9880",
    "sg:province":"Oost-Vlaanderen",
    "wof:name":"Noel Slock",
    "wof:placetype":"venue"
},
  "geometry": {"coordinates":[3.4413039684,51.0660133362],"type":"Point"}
}