{
  "type": "Feature",
  "properties": {
    "addr:full":"L\u00e9once Roelsstraat 15 Zottegem Oost-Vlaanderen 9620",
    "addr:housenumber":"15",
    "addr:postcode":"9620",
    "addr:street":"Roelsstraat",
    "iso:country":"BE",
    "sg:address":"L\u00e9once Roelsstraat 15",
    "sg:city":"Zottegem",
    "sg:classifiers":[
        {
            "category":"Autos & Motor Vehicles",
            "subcategory":"Automobile Sales",
            "type":"Retail Goods"
        }
    ],
    "sg:phone":"+32 9 360 12 52",
    "sg:postcode":"9620",
    "sg:province":"Oost-Vlaanderen",
    "sg:tags":[
        "ceremony",
        "car"
    ],
    "wof:name":"Denijs J",
    "wof:placetype":"venue"
},
  "geometry": {"coordinates":[3.8129870892,50.865650177],"type":"Point"}
}