{
  "type": "Feature",
  "properties": {
    "addr:full":"Hoekstraat 7 Box 2 Neerpelt Limburg 3910",
    "addr:housenumber":"7;2",
    "addr:postcode":"3910",
    "addr:street":"Hoekstraat;Box",
    "iso:country":"BE",
    "sg:address":"Hoekstraat 7 Box 2",
    "sg:city":"Neerpelt",
    "sg:classifiers":[
        {
            "category":"Manufacturing",
            "subcategory":"Tools & Machinery",
            "type":"Manufacturing & Wholesale Goods"
        }
    ],
    "sg:phone":"+32 11 64 19 56",
    "sg:postcode":"3910",
    "sg:province":"Limburg",
    "sg:tags":[
        "builder"
    ],
    "wof:name":"Houben-van Der Velden J",
    "wof:placetype":"venue"
},
  "geometry": {"coordinates":[5.4293408394,51.2285308838],"type":"Point"}
}