{
  "type": "Feature",
  "properties": {
    "addr:full":"Rue Du G\u00c9n\u00c9ral Molitor 8 Arlon (grand) Luxembourg 6700",
    "addr:housenumber":"8",
    "addr:postcode":"6700",
    "addr:street":"Rue Du Ge\u0301Ne\u0301Ral Molitor",
    "iso:country":"BE",
    "sg:address":"Rue Du G\u00c9n\u00c9ral Molitor 8",
    "sg:city":"Arlon (grand)",
    "sg:orig_category":"Werk and personeelsselectie",
    "sg:phone":"+32 63 24 29 40",
    "sg:postcode":"6700",
    "sg:province":"Luxembourg",
    "wof:name":"Forem",
    "wof:placetype":"venue"
},
  "geometry": {"coordinates":[5.8122329712,49.6817932129],"type":"Point"}
}