{
  "type": "Feature",
  "properties": {
    "iso:country":"BE",
    "sg:address":"Rue Des Grasses-oies 2 A",
    "sg:city":"Virton",
    "sg:classifiers":[
        {
            "category":"Banks & Credit Unions",
            "subcategory":"Financial Services",
            "type":"Services"
        }
    ],
    "sg:phone":"+32 63 57 93 11",
    "sg:postcode":"6760",
    "sg:province":"Luxembourg",
    "sg:tags":[
        "banking",
        "finance",
        "insurance"
    ],
    "wof:name":"Agf/assubel Banque",
    "wof:placetype":"venue"
},
  "geometry": {"coordinates":[5.5308799744,49.5683822632],"type":"Point"}
}