{
  "type": "Feature",
  "properties": {
    "iso:country":"BE",
    "sg:address":"Kameelstraat 6",
    "sg:city":"Dilbeek (sint-martens-bodegem)",
    "sg:classifiers":[
        {
            "category":"Professional",
            "subcategory":"Lawyer & Legal Services",
            "type":"Services"
        }
    ],
    "sg:phone":"+32 2 346 45 26",
    "sg:postcode":"1700",
    "sg:province":"Vlaams-Brabant",
    "wof:name":"De Corte Luc",
    "wof:placetype":"venue"
},
  "geometry": {"coordinates":[4.2138252258,50.8553352356],"type":"Point"}
}