{
  "type": "Feature",
  "properties": {
    "iso:country":"BE",
    "sg:address":"Chauss\u00e9e De Charleroi 76",
    "sg:city":"Lasne (plancenoit)",
    "sg:orig_category":"Non-Classified Establishments",
    "sg:phone":"+32 2 384 10 41",
    "sg:postcode":"1380",
    "sg:province":"Brabant Wallon",
    "wof:name":"Vetipro",
    "wof:placetype":"venue"
},
  "geometry": {"coordinates":[4.4127998352,50.65599823],"type":"Point"}
}