{
  "type": "Feature",
  "properties": {
    "addr:full":"Gezondheidslei 34 Brasschaat Antwerpen 2930",
    "addr:housenumber":"34",
    "addr:postcode":"2930",
    "addr:street":"Gezondheidslei",
    "iso:country":"BE",
    "sg:address":"Gezondheidslei 34",
    "sg:city":"Brasschaat",
    "sg:orig_category":"Jardinage",
    "sg:phone":"+32 3 605 14 52",
    "sg:postcode":"2930",
    "sg:province":"Antwerpen",
    "wof:name":"Nicolas Janssens",
    "wof:placetype":"venue"
},
  "geometry": {"coordinates":[4.4446158409,51.2944297791],"type":"Point"}
}