{
  "type": "Feature",
  "properties": {
    "iso:country":"BE",
    "sg:address":"Zonnebloemstraat 11-13",
    "sg:city":"Geraardsbergen",
    "sg:orig_category":"Chaussures",
    "sg:phone":"+32 54 41 84 26",
    "sg:postcode":"9500",
    "sg:province":"Oost-Vlaanderen",
    "wof:name":"Shoe Discount",
    "wof:placetype":"venue"
},
  "geometry": {"coordinates":[3.8868288994,50.7773017883],"type":"Point"}
}