{
  "type": "Feature",
  "properties": {
    "addr:full":"Dommelstraat 93 Waasmunster Oost-Vlaanderen 9250",
    "addr:housenumber":"93",
    "addr:postcode":"9250",
    "addr:street":"Dommelstraat",
    "iso:country":"BE",
    "sg:address":"Dommelstraat 93",
    "sg:city":"Waasmunster",
    "sg:orig_category":"Boissons",
    "sg:phone":"+32 52 46 00 33",
    "sg:postcode":"9250",
    "sg:province":"Oost-Vlaanderen",
    "wof:name":"Fa. Thuysbaert",
    "wof:placetype":"venue"
},
  "geometry": {"coordinates":[4.1199178696,51.114238739],"type":"Point"}
}