{
  "type": "Feature",
  "properties": {
    "addr:full":"Rue Saint-paul 56 Welkenraedt/welkenraedt Li\u00e8ge 4840",
    "addr:housenumber":"56",
    "addr:postcode":"4840",
    "addr:street":"Rue Saint-Paul",
    "iso:country":"BE",
    "sg:address":"Rue Saint-paul 56",
    "sg:city":"Welkenraedt/welkenraedt",
    "sg:orig_category":"Artsen and specialisten",
    "sg:phone":"+32 87 88 29 70",
    "sg:postcode":"4840",
    "sg:province":"Li\u00e8ge",
    "wof:name":"Carine Lenders",
    "wof:placetype":"venue"
},
  "geometry": {"coordinates":[5.9796700478,50.6616210938],"type":"Point"}
}