{
  "type": "Feature",
  "properties": {
    "iso:country":"BE",
    "sg:address":"Weg Zutendaal 107",
    "sg:city":"Maasmechelen",
    "sg:classifiers":[
        {
            "category":"Personal",
            "subcategory":"Beauty Salon",
            "type":"Services"
        }
    ],
    "sg:phone":"+32 89 76 01 28",
    "sg:postcode":"3630",
    "sg:province":"Limburg",
    "sg:tags":[
        "de",
        "coiffure"
    ],
    "wof:name":"Coiffure Tony",
    "wof:placetype":"venue"
},
  "geometry": {"coordinates":[5.6961350441,50.963848114],"type":"Point"}
}