{
  "type": "Feature",
  "properties": {
    "iso:country":"BE",
    "sg:address":"Statiestraat 58",
    "sg:city":"Ternat",
    "sg:orig_category":"Bloemen and planten",
    "sg:phone":"+32 2 582 15 63",
    "sg:postcode":"1740",
    "sg:province":"Vlaams-Brabant",
    "wof:name":"In De Bloemenkorf",
    "wof:placetype":"venue"
},
  "geometry": {"coordinates":[4.1723098755,50.8718833923],"type":"Point"}
}