{
  "type": "Feature",
  "properties": {
    "iso:country":"BE",
    "sg:address":"Martelarenstraat 40",
    "sg:city":"Aarschot",
    "sg:classifiers":[
        {
            "category":"Shopping",
            "subcategory":"Clothing, Apparel, & Fashions",
            "type":"Retail Goods"
        }
    ],
    "sg:phone":"+32 16 56 65 26",
    "sg:postcode":"3200",
    "sg:province":"Vlaams-Brabant",
    "sg:tags":[
        "lady",
        "clothing",
        "-"
    ],
    "wof:name":"Persy Nv",
    "wof:placetype":"venue"
},
  "geometry": {"coordinates":[4.8343081474,50.9843673706],"type":"Point"}
}