{
  "type": "Feature",
  "properties": {
    "iso:country":"BE",
    "sg:address":"Veldstraat 19",
    "sg:city":"Ardooie",
    "sg:orig_category":"Eleveurs d'animaux domestiques",
    "sg:phone":"+32 51 74 56 43",
    "sg:postcode":"8850",
    "sg:province":"West-Vlaanderen",
    "wof:name":"Of Baluchistan",
    "wof:placetype":"venue"
},
  "geometry": {"coordinates":[3.2232561111,50.9657402039],"type":"Point"}
}