{
  "type": "Feature",
  "properties": {
    "iso:country":"BE",
    "sg:address":"Tienbunder 40",
    "sg:city":"Waregem",
    "sg:orig_category":"Kapsalons Mobiele kappers Schoonheidssalons",
    "sg:phone":"+32 56 72 68 08",
    "sg:postcode":"8792",
    "sg:province":"West-Vlaanderen",
    "wof:name":"Pedicure Sevenoo",
    "wof:placetype":"venue"
},
  "geometry": {"coordinates":[3.348952055,50.8901023865],"type":"Point"}
}