{
  "type": "Feature",
  "properties": {
    "addr:full":"Rue De Saint-amand 86 P\u00e9ruwelz Hainaut 7600",
    "addr:housenumber":"86",
    "addr:postcode":"7600",
    "addr:street":"Rue De Saint-Amand",
    "iso:country":"BE",
    "sg:address":"Rue De Saint-amand 86",
    "sg:city":"P\u00e9ruwelz",
    "sg:classifiers":[
        {
            "category":"Arena",
            "subcategory":"Sports Club",
            "type":"Entertainment"
        }
    ],
    "sg:phone":"+32 69 77 62 39",
    "sg:postcode":"7600",
    "sg:province":"Hainaut",
    "wof:name":"Fun-gym",
    "wof:placetype":"venue"
},
  "geometry": {"coordinates":[3.5995159149,50.4944915771],"type":"Point"}
}