{
  "type": "Feature",
  "properties": {
    "iso:country":"BE",
    "sg:address":"Avenue Docteur Schweitzer 217",
    "sg:city":"Colfontaine (wasmes)",
    "sg:classifiers":[
        {
            "category":"Health Services",
            "subcategory":"Dentist",
            "type":"Services"
        }
    ],
    "sg:phone":"+32 65 79 38 08",
    "sg:postcode":"7340",
    "sg:province":"Hainaut",
    "wof:name":"Marchesani Carolina",
    "wof:placetype":"venue"
},
  "geometry": {"coordinates":[3.8464710712,50.4306030273],"type":"Point"}
}