{
  "type": "Feature",
  "properties": {
    "iso:country":"BE",
    "sg:address":"Rue Des Ganons 10",
    "sg:city":"Amay (ampsin)",
    "sg:classifiers":[
        {
            "category":"Home & Garden",
            "subcategory":"Carpets & Floor Coverings",
            "type":"Retail Goods"
        }
    ],
    "sg:phone":"+32 85 31 69 09",
    "sg:postcode":"4540",
    "sg:province":"Li\u00e8ge",
    "sg:tags":[
        "tile"
    ],
    "wof:name":"C\u00f4t\u00e9 Court C\u00f4t\u00e9 Jardin",
    "wof:placetype":"venue"
},
  "geometry": {"coordinates":[5.3180990219,50.5478668213],"type":"Point"}
}