{
  "type": "Feature",
  "properties": {
    "addr:full":"Bovenstraat 16 Maarkedal (maarke-kerkem) Oost-Vlaanderen 9680",
    "addr:housenumber":"16",
    "addr:postcode":"9680",
    "addr:street":"Bovenstraat",
    "iso:country":"BE",
    "sg:address":"Bovenstraat 16",
    "sg:city":"Maarkedal (maarke-kerkem)",
    "sg:classifiers":[
        {
            "category":"Real Estate",
            "subcategory":"Architect",
            "type":"Services"
        }
    ],
    "sg:phone":"+32 55 31 08 05",
    "sg:postcode":"9680",
    "sg:province":"Oost-Vlaanderen",
    "wof:name":"Bontinck Y",
    "wof:placetype":"venue"
},
  "geometry": {"coordinates":[3.6453249454,50.803691864],"type":"Point"}
}