{
  "type": "Feature",
  "properties": {
    "iso:country":"BE",
    "sg:address":"Albertlaan 19",
    "sg:city":"Tervuren",
    "sg:orig_category":"Sportclubs",
    "sg:phone":"+32 2 767 37 62",
    "sg:postcode":"3080",
    "sg:province":"Vlaams-Brabant",
    "wof:name":"La Colombe Joyeuse",
    "wof:placetype":"venue"
},
  "geometry": {"coordinates":[4.5132598877,50.8243637085],"type":"Point"}
}