{
  "type": "Feature",
  "properties": {
    "addr:full":"Rue De Valenciennes 29 Quievrain Hainaut 7380",
    "addr:housenumber":"29",
    "addr:postcode":"7380",
    "addr:street":"Rue De Valenciennes;Hainaut",
    "iso:country":"BE",
    "sg:address":"Rue De Valenciennes 29",
    "sg:city":"Quievrain",
    "sg:orig_category":"Dierenartsen",
    "sg:phone":"+32 65 43 03 32",
    "sg:postcode":"7380",
    "sg:province":"Hainaut",
    "wof:name":"Michel Doyen",
    "wof:placetype":"venue"
},
  "geometry": {"coordinates":[3.6791369915,50.4043083191],"type":"Point"}
}