{
  "type": "Feature",
  "properties": {
    "addr:full":"Avenue Du Marquis 25 Fleurus Hainaut 6220",
    "addr:housenumber":"25",
    "addr:postcode":"6220",
    "addr:street":"Avenue Du Marquis",
    "iso:country":"BE",
    "sg:address":"Avenue Du Marquis 25",
    "sg:city":"Fleurus",
    "sg:orig_category":"Non-Classified Establishments",
    "sg:phone":"+32 71 80 06 09",
    "sg:postcode":"6220",
    "sg:province":"Hainaut",
    "wof:name":"D\u00e9bit Et Froid Sa",
    "wof:placetype":"venue"
},
  "geometry": {"coordinates":[4.5300951004,50.4583282471],"type":"Point"}
}