{
  "type": "Feature",
  "properties": {
    "addr:full":"Klapstraat 70 Ninove Oost-Vlaanderen 9402",
    "addr:housenumber":"70",
    "addr:postcode":"9402",
    "addr:street":"Klapstraat",
    "iso:country":"BE",
    "sg:address":"Klapstraat 70",
    "sg:city":"Ninove",
    "sg:orig_category":"Installation de menuiserie en bois and plastique. Installation de menuiserie m\u00e9tallique",
    "sg:phone":"+32 54 32 49 66",
    "sg:postcode":"9402",
    "sg:province":"Oost-Vlaanderen",
    "wof:name":"Dirk De Doncker",
    "wof:placetype":"venue"
},
  "geometry": {"coordinates":[4.0395750999,50.8249015808],"type":"Point"}
}