{
  "type": "Feature",
  "properties": {
    "addr:full":"Meterkensstraat 27 Hoogstraten Antwerpen 2320",
    "addr:housenumber":"27",
    "addr:postcode":"2320",
    "addr:street":"Meterkensstraat",
    "iso:country":"BE",
    "sg:address":"Meterkensstraat 27",
    "sg:city":"Hoogstraten",
    "sg:orig_category":"Elektrische installaties voor woningen Loodgieterij, verwarming and sanitaire installaties",
    "sg:phone":"+32 3 314 43 33",
    "sg:postcode":"2320",
    "sg:province":"Antwerpen",
    "wof:name":"Van Gils Electro",
    "wof:placetype":"venue"
},
  "geometry": {"coordinates":[4.765545845,51.3905143738],"type":"Point"}
}