{
  "type": "Feature",
  "properties": {
    "iso:country":"BE",
    "sg:address":"Goswin De Stassartstraat 153",
    "sg:city":"Mechelen",
    "sg:classifiers":[
        {
            "category":"Museum",
            "type":"Entertainment"
        }
    ],
    "sg:phone":"+32 15 29 06 60",
    "sg:postcode":"2800",
    "sg:province":"Antwerpen",
    "wof:name":"Joods Museum V. Deportatie En",
    "wof:placetype":"venue"
},
  "geometry": {"coordinates":[4.4785428047,51.0341758728],"type":"Point"}
}