{
  "type": "Feature",
  "properties": {
    "iso:country":"BE",
    "sg:address":"Rue De Villers 145",
    "sg:city":"Charleroi (couillet)",
    "sg:classifiers":[
        {
            "category":"Professional",
            "subcategory":"Engineering",
            "type":"Services"
        }
    ],
    "sg:phone":"+32 71 51 34 50",
    "sg:postcode":"6010",
    "sg:province":"Hainaut",
    "sg:tags":[
        "technical",
        "equipment",
        "offices-"
    ],
    "wof:name":"Globe Marketing Sprl",
    "wof:placetype":"venue"
},
  "geometry": {"coordinates":[4.475001812,50.3875732422],"type":"Point"}
}