{
  "type": "Feature",
  "properties": {
    "iso:country":"BE",
    "sg:address":"Rupelmondestraat 107",
    "sg:city":"Kruibeke (bazel)",
    "sg:classifiers":[
        {
            "category":"Bars & Pubs",
            "type":"Food & Drink"
        }
    ],
    "sg:phone":"+32 3 774 40 65",
    "sg:postcode":"9150",
    "sg:province":"Oost-Vlaanderen",
    "wof:name":"Werkmansrust",
    "wof:placetype":"venue"
},
  "geometry": {"coordinates":[4.2963700294,51.1434898376],"type":"Point"}
}