{
  "type": "Feature",
  "properties": {
    "iso:country":"BE",
    "sg:address":"Mons. Trudo Jansstraat 1",
    "sg:city":"Riemst",
    "sg:orig_category":"Fruitteelt Rundveehouders",
    "sg:phone":"+32 12 45 32 83",
    "sg:postcode":"3770",
    "sg:province":"Limburg",
    "wof:name":"Herman Pauly",
    "wof:placetype":"venue"
},
  "geometry": {"coordinates":[5.5721378326,50.8066101074],"type":"Point"}
}