{
  "type": "Feature",
  "properties": {
    "addr:full":"Hoogstraat 6 Oudenburg West-Vlaanderen 8460",
    "addr:housenumber":"6",
    "addr:postcode":"8460",
    "addr:street":"Hoogstraat",
    "iso:country":"BE",
    "sg:address":"Hoogstraat 6",
    "sg:city":"Oudenburg",
    "sg:classifiers":[
        {
            "category":"Fast Food",
            "type":"Food & Drink"
        }
    ],
    "sg:phone":"+32 59 26 77 44",
    "sg:postcode":"8460",
    "sg:province":"West-Vlaanderen",
    "sg:tags":[
        "fried",
        "stand",
        "potato"
    ],
    "wof:name":"'t Frit-uurtje",
    "wof:placetype":"venue"
},
  "geometry": {"coordinates":[3.006403923,51.1834373474],"type":"Point"}
}