{
  "type": "Feature",
  "properties": {
    "addr:full":"Drieslaan 23 Wevelgem West-Vlaanderen 8560",
    "addr:housenumber":"23",
    "addr:postcode":"8560",
    "addr:street":"Drieslaan",
    "iso:country":"BE",
    "sg:address":"Drieslaan 23",
    "sg:city":"Wevelgem",
    "sg:classifiers":[
        {
            "category":"Manufacturing",
            "subcategory":"Motor Vehicles & Parts",
            "type":"Manufacturing & Wholesale Goods"
        }
    ],
    "sg:phone":"+32 56 40 20 57",
    "sg:postcode":"8560",
    "sg:province":"West-Vlaanderen",
    "sg:tags":[
        "industry",
        "metallurgical",
        "vendor"
    ],
    "wof:name":"Vancoillie Jos\u00e9 & Co B.v.b.a.",
    "wof:placetype":"venue"
},
  "geometry": {"coordinates":[3.1886200905,50.8492698669],"type":"Point"}
}