{
  "type": "Feature",
  "properties": {
    "iso:country":"BE",
    "sg:address":"Vlaamsekaai 7",
    "sg:city":"Antwerpen",
    "sg:orig_category":"Evaluation and estimation de biens immobiliers",
    "sg:phone":"+32 3 248 57 21",
    "sg:postcode":"2000",
    "sg:province":"Antwerpen",
    "wof:name":"Bureau Peeters Guy",
    "wof:placetype":"venue"
},
  "geometry": {"coordinates":[4.3934350014,51.2117271423],"type":"Point"}
}