{
  "type": "Feature",
  "properties": {
    "iso:country":"BE",
    "sg:address":"Eviestraat 19",
    "sg:city":"Houthalen-helchteren",
    "sg:orig_category":"Fleurs and plantes",
    "sg:phone":"+32 11 52 56 00",
    "sg:postcode":"3530",
    "sg:province":"Limburg",
    "wof:name":"Franciscus Clerix",
    "wof:placetype":"venue"
},
  "geometry": {"coordinates":[5.3820447922,51.0394439697],"type":"Point"}
}