{
  "type": "Feature",
  "properties": {
    "iso:country":"BE",
    "sg:address":"Hendrik Baelskaai 8",
    "sg:city":"Oostende",
    "sg:classifiers":[
        {
            "category":"Metro Station",
            "type":"Transportation"
        }
    ],
    "sg:phone":"+32 59 32 28 75",
    "sg:postcode":"8400",
    "sg:province":"West-Vlaanderen",
    "sg:tags":[
        "repair",
        "ship",
        "mainten",
        "-"
    ],
    "wof:name":"Renaud Scheepsdiesel",
    "wof:placetype":"venue"
},
  "geometry": {"coordinates":[2.93227911,51.2350463867],"type":"Point"}
}