{
  "type": "Feature",
  "properties": {
    "iso:country":"BE",
    "sg:address":"Kasteeldreef 23",
    "sg:city":"Ranst",
    "sg:orig_category":"Baby- and kinderkleding",
    "sg:phone":"+32 3 475 19 63",
    "sg:postcode":"2520",
    "sg:province":"Antwerpen",
    "wof:name":"Train De Vie",
    "wof:placetype":"venue"
},
  "geometry": {"coordinates":[4.5584921837,51.1949729919],"type":"Point"}
}