{
  "type": "Feature",
  "properties": {
    "addr:full":"Rue Des Angli\u00e8res 23 Marbehan Luxembourg 6724",
    "addr:housenumber":"23",
    "addr:postcode":"6724",
    "addr:street":"Rue Des Anglie\u0300Res",
    "iso:country":"BE",
    "sg:address":"Rue Des Angli\u00e8res 23",
    "sg:city":"Marbehan",
    "sg:orig_category":"Cd-Rom Juke Boxes",
    "sg:phone":"+32 63 44 48 98",
    "sg:postcode":"6724",
    "sg:province":"Luxembourg",
    "wof:name":"Gestion Loisir S.p.r.l.",
    "wof:placetype":"venue"
},
  "geometry": {"coordinates":[5.5394411087,49.7238731384],"type":"Point"}
}