{
  "type": "Feature",
  "properties": {
    "iso:country":"BE",
    "sg:address":"Rue Du Centre 60",
    "sg:city":"Ciney",
    "sg:orig_category":"Drogisterijen IJzerwaren, bouw- and verfmaterialen Plaatsen van vloer- and muurbekleding Schilders T",
    "sg:phone":"+32 83 21 21 33",
    "sg:postcode":"5590",
    "sg:province":"Namur",
    "wof:name":"Ceram",
    "wof:placetype":"venue"
},
  "geometry": {"coordinates":[5.1017398834,50.2966766357],"type":"Point"}
}