{
  "type": "Feature",
  "properties": {
    "addr:full":"Schurhovenveld 4068 Sint-truiden Limburg 3800",
    "addr:postcode":"4068;3800",
    "addr:street":"Schurhovenveld",
    "iso:country":"BE",
    "sg:address":"Schurhovenveld 4068",
    "sg:city":"Sint-truiden",
    "sg:classifiers":[
        {
            "category":"Landmark",
            "subcategory":"City Walls",
            "type":"Public Place"
        }
    ],
    "sg:phone":"+32 11 48 03 80",
    "sg:postcode":"3800",
    "sg:province":"Limburg",
    "sg:tags":[
        "shed",
        "open",
        "hangar"
    ],
    "wof:name":"M.t.s. Systems Gepa Nv",
    "wof:placetype":"venue"
},
  "geometry": {"coordinates":[5.1863641739,50.8153343201],"type":"Point"}
}