{
  "type": "Feature",
  "properties": {
    "addr:full":"Avenue Picquart 51-53 Bruxelles-schaerbeek Bruxelles-Capitale 1030",
    "addr:housenumber":"51-53",
    "addr:postcode":"1030",
    "addr:street":"Avenue Picquart",
    "iso:country":"BE",
    "sg:address":"Avenue Picquart 51-53",
    "sg:city":"Bruxelles-schaerbeek",
    "sg:orig_category":"Computers and computerapparatuur Diverse informatica-activiteiten Microsoft Onderhoud van kantoor- a",
    "sg:phone":"+32 2 242 72 20",
    "sg:postcode":"1030",
    "sg:province":"Bruxelles-Capitale",
    "wof:name":"Tase Research",
    "wof:placetype":"venue"
},
  "geometry": {"coordinates":[4.383043766,50.8775253296],"type":"Point"}
}