{
  "type": "Feature",
  "properties": {
    "addr:full":"Kokkelbeekstraat 47 Sint-niklaas Oost-Vlaanderen 9100",
    "addr:housenumber":"47",
    "addr:postcode":"9100",
    "addr:street":"Kokkelbeekstraat",
    "iso:country":"BE",
    "sg:address":"Kokkelbeekstraat 47",
    "sg:city":"Sint-niklaas",
    "sg:orig_category":"Brood, gebak and snoepgoed",
    "sg:phone":"+32 3 776 15 80",
    "sg:postcode":"9100",
    "sg:province":"Oost-Vlaanderen",
    "wof:name":"Fa. Thierens",
    "wof:placetype":"venue"
},
  "geometry": {"coordinates":[4.1418042183,51.1621742249],"type":"Point"}
}