{
  "type": "Feature",
  "properties": {
    "iso:country":"BE",
    "sg:address":"Pepingensesteenweg 120",
    "sg:city":"Sint-pieters-leeuw",
    "sg:classifiers":[
        {
            "category":"Building & Trades",
            "subcategory":"Construction",
            "type":"Services"
        }
    ],
    "sg:phone":"+32 2 305 42 03",
    "sg:postcode":"1600",
    "sg:province":"Vlaams-Brabant",
    "sg:tags":[
        "installation",
        "-",
        "central",
        "heating"
    ],
    "wof:name":"Colet Chauffage",
    "wof:placetype":"venue"
},
  "geometry": {"coordinates":[4.2386479378,50.7690658569],"type":"Point"}
}