{
  "type": "Feature",
  "properties": {
    "iso:country":"BE",
    "sg:address":"Kelderbeemd 14",
    "sg:city":"Retie",
    "sg:classifiers":[
        {
            "category":"Building & Trades",
            "subcategory":"Electrical",
            "type":"Services"
        }
    ],
    "sg:phone":"+32 3 646 08 00",
    "sg:postcode":"2470",
    "sg:province":"Antwerpen",
    "sg:tags":[
        "plants",
        "plant",
        "industrial",
        "buildings",
        "construction"
    ],
    "wof:name":"Bouwbedrijf Flor\u00e9 Nv",
    "wof:placetype":"venue"
},
  "geometry": {"coordinates":[4.4632902145,51.2627067566],"type":"Point"}
}