{
  "type": "Feature",
  "properties": {
    "iso:country":"BE",
    "sg:address":"Hoornzeelstraat 57 Box 3",
    "sg:city":"Tervuren",
    "sg:classifiers":[
        {
            "category":"Real Estate",
            "subcategory":"Architect",
            "type":"Services"
        }
    ],
    "sg:phone":"+32 2 306 63 47",
    "sg:postcode":"3080",
    "sg:province":"Vlaams-Brabant",
    "wof:name":"Vandevoorde E",
    "wof:placetype":"venue"
},
  "geometry": {"coordinates":[4.5121269226,50.8213348389],"type":"Point"}
}