{
  "type": "Feature",
  "properties": {
    "addr:full":"Keerbergsesteenweg 84 Haacht Vlaams-Brabant 3150",
    "addr:housenumber":"84",
    "addr:postcode":"3150",
    "addr:street":"Keerbergsesteenweg",
    "iso:country":"BE",
    "sg:address":"Keerbergsesteenweg 84",
    "sg:city":"Haacht",
    "sg:classifiers":[
        {
            "category":"Health Services",
            "subcategory":"Health Practitioner",
            "type":"Services"
        }
    ],
    "sg:phone":"+32 16 60 23 37",
    "sg:postcode":"3150",
    "sg:province":"Vlaams-Brabant",
    "sg:tags":[
        "therapist",
        "speech"
    ],
    "wof:name":"Blux T",
    "wof:placetype":"venue"
},
  "geometry": {"coordinates":[4.6432647705,50.9840202332],"type":"Point"}
}