{
  "type": "Feature",
  "properties": {
    "iso:country":"BE",
    "sg:address":"Statiestraat 95",
    "sg:city":"Zwijndrecht",
    "sg:orig_category":"M\u00e9decins and sp\u00e9cialistes",
    "sg:phone":"+32 3 252 81 73",
    "sg:postcode":"2070",
    "sg:province":"Antwerpen",
    "wof:name":"M. Van Proeyen",
    "wof:placetype":"venue"
},
  "geometry": {"coordinates":[4.3284277916,51.2160987854],"type":"Point"}
}