{
  "type": "Feature",
  "properties": {
    "addr:full":"Chemin De La Bicoque 3 Malmedy/malmedy Li\u00e8ge 4960",
    "addr:housenumber":"3",
    "addr:postcode":"4960",
    "addr:street":"Chemin De La Bicoque",
    "iso:country":"BE",
    "sg:address":"Chemin De La Bicoque 3",
    "sg:city":"Malmedy/malmedy",
    "sg:classifiers":[
        {
            "category":"Restaurant",
            "type":"Food & Drink"
        }
    ],
    "sg:phone":"+32 80 33 96 98",
    "sg:postcode":"4960",
    "sg:province":"Li\u00e8ge",
    "wof:name":"Restaurant Le Farfadet",
    "wof:placetype":"venue"
},
  "geometry": {"coordinates":[6.0845441818,50.4709815979],"type":"Point"}
}