{
  "type": "Feature",
  "properties": {
    "iso:country":"BE",
    "sg:address":"Europalaan 77",
    "sg:city":"Wevelgem",
    "sg:orig_category":"Plantes and fleurs Gr",
    "sg:phone":"+32 56 41 27 29",
    "sg:postcode":"8560",
    "sg:province":"West-Vlaanderen",
    "wof:name":"Exotic Plants",
    "wof:placetype":"venue"
},
  "geometry": {"coordinates":[3.2122569084,50.840133667],"type":"Point"}
}