{
  "type": "Feature",
  "properties": {
    "iso:country":"BE",
    "sg:address":"Kemelweg 8",
    "sg:city":"Denderleeuw (welle)",
    "sg:classifiers":[
        {
            "category":"Building & Trades",
            "subcategory":"Electrical",
            "type":"Services"
        }
    ],
    "sg:phone":"+32 53 68 03 74",
    "sg:postcode":"9473",
    "sg:province":"Oost-Vlaanderen",
    "sg:tags":[
        "electric",
        "-",
        "housewiring",
        "contractor"
    ],
    "wof:name":"Electro Soft Bvba",
    "wof:placetype":"venue"
},
  "geometry": {"coordinates":[4.0582060814,50.8992576599],"type":"Point"}
}