{
  "type": "Feature",
  "properties": {
    "iso:country":"BE",
    "sg:address":"15",
    "sg:city":"Katwilgweg 2050 Antwerpen",
    "sg:classifiers":[
        {
            "category":"Professional",
            "subcategory":"Engineering",
            "type":"Services"
        }
    ],
    "sg:phone":"+32 3 250 16 00",
    "sg:postcode":"15",
    "sg:tags":[
        "machine",
        "-",
        "mechanical"
    ],
    "wof:name":"Azo Nv",
    "wof:placetype":"venue"
},
  "geometry": {"coordinates":[4.3597202301,51.2179374695],"type":"Point"}
}