{
  "type": "Feature",
  "properties": {
    "iso:country":"BE",
    "sg:address":"Rue Du Maquis 4",
    "sg:city":"Saint-ghislain",
    "sg:orig_category":"Woningbouw",
    "sg:phone":"+32 65 62 07 49",
    "sg:postcode":"7334",
    "sg:province":"Hainaut",
    "wof:name":"Entreprises Dramaix",
    "wof:placetype":"venue"
},
  "geometry": {"coordinates":[3.7644500732,50.479675293],"type":"Point"}
}