{
  "type": "Feature",
  "properties": {
    "iso:country":"BE",
    "sg:address":"Genkerbaan 88",
    "sg:city":"Zonhoven",
    "sg:orig_category":"Salles de conf\u00e9rences and de r\u00e9ceptions. Dancings and bo\u00eetes de nuit",
    "sg:phone":"+32 11 81 42 88",
    "sg:postcode":"3520",
    "sg:province":"Limburg",
    "wof:name":"Super Palace",
    "wof:placetype":"venue"
},
  "geometry": {"coordinates":[5.3806328773,50.9916725159],"type":"Point"}
}