{
  "type": "Feature",
  "properties": {
    "iso:country":"BE",
    "sg:address":"Kerkhovensesteenweg 375",
    "sg:city":"Lommel",
    "sg:classifiers":[
        {
            "category":"Home & Garden",
            "subcategory":"Household Appliances",
            "type":"Retail Goods"
        }
    ],
    "sg:phone":"+32 11 34 16 31",
    "sg:postcode":"3920",
    "sg:province":"Limburg",
    "sg:tags":[
        "repair",
        "stove",
        "-"
    ],
    "wof:name":"Dierckx R Bvba",
    "wof:placetype":"venue"
},
  "geometry": {"coordinates":[5.269449234,51.1635513306],"type":"Point"}
}