{
  "type": "Feature",
  "properties": {
    "addr:full":"Stationsstraat 106 Essen Antwerpen 2910",
    "addr:housenumber":"106",
    "addr:postcode":"2910",
    "addr:street":"Stationsstraat",
    "iso:country":"BE",
    "sg:address":"Stationsstraat 106",
    "sg:city":"Essen",
    "sg:orig_category":"Meubles D\u00e9taillants, Am\u00e9nagement de B\u00e2timents et de Cuisines",
    "sg:phone":"+32 3 667 21 29",
    "sg:postcode":"2910",
    "sg:province":"Antwerpen",
    "wof:name":"Meubelhuis Suykerbuyk",
    "wof:placetype":"venue"
},
  "geometry": {"coordinates":[4.4607448578,51.4653320312],"type":"Point"}
}