{
  "type": "Feature",
  "properties": {
    "addr:full":"Zandvoordestraat 280 Oostende West-Vlaanderen 8400",
    "addr:housenumber":"280",
    "addr:postcode":"8400",
    "addr:street":"Zandvoordestraat",
    "iso:country":"BE",
    "sg:address":"Zandvoordestraat 280",
    "sg:city":"Oostende",
    "sg:classifiers":[
        {
            "category":"Communications",
            "subcategory":"Newspaper",
            "type":"Services"
        }
    ],
    "sg:phone":"+32 59 50 09 95",
    "sg:postcode":"8400",
    "sg:province":"West-Vlaanderen",
    "sg:tags":[
        "distributor",
        "magazine"
    ],
    "wof:name":"Internationale Boekhandel Distributie Dienst Nv",
    "wof:placetype":"venue"
},
  "geometry": {"coordinates":[2.9486699104,51.2127113342],"type":"Point"}
}