{
  "type": "Feature",
  "properties": {
    "iso:country":"BE",
    "sg:address":"Zeedijk-knokke 625b1",
    "sg:city":"Knokke-heist",
    "sg:orig_category":"Salles de spectacles",
    "sg:phone":"+32 50 37 19 03",
    "sg:postcode":"8300",
    "sg:province":"West-Vlaanderen",
    "wof:name":"Galerij Hermathena",
    "wof:placetype":"venue"
},
  "geometry": {"coordinates":[3.2812299728,51.3408164978],"type":"Point"}
}