{
  "type": "Feature",
  "properties": {
    "addr:full":"Lange Zandstraat 10 Mechelen Antwerpen 2800",
    "addr:housenumber":"10",
    "addr:postcode":"2800",
    "addr:street":"Lange Zandstraat",
    "iso:country":"BE",
    "sg:address":"Lange Zandstraat 10",
    "sg:city":"Mechelen",
    "sg:orig_category":"Woningbouw",
    "sg:phone":"+32 15 20 70 36",
    "sg:postcode":"2800",
    "sg:province":"Antwerpen",
    "wof:name":"Vercammen L.",
    "wof:placetype":"venue"
},
  "geometry": {"coordinates":[4.4593200684,51.0651741028],"type":"Point"}
}