{
  "type": "Feature",
  "properties": {
    "iso:country":"BE",
    "sg:address":"Tabaksvest 73",
    "sg:city":"Antwerpen",
    "sg:classifiers":[
        {
            "category":"Bars & Pubs",
            "type":"Food & Drink"
        }
    ],
    "sg:phone":"+32 3 232 53 35",
    "sg:postcode":"2000",
    "sg:province":"Antwerpen",
    "wof:name":"Blauwe Toren",
    "wof:placetype":"venue"
},
  "geometry": {"coordinates":[4.4088559151,51.2127990723],"type":"Point"}
}