{
  "type": "Feature",
  "properties": {
    "addr:full":"Vaartstraat 9 Genk Limburg 3600",
    "addr:housenumber":"9",
    "addr:postcode":"3600",
    "addr:street":"Vaartstraat",
    "iso:country":"BE",
    "sg:address":"Vaartstraat 9",
    "sg:city":"Genk",
    "sg:orig_category":"Autombile concessionaires",
    "sg:phone":"+32 89 35 84 01",
    "sg:postcode":"3600",
    "sg:province":"Limburg",
    "wof:name":"Group Pashuysen Limburg Nv",
    "wof:placetype":"venue"
},
  "geometry": {"coordinates":[5.4716229439,50.9433898926],"type":"Point"}
}