{
  "type": "Feature",
  "properties": {
    "iso:country":"BE",
    "sg:address":"Chemin Du Gros Tienne 97",
    "sg:city":"Lasne (ohain)",
    "sg:classifiers":[
        {
            "category":"Real Estate",
            "subcategory":"Architect",
            "type":"Services"
        }
    ],
    "sg:phone":"+32 477 32 44 30",
    "sg:postcode":"1380",
    "sg:province":"Brabant Wallon",
    "wof:name":"Mourialm\u00e9 P",
    "wof:placetype":"venue"
},
  "geometry": {"coordinates":[4.4774880409,50.719619751],"type":"Point"}
}