{
  "type": "Feature",
  "properties": {
    "iso:country":"BE",
    "sg:address":"Laarstraat 2",
    "sg:city":"Kampenhout (nederokkerzeel)",
    "sg:classifiers":[
        {
            "category":"Ice Cream",
            "type":"Food & Drink"
        }
    ],
    "sg:phone":"+32 16 65 69 26",
    "sg:postcode":"1910",
    "sg:province":"Vlaams-Brabant",
    "wof:name":"Verbist-bergijs",
    "wof:placetype":"venue"
},
  "geometry": {"coordinates":[4.5522961617,50.9221038818],"type":"Point"}
}