{
  "type": "Feature",
  "properties": {
    "addr:full":"Rue Mabiets 8 Villers-le-bouillet Li\u00e8ge 4530",
    "addr:housenumber":"8",
    "addr:postcode":"4530",
    "addr:street":"Rue Mabiets",
    "iso:country":"BE",
    "sg:address":"Rue Mabiets 8",
    "sg:city":"Villers-le-bouillet",
    "sg:classifiers":[
        {
            "category":"Health Services",
            "subcategory":"Health Practitioner",
            "type":"Services"
        }
    ],
    "sg:phone":"+32 85 25 23 31",
    "sg:postcode":"4530",
    "sg:province":"Li\u00e8ge",
    "sg:tags":[
        "physiotherapist"
    ],
    "wof:name":"Carion Fran\u00e7oise",
    "wof:placetype":"venue"
},
  "geometry": {"coordinates":[5.2625350952,50.5631103516],"type":"Point"}
}