{
  "type": "Feature",
  "properties": {
    "iso:country":"BE",
    "sg:address":"Lokerstraat 27",
    "sg:city":"Heuvelland",
    "sg:classifiers":[
        {
            "category":"Arena",
            "subcategory":"Sports Club",
            "type":"Entertainment"
        }
    ],
    "sg:phone":"+32 57 44 69 38",
    "sg:postcode":"8954",
    "sg:province":"West-Vlaanderen",
    "sg:tags":[
        "de"
    ],
    "wof:name":"Wielerclub De Westvlaamse Bergstreek",
    "wof:placetype":"venue"
},
  "geometry": {"coordinates":[2.8210220337,50.7830467224],"type":"Point"}
}