{
  "type": "Feature",
  "properties": {
    "iso:country":"BE",
    "sg:address":"Rue De Kleinbettingen 34",
    "sg:city":"Arlon (autelbas)",
    "sg:classifiers":[
        {
            "category":"Banks & Credit Unions",
            "subcategory":"Investment Brokerage",
            "type":"Services"
        }
    ],
    "sg:phone":"+32 495 51 83 39",
    "sg:postcode":"6706",
    "sg:province":"Luxembourg",
    "sg:tags":[
        "repair",
        "-",
        "installation",
        "sanitary",
        "article"
    ],
    "wof:name":"Sani-chauffe-lipolis P Sprl",
    "wof:placetype":"venue"
},
  "geometry": {"coordinates":[5.8697757721,49.6491928101],"type":"Point"}
}