{
  "type": "Feature",
  "properties": {
    "addr:full":"Hoevensebaan 47 Kapellen Antwerpen 2950",
    "addr:housenumber":"47",
    "addr:postcode":"2950",
    "addr:street":"Hoevensebaan",
    "iso:country":"BE",
    "sg:address":"Hoevensebaan 47",
    "sg:city":"Kapellen",
    "sg:classifiers":[
        {
            "category":"Restaurant",
            "type":"Food & Drink"
        }
    ],
    "sg:phone":"+32 3 297 06 18",
    "sg:postcode":"2950",
    "sg:province":"Antwerpen",
    "wof:name":"Janssens & Co",
    "wof:placetype":"venue"
},
  "geometry": {"coordinates":[4.4267477989,51.3138542175],"type":"Point"}
}