{
  "type": "Feature",
  "properties": {
    "addr:full":"Rue De Rotheux 46 Seraing Li\u00e8ge 4100",
    "addr:housenumber":"46",
    "addr:postcode":"4100",
    "addr:street":"Rue De Rotheux",
    "iso:country":"BE",
    "sg:address":"Rue De Rotheux 46",
    "sg:city":"Seraing",
    "sg:classifiers":[
        {
            "category":"Restaurant",
            "type":"Food & Drink"
        }
    ],
    "sg:phone":"+32 4 338 40 88",
    "sg:postcode":"4100",
    "sg:province":"Li\u00e8ge",
    "sg:tags":[
        "caf\u00e9s"
    ],
    "wof:name":"Taverne Le Serey",
    "wof:placetype":"venue"
},
  "geometry": {"coordinates":[5.5049448013,50.5863723755],"type":"Point"}
}