{
  "type": "Feature",
  "properties": {
    "iso:country":"BE",
    "sg:address":"Reetsesteenweg 124",
    "sg:city":"Aartselaar",
    "sg:classifiers":[
        {
            "category":"Professional",
            "subcategory":"Accounting & Tax Preparation",
            "type":"Services"
        }
    ],
    "sg:phone":"+32 3 887 86 07",
    "sg:postcode":"2630",
    "sg:province":"Antwerpen",
    "sg:tags":[
        "bookkeeper"
    ],
    "wof:name":"Canaco Bvba",
    "wof:placetype":"venue"
},
  "geometry": {"coordinates":[4.3935289383,51.1217002869],"type":"Point"}
}