{
  "type": "Feature",
  "properties": {
    "iso:country":"BE",
    "sg:address":"Steenweg Wijchmaal 12 Box 4",
    "sg:city":"Peer",
    "sg:classifiers":[
        {
            "category":"Airport",
            "subcategory":"General Aviation",
            "type":"Transportation"
        }
    ],
    "sg:phone":"+32 11 61 19 38",
    "sg:postcode":"3990",
    "sg:province":"Limburg",
    "sg:tags":[
        "transport"
    ],
    "wof:name":"Steyaert Bart",
    "wof:placetype":"venue"
},
  "geometry": {"coordinates":[5.4485669136,51.1328353882],"type":"Point"}
}