{
  "type": "Feature",
  "properties": {
    "addr:full":"Rue De Walcourt 29b Fosses-la-ville (vitrival) Namur 5070",
    "addr:housenumber":"29b",
    "addr:postcode":"5070",
    "addr:street":"Rue De Walcourt",
    "iso:country":"BE",
    "sg:address":"Rue De Walcourt 29b",
    "sg:city":"Fosses-la-ville (vitrival)",
    "sg:classifiers":[
        {
            "category":"Insurance",
            "subcategory":"Insurance Agent",
            "type":"Services"
        }
    ],
    "sg:phone":"+32 71 71 26 59",
    "sg:postcode":"5070",
    "sg:province":"Namur",
    "sg:tags":[
        "broker"
    ],
    "wof:name":"Vermoote A",
    "wof:placetype":"venue"
},
  "geometry": {"coordinates":[4.6303548813,50.3851776123],"type":"Point"}
}