{
  "type": "Feature",
  "properties": {
    "iso:country":"BE",
    "sg:address":"Neutralstrasse 206",
    "sg:city":"Lontzen/lontzen",
    "sg:orig_category":"Pleisterwerk Vloer- and muurbekleding",
    "sg:phone":"+32 87 88 16 30",
    "sg:postcode":"4710",
    "sg:province":"Li\u00e8ge",
    "wof:name":"B.p.g.",
    "wof:placetype":"venue"
},
  "geometry": {"coordinates":[5.99229002,50.6763191223],"type":"Point"}
}