{
  "type": "Feature",
  "properties": {
    "iso:country":"BE",
    "sg:address":"Rue Lambot 91",
    "sg:city":"Aiseau-presles",
    "sg:orig_category":"Installation de menuiserie en bois and plastique",
    "sg:phone":"+32 71 77 18 48",
    "sg:postcode":"6250",
    "sg:province":"Hainaut",
    "wof:name":"Menuiserie Polet",
    "wof:placetype":"venue"
},
  "geometry": {"coordinates":[4.5876197815,50.4255714417],"type":"Point"}
}