{
  "type": "Feature",
  "properties": {
    "addr:full":"Scheidestraat 45 Ninove Oost-Vlaanderen 9400",
    "addr:housenumber":"45",
    "addr:postcode":"9400",
    "addr:street":"Scheidestraat",
    "iso:country":"BE",
    "sg:address":"Scheidestraat 45",
    "sg:city":"Ninove",
    "sg:orig_category":"Alimentation sp\u00e9cialis\u00e9e",
    "sg:phone":"+32 54 32 68 95",
    "sg:postcode":"9400",
    "sg:province":"Oost-Vlaanderen",
    "wof:name":"Marc Van Melckebeke",
    "wof:placetype":"venue"
},
  "geometry": {"coordinates":[3.963570118,50.8571891785],"type":"Point"}
}