{
  "type": "Feature",
  "properties": {
    "addr:full":"Heyerstraat 17bb Lokeren Oost-Vlaanderen 9160",
    "addr:housenumber":"17bb",
    "addr:postcode":"9160",
    "addr:street":"Heyerstraat",
    "iso:country":"BE",
    "sg:address":"Heyerstraat 17bb",
    "sg:city":"Lokeren",
    "sg:orig_category":"Gespecialiseerde residenti\u00eble bouw",
    "sg:phone":"+32 9 348 77 70",
    "sg:postcode":"9160",
    "sg:province":"Oost-Vlaanderen",
    "wof:name":"Willem Van De Voorde",
    "wof:placetype":"venue"
},
  "geometry": {"coordinates":[3.953150034,51.1080322266],"type":"Point"}
}