{
  "type": "Feature",
  "properties": {
    "addr:full":"Craenenbroekstraat 41 Glabbeek Vlaams-Brabant 3380",
    "addr:housenumber":"41",
    "addr:postcode":"3380",
    "addr:street":"Craenenbroekstraat",
    "iso:country":"BE",
    "sg:address":"Craenenbroekstraat 41",
    "sg:city":"Glabbeek",
    "sg:orig_category":"Medische apparatuur, orthopedische artikelen and prothesen Fab",
    "sg:phone":"+32 16 77 99 44",
    "sg:postcode":"3380",
    "sg:province":"Vlaams-Brabant",
    "wof:name":"Herman Lambrechts",
    "wof:placetype":"venue"
},
  "geometry": {"coordinates":[4.9544429779,50.8669395447],"type":"Point"}
}