{
  "type": "Feature",
  "properties": {
    "iso:country":"BE",
    "sg:address":"Hotelstraat 2bb",
    "sg:city":"Westerlo",
    "sg:orig_category":"V\u00eatements pour Hommes. V\u00eatements pour Dames. V\u00eatements pour b\u00e9b\u00e9s and enfants. Chaussures",
    "sg:phone":"+32 14 59 35 20",
    "sg:postcode":"2260",
    "sg:province":"Antwerpen",
    "wof:name":"Pronti",
    "wof:placetype":"venue"
},
  "geometry": {"coordinates":[4.9402132034,51.1318626404],"type":"Point"}
}