{
  "type": "Feature",
  "properties": {
    "iso:country":"BE",
    "sg:address":"Grand'rue 30",
    "sg:city":"Durbuy",
    "sg:classifiers":[
        {
            "category":"Cafe",
            "type":"Food & Drink"
        }
    ],
    "sg:phone":"+32 86 21 82 40",
    "sg:postcode":"6940",
    "sg:province":"Luxembourg",
    "sg:tags":[
        "caf\u00e9s"
    ],
    "wof:name":"Caf\u00c9 Le Barril",
    "wof:placetype":"venue"
},
  "geometry": {"coordinates":[5.4936060905,50.3504981995],"type":"Point"}
}