{
  "type": "Feature",
  "properties": {
    "iso:country":"BE",
    "sg:address":"Chauss\u00c9e De Forest 175",
    "sg:city":"Sint-gillis/saint-gilles",
    "sg:orig_category":"Epiceries",
    "sg:phone":"+32 2 539 19 30",
    "sg:postcode":"1060",
    "sg:province":"Bruxelles-Capitale",
    "wof:name":"Euro Alimentar",
    "wof:placetype":"venue"
},
  "geometry": {"coordinates":[4.3397350311,50.8272628784],"type":"Point"}
}