{
  "type": "Feature",
  "properties": {
    "iso:country":"BE",
    "sg:address":"Onze-lieve-vrouwstraat 92-94",
    "sg:city":"Heusden-zolder (zolder)",
    "sg:classifiers":[
        {
            "category":"Shopping",
            "subcategory":"Stationery & Office Supplies",
            "type":"Retail Goods"
        }
    ],
    "sg:phone":"+32 11 53 38 54",
    "sg:postcode":"3550",
    "sg:province":"Limburg",
    "sg:tags":[
        "-"
    ],
    "wof:name":"R.t.o.c. Repro Bvba",
    "wof:placetype":"venue"
},
  "geometry": {"coordinates":[5.2784371376,51.0134277344],"type":"Point"}
}