{
  "type": "Feature",
  "properties": {
    "addr:full":"Rue Alfred Defuisseaux 1 Ans (loncin) Li\u00e8ge 4431",
    "addr:housenumber":"1",
    "addr:postcode":"4431",
    "addr:street":"Rue Alfred Defuisseaux",
    "iso:country":"BE",
    "sg:address":"Rue Alfred Defuisseaux 1",
    "sg:city":"Ans (loncin)",
    "sg:classifiers":[
        {
            "category":"Farming",
            "subcategory":"Livestock Farm",
            "type":"Manufacturing & Wholesale Goods"
        }
    ],
    "sg:phone":"+32 475 42 58 41",
    "sg:postcode":"4431",
    "sg:province":"Li\u00e8ge",
    "sg:tags":[
        "horse"
    ],
    "wof:name":"Bourdoux J",
    "wof:placetype":"venue"
},
  "geometry": {"coordinates":[5.4938488007,50.66065979],"type":"Point"}
}