{
  "type": "Feature",
  "properties": {
    "addr:full":"Grand'rue 30 Lessines Hainaut 7860",
    "addr:housenumber":"30",
    "addr:postcode":"7860",
    "addr:street":"Grand'Rue;Hainaut",
    "iso:country":"BE",
    "sg:address":"Grand'rue 30",
    "sg:city":"Lessines",
    "sg:orig_category":"Banken and kredietinstellingen",
    "sg:phone":"+32 68 33 20 49",
    "sg:postcode":"7860",
    "sg:province":"Hainaut",
    "wof:name":"Bacob",
    "wof:placetype":"venue"
},
  "geometry": {"coordinates":[3.8290889263,50.7124633789],"type":"Point"}
}