{
  "type": "Feature",
  "properties": {
    "addr:full":"Rue Stepp\u00e9 12 Bruxelles (jette) Bruxelles-Capitale 1090",
    "addr:housenumber":"12",
    "addr:postcode":"1090",
    "addr:street":"Rue Steppe\u0301",
    "iso:country":"BE",
    "sg:address":"Rue Stepp\u00e9 12",
    "sg:city":"Bruxelles (jette)",
    "sg:classifiers":[
        {
            "category":"Community Center",
            "type":"Public Place"
        }
    ],
    "sg:phone":"+32 2 427 66 71",
    "sg:postcode":"1090",
    "sg:province":"Bruxelles-Capitale",
    "sg:tags":[
        "medical"
    ],
    "wof:name":"Consultation N.d. De Lourdes",
    "wof:placetype":"venue"
},
  "geometry": {"coordinates":[4.3389000893,50.8742904663],"type":"Point"}
}