{
  "type": "Feature",
  "properties": {
    "iso:country":"BE",
    "sg:address":"Kontichsesteenweg 38",
    "sg:city":"Aartselaar",
    "sg:classifiers":[
        {
            "category":"Government",
            "subcategory":"Fire Station",
            "type":"Public Place"
        }
    ],
    "sg:phone":"+32 3 870 80 00",
    "sg:postcode":"2630",
    "sg:province":"Antwerpen",
    "sg:tags":[
        "packard",
        "nec",
        "bell"
    ],
    "wof:name":"Portable Center",
    "wof:placetype":"venue"
},
  "geometry": {"coordinates":[4.3867440224,51.1433067322],"type":"Point"}
}