{
  "type": "Feature",
  "properties": {
    "iso:country":"BE",
    "sg:address":"Lozerstraat 17",
    "sg:city":"Bocholt",
    "sg:classifiers":[
        {
            "category":"Cafe",
            "type":"Food & Drink"
        }
    ],
    "sg:phone":"+32 11 62 22 59",
    "sg:postcode":"3950",
    "sg:province":"Limburg",
    "sg:tags":[
        "caf\u00e9s"
    ],
    "wof:name":"Thea Vaesen",
    "wof:placetype":"venue"
},
  "geometry": {"coordinates":[5.5601129532,51.2091636658],"type":"Point"}
}