{
  "type": "Feature",
  "properties": {
    "iso:country":"BE",
    "sg:address":"Molenstraat 202",
    "sg:city":"Balen",
    "sg:classifiers":[
        {
            "category":"Arena",
            "subcategory":"Sports Club",
            "type":"Entertainment"
        }
    ],
    "sg:phone":"+32 14 81 28 88",
    "sg:postcode":"2490",
    "sg:province":"Antwerpen",
    "sg:tags":[
        "terrain",
        "hors",
        "de",
        "installation",
        "sportifs"
    ],
    "wof:name":"K. Verbr. Balen",
    "wof:placetype":"venue"
},
  "geometry": {"coordinates":[5.1953110695,51.1725082397],"type":"Point"}
}