{
  "type": "Feature",
  "properties": {
    "addr:full":"Vinkenpad 3 Vosselaar Antwerpen 2350",
    "addr:housenumber":"3",
    "addr:postcode":"2350",
    "addr:street":"Vinkenpad",
    "iso:country":"BE",
    "sg:address":"Vinkenpad 3",
    "sg:city":"Vosselaar",
    "sg:orig_category":"Dierenartsen",
    "sg:phone":"+32 14 61 60 91",
    "sg:postcode":"2350",
    "sg:province":"Antwerpen",
    "wof:name":"Kathleen Vlaminck",
    "wof:placetype":"venue"
},
  "geometry": {"coordinates":[4.8732709885,51.3035316467],"type":"Point"}
}