{
  "type": "Feature",
  "properties": {
    "addr:full":"Rue De La Vieille Cense 2 H\u00e9l\u00e9cine (neerheylissem) Brabant Wallon 1357",
    "addr:housenumber":"2",
    "addr:postcode":"1357",
    "addr:street":"Rue De La Vieille Cense;Wallon",
    "iso:country":"BE",
    "sg:address":"Rue De La Vieille Cense 2",
    "sg:city":"H\u00e9l\u00e9cine (neerheylissem)",
    "sg:classifiers":[
        {
            "category":"Health Services",
            "subcategory":"Health Practitioner",
            "type":"Services"
        }
    ],
    "sg:phone":"+32 19 65 69 63",
    "sg:postcode":"1357",
    "sg:province":"Brabant Wallon",
    "sg:tags":[
        "physiotherapist"
    ],
    "wof:name":"Gabriel Anne",
    "wof:placetype":"venue"
},
  "geometry": {"coordinates":[4.9907259941,50.7540283203],"type":"Point"}
}