{
  "type": "Feature",
  "properties": {
    "addr:full":"Molleree 27 Oostkamp West-Vlaanderen 8020",
    "addr:housenumber":"27",
    "addr:postcode":"8020",
    "addr:street":"Molleree",
    "iso:country":"BE",
    "sg:address":"Molleree 27",
    "sg:city":"Oostkamp",
    "sg:orig_category":"Rundveehouders Varkenskwekers",
    "sg:phone":"+32 50 27 80 27",
    "sg:postcode":"8020",
    "sg:province":"West-Vlaanderen",
    "wof:name":"Marcel Dedeyne",
    "wof:placetype":"venue"
},
  "geometry": {"coordinates":[3.2681291103,51.1051750183],"type":"Point"}
}