{
  "type": "Feature",
  "properties": {
    "iso:country":"BE",
    "sg:address":"Sint-elooistraat 40",
    "sg:city":"Staden",
    "sg:classifiers":[
        {
            "category":"Wholesale",
            "subcategory":"Machinery & Supplies",
            "type":"Manufacturing & Wholesale Goods"
        }
    ],
    "sg:phone":"+32 51 70 11 14",
    "sg:postcode":"8840",
    "sg:province":"West-Vlaanderen",
    "sg:tags":[
        "agricultural",
        "tractor"
    ],
    "wof:name":"Vanpeteghem Nv",
    "wof:placetype":"venue"
},
  "geometry": {"coordinates":[2.9876549244,50.9422340393],"type":"Point"}
}