{
  "type": "Feature",
  "properties": {
    "addr:full":"Alfons Pieterslaan 1a Oostende West-Vlaanderen 8400",
    "addr:housenumber":"1a",
    "addr:postcode":"8400",
    "addr:street":"Alfons Pieterslaan",
    "iso:country":"BE",
    "sg:address":"Alfons Pieterslaan 1a",
    "sg:city":"Oostende",
    "sg:classifiers":[
        {
            "category":"Shopping",
            "subcategory":"Florist",
            "type":"Retail Goods"
        }
    ],
    "sg:phone":"+32 59 51 07 41",
    "sg:postcode":"8400",
    "sg:province":"West-Vlaanderen",
    "wof:name":"Pistache & Vanille",
    "wof:placetype":"venue"
},
  "geometry": {"coordinates":[2.9161438942,51.2267913818],"type":"Point"}
}