{
  "type": "Feature",
  "properties": {
    "iso:country":"BE",
    "sg:address":"Reetsesteenweg 208",
    "sg:city":"Aartselaar",
    "sg:classifiers":[
        {
            "category":"Farming",
            "subcategory":"Livestock Farm",
            "type":"Manufacturing & Wholesale Goods"
        }
    ],
    "sg:phone":"+32 3 844 16 22",
    "sg:postcode":"2630",
    "sg:province":"Antwerpen",
    "sg:tags":[
        "horse"
    ],
    "wof:name":"Hofmans Stal E Bvba",
    "wof:placetype":"venue"
},
  "geometry": {"coordinates":[4.3933339119,51.1179237366],"type":"Point"}
}