{
  "type": "Feature",
  "properties": {
    "addr:full":"Visserskaai 1a Kortrijk West-Vlaanderen 8500",
    "addr:housenumber":"1a",
    "addr:postcode":"8500",
    "addr:street":"Visserskaai",
    "iso:country":"BE",
    "sg:address":"Visserskaai 1a",
    "sg:city":"Kortrijk",
    "sg:orig_category":"Elektrische installaties voor woningen Informaticaconsulenten",
    "sg:phone":"+32 56 21 22 94",
    "sg:postcode":"8500",
    "sg:province":"West-Vlaanderen",
    "wof:name":"Electrotechniek Derycke",
    "wof:placetype":"venue"
},
  "geometry": {"coordinates":[3.2859890461,50.8307723999],"type":"Point"}
}