{
  "type": "Feature",
  "properties": {
    "iso:country":"BE",
    "sg:address":"Korte Dijkstraat 12",
    "sg:city":"Antwerpen",
    "sg:classifiers":[
        {
            "category":"Professional",
            "subcategory":"Art Services",
            "type":"Services"
        }
    ],
    "sg:phone":"+32 3 203 01 35",
    "sg:postcode":"2060",
    "sg:province":"Antwerpen",
    "sg:tags":[
        "graphic",
        "designer"
    ],
    "wof:name":"Bats K",
    "wof:placetype":"venue"
},
  "geometry": {"coordinates":[4.4206609726,51.2284545898],"type":"Point"}
}