{
  "type": "Feature",
  "properties": {
    "iso:country":"BE",
    "sg:address":"Doornakkerstraat 53-55",
    "sg:city":"Gent (sint-amandsberg)",
    "sg:classifiers":[
        {
            "category":"Wholesale",
            "subcategory":"Machinery & Supplies",
            "type":"Manufacturing & Wholesale Goods"
        }
    ],
    "sg:phone":"+32 9 228 75 87",
    "sg:postcode":"9040",
    "sg:province":"Oost-Vlaanderen",
    "sg:tags":[
        "refrigeration",
        "-",
        "industrial",
        "commercial",
        "equipment"
    ],
    "wof:name":"Lemmens J",
    "wof:placetype":"venue"
},
  "geometry": {"coordinates":[3.7485001087,51.0540847778],"type":"Point"}
}