{
  "type": "Feature",
  "properties": {
    "addr:full":"Ijshoutestraat 20 Sint-lievens-houtem Oost-Vlaanderen 9520",
    "addr:housenumber":"20",
    "addr:postcode":"9520",
    "addr:street":"Ijshoutestraat;Oost-Vlaanderen",
    "iso:country":"BE",
    "sg:address":"Ijshoutestraat 20",
    "sg:city":"Sint-lievens-houtem",
    "sg:classifiers":[
        {
            "category":"Arena",
            "subcategory":"Sports Club",
            "type":"Entertainment"
        }
    ],
    "sg:phone":"+32 53 62 15 05",
    "sg:postcode":"9520",
    "sg:province":"Oost-Vlaanderen",
    "sg:tags":[
        "de"
    ],
    "wof:name":"W.c. Vliegend Wiel",
    "wof:placetype":"venue"
},
  "geometry": {"coordinates":[3.8429300785,50.9224395752],"type":"Point"}
}