{
  "type": "Feature",
  "properties": {
    "iso:country":"BE",
    "sg:address":"Voogdijstraat 29",
    "sg:city":"Hasselt",
    "sg:classifiers":[
        {
            "category":"Transit Center",
            "subcategory":"Freight",
            "type":"Transportation"
        }
    ],
    "sg:phone":"+32 11 27 20 12",
    "sg:postcode":"3500",
    "sg:province":"Limburg",
    "sg:tags":[
        "import",
        "export",
        "-"
    ],
    "wof:name":"I.b.r. Trading Nv",
    "wof:placetype":"venue"
},
  "geometry": {"coordinates":[5.3470649719,50.9065208435],"type":"Point"}
}