{
  "type": "Feature",
  "properties": {
    "addr:full":"Stuivenberg 17 Assenede Oost-Vlaanderen 9968",
    "addr:housenumber":"17",
    "addr:postcode":"9968",
    "addr:street":"Stuivenberg",
    "iso:country":"BE",
    "sg:address":"Stuivenberg 17",
    "sg:city":"Assenede",
    "sg:orig_category":"Rev\u00eatements de sols and murs. Meubles D\u00e9taillants, Am\u00e9nagement de B\u00e2timents et de Cuisines. Installa",
    "sg:phone":"+32 9 344 92 56",
    "sg:postcode":"9968",
    "sg:province":"Oost-Vlaanderen",
    "wof:name":"Meubelfabriek Marc Moens",
    "wof:placetype":"venue"
},
  "geometry": {"coordinates":[3.7251119614,51.1766166687],"type":"Point"}
}