{
  "type": "Feature",
  "properties": {
    "iso:country":"BE",
    "sg:address":"Krijgslaan 47",
    "sg:city":"Gent",
    "sg:classifiers":[
        {
            "category":"Professional",
            "subcategory":"Lawyer & Legal Services",
            "type":"Services"
        }
    ],
    "sg:phone":"+32 9 243 94 20",
    "sg:postcode":"9000",
    "sg:province":"Oost-Vlaanderen",
    "wof:name":"Van Vlaenderen Frank",
    "wof:placetype":"venue"
},
  "geometry": {"coordinates":[3.7205049992,51.0345191956],"type":"Point"}
}