{
  "type": "Feature",
  "properties": {
    "iso:country":"BE",
    "sg:address":"Rue De Sordeye 17",
    "sg:city":"Li\u00c8ge",
    "sg:orig_category":"M\u00e9decins and sp\u00e9cialistes",
    "sg:phone":"+32 4 367 31 85",
    "sg:postcode":"4031",
    "sg:province":"Li\u00e8ge",
    "wof:name":"Paul Mambourg",
    "wof:placetype":"venue"
},
  "geometry": {"coordinates":[5.5720710754,50.5907173157],"type":"Point"}
}