{
  "type": "Feature",
  "properties": {
    "addr:full":"Rue Carri\u00e8re Questiaux 3 Philippeville Namur 5600",
    "addr:housenumber":"3",
    "addr:postcode":"5600",
    "addr:street":"Rue Carrie\u0300Re Questiaux",
    "iso:country":"BE",
    "sg:address":"Rue Carri\u00e8re Questiaux 3",
    "sg:city":"Philippeville",
    "sg:classifiers":[
        {
            "category":"Building & Trades",
            "subcategory":"Pest Control",
            "type":"Services"
        }
    ],
    "sg:phone":"+32 71 66 78 68",
    "sg:postcode":"5600",
    "sg:province":"Namur",
    "sg:tags":[
        "painting",
        "contractor"
    ],
    "wof:name":"Bertholet J",
    "wof:placetype":"venue"
},
  "geometry": {"coordinates":[4.553981781,50.1891975403],"type":"Point"}
}