{
  "type": "Feature",
  "properties": {
    "addr:full":"Wintervijverstraat 31 Gent Oost-Vlaanderen 9052",
    "addr:housenumber":"31",
    "addr:postcode":"9052",
    "addr:street":"Wintervijverstraat;Oost-Vlaanderen",
    "iso:country":"BE",
    "sg:address":"Wintervijverstraat 31",
    "sg:city":"Gent",
    "sg:classifiers":[
        {
            "category":"Arena",
            "subcategory":"Sports Club",
            "type":"Entertainment"
        }
    ],
    "sg:phone":"+32 9 220 03 41",
    "sg:postcode":"9052",
    "sg:province":"Oost-Vlaanderen",
    "sg:tags":[
        "terrain",
        "hors",
        "de",
        "installation",
        "sportifs"
    ],
    "wof:name":"J.v. De Pinte",
    "wof:placetype":"venue"
},
  "geometry": {"coordinates":[3.7167270184,51.0002937317],"type":"Point"}
}