{
  "type": "Feature",
  "properties": {
    "addr:full":"Avenue De Grimberghe 13 Rixensart Brabant Wallon 1330",
    "addr:housenumber":"13",
    "addr:postcode":"1330",
    "addr:street":"Avenue De Grimberghe;Wallon",
    "iso:country":"BE",
    "sg:address":"Avenue De Grimberghe 13",
    "sg:city":"Rixensart",
    "sg:orig_category":"Informaticaconsulenten",
    "sg:phone":"+32 71 87 40 35",
    "sg:postcode":"1330",
    "sg:province":"Brabant Wallon",
    "wof:name":"S 2 L",
    "wof:placetype":"venue"
},
  "geometry": {"coordinates":[4.5197339058,50.7130661011],"type":"Point"}
}