{
  "type": "Feature",
  "properties": {
    "addr:full":"Bremstraat 10 Beringen Limburg 3580",
    "addr:housenumber":"10",
    "addr:postcode":"3580",
    "addr:street":"Bremstraat",
    "iso:country":"BE",
    "sg:address":"Bremstraat 10",
    "sg:city":"Beringen",
    "sg:orig_category":"Boekhouders",
    "sg:phone":"+32 11 42 19 47",
    "sg:postcode":"3580",
    "sg:province":"Limburg",
    "wof:name":"Philippe Marliere",
    "wof:placetype":"venue"
},
  "geometry": {"coordinates":[5.2094240189,51.0638885498],"type":"Point"}
}