{
  "type": "Feature",
  "properties": {
    "iso:country":"BE",
    "sg:address":"Wezelstraat 3",
    "sg:city":"Grimbergen",
    "sg:orig_category":"Plaatsen van vloer- and muurbekleding Schilders",
    "sg:phone":"+32 2 269 14 85",
    "sg:postcode":"1850",
    "sg:province":"Vlaams-Brabant",
    "wof:name":"Monticelli",
    "wof:placetype":"venue"
},
  "geometry": {"coordinates":[4.3678002357,50.9378547668],"type":"Point"}
}