{
  "type": "Feature",
  "properties": {
    "addr:full":"Chauss\u00e9e De Bruxelles 54 Ath Hainaut 7800",
    "addr:housenumber":"54",
    "addr:postcode":"7800",
    "addr:street":"Chausse\u0301E De Bruxelles",
    "iso:country":"BE",
    "sg:address":"Chauss\u00e9e De Bruxelles 54",
    "sg:city":"Ath",
    "sg:classifiers":[
        {
            "category":"Health Services",
            "subcategory":"Health Practitioner",
            "type":"Services"
        }
    ],
    "sg:phone":"+32 68 28 47 65",
    "sg:postcode":"7800",
    "sg:province":"Hainaut",
    "sg:tags":[
        "physiotherapist"
    ],
    "wof:name":"Pieters Damien",
    "wof:placetype":"venue"
},
  "geometry": {"coordinates":[3.7867670059,50.6321182251],"type":"Point"}
}