{
  "type": "Feature",
  "properties": {
    "addr:full":"Wijngaardstraat 33 Lanaken Limburg 3620",
    "addr:housenumber":"33",
    "addr:postcode":"3620",
    "addr:street":"Wijngaardstraat",
    "iso:country":"BE",
    "sg:address":"Wijngaardstraat 33",
    "sg:city":"Lanaken",
    "sg:orig_category":"Sportclubs",
    "sg:phone":"+32 89 71 53 83",
    "sg:postcode":"3620",
    "sg:province":"Limburg",
    "wof:name":"W.s.v. Sappi",
    "wof:placetype":"venue"
},
  "geometry": {"coordinates":[5.6472101212,50.8947105408],"type":"Point"}
}