{
  "type": "Feature",
  "properties": {
    "addr:full":"Rue Des Temples 2 Berloz Li\u00e8ge 4257",
    "addr:housenumber":"2",
    "addr:postcode":"4257",
    "addr:street":"Rue Des Temples",
    "iso:country":"BE",
    "sg:address":"Rue Des Temples 2",
    "sg:city":"Berloz",
    "sg:orig_category":"Postkantoren Verzekeringsmakelaars and experts",
    "sg:phone":"+32 19 32 32 02",
    "sg:postcode":"4257",
    "sg:province":"Li\u00e8ge",
    "wof:name":"La Poste",
    "wof:placetype":"venue"
},
  "geometry": {"coordinates":[5.2093911171,50.7051506042],"type":"Point"}
}