{
  "type": "Feature",
  "properties": {
    "addr:full":"Itali\u00eblei 2 Antwerpen Antwerpen 2000",
    "addr:housenumber":"2",
    "addr:postcode":"2000",
    "addr:street":"Italie\u0308Lei",
    "iso:country":"BE",
    "sg:address":"Itali\u00eblei 2",
    "sg:city":"Antwerpen",
    "sg:classifiers":[
        {
            "category":"Organizations",
            "subcategory":"Political Organization",
            "type":"Services"
        }
    ],
    "sg:phone":"+32 3 205 10 60",
    "sg:postcode":"2000",
    "sg:province":"Antwerpen",
    "sg:tags":[
        "owner",
        "ship"
    ],
    "wof:name":"Cast Agencies Belgium Nv Nv",
    "wof:placetype":"venue"
},
  "geometry": {"coordinates":[4.4126749039,51.2299003601],"type":"Point"}
}