{
  "type": "Feature",
  "properties": {
    "iso:country":"BE",
    "sg:address":"Rue Gachard 10",
    "sg:city":"Elsene/ixelles",
    "sg:orig_category":"Production de films, t\u00e9l\u00e9films and vid\u00e9os. Enregistrements sonores",
    "sg:phone":"+32 2 648 23 45",
    "sg:postcode":"1050",
    "sg:province":"Bruxelles-Capitale",
    "wof:name":"Musica Numeris",
    "wof:placetype":"venue"
},
  "geometry": {"coordinates":[4.3694829941,50.827255249],"type":"Point"}
}