{
  "type": "Feature",
  "properties": {
    "addr:full":"Hasseltweg 340 Genk Limburg 3600",
    "addr:housenumber":"340",
    "addr:postcode":"3600",
    "addr:street":"Hasseltweg",
    "iso:country":"BE",
    "sg:address":"Hasseltweg 340",
    "sg:city":"Genk",
    "sg:classifiers":[
        {
            "category":"Cafe",
            "type":"Food & Drink"
        }
    ],
    "sg:phone":"+32 89 35 91 92",
    "sg:postcode":"3600",
    "sg:province":"Limburg",
    "sg:tags":[
        "caf\u00e9s"
    ],
    "wof:name":"Lord Nelson",
    "wof:placetype":"venue"
},
  "geometry": {"coordinates":[5.4149489403,50.9540367126],"type":"Point"}
}