{
  "type": "Feature",
  "properties": {
    "iso:country":"BE",
    "sg:address":"Rue De Behogne 79",
    "sg:city":"Rochefort",
    "sg:orig_category":"Imprimeries and copyshops. Fournitures de bureau",
    "sg:phone":"+32 84 21 37 17",
    "sg:postcode":"5580",
    "sg:province":"Namur",
    "wof:name":"Librairie Du Pont De Pierre",
    "wof:placetype":"venue"
},
  "geometry": {"coordinates":[5.2202048302,50.1621284485],"type":"Point"}
}