{
  "type": "Feature",
  "properties": {
    "addr:full":"Dr\u00e8ve Aleyde De Brabant 1 Bruxelles (woluwe-saint-pierre) Bruxelles-Capitale 1150",
    "addr:housenumber":"1",
    "addr:postcode":"1150",
    "addr:street":"Dre\u0300Ve Aleyde De Brabant",
    "iso:country":"BE",
    "sg:address":"Dr\u00e8ve Aleyde De Brabant 1",
    "sg:city":"Bruxelles (woluwe-saint-pierre)",
    "sg:classifiers":[
        {
            "category":"Professional",
            "subcategory":"Art Services",
            "type":"Services"
        }
    ],
    "sg:phone":"+32 2 771 98 52",
    "sg:postcode":"1150",
    "sg:province":"Bruxelles-Capitale",
    "sg:tags":[
        "-",
        "valuer"
    ],
    "wof:name":"Arthes Nv",
    "wof:placetype":"venue"
},
  "geometry": {"coordinates":[4.4390969276,50.8247108459],"type":"Point"}
}