{
  "type": "Feature",
  "properties": {
    "addr:full":"Chee.de Bruxelles 25 Forest Bruxelles-Capitale 1190",
    "addr:housenumber":"25",
    "addr:postcode":"1190",
    "iso:country":"BE",
    "sg:address":"Chee.de Bruxelles 25",
    "sg:city":"Forest",
    "sg:classifiers":[
        {
            "category":"Government",
            "subcategory":"Fire Station",
            "type":"Public Place"
        }
    ],
    "sg:phone":"+32 2 376 12 72",
    "sg:postcode":"1190",
    "sg:province":"Bruxelles-Capitale",
    "sg:tags":[
        "packard",
        "nec",
        "bell"
    ],
    "wof:name":"Honhon",
    "wof:placetype":"venue"
},
  "geometry": {"coordinates":[4.3180379868,50.8104171753],"type":"Point"}
}