{
  "type": "Feature",
  "properties": {
    "addr:full":"Avenue De Flor\u00e9al 3 Bruxelles (uccle) Bruxelles-Capitale 1180",
    "addr:housenumber":"3",
    "addr:postcode":"1180",
    "addr:street":"Avenue De Flore\u0301Al",
    "iso:country":"BE",
    "sg:address":"Avenue De Flor\u00e9al 3",
    "sg:city":"Bruxelles (uccle)",
    "sg:classifiers":[
        {
            "category":"Community Center",
            "type":"Public Place"
        }
    ],
    "sg:phone":"+32 2 344 51 68",
    "sg:postcode":"1180",
    "sg:province":"Bruxelles-Capitale",
    "sg:tags":[
        "medical"
    ],
    "wof:name":"Centre Neuro-physiologique Floreal Asbl",
    "wof:placetype":"venue"
},
  "geometry": {"coordinates":[4.3373451233,50.8079681396],"type":"Point"}
}