{
  "type": "Feature",
  "properties": {
    "addr:full":"Kasteelstraat 36b3.2 De Panne West-Vlaanderen 8660",
    "addr:housenumber":"36b3.2",
    "addr:postcode":"8660",
    "addr:street":"Kasteelstraat",
    "iso:country":"BE",
    "sg:address":"Kasteelstraat 36b3.2",
    "sg:city":"De Panne",
    "sg:orig_category":"Gespecialiseerde residenti\u00eble bouw Woningbouw",
    "sg:phone":"+32 58 41 59 68",
    "sg:postcode":"8660",
    "sg:province":"West-Vlaanderen",
    "wof:name":"Wicke Jacky",
    "wof:placetype":"venue"
},
  "geometry": {"coordinates":[2.591561079,51.0975608826],"type":"Point"}
}