{
  "type": "Feature",
  "properties": {
    "addr:full":"Chauss\u00c9e De Waterloo 901 Ukkel/uccle Bruxelles-Capitale 1180",
    "addr:housenumber":"901",
    "addr:postcode":"1180",
    "addr:street":"Chausse\u0301E De Waterloo;/",
    "iso:country":"BE",
    "sg:address":"Chauss\u00c9e De Waterloo 901",
    "sg:city":"Ukkel/uccle",
    "sg:orig_category":"V\u00e9hicules automobiles",
    "sg:phone":"+32 2 374 90 13",
    "sg:postcode":"1180",
    "sg:province":"Bruxelles-Capitale",
    "wof:name":"Fink Car",
    "wof:placetype":"venue"
},
  "geometry": {"coordinates":[4.3703479767,50.8081283569],"type":"Point"}
}