{
  "type": "Feature",
  "properties": {
    "iso:country":"BE",
    "sg:address":"Klerkenstraat 11",
    "sg:city":"Langemark-poelkapelle (langemark)",
    "sg:classifiers":[
        {
            "category":"Professional",
            "subcategory":"Testing Lab",
            "type":"Services"
        }
    ],
    "sg:phone":"+32 57 48 89 75",
    "sg:postcode":"8920",
    "sg:province":"West-Vlaanderen",
    "sg:tags":[
        "chemist"
    ],
    "wof:name":"Apoteek Omnichemie",
    "wof:placetype":"venue"
},
  "geometry": {"coordinates":[2.9296720028,50.9334259033],"type":"Point"}
}