{
  "type": "Feature",
  "properties": {
    "addr:full":"Gasthuisstraat 69 Geraardsbergen Oost-Vlaanderen 9500",
    "addr:housenumber":"69",
    "addr:postcode":"9500",
    "addr:street":"Gasthuisstraat",
    "iso:country":"BE",
    "sg:address":"Gasthuisstraat 69",
    "sg:city":"Geraardsbergen",
    "sg:classifiers":[
        {
            "category":"Personal",
            "subcategory":"Beauty Salon",
            "type":"Services"
        }
    ],
    "sg:phone":"+32 54 42 28 00",
    "sg:postcode":"9500",
    "sg:province":"Oost-Vlaanderen",
    "wof:name":"Twins",
    "wof:placetype":"venue"
},
  "geometry": {"coordinates":[3.8764419556,50.7700996399],"type":"Point"}
}