{
  "type": "Feature",
  "properties": {
    "iso:country":"BE",
    "sg:address":"Begijnenstraat 36",
    "sg:city":"Diest",
    "sg:classifiers":[
        {
            "category":"Health Services",
            "subcategory":"Dentist",
            "type":"Services"
        }
    ],
    "sg:phone":"+32 13 33 84 40",
    "sg:postcode":"3290",
    "sg:province":"Vlaams-Brabant",
    "wof:name":"Aussems Sara",
    "wof:placetype":"venue"
},
  "geometry": {"coordinates":[5.0584139824,50.9878540039],"type":"Point"}
}