{
  "type": "Feature",
  "properties": {
    "iso:country":"BE",
    "sg:address":"Assenois 44",
    "sg:city":"Vaux-sur-sure",
    "sg:orig_category":"Voedingsspeciaalzaken",
    "sg:phone":"+32 61 26 64 24",
    "sg:postcode":"6640",
    "sg:province":"Luxembourg",
    "wof:name":"Marie-therese Henquinet",
    "wof:placetype":"venue"
},
  "geometry": {"coordinates":[5.5671000481,49.91065979],"type":"Point"}
}