{
  "type": "Feature",
  "properties": {
    "addr:full":"Muldersdreef 41 Sint-martens-latem (deurle) Oost-Vlaanderen 9831",
    "addr:housenumber":"41",
    "addr:postcode":"9831",
    "addr:street":"Muldersdreef",
    "iso:country":"BE",
    "sg:address":"Muldersdreef 41",
    "sg:city":"Sint-martens-latem (deurle)",
    "sg:classifiers":[
        {
            "category":"Real Estate",
            "subcategory":"Architect",
            "type":"Services"
        }
    ],
    "sg:phone":"+32 9 282 64 04",
    "sg:postcode":"9831",
    "sg:province":"Oost-Vlaanderen",
    "wof:name":"Content M",
    "wof:placetype":"venue"
},
  "geometry": {"coordinates":[3.6152501106,51.006061554],"type":"Point"}
}