{
  "type": "Feature",
  "properties": {
    "addr:full":"Rue D'anderlecht 102b6 Brussel/bruxelles Bruxelles-Capitale 1000",
    "addr:housenumber":"102b6",
    "addr:postcode":"1000",
    "addr:street":"Rue D'Anderlecht;/",
    "iso:country":"BE",
    "sg:address":"Rue D'anderlecht 102b6",
    "sg:city":"Brussel/bruxelles",
    "sg:orig_category":"Epiceries",
    "sg:phone":"+32 2 512 32 88",
    "sg:postcode":"1000",
    "sg:province":"Bruxelles-Capitale",
    "wof:name":"Triphon Jacobs",
    "wof:placetype":"venue"
},
  "geometry": {"coordinates":[4.3446140289,50.8455314636],"type":"Point"}
}