{
  "type": "Feature",
  "properties": {
    "iso:country":"BE",
    "sg:address":"Oostendestraat 33-35",
    "sg:city":"Diksmuide",
    "sg:orig_category":"Betonnen bouwelementen Fab Plaatsen van vloer- and muurbekleding Stortklaar beton Fab Vloer- and muu",
    "sg:phone":"+32 51 50 00 67",
    "sg:postcode":"8600",
    "sg:province":"West-Vlaanderen",
    "wof:name":"Germain Vinckier",
    "wof:placetype":"venue"
},
  "geometry": {"coordinates":[2.8661830425,51.03931427],"type":"Point"}
}