{
  "type": "Feature",
  "properties": {
    "iso:country":"BE",
    "sg:address":"Wechelsebaan 107",
    "sg:city":"Lille",
    "sg:orig_category":"Entretien and r\u00e9parations de voitures",
    "sg:phone":"+32 14 88 13 62",
    "sg:postcode":"2275",
    "sg:province":"Antwerpen",
    "wof:name":"Garage Raeymaekers",
    "wof:placetype":"venue"
},
  "geometry": {"coordinates":[4.8165397644,51.2503547668],"type":"Point"}
}