{
  "type": "Feature",
  "properties": {
    "addr:full":"Avenue Du Silence 45 Ukkel/uccle Bruxelles-Capitale 1180",
    "addr:housenumber":"45",
    "addr:postcode":"1180",
    "addr:street":"Avenue Du Silence;/",
    "iso:country":"BE",
    "sg:address":"Avenue Du Silence 45",
    "sg:city":"Ukkel/uccle",
    "sg:classifiers":[
        {
            "category":"Cafe",
            "type":"Food & Drink"
        }
    ],
    "sg:phone":"+32 2 332 16 74",
    "sg:postcode":"1180",
    "sg:province":"Bruxelles-Capitale",
    "sg:tags":[
        "caf\u00e9s"
    ],
    "wof:name":"Caf\u00c9 La Pompe \u00c0 Eau",
    "wof:placetype":"venue"
},
  "geometry": {"coordinates":[4.3292098045,50.7841567993],"type":"Point"}
}