{
  "type": "Feature",
  "properties": {
    "iso:country":"BE",
    "sg:address":"Rue Delfosse 4",
    "sg:city":"Frasnes-lez-anvaing (frasnes - Lez - Buissenal)",
    "sg:classifiers":[
        {
            "category":"Health Services",
            "subcategory":"Health Practitioner",
            "type":"Services"
        }
    ],
    "sg:phone":"+32 69 86 84 99",
    "sg:postcode":"7911",
    "sg:province":"Hainaut",
    "sg:tags":[
        "physiotherapist"
    ],
    "wof:name":"Raynal Patrice",
    "wof:placetype":"venue"
},
  "geometry": {"coordinates":[3.6238200665,50.6890182495],"type":"Point"}
}