{
  "type": "Feature",
  "properties": {
    "addr:full":"Onze-lieve-vrouwestraat 12 Zutendaal Limburg 3690",
    "addr:housenumber":"12",
    "addr:postcode":"3690",
    "addr:street":"Onze-Lieve-Vrouwestraat",
    "iso:country":"BE",
    "sg:address":"Onze-lieve-vrouwestraat 12",
    "sg:city":"Zutendaal",
    "sg:classifiers":[
        {
            "category":"Food & Beverages",
            "subcategory":"Fruits & Vegetables",
            "type":"Retail Goods"
        }
    ],
    "sg:phone":"+32 89 61 50 61",
    "sg:postcode":"3690",
    "sg:province":"Limburg",
    "sg:tags":[
        "-"
    ],
    "wof:name":"De Druivelaar",
    "wof:placetype":"venue"
},
  "geometry": {"coordinates":[5.5695500374,50.9327278137],"type":"Point"}
}