{
  "type": "Feature",
  "properties": {
    "addr:full":"Barastraat 8 Anderlecht Bruxelles-Capitale 1070",
    "addr:housenumber":"8",
    "addr:postcode":"1070",
    "addr:street":"Barastraat",
    "iso:country":"BE",
    "sg:address":"Barastraat 8",
    "sg:city":"Anderlecht",
    "sg:classifiers":[
        {
            "category":"Manufacturing",
            "subcategory":"Textiles",
            "type":"Manufacturing & Wholesale Goods"
        }
    ],
    "sg:phone":"+32 2 524 10 52",
    "sg:postcode":"1070",
    "sg:province":"Bruxelles-Capitale",
    "sg:tags":[
        "fab",
        "diverse",
        "textielproducten"
    ],
    "wof:name":"Colin Desreumaux",
    "wof:placetype":"venue"
},
  "geometry": {"coordinates":[4.3362078667,50.8396720886],"type":"Point"}
}