{
  "type": "Feature",
  "properties": {
    "iso:country":"BE",
    "sg:address":"Poelstraat 125",
    "sg:city":"Deinze (petegem-aan-de-leie)",
    "sg:classifiers":[
        {
            "category":"Wholesale",
            "subcategory":"Books, Periodicals, & Newspapers",
            "type":"Manufacturing & Wholesale Goods"
        }
    ],
    "sg:phone":"+32 9 380 05 00",
    "sg:postcode":"9800",
    "sg:province":"Oost-Vlaanderen",
    "sg:tags":[
        "banner"
    ],
    "wof:name":"Publi Dema Bvba",
    "wof:placetype":"venue"
},
  "geometry": {"coordinates":[3.54103899,50.9765853882],"type":"Point"}
}