{
  "type": "Feature",
  "properties": {
    "iso:country":"BE",
    "sg:address":"Rue Du Pape 3",
    "sg:city":"Beauraing",
    "sg:classifiers":[
        {
            "category":"Retail",
            "subcategory":"Animal Services",
            "type":"Services"
        }
    ],
    "sg:phone":"+32 82 71 44 98",
    "sg:postcode":"5570",
    "sg:province":"Namur",
    "sg:tags":[
        "grooming",
        "-",
        "dog"
    ],
    "wof:name":"Cani'coiff",
    "wof:placetype":"venue"
},
  "geometry": {"coordinates":[4.9576058388,50.1117591858],"type":"Point"}
}