{
  "type": "Feature",
  "properties": {
    "iso:country":"BE",
    "sg:address":"Kleempoelstraat 19",
    "sg:city":"Zemst",
    "sg:orig_category":"Artistes ind\u00e9pendants",
    "sg:phone":"+32 15 61 59 67",
    "sg:postcode":"1980",
    "sg:province":"Vlaams-Brabant",
    "wof:name":"Tine Deboosere",
    "wof:placetype":"venue"
},
  "geometry": {"coordinates":[4.4563889503,50.9871406555],"type":"Point"}
}