{
  "type": "Feature",
  "properties": {
    "addr:full":"Blaesstraat 160 Brussel Bruxelles-Capitale 1000",
    "addr:housenumber":"160",
    "addr:postcode":"1000",
    "addr:street":"Blaesstraat",
    "iso:country":"BE",
    "sg:address":"Blaesstraat 160",
    "sg:city":"Brussel",
    "sg:classifiers":[
        {
            "category":"Restaurant",
            "type":"Food & Drink"
        }
    ],
    "sg:phone":"+32 2 511 38 97",
    "sg:postcode":"1000",
    "sg:province":"Bruxelles-Capitale",
    "wof:name":"Indigo",
    "wof:placetype":"venue"
},
  "geometry": {"coordinates":[4.3472828865,50.8375320435],"type":"Point"}
}