{
  "type": "Feature",
  "properties": {
    "addr:full":"Muizendale 2 Nevele Oost-Vlaanderen 9850",
    "addr:housenumber":"2",
    "addr:postcode":"9850",
    "addr:street":"Muizendale",
    "iso:country":"BE",
    "sg:address":"Muizendale 2",
    "sg:city":"Nevele",
    "sg:orig_category":"Ecoles de pilotage de bateaux and d\u00b4avions. Transports a\u00e9riens r\u00e9guliers",
    "sg:phone":"+32 9 371 52 92",
    "sg:postcode":"9850",
    "sg:province":"Oost-Vlaanderen",
    "wof:name":"Walair Flying School",
    "wof:placetype":"venue"
},
  "geometry": {"coordinates":[3.5760529041,51.0675392151],"type":"Point"}
}