{
  "type": "Feature",
  "properties": {
    "addr:full":"Memlingdreef 37 Overijse Vlaams-Brabant 3090",
    "addr:housenumber":"37",
    "addr:postcode":"3090",
    "addr:street":"Memlingdreef",
    "iso:country":"BE",
    "sg:address":"Memlingdreef 37",
    "sg:city":"Overijse",
    "sg:classifiers":[
        {
            "category":"Professional",
            "subcategory":"Management & Consulting",
            "type":"Services"
        }
    ],
    "sg:phone":"+32 2 688 27 26",
    "sg:postcode":"3090",
    "sg:province":"Vlaams-Brabant",
    "sg:tags":[
        "-",
        "processing",
        "data",
        "consultant"
    ],
    "wof:name":"Easylog Sprl",
    "wof:placetype":"venue"
},
  "geometry": {"coordinates":[4.5049228668,50.7898597717],"type":"Point"}
}