{
  "type": "Feature",
  "properties": {
    "iso:country":"BE",
    "sg:address":"Aarschotseweg 30",
    "sg:city":"Herentals",
    "sg:orig_category":"Benzinestations and brandstoffen Herstellingen and onderhoud van auto's",
    "sg:phone":"+32 14 22 10 23",
    "sg:postcode":"2200",
    "sg:province":"Antwerpen",
    "wof:name":"Andy",
    "wof:placetype":"venue"
},
  "geometry": {"coordinates":[4.8461208344,51.1597671509],"type":"Point"}
}