{
  "type": "Feature",
  "properties": {
    "addr:full":"Filips Van Arteveldestr. 5 Gent Oost-Vlaanderen 9000",
    "addr:housenumber":"5",
    "addr:postcode":"9000",
    "addr:street":"Filips Van Arteveldestr.;Oost-Vlaanderen",
    "iso:country":"BE",
    "sg:address":"Filips Van Arteveldestr. 5",
    "sg:city":"Gent",
    "sg:orig_category":"Architectes",
    "sg:phone":"+32 9 234 04 50",
    "sg:postcode":"9000",
    "sg:province":"Oost-Vlaanderen",
    "wof:name":"Michael De Spiegelaere",
    "wof:placetype":"venue"
},
  "geometry": {"coordinates":[3.7349460125,51.0506896973],"type":"Point"}
}