{
  "type": "Feature",
  "properties": {
    "addr:full":"Rue Haute 18 Ath Hainaut 7800",
    "addr:housenumber":"18",
    "addr:postcode":"7800",
    "addr:street":"Rue Haute",
    "iso:country":"BE",
    "sg:address":"Rue Haute 18",
    "sg:city":"Ath",
    "sg:orig_category":"Maisons de repos and r\u00e9sidences",
    "sg:phone":"+32 68 28 00 32",
    "sg:postcode":"7800",
    "sg:province":"Hainaut",
    "wof:name":"R\u00c9sidence Les Glycines",
    "wof:placetype":"venue"
},
  "geometry": {"coordinates":[3.77967906,50.6296005249],"type":"Point"}
}