{
  "type": "Feature",
  "properties": {
    "iso:country":"BE",
    "sg:address":"Langendam 64bd",
    "sg:city":"Evergem",
    "sg:orig_category":"Plaatsen van vloer- and muurbekleding Schilders",
    "sg:phone":"+32 9 357 68 26",
    "sg:postcode":"9940",
    "sg:province":"Oost-Vlaanderen",
    "wof:name":"Frank Geurs",
    "wof:placetype":"venue"
},
  "geometry": {"coordinates":[3.6561889648,51.137638092],"type":"Point"}
}