{
  "type": "Feature",
  "properties": {
    "addr:full":"Rue Du Moulin 12 Li\u00e8ge 1 (bressoux) Li\u00e8ge 4020",
    "addr:housenumber":"12;1",
    "addr:postcode":"4020",
    "addr:street":"Rue Du Moulin",
    "iso:country":"BE",
    "sg:address":"Rue Du Moulin 12",
    "sg:city":"Li\u00e8ge 1 (bressoux)",
    "sg:classifiers":[
        {
            "category":"Health Services",
            "subcategory":"Dentist",
            "type":"Services"
        }
    ],
    "sg:phone":"+32 4 342 77 40",
    "sg:postcode":"4020",
    "sg:province":"Li\u00e8ge",
    "wof:name":"Altaep Wadah",
    "wof:placetype":"venue"
},
  "geometry": {"coordinates":[5.5937571526,50.6404800415],"type":"Point"}
}