{
  "type": "Feature",
  "properties": {
    "iso:country":"BE",
    "sg:address":"Iepenlaan 14",
    "sg:city":"Temse",
    "sg:classifiers":[
        {
            "category":"Cafe",
            "type":"Food & Drink"
        }
    ],
    "sg:phone":"+32 3 771 40 62",
    "sg:postcode":"9140",
    "sg:province":"Oost-Vlaanderen",
    "sg:tags":[
        "caf\u00e9s"
    ],
    "wof:name":"Linda Pilaet",
    "wof:placetype":"venue"
},
  "geometry": {"coordinates":[4.186645031,51.1203994751],"type":"Point"}
}