{
  "type": "Feature",
  "properties": {
    "iso:country":"BE",
    "sg:address":"Rue D'aix-la-chapelle 102",
    "sg:city":"Raeren/raeren",
    "sg:classifiers":[
        {
            "category":"Restaurant",
            "type":"Food & Drink"
        }
    ],
    "sg:phone":"+32 87 65 84 62",
    "sg:postcode":"4731",
    "sg:province":"Li\u00e8ge",
    "wof:name":"Wally Stop",
    "wof:placetype":"venue"
},
  "geometry": {"coordinates":[6.0926098824,50.6976699829],"type":"Point"}
}