{
  "type": "Feature",
  "properties": {
    "addr:full":"Molenstraat 7 Hamme (moerzeke) Oost-Vlaanderen 9220",
    "addr:housenumber":"7",
    "addr:postcode":"9220",
    "addr:street":"Molenstraat",
    "iso:country":"BE",
    "sg:address":"Molenstraat 7",
    "sg:city":"Hamme (moerzeke)",
    "sg:orig_category":"Newspapers, magazines, periodicals - Publishers",
    "sg:phone":"+32 52 47 81 95",
    "sg:postcode":"9220",
    "sg:province":"Oost-Vlaanderen",
    "wof:name":"De Stem Uit Moerzeke",
    "wof:placetype":"venue"
},
  "geometry": {"coordinates":[4.1513018608,51.0622711182],"type":"Point"}
}