{
  "type": "Feature",
  "properties": {
    "addr:full":"Noordkaai 26 Izegem West-Vlaanderen 8870",
    "addr:housenumber":"26",
    "addr:postcode":"8870",
    "addr:street":"Noordkaai",
    "iso:country":"BE",
    "sg:address":"Noordkaai 26",
    "sg:city":"Izegem",
    "sg:orig_category":"Herstellingen and onderhoud van auto's",
    "sg:phone":"+32 9 345 08 93",
    "sg:postcode":"8870",
    "sg:province":"West-Vlaanderen",
    "wof:name":"Dimant N.v.",
    "wof:placetype":"venue"
},
  "geometry": {"coordinates":[3.1849400997,50.9305114746],"type":"Point"}
}