{
  "type": "Feature",
  "properties": {
    "iso:country":"BE",
    "sg:address":"Rue Jean-d\u00b4outremeuse 72",
    "sg:city":"Li\u00c8ge",
    "sg:orig_category":"Installatie van metalen schrijnwerk Metaalbehandeling and -bekleding",
    "sg:phone":"+32 4 349 17 30",
    "sg:postcode":"4020",
    "sg:province":"Li\u00e8ge",
    "wof:name":"Velden Fr\u00c8res",
    "wof:placetype":"venue"
},
  "geometry": {"coordinates":[5.5861048698,50.6408729553],"type":"Point"}
}