{
  "type": "Feature",
  "properties": {
    "addr:full":"Weversstraat 80 Meerhout Antwerpen 2450",
    "addr:housenumber":"80",
    "addr:postcode":"2450",
    "addr:street":"Weversstraat",
    "iso:country":"BE",
    "sg:address":"Weversstraat 80",
    "sg:city":"Meerhout",
    "sg:classifiers":[
        {
            "category":"Retail",
            "subcategory":"Animal Services",
            "type":"Services"
        }
    ],
    "sg:phone":"+32 14 30 81 08",
    "sg:postcode":"2450",
    "sg:province":"Antwerpen",
    "sg:tags":[
        "breeding",
        "selling",
        "-",
        "dog"
    ],
    "wof:name":"Daems",
    "wof:placetype":"venue"
},
  "geometry": {"coordinates":[5.0875768661,51.1301727295],"type":"Point"}
}