{
  "type": "Feature",
  "properties": {
    "iso:country":"BE",
    "sg:address":"Brusselsesteenweg 31",
    "sg:city":"Tervuren",
    "sg:classifiers":[
        {
            "category":"Fast Food",
            "type":"Food & Drink"
        }
    ],
    "sg:phone":"+32 2 767 56 72",
    "sg:postcode":"3080",
    "sg:province":"Vlaams-Brabant",
    "sg:tags":[
        "meeneem",
        "restaurant"
    ],
    "wof:name":"Kwong-chow",
    "wof:placetype":"venue"
},
  "geometry": {"coordinates":[4.5106520653,50.8246383667],"type":"Point"}
}