{
  "type": "Feature",
  "properties": {
    "iso:country":"BE",
    "sg:address":"Stokerijstraat 30",
    "sg:city":"Wijnegem",
    "sg:orig_category":"Technische studies and ingenieursactiviteiten",
    "sg:phone":"+32 3 353 39 16",
    "sg:postcode":"2110",
    "sg:province":"Antwerpen",
    "wof:name":"C.z.e.",
    "wof:placetype":"venue"
},
  "geometry": {"coordinates":[4.5346298218,51.2267532349],"type":"Point"}
}