{
  "type": "Feature",
  "properties": {
    "addr:full":"Chauss\u00c9e De Charleroi 85 Namur Namur 5000",
    "addr:housenumber":"85",
    "addr:postcode":"5000",
    "addr:street":"Chausse\u0301E De Charleroi",
    "iso:country":"BE",
    "sg:address":"Chauss\u00c9e De Charleroi 85",
    "sg:city":"Namur",
    "sg:orig_category":"Enseignement sup\u00e9rieur",
    "sg:phone":"+32 81 73 53 69",
    "sg:postcode":"5000",
    "sg:province":"Namur",
    "wof:name":"Ecole Infirm.& D\u00b4accouch.",
    "wof:placetype":"venue"
},
  "geometry": {"coordinates":[4.8401441574,50.4614830017],"type":"Point"}
}