{
  "type": "Feature",
  "properties": {
    "addr:full":"Marnixlaan 12a Brussel/bruxelles Bruxelles-Capitale 1000",
    "addr:housenumber":"12a",
    "addr:postcode":"1000",
    "addr:street":"Marnixlaan;/",
    "iso:country":"BE",
    "sg:address":"Marnixlaan 12a",
    "sg:city":"Brussel/bruxelles",
    "sg:orig_category":"Catering and organisatie van feesten Fast food and meeneem restaurants Levering aan huis restaurants",
    "sg:phone":"+32 2 513 58 66",
    "sg:postcode":"1000",
    "sg:province":"Bruxelles-Capitale",
    "wof:name":"Restaurant Champ De Mars",
    "wof:placetype":"venue"
},
  "geometry": {"coordinates":[4.3631658554,50.8386497498],"type":"Point"}
}