{
  "type": "Feature",
  "properties": {
    "addr:full":"Rue Haute 111 Sambreville Namur 5060",
    "addr:housenumber":"111",
    "addr:postcode":"5060",
    "addr:street":"Rue Haute",
    "iso:country":"BE",
    "sg:address":"Rue Haute 111",
    "sg:city":"Sambreville",
    "sg:orig_category":"Kapsalons",
    "sg:phone":"+32 71 77 82 09",
    "sg:postcode":"5060",
    "sg:province":"Namur",
    "wof:name":"Antoinette Battilomo",
    "wof:placetype":"venue"
},
  "geometry": {"coordinates":[4.6285200119,50.4448738098],"type":"Point"}
}