{
  "type": "Feature",
  "properties": {
    "addr:full":"Eeuwfeestlaan 254 Lier Antwerpen 2500",
    "addr:housenumber":"254",
    "addr:postcode":"2500",
    "addr:street":"Eeuwfeestlaan",
    "iso:country":"BE",
    "sg:address":"Eeuwfeestlaan 254",
    "sg:city":"Lier",
    "sg:classifiers":[
        {
            "category":"Health Services",
            "subcategory":"Health Practitioner",
            "type":"Services"
        }
    ],
    "sg:phone":"+32 3 480 38 71",
    "sg:postcode":"2500",
    "sg:province":"Antwerpen",
    "sg:tags":[
        "physiotherapist"
    ],
    "wof:name":"Blaton Jo",
    "wof:placetype":"venue"
},
  "geometry": {"coordinates":[4.5709490776,51.1394691467],"type":"Point"}
}