{
  "type": "Feature",
  "properties": {
    "addr:full":"Rue G\u00c9n\u00c9ral Leman 7 Jemappes Hainaut 7012",
    "addr:housenumber":"7",
    "addr:postcode":"7012",
    "addr:street":"Rue Ge\u0301Ne\u0301Ral Leman;Hainaut",
    "iso:country":"BE",
    "sg:address":"Rue G\u00c9n\u00c9ral Leman 7",
    "sg:city":"Jemappes",
    "sg:orig_category":"Microsoft. Ordinateurs and \u00e9quipement informatique",
    "sg:phone":"+32 65 88 51 00",
    "sg:postcode":"7012",
    "sg:province":"Hainaut",
    "wof:name":"Netconsult",
    "wof:placetype":"venue"
},
  "geometry": {"coordinates":[3.891865015,50.4486656189],"type":"Point"}
}