{
  "type": "Feature",
  "properties": {
    "iso:country":"BE",
    "sg:address":"Kapelstraat 31ba",
    "sg:city":"Boutersem",
    "sg:orig_category":"Artsen and specialisten",
    "sg:phone":"+32 16 73 34 88",
    "sg:postcode":"3370",
    "sg:province":"Vlaams-Brabant",
    "wof:name":"A. Beelen",
    "wof:placetype":"venue"
},
  "geometry": {"coordinates":[4.8529858589,50.8473472595],"type":"Point"}
}