{
  "type": "Feature",
  "properties": {
    "addr:full":"Amandinaweg 40 Herk-de-stad Limburg 3540",
    "addr:housenumber":"40",
    "addr:postcode":"3540",
    "addr:street":"Amandinaweg",
    "iso:country":"BE",
    "sg:address":"Amandinaweg 40",
    "sg:city":"Herk-de-stad",
    "sg:orig_category":"Producteurs de fruits",
    "sg:phone":"+32 13 55 11 81",
    "sg:postcode":"3540",
    "sg:province":"Limburg",
    "wof:name":"Joseph Raskin",
    "wof:placetype":"venue"
},
  "geometry": {"coordinates":[5.1967658997,50.9161338806],"type":"Point"}
}