{
  "type": "Feature",
  "properties": {
    "addr:full":"Ave Des Arts 35 Bruxelles Bruxelles-Capitale 1040",
    "addr:housenumber":"35",
    "addr:postcode":"1040",
    "addr:street":"Ave Des Arts",
    "iso:country":"BE",
    "sg:address":"Ave Des Arts 35",
    "sg:city":"Bruxelles",
    "sg:classifiers":[
        {
            "category":"Banks & Credit Unions",
            "subcategory":"Bank",
            "type":"Services"
        }
    ],
    "sg:phone":"+32 16 24 24 05",
    "sg:postcode":"1040",
    "sg:province":"Bruxelles-Capitale",
    "wof:name":"Mrbb Cv",
    "wof:placetype":"venue"
},
  "geometry": {"coordinates":[4.6964907646,50.8777923584],"type":"Point"}
}