{
  "type": "Feature",
  "properties": {
    "addr:full":"Lege Moerstraat 26 Sint-laureins Oost-Vlaanderen 9980",
    "addr:housenumber":"26",
    "addr:postcode":"9980",
    "addr:street":"Lege Moerstraat",
    "iso:country":"BE",
    "sg:address":"Lege Moerstraat 26",
    "sg:city":"Sint-laureins",
    "sg:classifiers":[
        {
            "category":"Restaurant",
            "type":"Food & Drink"
        }
    ],
    "sg:phone":"+32 9 377 78 31",
    "sg:postcode":"9980",
    "sg:province":"Oost-Vlaanderen",
    "wof:name":"Slependamme",
    "wof:placetype":"venue"
},
  "geometry": {"coordinates":[3.5849759579,51.2272224426],"type":"Point"}
}