{
  "type": "Feature",
  "properties": {
    "iso:country":"BE",
    "sg:address":"Sint-blasiusstraat 11 A",
    "sg:city":"Rumbeke",
    "sg:orig_category":"Meubelzaken, woning- and keukeninrichting",
    "sg:phone":"+32 51 20 33 55",
    "sg:postcode":"8800",
    "sg:province":"West-Vlaanderen",
    "wof:name":"Zit- En Slaapcomfort Verbeest",
    "wof:placetype":"venue"
},
  "geometry": {"coordinates":[3.1511120796,50.9348487854],"type":"Point"}
}