{
  "type": "Feature",
  "properties": {
    "addr:full":"Bouwelsesteenweg 182 Nijlen Antwerpen 2560",
    "addr:housenumber":"182",
    "addr:postcode":"2560",
    "addr:street":"Bouwelsesteenweg",
    "iso:country":"BE",
    "sg:address":"Bouwelsesteenweg 182",
    "sg:city":"Nijlen",
    "sg:orig_category":"Epiceries",
    "sg:phone":"+32 3 481 81 92",
    "sg:postcode":"2560",
    "sg:province":"Antwerpen",
    "wof:name":"E. Sterckx",
    "wof:placetype":"venue"
},
  "geometry": {"coordinates":[4.6935019493,51.1650314331],"type":"Point"}
}