{
  "type": "Feature",
  "properties": {
    "addr:full":"Zeelsebaan 83w Dendermonde Oost-Vlaanderen 9200",
    "addr:housenumber":"83w",
    "addr:postcode":"9200",
    "addr:street":"Zeelsebaan;Oost-Vlaanderen",
    "iso:country":"BE",
    "sg:address":"Zeelsebaan 83w",
    "sg:city":"Dendermonde",
    "sg:classifiers":[
        {
            "category":"Professional",
            "subcategory":"Engineering",
            "type":"Services"
        }
    ],
    "sg:phone":"+32 52 25 03 50",
    "sg:postcode":"9200",
    "sg:province":"Oost-Vlaanderen",
    "sg:tags":[
        "machine",
        "-",
        "mechanical"
    ],
    "wof:name":"Sander Nv",
    "wof:placetype":"venue"
},
  "geometry": {"coordinates":[4.0910840034,51.046421051],"type":"Point"}
}