{
  "type": "Feature",
  "properties": {
    "iso:country":"BE",
    "sg:address":"Botermarkt 22",
    "sg:city":"Hasselt",
    "sg:orig_category":"V\u00eatements pour Hommes",
    "sg:phone":"+32 11 21 41 81",
    "sg:postcode":"3500",
    "sg:province":"Limburg",
    "wof:name":"Antares Sportswear",
    "wof:placetype":"venue"
},
  "geometry": {"coordinates":[5.3387670517,50.9306335449],"type":"Point"}
}