{
  "type": "Feature",
  "properties": {
    "addr:full":"Rue Albert I 20 Fleurus (lambusart) Hainaut 6220",
    "addr:housenumber":"20",
    "addr:postcode":"6220",
    "addr:street":"Rue Albert I",
    "iso:country":"BE",
    "sg:address":"Rue Albert I 20",
    "sg:city":"Fleurus (lambusart)",
    "sg:classifiers":[
        {
            "category":"Bars & Pubs",
            "type":"Food & Drink"
        }
    ],
    "sg:phone":"+32 71 81 58 79",
    "sg:postcode":"6220",
    "sg:province":"Hainaut",
    "wof:name":"Bienvenu (le)",
    "wof:placetype":"venue"
},
  "geometry": {"coordinates":[4.50025177,50.4469566345],"type":"Point"}
}