{
  "type": "Feature",
  "properties": {
    "addr:full":"Rue De Tournai 30d Mons (ghlin) Hainaut 7011",
    "addr:housenumber":"30d",
    "addr:postcode":"7011",
    "addr:street":"Rue De Tournai",
    "iso:country":"BE",
    "sg:address":"Rue De Tournai 30d",
    "sg:city":"Mons (ghlin)",
    "sg:classifiers":[
        {
            "category":"Building & Trades",
            "subcategory":"Construction",
            "type":"Services"
        }
    ],
    "sg:phone":"+32 65 33 87 36",
    "sg:postcode":"7011",
    "sg:province":"Hainaut",
    "sg:tags":[
        "ecological"
    ],
    "wof:name":"Rogowski G",
    "wof:placetype":"venue"
},
  "geometry": {"coordinates":[3.912539959,50.4712982178],"type":"Point"}
}