{
  "type": "Feature",
  "properties": {
    "addr:full":"Roosendaalsebaan 86 Kalmthout Antwerpen 2920",
    "addr:housenumber":"86",
    "addr:postcode":"2920",
    "addr:street":"Roosendaalsebaan",
    "iso:country":"BE",
    "sg:address":"Roosendaalsebaan 86",
    "sg:city":"Kalmthout",
    "sg:classifiers":[
        {
            "category":"Arena",
            "subcategory":"Sports Club",
            "type":"Entertainment"
        }
    ],
    "sg:phone":"+32 3 666 52 06",
    "sg:postcode":"2920",
    "sg:province":"Antwerpen",
    "sg:tags":[
        "de"
    ],
    "wof:name":"Duikklub Sea Eagles",
    "wof:placetype":"venue"
},
  "geometry": {"coordinates":[4.4969539642,51.410823822],"type":"Point"}
}