{
  "type": "Feature",
  "properties": {
    "iso:country":"BE",
    "sg:address":"Parochiestraat 54",
    "sg:city":"Denderleeuw",
    "sg:orig_category":"Artsen and specialisten",
    "sg:phone":"+32 53 67 31 33",
    "sg:postcode":"9472",
    "sg:province":"Oost-Vlaanderen",
    "wof:name":"Koen Jourquin",
    "wof:placetype":"venue"
},
  "geometry": {"coordinates":[4.0521378517,50.8737068176],"type":"Point"}
}