{
  "type": "Feature",
  "properties": {
    "iso:country":"BE",
    "sg:address":"Akkerstraat 24",
    "sg:city":"Hooglede",
    "sg:orig_category":"Boekhouders",
    "sg:phone":"+32 51 20 23 34",
    "sg:postcode":"8830",
    "sg:province":"West-Vlaanderen",
    "wof:name":"Luc Desimpel",
    "wof:placetype":"venue"
},
  "geometry": {"coordinates":[3.0701320171,50.9805030823],"type":"Point"}
}