{
  "type": "Feature",
  "properties": {
    "addr:full":"Rue De Mons 1 Estinnes (estinnes-au-val) Hainaut 7120",
    "addr:housenumber":"1",
    "addr:postcode":"7120",
    "addr:street":"Rue De Mons",
    "iso:country":"BE",
    "sg:address":"Rue De Mons 1",
    "sg:city":"Estinnes (estinnes-au-val)",
    "sg:classifiers":[
        {
            "category":"Manufacturing",
            "subcategory":"Textiles",
            "type":"Manufacturing & Wholesale Goods"
        }
    ],
    "sg:phone":"+32 64 36 69 45",
    "sg:postcode":"7120",
    "sg:province":"Hainaut",
    "sg:tags":[
        "retail",
        "-"
    ],
    "wof:name":"Planet Megastore",
    "wof:placetype":"venue"
},
  "geometry": {"coordinates":[4.1322259903,50.4197845459],"type":"Point"}
}