{
  "type": "Feature",
  "properties": {
    "addr:full":"Grand\u00b4rue 185 Charleroi Hainaut 6000",
    "addr:housenumber":"185",
    "addr:postcode":"6000",
    "addr:street":"Hainaut",
    "iso:country":"BE",
    "sg:address":"Grand\u00b4rue 185",
    "sg:city":"Charleroi",
    "sg:orig_category":"Volwassenenonderwijs",
    "sg:phone":"+32 71 41 39 39",
    "sg:postcode":"6000",
    "sg:province":"Hainaut",
    "wof:name":"Coll\u00c8ge Technique",
    "wof:placetype":"venue"
},
  "geometry": {"coordinates":[4.4591989517,50.4211502075],"type":"Point"}
}