{
  "type": "Feature",
  "properties": {
    "iso:country":"BE",
    "sg:address":"Stationsstraat 56",
    "sg:city":"Kluisbergen",
    "sg:orig_category":"Quincaillerie Gr",
    "sg:phone":"+32 55 38 80 44",
    "sg:postcode":"9690",
    "sg:province":"Oost-Vlaanderen",
    "wof:name":"D'huyvetter",
    "wof:placetype":"venue"
},
  "geometry": {"coordinates":[3.511111021,50.788394928],"type":"Point"}
}