{
  "type": "Feature",
  "properties": {
    "addr:full":"Den Abt 105 Beerse (vlimmeren) Antwerpen 2340",
    "addr:housenumber":"105",
    "addr:postcode":"2340",
    "addr:street":"Den Abt",
    "iso:country":"BE",
    "sg:address":"Den Abt 105",
    "sg:city":"Beerse (vlimmeren)",
    "sg:classifiers":[
        {
            "category":"Home & Garden",
            "subcategory":"Home Furnishings",
            "type":"Retail Goods"
        }
    ],
    "sg:phone":"+32 3 312 37 53",
    "sg:postcode":"2340",
    "sg:province":"Antwerpen",
    "sg:tags":[
        "interior",
        "decoration"
    ],
    "wof:name":"Vds Decor",
    "wof:placetype":"venue"
},
  "geometry": {"coordinates":[4.7871699333,51.3127975464],"type":"Point"}
}