{
  "type": "Feature",
  "properties": {
    "iso:country":"BE",
    "sg:address":"Zeypestraat 35",
    "sg:city":"Kampenhout",
    "sg:classifiers":[
        {
            "category":"Personal",
            "subcategory":"Beauty Salon",
            "type":"Services"
        }
    ],
    "sg:phone":"+32 16 65 63 63",
    "sg:postcode":"1910",
    "sg:province":"Vlaams-Brabant",
    "sg:tags":[
        "de",
        "coiffure"
    ],
    "wof:name":"Ernest Degreef",
    "wof:placetype":"venue"
},
  "geometry": {"coordinates":[4.5649261475,50.9476852417],"type":"Point"}
}