{
  "type": "Feature",
  "properties": {
    "iso:country":"BE",
    "sg:address":"Ijzerlaan 23",
    "sg:city":"Gent",
    "sg:classifiers":[
        {
            "category":"Insurance",
            "subcategory":"Life Insurance",
            "type":"Services"
        }
    ],
    "sg:phone":"+32 9 224 06 79",
    "sg:postcode":"9000",
    "sg:province":"Oost-Vlaanderen",
    "sg:tags":[
        "assurance"
    ],
    "wof:name":"Verschoore & Casier",
    "wof:placetype":"venue"
},
  "geometry": {"coordinates":[3.719135046,51.0422286987],"type":"Point"}
}