{
  "type": "Feature",
  "properties": {
    "addr:full":"Neerweg 23 Heist-op-den-berg Antwerpen 2220",
    "addr:housenumber":"23",
    "addr:postcode":"2220",
    "addr:street":"Neerweg",
    "iso:country":"BE",
    "sg:address":"Neerweg 23",
    "sg:city":"Heist-op-den-berg",
    "sg:classifiers":[
        {
            "category":"Personal",
            "subcategory":"Beauty Salon",
            "type":"Services"
        }
    ],
    "sg:phone":"+32 15 24 70 72",
    "sg:postcode":"2220",
    "sg:province":"Antwerpen",
    "sg:tags":[
        "lady",
        "-",
        "hairdressing"
    ],
    "wof:name":"Nicole",
    "wof:placetype":"venue"
},
  "geometry": {"coordinates":[4.7197561264,51.0787773132],"type":"Point"}
}