{
  "type": "Feature",
  "properties": {
    "addr:full":"Itterplein 24 Bree Limburg 3960",
    "addr:housenumber":"24",
    "addr:postcode":"3960",
    "addr:street":"Itterplein",
    "iso:country":"BE",
    "sg:address":"Itterplein 24",
    "sg:city":"Bree",
    "sg:orig_category":"Banken and kredietinstellingen",
    "sg:phone":"+32 89 86 55 52",
    "sg:postcode":"3960",
    "sg:province":"Limburg",
    "wof:name":"Kbc",
    "wof:placetype":"venue"
},
  "geometry": {"coordinates":[5.5944190025,51.1405677795],"type":"Point"}
}