{
  "type": "Feature",
  "properties": {
    "iso:country":"BE",
    "sg:address":"Grand Rue 71",
    "sg:city":"Mons",
    "sg:classifiers":[
        {
            "category":"Shopping",
            "subcategory":"Florist",
            "type":"Retail Goods"
        }
    ],
    "sg:phone":"+32 65 33 71 89",
    "sg:postcode":"7000",
    "sg:province":"Hainaut",
    "wof:name":"Floribel",
    "wof:placetype":"venue"
},
  "geometry": {"coordinates":[3.9496428967,50.4502830505],"type":"Point"}
}