{
  "type": "Feature",
  "properties": {
    "addr:full":"Idyllestraat 18 Sint-jans-molenbeek/molenbeek-saint-jean Bruxelles-Capitale 1080",
    "addr:housenumber":"18",
    "addr:postcode":"1080",
    "addr:street":"Idyllestraat",
    "iso:country":"BE",
    "sg:address":"Idyllestraat 18",
    "sg:city":"Sint-jans-molenbeek/molenbeek-saint-jean",
    "sg:orig_category":"Artsen and specialisten",
    "sg:phone":"+32 2 411 55 95",
    "sg:postcode":"1080",
    "sg:province":"Bruxelles-Capitale",
    "wof:name":"Norbert Van Osselt",
    "wof:placetype":"venue"
},
  "geometry": {"coordinates":[4.2972998619,50.849521637],"type":"Point"}
}