{
  "type": "Feature",
  "properties": {
    "addr:full":"Monnikenwerve 167 Brugge West-Vlaanderen 8000",
    "addr:housenumber":"167",
    "addr:postcode":"8000",
    "addr:street":"Monnikenwerve",
    "iso:country":"BE",
    "sg:address":"Monnikenwerve 167",
    "sg:city":"Brugge",
    "sg:orig_category":"Fujitsu Siemens. Ordinateurs and \u00e9quipement informatique",
    "sg:phone":"+32 50 31 70 70",
    "sg:postcode":"8000",
    "sg:province":"West-Vlaanderen",
    "wof:name":"Pdp",
    "wof:placetype":"venue"
},
  "geometry": {"coordinates":[3.2043468952,51.2462043762],"type":"Point"}
}