{
  "type": "Feature",
  "properties": {
    "iso:country":"BE",
    "sg:address":"Rue Henry De Rohan Chabot 1",
    "sg:city":"Florennes",
    "sg:classifiers":[
        {
            "category":"Bars & Pubs",
            "type":"Food & Drink"
        }
    ],
    "sg:phone":"+32 71 68 94 50",
    "sg:postcode":"5620",
    "sg:province":"Namur",
    "wof:name":"Tour Effel",
    "wof:placetype":"venue"
},
  "geometry": {"coordinates":[4.6073131561,50.2491607666],"type":"Point"}
}