{
  "type": "Feature",
  "properties": {
    "iso:country":"BE",
    "sg:address":"Bakvoordestraat 36",
    "sg:city":"Torhout",
    "sg:orig_category":"Non-Classified Establishments",
    "sg:phone":"+32 51 72 26 24",
    "sg:postcode":"8820",
    "sg:province":"West-Vlaanderen",
    "wof:name":"Real Import-export Bvba",
    "wof:placetype":"venue"
},
  "geometry": {"coordinates":[3.0939199924,51.0282897949],"type":"Point"}
}