{
  "type": "Feature",
  "properties": {
    "iso:country":"BE",
    "sg:address":"Tivolilaan 98",
    "sg:city":"Mechelen",
    "sg:orig_category":"Experts-comptables",
    "sg:phone":"+32 15 20 17 12",
    "sg:postcode":"2800",
    "sg:province":"Antwerpen",
    "wof:name":"Guido Noeth",
    "wof:placetype":"venue"
},
  "geometry": {"coordinates":[4.477039814,51.0476608276],"type":"Point"}
}