{
  "type": "Feature",
  "properties": {
    "iso:country":"BE",
    "sg:address":"Rue De Mont 8",
    "sg:city":"Rue De Mont 8",
    "sg:orig_category":"Diverse zakelijke dienstverlening",
    "sg:phone":"+32 83 21 67 08",
    "sg:postcode":"5590",
    "sg:province":"Namur",
    "wof:name":"Z\u00c9nith Event Agency",
    "wof:placetype":"venue"
},
  "geometry": {"coordinates":[5.0649871826,50.3120574951],"type":"Point"}
}