{
  "type": "Feature",
  "properties": {
    "iso:country":"BE",
    "sg:address":"Rue De La Station 25",
    "sg:city":"Manage (bois-d'haine)",
    "sg:orig_category":"Solar protection - Outside",
    "sg:phone":"+32 64 55 62 58",
    "sg:postcode":"7170",
    "sg:province":"Hainaut",
    "wof:name":"Centrale Wallonne D'isolation",
    "wof:placetype":"venue"
},
  "geometry": {"coordinates":[4.2116770744,50.4924125671],"type":"Point"}
}