{
  "type": "Feature",
  "properties": {
    "addr:full":"Plein 114 Kaprijke Oost-Vlaanderen 9970",
    "addr:housenumber":"114",
    "addr:postcode":"9970",
    "addr:street":"Plein",
    "iso:country":"BE",
    "sg:address":"Plein 114",
    "sg:city":"Kaprijke",
    "sg:orig_category":"Banken and kredietinstellingen",
    "sg:phone":"+32 9 373 73 61",
    "sg:postcode":"9970",
    "sg:province":"Oost-Vlaanderen",
    "wof:name":"V.d.k. Spaarbank",
    "wof:placetype":"venue"
},
  "geometry": {"coordinates":[3.6181631088,51.2176589966],"type":"Point"}
}