{
  "type": "Feature",
  "properties": {
    "iso:country":"BE",
    "sg:address":"Rue L\u00c9opold 15",
    "sg:city":"Gembloux",
    "sg:orig_category":"S\u00e9curit\u00e9 sociale",
    "sg:phone":"+32 477 31 87 48",
    "sg:postcode":"5030",
    "sg:province":"Namur",
    "wof:name":"Mutualit\u00c9 Neutre",
    "wof:placetype":"venue"
},
  "geometry": {"coordinates":[4.6928119659,50.5599784851],"type":"Point"}
}