{
  "type": "Feature",
  "properties": {
    "addr:full":"Rue Paul Janson 54 Anderlues Hainaut 6150",
    "addr:housenumber":"54",
    "addr:postcode":"6150",
    "addr:street":"Rue Paul Janson",
    "iso:country":"BE",
    "sg:address":"Rue Paul Janson 54",
    "sg:city":"Anderlues",
    "sg:orig_category":"Fietsen Herstellingen motorfietsen Motorfietsen",
    "sg:phone":"+32 71 52 37 01",
    "sg:postcode":"6150",
    "sg:province":"Hainaut",
    "wof:name":"Ets. Lef\u00c8vre",
    "wof:placetype":"venue"
},
  "geometry": {"coordinates":[4.275042057,50.4046363831],"type":"Point"}
}