{
  "type": "Feature",
  "properties": {
    "addr:full":"Geerdegemstraat 31 Mechelen Antwerpen 2800",
    "addr:housenumber":"31",
    "addr:postcode":"2800",
    "addr:street":"Geerdegemstraat",
    "iso:country":"BE",
    "sg:address":"Geerdegemstraat 31",
    "sg:city":"Mechelen",
    "sg:classifiers":[
        {
            "category":"Professional",
            "subcategory":"Art Services",
            "type":"Services"
        }
    ],
    "sg:phone":"+32 15 41 20 10",
    "sg:postcode":"2800",
    "sg:province":"Antwerpen",
    "sg:tags":[
        "technical",
        "photographer",
        "industrial",
        "-"
    ],
    "wof:name":"Van Den Brande Dries",
    "wof:placetype":"venue"
},
  "geometry": {"coordinates":[4.4745588303,51.0190162659],"type":"Point"}
}