{
  "type": "Feature",
  "properties": {
    "iso:country":"BE",
    "sg:address":"Rue Burenville 23",
    "sg:city":"Li\u00c8ge",
    "sg:orig_category":"Apotheken",
    "sg:phone":"+32 4 226 14 78",
    "sg:postcode":"4000",
    "sg:province":"Li\u00e8ge",
    "wof:name":"Brigitte Jeangette",
    "wof:placetype":"venue"
},
  "geometry": {"coordinates":[5.5473070145,50.6404647827],"type":"Point"}
}