{
  "type": "Feature",
  "properties": {
    "iso:country":"BE",
    "sg:address":"Chemin Des Bigaudes 48",
    "sg:city":"Ath",
    "sg:orig_category":"Eleveurs de bovins",
    "sg:phone":"+32 68 64 51 07",
    "sg:postcode":"7812",
    "sg:province":"Hainaut",
    "wof:name":"Paulette Dubrule",
    "wof:placetype":"venue"
},
  "geometry": {"coordinates":[3.7285408974,50.6608695984],"type":"Point"}
}