{
  "type": "Feature",
  "properties": {
    "iso:country":"BE",
    "sg:address":"Kosterstraat 28",
    "sg:city":"Linter (drieslinter)",
    "sg:classifiers":[
        {
            "category":"Personal",
            "subcategory":"Nail Salon",
            "type":"Services"
        }
    ],
    "sg:phone":"+32 477 58 57 66",
    "sg:postcode":"3350",
    "sg:province":"Vlaams-Brabant",
    "sg:tags":[
        "pedicure"
    ],
    "wof:name":"Debroeck K",
    "wof:placetype":"venue"
},
  "geometry": {"coordinates":[5.0539698601,50.845489502],"type":"Point"}
}