{
  "type": "Feature",
  "properties": {
    "addr:full":"Rue Du Luxembourg 7 Mouscron Hainaut 7700",
    "addr:housenumber":"7",
    "addr:postcode":"7700",
    "addr:street":"Rue Du Luxembourg",
    "iso:country":"BE",
    "sg:address":"Rue Du Luxembourg 7",
    "sg:city":"Mouscron",
    "sg:classifiers":[
        {
            "category":"Food & Beverages",
            "subcategory":"Liquor & Beverages",
            "type":"Retail Goods"
        }
    ],
    "sg:phone":"+32 56 33 49 08",
    "sg:postcode":"7700",
    "sg:province":"Hainaut",
    "sg:tags":[
        "-",
        "spirit",
        "wine"
    ],
    "wof:name":"De Lille",
    "wof:placetype":"venue"
},
  "geometry": {"coordinates":[3.2176039219,50.7429771423],"type":"Point"}
}