{
  "type": "Feature",
  "properties": {
    "addr:full":"Smisstraat 16 Riemst Limburg 3770",
    "addr:housenumber":"16",
    "addr:postcode":"3770",
    "addr:street":"Smisstraat",
    "iso:country":"BE",
    "sg:address":"Smisstraat 16",
    "sg:city":"Riemst",
    "sg:orig_category":"Apotheken",
    "sg:phone":"+32 12 45 21 56",
    "sg:postcode":"3770",
    "sg:province":"Limburg",
    "wof:name":"Jackers",
    "wof:placetype":"venue"
},
  "geometry": {"coordinates":[5.5914731026,50.8334732056],"type":"Point"}
}