{
  "type": "Feature",
  "properties": {
    "iso:country":"BE",
    "sg:address":"Avenue De Montalembert 35",
    "sg:city":"Rixensart",
    "sg:orig_category":"M\u00e9decins and sp\u00e9cialistes",
    "sg:phone":"+32 2 653 97 45",
    "sg:postcode":"1330",
    "sg:province":"Brabant Wallon",
    "wof:name":"Christine Hansen",
    "wof:placetype":"venue"
},
  "geometry": {"coordinates":[4.5236978531,50.7086029053],"type":"Point"}
}