{
  "type": "Feature",
  "properties": {
    "iso:country":"BE",
    "sg:address":"Sint-kristinastraat 1",
    "sg:city":"Sint-truiden",
    "sg:orig_category":"Fruitteelt",
    "sg:phone":"+32 11 68 81 86",
    "sg:postcode":"3800",
    "sg:province":"Limburg",
    "wof:name":"Theophile Benaets",
    "wof:placetype":"venue"
},
  "geometry": {"coordinates":[5.2228307724,50.8010635376],"type":"Point"}
}