{
  "type": "Feature",
  "properties": {
    "addr:full":"Waverse Steenweg 99 Elsene/ixelles Bruxelles-Capitale 1050",
    "addr:housenumber":"99",
    "addr:postcode":"1050",
    "addr:street":"Waverse Steenweg",
    "iso:country":"BE",
    "sg:address":"Waverse Steenweg 99",
    "sg:city":"Elsene/ixelles",
    "sg:orig_category":"Artsen and specialisten",
    "sg:phone":"+32 2 502 05 82",
    "sg:postcode":"1050",
    "sg:province":"Bruxelles-Capitale",
    "wof:name":"Fr\u00c9d\u00c9ric Jouvin",
    "wof:placetype":"venue"
},
  "geometry": {"coordinates":[4.3670129776,50.8363418579],"type":"Point"}
}