{
  "type": "Feature",
  "properties": {
    "iso:country":"BE",
    "sg:address":"Remoifosse 7ba",
    "sg:city":"Bastogne",
    "sg:orig_category":"Rundveehouders",
    "sg:phone":"+32 61 21 22 18",
    "sg:postcode":"6600",
    "sg:province":"Luxembourg",
    "wof:name":"Emile Thiry",
    "wof:placetype":"venue"
},
  "geometry": {"coordinates":[5.7158799171,49.9662704468],"type":"Point"}
}