{
  "type": "Feature",
  "properties": {
    "iso:country":"BE",
    "sg:address":"Louis Sauvestrelaan 78",
    "sg:city":"Beringen",
    "sg:classifiers":[
        {
            "category":"Arena",
            "subcategory":"Sports Club",
            "type":"Entertainment"
        }
    ],
    "sg:phone":"+32 477 25 62 64",
    "sg:postcode":"3581",
    "sg:province":"Limburg",
    "sg:tags":[
        "terrain",
        "hors",
        "de",
        "installation",
        "sportifs"
    ],
    "wof:name":"Turkse Fc",
    "wof:placetype":"venue"
},
  "geometry": {"coordinates":[5.2276721001,51.0786857605],"type":"Point"}
}