{
  "type": "Feature",
  "properties": {
    "addr:full":"Rue De La Croix 37 Namur Namur 5000",
    "addr:housenumber":"37",
    "addr:postcode":"5000",
    "addr:street":"Rue De La Croix",
    "iso:country":"BE",
    "sg:address":"Rue De La Croix 37",
    "sg:city":"Namur",
    "sg:classifiers":[
        {
            "category":"Shopping",
            "subcategory":"Clothing, Apparel, & Fashions",
            "type":"Retail Goods"
        }
    ],
    "sg:phone":"+32 81 24 15 72",
    "sg:postcode":"5000",
    "sg:province":"Namur",
    "sg:tags":[
        "lady",
        "clothing",
        "-"
    ],
    "wof:name":"Reflet Dore",
    "wof:placetype":"venue"
},
  "geometry": {"coordinates":[4.8641238213,50.4635276794],"type":"Point"}
}