{
  "type": "Feature",
  "properties": {
    "iso:country":"BE",
    "sg:address":"Rue De La Gare 73",
    "sg:city":"Braine-le-comte",
    "sg:orig_category":"Artiesten and kunstenaars",
    "sg:phone":"+32 67 63 67 95",
    "sg:postcode":"7090",
    "sg:province":"Hainaut",
    "wof:name":"Roger Fierain",
    "wof:placetype":"venue"
},
  "geometry": {"coordinates":[4.1777691841,50.6511497498],"type":"Point"}
}