{
  "type": "Feature",
  "properties": {
    "iso:country":"BE",
    "sg:address":"Rue De Bruxelles 45",
    "sg:city":"Mouscron",
    "sg:classifiers":[
        {
            "category":"Insurance",
            "subcategory":"Insurance Agent",
            "type":"Services"
        }
    ],
    "sg:phone":"+32 56 33 39 51",
    "sg:postcode":"7700",
    "sg:province":"Hainaut",
    "sg:tags":[
        "broker"
    ],
    "wof:name":"Nuttin & Carrette",
    "wof:placetype":"venue"
},
  "geometry": {"coordinates":[3.2131309509,50.7452163696],"type":"Point"}
}