{
  "type": "Feature",
  "properties": {
    "addr:full":"Rue De La Fronti\u00c8re 98 Dour Hainaut 7370",
    "addr:housenumber":"98",
    "addr:postcode":"7370",
    "addr:street":"Rue De La Frontie\u0300Re;Hainaut",
    "iso:country":"BE",
    "sg:address":"Rue De La Fronti\u00c8re 98",
    "sg:city":"Dour",
    "sg:orig_category":"Banken and kredietinstellingen",
    "sg:phone":"+32 65 65 36 41",
    "sg:postcode":"7370",
    "sg:province":"Hainaut",
    "wof:name":"Cr\u00c9dit Professionnel",
    "wof:placetype":"venue"
},
  "geometry": {"coordinates":[3.8100130558,50.3713035583],"type":"Point"}
}