{
  "type": "Feature",
  "properties": {
    "iso:country":"BE",
    "sg:address":"Rue Des Potiats 3",
    "sg:city":"Ch\u00c2telet",
    "sg:orig_category":"Plomberie, chauffage and installations sanitaires",
    "sg:phone":"+32 71 38 17 04",
    "sg:postcode":"6200",
    "sg:province":"Hainaut",
    "wof:name":"Fe. Willaert",
    "wof:placetype":"venue"
},
  "geometry": {"coordinates":[4.5163202286,50.3903198242],"type":"Point"}
}