{
  "type": "Feature",
  "properties": {
    "addr:full":"Rozenstraat 14 Hooglede West-Vlaanderen 8830",
    "addr:housenumber":"14",
    "addr:postcode":"8830",
    "addr:street":"Rozenstraat",
    "iso:country":"BE",
    "sg:address":"Rozenstraat 14",
    "sg:city":"Hooglede",
    "sg:classifiers":[
        {
            "category":"Community Center",
            "subcategory":"Social",
            "type":"Public Place"
        }
    ],
    "sg:phone":"+32 51 20 06 09",
    "sg:postcode":"8830",
    "sg:province":"West-Vlaanderen",
    "sg:tags":[
        "-",
        "haute",
        "clothing",
        "couture"
    ],
    "wof:name":"Verhelst C",
    "wof:placetype":"venue"
},
  "geometry": {"coordinates":[3.0870881081,50.9808197021],"type":"Point"}
}