{
  "type": "Feature",
  "properties": {
    "iso:country":"BE",
    "sg:address":"Huisepontweg 54",
    "sg:city":"Nazareth",
    "sg:classifiers":[
        {
            "category":"Shopping",
            "subcategory":"Antiques",
            "type":"Retail Goods"
        }
    ],
    "sg:phone":"+32 9 380 45 81",
    "sg:postcode":"9810",
    "sg:province":"Oost-Vlaanderen",
    "sg:tags":[
        "restoration"
    ],
    "wof:name":"Monville A",
    "wof:placetype":"venue"
},
  "geometry": {"coordinates":[3.5719389915,50.9377365112],"type":"Point"}
}