{
  "type": "Feature",
  "properties": {
    "iso:country":"BE",
    "sg:address":"Diestsesteenweg 119",
    "sg:city":"Leuven",
    "sg:classifiers":[
        {
            "category":"Restaurant",
            "type":"Food & Drink"
        }
    ],
    "sg:phone":"+32 16 25 99 53",
    "sg:postcode":"3010",
    "sg:province":"Vlaams-Brabant",
    "wof:name":"Mei-mei",
    "wof:placetype":"venue"
},
  "geometry": {"coordinates":[4.7097921371,50.8857421875],"type":"Point"}
}