{
  "type": "Feature",
  "properties": {
    "iso:country":"BE",
    "sg:address":"Rue Des Moulins 40",
    "sg:city":"Beyne-heusay",
    "sg:classifiers":[
        {
            "category":"Restaurant",
            "type":"Food & Drink"
        }
    ],
    "sg:phone":"+32 4 362 83 75",
    "sg:postcode":"4610",
    "sg:province":"Li\u00e8ge",
    "wof:name":"Restaurant Amon Nos Hotes",
    "wof:placetype":"venue"
},
  "geometry": {"coordinates":[5.6643519402,50.6332397461],"type":"Point"}
}