{
  "type": "Feature",
  "properties": {
    "iso:country":"BE",
    "sg:address":"Marktplein 52",
    "sg:city":"Sint-lievens-houtem",
    "sg:classifiers":[
        {
            "category":"Shopping",
            "subcategory":"Stationery & Office Supplies",
            "type":"Retail Goods"
        }
    ],
    "sg:phone":"+32 53 62 10 53",
    "sg:postcode":"9520",
    "sg:province":"Oost-Vlaanderen",
    "wof:name":"Ypsillon",
    "wof:placetype":"venue"
},
  "geometry": {"coordinates":[3.8561470509,50.9207801819],"type":"Point"}
}