{
  "type": "Feature",
  "properties": {
    "addr:full":"Everestraat 2 Zaventem Vlaams-Brabant 1932",
    "addr:housenumber":"2",
    "addr:postcode":"1932",
    "addr:street":"Everestraat",
    "iso:country":"BE",
    "sg:address":"Everestraat 2",
    "sg:city":"Zaventem",
    "sg:classifiers":[
        {
            "category":"Restaurant",
            "type":"Food & Drink"
        }
    ],
    "sg:phone":"+32 2 720 17 06",
    "sg:postcode":"1932",
    "sg:province":"Vlaams-Brabant",
    "wof:name":"Sol-mar",
    "wof:placetype":"venue"
},
  "geometry": {"coordinates":[4.4452381134,50.8669662476],"type":"Point"}
}