{
  "type": "Feature",
  "properties": {
    "addr:full":"Bouchebelle Erf 15 Moeskroen/mouscron Hainaut 7700",
    "addr:housenumber":"15",
    "addr:postcode":"7700",
    "addr:street":"Bouchebelle Erf",
    "iso:country":"BE",
    "sg:address":"Bouchebelle Erf 15",
    "sg:city":"Moeskroen/mouscron",
    "sg:orig_category":"Elektrische installaties voor woningen",
    "sg:phone":"+32 56 34 62 06",
    "sg:postcode":"7700",
    "sg:province":"Hainaut",
    "wof:name":"Guy Vanhamme",
    "wof:placetype":"venue"
},
  "geometry": {"coordinates":[3.2323200703,50.7400932312],"type":"Point"}
}