{
  "type": "Feature",
  "properties": {
    "addr:full":"Koralenhoeve 10 Wommelgem Antwerpen 2160",
    "addr:housenumber":"10",
    "addr:postcode":"2160",
    "addr:street":"Koralenhoeve",
    "iso:country":"BE",
    "sg:address":"Koralenhoeve 10",
    "sg:city":"Wommelgem",
    "sg:classifiers":[
        {
            "category":"Wholesale",
            "subcategory":"Vending Machines",
            "type":"Manufacturing & Wholesale Goods"
        }
    ],
    "sg:phone":"+32 3 355 15 35",
    "sg:postcode":"2160",
    "sg:province":"Antwerpen",
    "sg:tags":[
        "labeling"
    ],
    "wof:name":"Bopack (bopack Systems)",
    "wof:placetype":"venue"
},
  "geometry": {"coordinates":[4.5228691101,51.2103996277],"type":"Point"}
}