{
  "type": "Feature",
  "properties": {
    "iso:country":"BE",
    "sg:address":"Rue Pierre Hans 89",
    "sg:city":"Charleroi",
    "sg:orig_category":"Dakwerken",
    "sg:phone":"+32 71 30 14 68",
    "sg:postcode":"6031",
    "sg:province":"Hainaut",
    "wof:name":"Fe. Roussel-oerlemans",
    "wof:placetype":"venue"
},
  "geometry": {"coordinates":[4.3715481758,50.4151344299],"type":"Point"}
}