{
  "type": "Feature",
  "properties": {
    "addr:full":"Kempenarestraat 50a Box 5 Sint-katelijne-waver Antwerpen 2860",
    "addr:housenumber":"50a box 5",
    "addr:postcode":"2860",
    "addr:street":"Kempenarestraat",
    "iso:country":"BE",
    "sg:address":"Kempenarestraat 50a Box 5",
    "sg:city":"Sint-katelijne-waver",
    "sg:classifiers":[
        {
            "category":"Wholesale",
            "subcategory":"Fruits & Vegetables",
            "type":"Manufacturing & Wholesale Goods"
        }
    ],
    "sg:phone":"+32 15 56 07 56",
    "sg:postcode":"2860",
    "sg:province":"Antwerpen",
    "sg:tags":[
        "whol",
        "-"
    ],
    "wof:name":"Unidis-alimo",
    "wof:placetype":"venue"
},
  "geometry": {"coordinates":[4.5203351974,51.062171936],"type":"Point"}
}