{
  "type": "Feature",
  "properties": {
    "iso:country":"BE",
    "sg:address":"Brusselsesteenweg 33",
    "sg:city":"Meise",
    "sg:orig_category":"Kantoormateriaal Krantenwinkels Rookartikelen Speelgoed",
    "sg:phone":"+32 2 269 27 25",
    "sg:postcode":"1860",
    "sg:province":"Vlaams-Brabant",
    "wof:name":"Callebaut",
    "wof:placetype":"venue"
},
  "geometry": {"coordinates":[4.3273501396,50.9340782166],"type":"Point"}
}