{
  "type": "Feature",
  "properties": {
    "iso:country":"BE",
    "sg:address":"Rue De Borlon 11",
    "sg:city":"Somme-leuze (bonsin)",
    "sg:classifiers":[
        {
            "category":"Professional",
            "subcategory":"Accounting & Tax Preparation",
            "type":"Services"
        }
    ],
    "sg:phone":"+32 86 34 45 34",
    "sg:postcode":"5377",
    "sg:province":"Namur",
    "sg:tags":[
        "bookkeeper"
    ],
    "wof:name":"Willeme H",
    "wof:placetype":"venue"
},
  "geometry": {"coordinates":[5.3698949814,50.3404350281],"type":"Point"}
}