{
  "type": "Feature",
  "properties": {
    "iso:country":"BE",
    "sg:address":"Rue Reppe 3",
    "sg:city":"Andenne (seilles)",
    "sg:classifiers":[
        {
            "category":"Manufacturing",
            "subcategory":"Tools & Machinery",
            "type":"Manufacturing & Wholesale Goods"
        }
    ],
    "sg:phone":"+32 85 82 58 54",
    "sg:postcode":"5300",
    "sg:province":"Namur",
    "sg:tags":[
        "cast",
        "iron"
    ],
    "wof:name":"Fonderies Lecomte Sa",
    "wof:placetype":"venue"
},
  "geometry": {"coordinates":[5.0995202065,50.4812812805],"type":"Point"}
}