{
  "type": "Feature",
  "properties": {
    "addr:full":"Route D'esneux 87 Neupr\u00e9 (neuville-en-condroz) Li\u00e8ge 4121",
    "addr:housenumber":"87",
    "addr:postcode":"4121",
    "addr:street":"Route D'Esneux",
    "iso:country":"BE",
    "sg:address":"Route D'esneux 87",
    "sg:city":"Neupr\u00e9 (neuville-en-condroz)",
    "sg:classifiers":[
        {
            "category":"Health Services",
            "subcategory":"Doctor",
            "type":"Services"
        }
    ],
    "sg:phone":"+32 4 372 09 59",
    "sg:postcode":"4121",
    "sg:province":"Li\u00e8ge",
    "sg:tags":[
        "medicinephysicians",
        "surgeon"
    ],
    "wof:name":"Dubuisson A",
    "wof:placetype":"venue"
},
  "geometry": {"coordinates":[5.458671093,50.5439529419],"type":"Point"}
}