{
  "type": "Feature",
  "properties": {
    "addr:full":"Steegstraat 53 Balen Antwerpen 2490",
    "addr:housenumber":"53",
    "addr:postcode":"2490",
    "addr:street":"Steegstraat",
    "iso:country":"BE",
    "sg:address":"Steegstraat 53",
    "sg:city":"Balen",
    "sg:orig_category":"Reisbureaus",
    "sg:phone":"+32 14 82 98 61",
    "sg:postcode":"2490",
    "sg:province":"Antwerpen",
    "wof:name":"De Blauwvoet",
    "wof:placetype":"venue"
},
  "geometry": {"coordinates":[5.1718959808,51.1684341431],"type":"Point"}
}