{
  "type": "Feature",
  "properties": {
    "iso:country":"BE",
    "sg:address":"Place Charles-bergh 1",
    "sg:city":"Neufchateau",
    "sg:orig_category":"Openbare bibliotheken and archieven",
    "sg:phone":"+32 61 27 88 67",
    "sg:postcode":"6840",
    "sg:province":"Luxembourg",
    "wof:name":"Biblioth\u00c8que Publique",
    "wof:placetype":"venue"
},
  "geometry": {"coordinates":[5.4353051186,49.8418273926],"type":"Point"}
}