{
  "type": "Feature",
  "properties": {
    "addr:full":"Groenstraat 70 Houthalen-helchteren (houthalen) Limburg 3530",
    "addr:housenumber":"70",
    "addr:postcode":"3530",
    "addr:street":"Groenstraat",
    "iso:country":"BE",
    "sg:address":"Groenstraat 70",
    "sg:city":"Houthalen-helchteren (houthalen)",
    "sg:classifiers":[
        {
            "category":"Shopping",
            "subcategory":"Bicycles & Sporting Goods",
            "type":"Retail Goods"
        }
    ],
    "sg:phone":"+32 475 93 96 27",
    "sg:postcode":"3530",
    "sg:province":"Limburg",
    "sg:tags":[
        "tyre"
    ],
    "wof:name":"Diroco International Bvba",
    "wof:placetype":"venue"
},
  "geometry": {"coordinates":[5.3880858421,51.0294647217],"type":"Point"}
}