{
  "type": "Feature",
  "properties": {
    "addr:full":"Rue Du Mont 26 Saint-hubert Luxembourg 6870",
    "addr:housenumber":"26",
    "addr:postcode":"6870",
    "addr:street":"Rue Du Mont",
    "iso:country":"BE",
    "sg:address":"Rue Du Mont 26",
    "sg:city":"Saint-hubert",
    "sg:classifiers":[
        {
            "category":"Autos & Motor Vehicles",
            "subcategory":"Motorcycle Sales",
            "type":"Retail Goods"
        }
    ],
    "sg:phone":"+32 61 61 25 41",
    "sg:postcode":"6870",
    "sg:province":"Luxembourg",
    "sg:tags":[
        "motorbike"
    ],
    "wof:name":"Pecheur Jean-claude",
    "wof:placetype":"venue"
},
  "geometry": {"coordinates":[5.3745379448,50.0246925354],"type":"Point"}
}