{
  "type": "Feature",
  "properties": {
    "iso:country":"BE",
    "sg:address":"Stationsstraat 61",
    "sg:city":"Liedekerke",
    "sg:orig_category":"Services Erotiques et d'Escorte",
    "sg:phone":"+32 473 38 46 21",
    "sg:postcode":"1770",
    "sg:province":"Vlaams-Brabant",
    "wof:name":"Escort Man & Vrouw",
    "wof:placetype":"venue"
},
  "geometry": {"coordinates":[4.0848398209,50.8728942871],"type":"Point"}
}