{
  "type": "Feature",
  "properties": {
    "addr:full":"Rue D'en Haut 5 Lessines Hainaut 7864",
    "addr:housenumber":"5",
    "addr:postcode":"7864",
    "addr:street":"Rue D'En Haut;Hainaut",
    "iso:country":"BE",
    "sg:address":"Rue D'en Haut 5",
    "sg:city":"Lessines",
    "sg:orig_category":"Herstellingen and onderhoud van auto's",
    "sg:phone":"+32 68 33 75 73",
    "sg:postcode":"7864",
    "sg:province":"Hainaut",
    "wof:name":"Garage Hugo D'hollander",
    "wof:placetype":"venue"
},
  "geometry": {"coordinates":[1.6273139715,50.2169342041],"type":"Point"}
}