{
  "type": "Feature",
  "properties": {
    "iso:country":"BE",
    "sg:address":"Chauss\u00c9e Romaine 10",
    "sg:city":"Etalle",
    "sg:orig_category":"Woningbouw",
    "sg:phone":"+32 63 45 55 79",
    "sg:postcode":"6740",
    "sg:province":"Luxembourg",
    "wof:name":"Fran\u00c7ois L\u00c9onard",
    "wof:placetype":"venue"
},
  "geometry": {"coordinates":[5.5699081421,49.6704711914],"type":"Point"}
}