{
  "type": "Feature",
  "properties": {
    "addr:full":"Turnhoutsebaan 98 Dessel Antwerpen 2480",
    "addr:housenumber":"98",
    "addr:postcode":"2480",
    "addr:street":"Turnhoutsebaan",
    "iso:country":"BE",
    "sg:address":"Turnhoutsebaan 98",
    "sg:city":"Dessel",
    "sg:orig_category":"Varkenskwekers",
    "sg:phone":"+32 14 37 10 94",
    "sg:postcode":"2480",
    "sg:province":"Antwerpen",
    "wof:name":"Gustaaf Van Wuytswinkel",
    "wof:placetype":"venue"
},
  "geometry": {"coordinates":[5.1094322205,51.2458953857],"type":"Point"}
}