{
  "type": "Feature",
  "properties": {
    "iso:country":"BE",
    "sg:address":"Rue Laixheau 29",
    "sg:city":"Herstal",
    "sg:orig_category":"V\u00eatements sur mesure Fab",
    "sg:phone":"+32 4 264 03 38",
    "sg:postcode":"4040",
    "sg:province":"Li\u00e8ge",
    "wof:name":"Maison Bertrand",
    "wof:placetype":"venue"
},
  "geometry": {"coordinates":[5.6287212372,50.6666488647],"type":"Point"}
}