{
  "type": "Feature",
  "properties": {
    "iso:country":"BE",
    "sg:address":"Avenue Du Fusain 47",
    "sg:city":"Brussel/bruxelles",
    "sg:orig_category":"Instituts de beaut\u00e9. Centres de relaxation and bien-\u00eatre",
    "sg:phone":"+32 2 268 30 48",
    "sg:postcode":"1020",
    "sg:province":"Bruxelles-Capitale",
    "wof:name":"Sylviane Descamps",
    "wof:placetype":"venue"
},
  "geometry": {"coordinates":[4.3651790619,50.8947257996],"type":"Point"}
}