{
  "type": "Feature",
  "properties": {
    "addr:full":"Kallestraat 17 Alveringem West-Vlaanderen 8691",
    "addr:housenumber":"17",
    "addr:postcode":"8691",
    "addr:street":"Kallestraat",
    "iso:country":"BE",
    "sg:address":"Kallestraat 17",
    "sg:city":"Alveringem",
    "sg:orig_category":"Rundveehouders Varkenskwekers",
    "sg:phone":"+32 57 30 03 34",
    "sg:postcode":"8691",
    "sg:province":"West-Vlaanderen",
    "wof:name":"Etienne Vermander",
    "wof:placetype":"venue"
},
  "geometry": {"coordinates":[2.6389760971,50.9416656494],"type":"Point"}
}