{
  "type": "Feature",
  "properties": {
    "iso:country":"BE",
    "sg:address":"Gentsesteenweg 72a",
    "sg:city":"Eeklo",
    "sg:orig_category":"Antiquit\u00e9s",
    "sg:phone":"+32 9 377 55 11",
    "sg:postcode":"9900",
    "sg:province":"Oost-Vlaanderen",
    "wof:name":"Oud Eecloo",
    "wof:placetype":"venue"
},
  "geometry": {"coordinates":[3.5831439495,51.172706604],"type":"Point"}
}