{
  "type": "Feature",
  "properties": {
    "addr:full":"Chenogne 6a Vaux-sur-s\u00fbre (sibret) Luxembourg 6640",
    "addr:housenumber":"6a",
    "addr:postcode":"6640",
    "addr:street":"Chenogne",
    "iso:country":"BE",
    "sg:address":"Chenogne 6a",
    "sg:city":"Vaux-sur-s\u00fbre (sibret)",
    "sg:classifiers":[
        {
            "category":"Professional",
            "subcategory":"Lawyer & Legal Services",
            "type":"Services"
        }
    ],
    "sg:phone":"+32 61 26 70 04",
    "sg:postcode":"6640",
    "sg:province":"Luxembourg",
    "wof:name":"Farber Evelyne",
    "wof:placetype":"venue"
},
  "geometry": {"coordinates":[5.6199698448,49.9921913147],"type":"Point"}
}