{
  "type": "Feature",
  "properties": {
    "iso:country":"BE",
    "sg:address":"Antwerpsesteenweg 282",
    "sg:city":"Zwijndrecht",
    "sg:classifiers":[
        {
            "category":"Retail",
            "subcategory":"Animal Services",
            "type":"Services"
        }
    ],
    "sg:phone":"+32 3 253 04 73",
    "sg:postcode":"2070",
    "sg:province":"Antwerpen",
    "sg:tags":[
        "grooming",
        "-",
        "dog"
    ],
    "wof:name":"Clovis",
    "wof:placetype":"venue"
},
  "geometry": {"coordinates":[4.3408999443,51.2136383057],"type":"Point"}
}