{
  "type": "Feature",
  "properties": {
    "addr:full":"Huzenblek 2 Ravels (weelde) Antwerpen 2381",
    "addr:housenumber":"2",
    "addr:postcode":"2381",
    "addr:street":"Huzenblek",
    "iso:country":"BE",
    "sg:address":"Huzenblek 2",
    "sg:city":"Ravels (weelde)",
    "sg:classifiers":[
        {
            "category":"Community Center",
            "subcategory":"Social",
            "type":"Public Place"
        }
    ],
    "sg:phone":"+32 14 65 70 33",
    "sg:postcode":"2381",
    "sg:province":"Antwerpen",
    "sg:tags":[
        "polishing",
        "abrasive",
        "compound"
    ],
    "wof:name":"Wijhuis Ingenieurs Bureau",
    "wof:placetype":"venue"
},
  "geometry": {"coordinates":[5.006374836,51.4099845886],"type":"Point"}
}