{
  "type": "Feature",
  "properties": {
    "addr:full":"Vijfwegenstraat 14 Izegem West-Vlaanderen 8870",
    "addr:housenumber":"14",
    "addr:postcode":"8870",
    "addr:street":"Vijfwegenstraat",
    "iso:country":"BE",
    "sg:address":"Vijfwegenstraat 14",
    "sg:city":"Izegem",
    "sg:classifiers":[
        {
            "category":"Health Services",
            "subcategory":"Doctor",
            "type":"Services"
        }
    ],
    "sg:phone":"+32 51 30 40 60",
    "sg:postcode":"8870",
    "sg:province":"West-Vlaanderen",
    "sg:tags":[
        "medicinephysicians",
        "surgeon"
    ],
    "wof:name":"Coudron C",
    "wof:placetype":"venue"
},
  "geometry": {"coordinates":[3.2165710926,50.9256668091],"type":"Point"}
}