{
  "type": "Feature",
  "properties": {
    "addr:full":"Rue Des Ecoles 6 Berloz Li\u00e8ge 4257",
    "addr:housenumber":"6",
    "addr:postcode":"4257",
    "addr:street":"Rue Des Ecoles",
    "iso:country":"BE",
    "sg:address":"Rue Des Ecoles 6",
    "sg:city":"Berloz",
    "sg:orig_category":"Agences de relations publiques",
    "sg:phone":"+32 19 33 09 45",
    "sg:postcode":"4257",
    "sg:province":"Li\u00e8ge",
    "wof:name":"Tortuga Bay",
    "wof:placetype":"venue"
},
  "geometry": {"coordinates":[5.213602066,50.6992874146],"type":"Point"}
}