{
  "type": "Feature",
  "properties": {
    "iso:country":"BE",
    "sg:address":"Chauss\u00e9e De Dinant 5",
    "sg:city":"Anh\u00e9e",
    "sg:classifiers":[
        {
            "category":"Manufacturing",
            "subcategory":"Furniture",
            "type":"Manufacturing & Wholesale Goods"
        }
    ],
    "sg:phone":"+32 82 61 22 36",
    "sg:postcode":"5537",
    "sg:province":"Namur",
    "sg:tags":[
        "design",
        "-"
    ],
    "wof:name":"Interieur Sprl Sprl",
    "wof:placetype":"venue"
},
  "geometry": {"coordinates":[4.880838871,50.3082695007],"type":"Point"}
}