{
  "type": "Feature",
  "properties": {
    "addr:full":"Avenue Albert Ier 91 Namur Namur 5000",
    "addr:housenumber":"91",
    "addr:postcode":"5000",
    "addr:street":"Avenue Albert Ier",
    "iso:country":"BE",
    "sg:address":"Avenue Albert Ier 91",
    "sg:city":"Namur",
    "sg:orig_category":"Agences immobili\u00e8res",
    "sg:phone":"+32 81 22 37 41",
    "sg:postcode":"5000",
    "sg:province":"Namur",
    "wof:name":"Sud Epervier",
    "wof:placetype":"venue"
},
  "geometry": {"coordinates":[4.8822350502,50.4670143127],"type":"Point"}
}