{
  "type": "Feature",
  "properties": {
    "addr:full":"Noordlaan 19 Kuurne West-Vlaanderen 8520",
    "addr:housenumber":"19",
    "addr:postcode":"8520",
    "addr:street":"Noordlaan",
    "iso:country":"BE",
    "sg:address":"Noordlaan 19",
    "sg:city":"Kuurne",
    "sg:classifiers":[
        {
            "category":"Home & Garden",
            "subcategory":"Kitchen Supply",
            "type":"Retail Goods"
        }
    ],
    "sg:phone":"+32 56 35 70 12",
    "sg:postcode":"8520",
    "sg:province":"West-Vlaanderen",
    "sg:tags":[
        "-",
        "industrial",
        "installation",
        "equipment"
    ],
    "wof:name":"Bossuyt Grootkeuken Nv",
    "wof:placetype":"venue"
},
  "geometry": {"coordinates":[3.259581089,50.8585662842],"type":"Point"}
}