{
  "type": "Feature",
  "properties": {
    "addr:full":"Coursive Plein Ciel 42 Sint-pieters-woluwe/woluwe-saint-pierre Bruxelles-Capitale 1150",
    "addr:housenumber":"42",
    "addr:postcode":"1150",
    "addr:street":"Coursive Plein Ciel;/",
    "iso:country":"BE",
    "sg:address":"Coursive Plein Ciel 42",
    "sg:city":"Sint-pieters-woluwe/woluwe-saint-pierre",
    "sg:orig_category":"Agences de relations publiques",
    "sg:phone":"+32 2 762 17 59",
    "sg:postcode":"1150",
    "sg:province":"Bruxelles-Capitale",
    "wof:name":"Masc",
    "wof:placetype":"venue"
},
  "geometry": {"coordinates":[4.4432621002,50.8330497742],"type":"Point"}
}