{
  "type": "Feature",
  "properties": {
    "addr:full":"Louiza Espace 17 Bruxelles (ixelles) Bruxelles-Capitale 1050",
    "addr:postcode":"1050",
    "iso:country":"BE",
    "sg:address":"Louiza Espace 17",
    "sg:city":"Bruxelles (ixelles)",
    "sg:classifiers":[
        {
            "category":"Shopping",
            "subcategory":"Gifts & Souvenirs",
            "type":"Retail Goods"
        }
    ],
    "sg:phone":"+32 2 513 95 74",
    "sg:postcode":"1050",
    "sg:province":"Bruxelles-Capitale",
    "sg:tags":[
        "-"
    ],
    "wof:name":"K-d\u00f4",
    "wof:placetype":"venue"
},
  "geometry": {"coordinates":[4.356962204,50.8341941833],"type":"Point"}
}