{
  "type": "Feature",
  "properties": {
    "addr:full":"Berchemstraat 1 Kluisbergen Oost-Vlaanderen 9690",
    "addr:housenumber":"1",
    "addr:postcode":"9690",
    "addr:street":"Berchemstraat",
    "iso:country":"BE",
    "sg:address":"Berchemstraat 1",
    "sg:city":"Kluisbergen",
    "sg:orig_category":"Verlichting and huishoudartikelen",
    "sg:phone":"+32 55 38 87 06",
    "sg:postcode":"9690",
    "sg:province":"Oost-Vlaanderen",
    "wof:name":"A. Gheysen",
    "wof:placetype":"venue"
},
  "geometry": {"coordinates":[3.5100600719,50.7901039124],"type":"Point"}
}