{
  "type": "Feature",
  "properties": {
    "iso:country":"BE",
    "sg:address":"Spreet 30",
    "sg:city":"Lier",
    "sg:classifiers":[
        {
            "category":"Banks & Credit Unions",
            "subcategory":"Investment Brokerage",
            "type":"Services"
        }
    ],
    "sg:phone":"+32 3 482 11 40",
    "sg:postcode":"2500",
    "sg:province":"Antwerpen",
    "sg:tags":[
        "auditor"
    ],
    "wof:name":"Blanckaert D",
    "wof:placetype":"venue"
},
  "geometry": {"coordinates":[4.6036510468,51.1107597351],"type":"Point"}
}