{
  "type": "Feature",
  "properties": {
    "iso:country":"BE",
    "sg:address":"Rue Toussaint Gerkens 12b",
    "sg:city":"Chaudfontaine (beaufays)",
    "sg:classifiers":[
        {
            "category":"Personal",
            "subcategory":"Beauty Salon",
            "type":"Services"
        }
    ],
    "sg:phone":"+32 4 368 64 43",
    "sg:postcode":"4052",
    "sg:province":"Li\u00e8ge",
    "wof:name":"Metamorphose",
    "wof:placetype":"venue"
},
  "geometry": {"coordinates":[5.6395559311,50.5577049255],"type":"Point"}
}