{
  "type": "Feature",
  "properties": {
    "iso:country":"BE",
    "sg:address":"Bruglaan 23",
    "sg:city":"Bree",
    "sg:classifiers":[
        {
            "category":"Building & Trades",
            "subcategory":"Equipment Rental",
            "type":"Services"
        }
    ],
    "sg:phone":"+32 89 46 13 73",
    "sg:postcode":"3960",
    "sg:province":"Limburg",
    "sg:tags":[
        "de",
        "\u00e9v\u00e9nements",
        "pour",
        "mat\u00e9riel",
        "location",
        "banquet"
    ],
    "wof:name":"Frans Evens",
    "wof:placetype":"venue"
},
  "geometry": {"coordinates":[5.6093740463,51.1420288086],"type":"Point"}
}