{
  "type": "Feature",
  "properties": {
    "addr:full":"J. Van Clichthovenstraat 137 Nieuwpoort West-Vlaanderen 8620",
    "addr:housenumber":"137",
    "addr:postcode":"8620",
    "addr:street":"J. Van Clichthovenstraat",
    "iso:country":"BE",
    "sg:address":"J. Van Clichthovenstraat 137",
    "sg:city":"Nieuwpoort",
    "sg:orig_category":"Elektrische installaties voor woningen",
    "sg:phone":"+32 58 23 14 31",
    "sg:postcode":"8620",
    "sg:province":"West-Vlaanderen",
    "wof:name":"Fa. Javanel",
    "wof:placetype":"venue"
},
  "geometry": {"coordinates":[2.7518310547,51.1271324158],"type":"Point"}
}