{
  "type": "Feature",
  "properties": {
    "iso:country":"BE",
    "sg:address":"Collegelaan 27",
    "sg:city":"Bornem",
    "sg:orig_category":"Sportclubs",
    "sg:phone":"+32 3 899 00 98",
    "sg:postcode":"2880",
    "sg:province":"Antwerpen",
    "wof:name":"Ok.c. Bornem",
    "wof:placetype":"venue"
},
  "geometry": {"coordinates":[4.2243151665,51.0914268494],"type":"Point"}
}