{
  "type": "Feature",
  "properties": {
    "iso:country":"BE",
    "sg:address":"Tramstraat 15",
    "sg:city":"Destelbergen",
    "sg:orig_category":"Reisbureaus",
    "sg:phone":"+32 9 232 30 90",
    "sg:postcode":"9070",
    "sg:province":"Oost-Vlaanderen",
    "wof:name":"Flash Travel",
    "wof:placetype":"venue"
},
  "geometry": {"coordinates":[3.8010859489,51.0297470093],"type":"Point"}
}