{
  "type": "Feature",
  "properties": {
    "iso:country":"BE",
    "sg:address":"Rue Haute 159",
    "sg:city":"Dinant",
    "sg:orig_category":"Eleveurs de bovins",
    "sg:phone":"+32 82 74 48 70",
    "sg:postcode":"5500",
    "sg:province":"Namur",
    "wof:name":"Jean-marie Clarenne",
    "wof:placetype":"venue"
},
  "geometry": {"coordinates":[4.8889870644,50.2053222656],"type":"Point"}
}