{
  "type": "Feature",
  "properties": {
    "addr:full":"Rue De L'et\u00e9 53 Bruxelles (ixelles) Bruxelles-Capitale 1050",
    "addr:housenumber":"53",
    "addr:postcode":"1050",
    "addr:street":"Rue De L'Ete \u0301",
    "iso:country":"BE",
    "sg:address":"Rue De L'et\u00e9 53",
    "sg:city":"Bruxelles (ixelles)",
    "sg:classifiers":[
        {
            "category":"Professional",
            "subcategory":"Detective & Security Services",
            "type":"Services"
        }
    ],
    "sg:phone":"+32 2 646 08 42",
    "sg:postcode":"1050",
    "sg:province":"Bruxelles-Capitale",
    "sg:tags":[
        "guard"
    ],
    "wof:name":"Security Monitoring Centre Nv",
    "wof:placetype":"venue"
},
  "geometry": {"coordinates":[4.3886318207,50.8189086914],"type":"Point"}
}