{
  "type": "Feature",
  "properties": {
    "addr:full":"Witte Nonnenstraat 19 Hasselt Limburg 3500",
    "addr:housenumber":"19",
    "addr:postcode":"3500",
    "addr:street":"Witte Nonnenstraat",
    "iso:country":"BE",
    "sg:address":"Witte Nonnenstraat 19",
    "sg:city":"Hasselt",
    "sg:orig_category":"Mus\u00e9es and patrimoine culturel",
    "sg:phone":"+32 11 24 11 44",
    "sg:postcode":"3500",
    "sg:province":"Limburg",
    "wof:name":"Nationaal Jenevermuseum",
    "wof:placetype":"venue"
},
  "geometry": {"coordinates":[5.3406829834,50.9326515198],"type":"Point"}
}