{
  "type": "Feature",
  "properties": {
    "addr:full":"Stationsstraat 77 Aalter Oost-Vlaanderen 9880",
    "addr:housenumber":"77",
    "addr:postcode":"9880",
    "addr:street":"Stationsstraat",
    "iso:country":"BE",
    "sg:address":"Stationsstraat 77",
    "sg:city":"Aalter",
    "sg:orig_category":"Agences de publicit\u00e9",
    "sg:phone":"+32 9 374 10 84",
    "sg:postcode":"9880",
    "sg:province":"Oost-Vlaanderen",
    "wof:name":"Kleefletters Markant",
    "wof:placetype":"venue"
},
  "geometry": {"coordinates":[3.4474599361,51.0894699097],"type":"Point"}
}