{
  "type": "Feature",
  "properties": {
    "iso:country":"BE",
    "sg:address":"Meanderstraat 16",
    "sg:city":"Ichtegem (bekegem)",
    "sg:classifiers":[
        {
            "category":"Building & Trades",
            "subcategory":"Construction",
            "type":"Services"
        }
    ],
    "sg:phone":"+32 50 81 65 60",
    "sg:postcode":"8480",
    "sg:province":"West-Vlaanderen",
    "sg:tags":[
        "carpenter"
    ],
    "wof:name":"Rommelaere L",
    "wof:placetype":"venue"
},
  "geometry": {"coordinates":[3.047137022,51.1577186584],"type":"Point"}
}