{
  "type": "Feature",
  "properties": {
    "iso:country":"BE",
    "sg:address":"Rue Bel Air 40",
    "sg:city":"Ecaussinnes (ecaussinnes-d'enghien)",
    "sg:classifiers":[
        {
            "category":"Social Services",
            "subcategory":"Child Care",
            "type":"Services"
        }
    ],
    "sg:phone":"+32 67 44 22 03",
    "sg:postcode":"7190",
    "sg:province":"Hainaut",
    "sg:tags":[
        "home"
    ],
    "wof:name":"Gai Logis Asbl",
    "wof:placetype":"venue"
},
  "geometry": {"coordinates":[4.154279232,50.5648536682],"type":"Point"}
}