{
  "type": "Feature",
  "properties": {
    "addr:full":"Dorpstraat 26 Wichelen Oost-Vlaanderen 9260",
    "addr:housenumber":"26",
    "addr:postcode":"9260",
    "addr:street":"Dorpstraat",
    "iso:country":"BE",
    "sg:address":"Dorpstraat 26",
    "sg:city":"Wichelen",
    "sg:orig_category":"Studios photographiques",
    "sg:phone":"+32 9 369 03 35",
    "sg:postcode":"9260",
    "sg:province":"Oost-Vlaanderen",
    "wof:name":"Yves Samson",
    "wof:placetype":"venue"
},
  "geometry": {"coordinates":[3.9714560509,51.0123252869],"type":"Point"}
}