{
  "type": "Feature",
  "properties": {
    "iso:country":"BE",
    "sg:address":"Boulevard Cauchy 21",
    "sg:city":"Namur",
    "sg:classifiers":[
        {
            "category":"Professional",
            "subcategory":"Accounting & Tax Preparation",
            "type":"Services"
        }
    ],
    "sg:phone":"+32 81 22 20 49",
    "sg:postcode":"5000",
    "sg:province":"Namur",
    "sg:tags":[
        "accountant"
    ],
    "wof:name":"Sogeor Soci\u00e9t\u00e9 De Gestion Et D'organisation Sa",
    "wof:placetype":"venue"
},
  "geometry": {"coordinates":[4.8717870712,50.4683113098],"type":"Point"}
}