{
  "type": "Feature",
  "properties": {
    "iso:country":"BE",
    "sg:address":"Rue De L'hydrion 127",
    "sg:city":"Arlon",
    "sg:classifiers":[
        {
            "category":"Insurance",
            "subcategory":"Insurance Agent",
            "type":"Services"
        }
    ],
    "sg:phone":"+32 63 24 06 60",
    "sg:postcode":"6700",
    "sg:province":"Luxembourg",
    "sg:tags":[
        "broker"
    ],
    "wof:name":"Ofac + Sprl",
    "wof:placetype":"venue"
},
  "geometry": {"coordinates":[5.7952828407,49.6843414307],"type":"Point"}
}