{
  "type": "Feature",
  "properties": {
    "iso:country":"BE",
    "sg:address":"Oudenburgweg 46",
    "sg:city":"Jabbeke",
    "sg:orig_category":"Eleveurs and marchands de porcs. Eleveurs de bovins",
    "sg:phone":"+32 50 81 27 45",
    "sg:postcode":"8490",
    "sg:province":"West-Vlaanderen",
    "wof:name":"Luc Schollier",
    "wof:placetype":"venue"
},
  "geometry": {"coordinates":[3.1078000069,51.1871986389],"type":"Point"}
}