{
  "type": "Feature",
  "properties": {
    "addr:full":"Wijngaardstraat 36 Dilbeek Vlaams-Brabant 1703",
    "addr:housenumber":"36",
    "addr:postcode":"1703",
    "addr:street":"Wijngaardstraat",
    "iso:country":"BE",
    "sg:address":"Wijngaardstraat 36",
    "sg:city":"Dilbeek",
    "sg:classifiers":[
        {
            "category":"Sports & Exercise",
            "subcategory":"Sports Center",
            "type":"Entertainment"
        }
    ],
    "sg:phone":"+32 2 569 72 53",
    "sg:postcode":"1703",
    "sg:province":"Vlaams-Brabant",
    "sg:tags":[
        "de",
        "fitness"
    ],
    "wof:name":"Dilgym",
    "wof:placetype":"venue"
},
  "geometry": {"coordinates":[4.1980981827,50.8402748108],"type":"Point"}
}