{
  "type": "Feature",
  "properties": {
    "addr:full":"Parvis Sainte-alix 24 Sint-pieters-woluwe/woluwe-saint-pierre Bruxelles-Capitale 1150",
    "addr:housenumber":"24",
    "addr:postcode":"1150",
    "addr:street":"Parvis Sainte-Alix;/",
    "iso:country":"BE",
    "sg:address":"Parvis Sainte-alix 24",
    "sg:city":"Sint-pieters-woluwe/woluwe-saint-pierre",
    "sg:orig_category":"RESTAURANTS: CAF\u00c9S",
    "sg:phone":"+32 2 779 27 63",
    "sg:postcode":"1150",
    "sg:province":"Bruxelles-Capitale",
    "wof:name":"Taverne Sainte-alix",
    "wof:placetype":"venue"
},
  "geometry": {"coordinates":[4.4613242149,50.8281326294],"type":"Point"}
}