{
  "type": "Feature",
  "properties": {
    "iso:country":"BE",
    "sg:address":"Doelstraat 39",
    "sg:city":"Halen",
    "sg:classifiers":[
        {
            "category":"Personal",
            "subcategory":"Beauty Salon",
            "type":"Services"
        }
    ],
    "sg:phone":"+32 13 44 25 70",
    "sg:postcode":"3545",
    "sg:province":"Limburg",
    "sg:tags":[
        "de",
        "coiffure"
    ],
    "wof:name":"Louis Bastijns",
    "wof:placetype":"venue"
},
  "geometry": {"coordinates":[5.1140570641,50.9465560913],"type":"Point"}
}