{
  "type": "Feature",
  "properties": {
    "iso:country":"BE",
    "sg:address":"Menenstraat 390",
    "sg:city":"Wevelgem",
    "sg:orig_category":"Pain, p\u00e2tisseries and confiseries",
    "sg:phone":"+32 56 40 29 96",
    "sg:postcode":"8560",
    "sg:province":"West-Vlaanderen",
    "wof:name":"Kurt Vanhulle",
    "wof:placetype":"venue"
},
  "geometry": {"coordinates":[3.1567709446,50.8029556274],"type":"Point"}
}