{
  "type": "Feature",
  "properties": {
    "iso:country":"BE",
    "sg:address":"Rue De Tilff 52",
    "sg:city":"Li\u00e8ge 1 (angleur)",
    "sg:classifiers":[
        {
            "category":"Communications",
            "subcategory":"Film & Video Production",
            "type":"Services"
        }
    ],
    "sg:phone":"+32 4 384 30 25",
    "sg:postcode":"4031",
    "sg:province":"Li\u00e8ge",
    "sg:tags":[
        "professional",
        "material",
        "-"
    ],
    "wof:name":"Incentive Design Scs",
    "wof:placetype":"venue"
},
  "geometry": {"coordinates":[5.6009521484,50.6098136902],"type":"Point"}
}