{
  "type": "Feature",
  "properties": {
    "iso:country":"BE",
    "sg:address":"Arthur Quintusstraat 47 A",
    "sg:city":"Sint-pieters-leeuw",
    "sg:orig_category":"Kapsalons",
    "sg:phone":"+32 2 377 16 19",
    "sg:postcode":"1600",
    "sg:province":"Vlaams-Brabant",
    "wof:name":"Coiffure Alberte",
    "wof:placetype":"venue"
},
  "geometry": {"coordinates":[4.2767219543,50.7916793823],"type":"Point"}
}