{
  "type": "Feature",
  "properties": {
    "iso:country":"BE",
    "sg:address":"Driehoek 100",
    "sg:city":"Stabroek",
    "sg:classifiers":[
        {
            "category":"Professional",
            "type":"Services"
        }
    ],
    "sg:phone":"+32 3 664 72 97",
    "sg:postcode":"2940",
    "sg:province":"Antwerpen",
    "sg:tags":[
        "industrial",
        "work",
        "-",
        "maintenance"
    ],
    "wof:name":"Bouwonderneming Robert Maes Nv",
    "wof:placetype":"venue"
},
  "geometry": {"coordinates":[4.3984699249,51.3474273682],"type":"Point"}
}