{
  "type": "Feature",
  "properties": {
    "addr:full":"Rue De La Brasserie 1 Linkebeek/linkebeek Vlaams-Brabant 1630",
    "addr:housenumber":"1",
    "addr:postcode":"1630",
    "addr:street":"Rue De La Brasserie",
    "iso:country":"BE",
    "sg:address":"Rue De La Brasserie 1",
    "sg:city":"Linkebeek/linkebeek",
    "sg:orig_category":"Cr\u00e9dits divers",
    "sg:postcode":"1630",
    "sg:province":"Vlaams-Brabant",
    "wof:name":"Bancontact-mister Cash",
    "wof:placetype":"venue"
},
  "geometry": {"coordinates":[4.3269739151,50.7782516479],"type":"Point"}
}