{
  "type": "Feature",
  "properties": {
    "iso:country":"BE",
    "sg:address":"Bodegemstraat 78b82",
    "sg:city":"Brussel/bruxelles",
    "sg:orig_category":"Maatschappelijke dienstverlening",
    "sg:phone":"+32 2 511 04 17",
    "sg:postcode":"1000",
    "sg:province":"Bruxelles-Capitale",
    "wof:name":"Ouvroir Infirm. R\u00c9eduqu\u00c9s",
    "wof:placetype":"venue"
},
  "geometry": {"coordinates":[4.340941906,50.8430938721],"type":"Point"}
}