{
  "type": "Feature",
  "properties": {
    "iso:country":"BE",
    "sg:address":"Sint-andriessteenweg 142",
    "sg:city":"Zottegem",
    "sg:orig_category":"Pain, p\u00e2tisseries and confiseries",
    "sg:phone":"+32 9 360 48 99",
    "sg:postcode":"9620",
    "sg:province":"Oost-Vlaanderen",
    "wof:name":"Van Nieuwenhove Kinderen",
    "wof:placetype":"venue"
},
  "geometry": {"coordinates":[3.7959799767,50.868183136],"type":"Point"}
}