{
  "type": "Feature",
  "properties": {
    "addr:full":"Vilvertstraat 11 Dilsen Limburg 3650",
    "addr:housenumber":"11",
    "addr:postcode":"3650",
    "addr:street":"Vilvertstraat",
    "iso:country":"BE",
    "sg:address":"Vilvertstraat 11",
    "sg:city":"Dilsen",
    "sg:classifiers":[
        {
            "category":"Home & Garden",
            "subcategory":"Furniture",
            "type":"Retail Goods"
        }
    ],
    "sg:phone":"+32 89 79 82 99",
    "sg:postcode":"3650",
    "sg:province":"Limburg",
    "sg:tags":[
        "household",
        "wood"
    ],
    "wof:name":"Mecam Nv",
    "wof:placetype":"venue"
},
  "geometry": {"coordinates":[5.727396965,51.0364189148],"type":"Point"}
}