{
  "type": "Feature",
  "properties": {
    "iso:country":"BE",
    "sg:address":"Herentalse Steenweg 97a",
    "sg:city":"Herenthout",
    "sg:classifiers":[
        {
            "category":"Retail",
            "subcategory":"Animal Services",
            "type":"Services"
        }
    ],
    "sg:phone":"+32 14 21 42 41",
    "sg:postcode":"2270",
    "sg:province":"Antwerpen",
    "sg:tags":[
        "farrier"
    ],
    "wof:name":"Select",
    "wof:placetype":"venue"
},
  "geometry": {"coordinates":[4.8034100533,51.1533889771],"type":"Point"}
}