{
  "type": "Feature",
  "properties": {
    "addr:full":"Frederik De Merodestraat 93 Mechelen Antwerpen 2800",
    "addr:housenumber":"93",
    "addr:postcode":"2800",
    "addr:street":"Frederik De Merodestraat",
    "iso:country":"BE",
    "sg:address":"Frederik De Merodestraat 93",
    "sg:city":"Mechelen",
    "sg:classifiers":[
        {
            "category":"Health Services",
            "subcategory":"Doctor",
            "type":"Services"
        }
    ],
    "sg:phone":"+32 15 20 31 53",
    "sg:postcode":"2800",
    "sg:province":"Antwerpen",
    "sg:tags":[
        "medicinephysicians",
        "surgeon"
    ],
    "wof:name":"Jamar R",
    "wof:placetype":"venue"
},
  "geometry": {"coordinates":[4.4831628799,51.0322418213],"type":"Point"}
}