{
  "type": "Feature",
  "properties": {
    "iso:country":"BE",
    "sg:address":"Coupure 1a",
    "sg:city":"Brugge",
    "sg:orig_category":"Diverse organisaties and verenigingen Zalen voor culturele evenementen",
    "sg:phone":"+32 50 67 50 21",
    "sg:postcode":"8000",
    "sg:province":"West-Vlaanderen",
    "wof:name":"Stratemon Group",
    "wof:placetype":"venue"
},
  "geometry": {"coordinates":[3.2323420048,51.2086143494],"type":"Point"}
}