{
  "type": "Feature",
  "properties": {
    "addr:full":"Hagelstein 41bb Voeren/fourons Limburg 3791",
    "addr:postcode":"3791",
    "iso:country":"BE",
    "sg:address":"Hagelstein 41bb",
    "sg:city":"Voeren/fourons",
    "sg:orig_category":"Woningbouw",
    "sg:phone":"+32 4 381 21 88",
    "sg:postcode":"3791",
    "sg:province":"Limburg",
    "wof:name":"Pelsser En Cie",
    "wof:placetype":"venue"
},
  "geometry": {"coordinates":[5.867565155,50.7161064148],"type":"Point"}
}