{
  "type": "Feature",
  "properties": {
    "addr:full":"Scharestraat 48 Oostkamp (hertsberge) West-Vlaanderen 8020",
    "addr:housenumber":"48",
    "addr:postcode":"8020",
    "addr:street":"Scharestraat",
    "iso:country":"BE",
    "sg:address":"Scharestraat 48",
    "sg:city":"Oostkamp (hertsberge)",
    "sg:classifiers":[
        {
            "category":"Building & Trades",
            "subcategory":"Construction",
            "type":"Services"
        }
    ],
    "sg:phone":"+32 50 28 02 48",
    "sg:postcode":"8020",
    "sg:province":"West-Vlaanderen",
    "sg:tags":[
        "carpenter"
    ],
    "wof:name":"Soetaert Dirk",
    "wof:placetype":"venue"
},
  "geometry": {"coordinates":[3.2508690357,51.0881462097],"type":"Point"}
}