{
  "type": "Feature",
  "properties": {
    "addr:full":"Meensesteenweg 310 Kortrijk West-Vlaanderen 8501",
    "addr:housenumber":"310",
    "addr:postcode":"8501",
    "addr:street":"Meensesteenweg",
    "iso:country":"BE",
    "sg:address":"Meensesteenweg 310",
    "sg:city":"Kortrijk",
    "sg:orig_category":"Maroquinerie Fab",
    "sg:phone":"+32 56 35 21 19",
    "sg:postcode":"8501",
    "sg:province":"West-Vlaanderen",
    "wof:name":"P.b. Fashion",
    "wof:placetype":"venue"
},
  "geometry": {"coordinates":[3.2284789085,50.8242530823],"type":"Point"}
}