{
  "type": "Feature",
  "properties": {
    "addr:full":"Place D'autreppe 1 Ath (ormeignies) Hainaut 7802",
    "addr:housenumber":"1",
    "addr:postcode":"7802",
    "addr:street":"Place D'Autreppe",
    "iso:country":"BE",
    "sg:address":"Place D'autreppe 1",
    "sg:city":"Ath (ormeignies)",
    "sg:classifiers":[
        {
            "category":"Building & Trades",
            "subcategory":"Construction",
            "type":"Services"
        }
    ],
    "sg:phone":"+32 69 68 82 10",
    "sg:postcode":"7802",
    "sg:province":"Hainaut",
    "sg:tags":[
        "carpenter"
    ],
    "wof:name":"Foucart P",
    "wof:placetype":"venue"
},
  "geometry": {"coordinates":[3.7160470486,50.5887794495],"type":"Point"}
}