{
  "type": "Feature",
  "properties": {
    "addr:full":"Place Du Dix-sept Novembre 14 Seraing Li\u00e8ge 4100",
    "addr:housenumber":"14",
    "addr:postcode":"4100",
    "addr:street":"Place Du Dix-Sept Novembre",
    "iso:country":"BE",
    "sg:address":"Place Du Dix-sept Novembre 14",
    "sg:city":"Seraing",
    "sg:classifiers":[
        {
            "category":"Bars & Pubs",
            "type":"Food & Drink"
        }
    ],
    "sg:phone":"+32 4 336 63 47",
    "sg:postcode":"4100",
    "sg:province":"Li\u00e8ge",
    "wof:name":"March\u00e9 (caf\u00e9 Du)",
    "wof:placetype":"venue"
},
  "geometry": {"coordinates":[5.5096349716,50.6147155762],"type":"Point"}
}