{
  "type": "Feature",
  "properties": {
    "iso:country":"BE",
    "sg:address":"Herenthout 1",
    "sg:city":"Haaltert",
    "sg:orig_category":"Kapsalons",
    "sg:phone":"+32 53 83 41 16",
    "sg:postcode":"9450",
    "sg:province":"Oost-Vlaanderen",
    "wof:name":"Coiffure Derry",
    "wof:placetype":"venue"
},
  "geometry": {"coordinates":[4.0134391785,50.9068412781],"type":"Point"}
}