{
  "type": "Feature",
  "properties": {
    "iso:country":"BE",
    "sg:address":"Kruishuisstraat 114",
    "sg:city":"Turnhout",
    "sg:classifiers":[
        {
            "category":"Fast Food",
            "type":"Food & Drink"
        }
    ],
    "sg:phone":"+32 14 41 77 53",
    "sg:postcode":"2300",
    "sg:province":"Antwerpen",
    "sg:tags":[
        "fried",
        "stand",
        "potato"
    ],
    "wof:name":"Kruishuis ('t)",
    "wof:placetype":"venue"
},
  "geometry": {"coordinates":[4.9403829575,51.3184814453],"type":"Point"}
}