{
  "type": "Feature",
  "properties": {
    "addr:full":"Kattenbos 121 Lommel Limburg 3920",
    "addr:housenumber":"121",
    "addr:postcode":"3920",
    "addr:street":"Kattenbos",
    "iso:country":"BE",
    "sg:address":"Kattenbos 121",
    "sg:city":"Lommel",
    "sg:classifiers":[
        {
            "category":"Professional",
            "subcategory":"Advertising",
            "type":"Services"
        }
    ],
    "sg:phone":"+32 11 73 13 07",
    "sg:postcode":"3920",
    "sg:province":"Limburg",
    "sg:tags":[
        "item",
        "-",
        "business",
        "gift",
        "promotional"
    ],
    "wof:name":"L'exsellent Bvba",
    "wof:placetype":"venue"
},
  "geometry": {"coordinates":[5.3079161644,51.2036781311],"type":"Point"}
}