{
  "type": "Feature",
  "properties": {
    "addr:full":"Gentsesteenweg 1 Asse Vlaams-Brabant 1730",
    "addr:housenumber":"1",
    "addr:postcode":"1730",
    "addr:street":"Gentsesteenweg",
    "iso:country":"BE",
    "sg:address":"Gentsesteenweg 1",
    "sg:city":"Asse",
    "sg:orig_category":"Entretien and r\u00e9parations de voitures",
    "sg:phone":"+32 2 452 76 69",
    "sg:postcode":"1730",
    "sg:province":"Vlaams-Brabant",
    "wof:name":"Rene Bastaerts",
    "wof:placetype":"venue"
},
  "geometry": {"coordinates":[4.1856298447,50.9195289612],"type":"Point"}
}