{
  "type": "Feature",
  "properties": {
    "iso:country":"BE",
    "sg:address":"Ter Platen 66",
    "sg:city":"Gent",
    "sg:orig_category":"Eclairage et \u00e9quipements du foyer. Boucheries",
    "sg:phone":"+32 9 233 24 84",
    "sg:postcode":"9000",
    "sg:province":"Oost-Vlaanderen",
    "wof:name":"Erwin Geers",
    "wof:placetype":"venue"
},
  "geometry": {"coordinates":[3.7293651104,51.0384597778],"type":"Point"}
}