{
  "type": "Feature",
  "properties": {
    "addr:full":"Rue Du Parc 25 Verviers Li\u00e8ge 4800",
    "addr:housenumber":"25",
    "addr:postcode":"4800",
    "addr:street":"Rue Du Parc",
    "iso:country":"BE",
    "sg:address":"Rue Du Parc 25",
    "sg:city":"Verviers",
    "sg:classifiers":[
        {
            "category":"Health Services",
            "subcategory":"Doctor",
            "type":"Services"
        }
    ],
    "sg:phone":"+32 87 23 05 23",
    "sg:postcode":"4800",
    "sg:province":"Li\u00e8ge",
    "sg:tags":[
        "medicinephysicians",
        "surgeon"
    ],
    "wof:name":"Dubois V",
    "wof:placetype":"venue"
},
  "geometry": {"coordinates":[5.8580350876,50.5823364258],"type":"Point"}
}