{
  "type": "Feature",
  "properties": {
    "addr:full":"Haenhoutstraat 55 Destelbergen Oost-Vlaanderen 9070",
    "addr:housenumber":"55",
    "addr:postcode":"9070",
    "addr:street":"Haenhoutstraat",
    "iso:country":"BE",
    "sg:address":"Haenhoutstraat 55",
    "sg:city":"Destelbergen",
    "sg:orig_category":"M\u00e9decins and sp\u00e9cialistes",
    "sg:phone":"+32 9 355 75 26",
    "sg:postcode":"9070",
    "sg:province":"Oost-Vlaanderen",
    "wof:name":"Conny Matthys",
    "wof:placetype":"venue"
},
  "geometry": {"coordinates":[3.8177359104,51.0667152405],"type":"Point"}
}