{
  "type": "Feature",
  "properties": {
    "addr:full":"Avenue F\u00e9licien Rops 34 Namur Namur 5000",
    "addr:housenumber":"34",
    "addr:postcode":"5000",
    "addr:street":"Avenue Fe\u0301Licien Rops",
    "iso:country":"BE",
    "sg:address":"Avenue F\u00e9licien Rops 34",
    "sg:city":"Namur",
    "sg:classifiers":[
        {
            "category":"Health Services",
            "subcategory":"Health Practitioner",
            "type":"Services"
        }
    ],
    "sg:phone":"+32 81 22 90 82",
    "sg:postcode":"5000",
    "sg:province":"Namur",
    "sg:tags":[
        "physiotherapist"
    ],
    "wof:name":"Bertrand Vinciane",
    "wof:placetype":"venue"
},
  "geometry": {"coordinates":[4.8589940071,50.4463386536],"type":"Point"}
}