{
  "type": "Feature",
  "properties": {
    "iso:country":"BE",
    "sg:address":"Knesselarestraat 189",
    "sg:city":"Beernem",
    "sg:orig_category":"Installation de menuiserie en bois and plastique. Charpentes and couvertures",
    "sg:phone":"+32 50 78 19 01",
    "sg:postcode":"8730",
    "sg:province":"West-Vlaanderen",
    "wof:name":"Luc Claeysier",
    "wof:placetype":"venue"
},
  "geometry": {"coordinates":[3.377188921,51.1542053223],"type":"Point"}
}