{
  "type": "Feature",
  "properties": {
    "iso:country":"BE",
    "sg:address":"Rue De La Tonne 265",
    "sg:city":"Li\u00c8ge",
    "sg:orig_category":"Groenten and fruit Gh",
    "sg:phone":"+32 4 226 84 67",
    "sg:postcode":"4000",
    "sg:province":"Li\u00e8ge",
    "wof:name":"Vincenzo Buccoleri",
    "wof:placetype":"venue"
},
  "geometry": {"coordinates":[5.5554389954,50.6627388],"type":"Point"}
}