{
  "type": "Feature",
  "properties": {
    "addr:full":"Boulevard De Waterloo 65 Bruxelles Bruxelles-Capitale 1000",
    "addr:housenumber":"65",
    "addr:postcode":"1000",
    "addr:street":"Boulevard De Waterloo",
    "iso:country":"BE",
    "sg:address":"Boulevard De Waterloo 65",
    "sg:city":"Bruxelles",
    "sg:classifiers":[
        {
            "category":"Shopping",
            "subcategory":"Shoes",
            "type":"Retail Goods"
        }
    ],
    "sg:phone":"+32 2 512 52 06",
    "sg:postcode":"1000",
    "sg:province":"Bruxelles-Capitale",
    "sg:tags":[
        "slipper",
        "-"
    ],
    "wof:name":"Rossetti",
    "wof:placetype":"venue"
},
  "geometry": {"coordinates":[4.3552417755,50.8360786438],"type":"Point"}
}