{
  "type": "Feature",
  "properties": {
    "addr:full":"Rue De Pinchart 6 Ottignies-louvain-la-neuve (ottignies) Brabant Wallon 1340",
    "addr:housenumber":"6",
    "addr:postcode":"1340",
    "addr:street":"Rue De Pinchart",
    "iso:country":"BE",
    "sg:address":"Rue De Pinchart 6",
    "sg:city":"Ottignies-louvain-la-neuve (ottignies)",
    "sg:classifiers":[
        {
            "category":"Health Services",
            "subcategory":"Dentist",
            "type":"Services"
        }
    ],
    "sg:phone":"+32 10 41 12 31",
    "sg:postcode":"1340",
    "sg:province":"Brabant Wallon",
    "wof:name":"Volcher Jacques",
    "wof:placetype":"venue"
},
  "geometry": {"coordinates":[4.5542998314,50.6700935364],"type":"Point"}
}