{
  "type": "Feature",
  "properties": {
    "addr:full":"Putsebaan 10 Keerbergen Vlaams-Brabant 3140",
    "addr:housenumber":"10",
    "addr:postcode":"3140",
    "addr:street":"Putsebaan",
    "iso:country":"BE",
    "sg:address":"Putsebaan 10",
    "sg:city":"Keerbergen",
    "sg:classifiers":[
        {
            "category":"Personal",
            "subcategory":"Beauty Salon",
            "type":"Services"
        }
    ],
    "sg:phone":"+32 15 51 51 46",
    "sg:postcode":"3140",
    "sg:province":"Vlaams-Brabant",
    "sg:tags":[
        "de",
        "coiffure"
    ],
    "wof:name":"Coiffure My Lady",
    "wof:placetype":"venue"
},
  "geometry": {"coordinates":[4.6280670166,51.0048065186],"type":"Point"}
}