{
  "type": "Feature",
  "properties": {
    "iso:country":"BE",
    "sg:address":"Bistweg 72",
    "sg:city":"Ranst",
    "sg:orig_category":"Traitement and rev\u00eatement des m\u00e9taux",
    "sg:phone":"+32 3 475 07 00",
    "sg:postcode":"2520",
    "sg:province":"Antwerpen",
    "wof:name":"Claes Mechanics",
    "wof:placetype":"venue"
},
  "geometry": {"coordinates":[4.6173458099,51.1884117126],"type":"Point"}
}