{
  "type": "Feature",
  "properties": {
    "addr:full":"Beverlo-dorp 4-12 Beverlo Limburg 3581",
    "addr:housenumber":"4-12",
    "addr:postcode":"3581",
    "addr:street":"Beverlo-Dorp",
    "iso:country":"BE",
    "sg:address":"Beverlo-dorp 4-12",
    "sg:city":"Beverlo",
    "sg:classifiers":[
        {
            "category":"Shopping",
            "subcategory":"Bridal",
            "type":"Retail Goods"
        }
    ],
    "sg:phone":"+32 11 34 15 79",
    "sg:postcode":"3581",
    "sg:province":"Limburg",
    "sg:tags":[
        "gown"
    ],
    "wof:name":"Mathyro Nv",
    "wof:placetype":"venue"
},
  "geometry": {"coordinates":[5.2223620415,51.0879821777],"type":"Point"}
}