{
  "type": "Feature",
  "properties": {
    "iso:country":"BE",
    "sg:address":"Rue Des Bruy\u00c8res 89",
    "sg:city":"Leglise",
    "sg:orig_category":"Gespecialiseerde residenti\u00eble bouw Tuinen",
    "sg:phone":"+32 63 43 37 22",
    "sg:postcode":"6860",
    "sg:province":"Luxembourg",
    "wof:name":"Etienne D'ansembourg",
    "wof:placetype":"venue"
},
  "geometry": {"coordinates":[5.4626297951,49.8007392883],"type":"Point"}
}