{
  "type": "Feature",
  "properties": {
    "iso:country":"BE",
    "sg:address":"Rue De Dilbeek 16",
    "sg:city":"Sint-jans-molenbeek/molenbeek-saint-jean",
    "sg:orig_category":"Evaluation and estimation de biens immobiliers",
    "sg:phone":"+32 2 411 06 11",
    "sg:postcode":"1080",
    "sg:province":"Bruxelles-Capitale",
    "wof:name":"I.g.r.",
    "wof:placetype":"venue"
},
  "geometry": {"coordinates":[4.3141970634,50.8489761353],"type":"Point"}
}