{
  "type": "Feature",
  "properties": {
    "addr:full":"Kloosterstraat 25 Kinrooi Limburg 3640",
    "addr:housenumber":"25",
    "addr:postcode":"3640",
    "addr:street":"Kloosterstraat",
    "iso:country":"BE",
    "sg:address":"Kloosterstraat 25",
    "sg:city":"Kinrooi",
    "sg:orig_category":"M\u00e9decines alternatives",
    "sg:phone":"+32 89 70 33 02",
    "sg:postcode":"3640",
    "sg:province":"Limburg",
    "wof:name":"L. Lemahieu",
    "wof:placetype":"venue"
},
  "geometry": {"coordinates":[5.7373180389,51.1439323425],"type":"Point"}
}