{
  "type": "Feature",
  "properties": {
    "addr:full":"Brugmannlaan 529 Ukkel/uccle Bruxelles-Capitale 1180",
    "addr:housenumber":"529",
    "addr:postcode":"1180",
    "addr:street":"Brugmannlaan;/",
    "iso:country":"BE",
    "sg:address":"Brugmannlaan 529",
    "sg:city":"Ukkel/uccle",
    "sg:orig_category":"Banken and kredietinstellingen",
    "sg:phone":"+32 2 343 13 97",
    "sg:postcode":"1180",
    "sg:province":"Bruxelles-Capitale",
    "wof:name":"Banque Epargne Patriotiq.",
    "wof:placetype":"venue"
},
  "geometry": {"coordinates":[4.3407449722,50.8026313782],"type":"Point"}
}