{
  "type": "Feature",
  "properties": {
    "addr:full":"De Smet De Naeyerlaan 43 Blankenberge West-Vlaanderen 8370",
    "addr:housenumber":"43",
    "addr:postcode":"8370",
    "addr:street":"De Smet De Naeyerlaan",
    "iso:country":"BE",
    "sg:address":"De Smet De Naeyerlaan 43",
    "sg:city":"Blankenberge",
    "sg:classifiers":[
        {
            "category":"Fast Food",
            "type":"Food & Drink"
        }
    ],
    "sg:phone":"+32 50 41 29 42",
    "sg:postcode":"8370",
    "sg:province":"West-Vlaanderen",
    "sg:tags":[
        "meeneem",
        "restaurant"
    ],
    "wof:name":"Mosselhuis",
    "wof:placetype":"venue"
},
  "geometry": {"coordinates":[3.1229701042,51.3127403259],"type":"Point"}
}