{
  "type": "Feature",
  "properties": {
    "iso:country":"BE",
    "sg:address":"Rue Des Charrettes 14",
    "sg:city":"Paliseul",
    "sg:orig_category":"Travaux de pl\u00e2trage",
    "sg:phone":"+32 61 53 35 69",
    "sg:postcode":"6850",
    "sg:province":"Luxembourg",
    "wof:name":"Jean Etienne",
    "wof:placetype":"venue"
},
  "geometry": {"coordinates":[5.1392707825,49.9077796936],"type":"Point"}
}