{
  "type": "Feature",
  "properties": {
    "addr:full":"Rue De Cayoit 21 Leuze-en-hainaut Hainaut 7903",
    "addr:housenumber":"21",
    "addr:postcode":"7903",
    "addr:street":"Rue De Cayoit",
    "iso:country":"BE",
    "sg:address":"Rue De Cayoit 21",
    "sg:city":"Leuze-en-hainaut",
    "sg:orig_category":"Rundveehouders",
    "sg:phone":"+32 69 66 48 42",
    "sg:postcode":"7903",
    "sg:province":"Hainaut",
    "wof:name":"Fredy Delaunoit",
    "wof:placetype":"venue"
},
  "geometry": {"coordinates":[3.6512649059,50.6117897034],"type":"Point"}
}