{
  "type": "Feature",
  "properties": {
    "iso:country":"BE",
    "sg:address":"Stationsteenweg 238",
    "sg:city":"Nijlen",
    "sg:orig_category":"V\u00eatements, chaussures and accessoires Gr",
    "sg:phone":"+32 3 480 40 96",
    "sg:postcode":"2560",
    "sg:province":"Antwerpen",
    "wof:name":"Bib Promotions",
    "wof:placetype":"venue"
},
  "geometry": {"coordinates":[4.6200637817,51.1496353149],"type":"Point"}
}