{
  "type": "Feature",
  "properties": {
    "addr:full":"Leembosstraat 3 Wielsbeke West-Vlaanderen 8710",
    "addr:housenumber":"3",
    "addr:postcode":"8710",
    "addr:street":"Leembosstraat;West-Vlaanderen",
    "iso:country":"BE",
    "sg:address":"Leembosstraat 3",
    "sg:city":"Wielsbeke",
    "sg:orig_category":"Rundveehouders",
    "sg:phone":"+32 56 70 33 24",
    "sg:postcode":"8710",
    "sg:province":"West-Vlaanderen",
    "wof:name":"Bernard Soetaert",
    "wof:placetype":"venue"
},
  "geometry": {"coordinates":[3.3268339634,50.8870658875],"type":"Point"}
}