{
  "type": "Feature",
  "properties": {
    "addr:full":"Achtelsestraat 89 Hoogstraten Antwerpen 2320",
    "addr:housenumber":"89",
    "addr:postcode":"2320",
    "addr:street":"Achtelsestraat",
    "iso:country":"BE",
    "sg:address":"Achtelsestraat 89",
    "sg:city":"Hoogstraten",
    "sg:classifiers":[
        {
            "category":"Wholesale",
            "subcategory":"Machinery & Supplies",
            "type":"Manufacturing & Wholesale Goods"
        }
    ],
    "sg:phone":"+32 800 88 900",
    "sg:postcode":"2320",
    "sg:province":"Antwerpen",
    "sg:tags":[
        "refrigeration",
        "-",
        "industrial",
        "commercial",
        "equipment"
    ],
    "wof:name":"Coolworld Rentals Bvba",
    "wof:placetype":"venue"
},
  "geometry": {"coordinates":[4.7653021812,51.3899650574],"type":"Point"}
}