{
  "type": "Feature",
  "properties": {
    "addr:full":"Domaine De Bellevue 166 Durbuy Luxembourg 6940",
    "addr:housenumber":"166",
    "addr:postcode":"6940",
    "iso:country":"BE",
    "sg:address":"Domaine De Bellevue 166",
    "sg:city":"Durbuy",
    "sg:orig_category":"Installation de menuiserie en bois and plastique",
    "sg:phone":"+32 86 32 28 66",
    "sg:postcode":"6940",
    "sg:province":"Luxembourg",
    "wof:name":"Jean-pierre Giarelli",
    "wof:placetype":"venue"
},
  "geometry": {"coordinates":[5.4543361664,50.3515777588],"type":"Point"}
}