{
  "type": "Feature",
  "properties": {
    "addr:full":"Vieux Chemin De Mons 1b Tournai (vaulx) Hainaut 7536",
    "addr:housenumber":"1b",
    "addr:postcode":"7536",
    "addr:street":"Vieux Chemin De Mons",
    "iso:country":"BE",
    "sg:address":"Vieux Chemin De Mons 1b",
    "sg:city":"Tournai (vaulx)",
    "sg:classifiers":[
        {
            "category":"Professional",
            "subcategory":"Accounting & Tax Preparation",
            "type":"Services"
        }
    ],
    "sg:phone":"+32 69 21 35 25",
    "sg:postcode":"7536",
    "sg:province":"Hainaut",
    "sg:tags":[
        "bookkeeper"
    ],
    "wof:name":"Duquenne Ch",
    "wof:placetype":"venue"
},
  "geometry": {"coordinates":[3.4260430336,50.597240448],"type":"Point"}
}