{
  "type": "Feature",
  "properties": {
    "iso:country":"BE",
    "sg:address":"Steenweg 61",
    "sg:city":"Gavere (asper)",
    "sg:orig_category":"Non-Classified Establishments",
    "sg:phone":"+32 9 384 14 76",
    "sg:postcode":"9890",
    "sg:province":"Oost-Vlaanderen",
    "wof:name":"Stanley Fashion",
    "wof:placetype":"venue"
},
  "geometry": {"coordinates":[3.651695013,50.9142112732],"type":"Point"}
}