{
  "type": "Feature",
  "properties": {
    "addr:full":"Krommestraat 2 Ardooie West-Vlaanderen 8850",
    "addr:housenumber":"2",
    "addr:postcode":"8850",
    "addr:street":"Krommestraat",
    "iso:country":"BE",
    "sg:address":"Krommestraat 2",
    "sg:city":"Ardooie",
    "sg:orig_category":"Enseignement maternel and primaire",
    "sg:phone":"+32 51 20 38 33",
    "sg:postcode":"8850",
    "sg:province":"West-Vlaanderen",
    "wof:name":"Vrije Basisschool",
    "wof:placetype":"venue"
},
  "geometry": {"coordinates":[3.1705439091,50.9598846436],"type":"Point"}
}