{
  "type": "Feature",
  "properties": {
    "iso:country":"BE",
    "sg:address":"Place De Longchamps 13",
    "sg:city":"Eghezee",
    "sg:classifiers":[
        {
            "category":"Communications",
            "subcategory":"Radio Station",
            "type":"Services"
        }
    ],
    "sg:phone":"+32 81 51 21 21",
    "sg:postcode":"5310",
    "sg:province":"Namur",
    "sg:tags":[
        "diffusion",
        "production",
        "de",
        "programme"
    ],
    "wof:name":"Tam Tam Radio",
    "wof:placetype":"venue"
},
  "geometry": {"coordinates":[4.8962597847,50.5766143799],"type":"Point"}
}