{
  "type": "Feature",
  "properties": {
    "iso:country":"BE",
    "sg:address":"Moortselestraat 61-76-78",
    "sg:city":"Oosterzele",
    "sg:orig_category":"Cliniques and h\u00f4pitaux",
    "sg:phone":"+32 9 362 78 54",
    "sg:postcode":"9860",
    "sg:province":"Oost-Vlaanderen",
    "wof:name":"De Kiem Therapeutische Gemeenschap",
    "wof:placetype":"venue"
},
  "geometry": {"coordinates":[3.8105750084,50.9456481934],"type":"Point"}
}