{
  "type": "Feature",
  "properties": {
    "iso:country":"BE",
    "sg:address":"Lammerdries 26",
    "sg:city":"Olen",
    "sg:orig_category":"Non-Classified Establishments",
    "sg:phone":"+32 14 28 55 60",
    "sg:postcode":"2250",
    "sg:province":"Antwerpen",
    "wof:name":"Tops Foods",
    "wof:placetype":"venue"
},
  "geometry": {"coordinates":[4.9065208435,51.1517486572],"type":"Point"}
}