{
  "type": "Feature",
  "properties": {
    "addr:full":"Reepstraat 101b Sint-gillis-waas Oost-Vlaanderen 9170",
    "addr:housenumber":"101b",
    "addr:postcode":"9170",
    "addr:street":"Reepstraat",
    "iso:country":"BE",
    "sg:address":"Reepstraat 101b",
    "sg:city":"Sint-gillis-waas",
    "sg:orig_category":"Solar protection - Outside",
    "sg:phone":"+32 3 770 50 71",
    "sg:postcode":"9170",
    "sg:province":"Oost-Vlaanderen",
    "wof:name":"Rotthier Zonnetenten-willems Bvba",
    "wof:placetype":"venue"
},
  "geometry": {"coordinates":[4.1022391319,51.2276573181],"type":"Point"}
}