{
  "type": "Feature",
  "properties": {
    "iso:country":"BE",
    "sg:address":"Clos Du Pr\u00e9 Madame 6",
    "sg:city":"Namur (vedrin - Daussoulx)",
    "sg:classifiers":[
        {
            "category":"Professional",
            "subcategory":"Accounting & Tax Preparation",
            "type":"Services"
        }
    ],
    "sg:phone":"+32 81 21 30 00",
    "sg:postcode":"5020",
    "sg:province":"Namur",
    "sg:tags":[
        "accountant"
    ],
    "wof:name":"Dave J-p",
    "wof:placetype":"venue"
},
  "geometry": {"coordinates":[4.8800997734,50.5070762634],"type":"Point"}
}