{
  "type": "Feature",
  "properties": {
    "addr:full":"Keelstraat 4 Tielt-winge Vlaams-Brabant 3391",
    "addr:housenumber":"4",
    "addr:postcode":"3391",
    "addr:street":"Keelstraat",
    "iso:country":"BE",
    "sg:address":"Keelstraat 4",
    "sg:city":"Tielt-winge",
    "sg:orig_category":"Producteurs de fruits",
    "sg:phone":"+32 16 63 32 40",
    "sg:postcode":"3391",
    "sg:province":"Vlaams-Brabant",
    "wof:name":"Alois Ver Berne",
    "wof:placetype":"venue"
},
  "geometry": {"coordinates":[4.9073848724,50.8934440613],"type":"Point"}
}