{
  "type": "Feature",
  "properties": {
    "iso:country":"BE",
    "sg:address":"Geenend 17",
    "sg:city":"Retie",
    "sg:classifiers":[
        {
            "category":"Arena",
            "subcategory":"Sports Club",
            "type":"Entertainment"
        }
    ],
    "sg:phone":"+32 14 37 36 80",
    "sg:postcode":"2470",
    "sg:province":"Antwerpen",
    "wof:name":"De Bempdekens",
    "wof:placetype":"venue"
},
  "geometry": {"coordinates":[5.0738840103,51.2609062195],"type":"Point"}
}