{
  "type": "Feature",
  "properties": {
    "iso:country":"BE",
    "sg:address":"Rue Saint-jacques 24",
    "sg:city":"Farciennes",
    "sg:classifiers":[
        {
            "category":"Personal",
            "subcategory":"Beauty Salon",
            "type":"Services"
        }
    ],
    "sg:phone":"+32 71 38 08 02",
    "sg:postcode":"6240",
    "sg:province":"Hainaut",
    "sg:tags":[
        "lady",
        "-",
        "hairdressing"
    ],
    "wof:name":"Hairstyl",
    "wof:placetype":"venue"
},
  "geometry": {"coordinates":[4.5540270805,50.428314209],"type":"Point"}
}