{
  "type": "Feature",
  "properties": {
    "iso:country":"BE",
    "sg:address":"Chauss\u00c9e De Maubeuge 548",
    "sg:city":"Mons",
    "sg:orig_category":"Journaux",
    "sg:phone":"+32 65 84 35 75",
    "sg:postcode":"7024",
    "sg:province":"Hainaut",
    "wof:name":"Chez Claude & Annie",
    "wof:placetype":"venue"
},
  "geometry": {"coordinates":[3.9485740662,50.4223556519],"type":"Point"}
}