{
  "type": "Feature",
  "properties": {
    "addr:full":"Avenue Henri Jaspar 91b7 Sint-gillis/saint-gilles Bruxelles-Capitale 1060",
    "addr:housenumber":"91b7",
    "addr:postcode":"1060",
    "addr:street":"Avenue Henri Jaspar",
    "iso:country":"BE",
    "sg:address":"Avenue Henri Jaspar 91b7",
    "sg:city":"Sint-gillis/saint-gilles",
    "sg:orig_category":"Avocats and conseillers juridiques",
    "sg:phone":"+32 2 544 19 99",
    "sg:postcode":"1060",
    "sg:province":"Bruxelles-Capitale",
    "wof:name":"Johan Van Renterghem",
    "wof:placetype":"venue"
},
  "geometry": {"coordinates":[4.3500618935,50.8333244324],"type":"Point"}
}