{
  "type": "Feature",
  "properties": {
    "addr:full":"Markt 3b Waregem West-Vlaanderen 8790",
    "addr:housenumber":"3b",
    "addr:postcode":"8790",
    "addr:street":"Markt",
    "iso:country":"BE",
    "sg:address":"Markt 3b",
    "sg:city":"Waregem",
    "sg:classifiers":[
        {
            "category":"Bars & Pubs",
            "type":"Food & Drink"
        }
    ],
    "sg:phone":"+32 56 60 22 16",
    "sg:postcode":"8790",
    "sg:province":"West-Vlaanderen",
    "wof:name":"Radio 2 Caf\u00e9",
    "wof:placetype":"venue"
},
  "geometry": {"coordinates":[3.4325520992,50.8865089417],"type":"Point"}
}