{
  "type": "Feature",
  "properties": {
    "addr:full":"Hollebeek 39 Temse Oost-Vlaanderen 9140",
    "addr:housenumber":"39",
    "addr:postcode":"9140",
    "addr:street":"Hollebeek",
    "iso:country":"BE",
    "sg:address":"Hollebeek 39",
    "sg:city":"Temse",
    "sg:classifiers":[
        {
            "category":"Manufacturing",
            "subcategory":"Metals",
            "type":"Manufacturing & Wholesale Goods"
        }
    ],
    "sg:phone":"+32 3 711 00 71",
    "sg:postcode":"9140",
    "sg:province":"Oost-Vlaanderen",
    "sg:tags":[
        "ornamental",
        "work",
        "-"
    ],
    "wof:name":"Van Schoor P",
    "wof:placetype":"venue"
},
  "geometry": {"coordinates":[4.2354440689,51.1326828003],"type":"Point"}
}