{
  "type": "Feature",
  "properties": {
    "iso:country":"BE",
    "sg:address":"Molenstraat 92",
    "sg:city":"Dilbeek",
    "sg:orig_category":"Etalage- and showroomontwerpers",
    "sg:phone":"+32 2 582 67 78",
    "sg:postcode":"1700",
    "sg:province":"Vlaams-Brabant",
    "wof:name":"Bartholomeus Van Lint",
    "wof:placetype":"venue"
},
  "geometry": {"coordinates":[4.2072558403,50.866897583],"type":"Point"}
}