{
  "type": "Feature",
  "properties": {
    "iso:country":"BE",
    "sg:address":"Lubbeeksestraat 14",
    "sg:city":"Boutersem",
    "sg:classifiers":[
        {
            "category":"Personal",
            "subcategory":"Beauty Salon",
            "type":"Services"
        }
    ],
    "sg:phone":"+32 16 73 32 29",
    "sg:postcode":"3370",
    "sg:province":"Vlaams-Brabant",
    "sg:tags":[
        "de",
        "coiffure"
    ],
    "wof:name":"Timmy De Putter",
    "wof:placetype":"venue"
},
  "geometry": {"coordinates":[4.8618769646,50.8324699402],"type":"Point"}
}