{
  "type": "Feature",
  "properties": {
    "addr:full":"Chauss\u00e9e De Bruxelles 316 Waterloo Brabant Wallon 1410",
    "addr:housenumber":"316",
    "addr:postcode":"1410",
    "addr:street":"Chausse\u0301E De Bruxelles",
    "iso:country":"BE",
    "sg:address":"Chauss\u00e9e De Bruxelles 316",
    "sg:city":"Waterloo",
    "sg:classifiers":[
        {
            "category":"Professional",
            "subcategory":"Computer Services",
            "type":"Services"
        }
    ],
    "sg:phone":"+32 2 351 23 00",
    "sg:postcode":"1410",
    "sg:province":"Brabant Wallon",
    "sg:tags":[
        "-",
        "processing",
        "data"
    ],
    "wof:name":"Boss Computers",
    "wof:placetype":"venue"
},
  "geometry": {"coordinates":[4.4001760483,50.7121276855],"type":"Point"}
}