{
  "type": "Feature",
  "properties": {
    "addr:full":"Drieslaan 78 Wevelgem (gullegem) West-Vlaanderen 8560",
    "addr:housenumber":"78",
    "addr:postcode":"8560",
    "addr:street":"Drieslaan",
    "iso:country":"BE",
    "sg:address":"Drieslaan 78",
    "sg:city":"Wevelgem (gullegem)",
    "sg:orig_category":"Non-Classified Establishments",
    "sg:phone":"+32 56 25 77 57",
    "sg:postcode":"8560",
    "sg:province":"West-Vlaanderen",
    "wof:name":"Era Benelux",
    "wof:placetype":"venue"
},
  "geometry": {"coordinates":[3.1754500866,50.8463783264],"type":"Point"}
}