{
  "type": "Feature",
  "properties": {
    "addr:full":"Hasseltweg 188b Genk Limburg 3600",
    "addr:housenumber":"188b",
    "addr:postcode":"3600",
    "addr:street":"Hasseltweg",
    "iso:country":"BE",
    "sg:address":"Hasseltweg 188b",
    "sg:city":"Genk",
    "sg:classifiers":[
        {
            "category":"Home & Garden",
            "subcategory":"Building Materials",
            "type":"Retail Goods"
        }
    ],
    "sg:phone":"+32 89 61 28 55",
    "sg:postcode":"3600",
    "sg:province":"Limburg",
    "sg:tags":[
        "veranda"
    ],
    "wof:name":"Greenhouse Veranda's",
    "wof:placetype":"venue"
},
  "geometry": {"coordinates":[5.4551172256,50.960899353],"type":"Point"}
}