{
  "type": "Feature",
  "properties": {
    "addr:full":"Godveerdegemstraat 25 Zottegem Oost-Vlaanderen 9620",
    "addr:housenumber":"25",
    "addr:postcode":"9620",
    "addr:street":"Godveerdegemstraat",
    "iso:country":"BE",
    "sg:address":"Godveerdegemstraat 25",
    "sg:city":"Zottegem",
    "sg:orig_category":"Loodgieterij, verwarming and sanitaire installaties",
    "sg:phone":"+32 9 361 03 57",
    "sg:postcode":"9620",
    "sg:province":"Oost-Vlaanderen",
    "wof:name":"Roelandt Bart",
    "wof:placetype":"venue"
},
  "geometry": {"coordinates":[3.8183269501,50.8647956848],"type":"Point"}
}