{
  "type": "Feature",
  "properties": {
    "addr:full":"Place Emile De Lalieux 45 Nivelles Brabant Wallon 1400",
    "addr:housenumber":"45",
    "addr:postcode":"1400",
    "addr:street":"Place Emile De Lalieux",
    "iso:country":"BE",
    "sg:address":"Place Emile De Lalieux 45",
    "sg:city":"Nivelles",
    "sg:classifiers":[
        {
            "category":"Home & Garden",
            "subcategory":"Home Furnishings",
            "type":"Retail Goods"
        }
    ],
    "sg:phone":"+32 67 22 01 50",
    "sg:postcode":"1400",
    "sg:province":"Brabant Wallon",
    "sg:tags":[
        "interior",
        "decoration"
    ],
    "wof:name":"Beauty Home",
    "wof:placetype":"venue"
},
  "geometry": {"coordinates":[4.3289690018,50.5980682373],"type":"Point"}
}