{
  "type": "Feature",
  "properties": {
    "iso:country":"BE",
    "sg:address":"Rue De La Barri\u00e8re De Fer 40",
    "sg:city":"Mouscron (dottignies)",
    "sg:classifiers":[
        {
            "category":"Wholesale",
            "subcategory":"Fruits & Vegetables",
            "type":"Manufacturing & Wholesale Goods"
        }
    ],
    "sg:phone":"+32 56 48 55 71",
    "sg:postcode":"7711",
    "sg:province":"Hainaut",
    "sg:tags":[
        "whol",
        "-",
        "potato"
    ],
    "wof:name":"Frit Express Nv",
    "wof:placetype":"venue"
},
  "geometry": {"coordinates":[3.3190340996,50.727848053],"type":"Point"}
}