{
  "type": "Feature",
  "properties": {
    "addr:full":"Zeedijk 317-318 Koksijde West-Vlaanderen 8670",
    "addr:housenumber":"317-318",
    "addr:postcode":"8670",
    "addr:street":"Zeedijk",
    "iso:country":"BE",
    "sg:address":"Zeedijk 317-318",
    "sg:city":"Koksijde",
    "sg:orig_category":"RESTAURANTS: H\u00d4TELS",
    "sg:phone":"+32 58 51 13 49",
    "sg:postcode":"8670",
    "sg:province":"West-Vlaanderen",
    "wof:name":"Hotel Vieren",
    "wof:placetype":"venue"
},
  "geometry": {"coordinates":[2.6343419552,51.1209259033],"type":"Point"}
}