{
  "type": "Feature",
  "properties": {
    "iso:country":"BE",
    "sg:address":"Rue Lieutenant Freddy Wampach 38",
    "sg:city":"Bruxelles (woluwe-saint-lambert)",
    "sg:classifiers":[
        {
            "category":"Professional",
            "subcategory":"Art Services",
            "type":"Services"
        }
    ],
    "sg:phone":"+32 2 770 30 01",
    "sg:postcode":"1200",
    "sg:province":"Bruxelles-Capitale",
    "sg:tags":[
        "photographer"
    ],
    "wof:name":"Vanhoutte Sprl",
    "wof:placetype":"venue"
},
  "geometry": {"coordinates":[4.4160189629,50.8434638977],"type":"Point"}
}