{
  "type": "Feature",
  "properties": {
    "iso:country":"BE",
    "sg:address":"Pervijzestraat 6",
    "sg:city":"Veurne",
    "sg:orig_category":"Rundveehouders Varkenskwekers",
    "sg:phone":"+32 58 23 36 55",
    "sg:postcode":"8630",
    "sg:province":"West-Vlaanderen",
    "wof:name":"Guido Sys",
    "wof:placetype":"venue"
},
  "geometry": {"coordinates":[2.748611927,51.0915985107],"type":"Point"}
}