{
  "type": "Feature",
  "properties": {
    "addr:full":"Joos Van Den Steenelei 2 Deurne Antwerpen 2100",
    "addr:housenumber":"2",
    "addr:postcode":"2100",
    "addr:street":"Joos Van Den Steenelei",
    "iso:country":"BE",
    "sg:address":"Joos Van Den Steenelei 2",
    "sg:city":"Deurne",
    "sg:classifiers":[
        {
            "category":"Restaurant",
            "type":"Food & Drink"
        }
    ],
    "sg:phone":"+32 3 324 69 37",
    "sg:postcode":"2100",
    "sg:province":"Antwerpen",
    "wof:name":"Restaurant Bonaparte",
    "wof:placetype":"venue"
},
  "geometry": {"coordinates":[4.4728479385,51.2205467224],"type":"Point"}
}