{
  "type": "Feature",
  "properties": {
    "iso:country":"BE",
    "sg:address":"Bruggestraat 126",
    "sg:city":"Torhout",
    "sg:orig_category":"Microsoft. Ordinateurs and \u00e9quipement informatique",
    "sg:phone":"+32 50 21 38 57",
    "sg:postcode":"8820",
    "sg:province":"West-Vlaanderen",
    "wof:name":"Mmpcs",
    "wof:placetype":"venue"
},
  "geometry": {"coordinates":[3.1127231121,51.0787773132],"type":"Point"}
}