{
  "type": "Feature",
  "properties": {
    "addr:full":"Chauss\u00e9e De Wavre 724 Bruxelles (etterbeek) Bruxelles-Capitale 1040",
    "addr:housenumber":"724",
    "addr:postcode":"1040",
    "addr:street":"Chausse\u0301E De Wavre",
    "iso:country":"BE",
    "sg:address":"Chauss\u00e9e De Wavre 724",
    "sg:city":"Bruxelles (etterbeek)",
    "sg:classifiers":[
        {
            "category":"Banks & Credit Unions",
            "subcategory":"Financial Services",
            "type":"Services"
        }
    ],
    "sg:phone":"+32 2 647 58 20",
    "sg:postcode":"1040",
    "sg:province":"Bruxelles-Capitale",
    "sg:tags":[
        "financing"
    ],
    "wof:name":"Agence Maurice Noel",
    "wof:placetype":"venue"
},
  "geometry": {"coordinates":[4.3903408051,50.8303794861],"type":"Point"}
}