{
  "type": "Feature",
  "properties": {
    "addr:full":"Molenstraat 10a Aalter Oost-Vlaanderen 9880",
    "addr:housenumber":"10a",
    "addr:postcode":"9880",
    "addr:street":"Molenstraat",
    "iso:country":"BE",
    "sg:address":"Molenstraat 10a",
    "sg:city":"Aalter",
    "sg:classifiers":[
        {
            "category":"Professional",
            "subcategory":"Accounting & Tax Preparation",
            "type":"Services"
        }
    ],
    "sg:phone":"+32 9 374 48 55",
    "sg:postcode":"9880",
    "sg:province":"Oost-Vlaanderen",
    "sg:tags":[
        "accountant"
    ],
    "wof:name":"Derweduwen M",
    "wof:placetype":"venue"
},
  "geometry": {"coordinates":[3.4534640312,51.0882263184],"type":"Point"}
}