{
  "type": "Feature",
  "properties": {
    "addr:full":"Grote Steenweg 111 Landen (groot) Vlaams-Brabant 3400",
    "addr:housenumber":"111",
    "addr:postcode":"3400",
    "addr:street":"Grote Steenweg;Groot Vlaams-Brabant",
    "iso:country":"BE",
    "sg:address":"Grote Steenweg 111",
    "sg:city":"Landen (groot)",
    "sg:orig_category":"Jardinage",
    "sg:phone":"+32 16 78 21 37",
    "sg:postcode":"3400",
    "sg:province":"Vlaams-Brabant",
    "wof:name":"Vijvercenter Het Bloempke",
    "wof:placetype":"venue"
},
  "geometry": {"coordinates":[5.0078539848,50.7843284607],"type":"Point"}
}