{
  "type": "Feature",
  "properties": {
    "addr:full":"Sint-jansstraat 5 Staden West-Vlaanderen 8840",
    "addr:housenumber":"5",
    "addr:postcode":"8840",
    "addr:street":"Sint-Jansstraat",
    "iso:country":"BE",
    "sg:address":"Sint-jansstraat 5",
    "sg:city":"Staden",
    "sg:orig_category":"Reisbureaus",
    "sg:phone":"+32 51 70 05 16",
    "sg:postcode":"8840",
    "sg:province":"West-Vlaanderen",
    "wof:name":"V&d Travel",
    "wof:placetype":"venue"
},
  "geometry": {"coordinates":[3.0156478882,50.9737434387],"type":"Point"}
}