{
  "type": "Feature",
  "properties": {
    "addr:full":"Oude Kouterdreef 152 Zele Oost-Vlaanderen 9240",
    "addr:housenumber":"152",
    "addr:postcode":"9240",
    "addr:street":"Oude Kouterdreef",
    "iso:country":"BE",
    "sg:address":"Oude Kouterdreef 152",
    "sg:city":"Zele",
    "sg:orig_category":"Huishoudapparaten, televisies and radio's Verhuur televisie- and audiovisuele apparatuur",
    "sg:phone":"+32 52 44 61 07",
    "sg:postcode":"9240",
    "sg:province":"Oost-Vlaanderen",
    "wof:name":"Publi Sound",
    "wof:placetype":"venue"
},
  "geometry": {"coordinates":[4.0293588638,51.0583114624],"type":"Point"}
}