{
  "type": "Feature",
  "properties": {
    "addr:full":"Boulevard Saint-michel 17 Etterbeek Bruxelles-Capitale 1040",
    "addr:housenumber":"17",
    "addr:postcode":"1040",
    "addr:street":"Boulevard Saint-Michel",
    "iso:country":"BE",
    "sg:address":"Boulevard Saint-michel 17",
    "sg:city":"Etterbeek",
    "sg:classifiers":[
        {
            "category":"Restaurant",
            "type":"Food & Drink"
        }
    ],
    "sg:phone":"+32 2 735 49 89",
    "sg:postcode":"1040",
    "sg:province":"Bruxelles-Capitale",
    "wof:name":"The Open",
    "wof:placetype":"venue"
},
  "geometry": {"coordinates":[4.406414032,50.8359947205],"type":"Point"}
}