{
  "type": "Feature",
  "properties": {
    "addr:full":"Rue Modeste Cornil 42 Charleroi Hainaut 6041",
    "addr:housenumber":"42",
    "addr:postcode":"6041",
    "addr:street":"Rue Modeste Cornil;Hainaut",
    "iso:country":"BE",
    "sg:address":"Rue Modeste Cornil 42",
    "sg:city":"Charleroi",
    "sg:orig_category":"Slagers",
    "sg:phone":"+32 71 35 31 18",
    "sg:postcode":"6041",
    "sg:province":"Hainaut",
    "wof:name":"Boucherie Baugniet",
    "wof:placetype":"venue"
},
  "geometry": {"coordinates":[4.4314317703,50.4685935974],"type":"Point"}
}