{
  "type": "Feature",
  "properties": {
    "iso:country":"BE",
    "sg:address":"Rue Henri De Dinant 9",
    "sg:city":"Li\u00e8ge 1 (li\u00e8ge 2)",
    "sg:classifiers":[
        {
            "category":"Bars & Pubs",
            "type":"Food & Drink"
        }
    ],
    "sg:phone":"+32 4 342 14 94",
    "sg:postcode":"4020",
    "sg:province":"Li\u00e8ge",
    "wof:name":"Instant (club L')",
    "wof:placetype":"venue"
},
  "geometry": {"coordinates":[5.5831451416,50.6413574219],"type":"Point"}
}