{
  "type": "Feature",
  "properties": {
    "iso:country":"BE",
    "sg:address":"Aartselaarstraat 88",
    "sg:city":"Hoboken",
    "sg:orig_category":"Meubles D\u00e9taillants, Am\u00e9nagement de B\u00e2timents et de Cuisines. R\u00e9paration and restauration de meubles",
    "sg:phone":"+32 3 828 44 53",
    "sg:postcode":"2660",
    "sg:province":"Antwerpen",
    "wof:name":"Milystyle",
    "wof:placetype":"venue"
},
  "geometry": {"coordinates":[4.3614602089,51.1763839722],"type":"Point"}
}