{
  "type": "Feature",
  "properties": {
    "addr:full":"Vierschaarstraat 8 Kortrijk West-Vlaanderen 8500",
    "addr:housenumber":"8",
    "addr:postcode":"8500",
    "addr:street":"Vierschaarstraat",
    "iso:country":"BE",
    "sg:address":"Vierschaarstraat 8",
    "sg:city":"Kortrijk",
    "sg:classifiers":[
        {
            "category":"Building & Trades",
            "subcategory":"Construction",
            "type":"Services"
        }
    ],
    "sg:phone":"+32 56 20 47 47",
    "sg:postcode":"8500",
    "sg:province":"West-Vlaanderen",
    "sg:tags":[
        "ceiling"
    ],
    "wof:name":"Estrikor Nv",
    "wof:placetype":"venue"
},
  "geometry": {"coordinates":[3.2770810127,50.8215637207],"type":"Point"}
}