{
  "type": "Feature",
  "properties": {
    "iso:country":"BE",
    "sg:address":"Rue Saint G\u00c9r\u00c9on 41",
    "sg:city":"Lessines",
    "sg:orig_category":"Kapsalons",
    "sg:phone":"+32 68 33 21 95",
    "sg:postcode":"7864",
    "sg:province":"Hainaut",
    "wof:name":"Coiffure Martine",
    "wof:placetype":"venue"
},
  "geometry": {"coordinates":[3.846118927,50.7305374146],"type":"Point"}
}