{
  "type": "Feature",
  "properties": {
    "addr:full":"Rue Rosier Bois 1 Rixensart (rosi\u00e8res) Brabant Wallon 1331",
    "addr:housenumber":"1;1331",
    "addr:street":"Rue Rosier Bois",
    "iso:country":"BE",
    "sg:address":"Rue Rosier Bois 1",
    "sg:city":"Rixensart (rosi\u00e8res)",
    "sg:classifiers":[
        {
            "category":"Professional",
            "subcategory":"Testing Lab",
            "type":"Services"
        }
    ],
    "sg:phone":"+32 2 653 70 19",
    "sg:postcode":"1331",
    "sg:province":"Brabant Wallon",
    "sg:tags":[
        "chemist"
    ],
    "wof:name":"Pharmacie Rosier-bois Sa",
    "wof:placetype":"venue"
},
  "geometry": {"coordinates":[4.5451002121,50.73072052],"type":"Point"}
}