{
  "type": "Feature",
  "properties": {
    "iso:country":"BE",
    "sg:address":"Au Rosay 77",
    "sg:city":"Herve (chaineux)",
    "sg:classifiers":[
        {
            "category":"Farming",
            "subcategory":"Livestock Farm",
            "type":"Manufacturing & Wholesale Goods"
        }
    ],
    "sg:phone":"+32 87 67 56 00",
    "sg:postcode":"4650",
    "sg:province":"Li\u00e8ge",
    "sg:tags":[
        "buyer"
    ],
    "wof:name":"Dorthu G",
    "wof:placetype":"venue"
},
  "geometry": {"coordinates":[5.7943401337,50.6393814087],"type":"Point"}
}