{
  "type": "Feature",
  "properties": {
    "addr:full":"Rue De Menin 53 Bruxelles (molenbeek-saint-jean) Bruxelles-Capitale 1080",
    "addr:housenumber":"53",
    "addr:postcode":"1080",
    "addr:street":"Rue De Menin",
    "iso:country":"BE",
    "sg:address":"Rue De Menin 53",
    "sg:city":"Bruxelles (molenbeek-saint-jean)",
    "sg:classifiers":[
        {
            "category":"Utilities",
            "subcategory":"Refuse",
            "type":"Services"
        }
    ],
    "sg:phone":"+32 2 411 09 13",
    "sg:postcode":"1080",
    "sg:province":"Bruxelles-Capitale",
    "sg:tags":[
        "catering"
    ],
    "wof:name":"Eurokwizien Bvba",
    "wof:placetype":"venue"
},
  "geometry": {"coordinates":[4.328127861,50.8550796509],"type":"Point"}
}