{
  "type": "Feature",
  "properties": {
    "addr:full":"Honsfeld 78 B\u00dcllingen/bullange Li\u00e8ge 4760",
    "addr:housenumber":"78",
    "addr:postcode":"4760",
    "addr:street":"Honsfeld",
    "iso:country":"BE",
    "sg:address":"Honsfeld 78",
    "sg:city":"B\u00dcllingen/bullange",
    "sg:orig_category":"Eleveurs de bovins",
    "sg:phone":"+32 80 64 71 55",
    "sg:postcode":"4760",
    "sg:province":"Li\u00e8ge",
    "wof:name":"Edgar Jost",
    "wof:placetype":"venue"
},
  "geometry": {"coordinates":[6.2768001556,50.3823928833],"type":"Point"}
}