{
  "type": "Feature",
  "properties": {
    "addr:full":"Route De La Bruy\u00c8re 16 Eghezee Namur 5310",
    "addr:housenumber":"16",
    "addr:postcode":"5310",
    "addr:street":"Route De La Bruye\u0300Re;Namur",
    "iso:country":"BE",
    "sg:address":"Route De La Bruy\u00c8re 16",
    "sg:city":"Eghezee",
    "sg:orig_category":"Herstellingen and onderhoud van auto's Onderdelen and accessoires voor auto's Opel OK Quality Cars V",
    "sg:phone":"+32 81 81 33 33",
    "sg:postcode":"5310",
    "sg:province":"Namur",
    "wof:name":"Garage Piret",
    "wof:placetype":"venue"
},
  "geometry": {"coordinates":[4.9095578194,50.5840072632],"type":"Point"}
}