{
  "type": "Feature",
  "properties": {
    "iso:country":"BE",
    "sg:address":"Bergense Steenweg 1095b",
    "sg:city":"Anderlecht",
    "sg:orig_category":"Begrafeniswezen",
    "sg:phone":"+32 2 522 81 48",
    "sg:postcode":"1070",
    "sg:province":"Bruxelles-Capitale",
    "wof:name":"J. D\u00b4hoore",
    "wof:placetype":"venue"
},
  "geometry": {"coordinates":[4.2950749397,50.8232765198],"type":"Point"}
}