{
  "type": "Feature",
  "properties": {
    "iso:country":"BE",
    "sg:address":"Chauss\u00c9e De Bruxelles A425",
    "sg:city":"Waterloo",
    "sg:orig_category":"Pi\u00e8ces and accessoires de v\u00e9hicules automobiles D\u00e9taillants en pi\u00e8ces and accessoires de voitures",
    "sg:phone":"+32 2 354 77 35",
    "sg:postcode":"1410",
    "sg:province":"Brabant Wallon",
    "wof:name":"Laermans",
    "wof:placetype":"venue"
},
  "geometry": {"coordinates":[4.3980250359,50.7174263],"type":"Point"}
}