{
  "type": "Feature",
  "properties": {
    "iso:country":"BE",
    "sg:address":"Rue De La Buissi\u00c8re 9",
    "sg:city":"Estinnes",
    "sg:orig_category":"Verhuur bouwmachines Verhuur doe-het-zelf materiaal",
    "sg:phone":"+32 65 58 63 21",
    "sg:postcode":"7120",
    "sg:province":"Hainaut",
    "wof:name":"Repamine",
    "wof:placetype":"venue"
},
  "geometry": {"coordinates":[4.0828499794,50.391658783],"type":"Point"}
}