{
  "type": "Feature",
  "properties": {
    "iso:country":"BE",
    "sg:address":"Standplaats 62",
    "sg:city":"Duffel",
    "sg:classifiers":[
        {
            "category":"Personal",
            "subcategory":"Beauty Salon",
            "type":"Services"
        }
    ],
    "sg:phone":"+32 15 31 00 96",
    "sg:postcode":"2570",
    "sg:province":"Antwerpen",
    "sg:tags":[
        "de",
        "coiffure"
    ],
    "wof:name":"Emiel Van Hoof",
    "wof:placetype":"venue"
},
  "geometry": {"coordinates":[4.4914040565,51.090385437],"type":"Point"}
}