{
  "type": "Feature",
  "properties": {
    "addr:full":"10 Plein 3700 Tongeren 10",
    "addr:housenumber":"10",
    "addr:postcode":"3700",
    "addr:street":"10 Plein",
    "iso:country":"BE",
    "sg:address":"10",
    "sg:city":"Plein 3700 Tongeren",
    "sg:classifiers":[
        {
            "category":"Wholesale",
            "subcategory":"Meat",
            "type":"Manufacturing & Wholesale Goods"
        }
    ],
    "sg:phone":"+32 12 23 20 76",
    "sg:postcode":"10",
    "sg:tags":[
        "food",
        "cooked",
        "product",
        "related"
    ],
    "wof:name":"Charcuterie Bovie Nv",
    "wof:placetype":"venue"
},
  "geometry": {"coordinates":[5.4634141922,50.7796478271],"type":"Point"}
}