{
  "type": "Feature",
  "properties": {
    "iso:country":"BE",
    "sg:address":"Leuvense Steenweg 38",
    "sg:city":"Sint-joost-ten-node/saint-josse-ten-noode",
    "sg:orig_category":"Dancings and nachtclubs Ruimtes voor conferenties, recepties and feesten",
    "sg:phone":"+32 2 227 39 72",
    "sg:postcode":"1210",
    "sg:province":"Bruxelles-Capitale",
    "wof:name":"Mirano Continental",
    "wof:placetype":"venue"
},
  "geometry": {"coordinates":[4.3714442253,50.8493614197],"type":"Point"}
}