{
  "type": "Feature",
  "properties": {
    "addr:full":"Millesteenstraat 87 Moorslede West-Vlaanderen 8890",
    "addr:housenumber":"87",
    "addr:postcode":"8890",
    "addr:street":"Millesteenstraat",
    "iso:country":"BE",
    "sg:address":"Millesteenstraat 87",
    "sg:city":"Moorslede",
    "sg:orig_category":"Computers and computerapparatuur Diverse informatica-activiteiten Huishoudapparaten, televisies and ",
    "sg:phone":"+32 56 50 65 65",
    "sg:postcode":"8890",
    "sg:province":"West-Vlaanderen",
    "wof:name":"Media Markt",
    "wof:placetype":"venue"
},
  "geometry": {"coordinates":[3.1085569859,50.8427352905],"type":"Point"}
}