{
  "type": "Feature",
  "properties": {
    "addr:full":"Chauss\u00c9e De Ninove 688 Anderlecht/anderlecht Bruxelles-Capitale 1070",
    "addr:housenumber":"688",
    "addr:postcode":"1070",
    "addr:street":"Chausse\u0301E De Ninove",
    "iso:country":"BE",
    "sg:address":"Chauss\u00c9e De Ninove 688",
    "sg:city":"Anderlecht/anderlecht",
    "sg:orig_category":"Pain, p\u00e2tisseries and confiseries",
    "sg:phone":"+32 2 521 02 79",
    "sg:postcode":"1070",
    "sg:province":"Bruxelles-Capitale",
    "wof:name":"P\u00c2tiss. Tartine & Chocol.",
    "wof:placetype":"venue"
},
  "geometry": {"coordinates":[4.2980690002,50.8467178345],"type":"Point"}
}