{
  "type": "Feature",
  "properties": {
    "addr:full":"Rue Chauss\u00c9e 29 Awans Li\u00e8ge 4342",
    "addr:housenumber":"29",
    "addr:postcode":"4342",
    "addr:street":"Rue Chausse\u0301E",
    "iso:country":"BE",
    "sg:address":"Rue Chauss\u00c9e 29",
    "sg:city":"Awans",
    "sg:orig_category":"Meubles D\u00e9taillants, Am\u00e9nagement de B\u00e2timents et de Cuisines",
    "sg:phone":"+32 4 257 47 42",
    "sg:postcode":"4342",
    "sg:province":"Li\u00e8ge",
    "wof:name":"Mibelco",
    "wof:placetype":"venue"
},
  "geometry": {"coordinates":[5.4641771317,50.6824493408],"type":"Point"}
}