{
  "type": "Feature",
  "properties": {
    "addr:full":"Linkhoutsestraat Halen (zelem) Limburg 3545",
    "addr:postcode":"3545",
    "addr:street":"Linkhoutsestraat",
    "iso:country":"BE",
    "sg:address":"Linkhoutsestraat",
    "sg:city":"Halen (zelem)",
    "sg:classifiers":[
        {
            "category":"Arena",
            "subcategory":"Sports Club",
            "type":"Entertainment"
        }
    ],
    "sg:phone":"+32 13 44 44 14",
    "sg:postcode":"3545",
    "sg:province":"Limburg",
    "wof:name":"Tc Zelem",
    "wof:placetype":"venue"
},
  "geometry": {"coordinates":[5.1235618591,50.9774360657],"type":"Point"}
}