{
  "type": "Feature",
  "properties": {
    "addr:full":"Corneel Heymanstraat 6 Oostende (stene) West-Vlaanderen 8400",
    "addr:housenumber":"6",
    "addr:postcode":"8400",
    "addr:street":"Corneel Heymanstraat",
    "iso:country":"BE",
    "sg:address":"Corneel Heymanstraat 6",
    "sg:city":"Oostende (stene)",
    "sg:classifiers":[
        {
            "category":"Banks & Credit Unions",
            "subcategory":"Investment Brokerage",
            "type":"Services"
        }
    ],
    "sg:phone":"+32 59 80 12 97",
    "sg:postcode":"8400",
    "sg:province":"West-Vlaanderen",
    "sg:tags":[
        "repair",
        "-",
        "installation",
        "sanitary",
        "article"
    ],
    "wof:name":"Central Dalia Bvba",
    "wof:placetype":"venue"
},
  "geometry": {"coordinates":[2.9357481003,51.2060813904],"type":"Point"}
}