{
  "type": "Feature",
  "properties": {
    "addr:full":"Charles Woestelaan 151 Jette/jette Bruxelles-Capitale 1090",
    "addr:housenumber":"151",
    "addr:postcode":"1090",
    "addr:street":"Charles Woestelaan",
    "iso:country":"BE",
    "sg:address":"Charles Woestelaan 151",
    "sg:city":"Jette/jette",
    "sg:orig_category":"Artsen and specialisten",
    "sg:phone":"+32 2 426 65 16",
    "sg:postcode":"1090",
    "sg:province":"Bruxelles-Capitale",
    "wof:name":"Carine Deflorenne",
    "wof:placetype":"venue"
},
  "geometry": {"coordinates":[4.3335938454,50.873878479],"type":"Point"}
}