{
  "type": "Feature",
  "properties": {
    "addr:full":"Staatsbaan 123 Zulte Oost-Vlaanderen 9870",
    "addr:housenumber":"123",
    "addr:postcode":"9870",
    "addr:street":"Staatsbaan",
    "iso:country":"BE",
    "sg:address":"Staatsbaan 123",
    "sg:city":"Zulte",
    "sg:classifiers":[
        {
            "category":"Food & Beverages",
            "subcategory":"Chocolate",
            "type":"Retail Goods"
        }
    ],
    "sg:phone":"+32 9 388 41 86",
    "sg:postcode":"9870",
    "sg:province":"Oost-Vlaanderen",
    "sg:tags":[
        "confectionery",
        "-"
    ],
    "wof:name":"Leonidas",
    "wof:placetype":"venue"
},
  "geometry": {"coordinates":[3.4451019764,50.9224243164],"type":"Point"}
}