{
  "type": "Feature",
  "properties": {
    "iso:country":"BE",
    "sg:address":"Rue Lucien Foss\u00c9prez 41",
    "sg:city":"Profondeville",
    "sg:orig_category":"Traitements param\u00e9dicaux",
    "sg:phone":"+32 81 43 43 36",
    "sg:postcode":"5170",
    "sg:province":"Namur",
    "wof:name":"D. M\u00c9lin",
    "wof:placetype":"venue"
},
  "geometry": {"coordinates":[4.8109412193,50.3872528076],"type":"Point"}
}