{
  "type": "Feature",
  "properties": {
    "iso:country":"BE",
    "sg:address":"Route De Saint-g\u00e9rard 286",
    "sg:city":"Namur (w\u00e9pion)",
    "sg:classifiers":[
        {
            "category":"Banks & Credit Unions",
            "subcategory":"Financial Services",
            "type":"Services"
        }
    ],
    "sg:phone":"+32 81 46 08 64",
    "sg:postcode":"5100",
    "sg:province":"Namur",
    "sg:tags":[
        "financing"
    ],
    "wof:name":"Confort Cr\u00e9dit Sa",
    "wof:placetype":"venue"
},
  "geometry": {"coordinates":[4.8427000046,50.4140701294],"type":"Point"}
}