{
  "type": "Feature",
  "properties": {
    "addr:full":"Rue Du Basson 50 Charleroi Hainaut 6001",
    "addr:housenumber":"50",
    "addr:postcode":"6001",
    "addr:street":"Rue Du Basson;Hainaut",
    "iso:country":"BE",
    "sg:address":"Rue Du Basson 50",
    "sg:city":"Charleroi",
    "sg:orig_category":"M\u00e9decins and sp\u00e9cialistes",
    "sg:phone":"+32 71 36 91 16",
    "sg:postcode":"6001",
    "sg:province":"Hainaut",
    "wof:name":"Pierre Burteau",
    "wof:placetype":"venue"
},
  "geometry": {"coordinates":[4.4436101913,50.4001312256],"type":"Point"}
}