{
  "type": "Feature",
  "properties": {
    "addr:full":"Driesstraat 43 Sint-truiden Limburg 3800",
    "addr:housenumber":"43",
    "addr:postcode":"3800",
    "addr:street":"Driesstraat",
    "iso:country":"BE",
    "sg:address":"Driesstraat 43",
    "sg:city":"Sint-truiden",
    "sg:classifiers":[
        {
            "category":"Personal",
            "subcategory":"Piercing",
            "type":"Services"
        }
    ],
    "sg:phone":"+32 11 69 25 43",
    "sg:postcode":"3800",
    "sg:province":"Limburg",
    "sg:tags":[
        "piercings",
        "tatouages"
    ],
    "wof:name":"Body Decoration",
    "wof:placetype":"venue"
},
  "geometry": {"coordinates":[5.2388501167,50.8223571777],"type":"Point"}
}