{
  "type": "Feature",
  "properties": {
    "addr:full":"Rue Des Bl\u00c9s 12 Waremme Li\u00e8ge 4300",
    "addr:housenumber":"12",
    "addr:postcode":"4300",
    "addr:street":"Rue Des Ble\u0301S",
    "iso:country":"BE",
    "sg:address":"Rue Des Bl\u00c9s 12",
    "sg:city":"Waremme",
    "sg:orig_category":"Sportclubs",
    "sg:phone":"+32 19 32 77 15",
    "sg:postcode":"4300",
    "sg:province":"Li\u00e8ge",
    "wof:name":"T.c. Oreye Club",
    "wof:placetype":"venue"
},
  "geometry": {"coordinates":[5.2643351555,50.6953201294],"type":"Point"}
}