{
  "type": "Feature",
  "properties": {
    "iso:country":"BE",
    "sg:address":"Brugsesteenweg 95",
    "sg:city":"Kuurne",
    "sg:orig_category":"Appareils de pulv\u00e9risation Fab",
    "sg:phone":"+32 56 35 03 82",
    "sg:postcode":"8520",
    "sg:province":"West-Vlaanderen",
    "wof:name":"Dursin Thierry",
    "wof:placetype":"venue"
},
  "geometry": {"coordinates":[3.2695469856,50.8502082825],"type":"Point"}
}