{
  "type": "Feature",
  "properties": {
    "addr:full":"Oudaan 22-24 Antwerpen Antwerpen 2000",
    "addr:postcode":"22-24;2000",
    "addr:street":"Oudaan",
    "iso:country":"BE",
    "sg:address":"Oudaan 22-24",
    "sg:city":"Antwerpen",
    "sg:classifiers":[
        {
            "category":"Professional",
            "subcategory":"Lawyer & Legal Services",
            "type":"Services"
        }
    ],
    "sg:phone":"+32 3 213 26 48",
    "sg:postcode":"2000",
    "sg:province":"Antwerpen",
    "wof:name":"Goemans Filip",
    "wof:placetype":"venue"
},
  "geometry": {"coordinates":[4.4037661552,51.2157478333],"type":"Point"}
}