{
  "type": "Feature",
  "properties": {
    "iso:country":"BE",
    "sg:address":"Vic. Georges Minnestr. 6",
    "sg:city":"Moeskroen/mouscron",
    "sg:orig_category":"Instellingen voor mindervalide volwassenen",
    "sg:phone":"+32 56 48 57 07",
    "sg:postcode":"7711",
    "sg:province":"Hainaut",
    "wof:name":"La Cigali\u00c8re",
    "wof:placetype":"venue"
},
  "geometry": {"coordinates":[3.2929000854,50.7344207764],"type":"Point"}
}