{
  "type": "Feature",
  "properties": {
    "addr:full":"Neesveld 39 Huldenberg Vlaams-Brabant 3040",
    "addr:housenumber":"39",
    "addr:postcode":"3040",
    "addr:street":"Neesveld",
    "iso:country":"BE",
    "sg:address":"Neesveld 39",
    "sg:city":"Huldenberg",
    "sg:orig_category":"Rev\u00eatements pour sols and murs. Peinture",
    "sg:phone":"+32 2 688 06 75",
    "sg:postcode":"3040",
    "sg:province":"Vlaams-Brabant",
    "wof:name":"Alex Gahy",
    "wof:placetype":"venue"
},
  "geometry": {"coordinates":[4.5925221443,50.7840614319],"type":"Point"}
}