{
  "type": "Feature",
  "properties": {
    "iso:country":"BE",
    "sg:address":"Chauss\u00e9e De Ruisbroek 117",
    "sg:city":"Bruxelles (forest)",
    "sg:classifiers":[
        {
            "category":"Wholesale",
            "subcategory":"Vending Machines",
            "type":"Manufacturing & Wholesale Goods"
        }
    ],
    "sg:phone":"+32 2 332 12 45",
    "sg:postcode":"1190",
    "sg:province":"Bruxelles-Capitale",
    "sg:tags":[
        "pulley",
        "belting"
    ],
    "wof:name":"Industrial Products Sprl",
    "wof:placetype":"venue"
},
  "geometry": {"coordinates":[4.3130850792,50.7986831665],"type":"Point"}
}