{
  "type": "Feature",
  "properties": {
    "addr:full":"Karestraat 1a Halen (zelem) Limburg 3545",
    "addr:housenumber":"1a",
    "addr:postcode":"3545",
    "addr:street":"Karestraat",
    "iso:country":"BE",
    "sg:address":"Karestraat 1a",
    "sg:city":"Halen (zelem)",
    "sg:classifiers":[
        {
            "category":"Real Estate",
            "subcategory":"Architect",
            "type":"Services"
        }
    ],
    "sg:phone":"+32 13 46 15 03",
    "sg:postcode":"3545",
    "sg:province":"Limburg",
    "wof:name":"Claes G",
    "wof:placetype":"venue"
},
  "geometry": {"coordinates":[5.1112480164,50.9753913879],"type":"Point"}
}