{
  "type": "Feature",
  "properties": {
    "iso:country":"BE",
    "sg:address":"Braambeslei 24",
    "sg:city":"Kapellen",
    "sg:classifiers":[
        {
            "category":"Shopping",
            "subcategory":"Jewelry",
            "type":"Retail Goods"
        }
    ],
    "sg:phone":"+32 3 666 35 46",
    "sg:postcode":"2950",
    "sg:province":"Antwerpen",
    "sg:tags":[
        "jeweller",
        "-"
    ],
    "wof:name":"De Sadelaer L",
    "wof:placetype":"venue"
},
  "geometry": {"coordinates":[4.45601511,51.3556175232],"type":"Point"}
}