{
  "type": "Feature",
  "properties": {
    "addr:full":"Statiestraat 86 Zwijndrecht Antwerpen 2070",
    "addr:housenumber":"86",
    "addr:postcode":"2070",
    "addr:street":"Statiestraat",
    "iso:country":"BE",
    "sg:address":"Statiestraat 86",
    "sg:city":"Zwijndrecht",
    "sg:orig_category":"Quincailleries. Electrom\u00e9nager, t\u00e9l\u00e9visions and radios",
    "sg:phone":"+32 3 254 02 22",
    "sg:postcode":"2070",
    "sg:province":"Antwerpen",
    "wof:name":"Elektro Johan",
    "wof:placetype":"venue"
},
  "geometry": {"coordinates":[4.3290557861,51.2158279419],"type":"Point"}
}