{
  "type": "Feature",
  "properties": {
    "addr:full":"Rue De Mortagne 129b Leuze-en-hainaut (pipaix) Hainaut 7904",
    "addr:housenumber":"129b",
    "addr:postcode":"7904",
    "addr:street":"Rue De Mortagne",
    "iso:country":"BE",
    "sg:address":"Rue De Mortagne 129b",
    "sg:city":"Leuze-en-hainaut (pipaix)",
    "sg:classifiers":[
        {
            "category":"Professional",
            "subcategory":"Management & Consulting",
            "type":"Services"
        }
    ],
    "sg:phone":"+32 69 67 26 61",
    "sg:postcode":"7904",
    "sg:province":"Hainaut",
    "sg:tags":[
        "consultant"
    ],
    "wof:name":"Performance Group Corporation Sa",
    "wof:placetype":"venue"
},
  "geometry": {"coordinates":[3.579775095,50.5767745972],"type":"Point"}
}