{
  "type": "Feature",
  "properties": {
    "addr:full":"Industriepark Rostijne 19 Zelzate Oost-Vlaanderen 9060",
    "addr:housenumber":"19",
    "addr:postcode":"9060",
    "addr:street":"Industriepark Rostijne",
    "iso:country":"BE",
    "sg:address":"Industriepark Rostijne 19",
    "sg:city":"Zelzate",
    "sg:classifiers":[
        {
            "category":"Retail",
            "subcategory":"Auto Repair",
            "type":"Services"
        }
    ],
    "sg:phone":"+32 9 345 09 70",
    "sg:postcode":"9060",
    "sg:province":"Oost-Vlaanderen",
    "sg:tags":[
        "garage"
    ],
    "wof:name":"Opel Grensland Bvba",
    "wof:placetype":"venue"
},
  "geometry": {"coordinates":[3.8305959702,51.1886863708],"type":"Point"}
}