{
  "type": "Feature",
  "properties": {
    "addr:full":"Oostjachtpark 1 Sint-niklaas Oost-Vlaanderen 9100",
    "addr:housenumber":"1",
    "addr:postcode":"9100",
    "addr:street":"Oostjachtpark",
    "iso:country":"BE",
    "sg:address":"Oostjachtpark 1",
    "sg:city":"Sint-niklaas",
    "sg:classifiers":[
        {
            "category":"Manufacturing",
            "subcategory":"Chemicals & Compounds",
            "type":"Manufacturing & Wholesale Goods"
        }
    ],
    "sg:phone":"+32 3 780 33 10",
    "sg:postcode":"9100",
    "sg:province":"Oost-Vlaanderen",
    "sg:tags":[
        "agricultural"
    ],
    "wof:name":"Scotts Belgium Bvba",
    "wof:placetype":"venue"
},
  "geometry": {"coordinates":[4.1742529869,51.1440658569],"type":"Point"}
}