{
  "type": "Feature",
  "properties": {
    "iso:country":"BE",
    "sg:address":"Wisembach 23",
    "sg:city":"Fauvillers",
    "sg:orig_category":"Offices du tourisme",
    "sg:phone":"+32 63 60 13 36",
    "sg:postcode":"6637",
    "sg:province":"Luxembourg",
    "wof:name":"Syndicat D\u00b4initiative",
    "wof:placetype":"venue"
},
  "geometry": {"coordinates":[5.6638197899,49.8519592285],"type":"Point"}
}