{
  "type": "Feature",
  "properties": {
    "addr:full":"Uitbreidingsstraat 1 Antwerpen Antwerpen 2018",
    "addr:housenumber":"1",
    "addr:postcode":"2018",
    "addr:street":"Uitbreidingsstraat",
    "iso:country":"BE",
    "sg:address":"Uitbreidingsstraat 1",
    "sg:city":"Antwerpen",
    "sg:orig_category":"Brood, gebak and snoepgoed",
    "sg:phone":"+32 3 281 26 17",
    "sg:postcode":"2018",
    "sg:province":"Antwerpen",
    "wof:name":"Panos",
    "wof:placetype":"venue"
},
  "geometry": {"coordinates":[4.4311199188,51.1999092102],"type":"Point"}
}