{
  "type": "Feature",
  "properties": {
    "iso:country":"BE",
    "sg:address":"Rue Du Mont Doyelle 25",
    "sg:city":"Frasnes-lez-anvaing",
    "sg:orig_category":"Artsen and specialisten",
    "sg:phone":"+32 69 76 80 29",
    "sg:postcode":"7912",
    "sg:province":"Hainaut",
    "wof:name":"Philippe Rustin",
    "wof:placetype":"venue"
},
  "geometry": {"coordinates":[3.5833609104,50.7010917664],"type":"Point"}
}