{
  "type": "Feature",
  "properties": {
    "iso:country":"BE",
    "sg:address":"Dornestraat 4",
    "sg:city":"Maaseik",
    "sg:orig_category":"Activit\u00e9s r\u00e9cr\u00e9atives diverses. Installations and terrains de sport hors centres sportifs. Restauran",
    "sg:phone":"+32 89 85 72 14",
    "sg:postcode":"3680",
    "sg:province":"Limburg",
    "wof:name":"De Wouterbron",
    "wof:placetype":"venue"
},
  "geometry": {"coordinates":[5.791285038,51.0954208374],"type":"Point"}
}