{
  "type": "Feature",
  "properties": {
    "iso:country":"BE",
    "sg:address":"Place Alphonse Favresse 69",
    "sg:city":"La Hulpe",
    "sg:classifiers":[
        {
            "category":"Banks & Credit Unions",
            "subcategory":"Bank",
            "type":"Services"
        }
    ],
    "sg:phone":"+32 2 652 54 08",
    "sg:postcode":"1310",
    "sg:province":"Brabant Wallon",
    "sg:tags":[
        "savings-banks"
    ],
    "wof:name":"Korman J",
    "wof:placetype":"venue"
},
  "geometry": {"coordinates":[4.4965100288,50.7378387451],"type":"Point"}
}