{
  "type": "Feature",
  "properties": {
    "iso:country":"BE",
    "sg:address":"Rue Fosses Berger 32",
    "sg:city":"Olne",
    "sg:classifiers":[
        {
            "category":"Health Services",
            "subcategory":"Health Practitioner",
            "type":"Services"
        }
    ],
    "sg:phone":"+32 87 26 72 27",
    "sg:postcode":"4877",
    "sg:province":"Li\u00e8ge",
    "sg:tags":[
        "therapist",
        "speech"
    ],
    "wof:name":"Geron N",
    "wof:placetype":"venue"
},
  "geometry": {"coordinates":[5.7377772331,50.5900192261],"type":"Point"}
}