{
  "type": "Feature",
  "properties": {
    "addr:full":"Kinderstraat 6 Kruibeke Oost-Vlaanderen 9150",
    "addr:housenumber":"6",
    "addr:postcode":"9150",
    "addr:street":"Kinderstraat",
    "iso:country":"BE",
    "sg:address":"Kinderstraat 6",
    "sg:city":"Kruibeke",
    "sg:orig_category":"Rundveehouders Varkenskwekers",
    "sg:phone":"+32 3 774 14 85",
    "sg:postcode":"9150",
    "sg:province":"Oost-Vlaanderen",
    "wof:name":"Jeroom De Ryck",
    "wof:placetype":"venue"
},
  "geometry": {"coordinates":[4.2787599564,51.1528091431],"type":"Point"}
}