{
  "type": "Feature",
  "properties": {
    "addr:full":"Boulevard Anspach 123 Bruxelles Bruxelles-Capitale 1000",
    "addr:housenumber":"123",
    "addr:postcode":"1000",
    "addr:street":"Boulevard Anspach",
    "iso:country":"BE",
    "sg:address":"Boulevard Anspach 123",
    "sg:city":"Bruxelles",
    "sg:classifiers":[
        {
            "category":"Retail",
            "subcategory":"Pet Boarding",
            "type":"Services"
        }
    ],
    "sg:phone":"+32 2 512 62 32",
    "sg:postcode":"1000",
    "sg:province":"Bruxelles-Capitale",
    "sg:tags":[
        "-",
        "silverware"
    ],
    "wof:name":"Cristallerie Anspach",
    "wof:placetype":"venue"
},
  "geometry": {"coordinates":[4.347782135,50.8466072083],"type":"Point"}
}