{
  "type": "Feature",
  "properties": {
    "addr:full":"Industriestrasse 22 Eupen Li\u00e8ge 4700",
    "addr:housenumber":"22",
    "addr:postcode":"4700",
    "addr:street":"Industriestrasse",
    "iso:country":"BE",
    "sg:address":"Industriestrasse 22",
    "sg:city":"Eupen",
    "sg:classifiers":[
        {
            "category":"Airport",
            "subcategory":"International",
            "type":"Transportation"
        }
    ],
    "sg:phone":"+32 87 74 37 74",
    "sg:postcode":"4700",
    "sg:province":"Li\u00e8ge",
    "sg:tags":[
        "-",
        "transport"
    ],
    "wof:name":"Belspeed Sa",
    "wof:placetype":"venue"
},
  "geometry": {"coordinates":[6.0075001717,50.6406707764],"type":"Point"}
}