{
  "type": "Feature",
  "properties": {
    "addr:full":"Pauwelsdreef 76 Stabroek (hoevenen) Antwerpen 2940",
    "addr:housenumber":"76",
    "addr:postcode":"2940",
    "addr:street":"Pauwelsdreef",
    "iso:country":"BE",
    "sg:address":"Pauwelsdreef 76",
    "sg:city":"Stabroek (hoevenen)",
    "sg:classifiers":[
        {
            "category":"Health Services",
            "subcategory":"Health Practitioner",
            "type":"Services"
        }
    ],
    "sg:phone":"+32 3 605 28 41",
    "sg:postcode":"2940",
    "sg:province":"Antwerpen",
    "sg:tags":[
        "therapist",
        "speech"
    ],
    "wof:name":"Verreyken A",
    "wof:placetype":"venue"
},
  "geometry": {"coordinates":[4.39854002,51.3051605225],"type":"Point"}
}