{
  "type": "Feature",
  "properties": {
    "iso:country":"BE",
    "sg:address":"Rue D\u00b4hornu 18",
    "sg:city":"Colfontaine",
    "sg:orig_category":"Slagers",
    "sg:phone":"+32 65 77 77 40",
    "sg:postcode":"7340",
    "sg:province":"Hainaut",
    "wof:name":"Guy Bertiaux",
    "wof:placetype":"venue"
},
  "geometry": {"coordinates":[3.842607975,50.4235343933],"type":"Point"}
}