{
  "type": "Feature",
  "properties": {
    "addr:full":"Sint-catharinastraat 1 Ieper West-Vlaanderen 8900",
    "addr:housenumber":"1",
    "addr:postcode":"8900",
    "addr:street":"Sint-Catharinastraat",
    "iso:country":"BE",
    "sg:address":"Sint-catharinastraat 1",
    "sg:city":"Ieper",
    "sg:orig_category":"Brood, gebak and snoepgoed",
    "sg:phone":"+32 57 21 47 71",
    "sg:postcode":"8900",
    "sg:province":"West-Vlaanderen",
    "wof:name":"Bjorden D'hert",
    "wof:placetype":"venue"
},
  "geometry": {"coordinates":[2.8878018856,50.8472518921],"type":"Point"}
}