{
  "type": "Feature",
  "properties": {
    "addr:full":"Astridplein 37 Grobbendonk Antwerpen 2280",
    "addr:housenumber":"37",
    "addr:postcode":"2280",
    "addr:street":"Astridplein",
    "iso:country":"BE",
    "sg:address":"Astridplein 37",
    "sg:city":"Grobbendonk",
    "sg:orig_category":"Pharmaciens",
    "sg:phone":"+32 14 51 10 90",
    "sg:postcode":"2280",
    "sg:province":"Antwerpen",
    "wof:name":"Verelst Francis",
    "wof:placetype":"venue"
},
  "geometry": {"coordinates":[4.7395200729,51.1921081543],"type":"Point"}
}