{
  "type": "Feature",
  "properties": {
    "iso:country":"BE",
    "sg:address":"Ch De Tournai 4",
    "sg:city":"Leuze-en-hainaut",
    "sg:classifiers":[
        {
            "category":"Transit Center",
            "subcategory":"Freight",
            "type":"Transportation"
        }
    ],
    "sg:phone":"+32 69 66 21 19",
    "sg:postcode":"7900",
    "sg:province":"Hainaut",
    "sg:tags":[
        "metallurgy",
        "pipe",
        "metalworking",
        "sheet"
    ],
    "wof:name":"Entreprises O Malice Sa",
    "wof:placetype":"venue"
},
  "geometry": {"coordinates":[3.6176559925,50.5987358093],"type":"Point"}
}