{
  "type": "Feature",
  "properties": {
    "iso:country":"BE",
    "sg:address":"Lusthof 12",
    "sg:city":"Herentals (noorderwijk)",
    "sg:classifiers":[
        {
            "category":"Cafe",
            "type":"Food & Drink"
        }
    ],
    "sg:phone":"+32 14 26 27 53",
    "sg:postcode":"2200",
    "sg:province":"Antwerpen",
    "sg:tags":[
        "snack-bars"
    ],
    "wof:name":"Billy's Snacks",
    "wof:placetype":"venue"
},
  "geometry": {"coordinates":[4.8366980553,51.1428947449],"type":"Point"}
}