{
  "type": "Feature",
  "properties": {
    "iso:country":"BE",
    "sg:address":"Lostraat 50",
    "sg:city":"Aalter",
    "sg:classifiers":[
        {
            "category":"Health Services",
            "subcategory":"Dentist",
            "type":"Services"
        }
    ],
    "sg:phone":"+32 9 374 62 55",
    "sg:postcode":"9880",
    "sg:province":"Oost-Vlaanderen",
    "wof:name":"Govaert L",
    "wof:placetype":"venue"
},
  "geometry": {"coordinates":[3.450097084,51.0791740417],"type":"Point"}
}