{
  "type": "Feature",
  "properties": {
    "addr:full":"Rue De La Chiennerie 23 Braine-l'alleud Brabant Wallon 1420",
    "addr:housenumber":"23",
    "addr:postcode":"1420",
    "addr:street":"Rue De La Chiennerie",
    "iso:country":"BE",
    "sg:address":"Rue De La Chiennerie 23",
    "sg:city":"Braine-l'alleud",
    "sg:orig_category":"Herstellingen and onderhoud van auto's",
    "sg:phone":"+32 2 384 62 68",
    "sg:postcode":"1420",
    "sg:province":"Brabant Wallon",
    "wof:name":"Carrosserie Maloney",
    "wof:placetype":"venue"
},
  "geometry": {"coordinates":[-0.3389919996,48.4947509766],"type":"Point"}
}