{
  "type": "Feature",
  "properties": {
    "addr:full":"Meulebekesteenweg 20 Oostrozebeke West-Vlaanderen 8780",
    "addr:housenumber":"20",
    "addr:postcode":"8780",
    "addr:street":"Meulebekesteenweg",
    "iso:country":"BE",
    "sg:address":"Meulebekesteenweg 20",
    "sg:city":"Oostrozebeke",
    "sg:classifiers":[
        {
            "category":"Freight",
            "type":"Transportation"
        }
    ],
    "sg:phone":"+32 56 66 61 82",
    "sg:postcode":"8780",
    "sg:province":"West-Vlaanderen",
    "sg:tags":[
        "-",
        "transport"
    ],
    "wof:name":"Bossuyt J Transport",
    "wof:placetype":"venue"
},
  "geometry": {"coordinates":[3.3281879425,50.9223518372],"type":"Point"}
}