{
  "type": "Feature",
  "properties": {
    "addr:full":"Place D'acren 13 Lessines (deux-acren) Hainaut 7864",
    "addr:housenumber":"13",
    "addr:postcode":"7864",
    "addr:street":"Place D'Acren",
    "iso:country":"BE",
    "sg:address":"Place D'acren 13",
    "sg:city":"Lessines (deux-acren)",
    "sg:classifiers":[
        {
            "category":"Health Services",
            "subcategory":"Doctor",
            "type":"Services"
        }
    ],
    "sg:phone":"+32 68 33 63 42",
    "sg:postcode":"7864",
    "sg:province":"Hainaut",
    "sg:tags":[
        "medicinephysicians",
        "surgeon"
    ],
    "wof:name":"Gorlier Laurent",
    "wof:placetype":"venue"
},
  "geometry": {"coordinates":[3.8707389832,50.7259597778],"type":"Point"}
}