{
  "type": "Feature",
  "properties": {
    "iso:country":"BE",
    "sg:address":"Rue Van Campenhout 15",
    "sg:city":"Bruxelles",
    "sg:classifiers":[
        {
            "category":"Organizations",
            "subcategory":"Non-profit Organization",
            "type":"Services"
        }
    ],
    "sg:phone":"+32 2 732 20 09",
    "sg:postcode":"1000",
    "sg:province":"Bruxelles-Capitale",
    "sg:tags":[
        "international",
        "organisation"
    ],
    "wof:name":"Human Rights Watch Asbl",
    "wof:placetype":"venue"
},
  "geometry": {"coordinates":[4.3861179352,50.8476715088],"type":"Point"}
}