{
  "type": "Feature",
  "properties": {
    "addr:full":"Dagmoedstraat 2 Geraardsbergen Oost-Vlaanderen 9500",
    "addr:housenumber":"2",
    "addr:postcode":"9500",
    "addr:street":"Dagmoedstraat",
    "iso:country":"BE",
    "sg:address":"Dagmoedstraat 2",
    "sg:city":"Geraardsbergen",
    "sg:orig_category":"Computers and computerapparatuur Diverse informatica-activiteiten Onderhoud van kantoor- and compute",
    "sg:phone":"+32 54 41 91 69",
    "sg:postcode":"9500",
    "sg:province":"Oost-Vlaanderen",
    "wof:name":"Debcom-de Borre",
    "wof:placetype":"venue"
},
  "geometry": {"coordinates":[3.8843801022,50.7716445923],"type":"Point"}
}