{
  "type": "Feature",
  "properties": {
    "iso:country":"BE",
    "sg:address":"Stationsstraat 13",
    "sg:city":"Zaventem",
    "sg:orig_category":"Viessmann. Plomberie, chauffage and installations sanitaires",
    "sg:phone":"+32 2 721 05 29",
    "sg:postcode":"1930",
    "sg:province":"Vlaams-Brabant",
    "wof:name":"Van Hemelrijck",
    "wof:placetype":"venue"
},
  "geometry": {"coordinates":[4.4726848602,50.8794059753],"type":"Point"}
}