{
  "type": "Feature",
  "properties": {
    "addr:full":"Plantin En Moretuslei 335 Box 55 Antwerpen (borgerhout) Antwerpen 2140",
    "addr:housenumber":"335 box 55",
    "addr:postcode":"2140",
    "addr:street":"Plantin En Moretuslei",
    "iso:country":"BE",
    "sg:address":"Plantin En Moretuslei 335 Box 55",
    "sg:city":"Antwerpen (borgerhout)",
    "sg:classifiers":[
        {
            "category":"Insurance",
            "subcategory":"Insurance Agent",
            "type":"Services"
        }
    ],
    "sg:phone":"+32 3 272 23 53",
    "sg:postcode":"2140",
    "sg:province":"Antwerpen",
    "sg:tags":[
        "broker"
    ],
    "wof:name":"Peeters M",
    "wof:placetype":"venue"
},
  "geometry": {"coordinates":[4.4332199097,51.2137565613],"type":"Point"}
}