{
  "type": "Feature",
  "properties": {
    "iso:country":"BE",
    "sg:address":"Schutterijstraat 25",
    "sg:city":"Bilzen (waltwilder)",
    "sg:classifiers":[
        {
            "category":"Wholesale",
            "subcategory":"Seafood",
            "type":"Manufacturing & Wholesale Goods"
        }
    ],
    "sg:phone":"+32 473 62 21 70",
    "sg:postcode":"3740",
    "sg:province":"Limburg",
    "sg:tags":[
        "whol",
        "fish",
        "-",
        "shellfish"
    ],
    "wof:name":"Biese-fish",
    "wof:placetype":"venue"
},
  "geometry": {"coordinates":[5.5133070946,50.8699760437],"type":"Point"}
}