{
  "type": "Feature",
  "properties": {
    "iso:country":"BE",
    "sg:address":"Route D'eugies 109",
    "sg:city":"Frameries",
    "sg:classifiers":[
        {
            "category":"Home & Garden",
            "subcategory":"Garden Supply",
            "type":"Retail Goods"
        }
    ],
    "sg:phone":"+32 65 51 06 58",
    "sg:postcode":"7080",
    "sg:province":"Hainaut",
    "sg:tags":[
        "seed",
        "-"
    ],
    "wof:name":"Thonet Ets",
    "wof:placetype":"venue"
},
  "geometry": {"coordinates":[3.8895869255,50.3954086304],"type":"Point"}
}