{
  "type": "Feature",
  "properties": {
    "iso:country":"BE",
    "sg:address":"Vissegatstraat 113",
    "sg:city":"Kortenberg",
    "sg:orig_category":"Groententeelt",
    "sg:phone":"+32 2 759 98 18",
    "sg:postcode":"3071",
    "sg:province":"Vlaams-Brabant",
    "wof:name":"Hugo Gielis",
    "wof:placetype":"venue"
},
  "geometry": {"coordinates":[4.577589035,50.9085159302],"type":"Point"}
}