{
  "type": "Feature",
  "properties": {
    "addr:full":"Jan Breydellaan 3 Kortrijk West-Vlaanderen 8500",
    "addr:housenumber":"3",
    "addr:postcode":"8500",
    "addr:street":"Jan Breydellaan",
    "iso:country":"BE",
    "sg:address":"Jan Breydellaan 3",
    "sg:city":"Kortrijk",
    "sg:orig_category":"Services divers aux entreprises. Agences immobili\u00e8res",
    "sg:phone":"+32 56 21 31 34",
    "sg:postcode":"8500",
    "sg:province":"West-Vlaanderen",
    "wof:name":"Endeavour",
    "wof:placetype":"venue"
},
  "geometry": {"coordinates":[3.2789349556,50.8281059265],"type":"Point"}
}