{
  "type": "Feature",
  "properties": {
    "addr:full":"Oude Kuringerbaan 75 Hasselt Limburg 3500",
    "addr:housenumber":"75",
    "addr:postcode":"3500",
    "addr:street":"Oude Kuringerbaan",
    "iso:country":"BE",
    "sg:address":"Oude Kuringerbaan 75",
    "sg:city":"Hasselt",
    "sg:classifiers":[
        {
            "category":"Health Services",
            "subcategory":"Health Practitioner",
            "type":"Services"
        }
    ],
    "sg:phone":"+32 11 26 15 45",
    "sg:postcode":"3500",
    "sg:province":"Limburg",
    "sg:tags":[
        "physiotherapist"
    ],
    "wof:name":"Coenegrachts Juliette",
    "wof:placetype":"venue"
},
  "geometry": {"coordinates":[5.3240380287,50.9348983765],"type":"Point"}
}