{
  "type": "Feature",
  "properties": {
    "addr:full":"Sint-annastraat 21ba Tielt-winge Vlaams-Brabant 3390",
    "addr:housenumber":"21ba",
    "addr:postcode":"3390",
    "addr:street":"Sint-Annastraat",
    "iso:country":"BE",
    "sg:address":"Sint-annastraat 21ba",
    "sg:city":"Tielt-winge",
    "sg:orig_category":"Rundveehouders",
    "sg:phone":"+32 16 63 51 58",
    "sg:postcode":"3390",
    "sg:province":"Vlaams-Brabant",
    "wof:name":"Franciscus Dankaerts",
    "wof:placetype":"venue"
},
  "geometry": {"coordinates":[4.9024600983,50.9377784729],"type":"Point"}
}