{
  "type": "Feature",
  "properties": {
    "addr:full":"Rue De La Station 16 Ohey Brabant Wallon 1360",
    "addr:housenumber":"16",
    "addr:postcode":"1360",
    "addr:street":"Rue De La Station;Wallon",
    "iso:country":"BE",
    "sg:address":"Rue De La Station 16",
    "sg:city":"Ohey",
    "sg:orig_category":"Banques and organismes de cr\u00e9dit",
    "sg:phone":"+32 81 65 84 52",
    "sg:postcode":"1360",
    "sg:province":"Brabant Wallon",
    "wof:name":"Centea",
    "wof:placetype":"venue"
},
  "geometry": {"coordinates":[4.8146052361,50.6239395142],"type":"Point"}
}