{
  "type": "Feature",
  "properties": {
    "iso:country":"BE",
    "sg:address":"Hekkenstraat 7",
    "sg:city":"Dentergem (wakken)",
    "sg:classifiers":[
        {
            "category":"Food & Beverages",
            "subcategory":"Groceries & Convenience Stores",
            "type":"Retail Goods"
        }
    ],
    "sg:phone":"+32 56 60 54 64",
    "sg:postcode":"8720",
    "sg:province":"West-Vlaanderen",
    "sg:tags":[
        "grocer"
    ],
    "wof:name":"Bij Greta",
    "wof:placetype":"venue"
},
  "geometry": {"coordinates":[3.3983669281,50.9347953796],"type":"Point"}
}