{
  "type": "Feature",
  "properties": {
    "addr:full":"Stationstraat 14 Haacht Vlaams-Brabant 3150",
    "addr:housenumber":"14",
    "addr:postcode":"3150",
    "addr:street":"Stationstraat",
    "iso:country":"BE",
    "sg:address":"Stationstraat 14",
    "sg:city":"Haacht",
    "sg:classifiers":[
        {
            "category":"Restaurant",
            "type":"Food & Drink"
        }
    ],
    "sg:phone":"+32 16 60 63 19",
    "sg:postcode":"3150",
    "sg:province":"Vlaams-Brabant",
    "wof:name":"'t Galerijke",
    "wof:placetype":"venue"
},
  "geometry": {"coordinates":[4.6346387863,50.9771080017],"type":"Point"}
}