{
  "type": "Feature",
  "properties": {
    "iso:country":"BE",
    "sg:address":"Avenue De L'europe 100",
    "sg:city":"Charleroi",
    "sg:classifiers":[
        {
            "category":"Cafe",
            "type":"Food & Drink"
        }
    ],
    "sg:phone":"+32 71 33 06 77",
    "sg:postcode":"6000",
    "sg:province":"Hainaut",
    "sg:tags":[
        "caf\u00e9s"
    ],
    "wof:name":"Caf\u00c9 L'imeraude",
    "wof:placetype":"venue"
},
  "geometry": {"coordinates":[4.4363341331,50.40990448],"type":"Point"}
}