{
  "type": "Feature",
  "properties": {
    "addr:full":"Hauptstrasse 72 Raeren Li\u00e8ge 4730",
    "addr:housenumber":"72",
    "addr:postcode":"4730",
    "addr:street":"Hauptstrasse",
    "iso:country":"BE",
    "sg:address":"Hauptstrasse 72",
    "sg:city":"Raeren",
    "sg:orig_category":"Herstelling leer and schoeisel Verlichting and huishoudartikelen",
    "sg:phone":"+32 87 85 09 28",
    "sg:postcode":"4730",
    "sg:province":"Li\u00e8ge",
    "wof:name":"Marcel Jacobs",
    "wof:placetype":"venue"
},
  "geometry": {"coordinates":[6.1128840446,50.6738357544],"type":"Point"}
}