{
  "type": "Feature",
  "properties": {
    "iso:country":"BE",
    "sg:address":"Leistraat 94",
    "sg:city":"Kasterlee (lichtaart)",
    "sg:classifiers":[
        {
            "category":"Professional",
            "subcategory":"Testing Lab",
            "type":"Services"
        }
    ],
    "sg:phone":"+32 14 55 83 93",
    "sg:postcode":"2460",
    "sg:province":"Antwerpen",
    "sg:tags":[
        "chemist"
    ],
    "wof:name":"Vandoninck K",
    "wof:placetype":"venue"
},
  "geometry": {"coordinates":[4.9163389206,51.2246055603],"type":"Point"}
}