{
  "type": "Feature",
  "properties": {
    "addr:full":"Drogenbosstraat 20 Sint-pieters-leeuw Vlaams-Brabant 1600",
    "addr:housenumber":"20",
    "addr:postcode":"1600",
    "addr:street":"Drogenbosstraat",
    "iso:country":"BE",
    "sg:address":"Drogenbosstraat 20",
    "sg:city":"Sint-pieters-leeuw",
    "sg:orig_category":"Pain, p\u00e2tisseries and confiseries",
    "sg:phone":"+32 2 377 95 00",
    "sg:postcode":"1600",
    "sg:province":"Vlaams-Brabant",
    "wof:name":"Jos Vandersteen",
    "wof:placetype":"venue"
},
  "geometry": {"coordinates":[4.2910051346,50.7995643616],"type":"Point"}
}