{
  "type": "Feature",
  "properties": {
    "addr:full":"Handelsstraat 23 Duffel Antwerpen 2570",
    "addr:housenumber":"23",
    "addr:postcode":"2570",
    "addr:street":"Handelsstraat",
    "iso:country":"BE",
    "sg:address":"Handelsstraat 23",
    "sg:city":"Duffel",
    "sg:orig_category":"Banken and kredietinstellingen",
    "sg:phone":"+32 15 31 61 66",
    "sg:postcode":"2570",
    "sg:province":"Antwerpen",
    "wof:name":"Bacob",
    "wof:placetype":"venue"
},
  "geometry": {"coordinates":[4.5095419884,51.095664978],"type":"Point"}
}