{
  "type": "Feature",
  "properties": {
    "iso:country":"BE",
    "sg:address":"Kemzekestraat 31",
    "sg:city":"Stekene (kemzeke)",
    "sg:classifiers":[
        {
            "category":"Home & Garden",
            "subcategory":"Building Materials",
            "type":"Retail Goods"
        }
    ],
    "sg:phone":"+32 3 779 79 72",
    "sg:postcode":"9190",
    "sg:province":"Oost-Vlaanderen",
    "sg:tags":[
        "-",
        "fireplace",
        "open",
        "ornamental"
    ],
    "wof:name":"De Rudder Bvba",
    "wof:placetype":"venue"
},
  "geometry": {"coordinates":[4.082613945,51.2104148865],"type":"Point"}
}