{
  "type": "Feature",
  "properties": {
    "addr:full":"Rue Laneau 119-133 Bruxelles Bruxelles-Capitale 1020",
    "addr:postcode":"119-133;1020",
    "addr:street":"Rue Laneau",
    "iso:country":"BE",
    "sg:address":"Rue Laneau 119-133",
    "sg:city":"Bruxelles",
    "sg:classifiers":[
        {
            "category":"Professional",
            "subcategory":"Business Services",
            "type":"Services"
        }
    ],
    "sg:phone":"+32 2 736 99 55",
    "sg:postcode":"1020",
    "sg:province":"Bruxelles-Capitale",
    "sg:tags":[
        "bookmaker"
    ],
    "wof:name":"P.m.u.",
    "wof:placetype":"venue"
},
  "geometry": {"coordinates":[4.3402261734,50.8750495911],"type":"Point"}
}