{
  "type": "Feature",
  "properties": {
    "addr:full":"Stationsstraat 21-23 Leopoldsburg Limburg 3970",
    "addr:postcode":"21-23;3970",
    "addr:street":"Stationsstraat",
    "iso:country":"BE",
    "sg:address":"Stationsstraat 21-23",
    "sg:city":"Leopoldsburg",
    "sg:classifiers":[
        {
            "category":"Personal",
            "subcategory":"Beauty Salon",
            "type":"Services"
        }
    ],
    "sg:phone":"+32 11 34 17 32",
    "sg:postcode":"3970",
    "sg:province":"Limburg",
    "sg:tags":[
        "lady",
        "-",
        "hairdressing"
    ],
    "wof:name":"Godelieve",
    "wof:placetype":"venue"
},
  "geometry": {"coordinates":[5.2616977692,51.1179275513],"type":"Point"}
}