{
  "type": "Feature",
  "properties": {
    "addr:full":"Rue Joseph Desir 8 Remicourt Li\u00e8ge 4350",
    "addr:housenumber":"8",
    "addr:postcode":"4350",
    "addr:street":"Rue Joseph Desir",
    "iso:country":"BE",
    "sg:address":"Rue Joseph Desir 8",
    "sg:city":"Remicourt",
    "sg:orig_category":"Entretien and r\u00e9parations de voitures",
    "sg:phone":"+32 4 250 49 90",
    "sg:postcode":"4350",
    "sg:province":"Li\u00e8ge",
    "wof:name":"J.p. Car System",
    "wof:placetype":"venue"
},
  "geometry": {"coordinates":[5.3709402084,50.6766891479],"type":"Point"}
}