{
  "type": "Feature",
  "properties": {
    "addr:full":"Kerkstraat 46 Gavere (dikkelvenne) Oost-Vlaanderen 9890",
    "addr:housenumber":"46",
    "addr:postcode":"9890",
    "addr:street":"Kerkstraat",
    "iso:country":"BE",
    "sg:address":"Kerkstraat 46",
    "sg:city":"Gavere (dikkelvenne)",
    "sg:classifiers":[
        {
            "category":"Retail",
            "subcategory":"Auto Repair",
            "type":"Services"
        }
    ],
    "sg:phone":"+32 9 384 40 66",
    "sg:postcode":"9890",
    "sg:province":"Oost-Vlaanderen",
    "sg:tags":[
        "garage"
    ],
    "wof:name":"De Vriese L",
    "wof:placetype":"venue"
},
  "geometry": {"coordinates":[3.6865100861,50.9186706543],"type":"Point"}
}