{
  "type": "Feature",
  "properties": {
    "iso:country":"BE",
    "sg:address":"Oosterwijk 32",
    "sg:city":"Westerlo",
    "sg:orig_category":"Eleveurs de bovins",
    "sg:phone":"+32 14 26 54 58",
    "sg:postcode":"2260",
    "sg:province":"Antwerpen",
    "wof:name":"Jozef Robrechts",
    "wof:placetype":"venue"
},
  "geometry": {"coordinates":[4.8604249954,51.123626709],"type":"Point"}
}