{
  "type": "Feature",
  "properties": {
    "addr:full":"Lantaarnpad 9 Herentals Antwerpen 2200",
    "addr:housenumber":"9",
    "addr:postcode":"2200",
    "addr:street":"Lantaarnpad",
    "iso:country":"BE",
    "sg:address":"Lantaarnpad 9",
    "sg:city":"Herentals",
    "sg:orig_category":"R\u00e9alisation de programmes and logiciels",
    "sg:phone":"+32 14 21 58 29",
    "sg:postcode":"2200",
    "sg:province":"Antwerpen",
    "wof:name":"The Kick",
    "wof:placetype":"venue"
},
  "geometry": {"coordinates":[4.8375577927,51.1763420105],"type":"Point"}
}