{
  "type": "Feature",
  "properties": {
    "iso:country":"BE",
    "sg:address":"Koolskampstraat 37",
    "sg:city":"Hooglede",
    "sg:orig_category":"Enseignement secondaire g\u00e9n\u00e9ral. Enseignement maternel and primaire",
    "sg:phone":"+32 51 23 06 15",
    "sg:postcode":"8830",
    "sg:province":"West-Vlaanderen",
    "wof:name":"Bubao",
    "wof:placetype":"venue"
},
  "geometry": {"coordinates":[3.1247680187,50.9951477051],"type":"Point"}
}