{
  "type": "Feature",
  "properties": {
    "addr:full":"Mechelstraat 44 Grimbergen Vlaams-Brabant 1851",
    "addr:housenumber":"44",
    "addr:postcode":"1851",
    "addr:street":"Mechelstraat",
    "iso:country":"BE",
    "sg:address":"Mechelstraat 44",
    "sg:city":"Grimbergen",
    "sg:orig_category":"Transports routiers de marchandises",
    "sg:phone":"+32 2 253 67 16",
    "sg:postcode":"1851",
    "sg:province":"Vlaams-Brabant",
    "wof:name":"Intramet",
    "wof:placetype":"venue"
},
  "geometry": {"coordinates":[4.3917269707,50.9811248779],"type":"Point"}
}