{
  "type": "Feature",
  "properties": {
    "iso:country":"BE",
    "sg:address":"Onze Lieve Vrouwlaan 102",
    "sg:city":"Evere",
    "sg:orig_category":"Reisbureaus",
    "sg:phone":"+32 2 245 62 29",
    "sg:postcode":"1140",
    "sg:province":"Bruxelles-Capitale",
    "wof:name":"Business Tourism Travel",
    "wof:placetype":"venue"
},
  "geometry": {"coordinates":[4.4004998207,50.8711128235],"type":"Point"}
}