{
  "type": "Feature",
  "properties": {
    "iso:country":"BE",
    "sg:address":"Hulgenrodestraat 111",
    "sg:city":"Borsbeek",
    "sg:classifiers":[
        {
            "category":"Manufacturing",
            "subcategory":"Textiles",
            "type":"Manufacturing & Wholesale Goods"
        }
    ],
    "sg:phone":"+32 3 321 55 70",
    "sg:postcode":"2150",
    "sg:province":"Antwerpen",
    "wof:name":"Huis Anny Blatt",
    "wof:placetype":"venue"
},
  "geometry": {"coordinates":[4.497549057,51.1919288635],"type":"Point"}
}