{
  "type": "Feature",
  "properties": {
    "iso:country":"BE",
    "sg:address":"Ka\u00cfrostraat 22",
    "sg:city":"Oostende",
    "sg:orig_category":"Salles de spectacles",
    "sg:phone":"+32 59 80 99 10",
    "sg:postcode":"8400",
    "sg:province":"West-Vlaanderen",
    "wof:name":"Galerij Litera Este",
    "wof:placetype":"venue"
},
  "geometry": {"coordinates":[2.9173820019,51.2247276306],"type":"Point"}
}