{
  "type": "Feature",
  "properties": {
    "addr:full":"Dendermondesteenweg 75 Wetteren Oost-Vlaanderen 9230",
    "addr:housenumber":"75",
    "addr:postcode":"9230",
    "addr:street":"Dendermondesteenweg",
    "iso:country":"BE",
    "sg:address":"Dendermondesteenweg 75",
    "sg:city":"Wetteren",
    "sg:orig_category":"Boomkwekerijen",
    "sg:phone":"+32 9 366 31 14",
    "sg:postcode":"9230",
    "sg:province":"Oost-Vlaanderen",
    "wof:name":"Pascal De Winter",
    "wof:placetype":"venue"
},
  "geometry": {"coordinates":[3.9126529694,51.0113868713],"type":"Point"}
}