{
  "type": "Feature",
  "properties": {
    "addr:full":"1080 Molenbeek-saint-jean (bruxelles) Bruxelles-Capitale 1080",
    "addr:postcode":"1080;1080",
    "addr:street":"Molenbeek-Saint-Jean",
    "iso:country":"BE",
    "sg:address":"1080",
    "sg:city":"Molenbeek-saint-jean (bruxelles)",
    "sg:orig_category":"Pharmaciens",
    "sg:phone":"+32 900 10 500",
    "sg:postcode":"1080",
    "sg:province":"Bruxelles-Capitale",
    "wof:name":"Pharmacies De Garde",
    "wof:placetype":"venue"
},
  "geometry": {"coordinates":[4.3390049934,50.8550453186],"type":"Point"}
}