{
  "type": "Feature",
  "properties": {
    "iso:country":"BE",
    "sg:address":"Rue Jean Lipsin 8",
    "sg:city":"Charleroi (lodelinsart)",
    "sg:classifiers":[
        {
            "category":"Health Services",
            "subcategory":"Doctor",
            "type":"Services"
        }
    ],
    "sg:phone":"+32 71 30 95 21",
    "sg:postcode":"6042",
    "sg:province":"Hainaut",
    "sg:tags":[
        "psychotherapist",
        "psychoanalyst"
    ],
    "wof:name":"Vansnick M",
    "wof:placetype":"venue"
},
  "geometry": {"coordinates":[4.446586132,50.4357833862],"type":"Point"}
}