{
  "type": "Feature",
  "properties": {
    "addr:full":"Bissegemsestraat 207 Kortrijk West-Vlaanderen 8501",
    "addr:housenumber":"207",
    "addr:postcode":"8501",
    "addr:street":"Bissegemsestraat",
    "iso:country":"BE",
    "sg:address":"Bissegemsestraat 207",
    "sg:city":"Kortrijk",
    "sg:orig_category":"Traitement and rev\u00eatement des m\u00e9taux",
    "sg:phone":"+32 56 35 32 70",
    "sg:postcode":"8501",
    "sg:province":"West-Vlaanderen",
    "wof:name":"Alexy",
    "wof:placetype":"venue"
},
  "geometry": {"coordinates":[3.2304229736,50.8263473511],"type":"Point"}
}