{
  "type": "Feature",
  "properties": {
    "iso:country":"BE",
    "sg:address":"3220",
    "sg:city":"Holsbeek (groot)",
    "sg:orig_category":"Pharmaciens",
    "sg:phone":"+32 900 10 500",
    "sg:postcode":"3220",
    "sg:province":"Vlaams-Brabant",
    "wof:name":"Pharmacies De Garde",
    "wof:placetype":"venue"
},
  "geometry": {"coordinates":[4.7575721741,50.9207267761],"type":"Point"}
}