{
  "type": "Feature",
  "properties": {
    "addr:full":"Rue Notre Dame 51b Philippeville (sart-en-fagne) Namur 5600",
    "addr:housenumber":"51b",
    "addr:postcode":"5600",
    "addr:street":"Rue Notre Dame",
    "iso:country":"BE",
    "sg:address":"Rue Notre Dame 51b",
    "sg:city":"Philippeville (sart-en-fagne)",
    "sg:classifiers":[
        {
            "category":"Building & Trades",
            "subcategory":"Plumbing",
            "type":"Services"
        }
    ],
    "sg:phone":"+32 71 66 78 21",
    "sg:postcode":"5600",
    "sg:province":"Namur",
    "sg:tags":[
        "repair",
        "mainten",
        "-",
        "central",
        "heating"
    ],
    "wof:name":"Delmotte A",
    "wof:placetype":"venue"
},
  "geometry": {"coordinates":[4.6232600212,50.169719696],"type":"Point"}
}