{
  "type": "Feature",
  "properties": {
    "iso:country":"BE",
    "sg:address":"Rue Des Gen\u00eats 42",
    "sg:city":"Bastogne",
    "sg:classifiers":[
        {
            "category":"Banks & Credit Unions",
            "subcategory":"Financial Services",
            "type":"Services"
        }
    ],
    "sg:phone":"+32 61 21 20 86",
    "sg:postcode":"6600",
    "sg:province":"Luxembourg",
    "sg:tags":[
        "loan",
        "mortgage"
    ],
    "wof:name":"Terrienne De La Haute Ardenne (propriet\u00e9)scrl Scrl",
    "wof:placetype":"venue"
},
  "geometry": {"coordinates":[5.6977319717,50.0012512207],"type":"Point"}
}