{
  "type": "Feature",
  "properties": {
    "addr:full":"Rue De Solonne 28 Yvoir Namur 5530",
    "addr:housenumber":"28",
    "addr:postcode":"5530",
    "addr:street":"Rue De Solonne",
    "iso:country":"BE",
    "sg:address":"Rue De Solonne 28",
    "sg:city":"Yvoir",
    "sg:orig_category":"Banken and kredietinstellingen",
    "sg:phone":"+32 82 61 27 81",
    "sg:postcode":"5530",
    "sg:province":"Namur",
    "wof:name":"Centea",
    "wof:placetype":"venue"
},
  "geometry": {"coordinates":[4.9424829483,50.3122596741],"type":"Point"}
}