{
  "type": "Feature",
  "properties": {
    "iso:country":"BE",
    "sg:address":"Morrenweg 30a",
    "sg:city":"Tervuren (vossem)",
    "sg:classifiers":[
        {
            "category":"Retail",
            "subcategory":"Auto Repair",
            "type":"Services"
        }
    ],
    "sg:phone":"+32 2 767 05 44",
    "sg:postcode":"3080",
    "sg:province":"Vlaams-Brabant",
    "sg:tags":[
        "automobile-body"
    ],
    "wof:name":"Bruno",
    "wof:placetype":"venue"
},
  "geometry": {"coordinates":[4.5661640167,50.8395767212],"type":"Point"}
}