{
  "type": "Feature",
  "properties": {
    "iso:country":"BE",
    "sg:address":"Heuvelstraat 3",
    "sg:city":"Boechout",
    "sg:orig_category":"Diverse voedingsmiddelen Gh",
    "sg:phone":"+32 3 455 16 91",
    "sg:postcode":"2530",
    "sg:province":"Antwerpen",
    "wof:name":"Sluys International",
    "wof:placetype":"venue"
},
  "geometry": {"coordinates":[4.4890699387,51.1615447998],"type":"Point"}
}