{
  "type": "Feature",
  "properties": {
    "iso:country":"BE",
    "sg:address":"Rue Du H\u00eatre 2",
    "sg:city":"Celles (escanaffles)",
    "sg:classifiers":[
        {
            "category":"Building & Trades",
            "subcategory":"Cleaning & Sanitation",
            "type":"Services"
        }
    ],
    "sg:phone":"+32 69 45 40 64",
    "sg:postcode":"7760",
    "sg:province":"Hainaut",
    "sg:tags":[
        "fa\u00e7ade",
        "maintenance"
    ],
    "wof:name":"Parent J",
    "wof:placetype":"venue"
},
  "geometry": {"coordinates":[3.4574859142,50.7131690979],"type":"Point"}
}