{
  "type": "Feature",
  "properties": {
    "iso:country":"BE",
    "sg:address":"Grande Rue Au Bois 75",
    "sg:city":"Bruxelles (schaerbeek)",
    "sg:classifiers":[
        {
            "category":"Manufacturing",
            "subcategory":"Musical Instruments",
            "type":"Manufacturing & Wholesale Goods"
        }
    ],
    "sg:phone":"+32 2 245 69 27",
    "sg:postcode":"1030",
    "sg:province":"Bruxelles-Capitale",
    "sg:tags":[
        "repair",
        "mainten",
        "-"
    ],
    "wof:name":"Tamsma J",
    "wof:placetype":"venue"
},
  "geometry": {"coordinates":[4.3861107826,50.8555908203],"type":"Point"}
}