{
  "type": "Feature",
  "properties": {
    "iso:country":"BE",
    "sg:address":"Bredeweg 26",
    "sg:city":"Tongeren",
    "sg:orig_category":"Metaalafval, schrootrecyclage and sloperijen",
    "sg:phone":"+32 12 23 60 34",
    "sg:postcode":"3700",
    "sg:province":"Limburg",
    "wof:name":"Didier Houben",
    "wof:placetype":"venue"
},
  "geometry": {"coordinates":[5.4689497948,50.7792205811],"type":"Point"}
}