{
  "type": "Feature",
  "properties": {
    "addr:full":". Gingelom (groot) Limburg 3890",
    "addr:postcode":"3890",
    "addr:street":"Groot Limburg",
    "iso:country":"BE",
    "sg:address":".",
    "sg:city":"Gingelom (groot)",
    "sg:orig_category":"Apotheken",
    "sg:phone":"+32 900 10 500",
    "sg:postcode":"3890",
    "sg:province":"Limburg",
    "wof:name":"Apothekers Van Wacht",
    "wof:placetype":"venue"
},
  "geometry": {"coordinates":[5.1322197914,50.7487831116],"type":"Point"}
}