{
  "type": "Feature",
  "properties": {
    "addr:full":"Place Albert I 50 Florenville Luxembourg 6820",
    "addr:housenumber":"50",
    "addr:postcode":"6820",
    "addr:street":"Place Albert I",
    "iso:country":"BE",
    "sg:address":"Place Albert I 50",
    "sg:city":"Florenville",
    "sg:classifiers":[
        {
            "category":"Shopping",
            "subcategory":"Beauty & Cosmetics",
            "type":"Retail Goods"
        }
    ],
    "sg:phone":"+32 61 31 49 32",
    "sg:postcode":"6820",
    "sg:province":"Luxembourg",
    "sg:tags":[
        "-",
        "perfumery"
    ],
    "wof:name":"C\u00e9cile Parfumerie",
    "wof:placetype":"venue"
},
  "geometry": {"coordinates":[5.310500145,49.6980400085],"type":"Point"}
}