{
  "type": "Feature",
  "properties": {
    "iso:country":"BE",
    "sg:address":"Weertersteenweg 327",
    "sg:city":"Kinrooi",
    "sg:classifiers":[
        {
            "category":"Health Services",
            "subcategory":"Health Practitioner",
            "type":"Services"
        }
    ],
    "sg:phone":"+32 89 70 13 77",
    "sg:postcode":"3640",
    "sg:province":"Limburg",
    "sg:tags":[
        "physiotherapist"
    ],
    "wof:name":"Jeursen C",
    "wof:placetype":"venue"
},
  "geometry": {"coordinates":[5.7421097755,51.1599807739],"type":"Point"}
}