{
  "type": "Feature",
  "properties": {
    "iso:country":"BE",
    "sg:address":"Chauss\u00c9e De Asse 35",
    "sg:city":"Enghien",
    "sg:orig_category":"Bouwwerktuigen Gh Verhuur bouwmachines",
    "sg:phone":"+32 2 395 40 29",
    "sg:postcode":"7850",
    "sg:province":"Hainaut",
    "wof:name":"Robeys-huet",
    "wof:placetype":"venue"
},
  "geometry": {"coordinates":[4.0535969734,50.6991348267],"type":"Point"}
}