{
  "type": "Feature",
  "properties": {
    "addr:full":"Oud Kloosterlaan 0 Sint-genesius-rode/bruxelles Bruxelles-Capitale 1020",
    "addr:housenumber":"0",
    "addr:postcode":"1020",
    "addr:street":"Oud Kloosterlaan;/",
    "iso:country":"BE",
    "sg:address":"Oud Kloosterlaan 0",
    "sg:city":"Sint-genesius-rode/bruxelles",
    "sg:classifiers":[
        {
            "category":"Restaurant",
            "type":"Food & Drink"
        }
    ],
    "sg:phone":"+32 2 476 09 29",
    "sg:postcode":"1020",
    "sg:province":"Bruxelles-Capitale",
    "wof:name":"Summer House",
    "wof:placetype":"venue"
},
  "geometry": {"coordinates":[4.3436851501,50.8883552551],"type":"Point"}
}