{
  "type": "Feature",
  "properties": {
    "iso:country":"BE",
    "sg:address":"Ondankstraat 1ba",
    "sg:city":"Wingene",
    "sg:orig_category":"Eleveurs and marchands de porcs",
    "sg:phone":"+32 51 65 52 29",
    "sg:postcode":"8750",
    "sg:province":"West-Vlaanderen",
    "wof:name":"Walter Spriet",
    "wof:placetype":"venue"
},
  "geometry": {"coordinates":[3.24563694,51.0647163391],"type":"Point"}
}