{
  "type": "Feature",
  "properties": {
    "addr:full":"Langestraat 63 Kampenhout Vlaams-Brabant 1910",
    "addr:housenumber":"63",
    "addr:postcode":"1910",
    "addr:street":"Langestraat",
    "iso:country":"BE",
    "sg:address":"Langestraat 63",
    "sg:city":"Kampenhout",
    "sg:orig_category":"P\u00e9pini\u00e9ristes",
    "sg:phone":"+32 16 65 10 73",
    "sg:postcode":"1910",
    "sg:province":"Vlaams-Brabant",
    "wof:name":"Joseph Bogaerts",
    "wof:placetype":"venue"
},
  "geometry": {"coordinates":[4.558535099,50.9621353149],"type":"Point"}
}