{
  "type": "Feature",
  "properties": {
    "iso:country":"BE",
    "sg:address":"Markt 31",
    "sg:city":"Eeklo",
    "sg:classifiers":[
        {
            "category":"Shopping",
            "subcategory":"Clothing, Apparel, & Fashions",
            "type":"Retail Goods"
        }
    ],
    "sg:phone":"+32 9 377 17 55",
    "sg:postcode":"9900",
    "sg:province":"Oost-Vlaanderen",
    "sg:tags":[
        "lady",
        "clothing",
        "-"
    ],
    "wof:name":"Buyck R (modehuis)",
    "wof:placetype":"venue"
},
  "geometry": {"coordinates":[3.5662539005,51.1840171814],"type":"Point"}
}