{
  "type": "Feature",
  "properties": {
    "iso:country":"BE",
    "sg:address":"Itegemse Steenweg 126",
    "sg:city":"Herenthout",
    "sg:orig_category":"Bouwmaterialen Gh",
    "sg:phone":"+32 14 51 25 61",
    "sg:postcode":"2270",
    "sg:province":"Antwerpen",
    "wof:name":"Serneels A. & Co",
    "wof:placetype":"venue"
},
  "geometry": {"coordinates":[4.7608780861,51.1294746399],"type":"Point"}
}