{
  "type": "Feature",
  "properties": {
    "iso:country":"BE",
    "sg:address":"Gentseweg 566",
    "sg:city":"Waregem",
    "sg:orig_category":"Computers and computerapparatuur Diverse informatica-activiteiten Informaticaconsulenten Kantoormate",
    "sg:phone":"+32 56 61 27 67",
    "sg:postcode":"8793",
    "sg:province":"West-Vlaanderen",
    "wof:name":"C.b.m. Moerman Nv",
    "wof:placetype":"venue"
},
  "geometry": {"coordinates":[3.4059069157,50.9014053345],"type":"Point"}
}