{
  "type": "Feature",
  "properties": {
    "addr:full":"Vaddenhoek 116ba Oudenaarde Oost-Vlaanderen 9700",
    "addr:postcode":"9700",
    "addr:street":"Oost-Vlaanderen",
    "iso:country":"BE",
    "sg:address":"Vaddenhoek 116ba",
    "sg:city":"Oudenaarde",
    "sg:orig_category":"Rev\u00eatements de sols and murs",
    "sg:phone":"+32 9 384 20 17",
    "sg:postcode":"9700",
    "sg:province":"Oost-Vlaanderen",
    "wof:name":"Vandemaele Ruth",
    "wof:placetype":"venue"
},
  "geometry": {"coordinates":[3.6075809002,50.8895301819],"type":"Point"}
}