{
  "type": "Feature",
  "properties": {
    "addr:full":"Rue Neuve 23-1 Huy Li\u00e8ge 4500",
    "addr:housenumber":"23-1",
    "addr:postcode":"4500",
    "addr:street":"Rue Neuve",
    "iso:country":"BE",
    "sg:address":"Rue Neuve 23-1",
    "sg:city":"Huy",
    "sg:classifiers":[
        {
            "category":"Professional",
            "subcategory":"Accounting & Tax Preparation",
            "type":"Services"
        }
    ],
    "sg:phone":"+32 85 21 19 00",
    "sg:postcode":"4500",
    "sg:province":"Li\u00e8ge",
    "sg:tags":[
        "bookkeeper"
    ],
    "wof:name":"Bertrand J",
    "wof:placetype":"venue"
},
  "geometry": {"coordinates":[5.2355151176,50.5207290649],"type":"Point"}
}