{
  "type": "Feature",
  "properties": {
    "iso:country":"BE",
    "sg:address":"Michiel Jansplein 28-3b",
    "sg:city":"Lommel",
    "sg:classifiers":[
        {
            "category":"Professional",
            "subcategory":"Computer Services",
            "type":"Services"
        }
    ],
    "sg:phone":"+32 11 55 44 94",
    "sg:postcode":"3920",
    "sg:province":"Limburg",
    "sg:tags":[
        "-",
        "processing",
        "data"
    ],
    "wof:name":"B & C Bvba",
    "wof:placetype":"venue"
},
  "geometry": {"coordinates":[5.3150777817,51.2290153503],"type":"Point"}
}