{
  "type": "Feature",
  "properties": {
    "iso:country":"BE",
    "sg:address":"Kloosterstraat 181",
    "sg:city":"Antwerpen",
    "sg:orig_category":"Rev\u00eatements de sols and murs. Location de machines-outils and de mat\u00e9riel de bricolage",
    "sg:phone":"+32 3 237 27 46",
    "sg:postcode":"2000",
    "sg:province":"Antwerpen",
    "wof:name":"Alpa-arcum",
    "wof:placetype":"venue"
},
  "geometry": {"coordinates":[4.3941240311,51.2127037048],"type":"Point"}
}