{
  "type": "Feature",
  "properties": {
    "iso:country":"BE",
    "sg:address":"Avenue Marcel Thiry 208",
    "sg:city":"Brussels",
    "sg:classifiers":[
        {
            "category":"Banks & Credit Unions",
            "subcategory":"Bank",
            "type":"Services"
        }
    ],
    "sg:postcode":"1200",
    "sg:province":"Bruxelles-Capitale",
    "wof:name":"Van De Velde",
    "wof:placetype":"venue"
},
  "geometry": {"coordinates":[3.9351799488,51.0092086792],"type":"Point"}
}