{
  "type": "Feature",
  "properties": {
    "addr:full":"Rue Grande 32 Farciennes Hainaut 6240",
    "addr:housenumber":"32",
    "addr:postcode":"6240",
    "addr:street":"Rue Grande",
    "iso:country":"BE",
    "sg:address":"Rue Grande 32",
    "sg:city":"Farciennes",
    "sg:classifiers":[
        {
            "category":"Shopping",
            "subcategory":"Clothing, Apparel, & Fashions",
            "type":"Retail Goods"
        }
    ],
    "sg:phone":"+32 71 40 26 39",
    "sg:postcode":"6240",
    "sg:province":"Hainaut",
    "sg:tags":[
        "underwear",
        "lingerie",
        "-"
    ],
    "wof:name":"Boutique J",
    "wof:placetype":"venue"
},
  "geometry": {"coordinates":[4.5516600609,50.426700592],"type":"Point"}
}