{
  "type": "Feature",
  "properties": {
    "addr:full":"Chauss\u00c9e De Charleroi 7 Anderlues Hainaut 6150",
    "addr:housenumber":"7",
    "addr:postcode":"6150",
    "addr:street":"Chausse\u0301E De Charleroi",
    "iso:country":"BE",
    "sg:address":"Chauss\u00c9e De Charleroi 7",
    "sg:city":"Anderlues",
    "sg:orig_category":"Pain, p\u00e2tisseries and confiseries",
    "sg:phone":"+32 71 52 85 76",
    "sg:postcode":"6150",
    "sg:province":"Hainaut",
    "wof:name":"P\u00c2tisserie Schamp & Fils",
    "wof:placetype":"venue"
},
  "geometry": {"coordinates":[4.2729291916,50.4059257507],"type":"Point"}
}