{
  "type": "Feature",
  "properties": {
    "addr:full":"Monaville 524 Bertogne Luxembourg 6688",
    "addr:housenumber":"524",
    "addr:postcode":"6688",
    "addr:street":"Monaville",
    "iso:country":"BE",
    "sg:address":"Monaville 524",
    "sg:city":"Bertogne",
    "sg:orig_category":"Rundveehouders",
    "sg:phone":"+32 61 21 21 37",
    "sg:postcode":"6688",
    "sg:province":"Luxembourg",
    "wof:name":"Francis Choffray",
    "wof:placetype":"venue"
},
  "geometry": {"coordinates":[5.689948082,50.0525741577],"type":"Point"}
}