{
  "type": "Feature",
  "properties": {
    "addr:full":"Leuvensesteenweg 319 Aarschot Vlaams-Brabant 3200",
    "addr:housenumber":"319",
    "addr:postcode":"3200",
    "addr:street":"Leuvensesteenweg",
    "iso:country":"BE",
    "sg:address":"Leuvensesteenweg 319",
    "sg:city":"Aarschot",
    "sg:classifiers":[
        {
            "category":"Building & Trades",
            "subcategory":"Construction",
            "type":"Services"
        }
    ],
    "sg:phone":"+32 16 53 97 98",
    "sg:postcode":"3200",
    "sg:province":"Vlaams-Brabant",
    "sg:tags":[
        "stucco",
        "contractor"
    ],
    "wof:name":"Bezettingswerken Michel",
    "wof:placetype":"venue"
},
  "geometry": {"coordinates":[4.8058838844,50.9741363525],"type":"Point"}
}