{
  "type": "Feature",
  "properties": {
    "iso:country":"BE",
    "sg:address":"Rue Nouvelle 7",
    "sg:city":"Virton",
    "sg:orig_category":"Travail and traitement du bois",
    "sg:phone":"+32 63 57 88 88",
    "sg:postcode":"6760",
    "sg:province":"Luxembourg",
    "wof:name":"Scierie Cattoor Andr\u00c9",
    "wof:placetype":"venue"
},
  "geometry": {"coordinates":[5.585793972,49.5799789429],"type":"Point"}
}