{
  "type": "Feature",
  "properties": {
    "iso:country":"BE",
    "sg:address":"Hoekstraat 16",
    "sg:city":"Neerpelt",
    "sg:classifiers":[
        {
            "category":"Professional",
            "subcategory":"Accounting & Tax Preparation",
            "type":"Services"
        }
    ],
    "sg:phone":"+32 11 64 49 38",
    "sg:postcode":"3910",
    "sg:province":"Limburg",
    "sg:tags":[
        "accountant"
    ],
    "wof:name":"L. Notelaers",
    "wof:placetype":"venue"
},
  "geometry": {"coordinates":[5.4291949272,51.2287864685],"type":"Point"}
}