{
  "type": "Feature",
  "properties": {
    "iso:country":"BE",
    "sg:address":"Rue De Virton 9",
    "sg:city":"Etalle",
    "sg:orig_category":"Maisons de vacances",
    "sg:phone":"+32 63 45 68 22",
    "sg:postcode":"6740",
    "sg:province":"Luxembourg",
    "wof:name":"Lemaire Pierre",
    "wof:placetype":"venue"
},
  "geometry": {"coordinates":[5.6000561714,49.6714134216],"type":"Point"}
}