{
  "type": "Feature",
  "properties": {
    "iso:country":"BE",
    "sg:address":"Rue Croix Jacquet 196",
    "sg:city":"Florennes (saint-aubin)",
    "sg:classifiers":[
        {
            "category":"Building & Trades",
            "subcategory":"Landscaping Services",
            "type":"Services"
        }
    ],
    "sg:phone":"+32 71 68 64 42",
    "sg:postcode":"5620",
    "sg:province":"Namur",
    "sg:tags":[
        "forestry"
    ],
    "wof:name":"Foresti\u00e8re Henuzet Sprl",
    "wof:placetype":"venue"
},
  "geometry": {"coordinates":[4.581264019,50.2492675781],"type":"Point"}
}