{
  "type": "Feature",
  "properties": {
    "addr:full":"Lage Kaart 253 Brasschaat Antwerpen 2930",
    "addr:housenumber":"253",
    "addr:postcode":"2930",
    "addr:street":"Lage Kaart",
    "iso:country":"BE",
    "sg:address":"Lage Kaart 253",
    "sg:city":"Brasschaat",
    "sg:orig_category":"Motorfietsen",
    "sg:phone":"+32 3 651 65 76",
    "sg:postcode":"2930",
    "sg:province":"Antwerpen",
    "wof:name":"Minnebo R.",
    "wof:placetype":"venue"
},
  "geometry": {"coordinates":[4.4821491241,51.3010826111],"type":"Point"}
}