{
  "type": "Feature",
  "properties": {
    "addr:full":"Nieuwstraat 1 Damme West-Vlaanderen 8340",
    "addr:housenumber":"1",
    "addr:postcode":"8340",
    "addr:street":"Nieuwstraat",
    "iso:country":"BE",
    "sg:address":"Nieuwstraat 1",
    "sg:city":"Damme",
    "sg:orig_category":"Rundveehouders",
    "sg:phone":"+32 50 50 03 73",
    "sg:postcode":"8340",
    "sg:province":"West-Vlaanderen",
    "wof:name":"Aime Timmerman",
    "wof:placetype":"venue"
},
  "geometry": {"coordinates":[3.3436510563,51.2313728333],"type":"Point"}
}