{
  "type": "Feature",
  "properties": {
    "iso:country":"BE",
    "sg:address":"Meenseweg 120",
    "sg:city":"Ieper",
    "sg:orig_category":"Cr\u00e9meries",
    "sg:phone":"+32 57 20 70 74",
    "sg:postcode":"8900",
    "sg:province":"West-Vlaanderen",
    "wof:name":"Forrez",
    "wof:placetype":"venue"
},
  "geometry": {"coordinates":[2.9030930996,50.8495903015],"type":"Point"}
}