{
  "type": "Feature",
  "properties": {
    "iso:country":"BE",
    "sg:address":"Zilverboslaan 90",
    "sg:city":"Kapellen",
    "sg:orig_category":"Charpentes and couvertures",
    "sg:phone":"+32 3 665 29 34",
    "sg:postcode":"2950",
    "sg:province":"Antwerpen",
    "wof:name":"Vingerhoed En Co",
    "wof:placetype":"venue"
},
  "geometry": {"coordinates":[4.4314627647,51.3066711426],"type":"Point"}
}