{
  "type": "Feature",
  "properties": {
    "iso:country":"BE",
    "sg:address":"Petterstraat 1",
    "sg:city":"Affligem (teralfene)",
    "sg:classifiers":[
        {
            "category":"Personal",
            "subcategory":"Beauty Salon",
            "type":"Services"
        }
    ],
    "sg:phone":"+32 53 68 11 12",
    "sg:postcode":"1790",
    "sg:province":"Vlaams-Brabant",
    "wof:name":"Iris",
    "wof:placetype":"venue"
},
  "geometry": {"coordinates":[4.1075491905,50.8936958313],"type":"Point"}
}