{
  "type": "Feature",
  "properties": {
    "addr:full":"Isschotweg 116 Heist-op-den-berg Antwerpen 2222",
    "addr:housenumber":"116",
    "addr:postcode":"2222",
    "addr:street":"Isschotweg",
    "iso:country":"BE",
    "sg:address":"Isschotweg 116",
    "sg:city":"Heist-op-den-berg",
    "sg:orig_category":"Huisdieren and benodigdheden IJzerwaren, bouw- and verfmaterialen",
    "sg:phone":"+32 15 24 42 92",
    "sg:postcode":"2222",
    "sg:province":"Antwerpen",
    "wof:name":"Bellekens",
    "wof:placetype":"venue"
},
  "geometry": {"coordinates":[4.7292399406,51.1032218933],"type":"Point"}
}