{
  "type": "Feature",
  "properties": {
    "iso:country":"BE",
    "sg:address":"Nijverheidsstraat 54a",
    "sg:city":"Wommelgem",
    "sg:classifiers":[
        {
            "category":"Shopping",
            "subcategory":"Pawn Shop",
            "type":"Retail Goods"
        }
    ],
    "sg:phone":"+32 3 355 24 24",
    "sg:postcode":"2160",
    "sg:province":"Antwerpen",
    "sg:tags":[
        "tax",
        "free"
    ],
    "wof:name":"Chacalli-de Decker Duty Free Benelux",
    "wof:placetype":"venue"
},
  "geometry": {"coordinates":[4.5078129768,51.2111549377],"type":"Point"}
}