{
  "type": "Feature",
  "properties": {
    "addr:full":"Rittwegerln 20 Machelen Vlaams-Brabant 1830",
    "addr:housenumber":"20",
    "addr:postcode":"1830",
    "addr:street":"Rittwegerln",
    "iso:country":"BE",
    "sg:address":"Rittwegerln 20",
    "sg:city":"Machelen",
    "sg:classifiers":[
        {
            "category":"Professional",
            "type":"Services"
        }
    ],
    "sg:phone":"+32 2 253 02 27",
    "sg:postcode":"1830",
    "sg:province":"Vlaams-Brabant",
    "sg:tags":[
        "transport",
        "road"
    ],
    "wof:name":"Transport Buda Bvba",
    "wof:placetype":"venue"
},
  "geometry": {"coordinates":[4.4242281914,50.9114227295],"type":"Point"}
}