{
  "type": "Feature",
  "properties": {
    "addr:full":"Mechelsesteenweg 488 Herent Vlaams-Brabant 3020",
    "addr:housenumber":"488",
    "addr:postcode":"3020",
    "addr:street":"Mechelsesteenweg",
    "iso:country":"BE",
    "sg:address":"Mechelsesteenweg 488",
    "sg:city":"Herent",
    "sg:orig_category":"Artsen and specialisten",
    "sg:phone":"+32 16 22 00 53",
    "sg:postcode":"3020",
    "sg:province":"Vlaams-Brabant",
    "wof:name":"Lieve Deturck",
    "wof:placetype":"venue"
},
  "geometry": {"coordinates":[4.6684880257,50.9070587158],"type":"Point"}
}