{
  "type": "Feature",
  "properties": {
    "addr:full":"Rue Emile Cuvelier 1 Namur Namur 5000",
    "addr:housenumber":"1",
    "addr:postcode":"5000",
    "addr:street":"Rue Emile Cuvelier",
    "iso:country":"BE",
    "sg:address":"Rue Emile Cuvelier 1",
    "sg:city":"Namur",
    "sg:classifiers":[
        {
            "category":"Bars & Pubs",
            "type":"Food & Drink"
        }
    ],
    "sg:phone":"+32 81 23 05 65",
    "sg:postcode":"5000",
    "sg:province":"Namur",
    "wof:name":"Metropole",
    "wof:placetype":"venue"
},
  "geometry": {"coordinates":[4.8677458763,50.4638595581],"type":"Point"}
}