{
  "type": "Feature",
  "properties": {
    "addr:full":"Rue Jean-baptiste Petit 7 Brunehaut (bl\u00e9haries) Hainaut 7620",
    "addr:housenumber":"7",
    "addr:postcode":"7620",
    "addr:street":"Rue Jean-Baptiste Petit;Ble\u0301Haries Hainaut",
    "iso:country":"BE",
    "sg:address":"Rue Jean-baptiste Petit 7",
    "sg:city":"Brunehaut (bl\u00e9haries)",
    "sg:classifiers":[
        {
            "category":"Farming",
            "subcategory":"Livestock Farm",
            "type":"Manufacturing & Wholesale Goods"
        }
    ],
    "sg:phone":"+32 69 23 69 58",
    "sg:postcode":"7620",
    "sg:province":"Hainaut",
    "sg:tags":[
        "breeding"
    ],
    "wof:name":"Moulin Mobile",
    "wof:placetype":"venue"
},
  "geometry": {"coordinates":[3.4124701023,50.5111999512],"type":"Point"}
}