{
  "type": "Feature",
  "properties": {
    "iso:country":"BE",
    "sg:address":"Kotterstraat 10",
    "sg:city":"Antwerpen",
    "sg:orig_category":"Battery Service",
    "sg:phone":"+32 3 233 55 89",
    "sg:postcode":"2030",
    "sg:province":"Antwerpen",
    "wof:name":"Navex Elektro Nv",
    "wof:placetype":"venue"
},
  "geometry": {"coordinates":[4.4181351662,51.2446365356],"type":"Point"}
}