{
  "type": "Feature",
  "properties": {
    "iso:country":"BE",
    "sg:address":"Aalterstraat 38",
    "sg:city":"Ruiselede",
    "sg:orig_category":"Herstellingen and onderhoud van auto's",
    "sg:phone":"+32 51 68 72 12",
    "sg:postcode":"8755",
    "sg:province":"West-Vlaanderen",
    "wof:name":"Gerard Van Cauwenberghe",
    "wof:placetype":"venue"
},
  "geometry": {"coordinates":[3.4018490314,51.0436058044],"type":"Point"}
}