{
  "type": "Feature",
  "properties": {
    "addr:full":"Av De La Couronne 242 Bruxelles Bruxelles-Capitale 1050",
    "addr:housenumber":"242",
    "addr:postcode":"1050",
    "addr:street":"Av De La Couronne",
    "iso:country":"BE",
    "sg:address":"Av De La Couronne 242",
    "sg:city":"Bruxelles",
    "sg:classifiers":[
        {
            "category":"Manufacturing",
            "subcategory":"Paper Products",
            "type":"Manufacturing & Wholesale Goods"
        }
    ],
    "sg:phone":"+32 2 648 22 56",
    "sg:postcode":"1050",
    "sg:province":"Bruxelles-Capitale",
    "sg:tags":[
        "finished",
        "cardboard",
        "-"
    ],
    "wof:name":"Rose Et Associes Sa",
    "wof:placetype":"venue"
},
  "geometry": {"coordinates":[4.3831629753,50.8266372681],"type":"Point"}
}