{
  "type": "Feature",
  "properties": {
    "iso:country":"BE",
    "sg:address":"Place De Montroeul 14",
    "sg:city":"Hensies",
    "sg:classifiers":[
        {
            "category":"Cafe",
            "type":"Food & Drink"
        }
    ],
    "sg:phone":"+32 65 45 70 60",
    "sg:postcode":"7350",
    "sg:province":"Hainaut",
    "sg:tags":[
        "caf\u00e9s"
    ],
    "wof:name":"Marguerite Letellier",
    "wof:placetype":"venue"
},
  "geometry": {"coordinates":[3.7026820183,50.43409729],"type":"Point"}
}