{
  "type": "Feature",
  "properties": {
    "addr:full":"Place Ducale 1 Bouillon Luxembourg 6830",
    "addr:housenumber":"1",
    "addr:postcode":"6830",
    "addr:street":"Place Ducale",
    "iso:country":"BE",
    "sg:address":"Place Ducale 1",
    "sg:city":"Bouillon",
    "sg:orig_category":"S\u00e9lection de personnel and placement",
    "sg:phone":"+32 61 46 74 11",
    "sg:postcode":"6830",
    "sg:province":"Luxembourg",
    "wof:name":"Ale",
    "wof:placetype":"venue"
},
  "geometry": {"coordinates":[5.0675787926,49.7952613831],"type":"Point"}
}