{
  "type": "Feature",
  "properties": {
    "addr:full":"Grand Place 16 Paliseul Luxembourg 6850",
    "addr:housenumber":"16",
    "addr:postcode":"6850",
    "addr:street":"Grand Place",
    "iso:country":"BE",
    "sg:address":"Grand Place 16",
    "sg:city":"Paliseul",
    "sg:classifiers":[
        {
            "category":"Professional",
            "subcategory":"Testing Lab",
            "type":"Services"
        }
    ],
    "sg:phone":"+32 61 53 31 25",
    "sg:postcode":"6850",
    "sg:province":"Luxembourg",
    "sg:tags":[
        "chemist"
    ],
    "wof:name":"Vanhemmens N",
    "wof:placetype":"venue"
},
  "geometry": {"coordinates":[5.1350898743,49.9034004211],"type":"Point"}
}