{
  "type": "Feature",
  "properties": {
    "addr:full":"Chauss\u00c9e De Waterloo 1021b Ukkel/uccle Bruxelles-Capitale 1180",
    "addr:housenumber":"1021b",
    "addr:postcode":"1180",
    "addr:street":"Chausse\u0301E De Waterloo;/",
    "iso:country":"BE",
    "sg:address":"Chauss\u00c9e De Waterloo 1021b",
    "sg:city":"Ukkel/uccle",
    "sg:orig_category":"Dameskledingzaken",
    "sg:phone":"+32 2 375 45 06",
    "sg:postcode":"1180",
    "sg:province":"Bruxelles-Capitale",
    "wof:name":"Classic Design",
    "wof:placetype":"venue"
},
  "geometry": {"coordinates":[4.3718509674,50.805480957],"type":"Point"}
}