{
  "type": "Feature",
  "properties": {
    "addr:full":"Herbefays 15a Yvoir (durnal) Namur 5530",
    "addr:housenumber":"15a",
    "addr:postcode":"5530",
    "addr:street":"Herbefays",
    "iso:country":"BE",
    "sg:address":"Herbefays 15a",
    "sg:city":"Yvoir (durnal)",
    "sg:classifiers":[
        {
            "category":"Education",
            "subcategory":"Dance Studio",
            "type":"Public Place"
        }
    ],
    "sg:phone":"+32 83 69 00 12",
    "sg:postcode":"5530",
    "sg:province":"Namur",
    "sg:tags":[
        "school",
        "dancing"
    ],
    "wof:name":"Federation Belge De Danse Sportive",
    "wof:placetype":"venue"
},
  "geometry": {"coordinates":[4.9894008636,50.3444366455],"type":"Point"}
}