{
  "type": "Feature",
  "properties": {
    "addr:full":"Stuivenbergstraat 17 Brussel/bruxelles Bruxelles-Capitale 1020",
    "addr:housenumber":"17",
    "addr:postcode":"1020",
    "addr:street":"Stuivenbergstraat;/",
    "iso:country":"BE",
    "sg:address":"Stuivenbergstraat 17",
    "sg:city":"Brussel/bruxelles",
    "sg:orig_category":"Artsen and specialisten",
    "sg:phone":"+32 2 479 23 64",
    "sg:postcode":"1020",
    "sg:province":"Bruxelles-Capitale",
    "wof:name":"Jean Pierlot",
    "wof:placetype":"venue"
},
  "geometry": {"coordinates":[4.338160038,50.8881492615],"type":"Point"}
}