{
  "type": "Feature",
  "properties": {
    "addr:full":"Graethempoort 3 Borgloon (groot) Limburg 3840",
    "addr:housenumber":"3",
    "addr:postcode":"3840",
    "addr:street":"Graethempoort;Groot Limburg",
    "iso:country":"BE",
    "sg:address":"Graethempoort 3",
    "sg:city":"Borgloon (groot)",
    "sg:classifiers":[
        {
            "category":"Manufacturing",
            "subcategory":"Textiles",
            "type":"Manufacturing & Wholesale Goods"
        }
    ],
    "sg:phone":"+32 12 74 42 59",
    "sg:postcode":"3840",
    "sg:province":"Limburg",
    "wof:name":"Huis Andrea",
    "wof:placetype":"venue"
},
  "geometry": {"coordinates":[5.3395009041,50.803314209],"type":"Point"}
}