{
  "type": "Feature",
  "properties": {
    "addr:full":"Burgemeester Marresbaan 3a Riemst (vroenhoven) Limburg 3770",
    "addr:housenumber":"3a",
    "addr:postcode":"3770",
    "addr:street":"Burgemeester Marresbaan",
    "iso:country":"BE",
    "sg:address":"Burgemeester Marresbaan 3a",
    "sg:city":"Riemst (vroenhoven)",
    "sg:classifiers":[
        {
            "category":"Personal",
            "subcategory":"Beauty Salon",
            "type":"Services"
        }
    ],
    "sg:phone":"+32 12 45 32 12",
    "sg:postcode":"3770",
    "sg:province":"Limburg",
    "wof:name":"Schoonheidssalon Christel Gielen-janssen",
    "wof:placetype":"venue"
},
  "geometry": {"coordinates":[5.6256151199,50.8250083923],"type":"Point"}
}