{
  "type": "Feature",
  "properties": {
    "addr:full":"Vier Uitersten 1 Dendermonde Oost-Vlaanderen 9200",
    "addr:housenumber":"1",
    "addr:postcode":"9200",
    "addr:street":"Vier Uitersten;Oost-Vlaanderen",
    "iso:country":"BE",
    "sg:address":"Vier Uitersten 1",
    "sg:city":"Dendermonde",
    "sg:orig_category":"Industri\u00eble and commerci\u00eble bouw Woningbouw",
    "sg:phone":"+32 52 42 23 51",
    "sg:postcode":"9200",
    "sg:province":"Oost-Vlaanderen",
    "wof:name":"Cobbaut",
    "wof:placetype":"venue"
},
  "geometry": {"coordinates":[4.011223793,50.9928855896],"type":"Point"}
}