{
  "type": "Feature",
  "properties": {
    "addr:full":"Molenstraat 1 Lo-reninge West-Vlaanderen 8647",
    "addr:housenumber":"1",
    "addr:postcode":"8647",
    "addr:street":"Molenstraat",
    "iso:country":"BE",
    "sg:address":"Molenstraat 1",
    "sg:city":"Lo-reninge",
    "sg:orig_category":"Eleveurs de bovins",
    "sg:phone":"+32 57 40 05 21",
    "sg:postcode":"8647",
    "sg:province":"West-Vlaanderen",
    "wof:name":"Dani\u00cbl Decaestecker",
    "wof:placetype":"venue"
},
  "geometry": {"coordinates":[2.7931790352,50.935749054],"type":"Point"}
}