{
  "type": "Feature",
  "properties": {
    "addr:full":"Rue De La Halle 2 Lessines Hainaut 7860",
    "addr:housenumber":"2",
    "addr:postcode":"7860",
    "addr:street":"Rue De La Halle;Hainaut",
    "iso:country":"BE",
    "sg:address":"Rue De La Halle 2",
    "sg:city":"Lessines",
    "sg:orig_category":"Banques and organismes de cr\u00e9dit",
    "sg:phone":"+32 68 33 24 50",
    "sg:postcode":"7860",
    "sg:province":"Hainaut",
    "wof:name":"Ippa",
    "wof:placetype":"venue"
},
  "geometry": {"coordinates":[3.8293681145,50.7116279602],"type":"Point"}
}