{
  "type": "Feature",
  "properties": {
    "addr:full":"Rue De Limoges 44 Esneux Li\u00e8ge 4130",
    "addr:housenumber":"44",
    "addr:postcode":"4130",
    "addr:street":"Rue De Limoges",
    "iso:country":"BE",
    "sg:address":"Rue De Limoges 44",
    "sg:city":"Esneux",
    "sg:orig_category":"Paramedische behandelingen",
    "sg:phone":"+32 4 388 11 56",
    "sg:postcode":"4130",
    "sg:province":"Li\u00e8ge",
    "wof:name":"D. Di Duca",
    "wof:placetype":"venue"
},
  "geometry": {"coordinates":[5.5785570145,50.5699958801],"type":"Point"}
}