{
  "type": "Feature",
  "properties": {
    "addr:full":"Leffingestraat 91 Oostende West-Vlaanderen 8400",
    "addr:housenumber":"91",
    "addr:postcode":"8400",
    "addr:street":"Leffingestraat",
    "iso:country":"BE",
    "sg:address":"Leffingestraat 91",
    "sg:city":"Oostende",
    "sg:classifiers":[
        {
            "category":"Health Services",
            "subcategory":"Dentist",
            "type":"Services"
        }
    ],
    "sg:phone":"+32 59 50 51 93",
    "sg:postcode":"8400",
    "sg:province":"West-Vlaanderen",
    "wof:name":"Kyndt Heidi",
    "wof:placetype":"venue"
},
  "geometry": {"coordinates":[2.9097459316,51.2190628052],"type":"Point"}
}