{
  "type": "Feature",
  "properties": {
    "iso:country":"BE",
    "sg:address":"Molenmeers 52",
    "sg:city":"Brugge",
    "sg:orig_category":"Kapsalons",
    "sg:phone":"+32 50 33 01 15",
    "sg:postcode":"8000",
    "sg:province":"West-Vlaanderen",
    "wof:name":"Coiffure Ingrid",
    "wof:placetype":"venue"
},
  "geometry": {"coordinates":[3.2333700657,51.2113418579],"type":"Point"}
}