{
  "type": "Feature",
  "properties": {
    "iso:country":"BE",
    "sg:address":"Rue Des Fr\u00e8res Taymans 77",
    "sg:city":"Tubize",
    "sg:classifiers":[
        {
            "category":"Bars & Pubs",
            "type":"Food & Drink"
        }
    ],
    "sg:phone":"+32 2 355 01 05",
    "sg:postcode":"1480",
    "sg:province":"Brabant Wallon",
    "wof:name":"Repos De La Montagne (le)",
    "wof:placetype":"venue"
},
  "geometry": {"coordinates":[4.2064228058,50.6878929138],"type":"Point"}
}