{
  "type": "Feature",
  "properties": {
    "iso:country":"BE",
    "sg:address":"Rue D'alvau 4",
    "sg:city":"Mont-saint-guibert",
    "sg:orig_category":"Woningbouw",
    "sg:phone":"+32 10 65 89 05",
    "sg:postcode":"1435",
    "sg:province":"Brabant Wallon",
    "wof:name":"Pascal Denruyter",
    "wof:placetype":"venue"
},
  "geometry": {"coordinates":[4.6200151443,50.6332092285],"type":"Point"}
}