{
  "type": "Feature",
  "properties": {
    "addr:full":"Avenue Du Ch\u00c2teau Rock 5 Waterloo Brabant Wallon 1410",
    "addr:housenumber":"5",
    "addr:postcode":"1410",
    "addr:street":"Avenue Du Cha\u0302Teau Rock",
    "iso:country":"BE",
    "sg:address":"Avenue Du Ch\u00c2teau Rock 5",
    "sg:city":"Waterloo",
    "sg:orig_category":"Centres sportifs",
    "sg:phone":"+32 2 354 52 88",
    "sg:postcode":"1410",
    "sg:province":"Brabant Wallon",
    "wof:name":"Waterloo Yoga Genon Dominique",
    "wof:placetype":"venue"
},
  "geometry": {"coordinates":[4.3787751198,50.7174453735],"type":"Point"}
}