{
  "type": "Feature",
  "properties": {
    "iso:country":"BE",
    "sg:address":"Markekerkstraat 1",
    "sg:city":"Kortrijk",
    "sg:orig_category":"Banken and kredietinstellingen",
    "sg:phone":"+32 56 21 36 40",
    "sg:postcode":"8510",
    "sg:province":"West-Vlaanderen",
    "wof:name":"Kbc",
    "wof:placetype":"venue"
},
  "geometry": {"coordinates":[3.2336480618,50.8069915771],"type":"Point"}
}