{
  "type": "Feature",
  "properties": {
    "iso:country":"BE",
    "sg:address":"Kasteleinsstraat 8a",
    "sg:city":"Brussel/bruxelles",
    "sg:orig_category":"Herstellingswinkels voor diverse persoonlijke and huishoudartikelen Installatie van metalen schrijnw",
    "sg:phone":"+32 2 640 90 08",
    "sg:postcode":"1000",
    "sg:province":"Bruxelles-Capitale",
    "wof:name":"Tinant",
    "wof:placetype":"venue"
},
  "geometry": {"coordinates":[4.3635420799,50.8257522583],"type":"Point"}
}