{
  "type": "Feature",
  "properties": {
    "iso:country":"BE",
    "sg:address":"Stationsstr 89",
    "sg:city":"Brakel",
    "sg:classifiers":[
        {
            "category":"Fast Food",
            "type":"Food & Drink"
        }
    ],
    "sg:phone":"+32 55 42 57 58",
    "sg:postcode":"9660",
    "sg:province":"Oost-Vlaanderen",
    "sg:tags":[
        "meeneem",
        "restaurant"
    ],
    "wof:name":"Frituur Polleke",
    "wof:placetype":"venue"
},
  "geometry": {"coordinates":[3.7643089294,50.8024520874],"type":"Point"}
}