{
  "type": "Feature",
  "properties": {
    "addr:full":"Rue Joseph Wauters 4 Amay Li\u00e8ge 4540",
    "addr:housenumber":"4",
    "addr:postcode":"4540",
    "addr:street":"Rue Joseph Wauters",
    "iso:country":"BE",
    "sg:address":"Rue Joseph Wauters 4",
    "sg:city":"Amay",
    "sg:orig_category":"M\u00e9decins and sp\u00e9cialistes",
    "sg:phone":"+32 85 31 13 19",
    "sg:postcode":"4540",
    "sg:province":"Li\u00e8ge",
    "wof:name":"B. Per\u00c9e",
    "wof:placetype":"venue"
},
  "geometry": {"coordinates":[5.3190498352,50.5479354858],"type":"Point"}
}