{
  "type": "Feature",
  "properties": {
    "addr:full":"Rue Du Page 42-54 Bruxelles (ixelles) Bruxelles-Capitale 1050",
    "addr:housenumber":"42-54",
    "addr:postcode":"1050",
    "addr:street":"Rue Du Page",
    "iso:country":"BE",
    "sg:address":"Rue Du Page 42-54",
    "sg:city":"Bruxelles (ixelles)",
    "sg:classifiers":[
        {
            "category":"Autos & Motor Vehicles",
            "subcategory":"Auto Supplies",
            "type":"Retail Goods"
        }
    ],
    "sg:phone":"+32 2 537 45 66",
    "sg:postcode":"1050",
    "sg:province":"Bruxelles-Capitale",
    "sg:tags":[
        "access",
        "automobile",
        "part",
        "-"
    ],
    "wof:name":"Declercq Ets Sprl",
    "wof:placetype":"venue"
},
  "geometry": {"coordinates":[4.3586421013,50.823009491],"type":"Point"}
}