{
  "type": "Feature",
  "properties": {
    "iso:country":"BE",
    "sg:address":"Steenweg Op Turnhout 124",
    "sg:city":"Merksplas",
    "sg:orig_category":"Plaatsen van vloer- and muurbekleding Schilders",
    "sg:phone":"+32 14 63 26 70",
    "sg:postcode":"2330",
    "sg:province":"Antwerpen",
    "wof:name":"Ruben Lanslots",
    "wof:placetype":"venue"
},
  "geometry": {"coordinates":[4.8755321503,51.3493118286],"type":"Point"}
}