{
  "type": "Feature",
  "properties": {
    "addr:full":"Heikantstraat 3 Essen Antwerpen 2910",
    "addr:housenumber":"3",
    "addr:postcode":"2910",
    "addr:street":"Heikantstraat",
    "iso:country":"BE",
    "sg:address":"Heikantstraat 3",
    "sg:city":"Essen",
    "sg:orig_category":"Eleveurs de bovins",
    "sg:phone":"+32 3 667 27 06",
    "sg:postcode":"2910",
    "sg:province":"Antwerpen",
    "wof:name":"Leon Stevens",
    "wof:placetype":"venue"
},
  "geometry": {"coordinates":[4.462594986,51.4581871033],"type":"Point"}
}