{
  "type": "Feature",
  "properties": {
    "addr:full":"Rue Abb\u00e9 Demarteau 6 Sprimont Li\u00e8ge 4140",
    "addr:housenumber":"6",
    "addr:postcode":"4140",
    "addr:street":"Rue Abbe\u0301 Demarteau",
    "iso:country":"BE",
    "sg:address":"Rue Abb\u00e9 Demarteau 6",
    "sg:city":"Sprimont",
    "sg:classifiers":[
        {
            "category":"Wholesale",
            "subcategory":"Wine & Distilled Alcoholic Beverages",
            "type":"Manufacturing & Wholesale Goods"
        }
    ],
    "sg:phone":"+32 4 382 11 56",
    "sg:postcode":"4140",
    "sg:province":"Li\u00e8ge",
    "sg:tags":[
        "whol",
        "-",
        "spirit",
        "mfg"
    ],
    "wof:name":"Kassotakis G",
    "wof:placetype":"venue"
},
  "geometry": {"coordinates":[5.6597499847,50.5072059631],"type":"Point"}
}