{
  "type": "Feature",
  "properties": {
    "addr:full":"Leuvensesteenweg 312 Kortenberg Vlaams-Brabant 3070",
    "addr:housenumber":"312",
    "addr:postcode":"3070",
    "addr:street":"Leuvensesteenweg;Vlaams-Brabant",
    "iso:country":"BE",
    "sg:address":"Leuvensesteenweg 312",
    "sg:city":"Kortenberg",
    "sg:orig_category":"Auto-\u00e9coles",
    "sg:phone":"+32 2 756 06 66",
    "sg:postcode":"3070",
    "sg:province":"Vlaams-Brabant",
    "wof:name":"Rijschool Pole Promotions",
    "wof:placetype":"venue"
},
  "geometry": {"coordinates":[4.5453529358,50.8886146545],"type":"Point"}
}