{
  "type": "Feature",
  "properties": {
    "iso:country":"BE",
    "sg:address":"Interleuvenlaan 58",
    "sg:city":"Leuven (heverlee)",
    "sg:classifiers":[
        {
            "category":"Health Services",
            "subcategory":"Hospital",
            "type":"Services"
        }
    ],
    "sg:phone":"+32 3 218 83 83",
    "sg:postcode":"3001",
    "sg:province":"Vlaams-Brabant",
    "wof:name":"Idewe Vzw",
    "wof:placetype":"venue"
},
  "geometry": {"coordinates":[4.736620903,50.8478965759],"type":"Point"}
}