{
  "type": "Feature",
  "properties": {
    "iso:country":"BE",
    "sg:address":"Holliguette 462",
    "sg:city":"Herve",
    "sg:orig_category":"Persagentschappen",
    "sg:phone":"+32 87 68 80 62",
    "sg:postcode":"4654",
    "sg:province":"Li\u00e8ge",
    "wof:name":"Jos\u00c9 Lambiet",
    "wof:placetype":"venue"
},
  "geometry": {"coordinates":[5.8042421341,50.6694908142],"type":"Point"}
}