{
  "type": "Feature",
  "properties": {
    "addr:full":"Voormuide 71bb Gent Oost-Vlaanderen 9000",
    "addr:housenumber":"71bb",
    "addr:postcode":"9000",
    "addr:street":"Voormuide;Oost-Vlaanderen",
    "iso:country":"BE",
    "sg:address":"Voormuide 71bb",
    "sg:city":"Gent",
    "sg:orig_category":"Artiesten and kunstenaars",
    "sg:phone":"+32 9 233 82 80",
    "sg:postcode":"9000",
    "sg:province":"Oost-Vlaanderen",
    "wof:name":"Ricardo Rodriguez Brey",
    "wof:placetype":"venue"
},
  "geometry": {"coordinates":[3.7294139862,51.0687904358],"type":"Point"}
}