{
  "type": "Feature",
  "properties": {
    "iso:country":"BE",
    "sg:address":"R. Pierre Joseph Antoine 96",
    "sg:city":"Herstal",
    "sg:orig_category":"D\u00e9taillants en pi\u00e8ces and accessoires de voitures",
    "sg:phone":"+32 4 248 12 11",
    "sg:postcode":"4040",
    "sg:province":"Li\u00e8ge",
    "wof:name":"Ernotte",
    "wof:placetype":"venue"
},
  "geometry": {"coordinates":[5.6412520409,50.6799964905],"type":"Point"}
}