{
  "type": "Feature",
  "properties": {
    "addr:full":"Stationsstraat 15 Ronse/renaix Oost-Vlaanderen 9600",
    "addr:housenumber":"15",
    "addr:postcode":"9600",
    "addr:street":"Stationsstraat",
    "iso:country":"BE",
    "sg:address":"Stationsstraat 15",
    "sg:city":"Ronse/renaix",
    "sg:orig_category":"Herstellingen and onderhoud van auto's Voertuigen",
    "sg:phone":"+32 55 20 70 70",
    "sg:postcode":"9600",
    "sg:province":"Oost-Vlaanderen",
    "wof:name":"G. Van Coppenolle/gaston Vancoppenolle",
    "wof:placetype":"venue"
},
  "geometry": {"coordinates":[3.6008601189,50.7434539795],"type":"Point"}
}