{
  "type": "Feature",
  "properties": {
    "addr:full":"Dendermondsesteenweg 143 Gent Oost-Vlaanderen 9000",
    "addr:housenumber":"143",
    "addr:postcode":"9000",
    "addr:street":"Dendermondsesteenweg;Oost-Vlaanderen",
    "iso:country":"BE",
    "sg:address":"Dendermondsesteenweg 143",
    "sg:city":"Gent",
    "sg:classifiers":[
        {
            "category":"Shopping",
            "subcategory":"Clothing, Apparel, & Fashions",
            "type":"Retail Goods"
        }
    ],
    "sg:phone":"+32 9 228 29 00",
    "sg:postcode":"9000",
    "sg:province":"Oost-Vlaanderen",
    "sg:tags":[
        "lingerie",
        "sous-v\u00eatements"
    ],
    "wof:name":"Textiel Gina",
    "wof:placetype":"venue"
},
  "geometry": {"coordinates":[3.7437300682,51.0539283752],"type":"Point"}
}