{
  "type": "Feature",
  "properties": {
    "addr:full":"Heihoekstraat 114 Sint-niklaas Oost-Vlaanderen 9100",
    "addr:housenumber":"114",
    "addr:postcode":"9100",
    "addr:street":"Heihoekstraat",
    "iso:country":"BE",
    "sg:address":"Heihoekstraat 114",
    "sg:city":"Sint-niklaas",
    "sg:orig_category":"Plaatsen van vloer- and muurbekleding Schilders",
    "sg:phone":"+32 3 776 57 17",
    "sg:postcode":"9100",
    "sg:province":"Oost-Vlaanderen",
    "wof:name":"Hedan Decor",
    "wof:placetype":"venue"
},
  "geometry": {"coordinates":[4.1894721985,51.1832771301],"type":"Point"}
}