{
  "type": "Feature",
  "properties": {
    "addr:full":"Kloosterstraat 37 Beveren Oost-Vlaanderen 9120",
    "addr:housenumber":"37",
    "addr:postcode":"9120",
    "addr:street":"Kloosterstraat",
    "iso:country":"BE",
    "sg:address":"Kloosterstraat 37",
    "sg:city":"Beveren",
    "sg:orig_category":"Openbare bibliotheken and archieven",
    "sg:phone":"+32 3 775 79 59",
    "sg:postcode":"9120",
    "sg:province":"Oost-Vlaanderen",
    "wof:name":"Openbare Bibliotheek",
    "wof:placetype":"venue"
},
  "geometry": {"coordinates":[4.2593111992,51.2148361206],"type":"Point"}
}