{
  "type": "Feature",
  "properties": {
    "addr:full":"4120 Neupr\u00c9 Li\u00e8ge 4120",
    "addr:postcode":"4120;4120",
    "iso:country":"BE",
    "sg:address":"4120",
    "sg:city":"Neupr\u00c9",
    "sg:orig_category":"Pharmaciens",
    "sg:phone":"+32 900 10 500",
    "sg:postcode":"4120",
    "sg:province":"Li\u00e8ge",
    "wof:name":"Pharmacies De Garde",
    "wof:placetype":"venue"
},
  "geometry": {"coordinates":[5.4994301796,50.5423088074],"type":"Point"}
}