{
  "type": "Feature",
  "properties": {
    "addr:full":"Place Albert I 24 Florenville Luxembourg 6820",
    "addr:housenumber":"24",
    "addr:postcode":"6820",
    "addr:street":"Place Albert I",
    "iso:country":"BE",
    "sg:address":"Place Albert I 24",
    "sg:city":"Florenville",
    "sg:classifiers":[
        {
            "category":"Real Estate",
            "subcategory":"Real Estate Services",
            "type":"Services"
        }
    ],
    "sg:phone":"+32 61 32 00 00",
    "sg:postcode":"6820",
    "sg:province":"Luxembourg",
    "wof:name":"Interm\u00e9diaire Transaction Immobili\u00e8re",
    "wof:placetype":"venue"
},
  "geometry": {"coordinates":[5.3102898598,49.6983985901],"type":"Point"}
}