{
  "type": "Feature",
  "properties": {
    "iso:country":"BE",
    "sg:address":"Avenue Lat\u00c9rale 171",
    "sg:city":"Bruxelles",
    "sg:orig_category":"Cr\u00e8ches and garderies d'enfants. Activit\u00e9s r\u00e9cr\u00e9atives diverses",
    "sg:phone":"+32 2 375 60 76",
    "sg:postcode":"1180",
    "sg:province":"Bruxelles-Capitale",
    "wof:name":"Youplaboum",
    "wof:placetype":"venue"
},
  "geometry": {"coordinates":[4.3657588959,50.7957267761],"type":"Point"}
}