{
  "type": "Feature",
  "properties": {
    "iso:country":"BE",
    "sg:address":"Steenweg Op Tielen 27",
    "sg:city":"Turnhout",
    "sg:orig_category":"Installatie van metalen schrijnwerk",
    "sg:phone":"+32 14 43 03 32",
    "sg:postcode":"2300",
    "sg:province":"Antwerpen",
    "wof:name":"Mojaco",
    "wof:placetype":"venue"
},
  "geometry": {"coordinates":[4.9375748634,51.3063545227],"type":"Point"}
}