{
  "type": "Feature",
  "properties": {
    "addr:full":"Brusselsestraat 146a Brakel (nederbrakel) Oost-Vlaanderen 9660",
    "addr:housenumber":"146a",
    "addr:postcode":"9660",
    "addr:street":"Brusselsestraat",
    "iso:country":"BE",
    "sg:address":"Brusselsestraat 146a",
    "sg:city":"Brakel (nederbrakel)",
    "sg:classifiers":[
        {
            "category":"Place Of Worship",
            "subcategory":"Church",
            "type":"Public Place"
        }
    ],
    "sg:phone":"+32 55 42 19 89",
    "sg:postcode":"9660",
    "sg:province":"Oost-Vlaanderen",
    "sg:tags":[
        "article",
        "baptismal"
    ],
    "wof:name":"A & S Design",
    "wof:placetype":"venue"
},
  "geometry": {"coordinates":[3.785490036,50.8084716797],"type":"Point"}
}