{
  "type": "Feature",
  "properties": {
    "iso:country":"BE",
    "sg:address":"Vijverstraat 2",
    "sg:city":"Lede",
    "sg:orig_category":"Brandweer and civiele bescherming",
    "sg:phone":"+32 53 80 07 07",
    "sg:postcode":"9340",
    "sg:province":"Oost-Vlaanderen",
    "wof:name":"Brandweerkazerne",
    "wof:placetype":"venue"
},
  "geometry": {"coordinates":[3.9777851105,50.9678878784],"type":"Point"}
}