{
  "type": "Feature",
  "properties": {
    "addr:full":"Diksmuidsestraat 59 Ieper West-Vlaanderen 8900",
    "addr:housenumber":"59",
    "addr:postcode":"8900",
    "addr:street":"Diksmuidsestraat",
    "iso:country":"BE",
    "sg:address":"Diksmuidsestraat 59",
    "sg:city":"Ieper",
    "sg:classifiers":[
        {
            "category":"Personal",
            "subcategory":"Beauty Salon",
            "type":"Services"
        }
    ],
    "sg:phone":"+32 57 20 43 09",
    "sg:postcode":"8900",
    "sg:province":"West-Vlaanderen",
    "sg:tags":[
        "lady",
        "-",
        "hairdressing"
    ],
    "wof:name":"Christy (coiffure)",
    "wof:placetype":"venue"
},
  "geometry": {"coordinates":[2.8863079548,50.8536529541],"type":"Point"}
}