{
  "type": "Feature",
  "properties": {
    "addr:full":"Avenue De La Closi\u00e8re 8 Waterloo Brabant Wallon 1410",
    "addr:housenumber":"8",
    "addr:postcode":"1410",
    "addr:street":"Avenue De La Closie\u0300Re",
    "iso:country":"BE",
    "sg:address":"Avenue De La Closi\u00e8re 8",
    "sg:city":"Waterloo",
    "sg:classifiers":[
        {
            "category":"Real Estate",
            "subcategory":"Architect",
            "type":"Services"
        }
    ],
    "sg:phone":"+32 2 351 43 36",
    "sg:postcode":"1410",
    "sg:province":"Brabant Wallon",
    "wof:name":"Hac K-t",
    "wof:placetype":"venue"
},
  "geometry": {"coordinates":[4.3884620667,50.7096252441],"type":"Point"}
}