{
  "type": "Feature",
  "properties": {
    "addr:full":"Rue Bas-bruly 43 Couvin Namur 5660",
    "addr:housenumber":"43",
    "addr:postcode":"5660",
    "addr:street":"Rue Bas-Bruly",
    "iso:country":"BE",
    "sg:address":"Rue Bas-bruly 43",
    "sg:city":"Couvin",
    "sg:orig_category":"Dakwerken Loodgieterij, verwarming and sanitaire installaties",
    "sg:phone":"+32 60 37 75 19",
    "sg:postcode":"5660",
    "sg:province":"Namur",
    "wof:name":"Karine Papleux",
    "wof:placetype":"venue"
},
  "geometry": {"coordinates":[4.4653840065,50.0035171509],"type":"Point"}
}