{
  "type": "Feature",
  "properties": {
    "addr:full":"Leuerbroek 1082 Kinrooi (ophoven) Limburg 3640",
    "addr:postcode":"1082;3640",
    "iso:country":"BE",
    "sg:address":"Leuerbroek 1082",
    "sg:city":"Kinrooi (ophoven)",
    "sg:classifiers":[
        {
            "category":"Manufacturing",
            "subcategory":"Metals",
            "type":"Manufacturing & Wholesale Goods"
        }
    ],
    "sg:phone":"+32 89 70 32 42",
    "sg:postcode":"3640",
    "sg:province":"Limburg",
    "sg:tags":[
        "ornamental",
        "work",
        "-"
    ],
    "wof:name":"Segers J",
    "wof:placetype":"venue"
},
  "geometry": {"coordinates":[5.7518138885,51.1371650696],"type":"Point"}
}