{
  "type": "Feature",
  "properties": {
    "addr:full":"Nederhasseltstraat 200 Ninove Oost-Vlaanderen 9400",
    "addr:housenumber":"200",
    "addr:postcode":"9400",
    "addr:street":"Nederhasseltstraat",
    "iso:country":"BE",
    "sg:address":"Nederhasseltstraat 200",
    "sg:city":"Ninove",
    "sg:orig_category":"Rev\u00eatements pour sols and murs. Mat\u00e9riaux de construction Location de machines-outils and de mat\u00e9rie",
    "sg:phone":"+32 54 33 35 75",
    "sg:postcode":"9400",
    "sg:province":"Oost-Vlaanderen",
    "wof:name":"Luc Scheerlinck",
    "wof:placetype":"venue"
},
  "geometry": {"coordinates":[3.9777140617,50.8466567993],"type":"Point"}
}