{
  "type": "Feature",
  "properties": {
    "iso:country":"BE",
    "sg:address":"Wijtschotbaan 3",
    "sg:city":"Schoten",
    "sg:classifiers":[
        {
            "category":"Utilities",
            "subcategory":"Refuse",
            "type":"Services"
        }
    ],
    "sg:phone":"+32 3 658 06 78",
    "sg:postcode":"2900",
    "sg:province":"Antwerpen",
    "sg:tags":[
        "management",
        "waste"
    ],
    "wof:name":"Rendac Transport Nv",
    "wof:placetype":"venue"
},
  "geometry": {"coordinates":[4.5050148964,51.2428207397],"type":"Point"}
}