{
  "type": "Feature",
  "properties": {
    "iso:country":"BE",
    "sg:address":"Rue De Doriemont 19",
    "sg:city":"Doische",
    "sg:orig_category":"Hout and afgeleiden Gh IJzerwaren, bouw- and verfmaterialen",
    "sg:phone":"+32 82 67 81 39",
    "sg:postcode":"5680",
    "sg:province":"Namur",
    "wof:name":"Surenter",
    "wof:placetype":"venue"
},
  "geometry": {"coordinates":[4.7544307709,50.1842155457],"type":"Point"}
}