{
  "type": "Feature",
  "properties": {
    "iso:country":"BE",
    "sg:address":"Schouwburgstraat 3",
    "sg:city":"Gent",
    "sg:orig_category":"Salles de spectacles",
    "sg:phone":"+32 9 223 06 81",
    "sg:postcode":"9000",
    "sg:province":"Oost-Vlaanderen",
    "wof:name":"De Vlaamse Opera",
    "wof:placetype":"venue"
},
  "geometry": {"coordinates":[3.7221341133,51.0496673584],"type":"Point"}
}