{
  "type": "Feature",
  "properties": {
    "addr:full":"Poelstraat 28 Lebbeke Oost-Vlaanderen 9280",
    "addr:housenumber":"28",
    "addr:postcode":"9280",
    "addr:street":"Poelstraat",
    "iso:country":"BE",
    "sg:address":"Poelstraat 28",
    "sg:city":"Lebbeke",
    "sg:orig_category":"Elektrische installaties voor woningen",
    "sg:phone":"+32 52 41 12 49",
    "sg:postcode":"9280",
    "sg:province":"Oost-Vlaanderen",
    "wof:name":"Joseph Depauw",
    "wof:placetype":"venue"
},
  "geometry": {"coordinates":[4.1496191025,51.0129623413],"type":"Point"}
}