{
  "type": "Feature",
  "properties": {
    "addr:full":"Brugsesteenweg 2a Harelbeke West-Vlaanderen 8531",
    "addr:housenumber":"2a",
    "addr:postcode":"8531",
    "addr:street":"Brugsesteenweg",
    "iso:country":"BE",
    "sg:address":"Brugsesteenweg 2a",
    "sg:city":"Harelbeke",
    "sg:classifiers":[
        {
            "category":"Autos & Motor Vehicles",
            "subcategory":"Automobile Sales",
            "type":"Retail Goods"
        }
    ],
    "sg:phone":"+32 56 71 73 73",
    "sg:postcode":"8531",
    "sg:province":"West-Vlaanderen",
    "sg:tags":[
        "equipment",
        "industrial",
        "transport"
    ],
    "wof:name":"Satc Nv",
    "wof:placetype":"venue"
},
  "geometry": {"coordinates":[3.2725629807,50.8811035156],"type":"Point"}
}