{
  "type": "Feature",
  "properties": {
    "addr:full":"Rue Des D\u00c9port\u00c9s 74 Charleroi Hainaut 6032",
    "addr:housenumber":"74",
    "addr:postcode":"6032",
    "addr:street":"Rue Des De\u0301Porte\u0301S;Hainaut",
    "iso:country":"BE",
    "sg:address":"Rue Des D\u00c9port\u00c9s 74",
    "sg:city":"Charleroi",
    "sg:orig_category":"Installatie van houten of kunststof schrijnwerk",
    "sg:phone":"+32 71 47 35 24",
    "sg:postcode":"6032",
    "sg:province":"Hainaut",
    "wof:name":"Joel Vandendries",
    "wof:placetype":"venue"
},
  "geometry": {"coordinates":[4.415017128,50.3863258362],"type":"Point"}
}