{
  "type": "Feature",
  "properties": {
    "addr:full":"Grand-place 4 Bertrix Luxembourg 6880",
    "addr:housenumber":"4",
    "addr:postcode":"6880",
    "addr:street":"Grand-Place",
    "iso:country":"BE",
    "sg:address":"Grand-place 4",
    "sg:city":"Bertrix",
    "sg:classifiers":[
        {
            "category":"Health Services",
            "subcategory":"Health Practitioner",
            "type":"Services"
        }
    ],
    "sg:phone":"+32 61 61 38 76",
    "sg:postcode":"6880",
    "sg:province":"Luxembourg",
    "sg:tags":[
        "physiotherapist"
    ],
    "wof:name":"Shalon Eric",
    "wof:placetype":"venue"
},
  "geometry": {"coordinates":[5.2524261475,49.8544120789],"type":"Point"}
}