{
  "type": "Feature",
  "properties": {
    "iso:country":"BE",
    "sg:address":"Bilzersteenweg 126b1",
    "sg:city":"Tongeren",
    "sg:orig_category":"Installation \u00e9lectrique industrielle",
    "sg:phone":"+32 12 23 92 14",
    "sg:postcode":"3700",
    "sg:province":"Limburg",
    "wof:name":"B.s.g. Security",
    "wof:placetype":"venue"
},
  "geometry": {"coordinates":[5.4629878998,50.7876472473],"type":"Point"}
}