{
  "type": "Feature",
  "properties": {
    "iso:country":"BE",
    "sg:address":"Avenue Du Cerisier 2",
    "sg:city":"Charleroi (gosselies)",
    "sg:classifiers":[
        {
            "category":"Building & Trades",
            "subcategory":"Equipment Rental",
            "type":"Services"
        }
    ],
    "sg:postcode":"6041",
    "sg:province":"Hainaut",
    "sg:tags":[
        "crane",
        "-"
    ],
    "wof:name":"Van Egdom Lifting",
    "wof:placetype":"venue"
},
  "geometry": {"coordinates":[4.4314317703,50.4685935974],"type":"Point"}
}