{
  "type": "Feature",
  "properties": {
    "addr:full":"Britse Lei 3 Box 8 Antwerpen Antwerpen 2000",
    "addr:housenumber":"3;8",
    "addr:postcode":"2000",
    "addr:street":"Lei;Box",
    "iso:country":"BE",
    "sg:address":"Britse Lei 3 Box 8",
    "sg:city":"Antwerpen",
    "sg:classifiers":[
        {
            "category":"Professional",
            "subcategory":"Lawyer & Legal Services",
            "type":"Services"
        }
    ],
    "sg:phone":"+32 3 248 37 99",
    "sg:postcode":"2000",
    "sg:province":"Antwerpen",
    "wof:name":"Rappaport D",
    "wof:placetype":"venue"
},
  "geometry": {"coordinates":[4.4077401161,51.2106933594],"type":"Point"}
}