{
  "type": "Feature",
  "properties": {
    "addr:full":"Rue Saint-pierre 73 La Louviere Hainaut 7100",
    "addr:housenumber":"73",
    "addr:postcode":"7100",
    "addr:street":"Rue Saint-Pierre",
    "iso:country":"BE",
    "sg:address":"Rue Saint-pierre 73",
    "sg:city":"La Louviere",
    "sg:orig_category":"Woningbouw",
    "sg:phone":"+32 64 54 01 01",
    "sg:postcode":"7100",
    "sg:province":"Hainaut",
    "wof:name":"Cogeco",
    "wof:placetype":"venue"
},
  "geometry": {"coordinates":[4.2026472092,50.5105171204],"type":"Point"}
}