{
  "type": "Feature",
  "properties": {
    "addr:full":"Edestraat 85a Haaltert Oost-Vlaanderen 9450",
    "addr:housenumber":"85a",
    "addr:postcode":"9450",
    "addr:street":"Edestraat",
    "iso:country":"BE",
    "sg:address":"Edestraat 85a",
    "sg:city":"Haaltert",
    "sg:classifiers":[
        {
            "category":"Professional",
            "subcategory":"Testing Lab",
            "type":"Services"
        }
    ],
    "sg:phone":"+32 53 83 85 46",
    "sg:postcode":"9450",
    "sg:province":"Oost-Vlaanderen",
    "sg:tags":[
        "chemist"
    ],
    "wof:name":"De Fr\u00e9 D",
    "wof:placetype":"venue"
},
  "geometry": {"coordinates":[3.9935400486,50.9095916748],"type":"Point"}
}