{
  "type": "Feature",
  "properties": {
    "iso:country":"BE",
    "sg:address":"Zi 7",
    "sg:city":"Flemalle",
    "sg:classifiers":[
        {
            "category":"Professional",
            "type":"Services"
        }
    ],
    "sg:phone":"+32 4 330 33 33",
    "sg:postcode":"4400",
    "sg:province":"Li\u00e8ge",
    "sg:tags":[
        "-",
        "related",
        "road",
        "transport"
    ],
    "wof:name":"Transports Louis Frisaye Sa",
    "wof:placetype":"venue"
},
  "geometry": {"coordinates":[5.4576430321,50.5693130493],"type":"Point"}
}