{
  "type": "Feature",
  "properties": {
    "iso:country":"BE",
    "sg:address":"Welvaartstraat 89",
    "sg:city":"Berlaar",
    "sg:orig_category":"Epiceries",
    "sg:phone":"+32 3 482 41 50",
    "sg:postcode":"2590",
    "sg:province":"Antwerpen",
    "wof:name":"Tecno",
    "wof:placetype":"venue"
},
  "geometry": {"coordinates":[4.6389451027,51.10729599],"type":"Point"}
}