{
  "type": "Feature",
  "properties": {
    "addr:full":"Parklaan 143 Edegem Antwerpen 2650",
    "addr:housenumber":"143",
    "addr:postcode":"2650",
    "addr:street":"Parklaan",
    "iso:country":"BE",
    "sg:address":"Parklaan 143",
    "sg:city":"Edegem",
    "sg:classifiers":[
        {
            "category":"Manufacturing",
            "subcategory":"Furniture",
            "type":"Manufacturing & Wholesale Goods"
        }
    ],
    "sg:phone":"+32 3 449 66 79",
    "sg:postcode":"2650",
    "sg:province":"Antwerpen",
    "sg:tags":[
        "made",
        "-",
        "custom"
    ],
    "wof:name":"Verreyke H",
    "wof:placetype":"venue"
},
  "geometry": {"coordinates":[4.4278879166,51.1686668396],"type":"Point"}
}