{
  "type": "Feature",
  "properties": {
    "iso:country":"BE",
    "sg:address":"Commendries 25",
    "sg:city":"Kortenaken (kersbeek-miskom)",
    "sg:classifiers":[
        {
            "category":"Professional",
            "subcategory":"Management & Consulting",
            "type":"Services"
        }
    ],
    "sg:phone":"+32 11 58 33 26",
    "sg:postcode":"3472",
    "sg:province":"Vlaams-Brabant",
    "sg:tags":[
        "tax-consultants"
    ],
    "wof:name":"Hermans D",
    "wof:placetype":"venue"
},
  "geometry": {"coordinates":[5.032392025,50.8990745544],"type":"Point"}
}