{
  "type": "Feature",
  "properties": {
    "iso:country":"BE",
    "sg:address":"Cijnshofstraat 3",
    "sg:city":"Heusden-zolder",
    "sg:orig_category":"Banques and organismes de cr\u00e9dit",
    "sg:phone":"+32 11 42 50 92",
    "sg:postcode":"3550",
    "sg:province":"Limburg",
    "wof:name":"Bacob",
    "wof:placetype":"venue"
},
  "geometry": {"coordinates":[5.2809109688,51.0326919556],"type":"Point"}
}