{
  "type": "Feature",
  "properties": {
    "addr:full":"Pontweg 9bb Aalst Oost-Vlaanderen 9310",
    "addr:housenumber":"9bb",
    "addr:postcode":"9310",
    "addr:street":"Pontweg",
    "iso:country":"BE",
    "sg:address":"Pontweg 9bb",
    "sg:city":"Aalst",
    "sg:orig_category":"Charpentes and couvertures",
    "sg:phone":"+32 53 77 31 40",
    "sg:postcode":"9310",
    "sg:province":"Oost-Vlaanderen",
    "wof:name":"De Cock-boel",
    "wof:placetype":"venue"
},
  "geometry": {"coordinates":[4.0812802315,50.9653587341],"type":"Point"}
}