{
  "type": "Feature",
  "properties": {
    "iso:country":"BE",
    "sg:address":"Rue Saint-jacques 34",
    "sg:city":"Namur",
    "sg:classifiers":[
        {
            "category":"Professional",
            "type":"Services"
        }
    ],
    "sg:phone":"+32 81 26 03 30",
    "sg:postcode":"5000",
    "sg:province":"Namur",
    "sg:tags":[
        "organisation",
        "de",
        "restaurants",
        "f\u00cates",
        "catering"
    ],
    "wof:name":"Restaurant La Varenne",
    "wof:placetype":"venue"
},
  "geometry": {"coordinates":[4.864030838,50.4652290344],"type":"Point"}
}