{
  "type": "Feature",
  "properties": {
    "iso:country":"BE",
    "sg:address":"Auguste Rodinlaan 33",
    "sg:city":"Elsene/ixelles",
    "sg:orig_category":"Advocaten and juridische adviseurs",
    "sg:phone":"+32 2 648 67 77",
    "sg:postcode":"1050",
    "sg:province":"Bruxelles-Capitale",
    "wof:name":"Caroline Koelman",
    "wof:placetype":"venue"
},
  "geometry": {"coordinates":[4.3797621727,50.827205658],"type":"Point"}
}