{
  "type": "Feature",
  "properties": {
    "addr:full":"Rue Des Mara\u00eechers 67 Li\u00e8ge 1 (li\u00e8ge 2) Li\u00e8ge 4020",
    "addr:housenumber":"67;1;2",
    "addr:postcode":"4020",
    "addr:street":"Rue Des Marai\u0302Chers",
    "iso:country":"BE",
    "sg:address":"Rue Des Mara\u00eechers 67",
    "sg:city":"Li\u00e8ge 1 (li\u00e8ge 2)",
    "sg:classifiers":[
        {
            "category":"Health Services",
            "subcategory":"Medical Lab",
            "type":"Services"
        }
    ],
    "sg:phone":"+32 4 349 07 04",
    "sg:postcode":"4020",
    "sg:province":"Li\u00e8ge",
    "sg:tags":[
        "laboratory",
        "dental"
    ],
    "wof:name":"Picone M",
    "wof:placetype":"venue"
},
  "geometry": {"coordinates":[5.5941090584,50.6390151978],"type":"Point"}
}