{
  "type": "Feature",
  "properties": {
    "addr:full":"Rue Roger De Keyser 117 Chimay (forges) Hainaut 6464",
    "addr:housenumber":"117",
    "addr:postcode":"6464",
    "addr:street":"Rue Roger De Keyser",
    "iso:country":"BE",
    "sg:address":"Rue Roger De Keyser 117",
    "sg:city":"Chimay (forges)",
    "sg:classifiers":[
        {
            "category":"Farming",
            "subcategory":"Farm & Veterinary Services",
            "type":"Manufacturing & Wholesale Goods"
        }
    ],
    "sg:phone":"+32 60 21 20 68",
    "sg:postcode":"6464",
    "sg:province":"Hainaut",
    "sg:tags":[
        "agricultural",
        "contractor"
    ],
    "wof:name":"Masuy",
    "wof:placetype":"venue"
},
  "geometry": {"coordinates":[4.3197059631,50.018573761],"type":"Point"}
}