{
  "type": "Feature",
  "properties": {
    "addr:full":"Sluis 67 Mol Antwerpen 2400",
    "addr:housenumber":"67",
    "addr:postcode":"2400",
    "addr:street":"Sluis",
    "iso:country":"BE",
    "sg:address":"Sluis 67",
    "sg:city":"Mol",
    "sg:orig_category":"Epiceries",
    "sg:phone":"+32 14 31 42 49",
    "sg:postcode":"2400",
    "sg:province":"Antwerpen",
    "wof:name":"Spar",
    "wof:placetype":"venue"
},
  "geometry": {"coordinates":[5.1573371887,51.2166976929],"type":"Point"}
}