{
  "type": "Feature",
  "properties": {
    "addr:full":"Avenue Elgise Saint-julien Bruxelles-auderghem Bruxelles-Capitale 1160",
    "addr:postcode":"1160",
    "addr:street":"Avenue Elgise Saint-Julien",
    "iso:country":"BE",
    "sg:address":"Avenue Elgise Saint-julien",
    "sg:city":"Bruxelles-auderghem",
    "sg:orig_category":"Fleurs and plantes",
    "sg:phone":"+32 2 672 64 10",
    "sg:postcode":"1160",
    "sg:province":"Bruxelles-Capitale",
    "wof:name":"Jocelyne & Christian",
    "wof:placetype":"venue"
},
  "geometry": {"coordinates":[4.4085321426,50.8201141357],"type":"Point"}
}