{
  "type": "Feature",
  "properties": {
    "iso:country":"BE",
    "sg:address":"Sint-janslaan 26",
    "sg:city":"Diepenbeek",
    "sg:orig_category":"Mat\u00e9riel m\u00e9dical and orthop\u00e9dique and proth\u00e8ses Fab",
    "sg:phone":"+32 11 32 36 61",
    "sg:postcode":"3590",
    "sg:province":"Limburg",
    "wof:name":"Tandservice Beankens",
    "wof:placetype":"venue"
},
  "geometry": {"coordinates":[5.4201431274,50.9046821594],"type":"Point"}
}