{
  "type": "Feature",
  "properties": {
    "addr:full":"Kiezelstraat 56 Hasselt Limburg 3500",
    "addr:housenumber":"56",
    "addr:postcode":"3500",
    "addr:street":"Kiezelstraat",
    "iso:country":"BE",
    "sg:address":"Kiezelstraat 56",
    "sg:city":"Hasselt",
    "sg:orig_category":"Reclamebureaus",
    "sg:phone":"+32 11 24 31 26",
    "sg:postcode":"3500",
    "sg:province":"Limburg",
    "wof:name":"Indus",
    "wof:placetype":"venue"
},
  "geometry": {"coordinates":[5.3780961037,50.9324302673],"type":"Point"}
}