{
  "type": "Feature",
  "properties": {
    "addr:full":"Jacoletstraat 21 Leopoldsburg Limburg 3970",
    "addr:housenumber":"21",
    "addr:postcode":"3970",
    "addr:street":"Jacoletstraat",
    "iso:country":"BE",
    "sg:address":"Jacoletstraat 21",
    "sg:city":"Leopoldsburg",
    "sg:orig_category":"Pain, p\u00e2tisseries and confiseries",
    "sg:phone":"+32 11 34 14 51",
    "sg:postcode":"3970",
    "sg:province":"Limburg",
    "wof:name":"Leonidas",
    "wof:placetype":"venue"
},
  "geometry": {"coordinates":[5.2622032166,51.1165275574],"type":"Point"}
}