{
  "type": "Feature",
  "properties": {
    "addr:full":"Westkaai 6a Menen West-Vlaanderen 8930",
    "addr:housenumber":"6a",
    "addr:postcode":"8930",
    "addr:street":"Westkaai",
    "iso:country":"BE",
    "sg:address":"Westkaai 6a",
    "sg:city":"Menen",
    "sg:classifiers":[
        {
            "category":"Building & Trades",
            "subcategory":"Construction",
            "type":"Services"
        }
    ],
    "sg:phone":"+32 56 51 13 97",
    "sg:postcode":"8930",
    "sg:province":"West-Vlaanderen",
    "sg:tags":[
        "glazier"
    ],
    "wof:name":"E.v.m.",
    "wof:placetype":"venue"
},
  "geometry": {"coordinates":[3.1243100166,50.7901344299],"type":"Point"}
}