{
  "type": "Feature",
  "properties": {
    "iso:country":"BE",
    "sg:address":"Rue Nadet 57",
    "sg:city":"Herstal",
    "sg:classifiers":[
        {
            "category":"Home & Garden",
            "subcategory":"Kitchen Supply",
            "type":"Retail Goods"
        }
    ],
    "sg:phone":"+32 4 234 34 01",
    "sg:postcode":"4040",
    "sg:province":"Li\u00e8ge",
    "sg:tags":[
        "equipment",
        "baker",
        "-"
    ],
    "wof:name":"Briatte-coelen Sprl",
    "wof:placetype":"venue"
},
  "geometry": {"coordinates":[5.6256189346,50.666431427],"type":"Point"}
}