{
  "type": "Feature",
  "properties": {
    "iso:country":"BE",
    "sg:address":"Rue Alphonse Heureux 16",
    "sg:city":"Charleroi (mont-sur-marchienne)",
    "sg:classifiers":[
        {
            "category":"Arena",
            "subcategory":"Sports Club",
            "type":"Entertainment"
        }
    ],
    "sg:phone":"+32 71 51 52 63",
    "sg:postcode":"6032",
    "sg:province":"Hainaut",
    "wof:name":"Club Alpin Belge Section Du Hainaut",
    "wof:placetype":"venue"
},
  "geometry": {"coordinates":[4.3962750435,50.3722038269],"type":"Point"}
}