{
  "type": "Feature",
  "properties": {
    "iso:country":"BE",
    "sg:address":"Boulevard Des D\u00c9port\u00c9s 8",
    "sg:city":"Tournai",
    "sg:orig_category":"IJzerwaren, bouw- and verfmaterialen MEUBELONTWERP AND -INSTALLATIE Meubelzaken, woning- and keukeni",
    "sg:phone":"+32 69 84 50 28",
    "sg:postcode":"7500",
    "sg:province":"Hainaut",
    "wof:name":"Cadelbois",
    "wof:placetype":"venue"
},
  "geometry": {"coordinates":[3.4002110958,50.6113586426],"type":"Point"}
}