{
  "type": "Feature",
  "properties": {
    "iso:country":"BE",
    "sg:address":"Rue Cl\u00c9modeau 192",
    "sg:city":"Nandrin",
    "sg:orig_category":"Dierenartsen",
    "sg:phone":"+32 85 51 31 72",
    "sg:postcode":"4550",
    "sg:province":"Li\u00e8ge",
    "wof:name":"Jacques Mainil",
    "wof:placetype":"venue"
},
  "geometry": {"coordinates":[5.4204249382,50.5065155029],"type":"Point"}
}