{
  "type": "Feature",
  "properties": {
    "iso:country":"BE",
    "sg:address":"De Vunt 1",
    "sg:city":"Holsbeek",
    "sg:classifiers":[
        {
            "category":"Retail",
            "subcategory":"Car Wash",
            "type":"Services"
        }
    ],
    "sg:phone":"+32 16 46 47 12",
    "sg:postcode":"3220",
    "sg:province":"Vlaams-Brabant",
    "sg:tags":[
        "automobile",
        "washing",
        "-",
        "truck"
    ],
    "wof:name":"Car-wash De Vunt",
    "wof:placetype":"venue"
},
  "geometry": {"coordinates":[4.7167978287,50.9123573303],"type":"Point"}
}