{
  "type": "Feature",
  "properties": {
    "addr:full":"Rue De Botrange 131 Weismes/waimes Li\u00e8ge 4950",
    "addr:housenumber":"131",
    "addr:postcode":"4950",
    "addr:street":"Rue De Botrange",
    "iso:country":"BE",
    "sg:address":"Rue De Botrange 131",
    "sg:city":"Weismes/waimes",
    "sg:orig_category":"Luna-parks and parcs de r\u00e9cr\u00e9ation",
    "sg:phone":"+32 80 44 03 00",
    "sg:postcode":"4950",
    "sg:province":"Li\u00e8ge",
    "wof:name":"Hoge Venen Eifel",
    "wof:placetype":"venue"
},
  "geometry": {"coordinates":[6.1101899147,50.484249115],"type":"Point"}
}