{
  "type": "Feature",
  "properties": {
    "iso:country":"BE",
    "sg:address":"Chauss\u00e9e De Wavre 504 Box 7",
    "sg:city":"Grez-doiceau",
    "sg:classifiers":[
        {
            "category":"Communications",
            "subcategory":"Television Station",
            "type":"Services"
        }
    ],
    "sg:phone":"+32 10 84 12 48",
    "sg:postcode":"1390",
    "sg:province":"Brabant Wallon",
    "sg:tags":[
        "antenna"
    ],
    "wof:name":"Satellite Service",
    "wof:placetype":"venue"
},
  "geometry": {"coordinates":[4.6466069221,50.7328109741],"type":"Point"}
}