{
  "type": "Feature",
  "properties": {
    "addr:full":"Rue D'am\u00c9rique 51 Philippeville Namur 5600",
    "addr:housenumber":"51",
    "addr:postcode":"5600",
    "addr:street":"Rue D'Ame \u0301Rique",
    "iso:country":"BE",
    "sg:address":"Rue D'am\u00c9rique 51",
    "sg:city":"Philippeville",
    "sg:orig_category":"Enseignement maternel and primaire",
    "sg:phone":"+32 71 66 84 72",
    "sg:postcode":"5600",
    "sg:province":"Namur",
    "wof:name":"Ecole Fond. Communale",
    "wof:placetype":"venue"
},
  "geometry": {"coordinates":[4.5895829201,50.1967544556],"type":"Point"}
}