{
  "type": "Feature",
  "properties": {
    "iso:country":"BE",
    "sg:address":"Provinciestraat 160",
    "sg:city":"Antwerpen",
    "sg:classifiers":[
        {
            "category":"Shopping",
            "subcategory":"Bicycles & Sporting Goods",
            "type":"Retail Goods"
        }
    ],
    "sg:phone":"+32 3 232 90 54",
    "sg:postcode":"2018",
    "sg:province":"Antwerpen",
    "sg:tags":[
        "-"
    ],
    "wof:name":"Bruggeman Daniel",
    "wof:placetype":"venue"
},
  "geometry": {"coordinates":[4.4258880615,51.2127876282],"type":"Point"}
}