{
  "type": "Feature",
  "properties": {
    "iso:country":"BE",
    "sg:address":"Geldenaaksebaan 182",
    "sg:city":"Leuven",
    "sg:orig_category":"Epiceries",
    "sg:phone":"+32 16 23 95 80",
    "sg:postcode":"3001",
    "sg:province":"Vlaams-Brabant",
    "wof:name":"Elza Milan",
    "wof:placetype":"venue"
},
  "geometry": {"coordinates":[4.7111611366,50.8649291992],"type":"Point"}
}