{
  "type": "Feature",
  "properties": {
    "addr:full":"Chauss\u00c9e De Huy 290 Chaumont-gistoux Brabant Wallon 1325",
    "addr:housenumber":"290",
    "addr:postcode":"1325",
    "addr:street":"Chausse\u0301E De Huy",
    "iso:country":"BE",
    "sg:address":"Chauss\u00c9e De Huy 290",
    "sg:city":"Chaumont-gistoux",
    "sg:orig_category":"Bouwmaterialen Gh",
    "sg:phone":"+32 10 68 83 29",
    "sg:postcode":"1325",
    "sg:province":"Brabant Wallon",
    "wof:name":"Conard & Orleans",
    "wof:placetype":"venue"
},
  "geometry": {"coordinates":[4.7281661034,50.6682739258],"type":"Point"}
}