{
  "type": "Feature",
  "properties": {
    "addr:full":"Erasme Ruelensvest 91b41 Leuven Vlaams-Brabant 3001",
    "addr:housenumber":"91b41",
    "addr:postcode":"3001",
    "addr:street":"Erasme Ruelensvest",
    "iso:country":"BE",
    "sg:address":"Erasme Ruelensvest 91b41",
    "sg:city":"Leuven",
    "sg:orig_category":"Services pour animaux domestiques",
    "sg:phone":"+32 16 22 64 06",
    "sg:postcode":"3001",
    "sg:province":"Vlaams-Brabant",
    "wof:name":"Ir\u00c8ne Geukens",
    "wof:placetype":"venue"
},
  "geometry": {"coordinates":[4.7043781281,50.8680305481],"type":"Point"}
}