{
  "type": "Feature",
  "properties": {
    "addr:full":"Rue De La Bach\u00c9e 70 Lasne Brabant Wallon 1380",
    "addr:housenumber":"70",
    "addr:postcode":"1380",
    "addr:street":"Rue De La Bache\u0301E",
    "iso:country":"BE",
    "sg:address":"Rue De La Bach\u00c9e 70",
    "sg:city":"Lasne",
    "sg:orig_category":"Jardinage",
    "sg:phone":"+32 2 633 21 15",
    "sg:postcode":"1380",
    "sg:province":"Brabant Wallon",
    "wof:name":"Lamine J.-y.",
    "wof:placetype":"venue"
},
  "geometry": {"coordinates":[4.4240617752,50.6604804993],"type":"Point"}
}