{
  "type": "Feature",
  "properties": {
    "iso:country":"BE",
    "sg:address":"Place Communale 13",
    "sg:city":"Villers-la-ville (tilly)",
    "sg:classifiers":[
        {
            "category":"Professional",
            "subcategory":"Engineering",
            "type":"Services"
        }
    ],
    "sg:phone":"+32 71 87 83 16",
    "sg:postcode":"1495",
    "sg:province":"Brabant Wallon",
    "sg:tags":[
        "environmental",
        "technique",
        "-"
    ],
    "wof:name":"Geobelconseil-geofina Sa",
    "wof:placetype":"venue"
},
  "geometry": {"coordinates":[4.530477047,50.5786132812],"type":"Point"}
}