{
  "type": "Feature",
  "properties": {
    "addr:full":"Kapellensteenweg 252 Kalmthout Antwerpen 2920",
    "addr:housenumber":"252",
    "addr:postcode":"2920",
    "addr:street":"Kapellensteenweg",
    "iso:country":"BE",
    "sg:address":"Kapellensteenweg 252",
    "sg:city":"Kalmthout",
    "sg:classifiers":[
        {
            "category":"Fast Food",
            "type":"Food & Drink"
        }
    ],
    "sg:phone":"+32 3 666 44 76",
    "sg:postcode":"2920",
    "sg:province":"Antwerpen",
    "sg:tags":[
        "meeneem",
        "restaurant"
    ],
    "wof:name":"Adel",
    "wof:placetype":"venue"
},
  "geometry": {"coordinates":[4.4744949341,51.3786849976],"type":"Point"}
}