{
  "type": "Feature",
  "properties": {
    "addr:full":"Tassijnslaan 1 Beveren (haasdonk) Oost-Vlaanderen 9120",
    "addr:housenumber":"1",
    "addr:postcode":"9120",
    "addr:street":"Tassijnslaan",
    "iso:country":"BE",
    "sg:address":"Tassijnslaan 1",
    "sg:city":"Beveren (haasdonk)",
    "sg:classifiers":[
        {
            "category":"Shopping",
            "subcategory":"Discount & Variety Stores",
            "type":"Retail Goods"
        }
    ],
    "sg:phone":"+32 3 755 54 86",
    "sg:postcode":"9120",
    "sg:province":"Oost-Vlaanderen",
    "sg:tags":[
        "warehouse",
        "-",
        "merchandise"
    ],
    "wof:name":"C M C Trading",
    "wof:placetype":"venue"
},
  "geometry": {"coordinates":[4.2134051323,51.1754646301],"type":"Point"}
}