{
  "type": "Feature",
  "properties": {
    "iso:country":"BE",
    "sg:address":"Verheydenstraat 25",
    "sg:city":"Dilbeek",
    "sg:orig_category":"Boucheries",
    "sg:phone":"+32 2 569 56 19",
    "sg:postcode":"1700",
    "sg:province":"Vlaams-Brabant",
    "wof:name":"Ghislain Verbustel",
    "wof:placetype":"venue"
},
  "geometry": {"coordinates":[4.2621688843,50.8452415466],"type":"Point"}
}