{
  "type": "Feature",
  "properties": {
    "addr:full":"Rue De La Cabocherie 7 Mouscron (dottignies) Hainaut 7711",
    "addr:housenumber":"7",
    "addr:postcode":"7711",
    "addr:street":"Rue De La Cabocherie",
    "iso:country":"BE",
    "sg:address":"Rue De La Cabocherie 7",
    "sg:city":"Mouscron (dottignies)",
    "sg:classifiers":[
        {
            "category":"Health Services",
            "subcategory":"Doctor",
            "type":"Services"
        }
    ],
    "sg:phone":"+32 56 48 84 85",
    "sg:postcode":"7711",
    "sg:province":"Hainaut",
    "sg:tags":[
        "medicinephysicians",
        "surgeon"
    ],
    "wof:name":"Fourmeau V",
    "wof:placetype":"venue"
},
  "geometry": {"coordinates":[3.3098020554,50.7291755676],"type":"Point"}
}