{
  "type": "Feature",
  "properties": {
    "addr:full":"Dr. J. Geensstraat 22 Tienen Vlaams-Brabant 3300",
    "addr:housenumber":"22",
    "addr:postcode":"3300",
    "addr:street":"Dr. J. Geensstraat",
    "iso:country":"BE",
    "sg:address":"Dr. J. Geensstraat 22",
    "sg:city":"Tienen",
    "sg:orig_category":"Location de voitures",
    "sg:phone":"+32 16 81 24 09",
    "sg:postcode":"3300",
    "sg:province":"Vlaams-Brabant",
    "wof:name":"Sarcco",
    "wof:placetype":"venue"
},
  "geometry": {"coordinates":[4.9344639778,50.8074989319],"type":"Point"}
}