{
  "type": "Feature",
  "properties": {
    "addr:full":"Diksmuidebaan 122 Ichtegem West-Vlaanderen 8480",
    "addr:housenumber":"122",
    "addr:postcode":"8480",
    "iso:country":"BE",
    "sg:address":"Diksmuidebaan 122",
    "sg:city":"Ichtegem",
    "sg:orig_category":"Artists' Dolls",
    "sg:phone":"+32 51 58 21 05",
    "sg:postcode":"8480",
    "sg:province":"West-Vlaanderen",
    "wof:name":"Kunstatelier Claudine Roelens",
    "wof:placetype":"venue"
},
  "geometry": {"coordinates":[3.040802002,51.0829353333],"type":"Point"}
}