{
  "type": "Feature",
  "properties": {
    "iso:country":"BE",
    "sg:address":"Boulevard Auguste Reyers 163",
    "sg:city":"Bruxelles (schaerbeek)",
    "sg:classifiers":[
        {
            "category":"Museum",
            "type":"Entertainment"
        }
    ],
    "sg:phone":"+32 2 732 08 28",
    "sg:postcode":"1030",
    "sg:province":"Bruxelles-Capitale",
    "wof:name":"Clockarium Sprl",
    "wof:placetype":"venue"
},
  "geometry": {"coordinates":[4.4022288322,50.8483810425],"type":"Point"}
}