{
  "type": "Feature",
  "properties": {
    "iso:country":"BE",
    "sg:address":"Peerderbaan 2",
    "sg:city":"Bree",
    "sg:classifiers":[
        {
            "category":"Home & Garden",
            "subcategory":"Furniture",
            "type":"Retail Goods"
        }
    ],
    "sg:phone":"+32 89 46 53 74",
    "sg:postcode":"3960",
    "sg:province":"Limburg",
    "sg:tags":[
        "-"
    ],
    "wof:name":"Kena Tuindecor",
    "wof:placetype":"venue"
},
  "geometry": {"coordinates":[5.5944190025,51.1405677795],"type":"Point"}
}