{
  "type": "Feature",
  "properties": {
    "iso:country":"BE",
    "sg:address":"Broechemsesteenweg 159",
    "sg:city":"Nijlen",
    "sg:classifiers":[
        {
            "category":"Manufacturing",
            "subcategory":"Metals",
            "type":"Manufacturing & Wholesale Goods"
        }
    ],
    "sg:phone":"+32 3 481 75 24",
    "sg:postcode":"2560",
    "sg:province":"Antwerpen",
    "sg:tags":[
        "ironwork"
    ],
    "wof:name":"Algemene Smeed- En Constructiewerken Van Tendeloo Stefaan",
    "wof:placetype":"venue"
},
  "geometry": {"coordinates":[4.6584458351,51.1660346985],"type":"Point"}
}