{
  "type": "Feature",
  "properties": {
    "iso:country":"BE",
    "sg:address":"Vierlinden 37",
    "sg:city":"Evergem",
    "sg:classifiers":[
        {
            "category":"Travel",
            "subcategory":"Travel Agent",
            "type":"Entertainment"
        }
    ],
    "sg:phone":"+32 9 357 67 41",
    "sg:postcode":"9940",
    "sg:province":"Oost-Vlaanderen",
    "sg:tags":[
        "agency"
    ],
    "wof:name":"Galaxy Travel",
    "wof:placetype":"venue"
},
  "geometry": {"coordinates":[3.6934840679,51.1174545288],"type":"Point"}
}