{
  "type": "Feature",
  "properties": {
    "addr:full":"Chemin Des Postes 140 Waterloo Brabant Wallon 1410",
    "addr:housenumber":"140",
    "addr:postcode":"1410",
    "addr:street":"Chemin Des Postes",
    "iso:country":"BE",
    "sg:address":"Chemin Des Postes 140",
    "sg:city":"Waterloo",
    "sg:classifiers":[
        {
            "category":"Social Services",
            "subcategory":"Child Care",
            "type":"Services"
        }
    ],
    "sg:phone":"+32 2 354 21 49",
    "sg:postcode":"1410",
    "sg:province":"Brabant Wallon",
    "sg:tags":[
        "baby",
        "nursery",
        "day",
        "sitting"
    ],
    "wof:name":"Premiers Pas (aux)",
    "wof:placetype":"venue"
},
  "geometry": {"coordinates":[4.3714838028,50.7093925476],"type":"Point"}
}