{
  "type": "Feature",
  "properties": {
    "iso:country":"BE",
    "sg:address":"Square Plasky 92",
    "sg:city":"Brussel",
    "sg:orig_category":"Produits chimiques Gr",
    "sg:phone":"+32 2 735 10 75",
    "sg:postcode":"1030",
    "sg:province":"Bruxelles-Capitale",
    "wof:name":"Luzenac Benelux",
    "wof:placetype":"venue"
},
  "geometry": {"coordinates":[4.3958830833,50.8511657715],"type":"Point"}
}