{
  "type": "Feature",
  "properties": {
    "addr:full":"Dorp 6 Waarschoot Oost-Vlaanderen 9950",
    "addr:housenumber":"6",
    "addr:postcode":"9950",
    "addr:street":"Dorp",
    "iso:country":"BE",
    "sg:address":"Dorp 6",
    "sg:city":"Waarschoot",
    "sg:orig_category":"Traitements param\u00e9dicaux",
    "sg:phone":"+32 9 378 46 66",
    "sg:postcode":"9950",
    "sg:province":"Oost-Vlaanderen",
    "wof:name":"Vermeire Geert",
    "wof:placetype":"venue"
},
  "geometry": {"coordinates":[3.605727911,51.1512374878],"type":"Point"}
}