{
  "type": "Feature",
  "properties": {
    "addr:full":"Hogeschoollaan 61 Elsene/ixelles Bruxelles-Capitale 1050",
    "addr:housenumber":"61",
    "addr:postcode":"1050",
    "addr:street":"Hogeschoollaan",
    "iso:country":"BE",
    "sg:address":"Hogeschoollaan 61",
    "sg:city":"Elsene/ixelles",
    "sg:orig_category":"Architecten",
    "sg:phone":"+32 2 646 97 85",
    "sg:postcode":"1050",
    "sg:province":"Bruxelles-Capitale",
    "wof:name":"Daniel Culot",
    "wof:placetype":"venue"
},
  "geometry": {"coordinates":[4.38667202,50.8146781921],"type":"Point"}
}