{
  "type": "Feature",
  "properties": {
    "addr:full":"Rue Pascal Et Rapha\u00cbl Sacr\u00c9 7 Crisnee Li\u00e8ge 4367",
    "addr:housenumber":"7",
    "addr:postcode":"4367",
    "addr:street":"Rue Pascal Et Raphae\u0308L Sacre\u0301",
    "iso:country":"BE",
    "sg:address":"Rue Pascal Et Rapha\u00cbl Sacr\u00c9 7",
    "sg:city":"Crisnee",
    "sg:orig_category":"Tweedehandsgoederen",
    "sg:phone":"+32 4 257 60 49",
    "sg:postcode":"4367",
    "sg:province":"Li\u00e8ge",
    "wof:name":"Hubert Dubois",
    "wof:placetype":"venue"
},
  "geometry": {"coordinates":[5.4022278786,50.6971244812],"type":"Point"}
}