{
  "type": "Feature",
  "properties": {
    "iso:country":"BE",
    "sg:address":"Hospitaalstraat 51",
    "sg:city":"Temse (steendorp)",
    "sg:classifiers":[
        {
            "category":"Building & Trades",
            "subcategory":"Pest Control",
            "type":"Services"
        }
    ],
    "sg:phone":"+32 3 775 47 26",
    "sg:postcode":"9140",
    "sg:province":"Oost-Vlaanderen",
    "sg:tags":[
        "disinfectant",
        "insecticide"
    ],
    "wof:name":"Heyrman E",
    "wof:placetype":"venue"
},
  "geometry": {"coordinates":[4.2681469917,51.1349868774],"type":"Point"}
}