{
  "type": "Feature",
  "properties": {
    "iso:country":"BE",
    "sg:address":"Hoge Hul 34",
    "sg:city":"Brugge",
    "sg:orig_category":"Non-Classified Establishments",
    "sg:phone":"+32 50 31 06 51",
    "sg:postcode":"8000",
    "sg:province":"West-Vlaanderen",
    "wof:name":"Sweetee Bvba",
    "wof:placetype":"venue"
},
  "geometry": {"coordinates":[3.1994099617,51.246887207],"type":"Point"}
}