{
  "type": "Feature",
  "properties": {
    "iso:country":"BE",
    "sg:address":"Boechoutsesteenweg 132",
    "sg:city":"Hove",
    "sg:classifiers":[
        {
            "category":"Structure",
            "subcategory":"Office Building",
            "type":"Public Place"
        }
    ],
    "sg:phone":"+32 3 458 02 00",
    "sg:postcode":"2540",
    "sg:province":"Antwerpen",
    "sg:tags":[
        "roofing",
        "slate"
    ],
    "wof:name":"Dakwerken Walscharts Bvba",
    "wof:placetype":"venue"
},
  "geometry": {"coordinates":[4.4743199348,51.1623687744],"type":"Point"}
}