{
  "type": "Feature",
  "properties": {
    "addr:full":"Industrielaan 18 Lichtervelde West-Vlaanderen 8810",
    "addr:housenumber":"18",
    "addr:postcode":"8810",
    "addr:street":"Industrielaan",
    "iso:country":"BE",
    "sg:address":"Industrielaan 18",
    "sg:city":"Lichtervelde",
    "sg:classifiers":[
        {
            "category":"Bus Stop",
            "subcategory":"None",
            "type":"Transportation"
        }
    ],
    "sg:phone":"+32 51 72 42 51",
    "sg:postcode":"8810",
    "sg:province":"West-Vlaanderen",
    "sg:tags":[
        "electricity",
        "-",
        "high",
        "low",
        "cabin",
        "voltage"
    ],
    "wof:name":"Synerco",
    "wof:placetype":"venue"
},
  "geometry": {"coordinates":[3.1128630638,51.031211853],"type":"Point"}
}