{
  "type": "Feature",
  "properties": {
    "iso:country":"BE",
    "sg:address":"Rue Haute 116",
    "sg:city":"Soumagne",
    "sg:orig_category":"Huishoudapparaten, televisies and radio's",
    "sg:phone":"+32 4 377 55 19",
    "sg:postcode":"4633",
    "sg:province":"Li\u00e8ge",
    "wof:name":"Olivier Charlier",
    "wof:placetype":"venue"
},
  "geometry": {"coordinates":[5.7474370003,50.6441459656],"type":"Point"}
}