{
  "type": "Feature",
  "properties": {
    "addr:full":"Nijverheidsstraat 29 Erpe-mere (mere) Oost-Vlaanderen 9420",
    "addr:housenumber":"29",
    "addr:postcode":"9420",
    "addr:street":"Nijverheidsstraat;Mere Oost-Vlaanderen",
    "iso:country":"BE",
    "sg:address":"Nijverheidsstraat 29",
    "sg:city":"Erpe-mere (mere)",
    "sg:classifiers":[
        {
            "category":"Professional",
            "subcategory":"Advertising",
            "type":"Services"
        }
    ],
    "sg:phone":"+32 53 83 11 66",
    "sg:postcode":"9420",
    "sg:province":"Oost-Vlaanderen",
    "sg:tags":[
        "painter"
    ],
    "wof:name":"Publi-schouppe",
    "wof:placetype":"venue"
},
  "geometry": {"coordinates":[3.9671609402,50.9215698242],"type":"Point"}
}