{
  "type": "Feature",
  "properties": {
    "iso:country":"BE",
    "sg:address":"Kapelstraat 181",
    "sg:city":"Bredene",
    "sg:classifiers":[
        {
            "category":"Travel",
            "subcategory":"Hotels & Motels",
            "type":"Entertainment"
        }
    ],
    "sg:phone":"+32 59 32 11 93",
    "sg:postcode":"8450",
    "sg:province":"West-Vlaanderen",
    "wof:name":"Europa Hotel",
    "wof:placetype":"venue"
},
  "geometry": {"coordinates":[2.9736011028,51.251411438],"type":"Point"}
}