{
  "type": "Feature",
  "properties": {
    "iso:country":"BE",
    "sg:address":"Acaciastraat 27",
    "sg:city":"Diest",
    "sg:classifiers":[
        {
            "category":"Cafe",
            "type":"Food & Drink"
        }
    ],
    "sg:phone":"+32 13 33 37 56",
    "sg:postcode":"3290",
    "sg:province":"Vlaams-Brabant",
    "sg:tags":[
        "caf\u00e9s"
    ],
    "wof:name":"Samir Jarnija",
    "wof:placetype":"venue"
},
  "geometry": {"coordinates":[5.0637631416,50.9783401489],"type":"Point"}
}