{
  "type": "Feature",
  "properties": {
    "addr:full":"Douaneplein 4 Mechelen Antwerpen 2800",
    "addr:housenumber":"4",
    "addr:postcode":"2800",
    "addr:street":"Douaneplein",
    "iso:country":"BE",
    "sg:address":"Douaneplein 4",
    "sg:city":"Mechelen",
    "sg:classifiers":[
        {
            "category":"Social Services",
            "type":"Services"
        }
    ],
    "sg:phone":"+32 15 55 66 75",
    "sg:postcode":"2800",
    "sg:province":"Antwerpen",
    "sg:tags":[
        "handicapped",
        "-"
    ],
    "wof:name":"Atelier Helen Keller",
    "wof:placetype":"venue"
},
  "geometry": {"coordinates":[4.4940509796,51.0261306763],"type":"Point"}
}