{
  "type": "Feature",
  "properties": {
    "addr:full":"Rue V. Forthomme 64 Sprimont Li\u00e8ge 4140",
    "addr:housenumber":"64",
    "addr:postcode":"4140",
    "addr:street":"Rue V. Forthomme",
    "iso:country":"BE",
    "sg:address":"Rue V. Forthomme 64",
    "sg:city":"Sprimont",
    "sg:orig_category":"Afbraak- and draineerwerken",
    "sg:phone":"+32 4 382 14 03",
    "sg:postcode":"4140",
    "sg:province":"Li\u00e8ge",
    "wof:name":"Malherbe & Fils",
    "wof:placetype":"venue"
},
  "geometry": {"coordinates":[5.6597499847,50.5072059631],"type":"Point"}
}