{
  "type": "Feature",
  "properties": {
    "iso:country":"BE",
    "sg:address":"Schoolstraat 14a",
    "sg:city":"Schilde",
    "sg:classifiers":[
        {
            "category":"Social Services",
            "type":"Services"
        }
    ],
    "sg:phone":"+32 3 385 91 41",
    "sg:postcode":"2970",
    "sg:province":"Antwerpen",
    "wof:name":"Oxfam Wereldwinkel Schilde",
    "wof:placetype":"venue"
},
  "geometry": {"coordinates":[4.5800471306,51.237159729],"type":"Point"}
}