{
  "type": "Feature",
  "properties": {
    "iso:country":"BE",
    "sg:address":"Hondsweg 1ba",
    "sg:city":"Wingene",
    "sg:orig_category":"Groententeelt",
    "sg:phone":"+32 51 65 63 95",
    "sg:postcode":"8750",
    "sg:province":"West-Vlaanderen",
    "wof:name":"Guido Cogge",
    "wof:placetype":"venue"
},
  "geometry": {"coordinates":[3.2415249348,51.0531997681],"type":"Point"}
}