{
  "type": "Feature",
  "properties": {
    "addr:full":"Avenue L\u00e9on Mahillon 61 Bruxelles (schaerbeek) Bruxelles-Capitale 1030",
    "addr:housenumber":"61",
    "addr:postcode":"1030",
    "addr:street":"Avenue Le\u0301On Mahillon",
    "iso:country":"BE",
    "sg:address":"Avenue L\u00e9on Mahillon 61",
    "sg:city":"Bruxelles (schaerbeek)",
    "sg:classifiers":[
        {
            "category":"Real Estate",
            "subcategory":"Architect",
            "type":"Services"
        }
    ],
    "sg:phone":"+32 2 742 01 51",
    "sg:postcode":"1030",
    "sg:province":"Bruxelles-Capitale",
    "wof:name":"Brison A",
    "wof:placetype":"venue"
},
  "geometry": {"coordinates":[4.3927397728,50.8510551453],"type":"Point"}
}