{
  "type": "Feature",
  "properties": {
    "addr:full":"Rue Des M\u00e9sanges 1 Thuin (goz\u00e9e) Hainaut 6534",
    "addr:housenumber":"1",
    "addr:postcode":"6534",
    "addr:street":"Rue Des Me\u0301Sanges",
    "iso:country":"BE",
    "sg:address":"Rue Des M\u00e9sanges 1",
    "sg:city":"Thuin (goz\u00e9e)",
    "sg:classifiers":[
        {
            "category":"Health Services",
            "subcategory":"Health Practitioner",
            "type":"Services"
        }
    ],
    "sg:phone":"+32 71 51 90 72",
    "sg:postcode":"6534",
    "sg:province":"Hainaut",
    "sg:tags":[
        "physiotherapist"
    ],
    "wof:name":"Del Natale A",
    "wof:placetype":"venue"
},
  "geometry": {"coordinates":[4.3690280914,50.3558921814],"type":"Point"}
}