{
  "type": "Feature",
  "properties": {
    "iso:country":"BE",
    "sg:address":"Markt 49",
    "sg:city":"Geraardsbergen",
    "sg:orig_category":"M\u00e9decins and sp\u00e9cialistes",
    "sg:phone":"+32 54 41 41 91",
    "sg:postcode":"9500",
    "sg:province":"Oost-Vlaanderen",
    "wof:name":"Frank Douchy",
    "wof:placetype":"venue"
},
  "geometry": {"coordinates":[3.8838150501,50.7715530396],"type":"Point"}
}