{
  "type": "Feature",
  "properties": {
    "addr:full":"Rue Pont D'avroy 3 Li\u00e8ge 1 Li\u00e8ge 4000",
    "addr:housenumber":"3;1",
    "addr:postcode":"4000",
    "addr:street":"Rue Pont D'Avroy",
    "iso:country":"BE",
    "sg:address":"Rue Pont D'avroy 3",
    "sg:city":"Li\u00e8ge 1",
    "sg:classifiers":[
        {
            "category":"Shopping",
            "subcategory":"Jewelry",
            "type":"Retail Goods"
        }
    ],
    "sg:phone":"+32 4 221 14 08",
    "sg:postcode":"4000",
    "sg:province":"Li\u00e8ge",
    "sg:tags":[
        "-",
        "imitation"
    ],
    "wof:name":"Poncho",
    "wof:placetype":"venue"
},
  "geometry": {"coordinates":[5.5707001686,50.6407546997],"type":"Point"}
}