{
  "type": "Feature",
  "properties": {
    "iso:country":"BE",
    "sg:address":"Industrieweg 1035",
    "sg:city":"Herk-de-stad",
    "sg:orig_category":"Auctions - Greens, fruits, etc",
    "sg:phone":"+32 13 55 45 08",
    "sg:postcode":"3540",
    "sg:province":"Limburg",
    "wof:name":"Limburgse Tuinbouwveiling",
    "wof:placetype":"venue"
},
  "geometry": {"coordinates":[5.1668391228,50.9462432861],"type":"Point"}
}