{
  "type": "Feature",
  "properties": {
    "addr:full":"Steenweg Op Weelde 9 Merksplas Antwerpen 2330",
    "addr:housenumber":"9",
    "addr:postcode":"2330",
    "addr:street":"Steenweg Op Weelde",
    "iso:country":"BE",
    "sg:address":"Steenweg Op Weelde 9",
    "sg:city":"Merksplas",
    "sg:orig_category":"D\u00e9molition d\u00b4immeubles and terrassements",
    "sg:phone":"+32 14 63 50 08",
    "sg:postcode":"2330",
    "sg:province":"Antwerpen",
    "wof:name":"Lora",
    "wof:placetype":"venue"
},
  "geometry": {"coordinates":[4.8691620827,51.371925354],"type":"Point"}
}