{
  "type": "Feature",
  "properties": {
    "iso:country":"BE",
    "sg:address":"Rue De Velaine 164a",
    "sg:city":"Andenne",
    "sg:classifiers":[
        {
            "category":"Restaurant",
            "type":"Food & Drink"
        }
    ],
    "sg:phone":"+32 85 82 61 86",
    "sg:postcode":"5300",
    "sg:province":"Namur",
    "wof:name":"Restaurant La Velaine",
    "wof:placetype":"venue"
},
  "geometry": {"coordinates":[5.0982642174,50.4863739014],"type":"Point"}
}