{
  "type": "Feature",
  "properties": {
    "addr:full":"Hazelaarstraat 4 Sint-katelijne-waver Antwerpen 2860",
    "addr:housenumber":"4",
    "addr:postcode":"2860",
    "addr:street":"Hazelaarstraat",
    "iso:country":"BE",
    "sg:address":"Hazelaarstraat 4",
    "sg:city":"Sint-katelijne-waver",
    "sg:orig_category":"Gespecialiseerde residenti\u00eble bouw Verhuur voertuigen behalve auto's",
    "sg:phone":"+32 15 55 27 23",
    "sg:postcode":"2860",
    "sg:province":"Antwerpen",
    "wof:name":"Dockx",
    "wof:placetype":"venue"
},
  "geometry": {"coordinates":[4.5114941597,51.0460624695],"type":"Point"}
}