{
  "type": "Feature",
  "properties": {
    "iso:country":"BE",
    "sg:address":"Rue De Serbie 3",
    "sg:city":"Li\u00c8ge",
    "sg:classifiers":[
        {
            "category":"Restaurant",
            "type":"Food & Drink"
        }
    ],
    "sg:phone":"+32 4 252 55 33",
    "sg:postcode":"4000",
    "sg:province":"Li\u00e8ge",
    "wof:name":"Cortina",
    "wof:placetype":"venue"
},
  "geometry": {"coordinates":[5.5685777664,50.6295928955],"type":"Point"}
}