{
  "type": "Feature",
  "properties": {
    "addr:full":"Risstraat 10 Genk Limburg 3600",
    "addr:housenumber":"10",
    "addr:postcode":"3600",
    "addr:street":"Risstraat",
    "iso:country":"BE",
    "sg:address":"Risstraat 10",
    "sg:city":"Genk",
    "sg:orig_category":"Groenten and fruit Gh Warenhuizen",
    "sg:phone":"+32 89 84 10 20",
    "sg:postcode":"3600",
    "sg:province":"Limburg",
    "wof:name":"Huis Tima",
    "wof:placetype":"venue"
},
  "geometry": {"coordinates":[5.5096979141,51.0023956299],"type":"Point"}
}