{
  "type": "Feature",
  "properties": {
    "addr:full":"Grote Baan 46 Ravels Antwerpen 2380",
    "addr:housenumber":"46",
    "addr:postcode":"2380",
    "addr:street":"Grote Baan",
    "iso:country":"BE",
    "sg:address":"Grote Baan 46",
    "sg:city":"Ravels",
    "sg:classifiers":[
        {
            "category":"Home & Garden",
            "subcategory":"Carpets & Floor Coverings",
            "type":"Retail Goods"
        }
    ],
    "sg:phone":"+32 14 65 20 65",
    "sg:postcode":"2380",
    "sg:province":"Antwerpen",
    "sg:tags":[
        "material",
        "waterproofing"
    ],
    "wof:name":"Schrijver Systeem Vochtbestrijding Nv",
    "wof:placetype":"venue"
},
  "geometry": {"coordinates":[4.9932060242,51.3685646057],"type":"Point"}
}