{
  "type": "Feature",
  "properties": {
    "addr:full":"Rue De La Fourche 50 Brussel/bruxelles Bruxelles-Capitale 1000",
    "addr:housenumber":"50",
    "addr:postcode":"1000",
    "addr:street":"Rue De La Fourche;/",
    "iso:country":"BE",
    "sg:address":"Rue De La Fourche 50",
    "sg:city":"Brussel/bruxelles",
    "sg:classifiers":[
        {
            "category":"Bars & Pubs",
            "subcategory":"Nightclub",
            "type":"Food & Drink"
        }
    ],
    "sg:phone":"+32 477 55 15 32",
    "sg:postcode":"1000",
    "sg:province":"Bruxelles-Capitale",
    "sg:tags":[
        "bars"
    ],
    "wof:name":"L'ecrin Tropical",
    "wof:placetype":"venue"
},
  "geometry": {"coordinates":[4.3535699844,50.8490333557],"type":"Point"}
}