{
  "type": "Feature",
  "properties": {
    "addr:full":"Rue Ren\u00c9 Dewit 10 Waterloo Brabant Wallon 1410",
    "addr:housenumber":"10",
    "addr:postcode":"1410",
    "addr:street":"Rue Rene\u0301 Dewit",
    "iso:country":"BE",
    "sg:address":"Rue Ren\u00c9 Dewit 10",
    "sg:city":"Waterloo",
    "sg:orig_category":"Geschenken and souvenirs Verlichting and huishoudartikelen",
    "sg:phone":"+32 2 351 38 31",
    "sg:postcode":"1410",
    "sg:province":"Brabant Wallon",
    "wof:name":"La Maison D'a C\u00d4t\u00c9",
    "wof:placetype":"venue"
},
  "geometry": {"coordinates":[4.3977818489,50.7147369385],"type":"Point"}
}