{
  "type": "Feature",
  "properties": {
    "iso:country":"BE",
    "sg:address":"Heirbaan 103",
    "sg:city":"Machelen",
    "sg:classifiers":[
        {
            "category":"Arts & Performance",
            "subcategory":"Music",
            "type":"Entertainment"
        }
    ],
    "sg:phone":"+32 2 251 44 92",
    "sg:postcode":"1830",
    "sg:province":"Vlaams-Brabant",
    "sg:tags":[
        "freelance",
        "musician"
    ],
    "wof:name":"Van Bogaert R",
    "wof:placetype":"venue"
},
  "geometry": {"coordinates":[4.4454598427,50.9129638672],"type":"Point"}
}