{
  "type": "Feature",
  "properties": {
    "iso:country":"BE",
    "sg:address":"Sterrestraat 29",
    "sg:city":"Koekelare",
    "sg:orig_category":"S\u00e9curit\u00e9 sociale",
    "sg:phone":"+32 51 58 92 49",
    "sg:postcode":"8680",
    "sg:province":"West-Vlaanderen",
    "wof:name":"Vlaams Neutraal Ziekenf.",
    "wof:placetype":"venue"
},
  "geometry": {"coordinates":[2.9719059467,51.0882759094],"type":"Point"}
}