{
  "type": "Feature",
  "properties": {
    "addr:full":"Aarschotseweg 16 Herentals Antwerpen 2200",
    "addr:housenumber":"16",
    "addr:postcode":"2200",
    "addr:street":"Aarschotseweg",
    "iso:country":"BE",
    "sg:address":"Aarschotseweg 16",
    "sg:city":"Herentals",
    "sg:classifiers":[
        {
            "category":"Shopping",
            "subcategory":"Computers & Home Electronics",
            "type":"Retail Goods"
        }
    ],
    "sg:phone":"+32 14 22 00 63",
    "sg:postcode":"2200",
    "sg:province":"Antwerpen",
    "sg:tags":[
        "telephone",
        "apparatus",
        "accessory"
    ],
    "wof:name":"Van Looy Nv",
    "wof:placetype":"venue"
},
  "geometry": {"coordinates":[4.8470478058,51.1670227051],"type":"Point"}
}