{
  "type": "Feature",
  "properties": {
    "addr:full":"B\u00fcllingen 3 B\u00fcllingen Li\u00e8ge 4760",
    "addr:housenumber":"3",
    "addr:postcode":"4760",
    "addr:street":"Buellingen",
    "iso:country":"BE",
    "sg:address":"B\u00fcllingen 3",
    "sg:city":"B\u00fcllingen",
    "sg:classifiers":[
        {
            "category":"Insurance",
            "subcategory":"Insurance Agent",
            "type":"Services"
        }
    ],
    "sg:phone":"+32 80 64 21 30",
    "sg:postcode":"4760",
    "sg:province":"Li\u00e8ge",
    "sg:tags":[
        "broker"
    ],
    "wof:name":"Schroeder W",
    "wof:placetype":"venue"
},
  "geometry": {"coordinates":[6.2557492256,50.4061813354],"type":"Point"}
}