{
  "type": "Feature",
  "properties": {
    "iso:country":"BE",
    "sg:address":"Chemin D'esquimbreucq 8",
    "sg:city":"Lessines",
    "sg:orig_category":"Installatie van houten of kunststof schrijnwerk",
    "sg:phone":"+32 68 33 71 74",
    "sg:postcode":"7860",
    "sg:province":"Hainaut",
    "wof:name":"Christian Delcuve",
    "wof:placetype":"venue"
},
  "geometry": {"coordinates":[3.8141870499,50.71509552],"type":"Point"}
}