{
  "type": "Feature",
  "properties": {
    "iso:country":"BE",
    "sg:address":"Place Emile Vandervelde 15",
    "sg:city":"Saint-nicolas",
    "sg:classifiers":[
        {
            "category":"Cafe",
            "type":"Food & Drink"
        }
    ],
    "sg:phone":"+32 4 263 42 26",
    "sg:postcode":"4420",
    "sg:province":"Li\u00e8ge",
    "sg:tags":[
        "caf\u00e9s"
    ],
    "wof:name":"A C V",
    "wof:placetype":"venue"
},
  "geometry": {"coordinates":[5.5170350075,50.6369857788],"type":"Point"}
}