{
  "type": "Feature",
  "properties": {
    "iso:country":"BE",
    "sg:address":"Rue Du Foss\u00c9 1",
    "sg:city":"Aubange",
    "sg:orig_category":"Schoonheidssalons",
    "sg:phone":"+32 63 67 53 42",
    "sg:postcode":"6792",
    "sg:province":"Luxembourg",
    "wof:name":"Institut Val\u00c9rie",
    "wof:placetype":"venue"
},
  "geometry": {"coordinates":[5.7426528931,49.5602111816],"type":"Point"}
}