{
  "type": "Feature",
  "properties": {
    "iso:country":"BE",
    "sg:address":"Clos Pierre Gaultier 8",
    "sg:city":"La Hulpe",
    "sg:classifiers":[
        {
            "category":"Building & Trades",
            "subcategory":"Electrical",
            "type":"Services"
        }
    ],
    "sg:phone":"+32 2 652 48 23",
    "sg:postcode":"1310",
    "sg:province":"Brabant Wallon",
    "sg:tags":[
        "-",
        "electric",
        "contractor"
    ],
    "wof:name":"Fabry Ets",
    "wof:placetype":"venue"
},
  "geometry": {"coordinates":[4.4733920097,50.7267684937],"type":"Point"}
}