{
  "type": "Feature",
  "properties": {
    "addr:full":"A De Thomaz De Bossi\u00e8re 10 Ottignies-louvain-la-neuve (ottignies) Brabant Wallon 1340",
    "addr:housenumber":"10",
    "addr:postcode":"ottignies-louvain-la-neuve;1340",
    "addr:street":"A De Thomaz De Bossie\u0300Re",
    "iso:country":"BE",
    "sg:address":"A De Thomaz De Bossi\u00e8re 10",
    "sg:city":"Ottignies-louvain-la-neuve (ottignies)",
    "sg:classifiers":[
        {
            "category":"Building & Trades",
            "subcategory":"Electrical",
            "type":"Services"
        }
    ],
    "sg:phone":"+32 10 41 66 17",
    "sg:postcode":"1340",
    "sg:province":"Brabant Wallon",
    "sg:tags":[
        "electric",
        "-",
        "housewiring",
        "contractor"
    ],
    "wof:name":"Cumps Sprl",
    "wof:placetype":"venue"
},
  "geometry": {"coordinates":[4.5560340881,50.6678352356],"type":"Point"}
}