{
  "type": "Feature",
  "properties": {
    "addr:full":"Vlassenhove 16 Dentergem (oeselgem) West-Vlaanderen 8720",
    "addr:housenumber":"16",
    "addr:postcode":"8720",
    "addr:street":"Vlassenhove",
    "iso:country":"BE",
    "sg:address":"Vlassenhove 16",
    "sg:city":"Dentergem (oeselgem)",
    "sg:classifiers":[
        {
            "category":"Building & Trades",
            "subcategory":"Construction",
            "type":"Services"
        }
    ],
    "sg:phone":"+32 9 388 73 06",
    "sg:postcode":"8720",
    "sg:province":"West-Vlaanderen",
    "sg:tags":[
        "stucco",
        "contractor"
    ],
    "wof:name":"Diwa-plak",
    "wof:placetype":"venue"
},
  "geometry": {"coordinates":[3.4293599129,50.936794281],"type":"Point"}
}