{
  "type": "Feature",
  "properties": {
    "iso:country":"BE",
    "sg:address":"Mechelsesteenweg 305",
    "sg:city":"Kontich",
    "sg:classifiers":[
        {
            "category":"Home & Garden",
            "subcategory":"Building Materials",
            "type":"Retail Goods"
        }
    ],
    "sg:phone":"+32 3 457 69 58",
    "sg:postcode":"2550",
    "sg:province":"Antwerpen",
    "sg:tags":[
        "article",
        "-",
        "do-it-yourself"
    ],
    "wof:name":"Van Den Eynde (houthandel)",
    "wof:placetype":"venue"
},
  "geometry": {"coordinates":[4.4501571655,51.1216621399],"type":"Point"}
}