{
  "type": "Feature",
  "properties": {
    "addr:full":"Chauss\u00e9e De Waterloo 1384d Bruxelles (uccle) Bruxelles-Capitale 1180",
    "addr:housenumber":"1384d",
    "addr:postcode":"1180",
    "addr:street":"Chausse\u0301E De Waterloo",
    "iso:country":"BE",
    "sg:address":"Chauss\u00e9e De Waterloo 1384d",
    "sg:city":"Bruxelles (uccle)",
    "sg:classifiers":[
        {
            "category":"Communications",
            "subcategory":"Film & Video Production",
            "type":"Services"
        }
    ],
    "sg:phone":"+32 2 374 14 05",
    "sg:postcode":"1180",
    "sg:province":"Bruxelles-Capitale",
    "sg:tags":[
        "cassette",
        "retail",
        "-",
        "tape"
    ],
    "wof:name":"New Way",
    "wof:placetype":"venue"
},
  "geometry": {"coordinates":[4.3762331009,50.7875671387],"type":"Point"}
}