{
  "type": "Feature",
  "properties": {
    "addr:full":"Rue Martine Bourtonbourt 2 Namur Namur 5000",
    "addr:housenumber":"2",
    "addr:postcode":"5000",
    "addr:street":"Rue Martine Bourtonbourt",
    "iso:country":"BE",
    "sg:address":"Rue Martine Bourtonbourt 2",
    "sg:city":"Namur",
    "sg:orig_category":"Cr\u00e8ches and garderies d'enfants",
    "sg:phone":"+32 81 72 95 50",
    "sg:postcode":"5000",
    "sg:province":"Namur",
    "wof:name":"I.m.a.j.e.",
    "wof:placetype":"venue"
},
  "geometry": {"coordinates":[4.8407111168,50.4617919922],"type":"Point"}
}