{
  "type": "Feature",
  "properties": {
    "addr:full":"Turnhoutsebaan 391 Schilde Antwerpen 2970",
    "addr:housenumber":"391",
    "addr:postcode":"2970",
    "addr:street":"Turnhoutsebaan",
    "iso:country":"BE",
    "sg:address":"Turnhoutsebaan 391",
    "sg:city":"Schilde",
    "sg:orig_category":"Rev\u00eatements de sols and murs. Rev\u00eatements pour sols and murs",
    "sg:phone":"+32 3 383 14 33",
    "sg:postcode":"2970",
    "sg:province":"Antwerpen",
    "wof:name":"Fa. Granimar",
    "wof:placetype":"venue"
},
  "geometry": {"coordinates":[4.6022281647,51.2484741211],"type":"Point"}
}