{
  "type": "Feature",
  "properties": {
    "iso:country":"BE",
    "sg:address":"Rue Courtejoie 1",
    "sg:city":"Ciney",
    "sg:orig_category":"V\u00eatements pour b\u00e9b\u00e9s and enfants",
    "sg:phone":"+32 83 21 44 20",
    "sg:postcode":"5590",
    "sg:province":"Namur",
    "wof:name":"Menthe \u00c0 L'eau",
    "wof:placetype":"venue"
},
  "geometry": {"coordinates":[5.1003308296,50.2954216003],"type":"Point"}
}