{
  "type": "Feature",
  "properties": {
    "addr:full":"Kapelstraat 89 Hamont-achel (hamont) Limburg 3930",
    "addr:housenumber":"89",
    "addr:postcode":"3930",
    "addr:street":"Kapelstraat",
    "iso:country":"BE",
    "sg:address":"Kapelstraat 89",
    "sg:city":"Hamont-achel (hamont)",
    "sg:classifiers":[
        {
            "category":"Home & Garden",
            "subcategory":"Carpets & Floor Coverings",
            "type":"Retail Goods"
        }
    ],
    "sg:phone":"+32 11 44 56 88",
    "sg:postcode":"3930",
    "sg:province":"Limburg",
    "sg:tags":[
        "layer",
        "mosaicists"
    ],
    "wof:name":"Sutens Leyssen",
    "wof:placetype":"venue"
},
  "geometry": {"coordinates":[5.5450549126,51.2511863708],"type":"Point"}
}