{
  "type": "Feature",
  "properties": {
    "iso:country":"BE",
    "sg:address":"Zeedijk Centrum 476",
    "sg:city":"Koksijde (oostduinkerke)",
    "sg:classifiers":[
        {
            "category":"Tea Room",
            "subcategory":"None",
            "type":"Food & Drink"
        }
    ],
    "sg:phone":"+32 58 52 07 47",
    "sg:postcode":"8670",
    "sg:province":"West-Vlaanderen",
    "wof:name":"Zoet Genot ('t)",
    "wof:placetype":"venue"
},
  "geometry": {"coordinates":[2.6748790741,51.1337127686],"type":"Point"}
}