{
  "type": "Feature",
  "properties": {
    "iso:country":"BE",
    "sg:address":"Hoogstraat 36c",
    "sg:city":"Harelbeke",
    "sg:orig_category":"Ordinateurs and \u00e9quipement informatique",
    "sg:phone":"+32 56 71 67 61",
    "sg:postcode":"8531",
    "sg:province":"West-Vlaanderen",
    "wof:name":"Westsoft",
    "wof:placetype":"venue"
},
  "geometry": {"coordinates":[3.3114850521,50.880279541],"type":"Point"}
}