{
  "type": "Feature",
  "properties": {
    "addr:full":"Rijkmakerlaan 30 Essen Antwerpen 2910",
    "addr:housenumber":"30",
    "addr:postcode":"2910",
    "addr:street":"Rijkmakerlaan",
    "iso:country":"BE",
    "sg:address":"Rijkmakerlaan 30",
    "sg:city":"Essen",
    "sg:classifiers":[
        {
            "category":"Home & Garden",
            "subcategory":"Building Materials",
            "type":"Retail Goods"
        }
    ],
    "sg:phone":"+32 3 667 73 17",
    "sg:postcode":"2910",
    "sg:province":"Antwerpen",
    "sg:tags":[
        "window"
    ],
    "wof:name":"Berve Bvba",
    "wof:placetype":"venue"
},
  "geometry": {"coordinates":[4.5007348061,51.4471702576],"type":"Point"}
}