{
  "type": "Feature",
  "properties": {
    "iso:country":"BE",
    "sg:address":"Oude Markt 49",
    "sg:city":"Leuven",
    "sg:classifiers":[
        {
            "category":"Cafe",
            "type":"Food & Drink"
        }
    ],
    "sg:phone":"+32 16 20 03 37",
    "sg:postcode":"3000",
    "sg:province":"Vlaams-Brabant",
    "sg:tags":[
        "caf\u00e9s"
    ],
    "wof:name":"Caf\u00c9 Blokhut",
    "wof:placetype":"venue"
},
  "geometry": {"coordinates":[4.7439398766,50.8634796143],"type":"Point"}
}