{
  "type": "Feature",
  "properties": {
    "addr:full":"Rue Haute 254 Brussel/bruxelles Bruxelles-Capitale 1000",
    "addr:housenumber":"254",
    "addr:postcode":"1000",
    "addr:street":"Rue Haute;/",
    "iso:country":"BE",
    "sg:address":"Rue Haute 254",
    "sg:city":"Brussel/bruxelles",
    "sg:orig_category":"Pain, p\u00e2tisseries and confiseries",
    "sg:phone":"+32 2 512 32 83",
    "sg:postcode":"1000",
    "sg:province":"Bruxelles-Capitale",
    "wof:name":"Dirk Bergsma",
    "wof:placetype":"venue"
},
  "geometry": {"coordinates":[4.3483772278,50.8365135193],"type":"Point"}
}