{
  "type": "Feature",
  "properties": {
    "iso:country":"BE",
    "sg:address":"Rue Edmond Rostand 13",
    "sg:city":"Bruxelles (anderlecht)",
    "sg:classifiers":[
        {
            "category":"Health Services",
            "subcategory":"Doctor",
            "type":"Services"
        }
    ],
    "sg:phone":"+32 2 523 51 17",
    "sg:postcode":"1070",
    "sg:province":"Bruxelles-Capitale",
    "sg:tags":[
        "medicinephysicians",
        "surgeon"
    ],
    "wof:name":"Kartounian H",
    "wof:placetype":"venue"
},
  "geometry": {"coordinates":[4.3088459969,50.8452072144],"type":"Point"}
}