{
  "type": "Feature",
  "properties": {
    "addr:full":"Langeweg 11 Sint-laureins Oost-Vlaanderen 9980",
    "addr:housenumber":"11",
    "addr:postcode":"9980",
    "addr:street":"Langeweg",
    "iso:country":"BE",
    "sg:address":"Langeweg 11",
    "sg:city":"Sint-laureins",
    "sg:orig_category":"Eleveurs de bovins",
    "sg:phone":"+32 9 379 05 38",
    "sg:postcode":"9980",
    "sg:province":"Oost-Vlaanderen",
    "wof:name":"Gerardus Verwilst",
    "wof:placetype":"venue"
},
  "geometry": {"coordinates":[3.5582909584,51.2446060181],"type":"Point"}
}