{
  "type": "Feature",
  "properties": {
    "addr:full":"Koebrugstraat 27 Oostende West-Vlaanderen 8400",
    "addr:housenumber":"27",
    "addr:postcode":"8400",
    "addr:street":"Koebrugstraat",
    "iso:country":"BE",
    "sg:address":"Koebrugstraat 27",
    "sg:city":"Oostende",
    "sg:orig_category":"Entretien and r\u00e9parations de voitures",
    "sg:phone":"+32 59 51 45 20",
    "sg:postcode":"8400",
    "sg:province":"West-Vlaanderen",
    "wof:name":"Christy Motors",
    "wof:placetype":"venue"
},
  "geometry": {"coordinates":[2.9453411102,51.2119216919],"type":"Point"}
}