{
  "type": "Feature",
  "properties": {
    "iso:country":"BE",
    "sg:address":"Rue De La Bonne Fontaine 10",
    "sg:city":"Bertrix",
    "sg:classifiers":[
        {
            "category":"Mining & Drilling",
            "type":"Manufacturing & Wholesale Goods"
        }
    ],
    "sg:phone":"+32 61 41 16 93",
    "sg:postcode":"6880",
    "sg:province":"Luxembourg",
    "sg:tags":[
        "quarry"
    ],
    "wof:name":"Carriere Les Rochettes",
    "wof:placetype":"venue"
},
  "geometry": {"coordinates":[5.2459039688,49.8550071716],"type":"Point"}
}