{
  "type": "Feature",
  "properties": {
    "addr:full":"Zoutestraat 101 Antwerpen Antwerpen 2040",
    "addr:housenumber":"101",
    "addr:postcode":"2040",
    "addr:street":"Zoutestraat",
    "iso:country":"BE",
    "sg:address":"Zoutestraat 101",
    "sg:city":"Antwerpen",
    "sg:orig_category":"Goederenvervoer over de weg",
    "sg:phone":"+32 3 568 62 22",
    "sg:postcode":"2040",
    "sg:province":"Antwerpen",
    "wof:name":"Transport Frigo Express",
    "wof:placetype":"venue"
},
  "geometry": {"coordinates":[4.3060250282,51.3519096375],"type":"Point"}
}