{
  "type": "Feature",
  "properties": {
    "iso:country":"BE",
    "sg:address":"Avenue Adolphe Buyl 126",
    "sg:city":"Elsene/ixelles",
    "sg:orig_category":"Imprimeries and copyshops",
    "sg:phone":"+32 2 648 86 76",
    "sg:postcode":"1050",
    "sg:province":"Bruxelles-Capitale",
    "wof:name":"Print & Copy",
    "wof:placetype":"venue"
},
  "geometry": {"coordinates":[4.3844227791,50.8143577576],"type":"Point"}
}