{
  "type": "Feature",
  "properties": {
    "iso:country":"BE",
    "sg:address":"Korenbloemstraat 8",
    "sg:city":"Merelbeke",
    "sg:orig_category":"Boissons",
    "sg:phone":"+32 9 362 46 75",
    "sg:postcode":"9820",
    "sg:province":"Oost-Vlaanderen",
    "wof:name":"Georges De Leu",
    "wof:placetype":"venue"
},
  "geometry": {"coordinates":[3.7211470604,50.9652786255],"type":"Point"}
}