{
  "type": "Feature",
  "properties": {
    "addr:full":"Rue Du Mambour 7 Li\u00e8ge 1 Li\u00e8ge 4000",
    "addr:housenumber":"7;1",
    "addr:postcode":"4000",
    "addr:street":"Rue Du Mambour",
    "iso:country":"BE",
    "sg:address":"Rue Du Mambour 7",
    "sg:city":"Li\u00e8ge 1",
    "sg:classifiers":[
        {
            "category":"Wholesale",
            "subcategory":"Construction Materials",
            "type":"Manufacturing & Wholesale Goods"
        }
    ],
    "sg:phone":"+32 4 252 10 21",
    "sg:postcode":"4000",
    "sg:province":"Li\u00e8ge",
    "sg:tags":[
        "civil",
        "engineering",
        "-"
    ],
    "wof:name":"New Glass",
    "wof:placetype":"venue"
},
  "geometry": {"coordinates":[5.5701580048,50.6232299805],"type":"Point"}
}