{
  "type": "Feature",
  "properties": {
    "iso:country":"BE",
    "sg:address":"Albertlaan 257",
    "sg:city":"Vorst/forest",
    "sg:orig_category":"Boekenuitgeverijen",
    "sg:phone":"+32 2 346 05 36",
    "sg:postcode":"1190",
    "sg:province":"Bruxelles-Capitale",
    "wof:name":"S.d.s.",
    "wof:placetype":"venue"
},
  "geometry": {"coordinates":[4.3467960358,50.815196991],"type":"Point"}
}