{
  "type": "Feature",
  "properties": {
    "addr:full":"Torhoutsesteenweg 341 Oostende West-Vlaanderen 8400",
    "addr:housenumber":"341",
    "addr:postcode":"8400",
    "addr:street":"Torhoutsesteenweg",
    "iso:country":"BE",
    "sg:address":"Torhoutsesteenweg 341",
    "sg:city":"Oostende",
    "sg:classifiers":[
        {
            "category":"Professional",
            "subcategory":"Printing & Photocopies",
            "type":"Services"
        }
    ],
    "sg:phone":"+32 59 80 34 28",
    "sg:postcode":"8400",
    "sg:province":"West-Vlaanderen",
    "sg:tags":[
        "trophy",
        "medal"
    ],
    "wof:name":"Archery Dynamics",
    "wof:placetype":"venue"
},
  "geometry": {"coordinates":[2.9064619541,51.2149162292],"type":"Point"}
}