{
  "type": "Feature",
  "properties": {
    "addr:full":"Rue De La Paix 56 Saint-nicolas Li\u00e8ge 4420",
    "addr:housenumber":"56",
    "addr:postcode":"4420",
    "addr:street":"Rue De La Paix",
    "iso:country":"BE",
    "sg:address":"Rue De La Paix 56",
    "sg:city":"Saint-nicolas",
    "sg:orig_category":"Installation \u00e9lectrique r\u00e9sidentielle",
    "sg:phone":"+32 4 252 24 57",
    "sg:postcode":"4420",
    "sg:province":"Li\u00e8ge",
    "wof:name":"Telesca",
    "wof:placetype":"venue"
},
  "geometry": {"coordinates":[5.5408158302,50.6266593933],"type":"Point"}
}