{
  "type": "Feature",
  "properties": {
    "addr:full":"Rue De Binche 452 Boussu Hainaut 7300",
    "addr:housenumber":"452",
    "addr:postcode":"7300",
    "addr:street":"Rue De Binche",
    "iso:country":"BE",
    "sg:address":"Rue De Binche 452",
    "sg:city":"Boussu",
    "sg:classifiers":[
        {
            "category":"Arena",
            "subcategory":"Sports Club",
            "type":"Entertainment"
        }
    ],
    "sg:phone":"+32 65 77 05 23",
    "sg:postcode":"7300",
    "sg:province":"Hainaut",
    "sg:tags":[
        "de"
    ],
    "wof:name":"Un. B.c. Flenu Quaregnon",
    "wof:placetype":"venue"
},
  "geometry": {"coordinates":[3.8033089638,50.4264335632],"type":"Point"}
}