{
  "type": "Feature",
  "properties": {
    "addr:full":"Groendreef 4 Deinze Oost-Vlaanderen 9800",
    "addr:housenumber":"4",
    "addr:postcode":"9800",
    "addr:street":"Groendreef",
    "iso:country":"BE",
    "sg:address":"Groendreef 4",
    "sg:city":"Deinze",
    "sg:orig_category":"Eleveurs de bovins",
    "sg:phone":"+32 51 63 37 11",
    "sg:postcode":"9800",
    "sg:province":"Oost-Vlaanderen",
    "wof:name":"Firmin Lambert",
    "wof:placetype":"venue"
},
  "geometry": {"coordinates":[3.4608919621,51.0015983582],"type":"Point"}
}