{
  "type": "Feature",
  "properties": {
    "iso:country":"BE",
    "sg:address":"Place Jacques Brel 30",
    "sg:city":"Herstal",
    "sg:orig_category":"Drukkerijen and copyshops",
    "sg:phone":"+32 4 264 80 42",
    "sg:postcode":"4040",
    "sg:province":"Li\u00e8ge",
    "wof:name":"Emile Froidbise",
    "wof:placetype":"venue"
},
  "geometry": {"coordinates":[5.6118121147,50.6667098999],"type":"Point"}
}