{
  "type": "Feature",
  "properties": {
    "iso:country":"BE",
    "sg:address":"Oblatenstraat 21",
    "sg:city":"Waregem",
    "sg:orig_category":"Kapsalons",
    "sg:phone":"+32 56 60 43 57",
    "sg:postcode":"8790",
    "sg:province":"West-Vlaanderen",
    "wof:name":"Coiffure Betty",
    "wof:placetype":"venue"
},
  "geometry": {"coordinates":[3.3994250298,50.8635292053],"type":"Point"}
}