{
  "type": "Feature",
  "properties": {
    "addr:full":"Rue Miserque 7 Ham-sur-heure-nalinnes Hainaut 6120",
    "addr:housenumber":"7",
    "addr:postcode":"6120",
    "addr:street":"Rue Miserque;Hainaut",
    "iso:country":"BE",
    "sg:address":"Rue Miserque 7",
    "sg:city":"Ham-sur-heure-nalinnes",
    "sg:orig_category":"Slagers",
    "sg:phone":"+32 71 21 81 19",
    "sg:postcode":"6120",
    "sg:province":"Hainaut",
    "wof:name":"Dominique Bequet",
    "wof:placetype":"venue"
},
  "geometry": {"coordinates":[4.3872900009,50.3219146729],"type":"Point"}
}