{
  "type": "Feature",
  "properties": {
    "iso:country":"BE",
    "sg:address":"Turnhoutseweg 4",
    "sg:city":"Geel",
    "sg:classifiers":[
        {
            "category":"Professional",
            "subcategory":"Testing Lab",
            "type":"Services"
        }
    ],
    "sg:phone":"+32 14 85 28 43",
    "sg:postcode":"2440",
    "sg:province":"Antwerpen",
    "sg:tags":[
        "chemist"
    ],
    "wof:name":"Vloemans P",
    "wof:placetype":"venue"
},
  "geometry": {"coordinates":[4.9807801247,51.203704834],"type":"Point"}
}