{
  "type": "Feature",
  "properties": {
    "iso:country":"BE",
    "sg:address":"Ganzendries 7b1",
    "sg:city":"Lubbeek",
    "sg:orig_category":"M\u00e9decins and sp\u00e9cialistes",
    "sg:phone":"+32 16 46 28 57",
    "sg:postcode":"3212",
    "sg:province":"Vlaams-Brabant",
    "wof:name":"Willy Poppe",
    "wof:placetype":"venue"
},
  "geometry": {"coordinates":[4.7956628799,50.8717765808],"type":"Point"}
}