{
  "type": "Feature",
  "properties": {
    "iso:country":"BE",
    "sg:address":"Assesteenweg 9e",
    "sg:city":"Asse",
    "sg:orig_category":"Travaux d\u00b4installation divers",
    "sg:phone":"+32 2 452 27 00",
    "sg:postcode":"1730",
    "sg:province":"Vlaams-Brabant",
    "wof:name":"Labyrint Studiegroep",
    "wof:placetype":"venue"
},
  "geometry": {"coordinates":[4.1594591141,50.9177627563],"type":"Point"}
}