{
  "type": "Feature",
  "properties": {
    "iso:country":"BE",
    "sg:address":"Rue Joseph Ii 21",
    "sg:city":"Brussel/bruxelles",
    "sg:orig_category":"Pharmaciens",
    "sg:phone":"+32 2 230 93 55",
    "sg:postcode":"1000",
    "sg:province":"Bruxelles-Capitale",
    "wof:name":"Jose Mathet",
    "wof:placetype":"venue"
},
  "geometry": {"coordinates":[4.3708720207,50.8459320068],"type":"Point"}
}