{
  "type": "Feature",
  "properties": {
    "iso:country":"BE",
    "sg:address":"Gandastraat 17",
    "sg:city":"Gent",
    "sg:classifiers":[
        {
            "category":"Professional",
            "subcategory":"Accounting & Tax Preparation",
            "type":"Services"
        }
    ],
    "sg:phone":"+32 9 225 87 34",
    "sg:postcode":"9000",
    "sg:province":"Oost-Vlaanderen",
    "sg:tags":[
        "bookkeeper"
    ],
    "wof:name":"Web Verenigde Vleeshouwer",
    "wof:placetype":"venue"
},
  "geometry": {"coordinates":[3.737183094,51.0537414551],"type":"Point"}
}