{
  "type": "Feature",
  "properties": {
    "addr:full":"Lindendreef 12 Veurne West-Vlaanderen 8630",
    "addr:housenumber":"12",
    "addr:postcode":"8630",
    "addr:street":"Lindendreef",
    "iso:country":"BE",
    "sg:address":"Lindendreef 12",
    "sg:city":"Veurne",
    "sg:orig_category":"Rusthuizen and serviceflats",
    "sg:phone":"+32 58 31 15 73",
    "sg:postcode":"8630",
    "sg:province":"West-Vlaanderen",
    "wof:name":"Rusthuis Ter Linden",
    "wof:placetype":"venue"
},
  "geometry": {"coordinates":[2.6646399498,51.0701675415],"type":"Point"}
}