{
  "type": "Feature",
  "properties": {
    "addr:full":"Avenue Henri Strauven 16 Auderghem (bruxelles) Bruxelles-Capitale 1160",
    "addr:housenumber":"16",
    "addr:postcode":"1160",
    "addr:street":"Avenue Henri Strauven",
    "iso:country":"BE",
    "sg:address":"Avenue Henri Strauven 16",
    "sg:city":"Auderghem (bruxelles)",
    "sg:orig_category":"Immobili\u00ebnkantoren",
    "sg:phone":"+32 2 672 65 63",
    "sg:postcode":"1160",
    "sg:province":"Bruxelles-Capitale",
    "wof:name":"Acces Development",
    "wof:placetype":"venue"
},
  "geometry": {"coordinates":[4.4162712097,50.8179244995],"type":"Point"}
}