{
  "type": "Feature",
  "properties": {
    "iso:country":"BE",
    "sg:address":"Bronstraat 48",
    "sg:city":"Oudenaarde",
    "sg:classifiers":[
        {
            "category":"Arena",
            "subcategory":"Sports Club",
            "type":"Entertainment"
        }
    ],
    "sg:phone":"+32 55 45 52 17",
    "sg:postcode":"9700",
    "sg:province":"Oost-Vlaanderen",
    "sg:tags":[
        "de"
    ],
    "wof:name":"De Verdwaalde Duif",
    "wof:placetype":"venue"
},
  "geometry": {"coordinates":[3.6610190868,50.8532409668],"type":"Point"}
}