{
  "type": "Feature",
  "properties": {
    "iso:country":"BE",
    "sg:address":"Distellaan 29",
    "sg:city":"Middelkerke",
    "sg:orig_category":"Boucheries",
    "sg:phone":"+32 59 30 00 50",
    "sg:postcode":"8434",
    "sg:province":"West-Vlaanderen",
    "wof:name":"W. Degandt",
    "wof:placetype":"venue"
},
  "geometry": {"coordinates":[2.7569050789,51.1488685608],"type":"Point"}
}