{
  "type": "Feature",
  "properties": {
    "addr:full":"Avenue Albert-ier 12 Bastogne Luxembourg 6600",
    "addr:housenumber":"12",
    "addr:postcode":"6600",
    "addr:street":"Avenue Albert-Ier",
    "iso:country":"BE",
    "sg:address":"Avenue Albert-ier 12",
    "sg:city":"Bastogne",
    "sg:orig_category":"Traitements param\u00e9dicaux",
    "sg:phone":"+32 61 21 66 13",
    "sg:postcode":"6600",
    "sg:province":"Luxembourg",
    "wof:name":"V. Robin",
    "wof:placetype":"venue"
},
  "geometry": {"coordinates":[5.7154397964,49.9988517761],"type":"Point"}
}