{
  "type": "Feature",
  "properties": {
    "iso:country":"BE",
    "sg:address":"Rue Saint-martin 43",
    "sg:city":"Tournai",
    "sg:orig_category":"Instituts de beaut\u00e9",
    "sg:phone":"+32 69 21 29 36",
    "sg:postcode":"7500",
    "sg:province":"Hainaut",
    "wof:name":"Institut Frimousse",
    "wof:placetype":"venue"
},
  "geometry": {"coordinates":[3.3867530823,50.6046600342],"type":"Point"}
}