{
  "type": "Feature",
  "properties": {
    "iso:country":"BE",
    "sg:address":"Rue Fontaine 16",
    "sg:city":"Grez-doiceau",
    "sg:classifiers":[
        {
            "category":"Professional",
            "subcategory":"Computer Services",
            "type":"Services"
        }
    ],
    "sg:phone":"+32 10 84 50 33",
    "sg:postcode":"1390",
    "sg:province":"Brabant Wallon",
    "sg:tags":[
        "-",
        "processing",
        "data",
        "software"
    ],
    "wof:name":"Actis Systems",
    "wof:placetype":"venue"
},
  "geometry": {"coordinates":[4.6946268082,50.7364044189],"type":"Point"}
}