{
  "type": "Feature",
  "properties": {
    "addr:full":"Krokuslaan 81 Kasterlee Antwerpen 2460",
    "addr:housenumber":"81",
    "addr:postcode":"2460",
    "addr:street":"Krokuslaan",
    "iso:country":"BE",
    "sg:address":"Krokuslaan 81",
    "sg:city":"Kasterlee",
    "sg:classifiers":[
        {
            "category":"Arena",
            "subcategory":"Sports Club",
            "type":"Entertainment"
        }
    ],
    "sg:phone":"+32 14 55 39 31",
    "sg:postcode":"2460",
    "sg:province":"Antwerpen",
    "sg:tags":[
        "terrain",
        "hors",
        "de",
        "installation",
        "sportifs"
    ],
    "wof:name":"K. Kem. Vr. Sch. Herent",
    "wof:placetype":"venue"
},
  "geometry": {"coordinates":[4.9671049118,51.2406616211],"type":"Point"}
}