{
  "type": "Feature",
  "properties": {
    "addr:full":"Kerkstraat 62 Zulte Oost-Vlaanderen 9870",
    "addr:housenumber":"62",
    "addr:postcode":"9870",
    "addr:street":"Kerkstraat",
    "iso:country":"BE",
    "sg:address":"Kerkstraat 62",
    "sg:city":"Zulte",
    "sg:orig_category":"Musea and historische gebouwen",
    "sg:phone":"+32 9 388 57 77",
    "sg:postcode":"9870",
    "sg:province":"Oost-Vlaanderen",
    "wof:name":"Kantmuseum & Belgisch Circusarchief",
    "wof:placetype":"venue"
},
  "geometry": {"coordinates":[3.4568970203,50.9403343201],"type":"Point"}
}