{
  "type": "Feature",
  "properties": {
    "addr:full":"Ch De L'hoste 101 Wavre Brabant Wallon 1300",
    "addr:housenumber":"101;1300",
    "addr:street":"Ch De L'Hoste",
    "iso:country":"BE",
    "sg:address":"Ch De L'hoste 101",
    "sg:city":"Wavre",
    "sg:classifiers":[
        {
            "category":"Farming",
            "subcategory":"Farm & Veterinary Services",
            "type":"Manufacturing & Wholesale Goods"
        }
    ],
    "sg:phone":"+32 10 24 22 84",
    "sg:postcode":"1300",
    "sg:province":"Brabant Wallon",
    "sg:tags":[
        "advice",
        "agriculture",
        "livestock",
        "business"
    ],
    "wof:name":"De Bry Bernard M.",
    "wof:placetype":"venue"
},
  "geometry": {"coordinates":[4.620511055,50.7266731262],"type":"Point"}
}