{
  "type": "Feature",
  "properties": {
    "iso:country":"BE",
    "sg:address":"Rue Sous La Vigne 21ba",
    "sg:city":"Bassenge",
    "sg:classifiers":[
        {
            "category":"Restaurant",
            "type":"Food & Drink"
        }
    ],
    "sg:phone":"+32 4 286 27 58",
    "sg:postcode":"4690",
    "sg:province":"Li\u00e8ge",
    "wof:name":"Taverne Les Vignes",
    "wof:placetype":"venue"
},
  "geometry": {"coordinates":[5.6099390984,50.7597007751],"type":"Point"}
}