{
  "type": "Feature",
  "properties": {
    "iso:country":"BE",
    "sg:address":"Noordstraat 156",
    "sg:city":"Maldegem",
    "sg:orig_category":"HERSTELLING ELEKTRISCHE HUISHOUDAPPARATEN Herstelling aan huis van elektrische huishoudapparaten Hui",
    "sg:phone":"+32 50 71 85 03",
    "sg:postcode":"9990",
    "sg:province":"Oost-Vlaanderen",
    "wof:name":"Huis Derijcke & Zn",
    "wof:placetype":"venue"
},
  "geometry": {"coordinates":[3.4467489719,51.2154579163],"type":"Point"}
}