{
  "type": "Feature",
  "properties": {
    "addr:full":"Rue Des Combattants 6 Virton Luxembourg 6760",
    "addr:housenumber":"6",
    "addr:postcode":"6760",
    "addr:street":"Rue Des Combattants",
    "iso:country":"BE",
    "sg:address":"Rue Des Combattants 6",
    "sg:city":"Virton",
    "sg:classifiers":[
        {
            "category":"Home & Garden",
            "subcategory":"Home Furnishings",
            "type":"Retail Goods"
        }
    ],
    "sg:phone":"+32 63 57 61 29",
    "sg:postcode":"6760",
    "sg:province":"Luxembourg",
    "sg:tags":[
        "interior",
        "decoration"
    ],
    "wof:name":"Sebillot Architecture",
    "wof:placetype":"venue"
},
  "geometry": {"coordinates":[5.5318250656,49.5689582825],"type":"Point"}
}