{
  "type": "Feature",
  "properties": {
    "iso:country":"BE",
    "sg:address":"Avenue De Villegas 38",
    "sg:city":"Ganshoren/ganshoren",
    "sg:orig_category":"M\u00e9decins and sp\u00e9cialistes",
    "sg:phone":"+32 2 426 47 11",
    "sg:postcode":"1083",
    "sg:province":"Bruxelles-Capitale",
    "wof:name":"Michel Brys",
    "wof:placetype":"venue"
},
  "geometry": {"coordinates":[4.3088741302,50.8709411621],"type":"Point"}
}