{
  "type": "Feature",
  "properties": {
    "addr:full":"Ter Heide 25 Herenthout Antwerpen 2270",
    "addr:housenumber":"25",
    "addr:postcode":"2270",
    "addr:street":"Ter Heide",
    "iso:country":"BE",
    "sg:address":"Ter Heide 25",
    "sg:city":"Herenthout",
    "sg:orig_category":"Gespecialiseerde residenti\u00eble bouw",
    "sg:phone":"+32 14 50 07 99",
    "sg:postcode":"2270",
    "sg:province":"Antwerpen",
    "wof:name":"Jozef Canters",
    "wof:placetype":"venue"
},
  "geometry": {"coordinates":[4.7483639717,51.1358909607],"type":"Point"}
}