{
  "type": "Feature",
  "properties": {
    "iso:country":"BE",
    "sg:address":"Avenue Bel Air 12",
    "sg:city":"Bruxelles (uccle)",
    "sg:classifiers":[
        {
            "category":"Government",
            "subcategory":"Embassy",
            "type":"Public Place"
        }
    ],
    "sg:phone":"+32 2 346 49 35",
    "sg:postcode":"1180",
    "sg:province":"Bruxelles-Capitale",
    "sg:tags":[
        "consulate"
    ],
    "wof:name":"R\u00e9publique Dominicaine Office",
    "wof:placetype":"venue"
},
  "geometry": {"coordinates":[4.3670368195,50.8132247925],"type":"Point"}
}