{
  "type": "Feature",
  "properties": {
    "addr:full":"Rue Victor Lef\u00e8vre 58 Bruxelles (schaerbeek) Bruxelles-Capitale 1030",
    "addr:housenumber":"58",
    "addr:postcode":"1030",
    "addr:street":"Rue Victor Lefe\u0300Vre",
    "iso:country":"BE",
    "sg:address":"Rue Victor Lef\u00e8vre 58",
    "sg:city":"Bruxelles (schaerbeek)",
    "sg:classifiers":[
        {
            "category":"Building & Trades",
            "subcategory":"Construction",
            "type":"Services"
        }
    ],
    "sg:phone":"+32 2 732 00 92",
    "sg:postcode":"1030",
    "sg:province":"Bruxelles-Capitale",
    "sg:tags":[
        "carpenter"
    ],
    "wof:name":"Heynderickx S",
    "wof:placetype":"venue"
},
  "geometry": {"coordinates":[4.3978381157,50.8448638916],"type":"Point"}
}