{
  "type": "Feature",
  "properties": {
    "addr:full":"Sint-katelijneplein 5 Brussel/bruxelles Bruxelles-Capitale 1000",
    "addr:housenumber":"5",
    "addr:postcode":"1000",
    "addr:street":"Sint-Katelijneplein;/",
    "iso:country":"BE",
    "sg:address":"Sint-katelijneplein 5",
    "sg:city":"Brussel/bruxelles",
    "sg:classifiers":[
        {
            "category":"Restaurant",
            "type":"Food & Drink"
        }
    ],
    "sg:phone":"+32 2 513 19 92",
    "sg:postcode":"1000",
    "sg:province":"Bruxelles-Capitale",
    "wof:name":"Le Jardin De Catherine",
    "wof:placetype":"venue"
},
  "geometry": {"coordinates":[4.3474798203,50.8508110046],"type":"Point"}
}