{
  "type": "Feature",
  "properties": {
    "addr:full":"Galerie De L' Opera 3 Li\u00c8ge (grand) Li\u00e8ge 4000",
    "addr:housenumber":"3",
    "addr:postcode":"4000",
    "addr:street":"Galerie De L ' Opera",
    "iso:country":"BE",
    "sg:address":"Galerie De L' Opera 3",
    "sg:city":"Li\u00c8ge (grand)",
    "sg:orig_category":"Instituts de beaut\u00e9",
    "sg:postcode":"4000",
    "sg:province":"Li\u00e8ge",
    "wof:name":"Imagine'nails",
    "wof:placetype":"venue"
},
  "geometry": {"coordinates":[5.5386519432,50.656036377],"type":"Point"}
}