{
  "type": "Feature",
  "properties": {
    "iso:country":"BE",
    "sg:address":"Gaver 14",
    "sg:city":"Sint-martens-latem",
    "sg:classifiers":[
        {
            "category":"Health Services",
            "subcategory":"Health Practitioner",
            "type":"Services"
        }
    ],
    "sg:phone":"+32 9 281 00 36",
    "sg:postcode":"9830",
    "sg:province":"Oost-Vlaanderen",
    "sg:tags":[
        "osteopath"
    ],
    "wof:name":"Van Hecke J",
    "wof:placetype":"venue"
},
  "geometry": {"coordinates":[3.645334959,51.0152435303],"type":"Point"}
}