{
  "type": "Feature",
  "properties": {
    "addr:full":"Rue Albert 48 Tournai Hainaut 7540",
    "addr:housenumber":"48",
    "addr:postcode":"7540",
    "addr:street":"Rue Albert",
    "iso:country":"BE",
    "sg:address":"Rue Albert 48",
    "sg:city":"Tournai",
    "sg:orig_category":"Slagers",
    "sg:phone":"+32 69 22 52 52",
    "sg:postcode":"7540",
    "sg:province":"Hainaut",
    "wof:name":"Bouch.fran\u00c7ois J.m.& Fils",
    "wof:placetype":"venue"
},
  "geometry": {"coordinates":[3.3909020424,50.6236381531],"type":"Point"}
}