{
  "type": "Feature",
  "properties": {
    "iso:country":"BE",
    "sg:address":"Tussenbruggen 3",
    "sg:city":"Oudenaarde",
    "sg:orig_category":"Catering and organisation de f\u00eates. Alimentation sp\u00e9cialis\u00e9e",
    "sg:phone":"+32 55 31 93 96",
    "sg:postcode":"9700",
    "sg:province":"Oost-Vlaanderen",
    "wof:name":"Leconte",
    "wof:placetype":"venue"
},
  "geometry": {"coordinates":[3.6079161167,50.8428649902],"type":"Point"}
}