{
  "type": "Feature",
  "properties": {
    "iso:country":"BE",
    "sg:address":"Industrieterrein 1551",
    "sg:city":"Opglabbeek",
    "sg:orig_category":"Landbouwmachines Gh",
    "sg:phone":"+32 89 85 32 53",
    "sg:postcode":"3660",
    "sg:province":"Limburg",
    "wof:name":"Marc Brouns",
    "wof:placetype":"venue"
},
  "geometry": {"coordinates":[5.5838198662,51.0429496765],"type":"Point"}
}