{
  "type": "Feature",
  "properties": {
    "addr:full":"Petites-rues 11 Florenville Luxembourg 6820",
    "addr:housenumber":"11",
    "addr:postcode":"6820",
    "addr:street":"Petites-Rues",
    "iso:country":"BE",
    "sg:address":"Petites-rues 11",
    "sg:city":"Florenville",
    "sg:classifiers":[
        {
            "category":"Restaurant",
            "type":"Food & Drink"
        }
    ],
    "sg:phone":"+32 61 31 28 53",
    "sg:postcode":"6820",
    "sg:province":"Luxembourg",
    "wof:name":"Pic-nic",
    "wof:placetype":"venue"
},
  "geometry": {"coordinates":[5.3092608452,49.6987533569],"type":"Point"}
}