{
  "type": "Feature",
  "properties": {
    "iso:country":"BE",
    "sg:address":"Rue De Goz\u00e9e 430",
    "sg:city":"Montigny-le-tilleul",
    "sg:classifiers":[
        {
            "category":"Insurance",
            "subcategory":"Insurance Agent",
            "type":"Services"
        }
    ],
    "sg:phone":"+32 71 51 54 96",
    "sg:postcode":"6110",
    "sg:province":"Hainaut",
    "sg:tags":[
        "broker"
    ],
    "wof:name":"Lavergne L",
    "wof:placetype":"venue"
},
  "geometry": {"coordinates":[4.3697681427,50.3767051697],"type":"Point"}
}