{
  "type": "Feature",
  "properties": {
    "iso:country":"BE",
    "sg:address":"Chauss\u00c9e De Charleroi 58",
    "sg:city":"Jemeppe-sur-sambre",
    "sg:orig_category":"Entretien and r\u00e9parations de voitures",
    "sg:phone":"+32 71 78 51 77",
    "sg:postcode":"5190",
    "sg:province":"Namur",
    "wof:name":"Garage Leclercq",
    "wof:placetype":"venue"
},
  "geometry": {"coordinates":[4.650616169,50.4578437805],"type":"Point"}
}