{
  "type": "Feature",
  "properties": {
    "iso:country":"BE",
    "sg:address":"Chauss\u00c9e De Redemont 21",
    "sg:city":"La Louviere",
    "sg:orig_category":"Bouwmaterialen Gh Hout and afgeleiden Gh IJzerwaren, bouw- and verfmaterialen",
    "sg:phone":"+32 64 23 84 44",
    "sg:postcode":"7100",
    "sg:province":"Hainaut",
    "wof:name":"Brico",
    "wof:placetype":"venue"
},
  "geometry": {"coordinates":[4.2083249092,50.4672813416],"type":"Point"}
}