{
  "type": "Feature",
  "properties": {
    "iso:country":"BE",
    "sg:address":"Waregemstraat 265",
    "sg:city":"Deerlijk",
    "sg:classifiers":[
        {
            "category":"Personal",
            "subcategory":"Beauty Salon",
            "type":"Services"
        }
    ],
    "sg:phone":"+32 56 71 13 37",
    "sg:postcode":"8540",
    "sg:province":"West-Vlaanderen",
    "sg:tags":[
        "lady",
        "-",
        "hairdressing"
    ],
    "wof:name":"Christiaens M",
    "wof:placetype":"venue"
},
  "geometry": {"coordinates":[3.3695759773,50.8568305969],"type":"Point"}
}