{
  "type": "Feature",
  "properties": {
    "addr:full":"Markt 28 Lokeren Oost-Vlaanderen 9160",
    "addr:housenumber":"28",
    "addr:postcode":"9160",
    "addr:street":"Markt",
    "iso:country":"BE",
    "sg:address":"Markt 28",
    "sg:city":"Lokeren",
    "sg:orig_category":"Electrom\u00e9nager, t\u00e9l\u00e9visions and radios",
    "sg:phone":"+32 9 348 45 17",
    "sg:postcode":"9160",
    "sg:province":"Oost-Vlaanderen",
    "wof:name":"Verschelden",
    "wof:placetype":"venue"
},
  "geometry": {"coordinates":[3.9901111126,51.1046295166],"type":"Point"}
}