{
  "type": "Feature",
  "properties": {
    "iso:country":"BE",
    "sg:address":"Rue Adonis Descamps 104",
    "sg:city":"Mons (havr\u00e9)",
    "sg:classifiers":[
        {
            "category":"Health Services",
            "subcategory":"Doctor",
            "type":"Services"
        }
    ],
    "sg:phone":"+32 65 84 12 94",
    "sg:postcode":"7021",
    "sg:province":"Hainaut",
    "sg:tags":[
        "medicinephysicians",
        "surgeon"
    ],
    "wof:name":"Marcovitch O",
    "wof:placetype":"venue"
},
  "geometry": {"coordinates":[4.0456829071,50.4640655518],"type":"Point"}
}