{
  "type": "Feature",
  "properties": {
    "iso:country":"BE",
    "sg:address":"Rue De Brabant 63",
    "sg:city":"Schaarbeek/schaerbeek",
    "sg:orig_category":"Boucheries",
    "sg:phone":"+32 2 218 57 15",
    "sg:postcode":"1030",
    "sg:province":"Bruxelles-Capitale",
    "wof:name":"Ahmed Khafi",
    "wof:placetype":"venue"
},
  "geometry": {"coordinates":[4.3628211021,50.860042572],"type":"Point"}
}