{
  "type": "Feature",
  "properties": {
    "iso:country":"BE",
    "sg:address":"Oudebaan 140",
    "sg:city":"Maasmechelen",
    "sg:classifiers":[
        {
            "category":"Restaurant",
            "type":"Food & Drink"
        }
    ],
    "sg:phone":"+32 89 76 52 57",
    "sg:postcode":"3630",
    "sg:province":"Limburg",
    "wof:name":"Da Vinci",
    "wof:placetype":"venue"
},
  "geometry": {"coordinates":[5.6925411224,50.98387146],"type":"Point"}
}