{
  "type": "Feature",
  "properties": {
    "addr:full":"Nieuwstraat 9 Galmaarden Vlaams-Brabant 1570",
    "addr:housenumber":"9",
    "addr:postcode":"1570",
    "addr:street":"Nieuwstraat",
    "iso:country":"BE",
    "sg:address":"Nieuwstraat 9",
    "sg:city":"Galmaarden",
    "sg:classifiers":[
        {
            "category":"Wholesale",
            "subcategory":"Farm Supplies",
            "type":"Manufacturing & Wholesale Goods"
        }
    ],
    "sg:phone":"+32 54 58 80 20",
    "sg:postcode":"1570",
    "sg:province":"Vlaams-Brabant",
    "sg:tags":[
        "machine",
        "agricoles",
        "mat\u00e9riel",
        "gr"
    ],
    "wof:name":"Petrus Mignon",
    "wof:placetype":"venue"
},
  "geometry": {"coordinates":[3.9705579281,50.7516098022],"type":"Point"}
}