{
  "type": "Feature",
  "properties": {
    "addr:full":"Nieuwstraat 75 Westerlo Antwerpen 2260",
    "addr:housenumber":"75",
    "addr:postcode":"2260",
    "addr:street":"Nieuwstraat",
    "iso:country":"BE",
    "sg:address":"Nieuwstraat 75",
    "sg:city":"Westerlo",
    "sg:classifiers":[
        {
            "category":"Cafe",
            "type":"Food & Drink"
        }
    ],
    "sg:phone":"+32 14 54 40 94",
    "sg:postcode":"2260",
    "sg:province":"Antwerpen",
    "sg:tags":[
        "caf\u00e9s"
    ],
    "wof:name":"Jan Van Der Auwera",
    "wof:placetype":"venue"
},
  "geometry": {"coordinates":[4.9118671417,51.0857887268],"type":"Point"}
}