{
  "type": "Feature",
  "properties": {
    "iso:country":"BE",
    "sg:address":"Driesstraat 6",
    "sg:city":"Zwevegem",
    "sg:orig_category":"Instituts pour enfants en difficult\u00e9. Orphelinats",
    "sg:phone":"+32 56 45 51 52",
    "sg:postcode":"8554",
    "sg:province":"West-Vlaanderen",
    "wof:name":"Huize Ten Dries",
    "wof:placetype":"venue"
},
  "geometry": {"coordinates":[3.3661699295,50.754825592],"type":"Point"}
}