{
  "type": "Feature",
  "properties": {
    "addr:full":"Rue Cl\u00e9ment Delpierre 5 La Hulpe Brabant Wallon 1310",
    "addr:housenumber":"5",
    "addr:postcode":"1310",
    "addr:street":"Rue Cle\u0301Ment Delpierre",
    "iso:country":"BE",
    "sg:address":"Rue Cl\u00e9ment Delpierre 5",
    "sg:city":"La Hulpe",
    "sg:classifiers":[
        {
            "category":"Health Services",
            "subcategory":"Health Practitioner",
            "type":"Services"
        }
    ],
    "sg:phone":"+32 2 653 22 57",
    "sg:postcode":"1310",
    "sg:province":"Brabant Wallon",
    "sg:tags":[
        "physiotherapist"
    ],
    "wof:name":"Fallon Jacqueline",
    "wof:placetype":"venue"
},
  "geometry": {"coordinates":[4.4496450424,50.7235183716],"type":"Point"}
}