{
  "type": "Feature",
  "properties": {
    "addr:full":"Geraardsbergsesteenweg 75b Melle Oost-Vlaanderen 9090",
    "addr:housenumber":"75b",
    "addr:postcode":"9090",
    "addr:street":"Geraardsbergsesteenweg",
    "iso:country":"BE",
    "sg:address":"Geraardsbergsesteenweg 75b",
    "sg:city":"Melle",
    "sg:classifiers":[
        {
            "category":"Freight",
            "type":"Transportation"
        }
    ],
    "sg:phone":"+32 9 252 52 20",
    "sg:postcode":"9090",
    "sg:province":"Oost-Vlaanderen",
    "sg:tags":[
        "-",
        "transport"
    ],
    "wof:name":"Eeckhout Lucien Bvba",
    "wof:placetype":"venue"
},
  "geometry": {"coordinates":[3.7993750572,50.9910507202],"type":"Point"}
}