{
  "type": "Feature",
  "properties": {
    "addr:full":"Kunstenaarsstraat 25 Brussel/bruxelles Bruxelles-Capitale 1020",
    "addr:housenumber":"25",
    "addr:postcode":"1020",
    "addr:street":"Kunstenaarsstraat;/",
    "iso:country":"BE",
    "sg:address":"Kunstenaarsstraat 25",
    "sg:city":"Brussel/bruxelles",
    "sg:orig_category":"Artiesten and kunstenaars",
    "sg:phone":"+32 2 478 72 25",
    "sg:postcode":"1020",
    "sg:province":"Bruxelles-Capitale",
    "wof:name":"Publi-films-presse-relat.",
    "wof:placetype":"venue"
},
  "geometry": {"coordinates":[4.3481059074,50.8801383972],"type":"Point"}
}