{
  "type": "Feature",
  "properties": {
    "addr:full":"Chauss\u00e9e De Bruxelles 90 Mons (maisi\u00e8res) Hainaut 7020",
    "addr:housenumber":"90",
    "addr:postcode":"7020",
    "addr:street":"Chausse\u0301E De Bruxelles",
    "iso:country":"BE",
    "sg:address":"Chauss\u00e9e De Bruxelles 90",
    "sg:city":"Mons (maisi\u00e8res)",
    "sg:classifiers":[
        {
            "category":"Shopping",
            "subcategory":"Books",
            "type":"Retail Goods"
        }
    ],
    "sg:phone":"+32 65 72 83 82",
    "sg:postcode":"7020",
    "sg:province":"Hainaut",
    "sg:tags":[
        "bookseller"
    ],
    "wof:name":"Merveille",
    "wof:placetype":"venue"
},
  "geometry": {"coordinates":[3.9576330185,50.4674377441],"type":"Point"}
}