{
  "type": "Feature",
  "properties": {
    "iso:country":"BE",
    "sg:address":"Rue De Clavier 1-3",
    "sg:city":"Clavier (les Avins)",
    "sg:classifiers":[
        {
            "category":"Professional",
            "type":"Services"
        }
    ],
    "sg:phone":"+32 85 41 18 05",
    "sg:postcode":"4560",
    "sg:province":"Li\u00e8ge",
    "sg:tags":[
        "surveyor",
        "-",
        "valuer"
    ],
    "wof:name":"Globe Experts Sa",
    "wof:placetype":"venue"
},
  "geometry": {"coordinates":[5.3172001839,50.4228286743],"type":"Point"}
}