{
  "type": "Feature",
  "properties": {
    "iso:country":"BE",
    "sg:address":"Nieuwstraat 68",
    "sg:city":"Diepenbeek",
    "sg:orig_category":"Artsen and specialisten",
    "sg:phone":"+32 11 35 01 00",
    "sg:postcode":"3590",
    "sg:province":"Limburg",
    "wof:name":"M. Eyssen",
    "wof:placetype":"venue"
},
  "geometry": {"coordinates":[5.4413900375,50.9189987183],"type":"Point"}
}