{
  "type": "Feature",
  "properties": {
    "addr:full":"Rue Du Centi\u00e8me Anniversaire 36 Saint-ghislain (sirault) Hainaut 7332",
    "addr:housenumber":"36",
    "addr:postcode":"7332",
    "addr:street":"Rue Du Centie\u0300Me Anniversaire",
    "iso:country":"BE",
    "sg:address":"Rue Du Centi\u00e8me Anniversaire 36",
    "sg:city":"Saint-ghislain (sirault)",
    "sg:classifiers":[
        {
            "category":"Health Services",
            "subcategory":"Medical Lab",
            "type":"Services"
        }
    ],
    "sg:phone":"+32 65 62 26 65",
    "sg:postcode":"7332",
    "sg:province":"Hainaut",
    "sg:tags":[
        "laboratory",
        "dental"
    ],
    "wof:name":"Crickx D",
    "wof:placetype":"venue"
},
  "geometry": {"coordinates":[3.786839962,50.5054969788],"type":"Point"}
}