{
  "type": "Feature",
  "properties": {
    "iso:country":"BE",
    "sg:address":"Kleine Laan 12",
    "sg:city":"Sint-niklaas",
    "sg:classifiers":[
        {
            "category":"Autos & Motor Vehicles",
            "subcategory":"Fuel & Gas Station",
            "type":"Retail Goods"
        }
    ],
    "sg:phone":"+32 3 776 22 99",
    "sg:postcode":"9100",
    "sg:province":"Oost-Vlaanderen",
    "sg:tags":[
        "stations-service",
        "carburants"
    ],
    "wof:name":"Etienne Tollenaere",
    "wof:placetype":"venue"
},
  "geometry": {"coordinates":[4.1401348114,51.1699714661],"type":"Point"}
}