{
  "type": "Feature",
  "properties": {
    "addr:full":"Haag 107 Hamont-achel Limburg 3930",
    "addr:housenumber":"107",
    "addr:postcode":"3930",
    "addr:street":"Haag",
    "iso:country":"BE",
    "sg:address":"Haag 107",
    "sg:city":"Hamont-achel",
    "sg:orig_category":"Maisons de vacances",
    "sg:phone":"+32 11 64 14 83",
    "sg:postcode":"3930",
    "sg:province":"Limburg",
    "wof:name":"Ons Neerhof",
    "wof:placetype":"venue"
},
  "geometry": {"coordinates":[5.4718141556,51.2425460815],"type":"Point"}
}