{
  "type": "Feature",
  "properties": {
    "addr:full":"Rue Albrecht Rodenbach 35 Wemmel Vlaams-Brabant 1780",
    "addr:housenumber":"35",
    "addr:postcode":"1780",
    "addr:street":"Rue Albrecht Rodenbach;Vlaams-Brabant",
    "iso:country":"BE",
    "sg:address":"Rue Albrecht Rodenbach 35",
    "sg:city":"Wemmel",
    "sg:classifiers":[
        {
            "category":"Health Services",
            "subcategory":"Health Practitioner",
            "type":"Services"
        }
    ],
    "sg:phone":"+32 2 460 18 45",
    "sg:postcode":"1780",
    "sg:province":"Vlaams-Brabant",
    "sg:tags":[
        "physiotherapist"
    ],
    "wof:name":"Wernimont Stephane",
    "wof:placetype":"venue"
},
  "geometry": {"coordinates":[4.2980480194,50.9071121216],"type":"Point"}
}