{
  "type": "Feature",
  "properties": {
    "iso:country":"BE",
    "sg:address":"Rue Neuve 3ba",
    "sg:city":"Burdinne",
    "sg:orig_category":"Elektrische installaties voor woningen",
    "sg:phone":"+32 85 71 12 63",
    "sg:postcode":"4210",
    "sg:province":"Li\u00e8ge",
    "wof:name":"Philippe Mahiat",
    "wof:placetype":"venue"
},
  "geometry": {"coordinates":[5.0654520988,50.5827178955],"type":"Point"}
}