{
  "type": "Feature",
  "properties": {
    "addr:full":"Valk 30 Sint-niklaas (belsele) Oost-Vlaanderen 9111",
    "addr:housenumber":"30",
    "addr:postcode":"9111",
    "addr:street":"Valk",
    "iso:country":"BE",
    "sg:address":"Valk 30",
    "sg:city":"Sint-niklaas (belsele)",
    "sg:classifiers":[
        {
            "category":"Mining & Drilling",
            "type":"Manufacturing & Wholesale Goods"
        }
    ],
    "sg:phone":"+32 3 766 58 23",
    "sg:postcode":"9111",
    "sg:province":"Oost-Vlaanderen",
    "sg:tags":[
        "concrete",
        "reinforced",
        "sawing"
    ],
    "wof:name":"Embo Betonboringen Nv",
    "wof:placetype":"venue"
},
  "geometry": {"coordinates":[4.1158618927,51.1581687927],"type":"Point"}
}