{
  "type": "Feature",
  "properties": {
    "iso:country":"BE",
    "sg:address":"Kerlemeers 1",
    "sg:city":"Affligem (essene)",
    "sg:classifiers":[
        {
            "category":"Shopping",
            "subcategory":"Antiques",
            "type":"Retail Goods"
        }
    ],
    "sg:phone":"+32 2 582 26 41",
    "sg:postcode":"1790",
    "sg:province":"Vlaams-Brabant",
    "wof:name":"Van Sompel J",
    "wof:placetype":"venue"
},
  "geometry": {"coordinates":[4.1452498436,50.8960113525],"type":"Point"}
}