{
  "type": "Feature",
  "properties": {
    "addr:full":"Rue Du Lombard 30 Brussel/bruxelles Bruxelles-Capitale 1000",
    "addr:housenumber":"30",
    "addr:postcode":"1000",
    "addr:street":"Rue Du Lombard;/",
    "iso:country":"BE",
    "sg:address":"Rue Du Lombard 30",
    "sg:city":"Brussel/bruxelles",
    "sg:classifiers":[
        {
            "category":"Manufacturing",
            "subcategory":"Textiles",
            "type":"Manufacturing & Wholesale Goods"
        }
    ],
    "sg:phone":"+32 2 511 90 79",
    "sg:postcode":"1000",
    "sg:province":"Bruxelles-Capitale",
    "wof:name":"Lace Gallery",
    "wof:placetype":"venue"
},
  "geometry": {"coordinates":[4.3509478569,50.8455543518],"type":"Point"}
}