{
  "type": "Feature",
  "properties": {
    "addr:full":"Oude Desselgemstraat 45 Waregem West-Vlaanderen 8790",
    "addr:housenumber":"45",
    "addr:postcode":"8790",
    "addr:street":"Oude Desselgemstraat",
    "iso:country":"BE",
    "sg:address":"Oude Desselgemstraat 45",
    "sg:city":"Waregem",
    "sg:classifiers":[
        {
            "category":"Bars & Pubs",
            "type":"Food & Drink"
        }
    ],
    "sg:phone":"+32 56 60 71 76",
    "sg:postcode":"8790",
    "sg:province":"West-Vlaanderen",
    "sg:tags":[
        "fab",
        "chaise",
        "si\u00e8ges"
    ],
    "wof:name":"Meubelen De Smet M. & W.",
    "wof:placetype":"venue"
},
  "geometry": {"coordinates":[3.407845974,50.8804283142],"type":"Point"}
}