{
  "type": "Feature",
  "properties": {
    "iso:country":"BE",
    "sg:address":"Rue Du Radoux 23",
    "sg:city":"Kasteelbrakel",
    "sg:orig_category":"Tuinen",
    "sg:phone":"+32 2 366 17 15",
    "sg:postcode":"1440",
    "sg:province":"Brabant Wallon",
    "wof:name":"Damoiseaux",
    "wof:placetype":"venue"
},
  "geometry": {"coordinates":[4.2786359787,50.685344696],"type":"Point"}
}