{
  "type": "Feature",
  "properties": {
    "iso:country":"BE",
    "sg:address":"Bergemeersenstraat 18",
    "sg:city":"Aalst",
    "sg:orig_category":"Meubelzaken, woning- and keukeninrichting",
    "sg:phone":"+32 53 70 02 93",
    "sg:postcode":"9300",
    "sg:province":"Oost-Vlaanderen",
    "wof:name":"Firma Beeckman",
    "wof:placetype":"venue"
},
  "geometry": {"coordinates":[4.0506310463,50.940990448],"type":"Point"}
}