{
  "type": "Feature",
  "properties": {
    "iso:country":"BE",
    "sg:address":"Avenue De La Ram\u00e9e 18",
    "sg:city":"Bruxelles (uccle)",
    "sg:classifiers":[
        {
            "category":"Insurance",
            "subcategory":"Insurance Agent",
            "type":"Services"
        }
    ],
    "sg:phone":"+32 2 347 48 99",
    "sg:postcode":"1180",
    "sg:province":"Bruxelles-Capitale",
    "sg:tags":[
        "broker"
    ],
    "wof:name":"Tolrip Sa",
    "wof:placetype":"venue"
},
  "geometry": {"coordinates":[4.3440752029,50.8057746887],"type":"Point"}
}