{
  "type": "Feature",
  "properties": {
    "addr:full":"Kerkstraat 86 Sint-gillis-waas Oost-Vlaanderen 9170",
    "addr:housenumber":"86",
    "addr:postcode":"9170",
    "addr:street":"Kerkstraat",
    "iso:country":"BE",
    "sg:address":"Kerkstraat 86",
    "sg:city":"Sint-gillis-waas",
    "sg:classifiers":[
        {
            "category":"Recreation",
            "type":"Entertainment"
        }
    ],
    "sg:phone":"+32 3 770 55 70",
    "sg:postcode":"9170",
    "sg:province":"Oost-Vlaanderen",
    "sg:tags":[
        "diver",
        "amusement"
    ],
    "wof:name":"De Luc",
    "wof:placetype":"venue"
},
  "geometry": {"coordinates":[4.1263380051,51.2183151245],"type":"Point"}
}