{
  "type": "Feature",
  "properties": {
    "addr:full":"Rondplein 11b1 Mol Antwerpen 2400",
    "addr:housenumber":"11b1",
    "addr:postcode":"2400",
    "addr:street":"Rondplein",
    "iso:country":"BE",
    "sg:address":"Rondplein 11b1",
    "sg:city":"Mol",
    "sg:orig_category":"Boissons. Tabac",
    "sg:phone":"+32 14 31 27 18",
    "sg:postcode":"2400",
    "sg:province":"Antwerpen",
    "wof:name":"Huis Hardies",
    "wof:placetype":"venue"
},
  "geometry": {"coordinates":[5.1165409088,51.1871643066],"type":"Point"}
}