{
  "type": "Feature",
  "properties": {
    "iso:country":"BE",
    "sg:address":"Avenue Des Immortelles 3",
    "sg:city":"Anderlecht/anderlecht",
    "sg:orig_category":"Services de Nettoyage and de D\u00e9sinfection",
    "sg:phone":"+32 2 410 33 22",
    "sg:postcode":"1070",
    "sg:province":"Bruxelles-Capitale",
    "wof:name":"Azur Clean",
    "wof:placetype":"venue"
},
  "geometry": {"coordinates":[4.2821879387,50.8167877197],"type":"Point"}
}