{
  "type": "Feature",
  "properties": {
    "addr:full":"Gijmelsesteenweg 337 Aarschot (langdorp) Vlaams-Brabant 3201",
    "addr:housenumber":"337",
    "addr:postcode":"3201",
    "addr:street":"Gijmelsesteenweg",
    "iso:country":"BE",
    "sg:address":"Gijmelsesteenweg 337",
    "sg:city":"Aarschot (langdorp)",
    "sg:classifiers":[
        {
            "category":"Personal",
            "subcategory":"Beauty Salon",
            "type":"Services"
        }
    ],
    "sg:phone":"+32 16 57 33 65",
    "sg:postcode":"3201",
    "sg:province":"Vlaams-Brabant",
    "wof:name":"Elegancia",
    "wof:placetype":"venue"
},
  "geometry": {"coordinates":[4.8602647781,51.0087051392],"type":"Point"}
}