{
  "type": "Feature",
  "properties": {
    "iso:country":"BE",
    "sg:address":"Moeskroenstraat 511",
    "sg:city":"Menen",
    "sg:orig_category":"Installatie van houten of kunststof schrijnwerk",
    "sg:phone":"+32 56 40 11 07",
    "sg:postcode":"8930",
    "sg:province":"West-Vlaanderen",
    "wof:name":"Leopold Demuynck",
    "wof:placetype":"venue"
},
  "geometry": {"coordinates":[3.1650071144,50.7818069458],"type":"Point"}
}