{
  "type": "Feature",
  "properties": {
    "addr:full":"Rue Ry D'ao\u00fbt 55 Yvoir (spontin) Namur 5530",
    "addr:housenumber":"55",
    "addr:postcode":"5530",
    "addr:street":"Rue Ry D'Aou \u0302T",
    "iso:country":"BE",
    "sg:address":"Rue Ry D'ao\u00fbt 55",
    "sg:city":"Yvoir (spontin)",
    "sg:classifiers":[
        {
            "category":"Insurance",
            "subcategory":"Insurance Agent",
            "type":"Services"
        }
    ],
    "sg:phone":"+32 83 69 91 61",
    "sg:postcode":"5530",
    "sg:province":"Namur",
    "sg:tags":[
        "broker"
    ],
    "wof:name":"Asc Sprl",
    "wof:placetype":"venue"
},
  "geometry": {"coordinates":[4.9861707687,50.3179244995],"type":"Point"}
}