{
  "type": "Feature",
  "properties": {
    "addr:full":"Brusselbaan 120b1 Affligem Vlaams-Brabant 1790",
    "addr:housenumber":"120b1",
    "addr:postcode":"1790",
    "addr:street":"Brusselbaan",
    "iso:country":"BE",
    "sg:address":"Brusselbaan 120b1",
    "sg:city":"Affligem",
    "sg:orig_category":"Evaluation and estimation de biens immobiliers. Architectes",
    "sg:phone":"+32 53 67 31 51",
    "sg:postcode":"1790",
    "sg:province":"Vlaams-Brabant",
    "wof:name":"Geert Beck",
    "wof:placetype":"venue"
},
  "geometry": {"coordinates":[4.106651783,50.9130249023],"type":"Point"}
}