{
  "type": "Feature",
  "properties": {
    "addr:full":"Appelmansstraat 5-9 Antwerpen Antwerpen 2018",
    "addr:housenumber":"5-9",
    "addr:postcode":"2018",
    "addr:street":"Appelmansstraat",
    "iso:country":"BE",
    "sg:address":"Appelmansstraat 5-9",
    "sg:city":"Antwerpen",
    "sg:classifiers":[
        {
            "category":"Tea Room",
            "subcategory":"None",
            "type":"Food & Drink"
        }
    ],
    "sg:phone":"+32 3 233 29 37",
    "sg:postcode":"2018",
    "sg:province":"Antwerpen",
    "wof:name":"Del Rey",
    "wof:placetype":"venue"
},
  "geometry": {"coordinates":[4.4177079201,51.217124939],"type":"Point"}
}