{
  "type": "Feature",
  "properties": {
    "iso:country":"BE",
    "sg:address":"Hoogstuk 20",
    "sg:city":"Brugge",
    "sg:classifiers":[
        {
            "category":"Bars & Pubs",
            "type":"Food & Drink"
        }
    ],
    "sg:phone":"+32 50 33 89 68",
    "sg:postcode":"8000",
    "sg:province":"West-Vlaanderen",
    "wof:name":"Munckenhuis",
    "wof:placetype":"venue"
},
  "geometry": {"coordinates":[3.236716032,51.2062530518],"type":"Point"}
}