{
  "type": "Feature",
  "properties": {
    "addr:full":"Square Des Nations Unies 2 Nivelles Brabant Wallon 1400",
    "addr:housenumber":"2",
    "addr:postcode":"1400",
    "addr:street":"Square Des Nations Unies",
    "iso:country":"BE",
    "sg:address":"Square Des Nations Unies 2",
    "sg:city":"Nivelles",
    "sg:classifiers":[
        {
            "category":"Professional",
            "subcategory":"Secretarial Services",
            "type":"Services"
        }
    ],
    "sg:phone":"+32 67 41 05 55",
    "sg:postcode":"1400",
    "sg:province":"Brabant Wallon",
    "sg:tags":[
        "-",
        "wordprocessing"
    ],
    "wof:name":"Com-assistance Sprl",
    "wof:placetype":"venue"
},
  "geometry": {"coordinates":[4.344771862,50.6015281677],"type":"Point"}
}