{
  "type": "Feature",
  "properties": {
    "addr:full":"Dries 21 Buggenhout Oost-Vlaanderen 9255",
    "addr:housenumber":"21",
    "addr:postcode":"9255",
    "addr:street":"Dries",
    "iso:country":"BE",
    "sg:address":"Dries 21",
    "sg:city":"Buggenhout",
    "sg:classifiers":[
        {
            "category":"Bars & Pubs",
            "type":"Food & Drink"
        }
    ],
    "sg:phone":"+32 52 33 27 86",
    "sg:postcode":"9255",
    "sg:province":"Oost-Vlaanderen",
    "wof:name":"Biekorf",
    "wof:placetype":"venue"
},
  "geometry": {"coordinates":[4.1679840088,51.0071716309],"type":"Point"}
}