{
  "type": "Feature",
  "properties": {
    "iso:country":"BE",
    "sg:address":"Haezeweidestraat 14",
    "sg:city":"Langemark-poelkapelle",
    "sg:orig_category":"Varkenskwekers",
    "sg:phone":"+32 57 48 83 28",
    "sg:postcode":"8920",
    "sg:province":"West-Vlaanderen",
    "wof:name":"Roger Vandenbussche",
    "wof:placetype":"venue"
},
  "geometry": {"coordinates":[2.9436900616,50.882598877],"type":"Point"}
}