{
  "type": "Feature",
  "properties": {
    "iso:country":"BE",
    "sg:address":"Rue De L'eglise 40ba",
    "sg:city":"Chaumont-gistoux",
    "sg:orig_category":"Jardinage",
    "sg:phone":"+32 10 65 91 19",
    "sg:postcode":"1325",
    "sg:province":"Brabant Wallon",
    "wof:name":"La Bardane",
    "wof:placetype":"venue"
},
  "geometry": {"coordinates":[4.7142491341,50.7195053101],"type":"Point"}
}