{
  "type": "Feature",
  "properties": {
    "addr:full":"Bokterstraat 5 Peer Limburg 3990",
    "addr:housenumber":"5",
    "addr:postcode":"3990",
    "addr:street":"Bokterstraat",
    "iso:country":"BE",
    "sg:address":"Bokterstraat 5",
    "sg:city":"Peer",
    "sg:classifiers":[
        {
            "category":"Professional",
            "subcategory":"Accounting & Tax Preparation",
            "type":"Services"
        }
    ],
    "sg:phone":"+32 11 63 10 37",
    "sg:postcode":"3990",
    "sg:province":"Limburg",
    "sg:tags":[
        "accountant"
    ],
    "wof:name":"Eddy Linsen",
    "wof:placetype":"venue"
},
  "geometry": {"coordinates":[5.4516749382,51.1345672607],"type":"Point"}
}