{
  "type": "Feature",
  "properties": {
    "addr:full":"Meerstraat 20a Oosterzele Oost-Vlaanderen 9860",
    "addr:housenumber":"20a",
    "addr:postcode":"9860",
    "addr:street":"Meerstraat;Oost-Vlaanderen",
    "iso:country":"BE",
    "sg:address":"Meerstraat 20a",
    "sg:city":"Oosterzele",
    "sg:classifiers":[
        {
            "category":"Building & Trades",
            "subcategory":"Landscaping Services",
            "type":"Services"
        }
    ],
    "sg:phone":"+32 9 362 97 09",
    "sg:postcode":"9860",
    "sg:province":"Oost-Vlaanderen",
    "sg:tags":[
        "gardening",
        "garden",
        "maintenance"
    ],
    "wof:name":"Etienne D'haene Bvba",
    "wof:placetype":"venue"
},
  "geometry": {"coordinates":[3.8068220615,50.9560012817],"type":"Point"}
}