{
  "type": "Feature",
  "properties": {
    "iso:country":"BE",
    "sg:address":"Gullegemsestraat 42",
    "sg:city":"Kortrijk",
    "sg:orig_category":"Agences de publicit\u00e9. Bureaux d'\u00e9tudes de march\u00e9",
    "sg:phone":"+32 56 36 50 50",
    "sg:postcode":"8501",
    "sg:province":"West-Vlaanderen",
    "wof:name":"Focus Advertising",
    "wof:placetype":"venue"
},
  "geometry": {"coordinates":[3.2271609306,50.8443565369],"type":"Point"}
}