{
  "type": "Feature",
  "properties": {
    "addr:full":"Beneden Hemelrijk 5c Ninove (meerbeke) Oost-Vlaanderen 9402",
    "addr:housenumber":"5c",
    "addr:postcode":"9402",
    "addr:street":"Beneden Hemelrijk",
    "iso:country":"BE",
    "sg:address":"Beneden Hemelrijk 5c",
    "sg:city":"Ninove (meerbeke)",
    "sg:classifiers":[
        {
            "category":"Retail",
            "subcategory":"Auto Repair",
            "type":"Services"
        }
    ],
    "sg:phone":"+32 54 33 42 83",
    "sg:postcode":"9402",
    "sg:province":"Oost-Vlaanderen",
    "sg:tags":[
        "garage"
    ],
    "wof:name":"Bicke Jozef Bvba",
    "wof:placetype":"venue"
},
  "geometry": {"coordinates":[4.0395750999,50.8249015808],"type":"Point"}
}