{
  "type": "Feature",
  "properties": {
    "iso:country":"BE",
    "sg:address":"Sint-truidersteenweg 298",
    "sg:city":"Hasselt",
    "sg:classifiers":[
        {
            "category":"Professional",
            "subcategory":"Art Services",
            "type":"Services"
        }
    ],
    "sg:phone":"+32 11 27 23 44",
    "sg:postcode":"3500",
    "sg:province":"Limburg",
    "sg:tags":[
        "automobile",
        "transit",
        "-",
        "export",
        "import"
    ],
    "wof:name":"Billen Frans Nv",
    "wof:placetype":"venue"
},
  "geometry": {"coordinates":[5.327091217,50.9177436829],"type":"Point"}
}