{
  "type": "Feature",
  "properties": {
    "addr:full":"Bredabaan 226 Brasschaat Antwerpen 2930",
    "addr:housenumber":"226",
    "addr:postcode":"2930",
    "addr:street":"Bredabaan",
    "iso:country":"BE",
    "sg:address":"Bredabaan 226",
    "sg:city":"Brasschaat",
    "sg:classifiers":[
        {
            "category":"Real Estate",
            "subcategory":"Real Estate Services",
            "type":"Services"
        }
    ],
    "sg:phone":"+32 475 27 42 40",
    "sg:postcode":"2930",
    "sg:province":"Antwerpen",
    "wof:name":"Immo V.d.p. Bvba",
    "wof:placetype":"venue"
},
  "geometry": {"coordinates":[4.4895291328,51.2892341614],"type":"Point"}
}