{
  "type": "Feature",
  "properties": {
    "addr:full":"Staatsbaan 241 Kortemark West-Vlaanderen 8610",
    "addr:housenumber":"241",
    "addr:postcode":"8610",
    "addr:street":"Staatsbaan",
    "iso:country":"BE",
    "sg:address":"Staatsbaan 241",
    "sg:city":"Kortemark",
    "sg:orig_category":"Pi\u00e8ces and accessoires de v\u00e9hicules automobiles Mat\u00e9riaux de construction Gr",
    "sg:phone":"+32 51 56 96 56",
    "sg:postcode":"8610",
    "sg:province":"West-Vlaanderen",
    "wof:name":"North Sea Paints",
    "wof:placetype":"venue"
},
  "geometry": {"coordinates":[3.0162580013,51.0216026306],"type":"Point"}
}