{
  "type": "Feature",
  "properties": {
    "addr:full":"Kasteelstraat 21 Asse (mollem) Vlaams-Brabant 1730",
    "addr:housenumber":"21",
    "addr:postcode":"1730",
    "addr:street":"Kasteelstraat",
    "iso:country":"BE",
    "sg:address":"Kasteelstraat 21",
    "sg:city":"Asse (mollem)",
    "sg:classifiers":[
        {
            "category":"Bars & Pubs",
            "type":"Food & Drink"
        }
    ],
    "sg:phone":"+32 2 452 86 96",
    "sg:postcode":"1730",
    "sg:province":"Vlaams-Brabant",
    "wof:name":"Trapkes Op",
    "wof:placetype":"venue"
},
  "geometry": {"coordinates":[4.2268939018,50.9303779602],"type":"Point"}
}