{
  "type": "Feature",
  "properties": {
    "iso:country":"BE",
    "sg:address":"Lierseweg 298",
    "sg:city":"Herentals",
    "sg:classifiers":[
        {
            "category":"Food & Beverages",
            "subcategory":"Groceries & Convenience Stores",
            "type":"Retail Goods"
        }
    ],
    "sg:phone":"+32 14 28 58 80",
    "sg:postcode":"2200",
    "sg:province":"Antwerpen",
    "sg:tags":[
        "grocer"
    ],
    "wof:name":"Tecno Nv",
    "wof:placetype":"venue"
},
  "geometry": {"coordinates":[4.7981929779,51.1734199524],"type":"Point"}
}