{
  "type": "Feature",
  "properties": {
    "addr:full":"Rue Du Mar\u00c9chal Joffre 49 Colfontaine Hainaut 7340",
    "addr:housenumber":"49",
    "addr:postcode":"7340",
    "addr:street":"Rue Du Mare\u0301Chal Joffre",
    "iso:country":"BE",
    "sg:address":"Rue Du Mar\u00c9chal Joffre 49",
    "sg:city":"Colfontaine",
    "sg:classifiers":[
        {
            "category":"Arena",
            "subcategory":"Sports Club",
            "type":"Entertainment"
        }
    ],
    "sg:phone":"+32 65 66 68 36",
    "sg:postcode":"7340",
    "sg:province":"Hainaut",
    "sg:tags":[
        "de"
    ],
    "wof:name":"B.c. La Plume Boraine",
    "wof:placetype":"venue"
},
  "geometry": {"coordinates":[3.8463139534,50.4074440002],"type":"Point"}
}