{
  "type": "Feature",
  "properties": {
    "addr:full":"Rue Petite Aise 19 Charleroi (montignies-sur-sambre) Hainaut 6061",
    "addr:housenumber":"19",
    "addr:postcode":"6061",
    "addr:street":"Rue Petite Aise",
    "iso:country":"BE",
    "sg:address":"Rue Petite Aise 19",
    "sg:city":"Charleroi (montignies-sur-sambre)",
    "sg:classifiers":[
        {
            "category":"Retail",
            "subcategory":"Repair Shop",
            "type":"Services"
        }
    ],
    "sg:phone":"+32 71 41 11 16",
    "sg:postcode":"6061",
    "sg:province":"Hainaut",
    "sg:tags":[
        "upholsterer"
    ],
    "wof:name":"Buckens Ph Sprl",
    "wof:placetype":"venue"
},
  "geometry": {"coordinates":[4.4658889771,50.4227180481],"type":"Point"}
}