{
  "type": "Feature",
  "properties": {
    "addr:full":"Wechelsebaan 166 Lille Antwerpen 2275",
    "addr:housenumber":"166",
    "addr:postcode":"2275",
    "addr:street":"Wechelsebaan",
    "iso:country":"BE",
    "sg:address":"Wechelsebaan 166",
    "sg:city":"Lille",
    "sg:classifiers":[
        {
            "category":"Banks & Credit Unions",
            "subcategory":"Investment Brokerage",
            "type":"Services"
        }
    ],
    "sg:phone":"+32 14 88 12 26",
    "sg:postcode":"2275",
    "sg:province":"Antwerpen",
    "sg:tags":[
        "wreath",
        "mourning"
    ],
    "wof:name":"Amaryllis",
    "wof:placetype":"venue"
},
  "geometry": {"coordinates":[4.8161802292,51.2511711121],"type":"Point"}
}