{
  "type": "Feature",
  "properties": {
    "addr:full":"Avenue Van Volxem 461 Vorst/forest Bruxelles-Capitale 1190",
    "addr:housenumber":"461",
    "addr:postcode":"1190",
    "addr:street":"Avenue Van Volxem;/ Forest",
    "iso:country":"BE",
    "sg:address":"Avenue Van Volxem 461",
    "sg:city":"Vorst/forest",
    "sg:orig_category":"Imprimeries and copyshops",
    "sg:phone":"+32 2 543 01 60",
    "sg:postcode":"1190",
    "sg:province":"Bruxelles-Capitale",
    "wof:name":"Les Presses De L'avenir",
    "wof:placetype":"venue"
},
  "geometry": {"coordinates":[4.3283557892,50.8278236389],"type":"Point"}
}