{
  "type": "Feature",
  "properties": {
    "addr:full":"Oude Bruggestraat 3 Wingene West-Vlaanderen 8750",
    "addr:housenumber":"3",
    "addr:postcode":"8750",
    "addr:street":"Oude Bruggestraat",
    "iso:country":"BE",
    "sg:address":"Oude Bruggestraat 3",
    "sg:city":"Wingene",
    "sg:orig_category":"Banques and organismes de cr\u00e9dit",
    "sg:phone":"+32 51 65 69 70",
    "sg:postcode":"8750",
    "sg:province":"West-Vlaanderen",
    "wof:name":"Dexia",
    "wof:placetype":"venue"
},
  "geometry": {"coordinates":[3.2780959606,51.0576400757],"type":"Point"}
}