{
  "type": "Feature",
  "properties": {
    "iso:country":"BE",
    "sg:address":"Zeilschipstraat 30bis",
    "sg:city":"Gent",
    "sg:classifiers":[
        {
            "category":"Arena",
            "subcategory":"Sports Club",
            "type":"Entertainment"
        }
    ],
    "sg:phone":"+32 9 253 15 31",
    "sg:postcode":"9000",
    "sg:province":"Oost-Vlaanderen",
    "sg:tags":[
        "terrain",
        "hors",
        "de",
        "installation",
        "sportifs"
    ],
    "wof:name":"F.c. Gent",
    "wof:placetype":"venue"
},
  "geometry": {"coordinates":[3.717083931,51.0784759521],"type":"Point"}
}