{
  "type": "Feature",
  "properties": {
    "addr:full":"Stationsstraat 32 Veltem 3008",
    "addr:housenumber":"32",
    "addr:postcode":"3008",
    "addr:street":"Stationsstraat",
    "iso:country":"BE",
    "sg:address":"Stationsstraat 32",
    "sg:city":"Veltem",
    "sg:classifiers":[
        {
            "category":"Banks & Credit Unions",
            "subcategory":"Bank",
            "type":"Services"
        }
    ],
    "sg:phone":"+32 16 48 03 00",
    "sg:postcode":"3008",
    "wof:name":"Aslk-cger Bank",
    "wof:placetype":"venue"
},
  "geometry": {"coordinates":[145.01747131350001,-37.7819442749],"type":"Point"}
}