{
  "type": "Feature",
  "properties": {
    "addr:full":"Sint-martensstraat 6 Neerpelt Limburg 3910",
    "addr:housenumber":"6",
    "addr:postcode":"3910",
    "addr:street":"Sint-Martensstraat",
    "iso:country":"BE",
    "sg:address":"Sint-martensstraat 6",
    "sg:city":"Neerpelt",
    "sg:orig_category":"M\u00e9decins and sp\u00e9cialistes",
    "sg:phone":"+32 11 66 56 30",
    "sg:postcode":"3910",
    "sg:province":"Limburg",
    "wof:name":"Anne Nelissen",
    "wof:placetype":"venue"
},
  "geometry": {"coordinates":[5.4276428223,51.2326011658],"type":"Point"}
}