{
  "type": "Feature",
  "properties": {
    "iso:country":"BE",
    "sg:address":"Avenue De Tervueren 188a",
    "sg:city":"Bruxelles (woluwe-saint-pierre)",
    "sg:classifiers":[
        {
            "category":"Professional",
            "subcategory":"Management & Consulting",
            "type":"Services"
        }
    ],
    "sg:phone":"+32 2 770 25 97",
    "sg:postcode":"1150",
    "sg:province":"Bruxelles-Capitale",
    "sg:tags":[
        "tax-consultants"
    ],
    "wof:name":"Van Den Driessche P",
    "wof:placetype":"venue"
},
  "geometry": {"coordinates":[4.4113469124,50.8370170593],"type":"Point"}
}