{
  "type": "Feature",
  "properties": {
    "iso:country":"BE",
    "sg:address":"P.i. Taymansstraat 21",
    "sg:city":"Overijse",
    "sg:orig_category":"Services fun\u00e9raires",
    "sg:phone":"+32 2 687 58 84",
    "sg:postcode":"3090",
    "sg:province":"Vlaams-Brabant",
    "wof:name":"Begrafen. Vangrunderbeek",
    "wof:placetype":"venue"
},
  "geometry": {"coordinates":[4.5371069908,50.7739524841],"type":"Point"}
}