{
  "type": "Feature",
  "properties": {
    "addr:full":"Watertorenlaan 31 Zaventem Vlaams-Brabant 1930",
    "addr:housenumber":"31",
    "addr:postcode":"1930",
    "addr:street":"Watertorenlaan",
    "iso:country":"BE",
    "sg:address":"Watertorenlaan 31",
    "sg:city":"Zaventem",
    "sg:classifiers":[
        {
            "category":"Personal",
            "subcategory":"Beauty Salon",
            "type":"Services"
        }
    ],
    "sg:phone":"+32 2 720 93 54",
    "sg:postcode":"1930",
    "sg:province":"Vlaams-Brabant",
    "sg:tags":[
        "lady",
        "-",
        "hairdressing"
    ],
    "wof:name":"Hairstyle Paul",
    "wof:placetype":"venue"
},
  "geometry": {"coordinates":[4.4732642174,50.886264801],"type":"Point"}
}