{
  "type": "Feature",
  "properties": {
    "iso:country":"BE",
    "sg:address":"Mechelsesteenweg 40b8",
    "sg:city":"Vilvoorde",
    "sg:orig_category":"Ordinateurs and \u00e9quipement informatique. Disquaires",
    "sg:phone":"+32 2 251 13 40",
    "sg:postcode":"1800",
    "sg:province":"Vlaams-Brabant",
    "wof:name":"Extrazone Vilvoorde",
    "wof:placetype":"venue"
},
  "geometry": {"coordinates":[4.4243898392,50.9321632385],"type":"Point"}
}