{
  "type": "Feature",
  "properties": {
    "addr:full":"Burgemeester Van Lindtstraat 61 Overpelt Limburg 3900",
    "addr:housenumber":"61",
    "addr:postcode":"3900",
    "addr:street":"Burgemeester Van Lindtstraat",
    "iso:country":"BE",
    "sg:address":"Burgemeester Van Lindtstraat 61",
    "sg:city":"Overpelt",
    "sg:classifiers":[
        {
            "category":"Professional",
            "subcategory":"Lawyer & Legal Services",
            "type":"Services"
        }
    ],
    "sg:phone":"+32 11 80 47 30",
    "sg:postcode":"3900",
    "sg:province":"Limburg",
    "wof:name":"Fransen Jaak",
    "wof:placetype":"venue"
},
  "geometry": {"coordinates":[5.4197659492,51.2126045227],"type":"Point"}
}