{
  "type": "Feature",
  "properties": {
    "iso:country":"BE",
    "sg:address":"Avenue De La R\u00c9sistance 276",
    "sg:city":"Soumagne",
    "sg:orig_category":"Chaussures. Articles de camping and de sport",
    "sg:phone":"+32 4 377 44 13",
    "sg:postcode":"4630",
    "sg:province":"Li\u00e8ge",
    "wof:name":"B.m. Sport",
    "wof:placetype":"venue"
},
  "geometry": {"coordinates":[5.7361531258,50.6315498352],"type":"Point"}
}