{
  "type": "Feature",
  "properties": {
    "iso:country":"BE",
    "sg:address":"Helpt Elkanderstraat 48",
    "sg:city":"Wuustwezel",
    "sg:classifiers":[
        {
            "category":"Communications",
            "subcategory":"Film & Video Production",
            "type":"Services"
        }
    ],
    "sg:phone":"+32 3 663 54 05",
    "sg:postcode":"2990",
    "sg:province":"Antwerpen",
    "sg:tags":[
        "realisation",
        "-"
    ],
    "wof:name":"V D S Video Producties",
    "wof:placetype":"venue"
},
  "geometry": {"coordinates":[4.5411539078,51.3546180725],"type":"Point"}
}