{
  "type": "Feature",
  "properties": {
    "iso:country":"BE",
    "sg:address":"Burg-reuland 93bb",
    "sg:city":"Burg-reuland",
    "sg:orig_category":"Charpentes and couvertures",
    "sg:phone":"+32 80 42 90 20",
    "sg:postcode":"4790",
    "sg:province":"Li\u00e8ge",
    "wof:name":"Jacobs & Sohn",
    "wof:placetype":"venue"
},
  "geometry": {"coordinates":[6.1315698624,50.1943702698],"type":"Point"}
}