{
  "type": "Feature",
  "properties": {
    "addr:full":"Rue D'aulne 6 Montigny-le-tilleul Hainaut 6110",
    "addr:housenumber":"6",
    "addr:postcode":"6110",
    "addr:street":"Rue D'Aulne",
    "iso:country":"BE",
    "sg:address":"Rue D'aulne 6",
    "sg:city":"Montigny-le-tilleul",
    "sg:classifiers":[
        {
            "category":"Banks & Credit Unions",
            "subcategory":"Investment Brokerage",
            "type":"Services"
        }
    ],
    "sg:phone":"+32 71 51 16 07",
    "sg:postcode":"6110",
    "sg:province":"Hainaut",
    "sg:tags":[
        "repair",
        "-",
        "installation",
        "sanitary",
        "article"
    ],
    "wof:name":"Manutherm Sprl",
    "wof:placetype":"venue"
},
  "geometry": {"coordinates":[4.3635621071,50.3664398193],"type":"Point"}
}