{
  "type": "Feature",
  "properties": {
    "addr:full":"Rue Du Bas Hameau 38 Celles (velaines) Hainaut 7760",
    "addr:housenumber":"38",
    "addr:postcode":"7760",
    "addr:street":"Rue Du Bas Hameau",
    "iso:country":"BE",
    "sg:address":"Rue Du Bas Hameau 38",
    "sg:city":"Celles (velaines)",
    "sg:classifiers":[
        {
            "category":"Health Services",
            "subcategory":"Doctor",
            "type":"Services"
        }
    ],
    "sg:phone":"+32 69 85 91 00",
    "sg:postcode":"7760",
    "sg:province":"Hainaut",
    "sg:tags":[
        "medicinephysicians",
        "surgeon"
    ],
    "wof:name":"Deroubaix Michel",
    "wof:placetype":"venue"
},
  "geometry": {"coordinates":[3.4867479801,50.6638870239],"type":"Point"}
}