{
  "type": "Feature",
  "properties": {
    "iso:country":"BE",
    "sg:address":"Ieperstraat 126a",
    "sg:city":"Hooglede",
    "sg:classifiers":[
        {
            "category":"Professional",
            "subcategory":"Management & Consulting",
            "type":"Services"
        }
    ],
    "sg:phone":"+32 51 24 78 27",
    "sg:postcode":"8830",
    "sg:province":"West-Vlaanderen",
    "sg:tags":[
        "consultant"
    ],
    "wof:name":"Marcon",
    "wof:placetype":"venue"
},
  "geometry": {"coordinates":[3.0690219402,50.9697532654],"type":"Point"}
}