{
  "type": "Feature",
  "properties": {
    "iso:country":"BE",
    "sg:address":"Frederik De Merodestraat 111",
    "sg:city":"Mechelen",
    "sg:orig_category":"Boekhouders",
    "sg:phone":"+32 15 21 73 27",
    "sg:postcode":"2800",
    "sg:province":"Antwerpen",
    "wof:name":"L. Eyckmans",
    "wof:placetype":"venue"
},
  "geometry": {"coordinates":[4.483399868,51.0325584412],"type":"Point"}
}