{
  "type": "Feature",
  "properties": {
    "iso:country":"BE",
    "sg:address":"Rue Des Naiveux 14",
    "sg:city":"Herstal",
    "sg:classifiers":[
        {
            "category":"Shopping",
            "subcategory":"Hobbies, Toys, & Games",
            "type":"Retail Goods"
        }
    ],
    "sg:phone":"+32 4 264 25 09",
    "sg:postcode":"4040",
    "sg:province":"Li\u00e8ge",
    "sg:tags":[
        "toy",
        "-"
    ],
    "wof:name":"Dreamland",
    "wof:placetype":"venue"
},
  "geometry": {"coordinates":[5.6468567848,50.6881866455],"type":"Point"}
}