{
  "type": "Feature",
  "properties": {
    "addr:full":"Rue Sauveni\u00e8re 20 Ouffet Li\u00e8ge 4590",
    "addr:housenumber":"20",
    "addr:postcode":"4590",
    "addr:street":"Rue Sauvenie\u0300Re",
    "iso:country":"BE",
    "sg:address":"Rue Sauveni\u00e8re 20",
    "sg:city":"Ouffet",
    "sg:classifiers":[
        {
            "category":"Place Of Worship",
            "subcategory":"Church",
            "type":"Public Place"
        }
    ],
    "sg:phone":"+32 86 36 65 06",
    "sg:postcode":"4590",
    "sg:province":"Li\u00e8ge",
    "sg:tags":[
        "article",
        "baptismal"
    ],
    "wof:name":"De Pery",
    "wof:placetype":"venue"
},
  "geometry": {"coordinates":[5.4638061523,50.4390525818],"type":"Point"}
}