{
  "type": "Feature",
  "properties": {
    "addr:full":"Brildam 24 Torhout West-Vlaanderen 8820",
    "addr:housenumber":"24",
    "addr:postcode":"8820",
    "addr:street":"Brildam",
    "iso:country":"BE",
    "sg:address":"Brildam 24",
    "sg:city":"Torhout",
    "sg:classifiers":[
        {
            "category":"Health Services",
            "subcategory":"Health Practitioner",
            "type":"Services"
        }
    ],
    "sg:phone":"+32 50 21 71 89",
    "sg:postcode":"8820",
    "sg:province":"West-Vlaanderen",
    "sg:tags":[
        "dietitian"
    ],
    "wof:name":"Vanoverbeke Sandra",
    "wof:placetype":"venue"
},
  "geometry": {"coordinates":[3.1088769436,51.0672950745],"type":"Point"}
}