{
  "type": "Feature",
  "properties": {
    "iso:country":"BE",
    "sg:address":"Place De La Gare 36",
    "sg:city":"Qui\u00e9vrain",
    "sg:classifiers":[
        {
            "category":"Personal",
            "subcategory":"Nail Salon",
            "type":"Services"
        }
    ],
    "sg:phone":"+32 65 31 33 51",
    "sg:postcode":"7380",
    "sg:province":"Hainaut",
    "sg:tags":[
        "pedicure"
    ],
    "wof:name":"Ducruet V",
    "wof:placetype":"venue"
},
  "geometry": {"coordinates":[3.6870360374,50.4096794128],"type":"Point"}
}