{
  "type": "Feature",
  "properties": {
    "iso:country":"BE",
    "sg:address":"Weggevoerdenstraat 82",
    "sg:city":"Leuven",
    "sg:orig_category":"Schoonmaakbedrijven and ongediertebestrijding",
    "sg:phone":"+32 16 44 85 75",
    "sg:postcode":"3012",
    "sg:province":"Vlaams-Brabant",
    "wof:name":"G.r.g.",
    "wof:placetype":"venue"
},
  "geometry": {"coordinates":[4.716105938,50.9247016907],"type":"Point"}
}