{
  "type": "Feature",
  "properties": {
    "addr:full":"Alsembergse Steenweg 473 Ukkel/uccle Bruxelles-Capitale 1180",
    "addr:housenumber":"473",
    "addr:postcode":"1180",
    "addr:street":"Alsembergse Steenweg;/",
    "iso:country":"BE",
    "sg:address":"Alsembergse Steenweg 473",
    "sg:city":"Ukkel/uccle",
    "sg:orig_category":"Voedingsspeciaalzaken",
    "sg:phone":"+32 2 344 62 43",
    "sg:postcode":"1180",
    "sg:province":"Bruxelles-Capitale",
    "wof:name":"Eurovol",
    "wof:placetype":"venue"
},
  "geometry": {"coordinates":[4.33791399,50.8116149902],"type":"Point"}
}