{
  "type": "Feature",
  "properties": {
    "iso:country":"BE",
    "sg:address":"Leopoldstraat 27",
    "sg:city":"Brussel/bruxelles",
    "sg:orig_category":"Autoverhuur",
    "sg:phone":"+32 2 229 11 25",
    "sg:postcode":"1000",
    "sg:province":"Bruxelles-Capitale",
    "wof:name":"U.f.b.-a.c.e. Leasing",
    "wof:placetype":"venue"
},
  "geometry": {"coordinates":[4.3552379608,50.849697113],"type":"Point"}
}