{
  "type": "Feature",
  "properties": {
    "addr:full":"Rijksweg 429 Dilsen-stokkem Limburg 3650",
    "addr:housenumber":"429",
    "addr:postcode":"dilsen-stokkem;3650",
    "addr:street":"Rijksweg",
    "iso:country":"BE",
    "sg:address":"Rijksweg 429",
    "sg:city":"Dilsen-stokkem",
    "sg:orig_category":"Pharmaciens",
    "sg:phone":"+32 89 75 55 11",
    "sg:postcode":"3650",
    "sg:province":"Limburg",
    "wof:name":"Thevissen-meeus",
    "wof:placetype":"venue"
},
  "geometry": {"coordinates":[5.7289500237,51.0342674255],"type":"Point"}
}