{
  "type": "Feature",
  "properties": {
    "iso:country":"BE",
    "sg:address":"Avenue De La Gare 64",
    "sg:city":"Beyne-heusay",
    "sg:orig_category":"Fer and acier Fab",
    "sg:phone":"+32 4 358 56 40",
    "sg:postcode":"4610",
    "sg:province":"Li\u00e8ge",
    "wof:name":"M\u00c9talunion",
    "wof:placetype":"venue"
},
  "geometry": {"coordinates":[5.6568541527,50.6184082031],"type":"Point"}
}