{
  "type": "Feature",
  "properties": {
    "iso:country":"BE",
    "sg:address":"Rue Emile Vandervelde 55",
    "sg:city":"Pepinster (wegnez)",
    "sg:classifiers":[
        {
            "category":"Professional",
            "subcategory":"Management & Consulting",
            "type":"Services"
        }
    ],
    "sg:phone":"+32 87 46 31 75",
    "sg:postcode":"4860",
    "sg:province":"Li\u00e8ge",
    "sg:tags":[
        "consultant",
        "agency",
        "advertising"
    ],
    "wof:name":"Cosmos Graphic",
    "wof:placetype":"venue"
},
  "geometry": {"coordinates":[5.8236618042,50.579334259],"type":"Point"}
}