{
  "type": "Feature",
  "properties": {
    "addr:full":"Brugsestraat 265 Gent Oost-Vlaanderen 9000",
    "addr:housenumber":"265",
    "addr:postcode":"9000",
    "addr:street":"Brugsestraat;Oost-Vlaanderen",
    "iso:country":"BE",
    "sg:address":"Brugsestraat 265",
    "sg:city":"Gent",
    "sg:classifiers":[
        {
            "category":"Restaurant",
            "type":"Food & Drink"
        }
    ],
    "sg:phone":"+32 9 236 21 56",
    "sg:postcode":"9000",
    "sg:province":"Oost-Vlaanderen",
    "wof:name":"Swingline",
    "wof:placetype":"venue"
},
  "geometry": {"coordinates":[3.687169075,51.0670433044],"type":"Point"}
}