{
  "type": "Feature",
  "properties": {
    "addr:full":"Chauss\u00e9e De Wavre 504 Box 30 Grez-doiceau Brabant Wallon 1390",
    "addr:housenumber":"504 box 30",
    "addr:postcode":"1390",
    "addr:street":"Chausse\u0301E De Wavre",
    "iso:country":"BE",
    "sg:address":"Chauss\u00e9e De Wavre 504 Box 30",
    "sg:city":"Grez-doiceau",
    "sg:classifiers":[
        {
            "category":"Train Station",
            "subcategory":"Rail",
            "type":"Transportation"
        }
    ],
    "sg:phone":"+32 10 84 27 62",
    "sg:postcode":"1390",
    "sg:province":"Brabant Wallon",
    "sg:tags":[
        "transfer",
        "sticker"
    ],
    "wof:name":"Opriac",
    "wof:placetype":"venue"
},
  "geometry": {"coordinates":[4.6466069221,50.7328109741],"type":"Point"}
}