{
  "type": "Feature",
  "properties": {
    "addr:full":"Chauss\u00c9e De Binche 101 Mons Hainaut 7000",
    "addr:housenumber":"101",
    "addr:postcode":"7000",
    "addr:street":"Chausse\u0301E De Binche;Hainaut",
    "iso:country":"BE",
    "sg:address":"Chauss\u00c9e De Binche 101",
    "sg:city":"Mons",
    "sg:orig_category":"Software ontwikkeling and ontwerp",
    "sg:phone":"+32 65 84 11 04",
    "sg:postcode":"7000",
    "sg:province":"Hainaut",
    "wof:name":"Daphne",
    "wof:placetype":"venue"
},
  "geometry": {"coordinates":[3.9737520218,50.4527206421],"type":"Point"}
}