{
  "type": "Feature",
  "properties": {
    "addr:full":"Kerkstraat 7 Itterbeek Vlaams-Brabant 1701",
    "addr:housenumber":"7",
    "addr:postcode":"1701",
    "addr:street":"Kerkstraat",
    "iso:country":"BE",
    "sg:address":"Kerkstraat 7",
    "sg:city":"Itterbeek",
    "sg:orig_category":"Banken and kredietinstellingen Hypotheken and hypotheekbanken Verzekeringsmakelaars and experts",
    "sg:phone":"+32 2 569 03 73",
    "sg:postcode":"1701",
    "sg:province":"Vlaams-Brabant",
    "wof:name":"Kantoor De Knijf & Depoorter",
    "wof:placetype":"venue"
},
  "geometry": {"coordinates":[4.2462081909,50.8400917053],"type":"Point"}
}