{
  "type": "Feature",
  "properties": {
    "addr:full":"Lindelei 9 Aartselaar Antwerpen 2630",
    "addr:housenumber":"9",
    "addr:postcode":"2630",
    "addr:street":"Lindelei",
    "iso:country":"BE",
    "sg:address":"Lindelei 9",
    "sg:city":"Aartselaar",
    "sg:classifiers":[
        {
            "category":"Personal",
            "subcategory":"Beauty Salon",
            "type":"Services"
        }
    ],
    "sg:phone":"+32 3 887 62 47",
    "sg:postcode":"2630",
    "sg:province":"Antwerpen",
    "sg:tags":[
        "de",
        "coiffure"
    ],
    "wof:name":"Nikolaas Daems",
    "wof:placetype":"venue"
},
  "geometry": {"coordinates":[4.3888587952,51.1338157654],"type":"Point"}
}