{
  "type": "Feature",
  "properties": {
    "iso:country":"BE",
    "sg:address":"Avenue Houzeau 21",
    "sg:city":"Ukkel/uccle",
    "sg:classifiers":[
        {
            "category":"Restaurant",
            "type":"Food & Drink"
        }
    ],
    "sg:phone":"+32 2 375 36 32",
    "sg:postcode":"1180",
    "sg:province":"Bruxelles-Capitale",
    "wof:name":"Le Groom Gourmand",
    "wof:placetype":"venue"
},
  "geometry": {"coordinates":[4.3585262299,50.8033256531],"type":"Point"}
}