{
  "type": "Feature",
  "properties": {
    "iso:country":"BE",
    "sg:address":"Joseph Plateaustraat 5",
    "sg:city":"Oostende (stene)",
    "sg:classifiers":[
        {
            "category":"Retail",
            "subcategory":"Auto Repair",
            "type":"Services"
        }
    ],
    "sg:phone":"+32 59 70 53 08",
    "sg:postcode":"8400",
    "sg:province":"West-Vlaanderen",
    "sg:tags":[
        "garage"
    ],
    "wof:name":"Flanders U.s.-cars",
    "wof:placetype":"venue"
},
  "geometry": {"coordinates":[2.9374539852,51.2090988159],"type":"Point"}
}