{
  "type": "Feature",
  "properties": {
    "iso:country":"BE",
    "sg:address":"Leenstraat 55",
    "sg:city":"Zulte",
    "sg:classifiers":[
        {
            "category":"Professional",
            "subcategory":"Accounting & Tax Preparation",
            "type":"Services"
        }
    ],
    "sg:phone":"+32 9 388 82 18",
    "sg:postcode":"9870",
    "sg:province":"Oost-Vlaanderen",
    "sg:tags":[
        "accountant"
    ],
    "wof:name":"Carlos Van Simaey",
    "wof:placetype":"venue"
},
  "geometry": {"coordinates":[3.4558849335,50.9099235535],"type":"Point"}
}