{
  "type": "Feature",
  "properties": {
    "iso:country":"BE",
    "sg:address":"Korbeekse Kerkstraat 35",
    "sg:city":"Bertem",
    "sg:orig_category":"Installatie van houten of kunststof schrijnwerk Installatie van metalen schrijnwerk",
    "sg:phone":"+32 16 47 35 54",
    "sg:postcode":"3060",
    "sg:province":"Vlaams-Brabant",
    "wof:name":"Merckx Marc",
    "wof:placetype":"venue"
},
  "geometry": {"coordinates":[4.6298098564,50.8611297607],"type":"Point"}
}