{
  "type": "Feature",
  "properties": {
    "addr:full":"Ambachtstraat 13 Torhout West-Vlaanderen 8820",
    "addr:housenumber":"13",
    "addr:postcode":"8820",
    "addr:street":"Ambachtstraat",
    "iso:country":"BE",
    "sg:address":"Ambachtstraat 13",
    "sg:city":"Torhout",
    "sg:orig_category":"Woningbouw",
    "sg:phone":"+32 50 21 63 14",
    "sg:postcode":"8820",
    "sg:province":"West-Vlaanderen",
    "wof:name":"Marc Hollevoet",
    "wof:placetype":"venue"
},
  "geometry": {"coordinates":[3.1077818871,51.077507019],"type":"Point"}
}