{
  "type": "Feature",
  "properties": {
    "addr:full":"Rue Van Campenhout 25 Brussel/bruxelles Bruxelles-Capitale 1000",
    "addr:housenumber":"25",
    "addr:postcode":"1000",
    "addr:street":"Rue Van Campenhout;/",
    "iso:country":"BE",
    "sg:address":"Rue Van Campenhout 25",
    "sg:city":"Brussel/bruxelles",
    "sg:orig_category":"Artistes ind\u00e9pendants",
    "sg:phone":"+32 2 734 94 50",
    "sg:postcode":"1000",
    "sg:province":"Bruxelles-Capitale",
    "wof:name":"Romain Rabeaux",
    "wof:placetype":"venue"
},
  "geometry": {"coordinates":[4.3862938881,50.8479118347],"type":"Point"}
}