{
  "type": "Feature",
  "properties": {
    "addr:full":"Marktplein 20 Evergem Oost-Vlaanderen 9940",
    "addr:housenumber":"20",
    "addr:postcode":"9940",
    "addr:street":"Marktplein;Oost-Vlaanderen",
    "iso:country":"BE",
    "sg:address":"Marktplein 20",
    "sg:city":"Evergem",
    "sg:classifiers":[
        {
            "category":"Shopping",
            "subcategory":"Clothing, Apparel, & Fashions",
            "type":"Retail Goods"
        }
    ],
    "sg:phone":"+32 9 344 71 44",
    "sg:postcode":"9940",
    "sg:province":"Oost-Vlaanderen",
    "sg:tags":[
        "ondergoed",
        "lingerie"
    ],
    "wof:name":"Boetiek Popov",
    "wof:placetype":"venue"
},
  "geometry": {"coordinates":[3.7464809418,51.1785202026],"type":"Point"}
}