{
  "type": "Feature",
  "properties": {
    "iso:country":"BE",
    "sg:address":"Sterstraat 95",
    "sg:city":"Ukkel/uccle",
    "sg:orig_category":"Krantenwinkels Rookartikelen",
    "sg:phone":"+32 2 376 95 51",
    "sg:postcode":"1180",
    "sg:province":"Bruxelles-Capitale",
    "wof:name":"Librairie De L'etoile",
    "wof:placetype":"venue"
},
  "geometry": {"coordinates":[4.3204607964,50.793598175],"type":"Point"}
}