{
  "type": "Feature",
  "properties": {
    "iso:country":"BE",
    "sg:address":"Edelweisslaan 8",
    "sg:city":"Tervuren",
    "sg:orig_category":"Diverse opleidingen and onderwijs",
    "sg:phone":"+32 2 768 22 33",
    "sg:postcode":"3080",
    "sg:province":"Vlaams-Brabant",
    "wof:name":"Keys For Change",
    "wof:placetype":"venue"
},
  "geometry": {"coordinates":[4.5479311943,50.8416252136],"type":"Point"}
}