{
  "type": "Feature",
  "properties": {
    "iso:country":"BE",
    "sg:address":"Zeelaan 59",
    "sg:city":"De Panne",
    "sg:orig_category":"Blanchisseries and teintureries",
    "sg:phone":"+32 58 41 19 73",
    "sg:postcode":"8660",
    "sg:province":"West-Vlaanderen",
    "wof:name":"Droogkuis Tip-top",
    "wof:placetype":"venue"
},
  "geometry": {"coordinates":[2.591326952,51.0984268188],"type":"Point"}
}