{
  "type": "Feature",
  "properties": {
    "iso:country":"BE",
    "sg:address":"Nieuwe Weg 6a",
    "sg:city":"Sint-martens-latem",
    "sg:classifiers":[
        {
            "category":"Shopping",
            "subcategory":"Jewelry",
            "type":"Retail Goods"
        }
    ],
    "sg:phone":"+32 9 281 11 42",
    "sg:postcode":"9830",
    "sg:province":"Oost-Vlaanderen",
    "sg:tags":[
        "jeweller",
        "-"
    ],
    "wof:name":"Goudsmederij De Landtsheer",
    "wof:placetype":"venue"
},
  "geometry": {"coordinates":[3.6307320595,51.0106086731],"type":"Point"}
}