{
  "type": "Feature",
  "properties": {
    "iso:country":"BE",
    "sg:address":"Molendreef 9",
    "sg:city":"Zedelgem (loppem)",
    "sg:classifiers":[
        {
            "category":"Building & Trades",
            "subcategory":"Electrical",
            "type":"Services"
        }
    ],
    "sg:phone":"+32 50 84 00 54",
    "sg:postcode":"8210",
    "sg:province":"West-Vlaanderen",
    "sg:tags":[
        "electric",
        "-",
        "housewiring",
        "contractor"
    ],
    "wof:name":"Druwel Elektro & Partners",
    "wof:placetype":"venue"
},
  "geometry": {"coordinates":[3.1349589825,51.1403198242],"type":"Point"}
}