{
  "type": "Feature",
  "properties": {
    "addr:full":"Brusselsesteenweg 156 Halle Vlaams-Brabant 1500",
    "addr:housenumber":"156",
    "addr:postcode":"1500",
    "addr:street":"Brusselsesteenweg",
    "iso:country":"BE",
    "sg:address":"Brusselsesteenweg 156",
    "sg:city":"Halle",
    "sg:orig_category":"Fleurs and plantes",
    "sg:phone":"+32 2 356 74 15",
    "sg:postcode":"1500",
    "sg:province":"Vlaams-Brabant",
    "wof:name":"Boeketje Florist",
    "wof:placetype":"venue"
},
  "geometry": {"coordinates":[4.239880085,50.7414665222],"type":"Point"}
}