{
  "type": "Feature",
  "properties": {
    "addr:full":"Pav\u00c9 D'ath 43 Silly Hainaut 7830",
    "addr:housenumber":"43",
    "addr:postcode":"7830",
    "addr:street":"Pave\u0301 D'Ath",
    "iso:country":"BE",
    "sg:address":"Pav\u00c9 D'ath 43",
    "sg:city":"Silly",
    "sg:orig_category":"Voertuigen",
    "sg:phone":"+32 68 55 20 81",
    "sg:postcode":"7830",
    "sg:province":"Hainaut",
    "wof:name":"Garage Robeys",
    "wof:placetype":"venue"
},
  "geometry": {"coordinates":[3.9434161186,50.6698226929],"type":"Point"}
}