{
  "type": "Feature",
  "properties": {
    "iso:country":"BE",
    "sg:address":"Leeuwerikstraat 24",
    "sg:city":"Lommel",
    "sg:orig_category":"Installatie van houten of kunststof schrijnwerk",
    "sg:phone":"+32 11 55 19 73",
    "sg:postcode":"3920",
    "sg:province":"Limburg",
    "wof:name":"Patrick Adriaens",
    "wof:placetype":"venue"
},
  "geometry": {"coordinates":[5.296640873,51.227848053],"type":"Point"}
}