{
  "type": "Feature",
  "properties": {
    "addr:full":"Monnikenhofbaan 4 Aalst Oost-Vlaanderen 9310",
    "addr:housenumber":"4",
    "addr:postcode":"9310",
    "addr:street":"Monnikenhofbaan",
    "iso:country":"BE",
    "sg:address":"Monnikenhofbaan 4",
    "sg:city":"Aalst",
    "sg:orig_category":"Rundveehouders Varkenskwekers",
    "sg:phone":"+32 53 77 03 33",
    "sg:postcode":"9310",
    "sg:province":"Oost-Vlaanderen",
    "wof:name":"Clement Vermoesen",
    "wof:placetype":"venue"
},
  "geometry": {"coordinates":[4.0818147659,50.965461731],"type":"Point"}
}