{
  "type": "Feature",
  "properties": {
    "addr:full":"Muizenvenstr 1 Turnhout Antwerpen 2300",
    "addr:housenumber":"1",
    "addr:postcode":"2300",
    "addr:street":"Muizenvenstr",
    "iso:country":"BE",
    "sg:address":"Muizenvenstr 1",
    "sg:city":"Turnhout",
    "sg:classifiers":[
        {
            "category":"Manufacturing",
            "subcategory":"Tools & Machinery",
            "type":"Manufacturing & Wholesale Goods"
        }
    ],
    "sg:phone":"+32 14 47 11 70",
    "sg:postcode":"2300",
    "sg:province":"Antwerpen",
    "sg:tags":[
        "metallurgy",
        "metalworking"
    ],
    "wof:name":"Fabory Centre Turnhout",
    "wof:placetype":"venue"
},
  "geometry": {"coordinates":[4.920363903,51.3064575195],"type":"Point"}
}