{
  "type": "Feature",
  "properties": {
    "addr:full":"Tiensevest 40 Leuven Vlaams-Brabant 3000",
    "addr:housenumber":"40",
    "addr:postcode":"3000",
    "addr:street":"Tiensevest",
    "iso:country":"BE",
    "sg:address":"Tiensevest 40",
    "sg:city":"Leuven",
    "sg:orig_category":"Artsen and specialisten",
    "sg:phone":"+32 16 22 35 26",
    "sg:postcode":"3000",
    "sg:province":"Vlaams-Brabant",
    "wof:name":"Ingele Casteels",
    "wof:placetype":"venue"
},
  "geometry": {"coordinates":[4.7150220871,50.8796043396],"type":"Point"}
}