{
  "type": "Feature",
  "properties": {
    "iso:country":"BE",
    "sg:address":"Kosterstraat 107",
    "sg:city":"Machelen (diegem)",
    "sg:classifiers":[
        {
            "category":"Wholesale",
            "subcategory":"Wine & Distilled Alcoholic Beverages",
            "type":"Manufacturing & Wholesale Goods"
        }
    ],
    "sg:phone":"+32 2 720 31 26",
    "sg:postcode":"1831",
    "sg:province":"Vlaams-Brabant",
    "sg:tags":[
        "whol",
        "-",
        "spirit",
        "mfg"
    ],
    "wof:name":"Maison Des Vignes (la)",
    "wof:placetype":"venue"
},
  "geometry": {"coordinates":[4.4372110367,50.8881874084],"type":"Point"}
}