{
  "type": "Feature",
  "properties": {
    "addr:full":"Rue Du Parc 39 La Louviere Hainaut 7100",
    "addr:housenumber":"39",
    "addr:postcode":"7100",
    "addr:street":"Rue Du Parc",
    "iso:country":"BE",
    "sg:address":"Rue Du Parc 39",
    "sg:city":"La Louviere",
    "sg:orig_category":"Artsen and specialisten",
    "sg:phone":"+32 64 22 08 29",
    "sg:postcode":"7100",
    "sg:province":"Hainaut",
    "wof:name":"Philippe Pi\u00c9ron",
    "wof:placetype":"venue"
},
  "geometry": {"coordinates":[4.1917262077,50.4760437012],"type":"Point"}
}