{
  "type": "Feature",
  "properties": {
    "iso:country":"BE",
    "sg:address":"Koning Albertstraat 8",
    "sg:city":"Diksmuide",
    "sg:classifiers":[
        {
            "category":"Professional",
            "subcategory":"Lawyer & Legal Services",
            "type":"Services"
        }
    ],
    "sg:phone":"+32 51 50 50 27",
    "sg:postcode":"8600",
    "sg:province":"West-Vlaanderen",
    "wof:name":"Blanckaert Jan Advocatenkantoor",
    "wof:placetype":"venue"
},
  "geometry": {"coordinates":[2.8638279438,51.0323982239],"type":"Point"}
}