{
  "type": "Feature",
  "properties": {
    "addr:full":"Chauss\u00c9e De Wavre 2047 Oudergem/auderghem Bruxelles-Capitale 1160",
    "addr:postcode":"2047;1160",
    "addr:street":"Chausse\u0301E De Wavre",
    "iso:country":"BE",
    "sg:address":"Chauss\u00c9e De Wavre 2047",
    "sg:city":"Oudergem/auderghem",
    "sg:orig_category":"R\u00e9cup\u00e9ration de mati\u00e8res m\u00e9talliques recyclables and d\u00e9molisseurs de voitures. V\u00e9hicules automobiles",
    "sg:phone":"+32 2 672 36 71",
    "sg:postcode":"1160",
    "sg:province":"Bruxelles-Capitale",
    "wof:name":"Rover",
    "wof:placetype":"venue"
},
  "geometry": {"coordinates":[4.4421901703,50.8102684021],"type":"Point"}
}