{
  "type": "Feature",
  "properties": {
    "addr:full":"Rietweg 3 Hoogstraten (meerle) Antwerpen 2328",
    "addr:housenumber":"3",
    "addr:postcode":"2328",
    "addr:street":"Rietweg",
    "iso:country":"BE",
    "sg:address":"Rietweg 3",
    "sg:city":"Hoogstraten (meerle)",
    "sg:classifiers":[
        {
            "category":"Farming",
            "subcategory":"Crops",
            "type":"Manufacturing & Wholesale Goods"
        }
    ],
    "sg:phone":"+32 3 315 78 42",
    "sg:postcode":"2328",
    "sg:province":"Antwerpen",
    "sg:tags":[
        "vegetable",
        "fruit",
        "-",
        "grower"
    ],
    "wof:name":"Martens J",
    "wof:placetype":"venue"
},
  "geometry": {"coordinates":[4.7727608681,51.4735298157],"type":"Point"}
}