{
  "type": "Feature",
  "properties": {
    "iso:country":"BE",
    "sg:address":"Drukpersstraat 13",
    "sg:city":"Brussel/bruxelles",
    "sg:orig_category":"Boekhouders",
    "sg:phone":"+32 2 217 83 65",
    "sg:postcode":"1000",
    "sg:province":"Bruxelles-Capitale",
    "wof:name":"Joseph Bex",
    "wof:placetype":"venue"
},
  "geometry": {"coordinates":[4.3664870262,50.8490219116],"type":"Point"}
}