{
  "type": "Feature",
  "properties": {
    "iso:country":"BE",
    "sg:address":"Naamsesteenweg 207",
    "sg:city":"Leuven (heverlee)",
    "sg:classifiers":[
        {
            "category":"Shopping",
            "subcategory":"Florist",
            "type":"Retail Goods"
        }
    ],
    "sg:phone":"+32 16 22 45 54",
    "sg:postcode":"3001",
    "sg:province":"Vlaams-Brabant",
    "wof:name":"Anthurium (de)",
    "wof:placetype":"venue"
},
  "geometry": {"coordinates":[4.6959400177,50.8626670837],"type":"Point"}
}