{
  "type": "Feature",
  "properties": {
    "iso:country":"BE",
    "sg:address":"Rue De Botrange 23",
    "sg:city":"Waimes/waimes",
    "sg:orig_category":"Boissons",
    "sg:phone":"+32 80 44 40 76",
    "sg:postcode":"4950",
    "sg:province":"Li\u00e8ge",
    "wof:name":"Le Millesime",
    "wof:placetype":"venue"
},
  "geometry": {"coordinates":[6.1215639114,50.4709320068],"type":"Point"}
}