{
  "type": "Feature",
  "properties": {
    "addr:full":"Ch.de Bruxelles 44 Charleroi Hainaut 6042",
    "addr:housenumber":"44",
    "addr:postcode":"6042",
    "addr:street":"Hainaut",
    "iso:country":"BE",
    "sg:address":"Ch.de Bruxelles 44",
    "sg:city":"Charleroi",
    "sg:orig_category":"Metaalafval, schrootrecyclage and sloperijen Onderdelen and accessoires voor auto's",
    "sg:phone":"+32 71 37 08 44",
    "sg:postcode":"6042",
    "sg:province":"Hainaut",
    "wof:name":"V-recup Japan Parts",
    "wof:placetype":"venue"
},
  "geometry": {"coordinates":[4.4398589134,50.4364547729],"type":"Point"}
}