{
  "type": "Feature",
  "properties": {
    "addr:full":"Dentergemstraat 10 Tielt West-Vlaanderen 8700",
    "addr:housenumber":"10",
    "addr:postcode":"8700",
    "addr:street":"Dentergemstraat",
    "iso:country":"BE",
    "sg:address":"Dentergemstraat 10",
    "sg:city":"Tielt",
    "sg:classifiers":[
        {
            "category":"Health Services",
            "subcategory":"Doctor",
            "type":"Services"
        }
    ],
    "sg:phone":"+32 51 40 56 66",
    "sg:postcode":"8700",
    "sg:province":"West-Vlaanderen",
    "sg:tags":[
        "medicinephysicians",
        "surgeon"
    ],
    "wof:name":"Beyls J P",
    "wof:placetype":"venue"
},
  "geometry": {"coordinates":[3.3582699299,50.9858207703],"type":"Point"}
}