{
  "type": "Feature",
  "properties": {
    "iso:country":"BE",
    "sg:address":"Schotense Steenweg 37",
    "sg:city":"Schotense Steenweg 37",
    "sg:orig_category":"Entretien and r\u00e9parations de machines de bureau and ordinateurs. Ordinateurs and \u00e9quipement informat",
    "sg:phone":"+32 3 326 46 46",
    "sg:postcode":"2100",
    "sg:province":"Antwerpen",
    "wof:name":"Digita Computers",
    "wof:placetype":"venue"
},
  "geometry": {"coordinates":[4.4759979248,51.2200813293],"type":"Point"}
}