{
  "type": "Feature",
  "properties": {
    "iso:country":"BE",
    "sg:address":"Zandstraat 15",
    "sg:city":"Begijnendijk",
    "sg:orig_category":"Producteurs de l\u00e9gumes",
    "sg:phone":"+32 16 53 41 27",
    "sg:postcode":"3130",
    "sg:province":"Vlaams-Brabant",
    "wof:name":"Herman Corsus",
    "wof:placetype":"venue"
},
  "geometry": {"coordinates":[4.768351078,51.0191955566],"type":"Point"}
}