{
  "type": "Feature",
  "properties": {
    "addr:full":"Rue Lieutenant Lippens 2 Etterbeek Bruxelles-Capitale 1040",
    "addr:housenumber":"2",
    "addr:postcode":"1040",
    "addr:street":"Rue Lieutenant Lippens",
    "iso:country":"BE",
    "sg:address":"Rue Lieutenant Lippens 2",
    "sg:city":"Etterbeek",
    "sg:orig_category":"Traducteurs and interpr\u00e8tes",
    "sg:phone":"+32 2 732 04 12",
    "sg:postcode":"1040",
    "sg:province":"Bruxelles-Capitale",
    "wof:name":"Shovelin M. Cbtip/bkvtf",
    "wof:placetype":"venue"
},
  "geometry": {"coordinates":[4.3958010674,50.8293914795],"type":"Point"}
}