{
  "type": "Feature",
  "properties": {
    "addr:full":"Dorpsstraat 58 Sint-martens-latem Oost-Vlaanderen 9831",
    "addr:housenumber":"58",
    "addr:postcode":"9831",
    "addr:street":"Dorpsstraat",
    "iso:country":"BE",
    "sg:address":"Dorpsstraat 58",
    "sg:city":"Sint-martens-latem",
    "sg:orig_category":"Eclairage et \u00e9quipements du foyer. Fleurs and plantes",
    "sg:phone":"+32 9 282 78 10",
    "sg:postcode":"9831",
    "sg:province":"Oost-Vlaanderen",
    "wof:name":"Huis Katrien",
    "wof:placetype":"venue"
},
  "geometry": {"coordinates":[3.6028769016,51.0068397522],"type":"Point"}
}