{
  "type": "Feature",
  "properties": {
    "iso:country":"BE",
    "sg:address":"Nieuwstraat 5",
    "sg:city":"Kortemark",
    "sg:orig_category":"Artsen and specialisten",
    "sg:phone":"+32 51 56 62 88",
    "sg:postcode":"8610",
    "sg:province":"West-Vlaanderen",
    "wof:name":"Stefaan Favoreel",
    "wof:placetype":"venue"
},
  "geometry": {"coordinates":[3.0442860126,51.027923584],"type":"Point"}
}