{
  "type": "Feature",
  "properties": {
    "iso:country":"BE",
    "sg:address":"Mollevijver 2",
    "sg:city":"Maldegem",
    "sg:orig_category":"Instituts de beaut\u00e9",
    "sg:phone":"+32 9 377 43 92",
    "sg:postcode":"9991",
    "sg:province":"Oost-Vlaanderen",
    "wof:name":"Filip Claeys",
    "wof:placetype":"venue"
},
  "geometry": {"coordinates":[3.5096099377,51.1874771118],"type":"Point"}
}