{
  "type": "Feature",
  "properties": {
    "iso:country":"BE",
    "sg:address":"Zeedijk 109",
    "sg:city":"Blankenberge",
    "sg:orig_category":"Equipement photographique",
    "sg:phone":"+32 50 41 64 43",
    "sg:postcode":"8370",
    "sg:province":"West-Vlaanderen",
    "wof:name":"Photo Hall",
    "wof:placetype":"venue"
},
  "geometry": {"coordinates":[3.1247119904,51.3153572083],"type":"Point"}
}