{
  "type": "Feature",
  "properties": {
    "addr:full":"Hoogstraat 54 Zutendaal Limburg 3690",
    "addr:housenumber":"54",
    "addr:postcode":"3690",
    "addr:street":"Hoogstraat",
    "iso:country":"BE",
    "sg:address":"Hoogstraat 54",
    "sg:city":"Zutendaal",
    "sg:classifiers":[
        {
            "category":"Real Estate",
            "subcategory":"Architect",
            "type":"Services"
        }
    ],
    "sg:phone":"+32 89 79 16 64",
    "sg:postcode":"3690",
    "sg:province":"Limburg",
    "wof:name":"Olaerts Kris Architectenbureau",
    "wof:placetype":"venue"
},
  "geometry": {"coordinates":[5.5681200027,50.9351119995],"type":"Point"}
}