{
  "type": "Feature",
  "properties": {
    "iso:country":"BE",
    "sg:address":"Hasseltweg 403a",
    "sg:city":"Genk",
    "sg:classifiers":[
        {
            "category":"Insurance",
            "subcategory":"Insurance Agent",
            "type":"Services"
        }
    ],
    "sg:phone":"+32 11 23 21 19",
    "sg:postcode":"3600",
    "sg:province":"Limburg",
    "sg:tags":[
        "broker"
    ],
    "wof:name":"Interduo Bvba",
    "wof:placetype":"venue"
},
  "geometry": {"coordinates":[5.4345149994,50.9573249817],"type":"Point"}
}