{
  "type": "Feature",
  "properties": {
    "addr:full":"Rue De Jalhay 44 Verviers (stembert) Li\u00e8ge 4801",
    "addr:housenumber":"44",
    "addr:postcode":"4801",
    "addr:street":"Rue De Jalhay",
    "iso:country":"BE",
    "sg:address":"Rue De Jalhay 44",
    "sg:city":"Verviers (stembert)",
    "sg:classifiers":[
        {
            "category":"Home & Garden",
            "subcategory":"Building Materials",
            "type":"Retail Goods"
        }
    ],
    "sg:phone":"+32 87 22 54 51",
    "sg:postcode":"4801",
    "sg:province":"Li\u00e8ge",
    "sg:tags":[
        "window"
    ],
    "wof:name":"Debert J",
    "wof:placetype":"venue"
},
  "geometry": {"coordinates":[5.8930549622,50.5922393799],"type":"Point"}
}