{
  "type": "Feature",
  "properties": {
    "iso:country":"BE",
    "sg:address":"Beeklaan 73",
    "sg:city":"Kortrijk",
    "sg:classifiers":[
        {
            "category":"Home & Garden",
            "subcategory":"Home Furnishings",
            "type":"Retail Goods"
        }
    ],
    "sg:phone":"+32 56 25 82 82",
    "sg:postcode":"8500",
    "sg:province":"West-Vlaanderen",
    "sg:tags":[
        "lampshade",
        "chandelier",
        "-"
    ],
    "wof:name":"Labeeuw Bvba",
    "wof:placetype":"venue"
},
  "geometry": {"coordinates":[3.2987070084,50.8120422363],"type":"Point"}
}