{
  "type": "Feature",
  "properties": {
    "iso:country":"BE",
    "sg:address":"Rue De Chimay 40ba",
    "sg:city":"Chimay",
    "sg:orig_category":"Elektrische installaties voor woningen",
    "sg:phone":"+32 60 21 31 10",
    "sg:postcode":"6461",
    "sg:province":"Hainaut",
    "wof:name":"Guy Paquet",
    "wof:placetype":"venue"
},
  "geometry": {"coordinates":[4.3290729523,50.0528030396],"type":"Point"}
}