{
  "type": "Feature",
  "properties": {
    "addr:full":"Rue Des Acacias 22 Kraainem Vlaams-Brabant 1950",
    "addr:housenumber":"22",
    "addr:postcode":"1950",
    "addr:street":"Rue Des Acacias",
    "iso:country":"BE",
    "sg:address":"Rue Des Acacias 22",
    "sg:city":"Kraainem",
    "sg:classifiers":[
        {
            "category":"Health Services",
            "subcategory":"Health Practitioner",
            "type":"Services"
        }
    ],
    "sg:phone":"+32 2 784 28 55",
    "sg:postcode":"1950",
    "sg:province":"Vlaams-Brabant",
    "sg:tags":[
        "osteopath"
    ],
    "wof:name":"Biart A-f",
    "wof:placetype":"venue"
},
  "geometry": {"coordinates":[4.4638237953,50.8499221802],"type":"Point"}
}