{
  "type": "Feature",
  "properties": {
    "addr:full":"Grand'route 22 Braffe Hainaut 7604",
    "addr:housenumber":"22",
    "addr:postcode":"7604",
    "addr:street":"Grand'Route;Hainaut",
    "iso:country":"BE",
    "sg:address":"Grand'route 22",
    "sg:city":"Braffe",
    "sg:orig_category":"Ramassage and traitement des d\u00e9chets m\u00e9nagers",
    "sg:phone":"+32 477 45 26 48",
    "sg:postcode":"7604",
    "sg:province":"Hainaut",
    "wof:name":"Etablissment Bruno",
    "wof:placetype":"venue"
},
  "geometry": {"coordinates":[3.5923399925,50.5101509094],"type":"Point"}
}