{
  "type": "Feature",
  "properties": {
    "iso:country":"BE",
    "sg:address":"Rue De Limoges 91",
    "sg:city":"Esneux (tilff)",
    "sg:classifiers":[
        {
            "category":"Professional",
            "type":"Services"
        }
    ],
    "sg:phone":"+32 4 388 27 11",
    "sg:postcode":"4130",
    "sg:province":"Li\u00e8ge",
    "sg:tags":[
        "surveyor",
        "-",
        "valuer"
    ],
    "wof:name":"Bureau Technique D'expertises",
    "wof:placetype":"venue"
},
  "geometry": {"coordinates":[5.5687270164,50.5659294128],"type":"Point"}
}