{
  "type": "Feature",
  "properties": {
    "addr:full":"Westkerksestraat 136 Oudenburg West-Vlaanderen 8460",
    "addr:housenumber":"136",
    "addr:postcode":"8460",
    "addr:street":"Westkerksestraat",
    "iso:country":"BE",
    "sg:address":"Westkerksestraat 136",
    "sg:city":"Oudenburg",
    "sg:classifiers":[
        {
            "category":"Insurance",
            "subcategory":"Insurance Agent",
            "type":"Services"
        }
    ],
    "sg:phone":"+32 59 26 86 33",
    "sg:postcode":"8460",
    "sg:province":"West-Vlaanderen",
    "sg:tags":[
        "verzekeringsmakelaars",
        "expert"
    ],
    "wof:name":"O. Vantyghem",
    "wof:placetype":"venue"
},
  "geometry": {"coordinates":[3.0074698925,51.1757888794],"type":"Point"}
}