{
  "type": "Feature",
  "properties": {
    "addr:full":"Albertstraat 13 Zwevegem West-Vlaanderen 8550",
    "addr:housenumber":"13",
    "addr:postcode":"8550",
    "addr:street":"Albertstraat",
    "iso:country":"BE",
    "sg:address":"Albertstraat 13",
    "sg:city":"Zwevegem",
    "sg:orig_category":"R\u00e9parations d'appareils \u00e9lectrom\u00e9nagers. Electrom\u00e9nager, t\u00e9l\u00e9visions and radios",
    "sg:phone":"+32 56 75 50 88",
    "sg:postcode":"8550",
    "sg:province":"West-Vlaanderen",
    "wof:name":"Jean Claerhout",
    "wof:placetype":"venue"
},
  "geometry": {"coordinates":[3.3371329308,50.8122520447],"type":"Point"}
}