{
  "type": "Feature",
  "properties": {
    "addr:full":"Klissenhoek 102 Vorselaar Antwerpen 2290",
    "addr:housenumber":"102",
    "addr:postcode":"2290",
    "addr:street":"Klissenhoek",
    "iso:country":"BE",
    "sg:address":"Klissenhoek 102",
    "sg:city":"Vorselaar",
    "sg:classifiers":[
        {
            "category":"Building & Trades",
            "subcategory":"Construction",
            "type":"Services"
        }
    ],
    "sg:phone":"+32 14 50 03 63",
    "sg:postcode":"2290",
    "sg:province":"Antwerpen",
    "sg:tags":[
        "insulation",
        "thermical",
        "work",
        "acoustical"
    ],
    "wof:name":"Janssens L",
    "wof:placetype":"venue"
},
  "geometry": {"coordinates":[4.7579131126,51.2202644348],"type":"Point"}
}