{
  "type": "Feature",
  "properties": {
    "iso:country":"BE",
    "sg:address":"Heerbaan 51",
    "sg:city":"Opwijk",
    "sg:classifiers":[
        {
            "category":"Insurance",
            "subcategory":"Insurance Agent",
            "type":"Services"
        }
    ],
    "sg:phone":"+32 52 35 63 16",
    "sg:postcode":"1745",
    "sg:province":"Vlaams-Brabant",
    "sg:tags":[
        "verzekeringsmakelaars",
        "expert"
    ],
    "wof:name":"Braeckmans",
    "wof:placetype":"venue"
},
  "geometry": {"coordinates":[4.168284893,50.9411239624],"type":"Point"}
}