{
  "type": "Feature",
  "properties": {
    "iso:country":"BE",
    "sg:address":"Place Des D\u00c9port\u00c9s 7ba21",
    "sg:city":"Li\u00c8ge",
    "sg:orig_category":"Advocaten and juridische adviseurs",
    "sg:phone":"+32 4 227 05 08",
    "sg:postcode":"4000",
    "sg:province":"Li\u00e8ge",
    "wof:name":"J. Raskin",
    "wof:placetype":"venue"
},
  "geometry": {"coordinates":[5.5858998299,50.6483764648],"type":"Point"}
}