{
  "type": "Feature",
  "properties": {
    "iso:country":"BE",
    "sg:address":"Rue De La Vall\u00c9e 117",
    "sg:city":"Ham-sur-heure-nalinnes",
    "sg:orig_category":"H\u00f4tels",
    "sg:phone":"+32 71 21 93 37",
    "sg:postcode":"6120",
    "sg:province":"Hainaut",
    "wof:name":"Laudanel",
    "wof:placetype":"venue"
},
  "geometry": {"coordinates":[4.4674949646,50.3476867676],"type":"Point"}
}