{
  "type": "Feature",
  "properties": {
    "iso:country":"BE",
    "sg:address":"Turnhoutsebaan 27",
    "sg:city":"Schilde",
    "sg:classifiers":[
        {
            "category":"Communications",
            "type":"Services"
        }
    ],
    "sg:phone":"+32 3 353 23 55",
    "sg:postcode":"2970",
    "sg:province":"Antwerpen",
    "sg:tags":[
        "translator"
    ],
    "wof:name":"Dierckx M. Vertaalbureau",
    "wof:placetype":"venue"
},
  "geometry": {"coordinates":[4.5587120056,51.2334060669],"type":"Point"}
}