{
  "type": "Feature",
  "properties": {
    "iso:country":"BE",
    "sg:address":"Industrielaan 9",
    "sg:city":"Eeklo",
    "sg:orig_category":"Non-Classified Establishments",
    "sg:phone":"+32 9 377 56 33",
    "sg:postcode":"9900",
    "sg:province":"Oost-Vlaanderen",
    "wof:name":"Christiaens J Nv",
    "wof:placetype":"venue"
},
  "geometry": {"coordinates":[3.5420119762,51.1820678711],"type":"Point"}
}