{
  "type": "Feature",
  "properties": {
    "iso:country":"BE",
    "sg:address":"Lourdesstraat 40",
    "sg:city":"Gent (oostakker)",
    "sg:classifiers":[
        {
            "category":"Health Services",
            "subcategory":"Health Practitioner",
            "type":"Services"
        }
    ],
    "sg:phone":"+32 9 251 46 24",
    "sg:postcode":"9041",
    "sg:province":"Oost-Vlaanderen",
    "sg:tags":[
        "physiotherapist"
    ],
    "wof:name":"Verlaet L",
    "wof:placetype":"venue"
},
  "geometry": {"coordinates":[3.7550981045,51.0784034729],"type":"Point"}
}