{
  "type": "Feature",
  "properties": {
    "addr:full":"Chauss\u00e9e De Waterloo 235 Bruxelles (saint-gilles) Bruxelles-Capitale 1060",
    "addr:housenumber":"235",
    "addr:postcode":"1060",
    "addr:street":"Chausse\u0301E De Waterloo",
    "iso:country":"BE",
    "sg:address":"Chauss\u00e9e De Waterloo 235",
    "sg:city":"Bruxelles (saint-gilles)",
    "sg:orig_category":"Non-Classified Establishments",
    "sg:phone":"+32 2 539 04 39",
    "sg:postcode":"1060",
    "sg:province":"Bruxelles-Capitale",
    "wof:name":"Cotrem Sprl",
    "wof:placetype":"venue"
},
  "geometry": {"coordinates":[4.3481731415,50.8252029419],"type":"Point"}
}