{
  "type": "Feature",
  "properties": {
    "iso:country":"BE",
    "sg:address":"Rue Du Calvaire 7",
    "sg:city":"Jurbise (herchies)",
    "sg:classifiers":[
        {
            "category":"Retail",
            "subcategory":"Funeral Services",
            "type":"Services"
        }
    ],
    "sg:phone":"+32 65 22 95 03",
    "sg:postcode":"7050",
    "sg:province":"Hainaut",
    "sg:tags":[
        "director"
    ],
    "wof:name":"Berresse",
    "wof:placetype":"venue"
},
  "geometry": {"coordinates":[3.8588221073,50.5280647278],"type":"Point"}
}