{
  "type": "Feature",
  "properties": {
    "iso:country":"BE",
    "sg:address":"Joris Van Oostenrijkstr. 10",
    "sg:city":"Hasselt",
    "sg:orig_category":"Fleurs and plantes",
    "sg:phone":"+32 11 25 47 08",
    "sg:postcode":"3511",
    "sg:province":"Limburg",
    "wof:name":"Bloemen Edelweiss",
    "wof:placetype":"venue"
},
  "geometry": {"coordinates":[5.3059091568,50.9408073425],"type":"Point"}
}