{
  "type": "Feature",
  "properties": {
    "addr:full":"Mechelsesteenweg 20b4 Heist-op-den-berg Antwerpen 2220",
    "addr:housenumber":"20b4",
    "addr:postcode":"2220",
    "addr:street":"Mechelsesteenweg",
    "iso:country":"BE",
    "sg:address":"Mechelsesteenweg 20b4",
    "sg:city":"Heist-op-den-berg",
    "sg:orig_category":"Artsen and specialisten",
    "sg:phone":"+32 15 24 34 92",
    "sg:postcode":"2220",
    "sg:province":"Antwerpen",
    "wof:name":"Johan Willems",
    "wof:placetype":"venue"
},
  "geometry": {"coordinates":[4.7042169571,51.0727462769],"type":"Point"}
}