{
  "type": "Feature",
  "properties": {
    "iso:country":"BE",
    "sg:address":"Avenue Joseph Pr\u00e9vers 3",
    "sg:city":"Li\u00e8ge 1 (jupille-sur-meuse)",
    "sg:classifiers":[
        {
            "category":"Social Services",
            "subcategory":"Job Training",
            "type":"Services"
        }
    ],
    "sg:phone":"+32 4 377 29 05",
    "sg:postcode":"4020",
    "sg:province":"Li\u00e8ge",
    "sg:tags":[
        "personnel"
    ],
    "wof:name":"K.l. & Partners",
    "wof:placetype":"venue"
},
  "geometry": {"coordinates":[5.6257519722,50.6473426819],"type":"Point"}
}