{
  "type": "Feature",
  "properties": {
    "addr:full":"Pappotstraat 4 Ieper West-Vlaanderen 8902",
    "addr:housenumber":"4",
    "addr:postcode":"8902",
    "addr:street":"Pappotstraat",
    "iso:country":"BE",
    "sg:address":"Pappotstraat 4",
    "sg:city":"Ieper",
    "sg:orig_category":"Rundveehouders",
    "sg:phone":"+32 57 46 61 76",
    "sg:postcode":"8902",
    "sg:province":"West-Vlaanderen",
    "wof:name":"Marc Devos",
    "wof:placetype":"venue"
},
  "geometry": {"coordinates":[2.9445259571,50.8285713196],"type":"Point"}
}