{
  "type": "Feature",
  "properties": {
    "iso:country":"BE",
    "sg:address":"Oudenbos 70ba",
    "sg:city":"Aarschot",
    "sg:orig_category":"Pleisterwerk",
    "sg:phone":"+32 16 50 00 67",
    "sg:postcode":"3202",
    "sg:province":"Vlaams-Brabant",
    "wof:name":"Patrick Isenborghs",
    "wof:placetype":"venue"
},
  "geometry": {"coordinates":[4.9005708694,50.9661560059],"type":"Point"}
}