{
  "type": "Feature",
  "properties": {
    "addr:full":"Klaverzuringstraat 4 Watermaal-bosvoorde/watermael-boitsfort Bruxelles-Capitale 1170",
    "addr:housenumber":"4",
    "addr:postcode":"1170",
    "addr:street":"Klaverzuringstraat",
    "iso:country":"BE",
    "sg:address":"Klaverzuringstraat 4",
    "sg:city":"Watermaal-bosvoorde/watermael-boitsfort",
    "sg:orig_category":"Verlichting and huishoudartikelen",
    "sg:phone":"+32 2 673 71 65",
    "sg:postcode":"1170",
    "sg:province":"Bruxelles-Capitale",
    "wof:name":"Van Steensel/denis Van Steensel",
    "wof:placetype":"venue"
},
  "geometry": {"coordinates":[4.4246788025,50.8103485107],"type":"Point"}
}