{
  "type": "Feature",
  "properties": {
    "iso:country":"BE",
    "sg:address":"Steenputstraat 16",
    "sg:city":"Oudenaarde",
    "sg:orig_category":"Forge, Moulage and Profilage des M\u00e9taux. Plomberie, chauffage and installations sanitaires",
    "sg:phone":"+32 55 31 03 42",
    "sg:postcode":"9700",
    "sg:province":"Oost-Vlaanderen",
    "wof:name":"Sanirev",
    "wof:placetype":"venue"
},
  "geometry": {"coordinates":[3.6354999542,50.8633270264],"type":"Point"}
}