{
  "type": "Feature",
  "properties": {
    "addr:full":"Tabaksvest 49 Antwerpen Antwerpen 2000",
    "addr:housenumber":"49",
    "addr:postcode":"2000",
    "addr:street":"Tabaksvest",
    "iso:country":"BE",
    "sg:address":"Tabaksvest 49",
    "sg:city":"Antwerpen",
    "sg:classifiers":[
        {
            "category":"Professional",
            "subcategory":"Computer Services",
            "type":"Services"
        }
    ],
    "sg:phone":"+32 3 226 62 33",
    "sg:postcode":"2000",
    "sg:province":"Antwerpen",
    "sg:tags":[
        "webdesign",
        "-",
        "internet"
    ],
    "wof:name":"Protelco Vzw",
    "wof:placetype":"venue"
},
  "geometry": {"coordinates":[4.410572052,51.2140007019],"type":"Point"}
}