{
  "type": "Feature",
  "properties": {
    "addr:full":"Pannemeersstraat 1 Ruiselede West-Vlaanderen 8755",
    "addr:housenumber":"1",
    "addr:postcode":"8755",
    "addr:street":"Pannemeersstraat",
    "iso:country":"BE",
    "sg:address":"Pannemeersstraat 1",
    "sg:city":"Ruiselede",
    "sg:orig_category":"Rundveehouders Varkenskwekers",
    "sg:phone":"+32 51 68 83 20",
    "sg:postcode":"8755",
    "sg:province":"West-Vlaanderen",
    "wof:name":"Frans Declercq",
    "wof:placetype":"venue"
},
  "geometry": {"coordinates":[3.4101009369,51.0389404297],"type":"Point"}
}