{
  "type": "Feature",
  "properties": {
    "iso:country":"BE",
    "sg:address":"Rue De La Creugette 12",
    "sg:city":"Hamois",
    "sg:orig_category":"Enseignement maternel and primaire",
    "sg:phone":"+32 83 61 19 90",
    "sg:postcode":"5360",
    "sg:province":"Namur",
    "wof:name":"Ecole Prim. Communale",
    "wof:placetype":"venue"
},
  "geometry": {"coordinates":[5.1714801788,50.3380203247],"type":"Point"}
}