{
  "type": "Feature",
  "properties": {
    "iso:country":"BE",
    "sg:address":"Rue Pierre Timmermans 34",
    "sg:city":"Jette/jette",
    "sg:orig_category":"V\u00eatements",
    "sg:phone":"+32 2 428 41 22",
    "sg:postcode":"1090",
    "sg:province":"Bruxelles-Capitale",
    "wof:name":"Fe. Boterman",
    "wof:placetype":"venue"
},
  "geometry": {"coordinates":[4.3236551285,50.8735542297],"type":"Point"}
}