{
  "type": "Feature",
  "properties": {
    "addr:full":"Vinkstraat 13 Haacht (tildonk) Vlaams-Brabant 3150",
    "addr:housenumber":"13",
    "addr:postcode":"3150",
    "addr:street":"Vinkstraat",
    "iso:country":"BE",
    "sg:address":"Vinkstraat 13",
    "sg:city":"Haacht (tildonk)",
    "sg:classifiers":[
        {
            "category":"Health Services",
            "subcategory":"Health Practitioner",
            "type":"Services"
        }
    ],
    "sg:phone":"+32 16 60 96 71",
    "sg:postcode":"3150",
    "sg:province":"Vlaams-Brabant",
    "sg:tags":[
        "physiotherapist"
    ],
    "wof:name":"Laridon Katrien",
    "wof:placetype":"venue"
},
  "geometry": {"coordinates":[4.672041893,50.9566001892],"type":"Point"}
}