{
  "type": "Feature",
  "properties": {
    "iso:country":"BE",
    "sg:address":"Leuvense Steenweg 102",
    "sg:city":"Sint-joost-ten-node/saint-josse-ten-noode",
    "sg:orig_category":"Boekhouders",
    "sg:phone":"+32 2 230 04 22",
    "sg:postcode":"1210",
    "sg:province":"Bruxelles-Capitale",
    "wof:name":"Liliane Marage",
    "wof:placetype":"venue"
},
  "geometry": {"coordinates":[4.3737359047,50.8497467041],"type":"Point"}
}