{
  "type": "Feature",
  "properties": {
    "iso:country":"BE",
    "sg:address":"Brichautstraat 9",
    "sg:city":"Schaarbeek/schaerbeek",
    "sg:orig_category":"Boekhouders",
    "sg:phone":"+32 2 241 12 39",
    "sg:postcode":"1030",
    "sg:province":"Bruxelles-Capitale",
    "wof:name":"Eric De Becker",
    "wof:placetype":"venue"
},
  "geometry": {"coordinates":[4.3675408363,50.863571167],"type":"Point"}
}