{
  "type": "Feature",
  "properties": {
    "addr:full":"Nijsstraat 7a Oud-heverlee Vlaams-Brabant 3052",
    "addr:housenumber":"7a",
    "addr:postcode":"3052",
    "addr:street":"Nijsstraat",
    "iso:country":"BE",
    "sg:address":"Nijsstraat 7a",
    "sg:city":"Oud-heverlee",
    "sg:orig_category":"Installation \u00e9lectrique r\u00e9sidentielle",
    "sg:phone":"+32 16 40 06 05",
    "sg:postcode":"3052",
    "sg:province":"Vlaams-Brabant",
    "wof:name":"Geuvers",
    "wof:placetype":"venue"
},
  "geometry": {"coordinates":[4.7123150826,50.8256187439],"type":"Point"}
}