{
  "type": "Feature",
  "properties": {
    "iso:country":"BE",
    "sg:address":"Fays 25",
    "sg:city":"Ciney (ach\u00eane)",
    "sg:classifiers":[
        {
            "category":"Health Services",
            "subcategory":"Health Practitioner",
            "type":"Services"
        }
    ],
    "sg:phone":"+32 83 21 37 23",
    "sg:postcode":"5590",
    "sg:province":"Namur",
    "sg:tags":[
        "physiotherapist"
    ],
    "wof:name":"Leboutte J",
    "wof:placetype":"venue"
},
  "geometry": {"coordinates":[5.1022520065,50.297088623],"type":"Point"}
}