{
  "type": "Feature",
  "properties": {
    "iso:country":"BE",
    "sg:address":"Markt 16",
    "sg:city":"Deinze",
    "sg:classifiers":[
        {
            "category":"Health Services",
            "subcategory":"Doctor",
            "type":"Services"
        }
    ],
    "sg:phone":"+32 9 386 10 99",
    "sg:postcode":"9800",
    "sg:province":"Oost-Vlaanderen",
    "sg:tags":[
        "medicinephysicians",
        "surgeon"
    ],
    "wof:name":"De Busser\u00e9 Andr\u00e9",
    "wof:placetype":"venue"
},
  "geometry": {"coordinates":[3.5268599987,50.9835014343],"type":"Point"}
}