{
  "type": "Feature",
  "properties": {
    "addr:full":"Rue Du Pont D\u00b4avroy 20 Liege-centre Li\u00e8ge 4000",
    "addr:housenumber":"20",
    "addr:postcode":"4000",
    "addr:street":"Rue Du Pont D\u00b4Avroy",
    "iso:country":"BE",
    "sg:address":"Rue Du Pont D\u00b4avroy 20",
    "sg:city":"Liege-centre",
    "sg:classifiers":[
        {
            "category":"Utilities",
            "subcategory":"Telephone",
            "type":"Services"
        }
    ],
    "sg:phone":"+32 4 220 97 60",
    "sg:postcode":"4000",
    "sg:province":"Li\u00e8ge",
    "sg:tags":[
        "house",
        "phone",
        "telecommunicatieapparaten"
    ],
    "wof:name":"The Phone House",
    "wof:placetype":"venue"
},
  "geometry": {"coordinates":[6.2250900269,44.0888595581],"type":"Point"}
}