{
  "type": "Feature",
  "properties": {
    "addr:full":"Molenstraat 55 Baarle-hertog Antwerpen 2387",
    "addr:housenumber":"55",
    "addr:postcode":"2387",
    "addr:street":"Molenstraat",
    "iso:country":"BE",
    "sg:address":"Molenstraat 55",
    "sg:city":"Baarle-hertog",
    "sg:classifiers":[
        {
            "category":"Retail",
            "subcategory":"Event Space",
            "type":"Services"
        }
    ],
    "sg:phone":"+32 14 69 91 21",
    "sg:postcode":"2387",
    "sg:province":"Antwerpen",
    "sg:tags":[
        "rental",
        "-",
        "hall"
    ],
    "wof:name":"Olympia",
    "wof:placetype":"venue"
},
  "geometry": {"coordinates":[4.9326148033,51.4399452209],"type":"Point"}
}