{
  "type": "Feature",
  "properties": {
    "addr:full":"Nieuwstraat 41-43 Tienen Vlaams-Brabant 3300",
    "addr:postcode":"41-43;3300",
    "addr:street":"Nieuwstraat",
    "iso:country":"BE",
    "sg:address":"Nieuwstraat 41-43",
    "sg:city":"Tienen",
    "sg:classifiers":[
        {
            "category":"Travel",
            "subcategory":"Campground",
            "type":"Entertainment"
        }
    ],
    "sg:phone":"+32 16 81 54 53",
    "sg:postcode":"3300",
    "sg:province":"Vlaams-Brabant",
    "sg:tags":[
        "good"
    ],
    "wof:name":"Mia Style Bvba",
    "wof:placetype":"venue"
},
  "geometry": {"coordinates":[4.9396729469,50.8065605164],"type":"Point"}
}