{
  "type": "Feature",
  "properties": {
    "iso:country":"BE",
    "sg:address":"Bergstrasse 10",
    "sg:city":"Eupen",
    "sg:classifiers":[
        {
            "category":"Shopping",
            "subcategory":"Clothing, Apparel, & Fashions",
            "type":"Retail Goods"
        }
    ],
    "sg:phone":"+32 87 55 44 33",
    "sg:postcode":"4700",
    "sg:province":"Li\u00e8ge",
    "sg:tags":[
        "lady",
        "clothing",
        "-"
    ],
    "wof:name":"Splash",
    "wof:placetype":"venue"
},
  "geometry": {"coordinates":[6.0335798264,50.6299362183],"type":"Point"}
}