{
  "type": "Feature",
  "properties": {
    "addr:full":"Bruggestraat 28b Menen West-Vlaanderen 8930",
    "addr:housenumber":"28b",
    "addr:postcode":"8930",
    "addr:street":"Bruggestraat",
    "iso:country":"BE",
    "sg:address":"Bruggestraat 28b",
    "sg:city":"Menen",
    "sg:orig_category":"Immobili\u00ebnkantoren",
    "sg:phone":"+32 56 53 05 30",
    "sg:postcode":"8930",
    "sg:province":"West-Vlaanderen",
    "wof:name":"Benoot",
    "wof:placetype":"venue"
},
  "geometry": {"coordinates":[3.1216080189,50.7970161438],"type":"Point"}
}