{
  "type": "Feature",
  "properties": {
    "iso:country":"BE",
    "sg:address":"Nieder Emmels 100a",
    "sg:city":"Sankt Vith (crombach)",
    "sg:classifiers":[
        {
            "category":"Home & Garden",
            "subcategory":"Carpets & Floor Coverings",
            "type":"Retail Goods"
        }
    ],
    "sg:phone":"+32 80 22 89 30",
    "sg:postcode":"4784",
    "sg:province":"Li\u00e8ge",
    "sg:tags":[
        "-"
    ],
    "wof:name":"Berens A.g. Sa",
    "wof:placetype":"venue"
},
  "geometry": {"coordinates":[6.091219902,50.3113288879],"type":"Point"}
}