{
  "type": "Feature",
  "properties": {
    "iso:country":"BE",
    "sg:address":"Diestsestraat 10ba",
    "sg:city":"Kortenaken",
    "sg:orig_category":"M\u00e9decines alternatives",
    "sg:phone":"+32 11 58 30 52",
    "sg:postcode":"3470",
    "sg:province":"Vlaams-Brabant",
    "wof:name":"Claudine Casier",
    "wof:placetype":"venue"
},
  "geometry": {"coordinates":[5.0612201691,50.9141654968],"type":"Point"}
}