{
  "type": "Feature",
  "properties": {
    "iso:country":"BE",
    "sg:address":"Zeelaan 98",
    "sg:city":"De Panne",
    "sg:orig_category":"Voedingsspeciaalzaken",
    "sg:phone":"+32 58 41 18 10",
    "sg:postcode":"8660",
    "sg:province":"West-Vlaanderen",
    "wof:name":"Santos Palace",
    "wof:placetype":"venue"
},
  "geometry": {"coordinates":[2.5923728943,51.0994720459],"type":"Point"}
}