{
  "type": "Feature",
  "properties": {
    "iso:country":"BE",
    "sg:address":"Oude Brugseweg 270",
    "sg:city":"Oudenburg (roksem)",
    "sg:classifiers":[
        {
            "category":"Professional",
            "subcategory":"Engineering",
            "type":"Services"
        }
    ],
    "sg:phone":"+32 50 81 42 27",
    "sg:postcode":"8460",
    "sg:province":"West-Vlaanderen",
    "sg:tags":[
        "workshop"
    ],
    "wof:name":"Herpoele D",
    "wof:placetype":"venue"
},
  "geometry": {"coordinates":[3.0495140553,51.172794342],"type":"Point"}
}