{
  "type": "Feature",
  "properties": {
    "iso:country":"BE",
    "sg:address":"Chauss\u00c9e De Malines 130",
    "sg:city":"Wezembeek-oppem",
    "sg:orig_category":"Pharmaciens",
    "sg:phone":"+32 2 731 33 67",
    "sg:postcode":"1970",
    "sg:province":"Vlaams-Brabant",
    "wof:name":"I. Stevens",
    "wof:placetype":"venue"
},
  "geometry": {"coordinates":[4.4937500954,50.8400688171],"type":"Point"}
}