{
  "type": "Feature",
  "properties": {
    "addr:full":"Rue De L'h\u00f4tel Des Monnaies 120 Bruxelles (saint-gilles) Bruxelles-Capitale 1060",
    "addr:housenumber":"120",
    "addr:postcode":"1060",
    "addr:street":"Rue De L'Ho;Des Monnaies",
    "iso:country":"BE",
    "sg:address":"Rue De L'h\u00f4tel Des Monnaies 120",
    "sg:city":"Bruxelles (saint-gilles)",
    "sg:classifiers":[
        {
            "category":"Education",
            "subcategory":"Special Training",
            "type":"Public Place"
        }
    ],
    "sg:phone":"+32 2 534 64 32",
    "sg:postcode":"1060",
    "sg:province":"Bruxelles-Capitale",
    "sg:tags":[
        "-",
        "processing",
        "data"
    ],
    "wof:name":"Cristal Qui Songe",
    "wof:placetype":"venue"
},
  "geometry": {"coordinates":[4.3471632004,50.8294715881],"type":"Point"}
}