{
  "type": "Feature",
  "properties": {
    "addr:full":"Chauss\u00e9e De Ninove 770 Bruxelles (anderlecht) Bruxelles-Capitale 1070",
    "addr:housenumber":"770",
    "addr:postcode":"1070",
    "addr:street":"Chausse\u0301E De Ninove",
    "iso:country":"BE",
    "sg:address":"Chauss\u00e9e De Ninove 770",
    "sg:city":"Bruxelles (anderlecht)",
    "sg:orig_category":"Non-Classified Establishments",
    "sg:phone":"+32 2 527 42 35",
    "sg:postcode":"1070",
    "sg:province":"Bruxelles-Capitale",
    "wof:name":"Tessilform Distribution Sprl",
    "wof:placetype":"venue"
},
  "geometry": {"coordinates":[4.2938799858,50.8462295532],"type":"Point"}
}