{
  "type": "Feature",
  "properties": {
    "addr:full":"Monnikenwerve 12 Brugge West-Vlaanderen 8000",
    "addr:housenumber":"12",
    "addr:postcode":"8000",
    "addr:street":"Monnikenwerve",
    "iso:country":"BE",
    "sg:address":"Monnikenwerve 12",
    "sg:city":"Brugge",
    "sg:classifiers":[
        {
            "category":"Wholesale",
            "subcategory":"Meat",
            "type":"Manufacturing & Wholesale Goods"
        }
    ],
    "sg:phone":"+32 50 31 27 20",
    "sg:postcode":"8000",
    "sg:province":"West-Vlaanderen",
    "sg:tags":[
        "whol",
        "-"
    ],
    "wof:name":"Hoste Joseph & Zn Bvba",
    "wof:placetype":"venue"
},
  "geometry": {"coordinates":[3.1977291107,51.2478637695],"type":"Point"}
}