{
  "type": "Feature",
  "properties": {
    "iso:country":"BE",
    "sg:address":"Stationsstraat 36",
    "sg:city":"Nazareth (eke)",
    "sg:classifiers":[
        {
            "category":"Health Services",
            "subcategory":"Dentist",
            "type":"Services"
        }
    ],
    "sg:phone":"+32 9 385 85 02",
    "sg:postcode":"9810",
    "sg:province":"Oost-Vlaanderen",
    "wof:name":"D'huyvetter Eva",
    "wof:placetype":"venue"
},
  "geometry": {"coordinates":[3.6383099556,50.9575614929],"type":"Point"}
}