{
  "type": "Feature",
  "properties": {
    "iso:country":"BE",
    "sg:address":"Avenue Des M\u00c9tallurgistes 7",
    "sg:city":"Court-saint-etienne",
    "sg:orig_category":"Technische studies and ingenieursactiviteiten",
    "sg:phone":"+32 10 62 06 00",
    "sg:postcode":"1490",
    "sg:province":"Brabant Wallon",
    "wof:name":"Gamaco Ing\u00c9nieurs - Conseil",
    "wof:placetype":"venue"
},
  "geometry": {"coordinates":[4.5655741692,50.6531486511],"type":"Point"}
}