{
  "type": "Feature",
  "properties": {
    "addr:full":"Aalbeeksestraat 165 Kortrijk (rollegem) West-Vlaanderen 8510",
    "addr:housenumber":"165",
    "addr:postcode":"8510",
    "addr:street":"Aalbeeksestraat",
    "iso:country":"BE",
    "sg:address":"Aalbeeksestraat 165",
    "sg:city":"Kortrijk (rollegem)",
    "sg:classifiers":[
        {
            "category":"Transit Center",
            "subcategory":"Passenger",
            "type":"Transportation"
        }
    ],
    "sg:phone":"+32 56 42 25 93",
    "sg:postcode":"8510",
    "sg:province":"West-Vlaanderen",
    "sg:tags":[
        "taxidermist"
    ],
    "wof:name":"Bels D",
    "wof:placetype":"venue"
},
  "geometry": {"coordinates":[3.245773077,50.7736282349],"type":"Point"}
}