{
  "type": "Feature",
  "properties": {
    "addr:full":"Rue De La Montagne 48 Bruxelles Bruxelles-Capitale 1000",
    "addr:housenumber":"48",
    "addr:postcode":"1000",
    "addr:street":"Rue De La Montagne",
    "iso:country":"BE",
    "sg:address":"Rue De La Montagne 48",
    "sg:city":"Bruxelles",
    "sg:classifiers":[
        {
            "category":"Bars & Pubs",
            "type":"Food & Drink"
        }
    ],
    "sg:phone":"+32 2 514 03 10",
    "sg:postcode":"1000",
    "sg:province":"Bruxelles-Capitale",
    "wof:name":"Caf\u00e9 Des Banques",
    "wof:placetype":"venue"
},
  "geometry": {"coordinates":[4.3561058044,50.8473434448],"type":"Point"}
}