{
  "type": "Feature",
  "properties": {
    "addr:full":"Rue Du Gazom\u00c8tre 68 Fleurus Hainaut 6220",
    "addr:housenumber":"68",
    "addr:postcode":"6220",
    "addr:street":"Rue Du Gazome\u0300Tre",
    "iso:country":"BE",
    "sg:address":"Rue Du Gazom\u00c8tre 68",
    "sg:city":"Fleurus",
    "sg:classifiers":[
        {
            "category":"Arena",
            "subcategory":"Sports Club",
            "type":"Entertainment"
        }
    ],
    "sg:phone":"+32 71 81 67 84",
    "sg:postcode":"6220",
    "sg:province":"Hainaut",
    "sg:tags":[
        "terrain",
        "hors",
        "de",
        "installation",
        "sportifs"
    ],
    "wof:name":"A.s. Cheminots Ligne 140",
    "wof:placetype":"venue"
},
  "geometry": {"coordinates":[4.5428600311,50.4807510376],"type":"Point"}
}