{
  "type": "Feature",
  "properties": {
    "addr:full":"Gentsestraat 61 Izegem West-Vlaanderen 8870",
    "addr:housenumber":"61",
    "addr:postcode":"8870",
    "addr:street":"Gentsestraat",
    "iso:country":"BE",
    "sg:address":"Gentsestraat 61",
    "sg:city":"Izegem",
    "sg:orig_category":"Banques and organismes de cr\u00e9dit",
    "sg:phone":"+32 51 31 50 12",
    "sg:postcode":"8870",
    "sg:province":"West-Vlaanderen",
    "wof:name":"Kbc",
    "wof:placetype":"venue"
},
  "geometry": {"coordinates":[3.2193100452,50.9165115356],"type":"Point"}
}