{
  "type": "Feature",
  "properties": {
    "addr:full":"Europarklaan 38 Houthalen-helchteren Limburg 3530",
    "addr:housenumber":"38",
    "addr:postcode":"3530",
    "addr:street":"Europarklaan",
    "iso:country":"BE",
    "sg:address":"Europarklaan 38",
    "sg:city":"Houthalen-helchteren",
    "sg:classifiers":[
        {
            "category":"Arena",
            "subcategory":"Sports Club",
            "type":"Entertainment"
        }
    ],
    "sg:phone":"+32 11 52 42 80",
    "sg:postcode":"3530",
    "sg:province":"Limburg",
    "sg:tags":[
        "terrain",
        "hors",
        "de",
        "installation",
        "sportifs"
    ],
    "wof:name":"Red Star Laak",
    "wof:placetype":"venue"
},
  "geometry": {"coordinates":[5.3909878731,51.0352935791],"type":"Point"}
}