{
  "type": "Feature",
  "properties": {
    "iso:country":"BE",
    "sg:address":"Kerkstraat 34",
    "sg:city":"Lommel",
    "sg:classifiers":[
        {
            "category":"Restaurant",
            "type":"Food & Drink"
        }
    ],
    "sg:phone":"+32 11 55 30 87",
    "sg:postcode":"3920",
    "sg:province":"Limburg",
    "wof:name":"L'olivo",
    "wof:placetype":"venue"
},
  "geometry": {"coordinates":[5.3115758896,51.2297439575],"type":"Point"}
}