{
  "type": "Feature",
  "properties": {
    "iso:country":"BE",
    "sg:address":"Moerkerkse Steenweg 250",
    "sg:city":"Brugge (sint-kruis)",
    "sg:classifiers":[
        {
            "category":"Personal",
            "subcategory":"Sauna",
            "type":"Services"
        }
    ],
    "sg:phone":"+32 50 36 05 91",
    "sg:postcode":"8310",
    "sg:province":"West-Vlaanderen",
    "wof:name":"Deynique Estetiek",
    "wof:placetype":"venue"
},
  "geometry": {"coordinates":[3.2554531097,51.2142219543],"type":"Point"}
}