{
  "type": "Feature",
  "properties": {
    "addr:full":"Rue De La R\u00e2perie 19 Hannut (lens-saint-remy) Li\u00e8ge 4280",
    "addr:housenumber":"19",
    "addr:postcode":"4280",
    "addr:street":"Rue De La Ra\u0302Perie;Lens-Saint-Remy",
    "iso:country":"BE",
    "sg:address":"Rue De La R\u00e2perie 19",
    "sg:city":"Hannut (lens-saint-remy)",
    "sg:classifiers":[
        {
            "category":"Retail",
            "subcategory":"Auto Repair",
            "type":"Services"
        }
    ],
    "sg:phone":"+32 19 51 17 21",
    "sg:postcode":"4280",
    "sg:province":"Li\u00e8ge",
    "sg:tags":[
        "truck-body"
    ],
    "wof:name":"Lens Motor",
    "wof:placetype":"venue"
},
  "geometry": {"coordinates":[5.1270079613,50.6489982605],"type":"Point"}
}