{
  "type": "Feature",
  "properties": {
    "iso:country":"BE",
    "sg:address":"Raaftuinweg Z/n",
    "sg:city":"Ravels",
    "sg:classifiers":[
        {
            "category":"Arena",
            "subcategory":"Sports Club",
            "type":"Entertainment"
        }
    ],
    "sg:phone":"+32 14 65 69 19",
    "sg:postcode":"2380",
    "sg:province":"Antwerpen",
    "sg:tags":[
        "terrain",
        "hors",
        "de",
        "installation",
        "sportifs"
    ],
    "wof:name":"Kfc Flandria",
    "wof:placetype":"venue"
},
  "geometry": {"coordinates":[4.9936499596,51.370929718],"type":"Point"}
}