{
  "type": "Feature",
  "properties": {
    "iso:country":"BE",
    "sg:address":"Kasteelstraat 16",
    "sg:city":"Wortegem-petegem (wortegem)",
    "sg:classifiers":[
        {
            "category":"Health Services",
            "subcategory":"Nursing And Care Facility",
            "type":"Services"
        }
    ],
    "sg:phone":"+32 56 68 73 50",
    "sg:postcode":"9790",
    "sg:province":"Oost-Vlaanderen",
    "sg:tags":[
        "home"
    ],
    "wof:name":"Martens S",
    "wof:placetype":"venue"
},
  "geometry": {"coordinates":[3.491106987,50.8682899475],"type":"Point"}
}