{
  "type": "Feature",
  "properties": {
    "iso:country":"BE",
    "sg:address":"Rue De L'ecole 5",
    "sg:city":"Somme-leuze",
    "sg:orig_category":"Rundveehouders",
    "sg:phone":"+32 86 32 29 49",
    "sg:postcode":"5377",
    "sg:province":"Namur",
    "wof:name":"Marie Deroua",
    "wof:placetype":"venue"
},
  "geometry": {"coordinates":[5.369890213,50.3404312134],"type":"Point"}
}