{
  "type": "Feature",
  "properties": {
    "iso:country":"BE",
    "sg:address":"Sint-antoniusbaan 295",
    "sg:city":"Zoersel",
    "sg:classifiers":[
        {
            "category":"Health Services",
            "subcategory":"Health Practitioner",
            "type":"Services"
        }
    ],
    "sg:phone":"+32 3 383 68 09",
    "sg:postcode":"2980",
    "sg:province":"Antwerpen",
    "sg:tags":[
        "physiotherapist"
    ],
    "wof:name":"Goossens Annick",
    "wof:placetype":"venue"
},
  "geometry": {"coordinates":[4.6509599686,51.2668800354],"type":"Point"}
}