{
  "type": "Feature",
  "properties": {
    "addr:full":"Rue Du Mar\u00c9chal 2 Helecine Brabant Wallon 1357",
    "addr:housenumber":"2",
    "addr:postcode":"1357",
    "addr:street":"Rue Du Mare\u0301Chal",
    "iso:country":"BE",
    "sg:address":"Rue Du Mar\u00c9chal 2",
    "sg:city":"Helecine",
    "sg:orig_category":"Woningbouw",
    "sg:phone":"+32 19 65 65 19",
    "sg:postcode":"1357",
    "sg:province":"Brabant Wallon",
    "wof:name":"Thinic",
    "wof:placetype":"venue"
},
  "geometry": {"coordinates":[4.9853448868,50.7396430969],"type":"Point"}
}