{
  "type": "Feature",
  "properties": {
    "addr:full":"Demerstraat 81 Box 10 Hasselt Limburg 3500",
    "addr:housenumber":"81 box 10",
    "addr:postcode":"3500",
    "addr:street":"Demerstraat",
    "iso:country":"BE",
    "sg:address":"Demerstraat 81 Box 10",
    "sg:city":"Hasselt",
    "sg:classifiers":[
        {
            "category":"Real Estate",
            "subcategory":"Architect",
            "type":"Services"
        }
    ],
    "sg:phone":"+32 11 23 53 90",
    "sg:postcode":"3500",
    "sg:province":"Limburg",
    "wof:name":"Vaes F",
    "wof:placetype":"venue"
},
  "geometry": {"coordinates":[5.338906765,50.9329681396],"type":"Point"}
}