{
  "type": "Feature",
  "properties": {
    "addr:full":"Magdalenasteenweg 46 Mechelen Antwerpen 2812",
    "addr:housenumber":"46",
    "addr:postcode":"2812",
    "addr:street":"Magdalenasteenweg",
    "iso:country":"BE",
    "sg:address":"Magdalenasteenweg 46",
    "sg:city":"Mechelen",
    "sg:orig_category":"Banques and organismes de cr\u00e9dit",
    "sg:phone":"+32 15 41 32 31",
    "sg:postcode":"2812",
    "sg:province":"Antwerpen",
    "wof:name":"Dexia",
    "wof:placetype":"venue"
},
  "geometry": {"coordinates":[4.5149431229,51.0088806152],"type":"Point"}
}