{
  "type": "Feature",
  "properties": {
    "addr:full":"Heiend 58 Lille Antwerpen 2275",
    "addr:housenumber":"58",
    "addr:postcode":"2275",
    "addr:street":"Heiend",
    "iso:country":"BE",
    "sg:address":"Heiend 58",
    "sg:city":"Lille",
    "sg:classifiers":[
        {
            "category":"Banks & Credit Unions",
            "subcategory":"Investment Brokerage",
            "type":"Services"
        }
    ],
    "sg:phone":"+32 14 88 12 67",
    "sg:postcode":"2275",
    "sg:province":"Antwerpen",
    "sg:tags":[
        "fence"
    ],
    "wof:name":"Verbraken-de Bie",
    "wof:placetype":"venue"
},
  "geometry": {"coordinates":[4.8171191216,51.2338447571],"type":"Point"}
}