{
  "type": "Feature",
  "properties": {
    "addr:full":"Nekkerspoelstraat 97 Mechelen Antwerpen 2800",
    "addr:housenumber":"97",
    "addr:postcode":"2800",
    "addr:street":"Nekkerspoelstraat",
    "iso:country":"BE",
    "sg:address":"Nekkerspoelstraat 97",
    "sg:city":"Mechelen",
    "sg:orig_category":"Advocaten and juridische adviseurs",
    "sg:phone":"+32 15 55 68 90",
    "sg:postcode":"2800",
    "sg:province":"Antwerpen",
    "wof:name":"Jan Vrijdaghs",
    "wof:placetype":"venue"
},
  "geometry": {"coordinates":[4.4939727783,51.0311431885],"type":"Point"}
}