{
  "type": "Feature",
  "properties": {
    "addr:full":"Lijsterstraat 32 Zulte Oost-Vlaanderen 9870",
    "addr:housenumber":"32",
    "addr:postcode":"9870",
    "addr:street":"Lijsterstraat",
    "iso:country":"BE",
    "sg:address":"Lijsterstraat 32",
    "sg:city":"Zulte",
    "sg:classifiers":[
        {
            "category":"Professional",
            "subcategory":"Computer Services",
            "type":"Services"
        }
    ],
    "sg:phone":"+32 9 385 76 86",
    "sg:postcode":"9870",
    "sg:province":"Oost-Vlaanderen",
    "sg:tags":[
        "webdesign",
        "-",
        "internet"
    ],
    "wof:name":"Demeyer T",
    "wof:placetype":"venue"
},
  "geometry": {"coordinates":[3.4516429901,50.9241600037],"type":"Point"}
}