{
  "type": "Feature",
  "properties": {
    "addr:full":"Rue Reine-astrid 28 Rochefort Namur 5580",
    "addr:housenumber":"28",
    "addr:postcode":"5580",
    "addr:street":"Rue Reine-Astrid",
    "iso:country":"BE",
    "sg:address":"Rue Reine-astrid 28",
    "sg:city":"Rochefort",
    "sg:orig_category":"Artsen and specialisten",
    "sg:phone":"+32 84 22 12 82",
    "sg:postcode":"5580",
    "sg:province":"Namur",
    "wof:name":"Isabelle Evrard",
    "wof:placetype":"venue"
},
  "geometry": {"coordinates":[5.2200670242,50.1605186462],"type":"Point"}
}