{
  "type": "Feature",
  "properties": {
    "addr:full":"Antwerpsestraat 26b7 Diest Vlaams-Brabant 3290",
    "addr:housenumber":"26b7",
    "addr:postcode":"3290",
    "addr:street":"Antwerpsestraat",
    "iso:country":"BE",
    "sg:address":"Antwerpsestraat 26b7",
    "sg:city":"Diest",
    "sg:orig_category":"Entretien and r\u00e9parations de machines de bureau and ordinateurs",
    "sg:phone":"+32 13 32 66 66",
    "sg:postcode":"3290",
    "sg:province":"Vlaams-Brabant",
    "wof:name":"Lich",
    "wof:placetype":"venue"
},
  "geometry": {"coordinates":[5.0556077957,50.9904403687],"type":"Point"}
}