{
  "type": "Feature",
  "properties": {
    "addr:full":"Vooruitgangsstraat 22 Ieper West-Vlaanderen 8900",
    "addr:housenumber":"22",
    "addr:postcode":"8900",
    "addr:street":"Vooruitgangsstraat",
    "iso:country":"BE",
    "sg:address":"Vooruitgangsstraat 22",
    "sg:city":"Ieper",
    "sg:classifiers":[
        {
            "category":"Cafe",
            "type":"Food & Drink"
        }
    ],
    "sg:phone":"+32 57 20 19 90",
    "sg:postcode":"8900",
    "sg:province":"West-Vlaanderen",
    "sg:tags":[
        "caf\u00e9s"
    ],
    "wof:name":"Caf\u00c9 Esplanade",
    "wof:placetype":"venue"
},
  "geometry": {"coordinates":[2.880325079,50.8486289978],"type":"Point"}
}