{
  "type": "Feature",
  "properties": {
    "iso:country":"BE",
    "sg:address":"Vijfstraat 27",
    "sg:city":"Meulebeke",
    "sg:orig_category":"Eleveurs de bovins. Producteurs de l\u00e9gumes",
    "sg:phone":"+32 51 48 84 73",
    "sg:postcode":"8760",
    "sg:province":"West-Vlaanderen",
    "wof:name":"Daniel Simoens",
    "wof:placetype":"venue"
},
  "geometry": {"coordinates":[3.3135800362,50.9638710022],"type":"Point"}
}