{
  "type": "Feature",
  "properties": {
    "addr:full":"Roeselaarsestraat 393 Izegem West-Vlaanderen 8870",
    "addr:housenumber":"393",
    "addr:postcode":"8870",
    "addr:street":"Roeselaarsestraat",
    "iso:country":"BE",
    "sg:address":"Roeselaarsestraat 393",
    "sg:city":"Izegem",
    "sg:orig_category":"Dakwerken",
    "sg:phone":"+32 51 30 82 49",
    "sg:postcode":"8870",
    "sg:province":"West-Vlaanderen",
    "wof:name":"Dak-en Asfaltwerken Ameye",
    "wof:placetype":"venue"
},
  "geometry": {"coordinates":[3.1884300709,50.9246292114],"type":"Point"}
}