{
  "type": "Feature",
  "properties": {
    "addr:full":"Hanendreef 93 Brasschaat Antwerpen 2930",
    "addr:housenumber":"93",
    "addr:postcode":"2930",
    "addr:street":"Hanendreef",
    "iso:country":"BE",
    "sg:address":"Hanendreef 93",
    "sg:city":"Brasschaat",
    "sg:classifiers":[
        {
            "category":"Insurance",
            "subcategory":"Insurance Agent",
            "type":"Services"
        }
    ],
    "sg:phone":"+32 3 651 41 19",
    "sg:postcode":"2930",
    "sg:province":"Antwerpen",
    "sg:tags":[
        "verzekeringsmakelaars",
        "expert"
    ],
    "wof:name":"Vereecke En Zonen",
    "wof:placetype":"venue"
},
  "geometry": {"coordinates":[4.4795589447,51.2958488464],"type":"Point"}
}