{
  "type": "Feature",
  "properties": {
    "addr:full":"Rue De L'epine 49 Charleroi Hainaut 6061",
    "addr:housenumber":"49",
    "addr:postcode":"6061",
    "addr:street":"Rue De L'Epine;Hainaut",
    "iso:country":"BE",
    "sg:address":"Rue De L'epine 49",
    "sg:city":"Charleroi",
    "sg:orig_category":"Ordinateurs and \u00e9quipement informatique. Assistances juridiques. R\u00e9alisation de programmes and logic",
    "sg:phone":"+32 71 28 19 90",
    "sg:postcode":"6061",
    "sg:province":"Hainaut",
    "wof:name":"Anthonissen C",
    "wof:placetype":"venue"
},
  "geometry": {"coordinates":[4.4710688591,50.4160995483],"type":"Point"}
}