{
  "type": "Feature",
  "properties": {
    "iso:country":"BE",
    "sg:address":"Stormramstraat 10",
    "sg:city":"Evergem",
    "sg:orig_category":"Entretien and r\u00e9parations de voitures",
    "sg:phone":"+32 9 344 68 12",
    "sg:postcode":"9940",
    "sg:province":"Oost-Vlaanderen",
    "wof:name":"Philip Van Wynsberge",
    "wof:placetype":"venue"
},
  "geometry": {"coordinates":[3.7376050949,51.1725311279],"type":"Point"}
}