{
  "type": "Feature",
  "properties": {
    "iso:country":"BE",
    "sg:address":"Weg Naar Zwartberg 75",
    "sg:city":"Opglabbeek",
    "sg:orig_category":"Installation de menuiserie en bois and plastique. Meubles Fab. Meubles D\u00e9taillants, Am\u00e9nagement de B",
    "sg:phone":"+32 89 85 66 92",
    "sg:postcode":"3660",
    "sg:province":"Limburg",
    "wof:name":"Pro-line",
    "wof:placetype":"venue"
},
  "geometry": {"coordinates":[5.5765647888,51.0417747498],"type":"Point"}
}