{
  "type": "Feature",
  "properties": {
    "addr:full":"Markegemsesteenweg 14 Dentergem West-Vlaanderen 8720",
    "addr:housenumber":"14",
    "addr:postcode":"8720",
    "addr:street":"Markegemsesteenweg",
    "iso:country":"BE",
    "sg:address":"Markegemsesteenweg 14",
    "sg:city":"Dentergem",
    "sg:classifiers":[
        {
            "category":"Building & Trades",
            "subcategory":"Pest Control",
            "type":"Services"
        }
    ],
    "sg:phone":"+32 51 63 34 41",
    "sg:postcode":"8720",
    "sg:province":"West-Vlaanderen",
    "sg:tags":[
        "painting",
        "contractor"
    ],
    "wof:name":"Galle J",
    "wof:placetype":"venue"
},
  "geometry": {"coordinates":[3.41771698,50.9627113342],"type":"Point"}
}