{
  "type": "Feature",
  "properties": {
    "addr:full":"Weg Naar As 89 Genk Limburg 3600",
    "addr:housenumber":"89",
    "addr:postcode":"3600",
    "addr:street":"Weg Naar As",
    "iso:country":"BE",
    "sg:address":"Weg Naar As 89",
    "sg:city":"Genk",
    "sg:classifiers":[
        {
            "category":"Fast Food",
            "type":"Food & Drink"
        }
    ],
    "sg:phone":"+32 89 30 37 46",
    "sg:postcode":"3600",
    "sg:province":"Limburg",
    "sg:tags":[
        "meeneem",
        "restaurant"
    ],
    "wof:name":"Marc",
    "wof:placetype":"venue"
},
  "geometry": {"coordinates":[5.5340800285,50.982219696],"type":"Point"}
}