{
  "type": "Feature",
  "properties": {
    "addr:full":"Harelbekestraat 89 Deerlijk West-Vlaanderen 8540",
    "addr:housenumber":"89",
    "addr:postcode":"8540",
    "addr:street":"Harelbekestraat",
    "iso:country":"BE",
    "sg:address":"Harelbekestraat 89",
    "sg:city":"Deerlijk",
    "sg:classifiers":[
        {
            "category":"Building & Trades",
            "subcategory":"Construction",
            "type":"Services"
        }
    ],
    "sg:phone":"+32 56 72 39 30",
    "sg:postcode":"8540",
    "sg:province":"West-Vlaanderen",
    "sg:tags":[
        "installation",
        "-",
        "central",
        "heating"
    ],
    "wof:name":"Saverel",
    "wof:placetype":"venue"
},
  "geometry": {"coordinates":[3.3485610485,50.8523406982],"type":"Point"}
}