{
  "type": "Feature",
  "properties": {
    "addr:full":"Kerkstraat 4 Mechelen Antwerpen 2812",
    "addr:housenumber":"4",
    "addr:postcode":"2812",
    "addr:street":"Kerkstraat",
    "iso:country":"BE",
    "sg:address":"Kerkstraat 4",
    "sg:city":"Mechelen",
    "sg:orig_category":"Plaatsen van vloer- and muurbekleding Schilders",
    "sg:phone":"+32 15 43 24 46",
    "sg:postcode":"2812",
    "sg:province":"Antwerpen",
    "wof:name":"Peeters Patrick Et J\u00c9r\u00d4me",
    "wof:placetype":"venue"
},
  "geometry": {"coordinates":[4.5135359764,51.010597229],"type":"Point"}
}