{
  "type": "Feature",
  "properties": {
    "iso:country":"BE",
    "sg:address":"Grote Markt 15",
    "sg:city":"Herentals",
    "sg:orig_category":"Zuivelproducten",
    "sg:phone":"+32 14 21 14 18",
    "sg:postcode":"2200",
    "sg:province":"Antwerpen",
    "wof:name":"Huis Verwimp",
    "wof:placetype":"venue"
},
  "geometry": {"coordinates":[4.8359022141,51.1764945984],"type":"Point"}
}