{
  "type": "Feature",
  "properties": {
    "addr:full":"Generaal Belliardstraat 21 Antwerpen Antwerpen 2000",
    "addr:housenumber":"21",
    "addr:postcode":"2000",
    "addr:street":"Generaal Belliardstraat",
    "iso:country":"BE",
    "sg:address":"Generaal Belliardstraat 21",
    "sg:city":"Antwerpen",
    "sg:classifiers":[
        {
            "category":"Airport",
            "type":"Transportation"
        }
    ],
    "sg:phone":"+32 3 233 68 00",
    "sg:postcode":"2000",
    "sg:province":"Antwerpen",
    "sg:tags":[
        "air-freight",
        "forwarders"
    ],
    "wof:name":"Atramef Nv",
    "wof:placetype":"venue"
},
  "geometry": {"coordinates":[4.4073958397,51.2259674072],"type":"Point"}
}