{
  "type": "Feature",
  "properties": {
    "addr:full":"Albert I Laan 39 Vilvoorde Vlaams-Brabant 1800",
    "addr:housenumber":"39",
    "addr:postcode":"1800",
    "addr:street":"Albert I Laan",
    "iso:country":"BE",
    "sg:address":"Albert I Laan 39",
    "sg:city":"Vilvoorde",
    "sg:classifiers":[
        {
            "category":"Cafe",
            "type":"Food & Drink"
        }
    ],
    "sg:phone":"+32 2 251 50 91",
    "sg:postcode":"1800",
    "sg:province":"Vlaams-Brabant",
    "sg:tags":[
        "snack-bars"
    ],
    "wof:name":"Ring (de)",
    "wof:placetype":"venue"
},
  "geometry": {"coordinates":[4.4039740562,50.9199256897],"type":"Point"}
}