{
  "type": "Feature",
  "properties": {
    "iso:country":"BE",
    "sg:address":"Justus Lipsiusstraat 34",
    "sg:city":"Leuven",
    "sg:classifiers":[
        {
            "category":"Insurance",
            "subcategory":"Insurance Agent",
            "type":"Services"
        }
    ],
    "sg:phone":"+32 16 58 46 90",
    "sg:postcode":"3000",
    "sg:province":"Vlaams-Brabant",
    "sg:tags":[
        "broker"
    ],
    "wof:name":"Eurasca Houthalen Nv",
    "wof:placetype":"venue"
},
  "geometry": {"coordinates":[4.7120928764,50.879535675],"type":"Point"}
}