{
  "type": "Feature",
  "properties": {
    "iso:country":"BE",
    "sg:address":"Route De Philippeville 195",
    "sg:city":"Charleroi (marcinelle)",
    "sg:classifiers":[
        {
            "category":"Autos & Motor Vehicles",
            "subcategory":"Fuel & Gas Station",
            "type":"Retail Goods"
        }
    ],
    "sg:phone":"+32 71 36 16 71",
    "sg:postcode":"6001",
    "sg:province":"Hainaut",
    "wof:name":"Scipioni",
    "wof:placetype":"venue"
},
  "geometry": {"coordinates":[4.4553771019,50.3967247009],"type":"Point"}
}