{
  "type": "Feature",
  "properties": {
    "addr:full":"Bisschopslaan 71 Beerse Antwerpen 2340",
    "addr:housenumber":"71",
    "addr:postcode":"2340",
    "addr:street":"Bisschopslaan",
    "iso:country":"BE",
    "sg:address":"Bisschopslaan 71",
    "sg:city":"Beerse",
    "sg:classifiers":[
        {
            "category":"Utilities",
            "subcategory":"Water",
            "type":"Services"
        }
    ],
    "sg:phone":"+32 3 226 34 56",
    "sg:postcode":"2340",
    "sg:province":"Antwerpen",
    "sg:tags":[
        "softener"
    ],
    "wof:name":"Aa-algemene Ontstoppingsdienst",
    "wof:placetype":"venue"
},
  "geometry": {"coordinates":[4.8563680649,51.3107566833],"type":"Point"}
}