{
  "type": "Feature",
  "properties": {
    "addr:full":"Chauss\u00c9e De Tournai 15 Leuze-en-hainaut Hainaut 7904",
    "addr:housenumber":"15",
    "addr:postcode":"7904",
    "addr:street":"Chausse\u0301E De Tournai",
    "iso:country":"BE",
    "sg:address":"Chauss\u00c9e De Tournai 15",
    "sg:city":"Leuze-en-hainaut",
    "sg:classifiers":[
        {
            "category":"Restaurant",
            "type":"Food & Drink"
        }
    ],
    "sg:phone":"+32 69 66 44 07",
    "sg:postcode":"7904",
    "sg:province":"Hainaut",
    "wof:name":"R\u00d4tisserie De Beloeil",
    "wof:placetype":"venue"
},
  "geometry": {"coordinates":[3.5931339264,50.5953559875],"type":"Point"}
}