{
  "type": "Feature",
  "properties": {
    "addr:full":"Rue Heyvaert 167 Bruxelles (anderlecht) Bruxelles-Capitale 1070",
    "addr:housenumber":"167",
    "addr:postcode":"1070",
    "addr:street":"Rue Heyvaert",
    "iso:country":"BE",
    "sg:address":"Rue Heyvaert 167",
    "sg:city":"Bruxelles (anderlecht)",
    "sg:classifiers":[
        {
            "category":"Professional",
            "subcategory":"Art Services",
            "type":"Services"
        }
    ],
    "sg:phone":"+32 2 522 00 48",
    "sg:postcode":"1070",
    "sg:province":"Bruxelles-Capitale",
    "sg:tags":[
        "automobile",
        "transit",
        "-",
        "export",
        "import"
    ],
    "wof:name":"Hamouda Export Sprl",
    "wof:placetype":"venue"
},
  "geometry": {"coordinates":[4.3295850754,50.8451004028],"type":"Point"}
}