{
  "type": "Feature",
  "properties": {
    "addr:full":"Bosdreef 10 Lochristi Oost-Vlaanderen 9080",
    "addr:housenumber":"10",
    "addr:postcode":"9080",
    "addr:street":"Bosdreef",
    "iso:country":"BE",
    "sg:address":"Bosdreef 10",
    "sg:city":"Lochristi",
    "sg:orig_category":"Plantes and fleurs Gr",
    "sg:phone":"+32 9 355 72 53",
    "sg:postcode":"9080",
    "sg:province":"Oost-Vlaanderen",
    "wof:name":"Van Der Straeten W",
    "wof:placetype":"venue"
},
  "geometry": {"coordinates":[3.8387548923,51.0955734253],"type":"Point"}
}