{
  "type": "Feature",
  "properties": {
    "addr:full":"Atomiumsquare 0 Brussel/bruxelles Bruxelles-Capitale 1020",
    "addr:housenumber":"0",
    "addr:postcode":"1020",
    "addr:street":"Atomiumsquare;/",
    "iso:country":"BE",
    "sg:address":"Atomiumsquare 0",
    "sg:city":"Brussel/bruxelles",
    "sg:orig_category":"Winkelinrichting and handelsuitrusting Gh",
    "sg:phone":"+32 2 478 84 17",
    "sg:postcode":"1020",
    "sg:province":"Bruxelles-Capitale",
    "wof:name":"W.m.f.",
    "wof:placetype":"venue"
},
  "geometry": {"coordinates":[4.3419442177,50.895149231],"type":"Point"}
}