{
  "type": "Feature",
  "properties": {
    "iso:country":"BE",
    "sg:address":"Rue Th\u00e9odor Kl\u00fcber 8",
    "sg:city":"Dottignies",
    "sg:classifiers":[
        {
            "category":"Education",
            "subcategory":"Special Training",
            "type":"Public Place"
        }
    ],
    "sg:phone":"+32 56 48 38 38",
    "sg:postcode":"7711",
    "sg:province":"Hainaut",
    "sg:tags":[
        "technical",
        "felt",
        "purpose"
    ],
    "wof:name":"Procotex Corporation N.v./ S.a.",
    "wof:placetype":"venue"
},
  "geometry": {"coordinates":[3.2985730171,50.7206840515],"type":"Point"}
}