{
  "type": "Feature",
  "properties": {
    "iso:country":"BE",
    "sg:address":"Vosseslag 91",
    "sg:city":"De Haan (klemskerke)",
    "sg:classifiers":[
        {
            "category":"Fast Food",
            "type":"Food & Drink"
        }
    ],
    "sg:phone":"+32 59 23 65 53",
    "sg:postcode":"8420",
    "sg:province":"West-Vlaanderen",
    "sg:tags":[
        "fried",
        "stand",
        "potato"
    ],
    "wof:name":"Rita",
    "wof:placetype":"venue"
},
  "geometry": {"coordinates":[3.0090959072,51.257358551],"type":"Point"}
}