{
  "type": "Feature",
  "properties": {
    "addr:full":"Rue Des Iguanodons 30 Bernissart Hainaut 7320",
    "addr:housenumber":"30",
    "addr:postcode":"7320",
    "addr:street":"Rue Des Iguanodons",
    "iso:country":"BE",
    "sg:address":"Rue Des Iguanodons 30",
    "sg:city":"Bernissart",
    "sg:classifiers":[
        {
            "category":"Utilities",
            "subcategory":"Fuel Oil & Lpg",
            "type":"Services"
        }
    ],
    "sg:phone":"+32 69 57 50 97",
    "sg:postcode":"7320",
    "sg:province":"Hainaut",
    "wof:name":"Calorhome",
    "wof:placetype":"venue"
},
  "geometry": {"coordinates":[3.6556639671,50.4876403809],"type":"Point"}
}