{
  "type": "Feature",
  "properties": {
    "addr:full":"Solbossquare 1 Elsene/ixelles Bruxelles-Capitale 1050",
    "addr:housenumber":"1",
    "addr:postcode":"1050",
    "addr:street":"Solbossquare",
    "iso:country":"BE",
    "sg:address":"Solbossquare 1",
    "sg:city":"Elsene/ixelles",
    "sg:classifiers":[
        {
            "category":"Restaurant",
            "type":"Food & Drink"
        }
    ],
    "sg:phone":"+32 2 640 22 18",
    "sg:postcode":"1050",
    "sg:province":"Bruxelles-Capitale",
    "wof:name":"Le Matignon",
    "wof:placetype":"venue"
},
  "geometry": {"coordinates":[4.3862118721,50.8103370667],"type":"Point"}
}