{
  "type": "Feature",
  "properties": {
    "iso:country":"BE",
    "sg:address":"Terrasstraat 168",
    "sg:city":"Zottegem (sint-maria-oudenhove)",
    "sg:classifiers":[
        {
            "category":"Building & Trades",
            "subcategory":"Construction",
            "type":"Services"
        }
    ],
    "sg:phone":"+32 55 42 10 19",
    "sg:postcode":"9620",
    "sg:province":"Oost-Vlaanderen",
    "sg:tags":[
        "carpenter"
    ],
    "wof:name":"Haegeman D",
    "wof:placetype":"venue"
},
  "geometry": {"coordinates":[3.8075530529,50.8261184692],"type":"Point"}
}