{
  "type": "Feature",
  "properties": {
    "addr:full":"Huzarenberg 16 Stabroek Antwerpen 2940",
    "addr:housenumber":"16",
    "addr:postcode":"2940",
    "addr:street":"Huzarenberg",
    "iso:country":"BE",
    "sg:address":"Huzarenberg 16",
    "sg:city":"Stabroek",
    "sg:orig_category":"Diverse meubelen Fab Installatie van metalen schrijnwerk",
    "sg:phone":"+32 3 664 98 19",
    "sg:postcode":"2940",
    "sg:province":"Antwerpen",
    "wof:name":"Elmecon",
    "wof:placetype":"venue"
},
  "geometry": {"coordinates":[4.3917059898,51.3496665955],"type":"Point"}
}