{
  "type": "Feature",
  "properties": {
    "addr:full":"Rue De Menin 42 Mouscron Hainaut 7700",
    "addr:housenumber":"42",
    "addr:postcode":"7700",
    "addr:street":"Rue De Menin",
    "iso:country":"BE",
    "sg:address":"Rue De Menin 42",
    "sg:city":"Mouscron",
    "sg:classifiers":[
        {
            "category":"Health Services",
            "subcategory":"Doctor",
            "type":"Services"
        }
    ],
    "sg:phone":"+32 56 34 44 77",
    "sg:postcode":"7700",
    "sg:province":"Hainaut",
    "sg:tags":[
        "medicinephysicians",
        "surgeon"
    ],
    "wof:name":"Kistiaens Rita",
    "wof:placetype":"venue"
},
  "geometry": {"coordinates":[3.2150249481,50.7468261719],"type":"Point"}
}