{
  "type": "Feature",
  "properties": {
    "iso:country":"BE",
    "sg:address":"Tailles 43",
    "sg:city":"Houffalize",
    "sg:orig_category":"Eleveurs de bovins",
    "sg:phone":"+32 80 41 88 36",
    "sg:postcode":"6661",
    "sg:province":"Luxembourg",
    "wof:name":"Albert Cougnet",
    "wof:placetype":"venue"
},
  "geometry": {"coordinates":[5.7424798012,50.2272109985],"type":"Point"}
}