{
  "type": "Feature",
  "properties": {
    "iso:country":"BE",
    "sg:address":"Waterstraat 100",
    "sg:city":"Menen",
    "sg:orig_category":"Installation \u00e9lectrique r\u00e9sidentielle",
    "sg:phone":"+32 56 40 31 15",
    "sg:postcode":"8930",
    "sg:province":"West-Vlaanderen",
    "wof:name":"Philip Fabry",
    "wof:placetype":"venue"
},
  "geometry": {"coordinates":[3.1422801018,50.7909698486],"type":"Point"}
}