{
  "type": "Feature",
  "properties": {
    "addr:full":"Hutveld 24a Ranst (emblem) Antwerpen 2520",
    "addr:housenumber":"24a",
    "addr:postcode":"2520",
    "addr:street":"Hutveld",
    "iso:country":"BE",
    "sg:address":"Hutveld 24a",
    "sg:city":"Ranst (emblem)",
    "sg:classifiers":[
        {
            "category":"Building & Trades",
            "subcategory":"Landscaping Services",
            "type":"Services"
        }
    ],
    "sg:phone":"+32 3 488 52 02",
    "sg:postcode":"2520",
    "sg:province":"Antwerpen",
    "sg:tags":[
        "nurseryman"
    ],
    "wof:name":"Van Dessel W",
    "wof:placetype":"venue"
},
  "geometry": {"coordinates":[4.5766010284,51.1602935791],"type":"Point"}
}