{
  "type": "Feature",
  "properties": {
    "addr:full":"Kleine Heerweg 2 Waregem West-Vlaanderen 8791",
    "addr:housenumber":"2",
    "addr:postcode":"8791",
    "addr:street":"Kleine Heerweg",
    "iso:country":"BE",
    "sg:address":"Kleine Heerweg 2",
    "sg:city":"Waregem",
    "sg:classifiers":[
        {
            "category":"Personal",
            "subcategory":"Beauty Salon",
            "type":"Services"
        }
    ],
    "sg:phone":"+32 56 70 04 00",
    "sg:postcode":"8791",
    "sg:province":"West-Vlaanderen",
    "sg:tags":[
        "de",
        "coiffure"
    ],
    "wof:name":"Coiffure Linda",
    "wof:placetype":"venue"
},
  "geometry": {"coordinates":[3.3430380821,50.876663208],"type":"Point"}
}