{
  "type": "Feature",
  "properties": {
    "addr:full":"Thomas-bouquillonstraat 30 Komen-waasten/comines-warneton Hainaut 7784",
    "addr:housenumber":"30;7784",
    "addr:street":"Thomas-Bouquillonstraat",
    "iso:country":"BE",
    "sg:address":"Thomas-bouquillonstraat 30",
    "sg:city":"Komen-waasten/comines-warneton",
    "sg:orig_category":"WAPENS AND MUNITIE",
    "sg:phone":"+32 56 55 53 54",
    "sg:postcode":"7784",
    "sg:province":"Hainaut",
    "wof:name":"Maison Deconinck",
    "wof:placetype":"venue"
},
  "geometry": {"coordinates":[2.9385099411,50.738319397],"type":"Point"}
}