{
  "type": "Feature",
  "properties": {
    "addr:full":"Kerkstraat 41 Laarne Oost-Vlaanderen 9270",
    "addr:housenumber":"41",
    "addr:postcode":"9270",
    "addr:street":"Kerkstraat",
    "iso:country":"BE",
    "sg:address":"Kerkstraat 41",
    "sg:city":"Laarne",
    "sg:orig_category":"Gespecialiseerde residenti\u00eble bouw Woningbouw",
    "sg:phone":"+32 9 366 17 67",
    "sg:postcode":"9270",
    "sg:province":"Oost-Vlaanderen",
    "wof:name":"Fa. Versluys Andr\u00c9 & Zn",
    "wof:placetype":"venue"
},
  "geometry": {"coordinates":[3.8637061119,51.0380592346],"type":"Point"}
}