{
  "type": "Feature",
  "properties": {
    "iso:country":"BE",
    "sg:address":"Kruisdreef 2",
    "sg:city":"Zomergem",
    "sg:classifiers":[
        {
            "category":"Shopping",
            "subcategory":"Baby Store",
            "type":"Retail Goods"
        }
    ],
    "sg:phone":"+32 9 372 75 74",
    "sg:postcode":"9930",
    "sg:province":"Oost-Vlaanderen",
    "sg:tags":[
        "midwife"
    ],
    "wof:name":"De Backer G",
    "wof:placetype":"venue"
},
  "geometry": {"coordinates":[3.5637741089,51.1200561523],"type":"Point"}
}