{
  "type": "Feature",
  "properties": {
    "addr:full":"Koninginnelaan 55 Middelkerke West-Vlaanderen 8430",
    "addr:housenumber":"55",
    "addr:postcode":"8430",
    "addr:street":"Koninginnelaan",
    "iso:country":"BE",
    "sg:address":"Koninginnelaan 55",
    "sg:city":"Middelkerke",
    "sg:classifiers":[
        {
            "category":"Health Services",
            "subcategory":"Dentist",
            "type":"Services"
        }
    ],
    "sg:phone":"+32 59 30 20 66",
    "sg:postcode":"8430",
    "sg:province":"West-Vlaanderen",
    "wof:name":"De Boyser Robert",
    "wof:placetype":"venue"
},
  "geometry": {"coordinates":[2.8154389858,51.1863670349],"type":"Point"}
}