{
  "type": "Feature",
  "properties": {
    "iso:country":"BE",
    "sg:address":"G. Gezellelaan 163",
    "sg:city":"Heusden-zolder",
    "sg:orig_category":"V\u00e9hicules automobiles",
    "sg:phone":"+32 11 42 14 69",
    "sg:postcode":"3550",
    "sg:province":"Limburg",
    "wof:name":"Big Cars",
    "wof:placetype":"venue"
},
  "geometry": {"coordinates":[5.2703971863,51.0276222229],"type":"Point"}
}