{
  "type": "Feature",
  "properties": {
    "iso:country":"BE",
    "sg:address":"Koelarenvelden 8",
    "sg:city":"Sint-katelijne-waver",
    "sg:orig_category":"Producteurs de l\u00e9gumes",
    "sg:phone":"+32 15 76 12 60",
    "sg:postcode":"2861",
    "sg:province":"Antwerpen",
    "wof:name":"Willem Vertommen",
    "wof:placetype":"venue"
},
  "geometry": {"coordinates":[4.5797438622,51.072013855],"type":"Point"}
}