{
  "type": "Feature",
  "properties": {
    "addr:full":"Hazendonk 4 Lier Antwerpen 2500",
    "addr:housenumber":"4",
    "addr:postcode":"2500",
    "addr:street":"Hazendonk",
    "iso:country":"BE",
    "sg:address":"Hazendonk 4",
    "sg:city":"Lier",
    "sg:orig_category":"Groententeelt",
    "sg:phone":"+32 3 482 37 30",
    "sg:postcode":"2500",
    "sg:province":"Antwerpen",
    "wof:name":"Jozef Van Den Bergh",
    "wof:placetype":"venue"
},
  "geometry": {"coordinates":[4.5785131454,51.1298408508],"type":"Point"}
}