{
  "type": "Feature",
  "properties": {
    "iso:country":"BE",
    "sg:address":"Quai Du Gravier 6",
    "sg:city":"La Roche-en-ardenne",
    "sg:classifiers":[
        {
            "category":"Fast Food",
            "type":"Food & Drink"
        }
    ],
    "sg:phone":"+32 84 41 17 07",
    "sg:postcode":"6980",
    "sg:province":"Luxembourg",
    "sg:tags":[
        "fried",
        "stand",
        "potato"
    ],
    "wof:name":"Roosen",
    "wof:placetype":"venue"
},
  "geometry": {"coordinates":[5.5758748055,50.183921814],"type":"Point"}
}