{
  "type": "Feature",
  "properties": {
    "addr:full":"Rue De L'ardenne 34 Namur Namur 5024",
    "addr:housenumber":"34",
    "addr:postcode":"5024",
    "addr:street":"Rue De L'Ardenne",
    "iso:country":"BE",
    "sg:address":"Rue De L'ardenne 34",
    "sg:city":"Namur",
    "sg:orig_category":"Plaatsen van vloer- and muurbekleding Schilders",
    "sg:phone":"+32 81 58 14 44",
    "sg:postcode":"5024",
    "sg:province":"Namur",
    "wof:name":"Jean-luc Alsteen",
    "wof:placetype":"venue"
},
  "geometry": {"coordinates":[4.9763898849,50.4921836853],"type":"Point"}
}