{
  "type": "Feature",
  "properties": {
    "addr:full":"Vieux Chemin D'ere 21 Tournai Hainaut 7500",
    "addr:housenumber":"21",
    "addr:postcode":"7500",
    "addr:street":"Vieux Chemin D'Ere",
    "iso:country":"BE",
    "sg:address":"Vieux Chemin D'ere 21",
    "sg:city":"Tournai",
    "sg:classifiers":[
        {
            "category":"Health Services",
            "subcategory":"Nursing And Care Facility",
            "type":"Services"
        }
    ],
    "sg:phone":"+32 69 22 58 79",
    "sg:postcode":"7500",
    "sg:province":"Hainaut",
    "sg:tags":[
        "home"
    ],
    "wof:name":"Dehon Michelle Sprl",
    "wof:placetype":"venue"
},
  "geometry": {"coordinates":[3.3839569092,50.5957984924],"type":"Point"}
}