{
  "type": "Feature",
  "properties": {
    "iso:country":"BE",
    "sg:address":"Blauweweg 13",
    "sg:city":"De Panne",
    "sg:orig_category":"Artsen and specialisten",
    "sg:phone":"+32 58 41 17 93",
    "sg:postcode":"8660",
    "sg:province":"West-Vlaanderen",
    "wof:name":"Aim\u00c9 Cassiers",
    "wof:placetype":"venue"
},
  "geometry": {"coordinates":[2.5857551098,51.0984840393],"type":"Point"}
}