{
  "type": "Feature",
  "properties": {
    "addr:full":"Rue Des Alli\u00e9s 49 Frameries Hainaut 7080",
    "addr:housenumber":"49",
    "addr:postcode":"7080",
    "addr:street":"Rue Des Allie\u0301S",
    "iso:country":"BE",
    "sg:address":"Rue Des Alli\u00e9s 49",
    "sg:city":"Frameries",
    "sg:classifiers":[
        {
            "category":"Health Services",
            "subcategory":"Doctor",
            "type":"Services"
        }
    ],
    "sg:phone":"+32 65 67 25 78",
    "sg:postcode":"7080",
    "sg:province":"Hainaut",
    "sg:tags":[
        "orthopedist"
    ],
    "wof:name":"Creteur",
    "wof:placetype":"venue"
},
  "geometry": {"coordinates":[3.894562006,50.4090576172],"type":"Point"}
}