{
  "type": "Feature",
  "properties": {
    "addr:full":"Kerkweg 10 Herent Vlaams-Brabant 3020",
    "addr:housenumber":"10",
    "addr:postcode":"3020",
    "addr:street":"Kerkweg",
    "iso:country":"BE",
    "sg:address":"Kerkweg 10",
    "sg:city":"Herent",
    "sg:orig_category":"Paramedische behandelingen",
    "sg:phone":"+32 16 23 63 76",
    "sg:postcode":"3020",
    "sg:province":"Vlaams-Brabant",
    "wof:name":"J. Vandervennet",
    "wof:placetype":"venue"
},
  "geometry": {"coordinates":[4.6694669724,50.9107055664],"type":"Point"}
}