{
  "type": "Feature",
  "properties": {
    "addr:full":"Avenue De La Basilique 380 Bruxelles (koekelberg) Bruxelles-Capitale 1081",
    "addr:housenumber":"380",
    "addr:postcode":"1081",
    "addr:street":"Avenue De La Basilique",
    "iso:country":"BE",
    "sg:address":"Avenue De La Basilique 380",
    "sg:city":"Bruxelles (koekelberg)",
    "sg:classifiers":[
        {
            "category":"Government",
            "subcategory":"Post Office",
            "type":"Public Place"
        }
    ],
    "sg:phone":"+32 2 420 93 90",
    "sg:postcode":"1081",
    "sg:province":"Bruxelles-Capitale",
    "sg:tags":[
        "stamp"
    ],
    "wof:name":"Brussels Stamp Center",
    "wof:placetype":"venue"
},
  "geometry": {"coordinates":[4.3140501976,50.8662986755],"type":"Point"}
}