{
  "type": "Feature",
  "properties": {
    "iso:country":"BE",
    "sg:address":"Chauss\u00c9e De Charleroi 11",
    "sg:city":"Sint-gillis/saint-gilles",
    "sg:orig_category":"Pain, p\u00e2tisseries and confiseries",
    "sg:phone":"+32 2 538 13 50",
    "sg:postcode":"1060",
    "sg:province":"Bruxelles-Capitale",
    "wof:name":"Godiva",
    "wof:placetype":"venue"
},
  "geometry": {"coordinates":[4.3569898605,50.8333625793],"type":"Point"}
}