{
  "type": "Feature",
  "properties": {
    "addr:full":"Chauss\u00c9e De Boondael 276 Elsene/ixelles Bruxelles-Capitale 1050",
    "addr:housenumber":"276",
    "addr:postcode":"1050",
    "addr:street":"Chausse\u0301E De Boondael",
    "iso:country":"BE",
    "sg:address":"Chauss\u00c9e De Boondael 276",
    "sg:city":"Elsene/ixelles",
    "sg:orig_category":"Epiceries",
    "sg:phone":"+32 2 647 34 07",
    "sg:postcode":"1050",
    "sg:province":"Bruxelles-Capitale",
    "wof:name":"General Store Night",
    "wof:placetype":"venue"
},
  "geometry": {"coordinates":[4.3829498291,50.8195610046],"type":"Point"}
}