{
  "type": "Feature",
  "properties": {
    "iso:country":"BE",
    "sg:address":"Blancefloerlaan 41",
    "sg:city":"Antwerpen",
    "sg:orig_category":"Levering aan huis restaurants Restaurants",
    "sg:phone":"+32 3 219 15 06",
    "sg:postcode":"2050",
    "sg:province":"Antwerpen",
    "wof:name":"La Provence",
    "wof:placetype":"venue"
},
  "geometry": {"coordinates":[4.3832387924,51.2201080322],"type":"Point"}
}