{
  "type": "Feature",
  "properties": {
    "addr:full":"Torrekensstraat 17 Merelbeke Oost-Vlaanderen 9820",
    "addr:housenumber":"17",
    "addr:postcode":"9820",
    "addr:street":"Torrekensstraat",
    "iso:country":"BE",
    "sg:address":"Torrekensstraat 17",
    "sg:city":"Merelbeke",
    "sg:classifiers":[
        {
            "category":"Personal",
            "subcategory":"Beauty Salon",
            "type":"Services"
        }
    ],
    "sg:phone":"+32 9 362 60 08",
    "sg:postcode":"9820",
    "sg:province":"Oost-Vlaanderen",
    "sg:tags":[
        "de",
        "coiffure"
    ],
    "wof:name":"Coiffure Christiane",
    "wof:placetype":"venue"
},
  "geometry": {"coordinates":[3.7371768951,50.9423866272],"type":"Point"}
}