{
  "type": "Feature",
  "properties": {
    "addr:full":"Kruisveldstraat Dilsen-stokkem (elen) Limburg 3650",
    "addr:postcode":"3650",
    "addr:street":"Kruisveldstraat",
    "iso:country":"BE",
    "sg:address":"Kruisveldstraat",
    "sg:city":"Dilsen-stokkem (elen)",
    "sg:classifiers":[
        {
            "category":"Airport",
            "subcategory":"International",
            "type":"Transportation"
        }
    ],
    "sg:phone":"+32 89 56 31 49",
    "sg:postcode":"3650",
    "sg:province":"Limburg",
    "sg:tags":[
        "-",
        "transport"
    ],
    "wof:name":"Weetjens R Vervoer",
    "wof:placetype":"venue"
},
  "geometry": {"coordinates":[5.727396965,51.0364189148],"type":"Point"}
}