{
  "type": "Feature",
  "properties": {
    "iso:country":"BE",
    "sg:address":"Provinciebaan 28",
    "sg:city":"Koekelare",
    "sg:orig_category":"Eleveurs de bovins. Eleveurs and marchands de porcs",
    "sg:phone":"+32 51 58 84 47",
    "sg:postcode":"8680",
    "sg:province":"West-Vlaanderen",
    "wof:name":"Maria Coghe",
    "wof:placetype":"venue"
},
  "geometry": {"coordinates":[2.9713521004,51.0716705322],"type":"Point"}
}