{
  "type": "Feature",
  "properties": {
    "addr:full":"Dampoortstraat 81 Gent Oost-Vlaanderen 9000",
    "addr:housenumber":"81",
    "addr:postcode":"9000",
    "addr:street":"Dampoortstraat;Oost-Vlaanderen",
    "iso:country":"BE",
    "sg:address":"Dampoortstraat 81",
    "sg:city":"Gent",
    "sg:orig_category":"Rev\u00eatements de sols and murs. Installation de menuiserie m\u00e9tallique",
    "sg:phone":"+32 9 233 91 19",
    "sg:postcode":"9000",
    "sg:province":"Oost-Vlaanderen",
    "wof:name":"Art Parket",
    "wof:placetype":"venue"
},
  "geometry": {"coordinates":[3.737044096,51.0570144653],"type":"Point"}
}