{
  "type": "Feature",
  "properties": {
    "addr:full":"Booischotseweg 119 Hulshout Antwerpen 2235",
    "addr:housenumber":"119",
    "addr:postcode":"2235",
    "addr:street":"Booischotseweg",
    "iso:country":"BE",
    "sg:address":"Booischotseweg 119",
    "sg:city":"Hulshout",
    "sg:orig_category":"Maatschappelijke dienstverlening",
    "sg:phone":"+32 15 22 37 42",
    "sg:postcode":"2235",
    "sg:province":"Antwerpen",
    "wof:name":"Rode Kruis Hulshout",
    "wof:placetype":"venue"
},
  "geometry": {"coordinates":[4.7854452133,51.0673522949],"type":"Point"}
}