{
  "type": "Feature",
  "properties": {
    "iso:country":"BE",
    "sg:address":"Rue Du Warichet 14",
    "sg:city":"La Bruy\u00c8re",
    "sg:orig_category":"Animaux domestiques and accessoires. Eleveurs d'animaux domestiques",
    "sg:phone":"+32 81 56 97 33",
    "sg:postcode":"5081",
    "sg:province":"Namur",
    "wof:name":"Phrayalanna & Rose-fleur",
    "wof:placetype":"venue"
},
  "geometry": {"coordinates":[4.7978792191,50.5488510132],"type":"Point"}
}