{
  "type": "Feature",
  "properties": {
    "addr:full":"Leopoldlaan 119 Middelkerke West-Vlaanderen 8430",
    "addr:housenumber":"119",
    "addr:postcode":"8430",
    "addr:street":"Leopoldlaan",
    "iso:country":"BE",
    "sg:address":"Leopoldlaan 119",
    "sg:city":"Middelkerke",
    "sg:orig_category":"Librairies. Journaux",
    "sg:phone":"+32 59 30 68 89",
    "sg:postcode":"8430",
    "sg:province":"West-Vlaanderen",
    "wof:name":"Freddy Debeuckelaere",
    "wof:placetype":"venue"
},
  "geometry": {"coordinates":[2.8109900951,51.1859092712],"type":"Point"}
}