{
  "type": "Feature",
  "properties": {
    "addr:full":"Venelle De La R\u00e9serve 7 Wavre (bierges) Brabant Wallon 1301",
    "addr:housenumber":"7;1301",
    "addr:street":"Venelle De La Re\u0301Serve",
    "iso:country":"BE",
    "sg:address":"Venelle De La R\u00e9serve 7",
    "sg:city":"Wavre (bierges)",
    "sg:orig_category":"Non-Classified Establishments",
    "sg:phone":"+32 10 22 45 44",
    "sg:postcode":"1301",
    "sg:province":"Brabant Wallon",
    "wof:name":"La Chaumiere Cadeaux Sprl",
    "wof:placetype":"venue"
},
  "geometry": {"coordinates":[4.6163640022,50.7021484375],"type":"Point"}
}