{
  "type": "Feature",
  "properties": {
    "addr:full":"Steenweg Op Vilvoorde 16 Opwijk Vlaams-Brabant 1745",
    "addr:housenumber":"16",
    "addr:postcode":"1745",
    "addr:street":"Steenweg Op Vilvoorde",
    "iso:country":"BE",
    "sg:address":"Steenweg Op Vilvoorde 16",
    "sg:city":"Opwijk",
    "sg:classifiers":[
        {
            "category":"Utilities",
            "subcategory":"Recycling",
            "type":"Services"
        }
    ],
    "sg:phone":"+32 52 37 04 80",
    "sg:postcode":"1745",
    "sg:province":"Vlaams-Brabant",
    "sg:tags":[
        "plastic"
    ],
    "wof:name":"Polyrec B.v.b.a.",
    "wof:placetype":"venue"
},
  "geometry": {"coordinates":[4.2011098862,50.960231781],"type":"Point"}
}