{
  "type": "Feature",
  "properties": {
    "iso:country":"BE",
    "sg:address":"Rue Beeckman 25",
    "sg:city":"Li\u00e8ge 1",
    "sg:classifiers":[
        {
            "category":"Professional",
            "subcategory":"Lawyer & Legal Services",
            "type":"Services"
        }
    ],
    "sg:phone":"+32 4 232 31 31",
    "sg:postcode":"4000",
    "sg:province":"Li\u00e8ge",
    "wof:name":"Franchimont J-d",
    "wof:placetype":"venue"
},
  "geometry": {"coordinates":[5.5652952194,50.6365661621],"type":"Point"}
}