{
  "type": "Feature",
  "properties": {
    "addr:full":"Bte 1 Avenue Louise 287 Brussels Bruxelles-Capitale 1050",
    "addr:housenumber":"1;287",
    "addr:postcode":"1050",
    "addr:street":"Bte;Avenue Louise",
    "iso:country":"BE",
    "sg:address":"Bte 1 Avenue Louise 287",
    "sg:city":"Brussels",
    "sg:classifiers":[
        {
            "category":"Banks & Credit Unions",
            "subcategory":"Bank",
            "type":"Services"
        }
    ],
    "sg:postcode":"1050",
    "sg:province":"Bruxelles-Capitale",
    "wof:name":"Yucom",
    "wof:placetype":"venue"
},
  "geometry": {"coordinates":[4.4153409004,50.8752250671],"type":"Point"}
}