{
  "type": "Feature",
  "properties": {
    "addr:full":"Chauss\u00c9e Paul Houtart 288 La Louviere Hainaut 7110",
    "addr:housenumber":"288",
    "addr:postcode":"7110",
    "addr:street":"Chausse\u0301E Paul Houtart",
    "iso:country":"BE",
    "sg:address":"Chauss\u00c9e Paul Houtart 288",
    "sg:city":"La Louviere",
    "sg:orig_category":"Supermarkten",
    "sg:phone":"+32 64 22 52 26",
    "sg:postcode":"7110",
    "sg:province":"Hainaut",
    "wof:name":"Ad Delhaize",
    "wof:placetype":"venue"
},
  "geometry": {"coordinates":[4.1574149132,50.4868507385],"type":"Point"}
}