{
  "type": "Feature",
  "properties": {
    "iso:country":"BE",
    "sg:address":"Glazentrapstraat 11",
    "sg:city":"Maaseik",
    "sg:classifiers":[
        {
            "category":"Banks & Credit Unions",
            "subcategory":"Investment Brokerage",
            "type":"Services"
        }
    ],
    "sg:phone":"+32 89 56 52 66",
    "sg:postcode":"3680",
    "sg:province":"Limburg",
    "sg:tags":[
        "coil",
        "electric",
        "winding"
    ],
    "wof:name":"Cuypers Pierre",
    "wof:placetype":"venue"
},
  "geometry": {"coordinates":[5.7557549477,51.0837974548],"type":"Point"}
}