{
  "type": "Feature",
  "properties": {
    "iso:country":"BE",
    "sg:address":"Testeltsesteenweg 46",
    "sg:city":"Aarschot",
    "sg:orig_category":"Geschenken and souvenirs Juwelen and horloges",
    "sg:phone":"+32 16 56 03 97",
    "sg:postcode":"3201",
    "sg:province":"Vlaams-Brabant",
    "wof:name":"Bizy Special",
    "wof:placetype":"venue"
},
  "geometry": {"coordinates":[4.8786001205,50.9986915588],"type":"Point"}
}