{
  "type": "Feature",
  "properties": {
    "addr:full":"Rue L\u00c9on Duray 68 La Louviere Hainaut 7110",
    "addr:housenumber":"68",
    "addr:postcode":"7110",
    "addr:street":"Rue Le\u0301On Duray",
    "iso:country":"BE",
    "sg:address":"Rue L\u00c9on Duray 68",
    "sg:city":"La Louviere",
    "sg:classifiers":[
        {
            "category":"Personal",
            "subcategory":"Beauty Salon",
            "type":"Services"
        }
    ],
    "sg:phone":"+32 64 26 37 26",
    "sg:postcode":"7110",
    "sg:province":"Hainaut",
    "sg:tags":[
        "de",
        "coiffure"
    ],
    "wof:name":"Coiffure Mod'tif",
    "wof:placetype":"venue"
},
  "geometry": {"coordinates":[4.1562218666,50.484916687],"type":"Point"}
}