{
  "type": "Feature",
  "properties": {
    "addr:full":"Hollestraat 61 Galmaarden Vlaams-Brabant 1570",
    "addr:housenumber":"61",
    "addr:postcode":"1570",
    "addr:street":"Hollestraat",
    "iso:country":"BE",
    "sg:address":"Hollestraat 61",
    "sg:city":"Galmaarden",
    "sg:orig_category":"Rundveehouders",
    "sg:phone":"+32 54 58 90 28",
    "sg:postcode":"1570",
    "sg:province":"Vlaams-Brabant",
    "wof:name":"Luc Gierts",
    "wof:placetype":"venue"
},
  "geometry": {"coordinates":[3.9840409756,50.7543106079],"type":"Point"}
}