{
  "type": "Feature",
  "properties": {
    "addr:full":"Galgestraat 189 Sint-truiden Limburg 3803",
    "addr:housenumber":"189",
    "addr:postcode":"3803",
    "addr:street":"Galgestraat",
    "iso:country":"BE",
    "sg:address":"Galgestraat 189",
    "sg:city":"Sint-truiden",
    "sg:orig_category":"Diverse bouwafwerking and reiniging",
    "sg:phone":"+32 11 68 22 33",
    "sg:postcode":"3803",
    "sg:province":"Limburg",
    "wof:name":"Valentijn Smets",
    "wof:placetype":"venue"
},
  "geometry": {"coordinates":[5.1425499916,50.8252410889],"type":"Point"}
}