{
  "type": "Feature",
  "properties": {
    "iso:country":"BE",
    "sg:address":"Vieille Route De Rochefort 1 Box 6",
    "sg:city":"Marche-en-famenne (waha)",
    "sg:classifiers":[
        {
            "category":"Arts & Performance",
            "subcategory":"Music",
            "type":"Entertainment"
        }
    ],
    "sg:phone":"+32 84 32 31 08",
    "sg:postcode":"6900",
    "sg:province":"Luxembourg",
    "sg:tags":[
        "disc-jockeys"
    ],
    "wof:name":"Trembloy Jl",
    "wof:placetype":"venue"
},
  "geometry": {"coordinates":[5.3430151939,50.2273483276],"type":"Point"}
}