{
  "type": "Feature",
  "properties": {
    "addr:full":"Rue Joseph-dubois 22 Gedinne Namur 5575",
    "addr:housenumber":"22",
    "addr:postcode":"5575",
    "addr:street":"Rue Joseph-Dubois",
    "iso:country":"BE",
    "sg:address":"Rue Joseph-dubois 22",
    "sg:city":"Gedinne",
    "sg:orig_category":"Epiceries",
    "sg:phone":"+32 61 58 70 57",
    "sg:postcode":"5575",
    "sg:province":"Namur",
    "wof:name":"Anne-marie Collin",
    "wof:placetype":"venue"
},
  "geometry": {"coordinates":[4.9439320564,49.942440033],"type":"Point"}
}