{
  "type": "Feature",
  "properties": {
    "iso:country":"BE",
    "sg:address":"Kerkstraat 18",
    "sg:city":"Beerse (vlimmeren)",
    "sg:classifiers":[
        {
            "category":"Health Services",
            "subcategory":"Health Practitioner",
            "type":"Services"
        }
    ],
    "sg:phone":"+32 3 312 11 12",
    "sg:postcode":"2340",
    "sg:province":"Antwerpen",
    "sg:tags":[
        "physiotherapist"
    ],
    "wof:name":"Goossens J",
    "wof:placetype":"venue"
},
  "geometry": {"coordinates":[4.7807722092,51.2922706604],"type":"Point"}
}