{
  "type": "Feature",
  "properties": {
    "addr:full":"Eekhorentjesbrodenlaan 10 Elsene/ixelles Bruxelles-Capitale 1050",
    "addr:housenumber":"10",
    "addr:postcode":"1050",
    "addr:street":"Eekhorentjesbrodenlaan",
    "iso:country":"BE",
    "sg:address":"Eekhorentjesbrodenlaan 10",
    "sg:city":"Elsene/ixelles",
    "sg:orig_category":"Artsen and specialisten",
    "sg:phone":"+32 2 660 59 47",
    "sg:postcode":"1050",
    "sg:province":"Bruxelles-Capitale",
    "wof:name":"Jean Schmitt",
    "wof:placetype":"venue"
},
  "geometry": {"coordinates":[4.3952140808,50.8065795898],"type":"Point"}
}