{
  "type": "Feature",
  "properties": {
    "addr:full":"Frankrijkstraat 11 Moeskroen/mouscron Hainaut 7711",
    "addr:housenumber":"11",
    "addr:postcode":"7711",
    "addr:street":"Frankrijkstraat",
    "iso:country":"BE",
    "sg:address":"Frankrijkstraat 11",
    "sg:city":"Moeskroen/mouscron",
    "sg:classifiers":[
        {
            "category":"Cafe",
            "type":"Food & Drink"
        }
    ],
    "sg:phone":"+32 56 48 75 35",
    "sg:postcode":"7711",
    "sg:province":"Hainaut",
    "sg:tags":[
        "caf\u00e9s"
    ],
    "wof:name":"Simone Vandevelde",
    "wof:placetype":"venue"
},
  "geometry": {"coordinates":[3.3027570248,50.7270774841],"type":"Point"}
}