{
  "type": "Feature",
  "properties": {
    "iso:country":"BE",
    "sg:address":"Nonnenstraat 81",
    "sg:city":"Nijlen",
    "sg:orig_category":"Paramedische behandelingen",
    "sg:phone":"+32 3 481 85 10",
    "sg:postcode":"2560",
    "sg:province":"Antwerpen",
    "wof:name":"I.t.v. Annie",
    "wof:placetype":"venue"
},
  "geometry": {"coordinates":[4.6703820229,51.1662101746],"type":"Point"}
}