{
  "type": "Feature",
  "properties": {
    "addr:full":"Rue Du Clos Des Manoyes 13 Yvoir Namur 5530",
    "addr:housenumber":"13",
    "addr:postcode":"5530",
    "addr:street":"Rue Du Clos Des Manoyes",
    "iso:country":"BE",
    "sg:address":"Rue Du Clos Des Manoyes 13",
    "sg:city":"Yvoir",
    "sg:classifiers":[
        {
            "category":"Retail",
            "subcategory":"Event Space",
            "type":"Services"
        }
    ],
    "sg:phone":"+32 475 78 71 95",
    "sg:postcode":"5530",
    "sg:province":"Namur",
    "sg:tags":[
        "organisation"
    ],
    "wof:name":"Vliegen N",
    "wof:placetype":"venue"
},
  "geometry": {"coordinates":[4.8961920738,50.3046760559],"type":"Point"}
}