{
  "type": "Feature",
  "properties": {
    "iso:country":"BE",
    "sg:address":"Diepenbeemd 14",
    "sg:city":"Arendonk",
    "sg:classifiers":[
        {
            "category":"Community Center",
            "subcategory":"Youth",
            "type":"Public Place"
        }
    ],
    "sg:phone":"+32 14 67 79 06",
    "sg:postcode":"2370",
    "sg:province":"Antwerpen",
    "sg:tags":[
        "club"
    ],
    "wof:name":"Bemdhal",
    "wof:placetype":"venue"
},
  "geometry": {"coordinates":[5.083220005,51.3193588257],"type":"Point"}
}