{
  "type": "Feature",
  "properties": {
    "iso:country":"BE",
    "sg:address":"Rue Du Maireux 72",
    "sg:city":"Soumagne",
    "sg:orig_category":"Beheer van reclamemedia Film-, tv- and videoproductie Software ontwikkeling and ontwerp",
    "sg:phone":"+32 4 377 18 00",
    "sg:postcode":"4630",
    "sg:province":"Li\u00e8ge",
    "wof:name":"Interactive Business",
    "wof:placetype":"venue"
},
  "geometry": {"coordinates":[5.7479548454,50.6157531738],"type":"Point"}
}