{
  "type": "Feature",
  "properties": {
    "addr:full":"Kerkstraat 107 Blankenberge West-Vlaanderen 8370",
    "addr:housenumber":"107",
    "addr:postcode":"8370",
    "addr:street":"Kerkstraat",
    "iso:country":"BE",
    "sg:address":"Kerkstraat 107",
    "sg:city":"Blankenberge",
    "sg:orig_category":"Instituts de beaut\u00e9",
    "sg:phone":"+32 50 41 39 44",
    "sg:postcode":"8370",
    "sg:province":"West-Vlaanderen",
    "wof:name":"Yves Roche",
    "wof:placetype":"venue"
},
  "geometry": {"coordinates":[3.130614996,51.3137664795],"type":"Point"}
}