{
  "type": "Feature",
  "properties": {
    "addr:full":"Oostkade 57 Zelzate Oost-Vlaanderen 9060",
    "addr:housenumber":"57",
    "addr:postcode":"9060",
    "addr:street":"Oostkade",
    "iso:country":"BE",
    "sg:address":"Oostkade 57",
    "sg:city":"Zelzate",
    "sg:classifiers":[
        {
            "category":"Health Services",
            "subcategory":"Health Practitioner",
            "type":"Services"
        }
    ],
    "sg:phone":"+32 9 342 80 74",
    "sg:postcode":"9060",
    "sg:province":"Oost-Vlaanderen",
    "sg:tags":[
        "dietitian"
    ],
    "wof:name":"Criel M",
    "wof:placetype":"venue"
},
  "geometry": {"coordinates":[3.8102030754,51.1966056824],"type":"Point"}
}