{
  "type": "Feature",
  "properties": {
    "iso:country":"BE",
    "sg:address":"Chauss\u00e9e De Haecht 412",
    "sg:city":"Bruxelles (schaerbeek)",
    "sg:classifiers":[
        {
            "category":"Retail",
            "subcategory":"Laundry & Dry Cleaning",
            "type":"Services"
        }
    ],
    "sg:phone":"+32 2 215 02 79",
    "sg:postcode":"1030",
    "sg:province":"Bruxelles-Capitale",
    "sg:tags":[
        "dyer",
        "cleaner"
    ],
    "wof:name":"Emmy's Shop",
    "wof:placetype":"venue"
},
  "geometry": {"coordinates":[4.3762631416,50.8669013977],"type":"Point"}
}