{
  "type": "Feature",
  "properties": {
    "addr:full":"Zwaaikomstraat 16 Roeselare West-Vlaanderen 8800",
    "addr:housenumber":"16",
    "addr:postcode":"8800",
    "addr:street":"Zwaaikomstraat",
    "iso:country":"BE",
    "sg:address":"Zwaaikomstraat 16",
    "sg:city":"Roeselare",
    "sg:orig_category":"Charpentes and couvertures. Installation de menuiserie m\u00e9tallique",
    "sg:phone":"+32 51 22 57 25",
    "sg:postcode":"8800",
    "sg:province":"West-Vlaanderen",
    "wof:name":"Eeckhout",
    "wof:placetype":"venue"
},
  "geometry": {"coordinates":[3.1534540653,50.950012207],"type":"Point"}
}