{
  "type": "Feature",
  "properties": {
    "addr:full":"Martelarenstraat 44 Aarschot Vlaams-Brabant 3200",
    "addr:housenumber":"44",
    "addr:postcode":"3200",
    "addr:street":"Martelarenstraat",
    "iso:country":"BE",
    "sg:address":"Martelarenstraat 44",
    "sg:city":"Aarschot",
    "sg:orig_category":"Dameskledingzaken",
    "sg:phone":"+32 16 56 53 12",
    "sg:postcode":"3200",
    "sg:province":"Vlaams-Brabant",
    "wof:name":"Etam",
    "wof:placetype":"venue"
},
  "geometry": {"coordinates":[4.8323922157,50.9837646484],"type":"Point"}
}