{
  "type": "Feature",
  "properties": {
    "iso:country":"BE",
    "sg:address":"Rue Du Tilleul 19",
    "sg:city":"Hamoir",
    "sg:orig_category":"Groententeelt",
    "sg:phone":"+32 86 38 97 10",
    "sg:postcode":"4180",
    "sg:province":"Li\u00e8ge",
    "wof:name":"Laurent Born",
    "wof:placetype":"venue"
},
  "geometry": {"coordinates":[5.5427598953,50.445110321],"type":"Point"}
}