{
  "type": "Feature",
  "properties": {
    "addr:full":"Chauss\u00c9e Churchill 10 Saint-nicolas Li\u00e8ge 4420",
    "addr:housenumber":"10",
    "addr:postcode":"4420",
    "addr:street":"Chausse\u0301E Churchill",
    "iso:country":"BE",
    "sg:address":"Chauss\u00c9e Churchill 10",
    "sg:city":"Saint-nicolas",
    "sg:orig_category":"Volwassenenonderwijs",
    "sg:phone":"+32 4 246 51 54",
    "sg:postcode":"4420",
    "sg:province":"Li\u00e8ge",
    "wof:name":"Ec.prom.soc.reine Astrid",
    "wof:placetype":"venue"
},
  "geometry": {"coordinates":[5.5277490616,50.6455497742],"type":"Point"}
}