{
  "type": "Feature",
  "properties": {
    "iso:country":"BE",
    "sg:address":"Hulstersestraat 163",
    "sg:city":"Wielsbeke",
    "sg:orig_category":"Elektrische installaties voor woningen",
    "sg:phone":"+32 56 66 21 33",
    "sg:postcode":"8710",
    "sg:province":"West-Vlaanderen",
    "wof:name":"Dominique Christiaens",
    "wof:placetype":"venue"
},
  "geometry": {"coordinates":[3.3218839169,50.8995475769],"type":"Point"}
}