{
  "type": "Feature",
  "properties": {
    "iso:country":"BE",
    "sg:address":"Rue De Hermee 245",
    "sg:city":"Herstal",
    "sg:orig_category":"Fittings, Valves",
    "sg:phone":"+32 4 240 01 01",
    "sg:postcode":"4040",
    "sg:province":"Li\u00e8ge",
    "wof:name":"Icarus S.a.",
    "wof:placetype":"venue"
},
  "geometry": {"coordinates":[5.626789093,50.6972465515],"type":"Point"}
}