{
  "type": "Feature",
  "properties": {
    "addr:full":"Rue Des Muriers 13 Jemeppe-sur-sambre Namur 5190",
    "addr:housenumber":"13",
    "addr:postcode":"5190",
    "addr:street":"Rue Des Muriers",
    "iso:country":"BE",
    "sg:address":"Rue Des Muriers 13",
    "sg:city":"Jemeppe-sur-sambre",
    "sg:orig_category":"Architecten",
    "sg:phone":"+32 71 78 88 73",
    "sg:postcode":"5190",
    "sg:province":"Namur",
    "wof:name":"Fran\u00c7ois Elleboudt",
    "wof:placetype":"venue"
},
  "geometry": {"coordinates":[4.7114701271,50.4670982361],"type":"Point"}
}