{
  "type": "Feature",
  "properties": {
    "iso:country":"BE",
    "sg:address":"Kroonstraat 71",
    "sg:city":"Evergem",
    "sg:orig_category":"Medische apparatuur, orthopedische artikelen and prothesen Fab",
    "sg:phone":"+32 9 343 07 67",
    "sg:postcode":"9940",
    "sg:province":"Oost-Vlaanderen",
    "wof:name":"Schaers Tandtechn.bedrijf",
    "wof:placetype":"venue"
},
  "geometry": {"coordinates":[3.751732111,51.1841621399],"type":"Point"}
}