{
  "type": "Feature",
  "properties": {
    "addr:full":"Rue De La Poste 22 Plombi\u00c8res Li\u00e8ge 4850",
    "addr:housenumber":"22",
    "addr:postcode":"4850",
    "addr:street":"Rue De La Poste",
    "iso:country":"BE",
    "sg:address":"Rue De La Poste 22",
    "sg:city":"Plombi\u00c8res",
    "sg:orig_category":"Postkantoren",
    "sg:phone":"+32 87 78 92 40",
    "sg:postcode":"4850",
    "sg:province":"Li\u00e8ge",
    "wof:name":"De Post",
    "wof:placetype":"venue"
},
  "geometry": {"coordinates":[5.9626002312,50.7068138123],"type":"Point"}
}