{
  "type": "Feature",
  "properties": {
    "iso:country":"BE",
    "sg:address":"Raas Van Gaverestraat 102",
    "sg:city":"Gent",
    "sg:orig_category":"Vertalers and tolken",
    "sg:phone":"+32 9 233 27 97",
    "sg:postcode":"9000",
    "sg:province":"Oost-Vlaanderen",
    "wof:name":"De Coene",
    "wof:placetype":"venue"
},
  "geometry": {"coordinates":[3.7072970867,51.0510444641],"type":"Point"}
}