{
  "type": "Feature",
  "properties": {
    "iso:country":"BE",
    "sg:address":"Pontfort 114",
    "sg:city":"Retie",
    "sg:orig_category":"Boomkwekerijen",
    "sg:phone":"+32 14 37 73 76",
    "sg:postcode":"2470",
    "sg:province":"Antwerpen",
    "wof:name":"A. Deckx",
    "wof:placetype":"venue"
},
  "geometry": {"coordinates":[5.0419969559,51.2608261108],"type":"Point"}
}