{
  "type": "Feature",
  "properties": {
    "addr:full":"Grote Steenweg 83ba Lede Oost-Vlaanderen 9340",
    "addr:housenumber":"83ba",
    "addr:postcode":"9340",
    "addr:street":"Grote Steenweg",
    "iso:country":"BE",
    "sg:address":"Grote Steenweg 83ba",
    "sg:city":"Lede",
    "sg:orig_category":"V\u00e9hicules automobiles",
    "sg:phone":"+32 9 366 01 63",
    "sg:postcode":"9340",
    "sg:province":"Oost-Vlaanderen",
    "wof:name":"Auto\u00b4s Luc",
    "wof:placetype":"venue"
},
  "geometry": {"coordinates":[4.0041480064,50.9627113342],"type":"Point"}
}