{
  "type": "Feature",
  "properties": {
    "addr:full":"Rue Des Grands Pr\u00c9s 5 Neupre Li\u00e8ge 4120",
    "addr:housenumber":"5",
    "addr:postcode":"4120",
    "addr:street":"Rue Des Grands Pre\u0301S",
    "iso:country":"BE",
    "sg:address":"Rue Des Grands Pr\u00c9s 5",
    "sg:city":"Neupre",
    "sg:orig_category":"Ordinateurs and \u00e9quipement informatique",
    "sg:phone":"+32 495 33 26 70",
    "sg:postcode":"4120",
    "sg:province":"Li\u00e8ge",
    "wof:name":"Morreale",
    "wof:placetype":"venue"
},
  "geometry": {"coordinates":[5.4935002327,50.538936615],"type":"Point"}
}