{
  "type": "Feature",
  "properties": {
    "addr:full":"Bruyelstraat 11 Harelbeke (bavikhove) West-Vlaanderen 8531",
    "addr:housenumber":"11",
    "addr:postcode":"8531",
    "addr:street":"Bruyelstraat",
    "iso:country":"BE",
    "sg:address":"Bruyelstraat 11",
    "sg:city":"Harelbeke (bavikhove)",
    "sg:classifiers":[
        {
            "category":"Real Estate",
            "subcategory":"Real Estate Services",
            "type":"Services"
        }
    ],
    "sg:phone":"+32 56 32 61 32",
    "sg:postcode":"8531",
    "sg:province":"West-Vlaanderen",
    "wof:name":"Immo Rosa",
    "wof:placetype":"venue"
},
  "geometry": {"coordinates":[3.3120079041,50.875957489],"type":"Point"}
}