{
  "type": "Feature",
  "properties": {
    "iso:country":"BE",
    "sg:address":"Stenemolenstraat 7",
    "sg:city":"Zulte (olsene)",
    "sg:classifiers":[
        {
            "category":"Retail",
            "subcategory":"Animal Services",
            "type":"Services"
        }
    ],
    "sg:phone":"+32 9 280 02 87",
    "sg:postcode":"9870",
    "sg:province":"Oost-Vlaanderen",
    "sg:tags":[
        "training",
        "dog"
    ],
    "wof:name":"School Voor Gedrag En Opvoeding Van Honden",
    "wof:placetype":"venue"
},
  "geometry": {"coordinates":[3.4646890163,50.9291648865],"type":"Point"}
}