{
  "type": "Feature",
  "properties": {
    "addr:full":"Ruischer 1 Damme (moerkerke) West-Vlaanderen 8340",
    "addr:housenumber":"1",
    "addr:postcode":"8340",
    "addr:street":"Ruischer",
    "iso:country":"BE",
    "sg:address":"Ruischer 1",
    "sg:city":"Damme (moerkerke)",
    "sg:classifiers":[
        {
            "category":"Farming",
            "subcategory":"Livestock Farm",
            "type":"Manufacturing & Wholesale Goods"
        }
    ],
    "sg:phone":"+32 50 50 01 57",
    "sg:postcode":"8340",
    "sg:province":"West-Vlaanderen",
    "sg:tags":[
        "breeding"
    ],
    "wof:name":"Flip Cv",
    "wof:placetype":"venue"
},
  "geometry": {"coordinates":[3.2815999985,51.2513160706],"type":"Point"}
}