{
  "type": "Feature",
  "properties": {
    "iso:country":"BE",
    "sg:address":"Kortrijksestraat 119",
    "sg:city":"Oostkamp",
    "sg:classifiers":[
        {
            "category":"Home & Garden",
            "subcategory":"Building Materials",
            "type":"Retail Goods"
        }
    ],
    "sg:phone":"+32 50 82 37 59",
    "sg:postcode":"8020",
    "sg:province":"West-Vlaanderen",
    "sg:tags":[
        "article",
        "-",
        "do-it-yourself"
    ],
    "wof:name":"Stock Uni Shop Bvba",
    "wof:placetype":"venue"
},
  "geometry": {"coordinates":[3.2330389023,51.1490898132],"type":"Point"}
}