{
  "type": "Feature",
  "properties": {
    "addr:full":"Tiensesteenweg 48 Box 201 Leuven (heverlee) Vlaams-Brabant 3001",
    "addr:housenumber":"48",
    "addr:postcode":"3001",
    "addr:street":"Tiensesteenweg;Box 201",
    "iso:country":"BE",
    "sg:address":"Tiensesteenweg 48 Box 201",
    "sg:city":"Leuven (heverlee)",
    "sg:classifiers":[
        {
            "category":"Professional",
            "subcategory":"Art Services",
            "type":"Services"
        }
    ],
    "sg:phone":"+32 16 23 61 64",
    "sg:postcode":"3001",
    "sg:province":"Vlaams-Brabant",
    "sg:tags":[
        "graphic",
        "designer"
    ],
    "wof:name":"Foob",
    "wof:placetype":"venue"
},
  "geometry": {"coordinates":[4.7151432037,50.8792953491],"type":"Point"}
}