{
  "type": "Feature",
  "properties": {
    "addr:full":"Beemdenlaan 30b2 Kontich Antwerpen 2550",
    "addr:housenumber":"30b2",
    "addr:postcode":"2550",
    "addr:street":"Beemdenlaan",
    "iso:country":"BE",
    "sg:address":"Beemdenlaan 30b2",
    "sg:city":"Kontich",
    "sg:classifiers":[
        {
            "category":"Personal",
            "subcategory":"Beauty Salon",
            "type":"Services"
        }
    ],
    "sg:phone":"+32 3 457 57 76",
    "sg:postcode":"2550",
    "sg:province":"Antwerpen",
    "sg:tags":[
        "de",
        "coiffure"
    ],
    "wof:name":"Diana Stuyck",
    "wof:placetype":"venue"
},
  "geometry": {"coordinates":[4.4531550407,51.1363983154],"type":"Point"}
}