{
  "type": "Feature",
  "properties": {
    "iso:country":"BE",
    "sg:address":"Place Jules Destr\u00e9e 9a",
    "sg:city":"Ch\u00e2telet (ch\u00e2telineau)",
    "sg:classifiers":[
        {
            "category":"Shopping",
            "subcategory":"Books",
            "type":"Retail Goods"
        }
    ],
    "sg:phone":"+32 71 39 22 53",
    "sg:postcode":"6200",
    "sg:province":"Hainaut",
    "sg:tags":[
        "bookseller"
    ],
    "wof:name":"Nouvelle (librairie)",
    "wof:placetype":"venue"
},
  "geometry": {"coordinates":[4.5155482292,50.3903961182],"type":"Point"}
}