{
  "type": "Feature",
  "properties": {
    "iso:country":"BE",
    "sg:address":"Chauss\u00c9e De Tournai 224",
    "sg:city":"Ath",
    "sg:orig_category":"Elektrische installaties voor woningen",
    "sg:phone":"+32 68 28 47 34",
    "sg:postcode":"7801",
    "sg:province":"Hainaut",
    "wof:name":"Marc Debrue",
    "wof:placetype":"venue"
},
  "geometry": {"coordinates":[3.7640619278,50.6268997192],"type":"Point"}
}