{
  "type": "Feature",
  "properties": {
    "iso:country":"BE",
    "sg:address":"Lamorinierestraat 127",
    "sg:city":"Antwerpen",
    "sg:classifiers":[
        {
            "category":"Professional",
            "subcategory":"Management & Consulting",
            "type":"Services"
        }
    ],
    "sg:phone":"+32 3 286 70 90",
    "sg:postcode":"2018",
    "sg:province":"Antwerpen",
    "sg:tags":[
        "consultant",
        "promotion",
        "-",
        "sale"
    ],
    "wof:name":"La Sensazione",
    "wof:placetype":"venue"
},
  "geometry": {"coordinates":[4.4209637642,51.2036895752],"type":"Point"}
}