{
  "type": "Feature",
  "properties": {
    "iso:country":"BE",
    "sg:address":"Europark 2030",
    "sg:city":"Houthalen-helchteren",
    "sg:orig_category":"Mat\u00e9riaux de construction Gr",
    "sg:phone":"+32 11 60 18 78",
    "sg:postcode":"3530",
    "sg:province":"Limburg",
    "wof:name":"Ipp-industrial Professional Paints",
    "wof:placetype":"venue"
},
  "geometry": {"coordinates":[5.3954958916,51.040813446],"type":"Point"}
}