{
  "type": "Feature",
  "properties": {
    "addr:full":"Kollegestraat 52 Box 1 Geel Antwerpen 2440",
    "addr:housenumber":"52;1",
    "addr:postcode":"2440",
    "addr:street":"Kollegestraat;Box",
    "iso:country":"BE",
    "sg:address":"Kollegestraat 52 Box 1",
    "sg:city":"Geel",
    "sg:classifiers":[
        {
            "category":"Banks & Credit Unions",
            "subcategory":"Investment Brokerage",
            "type":"Services"
        }
    ],
    "sg:phone":"+32 14 59 33 64",
    "sg:postcode":"2440",
    "sg:province":"Antwerpen",
    "sg:tags":[
        "auditor"
    ],
    "wof:name":"Van Havermaet Bedrijfsrevisoren kasteel Ter Poorten",
    "wof:placetype":"venue"
},
  "geometry": {"coordinates":[4.9933052063,51.161026001],"type":"Point"}
}