{
  "type": "Feature",
  "properties": {
    "addr:full":"Bekedijkstr 1 Jabbeke West-Vlaanderen 8490",
    "addr:housenumber":"1",
    "addr:postcode":"8490",
    "addr:street":"Bekedijkstr",
    "iso:country":"BE",
    "sg:address":"Bekedijkstr 1",
    "sg:city":"Jabbeke",
    "sg:classifiers":[
        {
            "category":"Home & Garden",
            "subcategory":"Furniture",
            "type":"Retail Goods"
        }
    ],
    "sg:phone":"+32 50 81 15 73",
    "sg:postcode":"8490",
    "sg:province":"West-Vlaanderen",
    "sg:tags":[
        "household",
        "wood"
    ],
    "wof:name":"Diapal Keukens Nv",
    "wof:placetype":"venue"
},
  "geometry": {"coordinates":[3.078635931,51.194442749],"type":"Point"}
}