{
  "type": "Feature",
  "properties": {
    "iso:country":"BE",
    "sg:address":"Rue Reine Astrid 43",
    "sg:city":"Wanze (antheit)",
    "sg:classifiers":[
        {
            "category":"Insurance",
            "subcategory":"Insurance Agent",
            "type":"Services"
        }
    ],
    "sg:phone":"+32 85 21 61 97",
    "sg:postcode":"4520",
    "sg:province":"Li\u00e8ge",
    "sg:tags":[
        "broker"
    ],
    "wof:name":"Braibant H Sprl",
    "wof:placetype":"venue"
},
  "geometry": {"coordinates":[5.2323689461,50.5539131165],"type":"Point"}
}