{
  "type": "Feature",
  "properties": {
    "addr:full":"Rue De La Technologie 65 Sint-agatha-berchem/berchem-sainte-agathe Bruxelles-Capitale 1082",
    "addr:housenumber":"65",
    "addr:postcode":"1082",
    "addr:street":"Rue De La Technologie;/",
    "iso:country":"BE",
    "sg:address":"Rue De La Technologie 65",
    "sg:city":"Sint-agatha-berchem/berchem-sainte-agathe",
    "sg:orig_category":"Services de Nettoyage and de D\u00e9sinfection. Blanchisserie, Nettoyage \u00e0 Sec and Salons-Lavoirs",
    "sg:phone":"+32 2 482 09 50",
    "sg:postcode":"1082",
    "sg:province":"Bruxelles-Capitale",
    "wof:name":"Lavold Schoonmaak/lavold Nettoyage",
    "wof:placetype":"venue"
},
  "geometry": {"coordinates":[4.2919940948,50.8743858337],"type":"Point"}
}