{
  "type": "Feature",
  "properties": {
    "addr:full":"Achterstraat 10 Essen Antwerpen 2910",
    "addr:housenumber":"10",
    "addr:postcode":"2910",
    "addr:street":"Achterstraat",
    "iso:country":"BE",
    "sg:address":"Achterstraat 10",
    "sg:city":"Essen",
    "sg:classifiers":[
        {
            "category":"Personal",
            "subcategory":"Nail Salon",
            "type":"Services"
        }
    ],
    "sg:phone":"+32 3 667 20 79",
    "sg:postcode":"2910",
    "sg:province":"Antwerpen",
    "sg:tags":[
        "pedicure"
    ],
    "wof:name":"Margot",
    "wof:placetype":"venue"
},
  "geometry": {"coordinates":[4.4575109482,51.430267334],"type":"Point"}
}