{
  "type": "Feature",
  "properties": {
    "iso:country":"BE",
    "sg:address":"Sledderlo 50",
    "sg:city":"Genk",
    "sg:orig_category":"Apotheken",
    "sg:phone":"+32 89 61 28 12",
    "sg:postcode":"3600",
    "sg:province":"Limburg",
    "wof:name":"Myriam Roosen",
    "wof:placetype":"venue"
},
  "geometry": {"coordinates":[5.5135440826,50.9499511719],"type":"Point"}
}