{
  "type": "Feature",
  "properties": {
    "iso:country":"BE",
    "sg:address":"Rue Du Mont 7bb",
    "sg:city":"Mettet",
    "sg:classifiers":[
        {
            "category":"Shopping",
            "subcategory":"Clothing, Apparel, & Fashions",
            "type":"Retail Goods"
        }
    ],
    "sg:phone":"+32 71 72 52 23",
    "sg:postcode":"5640",
    "sg:province":"Namur",
    "sg:tags":[
        "v\u00eatements",
        "pour",
        "dame"
    ],
    "wof:name":"Tant Qu\u00b4il Y Aura Femmes",
    "wof:placetype":"venue"
},
  "geometry": {"coordinates":[4.7468738556,50.3465309143],"type":"Point"}
}