{
  "type": "Feature",
  "properties": {
    "iso:country":"BE",
    "sg:address":"Dokter Elie Lambottestr. 227",
    "sg:city":"Schaarbeek/schaerbeek",
    "sg:orig_category":"Brood, gebak and snoepgoed",
    "sg:phone":"+32 2 215 84 60",
    "sg:postcode":"1030",
    "sg:province":"Bruxelles-Capitale",
    "wof:name":"Hans De Meulemeester/h. De Meulemeester",
    "wof:placetype":"venue"
},
  "geometry": {"coordinates":[4.3903841972,50.872959137],"type":"Point"}
}