{
  "type": "Feature",
  "properties": {
    "addr:full":"Victor De Meyerestraat 18 Boom Antwerpen 2850",
    "addr:housenumber":"18",
    "addr:postcode":"2850",
    "addr:street":"Victor De Meyerestraat",
    "iso:country":"BE",
    "sg:address":"Victor De Meyerestraat 18",
    "sg:city":"Boom",
    "sg:classifiers":[
        {
            "category":"Fast Food",
            "type":"Food & Drink"
        }
    ],
    "sg:phone":"+32 3 844 37 46",
    "sg:postcode":"2850",
    "sg:province":"Antwerpen",
    "sg:tags":[
        "fried",
        "stand",
        "potato"
    ],
    "wof:name":"Den Dax",
    "wof:placetype":"venue"
},
  "geometry": {"coordinates":[4.3695898056,51.0974197388],"type":"Point"}
}