{
  "type": "Feature",
  "properties": {
    "iso:country":"BE",
    "sg:address":"Rue Des Haies 8",
    "sg:city":"Ottignies-louvain-la-neuve",
    "sg:orig_category":"Plomberie, chauffage and installations sanitaires",
    "sg:phone":"+32 10 41 48 68",
    "sg:postcode":"1340",
    "sg:province":"Brabant Wallon",
    "wof:name":"Lauvaux",
    "wof:placetype":"venue"
},
  "geometry": {"coordinates":[4.5758581161,50.6651763916],"type":"Point"}
}