{
  "type": "Feature",
  "properties": {
    "addr:full":"Koebaan 17 Keerbergen Vlaams-Brabant 3140",
    "addr:housenumber":"17",
    "addr:postcode":"3140",
    "addr:street":"Koebaan",
    "iso:country":"BE",
    "sg:address":"Koebaan 17",
    "sg:city":"Keerbergen",
    "sg:classifiers":[
        {
            "category":"Health Services",
            "subcategory":"Nursing And Care Facility",
            "type":"Services"
        }
    ],
    "sg:phone":"+32 15 23 40 45",
    "sg:postcode":"3140",
    "sg:province":"Vlaams-Brabant",
    "sg:tags":[
        "home"
    ],
    "wof:name":"Delen S",
    "wof:placetype":"venue"
},
  "geometry": {"coordinates":[4.6620149612,51.0099220276],"type":"Point"}
}