{
  "type": "Feature",
  "properties": {
    "iso:country":"BE",
    "sg:address":"Grotstraat 110",
    "sg:city":"As",
    "sg:classifiers":[
        {
            "category":"Retail",
            "subcategory":"Repair Shop",
            "type":"Services"
        }
    ],
    "sg:phone":"+32 89 65 90 87",
    "sg:postcode":"3665",
    "sg:province":"Limburg",
    "sg:tags":[
        "upholsterer"
    ],
    "wof:name":"Monissen D",
    "wof:placetype":"venue"
},
  "geometry": {"coordinates":[5.6075220108,51.0220832825],"type":"Point"}
}