{
  "type": "Feature",
  "properties": {
    "iso:country":"BE",
    "sg:address":"Firmin Deprezlaan 20",
    "sg:city":"Kortrijk",
    "sg:classifiers":[
        {
            "category":"Health Services",
            "subcategory":"Health Practitioner",
            "type":"Services"
        }
    ],
    "sg:phone":"+32 56 21 70 98",
    "sg:postcode":"8500",
    "sg:province":"West-Vlaanderen",
    "sg:tags":[
        "physiotherapist"
    ],
    "wof:name":"Lagae Sonja",
    "wof:placetype":"venue"
},
  "geometry": {"coordinates":[3.2835829258,50.8234443665],"type":"Point"}
}