{
  "type": "Feature",
  "properties": {
    "iso:country":"BE",
    "sg:address":"Guldendal 20",
    "sg:city":"Grimbergen",
    "sg:classifiers":[
        {
            "category":"Cafe",
            "type":"Food & Drink"
        }
    ],
    "sg:phone":"+32 2 270 81 11",
    "sg:postcode":"1850",
    "sg:province":"Vlaams-Brabant",
    "sg:tags":[
        "caf\u00e9s"
    ],
    "wof:name":"Heemschut",
    "wof:placetype":"venue"
},
  "geometry": {"coordinates":[4.3722448349,50.9276695251],"type":"Point"}
}