{
  "type": "Feature",
  "properties": {
    "iso:country":"BE",
    "sg:address":"R. L'h\u00d4tel Des Monnaies 53",
    "sg:city":"Sint-gillis/saint-gilles",
    "sg:orig_category":"M\u00e9decins and sp\u00e9cialistes",
    "sg:phone":"+32 2 537 22 04",
    "sg:postcode":"1060",
    "sg:province":"Bruxelles-Capitale",
    "wof:name":"Aleksander Biernacki",
    "wof:placetype":"venue"
},
  "geometry": {"coordinates":[4.3485708237,50.831451416],"type":"Point"}
}