{
  "type": "Feature",
  "properties": {
    "addr:full":"Rue De Baume 45 La Louviere Hainaut 7100",
    "addr:housenumber":"45",
    "addr:postcode":"7100",
    "addr:street":"Rue De Baume",
    "iso:country":"BE",
    "sg:address":"Rue De Baume 45",
    "sg:city":"La Louviere",
    "sg:classifiers":[
        {
            "category":"Restaurant",
            "type":"Food & Drink"
        }
    ],
    "sg:phone":"+32 64 26 61 10",
    "sg:postcode":"7100",
    "sg:province":"Hainaut",
    "wof:name":"La Vache Qui Chante",
    "wof:placetype":"venue"
},
  "geometry": {"coordinates":[4.200387001,50.4748420715],"type":"Point"}
}