{
  "type": "Feature",
  "properties": {
    "addr:full":"Lendedreef 94a Anzegem (vichte) West-Vlaanderen 8570",
    "addr:housenumber":"94a",
    "addr:postcode":"8570",
    "addr:street":"Lendedreef",
    "iso:country":"BE",
    "sg:address":"Lendedreef 94a",
    "sg:city":"Anzegem (vichte)",
    "sg:classifiers":[
        {
            "category":"Home & Garden",
            "subcategory":"Carpets & Floor Coverings",
            "type":"Retail Goods"
        }
    ],
    "sg:phone":"+32 56 44 01 57",
    "sg:postcode":"8570",
    "sg:province":"West-Vlaanderen",
    "sg:tags":[
        "armoring"
    ],
    "wof:name":"Decavele C",
    "wof:placetype":"venue"
},
  "geometry": {"coordinates":[3.3849380016,50.8378219604],"type":"Point"}
}