{
  "type": "Feature",
  "properties": {
    "iso:country":"BE",
    "sg:address":"Diestersesteenweg 65",
    "sg:city":"Beringen",
    "sg:orig_category":"Onderdelen and accessoires voor auto's Voertuigen",
    "sg:phone":"+32 11 43 72 38",
    "sg:postcode":"3583",
    "sg:province":"Limburg",
    "wof:name":"A.c.l.-autoparts",
    "wof:placetype":"venue"
},
  "geometry": {"coordinates":[5.1706700325,51.0389442444],"type":"Point"}
}