{
  "type": "Feature",
  "properties": {
    "iso:country":"BE",
    "sg:address":"Chauss\u00c9e De Philippeville 56",
    "sg:city":"Gerpinnes",
    "sg:orig_category":"D\u00e9taillants en pi\u00e8ces and accessoires de voitures",
    "sg:phone":"+32 71 47 61 62",
    "sg:postcode":"6280",
    "sg:province":"Hainaut",
    "wof:name":"Diamond's Car",
    "wof:placetype":"venue"
},
  "geometry": {"coordinates":[4.4700188637,50.3610610962],"type":"Point"}
}