{
  "type": "Feature",
  "properties": {
    "iso:country":"BE",
    "sg:address":"Rue Grand\u00b4route 65b6",
    "sg:city":"Beyne-heusay",
    "sg:orig_category":"Animations diverses",
    "sg:phone":"+32 4 361 19 30",
    "sg:postcode":"4610",
    "sg:province":"Li\u00e8ge",
    "wof:name":"D.j. Boulou",
    "wof:placetype":"venue"
},
  "geometry": {"coordinates":[5.6445841789,50.6255493164],"type":"Point"}
}