{
  "type": "Feature",
  "properties": {
    "iso:country":"BE",
    "sg:address":"Heesstraat 8",
    "sg:city":"Bilzen",
    "sg:orig_category":"Eleveurs and marchands de porcs",
    "sg:phone":"+32 12 45 20 49",
    "sg:postcode":"3740",
    "sg:province":"Limburg",
    "wof:name":"Martinus Palmaers",
    "wof:placetype":"venue"
},
  "geometry": {"coordinates":[5.6088190079,50.8465385437],"type":"Point"}
}