{
  "type": "Feature",
  "properties": {
    "iso:country":"BE",
    "sg:address":"Rue Du Stortoir 39",
    "sg:city":"Gembloux",
    "sg:orig_category":"Sportclubs",
    "sg:phone":"+32 81 61 37 62",
    "sg:postcode":"5030",
    "sg:province":"Namur",
    "wof:name":"Tennis De Table Sauveni\u00c8re",
    "wof:placetype":"venue"
},
  "geometry": {"coordinates":[4.7187671661,50.5801353455],"type":"Point"}
}