{
  "type": "Feature",
  "properties": {
    "iso:country":"BE",
    "sg:address":"Sint-jansstraat 23",
    "sg:city":"Waregem (beveren-leie)",
    "sg:classifiers":[
        {
            "category":"Home & Garden",
            "subcategory":"Carpets & Floor Coverings",
            "type":"Retail Goods"
        }
    ],
    "sg:phone":"+32 56 71 71 79",
    "sg:postcode":"8791",
    "sg:province":"West-Vlaanderen",
    "sg:tags":[
        "parquet"
    ],
    "wof:name":"Atelier Martinez",
    "wof:placetype":"venue"
},
  "geometry": {"coordinates":[3.3355259895,50.8701858521],"type":"Point"}
}