{
  "type": "Feature",
  "properties": {
    "addr:full":"Rue Herman Reuleaux 51 Li\u00c8ge Li\u00e8ge 4020",
    "addr:housenumber":"51",
    "addr:postcode":"4020",
    "addr:street":"Rue Herman Reuleaux",
    "iso:country":"BE",
    "sg:address":"Rue Herman Reuleaux 51",
    "sg:city":"Li\u00c8ge",
    "sg:orig_category":"R\u00e9paration and restauration de meubles",
    "sg:phone":"+32 4 342 24 24",
    "sg:postcode":"4020",
    "sg:province":"Li\u00e8ge",
    "wof:name":"Maison Acajou",
    "wof:placetype":"venue"
},
  "geometry": {"coordinates":[5.5918869972,50.6379776001],"type":"Point"}
}