{
  "type": "Feature",
  "properties": {
    "addr:full":"Avenue De Tervueren 296cb12 Sint-pieters-woluwe/woluwe-saint-pierre Bruxelles-Capitale 1150",
    "addr:housenumber":"296cb12",
    "addr:postcode":"1150",
    "addr:street":"Avenue De Tervueren;/",
    "iso:country":"BE",
    "sg:address":"Avenue De Tervueren 296cb12",
    "sg:city":"Sint-pieters-woluwe/woluwe-saint-pierre",
    "sg:orig_category":"Administration d'immeubles. Agences immobili\u00e8res",
    "sg:phone":"+32 2 762 40 38",
    "sg:postcode":"1150",
    "sg:province":"Bruxelles-Capitale",
    "wof:name":"Pr\u00c9vinaire G\u00c9rance",
    "wof:placetype":"venue"
},
  "geometry": {"coordinates":[4.4269962311,50.8352012634],"type":"Point"}
}