{
  "type": "Feature",
  "properties": {
    "iso:country":"BE",
    "sg:address":"Rue Albert Allard 42",
    "sg:city":"Tournai",
    "sg:classifiers":[
        {
            "category":"Professional",
            "subcategory":"Accounting & Tax Preparation",
            "type":"Services"
        }
    ],
    "sg:phone":"+32 69 23 32 73",
    "sg:postcode":"7500",
    "sg:province":"Hainaut",
    "sg:tags":[
        "bookkeeper"
    ],
    "wof:name":"Cassiers J-p",
    "wof:placetype":"venue"
},
  "geometry": {"coordinates":[3.3765349388,50.6074104309],"type":"Point"}
}