{
  "type": "Feature",
  "properties": {
    "iso:country":"BE",
    "sg:address":"Sint-petrus En Paulusstraat 12",
    "sg:city":"Roeselare (rumbeke)",
    "sg:classifiers":[
        {
            "category":"Shopping",
            "subcategory":"Florist",
            "type":"Retail Goods"
        }
    ],
    "sg:phone":"+32 51 20 61 78",
    "sg:postcode":"8800",
    "sg:province":"West-Vlaanderen",
    "wof:name":"Bloemen Donck",
    "wof:placetype":"venue"
},
  "geometry": {"coordinates":[3.1551349163,50.9342079163],"type":"Point"}
}