{
  "type": "Feature",
  "properties": {
    "addr:full":"Avenue De Tervueren 270b24 Sint-pieters-woluwe/woluwe-saint-pierre Bruxelles-Capitale 1150",
    "addr:housenumber":"270b24",
    "addr:postcode":"1150",
    "addr:street":"Avenue De Tervueren;/",
    "iso:country":"BE",
    "sg:address":"Avenue De Tervueren 270b24",
    "sg:city":"Sint-pieters-woluwe/woluwe-saint-pierre",
    "sg:orig_category":"Produits pharmaceutiques Fab",
    "sg:phone":"+32 2 776 36 11",
    "sg:postcode":"1150",
    "sg:province":"Bruxelles-Capitale",
    "wof:name":"Continental Pharma Inc./continental Pharma",
    "wof:placetype":"venue"
},
  "geometry": {"coordinates":[4.4198570251,50.8352546692],"type":"Point"}
}