{
  "type": "Feature",
  "properties": {
    "iso:country":"BE",
    "sg:address":"Rue Marcel Fikenne 32",
    "sg:city":"Pepinster",
    "sg:classifiers":[
        {
            "category":"Personal",
            "subcategory":"Beauty Salon",
            "type":"Services"
        }
    ],
    "sg:phone":"+32 87 46 07 61",
    "sg:postcode":"4860",
    "sg:province":"Li\u00e8ge",
    "sg:tags":[
        "lady",
        "-",
        "hairdressing"
    ],
    "wof:name":"Coiffure 2000",
    "wof:placetype":"venue"
},
  "geometry": {"coordinates":[5.796145916,50.559753418],"type":"Point"}
}