{
  "type": "Feature",
  "properties": {
    "addr:full":"Oostmalsebaan 7 Brecht (sint-lenaarts) Antwerpen 2960",
    "addr:housenumber":"7",
    "addr:postcode":"2960",
    "addr:street":"Oostmalsebaan",
    "iso:country":"BE",
    "sg:address":"Oostmalsebaan 7",
    "sg:city":"Brecht (sint-lenaarts)",
    "sg:classifiers":[
        {
            "category":"Shopping",
            "subcategory":"Party Supplies",
            "type":"Retail Goods"
        }
    ],
    "sg:phone":"+32 3 669 82 34",
    "sg:postcode":"2960",
    "sg:province":"Antwerpen",
    "sg:tags":[
        "rental",
        "-"
    ],
    "wof:name":"Aerts A",
    "wof:placetype":"venue"
},
  "geometry": {"coordinates":[4.6415200233,51.3512115479],"type":"Point"}
}