{
  "type": "Feature",
  "properties": {
    "addr:full":"Boxbergstraat 4 Genk Limburg 3600",
    "addr:housenumber":"4",
    "addr:postcode":"3600",
    "addr:street":"Boxbergstraat",
    "iso:country":"BE",
    "sg:address":"Boxbergstraat 4",
    "sg:city":"Genk",
    "sg:orig_category":"Banken and kredietinstellingen",
    "sg:phone":"+32 89 35 41 55",
    "sg:postcode":"3600",
    "sg:province":"Limburg",
    "wof:name":"Fortis",
    "wof:placetype":"venue"
},
  "geometry": {"coordinates":[5.4495911598,50.9679718018],"type":"Point"}
}