{
  "type": "Feature",
  "properties": {
    "iso:country":"BE",
    "sg:address":"Lage Kaart 462a",
    "sg:city":"Brasschaat",
    "sg:classifiers":[
        {
            "category":"Building & Trades",
            "subcategory":"Construction",
            "type":"Services"
        }
    ],
    "sg:phone":"+32 3 653 48 68",
    "sg:postcode":"2930",
    "sg:province":"Antwerpen",
    "sg:tags":[
        "ceiling"
    ],
    "wof:name":"Segers P",
    "wof:placetype":"venue"
},
  "geometry": {"coordinates":[4.4897708893,51.3065071106],"type":"Point"}
}