{
  "type": "Feature",
  "properties": {
    "addr:full":"Driepaalweg 5 Opoeteren Limburg 3680",
    "addr:housenumber":"5",
    "addr:postcode":"3680",
    "addr:street":"Driepaalweg",
    "iso:country":"BE",
    "sg:address":"Driepaalweg 5",
    "sg:city":"Opoeteren",
    "sg:orig_category":"Herstelling aan huis van elektrische huishoudapparaten Huishoudapparaten, televisies and radio's",
    "sg:phone":"+32 89 86 39 54",
    "sg:postcode":"3680",
    "sg:province":"Limburg",
    "wof:name":"Flux",
    "wof:placetype":"venue"
},
  "geometry": {"coordinates":[5.6594529152,51.0667037964],"type":"Point"}
}