{
  "type": "Feature",
  "properties": {
    "addr:full":"Bruggestraat 5 Ichtegem (eernegem) West-Vlaanderen 8480",
    "addr:housenumber":"5",
    "addr:postcode":"8480",
    "addr:street":"Bruggestraat",
    "iso:country":"BE",
    "sg:address":"Bruggestraat 5",
    "sg:city":"Ichtegem (eernegem)",
    "sg:classifiers":[
        {
            "category":"Professional",
            "subcategory":"Lawyer & Legal Services",
            "type":"Services"
        }
    ],
    "sg:phone":"+32 59 29 91 92",
    "sg:postcode":"8480",
    "sg:province":"West-Vlaanderen",
    "wof:name":"Bonny Karl",
    "wof:placetype":"venue"
},
  "geometry": {"coordinates":[3.0280179977,51.1305503845],"type":"Point"}
}