{
  "type": "Feature",
  "properties": {
    "iso:country":"BE",
    "sg:address":"Bergstraat 6",
    "sg:city":"Sint-katelijne-waver (onze-lieve-vrouw-waver)",
    "sg:classifiers":[
        {
            "category":"Education",
            "subcategory":"School",
            "type":"Public Place"
        }
    ],
    "sg:phone":"+32 15 25 33 60",
    "sg:postcode":"2861",
    "sg:province":"Antwerpen",
    "sg:tags":[
        "-",
        "private"
    ],
    "wof:name":"Muziekadvies Koenders Jan",
    "wof:placetype":"venue"
},
  "geometry": {"coordinates":[4.5655198097,51.0547866821],"type":"Point"}
}