{
  "type": "Feature",
  "properties": {
    "addr:full":"Rue De La Fus\u00e9e 100 Bruxelles Bruxelles-Capitale 1130",
    "addr:housenumber":"100",
    "addr:postcode":"1130",
    "addr:street":"Rue De La Fuse\u0301E",
    "iso:country":"BE",
    "sg:address":"Rue De La Fus\u00e9e 100",
    "sg:city":"Bruxelles",
    "sg:classifiers":[
        {
            "category":"Professional",
            "subcategory":"Computer Services",
            "type":"Services"
        }
    ],
    "sg:phone":"+32 2 725 25 12",
    "sg:postcode":"1130",
    "sg:province":"Bruxelles-Capitale",
    "sg:tags":[
        "-",
        "processing",
        "data"
    ],
    "wof:name":"Xoal Bvba",
    "wof:placetype":"venue"
},
  "geometry": {"coordinates":[4.4334049225,50.879535675],"type":"Point"}
}