{
  "type": "Feature",
  "properties": {
    "iso:country":"BE",
    "sg:address":"Lindestraat 42",
    "sg:city":"Lovendegem",
    "sg:orig_category":"Installation \u00e9lectrique r\u00e9sidentielle",
    "sg:phone":"+32 9 372 65 05",
    "sg:postcode":"9920",
    "sg:province":"Oost-Vlaanderen",
    "wof:name":"Eddy Seyssens",
    "wof:placetype":"venue"
},
  "geometry": {"coordinates":[3.6258850098,51.1078720093],"type":"Point"}
}