{
  "type": "Feature",
  "properties": {
    "addr:full":"Molenstraat 163 Lokeren Oost-Vlaanderen 9160",
    "addr:housenumber":"163",
    "addr:postcode":"9160",
    "addr:street":"Molenstraat",
    "iso:country":"BE",
    "sg:address":"Molenstraat 163",
    "sg:city":"Lokeren",
    "sg:orig_category":"Pain, p\u00e2tisseries and confiseries",
    "sg:phone":"+32 9 348 18 76",
    "sg:postcode":"9160",
    "sg:province":"Oost-Vlaanderen",
    "wof:name":"Hilaire De Wilde",
    "wof:placetype":"venue"
},
  "geometry": {"coordinates":[3.9973130226,51.0990104675],"type":"Point"}
}