{
  "type": "Feature",
  "properties": {
    "iso:country":"BE",
    "sg:address":"Oppemstraat 29",
    "sg:city":"Tervuren",
    "sg:orig_category":"Advocaten and juridische adviseurs",
    "sg:phone":"+32 2 768 03 30",
    "sg:postcode":"3080",
    "sg:province":"Vlaams-Brabant",
    "wof:name":"E. De Breucker",
    "wof:placetype":"venue"
},
  "geometry": {"coordinates":[4.5067129135,50.8293495178],"type":"Point"}
}