{
  "type": "Feature",
  "properties": {
    "addr:full":"Lucien Reychlerstraat 17-19 Waasmunster Oost-Vlaanderen 9250",
    "addr:housenumber":"17-19",
    "addr:postcode":"9250",
    "addr:street":"Lucien Reychlerstraat",
    "iso:country":"BE",
    "sg:address":"Lucien Reychlerstraat 17-19",
    "sg:city":"Waasmunster",
    "sg:classifiers":[
        {
            "category":"Home & Garden",
            "subcategory":"Kitchen Supply",
            "type":"Retail Goods"
        }
    ],
    "sg:phone":"+32 52 46 02 96",
    "sg:postcode":"9250",
    "sg:province":"Oost-Vlaanderen",
    "sg:tags":[
        "installation"
    ],
    "wof:name":"Wasocub Keukens",
    "wof:placetype":"venue"
},
  "geometry": {"coordinates":[4.1008200645,51.1157836914],"type":"Point"}
}