{
  "type": "Feature",
  "properties": {
    "iso:country":"BE",
    "sg:address":"Vleeshouwersstraat 5",
    "sg:city":"Veurne",
    "sg:orig_category":"Beheer onroerend goed",
    "sg:phone":"+32 58 31 10 36",
    "sg:postcode":"8630",
    "sg:province":"West-Vlaanderen",
    "wof:name":"Joseph Sierens",
    "wof:placetype":"venue"
},
  "geometry": {"coordinates":[2.6610510349,51.0720367432],"type":"Point"}
}