{
  "type": "Feature",
  "properties": {
    "iso:country":"BE",
    "sg:address":"Berkenlaan 29",
    "sg:city":"Overpelt",
    "sg:classifiers":[
        {
            "category":"Professional",
            "subcategory":"Art Services",
            "type":"Services"
        }
    ],
    "sg:phone":"+32 11 64 80 34",
    "sg:postcode":"3900",
    "sg:province":"Limburg",
    "sg:tags":[
        "realization",
        "audio-visual"
    ],
    "wof:name":"Verhoeven Media Solutions",
    "wof:placetype":"venue"
},
  "geometry": {"coordinates":[5.3951292038,51.2321166992],"type":"Point"}
}