{
  "type": "Feature",
  "properties": {
    "addr:full":"Rozenkranslaan 152 Genk Limburg 3600",
    "addr:housenumber":"152",
    "addr:postcode":"3600",
    "addr:street":"Rozenkranslaan",
    "iso:country":"BE",
    "sg:address":"Rozenkranslaan 152",
    "sg:city":"Genk",
    "sg:classifiers":[
        {
            "category":"Food & Beverages",
            "subcategory":"Meat & Fish",
            "type":"Retail Goods"
        }
    ],
    "sg:phone":"+32 89 35 22 56",
    "sg:postcode":"3600",
    "sg:province":"Limburg",
    "sg:tags":[
        "-",
        "livestock"
    ],
    "wof:name":"Pieters E",
    "wof:placetype":"venue"
},
  "geometry": {"coordinates":[5.487888813,50.9637832642],"type":"Point"}
}