{
  "type": "Feature",
  "properties": {
    "iso:country":"BE",
    "sg:address":"Henleykaai 87",
    "sg:city":"Gent",
    "sg:classifiers":[
        {
            "category":"Health Services",
            "subcategory":"Health Practitioner",
            "type":"Services"
        }
    ],
    "sg:phone":"+32 9 234 12 00",
    "sg:postcode":"9000",
    "sg:province":"Oost-Vlaanderen",
    "sg:tags":[
        "osteopath"
    ],
    "wof:name":"Poppe Y (d.o.)",
    "wof:placetype":"venue"
},
  "geometry": {"coordinates":[3.7129929066,51.0424613953],"type":"Point"}
}