{
  "type": "Feature",
  "properties": {
    "iso:country":"BE",
    "sg:address":"Rue De L\u00b4eglise 6",
    "sg:city":"Florenville",
    "sg:orig_category":"Artistes ind\u00e9pendants",
    "sg:phone":"+32 61 31 31 50",
    "sg:postcode":"6820",
    "sg:province":"Luxembourg",
    "wof:name":"Charles Mauri",
    "wof:placetype":"venue"
},
  "geometry": {"coordinates":[5.3113479614,49.6997833252],"type":"Point"}
}