{
  "type": "Feature",
  "properties": {
    "addr:full":"Rue Ecuelle 2 Rumes Hainaut 7618",
    "addr:housenumber":"2",
    "addr:postcode":"7618",
    "addr:street":"Rue Ecuelle",
    "iso:country":"BE",
    "sg:address":"Rue Ecuelle 2",
    "sg:city":"Rumes",
    "sg:orig_category":"Eclairage et \u00e9quipements du foyer. Fleurs and plantes",
    "sg:phone":"+32 69 64 92 84",
    "sg:postcode":"7618",
    "sg:province":"Hainaut",
    "wof:name":"L'ecuelle Fleurie",
    "wof:placetype":"venue"
},
  "geometry": {"coordinates":[3.3484699726,50.5439224243],"type":"Point"}
}