{
  "type": "Feature",
  "properties": {
    "addr:full":"Route De Bastogne 39b Nassogne (harsin) Luxembourg 6950",
    "addr:housenumber":"39b",
    "addr:postcode":"6950",
    "addr:street":"Route De Bastogne",
    "iso:country":"BE",
    "sg:address":"Route De Bastogne 39b",
    "sg:city":"Nassogne (harsin)",
    "sg:classifiers":[
        {
            "category":"Professional",
            "subcategory":"Accounting & Tax Preparation",
            "type":"Services"
        }
    ],
    "sg:phone":"+32 84 36 87 46",
    "sg:postcode":"6950",
    "sg:province":"Luxembourg",
    "sg:tags":[
        "bookkeeper"
    ],
    "wof:name":"Lillard J",
    "wof:placetype":"venue"
},
  "geometry": {"coordinates":[5.341301918,50.1289215088],"type":"Point"}
}