{
  "type": "Feature",
  "properties": {
    "iso:country":"BE",
    "sg:address":"Rue Cockerill 136",
    "sg:city":"Seraing",
    "sg:classifiers":[
        {
            "category":"Home & Garden",
            "subcategory":"Building Materials",
            "type":"Retail Goods"
        }
    ],
    "sg:phone":"+32 4 337 26 23",
    "sg:postcode":"4100",
    "sg:province":"Li\u00e8ge",
    "sg:tags":[
        "water",
        "heater"
    ],
    "wof:name":"Vandermeulen J",
    "wof:placetype":"venue"
},
  "geometry": {"coordinates":[5.5121669769,50.611114502],"type":"Point"}
}