{
  "type": "Feature",
  "properties": {
    "addr:full":"Freesiadreef 1b56 Schaarbeek/schaerbeek Bruxelles-Capitale 1030",
    "addr:housenumber":"1b56",
    "addr:postcode":"1030",
    "addr:street":"Freesiadreef",
    "iso:country":"BE",
    "sg:address":"Freesiadreef 1b56",
    "sg:city":"Schaarbeek/schaerbeek",
    "sg:orig_category":"Beheer onroerend goed",
    "sg:phone":"+32 2 241 30 93",
    "sg:postcode":"1030",
    "sg:province":"Bruxelles-Capitale",
    "wof:name":"Loncin-laevens-el Majeri",
    "wof:placetype":"venue"
},
  "geometry": {"coordinates":[4.3900241852,50.8658676147],"type":"Point"}
}