{
  "type": "Feature",
  "properties": {
    "addr:full":"Rue Des Artisans 61 Li\u00e8ge 1 (grivegn\u00e9e) Li\u00e8ge 4030",
    "addr:housenumber":"61;1",
    "addr:postcode":"4030",
    "addr:street":"Rue Des Artisans",
    "iso:country":"BE",
    "sg:address":"Rue Des Artisans 61",
    "sg:city":"Li\u00e8ge 1 (grivegn\u00e9e)",
    "sg:classifiers":[
        {
            "category":"Professional",
            "subcategory":"Printing & Photocopies",
            "type":"Services"
        }
    ],
    "sg:phone":"+32 4 366 11 49",
    "sg:postcode":"4030",
    "sg:province":"Li\u00e8ge",
    "sg:tags":[
        "engraving"
    ],
    "wof:name":"Nyssens F",
    "wof:placetype":"venue"
},
  "geometry": {"coordinates":[5.6086449623,50.618057251],"type":"Point"}
}