{
  "type": "Feature",
  "properties": {
    "iso:country":"BE",
    "sg:address":"Chauss\u00c9e De Charleroi 74",
    "sg:city":"Namur",
    "sg:orig_category":"Pain, p\u00e2tisseries and confiseries",
    "sg:phone":"+32 81 73 20 03",
    "sg:postcode":"5000",
    "sg:province":"Namur",
    "wof:name":"Le Croustillon",
    "wof:placetype":"venue"
},
  "geometry": {"coordinates":[4.8407278061,50.4621582031],"type":"Point"}
}