{
  "type": "Feature",
  "properties": {
    "addr:full":"Klossestraat 29a De Pinte Oost-Vlaanderen 9840",
    "addr:housenumber":"29a",
    "addr:postcode":"9840",
    "addr:street":"Klossestraat",
    "iso:country":"BE",
    "sg:address":"Klossestraat 29a",
    "sg:city":"De Pinte",
    "sg:classifiers":[
        {
            "category":"Professional",
            "subcategory":"Art Services",
            "type":"Services"
        }
    ],
    "sg:phone":"+32 9 220 78 90",
    "sg:postcode":"9840",
    "sg:province":"Oost-Vlaanderen",
    "sg:tags":[
        "photographer"
    ],
    "wof:name":"Leemans F",
    "wof:placetype":"venue"
},
  "geometry": {"coordinates":[3.6708180904,51.0078659058],"type":"Point"}
}