{
  "type": "Feature",
  "properties": {
    "addr:full":"Affligemdreef 11b Aalst Oost-Vlaanderen 9300",
    "addr:housenumber":"11b",
    "addr:postcode":"9300",
    "addr:street":"Affligemdreef",
    "iso:country":"BE",
    "sg:address":"Affligemdreef 11b",
    "sg:city":"Aalst",
    "sg:classifiers":[
        {
            "category":"Communications",
            "subcategory":"Film & Video Production",
            "type":"Services"
        }
    ],
    "sg:phone":"+32 53 78 83 86",
    "sg:postcode":"9300",
    "sg:province":"Oost-Vlaanderen",
    "sg:tags":[
        "multimedia",
        "-",
        "system"
    ],
    "wof:name":"Mithras",
    "wof:placetype":"venue"
},
  "geometry": {"coordinates":[4.0611009598,50.93176651],"type":"Point"}
}