{
  "type": "Feature",
  "properties": {
    "iso:country":"BE",
    "sg:address":"Heilig-kruisplein 4",
    "sg:city":"Roeselare",
    "sg:orig_category":"Bagage and lederwaren Kapsalons",
    "sg:phone":"+32 51 20 65 98",
    "sg:postcode":"8800",
    "sg:province":"West-Vlaanderen",
    "wof:name":"Christa Driessens",
    "wof:placetype":"venue"
},
  "geometry": {"coordinates":[3.1456298828,50.9680557251],"type":"Point"}
}