{
  "type": "Feature",
  "properties": {
    "addr:full":"Boulvard De La Souveniere 122 Liege Li\u00e8ge 4000",
    "addr:housenumber":"122",
    "addr:postcode":"4000",
    "addr:street":"Boulvard De La Souveniere",
    "iso:country":"BE",
    "sg:address":"Boulvard De La Souveniere 122",
    "sg:city":"Liege",
    "sg:orig_category":"Reisbureaus",
    "sg:phone":"+32 4 221 30 70",
    "sg:postcode":"4000",
    "sg:province":"Li\u00e8ge",
    "wof:name":"Ornella Travel",
    "wof:placetype":"venue"
},
  "geometry": {"coordinates":[5.5660009384,50.6420783997],"type":"Point"}
}