{
  "type": "Feature",
  "properties": {
    "iso:country":"BE",
    "sg:address":"C. Van Der Cruyssenstr. 18",
    "sg:city":"Nevele",
    "sg:orig_category":"Bijouteries and horlogeries",
    "sg:phone":"+32 9 371 87 30",
    "sg:postcode":"9850",
    "sg:province":"Oost-Vlaanderen",
    "wof:name":"Huis De Bruyne",
    "wof:placetype":"venue"
},
  "geometry": {"coordinates":[3.5496110916,51.0339012146],"type":"Point"}
}