{
  "type": "Feature",
  "properties": {
    "addr:full":"Chauss\u00e9e De Waterloo 174-176 Rhode-saint-gen\u00e8se Vlaams-Brabant 1640",
    "addr:postcode":"174-176;1640",
    "addr:street":"Chausse\u0301E De Waterloo",
    "iso:country":"BE",
    "sg:address":"Chauss\u00e9e De Waterloo 174-176",
    "sg:city":"Rhode-saint-gen\u00e8se",
    "sg:classifiers":[
        {
            "category":"Shopping",
            "subcategory":"Antiques",
            "type":"Retail Goods"
        }
    ],
    "sg:phone":"+32 2 358 28 08",
    "sg:postcode":"1640",
    "sg:province":"Vlaams-Brabant",
    "wof:name":"Galerie St-germain",
    "wof:placetype":"venue"
},
  "geometry": {"coordinates":[4.3935680389,50.7489318848],"type":"Point"}
}