{
  "type": "Feature",
  "properties": {
    "iso:country":"BE",
    "sg:address":"Hoogstraat 11",
    "sg:city":"Boom",
    "sg:classifiers":[
        {
            "category":"Shopping",
            "subcategory":"Clothing, Apparel, & Fashions",
            "type":"Retail Goods"
        }
    ],
    "sg:phone":"+32 3 888 37 68",
    "sg:postcode":"2850",
    "sg:province":"Antwerpen",
    "sg:tags":[
        "underwear",
        "lingerie",
        "-"
    ],
    "wof:name":"Jenny Bvba",
    "wof:placetype":"venue"
},
  "geometry": {"coordinates":[4.3647289276,51.0859718323],"type":"Point"}
}