{
  "type": "Feature",
  "properties": {
    "iso:country":"BE",
    "sg:address":"Av Jean Jaur\u00e8s 46",
    "sg:city":"Bruxelles",
    "sg:classifiers":[
        {
            "category":"Professional",
            "subcategory":"Business Services",
            "type":"Services"
        }
    ],
    "sg:phone":"+32 2 215 04 01",
    "sg:postcode":"1030",
    "sg:province":"Bruxelles-Capitale",
    "sg:tags":[
        "chemical",
        "pharmaceutical",
        "advice",
        "pharmacy"
    ],
    "wof:name":"Laboratoire De Controle Et Danalyse Sa",
    "wof:placetype":"venue"
},
  "geometry": {"coordinates":[4.3847579956,50.877658844],"type":"Point"}
}