{
  "type": "Feature",
  "properties": {
    "iso:country":"BE",
    "sg:address":"Provincieweg 92",
    "sg:city":"Gistel (moere)",
    "sg:classifiers":[
        {
            "category":"Personal",
            "subcategory":"Beauty Salon",
            "type":"Services"
        }
    ],
    "sg:phone":"+32 59 27 71 88",
    "sg:postcode":"8470",
    "sg:province":"West-Vlaanderen",
    "sg:tags":[
        "lady",
        "-",
        "hairdressing"
    ],
    "wof:name":"Verduyn M",
    "wof:placetype":"venue"
},
  "geometry": {"coordinates":[2.9592149258,51.1237106323],"type":"Point"}
}