{
  "type": "Feature",
  "properties": {
    "addr:full":"Rue De Waremme 21a Berloz Li\u00e8ge 4257",
    "addr:housenumber":"21a",
    "addr:postcode":"4257",
    "addr:street":"Rue De Waremme",
    "iso:country":"BE",
    "sg:address":"Rue De Waremme 21a",
    "sg:city":"Berloz",
    "sg:classifiers":[
        {
            "category":"Education",
            "subcategory":"Special Training",
            "type":"Public Place"
        }
    ],
    "sg:phone":"+32 479 37 02 17",
    "sg:postcode":"4257",
    "sg:province":"Li\u00e8ge",
    "sg:tags":[
        "school",
        "flying"
    ],
    "wof:name":"Bas E",
    "wof:placetype":"venue"
},
  "geometry": {"coordinates":[5.2214970589,50.6958847046],"type":"Point"}
}