{
  "type": "Feature",
  "properties": {
    "iso:country":"BE",
    "sg:address":"Benedenstraat 9",
    "sg:city":"Roosdaal",
    "sg:orig_category":"Fruitteelt",
    "sg:phone":"+32 53 66 92 80",
    "sg:postcode":"1761",
    "sg:province":"Vlaams-Brabant",
    "wof:name":"Frans Coremans",
    "wof:placetype":"venue"
},
  "geometry": {"coordinates":[4.136548996,50.848526001],"type":"Point"}
}