{
  "type": "Feature",
  "properties": {
    "iso:country":"BE",
    "sg:address":"Zammelseweg 141",
    "sg:city":"Geel",
    "sg:orig_category":"Produits laitiers and huiles comestibles Gr",
    "sg:phone":"+32 14 54 44 65",
    "sg:postcode":"2440",
    "sg:province":"Antwerpen",
    "wof:name":"Govers",
    "wof:placetype":"venue"
},
  "geometry": {"coordinates":[4.954875946,51.1005783081],"type":"Point"}
}