{
  "type": "Feature",
  "properties": {
    "iso:country":"BE",
    "sg:address":"Sint-rochusstraat 17",
    "sg:city":"Mouscron (herseaux)",
    "sg:classifiers":[
        {
            "category":"Home & Garden",
            "subcategory":"Hardware",
            "type":"Retail Goods"
        }
    ],
    "sg:phone":"+32 56 34 05 48",
    "sg:postcode":"7712",
    "sg:province":"Hainaut",
    "sg:tags":[
        "builders'",
        "-",
        "furniture"
    ],
    "wof:name":"Fapim Benelux",
    "wof:placetype":"venue"
},
  "geometry": {"coordinates":[3.2429950237,50.7182998657],"type":"Point"}
}