{
  "type": "Feature",
  "properties": {
    "iso:country":"BE",
    "sg:address":"Sint-godelievestraat 6",
    "sg:city":"Kortrijk",
    "sg:orig_category":"Activit\u00e9s diverses d'imprimerie",
    "sg:phone":"+32 56 35 03 53",
    "sg:postcode":"8501",
    "sg:province":"West-Vlaanderen",
    "wof:name":"Frederic De Ruyck",
    "wof:placetype":"venue"
},
  "geometry": {"coordinates":[3.2566230297,50.8399047852],"type":"Point"}
}