{
  "type": "Feature",
  "properties": {
    "addr:full":"Berkstraat 42 Bekkevoort Vlaams-Brabant 3460",
    "addr:housenumber":"42",
    "addr:postcode":"3460",
    "addr:street":"Berkstraat",
    "iso:country":"BE",
    "sg:address":"Berkstraat 42",
    "sg:city":"Bekkevoort",
    "sg:orig_category":"Boekhouders",
    "sg:phone":"+32 13 33 48 27",
    "sg:postcode":"3460",
    "sg:province":"Vlaams-Brabant",
    "wof:name":"H. Lambrechts",
    "wof:placetype":"venue"
},
  "geometry": {"coordinates":[4.9778170586,50.9416618347],"type":"Point"}
}