{
  "type": "Feature",
  "properties": {
    "iso:country":"BE",
    "sg:address":"Rue Alfred Defuisseaux 49",
    "sg:city":"Soumagne",
    "sg:orig_category":"Slagers",
    "sg:phone":"+32 4 377 56 31",
    "sg:postcode":"4630",
    "sg:province":"Li\u00e8ge",
    "wof:name":"Jean Henrard",
    "wof:placetype":"venue"
},
  "geometry": {"coordinates":[5.7476458549,50.6067619324],"type":"Point"}
}