{
  "type": "Feature",
  "properties": {
    "addr:full":"Nieuwrodese Steenweg 124 Aarschot Vlaams-Brabant 3200",
    "addr:housenumber":"124",
    "addr:postcode":"3200",
    "addr:street":"Steenweg",
    "iso:country":"BE",
    "sg:address":"Nieuwrodese Steenweg 124",
    "sg:city":"Aarschot",
    "sg:classifiers":[
        {
            "category":"Building & Trades",
            "subcategory":"Construction",
            "type":"Services"
        }
    ],
    "sg:phone":"+32 16 56 83 02",
    "sg:postcode":"3200",
    "sg:province":"Vlaams-Brabant",
    "sg:tags":[
        "stucco",
        "contractor"
    ],
    "wof:name":"Vandegaer R",
    "wof:placetype":"venue"
},
  "geometry": {"coordinates":[4.8351597786,50.9700813293],"type":"Point"}
}