{
  "type": "Feature",
  "properties": {
    "addr:full":"Avenue Comte G\u00e9rard D'ursel 185 Grez-doiceau Brabant Wallon 1390",
    "addr:housenumber":"185",
    "addr:postcode":"1390",
    "addr:street":"Avenue Comte Ge\u0301Rard D'Ursel",
    "iso:country":"BE",
    "sg:address":"Avenue Comte G\u00e9rard D'ursel 185",
    "sg:city":"Grez-doiceau",
    "sg:classifiers":[
        {
            "category":"Banks & Credit Unions",
            "subcategory":"Investment Brokerage",
            "type":"Services"
        }
    ],
    "sg:phone":"+32 10 84 24 39",
    "sg:postcode":"1390",
    "sg:province":"Brabant Wallon",
    "sg:tags":[
        "supply",
        "processing",
        "-",
        "access",
        "carrier",
        "data"
    ],
    "wof:name":"Fellowes Belux",
    "wof:placetype":"venue"
},
  "geometry": {"coordinates":[4.662484169,50.7226753235],"type":"Point"}
}