{
  "type": "Feature",
  "properties": {
    "iso:country":"BE",
    "sg:address":"Ranklaan 10",
    "sg:city":"Overijse",
    "sg:classifiers":[
        {
            "category":"Professional",
            "subcategory":"Accounting & Tax Preparation",
            "type":"Services"
        }
    ],
    "sg:phone":"+32 2 687 95 75",
    "sg:postcode":"3090",
    "sg:province":"Vlaams-Brabant",
    "sg:tags":[
        "bookkeeper"
    ],
    "wof:name":"Theuwissen D",
    "wof:placetype":"venue"
},
  "geometry": {"coordinates":[4.5117192268,50.7475967407],"type":"Point"}
}