{
  "type": "Feature",
  "properties": {
    "iso:country":"BE",
    "sg:address":"Chauss\u00c9e De Spa 90ba",
    "sg:city":"Theux",
    "sg:classifiers":[
        {
            "category":"Manufacturing",
            "subcategory":"Textiles",
            "type":"Manufacturing & Wholesale Goods"
        }
    ],
    "sg:phone":"+32 87 54 21 01",
    "sg:postcode":"4910",
    "sg:province":"Li\u00e8ge",
    "wof:name":"Pascale Gilson",
    "wof:placetype":"venue"
},
  "geometry": {"coordinates":[5.8156661987,50.5172576904],"type":"Point"}
}