{
  "type": "Feature",
  "properties": {
    "addr:full":"Risquons-toutsteenweg 275 Moeskroen/mouscron Hainaut 7700",
    "addr:housenumber":"275",
    "addr:postcode":"7700",
    "addr:street":"Moeskroen",
    "iso:country":"BE",
    "sg:address":"Risquons-toutsteenweg 275",
    "sg:city":"Moeskroen/mouscron",
    "sg:orig_category":"Brood, gebak and snoepgoed",
    "sg:phone":"+32 56 84 25 25",
    "sg:postcode":"7700",
    "sg:province":"Hainaut",
    "wof:name":"P\u00c2tisserie Du Madrigal",
    "wof:placetype":"venue"
},
  "geometry": {"coordinates":[3.2323200703,50.7400932312],"type":"Point"}
}