{
  "type": "Feature",
  "properties": {
    "addr:full":"Hoevenzavellaan 50 Genk (waterschei) Limburg 3600",
    "addr:housenumber":"50",
    "addr:postcode":"3600",
    "addr:street":"Hoevenzavellaan",
    "iso:country":"BE",
    "sg:address":"Hoevenzavellaan 50",
    "sg:city":"Genk (waterschei)",
    "sg:orig_category":"Non-Classified Establishments",
    "sg:phone":"+32 89 84 37 09",
    "sg:postcode":"3600",
    "sg:province":"Limburg",
    "wof:name":"White Beauty",
    "wof:placetype":"venue"
},
  "geometry": {"coordinates":[5.5078501701,51.0014686584],"type":"Point"}
}