{
  "type": "Feature",
  "properties": {
    "addr:full":"Rue De Tournai 199bb Brunehaut Hainaut 7620",
    "addr:housenumber":"199bb",
    "addr:postcode":"7620",
    "addr:street":"Rue De Tournai;Hainaut",
    "iso:country":"BE",
    "sg:address":"Rue De Tournai 199bb",
    "sg:city":"Brunehaut",
    "sg:orig_category":"M\u00e9decins and sp\u00e9cialistes",
    "sg:phone":"+32 69 34 42 13",
    "sg:postcode":"7620",
    "sg:province":"Hainaut",
    "wof:name":"J.p. Petillon",
    "wof:placetype":"venue"
},
  "geometry": {"coordinates":[3.4205698967,50.519908905],"type":"Point"}
}