{
  "type": "Feature",
  "properties": {
    "addr:full":"Korte Gasthuisstraat 18 Turnhout Antwerpen 2300",
    "addr:housenumber":"18",
    "addr:postcode":"2300",
    "addr:street":"Korte Gasthuisstraat",
    "iso:country":"BE",
    "sg:address":"Korte Gasthuisstraat 18",
    "sg:city":"Turnhout",
    "sg:classifiers":[
        {
            "category":"Shopping",
            "subcategory":"Clothing, Apparel, & Fashions",
            "type":"Retail Goods"
        }
    ],
    "sg:phone":"+32 14 41 33 36",
    "sg:postcode":"2300",
    "sg:province":"Antwerpen",
    "sg:tags":[
        "underwear",
        "lingerie",
        "-"
    ],
    "wof:name":"Silhouet",
    "wof:placetype":"venue"
},
  "geometry": {"coordinates":[4.9467129707,51.3225250244],"type":"Point"}
}