{
  "type": "Feature",
  "properties": {
    "addr:full":"Melkerijstraat 3 Ichtegem West-Vlaanderen 8480",
    "addr:housenumber":"3",
    "addr:postcode":"8480",
    "addr:street":"Melkerijstraat",
    "iso:country":"BE",
    "sg:address":"Melkerijstraat 3",
    "sg:city":"Ichtegem",
    "sg:classifiers":[
        {
            "category":"Personal",
            "subcategory":"Beauty Salon",
            "type":"Services"
        }
    ],
    "sg:phone":"+32 51 58 27 21",
    "sg:postcode":"8480",
    "sg:province":"West-Vlaanderen",
    "sg:tags":[
        "lady",
        "-",
        "hairdressing"
    ],
    "wof:name":"Josiane",
    "wof:placetype":"venue"
},
  "geometry": {"coordinates":[3.0146241188,51.0953521729],"type":"Point"}
}