{
  "type": "Feature",
  "properties": {
    "iso:country":"BE",
    "sg:address":"Kerkelei 18",
    "sg:city":"Brecht",
    "sg:classifiers":[
        {
            "category":"Fast Food",
            "type":"Food & Drink"
        }
    ],
    "sg:phone":"+32 3 313 86 69",
    "sg:postcode":"2960",
    "sg:province":"Antwerpen",
    "sg:tags":[
        "\u00c0",
        "emporter",
        "restaurants"
    ],
    "wof:name":"Robert Claes",
    "wof:placetype":"venue"
},
  "geometry": {"coordinates":[4.5743432045,51.2922744751],"type":"Point"}
}