{
  "type": "Feature",
  "properties": {
    "addr:full":"Pappelweg 27 Eupen Li\u00e8ge 4700",
    "addr:housenumber":"27",
    "addr:postcode":"4700",
    "addr:street":"Pappelweg",
    "iso:country":"BE",
    "sg:address":"Pappelweg 27",
    "sg:city":"Eupen",
    "sg:classifiers":[
        {
            "category":"Insurance",
            "subcategory":"Life Insurance",
            "type":"Services"
        }
    ],
    "sg:phone":"+32 87 55 40 06",
    "sg:postcode":"4700",
    "sg:province":"Li\u00e8ge",
    "sg:tags":[
        "assurance"
    ],
    "wof:name":"I. Schleck",
    "wof:placetype":"venue"
},
  "geometry": {"coordinates":[6.0223860741,50.6276245117],"type":"Point"}
}