{
  "type": "Feature",
  "properties": {
    "iso:country":"BE",
    "sg:address":"Schoolstraat 26",
    "sg:city":"Herselt",
    "sg:orig_category":"Enseignement maternel and primaire",
    "sg:phone":"+32 16 69 71 44",
    "sg:postcode":"2230",
    "sg:province":"Antwerpen",
    "wof:name":"Vrije Lagere School",
    "wof:placetype":"venue"
},
  "geometry": {"coordinates":[4.8295040131,51.0293579102],"type":"Point"}
}