{
  "type": "Feature",
  "properties": {
    "addr:full":"Broekkantstraat 16 Peer (grote Brogel) Limburg 3990",
    "addr:housenumber":"16",
    "addr:postcode":"3990",
    "addr:street":"Broekkantstraat;Grote Brogel Limburg",
    "iso:country":"BE",
    "sg:address":"Broekkantstraat 16",
    "sg:city":"Peer (grote Brogel)",
    "sg:classifiers":[
        {
            "category":"Building & Trades",
            "subcategory":"Electrical",
            "type":"Services"
        }
    ],
    "sg:phone":"+32 11 63 58 04",
    "sg:postcode":"3990",
    "sg:province":"Limburg",
    "sg:tags":[
        "electric",
        "-",
        "housewiring",
        "contractor"
    ],
    "wof:name":"Ceyssens S",
    "wof:placetype":"venue"
},
  "geometry": {"coordinates":[5.4992728233,51.1561317444],"type":"Point"}
}