{
  "type": "Feature",
  "properties": {
    "iso:country":"BE",
    "sg:address":"Ieperstraat 96",
    "sg:city":"Poperinge",
    "sg:orig_category":"Verplichte sociale verzekeringen",
    "sg:phone":"+32 57 33 36 50",
    "sg:postcode":"8970",
    "sg:province":"West-Vlaanderen",
    "wof:name":"Westvl. Liberaal Ziekenf.",
    "wof:placetype":"venue"
},
  "geometry": {"coordinates":[2.7318398952,50.8546257019],"type":"Point"}
}