{
  "type": "Feature",
  "properties": {
    "addr:full":"Boulevard Frankignoul 3 Li\u00c8ge Li\u00e8ge 4020",
    "addr:housenumber":"3",
    "addr:postcode":"4020",
    "addr:street":"Boulevard Frankignoul",
    "iso:country":"BE",
    "sg:address":"Boulevard Frankignoul 3",
    "sg:city":"Li\u00c8ge",
    "sg:orig_category":"Meubelzaken, woning- and keukeninrichting",
    "sg:phone":"+32 4 344 54 60",
    "sg:postcode":"4020",
    "sg:province":"Li\u00e8ge",
    "wof:name":"Le Roi Du Matelas",
    "wof:placetype":"venue"
},
  "geometry": {"coordinates":[5.5864181519,50.6283683777],"type":"Point"}
}