{
  "type": "Feature",
  "properties": {
    "addr:full":"Schoenmakersstraat 18 Gent (oostakker) Oost-Vlaanderen 9041",
    "addr:housenumber":"18",
    "addr:postcode":"9041",
    "addr:street":"Schoenmakersstraat",
    "iso:country":"BE",
    "sg:address":"Schoenmakersstraat 18",
    "sg:city":"Gent (oostakker)",
    "sg:classifiers":[
        {
            "category":"Health Services",
            "subcategory":"Dentist",
            "type":"Services"
        }
    ],
    "sg:phone":"+32 9 251 84 51",
    "sg:postcode":"9041",
    "sg:province":"Oost-Vlaanderen",
    "wof:name":"Van Houcke Lieselotte",
    "wof:placetype":"venue"
},
  "geometry": {"coordinates":[3.7632000446,51.0792198181],"type":"Point"}
}