{
  "type": "Feature",
  "properties": {
    "addr:full":"Avenue Du Centenaire 5 Mons (hyon) Hainaut 7022",
    "addr:housenumber":"5",
    "addr:postcode":"7022",
    "addr:street":"Avenue Du Centenaire",
    "iso:country":"BE",
    "sg:address":"Avenue Du Centenaire 5",
    "sg:city":"Mons (hyon)",
    "sg:classifiers":[
        {
            "category":"Health Services",
            "subcategory":"Doctor",
            "type":"Services"
        }
    ],
    "sg:phone":"+32 65 84 66 61",
    "sg:postcode":"7022",
    "sg:province":"Hainaut",
    "sg:tags":[
        "medicinephysicians",
        "surgeon"
    ],
    "wof:name":"De Vriendt J",
    "wof:placetype":"venue"
},
  "geometry": {"coordinates":[3.955534935,50.4399147034],"type":"Point"}
}