{
  "type": "Feature",
  "properties": {
    "iso:country":"BE",
    "sg:address":"Rue Des R\u00c9collets 25",
    "sg:city":"Binche",
    "sg:orig_category":"Articles m\u00e9dicaux and orthop\u00e9diques. Opticiens",
    "sg:phone":"+32 64 34 01 34",
    "sg:postcode":"7130",
    "sg:province":"Hainaut",
    "wof:name":"Binch'optic",
    "wof:placetype":"venue"
},
  "geometry": {"coordinates":[4.1672549248,50.4120368958],"type":"Point"}
}