{
  "type": "Feature",
  "properties": {
    "iso:country":"BE",
    "sg:address":"Kerkplein 3",
    "sg:city":"Wingene",
    "sg:orig_category":"Installation \u00e9lectrique r\u00e9sidentielle",
    "sg:phone":"+32 51 65 78 47",
    "sg:postcode":"8750",
    "sg:province":"West-Vlaanderen",
    "wof:name":"Peter Herman",
    "wof:placetype":"venue"
},
  "geometry": {"coordinates":[3.2778511047,51.0581855774],"type":"Point"}
}