{
  "type": "Feature",
  "properties": {
    "addr:full":"Rijselsestraat 39 Zedelgem (loppem) West-Vlaanderen 8210",
    "addr:housenumber":"39",
    "addr:postcode":"8210",
    "addr:street":"Rijselsestraat",
    "iso:country":"BE",
    "sg:address":"Rijselsestraat 39",
    "sg:city":"Zedelgem (loppem)",
    "sg:classifiers":[
        {
            "category":"Professional",
            "subcategory":"Computer Services",
            "type":"Services"
        }
    ],
    "sg:phone":"+32 50 82 49 28",
    "sg:postcode":"8210",
    "sg:province":"West-Vlaanderen",
    "sg:tags":[
        "-",
        "processing",
        "data",
        "software"
    ],
    "wof:name":"Cdc-soft Bvba",
    "wof:placetype":"venue"
},
  "geometry": {"coordinates":[3.1458399296,51.1376457214],"type":"Point"}
}