{
  "type": "Feature",
  "properties": {
    "iso:country":"BE",
    "sg:address":"De Breyne Peelaertstraat 12",
    "sg:city":"Diksmuide",
    "sg:classifiers":[
        {
            "category":"Farming",
            "subcategory":"Fish & Marine Products",
            "type":"Manufacturing & Wholesale Goods"
        }
    ],
    "sg:phone":"+32 51 50 25 20",
    "sg:postcode":"8600",
    "sg:province":"West-Vlaanderen",
    "sg:tags":[
        "retail",
        "-",
        "shellfish"
    ],
    "wof:name":"Saint Germain Frans",
    "wof:placetype":"venue"
},
  "geometry": {"coordinates":[2.8659009933,51.0337219238],"type":"Point"}
}