{
  "type": "Feature",
  "properties": {
    "addr:full":"Otterstraat 63 Turnhout Antwerpen 2300",
    "addr:housenumber":"63",
    "addr:postcode":"2300",
    "addr:street":"Otterstraat",
    "iso:country":"BE",
    "sg:address":"Otterstraat 63",
    "sg:city":"Turnhout",
    "sg:classifiers":[
        {
            "category":"Cafe",
            "type":"Food & Drink"
        }
    ],
    "sg:phone":"+32 14 43 15 34",
    "sg:postcode":"2300",
    "sg:province":"Antwerpen",
    "sg:tags":[
        "caf\u00e9s"
    ],
    "wof:name":"Caf\u00c9 Spotnic",
    "wof:placetype":"venue"
},
  "geometry": {"coordinates":[4.9530658722,51.3223114014],"type":"Point"}
}