{
  "type": "Feature",
  "properties": {
    "addr:full":"Rue De Mollendael 12 Beauvechain Brabant Wallon 1320",
    "addr:housenumber":"12",
    "addr:postcode":"1320",
    "addr:street":"Rue De Mollendael",
    "iso:country":"BE",
    "sg:address":"Rue De Mollendael 12",
    "sg:city":"Beauvechain",
    "sg:orig_category":"Eleveurs and marchands de porcs",
    "sg:phone":"+32 10 86 63 74",
    "sg:postcode":"1320",
    "sg:province":"Brabant Wallon",
    "wof:name":"Serge Vervaeren",
    "wof:placetype":"venue"
},
  "geometry": {"coordinates":[4.7677049637,50.7981872559],"type":"Point"}
}