{
  "type": "Feature",
  "properties": {
    "iso:country":"BE",
    "sg:address":"Nati\u00cbnlaan 37",
    "sg:city":"Knokke-heist",
    "sg:orig_category":"Antiek",
    "sg:phone":"+32 50 62 72 72",
    "sg:postcode":"8300",
    "sg:province":"West-Vlaanderen",
    "wof:name":"\u00b4t Paleis",
    "wof:placetype":"venue"
},
  "geometry": {"coordinates":[3.2867538929,51.339012146],"type":"Point"}
}