{
  "type": "Feature",
  "properties": {
    "addr:full":"Rue De Nivelles 52 Anderlues Hainaut 6150",
    "addr:housenumber":"52",
    "addr:postcode":"6150",
    "addr:street":"Rue De Nivelles",
    "iso:country":"BE",
    "sg:address":"Rue De Nivelles 52",
    "sg:city":"Anderlues",
    "sg:orig_category":"Plaatsen van vloer- and muurbekleding Schilders Verlichting and huishoudartikelen",
    "sg:phone":"+32 71 52 85 28",
    "sg:postcode":"6150",
    "sg:province":"Hainaut",
    "wof:name":"Antonini",
    "wof:placetype":"venue"
},
  "geometry": {"coordinates":[4.2751030922,50.4185714722],"type":"Point"}
}