{
  "type": "Feature",
  "properties": {
    "iso:country":"BE",
    "sg:address":"Rue Nicolas Dardenne 82",
    "sg:city":"Nandrin",
    "sg:orig_category":"Instituts de beaut\u00e9",
    "sg:phone":"+32 85 51 24 27",
    "sg:postcode":"4550",
    "sg:province":"Li\u00e8ge",
    "wof:name":"Le Coin Beaut\u00c9",
    "wof:placetype":"venue"
},
  "geometry": {"coordinates":[5.4204249382,50.5065155029],"type":"Point"}
}