{
  "type": "Feature",
  "properties": {
    "addr:full":"Pierstraat 228 Kontich Antwerpen 2550",
    "addr:housenumber":"228",
    "addr:postcode":"2550",
    "addr:street":"Pierstraat",
    "iso:country":"BE",
    "sg:address":"Pierstraat 228",
    "sg:city":"Kontich",
    "sg:orig_category":"Eleveurs de bovins",
    "sg:phone":"+32 3 457 44 53",
    "sg:postcode":"2550",
    "sg:province":"Antwerpen",
    "wof:name":"Rene S Jongers",
    "wof:placetype":"venue"
},
  "geometry": {"coordinates":[4.4185209274,51.1280593872],"type":"Point"}
}