{
  "type": "Feature",
  "properties": {
    "iso:country":"BE",
    "sg:address":"Oudenbos 42",
    "sg:city":"Aarschot",
    "sg:orig_category":"Producteurs de l\u00e9gumes. Producteurs de fruits",
    "sg:phone":"+32 16 50 00 50",
    "sg:postcode":"3202",
    "sg:province":"Vlaams-Brabant",
    "wof:name":"Fernand Bernar",
    "wof:placetype":"venue"
},
  "geometry": {"coordinates":[4.8978261948,50.9678039551],"type":"Point"}
}