{
  "type": "Feature",
  "properties": {
    "iso:country":"BE",
    "sg:address":"L\u00c9on Bekaertlaan 11",
    "sg:city":"Aalter",
    "sg:orig_category":"Huishoudapparaten, televisies and radio's Installatie van houten of kunststof schrijnwerk MEUBELONTW",
    "sg:phone":"+32 9 374 37 31",
    "sg:postcode":"9880",
    "sg:province":"Oost-Vlaanderen",
    "wof:name":"Fa. Maran",
    "wof:placetype":"venue"
},
  "geometry": {"coordinates":[3.4565160275,51.1027984619],"type":"Point"}
}