{
  "type": "Feature",
  "properties": {
    "addr:full":"Rue Henri Aubry 11 La Louvi\u00e8re (haine-saint-paul) Hainaut 7100",
    "addr:housenumber":"11",
    "addr:postcode":"7100",
    "addr:street":"Rue Henri Aubry",
    "iso:country":"BE",
    "sg:address":"Rue Henri Aubry 11",
    "sg:city":"La Louvi\u00e8re (haine-saint-paul)",
    "sg:classifiers":[
        {
            "category":"Organizations",
            "subcategory":"Community Association",
            "type":"Services"
        }
    ],
    "sg:phone":"+32 64 21 73 55",
    "sg:postcode":"7100",
    "sg:province":"Hainaut",
    "sg:tags":[
        "cultural"
    ],
    "wof:name":"Artifices Asbl",
    "wof:placetype":"venue"
},
  "geometry": {"coordinates":[4.1850848198,50.4748649597],"type":"Point"}
}