{
  "type": "Feature",
  "properties": {
    "addr:full":"Kruinstraat 11 Lokeren Oost-Vlaanderen 9160",
    "addr:housenumber":"11",
    "addr:postcode":"9160",
    "addr:street":"Kruinstraat",
    "iso:country":"BE",
    "sg:address":"Kruinstraat 11",
    "sg:city":"Lokeren",
    "sg:classifiers":[
        {
            "category":"Professional",
            "subcategory":"Accounting & Tax Preparation",
            "type":"Services"
        }
    ],
    "sg:phone":"+32 9 348 50 74",
    "sg:postcode":"9160",
    "sg:province":"Oost-Vlaanderen",
    "sg:tags":[
        "pattern",
        "maker"
    ],
    "wof:name":"Schelfhout L",
    "wof:placetype":"venue"
},
  "geometry": {"coordinates":[4.0172491074,51.0950737],"type":"Point"}
}