{
  "type": "Feature",
  "properties": {
    "addr:full":"Ommegangstraat 27 Deinze Oost-Vlaanderen 9800",
    "addr:housenumber":"27",
    "addr:postcode":"9800",
    "addr:street":"Ommegangstraat",
    "iso:country":"BE",
    "sg:address":"Ommegangstraat 27",
    "sg:city":"Deinze",
    "sg:orig_category":"Artiesten and kunstenaars",
    "sg:phone":"+32 9 386 86 16",
    "sg:postcode":"9800",
    "sg:province":"Oost-Vlaanderen",
    "wof:name":"Tony De Kimpe",
    "wof:placetype":"venue"
},
  "geometry": {"coordinates":[3.5310149193,50.977935791],"type":"Point"}
}