{
  "type": "Feature",
  "properties": {
    "addr:full":"Rue De La Station 64-66 Mouscron Hainaut 7700",
    "addr:housenumber":"64-66",
    "addr:postcode":"7700",
    "addr:street":"Rue De La Station",
    "iso:country":"BE",
    "sg:address":"Rue De La Station 64-66",
    "sg:city":"Mouscron",
    "sg:classifiers":[
        {
            "category":"Health Services",
            "subcategory":"Doctor",
            "type":"Services"
        }
    ],
    "sg:phone":"+32 56 33 10 97",
    "sg:postcode":"7700",
    "sg:province":"Hainaut",
    "sg:tags":[
        "medicinephysicians",
        "surgeon"
    ],
    "wof:name":"De Cock T",
    "wof:placetype":"venue"
},
  "geometry": {"coordinates":[3.2212300301,50.7434082031],"type":"Point"}
}