{
  "type": "Feature",
  "properties": {
    "addr:full":"Rue Des D\u00c9port\u00c9s 48 Soumagne Li\u00e8ge 4630",
    "addr:housenumber":"48",
    "addr:postcode":"4630",
    "addr:street":"Rue Des De\u0301Porte\u0301S",
    "iso:country":"BE",
    "sg:address":"Rue Des D\u00c9port\u00c9s 48",
    "sg:city":"Soumagne",
    "sg:orig_category":"Entretien and r\u00e9parations de voitures",
    "sg:phone":"+32 4 377 52 30",
    "sg:postcode":"4630",
    "sg:province":"Li\u00e8ge",
    "wof:name":"Carrosserie Philippe",
    "wof:placetype":"venue"
},
  "geometry": {"coordinates":[5.7497057915,50.6117935181],"type":"Point"}
}