{
  "type": "Feature",
  "properties": {
    "addr:full":"Schrijberg 165a Sint-niklaas (groot) Oost-Vlaanderen 9111",
    "addr:housenumber":"165a",
    "addr:postcode":"9111",
    "addr:street":"Schrijberg;Groot Oost-Vlaanderen",
    "iso:country":"BE",
    "sg:address":"Schrijberg 165a",
    "sg:city":"Sint-niklaas (groot)",
    "sg:classifiers":[
        {
            "category":"Personal",
            "subcategory":"Beauty Salon",
            "type":"Services"
        }
    ],
    "sg:phone":"+32 3 772 25 72",
    "sg:postcode":"9111",
    "sg:province":"Oost-Vlaanderen",
    "sg:tags":[
        "de",
        "coiffure"
    ],
    "wof:name":"Coiffure Pastel",
    "wof:placetype":"venue"
},
  "geometry": {"coordinates":[4.071018219,51.1380271912],"type":"Point"}
}