{
  "type": "Feature",
  "properties": {
    "iso:country":"BE",
    "sg:address":"Square De L\u00c9opoldville 17",
    "sg:city":"Etterbeek",
    "sg:orig_category":"M\u00e9decins and sp\u00e9cialistes",
    "sg:phone":"+32 2 649 00 01",
    "sg:postcode":"1040",
    "sg:province":"Bruxelles-Capitale",
    "wof:name":"Elisabeth Dugas",
    "wof:placetype":"venue"
},
  "geometry": {"coordinates":[4.3836731911,50.8283157349],"type":"Point"}
}