{
  "type": "Feature",
  "properties": {
    "iso:country":"BE",
    "sg:address":"Ertbruggestraat 3",
    "sg:city":"Wijnegem",
    "sg:orig_category":"Artsen and specialisten",
    "sg:phone":"+32 3 353 06 90",
    "sg:postcode":"2110",
    "sg:province":"Antwerpen",
    "wof:name":"Jan De Wachter",
    "wof:placetype":"venue"
},
  "geometry": {"coordinates":[4.5056538582,51.2306060791],"type":"Point"}
}