{
  "type": "Feature",
  "properties": {
    "iso:country":"BE",
    "sg:address":"Bellegemsestraat 6",
    "sg:city":"Kortrijk",
    "sg:orig_category":"Banken and kredietinstellingen",
    "sg:phone":"+32 56 21 34 94",
    "sg:postcode":"8510",
    "sg:province":"West-Vlaanderen",
    "wof:name":"Kbc",
    "wof:placetype":"venue"
},
  "geometry": {"coordinates":[3.2805809975,50.7776756287],"type":"Point"}
}