{
  "type": "Feature",
  "properties": {
    "iso:country":"BE",
    "sg:address":"Rue De Mery 11",
    "sg:city":"Esneux",
    "sg:classifiers":[
        {
            "category":"Professional",
            "subcategory":"Computer Services",
            "type":"Services"
        }
    ],
    "sg:phone":"+32 4 239 09 36",
    "sg:postcode":"4130",
    "sg:province":"Li\u00e8ge",
    "sg:tags":[
        "-",
        "processing",
        "data"
    ],
    "wof:name":"Sunergon Informatique",
    "wof:placetype":"venue"
},
  "geometry": {"coordinates":[5.5786747932,50.5373497009],"type":"Point"}
}