{
  "type": "Feature",
  "properties": {
    "addr:full":"R D'enhaive Namur Namur 5100",
    "addr:postcode":"5100",
    "iso:country":"BE",
    "sg:address":"R D'enhaive",
    "sg:city":"Namur",
    "sg:orig_category":"Installatie van houten of kunststof schrijnwerk",
    "sg:phone":"+32 81 30 07 70",
    "sg:postcode":"5100",
    "sg:province":"Namur",
    "wof:name":"Deveux",
    "wof:placetype":"venue"
},
  "geometry": {"coordinates":[4.8745741844,50.4576568604],"type":"Point"}
}