{
  "type": "Feature",
  "properties": {
    "iso:country":"BE",
    "sg:address":"Avenue Moli\u00e8re 192",
    "sg:city":"Bruxelles (ixelles)",
    "sg:classifiers":[
        {
            "category":"Government",
            "subcategory":"Embassy",
            "type":"Public Place"
        }
    ],
    "sg:phone":"+32 2 340 02 70",
    "sg:postcode":"1050",
    "sg:province":"Bruxelles-Capitale",
    "sg:tags":[
        "consulate"
    ],
    "wof:name":"Witrusland (ambassade)",
    "wof:placetype":"venue"
},
  "geometry": {"coordinates":[4.3543581963,50.8155822754],"type":"Point"}
}