{
  "type": "Feature",
  "properties": {
    "addr:full":"Chauss\u00e9e De Tirlemont 214 Wanze (vinalmont) Li\u00e8ge 4520",
    "addr:housenumber":"214",
    "addr:postcode":"4520",
    "addr:street":"Chausse\u0301E De Tirlemont",
    "iso:country":"BE",
    "sg:address":"Chauss\u00e9e De Tirlemont 214",
    "sg:city":"Wanze (vinalmont)",
    "sg:classifiers":[
        {
            "category":"Professional",
            "subcategory":"Testing Lab",
            "type":"Services"
        }
    ],
    "sg:phone":"+32 85 21 18 69",
    "sg:postcode":"4520",
    "sg:province":"Li\u00e8ge",
    "sg:tags":[
        "chemist"
    ],
    "wof:name":"Badot F",
    "wof:placetype":"venue"
},
  "geometry": {"coordinates":[5.2215199471,50.5430488586],"type":"Point"}
}