{
  "type": "Feature",
  "properties": {
    "addr:full":"Kuurnsestraat 60ba Lendelede West-Vlaanderen 8860",
    "addr:postcode":"8860",
    "addr:street":"Kuurnsestraat",
    "iso:country":"BE",
    "sg:address":"Kuurnsestraat 60ba",
    "sg:city":"Lendelede",
    "sg:classifiers":[
        {
            "category":"Shopping",
            "subcategory":"Clothing, Apparel, & Fashions",
            "type":"Retail Goods"
        }
    ],
    "sg:phone":"+32 51 30 07 79",
    "sg:postcode":"8860",
    "sg:province":"West-Vlaanderen",
    "sg:tags":[
        "v\u00eatements",
        "pour",
        "dame"
    ],
    "wof:name":"Bouss",
    "wof:placetype":"venue"
},
  "geometry": {"coordinates":[3.2436330318,50.8786506653],"type":"Point"}
}