{
  "type": "Feature",
  "properties": {
    "addr:full":"Overvloedstraat 66 Sint-joost-ten-node/saint-josse-ten-noode Bruxelles-Capitale 1210",
    "addr:housenumber":"66",
    "addr:postcode":"1210",
    "addr:street":"Overvloedstraat",
    "iso:country":"BE",
    "sg:address":"Overvloedstraat 66",
    "sg:city":"Sint-joost-ten-node/saint-josse-ten-noode",
    "sg:orig_category":"Artiesten and kunstenaars",
    "sg:phone":"+32 2 218 23 36",
    "sg:postcode":"1210",
    "sg:province":"Bruxelles-Capitale",
    "wof:name":"Jean Couvrin",
    "wof:placetype":"venue"
},
  "geometry": {"coordinates":[4.3717708588,50.8564453125],"type":"Point"}
}