{
  "type": "Feature",
  "properties": {
    "iso:country":"BE",
    "sg:address":"Lelielaan 3",
    "sg:city":"Wachtebeke",
    "sg:orig_category":"Belastingconsulenten Diverse juridische dienstverlening",
    "sg:phone":"+32 9 342 90 60",
    "sg:postcode":"9185",
    "sg:province":"Oost-Vlaanderen",
    "wof:name":"Dodone",
    "wof:placetype":"venue"
},
  "geometry": {"coordinates":[3.8512489796,51.1755561829],"type":"Point"}
}