{
  "type": "Feature",
  "properties": {
    "iso:country":"BE",
    "sg:address":"Denderhoutembaan 95",
    "sg:city":"Ninove",
    "sg:classifiers":[
        {
            "category":"Shopping Center",
            "type":"Public Place"
        }
    ],
    "sg:phone":"+32 54 34 30 79",
    "sg:postcode":"9400",
    "sg:province":"Oost-Vlaanderen",
    "sg:tags":[
        "enseignement",
        "formation"
    ],
    "wof:name":"De Lange Jo",
    "wof:placetype":"venue"
},
  "geometry": {"coordinates":[4.0213518143,50.8437194824],"type":"Point"}
}