{
  "type": "Feature",
  "properties": {
    "iso:country":"BE",
    "sg:address":"Nieuwe Kassei 10a",
    "sg:city":"Kampenhout",
    "sg:classifiers":[
        {
            "category":"Professional",
            "subcategory":"Management & Consulting",
            "type":"Services"
        }
    ],
    "sg:phone":"+32 16 65 90 24",
    "sg:postcode":"1910",
    "sg:province":"Vlaams-Brabant",
    "sg:tags":[
        "consultant"
    ],
    "wof:name":"Management Visie Tot Excelleren",
    "wof:placetype":"venue"
},
  "geometry": {"coordinates":[4.5648207664,50.9256057739],"type":"Point"}
}