{
  "type": "Feature",
  "properties": {
    "addr:full":"Schoolstraat 84 Lommel Limburg 3920",
    "addr:housenumber":"84",
    "addr:postcode":"3920",
    "addr:street":"Schoolstraat",
    "iso:country":"BE",
    "sg:address":"Schoolstraat 84",
    "sg:city":"Lommel",
    "sg:classifiers":[
        {
            "category":"Home & Garden",
            "subcategory":"Home Furnishings",
            "type":"Retail Goods"
        }
    ],
    "sg:phone":"+32 11 80 11 28",
    "sg:postcode":"3920",
    "sg:province":"Limburg",
    "sg:tags":[
        "interior",
        "decoration"
    ],
    "wof:name":"Dekkers F",
    "wof:placetype":"venue"
},
  "geometry": {"coordinates":[5.3607258797,51.2343635559],"type":"Point"}
}