{
  "type": "Feature",
  "properties": {
    "iso:country":"BE",
    "sg:address":"Rue Du Moulin 235",
    "sg:city":"Charleroi",
    "sg:orig_category":"Verlichting and huishoudartikelen",
    "sg:phone":"+32 71 30 91 10",
    "sg:postcode":"6061",
    "sg:province":"Hainaut",
    "wof:name":"Typic",
    "wof:placetype":"venue"
},
  "geometry": {"coordinates":[4.49087286,50.4102020264],"type":"Point"}
}