{
  "type": "Feature",
  "properties": {
    "iso:country":"BE",
    "sg:address":"Dr\u00c8ve De La Ferme 18",
    "sg:city":"Wezembeek-oppem/wezembeek-oppem",
    "sg:orig_category":"Artistes ind\u00e9pendants",
    "sg:phone":"+32 2 731 08 76",
    "sg:postcode":"1970",
    "sg:province":"Vlaams-Brabant",
    "wof:name":"Johan Van Assche",
    "wof:placetype":"venue"
},
  "geometry": {"coordinates":[4.4912700653,50.8503608704],"type":"Point"}
}