{
  "type": "Feature",
  "properties": {
    "addr:full":"Brugseweg 221 Langemark-poelkapelle (poelkapelle) West-Vlaanderen 8920",
    "addr:housenumber":"221",
    "addr:postcode":"8920",
    "addr:street":"Brugseweg",
    "iso:country":"BE",
    "sg:address":"Brugseweg 221",
    "sg:city":"Langemark-poelkapelle (poelkapelle)",
    "sg:classifiers":[
        {
            "category":"Bars & Pubs",
            "type":"Food & Drink"
        }
    ],
    "sg:phone":"+32 57 48 72 95",
    "sg:postcode":"8920",
    "sg:province":"West-Vlaanderen",
    "wof:name":"De Wilde M",
    "wof:placetype":"venue"
},
  "geometry": {"coordinates":[2.9379899502,50.8924789429],"type":"Point"}
}