{
  "type": "Feature",
  "properties": {
    "addr:full":"Rue De La Montagne 2 Aubange Luxembourg 6791",
    "addr:housenumber":"2",
    "addr:postcode":"6791",
    "addr:street":"Rue De La Montagne",
    "iso:country":"BE",
    "sg:address":"Rue De La Montagne 2",
    "sg:city":"Aubange",
    "sg:orig_category":"M\u00e9decins and sp\u00e9cialistes",
    "sg:phone":"+32 63 38 91 80",
    "sg:postcode":"6791",
    "sg:province":"Luxembourg",
    "wof:name":"Jean Launois",
    "wof:placetype":"venue"
},
  "geometry": {"coordinates":[5.8368301392,49.5627288818],"type":"Point"}
}