{
  "type": "Feature",
  "properties": {
    "iso:country":"BE",
    "sg:address":"Minderbroedersstraat 16",
    "sg:city":"Genk",
    "sg:orig_category":"Diverse opleidingen and onderwijs",
    "sg:phone":"+32 89 38 69 81",
    "sg:postcode":"3600",
    "sg:province":"Limburg",
    "wof:name":"Route Trainingscentrum",
    "wof:placetype":"venue"
},
  "geometry": {"coordinates":[5.5125279427,51.0010757446],"type":"Point"}
}