{
  "type": "Feature",
  "properties": {
    "addr:full":"Rue De La Soierie 21 Vorst/forest Bruxelles-Capitale 1190",
    "addr:housenumber":"21",
    "addr:postcode":"1190",
    "addr:street":"Rue De La Soierie;/ Forest",
    "iso:country":"BE",
    "sg:address":"Rue De La Soierie 21",
    "sg:city":"Vorst/forest",
    "sg:orig_category":"M\u00e9decins and sp\u00e9cialistes",
    "sg:phone":"+32 2 332 37 93",
    "sg:postcode":"1190",
    "sg:province":"Bruxelles-Capitale",
    "wof:name":"Vincent De Brouwere",
    "wof:placetype":"venue"
},
  "geometry": {"coordinates":[4.3124918938,50.8058586121],"type":"Point"}
}