{
  "type": "Feature",
  "properties": {
    "addr:full":"Chauss\u00e9e De Mons 463 Bruxelles (anderlecht) Bruxelles-Capitale 1070",
    "addr:housenumber":"463",
    "addr:postcode":"1070",
    "addr:street":"Chausse\u0301E De Mons",
    "iso:country":"BE",
    "sg:address":"Chauss\u00e9e De Mons 463",
    "sg:city":"Bruxelles (anderlecht)",
    "sg:classifiers":[
        {
            "category":"Professional",
            "subcategory":"Art Services",
            "type":"Services"
        }
    ],
    "sg:phone":"+32 2 527 87 61",
    "sg:postcode":"1070",
    "sg:province":"Bruxelles-Capitale",
    "sg:tags":[
        "installation",
        "cafe",
        "-",
        "equipment"
    ],
    "wof:name":"Belafrica",
    "wof:placetype":"venue"
},
  "geometry": {"coordinates":[4.3169369698,50.8362617493],"type":"Point"}
}