{
  "type": "Feature",
  "properties": {
    "addr:full":"Chemin De Gistoux 1 Chaumont-gistoux Brabant Wallon 1325",
    "addr:housenumber":"1",
    "addr:postcode":"1325",
    "addr:street":"Chemin De Gistoux",
    "iso:country":"BE",
    "sg:address":"Chemin De Gistoux 1",
    "sg:city":"Chaumont-gistoux",
    "sg:orig_category":"Eleveurs de bovins",
    "sg:phone":"+32 10 68 80 44",
    "sg:postcode":"1325",
    "sg:province":"Brabant Wallon",
    "wof:name":"Yvan Devlesaver",
    "wof:placetype":"venue"
},
  "geometry": {"coordinates":[4.6897549629,50.694316864],"type":"Point"}
}