{
  "type": "Feature",
  "properties": {
    "addr:full":"Rue Du Parc 33-35 Li\u00e8ge 1 (li\u00e8ge 2) Li\u00e8ge 4020",
    "addr:housenumber":"2",
    "addr:postcode":"33-35;4020",
    "addr:street":"Rue Du Parc;Lie\u0300Ge",
    "iso:country":"BE",
    "sg:address":"Rue Du Parc 33-35",
    "sg:city":"Li\u00e8ge 1 (li\u00e8ge 2)",
    "sg:classifiers":[
        {
            "category":"Health Services",
            "subcategory":"Doctor",
            "type":"Services"
        }
    ],
    "sg:phone":"+32 4 344 97 77",
    "sg:postcode":"4020",
    "sg:province":"Li\u00e8ge",
    "sg:tags":[
        "medicinephysicians",
        "surgeon"
    ],
    "wof:name":"Huskin J-p",
    "wof:placetype":"venue"
},
  "geometry": {"coordinates":[5.5756778717,50.6313438416],"type":"Point"}
}