{
  "type": "Feature",
  "properties": {
    "addr:full":"Marktplein 17 Sint-lievens-houtem Oost-Vlaanderen 9520",
    "addr:housenumber":"17",
    "addr:postcode":"9520",
    "addr:street":"Marktplein;Oost-Vlaanderen",
    "iso:country":"BE",
    "sg:address":"Marktplein 17",
    "sg:city":"Sint-lievens-houtem",
    "sg:orig_category":"Verlichting and huishoudartikelen",
    "sg:phone":"+32 53 63 01 08",
    "sg:postcode":"9520",
    "sg:province":"Oost-Vlaanderen",
    "wof:name":"Verzekeringen D'hauwers",
    "wof:placetype":"venue"
},
  "geometry": {"coordinates":[3.8576009274,50.9200897217],"type":"Point"}
}