{
  "type": "Feature",
  "properties": {
    "addr:full":"Rue Des Clarisses 50 Li\u00c8ge Li\u00e8ge 4000",
    "addr:housenumber":"50",
    "addr:postcode":"4000",
    "addr:street":"Rue Des Clarisses",
    "iso:country":"BE",
    "sg:address":"Rue Des Clarisses 50",
    "sg:city":"Li\u00c8ge",
    "sg:orig_category":"Kapsalons",
    "sg:phone":"+32 4 223 23 54",
    "sg:postcode":"4000",
    "sg:province":"Li\u00e8ge",
    "wof:name":"Coiffure Perri\u00c8re",
    "wof:placetype":"venue"
},
  "geometry": {"coordinates":[5.5708971024,50.6386871338],"type":"Point"}
}