{
  "type": "Feature",
  "properties": {
    "addr:full":"Sint-lenaartseweg 210 Wuustwezel (loenhout) Antwerpen 2990",
    "addr:housenumber":"210",
    "addr:postcode":"2990",
    "iso:country":"BE",
    "sg:address":"Sint-lenaartseweg 210",
    "sg:city":"Wuustwezel (loenhout)",
    "sg:classifiers":[
        {
            "category":"Farming",
            "subcategory":"Crops",
            "type":"Manufacturing & Wholesale Goods"
        }
    ],
    "sg:phone":"+32 3 313 62 42",
    "sg:postcode":"2990",
    "sg:province":"Antwerpen",
    "sg:tags":[
        "vegetable",
        "fruit",
        "-",
        "grower"
    ],
    "wof:name":"Varico",
    "wof:placetype":"venue"
},
  "geometry": {"coordinates":[4.6763768196,51.3776092529],"type":"Point"}
}