{
  "type": "Feature",
  "properties": {
    "addr:full":"Maastrichterstraat 385 Bilzen (mopertingen) Limburg 3740",
    "addr:housenumber":"385",
    "addr:postcode":"3740",
    "addr:street":"Maastrichterstraat",
    "iso:country":"BE",
    "sg:address":"Maastrichterstraat 385",
    "sg:city":"Bilzen (mopertingen)",
    "sg:classifiers":[
        {
            "category":"Bakery",
            "type":"Food & Drink"
        }
    ],
    "sg:phone":"+32 89 41 76 81",
    "sg:postcode":"3740",
    "sg:province":"Limburg",
    "sg:tags":[
        "confectioner",
        "baker"
    ],
    "wof:name":"St-martinus",
    "wof:placetype":"venue"
},
  "geometry": {"coordinates":[5.5271902084,50.8648300171],"type":"Point"}
}