{
  "type": "Feature",
  "properties": {
    "iso:country":"BE",
    "sg:address":"Heuntjesstraat 6",
    "sg:city":"Anzegem",
    "sg:classifiers":[
        {
            "category":"Professional",
            "subcategory":"Management & Consulting",
            "type":"Services"
        }
    ],
    "sg:phone":"+32 56 68 98 71",
    "sg:postcode":"8570",
    "sg:province":"West-Vlaanderen",
    "sg:tags":[
        "consultant",
        "agency",
        "advertising"
    ],
    "wof:name":"Graphisim",
    "wof:placetype":"venue"
},
  "geometry": {"coordinates":[3.4707360268,50.8437538147],"type":"Point"}
}