{
  "type": "Feature",
  "properties": {
    "addr:full":"Eedstraat 45 Anderlecht Bruxelles-Capitale 1070",
    "addr:housenumber":"45",
    "addr:postcode":"1070",
    "addr:street":"Eedstraat",
    "iso:country":"BE",
    "sg:address":"Eedstraat 45",
    "sg:city":"Anderlecht",
    "sg:orig_category":"Industri\u00eble wasserijen and droogkuis",
    "sg:phone":"+32 2 522 03 78",
    "sg:postcode":"1070",
    "sg:province":"Bruxelles-Capitale",
    "wof:name":"Duparc Cleaning",
    "wof:placetype":"venue"
},
  "geometry": {"coordinates":[4.3064990044,50.8386306763],"type":"Point"}
}