{
  "type": "Feature",
  "properties": {
    "addr:full":"Hinderhausen 3 Sankt Vith/saint-vith Li\u00e8ge 4784",
    "addr:housenumber":"3",
    "addr:postcode":"4784",
    "addr:street":"Hinderhausen",
    "iso:country":"BE",
    "sg:address":"Hinderhausen 3",
    "sg:city":"Sankt Vith/saint-vith",
    "sg:orig_category":"Elektrische installaties voor woningen",
    "sg:phone":"+32 80 22 83 33",
    "sg:postcode":"4784",
    "sg:province":"Li\u00e8ge",
    "wof:name":"Hubert Dahm",
    "wof:placetype":"venue"
},
  "geometry": {"coordinates":[6.0675911903,50.2596511841],"type":"Point"}
}