{
  "type": "Feature",
  "properties": {
    "addr:full":"Weverstraat 24 Hamme Oost-Vlaanderen 9220",
    "addr:housenumber":"24",
    "addr:postcode":"9220",
    "addr:street":"Weverstraat",
    "iso:country":"BE",
    "sg:address":"Weverstraat 24",
    "sg:city":"Hamme",
    "sg:orig_category":"Artiesten and kunstenaars",
    "sg:phone":"+32 52 47 26 76",
    "sg:postcode":"9220",
    "sg:province":"Oost-Vlaanderen",
    "wof:name":"Jean Ceelen",
    "wof:placetype":"venue"
},
  "geometry": {"coordinates":[4.1215748787,51.0820541382],"type":"Point"}
}