{
  "type": "Feature",
  "properties": {
    "iso:country":"BE",
    "sg:address":"Harmoniestraat 142",
    "sg:city":"Antwerpen",
    "sg:orig_category":"Diverse intermediaire producten Gh",
    "sg:phone":"+32 3 248 01 49",
    "sg:postcode":"2018",
    "sg:province":"Antwerpen",
    "wof:name":"Olivier Karsenty",
    "wof:placetype":"venue"
},
  "geometry": {"coordinates":[4.4078621864,51.199672699],"type":"Point"}
}