{
  "type": "Feature",
  "properties": {
    "addr:full":"Avenue De La Lib\u00e9ration 37a Sambreville (auvelais) Namur 5060",
    "addr:housenumber":"37a",
    "addr:postcode":"5060",
    "addr:street":"Avenue De La Libe\u0301Ration",
    "iso:country":"BE",
    "sg:address":"Avenue De La Lib\u00e9ration 37a",
    "sg:city":"Sambreville (auvelais)",
    "sg:classifiers":[
        {
            "category":"Shopping",
            "subcategory":"Gifts & Souvenirs",
            "type":"Retail Goods"
        }
    ],
    "sg:phone":"+32 71 74 15 45",
    "sg:postcode":"5060",
    "sg:province":"Namur",
    "sg:tags":[
        "-"
    ],
    "wof:name":"5\u00e8me Saison Sprl",
    "wof:placetype":"venue"
},
  "geometry": {"coordinates":[4.6285200119,50.4448738098],"type":"Point"}
}