{
  "type": "Feature",
  "properties": {
    "addr:full":"Avenue Louise 523 B31 Elsene/ixelles Bruxelles-Capitale 1050",
    "addr:housenumber":"523 b31",
    "addr:postcode":"1050",
    "addr:street":"Avenue Louise",
    "iso:country":"BE",
    "sg:address":"Avenue Louise 523 B31",
    "sg:city":"Elsene/ixelles",
    "sg:orig_category":"Advocaten and juridische adviseurs",
    "sg:phone":"+32 2 641 90 95",
    "sg:postcode":"1050",
    "sg:province":"Bruxelles-Capitale",
    "wof:name":"De Cort A.",
    "wof:placetype":"venue"
},
  "geometry": {"coordinates":[4.3798799515,50.8206710815],"type":"Point"}
}