{
  "type": "Feature",
  "properties": {
    "iso:country":"BE",
    "sg:address":"Boulevard L\u00c9opold 92bb",
    "sg:city":"Tournai",
    "sg:orig_category":"Algemeen secundair onderwijs Technisch and beroeps secundair onderwijs",
    "sg:phone":"+32 69 22 20 37",
    "sg:postcode":"7500",
    "sg:province":"Hainaut",
    "wof:name":"I.p.e.s.",
    "wof:placetype":"venue"
},
  "geometry": {"coordinates":[3.3768589497,50.6103248596],"type":"Point"}
}