{
  "type": "Feature",
  "properties": {
    "addr:full":"Avenue Reine Astrid 25 Waremme Li\u00e8ge 4300",
    "addr:housenumber":"25",
    "addr:postcode":"4300",
    "addr:street":"Avenue Reine Astrid",
    "iso:country":"BE",
    "sg:address":"Avenue Reine Astrid 25",
    "sg:city":"Waremme",
    "sg:classifiers":[
        {
            "category":"Food & Beverages",
            "subcategory":"Supermarket",
            "type":"Retail Goods"
        }
    ],
    "sg:phone":"+32 19 32 20 87",
    "sg:postcode":"4300",
    "sg:province":"Li\u00e8ge",
    "sg:tags":[
        "department",
        "store"
    ],
    "wof:name":"Herck Grand Magasin",
    "wof:placetype":"venue"
},
  "geometry": {"coordinates":[5.2507500648,50.6949462891],"type":"Point"}
}