{
  "type": "Feature",
  "properties": {
    "iso:country":"BE",
    "sg:address":"Alsembergse Steenweg 476",
    "sg:city":"Ukkel/uccle",
    "sg:orig_category":"Benzinestations and brandstoffen",
    "sg:phone":"+32 2 344 67 44",
    "sg:postcode":"1180",
    "sg:province":"Bruxelles-Capitale",
    "wof:name":"Texaco",
    "wof:placetype":"venue"
},
  "geometry": {"coordinates":[4.3378229141,50.8103218079],"type":"Point"}
}