{
  "type": "Feature",
  "properties": {
    "iso:country":"BE",
    "sg:address":"Leuvensebaan 154",
    "sg:city":"Putte",
    "sg:orig_category":"Non-Classified Establishments",
    "sg:phone":"+32 15 76 01 58",
    "sg:postcode":"2580",
    "sg:province":"Antwerpen",
    "wof:name":"Pirouette Bvba",
    "wof:placetype":"venue"
},
  "geometry": {"coordinates":[4.6344428062,51.0420608521],"type":"Point"}
}