{
  "type": "Feature",
  "properties": {
    "addr:full":"Kaulillerdorp 40 Bocholt Limburg 3950",
    "addr:housenumber":"40",
    "addr:postcode":"3950",
    "addr:street":"Kaulillerdorp",
    "iso:country":"BE",
    "sg:address":"Kaulillerdorp 40",
    "sg:city":"Bocholt",
    "sg:orig_category":"Supermarkten",
    "sg:phone":"+32 11 44 52 17",
    "sg:postcode":"3950",
    "sg:province":"Limburg",
    "wof:name":"Spar",
    "wof:placetype":"venue"
},
  "geometry": {"coordinates":[5.5792012215,51.1726074219],"type":"Point"}
}