{
  "type": "Feature",
  "properties": {
    "addr:full":"Place Du Baty 11 Dinant Namur 5500",
    "addr:housenumber":"11",
    "addr:postcode":"5500",
    "addr:street":"Place Du Baty",
    "iso:country":"BE",
    "sg:address":"Place Du Baty 11",
    "sg:city":"Dinant",
    "sg:classifiers":[
        {
            "category":"Arena",
            "subcategory":"Sports Club",
            "type":"Entertainment"
        }
    ],
    "sg:phone":"+32 82 74 47 48",
    "sg:postcode":"5500",
    "sg:province":"Namur",
    "sg:tags":[
        "de"
    ],
    "wof:name":"Hermathenae-ski",
    "wof:placetype":"venue"
},
  "geometry": {"coordinates":[4.8981938362,50.2014274597],"type":"Point"}
}