{
  "type": "Feature",
  "properties": {
    "iso:country":"BE",
    "sg:address":"Vertommensberg 31",
    "sg:city":"Leuven (kessel-lo)",
    "sg:classifiers":[
        {
            "category":"Shopping",
            "subcategory":"Jewelry",
            "type":"Retail Goods"
        }
    ],
    "sg:phone":"+32 16 25 94 76",
    "sg:postcode":"3010",
    "sg:province":"Vlaams-Brabant",
    "sg:tags":[
        "jeweller",
        "-"
    ],
    "wof:name":"Van Doninck-vanlaere-juweel On",
    "wof:placetype":"venue"
},
  "geometry": {"coordinates":[4.7512202263,50.8688201904],"type":"Point"}
}