{
  "type": "Feature",
  "properties": {
    "iso:country":"BE",
    "sg:address":"Kleine Heidelaan 8",
    "sg:city":"Bonheiden",
    "sg:classifiers":[
        {
            "category":"Banks & Credit Unions",
            "subcategory":"Investment Brokerage",
            "type":"Services"
        }
    ],
    "sg:phone":"+32 15 55 03 13",
    "sg:postcode":"2820",
    "sg:province":"Antwerpen",
    "sg:tags":[
        "auditor"
    ],
    "wof:name":"Van Roey A",
    "wof:placetype":"venue"
},
  "geometry": {"coordinates":[4.5353798866,51.0254402161],"type":"Point"}
}