{
  "type": "Feature",
  "properties": {
    "addr:full":"Avenue Wolfgang Amadeus Mozart 14 Mouscron Hainaut 7700",
    "addr:housenumber":"14",
    "addr:postcode":"7700",
    "addr:street":"Avenue Wolfgang Amadeus Mozart",
    "iso:country":"BE",
    "sg:address":"Avenue Wolfgang Amadeus Mozart 14",
    "sg:city":"Mouscron",
    "sg:classifiers":[
        {
            "category":"Shopping",
            "subcategory":"Beauty & Cosmetics",
            "type":"Retail Goods"
        }
    ],
    "sg:phone":"+32 56 48 85 37",
    "sg:postcode":"7700",
    "sg:province":"Hainaut",
    "sg:tags":[
        "-",
        "perfumery"
    ],
    "wof:name":"Di Mouscron",
    "wof:placetype":"venue"
},
  "geometry": {"coordinates":[3.2056760788,50.7316513062],"type":"Point"}
}