{
  "type": "Feature",
  "properties": {
    "iso:country":"BE",
    "sg:address":"Lomolenstraat 30",
    "sg:city":"Aalter (lotenhulle)",
    "sg:classifiers":[
        {
            "category":"Health Services",
            "subcategory":"Dentist",
            "type":"Services"
        }
    ],
    "sg:phone":"+32 51 68 95 95",
    "sg:postcode":"9880",
    "sg:province":"Oost-Vlaanderen",
    "wof:name":"Standaert F",
    "wof:placetype":"venue"
},
  "geometry": {"coordinates":[3.4613931179,51.0469818115],"type":"Point"}
}