{
  "type": "Feature",
  "properties": {
    "addr:full":"Avenue Duc Wenceslas 6 Wavre Brabant Wallon 1300",
    "addr:housenumber":"6;1300",
    "addr:street":"Avenue Duc Wenceslas",
    "iso:country":"BE",
    "sg:address":"Avenue Duc Wenceslas 6",
    "sg:city":"Wavre",
    "sg:classifiers":[
        {
            "category":"Health Services",
            "subcategory":"Health Practitioner",
            "type":"Services"
        }
    ],
    "sg:phone":"+32 10 22 49 58",
    "sg:postcode":"1300",
    "sg:province":"Brabant Wallon",
    "sg:tags":[
        "physiotherapist"
    ],
    "wof:name":"Otthiers Jacques",
    "wof:placetype":"venue"
},
  "geometry": {"coordinates":[4.6279401779,50.7140846252],"type":"Point"}
}