{
  "type": "Feature",
  "properties": {
    "addr:full":"Pl Albert 1er 26 Charleroi Hainaut 6000",
    "addr:housenumber":"26",
    "addr:postcode":"6000",
    "addr:street":"Pl Albert 1Er;Hainaut",
    "iso:country":"BE",
    "sg:address":"Pl Albert 1er 26",
    "sg:city":"Charleroi",
    "sg:orig_category":"Leather - raw materials Leather and Shoes Leather goods Shoes",
    "sg:phone":"+32 71 31 69 22",
    "sg:postcode":"6000",
    "sg:province":"Hainaut",
    "wof:name":"Chaussures Lachapelle",
    "wof:placetype":"venue"
},
  "geometry": {"coordinates":[4.4421701431,50.4079818726],"type":"Point"}
}