{
  "type": "Feature",
  "properties": {
    "addr:full":"Rue Vis\u00e9-voie 278 Herstal (vottem) Li\u00e8ge 4041",
    "addr:housenumber":"278",
    "addr:postcode":"4041",
    "addr:street":"Rue Vise\u0301-Voie;Vottem",
    "iso:country":"BE",
    "sg:address":"Rue Vis\u00e9-voie 278",
    "sg:city":"Herstal (vottem)",
    "sg:classifiers":[
        {
            "category":"Professional",
            "subcategory":"Computer Services",
            "type":"Services"
        }
    ],
    "sg:phone":"+32 4 227 55 79",
    "sg:postcode":"4041",
    "sg:province":"Li\u00e8ge",
    "sg:tags":[
        "-",
        "processing",
        "data",
        "software"
    ],
    "wof:name":"Aisb",
    "wof:placetype":"venue"
},
  "geometry": {"coordinates":[5.5792708397,50.6715316772],"type":"Point"}
}