{
  "type": "Feature",
  "properties": {
    "addr:full":"Place Roi-albert-ier 11 Rochefort Namur 5580",
    "addr:housenumber":"11",
    "addr:postcode":"5580",
    "addr:street":"Place Roi-Albert-Ier",
    "iso:country":"BE",
    "sg:address":"Place Roi-albert-ier 11",
    "sg:city":"Rochefort",
    "sg:orig_category":"Banken and kredietinstellingen",
    "sg:phone":"+32 84 21 16 50",
    "sg:postcode":"5580",
    "sg:province":"Namur",
    "wof:name":"Bbl",
    "wof:placetype":"venue"
},
  "geometry": {"coordinates":[5.2233099937,50.1594200134],"type":"Point"}
}