{
  "type": "Feature",
  "properties": {
    "addr:full":"Kapellestraat 52 Wervik West-Vlaanderen 8940",
    "addr:housenumber":"52",
    "addr:postcode":"8940",
    "addr:street":"Kapellestraat",
    "iso:country":"BE",
    "sg:address":"Kapellestraat 52",
    "sg:city":"Wervik",
    "sg:orig_category":"Maatkleding Fab",
    "sg:phone":"+32 56 51 41 11",
    "sg:postcode":"8940",
    "sg:province":"West-Vlaanderen",
    "wof:name":"Anny Verhalle",
    "wof:placetype":"venue"
},
  "geometry": {"coordinates":[3.0720360279,50.8161582947],"type":"Point"}
}