{
  "type": "Feature",
  "properties": {
    "addr:full":"Heuvenstraat 24 Zonhoven Limburg 3520",
    "addr:housenumber":"24",
    "addr:postcode":"3520",
    "addr:street":"Heuvenstraat",
    "iso:country":"BE",
    "sg:address":"Heuvenstraat 24",
    "sg:city":"Zonhoven",
    "sg:classifiers":[
        {
            "category":"Food & Beverages",
            "subcategory":"Chocolate",
            "type":"Retail Goods"
        }
    ],
    "sg:phone":"+32 11 82 27 28",
    "sg:postcode":"3520",
    "sg:province":"Limburg",
    "sg:tags":[
        "confectionery",
        "-"
    ],
    "wof:name":"Soete ('t) Huys",
    "wof:placetype":"venue"
},
  "geometry": {"coordinates":[5.3672032356,50.9896774292],"type":"Point"}
}