{
  "type": "Feature",
  "properties": {
    "addr:full":"Jan Palfijnstraat 18 Kortrijk West-Vlaanderen 8500",
    "addr:housenumber":"18",
    "addr:postcode":"8500",
    "addr:street":"Jan Palfijnstraat",
    "iso:country":"BE",
    "sg:address":"Jan Palfijnstraat 18",
    "sg:city":"Kortrijk",
    "sg:orig_category":"Salles de spectacles",
    "sg:phone":"+32 56 25 60 19",
    "sg:postcode":"8500",
    "sg:province":"West-Vlaanderen",
    "wof:name":"Galerij Kesteloot",
    "wof:placetype":"venue"
},
  "geometry": {"coordinates":[3.2631790638,50.8260726929],"type":"Point"}
}