{
  "type": "Feature",
  "properties": {
    "iso:country":"BE",
    "sg:address":"Zonhoevestraat 9",
    "sg:city":"Bilzen",
    "sg:orig_category":"M\u00e9decins and sp\u00e9cialistes",
    "sg:phone":"+32 89 49 26 40",
    "sg:postcode":"3740",
    "sg:province":"Limburg",
    "wof:name":"J. Schepers",
    "wof:placetype":"venue"
},
  "geometry": {"coordinates":[5.4712018967,50.8923530579],"type":"Point"}
}