{
  "type": "Feature",
  "properties": {
    "iso:country":"BE",
    "sg:address":"Casinoplein 10",
    "sg:city":"Kortrijk",
    "sg:classifiers":[
        {
            "category":"Organizations",
            "subcategory":"Professional Association",
            "type":"Services"
        }
    ],
    "sg:phone":"+32 56 26 42 00",
    "sg:postcode":"8500",
    "sg:province":"West-Vlaanderen",
    "sg:tags":[
        "trade-union",
        "federation"
    ],
    "wof:name":"Febeltex",
    "wof:placetype":"venue"
},
  "geometry": {"coordinates":[3.2620210648,50.8257102966],"type":"Point"}
}