{
  "type": "Feature",
  "properties": {
    "iso:country":"BE",
    "sg:address":"Bredeweg 14",
    "sg:city":"Aalst",
    "sg:orig_category":"Plomberie, chauffage and installations sanitaires",
    "sg:phone":"+32 53 83 33 34",
    "sg:postcode":"9320",
    "sg:province":"Oost-Vlaanderen",
    "wof:name":"Henri Nerinckx",
    "wof:placetype":"venue"
},
  "geometry": {"coordinates":[4.04459095,50.9475135803],"type":"Point"}
}