{
  "type": "Feature",
  "properties": {
    "iso:country":"BE",
    "sg:address":"Rue De La Bach\u00e9e 37",
    "sg:city":"Sambreville (auvelais)",
    "sg:classifiers":[
        {
            "category":"Building & Trades",
            "subcategory":"Electrical",
            "type":"Services"
        }
    ],
    "sg:phone":"+32 71 74 19 30",
    "sg:postcode":"5060",
    "sg:province":"Namur",
    "sg:tags":[
        "-",
        "electric",
        "contractor"
    ],
    "wof:name":"Ld Lec Sa",
    "wof:placetype":"venue"
},
  "geometry": {"coordinates":[4.6285200119,50.4448738098],"type":"Point"}
}