{
  "type": "Feature",
  "properties": {
    "addr:full":"Route De Charleroi 159 P\u00e9ronnes-lez-binche Hainaut 7134",
    "addr:housenumber":"159",
    "addr:postcode":"7134",
    "addr:street":"Route De Charleroi;Hainaut",
    "iso:country":"BE",
    "sg:address":"Route De Charleroi 159",
    "sg:city":"P\u00e9ronnes-lez-binche",
    "sg:classifiers":[
        {
            "category":"Professional",
            "type":"Services"
        }
    ],
    "sg:phone":"+32 64 31 12 12",
    "sg:postcode":"7134",
    "sg:province":"Hainaut",
    "sg:tags":[
        "transport"
    ],
    "wof:name":"Anciens Etablissements Debliquit S.a.",
    "wof:placetype":"venue"
},
  "geometry": {"coordinates":[4.2194561958,50.4081993103],"type":"Point"}
}