{
  "type": "Feature",
  "properties": {
    "addr:full":"Veemarkt 39 Tienen Vlaams-Brabant 3300",
    "addr:housenumber":"39",
    "addr:postcode":"3300",
    "addr:street":"Veemarkt",
    "iso:country":"BE",
    "sg:address":"Veemarkt 39",
    "sg:city":"Tienen",
    "sg:classifiers":[
        {
            "category":"Cafe",
            "type":"Food & Drink"
        }
    ],
    "sg:phone":"+32 16 78 94 77",
    "sg:postcode":"3300",
    "sg:province":"Vlaams-Brabant",
    "sg:tags":[
        "caf\u00e9s"
    ],
    "wof:name":"Caf\u00c9 The Vortex",
    "wof:placetype":"venue"
},
  "geometry": {"coordinates":[4.940059185,50.8055992126],"type":"Point"}
}