{
  "type": "Feature",
  "properties": {
    "iso:country":"BE",
    "sg:address":"Roodebeeksteenweg 320",
    "sg:city":"Sint-lambrechts-woluwe/woluwe-saint-lambert",
    "sg:orig_category":"Kinderopvang",
    "sg:phone":"+32 2 772 60 22",
    "sg:postcode":"1200",
    "sg:province":"Bruxelles-Capitale",
    "wof:name":"Cr\u00c8che Crescendo",
    "wof:placetype":"venue"
},
  "geometry": {"coordinates":[4.4223489761,50.8493843079],"type":"Point"}
}