{
  "type": "Feature",
  "properties": {
    "iso:country":"BE",
    "sg:address":"Langestraat 91",
    "sg:city":"Kruibeke",
    "sg:classifiers":[
        {
            "category":"Retail",
            "subcategory":"Auto Repair",
            "type":"Services"
        }
    ],
    "sg:phone":"+32 3 774 12 58",
    "sg:postcode":"9150",
    "sg:province":"Oost-Vlaanderen",
    "sg:tags":[
        "garage"
    ],
    "wof:name":"Citroen-engels M",
    "wof:placetype":"venue"
},
  "geometry": {"coordinates":[4.3141450882,51.1737251282],"type":"Point"}
}