{
  "type": "Feature",
  "properties": {
    "iso:country":"BE",
    "sg:address":"Rue Des Fripiers 6",
    "sg:city":"Brussel/bruxelles",
    "sg:orig_category":"Mobilier and \u00e9quipement m\u00e9nager Eclairage et \u00e9quipements du foyer",
    "sg:phone":"+32 2 218 00 86",
    "sg:postcode":"1000",
    "sg:province":"Bruxelles-Capitale",
    "wof:name":"Victorinox",
    "wof:placetype":"venue"
},
  "geometry": {"coordinates":[4.3517041206,50.8484420776],"type":"Point"}
}