{
  "type": "Feature",
  "properties": {
    "addr:full":"Schoonheidsplein 1 Anderlecht Bruxelles-Capitale 1070",
    "addr:housenumber":"1",
    "addr:postcode":"1070",
    "addr:street":"Schoonheidsplein",
    "iso:country":"BE",
    "sg:address":"Schoonheidsplein 1",
    "sg:city":"Anderlecht",
    "sg:orig_category":"Verplichte sociale verzekeringen",
    "sg:phone":"+32 2 522 07 49",
    "sg:postcode":"1070",
    "sg:province":"Bruxelles-Capitale",
    "wof:name":"Mutualit\u00c9 Socialiste",
    "wof:placetype":"venue"
},
  "geometry": {"coordinates":[4.307030201,50.8394050598],"type":"Point"}
}