{
  "type": "Feature",
  "properties": {
    "iso:country":"BE",
    "sg:address":"Beiaardstraat 5",
    "sg:city":"Kluisbergen (zulzeke)",
    "sg:classifiers":[
        {
            "category":"Professional",
            "subcategory":"Management & Consulting",
            "type":"Services"
        }
    ],
    "sg:phone":"+32 55 21 92 75",
    "sg:postcode":"9690",
    "sg:province":"Oost-Vlaanderen",
    "sg:tags":[
        "consultant"
    ],
    "wof:name":"Dehoorne Bvba",
    "wof:placetype":"venue"
},
  "geometry": {"coordinates":[3.5722649097,50.7744827271],"type":"Point"}
}