{
  "type": "Feature",
  "properties": {
    "addr:full":"Linneveld 13 Herent Vlaams-Brabant 3020",
    "addr:housenumber":"13",
    "addr:postcode":"3020",
    "addr:street":"Linneveld",
    "iso:country":"BE",
    "sg:address":"Linneveld 13",
    "sg:city":"Herent",
    "sg:classifiers":[
        {
            "category":"Professional",
            "subcategory":"Employment Agencies",
            "type":"Services"
        }
    ],
    "sg:phone":"+32 16 58 25 40",
    "sg:postcode":"3020",
    "sg:province":"Vlaams-Brabant",
    "wof:name":"Radix.be",
    "wof:placetype":"venue"
},
  "geometry": {"coordinates":[4.6746869087,50.8989830017],"type":"Point"}
}