{
  "type": "Feature",
  "properties": {
    "iso:country":"BE",
    "sg:address":"Winnepenninckxstraat 4",
    "sg:city":"Gooik",
    "sg:orig_category":"Caf\u00e9s. Centres sportifs",
    "sg:phone":"+32 2 532 02 02",
    "sg:postcode":"1755",
    "sg:province":"Vlaams-Brabant",
    "wof:name":"Sporthal Jona",
    "wof:placetype":"venue"
},
  "geometry": {"coordinates":[4.1223320961,50.7772407532],"type":"Point"}
}