{
  "type": "Feature",
  "properties": {
    "iso:country":"BE",
    "sg:address":"Van Iseghemlaan 84",
    "sg:city":"Oostende",
    "sg:orig_category":"Tabac",
    "sg:phone":"+32 59 70 75 04",
    "sg:postcode":"8400",
    "sg:province":"West-Vlaanderen",
    "wof:name":"Boekhandel Mireille",
    "wof:placetype":"venue"
},
  "geometry": {"coordinates":[2.9122149944,51.2303771973],"type":"Point"}
}