{
  "type": "Feature",
  "properties": {
    "addr:full":"Dokter Rouxstraat 26 Moeskroen/mouscron Hainaut 7700",
    "addr:housenumber":"26",
    "addr:postcode":"7700",
    "addr:street":"Dokter Rouxstraat",
    "iso:country":"BE",
    "sg:address":"Dokter Rouxstraat 26",
    "sg:city":"Moeskroen/mouscron",
    "sg:orig_category":"Plaatsen van vloer- and muurbekleding",
    "sg:phone":"+32 56 34 90 04",
    "sg:postcode":"7700",
    "sg:province":"Hainaut",
    "wof:name":"Carrelages Bourgois",
    "wof:placetype":"venue"
},
  "geometry": {"coordinates":[3.2323200703,50.7400932312],"type":"Point"}
}