{
  "type": "Feature",
  "properties": {
    "iso:country":"BE",
    "sg:address":"Rue Du Bosquet 16",
    "sg:city":"Beloeil",
    "sg:classifiers":[
        {
            "category":"Building & Trades",
            "subcategory":"Construction",
            "type":"Services"
        }
    ],
    "sg:phone":"+32 69 59 09 09",
    "sg:postcode":"7970",
    "sg:province":"Hainaut",
    "sg:tags":[
        "roofing",
        "material",
        "-"
    ],
    "wof:name":"Overlau",
    "wof:placetype":"venue"
},
  "geometry": {"coordinates":[3.7371668816,50.5437469482],"type":"Point"}
}