{
  "type": "Feature",
  "properties": {
    "addr:full":"Verbindingsstraat 11 Vosselaar Antwerpen 2350",
    "addr:housenumber":"11",
    "addr:postcode":"2350",
    "addr:street":"Verbindingsstraat",
    "iso:country":"BE",
    "sg:address":"Verbindingsstraat 11",
    "sg:city":"Vosselaar",
    "sg:classifiers":[
        {
            "category":"Arena",
            "subcategory":"Sports Club",
            "type":"Entertainment"
        }
    ],
    "sg:phone":"+32 14 61 13 77",
    "sg:postcode":"2350",
    "sg:province":"Antwerpen",
    "sg:tags":[
        "de"
    ],
    "wof:name":"Tkd Dragon Brecht",
    "wof:placetype":"venue"
},
  "geometry": {"coordinates":[4.8794631958,51.3071784973],"type":"Point"}
}