{
  "type": "Feature",
  "properties": {
    "iso:country":"BE",
    "sg:address":"Rue De Herve 12",
    "sg:city":"Herve",
    "sg:orig_category":"M\u00e9decins and sp\u00e9cialistes",
    "sg:phone":"+32 87 67 98 99",
    "sg:postcode":"4651",
    "sg:province":"Li\u00e8ge",
    "wof:name":"Laurent Jeanpierre",
    "wof:placetype":"venue"
},
  "geometry": {"coordinates":[5.8154802322,50.6476097107],"type":"Point"}
}