{
  "type": "Feature",
  "properties": {
    "addr:full":"Avenue Charles Quint 420 Molenbeek Bruxelles-Capitale 1080",
    "addr:housenumber":"420",
    "addr:postcode":"1080",
    "addr:street":"Avenue Charles Quint",
    "iso:country":"BE",
    "sg:address":"Avenue Charles Quint 420",
    "sg:city":"Molenbeek",
    "sg:orig_category":"Mobistar Centres. Mat\u00e9riel de T\u00e9l\u00e9communication",
    "sg:phone":"+32 2 469 39 69",
    "sg:postcode":"1080",
    "sg:province":"Bruxelles-Capitale",
    "wof:name":"Mobistar Center Basilix",
    "wof:placetype":"venue"
},
  "geometry": {"coordinates":[4.3390049934,50.8550453186],"type":"Point"}
}