{
  "type": "Feature",
  "properties": {
    "iso:country":"BE",
    "sg:address":"Borgwormsesteenweg 103",
    "sg:city":"Sint-truiden",
    "sg:orig_category":"Paramedische behandelingen",
    "sg:phone":"+32 11 67 13 22",
    "sg:postcode":"3800",
    "sg:province":"Limburg",
    "wof:name":"A. Brugmans",
    "wof:placetype":"venue"
},
  "geometry": {"coordinates":[5.2148199081,50.7904586792],"type":"Point"}
}