{
  "type": "Feature",
  "properties": {
    "addr:full":"Route De Beauraing 22 Dinant (falmagne) Namur 5500",
    "addr:housenumber":"22",
    "addr:postcode":"5500",
    "addr:street":"Route De Beauraing",
    "iso:country":"BE",
    "sg:address":"Route De Beauraing 22",
    "sg:city":"Dinant (falmagne)",
    "sg:classifiers":[
        {
            "category":"Travel",
            "subcategory":"Hotels & Motels",
            "type":"Entertainment"
        }
    ],
    "sg:phone":"+32 82 22 25 75",
    "sg:postcode":"5500",
    "sg:province":"Namur",
    "wof:name":"Freyr (le)",
    "wof:placetype":"venue"
},
  "geometry": {"coordinates":[4.896941185,50.197177887],"type":"Point"}
}