{
  "type": "Feature",
  "properties": {
    "addr:full":"Lostraat 9 Aalter Oost-Vlaanderen 9880",
    "addr:housenumber":"9",
    "addr:postcode":"9880",
    "addr:street":"Lostraat",
    "iso:country":"BE",
    "sg:address":"Lostraat 9",
    "sg:city":"Aalter",
    "sg:orig_category":"Schoenen Sport- and kampeermateriaal",
    "sg:phone":"+32 9 375 01 61",
    "sg:postcode":"9880",
    "sg:province":"Oost-Vlaanderen",
    "wof:name":"Smash Sport",
    "wof:placetype":"venue"
},
  "geometry": {"coordinates":[3.4492800236,51.083568573],"type":"Point"}
}