{
  "type": "Feature",
  "properties": {
    "addr:full":"Haasdonkse Steenweg 125 Sint-niklaas Oost-Vlaanderen 9100",
    "addr:housenumber":"125",
    "addr:postcode":"9100",
    "addr:street":"Steenweg",
    "iso:country":"BE",
    "sg:address":"Haasdonkse Steenweg 125",
    "sg:city":"Sint-niklaas",
    "sg:classifiers":[
        {
            "category":"Food & Beverages",
            "subcategory":"Fruits & Vegetables",
            "type":"Retail Goods"
        }
    ],
    "sg:phone":"+32 3 771 57 95",
    "sg:postcode":"9100",
    "sg:province":"Oost-Vlaanderen",
    "sg:tags":[
        "l\u00e9gumes"
    ],
    "wof:name":"Perry Fruit",
    "wof:placetype":"venue"
},
  "geometry": {"coordinates":[4.2117328644,51.1683273315],"type":"Point"}
}