{
  "type": "Feature",
  "properties": {
    "iso:country":"BE",
    "sg:address":"Damkouterbaan 29",
    "sg:city":"Aalst (gijzegem)",
    "sg:classifiers":[
        {
            "category":"Health Services",
            "subcategory":"Doctor",
            "type":"Services"
        }
    ],
    "sg:phone":"+32 53 70 37 00",
    "sg:postcode":"9308",
    "sg:province":"Oost-Vlaanderen",
    "sg:tags":[
        "medicinephysicians",
        "surgeon"
    ],
    "wof:name":"Fosselle E",
    "wof:placetype":"venue"
},
  "geometry": {"coordinates":[4.045320034,50.9827384949],"type":"Point"}
}