{
  "type": "Feature",
  "properties": {
    "addr:full":"Rue Neuve 6 Soignies Hainaut 7060",
    "addr:housenumber":"6",
    "addr:postcode":"7060",
    "addr:street":"Rue Neuve",
    "iso:country":"BE",
    "sg:address":"Rue Neuve 6",
    "sg:city":"Soignies",
    "sg:orig_category":"Decoratieve kunst and kunstbenodigdheden Drukkerijen and copyshops Kantoormateriaal",
    "sg:phone":"+32 67 33 40 98",
    "sg:postcode":"7060",
    "sg:province":"Hainaut",
    "wof:name":"Art Copy",
    "wof:placetype":"venue"
},
  "geometry": {"coordinates":[4.0722360611,50.5779914856],"type":"Point"}
}