{
  "type": "Feature",
  "properties": {
    "iso:country":"BE",
    "sg:address":"Anjerstraat 2",
    "sg:city":"Neerpelt",
    "sg:orig_category":"Charpentes and couvertures",
    "sg:phone":"+32 11 64 80 10",
    "sg:postcode":"3910",
    "sg:province":"Limburg",
    "wof:name":"Jean Verschakelen",
    "wof:placetype":"venue"
},
  "geometry": {"coordinates":[5.4554572105,51.2251472473],"type":"Point"}
}