{
  "type": "Feature",
  "properties": {
    "addr:full":"Mechelstraat 24 Grimbergen (humbeek) Vlaams-Brabant 1851",
    "addr:housenumber":"24",
    "addr:postcode":"1851",
    "addr:street":"Mechelstraat",
    "iso:country":"BE",
    "sg:address":"Mechelstraat 24",
    "sg:city":"Grimbergen (humbeek)",
    "sg:orig_category":"Non-Classified Establishments",
    "sg:phone":"+32 2 255 10 70",
    "sg:postcode":"1851",
    "sg:province":"Vlaams-Brabant",
    "wof:name":"Mallentjer-rufflette",
    "wof:placetype":"venue"
},
  "geometry": {"coordinates":[4.3910608292,50.9801139832],"type":"Point"}
}