{
  "type": "Feature",
  "properties": {
    "iso:country":"BE",
    "sg:address":"Fok 40",
    "sg:city":"Sint-amands",
    "sg:orig_category":"Eleveurs and marchands de porcs",
    "sg:phone":"+32 52 33 39 55",
    "sg:postcode":"2890",
    "sg:province":"Antwerpen",
    "wof:name":"Walter Van Goethem",
    "wof:placetype":"venue"
},
  "geometry": {"coordinates":[4.2127599716,51.0369186401],"type":"Point"}
}