{
  "type": "Feature",
  "properties": {
    "addr:full":"Rue Masui 6 Brussel/bruxelles Bruxelles-Capitale 1000",
    "addr:housenumber":"6",
    "addr:postcode":"1000",
    "addr:street":"Rue Masui;/",
    "iso:country":"BE",
    "sg:address":"Rue Masui 6",
    "sg:city":"Brussel/bruxelles",
    "sg:orig_category":"Graphologues, astrologues, voyants and radiesth\u00e9sistes. Meubles D\u00e9taillants, Am\u00e9nagement de B\u00e2timent",
    "sg:phone":"+32 2 203 45 07",
    "sg:postcode":"1000",
    "sg:province":"Bruxelles-Capitale",
    "wof:name":"Naturellement",
    "wof:placetype":"venue"
},
  "geometry": {"coordinates":[4.3556108475,50.8653717041],"type":"Point"}
}