{
  "type": "Feature",
  "properties": {
    "iso:country":"BE",
    "sg:address":"Houtkaai 24",
    "sg:city":"Brugge",
    "sg:classifiers":[
        {
            "category":"Home & Garden",
            "subcategory":"Furniture",
            "type":"Retail Goods"
        }
    ],
    "sg:phone":"+32 50 31 11 11",
    "sg:postcode":"8000",
    "sg:province":"West-Vlaanderen",
    "sg:tags":[
        "-"
    ],
    "wof:name":"Hornicub Bvba",
    "wof:placetype":"venue"
},
  "geometry": {"coordinates":[3.2132399082,51.2180786133],"type":"Point"}
}