{
  "type": "Feature",
  "properties": {
    "iso:country":"BE",
    "sg:address":"Kaboutermansstraat 121",
    "sg:city":"Leuven",
    "sg:orig_category":"Enseignement maternel and primaire",
    "sg:phone":"+32 16 22 93 17",
    "sg:postcode":"3000",
    "sg:province":"Vlaams-Brabant",
    "wof:name":"Kleuterschool",
    "wof:placetype":"venue"
},
  "geometry": {"coordinates":[4.6877098083,50.8807411194],"type":"Point"}
}