{
  "type": "Feature",
  "properties": {
    "iso:country":"BE",
    "sg:address":"Bruul 105",
    "sg:city":"Mechelen",
    "sg:classifiers":[
        {
            "category":"Cafe",
            "type":"Food & Drink"
        }
    ],
    "sg:phone":"+32 15 26 00 76",
    "sg:postcode":"2800",
    "sg:province":"Antwerpen",
    "sg:tags":[
        "snack-bars"
    ],
    "wof:name":"Lamourette",
    "wof:placetype":"venue"
},
  "geometry": {"coordinates":[4.4821271896,51.024017334],"type":"Point"}
}