{
  "type": "Feature",
  "properties": {
    "addr:full":"Neeravert 31 Londerzeel Vlaams-Brabant 1840",
    "addr:housenumber":"31",
    "addr:postcode":"1840",
    "addr:street":"Neeravert",
    "iso:country":"BE",
    "sg:address":"Neeravert 31",
    "sg:city":"Londerzeel",
    "sg:orig_category":"Bouwwerktuigen Gh",
    "sg:phone":"+32 52 30 39 21",
    "sg:postcode":"1840",
    "sg:province":"Vlaams-Brabant",
    "wof:name":"Kradebo",
    "wof:placetype":"venue"
},
  "geometry": {"coordinates":[4.3036460876,51.0250892639],"type":"Point"}
}