{
  "type": "Feature",
  "properties": {
    "iso:country":"BE",
    "sg:address":"Rue De L\u00b4europe 10",
    "sg:city":"La Bruy\u00c8re",
    "sg:orig_category":"Artsen and specialisten",
    "sg:phone":"+32 81 56 81 65",
    "sg:postcode":"5081",
    "sg:province":"Namur",
    "wof:name":"Consultation Nourissons",
    "wof:placetype":"venue"
},
  "geometry": {"coordinates":[4.7710499763,50.5210227966],"type":"Point"}
}