{
  "type": "Feature",
  "properties": {
    "addr:full":"Leuvensestraat 40 Tienen Vlaams-Brabant 3300",
    "addr:housenumber":"40",
    "addr:postcode":"3300",
    "addr:street":"Leuvensestraat",
    "iso:country":"BE",
    "sg:address":"Leuvensestraat 40",
    "sg:city":"Tienen",
    "sg:orig_category":"Parfumeries. Drogueries",
    "sg:phone":"+32 16 82 54 76",
    "sg:postcode":"3300",
    "sg:province":"Vlaams-Brabant",
    "wof:name":"Kruidvat",
    "wof:placetype":"venue"
},
  "geometry": {"coordinates":[4.9344248772,50.8088569641],"type":"Point"}
}