{
  "type": "Feature",
  "properties": {
    "iso:country":"BE",
    "sg:address":"Sint-jozefsstraat 2bc",
    "sg:city":"Lier",
    "sg:classifiers":[
        {
            "category":"Cafe",
            "type":"Food & Drink"
        }
    ],
    "sg:phone":"+32 3 488 08 99",
    "sg:postcode":"2500",
    "sg:province":"Antwerpen",
    "sg:tags":[
        "caf\u00e9s"
    ],
    "wof:name":"Robert Devinster",
    "wof:placetype":"venue"
},
  "geometry": {"coordinates":[4.5724592209,51.1469230652],"type":"Point"}
}