{
  "type": "Feature",
  "properties": {
    "iso:country":"BE",
    "sg:address":"Pater Damiaanstraat 6",
    "sg:city":"Kortrijk",
    "sg:classifiers":[
        {
            "category":"Social Services",
            "subcategory":"Child Care",
            "type":"Services"
        }
    ],
    "sg:phone":"+32 56 20 07 18",
    "sg:postcode":"8500",
    "sg:province":"West-Vlaanderen",
    "sg:tags":[
        "baby",
        "nursery",
        "day",
        "sitting"
    ],
    "wof:name":"Speelberg (de)",
    "wof:placetype":"venue"
},
  "geometry": {"coordinates":[3.2836520672,50.8263816833],"type":"Point"}
}