{
  "type": "Feature",
  "properties": {
    "addr:full":"Astridlaan 8 Overpelt Limburg 3900",
    "addr:housenumber":"8",
    "addr:postcode":"3900",
    "addr:street":"Astridlaan",
    "iso:country":"BE",
    "sg:address":"Astridlaan 8",
    "sg:city":"Overpelt",
    "sg:classifiers":[
        {
            "category":"Health Services",
            "subcategory":"Dentist",
            "type":"Services"
        }
    ],
    "sg:phone":"+32 11 64 35 72",
    "sg:postcode":"3900",
    "sg:province":"Limburg",
    "wof:name":"Vandeput Norbert",
    "wof:placetype":"venue"
},
  "geometry": {"coordinates":[5.4172739983,51.209487915],"type":"Point"}
}