{
  "type": "Feature",
  "properties": {
    "iso:country":"BE",
    "sg:address":"Gilainstraat 48",
    "sg:city":"Tienen",
    "sg:classifiers":[
        {
            "category":"Shopping",
            "subcategory":"Hobbies, Toys, & Games",
            "type":"Retail Goods"
        }
    ],
    "sg:phone":"+32 16 81 33 55",
    "sg:postcode":"3300",
    "sg:province":"Vlaams-Brabant",
    "sg:tags":[
        "computer",
        "video"
    ],
    "wof:name":"Game Zone",
    "wof:placetype":"venue"
},
  "geometry": {"coordinates":[4.9369711876,50.8094673157],"type":"Point"}
}