{
  "type": "Feature",
  "properties": {
    "addr:full":"Stationstraat 28 Lebbeke Oost-Vlaanderen 9280",
    "addr:housenumber":"28",
    "addr:postcode":"9280",
    "addr:street":"Stationstraat",
    "iso:country":"BE",
    "sg:address":"Stationstraat 28",
    "sg:city":"Lebbeke",
    "sg:orig_category":"V\u00eatements",
    "sg:phone":"+32 52 41 13 84",
    "sg:postcode":"9280",
    "sg:province":"Oost-Vlaanderen",
    "wof:name":"Touch",
    "wof:placetype":"venue"
},
  "geometry": {"coordinates":[4.1385698318,51.0018081665],"type":"Point"}
}