{
  "type": "Feature",
  "properties": {
    "iso:country":"BE",
    "sg:address":"Chauss\u00c9e De Ciney 53bd",
    "sg:city":"Andenne",
    "sg:orig_category":"Charpentes and couvertures. Epiceries",
    "sg:phone":"+32 85 61 14 56",
    "sg:postcode":"5300",
    "sg:province":"Namur",
    "wof:name":"Jocelyn Lebeau",
    "wof:placetype":"venue"
},
  "geometry": {"coordinates":[5.1014661789,50.4852714539],"type":"Point"}
}