{
  "type": "Feature",
  "properties": {
    "addr:full":"Rue Cl\u00c9menceau 258 Colfontaine Hainaut 7340",
    "addr:housenumber":"258",
    "addr:postcode":"7340",
    "addr:street":"Rue Cle\u0301Menceau",
    "iso:country":"BE",
    "sg:address":"Rue Cl\u00c9menceau 258",
    "sg:city":"Colfontaine",
    "sg:orig_category":"Artsen and specialisten",
    "sg:phone":"+32 65 67 40 77",
    "sg:postcode":"7340",
    "sg:province":"Hainaut",
    "wof:name":"Jean-pierre Bauwens",
    "wof:placetype":"venue"
},
  "geometry": {"coordinates":[3.8434700966,50.4102096558],"type":"Point"}
}