{
  "type": "Feature",
  "properties": {
    "addr:full":"Nieuwstraat 42 Nazareth Oost-Vlaanderen 9810",
    "addr:housenumber":"42",
    "addr:postcode":"9810",
    "addr:street":"Nieuwstraat",
    "iso:country":"BE",
    "sg:address":"Nieuwstraat 42",
    "sg:city":"Nazareth",
    "sg:orig_category":"Kapsalons",
    "sg:phone":"+32 9 385 89 19",
    "sg:postcode":"9810",
    "sg:province":"Oost-Vlaanderen",
    "wof:name":"Coiffure Hij & Zij",
    "wof:placetype":"venue"
},
  "geometry": {"coordinates":[3.5924189091,50.9633102417],"type":"Point"}
}