{
  "type": "Feature",
  "properties": {
    "iso:country":"BE",
    "sg:address":"Hamonterweg 139",
    "sg:city":"Hamont-achel",
    "sg:orig_category":"Mat\u00e9riel de contr\u00f4le des processus industriels Fab",
    "sg:phone":"+32 11 64 28 92",
    "sg:postcode":"3930",
    "sg:province":"Limburg",
    "wof:name":"Droeshaut",
    "wof:placetype":"venue"
},
  "geometry": {"coordinates":[5.4780330658,51.2409057617],"type":"Point"}
}