{
  "type": "Feature",
  "properties": {
    "iso:country":"BE",
    "sg:address":"Bondgenotenlaan 105",
    "sg:city":"Leuven",
    "sg:orig_category":"Disneyland Parijs Reisbureaus",
    "sg:phone":"+32 16 20 24 48",
    "sg:postcode":"3000",
    "sg:province":"Vlaams-Brabant",
    "wof:name":"Neckermann",
    "wof:placetype":"venue"
},
  "geometry": {"coordinates":[4.7096819878,50.8804283142],"type":"Point"}
}