{
  "type": "Feature",
  "properties": {
    "addr:full":"Maurits Noestraat 99 Oud-heverlee Vlaams-Brabant 3054",
    "addr:housenumber":"99",
    "addr:postcode":"3054",
    "addr:street":"Noestraat",
    "iso:country":"BE",
    "sg:address":"Maurits Noestraat 99",
    "sg:city":"Oud-heverlee",
    "sg:orig_category":"Experts-comptables",
    "sg:phone":"+32 16 40 08 85",
    "sg:postcode":"3054",
    "sg:province":"Vlaams-Brabant",
    "wof:name":"Andree Cauderlier",
    "wof:placetype":"venue"
},
  "geometry": {"coordinates":[4.6821627617,50.824962616],"type":"Point"}
}