{
  "type": "Feature",
  "properties": {
    "iso:country":"BE",
    "sg:address":"Antwerpsestraat 194",
    "sg:city":"Boom",
    "sg:classifiers":[
        {
            "category":"Health Services",
            "subcategory":"Dentist",
            "type":"Services"
        }
    ],
    "sg:phone":"+32 3 888 35 25",
    "sg:postcode":"2850",
    "sg:province":"Antwerpen",
    "wof:name":"Petitjean Michel",
    "wof:placetype":"venue"
},
  "geometry": {"coordinates":[4.3666100502,51.0949554443],"type":"Point"}
}