{
  "type": "Feature",
  "properties": {
    "addr:full":"Broekstraat 6 Waregem West-Vlaanderen 8790",
    "addr:housenumber":"6",
    "addr:postcode":"8790",
    "addr:street":"Broekstraat",
    "iso:country":"BE",
    "sg:address":"Broekstraat 6",
    "sg:city":"Waregem",
    "sg:orig_category":"Enseignement secondaire g\u00e9n\u00e9ral. Enseignement maternel and primaire",
    "sg:phone":"+32 56 60 39 70",
    "sg:postcode":"8790",
    "sg:province":"West-Vlaanderen",
    "wof:name":"Vrije Basisschool",
    "wof:placetype":"venue"
},
  "geometry": {"coordinates":[3.4212388992,50.8842773438],"type":"Point"}
}