{
  "type": "Feature",
  "properties": {
    "iso:country":"BE",
    "sg:address":"Galerie Cath\u00c9drale 46",
    "sg:city":"Li\u00c8ge",
    "sg:orig_category":"V\u00eatements pour Hommes",
    "sg:phone":"+32 4 223 04 79",
    "sg:postcode":"4000",
    "sg:province":"Li\u00e8ge",
    "wof:name":"Maison Gray",
    "wof:placetype":"venue"
},
  "geometry": {"coordinates":[5.5760521889,50.6431465149],"type":"Point"}
}