{
  "type": "Feature",
  "properties": {
    "iso:country":"BE",
    "sg:address":"Zoerselsteenweg 9",
    "sg:city":"Zoersel",
    "sg:orig_category":"Electrical And Electronic Cleaners",
    "sg:phone":"+32 3 219 59 66",
    "sg:postcode":"2980",
    "sg:province":"Antwerpen",
    "wof:name":"E.s. Supply Nv",
    "wof:placetype":"venue"
},
  "geometry": {"coordinates":[4.694270134,51.2433166504],"type":"Point"}
}