{
  "type": "Feature",
  "properties": {
    "addr:full":"Lange Herentalsestraat 1bb Antwerpen Antwerpen 2018",
    "addr:housenumber":"1bb",
    "addr:postcode":"2018",
    "addr:street":"Lange Herentalsestraat",
    "iso:country":"BE",
    "sg:address":"Lange Herentalsestraat 1bb",
    "sg:city":"Antwerpen",
    "sg:orig_category":"Produits interm\u00e9diaires Bijoux Fab",
    "sg:phone":"+32 3 225 25 11",
    "sg:postcode":"2018",
    "sg:province":"Antwerpen",
    "wof:name":"Lands Superabr.headquart.",
    "wof:placetype":"venue"
},
  "geometry": {"coordinates":[4.417470932,51.2161598206],"type":"Point"}
}