{
  "type": "Feature",
  "properties": {
    "iso:country":"BE",
    "sg:address":"Glazenleeuwstraat 8",
    "sg:city":"Beveren",
    "sg:orig_category":"Artistes ind\u00e9pendants. Editeurs de livres. Editeurs d'enregistrements sonores",
    "sg:phone":"+32 3 775 68 75",
    "sg:postcode":"9120",
    "sg:province":"Oost-Vlaanderen",
    "wof:name":"Deno-music",
    "wof:placetype":"venue"
},
  "geometry": {"coordinates":[4.249833107,51.2173881531],"type":"Point"}
}