{
  "type": "Feature",
  "properties": {
    "iso:country":"BE",
    "sg:address":"Rue Du Christ 4 Box 2",
    "sg:city":"Mouscron",
    "sg:classifiers":[
        {
            "category":"Health Services",
            "subcategory":"Doctor",
            "type":"Services"
        }
    ],
    "sg:phone":"+32 56 84 75 16",
    "sg:postcode":"7700",
    "sg:province":"Hainaut",
    "sg:tags":[
        "medicinephysicians",
        "surgeon"
    ],
    "wof:name":"Dechambre St\u00e9phane",
    "wof:placetype":"venue"
},
  "geometry": {"coordinates":[3.2094099522,50.744140625],"type":"Point"}
}