{
  "type": "Feature",
  "properties": {
    "iso:country":"BE",
    "sg:address":"Zuidstraat 33",
    "sg:city":"Ichtegem",
    "sg:orig_category":"M\u00e9decins and sp\u00e9cialistes",
    "sg:phone":"+32 51 58 30 30",
    "sg:postcode":"8480",
    "sg:province":"West-Vlaanderen",
    "wof:name":"Dirk Vermeulen",
    "wof:placetype":"venue"
},
  "geometry": {"coordinates":[3.0327880383,51.1032524109],"type":"Point"}
}