{
  "type": "Feature",
  "properties": {
    "addr:full":"Hoekskensstraat 136 Lochristi Oost-Vlaanderen 9080",
    "addr:housenumber":"136",
    "addr:postcode":"9080",
    "addr:street":"Hoekskensstraat",
    "iso:country":"BE",
    "sg:address":"Hoekskensstraat 136",
    "sg:city":"Lochristi",
    "sg:classifiers":[
        {
            "category":"Wholesale",
            "subcategory":"Plants",
            "type":"Manufacturing & Wholesale Goods"
        }
    ],
    "sg:phone":"+32 9 355 71 02",
    "sg:postcode":"9080",
    "sg:province":"Oost-Vlaanderen",
    "sg:tags":[
        "whol",
        "flower",
        "-",
        "grower"
    ],
    "wof:name":"Taghon D",
    "wof:placetype":"venue"
},
  "geometry": {"coordinates":[3.8364350796,51.1149139404],"type":"Point"}
}