{
  "type": "Feature",
  "properties": {
    "iso:country":"BE",
    "sg:address":"Rue De La Sarriette 14",
    "sg:city":"Ottignies-louvain-la-neuve",
    "sg:orig_category":"Production de films, t\u00e9l\u00e9films and vid\u00e9os",
    "sg:phone":"+32 10 45 02 34",
    "sg:postcode":"1348",
    "sg:province":"Brabant Wallon",
    "wof:name":"Stephan Ugeux",
    "wof:placetype":"venue"
},
  "geometry": {"coordinates":[4.6186461449,50.6629562378],"type":"Point"}
}