{
  "type": "Feature",
  "properties": {
    "iso:country":"BE",
    "sg:address":"Vestenstraat 96",
    "sg:city":"Tervuren",
    "sg:orig_category":"S\u00e9curit\u00e9 sociale",
    "sg:phone":"+32 2 767 40 20",
    "sg:postcode":"3080",
    "sg:province":"Vlaams-Brabant",
    "wof:name":"Socialist. Mutualiteit",
    "wof:placetype":"venue"
},
  "geometry": {"coordinates":[4.5059580803,50.8196525574],"type":"Point"}
}