{
  "type": "Feature",
  "properties": {
    "iso:country":"BE",
    "sg:address":"Speiestraat 48",
    "sg:city":"Wervik",
    "sg:orig_category":"Enseignement artistique",
    "sg:phone":"+32 56 31 24 99",
    "sg:postcode":"8940",
    "sg:province":"West-Vlaanderen",
    "wof:name":"Stedelijke Tekenacademie",
    "wof:placetype":"venue"
},
  "geometry": {"coordinates":[3.0468170643,50.7791976929],"type":"Point"}
}