{
  "type": "Feature",
  "properties": {
    "addr:full":"Rue De La Libert\u00e9 12 Chi\u00e8vres (ladeuze) Hainaut 7950",
    "addr:housenumber":"12",
    "addr:postcode":"7950",
    "addr:street":"Rue De La Liberte\u0301;Ladeuze Hainaut",
    "iso:country":"BE",
    "sg:address":"Rue De La Libert\u00e9 12",
    "sg:city":"Chi\u00e8vres (ladeuze)",
    "sg:classifiers":[
        {
            "category":"Home & Garden",
            "subcategory":"Garden Supply",
            "type":"Retail Goods"
        }
    ],
    "sg:phone":"+32 68 65 77 35",
    "sg:postcode":"7950",
    "sg:province":"Hainaut",
    "wof:name":"Drossart G",
    "wof:placetype":"venue"
},
  "geometry": {"coordinates":[3.8069698811,50.5864601135],"type":"Point"}
}