{
  "type": "Feature",
  "properties": {
    "addr:full":"Molenstraat 30 Zulte (olsene) Oost-Vlaanderen 9870",
    "addr:housenumber":"30",
    "addr:postcode":"9870",
    "addr:street":"Molenstraat",
    "iso:country":"BE",
    "sg:address":"Molenstraat 30",
    "sg:city":"Zulte (olsene)",
    "sg:classifiers":[
        {
            "category":"Health Services",
            "subcategory":"Doctor",
            "type":"Services"
        }
    ],
    "sg:phone":"+32 9 388 86 14",
    "sg:postcode":"9870",
    "sg:province":"Oost-Vlaanderen",
    "sg:tags":[
        "medicinephysicians",
        "surgeon"
    ],
    "wof:name":"Huys C",
    "wof:placetype":"venue"
},
  "geometry": {"coordinates":[3.4645910263,50.9347305298],"type":"Point"}
}