{
  "type": "Feature",
  "properties": {
    "addr:full":"Koningsdonkstraat 130 Gent Oost-Vlaanderen 9050",
    "addr:housenumber":"130",
    "addr:postcode":"9050",
    "addr:street":"Koningsdonkstraat;Oost-Vlaanderen",
    "iso:country":"BE",
    "sg:address":"Koningsdonkstraat 130",
    "sg:city":"Gent",
    "sg:orig_category":"Tuinen",
    "sg:phone":"+32 9 230 57 18",
    "sg:postcode":"9050",
    "sg:province":"Oost-Vlaanderen",
    "wof:name":"Fran\u00c7ois Tuinen",
    "wof:placetype":"venue"
},
  "geometry": {"coordinates":[3.7825388908,51.0319023132],"type":"Point"}
}