{
  "type": "Feature",
  "properties": {
    "addr:full":"Rue Vanderkindere 548 Ukkel/uccle Bruxelles-Capitale 1180",
    "addr:housenumber":"548",
    "addr:postcode":"1180",
    "addr:street":"Rue Vanderkindere;/",
    "iso:country":"BE",
    "sg:address":"Rue Vanderkindere 548",
    "sg:city":"Ukkel/uccle",
    "sg:orig_category":"Antiquit\u00e9s",
    "sg:phone":"+32 2 344 99 36",
    "sg:postcode":"1180",
    "sg:province":"Bruxelles-Capitale",
    "wof:name":"Le Coffre \u00c0 Surprises",
    "wof:placetype":"venue"
},
  "geometry": {"coordinates":[4.3657708168,50.814655304],"type":"Point"}
}