{
  "type": "Feature",
  "properties": {
    "addr:full":"Dr\u00e8ve Du Proph\u00e8te 24 Mons Hainaut 7000",
    "addr:housenumber":"24",
    "addr:postcode":"7000",
    "addr:street":"Dre\u0300Ve Du Prophe\u0300Te;Hainaut",
    "iso:country":"BE",
    "sg:address":"Dr\u00e8ve Du Proph\u00e8te 24",
    "sg:city":"Mons",
    "sg:classifiers":[
        {
            "category":"Professional",
            "subcategory":"Management & Consulting",
            "type":"Services"
        }
    ],
    "sg:phone":"+32 65 84 38 70",
    "sg:postcode":"7000",
    "sg:province":"Hainaut",
    "sg:tags":[
        "consultant",
        "agency",
        "advertising"
    ],
    "wof:name":"Eurovega Sprl",
    "wof:placetype":"venue"
},
  "geometry": {"coordinates":[3.9786880016,50.463809967],"type":"Point"}
}