{
  "type": "Feature",
  "properties": {
    "addr:full":"Rue De Grand Bigard 507 Sint-jans-molenbeek/molenbeek- Bruxelles-Capitale 1080",
    "addr:housenumber":"507;/",
    "addr:postcode":"1080",
    "addr:street":"Rue De Grand Bigard;Sint-Jans-Molenbeek",
    "iso:country":"BE",
    "sg:address":"Rue De Grand Bigard 507",
    "sg:city":"Sint-jans-molenbeek/molenbeek-",
    "sg:orig_category":"Electrom\u00e9nager, t\u00e9l\u00e9visions and radios. Mat\u00e9riel de T\u00e9l\u00e9communication",
    "sg:phone":"+32 2 465 65 59",
    "sg:postcode":"1080",
    "sg:province":"Bruxelles-Capitale",
    "wof:name":"Satbel",
    "wof:placetype":"venue"
},
  "geometry": {"coordinates":[4.3030090332,50.8590202332],"type":"Point"}
}