{
  "type": "Feature",
  "properties": {
    "addr:full":"Waalsekaai 44 Antwerpen Antwerpen 2000",
    "addr:housenumber":"44",
    "addr:postcode":"2000",
    "addr:street":"Waalsekaai",
    "iso:country":"BE",
    "sg:address":"Waalsekaai 44",
    "sg:city":"Antwerpen",
    "sg:classifiers":[
        {
            "category":"Restaurant",
            "type":"Food & Drink"
        }
    ],
    "sg:phone":"+32 3 248 59 02",
    "sg:postcode":"2000",
    "sg:province":"Antwerpen",
    "wof:name":"Asa 1200",
    "wof:placetype":"venue"
},
  "geometry": {"coordinates":[4.3879270554,51.2091026306],"type":"Point"}
}