{
  "type": "Feature",
  "properties": {
    "iso:country":"BE",
    "sg:address":"Rue Des Combattants 24",
    "sg:city":"Charleroi",
    "sg:orig_category":"Articles non-alimentaires",
    "sg:phone":"+32 71 70 03 96",
    "sg:postcode":"6031",
    "sg:province":"Hainaut",
    "wof:name":"Solderie La Moncelloise",
    "wof:placetype":"venue"
},
  "geometry": {"coordinates":[4.4559397697,50.3856468201],"type":"Point"}
}