{
  "type": "Feature",
  "properties": {
    "iso:country":"BE",
    "sg:address":"Rue Haute Sauveniere 17",
    "sg:city":"Liege",
    "sg:classifiers":[
        {
            "category":"Restaurant",
            "type":"Food & Drink"
        }
    ],
    "sg:phone":"+32 4 223 57 64",
    "sg:postcode":"4000",
    "sg:province":"Li\u00e8ge",
    "wof:name":"Chez Sullon",
    "wof:placetype":"venue"
},
  "geometry": {"coordinates":[5.5706930161,50.6445159912],"type":"Point"}
}