{
  "type": "Feature",
  "properties": {
    "addr:full":"Rector De Ramstraat 83 Nijlen Antwerpen 2560",
    "addr:housenumber":"83",
    "addr:postcode":"2560",
    "addr:street":"Rector De Ramstraat",
    "iso:country":"BE",
    "sg:address":"Rector De Ramstraat 83",
    "sg:city":"Nijlen",
    "sg:classifiers":[
        {
            "category":"Retail",
            "subcategory":"Auto Repair",
            "type":"Services"
        }
    ],
    "sg:phone":"+32 3 411 07 43",
    "sg:postcode":"2560",
    "sg:province":"Antwerpen",
    "sg:tags":[
        "automobile-body"
    ],
    "wof:name":"Ennekens H & Zonen",
    "wof:placetype":"venue"
},
  "geometry": {"coordinates":[4.6788749695,51.1581497192],"type":"Point"}
}