{
  "type": "Feature",
  "properties": {
    "iso:country":"BE",
    "sg:address":"Geluwestraat 33",
    "sg:city":"Zonnebeke",
    "sg:orig_category":"Rundveehouders Varkenskwekers",
    "sg:phone":"+32 57 46 65 17",
    "sg:postcode":"8980",
    "sg:province":"West-Vlaanderen",
    "wof:name":"Norbert Neirynck",
    "wof:placetype":"venue"
},
  "geometry": {"coordinates":[3.0314741135,50.8455963135],"type":"Point"}
}