{
  "type": "Feature",
  "properties": {
    "iso:country":"BE",
    "sg:address":"Steensedijk 378",
    "sg:city":"Oostende",
    "sg:classifiers":[
        {
            "category":"Health Services",
            "subcategory":"Dentist",
            "type":"Services"
        }
    ],
    "sg:phone":"+32 59 80 32 34",
    "sg:postcode":"8400",
    "sg:province":"West-Vlaanderen",
    "wof:name":"Vande Vannet B",
    "wof:placetype":"venue"
},
  "geometry": {"coordinates":[2.8931210041,51.211605072],"type":"Point"}
}