{
  "type": "Feature",
  "properties": {
    "iso:country":"BE",
    "sg:address":"Merelstraat 5",
    "sg:city":"Asse (zellik)",
    "sg:classifiers":[
        {
            "category":"Building & Trades",
            "subcategory":"Construction",
            "type":"Services"
        }
    ],
    "sg:phone":"+32 2 466 40 74",
    "sg:postcode":"1731",
    "sg:province":"Vlaams-Brabant",
    "sg:tags":[
        "glazier"
    ],
    "wof:name":"Opdebeeck J Bvba",
    "wof:placetype":"venue"
},
  "geometry": {"coordinates":[4.2741718292,50.8853912354],"type":"Point"}
}