{
  "type": "Feature",
  "properties": {
    "iso:country":"BE",
    "sg:address":"Rue De Bl\u00e9zy 47",
    "sg:city":"Bertrix",
    "sg:classifiers":[
        {
            "category":"Health Services",
            "subcategory":"Health Practitioner",
            "type":"Services"
        }
    ],
    "sg:phone":"+32 61 41 44 58",
    "sg:postcode":"6880",
    "sg:province":"Luxembourg",
    "sg:tags":[
        "physiotherapist"
    ],
    "wof:name":"Noizet N",
    "wof:placetype":"venue"
},
  "geometry": {"coordinates":[5.2667279243,49.8579444885],"type":"Point"}
}