{
  "type": "Feature",
  "properties": {
    "addr:full":"Burgemeester Lionel Pussemierstraat 159 Eeklo Oost-Vlaanderen 9900",
    "addr:housenumber":"159",
    "addr:postcode":"9900",
    "addr:street":"Burgemeester Lionel Pussemierstraat",
    "iso:country":"BE",
    "sg:address":"Burgemeester Lionel Pussemierstraat 159",
    "sg:city":"Eeklo",
    "sg:classifiers":[
        {
            "category":"Health Services",
            "subcategory":"Doctor",
            "type":"Services"
        }
    ],
    "sg:phone":"+32 9 377 24 68",
    "sg:postcode":"9900",
    "sg:province":"Oost-Vlaanderen",
    "sg:tags":[
        "medicinephysicians",
        "surgeon"
    ],
    "wof:name":"Bafort Jan",
    "wof:placetype":"venue"
},
  "geometry": {"coordinates":[3.5775539875,51.182258606],"type":"Point"}
}