{
  "type": "Feature",
  "properties": {
    "addr:full":"Rue De Porto 130 Li\u00e8ge 1 (li\u00e8ge 2) Li\u00e8ge 4020",
    "addr:housenumber":"130;1;2",
    "addr:postcode":"4020",
    "addr:street":"Rue De Porto",
    "iso:country":"BE",
    "sg:address":"Rue De Porto 130",
    "sg:city":"Li\u00e8ge 1 (li\u00e8ge 2)",
    "sg:classifiers":[
        {
            "category":"Food & Beverages",
            "subcategory":"Meat & Fish",
            "type":"Retail Goods"
        }
    ],
    "sg:phone":"+32 4 342 68 45",
    "sg:postcode":"4020",
    "sg:province":"Li\u00e8ge",
    "sg:tags":[
        "poultry",
        "whol",
        "game",
        "-"
    ],
    "wof:name":"Chatar Trading Sprl",
    "wof:placetype":"venue"
},
  "geometry": {"coordinates":[5.5978131294,50.6437721252],"type":"Point"}
}