{
  "type": "Feature",
  "properties": {
    "addr:full":"Aloise Biebuyckstraat 1 Waregem West-Vlaanderen 8793",
    "addr:housenumber":"1",
    "addr:postcode":"8793",
    "addr:street":"Aloise Biebuyckstraat",
    "iso:country":"BE",
    "sg:address":"Aloise Biebuyckstraat 1",
    "sg:city":"Waregem",
    "sg:orig_category":"Cr\u00e9dits divers",
    "sg:postcode":"8793",
    "sg:province":"West-Vlaanderen",
    "wof:name":"Bancontact-mister Cash",
    "wof:placetype":"venue"
},
  "geometry": {"coordinates":[3.4042789936,50.9061965942],"type":"Point"}
}