{
  "type": "Feature",
  "properties": {
    "addr:full":"Gerdingerstraat 11 Bree Limburg 3960",
    "addr:housenumber":"11",
    "addr:postcode":"3960",
    "addr:street":"Gerdingerstraat",
    "iso:country":"BE",
    "sg:address":"Gerdingerstraat 11",
    "sg:city":"Bree",
    "sg:classifiers":[
        {
            "category":"Restaurant",
            "type":"Food & Drink"
        }
    ],
    "sg:phone":"+32 89 47 30 62",
    "sg:postcode":"3960",
    "sg:province":"Limburg",
    "wof:name":"Meat-point",
    "wof:placetype":"venue"
},
  "geometry": {"coordinates":[5.5955710411,51.1416625977],"type":"Point"}
}