{
  "type": "Feature",
  "properties": {
    "iso:country":"BE",
    "sg:address":"Avenue Huart Hamoir 156",
    "sg:city":"Bruxelles",
    "sg:orig_category":"Serrures and charni\u00e8res Fab",
    "sg:phone":"+32 477 23 02 44",
    "sg:postcode":"1030",
    "sg:province":"Bruxelles-Capitale",
    "wof:name":"Multiportes",
    "wof:placetype":"venue"
},
  "geometry": {"coordinates":[4.3869428635,50.8741378784],"type":"Point"}
}