{
  "type": "Feature",
  "properties": {
    "iso:country":"BE",
    "sg:address":"Schoorbakkestr 22",
    "sg:city":"Diksmuide",
    "sg:classifiers":[
        {
            "category":"Professional",
            "type":"Services"
        }
    ],
    "sg:phone":"+32 64 67 79 40",
    "sg:postcode":"8600",
    "sg:province":"West-Vlaanderen",
    "sg:tags":[
        "transport",
        "road"
    ],
    "wof:name":"Societe Tournaisienne De Transport Sa",
    "wof:placetype":"venue"
},
  "geometry": {"coordinates":[4.1505050659,50.4826698303],"type":"Point"}
}