{
  "type": "Feature",
  "properties": {
    "addr:full":"Avenue Eiffel 3 Wavre Brabant Wallon 1300",
    "addr:housenumber":"3;1300",
    "addr:street":"Avenue Eiffel",
    "iso:country":"BE",
    "sg:address":"Avenue Eiffel 3",
    "sg:city":"Wavre",
    "sg:orig_category":"Catering and organisatie van feesten Voedingsspeciaalzaken",
    "sg:phone":"+32 10 22 93 90",
    "sg:postcode":"1300",
    "sg:province":"Brabant Wallon",
    "wof:name":"Traiteur St\u00c9phane Pierre Et Cie",
    "wof:placetype":"venue"
},
  "geometry": {"coordinates":[4.596558094,50.7371101379],"type":"Point"}
}