{
  "type": "Feature",
  "properties": {
    "addr:full":"Franslaan 35b1 Nieuwpoort West-Vlaanderen 8620",
    "addr:housenumber":"35b1",
    "addr:postcode":"8620",
    "addr:street":"Franslaan",
    "iso:country":"BE",
    "sg:address":"Franslaan 35b1",
    "sg:city":"Nieuwpoort",
    "sg:orig_category":"Loodgieterij, verwarming and sanitaire installaties",
    "sg:phone":"+32 58 23 34 07",
    "sg:postcode":"8620",
    "sg:province":"West-Vlaanderen",
    "wof:name":"Willy Clarys",
    "wof:placetype":"venue"
},
  "geometry": {"coordinates":[2.7185459137,51.1488380432],"type":"Point"}
}