{
  "type": "Feature",
  "properties": {
    "iso:country":"BE",
    "sg:address":"Slotlaan 42",
    "sg:city":"Sint-lambrechts-woluwe/woluwe-saint-lambert",
    "sg:orig_category":"Binnenhuisarchitecten",
    "sg:phone":"+32 2 732 92 99",
    "sg:postcode":"1200",
    "sg:province":"Bruxelles-Capitale",
    "wof:name":"Jean-louis Boonen",
    "wof:placetype":"venue"
},
  "geometry": {"coordinates":[4.4123277664,50.8416404724],"type":"Point"}
}