{
  "type": "Feature",
  "properties": {
    "iso:country":"BE",
    "sg:address":"Maria-theresiastraat 107",
    "sg:city":"Leuven",
    "sg:orig_category":"Notaires",
    "sg:phone":"+32 16 22 34 87",
    "sg:postcode":"3000",
    "sg:province":"Vlaams-Brabant",
    "wof:name":"Christian Maes",
    "wof:placetype":"venue"
},
  "geometry": {"coordinates":[4.7138528824,50.880065918],"type":"Point"}
}