{
  "type": "Feature",
  "properties": {
    "iso:country":"BE",
    "sg:address":"Rue Saint-jean 22a",
    "sg:city":"Jodoigne",
    "sg:classifiers":[
        {
            "category":"Utilities",
            "subcategory":"Mobile Phone",
            "type":"Services"
        }
    ],
    "sg:phone":"+32 10 24 88 98",
    "sg:postcode":"1370",
    "sg:province":"Brabant Wallon",
    "sg:tags":[
        "access",
        "gsm",
        "-",
        "apparatus"
    ],
    "wof:name":"Proxitel",
    "wof:placetype":"venue"
},
  "geometry": {"coordinates":[4.8708558083,50.7247924805],"type":"Point"}
}