{
  "type": "Feature",
  "properties": {
    "addr:full":"Rue Albert Cl\u00e9ment 1 Neufch\u00e2teau Luxembourg 6840",
    "addr:housenumber":"1",
    "addr:postcode":"6840",
    "addr:street":"Rue Albert Cle\u0301Ment",
    "iso:country":"BE",
    "sg:address":"Rue Albert Cl\u00e9ment 1",
    "sg:city":"Neufch\u00e2teau",
    "sg:classifiers":[
        {
            "category":"Wholesale",
            "subcategory":"Office Equipment",
            "type":"Manufacturing & Wholesale Goods"
        }
    ],
    "sg:phone":"+32 61 27 71 49",
    "sg:postcode":"6840",
    "sg:province":"Luxembourg",
    "sg:tags":[
        "machine",
        "rental",
        "retail",
        "-"
    ],
    "wof:name":"Michaud (maison)",
    "wof:placetype":"venue"
},
  "geometry": {"coordinates":[5.4345397949,49.8419799805],"type":"Point"}
}