{
  "type": "Feature",
  "properties": {
    "addr:full":"Z.i. De Petit Rechain 30 Chaineux Li\u00e8ge 4650",
    "addr:housenumber":"30",
    "addr:postcode":"4650",
    "addr:street":"Z.I. De Petit Rechain",
    "iso:country":"BE",
    "sg:address":"Z.i. De Petit Rechain 30",
    "sg:city":"Chaineux",
    "sg:classifiers":[
        {
            "category":"Professional",
            "type":"Services"
        }
    ],
    "sg:phone":"+32 87 31 57 76",
    "sg:postcode":"4650",
    "sg:province":"Li\u00e8ge",
    "sg:tags":[
        "transport"
    ],
    "wof:name":"Eral Trans S.a.",
    "wof:placetype":"venue"
},
  "geometry": {"coordinates":[5.8364291191,50.6253509521],"type":"Point"}
}