{
  "type": "Feature",
  "properties": {
    "addr:full":"Vanderkinderestraat 231 Ukkel/uccle Bruxelles-Capitale 1180",
    "addr:housenumber":"231",
    "addr:postcode":"1180",
    "addr:street":"Vanderkinderestraat;/",
    "iso:country":"BE",
    "sg:address":"Vanderkinderestraat 231",
    "sg:city":"Ukkel/uccle",
    "sg:orig_category":"Telecommunicatiesystemen",
    "sg:phone":"+32 2 535 74 79",
    "sg:postcode":"1180",
    "sg:province":"Bruxelles-Capitale",
    "wof:name":"Fe. Overdrive",
    "wof:placetype":"venue"
},
  "geometry": {"coordinates":[4.3527140617,50.8139305115],"type":"Point"}
}