{
  "type": "Feature",
  "properties": {
    "addr:full":"Schelfheidestraat 44 Nieuwerkerken Limburg 3850",
    "addr:housenumber":"44",
    "addr:postcode":"3850",
    "addr:street":"Schelfheidestraat",
    "iso:country":"BE",
    "sg:address":"Schelfheidestraat 44",
    "sg:city":"Nieuwerkerken",
    "sg:orig_category":"Eleveurs de volaille. Eleveurs de bovins",
    "sg:phone":"+32 11 68 22 58",
    "sg:postcode":"3850",
    "sg:province":"Limburg",
    "wof:name":"Ivo Mees",
    "wof:placetype":"venue"
},
  "geometry": {"coordinates":[5.1838288307,50.8730812073],"type":"Point"}
}