{
  "type": "Feature",
  "properties": {
    "addr:full":"Bammestraat 87 Bilzen Limburg 3740",
    "addr:housenumber":"87",
    "addr:postcode":"3740",
    "addr:street":"Bammestraat",
    "iso:country":"BE",
    "sg:address":"Bammestraat 87",
    "sg:city":"Bilzen",
    "sg:orig_category":"Kapsalons",
    "sg:phone":"+32 12 23 78 12",
    "sg:postcode":"3740",
    "sg:province":"Limburg",
    "wof:name":"Malvina Hofmans",
    "wof:placetype":"venue"
},
  "geometry": {"coordinates":[5.5188741684,50.8239555359],"type":"Point"}
}