{
  "type": "Feature",
  "properties": {
    "iso:country":"BE",
    "sg:address":"Brabantstraat 185",
    "sg:city":"Schaarbeek/schaerbeek",
    "sg:orig_category":"Bloemen and planten Verlichting and huishoudartikelen",
    "sg:phone":"+32 2 215 75 26",
    "sg:postcode":"1030",
    "sg:province":"Bruxelles-Capitale",
    "wof:name":"Maison Diodati Export",
    "wof:placetype":"venue"
},
  "geometry": {"coordinates":[4.3657531738,50.8634262085],"type":"Point"}
}