{
  "type": "Feature",
  "properties": {
    "iso:country":"BE",
    "sg:address":"Hoezestraat 71",
    "sg:city":"Aalst",
    "sg:orig_category":"Etalage- and showroomontwerpers",
    "sg:phone":"+32 53 78 20 72",
    "sg:postcode":"9300",
    "sg:province":"Oost-Vlaanderen",
    "wof:name":"Frank Coppens",
    "wof:placetype":"venue"
},
  "geometry": {"coordinates":[4.0308299065,50.925239563],"type":"Point"}
}