{
  "type": "Feature",
  "properties": {
    "addr:full":"Technologiepark-zwijnaarde 9 Zwijnaarde Oost-Vlaanderen 9052",
    "addr:housenumber":"9",
    "addr:postcode":"9052",
    "addr:street":"Technologiepark-Zwijnaarde",
    "iso:country":"BE",
    "sg:address":"Technologiepark-zwijnaarde 9",
    "sg:city":"Zwijnaarde",
    "sg:classifiers":[
        {
            "category":"Health Services",
            "subcategory":"Medical Lab",
            "type":"Services"
        }
    ],
    "sg:phone":"+32 9 324 24 24",
    "sg:postcode":"9052",
    "sg:province":"Oost-Vlaanderen",
    "sg:tags":[
        "laboratory",
        "bio-technology",
        "biological"
    ],
    "wof:name":"Devgen Nv",
    "wof:placetype":"venue"
},
  "geometry": {"coordinates":[3.7052550316,51.0111808777],"type":"Point"}
}