{
  "type": "Feature",
  "properties": {
    "addr:full":"Grand-rue 38 Clavier Li\u00e8ge 4560",
    "addr:housenumber":"38",
    "addr:postcode":"4560",
    "addr:street":"Grand-Rue",
    "iso:country":"BE",
    "sg:address":"Grand-rue 38",
    "sg:city":"Clavier",
    "sg:orig_category":"Epiceries",
    "sg:phone":"+32 86 34 49 46",
    "sg:postcode":"4560",
    "sg:province":"Li\u00e8ge",
    "wof:name":"Ad Delhaize",
    "wof:placetype":"venue"
},
  "geometry": {"coordinates":[5.3238911629,50.4303092957],"type":"Point"}
}