{
  "type": "Feature",
  "properties": {
    "iso:country":"BE",
    "sg:address":"Dolezlaan 586",
    "sg:city":"Ukkel/uccle",
    "sg:orig_category":"Artiesten and kunstenaars",
    "sg:phone":"+32 2 374 47 32",
    "sg:postcode":"1180",
    "sg:province":"Bruxelles-Capitale",
    "wof:name":"Olivier Strebelle",
    "wof:placetype":"venue"
},
  "geometry": {"coordinates":[4.3558168411,50.7746887207],"type":"Point"}
}