{
  "type": "Feature",
  "properties": {
    "iso:country":"BE",
    "sg:address":"Brugstraat 21",
    "sg:city":"Bilzen",
    "sg:classifiers":[
        {
            "category":"Bars & Pubs",
            "type":"Food & Drink"
        }
    ],
    "sg:phone":"+32 89 50 32 54",
    "sg:postcode":"3740",
    "sg:province":"Limburg",
    "wof:name":"Casino",
    "wof:placetype":"venue"
},
  "geometry": {"coordinates":[5.5174651146,50.8689918518],"type":"Point"}
}