{
  "type": "Feature",
  "properties": {
    "iso:country":"BE",
    "sg:address":"Heuveneindeweg 9b",
    "sg:city":"Zonhoven",
    "sg:classifiers":[
        {
            "category":"Insurance",
            "subcategory":"Insurance Agent",
            "type":"Services"
        }
    ],
    "sg:phone":"+32 11 81 89 31",
    "sg:postcode":"3520",
    "sg:province":"Limburg",
    "sg:tags":[
        "-",
        "representative"
    ],
    "wof:name":"Beelen & Thijs Dvv",
    "wof:placetype":"venue"
},
  "geometry": {"coordinates":[5.3611478806,50.9711074829],"type":"Point"}
}