{
  "type": "Feature",
  "properties": {
    "addr:full":"Prinsenlaan 55 Blankenberge West-Vlaanderen 8370",
    "addr:housenumber":"55",
    "addr:postcode":"8370",
    "addr:street":"Prinsenlaan",
    "iso:country":"BE",
    "sg:address":"Prinsenlaan 55",
    "sg:city":"Blankenberge",
    "sg:orig_category":"Plomberie, chauffage and installations sanitaires. Charpentes and couvertures",
    "sg:phone":"+32 50 41 57 42",
    "sg:postcode":"8370",
    "sg:province":"West-Vlaanderen",
    "wof:name":"Thermo",
    "wof:placetype":"venue"
},
  "geometry": {"coordinates":[3.1368620396,51.3148918152],"type":"Point"}
}