{
  "type": "Feature",
  "properties": {
    "addr:full":"Keulenstraat 56 Herent Vlaams-Brabant 3020",
    "addr:housenumber":"56",
    "addr:postcode":"3020",
    "addr:street":"Keulenstraat",
    "iso:country":"BE",
    "sg:address":"Keulenstraat 56",
    "sg:city":"Herent",
    "sg:orig_category":"M\u00e9decins and sp\u00e9cialistes",
    "sg:phone":"+32 16 20 28 91",
    "sg:postcode":"3020",
    "sg:province":"Vlaams-Brabant",
    "wof:name":"Gery Barbier",
    "wof:placetype":"venue"
},
  "geometry": {"coordinates":[4.683839798,50.9238204956],"type":"Point"}
}