{
  "type": "Feature",
  "properties": {
    "iso:country":"BE",
    "sg:address":"Rue Audrey Hepburn 10b7",
    "sg:city":"Jette",
    "sg:classifiers":[
        {
            "category":"Arena",
            "subcategory":"Sports Club",
            "type":"Entertainment"
        }
    ],
    "sg:phone":"+32 2 478 18 03",
    "sg:postcode":"1090",
    "sg:province":"Bruxelles-Capitale",
    "sg:tags":[
        "de"
    ],
    "wof:name":"Royal Fleur Bleue",
    "wof:placetype":"venue"
},
  "geometry": {"coordinates":[4.3127222061,50.8906745911],"type":"Point"}
}