{
  "type": "Feature",
  "properties": {
    "addr:full":"Rue De La Lib\u00c9ration 25 Charleroi Hainaut 6030",
    "addr:housenumber":"25",
    "addr:postcode":"6030",
    "addr:street":"Rue De La Libe\u0301Ration;Hainaut",
    "iso:country":"BE",
    "sg:address":"Rue De La Lib\u00c9ration 25",
    "sg:city":"Charleroi",
    "sg:orig_category":"Enseignement maternel and primaire",
    "sg:phone":"+32 71 52 91 12",
    "sg:postcode":"6030",
    "sg:province":"Hainaut",
    "wof:name":"Ecole Matern. Communale",
    "wof:placetype":"venue"
},
  "geometry": {"coordinates":[4.3603210449,50.406337738],"type":"Point"}
}