{
  "type": "Feature",
  "properties": {
    "iso:country":"BE",
    "sg:address":"Rue De Charleroi 4a",
    "sg:city":"Genepien",
    "sg:classifiers":[
        {
            "category":"Personal",
            "subcategory":"Beauty Salon",
            "type":"Services"
        }
    ],
    "sg:phone":"+32 67 79 19 24",
    "sg:postcode":"1470",
    "sg:province":"Brabant Wallon",
    "sg:tags":[
        "de",
        "coiffure"
    ],
    "wof:name":"Coiffure Art'tif",
    "wof:placetype":"venue"
},
  "geometry": {"coordinates":[4.4503808022,50.6104393005],"type":"Point"}
}