{
  "type": "Feature",
  "properties": {
    "addr:full":"Wilde Heide 18 Haacht Vlaams-Brabant 3150",
    "addr:housenumber":"18",
    "addr:postcode":"3150",
    "addr:street":"Wilde Heide",
    "iso:country":"BE",
    "sg:address":"Wilde Heide 18",
    "sg:city":"Haacht",
    "sg:classifiers":[
        {
            "category":"Freight",
            "type":"Transportation"
        }
    ],
    "sg:phone":"+32 16 60 02 59",
    "sg:postcode":"3150",
    "sg:province":"Vlaams-Brabant",
    "sg:tags":[
        "-",
        "refrigerated",
        "transport"
    ],
    "wof:name":"Ringoot Bvba",
    "wof:placetype":"venue"
},
  "geometry": {"coordinates":[4.6486029625,50.9805488586],"type":"Point"}
}