{
  "type": "Feature",
  "properties": {
    "iso:country":"BE",
    "sg:address":"Gielisheide 10",
    "sg:city":"Meeuwen-gruitrode",
    "sg:orig_category":"Rundveehouders Varkenskwekers",
    "sg:phone":"+32 11 79 17 52",
    "sg:postcode":"3670",
    "sg:province":"Limburg",
    "wof:name":"Jacob Niesen",
    "wof:placetype":"venue"
},
  "geometry": {"coordinates":[5.4896388054,51.1033172607],"type":"Point"}
}