{
  "type": "Feature",
  "properties": {
    "addr:full":"Avenue Cardinal Mercier 1 Namur Namur 5000",
    "addr:housenumber":"1",
    "addr:postcode":"5000",
    "addr:street":"Avenue Cardinal Mercier",
    "iso:country":"BE",
    "sg:address":"Avenue Cardinal Mercier 1",
    "sg:city":"Namur",
    "sg:orig_category":"Avocats and conseillers juridiques",
    "sg:phone":"+32 81 74 20 84",
    "sg:postcode":"5000",
    "sg:province":"Namur",
    "wof:name":"Beno\u00cet Hoc",
    "wof:placetype":"venue"
},
  "geometry": {"coordinates":[4.8529047966,50.4659538269],"type":"Point"}
}