{
  "type": "Feature",
  "properties": {
    "addr:full":"Rue Fran\u00e7ois Givron 13 Les Bons Villers (frasnes-lez-gosselies) Hainaut 6210",
    "addr:housenumber":"13",
    "addr:postcode":"6210",
    "addr:street":"Rue Franc\u0327Ois Givron",
    "iso:country":"BE",
    "sg:address":"Rue Fran\u00e7ois Givron 13",
    "sg:city":"Les Bons Villers (frasnes-lez-gosselies)",
    "sg:classifiers":[
        {
            "category":"Home & Garden",
            "subcategory":"Household Appliances",
            "type":"Retail Goods"
        }
    ],
    "sg:phone":"+32 71 85 11 03",
    "sg:postcode":"6210",
    "sg:province":"Hainaut",
    "sg:tags":[
        "repair",
        "mainten",
        "-",
        "electric"
    ],
    "wof:name":"Robert J",
    "wof:placetype":"venue"
},
  "geometry": {"coordinates":[4.4511561394,50.5378227234],"type":"Point"}
}