{
  "type": "Feature",
  "properties": {
    "iso:country":"BE",
    "sg:address":"Avenue L\u00e9on Champagne 2",
    "sg:city":"Tubize (saintes)",
    "sg:classifiers":[
        {
            "category":"Professional",
            "subcategory":"Management & Consulting",
            "type":"Services"
        }
    ],
    "sg:phone":"+32 2 391 45 45",
    "sg:postcode":"1480",
    "sg:province":"Brabant Wallon",
    "sg:tags":[
        "consultant"
    ],
    "wof:name":"United Consultant",
    "wof:placetype":"venue"
},
  "geometry": {"coordinates":[4.1754570007,50.70911026],"type":"Point"}
}