{
  "type": "Feature",
  "properties": {
    "addr:full":"Engelhoekstraat 56 Deinze Oost-Vlaanderen 9800",
    "addr:housenumber":"56",
    "addr:postcode":"9800",
    "addr:street":"Engelhoekstraat",
    "iso:country":"BE",
    "sg:address":"Engelhoekstraat 56",
    "sg:city":"Deinze",
    "sg:orig_category":"Epiceries",
    "sg:phone":"+32 9 282 33 02",
    "sg:postcode":"9800",
    "sg:province":"Oost-Vlaanderen",
    "wof:name":"Jean-paul Van De Walle",
    "wof:placetype":"venue"
},
  "geometry": {"coordinates":[3.5820960999,51.0230903625],"type":"Point"}
}