{
  "type": "Feature",
  "properties": {
    "iso:country":"BE",
    "sg:address":"Neerstraat 75",
    "sg:city":"Waasmunster",
    "sg:classifiers":[
        {
            "category":"Insurance",
            "subcategory":"Life Insurance",
            "type":"Services"
        }
    ],
    "sg:phone":"+32 52 46 36 61",
    "sg:postcode":"9250",
    "sg:province":"Oost-Vlaanderen",
    "sg:tags":[
        "assurance"
    ],
    "wof:name":"Dekadesign",
    "wof:placetype":"venue"
},
  "geometry": {"coordinates":[4.0626559258,51.111289978],"type":"Point"}
}