{
  "type": "Feature",
  "properties": {
    "iso:country":"BE",
    "sg:address":"Hernestraat 34",
    "sg:city":"Edingen/enghien",
    "sg:orig_category":"Verplichte sociale verzekeringen",
    "sg:phone":"+32 2 395 33 69",
    "sg:postcode":"7850",
    "sg:province":"Hainaut",
    "wof:name":"Mutualit\u00c9 Socialiste",
    "wof:placetype":"venue"
},
  "geometry": {"coordinates":[4.0385689735,50.6943893433],"type":"Point"}
}