{
  "type": "Feature",
  "properties": {
    "addr:full":"De Keyserlei 13 Antwerpen Antwerpen 2018",
    "addr:housenumber":"13",
    "addr:postcode":"2018",
    "addr:street":"De Keyserlei",
    "iso:country":"BE",
    "sg:address":"De Keyserlei 13",
    "sg:city":"Antwerpen",
    "sg:classifiers":[
        {
            "category":"Restaurant",
            "type":"Food & Drink"
        }
    ],
    "sg:phone":"+32 3 289 09 44",
    "sg:postcode":"2018",
    "sg:province":"Antwerpen",
    "sg:tags":[
        "caf\u00e9s"
    ],
    "wof:name":"The Coocking Village",
    "wof:placetype":"venue"
},
  "geometry": {"coordinates":[4.4171409607,51.217880249],"type":"Point"}
}