{
  "type": "Feature",
  "properties": {
    "iso:country":"BE",
    "sg:address":"Chauss\u00c9e D'audenarde 415",
    "sg:city":"Pecq",
    "sg:classifiers":[
        {
            "category":"Cafe",
            "type":"Food & Drink"
        }
    ],
    "sg:phone":"+32 69 55 70 76",
    "sg:postcode":"7742",
    "sg:province":"Hainaut",
    "sg:tags":[
        "caf\u00e9s"
    ],
    "wof:name":"Caf\u00c9 La Camargue",
    "wof:placetype":"venue"
},
  "geometry": {"coordinates":[3.3632400036,50.7007637024],"type":"Point"}
}