{
  "type": "Feature",
  "properties": {
    "iso:country":"BE",
    "sg:address":"Rue De La Bouteille 8a",
    "sg:city":"Gembloux-sur-orneau (gembloux)",
    "sg:classifiers":[
        {
            "category":"Shopping",
            "subcategory":"Crafts & Fabrics",
            "type":"Retail Goods"
        }
    ],
    "sg:phone":"+32 81 61 13 21",
    "sg:postcode":"5030",
    "sg:province":"Namur",
    "sg:tags":[
        "silk",
        "-"
    ],
    "wof:name":"Cousette (la)",
    "wof:placetype":"venue"
},
  "geometry": {"coordinates":[4.6986689568,50.5547790527],"type":"Point"}
}