{
  "type": "Feature",
  "properties": {
    "iso:country":"BE",
    "sg:address":"Nijverh. Begijnenmeers 63",
    "sg:city":"Liedekerke",
    "sg:orig_category":"Plomberie, chauffage and installations sanitaires",
    "sg:phone":"+32 53 68 10 10",
    "sg:postcode":"1770",
    "sg:province":"Vlaams-Brabant",
    "wof:name":"Weiss Technik-heraeus",
    "wof:placetype":"venue"
},
  "geometry": {"coordinates":[4.0907402039,50.8836326599],"type":"Point"}
}