{
  "type": "Feature",
  "properties": {
    "addr:full":"Waterloose Steenweg 219 Sint-gillis/saint-gilles Bruxelles-Capitale 1060",
    "addr:housenumber":"219",
    "addr:postcode":"1060",
    "addr:street":"Waterloose Steenweg",
    "iso:country":"BE",
    "sg:address":"Waterloose Steenweg 219",
    "sg:city":"Sint-gillis/saint-gilles",
    "sg:orig_category":"Zuivelproducten",
    "sg:phone":"+32 2 537 92 70",
    "sg:postcode":"1060",
    "sg:province":"Bruxelles-Capitale",
    "wof:name":"Cremerie Napoleon",
    "wof:placetype":"venue"
},
  "geometry": {"coordinates":[4.3474340439,50.8254699707],"type":"Point"}
}