{
  "type": "Feature",
  "properties": {
    "addr:full":"Poelstraat 25 Merelbeke Oost-Vlaanderen 9820",
    "addr:housenumber":"25",
    "addr:postcode":"9820",
    "addr:street":"Poelstraat",
    "iso:country":"BE",
    "sg:address":"Poelstraat 25",
    "sg:city":"Merelbeke",
    "sg:classifiers":[
        {
            "category":"Building & Trades",
            "subcategory":"Equipment Rental",
            "type":"Services"
        }
    ],
    "sg:phone":"+32 9 230 65 87",
    "sg:postcode":"9820",
    "sg:province":"Oost-Vlaanderen",
    "sg:tags":[
        "tableware",
        "-"
    ],
    "wof:name":"Levi Nv",
    "wof:placetype":"venue"
},
  "geometry": {"coordinates":[3.7478330135,50.9892692566],"type":"Point"}
}