{
  "type": "Feature",
  "properties": {
    "addr:full":"Kapellendries 24 Wetteren Oost-Vlaanderen 9230",
    "addr:housenumber":"24",
    "addr:postcode":"9230",
    "addr:street":"Kapellendries",
    "iso:country":"BE",
    "sg:address":"Kapellendries 24",
    "sg:city":"Wetteren",
    "sg:classifiers":[
        {
            "category":"Social Services",
            "subcategory":"Job Training",
            "type":"Services"
        }
    ],
    "sg:phone":"+32 9 366 38 23",
    "sg:postcode":"9230",
    "sg:province":"Oost-Vlaanderen",
    "sg:tags":[
        "condiment",
        "spice"
    ],
    "wof:name":"Specian Bvba-de Winter A.m.",
    "wof:placetype":"venue"
},
  "geometry": {"coordinates":[3.8825309277,51.0102005005],"type":"Point"}
}