{
  "type": "Feature",
  "properties": {
    "addr:full":"Lange Veldstraat 94 Waasmunster Oost-Vlaanderen 9250",
    "addr:housenumber":"94",
    "addr:postcode":"9250",
    "addr:street":"Lange Veldstraat",
    "iso:country":"BE",
    "sg:address":"Lange Veldstraat 94",
    "sg:city":"Waasmunster",
    "sg:orig_category":"Non-Classified Establishments",
    "sg:phone":"+32 3 772 44 46",
    "sg:postcode":"9250",
    "sg:province":"Oost-Vlaanderen",
    "wof:name":"Qualytex Bvba",
    "wof:placetype":"venue"
},
  "geometry": {"coordinates":[4.0486340523,51.1237030029],"type":"Point"}
}