{
  "type": "Feature",
  "properties": {
    "addr:full":"Rue De Chevelipont 2 Court-saint-etienne Brabant Wallon 1490",
    "addr:housenumber":"2;1490",
    "addr:street":"Rue De Chevelipont",
    "iso:country":"BE",
    "sg:address":"Rue De Chevelipont 2",
    "sg:city":"Court-saint-etienne",
    "sg:classifiers":[
        {
            "category":"Restaurant",
            "type":"Food & Drink"
        }
    ],
    "sg:phone":"+32 10 61 63 66",
    "sg:postcode":"1490",
    "sg:province":"Brabant Wallon",
    "wof:name":"Le Relais Gourmand",
    "wof:placetype":"venue"
},
  "geometry": {"coordinates":[4.534673214,50.5997085571],"type":"Point"}
}