{
  "type": "Feature",
  "properties": {
    "iso:country":"BE",
    "sg:address":"Th\u00c9ophile Donn\u00c9straat 23",
    "sg:city":"Herk-de-stad",
    "sg:orig_category":"Eclairage et \u00e9quipements du foyer. Electrom\u00e9nager, t\u00e9l\u00e9visions and radios",
    "sg:phone":"+32 13 44 10 47",
    "sg:postcode":"3540",
    "sg:province":"Limburg",
    "wof:name":"Weymac Electronics",
    "wof:placetype":"venue"
},
  "geometry": {"coordinates":[5.1400241852,50.9429397583],"type":"Point"}
}