{
  "type": "Feature",
  "properties": {
    "iso:country":"BE",
    "sg:address":"Resedastraat 23",
    "sg:city":"Lovendegem",
    "sg:classifiers":[
        {
            "category":"Health Services",
            "subcategory":"Hospital",
            "type":"Services"
        }
    ],
    "sg:phone":"+32 9 372 67 11",
    "sg:postcode":"9920",
    "sg:province":"Oost-Vlaanderen",
    "wof:name":"Ter Bronnen",
    "wof:placetype":"venue"
},
  "geometry": {"coordinates":[3.636480093,51.1058692932],"type":"Point"}
}