{
  "type": "Feature",
  "properties": {
    "addr:full":"Rue Saint-ulgiste 20 Binche Hainaut 7130",
    "addr:housenumber":"20",
    "addr:postcode":"7130",
    "addr:street":"Rue Saint-Ulgiste",
    "iso:country":"BE",
    "sg:address":"Rue Saint-ulgiste 20",
    "sg:city":"Binche",
    "sg:orig_category":"Instituts de beaut\u00e9",
    "sg:phone":"+32 64 33 23 40",
    "sg:postcode":"7130",
    "sg:province":"Hainaut",
    "wof:name":"Valerie De Simone",
    "wof:placetype":"venue"
},
  "geometry": {"coordinates":[4.1632342339,50.4124794006],"type":"Point"}
}