{
  "type": "Feature",
  "properties": {
    "addr:full":"Ingooigemplaats 44 Anzegem (ingooigem) West-Vlaanderen 8570",
    "addr:housenumber":"44",
    "addr:postcode":"8570",
    "addr:street":"Ingooigemplaats",
    "iso:country":"BE",
    "sg:address":"Ingooigemplaats 44",
    "sg:city":"Anzegem (ingooigem)",
    "sg:classifiers":[
        {
            "category":"Bars & Pubs",
            "type":"Food & Drink"
        }
    ],
    "sg:phone":"+32 56 77 61 41",
    "sg:postcode":"8570",
    "sg:province":"West-Vlaanderen",
    "wof:name":"D'halve Maan",
    "wof:placetype":"venue"
},
  "geometry": {"coordinates":[3.4309060574,50.8184242249],"type":"Point"}
}