{
  "type": "Feature",
  "properties": {
    "addr:full":"Oostrozebekestraat 96 Meulebeke West-Vlaanderen 8760",
    "addr:housenumber":"96",
    "addr:postcode":"8760",
    "addr:street":"Oostrozebekestraat",
    "iso:country":"BE",
    "sg:address":"Oostrozebekestraat 96",
    "sg:city":"Meulebeke",
    "sg:orig_category":"Banques and organismes de cr\u00e9dit",
    "sg:phone":"+32 51 48 90 66",
    "sg:postcode":"8760",
    "sg:province":"West-Vlaanderen",
    "wof:name":"Dipo",
    "wof:placetype":"venue"
},
  "geometry": {"coordinates":[3.2921481133,50.9454994202],"type":"Point"}
}