{
  "type": "Feature",
  "properties": {
    "addr:full":"Elleboogstraat 7 Kortrijk West-Vlaanderen 8500",
    "addr:housenumber":"7",
    "addr:postcode":"8500",
    "addr:street":"Elleboogstraat",
    "iso:country":"BE",
    "sg:address":"Elleboogstraat 7",
    "sg:city":"Kortrijk",
    "sg:classifiers":[
        {
            "category":"Manufacturing",
            "subcategory":"Metals",
            "type":"Manufacturing & Wholesale Goods"
        }
    ],
    "sg:phone":"+32 56 22 00 21",
    "sg:postcode":"8500",
    "sg:province":"West-Vlaanderen",
    "sg:tags":[
        "non-ferrous",
        "-"
    ],
    "wof:name":"Van Lerberghe A Etn",
    "wof:placetype":"venue"
},
  "geometry": {"coordinates":[3.283616066,50.7965583801],"type":"Point"}
}