{
  "type": "Feature",
  "properties": {
    "iso:country":"BE",
    "sg:address":"Chemin Du Sart 31",
    "sg:city":"Ham-sur-heure-nalinnes (ham-sur-heure)",
    "sg:classifiers":[
        {
            "category":"Sports & Exercise",
            "subcategory":"Race Track",
            "type":"Entertainment"
        }
    ],
    "sg:phone":"+32 71 21 36 07",
    "sg:postcode":"6120",
    "sg:province":"Hainaut",
    "sg:tags":[
        "guide"
    ],
    "wof:name":"Annuaire Du Commerce Sprl",
    "wof:placetype":"venue"
},
  "geometry": {"coordinates":[4.3872900009,50.3219146729],"type":"Point"}
}