{
  "type": "Feature",
  "properties": {
    "iso:country":"BE",
    "sg:address":"Poperingestraat 29",
    "sg:city":"Vleteren",
    "sg:orig_category":"Varkenskwekers",
    "sg:phone":"+32 57 42 24 06",
    "sg:postcode":"8640",
    "sg:province":"West-Vlaanderen",
    "wof:name":"Hugo Breemeersch",
    "wof:placetype":"venue"
},
  "geometry": {"coordinates":[2.7859508991,50.8980445862],"type":"Point"}
}