{
  "type": "Feature",
  "properties": {
    "addr:full":"Rue De La Paix 3 Charleroi Hainaut 6000",
    "addr:housenumber":"3",
    "addr:postcode":"6000",
    "addr:street":"Rue De La Paix;Hainaut",
    "iso:country":"BE",
    "sg:address":"Rue De La Paix 3",
    "sg:city":"Charleroi",
    "sg:orig_category":"Woningbouw",
    "sg:phone":"+32 71 30 80 17",
    "sg:postcode":"6000",
    "sg:province":"Hainaut",
    "wof:name":"S. Pozzi",
    "wof:placetype":"venue"
},
  "geometry": {"coordinates":[4.4532132149,50.4099159241],"type":"Point"}
}