{
  "type": "Feature",
  "properties": {
    "addr:full":"R. Volontaires De Guerre 72 Verviers Li\u00e8ge 4800",
    "addr:housenumber":"72",
    "addr:postcode":"4800",
    "iso:country":"BE",
    "sg:address":"R. Volontaires De Guerre 72",
    "sg:city":"Verviers",
    "sg:orig_category":"Experts-comptables",
    "sg:phone":"+32 87 35 18 88",
    "sg:postcode":"4800",
    "sg:province":"Li\u00e8ge",
    "wof:name":"Donatienne Courtois",
    "wof:placetype":"venue"
},
  "geometry": {"coordinates":[5.8594508171,50.5917663574],"type":"Point"}
}