{
  "type": "Feature",
  "properties": {
    "addr:full":"Grand'route 306 Tournai Hainaut 7530",
    "addr:housenumber":"306",
    "addr:postcode":"7530",
    "addr:street":"Grand'Route",
    "iso:country":"BE",
    "sg:address":"Grand'route 306",
    "sg:city":"Tournai",
    "sg:orig_category":"Entretien and r\u00e9parations de voitures. Articles de jardin",
    "sg:phone":"+32 69 54 67 60",
    "sg:postcode":"7530",
    "sg:province":"Hainaut",
    "wof:name":"Fe. Requier & Fils",
    "wof:placetype":"venue"
},
  "geometry": {"coordinates":[3.3858730793,50.6069221497],"type":"Point"}
}