{
  "type": "Feature",
  "properties": {
    "addr:full":"Rue L'h\u00d4tel Des Monnaies 142 Sint-gillis/saint-gilles Bruxelles-Capitale 1060",
    "addr:housenumber":"142",
    "addr:postcode":"1060",
    "addr:street":"Rue L'Ho;Des Monnaies",
    "iso:country":"BE",
    "sg:address":"Rue L'h\u00d4tel Des Monnaies 142",
    "sg:city":"Sint-gillis/saint-gilles",
    "sg:orig_category":"Epiceries",
    "sg:phone":"+32 2 537 62 75",
    "sg:postcode":"1060",
    "sg:province":"Bruxelles-Capitale",
    "wof:name":"Vassilios Nikolaou",
    "wof:placetype":"venue"
},
  "geometry": {"coordinates":[4.3465309143,50.828792572],"type":"Point"}
}