{
  "type": "Feature",
  "properties": {
    "addr:full":"Leuvensebaan 44 Heist-op-den-berg (schriek) Antwerpen 2223",
    "addr:housenumber":"44",
    "addr:postcode":"2223",
    "addr:street":"Leuvensebaan",
    "iso:country":"BE",
    "sg:address":"Leuvensebaan 44",
    "sg:city":"Heist-op-den-berg (schriek)",
    "sg:classifiers":[
        {
            "category":"Home & Garden",
            "subcategory":"Household Appliances",
            "type":"Retail Goods"
        }
    ],
    "sg:phone":"+32 15 23 32 08",
    "sg:postcode":"2223",
    "sg:province":"Antwerpen",
    "sg:tags":[
        "repair",
        "mainten",
        "-",
        "electric"
    ],
    "wof:name":"Scheirs J",
    "wof:placetype":"venue"
},
  "geometry": {"coordinates":[4.6935648918,51.0282707214],"type":"Point"}
}