{
  "type": "Feature",
  "properties": {
    "addr:full":"Rue No\u00cbl 108 Waterloo Brabant Wallon 1410",
    "addr:housenumber":"108",
    "addr:postcode":"1410",
    "addr:street":"Rue Noe\u0308L",
    "iso:country":"BE",
    "sg:address":"Rue No\u00cbl 108",
    "sg:city":"Waterloo",
    "sg:orig_category":"Installatie van houten of kunststof schrijnwerk",
    "sg:phone":"+32 2 384 96 89",
    "sg:postcode":"1410",
    "sg:province":"Brabant Wallon",
    "wof:name":"Free Am\u00c9nagement",
    "wof:placetype":"venue"
},
  "geometry": {"coordinates":[4.3709201813,50.7059402466],"type":"Point"}
}