{
  "type": "Feature",
  "properties": {
    "addr:full":"Kasteelstraat 10 Zonnebeke West-Vlaanderen 8980",
    "addr:housenumber":"10",
    "addr:postcode":"8980",
    "addr:street":"Kasteelstraat",
    "iso:country":"BE",
    "sg:address":"Kasteelstraat 10",
    "sg:city":"Zonnebeke",
    "sg:orig_category":"Eleveurs and marchands de porcs",
    "sg:phone":"+32 57 46 86 92",
    "sg:postcode":"8980",
    "sg:province":"West-Vlaanderen",
    "wof:name":"Lily Dewitte",
    "wof:placetype":"venue"
},
  "geometry": {"coordinates":[2.9563341141,50.8509559631],"type":"Point"}
}