{
  "type": "Feature",
  "properties": {
    "addr:full":"Ginstlaan 12 Sint-genesius-rode/rhode-saint-genese Vlaams-Brabant 1640",
    "addr:housenumber":"12",
    "addr:postcode":"1640",
    "addr:street":"Ginstlaan",
    "iso:country":"BE",
    "sg:address":"Ginstlaan 12",
    "sg:city":"Sint-genesius-rode/rhode-saint-genese",
    "sg:orig_category":"Advocaten and juridische adviseurs",
    "sg:phone":"+32 2 358 11 58",
    "sg:postcode":"1640",
    "sg:province":"Vlaams-Brabant",
    "wof:name":"R. De Kepper",
    "wof:placetype":"venue"
},
  "geometry": {"coordinates":[4.3657069206,50.7699317932],"type":"Point"}
}