{
  "type": "Feature",
  "properties": {
    "iso:country":"BE",
    "sg:address":"H\u00f6veler Gasse 19",
    "sg:city":"Raeren (eynatten)",
    "sg:classifiers":[
        {
            "category":"Health Services",
            "subcategory":"Dentist",
            "type":"Services"
        }
    ],
    "sg:phone":"+32 87 85 08 41",
    "sg:postcode":"4731",
    "sg:province":"Li\u00e8ge",
    "wof:name":"Mennicken Roger",
    "wof:placetype":"venue"
},
  "geometry": {"coordinates":[6.0842242241,50.6944389343],"type":"Point"}
}