{
  "type": "Feature",
  "properties": {
    "iso:country":"BE",
    "sg:address":"Camiel Schuermanslaan 52",
    "sg:city":"Kortenberg",
    "sg:orig_category":"V\u00e9t\u00e9rinaires",
    "sg:phone":"+32 2 759 77 02",
    "sg:postcode":"3070",
    "sg:province":"Vlaams-Brabant",
    "wof:name":"Dirk Van Tricht",
    "wof:placetype":"venue"
},
  "geometry": {"coordinates":[4.5409531593,50.882183075],"type":"Point"}
}