{
  "type": "Feature",
  "properties": {
    "iso:country":"BE",
    "sg:address":"Vinnekensstraat 16",
    "sg:city":"Kapelle-op-den-bos",
    "sg:orig_category":"Benzinestations and brandstoffen HUISBRANDOLIE",
    "sg:phone":"+32 15 71 14 80",
    "sg:postcode":"1880",
    "sg:province":"Vlaams-Brabant",
    "wof:name":"Den Tieleman",
    "wof:placetype":"venue"
},
  "geometry": {"coordinates":[4.3382048607,51.0223464966],"type":"Point"}
}