{
  "type": "Feature",
  "properties": {
    "iso:country":"BE",
    "sg:address":"Rue Pasc. Et Raph. Sacr\u00c9 19",
    "sg:city":"Crisn\u00c9e",
    "sg:classifiers":[
        {
            "category":"Shopping",
            "subcategory":"Clothing, Apparel, & Fashions",
            "type":"Retail Goods"
        }
    ],
    "sg:phone":"+32 4 257 40 41",
    "sg:postcode":"4367",
    "sg:province":"Li\u00e8ge",
    "sg:tags":[
        "lingerie",
        "sous-v\u00eatements"
    ],
    "wof:name":"Nouvelle Lingerie Latour",
    "wof:placetype":"venue"
},
  "geometry": {"coordinates":[5.3976340294,50.716632843],"type":"Point"}
}