{
  "type": "Feature",
  "properties": {
    "addr:full":"Rue Entre Les Maisons 90 Vis\u00e9 (cheratte) Li\u00e8ge 4602",
    "addr:housenumber":"90",
    "addr:postcode":"4602",
    "addr:street":"Rue Entre Les Maisons;Cheratte",
    "iso:country":"BE",
    "sg:address":"Rue Entre Les Maisons 90",
    "sg:city":"Vis\u00e9 (cheratte)",
    "sg:classifiers":[
        {
            "category":"Shopping",
            "subcategory":"Bicycles & Sporting Goods",
            "type":"Retail Goods"
        }
    ],
    "sg:phone":"+32 4 362 72 78",
    "sg:postcode":"4602",
    "sg:province":"Li\u00e8ge",
    "sg:tags":[
        "-"
    ],
    "wof:name":"Jacky Sport",
    "wof:placetype":"venue"
},
  "geometry": {"coordinates":[5.6729259491,50.6866836548],"type":"Point"}
}