{
  "type": "Feature",
  "properties": {
    "addr:full":"Rue De Gravelines 28 Brussel/bruxelles Bruxelles-Capitale 1000",
    "addr:housenumber":"28",
    "addr:postcode":"1000",
    "addr:street":"Rue De Gravelines;/",
    "iso:country":"BE",
    "sg:address":"Rue De Gravelines 28",
    "sg:city":"Brussel/bruxelles",
    "sg:classifiers":[
        {
            "category":"Building & Trades",
            "subcategory":"Plumbing",
            "type":"Services"
        }
    ],
    "sg:phone":"+32 2 230 43 02",
    "sg:postcode":"1000",
    "sg:province":"Bruxelles-Capitale",
    "sg:tags":[
        "diver",
        "commerce",
        "gr",
        "pour",
        "equipement"
    ],
    "wof:name":"J.c.",
    "wof:placetype":"venue"
},
  "geometry": {"coordinates":[4.380027771,50.8488616943],"type":"Point"}
}