{
  "type": "Feature",
  "properties": {
    "iso:country":"BE",
    "sg:address":"Sluisweg 8",
    "sg:city":"Merelbeke",
    "sg:orig_category":"Emballages en plastique Fab",
    "sg:phone":"+32 9 241 12 11",
    "sg:postcode":"9820",
    "sg:province":"Oost-Vlaanderen",
    "wof:name":"Ici Belgium",
    "wof:placetype":"venue"
},
  "geometry": {"coordinates":[3.7407000065,51.0119628906],"type":"Point"}
}