{
  "type": "Feature",
  "properties": {
    "addr:full":"Rue Stendrich 51 Baelen (membach) Li\u00e8ge 4837",
    "addr:housenumber":"51",
    "addr:postcode":"4837",
    "addr:street":"Rue Stendrich",
    "iso:country":"BE",
    "sg:address":"Rue Stendrich 51",
    "sg:city":"Baelen (membach)",
    "sg:classifiers":[
        {
            "category":"Personal",
            "subcategory":"Nail Salon",
            "type":"Services"
        }
    ],
    "sg:phone":"+32 87 74 00 76",
    "sg:postcode":"4837",
    "sg:province":"Li\u00e8ge",
    "sg:tags":[
        "pedicure"
    ],
    "wof:name":"Ernst",
    "wof:placetype":"venue"
},
  "geometry": {"coordinates":[6.0040922165,50.6225891113],"type":"Point"}
}