{
  "type": "Feature",
  "properties": {
    "addr:full":"Dorpsstraat 36 Wellen (groot) Limburg 3830",
    "addr:housenumber":"36",
    "addr:postcode":"3830",
    "addr:street":"Dorpsstraat;Groot Limburg",
    "iso:country":"BE",
    "sg:address":"Dorpsstraat 36",
    "sg:city":"Wellen (groot)",
    "sg:orig_category":"Woningbouw",
    "sg:phone":"+32 12 74 60 48",
    "sg:postcode":"3830",
    "sg:province":"Limburg",
    "wof:name":"Nagels Bouwservice",
    "wof:placetype":"venue"
},
  "geometry": {"coordinates":[5.3327941895,50.8405265808],"type":"Point"}
}