{
  "type": "Feature",
  "properties": {
    "iso:country":"BE",
    "sg:address":"Oude-bruglaan 32",
    "sg:city":"Lokeren",
    "sg:classifiers":[
        {
            "category":"Cafe",
            "type":"Food & Drink"
        }
    ],
    "sg:phone":"+32 9 348 33 52",
    "sg:postcode":"9160",
    "sg:province":"Oost-Vlaanderen",
    "sg:tags":[
        "caf\u00e9s"
    ],
    "wof:name":"Gert Van De Wiele",
    "wof:placetype":"venue"
},
  "geometry": {"coordinates":[4.0009632111,51.1039047241],"type":"Point"}
}