{
  "type": "Feature",
  "properties": {
    "iso:country":"BE",
    "sg:address":"Schiphollaan 6",
    "sg:city":"Evere/evere",
    "sg:orig_category":"Verbruikerskredietinstellingen",
    "sg:phone":"+32 2 702 54 11",
    "sg:postcode":"1140",
    "sg:province":"Bruxelles-Capitale",
    "wof:name":"C.i.k./caisse Interprof. C.i.k.",
    "wof:placetype":"venue"
},
  "geometry": {"coordinates":[4.4162697792,50.8755111694],"type":"Point"}
}