{
  "type": "Feature",
  "properties": {
    "addr:full":"Lindestraat 16 Zwalm Oost-Vlaanderen 9636",
    "addr:housenumber":"16",
    "addr:postcode":"9636",
    "addr:street":"Lindestraat;Oost-Vlaanderen",
    "iso:country":"BE",
    "sg:address":"Lindestraat 16",
    "sg:city":"Zwalm",
    "sg:orig_category":"Charpentes and couvertures",
    "sg:phone":"+32 55 49 67 27",
    "sg:postcode":"9636",
    "sg:province":"Oost-Vlaanderen",
    "wof:name":"Wattez & Co",
    "wof:placetype":"venue"
},
  "geometry": {"coordinates":[3.6871650219,50.8884658813],"type":"Point"}
}