{
  "type": "Feature",
  "properties": {
    "addr:full":"Winterstraat 32b4 Bilzen Limburg 3740",
    "addr:housenumber":"32b4",
    "addr:postcode":"3740",
    "addr:street":"Winterstraat",
    "iso:country":"BE",
    "sg:address":"Winterstraat 32b4",
    "sg:city":"Bilzen",
    "sg:orig_category":"Boomkwekerijen Drogisterijen Groententeelt",
    "sg:phone":"+32 89 41 84 37",
    "sg:postcode":"3740",
    "sg:province":"Limburg",
    "wof:name":"Greta Lathouwers",
    "wof:placetype":"venue"
},
  "geometry": {"coordinates":[5.5175480843,50.8756103516],"type":"Point"}
}