{
  "type": "Feature",
  "properties": {
    "iso:country":"BE",
    "sg:address":"Brugsesteenweg 90",
    "sg:city":"Roeselare",
    "sg:orig_category":"Cliniques and h\u00f4pitaux. Ambulances",
    "sg:phone":"+32 51 23 61 11",
    "sg:postcode":"8800",
    "sg:province":"West-Vlaanderen",
    "wof:name":"Stedelijk Ziekenhuis",
    "wof:placetype":"venue"
},
  "geometry": {"coordinates":[3.1221129894,50.9538230896],"type":"Point"}
}