{
  "type": "Feature",
  "properties": {
    "iso:country":"BE",
    "sg:address":"Naamsestraat 46",
    "sg:city":"Leuven",
    "sg:classifiers":[
        {
            "category":"Cafe",
            "type":"Food & Drink"
        }
    ],
    "sg:phone":"+32 16 22 26 00",
    "sg:postcode":"3000",
    "sg:province":"Vlaams-Brabant",
    "sg:tags":[
        "caf\u00e9s"
    ],
    "wof:name":"'t Plectrum",
    "wof:placetype":"venue"
},
  "geometry": {"coordinates":[4.7001180649,50.868473053],"type":"Point"}
}