{
  "type": "Feature",
  "properties": {
    "addr:full":"Ingelmunstersestraat 12 Izegem West-Vlaanderen 8870",
    "addr:housenumber":"12",
    "addr:postcode":"8870",
    "addr:street":"Ingelmunstersestraat",
    "iso:country":"BE",
    "sg:address":"Ingelmunstersestraat 12",
    "sg:city":"Izegem",
    "sg:orig_category":"Pain, p\u00e2tisseries and confiseries",
    "sg:phone":"+32 51 30 16 88",
    "sg:postcode":"8870",
    "sg:province":"West-Vlaanderen",
    "wof:name":"Arnold Pauwelyn",
    "wof:placetype":"venue"
},
  "geometry": {"coordinates":[3.2318310738,50.9235153198],"type":"Point"}
}