{
  "type": "Feature",
  "properties": {
    "addr:full":"Feltzstrasse 19 Sankt Vith/saint-vith Li\u00e8ge 4780",
    "addr:housenumber":"19",
    "addr:postcode":"4780",
    "addr:street":"Feltzstrasse",
    "iso:country":"BE",
    "sg:address":"Feltzstrasse 19",
    "sg:city":"Sankt Vith/saint-vith",
    "sg:orig_category":"Boekhouders",
    "sg:postcode":"4780",
    "sg:province":"Li\u00e8ge",
    "wof:name":"Norbert Dusseldorf",
    "wof:placetype":"venue"
},
  "geometry": {"coordinates":[6.0429549217,50.3349761963],"type":"Point"}
}