{
  "type": "Feature",
  "properties": {
    "iso:country":"BE",
    "sg:address":"Everbergstraat 34",
    "sg:city":"Kortenberg",
    "sg:classifiers":[
        {
            "category":"Wholesale",
            "subcategory":"Meat",
            "type":"Manufacturing & Wholesale Goods"
        }
    ],
    "sg:phone":"+32 2 759 26 19",
    "sg:postcode":"3070",
    "sg:province":"Vlaams-Brabant",
    "sg:tags":[
        "machine",
        "product",
        "-",
        "supply"
    ],
    "wof:name":"Voet",
    "wof:placetype":"venue"
},
  "geometry": {"coordinates":[4.5531249046,50.8938140869],"type":"Point"}
}