{
  "type": "Feature",
  "properties": {
    "addr:full":"Heldenlaan 17 Zottegem Oost-Vlaanderen 9620",
    "addr:housenumber":"17",
    "addr:postcode":"9620",
    "addr:street":"Heldenlaan",
    "iso:country":"BE",
    "sg:address":"Heldenlaan 17",
    "sg:city":"Zottegem",
    "sg:classifiers":[
        {
            "category":"Bars & Pubs",
            "type":"Food & Drink"
        }
    ],
    "sg:phone":"+32 9 360 87 00",
    "sg:postcode":"9620",
    "sg:province":"Oost-Vlaanderen",
    "sg:tags":[
        "tavern"
    ],
    "wof:name":"Scotch Inn",
    "wof:placetype":"venue"
},
  "geometry": {"coordinates":[3.8104000092,50.8709030151],"type":"Point"}
}