{
  "type": "Feature",
  "properties": {
    "addr:full":"Hoogstraat 1-3 Beringen Limburg 3580",
    "addr:housenumber":"1-3",
    "addr:postcode":"3580",
    "addr:street":"Hoogstraat",
    "iso:country":"BE",
    "sg:address":"Hoogstraat 1-3",
    "sg:city":"Beringen",
    "sg:classifiers":[
        {
            "category":"Shopping",
            "subcategory":"Shoes",
            "type":"Retail Goods"
        }
    ],
    "sg:phone":"+32 11 45 50 57",
    "sg:postcode":"3580",
    "sg:province":"Limburg",
    "sg:tags":[
        "slipper",
        "-"
    ],
    "wof:name":"Stiff-style",
    "wof:placetype":"venue"
},
  "geometry": {"coordinates":[5.2239232063,51.048248291],"type":"Point"}
}