{
  "type": "Feature",
  "properties": {
    "addr:full":"Avenue Moli\u00e8re 119 Bruxelles (forest) Bruxelles-Capitale 1190",
    "addr:housenumber":"119",
    "addr:postcode":"1190",
    "addr:street":"Avenue Molie\u0300Re",
    "iso:country":"BE",
    "sg:address":"Avenue Moli\u00e8re 119",
    "sg:city":"Bruxelles (forest)",
    "sg:classifiers":[
        {
            "category":"Social Services",
            "subcategory":"Job Training",
            "type":"Services"
        }
    ],
    "sg:phone":"+32 2 346 44 64",
    "sg:postcode":"1190",
    "sg:province":"Bruxelles-Capitale",
    "sg:tags":[
        "personnel",
        "-selection",
        "recruitment"
    ],
    "wof:name":"Secretary Plus Management Support",
    "wof:placetype":"venue"
},
  "geometry": {"coordinates":[4.3454089165,50.8160820007],"type":"Point"}
}