{
  "type": "Feature",
  "properties": {
    "addr:full":"Molenbergstraat 16 Scherpenheuvel-zichem (testelt) Vlaams-Brabant 3272",
    "addr:housenumber":"16",
    "addr:postcode":"3272",
    "addr:street":"Molenbergstraat",
    "iso:country":"BE",
    "sg:address":"Molenbergstraat 16",
    "sg:city":"Scherpenheuvel-zichem (testelt)",
    "sg:classifiers":[
        {
            "category":"Health Services",
            "subcategory":"Doctor",
            "type":"Services"
        }
    ],
    "sg:phone":"+32 13 77 53 36",
    "sg:postcode":"3272",
    "sg:province":"Vlaams-Brabant",
    "sg:tags":[
        "medicinephysicians",
        "surgeon"
    ],
    "wof:name":"Geys Walter",
    "wof:placetype":"venue"
},
  "geometry": {"coordinates":[4.9496150017,51.0220832825],"type":"Point"}
}