{
  "type": "Feature",
  "properties": {
    "addr:full":"Hilaire Depraeterestraat 3 Ingelmunster West-Vlaanderen 8770",
    "addr:housenumber":"3",
    "addr:postcode":"8770",
    "addr:street":"Depraeterestraat",
    "iso:country":"BE",
    "sg:address":"Hilaire Depraeterestraat 3",
    "sg:city":"Ingelmunster",
    "sg:classifiers":[
        {
            "category":"Personal",
            "subcategory":"Nail Salon",
            "type":"Services"
        }
    ],
    "sg:phone":"+32 51 31 39 27",
    "sg:postcode":"8770",
    "sg:province":"West-Vlaanderen",
    "sg:tags":[
        "pedicure"
    ],
    "wof:name":"Demeulenaere K",
    "wof:placetype":"venue"
},
  "geometry": {"coordinates":[3.2416501045,50.9274711609],"type":"Point"}
}