{
  "type": "Feature",
  "properties": {
    "iso:country":"BE",
    "sg:address":"Rechtestraat 31",
    "sg:city":"Lier",
    "sg:classifiers":[
        {
            "category":"Building & Trades",
            "subcategory":"Cleaning & Sanitation",
            "type":"Services"
        }
    ],
    "sg:phone":"+32 3 480 95 97",
    "sg:postcode":"2500",
    "sg:province":"Antwerpen",
    "sg:tags":[
        "fa\u00e7ade",
        "maintenance"
    ],
    "wof:name":"Stef's Gevel Cleaning Bvba",
    "wof:placetype":"venue"
},
  "geometry": {"coordinates":[4.5730171204,51.1302871704],"type":"Point"}
}