{
  "type": "Feature",
  "properties": {
    "iso:country":"BE",
    "sg:address":"Place Palais De Justice 5",
    "sg:city":"Namur",
    "sg:orig_category":"Tribunaux",
    "sg:phone":"+32 81 25 18 47",
    "sg:postcode":"5000",
    "sg:province":"Namur",
    "wof:name":"Tribunal Du Travail",
    "wof:placetype":"venue"
},
  "geometry": {"coordinates":[4.8594150543,50.4652709961],"type":"Point"}
}