{
  "type": "Feature",
  "properties": {
    "iso:country":"BE",
    "sg:address":"A.reyerslaan 52 Kamer 2n 11-12",
    "sg:city":"Schaerbeek",
    "sg:orig_category":"Randstad",
    "sg:phone":"+32 2 741 58 40",
    "sg:postcode":"1030",
    "sg:province":"Bruxelles-Capitale",
    "wof:name":"Randstad",
    "wof:placetype":"venue"
},
  "geometry": {"coordinates":[4.3749351501,50.8680000305],"type":"Point"}
}