{
  "type": "Feature",
  "properties": {
    "addr:full":"Stationsstraat 8 Eernegem 8250",
    "addr:housenumber":"8",
    "addr:postcode":"8250",
    "addr:street":"Stationsstraat",
    "iso:country":"BE",
    "sg:address":"Stationsstraat 8",
    "sg:city":"Eernegem",
    "sg:classifiers":[
        {
            "category":"Banks & Credit Unions",
            "subcategory":"Bank",
            "type":"Services"
        }
    ],
    "sg:phone":"+32 59 29 03 29",
    "sg:postcode":"8250",
    "wof:name":"Aslk-cger Bank",
    "wof:placetype":"venue"
},
  "geometry": {"coordinates":[172.64245605470001,-43.3614006042],"type":"Point"}
}