{
  "type": "Feature",
  "properties": {
    "iso:country":"BE",
    "sg:address":"Leegheid 16",
    "sg:city":"Mechelen",
    "sg:classifiers":[
        {
            "category":"Health Services",
            "subcategory":"Health Practitioner",
            "type":"Services"
        }
    ],
    "sg:phone":"+32 15 27 36 52",
    "sg:postcode":"2800",
    "sg:province":"Antwerpen",
    "sg:tags":[
        "physiotherapist"
    ],
    "wof:name":"Berg\u00e9 W",
    "wof:placetype":"venue"
},
  "geometry": {"coordinates":[4.4844741821,51.0279655457],"type":"Point"}
}