{
  "type": "Feature",
  "properties": {
    "addr:full":"Rue De Tournai 12 Pecq Hainaut 7740",
    "addr:housenumber":"12",
    "addr:postcode":"7740",
    "addr:street":"Rue De Tournai",
    "iso:country":"BE",
    "sg:address":"Rue De Tournai 12",
    "sg:city":"Pecq",
    "sg:orig_category":"Slagers",
    "sg:phone":"+32 69 55 62 48",
    "sg:postcode":"7740",
    "sg:province":"Hainaut",
    "wof:name":"Boucherie Nuttens",
    "wof:placetype":"venue"
},
  "geometry": {"coordinates":[3.3389120102,50.6848754883],"type":"Point"}
}