{
  "type": "Feature",
  "properties": {
    "addr:full":"Paul De Smet De Naeyerstraat 19 Middelkerke West-Vlaanderen 8430",
    "addr:housenumber":"19",
    "addr:postcode":"8430",
    "addr:street":"Paul De Smet De Naeyerstraat",
    "iso:country":"BE",
    "sg:address":"Paul De Smet De Naeyerstraat 19",
    "sg:city":"Middelkerke",
    "sg:classifiers":[
        {
            "category":"Travel",
            "subcategory":"Hotels & Motels",
            "type":"Entertainment"
        }
    ],
    "sg:phone":"+32 59 30 11 88",
    "sg:postcode":"8430",
    "sg:province":"West-Vlaanderen",
    "wof:name":"Were Di",
    "wof:placetype":"venue"
},
  "geometry": {"coordinates":[2.8176510334,51.1883468628],"type":"Point"}
}