{
  "type": "Feature",
  "properties": {
    "iso:country":"BE",
    "sg:address":"Wiekevorstseweg 26",
    "sg:city":"Herentals (morkhoven)",
    "sg:classifiers":[
        {
            "category":"Real Estate",
            "subcategory":"Surveying",
            "type":"Services"
        }
    ],
    "sg:phone":"+32 14 26 10 68",
    "sg:postcode":"2200",
    "sg:province":"Antwerpen",
    "sg:tags":[
        "surveyor",
        "land"
    ],
    "wof:name":"Bouwen F",
    "wof:placetype":"venue"
},
  "geometry": {"coordinates":[4.8150281906,51.1173019409],"type":"Point"}
}