{
  "type": "Feature",
  "properties": {
    "addr:full":"Rue D\u00b4oignies 111b1 Aiseau-presles Hainaut 6250",
    "addr:housenumber":"111b1",
    "addr:postcode":"6250",
    "addr:street":"Rue D\u00b4Oignies;Hainaut",
    "iso:country":"BE",
    "sg:address":"Rue D\u00b4oignies 111b1",
    "sg:city":"Aiseau-presles",
    "sg:orig_category":"Herstellingen and onderhoud van auto's",
    "sg:phone":"+32 71 77 22 40",
    "sg:postcode":"6250",
    "sg:province":"Hainaut",
    "wof:name":"Car D\u00b4oignies",
    "wof:placetype":"venue"
},
  "geometry": {"coordinates":[4.606554985,50.4259185791],"type":"Point"}
}