{
  "type": "Feature",
  "properties": {
    "addr:full":"Antwerpsesteenweg 356 Malle (westmalle) Antwerpen 2390",
    "addr:housenumber":"356",
    "addr:postcode":"2390",
    "addr:street":"Antwerpsesteenweg",
    "iso:country":"BE",
    "sg:address":"Antwerpsesteenweg 356",
    "sg:city":"Malle (westmalle)",
    "sg:classifiers":[
        {
            "category":"Manufacturing",
            "subcategory":"Printing",
            "type":"Manufacturing & Wholesale Goods"
        }
    ],
    "sg:phone":"+32 3 312 51 78",
    "sg:postcode":"2390",
    "sg:province":"Antwerpen",
    "sg:tags":[
        "textile",
        "-"
    ],
    "wof:name":"J-p Shirt Printing",
    "wof:placetype":"venue"
},
  "geometry": {"coordinates":[4.683016777,51.2960205078],"type":"Point"}
}