{
  "type": "Feature",
  "properties": {
    "addr:full":"Gasthuisstraat 33bb Geel Antwerpen 2440",
    "addr:housenumber":"33bb",
    "addr:postcode":"2440",
    "addr:street":"Gasthuisstraat",
    "iso:country":"BE",
    "sg:address":"Gasthuisstraat 33bb",
    "sg:city":"Geel",
    "sg:orig_category":"Artsen and specialisten",
    "sg:phone":"+32 14 59 14 64",
    "sg:postcode":"2440",
    "sg:province":"Antwerpen",
    "wof:name":"R. Colon",
    "wof:placetype":"venue"
},
  "geometry": {"coordinates":[4.9972019196,51.1601715088],"type":"Point"}
}