{
  "type": "Feature",
  "properties": {
    "addr:full":"Rue J. Kurtz 9 Verviers (stembert) Li\u00e8ge 4801",
    "addr:housenumber":"9",
    "addr:postcode":"4801",
    "addr:street":"Rue J. Kurtz",
    "iso:country":"BE",
    "sg:address":"Rue J. Kurtz 9",
    "sg:city":"Verviers (stembert)",
    "sg:classifiers":[
        {
            "category":"Education",
            "subcategory":"School",
            "type":"Public Place"
        }
    ],
    "sg:phone":"+32 87 22 91 39",
    "sg:postcode":"4801",
    "sg:province":"Li\u00e8ge",
    "sg:tags":[
        "primary"
    ],
    "wof:name":"Athenee Royal Verdi",
    "wof:placetype":"venue"
},
  "geometry": {"coordinates":[5.8930549622,50.5922393799],"type":"Point"}
}