{
  "type": "Feature",
  "properties": {
    "addr:full":"Chauss\u00c9e De Wavre 1281 Oudergem/auderghem Bruxelles-Capitale 1160",
    "addr:postcode":"1281;1160",
    "addr:street":"Chausse\u0301E De Wavre",
    "iso:country":"BE",
    "sg:address":"Chauss\u00c9e De Wavre 1281",
    "sg:city":"Oudergem/auderghem",
    "sg:orig_category":"Pain, p\u00e2tisseries and confiseries",
    "sg:phone":"+32 2 660 73 61",
    "sg:postcode":"1160",
    "sg:province":"Bruxelles-Capitale",
    "wof:name":"Georges Debacker",
    "wof:placetype":"venue"
},
  "geometry": {"coordinates":[4.4076991081,50.8210067749],"type":"Point"}
}