{
  "type": "Feature",
  "properties": {
    "iso:country":"BE",
    "sg:address":"Weidestraat 23",
    "sg:city":"Hasselt",
    "sg:orig_category":"Charpentes and couvertures. Plomberie, chauffage and installations sanitaires. Services de Nettoyage",
    "sg:phone":"+32 11 22 78 20",
    "sg:postcode":"3511",
    "sg:province":"Limburg",
    "wof:name":"Heeren Roger",
    "wof:placetype":"venue"
},
  "geometry": {"coordinates":[5.3343038559,50.9493522644],"type":"Point"}
}