{
  "type": "Feature",
  "properties": {
    "addr:full":"Kleine Heidestraat 6 Zottegem (leeuwergem) Oost-Vlaanderen 9620",
    "addr:housenumber":"6",
    "addr:postcode":"9620",
    "addr:street":"Kleine Heidestraat",
    "iso:country":"BE",
    "sg:address":"Kleine Heidestraat 6",
    "sg:city":"Zottegem (leeuwergem)",
    "sg:classifiers":[
        {
            "category":"Building & Trades",
            "subcategory":"Construction",
            "type":"Services"
        }
    ],
    "sg:phone":"+32 9 360 22 30",
    "sg:postcode":"9620",
    "sg:province":"Oost-Vlaanderen",
    "sg:tags":[
        "installation",
        "-",
        "central",
        "heating"
    ],
    "wof:name":"Vermassen Wilfried",
    "wof:placetype":"venue"
},
  "geometry": {"coordinates":[3.8134069443,50.8680229187],"type":"Point"}
}