{
  "type": "Feature",
  "properties": {
    "iso:country":"BE",
    "sg:address":"Chauss\u00e9e De Gand 366",
    "sg:city":"Bruxelles (molenbeek-saint-jean)",
    "sg:classifiers":[
        {
            "category":"Shopping",
            "subcategory":"Antiques",
            "type":"Retail Goods"
        }
    ],
    "sg:phone":"+32 2 512 28 03",
    "sg:postcode":"1080",
    "sg:province":"Bruxelles-Capitale",
    "sg:tags":[
        "restoration"
    ],
    "wof:name":"No\u00ebl Daniel",
    "wof:placetype":"venue"
},
  "geometry": {"coordinates":[4.3207421303,50.8574028015],"type":"Point"}
}