{
  "type": "Feature",
  "properties": {
    "addr:full":"Chemin Du Rossignol 50 Bruxelles Bruxelles-Capitale 1120",
    "addr:housenumber":"50",
    "addr:postcode":"1120",
    "addr:street":"Chemin Du Rossignol",
    "iso:country":"BE",
    "sg:address":"Chemin Du Rossignol 50",
    "sg:city":"Bruxelles",
    "sg:classifiers":[
        {
            "category":"Education",
            "subcategory":"Vocational School",
            "type":"Public Place"
        }
    ],
    "sg:phone":"+32 2 269 91 11",
    "sg:postcode":"1120",
    "sg:province":"Bruxelles-Capitale",
    "sg:tags":[
        "teaching",
        "material"
    ],
    "wof:name":"Eklyps Sc",
    "wof:placetype":"venue"
},
  "geometry": {"coordinates":[4.3852128983,50.8963317871],"type":"Point"}
}