{
  "type": "Feature",
  "properties": {
    "addr:full":"Schoonaerde 26 Diest Vlaams-Brabant 3290",
    "addr:housenumber":"26",
    "addr:postcode":"3290",
    "addr:street":"Schoonaerde",
    "iso:country":"BE",
    "sg:address":"Schoonaerde 26",
    "sg:city":"Diest",
    "sg:classifiers":[
        {
            "category":"Retail",
            "subcategory":"Repair Shop",
            "type":"Services"
        }
    ],
    "sg:phone":"+32 13 31 26 88",
    "sg:postcode":"3290",
    "sg:province":"Vlaams-Brabant",
    "sg:tags":[
        "-",
        "clothing",
        "alteration"
    ],
    "wof:name":"Retoucheshop Knip Knap",
    "wof:placetype":"venue"
},
  "geometry": {"coordinates":[5.069234848,50.9947814941],"type":"Point"}
}