{
  "type": "Feature",
  "properties": {
    "addr:full":"Bosstraat 22 Mechelen Antwerpen 2811",
    "addr:housenumber":"22",
    "addr:postcode":"2811",
    "addr:street":"Bosstraat",
    "iso:country":"BE",
    "sg:address":"Bosstraat 22",
    "sg:city":"Mechelen",
    "sg:orig_category":"Rundveehouders",
    "sg:phone":"+32 15 61 19 15",
    "sg:postcode":"2811",
    "sg:province":"Antwerpen",
    "wof:name":"Marc Truyen",
    "wof:placetype":"venue"
},
  "geometry": {"coordinates":[4.3962950706,51.0056381226],"type":"Point"}
}