{
  "type": "Feature",
  "properties": {
    "iso:country":"BE",
    "sg:address":"Meerweg",
    "sg:city":"Ruisbroek",
    "sg:orig_category":"Aardappelproducten Gh Bloemen and planten Geschenken and souvenirs Groenten and fruit Gh Huisdieren ",
    "sg:phone":"+32 2 377 60 81",
    "sg:postcode":"1601",
    "sg:province":"Vlaams-Brabant",
    "wof:name":"Van Cutsem",
    "wof:placetype":"venue"
},
  "geometry": {"coordinates":[4.286465168,50.784828186],"type":"Point"}
}