{
  "type": "Feature",
  "properties": {
    "iso:country":"BE",
    "sg:address":"Rue Saint-joseph 9",
    "sg:city":"Assesse (crupet)",
    "sg:classifiers":[
        {
            "category":"Manufacturing",
            "subcategory":"Leather Goods",
            "type":"Manufacturing & Wholesale Goods"
        }
    ],
    "sg:phone":"+32 83 69 96 82",
    "sg:postcode":"5332",
    "sg:province":"Namur",
    "sg:tags":[
        "repair",
        "buckskin",
        "-",
        "fur",
        "cleaning"
    ],
    "wof:name":"Repar-cuir",
    "wof:placetype":"venue"
},
  "geometry": {"coordinates":[4.9643740654,50.349609375],"type":"Point"}
}