{
  "type": "Feature",
  "properties": {
    "addr:full":"De Ring 5 Hamme Oost-Vlaanderen 9220",
    "addr:housenumber":"5",
    "addr:postcode":"9220",
    "addr:street":"De Ring",
    "iso:country":"BE",
    "sg:address":"De Ring 5",
    "sg:city":"Hamme",
    "sg:orig_category":"Artsen and specialisten",
    "sg:phone":"+32 52 47 08 77",
    "sg:postcode":"9220",
    "sg:province":"Oost-Vlaanderen",
    "wof:name":"L. Duinslaeger",
    "wof:placetype":"venue"
},
  "geometry": {"coordinates":[4.1354570389,51.096206665],"type":"Point"}
}