{
  "type": "Feature",
  "properties": {
    "iso:country":"BE",
    "sg:address":"Place Du Mill\u00c9naire",
    "sg:city":"Zinnik",
    "sg:orig_category":"Diverse kredietdiensten",
    "sg:postcode":"7060",
    "sg:province":"Hainaut",
    "wof:name":"Bancontact-mister Cash",
    "wof:placetype":"venue"
},
  "geometry": {"coordinates":[4.0722699165,50.579574585],"type":"Point"}
}