{
  "type": "Feature",
  "properties": {
    "iso:country":"BE",
    "sg:address":"Bagattenstraat 191",
    "sg:city":"Gent",
    "sg:classifiers":[
        {
            "category":"Shopping",
            "subcategory":"Clothing, Apparel, & Fashions",
            "type":"Retail Goods"
        }
    ],
    "sg:phone":"+32 9 223 19 36",
    "sg:postcode":"9000",
    "sg:province":"Oost-Vlaanderen",
    "sg:tags":[
        "v\u00eatements",
        "pour",
        "dame"
    ],
    "wof:name":"Huis La Luna",
    "wof:placetype":"venue"
},
  "geometry": {"coordinates":[3.726913929,51.0477752686],"type":"Point"}
}