{
  "type": "Feature",
  "properties": {
    "addr:full":"Rue Du Hameau 187 Rhode-saint-gen\u00e8se Vlaams-Brabant 1640",
    "addr:housenumber":"187",
    "addr:postcode":"1640",
    "addr:street":"Rue Du Hameau",
    "iso:country":"BE",
    "sg:address":"Rue Du Hameau 187",
    "sg:city":"Rhode-saint-gen\u00e8se",
    "sg:classifiers":[
        {
            "category":"Personal",
            "subcategory":"Beauty Salon",
            "type":"Services"
        }
    ],
    "sg:phone":"+32 486 76 79 07",
    "sg:postcode":"1640",
    "sg:province":"Vlaams-Brabant",
    "wof:name":"Beauty Relose",
    "wof:placetype":"venue"
},
  "geometry": {"coordinates":[4.3721032143,50.7389945984],"type":"Point"}
}