{
  "type": "Feature",
  "properties": {
    "addr:full":"Eendrachtstraat 5 Houthulst (ronehoek - Nieuwe Stede) West-Vlaanderen 8650",
    "addr:housenumber":"5",
    "addr:postcode":"8650",
    "addr:street":"Eendrachtstraat;Ronehoek Nieuwe Stede",
    "iso:country":"BE",
    "sg:address":"Eendrachtstraat 5",
    "sg:city":"Houthulst (ronehoek - Nieuwe Stede)",
    "sg:classifiers":[
        {
            "category":"Building & Trades",
            "subcategory":"Cleaning & Sanitation",
            "type":"Services"
        }
    ],
    "sg:phone":"+32 475 24 94 31",
    "sg:postcode":"8650",
    "sg:province":"West-Vlaanderen",
    "sg:tags":[
        "janitor"
    ],
    "wof:name":"Twingo",
    "wof:placetype":"venue"
},
  "geometry": {"coordinates":[2.9509439468,50.9778862],"type":"Point"}
}