{
  "type": "Feature",
  "properties": {
    "iso:country":"BE",
    "sg:address":"Beukenootjesstraat 29",
    "sg:city":"Brussel/bruxelles",
    "sg:orig_category":"Benzinestations and brandstoffen",
    "sg:phone":"+32 2 268 53 20",
    "sg:postcode":"1120",
    "sg:province":"Bruxelles-Capitale",
    "wof:name":"Jean Lauwers",
    "wof:placetype":"venue"
},
  "geometry": {"coordinates":[4.3935279846,50.8944282532],"type":"Point"}
}