{
  "type": "Feature",
  "properties": {
    "iso:country":"BE",
    "sg:address":"Kraneveld 13",
    "sg:city":"Oudenaarde",
    "sg:classifiers":[
        {
            "category":"Building & Trades",
            "subcategory":"Construction",
            "type":"Services"
        }
    ],
    "sg:phone":"+32 55 31 74 24",
    "sg:postcode":"9700",
    "sg:province":"Oost-Vlaanderen",
    "sg:tags":[
        "carpenter"
    ],
    "wof:name":"Sion",
    "wof:placetype":"venue"
},
  "geometry": {"coordinates":[3.6100239754,50.8735313416],"type":"Point"}
}