{
  "type": "Feature",
  "properties": {
    "addr:full":"Grote Markt Koning Albert I 14 Ieper West-Vlaanderen 8900",
    "addr:housenumber":"14",
    "addr:postcode":"8900",
    "addr:street":"Grote Markt Koning Albert I",
    "iso:country":"BE",
    "sg:address":"Grote Markt Koning Albert I 14",
    "sg:city":"Ieper",
    "sg:classifiers":[
        {
            "category":"Tea Room",
            "subcategory":"None",
            "type":"Food & Drink"
        }
    ],
    "sg:phone":"+32 57 20 17 60",
    "sg:postcode":"8900",
    "sg:province":"West-Vlaanderen",
    "wof:name":"Central",
    "wof:placetype":"venue"
},
  "geometry": {"coordinates":[2.8878269196,50.8513641357],"type":"Point"}
}