{
  "type": "Feature",
  "properties": {
    "addr:full":"Avenue Des Combattants 107 Ottignies-louvain-la-neuve Brabant Wallon 1340",
    "addr:housenumber":"107",
    "addr:postcode":"1340",
    "addr:street":"Avenue Des Combattants",
    "iso:country":"BE",
    "sg:address":"Avenue Des Combattants 107",
    "sg:city":"Ottignies-louvain-la-neuve",
    "sg:orig_category":"Biens d'occasion",
    "sg:phone":"+32 10 41 23 73",
    "sg:postcode":"1340",
    "sg:province":"Brabant Wallon",
    "wof:name":"La Brique",
    "wof:placetype":"venue"
},
  "geometry": {"coordinates":[4.5689311028,50.6694374084],"type":"Point"}
}