{
  "type": "Feature",
  "properties": {
    "addr:full":"Duinenabdijstraat 6 Brugge West-Vlaanderen 8000",
    "addr:housenumber":"6",
    "addr:postcode":"8000",
    "addr:street":"Duinenabdijstraat",
    "iso:country":"BE",
    "sg:address":"Duinenabdijstraat 6",
    "sg:city":"Brugge",
    "sg:orig_category":"M\u00e9decins and sp\u00e9cialistes",
    "sg:phone":"+32 50 34 19 66",
    "sg:postcode":"8000",
    "sg:province":"West-Vlaanderen",
    "wof:name":"C. Van Nevel",
    "wof:placetype":"venue"
},
  "geometry": {"coordinates":[3.2303740978,51.2172813416],"type":"Point"}
}