{
  "type": "Feature",
  "properties": {
    "addr:full":"Gentsesteenweg 678 Brussel Bruxelles-Capitale 1080",
    "addr:housenumber":"678",
    "addr:postcode":"1080",
    "addr:street":"Gentsesteenweg",
    "iso:country":"BE",
    "sg:address":"Gentsesteenweg 678",
    "sg:city":"Brussel",
    "sg:orig_category":"Non-Classified Establishments",
    "sg:phone":"+32 2 465 25 88",
    "sg:postcode":"1080",
    "sg:province":"Bruxelles-Capitale",
    "wof:name":"Motos Norman Vandenhoute",
    "wof:placetype":"venue"
},
  "geometry": {"coordinates":[4.3390049934,50.8550453186],"type":"Point"}
}