{
  "type": "Feature",
  "properties": {
    "iso:country":"BE",
    "sg:address":"Interleuvenlaan 62a",
    "sg:city":"Leuven (heverlee)",
    "sg:classifiers":[
        {
            "category":"Professional",
            "subcategory":"Computer Services",
            "type":"Services"
        }
    ],
    "sg:phone":"+32 16 39 48 22",
    "sg:postcode":"3001",
    "sg:province":"Vlaams-Brabant",
    "sg:tags":[
        "-",
        "processing",
        "data",
        "software"
    ],
    "wof:name":"Brain +",
    "wof:placetype":"venue"
},
  "geometry": {"coordinates":[4.7360210419,50.849067688],"type":"Point"}
}