{
  "type": "Feature",
  "properties": {
    "addr:full":"Rue Beeckman 117b1/2 Ukkel/uccle Bruxelles-Capitale 1180",
    "addr:housenumber":"117b1 / 2",
    "addr:postcode":"1180",
    "addr:street":"Rue Beeckman;/",
    "iso:country":"BE",
    "sg:address":"Rue Beeckman 117b1/2",
    "sg:city":"Ukkel/uccle",
    "sg:orig_category":"Experts-comptables",
    "sg:phone":"+32 2 376 76 50",
    "sg:postcode":"1180",
    "sg:province":"Bruxelles-Capitale",
    "wof:name":"Paul Lurkin",
    "wof:placetype":"venue"
},
  "geometry": {"coordinates":[4.3344931602,50.8031272888],"type":"Point"}
}