{
  "type": "Feature",
  "properties": {
    "addr:full":"Barri\u00c8re De Fer 40 Spiere-helkijn/espierres-helchin West-Vlaanderen 8587",
    "addr:housenumber":"40;/",
    "addr:postcode":"8587",
    "addr:street":"Barrie\u0300Re;Spiere-Helkijn",
    "iso:country":"BE",
    "sg:address":"Barri\u00c8re De Fer 40",
    "sg:city":"Spiere-helkijn/espierres-helchin",
    "sg:orig_category":"Pharmaciens",
    "sg:phone":"+32 56 45 70 00",
    "sg:postcode":"8587",
    "sg:province":"West-Vlaanderen",
    "wof:name":"Pharmacie Du Roc/du Roc",
    "wof:placetype":"venue"
},
  "geometry": {"coordinates":[3.3311500549,50.7230148315],"type":"Point"}
}