{
  "type": "Feature",
  "properties": {
    "addr:full":"Hoogstraat 56 Boortmeerbeek (hever) Vlaams-Brabant 3191",
    "addr:housenumber":"56",
    "addr:postcode":"3191",
    "addr:street":"Hoogstraat",
    "iso:country":"BE",
    "sg:address":"Hoogstraat 56",
    "sg:city":"Boortmeerbeek (hever)",
    "sg:classifiers":[
        {
            "category":"Professional",
            "subcategory":"Lawyer & Legal Services",
            "type":"Services"
        }
    ],
    "sg:phone":"+32 15 52 08 14",
    "sg:postcode":"3191",
    "sg:province":"Vlaams-Brabant",
    "sg:tags":[
        "notary"
    ],
    "wof:name":"Van Edom C",
    "wof:placetype":"venue"
},
  "geometry": {"coordinates":[4.5514450073,50.995174408],"type":"Point"}
}