{
  "type": "Feature",
  "properties": {
    "iso:country":"BE",
    "sg:address":"Dr\u00e8ve Du Brocard 8",
    "sg:city":"Waterloo",
    "sg:classifiers":[
        {
            "category":"Health Services",
            "subcategory":"Doctor",
            "type":"Services"
        }
    ],
    "sg:phone":"+32 2 354 52 66",
    "sg:postcode":"1410",
    "sg:province":"Brabant Wallon",
    "sg:tags":[
        "medicinephysicians",
        "surgeon"
    ],
    "wof:name":"Bougaenko A",
    "wof:placetype":"venue"
},
  "geometry": {"coordinates":[4.4169549942,50.7090911865],"type":"Point"}
}