{
  "type": "Feature",
  "properties": {
    "addr:full":"Ashoop 12 Lo-reninge West-Vlaanderen 8647",
    "addr:housenumber":"12",
    "addr:postcode":"8647",
    "addr:street":"Ashoop",
    "iso:country":"BE",
    "sg:address":"Ashoop 12",
    "sg:city":"Lo-reninge",
    "sg:orig_category":"Chaussures",
    "sg:phone":"+32 58 28 89 01",
    "sg:postcode":"8647",
    "sg:province":"West-Vlaanderen",
    "wof:name":"Huis Vivace",
    "wof:placetype":"venue"
},
  "geometry": {"coordinates":[2.7670459747,51.0002746582],"type":"Point"}
}