{
  "type": "Feature",
  "properties": {
    "addr:full":"Lindendreef 8 Wemmel Vlaams-Brabant 1780",
    "addr:housenumber":"8",
    "addr:postcode":"1780",
    "addr:street":"Lindendreef;Vlaams-Brabant",
    "iso:country":"BE",
    "sg:address":"Lindendreef 8",
    "sg:city":"Wemmel",
    "sg:classifiers":[
        {
            "category":"Professional",
            "subcategory":"Business Services",
            "type":"Services"
        }
    ],
    "sg:phone":"+32 2 460 40 94",
    "sg:postcode":"1780",
    "sg:province":"Vlaams-Brabant",
    "sg:tags":[
        "agency",
        "export"
    ],
    "wof:name":"Sodexim Sino - Belgian Trade Nv",
    "wof:placetype":"venue"
},
  "geometry": {"coordinates":[4.3147821426,50.9175643921],"type":"Point"}
}