{
  "type": "Feature",
  "properties": {
    "iso:country":"BE",
    "sg:address":"Vijfstraten 113",
    "sg:city":"Sint-niklaas",
    "sg:orig_category":"Immobili\u00ebnkantoren",
    "sg:phone":"+32 3 766 82 42",
    "sg:postcode":"9100",
    "sg:province":"Oost-Vlaanderen",
    "wof:name":"Immo De Laet",
    "wof:placetype":"venue"
},
  "geometry": {"coordinates":[4.1528348923,51.1766967773],"type":"Point"}
}