{
  "type": "Feature",
  "properties": {
    "iso:country":"BE",
    "sg:address":"Kortrijkstraat 99",
    "sg:city":"Tielt",
    "sg:orig_category":"V\u00eatements pour Dames. V\u00eatements. V\u00eatements de mariage and c\u00e9r\u00e9monies",
    "sg:phone":"+32 51 40 00 20",
    "sg:postcode":"8700",
    "sg:province":"West-Vlaanderen",
    "wof:name":"Cr\u00c9ations Jacques D'orly",
    "wof:placetype":"venue"
},
  "geometry": {"coordinates":[3.3256950378,50.9960861206],"type":"Point"}
}