{
  "type": "Feature",
  "properties": {
    "iso:country":"BE",
    "sg:address":"Elsenhoutstraat 24",
    "sg:city":"Genk (waterschei)",
    "sg:classifiers":[
        {
            "category":"Health Services",
            "subcategory":"Doctor",
            "type":"Services"
        }
    ],
    "sg:phone":"+32 89 84 33 25",
    "sg:postcode":"3600",
    "sg:province":"Limburg",
    "sg:tags":[
        "medicinephysicians",
        "surgeon"
    ],
    "wof:name":"Goethuys Hans",
    "wof:placetype":"venue"
},
  "geometry": {"coordinates":[5.5215511322,50.9930381775],"type":"Point"}
}