{
  "type": "Feature",
  "properties": {
    "addr:full":"Stationstraat 38 Ternat Vlaams-Brabant 1740",
    "addr:housenumber":"38",
    "addr:postcode":"1740",
    "addr:street":"Stationstraat",
    "iso:country":"BE",
    "sg:address":"Stationstraat 38",
    "sg:city":"Ternat",
    "sg:classifiers":[
        {
            "category":"Professional",
            "subcategory":"Lawyer & Legal Services",
            "type":"Services"
        }
    ],
    "sg:phone":"+32 2 532 16 18",
    "sg:postcode":"1740",
    "sg:province":"Vlaams-Brabant",
    "wof:name":"Vandam Axel",
    "wof:placetype":"venue"
},
  "geometry": {"coordinates":[4.1747279167,50.8705825806],"type":"Point"}
}