{
  "type": "Feature",
  "properties": {
    "iso:country":"BE",
    "sg:address":"Paddenhoek 36",
    "sg:city":"Herzele",
    "sg:orig_category":"Eleveurs de bovins",
    "sg:phone":"+32 53 62 42 61",
    "sg:postcode":"9551",
    "sg:province":"Oost-Vlaanderen",
    "wof:name":"Albert Van Liedekerke",
    "wof:placetype":"venue"
},
  "geometry": {"coordinates":[3.9166009426,50.8923377991],"type":"Point"}
}