{
  "type": "Feature",
  "properties": {
    "addr:full":"Peltanusstraat 25 Overpelt Limburg 3900",
    "addr:housenumber":"25",
    "addr:postcode":"3900",
    "addr:street":"Peltanusstraat",
    "iso:country":"BE",
    "sg:address":"Peltanusstraat 25",
    "sg:city":"Overpelt",
    "sg:orig_category":"Blanchisseries and teintureries",
    "sg:phone":"+32 11 64 12 97",
    "sg:postcode":"3900",
    "sg:province":"Limburg",
    "wof:name":"Wasserij De Lente",
    "wof:placetype":"venue"
},
  "geometry": {"coordinates":[5.4236102104,51.2092399597],"type":"Point"}
}