{
  "type": "Feature",
  "properties": {
    "iso:country":"BE",
    "sg:address":"Vierhuizen 1d",
    "sg:city":"Olen",
    "sg:orig_category":"Dakwerken Loodgieterij, verwarming and sanitaire installaties Verhuur bouwmachines",
    "sg:phone":"+32 14 21 67 81",
    "sg:postcode":"2250",
    "sg:province":"Antwerpen",
    "wof:name":"Slaets Marc",
    "wof:placetype":"venue"
},
  "geometry": {"coordinates":[4.888988018,51.1651268005],"type":"Point"}
}