{
  "type": "Feature",
  "properties": {
    "iso:country":"BE",
    "sg:address":"Avenue Des Thermes 42",
    "sg:city":"Chaudfontaine",
    "sg:orig_category":"Artsen and specialisten",
    "sg:phone":"+32 4 365 10 17",
    "sg:postcode":"4050",
    "sg:province":"Li\u00e8ge",
    "wof:name":"Jules-luc Detroux",
    "wof:placetype":"venue"
},
  "geometry": {"coordinates":[5.6384620667,50.5865440369],"type":"Point"}
}