{
  "type": "Feature",
  "properties": {
    "addr:full":"Rue Sur L'ile 7 Beyne-heusay Li\u00e8ge 4610",
    "addr:housenumber":"7",
    "addr:postcode":"4610",
    "addr:street":"Rue Sur L'Ile",
    "iso:country":"BE",
    "sg:address":"Rue Sur L'ile 7",
    "sg:city":"Beyne-heusay",
    "sg:orig_category":"G\u00e9om\u00e8tres",
    "sg:phone":"+32 4 367 05 72",
    "sg:postcode":"4610",
    "sg:province":"Li\u00e8ge",
    "wof:name":"Christian Thonus",
    "wof:placetype":"venue"
},
  "geometry": {"coordinates":[5.6407542229,50.625831604],"type":"Point"}
}