{
  "type": "Feature",
  "properties": {
    "addr:full":"Rue Des Forges 64 Dinant Namur 5500",
    "addr:housenumber":"64",
    "addr:postcode":"5500",
    "addr:street":"Rue Des Forges",
    "iso:country":"BE",
    "sg:address":"Rue Des Forges 64",
    "sg:city":"Dinant",
    "sg:orig_category":"Installation de menuiserie m\u00e9tallique. R\u00e9paration and restauration de meubles. Peinture. Rev\u00eatements",
    "sg:phone":"+32 82 22 72 41",
    "sg:postcode":"5500",
    "sg:province":"Namur",
    "wof:name":"Multi-services",
    "wof:placetype":"venue"
},
  "geometry": {"coordinates":[4.9010829926,50.232875824],"type":"Point"}
}