{
  "type": "Feature",
  "properties": {
    "iso:country":"BE",
    "sg:address":"Vinkenlaan 9",
    "sg:city":"Sint-genesius-rode/rhode-saint-gen\u00c8se",
    "sg:orig_category":"Public-relationsbureaus",
    "sg:phone":"+32 2 381 21 82",
    "sg:postcode":"1640",
    "sg:province":"Vlaams-Brabant",
    "wof:name":"J.j. Durr\u00c9",
    "wof:placetype":"venue"
},
  "geometry": {"coordinates":[4.3585357666,50.7374534607],"type":"Point"}
}