{
  "type": "Feature",
  "properties": {
    "iso:country":"BE",
    "sg:address":"Berendrechtsvoetpad 17b1",
    "sg:city":"Antwerpen",
    "sg:orig_category":"Gespecialiseerde residenti\u00eble bouw Plaatsen van vloer- and muurbekleding",
    "sg:phone":"+32 3 568 76 66",
    "sg:postcode":"2040",
    "sg:province":"Antwerpen",
    "wof:name":"De Langh",
    "wof:placetype":"venue"
},
  "geometry": {"coordinates":[4.3137898445,51.355091095],"type":"Point"}
}