{
  "type": "Feature",
  "properties": {
    "addr:full":"Rue De Dinant 8 Nandrin (groot) Li\u00e8ge 4550",
    "addr:housenumber":"8",
    "addr:postcode":"4550",
    "addr:street":"Rue De Dinant;Groot Lie\u0300Ge",
    "iso:country":"BE",
    "sg:address":"Rue De Dinant 8",
    "sg:city":"Nandrin (groot)",
    "sg:orig_category":"Medische and orthopedische apparaten",
    "sg:phone":"+32 485 86 53 92",
    "sg:postcode":"4550",
    "sg:province":"Li\u00e8ge",
    "wof:name":"Famedic",
    "wof:placetype":"venue"
},
  "geometry": {"coordinates":[5.3954467773,50.5062141418],"type":"Point"}
}