{
  "type": "Feature",
  "properties": {
    "addr:full":"Wilfordkaai 41 Temse Oost-Vlaanderen 9140",
    "addr:housenumber":"41",
    "addr:postcode":"9140",
    "addr:street":"Wilfordkaai",
    "iso:country":"BE",
    "sg:address":"Wilfordkaai 41",
    "sg:city":"Temse",
    "sg:orig_category":"Transports routiers de marchandises",
    "sg:phone":"+32 3 771 38 01",
    "sg:postcode":"9140",
    "sg:province":"Oost-Vlaanderen",
    "wof:name":"Vervoer Lambin",
    "wof:placetype":"venue"
},
  "geometry": {"coordinates":[4.2177348137,51.1233406067],"type":"Point"}
}