{
  "type": "Feature",
  "properties": {
    "addr:full":"Centrumlaan 38 Ninove Oost-Vlaanderen 9400",
    "addr:housenumber":"38",
    "addr:postcode":"9400",
    "addr:street":"Centrumlaan",
    "iso:country":"BE",
    "sg:address":"Centrumlaan 38",
    "sg:city":"Ninove",
    "sg:classifiers":[
        {
            "category":"Shopping",
            "subcategory":"Clothing, Apparel, & Fashions",
            "type":"Retail Goods"
        }
    ],
    "sg:phone":"+32 54 33 13 13",
    "sg:postcode":"9400",
    "sg:province":"Oost-Vlaanderen",
    "sg:tags":[
        "clothing",
        "-",
        "gentleman"
    ],
    "wof:name":"Gijssels Herenmode",
    "wof:placetype":"venue"
},
  "geometry": {"coordinates":[4.0213398933,50.8344306946],"type":"Point"}
}