{
  "type": "Feature",
  "properties": {
    "iso:country":"BE",
    "sg:address":"Olmenstraat 10",
    "sg:city":"Middelkerke (westende)",
    "sg:classifiers":[
        {
            "category":"Shopping",
            "subcategory":"Gifts & Souvenirs",
            "type":"Retail Goods"
        }
    ],
    "sg:phone":"+32 58 23 57 44",
    "sg:postcode":"8434",
    "sg:province":"West-Vlaanderen",
    "sg:tags":[
        "calendar"
    ],
    "wof:name":"Lab Calendars Bvba",
    "wof:placetype":"venue"
},
  "geometry": {"coordinates":[2.7569050789,51.1488685608],"type":"Point"}
}