{
  "type": "Feature",
  "properties": {
    "addr:full":"Monseigneur De Haernelaan 56a Kortrijk West-Vlaanderen 8500",
    "addr:housenumber":"56a",
    "addr:postcode":"8500",
    "addr:street":"Monseigneur De Haernelaan",
    "iso:country":"BE",
    "sg:address":"Monseigneur De Haernelaan 56a",
    "sg:city":"Kortrijk",
    "sg:classifiers":[
        {
            "category":"Health Services",
            "subcategory":"Doctor",
            "type":"Services"
        }
    ],
    "sg:phone":"+32 56 20 52 22",
    "sg:postcode":"8500",
    "sg:province":"West-Vlaanderen",
    "sg:tags":[
        "medicinephysicians",
        "surgeon"
    ],
    "wof:name":"D'haeseleire P",
    "wof:placetype":"venue"
},
  "geometry": {"coordinates":[3.2599790096,50.8211593628],"type":"Point"}
}