{
  "type": "Feature",
  "properties": {
    "addr:full":"Rue Laurent Vandenhoven 51 Bruxelles (evere) Bruxelles-Capitale 1140",
    "addr:housenumber":"51",
    "addr:postcode":"1140",
    "addr:street":"Rue Laurent Vandenhoven",
    "iso:country":"BE",
    "sg:address":"Rue Laurent Vandenhoven 51",
    "sg:city":"Bruxelles (evere)",
    "sg:classifiers":[
        {
            "category":"Retail",
            "subcategory":"Auto Repair",
            "type":"Services"
        }
    ],
    "sg:phone":"+32 2 242 78 50",
    "sg:postcode":"1140",
    "sg:province":"Bruxelles-Capitale",
    "sg:tags":[
        "garage"
    ],
    "wof:name":"Mav St-vincent",
    "wof:placetype":"venue"
},
  "geometry": {"coordinates":[4.4055581093,50.8826141357],"type":"Point"}
}