{
  "type": "Feature",
  "properties": {
    "iso:country":"BE",
    "sg:address":"Rue De La Cible 17",
    "sg:city":"Schaarbeek/schaerbeek",
    "sg:orig_category":"M\u00e9decins and sp\u00e9cialistes",
    "sg:phone":"+32 2 736 20 96",
    "sg:postcode":"1030",
    "sg:province":"Bruxelles-Capitale",
    "wof:name":"Etienne Paquot",
    "wof:placetype":"venue"
},
  "geometry": {"coordinates":[4.3823609352,50.8521499634],"type":"Point"}
}