{
  "type": "Feature",
  "properties": {
    "addr:full":"Avenue Paul Hymans 109 Woluw\u00c9-saint-lambert Bruxelles-Capitale 1200",
    "addr:housenumber":"109",
    "addr:postcode":"1200",
    "addr:street":"Avenue Paul Hymans",
    "iso:country":"BE",
    "sg:address":"Avenue Paul Hymans 109",
    "sg:city":"Woluw\u00c9-saint-lambert",
    "sg:orig_category":"Diverse opleidingen and onderwijs",
    "sg:phone":"+32 87 77 39 76",
    "sg:postcode":"1200",
    "sg:province":"Bruxelles-Capitale",
    "wof:name":"Dialogue",
    "wof:placetype":"venue"
},
  "geometry": {"coordinates":[4.4314317703,50.8470687866],"type":"Point"}
}