{
  "type": "Feature",
  "properties": {
    "iso:country":"BE",
    "sg:address":"Torhoutsesteenweg 123",
    "sg:city":"Oostende",
    "sg:classifiers":[
        {
            "category":"Manufacturing",
            "subcategory":"Textiles",
            "type":"Manufacturing & Wholesale Goods"
        }
    ],
    "sg:phone":"+32 59 70 83 31",
    "sg:postcode":"8400",
    "sg:province":"West-Vlaanderen",
    "sg:tags":[
        "retail",
        "-"
    ],
    "wof:name":"Altex",
    "wof:placetype":"venue"
},
  "geometry": {"coordinates":[2.9082400799,51.2220535278],"type":"Point"}
}