{
  "type": "Feature",
  "properties": {
    "addr:full":"Dorpsstraat 13 Londerzeel Vlaams-Brabant 1840",
    "addr:housenumber":"13",
    "addr:postcode":"1840",
    "addr:street":"Dorpsstraat",
    "iso:country":"BE",
    "sg:address":"Dorpsstraat 13",
    "sg:city":"Londerzeel",
    "sg:orig_category":"R\u00e9parations d'horloges, montres and bijoux. Bijouteries and horlogeries. Produits interm\u00e9diaires Gr",
    "sg:phone":"+32 52 30 95 65",
    "sg:postcode":"1840",
    "sg:province":"Vlaams-Brabant",
    "wof:name":"Huis Eeraerts",
    "wof:placetype":"venue"
},
  "geometry": {"coordinates":[4.3025898933,51.0035209656],"type":"Point"}
}