{
  "type": "Feature",
  "properties": {
    "addr:full":"Nieuwpoortsesteenweg 22 Box 9 Oostende West-Vlaanderen 8400",
    "addr:housenumber":"22;9",
    "addr:postcode":"8400",
    "addr:street":"Nieuwpoortsesteenweg;Box",
    "iso:country":"BE",
    "sg:address":"Nieuwpoortsesteenweg 22 Box 9",
    "sg:city":"Oostende",
    "sg:classifiers":[
        {
            "category":"Personal",
            "subcategory":"Shoe Repair & Shine",
            "type":"Services"
        }
    ],
    "sg:phone":"+32 59 51 22 38",
    "sg:postcode":"8400",
    "sg:province":"West-Vlaanderen",
    "sg:tags":[
        "shoemaker"
    ],
    "wof:name":"Yves",
    "wof:placetype":"venue"
},
  "geometry": {"coordinates":[2.9078240395,51.2242164612],"type":"Point"}
}