{
  "type": "Feature",
  "properties": {
    "addr:full":"Avenue Ren\u00e9 Gobert 14 Bruxelles (uccle) Bruxelles-Capitale 1180",
    "addr:housenumber":"14",
    "addr:postcode":"1180",
    "addr:street":"Avenue Rene\u0301 Gobert",
    "iso:country":"BE",
    "sg:address":"Avenue Ren\u00e9 Gobert 14",
    "sg:city":"Bruxelles (uccle)",
    "sg:classifiers":[
        {
            "category":"Professional",
            "subcategory":"Management & Consulting",
            "type":"Services"
        }
    ],
    "sg:phone":"+32 2 375 66 58",
    "sg:postcode":"1180",
    "sg:province":"Bruxelles-Capitale",
    "sg:tags":[
        "consultant"
    ],
    "wof:name":"Rog\u00e9 C",
    "wof:placetype":"venue"
},
  "geometry": {"coordinates":[4.3695468903,50.8082809448],"type":"Point"}
}