{
  "type": "Feature",
  "properties": {
    "addr:full":"St.- Anna 27a Hamme Oost-Vlaanderen 9220",
    "addr:housenumber":"27a",
    "addr:postcode":"9220",
    "iso:country":"BE",
    "sg:address":"St.- Anna 27a",
    "sg:city":"Hamme",
    "sg:orig_category":"Metalen constructies Fab Verhuur bouwmachines",
    "sg:phone":"+32 52 47 78 31",
    "sg:postcode":"9220",
    "sg:province":"Oost-Vlaanderen",
    "wof:name":"Hofman Construct",
    "wof:placetype":"venue"
},
  "geometry": {"coordinates":[4.0807738304,51.0947647095],"type":"Point"}
}