{
  "type": "Feature",
  "properties": {
    "iso:country":"BE",
    "sg:address":"Hannesstraat 5",
    "sg:city":"Genk",
    "sg:classifiers":[
        {
            "category":"Building & Trades",
            "subcategory":"Plumbing",
            "type":"Services"
        }
    ],
    "sg:phone":"+32 89 35 18 03",
    "sg:postcode":"3600",
    "sg:province":"Limburg",
    "sg:tags":[
        "diver",
        "commerce",
        "gr",
        "pour",
        "equipement"
    ],
    "wof:name":"Simon Reynders",
    "wof:placetype":"venue"
},
  "geometry": {"coordinates":[5.4957351685,50.9461479187],"type":"Point"}
}