{
  "type": "Feature",
  "properties": {
    "iso:country":"BE",
    "sg:address":"Meir 85",
    "sg:city":"Sint-amands",
    "sg:orig_category":"Eleveurs de bovins",
    "sg:phone":"+32 3 889 16 48",
    "sg:postcode":"2890",
    "sg:province":"Antwerpen",
    "wof:name":"Gaston Pauwels",
    "wof:placetype":"venue"
},
  "geometry": {"coordinates":[4.2478790283,51.0754165649],"type":"Point"}
}