{
  "type": "Feature",
  "properties": {
    "iso:country":"BE",
    "sg:address":"Kemmelseweg 86",
    "sg:city":"Ieper",
    "sg:orig_category":"Eleveurs de bovins",
    "sg:phone":"+32 57 44 46 24",
    "sg:postcode":"8902",
    "sg:province":"West-Vlaanderen",
    "wof:name":"Johan Geerardyn",
    "wof:placetype":"venue"
},
  "geometry": {"coordinates":[2.8558499813,50.8053588867],"type":"Point"}
}