{
  "type": "Feature",
  "properties": {
    "iso:country":"BE",
    "sg:address":"Chauss\u00c9e De Wavre 179",
    "sg:city":"Elsene/ixelles",
    "sg:orig_category":"Librairies. Biens d'occasion",
    "sg:phone":"+32 2 513 72 58",
    "sg:postcode":"1050",
    "sg:province":"Bruxelles-Capitale",
    "wof:name":"La Bande De Six Nez",
    "wof:placetype":"venue"
},
  "geometry": {"coordinates":[4.3712859154,50.8356285095],"type":"Point"}
}