{
  "type": "Feature",
  "properties": {
    "addr:full":"Leurbroek 1070 Kinrooi Limburg 3640",
    "addr:postcode":"1070 kinrooi;3640",
    "iso:country":"BE",
    "sg:address":"Leurbroek 1070",
    "sg:city":"Kinrooi",
    "sg:classifiers":[
        {
            "category":"Manufacturing",
            "subcategory":"Wood Products",
            "type":"Manufacturing & Wholesale Goods"
        }
    ],
    "sg:phone":"+32 89 70 36 01",
    "sg:postcode":"3640",
    "sg:province":"Limburg",
    "sg:tags":[
        "cnc",
        "working"
    ],
    "wof:name":"Ergon Maasland C.v.b.",
    "wof:placetype":"venue"
},
  "geometry": {"coordinates":[5.75147295,51.1375045776],"type":"Point"}
}