{
  "type": "Feature",
  "properties": {
    "iso:country":"BE",
    "sg:address":"Marcel Herpelinckstraat 31",
    "sg:city":"Gent",
    "sg:orig_category":"Activit\u00e9s diverses d'imprimerie",
    "sg:phone":"+32 9 345 83 62",
    "sg:postcode":"9042",
    "sg:province":"Oost-Vlaanderen",
    "wof:name":"Bureau Creativan",
    "wof:placetype":"venue"
},
  "geometry": {"coordinates":[3.8129379749,51.1501312256],"type":"Point"}
}