{
  "type": "Feature",
  "properties": {
    "addr:full":"Rue Des Gen\u00eats 12 Ittre Brabant Wallon 1460",
    "addr:housenumber":"12;1460",
    "addr:street":"Rue Des Gene\u0302Ts",
    "iso:country":"BE",
    "sg:address":"Rue Des Gen\u00eats 12",
    "sg:city":"Ittre",
    "sg:classifiers":[
        {
            "category":"Professional",
            "subcategory":"Management & Consulting",
            "type":"Services"
        }
    ],
    "sg:phone":"+32 67 64 84 22",
    "sg:postcode":"1460",
    "sg:province":"Brabant Wallon",
    "sg:tags":[
        "-",
        "processing",
        "data",
        "consultant"
    ],
    "wof:name":"M 21",
    "wof:placetype":"venue"
},
  "geometry": {"coordinates":[4.2559151649,50.6468811035],"type":"Point"}
}