{
  "type": "Feature",
  "properties": {
    "addr:full":"Steenweg 130 Box 1 As Limburg 3665",
    "addr:housenumber":"130;as",
    "addr:postcode":"3665",
    "addr:street":"Steenweg;Box 1",
    "iso:country":"BE",
    "sg:address":"Steenweg 130 Box 1",
    "sg:city":"As",
    "sg:classifiers":[
        {
            "category":"Insurance",
            "subcategory":"Insurance Agent",
            "type":"Services"
        }
    ],
    "sg:phone":"+32 89 65 65 80",
    "sg:postcode":"3665",
    "sg:province":"Limburg",
    "sg:tags":[
        "broker"
    ],
    "wof:name":"Vranken Verzekeringsadvies Bvba",
    "wof:placetype":"venue"
},
  "geometry": {"coordinates":[5.5706281662,51.0006141663],"type":"Point"}
}