{
  "type": "Feature",
  "properties": {
    "iso:country":"BE",
    "sg:address":"Blekerijweg 98",
    "sg:city":"Poperinge",
    "sg:orig_category":"Eleveurs and marchands de porcs",
    "sg:phone":"+32 57 38 82 06",
    "sg:postcode":"8972",
    "sg:province":"West-Vlaanderen",
    "wof:name":"Nofra",
    "wof:placetype":"venue"
},
  "geometry": {"coordinates":[2.631855011,50.876335144],"type":"Point"}
}