{
  "type": "Feature",
  "properties": {
    "addr:full":"Rijksweg 253b2 Maasmechelen Limburg 3630",
    "addr:housenumber":"253b2",
    "addr:postcode":"3630",
    "addr:street":"Rijksweg",
    "iso:country":"BE",
    "sg:address":"Rijksweg 253b2",
    "sg:city":"Maasmechelen",
    "sg:orig_category":"Timbres, monnaies and troph\u00e9es",
    "sg:phone":"+32 89 76 28 24",
    "sg:postcode":"3630",
    "sg:province":"Limburg",
    "wof:name":"Victory Trophy Shop",
    "wof:placetype":"venue"
},
  "geometry": {"coordinates":[5.6987891197,50.973110199],"type":"Point"}
}