{
  "type": "Feature",
  "properties": {
    "addr:full":"Zoning Industriel 28 Perwez Brabant Wallon 1360",
    "addr:housenumber":"28",
    "addr:postcode":"1360",
    "addr:street":"Zoning Industriel",
    "iso:country":"BE",
    "sg:address":"Zoning Industriel 28",
    "sg:city":"Perwez",
    "sg:classifiers":[
        {
            "category":"Retail",
            "subcategory":"Auto Repair",
            "type":"Services"
        }
    ],
    "sg:phone":"+32 81 65 74 54",
    "sg:postcode":"1360",
    "sg:province":"Brabant Wallon",
    "sg:tags":[
        "breakdown",
        "automobile",
        "-",
        "recovery"
    ],
    "wof:name":"Carrosserie H.l. Sa",
    "wof:placetype":"venue"
},
  "geometry": {"coordinates":[4.8146052361,50.6239395142],"type":"Point"}
}