{
  "type": "Feature",
  "properties": {
    "iso:country":"BE",
    "sg:address":"Maalbeekstraat 25",
    "sg:city":"Dilbeek",
    "sg:orig_category":"Eleveurs and marchands de porcs",
    "sg:phone":"+32 2 466 04 36",
    "sg:postcode":"1700",
    "sg:province":"Vlaams-Brabant",
    "wof:name":"De Gieter",
    "wof:placetype":"venue"
},
  "geometry": {"coordinates":[4.2752189636,50.8631858826],"type":"Point"}
}