{
  "type": "Feature",
  "properties": {
    "iso:country":"BE",
    "sg:address":"Zwaluwenlaan 35",
    "sg:city":"Aartselaar",
    "sg:orig_category":"Koerierbedrijven",
    "sg:phone":"+32 475 74 73 87",
    "sg:postcode":"2630",
    "sg:province":"Antwerpen",
    "wof:name":"Transport Basetrans",
    "wof:placetype":"venue"
},
  "geometry": {"coordinates":[4.3844718933,51.1290817261],"type":"Point"}
}