{
  "type": "Feature",
  "properties": {
    "iso:country":"BE",
    "sg:address":"Baalhoek 48",
    "sg:city":"Grimbergen (strombeek-bever)",
    "sg:orig_category":"Non-Classified Establishments",
    "sg:phone":"+32 2 267 46 57",
    "sg:postcode":"1853",
    "sg:province":"Vlaams-Brabant",
    "wof:name":"Massenberg Collecties",
    "wof:placetype":"venue"
},
  "geometry": {"coordinates":[4.3520140648,50.9046897888],"type":"Point"}
}