{
  "type": "Feature",
  "properties": {
    "addr:full":"Place Xhov\u00e9mont 6 Verviers (petit-rechain) Li\u00e8ge 4800",
    "addr:housenumber":"6",
    "addr:postcode":"4800",
    "addr:street":"Place Xhove\u0301Mont",
    "iso:country":"BE",
    "sg:address":"Place Xhov\u00e9mont 6",
    "sg:city":"Verviers (petit-rechain)",
    "sg:classifiers":[
        {
            "category":"Health Services",
            "subcategory":"Dentist",
            "type":"Services"
        }
    ],
    "sg:phone":"+32 87 33 20 35",
    "sg:postcode":"4800",
    "sg:province":"Li\u00e8ge",
    "wof:name":"Callut Murielle",
    "wof:placetype":"venue"
},
  "geometry": {"coordinates":[5.8594508171,50.5917663574],"type":"Point"}
}