{
  "type": "Feature",
  "properties": {
    "iso:country":"BE",
    "sg:address":"Schensbossen 15",
    "sg:city":"Rumst (reet)",
    "sg:classifiers":[
        {
            "category":"Professional",
            "subcategory":"Management & Consulting",
            "type":"Services"
        }
    ],
    "sg:phone":"+32 3 844 35 33",
    "sg:postcode":"2840",
    "sg:province":"Antwerpen",
    "sg:tags":[
        "consultant",
        "agency",
        "advertising"
    ],
    "wof:name":"Callec Nv",
    "wof:placetype":"venue"
},
  "geometry": {"coordinates":[4.4031271935,51.105670929],"type":"Point"}
}