{
  "type": "Feature",
  "properties": {
    "iso:country":"BE",
    "sg:address":"Kaperberg 8",
    "sg:city":"Eupen",
    "sg:classifiers":[
        {
            "category":"Health Services",
            "subcategory":"Nursing And Care Facility",
            "type":"Services"
        }
    ],
    "sg:phone":"+32 87 55 59 74",
    "sg:postcode":"4700",
    "sg:province":"Li\u00e8ge",
    "sg:tags":[
        "public"
    ],
    "wof:name":"Service De Documentation Conseil Comm. German.",
    "wof:placetype":"venue"
},
  "geometry": {"coordinates":[6.0399870872,50.6313018799],"type":"Point"}
}