{
  "type": "Feature",
  "properties": {
    "iso:country":"BE",
    "sg:address":"Vierbunderstraat 105",
    "sg:city":"Buggenhout",
    "sg:orig_category":"Fairs, shows, exhibitions",
    "sg:phone":"+32 52 34 27 53",
    "sg:postcode":"9255",
    "sg:province":"Oost-Vlaanderen",
    "wof:name":"Bv Projects Sprl-bvba",
    "wof:placetype":"venue"
},
  "geometry": {"coordinates":[4.2365098,51.0200805664],"type":"Point"}
}