{
  "type": "Feature",
  "properties": {
    "iso:country":"BE",
    "sg:address":"Rue Des Saules 49",
    "sg:city":"Lasne (ohain)",
    "sg:orig_category":"Non-Classified Establishments",
    "sg:phone":"+32 2 512 36 41",
    "sg:postcode":"1380",
    "sg:province":"Brabant Wallon",
    "wof:name":"L. Trading Company",
    "wof:placetype":"venue"
},
  "geometry": {"coordinates":[4.483235836,50.6850166321],"type":"Point"}
}