{
  "type": "Feature",
  "properties": {
    "iso:country":"BE",
    "sg:address":"Eethuisstraat 109",
    "sg:city":"Schoten",
    "sg:orig_category":"Slagers",
    "sg:phone":"+32 3 645 94 53",
    "sg:postcode":"2900",
    "sg:province":"Antwerpen",
    "wof:name":"Beenhouwerij Van Mechelen",
    "wof:placetype":"venue"
},
  "geometry": {"coordinates":[4.4617099762,51.2482948303],"type":"Point"}
}