{
  "type": "Feature",
  "properties": {
    "addr:full":"Rue Adrien Materne 9 Grace-hollogne Li\u00e8ge 4460",
    "addr:housenumber":"9",
    "addr:postcode":"4460",
    "addr:street":"Rue Adrien Materne",
    "iso:country":"BE",
    "sg:address":"Rue Adrien Materne 9",
    "sg:city":"Grace-hollogne",
    "sg:orig_category":"Kapsalons",
    "sg:phone":"+32 4 263 56 02",
    "sg:postcode":"4460",
    "sg:province":"Li\u00e8ge",
    "wof:name":"Coiffure Michelle",
    "wof:placetype":"venue"
},
  "geometry": {"coordinates":[5.5023050308,50.6443901062],"type":"Point"}
}