{
  "type": "Feature",
  "properties": {
    "addr:full":"Prins Boudewijnlaan 361 Edegem Antwerpen 2650",
    "addr:housenumber":"361",
    "addr:postcode":"2650",
    "addr:street":"Prins Boudewijnlaan",
    "iso:country":"BE",
    "sg:address":"Prins Boudewijnlaan 361",
    "sg:city":"Edegem",
    "sg:classifiers":[
        {
            "category":"Health Services",
            "subcategory":"Dentist",
            "type":"Services"
        }
    ],
    "sg:phone":"+32 3 449 50 71",
    "sg:postcode":"2650",
    "sg:province":"Antwerpen",
    "wof:name":"Adriaensen Marianne",
    "wof:placetype":"venue"
},
  "geometry": {"coordinates":[4.4265189171,51.1668014526],"type":"Point"}
}