{
  "type": "Feature",
  "properties": {
    "addr:full":"Industriepark 16 Box Iii Tienen Vlaams-Brabant 3300",
    "addr:housenumber":"16",
    "addr:postcode":"3300",
    "addr:street":"Industriepark;Box Iii",
    "iso:country":"BE",
    "sg:address":"Industriepark 16 Box Iii",
    "sg:city":"Tienen",
    "sg:classifiers":[
        {
            "category":"Professional",
            "type":"Services"
        }
    ],
    "sg:phone":"+32 16 80 10 44",
    "sg:postcode":"3300",
    "sg:province":"Vlaams-Brabant",
    "sg:tags":[
        "packing",
        "-"
    ],
    "wof:name":"D. Logistics Packing Nv",
    "wof:placetype":"venue"
},
  "geometry": {"coordinates":[4.930077076,50.8096694946],"type":"Point"}
}