{
  "type": "Feature",
  "properties": {
    "addr:full":"Avenue Reine Astrid 67 Wavre Brabant Wallon 1300",
    "addr:housenumber":"67;1300",
    "addr:street":"Avenue Reine Astrid",
    "iso:country":"BE",
    "sg:address":"Avenue Reine Astrid 67",
    "sg:city":"Wavre",
    "sg:orig_category":"Benzinestations and brandstoffen HUISBRANDOLIE",
    "sg:phone":"+32 10 22 85 31",
    "sg:postcode":"1300",
    "sg:province":"Brabant Wallon",
    "wof:name":"Fina",
    "wof:placetype":"venue"
},
  "geometry": {"coordinates":[4.6162781715,50.7105331421],"type":"Point"}
}