{
  "type": "Feature",
  "properties": {
    "iso:country":"BE",
    "sg:address":"Rillaarsebaan 81",
    "sg:city":"Aarschot",
    "sg:orig_category":"Fruitteelt",
    "sg:phone":"+32 16 57 07 78",
    "sg:postcode":"3200",
    "sg:province":"Vlaams-Brabant",
    "wof:name":"Jozef Spiessens",
    "wof:placetype":"venue"
},
  "geometry": {"coordinates":[4.8295297623,50.9657592773],"type":"Point"}
}