{
  "type": "Feature",
  "properties": {
    "iso:country":"BE",
    "sg:address":"Tieltstraat 135",
    "sg:city":"Meulebeke",
    "sg:orig_category":"Avocats and conseillers juridiques",
    "sg:phone":"+32 51 48 82 35",
    "sg:postcode":"8760",
    "sg:province":"West-Vlaanderen",
    "wof:name":"Isabelle Crop",
    "wof:placetype":"venue"
},
  "geometry": {"coordinates":[3.2992329597,50.9586219788],"type":"Point"}
}