{
  "type": "Feature",
  "properties": {
    "addr:full":"Kruisbeklaan 4 Kalmthout Antwerpen 2920",
    "addr:housenumber":"4",
    "addr:postcode":"2920",
    "addr:street":"Kruisbeklaan",
    "iso:country":"BE",
    "sg:address":"Kruisbeklaan 4",
    "sg:city":"Kalmthout",
    "sg:orig_category":"Boekhouders",
    "sg:phone":"+32 3 666 35 55",
    "sg:postcode":"2920",
    "sg:province":"Antwerpen",
    "wof:name":"Marianne Coulier",
    "wof:placetype":"venue"
},
  "geometry": {"coordinates":[4.4829888344,51.3563346863],"type":"Point"}
}