{
  "type": "Feature",
  "properties": {
    "addr:full":"Rue Victor Besme 37 Vervier Li\u00e8ge 4800",
    "addr:housenumber":"37",
    "addr:postcode":"4800",
    "addr:street":"Rue Victor Besme",
    "iso:country":"BE",
    "sg:address":"Rue Victor Besme 37",
    "sg:city":"Vervier",
    "sg:classifiers":[
        {
            "category":"Shopping",
            "subcategory":"Crafts & Fabrics",
            "type":"Retail Goods"
        }
    ],
    "sg:phone":"+32 87 33 37 34",
    "sg:postcode":"4800",
    "sg:province":"Li\u00e8ge",
    "sg:tags":[
        "textile",
        "clothing"
    ],
    "wof:name":"Dyvertex Sprl",
    "wof:placetype":"venue"
},
  "geometry": {"coordinates":[5.9143800735,43.7566184998],"type":"Point"}
}