{
  "type": "Feature",
  "properties": {
    "iso:country":"BE",
    "sg:address":"Nachtvlinder 7",
    "sg:city":"Dilbeek",
    "sg:classifiers":[
        {
            "category":"Building & Trades",
            "subcategory":"Plumbing",
            "type":"Services"
        }
    ],
    "sg:phone":"+32 2 569 75 58",
    "sg:postcode":"1700",
    "sg:province":"Vlaams-Brabant",
    "sg:tags":[
        "contractor"
    ],
    "wof:name":"Callebaut Staf",
    "wof:placetype":"venue"
},
  "geometry": {"coordinates":[4.2395029068,50.8622512817],"type":"Point"}
}