{
  "type": "Feature",
  "properties": {
    "iso:country":"BE",
    "sg:address":"Galgeveldstraat 16b",
    "sg:city":"Diest",
    "sg:orig_category":"Agences d'exp\u00e9dition",
    "sg:phone":"+32 13 32 77 90",
    "sg:postcode":"3293",
    "sg:province":"Vlaams-Brabant",
    "wof:name":"De Reze",
    "wof:placetype":"venue"
},
  "geometry": {"coordinates":[5.0418610573,50.9789123535],"type":"Point"}
}