{
  "type": "Feature",
  "properties": {
    "iso:country":"BE",
    "sg:address":"Vlamingenstraat 40",
    "sg:city":"Mechelen",
    "sg:orig_category":"Diverse bouwinstallaties Spuittoestellen Fab",
    "sg:phone":"+32 15 41 49 57",
    "sg:postcode":"2812",
    "sg:province":"Antwerpen",
    "wof:name":"All Protec",
    "wof:placetype":"venue"
},
  "geometry": {"coordinates":[4.5180058479,51.0066947937],"type":"Point"}
}