{
  "type": "Feature",
  "properties": {
    "addr:full":"Avenue Des Peupliers 90 Ottignies-louvain-la-neuve Brabant Wallon 1340",
    "addr:housenumber":"90",
    "addr:postcode":"1340",
    "addr:street":"Avenue Des Peupliers",
    "iso:country":"BE",
    "sg:address":"Avenue Des Peupliers 90",
    "sg:city":"Ottignies-louvain-la-neuve",
    "sg:orig_category":"Catering and organisatie van feesten",
    "sg:phone":"+32 10 41 60 18",
    "sg:postcode":"1340",
    "sg:province":"Brabant Wallon",
    "wof:name":"Alain Pigeolet",
    "wof:placetype":"venue"
},
  "geometry": {"coordinates":[4.552822113,50.6710510254],"type":"Point"}
}