{
  "type": "Feature",
  "properties": {
    "addr:full":"Rue Xhav\u00e9e 24 Verviers Li\u00e8ge 4800",
    "addr:housenumber":"24",
    "addr:postcode":"4800",
    "addr:street":"Rue Xhave\u0301E",
    "iso:country":"BE",
    "sg:address":"Rue Xhav\u00e9e 24",
    "sg:city":"Verviers",
    "sg:classifiers":[
        {
            "category":"Personal",
            "subcategory":"Shoe Repair & Shine",
            "type":"Services"
        }
    ],
    "sg:phone":"+32 87 33 24 01",
    "sg:postcode":"4800",
    "sg:province":"Li\u00e8ge",
    "sg:tags":[
        "shoemaker"
    ],
    "wof:name":"Cordonnerie Rapide",
    "wof:placetype":"venue"
},
  "geometry": {"coordinates":[5.8591351509,50.591796875],"type":"Point"}
}