{
  "type": "Feature",
  "properties": {
    "iso:country":"BE",
    "sg:address":"Riemstraat 18",
    "sg:city":"Antwerpen",
    "sg:orig_category":"Diverse grafische activiteiten",
    "sg:phone":"+32 3 238 84 27",
    "sg:postcode":"2000",
    "sg:province":"Antwerpen",
    "wof:name":"Bureau Anthologie",
    "wof:placetype":"venue"
},
  "geometry": {"coordinates":[4.3927412033,51.2132377625],"type":"Point"}
}