{
  "type": "Feature",
  "properties": {
    "iso:country":"BE",
    "sg:address":"Markt 24",
    "sg:city":"Meerhout",
    "sg:orig_category":"Banques and organismes de cr\u00e9dit",
    "sg:phone":"+32 14 30 35 91",
    "sg:postcode":"2450",
    "sg:province":"Antwerpen",
    "wof:name":"Kbc",
    "wof:placetype":"venue"
},
  "geometry": {"coordinates":[5.0784749985,51.1316184998],"type":"Point"}
}