{
  "type": "Feature",
  "properties": {
    "addr:full":"Rue Des Ch\u00eanays 121 Wellin (chanly) Luxembourg 6921",
    "addr:housenumber":"121",
    "addr:postcode":"6921",
    "addr:street":"Rue Des Che\u0302Nays",
    "iso:country":"BE",
    "sg:address":"Rue Des Ch\u00eanays 121",
    "sg:city":"Wellin (chanly)",
    "sg:classifiers":[
        {
            "category":"Health Services",
            "subcategory":"Nursing And Care Facility",
            "type":"Services"
        }
    ],
    "sg:phone":"+32 84 38 89 11",
    "sg:postcode":"6921",
    "sg:province":"Luxembourg",
    "sg:tags":[
        "home",
        "rest"
    ],
    "wof:name":"Val Des Seniors",
    "wof:placetype":"venue"
},
  "geometry": {"coordinates":[5.154583931,50.0783538818],"type":"Point"}
}