{
  "type": "Feature",
  "properties": {
    "addr:full":"Wijnendaelestraat 76 Torhout West-Vlaanderen 8820",
    "addr:housenumber":"76",
    "addr:postcode":"8820",
    "addr:street":"Wijnendaelestraat",
    "iso:country":"BE",
    "sg:address":"Wijnendaelestraat 76",
    "sg:city":"Torhout",
    "sg:orig_category":"Royal Canin",
    "sg:phone":"+32 50 21 11 15",
    "sg:postcode":"8820",
    "sg:province":"West-Vlaanderen",
    "wof:name":"Bolliou Michel",
    "wof:placetype":"venue"
},
  "geometry": {"coordinates":[3.0743210316,51.0973777771],"type":"Point"}
}