{
  "type": "Feature",
  "properties": {
    "iso:country":"BE",
    "sg:address":"Jan Palfijnlaan 27",
    "sg:city":"Hasselt",
    "sg:orig_category":"Beheer onroerend goed",
    "sg:phone":"+32 11 22 94 76",
    "sg:postcode":"3500",
    "sg:province":"Limburg",
    "wof:name":"Francis Dewaleffe",
    "wof:placetype":"venue"
},
  "geometry": {"coordinates":[5.3526802063,50.925151825],"type":"Point"}
}