{
  "type": "Feature",
  "properties": {
    "iso:country":"BE",
    "sg:address":"Kapellenstrasse 39",
    "sg:city":"Lontzen",
    "sg:classifiers":[
        {
            "category":"Shopping",
            "subcategory":"Antiques",
            "type":"Retail Goods"
        }
    ],
    "sg:phone":"+32 87 65 73 96",
    "sg:postcode":"4710",
    "sg:province":"Li\u00e8ge",
    "sg:tags":[
        "restoration"
    ],
    "wof:name":"Corman T",
    "wof:placetype":"venue"
},
  "geometry": {"coordinates":[5.9898557663,50.6833686829],"type":"Point"}
}