{
  "type": "Feature",
  "properties": {
    "iso:country":"BE",
    "sg:address":"Winninglaan 8",
    "sg:city":"Temse",
    "sg:classifiers":[
        {
            "category":"Professional",
            "subcategory":"Testing Lab",
            "type":"Services"
        }
    ],
    "sg:phone":"+32 3 710 93 40",
    "sg:postcode":"9140",
    "sg:province":"Oost-Vlaanderen",
    "sg:tags":[
        "laboratory",
        "-",
        "machines",
        "apparatus",
        "supply"
    ],
    "wof:name":"Hanna Instruments",
    "wof:placetype":"venue"
},
  "geometry": {"coordinates":[4.1934452057,51.1354446411],"type":"Point"}
}