{
  "type": "Feature",
  "properties": {
    "addr:full":"Jozef Wautersplein 5 Boom Antwerpen 2850",
    "addr:housenumber":"5",
    "addr:postcode":"2850",
    "addr:street":"Jozef Wautersplein",
    "iso:country":"BE",
    "sg:address":"Jozef Wautersplein 5",
    "sg:city":"Boom",
    "sg:classifiers":[
        {
            "category":"Manufacturing",
            "subcategory":"Motor Vehicles & Parts",
            "type":"Manufacturing & Wholesale Goods"
        }
    ],
    "sg:phone":"+32 3 294 44 74",
    "sg:postcode":"2850",
    "sg:province":"Antwerpen",
    "sg:tags":[
        "electromechanical",
        "component"
    ],
    "wof:name":"Amc Print Services",
    "wof:placetype":"venue"
},
  "geometry": {"coordinates":[4.3753871918,51.0995140076],"type":"Point"}
}