{
  "type": "Feature",
  "properties": {
    "addr:full":"Chauss\u00e9e De Charleroi 106 Fosses-la-ville (vitrival) Namur 5070",
    "addr:housenumber":"106",
    "addr:postcode":"5070",
    "addr:street":"Chausse\u0301E De Charleroi",
    "iso:country":"BE",
    "sg:address":"Chauss\u00e9e De Charleroi 106",
    "sg:city":"Fosses-la-ville (vitrival)",
    "sg:classifiers":[
        {
            "category":"Autos & Motor Vehicles",
            "subcategory":"Automobile Sales",
            "type":"Retail Goods"
        }
    ],
    "sg:phone":"+32 71 71 22 52",
    "sg:postcode":"5070",
    "sg:province":"Namur",
    "sg:tags":[
        "car",
        "used",
        "-"
    ],
    "wof:name":"Mazuin Hugues Sprl",
    "wof:placetype":"venue"
},
  "geometry": {"coordinates":[4.6720352173,50.3934173584],"type":"Point"}
}