{
  "type": "Feature",
  "properties": {
    "iso:country":"BE",
    "sg:address":"Gen. Baron Jacquesstraat 92",
    "sg:city":"Diksmuide",
    "sg:orig_category":"Dameskledingzaken Herenkledingzaken",
    "sg:phone":"+32 51 51 19 59",
    "sg:postcode":"8600",
    "sg:province":"West-Vlaanderen",
    "wof:name":"Huis Dolce Fashion",
    "wof:placetype":"venue"
},
  "geometry": {"coordinates":[2.8589680195,51.0327301025],"type":"Point"}
}