{
  "type": "Feature",
  "properties": {
    "addr:full":"Jan Baptist Davidstraat 15 Boom Antwerpen 2850",
    "addr:housenumber":"15",
    "addr:postcode":"2850",
    "addr:street":"Jan Baptist Davidstraat",
    "iso:country":"BE",
    "sg:address":"Jan Baptist Davidstraat 15",
    "sg:city":"Boom",
    "sg:classifiers":[
        {
            "category":"Arena",
            "subcategory":"Sports Club",
            "type":"Entertainment"
        }
    ],
    "sg:phone":"+32 3 844 24 11",
    "sg:postcode":"2850",
    "sg:province":"Antwerpen",
    "sg:tags":[
        "de"
    ],
    "wof:name":"Kon. Zwemclub De Ijsberen",
    "wof:placetype":"venue"
},
  "geometry": {"coordinates":[4.3741021156,51.0968437195],"type":"Point"}
}