{
  "type": "Feature",
  "properties": {
    "addr:full":"Preenakker 2-4 Merchtem Vlaams-Brabant 1785",
    "addr:housenumber":"2-4",
    "addr:postcode":"1785",
    "addr:street":"Preenakker",
    "iso:country":"BE",
    "sg:address":"Preenakker 2-4",
    "sg:city":"Merchtem",
    "sg:classifiers":[
        {
            "category":"Manufacturing",
            "subcategory":"Rubber & Plastics",
            "type":"Manufacturing & Wholesale Goods"
        }
    ],
    "sg:phone":"+32 52 38 19 10",
    "sg:postcode":"1785",
    "sg:province":"Vlaams-Brabant",
    "sg:tags":[
        "hose"
    ],
    "wof:name":"Articom",
    "wof:placetype":"venue"
},
  "geometry": {"coordinates":[4.2478981018,50.9510002136],"type":"Point"}
}