{
  "type": "Feature",
  "properties": {
    "addr:full":"Oudstrijdersplein 17 Ninove Oost-Vlaanderen 9400",
    "addr:housenumber":"17",
    "addr:postcode":"9400",
    "addr:street":"Oudstrijdersplein",
    "iso:country":"BE",
    "sg:address":"Oudstrijdersplein 17",
    "sg:city":"Ninove",
    "sg:classifiers":[
        {
            "category":"Shopping",
            "subcategory":"Clothing, Apparel, & Fashions",
            "type":"Retail Goods"
        }
    ],
    "sg:phone":"+32 54 33 88 40",
    "sg:postcode":"9400",
    "sg:province":"Oost-Vlaanderen",
    "sg:tags":[
        "-",
        "haberdashery"
    ],
    "wof:name":"De Backer (huis)",
    "wof:placetype":"venue"
},
  "geometry": {"coordinates":[4.0224719048,50.835269928],"type":"Point"}
}