{
  "type": "Feature",
  "properties": {
    "iso:country":"BE",
    "sg:address":"Hulsterweg 71",
    "sg:city":"Tessenderlo",
    "sg:orig_category":"Sportclubs",
    "sg:phone":"+32 13 67 64 28",
    "sg:postcode":"3980",
    "sg:province":"Limburg",
    "wof:name":"Looise Badmintonclub",
    "wof:placetype":"venue"
},
  "geometry": {"coordinates":[5.1147727966,51.0688285828],"type":"Point"}
}