{
  "type": "Feature",
  "properties": {
    "iso:country":"BE",
    "sg:address":"Veldstraat 3",
    "sg:city":"Staden (oostnieuwkerke)",
    "sg:classifiers":[
        {
            "category":"Building & Trades",
            "subcategory":"Landscaping Services",
            "type":"Services"
        }
    ],
    "sg:phone":"+32 51 25 25 03",
    "sg:postcode":"8840",
    "sg:province":"West-Vlaanderen",
    "sg:tags":[
        "slaughterer"
    ],
    "wof:name":"Denorme-platteeuw H",
    "wof:placetype":"venue"
},
  "geometry": {"coordinates":[3.0509519577,50.9352531433],"type":"Point"}
}