{
  "type": "Feature",
  "properties": {
    "iso:country":"BE",
    "sg:address":"Rue Jean Volders 37",
    "sg:city":"Awans",
    "sg:orig_category":"Sportclubs",
    "sg:phone":"+32 4 246 45 97",
    "sg:postcode":"4340",
    "sg:province":"Li\u00e8ge",
    "wof:name":"T.c. Awans",
    "wof:placetype":"venue"
},
  "geometry": {"coordinates":[5.4589080811,50.6718902588],"type":"Point"}
}