{
  "type": "Feature",
  "properties": {
    "iso:country":"BE",
    "sg:address":"Rue De Charleville 5",
    "sg:city":"Gedinne",
    "sg:orig_category":"Production and transformation de viande. Boucheries",
    "sg:phone":"+32 61 58 80 18",
    "sg:postcode":"5575",
    "sg:province":"Namur",
    "wof:name":"Alain Ridelle",
    "wof:placetype":"venue"
},
  "geometry": {"coordinates":[4.9366598129,49.9796981812],"type":"Point"}
}