{
  "type": "Feature",
  "properties": {
    "addr:full":"Woestijne 34 Aalter Oost-Vlaanderen 9880",
    "addr:housenumber":"34",
    "addr:postcode":"9880",
    "addr:street":"Woestijne",
    "iso:country":"BE",
    "sg:address":"Woestijne 34",
    "sg:city":"Aalter",
    "sg:orig_category":"Installatie van houten of kunststof schrijnwerk",
    "sg:phone":"+32 9 374 48 43",
    "sg:postcode":"9880",
    "sg:province":"Oost-Vlaanderen",
    "wof:name":"Patrick De Smet",
    "wof:placetype":"venue"
},
  "geometry": {"coordinates":[3.448884964,51.1140632629],"type":"Point"}
}