{
  "type": "Feature",
  "properties": {
    "addr:full":"Statiestr 84 Zulte Oost-Vlaanderen 9870",
    "addr:housenumber":"84",
    "addr:postcode":"9870",
    "addr:street":"Statiestr",
    "iso:country":"BE",
    "sg:address":"Statiestr 84",
    "sg:city":"Zulte",
    "sg:classifiers":[
        {
            "category":"Social Services",
            "subcategory":"Job Training",
            "type":"Services"
        }
    ],
    "sg:phone":"+32 64 22 14 52",
    "sg:postcode":"9870",
    "sg:province":"Oost-Vlaanderen",
    "sg:tags":[
        "metallurgy",
        "metal",
        "processing",
        "-",
        "metalworking",
        "machine",
        "engineering",
        "mechanical"
    ],
    "wof:name":"Durant Fr\u00c8res Sa",
    "wof:placetype":"venue"
},
  "geometry": {"coordinates":[4.2048139572,50.488861084],"type":"Point"}
}