{
  "type": "Feature",
  "properties": {
    "iso:country":"BE",
    "sg:address":"Engelbert Moensstraat 36",
    "sg:city":"Kortenberg (meerbeek)",
    "sg:classifiers":[
        {
            "category":"Professional",
            "subcategory":"Art Services",
            "type":"Services"
        }
    ],
    "sg:phone":"+32 2 757 17 45",
    "sg:postcode":"3078",
    "sg:province":"Vlaams-Brabant",
    "sg:tags":[
        "-",
        "painter",
        "artist"
    ],
    "wof:name":"Van Orshaegen L",
    "wof:placetype":"venue"
},
  "geometry": {"coordinates":[4.5937290192,50.877948761],"type":"Point"}
}