{
  "type": "Feature",
  "properties": {
    "iso:country":"BE",
    "sg:address":"Processiestraat 2",
    "sg:city":"Hooglede",
    "sg:orig_category":"Producteurs de l\u00e9gumes",
    "sg:phone":"+32 51 70 06 80",
    "sg:postcode":"8830",
    "sg:province":"West-Vlaanderen",
    "wof:name":"Paul Pauwelyn",
    "wof:placetype":"venue"
},
  "geometry": {"coordinates":[3.0413770676,50.9733695984],"type":"Point"}
}