{
  "type": "Feature",
  "properties": {
    "iso:country":"BE",
    "sg:address":"Goteringenstraat 65",
    "sg:city":"Gooik",
    "sg:orig_category":"Sportclubs",
    "sg:phone":"+32 54 56 75 16",
    "sg:postcode":"1755",
    "sg:province":"Vlaams-Brabant",
    "wof:name":"Govok Cammaert Gooik",
    "wof:placetype":"venue"
},
  "geometry": {"coordinates":[4.0860290527,50.7686424255],"type":"Point"}
}