{
  "type": "Feature",
  "properties": {
    "addr:full":"Rue Capitaine Crespel 10 Elsene Bruxelles-Capitale 1050",
    "addr:housenumber":"10",
    "addr:postcode":"1050",
    "addr:street":"Rue Capitaine Crespel",
    "iso:country":"BE",
    "sg:address":"Rue Capitaine Crespel 10",
    "sg:city":"Elsene",
    "sg:classifiers":[
        {
            "category":"Fast Food",
            "type":"Food & Drink"
        }
    ],
    "sg:phone":"+32 2 512 83 19",
    "sg:postcode":"1050",
    "sg:province":"Bruxelles-Capitale",
    "sg:tags":[
        "d",
        "restaurant",
        "organisation",
        "\u00c0",
        "domicile",
        "catering",
        "emporter",
        "livraison",
        "restaurants"
    ],
    "wof:name":"Shogun",
    "wof:placetype":"venue"
},
  "geometry": {"coordinates":[4.3581027985,50.8359222412],"type":"Point"}
}