{
  "type": "Feature",
  "properties": {
    "iso:country":"BE",
    "sg:address":"Rue De La Briqueterie 3",
    "sg:city":"Somme-leuze",
    "sg:orig_category":"Astrologen, grafologen and mediums",
    "sg:phone":"+32 84 32 22 99",
    "sg:postcode":"5377",
    "sg:province":"Namur",
    "wof:name":"Astro-conseils",
    "wof:placetype":"venue"
},
  "geometry": {"coordinates":[5.3089118004,50.2573356628],"type":"Point"}
}