{
  "type": "Feature",
  "properties": {
    "addr:full":"Rue Fond-pirette 41 Li\u00c8ge Li\u00e8ge 4000",
    "addr:housenumber":"41",
    "addr:postcode":"4000",
    "addr:street":"Rue Fond-Pirette",
    "iso:country":"BE",
    "sg:address":"Rue Fond-pirette 41",
    "sg:city":"Li\u00c8ge",
    "sg:orig_category":"Diverse organisaties and verenigingen",
    "sg:phone":"+32 4 222 11 47",
    "sg:postcode":"4000",
    "sg:province":"Li\u00e8ge",
    "wof:name":"G.a.t.a.",
    "wof:placetype":"venue"
},
  "geometry": {"coordinates":[5.5671019554,50.6490249634],"type":"Point"}
}