{
  "type": "Feature",
  "properties": {
    "addr:full":"Platanenlaan 20 Meise Vlaams-Brabant 1861",
    "addr:housenumber":"20",
    "addr:postcode":"1861",
    "addr:street":"Platanenlaan",
    "iso:country":"BE",
    "sg:address":"Platanenlaan 20",
    "sg:city":"Meise",
    "sg:orig_category":"Schoonheidssalons",
    "sg:phone":"+32 2 269 02 86",
    "sg:postcode":"1861",
    "sg:province":"Vlaams-Brabant",
    "wof:name":"Agnes Van Malder",
    "wof:placetype":"venue"
},
  "geometry": {"coordinates":[4.310172081,50.9555511475],"type":"Point"}
}