{
  "type": "Feature",
  "properties": {
    "iso:country":"BE",
    "sg:address":"Wiedauwkaai 71",
    "sg:city":"Gent",
    "sg:classifiers":[
        {
            "category":"Wholesale",
            "subcategory":"Painting Supplies",
            "type":"Manufacturing & Wholesale Goods"
        }
    ],
    "sg:phone":"+32 9 253 07 17",
    "sg:postcode":"9000",
    "sg:province":"Oost-Vlaanderen",
    "sg:tags":[
        "spray"
    ],
    "wof:name":"Roggeman",
    "wof:placetype":"venue"
},
  "geometry": {"coordinates":[3.7256650925,51.0769424438],"type":"Point"}
}