{
  "type": "Feature",
  "properties": {
    "addr:full":"Rue Du Temple 21 La Louvi\u00e8re Hainaut 7100",
    "addr:housenumber":"21",
    "addr:postcode":"7100",
    "addr:street":"Rue Du Temple",
    "iso:country":"BE",
    "sg:address":"Rue Du Temple 21",
    "sg:city":"La Louvi\u00e8re",
    "sg:classifiers":[
        {
            "category":"Personal",
            "subcategory":"Tattoo Parlor",
            "type":"Services"
        }
    ],
    "sg:phone":"+32 64 21 47 35",
    "sg:postcode":"7100",
    "sg:province":"Hainaut",
    "sg:tags":[
        "tattooists"
    ],
    "wof:name":"No Comment Tattoo & Piercing",
    "wof:placetype":"venue"
},
  "geometry": {"coordinates":[4.1878948212,50.4757843018],"type":"Point"}
}