{
  "type": "Feature",
  "properties": {
    "iso:country":"BE",
    "sg:address":"Rue Grande 71",
    "sg:city":"Dour",
    "sg:orig_category":"Postkantoren",
    "sg:phone":"+32 65 71 80 40",
    "sg:postcode":"7370",
    "sg:province":"Hainaut",
    "wof:name":"La Poste",
    "wof:placetype":"venue"
},
  "geometry": {"coordinates":[3.7809209824,50.3990325928],"type":"Point"}
}