{
  "type": "Feature",
  "properties": {
    "iso:country":"BE",
    "sg:address":"Rue De La Croy\u00c8re 3",
    "sg:city":"Manage",
    "sg:orig_category":"Entretien and r\u00e9parations de voitures. V\u00e9hicules automobiles",
    "sg:phone":"+32 64 54 01 61",
    "sg:postcode":"7170",
    "sg:province":"Hainaut",
    "wof:name":"R. Gardi",
    "wof:placetype":"venue"
},
  "geometry": {"coordinates":[4.2234501839,50.4910812378],"type":"Point"}
}