{
  "type": "Feature",
  "properties": {
    "addr:full":"Avenue Des Liserons 37b31 Brussel/bruxelles Bruxelles-Capitale 1020",
    "addr:housenumber":"37b31",
    "addr:postcode":"1020",
    "addr:street":"Avenue Des Liserons;/",
    "iso:country":"BE",
    "sg:address":"Avenue Des Liserons 37b31",
    "sg:city":"Brussel/bruxelles",
    "sg:orig_category":"Ordinateurs and \u00e9quipement informatique",
    "sg:phone":"+32 2 268 45 10",
    "sg:postcode":"1020",
    "sg:province":"Bruxelles-Capitale",
    "wof:name":"De Ridder Concepts",
    "wof:placetype":"venue"
},
  "geometry": {"coordinates":[4.3711700439,50.897518158],"type":"Point"}
}