{
  "type": "Feature",
  "properties": {
    "addr:full":"Eindeken 3 Evergem Oost-Vlaanderen 9940",
    "addr:housenumber":"3",
    "addr:postcode":"9940",
    "addr:street":"Eindeken;Oost-Vlaanderen",
    "iso:country":"BE",
    "sg:address":"Eindeken 3",
    "sg:city":"Evergem",
    "sg:orig_category":"Plantes and fleurs Gr",
    "sg:phone":"+32 9 253 85 72",
    "sg:postcode":"9940",
    "sg:province":"Oost-Vlaanderen",
    "wof:name":"De Groote",
    "wof:placetype":"venue"
},
  "geometry": {"coordinates":[3.7090699673,51.1075439453],"type":"Point"}
}