{
  "type": "Feature",
  "properties": {
    "addr:full":"Albertlaan 49 Vorst/forest Bruxelles-Capitale 1190",
    "addr:housenumber":"49",
    "addr:postcode":"1190",
    "addr:street":"Albertlaan;/ Forest",
    "iso:country":"BE",
    "sg:address":"Albertlaan 49",
    "sg:city":"Vorst/forest",
    "sg:orig_category":"Marketingbureaus Reclamebureaus",
    "sg:phone":"+32 2 344 87 60",
    "sg:postcode":"1190",
    "sg:province":"Bruxelles-Capitale",
    "wof:name":"The Performers Group",
    "wof:placetype":"venue"
},
  "geometry": {"coordinates":[4.3436250687,50.8209228516],"type":"Point"}
}