{
  "type": "Feature",
  "properties": {
    "addr:full":"Tiensevest 174 Leuven Vlaams-Brabant 3000",
    "addr:housenumber":"174",
    "addr:postcode":"3000",
    "addr:street":"Tiensevest",
    "iso:country":"BE",
    "sg:address":"Tiensevest 174",
    "sg:city":"Leuven",
    "sg:classifiers":[
        {
            "category":"Health Services",
            "subcategory":"Dentist",
            "type":"Services"
        }
    ],
    "sg:phone":"+32 16 29 07 55",
    "sg:postcode":"3000",
    "sg:province":"Vlaams-Brabant",
    "wof:name":"Roosen Jan",
    "wof:placetype":"venue"
},
  "geometry": {"coordinates":[4.7143769264,50.8743858337],"type":"Point"}
}