{
  "type": "Feature",
  "properties": {
    "iso:country":"BE",
    "sg:address":"Goeslaerstraat 6",
    "sg:city":"Lummen",
    "sg:orig_category":"Sportterreinen and installaties behalve sportcentra",
    "sg:phone":"+32 13 44 44 45",
    "sg:postcode":"3560",
    "sg:province":"Limburg",
    "wof:name":"Military Lummen",
    "wof:placetype":"venue"
},
  "geometry": {"coordinates":[5.1519899368,50.9802284241],"type":"Point"}
}