{
  "type": "Feature",
  "properties": {
    "iso:country":"BE",
    "sg:address":"Zwevegemsestraat 50",
    "sg:city":"Kortrijk",
    "sg:classifiers":[
        {
            "category":"Food & Beverages",
            "subcategory":"Specialty",
            "type":"Retail Goods"
        }
    ],
    "sg:phone":"+32 56 22 02 42",
    "sg:postcode":"8500",
    "sg:province":"West-Vlaanderen",
    "sg:tags":[
        "health",
        "dietary",
        "-",
        "biological"
    ],
    "wof:name":"Maelfait Slagerij",
    "wof:placetype":"venue"
},
  "geometry": {"coordinates":[3.2720270157,50.8252716064],"type":"Point"}
}