{
  "type": "Feature",
  "properties": {
    "iso:country":"BE",
    "sg:address":"Rue Waroquier 31",
    "sg:city":"Erquelinnes",
    "sg:orig_category":"Sportclubs",
    "sg:phone":"+32 71 55 58 01",
    "sg:postcode":"6560",
    "sg:province":"Hainaut",
    "wof:name":"B.c. Erquelinnes",
    "wof:placetype":"venue"
},
  "geometry": {"coordinates":[4.1139678955,50.3081054688],"type":"Point"}
}