{
  "type": "Feature",
  "properties": {
    "iso:country":"BE",
    "sg:address":"Brusselbaan 11",
    "sg:city":"Herzele",
    "sg:orig_category":"Afbraak- and draineerwerken",
    "sg:phone":"+32 54 50 11 83",
    "sg:postcode":"9550",
    "sg:province":"Oost-Vlaanderen",
    "wof:name":"De Henau M",
    "wof:placetype":"venue"
},
  "geometry": {"coordinates":[3.9109070301,50.8260993958],"type":"Point"}
}