{
  "type": "Feature",
  "properties": {
    "addr:full":"Rue De La Croix 54 Namur Namur 5000",
    "addr:housenumber":"54",
    "addr:postcode":"5000",
    "addr:street":"Rue De La Croix",
    "iso:country":"BE",
    "sg:address":"Rue De La Croix 54",
    "sg:city":"Namur",
    "sg:classifiers":[
        {
            "category":"Shopping",
            "subcategory":"Clothing, Apparel, & Fashions",
            "type":"Retail Goods"
        }
    ],
    "sg:phone":"+32 81 22 46 90",
    "sg:postcode":"5000",
    "sg:province":"Namur",
    "sg:tags":[
        "boutique"
    ],
    "wof:name":"Belle Et La B\u00eate (la)",
    "wof:placetype":"venue"
},
  "geometry": {"coordinates":[4.8640899658,50.4637947083],"type":"Point"}
}