{
  "type": "Feature",
  "properties": {
    "iso:country":"BE",
    "sg:address":"Osystraat 20",
    "sg:city":"Antwerpen",
    "sg:orig_category":"M\u00e9decins and sp\u00e9cialistes",
    "sg:phone":"+32 3 231 32 95",
    "sg:postcode":"2060",
    "sg:province":"Antwerpen",
    "wof:name":"J. Immanuel",
    "wof:placetype":"venue"
},
  "geometry": {"coordinates":[4.4185290337,51.2220230103],"type":"Point"}
}