{
  "type": "Feature",
  "properties": {
    "iso:country":"BE",
    "sg:address":"Avenue Emile Rousseaux 40",
    "sg:city":"Charleroi (marcinelle)",
    "sg:classifiers":[
        {
            "category":"Building & Trades",
            "subcategory":"Equipment Rental",
            "type":"Services"
        }
    ],
    "sg:phone":"+32 71 44 03 11",
    "sg:postcode":"6001",
    "sg:province":"Hainaut",
    "sg:tags":[
        "use",
        "apparatus",
        "tool",
        "-",
        "professional",
        "machines"
    ],
    "wof:name":"De Cock R (entreprises R\u00e9unies)",
    "wof:placetype":"venue"
},
  "geometry": {"coordinates":[4.4274878502,50.4021644592],"type":"Point"}
}