{
  "type": "Feature",
  "properties": {
    "addr:full":"Achterbroeksesteenweg 1 Kalmthout Antwerpen 2920",
    "addr:housenumber":"1",
    "addr:postcode":"2920",
    "addr:street":"Achterbroeksesteenweg",
    "iso:country":"BE",
    "sg:address":"Achterbroeksesteenweg 1",
    "sg:city":"Kalmthout",
    "sg:orig_category":"Royal Canin. Animaux domestiques and accessoires. Fleurs and plantes. Articles de jardin",
    "sg:phone":"+32 3 666 55 84",
    "sg:postcode":"2920",
    "sg:province":"Antwerpen",
    "wof:name":"Garfo Bvba",
    "wof:placetype":"venue"
},
  "geometry": {"coordinates":[4.4742598534,51.393901825],"type":"Point"}
}