{
  "type": "Feature",
  "properties": {
    "iso:country":"BE",
    "sg:address":"Monseigneur Trudo Jansstraat 31",
    "sg:city":"Riemst (zichen-zussen-bolder)",
    "sg:classifiers":[
        {
            "category":"Food & Beverages",
            "subcategory":"Groceries & Convenience Stores",
            "type":"Retail Goods"
        }
    ],
    "sg:phone":"+32 12 45 70 73",
    "sg:postcode":"3770",
    "sg:province":"Limburg",
    "sg:tags":[
        "grocer"
    ],
    "wof:name":"Voeding Miranda",
    "wof:placetype":"venue"
},
  "geometry": {"coordinates":[5.5746321678,50.8097381592],"type":"Point"}
}