{
  "type": "Feature",
  "properties": {
    "addr:full":"Booglaan 22 Denderleeuw Oost-Vlaanderen 9473",
    "addr:housenumber":"22",
    "addr:postcode":"9473",
    "addr:street":"Booglaan",
    "iso:country":"BE",
    "sg:address":"Booglaan 22",
    "sg:city":"Denderleeuw",
    "sg:orig_category":"Voedingsspeciaalzaken",
    "sg:phone":"+32 53 67 10 28",
    "sg:postcode":"9473",
    "sg:province":"Oost-Vlaanderen",
    "wof:name":"Guy Roelandt",
    "wof:placetype":"venue"
},
  "geometry": {"coordinates":[4.05479002,50.8952331543],"type":"Point"}
}