{
  "type": "Feature",
  "properties": {
    "iso:country":"BE",
    "sg:address":"Avenue De L'industrie 21",
    "sg:city":"Braine L'alleud (braine-l'alleud)",
    "sg:classifiers":[
        {
            "category":"Retail",
            "subcategory":"Repair Shop",
            "type":"Services"
        }
    ],
    "sg:phone":"+32 2 387 07 07",
    "sg:postcode":"1420",
    "sg:province":"Brabant Wallon",
    "sg:tags":[
        "machine",
        "sewing",
        "-"
    ],
    "wof:name":"Aisin Europe Nv",
    "wof:placetype":"venue"
},
  "geometry": {"coordinates":[-0.7004899979,47.369140625],"type":"Point"}
}