{
  "type": "Feature",
  "properties": {
    "iso:country":"BE",
    "sg:address":"Stationsstraat 129",
    "sg:city":"Zaventem",
    "sg:classifiers":[
        {
            "category":"Wholesale",
            "subcategory":"Medical Equipment & Supplies",
            "type":"Manufacturing & Wholesale Goods"
        }
    ],
    "sg:phone":"+32 2 720 47 25",
    "sg:postcode":"1930",
    "sg:province":"Vlaams-Brabant",
    "sg:tags":[
        "aid",
        "hearing"
    ],
    "wof:name":"Caluwaerts B",
    "wof:placetype":"venue"
},
  "geometry": {"coordinates":[4.4709830284,50.8842544556],"type":"Point"}
}