{
  "type": "Feature",
  "properties": {
    "addr:full":"Rue Des Binches 2 Chatelet Hainaut 6200",
    "addr:housenumber":"2",
    "addr:postcode":"6200",
    "addr:street":"Rue Des Binches;Hainaut",
    "iso:country":"BE",
    "sg:address":"Rue Des Binches 2",
    "sg:city":"Chatelet",
    "sg:orig_category":"Woningbouw",
    "sg:phone":"+32 71 39 01 01",
    "sg:postcode":"6200",
    "sg:province":"Hainaut",
    "wof:name":"Guy Faini",
    "wof:placetype":"venue"
},
  "geometry": {"coordinates":[4.5546917915,50.3849983215],"type":"Point"}
}