{
  "type": "Feature",
  "properties": {
    "iso:country":"BE",
    "sg:address":"Schone Luchtlaan 31",
    "sg:city":"Wezembeek-oppem",
    "sg:classifiers":[
        {
            "category":"Insurance",
            "subcategory":"Insurance Agent",
            "type":"Services"
        }
    ],
    "sg:phone":"+32 2 731 55 14",
    "sg:postcode":"1970",
    "sg:province":"Vlaams-Brabant",
    "sg:tags":[
        "verzekeringsmakelaars",
        "expert"
    ],
    "wof:name":"J.l. Follong",
    "wof:placetype":"venue"
},
  "geometry": {"coordinates":[4.4800701141,50.8459358215],"type":"Point"}
}