{
  "type": "Feature",
  "properties": {
    "addr:full":"Stationsstraat 23 Lede Oost-Vlaanderen 9340",
    "addr:housenumber":"23",
    "addr:postcode":"9340",
    "addr:street":"Stationsstraat",
    "iso:country":"BE",
    "sg:address":"Stationsstraat 23",
    "sg:city":"Lede",
    "sg:orig_category":"D\u00e9molition d\u00b4immeubles and terrassements",
    "sg:phone":"+32 53 80 04 94",
    "sg:postcode":"9340",
    "sg:province":"Oost-Vlaanderen",
    "wof:name":"Ronny Van Der Spiegel",
    "wof:placetype":"venue"
},
  "geometry": {"coordinates":[3.980973959,50.9684791565],"type":"Point"}
}