{
  "type": "Feature",
  "properties": {
    "iso:country":"BE",
    "sg:address":"Omgangstraat 87",
    "sg:city":"Bornem (mariekerke)",
    "sg:classifiers":[
        {
            "category":"Personal",
            "subcategory":"Beauty Salon",
            "type":"Services"
        }
    ],
    "sg:phone":"+32 52 33 28 58",
    "sg:postcode":"2880",
    "sg:province":"Antwerpen",
    "wof:name":"La Sophia",
    "wof:placetype":"venue"
},
  "geometry": {"coordinates":[4.1917228699,51.0634346008],"type":"Point"}
}