{
  "type": "Feature",
  "properties": {
    "iso:country":"BE",
    "sg:address":"Geraardsbergsestraat 178",
    "sg:city":"Aalst",
    "sg:orig_category":"Alimentation sp\u00e9cialis\u00e9e",
    "sg:phone":"+32 53 70 62 67",
    "sg:postcode":"9300",
    "sg:province":"Oost-Vlaanderen",
    "wof:name":"Traiteur David",
    "wof:placetype":"venue"
},
  "geometry": {"coordinates":[4.035900116,50.9301528931],"type":"Point"}
}