{
  "type": "Feature",
  "properties": {
    "iso:country":"BE",
    "sg:address":"Rue Vanderlinden 115",
    "sg:city":"Schaarbeek/schaerbeek",
    "sg:orig_category":"Installation de menuiserie en bois and plastique. Installation de menuiserie m\u00e9tallique. Forge, Moul",
    "sg:phone":"+32 2 216 49 50",
    "sg:postcode":"1030",
    "sg:province":"Bruxelles-Capitale",
    "wof:name":"T.d.s.",
    "wof:placetype":"venue"
},
  "geometry": {"coordinates":[4.3698348999,50.8699455261],"type":"Point"}
}