{
  "type": "Feature",
  "properties": {
    "addr:full":"Bracht 4 Burg-reuland Li\u00e8ge 4790",
    "addr:housenumber":"4",
    "addr:postcode":"4790",
    "addr:street":"Bracht",
    "iso:country":"BE",
    "sg:address":"Bracht 4",
    "sg:city":"Burg-reuland",
    "sg:orig_category":"Non-Classified Establishments",
    "sg:phone":"+32 80 42 00 82",
    "sg:postcode":"4790",
    "sg:province":"Li\u00e8ge",
    "wof:name":"Phytol",
    "wof:placetype":"venue"
},
  "geometry": {"coordinates":[6.1315770149,50.1943702698],"type":"Point"}
}