{
  "type": "Feature",
  "properties": {
    "addr:full":"Place Aux Foires 18 Marche-en-famenne Luxembourg 6900",
    "addr:housenumber":"18",
    "addr:postcode":"6900",
    "addr:street":"Place Aux Foires",
    "iso:country":"BE",
    "sg:address":"Place Aux Foires 18",
    "sg:city":"Marche-en-famenne",
    "sg:classifiers":[
        {
            "category":"Cafe",
            "type":"Food & Drink"
        }
    ],
    "sg:phone":"+32 84 31 12 75",
    "sg:postcode":"6900",
    "sg:province":"Luxembourg",
    "sg:tags":[
        "caf\u00e9s"
    ],
    "wof:name":"Caf\u00c9 Au Charleroi",
    "wof:placetype":"venue"
},
  "geometry": {"coordinates":[5.3450231552,50.2253417969],"type":"Point"}
}