{
  "type": "Feature",
  "properties": {
    "addr:full":"Leermarkt 50 Mechelen Antwerpen 2800",
    "addr:housenumber":"50",
    "addr:postcode":"2800",
    "addr:street":"Leermarkt",
    "iso:country":"BE",
    "sg:address":"Leermarkt 50",
    "sg:city":"Mechelen",
    "sg:classifiers":[
        {
            "category":"Shopping",
            "subcategory":"Bicycles & Sporting Goods",
            "type":"Retail Goods"
        }
    ],
    "sg:phone":"+32 15 21 21 41",
    "sg:postcode":"2800",
    "sg:province":"Antwerpen",
    "sg:tags":[
        "article",
        "de",
        "sport",
        "camping"
    ],
    "wof:name":"Start",
    "wof:placetype":"venue"
},
  "geometry": {"coordinates":[4.4827451706,51.0253105164],"type":"Point"}
}