{
  "type": "Feature",
  "properties": {
    "addr:full":"Kapellebaan 30 Liedekerke Vlaams-Brabant 1770",
    "addr:housenumber":"30",
    "addr:postcode":"1770",
    "addr:street":"Kapellebaan;Vlaams-Brabant",
    "iso:country":"BE",
    "sg:address":"Kapellebaan 30",
    "sg:city":"Liedekerke",
    "sg:orig_category":"Protection civile",
    "sg:phone":"+32 53 66 67 95",
    "sg:postcode":"1770",
    "sg:province":"Vlaams-Brabant",
    "wof:name":"Civiele Bescherming",
    "wof:placetype":"venue"
},
  "geometry": {"coordinates":[4.0988278389,50.8682937622],"type":"Point"}
}