{
  "type": "Feature",
  "properties": {
    "addr:full":"Boulevard Heynen 6 Bouillon Luxembourg 6830",
    "addr:housenumber":"6",
    "addr:postcode":"6830",
    "addr:street":"Boulevard Heynen",
    "iso:country":"BE",
    "sg:address":"Boulevard Heynen 6",
    "sg:city":"Bouillon",
    "sg:classifiers":[
        {
            "category":"Shopping",
            "subcategory":"Clothing, Apparel, & Fashions",
            "type":"Retail Goods"
        }
    ],
    "sg:phone":"+32 61 46 90 33",
    "sg:postcode":"6830",
    "sg:province":"Luxembourg",
    "sg:tags":[
        "bathing-",
        "beachwear"
    ],
    "wof:name":"Sensuelle",
    "wof:placetype":"venue"
},
  "geometry": {"coordinates":[5.0697760582,49.7954444885],"type":"Point"}
}