{
  "type": "Feature",
  "properties": {
    "iso:country":"BE",
    "sg:address":"Pallieterdreef 5",
    "sg:city":"Grobbendonk",
    "sg:classifiers":[
        {
            "category":"Shopping",
            "subcategory":"Florist",
            "type":"Retail Goods"
        }
    ],
    "sg:phone":"+32 14 50 02 29",
    "sg:postcode":"2280",
    "sg:province":"Antwerpen",
    "wof:name":"Boen R",
    "wof:placetype":"venue"
},
  "geometry": {"coordinates":[4.7374901772,51.1717681885],"type":"Point"}
}