{
  "type": "Feature",
  "properties": {
    "iso:country":"BE",
    "sg:address":"Rue De Marcinelle 30",
    "sg:city":"Ham-sur-heure-nalinnes (nalinnes)",
    "sg:orig_category":"Non-Classified Establishments",
    "sg:phone":"+32 71 21 37 59",
    "sg:postcode":"6120",
    "sg:province":"Hainaut",
    "wof:name":"Stiernon & Fils Europa Sprl",
    "wof:placetype":"venue"
},
  "geometry": {"coordinates":[4.4420170784,50.3412322998],"type":"Point"}
}