{
  "type": "Feature",
  "properties": {
    "addr:full":"Brusselsestraat 21-27 Leuven Vlaams-Brabant 3000",
    "addr:postcode":"21-27;3000",
    "addr:street":"Brusselsestraat",
    "iso:country":"BE",
    "sg:address":"Brusselsestraat 21-27",
    "sg:city":"Leuven",
    "sg:classifiers":[
        {
            "category":"Shopping",
            "subcategory":"Clothing, Apparel, & Fashions",
            "type":"Retail Goods"
        }
    ],
    "sg:phone":"+32 16 22 38 63",
    "sg:postcode":"3000",
    "sg:province":"Vlaams-Brabant",
    "sg:tags":[
        "lady",
        "clothing",
        "-"
    ],
    "wof:name":"Devernois-lambert",
    "wof:placetype":"venue"
},
  "geometry": {"coordinates":[4.69911623,50.8794326782],"type":"Point"}
}