{
  "type": "Feature",
  "properties": {
    "addr:full":"Rue Fran\u00c7ois Cloes 51 Saint-nicolas Li\u00e8ge 4420",
    "addr:housenumber":"51",
    "addr:postcode":"4420",
    "addr:street":"Rue Franc\u0327Ois Cloes",
    "iso:country":"BE",
    "sg:address":"Rue Fran\u00c7ois Cloes 51",
    "sg:city":"Saint-nicolas",
    "sg:classifiers":[
        {
            "category":"Autos & Motor Vehicles",
            "subcategory":"Fuel & Gas Station",
            "type":"Retail Goods"
        }
    ],
    "sg:phone":"+32 4 263 55 14",
    "sg:postcode":"4420",
    "sg:province":"Li\u00e8ge",
    "sg:tags":[
        "stations-service",
        "carburants"
    ],
    "wof:name":"Shell",
    "wof:placetype":"venue"
},
  "geometry": {"coordinates":[5.5174632072,50.6369895935],"type":"Point"}
}