{
  "type": "Feature",
  "properties": {
    "iso:country":"BE",
    "sg:address":"Kortrijksestraat 407",
    "sg:city":"Oostkamp",
    "sg:orig_category":"D\u00e9taillants en pi\u00e8ces and accessoires de voitures",
    "sg:phone":"+32 50 27 78 02",
    "sg:postcode":"8020",
    "sg:province":"West-Vlaanderen",
    "wof:name":"Lin Autoshop",
    "wof:placetype":"venue"
},
  "geometry": {"coordinates":[3.2227499485,51.1264457703],"type":"Point"}
}