{
  "type": "Feature",
  "properties": {
    "addr:full":"Rue Joseph War\u00e8gne 24 Namur (flawinne) Namur 5020",
    "addr:housenumber":"24",
    "addr:postcode":"5020",
    "addr:street":"Rue Joseph Ware\u0300Gne",
    "iso:country":"BE",
    "sg:address":"Rue Joseph War\u00e8gne 24",
    "sg:city":"Namur (flawinne)",
    "sg:classifiers":[
        {
            "category":"Manufacturing",
            "subcategory":"Wood Products",
            "type":"Manufacturing & Wholesale Goods"
        }
    ],
    "sg:phone":"+32 81 74 55 96",
    "sg:postcode":"5020",
    "sg:province":"Namur",
    "sg:tags":[
        "preservation"
    ],
    "wof:name":"La Maison Neuve",
    "wof:placetype":"venue"
},
  "geometry": {"coordinates":[4.8769698143,50.4837303162],"type":"Point"}
}