{
  "type": "Feature",
  "properties": {
    "iso:country":"BE",
    "sg:address":"Rue De Oizy 39",
    "sg:city":"Monceau-en-ardenne",
    "sg:orig_category":"Dakwerken Schoonmaakbedrijven and ongediertebestrijding",
    "sg:phone":"+32 61 51 20 89",
    "sg:postcode":"5555",
    "sg:province":"Namur",
    "wof:name":"Roger Martin",
    "wof:placetype":"venue"
},
  "geometry": {"coordinates":[4.9859790802,49.9040679932],"type":"Point"}
}