{
  "type": "Feature",
  "properties": {
    "addr:full":"Congregatiestraat 16 Gent Oost-Vlaanderen 9031",
    "addr:housenumber":"16",
    "addr:postcode":"9031",
    "addr:street":"Congregatiestraat;Oost-Vlaanderen",
    "iso:country":"BE",
    "sg:address":"Congregatiestraat 16",
    "sg:city":"Gent",
    "sg:classifiers":[
        {
            "category":"Communications",
            "subcategory":"Film & Video Production",
            "type":"Services"
        }
    ],
    "sg:phone":"+32 9 227 42 81",
    "sg:postcode":"9031",
    "sg:province":"Oost-Vlaanderen",
    "sg:tags":[
        "platen",
        "cassette",
        "cd's"
    ],
    "wof:name":"Margareta Doutrepont",
    "wof:placetype":"venue"
},
  "geometry": {"coordinates":[3.6528720856,51.052532196],"type":"Point"}
}