{
  "type": "Feature",
  "properties": {
    "addr:full":"Chevauchoire De Viane 93 Lessines Hainaut 7860",
    "addr:housenumber":"93",
    "addr:postcode":"7860",
    "addr:street":"Hainaut",
    "iso:country":"BE",
    "sg:address":"Chevauchoire De Viane 93",
    "sg:city":"Lessines",
    "sg:classifiers":[
        {
            "category":"Restaurant",
            "type":"Food & Drink"
        }
    ],
    "sg:phone":"+32 68 33 97 40",
    "sg:postcode":"7860",
    "sg:province":"Hainaut",
    "sg:tags":[
        "caf\u00e9s"
    ],
    "wof:name":"Taverne Le Ramier",
    "wof:placetype":"venue"
},
  "geometry": {"coordinates":[3.8400800228,50.7179107666],"type":"Point"}
}