{
  "type": "Feature",
  "properties": {
    "addr:full":"Rue Tour Petit Ch\u00c2teau 9 Soignies Hainaut 7060",
    "addr:housenumber":"9",
    "addr:postcode":"7060",
    "addr:street":"Rue Tour Petit Cha\u0302Teau",
    "iso:country":"BE",
    "sg:address":"Rue Tour Petit Ch\u00c2teau 9",
    "sg:city":"Soignies",
    "sg:orig_category":"Woningbouw",
    "sg:phone":"+32 67 33 45 90",
    "sg:postcode":"7060",
    "sg:province":"Hainaut",
    "wof:name":"Chantier Lenoir",
    "wof:placetype":"venue"
},
  "geometry": {"coordinates":[4.0614800453,50.5733947754],"type":"Point"}
}