{
  "type": "Feature",
  "properties": {
    "iso:country":"BE",
    "sg:address":"Rue Bidaut 7",
    "sg:city":"Li\u00e8ge 1",
    "sg:classifiers":[
        {
            "category":"Home & Garden",
            "subcategory":"Carpets & Floor Coverings",
            "type":"Retail Goods"
        }
    ],
    "sg:phone":"+32 4 226 32 87",
    "sg:postcode":"4000",
    "sg:province":"Li\u00e8ge",
    "sg:tags":[
        "-"
    ],
    "wof:name":"Piccard P",
    "wof:placetype":"venue"
},
  "geometry": {"coordinates":[5.5573477745,50.6410331726],"type":"Point"}
}