{
  "type": "Feature",
  "properties": {
    "iso:country":"BE",
    "sg:address":"Boulevard Dolez 37",
    "sg:city":"Mons",
    "sg:classifiers":[
        {
            "category":"Real Estate",
            "subcategory":"Architect",
            "type":"Services"
        }
    ],
    "sg:phone":"+32 65 31 47 38",
    "sg:postcode":"7000",
    "sg:province":"Hainaut",
    "wof:name":"Lousse Y",
    "wof:placetype":"venue"
},
  "geometry": {"coordinates":[3.9583930969,50.4511146545],"type":"Point"}
}