{
  "type": "Feature",
  "properties": {
    "addr:full":"Sint-antoniusstraat 95 Anzegem West-Vlaanderen 8570",
    "addr:housenumber":"95",
    "addr:postcode":"8570",
    "addr:street":"Sint-Antoniusstraat",
    "iso:country":"BE",
    "sg:address":"Sint-antoniusstraat 95",
    "sg:city":"Anzegem",
    "sg:orig_category":"Rundveehouders Varkenskwekers",
    "sg:phone":"+32 56 77 76 08",
    "sg:postcode":"8570",
    "sg:province":"West-Vlaanderen",
    "wof:name":"Marnix Demeurie",
    "wof:placetype":"venue"
},
  "geometry": {"coordinates":[3.4302461147,50.8304977417],"type":"Point"}
}