{
  "type": "Feature",
  "properties": {
    "addr:full":"Chauss\u00e9e Brunehault 573 Herstal (vottem) Li\u00e8ge 4041",
    "addr:housenumber":"573",
    "addr:postcode":"4041",
    "addr:street":"Chausse\u0301E Brunehault;Vottem",
    "iso:country":"BE",
    "sg:address":"Chauss\u00e9e Brunehault 573",
    "sg:city":"Herstal (vottem)",
    "sg:classifiers":[
        {
            "category":"Banks & Credit Unions",
            "subcategory":"Bureau De Change",
            "type":"Services"
        }
    ],
    "sg:phone":"+32 4 227 15 21",
    "sg:postcode":"4041",
    "sg:province":"Li\u00e8ge",
    "sg:tags":[
        "-",
        "household",
        "gas"
    ],
    "wof:name":"Jacquemin P\u00e8re & Fils",
    "wof:placetype":"venue"
},
  "geometry": {"coordinates":[5.5818748474,50.6797142029],"type":"Point"}
}