{
  "type": "Feature",
  "properties": {
    "iso:country":"BE",
    "sg:address":"Lepelstraat 16b303",
    "sg:city":"Sint-truiden",
    "sg:orig_category":"M\u00e9decins and sp\u00e9cialistes",
    "sg:phone":"+32 11 68 55 35",
    "sg:postcode":"3800",
    "sg:province":"Limburg",
    "wof:name":"Anneliese Mo\u00cbsse",
    "wof:placetype":"venue"
},
  "geometry": {"coordinates":[5.1845860481,50.8115310669],"type":"Point"}
}