{
  "type": "Feature",
  "properties": {
    "addr:full":"Spoorwegstraat 12 Peer (wijchmaal) Limburg 3990",
    "addr:housenumber":"12",
    "addr:postcode":"3990",
    "addr:street":"Spoorwegstraat",
    "iso:country":"BE",
    "sg:address":"Spoorwegstraat 12",
    "sg:city":"Peer (wijchmaal)",
    "sg:classifiers":[
        {
            "category":"Building & Trades",
            "subcategory":"Pest Control",
            "type":"Services"
        }
    ],
    "sg:phone":"+32 11 63 67 00",
    "sg:postcode":"3990",
    "sg:province":"Limburg",
    "sg:tags":[
        "painting",
        "contractor"
    ],
    "wof:name":"Accent Interieur",
    "wof:placetype":"venue"
},
  "geometry": {"coordinates":[5.4533009529,51.1329536438],"type":"Point"}
}