{
  "type": "Feature",
  "properties": {
    "iso:country":"BE",
    "sg:address":"Rue De La C\u00e9lid\u00e9e 24 Box 2",
    "sg:city":"Bruxelles (molenbeek-saint-jean)",
    "sg:classifiers":[
        {
            "category":"Building & Trades",
            "subcategory":"Pest Control",
            "type":"Services"
        }
    ],
    "sg:phone":"+32 2 345 83 03",
    "sg:postcode":"1080",
    "sg:province":"Bruxelles-Capitale",
    "sg:tags":[
        "machine",
        "vending"
    ],
    "wof:name":"Baudoux J & A",
    "wof:placetype":"venue"
},
  "geometry": {"coordinates":[4.3198828697,50.858253479],"type":"Point"}
}