{
  "type": "Feature",
  "properties": {
    "iso:country":"BE",
    "sg:address":"Rue 't Serstevens 41",
    "sg:city":"Thuin",
    "sg:orig_category":"Alternatieve geneeskunde Artsen and specialisten",
    "sg:phone":"+32 71 59 14 59",
    "sg:postcode":"6530",
    "sg:province":"Hainaut",
    "wof:name":"Dokter Leroy Fran\u00c7ois-louis",
    "wof:placetype":"venue"
},
  "geometry": {"coordinates":[4.2822918892,50.3416824341],"type":"Point"}
}