{
  "type": "Feature",
  "properties": {
    "addr:full":"Massemsesteenweg 56a Wetteren Oost-Vlaanderen 9230",
    "addr:housenumber":"56a",
    "addr:postcode":"9230",
    "addr:street":"Massemsesteenweg",
    "iso:country":"BE",
    "sg:address":"Massemsesteenweg 56a",
    "sg:city":"Wetteren",
    "sg:classifiers":[
        {
            "category":"Retail",
            "subcategory":"Event Space",
            "type":"Services"
        }
    ],
    "sg:phone":"+32 9 369 66 23",
    "sg:postcode":"9230",
    "sg:province":"Oost-Vlaanderen",
    "sg:tags":[
        "rental",
        "-",
        "hall"
    ],
    "wof:name":"Dasseveld",
    "wof:placetype":"venue"
},
  "geometry": {"coordinates":[3.8775980473,50.9954719543],"type":"Point"}
}