{
  "type": "Feature",
  "properties": {
    "addr:full":"Rue Jean Jaur\u00e8s 73 Binche (leval-trahegnies) Hainaut 7134",
    "addr:housenumber":"73",
    "addr:postcode":"7134",
    "addr:street":"Rue Jean Jaure\u0300S",
    "iso:country":"BE",
    "sg:address":"Rue Jean Jaur\u00e8s 73",
    "sg:city":"Binche (leval-trahegnies)",
    "sg:classifiers":[
        {
            "category":"Personal",
            "subcategory":"Beauty Salon",
            "type":"Services"
        }
    ],
    "sg:phone":"+32 64 33 91 94",
    "sg:postcode":"7134",
    "sg:province":"Hainaut",
    "sg:tags":[
        "lady",
        "-",
        "hairdressing"
    ],
    "wof:name":"Madeleine",
    "wof:placetype":"venue"
},
  "geometry": {"coordinates":[4.2159090042,50.4143066406],"type":"Point"}
}