{
  "type": "Feature",
  "properties": {
    "addr:full":"Oude Markt 10 Dessel Antwerpen 2480",
    "addr:housenumber":"10",
    "addr:postcode":"2480",
    "addr:street":"Oude Markt",
    "iso:country":"BE",
    "sg:address":"Oude Markt 10",
    "sg:city":"Dessel",
    "sg:classifiers":[
        {
            "category":"Shopping",
            "subcategory":"Clothing, Apparel, & Fashions",
            "type":"Retail Goods"
        }
    ],
    "sg:phone":"+32 14 37 35 60",
    "sg:postcode":"2480",
    "sg:province":"Antwerpen",
    "sg:tags":[
        "-",
        "clothing",
        "child"
    ],
    "wof:name":"Popolle",
    "wof:placetype":"venue"
},
  "geometry": {"coordinates":[5.1124448776,51.2405509949],"type":"Point"}
}