{
  "type": "Feature",
  "properties": {
    "addr:full":"Meldertsestraat 55 Halen (zelem) Limburg 3545",
    "addr:housenumber":"55",
    "addr:postcode":"3545",
    "addr:street":"Meldertsestraat",
    "iso:country":"BE",
    "sg:address":"Meldertsestraat 55",
    "sg:city":"Halen (zelem)",
    "sg:classifiers":[
        {
            "category":"Manufacturing",
            "subcategory":"Tools & Machinery",
            "type":"Manufacturing & Wholesale Goods"
        }
    ],
    "sg:phone":"+32 13 55 63 83",
    "sg:postcode":"3545",
    "sg:province":"Limburg",
    "sg:tags":[
        "machine"
    ],
    "wof:name":"Coun M",
    "wof:placetype":"venue"
},
  "geometry": {"coordinates":[5.1127400398,50.9482154846],"type":"Point"}
}