{
  "type": "Feature",
  "properties": {
    "iso:country":"BE",
    "sg:address":"Rue Jean F\u00c9rard 2",
    "sg:city":"Beyne-heusay",
    "sg:orig_category":"Alimentation sp\u00e9cialis\u00e9e. Epiceries",
    "sg:phone":"+32 4 358 11 97",
    "sg:postcode":"4610",
    "sg:province":"Li\u00e8ge",
    "wof:name":"Aydogdu",
    "wof:placetype":"venue"
},
  "geometry": {"coordinates":[5.6536698341,50.623550415],"type":"Point"}
}