{
  "type": "Feature",
  "properties": {
    "iso:country":"BE",
    "sg:address":"Kouterveldstraat 11",
    "sg:city":"Machelen (diegem)",
    "sg:classifiers":[
        {
            "category":"Professional",
            "subcategory":"Detective & Security Services",
            "type":"Services"
        }
    ],
    "sg:phone":"+32 2 719 54 11",
    "sg:postcode":"1831",
    "sg:province":"Vlaams-Brabant",
    "sg:tags":[
        "door",
        "videophones",
        "operating",
        "equipment"
    ],
    "wof:name":"Bticino Sa",
    "wof:placetype":"venue"
},
  "geometry": {"coordinates":[4.4525299072,50.8848304749],"type":"Point"}
}