{
  "type": "Feature",
  "properties": {
    "iso:country":"BE",
    "sg:address":"Herkenrodesingel 2b3",
    "sg:city":"Hasselt",
    "sg:orig_category":"Kapsalons",
    "sg:phone":"+32 11 25 07 65",
    "sg:postcode":"3500",
    "sg:province":"Limburg",
    "wof:name":"Coiffure Martine",
    "wof:placetype":"venue"
},
  "geometry": {"coordinates":[5.3173890114,50.937412262],"type":"Point"}
}