{
  "type": "Feature",
  "properties": {
    "iso:country":"BE",
    "sg:address":"Dennenlaan 77",
    "sg:city":"Pulle",
    "sg:classifiers":[
        {
            "category":"Manufacturing",
            "subcategory":"Chemicals & Compounds",
            "type":"Manufacturing & Wholesale Goods"
        }
    ],
    "sg:phone":"+32 3 484 31 33",
    "sg:postcode":"2243",
    "sg:province":"Antwerpen",
    "sg:tags":[
        "pharmaceutical",
        "chemistry",
        "-",
        "by-product"
    ],
    "wof:name":"Corosa Bvba",
    "wof:placetype":"venue"
},
  "geometry": {"coordinates":[4.6952700615,51.1945610046],"type":"Point"}
}