{
  "type": "Feature",
  "properties": {
    "iso:country":"BE",
    "sg:address":"Sint-odilialaan 1",
    "sg:city":"Hamont-achel (achel)",
    "sg:classifiers":[
        {
            "category":"Fast Food",
            "type":"Food & Drink"
        }
    ],
    "sg:phone":"+32 11 64 33 70",
    "sg:postcode":"3930",
    "sg:province":"Limburg",
    "sg:tags":[
        "fried",
        "stand",
        "potato"
    ],
    "wof:name":"Mike",
    "wof:placetype":"venue"
},
  "geometry": {"coordinates":[5.4754538536,51.2674713135],"type":"Point"}
}