{
  "type": "Feature",
  "properties": {
    "addr:full":"Lichterveldestraat 39ba Torhout West-Vlaanderen 8820",
    "addr:housenumber":"39ba",
    "addr:postcode":"8820",
    "addr:street":"Lichterveldestraat",
    "iso:country":"BE",
    "sg:address":"Lichterveldestraat 39ba",
    "sg:city":"Torhout",
    "sg:orig_category":"Reclamebureaus",
    "sg:phone":"+32 50 22 10 71",
    "sg:postcode":"8820",
    "sg:province":"West-Vlaanderen",
    "wof:name":"Belg. Translation Centre",
    "wof:placetype":"venue"
},
  "geometry": {"coordinates":[3.1043319702,51.0613212585],"type":"Point"}
}