{
  "type": "Feature",
  "properties": {
    "iso:country":"BE",
    "sg:address":"Walgracht 2",
    "sg:city":"Evergem",
    "sg:orig_category":"Non-Classified Establishments",
    "sg:phone":"+32 9 253 90 37",
    "sg:postcode":"9940",
    "sg:province":"Oost-Vlaanderen",
    "wof:name":"Lybaert Voeders Nv",
    "wof:placetype":"venue"
},
  "geometry": {"coordinates":[3.7552359104,51.1400756836],"type":"Point"}
}