{
  "type": "Feature",
  "properties": {
    "iso:country":"BE",
    "sg:address":"Gaverlandwegel 83",
    "sg:city":"Beveren",
    "sg:classifiers":[
        {
            "category":"Cafe",
            "type":"Food & Drink"
        }
    ],
    "sg:phone":"+32 3 775 66 29",
    "sg:postcode":"9120",
    "sg:province":"Oost-Vlaanderen",
    "sg:tags":[
        "caf\u00e9s"
    ],
    "wof:name":"Patrick Bosman",
    "wof:placetype":"venue"
},
  "geometry": {"coordinates":[4.2794828415,51.2275352478],"type":"Point"}
}