{
  "type": "Feature",
  "properties": {
    "addr:full":"Tulpenstraat 8 Wielsbeke West-Vlaanderen 8710",
    "addr:housenumber":"8",
    "addr:postcode":"8710",
    "addr:street":"Tulpenstraat;West-Vlaanderen",
    "iso:country":"BE",
    "sg:address":"Tulpenstraat 8",
    "sg:city":"Wielsbeke",
    "sg:classifiers":[
        {
            "category":"Home & Garden",
            "subcategory":"Carpets & Floor Coverings",
            "type":"Retail Goods"
        }
    ],
    "sg:phone":"+32 56 32 65 30",
    "sg:postcode":"8710",
    "sg:province":"West-Vlaanderen",
    "sg:tags":[
        "parquet"
    ],
    "wof:name":"Arti Legno A Bvba",
    "wof:placetype":"venue"
},
  "geometry": {"coordinates":[3.3793621063,50.9121017456],"type":"Point"}
}