{
  "type": "Feature",
  "properties": {
    "iso:country":"BE",
    "sg:address":"Luchterenkerkweg 91",
    "sg:city":"Gent",
    "sg:orig_category":"Boissons",
    "sg:phone":"+32 9 226 54 00",
    "sg:postcode":"9031",
    "sg:province":"Oost-Vlaanderen",
    "wof:name":"Hugo Godefroot",
    "wof:placetype":"venue"
},
  "geometry": {"coordinates":[3.6473469734,51.057636261],"type":"Point"}
}