{
  "type": "Feature",
  "properties": {
    "iso:country":"BE",
    "sg:address":"Champ De Pr\u00e9senne 46",
    "sg:city":"Grez-doiceau",
    "sg:classifiers":[
        {
            "category":"Manufacturing",
            "subcategory":"Paper Products",
            "type":"Manufacturing & Wholesale Goods"
        }
    ],
    "sg:phone":"+32 10 84 51 04",
    "sg:postcode":"1390",
    "sg:province":"Brabant Wallon",
    "sg:tags":[
        "-"
    ],
    "wof:name":"Clairefontaine (papeteries De)",
    "wof:placetype":"venue"
},
  "geometry": {"coordinates":[4.6775398254,50.7236938477],"type":"Point"}
}