{
  "type": "Feature",
  "properties": {
    "iso:country":"BE",
    "sg:address":"Hof Ter Puttenlaan 46",
    "sg:city":"Dilbeek",
    "sg:orig_category":"DIVERSE RECREATIEVE ACTIVITEITEN",
    "sg:phone":"+32 2 466 64 54",
    "sg:postcode":"1700",
    "sg:province":"Vlaams-Brabant",
    "wof:name":"Bridge Club Westrand",
    "wof:placetype":"venue"
},
  "geometry": {"coordinates":[4.2712721825,50.8518486023],"type":"Point"}
}