{
  "type": "Feature",
  "properties": {
    "addr:full":"Rue Du Printemps 50 Elsene/ixelles Bruxelles-Capitale 1050",
    "addr:housenumber":"50",
    "addr:postcode":"1050",
    "addr:street":"Rue Du Printemps",
    "iso:country":"BE",
    "sg:address":"Rue Du Printemps 50",
    "sg:city":"Elsene/ixelles",
    "sg:orig_category":"Installation de menuiserie en bois and plastique",
    "sg:phone":"+32 2 639 08 40",
    "sg:postcode":"1050",
    "sg:province":"Bruxelles-Capitale",
    "wof:name":"Harpo",
    "wof:placetype":"venue"
},
  "geometry": {"coordinates":[4.3878889084,50.8202323914],"type":"Point"}
}