{
  "type": "Feature",
  "properties": {
    "iso:country":"BE",
    "sg:address":"Ommegangstraat 1l",
    "sg:city":"Zwevegem",
    "sg:orig_category":"Schoonheidssalons",
    "sg:phone":"+32 56 75 97 75",
    "sg:postcode":"8550",
    "sg:province":"West-Vlaanderen",
    "wof:name":"Instituut Chiara",
    "wof:placetype":"venue"
},
  "geometry": {"coordinates":[3.3389000893,50.8128852844],"type":"Point"}
}