{
  "type": "Feature",
  "properties": {
    "addr:full":"Langemarkseweg 26 Ieper (boezinge) West-Vlaanderen 8904",
    "addr:housenumber":"26",
    "addr:postcode":"8904",
    "addr:street":"Langemarkseweg",
    "iso:country":"BE",
    "sg:address":"Langemarkseweg 26",
    "sg:city":"Ieper (boezinge)",
    "sg:classifiers":[
        {
            "category":"Building & Trades",
            "subcategory":"Cleaning & Sanitation",
            "type":"Services"
        }
    ],
    "sg:phone":"+32 57 48 54 76",
    "sg:postcode":"8904",
    "sg:province":"West-Vlaanderen",
    "wof:name":"Osd-uniefog Bvba",
    "wof:placetype":"venue"
},
  "geometry": {"coordinates":[2.8812789917,50.8986473083],"type":"Point"}
}