{
  "type": "Feature",
  "properties": {
    "addr:full":"Avenue Albert Ier 129 Ottignies-louvain-la-neuve Brabant Wallon 1342",
    "addr:housenumber":"129",
    "addr:postcode":"1342",
    "addr:street":"Avenue Albert Ier",
    "iso:country":"BE",
    "sg:address":"Avenue Albert Ier 129",
    "sg:city":"Ottignies-louvain-la-neuve",
    "sg:orig_category":"Benzinestations and brandstoffen Herstellingen and onderhoud van auto's",
    "sg:phone":"+32 10 41 51 10",
    "sg:postcode":"1342",
    "sg:province":"Brabant Wallon",
    "wof:name":"Garage Berthet",
    "wof:placetype":"venue"
},
  "geometry": {"coordinates":[4.5709409714,50.6743087769],"type":"Point"}
}