{
  "type": "Feature",
  "properties": {
    "addr:full":"Bloemenlaan 11 Dilbeek (groot - Bijgaarden) Vlaams-Brabant 1702",
    "addr:housenumber":"11;1702",
    "addr:street":"Bloemenlaan;Groot Bijgaarden Vlaams-Brabant",
    "iso:country":"BE",
    "sg:address":"Bloemenlaan 11",
    "sg:city":"Dilbeek (groot - Bijgaarden)",
    "sg:classifiers":[
        {
            "category":"Health Services",
            "subcategory":"Health Practitioner",
            "type":"Services"
        }
    ],
    "sg:phone":"+32 2 306 03 86",
    "sg:postcode":"1702",
    "sg:province":"Vlaams-Brabant",
    "sg:tags":[
        "physiotherapist"
    ],
    "wof:name":"Trossaert Luc",
    "wof:placetype":"venue"
},
  "geometry": {"coordinates":[4.2537441254,50.8713378906],"type":"Point"}
}