{
  "type": "Feature",
  "properties": {
    "addr:full":"Groot-molenveldlaan 64 Grimbergen Vlaams-Brabant 1850",
    "addr:housenumber":"64",
    "addr:postcode":"1850",
    "addr:street":"Groot-Molenveldlaan",
    "iso:country":"BE",
    "sg:address":"Groot-molenveldlaan 64",
    "sg:city":"Grimbergen",
    "sg:orig_category":"Herstellingen and onderhoud van auto's",
    "sg:phone":"+32 2 251 72 01",
    "sg:postcode":"1850",
    "sg:province":"Vlaams-Brabant",
    "wof:name":"Nicolas Huyghe",
    "wof:placetype":"venue"
},
  "geometry": {"coordinates":[4.3975300789,50.9227142334],"type":"Point"}
}