{
  "type": "Feature",
  "properties": {
    "addr:full":"Erasme Ruelensvest 101 Leuven (heverlee) Vlaams-Brabant 3001",
    "addr:housenumber":"101",
    "addr:postcode":"3001",
    "addr:street":"Erasme Ruelensvest",
    "iso:country":"BE",
    "sg:address":"Erasme Ruelensvest 101",
    "sg:city":"Leuven (heverlee)",
    "sg:classifiers":[
        {
            "category":"Real Estate",
            "subcategory":"Architect",
            "type":"Services"
        }
    ],
    "sg:phone":"+32 16 22 44 22",
    "sg:postcode":"3001",
    "sg:province":"Vlaams-Brabant",
    "wof:name":"Claessens D",
    "wof:placetype":"venue"
},
  "geometry": {"coordinates":[4.7046380043,50.8680801392],"type":"Point"}
}