{
  "type": "Feature",
  "properties": {
    "addr:full":"Diestsestraat 83 Leuven Vlaams-Brabant 3000",
    "addr:housenumber":"83",
    "addr:postcode":"3000",
    "addr:street":"Diestsestraat",
    "iso:country":"BE",
    "sg:address":"Diestsestraat 83",
    "sg:city":"Leuven",
    "sg:classifiers":[
        {
            "category":"Shopping",
            "subcategory":"Clothing, Apparel, & Fashions",
            "type":"Retail Goods"
        }
    ],
    "sg:phone":"+32 16 58 35 94",
    "sg:postcode":"3000",
    "sg:province":"Vlaams-Brabant",
    "sg:tags":[
        "lady",
        "clothing",
        "-"
    ],
    "wof:name":"Laura Damesmode Nv",
    "wof:placetype":"venue"
},
  "geometry": {"coordinates":[4.7055401802,50.8804283142],"type":"Point"}
}