{
  "type": "Feature",
  "properties": {
    "addr:full":"Neerland 4 Belgium Antwerpen 2547",
    "addr:housenumber":"4",
    "addr:postcode":"2547",
    "addr:street":"Neerland",
    "iso:country":"BE",
    "sg:address":"Neerland 4",
    "sg:city":"Belgium",
    "sg:orig_category":"Ordinateurs and \u00e9quipement informatique",
    "sg:phone":"+32 3 455 85 27",
    "sg:postcode":"2547",
    "sg:province":"Antwerpen",
    "wof:name":"Freedom Computer",
    "wof:placetype":"venue"
},
  "geometry": {"coordinates":[4.4952139854,51.1217498779],"type":"Point"}
}