{
  "type": "Feature",
  "properties": {
    "iso:country":"BE",
    "sg:address":"Pouillou Fourneau 23",
    "sg:city":"Theux",
    "sg:classifiers":[
        {
            "category":"Professional",
            "subcategory":"Management & Consulting",
            "type":"Services"
        }
    ],
    "sg:phone":"+32 87 26 96 76",
    "sg:postcode":"4910",
    "sg:province":"Li\u00e8ge",
    "sg:tags":[
        "-",
        "processing",
        "data",
        "consultant"
    ],
    "wof:name":"A4c Ahead For Communication Sprl",
    "wof:placetype":"venue"
},
  "geometry": {"coordinates":[5.7964200974,50.5464515686],"type":"Point"}
}