{
  "type": "Feature",
  "properties": {
    "iso:country":"BE",
    "sg:address":"Driehoekstraat 60a",
    "sg:city":"Haaltert (kerksken)",
    "sg:classifiers":[
        {
            "category":"Food & Beverages",
            "subcategory":"Chocolate",
            "type":"Retail Goods"
        }
    ],
    "sg:phone":"+32 53 83 51 50",
    "sg:postcode":"9451",
    "sg:province":"Oost-Vlaanderen",
    "sg:tags":[
        "confectionery",
        "-"
    ],
    "wof:name":"Sweet Success",
    "wof:placetype":"venue"
},
  "geometry": {"coordinates":[3.9828579426,50.8870735168],"type":"Point"}
}