{
  "type": "Feature",
  "properties": {
    "addr:full":"Koolmijnlaan 43 Heusden-zolder (heusden) Limburg 3550",
    "addr:housenumber":"43",
    "addr:postcode":"3550",
    "addr:street":"Koolmijnlaan",
    "iso:country":"BE",
    "sg:address":"Koolmijnlaan 43",
    "sg:city":"Heusden-zolder (heusden)",
    "sg:classifiers":[
        {
            "category":"Shopping",
            "subcategory":"Bicycles & Sporting Goods",
            "type":"Retail Goods"
        }
    ],
    "sg:phone":"+32 11 57 16 56",
    "sg:postcode":"3550",
    "sg:province":"Limburg",
    "sg:tags":[
        "tyre"
    ],
    "wof:name":"Autobanden Erwin Nv",
    "wof:placetype":"venue"
},
  "geometry": {"coordinates":[5.2960758209,51.0383911133],"type":"Point"}
}