{
  "type": "Feature",
  "properties": {
    "iso:country":"BE",
    "sg:address":"Voorthoek 84",
    "sg:city":"Stekene",
    "sg:classifiers":[
        {
            "category":"Professional",
            "subcategory":"Computer Services",
            "type":"Services"
        }
    ],
    "sg:phone":"+32 3 789 03 93",
    "sg:postcode":"9190",
    "sg:province":"Oost-Vlaanderen",
    "sg:tags":[
        "-",
        "processing",
        "data",
        "software"
    ],
    "wof:name":"Inter Networks Belgium",
    "wof:placetype":"venue"
},
  "geometry": {"coordinates":[4.0495209694,51.2318992615],"type":"Point"}
}