{
  "type": "Feature",
  "properties": {
    "iso:country":"BE",
    "sg:address":"Oude Beekstraat 20",
    "sg:city":"Bilzen (munsterbilzen)",
    "sg:classifiers":[
        {
            "category":"Health Services",
            "subcategory":"Doctor",
            "type":"Services"
        }
    ],
    "sg:phone":"+32 89 41 46 30",
    "sg:postcode":"3740",
    "sg:province":"Limburg",
    "sg:tags":[
        "medicinephysicians",
        "surgeon"
    ],
    "wof:name":"Blauwens Frans",
    "wof:placetype":"venue"
},
  "geometry": {"coordinates":[5.5270600319,50.8937416077],"type":"Point"}
}