{
  "type": "Feature",
  "properties": {
    "iso:country":"BE",
    "sg:address":"Poststraat 106",
    "sg:city":"Lokeren",
    "sg:orig_category":"Forge, Moulage and Profilage des M\u00e9taux",
    "sg:phone":"+32 9 348 69 63",
    "sg:postcode":"9160",
    "sg:province":"Oost-Vlaanderen",
    "wof:name":"Guido Verhaegen",
    "wof:placetype":"venue"
},
  "geometry": {"coordinates":[3.995953083,51.1051101685],"type":"Point"}
}