{
  "type": "Feature",
  "properties": {
    "iso:country":"BE",
    "sg:address":"Rozendaalstraat 1",
    "sg:city":"Ieper",
    "sg:orig_category":"Diverse bouwafwerking and reiniging Gespecialiseerde residenti\u00eble bouw Woningbouw",
    "sg:phone":"+32 57 20 21 17",
    "sg:postcode":"8900",
    "sg:province":"West-Vlaanderen",
    "wof:name":"Hugo Sohie",
    "wof:placetype":"venue"
},
  "geometry": {"coordinates":[2.8833129406,50.8742027283],"type":"Point"}
}