{
  "type": "Feature",
  "properties": {
    "addr:full":"Square De Quinaux 14 Namur Namur 5100",
    "addr:housenumber":"14",
    "addr:postcode":"5100",
    "addr:street":"Square De Quinaux",
    "iso:country":"BE",
    "sg:address":"Square De Quinaux 14",
    "sg:city":"Namur",
    "sg:orig_category":"Plaatsen van vloer- and muurbekleding Schilders Verlichting and huishoudartikelen",
    "sg:phone":"+32 81 40 12 19",
    "sg:postcode":"5100",
    "sg:province":"Namur",
    "wof:name":"Meseguer & Fils",
    "wof:placetype":"venue"
},
  "geometry": {"coordinates":[4.8713750839,50.4566345215],"type":"Point"}
}