{
  "type": "Feature",
  "properties": {
    "addr:full":"Rue De L'abbaye 29 H\u00e9l\u00e9cine (neerheylissem) Brabant Wallon 1357",
    "addr:housenumber":"29",
    "addr:postcode":"1357",
    "addr:street":"Rue De L'Abbaye;Wallon",
    "iso:country":"BE",
    "sg:address":"Rue De L'abbaye 29",
    "sg:city":"H\u00e9l\u00e9cine (neerheylissem)",
    "sg:classifiers":[
        {
            "category":"Bakery",
            "type":"Food & Drink"
        }
    ],
    "sg:phone":"+32 19 65 55 90",
    "sg:postcode":"1357",
    "sg:province":"Brabant Wallon",
    "sg:tags":[
        "confectioner",
        "baker"
    ],
    "wof:name":"Deroloffe J",
    "wof:placetype":"venue"
},
  "geometry": {"coordinates":[4.9782118797,50.7480201721],"type":"Point"}
}