{
  "type": "Feature",
  "properties": {
    "iso:country":"BE",
    "sg:address":"Krepelstraat 150",
    "sg:city":"Ninove",
    "sg:orig_category":"Eleveurs de bovins",
    "sg:phone":"+32 54 33 46 91",
    "sg:postcode":"9400",
    "sg:province":"Oost-Vlaanderen",
    "wof:name":"Joseph Bouvaert",
    "wof:placetype":"venue"
},
  "geometry": {"coordinates":[4.0023288727,50.7936058044],"type":"Point"}
}