{
  "type": "Feature",
  "properties": {
    "addr:full":"Wijnegem Shopping Center 46-47 Wijnegem Antwerpen 2110",
    "addr:housenumber":"46-47",
    "addr:postcode":"2110",
    "iso:country":"BE",
    "sg:address":"Wijnegem Shopping Center 46-47",
    "sg:city":"Wijnegem",
    "sg:classifiers":[
        {
            "category":"Shopping",
            "subcategory":"Clothing, Apparel, & Fashions",
            "type":"Retail Goods"
        }
    ],
    "sg:phone":"+32 3 354 07 58",
    "sg:postcode":"2110",
    "sg:province":"Antwerpen",
    "sg:tags":[
        "lady",
        "clothing",
        "-"
    ],
    "wof:name":"Trent",
    "wof:placetype":"venue"
},
  "geometry": {"coordinates":[4.5248470306,51.2279434204],"type":"Point"}
}