{
  "type": "Feature",
  "properties": {
    "iso:country":"BE",
    "sg:address":"Chauss\u00e9e De W\u00e9gimont 87",
    "sg:city":"Soumagne (ayeneux)",
    "sg:classifiers":[
        {
            "category":"Arts & Performance",
            "subcategory":"Arts Center",
            "type":"Entertainment"
        }
    ],
    "sg:phone":"+32 4 377 34 26",
    "sg:postcode":"4630",
    "sg:province":"Li\u00e8ge",
    "sg:tags":[
        "slide"
    ],
    "wof:name":"New Slide Sc",
    "wof:placetype":"venue"
},
  "geometry": {"coordinates":[5.7388620377,50.6098442078],"type":"Point"}
}