{
  "type": "Feature",
  "properties": {
    "iso:country":"BE",
    "sg:address":"Aseindestraat 7",
    "sg:city":"Kortessem",
    "sg:orig_category":"Beautyfarms, relaxatie and lichamelijk welzijn Schoonheidssalons",
    "sg:phone":"+32 11 37 76 19",
    "sg:postcode":"3720",
    "sg:province":"Limburg",
    "wof:name":"Estetiek Tanita",
    "wof:placetype":"venue"
},
  "geometry": {"coordinates":[5.3773531914,50.8678817749],"type":"Point"}
}