{
  "type": "Feature",
  "properties": {
    "iso:country":"BE",
    "sg:address":"Heuvelstraat 80",
    "sg:city":"Boechout",
    "sg:orig_category":"Notarissen",
    "sg:phone":"+32 3 454 14 54",
    "sg:postcode":"2530",
    "sg:province":"Antwerpen",
    "wof:name":"Ph. Coppens",
    "wof:placetype":"venue"
},
  "geometry": {"coordinates":[4.4929900169,51.1624603271],"type":"Point"}
}