{
  "type": "Feature",
  "properties": {
    "iso:country":"BE",
    "sg:address":"Wijnendalestraat 65",
    "sg:city":"Torhout",
    "sg:orig_category":"Boomkwekerijen",
    "sg:phone":"+32 50 21 22 84",
    "sg:postcode":"8820",
    "sg:province":"West-Vlaanderen",
    "wof:name":"Rita Cool",
    "wof:placetype":"venue"
},
  "geometry": {"coordinates":[3.0749359131,51.0973930359],"type":"Point"}
}