{
  "type": "Feature",
  "properties": {
    "iso:country":"BE",
    "sg:address":".",
    "sg:city":"Zomergem (groot)",
    "sg:orig_category":"Apotheken",
    "sg:phone":"+32 900 10 500",
    "sg:postcode":"9930",
    "sg:province":"Oost-Vlaanderen",
    "wof:name":"Apothekers Van Wacht",
    "wof:placetype":"venue"
},
  "geometry": {"coordinates":[3.5583870411,51.1183052063],"type":"Point"}
}