{
  "type": "Feature",
  "properties": {
    "iso:country":"BE",
    "sg:address":"Churchillsteenweg 17",
    "sg:city":"Aalst",
    "sg:orig_category":"Diverse producten Gh Platenmaatschappijen",
    "sg:phone":"+32 53 83 52 04",
    "sg:postcode":"9320",
    "sg:province":"Oost-Vlaanderen",
    "wof:name":"Impuls International",
    "wof:placetype":"venue"
},
  "geometry": {"coordinates":[4.0553851128,50.9209976196],"type":"Point"}
}