{
  "type": "Feature",
  "properties": {
    "iso:country":"BE",
    "sg:address":"Chauss\u00e9e De Vleurgat 299",
    "sg:city":"Bruxelles (ixelles)",
    "sg:classifiers":[
        {
            "category":"Shopping",
            "subcategory":"Hobbies, Toys, & Games",
            "type":"Retail Goods"
        }
    ],
    "sg:phone":"+32 2 347 35 40",
    "sg:postcode":"1050",
    "sg:province":"Bruxelles-Capitale",
    "sg:tags":[
        "computer",
        "video"
    ],
    "wof:name":"Cyberspace Sprl",
    "wof:placetype":"venue"
},
  "geometry": {"coordinates":[4.3663649559,50.8173217773],"type":"Point"}
}