{
  "type": "Feature",
  "properties": {
    "iso:country":"BE",
    "sg:address":"Kasteelstraat 8",
    "sg:city":"Dilbeek",
    "sg:orig_category":"Boekhouders",
    "sg:phone":"+32 2 567 00 83",
    "sg:postcode":"1703",
    "sg:province":"Vlaams-Brabant",
    "wof:name":"Simonne Lauwaert",
    "wof:placetype":"venue"
},
  "geometry": {"coordinates":[4.205206871,50.8365898132],"type":"Point"}
}