{
  "type": "Feature",
  "properties": {
    "addr:full":"Guido Gezellelaan 60 Deinze Oost-Vlaanderen 9800",
    "addr:housenumber":"60",
    "addr:postcode":"9800",
    "addr:street":"Guido Gezellelaan",
    "iso:country":"BE",
    "sg:address":"Guido Gezellelaan 60",
    "sg:city":"Deinze",
    "sg:orig_category":"Notarissen",
    "sg:phone":"+32 9 386 13 30",
    "sg:postcode":"9800",
    "sg:province":"Oost-Vlaanderen",
    "wof:name":"P. Pauwels",
    "wof:placetype":"venue"
},
  "geometry": {"coordinates":[3.5327010155,50.9835243225],"type":"Point"}
}