{
  "type": "Feature",
  "properties": {
    "addr:full":"Heirbaan 19 Deinze Oost-Vlaanderen 9800",
    "addr:housenumber":"19",
    "addr:postcode":"9800",
    "addr:street":"Heirbaan",
    "iso:country":"BE",
    "sg:address":"Heirbaan 19",
    "sg:city":"Deinze",
    "sg:orig_category":"Rundveehouders Varkenskwekers",
    "sg:phone":"+32 51 63 60 36",
    "sg:postcode":"9800",
    "sg:province":"Oost-Vlaanderen",
    "wof:name":"Johan Malfait",
    "wof:placetype":"venue"
},
  "geometry": {"coordinates":[3.4500861168,50.9626083374],"type":"Point"}
}