{
  "type": "Feature",
  "properties": {
    "addr:full":"Witte Baliestraat 3 Diksmuide West-Vlaanderen 8600",
    "addr:housenumber":"3",
    "addr:postcode":"8600",
    "addr:street":"Witte Baliestraat",
    "iso:country":"BE",
    "sg:address":"Witte Baliestraat 3",
    "sg:city":"Diksmuide",
    "sg:orig_category":"Voertuigen",
    "sg:phone":"+32 51 50 31 20",
    "sg:postcode":"8600",
    "sg:province":"West-Vlaanderen",
    "wof:name":"Fa. Tanghe A. & Zn.",
    "wof:placetype":"venue"
},
  "geometry": {"coordinates":[2.893517971,51.0973777771],"type":"Point"}
}