{
  "type": "Feature",
  "properties": {
    "iso:country":"BE",
    "sg:address":"Chauss\u00c9e De Dinant 119",
    "sg:city":"Anhee",
    "sg:orig_category":"Loodgieterij and centrale verwarming Gh",
    "sg:phone":"+32 82 61 33 66",
    "sg:postcode":"5537",
    "sg:province":"Namur",
    "wof:name":"Philippe Faeles",
    "wof:placetype":"venue"
},
  "geometry": {"coordinates":[4.8927950859,50.2973403931],"type":"Point"}
}