{
  "type": "Feature",
  "properties": {
    "addr:full":"Rue De La Gare 4 Malmedy Li\u00e8ge 4960",
    "addr:housenumber":"4",
    "addr:postcode":"4960",
    "addr:street":"Rue De La Gare",
    "iso:country":"BE",
    "sg:address":"Rue De La Gare 4",
    "sg:city":"Malmedy",
    "sg:classifiers":[
        {
            "category":"Health Services",
            "subcategory":"Doctor",
            "type":"Services"
        }
    ],
    "sg:phone":"+32 80 33 06 78",
    "sg:postcode":"4960",
    "sg:province":"Li\u00e8ge",
    "sg:tags":[
        "medicinephysicians",
        "surgeon"
    ],
    "wof:name":"Choul P",
    "wof:placetype":"venue"
},
  "geometry": {"coordinates":[6.0313057899,50.4245262146],"type":"Point"}
}