{
  "type": "Feature",
  "properties": {
    "iso:country":"BE",
    "sg:address":"Rue Nihar 3",
    "sg:city":"Seraing",
    "sg:orig_category":"R\u00e9parations d'appareils \u00e9lectrom\u00e9nagers. Electrom\u00e9nager, t\u00e9l\u00e9visions and radios. Mat\u00e9riel de T\u00e9l\u00e9com",
    "sg:phone":"+32 4 233 78 31",
    "sg:postcode":"4101",
    "sg:province":"Li\u00e8ge",
    "wof:name":"Kr\u00cbfel",
    "wof:placetype":"venue"
},
  "geometry": {"coordinates":[5.5024199486,50.6139183044],"type":"Point"}
}