{
  "type": "Feature",
  "properties": {
    "iso:country":"BE",
    "sg:address":"Avenue De La P\u00e9pini\u00e8re 6",
    "sg:city":"Rhode-saint-gen\u00e8se",
    "sg:classifiers":[
        {
            "category":"Shopping",
            "subcategory":"Computers & Home Electronics",
            "type":"Retail Goods"
        }
    ],
    "sg:phone":"+32 2 381 05 79",
    "sg:postcode":"1640",
    "sg:province":"Vlaams-Brabant",
    "sg:tags":[
        "personal",
        "-",
        "processing",
        "data"
    ],
    "wof:name":"Double D Computers",
    "wof:placetype":"venue"
},
  "geometry": {"coordinates":[4.3593959808,50.751701355],"type":"Point"}
}