{
  "type": "Feature",
  "properties": {
    "addr:full":"Quai De Rome 24b93 Li\u00c8ge Li\u00e8ge 4000",
    "addr:housenumber":"24b93",
    "addr:postcode":"4000",
    "addr:street":"Quai De Rome",
    "iso:country":"BE",
    "sg:address":"Quai De Rome 24b93",
    "sg:city":"Li\u00c8ge",
    "sg:orig_category":"M\u00e9decins and sp\u00e9cialistes",
    "sg:phone":"+32 4 253 05 73",
    "sg:postcode":"4000",
    "sg:province":"Li\u00e8ge",
    "wof:name":"Yvette Monard",
    "wof:placetype":"venue"
},
  "geometry": {"coordinates":[5.5750279427,50.6251754761],"type":"Point"}
}