{
  "type": "Feature",
  "properties": {
    "addr:full":"Albert I Laan 13 Nieuwpoort West-Vlaanderen 8620",
    "addr:housenumber":"13",
    "addr:postcode":"8620",
    "addr:street":"Albert I Laan",
    "iso:country":"BE",
    "sg:address":"Albert I Laan 13",
    "sg:city":"Nieuwpoort",
    "sg:orig_category":"Herstelling aan huis van huishoudartikelen",
    "sg:phone":"+32 58 23 56 64",
    "sg:postcode":"8620",
    "sg:province":"West-Vlaanderen",
    "wof:name":"Sani-centrum Peter Ostyn",
    "wof:placetype":"venue"
},
  "geometry": {"coordinates":[2.7401540279,51.1380119324],"type":"Point"}
}