{
  "type": "Feature",
  "properties": {
    "iso:country":"BE",
    "sg:address":"Lindestraat 40",
    "sg:city":"Gooik",
    "sg:classifiers":[
        {
            "category":"Cafe",
            "type":"Food & Drink"
        }
    ],
    "sg:phone":"+32 54 56 73 41",
    "sg:postcode":"1755",
    "sg:province":"Vlaams-Brabant",
    "sg:tags":[
        "caf\u00e9s"
    ],
    "wof:name":"Erwin Ophalvens",
    "wof:placetype":"venue"
},
  "geometry": {"coordinates":[4.0979371071,50.7964706421],"type":"Point"}
}