{
  "type": "Feature",
  "properties": {
    "addr:full":"Rue Hamoir 1 La Louviere Hainaut 7100",
    "addr:housenumber":"1",
    "addr:postcode":"7100",
    "addr:street":"Rue Hamoir",
    "iso:country":"BE",
    "sg:address":"Rue Hamoir 1",
    "sg:city":"La Louviere",
    "sg:orig_category":"Services de t\u00e9l\u00e9communications",
    "sg:phone":"+32 64 26 56 11",
    "sg:postcode":"7100",
    "sg:province":"Hainaut",
    "wof:name":"Ideatel",
    "wof:placetype":"venue"
},
  "geometry": {"coordinates":[4.1867599487,50.4748306274],"type":"Point"}
}