{
  "type": "Feature",
  "properties": {
    "iso:country":"BE",
    "sg:address":"Chauss\u00c9e Victor Lampe 134",
    "sg:city":"Lessines",
    "sg:orig_category":"Eleveurs de bovins",
    "sg:phone":"+32 68 33 37 27",
    "sg:postcode":"7866",
    "sg:province":"Hainaut",
    "wof:name":"Andr\u00c9 Deronne",
    "wof:placetype":"venue"
},
  "geometry": {"coordinates":[3.8632910252,50.6800308228],"type":"Point"}
}