{
  "type": "Feature",
  "properties": {
    "addr:full":"Tivolilaan 94 Mechelen Antwerpen 2800",
    "addr:housenumber":"94",
    "addr:postcode":"2800",
    "addr:street":"Tivolilaan",
    "iso:country":"BE",
    "sg:address":"Tivolilaan 94",
    "sg:city":"Mechelen",
    "sg:classifiers":[
        {
            "category":"Health Services",
            "subcategory":"Health Practitioner",
            "type":"Services"
        }
    ],
    "sg:phone":"+32 15 33 67 06",
    "sg:postcode":"2800",
    "sg:province":"Antwerpen",
    "sg:tags":[
        "physiotherapist"
    ],
    "wof:name":"Detavernier Bart",
    "wof:placetype":"venue"
},
  "geometry": {"coordinates":[4.4770870209,51.047668457],"type":"Point"}
}