{
  "type": "Feature",
  "properties": {
    "iso:country":"BE",
    "sg:address":"Krijtekerkweg 6",
    "sg:city":"Gent",
    "sg:orig_category":"Ordinateurs and \u00e9quipement informatique",
    "sg:phone":"+32 9 251 12 85",
    "sg:postcode":"9041",
    "sg:province":"Oost-Vlaanderen",
    "wof:name":"Fa. Danco",
    "wof:placetype":"venue"
},
  "geometry": {"coordinates":[3.7723839283,51.0832138062],"type":"Point"}
}