{
  "type": "Feature",
  "properties": {
    "addr:full":"Westelsebaan 141 Scherpenheuvel-zichem (averbode) Vlaams-Brabant 3271",
    "addr:housenumber":"141",
    "addr:postcode":"3271",
    "addr:street":"Scherpenheuvel-Zichem",
    "iso:country":"BE",
    "sg:address":"Westelsebaan 141",
    "sg:city":"Scherpenheuvel-zichem (averbode)",
    "sg:classifiers":[
        {
            "category":"Bars & Pubs",
            "type":"Food & Drink"
        }
    ],
    "sg:phone":"+32 13 78 30 02",
    "sg:postcode":"3271",
    "sg:province":"Vlaams-Brabant",
    "sg:tags":[
        "tavern"
    ],
    "wof:name":"Mrs Rose",
    "wof:placetype":"venue"
},
  "geometry": {"coordinates":[4.9809098244,51.0286979675],"type":"Point"}
}