{
  "type": "Feature",
  "properties": {
    "addr:full":"Mezegemstraat 11b1 Izegem West-Vlaanderen 8870",
    "addr:housenumber":"11b1",
    "addr:postcode":"8870",
    "addr:street":"Mezegemstraat",
    "iso:country":"BE",
    "sg:address":"Mezegemstraat 11b1",
    "sg:city":"Izegem",
    "sg:orig_category":"Producteurs de fruits. Producteurs de l\u00e9gumes",
    "sg:phone":"+32 51 30 78 68",
    "sg:postcode":"8870",
    "sg:province":"West-Vlaanderen",
    "wof:name":"Rudi Pattyn",
    "wof:placetype":"venue"
},
  "geometry": {"coordinates":[3.1798899174,50.9414825439],"type":"Point"}
}