{
  "type": "Feature",
  "properties": {
    "iso:country":"BE",
    "sg:address":"Rue Des Chapeliers 23",
    "sg:city":"Tournai",
    "sg:classifiers":[
        {
            "category":"Shopping",
            "subcategory":"Clothing, Apparel, & Fashions",
            "type":"Retail Goods"
        }
    ],
    "sg:phone":"+32 69 22 18 75",
    "sg:postcode":"7500",
    "sg:province":"Hainaut",
    "sg:tags":[
        "clothing",
        "-",
        "gentleman"
    ],
    "wof:name":"Yentl",
    "wof:placetype":"venue"
},
  "geometry": {"coordinates":[3.3896560669,50.6058158875],"type":"Point"}
}