{
  "type": "Feature",
  "properties": {
    "addr:full":"Nijverheidslaan 1524 Opglabbeek Limburg 3660",
    "addr:postcode":"1524 opglabbeek;3660",
    "addr:street":"Nijverheidslaan",
    "iso:country":"BE",
    "sg:address":"Nijverheidslaan 1524",
    "sg:city":"Opglabbeek",
    "sg:classifiers":[
        {
            "category":"Building & Trades",
            "subcategory":"Locksmith",
            "type":"Services"
        }
    ],
    "sg:phone":"+32 89 86 90 90",
    "sg:postcode":"3660",
    "sg:province":"Limburg",
    "sg:tags":[
        "roofing",
        "industrial"
    ],
    "wof:name":"Kimmenade Belgium Nv",
    "wof:placetype":"venue"
},
  "geometry": {"coordinates":[5.54433918,51.0415420532],"type":"Point"}
}