{
  "type": "Feature",
  "properties": {
    "addr:full":"Nervierstraat 74 Asse Vlaams-Brabant 1730",
    "addr:housenumber":"74",
    "addr:postcode":"1730",
    "addr:street":"Nervierstraat",
    "iso:country":"BE",
    "sg:address":"Nervierstraat 74",
    "sg:city":"Asse",
    "sg:orig_category":"Diensten voor huisdieren Huisdieren and benodigdheden Royal Canin",
    "sg:phone":"+32 2 452 97 23",
    "sg:postcode":"1730",
    "sg:province":"Vlaams-Brabant",
    "wof:name":"Samoya Aelbrecht",
    "wof:placetype":"venue"
},
  "geometry": {"coordinates":[4.1889638901,50.9174003601],"type":"Point"}
}