{
  "type": "Feature",
  "properties": {
    "iso:country":"BE",
    "sg:address":"Fonds De Bouvignes 20",
    "sg:city":"Dinant",
    "sg:classifiers":[
        {
            "category":"Travel",
            "subcategory":"Resort",
            "type":"Entertainment"
        }
    ],
    "sg:phone":"+32 82 22 60 81",
    "sg:postcode":"5500",
    "sg:province":"Namur",
    "sg:tags":[
        "rental",
        "accomodation",
        "holiday",
        "-"
    ],
    "wof:name":"Poudrerie",
    "wof:placetype":"venue"
},
  "geometry": {"coordinates":[4.9454951286,50.2631988525],"type":"Point"}
}