{
  "type": "Feature",
  "properties": {
    "addr:full":"Oudstrijderslaan 24 Lendelede West-Vlaanderen 8860",
    "addr:housenumber":"24",
    "addr:postcode":"8860",
    "addr:street":"Oudstrijderslaan",
    "iso:country":"BE",
    "sg:address":"Oudstrijderslaan 24",
    "sg:city":"Lendelede",
    "sg:classifiers":[
        {
            "category":"Personal",
            "subcategory":"Beauty Salon",
            "type":"Services"
        }
    ],
    "sg:phone":"+32 51 30 30 21",
    "sg:postcode":"8860",
    "sg:province":"West-Vlaanderen",
    "sg:tags":[
        "de",
        "coiffure"
    ],
    "wof:name":"Kapsalon Mieke",
    "wof:placetype":"venue"
},
  "geometry": {"coordinates":[3.2327780724,50.8875350952],"type":"Point"}
}