{
  "type": "Feature",
  "properties": {
    "addr:full":"Rue Montagne Aux Herbes Potag\u00c8res 7 Brussel/bruxelles Bruxelles-Capitale 1000",
    "addr:housenumber":"7",
    "addr:postcode":"1000",
    "addr:street":"Rue Montagne Aux Herbes Potage\u0300Res;/",
    "iso:country":"BE",
    "sg:address":"Rue Montagne Aux Herbes Potag\u00c8res 7",
    "sg:city":"Brussel/bruxelles",
    "sg:classifiers":[
        {
            "category":"Cafe",
            "type":"Food & Drink"
        }
    ],
    "sg:phone":"+32 2 513 13 18",
    "sg:postcode":"1000",
    "sg:province":"Bruxelles-Capitale",
    "sg:tags":[
        "caf\u00e9s"
    ],
    "wof:name":"A La Mort Subite",
    "wof:placetype":"venue"
},
  "geometry": {"coordinates":[4.3562340736,50.8485603333],"type":"Point"}
}