{
  "type": "Feature",
  "properties": {
    "addr:full":"Sint-paulusstraat 50 Oostende West-Vlaanderen 8400",
    "addr:housenumber":"50",
    "addr:postcode":"8400",
    "addr:street":"Sint-Paulusstraat",
    "iso:country":"BE",
    "sg:address":"Sint-paulusstraat 50",
    "sg:city":"Oostende",
    "sg:orig_category":"Salles de spectacles",
    "sg:phone":"+32 59 80 89 05",
    "sg:postcode":"8400",
    "sg:province":"West-Vlaanderen",
    "wof:name":"Galerij Emils",
    "wof:placetype":"venue"
},
  "geometry": {"coordinates":[2.9206209183,51.230255127],"type":"Point"}
}