{
  "type": "Feature",
  "properties": {
    "addr:full":"Hovestraat 12 Edegem Antwerpen 2650",
    "addr:housenumber":"12",
    "addr:postcode":"2650",
    "addr:street":"Hovestraat",
    "iso:country":"BE",
    "sg:address":"Hovestraat 12",
    "sg:city":"Edegem",
    "sg:classifiers":[
        {
            "category":"Shopping",
            "subcategory":"Clothing, Apparel, & Fashions",
            "type":"Retail Goods"
        }
    ],
    "sg:phone":"+32 3 458 57 92",
    "sg:postcode":"2650",
    "sg:province":"Antwerpen",
    "sg:tags":[
        "lady",
        "clothing",
        "-"
    ],
    "wof:name":"Passe Partout",
    "wof:placetype":"venue"
},
  "geometry": {"coordinates":[4.4459347725,51.1556587219],"type":"Point"}
}