{
  "type": "Feature",
  "properties": {
    "addr:full":"Stationsstraat 36 Puurs Antwerpen 2870",
    "addr:housenumber":"36",
    "addr:postcode":"2870",
    "addr:street":"Stationsstraat",
    "iso:country":"BE",
    "sg:address":"Stationsstraat 36",
    "sg:city":"Puurs",
    "sg:orig_category":"Peinture. Rev\u00eatements pour sols and murs",
    "sg:phone":"+32 3 889 16 36",
    "sg:postcode":"2870",
    "sg:province":"Antwerpen",
    "wof:name":"Coeckelbergh-van Dam",
    "wof:placetype":"venue"
},
  "geometry": {"coordinates":[4.2816619873,51.0769500732],"type":"Point"}
}