{
  "type": "Feature",
  "properties": {
    "iso:country":"BE",
    "sg:address":"Pottatenhuizen 13",
    "sg:city":"Westerlo",
    "sg:orig_category":"Eleveurs de bovins",
    "sg:phone":"+32 14 26 55 68",
    "sg:postcode":"2260",
    "sg:province":"Antwerpen",
    "wof:name":"Frans Van Bylen",
    "wof:placetype":"venue"
},
  "geometry": {"coordinates":[4.8772950172,51.1211662292],"type":"Point"}
}