{
  "type": "Feature",
  "properties": {
    "iso:country":"BE",
    "sg:address":"Avenue De France 28",
    "sg:city":"Maubeuge",
    "sg:classifiers":[
        {
            "category":"Shopping",
            "subcategory":"Optician",
            "type":"Retail Goods"
        }
    ],
    "sg:phone":"+33 3 27 62 20 00",
    "sg:postcode":"59600",
    "sg:tags":[
        "-"
    ],
    "wof:name":"Optique De France",
    "wof:placetype":"venue"
},
  "geometry": {"coordinates":[3.973845005,50.2786636353],"type":"Point"}
}