{
  "type": "Feature",
  "properties": {
    "iso:country":"BE",
    "sg:address":"Chauss\u00c9e De Mons 131",
    "sg:city":"Anderlues",
    "sg:orig_category":"RESTAURANTS: DANCINGS AND BO\u00ceTES DE NUIT",
    "sg:phone":"+32 71 54 35 98",
    "sg:postcode":"6150",
    "sg:province":"Hainaut",
    "wof:name":"Star Rock Caf\u00c9",
    "wof:placetype":"venue"
},
  "geometry": {"coordinates":[4.2854700089,50.4062919617],"type":"Point"}
}