{
  "type": "Feature",
  "properties": {
    "iso:country":"BE",
    "sg:address":"Savaanstraat 13",
    "sg:city":"Gent",
    "sg:classifiers":[
        {
            "category":"Parking",
            "subcategory":"Garage",
            "type":"Transportation"
        }
    ],
    "sg:phone":"+32 9 233 66 35",
    "sg:postcode":"9000",
    "sg:province":"Oost-Vlaanderen",
    "wof:name":"City Parking",
    "wof:placetype":"venue"
},
  "geometry": {"coordinates":[3.721914053,51.0487670898],"type":"Point"}
}