{
  "type": "Feature",
  "properties": {
    "iso:country":"BE",
    "sg:address":"Meersstraat 235",
    "sg:city":"Ternat",
    "sg:orig_category":"Eleveurs de bovins",
    "sg:phone":"+32 2 582 25 87",
    "sg:postcode":"1742",
    "sg:province":"Vlaams-Brabant",
    "wof:name":"Joannes De Wever",
    "wof:placetype":"venue"
},
  "geometry": {"coordinates":[4.1334080696,50.8817024231],"type":"Point"}
}