{
  "type": "Feature",
  "properties": {
    "addr:full":"Rue De La Chauss\u00c9e 33 Mons Hainaut 7000",
    "addr:housenumber":"33",
    "addr:postcode":"7000",
    "addr:street":"Rue De La Chausse\u0301E;Hainaut",
    "iso:country":"BE",
    "sg:address":"Rue De La Chauss\u00c9e 33",
    "sg:city":"Mons",
    "sg:orig_category":"Opticiens",
    "sg:phone":"+32 65 31 41 31",
    "sg:postcode":"7000",
    "sg:province":"Hainaut",
    "wof:name":"Clara-clara",
    "wof:placetype":"venue"
},
  "geometry": {"coordinates":[3.951351881,50.4530067444],"type":"Point"}
}