{
  "type": "Feature",
  "properties": {
    "iso:country":"BE",
    "sg:address":"Avenue De Broqueville 258b4",
    "sg:city":"Sint-lambrechts-woluwe/woluwe-saint-lambert",
    "sg:orig_category":"Location de logements sociaux",
    "sg:phone":"+32 2 762 58 95",
    "sg:postcode":"1200",
    "sg:province":"Bruxelles-Capitale",
    "wof:name":"Les Locataires R\u00c9unis",
    "wof:placetype":"venue"
},
  "geometry": {"coordinates":[4.421107769,50.842502594],"type":"Point"}
}