{
  "type": "Feature",
  "properties": {
    "addr:full":"Appeldonkstraat 173 Willebroek Antwerpen 2830",
    "addr:housenumber":"173",
    "addr:postcode":"2830",
    "addr:street":"Appeldonkstraat",
    "iso:country":"BE",
    "sg:address":"Appeldonkstraat 173",
    "sg:city":"Willebroek",
    "sg:orig_category":"R\u00e9cup\u00e9ration de mati\u00e8res m\u00e9talliques recyclables and d\u00e9molisseurs de voitures",
    "sg:phone":"+32 3 866 02 55",
    "sg:postcode":"2830",
    "sg:province":"Antwerpen",
    "wof:name":"Fa. Ceara",
    "wof:placetype":"venue"
},
  "geometry": {"coordinates":[4.352722168,51.0705490112],"type":"Point"}
}