{
  "type": "Feature",
  "properties": {
    "iso:country":"BE",
    "sg:address":"Zeedijk 230-231",
    "sg:city":"Blankenberge",
    "sg:classifiers":[
        {
            "category":"Shopping",
            "subcategory":"Hobbies, Toys, & Games",
            "type":"Retail Goods"
        }
    ],
    "sg:phone":"+32 50 41 82 52",
    "sg:postcode":"8370",
    "sg:province":"West-Vlaanderen",
    "sg:tags":[
        "toy",
        "-"
    ],
    "wof:name":"Holiday Shop",
    "wof:placetype":"venue"
},
  "geometry": {"coordinates":[3.1396501064,51.3189086914],"type":"Point"}
}