{
  "type": "Feature",
  "properties": {
    "addr:full":"Beauduinstraat 1 Tienen Vlaams-Brabant 3300",
    "addr:housenumber":"1",
    "addr:postcode":"3300",
    "addr:street":"Beauduinstraat",
    "iso:country":"BE",
    "sg:address":"Beauduinstraat 1",
    "sg:city":"Tienen",
    "sg:classifiers":[
        {
            "category":"Personal",
            "subcategory":"Beauty Salon",
            "type":"Services"
        }
    ],
    "sg:phone":"+32 16 81 95 60",
    "sg:postcode":"3300",
    "sg:province":"Vlaams-Brabant",
    "sg:tags":[
        "lady",
        "-",
        "hairdressing"
    ],
    "wof:name":"Philippe",
    "wof:placetype":"venue"
},
  "geometry": {"coordinates":[4.9407548904,50.8055534363],"type":"Point"}
}