{
  "type": "Feature",
  "properties": {
    "iso:country":"BE",
    "sg:address":"Avenue Paul Pastur 392",
    "sg:city":"Charleroi (mont-sur-marchienne)",
    "sg:classifiers":[
        {
            "category":"Freight",
            "type":"Transportation"
        }
    ],
    "sg:phone":"+32 71 43 42 12",
    "sg:postcode":"6032",
    "sg:province":"Hainaut",
    "sg:tags":[
        "-",
        "transport"
    ],
    "wof:name":"Hemberg Fils Sprl",
    "wof:placetype":"venue"
},
  "geometry": {"coordinates":[4.4210209846,50.3978233337],"type":"Point"}
}