{
  "type": "Feature",
  "properties": {
    "iso:country":"BE",
    "sg:address":"Rue Vandercoilden 40",
    "sg:city":"Mouscron (herseaux)",
    "sg:classifiers":[
        {
            "category":"Building & Trades",
            "subcategory":"Construction",
            "type":"Services"
        }
    ],
    "sg:phone":"+32 56 84 00 72",
    "sg:postcode":"7712",
    "sg:province":"Hainaut",
    "sg:tags":[
        "carpenter"
    ],
    "wof:name":"Parent B",
    "wof:placetype":"venue"
},
  "geometry": {"coordinates":[3.2360100746,50.7227210999],"type":"Point"}
}