{
  "type": "Feature",
  "properties": {
    "addr:full":"Chemin Du Congo 55 Theux (la Reid) Li\u00e8ge 4910",
    "addr:housenumber":"55",
    "addr:postcode":"4910",
    "addr:street":"Chemin Du Congo;La Reid",
    "iso:country":"BE",
    "sg:address":"Chemin Du Congo 55",
    "sg:city":"Theux (la Reid)",
    "sg:classifiers":[
        {
            "category":"Building & Trades",
            "subcategory":"Pest Control",
            "type":"Services"
        }
    ],
    "sg:phone":"+32 87 37 68 51",
    "sg:postcode":"4910",
    "sg:province":"Li\u00e8ge",
    "sg:tags":[
        "painting",
        "contractor"
    ],
    "wof:name":"Jcv Decor",
    "wof:placetype":"venue"
},
  "geometry": {"coordinates":[5.8019189835,50.4593696594],"type":"Point"}
}