{
  "type": "Feature",
  "properties": {
    "addr:full":"Peerderbaan 73 Bree Limburg 3960",
    "addr:housenumber":"73",
    "addr:postcode":"3960",
    "addr:street":"Peerderbaan",
    "iso:country":"BE",
    "sg:address":"Peerderbaan 73",
    "sg:city":"Bree",
    "sg:classifiers":[
        {
            "category":"Health Services",
            "subcategory":"Health Practitioner",
            "type":"Services"
        }
    ],
    "sg:phone":"+32 89 47 13 01",
    "sg:postcode":"3960",
    "sg:province":"Limburg",
    "sg:tags":[
        "physiotherapist"
    ],
    "wof:name":"Molemans Jos",
    "wof:placetype":"venue"
},
  "geometry": {"coordinates":[5.5944190025,51.1405677795],"type":"Point"}
}