{
  "type": "Feature",
  "properties": {
    "addr:full":"Leliestraat 26 Diepenbeek Limburg 3590",
    "addr:housenumber":"26",
    "addr:postcode":"3590",
    "addr:street":"Leliestraat",
    "iso:country":"BE",
    "sg:address":"Leliestraat 26",
    "sg:city":"Diepenbeek",
    "sg:orig_category":"Epiceries",
    "sg:phone":"+32 11 33 24 82",
    "sg:postcode":"3590",
    "sg:province":"Limburg",
    "wof:name":"Jan Lambrichts",
    "wof:placetype":"venue"
},
  "geometry": {"coordinates":[5.4683499336,50.9274024963],"type":"Point"}
}