{
  "type": "Feature",
  "properties": {
    "addr:full":"Sportlaan 20 Beringen (koersel) Limburg 3582",
    "addr:housenumber":"20",
    "addr:postcode":"3582",
    "addr:street":"Sportlaan",
    "iso:country":"BE",
    "sg:address":"Sportlaan 20",
    "sg:city":"Beringen (koersel)",
    "sg:classifiers":[
        {
            "category":"Personal",
            "subcategory":"Beauty Salon",
            "type":"Services"
        }
    ],
    "sg:phone":"+32 11 42 68 63",
    "sg:postcode":"3582",
    "sg:province":"Limburg",
    "wof:name":"Instituut Linda",
    "wof:placetype":"venue"
},
  "geometry": {"coordinates":[5.2708749771,51.0595359802],"type":"Point"}
}