{
  "type": "Feature",
  "properties": {
    "addr:full":"Tulpendreef 2a Koksijde (oostduinkerke) West-Vlaanderen 8670",
    "addr:housenumber":"2a",
    "addr:postcode":"8670",
    "addr:street":"Tulpendreef",
    "iso:country":"BE",
    "sg:address":"Tulpendreef 2a",
    "sg:city":"Koksijde (oostduinkerke)",
    "sg:classifiers":[
        {
            "category":"Professional",
            "subcategory":"Printing & Photocopies",
            "type":"Services"
        }
    ],
    "sg:phone":"+32 58 52 05 52",
    "sg:postcode":"8670",
    "sg:province":"West-Vlaanderen",
    "sg:tags":[
        "-",
        "offset"
    ],
    "wof:name":"Color Match Printing Bvba",
    "wof:placetype":"venue"
},
  "geometry": {"coordinates":[2.6815960407,51.1266784668],"type":"Point"}
}