{
  "type": "Feature",
  "properties": {
    "iso:country":"BE",
    "sg:address":"Goorbergenlaan 51",
    "sg:city":"Vorselaar",
    "sg:classifiers":[
        {
            "category":"Health Services",
            "subcategory":"Health Practitioner",
            "type":"Services"
        }
    ],
    "sg:phone":"+32 14 51 57 47",
    "sg:postcode":"2290",
    "sg:province":"Antwerpen",
    "sg:tags":[
        "physiotherapist"
    ],
    "wof:name":"Dillen P",
    "wof:placetype":"venue"
},
  "geometry": {"coordinates":[4.7649102211,51.2030601501],"type":"Point"}
}