{
  "type": "Feature",
  "properties": {
    "addr:full":"Leopoldstraat 73 Antwerpen Antwerpen 2000",
    "addr:housenumber":"73",
    "addr:postcode":"2000",
    "addr:street":"Leopoldstraat",
    "iso:country":"BE",
    "sg:address":"Leopoldstraat 73",
    "sg:city":"Antwerpen",
    "sg:classifiers":[
        {
            "category":"Shopping",
            "subcategory":"Clothing, Apparel, & Fashions",
            "type":"Retail Goods"
        }
    ],
    "sg:phone":"+32 3 234 25 36",
    "sg:postcode":"2000",
    "sg:province":"Antwerpen",
    "sg:tags":[
        "underwear",
        "lingerie",
        "-"
    ],
    "wof:name":"Sylphide",
    "wof:placetype":"venue"
},
  "geometry": {"coordinates":[4.4075517654,51.2130012512],"type":"Point"}
}