{
  "type": "Feature",
  "properties": {
    "addr:full":"Golfclub 1 Houthalen-helchteren Limburg 3530",
    "addr:postcode":"3530",
    "addr:street":"Houthalen-Helchteren Limburg",
    "iso:country":"BE",
    "sg:address":"Golfclub 1",
    "sg:city":"Houthalen-helchteren",
    "sg:classifiers":[
        {
            "category":"Shopping",
            "subcategory":"Bicycles & Sporting Goods",
            "type":"Retail Goods"
        }
    ],
    "sg:phone":"+32 89 84 32 04",
    "sg:postcode":"3530",
    "sg:province":"Limburg",
    "sg:tags":[
        "article",
        "de",
        "sport",
        "camping"
    ],
    "wof:name":"Golfshop",
    "wof:placetype":"venue"
},
  "geometry": {"coordinates":[5.434773922,51.0222930908],"type":"Point"}
}