{
  "type": "Feature",
  "properties": {
    "addr:full":"Rue De Rochefort 219 Beauraing Namur 5570",
    "addr:housenumber":"219",
    "addr:postcode":"5570",
    "addr:street":"Rue De Rochefort",
    "iso:country":"BE",
    "sg:address":"Rue De Rochefort 219",
    "sg:city":"Beauraing",
    "sg:orig_category":"Protection civile",
    "sg:phone":"+32 82 71 24 13",
    "sg:postcode":"5570",
    "sg:province":"Namur",
    "wof:name":"Corps De Pompiers",
    "wof:placetype":"venue"
},
  "geometry": {"coordinates":[4.9784049988,50.1204071045],"type":"Point"}
}