{
  "type": "Feature",
  "properties": {
    "iso:country":"BE",
    "sg:address":"Rue Smeets 28",
    "sg:city":"Seraing",
    "sg:orig_category":"Kapsalons",
    "sg:phone":"+32 4 337 10 55",
    "sg:postcode":"4100",
    "sg:province":"Li\u00e8ge",
    "wof:name":"Coiffure Ferdinand",
    "wof:placetype":"venue"
},
  "geometry": {"coordinates":[5.5153107643,50.6049880981],"type":"Point"}
}