{
  "type": "Feature",
  "properties": {
    "iso:country":"BE",
    "sg:address":"Kortrijksesteenweg 152",
    "sg:city":"Sint-martens-latem",
    "sg:classifiers":[
        {
            "category":"Banks & Credit Unions",
            "subcategory":"Investment Brokerage",
            "type":"Services"
        }
    ],
    "sg:phone":"+32 9 282 99 65",
    "sg:postcode":"9830",
    "sg:province":"Oost-Vlaanderen",
    "sg:tags":[
        "auditor"
    ],
    "wof:name":"Kaekebeke W",
    "wof:placetype":"venue"
},
  "geometry": {"coordinates":[3.6298229694,51.0077438354],"type":"Point"}
}