{
  "type": "Feature",
  "properties": {
    "addr:full":"Populierenlaan 30 Zoersel Antwerpen 2980",
    "addr:housenumber":"30",
    "addr:postcode":"2980",
    "addr:street":"Populierenlaan",
    "iso:country":"BE",
    "sg:address":"Populierenlaan 30",
    "sg:city":"Zoersel",
    "sg:orig_category":"Mat\u00e9riel de contr\u00f4le des processus industriels Fab",
    "sg:phone":"+32 3 385 83 46",
    "sg:postcode":"2980",
    "sg:province":"Antwerpen",
    "wof:name":"B & C Engineering",
    "wof:placetype":"venue"
},
  "geometry": {"coordinates":[4.6650900841,51.2713890076],"type":"Point"}
}