{
  "type": "Feature",
  "properties": {
    "addr:full":"Rue Des Gaillettes 34 Herve Li\u00e8ge 4651",
    "addr:housenumber":"34",
    "addr:postcode":"4651",
    "addr:street":"Rue Des Gaillettes",
    "iso:country":"BE",
    "sg:address":"Rue Des Gaillettes 34",
    "sg:city":"Herve",
    "sg:orig_category":"Installatie van metalen schrijnwerk",
    "sg:phone":"+32 87 67 95 12",
    "sg:postcode":"4651",
    "sg:province":"Li\u00e8ge",
    "wof:name":"Te Ge Co",
    "wof:placetype":"venue"
},
  "geometry": {"coordinates":[5.8098120689,50.6486549377],"type":"Point"}
}