{
  "type": "Feature",
  "properties": {
    "addr:full":"Grayaertstraat 3 Veurne West-Vlaanderen 8630",
    "addr:housenumber":"3",
    "addr:postcode":"8630",
    "addr:street":"Grayaertstraat",
    "iso:country":"BE",
    "sg:address":"Grayaertstraat 3",
    "sg:city":"Veurne",
    "sg:orig_category":"Rundveehouders",
    "sg:phone":"+32 58 29 92 85",
    "sg:postcode":"8630",
    "sg:province":"West-Vlaanderen",
    "wof:name":"Werner Vanveuren",
    "wof:placetype":"venue"
},
  "geometry": {"coordinates":[2.5910820961,50.9976043701],"type":"Point"}
}