{
  "type": "Feature",
  "properties": {
    "iso:country":"BE",
    "sg:address":"Bonestraat 50",
    "sg:city":"Meulebeke",
    "sg:orig_category":"Studios photographiques",
    "sg:phone":"+32 51 48 92 51",
    "sg:postcode":"8760",
    "sg:province":"West-Vlaanderen",
    "wof:name":"Yves Sanders",
    "wof:placetype":"venue"
},
  "geometry": {"coordinates":[3.298418045,50.9542808533],"type":"Point"}
}