{
  "type": "Feature",
  "properties": {
    "addr:full":"Voortkapelseweg 48 Herentals Antwerpen 2200",
    "addr:housenumber":"48",
    "addr:postcode":"2200",
    "addr:street":"Voortkapelseweg",
    "iso:country":"BE",
    "sg:address":"Voortkapelseweg 48",
    "sg:city":"Herentals",
    "sg:classifiers":[
        {
            "category":"Cafe",
            "type":"Food & Drink"
        }
    ],
    "sg:phone":"+32 14 26 15 66",
    "sg:postcode":"2200",
    "sg:province":"Antwerpen",
    "sg:tags":[
        "caf\u00e9s"
    ],
    "wof:name":"Renaat Van Wolputte",
    "wof:placetype":"venue"
},
  "geometry": {"coordinates":[4.8364977837,51.121963501],"type":"Point"}
}