{
  "type": "Feature",
  "properties": {
    "addr:full":"Avenue Lavoisier 16b Wavre Brabant Wallon 1300",
    "addr:housenumber":"16b;1300",
    "addr:street":"Avenue Lavoisier",
    "iso:country":"BE",
    "sg:address":"Avenue Lavoisier 16b",
    "sg:city":"Wavre",
    "sg:classifiers":[
        {
            "category":"Retail",
            "subcategory":"Storage",
            "type":"Services"
        }
    ],
    "sg:phone":"+32 10 88 00 08",
    "sg:postcode":"1300",
    "sg:province":"Brabant Wallon",
    "sg:tags":[
        "shelf",
        "chassis",
        "shifting",
        "archive"
    ],
    "wof:name":"Mecalux Belgium S.a.",
    "wof:placetype":"venue"
},
  "geometry": {"coordinates":[4.5890030861,50.7348594666],"type":"Point"}
}