{
  "type": "Feature",
  "properties": {
    "addr:full":"Avenue Kersbeek 222 Bruxelles (forest) Bruxelles-Capitale 1190",
    "addr:housenumber":"222",
    "addr:postcode":"1190",
    "addr:street":"Avenue Kersbeek",
    "iso:country":"BE",
    "sg:address":"Avenue Kersbeek 222",
    "sg:city":"Bruxelles (forest)",
    "sg:classifiers":[
        {
            "category":"Utilities",
            "subcategory":"Recycling",
            "type":"Services"
        }
    ],
    "sg:phone":"+32 2 356 11 74",
    "sg:postcode":"1190",
    "sg:province":"Bruxelles-Capitale",
    "sg:tags":[
        "rubbish",
        "removal"
    ],
    "wof:name":"Louis Le Deboucheur",
    "wof:placetype":"venue"
},
  "geometry": {"coordinates":[4.3198361397,50.8024902344],"type":"Point"}
}