{
  "type": "Feature",
  "properties": {
    "iso:country":"BE",
    "sg:address":"Gelemanstraat 1",
    "sg:city":"Kortenaken",
    "sg:classifiers":[
        {
            "category":"Insurance",
            "subcategory":"Life Insurance",
            "type":"Services"
        }
    ],
    "sg:phone":"+32 11 58 84 84",
    "sg:postcode":"3470",
    "sg:province":"Vlaams-Brabant",
    "sg:tags":[
        "assurance"
    ],
    "wof:name":"J. Vlayen",
    "wof:placetype":"venue"
},
  "geometry": {"coordinates":[5.0821537971,50.9090423584],"type":"Point"}
}