{
  "type": "Feature",
  "properties": {
    "iso:country":"BE",
    "sg:address":"Avenue Gevaert 151",
    "sg:city":"Rixensart (genval)",
    "sg:classifiers":[
        {
            "category":"Real Estate",
            "subcategory":"Real Estate Services",
            "type":"Services"
        }
    ],
    "sg:phone":"+32 2 652 35 77",
    "sg:postcode":"1332",
    "sg:province":"Brabant Wallon",
    "wof:name":"Boels Immobiliere",
    "wof:placetype":"venue"
},
  "geometry": {"coordinates":[4.5040249825,50.723865509],"type":"Point"}
}