{
  "type": "Feature",
  "properties": {
    "iso:country":"BE",
    "sg:address":"Hasseltsesteenweg 455",
    "sg:city":"Tongeren",
    "sg:classifiers":[
        {
            "category":"Building & Trades",
            "subcategory":"Landscaping Services",
            "type":"Services"
        }
    ],
    "sg:phone":"+32 12 23 04 56",
    "sg:postcode":"3700",
    "sg:province":"Limburg",
    "sg:tags":[
        "equipment",
        "swimming",
        "-",
        "pool",
        "contractor"
    ],
    "wof:name":"Opreij G",
    "wof:placetype":"venue"
},
  "geometry": {"coordinates":[5.459335804,50.7829055786],"type":"Point"}
}