{
  "type": "Feature",
  "properties": {
    "addr:full":"Nestor De Ti\u00e8restraat 138 Oudenaarde Oost-Vlaanderen 9700",
    "addr:housenumber":"138",
    "addr:postcode":"9700",
    "addr:street":"Nestor De Tie\u0300Restraat",
    "iso:country":"BE",
    "sg:address":"Nestor De Ti\u00e8restraat 138",
    "sg:city":"Oudenaarde",
    "sg:classifiers":[
        {
            "category":"Transit Center",
            "subcategory":"Freight",
            "type":"Transportation"
        }
    ],
    "sg:phone":"+32 55 23 99 97",
    "sg:postcode":"9700",
    "sg:province":"Oost-Vlaanderen",
    "sg:tags":[
        "import",
        "export",
        "-"
    ],
    "wof:name":"Deconinck Bvba",
    "wof:placetype":"venue"
},
  "geometry": {"coordinates":[3.619494915,50.8685646057],"type":"Point"}
}