{
  "type": "Feature",
  "properties": {
    "iso:country":"BE",
    "sg:address":"Heirweg 14",
    "sg:city":"Kuurne",
    "sg:classifiers":[
        {
            "category":"Home & Garden",
            "subcategory":"Building Materials",
            "type":"Retail Goods"
        }
    ],
    "sg:phone":"+32 56 35 52 42",
    "sg:postcode":"8520",
    "sg:province":"West-Vlaanderen",
    "sg:tags":[
        "aluminium",
        "construction",
        "-"
    ],
    "wof:name":"Halsberghe Gebroeders",
    "wof:placetype":"venue"
},
  "geometry": {"coordinates":[3.2645390034,50.8541526794],"type":"Point"}
}