{
  "type": "Feature",
  "properties": {
    "iso:country":"BE",
    "sg:address":"Oranjestraat 56",
    "sg:city":"Scherpenheuvel-zichem",
    "sg:orig_category":"Artsen and specialisten",
    "sg:phone":"+32 13 77 65 45",
    "sg:postcode":"3271",
    "sg:province":"Vlaams-Brabant",
    "wof:name":"Johan Peeters",
    "wof:placetype":"venue"
},
  "geometry": {"coordinates":[4.984495163,51.0000228882],"type":"Point"}
}