{
  "type": "Feature",
  "properties": {
    "iso:country":"BE",
    "sg:address":"Kapellestraat 8",
    "sg:city":"Oostkamp",
    "sg:orig_category":"Quincailleries",
    "sg:phone":"+32 50 82 43 44",
    "sg:postcode":"8020",
    "sg:province":"West-Vlaanderen",
    "wof:name":"Luc Decraemer",
    "wof:placetype":"venue"
},
  "geometry": {"coordinates":[3.2374150753,51.1537628174],"type":"Point"}
}