{
  "type": "Feature",
  "properties": {
    "iso:country":"BE",
    "sg:address":"Rue F\u00c9lix Dutry 6",
    "sg:city":"Beaumont",
    "sg:orig_category":"Installation \u00e9lectrique r\u00e9sidentielle",
    "sg:phone":"+32 495 79 08 25",
    "sg:postcode":"6500",
    "sg:province":"Hainaut",
    "wof:name":"B. Lamourette",
    "wof:placetype":"venue"
},
  "geometry": {"coordinates":[4.237154007,50.2357711792],"type":"Point"}
}