{
  "type": "Feature",
  "properties": {
    "iso:country":"BE",
    "sg:address":"Abdijlaan 46",
    "sg:city":"Brecht",
    "sg:orig_category":"Eleveurs and marchands de porcs",
    "sg:phone":"+32 3 313 92 41",
    "sg:postcode":"2960",
    "sg:province":"Antwerpen",
    "wof:name":"Monique Adriaenssens",
    "wof:placetype":"venue"
},
  "geometry": {"coordinates":[4.6306967735,51.2992134094],"type":"Point"}
}