{
  "type": "Feature",
  "properties": {
    "iso:country":"BE",
    "sg:address":"Smedenstraat 67",
    "sg:city":"Brugge",
    "sg:classifiers":[
        {
            "category":"Shopping",
            "subcategory":"Pets & Pet Supplies",
            "type":"Retail Goods"
        }
    ],
    "sg:phone":"+32 50 33 24 01",
    "sg:postcode":"8000",
    "sg:province":"West-Vlaanderen",
    "sg:tags":[
        "aquarium",
        "accessory"
    ],
    "wof:name":"Anthias",
    "wof:placetype":"venue"
},
  "geometry": {"coordinates":[3.2134149075,51.2048225403],"type":"Point"}
}