{
  "type": "Feature",
  "properties": {
    "iso:country":"BE",
    "sg:address":"Termereboslaan 14",
    "sg:city":"Herent (winksele)",
    "sg:classifiers":[
        {
            "category":"Professional",
            "subcategory":"Art Services",
            "type":"Services"
        }
    ],
    "sg:phone":"+32 16 48 07 65",
    "sg:postcode":"3020",
    "sg:province":"Vlaams-Brabant",
    "sg:tags":[
        "photographer"
    ],
    "wof:name":"Foto Karel Rondou",
    "wof:placetype":"venue"
},
  "geometry": {"coordinates":[4.6749200821,50.9079055786],"type":"Point"}
}