{
  "type": "Feature",
  "properties": {
    "addr:full":"Place Du Vieux March\u00e9 11 Enghien Hainaut 7850",
    "addr:housenumber":"11",
    "addr:postcode":"7850",
    "addr:street":"Place Du Vieux Marche\u0301",
    "iso:country":"BE",
    "sg:address":"Place Du Vieux March\u00e9 11",
    "sg:city":"Enghien",
    "sg:classifiers":[
        {
            "category":"Community Center",
            "type":"Public Place"
        }
    ],
    "sg:phone":"+32 2 395 65 41",
    "sg:postcode":"7850",
    "sg:province":"Hainaut",
    "sg:tags":[
        "medical"
    ],
    "wof:name":"Croix Rouge",
    "wof:placetype":"venue"
},
  "geometry": {"coordinates":[4.0428619385,50.6949768066],"type":"Point"}
}