{
  "type": "Feature",
  "properties": {
    "iso:country":"BE",
    "sg:address":"Weg Naar Zwartberg 28",
    "sg:city":"Opglabbeek",
    "sg:classifiers":[
        {
            "category":"Shopping",
            "subcategory":"Clothing, Apparel, & Fashions",
            "type":"Retail Goods"
        }
    ],
    "sg:postcode":"3660",
    "sg:province":"Limburg",
    "sg:tags":[
        "wear",
        "mourning"
    ],
    "wof:name":"Schreurs Wed.",
    "wof:placetype":"venue"
},
  "geometry": {"coordinates":[5.5800890923,51.0419120789],"type":"Point"}
}