{
  "type": "Feature",
  "properties": {
    "iso:country":"BE",
    "sg:address":"Overlelestraat 57",
    "sg:city":"Kortrijk",
    "sg:orig_category":"Medische and orthopedische apparaten",
    "sg:phone":"+32 56 35 18 52",
    "sg:postcode":"8500",
    "sg:province":"West-Vlaanderen",
    "wof:name":"Hoorcentrum Overlele",
    "wof:placetype":"venue"
},
  "geometry": {"coordinates":[3.2593359947,50.8330459595],"type":"Point"}
}