{
  "type": "Feature",
  "properties": {
    "iso:country":"BE",
    "sg:address":"Overheulestraat 51",
    "sg:city":"Wevelgem (moorsele)",
    "sg:classifiers":[
        {
            "category":"Professional",
            "subcategory":"Printing & Photocopies",
            "type":"Services"
        }
    ],
    "sg:phone":"+32 56 41 68 62",
    "sg:postcode":"8560",
    "sg:province":"West-Vlaanderen",
    "sg:tags":[
        "-",
        "offset"
    ],
    "wof:name":"G.s. Printing",
    "wof:placetype":"venue"
},
  "geometry": {"coordinates":[3.1640539169,50.8425369263],"type":"Point"}
}