{
  "type": "Feature",
  "properties": {
    "iso:country":"BE",
    "sg:address":"Faubourg De Bruxelles 30",
    "sg:city":"Nivelles",
    "sg:orig_category":"MBK. Motos. V\u00e9los. R\u00e9parations and entretien de motos",
    "sg:phone":"+32 67 21 35 45",
    "sg:postcode":"1400",
    "sg:province":"Brabant Wallon",
    "wof:name":"City 2 Roues",
    "wof:placetype":"venue"
},
  "geometry": {"coordinates":[4.3270530701,50.6014328003],"type":"Point"}
}