{
  "type": "Feature",
  "properties": {
    "iso:country":"BE",
    "sg:address":"Stockem 63",
    "sg:city":"Eupen",
    "sg:classifiers":[
        {
            "category":"Professional",
            "subcategory":"Accounting & Tax Preparation",
            "type":"Services"
        }
    ],
    "sg:phone":"+32 87 55 48 42",
    "sg:postcode":"4700",
    "sg:province":"Li\u00e8ge",
    "sg:tags":[
        "bookkeeper"
    ],
    "wof:name":"Rolf Hilgers Sprl",
    "wof:placetype":"venue"
},
  "geometry": {"coordinates":[6.0296521187,50.6318206787],"type":"Point"}
}