{
  "type": "Feature",
  "properties": {
    "addr:full":"Ankerstraat 77 Sint-niklaas Oost-Vlaanderen 9100",
    "addr:housenumber":"77",
    "addr:postcode":"9100",
    "addr:street":"Ankerstraat",
    "iso:country":"BE",
    "sg:address":"Ankerstraat 77",
    "sg:city":"Sint-niklaas",
    "sg:orig_category":"Production de films, t\u00e9l\u00e9films and vid\u00e9os. Studios photographiques. Equipement photographique",
    "sg:phone":"+32 3 776 05 98",
    "sg:postcode":"9100",
    "sg:province":"Oost-Vlaanderen",
    "wof:name":"Photall",
    "wof:placetype":"venue"
},
  "geometry": {"coordinates":[4.1464371681,51.1657981873],"type":"Point"}
}