{
  "type": "Feature",
  "properties": {
    "addr:full":"Parklaan 54 Box 1 Aalst Oost-Vlaanderen 9300",
    "addr:housenumber":"54;1",
    "addr:postcode":"9300",
    "addr:street":"Parklaan;Box",
    "iso:country":"BE",
    "sg:address":"Parklaan 54 Box 1",
    "sg:city":"Aalst",
    "sg:classifiers":[
        {
            "category":"Banks & Credit Unions",
            "subcategory":"Investment Brokerage",
            "type":"Services"
        }
    ],
    "sg:phone":"+32 53 21 29 99",
    "sg:postcode":"9300",
    "sg:province":"Oost-Vlaanderen",
    "wof:name":"Financieel Centrum",
    "wof:placetype":"venue"
},
  "geometry": {"coordinates":[4.0360832214,50.9278907776],"type":"Point"}
}