{
  "type": "Feature",
  "properties": {
    "addr:full":"Industriepark 55 Tienen Vlaams-Brabant 3300",
    "addr:housenumber":"55",
    "addr:postcode":"3300",
    "addr:street":"Industriepark",
    "iso:country":"BE",
    "sg:address":"Industriepark 55",
    "sg:city":"Tienen",
    "sg:classifiers":[
        {
            "category":"Home & Garden",
            "subcategory":"Building Materials",
            "type":"Retail Goods"
        }
    ],
    "sg:phone":"+32 16 81 35 06",
    "sg:postcode":"3300",
    "sg:province":"Vlaams-Brabant",
    "sg:tags":[
        "window"
    ],
    "wof:name":"R.l.k. Bvba",
    "wof:placetype":"venue"
},
  "geometry": {"coordinates":[4.9709920883,50.8152999878],"type":"Point"}
}