{
  "type": "Feature",
  "properties": {
    "iso:country":"BE",
    "sg:address":"Rue Docteur Emile Neuville 4",
    "sg:city":"Villers-le-bouillet (vaux-et-borset)",
    "sg:classifiers":[
        {
            "category":"Banks & Credit Unions",
            "subcategory":"Investment Brokerage",
            "type":"Services"
        }
    ],
    "sg:phone":"+32 19 56 74 91",
    "sg:postcode":"4530",
    "sg:province":"Li\u00e8ge",
    "sg:tags":[
        "fence"
    ],
    "wof:name":"Braine M",
    "wof:placetype":"venue"
},
  "geometry": {"coordinates":[5.2435750961,50.6105957031],"type":"Point"}
}