{
  "type": "Feature",
  "properties": {
    "iso:country":"BE",
    "sg:address":"Rue Des Arquebusiers 35b",
    "sg:city":"Mons",
    "sg:classifiers":[
        {
            "category":"Retail",
            "subcategory":"Auto Repair",
            "type":"Services"
        }
    ],
    "sg:phone":"+32 65 33 53 65",
    "sg:postcode":"7000",
    "sg:province":"Hainaut",
    "sg:tags":[
        "garage"
    ],
    "wof:name":"Skoda-norguet",
    "wof:placetype":"venue"
},
  "geometry": {"coordinates":[3.9505000114,50.4471168518],"type":"Point"}
}