{
  "type": "Feature",
  "properties": {
    "addr:full":"Ch Vert 80 Ham-sur-heure-nalinnes Hainaut 6120",
    "addr:housenumber":"80",
    "addr:postcode":"6120",
    "addr:street":"Ham-Sur-Heure-Nalinnes Hainaut",
    "iso:country":"BE",
    "sg:address":"Ch Vert 80",
    "sg:city":"Ham-sur-heure-nalinnes",
    "sg:orig_category":"Installation \u00e9lectrique r\u00e9sidentielle",
    "sg:phone":"+32 71 21 31 35",
    "sg:postcode":"6120",
    "sg:province":"Hainaut",
    "wof:name":"Electraco",
    "wof:placetype":"venue"
},
  "geometry": {"coordinates":[4.4356579781,50.3451194763],"type":"Point"}
}