{
  "type": "Feature",
  "properties": {
    "iso:country":"BE",
    "sg:address":"Rue Gustave Deti\u00c8ge 1",
    "sg:city":"Hannut",
    "sg:orig_category":"Opticiens",
    "sg:phone":"+32 19 51 56 46",
    "sg:postcode":"4280",
    "sg:province":"Li\u00e8ge",
    "wof:name":"Optica",
    "wof:placetype":"venue"
},
  "geometry": {"coordinates":[5.0781698227,50.6718559265],"type":"Point"}
}