{
  "type": "Feature",
  "properties": {
    "addr:full":"Schoolstraat 56 Westerlo Antwerpen 2260",
    "addr:housenumber":"56",
    "addr:postcode":"2260",
    "addr:street":"Schoolstraat",
    "iso:country":"BE",
    "sg:address":"Schoolstraat 56",
    "sg:city":"Westerlo",
    "sg:classifiers":[
        {
            "category":"Banks & Credit Unions",
            "subcategory":"Investment Brokerage",
            "type":"Services"
        }
    ],
    "sg:phone":"+32 2 774 91 11",
    "sg:postcode":"2260",
    "sg:province":"Antwerpen",
    "sg:tags":[
        "auditor"
    ],
    "wof:name":"Engelen J",
    "wof:placetype":"venue"
},
  "geometry": {"coordinates":[4.8402957916,51.0820922852],"type":"Point"}
}