{
  "type": "Feature",
  "properties": {
    "iso:country":"BE",
    "sg:address":"Rue Joseph Heusdens 23",
    "sg:city":"Grace-hollogne",
    "sg:orig_category":"M\u00e9decins and sp\u00e9cialistes",
    "sg:phone":"+32 4 234 43 33",
    "sg:postcode":"4460",
    "sg:province":"Li\u00e8ge",
    "wof:name":"Sabri Tezel",
    "wof:placetype":"venue"
},
  "geometry": {"coordinates":[5.5039300919,50.6390838623],"type":"Point"}
}