{
  "type": "Feature",
  "properties": {
    "addr:full":"Kouterbaan 56 Lebbeke Oost-Vlaanderen 9280",
    "addr:housenumber":"56",
    "addr:postcode":"9280",
    "addr:street":"Kouterbaan",
    "iso:country":"BE",
    "sg:address":"Kouterbaan 56",
    "sg:city":"Lebbeke",
    "sg:classifiers":[
        {
            "category":"Food & Beverages",
            "subcategory":"Dairy",
            "type":"Retail Goods"
        }
    ],
    "sg:phone":"+32 52 41 07 83",
    "sg:postcode":"9280",
    "sg:province":"Oost-Vlaanderen",
    "sg:tags":[
        "product",
        "-"
    ],
    "wof:name":"Ost F",
    "wof:placetype":"venue"
},
  "geometry": {"coordinates":[4.1192040443,50.9968070984],"type":"Point"}
}