{
  "type": "Feature",
  "properties": {
    "iso:country":"BE",
    "sg:address":"Rue De La Station De Woluw\u00c9 52",
    "sg:city":"Brussel/bruxelles",
    "sg:orig_category":"Gespecialiseerde niet-residenti\u00eble bouw Installatie van metalen schrijnwerk",
    "sg:phone":"+32 2 770 18 33",
    "sg:postcode":"1200",
    "sg:province":"Bruxelles-Capitale",
    "wof:name":"Nootens Fr\u00cares",
    "wof:placetype":"venue"
},
  "geometry": {"coordinates":[4.4362478256,50.8373603821],"type":"Point"}
}