{
  "type": "Feature",
  "properties": {
    "iso:country":"BE",
    "sg:address":"Stationsstraat 131",
    "sg:city":"Geel",
    "sg:orig_category":"Notaires",
    "sg:phone":"+32 14 58 80 98",
    "sg:postcode":"2440",
    "sg:province":"Antwerpen",
    "wof:name":"L. Moortgat",
    "wof:placetype":"venue"
},
  "geometry": {"coordinates":[4.9890489578,51.1670074463],"type":"Point"}
}