{
  "type": "Feature",
  "properties": {
    "addr:full":"Nieuwstraat 58 Mol Antwerpen 2400",
    "addr:housenumber":"58",
    "addr:postcode":"2400",
    "addr:street":"Nieuwstraat",
    "iso:country":"BE",
    "sg:address":"Nieuwstraat 58",
    "sg:city":"Mol",
    "sg:classifiers":[
        {
            "category":"Arena",
            "subcategory":"Sports Club",
            "type":"Entertainment"
        }
    ],
    "sg:phone":"+32 14 31 37 90",
    "sg:postcode":"2400",
    "sg:province":"Antwerpen",
    "sg:tags":[
        "de"
    ],
    "wof:name":"Solaris Naturisme",
    "wof:placetype":"venue"
},
  "geometry": {"coordinates":[5.1145739555,51.1836624146],"type":"Point"}
}