{
  "type": "Feature",
  "properties": {
    "iso:country":"BE",
    "sg:address":"Blijde Inkomst 60",
    "sg:city":"Leuven",
    "sg:orig_category":"Agents artistiques",
    "sg:phone":"+32 16 22 00 22",
    "sg:postcode":"3000",
    "sg:province":"Vlaams-Brabant",
    "wof:name":"European Merchandising Company",
    "wof:placetype":"venue"
},
  "geometry": {"coordinates":[4.7100858688,50.8759231567],"type":"Point"}
}