{
  "type": "Feature",
  "properties": {
    "addr:full":"Fr\u00e8re-orbanstraat 16 Oostende West-Vlaanderen 8400",
    "addr:housenumber":"16",
    "addr:postcode":"8400",
    "addr:street":"Fre\u0300Re-Orbanstraat",
    "iso:country":"BE",
    "sg:address":"Fr\u00e8re-orbanstraat 16",
    "sg:city":"Oostende",
    "sg:classifiers":[
        {
            "category":"Real Estate",
            "subcategory":"Architect",
            "type":"Services"
        }
    ],
    "sg:phone":"+32 59 70 93 48",
    "sg:postcode":"8400",
    "sg:province":"West-Vlaanderen",
    "wof:name":"Catteeuw A",
    "wof:placetype":"venue"
},
  "geometry": {"coordinates":[2.9091730118,51.2213592529],"type":"Point"}
}