{
  "type": "Feature",
  "properties": {
    "addr:full":"All\u00e9e Des Lacs 8 Gerpinnes (loverval) Hainaut 6280",
    "addr:housenumber":"8",
    "addr:postcode":"6280",
    "addr:street":"Alle\u0301E Des Lacs",
    "iso:country":"BE",
    "sg:address":"All\u00e9e Des Lacs 8",
    "sg:city":"Gerpinnes (loverval)",
    "sg:classifiers":[
        {
            "category":"Health Services",
            "subcategory":"Health Practitioner",
            "type":"Services"
        }
    ],
    "sg:phone":"+32 71 43 05 16",
    "sg:postcode":"6280",
    "sg:province":"Hainaut",
    "sg:tags":[
        "physiotherapist"
    ],
    "wof:name":"Aubert S",
    "wof:placetype":"venue"
},
  "geometry": {"coordinates":[4.5276851654,50.3365364075],"type":"Point"}
}