{
  "type": "Feature",
  "properties": {
    "iso:country":"BE",
    "sg:address":"Fosse-des-biays 63",
    "sg:city":"Libin",
    "sg:orig_category":"Installation de menuiserie en bois and plastique",
    "sg:phone":"+32 61 65 58 62",
    "sg:postcode":"6890",
    "sg:province":"Luxembourg",
    "wof:name":"Lionel Javaux",
    "wof:placetype":"venue"
},
  "geometry": {"coordinates":[5.2684388161,49.9823684692],"type":"Point"}
}