{
  "type": "Feature",
  "properties": {
    "addr:full":"Pannestraat 30 Scherpenheuvel-zichem (messelbroek) Vlaams-Brabant 3272",
    "addr:housenumber":"30",
    "addr:postcode":"3272",
    "addr:street":"Pannestraat;Messelbroek Vlaams-Brabant",
    "iso:country":"BE",
    "sg:address":"Pannestraat 30",
    "sg:city":"Scherpenheuvel-zichem (messelbroek)",
    "sg:classifiers":[
        {
            "category":"Health Services",
            "subcategory":"Dentist",
            "type":"Services"
        }
    ],
    "sg:phone":"+32 13 77 66 47",
    "sg:postcode":"3272",
    "sg:province":"Vlaams-Brabant",
    "wof:name":"Coenen Godelieve",
    "wof:placetype":"venue"
},
  "geometry": {"coordinates":[4.9398789406,50.9959945679],"type":"Point"}
}