{
  "type": "Feature",
  "properties": {
    "addr:full":"Ninoofsesteenweg 22 Pepingen Vlaams-Brabant 1670",
    "addr:housenumber":"22",
    "addr:postcode":"1670",
    "addr:street":"Ninoofsesteenweg",
    "iso:country":"BE",
    "sg:address":"Ninoofsesteenweg 22",
    "sg:city":"Pepingen",
    "sg:orig_category":"Groenten and fruit Gh",
    "sg:phone":"+32 2 361 24 86",
    "sg:postcode":"1670",
    "sg:province":"Vlaams-Brabant",
    "wof:name":"Leo Neetens",
    "wof:placetype":"venue"
},
  "geometry": {"coordinates":[4.1779689789,50.7533721924],"type":"Point"}
}