{
  "type": "Feature",
  "properties": {
    "iso:country":"BE",
    "sg:address":"Nieuwlandstraat 3",
    "sg:city":"Beveren",
    "sg:orig_category":"Eleveurs de bovins",
    "sg:phone":"+32 3 252 67 83",
    "sg:postcode":"9120",
    "sg:province":"Oost-Vlaanderen",
    "wof:name":"Heirbaut Paul & Roger",
    "wof:placetype":"venue"
},
  "geometry": {"coordinates":[4.3109359741,51.2028465271],"type":"Point"}
}