{
  "type": "Feature",
  "properties": {
    "addr:full":"Avenue De Ninove 184 Rochefort (jemelle) Namur 5580",
    "addr:housenumber":"184",
    "addr:postcode":"5580",
    "addr:street":"Avenue De Ninove",
    "iso:country":"BE",
    "sg:address":"Avenue De Ninove 184",
    "sg:city":"Rochefort (jemelle)",
    "sg:classifiers":[
        {
            "category":"Health Services",
            "subcategory":"Health Practitioner",
            "type":"Services"
        }
    ],
    "sg:phone":"+32 84 21 13 44",
    "sg:postcode":"5580",
    "sg:province":"Namur",
    "sg:tags":[
        "physiotherapist"
    ],
    "wof:name":"Charlier Laurence",
    "wof:placetype":"venue"
},
  "geometry": {"coordinates":[5.2491688728,50.1618652344],"type":"Point"}
}