{
  "type": "Feature",
  "properties": {
    "iso:country":"BE",
    "sg:address":"Chauss\u00e9e De Mons 211",
    "sg:city":"Anderlues",
    "sg:classifiers":[
        {
            "category":"Home & Garden",
            "subcategory":"Garden Supply",
            "type":"Retail Goods"
        }
    ],
    "sg:phone":"+32 64 34 00 86",
    "sg:postcode":"6150",
    "sg:province":"Hainaut",
    "sg:tags":[
        "lawn",
        "mower"
    ],
    "wof:name":"Christian Wautier",
    "wof:placetype":"venue"
},
  "geometry": {"coordinates":[4.2286968231,50.4077949524],"type":"Point"}
}