{
  "type": "Feature",
  "properties": {
    "addr:full":"Rue Neuve Chauss\u00e9e 135 P\u00e9ruwelz Hainaut 7600",
    "addr:housenumber":"135",
    "addr:postcode":"7600",
    "addr:street":"Rue;Chausse\u0301E",
    "iso:country":"BE",
    "sg:address":"Rue Neuve Chauss\u00e9e 135",
    "sg:city":"P\u00e9ruwelz",
    "sg:classifiers":[
        {
            "category":"Retail",
            "subcategory":"Veterinary Services",
            "type":"Services"
        }
    ],
    "sg:phone":"+32 69 77 24 29",
    "sg:postcode":"7600",
    "sg:province":"Hainaut",
    "sg:tags":[
        "veterinarian"
    ],
    "wof:name":"Hocq R",
    "wof:placetype":"venue"
},
  "geometry": {"coordinates":[3.6009199619,50.5246620178],"type":"Point"}
}