{
  "type": "Feature",
  "properties": {
    "iso:country":"BE",
    "sg:address":"Kroonstraat 167",
    "sg:city":"Beringen (beverlo)",
    "sg:orig_category":"Non-Classified Establishments",
    "sg:phone":"+32 11 34 15 02",
    "sg:postcode":"3581",
    "sg:province":"Limburg",
    "wof:name":"Sanicole Nv",
    "wof:placetype":"venue"
},
  "geometry": {"coordinates":[5.2692751884,51.0918197632],"type":"Point"}
}