{
  "type": "Feature",
  "properties": {
    "addr:full":"Rue Fran\u00e7ois Vervloet 10-12 Bruxelles (uccle) Bruxelles-Capitale 1180",
    "addr:housenumber":"10-12",
    "addr:postcode":"1180",
    "addr:street":"Rue Franc\u0327Ois Vervloet",
    "iso:country":"BE",
    "sg:address":"Rue Fran\u00e7ois Vervloet 10-12",
    "sg:city":"Bruxelles (uccle)",
    "sg:classifiers":[
        {
            "category":"Education",
            "subcategory":"School",
            "type":"Public Place"
        }
    ],
    "sg:phone":"+32 2 376 36 62",
    "sg:postcode":"1180",
    "sg:province":"Bruxelles-Capitale",
    "sg:tags":[
        "secondary"
    ],
    "wof:name":"Muziekacademie",
    "wof:placetype":"venue"
},
  "geometry": {"coordinates":[4.3311810493,50.7910842896],"type":"Point"}
}