{
  "type": "Feature",
  "properties": {
    "addr:full":"Tieltsebaan 31 Scherpenheuvel-zichem (messelbroek) Vlaams-Brabant 3272",
    "addr:housenumber":"31",
    "addr:postcode":"3272",
    "addr:street":"Tieltsebaan;Messelbroek Vlaams-Brabant",
    "iso:country":"BE",
    "sg:address":"Tieltsebaan 31",
    "sg:city":"Scherpenheuvel-zichem (messelbroek)",
    "sg:classifiers":[
        {
            "category":"Retail",
            "subcategory":"Repair Shop",
            "type":"Services"
        }
    ],
    "sg:phone":"+32 13 78 39 06",
    "sg:postcode":"3272",
    "sg:province":"Vlaams-Brabant",
    "wof:name":"Goossens John",
    "wof:placetype":"venue"
},
  "geometry": {"coordinates":[4.9398789406,50.9959945679],"type":"Point"}
}