{
  "type": "Feature",
  "properties": {
    "addr:full":"Rue Roland Vanoverschelde 10 Mouscron Hainaut 7700",
    "addr:housenumber":"10",
    "addr:postcode":"7700",
    "addr:street":"Rue Roland Vanoverschelde",
    "iso:country":"BE",
    "sg:address":"Rue Roland Vanoverschelde 10",
    "sg:city":"Mouscron",
    "sg:classifiers":[
        {
            "category":"Banks & Credit Unions",
            "subcategory":"Investment Brokerage",
            "type":"Services"
        }
    ],
    "sg:phone":"+32 56 33 07 71",
    "sg:postcode":"7700",
    "sg:province":"Hainaut",
    "sg:tags":[
        "printing",
        "-"
    ],
    "wof:name":"Pillyser J",
    "wof:placetype":"venue"
},
  "geometry": {"coordinates":[3.2016880512,50.7465057373],"type":"Point"}
}