{
  "type": "Feature",
  "properties": {
    "addr:full":"Rue Adolphe Chif 42 Chatelet Hainaut 6200",
    "addr:housenumber":"42",
    "addr:postcode":"6200",
    "addr:street":"Rue Adolphe Chif;Hainaut",
    "iso:country":"BE",
    "sg:address":"Rue Adolphe Chif 42",
    "sg:city":"Chatelet",
    "sg:orig_category":"Enseignement maternel and primaire",
    "sg:phone":"+32 71 38 73 62",
    "sg:postcode":"6200",
    "sg:province":"Hainaut",
    "wof:name":"Ecole Fondamentale Libre",
    "wof:placetype":"venue"
},
  "geometry": {"coordinates":[4.5154719353,50.4130821228],"type":"Point"}
}