{
  "type": "Feature",
  "properties": {
    "addr:full":"Stationsstraat 32 De Haan West-Vlaanderen 8420",
    "addr:housenumber":"32",
    "addr:postcode":"8420",
    "addr:street":"Stationsstraat",
    "iso:country":"BE",
    "sg:address":"Stationsstraat 32",
    "sg:city":"De Haan",
    "sg:orig_category":"Assurances. Bureaux de poste",
    "sg:phone":"+32 59 24 29 50",
    "sg:postcode":"8420",
    "sg:province":"West-Vlaanderen",
    "wof:name":"De Post",
    "wof:placetype":"venue"
},
  "geometry": {"coordinates":[3.0344591141,51.2708015442],"type":"Point"}
}