{
  "type": "Feature",
  "properties": {
    "iso:country":"BE",
    "sg:address":"Lourdesstraat 75",
    "sg:city":"Gent (oostakker)",
    "sg:classifiers":[
        {
            "category":"Insurance",
            "subcategory":"Insurance Agent",
            "type":"Services"
        }
    ],
    "sg:phone":"+32 9 251 08 00",
    "sg:postcode":"9041",
    "sg:province":"Oost-Vlaanderen",
    "sg:tags":[
        "broker"
    ],
    "wof:name":"Depaepe A & L Bvba",
    "wof:placetype":"venue"
},
  "geometry": {"coordinates":[3.7568609715,51.0797348022],"type":"Point"}
}