{
  "type": "Feature",
  "properties": {
    "iso:country":"BE",
    "sg:address":"Avenue J. Dubrucq 100",
    "sg:city":"Sint-jans-molenbeek/molenbeek-",
    "sg:orig_category":"Gestion de media publicitaires",
    "sg:phone":"+32 2 424 05 32",
    "sg:postcode":"1080",
    "sg:province":"Bruxelles-Capitale",
    "wof:name":"Music All",
    "wof:placetype":"venue"
},
  "geometry": {"coordinates":[4.3362441063,50.86668396],"type":"Point"}
}