{
  "type": "Feature",
  "properties": {
    "addr:full":"Brakelsesteenweg 199 Ninove (outer) Oost-Vlaanderen 9406",
    "addr:housenumber":"199",
    "addr:postcode":"9406",
    "addr:street":"Brakelsesteenweg;Outer Oost-Vlaanderen",
    "iso:country":"BE",
    "sg:address":"Brakelsesteenweg 199",
    "sg:city":"Ninove (outer)",
    "sg:classifiers":[
        {
            "category":"Autos & Motor Vehicles",
            "subcategory":"Automobile Sales",
            "type":"Retail Goods"
        }
    ],
    "sg:phone":"+32 54 32 29 82",
    "sg:postcode":"9406",
    "sg:province":"Oost-Vlaanderen",
    "sg:tags":[
        "car",
        "used",
        "-"
    ],
    "wof:name":"Lambrecht R",
    "wof:placetype":"venue"
},
  "geometry": {"coordinates":[3.9967310429,50.8345985413],"type":"Point"}
}