{
  "type": "Feature",
  "properties": {
    "iso:country":"BE",
    "sg:address":"Rue Jules Destr\u00c9e 435",
    "sg:city":"Quaregnon",
    "sg:orig_category":"Cr\u00e9dit \u00e0 la consommation. Pr\u00eats hypoth\u00e9caires and cr\u00e9dits immobiliers. Agences immobili\u00e8res. Assuran",
    "sg:phone":"+32 65 80 36 15",
    "sg:postcode":"7390",
    "sg:province":"Hainaut",
    "wof:name":"La Mondiale Immobili\u00c8re",
    "wof:placetype":"venue"
},
  "geometry": {"coordinates":[3.8538761139,50.4422912598],"type":"Point"}
}