{
  "type": "Feature",
  "properties": {
    "addr:full":"Bleekhoefstraat 2 Turnhout Antwerpen 2300",
    "addr:housenumber":"2",
    "addr:postcode":"2300",
    "addr:street":"Bleekhoefstraat",
    "iso:country":"BE",
    "sg:address":"Bleekhoefstraat 2",
    "sg:city":"Turnhout",
    "sg:orig_category":"Advocaten and juridische adviseurs",
    "sg:phone":"+32 14 42 05 15",
    "sg:postcode":"2300",
    "sg:province":"Antwerpen",
    "wof:name":"T. Lauwers",
    "wof:placetype":"venue"
},
  "geometry": {"coordinates":[4.9327731133,51.3084182739],"type":"Point"}
}