{
  "type": "Feature",
  "properties": {
    "iso:country":"BE",
    "sg:address":"Avenue Du Bosquet 57",
    "sg:city":"Bousval",
    "sg:classifiers":[
        {
            "category":"Military Area",
            "subcategory":"Air Force Base",
            "type":"Public Place"
        }
    ],
    "sg:phone":"+32 10 61 18 45",
    "sg:postcode":"1470",
    "sg:province":"Brabant Wallon",
    "sg:tags":[
        "prime",
        "contractor",
        "contractors"
    ],
    "wof:name":"Ingelec S.p.r.l.",
    "wof:placetype":"venue"
},
  "geometry": {"coordinates":[4.5289788246,50.6329727173],"type":"Point"}
}