{
  "type": "Feature",
  "properties": {
    "iso:country":"BE",
    "sg:address":"Boulevard E. De Laveleye 225",
    "sg:city":"Liege",
    "sg:orig_category":"Diverse opleidingen and onderwijs",
    "sg:phone":"+32 4 349 18 68",
    "sg:postcode":"4020",
    "sg:province":"Li\u00e8ge",
    "wof:name":"Forma Lingua",
    "wof:placetype":"venue"
},
  "geometry": {"coordinates":[5.5928530693,50.6185874939],"type":"Point"}
}