{
  "type": "Feature",
  "properties": {
    "iso:country":"BE",
    "sg:address":"Berlaarbaan 148",
    "sg:city":"Sint-katelijne-waver (grand)",
    "sg:classifiers":[
        {
            "category":"Restaurant",
            "type":"Food & Drink"
        }
    ],
    "sg:phone":"+32 15 25 34 34",
    "sg:postcode":"2861",
    "sg:province":"Antwerpen",
    "wof:name":"De Bosmolen",
    "wof:placetype":"venue"
},
  "geometry": {"coordinates":[4.5348501205,51.0485801697],"type":"Point"}
}