{
  "type": "Feature",
  "properties": {
    "addr:full":"Haanhoutstraat 94ba Lochristi Oost-Vlaanderen 9080",
    "addr:housenumber":"94ba",
    "addr:postcode":"9080",
    "addr:street":"Haanhoutstraat",
    "iso:country":"BE",
    "sg:address":"Haanhoutstraat 94ba",
    "sg:city":"Lochristi",
    "sg:orig_category":"Boomkwekerijen",
    "sg:phone":"+32 9 356 98 07",
    "sg:postcode":"9080",
    "sg:province":"Oost-Vlaanderen",
    "wof:name":"Carol Vande Putte",
    "wof:placetype":"venue"
},
  "geometry": {"coordinates":[3.8504741192,51.0769042969],"type":"Point"}
}