{
  "type": "Feature",
  "properties": {
    "addr:full":"329 Hubert Fr\u00e8re Orbanlaan 9000 Gent 329",
    "addr:housenumber":"329;329",
    "addr:postcode":"9000",
    "addr:street":"Hubert Fre\u0300Re Orbanlaan",
    "iso:country":"BE",
    "sg:address":"329",
    "sg:city":"Hubert Fr\u00e8re Orbanlaan 9000 Gent",
    "sg:classifiers":[
        {
            "category":"Manufacturing",
            "subcategory":"Textiles",
            "type":"Manufacturing & Wholesale Goods"
        }
    ],
    "sg:phone":"+32 9 223 02 47",
    "sg:postcode":"329",
    "sg:tags":[
        "linen",
        "clothing",
        "fabric"
    ],
    "wof:name":"Belena Bvba- Carreblanc Distributor",
    "wof:placetype":"venue"
},
  "geometry": {"coordinates":[3.7343549728,51.043586731],"type":"Point"}
}