{
  "type": "Feature",
  "properties": {
    "addr:full":"Karel Soetelaan 64 Borsbeek Antwerpen 2150",
    "addr:housenumber":"64",
    "addr:postcode":"2150",
    "addr:street":"Karel Soetelaan",
    "iso:country":"BE",
    "sg:address":"Karel Soetelaan 64",
    "sg:city":"Borsbeek",
    "sg:classifiers":[
        {
            "category":"Health Services",
            "subcategory":"Doctor",
            "type":"Services"
        }
    ],
    "sg:phone":"+32 3 321 45 33",
    "sg:postcode":"2150",
    "sg:province":"Antwerpen",
    "sg:tags":[
        "medicinephysicians",
        "surgeon"
    ],
    "wof:name":"De Loose F",
    "wof:placetype":"venue"
},
  "geometry": {"coordinates":[4.4794502258,51.2004089355],"type":"Point"}
}