{
  "type": "Feature",
  "properties": {
    "addr:full":"Chauss\u00c9e De Lodelinsart 36 Charleroi Hainaut 6060",
    "addr:housenumber":"36",
    "addr:postcode":"6060",
    "addr:street":"Chausse\u0301E De Lodelinsart;Hainaut",
    "iso:country":"BE",
    "sg:address":"Chauss\u00c9e De Lodelinsart 36",
    "sg:city":"Charleroi",
    "sg:classifiers":[
        {
            "category":"Cafe",
            "type":"Food & Drink"
        }
    ],
    "sg:phone":"+32 71 42 06 07",
    "sg:postcode":"6060",
    "sg:province":"Hainaut",
    "sg:tags":[
        "caf\u00e9s"
    ],
    "wof:name":"Caf\u00c9 De L'h\u00d4tel De Ville",
    "wof:placetype":"venue"
},
  "geometry": {"coordinates":[4.4880981445,50.4251937866],"type":"Point"}
}