{
  "type": "Feature",
  "properties": {
    "iso:country":"BE",
    "sg:address":"Avenue De La Chapelle 124",
    "sg:city":"Kraainem/kraainem",
    "sg:orig_category":"Artistes ind\u00e9pendants",
    "sg:phone":"+32 2 720 11 41",
    "sg:postcode":"1950",
    "sg:province":"Vlaams-Brabant",
    "wof:name":"Luc Andr\u00c9",
    "wof:placetype":"venue"
},
  "geometry": {"coordinates":[4.4572768211,50.8578605652],"type":"Point"}
}