{
  "type": "Feature",
  "properties": {
    "iso:country":"BE",
    "sg:address":"Rue De Pintamont 31",
    "sg:city":"Ath",
    "sg:orig_category":"Woningbouw",
    "sg:phone":"+32 68 28 68 74",
    "sg:postcode":"7800",
    "sg:province":"Hainaut",
    "wof:name":"M. Poley",
    "wof:placetype":"venue"
},
  "geometry": {"coordinates":[3.7745931149,50.628616333],"type":"Point"}
}