{
  "type": "Feature",
  "properties": {
    "addr:full":"Ophovenstraat 86 Meeuwen-gruitrode (gruitrode) Limburg 3670",
    "addr:housenumber":"86",
    "addr:postcode":"3670",
    "addr:street":"Ophovenstraat",
    "iso:country":"BE",
    "sg:address":"Ophovenstraat 86",
    "sg:city":"Meeuwen-gruitrode (gruitrode)",
    "sg:classifiers":[
        {
            "category":"Sports & Exercise",
            "subcategory":"Stables",
            "type":"Entertainment"
        }
    ],
    "sg:phone":"+32 89 85 24 40",
    "sg:postcode":"3670",
    "sg:province":"Limburg",
    "sg:tags":[
        "riding",
        "school"
    ],
    "wof:name":"M & D",
    "wof:placetype":"venue"
},
  "geometry": {"coordinates":[5.5348110199,51.0683021545],"type":"Point"}
}