{
  "type": "Feature",
  "properties": {
    "addr:full":"Rue Ernest Malvoz 14 Flemalle Li\u00e8ge 4400",
    "addr:housenumber":"14",
    "addr:postcode":"4400",
    "addr:street":"Rue Ernest Malvoz",
    "iso:country":"BE",
    "sg:address":"Rue Ernest Malvoz 14",
    "sg:city":"Flemalle",
    "sg:orig_category":"Advocaten and juridische adviseurs",
    "sg:phone":"+32 4 231 08 88",
    "sg:postcode":"4400",
    "sg:province":"Li\u00e8ge",
    "wof:name":"Bernadette Londot",
    "wof:placetype":"venue"
},
  "geometry": {"coordinates":[5.4595398903,50.5947494507],"type":"Point"}
}