{
  "type": "Feature",
  "properties": {
    "addr:full":"Halvemaanstraat 88 Gent Oost-Vlaanderen 9040",
    "addr:housenumber":"88",
    "addr:postcode":"9040",
    "addr:street":"Halvemaanstraat;Oost-Vlaanderen",
    "iso:country":"BE",
    "sg:address":"Halvemaanstraat 88",
    "sg:city":"Gent",
    "sg:orig_category":"Artiesten and kunstenaars Decoratieve kunst and kunstbenodigdheden",
    "sg:phone":"+32 9 228 13 48",
    "sg:postcode":"9040",
    "sg:province":"Oost-Vlaanderen",
    "wof:name":"Gaetan Van Langenhove",
    "wof:placetype":"venue"
},
  "geometry": {"coordinates":[3.7453920841,51.0615653992],"type":"Point"}
}