{
  "type": "Feature",
  "properties": {
    "addr:full":"Maastrichterstraat 61 Tongeren Limburg 3700",
    "addr:housenumber":"61",
    "addr:postcode":"3700",
    "addr:street":"Maastrichterstraat",
    "iso:country":"BE",
    "sg:address":"Maastrichterstraat 61",
    "sg:city":"Tongeren",
    "sg:orig_category":"V\u00eatements pour b\u00e9b\u00e9s and enfants",
    "sg:phone":"+32 12 39 19 26",
    "sg:postcode":"3700",
    "sg:province":"Limburg",
    "wof:name":"De Klaproos",
    "wof:placetype":"venue"
},
  "geometry": {"coordinates":[5.4665141106,50.7821006775],"type":"Point"}
}