{
  "type": "Feature",
  "properties": {
    "addr:full":"Lindestraat 210 Alken Limburg 3570",
    "addr:housenumber":"210",
    "addr:postcode":"3570",
    "addr:street":"Lindestraat",
    "iso:country":"BE",
    "sg:address":"Lindestraat 210",
    "sg:city":"Alken",
    "sg:orig_category":"Varkenskwekers",
    "sg:phone":"+32 11 31 10 37",
    "sg:postcode":"3570",
    "sg:province":"Limburg",
    "wof:name":"Stan Geerdens",
    "wof:placetype":"venue"
},
  "geometry": {"coordinates":[5.2589550018,50.9003715515],"type":"Point"}
}