{
  "type": "Feature",
  "properties": {
    "iso:country":"BE",
    "sg:address":"Sint-annastraat 60",
    "sg:city":"Waasmunster",
    "sg:orig_category":"Eleveurs and marchands de porcs. Eleveurs de volaille",
    "sg:phone":"+32 52 47 80 29",
    "sg:postcode":"9250",
    "sg:province":"Oost-Vlaanderen",
    "wof:name":"Vercauteren",
    "wof:placetype":"venue"
},
  "geometry": {"coordinates":[4.0826330185,51.094959259],"type":"Point"}
}