{
  "type": "Feature",
  "properties": {
    "addr:full":"Rue Du Poirier 22 Ottignies-louvain-la-neuve (louvain-la-neuve) Brabant Wallon 1348",
    "addr:housenumber":"22",
    "addr:postcode":"1348",
    "addr:street":"Rue Du Poirier",
    "iso:country":"BE",
    "sg:address":"Rue Du Poirier 22",
    "sg:city":"Ottignies-louvain-la-neuve (louvain-la-neuve)",
    "sg:classifiers":[
        {
            "category":"Professional",
            "subcategory":"Management & Consulting",
            "type":"Services"
        }
    ],
    "sg:phone":"+32 10 45 22 81",
    "sg:postcode":"1348",
    "sg:province":"Brabant Wallon",
    "sg:tags":[
        "consultant"
    ],
    "wof:name":"Meurens & Associ\u00e9s Sprl",
    "wof:placetype":"venue"
},
  "geometry": {"coordinates":[4.6218109131,50.6702308655],"type":"Point"}
}