{
  "type": "Feature",
  "properties": {
    "addr:full":"Chauss\u00e9e De Haecht 1163 Bruxelles (evere) Bruxelles-Capitale 1140",
    "addr:postcode":"1163;1140",
    "addr:street":"Chausse\u0301E De Haecht",
    "iso:country":"BE",
    "sg:address":"Chauss\u00e9e De Haecht 1163",
    "sg:city":"Bruxelles (evere)",
    "sg:classifiers":[
        {
            "category":"Bars & Pubs",
            "type":"Food & Drink"
        }
    ],
    "sg:phone":"+32 2 245 43 50",
    "sg:postcode":"1140",
    "sg:province":"Bruxelles-Capitale",
    "wof:name":"Depannage (au)",
    "wof:placetype":"venue"
},
  "geometry": {"coordinates":[4.409512043,50.8778953552],"type":"Point"}
}