{
  "type": "Feature",
  "properties": {
    "addr:full":"Kazernevest 10 Sint-truiden Limburg 3800",
    "addr:housenumber":"10",
    "addr:postcode":"3800",
    "addr:street":"Kazernevest",
    "iso:country":"BE",
    "sg:address":"Kazernevest 10",
    "sg:city":"Sint-truiden",
    "sg:orig_category":"Rechtbanken",
    "sg:phone":"+32 11 68 29 96",
    "sg:postcode":"3800",
    "sg:province":"Limburg",
    "wof:name":"Vredegerecht",
    "wof:placetype":"venue"
},
  "geometry": {"coordinates":[5.1813650131,50.8169212341],"type":"Point"}
}