{
  "type": "Feature",
  "properties": {
    "addr:full":"Oude Godstraat 248 Edegem Antwerpen 2650",
    "addr:housenumber":"248",
    "addr:postcode":"2650",
    "addr:street":"Oude Godstraat",
    "iso:country":"BE",
    "sg:address":"Oude Godstraat 248",
    "sg:city":"Edegem",
    "sg:classifiers":[
        {
            "category":"Bars & Pubs",
            "type":"Food & Drink"
        }
    ],
    "sg:phone":"+32 3 449 06 24",
    "sg:postcode":"2650",
    "sg:province":"Antwerpen",
    "wof:name":"Oud Antwerpen",
    "wof:placetype":"venue"
},
  "geometry": {"coordinates":[4.444439888,51.1615905762],"type":"Point"}
}