{
  "type": "Feature",
  "properties": {
    "addr:full":"Antwerpsesteenweg 341 Malle Antwerpen 2390",
    "addr:housenumber":"341",
    "addr:postcode":"2390",
    "addr:street":"Antwerpsesteenweg",
    "iso:country":"BE",
    "sg:address":"Antwerpsesteenweg 341",
    "sg:city":"Malle",
    "sg:orig_category":"Dancings and bo\u00eetes de nuit",
    "sg:phone":"+32 3 312 58 63",
    "sg:postcode":"2390",
    "sg:province":"Antwerpen",
    "wof:name":"Tiqilas",
    "wof:placetype":"venue"
},
  "geometry": {"coordinates":[4.6865267754,51.2972640991],"type":"Point"}
}