{
  "type": "Feature",
  "properties": {
    "iso:country":"BE",
    "sg:address":"De Pintelaan 29",
    "sg:city":"Gent",
    "sg:orig_category":"M\u00e9decins and sp\u00e9cialistes",
    "sg:phone":"+32 9 222 05 88",
    "sg:postcode":"9000",
    "sg:province":"Oost-Vlaanderen",
    "wof:name":"A. De Kezel",
    "wof:placetype":"venue"
},
  "geometry": {"coordinates":[3.728276968,51.0296096802],"type":"Point"}
}