{
  "type": "Feature",
  "properties": {
    "addr:full":"Chauss\u00c9e De Hannut 7 Helecine Brabant Wallon 1357",
    "addr:housenumber":"7",
    "addr:postcode":"1357",
    "addr:street":"Chausse\u0301E De Hannut",
    "iso:country":"BE",
    "sg:address":"Chauss\u00c9e De Hannut 7",
    "sg:city":"Helecine",
    "sg:orig_category":"Rev\u00eatements de sols and murs. Jardinage",
    "sg:phone":"+32 19 65 51 38",
    "sg:postcode":"1357",
    "sg:province":"Brabant Wallon",
    "wof:name":"Theunis",
    "wof:placetype":"venue"
},
  "geometry": {"coordinates":[4.9982299805,50.7381896973],"type":"Point"}
}