{
  "type": "Feature",
  "properties": {
    "addr:full":"Overveldstraat 10 Dilbeek (schepdaal) Vlaams-Brabant 1703",
    "addr:housenumber":"10",
    "addr:postcode":"1703",
    "addr:street":"Overveldstraat",
    "iso:country":"BE",
    "sg:address":"Overveldstraat 10",
    "sg:city":"Dilbeek (schepdaal)",
    "sg:classifiers":[
        {
            "category":"Real Estate",
            "subcategory":"Architect",
            "type":"Services"
        }
    ],
    "sg:phone":"+32 2 569 18 93",
    "sg:postcode":"1703",
    "sg:province":"Vlaams-Brabant",
    "wof:name":"Goossens P",
    "wof:placetype":"venue"
},
  "geometry": {"coordinates":[4.1980700493,50.8360786438],"type":"Point"}
}