{
  "type": "Feature",
  "properties": {
    "addr:full":"Basilieklaan 68 Scherpenheuvel-zichem Vlaams-Brabant 3270",
    "addr:housenumber":"68",
    "addr:postcode":"3270",
    "addr:street":"Basilieklaan",
    "iso:country":"BE",
    "sg:address":"Basilieklaan 68",
    "sg:city":"Scherpenheuvel-zichem",
    "sg:orig_category":"Alimentation sp\u00e9cialis\u00e9e",
    "sg:phone":"+32 13 77 71 59",
    "sg:postcode":"3270",
    "sg:province":"Vlaams-Brabant",
    "wof:name":"Bioshop",
    "wof:placetype":"venue"
},
  "geometry": {"coordinates":[4.9728331566,50.9797935486],"type":"Point"}
}