{
  "type": "Feature",
  "properties": {
    "addr:full":"Hekkenstraat 41 Dentergem West-Vlaanderen 8720",
    "addr:housenumber":"41",
    "addr:postcode":"8720",
    "addr:street":"Hekkenstraat",
    "iso:country":"BE",
    "sg:address":"Hekkenstraat 41",
    "sg:city":"Dentergem",
    "sg:orig_category":"Fruitteelt GROENTEN AND FRUIT Pluimveekwekers Varkenskwekers",
    "sg:phone":"+32 56 60 22 28",
    "sg:postcode":"8720",
    "sg:province":"West-Vlaanderen",
    "wof:name":"Gilbert Wolfcarius",
    "wof:placetype":"venue"
},
  "geometry": {"coordinates":[3.4071199894,50.9371528625],"type":"Point"}
}