{
  "type": "Feature",
  "properties": {
    "addr:full":"Van Breestraat 7 Antwerpen Antwerpen 2018",
    "addr:housenumber":"7",
    "addr:postcode":"2018",
    "addr:street":"Van Breestraat",
    "iso:country":"BE",
    "sg:address":"Van Breestraat 7",
    "sg:city":"Antwerpen",
    "sg:orig_category":"Administration d'immeubles. Agences immobili\u00e8res",
    "sg:phone":"+32 3 227 08 05",
    "sg:postcode":"2018",
    "sg:province":"Antwerpen",
    "wof:name":"Zakenkantoor Vastgoed Advies",
    "wof:placetype":"venue"
},
  "geometry": {"coordinates":[4.4100837708,51.2106781006],"type":"Point"}
}