{
  "type": "Feature",
  "properties": {
    "iso:country":"BE",
    "sg:address":"Pilkemseweg 21a",
    "sg:city":"Ieper",
    "sg:classifiers":[
        {
            "category":"Professional",
            "subcategory":"Management & Consulting",
            "type":"Services"
        }
    ],
    "sg:phone":"+32 57 22 09 50",
    "sg:postcode":"8900",
    "sg:province":"West-Vlaanderen",
    "sg:tags":[
        "tax-consultants"
    ],
    "wof:name":"Blanckaert R",
    "wof:placetype":"venue"
},
  "geometry": {"coordinates":[2.8922700882,50.8616600037],"type":"Point"}
}