{
  "type": "Feature",
  "properties": {
    "addr:full":"Rue De La Motte 36 Soignies (thieusies) Hainaut 7061",
    "addr:housenumber":"36",
    "addr:postcode":"7061",
    "addr:street":"Rue De La Motte",
    "iso:country":"BE",
    "sg:address":"Rue De La Motte 36",
    "sg:city":"Soignies (thieusies)",
    "sg:classifiers":[
        {
            "category":"Building & Trades",
            "subcategory":"Landscaping Services",
            "type":"Services"
        }
    ],
    "sg:phone":"+32 65 73 18 70",
    "sg:postcode":"7061",
    "sg:province":"Hainaut",
    "sg:tags":[
        "gardening",
        "garden",
        "maintenance"
    ],
    "wof:name":"Parcs Et Jardins",
    "wof:placetype":"venue"
},
  "geometry": {"coordinates":[4.0133500099,50.5159416199],"type":"Point"}
}