{
  "type": "Feature",
  "properties": {
    "addr:full":"Rue Verte 12 Gouvy Luxembourg 6670",
    "addr:housenumber":"12",
    "addr:postcode":"6670",
    "addr:street":"Rue Verte",
    "iso:country":"BE",
    "sg:address":"Rue Verte 12",
    "sg:city":"Gouvy",
    "sg:orig_category":"Eleveurs de bovins",
    "sg:phone":"+32 80 51 79 85",
    "sg:postcode":"6670",
    "sg:province":"Luxembourg",
    "wof:name":"Rene Toussaint",
    "wof:placetype":"venue"
},
  "geometry": {"coordinates":[5.9401988983,50.1855697632],"type":"Point"}
}