{
  "type": "Feature",
  "properties": {
    "iso:country":"BE",
    "sg:address":"Bosstraat 16",
    "sg:city":"Bocholt",
    "sg:orig_category":"Installation de menuiserie en bois and plastique",
    "sg:phone":"+32 89 46 49 88",
    "sg:postcode":"3950",
    "sg:province":"Limburg",
    "wof:name":"Commerce",
    "wof:placetype":"venue"
},
  "geometry": {"coordinates":[5.5528597832,51.1815605164],"type":"Point"}
}