{
  "type": "Feature",
  "properties": {
    "iso:country":"BE",
    "sg:address":"Rue Jean-haust 32",
    "sg:city":"Li\u00e8ge 1",
    "sg:classifiers":[
        {
            "category":"Health Services",
            "subcategory":"Doctor",
            "type":"Services"
        }
    ],
    "sg:phone":"+32 4 226 14 56",
    "sg:postcode":"4000",
    "sg:province":"Li\u00e8ge",
    "sg:tags":[
        "medicinephysicians",
        "surgeon"
    ],
    "wof:name":"Gugenberger H",
    "wof:placetype":"venue"
},
  "geometry": {"coordinates":[5.5701909065,50.6525268555],"type":"Point"}
}