{
  "type": "Feature",
  "properties": {
    "iso:country":"BE",
    "sg:address":"'t Rode Paard 51",
    "sg:city":"Kortrijk (bellegem)",
    "sg:classifiers":[
        {
            "category":"Building & Trades",
            "subcategory":"Cleaning & Sanitation",
            "type":"Services"
        }
    ],
    "sg:phone":"+32 56 32 83 51",
    "sg:postcode":"8510",
    "sg:province":"West-Vlaanderen",
    "sg:tags":[
        "janitor"
    ],
    "wof:name":"Cleserco",
    "wof:placetype":"venue"
},
  "geometry": {"coordinates":[3.2949399948,50.7839431763],"type":"Point"}
}