{
  "type": "Feature",
  "properties": {
    "iso:country":"BE",
    "sg:address":"Quai De L'ecluse 1",
    "sg:city":"Huy",
    "sg:orig_category":"HUISBRANDOLIE Tuinen",
    "sg:phone":"+32 85 23 68 07",
    "sg:postcode":"4500",
    "sg:province":"Li\u00e8ge",
    "wof:name":"Pascal Feron",
    "wof:placetype":"venue"
},
  "geometry": {"coordinates":[5.1794891357,50.5142593384],"type":"Point"}
}