{
  "type": "Feature",
  "properties": {
    "iso:country":"BE",
    "sg:address":"Avenue De Maire 133",
    "sg:city":"Tournai",
    "sg:classifiers":[
        {
            "category":"Shopping",
            "subcategory":"Bicycles & Sporting Goods",
            "type":"Retail Goods"
        }
    ],
    "sg:phone":"+32 69 22 47 24",
    "sg:postcode":"7500",
    "sg:province":"Hainaut",
    "sg:tags":[
        "tyre"
    ],
    "wof:name":"Tournai-pneu Fiquet Ets",
    "wof:placetype":"venue"
},
  "geometry": {"coordinates":[3.3721170425,50.6190795898],"type":"Point"}
}