{
  "type": "Feature",
  "properties": {
    "addr:full":"Lijnwaadstraat 29 Gent Oost-Vlaanderen 9000",
    "addr:housenumber":"29",
    "addr:postcode":"9000",
    "addr:street":"Lijnwaadstraat;Oost-Vlaanderen",
    "iso:country":"BE",
    "sg:address":"Lijnwaadstraat 29",
    "sg:city":"Gent",
    "sg:orig_category":"Aardappelproducten Gh GROENTEN AND FRUIT Groenten and fruit Gh",
    "sg:phone":"+32 9 226 54 21",
    "sg:postcode":"9000",
    "sg:province":"Oost-Vlaanderen",
    "wof:name":"Albert Boone",
    "wof:placetype":"venue"
},
  "geometry": {"coordinates":[3.6868810654,51.0687141418],"type":"Point"}
}