{
  "type": "Feature",
  "properties": {
    "iso:country":"BE",
    "sg:address":"Lange Boomgaardstraat 88",
    "sg:city":"Gent",
    "sg:orig_category":"M\u00e9decins and sp\u00e9cialistes",
    "sg:phone":"+32 9 233 42 96",
    "sg:postcode":"9000",
    "sg:province":"Oost-Vlaanderen",
    "wof:name":"Ann De Naeyer",
    "wof:placetype":"venue"
},
  "geometry": {"coordinates":[3.7321178913,51.0514717102],"type":"Point"}
}