{
  "type": "Feature",
  "properties": {
    "addr:full":"Rue De La Vall\u00c9e 9 Bassenge Li\u00e8ge 4690",
    "addr:housenumber":"9",
    "addr:postcode":"4690",
    "addr:street":"Rue De La Valle\u0301E",
    "iso:country":"BE",
    "sg:address":"Rue De La Vall\u00c9e 9",
    "sg:city":"Bassenge",
    "sg:orig_category":"M\u00e9decins and sp\u00e9cialistes",
    "sg:phone":"+32 4 286 12 17",
    "sg:postcode":"4690",
    "sg:province":"Li\u00e8ge",
    "wof:name":"P. Bastin",
    "wof:placetype":"venue"
},
  "geometry": {"coordinates":[5.667069912,50.7956008911],"type":"Point"}
}