{
  "type": "Feature",
  "properties": {
    "addr:full":"Eug\u00c8ne Flageyplein 10 Elsene/ixelles Bruxelles-Capitale 1050",
    "addr:housenumber":"10",
    "addr:postcode":"1050",
    "addr:street":"Euge\u0300Ne Flageyplein",
    "iso:country":"BE",
    "sg:address":"Eug\u00c8ne Flageyplein 10",
    "sg:city":"Elsene/ixelles",
    "sg:orig_category":"Cosmetica and toiletartikelen Drogisterijen",
    "sg:phone":"+32 2 648 69 39",
    "sg:postcode":"1050",
    "sg:province":"Bruxelles-Capitale",
    "wof:name":"Di",
    "wof:placetype":"venue"
},
  "geometry": {"coordinates":[4.3715138435,50.8281974792],"type":"Point"}
}