{
  "type": "Feature",
  "properties": {
    "iso:country":"BE",
    "sg:address":"Jules Fr\u00e8relaan 36",
    "sg:city":"Tongeren",
    "sg:classifiers":[
        {
            "category":"Retail",
            "subcategory":"Auto Repair",
            "type":"Services"
        }
    ],
    "sg:phone":"+32 12 24 14 44",
    "sg:postcode":"3700",
    "sg:province":"Limburg",
    "sg:tags":[
        "garage"
    ],
    "wof:name":"Knapen M",
    "wof:placetype":"venue"
},
  "geometry": {"coordinates":[5.4801859856,50.7884674072],"type":"Point"}
}