{
  "type": "Feature",
  "properties": {
    "iso:country":"BE",
    "sg:address":"Taboralaan 216bb",
    "sg:city":"Oostende",
    "sg:orig_category":"Instituts de beaut\u00e9",
    "sg:phone":"+32 59 32 05 35",
    "sg:postcode":"8400",
    "sg:province":"West-Vlaanderen",
    "wof:name":"Dorine Vanpachtenbeke",
    "wof:placetype":"venue"
},
  "geometry": {"coordinates":[2.9126999378,51.2312583923],"type":"Point"}
}