{
  "type": "Feature",
  "properties": {
    "iso:country":"BE",
    "sg:address":"St. Truidensesteenweg 125",
    "sg:city":"Tienen",
    "sg:classifiers":[
        {
            "category":"Autos & Motor Vehicles",
            "subcategory":"Automobile Sales",
            "type":"Retail Goods"
        }
    ],
    "sg:phone":"+32 16 81 11 29",
    "sg:postcode":"3300",
    "sg:province":"Vlaams-Brabant",
    "sg:tags":[
        "qualit\u00e9",
        "ok",
        "automobiles",
        "v\u00e9hicules",
        "occasion",
        "opel"
    ],
    "wof:name":"Garage Debot",
    "wof:placetype":"venue"
},
  "geometry": {"coordinates":[4.9602179527,50.8002662659],"type":"Point"}
}