{
  "type": "Feature",
  "properties": {
    "addr:full":"Schoon Verblijflaan 4 Ukkel Bruxelles-Capitale 1180",
    "addr:housenumber":"4",
    "addr:postcode":"1180",
    "addr:street":"Schoon Verblijflaan",
    "iso:country":"BE",
    "sg:address":"Schoon Verblijflaan 4",
    "sg:city":"Ukkel",
    "sg:orig_category":"Woningbouw",
    "sg:phone":"+32 2 372 01 71",
    "sg:postcode":"1180",
    "sg:province":"Bruxelles-Capitale",
    "wof:name":"H & M Construct",
    "wof:placetype":"venue"
},
  "geometry": {"coordinates":[4.3693919182,50.8096122742],"type":"Point"}
}