{
  "type": "Feature",
  "properties": {
    "iso:country":"BE",
    "sg:address":"Pyckestraat 37",
    "sg:city":"Antwerpen",
    "sg:classifiers":[
        {
            "category":"Professional",
            "subcategory":"Accounting & Tax Preparation",
            "type":"Services"
        }
    ],
    "sg:phone":"+32 3 238 77 51",
    "sg:postcode":"2018",
    "sg:province":"Antwerpen",
    "sg:tags":[
        "accountant"
    ],
    "wof:name":"Accountantskantoor B & M Bvba",
    "wof:placetype":"venue"
},
  "geometry": {"coordinates":[4.3997821808,51.2013511658],"type":"Point"}
}