{
  "type": "Feature",
  "properties": {
    "addr:full":"Rue Hamerenne 29 Rochefort Namur 5580",
    "addr:housenumber":"29",
    "addr:postcode":"5580",
    "addr:street":"Rue Hamerenne",
    "iso:country":"BE",
    "sg:address":"Rue Hamerenne 29",
    "sg:city":"Rochefort",
    "sg:orig_category":"Rundveehouders",
    "sg:phone":"+32 84 21 11 71",
    "sg:postcode":"5580",
    "sg:province":"Namur",
    "wof:name":"Victor Pirotte",
    "wof:placetype":"venue"
},
  "geometry": {"coordinates":[5.2134828568,50.1450119019],"type":"Point"}
}