{
  "type": "Feature",
  "properties": {
    "addr:full":"Chauss\u00c9e De Boondael 360 Elsene/ixelles Bruxelles-Capitale 1050",
    "addr:housenumber":"360",
    "addr:postcode":"1050",
    "addr:street":"Chausse\u0301E De Boondael",
    "iso:country":"BE",
    "sg:address":"Chauss\u00c9e De Boondael 360",
    "sg:city":"Elsene/ixelles",
    "sg:classifiers":[
        {
            "category":"Fast Food",
            "type":"Food & Drink"
        }
    ],
    "sg:phone":"+32 2 649 15 96",
    "sg:postcode":"1050",
    "sg:province":"Bruxelles-Capitale",
    "sg:tags":[
        "\u00c0",
        "restaurants",
        "emporter",
        "restaurant"
    ],
    "wof:name":"Exodus",
    "wof:placetype":"venue"
},
  "geometry": {"coordinates":[4.3858799934,50.8180007935],"type":"Point"}
}