{
  "type": "Feature",
  "properties": {
    "iso:country":"BE",
    "sg:address":"Oosteeklodorp 30",
    "sg:city":"Assenede",
    "sg:orig_category":"Banques and organismes de cr\u00e9dit",
    "sg:phone":"+32 9 373 72 82",
    "sg:postcode":"9968",
    "sg:province":"Oost-Vlaanderen",
    "wof:name":"Ippa",
    "wof:placetype":"venue"
},
  "geometry": {"coordinates":[3.6878700256,51.1917457581],"type":"Point"}
}