{
  "type": "Feature",
  "properties": {
    "addr:full":"Rue Foidart 50 Li\u00e8ge 1 (bressoux) Li\u00e8ge 4020",
    "addr:housenumber":"50;1",
    "addr:postcode":"4020",
    "addr:street":"Rue Foidart",
    "iso:country":"BE",
    "sg:address":"Rue Foidart 50",
    "sg:city":"Li\u00e8ge 1 (bressoux)",
    "sg:classifiers":[
        {
            "category":"Professional",
            "subcategory":"Testing Lab",
            "type":"Services"
        }
    ],
    "sg:phone":"+32 4 343 74 66",
    "sg:postcode":"4020",
    "sg:province":"Li\u00e8ge",
    "sg:tags":[
        "chemist"
    ],
    "wof:name":"Barras B",
    "wof:placetype":"venue"
},
  "geometry": {"coordinates":[5.5975761414,50.6430435181],"type":"Point"}
}