{
  "type": "Feature",
  "properties": {
    "iso:country":"BE",
    "sg:address":"Rue Sur Les Thiers 29",
    "sg:city":"Oreye",
    "sg:orig_category":"Dierenartsen",
    "sg:phone":"+32 19 67 74 14",
    "sg:postcode":"4360",
    "sg:province":"Li\u00e8ge",
    "wof:name":"Christian Paques",
    "wof:placetype":"venue"
},
  "geometry": {"coordinates":[5.3567152023,50.7285881042],"type":"Point"}
}