{
  "type": "Feature",
  "properties": {
    "iso:country":"BE",
    "sg:address":"Kempische Steenweg 519 Box 1",
    "sg:city":"Hasselt",
    "sg:classifiers":[
        {
            "category":"Arts & Performance",
            "subcategory":"Music",
            "type":"Entertainment"
        }
    ],
    "sg:phone":"+32 11 72 95 50",
    "sg:postcode":"3500",
    "sg:province":"Limburg",
    "sg:tags":[
        "freelance",
        "musician"
    ],
    "wof:name":"Wouters J Vof",
    "wof:placetype":"venue"
},
  "geometry": {"coordinates":[5.3410100937,50.9384231567],"type":"Point"}
}