{
  "type": "Feature",
  "properties": {
    "addr:full":"Rue D'hoves 97 Enghien Hainaut 7850",
    "addr:housenumber":"97",
    "addr:postcode":"7850",
    "addr:street":"Rue D'Hoves",
    "iso:country":"BE",
    "sg:address":"Rue D'hoves 97",
    "sg:city":"Enghien",
    "sg:classifiers":[
        {
            "category":"Shopping",
            "subcategory":"Books",
            "type":"Retail Goods"
        }
    ],
    "sg:phone":"+32 2 395 84 63",
    "sg:postcode":"7850",
    "sg:province":"Hainaut",
    "sg:tags":[
        "bookseller"
    ],
    "wof:name":"Potins De La Dodane (les)",
    "wof:placetype":"venue"
},
  "geometry": {"coordinates":[4.0340819359,50.6919670105],"type":"Point"}
}