{
  "type": "Feature",
  "properties": {
    "iso:country":"BE",
    "sg:address":"Koning Albertstraat 33",
    "sg:city":"Hasselt",
    "sg:orig_category":"Disquaires",
    "sg:phone":"+32 11 23 17 05",
    "sg:postcode":"3500",
    "sg:province":"Limburg",
    "wof:name":"Free Record Shop",
    "wof:placetype":"venue"
},
  "geometry": {"coordinates":[5.3364048004,50.9279098511],"type":"Point"}
}