{
  "type": "Feature",
  "properties": {
    "addr:full":"Landwaartslaan 68 Genk Limburg 3600",
    "addr:housenumber":"68",
    "addr:postcode":"3600",
    "addr:street":"Landwaartslaan",
    "iso:country":"BE",
    "sg:address":"Landwaartslaan 68",
    "sg:city":"Genk",
    "sg:orig_category":"Newspapers, magazines, periodicals - Distribution",
    "sg:phone":"+32 89 35 69 13",
    "sg:postcode":"3600",
    "sg:province":"Limburg",
    "wof:name":"Nadia",
    "wof:placetype":"venue"
},
  "geometry": {"coordinates":[5.4494390488,50.9672698975],"type":"Point"}
}