{
  "type": "Feature",
  "properties": {
    "iso:country":"BE",
    "sg:address":"Opperstraat 78",
    "sg:city":"Nieuwerkerken",
    "sg:orig_category":"Sportclubs Sportterreinen and installaties behalve sportcentra",
    "sg:phone":"+32 11 31 48 62",
    "sg:postcode":"3850",
    "sg:province":"Limburg",
    "wof:name":"F.c. Aman Schakkebroek",
    "wof:placetype":"venue"
},
  "geometry": {"coordinates":[5.2145681381,50.8929405212],"type":"Point"}
}