{
  "type": "Feature",
  "properties": {
    "addr:full":"Muizelaarstraat 27bb Pittem West-Vlaanderen 8740",
    "addr:housenumber":"27bb",
    "addr:postcode":"8740",
    "addr:street":"Muizelaarstraat",
    "iso:country":"BE",
    "sg:address":"Muizelaarstraat 27bb",
    "sg:city":"Pittem",
    "sg:orig_category":"Groententeelt",
    "sg:phone":"+32 51 46 65 44",
    "sg:postcode":"8740",
    "sg:province":"West-Vlaanderen",
    "wof:name":"Dirk Biesbrouck",
    "wof:placetype":"venue"
},
  "geometry": {"coordinates":[3.2490200996,50.9728088379],"type":"Point"}
}