{
  "type": "Feature",
  "properties": {
    "iso:country":"BE",
    "sg:address":"Aarschotseweg 16",
    "sg:city":"Herentals",
    "sg:classifiers":[
        {
            "category":"Autos & Motor Vehicles",
            "subcategory":"Auto Supplies",
            "type":"Retail Goods"
        }
    ],
    "sg:phone":"+32 14 22 00 63",
    "sg:postcode":"2200",
    "sg:province":"Antwerpen",
    "sg:tags":[
        "access",
        "automobile",
        "part",
        "-"
    ],
    "wof:name":"Van Looy Nv",
    "wof:placetype":"venue"
},
  "geometry": {"coordinates":[4.8470478058,51.1670227051],"type":"Point"}
}