{
  "type": "Feature",
  "properties": {
    "addr:full":"Rue Henri-vieuxtemps 4 Box 1 Li\u00e8ge 1 Li\u00e8ge 4000",
    "addr:housenumber":"4;1;1",
    "addr:postcode":"4000",
    "addr:street":"Rue Henri-Vieuxtemps;Box",
    "iso:country":"BE",
    "sg:address":"Rue Henri-vieuxtemps 4 Box 1",
    "sg:city":"Li\u00e8ge 1",
    "sg:classifiers":[
        {
            "category":"Health Services",
            "subcategory":"Doctor",
            "type":"Services"
        }
    ],
    "sg:phone":"+32 4 226 88 50",
    "sg:postcode":"4000",
    "sg:province":"Li\u00e8ge",
    "sg:tags":[
        "medicinephysicians",
        "surgeon"
    ],
    "wof:name":"Bologne Richard",
    "wof:placetype":"venue"
},
  "geometry": {"coordinates":[5.5633602142,50.6480445862],"type":"Point"}
}