{
  "type": "Feature",
  "properties": {
    "iso:country":"BE",
    "sg:address":"Rue Heuschen 3",
    "sg:city":"Welkenraedt",
    "sg:classifiers":[
        {
            "category":"Personal",
            "subcategory":"Beauty Salon",
            "type":"Services"
        }
    ],
    "sg:phone":"+32 87 88 21 65",
    "sg:postcode":"4840",
    "sg:province":"Li\u00e8ge",
    "sg:tags":[
        "de",
        "coiffure"
    ],
    "wof:name":"Coiffure Brigitte",
    "wof:placetype":"venue"
},
  "geometry": {"coordinates":[5.9631500244,50.658241272],"type":"Point"}
}