{
  "type": "Feature",
  "properties": {
    "addr:full":"Avenue Emile Van Becelaere 24b Bruxelles (watermael-boitsfort) Bruxelles-Capitale 1170",
    "addr:housenumber":"24b",
    "addr:postcode":"1170",
    "addr:street":"Avenue Emile Van Becelaere",
    "iso:country":"BE",
    "sg:address":"Avenue Emile Van Becelaere 24b",
    "sg:city":"Bruxelles (watermael-boitsfort)",
    "sg:classifiers":[
        {
            "category":"Structure",
            "subcategory":"Office Building",
            "type":"Public Place"
        }
    ],
    "sg:phone":"+32 2 675 11 71",
    "sg:postcode":"1170",
    "sg:province":"Bruxelles-Capitale",
    "sg:tags":[
        "drawing"
    ],
    "wof:name":"Servais F",
    "wof:placetype":"venue"
},
  "geometry": {"coordinates":[4.4061560631,50.7983093262],"type":"Point"}
}