{
  "type": "Feature",
  "properties": {
    "addr:full":"Rue De La Bruy\u00c8re 62 Sambreville Namur 5060",
    "addr:housenumber":"62",
    "addr:postcode":"5060",
    "addr:street":"Rue De La Bruye\u0300Re",
    "iso:country":"BE",
    "sg:address":"Rue De La Bruy\u00c8re 62",
    "sg:city":"Sambreville",
    "sg:classifiers":[
        {
            "category":"Insurance",
            "subcategory":"Life Insurance",
            "type":"Services"
        }
    ],
    "sg:phone":"+32 71 77 35 41",
    "sg:postcode":"5060",
    "sg:province":"Namur",
    "sg:tags":[
        "assurance"
    ],
    "wof:name":"Fays Vincent",
    "wof:placetype":"venue"
},
  "geometry": {"coordinates":[4.6329808235,50.4382400513],"type":"Point"}
}