{
  "type": "Feature",
  "properties": {
    "iso:country":"BE",
    "sg:address":"Rue D'angleterre 10",
    "sg:city":"Charleroi",
    "sg:classifiers":[
        {
            "category":"Social Services",
            "type":"Services"
        }
    ],
    "sg:phone":"+32 71 30 26 56",
    "sg:postcode":"6000",
    "sg:province":"Hainaut",
    "wof:name":"Carolo Contact Drogue",
    "wof:placetype":"venue"
},
  "geometry": {"coordinates":[4.4443669319,50.4160881042],"type":"Point"}
}