{
  "type": "Feature",
  "properties": {
    "iso:country":"BE",
    "sg:address":"Jourdanstraat 189",
    "sg:city":"Sint-gillis/saint-gilles",
    "sg:orig_category":"Brood, gebak and snoepgoed",
    "sg:phone":"+32 2 537 62 35",
    "sg:postcode":"1060",
    "sg:province":"Bruxelles-Capitale",
    "wof:name":"P\u00c2tisserie Olmos",
    "wof:placetype":"venue"
},
  "geometry": {"coordinates":[4.3467111588,50.8311729431],"type":"Point"}
}