{
  "type": "Feature",
  "properties": {
    "iso:country":"BE",
    "sg:address":"Netestraat 49",
    "sg:city":"Rumst",
    "sg:classifiers":[
        {
            "category":"Retail",
            "subcategory":"Event Space",
            "type":"Services"
        }
    ],
    "sg:phone":"+32 15 31 79 54",
    "sg:postcode":"2840",
    "sg:province":"Antwerpen",
    "sg:tags":[
        "organisation"
    ],
    "wof:name":"Inside & Outdoor",
    "wof:placetype":"venue"
},
  "geometry": {"coordinates":[4.4512448311,51.0767250061],"type":"Point"}
}