{
  "type": "Feature",
  "properties": {
    "addr:full":"Grotestraat 20 Geraardsbergen Oost-Vlaanderen 9500",
    "addr:housenumber":"20",
    "addr:postcode":"9500",
    "addr:street":"Grotestraat",
    "iso:country":"BE",
    "sg:address":"Grotestraat 20",
    "sg:city":"Geraardsbergen",
    "sg:orig_category":"Bijouteries and horlogeries. R\u00e9parations d'horloges, montres and bijoux",
    "sg:phone":"+32 54 41 94 47",
    "sg:postcode":"9500",
    "sg:province":"Oost-Vlaanderen",
    "wof:name":"Huis Solluna",
    "wof:placetype":"venue"
},
  "geometry": {"coordinates":[3.8790130615,50.7716331482],"type":"Point"}
}