{
  "type": "Feature",
  "properties": {
    "addr:full":"Elderenstraat 133 Tongeren Limburg 3700",
    "addr:housenumber":"133",
    "addr:postcode":"3700",
    "addr:street":"Elderenstraat",
    "iso:country":"BE",
    "sg:address":"Elderenstraat 133",
    "sg:city":"Tongeren",
    "sg:classifiers":[
        {
            "category":"Restaurant",
            "type":"Food & Drink"
        }
    ],
    "sg:phone":"+32 12 23 43 18",
    "sg:postcode":"3700",
    "sg:province":"Limburg",
    "sg:tags":[
        "caf\u00e9s",
        "h\u00f4tels"
    ],
    "wof:name":"Hotel Bavershof",
    "wof:placetype":"venue"
},
  "geometry": {"coordinates":[5.5129652023,50.817615509],"type":"Point"}
}