{
  "type": "Feature",
  "properties": {
    "addr:full":"Rue De Bouillon 33 Beauraing Namur 5570",
    "addr:housenumber":"33",
    "addr:postcode":"5570",
    "addr:street":"Rue De Bouillon",
    "iso:country":"BE",
    "sg:address":"Rue De Bouillon 33",
    "sg:city":"Beauraing",
    "sg:orig_category":"Schoenen",
    "sg:phone":"+32 82 71 15 05",
    "sg:postcode":"5570",
    "sg:province":"Namur",
    "wof:name":"Chaussures Gremo",
    "wof:placetype":"venue"
},
  "geometry": {"coordinates":[4.9568581581,50.1092147827],"type":"Point"}
}