{
  "type": "Feature",
  "properties": {
    "addr:full":"Avenue De Roodebeek 65 Schaarbeek/schaerbeek Bruxelles-Capitale 1030",
    "addr:housenumber":"65",
    "addr:postcode":"1030",
    "addr:street":"Avenue De Roodebeek",
    "iso:country":"BE",
    "sg:address":"Avenue De Roodebeek 65",
    "sg:city":"Schaarbeek/schaerbeek",
    "sg:orig_category":"Plomberie, chauffage and installations sanitaires",
    "sg:phone":"+32 2 733 20 40",
    "sg:postcode":"1030",
    "sg:province":"Bruxelles-Capitale",
    "wof:name":"Van Saet Sanitaire",
    "wof:placetype":"venue"
},
  "geometry": {"coordinates":[4.3985180855,50.8479766846],"type":"Point"}
}