{
  "type": "Feature",
  "properties": {
    "addr:full":"Sparrenstraat 21 Zulte Oost-Vlaanderen 9870",
    "addr:housenumber":"21",
    "addr:postcode":"9870",
    "addr:street":"Sparrenstraat",
    "iso:country":"BE",
    "sg:address":"Sparrenstraat 21",
    "sg:city":"Zulte",
    "sg:classifiers":[
        {
            "category":"Home & Garden",
            "subcategory":"Hardware",
            "type":"Retail Goods"
        }
    ],
    "sg:phone":"+32 9 386 33 01",
    "sg:postcode":"9870",
    "sg:province":"Oost-Vlaanderen",
    "sg:tags":[
        "quincailleries",
        "bois",
        "gr"
    ],
    "wof:name":"Etienne Moncarey",
    "wof:placetype":"venue"
},
  "geometry": {"coordinates":[3.5081520081,50.9423294067],"type":"Point"}
}