{
  "type": "Feature",
  "properties": {
    "addr:full":"Rue Jean Ekelmans 10 Bruxelles (auderghem) Bruxelles-Capitale 1160",
    "addr:housenumber":"10",
    "addr:postcode":"1160",
    "addr:street":"Rue Jean Ekelmans",
    "iso:country":"BE",
    "sg:address":"Rue Jean Ekelmans 10",
    "sg:city":"Bruxelles (auderghem)",
    "sg:classifiers":[
        {
            "category":"Building & Trades",
            "subcategory":"Plumbing",
            "type":"Services"
        }
    ],
    "sg:phone":"+32 2 660 67 11",
    "sg:postcode":"1160",
    "sg:province":"Bruxelles-Capitale",
    "sg:tags":[
        "contractor"
    ],
    "wof:name":"Assenmaker G",
    "wof:placetype":"venue"
},
  "geometry": {"coordinates":[4.4325819016,50.806854248],"type":"Point"}
}