{
  "type": "Feature",
  "properties": {
    "addr:full":"Portugiezenstraat 28 Laarne Oost-Vlaanderen 9270",
    "addr:housenumber":"28",
    "addr:postcode":"9270",
    "addr:street":"Portugiezenstraat",
    "iso:country":"BE",
    "sg:address":"Portugiezenstraat 28",
    "sg:city":"Laarne",
    "sg:orig_category":"Eleveurs de bovins",
    "sg:phone":"+32 9 367 62 84",
    "sg:postcode":"9270",
    "sg:province":"Oost-Vlaanderen",
    "wof:name":"Van Peteghem Armand Remie",
    "wof:placetype":"venue"
},
  "geometry": {"coordinates":[3.9182789326,51.0612602234],"type":"Point"}
}