{
  "type": "Feature",
  "properties": {
    "addr:full":"So L\u00c8s Beurs 3 Anthisnes Li\u00e8ge 4160",
    "addr:housenumber":"3",
    "addr:postcode":"4160",
    "addr:street":"Beurs",
    "iso:country":"BE",
    "sg:address":"So L\u00c8s Beurs 3",
    "sg:city":"Anthisnes",
    "sg:orig_category":"Airconditioning and ventilatie Dakwerken Loodgieterij, verwarming and sanitaire installaties",
    "sg:phone":"+32 4 383 66 64",
    "sg:postcode":"4160",
    "sg:province":"Li\u00e8ge",
    "wof:name":"D.l.p.",
    "wof:placetype":"venue"
},
  "geometry": {"coordinates":[5.5192217827,50.4733963013],"type":"Point"}
}