{
  "type": "Feature",
  "properties": {
    "addr:full":"Avenue De L\u00b4argoat 9 Lasne Brabant Wallon 1380",
    "addr:housenumber":"9",
    "addr:postcode":"1380",
    "addr:street":"Avenue De L\u00b4Argoat",
    "iso:country":"BE",
    "sg:address":"Avenue De L\u00b4argoat 9",
    "sg:city":"Lasne",
    "sg:classifiers":[
        {
            "category":"Farming",
            "subcategory":"Fish & Marine Products",
            "type":"Manufacturing & Wholesale Goods"
        }
    ],
    "sg:phone":"+32 2 633 31 39",
    "sg:postcode":"1380",
    "sg:province":"Brabant Wallon",
    "sg:tags":[
        "schaaldierenkwekers",
        "vis-"
    ],
    "wof:name":"Piscicult.belg.anguilles",
    "wof:placetype":"venue"
},
  "geometry": {"coordinates":[4.483235836,50.6850166321],"type":"Point"}
}