{
  "type": "Feature",
  "properties": {
    "iso:country":"BE",
    "sg:address":"Turnhoutsebaan 5",
    "sg:city":"Wijnegem",
    "sg:orig_category":"Packard Bell Nec. Disquaires. Ordinateurs and \u00e9quipement informatique. Librairies. Equipement photog",
    "sg:phone":"+32 3 355 22 00",
    "sg:postcode":"2110",
    "sg:province":"Antwerpen",
    "wof:name":"Fnac Wijnegem",
    "wof:placetype":"venue"
},
  "geometry": {"coordinates":[4.5043401718,51.2240219116],"type":"Point"}
}