{
  "type": "Feature",
  "properties": {
    "iso:country":"BE",
    "sg:address":"Lippenslaan 261",
    "sg:city":"Knokke-heist",
    "sg:orig_category":"Diverse kredietdiensten",
    "sg:postcode":"8300",
    "sg:province":"West-Vlaanderen",
    "wof:name":"Bancontact-mister Cash",
    "wof:placetype":"venue"
},
  "geometry": {"coordinates":[3.2882900238,51.3466911316],"type":"Point"}
}