{
  "type": "Feature",
  "properties": {
    "iso:country":"BE",
    "sg:address":"Rue Neuve 2-4",
    "sg:city":"Peruwelz",
    "sg:orig_category":"Pr\u00eats hypoth\u00e9caires and cr\u00e9dits immobiliers. Cr\u00e9dit \u00e0 la consommation",
    "sg:phone":"+32 69 77 25 29",
    "sg:postcode":"7601",
    "sg:province":"Hainaut",
    "wof:name":"Entr. Financ. Tournaisis",
    "wof:placetype":"venue"
},
  "geometry": {"coordinates":[3.587567091,50.5271263123],"type":"Point"}
}