{
  "type": "Feature",
  "properties": {
    "iso:country":"BE",
    "sg:address":"Volpestraat 30-32",
    "sg:city":"Halle",
    "sg:classifiers":[
        {
            "category":"Communications",
            "subcategory":"Newspaper",
            "type":"Services"
        }
    ],
    "sg:phone":"+32 2 365 04 11",
    "sg:postcode":"1500",
    "sg:province":"Vlaams-Brabant",
    "sg:tags":[
        "paper",
        "local",
        "free"
    ],
    "wof:name":"Zondag (de)",
    "wof:placetype":"venue"
},
  "geometry": {"coordinates":[4.2345600128,50.7358779907],"type":"Point"}
}