{
  "type": "Feature",
  "properties": {
    "iso:country":"BE",
    "sg:address":"Jan Hammeneckerstraat 141",
    "sg:city":"Bornem",
    "sg:classifiers":[
        {
            "category":"Fast Food",
            "type":"Food & Drink"
        }
    ],
    "sg:phone":"+32 52 33 22 89",
    "sg:postcode":"2880",
    "sg:province":"Antwerpen",
    "sg:tags":[
        "meeneem",
        "restaurant"
    ],
    "wof:name":"De Ster",
    "wof:placetype":"venue"
},
  "geometry": {"coordinates":[4.2006850243,51.0604667664],"type":"Point"}
}