{
  "type": "Feature",
  "properties": {
    "iso:country":"BE",
    "sg:address":"Schrieksebaan 36",
    "sg:city":"Tremelo",
    "sg:classifiers":[
        {
            "category":"Retail",
            "subcategory":"Repair Shop",
            "type":"Services"
        }
    ],
    "sg:phone":"+32 16 53 12 28",
    "sg:postcode":"3120",
    "sg:province":"Vlaams-Brabant",
    "sg:tags":[
        "-",
        "mainten",
        "watch",
        "clock"
    ],
    "wof:name":"Van Dyck Jef Bvba",
    "wof:placetype":"venue"
},
  "geometry": {"coordinates":[4.7065749168,50.9928588867],"type":"Point"}
}