{
  "type": "Feature",
  "properties": {
    "addr:full":"Rue Neuve Chauss\u00e9e 92 P\u00e9ruwelz Hainaut 7600",
    "addr:housenumber":"92",
    "addr:postcode":"7600",
    "addr:street":"Rue;Chausse\u0301E",
    "iso:country":"BE",
    "sg:address":"Rue Neuve Chauss\u00e9e 92",
    "sg:city":"P\u00e9ruwelz",
    "sg:classifiers":[
        {
            "category":"Home & Garden",
            "subcategory":"Carpets & Floor Coverings",
            "type":"Retail Goods"
        }
    ],
    "sg:phone":"+32 69 77 51 25",
    "sg:postcode":"7600",
    "sg:province":"Hainaut",
    "sg:tags":[
        "delivery",
        "-",
        "van"
    ],
    "wof:name":"Carlier M & Fils",
    "wof:placetype":"venue"
},
  "geometry": {"coordinates":[3.6011490822,50.5231704712],"type":"Point"}
}