{
  "type": "Feature",
  "properties": {
    "addr:full":"Rue Des Maraichers 122 Li\u00c8ge Li\u00e8ge 4020",
    "addr:housenumber":"122",
    "addr:postcode":"4020",
    "addr:street":"Rue Des Maraichers",
    "iso:country":"BE",
    "sg:address":"Rue Des Maraichers 122",
    "sg:city":"Li\u00c8ge",
    "sg:orig_category":"Kapsalons",
    "sg:phone":"+32 4 342 87 77",
    "sg:postcode":"4020",
    "sg:province":"Li\u00e8ge",
    "wof:name":"Coiffure La Farandole",
    "wof:placetype":"venue"
},
  "geometry": {"coordinates":[5.5958690643,50.6382980347],"type":"Point"}
}