{
  "type": "Feature",
  "properties": {
    "addr:full":"Champ Des Dames 11 Vielsalm (bihain) Luxembourg 6690",
    "addr:housenumber":"11",
    "addr:postcode":"6690",
    "addr:street":"Champ Des Dames",
    "iso:country":"BE",
    "sg:address":"Champ Des Dames 11",
    "sg:city":"Vielsalm (bihain)",
    "sg:classifiers":[
        {
            "category":"Professional",
            "subcategory":"Art Services",
            "type":"Services"
        }
    ],
    "sg:phone":"+32 80 21 49 54",
    "sg:postcode":"6690",
    "sg:province":"Luxembourg",
    "sg:tags":[
        "graphic",
        "designer"
    ],
    "wof:name":"Blanchy M",
    "wof:placetype":"venue"
},
  "geometry": {"coordinates":[5.9002261162,50.26612854],"type":"Point"}
}