{
  "type": "Feature",
  "properties": {
    "addr:full":"Oude Waversebaan 118 Huldenberg Vlaams-Brabant 3040",
    "addr:housenumber":"118",
    "addr:postcode":"3040",
    "addr:street":"Oude Waversebaan",
    "iso:country":"BE",
    "sg:address":"Oude Waversebaan 118",
    "sg:city":"Huldenberg",
    "sg:orig_category":"Alternatieve geneeskunde",
    "sg:phone":"+32 16 47 01 54",
    "sg:postcode":"3040",
    "sg:province":"Vlaams-Brabant",
    "wof:name":"Christine Tobback",
    "wof:placetype":"venue"
},
  "geometry": {"coordinates":[4.6274399757,50.7764396667],"type":"Point"}
}