{
  "type": "Feature",
  "properties": {
    "addr:full":"Rue Le Campinaire 291 Farciennes Hainaut 6240",
    "addr:housenumber":"291",
    "addr:postcode":"6240",
    "addr:street":"Rue Le Campinaire",
    "iso:country":"BE",
    "sg:address":"Rue Le Campinaire 291",
    "sg:city":"Farciennes",
    "sg:orig_category":"Kapsalons",
    "sg:phone":"+32 71 38 86 11",
    "sg:postcode":"6240",
    "sg:province":"Hainaut",
    "wof:name":"Claudio Venturi",
    "wof:placetype":"venue"
},
  "geometry": {"coordinates":[4.5338110924,50.4366722107],"type":"Point"}
}