{
  "type": "Feature",
  "properties": {
    "addr:full":"Rue Des Sorbiers 19 Namur (erpent) Namur 5101",
    "addr:housenumber":"19",
    "addr:postcode":"5101",
    "addr:street":"Rue Des Sorbiers",
    "iso:country":"BE",
    "sg:address":"Rue Des Sorbiers 19",
    "sg:city":"Namur (erpent)",
    "sg:classifiers":[
        {
            "category":"Professional",
            "subcategory":"Engineering",
            "type":"Services"
        }
    ],
    "sg:phone":"+32 81 30 77 85",
    "sg:postcode":"5101",
    "sg:province":"Namur",
    "sg:tags":[
        "technical",
        "equipment",
        "offices-"
    ],
    "wof:name":"Engineering And Management",
    "wof:placetype":"venue"
},
  "geometry": {"coordinates":[4.903840065,50.4547958374],"type":"Point"}
}