{
  "type": "Feature",
  "properties": {
    "addr:full":"Nieuwenhovestraat 6 Waregem West-Vlaanderen 8790",
    "addr:housenumber":"6",
    "addr:postcode":"8790",
    "addr:street":"Nieuwenhovestraat",
    "iso:country":"BE",
    "sg:address":"Nieuwenhovestraat 6",
    "sg:city":"Waregem",
    "sg:orig_category":"Schoonmaakbedrijven and ongediertebestrijding",
    "sg:phone":"+32 56 61 41 21",
    "sg:postcode":"8790",
    "sg:province":"West-Vlaanderen",
    "wof:name":"A.c.a. Cleaning",
    "wof:placetype":"venue"
},
  "geometry": {"coordinates":[3.398225069,50.8666534424],"type":"Point"}
}