{
  "type": "Feature",
  "properties": {
    "addr:full":"Deidenberg 106 Amel Li\u00e8ge 4770",
    "addr:housenumber":"106",
    "addr:postcode":"4770",
    "addr:street":"Deidenberg",
    "iso:country":"BE",
    "sg:address":"Deidenberg 106",
    "sg:city":"Amel",
    "sg:classifiers":[
        {
            "category":"Retail",
            "subcategory":"Auto Repair",
            "type":"Services"
        }
    ],
    "sg:phone":"+32 80 34 98 19",
    "sg:postcode":"4770",
    "sg:province":"Li\u00e8ge",
    "sg:tags":[
        "garage"
    ],
    "wof:name":"Arens P",
    "wof:placetype":"venue"
},
  "geometry": {"coordinates":[6.1512641907,50.3556022644],"type":"Point"}
}