{
  "type": "Feature",
  "properties": {
    "addr:full":"Langblookstraat 10 Zutendaal Limburg 3690",
    "addr:housenumber":"10",
    "addr:postcode":"3690",
    "addr:street":"Langblookstraat",
    "iso:country":"BE",
    "sg:address":"Langblookstraat 10",
    "sg:city":"Zutendaal",
    "sg:classifiers":[
        {
            "category":"Building & Trades",
            "subcategory":"Electrical",
            "type":"Services"
        }
    ],
    "sg:phone":"+32 89 61 21 86",
    "sg:postcode":"3690",
    "sg:province":"Limburg",
    "sg:tags":[
        "electric",
        "-",
        "housewiring",
        "contractor"
    ],
    "wof:name":"Beuls D",
    "wof:placetype":"venue"
},
  "geometry": {"coordinates":[5.5504908562,50.951084137],"type":"Point"}
}