{
  "type": "Feature",
  "properties": {
    "iso:country":"BE",
    "sg:address":"Beekstraat 1",
    "sg:city":"Borgloon",
    "sg:orig_category":"Fruitteelt",
    "sg:phone":"+32 12 74 16 75",
    "sg:postcode":"3840",
    "sg:province":"Limburg",
    "wof:name":"Koen Neven",
    "wof:placetype":"venue"
},
  "geometry": {"coordinates":[5.286260128,50.8112564087],"type":"Point"}
}