{
  "type": "Feature",
  "properties": {
    "iso:country":"BE",
    "sg:address":"Place Ferrer 13",
    "sg:city":"Soumagne",
    "sg:classifiers":[
        {
            "category":"Manufacturing",
            "subcategory":"Tools & Machinery",
            "type":"Manufacturing & Wholesale Goods"
        }
    ],
    "sg:phone":"+32 4 377 11 49",
    "sg:postcode":"4630",
    "sg:province":"Li\u00e8ge",
    "sg:tags":[
        "builder"
    ],
    "wof:name":"Laval Smp Sprl",
    "wof:placetype":"venue"
},
  "geometry": {"coordinates":[5.7481861115,50.6116676331],"type":"Point"}
}