{
  "type": "Feature",
  "properties": {
    "addr:full":"Chauss\u00e9e De Ramet 44 Fl\u00e9malle (ivoz-ramet) Li\u00e8ge 4400",
    "addr:housenumber":"44",
    "addr:postcode":"4400",
    "addr:street":"Chausse\u0301E De Ramet;Ivoz-Ramet",
    "iso:country":"BE",
    "sg:address":"Chauss\u00e9e De Ramet 44",
    "sg:city":"Fl\u00e9malle (ivoz-ramet)",
    "sg:classifiers":[
        {
            "category":"Professional",
            "subcategory":"Computer Services",
            "type":"Services"
        }
    ],
    "sg:phone":"+32 4 330 97 81",
    "sg:postcode":"4400",
    "sg:province":"Li\u00e8ge",
    "sg:tags":[
        "-",
        "processing",
        "data",
        "software"
    ],
    "wof:name":"Art-alia",
    "wof:placetype":"venue"
},
  "geometry": {"coordinates":[5.4603381157,50.5874443054],"type":"Point"}
}