{
  "type": "Feature",
  "properties": {
    "iso:country":"BE",
    "sg:address":"Rue De Valenciennes 90",
    "sg:city":"Qui\u00c9vrain",
    "sg:orig_category":"Sportclubs",
    "sg:phone":"+32 65 45 81 99",
    "sg:postcode":"7380",
    "sg:province":"Hainaut",
    "wof:name":"Bbc Les Gaulois Quievrain",
    "wof:placetype":"venue"
},
  "geometry": {"coordinates":[3.677054882,50.4041366577],"type":"Point"}
}