{
  "type": "Feature",
  "properties": {
    "iso:country":"BE",
    "sg:address":"Rue Wayez 11",
    "sg:city":"Anderlecht",
    "sg:classifiers":[
        {
            "category":"Insurance",
            "subcategory":"Life Insurance",
            "type":"Services"
        }
    ],
    "sg:phone":"+32 2 521 75 74",
    "sg:postcode":"1070",
    "sg:province":"Bruxelles-Capitale",
    "sg:tags":[
        "assurance"
    ],
    "wof:name":"Bougelet & Cie",
    "wof:placetype":"venue"
},
  "geometry": {"coordinates":[4.3166022301,50.8366127014],"type":"Point"}
}