{
  "type": "Feature",
  "properties": {
    "iso:country":"BE",
    "sg:address":"Opperstraat 250",
    "sg:city":"Liedekerke",
    "sg:classifiers":[
        {
            "category":"Personal",
            "subcategory":"Beauty Salon",
            "type":"Services"
        }
    ],
    "sg:phone":"+32 53 68 26 68",
    "sg:postcode":"1770",
    "sg:province":"Vlaams-Brabant",
    "sg:tags":[
        "equipment",
        "hairdressing",
        "-",
        "supply"
    ],
    "wof:name":"De Haarshop",
    "wof:placetype":"venue"
},
  "geometry": {"coordinates":[4.0964021683,50.8674850464],"type":"Point"}
}