{
  "type": "Feature",
  "properties": {
    "addr:full":"Rue Mab\u00eeme 41 Ans (alleur) Li\u00e8ge 4432",
    "addr:housenumber":"41",
    "addr:postcode":"4432",
    "addr:street":"Rue Mabi\u0302Me",
    "iso:country":"BE",
    "sg:address":"Rue Mab\u00eeme 41",
    "sg:city":"Ans (alleur)",
    "sg:orig_category":"Non-Classified Establishments",
    "sg:phone":"+32 4 247 56 99",
    "sg:postcode":"4432",
    "sg:province":"Li\u00e8ge",
    "wof:name":"Bergen P",
    "wof:placetype":"venue"
},
  "geometry": {"coordinates":[5.5210242271,50.670375824],"type":"Point"}
}