{
  "type": "Feature",
  "properties": {
    "addr:full":"Rue De La Source 3 Wavre Brabant Wallon 1300",
    "addr:housenumber":"3;1300",
    "addr:street":"Rue De La Source",
    "iso:country":"BE",
    "sg:address":"Rue De La Source 3",
    "sg:city":"Wavre",
    "sg:classifiers":[
        {
            "category":"Cafe",
            "type":"Food & Drink"
        }
    ],
    "sg:phone":"+32 10 24 47 03",
    "sg:postcode":"1300",
    "sg:province":"Brabant Wallon",
    "sg:tags":[
        "snack-bars"
    ],
    "wof:name":"3i\u00e8me Oeil (le)",
    "wof:placetype":"venue"
},
  "geometry": {"coordinates":[4.6108851433,50.7160758972],"type":"Point"}
}