{
  "type": "Feature",
  "properties": {
    "addr:full":"4000 Rocourt Li\u00e8ge 4000",
    "addr:postcode":"4000;4000",
    "iso:country":"BE",
    "sg:address":"4000",
    "sg:city":"Rocourt",
    "sg:orig_category":"Huisdieren and benodigdheden Tuinen Zwembadinstallatie",
    "sg:phone":"+32 475 49 58 65",
    "sg:postcode":"4000",
    "sg:province":"Li\u00e8ge",
    "wof:name":"Envitech & Co",
    "wof:placetype":"venue"
},
  "geometry": {"coordinates":[5.5473198891,50.6792297363],"type":"Point"}
}