{
  "type": "Feature",
  "properties": {
    "addr:full":"Avenue De Tervueren 182 Sint-pieters-woluwe/woluwe-saint-pierre Bruxelles-Capitale 1150",
    "addr:housenumber":"182",
    "addr:postcode":"1150",
    "addr:street":"Avenue De Tervueren;/",
    "iso:country":"BE",
    "sg:address":"Avenue De Tervueren 182",
    "sg:city":"Sint-pieters-woluwe/woluwe-saint-pierre",
    "sg:orig_category":"Editeurs de journaux. Editeurs de revues and p\u00e9riodiques",
    "sg:phone":"+32 2 775 80 69",
    "sg:postcode":"1150",
    "sg:province":"Bruxelles-Capitale",
    "wof:name":"La Sucrerie Belge",
    "wof:placetype":"venue"
},
  "geometry": {"coordinates":[4.4110479355,50.8370742798],"type":"Point"}
}