{
  "type": "Feature",
  "properties": {
    "addr:full":"Ardooisesteenweg 83 Roeselare West-Vlaanderen 8800",
    "addr:housenumber":"83",
    "addr:postcode":"8800",
    "addr:street":"Ardooisesteenweg",
    "iso:country":"BE",
    "sg:address":"Ardooisesteenweg 83",
    "sg:city":"Roeselare",
    "sg:classifiers":[
        {
            "category":"Health Services",
            "subcategory":"Health Practitioner",
            "type":"Services"
        }
    ],
    "sg:phone":"+32 51 24 61 59",
    "sg:postcode":"8800",
    "sg:province":"West-Vlaanderen",
    "sg:tags":[
        "therapist",
        "speech"
    ],
    "wof:name":"Houthoofd S",
    "wof:placetype":"venue"
},
  "geometry": {"coordinates":[3.1340019703,50.9504013062],"type":"Point"}
}