{
  "type": "Feature",
  "properties": {
    "iso:country":"BE",
    "sg:address":"Avenue Du Bois Imp\u00c9rial De Rognac 37",
    "sg:city":"Neupre",
    "sg:orig_category":"Diverse bouwafwerking and reiniging Gespecialiseerde residenti\u00eble bouw Woningbouw",
    "sg:phone":"+32 4 371 23 22",
    "sg:postcode":"4121",
    "sg:province":"Li\u00e8ge",
    "wof:name":"Mirsic",
    "wof:placetype":"venue"
},
  "geometry": {"coordinates":[5.4884619713,50.5435295105],"type":"Point"}
}