{
  "type": "Feature",
  "properties": {
    "addr:full":"J.f. Vincklaan 11 Wuustwezel Antwerpen 2990",
    "addr:housenumber":"11",
    "addr:postcode":"2990",
    "addr:street":"J.F. Vincklaan",
    "iso:country":"BE",
    "sg:address":"J.f. Vincklaan 11",
    "sg:city":"Wuustwezel",
    "sg:orig_category":"Peinture. Rev\u00eatements pour sols and murs",
    "sg:phone":"+32 3 669 77 59",
    "sg:postcode":"2990",
    "sg:province":"Antwerpen",
    "wof:name":"Willemsen",
    "wof:placetype":"venue"
},
  "geometry": {"coordinates":[4.6043219566,51.3935050964],"type":"Point"}
}