{
  "type": "Feature",
  "properties": {
    "iso:country":"BE",
    "sg:address":"Chasse Des Bonniers 56",
    "sg:city":"Quaregnon",
    "sg:classifiers":[
        {
            "category":"Professional",
            "type":"Services"
        }
    ],
    "sg:phone":"+32 65 79 15 15",
    "sg:postcode":"7390",
    "sg:province":"Hainaut",
    "sg:tags":[
        "surveyor",
        "-",
        "valuer"
    ],
    "wof:name":"Lienard M",
    "wof:placetype":"venue"
},
  "geometry": {"coordinates":[3.8566000462,50.4552116394],"type":"Point"}
}