{
  "type": "Feature",
  "properties": {
    "addr:full":"Twee Molenstraat 1 Zwevegem West-Vlaanderen 8550",
    "addr:housenumber":"1",
    "addr:postcode":"8550",
    "addr:street":"Twee Molenstraat",
    "iso:country":"BE",
    "sg:address":"Twee Molenstraat 1",
    "sg:city":"Zwevegem",
    "sg:classifiers":[
        {
            "category":"Insurance",
            "subcategory":"Insurance Agent",
            "type":"Services"
        }
    ],
    "sg:phone":"+32 56 75 62 41",
    "sg:postcode":"8550",
    "sg:province":"West-Vlaanderen",
    "sg:tags":[
        "broker"
    ],
    "wof:name":"Desmet Jan Verzekeringen Bvba",
    "wof:placetype":"venue"
},
  "geometry": {"coordinates":[3.3339130878,50.810459137],"type":"Point"}
}