{
  "type": "Feature",
  "properties": {
    "iso:country":"BE",
    "sg:address":"Vlaanderenstraat 3",
    "sg:city":"Oostende",
    "sg:classifiers":[
        {
            "category":"Shopping",
            "subcategory":"Bicycles & Sporting Goods",
            "type":"Retail Goods"
        }
    ],
    "sg:phone":"+32 59 50 37 30",
    "sg:postcode":"8400",
    "sg:province":"West-Vlaanderen",
    "sg:tags":[
        "article",
        "de",
        "sport",
        "camping"
    ],
    "wof:name":"Sporthome",
    "wof:placetype":"venue"
},
  "geometry": {"coordinates":[2.9170238972,51.2322845459],"type":"Point"}
}