{
  "type": "Feature",
  "properties": {
    "iso:country":"BE",
    "sg:address":"Dorp 10b1",
    "sg:city":"Oosterzele",
    "sg:classifiers":[
        {
            "category":"Insurance",
            "subcategory":"Life Insurance",
            "type":"Services"
        }
    ],
    "sg:phone":"+32 9 362 68 69",
    "sg:postcode":"9860",
    "sg:province":"Oost-Vlaanderen",
    "sg:tags":[
        "assurance"
    ],
    "wof:name":"Waterloos-de Block",
    "wof:placetype":"venue"
},
  "geometry": {"coordinates":[3.8067340851,50.9456787109],"type":"Point"}
}