{
  "type": "Feature",
  "properties": {
    "iso:country":"BE",
    "sg:address":"Kleinzand 11",
    "sg:city":"Dendermonde",
    "sg:orig_category":"Rev\u00eatements pour sols and murs. Peinture",
    "sg:phone":"+32 52 20 01 02",
    "sg:postcode":"9200",
    "sg:province":"Oost-Vlaanderen",
    "wof:name":"Dany Leybaert",
    "wof:placetype":"venue"
},
  "geometry": {"coordinates":[4.1001849174,51.0487480164],"type":"Point"}
}