{
  "type": "Feature",
  "properties": {
    "iso:country":"BE",
    "sg:address":"Bruisbeke 69",
    "sg:city":"Sint-lievens-houtem",
    "sg:orig_category":"Boekhouders",
    "sg:phone":"+32 9 362 53 38",
    "sg:postcode":"9520",
    "sg:province":"Oost-Vlaanderen",
    "wof:name":"Maurice Van Driessche",
    "wof:placetype":"venue"
},
  "geometry": {"coordinates":[3.8392829895,50.9303665161],"type":"Point"}
}