{
  "type": "Feature",
  "properties": {
    "iso:country":"BE",
    "sg:address":"Deinzestraat 65",
    "sg:city":"Oudenaarde",
    "sg:orig_category":"Non-Classified Establishments",
    "sg:phone":"+32 55 38 82 84",
    "sg:postcode":"9700",
    "sg:province":"Oost-Vlaanderen",
    "wof:name":"Anex-formenti Nv",
    "wof:placetype":"venue"
},
  "geometry": {"coordinates":[3.5924100876,50.8542900085],"type":"Point"}
}