{
  "type": "Feature",
  "properties": {
    "iso:country":"BE",
    "sg:address":"Ketterijstraat 38ba",
    "sg:city":"Sint-laureins",
    "sg:orig_category":"Plaatsen van vloer- and muurbekleding Schilders",
    "sg:phone":"+32 9 379 98 77",
    "sg:postcode":"9988",
    "sg:province":"Oost-Vlaanderen",
    "wof:name":"J. Van Driessen",
    "wof:placetype":"venue"
},
  "geometry": {"coordinates":[3.6222031116,51.2718734741],"type":"Point"}
}