{
  "type": "Feature",
  "properties": {
    "iso:country":"BE",
    "sg:address":"Neremsplein 19 Box 1",
    "sg:city":"Tongeren (nerem)",
    "sg:classifiers":[
        {
            "category":"Fast Food",
            "type":"Food & Drink"
        }
    ],
    "sg:phone":"+32 12 74 77 74",
    "sg:postcode":"3700",
    "sg:province":"Limburg",
    "sg:tags":[
        "fried",
        "stand",
        "potato"
    ],
    "wof:name":"Brekske ('t)",
    "wof:placetype":"venue"
},
  "geometry": {"coordinates":[5.4719800949,50.7779197693],"type":"Point"}
}