{
  "type": "Feature",
  "properties": {
    "iso:country":"BE",
    "sg:address":"Rue Joseph Wauters 374",
    "sg:city":"Charleroi (dampremy)",
    "sg:classifiers":[
        {
            "category":"Personal",
            "subcategory":"Barber",
            "type":"Services"
        }
    ],
    "sg:phone":"+32 71 33 32 35",
    "sg:postcode":"6020",
    "sg:province":"Hainaut",
    "sg:tags":[
        "gentleman",
        "salon",
        "-",
        "hairdressing"
    ],
    "wof:name":"Fil Coif",
    "wof:placetype":"venue"
},
  "geometry": {"coordinates":[4.425699234,50.4243087769],"type":"Point"}
}