{
  "type": "Feature",
  "properties": {
    "addr:full":"Steenweg 117 Gingelom Limburg 3890",
    "addr:housenumber":"117",
    "addr:postcode":"3890",
    "addr:street":"Steenweg",
    "iso:country":"BE",
    "sg:address":"Steenweg 117",
    "sg:city":"Gingelom",
    "sg:classifiers":[
        {
            "category":"Banks & Credit Unions",
            "subcategory":"Bank",
            "type":"Services"
        }
    ],
    "sg:phone":"+32 11 88 38 36",
    "sg:postcode":"3890",
    "sg:province":"Limburg",
    "wof:name":"Aslk-cger Bank",
    "wof:placetype":"venue"
},
  "geometry": {"coordinates":[5.1348252296,50.7518081665],"type":"Point"}
}