{
  "type": "Feature",
  "properties": {
    "addr:full":"Sint-bernardsesteenweg 602 Antwerpen Antwerpen 2660",
    "addr:housenumber":"602",
    "addr:postcode":"2660",
    "addr:street":"Sint-Bernardsesteenweg",
    "iso:country":"BE",
    "sg:address":"Sint-bernardsesteenweg 602",
    "sg:city":"Antwerpen",
    "sg:orig_category":"Verplichte sociale verzekeringen",
    "sg:phone":"+32 3 828 43 48",
    "sg:postcode":"2660",
    "sg:province":"Antwerpen",
    "wof:name":"Socialist. Mutualiteit",
    "wof:placetype":"venue"
},
  "geometry": {"coordinates":[4.3397898674,51.1732788086],"type":"Point"}
}