{
  "type": "Feature",
  "properties": {
    "addr:full":"Chauss\u00e9e De Marche 837 Namur (wierde) Namur 5100",
    "addr:housenumber":"837",
    "addr:postcode":"5100",
    "addr:street":"Chausse\u0301E De Marche",
    "iso:country":"BE",
    "sg:address":"Chauss\u00e9e De Marche 837",
    "sg:city":"Namur (wierde)",
    "sg:classifiers":[
        {
            "category":"Autos & Motor Vehicles",
            "subcategory":"Recreational Vehicle Sales",
            "type":"Retail Goods"
        }
    ],
    "sg:phone":"+32 81 40 03 78",
    "sg:postcode":"5100",
    "sg:province":"Namur",
    "sg:tags":[
        "caravan",
        "accessory"
    ],
    "wof:name":"D.l.m. Caravanes Sprl",
    "wof:placetype":"venue"
},
  "geometry": {"coordinates":[4.8713750839,50.4566345215],"type":"Point"}
}