{
  "type": "Feature",
  "properties": {
    "addr:full":"Rue De Moorslede 54 Brussel/bruxelles Bruxelles-Capitale 1020",
    "addr:housenumber":"54",
    "addr:postcode":"1020",
    "addr:street":"Rue De Moorslede;/",
    "iso:country":"BE",
    "sg:address":"Rue De Moorslede 54",
    "sg:city":"Brussel/bruxelles",
    "sg:orig_category":"Parfumeries. Centres de relaxation and bien-\u00eatre. Instituts de beaut\u00e9",
    "sg:phone":"+32 2 420 39 38",
    "sg:postcode":"1020",
    "sg:province":"Bruxelles-Capitale",
    "wof:name":"Parfumerie Cloquet",
    "wof:placetype":"venue"
},
  "geometry": {"coordinates":[4.3504900932,50.8758506775],"type":"Point"}
}