{
  "type": "Feature",
  "properties": {
    "addr:full":"Stationsstraat 176-178 Lommel Limburg 3920",
    "addr:housenumber":"176-178",
    "addr:postcode":"3920",
    "addr:street":"Stationsstraat",
    "iso:country":"BE",
    "sg:address":"Stationsstraat 176-178",
    "sg:city":"Lommel",
    "sg:orig_category":"Onderdelen and accessoires voor auto's Voertuigen",
    "sg:phone":"+32 11 54 11 85",
    "sg:postcode":"3920",
    "sg:province":"Limburg",
    "wof:name":"Midas",
    "wof:placetype":"venue"
},
  "geometry": {"coordinates":[5.3133158684,51.2185058594],"type":"Point"}
}