{
  "type": "Feature",
  "properties": {
    "iso:country":"BE",
    "sg:address":"Oberhausen 8",
    "sg:city":"Burg-reuland/burg-reuland",
    "sg:orig_category":"H\u00f4tels",
    "sg:phone":"+32 80 32 94 97",
    "sg:postcode":"4790",
    "sg:province":"Li\u00e8ge",
    "wof:name":"Hotel Oberhausen",
    "wof:placetype":"venue"
},
  "geometry": {"coordinates":[6.1381931305,50.1572494507],"type":"Point"}
}