{
  "type": "Feature",
  "properties": {
    "addr:full":"Houwerstraat 3 Antwerpen Antwerpen 2060",
    "addr:housenumber":"3",
    "addr:postcode":"2060",
    "addr:street":"Houwerstraat",
    "iso:country":"BE",
    "sg:address":"Houwerstraat 3",
    "sg:city":"Antwerpen",
    "sg:classifiers":[
        {
            "category":"Bars & Pubs",
            "type":"Food & Drink"
        }
    ],
    "sg:phone":"+32 3 233 25 88",
    "sg:postcode":"2060",
    "sg:province":"Antwerpen",
    "wof:name":"Silver",
    "wof:placetype":"venue"
},
  "geometry": {"coordinates":[4.4155039787,51.2254905701],"type":"Point"}
}