{
  "type": "Feature",
  "properties": {
    "addr:full":"Avenue Cl\u00e9mentine 19 Bruxelles (forest) Bruxelles-Capitale 1190",
    "addr:housenumber":"19",
    "addr:postcode":"1190",
    "addr:street":"Avenue Cle\u0301Mentine",
    "iso:country":"BE",
    "sg:address":"Avenue Cl\u00e9mentine 19",
    "sg:city":"Bruxelles (forest)",
    "sg:classifiers":[
        {
            "category":"Professional",
            "subcategory":"Lawyer & Legal Services",
            "type":"Services"
        }
    ],
    "sg:phone":"+32 2 541 05 00",
    "sg:postcode":"1190",
    "sg:province":"Bruxelles-Capitale",
    "wof:name":"Massart Pol",
    "wof:placetype":"venue"
},
  "geometry": {"coordinates":[4.3387031555,50.8244476318],"type":"Point"}
}