{
  "type": "Feature",
  "properties": {
    "addr:full":"Grotestraat 35 Komen-waasten/comines-warneton Hainaut 7780",
    "addr:housenumber":"35;7780",
    "addr:street":"Grotestraat",
    "iso:country":"BE",
    "sg:address":"Grotestraat 35",
    "sg:city":"Komen-waasten/comines-warneton",
    "sg:orig_category":"Loodgieterij, verwarming and sanitaire installaties",
    "sg:phone":"+32 56 55 64 53",
    "sg:postcode":"7780",
    "sg:province":"Hainaut",
    "wof:name":"Albert Derudder",
    "wof:placetype":"venue"
},
  "geometry": {"coordinates":[3.0028290749,50.7929916382],"type":"Point"}
}