{
  "type": "Feature",
  "properties": {
    "iso:country":"BE",
    "sg:address":"Rue De Valenciennes 76",
    "sg:city":"Quievrain",
    "sg:orig_category":"Catering and organisatie van feesten Fast food and meeneem restaurants Levering aan huis restaurants",
    "sg:phone":"+32 65 43 13 70",
    "sg:postcode":"7380",
    "sg:province":"Hainaut",
    "wof:name":"Restaurant Costa Verde",
    "wof:placetype":"venue"
},
  "geometry": {"coordinates":[3.6776669025,50.4042701721],"type":"Point"}
}