{
  "type": "Feature",
  "properties": {
    "addr:full":"Rue Du Pensionnat 7 Baelen Li\u00e8ge 4837",
    "addr:housenumber":"7",
    "addr:postcode":"4837",
    "addr:street":"Rue Du Pensionnat",
    "iso:country":"BE",
    "sg:address":"Rue Du Pensionnat 7",
    "sg:city":"Baelen",
    "sg:orig_category":"Rusthuizen and serviceflats",
    "sg:phone":"+32 87 74 22 73",
    "sg:postcode":"4837",
    "sg:province":"Li\u00e8ge",
    "wof:name":"Home St.joseph",
    "wof:placetype":"venue"
},
  "geometry": {"coordinates":[5.9983701706,50.6205711365],"type":"Point"}
}