{
  "type": "Feature",
  "properties": {
    "iso:country":"BE",
    "sg:address":"Grote Baan 206",
    "sg:city":"Lovendegem",
    "sg:classifiers":[
        {
            "category":"Parking",
            "subcategory":"Lot",
            "type":"Transportation"
        }
    ],
    "sg:phone":"+32 9 372 95 27",
    "sg:postcode":"9920",
    "sg:province":"Oost-Vlaanderen",
    "sg:tags":[
        "parking-places",
        "laying-out"
    ],
    "wof:name":"Van De Walle J & Zn",
    "wof:placetype":"venue"
},
  "geometry": {"coordinates":[3.6195058823,51.1070823669],"type":"Point"}
}