{
  "type": "Feature",
  "properties": {
    "iso:country":"BE",
    "sg:address":"Kleinendries 39",
    "sg:city":"Meise",
    "sg:orig_category":"Fleurs and plantes",
    "sg:phone":"+32 52 37 50 94",
    "sg:postcode":"1861",
    "sg:province":"Vlaams-Brabant",
    "wof:name":"Dirk De Buyser",
    "wof:placetype":"venue"
},
  "geometry": {"coordinates":[4.2846431732,50.9714927673],"type":"Point"}
}