{
  "type": "Feature",
  "properties": {
    "iso:country":"BE",
    "sg:address":"Processieweg 11",
    "sg:city":"Tienen",
    "sg:orig_category":"Kapsalons",
    "sg:phone":"+32 16 78 90 73",
    "sg:postcode":"3300",
    "sg:province":"Vlaams-Brabant",
    "wof:name":"Marie-rose Finoulst",
    "wof:placetype":"venue"
},
  "geometry": {"coordinates":[4.930077076,50.8096694946],"type":"Point"}
}