{
  "type": "Feature",
  "properties": {
    "iso:country":"BE",
    "sg:address":"Lillo Steenweg 42",
    "sg:city":"Houthalen",
    "sg:classifiers":[
        {
            "category":"Manufacturing",
            "subcategory":"Chemicals & Compounds",
            "type":"Manufacturing & Wholesale Goods"
        }
    ],
    "sg:phone":"+32 11 57 38 58",
    "sg:postcode":"3530",
    "sg:province":"Limburg",
    "sg:tags":[
        "pharmaceutical",
        "energy",
        "chemistry",
        "-",
        "by-product"
    ],
    "wof:name":"Totalfina Elf Nv",
    "wof:placetype":"venue"
},
  "geometry": {"coordinates":[5.3457131386,51.0409011841],"type":"Point"}
}