{
  "type": "Feature",
  "properties": {
    "iso:country":"BE",
    "sg:address":"Rue Haie Monseu 30",
    "sg:city":"Nandrin",
    "sg:classifiers":[
        {
            "category":"Wholesale",
            "subcategory":"Machinery & Supplies",
            "type":"Manufacturing & Wholesale Goods"
        }
    ],
    "sg:phone":"+32 476 22 52 86",
    "sg:postcode":"4550",
    "sg:province":"Li\u00e8ge",
    "sg:tags":[
        "water",
        "pump",
        "-"
    ],
    "wof:name":"Loneux G",
    "wof:placetype":"venue"
},
  "geometry": {"coordinates":[5.4284582138,50.4998664856],"type":"Point"}
}