{
  "type": "Feature",
  "properties": {
    "iso:country":"BE",
    "sg:address":"Rue Du Trichon 76",
    "sg:city":"Gembloux",
    "sg:orig_category":"Ordinateurs and \u00e9quipement informatique",
    "sg:phone":"+32 81 60 05 69",
    "sg:postcode":"5030",
    "sg:province":"Namur",
    "wof:name":"F. Renier",
    "wof:placetype":"venue"
},
  "geometry": {"coordinates":[4.7176709175,50.5755805969],"type":"Point"}
}