{
  "type": "Feature",
  "properties": {
    "addr:full":"Nieuwstraat 30 Alveringem West-Vlaanderen 8690",
    "addr:housenumber":"30",
    "addr:postcode":"8690",
    "addr:street":"Nieuwstraat",
    "iso:country":"BE",
    "sg:address":"Nieuwstraat 30",
    "sg:city":"Alveringem",
    "sg:orig_category":"Slagers",
    "sg:phone":"+32 58 28 94 32",
    "sg:postcode":"8690",
    "sg:province":"West-Vlaanderen",
    "wof:name":"Beenhouwerij Martin",
    "wof:placetype":"venue"
},
  "geometry": {"coordinates":[2.7126820087,51.0129356384],"type":"Point"}
}