{
  "type": "Feature",
  "properties": {
    "iso:country":"BE",
    "sg:address":"Paalstraat 20",
    "sg:city":"Schoten",
    "sg:classifiers":[
        {
            "category":"Personal",
            "subcategory":"Beauty Salon",
            "type":"Services"
        }
    ],
    "sg:phone":"+32 3 658 22 09",
    "sg:postcode":"2900",
    "sg:province":"Antwerpen",
    "wof:name":"Cleopatra",
    "wof:placetype":"venue"
},
  "geometry": {"coordinates":[4.4994411469,51.251499176],"type":"Point"}
}