{
  "type": "Feature",
  "properties": {
    "iso:country":"BE",
    "sg:address":"Stoopkensstraat 113",
    "sg:city":"Hoegaarden",
    "sg:classifiers":[
        {
            "category":"Home & Garden",
            "subcategory":"Building Materials",
            "type":"Retail Goods"
        }
    ],
    "sg:phone":"+32 16 76 61 35",
    "sg:postcode":"3320",
    "sg:province":"Vlaams-Brabant",
    "sg:tags":[
        "article",
        "-",
        "do-it-yourself"
    ],
    "wof:name":"Vandermolen Bvba",
    "wof:placetype":"venue"
},
  "geometry": {"coordinates":[4.8920297623,50.7786941528],"type":"Point"}
}