{
  "type": "Feature",
  "properties": {
    "addr:full":"Molenhoek 168 Lede Oost-Vlaanderen 9340",
    "addr:housenumber":"168",
    "addr:postcode":"9340",
    "addr:street":"Molenhoek",
    "iso:country":"BE",
    "sg:address":"Molenhoek 168",
    "sg:city":"Lede",
    "sg:orig_category":"Instituts de beaut\u00e9. Centres de relaxation and bien-\u00eatre",
    "sg:phone":"+32 9 366 27 00",
    "sg:postcode":"9340",
    "sg:province":"Oost-Vlaanderen",
    "wof:name":"Rita De Gussem",
    "wof:placetype":"venue"
},
  "geometry": {"coordinates":[3.9139699936,50.9627037048],"type":"Point"}
}