{
  "type": "Feature",
  "properties": {
    "iso:country":"BE",
    "sg:address":"Herten Bruin 2",
    "sg:city":"Boom",
    "sg:orig_category":"Location d'appareils audio-visuels",
    "sg:phone":"+32 3 844 77 05",
    "sg:postcode":"2850",
    "sg:province":"Antwerpen",
    "wof:name":"Music Equipment",
    "wof:placetype":"venue"
},
  "geometry": {"coordinates":[4.3753890991,51.0928077698],"type":"Point"}
}