{
  "type": "Feature",
  "properties": {
    "addr:full":"Seb. Nachtegaelestraat 2 Knokke-heist West-Vlaanderen 8300",
    "addr:housenumber":"2",
    "addr:postcode":"8300",
    "addr:street":"Nachtegaelestraat",
    "iso:country":"BE",
    "sg:address":"Seb. Nachtegaelestraat 2",
    "sg:city":"Knokke-heist",
    "sg:orig_category":"Medische apparatuur, orthopedische artikelen and prothesen Fab",
    "sg:phone":"+32 50 61 49 69",
    "sg:postcode":"8300",
    "sg:province":"West-Vlaanderen",
    "wof:name":"Dental Service",
    "wof:placetype":"venue"
},
  "geometry": {"coordinates":[3.2873430252,51.3409576416],"type":"Point"}
}