{
  "type": "Feature",
  "properties": {
    "addr:full":"Dorpsstraat 1 Kortessem Limburg 3720",
    "addr:housenumber":"1",
    "addr:postcode":"3720",
    "addr:street":"Dorpsstraat",
    "iso:country":"BE",
    "sg:address":"Dorpsstraat 1",
    "sg:city":"Kortessem",
    "sg:orig_category":"Banques and organismes de cr\u00e9dit",
    "sg:phone":"+32 11 37 61 28",
    "sg:postcode":"3720",
    "sg:province":"Limburg",
    "wof:name":"Kbc",
    "wof:placetype":"venue"
},
  "geometry": {"coordinates":[5.3892002106,50.8587493896],"type":"Point"}
}