{
  "type": "Feature",
  "properties": {
    "iso:country":"BE",
    "sg:address":"Houtkaai 12",
    "sg:city":"Aalst",
    "sg:classifiers":[
        {
            "category":"Social Services",
            "subcategory":"Child Care",
            "type":"Services"
        }
    ],
    "sg:phone":"+32 53 70 86 34",
    "sg:postcode":"9300",
    "sg:province":"Oost-Vlaanderen",
    "sg:tags":[
        "baby",
        "nursery",
        "day",
        "sitting"
    ],
    "wof:name":"De Vismijn",
    "wof:placetype":"venue"
},
  "geometry": {"coordinates":[4.0427279472,50.9427261353],"type":"Point"}
}