{
  "type": "Feature",
  "properties": {
    "addr:full":"Boechoutsesteenweg 70 Hove Antwerpen 2540",
    "addr:housenumber":"70",
    "addr:postcode":"2540",
    "addr:street":"Boechoutsesteenweg",
    "iso:country":"BE",
    "sg:address":"Boechoutsesteenweg 70",
    "sg:city":"Hove",
    "sg:classifiers":[
        {
            "category":"Professional",
            "subcategory":"Management & Consulting",
            "type":"Services"
        }
    ],
    "sg:phone":"+32 3 455 14 11",
    "sg:postcode":"2540",
    "sg:province":"Antwerpen",
    "sg:tags":[
        "consultant"
    ],
    "wof:name":"Sirius And Stars Consulting Nv",
    "wof:placetype":"venue"
},
  "geometry": {"coordinates":[4.4756798744,51.1549530029],"type":"Point"}
}