{
  "type": "Feature",
  "properties": {
    "iso:country":"BE",
    "sg:address":"Minister Tacklaan 5",
    "sg:city":"Kortrijk",
    "sg:classifiers":[
        {
            "category":"Fast Food",
            "type":"Food & Drink"
        }
    ],
    "sg:phone":"+32 56 20 03 37",
    "sg:postcode":"8500",
    "sg:province":"West-Vlaanderen",
    "sg:tags":[
        "meeneem",
        "restaurant"
    ],
    "wof:name":"Saint Christophe",
    "wof:placetype":"venue"
},
  "geometry": {"coordinates":[3.2675850391,50.8237762451],"type":"Point"}
}