{
  "type": "Feature",
  "properties": {
    "addr:full":"Kwikstraat 35 Kortenberg Vlaams-Brabant 3078",
    "addr:housenumber":"35",
    "addr:postcode":"3078",
    "addr:street":"Kwikstraat;Vlaams-Brabant",
    "iso:country":"BE",
    "sg:address":"Kwikstraat 35",
    "sg:city":"Kortenberg",
    "sg:orig_category":"Huishoudapparaten, televisies and radio's",
    "sg:phone":"+32 2 759 29 01",
    "sg:postcode":"3078",
    "sg:province":"Vlaams-Brabant",
    "wof:name":"Prestige Intern. Pace",
    "wof:placetype":"venue"
},
  "geometry": {"coordinates":[4.5750827789,50.8783149719],"type":"Point"}
}