{
  "type": "Feature",
  "properties": {
    "addr:full":"Groeneweg 28 Zulte Oost-Vlaanderen 9870",
    "addr:housenumber":"28",
    "addr:postcode":"9870",
    "addr:street":"Groeneweg",
    "iso:country":"BE",
    "sg:address":"Groeneweg 28",
    "sg:city":"Zulte",
    "sg:orig_category":"Dierenartsen",
    "sg:phone":"+32 9 388 88 28",
    "sg:postcode":"9870",
    "sg:province":"Oost-Vlaanderen",
    "wof:name":"Daniel Sabbe",
    "wof:placetype":"venue"
},
  "geometry": {"coordinates":[3.4648709297,50.9290313721],"type":"Point"}
}