{
  "type": "Feature",
  "properties": {
    "iso:country":"BE",
    "sg:address":"Rue Du Perron 4",
    "sg:city":"Vis\u00c9",
    "sg:orig_category":"Mat\u00e9riel m\u00e9dical and orthop\u00e9dique and proth\u00e8ses Fab",
    "sg:phone":"+32 4 379 12 49",
    "sg:postcode":"4600",
    "sg:province":"Li\u00e8ge",
    "wof:name":"L. Oblinger",
    "wof:placetype":"venue"
},
  "geometry": {"coordinates":[5.6940751076,50.7349205017],"type":"Point"}
}