{
  "type": "Feature",
  "properties": {
    "iso:country":"BE",
    "sg:address":"Chauss\u00e9e D'argenteau 24",
    "sg:city":"Vis\u00e9 (argenteau)",
    "sg:classifiers":[
        {
            "category":"Wholesale",
            "subcategory":"Auto Parts",
            "type":"Manufacturing & Wholesale Goods"
        }
    ],
    "sg:phone":"+32 4 374 19 49",
    "sg:postcode":"4601",
    "sg:province":"Li\u00e8ge",
    "sg:tags":[
        "body",
        "automobile",
        "supply",
        "equipment"
    ],
    "wof:name":"Autostar",
    "wof:placetype":"venue"
},
  "geometry": {"coordinates":[5.6850438118,50.7067985535],"type":"Point"}
}