{
  "type": "Feature",
  "properties": {
    "iso:country":"BE",
    "sg:address":"Kruishoutemseweg 225",
    "sg:city":"Waregem",
    "sg:orig_category":"Boucheries. Alimentation sp\u00e9cialis\u00e9e",
    "sg:phone":"+32 56 61 34 17",
    "sg:postcode":"8790",
    "sg:province":"West-Vlaanderen",
    "wof:name":"Patrick Baert",
    "wof:placetype":"venue"
},
  "geometry": {"coordinates":[3.4695920944,50.8937988281],"type":"Point"}
}