{
  "type": "Feature",
  "properties": {
    "iso:country":"BE",
    "sg:address":"Linthoutstraat 59",
    "sg:city":"Schaarbeek/schaerbeek",
    "sg:orig_category":"Kapsalons",
    "sg:phone":"+32 2 735 34 70",
    "sg:postcode":"1030",
    "sg:province":"Bruxelles-Capitale",
    "wof:name":"Nadine",
    "wof:placetype":"venue"
},
  "geometry": {"coordinates":[4.3979868889,50.8457336426],"type":"Point"}
}