{
  "type": "Feature",
  "properties": {
    "addr:full":"Lucien Hendrickxlei 46 Borsbeek Antwerpen 2150",
    "addr:housenumber":"46",
    "addr:postcode":"2150",
    "addr:street":"Lucien Hendrickxlei",
    "iso:country":"BE",
    "sg:address":"Lucien Hendrickxlei 46",
    "sg:city":"Borsbeek",
    "sg:classifiers":[
        {
            "category":"Professional",
            "subcategory":"Computer Services",
            "type":"Services"
        }
    ],
    "sg:phone":"+32 3 366 46 80",
    "sg:postcode":"2150",
    "sg:province":"Antwerpen",
    "sg:tags":[
        "-",
        "processing",
        "data"
    ],
    "wof:name":"Omnia Fausta",
    "wof:placetype":"venue"
},
  "geometry": {"coordinates":[4.4868478775,51.190284729],"type":"Point"}
}