{
  "type": "Feature",
  "properties": {
    "addr:full":"Achterbos 80 Mol Antwerpen 2400",
    "addr:housenumber":"80",
    "addr:postcode":"2400",
    "addr:street":"Achterbos",
    "iso:country":"BE",
    "sg:address":"Achterbos 80",
    "sg:city":"Mol",
    "sg:classifiers":[
        {
            "category":"Retail",
            "subcategory":"Event Space",
            "type":"Services"
        }
    ],
    "sg:phone":"+32 14 31 12 34",
    "sg:postcode":"2400",
    "sg:province":"Antwerpen",
    "sg:tags":[
        "rental",
        "-",
        "hall"
    ],
    "wof:name":"Welkom",
    "wof:placetype":"venue"
},
  "geometry": {"coordinates":[5.0992851257,51.2018127441],"type":"Point"}
}