{
  "type": "Feature",
  "properties": {
    "addr:full":"Chauss\u00c9e Freddy Terwagne 7 Engis Li\u00e8ge 4480",
    "addr:housenumber":"7",
    "addr:postcode":"4480",
    "addr:street":"Chausse\u0301E Freddy Terwagne",
    "iso:country":"BE",
    "sg:address":"Chauss\u00c9e Freddy Terwagne 7",
    "sg:city":"Engis",
    "sg:orig_category":"Dranken Verhuur cateringmateriaal and evenementuitrusting Winkelinrichting and handelsuitrusting Gh",
    "sg:phone":"+32 85 31 35 53",
    "sg:postcode":"4480",
    "sg:province":"Li\u00e8ge",
    "wof:name":"Brasserie Basciu",
    "wof:placetype":"venue"
},
  "geometry": {"coordinates":[5.4045758247,50.582069397],"type":"Point"}
}