{
  "type": "Feature",
  "properties": {
    "addr:full":"Zwaluwenlaan 3 Malle (oostmalle) Antwerpen 2390",
    "addr:housenumber":"3",
    "addr:postcode":"2390",
    "addr:street":"Zwaluwenlaan",
    "iso:country":"BE",
    "sg:address":"Zwaluwenlaan 3",
    "sg:city":"Malle (oostmalle)",
    "sg:classifiers":[
        {
            "category":"Manufacturing",
            "subcategory":"Metals",
            "type":"Manufacturing & Wholesale Goods"
        }
    ],
    "sg:phone":"+32 3 309 31 33",
    "sg:postcode":"2390",
    "sg:province":"Antwerpen",
    "sg:tags":[
        "ornamental",
        "work",
        "-"
    ],
    "wof:name":"Amts",
    "wof:placetype":"venue"
},
  "geometry": {"coordinates":[4.7220220566,51.284072876],"type":"Point"}
}