{
  "type": "Feature",
  "properties": {
    "addr:full":"Rotsestraat 32 Gavere (dikkelvenne) Oost-Vlaanderen 9890",
    "addr:housenumber":"32",
    "addr:postcode":"9890",
    "addr:street":"Rotsestraat",
    "iso:country":"BE",
    "sg:address":"Rotsestraat 32",
    "sg:city":"Gavere (dikkelvenne)",
    "sg:classifiers":[
        {
            "category":"Banks & Credit Unions",
            "subcategory":"Investment Brokerage",
            "type":"Services"
        }
    ],
    "sg:phone":"+32 9 384 32 20",
    "sg:postcode":"9890",
    "sg:province":"Oost-Vlaanderen",
    "sg:tags":[
        "supply",
        "processing",
        "-",
        "access",
        "carrier",
        "data"
    ],
    "wof:name":"C.s.s.",
    "wof:placetype":"venue"
},
  "geometry": {"coordinates":[3.6757099628,50.9180793762],"type":"Point"}
}