{
  "type": "Feature",
  "properties": {
    "iso:country":"BE",
    "sg:address":"Ruelle Du Cur\u00c9 1",
    "sg:city":"Sombreffe",
    "sg:classifiers":[
        {
            "category":"Personal",
            "subcategory":"Beauty Salon",
            "type":"Services"
        }
    ],
    "sg:phone":"+32 71 88 84 02",
    "sg:postcode":"5140",
    "sg:province":"Namur",
    "sg:tags":[
        "de",
        "coiffure"
    ],
    "wof:name":"Coiffure Anny",
    "wof:placetype":"venue"
},
  "geometry": {"coordinates":[4.6057400703,50.5255966187],"type":"Point"}
}