{
  "type": "Feature",
  "properties": {
    "iso:country":"BE",
    "sg:address":"Sledderloweg 59",
    "sg:city":"Genk",
    "sg:classifiers":[
        {
            "category":"Freight",
            "type":"Transportation"
        }
    ],
    "sg:phone":"+32 89 35 26 39",
    "sg:postcode":"3600",
    "sg:province":"Limburg",
    "sg:tags":[
        "-",
        "transport"
    ],
    "wof:name":"Driessen Transport Nv",
    "wof:placetype":"venue"
},
  "geometry": {"coordinates":[5.5146889687,50.9486808777],"type":"Point"}
}