{
  "type": "Feature",
  "properties": {
    "addr:full":"Rue D'erbisoeul 44 Jurbise Hainaut 7050",
    "addr:housenumber":"44",
    "addr:postcode":"7050",
    "addr:street":"Rue D'Erbisoeul",
    "iso:country":"BE",
    "sg:address":"Rue D'erbisoeul 44",
    "sg:city":"Jurbise",
    "sg:orig_category":"Fotografen and fotostudio's",
    "sg:phone":"+32 65 23 59 99",
    "sg:postcode":"7050",
    "sg:province":"Hainaut",
    "wof:name":"Adtp Alain Debay",
    "wof:placetype":"venue"
},
  "geometry": {"coordinates":[3.8777389526,50.5101318359],"type":"Point"}
}