{
  "type": "Feature",
  "properties": {
    "iso:country":"BE",
    "sg:address":"Maldersesteenweg 21",
    "sg:city":"Londerzeel",
    "sg:orig_category":"Installatie van houten of kunststof schrijnwerk Organisatie van beurzen, congressen and tentoonstell",
    "sg:phone":"+32 52 30 13 12",
    "sg:postcode":"1840",
    "sg:province":"Vlaams-Brabant",
    "wof:name":"M Stands",
    "wof:placetype":"venue"
},
  "geometry": {"coordinates":[4.2806968689,51.0305938721],"type":"Point"}
}