{
  "type": "Feature",
  "properties": {
    "addr:full":"Rue Drootbeek 22 Brussel/bruxelles Bruxelles-Capitale 1020",
    "addr:housenumber":"22",
    "addr:postcode":"1020",
    "addr:street":"Rue Drootbeek;/",
    "iso:country":"BE",
    "sg:address":"Rue Drootbeek 22",
    "sg:city":"Brussel/bruxelles",
    "sg:orig_category":"Travail and traitement du bois",
    "sg:phone":"+32 2 426 08 32",
    "sg:postcode":"1020",
    "sg:province":"Bruxelles-Capitale",
    "wof:name":"Sysmans Charles & Fils",
    "wof:placetype":"venue"
},
  "geometry": {"coordinates":[4.347714901,50.8720741272],"type":"Point"}
}