{
  "type": "Feature",
  "properties": {
    "iso:country":"BE",
    "sg:address":"Schepensstraat 11",
    "sg:city":"Koksijde (oostduinkerke)",
    "sg:classifiers":[
        {
            "category":"Building & Trades",
            "subcategory":"Cleaning & Sanitation",
            "type":"Services"
        }
    ],
    "sg:phone":"+32 58 51 65 45",
    "sg:postcode":"8670",
    "sg:province":"West-Vlaanderen",
    "sg:tags":[
        "janitor"
    ],
    "wof:name":"Joske",
    "wof:placetype":"venue"
},
  "geometry": {"coordinates":[2.6825408936,51.1194152832],"type":"Point"}
}