{
  "type": "Feature",
  "properties": {
    "addr:full":"Kloosterstraat 33 Antwerpen Antwerpen 2000",
    "addr:housenumber":"33",
    "addr:postcode":"2000",
    "addr:street":"Kloosterstraat",
    "iso:country":"BE",
    "sg:address":"Kloosterstraat 33",
    "sg:city":"Antwerpen",
    "sg:classifiers":[
        {
            "category":"Shopping",
            "subcategory":"Antiques",
            "type":"Retail Goods"
        }
    ],
    "sg:phone":"+32 3 707 26 62",
    "sg:postcode":"2000",
    "sg:province":"Antwerpen",
    "wof:name":"Teijink",
    "wof:placetype":"venue"
},
  "geometry": {"coordinates":[4.395316124,51.2162590027],"type":"Point"}
}