{
  "type": "Feature",
  "properties": {
    "addr:full":"Paalstraat 98ba Schoten Antwerpen 2900",
    "addr:housenumber":"98ba",
    "addr:postcode":"2900",
    "addr:street":"Paalstraat",
    "iso:country":"BE",
    "sg:address":"Paalstraat 98ba",
    "sg:city":"Schoten",
    "sg:classifiers":[
        {
            "category":"Restaurant",
            "type":"Food & Drink"
        }
    ],
    "sg:phone":"+32 3 685 29 89",
    "sg:postcode":"2900",
    "sg:province":"Antwerpen",
    "wof:name":"\u00b4t Gebrand Verlangen",
    "wof:placetype":"venue"
},
  "geometry": {"coordinates":[4.5023488998,51.2530937195],"type":"Point"}
}