{
  "type": "Feature",
  "properties": {
    "iso:country":"BE",
    "sg:address":"Rue Soeurs-de-hasque 1",
    "sg:city":"Li\u00e8ge 1",
    "sg:classifiers":[
        {
            "category":"Personal",
            "subcategory":"Beauty Salon",
            "type":"Services"
        }
    ],
    "sg:phone":"+32 4 223 41 14",
    "sg:postcode":"4000",
    "sg:province":"Li\u00e8ge",
    "wof:name":"Maud Marcy Sprl",
    "wof:placetype":"venue"
},
  "geometry": {"coordinates":[5.5734620094,50.6407661438],"type":"Point"}
}