{
  "type": "Feature",
  "properties": {
    "iso:country":"BE",
    "sg:address":"Onze Lieve Vrouwstraat 12b2",
    "sg:city":"Beringen",
    "sg:orig_category":"Opticiens",
    "sg:phone":"+32 11 42 12 05",
    "sg:postcode":"3580",
    "sg:province":"Limburg",
    "wof:name":"Marleen Fouarge",
    "wof:placetype":"venue"
},
  "geometry": {"coordinates":[5.2191801071,51.0480575562],"type":"Point"}
}