{
  "type": "Feature",
  "properties": {
    "iso:country":"BE",
    "sg:address":"Sint-michielsstraat 2",
    "sg:city":"Roeselare",
    "sg:classifiers":[
        {
            "category":"Fast Food",
            "type":"Food & Drink"
        }
    ],
    "sg:phone":"+32 51 22 51 09",
    "sg:postcode":"8800",
    "sg:province":"West-Vlaanderen",
    "sg:tags":[
        "fried",
        "stand",
        "potato"
    ],
    "wof:name":"Dave En Yoerie",
    "wof:placetype":"venue"
},
  "geometry": {"coordinates":[3.1228089333,50.9437866211],"type":"Point"}
}