{
  "type": "Feature",
  "properties": {
    "iso:country":"BE",
    "sg:address":"Baalhoek 9",
    "sg:city":"Grimbergen",
    "sg:orig_category":"Artsen and specialisten",
    "sg:phone":"+32 2 267 45 10",
    "sg:postcode":"1853",
    "sg:province":"Vlaams-Brabant",
    "wof:name":"Philippe Snauwaert",
    "wof:placetype":"venue"
},
  "geometry": {"coordinates":[4.3526301384,50.9054336548],"type":"Point"}
}