{
  "type": "Feature",
  "properties": {
    "iso:country":"BE",
    "sg:address":"Sint-jorisstraat 120",
    "sg:city":"Beernem",
    "sg:orig_category":"Rev\u00eatements pour sols and murs. Peinture",
    "sg:phone":"+32 50 79 00 25",
    "sg:postcode":"8730",
    "sg:province":"West-Vlaanderen",
    "wof:name":"Luc Schoonbaert",
    "wof:placetype":"venue"
},
  "geometry": {"coordinates":[3.3475100994,51.126121521],"type":"Point"}
}