{
  "type": "Feature",
  "properties": {
    "addr:full":"Bredabaan 71 Antwerpen Antwerpen 2170",
    "addr:housenumber":"71",
    "addr:postcode":"2170",
    "addr:street":"Bredabaan",
    "iso:country":"BE",
    "sg:address":"Bredabaan 71",
    "sg:city":"Antwerpen",
    "sg:classifiers":[
        {
            "category":"Cafe",
            "type":"Food & Drink"
        }
    ],
    "sg:phone":"+32 3 646 37 37",
    "sg:postcode":"2170",
    "sg:province":"Antwerpen",
    "sg:tags":[
        "caf\u00e9s"
    ],
    "wof:name":"Leonia Verhiest",
    "wof:placetype":"venue"
},
  "geometry": {"coordinates":[4.4228038788,51.2338294983],"type":"Point"}
}