{
  "type": "Feature",
  "properties": {
    "addr:full":"Rue De L'enseignement 9 Chapelle-lez-herlaimont Hainaut 7160",
    "addr:housenumber":"9",
    "addr:postcode":"7160",
    "addr:street":"Rue De L'Enseignement",
    "iso:country":"BE",
    "sg:address":"Rue De L'enseignement 9",
    "sg:city":"Chapelle-lez-herlaimont",
    "sg:orig_category":"Enseignement maternel and primaire",
    "sg:phone":"+32 64 44 20 60",
    "sg:postcode":"7160",
    "sg:province":"Hainaut",
    "wof:name":"Ecole Fond. Communale",
    "wof:placetype":"venue"
},
  "geometry": {"coordinates":[4.2858757973,50.4945220947],"type":"Point"}
}