{
  "type": "Feature",
  "properties": {
    "addr:full":"Breughelpark 6 Asse (zellik) Vlaams-Brabant 1731",
    "addr:housenumber":"6",
    "addr:postcode":"1731",
    "addr:street":"Breughelpark",
    "iso:country":"BE",
    "sg:address":"Breughelpark 6",
    "sg:city":"Asse (zellik)",
    "sg:classifiers":[
        {
            "category":"Education",
            "subcategory":"Special Training",
            "type":"Public Place"
        }
    ],
    "sg:phone":"+32 2 465 67 64",
    "sg:postcode":"1731",
    "sg:province":"Vlaams-Brabant",
    "sg:tags":[
        "school",
        "language"
    ],
    "wof:name":"Nederbelga",
    "wof:placetype":"venue"
},
  "geometry": {"coordinates":[4.2718949318,50.8832626343],"type":"Point"}
}