{
  "type": "Feature",
  "properties": {
    "iso:country":"BE",
    "sg:address":"All\u00c9e De Bernardfagne 7",
    "sg:city":"Ferrieres",
    "sg:orig_category":"Diverse organisaties and verenigingen",
    "sg:phone":"+32 86 40 11 71",
    "sg:postcode":"4190",
    "sg:province":"Li\u00e8ge",
    "wof:name":"Le G\u00c9n\u00c9vrier",
    "wof:placetype":"venue"
},
  "geometry": {"coordinates":[5.6352081299,50.4249458313],"type":"Point"}
}