{
  "type": "Feature",
  "properties": {
    "iso:country":"BE",
    "sg:address":"Drieslaan 42",
    "sg:city":"Wevelgem",
    "sg:orig_category":"Installation de menuiserie m\u00e9tallique",
    "sg:phone":"+32 56 41 29 42",
    "sg:postcode":"8560",
    "sg:province":"West-Vlaanderen",
    "wof:name":"Boal-belgium",
    "wof:placetype":"venue"
},
  "geometry": {"coordinates":[3.1816039085,50.8479919434],"type":"Point"}
}