{
  "type": "Feature",
  "properties": {
    "addr:full":"Laurierstraat 22 Beveren Oost-Vlaanderen 9120",
    "addr:housenumber":"22",
    "addr:postcode":"9120",
    "addr:street":"Laurierstraat",
    "iso:country":"BE",
    "sg:address":"Laurierstraat 22",
    "sg:city":"Beveren",
    "sg:orig_category":"Informaticaconsulenten",
    "sg:phone":"+32 3 775 13 30",
    "sg:postcode":"9120",
    "sg:province":"Oost-Vlaanderen",
    "wof:name":"Edp Assist",
    "wof:placetype":"venue"
},
  "geometry": {"coordinates":[4.2671570778,51.2284812927],"type":"Point"}
}