{
  "type": "Feature",
  "properties": {
    "iso:country":"BE",
    "sg:address":"Avenue D\u00b4auderghem 169",
    "sg:city":"Etterbeek",
    "sg:classifiers":[
        {
            "category":"Insurance",
            "subcategory":"Life Insurance",
            "type":"Services"
        }
    ],
    "sg:phone":"+32 2 644 92 82",
    "sg:postcode":"1040",
    "sg:province":"Bruxelles-Capitale",
    "sg:tags":[
        "assurance"
    ],
    "wof:name":"Eric Michiels",
    "wof:placetype":"venue"
},
  "geometry": {"coordinates":[4.3876709938,50.8349494934],"type":"Point"}
}