{
  "type": "Feature",
  "properties": {
    "iso:country":"BE",
    "sg:address":"Van Benedenlaan 16",
    "sg:city":"Mechelen",
    "sg:orig_category":"M\u00e9decins and sp\u00e9cialistes",
    "sg:phone":"+32 15 45 12 01",
    "sg:postcode":"2800",
    "sg:province":"Antwerpen",
    "wof:name":"C.l.g. Neutra",
    "wof:placetype":"venue"
},
  "geometry": {"coordinates":[4.4745030403,51.0212669373],"type":"Point"}
}