{
  "type": "Feature",
  "properties": {
    "iso:country":"BE",
    "sg:address":"Chemin Des Coquelicois16",
    "sg:city":"Linkebeek",
    "sg:orig_category":"M\u00e9decins and sp\u00e9cialistes",
    "sg:phone":"+32 2 381 20 96",
    "sg:postcode":"1630",
    "sg:province":"Vlaams-Brabant",
    "wof:name":"Caroline Dubois",
    "wof:placetype":"venue"
},
  "geometry": {"coordinates":[4.3354802132,50.7734260559],"type":"Point"}
}