{
  "type": "Feature",
  "properties": {
    "addr:full":"Pepijnstraat 13 Landen Vlaams-Brabant 3400",
    "addr:housenumber":"13",
    "addr:postcode":"3400",
    "addr:street":"Pepijnstraat",
    "iso:country":"BE",
    "sg:address":"Pepijnstraat 13",
    "sg:city":"Landen",
    "sg:classifiers":[
        {
            "category":"Home & Garden",
            "subcategory":"Home Furnishings",
            "type":"Retail Goods"
        }
    ],
    "sg:phone":"+32 11 88 21 05",
    "sg:postcode":"3400",
    "sg:province":"Vlaams-Brabant",
    "sg:tags":[
        "interior",
        "decoration"
    ],
    "wof:name":"Decor Landen Nv",
    "wof:placetype":"venue"
},
  "geometry": {"coordinates":[5.0801100731,50.7506027222],"type":"Point"}
}