{
  "type": "Feature",
  "properties": {
    "addr:full":"Rue Alexandre Patte 22 Dour Hainaut 7370",
    "addr:housenumber":"22",
    "addr:postcode":"7370",
    "addr:street":"Rue Alexandre Patte;Hainaut",
    "iso:country":"BE",
    "sg:address":"Rue Alexandre Patte 22",
    "sg:city":"Dour",
    "sg:orig_category":"Cr\u00e8ches and garderies d'enfants",
    "sg:phone":"+32 65 65 55 59",
    "sg:postcode":"7370",
    "sg:province":"Hainaut",
    "wof:name":"La Sapiniere",
    "wof:placetype":"venue"
},
  "geometry": {"coordinates":[3.7838380337,50.4023017883],"type":"Point"}
}