{
  "type": "Feature",
  "properties": {
    "addr:full":"Rue Ponchaux 12 Frasnes-lez-anvaing Hainaut 7910",
    "addr:housenumber":"12",
    "addr:postcode":"7910",
    "addr:street":"Rue Ponchaux",
    "iso:country":"BE",
    "sg:address":"Rue Ponchaux 12",
    "sg:city":"Frasnes-lez-anvaing",
    "sg:classifiers":[
        {
            "category":"Professional",
            "subcategory":"Accounting & Tax Preparation",
            "type":"Services"
        }
    ],
    "sg:phone":"+32 69 76 81 90",
    "sg:postcode":"7910",
    "sg:province":"Hainaut",
    "sg:tags":[
        "accountant"
    ],
    "wof:name":"Andre Mulhauser",
    "wof:placetype":"venue"
},
  "geometry": {"coordinates":[3.5487949848,50.7252426147],"type":"Point"}
}