{
  "type": "Feature",
  "properties": {
    "iso:country":"BE",
    "sg:address":"Avenue De La Salm 7",
    "sg:city":"Trois-ponts",
    "sg:orig_category":"Jeux de hasard",
    "sg:phone":"+32 80 68 45 29",
    "sg:postcode":"4980",
    "sg:province":"Li\u00e8ge",
    "wof:name":"Tierc\u00c9 Franco Belge",
    "wof:placetype":"venue"
},
  "geometry": {"coordinates":[5.8712348938,50.3707962036],"type":"Point"}
}