{
  "type": "Feature",
  "properties": {
    "addr:full":"Rue Mouligneaux 18 Estinnes (estinnes-au-val) Hainaut 7120",
    "addr:housenumber":"18",
    "addr:postcode":"7120",
    "addr:street":"Rue Mouligneaux",
    "iso:country":"BE",
    "sg:address":"Rue Mouligneaux 18",
    "sg:city":"Estinnes (estinnes-au-val)",
    "sg:classifiers":[
        {
            "category":"Health Services",
            "subcategory":"Dentist",
            "type":"Services"
        }
    ],
    "sg:phone":"+32 64 37 00 59",
    "sg:postcode":"7120",
    "sg:province":"Hainaut",
    "wof:name":"Degreve Jean-victor",
    "wof:placetype":"venue"
},
  "geometry": {"coordinates":[4.1036581993,50.4070472717],"type":"Point"}
}