{
  "type": "Feature",
  "properties": {
    "addr:full":"Kleinesteenweg 39 Begijnendijk Vlaams-Brabant 3130",
    "addr:housenumber":"39",
    "addr:postcode":"3130",
    "addr:street":"Kleinesteenweg",
    "iso:country":"BE",
    "sg:address":"Kleinesteenweg 39",
    "sg:city":"Begijnendijk",
    "sg:classifiers":[
        {
            "category":"Building & Trades",
            "subcategory":"Landscaping Services",
            "type":"Services"
        }
    ],
    "sg:phone":"+32 16 52 06 38",
    "sg:postcode":"3130",
    "sg:province":"Vlaams-Brabant",
    "sg:tags":[
        "moss",
        "removal"
    ],
    "wof:name":"Verbeeck A",
    "wof:placetype":"venue"
},
  "geometry": {"coordinates":[4.7900128365,51.0197372437],"type":"Point"}
}