{
  "type": "Feature",
  "properties": {
    "addr:full":"Molenstraat 1 Torhout West-Vlaanderen 8820",
    "addr:housenumber":"1",
    "addr:postcode":"8820",
    "addr:street":"Molenstraat",
    "iso:country":"BE",
    "sg:address":"Molenstraat 1",
    "sg:city":"Torhout",
    "sg:classifiers":[
        {
            "category":"Professional",
            "subcategory":"Accounting & Tax Preparation",
            "type":"Services"
        }
    ],
    "sg:phone":"+32 50 21 71 52",
    "sg:postcode":"8820",
    "sg:province":"West-Vlaanderen",
    "sg:tags":[
        "bookkeeper"
    ],
    "wof:name":"Caerels J",
    "wof:placetype":"venue"
},
  "geometry": {"coordinates":[3.0925269127,51.0649604797],"type":"Point"}
}