{
  "type": "Feature",
  "properties": {
    "addr:full":"Rue Du Fays 7 Sprimont Li\u00e8ge 4140",
    "addr:housenumber":"7",
    "addr:postcode":"4140",
    "addr:street":"Rue Du Fays",
    "iso:country":"BE",
    "sg:address":"Rue Du Fays 7",
    "sg:city":"Sprimont",
    "sg:classifiers":[
        {
            "category":"Wholesale",
            "subcategory":"Scrap",
            "type":"Manufacturing & Wholesale Goods"
        }
    ],
    "sg:phone":"+32 4 382 36 76",
    "sg:postcode":"4140",
    "sg:province":"Li\u00e8ge",
    "sg:tags":[
        "metal"
    ],
    "wof:name":"G\u00e9om\u00e9tal Sa",
    "wof:placetype":"venue"
},
  "geometry": {"coordinates":[5.6284141541,50.51329422],"type":"Point"}
}