{
  "type": "Feature",
  "properties": {
    "iso:country":"BE",
    "sg:address":"Schriekstraat 50",
    "sg:city":"Laarne",
    "sg:orig_category":"Kapsalons",
    "sg:phone":"+32 9 367 97 16",
    "sg:postcode":"9270",
    "sg:province":"Oost-Vlaanderen",
    "wof:name":"Ann Lebon",
    "wof:placetype":"venue"
},
  "geometry": {"coordinates":[3.9109649658,51.0479774475],"type":"Point"}
}