{
  "type": "Feature",
  "properties": {
    "addr:full":"Grootveld 5 Opwijk Vlaams-Brabant 1745",
    "addr:housenumber":"5",
    "addr:postcode":"1745",
    "addr:street":"Grootveld",
    "iso:country":"BE",
    "sg:address":"Grootveld 5",
    "sg:city":"Opwijk",
    "sg:classifiers":[
        {
            "category":"Food & Beverages",
            "subcategory":"Fruits & Vegetables",
            "type":"Retail Goods"
        }
    ],
    "sg:phone":"+32 52 37 29 39",
    "sg:postcode":"1745",
    "sg:province":"Vlaams-Brabant",
    "sg:tags":[
        "l\u00e9gumes"
    ],
    "wof:name":"Magda Vanderborght",
    "wof:placetype":"venue"
},
  "geometry": {"coordinates":[4.2000441551,50.9547348022],"type":"Point"}
}