{
  "type": "Feature",
  "properties": {
    "addr:full":"Handelslei 204 Zoersel Antwerpen 2980",
    "addr:housenumber":"204",
    "addr:postcode":"2980",
    "iso:country":"BE",
    "sg:address":"Handelslei 204",
    "sg:city":"Zoersel",
    "sg:orig_category":"Meubelzaken, woning- and keukeninrichting Verlichting and huishoudartikelen",
    "sg:phone":"+32 3 383 08 58",
    "sg:postcode":"2980",
    "sg:province":"Antwerpen",
    "wof:name":"Ludovicus Laureyssens",
    "wof:placetype":"venue"
},
  "geometry": {"coordinates":[4.6484470367,51.2730941772],"type":"Point"}
}