{
  "type": "Feature",
  "properties": {
    "iso:country":"BE",
    "sg:address":"Steenweg Naar Merchtem 70",
    "sg:city":"Wemmel",
    "sg:orig_category":"Slagers",
    "sg:phone":"+32 2 461 36 66",
    "sg:postcode":"1780",
    "sg:province":"Vlaams-Brabant",
    "wof:name":"Slagerij Peter",
    "wof:placetype":"venue"
},
  "geometry": {"coordinates":[4.3003997803,50.911239624],"type":"Point"}
}