{
  "type": "Feature",
  "properties": {
    "iso:country":"BE",
    "sg:address":"Hasseltsesteenweg 61",
    "sg:city":"Sint-truiden",
    "sg:classifiers":[
        {
            "category":"Restaurant",
            "type":"Food & Drink"
        }
    ],
    "sg:phone":"+32 11 68 76 34",
    "sg:postcode":"3800",
    "sg:province":"Limburg",
    "wof:name":"Restaurant De Fakkels",
    "wof:placetype":"venue"
},
  "geometry": {"coordinates":[5.20125103,50.8279876709],"type":"Point"}
}