{
  "type": "Feature",
  "properties": {
    "addr:full":"Avenue Albert Lancaster 66 Bruxelles (uccle) Bruxelles-Capitale 1180",
    "addr:housenumber":"66",
    "addr:postcode":"1180",
    "addr:street":"Avenue Albert Lancaster",
    "iso:country":"BE",
    "sg:address":"Avenue Albert Lancaster 66",
    "sg:city":"Bruxelles (uccle)",
    "sg:classifiers":[
        {
            "category":"Health Services",
            "subcategory":"Doctor",
            "type":"Services"
        }
    ],
    "sg:phone":"+32 2 374 08 13",
    "sg:postcode":"1180",
    "sg:province":"Bruxelles-Capitale",
    "sg:tags":[
        "medicinephysicians",
        "surgeon"
    ],
    "wof:name":"Gebhart Michael",
    "wof:placetype":"venue"
},
  "geometry": {"coordinates":[4.362224102,50.7959213257],"type":"Point"}
}