{
  "type": "Feature",
  "properties": {
    "iso:country":"BE",
    "sg:address":"Platanenlaan 4",
    "sg:city":"Mol",
    "sg:orig_category":"Activit\u00e9s r\u00e9cr\u00e9atives diverses",
    "sg:phone":"+32 14 81 22 71",
    "sg:postcode":"2400",
    "sg:province":"Antwerpen",
    "wof:name":"B.c. Wezel",
    "wof:placetype":"venue"
},
  "geometry": {"coordinates":[5.2171759605,51.1975631714],"type":"Point"}
}