{
  "type": "Feature",
  "properties": {
    "addr:full":"Avenue Nestor Martin 69 Saint-hubert Luxembourg 6870",
    "addr:housenumber":"69",
    "addr:postcode":"6870",
    "addr:street":"Avenue Nestor Martin",
    "iso:country":"BE",
    "sg:address":"Avenue Nestor Martin 69",
    "sg:city":"Saint-hubert",
    "sg:classifiers":[
        {
            "category":"Building & Trades",
            "subcategory":"Construction",
            "type":"Services"
        }
    ],
    "sg:phone":"+32 61 61 54 45",
    "sg:postcode":"6870",
    "sg:province":"Luxembourg",
    "sg:tags":[
        "surveyor",
        "-"
    ],
    "wof:name":"Alexci-van Molle G",
    "wof:placetype":"venue"
},
  "geometry": {"coordinates":[5.3661160469,50.0264320374],"type":"Point"}
}