{
  "type": "Feature",
  "properties": {
    "addr:full":"Jozef Van Damstraat 3 Zaventem Vlaams-Brabant 1932",
    "addr:housenumber":"3",
    "addr:postcode":"1932",
    "addr:street":"Jozef Van Damstraat",
    "iso:country":"BE",
    "sg:address":"Jozef Van Damstraat 3",
    "sg:city":"Zaventem",
    "sg:orig_category":"Supermarch\u00e9s",
    "sg:postcode":"1932",
    "sg:province":"Vlaams-Brabant",
    "wof:name":"Aldi",
    "wof:placetype":"venue"
},
  "geometry": {"coordinates":[4.4554200172,50.8732185364],"type":"Point"}
}