{
  "type": "Feature",
  "properties": {
    "iso:country":"BE",
    "sg:address":"Vreehof 20",
    "sg:city":"Arendonk",
    "sg:orig_category":"Woningbouw",
    "sg:phone":"+32 14 67 79 52",
    "sg:postcode":"2370",
    "sg:province":"Antwerpen",
    "wof:name":"Bouwondern. Coenraerds",
    "wof:placetype":"venue"
},
  "geometry": {"coordinates":[5.0938611031,51.3345146179],"type":"Point"}
}