{
  "type": "Feature",
  "properties": {
    "iso:country":"BE",
    "sg:address":"Kartuizersvest 6-56",
    "sg:city":"Lier",
    "sg:classifiers":[
        {
            "category":"Home & Garden",
            "subcategory":"Home Furnishings",
            "type":"Retail Goods"
        }
    ],
    "sg:phone":"+32 3 480 14 45",
    "sg:postcode":"2500",
    "sg:province":"Antwerpen",
    "sg:tags":[
        "curtain",
        "-",
        "fixture"
    ],
    "wof:name":"Vaes Bvba",
    "wof:placetype":"venue"
},
  "geometry": {"coordinates":[4.5679450035,51.1333885193],"type":"Point"}
}