{
  "type": "Feature",
  "properties": {
    "iso:country":"BE",
    "sg:address":"Rue De La R\u00e9gence 11",
    "sg:city":"Soignies",
    "sg:classifiers":[
        {
            "category":"Bars & Pubs",
            "type":"Food & Drink"
        }
    ],
    "sg:phone":"+32 67 33 42 15",
    "sg:postcode":"7060",
    "sg:province":"Hainaut",
    "wof:name":"Carillon (le)",
    "wof:placetype":"venue"
},
  "geometry": {"coordinates":[4.0695538521,50.5792541504],"type":"Point"}
}