{
  "type": "Feature",
  "properties": {
    "iso:country":"BE",
    "sg:address":"Tresoriestraat 1bc",
    "sg:city":"Zonnebeke",
    "sg:orig_category":"Woningbouw",
    "sg:phone":"+32 51 78 01 21",
    "sg:postcode":"8980",
    "sg:province":"West-Vlaanderen",
    "wof:name":"Bouwwerken Mylleville",
    "wof:placetype":"venue"
},
  "geometry": {"coordinates":[2.9771358967,50.8692779541],"type":"Point"}
}