{
  "type": "Feature",
  "properties": {
    "iso:country":"BE",
    "sg:address":"Avenue Nouvelle 50",
    "sg:city":"Etterbeek",
    "sg:orig_category":"M\u00e9decins and sp\u00e9cialistes",
    "sg:phone":"+32 2 640 30 89",
    "sg:postcode":"1040",
    "sg:province":"Bruxelles-Capitale",
    "wof:name":"Michel Dumonceaux",
    "wof:placetype":"venue"
},
  "geometry": {"coordinates":[4.3837161064,50.8278694153],"type":"Point"}
}