{
  "type": "Feature",
  "properties": {
    "addr:full":"Rue De Saint-lazare 36 Mons Hainaut 7000",
    "addr:housenumber":"36",
    "addr:postcode":"7000",
    "addr:street":"Rue De Saint-Lazare;Hainaut",
    "iso:country":"BE",
    "sg:address":"Rue De Saint-lazare 36",
    "sg:city":"Mons",
    "sg:orig_category":"Herstellingen and onderhoud van auto's",
    "sg:phone":"+32 65 31 75 73",
    "sg:postcode":"7000",
    "sg:province":"Hainaut",
    "wof:name":"Dimitri Daussy",
    "wof:placetype":"venue"
},
  "geometry": {"coordinates":[3.959690094,50.4637451172],"type":"Point"}
}