{
  "type": "Feature",
  "properties": {
    "iso:country":"BE",
    "sg:address":"Hogerlucht 65",
    "sg:city":"Ronse/renaix",
    "sg:orig_category":"Alternatieve geneeskunde",
    "sg:phone":"+32 55 21 06 75",
    "sg:postcode":"9600",
    "sg:province":"Oost-Vlaanderen",
    "wof:name":"Brigitte Depraetere",
    "wof:placetype":"venue"
},
  "geometry": {"coordinates":[3.603454113,50.7640686035],"type":"Point"}
}