{
  "type": "Feature",
  "properties": {
    "addr:full":"Nieuwpoortstraat 156 Lokeren Oost-Vlaanderen 9160",
    "addr:housenumber":"156",
    "addr:postcode":"9160",
    "addr:street":"Nieuwpoortstraat",
    "iso:country":"BE",
    "sg:address":"Nieuwpoortstraat 156",
    "sg:city":"Lokeren",
    "sg:classifiers":[
        {
            "category":"Parking",
            "subcategory":"Lot",
            "type":"Transportation"
        }
    ],
    "sg:phone":"+32 9 349 14 71",
    "sg:postcode":"9160",
    "sg:province":"Oost-Vlaanderen",
    "sg:tags":[
        "parking-places",
        "laying-out"
    ],
    "wof:name":"Dallaard",
    "wof:placetype":"venue"
},
  "geometry": {"coordinates":[3.9075360298,51.0981826782],"type":"Point"}
}