{
  "type": "Feature",
  "properties": {
    "addr:full":"Charles De Kerchovelaan 3 Gent Oost-Vlaanderen 9000",
    "addr:housenumber":"3",
    "addr:postcode":"9000",
    "addr:street":"Charles De Kerchovelaan;Oost-Vlaanderen",
    "iso:country":"BE",
    "sg:address":"Charles De Kerchovelaan 3",
    "sg:city":"Gent",
    "sg:orig_category":"Etalage- and showroomontwerpers",
    "sg:phone":"+32 9 223 33 29",
    "sg:postcode":"9000",
    "sg:province":"Oost-Vlaanderen",
    "wof:name":"Ann Coppens",
    "wof:placetype":"venue"
},
  "geometry": {"coordinates":[3.7210071087,51.0412216187],"type":"Point"}
}