{
  "type": "Feature",
  "properties": {
    "iso:country":"BE",
    "sg:address":"Gentsesteenweg 114",
    "sg:city":"Damme",
    "sg:orig_category":"Biens d'occasion",
    "sg:phone":"+32 50 37 11 89",
    "sg:postcode":"8340",
    "sg:province":"West-Vlaanderen",
    "wof:name":"Peter Sneppe",
    "wof:placetype":"venue"
},
  "geometry": {"coordinates":[3.3676660061,51.2043914795],"type":"Point"}
}