{
  "type": "Feature",
  "properties": {
    "iso:country":"BE",
    "sg:address":"Rue Du Pav\u00c9 21",
    "sg:city":"Beaumont",
    "sg:orig_category":"Woningbouw",
    "sg:phone":"+32 71 58 95 41",
    "sg:postcode":"6500",
    "sg:province":"Hainaut",
    "wof:name":"Atout Main",
    "wof:placetype":"venue"
},
  "geometry": {"coordinates":[4.282392025,50.2229042053],"type":"Point"}
}