{
  "type": "Feature",
  "properties": {
    "addr:full":"Ter Beke 11 Brugge (sint-michiels) West-Vlaanderen 8200",
    "addr:housenumber":"11",
    "addr:postcode":"8200",
    "addr:street":"Ter Beke",
    "iso:country":"BE",
    "sg:address":"Ter Beke 11",
    "sg:city":"Brugge (sint-michiels)",
    "sg:classifiers":[
        {
            "category":"Communications",
            "subcategory":"Film & Video Production",
            "type":"Services"
        }
    ],
    "sg:phone":"+32 50 40 28 52",
    "sg:postcode":"8200",
    "sg:province":"West-Vlaanderen",
    "sg:tags":[
        "realisation",
        "-"
    ],
    "wof:name":"Limora Nv",
    "wof:placetype":"venue"
},
  "geometry": {"coordinates":[3.2135510445,51.1896781921],"type":"Point"}
}