{
  "type": "Feature",
  "properties": {
    "iso:country":"BE",
    "sg:address":"Ninoofsesteenweg 79/81",
    "sg:city":"Brussel",
    "sg:classifiers":[
        {
            "category":"Personal",
            "subcategory":"Barber",
            "type":"Services"
        }
    ],
    "sg:phone":"+32 2 410 11 76",
    "sg:postcode":"1080",
    "sg:province":"Bruxelles-Capitale",
    "sg:tags":[
        "barber's",
        "equipment"
    ],
    "wof:name":"Parfumerie D'albert Nv",
    "wof:placetype":"venue"
},
  "geometry": {"coordinates":[4.331843853,50.8498306274],"type":"Point"}
}