{
  "type": "Feature",
  "properties": {
    "addr:full":"Chauss\u00c9e Paul Houtart 147 La Louviere Hainaut 7110",
    "addr:housenumber":"147",
    "addr:postcode":"7110",
    "addr:street":"Chausse\u0301E Paul Houtart",
    "iso:country":"BE",
    "sg:address":"Chauss\u00c9e Paul Houtart 147",
    "sg:city":"La Louviere",
    "sg:orig_category":"D\u00e9taillants en pi\u00e8ces and accessoires de voitures",
    "sg:phone":"+32 64 22 95 01",
    "sg:postcode":"7110",
    "sg:province":"Hainaut",
    "wof:name":"Auto 5",
    "wof:placetype":"venue"
},
  "geometry": {"coordinates":[4.1627550125,50.4840049744],"type":"Point"}
}