{
  "type": "Feature",
  "properties": {
    "iso:country":"BE",
    "sg:address":"R De La Casquette 40",
    "sg:city":"Li\u00e8ge",
    "sg:classifiers":[
        {
            "category":"Shopping",
            "subcategory":"Hobbies, Toys, & Games",
            "type":"Retail Goods"
        }
    ],
    "sg:phone":"+32 4 222 49 40",
    "sg:postcode":"4000",
    "sg:province":"Li\u00e8ge",
    "sg:tags":[
        "product",
        "miscellaneous",
        "entertainment"
    ],
    "wof:name":"Investissements Et Leisure Sa",
    "wof:placetype":"venue"
},
  "geometry": {"coordinates":[5.5672869682,50.6419677734],"type":"Point"}
}