{
  "type": "Feature",
  "properties": {
    "addr:full":"Sleutelplasstraat 56 Dilbeek Vlaams-Brabant 1700",
    "addr:housenumber":"56",
    "addr:postcode":"1700",
    "addr:street":"Sleutelplasstraat",
    "iso:country":"BE",
    "sg:address":"Sleutelplasstraat 56",
    "sg:city":"Dilbeek",
    "sg:orig_category":"Diverse bouwafwerking and reiniging Schoonmaakbedrijven and ongediertebestrijding",
    "sg:phone":"+32 2 463 13 71",
    "sg:postcode":"1700",
    "sg:province":"Vlaams-Brabant",
    "wof:name":"Alain Bekkari",
    "wof:placetype":"venue"
},
  "geometry": {"coordinates":[4.2853198051,50.8486976624],"type":"Point"}
}