{
  "type": "Feature",
  "properties": {
    "iso:country":"BE",
    "sg:address":"E. Eylenboschstraat 1bb",
    "sg:city":"Dilbeek",
    "sg:orig_category":"V\u00e9t\u00e9rinaires",
    "sg:phone":"+32 2 567 26 72",
    "sg:postcode":"1703",
    "sg:province":"Vlaams-Brabant",
    "wof:name":"C. De Baere",
    "wof:placetype":"venue"
},
  "geometry": {"coordinates":[4.1941208839,50.8360862732],"type":"Point"}
}