{
  "type": "Feature",
  "properties": {
    "addr:full":"Tweelingenstraat 28 Antwerpen Antwerpen 2018",
    "addr:housenumber":"28",
    "addr:postcode":"2018",
    "addr:street":"Tweelingenstraat",
    "iso:country":"BE",
    "sg:address":"Tweelingenstraat 28",
    "sg:city":"Antwerpen",
    "sg:classifiers":[
        {
            "category":"Shopping",
            "subcategory":"Clothing, Apparel, & Fashions",
            "type":"Retail Goods"
        }
    ],
    "sg:phone":"+32 3 236 61 11",
    "sg:postcode":"2018",
    "sg:province":"Antwerpen",
    "sg:tags":[
        "milliner"
    ],
    "wof:name":"Hat Lines",
    "wof:placetype":"venue"
},
  "geometry": {"coordinates":[4.4344291687,51.2071914673],"type":"Point"}
}