{
  "type": "Feature",
  "properties": {
    "addr:full":"Leuvensesteenweg 1048 Evere Bruxelles-Capitale 1140",
    "addr:housenumber":"1048",
    "addr:postcode":"1140",
    "addr:street":"Leuvensesteenweg",
    "iso:country":"BE",
    "sg:address":"Leuvensesteenweg 1048",
    "sg:city":"Evere",
    "sg:orig_category":"Industri\u00eble elektrische installaties",
    "sg:phone":"+32 2 730 92 11",
    "sg:postcode":"1140",
    "sg:province":"Bruxelles-Capitale",
    "wof:name":"Kone Belgium",
    "wof:placetype":"venue"
},
  "geometry": {"coordinates":[4.4210419655,50.8605537415],"type":"Point"}
}