{
  "type": "Feature",
  "properties": {
    "addr:full":"Place De La Gare 1 Moeskroen Hainaut 7700",
    "addr:housenumber":"1",
    "addr:postcode":"7700",
    "addr:street":"Place De La Gare;Hainaut",
    "iso:country":"BE",
    "sg:address":"Place De La Gare 1",
    "sg:city":"Moeskroen",
    "sg:orig_category":"Treinen and spoorwegen",
    "sg:phone":"+32 56 33 01 06",
    "sg:postcode":"7700",
    "sg:province":"Hainaut",
    "wof:name":"Gare De Mouscron",
    "wof:placetype":"venue"
},
  "geometry": {"coordinates":[3.2288160324,50.7414855957],"type":"Point"}
}