{
  "type": "Feature",
  "properties": {
    "iso:country":"BE",
    "sg:address":"Witte Torenstraat 17",
    "sg:city":"Bree",
    "sg:classifiers":[
        {
            "category":"Quarry",
            "type":"Physical Feature"
        }
    ],
    "sg:phone":"+32 89 46 18 43",
    "sg:postcode":"3960",
    "sg:province":"Limburg",
    "sg:tags":[
        "granite",
        "work",
        "marble"
    ],
    "wof:name":"Das M Bvba",
    "wof:placetype":"venue"
},
  "geometry": {"coordinates":[5.5994458199,51.1433181763],"type":"Point"}
}