{
  "type": "Feature",
  "properties": {
    "iso:country":"BE",
    "sg:address":"Place Albert- Elizabeth 56",
    "sg:city":"Saint-ghislain",
    "sg:orig_category":"Transports ferroviaires",
    "sg:phone":"+32 65 78 41 22",
    "sg:postcode":"7330",
    "sg:province":"Hainaut",
    "wof:name":"Gare De Saint-ghislain",
    "wof:placetype":"venue"
},
  "geometry": {"coordinates":[3.8191990852,50.4427947998],"type":"Point"}
}