{
  "type": "Feature",
  "properties": {
    "addr:full":"Grand'rue 15 Hensies Hainaut 7350",
    "addr:housenumber":"15",
    "addr:postcode":"7350",
    "addr:street":"Grand'Rue",
    "iso:country":"BE",
    "sg:address":"Grand'rue 15",
    "sg:city":"Hensies",
    "sg:classifiers":[
        {
            "category":"Personal",
            "subcategory":"Beauty Salon",
            "type":"Services"
        }
    ],
    "sg:phone":"+32 65 65 91 24",
    "sg:postcode":"7350",
    "sg:province":"Hainaut",
    "sg:tags":[
        "de",
        "coiffure"
    ],
    "wof:name":"Coiffure Marie-agnes",
    "wof:placetype":"venue"
},
  "geometry": {"coordinates":[3.7423369884,50.4263687134],"type":"Point"}
}