{
  "type": "Feature",
  "properties": {
    "addr:full":"Kranenburgstraat 5 Scherpenheuvel-zichem Vlaams-Brabant 3271",
    "addr:housenumber":"5",
    "addr:postcode":"3271",
    "addr:street":"Kranenburgstraat",
    "iso:country":"BE",
    "sg:address":"Kranenburgstraat 5",
    "sg:city":"Scherpenheuvel-zichem",
    "sg:orig_category":"Banques and organismes de cr\u00e9dit",
    "sg:phone":"+32 13 77 12 10",
    "sg:postcode":"3271",
    "sg:province":"Vlaams-Brabant",
    "wof:name":"Bbl",
    "wof:placetype":"venue"
},
  "geometry": {"coordinates":[4.9879450798,51.0009498596],"type":"Point"}
}