{
  "type": "Feature",
  "properties": {
    "addr:full":"Guido Gezellestraat 10 Aartselaar Antwerpen 2630",
    "addr:housenumber":"10",
    "addr:postcode":"2630",
    "addr:street":"Guido Gezellestraat",
    "iso:country":"BE",
    "sg:address":"Guido Gezellestraat 10",
    "sg:city":"Aartselaar",
    "sg:orig_category":"Apotheken",
    "sg:phone":"+32 3 887 23 20",
    "sg:postcode":"2630",
    "sg:province":"Antwerpen",
    "wof:name":"Apotheek Bytebier R.",
    "wof:placetype":"venue"
},
  "geometry": {"coordinates":[4.3864412308,51.1346130371],"type":"Point"}
}