{
  "type": "Feature",
  "properties": {
    "addr:full":"Nestor De Ti\u00c8restraat 167 Oudenaarde Oost-Vlaanderen 9700",
    "addr:housenumber":"167",
    "addr:postcode":"9700",
    "addr:street":"Nestor De Tie\u0300Restraat",
    "iso:country":"BE",
    "sg:address":"Nestor De Ti\u00c8restraat 167",
    "sg:city":"Oudenaarde",
    "sg:orig_category":"Bloemen and planten",
    "sg:phone":"+32 55 31 14 86",
    "sg:postcode":"9700",
    "sg:province":"Oost-Vlaanderen",
    "wof:name":"Huis Kriss",
    "wof:placetype":"venue"
},
  "geometry": {"coordinates":[3.6199800968,50.8684997559],"type":"Point"}
}