{
  "type": "Feature",
  "properties": {
    "iso:country":"BE",
    "sg:address":"Rue Dessous L'eglise 9",
    "sg:city":"Juprelle",
    "sg:orig_category":"Maisons de repos and r\u00e9sidences",
    "sg:phone":"+32 4 278 20 51",
    "sg:postcode":"4450",
    "sg:province":"Li\u00e8ge",
    "wof:name":"Home Les Oliviers",
    "wof:placetype":"venue"
},
  "geometry": {"coordinates":[5.5636920929,50.7285270691],"type":"Point"}
}