{
  "type": "Feature",
  "properties": {
    "iso:country":"BE",
    "sg:address":"Lange Nieuwstraat 12",
    "sg:city":"Antwerpen",
    "sg:orig_category":"Antiek Tweedehandsgoederen",
    "sg:phone":"+32 3 226 75 30",
    "sg:postcode":"2000",
    "sg:province":"Antwerpen",
    "wof:name":"Archim\u00c9",
    "wof:placetype":"venue"
},
  "geometry": {"coordinates":[4.4058618546,51.2199249268],"type":"Point"}
}