{
  "type": "Feature",
  "properties": {
    "addr:full":"Veemarkt 14 Kortrijk West-Vlaanderen 8500",
    "addr:housenumber":"14",
    "addr:postcode":"8500",
    "addr:street":"Veemarkt",
    "iso:country":"BE",
    "sg:address":"Veemarkt 14",
    "sg:city":"Kortrijk",
    "sg:orig_category":"Immobili\u00ebnkantoren Projectontwikkelaars",
    "sg:phone":"+32 56 25 95 20",
    "sg:postcode":"8500",
    "sg:province":"West-Vlaanderen",
    "wof:name":"Immo Decibo",
    "wof:placetype":"venue"
},
  "geometry": {"coordinates":[3.2725279331,50.8262939453],"type":"Point"}
}