{
  "type": "Feature",
  "properties": {
    "addr:full":"Provinciebaan 140 Zottegem (velzeke-ruddershove) Oost-Vlaanderen 9620",
    "addr:housenumber":"140",
    "addr:postcode":"9620",
    "addr:street":"Provinciebaan",
    "iso:country":"BE",
    "sg:address":"Provinciebaan 140",
    "sg:city":"Zottegem (velzeke-ruddershove)",
    "sg:classifiers":[
        {
            "category":"Home & Garden",
            "subcategory":"Home Furnishings",
            "type":"Retail Goods"
        }
    ],
    "sg:phone":"+32 9 361 12 35",
    "sg:postcode":"9620",
    "sg:province":"Oost-Vlaanderen",
    "sg:tags":[
        "interior",
        "decoration"
    ],
    "wof:name":"Ck Deco",
    "wof:placetype":"venue"
},
  "geometry": {"coordinates":[3.8112111092,50.871181488],"type":"Point"}
}