{
  "type": "Feature",
  "properties": {
    "iso:country":"BE",
    "sg:address":"Industriepark De Bruwaan 2",
    "sg:city":"Oudenaarde",
    "sg:classifiers":[
        {
            "category":"Home & Garden",
            "subcategory":"Kitchen Supply",
            "type":"Retail Goods"
        }
    ],
    "sg:phone":"+32 55 31 46 83",
    "sg:postcode":"9700",
    "sg:province":"Oost-Vlaanderen",
    "sg:tags":[
        "installation"
    ],
    "wof:name":"Adv-keukens En Kasten",
    "wof:placetype":"venue"
},
  "geometry": {"coordinates":[3.5877420902,50.8593902588],"type":"Point"}
}