{
  "type": "Feature",
  "properties": {
    "iso:country":"BE",
    "sg:address":"Jozef Van Bogaertstraat 6",
    "sg:city":"Dendermonde",
    "sg:orig_category":"Schoonheidssalons",
    "sg:phone":"+32 52 22 11 80",
    "sg:postcode":"9200",
    "sg:province":"Oost-Vlaanderen",
    "wof:name":"Veronique Van Steen",
    "wof:placetype":"venue"
},
  "geometry": {"coordinates":[4.1025161743,51.0310440063],"type":"Point"}
}