{
  "type": "Feature",
  "properties": {
    "iso:country":"BE",
    "sg:address":"Berg 10",
    "sg:city":"Lille",
    "sg:classifiers":[
        {
            "category":"Education",
            "subcategory":"School",
            "type":"Public Place"
        }
    ],
    "sg:phone":"+32 14 88 06 35",
    "sg:postcode":"2275",
    "sg:province":"Antwerpen",
    "sg:tags":[
        "primary"
    ],
    "wof:name":"Leefschool de Vlindertuin",
    "wof:placetype":"venue"
},
  "geometry": {"coordinates":[4.8288788795,51.2365684509],"type":"Point"}
}