{
  "type": "Feature",
  "properties": {
    "addr:full":"Chauss\u00c9e De Gilly 28 Charleroi Hainaut 6043",
    "addr:housenumber":"28",
    "addr:postcode":"6043",
    "addr:street":"Chausse\u0301E De Gilly;Hainaut",
    "iso:country":"BE",
    "sg:address":"Chauss\u00c9e De Gilly 28",
    "sg:city":"Charleroi",
    "sg:orig_category":"Bouwmaterialen Gh",
    "sg:phone":"+32 71 37 73 55",
    "sg:postcode":"6043",
    "sg:province":"Hainaut",
    "wof:name":"A. Giacalone",
    "wof:placetype":"venue"
},
  "geometry": {"coordinates":[4.4406552315,50.4419136047],"type":"Point"}
}