{
  "type": "Feature",
  "properties": {
    "addr:full":"Avenue Wolfers 21 La Hulpe Brabant Wallon 1310",
    "addr:housenumber":"21",
    "addr:postcode":"1310",
    "addr:street":"Avenue Wolfers",
    "iso:country":"BE",
    "sg:address":"Avenue Wolfers 21",
    "sg:city":"La Hulpe",
    "sg:classifiers":[
        {
            "category":"Building & Trades",
            "subcategory":"Electrical",
            "type":"Services"
        }
    ],
    "sg:phone":"+32 2 653 45 22",
    "sg:postcode":"1310",
    "sg:province":"Brabant Wallon",
    "sg:tags":[
        "electric",
        "-",
        "housewiring",
        "contractor"
    ],
    "wof:name":"Multi-elec",
    "wof:placetype":"venue"
},
  "geometry": {"coordinates":[4.5003461838,50.7382164001],"type":"Point"}
}