{
  "type": "Feature",
  "properties": {
    "iso:country":"BE",
    "sg:address":"Hagedoornlaan 56",
    "sg:city":"Ukkel/uccle",
    "sg:orig_category":"Advocaten and juridische adviseurs",
    "sg:phone":"+32 2 372 01 03",
    "sg:postcode":"1180",
    "sg:province":"Bruxelles-Capitale",
    "wof:name":"Chr. Leblon",
    "wof:placetype":"venue"
},
  "geometry": {"coordinates":[4.3756108284,50.7753677368],"type":"Point"}
}