{
  "type": "Feature",
  "properties": {
    "iso:country":"BE",
    "sg:address":"Armoedestraat 28",
    "sg:city":"Roeselare (rumbeke)",
    "sg:classifiers":[
        {
            "category":"Health Services",
            "subcategory":"Health Practitioner",
            "type":"Services"
        }
    ],
    "sg:phone":"+32 51 20 04 81",
    "sg:postcode":"8800",
    "sg:province":"West-Vlaanderen",
    "sg:tags":[
        "physiotherapist"
    ],
    "wof:name":"Wertelaers An",
    "wof:placetype":"venue"
},
  "geometry": {"coordinates":[3.1230149269,50.9443435669],"type":"Point"}
}