{
  "type": "Feature",
  "properties": {
    "iso:country":"BE",
    "sg:address":"Van Duysestraat 7",
    "sg:city":"Lokeren",
    "sg:orig_category":"Binnenhuisarchitecten Installatie van houten of kunststof schrijnwerk",
    "sg:phone":"+32 9 349 42 60",
    "sg:postcode":"9160",
    "sg:province":"Oost-Vlaanderen",
    "wof:name":"Jan Rymenants",
    "wof:placetype":"venue"
},
  "geometry": {"coordinates":[3.9788110256,51.1116027832],"type":"Point"}
}