{
  "type": "Feature",
  "properties": {
    "addr:full":"Steenrijt 2 Geel Antwerpen 2440",
    "addr:housenumber":"2",
    "addr:postcode":"2440",
    "addr:street":"Steenrijt",
    "iso:country":"BE",
    "sg:address":"Steenrijt 2",
    "sg:city":"Geel",
    "sg:orig_category":"R\u00e9alisation de programmes and logiciels",
    "sg:phone":"+32 14 58 14 42",
    "sg:postcode":"2440",
    "sg:province":"Antwerpen",
    "wof:name":"A.s.b.",
    "wof:placetype":"venue"
},
  "geometry": {"coordinates":[4.9575028419,51.1532783508],"type":"Point"}
}