{
  "type": "Feature",
  "properties": {
    "addr:full":"Avenue Des H\u00eatres 16 Hannut Li\u00e8ge 4280",
    "addr:housenumber":"16",
    "addr:postcode":"4280",
    "addr:street":"Avenue Des He\u0302Tres",
    "iso:country":"BE",
    "sg:address":"Avenue Des H\u00eatres 16",
    "sg:city":"Hannut",
    "sg:classifiers":[
        {
            "category":"Health Services",
            "subcategory":"Health Practitioner",
            "type":"Services"
        }
    ],
    "sg:phone":"+32 19 51 15 53",
    "sg:postcode":"4280",
    "sg:province":"Li\u00e8ge",
    "sg:tags":[
        "physiotherapist"
    ],
    "wof:name":"Roland Marie-jeanne",
    "wof:placetype":"venue"
},
  "geometry": {"coordinates":[5.0844039917,50.6720504761],"type":"Point"}
}