{
  "type": "Feature",
  "properties": {
    "iso:country":"BE",
    "sg:address":"Leopold Iii Straat 64",
    "sg:city":"Kortessem",
    "sg:orig_category":"Plaatsen van vloer- and muurbekleding Schilders",
    "sg:phone":"+32 12 21 01 41",
    "sg:postcode":"3724",
    "sg:province":"Limburg",
    "wof:name":"Nijs R. & Zn",
    "wof:placetype":"venue"
},
  "geometry": {"coordinates":[5.4325428009,50.8433494568],"type":"Point"}
}