{
  "type": "Feature",
  "properties": {
    "iso:country":"BE",
    "sg:address":"Dungelstraat 54",
    "sg:city":"Zoutleeuw (halle-booienhoven)",
    "sg:classifiers":[
        {
            "category":"Real Estate",
            "subcategory":"Architect",
            "type":"Services"
        }
    ],
    "sg:phone":"+32 11 78 21 99",
    "sg:postcode":"3440",
    "sg:province":"Vlaams-Brabant",
    "wof:name":"Verbeeck D",
    "wof:placetype":"venue"
},
  "geometry": {"coordinates":[5.1109142303,50.8139762878],"type":"Point"}
}