{
  "type": "Feature",
  "properties": {
    "addr:full":"Boomse Steenweg 276 Antwerpen Antwerpen 2020",
    "addr:housenumber":"276",
    "addr:postcode":"2020",
    "addr:street":"Steenweg",
    "iso:country":"BE",
    "sg:address":"Boomse Steenweg 276",
    "sg:city":"Antwerpen",
    "sg:classifiers":[
        {
            "category":"Cafe",
            "type":"Food & Drink"
        }
    ],
    "sg:phone":"+32 3 237 38 32",
    "sg:postcode":"2020",
    "sg:province":"Antwerpen",
    "sg:tags":[
        "snack-bars"
    ],
    "wof:name":"Goei Beleg (t')",
    "wof:placetype":"venue"
},
  "geometry": {"coordinates":[4.3866810799,51.1896629333],"type":"Point"}
}