{
  "type": "Feature",
  "properties": {
    "iso:country":"BE",
    "sg:address":"Beerlegemsebaan 4",
    "sg:city":"Zwalm (munkzwalm)",
    "sg:classifiers":[
        {
            "category":"Wholesale",
            "subcategory":"Plants",
            "type":"Manufacturing & Wholesale Goods"
        }
    ],
    "sg:phone":"+32 55 49 93 46",
    "sg:postcode":"9630",
    "sg:province":"Oost-Vlaanderen",
    "sg:tags":[
        "whol",
        "flower",
        "-",
        "grower"
    ],
    "wof:name":"Glorieux J",
    "wof:placetype":"venue"
},
  "geometry": {"coordinates":[3.7323698997,50.8955841064],"type":"Point"}
}