{
  "type": "Feature",
  "properties": {
    "addr:full":"Kazernstraat 13 Zottegem Oost-Vlaanderen 9620",
    "addr:housenumber":"13",
    "addr:postcode":"9620",
    "addr:street":"Kazernstraat",
    "iso:country":"BE",
    "sg:address":"Kazernstraat 13",
    "sg:city":"Zottegem",
    "sg:classifiers":[
        {
            "category":"Cafe",
            "type":"Food & Drink"
        }
    ],
    "sg:phone":"+32 9 360 77 01",
    "sg:postcode":"9620",
    "sg:province":"Oost-Vlaanderen",
    "sg:tags":[
        "caf\u00e9s"
    ],
    "wof:name":"Vermoesen & Van Kerkhoven",
    "wof:placetype":"venue"
},
  "geometry": {"coordinates":[3.8132560253,50.8683013916],"type":"Point"}
}