{
  "type": "Feature",
  "properties": {
    "addr:full":"Rue De Chassepierre 3 Florenville Luxembourg 6820",
    "addr:housenumber":"3",
    "addr:postcode":"6820",
    "addr:street":"Rue De Chassepierre",
    "iso:country":"BE",
    "sg:address":"Rue De Chassepierre 3",
    "sg:city":"Florenville",
    "sg:orig_category":"Toeristische diensten",
    "sg:phone":"+32 61 31 41 58",
    "sg:postcode":"6820",
    "sg:province":"Luxembourg",
    "wof:name":"Syndicat D\u00b4initiative",
    "wof:placetype":"venue"
},
  "geometry": {"coordinates":[5.2428569794,49.7272377014],"type":"Point"}
}