{
  "type": "Feature",
  "properties": {
    "iso:country":"BE",
    "sg:address":"Chemin Des Flamands 46",
    "sg:city":"Ronse/renaix",
    "sg:orig_category":"Travaux de pl\u00e2trage. Installation de menuiserie en bois and plastique",
    "sg:phone":"+32 55 21 48 74",
    "sg:postcode":"9600",
    "sg:province":"Oost-Vlaanderen",
    "wof:name":"Andre Vancoppenolle",
    "wof:placetype":"venue"
},
  "geometry": {"coordinates":[3.5992999077,50.7470397949],"type":"Point"}
}