{
  "type": "Feature",
  "properties": {
    "addr:full":"Montenau 146 Amel/ambleve Li\u00e8ge 4770",
    "addr:housenumber":"146",
    "addr:postcode":"4770",
    "addr:street":"Montenau",
    "iso:country":"BE",
    "sg:address":"Montenau 146",
    "sg:city":"Amel/ambleve",
    "sg:orig_category":"Rundveehouders",
    "sg:phone":"+32 80 34 05 01",
    "sg:postcode":"4770",
    "sg:province":"Li\u00e8ge",
    "wof:name":"Manfred Spoden",
    "wof:placetype":"venue"
},
  "geometry": {"coordinates":[6.1876211166,50.3251914978],"type":"Point"}
}