{
  "type": "Feature",
  "properties": {
    "addr:full":"Havelange 40 Aywaille Li\u00e8ge 4920",
    "addr:housenumber":"40",
    "addr:postcode":"4920",
    "addr:street":"Havelange",
    "iso:country":"BE",
    "sg:address":"Havelange 40",
    "sg:city":"Aywaille",
    "sg:orig_category":"Eleveurs d'\u00e9quid\u00e9s",
    "sg:phone":"+32 4 384 56 49",
    "sg:postcode":"4920",
    "sg:province":"Li\u00e8ge",
    "wof:name":"Arabian Stud H",
    "wof:placetype":"venue"
},
  "geometry": {"coordinates":[5.7098178864,50.4444274902],"type":"Point"}
}