{
  "type": "Feature",
  "properties": {
    "iso:country":"BE",
    "sg:address":"Rue Des R\u00c9sistants 7ba",
    "sg:city":"Mont-de-l'enclus",
    "sg:classifiers":[
        {
            "category":"Cafe",
            "type":"Food & Drink"
        }
    ],
    "sg:phone":"+32 69 45 59 26",
    "sg:postcode":"7750",
    "sg:province":"Hainaut",
    "sg:tags":[
        "caf\u00e9s"
    ],
    "wof:name":"Liliane Martens",
    "wof:placetype":"venue"
},
  "geometry": {"coordinates":[5.0023469925,50.3222923279],"type":"Point"}
}