{
  "type": "Feature",
  "properties": {
    "iso:country":"BE",
    "sg:address":"Nieuwstadpoort 14",
    "sg:city":"Bree",
    "sg:classifiers":[
        {
            "category":"Personal",
            "subcategory":"Beauty Salon",
            "type":"Services"
        }
    ],
    "sg:phone":"+32 89 46 20 45",
    "sg:postcode":"3960",
    "sg:province":"Limburg",
    "sg:tags":[
        "lady",
        "-",
        "hairdressing"
    ],
    "wof:name":"Vandewinkel J",
    "wof:placetype":"venue"
},
  "geometry": {"coordinates":[5.5940561295,51.140537262],"type":"Point"}
}