{
  "type": "Feature",
  "properties": {
    "addr:full":"Rue Elisa Dumonceau 9 Herstal Li\u00e8ge 4040",
    "addr:housenumber":"9",
    "addr:postcode":"4040",
    "addr:street":"Rue Elisa Dumonceau",
    "iso:country":"BE",
    "sg:address":"Rue Elisa Dumonceau 9",
    "sg:city":"Herstal",
    "sg:orig_category":"Banques and organismes de cr\u00e9dit",
    "sg:phone":"+32 4 264 17 59",
    "sg:postcode":"4040",
    "sg:province":"Li\u00e8ge",
    "wof:name":"Bbl",
    "wof:placetype":"venue"
},
  "geometry": {"coordinates":[5.630671978,50.6647911072],"type":"Point"}
}