{
  "type": "Feature",
  "properties": {
    "iso:country":"BE",
    "sg:address":"Rue De Saint-remy 31",
    "sg:city":"Vis\u00c9",
    "sg:orig_category":"Services pour animaux domestiques",
    "sg:phone":"+32 4 387 78 65",
    "sg:postcode":"4601",
    "sg:province":"Li\u00e8ge",
    "wof:name":"Topaze",
    "wof:placetype":"venue"
},
  "geometry": {"coordinates":[5.6964278221,50.6961212158],"type":"Point"}
}