{
  "type": "Feature",
  "properties": {
    "iso:country":"BE",
    "sg:address":"Avenue De Tyras 109",
    "sg:city":"Bruxelles",
    "sg:classifiers":[
        {
            "category":"Manufacturing",
            "subcategory":"Chemicals & Compounds",
            "type":"Manufacturing & Wholesale Goods"
        }
    ],
    "sg:phone":"+32 2 264 64 11",
    "sg:postcode":"1120",
    "sg:province":"Bruxelles-Capitale",
    "sg:tags":[
        "pharmaceutical",
        "product"
    ],
    "wof:name":"Caf-dcf Scrl",
    "wof:placetype":"venue"
},
  "geometry": {"coordinates":[4.392250061,50.9096755981],"type":"Point"}
}