{
  "type": "Feature",
  "properties": {
    "addr:full":"Grand'rue 115 Saint-leger Luxembourg 6747",
    "addr:housenumber":"115",
    "addr:postcode":"6747",
    "addr:street":"Grand'Rue",
    "iso:country":"BE",
    "sg:address":"Grand'rue 115",
    "sg:city":"Saint-leger",
    "sg:orig_category":"Epiceries",
    "sg:phone":"+32 63 22 18 83",
    "sg:postcode":"6747",
    "sg:province":"Luxembourg",
    "wof:name":"Poids D'or",
    "wof:placetype":"venue"
},
  "geometry": {"coordinates":[5.6567749977,49.6120567322],"type":"Point"}
}