{
  "type": "Feature",
  "properties": {
    "addr:full":"Rue Du Castert 135 Mouscron Hainaut 7700",
    "addr:housenumber":"135",
    "addr:postcode":"7700",
    "addr:street":"Rue Du Castert",
    "iso:country":"BE",
    "sg:address":"Rue Du Castert 135",
    "sg:city":"Mouscron",
    "sg:classifiers":[
        {
            "category":"Food & Beverages",
            "subcategory":"Groceries & Convenience Stores",
            "type":"Retail Goods"
        }
    ],
    "sg:phone":"+32 56 84 01 36",
    "sg:postcode":"7700",
    "sg:province":"Hainaut",
    "sg:tags":[
        "grocer"
    ],
    "wof:name":"Coorevits S",
    "wof:placetype":"venue"
},
  "geometry": {"coordinates":[3.1932001114,50.7528419495],"type":"Point"}
}