{
  "type": "Feature",
  "properties": {
    "addr:full":"Markt 15 Lo-reninge (lo) West-Vlaanderen 8647",
    "addr:housenumber":"15",
    "addr:postcode":"8647",
    "addr:street":"Markt;Lo-Reninge Lo West-Vlaanderen",
    "iso:country":"BE",
    "sg:address":"Markt 15",
    "sg:city":"Lo-reninge (lo)",
    "sg:classifiers":[
        {
            "category":"Health Services",
            "subcategory":"Health Practitioner",
            "type":"Services"
        }
    ],
    "sg:phone":"+32 58 28 80 71",
    "sg:postcode":"8647",
    "sg:province":"West-Vlaanderen",
    "sg:tags":[
        "physiotherapist"
    ],
    "wof:name":"Lemahieu J",
    "wof:placetype":"venue"
},
  "geometry": {"coordinates":[2.7486629486,50.9795036316],"type":"Point"}
}