{
  "type": "Feature",
  "properties": {
    "iso:country":"BE",
    "sg:address":"Grotedijk 10",
    "sg:city":"Diksmuide",
    "sg:orig_category":"Diverse grafische activiteiten",
    "sg:phone":"+32 51 50 36 23",
    "sg:postcode":"8600",
    "sg:province":"West-Vlaanderen",
    "wof:name":"Bureau Lieven",
    "wof:placetype":"venue"
},
  "geometry": {"coordinates":[2.8641200066,51.0357131958],"type":"Point"}
}