{
  "type": "Feature",
  "properties": {
    "addr:full":"Avenue Van Crombrugghe 190 Bruxelles (woluwe-saint-pierre) Bruxelles-Capitale 1150",
    "addr:housenumber":"190",
    "addr:postcode":"1150",
    "addr:street":"Avenue Van Crombrugghe",
    "iso:country":"BE",
    "sg:address":"Avenue Van Crombrugghe 190",
    "sg:city":"Bruxelles (woluwe-saint-pierre)",
    "sg:classifiers":[
        {
            "category":"Science Facility",
            "type":"Public Place"
        }
    ],
    "sg:phone":"+32 2 771 97 97",
    "sg:postcode":"1150",
    "sg:province":"Bruxelles-Capitale",
    "sg:tags":[
        "-",
        "management",
        "data",
        "processing"
    ],
    "wof:name":"Data Ware C S Sprl",
    "wof:placetype":"venue"
},
  "geometry": {"coordinates":[4.4646921158,50.830291748],"type":"Point"}
}