{
  "type": "Feature",
  "properties": {
    "addr:full":"Papestraat 10 Bilzen Limburg 3740",
    "addr:housenumber":"10",
    "addr:postcode":"3740",
    "addr:street":"Papestraat",
    "iso:country":"BE",
    "sg:address":"Papestraat 10",
    "sg:city":"Bilzen",
    "sg:orig_category":"Varkenskwekers",
    "sg:phone":"+32 12 45 19 31",
    "sg:postcode":"3740",
    "sg:province":"Limburg",
    "wof:name":"Gustaaf Hardy",
    "wof:placetype":"venue"
},
  "geometry": {"coordinates":[5.5576210022,50.8329696655],"type":"Point"}
}