{
  "type": "Feature",
  "properties": {
    "iso:country":"BE",
    "sg:address":"Edestraat 14",
    "sg:city":"Haaltert",
    "sg:classifiers":[
        {
            "category":"Home & Garden",
            "subcategory":"Kitchen Supply",
            "type":"Retail Goods"
        }
    ],
    "sg:phone":"+32 53 83 55 62",
    "sg:postcode":"9450",
    "sg:province":"Oost-Vlaanderen",
    "sg:tags":[
        "installation"
    ],
    "wof:name":"Beernaert",
    "wof:placetype":"venue"
},
  "geometry": {"coordinates":[3.9953699112,50.9091796875],"type":"Point"}
}