{
  "type": "Feature",
  "properties": {
    "iso:country":"BE",
    "sg:address":"Tragelweg 5",
    "sg:city":"Wetteren",
    "sg:classifiers":[
        {
            "category":"Wholesale",
            "subcategory":"Machinery & Supplies",
            "type":"Manufacturing & Wholesale Goods"
        }
    ],
    "sg:phone":"+32 9 369 01 28",
    "sg:postcode":"9230",
    "sg:province":"Oost-Vlaanderen",
    "sg:tags":[
        "-",
        "publishing",
        "apparatus",
        "desktop"
    ],
    "wof:name":"Buck Nv",
    "wof:placetype":"venue"
},
  "geometry": {"coordinates":[3.8954899311,51.0118179321],"type":"Point"}
}