{
  "type": "Feature",
  "properties": {
    "iso:country":"BE",
    "sg:address":"Rue Du Pr\u00c9au",
    "sg:city":"Bernissart",
    "sg:orig_category":"Sportterreinen and installaties behalve sportcentra",
    "sg:phone":"+32 65 56 11 29",
    "sg:postcode":"7321",
    "sg:province":"Hainaut",
    "wof:name":"V.c Bernissart",
    "wof:placetype":"venue"
},
  "geometry": {"coordinates":[3.6735908985,50.4789962769],"type":"Point"}
}