{
  "type": "Feature",
  "properties": {
    "iso:country":"BE",
    "sg:address":"Industrieter. Heikemp 1107",
    "sg:city":"Kinrooi",
    "sg:orig_category":"Installation de menuiserie en bois and plastique",
    "sg:phone":"+32 89 70 12 21",
    "sg:postcode":"3640",
    "sg:province":"Limburg",
    "wof:name":"Warande",
    "wof:placetype":"venue"
},
  "geometry": {"coordinates":[5.7249832153,51.1801643372],"type":"Point"}
}