{
  "type": "Feature",
  "properties": {
    "addr:full":"Rue De La Boverie 255 Seraing Li\u00e8ge 4100",
    "addr:housenumber":"255",
    "addr:postcode":"4100",
    "addr:street":"Rue De La Boverie",
    "iso:country":"BE",
    "sg:address":"Rue De La Boverie 255",
    "sg:city":"Seraing",
    "sg:orig_category":"Sportclubs Sportterreinen and installaties behalve sportcentra",
    "sg:phone":"+32 4 338 07 27",
    "sg:postcode":"4100",
    "sg:province":"Li\u00e8ge",
    "wof:name":"Rfc De Li\u00c8ge",
    "wof:placetype":"venue"
},
  "geometry": {"coordinates":[5.5030350685,50.6013298035],"type":"Point"}
}