{
  "type": "Feature",
  "properties": {
    "addr:full":"1\u00e8re Avenue 285 Herstal Li\u00e8ge 4040",
    "addr:housenumber":"285",
    "addr:postcode":"4040",
    "addr:street":"1E\u0300Re Avenue",
    "iso:country":"BE",
    "sg:address":"1\u00e8re Avenue 285",
    "sg:city":"Herstal",
    "sg:classifiers":[
        {
            "category":"Government",
            "subcategory":"Post Office",
            "type":"Public Place"
        }
    ],
    "sg:phone":"+32 4 240 72 72",
    "sg:postcode":"4040",
    "sg:province":"Li\u00e8ge",
    "sg:tags":[
        "access",
        "-",
        "part",
        "truck"
    ],
    "wof:name":"Wfz Belgium",
    "wof:placetype":"venue"
},
  "geometry": {"coordinates":[5.6154317856,50.6897239685],"type":"Point"}
}