{
  "type": "Feature",
  "properties": {
    "iso:country":"BE",
    "sg:address":"Molenstraat 7",
    "sg:city":"Hamme",
    "sg:orig_category":"Maisons de repos and r\u00e9sidences",
    "sg:phone":"+32 52 48 08 80",
    "sg:postcode":"9220",
    "sg:province":"Oost-Vlaanderen",
    "wof:name":"Rusthuis St.jozef",
    "wof:placetype":"venue"
},
  "geometry": {"coordinates":[4.1513018608,51.0622711182],"type":"Point"}
}