{
  "type": "Feature",
  "properties": {
    "addr:full":"Stationsstraat 30 Gistel West-Vlaanderen 8470",
    "addr:housenumber":"30",
    "addr:postcode":"8470",
    "addr:street":"Stationsstraat",
    "iso:country":"BE",
    "sg:address":"Stationsstraat 30",
    "sg:city":"Gistel",
    "sg:classifiers":[
        {
            "category":"Professional",
            "subcategory":"Testing Lab",
            "type":"Services"
        }
    ],
    "sg:phone":"+32 59 27 87 98",
    "sg:postcode":"8470",
    "sg:province":"West-Vlaanderen",
    "sg:tags":[
        "chemist"
    ],
    "wof:name":"Jonckheere J",
    "wof:placetype":"venue"
},
  "geometry": {"coordinates":[2.9651548862,51.1558418274],"type":"Point"}
}