{
  "type": "Feature",
  "properties": {
    "addr:full":"Rue Des Vaches 166 Quaregnon Hainaut 7390",
    "addr:housenumber":"166",
    "addr:postcode":"7390",
    "addr:street":"Rue Des Vaches",
    "iso:country":"BE",
    "sg:address":"Rue Des Vaches 166",
    "sg:city":"Quaregnon",
    "sg:orig_category":"D\u00e9taillants en pi\u00e8ces and accessoires de voitures",
    "sg:phone":"+32 65 66 72 78",
    "sg:postcode":"7390",
    "sg:province":"Hainaut",
    "wof:name":"Boutachidis",
    "wof:placetype":"venue"
},
  "geometry": {"coordinates":[3.8649699688,50.4268188477],"type":"Point"}
}