{
  "type": "Feature",
  "properties": {
    "addr:full":"Rue De La Poudri\u00c8re 6 Charleroi Hainaut 6060",
    "addr:housenumber":"6",
    "addr:postcode":"6060",
    "addr:street":"Rue De La Poudrie\u0300Re;Hainaut",
    "iso:country":"BE",
    "sg:address":"Rue De La Poudri\u00c8re 6",
    "sg:city":"Charleroi",
    "sg:orig_category":"Epiceries",
    "sg:phone":"+32 71 41 83 82",
    "sg:postcode":"6060",
    "sg:province":"Hainaut",
    "wof:name":"Maison La Brioche",
    "wof:placetype":"venue"
},
  "geometry": {"coordinates":[4.4880981445,50.4251937866],"type":"Point"}
}