{
  "type": "Feature",
  "properties": {
    "iso:country":"BE",
    "sg:address":"Industrielaan 10-12",
    "sg:city":"Hoeselt",
    "sg:classifiers":[
        {
            "category":"Parking",
            "subcategory":"Garage",
            "type":"Transportation"
        }
    ],
    "sg:phone":"+32 89 49 19 76",
    "sg:postcode":"3730",
    "sg:province":"Limburg",
    "sg:tags":[
        "truck",
        "-",
        "dump",
        "transport"
    ],
    "wof:name":"Coopmans Gebr Bvba",
    "wof:placetype":"venue"
},
  "geometry": {"coordinates":[5.4932751656,50.8588790894],"type":"Point"}
}