{
  "type": "Feature",
  "properties": {
    "iso:country":"BE",
    "sg:address":"Avenue De Jaer 22",
    "sg:city":"Sint-gillis/saint-gilles",
    "sg:orig_category":"Instituts de beaut\u00e9",
    "sg:phone":"+32 2 534 42 29",
    "sg:postcode":"1060",
    "sg:province":"Bruxelles-Capitale",
    "wof:name":"L'esth\u00c9tique Santi's",
    "wof:placetype":"venue"
},
  "geometry": {"coordinates":[4.3452181816,50.8258476257],"type":"Point"}
}