{
  "type": "Feature",
  "properties": {
    "addr:full":"Oude Koornmarkt 42 Antwerpen Antwerpen 2000",
    "addr:housenumber":"42",
    "addr:postcode":"2000",
    "addr:street":"Oude Koornmarkt",
    "iso:country":"BE",
    "sg:address":"Oude Koornmarkt 42",
    "sg:city":"Antwerpen",
    "sg:classifiers":[
        {
            "category":"Restaurant",
            "type":"Food & Drink"
        }
    ],
    "sg:phone":"+32 477 96 35 92",
    "sg:postcode":"2000",
    "sg:province":"Antwerpen",
    "wof:name":"Flamenco Caf\u00c9",
    "wof:placetype":"venue"
},
  "geometry": {"coordinates":[4.4003248215,51.219871521],"type":"Point"}
}