{
  "type": "Feature",
  "properties": {
    "addr:full":"Fonteinstraat 22 Menen (rekkem) West-Vlaanderen 8930",
    "addr:housenumber":"22",
    "addr:postcode":"8930",
    "addr:street":"Fonteinstraat",
    "iso:country":"BE",
    "sg:address":"Fonteinstraat 22",
    "sg:city":"Menen (rekkem)",
    "sg:classifiers":[
        {
            "category":"Retail",
            "subcategory":"Auto Repair",
            "type":"Services"
        }
    ],
    "sg:phone":"+32 56 42 48 66",
    "sg:postcode":"8930",
    "sg:province":"West-Vlaanderen",
    "sg:tags":[
        "garage"
    ],
    "wof:name":"Denijs L",
    "wof:placetype":"venue"
},
  "geometry": {"coordinates":[3.1662430763,50.7851104736],"type":"Point"}
}