{
  "type": "Feature",
  "properties": {
    "addr:full":"Arthur D\u00c9zangr\u00c9laan 78 Kraainem Vlaams-Brabant 1950",
    "addr:housenumber":"78",
    "addr:postcode":"1950",
    "addr:street":"De\u0301Zangre\u0301Laan",
    "iso:country":"BE",
    "sg:address":"Arthur D\u00c9zangr\u00c9laan 78",
    "sg:city":"Kraainem",
    "sg:orig_category":"Keukens and Keukenapparatuur MEUBELONTWERP AND -INSTALLATIE Meubelzaken, woning- and keukeninrichtin",
    "sg:phone":"+32 2 721 36 97",
    "sg:postcode":"1950",
    "sg:province":"Vlaams-Brabant",
    "wof:name":"Ima-kitchen Machtelinckx Bvba",
    "wof:placetype":"venue"
},
  "geometry": {"coordinates":[4.4714717865,50.861000061],"type":"Point"}
}