{
  "type": "Feature",
  "properties": {
    "addr:full":"Rue Aux Laines 59b1 Verviers Li\u00e8ge 4800",
    "addr:housenumber":"59b1",
    "addr:postcode":"4800",
    "addr:street":"Rue Aux Laines",
    "iso:country":"BE",
    "sg:address":"Rue Aux Laines 59b1",
    "sg:city":"Verviers",
    "sg:orig_category":"Rev\u00eatements pour sols and murs. Rev\u00eatements de sols and murs",
    "sg:phone":"+32 87 33 88 08",
    "sg:postcode":"4800",
    "sg:province":"Li\u00e8ge",
    "wof:name":"Grilli Michel",
    "wof:placetype":"venue"
},
  "geometry": {"coordinates":[5.8536901474,50.5889358521],"type":"Point"}
}