{
  "type": "Feature",
  "properties": {
    "addr:full":"Chauss\u00c9e De Wavre 333 Jodoigne Brabant Wallon 1370",
    "addr:housenumber":"333",
    "addr:postcode":"1370",
    "addr:street":"Chausse\u0301E De Wavre",
    "iso:country":"BE",
    "sg:address":"Chauss\u00c9e De Wavre 333",
    "sg:city":"Jodoigne",
    "sg:orig_category":"Installation \u00e9lectrique r\u00e9sidentielle",
    "sg:phone":"+32 10 81 55 54",
    "sg:postcode":"1370",
    "sg:province":"Brabant Wallon",
    "wof:name":"A.l.m. Electrics",
    "wof:placetype":"venue"
},
  "geometry": {"coordinates":[4.8418431282,50.7296600342],"type":"Point"}
}