{
  "type": "Feature",
  "properties": {
    "addr:full":"Hundelgemsebaan 79 Zwalm (hundelgem) Oost-Vlaanderen 9630",
    "addr:housenumber":"79",
    "addr:postcode":"9630",
    "addr:street":"Hundelgemsebaan;Hundelgem Oost-Vlaanderen",
    "iso:country":"BE",
    "sg:address":"Hundelgemsebaan 79",
    "sg:city":"Zwalm (hundelgem)",
    "sg:classifiers":[
        {
            "category":"Real Estate",
            "subcategory":"Architect",
            "type":"Services"
        }
    ],
    "sg:phone":"+32 55 49 77 66",
    "sg:postcode":"9630",
    "sg:province":"Oost-Vlaanderen",
    "wof:name":"Ghijselinck H",
    "wof:placetype":"venue"
},
  "geometry": {"coordinates":[3.7465429306,50.8905525208],"type":"Point"}
}