{
  "type": "Feature",
  "properties": {
    "iso:country":"BE",
    "sg:address":"Meensesteenweg 131ba",
    "sg:city":"Kortrijk",
    "sg:orig_category":"Gespecialiseerde residenti\u00eble bouw",
    "sg:phone":"+32 56 35 96 88",
    "sg:postcode":"8500",
    "sg:province":"West-Vlaanderen",
    "wof:name":"Peter Leperre",
    "wof:placetype":"venue"
},
  "geometry": {"coordinates":[3.2448120117,50.8276329041],"type":"Point"}
}