{
  "type": "Feature",
  "properties": {
    "addr:full":"Jan Stasstraat 14 Leuven Vlaams-Brabant 3000",
    "addr:housenumber":"14",
    "addr:postcode":"3000",
    "addr:street":"Jan Stasstraat",
    "iso:country":"BE",
    "sg:address":"Jan Stasstraat 14",
    "sg:city":"Leuven",
    "sg:orig_category":"Banken and kredietinstellingen",
    "sg:phone":"+32 16 22 07 21",
    "sg:postcode":"3000",
    "sg:province":"Vlaams-Brabant",
    "wof:name":"Fortis",
    "wof:placetype":"venue"
},
  "geometry": {"coordinates":[4.7072820663,50.8796577454],"type":"Point"}
}