{
  "type": "Feature",
  "properties": {
    "addr:full":"Lampstraat 60 Halle Vlaams-Brabant 1500",
    "addr:housenumber":"60",
    "addr:postcode":"1500",
    "addr:street":"Lampstraat",
    "iso:country":"BE",
    "sg:address":"Lampstraat 60",
    "sg:city":"Halle",
    "sg:orig_category":"Slagers",
    "sg:phone":"+32 2 360 15 83",
    "sg:postcode":"1500",
    "sg:province":"Vlaams-Brabant",
    "wof:name":"Fa. Pieters Luk",
    "wof:placetype":"venue"
},
  "geometry": {"coordinates":[4.2185459137,50.7431144714],"type":"Point"}
}