{
  "type": "Feature",
  "properties": {
    "addr:full":"Dorpsstraat 1 Wetteren (westrem) Oost-Vlaanderen 9230",
    "addr:housenumber":"1",
    "addr:postcode":"9230",
    "addr:street":"Dorpsstraat",
    "iso:country":"BE",
    "sg:address":"Dorpsstraat 1",
    "sg:city":"Wetteren (westrem)",
    "sg:classifiers":[
        {
            "category":"Autos & Motor Vehicles",
            "subcategory":"Automobile Sales",
            "type":"Retail Goods"
        }
    ],
    "sg:phone":"+32 9 366 26 65",
    "sg:postcode":"9230",
    "sg:province":"Oost-Vlaanderen",
    "sg:tags":[
        "car",
        "used",
        "-"
    ],
    "wof:name":"De Backer C",
    "wof:placetype":"venue"
},
  "geometry": {"coordinates":[3.8692989349,50.9719467163],"type":"Point"}
}