{
  "type": "Feature",
  "properties": {
    "iso:country":"BE",
    "sg:address":"Tielensteenweg 14",
    "sg:city":"Kasterlee (lichtaart)",
    "sg:orig_category":"Non-Classified Establishments",
    "sg:phone":"+32 14 55 19 90",
    "sg:postcode":"2460",
    "sg:province":"Antwerpen",
    "wof:name":"Nutri-ad International",
    "wof:placetype":"venue"
},
  "geometry": {"coordinates":[4.8991398811,51.2407302856],"type":"Point"}
}