{
  "type": "Feature",
  "properties": {
    "addr:full":"Dr. E. Van Winckellaan 7 Dendermonde Oost-Vlaanderen 9200",
    "addr:housenumber":"7",
    "addr:postcode":"9200",
    "addr:street":"Dr. E. Van Winckellaan;Oost-Vlaanderen",
    "iso:country":"BE",
    "sg:address":"Dr. E. Van Winckellaan 7",
    "sg:city":"Dendermonde",
    "sg:orig_category":"Notarissen",
    "sg:phone":"+32 52 20 28 59",
    "sg:postcode":"9200",
    "sg:province":"Oost-Vlaanderen",
    "wof:name":"Fran\u00c7ois De Clippel",
    "wof:placetype":"venue"
},
  "geometry": {"coordinates":[4.0971651077,51.029838562],"type":"Point"}
}