{
  "type": "Feature",
  "properties": {
    "iso:country":"BE",
    "sg:address":"Avenue Marie-jos\u00e9 57",
    "sg:city":"Binche",
    "sg:classifiers":[
        {
            "category":"Personal",
            "type":"Services"
        }
    ],
    "sg:phone":"+32 64 33 19 52",
    "sg:postcode":"7130",
    "sg:province":"Hainaut",
    "sg:tags":[
        "clothing",
        "men's",
        "tailor",
        "-"
    ],
    "wof:name":"Salciccia E",
    "wof:placetype":"venue"
},
  "geometry": {"coordinates":[4.1799411774,50.4137191772],"type":"Point"}
}