{
  "type": "Feature",
  "properties": {
    "addr:full":"Avenue Blonden 90 Li\u00c8ge Li\u00e8ge 4000",
    "addr:housenumber":"90",
    "addr:postcode":"4000",
    "addr:street":"Avenue Blonden",
    "iso:country":"BE",
    "sg:address":"Avenue Blonden 90",
    "sg:city":"Li\u00c8ge",
    "sg:orig_category":"Pharmaciens",
    "sg:phone":"+32 4 252 41 87",
    "sg:postcode":"4000",
    "sg:province":"Li\u00e8ge",
    "wof:name":"Pharm. Lemperez-delbrouck",
    "wof:placetype":"venue"
},
  "geometry": {"coordinates":[5.571996212,50.6274261475],"type":"Point"}
}