{
  "type": "Feature",
  "properties": {
    "iso:country":"BE",
    "sg:address":"Rue Dehan 11",
    "sg:city":"Rixensart (genval)",
    "sg:classifiers":[
        {
            "category":"Health Services",
            "subcategory":"Nursing And Care Facility",
            "type":"Services"
        }
    ],
    "sg:phone":"+32 2 654 03 20",
    "sg:postcode":"1332",
    "sg:province":"Brabant Wallon",
    "sg:tags":[
        "home"
    ],
    "wof:name":"Dominique P",
    "wof:placetype":"venue"
},
  "geometry": {"coordinates":[4.4955229759,50.7149200439],"type":"Point"}
}