{
  "type": "Feature",
  "properties": {
    "addr:full":"Rue Des Ecoles 27 Pont-a-celles Hainaut 6230",
    "addr:housenumber":"27",
    "addr:postcode":"6230",
    "addr:street":"Rue Des Ecoles",
    "iso:country":"BE",
    "sg:address":"Rue Des Ecoles 27",
    "sg:city":"Pont-a-celles",
    "sg:orig_category":"Installation de menuiserie m\u00e9tallique",
    "sg:phone":"+32 71 84 43 46",
    "sg:postcode":"6230",
    "sg:province":"Hainaut",
    "wof:name":"La Chainerie G. & Fils",
    "wof:placetype":"venue"
},
  "geometry": {"coordinates":[4.3582878113,50.5130577087],"type":"Point"}
}