{
  "type": "Feature",
  "properties": {
    "addr:full":"Hagelstein 27 Voeren/fourons Limburg 3791",
    "addr:housenumber":"27",
    "addr:postcode":"3791",
    "addr:street":"Hagelstein",
    "iso:country":"BE",
    "sg:address":"Hagelstein 27",
    "sg:city":"Voeren/fourons",
    "sg:orig_category":"Eleveurs de bovins",
    "sg:phone":"+32 4 381 07 12",
    "sg:postcode":"3791",
    "sg:province":"Limburg",
    "wof:name":"Antoine Leclerc",
    "wof:placetype":"venue"
},
  "geometry": {"coordinates":[5.8722071648,50.7144393921],"type":"Point"}
}