{
  "type": "Feature",
  "properties": {
    "addr:full":"Chemin Des Merles 2 Lessines (deux-acren) Hainaut 7864",
    "addr:housenumber":"2",
    "addr:postcode":"7864",
    "addr:street":"Chemin Des Merles",
    "iso:country":"BE",
    "sg:address":"Chemin Des Merles 2",
    "sg:city":"Lessines (deux-acren)",
    "sg:classifiers":[
        {
            "category":"Retail",
            "subcategory":"Auto Repair",
            "type":"Services"
        }
    ],
    "sg:phone":"+32 496 27 50 94",
    "sg:postcode":"7864",
    "sg:province":"Hainaut",
    "sg:tags":[
        "garage"
    ],
    "wof:name":"Vanderzwalmen M",
    "wof:placetype":"venue"
},
  "geometry": {"coordinates":[3.8372719288,50.7339935303],"type":"Point"}
}