{
  "type": "Feature",
  "properties": {
    "iso:country":"BE",
    "sg:address":"Av. De Woluwe-st-lambert 2",
    "sg:city":"Sint-lambrechts-woluwe/woluwe-saint-lambert",
    "sg:classifiers":[
        {
            "category":"Restaurant",
            "type":"Food & Drink"
        }
    ],
    "sg:phone":"+32 2 735 92 82",
    "sg:postcode":"1200",
    "sg:province":"Bruxelles-Capitale",
    "wof:name":"Kipling Grill",
    "wof:placetype":"venue"
},
  "geometry": {"coordinates":[4.411796093,50.8403205872],"type":"Point"}
}