{
  "type": "Feature",
  "properties": {
    "iso:country":"BE",
    "sg:address":"Rue Grand'rue 16",
    "sg:city":"Ottignies-louvain-la-neuve (c\u00e9roux-mousty)",
    "sg:classifiers":[
        {
            "category":"Utilities",
            "subcategory":"Fuel Oil & Lpg",
            "type":"Services"
        }
    ],
    "sg:phone":"+32 10 61 23 57",
    "sg:postcode":"1341",
    "sg:province":"Brabant Wallon",
    "wof:name":"Maboge L Mazout",
    "wof:placetype":"venue"
},
  "geometry": {"coordinates":[4.5068697929,50.667175293],"type":"Point"}
}