{
  "type": "Feature",
  "properties": {
    "iso:country":"BE",
    "sg:address":"Kasteelstraat 20",
    "sg:city":"Mol",
    "sg:classifiers":[
        {
            "category":"Food & Beverages",
            "subcategory":"Dairy",
            "type":"Retail Goods"
        }
    ],
    "sg:phone":"+32 14 31 66 17",
    "sg:postcode":"2400",
    "sg:province":"Antwerpen",
    "sg:tags":[
        "product",
        "-"
    ],
    "wof:name":"Goetschalckx J",
    "wof:placetype":"venue"
},
  "geometry": {"coordinates":[5.1840810776,51.2852249146],"type":"Point"}
}