{
  "type": "Feature",
  "properties": {
    "addr:full":"Rue Des R\u00e9collets 12 Bastogne Luxembourg 6600",
    "addr:housenumber":"12",
    "addr:postcode":"6600",
    "addr:street":"Rue Des Re\u0301Collets",
    "iso:country":"BE",
    "sg:address":"Rue Des R\u00e9collets 12",
    "sg:city":"Bastogne",
    "sg:classifiers":[
        {
            "category":"Social Services",
            "type":"Services"
        }
    ],
    "sg:phone":"+32 61 24 09 20",
    "sg:postcode":"6600",
    "sg:province":"Luxembourg",
    "wof:name":"Cpas",
    "wof:placetype":"venue"
},
  "geometry": {"coordinates":[5.7187128067,50.0017852783],"type":"Point"}
}