{
  "type": "Feature",
  "properties": {
    "iso:country":"BE",
    "sg:address":"Route Provinciale 330",
    "sg:city":"Wavre",
    "sg:orig_category":"Herstellingen and onderhoud van auto's",
    "sg:phone":"+32 10 41 31 36",
    "sg:postcode":"1301",
    "sg:province":"Brabant Wallon",
    "wof:name":"Desmet & Fils",
    "wof:placetype":"venue"
},
  "geometry": {"coordinates":[4.5812849998,50.7129745483],"type":"Point"}
}