{
  "type": "Feature",
  "properties": {
    "addr:full":"Avenue Moli\u00e8re 339 Bruxelles (uccle) Bruxelles-Capitale 1180",
    "addr:housenumber":"339",
    "addr:postcode":"1180",
    "addr:street":"Avenue Molie\u0300Re",
    "iso:country":"BE",
    "sg:address":"Avenue Moli\u00e8re 339",
    "sg:city":"Bruxelles (uccle)",
    "sg:classifiers":[
        {
            "category":"Professional",
            "subcategory":"Engineering",
            "type":"Services"
        }
    ],
    "sg:phone":"+32 2 345 20 85",
    "sg:postcode":"1180",
    "sg:province":"Bruxelles-Capitale",
    "sg:tags":[
        "-"
    ],
    "wof:name":"Interaqua Sa",
    "wof:placetype":"venue"
},
  "geometry": {"coordinates":[4.359954834,50.8154792786],"type":"Point"}
}