{
  "type": "Feature",
  "properties": {
    "addr:full":"Place Emile Vandervelde 56 Saint-nicolas (montegn\u00e9e) Li\u00e8ge 4420",
    "addr:housenumber":"56",
    "addr:postcode":"4420",
    "addr:street":"Place Emile Vandervelde;Montegne\u0301E",
    "iso:country":"BE",
    "sg:address":"Place Emile Vandervelde 56",
    "sg:city":"Saint-nicolas (montegn\u00e9e)",
    "sg:classifiers":[
        {
            "category":"Bakery",
            "type":"Food & Drink"
        }
    ],
    "sg:phone":"+32 4 263 79 34",
    "sg:postcode":"4420",
    "sg:province":"Li\u00e8ge",
    "sg:tags":[
        "confectioner",
        "baker"
    ],
    "wof:name":"Dozo P",
    "wof:placetype":"venue"
},
  "geometry": {"coordinates":[5.516272068,50.6368637085],"type":"Point"}
}