{
  "type": "Feature",
  "properties": {
    "iso:country":"BE",
    "sg:address":"Pylyserlaan 46",
    "sg:city":"Koksijde",
    "sg:classifiers":[
        {
            "category":"Building & Trades",
            "subcategory":"Landscaping Services",
            "type":"Services"
        }
    ],
    "sg:phone":"+32 58 51 59 09",
    "sg:postcode":"8670",
    "sg:province":"West-Vlaanderen",
    "sg:tags":[
        "gardening",
        "garden",
        "maintenance"
    ],
    "wof:name":"Depuydt J",
    "wof:placetype":"venue"
},
  "geometry": {"coordinates":[2.6512351036,51.1086883545],"type":"Point"}
}