{
  "type": "Feature",
  "properties": {
    "iso:country":"BE",
    "sg:address":"Milisstraat 14",
    "sg:city":"Antwerpen",
    "sg:orig_category":"Artiesten and kunstenaars",
    "sg:phone":"+32 3 236 21 67",
    "sg:postcode":"2018",
    "sg:province":"Antwerpen",
    "wof:name":"Van Overberghe",
    "wof:placetype":"venue"
},
  "geometry": {"coordinates":[4.4265418053,51.2137947083],"type":"Point"}
}