{
  "type": "Feature",
  "properties": {
    "iso:country":"BE",
    "sg:address":"Vaartlaan 52",
    "sg:city":"Brecht",
    "sg:classifiers":[
        {
            "category":"Food & Beverages",
            "subcategory":"Fruits & Vegetables",
            "type":"Retail Goods"
        }
    ],
    "sg:phone":"+32 3 636 18 76",
    "sg:postcode":"2960",
    "sg:province":"Antwerpen",
    "sg:tags":[
        "l\u00e9gumes"
    ],
    "wof:name":"Bauweraerts",
    "wof:placetype":"venue"
},
  "geometry": {"coordinates":[4.5580301285,51.2971572876],"type":"Point"}
}