{
  "type": "Feature",
  "properties": {
    "iso:country":"BE",
    "sg:address":"Nederstenkouter 4",
    "sg:city":"Brakel",
    "sg:orig_category":"Sportclubs",
    "sg:phone":"+32 55 42 17 01",
    "sg:postcode":"9660",
    "sg:province":"Oost-Vlaanderen",
    "wof:name":"W.s.c. Jong & Moedig",
    "wof:placetype":"venue"
},
  "geometry": {"coordinates":[3.7647950649,50.807598114],"type":"Point"}
}