{
  "type": "Feature",
  "properties": {
    "iso:country":"BE",
    "sg:address":"Rue De Saint-leger 180",
    "sg:city":"Moeskroen/mouscron",
    "sg:classifiers":[
        {
            "category":"Cafe",
            "type":"Food & Drink"
        }
    ],
    "sg:phone":"+32 56 48 96 49",
    "sg:postcode":"7711",
    "sg:province":"Hainaut",
    "sg:tags":[
        "caf\u00e9s"
    ],
    "wof:name":"Caf\u00c9 Le Royal",
    "wof:placetype":"venue"
},
  "geometry": {"coordinates":[3.2929000854,50.7344207764],"type":"Point"}
}