{
  "type": "Feature",
  "properties": {
    "addr:full":"Rue Jules Rasquinet 97 Beyne-heusay Li\u00e8ge 4610",
    "addr:housenumber":"97",
    "addr:postcode":"4610",
    "addr:street":"Rue Jules Rasquinet",
    "iso:country":"BE",
    "sg:address":"Rue Jules Rasquinet 97",
    "sg:city":"Beyne-heusay",
    "sg:orig_category":"Verhuisdiensten",
    "sg:phone":"+32 4 370 02 22",
    "sg:postcode":"4610",
    "sg:province":"Li\u00e8ge",
    "wof:name":"Thierry Fontaine",
    "wof:placetype":"venue"
},
  "geometry": {"coordinates":[5.6611189842,50.6181983948],"type":"Point"}
}