{
  "type": "Feature",
  "properties": {
    "addr:full":"St-laurentiuslaan 53 Oostakker Oost-Vlaanderen 9041",
    "addr:housenumber":"53",
    "addr:postcode":"9041",
    "addr:street":"St-Laurentiuslaan",
    "iso:country":"BE",
    "sg:address":"St-laurentiuslaan 53",
    "sg:city":"Oostakker",
    "sg:classifiers":[
        {
            "category":"Manufacturing",
            "subcategory":"Printing",
            "type":"Manufacturing & Wholesale Goods"
        }
    ],
    "sg:phone":"+32 9 251 42 94",
    "sg:postcode":"9041",
    "sg:province":"Oost-Vlaanderen",
    "sg:tags":[
        "publishing"
    ],
    "wof:name":"Diligentia Uitgeverij Bvba",
    "wof:placetype":"venue"
},
  "geometry": {"coordinates":[3.772190094,51.0995330811],"type":"Point"}
}