{
  "type": "Feature",
  "properties": {
    "addr:full":"Rue De L'ermitage 48a Jalhay (sart) Li\u00e8ge 4845",
    "addr:housenumber":"48a",
    "addr:postcode":"4845",
    "addr:street":"Rue De L'Ermitage;Sart Lie\u0300Ge",
    "iso:country":"BE",
    "sg:address":"Rue De L'ermitage 48a",
    "sg:city":"Jalhay (sart)",
    "sg:classifiers":[
        {
            "category":"Health Services",
            "subcategory":"Nursing And Care Facility",
            "type":"Services"
        }
    ],
    "sg:phone":"+32 87 47 48 78",
    "sg:postcode":"4845",
    "sg:province":"Li\u00e8ge",
    "sg:tags":[
        "home"
    ],
    "wof:name":"Moureau N",
    "wof:placetype":"venue"
},
  "geometry": {"coordinates":[5.9259181023,50.5121154785],"type":"Point"}
}