{
  "type": "Feature",
  "properties": {
    "iso:country":"BE",
    "sg:address":"Rue Des Ecoles 30",
    "sg:city":"Comblain-au-pont",
    "sg:classifiers":[
        {
            "category":"Insurance",
            "subcategory":"Life Insurance",
            "type":"Services"
        }
    ],
    "sg:phone":"+32 4 380 93 11",
    "sg:postcode":"4171",
    "sg:province":"Li\u00e8ge",
    "sg:tags":[
        "assurance"
    ],
    "wof:name":"P&v",
    "wof:placetype":"venue"
},
  "geometry": {"coordinates":[5.5812139511,50.5091629028],"type":"Point"}
}