{
  "type": "Feature",
  "properties": {
    "iso:country":"BE",
    "sg:address":"Hoge Darisdonk 43",
    "sg:city":"Oud-turnhout",
    "sg:orig_category":"Rundveehouders",
    "sg:phone":"+32 14 45 15 30",
    "sg:postcode":"2360",
    "sg:province":"Antwerpen",
    "wof:name":"Paul Wens",
    "wof:placetype":"venue"
},
  "geometry": {"coordinates":[5.0002031326,51.2898445129],"type":"Point"}
}