{
  "type": "Feature",
  "properties": {
    "iso:country":"BE",
    "sg:address":"Huybergsebaan 88",
    "sg:city":"Essen",
    "sg:classifiers":[
        {
            "category":"Building & Trades",
            "subcategory":"Landscaping Services",
            "type":"Services"
        }
    ],
    "sg:phone":"+32 3 677 23 63",
    "sg:postcode":"2910",
    "sg:province":"Antwerpen",
    "sg:tags":[
        "gardening",
        "garden",
        "maintenance"
    ],
    "wof:name":"Gebruers M",
    "wof:placetype":"venue"
},
  "geometry": {"coordinates":[4.4236001968,51.4282913208],"type":"Point"}
}