{
  "type": "Feature",
  "properties": {
    "addr:full":"Rue Albert Ier 45 Erquelinnes Hainaut 6560",
    "addr:housenumber":"45",
    "addr:postcode":"6560",
    "addr:street":"Rue Albert Ier",
    "iso:country":"BE",
    "sg:address":"Rue Albert Ier 45",
    "sg:city":"Erquelinnes",
    "sg:classifiers":[
        {
            "category":"Professional",
            "subcategory":"Accounting & Tax Preparation",
            "type":"Services"
        }
    ],
    "sg:phone":"+32 71 55 61 81",
    "sg:postcode":"6560",
    "sg:province":"Hainaut",
    "sg:tags":[
        "accountant"
    ],
    "wof:name":"Jean-marie Potie",
    "wof:placetype":"venue"
},
  "geometry": {"coordinates":[4.1207499504,50.3097915649],"type":"Point"}
}