{
  "type": "Feature",
  "properties": {
    "iso:country":"BE",
    "sg:address":"Quai Winston Churchill 11bb",
    "sg:city":"Li\u00c8ge",
    "sg:classifiers":[
        {
            "category":"Personal",
            "subcategory":"Beauty Salon",
            "type":"Services"
        }
    ],
    "sg:phone":"+32 4 342 13 20",
    "sg:postcode":"4020",
    "sg:province":"Li\u00e8ge",
    "sg:tags":[
        "de",
        "coiffure"
    ],
    "wof:name":"Coiffure Racine Carr\u00c9e",
    "wof:placetype":"venue"
},
  "geometry": {"coordinates":[5.5772299767,50.6367111206],"type":"Point"}
}