{
  "type": "Feature",
  "properties": {
    "addr:full":"Turnhoutsebaan 8bb Diest Vlaams-Brabant 3290",
    "addr:housenumber":"8bb",
    "addr:postcode":"3290",
    "addr:street":"Turnhoutsebaan",
    "iso:country":"BE",
    "sg:address":"Turnhoutsebaan 8bb",
    "sg:city":"Diest",
    "sg:classifiers":[
        {
            "category":"Taxi",
            "type":"Transportation"
        }
    ],
    "sg:phone":"+32 13 31 11 56",
    "sg:postcode":"3290",
    "sg:province":"Vlaams-Brabant",
    "sg:tags":[
        "taxi's"
    ],
    "wof:name":"Taxi Bergmans",
    "wof:placetype":"venue"
},
  "geometry": {"coordinates":[5.0508031845,50.9924812317],"type":"Point"}
}