{
  "type": "Feature",
  "properties": {
    "addr:full":"Rue L\u00c9on Dubray 7 Montigny-le-tilleul Hainaut 6110",
    "addr:housenumber":"7",
    "addr:postcode":"6110",
    "addr:street":"Rue Le\u0301On Dubray",
    "iso:country":"BE",
    "sg:address":"Rue L\u00c9on Dubray 7",
    "sg:city":"Montigny-le-tilleul",
    "sg:orig_category":"M\u00e9decins and sp\u00e9cialistes",
    "sg:phone":"+32 71 51 52 26",
    "sg:postcode":"6110",
    "sg:province":"Hainaut",
    "wof:name":"Anne Charon",
    "wof:placetype":"venue"
},
  "geometry": {"coordinates":[4.3708000183,50.3702507019],"type":"Point"}
}