{
  "type": "Feature",
  "properties": {
    "iso:country":"BE",
    "sg:address":"Rue De La Montagne 14",
    "sg:city":"Walcourt",
    "sg:classifiers":[
        {
            "category":"Insurance",
            "subcategory":"Insurance Agent",
            "type":"Services"
        }
    ],
    "sg:phone":"+32 71 61 15 62",
    "sg:postcode":"5650",
    "sg:province":"Namur",
    "sg:tags":[
        "broker"
    ],
    "wof:name":"Werion J P Sca",
    "wof:placetype":"venue"
},
  "geometry": {"coordinates":[4.4329061508,50.2537269592],"type":"Point"}
}