{
  "type": "Feature",
  "properties": {
    "iso:country":"BE",
    "sg:address":"Rue Du Calvaire 171",
    "sg:city":"Mouscron",
    "sg:classifiers":[
        {
            "category":"Retail",
            "subcategory":"Event Space",
            "type":"Services"
        }
    ],
    "sg:phone":"+32 56 33 59 89",
    "sg:postcode":"7700",
    "sg:province":"Hainaut",
    "sg:tags":[
        "rental",
        "-",
        "hall"
    ],
    "wof:name":"Compagnons De La Ste Famille (les)",
    "wof:placetype":"venue"
},
  "geometry": {"coordinates":[3.1891379356,50.7448005676],"type":"Point"}
}