{
  "type": "Feature",
  "properties": {
    "addr:full":"Kortrijkstraat 63bz Deinze Oost-Vlaanderen 9800",
    "addr:postcode":"9800",
    "addr:street":"Kortrijkstraat;Oost-Vlaanderen",
    "iso:country":"BE",
    "sg:address":"Kortrijkstraat 63bz",
    "sg:city":"Deinze",
    "sg:classifiers":[
        {
            "category":"Fast Food",
            "type":"Food & Drink"
        }
    ],
    "sg:phone":"+32 9 380 43 63",
    "sg:postcode":"9800",
    "sg:province":"Oost-Vlaanderen",
    "sg:tags":[
        "meeneem",
        "restaurant"
    ],
    "wof:name":"Monique",
    "wof:placetype":"venue"
},
  "geometry": {"coordinates":[3.5275781155,50.9773712158],"type":"Point"}
}