{
  "type": "Feature",
  "properties": {
    "addr:full":"Rue De Huy 45 Ohey Namur 5350",
    "addr:housenumber":"45",
    "addr:postcode":"5350",
    "addr:street":"Rue De Huy",
    "iso:country":"BE",
    "sg:address":"Rue De Huy 45",
    "sg:city":"Ohey",
    "sg:orig_category":"Eleveurs de bovins",
    "sg:phone":"+32 85 61 16 62",
    "sg:postcode":"5350",
    "sg:province":"Namur",
    "wof:name":"Philippe Depaye",
    "wof:placetype":"venue"
},
  "geometry": {"coordinates":[5.1267800331,50.4299316406],"type":"Point"}
}