{
  "type": "Feature",
  "properties": {
    "iso:country":"BE",
    "sg:address":"Rue Du Cou\u00ebt 20",
    "sg:city":"Mouscron",
    "sg:classifiers":[
        {
            "category":"Personal",
            "subcategory":"Beauty Salon",
            "type":"Services"
        }
    ],
    "sg:phone":"+32 56 84 42 56",
    "sg:postcode":"7700",
    "sg:province":"Hainaut",
    "sg:tags":[
        "lady",
        "-",
        "hairdressing"
    ],
    "wof:name":"Michele",
    "wof:placetype":"venue"
},
  "geometry": {"coordinates":[3.194988966,50.7406196594],"type":"Point"}
}