{
  "type": "Feature",
  "properties": {
    "iso:country":"BE",
    "sg:address":"Tiensesteenweg 195",
    "sg:city":"Sint-truiden",
    "sg:classifiers":[
        {
            "category":"Bars & Pubs",
            "type":"Food & Drink"
        }
    ],
    "sg:phone":"+32 11 48 46 33",
    "sg:postcode":"3800",
    "sg:province":"Limburg",
    "sg:tags":[
        "tavern"
    ],
    "wof:name":"Bourgonier (de)",
    "wof:placetype":"venue"
},
  "geometry": {"coordinates":[5.1676530838,50.8145217896],"type":"Point"}
}