{
  "type": "Feature",
  "properties": {
    "iso:country":"BE",
    "sg:address":"Viermaartlaan 21",
    "sg:city":"Ronse",
    "sg:orig_category":"Agences de publicit\u00e9",
    "sg:phone":"+32 55 20 76 10",
    "sg:postcode":"9600",
    "sg:province":"Oost-Vlaanderen",
    "wof:name":"Kate Connelly",
    "wof:placetype":"venue"
},
  "geometry": {"coordinates":[3.5962200165,50.7408714294],"type":"Point"}
}