{
  "type": "Feature",
  "properties": {
    "iso:country":"BE",
    "sg:address":"Place Du Souvenir 2",
    "sg:city":"Seraing",
    "sg:classifiers":[
        {
            "category":"Health Services",
            "subcategory":"Doctor",
            "type":"Services"
        }
    ],
    "sg:phone":"+32 4 337 53 42",
    "sg:postcode":"4100",
    "sg:province":"Li\u00e8ge",
    "sg:tags":[
        "medicinephysicians",
        "surgeon"
    ],
    "wof:name":"Bou\u00fcaert C",
    "wof:placetype":"venue"
},
  "geometry": {"coordinates":[5.5109558105,50.5825767517],"type":"Point"}
}