{
  "type": "Feature",
  "properties": {
    "iso:country":"BE",
    "sg:address":"Kerkeneind 16-18",
    "sg:city":"Kalmthout",
    "sg:classifiers":[
        {
            "category":"Shopping",
            "subcategory":"Hobbies, Toys, & Games",
            "type":"Retail Goods"
        }
    ],
    "sg:phone":"+32 3 666 47 13",
    "sg:postcode":"2920",
    "sg:province":"Antwerpen",
    "sg:tags":[
        "toy",
        "-"
    ],
    "wof:name":"Sparreke ('t)",
    "wof:placetype":"venue"
},
  "geometry": {"coordinates":[4.4762392044,51.3824920654],"type":"Point"}
}