{
  "type": "Feature",
  "properties": {
    "addr:full":"Pontstraat 109 Deinze (astene) Oost-Vlaanderen 9800",
    "addr:housenumber":"109",
    "addr:postcode":"9800",
    "addr:street":"Pontstraat",
    "iso:country":"BE",
    "sg:address":"Pontstraat 109",
    "sg:city":"Deinze (astene)",
    "sg:classifiers":[
        {
            "category":"Retail",
            "subcategory":"Auto Repair",
            "type":"Services"
        }
    ],
    "sg:phone":"+32 9 386 11 52",
    "sg:postcode":"9800",
    "sg:province":"Oost-Vlaanderen",
    "sg:tags":[
        "garage"
    ],
    "wof:name":"Weytens Bvba",
    "wof:placetype":"venue"
},
  "geometry": {"coordinates":[3.5719320774,50.9802322388],"type":"Point"}
}