{
  "type": "Feature",
  "properties": {
    "iso:country":"BE",
    "sg:address":"Geraardsbergsestraat 89",
    "sg:city":"Aalst",
    "sg:orig_category":"Epiceries",
    "sg:phone":"+32 53 21 16 58",
    "sg:postcode":"9300",
    "sg:province":"Oost-Vlaanderen",
    "wof:name":"E. Boone",
    "wof:placetype":"venue"
},
  "geometry": {"coordinates":[4.0359539986,50.9320220947],"type":"Point"}
}