{
  "type": "Feature",
  "properties": {
    "addr:full":"Avenue Georges Lecointe 50 Bruxelles (uccle) Bruxelles-Capitale 1180",
    "addr:housenumber":"50",
    "addr:postcode":"1180",
    "addr:street":"Avenue Georges Lecointe",
    "iso:country":"BE",
    "sg:address":"Avenue Georges Lecointe 50",
    "sg:city":"Bruxelles (uccle)",
    "sg:classifiers":[
        {
            "category":"Professional",
            "subcategory":"Art Services",
            "type":"Services"
        }
    ],
    "sg:phone":"+32 2 375 39 62",
    "sg:postcode":"1180",
    "sg:province":"Bruxelles-Capitale",
    "sg:tags":[
        "design",
        "packing",
        "-",
        "realization"
    ],
    "wof:name":"Design Board Sa",
    "wof:placetype":"venue"
},
  "geometry": {"coordinates":[4.3519182205,50.7959213257],"type":"Point"}
}