{
  "type": "Feature",
  "properties": {
    "addr:full":"Rue Albert Ier 36 Pont-a-celles Hainaut 6230",
    "addr:housenumber":"36",
    "addr:postcode":"6230",
    "addr:street":"Rue Albert Ier",
    "iso:country":"BE",
    "sg:address":"Rue Albert Ier 36",
    "sg:city":"Pont-a-celles",
    "sg:orig_category":"Artsen and specialisten",
    "sg:phone":"+32 71 35 97 56",
    "sg:postcode":"6230",
    "sg:province":"Hainaut",
    "wof:name":"P. Dandoy",
    "wof:placetype":"venue"
},
  "geometry": {"coordinates":[4.3707361221,50.507106781],"type":"Point"}
}