{
  "type": "Feature",
  "properties": {
    "iso:country":"BE",
    "sg:address":"Bure Close 5",
    "sg:city":"Thimister-clermont (thimister)",
    "sg:classifiers":[
        {
            "category":"Health Services",
            "subcategory":"Health Practitioner",
            "type":"Services"
        }
    ],
    "sg:phone":"+32 87 44 56 41",
    "sg:postcode":"4890",
    "sg:province":"Li\u00e8ge",
    "sg:tags":[
        "physiotherapist"
    ],
    "wof:name":"Bastin Jean-michel",
    "wof:placetype":"venue"
},
  "geometry": {"coordinates":[5.8408198357,50.663444519],"type":"Point"}
}