{
  "type": "Feature",
  "properties": {
    "addr:full":"Rue Du Centre 98 Fauvillers Luxembourg 6637",
    "addr:housenumber":"98",
    "addr:postcode":"6637",
    "addr:street":"Rue Du Centre",
    "iso:country":"BE",
    "sg:address":"Rue Du Centre 98",
    "sg:city":"Fauvillers",
    "sg:orig_category":"Jardinage",
    "sg:phone":"+32 63 60 13 97",
    "sg:postcode":"6637",
    "sg:province":"Luxembourg",
    "wof:name":"L'arboriste",
    "wof:placetype":"venue"
},
  "geometry": {"coordinates":[5.6638197899,49.8519592285],"type":"Point"}
}