{
  "type": "Feature",
  "properties": {
    "iso:country":"BE",
    "sg:address":"Chauss\u00e9e De Louvain 43 Box 5",
    "sg:city":"Wavre",
    "sg:classifiers":[
        {
            "category":"Social Services",
            "type":"Services"
        }
    ],
    "sg:phone":"+32 10 24 20 45",
    "sg:postcode":"1300",
    "sg:province":"Brabant Wallon",
    "wof:name":"Mutualit\u00e9s Libres-centre Ind\u00e9pendant D'aide Sociale",
    "wof:placetype":"venue"
},
  "geometry": {"coordinates":[4.6140141487,50.7140464783],"type":"Point"}
}