{
  "type": "Feature",
  "properties": {
    "iso:country":"BE",
    "sg:address":"Diestsesteenweg 79",
    "sg:city":"Herk-de-stad",
    "sg:classifiers":[
        {
            "category":"Food & Beverages",
            "subcategory":"Groceries & Convenience Stores",
            "type":"Retail Goods"
        }
    ],
    "sg:phone":"+32 13 55 19 76",
    "sg:postcode":"3540",
    "sg:province":"Limburg",
    "sg:tags":[
        "grocer"
    ],
    "wof:name":"Smeets L",
    "wof:placetype":"venue"
},
  "geometry": {"coordinates":[5.1511001587,50.9432029724],"type":"Point"}
}