{
  "type": "Feature",
  "properties": {
    "addr:full":"Avenue J. De Ridder 74 Wemmel Vlaams-Brabant 1780",
    "addr:housenumber":"74",
    "addr:postcode":"1780",
    "addr:street":"Avenue J. De Ridder;Vlaams-Brabant",
    "iso:country":"BE",
    "sg:address":"Avenue J. De Ridder 74",
    "sg:city":"Wemmel",
    "sg:classifiers":[
        {
            "category":"Professional",
            "subcategory":"Management & Consulting",
            "type":"Services"
        }
    ],
    "sg:phone":"+32 2 461 07 20",
    "sg:postcode":"1780",
    "sg:province":"Vlaams-Brabant",
    "sg:tags":[
        "tax-consultants"
    ],
    "wof:name":"Florizoone Anthony Expert-comptable Sprl",
    "wof:placetype":"venue"
},
  "geometry": {"coordinates":[4.3145461082,50.9005775452],"type":"Point"}
}