{
  "type": "Feature",
  "properties": {
    "addr:full":"Patersstraat 117 Turnhout Antwerpen 2300",
    "addr:housenumber":"117",
    "addr:postcode":"2300",
    "addr:street":"Patersstraat",
    "iso:country":"BE",
    "sg:address":"Patersstraat 117",
    "sg:city":"Turnhout",
    "sg:classifiers":[
        {
            "category":"Communications",
            "subcategory":"Film & Video Production",
            "type":"Services"
        }
    ],
    "sg:phone":"+32 14 41 23 65",
    "sg:postcode":"2300",
    "sg:province":"Antwerpen",
    "sg:tags":[
        "multimedia",
        "-",
        "system"
    ],
    "wof:name":"Wim Proost - Pro Graphic Bvba",
    "wof:placetype":"venue"
},
  "geometry": {"coordinates":[4.9493842125,51.3274765015],"type":"Point"}
}