{
  "type": "Feature",
  "properties": {
    "iso:country":"BE",
    "sg:address":"Heyaard 19",
    "sg:city":"Brecht",
    "sg:orig_category":"Schoonheidssalons",
    "sg:phone":"+32 3 636 21 61",
    "sg:postcode":"2960",
    "sg:province":"Antwerpen",
    "wof:name":"Tanja Van Dooren",
    "wof:placetype":"venue"
},
  "geometry": {"coordinates":[4.555533886,51.287979126],"type":"Point"}
}