{
  "type": "Feature",
  "properties": {
    "addr:full":"Grasmarkt 105b460 Brussel/bruxelles Bruxelles-Capitale 1000",
    "addr:housenumber":"105b460",
    "addr:postcode":"1000",
    "addr:street":"Grasmarkt;/",
    "iso:country":"BE",
    "sg:address":"Grasmarkt 105b460",
    "sg:city":"Brussel/bruxelles",
    "sg:orig_category":"Postzegels, munten and trofee\u00ebn",
    "sg:phone":"+32 2 513 07 96",
    "sg:postcode":"1000",
    "sg:province":"Bruxelles-Capitale",
    "wof:name":"Stevens",
    "wof:placetype":"venue"
},
  "geometry": {"coordinates":[4.3543372154,50.8464202881],"type":"Point"}
}