{
  "type": "Feature",
  "properties": {
    "iso:country":"BE",
    "sg:address":"Avenue Du Haut Pays 70",
    "sg:city":"Honnelles (athis)",
    "sg:classifiers":[
        {
            "category":"Real Estate",
            "subcategory":"Real Estate Services",
            "type":"Services"
        }
    ],
    "sg:phone":"+32 65 65 57 57",
    "sg:postcode":"7387",
    "sg:province":"Hainaut",
    "wof:name":"Immobili\u00e8re C S I",
    "wof:placetype":"venue"
},
  "geometry": {"coordinates":[3.7800400257,50.3620796204],"type":"Point"}
}