{
  "type": "Feature",
  "properties": {
    "iso:country":"BE",
    "sg:address":"Eigen Heerdlaan 81",
    "sg:city":"Brugge (sint-andries)",
    "sg:classifiers":[
        {
            "category":"Communications",
            "type":"Services"
        }
    ],
    "sg:phone":"+32 50 39 27 30",
    "sg:postcode":"8200",
    "sg:province":"West-Vlaanderen",
    "sg:tags":[
        "translator"
    ],
    "wof:name":"Szczutowska E",
    "wof:placetype":"venue"
},
  "geometry": {"coordinates":[3.1904699802,51.1992111206],"type":"Point"}
}