{
  "type": "Feature",
  "properties": {
    "iso:country":"BE",
    "sg:address":"Donkerstraat 26",
    "sg:city":"Lennik (gaasbeek)",
    "sg:classifiers":[
        {
            "category":"Bars & Pubs",
            "type":"Food & Drink"
        }
    ],
    "sg:phone":"+32 2 532 47 70",
    "sg:postcode":"1750",
    "sg:province":"Vlaams-Brabant",
    "wof:name":"Vanwaeyenberg A",
    "wof:placetype":"venue"
},
  "geometry": {"coordinates":[4.1896481514,50.7998580933],"type":"Point"}
}