{
  "type": "Feature",
  "properties": {
    "iso:country":"BE",
    "sg:address":"Rue J Wauters 23",
    "sg:city":"Huy",
    "sg:classifiers":[
        {
            "category":"Personal",
            "subcategory":"Beauty Salon",
            "type":"Services"
        }
    ],
    "sg:phone":"+32 85 23 39 43",
    "sg:postcode":"4500",
    "sg:province":"Li\u00e8ge",
    "sg:tags":[
        "de",
        "coiffure"
    ],
    "wof:name":"Coiffure Imagine",
    "wof:placetype":"venue"
},
  "geometry": {"coordinates":[5.2400307655,50.5178337097],"type":"Point"}
}