{
  "type": "Feature",
  "properties": {
    "addr:full":"Rue De La Croy\u00c8re 122 Manage Hainaut 7170",
    "addr:housenumber":"122",
    "addr:postcode":"7170",
    "addr:street":"Rue De La Croye\u0300Re",
    "iso:country":"BE",
    "sg:address":"Rue De La Croy\u00c8re 122",
    "sg:city":"Manage",
    "sg:orig_category":"Alimentation sp\u00e9cialis\u00e9e",
    "sg:phone":"+32 64 55 79 90",
    "sg:postcode":"7170",
    "sg:province":"Hainaut",
    "wof:name":"Mario Gallo",
    "wof:placetype":"venue"
},
  "geometry": {"coordinates":[4.2195072174,50.4914855957],"type":"Point"}
}