{
  "type": "Feature",
  "properties": {
    "iso:country":"BE",
    "sg:address":"Meiboomlaan 25",
    "sg:city":"Tremelo",
    "sg:orig_category":"Artsen and specialisten",
    "sg:phone":"+32 16 53 83 00",
    "sg:postcode":"3120",
    "sg:province":"Vlaams-Brabant",
    "wof:name":"Katty Quadens",
    "wof:placetype":"venue"
},
  "geometry": {"coordinates":[4.7277669907,51.008682251],"type":"Point"}
}