{
  "type": "Feature",
  "properties": {
    "addr:full":"A. Ruzettelaan 97 Blankenberge West-Vlaanderen 8370",
    "addr:housenumber":"97",
    "addr:postcode":"8370",
    "addr:street":"A. Ruzettelaan",
    "iso:country":"BE",
    "sg:address":"A. Ruzettelaan 97",
    "sg:city":"Blankenberge",
    "sg:classifiers":[
        {
            "category":"Real Estate",
            "subcategory":"Real Estate Services",
            "type":"Services"
        }
    ],
    "sg:phone":"+32 50 41 08 00",
    "sg:postcode":"8370",
    "sg:province":"West-Vlaanderen",
    "wof:name":"Parksuite Nv",
    "wof:placetype":"venue"
},
  "geometry": {"coordinates":[3.1409299374,51.3182868958],"type":"Point"}
}