{
  "type": "Feature",
  "properties": {
    "iso:country":"BE",
    "sg:address":"Rue De La Vieille Place 85",
    "sg:city":"Charleroi (marcinelle)",
    "sg:classifiers":[
        {
            "category":"Manufacturing",
            "subcategory":"Signs",
            "type":"Manufacturing & Wholesale Goods"
        }
    ],
    "sg:phone":"+32 71 43 12 83",
    "sg:postcode":"6001",
    "sg:province":"Hainaut",
    "sg:tags":[
        "sign-boards"
    ],
    "wof:name":"Neon 2000",
    "wof:placetype":"venue"
},
  "geometry": {"coordinates":[4.4412269592,50.3974304199],"type":"Point"}
}