{
  "type": "Feature",
  "properties": {
    "iso:country":"BE",
    "sg:address":"Grote Steenweg 144",
    "sg:city":"Linter (neerlinter)",
    "sg:classifiers":[
        {
            "category":"Health Services",
            "subcategory":"Health Practitioner",
            "type":"Services"
        }
    ],
    "sg:phone":"+32 11 78 06 72",
    "sg:postcode":"3350",
    "sg:province":"Vlaams-Brabant",
    "sg:tags":[
        "physiotherapist"
    ],
    "wof:name":"Hendrickx Tony",
    "wof:placetype":"venue"
},
  "geometry": {"coordinates":[5.0346398354,50.841129303],"type":"Point"}
}