{
  "type": "Feature",
  "properties": {
    "addr:full":"Heistraat 247 Sint-niklaas Oost-Vlaanderen 9100",
    "addr:housenumber":"247",
    "addr:postcode":"9100",
    "addr:street":"Heistraat",
    "iso:country":"BE",
    "sg:address":"Heistraat 247",
    "sg:city":"Sint-niklaas",
    "sg:classifiers":[
        {
            "category":"Personal",
            "subcategory":"Barber",
            "type":"Services"
        }
    ],
    "sg:phone":"+32 3 777 28 71",
    "sg:postcode":"9100",
    "sg:province":"Oost-Vlaanderen",
    "sg:tags":[
        "gentleman",
        "salon",
        "-",
        "hairdressing"
    ],
    "wof:name":"Jeangout Coiffure",
    "wof:placetype":"venue"
},
  "geometry": {"coordinates":[4.1390881538,51.1758728027],"type":"Point"}
}