{
  "type": "Feature",
  "properties": {
    "addr:full":"Rue De Spiennes 5 Mons Hainaut 7022",
    "addr:housenumber":"5",
    "addr:postcode":"7022",
    "addr:street":"Rue De Spiennes;Hainaut",
    "iso:country":"BE",
    "sg:address":"Rue De Spiennes 5",
    "sg:city":"Mons",
    "sg:orig_category":"Elektrische installaties voor woningen",
    "sg:phone":"+32 65 33 88 96",
    "sg:postcode":"7022",
    "sg:province":"Hainaut",
    "wof:name":"Berthiaux-denis",
    "wof:placetype":"venue"
},
  "geometry": {"coordinates":[3.9900839329,50.3971977234],"type":"Point"}
}