{
  "type": "Feature",
  "properties": {
    "addr:full":"Rue Grande 52 Beloeil (bas\u00e8cles) Hainaut 7971",
    "addr:housenumber":"52",
    "addr:postcode":"7971",
    "addr:street":"Rue Grande",
    "iso:country":"BE",
    "sg:address":"Rue Grande 52",
    "sg:city":"Beloeil (bas\u00e8cles)",
    "sg:classifiers":[
        {
            "category":"Health Services",
            "subcategory":"Dentist",
            "type":"Services"
        }
    ],
    "sg:phone":"+32 69 57 97 82",
    "sg:postcode":"7971",
    "sg:province":"Hainaut",
    "wof:name":"Caulier Caroline",
    "wof:placetype":"venue"
},
  "geometry": {"coordinates":[3.6502730846,50.5250587463],"type":"Point"}
}