{
  "type": "Feature",
  "properties": {
    "iso:country":"BE",
    "sg:address":"Chauss\u00c9e De La Hulpe 225",
    "sg:city":"Watermael-boitsfort",
    "sg:orig_category":"V\u00e9hicules automobiles. Entretien and r\u00e9parations de voitures",
    "sg:phone":"+32 2 672 03 91",
    "sg:postcode":"1170",
    "sg:province":"Bruxelles-Capitale",
    "wof:name":"Lesage Andr\u00c9",
    "wof:placetype":"venue"
},
  "geometry": {"coordinates":[4.4168338776,50.7941894531],"type":"Point"}
}