{
  "type": "Feature",
  "properties": {
    "iso:country":"BE",
    "sg:address":"Schillebeeksevoetweg 1a",
    "sg:city":"Geraardsbergen",
    "sg:classifiers":[
        {
            "category":"Real Estate",
            "subcategory":"Surveying",
            "type":"Services"
        }
    ],
    "sg:phone":"+32 54 41 13 48",
    "sg:postcode":"9500",
    "sg:province":"Oost-Vlaanderen",
    "sg:tags":[
        "surveyor",
        "land"
    ],
    "wof:name":"Van Der Putten M",
    "wof:placetype":"venue"
},
  "geometry": {"coordinates":[3.8845100403,50.7619400024],"type":"Point"}
}