{
  "type": "Feature",
  "properties": {
    "addr:full":"Avenue De Wandre 4 Vis\u00c9 Li\u00e8ge 4602",
    "addr:housenumber":"4",
    "addr:postcode":"4602",
    "addr:street":"Avenue De Wandre",
    "iso:country":"BE",
    "sg:address":"Avenue De Wandre 4",
    "sg:city":"Vis\u00c9",
    "sg:orig_category":"Woningbouw",
    "sg:phone":"+32 4 362 97 22",
    "sg:postcode":"4602",
    "sg:province":"Li\u00e8ge",
    "wof:name":"Kazanci Kenan",
    "wof:placetype":"venue"
},
  "geometry": {"coordinates":[5.6658601761,50.6814308167],"type":"Point"}
}