{
  "type": "Feature",
  "properties": {
    "iso:country":"BE",
    "sg:address":"Waterloose Steenweg 119",
    "sg:city":"Sint-genesius-rode/rhode-saint-genese",
    "sg:orig_category":"Immobili\u00ebnkantoren",
    "sg:phone":"+32 2 358 51 51",
    "sg:postcode":"1640",
    "sg:province":"Vlaams-Brabant",
    "wof:name":"C\u00d4t\u00c9 France",
    "wof:placetype":"venue"
},
  "geometry": {"coordinates":[4.3960881233,50.7352256775],"type":"Point"}
}