{
  "type": "Feature",
  "properties": {
    "iso:country":"BE",
    "sg:address":"Franklin Rooseveltlaan 222",
    "sg:city":"Gent",
    "sg:classifiers":[
        {
            "category":"Professional",
            "subcategory":"Lawyer & Legal Services",
            "type":"Services"
        }
    ],
    "sg:phone":"+32 9 224 24 94",
    "sg:postcode":"9000",
    "sg:province":"Oost-Vlaanderen",
    "wof:name":"Bekaert D",
    "wof:placetype":"venue"
},
  "geometry": {"coordinates":[3.7309010029,51.045665741],"type":"Point"}
}