{
  "type": "Feature",
  "properties": {
    "iso:country":"BE",
    "sg:address":"Tumkensberg 45",
    "sg:city":"Begijnendijk (betekom)",
    "sg:classifiers":[
        {
            "category":"Wholesale",
            "subcategory":"Vending Machines",
            "type":"Manufacturing & Wholesale Goods"
        }
    ],
    "sg:phone":"+32 16 56 00 01",
    "sg:postcode":"3130",
    "sg:province":"Vlaams-Brabant",
    "sg:tags":[
        "-",
        "electric",
        "motor"
    ],
    "wof:name":"Maxon Motor",
    "wof:placetype":"venue"
},
  "geometry": {"coordinates":[4.7892870903,50.9903869629],"type":"Point"}
}