{
  "type": "Feature",
  "properties": {
    "iso:country":"BE",
    "sg:address":"Leeuwerikweg 45",
    "sg:city":"Keerbergen",
    "sg:orig_category":"Non-Classified Establishments",
    "sg:phone":"+32 16 53 56 71",
    "sg:postcode":"3140",
    "sg:province":"Vlaams-Brabant",
    "wof:name":"Lieckens A",
    "wof:placetype":"venue"
},
  "geometry": {"coordinates":[4.6798877716,50.9985466003],"type":"Point"}
}