{
  "type": "Feature",
  "properties": {
    "addr:full":"Roddam 14 Bornem Antwerpen 2880",
    "addr:housenumber":"14",
    "addr:postcode":"2880",
    "addr:street":"Roddam",
    "iso:country":"BE",
    "sg:address":"Roddam 14",
    "sg:city":"Bornem",
    "sg:orig_category":"Computers and computerapparatuur Diverse informatica-activiteiten Diverse opleidingen and onderwijs ",
    "sg:phone":"+32 3 889 21 04",
    "sg:postcode":"2880",
    "sg:province":"Antwerpen",
    "wof:name":"Vpc Systems",
    "wof:placetype":"venue"
},
  "geometry": {"coordinates":[4.2430729866,51.1019325256],"type":"Point"}
}