{
  "type": "Feature",
  "properties": {
    "iso:country":"BE",
    "sg:address":"Markt 48",
    "sg:city":"Deinze",
    "sg:classifiers":[
        {
            "category":"Shopping",
            "subcategory":"Clothing, Apparel, & Fashions",
            "type":"Retail Goods"
        }
    ],
    "sg:phone":"+32 9 386 15 83",
    "sg:postcode":"9800",
    "sg:province":"Oost-Vlaanderen",
    "sg:tags":[
        "clothing",
        "-",
        "gentleman"
    ],
    "wof:name":"Huis De Ruyck",
    "wof:placetype":"venue"
},
  "geometry": {"coordinates":[3.5266458988,50.9838981628],"type":"Point"}
}