{
  "type": "Feature",
  "properties": {
    "addr:full":"Place Jean Jaur\u00c8s 21 Charleroi Hainaut 6040",
    "addr:housenumber":"21",
    "addr:postcode":"6040",
    "addr:street":"Place Jean Jaure\u0300S;Hainaut",
    "iso:country":"BE",
    "sg:address":"Place Jean Jaur\u00c8s 21",
    "sg:city":"Charleroi",
    "sg:classifiers":[
        {
            "category":"Professional",
            "subcategory":"Art Services",
            "type":"Services"
        }
    ],
    "sg:phone":"+32 71 34 29 43",
    "sg:postcode":"6040",
    "sg:province":"Hainaut",
    "sg:tags":[
        "designer",
        "cr\u00e9ateurs"
    ],
    "wof:name":"Val\u00c9rie Janssens",
    "wof:placetype":"venue"
},
  "geometry": {"coordinates":[4.4393367767,50.443271637],"type":"Point"}
}