{
  "type": "Feature",
  "properties": {
    "addr:full":"Rue De La Clef 51 Fleron Li\u00e8ge 4621",
    "addr:housenumber":"51",
    "addr:postcode":"4621",
    "addr:street":"Rue De La Clef",
    "iso:country":"BE",
    "sg:address":"Rue De La Clef 51",
    "sg:city":"Fleron",
    "sg:orig_category":"Bloemen and planten Boomkwekerijen Tuinen",
    "sg:phone":"+32 4 358 18 55",
    "sg:postcode":"4621",
    "sg:province":"Li\u00e8ge",
    "wof:name":"Exotic Plantes 2000",
    "wof:placetype":"venue"
},
  "geometry": {"coordinates":[5.69480896,50.6185646057],"type":"Point"}
}