{
  "type": "Feature",
  "properties": {
    "iso:country":"BE",
    "sg:address":"Rue De Th\u00c9bais 34",
    "sg:city":"Villers-la-ville",
    "sg:orig_category":"Brood, gebak and snoepgoed",
    "sg:phone":"+32 71 87 87 61",
    "sg:postcode":"1495",
    "sg:province":"Brabant Wallon",
    "wof:name":"Rene Flament",
    "wof:placetype":"venue"
},
  "geometry": {"coordinates":[4.5674052238,50.5785484314],"type":"Point"}
}