{
  "type": "Feature",
  "properties": {
    "addr:full":"Rue De Frameries 541 Mons (cuesmes) Hainaut 7033",
    "addr:housenumber":"541",
    "addr:postcode":"7033",
    "addr:street":"Rue De Frameries",
    "iso:country":"BE",
    "sg:address":"Rue De Frameries 541",
    "sg:city":"Mons (cuesmes)",
    "sg:classifiers":[
        {
            "category":"Food & Beverages",
            "subcategory":"Groceries & Convenience Stores",
            "type":"Retail Goods"
        }
    ],
    "sg:phone":"+32 65 31 18 81",
    "sg:postcode":"7033",
    "sg:province":"Hainaut",
    "sg:tags":[
        "baker",
        "-",
        "ingredient"
    ],
    "wof:name":"Paniblond",
    "wof:placetype":"venue"
},
  "geometry": {"coordinates":[3.9253261089,50.4366378784],"type":"Point"}
}