{
  "type": "Feature",
  "properties": {
    "addr:full":"Ten Stroom 6 Gavere Oost-Vlaanderen 9890",
    "addr:housenumber":"6",
    "addr:postcode":"9890",
    "addr:street":"Ten Stroom",
    "iso:country":"BE",
    "sg:address":"Ten Stroom 6",
    "sg:city":"Gavere",
    "sg:orig_category":"Sportclubs",
    "sg:phone":"+32 9 384 61 54",
    "sg:postcode":"9890",
    "sg:province":"Oost-Vlaanderen",
    "wof:name":"W.c. De Scheldevrienden",
    "wof:placetype":"venue"
},
  "geometry": {"coordinates":[3.6588599682,50.9283752441],"type":"Point"}
}