{
  "type": "Feature",
  "properties": {
    "iso:country":"BE",
    "sg:address":"Avenue Du Chalon 1bb",
    "sg:city":"Chimay",
    "sg:orig_category":"Sportclubs Sportterreinen and installaties behalve sportcentra",
    "sg:phone":"+32 60 21 12 13",
    "sg:postcode":"6460",
    "sg:province":"Hainaut",
    "wof:name":"Piscine Interc. Sud Hain.",
    "wof:placetype":"venue"
},
  "geometry": {"coordinates":[4.3223819733,50.0470657349],"type":"Point"}
}