{
  "type": "Feature",
  "properties": {
    "iso:country":"BE",
    "sg:address":"Bostsestraat 15",
    "sg:city":"Tienen",
    "sg:classifiers":[
        {
            "category":"Bars & Pubs",
            "type":"Food & Drink"
        }
    ],
    "sg:phone":"+32 16 82 33 04",
    "sg:postcode":"3300",
    "sg:province":"Vlaams-Brabant",
    "wof:name":"Artist",
    "wof:placetype":"venue"
},
  "geometry": {"coordinates":[4.9398789406,50.8035621643],"type":"Point"}
}