{
  "type": "Feature",
  "properties": {
    "addr:full":"Draaiboom 129 Oud-turnhout Antwerpen 2360",
    "addr:housenumber":"129",
    "addr:postcode":"2360",
    "addr:street":"Draaiboom",
    "iso:country":"BE",
    "sg:address":"Draaiboom 129",
    "sg:city":"Oud-turnhout",
    "sg:orig_category":"Eleveurs de bovins",
    "sg:phone":"+32 14 45 17 12",
    "sg:postcode":"2360",
    "sg:province":"Antwerpen",
    "wof:name":"Franciscus Van Herck",
    "wof:placetype":"venue"
},
  "geometry": {"coordinates":[4.9984359741,51.3211593628],"type":"Point"}
}