{
  "type": "Feature",
  "properties": {
    "iso:country":"BE",
    "sg:address":"Nijverheidskaai 15",
    "sg:city":"Eeklo",
    "sg:classifiers":[
        {
            "category":"Professional",
            "subcategory":"Management & Consulting",
            "type":"Services"
        }
    ],
    "sg:phone":"+32 9 378 59 65",
    "sg:postcode":"9900",
    "sg:province":"Oost-Vlaanderen",
    "sg:tags":[
        "consultant"
    ],
    "wof:name":"Matteo Nv",
    "wof:placetype":"venue"
},
  "geometry": {"coordinates":[3.5528318882,51.1816368103],"type":"Point"}
}