{
  "type": "Feature",
  "properties": {
    "addr:full":"Grote Markt 34 Vilvoorde Vlaams-Brabant 1800",
    "addr:housenumber":"34",
    "addr:postcode":"1800",
    "addr:street":"Grote Markt",
    "iso:country":"BE",
    "sg:address":"Grote Markt 34",
    "sg:city":"Vilvoorde",
    "sg:classifiers":[
        {
            "category":"Insurance",
            "subcategory":"Life Insurance",
            "type":"Services"
        }
    ],
    "sg:phone":"+32 2 255 09 11",
    "sg:postcode":"1800",
    "sg:province":"Vlaams-Brabant",
    "sg:tags":[
        "assurance"
    ],
    "wof:name":"P&v",
    "wof:placetype":"venue"
},
  "geometry": {"coordinates":[4.4223899841,50.9286499023],"type":"Point"}
}