{
  "type": "Feature",
  "properties": {
    "addr:full":"Rue De Nivelles 21 Manage Hainaut 7170",
    "addr:housenumber":"21",
    "addr:postcode":"7170",
    "addr:street":"Rue De Nivelles",
    "iso:country":"BE",
    "sg:address":"Rue De Nivelles 21",
    "sg:city":"Manage",
    "sg:orig_category":"Installation \u00e9lectrique r\u00e9sidentielle",
    "sg:phone":"+32 64 55 83 75",
    "sg:postcode":"7170",
    "sg:province":"Hainaut",
    "wof:name":"Mario Spitaleri",
    "wof:placetype":"venue"
},
  "geometry": {"coordinates":[4.2412490845,50.4783744812],"type":"Point"}
}