{
  "type": "Feature",
  "properties": {
    "iso:country":"BE",
    "sg:address":"Rue Du H\u00e9raut 20",
    "sg:city":"Herbeumont (straimont)",
    "sg:classifiers":[
        {
            "category":"Farming",
            "subcategory":"Livestock Farm",
            "type":"Manufacturing & Wholesale Goods"
        }
    ],
    "sg:phone":"+32 61 27 74 00",
    "sg:postcode":"6887",
    "sg:province":"Luxembourg",
    "sg:tags":[
        "buyer"
    ],
    "wof:name":"Mernier A",
    "wof:placetype":"venue"
},
  "geometry": {"coordinates":[5.3811798096,49.7957305908],"type":"Point"}
}