{
  "type": "Feature",
  "properties": {
    "addr:full":"Place De La Gare 16 Mons Hainaut 7012",
    "addr:housenumber":"16",
    "addr:postcode":"7012",
    "addr:street":"Place De La Gare;Hainaut",
    "iso:country":"BE",
    "sg:address":"Place De La Gare 16",
    "sg:city":"Mons",
    "sg:classifiers":[
        {
            "category":"Cafe",
            "type":"Food & Drink"
        }
    ],
    "sg:phone":"+32 65 88 58 30",
    "sg:postcode":"7012",
    "sg:province":"Hainaut",
    "sg:tags":[
        "caf\u00e9s"
    ],
    "wof:name":"Sardes De Mons Su Nureghe",
    "wof:placetype":"venue"
},
  "geometry": {"coordinates":[3.8894600868,50.4481964111],"type":"Point"}
}