{
  "type": "Feature",
  "properties": {
    "addr:full":"Energielaan 22-8 Kapellen Antwerpen 2950",
    "addr:housenumber":"22-8",
    "addr:postcode":"2950",
    "addr:street":"Energielaan",
    "iso:country":"BE",
    "sg:address":"Energielaan 22-8",
    "sg:city":"Kapellen",
    "sg:orig_category":"Non-Classified Establishments",
    "sg:phone":"+32 3 665 01 59",
    "sg:postcode":"2950",
    "sg:province":"Antwerpen",
    "wof:name":"Alpha Industries",
    "wof:placetype":"venue"
},
  "geometry": {"coordinates":[4.5024299622,51.3551940918],"type":"Point"}
}