{
  "type": "Feature",
  "properties": {
    "addr:full":"Rue Hubert L\u00e9onard 30 Beyne-heusay (bellaire) Li\u00e8ge 4610",
    "addr:housenumber":"30",
    "addr:postcode":"4610",
    "addr:street":"Rue Hubert Le\u0301Onard",
    "iso:country":"BE",
    "sg:address":"Rue Hubert L\u00e9onard 30",
    "sg:city":"Beyne-heusay (bellaire)",
    "sg:classifiers":[
        {
            "category":"Building & Trades",
            "subcategory":"Electrical",
            "type":"Services"
        }
    ],
    "sg:phone":"+32 4 362 20 90",
    "sg:postcode":"4610",
    "sg:province":"Li\u00e8ge",
    "sg:tags":[
        "electric",
        "-",
        "housewiring",
        "contractor"
    ],
    "wof:name":"Charlier Alain",
    "wof:placetype":"venue"
},
  "geometry": {"coordinates":[5.6680798531,50.6448516846],"type":"Point"}
}