{
  "type": "Feature",
  "properties": {
    "iso:country":"BE",
    "sg:address":"Rue Abb\u00e9 P\u00e9ters 38",
    "sg:city":"Malmedy",
    "sg:classifiers":[
        {
            "category":"Health Services",
            "subcategory":"Dentist",
            "type":"Services"
        }
    ],
    "sg:phone":"+32 80 54 96 26",
    "sg:postcode":"4960",
    "sg:province":"Li\u00e8ge",
    "wof:name":"Grosjean Olivier",
    "wof:placetype":"venue"
},
  "geometry": {"coordinates":[6.0313792229,50.4234809875],"type":"Point"}
}