{
  "type": "Feature",
  "properties": {
    "addr:full":"Rue De La Bouteillerie 47 Estaimpuis Hainaut 7730",
    "addr:housenumber":"47",
    "addr:postcode":"7730",
    "addr:street":"Rue De La Bouteillerie;Hainaut",
    "iso:country":"BE",
    "sg:address":"Rue De La Bouteillerie 47",
    "sg:city":"Estaimpuis",
    "sg:classifiers":[
        {
            "category":"Professional",
            "subcategory":"Accounting & Tax Preparation",
            "type":"Services"
        }
    ],
    "sg:phone":"+32 56 48 98 42",
    "sg:postcode":"7730",
    "sg:province":"Hainaut",
    "sg:tags":[
        "accountant"
    ],
    "wof:name":"C.p.e.c. Sprl",
    "wof:placetype":"venue"
},
  "geometry": {"coordinates":[3.2621290684,50.7110137939],"type":"Point"}
}