{
  "type": "Feature",
  "properties": {
    "addr:full":"Lange Herentalsestraat 2 Antwerpen Antwerpen 2018",
    "addr:housenumber":"2",
    "addr:postcode":"2018",
    "addr:street":"Lange Herentalsestraat",
    "iso:country":"BE",
    "sg:address":"Lange Herentalsestraat 2",
    "sg:city":"Antwerpen",
    "sg:classifiers":[
        {
            "category":"Cafe",
            "type":"Food & Drink"
        }
    ],
    "sg:phone":"+32 3 233 30 38",
    "sg:postcode":"2018",
    "sg:province":"Antwerpen",
    "sg:tags":[
        "caf\u00e9s"
    ],
    "wof:name":"Caf\u00c9 \u00b4t Empierke",
    "wof:placetype":"venue"
},
  "geometry": {"coordinates":[4.417142868,51.2162246704],"type":"Point"}
}