{
  "type": "Feature",
  "properties": {
    "addr:full":"Porte \u00e0 Camp 48 Beloeil (bas\u00e8cles) Hainaut 7971",
    "addr:housenumber":"48",
    "addr:postcode":"7971",
    "addr:street":"Beloeil;Hainaut",
    "iso:country":"BE",
    "sg:address":"Porte \u00e0 Camp 48",
    "sg:city":"Beloeil (bas\u00e8cles)",
    "sg:classifiers":[
        {
            "category":"Health Services",
            "subcategory":"Doctor",
            "type":"Services"
        }
    ],
    "sg:phone":"+32 69 58 03 03",
    "sg:postcode":"7971",
    "sg:province":"Hainaut",
    "sg:tags":[
        "medicinephysicians",
        "surgeon"
    ],
    "wof:name":"Debouvrie S\u00e9bastien",
    "wof:placetype":"venue"
},
  "geometry": {"coordinates":[3.6475970745,50.5229644775],"type":"Point"}
}