{
  "type": "Feature",
  "properties": {
    "addr:full":"Parvis Sainte-alix 17 Sint-pieters-woluwe/woluwe-sai Bruxelles-Capitale 1150",
    "addr:housenumber":"17",
    "addr:postcode":"1150",
    "addr:street":"Parvis Sainte-Alix",
    "iso:country":"BE",
    "sg:address":"Parvis Sainte-alix 17",
    "sg:city":"Sint-pieters-woluwe/woluwe-sai",
    "sg:orig_category":"Banques and organismes de cr\u00e9dit",
    "sg:phone":"+32 2 771 77 49",
    "sg:postcode":"1150",
    "sg:province":"Bruxelles-Capitale",
    "wof:name":"Fortis",
    "wof:placetype":"venue"
},
  "geometry": {"coordinates":[4.4618048668,50.8275146484],"type":"Point"}
}