{
  "type": "Feature",
  "properties": {
    "addr:full":"Rue De Gosselies 19 Charleroi (jumet) Hainaut 6040",
    "addr:housenumber":"19",
    "addr:postcode":"6040",
    "addr:street":"Rue De Gosselies",
    "iso:country":"BE",
    "sg:address":"Rue De Gosselies 19",
    "sg:city":"Charleroi (jumet)",
    "sg:classifiers":[
        {
            "category":"Social Services",
            "type":"Services"
        }
    ],
    "sg:phone":"+32 475 27 46 48",
    "sg:postcode":"6040",
    "sg:province":"Hainaut",
    "wof:name":"Gema",
    "wof:placetype":"venue"
},
  "geometry": {"coordinates":[4.4260010719,50.4519309998],"type":"Point"}
}