{
  "type": "Feature",
  "properties": {
    "iso:country":"BE",
    "sg:address":"Rue De La Citadelle 153",
    "sg:city":"Mouscron (herseaux)",
    "sg:classifiers":[
        {
            "category":"Education",
            "subcategory":"Dance Studio",
            "type":"Public Place"
        }
    ],
    "sg:phone":"+32 56 34 12 68",
    "sg:postcode":"7712",
    "sg:province":"Hainaut",
    "sg:tags":[
        "school",
        "dancing"
    ],
    "wof:name":"Attitude Show",
    "wof:placetype":"venue"
},
  "geometry": {"coordinates":[3.2435810566,50.7137184143],"type":"Point"}
}