{
  "type": "Feature",
  "properties": {
    "addr:full":"Leuvensesteenweg 517 Kortenberg Vlaams-Brabant 3070",
    "addr:housenumber":"517",
    "addr:postcode":"3070",
    "addr:street":"Leuvensesteenweg;Vlaams-Brabant",
    "iso:country":"BE",
    "sg:address":"Leuvensesteenweg 517",
    "sg:city":"Kortenberg",
    "sg:orig_category":"Banques and organismes de cr\u00e9dit",
    "sg:phone":"+32 2 758 07 86",
    "sg:postcode":"3070",
    "sg:province":"Vlaams-Brabant",
    "wof:name":"Bacob",
    "wof:placetype":"venue"
},
  "geometry": {"coordinates":[4.5535349846,50.8899536133],"type":"Point"}
}