{
  "type": "Feature",
  "properties": {
    "addr:full":"Zepstraat 67 Mechelen (hombeek) Antwerpen 2811",
    "addr:housenumber":"67",
    "addr:postcode":"2811",
    "addr:street":"Zepstraat",
    "iso:country":"BE",
    "sg:address":"Zepstraat 67",
    "sg:city":"Mechelen (hombeek)",
    "sg:classifiers":[
        {
            "category":"Manufacturing",
            "subcategory":"Metals",
            "type":"Manufacturing & Wholesale Goods"
        }
    ],
    "sg:phone":"+32 15 41 07 31",
    "sg:postcode":"2811",
    "sg:province":"Antwerpen",
    "sg:tags":[
        "turning"
    ],
    "wof:name":"Siebens L",
    "wof:placetype":"venue"
},
  "geometry": {"coordinates":[4.4240489006,51.0090370178],"type":"Point"}
}