{
  "type": "Feature",
  "properties": {
    "addr:full":"Grote Bosstraat 123 Brussel/bruxelles Bruxelles-Capitale 1030",
    "addr:housenumber":"123",
    "addr:postcode":"1030",
    "addr:street":"Grote Bosstraat;/",
    "iso:country":"BE",
    "sg:address":"Grote Bosstraat 123",
    "sg:city":"Brussel/bruxelles",
    "sg:orig_category":"Voedingsspeciaalzaken",
    "sg:phone":"+32 2 733 16 97",
    "sg:postcode":"1030",
    "sg:province":"Bruxelles-Capitale",
    "wof:name":"Source De Vie",
    "wof:placetype":"venue"
},
  "geometry": {"coordinates":[4.3876309395,50.8542060852],"type":"Point"}
}