{
  "type": "Feature",
  "properties": {
    "addr:full":"Rue Des Brasseries 29 Wavre Brabant Wallon 1300",
    "addr:housenumber":"29;1300",
    "addr:street":"Rue Des Brasseries",
    "iso:country":"BE",
    "sg:address":"Rue Des Brasseries 29",
    "sg:city":"Wavre",
    "sg:classifiers":[
        {
            "category":"Personal",
            "subcategory":"Beauty Salon",
            "type":"Services"
        }
    ],
    "sg:phone":"+32 10 22 64 54",
    "sg:postcode":"1300",
    "sg:province":"Brabant Wallon",
    "sg:tags":[
        "de",
        "coiffure"
    ],
    "wof:name":"Jean-claude Biguine",
    "wof:placetype":"venue"
},
  "geometry": {"coordinates":[4.6108751297,50.7151832581],"type":"Point"}
}