{
  "type": "Feature",
  "properties": {
    "addr:full":"Avenue Des Acacias 50 Neupre Li\u00e8ge 4120",
    "addr:housenumber":"50",
    "addr:postcode":"4120",
    "addr:street":"Avenue Des Acacias",
    "iso:country":"BE",
    "sg:address":"Avenue Des Acacias 50",
    "sg:city":"Neupre",
    "sg:classifiers":[
        {
            "category":"Insurance",
            "subcategory":"Insurance Agent",
            "type":"Services"
        }
    ],
    "sg:phone":"+32 4 371 29 44",
    "sg:postcode":"4120",
    "sg:province":"Li\u00e8ge",
    "sg:tags":[
        "verzekeringsmakelaars",
        "expert"
    ],
    "wof:name":"D. Silvano",
    "wof:placetype":"venue"
},
  "geometry": {"coordinates":[5.4987039566,50.541557312],"type":"Point"}
}