{
  "type": "Feature",
  "properties": {
    "iso:country":"BE",
    "sg:address":"Boulevard Des Anglais 2",
    "sg:city":"Spa",
    "sg:orig_category":"V\u00e9hicules automobiles. Entretien and r\u00e9parations de voitures",
    "sg:phone":"+32 87 77 22 63",
    "sg:postcode":"4900",
    "sg:province":"Li\u00e8ge",
    "wof:name":"Garage Jean-marie Herman",
    "wof:placetype":"venue"
},
  "geometry": {"coordinates":[5.8688678741,50.4921379089],"type":"Point"}
}