{
  "type": "Feature",
  "properties": {
    "addr:full":"Lombaardstraat 6 Hasselt Limburg 3500",
    "addr:housenumber":"6",
    "addr:postcode":"3500",
    "addr:street":"Lombaardstraat",
    "iso:country":"BE",
    "sg:address":"Lombaardstraat 6",
    "sg:city":"Hasselt",
    "sg:classifiers":[
        {
            "category":"Cafe",
            "type":"Food & Drink"
        }
    ],
    "sg:phone":"+32 11 22 91 97",
    "sg:postcode":"3500",
    "sg:province":"Limburg",
    "sg:tags":[
        "caf\u00e9s"
    ],
    "wof:name":"Caf\u00c9 Hooghuis",
    "wof:placetype":"venue"
},
  "geometry": {"coordinates":[5.3368620872,50.9306335449],"type":"Point"}
}