{
  "type": "Feature",
  "properties": {
    "addr:full":"Place Des Combattants 24 Walcourt Namur 5650",
    "addr:housenumber":"24",
    "addr:postcode":"5650",
    "addr:street":"Place Des Combattants",
    "iso:country":"BE",
    "sg:address":"Place Des Combattants 24",
    "sg:city":"Walcourt",
    "sg:orig_category":"Postkantoren Verzekeringsmakelaars and experts",
    "sg:phone":"+32 71 61 17 35",
    "sg:postcode":"5650",
    "sg:province":"Namur",
    "wof:name":"La Poste",
    "wof:placetype":"venue"
},
  "geometry": {"coordinates":[4.4311299324,50.2532691956],"type":"Point"}
}