{
  "type": "Feature",
  "properties": {
    "addr:full":"Waterpolder 4 Maldegem Oost-Vlaanderen 9992",
    "addr:housenumber":"4",
    "addr:postcode":"9992",
    "addr:street":"Waterpolder",
    "iso:country":"BE",
    "sg:address":"Waterpolder 4",
    "sg:city":"Maldegem",
    "sg:orig_category":"V\u00eatements pour Hommes",
    "sg:phone":"+32 50 71 83 65",
    "sg:postcode":"9992",
    "sg:province":"Oost-Vlaanderen",
    "wof:name":"Universal Top Collections",
    "wof:placetype":"venue"
},
  "geometry": {"coordinates":[3.4132359028,51.2522354126],"type":"Point"}
}