{
  "type": "Feature",
  "properties": {
    "addr:full":"Avenue De La R\u00e9sistance 98 Soumagne Li\u00e8ge 4630",
    "addr:housenumber":"98",
    "addr:postcode":"4630",
    "addr:street":"Avenue De La Re\u0301Sistance",
    "iso:country":"BE",
    "sg:address":"Avenue De La R\u00e9sistance 98",
    "sg:city":"Soumagne",
    "sg:classifiers":[
        {
            "category":"Building & Trades",
            "subcategory":"Locksmith",
            "type":"Services"
        }
    ],
    "sg:phone":"+32 4 377 18 21",
    "sg:postcode":"4630",
    "sg:province":"Li\u00e8ge",
    "sg:tags":[
        "material",
        "road"
    ],
    "wof:name":"B\u00e9ton Mosan Sprl",
    "wof:placetype":"venue"
},
  "geometry": {"coordinates":[5.7287921906,50.6292724609],"type":"Point"}
}