{
  "type": "Feature",
  "properties": {
    "addr:full":"Ambroossteenweg 24 Zemst (hofstade) Vlaams-Brabant 1981",
    "addr:housenumber":"24",
    "addr:postcode":"1981",
    "addr:street":"Ambroossteenweg",
    "iso:country":"BE",
    "sg:address":"Ambroossteenweg 24",
    "sg:city":"Zemst (hofstade)",
    "sg:classifiers":[
        {
            "category":"Communications",
            "subcategory":"Film & Video Production",
            "type":"Services"
        }
    ],
    "sg:phone":"+32 15 61 01 80",
    "sg:postcode":"1981",
    "sg:province":"Vlaams-Brabant",
    "sg:tags":[
        "sound",
        "recording",
        "studio"
    ],
    "wof:name":"Owen G",
    "wof:placetype":"venue"
},
  "geometry": {"coordinates":[4.495721817,50.9922561646],"type":"Point"}
}