{
  "type": "Feature",
  "properties": {
    "addr:full":"Beselarestraat 294 Zonnebeke West-Vlaanderen 8980",
    "addr:housenumber":"294",
    "addr:postcode":"8980",
    "addr:street":"Beselarestraat",
    "iso:country":"BE",
    "sg:address":"Beselarestraat 294",
    "sg:city":"Zonnebeke",
    "sg:orig_category":"Kapsalons",
    "sg:phone":"+32 57 46 66 57",
    "sg:postcode":"8980",
    "sg:province":"West-Vlaanderen",
    "wof:name":"Roland Taillieu",
    "wof:placetype":"venue"
},
  "geometry": {"coordinates":[3.0099699497,50.8603096008],"type":"Point"}
}