{
  "type": "Feature",
  "properties": {
    "iso:country":"BE",
    "sg:address":"Rue Du Temple 1",
    "sg:city":"La Louvi\u00c8re",
    "sg:orig_category":"Enseignement secondaire g\u00e9n\u00e9ral",
    "sg:phone":"+32 64 22 26 67",
    "sg:postcode":"7100",
    "sg:province":"Hainaut",
    "wof:name":"Ath\u00c9n\u00c9e Royal",
    "wof:placetype":"venue"
},
  "geometry": {"coordinates":[4.1888260841,50.476776123],"type":"Point"}
}