{
  "type": "Feature",
  "properties": {
    "iso:country":"BE",
    "sg:address":"Kapellei 5",
    "sg:city":"Brasschaat",
    "sg:orig_category":"Installation \u00e9lectrique r\u00e9sidentielle",
    "sg:phone":"+32 3 633 27 21",
    "sg:postcode":"2930",
    "sg:province":"Antwerpen",
    "wof:name":"Therelec",
    "wof:placetype":"venue"
},
  "geometry": {"coordinates":[4.5197482109,51.324546814],"type":"Point"}
}