{
  "type": "Feature",
  "properties": {
    "addr:full":"Edinburgstraat 18 Elsene/ixelles Bruxelles-Capitale 1050",
    "addr:housenumber":"18",
    "addr:postcode":"1050",
    "addr:street":"Edinburgstraat",
    "iso:country":"BE",
    "sg:address":"Edinburgstraat 18",
    "sg:city":"Elsene/ixelles",
    "sg:orig_category":"Beheer onroerend goed",
    "sg:phone":"+32 2 518 92 11",
    "sg:postcode":"1050",
    "sg:province":"Bruxelles-Capitale",
    "wof:name":"Gesinfor",
    "wof:placetype":"venue"
},
  "geometry": {"coordinates":[4.364221096,50.837726593],"type":"Point"}
}