{
  "type": "Feature",
  "properties": {
    "iso:country":"BE",
    "sg:address":"Munthofstraat 66",
    "sg:city":"Sint-gillis/saint-gilles",
    "sg:classifiers":[
        {
            "category":"Insurance",
            "subcategory":"Insurance Agent",
            "type":"Services"
        }
    ],
    "sg:phone":"+32 2 537 96 98",
    "sg:postcode":"1060",
    "sg:province":"Bruxelles-Capitale",
    "sg:tags":[
        "verzekeringsmakelaars",
        "expert"
    ],
    "wof:name":"Belgische Leeuw/lion Belge",
    "wof:placetype":"venue"
},
  "geometry": {"coordinates":[4.3486289978,50.8309822083],"type":"Point"}
}