{
  "type": "Feature",
  "properties": {
    "iso:country":"BE",
    "sg:address":"Barri\u00e8re Hinck 8",
    "sg:city":"Sainte-ode (amberloup)",
    "sg:classifiers":[
        {
            "category":"Wholesale",
            "subcategory":"Scrap",
            "type":"Manufacturing & Wholesale Goods"
        }
    ],
    "sg:phone":"+32 61 68 85 26",
    "sg:postcode":"6680",
    "sg:province":"Luxembourg",
    "sg:tags":[
        "dustbin",
        "dustbagholders"
    ],
    "wof:name":"L.e.l.-les Entrepots Luxembour Sa",
    "wof:placetype":"venue"
},
  "geometry": {"coordinates":[5.5304489136,50.0108299255],"type":"Point"}
}