{
  "type": "Feature",
  "properties": {
    "iso:country":"BE",
    "sg:address":"Blvd D'avroy 4",
    "sg:city":"Li\u00e8ge",
    "sg:classifiers":[
        {
            "category":"Banks & Credit Unions",
            "subcategory":"Bank",
            "type":"Services"
        }
    ],
    "sg:phone":"+32 41237960",
    "sg:postcode":"4000",
    "sg:province":"Li\u00e8ge",
    "wof:name":"Banque De Schaetzen Scs",
    "wof:placetype":"venue"
},
  "geometry": {"coordinates":[5.570494175,50.6409683228],"type":"Point"}
}