{
  "type": "Feature",
  "properties": {
    "addr:full":"Rekegemstraat 32 Zwalm (munkzwalm) Oost-Vlaanderen 9630",
    "addr:housenumber":"32",
    "addr:postcode":"9630",
    "addr:street":"Rekegemstraat;Munkzwalm Oost-Vlaanderen",
    "iso:country":"BE",
    "sg:address":"Rekegemstraat 32",
    "sg:city":"Zwalm (munkzwalm)",
    "sg:classifiers":[
        {
            "category":"Social Services",
            "subcategory":"Job Training",
            "type":"Services"
        }
    ],
    "sg:phone":"+32 55 23 22 66",
    "sg:postcode":"9630",
    "sg:province":"Oost-Vlaanderen",
    "sg:tags":[
        "personnel"
    ],
    "wof:name":"G.e.a. Centrum Voor Psycho Dynamica En Communicatie",
    "wof:placetype":"venue"
},
  "geometry": {"coordinates":[3.7435479164,50.8806037903],"type":"Point"}
}