{
  "type": "Feature",
  "properties": {
    "addr:full":"Industrieterrein Jagersborg 1314 Maaseik Limburg 3680",
    "addr:housenumber":"1314",
    "addr:postcode":"3680",
    "addr:street":"Industrieterrein Jagersborg",
    "iso:country":"BE",
    "sg:address":"Industrieterrein Jagersborg 1314",
    "sg:city":"Maaseik",
    "sg:classifiers":[
        {
            "category":"Home & Garden",
            "subcategory":"Garden Supply",
            "type":"Retail Goods"
        }
    ],
    "sg:postcode":"3680",
    "sg:province":"Limburg",
    "sg:tags":[
        "machine",
        "agricultural",
        "-"
    ],
    "wof:name":"Brouns Jozef",
    "wof:placetype":"venue"
},
  "geometry": {"coordinates":[5.7457351685,51.1024703979],"type":"Point"}
}