{
  "type": "Feature",
  "properties": {
    "iso:country":"BE",
    "sg:address":"Turnhoutseweg 69",
    "sg:city":"Beerse",
    "sg:classifiers":[
        {
            "category":"Autos & Motor Vehicles",
            "subcategory":"Auto Supplies",
            "type":"Retail Goods"
        }
    ],
    "sg:phone":"+32 14 61 52 52",
    "sg:postcode":"2340",
    "sg:province":"Antwerpen",
    "sg:tags":[
        "automobile",
        "-",
        "equipment",
        "air conditioning"
    ],
    "wof:name":"U.s.t. Auto-service Nv",
    "wof:placetype":"venue"
},
  "geometry": {"coordinates":[4.8660769463,51.3118553162],"type":"Point"}
}