{
  "type": "Feature",
  "properties": {
    "iso:country":"BE",
    "sg:address":"Rue Joseph Calozet 18",
    "sg:city":"Saint-hubert (awenne)",
    "sg:classifiers":[
        {
            "category":"Health Services",
            "subcategory":"Doctor",
            "type":"Services"
        }
    ],
    "sg:phone":"+32 84 36 73 16",
    "sg:postcode":"6870",
    "sg:province":"Luxembourg",
    "sg:tags":[
        "medicinephysicians",
        "surgeon"
    ],
    "wof:name":"Jadoul Bernard",
    "wof:placetype":"venue"
},
  "geometry": {"coordinates":[5.3086361885,50.0749053955],"type":"Point"}
}