{
  "type": "Feature",
  "properties": {
    "addr:full":"Erberstraat 31 Sint-truiden Limburg 3800",
    "addr:housenumber":"31",
    "addr:postcode":"3800",
    "addr:street":"Erberstraat",
    "iso:country":"BE",
    "sg:address":"Erberstraat 31",
    "sg:city":"Sint-truiden",
    "sg:orig_category":"Groenten and fruit Gh",
    "sg:phone":"+32 11 68 24 61",
    "sg:postcode":"3800",
    "sg:province":"Limburg",
    "wof:name":"Tilkens",
    "wof:placetype":"venue"
},
  "geometry": {"coordinates":[5.1863641739,50.8153343201],"type":"Point"}
}