{
  "type": "Feature",
  "properties": {
    "addr:full":"Clos Du Parnasse 2ba Elsene/ixelles Bruxelles-Capitale 1050",
    "addr:housenumber":"2ba",
    "addr:postcode":"1050",
    "addr:street":"Clos Du Parnasse",
    "iso:country":"BE",
    "sg:address":"Clos Du Parnasse 2ba",
    "sg:city":"Elsene/ixelles",
    "sg:orig_category":"Secr\u00e9tariats. Composition and photogravure",
    "sg:phone":"+32 2 513 60 34",
    "sg:postcode":"1050",
    "sg:province":"Bruxelles-Capitale",
    "wof:name":"Ro-scan",
    "wof:placetype":"venue"
},
  "geometry": {"coordinates":[4.3698368073,50.8378067017],"type":"Point"}
}