{
  "type": "Feature",
  "properties": {
    "iso:country":"BE",
    "sg:address":"Rue De La Croisette 39",
    "sg:city":"Hannut",
    "sg:classifiers":[
        {
            "category":"Insurance",
            "subcategory":"Life Insurance",
            "type":"Services"
        }
    ],
    "sg:phone":"+32 19 51 28 72",
    "sg:postcode":"4280",
    "sg:province":"Li\u00e8ge",
    "sg:tags":[
        "assurance"
    ],
    "wof:name":"Michel Moes Assurances",
    "wof:placetype":"venue"
},
  "geometry": {"coordinates":[5.067056179,50.6623497009],"type":"Point"}
}