{
  "type": "Feature",
  "properties": {
    "iso:country":"BE",
    "sg:address":"Lodewijk Dosfelstraat 65",
    "sg:city":"Dendermonde",
    "sg:orig_category":"Avocats and conseillers juridiques",
    "sg:phone":"+32 52 21 78 14",
    "sg:postcode":"9200",
    "sg:province":"Oost-Vlaanderen",
    "wof:name":"Marc Verwilghen",
    "wof:placetype":"venue"
},
  "geometry": {"coordinates":[4.0933361053,51.0334434509],"type":"Point"}
}