{
  "type": "Feature",
  "properties": {
    "iso:country":"BE",
    "sg:address":"Rue De Deminche 122",
    "sg:city":"Floreffe",
    "sg:orig_category":"Charpentes and couvertures",
    "sg:phone":"+32 81 44 13 55",
    "sg:postcode":"5150",
    "sg:province":"Namur",
    "wof:name":"Joel Deroisy",
    "wof:placetype":"venue"
},
  "geometry": {"coordinates":[4.7108898163,50.433555603],"type":"Point"}
}