{
  "type": "Feature",
  "properties": {
    "iso:country":"BE",
    "sg:address":"Route D'eghez\u00e9e 61",
    "sg:city":"Jemeppe-sur-sambre",
    "sg:classifiers":[
        {
            "category":"Home & Garden",
            "subcategory":"Building Materials",
            "type":"Retail Goods"
        }
    ],
    "sg:phone":"+32 71 78 75 66",
    "sg:postcode":"5190",
    "sg:province":"Namur",
    "sg:tags":[
        "window"
    ],
    "wof:name":"Numes Marques",
    "wof:placetype":"venue"
},
  "geometry": {"coordinates":[4.6649460793,50.462146759],"type":"Point"}
}