{
  "type": "Feature",
  "properties": {
    "iso:country":"BE",
    "sg:address":"Guillaume Stocqstraat 43",
    "sg:city":"Elsene/ixelles",
    "sg:orig_category":"Boekenuitgeverijen Diverse grafische activiteiten",
    "sg:phone":"+32 2 646 65 33",
    "sg:postcode":"1050",
    "sg:province":"Bruxelles-Capitale",
    "wof:name":"E.d.p.",
    "wof:placetype":"venue"
},
  "geometry": {"coordinates":[4.376639843,50.8237495422],"type":"Point"}
}