{
  "type": "Feature",
  "properties": {
    "iso:country":"BE",
    "sg:address":"Robert Molsstraat 8",
    "sg:city":"Antwerpen",
    "sg:orig_category":"Schoonmaakbedrijven and ongediertebestrijding",
    "sg:phone":"+32 3 237 72 77",
    "sg:postcode":"2018",
    "sg:province":"Antwerpen",
    "wof:name":"Schoeters",
    "wof:placetype":"venue"
},
  "geometry": {"coordinates":[4.4025268555,51.2008361816],"type":"Point"}
}