{
  "type": "Feature",
  "properties": {
    "iso:country":"BE",
    "sg:address":"Engelstraat 27",
    "sg:city":"Gent (sint-amandsberg)",
    "sg:classifiers":[
        {
            "category":"Building & Trades",
            "subcategory":"Construction",
            "type":"Services"
        }
    ],
    "sg:phone":"+32 9 229 29 47",
    "sg:postcode":"9040",
    "sg:province":"Oost-Vlaanderen",
    "sg:tags":[
        "installation",
        "-",
        "central",
        "heating"
    ],
    "wof:name":"Md-chauffage Bvba",
    "wof:placetype":"venue"
},
  "geometry": {"coordinates":[3.7501409054,51.0559196472],"type":"Point"}
}