{
  "type": "Feature",
  "properties": {
    "addr:full":"Heuvelstraat 24 Boechout Antwerpen 2530",
    "addr:housenumber":"24",
    "addr:postcode":"2530",
    "addr:street":"Heuvelstraat",
    "iso:country":"BE",
    "sg:address":"Heuvelstraat 24",
    "sg:city":"Boechout",
    "sg:orig_category":"Cr\u00e8ches and garderies d'enfants",
    "sg:phone":"+32 3 454 24 44",
    "sg:postcode":"2530",
    "sg:province":"Antwerpen",
    "wof:name":"Kribbe De Kleine Berg(vanaf 18mnd)",
    "wof:placetype":"venue"
},
  "geometry": {"coordinates":[4.4906640053,51.162311554],"type":"Point"}
}