{
  "type": "Feature",
  "properties": {
    "iso:country":"BE",
    "sg:address":"Joseph Kelchtermansstr. 30",
    "sg:city":"Anderlecht/anderlecht",
    "sg:orig_category":"Artiesten and kunstenaars",
    "sg:phone":"+32 2 522 03 14",
    "sg:postcode":"1070",
    "sg:province":"Bruxelles-Capitale",
    "wof:name":"Daniel Shirer",
    "wof:placetype":"venue"
},
  "geometry": {"coordinates":[4.3029260635,50.8451271057],"type":"Point"}
}