{
  "type": "Feature",
  "properties": {
    "addr:full":"Strikkeweg 21 Merksplas Antwerpen 2330",
    "addr:housenumber":"21",
    "addr:postcode":"2330",
    "addr:street":"Strikkeweg",
    "iso:country":"BE",
    "sg:address":"Strikkeweg 21",
    "sg:city":"Merksplas",
    "sg:orig_category":"Eleveurs and marchands de porcs",
    "sg:phone":"+32 14 63 48 46",
    "sg:postcode":"2330",
    "sg:province":"Antwerpen",
    "wof:name":"Henricus Aerts",
    "wof:placetype":"venue"
},
  "geometry": {"coordinates":[4.8679051399,51.3960418701],"type":"Point"}
}