{
  "type": "Feature",
  "properties": {
    "iso:country":"BE",
    "sg:address":"Leiekaai 18",
    "sg:city":"Gent",
    "sg:orig_category":"Herstellingen and onderhoud van auto's Voertuigen",
    "sg:phone":"+32 9 216 70 50",
    "sg:postcode":"9000",
    "sg:province":"Oost-Vlaanderen",
    "wof:name":"N.a.m.",
    "wof:placetype":"venue"
},
  "geometry": {"coordinates":[3.7059168816,51.0571670532],"type":"Point"}
}