{
  "type": "Feature",
  "properties": {
    "addr:full":"S\u00e8cheval 1 Jalhay Li\u00e8ge 4845",
    "addr:housenumber":"1",
    "addr:postcode":"4845",
    "addr:street":"Se\u0300Cheval",
    "iso:country":"BE",
    "sg:address":"S\u00e8cheval 1",
    "sg:city":"Jalhay",
    "sg:classifiers":[
        {
            "category":"Building & Trades",
            "subcategory":"Plumbing",
            "type":"Services"
        }
    ],
    "sg:phone":"+32 87 22 59 66",
    "sg:postcode":"4845",
    "sg:province":"Li\u00e8ge",
    "sg:tags":[
        "contractor"
    ],
    "wof:name":"Drossard Ph",
    "wof:placetype":"venue"
},
  "geometry": {"coordinates":[5.903263092,50.5808486938],"type":"Point"}
}