{
  "type": "Feature",
  "properties": {
    "addr:full":"53 Nijverheidszone Begijnenmeers 1770 Liedekerke 53",
    "addr:housenumber":"53;1770;53",
    "addr:street":"Nijverheidszone Begijnenmeers;Liedekerke",
    "iso:country":"BE",
    "sg:address":"53",
    "sg:city":"Nijverheidszone Begijnenmeers 1770 Liedekerke",
    "sg:classifiers":[
        {
            "category":"Manufacturing",
            "subcategory":"Rubber & Plastics",
            "type":"Manufacturing & Wholesale Goods"
        }
    ],
    "sg:phone":"+32 53 68 10 50",
    "sg:postcode":"53",
    "sg:tags":[
        "packaging",
        "material",
        "-"
    ],
    "wof:name":"D.m. Plastics Nv",
    "wof:placetype":"venue"
},
  "geometry": {"coordinates":[4.0886540413,50.8841819763],"type":"Point"}
}