{
  "type": "Feature",
  "properties": {
    "iso:country":"BE",
    "sg:address":"Chauss\u00c9e De Spa 107",
    "sg:city":"Theux",
    "sg:orig_category":"Antiek",
    "sg:phone":"+32 87 89 00 29",
    "sg:postcode":"4910",
    "sg:province":"Li\u00e8ge",
    "wof:name":"Maison Delhez J.",
    "wof:placetype":"venue"
},
  "geometry": {"coordinates":[5.8163480759,50.5162773132],"type":"Point"}
}