{
  "type": "Feature",
  "properties": {
    "addr:full":"Turnhoutsebaan 108 Mol Antwerpen 2400",
    "addr:housenumber":"108",
    "addr:postcode":"2400",
    "addr:street":"Turnhoutsebaan",
    "iso:country":"BE",
    "sg:address":"Turnhoutsebaan 108",
    "sg:city":"Mol",
    "sg:classifiers":[
        {
            "category":"Professional",
            "subcategory":"Management & Consulting",
            "type":"Services"
        }
    ],
    "sg:phone":"+32 14 31 19 96",
    "sg:postcode":"2400",
    "sg:province":"Antwerpen",
    "sg:tags":[
        "consultant",
        "law"
    ],
    "wof:name":"Adacfi Blockx Bvba",
    "wof:placetype":"venue"
},
  "geometry": {"coordinates":[5.1153898239,51.1961212158],"type":"Point"}
}