{
  "type": "Feature",
  "properties": {
    "iso:country":"BE",
    "sg:address":"Beringersteenweg 2",
    "sg:city":"Heusden-zolder",
    "sg:orig_category":"Agences immobili\u00e8res",
    "sg:phone":"+32 11 45 29 70",
    "sg:postcode":"3550",
    "sg:province":"Limburg",
    "wof:name":"Racio",
    "wof:placetype":"venue"
},
  "geometry": {"coordinates":[5.2662401199,51.0264396667],"type":"Point"}
}