{
  "type": "Feature",
  "properties": {
    "addr:full":"Rue De La Dr\u00eave 1c Clavier Li\u00e8ge 4560",
    "addr:housenumber":"1c",
    "addr:postcode":"4560",
    "addr:street":"Rue De La Dre\u0302Ve",
    "iso:country":"BE",
    "sg:address":"Rue De La Dr\u00eave 1c",
    "sg:city":"Clavier",
    "sg:classifiers":[
        {
            "category":"Autos & Motor Vehicles",
            "subcategory":"Motorcycle Sales",
            "type":"Retail Goods"
        }
    ],
    "sg:phone":"+32 86 34 55 04",
    "sg:postcode":"4560",
    "sg:province":"Li\u00e8ge",
    "sg:tags":[
        "motorbike"
    ],
    "wof:name":"Pb (carrosserie Motos)",
    "wof:placetype":"venue"
},
  "geometry": {"coordinates":[5.354352951,50.428024292],"type":"Point"}
}