{
  "type": "Feature",
  "properties": {
    "addr:full":"Cour Du Val 245 Seraing Li\u00e8ge 4100",
    "addr:housenumber":"245",
    "addr:postcode":"4100",
    "addr:street":"Cour Du Val",
    "iso:country":"BE",
    "sg:address":"Cour Du Val 245",
    "sg:city":"Seraing",
    "sg:orig_category":"RESTAURANTS: SALLES DE CONF\u00c9RENCES AND DE R\u00c9CEPTIONS",
    "sg:phone":"+32 4 337 59 87",
    "sg:postcode":"4100",
    "sg:province":"Li\u00e8ge",
    "wof:name":"Val Saint Lambert",
    "wof:placetype":"venue"
},
  "geometry": {"coordinates":[5.480632782,50.5933036804],"type":"Point"}
}