{
  "type": "Feature",
  "properties": {
    "addr:full":"Molenstraat 81 Dilbeek Vlaams-Brabant 1700",
    "addr:housenumber":"81",
    "addr:postcode":"1700",
    "addr:street":"Molenstraat",
    "iso:country":"BE",
    "sg:address":"Molenstraat 81",
    "sg:city":"Dilbeek",
    "sg:orig_category":"Krantenwinkels Rookartikelen",
    "sg:phone":"+32 2 582 09 38",
    "sg:postcode":"1700",
    "sg:province":"Vlaams-Brabant",
    "wof:name":"Liesbet",
    "wof:placetype":"venue"
},
  "geometry": {"coordinates":[4.2069859505,50.8665122986],"type":"Point"}
}