{
  "type": "Feature",
  "properties": {
    "iso:country":"BE",
    "sg:address":"Hezerstraat 11",
    "sg:city":"Kinrooi",
    "sg:classifiers":[
        {
            "category":"Wholesale",
            "subcategory":"Machinery & Supplies",
            "type":"Manufacturing & Wholesale Goods"
        }
    ],
    "sg:phone":"+32 89 46 56 50",
    "sg:postcode":"3640",
    "sg:province":"Limburg",
    "sg:tags":[
        "refrigeration",
        "-",
        "industrial",
        "commercial",
        "equipment"
    ],
    "wof:name":"Pm Koudetechniek",
    "wof:placetype":"venue"
},
  "geometry": {"coordinates":[5.7419490814,51.1648101807],"type":"Point"}
}