{
  "type": "Feature",
  "properties": {
    "addr:full":"Blaasveldstraat 185 Willebroek Antwerpen 2830",
    "addr:housenumber":"185",
    "addr:postcode":"2830",
    "addr:street":"Blaasveldstraat",
    "iso:country":"BE",
    "sg:address":"Blaasveldstraat 185",
    "sg:city":"Willebroek",
    "sg:orig_category":"Artsen and specialisten",
    "sg:phone":"+32 3 866 06 12",
    "sg:postcode":"2830",
    "sg:province":"Antwerpen",
    "wof:name":"Danny Adams",
    "wof:placetype":"venue"
},
  "geometry": {"coordinates":[4.3751702309,51.0428657532],"type":"Point"}
}