{
  "type": "Feature",
  "properties": {
    "iso:country":"BE",
    "sg:address":"Lusthoflaan 55",
    "sg:city":"Gent (mariakerke)",
    "sg:classifiers":[
        {
            "category":"Health Services",
            "subcategory":"Doctor",
            "type":"Services"
        }
    ],
    "sg:phone":"+32 9 227 67 17",
    "sg:postcode":"9030",
    "sg:province":"Oost-Vlaanderen",
    "sg:tags":[
        "medicinephysicians",
        "surgeon"
    ],
    "wof:name":"Haemers S",
    "wof:placetype":"venue"
},
  "geometry": {"coordinates":[3.6977159977,51.0775947571],"type":"Point"}
}