{
  "type": "Feature",
  "properties": {
    "addr:full":"Avenue Du Vivier D'oie 19 Brussel/bruxelles Bruxelles-Capitale 1000",
    "addr:housenumber":"19",
    "addr:postcode":"1000",
    "addr:street":"Avenue Du Vivier D'Oie;/",
    "iso:country":"BE",
    "sg:address":"Avenue Du Vivier D'oie 19",
    "sg:city":"Brussel/bruxelles",
    "sg:orig_category":"Agences immobili\u00e8res",
    "sg:phone":"+32 2 379 29 11",
    "sg:postcode":"1000",
    "sg:province":"Bruxelles-Capitale",
    "wof:name":"Bureau Arthur Loyd",
    "wof:placetype":"venue"
},
  "geometry": {"coordinates":[4.377407074,50.802822113],"type":"Point"}
}