{
  "type": "Feature",
  "properties": {
    "iso:country":"BE",
    "sg:address":"Vrijheid 63",
    "sg:city":"Arendonk",
    "sg:classifiers":[
        {
            "category":"Banks & Credit Unions",
            "subcategory":"Investment Brokerage",
            "type":"Services"
        }
    ],
    "sg:postcode":"2370",
    "sg:province":"Antwerpen",
    "sg:tags":[
        "printing",
        "-"
    ],
    "wof:name":"Hoger Op Bvba",
    "wof:placetype":"venue"
},
  "geometry": {"coordinates":[5.0896148682,51.3214302063],"type":"Point"}
}