{
  "type": "Feature",
  "properties": {
    "iso:country":"BE",
    "sg:address":"Nukkerstraat 25",
    "sg:city":"Bredene",
    "sg:classifiers":[
        {
            "category":"Food & Beverages",
            "subcategory":"Supermarket",
            "type":"Retail Goods"
        }
    ],
    "sg:phone":"+32 59 32 12 16",
    "sg:postcode":"8450",
    "sg:province":"West-Vlaanderen",
    "sg:tags":[
        "department",
        "store"
    ],
    "wof:name":"Vanhee Bvba",
    "wof:placetype":"venue"
},
  "geometry": {"coordinates":[2.9577479362,51.2220878601],"type":"Point"}
}