{
  "type": "Feature",
  "properties": {
    "iso:country":"BE",
    "sg:address":"Westvleterendorp 21",
    "sg:city":"Vleteren",
    "sg:orig_category":"Slagers",
    "sg:phone":"+32 57 40 03 42",
    "sg:postcode":"8640",
    "sg:province":"West-Vlaanderen",
    "wof:name":"Slagerij Van Oost",
    "wof:placetype":"venue"
},
  "geometry": {"coordinates":[2.7188160419,50.9262008667],"type":"Point"}
}