{
  "type": "Feature",
  "properties": {
    "addr:full":"Rue Basse-hollande 42 Ittre Brabant Wallon 1460",
    "addr:housenumber":"42;1460",
    "addr:street":"Rue Basse-Hollande",
    "iso:country":"BE",
    "sg:address":"Rue Basse-hollande 42",
    "sg:city":"Ittre",
    "sg:orig_category":"Rundveehouders",
    "sg:phone":"+32 67 64 76 87",
    "sg:postcode":"1460",
    "sg:province":"Brabant Wallon",
    "wof:name":"Georges Everard De Harzir",
    "wof:placetype":"venue"
},
  "geometry": {"coordinates":[4.2561740875,50.6198387146],"type":"Point"}
}