{
  "type": "Feature",
  "properties": {
    "iso:country":"BE",
    "sg:address":"Kaalheide 15",
    "sg:city":"Overijse",
    "sg:classifiers":[
        {
            "category":"Professional",
            "subcategory":"Business Services",
            "type":"Services"
        }
    ],
    "sg:phone":"+32 2 687 49 74",
    "sg:postcode":"3090",
    "sg:province":"Vlaams-Brabant",
    "sg:tags":[
        "firm"
    ],
    "wof:name":"Trevena",
    "wof:placetype":"venue"
},
  "geometry": {"coordinates":[4.5556979179,50.7951469421],"type":"Point"}
}