{
  "type": "Feature",
  "properties": {
    "iso:country":"BE",
    "sg:address":"Orval 2",
    "sg:city":"Villers-devant-orval",
    "sg:classifiers":[
        {
            "category":"Wholesale",
            "subcategory":"Beer",
            "type":"Manufacturing & Wholesale Goods"
        }
    ],
    "sg:phone":"+32 61 31 12 61",
    "sg:postcode":"6823",
    "sg:province":"Luxembourg",
    "sg:tags":[
        "regional"
    ],
    "wof:name":"Brasserie D'orval S.a.",
    "wof:placetype":"venue"
},
  "geometry": {"coordinates":[5.3342962265,49.6187934875],"type":"Point"}
}