{
  "type": "Feature",
  "properties": {
    "addr:full":"Rue Octave Battaille 163 Beloeil (bas\u00e8cles) Hainaut 7971",
    "addr:housenumber":"163",
    "addr:postcode":"7971",
    "addr:street":"Rue Octave Battaille",
    "iso:country":"BE",
    "sg:address":"Rue Octave Battaille 163",
    "sg:city":"Beloeil (bas\u00e8cles)",
    "sg:classifiers":[
        {
            "category":"Retail",
            "subcategory":"Auto Repair",
            "type":"Services"
        }
    ],
    "sg:postcode":"7971",
    "sg:province":"Hainaut",
    "sg:tags":[
        "garage"
    ],
    "wof:name":"Ath Motor Sa Fiat-alfa Romeo",
    "wof:placetype":"venue"
},
  "geometry": {"coordinates":[3.6480550766,50.5259284973],"type":"Point"}
}