{
  "type": "Feature",
  "properties": {
    "iso:country":"BE",
    "sg:address":"Chauss\u00e9e De Li\u00e8ge 68",
    "sg:city":"Amay (ampsin)",
    "sg:classifiers":[
        {
            "category":"Professional",
            "subcategory":"Accounting & Tax Preparation",
            "type":"Services"
        }
    ],
    "sg:phone":"+32 85 31 51 23",
    "sg:postcode":"4540",
    "sg:province":"Li\u00e8ge",
    "sg:tags":[
        "bookkeeper"
    ],
    "wof:name":"Cellier Mm",
    "wof:placetype":"venue"
},
  "geometry": {"coordinates":[5.2987098694,50.5410614014],"type":"Point"}
}