{
  "type": "Feature",
  "properties": {
    "addr:full":"Rue De France 20 Verviers Li\u00e8ge 4800",
    "addr:housenumber":"20",
    "addr:postcode":"4800",
    "addr:street":"Rue De France",
    "iso:country":"BE",
    "sg:address":"Rue De France 20",
    "sg:city":"Verviers",
    "sg:classifiers":[
        {
            "category":"Professional",
            "subcategory":"Lawyer & Legal Services",
            "type":"Services"
        }
    ],
    "sg:phone":"+32 87 26 97 90",
    "sg:postcode":"4800",
    "sg:province":"Li\u00e8ge",
    "wof:name":"Luypaerts Aur\u00e9lia",
    "wof:placetype":"venue"
},
  "geometry": {"coordinates":[5.8600931168,50.5879402161],"type":"Point"}
}