{
  "type": "Feature",
  "properties": {
    "addr:full":"Elenestraat 147 Zottegem (elene - Oombergen) Oost-Vlaanderen 9620",
    "addr:housenumber":"147",
    "addr:postcode":"9620",
    "addr:street":"Elenestraat;Oost-Vlaanderen",
    "iso:country":"BE",
    "sg:address":"Elenestraat 147",
    "sg:city":"Zottegem (elene - Oombergen)",
    "sg:classifiers":[
        {
            "category":"Real Estate",
            "subcategory":"Architect",
            "type":"Services"
        }
    ],
    "sg:phone":"+32 9 360 90 13",
    "sg:postcode":"9620",
    "sg:province":"Oost-Vlaanderen",
    "wof:name":"Verdegem G",
    "wof:placetype":"venue"
},
  "geometry": {"coordinates":[3.8086929321,50.8774681091],"type":"Point"}
}