{
  "type": "Feature",
  "properties": {
    "addr:full":"Rue Nicolas Lambercy 14 Aywaille Li\u00e8ge 4920",
    "addr:housenumber":"14",
    "addr:postcode":"4920",
    "addr:street":"Rue Nicolas Lambercy",
    "iso:country":"BE",
    "sg:address":"Rue Nicolas Lambercy 14",
    "sg:city":"Aywaille",
    "sg:classifiers":[
        {
            "category":"Bars & Pubs",
            "type":"Food & Drink"
        }
    ],
    "sg:phone":"+32 4 384 40 67",
    "sg:postcode":"4920",
    "sg:province":"Li\u00e8ge",
    "wof:name":"Honhon C",
    "wof:placetype":"venue"
},
  "geometry": {"coordinates":[5.6757640839,50.4726715088],"type":"Point"}
}