{
  "type": "Feature",
  "properties": {
    "addr:full":"Statiestraat 7 Nijlen Antwerpen 2560",
    "addr:housenumber":"7",
    "addr:postcode":"2560",
    "addr:street":"Statiestraat",
    "iso:country":"BE",
    "sg:address":"Statiestraat 7",
    "sg:city":"Nijlen",
    "sg:classifiers":[
        {
            "category":"Health Services",
            "subcategory":"Dentist",
            "type":"Services"
        }
    ],
    "sg:phone":"+32 3 481 71 18",
    "sg:postcode":"2560",
    "sg:province":"Antwerpen",
    "wof:name":"Verhaegen M",
    "wof:placetype":"venue"
},
  "geometry": {"coordinates":[4.6683712006,51.1603317261],"type":"Point"}
}