{
  "type": "Feature",
  "properties": {
    "iso:country":"BE",
    "sg:address":"Knokbosstraat 10",
    "sg:city":"Deerlijk",
    "sg:classifiers":[
        {
            "category":"Building & Trades",
            "subcategory":"Pest Control",
            "type":"Services"
        }
    ],
    "sg:phone":"+32 56 77 48 55",
    "sg:postcode":"8540",
    "sg:province":"West-Vlaanderen",
    "sg:tags":[
        "painting",
        "contractor"
    ],
    "wof:name":"De Gezelle F",
    "wof:placetype":"venue"
},
  "geometry": {"coordinates":[3.3580029011,50.8397941589],"type":"Point"}
}