{
  "type": "Feature",
  "properties": {
    "addr:full":"Antwerpsesteenweg 208 Kapellen Antwerpen 2950",
    "addr:housenumber":"208",
    "addr:postcode":"2950",
    "addr:street":"Antwerpsesteenweg",
    "iso:country":"BE",
    "sg:address":"Antwerpsesteenweg 208",
    "sg:city":"Kapellen",
    "sg:classifiers":[
        {
            "category":"Restaurant",
            "type":"Food & Drink"
        }
    ],
    "sg:phone":"+32 3 664 10 42",
    "sg:postcode":"2950",
    "sg:province":"Antwerpen",
    "wof:name":"Rialto's Smulkroeg",
    "wof:placetype":"venue"
},
  "geometry": {"coordinates":[4.434240818,51.3056221008],"type":"Point"}
}