{
  "type": "Feature",
  "properties": {
    "addr:full":"Rue Du Centenaire 74 Boussu Hainaut 7300",
    "addr:housenumber":"74",
    "addr:postcode":"7300",
    "addr:street":"Rue Du Centenaire",
    "iso:country":"BE",
    "sg:address":"Rue Du Centenaire 74",
    "sg:city":"Boussu",
    "sg:orig_category":"Rev\u00eatements pour sols and murs. Construction de maisons. Installation de menuiserie en bois and plas",
    "sg:phone":"+32 65 77 84 49",
    "sg:postcode":"7300",
    "sg:province":"Hainaut",
    "wof:name":"Batibor",
    "wof:placetype":"venue"
},
  "geometry": {"coordinates":[3.795582056,50.4296226501],"type":"Point"}
}