{
  "type": "Feature",
  "properties": {
    "iso:country":"BE",
    "sg:address":"Rue Bellaire 2",
    "sg:city":"Neupre",
    "sg:classifiers":[
        {
            "category":"Food & Beverages",
            "subcategory":"Fruits & Vegetables",
            "type":"Retail Goods"
        }
    ],
    "sg:phone":"+32 4 371 39 76",
    "sg:postcode":"4120",
    "sg:province":"Li\u00e8ge",
    "sg:tags":[
        "groenten"
    ],
    "wof:name":"Le Verger Gourmand",
    "wof:placetype":"venue"
},
  "geometry": {"coordinates":[5.4811987877,50.5346641541],"type":"Point"}
}