{
  "type": "Feature",
  "properties": {
    "addr:full":"Plein 39 Kortrijk West-Vlaanderen 8500",
    "addr:housenumber":"39",
    "addr:postcode":"8500",
    "addr:street":"Plein",
    "iso:country":"BE",
    "sg:address":"Plein 39",
    "sg:city":"Kortrijk",
    "sg:classifiers":[
        {
            "category":"Health Services",
            "subcategory":"Doctor",
            "type":"Services"
        }
    ],
    "sg:phone":"+32 56 24 25 10",
    "sg:postcode":"8500",
    "sg:province":"West-Vlaanderen",
    "sg:tags":[
        "medicinephysicians",
        "surgeon"
    ],
    "wof:name":"De Moor M",
    "wof:placetype":"venue"
},
  "geometry": {"coordinates":[3.2721738815,50.8289527893],"type":"Point"}
}