{
  "type": "Feature",
  "properties": {
    "addr:full":"Hamerstraat 71 Brussel/bruxelles Bruxelles-Capitale 1000",
    "addr:housenumber":"71",
    "addr:postcode":"1000",
    "addr:street":"Hamerstraat;/",
    "iso:country":"BE",
    "sg:address":"Hamerstraat 71",
    "sg:city":"Brussel/bruxelles",
    "sg:orig_category":"Film-, tv- and videoproductie",
    "sg:phone":"+32 2 280 38 88",
    "sg:postcode":"1000",
    "sg:province":"Bruxelles-Capitale",
    "wof:name":"E. Pardo",
    "wof:placetype":"venue"
},
  "geometry": {"coordinates":[4.3751091957,50.8467483521],"type":"Point"}
}