{
  "type": "Feature",
  "properties": {
    "iso:country":"BE",
    "sg:address":"Theofiel Van Cauwenberghslei 12",
    "sg:city":"Schoten",
    "sg:classifiers":[
        {
            "category":"Banks & Credit Unions",
            "subcategory":"Investment Brokerage",
            "type":"Services"
        }
    ],
    "sg:phone":"+32 3 685 40 07",
    "sg:postcode":"2900",
    "sg:province":"Antwerpen",
    "sg:tags":[
        "auditor"
    ],
    "wof:name":"Parmentier G",
    "wof:placetype":"venue"
},
  "geometry": {"coordinates":[4.5021219254,51.2524299622],"type":"Point"}
}