{
  "type": "Feature",
  "properties": {
    "addr:full":"Mechelsesteenweg 73 Mortsel Antwerpen 2640",
    "addr:housenumber":"73",
    "addr:postcode":"2640",
    "addr:street":"Mechelsesteenweg",
    "iso:country":"BE",
    "sg:address":"Mechelsesteenweg 73",
    "sg:city":"Mortsel",
    "sg:orig_category":"Newspapers, magazines, periodicals - Distribution",
    "sg:phone":"+32 3 448 17 06",
    "sg:postcode":"2640",
    "sg:province":"Antwerpen",
    "wof:name":"Dagbladhandel Rudy",
    "wof:placetype":"venue"
},
  "geometry": {"coordinates":[4.4523172379,51.1680488586],"type":"Point"}
}