{
  "type": "Feature",
  "properties": {
    "iso:country":"BE",
    "sg:address":"Motteveld 6",
    "sg:city":"Aarschot",
    "sg:classifiers":[
        {
            "category":"Food & Beverages",
            "subcategory":"Fruits & Vegetables",
            "type":"Retail Goods"
        }
    ],
    "sg:phone":"+32 16 50 29 01",
    "sg:postcode":"3202",
    "sg:province":"Vlaams-Brabant",
    "sg:tags":[
        "l\u00e9gumes",
        "gr"
    ],
    "wof:name":"Richard Van Calster",
    "wof:placetype":"venue"
},
  "geometry": {"coordinates":[4.8977022171,50.9747047424],"type":"Point"}
}