{
  "type": "Feature",
  "properties": {
    "iso:country":"BE",
    "sg:address":"Route De Falize 2h",
    "sg:city":"Malmedy",
    "sg:classifiers":[
        {
            "category":"Professional",
            "subcategory":"Secretarial Services",
            "type":"Services"
        }
    ],
    "sg:phone":"+32 80 33 71 88",
    "sg:postcode":"4960",
    "sg:province":"Li\u00e8ge",
    "sg:tags":[
        "firm"
    ],
    "wof:name":"Gazon G-service",
    "wof:placetype":"venue"
},
  "geometry": {"coordinates":[6.0189809799,50.4228286743],"type":"Point"}
}