{
  "type": "Feature",
  "properties": {
    "addr:full":"Moulin De Dison 57 Jalhay Li\u00e8ge 4845",
    "addr:housenumber":"57",
    "addr:postcode":"4845",
    "addr:street":"Moulin De Dison",
    "iso:country":"BE",
    "sg:address":"Moulin De Dison 57",
    "sg:city":"Jalhay",
    "sg:classifiers":[
        {
            "category":"Professional",
            "subcategory":"Accounting & Tax Preparation",
            "type":"Services"
        }
    ],
    "sg:phone":"+32 87 64 71 17",
    "sg:postcode":"4845",
    "sg:province":"Li\u00e8ge",
    "sg:tags":[
        "bookkeeper"
    ],
    "wof:name":"Koch M",
    "wof:placetype":"venue"
},
  "geometry": {"coordinates":[5.966217041,50.5458984375],"type":"Point"}
}