{
  "type": "Feature",
  "properties": {
    "addr:full":"Rue Grande 251 Beloeil (bas\u00e8cles) Hainaut 7971",
    "addr:housenumber":"251",
    "addr:postcode":"7971",
    "addr:street":"Rue Grande",
    "iso:country":"BE",
    "sg:address":"Rue Grande 251",
    "sg:city":"Beloeil (bas\u00e8cles)",
    "sg:classifiers":[
        {
            "category":"Bakery",
            "type":"Food & Drink"
        }
    ],
    "sg:phone":"+32 69 56 21 80",
    "sg:postcode":"7971",
    "sg:province":"Hainaut",
    "sg:tags":[
        "confectioner",
        "baker"
    ],
    "wof:name":"Zanella T",
    "wof:placetype":"venue"
},
  "geometry": {"coordinates":[3.6605861187,50.5207138062],"type":"Point"}
}