{
  "type": "Feature",
  "properties": {
    "iso:country":"BE",
    "sg:address":"Koekoekstraat 33",
    "sg:city":"Gooik",
    "sg:classifiers":[
        {
            "category":"Retail",
            "subcategory":"Event Space",
            "type":"Services"
        }
    ],
    "sg:phone":"+32 2 532 40 08",
    "sg:postcode":"1755",
    "sg:province":"Vlaams-Brabant",
    "sg:tags":[
        "product",
        "snack",
        "speciality",
        "potato",
        "stand",
        "fried"
    ],
    "wof:name":"Devoghel",
    "wof:placetype":"venue"
},
  "geometry": {"coordinates":[4.1127328873,50.7944068909],"type":"Point"}
}