{
  "type": "Feature",
  "properties": {
    "iso:country":"BE",
    "sg:address":"Ijsvogellaan 3",
    "sg:city":"Hove",
    "sg:classifiers":[
        {
            "category":"Health Services",
            "subcategory":"Health Practitioner",
            "type":"Services"
        }
    ],
    "sg:phone":"+32 475 59 14 82",
    "sg:postcode":"2540",
    "sg:province":"Antwerpen",
    "sg:tags":[
        "therapist",
        "speech"
    ],
    "wof:name":"Geluykens E",
    "wof:placetype":"venue"
},
  "geometry": {"coordinates":[4.4836301804,51.1468467712],"type":"Point"}
}