{
  "type": "Feature",
  "properties": {
    "iso:country":"BE",
    "sg:address":"Rue Schmit 21",
    "sg:city":"Aubange",
    "sg:orig_category":"Salles de conf\u00e9rences and de r\u00e9ceptions",
    "sg:phone":"+32 63 38 74 69",
    "sg:postcode":"6790",
    "sg:province":"Luxembourg",
    "wof:name":"Salle Polyvalente",
    "wof:placetype":"venue"
},
  "geometry": {"coordinates":[5.8046097755,49.5667800903],"type":"Point"}
}