{
  "type": "Feature",
  "properties": {
    "addr:full":"Stevoortse Kiezel 305 Hasselt Limburg 3512",
    "addr:housenumber":"305",
    "addr:postcode":"3512",
    "addr:street":"Stevoortse Kiezel",
    "iso:country":"BE",
    "sg:address":"Stevoortse Kiezel 305",
    "sg:city":"Hasselt",
    "sg:orig_category":"Artsen and specialisten",
    "sg:phone":"+32 11 59 27 63",
    "sg:postcode":"3512",
    "sg:province":"Limburg",
    "wof:name":"L. Delsupehe",
    "wof:placetype":"venue"
},
  "geometry": {"coordinates":[5.2607650757,50.9241867065],"type":"Point"}
}