{
  "type": "Feature",
  "properties": {
    "iso:country":"BE",
    "sg:address":"Houzeaulaan 17",
    "sg:city":"Ukkel/uccle",
    "sg:orig_category":"Architecten",
    "sg:phone":"+32 2 375 47 94",
    "sg:postcode":"1180",
    "sg:province":"Bruxelles-Capitale",
    "wof:name":"Vincent Delaunois",
    "wof:placetype":"venue"
},
  "geometry": {"coordinates":[4.3585300446,50.8034515381],"type":"Point"}
}