{
  "type": "Feature",
  "properties": {
    "iso:country":"BE",
    "sg:address":"Place De Naast 2",
    "sg:city":"Soignies (naast)",
    "sg:classifiers":[
        {
            "category":"Airport",
            "subcategory":"International",
            "type":"Transportation"
        }
    ],
    "sg:phone":"+32 67 33 41 70",
    "sg:postcode":"7062",
    "sg:province":"Hainaut",
    "sg:tags":[
        "-",
        "transport"
    ],
    "wof:name":"Trans Adricam",
    "wof:placetype":"venue"
},
  "geometry": {"coordinates":[4.0996851921,50.5541000366],"type":"Point"}
}