{
  "type": "Feature",
  "properties": {
    "iso:country":"BE",
    "sg:address":"Sint-amandusstraat 7",
    "sg:city":"Kortessem",
    "sg:orig_category":"Producteurs de fruits",
    "sg:phone":"+32 12 23 42 52",
    "sg:postcode":"3724",
    "sg:province":"Limburg",
    "wof:name":"Danny Schoels",
    "wof:placetype":"venue"
},
  "geometry": {"coordinates":[5.4069547653,50.8142776489],"type":"Point"}
}