{
  "type": "Feature",
  "properties": {
    "addr:full":"Wegvoeringstraat 11 Wetteren Oost-Vlaanderen 9230",
    "addr:housenumber":"11",
    "addr:postcode":"9230",
    "addr:street":"Wegvoeringstraat",
    "iso:country":"BE",
    "sg:address":"Wegvoeringstraat 11",
    "sg:city":"Wetteren",
    "sg:orig_category":"Diverse kredietdiensten",
    "sg:postcode":"9230",
    "sg:province":"Oost-Vlaanderen",
    "wof:name":"Bancontact-mister Cash",
    "wof:placetype":"venue"
},
  "geometry": {"coordinates":[3.8865509033,51.0072746277],"type":"Point"}
}