{
  "type": "Feature",
  "properties": {
    "addr:full":"Ruiseleedsesteenweg 7 Tielt West-Vlaanderen 8700",
    "addr:housenumber":"7",
    "addr:postcode":"8700",
    "addr:street":"Ruiseleedsesteenweg",
    "iso:country":"BE",
    "sg:address":"Ruiseleedsesteenweg 7",
    "sg:city":"Tielt",
    "sg:orig_category":"Sportclubs",
    "sg:phone":"+32 51 40 32 94",
    "sg:postcode":"8700",
    "sg:province":"West-Vlaanderen",
    "wof:name":"De Kapelse Wielerclub - Schuiferskapelle",
    "wof:placetype":"venue"
},
  "geometry": {"coordinates":[3.3404140472,51.0044136047],"type":"Point"}
}