{
  "type": "Feature",
  "properties": {
    "addr:full":"Maenrot 8 Boortmeerbeek Vlaams-Brabant 3190",
    "addr:housenumber":"8",
    "addr:postcode":"3190",
    "addr:street":"Maenrot",
    "iso:country":"BE",
    "sg:address":"Maenrot 8",
    "sg:city":"Boortmeerbeek",
    "sg:orig_category":"Groenten and fruit Gh",
    "sg:phone":"+32 16 65 70 25",
    "sg:postcode":"3190",
    "sg:province":"Vlaams-Brabant",
    "wof:name":"Ingrid Devinck",
    "wof:placetype":"venue"
},
  "geometry": {"coordinates":[4.5613479614,50.9704933167],"type":"Point"}
}