{
  "type": "Feature",
  "properties": {
    "iso:country":"BE",
    "sg:address":"Bolderstraat 70",
    "sg:city":"Riemst",
    "sg:orig_category":"M\u00e9decins and sp\u00e9cialistes",
    "sg:phone":"+32 12 45 58 91",
    "sg:postcode":"3770",
    "sg:province":"Limburg",
    "wof:name":"Luc Hardy",
    "wof:placetype":"venue"
},
  "geometry": {"coordinates":[5.6003341675,50.7908248901],"type":"Point"}
}