{
  "type": "Feature",
  "properties": {
    "iso:country":"BE",
    "sg:address":"Ijzerwegstr 1ba",
    "sg:city":"Ostende",
    "sg:orig_category":"Reliure and finition",
    "sg:phone":"+32 59 80 81 73",
    "sg:postcode":"8400",
    "sg:province":"West-Vlaanderen",
    "wof:name":"Belgocard",
    "wof:placetype":"venue"
},
  "geometry": {"coordinates":[2.9358789921,51.2169532776],"type":"Point"}
}