{
  "type": "Feature",
  "properties": {
    "iso:country":"BE",
    "sg:address":"Sint-salvatorstraat 113",
    "sg:city":"Gent",
    "sg:classifiers":[
        {
            "category":"Personal",
            "subcategory":"Nail Salon",
            "type":"Services"
        }
    ],
    "sg:phone":"+32 9 259 23 14",
    "sg:postcode":"9000",
    "sg:province":"Oost-Vlaanderen",
    "sg:tags":[
        "pedicure"
    ],
    "wof:name":"Freya",
    "wof:placetype":"venue"
},
  "geometry": {"coordinates":[3.7288410664,51.0660247803],"type":"Point"}
}