{
  "type": "Feature",
  "properties": {
    "addr:full":"Legeweg 231 Brugge West-Vlaanderen 8200",
    "addr:housenumber":"231",
    "addr:postcode":"8200",
    "addr:street":"Legeweg",
    "iso:country":"BE",
    "sg:address":"Legeweg 231",
    "sg:city":"Brugge",
    "sg:orig_category":"Pharmaciens",
    "sg:phone":"+32 50 32 07 67",
    "sg:postcode":"8200",
    "sg:province":"West-Vlaanderen",
    "wof:name":"Luc Monkerhey",
    "wof:placetype":"venue"
},
  "geometry": {"coordinates":[3.1957600117,51.2053184509],"type":"Point"}
}