{
  "type": "Feature",
  "properties": {
    "addr:full":"Hoogstraat 38 Oudenaarde Oost-Vlaanderen 9700",
    "addr:housenumber":"38",
    "addr:postcode":"9700",
    "addr:street":"Hoogstraat",
    "iso:country":"BE",
    "sg:address":"Hoogstraat 38",
    "sg:city":"Oudenaarde",
    "sg:orig_category":"Advocaten and juridische adviseurs",
    "sg:phone":"+32 55 31 65 33",
    "sg:postcode":"9700",
    "sg:province":"Oost-Vlaanderen",
    "wof:name":"Dirk Vanschoubroek",
    "wof:placetype":"venue"
},
  "geometry": {"coordinates":[3.6019248962,50.8455734253],"type":"Point"}
}