{
  "type": "Feature",
  "properties": {
    "iso:country":"BE",
    "sg:address":"Klein Rootstraat 8",
    "sg:city":"Maaseik (neeroeteren)",
    "sg:classifiers":[
        {
            "category":"Home & Garden",
            "subcategory":"Home Furnishings",
            "type":"Retail Goods"
        }
    ],
    "sg:phone":"+32 89 86 48 40",
    "sg:postcode":"3680",
    "sg:province":"Limburg",
    "sg:tags":[
        "interior",
        "decoration"
    ],
    "wof:name":"Hawi Interieur",
    "wof:placetype":"venue"
},
  "geometry": {"coordinates":[5.7063498497,51.0961265564],"type":"Point"}
}