{
  "type": "Feature",
  "properties": {
    "addr:full":"Avenue Du Panth\u00e9on 35 Bruxelles (koekelberg) Bruxelles-Capitale 1081",
    "addr:housenumber":"35",
    "addr:postcode":"1081",
    "addr:street":"Avenue Du Panthe\u0301On",
    "iso:country":"BE",
    "sg:address":"Avenue Du Panth\u00e9on 35",
    "sg:city":"Bruxelles (koekelberg)",
    "sg:classifiers":[
        {
            "category":"Real Estate",
            "subcategory":"Real Estate Services",
            "type":"Services"
        }
    ],
    "sg:phone":"+32 2 414 60 69",
    "sg:postcode":"1081",
    "sg:province":"Bruxelles-Capitale",
    "wof:name":"Immobur",
    "wof:placetype":"venue"
},
  "geometry": {"coordinates":[4.3224658966,50.8642501831],"type":"Point"}
}