{
  "type": "Feature",
  "properties": {
    "addr:full":"Rue De Tournai 34ba Beloeil Hainaut 7972",
    "addr:housenumber":"34ba",
    "addr:postcode":"7972",
    "addr:street":"Rue De Tournai",
    "iso:country":"BE",
    "sg:address":"Rue De Tournai 34ba",
    "sg:city":"Beloeil",
    "sg:orig_category":"Herstellingswinkels voor diverse persoonlijke and huishoudartikelen",
    "sg:phone":"+32 69 56 28 78",
    "sg:postcode":"7972",
    "sg:province":"Hainaut",
    "wof:name":"Maison Bout D\u00b4fil",
    "wof:placetype":"venue"
},
  "geometry": {"coordinates":[3.6921050549,50.5274238586],"type":"Point"}
}