{
  "type": "Feature",
  "properties": {
    "addr:full":"Rue De Renory Li\u00e8ge 1 (angleur) Li\u00e8ge 4031",
    "addr:housenumber":"1",
    "addr:postcode":"4031",
    "addr:street":"Rue De Renory Lie\u0300Ge",
    "iso:country":"BE",
    "sg:address":"Rue De Renory",
    "sg:city":"Li\u00e8ge 1 (angleur)",
    "sg:classifiers":[
        {
            "category":"Professional",
            "type":"Services"
        }
    ],
    "sg:phone":"+32 4 344 89 30",
    "sg:postcode":"4031",
    "sg:province":"Li\u00e8ge",
    "sg:tags":[
        "forwarding",
        "agency"
    ],
    "wof:name":"Ctb Logistics Sa",
    "wof:placetype":"venue"
},
  "geometry": {"coordinates":[5.5317320824,50.6319351196],"type":"Point"}
}