{
  "type": "Feature",
  "properties": {
    "addr:full":"Avenue Belle Vue 74 La Hulpe Brabant Wallon 1310",
    "addr:housenumber":"74",
    "addr:postcode":"1310",
    "addr:street":"Avenue Belle Vue",
    "iso:country":"BE",
    "sg:address":"Avenue Belle Vue 74",
    "sg:city":"La Hulpe",
    "sg:classifiers":[
        {
            "category":"Arena",
            "subcategory":"Sports Club",
            "type":"Entertainment"
        }
    ],
    "sg:phone":"+32 2 653 52 09",
    "sg:postcode":"1310",
    "sg:province":"Brabant Wallon",
    "sg:tags":[
        "de"
    ],
    "wof:name":"T.c. 1310 La Hulpe",
    "wof:placetype":"venue"
},
  "geometry": {"coordinates":[4.4846601486,50.7362861633],"type":"Point"}
}