{
  "type": "Feature",
  "properties": {
    "iso:country":"BE",
    "sg:address":"Rue L\u00c9on Blum 109",
    "sg:city":"Jemeppe-sur-meuse",
    "sg:orig_category":"Services fun\u00e9raires",
    "sg:phone":"+32 4 233 77 92",
    "sg:postcode":"4101",
    "sg:province":"Li\u00e8ge",
    "wof:name":"T\u00c9jean",
    "wof:placetype":"venue"
},
  "geometry": {"coordinates":[5.4893121719,50.6177635193],"type":"Point"}
}