{
  "type": "Feature",
  "properties": {
    "addr:full":"Chauss\u00c9e De Tournai 393 Ath Hainaut 7812",
    "addr:housenumber":"393",
    "addr:postcode":"7812",
    "addr:street":"Chausse\u0301E De Tournai",
    "iso:country":"BE",
    "sg:address":"Chauss\u00c9e De Tournai 393",
    "sg:city":"Ath",
    "sg:orig_category":"Industri\u00eble elektrische installaties",
    "sg:phone":"+32 68 28 12 17",
    "sg:postcode":"7812",
    "sg:province":"Hainaut",
    "wof:name":"Champion Watching",
    "wof:placetype":"venue"
},
  "geometry": {"coordinates":[3.7079770565,50.6189002991],"type":"Point"}
}