{
  "type": "Feature",
  "properties": {
    "iso:country":"BE",
    "sg:address":"Kapellei 98",
    "sg:city":"Zoersel",
    "sg:orig_category":"Yamaha. Motos",
    "sg:phone":"+32 3 288 46 05",
    "sg:postcode":"2980",
    "sg:province":"Antwerpen",
    "wof:name":"Mtc Verho",
    "wof:placetype":"venue"
},
  "geometry": {"coordinates":[4.6296100616,51.2601013184],"type":"Point"}
}