{
  "type": "Feature",
  "properties": {
    "iso:country":"BE",
    "sg:address":"Bevelsesteenweg 140",
    "sg:city":"Nijlen",
    "sg:orig_category":"Woningbouw",
    "sg:phone":"+32 3 481 70 23",
    "sg:postcode":"2560",
    "sg:province":"Antwerpen",
    "wof:name":"Emiel Heylen",
    "wof:placetype":"venue"
},
  "geometry": {"coordinates":[4.6749548912,51.1521568298],"type":"Point"}
}