{
  "type": "Feature",
  "properties": {
    "addr:full":"Sint-amandsstraat 7 Grimbergen (strombeek-bever) Vlaams-Brabant 1853",
    "addr:housenumber":"7",
    "addr:postcode":"1853",
    "addr:street":"Sint-Amandsstraat",
    "iso:country":"BE",
    "sg:address":"Sint-amandsstraat 7",
    "sg:city":"Grimbergen (strombeek-bever)",
    "sg:classifiers":[
        {
            "category":"Shopping",
            "subcategory":"Stationery & Office Supplies",
            "type":"Retail Goods"
        }
    ],
    "sg:phone":"+32 2 267 15 77",
    "sg:postcode":"1853",
    "sg:province":"Vlaams-Brabant",
    "wof:name":"Discova",
    "wof:placetype":"venue"
},
  "geometry": {"coordinates":[4.3574419022,50.9096565247],"type":"Point"}
}