{
  "type": "Feature",
  "properties": {
    "addr:full":"Rue Rouge Fontaine 59 - Zi Du Ped Aubange Luxembourg 6790",
    "addr:housenumber":"59",
    "addr:postcode":"6790",
    "addr:street":"Rue Rouge Fontaine;Du Ped",
    "iso:country":"BE",
    "sg:address":"Rue Rouge Fontaine 59 - Zi Du Ped",
    "sg:city":"Aubange",
    "sg:classifiers":[
        {
            "category":"Professional",
            "subcategory":"Management & Consulting",
            "type":"Services"
        }
    ],
    "sg:phone":"+32 63 38 31 94",
    "sg:postcode":"6790",
    "sg:province":"Luxembourg",
    "sg:tags":[
        "archive"
    ],
    "wof:name":"Security Storage",
    "wof:placetype":"venue"
},
  "geometry": {"coordinates":[5.8051338196,49.5689849854],"type":"Point"}
}