{
  "type": "Feature",
  "properties": {
    "iso:country":"BE",
    "sg:address":"Inakker 122",
    "sg:city":"Heusden-zolder",
    "sg:orig_category":"Public-relationsbureaus",
    "sg:phone":"+32 475 65 58 47",
    "sg:postcode":"3550",
    "sg:province":"Limburg",
    "wof:name":"Azo",
    "wof:placetype":"venue"
},
  "geometry": {"coordinates":[5.3057570457,51.0172080994],"type":"Point"}
}