{
  "type": "Feature",
  "properties": {
    "addr:full":"Rue Seraphin Anthoine 91 Charleroi (mont-sur-marchienne) Hainaut 6032",
    "addr:housenumber":"91",
    "addr:postcode":"6032",
    "addr:street":"Rue Seraphin Anthoine",
    "iso:country":"BE",
    "sg:address":"Rue Seraphin Anthoine 91",
    "sg:city":"Charleroi (mont-sur-marchienne)",
    "sg:classifiers":[
        {
            "category":"Health Services",
            "subcategory":"Health Practitioner",
            "type":"Services"
        }
    ],
    "sg:phone":"+32 71 47 83 86",
    "sg:postcode":"6032",
    "sg:province":"Hainaut",
    "sg:tags":[
        "therapist",
        "speech"
    ],
    "wof:name":"Moine A",
    "wof:placetype":"venue"
},
  "geometry": {"coordinates":[4.4169588089,50.3788146973],"type":"Point"}
}