{
  "type": "Feature",
  "properties": {
    "addr:full":"Vrasenestraat 2 Sint-niklaas (nieuwkerken-waas) Oost-Vlaanderen 9100",
    "addr:housenumber":"2",
    "addr:postcode":"9100",
    "addr:street":"Vrasenestraat;Nieuwkerken-Waas",
    "iso:country":"BE",
    "sg:address":"Vrasenestraat 2",
    "sg:city":"Sint-niklaas (nieuwkerken-waas)",
    "sg:classifiers":[
        {
            "category":"Bars & Pubs",
            "type":"Food & Drink"
        }
    ],
    "sg:phone":"+32 3 766 66 81",
    "sg:postcode":"9100",
    "sg:province":"Oost-Vlaanderen",
    "wof:name":"Witten (bij De)",
    "wof:placetype":"venue"
},
  "geometry": {"coordinates":[4.1783418655,51.1942901611],"type":"Point"}
}