{
  "type": "Feature",
  "properties": {
    "addr:full":"Havelange 71 Aywaille (harz\u00e9) Li\u00e8ge 4920",
    "addr:housenumber":"71",
    "addr:postcode":"4920",
    "addr:street":"Havelange",
    "iso:country":"BE",
    "sg:address":"Havelange 71",
    "sg:city":"Aywaille (harz\u00e9)",
    "sg:classifiers":[
        {
            "category":"Home & Garden",
            "subcategory":"Carpets & Floor Coverings",
            "type":"Retail Goods"
        }
    ],
    "sg:phone":"+32 4 384 89 65",
    "sg:postcode":"4920",
    "sg:province":"Li\u00e8ge",
    "sg:tags":[
        "layer",
        "mosaicists"
    ],
    "wof:name":"Pro-chapes Sprl",
    "wof:placetype":"venue"
},
  "geometry": {"coordinates":[5.7098178864,50.4444274902],"type":"Point"}
}