{
  "type": "Feature",
  "properties": {
    "addr:full":"Rue Haute 219 Brussel/bruxelles Bruxelles-Capitale 1000",
    "addr:housenumber":"219",
    "addr:postcode":"1000",
    "addr:street":"Rue Haute;/",
    "iso:country":"BE",
    "sg:address":"Rue Haute 219",
    "sg:city":"Brussel/bruxelles",
    "sg:classifiers":[
        {
            "category":"Personal",
            "subcategory":"Beauty Salon",
            "type":"Services"
        }
    ],
    "sg:phone":"+32 2 512 03 55",
    "sg:postcode":"1000",
    "sg:province":"Bruxelles-Capitale",
    "sg:tags":[
        "de",
        "coiffure"
    ],
    "wof:name":"Saletzky",
    "wof:placetype":"venue"
},
  "geometry": {"coordinates":[4.348429203,50.8371047974],"type":"Point"}
}