{
  "type": "Feature",
  "properties": {
    "addr:full":"Walburgstraat 54 Sint-niklaas Oost-Vlaanderen 9100",
    "addr:housenumber":"54",
    "addr:postcode":"9100",
    "addr:street":"Walburgstraat",
    "iso:country":"BE",
    "sg:address":"Walburgstraat 54",
    "sg:city":"Sint-niklaas",
    "sg:orig_category":"Avocats and conseillers juridiques",
    "sg:phone":"+32 3 760 17 79",
    "sg:postcode":"9100",
    "sg:province":"Oost-Vlaanderen",
    "wof:name":"Advokatenkantoor Seghers Marc",
    "wof:placetype":"venue"
},
  "geometry": {"coordinates":[4.1473789215,51.1633224487],"type":"Point"}
}