{
  "type": "Feature",
  "properties": {
    "iso:country":"BE",
    "sg:address":"Oostmalsesteenweg 88ba",
    "sg:city":"Ranst",
    "sg:orig_category":"Fruitteelt Groententeelt",
    "sg:phone":"+32 3 480 95 69",
    "sg:postcode":"2520",
    "sg:province":"Antwerpen",
    "wof:name":"Erik Van Goylen",
    "wof:placetype":"venue"
},
  "geometry": {"coordinates":[4.6206798553,51.1704940796],"type":"Point"}
}