{
  "type": "Feature",
  "properties": {
    "iso:country":"BE",
    "sg:address":"Sint-lenaartsbaan 4bb",
    "sg:city":"Brecht",
    "sg:orig_category":"Rundveehouders",
    "sg:phone":"+32 3 313 03 67",
    "sg:postcode":"2960",
    "sg:province":"Antwerpen",
    "wof:name":"Josephus Peeters",
    "wof:placetype":"venue"
},
  "geometry": {"coordinates":[4.656539917,51.3644981384],"type":"Point"}
}