{
  "type": "Feature",
  "properties": {
    "iso:country":"BE",
    "sg:address":"Andr\u00c9 Dumontlaan 236",
    "sg:city":"Genk",
    "sg:orig_category":"Kapsalons",
    "sg:phone":"+32 89 84 47 08",
    "sg:postcode":"3600",
    "sg:province":"Limburg",
    "wof:name":"Coiffure Art Nouveau",
    "wof:placetype":"venue"
},
  "geometry": {"coordinates":[5.538602829,50.9873733521],"type":"Point"}
}