{
  "type": "Feature",
  "properties": {
    "addr:full":"Molemstraat 104 Lummen Limburg 3560",
    "addr:housenumber":"104",
    "addr:postcode":"3560",
    "addr:street":"Molemstraat",
    "iso:country":"BE",
    "sg:address":"Molemstraat 104",
    "sg:city":"Lummen",
    "sg:orig_category":"Woningbouw",
    "sg:phone":"+32 13 52 31 64",
    "sg:postcode":"3560",
    "sg:province":"Limburg",
    "wof:name":"Postelmans-peeters",
    "wof:placetype":"venue"
},
  "geometry": {"coordinates":[5.2146701813,51.0000534058],"type":"Point"}
}