{
  "type": "Feature",
  "properties": {
    "iso:country":"BE",
    "sg:address":"Sint-margrietstraat 19",
    "sg:city":"Gent",
    "sg:classifiers":[
        {
            "category":"Food & Beverages",
            "subcategory":"Fruits & Vegetables",
            "type":"Retail Goods"
        }
    ],
    "sg:phone":"+32 9 225 43 77",
    "sg:postcode":"9000",
    "sg:province":"Oost-Vlaanderen",
    "sg:tags":[
        "l\u00e9gumes"
    ],
    "wof:name":"Etienne Van Wassenhove",
    "wof:placetype":"venue"
},
  "geometry": {"coordinates":[3.7204608917,51.0597953796],"type":"Point"}
}