{
  "type": "Feature",
  "properties": {
    "iso:country":"BE",
    "sg:address":"Charlestonstraat 36",
    "sg:city":"Aalter",
    "sg:orig_category":"Rundveehouders",
    "sg:phone":"+32 9 374 27 71",
    "sg:postcode":"9880",
    "sg:province":"Oost-Vlaanderen",
    "wof:name":"Stefaan Vermeersch",
    "wof:placetype":"venue"
},
  "geometry": {"coordinates":[3.4298870564,51.0926437378],"type":"Point"}
}