{
  "type": "Feature",
  "properties": {
    "addr:full":"Chaussee De Wavre 1490 Bruxelles Bruxelles-Capitale 1160",
    "addr:postcode":"1490;1160",
    "addr:street":"Chaussee De Wavre",
    "iso:country":"BE",
    "sg:address":"Chaussee De Wavre 1490",
    "sg:city":"Bruxelles",
    "sg:classifiers":[
        {
            "category":"Communications",
            "subcategory":"Film & Video Production",
            "type":"Services"
        }
    ],
    "sg:phone":"+32 2 675 05 55",
    "sg:postcode":"1160",
    "sg:province":"Bruxelles-Capitale",
    "sg:tags":[
        "workshop",
        "graphic"
    ],
    "wof:name":"Graphic Mouse S.p.r.l.",
    "wof:placetype":"venue"
},
  "geometry": {"coordinates":[4.4193720818,50.8180007935],"type":"Point"}
}