{
  "type": "Feature",
  "properties": {
    "iso:country":"BE",
    "sg:address":"Rue Frantois Gay 354",
    "sg:city":"Sint-pieters-woluwe/woluwe-saint-pierre",
    "sg:orig_category":"Journaux. Tabac",
    "sg:phone":"+32 2 770 04 08",
    "sg:postcode":"1150",
    "sg:province":"Bruxelles-Capitale",
    "wof:name":"Janssens-leleu",
    "wof:placetype":"venue"
},
  "geometry": {"coordinates":[4.416012764,50.8372001648],"type":"Point"}
}