{
  "type": "Feature",
  "properties": {
    "addr:full":"Pastorijstraat 1a Temse (tielrode) Oost-Vlaanderen 9140",
    "addr:housenumber":"1a",
    "addr:postcode":"9140",
    "addr:street":"Pastorijstraat",
    "iso:country":"BE",
    "sg:address":"Pastorijstraat 1a",
    "sg:city":"Temse (tielrode)",
    "sg:classifiers":[
        {
            "category":"Health Services",
            "subcategory":"Health Practitioner",
            "type":"Services"
        }
    ],
    "sg:phone":"+32 3 711 39 04",
    "sg:postcode":"9140",
    "sg:province":"Oost-Vlaanderen",
    "sg:tags":[
        "psychologist"
    ],
    "wof:name":"Peelman A",
    "wof:placetype":"venue"
},
  "geometry": {"coordinates":[4.1731491089,51.1119613647],"type":"Point"}
}