{
  "type": "Feature",
  "properties": {
    "addr:full":"Dolfijnkaai 2 Kortrijk West-Vlaanderen 8500",
    "addr:housenumber":"2",
    "addr:postcode":"8500",
    "addr:street":"Dolfijnkaai",
    "iso:country":"BE",
    "sg:address":"Dolfijnkaai 2",
    "sg:city":"Kortrijk",
    "sg:classifiers":[
        {
            "category":"Retail",
            "subcategory":"Event Space",
            "type":"Services"
        }
    ],
    "sg:phone":"+32 496 91 63 22",
    "sg:postcode":"8500",
    "sg:province":"West-Vlaanderen",
    "sg:tags":[
        "organisation"
    ],
    "wof:name":"Neon Fun & Ambiance",
    "wof:placetype":"venue"
},
  "geometry": {"coordinates":[3.2642529011,50.8294067383],"type":"Point"}
}