{
  "type": "Feature",
  "properties": {
    "iso:country":"BE",
    "sg:address":"Rue Du Thier 3",
    "sg:city":"Verviers",
    "sg:orig_category":"Charpentes and couvertures",
    "sg:phone":"+32 87 22 16 67",
    "sg:postcode":"4801",
    "sg:province":"Li\u00e8ge",
    "wof:name":"Ascoplan",
    "wof:placetype":"venue"
},
  "geometry": {"coordinates":[5.8897161484,50.5855102539],"type":"Point"}
}