{
  "type": "Feature",
  "properties": {
    "addr:full":"Weggevoerdenstraat 10 Herent Vlaams-Brabant 3020",
    "addr:housenumber":"10",
    "addr:postcode":"3020",
    "addr:street":"Weggevoerdenstraat",
    "iso:country":"BE",
    "sg:address":"Weggevoerdenstraat 10",
    "sg:city":"Herent",
    "sg:orig_category":"Rundveehouders",
    "sg:phone":"+32 16 23 37 08",
    "sg:postcode":"3020",
    "sg:province":"Vlaams-Brabant",
    "wof:name":"Alfons Verhoeft",
    "wof:placetype":"venue"
},
  "geometry": {"coordinates":[4.6791372299,50.9094772339],"type":"Point"}
}