{
  "type": "Feature",
  "properties": {
    "iso:country":"BE",
    "sg:address":"Rue Des Fabriques 2",
    "sg:city":"Obourg",
    "sg:classifiers":[
        {
            "category":"Manufacturing",
            "subcategory":"Building Materials",
            "type":"Manufacturing & Wholesale Goods"
        }
    ],
    "sg:phone":"+32 65 35 81 11",
    "sg:postcode":"7034",
    "sg:province":"Hainaut",
    "sg:tags":[
        "cement"
    ],
    "wof:name":"Ciments D'obourg S.a.",
    "wof:placetype":"venue"
},
  "geometry": {"coordinates":[4.0086159706,50.4765396118],"type":"Point"}
}