{
  "type": "Feature",
  "properties": {
    "addr:full":"Avenue Baron Fallon 28 Namur Namur 5000",
    "addr:housenumber":"28",
    "addr:postcode":"5000",
    "addr:street":"Avenue Baron Fallon",
    "iso:country":"BE",
    "sg:address":"Avenue Baron Fallon 28",
    "sg:city":"Namur",
    "sg:classifiers":[
        {
            "category":"Professional",
            "subcategory":"Lawyer & Legal Services",
            "type":"Services"
        }
    ],
    "sg:phone":"+32 81 43 31 16",
    "sg:postcode":"5000",
    "sg:province":"Namur",
    "wof:name":"Lebrun Pierre",
    "wof:placetype":"venue"
},
  "geometry": {"coordinates":[4.8425431252,50.4540519714],"type":"Point"}
}