{
  "type": "Feature",
  "properties": {
    "iso:country":"BE",
    "sg:address":"Galerie Saint-hubert",
    "sg:city":"Louvain",
    "sg:classifiers":[
        {
            "category":"Shopping",
            "subcategory":"Clothing, Apparel, & Fashions",
            "type":"Retail Goods"
        }
    ],
    "sg:phone":"+32 10 45 49 37",
    "sg:postcode":"1348",
    "sg:province":"Brabant Wallon",
    "sg:tags":[
        "v\u00eatements",
        "pour",
        "dame"
    ],
    "wof:name":"Totem",
    "wof:placetype":"venue"
},
  "geometry": {"coordinates":[4.703690052,50.8793487549],"type":"Point"}
}