{
  "type": "Feature",
  "properties": {
    "addr:full":"Rue G\u00c9n\u00c9ral Buisseret 10 Soignies Hainaut 7060",
    "addr:housenumber":"10",
    "addr:postcode":"7060",
    "addr:street":"Rue Ge\u0301Ne\u0301Ral Buisseret",
    "iso:country":"BE",
    "sg:address":"Rue G\u00c9n\u00c9ral Buisseret 10",
    "sg:city":"Soignies",
    "sg:classifiers":[
        {
            "category":"Arena",
            "subcategory":"Sports Club",
            "type":"Entertainment"
        }
    ],
    "sg:phone":"+32 67 33 24 61",
    "sg:postcode":"7060",
    "sg:province":"Hainaut",
    "sg:tags":[
        "de"
    ],
    "wof:name":"L'egalit\u00c9",
    "wof:placetype":"venue"
},
  "geometry": {"coordinates":[4.0788497925,50.5696258545],"type":"Point"}
}