{
  "type": "Feature",
  "properties": {
    "addr:full":"Pullewouwe 6 Asse Vlaams-Brabant 1730",
    "addr:housenumber":"6",
    "addr:postcode":"1730",
    "addr:street":"Pullewouwe",
    "iso:country":"BE",
    "sg:address":"Pullewouwe 6",
    "sg:city":"Asse",
    "sg:orig_category":"Woningbouw",
    "sg:phone":"+32 2 452 88 74",
    "sg:postcode":"1730",
    "sg:province":"Vlaams-Brabant",
    "wof:name":"Erzeel Marievoet",
    "wof:placetype":"venue"
},
  "geometry": {"coordinates":[4.1646838188,50.9025993347],"type":"Point"}
}