{
  "type": "Feature",
  "properties": {
    "addr:full":"Kliniekstraat 9 Hasselt Limburg 3500",
    "addr:housenumber":"9",
    "addr:postcode":"3500",
    "addr:street":"Kliniekstraat",
    "iso:country":"BE",
    "sg:address":"Kliniekstraat 9",
    "sg:city":"Hasselt",
    "sg:classifiers":[
        {
            "category":"Health Services",
            "subcategory":"Dentist",
            "type":"Services"
        }
    ],
    "sg:phone":"+32 11 27 36 99",
    "sg:postcode":"3500",
    "sg:province":"Limburg",
    "wof:name":"Merchiers Annemie",
    "wof:placetype":"venue"
},
  "geometry": {"coordinates":[5.3424339294,50.9132919312],"type":"Point"}
}