{
  "type": "Feature",
  "properties": {
    "iso:country":"BE",
    "sg:address":"Weg Naar Opoeteren 9 Box 2",
    "sg:city":"Opglabbeek",
    "sg:classifiers":[
        {
            "category":"Shopping",
            "subcategory":"Clothing, Apparel, & Fashions",
            "type":"Retail Goods"
        }
    ],
    "sg:phone":"+32 89 85 22 20",
    "sg:postcode":"3660",
    "sg:province":"Limburg",
    "sg:tags":[
        "underwear",
        "lingerie",
        "-"
    ],
    "wof:name":"Caresse",
    "wof:placetype":"venue"
},
  "geometry": {"coordinates":[5.586616993,51.0445671082],"type":"Point"}
}