{
  "type": "Feature",
  "properties": {
    "iso:country":"BE",
    "sg:address":"Rue De La R\u00c9sistance 164",
    "sg:city":"Remicourt",
    "sg:orig_category":"Quincailleries. Meubles D\u00e9taillants, Am\u00e9nagement de B\u00e2timents et de Cuisines",
    "sg:phone":"+32 19 54 42 32",
    "sg:postcode":"4351",
    "sg:province":"Li\u00e8ge",
    "wof:name":"Dessart",
    "wof:placetype":"venue"
},
  "geometry": {"coordinates":[5.3348469734,50.6955184937],"type":"Point"}
}