{
  "type": "Feature",
  "properties": {
    "iso:country":"BE",
    "sg:address":"Rue Du Ch\u00c9niat 45",
    "sg:city":"Walcourt",
    "sg:orig_category":"Sportclubs",
    "sg:phone":"+32 71 61 28 65",
    "sg:postcode":"5651",
    "sg:province":"Namur",
    "wof:name":"P.c. La Thyria",
    "wof:placetype":"venue"
},
  "geometry": {"coordinates":[4.4332671165,50.2858657837],"type":"Point"}
}