{
  "type": "Feature",
  "properties": {
    "addr:full":"Myosotisstraat 2 Gent Oost-Vlaanderen 9000",
    "addr:housenumber":"2",
    "addr:postcode":"9000",
    "addr:street":"Myosotisstraat;Oost-Vlaanderen",
    "iso:country":"BE",
    "sg:address":"Myosotisstraat 2",
    "sg:city":"Gent",
    "sg:classifiers":[
        {
            "category":"Food & Beverages",
            "subcategory":"Fruits & Vegetables",
            "type":"Retail Goods"
        }
    ],
    "sg:phone":"+32 9 226 43 51",
    "sg:postcode":"9000",
    "sg:province":"Oost-Vlaanderen",
    "sg:tags":[
        "-"
    ],
    "wof:name":"Vershoek Van Der Poorten",
    "wof:placetype":"venue"
},
  "geometry": {"coordinates":[3.7108669281,51.0732574463],"type":"Point"}
}