{
  "type": "Feature",
  "properties": {
    "iso:country":"BE",
    "sg:address":"Vieux Chemin D'ath 199",
    "sg:city":"Tournai (warchin)",
    "sg:classifiers":[
        {
            "category":"Health Services",
            "subcategory":"Doctor",
            "type":"Services"
        }
    ],
    "sg:phone":"+32 69 22 13 14",
    "sg:postcode":"7548",
    "sg:province":"Hainaut",
    "sg:tags":[
        "medicinephysicians",
        "surgeon"
    ],
    "wof:name":"Lecocq E",
    "wof:placetype":"venue"
},
  "geometry": {"coordinates":[3.4255011082,50.6115913391],"type":"Point"}
}