{
  "type": "Feature",
  "properties": {
    "iso:country":"BE",
    "sg:address":"Langveldweg 58",
    "sg:city":"Opglabbeek",
    "sg:orig_category":"Dierenartsen",
    "sg:phone":"+32 89 85 44 24",
    "sg:postcode":"3660",
    "sg:province":"Limburg",
    "wof:name":"Peter Dierickx",
    "wof:placetype":"venue"
},
  "geometry": {"coordinates":[5.5785198212,51.0511741638],"type":"Point"}
}