{
  "type": "Feature",
  "properties": {
    "iso:country":"BE",
    "sg:address":"Chauss\u00c9e De Lodelinsart 21",
    "sg:city":"Charleroi",
    "sg:orig_category":"Bagage and lederwaren",
    "sg:phone":"+32 71 42 20 02",
    "sg:postcode":"6060",
    "sg:province":"Hainaut",
    "wof:name":"Maison Arlequin",
    "wof:placetype":"venue"
},
  "geometry": {"coordinates":[4.4880981445,50.4251937866],"type":"Point"}
}