{
  "type": "Feature",
  "properties": {
    "iso:country":"BE",
    "sg:address":"Avenue Van Nieuwenhuyse 6",
    "sg:city":"Brussels",
    "sg:classifiers":[
        {
            "category":"Banks & Credit Unions",
            "subcategory":"Bank",
            "type":"Services"
        }
    ],
    "sg:postcode":"1160",
    "sg:province":"Bruxelles-Capitale",
    "wof:name":"Cogifi Sa",
    "wof:placetype":"venue"
},
  "geometry": {"coordinates":[4.4193348885,50.8138084412],"type":"Point"}
}