{
  "type": "Feature",
  "properties": {
    "iso:country":"BE",
    "sg:address":"Vieille-voie 15",
    "sg:city":"Libin",
    "sg:orig_category":"Banques and organismes de cr\u00e9dit",
    "sg:phone":"+32 61 65 62 84",
    "sg:postcode":"6890",
    "sg:province":"Luxembourg",
    "wof:name":"Nagelmackers",
    "wof:placetype":"venue"
},
  "geometry": {"coordinates":[5.2302350998,49.9459075928],"type":"Point"}
}