{
  "type": "Feature",
  "properties": {
    "addr:full":"Chauss\u00e9e De Charleroi 118 Anderlues Hainaut 6150",
    "addr:housenumber":"118",
    "addr:postcode":"6150",
    "addr:street":"Chausse\u0301E De Charleroi",
    "iso:country":"BE",
    "sg:address":"Chauss\u00e9e De Charleroi 118",
    "sg:city":"Anderlues",
    "sg:classifiers":[
        {
            "category":"Bakery",
            "type":"Food & Drink"
        }
    ],
    "sg:phone":"+32 71 52 38 53",
    "sg:postcode":"6150",
    "sg:province":"Hainaut",
    "sg:tags":[
        "confectioner",
        "baker"
    ],
    "wof:name":"Czerepaniak D",
    "wof:placetype":"venue"
},
  "geometry": {"coordinates":[4.283053875,50.4059638977],"type":"Point"}
}