{
  "type": "Feature",
  "properties": {
    "iso:country":"BE",
    "sg:address":"Aachener Strasse 62",
    "sg:city":"Eupen",
    "sg:classifiers":[
        {
            "category":"Building & Trades",
            "subcategory":"Cleaning & Sanitation",
            "type":"Services"
        }
    ],
    "sg:phone":"+32 87 56 00 87",
    "sg:postcode":"4700",
    "sg:province":"Li\u00e8ge",
    "sg:tags":[
        "sweep",
        "chimney"
    ],
    "wof:name":"Vondenhoff H",
    "wof:placetype":"venue"
},
  "geometry": {"coordinates":[6.0349202156,50.6345405579],"type":"Point"}
}