{
  "type": "Feature",
  "properties": {
    "iso:country":"BE",
    "sg:address":"Tongersestraat 72",
    "sg:city":"Bilzen",
    "sg:orig_category":"Installation de menuiserie en bois and plastique. Equipement divers pour commerces Gr",
    "sg:phone":"+32 89 50 15 84",
    "sg:postcode":"3740",
    "sg:province":"Limburg",
    "wof:name":"J.c.w. Interieur",
    "wof:placetype":"venue"
},
  "geometry": {"coordinates":[5.5053801537,50.8638877869],"type":"Point"}
}