{
  "type": "Feature",
  "properties": {
    "iso:country":"BE",
    "sg:address":"Quai Godefroid Kurth 10",
    "sg:city":"Li\u00c8ge",
    "sg:orig_category":"Notarissen",
    "sg:phone":"+32 4 343 98 58",
    "sg:postcode":"4020",
    "sg:province":"Li\u00e8ge",
    "wof:name":"Y. Guillaume",
    "wof:placetype":"venue"
},
  "geometry": {"coordinates":[5.5873289108,50.6458053589],"type":"Point"}
}