{
  "type": "Feature",
  "properties": {
    "iso:country":"BE",
    "sg:address":"Gauwerstraat 86",
    "sg:city":"Kortessem",
    "sg:orig_category":"Eleveurs and marchands de porcs",
    "sg:phone":"+32 11 37 76 30",
    "sg:postcode":"3721",
    "sg:province":"Limburg",
    "wof:name":"Johny Gielen",
    "wof:placetype":"venue"
},
  "geometry": {"coordinates":[5.4150509834,50.8702545166],"type":"Point"}
}