{
  "type": "Feature",
  "properties": {
    "iso:country":"BE",
    "sg:address":"Rue De La Station 20",
    "sg:city":"Les Bons Villers",
    "sg:orig_category":"Rundveehouders",
    "sg:phone":"+32 71 84 38 61",
    "sg:postcode":"6210",
    "sg:province":"Hainaut",
    "wof:name":"Michel Ransquin",
    "wof:placetype":"venue"
},
  "geometry": {"coordinates":[4.4131398201,50.5405082703],"type":"Point"}
}