{
  "type": "Feature",
  "properties": {
    "addr:full":"Rue Du Viaduc 38 Elsene/ixelles Bruxelles-Capitale 1050",
    "addr:housenumber":"38",
    "addr:postcode":"1050",
    "addr:street":"Rue Du Viaduc",
    "iso:country":"BE",
    "sg:address":"Rue Du Viaduc 38",
    "sg:city":"Elsene/ixelles",
    "sg:orig_category":"Epiceries",
    "sg:phone":"+32 2 511 70 38",
    "sg:postcode":"1050",
    "sg:province":"Bruxelles-Capitale",
    "wof:name":"Paul Schoriels",
    "wof:placetype":"venue"
},
  "geometry": {"coordinates":[4.3688149452,50.8329391479],"type":"Point"}
}