{
  "type": "Feature",
  "properties": {
    "iso:country":"BE",
    "sg:address":"Dorpsstraat 19b5",
    "sg:city":"Diepenbeek",
    "sg:orig_category":"Experts-comptables",
    "sg:phone":"+32 11 33 21 07",
    "sg:postcode":"3590",
    "sg:province":"Limburg",
    "wof:name":"Yves Poels",
    "wof:placetype":"venue"
},
  "geometry": {"coordinates":[5.4206418991,50.908454895],"type":"Point"}
}