{
  "type": "Feature",
  "properties": {
    "addr:full":"Heidestraat 6ba Bocholt Limburg 3950",
    "addr:housenumber":"6ba",
    "addr:postcode":"3950",
    "addr:street":"Heidestraat",
    "iso:country":"BE",
    "sg:address":"Heidestraat 6ba",
    "sg:city":"Bocholt",
    "sg:orig_category":"Eleveurs and marchands de porcs",
    "sg:phone":"+32 89 47 34 71",
    "sg:postcode":"3950",
    "sg:province":"Limburg",
    "wof:name":"Theodoor Donne",
    "wof:placetype":"venue"
},
  "geometry": {"coordinates":[5.5965237617,51.198059082],"type":"Point"}
}