{
  "type": "Feature",
  "properties": {
    "iso:country":"BE",
    "sg:address":"Mutsaardlaan 78b30",
    "sg:city":"Brussel",
    "sg:orig_category":"Diverse bedrijfsbeheeradviesbureaus",
    "sg:phone":"+32 2 268 62 89",
    "sg:postcode":"1020",
    "sg:province":"Bruxelles-Capitale",
    "wof:name":"A.i.b.p.",
    "wof:placetype":"venue"
},
  "geometry": {"coordinates":[4.3572969437,50.8994674683],"type":"Point"}
}