{
  "type": "Feature",
  "properties": {
    "iso:country":"BE",
    "sg:address":"Rue Du Christ 69",
    "sg:city":"Mouscron",
    "sg:classifiers":[
        {
            "category":"Shopping",
            "subcategory":"Florist",
            "type":"Retail Goods"
        }
    ],
    "sg:phone":"+32 56 33 68 50",
    "sg:postcode":"7700",
    "sg:province":"Hainaut",
    "wof:name":"Christophe Fleurs",
    "wof:placetype":"venue"
},
  "geometry": {"coordinates":[3.2070319653,50.7438278198],"type":"Point"}
}