{
  "type": "Feature",
  "properties": {
    "addr:full":"Mosselmarktstraat 7 Zonnebeke West-Vlaanderen 8980",
    "addr:housenumber":"7",
    "addr:postcode":"8980",
    "addr:street":"Mosselmarktstraat",
    "iso:country":"BE",
    "sg:address":"Mosselmarktstraat 7",
    "sg:city":"Zonnebeke",
    "sg:orig_category":"Woningbouw",
    "sg:phone":"+32 51 77 90 53",
    "sg:postcode":"8980",
    "sg:province":"West-Vlaanderen",
    "wof:name":"Bouwonderneming Bossu",
    "wof:placetype":"venue"
},
  "geometry": {"coordinates":[2.9872550964,50.8730812073],"type":"Point"}
}