{
  "type": "Feature",
  "properties": {
    "addr:full":"Geraardsbergse Steenweg 126 Oosterzele Oost-Vlaanderen 9860",
    "addr:housenumber":"126",
    "addr:postcode":"9860",
    "addr:street":"Steenweg;Oost-Vlaanderen",
    "iso:country":"BE",
    "sg:address":"Geraardsbergse Steenweg 126",
    "sg:city":"Oosterzele",
    "sg:classifiers":[
        {
            "category":"Transit Center",
            "subcategory":"Passenger",
            "type":"Transportation"
        }
    ],
    "sg:phone":"+32 9 362 87 82",
    "sg:postcode":"9860",
    "sg:province":"Oost-Vlaanderen",
    "sg:tags":[
        "sand",
        "gravel"
    ],
    "wof:name":"Bekaert Bvba",
    "wof:placetype":"venue"
},
  "geometry": {"coordinates":[3.8128778934,50.9490814209],"type":"Point"}
}