{
  "type": "Feature",
  "properties": {
    "iso:country":"BE",
    "sg:address":"De Nayerstraat 11ba",
    "sg:city":"Denderleeuw",
    "sg:orig_category":"Activit\u00e9s d\u00b4action sociale sans h\u00e9bergement",
    "sg:phone":"+32 53 66 65 25",
    "sg:postcode":"9470",
    "sg:province":"Oost-Vlaanderen",
    "wof:name":"Vclb Rijkscentrum",
    "wof:placetype":"venue"
},
  "geometry": {"coordinates":[4.0780367851,50.8906936646],"type":"Point"}
}