{
  "type": "Feature",
  "properties": {
    "iso:country":"BE",
    "sg:address":"Hoogstraat 337",
    "sg:city":"Duffel",
    "sg:orig_category":"Producteurs de l\u00e9gumes",
    "sg:phone":"+32 15 31 28 67",
    "sg:postcode":"2570",
    "sg:province":"Antwerpen",
    "wof:name":"Corneel De Bruyn",
    "wof:placetype":"venue"
},
  "geometry": {"coordinates":[4.5426630974,51.0918083191],"type":"Point"}
}