{
  "type": "Feature",
  "properties": {
    "iso:country":"BE",
    "sg:address":"Rue De L'egalit\u00e9 20",
    "sg:city":"Frameries (eugies)",
    "sg:classifiers":[
        {
            "category":"Retail",
            "subcategory":"Repair Shop",
            "type":"Services"
        }
    ],
    "sg:phone":"+32 65 67 78 36",
    "sg:postcode":"7080",
    "sg:province":"Hainaut",
    "sg:tags":[
        "upholsterer"
    ],
    "wof:name":"Fauteuils D'eugies",
    "wof:placetype":"venue"
},
  "geometry": {"coordinates":[3.8884210587,50.3920021057],"type":"Point"}
}