{
  "type": "Feature",
  "properties": {
    "iso:country":"BE",
    "sg:address":"Burg. Van Landeghemstraat 7",
    "sg:city":"Sint-gillis-waas",
    "sg:classifiers":[
        {
            "category":"Arena",
            "subcategory":"Sports Club",
            "type":"Entertainment"
        }
    ],
    "sg:phone":"+32 3 770 73 45",
    "sg:postcode":"9170",
    "sg:province":"Oost-Vlaanderen",
    "sg:tags":[
        "de"
    ],
    "wof:name":"Yukan Kwai Karateclub",
    "wof:placetype":"venue"
},
  "geometry": {"coordinates":[4.1240258217,51.2169113159],"type":"Point"}
}