{
  "type": "Feature",
  "properties": {
    "addr:full":"Boulevard Du Centenaire 88 Chaumont-gistoux Brabant Wallon 1325",
    "addr:housenumber":"88",
    "addr:postcode":"1325",
    "addr:street":"Boulevard Du Centenaire",
    "iso:country":"BE",
    "sg:address":"Boulevard Du Centenaire 88",
    "sg:city":"Chaumont-gistoux",
    "sg:orig_category":"Artsen and specialisten",
    "sg:phone":"+32 10 22 61 35",
    "sg:postcode":"1325",
    "sg:province":"Brabant Wallon",
    "wof:name":"Anne-fr\u00c9d\u00c9rique Hubert",
    "wof:placetype":"venue"
},
  "geometry": {"coordinates":[4.6595492363,50.714050293],"type":"Point"}
}