{
  "type": "Feature",
  "properties": {
    "addr:full":"Gemeentehuisstraat 20 Ninove (meerbeke) Oost-Vlaanderen 9402",
    "addr:housenumber":"20",
    "addr:postcode":"9402",
    "addr:street":"Gemeentehuisstraat",
    "iso:country":"BE",
    "sg:address":"Gemeentehuisstraat 20",
    "sg:city":"Ninove (meerbeke)",
    "sg:classifiers":[
        {
            "category":"Professional",
            "subcategory":"Engineering",
            "type":"Services"
        }
    ],
    "sg:phone":"+32 54 32 04 70",
    "sg:postcode":"9402",
    "sg:province":"Oost-Vlaanderen",
    "sg:tags":[
        "civil",
        "offices-"
    ],
    "wof:name":"D'hauwer J",
    "wof:placetype":"venue"
},
  "geometry": {"coordinates":[4.0395750999,50.8249015808],"type":"Point"}
}