{
  "type": "Feature",
  "properties": {
    "addr:full":"F Timmermanlaan 8 Zoersel Antwerpen 2980",
    "addr:housenumber":"8",
    "addr:postcode":"2980",
    "addr:street":"Timmermanlaan",
    "iso:country":"BE",
    "sg:address":"F Timmermanlaan 8",
    "sg:city":"Zoersel",
    "sg:orig_category":"Installation \u00e9lectrique r\u00e9sidentielle",
    "sg:phone":"+32 477 60 67 28",
    "sg:postcode":"2980",
    "sg:province":"Antwerpen",
    "wof:name":"Belgytra",
    "wof:placetype":"venue"
},
  "geometry": {"coordinates":[4.6541938782,51.2641448975],"type":"Point"}
}