{
  "type": "Feature",
  "properties": {
    "addr:full":"Smisstraat 5 Borgloon Limburg 3840",
    "addr:housenumber":"5",
    "addr:postcode":"3840",
    "addr:street":"Smisstraat",
    "iso:country":"BE",
    "sg:address":"Smisstraat 5",
    "sg:city":"Borgloon",
    "sg:orig_category":"Enseignement maternel and primaire",
    "sg:phone":"+32 12 74 40 24",
    "sg:postcode":"3840",
    "sg:province":"Limburg",
    "wof:name":"Vrije Lagere School",
    "wof:placetype":"venue"
},
  "geometry": {"coordinates":[5.2854800224,50.8141098022],"type":"Point"}
}