{
  "type": "Feature",
  "properties": {
    "iso:country":"BE",
    "sg:address":"Rue Des Bl\u00e9s 12",
    "sg:city":"Waremme",
    "sg:classifiers":[
        {
            "category":"Health Services",
            "subcategory":"Health Practitioner",
            "type":"Services"
        }
    ],
    "sg:phone":"+32 19 32 34 41",
    "sg:postcode":"4300",
    "sg:province":"Li\u00e8ge",
    "sg:tags":[
        "physiotherapist"
    ],
    "wof:name":"Dormal Sandra",
    "wof:placetype":"venue"
},
  "geometry": {"coordinates":[5.2643351555,50.6953201294],"type":"Point"}
}