{
  "type": "Feature",
  "properties": {
    "addr:full":"Sluis 60 Berlare Oost-Vlaanderen 9290",
    "addr:housenumber":"60",
    "addr:postcode":"9290",
    "addr:street":"Sluis",
    "iso:country":"BE",
    "sg:address":"Sluis 60",
    "sg:city":"Berlare",
    "sg:classifiers":[
        {
            "category":"Professional",
            "subcategory":"Accounting & Tax Preparation",
            "type":"Services"
        }
    ],
    "sg:phone":"+32 52 42 69 39",
    "sg:postcode":"9290",
    "sg:province":"Oost-Vlaanderen",
    "sg:tags":[
        "bookkeeper"
    ],
    "wof:name":"Verhelst L",
    "wof:placetype":"venue"
},
  "geometry": {"coordinates":[3.9870500565,51.0205383301],"type":"Point"}
}