{
  "type": "Feature",
  "properties": {
    "addr:full":"Avenue Achille Reisdorff 45 Ukkel/uccle Bruxelles-Capitale 1180",
    "addr:housenumber":"45",
    "addr:postcode":"1180",
    "addr:street":"Avenue Achille Reisdorff;/",
    "iso:country":"BE",
    "sg:address":"Avenue Achille Reisdorff 45",
    "sg:city":"Ukkel/uccle",
    "sg:orig_category":"Agents artistiques. Animations diverses. Enregistrements sonores",
    "sg:phone":"+32 2 376 37 63",
    "sg:postcode":"1180",
    "sg:province":"Bruxelles-Capitale",
    "wof:name":"J.v.p.",
    "wof:placetype":"venue"
},
  "geometry": {"coordinates":[4.3249630928,50.7932548523],"type":"Point"}
}