{
  "type": "Feature",
  "properties": {
    "addr:full":"Kallebeekstraat 3 Boortmeerbeek (hever) Vlaams-Brabant 3191",
    "addr:housenumber":"3",
    "addr:postcode":"3191",
    "addr:street":"Kallebeekstraat",
    "iso:country":"BE",
    "sg:address":"Kallebeekstraat 3",
    "sg:city":"Boortmeerbeek (hever)",
    "sg:classifiers":[
        {
            "category":"Professional",
            "subcategory":"Computer Services",
            "type":"Services"
        }
    ],
    "sg:phone":"+32 15 51 25 33",
    "sg:postcode":"3191",
    "sg:province":"Vlaams-Brabant",
    "sg:tags":[
        "-",
        "processing",
        "data",
        "software"
    ],
    "wof:name":"Mature Technology Bvba",
    "wof:placetype":"venue"
},
  "geometry": {"coordinates":[4.5590229034,50.9864387512],"type":"Point"}
}