{
  "type": "Feature",
  "properties": {
    "iso:country":"BE",
    "sg:address":"Draplei 3",
    "sg:city":"Putte",
    "sg:orig_category":"Producteurs de l\u00e9gumes",
    "sg:phone":"+32 15 75 57 64",
    "sg:postcode":"2580",
    "sg:province":"Antwerpen",
    "wof:name":"Blommaerts Frans & Rene",
    "wof:placetype":"venue"
},
  "geometry": {"coordinates":[4.6016697884,51.0732383728],"type":"Point"}
}