{
  "type": "Feature",
  "properties": {
    "addr:full":"Heilig Bloedstraat 19 Hoogstraten Antwerpen 2320",
    "addr:housenumber":"19",
    "addr:postcode":"2320",
    "addr:street":"Heilig Bloedstraat",
    "iso:country":"BE",
    "sg:address":"Heilig Bloedstraat 19",
    "sg:city":"Hoogstraten",
    "sg:orig_category":"Producteurs de l\u00e9gumes",
    "sg:phone":"+32 3 314 75 90",
    "sg:postcode":"2320",
    "sg:province":"Antwerpen",
    "wof:name":"Josephus Hermans",
    "wof:placetype":"venue"
},
  "geometry": {"coordinates":[4.7606878281,51.3936080933],"type":"Point"}
}