{
  "type": "Feature",
  "properties": {
    "addr:full":"Plasstraat 15 Stabroek (hoevenen) Antwerpen 2940",
    "addr:housenumber":"15",
    "addr:postcode":"2940",
    "addr:street":"Plasstraat",
    "iso:country":"BE",
    "sg:address":"Plasstraat 15",
    "sg:city":"Stabroek (hoevenen)",
    "sg:classifiers":[
        {
            "category":"Building & Trades",
            "subcategory":"Cleaning & Sanitation",
            "type":"Services"
        }
    ],
    "sg:phone":"+32 3 665 04 04",
    "sg:postcode":"2940",
    "sg:province":"Antwerpen",
    "sg:tags":[
        "janitor"
    ],
    "wof:name":"Acs Cleaning Services",
    "wof:placetype":"venue"
},
  "geometry": {"coordinates":[4.4108901024,51.3036956787],"type":"Point"}
}