{
  "type": "Feature",
  "properties": {
    "addr:full":"Chemin De Moustier 54 Namur Namur 5020",
    "addr:housenumber":"54",
    "addr:postcode":"5020",
    "addr:street":"Chemin De Moustier",
    "iso:country":"BE",
    "sg:address":"Chemin De Moustier 54",
    "sg:city":"Namur",
    "sg:orig_category":"Gespecialiseerde residenti\u00eble bouw",
    "sg:phone":"+32 81 56 05 07",
    "sg:postcode":"5020",
    "sg:province":"Namur",
    "wof:name":"F. Massart",
    "wof:placetype":"venue"
},
  "geometry": {"coordinates":[4.7952418327,50.4352035522],"type":"Point"}
}