{
  "type": "Feature",
  "properties": {
    "addr:full":"Dr\u00c8ve De L'arc-en-ciel 98 Arlon Luxembourg 6700",
    "addr:housenumber":"98",
    "addr:postcode":"6700",
    "addr:street":"Dre\u0300Ve De L'Arc-En-Ciel",
    "iso:country":"BE",
    "sg:address":"Dr\u00c8ve De L'arc-en-ciel 98",
    "sg:city":"Arlon",
    "sg:orig_category":"Overheidsdiensten",
    "sg:phone":"+32 63 23 18 65",
    "sg:postcode":"6700",
    "sg:province":"Luxembourg",
    "wof:name":"Centre De D\u00c9veloppement D' Id\u00c9lux",
    "wof:placetype":"venue"
},
  "geometry": {"coordinates":[5.7870368958,49.6754684448],"type":"Point"}
}