{
  "type": "Feature",
  "properties": {
    "iso:country":"BE",
    "sg:address":"Gistelse Steenweg 204",
    "sg:city":"Brugge",
    "sg:orig_category":"Boucheries. Fruits and l\u00e9gumes",
    "sg:phone":"+32 50 38 73 90",
    "sg:postcode":"8200",
    "sg:province":"West-Vlaanderen",
    "wof:name":"Martin Huys",
    "wof:placetype":"venue"
},
  "geometry": {"coordinates":[3.1986079216,51.2010955811],"type":"Point"}
}