{
  "type": "Feature",
  "properties": {
    "addr:full":"Kortrijksesteenweg 686 Gent Oost-Vlaanderen 9000",
    "addr:housenumber":"686",
    "addr:postcode":"9000",
    "addr:street":"Kortrijksesteenweg;Oost-Vlaanderen",
    "iso:country":"BE",
    "sg:address":"Kortrijksesteenweg 686",
    "sg:city":"Gent",
    "sg:classifiers":[
        {
            "category":"Health Services",
            "subcategory":"Doctor",
            "type":"Services"
        }
    ],
    "sg:phone":"+32 9 221 66 03",
    "sg:postcode":"9000",
    "sg:province":"Oost-Vlaanderen",
    "sg:tags":[
        "medicinephysicians",
        "surgeon"
    ],
    "wof:name":"Bonte Jan",
    "wof:placetype":"venue"
},
  "geometry": {"coordinates":[3.71230793,51.0296936035],"type":"Point"}
}