{
  "type": "Feature",
  "properties": {
    "addr:full":"Meensesteenweg 222 Izegem West-Vlaanderen 8870",
    "addr:housenumber":"222",
    "addr:postcode":"8870",
    "addr:street":"Meensesteenweg",
    "iso:country":"BE",
    "sg:address":"Meensesteenweg 222",
    "sg:city":"Izegem",
    "sg:classifiers":[
        {
            "category":"Health Services",
            "subcategory":"Health Practitioner",
            "type":"Services"
        }
    ],
    "sg:phone":"+32 51 30 79 11",
    "sg:postcode":"8870",
    "sg:province":"West-Vlaanderen",
    "sg:tags":[
        "physiotherapist"
    ],
    "wof:name":"Poleyn Domien",
    "wof:placetype":"venue"
},
  "geometry": {"coordinates":[3.1918160915,50.901222229],"type":"Point"}
}