{
  "type": "Feature",
  "properties": {
    "addr:full":"Ankerstraat 88 Sint-niklaas Oost-Vlaanderen 9100",
    "addr:housenumber":"88",
    "addr:postcode":"9100",
    "addr:street":"Ankerstraat",
    "iso:country":"BE",
    "sg:address":"Ankerstraat 88",
    "sg:city":"Sint-niklaas",
    "sg:orig_category":"Tijdelijke werkgelegenheid and uitzendkantoren",
    "sg:phone":"+32 3 765 98 63",
    "sg:postcode":"9100",
    "sg:province":"Oost-Vlaanderen",
    "wof:name":"T Interim",
    "wof:placetype":"venue"
},
  "geometry": {"coordinates":[4.1474208832,51.1670188904],"type":"Point"}
}