{
  "type": "Feature",
  "properties": {
    "addr:full":"Scheidingsstraat 1 Wingene West-Vlaanderen 8750",
    "addr:housenumber":"1",
    "addr:postcode":"8750",
    "addr:street":"Scheidingsstraat",
    "iso:country":"BE",
    "sg:address":"Scheidingsstraat 1",
    "sg:city":"Wingene",
    "sg:classifiers":[
        {
            "category":"Manufacturing",
            "subcategory":"Metals",
            "type":"Manufacturing & Wholesale Goods"
        }
    ],
    "sg:phone":"+32 479 63 94 65",
    "sg:postcode":"8750",
    "sg:province":"West-Vlaanderen",
    "sg:tags":[
        "ironwork"
    ],
    "wof:name":"H.w.p.",
    "wof:placetype":"venue"
},
  "geometry": {"coordinates":[3.3437850475,51.0592575073],"type":"Point"}
}