{
  "type": "Feature",
  "properties": {
    "iso:country":"BE",
    "sg:address":"Pont D'ile 45",
    "sg:city":"Li\u00c8ge",
    "sg:orig_category":"Boekhandels",
    "sg:phone":"+32 4 223 24 02",
    "sg:postcode":"4000",
    "sg:province":"Li\u00e8ge",
    "wof:name":"Maxi Livres",
    "wof:placetype":"venue"
},
  "geometry": {"coordinates":[5.5713429451,50.6422920227],"type":"Point"}
}