{
  "type": "Feature",
  "properties": {
    "iso:country":"BE",
    "sg:address":"Kasteelstraat 34",
    "sg:city":"Temse",
    "sg:orig_category":"Solariums",
    "sg:phone":"+32 3 771 02 76",
    "sg:postcode":"9140",
    "sg:province":"Oost-Vlaanderen",
    "wof:name":"Hilde",
    "wof:placetype":"venue"
},
  "geometry": {"coordinates":[4.2161860466,51.124622345],"type":"Point"}
}