{
  "type": "Feature",
  "properties": {
    "iso:country":"BE",
    "sg:address":"Pastoor Frederickxstraat 9",
    "sg:city":"Lummen",
    "sg:classifiers":[
        {
            "category":"Education",
            "subcategory":"School",
            "type":"Public Place"
        }
    ],
    "sg:phone":"+32 13 52 10 07",
    "sg:postcode":"3560",
    "sg:province":"Limburg",
    "sg:tags":[
        "secondary"
    ],
    "wof:name":"Instituut Onbevlekt Hart Van Maria",
    "wof:placetype":"venue"
},
  "geometry": {"coordinates":[5.1944937706,50.9859733582],"type":"Point"}
}