{
  "type": "Feature",
  "properties": {
    "addr:full":"Rue Des Remparts 6 Vis\u00c9 Li\u00e8ge 4600",
    "addr:housenumber":"6",
    "addr:postcode":"4600",
    "addr:street":"Rue Des Remparts",
    "iso:country":"BE",
    "sg:address":"Rue Des Remparts 6",
    "sg:city":"Vis\u00c9",
    "sg:classifiers":[
        {
            "category":"Shopping",
            "subcategory":"Clothing, Apparel, & Fashions",
            "type":"Retail Goods"
        }
    ],
    "sg:phone":"+32 4 379 80 02",
    "sg:postcode":"4600",
    "sg:province":"Li\u00e8ge",
    "sg:tags":[
        "v\u00eatements",
        "pour",
        "dame"
    ],
    "wof:name":"Boutique Marithe",
    "wof:placetype":"venue"
},
  "geometry": {"coordinates":[5.6955771446,50.7355537415],"type":"Point"}
}