{
  "type": "Feature",
  "properties": {
    "addr:full":"Chauss\u00e9e D'ixelles 27c Bruxelles Bruxelles-Capitale 1000",
    "addr:housenumber":"27c",
    "addr:postcode":"1000",
    "addr:street":"Chausse\u0301E D'Ixelles",
    "iso:country":"BE",
    "sg:address":"Chauss\u00e9e D'ixelles 27c",
    "sg:city":"Bruxelles",
    "sg:classifiers":[
        {
            "category":"Food & Beverages",
            "subcategory":"Fruits & Vegetables",
            "type":"Retail Goods"
        }
    ],
    "sg:phone":"+32 2 640 60 16",
    "sg:postcode":"1000",
    "sg:province":"Bruxelles-Capitale",
    "sg:tags":[
        "-"
    ],
    "wof:name":"Tesay",
    "wof:placetype":"venue"
},
  "geometry": {"coordinates":[4.3408322334,50.8320045471],"type":"Point"}
}