{
  "type": "Feature",
  "properties": {
    "iso:country":"BE",
    "sg:address":"Rector De Ramstraat 50",
    "sg:city":"Nijlen",
    "sg:orig_category":"Huisdieren and benodigdheden",
    "sg:phone":"+32 3 411 02 55",
    "sg:postcode":"2560",
    "sg:province":"Antwerpen",
    "wof:name":"Wijns",
    "wof:placetype":"venue"
},
  "geometry": {"coordinates":[4.6775078773,51.1586799622],"type":"Point"}
}