{
  "type": "Feature",
  "properties": {
    "addr:full":"Albert I Laan 177 Nieuwpoort West-Vlaanderen 8620",
    "addr:housenumber":"177",
    "addr:postcode":"8620",
    "addr:street":"Albert I Laan",
    "iso:country":"BE",
    "sg:address":"Albert I Laan 177",
    "sg:city":"Nieuwpoort",
    "sg:classifiers":[
        {
            "category":"Food & Beverages",
            "subcategory":"Chocolate",
            "type":"Retail Goods"
        }
    ],
    "sg:phone":"+32 58 23 48 43",
    "sg:postcode":"8620",
    "sg:province":"West-Vlaanderen",
    "sg:tags":[
        "confectionery",
        "-"
    ],
    "wof:name":"Bonbon Karamel",
    "wof:placetype":"venue"
},
  "geometry": {"coordinates":[2.7182519436,51.1491699219],"type":"Point"}
}