{
  "type": "Feature",
  "properties": {
    "addr:full":"Strombeeksesteenweg 34 Vilvoorde Vlaams-Brabant 1800",
    "addr:housenumber":"34",
    "addr:postcode":"1800",
    "addr:street":"Strombeeksesteenweg",
    "iso:country":"BE",
    "sg:address":"Strombeeksesteenweg 34",
    "sg:city":"Vilvoorde",
    "sg:orig_category":"Opslagvoorzieningen",
    "sg:phone":"+32 2 263 05 58",
    "sg:postcode":"1800",
    "sg:province":"Vlaams-Brabant",
    "wof:name":"Merak",
    "wof:placetype":"venue"
},
  "geometry": {"coordinates":[4.3751888275,50.9046669006],"type":"Point"}
}