{
  "type": "Feature",
  "properties": {
    "addr:full":"Rue Du Pairay 43 Seraing Li\u00e8ge 4100",
    "addr:housenumber":"43",
    "addr:postcode":"4100",
    "addr:street":"Rue Du Pairay",
    "iso:country":"BE",
    "sg:address":"Rue Du Pairay 43",
    "sg:city":"Seraing",
    "sg:orig_category":"Services de t\u00e9l\u00e9communications. Mobistar Centres",
    "sg:phone":"+32 4 338 38 47",
    "sg:postcode":"4100",
    "sg:province":"Li\u00e8ge",
    "wof:name":"Mobistar Center Seraing",
    "wof:placetype":"venue"
},
  "geometry": {"coordinates":[5.5113759041,50.5976409912],"type":"Point"}
}