{
  "type": "Feature",
  "properties": {
    "iso:country":"BE",
    "sg:address":"Avenue Des Etangs 148",
    "sg:city":"Wemmel/wemmel",
    "sg:orig_category":"Installation \u00e9lectrique r\u00e9sidentielle",
    "sg:phone":"+32 2 461 15 01",
    "sg:postcode":"1780",
    "sg:province":"Vlaams-Brabant",
    "wof:name":"Freddy Callebaut",
    "wof:placetype":"venue"
},
  "geometry": {"coordinates":[4.3051190376,50.9019737244],"type":"Point"}
}