{
  "type": "Feature",
  "properties": {
    "addr:full":"Rue Aux Foires 126 Florennes (ros\u00e9e) Namur 5620",
    "addr:housenumber":"126",
    "addr:postcode":"5620",
    "addr:street":"Rue Aux Foires",
    "iso:country":"BE",
    "sg:address":"Rue Aux Foires 126",
    "sg:city":"Florennes (ros\u00e9e)",
    "sg:classifiers":[
        {
            "category":"Personal",
            "subcategory":"Beauty Salon",
            "type":"Services"
        }
    ],
    "sg:phone":"+32 82 68 85 69",
    "sg:postcode":"5620",
    "sg:province":"Namur",
    "sg:tags":[
        "lady",
        "-",
        "hairdressing"
    ],
    "wof:name":"B\u00e9atrice (coiffure)",
    "wof:placetype":"venue"
},
  "geometry": {"coordinates":[4.6872329712,50.2324943542],"type":"Point"}
}