{
  "type": "Feature",
  "properties": {
    "iso:country":"BE",
    "sg:address":"Avenue De Berlin 247",
    "sg:city":"Mons",
    "sg:orig_category":"Openbare veiligheid",
    "sg:phone":"+32 65 44 92 11",
    "sg:postcode":"7010",
    "wof:name":"Police F\u00c9d\u00c9rale/federale Politie",
    "wof:placetype":"venue"
},
  "geometry": {"coordinates":[3.9827299118,50.5000114441],"type":"Point"}
}