{
  "type": "Feature",
  "properties": {
    "iso:country":"BE",
    "sg:address":"Place Du Bailli 3",
    "sg:city":"Neupre",
    "sg:orig_category":"Sportcentra",
    "sg:phone":"+32 4 371 38 90",
    "sg:postcode":"4121",
    "sg:province":"Li\u00e8ge",
    "wof:name":"Colas M",
    "wof:placetype":"venue"
},
  "geometry": {"coordinates":[5.4816398621,50.541721344],"type":"Point"}
}