{
  "type": "Feature",
  "properties": {
    "iso:country":"BE",
    "sg:address":"Gasthuisstraat 4",
    "sg:city":"Temse",
    "sg:orig_category":"Bloemen and planten",
    "sg:phone":"+32 3 771 13 96",
    "sg:postcode":"9140",
    "sg:province":"Oost-Vlaanderen",
    "wof:name":"Meeus M",
    "wof:placetype":"venue"
},
  "geometry": {"coordinates":[4.2131299973,51.1279449463],"type":"Point"}
}