{
  "type": "Feature",
  "properties": {
    "addr:full":"Klemhoutstraat 124 Zottegem Oost-Vlaanderen 9620",
    "addr:housenumber":"124",
    "addr:postcode":"9620",
    "addr:street":"Klemhoutstraat",
    "iso:country":"BE",
    "sg:address":"Klemhoutstraat 124",
    "sg:city":"Zottegem",
    "sg:orig_category":"Rundveehouders",
    "sg:phone":"+32 9 360 33 20",
    "sg:postcode":"9620",
    "sg:province":"Oost-Vlaanderen",
    "wof:name":"Andre Van Ruyskensvelde",
    "wof:placetype":"venue"
},
  "geometry": {"coordinates":[3.8112111092,50.871181488],"type":"Point"}
}