{
  "type": "Feature",
  "properties": {
    "addr:full":"A.b.-straat 1 Mechelen Antwerpen 2800",
    "addr:housenumber":"1",
    "addr:postcode":"2800",
    "addr:street":"A.B.-Straat",
    "iso:country":"BE",
    "sg:address":"A.b.-straat 1",
    "sg:city":"Mechelen",
    "sg:orig_category":"Antiek",
    "sg:phone":"+32 15 20 29 47",
    "sg:postcode":"2800",
    "sg:province":"Antwerpen",
    "wof:name":"De Vijgenboom",
    "wof:placetype":"venue"
},
  "geometry": {"coordinates":[4.4771399498,51.0303192139],"type":"Point"}
}