{
  "type": "Feature",
  "properties": {
    "addr:full":"Vijverstraat 1 Brecht (sint-job-in-'t Goor) Antwerpen 2960",
    "addr:housenumber":"1",
    "addr:postcode":"2960",
    "addr:street":"Vijverstraat;' T Goor",
    "iso:country":"BE",
    "sg:address":"Vijverstraat 1",
    "sg:city":"Brecht (sint-job-in-'t Goor)",
    "sg:classifiers":[
        {
            "category":"Arts & Performance",
            "subcategory":"Symphony",
            "type":"Entertainment"
        }
    ],
    "sg:phone":"+32 3 636 19 00",
    "sg:postcode":"2960",
    "sg:province":"Antwerpen",
    "sg:tags":[
        "orchestra"
    ],
    "wof:name":"Rico Zoroh Band & Nicole",
    "wof:placetype":"venue"
},
  "geometry": {"coordinates":[4.5659298897,51.2962493896],"type":"Point"}
}