{
  "type": "Feature",
  "properties": {
    "iso:country":"BE",
    "sg:address":"Balendijk 5-131",
    "sg:city":"Lommel",
    "sg:orig_category":"Imitation jewelry - Mfg.& Whol.",
    "sg:phone":"+32 11 55 37 37",
    "sg:postcode":"3920",
    "sg:province":"Limburg",
    "wof:name":"Creemers",
    "wof:placetype":"venue"
},
  "geometry": {"coordinates":[5.3073878288,51.2247467041],"type":"Point"}
}