{
  "type": "Feature",
  "properties": {
    "addr:full":"Rue L\u00c9on Evrard 5 Grez-doiceau Brabant Wallon 1390",
    "addr:housenumber":"5",
    "addr:postcode":"1390",
    "addr:street":"Rue Le\u0301On Evrard",
    "iso:country":"BE",
    "sg:address":"Rue L\u00c9on Evrard 5",
    "sg:city":"Grez-doiceau",
    "sg:orig_category":"Eleveurs and marchands de porcs. Eleveurs de bovins",
    "sg:phone":"+32 10 84 42 29",
    "sg:postcode":"1390",
    "sg:province":"Brabant Wallon",
    "wof:name":"Paul Ballieux",
    "wof:placetype":"venue"
},
  "geometry": {"coordinates":[4.6932320595,50.7602233887],"type":"Point"}
}