{
  "type": "Feature",
  "properties": {
    "addr:full":"Rue De Velupont 19 Braives (ville-en-hesbaye) Li\u00e8ge 4260",
    "addr:housenumber":"19",
    "addr:postcode":"4260",
    "addr:street":"Rue De Velupont;Ville-En-Hesbaye",
    "iso:country":"BE",
    "sg:address":"Rue De Velupont 19",
    "sg:city":"Braives (ville-en-hesbaye)",
    "sg:classifiers":[
        {
            "category":"Building & Trades",
            "subcategory":"Cleaning & Sanitation",
            "type":"Services"
        }
    ],
    "sg:phone":"+32 19 69 81 78",
    "sg:postcode":"4260",
    "sg:province":"Li\u00e8ge",
    "sg:tags":[
        "cleaner",
        "window"
    ],
    "wof:name":"Grimpret M",
    "wof:placetype":"venue"
},
  "geometry": {"coordinates":[5.1177811623,50.6223754883],"type":"Point"}
}