{
  "type": "Feature",
  "properties": {
    "addr:full":"Asterstraat 7 Knokke-heist (knokke) West-Vlaanderen 8300",
    "addr:housenumber":"7",
    "addr:postcode":"8300",
    "addr:street":"Asterstraat",
    "iso:country":"BE",
    "sg:address":"Asterstraat 7",
    "sg:city":"Knokke-heist (knokke)",
    "sg:classifiers":[
        {
            "category":"Home & Garden",
            "subcategory":"Hardware",
            "type":"Retail Goods"
        }
    ],
    "sg:phone":"+32 50 62 14 98",
    "sg:postcode":"8300",
    "sg:province":"West-Vlaanderen",
    "sg:tags":[
        "gate",
        "opener",
        "door",
        "automatic"
    ],
    "wof:name":"A.d.s. Security Bvba",
    "wof:placetype":"venue"
},
  "geometry": {"coordinates":[3.275001049,51.3408622742],"type":"Point"}
}