{
  "type": "Feature",
  "properties": {
    "iso:country":"BE",
    "sg:address":"Heymansdries 28",
    "sg:city":"Sint-genesius-rode/rhode-saint-genese",
    "sg:orig_category":"Artistes ind\u00e9pendants",
    "sg:phone":"+32 2 380 97 37",
    "sg:postcode":"1640",
    "sg:province":"Vlaams-Brabant",
    "wof:name":"Jorgen Missotten",
    "wof:placetype":"venue"
},
  "geometry": {"coordinates":[4.3613262177,50.7370071411],"type":"Point"}
}