{
  "type": "Feature",
  "properties": {
    "iso:country":"BE",
    "sg:address":"Kalkenstraat 21a",
    "sg:city":"Buggenhout",
    "sg:classifiers":[
        {
            "category":"Farming",
            "subcategory":"Poultry Farm",
            "type":"Manufacturing & Wholesale Goods"
        }
    ],
    "sg:phone":"+32 52 33 28 46",
    "sg:postcode":"9255",
    "sg:province":"Oost-Vlaanderen",
    "sg:tags":[
        "rabbit",
        "slaughterhouse"
    ],
    "wof:name":"Vanifood Bvba",
    "wof:placetype":"venue"
},
  "geometry": {"coordinates":[4.1991620064,51.0016899109],"type":"Point"}
}