{
  "type": "Feature",
  "properties": {
    "addr:full":"Ommegangstraat 4 Geraardsbergen Oost-Vlaanderen 9500",
    "addr:housenumber":"4",
    "addr:postcode":"9500",
    "addr:street":"Ommegangstraat",
    "iso:country":"BE",
    "sg:address":"Ommegangstraat 4",
    "sg:city":"Geraardsbergen",
    "sg:orig_category":"Sportclubs Sportterreinen and installaties behalve sportcentra",
    "sg:phone":"+32 54 50 04 44",
    "sg:postcode":"9500",
    "sg:province":"Oost-Vlaanderen",
    "wof:name":"Rapide Club Ophasselt",
    "wof:placetype":"venue"
},
  "geometry": {"coordinates":[3.8843801022,50.7716445923],"type":"Point"}
}