{
  "type": "Feature",
  "properties": {
    "addr:full":"Place Cardinal Mercier 36 Rixensart Brabant Wallon 1330",
    "addr:housenumber":"36",
    "addr:postcode":"1330",
    "addr:street":"Place Cardinal Mercier;Wallon",
    "iso:country":"BE",
    "sg:address":"Place Cardinal Mercier 36",
    "sg:city":"Rixensart",
    "sg:classifiers":[
        {
            "category":"Bakery",
            "type":"Food & Drink"
        }
    ],
    "sg:phone":"+32 2 653 72 40",
    "sg:postcode":"1330",
    "sg:province":"Brabant Wallon",
    "sg:tags":[
        "confectioner",
        "baker"
    ],
    "wof:name":"Lois R",
    "wof:placetype":"venue"
},
  "geometry": {"coordinates":[4.5097970963,50.7094917297],"type":"Point"}
}