{
  "type": "Feature",
  "properties": {
    "addr:full":"Avenue Eug\u00e8ne Mascaux 697 Charleroi (marcinelle) Hainaut 6001",
    "addr:housenumber":"697",
    "addr:postcode":"6001",
    "addr:street":"Avenue Euge\u0300Ne Mascaux",
    "iso:country":"BE",
    "sg:address":"Avenue Eug\u00e8ne Mascaux 697",
    "sg:city":"Charleroi (marcinelle)",
    "sg:classifiers":[
        {
            "category":"Personal",
            "subcategory":"Psychics & Astrologers",
            "type":"Services"
        }
    ],
    "sg:phone":"+32 71 47 21 73",
    "sg:postcode":"6001",
    "sg:province":"Hainaut",
    "sg:tags":[
        "astrology"
    ],
    "wof:name":"Monica",
    "wof:placetype":"venue"
},
  "geometry": {"coordinates":[4.4315299988,50.3852462769],"type":"Point"}
}