{
  "type": "Feature",
  "properties": {
    "addr:full":"Liersesteenweg 97 A Heist-op-den-berg Antwerpen 2220",
    "addr:housenumber":"97 a",
    "addr:postcode":"2220",
    "addr:street":"Liersesteenweg",
    "iso:country":"BE",
    "sg:address":"Liersesteenweg 97 A",
    "sg:city":"Heist-op-den-berg",
    "sg:classifiers":[
        {
            "category":"Restaurant",
            "type":"Food & Drink"
        }
    ],
    "sg:phone":"+32 15 22 09 09",
    "sg:postcode":"2220",
    "sg:province":"Antwerpen",
    "wof:name":"Eethuis \u00b4t Goor",
    "wof:placetype":"venue"
},
  "geometry": {"coordinates":[4.7418208122,51.0461006165],"type":"Point"}
}