{
  "type": "Feature",
  "properties": {
    "addr:full":"Rue J.-b. Decock 5 Sint-jans-molenbeek/molenbeek-saint-jean Bruxelles-Capitale 1080",
    "addr:housenumber":"5",
    "addr:postcode":"1080",
    "addr:street":"Rue J.-B. Decock",
    "iso:country":"BE",
    "sg:address":"Rue J.-b. Decock 5",
    "sg:city":"Sint-jans-molenbeek/molenbeek-saint-jean",
    "sg:orig_category":"Agences de relations publiques",
    "sg:phone":"+32 2 413 03 71",
    "sg:postcode":"1080",
    "sg:province":"Bruxelles-Capitale",
    "wof:name":"Challenger Organisation",
    "wof:placetype":"venue"
},
  "geometry": {"coordinates":[4.328417778,50.8513450623],"type":"Point"}
}