{
  "type": "Feature",
  "properties": {
    "addr:full":"Venstraat 29 Wuustwezel Antwerpen 2990",
    "addr:housenumber":"29",
    "addr:postcode":"2990",
    "addr:street":"Venstraat",
    "iso:country":"BE",
    "sg:address":"Venstraat 29",
    "sg:city":"Wuustwezel",
    "sg:classifiers":[
        {
            "category":"Building & Trades",
            "subcategory":"Construction",
            "type":"Services"
        }
    ],
    "sg:phone":"+32 3 663 52 13",
    "sg:postcode":"2990",
    "sg:province":"Antwerpen",
    "sg:tags":[
        "stucco",
        "contractor"
    ],
    "wof:name":"Van Hoeydonck E & W Bvba",
    "wof:placetype":"venue"
},
  "geometry": {"coordinates":[4.5414991379,51.3522872925],"type":"Point"}
}