{
  "type": "Feature",
  "properties": {
    "addr:full":"Bodemstraat 5 Riemst Limburg 3770",
    "addr:housenumber":"5",
    "addr:postcode":"3770",
    "addr:street":"Bodemstraat",
    "iso:country":"BE",
    "sg:address":"Bodemstraat 5",
    "sg:city":"Riemst",
    "sg:orig_category":"Fleurs and plantes",
    "sg:phone":"+32 12 45 57 06",
    "sg:postcode":"3770",
    "sg:province":"Limburg",
    "wof:name":"Bloemenhof Floragie",
    "wof:placetype":"venue"
},
  "geometry": {"coordinates":[5.5969901085,50.8109016418],"type":"Point"}
}