{
  "type": "Feature",
  "properties": {
    "addr:full":"Rue Du Dobbelenberg 88ba Brussel/bruxelles Bruxelles-Capitale 1130",
    "addr:housenumber":"88ba",
    "addr:postcode":"1130",
    "addr:street":"Rue Du Dobbelenberg;/",
    "iso:country":"BE",
    "sg:address":"Rue Du Dobbelenberg 88ba",
    "sg:city":"Brussel/bruxelles",
    "sg:orig_category":"D\u00e9chets and d\u00e9bris Gr",
    "sg:phone":"+32 2 216 93 74",
    "sg:postcode":"1130",
    "sg:province":"Bruxelles-Capitale",
    "wof:name":"G.a. Trading",
    "wof:placetype":"venue"
},
  "geometry": {"coordinates":[4.4196109772,50.903213501],"type":"Point"}
}