{
  "type": "Feature",
  "properties": {
    "addr:full":"Stationsstraat 146d Aalter Oost-Vlaanderen 9880",
    "addr:housenumber":"146d",
    "addr:postcode":"9880",
    "addr:street":"Stationsstraat",
    "iso:country":"BE",
    "sg:address":"Stationsstraat 146d",
    "sg:city":"Aalter",
    "sg:classifiers":[
        {
            "category":"Sports & Exercise",
            "subcategory":"Sports Center",
            "type":"Entertainment"
        }
    ],
    "sg:phone":"+32 9 374 75 59",
    "sg:postcode":"9880",
    "sg:province":"Oost-Vlaanderen",
    "sg:tags":[
        "de",
        "fitness"
    ],
    "wof:name":"Action Unlimited-pfto/personal Trainers",
    "wof:placetype":"venue"
},
  "geometry": {"coordinates":[3.4480550289,51.088508606],"type":"Point"}
}