{
  "type": "Feature",
  "properties": {
    "iso:country":"BE",
    "sg:address":"Rozenlaan 14",
    "sg:city":"Schilde",
    "sg:orig_category":"Artsen and specialisten",
    "sg:phone":"+32 3 353 37 82",
    "sg:postcode":"2970",
    "sg:province":"Antwerpen",
    "wof:name":"Monique M.l. Janssens",
    "wof:placetype":"venue"
},
  "geometry": {"coordinates":[4.5601420403,51.2392921448],"type":"Point"}
}