{
  "type": "Feature",
  "properties": {
    "iso:country":"BE",
    "sg:address":"Katwilgweg 9",
    "sg:city":"Antwerpen",
    "sg:orig_category":"Entretien and r\u00e9parations de voitures. V\u00e9hicules automobiles",
    "sg:phone":"+32 3 254 06 10",
    "sg:postcode":"2050",
    "sg:province":"Antwerpen",
    "wof:name":"Carrosserie Jego",
    "wof:placetype":"venue"
},
  "geometry": {"coordinates":[4.354268074,51.2194023132],"type":"Point"}
}