{
  "type": "Feature",
  "properties": {
    "addr:full":"Nieuwe Steenweg 41 Heers Limburg 3870",
    "addr:housenumber":"41",
    "addr:postcode":"3870",
    "addr:street":"Nieuwe Steenweg",
    "iso:country":"BE",
    "sg:address":"Nieuwe Steenweg 41",
    "sg:city":"Heers",
    "sg:orig_category":"S\u00e9lection de personnel and placement",
    "sg:phone":"+32 11 48 46 73",
    "sg:postcode":"3870",
    "sg:province":"Limburg",
    "wof:name":"Pwa Heers",
    "wof:placetype":"venue"
},
  "geometry": {"coordinates":[5.3015351295,50.7525215149],"type":"Point"}
}