{
  "type": "Feature",
  "properties": {
    "iso:country":"BE",
    "sg:address":"Kleehofkensstraat 28",
    "sg:city":"Bilzen",
    "sg:orig_category":"Kapsalons",
    "sg:phone":"+32 89 41 56 34",
    "sg:postcode":"3740",
    "sg:province":"Limburg",
    "wof:name":"Coiffure Arlette",
    "wof:placetype":"venue"
},
  "geometry": {"coordinates":[5.5768527985,50.8623695374],"type":"Point"}
}