{
  "type": "Feature",
  "properties": {
    "addr:full":"Avenue L\u00c9on Jourez 69 Braine-l'alleud Brabant Wallon 1420",
    "addr:housenumber":"69",
    "addr:postcode":"1420",
    "addr:street":"Avenue Le\u0301On Jourez",
    "iso:country":"BE",
    "sg:address":"Avenue L\u00c9on Jourez 69",
    "sg:city":"Braine-l'alleud",
    "sg:orig_category":"Cosmetica and toiletartikelen Drogisterijen",
    "sg:phone":"+32 2 384 02 38",
    "sg:postcode":"1420",
    "sg:province":"Brabant Wallon",
    "wof:name":"Di",
    "wof:placetype":"venue"
},
  "geometry": {"coordinates":[-0.7004899979,47.369140625],"type":"Point"}
}