{
  "type": "Feature",
  "properties": {
    "addr:full":"Bovenstraat 19 Bornem Antwerpen 2880",
    "addr:housenumber":"19",
    "addr:postcode":"2880",
    "addr:street":"Bovenstraat",
    "iso:country":"BE",
    "sg:address":"Bovenstraat 19",
    "sg:city":"Bornem",
    "sg:orig_category":"Artsen and specialisten",
    "sg:phone":"+32 3 899 01 10",
    "sg:postcode":"2880",
    "sg:province":"Antwerpen",
    "wof:name":"C. Himpe",
    "wof:placetype":"venue"
},
  "geometry": {"coordinates":[4.1931600571,51.0694007874],"type":"Point"}
}