{
  "type": "Feature",
  "properties": {
    "iso:country":"BE",
    "sg:address":"Rue E. Gersis",
    "sg:city":"Sint-pieters-woluwe",
    "sg:orig_category":"Loodgieterij, verwarming and sanitaire installaties",
    "sg:phone":"+32 2 767 44 27",
    "sg:postcode":"1150",
    "sg:province":"Bruxelles-Capitale",
    "wof:name":"Lucitherm",
    "wof:placetype":"venue"
},
  "geometry": {"coordinates":[4.4594888687,50.8406181335],"type":"Point"}
}