{
  "type": "Feature",
  "properties": {
    "iso:country":"BE",
    "sg:address":"Appelboomgaardstraat 13",
    "sg:city":"Bilzen (munsterbilzen)",
    "sg:classifiers":[
        {
            "category":"Personal",
            "subcategory":"Barber",
            "type":"Services"
        }
    ],
    "sg:phone":"+32 89 49 22 07",
    "sg:postcode":"3740",
    "sg:province":"Limburg",
    "sg:tags":[
        "gentleman",
        "salon",
        "-",
        "hairdressing"
    ],
    "wof:name":"Ann",
    "wof:placetype":"venue"
},
  "geometry": {"coordinates":[5.5224938393,50.891910553],"type":"Point"}
}