{
  "type": "Feature",
  "properties": {
    "addr:full":"Chauss\u00c9e De Haecht 120 Schaarbeek/schaerbeek Bruxelles-Capitale 1030",
    "addr:housenumber":"120",
    "addr:postcode":"1030",
    "addr:street":"Chausse\u0301E De Haecht",
    "iso:country":"BE",
    "sg:address":"Chauss\u00c9e De Haecht 120",
    "sg:city":"Schaarbeek/schaerbeek",
    "sg:orig_category":"Syst\u00e8mes de t\u00e9l\u00e9communications",
    "sg:phone":"+32 2 229 00 08",
    "sg:postcode":"1030",
    "sg:province":"Bruxelles-Capitale",
    "wof:name":"Faith Communications",
    "wof:placetype":"venue"
},
  "geometry": {"coordinates":[4.3704710007,50.8584747314],"type":"Point"}
}