{
  "type": "Feature",
  "properties": {
    "addr:full":"Avenue Wannecouter 145 Bruxelles Bruxelles-Capitale 1020",
    "addr:housenumber":"145",
    "addr:postcode":"1020",
    "addr:street":"Avenue Wannecouter",
    "iso:country":"BE",
    "sg:address":"Avenue Wannecouter 145",
    "sg:city":"Bruxelles",
    "sg:classifiers":[
        {
            "category":"Structure",
            "subcategory":"Office Building",
            "type":"Public Place"
        }
    ],
    "sg:phone":"+32 2 268 38 96",
    "sg:postcode":"1020",
    "sg:province":"Bruxelles-Capitale",
    "sg:tags":[
        "roofing",
        "slate"
    ],
    "wof:name":"Galliot P",
    "wof:placetype":"venue"
},
  "geometry": {"coordinates":[4.3598070145,50.8994598389],"type":"Point"}
}