{
  "type": "Feature",
  "properties": {
    "addr:full":"E 3 Laan 2 Deinze Oost-Vlaanderen 9800",
    "addr:housenumber":"2",
    "addr:postcode":"9800",
    "addr:street":"E 3 Laan",
    "iso:country":"BE",
    "sg:address":"E 3 Laan 2",
    "sg:city":"Deinze",
    "sg:classifiers":[
        {
            "category":"Home & Garden",
            "subcategory":"Kitchen Supply",
            "type":"Retail Goods"
        }
    ],
    "sg:phone":"+32 9 386 38 72",
    "sg:postcode":"9800",
    "sg:province":"Oost-Vlaanderen",
    "sg:tags":[
        "fitted"
    ],
    "wof:name":"Alno Nv",
    "wof:placetype":"venue"
},
  "geometry": {"coordinates":[3.5455598831,50.9589500427],"type":"Point"}
}