{
  "type": "Feature",
  "properties": {
    "addr:full":"Chauss\u00c9e De Bruxelles 253 Charleroi Hainaut 6040",
    "addr:housenumber":"253",
    "addr:postcode":"6040",
    "addr:street":"Chausse\u0301E De Bruxelles;Hainaut",
    "iso:country":"BE",
    "sg:address":"Chauss\u00c9e De Bruxelles 253",
    "sg:city":"Charleroi",
    "sg:orig_category":"Herstellingen and onderhoud van auto's Voertuigen",
    "sg:phone":"+32 71 35 10 66",
    "sg:postcode":"6040",
    "sg:province":"Hainaut",
    "wof:name":"Garage Central",
    "wof:placetype":"venue"
},
  "geometry": {"coordinates":[4.4364218712,50.4439544678],"type":"Point"}
}