{
  "type": "Feature",
  "properties": {
    "iso:country":"BE",
    "sg:address":"Rue De La Consolation 56",
    "sg:city":"Bruxelles",
    "sg:classifiers":[
        {
            "category":"Professional",
            "subcategory":"Art Services",
            "type":"Services"
        }
    ],
    "sg:phone":"+32 2 242 78 20",
    "sg:postcode":"1030",
    "sg:province":"Bruxelles-Capitale",
    "sg:tags":[
        "packaging",
        "design"
    ],
    "wof:name":"Pineapple Design S.a.",
    "wof:placetype":"venue"
},
  "geometry": {"coordinates":[4.378619194,50.8554267883],"type":"Point"}
}