{
  "type": "Feature",
  "properties": {
    "addr:full":"Chauss\u00c9e De Wavre 163 Grez-doiceau Brabant Wallon 1390",
    "addr:housenumber":"163",
    "addr:postcode":"1390",
    "addr:street":"Chausse\u0301E De Wavre",
    "iso:country":"BE",
    "sg:address":"Chauss\u00c9e De Wavre 163",
    "sg:city":"Grez-doiceau",
    "sg:orig_category":"Services pour animaux domestiques",
    "sg:phone":"+32 10 84 22 10",
    "sg:postcode":"1390",
    "sg:province":"Brabant Wallon",
    "wof:name":"Au Grez Du Chien",
    "wof:placetype":"venue"
},
  "geometry": {"coordinates":[4.6869029999,50.7463531494],"type":"Point"}
}