{
  "type": "Feature",
  "properties": {
    "addr:full":"Acht Meilaan 7 Heusden-zolder Limburg 3550",
    "addr:housenumber":"7",
    "addr:postcode":"3550",
    "addr:street":"Acht Meilaan",
    "iso:country":"BE",
    "sg:address":"Acht Meilaan 7",
    "sg:city":"Heusden-zolder",
    "sg:orig_category":"Quincailleries",
    "sg:phone":"+32 11 53 70 92",
    "sg:postcode":"3550",
    "sg:province":"Limburg",
    "wof:name":"Fa. Jeva",
    "wof:placetype":"venue"
},
  "geometry": {"coordinates":[5.3284459114,51.0260658264],"type":"Point"}
}