{
  "type": "Feature",
  "properties": {
    "iso:country":"BE",
    "sg:address":"Elsbos 30b5",
    "sg:city":"Edegem",
    "sg:orig_category":"Artsen and specialisten",
    "sg:phone":"+32 3 457 33 99",
    "sg:postcode":"2650",
    "sg:province":"Antwerpen",
    "wof:name":"Raimond Dikker",
    "wof:placetype":"venue"
},
  "geometry": {"coordinates":[4.4527888298,51.1478614807],"type":"Point"}
}