{
  "type": "Feature",
  "properties": {
    "iso:country":"BE",
    "sg:address":"Boeimeerstraat 35",
    "sg:city":"Bonheiden",
    "sg:orig_category":"Koerierbedrijven",
    "sg:phone":"+32 15 52 92 40",
    "sg:postcode":"2820",
    "sg:province":"Antwerpen",
    "wof:name":"Crivitrans",
    "wof:placetype":"venue"
},
  "geometry": {"coordinates":[4.5676951408,51.0153198242],"type":"Point"}
}