{
  "type": "Feature",
  "properties": {
    "iso:country":"BE",
    "sg:address":"Bevegemstraat 1",
    "sg:city":"Zottegem",
    "sg:classifiers":[
        {
            "category":"Arena",
            "subcategory":"Sports Club",
            "type":"Entertainment"
        }
    ],
    "sg:phone":"+32 9 360 23 53",
    "sg:postcode":"9620",
    "sg:province":"Oost-Vlaanderen",
    "wof:name":"Tennisclub Zottegem",
    "wof:placetype":"venue"
},
  "geometry": {"coordinates":[3.8235011101,50.8661193848],"type":"Point"}
}