{
  "type": "Feature",
  "properties": {
    "iso:country":"BE",
    "sg:address":"Groenstraat 121",
    "sg:city":"Bree",
    "sg:orig_category":"Rundveehouders Varkenskwekers",
    "sg:phone":"+32 89 86 45 64",
    "sg:postcode":"3960",
    "sg:province":"Limburg",
    "wof:name":"Paul Pouls",
    "wof:placetype":"venue"
},
  "geometry": {"coordinates":[5.6869869232,51.1356811523],"type":"Point"}
}