{
  "type": "Feature",
  "properties": {
    "addr:full":"Industrieterrein Jagersborg 1007 Maaseik Limburg 3680",
    "addr:postcode":"1007 maaseik;3680",
    "addr:street":"Industrieterrein Jagersborg",
    "iso:country":"BE",
    "sg:address":"Industrieterrein Jagersborg 1007",
    "sg:city":"Maaseik",
    "sg:classifiers":[
        {
            "category":"Real Estate",
            "subcategory":"Real Estate Services",
            "type":"Services"
        }
    ],
    "sg:phone":"+32 89 57 21 01",
    "sg:postcode":"3680",
    "sg:province":"Limburg",
    "wof:name":"Groep Knippenberg",
    "wof:placetype":"venue"
},
  "geometry": {"coordinates":[5.7457351685,51.1024703979],"type":"Point"}
}