{
  "type": "Feature",
  "properties": {
    "addr:full":"Sentier Branquart 8 Lessines Hainaut 7860",
    "addr:housenumber":"8",
    "addr:postcode":"7860",
    "addr:street":"Sentier Branquart;Hainaut",
    "iso:country":"BE",
    "sg:address":"Sentier Branquart 8",
    "sg:city":"Lessines",
    "sg:classifiers":[
        {
            "category":"Health Services",
            "subcategory":"Health Practitioner",
            "type":"Services"
        }
    ],
    "sg:phone":"+32 68 33 26 19",
    "sg:postcode":"7860",
    "sg:province":"Hainaut",
    "sg:tags":[
        "physiotherapist"
    ],
    "wof:name":"Williaume M",
    "wof:placetype":"venue"
},
  "geometry": {"coordinates":[3.8192899227,50.713886261],"type":"Point"}
}