{
  "type": "Feature",
  "properties": {
    "iso:country":"BE",
    "sg:address":"Baasrodestraat 131",
    "sg:city":"Dendermonde",
    "sg:classifiers":[
        {
            "category":"Food & Beverages",
            "subcategory":"Fruits & Vegetables",
            "type":"Retail Goods"
        }
    ],
    "sg:phone":"+32 52 21 48 37",
    "sg:postcode":"9200",
    "sg:province":"Oost-Vlaanderen",
    "sg:tags":[
        "l\u00e9gumes",
        "gr"
    ],
    "wof:name":"Margriet Colman",
    "wof:placetype":"venue"
},
  "geometry": {"coordinates":[4.0983099937,51.0315208435],"type":"Point"}
}