{
  "type": "Feature",
  "properties": {
    "addr:full":"Rue De La Maladrerie 16 Bouillon Luxembourg 6830",
    "addr:housenumber":"16",
    "addr:postcode":"6830",
    "addr:street":"Rue De La Maladrerie",
    "iso:country":"BE",
    "sg:address":"Rue De La Maladrerie 16",
    "sg:city":"Bouillon",
    "sg:classifiers":[
        {
            "category":"Professional",
            "subcategory":"Accounting & Tax Preparation",
            "type":"Services"
        }
    ],
    "sg:phone":"+32 61 46 91 08",
    "sg:postcode":"6830",
    "sg:province":"Luxembourg",
    "sg:tags":[
        "accountant"
    ],
    "wof:name":"Alain Kowal",
    "wof:placetype":"venue"
},
  "geometry": {"coordinates":[5.0709600449,49.7951507568],"type":"Point"}
}