{
  "type": "Feature",
  "properties": {
    "addr:full":"Roklijf 2 Aalst Oost-Vlaanderen 9300",
    "addr:housenumber":"2",
    "addr:postcode":"9300",
    "addr:street":"Roklijf",
    "iso:country":"BE",
    "sg:address":"Roklijf 2",
    "sg:city":"Aalst",
    "sg:orig_category":"Ruimtes voor conferenties, recepties and feesten",
    "sg:phone":"+32 53 21 32 16",
    "sg:postcode":"9300",
    "sg:province":"Oost-Vlaanderen",
    "wof:name":"St.annazaal",
    "wof:placetype":"venue"
},
  "geometry": {"coordinates":[4.0170001984,50.9401702881],"type":"Point"}
}