{
  "type": "Feature",
  "properties": {
    "addr:full":"Rue Neuve Maye 56 Herve Li\u00e8ge 4650",
    "addr:housenumber":"56",
    "addr:postcode":"4650",
    "addr:street":"Rue Neuve Maye",
    "iso:country":"BE",
    "sg:address":"Rue Neuve Maye 56",
    "sg:city":"Herve",
    "sg:orig_category":"Production de films, t\u00e9l\u00e9films and vid\u00e9os",
    "sg:phone":"+32 87 33 31 04",
    "sg:postcode":"4650",
    "sg:province":"Li\u00e8ge",
    "wof:name":"D.j.v. Mega Vision",
    "wof:placetype":"venue"
},
  "geometry": {"coordinates":[5.8128499985,50.6047363281],"type":"Point"}
}