{
  "type": "Feature",
  "properties": {
    "addr:full":"Kiewitstraat 151 Hasselt Limburg 3500",
    "addr:housenumber":"151",
    "addr:postcode":"3500",
    "addr:street":"Kiewitstraat",
    "iso:country":"BE",
    "sg:address":"Kiewitstraat 151",
    "sg:city":"Hasselt",
    "sg:classifiers":[
        {
            "category":"Cafe",
            "type":"Food & Drink"
        }
    ],
    "sg:phone":"+32 11 21 13 84",
    "sg:postcode":"3500",
    "sg:province":"Limburg",
    "sg:tags":[
        "caf\u00e9s"
    ],
    "wof:name":"Caf\u00c9 Lorelei",
    "wof:placetype":"venue"
},
  "geometry": {"coordinates":[5.3677201271,50.9558410645],"type":"Point"}
}