{
  "type": "Feature",
  "properties": {
    "addr:full":"Quai De Flandre 2 Charleroi Hainaut 6000",
    "addr:housenumber":"2",
    "addr:postcode":"6000",
    "addr:street":"Quai De Flandre;Hainaut",
    "iso:country":"BE",
    "sg:address":"Quai De Flandre 2",
    "sg:city":"Charleroi",
    "sg:orig_category":"Editeurs de revues and p\u00e9riodiques. Imprimeries and copyshops. Editeurs de journaux",
    "sg:phone":"+32 71 27 64 11",
    "sg:postcode":"6000",
    "sg:province":"Hainaut",
    "wof:name":"La Nouvelle Gazette",
    "wof:placetype":"venue"
},
  "geometry": {"coordinates":[4.4376912117,50.4064483643],"type":"Point"}
}