{
  "type": "Feature",
  "properties": {
    "addr:full":"Grote Bergstraat 32 Tienen Vlaams-Brabant 3300",
    "addr:housenumber":"32",
    "addr:postcode":"3300",
    "addr:street":"Grote Bergstraat",
    "iso:country":"BE",
    "sg:address":"Grote Bergstraat 32",
    "sg:city":"Tienen",
    "sg:classifiers":[
        {
            "category":"Cafe",
            "type":"Food & Drink"
        }
    ],
    "sg:phone":"+32 16 82 28 83",
    "sg:postcode":"3300",
    "sg:province":"Vlaams-Brabant",
    "sg:tags":[
        "caf\u00e9s"
    ],
    "wof:name":"Bij Wes",
    "wof:placetype":"venue"
},
  "geometry": {"coordinates":[4.9400939941,50.8039855957],"type":"Point"}
}