{
  "type": "Feature",
  "properties": {
    "addr:full":"Chauss\u00e9e De Lille 53 Comines-warneton (warneton) Hainaut 7784",
    "addr:housenumber":"53",
    "addr:postcode":"7784",
    "addr:street":"Chausse\u0301E De Lille",
    "iso:country":"BE",
    "sg:address":"Chauss\u00e9e De Lille 53",
    "sg:city":"Comines-warneton (warneton)",
    "sg:classifiers":[
        {
            "category":"Autos & Motor Vehicles",
            "subcategory":"Fuel & Gas Station",
            "type":"Retail Goods"
        }
    ],
    "sg:phone":"+32 56 58 88 15",
    "sg:postcode":"7784",
    "sg:province":"Hainaut",
    "wof:name":"Copains (les) Sprl",
    "wof:placetype":"venue"
},
  "geometry": {"coordinates":[2.9404909611,50.7490615845],"type":"Point"}
}