{
  "type": "Feature",
  "properties": {
    "addr:full":"Vissersstraat 2 Oudenburg West-Vlaanderen 8460",
    "addr:housenumber":"2",
    "addr:postcode":"8460",
    "addr:street":"Vissersstraat",
    "iso:country":"BE",
    "sg:address":"Vissersstraat 2",
    "sg:city":"Oudenburg",
    "sg:classifiers":[
        {
            "category":"Autos & Motor Vehicles",
            "subcategory":"Automobile Sales",
            "type":"Retail Goods"
        }
    ],
    "sg:phone":"+32 59 26 55 34",
    "sg:postcode":"8460",
    "sg:province":"West-Vlaanderen",
    "sg:tags":[
        "car",
        "used",
        "-"
    ],
    "wof:name":"Lievens Autohandel",
    "wof:placetype":"venue"
},
  "geometry": {"coordinates":[2.9995100498,51.1861190796],"type":"Point"}
}