{
  "type": "Feature",
  "properties": {
    "addr:full":"Hemelrijk 22 Hasselt Limburg 3500",
    "addr:housenumber":"22",
    "addr:postcode":"3500",
    "addr:street":"Hemelrijk",
    "iso:country":"BE",
    "sg:address":"Hemelrijk 22",
    "sg:city":"Hasselt",
    "sg:classifiers":[
        {
            "category":"Fast Food",
            "type":"Food & Drink"
        }
    ],
    "sg:phone":"+32 11 23 40 89",
    "sg:postcode":"3500",
    "sg:province":"Limburg",
    "sg:tags":[
        "meeneem",
        "restaurant"
    ],
    "wof:name":"Entrepot",
    "wof:placetype":"venue"
},
  "geometry": {"coordinates":[5.3399682045,50.9306640625],"type":"Point"}
}