{
  "type": "Feature",
  "properties": {
    "addr:full":"Beverhoutsveldstraat 2 Beernem West-Vlaanderen 8730",
    "addr:housenumber":"2",
    "addr:postcode":"8730",
    "addr:street":"Beverhoutsveldstraat",
    "iso:country":"BE",
    "sg:address":"Beverhoutsveldstraat 2",
    "sg:city":"Beernem",
    "sg:orig_category":"Cr\u00e8ches and garderies d'enfants",
    "sg:phone":"+32 50 35 58 31",
    "sg:postcode":"8730",
    "sg:province":"West-Vlaanderen",
    "wof:name":"Zonnebloemen",
    "wof:placetype":"venue"
},
  "geometry": {"coordinates":[3.3033790588,51.1817474365],"type":"Point"}
}