{
  "type": "Feature",
  "properties": {
    "iso:country":"BE",
    "sg:address":"Fazantenlaan 6",
    "sg:city":"Kruibeke (bazel)",
    "sg:classifiers":[
        {
            "category":"Health Services",
            "subcategory":"Dentist",
            "type":"Services"
        }
    ],
    "sg:phone":"+32 3 774 31 83",
    "sg:postcode":"9150",
    "sg:province":"Oost-Vlaanderen",
    "wof:name":"De Mulder Roland",
    "wof:placetype":"venue"
},
  "geometry": {"coordinates":[4.3020410538,51.1504554749],"type":"Point"}
}