{
  "type": "Feature",
  "properties": {
    "iso:country":"BE",
    "sg:address":"Hoogstraat 58",
    "sg:city":"Bilzen",
    "sg:orig_category":"Installatie van houten of kunststof schrijnwerk MEUBELONTWERP AND -INSTALLATIE",
    "sg:phone":"+32 12 45 15 50",
    "sg:postcode":"3740",
    "sg:province":"Limburg",
    "wof:name":"Greven",
    "wof:placetype":"venue"
},
  "geometry": {"coordinates":[5.4791321754,50.9003791809],"type":"Point"}
}