{
  "type": "Feature",
  "properties": {
    "iso:country":"BE",
    "sg:address":"Stroomstraat 86",
    "sg:city":"Assenede",
    "sg:orig_category":"Bouwmaterialen Gh",
    "sg:phone":"+32 9 373 65 43",
    "sg:postcode":"9968",
    "sg:province":"Oost-Vlaanderen",
    "wof:name":"G Mattheeuws",
    "wof:placetype":"venue"
},
  "geometry": {"coordinates":[3.6856400967,51.2023887634],"type":"Point"}
}