{
  "type": "Feature",
  "properties": {
    "addr:full":"Oudstrijdersplein 18 Ninove Oost-Vlaanderen 9400",
    "addr:housenumber":"18",
    "addr:postcode":"9400",
    "addr:street":"Oudstrijdersplein",
    "iso:country":"BE",
    "sg:address":"Oudstrijdersplein 18",
    "sg:city":"Ninove",
    "sg:classifiers":[
        {
            "category":"Shopping",
            "subcategory":"Shoes",
            "type":"Retail Goods"
        }
    ],
    "sg:phone":"+32 54 33 34 32",
    "sg:postcode":"9400",
    "sg:province":"Oost-Vlaanderen",
    "sg:tags":[
        "slipper",
        "-"
    ],
    "wof:name":"Carina",
    "wof:placetype":"venue"
},
  "geometry": {"coordinates":[4.022810936,50.8352165222],"type":"Point"}
}