{
  "type": "Feature",
  "properties": {
    "iso:country":"BE",
    "sg:address":"J. De Sint-genoisstraat 123",
    "sg:city":"Gent",
    "sg:orig_category":"Boekhandels Krantenuitgeverijen Tijdschriftenuitgeverijen",
    "sg:phone":"+32 9 232 01 65",
    "sg:postcode":"9050",
    "sg:province":"Oost-Vlaanderen",
    "wof:name":"Press News",
    "wof:placetype":"venue"
},
  "geometry": {"coordinates":[3.7562999725,51.0277175903],"type":"Point"}
}