{
  "type": "Feature",
  "properties": {
    "iso:country":"BE",
    "sg:address":"Bruggestraat 337",
    "sg:city":"Ingelmunster",
    "sg:classifiers":[
        {
            "category":"Bars & Pubs",
            "type":"Food & Drink"
        }
    ],
    "sg:phone":"+32 51 48 87 92",
    "sg:postcode":"8770",
    "sg:province":"West-Vlaanderen",
    "wof:name":"Leestje ('t)",
    "wof:placetype":"venue"
},
  "geometry": {"coordinates":[3.2473869324,50.9464530945],"type":"Point"}
}