{
  "type": "Feature",
  "properties": {
    "addr:full":"Kievermont 80 Geel Antwerpen 2440",
    "addr:housenumber":"80",
    "addr:postcode":"2440",
    "addr:street":"Kievermont",
    "iso:country":"BE",
    "sg:address":"Kievermont 80",
    "sg:city":"Geel",
    "sg:orig_category":"Voertuigen",
    "sg:phone":"+32 14 59 23 02",
    "sg:postcode":"2440",
    "sg:province":"Antwerpen",
    "wof:name":"Auto\u00b4s John",
    "wof:placetype":"venue"
},
  "geometry": {"coordinates":[5.0284328461,51.1715240479],"type":"Point"}
}