{
  "type": "Feature",
  "properties": {
    "addr:full":"Gladiolenstraat 14 Sint-niklaas Oost-Vlaanderen 9100",
    "addr:housenumber":"14",
    "addr:postcode":"9100",
    "addr:street":"Gladiolenstraat",
    "iso:country":"BE",
    "sg:address":"Gladiolenstraat 14",
    "sg:city":"Sint-niklaas",
    "sg:classifiers":[
        {
            "category":"Manufacturing",
            "subcategory":"Musical Instruments",
            "type":"Manufacturing & Wholesale Goods"
        }
    ],
    "sg:phone":"+32 3 777 93 09",
    "sg:postcode":"9100",
    "sg:province":"Oost-Vlaanderen",
    "sg:tags":[
        "repair",
        "mainten",
        "-"
    ],
    "wof:name":"Marcus Gitaarbouw",
    "wof:placetype":"venue"
},
  "geometry": {"coordinates":[4.1590647697,51.1604995728],"type":"Point"}
}