{
  "type": "Feature",
  "properties": {
    "addr:full":"Dr\u00e8ve Alain 12 Genappe (bousval) Brabant Wallon 1470",
    "addr:housenumber":"12",
    "addr:postcode":"1470",
    "addr:street":"Dre\u0300Ve Alain;Wallon",
    "iso:country":"BE",
    "sg:address":"Dr\u00e8ve Alain 12",
    "sg:city":"Genappe (bousval)",
    "sg:classifiers":[
        {
            "category":"Arena",
            "subcategory":"Sports Club",
            "type":"Entertainment"
        }
    ],
    "sg:phone":"+32 10 61 80 33",
    "sg:postcode":"1470",
    "sg:province":"Brabant Wallon",
    "wof:name":"Tie Break Sc",
    "wof:placetype":"venue"
},
  "geometry": {"coordinates":[4.534927845,50.6448516846],"type":"Point"}
}