{
  "type": "Feature",
  "properties": {
    "iso:country":"BE",
    "sg:address":"Camping De Martinrive 17",
    "sg:city":"Aywaille",
    "sg:orig_category":"Kampeerterreinen",
    "sg:phone":"+32 4 384 87 02",
    "sg:postcode":"4920",
    "sg:province":"Li\u00e8ge",
    "wof:name":"Camping De Martinrive",
    "wof:placetype":"venue"
},
  "geometry": {"coordinates":[5.6370658875,50.4785614014],"type":"Point"}
}