{
  "type": "Feature",
  "properties": {
    "addr:full":"Kapellei 55 Zoersel Antwerpen 2980",
    "addr:housenumber":"55",
    "addr:postcode":"2980",
    "addr:street":"Kapellei",
    "iso:country":"BE",
    "sg:address":"Kapellei 55",
    "sg:city":"Zoersel",
    "sg:classifiers":[
        {
            "category":"Health Services",
            "subcategory":"Health Practitioner",
            "type":"Services"
        }
    ],
    "sg:phone":"+32 3 293 04 74",
    "sg:postcode":"2980",
    "sg:province":"Antwerpen",
    "sg:tags":[
        "physiotherapist"
    ],
    "wof:name":"Sebreghts J",
    "wof:placetype":"venue"
},
  "geometry": {"coordinates":[4.6313138008,51.2618904114],"type":"Point"}
}