{
  "type": "Feature",
  "properties": {
    "addr:full":"Groenendaalsesteenweg 36 Hoeilaart Vlaams-Brabant 1560",
    "addr:housenumber":"36",
    "addr:postcode":"1560",
    "addr:street":"Groenendaalsesteenweg",
    "iso:country":"BE",
    "sg:address":"Groenendaalsesteenweg 36",
    "sg:city":"Hoeilaart",
    "sg:orig_category":"Artsen and specialisten",
    "sg:phone":"+32 2 657 00 11",
    "sg:postcode":"1560",
    "sg:province":"Vlaams-Brabant",
    "wof:name":"Marc Denayer",
    "wof:placetype":"venue"
},
  "geometry": {"coordinates":[4.4682497978,50.7681007385],"type":"Point"}
}