{
  "type": "Feature",
  "properties": {
    "iso:country":"BE",
    "sg:address":"Ganzendries 205",
    "sg:city":"Tienen (oplinter)",
    "sg:classifiers":[
        {
            "category":"Building & Trades",
            "subcategory":"Landscaping Services",
            "type":"Services"
        }
    ],
    "sg:phone":"+32 16 77 96 25",
    "sg:postcode":"3300",
    "sg:province":"Vlaams-Brabant",
    "sg:tags":[
        "architect",
        "landscape"
    ],
    "wof:name":"Verdigo",
    "wof:placetype":"venue"
},
  "geometry": {"coordinates":[5.0020108223,50.8216438293],"type":"Point"}
}