{
  "type": "Feature",
  "properties": {
    "addr:full":"Hendrik Waelputstraat 21 Gent Oost-Vlaanderen 9000",
    "addr:housenumber":"21",
    "addr:postcode":"9000",
    "addr:street":"Hendrik Waelputstraat;Oost-Vlaanderen",
    "iso:country":"BE",
    "sg:address":"Hendrik Waelputstraat 21",
    "sg:city":"Gent",
    "sg:orig_category":"Kinderopvang",
    "sg:phone":"+32 9 225 39 23",
    "sg:postcode":"9000",
    "sg:province":"Oost-Vlaanderen",
    "wof:name":"Kribbe De Pestkopjes",
    "wof:placetype":"venue"
},
  "geometry": {"coordinates":[3.7357070446,51.0433502197],"type":"Point"}
}