{
  "type": "Feature",
  "properties": {
    "addr:full":"Industrieterrein Kolmen 1707 Alken Limburg 3570",
    "addr:postcode":"1707 alken;3570",
    "addr:street":"Industrieterrein Kolmen",
    "iso:country":"BE",
    "sg:address":"Industrieterrein Kolmen 1707",
    "sg:city":"Alken",
    "sg:orig_category":"Quincailleries. Installation de menuiserie en bois and plastique. Mat\u00e9riaux de construction Installa",
    "sg:phone":"+32 11 31 29 31",
    "sg:postcode":"3570",
    "sg:province":"Limburg",
    "wof:name":"Houbrechts Plastie-bouw",
    "wof:placetype":"venue"
},
  "geometry": {"coordinates":[5.2972297668,50.8865318298],"type":"Point"}
}