{
  "type": "Feature",
  "properties": {
    "addr:full":"Veldstraat 1 Bredene West-Vlaanderen 8450",
    "addr:housenumber":"1",
    "addr:postcode":"8450",
    "addr:street":"Veldstraat",
    "iso:country":"BE",
    "sg:address":"Veldstraat 1",
    "sg:city":"Bredene",
    "sg:classifiers":[
        {
            "category":"Food & Beverages",
            "subcategory":"Groceries & Convenience Stores",
            "type":"Retail Goods"
        }
    ],
    "sg:phone":"+32 59 32 32 64",
    "sg:postcode":"8450",
    "sg:province":"West-Vlaanderen",
    "sg:tags":[
        "grocer"
    ],
    "wof:name":"Dehaeze M",
    "wof:placetype":"venue"
},
  "geometry": {"coordinates":[2.9609639645,51.2237930298],"type":"Point"}
}