{
  "type": "Feature",
  "properties": {
    "iso:country":"BE",
    "sg:address":"Frankrijklei 144",
    "sg:city":"Antwerpen",
    "sg:classifiers":[
        {
            "category":"Communications",
            "subcategory":"Film & Video Production",
            "type":"Services"
        }
    ],
    "sg:phone":"+32 3 233 07 02",
    "sg:postcode":"2000",
    "sg:province":"Antwerpen",
    "sg:tags":[
        "hiring",
        "-",
        "equipment"
    ],
    "wof:name":"New Generation Dvd",
    "wof:placetype":"venue"
},
  "geometry": {"coordinates":[4.4101481438,51.2133865356],"type":"Point"}
}