{
  "type": "Feature",
  "properties": {
    "addr:full":"Sint-maternuswal 10 Tongeren Limburg 3700",
    "addr:housenumber":"10",
    "addr:postcode":"3700",
    "addr:street":"Sint-Maternuswal",
    "iso:country":"BE",
    "sg:address":"Sint-maternuswal 10",
    "sg:city":"Tongeren",
    "sg:orig_category":"Protection civile",
    "sg:phone":"+32 12 39 02 07",
    "sg:postcode":"3700",
    "sg:province":"Limburg",
    "wof:name":"Brandweerkazerne",
    "wof:placetype":"venue"
},
  "geometry": {"coordinates":[5.4635639191,50.7836914062],"type":"Point"}
}