{
  "type": "Feature",
  "properties": {
    "addr:full":"Van Ooststraat 26 Brussel/bruxelles Bruxelles-Capitale 1030",
    "addr:housenumber":"26",
    "addr:postcode":"1030",
    "addr:street":"Van Ooststraat;/",
    "iso:country":"BE",
    "sg:address":"Van Ooststraat 26",
    "sg:city":"Brussel/bruxelles",
    "sg:orig_category":"Industri\u00eble elektrische installaties Plaatsen van vloer- and muurbekleding Schilders Woningbouw",
    "sg:phone":"+32 2 242 00 54",
    "sg:postcode":"1030",
    "sg:province":"Bruxelles-Capitale",
    "wof:name":"Move And Fix",
    "wof:placetype":"venue"
},
  "geometry": {"coordinates":[4.3741722107,50.8620491028],"type":"Point"}
}