{
  "type": "Feature",
  "properties": {
    "iso:country":"BE",
    "sg:address":"Avenue Albert 190",
    "sg:city":"Bruxelles (forest)",
    "sg:classifiers":[
        {
            "category":"Home & Garden",
            "subcategory":"Hardware",
            "type":"Retail Goods"
        }
    ],
    "sg:phone":"+32 2 344 17 58",
    "sg:postcode":"1190",
    "sg:province":"Bruxelles-Capitale",
    "sg:tags":[
        "battery",
        "dry"
    ],
    "wof:name":"Orsones Sprl",
    "wof:placetype":"venue"
},
  "geometry": {"coordinates":[4.3468608856,50.8168678284],"type":"Point"}
}