{
  "type": "Feature",
  "properties": {
    "iso:country":"BE",
    "sg:address":"Molenstraat 70",
    "sg:city":"Eeklo",
    "sg:classifiers":[
        {
            "category":"Real Estate",
            "subcategory":"Architect",
            "type":"Services"
        }
    ],
    "sg:phone":"+32 9 377 97 76",
    "sg:postcode":"9900",
    "sg:province":"Oost-Vlaanderen",
    "wof:name":"Rummens J",
    "wof:placetype":"venue"
},
  "geometry": {"coordinates":[3.561467886,51.1870422363],"type":"Point"}
}