{
  "type": "Feature",
  "properties": {
    "addr:full":"Rue Des Trois Pertuis 2 Brussel/bruxelles Bruxelles-Capitale 1120",
    "addr:housenumber":"2",
    "addr:postcode":"1120",
    "addr:street":"Rue Des Trois Pertuis;/",
    "iso:country":"BE",
    "sg:address":"Rue Des Trois Pertuis 2",
    "sg:city":"Brussel/bruxelles",
    "sg:orig_category":"Cr\u00e8ches and garderies d'enfants",
    "sg:phone":"+32 2 267 59 37",
    "sg:postcode":"1120",
    "sg:province":"Bruxelles-Capitale",
    "wof:name":"Gemeent. Kinderdagverbl.",
    "wof:placetype":"venue"
},
  "geometry": {"coordinates":[4.3905467987,50.894695282],"type":"Point"}
}