{
  "type": "Feature",
  "properties": {
    "addr:full":"Woeringenstraat 111 Gent Oost-Vlaanderen 9000",
    "addr:housenumber":"111",
    "addr:postcode":"9000",
    "addr:street":"Woeringenstraat;Oost-Vlaanderen",
    "iso:country":"BE",
    "sg:address":"Woeringenstraat 111",
    "sg:city":"Gent",
    "sg:classifiers":[
        {
            "category":"Real Estate",
            "subcategory":"Architect",
            "type":"Services"
        }
    ],
    "sg:phone":"+32 9 222 00 11",
    "sg:postcode":"9000",
    "sg:province":"Oost-Vlaanderen",
    "wof:name":"Landuyt P",
    "wof:placetype":"venue"
},
  "geometry": {"coordinates":[3.7166199684,51.0321083069],"type":"Point"}
}