{
  "type": "Feature",
  "properties": {
    "addr:full":"Rue Neuve 25 Gr\u00e2ce-hollogne (hollogne-aux-pierres) Li\u00e8ge 4460",
    "addr:housenumber":"25",
    "addr:postcode":"4460",
    "addr:street":"Rue Neuve;Hollogne-Aux-Pierres",
    "iso:country":"BE",
    "sg:address":"Rue Neuve 25",
    "sg:city":"Gr\u00e2ce-hollogne (hollogne-aux-pierres)",
    "sg:classifiers":[
        {
            "category":"Community Center",
            "subcategory":"Social",
            "type":"Public Place"
        }
    ],
    "sg:phone":"+32 4 239 07 46",
    "sg:postcode":"4460",
    "sg:province":"Li\u00e8ge",
    "sg:tags":[
        "polishing",
        "abrasive",
        "compound"
    ],
    "wof:name":"Metfield",
    "wof:placetype":"venue"
},
  "geometry": {"coordinates":[5.4745230675,50.6298904419],"type":"Point"}
}