{
  "type": "Feature",
  "properties": {
    "iso:country":"BE",
    "sg:address":"Kapelsestraat 43",
    "sg:city":"Kapellen",
    "sg:orig_category":"Meubelzaken, woning- and keukeninrichting",
    "sg:phone":"+32 3 605 02 88",
    "sg:postcode":"2950",
    "sg:province":"Antwerpen",
    "wof:name":"China Euro Arts & Crafts",
    "wof:placetype":"venue"
},
  "geometry": {"coordinates":[4.4191718102,51.3252182007],"type":"Point"}
}