{
  "type": "Feature",
  "properties": {
    "addr:full":"Rue Sous-le-ch\u00e2teau 47-49 Huy Li\u00e8ge 4500",
    "addr:postcode":"47-49;4500",
    "addr:street":"Rue Sous-Le-Cha\u0302Teau",
    "iso:country":"BE",
    "sg:address":"Rue Sous-le-ch\u00e2teau 47-49",
    "sg:city":"Huy",
    "sg:classifiers":[
        {
            "category":"Education",
            "subcategory":"Special Training",
            "type":"Public Place"
        }
    ],
    "sg:phone":"+32 85 25 15 86",
    "sg:postcode":"4500",
    "sg:province":"Li\u00e8ge",
    "sg:tags":[
        "-",
        "processing",
        "data"
    ],
    "wof:name":"Vega Engineering Scris",
    "wof:placetype":"venue"
},
  "geometry": {"coordinates":[5.2389669418,50.5167961121],"type":"Point"}
}