{
  "type": "Feature",
  "properties": {
    "addr:full":"Rue D'houdeng 224 Le Roeulx Hainaut 7070",
    "addr:housenumber":"224",
    "addr:postcode":"7070",
    "addr:street":"Rue D'Houdeng",
    "iso:country":"BE",
    "sg:address":"Rue D'houdeng 224",
    "sg:city":"Le Roeulx",
    "sg:orig_category":"Electrom\u00e9nager, t\u00e9l\u00e9visions and radios",
    "sg:phone":"+32 64 67 11 11",
    "sg:postcode":"7070",
    "sg:province":"Hainaut",
    "wof:name":"Acec",
    "wof:placetype":"venue"
},
  "geometry": {"coordinates":[4.1265220642,50.4976272583],"type":"Point"}
}