{
  "type": "Feature",
  "properties": {
    "addr:full":"Rue Emile Regard 13 Ukkel/uccle Bruxelles-Capitale 1180",
    "addr:housenumber":"13",
    "addr:postcode":"1180",
    "addr:street":"Rue Emile Regard;/",
    "iso:country":"BE",
    "sg:address":"Rue Emile Regard 13",
    "sg:city":"Ukkel/uccle",
    "sg:orig_category":"M\u00e9decins and sp\u00e9cialistes",
    "sg:phone":"+32 2 345 45 70",
    "sg:postcode":"1180",
    "sg:province":"Bruxelles-Capitale",
    "wof:name":"Mich\u00c8le Zucker",
    "wof:placetype":"venue"
},
  "geometry": {"coordinates":[4.3375968933,50.8124961853],"type":"Point"}
}