{
  "type": "Feature",
  "properties": {
    "iso:country":"BE",
    "sg:address":"Antwerpsestraat 91",
    "sg:city":"Boom",
    "sg:orig_category":"Domotics",
    "sg:phone":"+32 3 888 08 77",
    "sg:postcode":"2850",
    "sg:province":"Antwerpen",
    "wof:name":"Chamar Electronics Nv",
    "wof:placetype":"venue"
},
  "geometry": {"coordinates":[4.3652057648,51.0882644653],"type":"Point"}
}