{
  "type": "Feature",
  "properties": {
    "iso:country":"BE",
    "sg:address":"Gemeenteplein 13",
    "sg:city":"Lummen",
    "sg:orig_category":"Offices du tourisme",
    "sg:phone":"+32 13 53 05 89",
    "sg:postcode":"3560",
    "sg:province":"Limburg",
    "wof:name":"Dienst Voor Toerisme",
    "wof:placetype":"venue"
},
  "geometry": {"coordinates":[5.1919608116,50.9865455627],"type":"Point"}
}