{
  "type": "Feature",
  "properties": {
    "addr:full":". Waterloo (groot) Brabant Wallon 1410",
    "addr:postcode":"1410",
    "addr:street":"Groot Brabant Wallon",
    "iso:country":"BE",
    "sg:address":".",
    "sg:city":"Waterloo (groot)",
    "sg:orig_category":"Apotheken",
    "sg:phone":"+32 900 10 500",
    "sg:postcode":"1410",
    "sg:province":"Brabant Wallon",
    "wof:name":"Apothekers Van Wacht",
    "wof:placetype":"venue"
},
  "geometry": {"coordinates":[4.3980250359,50.7174263],"type":"Point"}
}