{
  "type": "Feature",
  "properties": {
    "addr:full":"Emiel Vanderveldestraat 136 Willebroek Antwerpen 2830",
    "addr:housenumber":"136",
    "addr:postcode":"2830",
    "addr:street":"Emiel Vanderveldestraat",
    "iso:country":"BE",
    "sg:address":"Emiel Vanderveldestraat 136",
    "sg:city":"Willebroek",
    "sg:orig_category":"Non-Classified Establishments",
    "sg:phone":"+32 3 290 02 11",
    "sg:postcode":"2830",
    "sg:province":"Antwerpen",
    "wof:name":"Feryn International Nv",
    "wof:placetype":"venue"
},
  "geometry": {"coordinates":[4.3448519707,51.0639190674],"type":"Point"}
}