{
  "type": "Feature",
  "properties": {
    "addr:full":"Nerm 123 Hoegaarden Vlaams-Brabant 3320",
    "addr:housenumber":"123",
    "addr:postcode":"3320",
    "addr:street":"Nerm",
    "iso:country":"BE",
    "sg:address":"Nerm 123",
    "sg:city":"Hoegaarden",
    "sg:orig_category":"Eleveurs de bovins",
    "sg:phone":"+32 16 76 66 96",
    "sg:postcode":"3320",
    "sg:province":"Vlaams-Brabant",
    "wof:name":"Charles Stockmans",
    "wof:placetype":"venue"
},
  "geometry": {"coordinates":[4.8714661598,50.7715644836],"type":"Point"}
}