{
  "type": "Feature",
  "properties": {
    "addr:full":"Zomerweg 30ba Antwerpen Antwerpen 2030",
    "addr:housenumber":"30ba",
    "addr:postcode":"2030",
    "addr:street":"Zomerweg",
    "iso:country":"BE",
    "sg:address":"Zomerweg 30ba",
    "sg:city":"Antwerpen",
    "sg:orig_category":"Douanekantoren",
    "sg:phone":"+32 3 544 97 48",
    "sg:postcode":"2030",
    "sg:province":"Antwerpen",
    "wof:name":"Vreysen",
    "wof:placetype":"venue"
},
  "geometry": {"coordinates":[4.374106884,51.2692718506],"type":"Point"}
}