{
  "type": "Feature",
  "properties": {
    "iso:country":"BE",
    "sg:address":"Picardi\u00cblaan 21",
    "sg:city":"Schilde",
    "sg:orig_category":"Diverse organisaties and verenigingen",
    "sg:phone":"+32 3 385 26 24",
    "sg:postcode":"2970",
    "sg:province":"Antwerpen",
    "wof:name":"Guido Van Arezzo",
    "wof:placetype":"venue"
},
  "geometry": {"coordinates":[4.582886219,51.2430534363],"type":"Point"}
}