{
  "type": "Feature",
  "properties": {
    "iso:country":"BE",
    "sg:address":"Ophovenstraat 17",
    "sg:city":"Opglabbeek",
    "sg:orig_category":"Installation de menuiserie en bois and plastique. Fabrication and montage de mobilier",
    "sg:phone":"+32 89 85 60 93",
    "sg:postcode":"3660",
    "sg:province":"Limburg",
    "wof:name":"Hubertina Thielens",
    "wof:placetype":"venue"
},
  "geometry": {"coordinates":[5.5741667747,51.0430717468],"type":"Point"}
}