{
  "type": "Feature",
  "properties": {
    "iso:country":"BE",
    "sg:address":"Rue Albert Ier 17",
    "sg:city":"Dison",
    "sg:orig_category":"R\u00e9cup\u00e9ration de mati\u00e8res m\u00e9talliques recyclables and d\u00e9molisseurs de voitures. Stations-service and ",
    "sg:phone":"+32 87 33 75 29",
    "sg:postcode":"4820",
    "sg:province":"Li\u00e8ge",
    "wof:name":"Fe. Hansenne",
    "wof:placetype":"venue"
},
  "geometry": {"coordinates":[5.8543801308,50.6085395813],"type":"Point"}
}