{
  "type": "Feature",
  "properties": {
    "iso:country":"BE",
    "sg:address":"Avenue Reine Astrid 300",
    "sg:city":"Seneffe",
    "sg:orig_category":"Cabinets d\u00b4huissiers",
    "sg:phone":"+32 64 55 95 84",
    "sg:postcode":"7180",
    "sg:province":"Hainaut",
    "wof:name":"Jacqueline Duchateau",
    "wof:placetype":"venue"
},
  "geometry": {"coordinates":[4.2556490898,50.5305366516],"type":"Point"}
}