{
  "type": "Feature",
  "properties": {
    "addr:full":"Bellestraat 58 Heuvelland West-Vlaanderen 8954",
    "addr:housenumber":"58",
    "addr:postcode":"8954",
    "addr:street":"Bellestraat",
    "iso:country":"BE",
    "sg:address":"Bellestraat 58",
    "sg:city":"Heuvelland",
    "sg:orig_category":"Kampeerterreinen",
    "sg:phone":"+32 57 44 45 41",
    "sg:postcode":"8954",
    "sg:province":"West-Vlaanderen",
    "wof:name":"Camping Douve",
    "wof:placetype":"venue"
},
  "geometry": {"coordinates":[2.7476201057,50.7867088318],"type":"Point"}
}