{
  "type": "Feature",
  "properties": {
    "addr:full":"Rue Godefroid Kurth 9 Saint-leger Luxembourg 6747",
    "addr:housenumber":"9",
    "addr:postcode":"6747",
    "addr:street":"Rue Godefroid Kurth",
    "iso:country":"BE",
    "sg:address":"Rue Godefroid Kurth 9",
    "sg:city":"Saint-leger",
    "sg:orig_category":"Bloemen and planten",
    "sg:phone":"+32 63 23 95 64",
    "sg:postcode":"6747",
    "sg:province":"Luxembourg",
    "wof:name":"Maison Amarante",
    "wof:placetype":"venue"
},
  "geometry": {"coordinates":[5.6573219299,49.6116256714],"type":"Point"}
}