{
  "type": "Feature",
  "properties": {
    "iso:country":"BE",
    "sg:address":"Krabbesheidestraat 1",
    "sg:city":"Bierbeek",
    "sg:orig_category":"Accumulators",
    "sg:phone":"+32 16 46 36 37",
    "sg:postcode":"3360",
    "sg:province":"Vlaams-Brabant",
    "wof:name":"Verlinden Battery Industrie",
    "wof:placetype":"venue"
},
  "geometry": {"coordinates":[4.7604432106,50.8224258423],"type":"Point"}
}