{
  "type": "Feature",
  "properties": {
    "iso:country":"BE",
    "sg:address":"Industriepark 3",
    "sg:city":"Tienen",
    "sg:orig_category":"Bouwmaterialen Gh Dakwerken IJzerwaren, bouw- and verfmaterialen Tuinbenodigdheden",
    "sg:phone":"+32 16 81 60 89",
    "sg:postcode":"3300",
    "sg:province":"Vlaams-Brabant",
    "wof:name":"De Brabantse Dakwerken",
    "wof:placetype":"venue"
},
  "geometry": {"coordinates":[4.9578828812,50.8063354492],"type":"Point"}
}