{
  "type": "Feature",
  "properties": {
    "addr:full":"Kerklei 75a Brecht (sint-job-in-'t Goor) Antwerpen 2960",
    "addr:housenumber":"75a",
    "addr:postcode":"2960",
    "addr:street":"Kerklei;' T Goor",
    "iso:country":"BE",
    "sg:address":"Kerklei 75a",
    "sg:city":"Brecht (sint-job-in-'t Goor)",
    "sg:classifiers":[
        {
            "category":"Science Facility",
            "type":"Public Place"
        }
    ],
    "sg:phone":"+32 3 636 12 00",
    "sg:postcode":"2960",
    "sg:province":"Antwerpen",
    "sg:tags":[
        "-",
        "management",
        "data",
        "processing"
    ],
    "wof:name":"Garmyn K",
    "wof:placetype":"venue"
},
  "geometry": {"coordinates":[4.5846581459,51.2930831909],"type":"Point"}
}