{
  "type": "Feature",
  "properties": {
    "iso:country":"BE",
    "sg:address":"Rue Docteur-laurent 6",
    "sg:city":"Vaux-sur-sure",
    "sg:orig_category":"Installation de menuiserie en bois and plastique",
    "sg:phone":"+32 61 26 72 85",
    "sg:postcode":"6640",
    "sg:province":"Luxembourg",
    "wof:name":"Alain Clarenne",
    "wof:placetype":"venue"
},
  "geometry": {"coordinates":[5.5671000481,49.91065979],"type":"Point"}
}