{
  "type": "Feature",
  "properties": {
    "addr:full":"Rue De L'independance 56 Bruxelles Bruxelles-Capitale 1080",
    "addr:housenumber":"56",
    "addr:postcode":"1080",
    "addr:street":"Rue De L'Independance",
    "iso:country":"BE",
    "sg:address":"Rue De L'independance 56",
    "sg:city":"Bruxelles",
    "sg:classifiers":[
        {
            "category":"Banks & Credit Unions",
            "subcategory":"Bureau De Change",
            "type":"Services"
        }
    ],
    "sg:phone":"+32 2 410 32 50",
    "sg:postcode":"1080",
    "sg:province":"Bruxelles-Capitale",
    "sg:tags":[
        "archive",
        "system"
    ],
    "wof:name":"Magister B.v.b.a.",
    "wof:placetype":"venue"
},
  "geometry": {"coordinates":[4.3314452171,50.8511352539],"type":"Point"}
}