{
  "type": "Feature",
  "properties": {
    "addr:full":"All\u00c9e Du Franc-etau 4 Nivelles Brabant Wallon 1400",
    "addr:housenumber":"4",
    "addr:postcode":"1400",
    "addr:street":"Alle\u0301E Du Franc-Etau",
    "iso:country":"BE",
    "sg:address":"All\u00c9e Du Franc-etau 4",
    "sg:city":"Nivelles",
    "sg:orig_category":"Sportclubs Sportterreinen and installaties behalve sportcentra",
    "sg:phone":"+32 67 21 04 97",
    "sg:postcode":"1400",
    "sg:province":"Brabant Wallon",
    "wof:name":"F.c. Houtain-genappe",
    "wof:placetype":"venue"
},
  "geometry": {"coordinates":[4.3416390419,50.5985069275],"type":"Point"}
}