{
  "type": "Feature",
  "properties": {
    "addr:full":"Knokkestraat 20 Knokke-heist West-Vlaanderen 8301",
    "addr:housenumber":"20",
    "addr:postcode":"8301",
    "addr:street":"Knokkestraat",
    "iso:country":"BE",
    "sg:address":"Knokkestraat 20",
    "sg:city":"Knokke-heist",
    "sg:classifiers":[
        {
            "category":"Cafe",
            "type":"Food & Drink"
        }
    ],
    "sg:phone":"+32 50 51 71 95",
    "sg:postcode":"8301",
    "sg:province":"West-Vlaanderen",
    "sg:tags":[
        "caf\u00e9s"
    ],
    "wof:name":"Woody's Caf\u00c9",
    "wof:placetype":"venue"
},
  "geometry": {"coordinates":[3.2555201054,51.3391609192],"type":"Point"}
}