{
  "type": "Feature",
  "properties": {
    "addr:full":"August De Boeckstraat 31 Merchtem Vlaams-Brabant 1785",
    "addr:housenumber":"31",
    "addr:postcode":"1785",
    "addr:street":"August De Boeckstraat",
    "iso:country":"BE",
    "sg:address":"August De Boeckstraat 31",
    "sg:city":"Merchtem",
    "sg:classifiers":[
        {
            "category":"Shopping",
            "subcategory":"Computers & Home Electronics",
            "type":"Retail Goods"
        }
    ],
    "sg:phone":"+32 52 37 48 74",
    "sg:postcode":"1785",
    "sg:province":"Vlaams-Brabant",
    "sg:tags":[
        "-",
        "peripheral",
        "processing",
        "data",
        "equipment"
    ],
    "wof:name":"Compu-trade",
    "wof:placetype":"venue"
},
  "geometry": {"coordinates":[4.2275462151,50.9601402283],"type":"Point"}
}