{
  "type": "Feature",
  "properties": {
    "iso:country":"BE",
    "sg:address":"Dijkstraat 20",
    "sg:city":"Hamme",
    "sg:orig_category":"Non-Classified Establishments",
    "sg:phone":"+32 52 22 68 21",
    "sg:postcode":"9220",
    "sg:province":"Oost-Vlaanderen",
    "wof:name":"Daya Bvba",
    "wof:placetype":"venue"
},
  "geometry": {"coordinates":[4.1406331062,51.0995979309],"type":"Point"}
}