{
  "type": "Feature",
  "properties": {
    "iso:country":"BE",
    "sg:address":"Gasthuisstraat 39",
    "sg:city":"Kuurne",
    "sg:classifiers":[
        {
            "category":"Professional",
            "subcategory":"Printing & Photocopies",
            "type":"Services"
        }
    ],
    "sg:phone":"+32 56 71 66 76",
    "sg:postcode":"8520",
    "sg:province":"West-Vlaanderen",
    "sg:tags":[
        "trophy",
        "medal"
    ],
    "wof:name":"Karrewiel ('t)",
    "wof:placetype":"venue"
},
  "geometry": {"coordinates":[3.282186985,50.8507919312],"type":"Point"}
}