{
  "type": "Feature",
  "properties": {
    "addr:full":"Avenue Maurice Dekeyser 22 Bruxelles (jette) Bruxelles-Capitale 1090",
    "addr:housenumber":"22",
    "addr:postcode":"1090",
    "addr:street":"Avenue Maurice Dekeyser",
    "iso:country":"BE",
    "sg:address":"Avenue Maurice Dekeyser 22",
    "sg:city":"Bruxelles (jette)",
    "sg:classifiers":[
        {
            "category":"Parking",
            "subcategory":"Bicycle",
            "type":"Transportation"
        }
    ],
    "sg:phone":"+32 2 478 48 27",
    "sg:postcode":"1090",
    "sg:province":"Bruxelles-Capitale",
    "sg:tags":[
        "chiropodist"
    ],
    "wof:name":"P\u00e9disoins Asbl",
    "wof:placetype":"venue"
},
  "geometry": {"coordinates":[4.326130867,50.8934020996],"type":"Point"}
}