{
  "type": "Feature",
  "properties": {
    "addr:full":"Luikersteenweg 41 Hasselt Limburg 3500",
    "addr:housenumber":"41",
    "addr:postcode":"3500",
    "addr:street":"Luikersteenweg",
    "iso:country":"BE",
    "sg:address":"Luikersteenweg 41",
    "sg:city":"Hasselt",
    "sg:orig_category":"Instellingen voor probleemkinderen Kindertehuizen",
    "sg:phone":"+32 11 22 59 86",
    "sg:postcode":"3500",
    "sg:province":"Limburg",
    "wof:name":"Home De Oever",
    "wof:placetype":"venue"
},
  "geometry": {"coordinates":[5.3373041153,50.9255561829],"type":"Point"}
}