{
  "type": "Feature",
  "properties": {
    "addr:full":"Heldenlaan 39 Beringen (paal) Limburg 3583",
    "addr:housenumber":"39",
    "addr:postcode":"3583",
    "addr:street":"Heldenlaan",
    "iso:country":"BE",
    "sg:address":"Heldenlaan 39",
    "sg:city":"Beringen (paal)",
    "sg:classifiers":[
        {
            "category":"Personal",
            "subcategory":"Beauty Salon",
            "type":"Services"
        }
    ],
    "sg:phone":"+32 11 42 64 30",
    "sg:postcode":"3583",
    "sg:province":"Limburg",
    "sg:tags":[
        "lady",
        "-",
        "hairdressing"
    ],
    "wof:name":"Benny",
    "wof:placetype":"venue"
},
  "geometry": {"coordinates":[5.1706700325,51.0389442444],"type":"Point"}
}