{
  "type": "Feature",
  "properties": {
    "addr:full":"Edmond De Deynstraat 20 Ninove Oost-Vlaanderen 9400",
    "addr:housenumber":"20",
    "addr:postcode":"9400",
    "addr:street":"Edmond De Deynstraat",
    "iso:country":"BE",
    "sg:address":"Edmond De Deynstraat 20",
    "sg:city":"Ninove",
    "sg:orig_category":"Installation de menuiserie en bois and plastique",
    "sg:phone":"+32 54 32 08 78",
    "sg:postcode":"9400",
    "sg:province":"Oost-Vlaanderen",
    "wof:name":"Boils Pascal",
    "wof:placetype":"venue"
},
  "geometry": {"coordinates":[4.0237498283,50.8366088867],"type":"Point"}
}