{
  "type": "Feature",
  "properties": {
    "addr:full":"Mouthorensteenweg 31 Aarschot (langdorp) Vlaams-Brabant 3201",
    "addr:housenumber":"31",
    "addr:postcode":"3201",
    "addr:street":"Mouthorensteenweg",
    "iso:country":"BE",
    "sg:address":"Mouthorensteenweg 31",
    "sg:city":"Aarschot (langdorp)",
    "sg:classifiers":[
        {
            "category":"Bars & Pubs",
            "type":"Food & Drink"
        }
    ],
    "sg:phone":"+32 13 77 19 95",
    "sg:postcode":"3201",
    "sg:province":"Vlaams-Brabant",
    "wof:name":"Arend (den)",
    "wof:placetype":"venue"
},
  "geometry": {"coordinates":[4.9274978638,51.0171890259],"type":"Point"}
}