{
  "type": "Feature",
  "properties": {
    "iso:country":"BE",
    "sg:address":"Veeweidestraat 2",
    "sg:city":"Tienen",
    "sg:orig_category":"Jardinage",
    "sg:phone":"+32 16 77 96 25",
    "sg:postcode":"3300",
    "sg:province":"Vlaams-Brabant",
    "wof:name":"P. Van Huychem",
    "wof:placetype":"venue"
},
  "geometry": {"coordinates":[4.9718570709,50.8425674438],"type":"Point"}
}