{
  "type": "Feature",
  "properties": {
    "addr:full":"Oude Putsebaan 28 Putte Antwerpen 2580",
    "addr:housenumber":"28",
    "addr:postcode":"2580",
    "addr:street":"Oude Putsebaan",
    "iso:country":"BE",
    "sg:address":"Oude Putsebaan 28",
    "sg:city":"Putte",
    "sg:classifiers":[
        {
            "category":"Personal",
            "subcategory":"Beauty Salon",
            "type":"Services"
        }
    ],
    "sg:phone":"+32 15 75 51 67",
    "sg:postcode":"2580",
    "sg:province":"Antwerpen",
    "sg:tags":[
        "lady",
        "-",
        "hairdressing"
    ],
    "wof:name":"Hilda",
    "wof:placetype":"venue"
},
  "geometry": {"coordinates":[4.5897250175,51.0372962952],"type":"Point"}
}