{
  "type": "Feature",
  "properties": {
    "iso:country":"BE",
    "sg:address":"Hagedoornlaan 5a",
    "sg:city":"Schilde",
    "sg:orig_category":"Non-Classified Establishments",
    "sg:phone":"+32 3 385 80 01",
    "sg:postcode":"2970",
    "sg:province":"Antwerpen",
    "wof:name":"Benelux Paper Agencies",
    "wof:placetype":"venue"
},
  "geometry": {"coordinates":[4.5747799873,51.2351226807],"type":"Point"}
}