{
  "type": "Feature",
  "properties": {
    "iso:country":"BE",
    "sg:address":"Hogenhovestraat 42",
    "sg:city":"Tielt",
    "sg:orig_category":"Installation de menuiserie en bois and plastique",
    "sg:phone":"+32 51 63 62 34",
    "sg:postcode":"8700",
    "sg:province":"West-Vlaanderen",
    "wof:name":"Geert Debie",
    "wof:placetype":"venue"
},
  "geometry": {"coordinates":[3.4184820652,50.9867172241],"type":"Point"}
}