{
  "type": "Feature",
  "properties": {
    "iso:country":"BE",
    "sg:address":"Essenestraat 16",
    "sg:city":"Ternat",
    "sg:classifiers":[
        {
            "category":"Autos & Motor Vehicles",
            "subcategory":"Auto Supplies",
            "type":"Retail Goods"
        }
    ],
    "sg:phone":"+32 2 582 42 75",
    "sg:postcode":"1740",
    "sg:province":"Vlaams-Brabant",
    "sg:tags":[
        "automobile",
        "-",
        "truck",
        "gear-boxes"
    ],
    "wof:name":"M.t.s.",
    "wof:placetype":"venue"
},
  "geometry": {"coordinates":[4.1647248268,50.8836517334],"type":"Point"}
}