{
  "type": "Feature",
  "properties": {
    "addr:full":"Hendrik Van Veldekesingel 1b Hasselt (groot) Limburg 3500",
    "addr:housenumber":"1b",
    "addr:postcode":"3500",
    "addr:street":"Hendrik Van Veldekesingel;Groot Limburg",
    "iso:country":"BE",
    "sg:address":"Hendrik Van Veldekesingel 1b",
    "sg:city":"Hasselt (groot)",
    "sg:orig_category":"V\u00eatements pour b\u00e9b\u00e9s and enfants. V\u00eatements pour Dames. V\u00eatements pour Hommes",
    "sg:phone":"+32 11 28 47 93",
    "sg:postcode":"3500",
    "sg:province":"Limburg",
    "wof:name":"Jbc Mode",
    "wof:placetype":"venue"
},
  "geometry": {"coordinates":[5.3170452118,50.9263801575],"type":"Point"}
}