{
  "type": "Feature",
  "properties": {
    "addr:full":"Jevign\u00c9 21 Lierneux Li\u00e8ge 4990",
    "addr:housenumber":"21",
    "addr:postcode":"4990",
    "addr:street":"Jevigne\u0301",
    "iso:country":"BE",
    "sg:address":"Jevign\u00c9 21",
    "sg:city":"Lierneux",
    "sg:orig_category":"Enseignement maternel and primaire",
    "sg:phone":"+32 80 31 91 37",
    "sg:postcode":"4990",
    "sg:province":"Li\u00e8ge",
    "wof:name":"Ecole Fond. Communale",
    "wof:placetype":"venue"
},
  "geometry": {"coordinates":[5.7763490677,50.2862052917],"type":"Point"}
}