{
  "type": "Feature",
  "properties": {
    "iso:country":"BE",
    "sg:address":"Minimenstraat 38",
    "sg:city":"Brussel/bruxelles",
    "sg:orig_category":"Decoratieve kunst and kunstbenodigdheden",
    "sg:phone":"+32 2 511 08 81",
    "sg:postcode":"1000",
    "sg:province":"Bruxelles-Capitale",
    "wof:name":"Galerie Lancz Patrick",
    "wof:placetype":"venue"
},
  "geometry": {"coordinates":[4.3533492088,50.8400268555],"type":"Point"}
}