{
  "type": "Feature",
  "properties": {
    "iso:country":"BE",
    "sg:address":"Rue Du Tru 54",
    "sg:city":"Etalle",
    "sg:orig_category":"Alternatieve geneeskunde Artsen and specialisten Boekenuitgeverijen",
    "sg:phone":"+32 63 41 14 76",
    "sg:postcode":"6740",
    "sg:province":"Luxembourg",
    "wof:name":"Raymond Duvigneaud",
    "wof:placetype":"venue"
},
  "geometry": {"coordinates":[5.5643639565,49.6986274719],"type":"Point"}
}