{
  "type": "Feature",
  "properties": {
    "iso:country":"BE",
    "sg:address":"Waversebaan 166",
    "sg:city":"Oud-heverlee",
    "sg:classifiers":[
        {
            "category":"Structure",
            "subcategory":"Building",
            "type":"Public Place"
        }
    ],
    "sg:phone":"+32 16 47 33 54",
    "sg:postcode":"3050",
    "sg:province":"Vlaams-Brabant",
    "sg:tags":[
        "door"
    ],
    "wof:name":"Vandezande Marc",
    "wof:placetype":"venue"
},
  "geometry": {"coordinates":[4.6617288589,50.8342094421],"type":"Point"}
}