{
  "type": "Feature",
  "properties": {
    "iso:country":"BE",
    "sg:address":"Verbindingsstraat 137",
    "sg:city":"Sint-niklaas",
    "sg:classifiers":[
        {
            "category":"Food & Beverages",
            "subcategory":"Groceries & Convenience Stores",
            "type":"Retail Goods"
        }
    ],
    "sg:phone":"+32 3 777 70 22",
    "sg:postcode":"9100",
    "sg:province":"Oost-Vlaanderen",
    "sg:tags":[
        "grocer"
    ],
    "wof:name":"Verheyden J",
    "wof:placetype":"venue"
},
  "geometry": {"coordinates":[4.1483898163,51.1561584473],"type":"Point"}
}