{
  "type": "Feature",
  "properties": {
    "iso:country":"BE",
    "sg:address":"Dorp 63",
    "sg:city":"Lommel",
    "sg:classifiers":[
        {
            "category":"Cafe",
            "type":"Food & Drink"
        }
    ],
    "sg:phone":"+32 11 55 14 68",
    "sg:postcode":"3920",
    "sg:province":"Limburg",
    "sg:tags":[
        "caf\u00e9s"
    ],
    "wof:name":"Caf\u00c9 Den Bos",
    "wof:placetype":"venue"
},
  "geometry": {"coordinates":[5.3067817688,51.2310638428],"type":"Point"}
}