{
  "type": "Feature",
  "properties": {
    "iso:country":"BE",
    "sg:address":"Vronemeers 23",
    "sg:city":"Asse",
    "sg:classifiers":[
        {
            "category":"Personal",
            "subcategory":"Beauty Salon",
            "type":"Services"
        }
    ],
    "sg:phone":"+32 2 452 97 03",
    "sg:postcode":"1730",
    "sg:province":"Vlaams-Brabant",
    "sg:tags":[
        "lady",
        "-",
        "hairdressing"
    ],
    "wof:name":"Kapper Mario",
    "wof:placetype":"venue"
},
  "geometry": {"coordinates":[4.2007160187,50.9088821411],"type":"Point"}
}