{
  "type": "Feature",
  "properties": {
    "addr:full":"Place Monseigneur Heylen 11 Namur Namur 5000",
    "addr:housenumber":"11",
    "addr:postcode":"5000",
    "addr:street":"Place Monseigneur Heylen",
    "iso:country":"BE",
    "sg:address":"Place Monseigneur Heylen 11",
    "sg:city":"Namur",
    "sg:classifiers":[
        {
            "category":"Arts & Performance",
            "subcategory":"Dance",
            "type":"Entertainment"
        }
    ],
    "sg:phone":"+32 81 22 11 22",
    "sg:postcode":"5000",
    "sg:province":"Namur",
    "sg:tags":[
        "supply"
    ],
    "wof:name":"Centre De Danse Osmose Giny Jones",
    "wof:placetype":"venue"
},
  "geometry": {"coordinates":[4.8669838905,50.4714584351],"type":"Point"}
}