{
  "type": "Feature",
  "properties": {
    "addr:full":"Industrielaan 3 Diepenbeek Limburg 3590",
    "addr:housenumber":"3",
    "addr:postcode":"3590",
    "addr:street":"Industrielaan",
    "iso:country":"BE",
    "sg:address":"Industrielaan 3",
    "sg:city":"Diepenbeek",
    "sg:orig_category":"Afbraak- and draineerwerken",
    "sg:phone":"+32 11 32 10 50",
    "sg:postcode":"3590",
    "sg:province":"Limburg",
    "wof:name":"Machiels Gebr.",
    "wof:placetype":"venue"
},
  "geometry": {"coordinates":[5.4274039268,50.9086265564],"type":"Point"}
}