{
  "type": "Feature",
  "properties": {
    "iso:country":"BE",
    "sg:address":"Jacob Jacobsstraat 41",
    "sg:city":"Antwerpen",
    "sg:orig_category":"Catering and organisation de f\u00eates. Alimentation sp\u00e9cialis\u00e9e",
    "sg:phone":"+32 3 226 02 58",
    "sg:postcode":"2018",
    "sg:province":"Antwerpen",
    "wof:name":"Frank De Boeck",
    "wof:placetype":"venue"
},
  "geometry": {"coordinates":[4.4203500748,51.2114067078],"type":"Point"}
}