{
  "type": "Feature",
  "properties": {
    "iso:country":"BE",
    "sg:address":"Sint-jozefstraat 97",
    "sg:city":"Lokeren",
    "sg:classifiers":[
        {
            "category":"Education",
            "subcategory":"Music School",
            "type":"Public Place"
        }
    ],
    "sg:phone":"+32 9 349 49 00",
    "sg:postcode":"9160",
    "sg:province":"Oost-Vlaanderen",
    "sg:tags":[
        "rental",
        "grandstand",
        "stage",
        "-",
        "mfg"
    ],
    "wof:name":"Mobile Systems",
    "wof:placetype":"venue"
},
  "geometry": {"coordinates":[3.9640569687,51.0881958008],"type":"Point"}
}