{
  "type": "Feature",
  "properties": {
    "iso:country":"BE",
    "sg:address":"Grote Steenweg 48",
    "sg:city":"De Pinte (zevergem)",
    "sg:classifiers":[
        {
            "category":"Shopping",
            "subcategory":"Bicycles & Sporting Goods",
            "type":"Retail Goods"
        }
    ],
    "sg:phone":"+32 9 220 18 29",
    "sg:postcode":"9840",
    "sg:province":"Oost-Vlaanderen",
    "sg:tags":[
        "-"
    ],
    "wof:name":"Fietsen Tempo",
    "wof:placetype":"venue"
},
  "geometry": {"coordinates":[3.6847500801,50.9958305359],"type":"Point"}
}