{
  "type": "Feature",
  "properties": {
    "addr:full":"Place Saint-lambert 8 Walcourt (laneffe) Namur 5651",
    "addr:housenumber":"8",
    "addr:postcode":"5651",
    "addr:street":"Place Saint-Lambert",
    "iso:country":"BE",
    "sg:address":"Place Saint-lambert 8",
    "sg:city":"Walcourt (laneffe)",
    "sg:classifiers":[
        {
            "category":"Retail",
            "subcategory":"Event Space",
            "type":"Services"
        }
    ],
    "sg:phone":"+32 71 65 56 62",
    "sg:postcode":"5651",
    "sg:province":"Namur",
    "sg:tags":[
        "rental",
        "-",
        "hall"
    ],
    "wof:name":"Palace (le)",
    "wof:placetype":"venue"
},
  "geometry": {"coordinates":[4.4942688942,50.278339386],"type":"Point"}
}