{
  "type": "Feature",
  "properties": {
    "addr:full":"Place Albert-ier 27 La Bruyere Namur 5081",
    "addr:housenumber":"27",
    "addr:postcode":"5081",
    "addr:street":"Place Albert-Ier;La Bruyere",
    "iso:country":"BE",
    "sg:address":"Place Albert-ier 27",
    "sg:city":"La Bruyere",
    "sg:classifiers":[
        {
            "category":"Cafe",
            "type":"Food & Drink"
        }
    ],
    "sg:phone":"+32 81 56 83 70",
    "sg:postcode":"5081",
    "sg:province":"Namur",
    "sg:tags":[
        "caf\u00e9s"
    ],
    "wof:name":"Caf\u00c9 L'embuscade",
    "wof:placetype":"venue"
},
  "geometry": {"coordinates":[4.782954216,50.5352249146],"type":"Point"}
}