{
  "type": "Feature",
  "properties": {
    "addr:full":"Dijkstraat 5 Hamme Oost-Vlaanderen 9220",
    "addr:housenumber":"5",
    "addr:postcode":"9220",
    "addr:street":"Dijkstraat",
    "iso:country":"BE",
    "sg:address":"Dijkstraat 5",
    "sg:city":"Hamme",
    "sg:classifiers":[
        {
            "category":"Health Services",
            "subcategory":"Dentist",
            "type":"Services"
        }
    ],
    "sg:phone":"+32 52 47 35 36",
    "sg:postcode":"9220",
    "sg:province":"Oost-Vlaanderen",
    "wof:name":"Brusselmans C",
    "wof:placetype":"venue"
},
  "geometry": {"coordinates":[4.1411719322,51.0993804932],"type":"Point"}
}