{
  "type": "Feature",
  "properties": {
    "iso:country":"BE",
    "sg:address":"Steystraat 30",
    "sg:city":"Aarschot",
    "sg:orig_category":"M\u00e9decines alternatives",
    "sg:phone":"+32 16 56 64 93",
    "sg:postcode":"3200",
    "sg:province":"Vlaams-Brabant",
    "wof:name":"Liesbet Segers",
    "wof:placetype":"venue"
},
  "geometry": {"coordinates":[4.8458881378,50.9917488098],"type":"Point"}
}