{
  "type": "Feature",
  "properties": {
    "addr:full":"Route De Longwy 586 Arlon Luxembourg 6700",
    "addr:housenumber":"586",
    "addr:postcode":"6700",
    "addr:street":"Route De Longwy",
    "iso:country":"BE",
    "sg:address":"Route De Longwy 586",
    "sg:city":"Arlon",
    "sg:orig_category":"Herstellingen motorfietsen Motorfietsen Voertuigen",
    "sg:phone":"+32 63 23 67 60",
    "sg:postcode":"6700",
    "sg:province":"Luxembourg",
    "wof:name":"Top Motos",
    "wof:placetype":"venue"
},
  "geometry": {"coordinates":[5.8241500854,49.6701087952],"type":"Point"}
}