{
  "type": "Feature",
  "properties": {
    "addr:full":"Ijzerstraat 58 Tervuren Vlaams-Brabant 3080",
    "addr:housenumber":"58",
    "addr:postcode":"3080",
    "addr:street":"Ijzerstraat",
    "iso:country":"BE",
    "sg:address":"Ijzerstraat 58",
    "sg:city":"Tervuren",
    "sg:classifiers":[
        {
            "category":"Real Estate",
            "subcategory":"Surveying",
            "type":"Services"
        }
    ],
    "sg:phone":"+32 2 688 28 19",
    "sg:postcode":"3080",
    "sg:province":"Vlaams-Brabant",
    "sg:tags":[
        "surveyor",
        "land"
    ],
    "wof:name":"Stappers A",
    "wof:placetype":"venue"
},
  "geometry": {"coordinates":[4.5436320305,50.8024597168],"type":"Point"}
}