{
  "type": "Feature",
  "properties": {
    "addr:full":"Haifastraat 9 Antwerpen Antwerpen 2030",
    "addr:housenumber":"9",
    "addr:postcode":"2030",
    "addr:street":"Haifastraat",
    "iso:country":"BE",
    "sg:address":"Haifastraat 9",
    "sg:city":"Antwerpen",
    "sg:classifiers":[
        {
            "category":"Freight",
            "type":"Transportation"
        }
    ],
    "sg:phone":"+32 3 542 42 35",
    "sg:postcode":"2030",
    "sg:province":"Antwerpen",
    "sg:tags":[
        "container",
        "-",
        "transport"
    ],
    "wof:name":"Immo-trans",
    "wof:placetype":"venue"
},
  "geometry": {"coordinates":[4.4139127731,51.2628440857],"type":"Point"}
}