{
  "type": "Feature",
  "properties": {
    "iso:country":"BE",
    "sg:address":"Rue Marie-christine 181-183",
    "sg:city":"Bruxelles",
    "sg:orig_category":"Chaussures",
    "sg:phone":"+32 2 427 38 97",
    "sg:postcode":"1020",
    "sg:province":"Bruxelles-Capitale",
    "wof:name":"Shoes In The Box",
    "wof:placetype":"venue"
},
  "geometry": {"coordinates":[4.3500909805,50.8768043518],"type":"Point"}
}