{
  "type": "Feature",
  "properties": {
    "addr:full":"Diestsesteenweg 333 Tienen Vlaams-Brabant 3300",
    "addr:housenumber":"333",
    "addr:postcode":"3300",
    "addr:street":"Diestsesteenweg",
    "iso:country":"BE",
    "sg:address":"Diestsesteenweg 333",
    "sg:city":"Tienen",
    "sg:orig_category":"Travaux de pl\u00e2trage",
    "sg:phone":"+32 16 81 07 53",
    "sg:postcode":"3300",
    "sg:province":"Vlaams-Brabant",
    "wof:name":"Roger Logist",
    "wof:placetype":"venue"
},
  "geometry": {"coordinates":[4.9374461174,50.8222961426],"type":"Point"}
}