{
  "type": "Feature",
  "properties": {
    "iso:country":"BE",
    "sg:address":"Chauss\u00c9e Paul Houtart 306",
    "sg:city":"La Louviere",
    "sg:orig_category":"Fleurs and plantes",
    "sg:phone":"+32 64 84 85 16",
    "sg:postcode":"7110",
    "sg:province":"Hainaut",
    "wof:name":"Au Saint Fiacre",
    "wof:placetype":"venue"
},
  "geometry": {"coordinates":[4.1559967995,50.4874954224],"type":"Point"}
}