{
  "type": "Feature",
  "properties": {
    "addr:full":"Rue De Coquiane 110 Edingen/enghien Hainaut 7850",
    "addr:housenumber":"110",
    "addr:postcode":"7850",
    "addr:street":"Rue De Coquiane",
    "iso:country":"BE",
    "sg:address":"Rue De Coquiane 110",
    "sg:city":"Edingen/enghien",
    "sg:orig_category":"M\u00e9decins and sp\u00e9cialistes",
    "sg:phone":"+32 2 395 49 00",
    "sg:postcode":"7850",
    "sg:province":"Hainaut",
    "wof:name":"C. Amand",
    "wof:placetype":"venue"
},
  "geometry": {"coordinates":[4.0790348053,50.7001533508],"type":"Point"}
}