{
  "type": "Feature",
  "properties": {
    "addr:full":"Tongerlostraat 15 Westerlo Antwerpen 2260",
    "addr:housenumber":"15",
    "addr:postcode":"2260",
    "addr:street":"Tongerlostraat",
    "iso:country":"BE",
    "sg:address":"Tongerlostraat 15",
    "sg:city":"Westerlo",
    "sg:classifiers":[
        {
            "category":"Personal",
            "subcategory":"Beauty Salon",
            "type":"Services"
        }
    ],
    "sg:phone":"+32 14 23 09 63",
    "sg:postcode":"2260",
    "sg:province":"Antwerpen",
    "sg:tags":[
        "de",
        "coiffure"
    ],
    "wof:name":"Marina Aerts",
    "wof:placetype":"venue"
},
  "geometry": {"coordinates":[4.9042348862,51.1356124878],"type":"Point"}
}