{
  "type": "Feature",
  "properties": {
    "iso:country":"BE",
    "sg:address":"Nerenbroekstraat 82",
    "sg:city":"Erpe-mere (erpe)",
    "sg:classifiers":[
        {
            "category":"Home & Garden",
            "subcategory":"Home Furnishings",
            "type":"Retail Goods"
        }
    ],
    "sg:phone":"+32 53 80 09 65",
    "sg:postcode":"9420",
    "sg:province":"Oost-Vlaanderen",
    "sg:tags":[
        "-",
        "furniture"
    ],
    "wof:name":"Van Der Stockt J",
    "wof:placetype":"venue"
},
  "geometry": {"coordinates":[3.9762101173,50.9441757202],"type":"Point"}
}