{
  "type": "Feature",
  "properties": {
    "addr:full":"Stationsstraat 68 Asse Vlaams-Brabant 1730",
    "addr:housenumber":"68",
    "addr:postcode":"1730",
    "addr:street":"Stationsstraat",
    "iso:country":"BE",
    "sg:address":"Stationsstraat 68",
    "sg:city":"Asse",
    "sg:classifiers":[
        {
            "category":"Personal",
            "subcategory":"Beauty Salon",
            "type":"Services"
        }
    ],
    "sg:phone":"+32 2 452 53 59",
    "sg:postcode":"1730",
    "sg:province":"Vlaams-Brabant",
    "sg:tags":[
        "lady",
        "-",
        "hairdressing"
    ],
    "wof:name":"Myriam",
    "wof:placetype":"venue"
},
  "geometry": {"coordinates":[4.2065711021,50.9066581726],"type":"Point"}
}