{
  "type": "Feature",
  "properties": {
    "iso:country":"BE",
    "sg:address":"Winkelsestraat 99b204",
    "sg:city":"Lendelede",
    "sg:orig_category":"Eleveurs de bovins",
    "sg:phone":"+32 51 30 70 46",
    "sg:postcode":"8860",
    "sg:province":"West-Vlaanderen",
    "wof:name":"Delaere Jose",
    "wof:placetype":"venue"
},
  "geometry": {"coordinates":[3.2096030712,50.8816986084],"type":"Point"}
}