{
  "type": "Feature",
  "properties": {
    "addr:full":"Rue De Gozee 425 Montigny-le-tilleul (grand) Hainaut 6110",
    "addr:housenumber":"425",
    "addr:postcode":"6110",
    "addr:street":"Rue De Gozee",
    "iso:country":"BE",
    "sg:address":"Rue De Gozee 425",
    "sg:city":"Montigny-le-tilleul (grand)",
    "sg:orig_category":"Kapsalons",
    "sg:phone":"+32 71 51 89 68",
    "sg:postcode":"6110",
    "sg:province":"Hainaut",
    "wof:name":"Coiffure Vanessa",
    "wof:placetype":"venue"
},
  "geometry": {"coordinates":[4.3702168465,50.3775100708],"type":"Point"}
}