{
  "type": "Feature",
  "properties": {
    "addr:full":"De Vierseizoenenstraat 1b25 Moorslede West-Vlaanderen 8890",
    "addr:housenumber":"1b25",
    "addr:postcode":"8890",
    "addr:street":"Vierseizoenenstraat",
    "iso:country":"BE",
    "sg:address":"De Vierseizoenenstraat 1b25",
    "sg:city":"Moorslede",
    "sg:orig_category":"Maisons de repos and r\u00e9sidences",
    "sg:phone":"+32 51 77 11 21",
    "sg:postcode":"8890",
    "sg:province":"West-Vlaanderen",
    "wof:name":"Resid. De Vierseizoenen",
    "wof:placetype":"venue"
},
  "geometry": {"coordinates":[3.0637769699,50.891456604],"type":"Point"}
}