{
  "type": "Feature",
  "properties": {
    "addr:full":"Rue Albert Ier 2 Mettet Namur 5640",
    "addr:housenumber":"2",
    "addr:postcode":"5640",
    "addr:street":"Rue Albert Ier",
    "iso:country":"BE",
    "sg:address":"Rue Albert Ier 2",
    "sg:city":"Mettet",
    "sg:orig_category":"Cr\u00e9dits divers",
    "sg:postcode":"5640",
    "sg:province":"Namur",
    "wof:name":"Bancontact-mister Cash",
    "wof:placetype":"venue"
},
  "geometry": {"coordinates":[4.6580481529,50.3211746216],"type":"Point"}
}