{
  "type": "Feature",
  "properties": {
    "iso:country":"BE",
    "sg:address":"Rijmenamsebaan 26",
    "sg:city":"Keerbergen",
    "sg:classifiers":[
        {
            "category":"Professional",
            "subcategory":"Computer Services",
            "type":"Services"
        }
    ],
    "sg:phone":"+32 15 51 13 04",
    "sg:postcode":"3140",
    "sg:province":"Vlaams-Brabant",
    "sg:tags":[
        "-",
        "processing",
        "data",
        "software"
    ],
    "wof:name":"Epsilon Bvba",
    "wof:placetype":"venue"
},
  "geometry": {"coordinates":[4.6156749725,51.0040893555],"type":"Point"}
}