{
  "type": "Feature",
  "properties": {
    "addr:full":"Grootveldstraat 27 Beersel Vlaams-Brabant 1652",
    "addr:housenumber":"27",
    "addr:postcode":"1652",
    "addr:street":"Grootveldstraat",
    "iso:country":"BE",
    "sg:address":"Grootveldstraat 27",
    "sg:city":"Beersel",
    "sg:orig_category":"Benzinestations and brandstoffen",
    "sg:phone":"+32 2 381 15 58",
    "sg:postcode":"1652",
    "sg:province":"Vlaams-Brabant",
    "wof:name":"Christian Vancutsem",
    "wof:placetype":"venue"
},
  "geometry": {"coordinates":[4.330286026,50.7487487793],"type":"Point"}
}