{
  "type": "Feature",
  "properties": {
    "addr:full":"Sint-gillisvoorplein 18 Sint-gillis/saint-gilles Bruxelles-Capitale 1060",
    "addr:housenumber":"18",
    "addr:postcode":"1060",
    "addr:street":"Sint-Gillisvoorplein",
    "iso:country":"BE",
    "sg:address":"Sint-gillisvoorplein 18",
    "sg:city":"Sint-gillis/saint-gilles",
    "sg:orig_category":"Rusthuizen and serviceflats",
    "sg:phone":"+32 2 537 28 43",
    "sg:postcode":"1060",
    "sg:province":"Bruxelles-Capitale",
    "wof:name":"Centre Serv. Commun.",
    "wof:placetype":"venue"
},
  "geometry": {"coordinates":[4.3454170227,50.8307342529],"type":"Point"}
}