{
  "type": "Feature",
  "properties": {
    "iso:country":"BE",
    "sg:address":"Lijsterstraat 2",
    "sg:city":"Mechelen",
    "sg:orig_category":"Enseignement maternel and primaire",
    "sg:phone":"+32 15 21 83 33",
    "sg:postcode":"2800",
    "sg:province":"Antwerpen",
    "wof:name":"Stedelijke Kleuterschool",
    "wof:placetype":"venue"
},
  "geometry": {"coordinates":[4.4743690491,51.0437850952],"type":"Point"}
}