{
  "type": "Feature",
  "properties": {
    "iso:country":"BE",
    "sg:address":"Avenue Louis Lepoutre 57",
    "sg:city":"Bruxelles (ixelles)",
    "sg:classifiers":[
        {
            "category":"Shopping",
            "subcategory":"Antiques",
            "type":"Retail Goods"
        }
    ],
    "sg:phone":"+32 2 347 62 27",
    "sg:postcode":"1050",
    "sg:province":"Bruxelles-Capitale",
    "wof:name":"Galerie De Breyne & Co",
    "wof:placetype":"venue"
},
  "geometry": {"coordinates":[4.3570871353,50.8189888],"type":"Point"}
}