{
  "type": "Feature",
  "properties": {
    "addr:full":"Rue K\u00e9ramis 9 La Louvi\u00e8re Hainaut 7100",
    "addr:housenumber":"9",
    "addr:postcode":"7100",
    "addr:street":"Rue Ke\u0301Ramis",
    "iso:country":"BE",
    "sg:address":"Rue K\u00e9ramis 9",
    "sg:city":"La Louvi\u00e8re",
    "sg:classifiers":[
        {
            "category":"Bars & Pubs",
            "type":"Food & Drink"
        }
    ],
    "sg:phone":"+32 485 20 98 61",
    "sg:postcode":"7100",
    "sg:province":"Hainaut",
    "wof:name":"St Trop (le)",
    "wof:placetype":"venue"
},
  "geometry": {"coordinates":[4.1875209808,50.4777069092],"type":"Point"}
}