{
  "type": "Feature",
  "properties": {
    "addr:full":"Vredelaan 22 Houthalen-helchteren (houthalen) Limburg 3530",
    "addr:housenumber":"22",
    "addr:postcode":"3530",
    "addr:street":"Vredelaan",
    "iso:country":"BE",
    "sg:address":"Vredelaan 22",
    "sg:city":"Houthalen-helchteren (houthalen)",
    "sg:classifiers":[
        {
            "category":"Shopping",
            "subcategory":"Florist",
            "type":"Retail Goods"
        }
    ],
    "sg:phone":"+32 11 52 41 51",
    "sg:postcode":"3530",
    "sg:province":"Limburg",
    "wof:name":"Bloemenhuis Bude",
    "wof:placetype":"venue"
},
  "geometry": {"coordinates":[5.3735327721,51.0317382812],"type":"Point"}
}