{
  "type": "Feature",
  "properties": {
    "addr:full":"Ommegang-noord 36 Westrozebeke West-Vlaanderen 8840",
    "addr:housenumber":"36",
    "addr:postcode":"8840",
    "addr:street":"Ommegang-Noord",
    "iso:country":"BE",
    "sg:address":"Ommegang-noord 36",
    "sg:city":"Westrozebeke",
    "sg:orig_category":"Royal Canin. Animaux domestiques and accessoires",
    "sg:phone":"+32 51 77 76 25",
    "sg:postcode":"8840",
    "sg:province":"West-Vlaanderen",
    "wof:name":"Thevelein Frank",
    "wof:placetype":"venue"
},
  "geometry": {"coordinates":[3.0106840134,50.9343719482],"type":"Point"}
}