{
  "type": "Feature",
  "properties": {
    "addr:full":"Loosplaats 1 Antwerpen Antwerpen 2018",
    "addr:housenumber":"1",
    "addr:postcode":"2018",
    "addr:street":"Loosplaats",
    "iso:country":"BE",
    "sg:address":"Loosplaats 1",
    "sg:city":"Antwerpen",
    "sg:classifiers":[
        {
            "category":"Restaurant",
            "type":"Food & Drink"
        }
    ],
    "sg:phone":"+32 3 218 92 82",
    "sg:postcode":"2018",
    "sg:province":"Antwerpen",
    "wof:name":"\u00b4t Park",
    "wof:placetype":"venue"
},
  "geometry": {"coordinates":[4.4181780815,51.2105407715],"type":"Point"}
}