{
  "type": "Feature",
  "properties": {
    "addr:full":"Oostvleterenstraat 14 Lo-reninge West-Vlaanderen 8647",
    "addr:housenumber":"14",
    "addr:postcode":"8647",
    "addr:street":"Oostvleterenstraat",
    "iso:country":"BE",
    "sg:address":"Oostvleterenstraat 14",
    "sg:city":"Lo-reninge",
    "sg:orig_category":"Varkenskwekers",
    "sg:phone":"+32 57 40 06 09",
    "sg:postcode":"8647",
    "sg:province":"West-Vlaanderen",
    "wof:name":"Herman Lannoye",
    "wof:placetype":"venue"
},
  "geometry": {"coordinates":[2.7697451115,50.9406204224],"type":"Point"}
}