{
  "type": "Feature",
  "properties": {
    "iso:country":"BE",
    "sg:address":"Rue De Berneau 100",
    "sg:city":"Vise",
    "sg:orig_category":"Loodgieterij, verwarming and sanitaire installaties",
    "sg:phone":"+32 4 379 42 10",
    "sg:postcode":"4600",
    "sg:province":"Li\u00e8ge",
    "wof:name":"Francois Brune",
    "wof:placetype":"venue"
},
  "geometry": {"coordinates":[5.7093200684,50.7378807068],"type":"Point"}
}