{
  "type": "Feature",
  "properties": {
    "addr:full":"Meersbloem Leupegem 50 Oudenaarde Oost-Vlaanderen 9700",
    "addr:housenumber":"50",
    "addr:postcode":"9700",
    "addr:street":"Leupegem",
    "iso:country":"BE",
    "sg:address":"Meersbloem Leupegem 50",
    "sg:city":"Oudenaarde",
    "sg:classifiers":[
        {
            "category":"Real Estate",
            "subcategory":"Real Estate Services",
            "type":"Services"
        }
    ],
    "sg:phone":"+32 55 31 66 28",
    "sg:postcode":"9700",
    "sg:province":"Oost-Vlaanderen",
    "wof:name":"Algifin",
    "wof:placetype":"venue"
},
  "geometry": {"coordinates":[3.6047101021,50.833568573],"type":"Point"}
}