{
  "type": "Feature",
  "properties": {
    "iso:country":"BE",
    "sg:address":"Bovekerkestraat 136",
    "sg:city":"Koekelare",
    "sg:classifiers":[
        {
            "category":"Banks & Credit Unions",
            "subcategory":"Investment Brokerage",
            "type":"Services"
        }
    ],
    "sg:phone":"+32 51 58 36 00",
    "sg:postcode":"8680",
    "sg:province":"West-Vlaanderen",
    "sg:tags":[
        "repair",
        "-",
        "installation",
        "sanitary",
        "article"
    ],
    "wof:name":"Beeckaert Danny Bvba",
    "wof:placetype":"venue"
},
  "geometry": {"coordinates":[2.9633500576,51.0647583008],"type":"Point"}
}