{
  "type": "Feature",
  "properties": {
    "iso:country":"BE",
    "sg:address":"Rue De Mons 46",
    "sg:city":"Soignies",
    "sg:orig_category":"Meubelzaken, woning- and keukeninrichting",
    "sg:phone":"+32 67 33 40 70",
    "sg:postcode":"7060",
    "sg:province":"Hainaut",
    "wof:name":"Meubles La Maison",
    "wof:placetype":"venue"
},
  "geometry": {"coordinates":[4.0716371536,50.5781860352],"type":"Point"}
}