{
  "type": "Feature",
  "properties": {
    "addr:full":"Oude Baan 35 Diest Vlaams-Brabant 3290",
    "addr:housenumber":"35",
    "addr:postcode":"3290",
    "addr:street":"Oude Baan",
    "iso:country":"BE",
    "sg:address":"Oude Baan 35",
    "sg:city":"Diest",
    "sg:classifiers":[
        {
            "category":"Building & Trades",
            "subcategory":"Cleaning & Sanitation",
            "type":"Services"
        }
    ],
    "sg:phone":"+32 472 22 95 50",
    "sg:postcode":"3290",
    "sg:province":"Vlaams-Brabant",
    "sg:tags":[
        "cleaner",
        "window"
    ],
    "wof:name":"Bb Cleaning",
    "wof:placetype":"venue"
},
  "geometry": {"coordinates":[5.0596561432,50.9780082703],"type":"Point"}
}