{
  "type": "Feature",
  "properties": {
    "iso:country":"BE",
    "sg:address":"Hoevenstraat 102",
    "sg:city":"Herselt",
    "sg:orig_category":"Bloemen and planten",
    "sg:phone":"+32 16 56 76 89",
    "sg:postcode":"2230",
    "sg:province":"Antwerpen",
    "wof:name":"Vandijck",
    "wof:placetype":"venue"
},
  "geometry": {"coordinates":[4.8224439621,51.0229682922],"type":"Point"}
}