{
  "type": "Feature",
  "properties": {
    "iso:country":"BE",
    "sg:address":"Rue De L'h\u00d4tel De Ville 10",
    "sg:city":"Sprimont",
    "sg:orig_category":"Epiceries",
    "sg:phone":"+32 4 382 11 84",
    "sg:postcode":"4140",
    "sg:province":"Li\u00e8ge",
    "wof:name":"Confiserie Grignet",
    "wof:placetype":"venue"
},
  "geometry": {"coordinates":[5.661151886,50.5028266907],"type":"Point"}
}