{
  "type": "Feature",
  "properties": {
    "addr:full":"Tempelierstraat 22 Gistel West-Vlaanderen 8470",
    "addr:housenumber":"22",
    "addr:postcode":"8470",
    "addr:street":"Tempelierstraat",
    "iso:country":"BE",
    "sg:address":"Tempelierstraat 22",
    "sg:city":"Gistel",
    "sg:classifiers":[
        {
            "category":"Farming",
            "subcategory":"Crops",
            "type":"Manufacturing & Wholesale Goods"
        }
    ],
    "sg:phone":"+32 59 27 83 13",
    "sg:postcode":"8470",
    "sg:province":"West-Vlaanderen",
    "sg:tags":[
        "vegetable",
        "fruit",
        "-",
        "grower"
    ],
    "wof:name":"Gevaert J",
    "wof:placetype":"venue"
},
  "geometry": {"coordinates":[2.9585940838,51.1538925171],"type":"Point"}
}