{
  "type": "Feature",
  "properties": {
    "addr:full":"Bosakkerstraat 12ba Tielt West-Vlaanderen 8700",
    "addr:postcode":"8700",
    "addr:street":"Bosakkerstraat",
    "iso:country":"BE",
    "sg:address":"Bosakkerstraat 12ba",
    "sg:city":"Tielt",
    "sg:orig_category":"Woningbouw",
    "sg:phone":"+32 51 40 48 23",
    "sg:postcode":"8700",
    "sg:province":"West-Vlaanderen",
    "wof:name":"Vandeviane",
    "wof:placetype":"venue"
},
  "geometry": {"coordinates":[3.3344221115,50.9680709839],"type":"Point"}
}