{
  "type": "Feature",
  "properties": {
    "iso:country":"BE",
    "sg:address":"Bocholterweg 102",
    "sg:city":"Peer (grote Brogel)",
    "sg:classifiers":[
        {
            "category":"Professional",
            "type":"Services"
        }
    ],
    "sg:phone":"+32 11 63 37 44",
    "sg:postcode":"3990",
    "sg:province":"Limburg",
    "sg:tags":[
        "industrial",
        "automation"
    ],
    "wof:name":"Delaet Engineering",
    "wof:placetype":"venue"
},
  "geometry": {"coordinates":[5.5312180519,51.1607093811],"type":"Point"}
}