{
  "type": "Feature",
  "properties": {
    "addr:full":"Schoonstraat 272 Evergem Oost-Vlaanderen 9940",
    "addr:housenumber":"272",
    "addr:postcode":"9940",
    "addr:street":"Schoonstraat;Oost-Vlaanderen",
    "iso:country":"BE",
    "sg:address":"Schoonstraat 272",
    "sg:city":"Evergem",
    "sg:orig_category":"Kapsalons",
    "sg:phone":"+32 9 253 65 22",
    "sg:postcode":"9940",
    "sg:province":"Oost-Vlaanderen",
    "wof:name":"Coiffure Christa",
    "wof:placetype":"venue"
},
  "geometry": {"coordinates":[3.6743481159,51.1046905518],"type":"Point"}
}