{
  "type": "Feature",
  "properties": {
    "iso:country":"BE",
    "sg:address":"Quai De La Boverie 3",
    "sg:city":"Li\u00c8ge",
    "sg:orig_category":"Kapsalons",
    "sg:phone":"+32 4 343 70 10",
    "sg:postcode":"4020",
    "sg:province":"Li\u00e8ge",
    "wof:name":"Hair France",
    "wof:placetype":"venue"
},
  "geometry": {"coordinates":[5.5783920288,50.6368865967],"type":"Point"}
}