{
  "type": "Feature",
  "properties": {
    "addr:full":"Kapellestraat 243 Bredene West-Vlaanderen 8450",
    "addr:housenumber":"243",
    "addr:postcode":"8450",
    "addr:street":"Kapellestraat",
    "iso:country":"BE",
    "sg:address":"Kapellestraat 243",
    "sg:city":"Bredene",
    "sg:classifiers":[
        {
            "category":"Restaurant",
            "type":"Food & Drink"
        }
    ],
    "sg:phone":"+32 59 32 04 94",
    "sg:postcode":"8450",
    "sg:province":"West-Vlaanderen",
    "wof:name":"Bij Ons/chez Nous",
    "wof:placetype":"venue"
},
  "geometry": {"coordinates":[2.9802820683,51.2532691956],"type":"Point"}
}