{
  "type": "Feature",
  "properties": {
    "iso:country":"BE",
    "sg:address":"Rue Des Conf\u00e9d\u00e9r\u00e9s 55",
    "sg:city":"Bruxelles",
    "sg:classifiers":[
        {
            "category":"Professional",
            "subcategory":"Engineering",
            "type":"Services"
        }
    ],
    "sg:phone":"+32 2 735 92 50",
    "sg:postcode":"1000",
    "sg:province":"Bruxelles-Capitale",
    "sg:tags":[
        "technical",
        "equipment",
        "offices-"
    ],
    "wof:name":"Louis Ryelandt Engineering Sprl",
    "wof:placetype":"venue"
},
  "geometry": {"coordinates":[4.3858242035,50.8485298157],"type":"Point"}
}