{
  "type": "Feature",
  "properties": {
    "iso:country":"BE",
    "sg:address":"Desguinlei 102",
    "sg:city":"Antwerpen",
    "sg:classifiers":[
        {
            "category":"Banks & Credit Unions",
            "subcategory":"Financial Services",
            "type":"Services"
        }
    ],
    "sg:phone":"+32 3 247 23 80",
    "sg:postcode":"2018",
    "sg:province":"Antwerpen",
    "sg:tags":[
        "banking",
        "finance",
        "insurance"
    ],
    "wof:name":"Amazon Insurance Nv",
    "wof:placetype":"venue"
},
  "geometry": {"coordinates":[4.4042358398,51.1943893433],"type":"Point"}
}