{
  "type": "Feature",
  "properties": {
    "addr:full":"Asterstraat 14 Lovendegem Oost-Vlaanderen 9920",
    "addr:housenumber":"14",
    "addr:postcode":"9920",
    "addr:street":"Asterstraat",
    "iso:country":"BE",
    "sg:address":"Asterstraat 14",
    "sg:city":"Lovendegem",
    "sg:classifiers":[
        {
            "category":"Home & Garden",
            "subcategory":"Kitchen Supply",
            "type":"Retail Goods"
        }
    ],
    "sg:phone":"+32 9 372 68 63",
    "sg:postcode":"9920",
    "sg:province":"Oost-Vlaanderen",
    "sg:tags":[
        "-",
        "industrial",
        "installation",
        "equipment"
    ],
    "wof:name":"'spresso",
    "wof:placetype":"venue"
},
  "geometry": {"coordinates":[3.6351668835,51.1062583923],"type":"Point"}
}