{
  "type": "Feature",
  "properties": {
    "addr:full":"Rue Porselein 13 Anderlecht Bruxelles-Capitale 1070",
    "addr:housenumber":"13",
    "addr:postcode":"1070",
    "addr:street":"Rue Porselein",
    "iso:country":"BE",
    "sg:address":"Rue Porselein 13",
    "sg:city":"Anderlecht",
    "sg:orig_category":"Medische apparatuur, orthopedische artikelen and prothesen Fab",
    "sg:phone":"+32 2 523 92 60",
    "sg:postcode":"1070",
    "sg:province":"Bruxelles-Capitale",
    "wof:name":"Van Ackere",
    "wof:placetype":"venue"
},
  "geometry": {"coordinates":[4.3050041199,50.8361473083],"type":"Point"}
}