{
  "type": "Feature",
  "properties": {
    "iso:country":"BE",
    "sg:address":"Koeivijverstraat 61",
    "sg:city":"Dilbeek",
    "sg:orig_category":"Sportclubs",
    "sg:phone":"+32 2 569 70 32",
    "sg:postcode":"1700",
    "sg:province":"Vlaams-Brabant",
    "wof:name":"Tennis S.d.i.",
    "wof:placetype":"venue"
},
  "geometry": {"coordinates":[4.2483000755,50.8299293518],"type":"Point"}
}