{
  "type": "Feature",
  "properties": {
    "addr:full":"Route De Bastogne 39a Martelange Luxembourg 6630",
    "addr:housenumber":"39a",
    "addr:postcode":"6630",
    "addr:street":"Route De Bastogne",
    "iso:country":"BE",
    "sg:address":"Route De Bastogne 39a",
    "sg:city":"Martelange",
    "sg:classifiers":[
        {
            "category":"Food & Beverages",
            "subcategory":"Fruits & Vegetables",
            "type":"Retail Goods"
        }
    ],
    "sg:phone":"+32 63 60 16 52",
    "sg:postcode":"6630",
    "sg:province":"Luxembourg",
    "sg:tags":[
        "-"
    ],
    "wof:name":"Maison Feller",
    "wof:placetype":"venue"
},
  "geometry": {"coordinates":[5.738047123,49.8359184265],"type":"Point"}
}