{
  "type": "Feature",
  "properties": {
    "iso:country":"BE",
    "sg:address":"Rue Du Vallon 8",
    "sg:city":"Rixensart",
    "sg:orig_category":"Woningbouw",
    "sg:phone":"+32 2 653 16 49",
    "sg:postcode":"1332",
    "sg:province":"Brabant Wallon",
    "wof:name":"Warzee",
    "wof:placetype":"venue"
},
  "geometry": {"coordinates":[4.4985761642,50.7171554565],"type":"Point"}
}