{
  "type": "Feature",
  "properties": {
    "addr:full":"Rue Benjamin Lebrun 14 Enghien (petit-enghien) Hainaut 7850",
    "addr:housenumber":"14",
    "addr:postcode":"7850",
    "addr:street":"Rue Benjamin Lebrun",
    "iso:country":"BE",
    "sg:address":"Rue Benjamin Lebrun 14",
    "sg:city":"Enghien (petit-enghien)",
    "sg:classifiers":[
        {
            "category":"Building & Trades",
            "subcategory":"Electrical",
            "type":"Services"
        }
    ],
    "sg:phone":"+32 2 395 56 34",
    "sg:postcode":"7850",
    "sg:province":"Hainaut",
    "sg:tags":[
        "electric",
        "-",
        "housewiring",
        "contractor"
    ],
    "wof:name":"A.b. Electricit\u00e9 G\u00e9n\u00e9rale",
    "wof:placetype":"venue"
},
  "geometry": {"coordinates":[4.0491957664,50.6945037842],"type":"Point"}
}