{
  "type": "Feature",
  "properties": {
    "iso:country":"BE",
    "sg:address":"Rue Massart 4",
    "sg:city":"Court-saint-etienne",
    "sg:classifiers":[
        {
            "category":"Home & Garden",
            "subcategory":"Building Materials",
            "type":"Retail Goods"
        }
    ],
    "sg:phone":"+32 10 61 56 48",
    "sg:postcode":"1490",
    "sg:province":"Brabant Wallon",
    "sg:tags":[
        "wall",
        "cupboard"
    ],
    "wof:name":"Heylen Reno Habitat",
    "wof:placetype":"venue"
},
  "geometry": {"coordinates":[4.557721138,50.6163787842],"type":"Point"}
}