{
  "type": "Feature",
  "properties": {
    "iso:country":"BE",
    "sg:address":"Planchestraat 8",
    "sg:city":"Vloesberg/flobecq",
    "sg:orig_category":"Sportclubs",
    "sg:phone":"+32 68 44 70 67",
    "sg:postcode":"7880",
    "sg:province":"Hainaut",
    "wof:name":"Les Amis R\u00c9unis",
    "wof:placetype":"venue"
},
  "geometry": {"coordinates":[3.7241990566,50.7410774231],"type":"Point"}
}