{
  "type": "Feature",
  "properties": {
    "addr:full":"Gellenberg 83 Lubbeek Vlaams-Brabant 3210",
    "addr:housenumber":"83",
    "addr:postcode":"3210",
    "addr:street":"Gellenberg",
    "iso:country":"BE",
    "sg:address":"Gellenberg 83",
    "sg:city":"Lubbeek",
    "sg:orig_category":"M\u00e9decins and sp\u00e9cialistes",
    "sg:phone":"+32 16 63 54 58",
    "sg:postcode":"3210",
    "sg:province":"Vlaams-Brabant",
    "wof:name":"Kristin Adams",
    "wof:placetype":"venue"
},
  "geometry": {"coordinates":[4.8376197815,50.8842086792],"type":"Point"}
}