{
  "type": "Feature",
  "properties": {
    "addr:full":"Kolaerdstraat 109 Gistel West-Vlaanderen 8470",
    "addr:housenumber":"109",
    "addr:postcode":"8470",
    "addr:street":"Kolaerdstraat",
    "iso:country":"BE",
    "sg:address":"Kolaerdstraat 109",
    "sg:city":"Gistel",
    "sg:classifiers":[
        {
            "category":"Health Services",
            "subcategory":"Health Practitioner",
            "type":"Services"
        }
    ],
    "sg:phone":"+32 59 27 89 76",
    "sg:postcode":"8470",
    "sg:province":"West-Vlaanderen",
    "sg:tags":[
        "physiotherapist"
    ],
    "wof:name":"Monstrey A",
    "wof:placetype":"venue"
},
  "geometry": {"coordinates":[2.9517800808,51.1536254883],"type":"Point"}
}