{
  "type": "Feature",
  "properties": {
    "iso:country":"BE",
    "sg:address":"Rue Edith Cavell 155",
    "sg:city":"Ukkel/uccle",
    "sg:orig_category":"Services de Nettoyage and de D\u00e9sinfection. Rev\u00eatements de sols and murs",
    "sg:phone":"+32 2 374 28 15",
    "sg:postcode":"1180",
    "sg:province":"Bruxelles-Capitale",
    "wof:name":"M.l. Verdoot",
    "wof:placetype":"venue"
},
  "geometry": {"coordinates":[4.3577990532,50.8058624268],"type":"Point"}
}