{
  "type": "Feature",
  "properties": {
    "addr:full":"Rue De Villers-la Ville 65 Genappe Brabant Wallon 1471",
    "addr:housenumber":"65",
    "addr:postcode":"1471",
    "addr:street":"Rue De Villers-La Ville;Wallon",
    "iso:country":"BE",
    "sg:address":"Rue De Villers-la Ville 65",
    "sg:city":"Genappe",
    "sg:orig_category":"Articles de jardin. Mat\u00e9riaux de construction Gr",
    "sg:phone":"+32 67 79 02 04",
    "sg:postcode":"1471",
    "sg:province":"Brabant Wallon",
    "wof:name":"Genappe Mat\u00c9riaux",
    "wof:placetype":"venue"
},
  "geometry": {"coordinates":[4.4546198845,50.6058311462],"type":"Point"}
}