{
  "type": "Feature",
  "properties": {
    "iso:country":"BE",
    "sg:address":"Casterhovenstraat 39",
    "sg:city":"Hasselt",
    "sg:classifiers":[
        {
            "category":"Health Services",
            "subcategory":"Nursing And Care Facility",
            "type":"Services"
        }
    ],
    "sg:phone":"+32 477 45 89 39",
    "sg:postcode":"3500",
    "sg:province":"Limburg",
    "sg:tags":[
        "home"
    ],
    "wof:name":"Bergmans Diane",
    "wof:placetype":"venue"
},
  "geometry": {"coordinates":[5.354347229,50.9300460815],"type":"Point"}
}