{
  "type": "Feature",
  "properties": {
    "iso:country":"BE",
    "sg:address":"Tervuursesteenweg 96",
    "sg:city":"Zemst",
    "sg:orig_category":"M\u00e9decins and sp\u00e9cialistes",
    "sg:phone":"+32 15 41 66 01",
    "sg:postcode":"1981",
    "sg:province":"Vlaams-Brabant",
    "wof:name":"R. Tielemans",
    "wof:placetype":"venue"
},
  "geometry": {"coordinates":[4.4885759354,50.9981689453],"type":"Point"}
}