{
  "type": "Feature",
  "properties": {
    "addr:full":"Place Albert Ier 15 Wavre Brabant Wallon 1300",
    "addr:housenumber":"15;1300",
    "addr:street":"Place Albert Ier",
    "iso:country":"BE",
    "sg:address":"Place Albert Ier 15",
    "sg:city":"Wavre",
    "sg:orig_category":"Boekhandels Krantenwinkels",
    "sg:phone":"+32 10 41 16 03",
    "sg:postcode":"1300",
    "sg:province":"Brabant Wallon",
    "wof:name":"Librairie De Limal",
    "wof:placetype":"venue"
},
  "geometry": {"coordinates":[4.6243238449,50.7079315186],"type":"Point"}
}