{
  "type": "Feature",
  "properties": {
    "addr:full":"Kieverstraat 5 Kluisbergen Oost-Vlaanderen 9690",
    "addr:housenumber":"5",
    "addr:postcode":"9690",
    "addr:street":"Kieverstraat",
    "iso:country":"BE",
    "sg:address":"Kieverstraat 5",
    "sg:city":"Kluisbergen",
    "sg:orig_category":"Banken and kredietinstellingen",
    "sg:phone":"+32 55 38 91 26",
    "sg:postcode":"9690",
    "sg:province":"Oost-Vlaanderen",
    "wof:name":"Centea",
    "wof:placetype":"venue"
},
  "geometry": {"coordinates":[3.5145978928,50.7768478394],"type":"Point"}
}