{
  "type": "Feature",
  "properties": {
    "addr:full":"Quai Jean-baptiste-culot 18 Dinant Namur 5500",
    "addr:housenumber":"18",
    "addr:postcode":"5500",
    "addr:street":"Quai Jean-Baptiste-Culot",
    "iso:country":"BE",
    "sg:address":"Quai Jean-baptiste-culot 18",
    "sg:city":"Dinant",
    "sg:orig_category":"Herstellingen and onderhoud van auto's Voertuigen",
    "sg:phone":"+32 82 22 39 39",
    "sg:postcode":"5500",
    "sg:province":"Namur",
    "wof:name":"Garage Beaujean",
    "wof:placetype":"venue"
},
  "geometry": {"coordinates":[4.9079151154,50.2644042969],"type":"Point"}
}