{
  "type": "Feature",
  "properties": {
    "iso:country":"BE",
    "sg:address":"Rue De La Station 48",
    "sg:city":"Soignies",
    "sg:classifiers":[
        {
            "category":"Professional",
            "subcategory":"Lawyer & Legal Services",
            "type":"Services"
        }
    ],
    "sg:phone":"+32 67 33 49 54",
    "sg:postcode":"7060",
    "sg:province":"Hainaut",
    "wof:name":"Godfrind Jean-marc",
    "wof:placetype":"venue"
},
  "geometry": {"coordinates":[4.0699858665,50.5755844116],"type":"Point"}
}