{
  "type": "Feature",
  "properties": {
    "iso:country":"BE",
    "sg:address":"Witbos 26",
    "sg:city":"Herentals",
    "sg:orig_category":"Articles non-alimentaires",
    "sg:phone":"+32 14 26 15 73",
    "sg:postcode":"2200",
    "sg:province":"Antwerpen",
    "wof:name":"Huis Bogaert-de Hin",
    "wof:placetype":"venue"
},
  "geometry": {"coordinates":[4.8352470398,51.1293754578],"type":"Point"}
}