{
  "type": "Feature",
  "properties": {
    "iso:country":"BE",
    "sg:address":"Brugsesteenweg 46",
    "sg:city":"Kortrijk",
    "sg:classifiers":[
        {
            "category":"Bakery",
            "type":"Food & Drink"
        }
    ],
    "sg:phone":"+32 56 35 47 59",
    "sg:postcode":"8500",
    "sg:province":"West-Vlaanderen",
    "sg:tags":[
        "confectioner",
        "baker"
    ],
    "wof:name":"Vanzieleghem Bvba",
    "wof:placetype":"venue"
},
  "geometry": {"coordinates":[3.2624518871,50.8373985291],"type":"Point"}
}