{
  "type": "Feature",
  "properties": {
    "iso:country":"BE",
    "sg:address":"Rue De Philippeville 20",
    "sg:city":"Ham-sur-heure-nalinnes",
    "sg:orig_category":"Tabac. Journaux",
    "sg:phone":"+32 71 21 90 92",
    "sg:postcode":"6120",
    "sg:province":"Hainaut",
    "wof:name":"Librairie Clin D'oeil",
    "wof:placetype":"venue"
},
  "geometry": {"coordinates":[4.4733738899,50.3421173096],"type":"Point"}
}