{
  "type": "Feature",
  "properties": {
    "iso:country":"BE",
    "sg:address":"Steenweg Op Brussel 257",
    "sg:city":"Wemmel/wemmel",
    "sg:orig_category":"Brood, gebak and snoepgoed",
    "sg:phone":"+32 2 460 59 28",
    "sg:postcode":"1780",
    "sg:province":"Vlaams-Brabant",
    "wof:name":"Henri Coolen",
    "wof:placetype":"venue"
},
  "geometry": {"coordinates":[4.3097071648,50.8997001648],"type":"Point"}
}