{
  "type": "Feature",
  "properties": {
    "addr:full":"Chauss\u00c9e De Waterloo 1535 Ukkel/uccle Bruxelles-Capitale 1180",
    "addr:postcode":"1535;1180",
    "addr:street":"Chausse\u0301E De Waterloo",
    "iso:country":"BE",
    "sg:address":"Chauss\u00c9e De Waterloo 1535",
    "sg:city":"Ukkel/uccle",
    "sg:orig_category":"Autoverhuur Benzinestations and brandstoffen",
    "sg:phone":"+32 2 374 60 96",
    "sg:postcode":"1180",
    "sg:province":"Bruxelles-Capitale",
    "wof:name":"Texaco",
    "wof:placetype":"venue"
},
  "geometry": {"coordinates":[4.3810768127,50.7807350159],"type":"Point"}
}