{
  "type": "Feature",
  "properties": {
    "addr:full":"Place J.-p.-lavall\u00c9 5 Virton Luxembourg 6762",
    "addr:housenumber":"5",
    "addr:postcode":"6762",
    "addr:street":"Place J.-P.-Lavalle\u0301",
    "iso:country":"BE",
    "sg:address":"Place J.-p.-lavall\u00c9 5",
    "sg:city":"Virton",
    "sg:classifiers":[
        {
            "category":"Cafe",
            "type":"Food & Drink"
        }
    ],
    "sg:phone":"+32 63 57 07 90",
    "sg:postcode":"6762",
    "sg:province":"Luxembourg",
    "sg:tags":[
        "caf\u00e9s"
    ],
    "wof:name":"Sama Caf\u00c9",
    "wof:placetype":"venue"
},
  "geometry": {"coordinates":[5.5332231522,49.5546951294],"type":"Point"}
}