{
  "type": "Feature",
  "properties": {
    "iso:country":"BE",
    "sg:address":"Koningin Astridlaan 29",
    "sg:city":"Lier",
    "sg:classifiers":[
        {
            "category":"Health Services",
            "subcategory":"Dentist",
            "type":"Services"
        }
    ],
    "sg:phone":"+32 3 488 20 91",
    "sg:postcode":"2500",
    "sg:province":"Antwerpen",
    "wof:name":"De Pauw Guy",
    "wof:placetype":"venue"
},
  "geometry": {"coordinates":[4.5781140327,51.1268081665],"type":"Point"}
}