{
  "type": "Feature",
  "properties": {
    "iso:country":"BE",
    "sg:address":"Veldhoven 54",
    "sg:city":"Herentals",
    "sg:orig_category":"Domotics",
    "sg:phone":"+32 14 72 50 58",
    "sg:postcode":"2200",
    "sg:province":"Antwerpen",
    "wof:name":"Electro Segers",
    "wof:placetype":"venue"
},
  "geometry": {"coordinates":[4.8105111122,51.1623191833],"type":"Point"}
}