{
  "type": "Feature",
  "properties": {
    "addr:full":"Place Du Perron 32 Ch\u00e2telet Hainaut 6200",
    "addr:housenumber":"32",
    "addr:postcode":"6200",
    "addr:street":"Place Du Perron",
    "iso:country":"BE",
    "sg:address":"Place Du Perron 32",
    "sg:city":"Ch\u00e2telet",
    "sg:classifiers":[
        {
            "category":"Shopping",
            "subcategory":"Jewelry",
            "type":"Retail Goods"
        }
    ],
    "sg:phone":"+32 71 38 07 81",
    "sg:postcode":"6200",
    "sg:province":"Hainaut",
    "sg:tags":[
        "jeweller",
        "-"
    ],
    "wof:name":"Maison Alexandre",
    "wof:placetype":"venue"
},
  "geometry": {"coordinates":[4.5213952065,50.4045257568],"type":"Point"}
}