{
  "type": "Feature",
  "properties": {
    "addr:full":"Chauss\u00e9e D'alsemberg 710 Bruxelles (uccle) Bruxelles-Capitale 1180",
    "addr:housenumber":"710",
    "addr:postcode":"1180",
    "addr:street":"Chausse\u0301E D'Alsemberg",
    "iso:country":"BE",
    "sg:address":"Chauss\u00e9e D'alsemberg 710",
    "sg:city":"Bruxelles (uccle)",
    "sg:classifiers":[
        {
            "category":"Shopping",
            "subcategory":"Jewelry",
            "type":"Retail Goods"
        }
    ],
    "sg:phone":"+32 2 345 75 90",
    "sg:postcode":"1180",
    "sg:province":"Bruxelles-Capitale",
    "sg:tags":[
        "-",
        "imitation"
    ],
    "wof:name":"Twice As Nice",
    "wof:placetype":"venue"
},
  "geometry": {"coordinates":[4.3368721008,50.8021125793],"type":"Point"}
}