{
  "type": "Feature",
  "properties": {
    "addr:full":"Rue Henri Degorge 23 Hornu Hainaut 7301",
    "addr:housenumber":"23",
    "addr:postcode":"7301",
    "addr:street":"Rue Henri Degorge",
    "iso:country":"BE",
    "sg:address":"Rue Henri Degorge 23",
    "sg:city":"Hornu",
    "sg:orig_category":"Diverse opleidingen and onderwijs",
    "sg:phone":"+32 65 76 67 10",
    "sg:postcode":"7301",
    "sg:province":"Hainaut",
    "wof:name":"Technocit\u00c9",
    "wof:placetype":"venue"
},
  "geometry": {"coordinates":[3.8397390842,50.4344139099],"type":"Point"}
}