{
  "type": "Feature",
  "properties": {
    "iso:country":"BE",
    "sg:address":"Zweerdstraat 8bb2",
    "sg:city":"Ieper",
    "sg:orig_category":"Plaatsen van vloer- and muurbekleding Schilders",
    "sg:phone":"+32 57 33 69 83",
    "sg:postcode":"8900",
    "sg:province":"West-Vlaanderen",
    "wof:name":"Bavo S.i.",
    "wof:placetype":"venue"
},
  "geometry": {"coordinates":[2.8067040443,50.8314819336],"type":"Point"}
}