{
  "type": "Feature",
  "properties": {
    "addr:full":"Kerkstraat 152 Grimbergen (humbeek) Vlaams-Brabant 1851",
    "addr:housenumber":"152",
    "addr:postcode":"1851",
    "addr:street":"Kerkstraat",
    "iso:country":"BE",
    "sg:address":"Kerkstraat 152",
    "sg:city":"Grimbergen (humbeek)",
    "sg:classifiers":[
        {
            "category":"Banks & Credit Unions",
            "subcategory":"Investment Brokerage",
            "type":"Services"
        }
    ],
    "sg:phone":"+32 2 270 19 70",
    "sg:postcode":"1851",
    "sg:province":"Vlaams-Brabant",
    "sg:tags":[
        "auditor"
    ],
    "wof:name":"Van Goolen G",
    "wof:placetype":"venue"
},
  "geometry": {"coordinates":[4.3866209984,50.9739875793],"type":"Point"}
}