{
  "type": "Feature",
  "properties": {
    "addr:full":"Beukenstraat 3 Olen Antwerpen 2250",
    "addr:housenumber":"3",
    "addr:postcode":"2250",
    "addr:street":"Beukenstraat",
    "iso:country":"BE",
    "sg:address":"Beukenstraat 3",
    "sg:city":"Olen",
    "sg:classifiers":[
        {
            "category":"Building & Trades",
            "subcategory":"Plumbing",
            "type":"Services"
        }
    ],
    "sg:phone":"+32 475 84 37 87",
    "sg:postcode":"2250",
    "sg:province":"Antwerpen",
    "sg:tags":[
        "repair",
        "mainten",
        "-",
        "central",
        "heating"
    ],
    "wof:name":"Vansprengel Dirk Cv",
    "wof:placetype":"venue"
},
  "geometry": {"coordinates":[4.8463702202,51.1465644836],"type":"Point"}
}