{
  "type": "Feature",
  "properties": {
    "addr:full":"Schoenbeekstraat 21 Alken Limburg 3570",
    "addr:housenumber":"21",
    "addr:postcode":"3570",
    "addr:street":"Schoenbeekstraat",
    "iso:country":"BE",
    "sg:address":"Schoenbeekstraat 21",
    "sg:city":"Alken",
    "sg:orig_category":"Artiesten and kunstenaars",
    "sg:phone":"+32 11 37 65 88",
    "sg:postcode":"3570",
    "sg:province":"Limburg",
    "wof:name":"Lucien Verlee",
    "wof:placetype":"venue"
},
  "geometry": {"coordinates":[5.3430957794,50.870475769],"type":"Point"}
}