{
  "type": "Feature",
  "properties": {
    "addr:full":"Hendrik Baelskaai 24 Oostende West-Vlaanderen 8400",
    "addr:housenumber":"24",
    "addr:postcode":"8400",
    "iso:country":"BE",
    "sg:address":"Hendrik Baelskaai 24",
    "sg:city":"Oostende",
    "sg:classifiers":[
        {
            "category":"Food & Beverages",
            "subcategory":"Supermarket",
            "type":"Retail Goods"
        }
    ],
    "sg:phone":"+32 59 32 04 81",
    "sg:postcode":"8400",
    "sg:province":"West-Vlaanderen",
    "sg:tags":[
        "frozen",
        "-"
    ],
    "wof:name":"Mccain Froozen Foods",
    "wof:placetype":"venue"
},
  "geometry": {"coordinates":[2.9351189137,51.2330436707],"type":"Point"}
}