{
  "type": "Feature",
  "properties": {
    "addr:full":"Berlarij 19 Lier Antwerpen 2500",
    "addr:housenumber":"19",
    "addr:postcode":"2500",
    "addr:street":"Berlarij",
    "iso:country":"BE",
    "sg:address":"Berlarij 19",
    "sg:city":"Lier",
    "sg:orig_category":"V\u00eatements pour Hommes",
    "sg:phone":"+32 3 488 27 09",
    "sg:postcode":"2500",
    "sg:province":"Antwerpen",
    "wof:name":"Huis Vice Versa",
    "wof:placetype":"venue"
},
  "geometry": {"coordinates":[4.5783381462,51.1288604736],"type":"Point"}
}