{
  "type": "Feature",
  "properties": {
    "addr:full":"Contour De L'eglise 1bb Estaimpuis Hainaut 7730",
    "addr:housenumber":"1bb",
    "addr:postcode":"7730",
    "addr:street":"De L'Eglise;Hainaut",
    "iso:country":"BE",
    "sg:address":"Contour De L'eglise 1bb",
    "sg:city":"Estaimpuis",
    "sg:orig_category":"Enseignement maternel and primaire",
    "sg:phone":"+32 56 48 76 62",
    "sg:postcode":"7730",
    "sg:province":"Hainaut",
    "wof:name":"Ecole Fond. Communale",
    "wof:placetype":"venue"
},
  "geometry": {"coordinates":[3.2643659115,50.7064094543],"type":"Point"}
}