{
  "type": "Feature",
  "properties": {
    "iso:country":"BE",
    "sg:address":"Sint-rochusstraat 21",
    "sg:city":"Balen",
    "sg:classifiers":[
        {
            "category":"Health Services",
            "subcategory":"Nursing And Care Facility",
            "type":"Services"
        }
    ],
    "sg:phone":"+32 14 81 22 74",
    "sg:postcode":"2490",
    "sg:province":"Antwerpen",
    "sg:tags":[
        "home"
    ],
    "wof:name":"Lodewyckx B",
    "wof:placetype":"venue"
},
  "geometry": {"coordinates":[5.1780238152,51.1669998169],"type":"Point"}
}