{
  "type": "Feature",
  "properties": {
    "iso:country":"BE",
    "sg:address":"Rue Du Grand Pr\u00c9 60",
    "sg:city":"Comblain-au-pont",
    "sg:orig_category":"Herstellingen and onderhoud van auto's",
    "sg:phone":"+32 4 369 13 50",
    "sg:postcode":"4170",
    "sg:province":"Li\u00e8ge",
    "wof:name":"Garage Du Grand Pr\u00c9",
    "wof:placetype":"venue"
},
  "geometry": {"coordinates":[5.5802388191,50.4674263],"type":"Point"}
}