{
  "type": "Feature",
  "properties": {
    "iso:country":"BE",
    "sg:address":"Chauss\u00e9e De Lille 353",
    "sg:city":"Mouscron",
    "sg:classifiers":[
        {
            "category":"Professional",
            "subcategory":"Computer Services",
            "type":"Services"
        }
    ],
    "sg:phone":"+32 56 34 00 59",
    "sg:postcode":"7700",
    "sg:province":"Hainaut",
    "sg:tags":[
        "-",
        "processing",
        "data"
    ],
    "wof:name":"Visuel.com (le)",
    "wof:placetype":"venue"
},
  "geometry": {"coordinates":[3.187114954,50.7517852783],"type":"Point"}
}