{
  "type": "Feature",
  "properties": {
    "iso:country":"BE",
    "sg:address":"Voorstraat 7",
    "sg:city":"Kortrijk",
    "sg:orig_category":"Brood, gebak and snoepgoed",
    "sg:phone":"+32 56 22 18 39",
    "sg:postcode":"8500",
    "sg:province":"West-Vlaanderen",
    "wof:name":"Delsens",
    "wof:placetype":"venue"
},
  "geometry": {"coordinates":[3.2707140446,50.8276901245],"type":"Point"}
}