{
  "type": "Feature",
  "properties": {
    "iso:country":"BE",
    "sg:address":"Route De Xhoffraix 41",
    "sg:city":"Stavelot",
    "sg:orig_category":"Vakantiedorpen",
    "sg:phone":"+32 87 27 51 47",
    "sg:postcode":"4970",
    "sg:province":"Li\u00e8ge",
    "wof:name":"Amis De La Nature",
    "wof:placetype":"venue"
},
  "geometry": {"coordinates":[5.999630928,50.4797058105],"type":"Point"}
}