{
  "type": "Feature",
  "properties": {
    "addr:full":"Sluizenstraat 47 Schoten Antwerpen 2900",
    "addr:housenumber":"47",
    "addr:postcode":"2900",
    "addr:street":"Sluizenstraat",
    "iso:country":"BE",
    "sg:address":"Sluizenstraat 47",
    "sg:city":"Schoten",
    "sg:orig_category":"Flongs",
    "sg:phone":"+32 3 658 07 49",
    "sg:postcode":"2900",
    "sg:province":"Antwerpen",
    "wof:name":"Ivo Martens B.v.b.a.",
    "wof:placetype":"venue"
},
  "geometry": {"coordinates":[4.5063209534,51.2491645813],"type":"Point"}
}