{
  "type": "Feature",
  "properties": {
    "iso:country":"BE",
    "sg:address":"Avenue D'auderghem 84",
    "sg:city":"Bruxelles (etterbeek)",
    "sg:classifiers":[
        {
            "category":"Professional",
            "subcategory":"Lawyer & Legal Services",
            "type":"Services"
        }
    ],
    "sg:phone":"+32 2 737 71 80",
    "sg:postcode":"1040",
    "sg:province":"Bruxelles-Capitale",
    "sg:tags":[
        "-",
        "foreign"
    ],
    "wof:name":"Leinen & Derichs",
    "wof:placetype":"venue"
},
  "geometry": {"coordinates":[4.3862199783,50.838394165],"type":"Point"}
}