{
  "type": "Feature",
  "properties": {
    "iso:country":"BE",
    "sg:address":"Hauwerstraat 5",
    "sg:city":"Brugge",
    "sg:classifiers":[
        {
            "category":"Bars & Pubs",
            "type":"Food & Drink"
        }
    ],
    "sg:phone":"+32 50 34 53 50",
    "sg:postcode":"8000",
    "sg:province":"West-Vlaanderen",
    "wof:name":"Vetten Os",
    "wof:placetype":"venue"
},
  "geometry": {"coordinates":[3.2157011032,51.2038650513],"type":"Point"}
}