{
  "type": "Feature",
  "properties": {
    "iso:country":"BE",
    "sg:address":"Aalststraat 3",
    "sg:city":"Oudenaarde",
    "sg:orig_category":"Producteurs de fruits",
    "sg:phone":"+32 55 31 12 91",
    "sg:postcode":"9700",
    "sg:province":"Oost-Vlaanderen",
    "wof:name":"Aldia",
    "wof:placetype":"venue"
},
  "geometry": {"coordinates":[3.6105720997,50.8362503052],"type":"Point"}
}