{
  "type": "Feature",
  "properties": {
    "iso:country":"BE",
    "sg:address":"Chauss\u00e9e De Tirlemont 137",
    "sg:city":"Jodoigne",
    "sg:classifiers":[
        {
            "category":"Structure",
            "subcategory":"Office Building",
            "type":"Public Place"
        }
    ],
    "sg:phone":"+32 10 81 33 33",
    "sg:postcode":"1370",
    "sg:province":"Brabant Wallon",
    "sg:tags":[
        "roofing",
        "slate"
    ],
    "wof:name":"Lesage Fres",
    "wof:placetype":"venue"
},
  "geometry": {"coordinates":[4.8803319931,50.7329330444],"type":"Point"}
}