{
  "type": "Feature",
  "properties": {
    "iso:country":"BE",
    "sg:address":"Chauss\u00e9e De Charleroi 302",
    "sg:city":"Jodoigne",
    "sg:classifiers":[
        {
            "category":"Manufacturing",
            "subcategory":"Paper Products",
            "type":"Manufacturing & Wholesale Goods"
        }
    ],
    "sg:phone":"+32 10 81 30 54",
    "sg:postcode":"1370",
    "sg:province":"Brabant Wallon",
    "sg:tags":[
        "bookbinding"
    ],
    "wof:name":"Lambermont S",
    "wof:placetype":"venue"
},
  "geometry": {"coordinates":[4.8615598679,50.7133712769],"type":"Point"}
}