{
  "type": "Feature",
  "properties": {
    "addr:full":"Nederheirweg 46 Waasmunster Oost-Vlaanderen 9250",
    "addr:housenumber":"46",
    "addr:postcode":"9250",
    "addr:street":"Nederheirweg",
    "iso:country":"BE",
    "sg:address":"Nederheirweg 46",
    "sg:city":"Waasmunster",
    "sg:orig_category":"Charpentes and couvertures",
    "sg:phone":"+32 9 349 14 88",
    "sg:postcode":"9250",
    "sg:province":"Oost-Vlaanderen",
    "wof:name":"Dakwerken Luc Baeck",
    "wof:placetype":"venue"
},
  "geometry": {"coordinates":[4.0579071045,51.1104316711],"type":"Point"}
}