{
  "type": "Feature",
  "properties": {
    "iso:country":"BE",
    "sg:address":"Elzelestraat 37-39",
    "sg:city":"Ronse/renaix",
    "sg:orig_category":"Herstellingen and onderhoud van auto's",
    "sg:phone":"+32 55 21 35 25",
    "sg:postcode":"9600",
    "sg:province":"Oost-Vlaanderen",
    "wof:name":"Garage Landrien",
    "wof:placetype":"venue"
},
  "geometry": {"coordinates":[3.6057040691,50.7468414307],"type":"Point"}
}