{
  "type": "Feature",
  "properties": {
    "iso:country":"BE",
    "sg:address":"Vichtsesteenweg 171",
    "sg:city":"Anzegem",
    "sg:orig_category":"Eleveurs and marchands de porcs",
    "sg:phone":"+32 56 68 94 41",
    "sg:postcode":"8570",
    "sg:province":"West-Vlaanderen",
    "wof:name":"Albert Verhelst",
    "wof:placetype":"venue"
},
  "geometry": {"coordinates":[3.4380149841,50.8429374695],"type":"Point"}
}