{
  "type": "Feature",
  "properties": {
    "addr:full":"Rue Gr\u00c9try 23 Li\u00c8ge Li\u00e8ge 4020",
    "addr:housenumber":"23",
    "addr:postcode":"4020",
    "addr:street":"Rue Gre\u0301Try",
    "iso:country":"BE",
    "sg:address":"Rue Gr\u00c9try 23",
    "sg:city":"Li\u00c8ge",
    "sg:classifiers":[
        {
            "category":"Cafe",
            "type":"Food & Drink"
        }
    ],
    "sg:phone":"+32 4 343 51 76",
    "sg:postcode":"4020",
    "sg:province":"Li\u00e8ge",
    "sg:tags":[
        "caf\u00e9s"
    ],
    "wof:name":"Aux Caves De Longdoz",
    "wof:placetype":"venue"
},
  "geometry": {"coordinates":[5.5789370537,50.6371917725],"type":"Point"}
}