{
  "type": "Feature",
  "properties": {
    "iso:country":"BE",
    "sg:address":"Avenue De L'uruguay 28",
    "sg:city":"Bruxelles",
    "sg:classifiers":[
        {
            "category":"Government",
            "subcategory":"Embassy",
            "type":"Public Place"
        }
    ],
    "sg:phone":"+32 2 675 02 28",
    "sg:postcode":"1000",
    "sg:province":"Bruxelles-Capitale",
    "sg:tags":[
        "consulate"
    ],
    "wof:name":"Ligue Des Etats Arabes (mission Permanente)",
    "wof:placetype":"venue"
},
  "geometry": {"coordinates":[4.3951539993,50.8008956909],"type":"Point"}
}