{
  "type": "Feature",
  "properties": {
    "addr:full":"Avenue Albert I 1 Vis\u00e9 Li\u00e8ge 4600",
    "addr:housenumber":"1",
    "addr:postcode":"4600",
    "addr:street":"Avenue Albert I",
    "iso:country":"BE",
    "sg:address":"Avenue Albert I 1",
    "sg:city":"Vis\u00e9",
    "sg:classifiers":[
        {
            "category":"Bakery",
            "type":"Food & Drink"
        }
    ],
    "sg:phone":"+32 4 379 25 09",
    "sg:postcode":"4600",
    "sg:province":"Li\u00e8ge",
    "sg:tags":[
        "confectioner",
        "baker"
    ],
    "wof:name":"D\u00e9lices (aux)",
    "wof:placetype":"venue"
},
  "geometry": {"coordinates":[5.7004270554,50.7367095947],"type":"Point"}
}