{
  "type": "Feature",
  "properties": {
    "addr:full":"Dr\u00e8ve De Nivelles 145 Bruxelles (woluwe-saint-pierre) Bruxelles-Capitale 1150",
    "addr:housenumber":"145",
    "addr:postcode":"1150",
    "addr:street":"Dre\u0300Ve De Nivelles",
    "iso:country":"BE",
    "sg:address":"Dr\u00e8ve De Nivelles 145",
    "sg:city":"Bruxelles (woluwe-saint-pierre)",
    "sg:classifiers":[
        {
            "category":"Health Services",
            "subcategory":"Health Practitioner",
            "type":"Services"
        }
    ],
    "sg:phone":"+32 2 673 90 29",
    "sg:postcode":"1150",
    "sg:province":"Bruxelles-Capitale",
    "sg:tags":[
        "therapist",
        "speech"
    ],
    "wof:name":"Bistiaux",
    "wof:placetype":"venue"
},
  "geometry": {"coordinates":[4.4104528427,50.8249511719],"type":"Point"}
}