{
  "type": "Feature",
  "properties": {
    "addr:full":"Th. Decuyperstraat 165b51 Sint-lambrechts-woluwe/woluwe-saint-lambert Bruxelles-Capitale 1200",
    "addr:housenumber":"165b51 sint-lambrechts-woluwe",
    "addr:postcode":"1200",
    "addr:street":"Decuyperstraat",
    "iso:country":"BE",
    "sg:address":"Th. Decuyperstraat 165b51",
    "sg:city":"Sint-lambrechts-woluwe/woluwe-saint-lambert",
    "sg:orig_category":"Apotheken",
    "sg:phone":"+32 2 770 05 96",
    "sg:postcode":"1200",
    "sg:province":"Bruxelles-Capitale",
    "wof:name":"Pharmacie Schmit",
    "wof:placetype":"venue"
},
  "geometry": {"coordinates":[4.4252500534,50.8438110352],"type":"Point"}
}