{
  "type": "Feature",
  "properties": {
    "iso:country":"BE",
    "sg:address":"Turnhoutsebaan 172",
    "sg:city":"Malle",
    "sg:orig_category":"Dranken Zuivelproducten",
    "sg:phone":"+32 3 312 06 50",
    "sg:postcode":"2390",
    "sg:province":"Antwerpen",
    "wof:name":"Drankcenter Kerstens",
    "wof:placetype":"venue"
},
  "geometry": {"coordinates":[4.7593979836,51.301410675],"type":"Point"}
}