{
  "type": "Feature",
  "properties": {
    "addr:full":"Universiteitslaan 13 Hasselt Limburg 3500",
    "addr:housenumber":"13",
    "addr:postcode":"3500",
    "addr:street":"Universiteitslaan",
    "iso:country":"BE",
    "sg:address":"Universiteitslaan 13",
    "sg:city":"Hasselt",
    "sg:classifiers":[
        {
            "category":"Community Center",
            "subcategory":"Ethnic",
            "type":"Public Place"
        }
    ],
    "sg:phone":"+32 11 71 22 99",
    "sg:postcode":"3500",
    "sg:province":"Limburg",
    "sg:tags":[
        "medium"
    ],
    "wof:name":"Avalon",
    "wof:placetype":"venue"
},
  "geometry": {"coordinates":[5.3700032234,50.9305953979],"type":"Point"}
}