{
  "type": "Feature",
  "properties": {
    "addr:full":"Vorstse Steenweg 64 Sint-gillis/saint-gilles Bruxelles-Capitale 1060",
    "addr:housenumber":"64",
    "addr:postcode":"1060",
    "addr:street":"Vorstse Steenweg",
    "iso:country":"BE",
    "sg:address":"Vorstse Steenweg 64",
    "sg:city":"Sint-gillis/saint-gilles",
    "sg:orig_category":"Artsen and specialisten",
    "sg:phone":"+32 2 538 22 51",
    "sg:postcode":"1060",
    "sg:province":"Bruxelles-Capitale",
    "wof:name":"Jos\u00c9-maria Fernandez",
    "wof:placetype":"venue"
},
  "geometry": {"coordinates":[4.3405008316,50.8315315247],"type":"Point"}
}