{
  "type": "Feature",
  "properties": {
    "iso:country":"BE",
    "sg:address":"Sint-veerleplein 11",
    "sg:city":"Gent",
    "sg:orig_category":"Mus\u00e9es and patrimoine culturel",
    "sg:phone":"+32 9 225 93 06",
    "sg:postcode":"9000",
    "sg:province":"Oost-Vlaanderen",
    "wof:name":"Museum V. Gerechtsvoorwerpen",
    "wof:placetype":"venue"
},
  "geometry": {"coordinates":[3.7211129665,51.0569458008],"type":"Point"}
}