{
  "type": "Feature",
  "properties": {
    "addr:full":"Boerenstraat 37 Etterbeek Bruxelles-Capitale 1040",
    "addr:housenumber":"37",
    "addr:postcode":"1040",
    "addr:street":"Boerenstraat",
    "iso:country":"BE",
    "sg:address":"Boerenstraat 37",
    "sg:city":"Etterbeek",
    "sg:orig_category":"Binnenhuisarchitecten",
    "sg:phone":"+32 2 735 59 10",
    "sg:postcode":"1040",
    "sg:province":"Bruxelles-Capitale",
    "wof:name":"Crearte",
    "wof:placetype":"venue"
},
  "geometry": {"coordinates":[4.3927488327,50.8358955383],"type":"Point"}
}