{
  "type": "Feature",
  "properties": {
    "iso:country":"BE",
    "sg:address":"Spoorwegstraat 8",
    "sg:city":"Herent",
    "sg:orig_category":"Gestion des d\u00e9charges and sites d\u00e9finitifs de stockage",
    "sg:phone":"+32 16 21 13 82",
    "sg:postcode":"3020",
    "sg:province":"Vlaams-Brabant",
    "wof:name":"Containerpark Herent",
    "wof:placetype":"venue"
},
  "geometry": {"coordinates":[4.6701598167,50.9030380249],"type":"Point"}
}