{
  "type": "Feature",
  "properties": {
    "addr:full":"Rue Des Laderies 4b La Bruy\u00e8re (villers-lez-heest) Namur 5080",
    "addr:housenumber":"4b",
    "addr:postcode":"5080",
    "addr:street":"Rue Des Laderies;Namur",
    "iso:country":"BE",
    "sg:address":"Rue Des Laderies 4b",
    "sg:city":"La Bruy\u00e8re (villers-lez-heest)",
    "sg:classifiers":[
        {
            "category":"Sports & Exercise",
            "subcategory":"Stables",
            "type":"Entertainment"
        }
    ],
    "sg:phone":"+32 81 51 37 37",
    "sg:postcode":"5080",
    "sg:province":"Namur",
    "sg:tags":[
        "riding",
        "school"
    ],
    "wof:name":"Poney Club Arets",
    "wof:placetype":"venue"
},
  "geometry": {"coordinates":[4.8421931267,50.5278968811],"type":"Point"}
}