{
  "type": "Feature",
  "properties": {
    "addr:full":"Rue Froide 12 Ham-sur-heure-nalinnes Hainaut 6120",
    "addr:housenumber":"12",
    "addr:postcode":"6120",
    "addr:street":"Rue Froide;Hainaut",
    "iso:country":"BE",
    "sg:address":"Rue Froide 12",
    "sg:city":"Ham-sur-heure-nalinnes",
    "sg:classifiers":[
        {
            "category":"Personal",
            "subcategory":"Beauty Salon",
            "type":"Services"
        }
    ],
    "sg:phone":"+32 71 21 32 59",
    "sg:postcode":"6120",
    "sg:province":"Hainaut",
    "sg:tags":[
        "de",
        "coiffure"
    ],
    "wof:name":"Daniel",
    "wof:placetype":"venue"
},
  "geometry": {"coordinates":[4.3872900009,50.3219146729],"type":"Point"}
}