{
  "type": "Feature",
  "properties": {
    "addr:full":"Bochtlaan 12b8 Genk Limburg 3600",
    "addr:housenumber":"12b8",
    "addr:postcode":"3600",
    "addr:street":"Bochtlaan",
    "iso:country":"BE",
    "sg:address":"Bochtlaan 12b8",
    "sg:city":"Genk",
    "sg:orig_category":"Advocaten and juridische adviseurs",
    "sg:phone":"+32 89 35 17 18",
    "sg:postcode":"3600",
    "sg:province":"Limburg",
    "wof:name":"Christel Vanreyten",
    "wof:placetype":"venue"
},
  "geometry": {"coordinates":[5.5022702217,50.9666023254],"type":"Point"}
}