{
  "type": "Feature",
  "properties": {
    "iso:country":"BE",
    "sg:address":"Rue Du Centre 18bb",
    "sg:city":"Profondeville",
    "sg:orig_category":"Journaux. Tabac",
    "sg:phone":"+32 81 43 44 68",
    "sg:postcode":"5170",
    "sg:province":"Namur",
    "wof:name":"Horizon",
    "wof:placetype":"venue"
},
  "geometry": {"coordinates":[4.8674049377,50.3786392212],"type":"Point"}
}