{
  "type": "Feature",
  "properties": {
    "addr:full":"Rue De Frameries 6 Qu\u00e9vy (qu\u00e9vy-le-petit) Hainaut 7040",
    "addr:housenumber":"6",
    "addr:postcode":"7040",
    "addr:street":"Rue De Frameries;Que\u0301Vy-Le-Petit Hainaut",
    "iso:country":"BE",
    "sg:address":"Rue De Frameries 6",
    "sg:city":"Qu\u00e9vy (qu\u00e9vy-le-petit)",
    "sg:classifiers":[
        {
            "category":"Health Services",
            "subcategory":"Dentist",
            "type":"Services"
        }
    ],
    "sg:phone":"+32 65 56 73 94",
    "sg:postcode":"7040",
    "sg:province":"Hainaut",
    "wof:name":"Coche Ph",
    "wof:placetype":"venue"
},
  "geometry": {"coordinates":[3.938229084,50.368144989],"type":"Point"}
}