{
  "type": "Feature",
  "properties": {
    "addr:full":"Leenstraat 51 Izegem West-Vlaanderen 8870",
    "addr:housenumber":"51",
    "addr:postcode":"8870",
    "addr:street":"Leenstraat",
    "iso:country":"BE",
    "sg:address":"Leenstraat 51",
    "sg:city":"Izegem",
    "sg:orig_category":"R\u00e9alisation de programmes and logiciels",
    "sg:phone":"+32 51 30 75 58",
    "sg:postcode":"8870",
    "sg:province":"West-Vlaanderen",
    "wof:name":"C.c.i.",
    "wof:placetype":"venue"
},
  "geometry": {"coordinates":[3.1957778931,50.910785675],"type":"Point"}
}