{
  "type": "Feature",
  "properties": {
    "iso:country":"BE",
    "sg:address":"Oelegemsesteenweg 27a",
    "sg:city":"Ranst (broechem)",
    "sg:classifiers":[
        {
            "category":"Insurance",
            "subcategory":"Insurance Agent",
            "type":"Services"
        }
    ],
    "sg:phone":"+32 3 485 54 20",
    "sg:postcode":"2520",
    "sg:province":"Antwerpen",
    "sg:tags":[
        "broker"
    ],
    "wof:name":"Nauwelaers H",
    "wof:placetype":"venue"
},
  "geometry": {"coordinates":[4.6047000885,51.1887283325],"type":"Point"}
}