{
  "type": "Feature",
  "properties": {
    "addr:full":"Chauss\u00c9e De Bruxelles 535 Waterloo Brabant Wallon 1410",
    "addr:housenumber":"535",
    "addr:postcode":"1410",
    "addr:street":"Chausse\u0301E De Bruxelles",
    "iso:country":"BE",
    "sg:address":"Chauss\u00c9e De Bruxelles 535",
    "sg:city":"Waterloo",
    "sg:orig_category":"Herstellingen and onderhoud van auto's",
    "sg:phone":"+32 2 384 48 85",
    "sg:postcode":"1410",
    "sg:province":"Brabant Wallon",
    "wof:name":"Garage Hazard",
    "wof:placetype":"venue"
},
  "geometry": {"coordinates":[4.4059472084,50.6915054321],"type":"Point"}
}