{
  "type": "Feature",
  "properties": {
    "iso:country":"BE",
    "sg:address":"Botermelkstraat 8",
    "sg:city":"Erpe-mere",
    "sg:classifiers":[
        {
            "category":"Personal",
            "subcategory":"Beauty Salon",
            "type":"Services"
        }
    ],
    "sg:phone":"+32 53 80 79 54",
    "sg:postcode":"9420",
    "sg:province":"Oost-Vlaanderen",
    "sg:tags":[
        "de",
        "coiffure"
    ],
    "wof:name":"Nancy's Hair Fashion",
    "wof:placetype":"venue"
},
  "geometry": {"coordinates":[3.9807019234,50.9371299744],"type":"Point"}
}