{
  "type": "Feature",
  "properties": {
    "iso:country":"BE",
    "sg:address":"Mechelsesteenweg 92",
    "sg:city":"Lier",
    "sg:classifiers":[
        {
            "category":"Professional",
            "subcategory":"Lawyer & Legal Services",
            "type":"Services"
        }
    ],
    "sg:phone":"+32 3 480 00 46",
    "sg:postcode":"2500",
    "sg:province":"Antwerpen",
    "sg:tags":[
        "notary"
    ],
    "wof:name":"De Strycker J",
    "wof:placetype":"venue"
},
  "geometry": {"coordinates":[4.5571742058,51.1279296875],"type":"Point"}
}