{
  "type": "Feature",
  "properties": {
    "iso:country":"BE",
    "sg:address":"Rue Emile Tumelaire 23b8",
    "sg:city":"Charleroi",
    "sg:orig_category":"Deurwaarders",
    "sg:phone":"+32 71 58 75 20",
    "sg:postcode":"6000",
    "sg:province":"Hainaut",
    "wof:name":"Martine Heusschen",
    "wof:placetype":"venue"
},
  "geometry": {"coordinates":[4.447329998,50.4110603333],"type":"Point"}
}