{
  "type": "Feature",
  "properties": {
    "addr:full":"Roeselarestraat 340 Wevelgem West-Vlaanderen 8560",
    "addr:housenumber":"340",
    "addr:postcode":"8560",
    "addr:street":"Roeselarestraat",
    "iso:country":"BE",
    "sg:address":"Roeselarestraat 340",
    "sg:city":"Wevelgem",
    "sg:classifiers":[
        {
            "category":"Food & Beverages",
            "subcategory":"Groceries & Convenience Stores",
            "type":"Retail Goods"
        }
    ],
    "sg:phone":"+32 56 41 54 11",
    "sg:postcode":"8560",
    "sg:province":"West-Vlaanderen",
    "sg:tags":[
        "grocer"
    ],
    "wof:name":"Korf (de)",
    "wof:placetype":"venue"
},
  "geometry": {"coordinates":[3.1760010719,50.8219604492],"type":"Point"}
}