{
  "type": "Feature",
  "properties": {
    "addr:full":"Oudebaan 349 Box 2 Leuven Vlaams-Brabant 3000",
    "addr:housenumber":"349;2",
    "addr:postcode":"3000",
    "addr:street":"Oudebaan;Box",
    "iso:country":"BE",
    "sg:address":"Oudebaan 349 Box 2",
    "sg:city":"Leuven",
    "sg:classifiers":[
        {
            "category":"Education",
            "subcategory":"School",
            "type":"Public Place"
        }
    ],
    "sg:phone":"+32 16 35 05 85",
    "sg:postcode":"3000",
    "sg:province":"Vlaams-Brabant",
    "sg:tags":[
        "-",
        "private"
    ],
    "wof:name":"Verjans S",
    "wof:placetype":"venue"
},
  "geometry": {"coordinates":[4.7319631577,50.8670654297],"type":"Point"}
}