{
  "type": "Feature",
  "properties": {
    "addr:full":"Ter Goedingen 25 Aalter (bellem) Oost-Vlaanderen 9881",
    "addr:housenumber":"25",
    "addr:postcode":"9881",
    "addr:street":"Goedingen",
    "iso:country":"BE",
    "sg:address":"Ter Goedingen 25",
    "sg:city":"Aalter (bellem)",
    "sg:classifiers":[
        {
            "category":"Professional",
            "subcategory":"Management & Consulting",
            "type":"Services"
        }
    ],
    "sg:phone":"+32 9 374 66 02",
    "sg:postcode":"9881",
    "sg:province":"Oost-Vlaanderen",
    "sg:tags":[
        "tax-consultants"
    ],
    "wof:name":"Verstraete L",
    "wof:placetype":"venue"
},
  "geometry": {"coordinates":[3.4969370365,51.0925483704],"type":"Point"}
}