{
  "type": "Feature",
  "properties": {
    "addr:full":"Rue De La Vaulx 99 Fl\u00e9ron (retinne) Li\u00e8ge 4621",
    "addr:housenumber":"99",
    "addr:postcode":"4621",
    "addr:street":"Rue De La Vaulx",
    "iso:country":"BE",
    "sg:address":"Rue De La Vaulx 99",
    "sg:city":"Fl\u00e9ron (retinne)",
    "sg:classifiers":[
        {
            "category":"Autos & Motor Vehicles",
            "subcategory":"Automobile Sales",
            "type":"Retail Goods"
        }
    ],
    "sg:phone":"+32 4 355 09 01",
    "sg:postcode":"4621",
    "sg:province":"Li\u00e8ge",
    "sg:tags":[
        "car",
        "used",
        "-"
    ],
    "wof:name":"Stainier E",
    "wof:placetype":"venue"
},
  "geometry": {"coordinates":[5.7002191544,50.6293945312],"type":"Point"}
}