{
  "type": "Feature",
  "properties": {
    "addr:full":"Dorpsstraat 48 Ham Limburg 3945",
    "addr:housenumber":"48",
    "addr:postcode":"3945",
    "addr:street":"Dorpsstraat",
    "iso:country":"BE",
    "sg:address":"Dorpsstraat 48",
    "sg:city":"Ham",
    "sg:orig_category":"Banken and kredietinstellingen",
    "sg:phone":"+32 13 66 47 63",
    "sg:postcode":"3945",
    "sg:province":"Limburg",
    "wof:name":"Fortis",
    "wof:placetype":"venue"
},
  "geometry": {"coordinates":[5.1776199341,51.1046104431],"type":"Point"}
}