{
  "type": "Feature",
  "properties": {
    "iso:country":"BE",
    "sg:address":"Zwaaidok 2a",
    "sg:city":"Oostende",
    "sg:classifiers":[
        {
            "category":"Home & Garden",
            "subcategory":"Building Materials",
            "type":"Retail Goods"
        }
    ],
    "sg:phone":"+32 59 70 74 32",
    "sg:postcode":"8400",
    "sg:province":"West-Vlaanderen",
    "sg:tags":[
        "ready-mixed",
        "fresh",
        "concrete"
    ],
    "wof:name":"Inter-beton Nv",
    "wof:placetype":"venue"
},
  "geometry": {"coordinates":[2.9406650066,51.2183609009],"type":"Point"}
}