{
  "type": "Feature",
  "properties": {
    "iso:country":"BE",
    "sg:address":"Snellegemsestraat 41",
    "sg:city":"Zedelgem",
    "sg:classifiers":[
        {
            "category":"Professional",
            "subcategory":"Art Services",
            "type":"Services"
        }
    ],
    "sg:phone":"+32 50 82 02 28",
    "sg:postcode":"8210",
    "sg:province":"West-Vlaanderen",
    "sg:tags":[
        "-",
        "painter",
        "artist"
    ],
    "wof:name":"Verplanke J",
    "wof:placetype":"venue"
},
  "geometry": {"coordinates":[3.1340830326,51.1470069885],"type":"Point"}
}