{
  "type": "Feature",
  "properties": {
    "addr:full":"Rue Louis Pasteur 58 Soumagne Li\u00e8ge 4630",
    "addr:housenumber":"58",
    "addr:postcode":"4630",
    "addr:street":"Rue Louis Pasteur",
    "iso:country":"BE",
    "sg:address":"Rue Louis Pasteur 58",
    "sg:city":"Soumagne",
    "sg:orig_category":"Services pour animaux domestiques",
    "sg:phone":"+32 4 377 59 03",
    "sg:postcode":"4630",
    "sg:province":"Li\u00e8ge",
    "wof:name":"Au Cabot Chic",
    "wof:placetype":"venue"
},
  "geometry": {"coordinates":[5.7339959145,50.6333351135],"type":"Point"}
}