{
  "type": "Feature",
  "properties": {
    "addr:full":"Nieuwstraat 20 Galmaarden Vlaams-Brabant 1570",
    "addr:housenumber":"20",
    "addr:postcode":"1570",
    "addr:street":"Nieuwstraat",
    "iso:country":"BE",
    "sg:address":"Nieuwstraat 20",
    "sg:city":"Galmaarden",
    "sg:orig_category":"Houtbewerking and -behandeling",
    "sg:phone":"+32 54 58 88 82",
    "sg:postcode":"1570",
    "sg:province":"Vlaams-Brabant",
    "wof:name":"Joel Doraene",
    "wof:placetype":"venue"
},
  "geometry": {"coordinates":[3.9714028835,50.7505874634],"type":"Point"}
}