{
  "type": "Feature",
  "properties": {
    "iso:country":"BE",
    "sg:address":"Avenue Eug\u00c8ne Mascaux 117",
    "sg:city":"Charleroi",
    "sg:orig_category":"M\u00e9decins and sp\u00e9cialistes",
    "sg:phone":"+32 71 47 99 48",
    "sg:postcode":"6001",
    "sg:province":"Hainaut",
    "wof:name":"R\u00c9my Ndigeba Bamaraki",
    "wof:placetype":"venue"
},
  "geometry": {"coordinates":[4.4447088242,50.3971176147],"type":"Point"}
}