{
  "type": "Feature",
  "properties": {
    "iso:country":"BE",
    "sg:address":"Hoogleedsesteenweg 128",
    "sg:city":"Roeselare",
    "sg:orig_category":"Biens d'occasion",
    "sg:phone":"+32 51 69 03 06",
    "sg:postcode":"8800",
    "sg:province":"West-Vlaanderen",
    "wof:name":"The Popcorn",
    "wof:placetype":"venue"
},
  "geometry": {"coordinates":[3.1160430908,50.9537315369],"type":"Point"}
}