{
  "type": "Feature",
  "properties": {
    "iso:country":"BE",
    "sg:address":"Rue Du Pont 10",
    "sg:city":"Hamoir",
    "sg:classifiers":[
        {
            "category":"Professional",
            "subcategory":"Testing Lab",
            "type":"Services"
        }
    ],
    "sg:phone":"+32 86 38 82 61",
    "sg:postcode":"4180",
    "sg:province":"Li\u00e8ge",
    "sg:tags":[
        "chemist"
    ],
    "wof:name":"Chaspierre A",
    "wof:placetype":"venue"
},
  "geometry": {"coordinates":[5.5353331566,50.4260063171],"type":"Point"}
}