{
  "type": "Feature",
  "properties": {
    "iso:country":"BE",
    "sg:address":"Helshovenstraat 18",
    "sg:city":"Borgloon",
    "sg:orig_category":"Fruitteelt",
    "sg:phone":"+32 11 48 69 74",
    "sg:postcode":"3840",
    "sg:province":"Limburg",
    "wof:name":"Ghislain Ghijsens",
    "wof:placetype":"venue"
},
  "geometry": {"coordinates":[5.3441700935,50.8012466431],"type":"Point"}
}