{
  "type": "Feature",
  "properties": {
    "iso:country":"BE",
    "sg:address":"Zapstraat 37",
    "sg:city":"Hoeselt",
    "sg:orig_category":"R\u00e9parations de chaussures and articles en cuir",
    "sg:phone":"+32 89 41 17 50",
    "sg:postcode":"3730",
    "sg:province":"Limburg",
    "wof:name":"Joseph Partoens",
    "wof:placetype":"venue"
},
  "geometry": {"coordinates":[5.4924201965,50.847278595],"type":"Point"}
}