{
  "type": "Feature",
  "properties": {
    "iso:country":"BE",
    "sg:address":"Rue Kamme 27",
    "sg:city":"Bi\u00e9v\u00e8ne",
    "sg:classifiers":[
        {
            "category":"Retail",
            "subcategory":"Event Space",
            "type":"Services"
        }
    ],
    "sg:phone":"+32 54 58 98 41",
    "sg:postcode":"1547",
    "sg:province":"Vlaams-Brabant",
    "sg:tags":[
        "rental",
        "-",
        "hall"
    ],
    "wof:name":"Ferme D'haumautveld",
    "wof:placetype":"venue"
},
  "geometry": {"coordinates":[3.9486598969,50.7170295715],"type":"Point"}
}