{
  "type": "Feature",
  "properties": {
    "addr:full":"Chauss\u00c9e De Louvain 417 Schaarbeek/schaerbeek Bruxelles-Capitale 1030",
    "addr:housenumber":"417",
    "addr:postcode":"1030",
    "addr:street":"Chausse\u0301E De Louvain",
    "iso:country":"BE",
    "sg:address":"Chauss\u00c9e De Louvain 417",
    "sg:city":"Schaarbeek/schaerbeek",
    "sg:orig_category":"M\u00e9decins and sp\u00e9cialistes",
    "sg:phone":"+32 2 735 31 36",
    "sg:postcode":"1030",
    "sg:province":"Bruxelles-Capitale",
    "wof:name":"Abraham Ickowicz",
    "wof:placetype":"venue"
},
  "geometry": {"coordinates":[4.3928289413,50.8538093567],"type":"Point"}
}