{
  "type": "Feature",
  "properties": {
    "iso:country":"BE",
    "sg:address":"Vieille Eglise 3",
    "sg:city":"Pepinster",
    "sg:orig_category":"Artsen and specialisten",
    "sg:phone":"+32 87 46 13 06",
    "sg:postcode":"4860",
    "sg:province":"Li\u00e8ge",
    "wof:name":"Brigitte Hereng",
    "wof:placetype":"venue"
},
  "geometry": {"coordinates":[5.7853918076,50.5754165649],"type":"Point"}
}