{
  "type": "Feature",
  "properties": {
    "iso:country":"BE",
    "sg:address":"Pycke De Ten Aerdeln 40",
    "sg:city":"Oostende",
    "sg:orig_category":"Aardappelproducten Gh Groenten and fruit Gh",
    "sg:phone":"+32 59 80 99 66",
    "sg:postcode":"8400",
    "sg:province":"West-Vlaanderen",
    "wof:name":"R. Verbiest",
    "wof:placetype":"venue"
},
  "geometry": {"coordinates":[2.9126999378,51.2312583923],"type":"Point"}
}