{
  "type": "Feature",
  "properties": {
    "iso:country":"BE",
    "sg:address":"Markt 1",
    "sg:city":"Beringen",
    "sg:orig_category":"Supermarch\u00e9s",
    "sg:phone":"+32 11 42 29 04",
    "sg:postcode":"3580",
    "sg:province":"Limburg",
    "wof:name":"Ad Delhaize",
    "wof:placetype":"venue"
},
  "geometry": {"coordinates":[5.2238988876,51.0479545593],"type":"Point"}
}