{
  "type": "Feature",
  "properties": {
    "iso:country":"BE",
    "sg:address":"Tenbosstraat 94",
    "sg:city":"Elsene/ixelles",
    "sg:orig_category":"Drukkerijen and copyshops Fotogravure and zetwerk Secretariaatsdiensten",
    "sg:phone":"+32 2 340 72 72",
    "sg:postcode":"1050",
    "sg:province":"Bruxelles-Capitale",
    "wof:name":"Microscript",
    "wof:placetype":"venue"
},
  "geometry": {"coordinates":[4.3618831635,50.8212013245],"type":"Point"}
}