{
  "type": "Feature",
  "properties": {
    "addr:full":"Bergstraat 17 Sint-niklaas (belsele) Oost-Vlaanderen 9111",
    "addr:housenumber":"17",
    "addr:postcode":"9111",
    "addr:street":"Bergstraat",
    "iso:country":"BE",
    "sg:address":"Bergstraat 17",
    "sg:city":"Sint-niklaas (belsele)",
    "sg:classifiers":[
        {
            "category":"Health Services",
            "subcategory":"Dentist",
            "type":"Services"
        }
    ],
    "sg:phone":"+32 3 772 49 25",
    "sg:postcode":"9111",
    "sg:province":"Oost-Vlaanderen",
    "wof:name":"Uvin Paul",
    "wof:placetype":"venue"
},
  "geometry": {"coordinates":[4.0875859261,51.1402549744],"type":"Point"}
}