{
  "type": "Feature",
  "properties": {
    "addr:full":"Spinstersstr 2 Ronse Oost-Vlaanderen 9600",
    "addr:housenumber":"2",
    "addr:postcode":"9600",
    "addr:street":"Spinstersstr",
    "iso:country":"BE",
    "sg:address":"Spinstersstr 2",
    "sg:city":"Ronse",
    "sg:classifiers":[
        {
            "category":"Banks & Credit Unions",
            "subcategory":"Bank",
            "type":"Services"
        }
    ],
    "sg:phone":"+32 55 21 43 24",
    "sg:postcode":"9600",
    "sg:province":"Oost-Vlaanderen",
    "wof:name":"Indosuez Bank",
    "wof:placetype":"venue"
},
  "geometry": {"coordinates":[3.5924499035,50.7506904602],"type":"Point"}
}