{
  "type": "Feature",
  "properties": {
    "iso:country":"BE",
    "sg:address":"Gospertstrasse 54",
    "sg:city":"Eupen",
    "sg:classifiers":[
        {
            "category":"Banks & Credit Unions",
            "subcategory":"Bureau De Change",
            "type":"Services"
        }
    ],
    "sg:phone":"+32 87 55 38 42",
    "sg:postcode":"4700",
    "sg:province":"Li\u00e8ge",
    "sg:tags":[
        "-",
        "household",
        "gas"
    ],
    "wof:name":"Zimmermann J",
    "wof:placetype":"venue"
},
  "geometry": {"coordinates":[6.0346541405,50.6319389343],"type":"Point"}
}