{
  "type": "Feature",
  "properties": {
    "iso:country":"BE",
    "sg:address":"Rue Elisabeth 4",
    "sg:city":"Gembloux",
    "sg:classifiers":[
        {
            "category":"Arena",
            "subcategory":"Sports Club",
            "type":"Entertainment"
        }
    ],
    "sg:phone":"+32 81 61 50 62",
    "sg:postcode":"5030",
    "sg:province":"Namur",
    "sg:tags":[
        "de"
    ],
    "wof:name":"Les Canetons Gembloux",
    "wof:placetype":"venue"
},
  "geometry": {"coordinates":[4.6981248856,50.5586395264],"type":"Point"}
}