{
  "type": "Feature",
  "properties": {
    "addr:full":"Gorsemweg 120 Sint-truiden Limburg 3800",
    "addr:housenumber":"120",
    "addr:postcode":"sint-truiden;3800",
    "addr:street":"Gorsemweg",
    "iso:country":"BE",
    "sg:address":"Gorsemweg 120",
    "sg:city":"Sint-truiden",
    "sg:orig_category":"Fietsen",
    "sg:phone":"+32 11 68 00 75",
    "sg:postcode":"3800",
    "sg:province":"Limburg",
    "wof:name":"Motmans",
    "wof:placetype":"venue"
},
  "geometry": {"coordinates":[5.1776380539,50.8220062256],"type":"Point"}
}