{
  "type": "Feature",
  "properties": {
    "addr:full":"Stalingradlaan 2 Brussel/bruxelles Bruxelles-Capitale 1000",
    "addr:housenumber":"2",
    "addr:postcode":"1000",
    "addr:street":"Stalingradlaan;/",
    "iso:country":"BE",
    "sg:address":"Stalingradlaan 2",
    "sg:city":"Brussel/bruxelles",
    "sg:classifiers":[
        {
            "category":"Cafe",
            "type":"Food & Drink"
        }
    ],
    "sg:phone":"+32 2 513 34 74",
    "sg:postcode":"1000",
    "sg:province":"Bruxelles-Capitale",
    "sg:tags":[
        "caf\u00e9s"
    ],
    "wof:name":"Caf\u00c9 La Fourmilli\u00c8re",
    "wof:placetype":"venue"
},
  "geometry": {"coordinates":[4.3456830978,50.8424873352],"type":"Point"}
}