{
  "type": "Feature",
  "properties": {
    "addr:full":"Rue Du Bailly 13 Frasnes-lez-anvaing Hainaut 7912",
    "addr:housenumber":"13",
    "addr:postcode":"7912",
    "addr:street":"Rue Du Bailly",
    "iso:country":"BE",
    "sg:address":"Rue Du Bailly 13",
    "sg:city":"Frasnes-lez-anvaing",
    "sg:orig_category":"Rundveehouders Varkenskwekers",
    "sg:phone":"+32 69 76 83 40",
    "sg:postcode":"7912",
    "sg:province":"Hainaut",
    "wof:name":"Lucien Delaunoit",
    "wof:placetype":"venue"
},
  "geometry": {"coordinates":[3.5986890793,50.7155075073],"type":"Point"}
}