{
  "type": "Feature",
  "properties": {
    "iso:country":"BE",
    "sg:address":"Renkinstraat 27",
    "sg:city":"Schaarbeek/schaerbeek",
    "sg:orig_category":"Brood, gebak and snoepgoed",
    "sg:phone":"+32 2 242 08 10",
    "sg:postcode":"1030",
    "sg:province":"Bruxelles-Capitale",
    "wof:name":"Zohra Fadil",
    "wof:placetype":"venue"
},
  "geometry": {"coordinates":[4.3711400032,50.8656692505],"type":"Point"}
}