{
  "type": "Feature",
  "properties": {
    "addr:full":"Stationsstraat 6b Aalter Oost-Vlaanderen 9880",
    "addr:housenumber":"6b",
    "addr:postcode":"9880",
    "addr:street":"Stationsstraat",
    "iso:country":"BE",
    "sg:address":"Stationsstraat 6b",
    "sg:city":"Aalter",
    "sg:classifiers":[
        {
            "category":"Shopping",
            "subcategory":"Clothing, Apparel, & Fashions",
            "type":"Retail Goods"
        }
    ],
    "sg:phone":"+32 9 325 07 05",
    "sg:postcode":"9880",
    "sg:province":"Oost-Vlaanderen",
    "sg:tags":[
        "-",
        "clothing",
        "child"
    ],
    "wof:name":"De Verborgen Schat",
    "wof:placetype":"venue"
},
  "geometry": {"coordinates":[3.4487071037,51.0844650269],"type":"Point"}
}