{
  "type": "Feature",
  "properties": {
    "iso:country":"BE",
    "sg:address":"Route De Lessines 1",
    "sg:city":"Frasnes-lez-anvaing",
    "sg:classifiers":[
        {
            "category":"Communications",
            "subcategory":"Radio Station",
            "type":"Services"
        }
    ],
    "sg:phone":"+32 69 86 74 45",
    "sg:postcode":"7911",
    "sg:province":"Hainaut",
    "sg:tags":[
        "diffusion",
        "production",
        "de",
        "programme"
    ],
    "wof:name":"Radio Tcheuw Beuzie",
    "wof:placetype":"venue"
},
  "geometry": {"coordinates":[3.6415519714,50.6778526306],"type":"Point"}
}