{
  "type": "Feature",
  "properties": {
    "iso:country":"BE",
    "sg:address":"Rue Saint-remy 11",
    "sg:city":"Li\u00e8ge 1",
    "sg:classifiers":[
        {
            "category":"Shopping",
            "subcategory":"Stationery & Office Supplies",
            "type":"Retail Goods"
        }
    ],
    "sg:phone":"+32 4 223 18 24",
    "sg:postcode":"4000",
    "sg:province":"Li\u00e8ge",
    "wof:name":"I.p.l. Sa",
    "wof:placetype":"venue"
},
  "geometry": {"coordinates":[5.5702757835,50.6387481689],"type":"Point"}
}