{
  "type": "Feature",
  "properties": {
    "iso:country":"BE",
    "sg:address":"Luithagenhaven Hal F 2",
    "sg:city":"Antwerpen",
    "sg:orig_category":"Serres and speciale beglazing",
    "sg:phone":"+32 3 542 48 05",
    "sg:postcode":"2030",
    "sg:province":"Antwerpen",
    "wof:name":"Baeyens Glass",
    "wof:placetype":"venue"
},
  "geometry": {"coordinates":[4.3637099266,51.2742385864],"type":"Point"}
}