{
  "type": "Feature",
  "properties": {
    "addr:full":"Rue De Wavre 3 Chaumont-gistoux (grand) Brabant Wallon 1325",
    "addr:housenumber":"3;1325",
    "addr:street":"Rue De Wavre;Wallon",
    "iso:country":"BE",
    "sg:address":"Rue De Wavre 3",
    "sg:city":"Chaumont-gistoux (grand)",
    "sg:orig_category":"Kapsalons",
    "sg:phone":"+32 10 68 92 32",
    "sg:postcode":"1325",
    "sg:province":"Brabant Wallon",
    "wof:name":"Momotif",
    "wof:placetype":"venue"
},
  "geometry": {"coordinates":[4.6967959404,50.6839294434],"type":"Point"}
}