{
  "type": "Feature",
  "properties": {
    "iso:country":"BE",
    "sg:address":"Tieltstraat 16",
    "sg:city":"Wingene",
    "sg:orig_category":"Banken and kredietinstellingen",
    "sg:phone":"+32 51 65 74 75",
    "sg:postcode":"8750",
    "sg:province":"West-Vlaanderen",
    "wof:name":"Centea",
    "wof:placetype":"venue"
},
  "geometry": {"coordinates":[3.2796740532,51.0571022034],"type":"Point"}
}