{
  "type": "Feature",
  "properties": {
    "iso:country":"BE",
    "sg:address":"Rue Du Dowaire 1",
    "sg:city":"Couvin",
    "sg:orig_category":"Rundveehouders",
    "sg:phone":"+32 60 34 43 56",
    "sg:postcode":"5660",
    "sg:province":"Namur",
    "wof:name":"Jean-claude Beroudiaux",
    "wof:placetype":"venue"
},
  "geometry": {"coordinates":[4.4966731071,50.0532150269],"type":"Point"}
}