{
  "type": "Feature",
  "properties": {
    "iso:country":"BE",
    "sg:address":"St Baafspln 12",
    "sg:city":"Gent",
    "sg:classifiers":[
        {
            "category":"Banks & Credit Unions",
            "subcategory":"Bank",
            "type":"Services"
        }
    ],
    "sg:phone":"+32 53 25 66 37",
    "sg:postcode":"9000",
    "sg:province":"Oost-Vlaanderen",
    "wof:name":"Krediet Nuverheid",
    "wof:placetype":"venue"
},
  "geometry": {"coordinates":[3.7250990868,51.0533256531],"type":"Point"}
}