{
  "type": "Feature",
  "properties": {
    "iso:country":"BE",
    "sg:address":"Snoekstraat 5",
    "sg:city":"Elsene/ixelles",
    "sg:orig_category":"Dansscholen",
    "sg:phone":"+32 2 647 68 78",
    "sg:postcode":"1050",
    "sg:province":"Bruxelles-Capitale",
    "wof:name":"Un Oeuf Is In Oeuf",
    "wof:placetype":"venue"
},
  "geometry": {"coordinates":[4.3789110184,50.8333778381],"type":"Point"}
}