{
  "type": "Feature",
  "properties": {
    "addr:full":"Place Saint-roch 4 Wemmel/wemmel Vlaams-Brabant 1780",
    "addr:housenumber":"4",
    "addr:postcode":"1780",
    "addr:street":"Place Saint-Roch",
    "iso:country":"BE",
    "sg:address":"Place Saint-roch 4",
    "sg:city":"Wemmel/wemmel",
    "sg:orig_category":"M\u00e9decins and sp\u00e9cialistes",
    "sg:phone":"+32 2 460 48 48",
    "sg:postcode":"1780",
    "sg:province":"Vlaams-Brabant",
    "wof:name":"Thierry Van Hedent",
    "wof:placetype":"venue"
},
  "geometry": {"coordinates":[4.3070898056,50.9067382812],"type":"Point"}
}