{
  "type": "Feature",
  "properties": {
    "iso:country":"BE",
    "sg:address":"Charlottalei 37",
    "sg:city":"Antwerpen",
    "sg:orig_category":"Non-Classified Establishments",
    "sg:phone":"+32 3 230 42 01",
    "sg:postcode":"2018",
    "sg:province":"Antwerpen",
    "wof:name":"Bulwick M Bvba",
    "wof:placetype":"venue"
},
  "geometry": {"coordinates":[4.4194049835,51.2081260681],"type":"Point"}
}