{
  "type": "Feature",
  "properties": {
    "iso:country":"BE",
    "sg:address":"Eug\u00c8ne Keymplein 71",
    "sg:city":"Watermaal-bosvoorde/watermael-boitsfort",
    "sg:orig_category":"Kapsalons Mobiele kappers",
    "sg:phone":"+32 2 660 90 29",
    "sg:postcode":"1170",
    "sg:province":"Bruxelles-Capitale",
    "wof:name":"Coiff. Fabrice Francklin",
    "wof:placetype":"venue"
},
  "geometry": {"coordinates":[4.4031639099,50.8092842102],"type":"Point"}
}