{
  "type": "Feature",
  "properties": {
    "iso:country":"BE",
    "sg:address":"Zone Industrielle",
    "sg:city":"Arlon",
    "sg:classifiers":[
        {
            "category":"Manufacturing",
            "subcategory":"Soap",
            "type":"Manufacturing & Wholesale Goods"
        }
    ],
    "sg:phone":"+32 63 22 45 36",
    "sg:postcode":"6700",
    "sg:province":"Luxembourg",
    "sg:tags":[
        "dispenser",
        "automatic",
        "towel"
    ],
    "wof:name":"Tounet Sa",
    "wof:placetype":"venue"
},
  "geometry": {"coordinates":[5.8126749992,49.6823234558],"type":"Point"}
}