{
  "type": "Feature",
  "properties": {
    "iso:country":"BE",
    "sg:address":"Rapaertstraat 18",
    "sg:city":"Brugge (assebroek)",
    "sg:classifiers":[
        {
            "category":"Manufacturing",
            "subcategory":"Electronics",
            "type":"Manufacturing & Wholesale Goods"
        }
    ],
    "sg:phone":"+32 50 67 01 48",
    "sg:postcode":"8310",
    "sg:province":"West-Vlaanderen",
    "sg:tags":[
        "component",
        "-"
    ],
    "wof:name":"Trans Electronic Railways",
    "wof:placetype":"venue"
},
  "geometry": {"coordinates":[3.2367351055,51.1855888367],"type":"Point"}
}