{
  "type": "Feature",
  "properties": {
    "addr:full":"Route De Hombourg 5 Welkenraedt Li\u00e8ge 4841",
    "addr:housenumber":"5",
    "addr:postcode":"4841",
    "addr:street":"Route De Hombourg",
    "iso:country":"BE",
    "sg:address":"Route De Hombourg 5",
    "sg:city":"Welkenraedt",
    "sg:orig_category":"Installation \u00e9lectrique r\u00e9sidentielle",
    "sg:phone":"+32 87 89 07 35",
    "sg:postcode":"4841",
    "sg:province":"Li\u00e8ge",
    "wof:name":"Luc Pirenne",
    "wof:placetype":"venue"
},
  "geometry": {"coordinates":[5.9262828827,50.6782188416],"type":"Point"}
}