{
  "type": "Feature",
  "properties": {
    "addr:full":"Avenue G\u00c9n\u00c9ral Michel 1be Charleroi Hainaut 6000",
    "addr:postcode":"6000",
    "addr:street":"Avenue Ge\u0301Ne\u0301Ral Michel 1Be;Hainaut",
    "iso:country":"BE",
    "sg:address":"Avenue G\u00c9n\u00c9ral Michel 1be",
    "sg:city":"Charleroi",
    "sg:classifiers":[
        {
            "category":"Shopping Center",
            "type":"Public Place"
        }
    ],
    "sg:phone":"+32 71 30 91 33",
    "sg:postcode":"6000",
    "sg:province":"Hainaut",
    "sg:tags":[
        "enseignement",
        "formation"
    ],
    "wof:name":"Strat\u00c9gies Et Succ\u00c8s",
    "wof:placetype":"venue"
},
  "geometry": {"coordinates":[4.4504227638,50.4104766846],"type":"Point"}
}