{
  "type": "Feature",
  "properties": {
    "iso:country":"BE",
    "sg:address":"Steyvenstraat 18",
    "sg:city":"Bree",
    "sg:classifiers":[
        {
            "category":"Arena",
            "subcategory":"Sports Club",
            "type":"Entertainment"
        }
    ],
    "sg:phone":"+32 89 46 68 83",
    "sg:postcode":"3960",
    "sg:province":"Limburg",
    "sg:tags":[
        "de"
    ],
    "wof:name":"Molenkracht Bree",
    "wof:placetype":"venue"
},
  "geometry": {"coordinates":[5.60810709,51.1457061768],"type":"Point"}
}