{
  "type": "Feature",
  "properties": {
    "iso:country":"BE",
    "sg:address":"Itterbeekselaan 263",
    "sg:city":"Anderlecht",
    "sg:orig_category":"Papierwaren and schoolbenodigdheden Gh",
    "sg:phone":"+32 2 523 16 19",
    "sg:postcode":"1070",
    "sg:province":"Bruxelles-Capitale",
    "wof:name":"Scas",
    "wof:placetype":"venue"
},
  "geometry": {"coordinates":[4.2850928307,50.8349227905],"type":"Point"}
}