{
  "type": "Feature",
  "properties": {
    "addr:full":"Platanenstraat 5 Houthalen-helchteren (houthalen) Limburg 3530",
    "addr:housenumber":"5",
    "addr:postcode":"3530",
    "addr:street":"Platanenstraat",
    "iso:country":"BE",
    "sg:address":"Platanenstraat 5",
    "sg:city":"Houthalen-helchteren (houthalen)",
    "sg:classifiers":[
        {
            "category":"Health Services",
            "subcategory":"Doctor",
            "type":"Services"
        }
    ],
    "sg:phone":"+32 11 52 28 76",
    "sg:postcode":"3530",
    "sg:province":"Limburg",
    "sg:tags":[
        "medicinephysicians",
        "surgeon"
    ],
    "wof:name":"Huisartsen Groepspraktijk",
    "wof:placetype":"venue"
},
  "geometry": {"coordinates":[5.396282196,51.0226364136],"type":"Point"}
}