{
  "type": "Feature",
  "properties": {
    "addr:full":"Rue Mont Leva 15 Amay (ampsin) Li\u00e8ge 4540",
    "addr:housenumber":"15",
    "addr:postcode":"4540",
    "addr:street":"Rue Mont Leva;Ampsin",
    "iso:country":"BE",
    "sg:address":"Rue Mont Leva 15",
    "sg:city":"Amay (ampsin)",
    "sg:classifiers":[
        {
            "category":"Health Services",
            "subcategory":"Nursing And Care Facility",
            "type":"Services"
        }
    ],
    "sg:phone":"+32 479 35 13 91",
    "sg:postcode":"4540",
    "sg:province":"Li\u00e8ge",
    "sg:tags":[
        "home"
    ],
    "wof:name":"Resimont M-r",
    "wof:placetype":"venue"
},
  "geometry": {"coordinates":[5.3180990219,50.5478668213],"type":"Point"}
}