{
  "type": "Feature",
  "properties": {
    "iso:country":"BE",
    "sg:address":"Rue Gr\u00c9try 249",
    "sg:city":"Li\u00c8ge",
    "sg:orig_category":"Installatie van houten of kunststof schrijnwerk",
    "sg:phone":"+32 4 343 33 50",
    "sg:postcode":"4020",
    "sg:province":"Li\u00e8ge",
    "wof:name":"Guiseppe Sollami",
    "wof:placetype":"venue"
},
  "geometry": {"coordinates":[5.5866332054,50.6300468445],"type":"Point"}
}