{
  "type": "Feature",
  "properties": {
    "addr:full":"Pastoor De Katerstraat 23 Baarle-hertog Antwerpen 2387",
    "addr:housenumber":"23",
    "addr:postcode":"2387",
    "addr:street":"Pastoor De Katerstraat",
    "iso:country":"BE",
    "sg:address":"Pastoor De Katerstraat 23",
    "sg:city":"Baarle-hertog",
    "sg:classifiers":[
        {
            "category":"Travel",
            "subcategory":"Hotels & Motels",
            "type":"Entertainment"
        }
    ],
    "sg:phone":"+32 14 69 90 16",
    "sg:postcode":"2387",
    "sg:province":"Antwerpen",
    "wof:name":"Den Bonten Os",
    "wof:placetype":"venue"
},
  "geometry": {"coordinates":[4.9236111641,51.4418525696],"type":"Point"}
}