{
  "type": "Feature",
  "properties": {
    "addr:full":"Markt 12 Tervuren Vlaams-Brabant 3080",
    "addr:housenumber":"12",
    "addr:postcode":"3080",
    "addr:street":"Markt",
    "iso:country":"BE",
    "sg:address":"Markt 12",
    "sg:city":"Tervuren",
    "sg:classifiers":[
        {
            "category":"Restaurant",
            "type":"Food & Drink"
        }
    ],
    "sg:phone":"+32 2 767 87 53",
    "sg:postcode":"3080",
    "sg:province":"Vlaams-Brabant",
    "sg:tags":[
        "caf\u00e9s"
    ],
    "wof:name":"Gambrinus",
    "wof:placetype":"venue"
},
  "geometry": {"coordinates":[4.5145378113,50.8242721558],"type":"Point"}
}