{
  "type": "Feature",
  "properties": {
    "addr:full":"Grote Markt 6 Blankenberge West-Vlaanderen 8370",
    "addr:housenumber":"6",
    "addr:postcode":"8370",
    "addr:street":"Grote Markt",
    "iso:country":"BE",
    "sg:address":"Grote Markt 6",
    "sg:city":"Blankenberge",
    "sg:classifiers":[
        {
            "category":"Travel",
            "subcategory":"Hotels & Motels",
            "type":"Entertainment"
        }
    ],
    "sg:phone":"+32 50 41 30 40",
    "sg:postcode":"8370",
    "sg:province":"West-Vlaanderen",
    "sg:tags":[
        "restaurant"
    ],
    "wof:name":"Olympia",
    "wof:placetype":"venue"
},
  "geometry": {"coordinates":[3.1245439053,51.3132781982],"type":"Point"}
}