{
  "type": "Feature",
  "properties": {
    "iso:country":"BE",
    "sg:address":"Lostraat 32",
    "sg:city":"Nevele",
    "sg:classifiers":[
        {
            "category":"Cafe",
            "type":"Food & Drink"
        }
    ],
    "sg:phone":"+32 9 371 90 39",
    "sg:postcode":"9850",
    "sg:province":"Oost-Vlaanderen",
    "sg:tags":[
        "caf\u00e9s"
    ],
    "wof:name":"L.s.merendree",
    "wof:placetype":"venue"
},
  "geometry": {"coordinates":[3.5869579315,51.0848770142],"type":"Point"}
}