{
  "type": "Feature",
  "properties": {
    "iso:country":"BE",
    "sg:address":"Gaversstraat 8",
    "sg:city":"Harelbeke",
    "sg:orig_category":"Zalen voor culturele evenementen",
    "sg:phone":"+32 56 70 26 26",
    "sg:postcode":"8530",
    "sg:province":"West-Vlaanderen",
    "wof:name":"Ontmoetingscentrum",
    "wof:placetype":"venue"
},
  "geometry": {"coordinates":[3.3140280247,50.8550491333],"type":"Point"}
}