{
  "type": "Feature",
  "properties": {
    "addr:full":"Chauss\u00c9e De Wavre 0 Perwez Brabant Wallon 1360",
    "addr:housenumber":"0",
    "addr:postcode":"1360",
    "addr:street":"Chausse\u0301E De Wavre",
    "iso:country":"BE",
    "sg:address":"Chauss\u00c9e De Wavre 0",
    "sg:city":"Perwez",
    "sg:orig_category":"V\u00e9hicules automobiles",
    "sg:phone":"+32 81 65 72 75",
    "sg:postcode":"1360",
    "sg:province":"Brabant Wallon",
    "wof:name":"Perwez Motors",
    "wof:placetype":"venue"
},
  "geometry": {"coordinates":[4.8045802116,50.6276512146],"type":"Point"}
}