{
  "type": "Feature",
  "properties": {
    "addr:full":"Pastoriestraat 33 Tremelo (baal) Vlaams-Brabant 3128",
    "addr:housenumber":"33",
    "addr:postcode":"3128",
    "addr:street":"Pastoriestraat",
    "iso:country":"BE",
    "sg:address":"Pastoriestraat 33",
    "sg:city":"Tremelo (baal)",
    "sg:classifiers":[
        {
            "category":"Wholesale",
            "subcategory":"Beer",
            "type":"Manufacturing & Wholesale Goods"
        }
    ],
    "sg:phone":"+32 16 53 23 17",
    "sg:postcode":"3128",
    "sg:province":"Vlaams-Brabant",
    "sg:tags":[
        "ale",
        "-"
    ],
    "wof:name":"Volckaerts A & Zn",
    "wof:placetype":"venue"
},
  "geometry": {"coordinates":[4.7517337799,50.9973907471],"type":"Point"}
}