{
  "type": "Feature",
  "properties": {
    "iso:country":"BE",
    "sg:address":"Zonnegemdorp 5",
    "sg:city":"Sint-lievens-houtem (zonnegem)",
    "sg:classifiers":[
        {
            "category":"Restaurant",
            "type":"Food & Drink"
        }
    ],
    "sg:phone":"+32 53 62 85 45",
    "sg:postcode":"9520",
    "sg:province":"Oost-Vlaanderen",
    "sg:tags":[
        "industrial",
        "kitchen",
        "catering"
    ],
    "wof:name":"Vermeulen C",
    "wof:placetype":"venue"
},
  "geometry": {"coordinates":[3.9095330238,50.9268493652],"type":"Point"}
}