{
  "type": "Feature",
  "properties": {
    "iso:country":"BE",
    "sg:address":"Kerkstraat 82",
    "sg:city":"Antwerpen",
    "sg:classifiers":[
        {
            "category":"Building & Trades",
            "subcategory":"Construction",
            "type":"Services"
        }
    ],
    "sg:phone":"+32 3 236 26 79",
    "sg:postcode":"2060",
    "sg:province":"Antwerpen",
    "sg:tags":[
        "stucco",
        "contractor"
    ],
    "wof:name":"C.b.b. Art-lodge",
    "wof:placetype":"venue"
},
  "geometry": {"coordinates":[4.4316449165,51.21875],"type":"Point"}
}