{
  "type": "Feature",
  "properties": {
    "addr:full":"Berkenlaan 9 Bree Limburg 3960",
    "addr:housenumber":"9",
    "addr:postcode":"3960",
    "addr:street":"Berkenlaan",
    "iso:country":"BE",
    "sg:address":"Berkenlaan 9",
    "sg:city":"Bree",
    "sg:orig_category":"Quincailleries. Installations and terrains de sport hors centres sportifs. Clubs de sport",
    "sg:phone":"+32 89 46 51 64",
    "sg:postcode":"3960",
    "sg:province":"Limburg",
    "wof:name":"Blauw-wit Bree",
    "wof:placetype":"venue"
},
  "geometry": {"coordinates":[5.5868821144,51.1245765686],"type":"Point"}
}