{
  "type": "Feature",
  "properties": {
    "iso:country":"BE",
    "sg:address":"Truweelweg 7",
    "sg:city":"Kruishoutem",
    "sg:classifiers":[
        {
            "category":"Personal",
            "subcategory":"Beauty Salon",
            "type":"Services"
        }
    ],
    "sg:phone":"+32 9 380 14 85",
    "sg:postcode":"9770",
    "sg:province":"Oost-Vlaanderen",
    "sg:tags":[
        "de",
        "coiffure"
    ],
    "wof:name":"Coiffure Marleen",
    "wof:placetype":"venue"
},
  "geometry": {"coordinates":[3.5373599529,50.9455909729],"type":"Point"}
}