{
  "type": "Feature",
  "properties": {
    "addr:full":"Rue D'arquet 53 Namur Namur 5000",
    "addr:housenumber":"53",
    "addr:postcode":"5000",
    "addr:street":"Rue D'Arquet",
    "iso:country":"BE",
    "sg:address":"Rue D'arquet 53",
    "sg:city":"Namur",
    "sg:orig_category":"Beschutte werkplaatsen Drukkerijen and copyshops",
    "sg:phone":"+32 81 71 92 00",
    "sg:postcode":"5000",
    "sg:province":"Namur",
    "wof:name":"Entraide Par Le Travail",
    "wof:placetype":"venue"
},
  "geometry": {"coordinates":[4.8666191101,50.4727020264],"type":"Point"}
}