{
  "type": "Feature",
  "properties": {
    "addr:full":"Grand Route 48 Antoing Hainaut 7640",
    "addr:postcode":"7640",
    "addr:street":"Grand Route 48;Hainaut",
    "iso:country":"BE",
    "sg:address":"Grand Route 48",
    "sg:city":"Antoing",
    "sg:orig_category":"Rundveehouders Zuivelproducten",
    "sg:phone":"+32 69 44 23 52",
    "sg:postcode":"7640",
    "sg:province":"Hainaut",
    "wof:name":"Feys Gery Et Feys Eric",
    "wof:placetype":"venue"
},
  "geometry": {"coordinates":[3.4929759502,50.5457305908],"type":"Point"}
}