{
  "type": "Feature",
  "properties": {
    "iso:country":"BE",
    "sg:address":"Rue Poteray 5",
    "sg:city":"Lens",
    "sg:orig_category":"Eleveurs de bovins",
    "sg:phone":"+32 68 45 42 14",
    "sg:postcode":"7870",
    "sg:province":"Hainaut",
    "wof:name":"Frantz Limbourg",
    "wof:placetype":"venue"
},
  "geometry": {"coordinates":[3.943253994,50.5870513916],"type":"Point"}
}