{
  "type": "Feature",
  "properties": {
    "iso:country":"BE",
    "sg:address":"Avenue Leray 1b",
    "sg:city":"Tournai",
    "sg:classifiers":[
        {
            "category":"Personal",
            "subcategory":"Beauty Salon",
            "type":"Services"
        }
    ],
    "sg:phone":"+32 69 22 79 99",
    "sg:postcode":"7500",
    "sg:province":"Hainaut",
    "sg:tags":[
        "de",
        "coiffure"
    ],
    "wof:name":"Coiffure G\u00c9raldine",
    "wof:placetype":"venue"
},
  "geometry": {"coordinates":[3.3950560093,50.6119346619],"type":"Point"}
}