{
  "type": "Feature",
  "properties": {
    "iso:country":"BE",
    "sg:address":"Abdijstraat 115",
    "sg:city":"Elsene/ixelles",
    "sg:orig_category":"Herstellingswinkels voor diverse persoonlijke and huishoudartikelen",
    "sg:phone":"+32 2 344 02 30",
    "sg:postcode":"1050",
    "sg:province":"Bruxelles-Capitale",
    "wof:name":"Fil D'or",
    "wof:placetype":"venue"
},
  "geometry": {"coordinates":[4.3633952141,50.8186645508],"type":"Point"}
}