{
  "type": "Feature",
  "properties": {
    "iso:country":"BE",
    "sg:address":"Fonteinstraat 25",
    "sg:city":"Haaltert",
    "sg:orig_category":"Schoonheidssalons",
    "sg:phone":"+32 53 83 50 11",
    "sg:postcode":"9450",
    "sg:province":"Oost-Vlaanderen",
    "wof:name":"Instituut Babor",
    "wof:placetype":"venue"
},
  "geometry": {"coordinates":[4.0094261169,50.8962287903],"type":"Point"}
}