{
  "type": "Feature",
  "properties": {
    "addr:full":"Chauss\u00c9e De Waterloo 433 Elsene/ixelles Bruxelles-Capitale 1050",
    "addr:housenumber":"433",
    "addr:postcode":"1050",
    "addr:street":"Chausse\u0301E De Waterloo",
    "iso:country":"BE",
    "sg:address":"Chauss\u00c9e De Waterloo 433",
    "sg:city":"Elsene/ixelles",
    "sg:orig_category":"Antiek",
    "sg:phone":"+32 475 74 27 45",
    "sg:postcode":"1050",
    "sg:province":"Bruxelles-Capitale",
    "wof:name":"Antiquit\u00c9s",
    "wof:placetype":"venue"
},
  "geometry": {"coordinates":[4.3563709259,50.8214225769],"type":"Point"}
}