{
  "type": "Feature",
  "properties": {
    "iso:country":"BE",
    "sg:address":"Kasteelstraat 2ba",
    "sg:city":"Borgloon",
    "sg:orig_category":"Kapsalons",
    "sg:phone":"+32 12 74 64 50",
    "sg:postcode":"3840",
    "sg:province":"Limburg",
    "wof:name":"Linda Neven",
    "wof:placetype":"venue"
},
  "geometry": {"coordinates":[5.3441700935,50.8012466431],"type":"Point"}
}