{
  "type": "Feature",
  "properties": {
    "addr:full":"Place De La Justice 19 Mouscron Hainaut 7700",
    "addr:housenumber":"19",
    "addr:postcode":"7700",
    "addr:street":"Place De La Justice",
    "iso:country":"BE",
    "sg:address":"Place De La Justice 19",
    "sg:city":"Mouscron",
    "sg:classifiers":[
        {
            "category":"Sports & Exercise",
            "subcategory":"Bowling",
            "type":"Entertainment"
        }
    ],
    "sg:phone":"+32 56 34 57 00",
    "sg:postcode":"7700",
    "sg:province":"Hainaut",
    "sg:tags":[
        "skittle",
        "alley"
    ],
    "wof:name":"Themis Bowling",
    "wof:placetype":"venue"
},
  "geometry": {"coordinates":[3.2198879719,50.7391166687],"type":"Point"}
}