{
  "type": "Feature",
  "properties": {
    "addr:full":"Rue Paul Janson 16 Charleroi (montignies-sur-sambre) Hainaut 6061",
    "addr:housenumber":"16",
    "addr:postcode":"6061",
    "addr:street":"Rue Paul Janson",
    "iso:country":"BE",
    "sg:address":"Rue Paul Janson 16",
    "sg:city":"Charleroi (montignies-sur-sambre)",
    "sg:classifiers":[
        {
            "category":"Health Services",
            "subcategory":"Doctor",
            "type":"Services"
        }
    ],
    "sg:phone":"+32 71 31 10 67",
    "sg:postcode":"6061",
    "sg:province":"Hainaut",
    "sg:tags":[
        "medicinephysicians",
        "surgeon"
    ],
    "wof:name":"Baivier F",
    "wof:placetype":"venue"
},
  "geometry": {"coordinates":[4.4583058357,50.4094963074],"type":"Point"}
}