{
  "type": "Feature",
  "properties": {
    "addr:full":"Rue W\u00c9ry 23 Elsene/ixelles Bruxelles-Capitale 1050",
    "addr:housenumber":"23",
    "addr:postcode":"1050",
    "addr:street":"Rue We\u0301Ry",
    "iso:country":"BE",
    "sg:address":"Rue W\u00c9ry 23",
    "sg:city":"Elsene/ixelles",
    "sg:orig_category":"Epiceries",
    "sg:phone":"+32 2 647 59 31",
    "sg:postcode":"1050",
    "sg:province":"Bruxelles-Capitale",
    "wof:name":"Ixel",
    "wof:placetype":"venue"
},
  "geometry": {"coordinates":[4.3754348755,50.831615448],"type":"Point"}
}