{
  "type": "Feature",
  "properties": {
    "addr:full":"Meeuwerbaan 8 Peer Limburg 3990",
    "addr:housenumber":"8",
    "addr:postcode":"3990",
    "addr:street":"Meeuwerbaan",
    "iso:country":"BE",
    "sg:address":"Meeuwerbaan 8",
    "sg:city":"Peer",
    "sg:orig_category":"Woningbouw",
    "sg:phone":"+32 11 79 40 80",
    "sg:postcode":"3990",
    "sg:province":"Limburg",
    "wof:name":"Projectontwikkeling Compass",
    "wof:placetype":"venue"
},
  "geometry": {"coordinates":[5.4535799026,51.0806617737],"type":"Point"}
}