{
  "type": "Feature",
  "properties": {
    "iso:country":"BE",
    "sg:address":"Stationsstraat 26",
    "sg:city":"Dilbeek (groot - Bijgaarden)",
    "sg:classifiers":[
        {
            "category":"Home & Garden",
            "subcategory":"Hardware",
            "type":"Retail Goods"
        }
    ],
    "sg:phone":"+32 2 481 11 70",
    "sg:postcode":"1702",
    "sg:province":"Vlaams-Brabant",
    "sg:tags":[
        "battery",
        "dry"
    ],
    "wof:name":"Panasonic Battery Sales Europe Nv",
    "wof:placetype":"venue"
},
  "geometry": {"coordinates":[4.2761878967,50.8697929382],"type":"Point"}
}