{
  "type": "Feature",
  "properties": {
    "iso:country":"BE",
    "sg:address":"Rue De La Bouxhe 3",
    "sg:city":"Trooz",
    "sg:orig_category":"Technische studies and ingenieursactiviteiten",
    "sg:phone":"+32 4 351 63 16",
    "sg:postcode":"4870",
    "sg:province":"Li\u00e8ge",
    "wof:name":"Bureau D'etude J Sougnez",
    "wof:placetype":"venue"
},
  "geometry": {"coordinates":[5.6696338654,50.5597267151],"type":"Point"}
}