{
  "type": "Feature",
  "properties": {
    "addr:full":"Rue Lens 26 Elsene/ixelles Bruxelles-Capitale 1050",
    "addr:housenumber":"26",
    "addr:postcode":"1050",
    "addr:street":"Rue Lens",
    "iso:country":"BE",
    "sg:address":"Rue Lens 26",
    "sg:city":"Elsene/ixelles",
    "sg:classifiers":[
        {
            "category":"Sports & Exercise",
            "subcategory":"Sports Center",
            "type":"Entertainment"
        }
    ],
    "sg:phone":"+32 2 647 99 36",
    "sg:postcode":"1050",
    "sg:province":"Bruxelles-Capitale",
    "sg:tags":[
        "de",
        "fitness"
    ],
    "wof:name":"Culture Club",
    "wof:placetype":"venue"
},
  "geometry": {"coordinates":[4.3659501076,50.8269615173],"type":"Point"}
}