{
  "type": "Feature",
  "properties": {
    "addr:full":"Antwerpse Steenweg 31 Lochristi Oost-Vlaanderen 9080",
    "addr:housenumber":"31",
    "addr:postcode":"9080",
    "addr:street":"Antwerpse Steenweg",
    "iso:country":"BE",
    "sg:address":"Antwerpse Steenweg 31",
    "sg:city":"Lochristi",
    "sg:classifiers":[
        {
            "category":"Home & Garden",
            "subcategory":"Building Materials",
            "type":"Retail Goods"
        }
    ],
    "sg:phone":"+32 9 355 82 87",
    "sg:postcode":"9080",
    "sg:province":"Oost-Vlaanderen",
    "sg:tags":[
        "bathroom",
        "installation",
        "accessory"
    ],
    "wof:name":"Decosan Bvba",
    "wof:placetype":"venue"
},
  "geometry": {"coordinates":[3.8170249462,51.0914115906],"type":"Point"}
}