{
  "type": "Feature",
  "properties": {
    "iso:country":"BE",
    "sg:address":"Bochtenstraat 16",
    "sg:city":"Destelbergen",
    "sg:classifiers":[
        {
            "category":"Health Services",
            "subcategory":"Doctor",
            "type":"Services"
        }
    ],
    "sg:phone":"+32 9 355 23 50",
    "sg:postcode":"9070",
    "sg:province":"Oost-Vlaanderen",
    "sg:tags":[
        "orthopedist"
    ],
    "wof:name":"Watson H",
    "wof:placetype":"venue"
},
  "geometry": {"coordinates":[3.831414938,51.0665779114],"type":"Point"}
}