{
  "type": "Feature",
  "properties": {
    "iso:country":"BE",
    "sg:address":"Rue De Merbes 355",
    "sg:city":"Binche",
    "sg:classifiers":[
        {
            "category":"Restaurant",
            "type":"Food & Drink"
        }
    ],
    "sg:phone":"+32 64 33 62 09",
    "sg:postcode":"7130",
    "sg:province":"Hainaut",
    "wof:name":"Restaurant La Cr\u00c9dence",
    "wof:placetype":"venue"
},
  "geometry": {"coordinates":[4.1727237701,50.3898544312],"type":"Point"}
}