{
  "type": "Feature",
  "properties": {
    "iso:country":"BE",
    "sg:address":"Lentelaan 1",
    "sg:city":"Waasmunster",
    "sg:classifiers":[
        {
            "category":"Travel",
            "subcategory":"Resort",
            "type":"Entertainment"
        }
    ],
    "sg:phone":"+32 52 55 50 01",
    "sg:postcode":"9250",
    "sg:province":"Oost-Vlaanderen",
    "sg:tags":[
        "health"
    ],
    "wof:name":"Stille Waters",
    "wof:placetype":"venue"
},
  "geometry": {"coordinates":[4.1011629105,51.1189346313],"type":"Point"}
}