{
  "type": "Feature",
  "properties": {
    "addr:full":"Pennemanstraat 68 Deinze (astene) Oost-Vlaanderen 9800",
    "addr:housenumber":"68",
    "addr:postcode":"9800",
    "addr:street":"Pennemanstraat",
    "iso:country":"BE",
    "sg:address":"Pennemanstraat 68",
    "sg:city":"Deinze (astene)",
    "sg:classifiers":[
        {
            "category":"Banks & Credit Unions",
            "subcategory":"Bureau De Change",
            "type":"Services"
        }
    ],
    "sg:phone":"+32 9 386 56 92",
    "sg:postcode":"9800",
    "sg:province":"Oost-Vlaanderen",
    "sg:tags":[
        "regulating",
        "system"
    ],
    "wof:name":"E.v.s.",
    "wof:placetype":"venue"
},
  "geometry": {"coordinates":[3.5734109879,50.9819564819],"type":"Point"}
}