{
  "type": "Feature",
  "properties": {
    "addr:full":"Kasteeldreef 37-39 Lede Oost-Vlaanderen 9340",
    "addr:housenumber":"37-39",
    "addr:postcode":"9340",
    "addr:street":"Kasteeldreef",
    "iso:country":"BE",
    "sg:address":"Kasteeldreef 37-39",
    "sg:city":"Lede",
    "sg:orig_category":"Dameskledingzaken",
    "sg:phone":"+32 53 80 59 02",
    "sg:postcode":"9340",
    "sg:province":"Oost-Vlaanderen",
    "wof:name":"Machteld",
    "wof:placetype":"venue"
},
  "geometry": {"coordinates":[3.9814929962,50.9662475586],"type":"Point"}
}