{
  "type": "Feature",
  "properties": {
    "addr:full":"Albrecht Rodenbachlaan 13 Grimbergen Vlaams-Brabant 1850",
    "addr:housenumber":"13",
    "addr:postcode":"1850",
    "addr:street":"Albrecht Rodenbachlaan",
    "iso:country":"BE",
    "sg:address":"Albrecht Rodenbachlaan 13",
    "sg:city":"Grimbergen",
    "sg:orig_category":"Reclamebureaus",
    "sg:phone":"+32 2 544 08 97",
    "sg:postcode":"1850",
    "sg:province":"Vlaams-Brabant",
    "wof:name":"Spot-on",
    "wof:placetype":"venue"
},
  "geometry": {"coordinates":[4.3676700592,50.9319877625],"type":"Point"}
}