{
  "type": "Feature",
  "properties": {
    "iso:country":"BE",
    "sg:address":"Brugstraat 1",
    "sg:city":"Lochristi",
    "sg:orig_category":"Eleveurs de bovins",
    "sg:phone":"+32 9 367 82 62",
    "sg:postcode":"9080",
    "sg:province":"Oost-Vlaanderen",
    "wof:name":"Aime De Jaeger",
    "wof:placetype":"venue"
},
  "geometry": {"coordinates":[3.8969979286,51.063621521],"type":"Point"}
}