{
  "type": "Feature",
  "properties": {
    "addr:full":"Brugstraat 1 Lochristi Oost-Vlaanderen 9080",
    "addr:housenumber":"1",
    "addr:postcode":"9080",
    "addr:street":"Brugstraat",
    "iso:country":"BE",
    "sg:address":"Brugstraat 1",
    "sg:city":"Lochristi",
    "sg:orig_category":"Eleveurs de bovins",
    "sg:phone":"+32 9 367 82 62",
    "sg:postcode":"9080",
    "sg:province":"Oost-Vlaanderen",
    "wof:name":"Aime De Jaeger",
    "wof:placetype":"venue"
},
  "geometry": {"coordinates":[3.8969979286,51.063621521],"type":"Point"}
}