{
  "type": "Feature",
  "properties": {
    "iso:country":"BE",
    "sg:address":"Rue De La Justice 84",
    "sg:city":"Saint-nicolas",
    "sg:classifiers":[
        {
            "category":"Education",
            "subcategory":"School",
            "type":"Public Place"
        }
    ],
    "sg:phone":"+32 4 254 25 35",
    "sg:postcode":"4420",
    "sg:province":"Li\u00e8ge",
    "sg:tags":[
        "supply"
    ],
    "wof:name":"L'ami Couleur",
    "wof:placetype":"venue"
},
  "geometry": {"coordinates":[5.5406498909,50.625579834],"type":"Point"}
}