{
  "type": "Feature",
  "properties": {
    "iso:country":"BE",
    "sg:address":"Oudstrijdersstraat 75",
    "sg:city":"Oudenaarde",
    "sg:orig_category":"Kapsalons",
    "sg:phone":"+32 55 31 15 12",
    "sg:postcode":"9700",
    "sg:province":"Oost-Vlaanderen",
    "wof:name":"Coiffure Wivina",
    "wof:placetype":"venue"
},
  "geometry": {"coordinates":[3.6336228848,50.8633041382],"type":"Point"}
}