{
  "type": "Feature",
  "properties": {
    "addr:full":"Dieweg 130 Ukkel/uccle Bruxelles-Capitale 1180",
    "addr:housenumber":"130",
    "addr:postcode":"1180",
    "addr:street":"Dieweg;/",
    "iso:country":"BE",
    "sg:address":"Dieweg 130",
    "sg:city":"Ukkel/uccle",
    "sg:classifiers":[
        {
            "category":"Autos & Motor Vehicles",
            "subcategory":"Fuel & Gas Station",
            "type":"Retail Goods"
        }
    ],
    "sg:phone":"+32 2 374 03 29",
    "sg:postcode":"1180",
    "sg:province":"Bruxelles-Capitale",
    "sg:tags":[
        "stations-service",
        "carburants"
    ],
    "wof:name":"Jet",
    "wof:placetype":"venue"
},
  "geometry": {"coordinates":[4.3476428986,50.7960968018],"type":"Point"}
}