{
  "type": "Feature",
  "properties": {
    "addr:full":"Boulevard Emile De Laveleye 132b Li\u00e8ge 1 (li\u00e8ge 2) Li\u00e8ge 4020",
    "addr:housenumber":"132b;1;2",
    "addr:postcode":"4020",
    "addr:street":"Boulevard Emile De Laveleye",
    "iso:country":"BE",
    "sg:address":"Boulevard Emile De Laveleye 132b",
    "sg:city":"Li\u00e8ge 1 (li\u00e8ge 2)",
    "sg:classifiers":[
        {
            "category":"Personal",
            "subcategory":"Beauty Salon",
            "type":"Services"
        }
    ],
    "sg:phone":"+32 4 344 45 47",
    "sg:postcode":"4020",
    "sg:province":"Li\u00e8ge",
    "sg:tags":[
        "lady",
        "-",
        "hairdressing"
    ],
    "wof:name":"Animatiff",
    "wof:placetype":"venue"
},
  "geometry": {"coordinates":[5.5909700394,50.6199188232],"type":"Point"}
}