{
  "type": "Feature",
  "properties": {
    "iso:country":"BE",
    "sg:address":"Gemehret 41",
    "sg:city":"Eupen",
    "sg:orig_category":"Dakwerken",
    "sg:phone":"+32 87 56 10 94",
    "sg:postcode":"4701",
    "sg:province":"Li\u00e8ge",
    "wof:name":"Dieter Groteclaes",
    "wof:placetype":"venue"
},
  "geometry": {"coordinates":[6.0163230896,50.6454277039],"type":"Point"}
}