{
  "type": "Feature",
  "properties": {
    "addr:full":"Molenstraat 5a Ieper (boezinge) West-Vlaanderen 8904",
    "addr:housenumber":"5a",
    "addr:postcode":"8904",
    "addr:street":"Molenstraat",
    "iso:country":"BE",
    "sg:address":"Molenstraat 5a",
    "sg:city":"Ieper (boezinge)",
    "sg:classifiers":[
        {
            "category":"Real Estate",
            "subcategory":"Architect",
            "type":"Services"
        }
    ],
    "sg:phone":"+32 57 42 37 14",
    "sg:postcode":"8904",
    "sg:province":"West-Vlaanderen",
    "wof:name":"Kinget M",
    "wof:placetype":"venue"
},
  "geometry": {"coordinates":[2.8638811111,50.896900177],"type":"Point"}
}