{
  "type": "Feature",
  "properties": {
    "addr:full":"Boechoutlaan 55 Grimbergen (strombeek-bever) Vlaams-Brabant 1853",
    "addr:housenumber":"55",
    "addr:postcode":"1853",
    "addr:street":"Boechoutlaan",
    "iso:country":"BE",
    "sg:address":"Boechoutlaan 55",
    "sg:city":"Grimbergen (strombeek-bever)",
    "sg:orig_category":"Smokers' supplies",
    "sg:phone":"+32 2 462 02 11",
    "sg:postcode":"1853",
    "sg:province":"Vlaams-Brabant",
    "wof:name":"Jt International Company Netherlands Bv (belgian Branch)",
    "wof:placetype":"venue"
},
  "geometry": {"coordinates":[4.3446741104,50.9036521912],"type":"Point"}
}