{
  "type": "Feature",
  "properties": {
    "iso:country":"BE",
    "sg:address":"Heidestraat 6c",
    "sg:city":"Hasselt",
    "sg:classifiers":[
        {
            "category":"Home & Garden",
            "subcategory":"Home Furnishings",
            "type":"Retail Goods"
        }
    ],
    "sg:phone":"+32 11 22 06 22",
    "sg:postcode":"3500",
    "sg:province":"Limburg",
    "sg:tags":[
        "lighting",
        "fixture",
        "-"
    ],
    "wof:name":"Crea Luce Bvba",
    "wof:placetype":"venue"
},
  "geometry": {"coordinates":[5.3674798012,50.9462013245],"type":"Point"}
}