{
  "type": "Feature",
  "properties": {
    "iso:country":"BE",
    "sg:address":"Rue Sondeville 115",
    "sg:city":"Oupeye",
    "sg:classifiers":[
        {
            "category":"Health Services",
            "subcategory":"Doctor",
            "type":"Services"
        }
    ],
    "sg:phone":"+32 4 248 37 33",
    "sg:postcode":"4680",
    "sg:province":"Li\u00e8ge",
    "sg:tags":[
        "medicinephysicians",
        "surgeon"
    ],
    "wof:name":"Bustin Willy",
    "wof:placetype":"venue"
},
  "geometry": {"coordinates":[5.6560401917,50.7091217041],"type":"Point"}
}