{
  "type": "Feature",
  "properties": {
    "iso:country":"BE",
    "sg:address":"Rue Du Moulin 80",
    "sg:city":"Boussu",
    "sg:classifiers":[
        {
            "category":"Health Services",
            "subcategory":"Doctor",
            "type":"Services"
        }
    ],
    "sg:phone":"+32 65 78 47 28",
    "sg:postcode":"7300",
    "sg:province":"Hainaut",
    "sg:tags":[
        "medicinephysicians",
        "surgeon"
    ],
    "wof:name":"Allart Fabienne",
    "wof:placetype":"venue"
},
  "geometry": {"coordinates":[3.7957689762,50.4400939941],"type":"Point"}
}