{
  "type": "Feature",
  "properties": {
    "addr:full":"Rue Basse 24br Ittre Brabant Wallon 1460",
    "addr:housenumber":"1460",
    "addr:street":"Rue Basse 24Br",
    "iso:country":"BE",
    "sg:address":"Rue Basse 24br",
    "sg:city":"Ittre",
    "sg:orig_category":"Advocaten and juridische adviseurs",
    "sg:phone":"+32 67 64 60 01",
    "sg:postcode":"1460",
    "sg:province":"Brabant Wallon",
    "wof:name":"S. Lenaerts",
    "wof:placetype":"venue"
},
  "geometry": {"coordinates":[4.2635231018,50.6487121582],"type":"Point"}
}