{
  "type": "Feature",
  "properties": {
    "addr:full":"Hofzomergem 0 Aalst Oost-Vlaanderen 9320",
    "addr:housenumber":"0",
    "addr:postcode":"9320",
    "addr:street":"Hofzomergem",
    "iso:country":"BE",
    "sg:address":"Hofzomergem 0",
    "sg:city":"Aalst",
    "sg:orig_category":"Sportclubs Sportterreinen and installaties behalve sportcentra",
    "sg:phone":"+32 53 77 76 79",
    "sg:postcode":"9320",
    "sg:province":"Oost-Vlaanderen",
    "wof:name":"Kangaroos K.a.t.c.",
    "wof:placetype":"venue"
},
  "geometry": {"coordinates":[4.0553851128,50.9209976196],"type":"Point"}
}