{
  "type": "Feature",
  "properties": {
    "addr:full":"Avenue Reine Astrid 6 Namur Namur 5000",
    "addr:housenumber":"6",
    "addr:postcode":"5000",
    "addr:street":"Avenue Reine Astrid",
    "iso:country":"BE",
    "sg:address":"Avenue Reine Astrid 6",
    "sg:city":"Namur",
    "sg:orig_category":"M\u00e9decins and sp\u00e9cialistes",
    "sg:phone":"+32 81 73 86 20",
    "sg:postcode":"5000",
    "sg:province":"Namur",
    "wof:name":"S. Newbery",
    "wof:placetype":"venue"
},
  "geometry": {"coordinates":[4.8582048416,50.4620933533],"type":"Point"}
}