{
  "type": "Feature",
  "properties": {
    "addr:full":"Veurnestraat 22 Diksmuide (pervijze) West-Vlaanderen 8600",
    "addr:housenumber":"22",
    "addr:postcode":"8600",
    "addr:street":"Veurnestraat",
    "iso:country":"BE",
    "sg:address":"Veurnestraat 22",
    "sg:city":"Diksmuide (pervijze)",
    "sg:classifiers":[
        {
            "category":"Bars & Pubs",
            "type":"Food & Drink"
        }
    ],
    "sg:phone":"+32 51 55 53 78",
    "sg:postcode":"8600",
    "sg:province":"West-Vlaanderen",
    "wof:name":"Druivenhof",
    "wof:placetype":"venue"
},
  "geometry": {"coordinates":[2.7915050983,51.073425293],"type":"Point"}
}