{
  "type": "Feature",
  "properties": {
    "addr:full":"Kneuterweg 3 Zonhoven Limburg 3520",
    "addr:housenumber":"3",
    "addr:postcode":"3520",
    "addr:street":"Kneuterweg",
    "iso:country":"BE",
    "sg:address":"Kneuterweg 3",
    "sg:city":"Zonhoven",
    "sg:orig_category":"Brood, gebak and snoepgoed",
    "sg:phone":"+32 11 82 16 81",
    "sg:postcode":"3520",
    "sg:province":"Limburg",
    "wof:name":"Bakkerij A Milissen",
    "wof:placetype":"venue"
},
  "geometry": {"coordinates":[5.4140729904,50.988155365],"type":"Point"}
}