{
  "type": "Feature",
  "properties": {
    "iso:country":"BE",
    "sg:address":"Arenbergstraat 10",
    "sg:city":"Brussel/bruxelles",
    "sg:orig_category":"Kapsalons",
    "sg:phone":"+32 2 513 27 82",
    "sg:postcode":"1000",
    "sg:province":"Bruxelles-Capitale",
    "wof:name":"Jacques Dessange",
    "wof:placetype":"venue"
},
  "geometry": {"coordinates":[4.3561549187,50.8485374451],"type":"Point"}
}