{
  "type": "Feature",
  "properties": {
    "iso:country":"BE",
    "sg:address":"Zuidstraat 94",
    "sg:city":"Ichtegem",
    "sg:orig_category":"Diverse grafische activiteiten",
    "sg:phone":"+32 51 58 20 81",
    "sg:postcode":"8480",
    "sg:province":"West-Vlaanderen",
    "wof:name":"Bureau Vermeersch",
    "wof:placetype":"venue"
},
  "geometry": {"coordinates":[3.0366659164,51.1061096191],"type":"Point"}
}