{
  "type": "Feature",
  "properties": {
    "addr:full":"Rue D'hannetaire 18 Bruxelles Bruxelles-Capitale 1130",
    "addr:housenumber":"18",
    "addr:postcode":"1130",
    "addr:street":"Rue D'Hannetaire",
    "iso:country":"BE",
    "sg:address":"Rue D'hannetaire 18",
    "sg:city":"Bruxelles",
    "sg:classifiers":[
        {
            "category":"Professional",
            "subcategory":"Management & Consulting",
            "type":"Services"
        }
    ],
    "sg:phone":"+32 2 245 24 11",
    "sg:postcode":"1130",
    "sg:province":"Bruxelles-Capitale",
    "sg:tags":[
        "consultant",
        "promotion",
        "-",
        "sale"
    ],
    "wof:name":"R.c.g. Organisation",
    "wof:placetype":"venue"
},
  "geometry": {"coordinates":[4.4147229195,50.891620636],"type":"Point"}
}