{
  "type": "Feature",
  "properties": {
    "addr:full":"Kruisstraat 13 Begijnendijk Vlaams-Brabant 3130",
    "addr:housenumber":"13",
    "addr:postcode":"3130",
    "addr:street":"Kruisstraat",
    "iso:country":"BE",
    "sg:address":"Kruisstraat 13",
    "sg:city":"Begijnendijk",
    "sg:classifiers":[
        {
            "category":"Health Services",
            "subcategory":"Hospital",
            "type":"Services"
        }
    ],
    "sg:phone":"+32 16 68 09 10",
    "sg:postcode":"3130",
    "sg:province":"Vlaams-Brabant",
    "sg:tags":[
        "ambulance"
    ],
    "wof:name":"Levenskruis Vzw",
    "wof:placetype":"venue"
},
  "geometry": {"coordinates":[4.7867121696,51.0318756104],"type":"Point"}
}