{
  "type": "Feature",
  "properties": {
    "addr:full":"Watermolenstraat 43 Dilsen-stokkem Limburg 3650",
    "addr:housenumber":"43",
    "addr:postcode":"3650",
    "addr:street":"Watermolenstraat",
    "iso:country":"BE",
    "sg:address":"Watermolenstraat 43",
    "sg:city":"Dilsen-stokkem",
    "sg:orig_category":"Plaatsen van vloer- and muurbekleding Schilders",
    "sg:phone":"+32 89 75 74 02",
    "sg:postcode":"3650",
    "sg:province":"Limburg",
    "wof:name":"Jacobus Hornix",
    "wof:placetype":"venue"
},
  "geometry": {"coordinates":[5.7373299599,51.0299301147],"type":"Point"}
}