{
  "type": "Feature",
  "properties": {
    "iso:country":"BE",
    "sg:address":"Tiensestraat 255",
    "sg:city":"Leuven",
    "sg:orig_category":"Tweedehandsgoederen",
    "sg:phone":"+32 16 23 28 65",
    "sg:postcode":"3000",
    "sg:province":"Vlaams-Brabant",
    "wof:name":"'t Pand",
    "wof:placetype":"venue"
},
  "geometry": {"coordinates":[4.7132167816,50.8740081787],"type":"Point"}
}