{
  "type": "Feature",
  "properties": {
    "iso:country":"BE",
    "sg:address":"Felix Moonsstraat 2",
    "sg:city":"Diest",
    "sg:orig_category":"Banques and organismes de cr\u00e9dit",
    "sg:phone":"+32 13 33 33 01",
    "sg:postcode":"3290",
    "sg:province":"Vlaams-Brabant",
    "wof:name":"Fortis",
    "wof:placetype":"venue"
},
  "geometry": {"coordinates":[5.0534200668,50.9853973389],"type":"Point"}
}