{
  "type": "Feature",
  "properties": {
    "addr:full":"Tuinwijk 24 Rumst Antwerpen 2840",
    "addr:housenumber":"24",
    "addr:postcode":"2840",
    "addr:street":"Tuinwijk",
    "iso:country":"BE",
    "sg:address":"Tuinwijk 24",
    "sg:city":"Rumst",
    "sg:classifiers":[
        {
            "category":"Personal",
            "subcategory":"Beauty Salon",
            "type":"Services"
        }
    ],
    "sg:phone":"+32 3 290 38 36",
    "sg:postcode":"2840",
    "sg:province":"Antwerpen",
    "sg:tags":[
        "lady",
        "-",
        "hairdressing"
    ],
    "wof:name":"Dreams",
    "wof:placetype":"venue"
},
  "geometry": {"coordinates":[4.4238882065,51.0799560547],"type":"Point"}
}