{
  "type": "Feature",
  "properties": {
    "addr:full":"Monnikenwerve 95 Brugge West-Vlaanderen 8000",
    "addr:housenumber":"95",
    "addr:postcode":"8000",
    "addr:street":"Monnikenwerve",
    "iso:country":"BE",
    "sg:address":"Monnikenwerve 95",
    "sg:city":"Brugge",
    "sg:classifiers":[
        {
            "category":"Utilities",
            "subcategory":"Fuel Oil & Lpg",
            "type":"Services"
        }
    ],
    "sg:phone":"+32 50 31 46 14",
    "sg:postcode":"8000",
    "sg:province":"West-Vlaanderen",
    "wof:name":"Cools & Zn",
    "wof:placetype":"venue"
},
  "geometry": {"coordinates":[3.2007861137,51.2488861084],"type":"Point"}
}