{
  "type": "Feature",
  "properties": {
    "addr:full":"Immerzeeldreef 111 Aalst Oost-Vlaanderen 9300",
    "addr:housenumber":"111",
    "addr:postcode":"9300",
    "iso:country":"BE",
    "sg:address":"Immerzeeldreef 111",
    "sg:city":"Aalst",
    "sg:classifiers":[
        {
            "category":"Health Services",
            "subcategory":"Doctor",
            "type":"Services"
        }
    ],
    "sg:phone":"+32 53 77 96 62",
    "sg:postcode":"9300",
    "sg:province":"Oost-Vlaanderen",
    "sg:tags":[
        "medicinephysicians",
        "surgeon"
    ],
    "wof:name":"De Geest R",
    "wof:placetype":"venue"
},
  "geometry": {"coordinates":[4.0708360672,50.9299697876],"type":"Point"}
}