{
  "type": "Feature",
  "properties": {
    "iso:country":"BE",
    "sg:address":"De Billemontstraat 109",
    "sg:city":"Geel",
    "sg:classifiers":[
        {
            "category":"Social Services",
            "subcategory":"Job Training",
            "type":"Services"
        }
    ],
    "sg:phone":"+32 14 58 02 44",
    "sg:postcode":"2440",
    "sg:province":"Antwerpen",
    "sg:tags":[
        "personnel"
    ],
    "wof:name":"Vansant & Partners Bvba",
    "wof:placetype":"venue"
},
  "geometry": {"coordinates":[5.0004000664,51.162311554],"type":"Point"}
}