{
  "type": "Feature",
  "properties": {
    "addr:full":"Rue Libeau 33 Oupeye (houtain-saint-sim\u00e9on) Li\u00e8ge 4682",
    "addr:housenumber":"33",
    "addr:postcode":"4682",
    "addr:street":"Rue Libeau;Houtain-Saint-Sime\u0301On",
    "iso:country":"BE",
    "sg:address":"Rue Libeau 33",
    "sg:city":"Oupeye (houtain-saint-sim\u00e9on)",
    "sg:classifiers":[
        {
            "category":"Health Services",
            "subcategory":"Health Practitioner",
            "type":"Services"
        }
    ],
    "sg:phone":"+32 4 286 36 70",
    "sg:postcode":"4682",
    "sg:province":"Li\u00e8ge",
    "sg:tags":[
        "physiotherapist"
    ],
    "wof:name":"Maloir M",
    "wof:placetype":"venue"
},
  "geometry": {"coordinates":[5.6338701248,50.7312393188],"type":"Point"}
}