{
  "type": "Feature",
  "properties": {
    "addr:full":"Chauss\u00c9e D'arlon 39 Bastogne Luxembourg 6600",
    "addr:housenumber":"39",
    "addr:postcode":"6600",
    "addr:street":"Chausse\u0301E D'Arlon",
    "iso:country":"BE",
    "sg:address":"Chauss\u00c9e D'arlon 39",
    "sg:city":"Bastogne",
    "sg:orig_category":"Dakwerken Installatie van houten of kunststof schrijnwerk Installatie van metalen schrijnwerk Schoon",
    "sg:phone":"+32 61 21 40 94",
    "sg:postcode":"6600",
    "sg:province":"Luxembourg",
    "wof:name":"Debras-vaguet",
    "wof:placetype":"venue"
},
  "geometry": {"coordinates":[5.7180709839,49.9960899353],"type":"Point"}
}