{
  "type": "Feature",
  "properties": {
    "addr:full":"Oude Vest 79 Dendermonde Oost-Vlaanderen 9200",
    "addr:housenumber":"79",
    "addr:postcode":"9200",
    "addr:street":"Oude Vest;Oost-Vlaanderen",
    "iso:country":"BE",
    "sg:address":"Oude Vest 79",
    "sg:city":"Dendermonde",
    "sg:classifiers":[
        {
            "category":"Shopping",
            "subcategory":"Clothing, Apparel, & Fashions",
            "type":"Retail Goods"
        }
    ],
    "sg:phone":"+32 52 21 97 11",
    "sg:postcode":"9200",
    "sg:province":"Oost-Vlaanderen",
    "sg:tags":[
        "lady",
        "clothing",
        "-"
    ],
    "wof:name":"Miss Cannes",
    "wof:placetype":"venue"
},
  "geometry": {"coordinates":[4.1023907661,51.0298500061],"type":"Point"}
}