{
  "type": "Feature",
  "properties": {
    "iso:country":"BE",
    "sg:address":"Avenue Charles Woeste 281",
    "sg:city":"Bruxelles (jette)",
    "sg:classifiers":[
        {
            "category":"Professional",
            "subcategory":"Credit Reporting & Collection",
            "type":"Services"
        }
    ],
    "sg:phone":"+32 2 478 66 31",
    "sg:postcode":"1090",
    "sg:province":"Bruxelles-Capitale",
    "sg:tags":[
        "bailiff"
    ],
    "wof:name":"Dartevelle Ph",
    "wof:placetype":"venue"
},
  "geometry": {"coordinates":[4.335149765,50.8683395386],"type":"Point"}
}