{
  "type": "Feature",
  "properties": {
    "addr:full":"Blindeliedenstraat 3 Ieper West-Vlaanderen 8900",
    "addr:housenumber":"3",
    "addr:postcode":"8900",
    "addr:street":"Blindeliedenstraat",
    "iso:country":"BE",
    "sg:address":"Blindeliedenstraat 3",
    "sg:city":"Ieper",
    "sg:classifiers":[
        {
            "category":"Home & Garden",
            "subcategory":"Hardware",
            "type":"Retail Goods"
        }
    ],
    "sg:phone":"+32 57 20 46 18",
    "sg:postcode":"8900",
    "sg:province":"West-Vlaanderen",
    "sg:tags":[
        "gate",
        "opener",
        "door",
        "automatic"
    ],
    "wof:name":"De Nieuwe Gouden Spade",
    "wof:placetype":"venue"
},
  "geometry": {"coordinates":[2.886384964,50.8473854065],"type":"Point"}
}