{
  "type": "Feature",
  "properties": {
    "addr:full":"Chemin Saint Pierre 33 Mons Hainaut 7030",
    "addr:housenumber":"33",
    "addr:postcode":"7030",
    "addr:street":"Chemin Saint Pierre;Hainaut",
    "iso:country":"BE",
    "sg:address":"Chemin Saint Pierre 33",
    "sg:city":"Mons",
    "sg:orig_category":"Astrologen, grafologen and mediums",
    "sg:phone":"+32 65 33 45 79",
    "sg:postcode":"7030",
    "sg:province":"Hainaut",
    "wof:name":"Pernot C",
    "wof:placetype":"venue"
},
  "geometry": {"coordinates":[3.9957809448,50.4399490356],"type":"Point"}
}