{
  "type": "Feature",
  "properties": {
    "iso:country":"BE",
    "sg:address":"Avenue Albert I 277",
    "sg:city":"Rixensart (genval)",
    "sg:classifiers":[
        {
            "category":"Social Services",
            "type":"Services"
        }
    ],
    "sg:phone":"+32 2 653 86 75",
    "sg:postcode":"1332",
    "sg:province":"Brabant Wallon",
    "wof:name":"Centre De Planning & Consultations Conjugales Et Familiales",
    "wof:placetype":"venue"
},
  "geometry": {"coordinates":[4.5139670372,50.7253112793],"type":"Point"}
}