{
  "type": "Feature",
  "properties": {
    "addr:full":"Rue De France 72 Philippeville Namur 5600",
    "addr:housenumber":"72",
    "addr:postcode":"5600",
    "addr:street":"Rue De France",
    "iso:country":"BE",
    "sg:address":"Rue De France 72",
    "sg:city":"Philippeville",
    "sg:classifiers":[
        {
            "category":"Retail",
            "subcategory":"Auto Repair",
            "type":"Services"
        }
    ],
    "sg:phone":"+32 71 66 60 40",
    "sg:postcode":"5600",
    "sg:province":"Namur",
    "sg:tags":[
        "garage"
    ],
    "wof:name":"Delfosse Garage",
    "wof:placetype":"venue"
},
  "geometry": {"coordinates":[4.5378928185,50.1962547302],"type":"Point"}
}