{
  "type": "Feature",
  "properties": {
    "addr:full":"Voorstehoeve 130 Asse (mollem) Vlaams-Brabant 1730",
    "addr:housenumber":"130",
    "addr:postcode":"1730",
    "addr:street":"Voorstehoeve",
    "iso:country":"BE",
    "sg:address":"Voorstehoeve 130",
    "sg:city":"Asse (mollem)",
    "sg:classifiers":[
        {
            "category":"Retail",
            "subcategory":"Event Space",
            "type":"Services"
        }
    ],
    "sg:phone":"+32 2 452 95 33",
    "sg:postcode":"1730",
    "sg:province":"Vlaams-Brabant",
    "sg:tags":[
        "organisation"
    ],
    "wof:name":"A.a. Promotion Services Bvba",
    "wof:placetype":"venue"
},
  "geometry": {"coordinates":[4.214589119,50.9331817627],"type":"Point"}
}