{
  "type": "Feature",
  "properties": {
    "addr:full":"G. Gezellestraat 2 Staden West-Vlaanderen 8840",
    "addr:housenumber":"2",
    "addr:postcode":"8840",
    "addr:street":"G. Gezellestraat",
    "iso:country":"BE",
    "sg:address":"G. Gezellestraat 2",
    "sg:city":"Staden",
    "sg:classifiers":[
        {
            "category":"Personal",
            "subcategory":"Beauty Salon",
            "type":"Services"
        }
    ],
    "sg:phone":"+32 51 22 35 52",
    "sg:postcode":"8840",
    "sg:province":"West-Vlaanderen",
    "sg:tags":[
        "de",
        "coiffure"
    ],
    "wof:name":"Coiffure Chantal",
    "wof:placetype":"venue"
},
  "geometry": {"coordinates":[3.0598061085,50.9400863647],"type":"Point"}
}