{
  "type": "Feature",
  "properties": {
    "addr:full":"Rue De Fer 70 Namur Namur 5000",
    "addr:housenumber":"70",
    "addr:postcode":"5000",
    "addr:street":"Rue De Fer",
    "iso:country":"BE",
    "sg:address":"Rue De Fer 70",
    "sg:city":"Namur",
    "sg:classifiers":[
        {
            "category":"Shopping",
            "subcategory":"Clothing, Apparel, & Fashions",
            "type":"Retail Goods"
        }
    ],
    "sg:phone":"+32 81 22 50 81",
    "sg:postcode":"5000",
    "sg:province":"Namur",
    "sg:tags":[
        "v\u00eatements",
        "pour",
        "dame"
    ],
    "wof:name":"Maison Mayerline",
    "wof:placetype":"venue"
},
  "geometry": {"coordinates":[4.8654708862,50.4670715332],"type":"Point"}
}