{
  "type": "Feature",
  "properties": {
    "iso:country":"BE",
    "sg:address":"Stuiverwijk 72",
    "sg:city":"Nieuwpoort",
    "sg:orig_category":"Diverse persoonlijke diensten",
    "sg:phone":"+32 58 23 58 48",
    "sg:postcode":"8620",
    "sg:province":"West-Vlaanderen",
    "wof:name":"Kurt Adriansens",
    "wof:placetype":"venue"
},
  "geometry": {"coordinates":[2.7381999493,51.1313095093],"type":"Point"}
}