{
  "type": "Feature",
  "properties": {
    "addr:full":"Zwarte Zusterslaan 1 Maldegem Oost-Vlaanderen 9990",
    "addr:housenumber":"1",
    "addr:postcode":"9990",
    "addr:street":"Zusterslaan",
    "iso:country":"BE",
    "sg:address":"Zwarte Zusterslaan 1",
    "sg:city":"Maldegem",
    "sg:classifiers":[
        {
            "category":"Education",
            "subcategory":"School",
            "type":"Public Place"
        }
    ],
    "sg:phone":"+32 50 71 23 81",
    "sg:postcode":"9990",
    "sg:province":"Oost-Vlaanderen",
    "sg:tags":[
        "primary"
    ],
    "wof:name":"Broedersschool",
    "wof:placetype":"venue"
},
  "geometry": {"coordinates":[3.4523251057,51.206401825],"type":"Point"}
}