{
  "type": "Feature",
  "properties": {
    "addr:full":"Staatsbaan 160 Zulte Oost-Vlaanderen 9870",
    "addr:housenumber":"160",
    "addr:postcode":"9870",
    "addr:street":"Staatsbaan",
    "iso:country":"BE",
    "sg:address":"Staatsbaan 160",
    "sg:city":"Zulte",
    "sg:classifiers":[
        {
            "category":"Sports & Exercise",
            "subcategory":"Bowling",
            "type":"Entertainment"
        }
    ],
    "sg:phone":"+32 9 388 93 29",
    "sg:postcode":"9870",
    "sg:province":"Oost-Vlaanderen",
    "sg:tags":[
        "skittle",
        "alley"
    ],
    "wof:name":"Bowling Strike Zulte",
    "wof:placetype":"venue"
},
  "geometry": {"coordinates":[3.4417619705,50.9207267761],"type":"Point"}
}