{
  "type": "Feature",
  "properties": {
    "addr:full":"Rue De Mons 230 Boussu (hornu) Hainaut 7301",
    "addr:housenumber":"230",
    "addr:postcode":"7301",
    "addr:street":"Rue De Mons",
    "iso:country":"BE",
    "sg:address":"Rue De Mons 230",
    "sg:city":"Boussu (hornu)",
    "sg:classifiers":[
        {
            "category":"Health Services",
            "subcategory":"Doctor",
            "type":"Services"
        }
    ],
    "sg:phone":"+32 65 71 07 11",
    "sg:postcode":"7301",
    "sg:province":"Hainaut",
    "sg:tags":[
        "medicinephysicians",
        "surgeon"
    ],
    "wof:name":"Mahillon Ph",
    "wof:placetype":"venue"
},
  "geometry": {"coordinates":[3.8257451057,50.4362258911],"type":"Point"}
}