{
  "type": "Feature",
  "properties": {
    "iso:country":"BE",
    "sg:address":"Rue De Namur 67",
    "sg:city":"Mont-sainte-aldegonde",
    "sg:orig_category":"Cardboard Finishing",
    "sg:phone":"+32 64 33 12 78",
    "sg:postcode":"7141",
    "sg:province":"Hainaut",
    "wof:name":"Ets Bernard",
    "wof:placetype":"venue"
},
  "geometry": {"coordinates":[4.2275471687,50.4308509827],"type":"Point"}
}