{
  "type": "Feature",
  "properties": {
    "addr:full":"Avenue H\u00c9l\u00c8ne-solvay 3 Gembloux Namur 5030",
    "addr:housenumber":"3",
    "addr:postcode":"5030",
    "addr:street":"Avenue He\u0301Le\u0300Ne-Solvay;Namur",
    "iso:country":"BE",
    "sg:address":"Avenue H\u00c9l\u00c8ne-solvay 3",
    "sg:city":"Gembloux",
    "sg:classifiers":[
        {
            "category":"Insurance",
            "subcategory":"Insurance Agent",
            "type":"Services"
        }
    ],
    "sg:phone":"+32 81 56 08 86",
    "sg:postcode":"5030",
    "sg:province":"Namur",
    "sg:tags":[
        "verzekeringsmakelaars",
        "expert"
    ],
    "wof:name":"Assurances Ghislain",
    "wof:placetype":"venue"
},
  "geometry": {"coordinates":[4.7441129684,50.5325012207],"type":"Point"}
}