{
  "type": "Feature",
  "properties": {
    "addr:full":"1820 Steenokkerzeel Vlaams-Brabant 1820",
    "addr:postcode":"1820;1820",
    "iso:country":"BE",
    "sg:address":"1820",
    "sg:city":"Steenokkerzeel",
    "sg:orig_category":"Services annexes des transports terrestres",
    "sg:phone":"+32 2 753 01 10",
    "sg:postcode":"1820",
    "sg:province":"Vlaams-Brabant",
    "wof:name":"Car Hotel",
    "wof:placetype":"venue"
},
  "geometry": {"coordinates":[4.5128650665,50.9095802307],"type":"Point"}
}