{
  "type": "Feature",
  "properties": {
    "addr:full":"Keizer Karellaan 557 Sint-agatha-berchem/berchem-sainte-agathe Bruxelles-Capitale 1082",
    "addr:housenumber":"557",
    "addr:postcode":"1082",
    "addr:street":"Keizer Karellaan;/",
    "iso:country":"BE",
    "sg:address":"Keizer Karellaan 557",
    "sg:city":"Sint-agatha-berchem/berchem-sainte-agathe",
    "sg:orig_category":"Benzinestations and brandstoffen",
    "sg:phone":"+32 2 465 47 65",
    "sg:postcode":"1082",
    "sg:province":"Bruxelles-Capitale",
    "wof:name":"Bp",
    "wof:placetype":"venue"
},
  "geometry": {"coordinates":[4.2886891365,50.8709068298],"type":"Point"}
}