{
  "type": "Feature",
  "properties": {
    "iso:country":"BE",
    "sg:address":"Diksmuidsestraat 63",
    "sg:city":"Ieper",
    "sg:orig_category":"M\u00e9decins and sp\u00e9cialistes",
    "sg:phone":"+32 57 20 22 59",
    "sg:postcode":"8900",
    "sg:province":"West-Vlaanderen",
    "wof:name":"P. Wullus",
    "wof:placetype":"venue"
},
  "geometry": {"coordinates":[2.886425972,50.853729248],"type":"Point"}
}