{
  "type": "Feature",
  "properties": {
    "addr:full":"Rue Des Roches 25 Gedinne Namur 5575",
    "addr:housenumber":"25",
    "addr:postcode":"5575",
    "addr:street":"Rue Des Roches",
    "iso:country":"BE",
    "sg:address":"Rue Des Roches 25",
    "sg:city":"Gedinne",
    "sg:orig_category":"Woningbouw",
    "sg:phone":"+32 61 58 83 15",
    "sg:postcode":"5575",
    "sg:province":"Namur",
    "wof:name":"Fe. Arnould F. & E.",
    "wof:placetype":"venue"
},
  "geometry": {"coordinates":[4.9549422264,49.9604187012],"type":"Point"}
}