{
  "type": "Feature",
  "properties": {
    "addr:full":"Zeswegenstraat 62 Waregem West-Vlaanderen 8790",
    "addr:housenumber":"62",
    "addr:postcode":"8790",
    "addr:street":"Zeswegenstraat",
    "iso:country":"BE",
    "sg:address":"Zeswegenstraat 62",
    "sg:city":"Waregem",
    "sg:orig_category":"Herstellingswinkels voor diverse persoonlijke and huishoudartikelen IJzerwaren, bouw- and verfmateri",
    "sg:phone":"+32 56 60 12 24",
    "sg:postcode":"8790",
    "sg:province":"West-Vlaanderen",
    "wof:name":"Van Thuyne",
    "wof:placetype":"venue"
},
  "geometry": {"coordinates":[3.4224729538,50.8888587952],"type":"Point"}
}