{
  "type": "Feature",
  "properties": {
    "addr:full":"Pand 203 Waregem West-Vlaanderen 8790",
    "addr:housenumber":"203",
    "addr:postcode":"8790",
    "addr:street":"Pand",
    "iso:country":"BE",
    "sg:address":"Pand 203",
    "sg:city":"Waregem",
    "sg:orig_category":"Disquaires",
    "sg:phone":"+32 56 60 81 62",
    "sg:postcode":"8790",
    "sg:province":"West-Vlaanderen",
    "wof:name":"Musikladen",
    "wof:placetype":"venue"
},
  "geometry": {"coordinates":[3.432890892,50.8854866028],"type":"Point"}
}