{
  "type": "Feature",
  "properties": {
    "addr:full":"Rue Du Parc 23-33 Liege Li\u00e8ge 4020",
    "addr:postcode":"23-33;4020",
    "addr:street":"Rue Du Parc",
    "iso:country":"BE",
    "sg:address":"Rue Du Parc 23-33",
    "sg:city":"Liege",
    "sg:orig_category":"Diverse bedrijfsbeheeradviesbureaus",
    "sg:phone":"+32 4 342 88 09",
    "sg:postcode":"4020",
    "sg:province":"Li\u00e8ge",
    "wof:name":"Bureau Gama",
    "wof:placetype":"venue"
},
  "geometry": {"coordinates":[5.5754761696,50.6315574646],"type":"Point"}
}