{
  "type": "Feature",
  "properties": {
    "addr:full":"Rue Lanfray 19 Ixelles Bruxelles-Capitale 1050",
    "addr:housenumber":"19",
    "addr:postcode":"1050",
    "addr:street":"Rue Lanfray",
    "iso:country":"BE",
    "sg:address":"Rue Lanfray 19",
    "sg:city":"Ixelles",
    "sg:orig_category":"Jardinage",
    "sg:phone":"+32 2 647 94 61",
    "sg:postcode":"1050",
    "sg:province":"Bruxelles-Capitale",
    "wof:name":"Greenexpress",
    "wof:placetype":"venue"
},
  "geometry": {"coordinates":[4.3738980293,50.8255844116],"type":"Point"}
}