{
  "type": "Feature",
  "properties": {
    "addr:full":"Patersstraat 69 Turnhout Antwerpen 2300",
    "addr:housenumber":"69",
    "addr:postcode":"2300",
    "addr:street":"Patersstraat",
    "iso:country":"BE",
    "sg:address":"Patersstraat 69",
    "sg:city":"Turnhout",
    "sg:orig_category":"Dameskledingzaken",
    "sg:phone":"+32 14 41 58 39",
    "sg:postcode":"2300",
    "sg:province":"Antwerpen",
    "wof:name":"Miss Boetiek",
    "wof:placetype":"venue"
},
  "geometry": {"coordinates":[4.9493041039,51.3260421753],"type":"Point"}
}