{
  "type": "Feature",
  "properties": {
    "iso:country":"BE",
    "sg:address":"Rue Gallait 143",
    "sg:city":"Schaarbeek/schaerbeek",
    "sg:orig_category":"Artistes ind\u00e9pendants",
    "sg:phone":"+32 2 241 94 78",
    "sg:postcode":"1030",
    "sg:province":"Bruxelles-Capitale",
    "wof:name":"Louis Vehent",
    "wof:placetype":"venue"
},
  "geometry": {"coordinates":[4.3712539673,50.8692054749],"type":"Point"}
}