{
  "type": "Feature",
  "properties": {
    "addr:full":"Avenue Laboulle 32 Esneux (tilff) Li\u00e8ge 4130",
    "addr:housenumber":"32",
    "addr:postcode":"4130",
    "addr:street":"Avenue Laboulle",
    "iso:country":"BE",
    "sg:address":"Avenue Laboulle 32",
    "sg:city":"Esneux (tilff)",
    "sg:classifiers":[
        {
            "category":"Personal",
            "subcategory":"Beauty Salon",
            "type":"Services"
        }
    ],
    "sg:phone":"+32 4 388 27 71",
    "sg:postcode":"4130",
    "sg:province":"Li\u00e8ge",
    "wof:name":"Anemone",
    "wof:placetype":"venue"
},
  "geometry": {"coordinates":[5.5669360161,50.5327568054],"type":"Point"}
}