{
  "type": "Feature",
  "properties": {
    "addr:full":"Eikenstraat 86 Rumst Antwerpen 2840",
    "addr:housenumber":"86",
    "addr:postcode":"2840",
    "addr:street":"Eikenstraat",
    "iso:country":"BE",
    "sg:address":"Eikenstraat 86",
    "sg:city":"Rumst",
    "sg:orig_category":"Bloemen and planten",
    "sg:phone":"+32 3 888 84 36",
    "sg:postcode":"2840",
    "sg:province":"Antwerpen",
    "wof:name":"De Maretak",
    "wof:placetype":"venue"
},
  "geometry": {"coordinates":[4.410241127,51.1062240601],"type":"Point"}
}