{
  "type": "Feature",
  "properties": {
    "addr:full":"Avenue Alphonse Allard 232 Braine L'alleud (braine-l'alleud) Brabant Wallon 1420",
    "addr:housenumber":"232",
    "addr:postcode":"1420",
    "addr:street":"Avenue Alphonse Allard",
    "iso:country":"BE",
    "sg:address":"Avenue Alphonse Allard 232",
    "sg:city":"Braine L'alleud (braine-l'alleud)",
    "sg:classifiers":[
        {
            "category":"Home & Garden",
            "subcategory":"Carpets & Floor Coverings",
            "type":"Retail Goods"
        }
    ],
    "sg:phone":"+32 2 387 34 79",
    "sg:postcode":"1420",
    "sg:province":"Brabant Wallon",
    "sg:tags":[
        "-"
    ],
    "wof:name":"Stordeur Fr\u00e9res Sprl",
    "wof:placetype":"venue"
},
  "geometry": {"coordinates":[-0.7004899979,47.369140625],"type":"Point"}
}