{
  "type": "Feature",
  "properties": {
    "addr:full":"Bredabaan 63 Brasschaat Antwerpen 2930",
    "addr:housenumber":"63",
    "addr:postcode":"2930",
    "addr:street":"Bredabaan",
    "iso:country":"BE",
    "sg:address":"Bredabaan 63",
    "sg:city":"Brasschaat",
    "sg:orig_category":"Avocats and conseillers juridiques",
    "sg:phone":"+32 3 651 44 26",
    "sg:postcode":"2930",
    "sg:province":"Antwerpen",
    "wof:name":"Karel Wille",
    "wof:placetype":"venue"
},
  "geometry": {"coordinates":[4.4743318558,51.2768783569],"type":"Point"}
}