{
  "type": "Feature",
  "properties": {
    "addr:full":"Avenue De Mai 206 Bruxelles (woluwe-saint-lambert) Bruxelles-Capitale 1200",
    "addr:housenumber":"206",
    "addr:postcode":"1200",
    "addr:street":"Avenue De Mai",
    "iso:country":"BE",
    "sg:address":"Avenue De Mai 206",
    "sg:city":"Bruxelles (woluwe-saint-lambert)",
    "sg:classifiers":[
        {
            "category":"Communications",
            "type":"Services"
        }
    ],
    "sg:phone":"+32 2 733 07 85",
    "sg:postcode":"1200",
    "sg:province":"Bruxelles-Capitale",
    "sg:tags":[
        "translator"
    ],
    "wof:name":"Brian Frost-smith Sprl",
    "wof:placetype":"venue"
},
  "geometry": {"coordinates":[4.4133048058,50.8485488892],"type":"Point"}
}