{
  "type": "Feature",
  "properties": {
    "addr:full":"Ringlaan Eeklo Oost-Vlaanderen 9900",
    "addr:postcode":"9900",
    "addr:street":"Ringlaan",
    "iso:country":"BE",
    "sg:address":"Ringlaan",
    "sg:city":"Eeklo",
    "sg:orig_category":"Beheer van afvalopslag- and stortplaatsen",
    "sg:phone":"+32 9 378 36 62",
    "sg:postcode":"9900",
    "sg:province":"Oost-Vlaanderen",
    "wof:name":"Containerpark Eeklo",
    "wof:placetype":"venue"
},
  "geometry": {"coordinates":[3.5371360779,51.1798667908],"type":"Point"}
}