{
  "type": "Feature",
  "properties": {
    "iso:country":"BE",
    "sg:address":"Ligywijk 37",
    "sg:city":"Ieper",
    "sg:orig_category":"Rev\u00eatements pour sols and murs. Construction de maisons",
    "sg:phone":"+32 57 21 91 15",
    "sg:postcode":"8900",
    "sg:province":"West-Vlaanderen",
    "wof:name":"Malfait-bourgeois",
    "wof:placetype":"venue"
},
  "geometry": {"coordinates":[2.9015519619,50.8544044495],"type":"Point"}
}