{
  "type": "Feature",
  "properties": {
    "addr:full":"Dorpsstraat 57 Lubbeek Vlaams-Brabant 3210",
    "addr:housenumber":"57",
    "addr:postcode":"3210",
    "addr:street":"Dorpsstraat",
    "iso:country":"BE",
    "sg:address":"Dorpsstraat 57",
    "sg:city":"Lubbeek",
    "sg:orig_category":"Charpentes and couvertures",
    "sg:phone":"+32 16 63 10 45",
    "sg:postcode":"3210",
    "sg:province":"Vlaams-Brabant",
    "wof:name":"Fa. Bollen-van Den Berghe",
    "wof:placetype":"venue"
},
  "geometry": {"coordinates":[4.8395581245,50.8752326965],"type":"Point"}
}