{
  "type": "Feature",
  "properties": {
    "addr:full":"Eeuwfeestwal 12 Tongeren Limburg 3700",
    "addr:housenumber":"12",
    "addr:postcode":"3700",
    "addr:street":"Eeuwfeestwal",
    "iso:country":"BE",
    "sg:address":"Eeuwfeestwal 12",
    "sg:city":"Tongeren",
    "sg:classifiers":[
        {
            "category":"Personal",
            "subcategory":"Beauty Salon",
            "type":"Services"
        }
    ],
    "sg:phone":"+32 12 26 35 51",
    "sg:postcode":"3700",
    "sg:province":"Limburg",
    "sg:tags":[
        "lady",
        "-",
        "hairdressing"
    ],
    "wof:name":"Alexandra Coiffure",
    "wof:placetype":"venue"
},
  "geometry": {"coordinates":[5.4606051445,50.7812614441],"type":"Point"}
}