{
  "type": "Feature",
  "properties": {
    "iso:country":"BE",
    "sg:address":"Lange Beemdenlaan 8",
    "sg:city":"Leuven (wilsele)",
    "sg:classifiers":[
        {
            "category":"Professional",
            "subcategory":"Art Services",
            "type":"Services"
        }
    ],
    "sg:phone":"+32 16 44 72 51",
    "sg:postcode":"3012",
    "sg:province":"Vlaams-Brabant",
    "sg:tags":[
        "designer",
        "display"
    ],
    "wof:name":"Fabry S",
    "wof:placetype":"venue"
},
  "geometry": {"coordinates":[4.7129220963,50.9237136841],"type":"Point"}
}