{
  "type": "Feature",
  "properties": {
    "iso:country":"BE",
    "sg:address":"Centrum Zuid 3033",
    "sg:city":"Houthalen",
    "sg:classifiers":[
        {
            "category":"Building & Trades",
            "subcategory":"Electrical",
            "type":"Services"
        }
    ],
    "sg:phone":"+32 11 51 01 90",
    "sg:postcode":"3530",
    "sg:province":"Limburg",
    "sg:tags":[
        "repair",
        "installation"
    ],
    "wof:name":"Elektro Gijbels B.v.b.a.",
    "wof:placetype":"venue"
},
  "geometry": {"coordinates":[5.3613052368,51.0166015625],"type":"Point"}
}