{
  "type": "Feature",
  "properties": {
    "iso:country":"BE",
    "sg:address":"Rue Du Cur\u00c9 7",
    "sg:city":"Philippeville",
    "sg:orig_category":"Apotheken",
    "sg:phone":"+32 71 66 63 54",
    "sg:postcode":"5600",
    "sg:province":"Namur",
    "wof:name":"Leon Scailteur",
    "wof:placetype":"venue"
},
  "geometry": {"coordinates":[4.6099991798,50.1895713806],"type":"Point"}
}