{
  "type": "Feature",
  "properties": {
    "iso:country":"BE",
    "sg:address":"Avenue Des Combattants 169",
    "sg:city":"Court-saint-etienne",
    "sg:classifiers":[
        {
            "category":"Health Services",
            "subcategory":"Nursing And Care Facility",
            "type":"Services"
        }
    ],
    "sg:phone":"+32 10 61 27 29",
    "sg:postcode":"1490",
    "sg:province":"Brabant Wallon",
    "sg:tags":[
        "home",
        "rest"
    ],
    "wof:name":"Chantebrise",
    "wof:placetype":"venue"
},
  "geometry": {"coordinates":[4.5587849617,50.6430053711],"type":"Point"}
}