{
  "type": "Feature",
  "properties": {
    "addr:full":"Ambiorixsq 21 Bruxelles Bruxelles-Capitale 1000",
    "addr:housenumber":"21",
    "addr:postcode":"1000",
    "addr:street":"Ambiorixsq",
    "iso:country":"BE",
    "sg:address":"Ambiorixsq 21",
    "sg:city":"Bruxelles",
    "sg:classifiers":[
        {
            "category":"Banks & Credit Unions",
            "subcategory":"Bank",
            "type":"Services"
        }
    ],
    "sg:phone":"+32 2 736 79 57",
    "sg:postcode":"1000",
    "sg:province":"Bruxelles-Capitale",
    "wof:name":"G\u00e9n\u00e9rale De Banque Sa",
    "wof:placetype":"venue"
},
  "geometry": {"coordinates":[4.3848009109,50.8473243713],"type":"Point"}
}