{
  "type": "Feature",
  "properties": {
    "addr:full":"Koning Boudewijnstraat 154 Menen West-Vlaanderen 8930",
    "addr:housenumber":"154",
    "addr:postcode":"8930",
    "addr:street":"Koning Boudewijnstraat",
    "iso:country":"BE",
    "sg:address":"Koning Boudewijnstraat 154",
    "sg:city":"Menen",
    "sg:orig_category":"Kapsalons",
    "sg:phone":"+32 56 42 26 96",
    "sg:postcode":"8930",
    "sg:province":"West-Vlaanderen",
    "wof:name":"Coiffure Philip",
    "wof:placetype":"venue"
},
  "geometry": {"coordinates":[3.1209149361,50.7961845398],"type":"Point"}
}