{
  "type": "Feature",
  "properties": {
    "iso:country":"BE",
    "sg:address":"Ferme D'othet Les Bois 303",
    "sg:city":"Flemalle",
    "sg:orig_category":"Eleveurs de bovins",
    "sg:phone":"+32 4 275 61 74",
    "sg:postcode":"4400",
    "sg:province":"Li\u00e8ge",
    "wof:name":"Degive-streel",
    "wof:placetype":"venue"
},
  "geometry": {"coordinates":[5.4349040985,50.6041030884],"type":"Point"}
}