{
  "type": "Feature",
  "properties": {
    "addr:full":"Brusselstraat 366 Dilbeek (groot - Bijgaarden) Vlaams-Brabant 1702",
    "addr:housenumber":"366;1702",
    "addr:street":"Brusselstraat;Groot Bijgaarden Vlaams-Brabant",
    "iso:country":"BE",
    "sg:address":"Brusselstraat 366",
    "sg:city":"Dilbeek (groot - Bijgaarden)",
    "sg:classifiers":[
        {
            "category":"Shopping",
            "subcategory":"Clothing, Apparel, & Fashions",
            "type":"Retail Goods"
        }
    ],
    "sg:phone":"+32 2 466 36 99",
    "sg:postcode":"1702",
    "sg:province":"Vlaams-Brabant",
    "sg:tags":[
        "boutique"
    ],
    "wof:name":"Vivi (boetiek)",
    "wof:placetype":"venue"
},
  "geometry": {"coordinates":[4.2542028427,50.8710594177],"type":"Point"}
}