{
  "type": "Feature",
  "properties": {
    "addr:full":"Rue Des Ecoliers 62-64 Seraing Li\u00e8ge 4100",
    "addr:postcode":"62-64;4100",
    "addr:street":"Rue Des Ecoliers",
    "iso:country":"BE",
    "sg:address":"Rue Des Ecoliers 62-64",
    "sg:city":"Seraing",
    "sg:classifiers":[
        {
            "category":"Professional",
            "subcategory":"Lawyer & Legal Services",
            "type":"Services"
        }
    ],
    "sg:phone":"+32 4 337 61 37",
    "sg:postcode":"4100",
    "sg:province":"Li\u00e8ge",
    "wof:name":"Crucifix V",
    "wof:placetype":"venue"
},
  "geometry": {"coordinates":[5.5082011223,50.5972671509],"type":"Point"}
}