{
  "type": "Feature",
  "properties": {
    "addr:full":"Rue Des Gen\u00eats 6 Seraing Li\u00e8ge 4100",
    "addr:housenumber":"6",
    "addr:postcode":"4100",
    "addr:street":"Rue Des Gene\u0302Ts",
    "iso:country":"BE",
    "sg:address":"Rue Des Gen\u00eats 6",
    "sg:city":"Seraing",
    "sg:classifiers":[
        {
            "category":"Banks & Credit Unions",
            "subcategory":"Investment Brokerage",
            "type":"Services"
        }
    ],
    "sg:phone":"+32 4 337 55 81",
    "sg:postcode":"4100",
    "sg:province":"Li\u00e8ge",
    "sg:tags":[
        "auditor"
    ],
    "wof:name":"Todaro Salvadore & Cie Sprl",
    "wof:placetype":"venue"
},
  "geometry": {"coordinates":[5.5111842155,50.581413269],"type":"Point"}
}