{
  "type": "Feature",
  "properties": {
    "addr:full":"Tieltstraat 43 Wingene West-Vlaanderen 8750",
    "addr:housenumber":"43",
    "addr:postcode":"8750",
    "addr:street":"Tieltstraat",
    "iso:country":"BE",
    "sg:address":"Tieltstraat 43",
    "sg:city":"Wingene",
    "sg:classifiers":[
        {
            "category":"Real Estate",
            "subcategory":"Architect",
            "type":"Services"
        }
    ],
    "sg:phone":"+32 51 65 52 72",
    "sg:postcode":"8750",
    "sg:province":"West-Vlaanderen",
    "wof:name":"Deryckere B",
    "wof:placetype":"venue"
},
  "geometry": {"coordinates":[3.2830529213,51.0567131042],"type":"Point"}
}