{
  "type": "Feature",
  "properties": {
    "addr:full":"Frankrijklei 104a Antwerpen Antwerpen 2000",
    "addr:housenumber":"104a",
    "addr:postcode":"2000",
    "addr:street":"Frankrijklei",
    "iso:country":"BE",
    "sg:address":"Frankrijklei 104a",
    "sg:city":"Antwerpen",
    "sg:classifiers":[
        {
            "category":"Wholesale",
            "subcategory":"Office Equipment",
            "type":"Manufacturing & Wholesale Goods"
        }
    ],
    "sg:phone":"+32 3 232 91 27",
    "sg:postcode":"2000",
    "sg:province":"Antwerpen",
    "sg:tags":[
        "manager's"
    ],
    "wof:name":"Tds Acior Nv",
    "wof:placetype":"venue"
},
  "geometry": {"coordinates":[4.4124531746,51.2149810791],"type":"Point"}
}