{
  "type": "Feature",
  "properties": {
    "iso:country":"BE",
    "sg:address":"Turnhoutsebaan 168a",
    "sg:city":"Mol",
    "sg:classifiers":[
        {
            "category":"Autos & Motor Vehicles",
            "subcategory":"Automobile Sales",
            "type":"Retail Goods"
        }
    ],
    "sg:phone":"+32 14 31 30 29",
    "sg:postcode":"2400",
    "sg:province":"Antwerpen",
    "sg:tags":[
        "motorhomes",
        "accessory"
    ],
    "wof:name":"Auto Quick Bvba",
    "wof:placetype":"venue"
},
  "geometry": {"coordinates":[5.1153898239,51.1961212158],"type":"Point"}
}