{
  "type": "Feature",
  "properties": {
    "addr:full":"Rue Du Ch\u00c2teau-le-duc 56 Bouillon Luxembourg 6833",
    "addr:housenumber":"56",
    "addr:postcode":"6833",
    "addr:street":"Rue Du Cha\u0302Teau-Le-Duc",
    "iso:country":"BE",
    "sg:address":"Rue Du Ch\u00c2teau-le-duc 56",
    "sg:city":"Bouillon",
    "sg:orig_category":"Woningbouw",
    "sg:phone":"+32 61 46 73 43",
    "sg:postcode":"6833",
    "sg:province":"Luxembourg",
    "wof:name":"Francis Poncin",
    "wof:placetype":"venue"
},
  "geometry": {"coordinates":[5.0365228653,49.865940094],"type":"Point"}
}