{
  "type": "Feature",
  "properties": {
    "addr:full":"Kruisboogsquare 6 Watermaal-bosvoorde/watermael-boitsfort Bruxelles-Capitale 1170",
    "addr:housenumber":"6",
    "addr:postcode":"1170",
    "addr:street":"Kruisboogsquare",
    "iso:country":"BE",
    "sg:address":"Kruisboogsquare 6",
    "sg:city":"Watermaal-bosvoorde/watermael-boitsfort",
    "sg:orig_category":"Diverse zakelijke dienstverlening Reclamebureaus",
    "sg:phone":"+32 2 673 81 86",
    "sg:postcode":"1170",
    "sg:province":"Bruxelles-Capitale",
    "wof:name":"Eleven",
    "wof:placetype":"venue"
},
  "geometry": {"coordinates":[4.4127278328,50.8024902344],"type":"Point"}
}