{
  "type": "Feature",
  "properties": {
    "iso:country":"BE",
    "sg:address":"Vagevuurstr 25 Industriepark",
    "sg:city":"Wervik",
    "sg:classifiers":[
        {
            "category":"Food & Beverages",
            "subcategory":"Dairy",
            "type":"Retail Goods"
        }
    ],
    "sg:phone":"+32 56 31 12 45",
    "sg:postcode":"8940",
    "sg:province":"West-Vlaanderen",
    "sg:tags":[
        "product",
        "related"
    ],
    "wof:name":"Triporteur Nv",
    "wof:placetype":"venue"
},
  "geometry": {"coordinates":[3.0421171188,50.7773590088],"type":"Point"}
}