{
  "type": "Feature",
  "properties": {
    "iso:country":"BE",
    "sg:address":"Geistingen 27",
    "sg:city":"Kinrooi",
    "sg:orig_category":"Brood, gebak and snoepgoed",
    "sg:phone":"+32 89 56 48 73",
    "sg:postcode":"3640",
    "sg:province":"Limburg",
    "wof:name":"Mario Henckens",
    "wof:placetype":"venue"
},
  "geometry": {"coordinates":[5.8079137802,51.1324005127],"type":"Point"}
}