{
  "type": "Feature",
  "properties": {
    "iso:country":"BE",
    "sg:address":"Rue Des Awirs 209-211",
    "sg:city":"Fl\u00e9malle",
    "sg:classifiers":[
        {
            "category":"Health Services",
            "subcategory":"Nursing And Care Facility",
            "type":"Services"
        }
    ],
    "sg:phone":"+32 4 275 72 96",
    "sg:postcode":"4400",
    "sg:province":"Li\u00e8ge",
    "sg:tags":[
        "home",
        "rest"
    ],
    "wof:name":"La Rotonde",
    "wof:placetype":"venue"
},
  "geometry": {"coordinates":[5.3892731667,50.6146774292],"type":"Point"}
}