{
  "type": "Feature",
  "properties": {
    "addr:full":"Henri Lebbestraat 141 Waregem West-Vlaanderen 8790",
    "addr:housenumber":"141",
    "addr:postcode":"8790",
    "addr:street":"Henri Lebbestraat",
    "iso:country":"BE",
    "sg:address":"Henri Lebbestraat 141",
    "sg:city":"Waregem",
    "sg:classifiers":[
        {
            "category":"Health Services",
            "subcategory":"Dentist",
            "type":"Services"
        }
    ],
    "sg:phone":"+32 56 60 56 76",
    "sg:postcode":"8790",
    "sg:province":"West-Vlaanderen",
    "wof:name":"Verhamme Franceska",
    "wof:placetype":"venue"
},
  "geometry": {"coordinates":[3.4231290817,50.8771514893],"type":"Point"}
}