{
  "type": "Feature",
  "properties": {
    "addr:full":"Guido Gezellelaan 29 Puurs Antwerpen 2870",
    "addr:housenumber":"29",
    "addr:postcode":"2870",
    "addr:street":"Guido Gezellelaan",
    "iso:country":"BE",
    "sg:address":"Guido Gezellelaan 29",
    "sg:city":"Puurs",
    "sg:classifiers":[
        {
            "category":"Bars & Pubs",
            "type":"Food & Drink"
        }
    ],
    "sg:phone":"+32 3 755 18 02",
    "sg:postcode":"2870",
    "sg:province":"Antwerpen",
    "sg:tags":[
        "tavern"
    ],
    "wof:name":"Jules Verne",
    "wof:placetype":"venue"
},
  "geometry": {"coordinates":[4.2844161987,51.0760307312],"type":"Point"}
}