{
  "type": "Feature",
  "properties": {
    "addr:full":"Chauss\u00e9e Brunehault 58 Bernissart (blaton) Hainaut 7321",
    "addr:housenumber":"58",
    "addr:postcode":"7321",
    "addr:street":"Chausse\u0301E Brunehault",
    "iso:country":"BE",
    "sg:address":"Chauss\u00e9e Brunehault 58",
    "sg:city":"Bernissart (blaton)",
    "sg:classifiers":[
        {
            "category":"Structure",
            "subcategory":"Office Building",
            "type":"Public Place"
        }
    ],
    "sg:phone":"+32 69 57 95 38",
    "sg:postcode":"7321",
    "sg:province":"Hainaut",
    "sg:tags":[
        "drawing"
    ],
    "wof:name":"Bureau Service Dessins",
    "wof:placetype":"venue"
},
  "geometry": {"coordinates":[3.6972351074,50.4765625],"type":"Point"}
}