{
  "type": "Feature",
  "properties": {
    "addr:full":"Avenue Monseigneur 38 Rixensart Brabant Wallon 1330",
    "addr:housenumber":"38",
    "addr:postcode":"1330",
    "addr:street":"Avenue Monseigneur;Wallon",
    "iso:country":"BE",
    "sg:address":"Avenue Monseigneur 38",
    "sg:city":"Rixensart",
    "sg:classifiers":[
        {
            "category":"Professional",
            "subcategory":"Secretarial Services",
            "type":"Services"
        }
    ],
    "sg:phone":"+32 2 653 52 10",
    "sg:postcode":"1330",
    "sg:province":"Brabant Wallon",
    "sg:tags":[
        "-",
        "wordprocessing"
    ],
    "wof:name":"T.d.s. Service Bureau",
    "wof:placetype":"venue"
},
  "geometry": {"coordinates":[4.5257768631,50.7205200195],"type":"Point"}
}