{
  "type": "Feature",
  "properties": {
    "iso:country":"BE",
    "sg:address":"Reigerstraat 30",
    "sg:city":"Oosterzele",
    "sg:orig_category":"Installation de menuiserie en bois and plastique",
    "sg:phone":"+32 9 362 33 18",
    "sg:postcode":"9860",
    "sg:province":"Oost-Vlaanderen",
    "wof:name":"Johan Vdv",
    "wof:placetype":"venue"
},
  "geometry": {"coordinates":[3.8199110031,50.9544258118],"type":"Point"}
}