{
  "type": "Feature",
  "properties": {
    "addr:full":"Rue D'havr\u00e9 99ter Mons Hainaut 7000",
    "addr:housenumber":"99ter",
    "addr:postcode":"7000",
    "addr:street":"Rue D'Havre \u0301;Hainaut",
    "iso:country":"BE",
    "sg:address":"Rue D'havr\u00e9 99ter",
    "sg:city":"Mons",
    "sg:classifiers":[
        {
            "category":"Health Services",
            "subcategory":"Nursing And Care Facility",
            "type":"Services"
        }
    ],
    "sg:phone":"+32 65 36 41 41",
    "sg:postcode":"7000",
    "sg:province":"Hainaut",
    "sg:tags":[
        "home",
        "rest"
    ],
    "wof:name":"Seigneurie Sous Le Tilleul (la)",
    "wof:placetype":"venue"
},
  "geometry": {"coordinates":[3.9567921162,50.4539833069],"type":"Point"}
}