{
  "type": "Feature",
  "properties": {
    "iso:country":"BE",
    "sg:address":"Brakelsestw 712",
    "sg:city":"Ninove",
    "sg:orig_category":"Stortklaar beton Fab",
    "sg:phone":"+32 54 51 71 71",
    "sg:postcode":"9400",
    "sg:province":"Oost-Vlaanderen",
    "wof:name":"C.c.b",
    "wof:placetype":"venue"
},
  "geometry": {"coordinates":[4.0039701462,50.8359107971],"type":"Point"}
}