{
  "type": "Feature",
  "properties": {
    "addr:full":"Rue De Bruxelles 54 Namur Namur 5000",
    "addr:housenumber":"54",
    "addr:postcode":"5000",
    "addr:street":"Rue De Bruxelles",
    "iso:country":"BE",
    "sg:address":"Rue De Bruxelles 54",
    "sg:city":"Namur",
    "sg:classifiers":[
        {
            "category":"Real Estate",
            "subcategory":"Real Estate Services",
            "type":"Services"
        }
    ],
    "sg:phone":"+32 81 22 74 83",
    "sg:postcode":"5000",
    "sg:province":"Namur",
    "wof:name":"Grevisse",
    "wof:placetype":"venue"
},
  "geometry": {"coordinates":[4.8611102104,50.4660987854],"type":"Point"}
}