{
  "type": "Feature",
  "properties": {
    "addr:full":"Huisjes 4 Retie Antwerpen 2470",
    "addr:housenumber":"4",
    "addr:postcode":"2470",
    "addr:street":"Huisjes",
    "iso:country":"BE",
    "sg:address":"Huisjes 4",
    "sg:city":"Retie",
    "sg:classifiers":[
        {
            "category":"Farming",
            "subcategory":"Livestock Farm",
            "type":"Manufacturing & Wholesale Goods"
        }
    ],
    "sg:phone":"+32 14 67 83 27",
    "sg:postcode":"2470",
    "sg:province":"Antwerpen",
    "sg:tags":[
        "buyer"
    ],
    "wof:name":"Chanelca Bvba",
    "wof:placetype":"venue"
},
  "geometry": {"coordinates":[5.103260994,51.2936325073],"type":"Point"}
}