{
  "type": "Feature",
  "properties": {
    "iso:country":"BE",
    "sg:address":"Wijgendaalstraat 7",
    "sg:city":"Schoten",
    "sg:orig_category":"Enseignement secondaire g\u00e9n\u00e9ral. Enseignement secondaire technique and professionnel",
    "sg:phone":"+32 3 658 94 49",
    "sg:postcode":"2900",
    "sg:province":"Antwerpen",
    "wof:name":"Sint Coroula Instituut",
    "wof:placetype":"venue"
},
  "geometry": {"coordinates":[4.4965457916,51.2535362244],"type":"Point"}
}