{
  "type": "Feature",
  "properties": {
    "addr:full":"Rue Hippolyte-cornet 4b403 Li\u00c8ge Li\u00e8ge 4032",
    "addr:housenumber":"4b403",
    "addr:postcode":"4032",
    "addr:street":"Rue Hippolyte-Cornet",
    "iso:country":"BE",
    "sg:address":"Rue Hippolyte-cornet 4b403",
    "sg:city":"Li\u00c8ge",
    "sg:orig_category":"Pharmaciens",
    "sg:phone":"+32 4 365 13 21",
    "sg:postcode":"4032",
    "sg:province":"Li\u00e8ge",
    "wof:name":"J. Lemaire",
    "wof:placetype":"venue"
},
  "geometry": {"coordinates":[5.619579792,50.6117401123],"type":"Point"}
}