{
  "type": "Feature",
  "properties": {
    "iso:country":"BE",
    "sg:address":"Place Alphonse Bosch 37",
    "sg:city":"Wavre",
    "sg:classifiers":[
        {
            "category":"Professional",
            "subcategory":"Testing Lab",
            "type":"Services"
        }
    ],
    "sg:phone":"+32 10 22 22 42",
    "sg:postcode":"1300",
    "sg:province":"Brabant Wallon",
    "sg:tags":[
        "chemist"
    ],
    "wof:name":"Guilmin Sprl",
    "wof:placetype":"venue"
},
  "geometry": {"coordinates":[4.6108422279,50.7137527466],"type":"Point"}
}