{
  "type": "Feature",
  "properties": {
    "addr:full":"Steenweg Op Merchtem 50 Sint-jans-molenbeek/molenbeek- Bruxelles-Capitale 1080",
    "addr:housenumber":"50",
    "addr:postcode":"1080",
    "addr:street":"Steenweg Op Merchtem",
    "iso:country":"BE",
    "sg:address":"Steenweg Op Merchtem 50",
    "sg:city":"Sint-jans-molenbeek/molenbeek-",
    "sg:orig_category":"Cr\u00e9meries",
    "sg:phone":"+32 2 414 59 24",
    "sg:postcode":"1080",
    "sg:province":"Bruxelles-Capitale",
    "wof:name":"Chao",
    "wof:placetype":"venue"
},
  "geometry": {"coordinates":[4.3366761208,50.8571624756],"type":"Point"}
}