{
  "type": "Feature",
  "properties": {
    "addr:full":"Lindenberg 10-12 Sint-ulriks-kapelle Vlaams-Brabant 1700",
    "addr:housenumber":"10-12",
    "addr:postcode":"1700",
    "addr:street":"Lindenberg",
    "iso:country":"BE",
    "sg:address":"Lindenberg 10-12",
    "sg:city":"Sint-ulriks-kapelle",
    "sg:classifiers":[
        {
            "category":"Wholesale",
            "subcategory":"Beer",
            "type":"Manufacturing & Wholesale Goods"
        }
    ],
    "sg:phone":"+32 2 453 94 19",
    "sg:postcode":"1700",
    "sg:province":"Vlaams-Brabant",
    "wof:name":"Brouwerij Girardin",
    "wof:placetype":"venue"
},
  "geometry": {"coordinates":[4.2351341248,50.8751144409],"type":"Point"}
}