{
  "type": "Feature",
  "properties": {
    "iso:country":"BE",
    "sg:address":"Heidelbergstraat 1",
    "sg:city":"Zedelgem",
    "sg:orig_category":"Herstelling and restauratie van meubelen",
    "sg:phone":"+32 50 84 22 92",
    "sg:postcode":"8210",
    "sg:province":"West-Vlaanderen",
    "wof:name":"Antiques Market Bruges",
    "wof:placetype":"venue"
},
  "geometry": {"coordinates":[3.1458399296,51.1376457214],"type":"Point"}
}