{
  "type": "Feature",
  "properties": {
    "addr:full":"Hoogstraat 90 Willebroek Antwerpen 2830",
    "addr:housenumber":"90",
    "addr:postcode":"2830",
    "addr:street":"Hoogstraat",
    "iso:country":"BE",
    "sg:address":"Hoogstraat 90",
    "sg:city":"Willebroek",
    "sg:orig_category":"Radioproductie and uitzendingen",
    "sg:phone":"+32 3 886 36 90",
    "sg:postcode":"2830",
    "sg:province":"Antwerpen",
    "wof:name":"Radio Sint Jan",
    "wof:placetype":"venue"
},
  "geometry": {"coordinates":[4.3632268906,51.0308532715],"type":"Point"}
}