{
  "type": "Feature",
  "properties": {
    "iso:country":"BE",
    "sg:address":"Kaphaanlei 50",
    "sg:city":"Mortsel",
    "sg:classifiers":[
        {
            "category":"Professional",
            "subcategory":"Computer Services",
            "type":"Services"
        }
    ],
    "sg:phone":"+32 3 455 48 64",
    "sg:postcode":"2640",
    "sg:province":"Antwerpen",
    "sg:tags":[
        "-",
        "processing",
        "data",
        "software"
    ],
    "wof:name":"Verima Bvba",
    "wof:placetype":"venue"
},
  "geometry": {"coordinates":[4.4734082222,51.166973114],"type":"Point"}
}