{
  "type": "Feature",
  "properties": {
    "iso:country":"BE",
    "sg:address":"Berlaarbaan 240",
    "sg:city":"Sint-katelijne-waver",
    "sg:orig_category":"Producteurs de l\u00e9gumes",
    "sg:phone":"+32 15 55 17 54",
    "sg:postcode":"2861",
    "sg:province":"Antwerpen",
    "wof:name":"Jan Hendrikckx",
    "wof:placetype":"venue"
},
  "geometry": {"coordinates":[4.5488791466,51.0543174744],"type":"Point"}
}