{
  "type": "Feature",
  "properties": {
    "addr:full":"Rue Saint-martin 58 Ham-sur-heure-nalinnes (ham-sur-heure) Hainaut 6120",
    "addr:housenumber":"58",
    "addr:postcode":"6120",
    "addr:street":"Rue Saint-Martin",
    "iso:country":"BE",
    "sg:address":"Rue Saint-martin 58",
    "sg:city":"Ham-sur-heure-nalinnes (ham-sur-heure)",
    "sg:classifiers":[
        {
            "category":"Health Services",
            "subcategory":"Medical Lab",
            "type":"Services"
        }
    ],
    "sg:phone":"+32 71 31 75 10",
    "sg:postcode":"6120",
    "sg:province":"Hainaut",
    "sg:tags":[
        "laboratory",
        "dental"
    ],
    "wof:name":"Salingros E",
    "wof:placetype":"venue"
},
  "geometry": {"coordinates":[4.3872900009,50.3219146729],"type":"Point"}
}