{
  "type": "Feature",
  "properties": {
    "addr:full":"Pacificatiestraat 39 Antwerpen Antwerpen 2000",
    "addr:housenumber":"39",
    "addr:postcode":"2000",
    "addr:street":"Pacificatiestraat",
    "iso:country":"BE",
    "sg:address":"Pacificatiestraat 39",
    "sg:city":"Antwerpen",
    "sg:classifiers":[
        {
            "category":"Banks & Credit Unions",
            "subcategory":"Investment Brokerage",
            "type":"Services"
        }
    ],
    "sg:phone":"+32 3 238 15 73",
    "sg:postcode":"2000",
    "sg:province":"Antwerpen",
    "wof:name":"Ficoma",
    "wof:placetype":"venue"
},
  "geometry": {"coordinates":[4.3892960548,51.2063179016],"type":"Point"}
}