{
  "type": "Feature",
  "properties": {
    "iso:country":"BE",
    "sg:address":"Chauss\u00c9e De Renaix 142",
    "sg:city":"Tournai",
    "sg:classifiers":[
        {
            "category":"Cafe",
            "type":"Food & Drink"
        }
    ],
    "sg:phone":"+32 69 21 13 39",
    "sg:postcode":"7500",
    "sg:province":"Hainaut",
    "sg:tags":[
        "caf\u00e9s"
    ],
    "wof:name":"Caf\u00c9 Le 24 Ao\u00dbt",
    "wof:placetype":"venue"
},
  "geometry": {"coordinates":[3.4094150066,50.6151733398],"type":"Point"}
}