{
  "type": "Feature",
  "properties": {
    "iso:country":"BE",
    "sg:address":"Rogery 20ba",
    "sg:city":"Gouvy",
    "sg:orig_category":"Installation de menuiserie en bois and plastique",
    "sg:phone":"+32 80 21 48 88",
    "sg:postcode":"6671",
    "sg:province":"Luxembourg",
    "wof:name":"Marc Foeteler",
    "wof:placetype":"venue"
},
  "geometry": {"coordinates":[5.9493122101,50.2422142029],"type":"Point"}
}