{
  "type": "Feature",
  "properties": {
    "addr:full":"Parkstraat 111 Leuven Vlaams-Brabant 3000",
    "addr:housenumber":"111",
    "addr:postcode":"3000",
    "addr:street":"Parkstraat",
    "iso:country":"BE",
    "sg:address":"Parkstraat 111",
    "sg:city":"Leuven",
    "sg:classifiers":[
        {
            "category":"Bars & Pubs",
            "type":"Food & Drink"
        }
    ],
    "sg:phone":"+32 16 20 10 46",
    "sg:postcode":"3000",
    "sg:province":"Vlaams-Brabant",
    "wof:name":"L'affaire",
    "wof:placetype":"venue"
},
  "geometry": {"coordinates":[4.7037439346,50.8722648621],"type":"Point"}
}