{
  "type": "Feature",
  "properties": {
    "iso:country":"BE",
    "sg:address":"Rue Du Centre 32",
    "sg:city":"Sprimont",
    "sg:orig_category":"Kapsalons",
    "sg:phone":"+32 4 382 18 70",
    "sg:postcode":"4140",
    "sg:province":"Li\u00e8ge",
    "wof:name":"Coiffure Dom",
    "wof:placetype":"venue"
},
  "geometry": {"coordinates":[5.6621489525,50.5040206909],"type":"Point"}
}