{
  "type": "Feature",
  "properties": {
    "addr:full":"De Pannestraat 5 Hamme (moerzeke) Oost-Vlaanderen 9220",
    "addr:housenumber":"5",
    "addr:postcode":"9220",
    "addr:street":"De Pannestraat",
    "iso:country":"BE",
    "sg:address":"De Pannestraat 5",
    "sg:city":"Hamme (moerzeke)",
    "sg:classifiers":[
        {
            "category":"Freight",
            "type":"Transportation"
        }
    ],
    "sg:phone":"+32 52 48 34 56",
    "sg:postcode":"9220",
    "sg:province":"Oost-Vlaanderen",
    "sg:tags":[
        "-",
        "transport"
    ],
    "wof:name":"Vws Bvba",
    "wof:placetype":"venue"
},
  "geometry": {"coordinates":[4.1660280228,51.0503997803],"type":"Point"}
}