{
  "type": "Feature",
  "properties": {
    "addr:full":"Zoutestraat 113 Antwerpen Antwerpen 2040",
    "addr:housenumber":"113",
    "addr:postcode":"2040",
    "addr:street":"Zoutestraat",
    "iso:country":"BE",
    "sg:address":"Zoutestraat 113",
    "sg:city":"Antwerpen",
    "sg:orig_category":"Sportclubs",
    "sg:phone":"+32 3 568 97 77",
    "sg:postcode":"2040",
    "sg:province":"Antwerpen",
    "wof:name":"T.c. Raffic Ii",
    "wof:placetype":"venue"
},
  "geometry": {"coordinates":[4.3060407639,51.3532676697],"type":"Point"}
}