{
  "type": "Feature",
  "properties": {
    "addr:full":"Avenue Edgard Tytgat 38 Bruxelles (woluwe-saint-lambert) Bruxelles-Capitale 1200",
    "addr:housenumber":"38",
    "addr:postcode":"1200",
    "addr:street":"Avenue Edgard Tytgat",
    "iso:country":"BE",
    "sg:address":"Avenue Edgard Tytgat 38",
    "sg:city":"Bruxelles (woluwe-saint-lambert)",
    "sg:classifiers":[
        {
            "category":"Professional",
            "subcategory":"Testing Lab",
            "type":"Services"
        }
    ],
    "sg:phone":"+32 2 771 24 21",
    "sg:postcode":"1200",
    "sg:province":"Bruxelles-Capitale",
    "sg:tags":[
        "chemist"
    ],
    "wof:name":"Noynaert C",
    "wof:placetype":"venue"
},
  "geometry": {"coordinates":[4.4221959114,50.8391838074],"type":"Point"}
}