{
  "type": "Feature",
  "properties": {
    "addr:full":"Rue De Saint-donat 7 Mettet Namur 5640",
    "addr:housenumber":"7",
    "addr:postcode":"5640",
    "addr:street":"Rue De Saint-Donat",
    "iso:country":"BE",
    "sg:address":"Rue De Saint-donat 7",
    "sg:city":"Mettet",
    "sg:classifiers":[
        {
            "category":"Retail",
            "subcategory":"Auto Repair",
            "type":"Services"
        }
    ],
    "sg:phone":"+32 71 72 77 03",
    "sg:postcode":"5640",
    "sg:province":"Namur",
    "sg:tags":[
        "automobile-body"
    ],
    "wof:name":"Pestiaux",
    "wof:placetype":"venue"
},
  "geometry": {"coordinates":[4.66664505,50.3093338013],"type":"Point"}
}