{
  "type": "Feature",
  "properties": {
    "iso:country":"BE",
    "sg:address":"Rue De Crupet 20",
    "sg:city":"Assesse (maillen)",
    "sg:classifiers":[
        {
            "category":"Professional",
            "subcategory":"Management & Consulting",
            "type":"Services"
        }
    ],
    "sg:phone":"+32 83 65 58 87",
    "sg:postcode":"5330",
    "sg:province":"Namur",
    "sg:tags":[
        "-",
        "processing",
        "data",
        "consultant"
    ],
    "wof:name":"Rossignon G",
    "wof:placetype":"venue"
},
  "geometry": {"coordinates":[4.9730539322,50.3773765564],"type":"Point"}
}