{
  "type": "Feature",
  "properties": {
    "addr:full":"Stationsstraat 81 Oostkamp West-Vlaanderen 8020",
    "addr:housenumber":"81",
    "addr:postcode":"8020",
    "addr:street":"Stationsstraat",
    "iso:country":"BE",
    "sg:address":"Stationsstraat 81",
    "sg:city":"Oostkamp",
    "sg:classifiers":[
        {
            "category":"Professional",
            "type":"Services"
        }
    ],
    "sg:phone":"+32 50 84 11 81",
    "sg:postcode":"8020",
    "sg:province":"West-Vlaanderen",
    "sg:tags":[
        "entertainer"
    ],
    "wof:name":"Futuristic Artist",
    "wof:placetype":"venue"
},
  "geometry": {"coordinates":[3.2410171032,51.1538124084],"type":"Point"}
}