{
  "type": "Feature",
  "properties": {
    "iso:country":"BE",
    "sg:address":"Rue De La Citadelle 177",
    "sg:city":"Mouscron (herseaux)",
    "sg:classifiers":[
        {
            "category":"Health Services",
            "subcategory":"Health Practitioner",
            "type":"Services"
        }
    ],
    "sg:phone":"+32 56 34 09 09",
    "sg:postcode":"7712",
    "sg:province":"Hainaut",
    "sg:tags":[
        "physiotherapist"
    ],
    "wof:name":"Provis Emmanuel",
    "wof:placetype":"venue"
},
  "geometry": {"coordinates":[3.2441730499,50.7132225037],"type":"Point"}
}