{
  "type": "Feature",
  "properties": {
    "iso:country":"BE",
    "sg:address":"Hameau De Thanville 6",
    "sg:city":"Beauraing",
    "sg:orig_category":"Rundveehouders",
    "sg:phone":"+32 82 71 17 14",
    "sg:postcode":"5574",
    "sg:province":"Namur",
    "wof:name":"Bertholet Gaston & Bruno",
    "wof:placetype":"venue"
},
  "geometry": {"coordinates":[5.013504982,50.0979156494],"type":"Point"}
}