{
  "type": "Feature",
  "properties": {
    "iso:country":"BE",
    "sg:address":"Rue Rosimbois 7ba",
    "sg:city":"Mettet",
    "sg:classifiers":[
        {
            "category":"Arena",
            "subcategory":"Sports Club",
            "type":"Entertainment"
        }
    ],
    "sg:phone":"+32 71 72 92 98",
    "sg:postcode":"5640",
    "sg:province":"Namur",
    "sg:tags":[
        "de"
    ],
    "wof:name":"Tennis Indoors Mettet",
    "wof:placetype":"venue"
},
  "geometry": {"coordinates":[4.6578397751,50.3198051453],"type":"Point"}
}