{
  "type": "Feature",
  "properties": {
    "addr:full":"Rue Du Village 4 Voeren/fourons Limburg 3790",
    "addr:housenumber":"4",
    "addr:postcode":"3790",
    "addr:street":"Rue Du Village",
    "iso:country":"BE",
    "sg:address":"Rue Du Village 4",
    "sg:city":"Voeren/fourons",
    "sg:orig_category":"RESTAURANTS: H\u00d4TELS",
    "sg:phone":"+32 4 381 10 22",
    "sg:postcode":"3790",
    "sg:province":"Limburg",
    "wof:name":"De Oude Bron",
    "wof:placetype":"venue"
},
  "geometry": {"coordinates":[5.8454608917,50.7517814636],"type":"Point"}
}