{
  "type": "Feature",
  "properties": {
    "addr:full":"Rue De Boussoit 31 La Louvi\u00e8re (maurage) Hainaut 7110",
    "addr:housenumber":"31",
    "addr:postcode":"7110",
    "addr:street":"Rue De Boussoit",
    "iso:country":"BE",
    "sg:address":"Rue De Boussoit 31",
    "sg:city":"La Louvi\u00e8re (maurage)",
    "sg:classifiers":[
        {
            "category":"Retail",
            "subcategory":"Event Space",
            "type":"Services"
        }
    ],
    "sg:phone":"+32 497 53 74 09",
    "sg:postcode":"7110",
    "sg:province":"Hainaut",
    "sg:tags":[
        "rental",
        "-",
        "hall"
    ],
    "wof:name":"El\u00e9gance (l')",
    "wof:placetype":"venue"
},
  "geometry": {"coordinates":[4.1505050659,50.4826698303],"type":"Point"}
}