{
  "type": "Feature",
  "properties": {
    "addr:full":"Avenue Charles Deli\u00e8ge 66 Binche Hainaut 7130",
    "addr:housenumber":"66",
    "addr:postcode":"7130",
    "addr:street":"Avenue Charles Delie\u0300Ge",
    "iso:country":"BE",
    "sg:address":"Avenue Charles Deli\u00e8ge 66",
    "sg:city":"Binche",
    "sg:classifiers":[
        {
            "category":"Social Services",
            "type":"Services"
        }
    ],
    "sg:phone":"+32 64 34 13 48",
    "sg:postcode":"7130",
    "sg:province":"Hainaut",
    "wof:name":"Centre De Planning Et De Consultation Conjugales & Familiales",
    "wof:placetype":"venue"
},
  "geometry": {"coordinates":[4.1664958,50.4132232666],"type":"Point"}
}