{
  "type": "Feature",
  "properties": {
    "addr:full":"Rue De La Jonction 22 Anhee Namur 5537",
    "addr:housenumber":"22",
    "addr:postcode":"5537",
    "addr:street":"Rue De La Jonction",
    "iso:country":"BE",
    "sg:address":"Rue De La Jonction 22",
    "sg:city":"Anhee",
    "sg:orig_category":"Dierenartsen",
    "sg:phone":"+32 82 61 23 50",
    "sg:postcode":"5537",
    "sg:province":"Namur",
    "wof:name":"Michel Wauthier",
    "wof:placetype":"venue"
},
  "geometry": {"coordinates":[4.8865609169,50.3050994873],"type":"Point"}
}