{
  "type": "Feature",
  "properties": {
    "addr:full":"Kloosterstraat 20b2 Neerpelt Limburg 3910",
    "addr:housenumber":"20b2",
    "addr:postcode":"3910",
    "addr:street":"Kloosterstraat",
    "iso:country":"BE",
    "sg:address":"Kloosterstraat 20b2",
    "sg:city":"Neerpelt",
    "sg:orig_category":"Banken and kredietinstellingen",
    "sg:phone":"+32 11 64 85 72",
    "sg:postcode":"3910",
    "sg:province":"Limburg",
    "wof:name":"H.sa. Spaarbank",
    "wof:placetype":"venue"
},
  "geometry": {"coordinates":[5.4335598946,51.2295951843],"type":"Point"}
}