{
  "type": "Feature",
  "properties": {
    "addr:full":"Krapstraat 124 Buggenhout Oost-Vlaanderen 9255",
    "addr:housenumber":"124",
    "addr:postcode":"9255",
    "addr:street":"Krapstraat",
    "iso:country":"BE",
    "sg:address":"Krapstraat 124",
    "sg:city":"Buggenhout",
    "sg:classifiers":[
        {
            "category":"Shopping",
            "subcategory":"Optician",
            "type":"Retail Goods"
        }
    ],
    "sg:phone":"+32 52 35 61 64",
    "sg:postcode":"9255",
    "sg:province":"Oost-Vlaanderen",
    "sg:tags":[
        "-"
    ],
    "wof:name":"Teck Optiek",
    "wof:placetype":"venue"
},
  "geometry": {"coordinates":[4.1809902191,51.0031890869],"type":"Point"}
}