{
  "type": "Feature",
  "properties": {
    "addr:full":"Rue De La Station 40 Saint-ghislain (hautrage) Hainaut 7334",
    "addr:housenumber":"40",
    "addr:postcode":"7334",
    "addr:street":"Rue De La Station",
    "iso:country":"BE",
    "sg:address":"Rue De La Station 40",
    "sg:city":"Saint-ghislain (hautrage)",
    "sg:classifiers":[
        {
            "category":"Professional",
            "subcategory":"Management & Consulting",
            "type":"Services"
        }
    ],
    "sg:phone":"+32 65 62 30 86",
    "sg:postcode":"7334",
    "sg:province":"Hainaut",
    "sg:tags":[
        "consultant"
    ],
    "wof:name":"Ppg Construct",
    "wof:placetype":"venue"
},
  "geometry": {"coordinates":[3.7730228901,50.4626922607],"type":"Point"}
}