{
  "type": "Feature",
  "properties": {
    "addr:full":"Hoogstraat 20 Oudenaarde Oost-Vlaanderen 9700",
    "addr:housenumber":"20",
    "addr:postcode":"9700",
    "addr:street":"Hoogstraat",
    "iso:country":"BE",
    "sg:address":"Hoogstraat 20",
    "sg:city":"Oudenaarde",
    "sg:classifiers":[
        {
            "category":"Education",
            "subcategory":"School",
            "type":"Public Place"
        }
    ],
    "sg:phone":"+32 55 33 46 80",
    "sg:postcode":"9700",
    "sg:province":"Oost-Vlaanderen",
    "sg:tags":[
        "secondary"
    ],
    "wof:name":"Vrij Landelijk Instituut",
    "wof:placetype":"venue"
},
  "geometry": {"coordinates":[3.6025290489,50.8446731567],"type":"Point"}
}