{
  "type": "Feature",
  "properties": {
    "iso:country":"BE",
    "sg:address":"Place Des D\u00e9port\u00e9s 4",
    "sg:city":"Rochefort (jemelle)",
    "sg:classifiers":[
        {
            "category":"Building & Trades",
            "subcategory":"Plumbing",
            "type":"Services"
        }
    ],
    "sg:phone":"+32 84 21 14 31",
    "sg:postcode":"5580",
    "sg:province":"Namur",
    "sg:tags":[
        "repair",
        "mainten",
        "-",
        "central",
        "heating"
    ],
    "wof:name":"Vuidar M",
    "wof:placetype":"venue"
},
  "geometry": {"coordinates":[5.2659201622,50.1613388062],"type":"Point"}
}