{
  "type": "Feature",
  "properties": {
    "addr:full":"Rue Emile Vandervelde 6 Charleroi Hainaut 6010",
    "addr:housenumber":"6",
    "addr:postcode":"6010",
    "addr:street":"Rue Emile Vandervelde;Hainaut",
    "iso:country":"BE",
    "sg:address":"Rue Emile Vandervelde 6",
    "sg:city":"Charleroi",
    "sg:orig_category":"Artsen and specialisten",
    "sg:phone":"+32 71 43 47 24",
    "sg:postcode":"6010",
    "sg:province":"Hainaut",
    "wof:name":"G. Cornant",
    "wof:placetype":"venue"
},
  "geometry": {"coordinates":[4.4689979553,50.3914680481],"type":"Point"}
}