{
  "type": "Feature",
  "properties": {
    "addr:full":"All\u00e9e Des Houx 58 Oupeye (herm\u00e9e) Li\u00e8ge 4680",
    "addr:housenumber":"58",
    "addr:postcode":"4680",
    "addr:street":"Alle\u0301E Des Houx",
    "iso:country":"BE",
    "sg:address":"All\u00e9e Des Houx 58",
    "sg:city":"Oupeye (herm\u00e9e)",
    "sg:classifiers":[
        {
            "category":"Health Services",
            "subcategory":"Doctor",
            "type":"Services"
        }
    ],
    "sg:phone":"+32 4 278 41 66",
    "sg:postcode":"4680",
    "sg:province":"Li\u00e8ge",
    "sg:tags":[
        "medicinephysicians",
        "surgeon"
    ],
    "wof:name":"Claus Daniel",
    "wof:placetype":"venue"
},
  "geometry": {"coordinates":[5.6444120407,50.7089729309],"type":"Point"}
}