{
  "type": "Feature",
  "properties": {
    "iso:country":"BE",
    "sg:address":"Trippengasse 8",
    "sg:city":"B\u00dctgenbach/butgenbach",
    "sg:classifiers":[
        {
            "category":"Arena",
            "subcategory":"Sports Club",
            "type":"Entertainment"
        }
    ],
    "sg:phone":"+32 80 44 55 68",
    "sg:postcode":"4750",
    "sg:province":"Li\u00e8ge",
    "sg:tags":[
        "de"
    ],
    "wof:name":"Skiclub Weywertz",
    "wof:placetype":"venue"
},
  "geometry": {"coordinates":[6.2206501961,50.457408905],"type":"Point"}
}