{
  "type": "Feature",
  "properties": {
    "addr:full":"Raborive 13 Theux Li\u00e8ge 4910",
    "addr:housenumber":"13",
    "addr:postcode":"4910",
    "addr:street":"Raborive",
    "iso:country":"BE",
    "sg:address":"Raborive 13",
    "sg:city":"Theux",
    "sg:orig_category":"Elektrische installaties voor woningen",
    "sg:phone":"+32 87 54 29 24",
    "sg:postcode":"4910",
    "sg:province":"Li\u00e8ge",
    "wof:name":"Fe. Fransolet",
    "wof:placetype":"venue"
},
  "geometry": {"coordinates":[5.7928099632,50.5498504639],"type":"Point"}
}