{
  "type": "Feature",
  "properties": {
    "addr:full":"Passage Saint-barth\u00e9lemy Mouscron Hainaut 7700",
    "addr:postcode":"7700",
    "addr:street":"Passage",
    "iso:country":"BE",
    "sg:address":"Passage Saint-barth\u00e9lemy",
    "sg:city":"Mouscron",
    "sg:classifiers":[
        {
            "category":"Shopping",
            "subcategory":"Bicycles & Sporting Goods",
            "type":"Retail Goods"
        }
    ],
    "sg:phone":"+32 56 86 03 70",
    "sg:postcode":"7700",
    "sg:province":"Hainaut",
    "sg:tags":[
        "sport",
        "-"
    ],
    "wof:name":"Excel Shop",
    "wof:placetype":"venue"
},
  "geometry": {"coordinates":[3.2136929035,50.7446708679],"type":"Point"}
}