{
  "type": "Feature",
  "properties": {
    "addr:full":"Rembertstraat 104 Zedelgem West-Vlaanderen 8210",
    "addr:housenumber":"104",
    "addr:postcode":"8210",
    "addr:street":"Rembertstraat",
    "iso:country":"BE",
    "sg:address":"Rembertstraat 104",
    "sg:city":"Zedelgem",
    "sg:orig_category":"Eleveurs de bovins. Eleveurs and marchands de porcs",
    "sg:phone":"+32 50 27 76 01",
    "sg:postcode":"8210",
    "sg:province":"West-Vlaanderen",
    "wof:name":"Daniel Cauwels",
    "wof:placetype":"venue"
},
  "geometry": {"coordinates":[3.1458399296,51.1376457214],"type":"Point"}
}