{
  "type": "Feature",
  "properties": {
    "iso:country":"BE",
    "sg:address":"Rue Adelin Remy 9",
    "sg:city":"Floreffe",
    "sg:classifiers":[
        {
            "category":"Building & Trades",
            "subcategory":"Construction",
            "type":"Services"
        }
    ],
    "sg:phone":"+32 81 44 63 19",
    "sg:postcode":"5150",
    "sg:province":"Namur",
    "sg:tags":[
        "stucco",
        "contractor"
    ],
    "wof:name":"Maison Toussaint-mtg",
    "wof:placetype":"venue"
},
  "geometry": {"coordinates":[4.7658529282,50.4450569153],"type":"Point"}
}