{
  "type": "Feature",
  "properties": {
    "iso:country":"BE",
    "sg:address":"Lippenslaan 77",
    "sg:city":"Knokke-heist",
    "sg:classifiers":[
        {
            "category":"Fast Food",
            "type":"Food & Drink"
        }
    ],
    "sg:phone":"+32 50 62 25 59",
    "sg:postcode":"8300",
    "sg:province":"West-Vlaanderen",
    "sg:tags":[
        "\u00c0",
        "emporter",
        "restaurants"
    ],
    "wof:name":"Ritchie's Fast Food",
    "wof:placetype":"venue"
},
  "geometry": {"coordinates":[3.287676096,51.3438224792],"type":"Point"}
}