{
  "type": "Feature",
  "properties": {
    "addr:full":"Lange Lozanastraat 250 Antwerpen Antwerpen 2018",
    "addr:housenumber":"250",
    "addr:postcode":"2018",
    "addr:street":"Lange Lozanastraat",
    "iso:country":"BE",
    "sg:address":"Lange Lozanastraat 250",
    "sg:city":"Antwerpen",
    "sg:orig_category":"Banques and organismes de cr\u00e9dit",
    "sg:phone":"+32 3 238 15 80",
    "sg:postcode":"2018",
    "sg:province":"Antwerpen",
    "wof:name":"Mercator Bank",
    "wof:placetype":"venue"
},
  "geometry": {"coordinates":[4.4068131447,51.1995162964],"type":"Point"}
}