{
  "type": "Feature",
  "properties": {
    "iso:country":"BE",
    "sg:address":"Rue Du Couvent 2",
    "sg:city":"L\u00e9glise",
    "sg:classifiers":[
        {
            "category":"Food & Beverages",
            "subcategory":"Meat & Fish",
            "type":"Retail Goods"
        }
    ],
    "sg:phone":"+32 63 43 30 82",
    "sg:postcode":"6860",
    "sg:province":"Luxembourg",
    "sg:tags":[
        "-",
        "livestock"
    ],
    "wof:name":"Grange (la)",
    "wof:placetype":"venue"
},
  "geometry": {"coordinates":[5.5546889305,49.8167762756],"type":"Point"}
}