{
  "type": "Feature",
  "properties": {
    "iso:country":"BE",
    "sg:address":"Rue De La Caillouti\u00c8re 20",
    "sg:city":"Brugelette",
    "sg:orig_category":"Eleveurs de bovins",
    "sg:phone":"+32 68 45 43 62",
    "sg:postcode":"7941",
    "sg:province":"Hainaut",
    "wof:name":"Omer Van Vooren",
    "wof:placetype":"venue"
},
  "geometry": {"coordinates":[3.8342299461,50.6032867432],"type":"Point"}
}