{
  "type": "Feature",
  "properties": {
    "iso:country":"BE",
    "sg:address":"Rue Du Moulin 6",
    "sg:city":"Rixensart",
    "sg:orig_category":"Cr\u00e9meries",
    "sg:phone":"+32 2 653 45 56",
    "sg:postcode":"1330",
    "sg:province":"Brabant Wallon",
    "wof:name":"Guy Stouffs",
    "wof:placetype":"venue"
},
  "geometry": {"coordinates":[4.509221077,50.711315155],"type":"Point"}
}