{
  "type": "Feature",
  "properties": {
    "iso:country":"BE",
    "sg:address":"Vloedstraat 19",
    "sg:city":"Roeselare",
    "sg:classifiers":[
        {
            "category":"Professional",
            "subcategory":"Advertising",
            "type":"Services"
        }
    ],
    "sg:phone":"+32 495 32 94 38",
    "sg:postcode":"8800",
    "sg:province":"West-Vlaanderen",
    "sg:tags":[
        "painter"
    ],
    "wof:name":"Publi-ba-ro",
    "wof:placetype":"venue"
},
  "geometry": {"coordinates":[3.1540699005,50.9727096558],"type":"Point"}
}