{
  "type": "Feature",
  "properties": {
    "iso:country":"BE",
    "sg:address":"Zwanenberg 48",
    "sg:city":"Kalmthout",
    "sg:orig_category":"Eleveurs and marchands de porcs",
    "sg:phone":"+32 3 666 42 92",
    "sg:postcode":"2920",
    "sg:province":"Antwerpen",
    "wof:name":"Pauwels Dirk",
    "wof:placetype":"venue"
},
  "geometry": {"coordinates":[4.479115963,51.4092597961],"type":"Point"}
}