{
  "type": "Feature",
  "properties": {
    "addr:full":"Grote Markt 7 Turnhout Antwerpen 2300",
    "addr:housenumber":"7",
    "addr:postcode":"2300",
    "addr:street":"Grote Markt",
    "iso:country":"BE",
    "sg:address":"Grote Markt 7",
    "sg:city":"Turnhout",
    "sg:classifiers":[
        {
            "category":"Restaurant",
            "type":"Food & Drink"
        }
    ],
    "sg:phone":"+32 14 42 37 87",
    "sg:postcode":"2300",
    "sg:province":"Antwerpen",
    "wof:name":"Tamboerke",
    "wof:placetype":"venue"
},
  "geometry": {"coordinates":[4.9482860565,51.3236122131],"type":"Point"}
}