{
  "type": "Feature",
  "properties": {
    "addr:full":"Langenberg 34 Hoogstraten (wortel) Antwerpen 2323",
    "addr:housenumber":"34",
    "addr:postcode":"2323",
    "addr:street":"Langenberg",
    "iso:country":"BE",
    "sg:address":"Langenberg 34",
    "sg:city":"Hoogstraten (wortel)",
    "sg:classifiers":[
        {
            "category":"Professional",
            "subcategory":"Lawyer & Legal Services",
            "type":"Services"
        }
    ],
    "sg:phone":"+32 3 314 51 67",
    "sg:postcode":"2323",
    "sg:province":"Antwerpen",
    "wof:name":"De Meester J",
    "wof:placetype":"venue"
},
  "geometry": {"coordinates":[4.7957539558,51.3966712952],"type":"Point"}
}