{
  "type": "Feature",
  "properties": {
    "addr:full":"Rijthof 19 Heusden-zolder Limburg 3550",
    "addr:housenumber":"19",
    "addr:postcode":"3550",
    "addr:street":"Rijthof",
    "iso:country":"BE",
    "sg:address":"Rijthof 19",
    "sg:city":"Heusden-zolder",
    "sg:orig_category":"Plomberie, chauffage and installations sanitaires",
    "sg:phone":"+32 11 53 71 47",
    "sg:postcode":"3550",
    "sg:province":"Limburg",
    "wof:name":"Beko",
    "wof:placetype":"venue"
},
  "geometry": {"coordinates":[5.3193368912,51.0179023743],"type":"Point"}
}