{
  "type": "Feature",
  "properties": {
    "addr:full":"Houtemsesteenweg 330 Vilvoorde Vlaams-Brabant 1800",
    "addr:housenumber":"330",
    "addr:postcode":"1800",
    "addr:street":"Houtemsesteenweg",
    "iso:country":"BE",
    "sg:address":"Houtemsesteenweg 330",
    "sg:city":"Vilvoorde",
    "sg:classifiers":[
        {
            "category":"Building & Trades",
            "subcategory":"Electrical",
            "type":"Services"
        }
    ],
    "sg:phone":"+32 475 26 89 71",
    "sg:postcode":"1800",
    "sg:province":"Vlaams-Brabant",
    "sg:tags":[
        "electric",
        "-",
        "housewiring",
        "contractor"
    ],
    "wof:name":"Techno Dmc Bvba",
    "wof:placetype":"venue"
},
  "geometry": {"coordinates":[4.4530000687,50.9348716736],"type":"Point"}
}