{
  "type": "Feature",
  "properties": {
    "iso:country":"BE",
    "sg:address":"Avenue Fonsny 72",
    "sg:city":"Sint-gillis",
    "sg:orig_category":"Woningbouw",
    "sg:phone":"+32 2 534 43 74",
    "sg:postcode":"1060",
    "sg:province":"Bruxelles-Capitale",
    "wof:name":"Portelinha",
    "wof:placetype":"venue"
},
  "geometry": {"coordinates":[4.3353381157,50.8335418701],"type":"Point"}
}