{
  "type": "Feature",
  "properties": {
    "addr:full":"Rue De Brabant 62 Bruxelles (saint-josse-ten-noode) Bruxelles-Capitale 1210",
    "addr:housenumber":"62",
    "addr:postcode":"1210",
    "addr:street":"Rue De Brabant",
    "iso:country":"BE",
    "sg:address":"Rue De Brabant 62",
    "sg:city":"Bruxelles (saint-josse-ten-noode)",
    "sg:classifiers":[
        {
            "category":"Professional",
            "subcategory":"Management & Consulting",
            "type":"Services"
        }
    ],
    "sg:phone":"+32 2 209 13 13",
    "sg:postcode":"1210",
    "sg:province":"Bruxelles-Capitale",
    "sg:tags":[
        "consultant",
        "-",
        "legislation",
        "social"
    ],
    "wof:name":"Caisse Aux. Paiement Allocations De Ch\u00f4mage (capac)",
    "wof:placetype":"venue"
},
  "geometry": {"coordinates":[4.3616981506,50.8576583862],"type":"Point"}
}