{
  "type": "Feature",
  "properties": {
    "addr:full":"Rue De La Station 65 Havelange Namur 5370",
    "addr:housenumber":"65",
    "addr:postcode":"5370",
    "addr:street":"Rue De La Station",
    "iso:country":"BE",
    "sg:address":"Rue De La Station 65",
    "sg:city":"Havelange",
    "sg:classifiers":[
        {
            "category":"Professional",
            "subcategory":"Art Services",
            "type":"Services"
        }
    ],
    "sg:phone":"+32 83 63 45 40",
    "sg:postcode":"5370",
    "sg:province":"Namur",
    "sg:tags":[
        "photographer"
    ],
    "wof:name":"Ross B",
    "wof:placetype":"venue"
},
  "geometry": {"coordinates":[5.2428817749,50.3872184753],"type":"Point"}
}