{
  "type": "Feature",
  "properties": {
    "iso:country":"BE",
    "sg:address":"Veldstraat 12",
    "sg:city":"Knesselare",
    "sg:orig_category":"Pain, p\u00e2tisseries and confiseries",
    "sg:phone":"+32 9 374 22 15",
    "sg:postcode":"9910",
    "sg:province":"Oost-Vlaanderen",
    "wof:name":"R. Verkimpe",
    "wof:placetype":"venue"
},
  "geometry": {"coordinates":[3.4137630463,51.1385154724],"type":"Point"}
}