{
  "type": "Feature",
  "properties": {
    "addr:full":"Lambertusstraat 159 Borgloon Limburg 3840",
    "addr:housenumber":"159",
    "addr:postcode":"3840",
    "addr:street":"Lambertusstraat",
    "iso:country":"BE",
    "sg:address":"Lambertusstraat 159",
    "sg:city":"Borgloon",
    "sg:orig_category":"Fruitteelt",
    "sg:phone":"+32 12 74 45 84",
    "sg:postcode":"3840",
    "sg:province":"Limburg",
    "wof:name":"Johny Warnots",
    "wof:placetype":"venue"
},
  "geometry": {"coordinates":[5.3290491104,50.7983360291],"type":"Point"}
}