{
  "type": "Feature",
  "properties": {
    "iso:country":"BE",
    "sg:address":"Avenue Ferdinand Nicolay 3",
    "sg:city":"Stavelot",
    "sg:orig_category":"Brood, gebak and snoepgoed",
    "sg:phone":"+32 80 86 22 82",
    "sg:postcode":"4970",
    "sg:province":"Li\u00e8ge",
    "wof:name":"Albert Marechal",
    "wof:placetype":"venue"
},
  "geometry": {"coordinates":[5.9305510521,50.3943061829],"type":"Point"}
}