{
  "type": "Feature",
  "properties": {
    "iso:country":"BE",
    "sg:address":"Rue Des Six Jetons 45 Box 8",
    "sg:city":"Bruxelles",
    "sg:classifiers":[
        {
            "category":"Real Estate",
            "subcategory":"Architect",
            "type":"Services"
        }
    ],
    "sg:phone":"+32 478 32 55 05",
    "sg:postcode":"1000",
    "sg:province":"Bruxelles-Capitale",
    "wof:name":"Guz P",
    "wof:placetype":"venue"
},
  "geometry": {"coordinates":[4.3446350098,50.8469734192],"type":"Point"}
}