{
  "type": "Feature",
  "properties": {
    "addr:full":"Jacques Ray\u00c9straat 33 Schaarbeek/schaerbeek Bruxelles-Capitale 1030",
    "addr:housenumber":"33",
    "addr:postcode":"1030",
    "addr:street":"Raye\u0301Straat",
    "iso:country":"BE",
    "sg:address":"Jacques Ray\u00c9straat 33",
    "sg:city":"Schaarbeek/schaerbeek",
    "sg:orig_category":"Dakwerken",
    "sg:phone":"+32 2 245 20 51",
    "sg:postcode":"1030",
    "sg:province":"Bruxelles-Capitale",
    "wof:name":"Jean Hootele",
    "wof:placetype":"venue"
},
  "geometry": {"coordinates":[4.3824458122,50.8694725037],"type":"Point"}
}