{
  "type": "Feature",
  "properties": {
    "iso:country":"BE",
    "sg:address":"Handelslei 27",
    "sg:city":"Brecht",
    "sg:orig_category":"Herenkledingzaken",
    "sg:phone":"+32 3 636 43 90",
    "sg:postcode":"2960",
    "sg:province":"Antwerpen",
    "wof:name":"Suitsdirect",
    "wof:placetype":"venue"
},
  "geometry": {"coordinates":[4.5684871674,51.3032226562],"type":"Point"}
}