{
  "type": "Feature",
  "properties": {
    "addr:full":"Steenovenstraat 64 Jabbeke (varsenare) West-Vlaanderen 8490",
    "addr:housenumber":"64",
    "addr:postcode":"8490",
    "addr:street":"Steenovenstraat",
    "iso:country":"BE",
    "sg:address":"Steenovenstraat 64",
    "sg:city":"Jabbeke (varsenare)",
    "sg:classifiers":[
        {
            "category":"Shopping",
            "subcategory":"Crafts & Fabrics",
            "type":"Retail Goods"
        }
    ],
    "sg:phone":"+32 50 38 48 60",
    "sg:postcode":"8490",
    "sg:province":"West-Vlaanderen",
    "sg:tags":[
        "plant",
        "flower",
        "artificial"
    ],
    "wof:name":"Cr\u00e9ation",
    "wof:placetype":"venue"
},
  "geometry": {"coordinates":[3.1472918987,51.1849212646],"type":"Point"}
}