{
  "type": "Feature",
  "properties": {
    "addr:full":"Avenue Hansen Soulie 8 Bruxelles (etterbeek) Bruxelles-Capitale 1040",
    "addr:housenumber":"8",
    "addr:postcode":"1040",
    "addr:street":"Avenue Hansen Soulie",
    "iso:country":"BE",
    "sg:address":"Avenue Hansen Soulie 8",
    "sg:city":"Bruxelles (etterbeek)",
    "sg:classifiers":[
        {
            "category":"Shopping",
            "subcategory":"Books",
            "type":"Retail Goods"
        }
    ],
    "sg:phone":"+32 2 735 29 39",
    "sg:postcode":"1040",
    "sg:province":"Bruxelles-Capitale",
    "sg:tags":[
        "bookseller"
    ],
    "wof:name":"Librairie Roi Chevalier Sprl",
    "wof:placetype":"venue"
},
  "geometry": {"coordinates":[4.3982620239,50.8318977356],"type":"Point"}
}