{
  "type": "Feature",
  "properties": {
    "iso:country":"BE",
    "sg:address":"Klein Heiken 75",
    "sg:city":"Kapellen (mariaburg)",
    "sg:classifiers":[
        {
            "category":"Personal",
            "subcategory":"Sauna",
            "type":"Services"
        }
    ],
    "sg:phone":"+32 3 664 15 10",
    "sg:postcode":"2950",
    "sg:province":"Antwerpen",
    "wof:name":"Koraal",
    "wof:placetype":"venue"
},
  "geometry": {"coordinates":[4.4302959442,51.302734375],"type":"Point"}
}