{
  "type": "Feature",
  "properties": {
    "iso:country":"BE",
    "sg:address":"Nervi\u00ebrslei 32",
    "sg:city":"Schoten",
    "sg:classifiers":[
        {
            "category":"Banks & Credit Unions",
            "subcategory":"Investment Brokerage",
            "type":"Services"
        }
    ],
    "sg:phone":"+32 3 270 12 00",
    "sg:postcode":"2900",
    "sg:province":"Antwerpen",
    "sg:tags":[
        "auditor"
    ],
    "wof:name":"Herrewijn G",
    "wof:placetype":"venue"
},
  "geometry": {"coordinates":[4.5264391899,51.2697639465],"type":"Point"}
}