{
  "type": "Feature",
  "properties": {
    "addr:full":"Gal.anc.h\u00d4tel Des Postes 73 Brussel/bruxelles Bruxelles-Capitale 1000",
    "addr:housenumber":"73",
    "addr:postcode":"1000",
    "addr:street":"/",
    "iso:country":"BE",
    "sg:address":"Gal.anc.h\u00d4tel Des Postes 73",
    "sg:city":"Brussel/bruxelles",
    "sg:orig_category":"Services annexes des transports terrestres",
    "sg:phone":"+32 2 217 04 67",
    "sg:postcode":"1000",
    "sg:province":"Bruxelles-Capitale",
    "wof:name":"Parking Monnaie",
    "wof:placetype":"venue"
},
  "geometry": {"coordinates":[4.3534507751,50.8516616821],"type":"Point"}
}