{
  "type": "Feature",
  "properties": {
    "addr:full":"Rue Feroobu 25 Gembloux Namur 5030",
    "addr:housenumber":"25",
    "addr:postcode":"5030",
    "addr:street":"Rue Feroobu;Namur",
    "iso:country":"BE",
    "sg:address":"Rue Feroobu 25",
    "sg:city":"Gembloux",
    "sg:orig_category":"V\u00e9t\u00e9rinaires",
    "sg:phone":"+32 81 56 65 55",
    "sg:postcode":"5030",
    "sg:province":"Namur",
    "wof:name":"Isabelle Dewez",
    "wof:placetype":"venue"
},
  "geometry": {"coordinates":[4.7532658577,50.5304603577],"type":"Point"}
}