{
  "type": "Feature",
  "properties": {
    "addr:full":"Avenue Des Foug\u00e8res 76 La Louvi\u00e8re Hainaut 7100",
    "addr:housenumber":"76",
    "addr:postcode":"7100",
    "addr:street":"Avenue Des Fouge\u0300Res",
    "iso:country":"BE",
    "sg:address":"Avenue Des Foug\u00e8res 76",
    "sg:city":"La Louvi\u00e8re",
    "sg:classifiers":[
        {
            "category":"Professional",
            "subcategory":"Accounting & Tax Preparation",
            "type":"Services"
        }
    ],
    "sg:phone":"+32 64 55 57 45",
    "sg:postcode":"7100",
    "sg:province":"Hainaut",
    "sg:tags":[
        "accountant"
    ],
    "wof:name":"Cab D'expertises Du Centre Sprl",
    "wof:placetype":"venue"
},
  "geometry": {"coordinates":[4.1892647743,50.5198249817],"type":"Point"}
}