{
  "type": "Feature",
  "properties": {
    "addr:full":"Sint-ermelindisstraat 20 Hoegaarden Vlaams-Brabant 3320",
    "addr:housenumber":"20",
    "addr:postcode":"3320",
    "addr:street":"Sint-Ermelindisstraat",
    "iso:country":"BE",
    "sg:address":"Sint-ermelindisstraat 20",
    "sg:city":"Hoegaarden",
    "sg:orig_category":"M\u00e9decins and sp\u00e9cialistes",
    "sg:phone":"+32 16 76 57 77",
    "sg:postcode":"3320",
    "sg:province":"Vlaams-Brabant",
    "wof:name":"Katty Govers",
    "wof:placetype":"venue"
},
  "geometry": {"coordinates":[4.8371148109,50.7878494263],"type":"Point"}
}