{
  "type": "Feature",
  "properties": {
    "iso:country":"BE",
    "sg:address":"Lavenderstraat 1b5",
    "sg:city":"Herzele",
    "sg:orig_category":"Architectes",
    "sg:phone":"+32 9 361 23 26",
    "sg:postcode":"9550",
    "sg:province":"Oost-Vlaanderen",
    "wof:name":"Interbouw",
    "wof:placetype":"venue"
},
  "geometry": {"coordinates":[3.860804081,50.8975830078],"type":"Point"}
}