{
  "type": "Feature",
  "properties": {
    "addr:full":"Stoopkensstraat 46 Hoegaarden (groot) Vlaams-Brabant 3320",
    "addr:housenumber":"46",
    "addr:postcode":"3320",
    "addr:street":"Stoopkensstraat;Groot Vlaams-Brabant",
    "iso:country":"BE",
    "sg:address":"Stoopkensstraat 46",
    "sg:city":"Hoegaarden (groot)",
    "sg:orig_category":"Bierproductie and Brouwerijen",
    "sg:phone":"+32 16 76 98 11",
    "sg:postcode":"3320",
    "sg:province":"Vlaams-Brabant",
    "wof:name":"Brouwerij Van Hoegaarden",
    "wof:placetype":"venue"
},
  "geometry": {"coordinates":[4.8873901367,50.7777099609],"type":"Point"}
}