{
  "type": "Feature",
  "properties": {
    "addr:full":"Kazernstraat 12 Zottegem Oost-Vlaanderen 9620",
    "addr:housenumber":"12",
    "addr:postcode":"9620",
    "addr:street":"Kazernstraat",
    "iso:country":"BE",
    "sg:address":"Kazernstraat 12",
    "sg:city":"Zottegem",
    "sg:classifiers":[
        {
            "category":"Bars & Pubs",
            "type":"Food & Drink"
        }
    ],
    "sg:phone":"+32 9 361 14 78",
    "sg:postcode":"9620",
    "sg:province":"Oost-Vlaanderen",
    "wof:name":"Cocoon",
    "wof:placetype":"venue"
},
  "geometry": {"coordinates":[3.8130090237,50.8679733276],"type":"Point"}
}