{
  "type": "Feature",
  "properties": {
    "addr:full":"Wavervelden 22 Sint-katelijne-waver Antwerpen 2861",
    "addr:housenumber":"22",
    "addr:postcode":"2861",
    "addr:street":"Wavervelden",
    "iso:country":"BE",
    "sg:address":"Wavervelden 22",
    "sg:city":"Sint-katelijne-waver",
    "sg:orig_category":"Groententeelt",
    "sg:phone":"+32 15 75 40 91",
    "sg:postcode":"2861",
    "sg:province":"Antwerpen",
    "wof:name":"Jozef Vets",
    "wof:placetype":"venue"
},
  "geometry": {"coordinates":[4.5745410919,51.0609931946],"type":"Point"}
}