{
  "type": "Feature",
  "properties": {
    "addr:full":"Groot-bijgaardenstraat 431 Sint-agatha-berchem/berchem-sainte-agathe Bruxelles-Capitale 1082",
    "addr:housenumber":"431;/",
    "addr:postcode":"1082",
    "addr:street":"Groot-Bijgaardenstraat;Sint-Agatha-Berchem",
    "iso:country":"BE",
    "sg:address":"Groot-bijgaardenstraat 431",
    "sg:city":"Sint-agatha-berchem/berchem-sainte-agathe",
    "sg:orig_category":"Kapsalons",
    "sg:phone":"+32 2 468 26 61",
    "sg:postcode":"1082",
    "sg:province":"Bruxelles-Capitale",
    "wof:name":"Coiffure Marie-lou",
    "wof:placetype":"venue"
},
  "geometry": {"coordinates":[4.2884120941,50.8627243042],"type":"Point"}
}