{
  "type": "Feature",
  "properties": {
    "iso:country":"BE",
    "sg:address":"'s Herenbaan 216",
    "sg:city":"Rumst (reet)",
    "sg:orig_category":"Non-Classified Establishments",
    "sg:phone":"+32 3 888 38 00",
    "sg:postcode":"2840",
    "sg:province":"Antwerpen",
    "wof:name":"Mobi-light Nv",
    "wof:placetype":"venue"
},
  "geometry": {"coordinates":[4.365664959,51.1060752869],"type":"Point"}
}