{
  "type": "Feature",
  "properties": {
    "iso:country":"BE",
    "sg:address":"Sint-apollonialaan 188",
    "sg:city":"Mol",
    "sg:orig_category":"Drogisterijen IJzerwaren, bouw- and verfmaterialen",
    "sg:phone":"+32 14 31 10 29",
    "sg:postcode":"2400",
    "sg:province":"Antwerpen",
    "wof:name":"Durox Paints",
    "wof:placetype":"venue"
},
  "geometry": {"coordinates":[5.1017208099,51.1917686462],"type":"Point"}
}