{
  "type": "Feature",
  "properties": {
    "addr:full":"Bellegemsestraat 107 Kortrijk West-Vlaanderen 8510",
    "addr:housenumber":"107",
    "addr:postcode":"8510",
    "addr:street":"Bellegemsestraat",
    "iso:country":"BE",
    "sg:address":"Bellegemsestraat 107",
    "sg:city":"Kortrijk",
    "sg:orig_category":"Banken and kredietinstellingen",
    "sg:phone":"+32 56 22 18 98",
    "sg:postcode":"8510",
    "sg:province":"West-Vlaanderen",
    "wof:name":"Bacob",
    "wof:placetype":"venue"
},
  "geometry": {"coordinates":[3.2881569862,50.7778244019],"type":"Point"}
}