{
  "type": "Feature",
  "properties": {
    "addr:full":"Mulkstraat 188 Tienen Vlaams-Brabant 3300",
    "addr:housenumber":"188",
    "addr:postcode":"3300",
    "addr:street":"Mulkstraat",
    "iso:country":"BE",
    "sg:address":"Mulkstraat 188",
    "sg:city":"Tienen",
    "sg:classifiers":[
        {
            "category":"Cafe",
            "type":"Food & Drink"
        }
    ],
    "sg:phone":"+32 16 81 15 34",
    "sg:postcode":"3300",
    "sg:province":"Vlaams-Brabant",
    "sg:tags":[
        "caf\u00e9s"
    ],
    "wof:name":"Caf\u00c9 Tramstatie",
    "wof:placetype":"venue"
},
  "geometry": {"coordinates":[4.9267787933,50.8008079529],"type":"Point"}
}