{
  "type": "Feature",
  "properties": {
    "iso:country":"BE",
    "sg:address":"Rue De La Plite 29",
    "sg:city":"Herbeumont",
    "sg:classifiers":[
        {
            "category":"Real Estate",
            "subcategory":"Architect",
            "type":"Services"
        }
    ],
    "sg:phone":"+32 61 41 30 85",
    "sg:postcode":"6887",
    "sg:province":"Luxembourg",
    "wof:name":"Lep\u00e8re M",
    "wof:placetype":"venue"
},
  "geometry": {"coordinates":[5.2405791283,49.7859153748],"type":"Point"}
}