{
  "type": "Feature",
  "properties": {
    "addr:full":"Avenue Louise 391 Brussel (brussel) Bruxelles-Capitale 1050",
    "addr:housenumber":"391",
    "addr:postcode":"1050",
    "addr:street":"Avenue Louise",
    "iso:country":"BE",
    "sg:address":"Avenue Louise 391",
    "sg:city":"Brussel (brussel)",
    "sg:orig_category":"Transports ferroviaires",
    "sg:phone":"+32 2 626 26 80",
    "sg:postcode":"1050",
    "sg:province":"Bruxelles-Capitale",
    "wof:name":"Comazar Limited",
    "wof:placetype":"venue"
},
  "geometry": {"coordinates":[4.3702440262,50.820148468],"type":"Point"}
}