{
  "type": "Feature",
  "properties": {
    "iso:country":"BE",
    "sg:address":"Rue De L'egalit\u00e9 35",
    "sg:city":"Ath",
    "sg:classifiers":[
        {
            "category":"Health Services",
            "subcategory":"Doctor",
            "type":"Services"
        }
    ],
    "sg:phone":"+32 68 28 10 74",
    "sg:postcode":"7800",
    "sg:province":"Hainaut",
    "sg:tags":[
        "medicinephysicians",
        "surgeon"
    ],
    "wof:name":"Bastien P",
    "wof:placetype":"venue"
},
  "geometry": {"coordinates":[3.7847900391,50.6294555664],"type":"Point"}
}