{
  "type": "Feature",
  "properties": {
    "addr:full":"Kortenbosstraat 74 Sint-truiden Limburg 3800",
    "addr:housenumber":"74",
    "addr:postcode":"3800",
    "addr:street":"Kortenbosstraat",
    "iso:country":"BE",
    "sg:address":"Kortenbosstraat 74",
    "sg:city":"Sint-truiden",
    "sg:orig_category":"Producteurs de fruits",
    "sg:phone":"+32 11 67 40 93",
    "sg:postcode":"3800",
    "sg:province":"Limburg",
    "wof:name":"Minten A. & Leclere D.",
    "wof:placetype":"venue"
},
  "geometry": {"coordinates":[5.1863641739,50.8153343201],"type":"Point"}
}