{
  "type": "Feature",
  "properties": {
    "addr:full":"Grote Peperstraat 19 Sint-niklaas Oost-Vlaanderen 9100",
    "addr:housenumber":"19",
    "addr:postcode":"9100",
    "addr:street":"Peperstraat",
    "iso:country":"BE",
    "sg:address":"Grote Peperstraat 19",
    "sg:city":"Sint-niklaas",
    "sg:classifiers":[
        {
            "category":"Retail",
            "subcategory":"Event Space",
            "type":"Services"
        }
    ],
    "sg:phone":"+32 3 776 15 72",
    "sg:postcode":"9100",
    "sg:province":"Oost-Vlaanderen",
    "sg:tags":[
        "rental",
        "-",
        "hall"
    ],
    "wof:name":"Orban J P",
    "wof:placetype":"venue"
},
  "geometry": {"coordinates":[4.1429591179,51.1631851196],"type":"Point"}
}