{
  "type": "Feature",
  "properties": {
    "addr:full":"Avenue De La Bruy\u00c8re 32 Sint-genesius-rode/rhode-saint-genese Vlaams-Brabant 1640",
    "addr:housenumber":"32",
    "addr:postcode":"1640",
    "addr:street":"Avenue De La Bruye\u0300Re",
    "iso:country":"BE",
    "sg:address":"Avenue De La Bruy\u00c8re 32",
    "sg:city":"Sint-genesius-rode/rhode-saint-genese",
    "sg:orig_category":"Artistes ind\u00e9pendants",
    "sg:phone":"+32 2 380 30 05",
    "sg:postcode":"1640",
    "sg:province":"Vlaams-Brabant",
    "wof:name":"Roger Van Belleghem",
    "wof:placetype":"venue"
},
  "geometry": {"coordinates":[4.3242602348,50.7281990051],"type":"Point"}
}