{
  "type": "Feature",
  "properties": {
    "iso:country":"BE",
    "sg:address":"Rue De Mortagne 44a",
    "sg:city":"P\u00e9ruwelz (baugnies)",
    "sg:classifiers":[
        {
            "category":"Retail",
            "subcategory":"Veterinary Services",
            "type":"Services"
        }
    ],
    "sg:phone":"+32 69 77 55 22",
    "sg:postcode":"7604",
    "sg:province":"Hainaut",
    "sg:tags":[
        "veterinarian"
    ],
    "wof:name":"Debailleul A",
    "wof:placetype":"venue"
},
  "geometry": {"coordinates":[3.5557479858,50.5643234253],"type":"Point"}
}