{
  "type": "Feature",
  "properties": {
    "iso:country":"BE",
    "sg:address":"Rue Loos 25",
    "sg:city":"Charleroi (jumet)",
    "sg:classifiers":[
        {
            "category":"Personal",
            "subcategory":"Beauty Salon",
            "type":"Services"
        }
    ],
    "sg:phone":"+32 71 34 52 43",
    "sg:postcode":"6040",
    "sg:province":"Hainaut",
    "sg:tags":[
        "lady",
        "-",
        "hairdressing"
    ],
    "wof:name":"Taranto A",
    "wof:placetype":"venue"
},
  "geometry": {"coordinates":[4.4201822281,50.4363250732],"type":"Point"}
}