{
  "type": "Feature",
  "properties": {
    "iso:country":"BE",
    "sg:address":"Kasteellei 89",
    "sg:city":"Wijnegem",
    "sg:orig_category":"R\u00e9cup\u00e9ration de mati\u00e8res m\u00e9talliques recyclables and d\u00e9molisseurs de voitures. Messageries. Entretie",
    "sg:phone":"+32 3 353 91 93",
    "sg:postcode":"2110",
    "sg:province":"Antwerpen",
    "wof:name":"Demoor",
    "wof:placetype":"venue"
},
  "geometry": {"coordinates":[4.5392050743,51.2241325378],"type":"Point"}
}