{
  "type": "Feature",
  "properties": {
    "iso:country":"BE",
    "sg:address":"Olmensesteenweg 22",
    "sg:city":"Ham",
    "sg:orig_category":"S\u00e9curit\u00e9 sociale",
    "sg:phone":"+32 11 34 76 59",
    "sg:postcode":"3945",
    "sg:province":"Limburg",
    "wof:name":"De Voorzorg",
    "wof:placetype":"venue"
},
  "geometry": {"coordinates":[5.1776199341,51.1046104431],"type":"Point"}
}