{
  "type": "Feature",
  "properties": {
    "iso:country":"BE",
    "sg:address":"Baekelandlaan 4",
    "sg:city":"Zedelgem",
    "sg:classifiers":[
        {
            "category":"Shopping",
            "subcategory":"Clothing, Apparel, & Fashions",
            "type":"Retail Goods"
        }
    ],
    "sg:phone":"+32 50 20 94 25",
    "sg:postcode":"8211",
    "sg:province":"West-Vlaanderen",
    "sg:tags":[
        "lingerie",
        "sous-v\u00eatements"
    ],
    "wof:name":"Huis La-nothe",
    "wof:placetype":"venue"
},
  "geometry": {"coordinates":[3.0889649391,51.1200408936],"type":"Point"}
}