{
  "type": "Feature",
  "properties": {
    "addr:full":"Gulkenrodestraat 8 Wommelgem Antwerpen 2160",
    "addr:housenumber":"8",
    "addr:postcode":"2160",
    "addr:street":"Gulkenrodestraat",
    "iso:country":"BE",
    "sg:address":"Gulkenrodestraat 8",
    "sg:city":"Wommelgem",
    "sg:orig_category":"Services pour animaux domestiques",
    "sg:phone":"+32 3 322 74 90",
    "sg:postcode":"2160",
    "sg:province":"Antwerpen",
    "wof:name":"Laika Hondenkapsalon",
    "wof:placetype":"venue"
},
  "geometry": {"coordinates":[4.5059008598,51.1930809021],"type":"Point"}
}