{
  "type": "Feature",
  "properties": {
    "iso:country":"BE",
    "sg:address":"Chauss\u00c9e De Bruxelles 600",
    "sg:city":"Waterloo",
    "sg:orig_category":"Boekhandels Krantenwinkels Rookartikelen",
    "sg:phone":"+32 2 354 40 86",
    "sg:postcode":"1410",
    "sg:province":"Brabant Wallon",
    "wof:name":"Librairie Joli-bois",
    "wof:placetype":"venue"
},
  "geometry": {"coordinates":[4.4020638466,50.6990470886],"type":"Point"}
}