{
  "type": "Feature",
  "properties": {
    "iso:country":"BE",
    "sg:address":"Place Du March\u00c9 20",
    "sg:city":"Herve",
    "sg:orig_category":"Apotheken",
    "sg:phone":"+32 87 67 41 74",
    "sg:postcode":"4651",
    "sg:province":"Li\u00e8ge",
    "wof:name":"Pharmacie Renardy",
    "wof:placetype":"venue"
},
  "geometry": {"coordinates":[5.8220601082,50.6473503113],"type":"Point"}
}