{
  "type": "Feature",
  "properties": {
    "iso:country":"BE",
    "sg:address":"Boomgaardstraat 109",
    "sg:city":"Antwerpen",
    "sg:orig_category":"Bouwmaterialen Gh",
    "sg:phone":"+32 3 239 23 25",
    "sg:postcode":"2018",
    "sg:province":"Antwerpen",
    "wof:name":"Louwers",
    "wof:placetype":"venue"
},
  "geometry": {"coordinates":[4.4243822098,51.2012481689],"type":"Point"}
}