{
  "type": "Feature",
  "properties": {
    "addr:full":"Venlosesteenweg 315 Kinrooi Limburg 3640",
    "addr:housenumber":"315",
    "addr:postcode":"3640",
    "addr:street":"Venlosesteenweg",
    "iso:country":"BE",
    "sg:address":"Venlosesteenweg 315",
    "sg:city":"Kinrooi",
    "sg:classifiers":[
        {
            "category":"Cafe",
            "type":"Food & Drink"
        }
    ],
    "sg:phone":"+32 89 56 78 05",
    "sg:postcode":"3640",
    "sg:province":"Limburg",
    "sg:tags":[
        "caf\u00e9s"
    ],
    "wof:name":"Jozef Steyvers",
    "wof:placetype":"venue"
},
  "geometry": {"coordinates":[5.8074197769,51.1413993835],"type":"Point"}
}