{
  "type": "Feature",
  "properties": {
    "addr:full":"Goormansdijk 1 Dessel Antwerpen 2480",
    "addr:housenumber":"1",
    "addr:postcode":"2480",
    "addr:street":"Goormansdijk",
    "iso:country":"BE",
    "sg:address":"Goormansdijk 1",
    "sg:city":"Dessel",
    "sg:orig_category":"Onderdelen and accessoires voor auto's",
    "sg:phone":"+32 14 37 57 57",
    "sg:postcode":"2480",
    "sg:province":"Antwerpen",
    "wof:name":"De Wuyts",
    "wof:placetype":"venue"
},
  "geometry": {"coordinates":[5.1174907684,51.2271347046],"type":"Point"}
}