{
  "type": "Feature",
  "properties": {
    "iso:country":"BE",
    "sg:address":"Technoparc De Thudinie",
    "sg:city":"Thuillies",
    "sg:classifiers":[
        {
            "category":"Bars & Pubs",
            "subcategory":"Sports Bar",
            "type":"Food & Drink"
        }
    ],
    "sg:phone":"+32 71 53 48 11",
    "sg:postcode":"6536",
    "sg:province":"Hainaut",
    "wof:name":"Nature's Best Europe Sa",
    "wof:placetype":"venue"
},
  "geometry": {"coordinates":[4.3290910721,50.2941627502],"type":"Point"}
}