{
  "type": "Feature",
  "properties": {
    "iso:country":"BE",
    "sg:address":"Zelle 4",
    "sg:city":"Herenthout",
    "sg:classifiers":[
        {
            "category":"Sports & Exercise",
            "subcategory":"Stables",
            "type":"Entertainment"
        }
    ],
    "sg:phone":"+32 14 51 13 08",
    "sg:postcode":"2270",
    "sg:province":"Antwerpen",
    "sg:tags":[
        "riding",
        "school"
    ],
    "wof:name":"Buts Gebr",
    "wof:placetype":"venue"
},
  "geometry": {"coordinates":[4.7732429504,51.1585769653],"type":"Point"}
}