{
  "type": "Feature",
  "properties": {
    "addr:full":"Rue D'acoz 44 Chatelet Hainaut 6200",
    "addr:housenumber":"44",
    "addr:postcode":"6200",
    "addr:street":"Rue D'Acoz;Hainaut",
    "iso:country":"BE",
    "sg:address":"Rue D'acoz 44",
    "sg:city":"Chatelet",
    "sg:orig_category":"Avocats and conseillers juridiques",
    "sg:phone":"+32 71 38 31 14",
    "sg:postcode":"6200",
    "sg:province":"Hainaut",
    "wof:name":"J.m. Mattelart",
    "wof:placetype":"venue"
},
  "geometry": {"coordinates":[4.5197582245,50.4025611877],"type":"Point"}
}