{
  "type": "Feature",
  "properties": {
    "iso:country":"BE",
    "sg:address":"Rue Paul Pastur 75",
    "sg:city":"Charleroi (ransart)",
    "sg:classifiers":[
        {
            "category":"Building & Trades",
            "subcategory":"Plumbing",
            "type":"Services"
        }
    ],
    "sg:postcode":"6043",
    "sg:province":"Hainaut",
    "sg:tags":[
        "contractor"
    ],
    "wof:name":"Robain (ets)",
    "wof:placetype":"venue"
},
  "geometry": {"coordinates":[4.4733419418,50.4061164856],"type":"Point"}
}