{
  "type": "Feature",
  "properties": {
    "iso:country":"BE",
    "sg:address":"Arme Duivelstraat 11",
    "sg:city":"Antwerpen",
    "sg:classifiers":[
        {
            "category":"Cafe",
            "type":"Food & Drink"
        }
    ],
    "sg:phone":"+32 3 213 01 80",
    "sg:postcode":"2000",
    "sg:province":"Antwerpen",
    "sg:tags":[
        "caf\u00e9s"
    ],
    "wof:name":"Plezier",
    "wof:placetype":"venue"
},
  "geometry": {"coordinates":[4.4080638885,51.2161140442],"type":"Point"}
}