{
  "type": "Feature",
  "properties": {
    "iso:country":"BE",
    "sg:address":"Mercatorstraat 22",
    "sg:city":"Sint-niklaas",
    "sg:orig_category":"Non-Classified Establishments",
    "sg:phone":"+32 3 776 87 98",
    "sg:postcode":"9100",
    "sg:province":"Oost-Vlaanderen",
    "wof:name":"Cotone & Lana",
    "wof:placetype":"venue"
},
  "geometry": {"coordinates":[4.1444940567,51.1704063416],"type":"Point"}
}