{
  "type": "Feature",
  "properties": {
    "iso:country":"BE",
    "sg:address":"Tolpoortstraat 74",
    "sg:city":"Deinze",
    "sg:orig_category":"Apotheken",
    "sg:phone":"+32 9 386 11 89",
    "sg:postcode":"9800",
    "sg:province":"Oost-Vlaanderen",
    "wof:name":"Apotheek Noe - Deinze",
    "wof:placetype":"venue"
},
  "geometry": {"coordinates":[3.5299999714,50.9802780151],"type":"Point"}
}