{
  "type": "Feature",
  "properties": {
    "addr:full":"Dries 48 Merchtem Vlaams-Brabant 1785",
    "addr:housenumber":"48",
    "addr:postcode":"1785",
    "addr:street":"Dries",
    "iso:country":"BE",
    "sg:address":"Dries 48",
    "sg:city":"Merchtem",
    "sg:orig_category":"Woningbouw",
    "sg:phone":"+32 52 37 40 72",
    "sg:postcode":"1785",
    "sg:province":"Vlaams-Brabant",
    "wof:name":"Roger Van Audenhove",
    "wof:placetype":"venue"
},
  "geometry": {"coordinates":[4.2106618881,50.9790802002],"type":"Point"}
}