{
  "type": "Feature",
  "properties": {
    "iso:country":"BE",
    "sg:address":"Keuvelhoekstraat 44",
    "sg:city":"Knokke-heist",
    "sg:orig_category":"Studios photographiques",
    "sg:phone":"+32 50 62 36 90",
    "sg:postcode":"8300",
    "sg:province":"West-Vlaanderen",
    "wof:name":"Lang Photographics",
    "wof:placetype":"venue"
},
  "geometry": {"coordinates":[3.2979741096,51.3399162292],"type":"Point"}
}