{
  "type": "Feature",
  "properties": {
    "addr:full":"Heuvelstraat 23 Geraardsbergen (moerbeke) Oost-Vlaanderen 9500",
    "addr:housenumber":"23",
    "addr:postcode":"9500",
    "addr:street":"Heuvelstraat",
    "iso:country":"BE",
    "sg:address":"Heuvelstraat 23",
    "sg:city":"Geraardsbergen (moerbeke)",
    "sg:classifiers":[
        {
            "category":"Professional",
            "subcategory":"Accounting & Tax Preparation",
            "type":"Services"
        }
    ],
    "sg:phone":"+32 54 41 52 92",
    "sg:postcode":"9500",
    "sg:province":"Oost-Vlaanderen",
    "sg:tags":[
        "accountant"
    ],
    "wof:name":"Decat J",
    "wof:placetype":"venue"
},
  "geometry": {"coordinates":[3.9146330357,50.7502670288],"type":"Point"}
}