{
  "type": "Feature",
  "properties": {
    "iso:country":"BE",
    "sg:address":"Predikherenlaan 96",
    "sg:city":"Lier",
    "sg:classifiers":[
        {
            "category":"Social Services",
            "type":"Services"
        }
    ],
    "sg:phone":"+32 3 488 01 37",
    "sg:postcode":"2500",
    "sg:province":"Antwerpen",
    "wof:name":"Dagcentrum De Oever Vzw Werk Van Den Bosco",
    "wof:placetype":"venue"
},
  "geometry": {"coordinates":[4.57315588,51.133430481],"type":"Point"}
}