{
  "type": "Feature",
  "properties": {
    "iso:country":"BE",
    "sg:address":"Gaverstraat 5",
    "sg:city":"Zele",
    "sg:classifiers":[
        {
            "category":"Manufacturing",
            "subcategory":"Metals",
            "type":"Manufacturing & Wholesale Goods"
        }
    ],
    "sg:phone":"+32 52 45 00 78",
    "sg:postcode":"9240",
    "sg:province":"Oost-Vlaanderen",
    "sg:tags":[
        "ironwork"
    ],
    "wof:name":"Vad-van Acker D",
    "wof:placetype":"venue"
},
  "geometry": {"coordinates":[4.0067200661,51.0684318542],"type":"Point"}
}