{
  "type": "Feature",
  "properties": {
    "addr:full":"Johannesstrasse 10 Eupen Li\u00e8ge 4701",
    "addr:housenumber":"10",
    "addr:postcode":"4701",
    "addr:street":"Johannesstrasse",
    "iso:country":"BE",
    "sg:address":"Johannesstrasse 10",
    "sg:city":"Eupen",
    "sg:orig_category":"Afvalwaterverwerking and ontstoppingsdiensten",
    "sg:phone":"+32 87 55 32 08",
    "sg:postcode":"4701",
    "sg:province":"Li\u00e8ge",
    "wof:name":"Mattar-radermacher",
    "wof:placetype":"venue"
},
  "geometry": {"coordinates":[6.0458259583,50.6344566345],"type":"Point"}
}