{
  "type": "Feature",
  "properties": {
    "iso:country":"BE",
    "sg:address":"Leieoever 200",
    "sg:city":"Deinze (astene)",
    "sg:classifiers":[
        {
            "category":"Real Estate",
            "subcategory":"Architect",
            "type":"Services"
        }
    ],
    "sg:phone":"+32 9 380 02 16",
    "sg:postcode":"9800",
    "sg:province":"Oost-Vlaanderen",
    "wof:name":"Belderbos M",
    "wof:placetype":"venue"
},
  "geometry": {"coordinates":[3.5618329048,50.9902534485],"type":"Point"}
}