{
  "type": "Feature",
  "properties": {
    "addr:full":"Stationsplein 4 Erpe-mere (burst) Oost-Vlaanderen 9420",
    "addr:housenumber":"4",
    "addr:postcode":"9420",
    "addr:street":"Stationsplein",
    "iso:country":"BE",
    "sg:address":"Stationsplein 4",
    "sg:city":"Erpe-mere (burst)",
    "sg:classifiers":[
        {
            "category":"Bars & Pubs",
            "type":"Food & Drink"
        }
    ],
    "sg:phone":"+32 53 62 65 76",
    "sg:postcode":"9420",
    "sg:province":"Oost-Vlaanderen",
    "wof:name":"Modern",
    "wof:placetype":"venue"
},
  "geometry": {"coordinates":[3.9216790199,50.907333374],"type":"Point"}
}