{
  "type": "Feature",
  "properties": {
    "addr:full":"Oude Bruggestraat 39 Wingene West-Vlaanderen 8750",
    "addr:housenumber":"39",
    "addr:postcode":"8750",
    "addr:street":"Oude Bruggestraat",
    "iso:country":"BE",
    "sg:address":"Oude Bruggestraat 39",
    "sg:city":"Wingene",
    "sg:orig_category":"Banques and organismes de cr\u00e9dit",
    "sg:phone":"+32 51 65 70 28",
    "sg:postcode":"8750",
    "sg:province":"West-Vlaanderen",
    "wof:name":"Fortis",
    "wof:placetype":"venue"
},
  "geometry": {"coordinates":[3.2757248878,51.0583496094],"type":"Point"}
}