{
  "type": "Feature",
  "properties": {
    "addr:full":"Rue Loan 280 Chimay Hainaut 6464",
    "addr:housenumber":"280",
    "addr:postcode":"6464",
    "addr:street":"Rue Loan",
    "iso:country":"BE",
    "sg:address":"Rue Loan 280",
    "sg:city":"Chimay",
    "sg:orig_category":"Eleveurs de bovins",
    "sg:phone":"+32 60 21 22 97",
    "sg:postcode":"6464",
    "sg:province":"Hainaut",
    "wof:name":"Etienne Lannoo",
    "wof:placetype":"venue"
},
  "geometry": {"coordinates":[4.3335928917,49.9972000122],"type":"Point"}
}