{
  "type": "Feature",
  "properties": {
    "iso:country":"BE",
    "sg:address":"Lomolenstraat 98",
    "sg:city":"Aalter",
    "sg:orig_category":"Banques and organismes de cr\u00e9dit",
    "sg:phone":"+32 9 371 61 18",
    "sg:postcode":"9880",
    "sg:province":"Oost-Vlaanderen",
    "wof:name":"V.d.k. Spaarbank",
    "wof:placetype":"venue"
},
  "geometry": {"coordinates":[3.4734339714,51.0437355042],"type":"Point"}
}