{
  "type": "Feature",
  "properties": {
    "addr:full":"Rue Des Carmes 28 A 32 Li\u00e8ge Li\u00e8ge 4000",
    "addr:housenumber":"28 a 32",
    "addr:postcode":"4000",
    "addr:street":"Rue Des Carmes",
    "iso:country":"BE",
    "sg:address":"Rue Des Carmes 28 A 32",
    "sg:city":"Li\u00e8ge",
    "sg:classifiers":[
        {
            "category":"Banks & Credit Unions",
            "subcategory":"Bank",
            "type":"Services"
        }
    ],
    "sg:postcode":"4000",
    "sg:province":"Li\u00e8ge",
    "wof:name":"Banque Du Cr\u00e9dit Li\u00e9geois",
    "wof:placetype":"venue"
},
  "geometry": {"coordinates":[5.541164875,50.6114616394],"type":"Point"}
}