{
  "type": "Feature",
  "properties": {
    "addr:full":"Route De Montignies 4 Soignies (neufvilles) Hainaut 7063",
    "addr:housenumber":"4",
    "addr:postcode":"7063",
    "addr:street":"Route De Montignies",
    "iso:country":"BE",
    "sg:address":"Route De Montignies 4",
    "sg:city":"Soignies (neufvilles)",
    "sg:classifiers":[
        {
            "category":"Health Services",
            "subcategory":"Health Practitioner",
            "type":"Services"
        }
    ],
    "sg:phone":"+32 67 33 12 15",
    "sg:postcode":"7063",
    "sg:province":"Hainaut",
    "sg:tags":[
        "physiotherapist"
    ],
    "wof:name":"Puche J L",
    "wof:placetype":"venue"
},
  "geometry": {"coordinates":[3.993940115,50.5837898254],"type":"Point"}
}