{
  "type": "Feature",
  "properties": {
    "iso:country":"BE",
    "sg:address":"Nieuwe Baan 149",
    "sg:city":"Sint-niklaas (belsele)",
    "sg:classifiers":[
        {
            "category":"Shopping",
            "subcategory":"Bicycles & Sporting Goods",
            "type":"Retail Goods"
        }
    ],
    "sg:phone":"+32 3 776 17 23",
    "sg:postcode":"9111",
    "sg:province":"Oost-Vlaanderen",
    "sg:tags":[
        "sport",
        "-"
    ],
    "wof:name":"'t Lammeken Sport",
    "wof:placetype":"venue"
},
  "geometry": {"coordinates":[4.116481781,51.1468315125],"type":"Point"}
}