{
  "type": "Feature",
  "properties": {
    "iso:country":"BE",
    "sg:address":"Hubert Fr\u00c8re-orbanlaan 329",
    "sg:city":"Gent",
    "sg:classifiers":[
        {
            "category":"Manufacturing",
            "subcategory":"Textiles",
            "type":"Manufacturing & Wholesale Goods"
        }
    ],
    "sg:phone":"+32 9 223 02 47",
    "sg:postcode":"9000",
    "sg:province":"Oost-Vlaanderen",
    "sg:tags":[
        "lingerie",
        "textiles",
        "sous-v\u00eatements"
    ],
    "wof:name":"Belena",
    "wof:placetype":"venue"
},
  "geometry": {"coordinates":[3.7358660698,51.0414047241],"type":"Point"}
}