{
  "type": "Feature",
  "properties": {
    "addr:full":"Drapstraat 36 Nazareth Oost-Vlaanderen 9810",
    "addr:housenumber":"36",
    "addr:postcode":"9810",
    "addr:street":"Drapstraat",
    "iso:country":"BE",
    "sg:address":"Drapstraat 36",
    "sg:city":"Nazareth",
    "sg:orig_category":"Levensverzekeringsmaatschappijen Verzekeringen vastgoed",
    "sg:phone":"+32 9 253 79 33",
    "sg:postcode":"9810",
    "sg:province":"Oost-Vlaanderen",
    "wof:name":"Sint - Donatusgilde",
    "wof:placetype":"venue"
},
  "geometry": {"coordinates":[3.6046209335,50.9590377808],"type":"Point"}
}