{
  "type": "Feature",
  "properties": {
    "addr:full":"Thonissenlaan 70 Hasselt Limburg 3500",
    "addr:housenumber":"70",
    "addr:postcode":"3500",
    "addr:street":"Thonissenlaan",
    "iso:country":"BE",
    "sg:address":"Thonissenlaan 70",
    "sg:city":"Hasselt",
    "sg:classifiers":[
        {
            "category":"Real Estate",
            "subcategory":"Real Estate Services",
            "type":"Services"
        }
    ],
    "sg:phone":"+32 11 22 24 00",
    "sg:postcode":"3500",
    "sg:province":"Limburg",
    "wof:name":"Limburgse Wooncentrale Cv",
    "wof:placetype":"venue"
},
  "geometry": {"coordinates":[5.3352432251,50.9334106445],"type":"Point"}
}