{
  "type": "Feature",
  "properties": {
    "addr:full":"Rue Aux Communes 64 Vise Li\u00e8ge 4602",
    "addr:housenumber":"64",
    "addr:postcode":"4602",
    "addr:street":"Rue Aux Communes",
    "iso:country":"BE",
    "sg:address":"Rue Aux Communes 64",
    "sg:city":"Vise",
    "sg:classifiers":[
        {
            "category":"Personal",
            "subcategory":"Beauty Salon",
            "type":"Services"
        }
    ],
    "sg:phone":"+32 4 362 82 69",
    "sg:postcode":"4602",
    "sg:province":"Li\u00e8ge",
    "sg:tags":[
        "de",
        "coiffure"
    ],
    "wof:name":"Sabiha Ozturk",
    "wof:placetype":"venue"
},
  "geometry": {"coordinates":[5.6781630516,50.6845283508],"type":"Point"}
}