{
  "type": "Feature",
  "properties": {
    "iso:country":"BE",
    "sg:address":"Molenweg 1c",
    "sg:city":"Libramont-chevigny",
    "sg:orig_category":"Agences d'exp\u00e9dition",
    "sg:phone":"+32 3 605 40 28",
    "sg:postcode":"2930",
    "sg:province":"Antwerpen",
    "wof:name":"Multi Trade Service",
    "wof:placetype":"venue"
},
  "geometry": {"coordinates":[4.4865899086,51.2875900269],"type":"Point"}
}