{
  "type": "Feature",
  "properties": {
    "addr:full":"Sprokkelstraat 21 Lanaken Limburg 3620",
    "addr:housenumber":"21",
    "addr:postcode":"3620",
    "addr:street":"Sprokkelstraat",
    "iso:country":"BE",
    "sg:address":"Sprokkelstraat 21",
    "sg:city":"Lanaken",
    "sg:classifiers":[
        {
            "category":"Sports & Exercise",
            "subcategory":"Stables",
            "type":"Entertainment"
        }
    ],
    "sg:phone":"+32 89 72 37 90",
    "sg:postcode":"3620",
    "sg:province":"Limburg",
    "sg:tags":[
        "riding",
        "school"
    ],
    "wof:name":"Van Der Stappen Pension",
    "wof:placetype":"venue"
},
  "geometry": {"coordinates":[5.650949955,50.9021072388],"type":"Point"}
}