{
  "type": "Feature",
  "properties": {
    "addr:full":"Bogaardestraat 234ba Maldegem Oost-Vlaanderen 9990",
    "addr:postcode":"9990",
    "addr:street":"Bogaardestraat;Oost-Vlaanderen",
    "iso:country":"BE",
    "sg:address":"Bogaardestraat 234ba",
    "sg:city":"Maldegem",
    "sg:orig_category":"Rundveehouders Varkenskwekers",
    "sg:phone":"+32 50 71 40 90",
    "sg:postcode":"9990",
    "sg:province":"Oost-Vlaanderen",
    "wof:name":"Paul Inghelram",
    "wof:placetype":"venue"
},
  "geometry": {"coordinates":[3.4280889034,51.1981010437],"type":"Point"}
}