{
  "type": "Feature",
  "properties": {
    "addr:full":"Rue Des Trois Entit\u00e9s 8 Thimister Li\u00e8ge 4890",
    "addr:housenumber":"8",
    "addr:postcode":"4890",
    "addr:street":"Rue Des Trois Entite\u0301S",
    "iso:country":"BE",
    "sg:address":"Rue Des Trois Entit\u00e9s 8",
    "sg:city":"Thimister",
    "sg:classifiers":[
        {
            "category":"Utilities",
            "subcategory":"Natural Gas",
            "type":"Services"
        }
    ],
    "sg:phone":"+32 53 66 28 28",
    "sg:postcode":"4890",
    "sg:province":"Li\u00e8ge",
    "sg:tags":[
        "serving",
        "tray"
    ],
    "wof:name":"Roltex Belgium Nv",
    "wof:placetype":"venue"
},
  "geometry": {"coordinates":[4.0509200096,50.9077682495],"type":"Point"}
}