{
  "type": "Feature",
  "properties": {
    "iso:country":"BE",
    "sg:address":"Ter Platen 17-19",
    "sg:city":"Gent",
    "sg:classifiers":[
        {
            "category":"Bars & Pubs",
            "type":"Food & Drink"
        }
    ],
    "sg:phone":"+32 9 224 33 92",
    "sg:postcode":"9000",
    "sg:province":"Oost-Vlaanderen",
    "wof:name":"Brouwzaele(de)",
    "wof:placetype":"venue"
},
  "geometry": {"coordinates":[3.7298710346,51.0402450562],"type":"Point"}
}