{
  "type": "Feature",
  "properties": {
    "iso:country":"BE",
    "sg:address":"Rue Du Chemin Vert 129",
    "sg:city":"Charleroi",
    "sg:orig_category":"Boucheries. Cr\u00e9meries",
    "sg:phone":"+32 71 43 32 64",
    "sg:postcode":"6001",
    "sg:province":"Hainaut",
    "wof:name":"Fa. Markopoulos D.",
    "wof:placetype":"venue"
},
  "geometry": {"coordinates":[4.4363698959,50.3886985779],"type":"Point"}
}