{
  "type": "Feature",
  "properties": {
    "iso:country":"BE",
    "sg:address":"\u00b4s Herenbaan 214",
    "sg:city":"Rumst",
    "sg:orig_category":"Architectes",
    "sg:phone":"+32 3 844 06 14",
    "sg:postcode":"2840",
    "sg:province":"Antwerpen",
    "wof:name":"Iris Delvaux",
    "wof:placetype":"venue"
},
  "geometry": {"coordinates":[4.3654499054,51.1059417725],"type":"Point"}
}