{
  "type": "Feature",
  "properties": {
    "iso:country":"BE",
    "sg:address":"Place D'anvaing 29",
    "sg:city":"Frasnes-lez-anvaing",
    "sg:orig_category":"Herstellingen and onderhoud van auto's Voertuigen",
    "sg:phone":"+32 69 86 62 55",
    "sg:postcode":"7910",
    "sg:province":"Hainaut",
    "wof:name":"Garage Remy",
    "wof:placetype":"venue"
},
  "geometry": {"coordinates":[3.553771019,50.7000999451],"type":"Point"}
}