{
  "type": "Feature",
  "properties": {
    "iso:country":"BE",
    "sg:address":"Duffelsesteenweg 90",
    "sg:city":"Kontich",
    "sg:orig_category":"Hydraulic Dumping Devices For Trucks",
    "sg:phone":"+32 3 457 35 50",
    "sg:postcode":"2550",
    "sg:province":"Antwerpen",
    "wof:name":"Humblet Hydraulics Nv",
    "wof:placetype":"venue"
},
  "geometry": {"coordinates":[4.450671196,51.1297187805],"type":"Point"}
}