{
  "type": "Feature",
  "properties": {
    "iso:country":"BE",
    "sg:address":"Kerkstraat 62",
    "sg:city":"Buggenhout",
    "sg:classifiers":[
        {
            "category":"Shopping",
            "subcategory":"Clothing, Apparel, & Fashions",
            "type":"Retail Goods"
        }
    ],
    "sg:phone":"+32 52 33 22 43",
    "sg:postcode":"9255",
    "sg:province":"Oost-Vlaanderen",
    "sg:tags":[
        "underwear",
        "lingerie",
        "-"
    ],
    "wof:name":"De Maeyer O",
    "wof:placetype":"venue"
},
  "geometry": {"coordinates":[4.2020111084,51.0151596069],"type":"Point"}
}