{
  "type": "Feature",
  "properties": {
    "addr:full":"Boulevard De La Sennette 1 Ecaussinnes Hainaut 7190",
    "addr:housenumber":"1",
    "addr:postcode":"7190",
    "addr:street":"Boulevard De La Sennette;Hainaut",
    "iso:country":"BE",
    "sg:address":"Boulevard De La Sennette 1",
    "sg:city":"Ecaussinnes",
    "sg:orig_category":"Pharmaciens",
    "sg:phone":"+32 67 44 21 20",
    "sg:postcode":"7190",
    "sg:province":"Hainaut",
    "wof:name":"Fran\u00c7oise Poulet",
    "wof:placetype":"venue"
},
  "geometry": {"coordinates":[4.1704659462,50.565071106],"type":"Point"}
}