{
  "type": "Feature",
  "properties": {
    "addr:full":"Rue Sars Longchamps 2 Box 16 La Louvi\u00e8re Hainaut 7100",
    "addr:housenumber":"2 box 16",
    "addr:postcode":"7100",
    "addr:street":"Rue Sars Longchamps",
    "iso:country":"BE",
    "sg:address":"Rue Sars Longchamps 2 Box 16",
    "sg:city":"La Louvi\u00e8re",
    "sg:classifiers":[
        {
            "category":"Real Estate",
            "subcategory":"Real Estate Services",
            "type":"Services"
        }
    ],
    "sg:phone":"+32 64 84 85 56",
    "sg:postcode":"7100",
    "sg:province":"Hainaut",
    "wof:name":"Immobilier Tebaldi Sprl",
    "wof:placetype":"venue"
},
  "geometry": {"coordinates":[4.1946439743,50.4738426208],"type":"Point"}
}