{
  "type": "Feature",
  "properties": {
    "iso:country":"BE",
    "sg:address":"Sint-denijseweg 216b",
    "sg:city":"Kortrijk",
    "sg:classifiers":[
        {
            "category":"Arena",
            "subcategory":"Sports Club",
            "type":"Entertainment"
        }
    ],
    "sg:phone":"+32 56 22 78 10",
    "sg:postcode":"8500",
    "sg:province":"West-Vlaanderen",
    "wof:name":"Petanque Club",
    "wof:placetype":"venue"
},
  "geometry": {"coordinates":[3.2750780582,50.8184661865],"type":"Point"}
}