{
  "type": "Feature",
  "properties": {
    "addr:full":"Rue Michel Servet 49b Seraing Li\u00e8ge 4100",
    "addr:housenumber":"49b",
    "addr:postcode":"4100",
    "addr:street":"Rue Michel Servet",
    "iso:country":"BE",
    "sg:address":"Rue Michel Servet 49b",
    "sg:city":"Seraing",
    "sg:classifiers":[
        {
            "category":"Retail",
            "subcategory":"Animal Services",
            "type":"Services"
        }
    ],
    "sg:phone":"+32 475 71 77 01",
    "sg:postcode":"4100",
    "sg:province":"Li\u00e8ge",
    "sg:tags":[
        "training",
        "dog"
    ],
    "wof:name":"Club Canin Du Haut-pr\u00e9",
    "wof:placetype":"venue"
},
  "geometry": {"coordinates":[5.5263690948,50.5984153748],"type":"Point"}
}