{
  "type": "Feature",
  "properties": {
    "iso:country":"BE",
    "sg:address":"Korte Meer 14",
    "sg:city":"Gent",
    "sg:orig_category":"Fournitures de bureau",
    "sg:phone":"+32 9 224 13 78",
    "sg:postcode":"9000",
    "sg:province":"Oost-Vlaanderen",
    "wof:name":"Ava-papierwaren",
    "wof:placetype":"venue"
},
  "geometry": {"coordinates":[3.7226989269,51.0516929626],"type":"Point"}
}