{
  "type": "Feature",
  "properties": {
    "addr:full":"Heilig-hartplein 8 Sint-truiden Limburg 3800",
    "addr:housenumber":"8",
    "addr:postcode":"3800",
    "addr:street":"Heilig-Hartplein",
    "iso:country":"BE",
    "sg:address":"Heilig-hartplein 8",
    "sg:city":"Sint-truiden",
    "sg:orig_category":"Brood, gebak and snoepgoed",
    "sg:phone":"+32 11 68 05 77",
    "sg:postcode":"3800",
    "sg:province":"Limburg",
    "wof:name":"Bakkerij De Suikerij",
    "wof:placetype":"venue"
},
  "geometry": {"coordinates":[5.1876292229,50.8155097961],"type":"Point"}
}