{
  "type": "Feature",
  "properties": {
    "iso:country":"BE",
    "sg:address":"Rue Des Correttes 5",
    "sg:city":"Bertrix",
    "sg:classifiers":[
        {
            "category":"Home & Garden",
            "subcategory":"Kitchen Supply",
            "type":"Retail Goods"
        }
    ],
    "sg:phone":"+32 61 41 37 79",
    "sg:postcode":"6880",
    "sg:province":"Luxembourg",
    "sg:tags":[
        "installation"
    ],
    "wof:name":"Ou-qui-bat Sprl",
    "wof:placetype":"venue"
},
  "geometry": {"coordinates":[5.2497081757,49.8684272766],"type":"Point"}
}