{
  "type": "Feature",
  "properties": {
    "iso:country":"BE",
    "sg:address":"Rue De Namur 49",
    "sg:city":"Charleroi",
    "sg:orig_category":"Elektrische installaties voor woningen",
    "sg:phone":"+32 71 34 37 53",
    "sg:postcode":"6041",
    "sg:province":"Hainaut",
    "wof:name":"Paolo Corona",
    "wof:placetype":"venue"
},
  "geometry": {"coordinates":[4.4416298866,50.4213562012],"type":"Point"}
}