{
  "type": "Feature",
  "properties": {
    "iso:country":"BE",
    "sg:address":"Leuvensestraat 63",
    "sg:city":"Aarschot (groot)",
    "sg:classifiers":[
        {
            "category":"Manufacturing",
            "subcategory":"Textiles",
            "type":"Manufacturing & Wholesale Goods"
        }
    ],
    "sg:phone":"+32 16 56 97 83",
    "sg:postcode":"3200",
    "sg:province":"Vlaams-Brabant",
    "wof:name":"Lutgarde Bonne",
    "wof:placetype":"venue"
},
  "geometry": {"coordinates":[4.8230700493,50.9806289673],"type":"Point"}
}