{
  "type": "Feature",
  "properties": {
    "iso:country":"BE",
    "sg:address":"Dries 40",
    "sg:city":"Buggenhout",
    "sg:classifiers":[
        {
            "category":"Health Services",
            "subcategory":"Doctor",
            "type":"Services"
        }
    ],
    "sg:phone":"+32 52 33 42 00",
    "sg:postcode":"9255",
    "sg:province":"Oost-Vlaanderen",
    "sg:tags":[
        "medicinephysicians",
        "surgeon"
    ],
    "wof:name":"De Brandt F",
    "wof:placetype":"venue"
},
  "geometry": {"coordinates":[4.2204041481,51.0278625488],"type":"Point"}
}