{
  "type": "Feature",
  "properties": {
    "addr:full":"Willem Van Doornyckstraat 115 Beveren (haasdonk) Oost-Vlaanderen 9120",
    "addr:housenumber":"115",
    "addr:postcode":"9120",
    "addr:street":"Willem Van Doornyckstraat",
    "iso:country":"BE",
    "sg:address":"Willem Van Doornyckstraat 115",
    "sg:city":"Beveren (haasdonk)",
    "sg:classifiers":[
        {
            "category":"Health Services",
            "subcategory":"Health Practitioner",
            "type":"Services"
        }
    ],
    "sg:phone":"+32 3 775 77 92",
    "sg:postcode":"9120",
    "sg:province":"Oost-Vlaanderen",
    "sg:tags":[
        "physiotherapist"
    ],
    "wof:name":"De Maeyer Chris",
    "wof:placetype":"venue"
},
  "geometry": {"coordinates":[4.2318592072,51.1794624329],"type":"Point"}
}