{
  "type": "Feature",
  "properties": {
    "addr:full":"Hameau Du Fourcroix 28 Tournai (blandain - Hertain) Hainaut 7522",
    "addr:housenumber":"28",
    "addr:postcode":"7522",
    "addr:street":"Hameau Du Fourcroix;Hainaut",
    "iso:country":"BE",
    "sg:address":"Hameau Du Fourcroix 28",
    "sg:city":"Tournai (blandain - Hertain)",
    "sg:classifiers":[
        {
            "category":"Professional",
            "subcategory":"Lawyer & Legal Services",
            "type":"Services"
        }
    ],
    "sg:phone":"+32 69 36 09 99",
    "sg:postcode":"7522",
    "sg:province":"Hainaut",
    "wof:name":"Dewez Nicolas",
    "wof:placetype":"venue"
},
  "geometry": {"coordinates":[3.3240020275,50.6392440796],"type":"Point"}
}