{
  "type": "Feature",
  "properties": {
    "addr:full":"Veumedreef 11 Oostkamp (waardamme) West-Vlaanderen 8020",
    "addr:housenumber":"11",
    "addr:postcode":"8020",
    "addr:street":"Veumedreef",
    "iso:country":"BE",
    "sg:address":"Veumedreef 11",
    "sg:city":"Oostkamp (waardamme)",
    "sg:orig_category":"Non-Classified Establishments",
    "sg:phone":"+32 50 27 64 56",
    "sg:postcode":"8020",
    "sg:province":"West-Vlaanderen",
    "wof:name":"Atelier V.s Textiles",
    "wof:placetype":"venue"
},
  "geometry": {"coordinates":[3.20896101,51.122341156],"type":"Point"}
}