{
  "type": "Feature",
  "properties": {
    "addr:full":"Rue Du Onze Novembre 12ba Chimay Hainaut 6460",
    "addr:housenumber":"12ba",
    "addr:postcode":"6460",
    "addr:street":"Rue Du Onze Novembre",
    "iso:country":"BE",
    "sg:address":"Rue Du Onze Novembre 12ba",
    "sg:city":"Chimay",
    "sg:orig_category":"Biens d'occasion",
    "sg:phone":"+32 60 21 30 24",
    "sg:postcode":"6460",
    "sg:province":"Hainaut",
    "wof:name":"Aux Petits Prix",
    "wof:placetype":"venue"
},
  "geometry": {"coordinates":[4.3104839325,50.0482597351],"type":"Point"}
}