{
  "type": "Feature",
  "properties": {
    "iso:country":"BE",
    "sg:address":"Quai Sainte-barbe 20",
    "sg:city":"Li\u00c8ge",
    "sg:orig_category":"Artsen and specialisten",
    "sg:phone":"+32 4 342 80 47",
    "sg:postcode":"4020",
    "sg:province":"Li\u00e8ge",
    "wof:name":"Fawaz El-hajje",
    "wof:placetype":"venue"
},
  "geometry": {"coordinates":[5.5837311745,50.6450843811],"type":"Point"}
}