{
  "type": "Feature",
  "properties": {
    "addr:full":"Boulevard De La Cambre 40 Bruxelles Bruxelles-Capitale 1000",
    "addr:housenumber":"40",
    "addr:postcode":"1000",
    "addr:street":"Boulevard De La Cambre",
    "iso:country":"BE",
    "sg:address":"Boulevard De La Cambre 40",
    "sg:city":"Bruxelles",
    "sg:classifiers":[
        {
            "category":"Health Services",
            "subcategory":"Doctor",
            "type":"Services"
        }
    ],
    "sg:phone":"+32 2 648 84 37",
    "sg:postcode":"1000",
    "sg:province":"Bruxelles-Capitale",
    "sg:tags":[
        "medicinephysicians",
        "surgeon"
    ],
    "wof:name":"Castro Peter",
    "wof:placetype":"venue"
},
  "geometry": {"coordinates":[4.3747091293,50.8159370422],"type":"Point"}
}