{
  "type": "Feature",
  "properties": {
    "iso:country":"BE",
    "sg:address":"Leopold Ii-laan 22",
    "sg:city":"Oostende",
    "sg:orig_category":"H\u00f4tels",
    "sg:phone":"+32 59 70 53 06",
    "sg:postcode":"8400",
    "sg:province":"West-Vlaanderen",
    "wof:name":"Hotel Prado",
    "wof:placetype":"venue"
},
  "geometry": {"coordinates":[2.9132330418,51.2304496765],"type":"Point"}
}