{
  "type": "Feature",
  "properties": {
    "iso:country":"BE",
    "sg:address":"Kolveniersvest 17",
    "sg:city":"Lier",
    "sg:classifiers":[
        {
            "category":"Real Estate",
            "subcategory":"Real Estate Services",
            "type":"Services"
        }
    ],
    "sg:phone":"+32 3 489 35 50",
    "sg:postcode":"2500",
    "sg:province":"Antwerpen",
    "wof:name":"Immo 4 Ever",
    "wof:placetype":"venue"
},
  "geometry": {"coordinates":[4.5669660568,51.1321792603],"type":"Point"}
}