{
  "type": "Feature",
  "properties": {
    "iso:country":"BE",
    "sg:address":"Place Des Martyrs 4bb",
    "sg:city":"Pont-a-celles",
    "sg:orig_category":"Pain, p\u00e2tisseries and confiseries",
    "sg:phone":"+32 71 84 76 81",
    "sg:postcode":"6238",
    "sg:province":"Hainaut",
    "wof:name":"P\u00c2tisserie Desclin",
    "wof:placetype":"venue"
},
  "geometry": {"coordinates":[4.3931069374,50.5095367432],"type":"Point"}
}