{
  "type": "Feature",
  "properties": {
    "addr:full":"Avenue Mar\u00c9chal Foch 945 Mons Hainaut 7012",
    "addr:housenumber":"945",
    "addr:postcode":"7012",
    "addr:street":"Avenue Mare\u0301Chal Foch;Hainaut",
    "iso:country":"BE",
    "sg:address":"Avenue Mar\u00c9chal Foch 945",
    "sg:city":"Mons",
    "sg:classifiers":[
        {
            "category":"Shopping",
            "subcategory":"Clothing, Apparel, & Fashions",
            "type":"Retail Goods"
        }
    ],
    "sg:phone":"+32 65 88 58 48",
    "sg:postcode":"7012",
    "sg:province":"Hainaut",
    "sg:tags":[
        "v\u00eatements",
        "pour",
        "dame"
    ],
    "wof:name":"Promo Fashion",
    "wof:placetype":"venue"
},
  "geometry": {"coordinates":[3.8894600868,50.4481964111],"type":"Point"}
}