{
  "type": "Feature",
  "properties": {
    "iso:country":"BE",
    "sg:address":"Avenue Albert I 18",
    "sg:city":"Huy",
    "sg:classifiers":[
        {
            "category":"Health Services",
            "subcategory":"Doctor",
            "type":"Services"
        }
    ],
    "sg:phone":"+32 85 25 52 73",
    "sg:postcode":"4500",
    "sg:province":"Li\u00e8ge",
    "sg:tags":[
        "medicinephysicians",
        "surgeon"
    ],
    "wof:name":"Dehon J",
    "wof:placetype":"venue"
},
  "geometry": {"coordinates":[5.2349591255,50.524936676],"type":"Point"}
}