{
  "type": "Feature",
  "properties": {
    "addr:full":"Rue Pionveau 5 Momignies Hainaut 6591",
    "addr:housenumber":"5",
    "addr:postcode":"6591",
    "addr:street":"Rue Pionveau;Hainaut",
    "iso:country":"BE",
    "sg:address":"Rue Pionveau 5",
    "sg:city":"Momignies",
    "sg:orig_category":"DIVERSE RECREATIEVE ACTIVITEITEN",
    "sg:phone":"+32 60 51 12 89",
    "sg:postcode":"6591",
    "sg:province":"Hainaut",
    "wof:name":"Momignies-juniors",
    "wof:placetype":"venue"
},
  "geometry": {"coordinates":[4.2032260895,50.0394706726],"type":"Point"}
}