{
  "type": "Feature",
  "properties": {
    "addr:full":"Herpelstraat 46 Zwalm (roborst) Oost-Vlaanderen 9630",
    "addr:housenumber":"46",
    "addr:postcode":"9630",
    "addr:street":"Herpelstraat;Roborst Oost-Vlaanderen",
    "iso:country":"BE",
    "sg:address":"Herpelstraat 46",
    "sg:city":"Zwalm (roborst)",
    "sg:classifiers":[
        {
            "category":"Building & Trades",
            "subcategory":"Plumbing",
            "type":"Services"
        }
    ],
    "sg:phone":"+32 55 49 71 79",
    "sg:postcode":"9630",
    "sg:province":"Oost-Vlaanderen",
    "sg:tags":[
        "pipe",
        "drain",
        "unblocking"
    ],
    "wof:name":"Buyse K",
    "wof:placetype":"venue"
},
  "geometry": {"coordinates":[3.7467739582,50.8712158203],"type":"Point"}
}