{
  "type": "Feature",
  "properties": {
    "iso:country":"BE",
    "sg:address":"Rue F\u00c9lix Dutry 33",
    "sg:city":"Beaumont",
    "sg:orig_category":"Pain, p\u00e2tisseries and confiseries",
    "sg:phone":"+32 71 58 86 48",
    "sg:postcode":"6500",
    "sg:province":"Hainaut",
    "wof:name":"Sylvie Dutry",
    "wof:placetype":"venue"
},
  "geometry": {"coordinates":[4.2369718552,50.2362594604],"type":"Point"}
}