{
  "type": "Feature",
  "properties": {
    "addr:full":"Broekelei 5 Keerbergen Vlaams-Brabant 3140",
    "addr:housenumber":"5",
    "addr:postcode":"3140",
    "addr:street":"Broekelei",
    "iso:country":"BE",
    "sg:address":"Broekelei 5",
    "sg:city":"Keerbergen",
    "sg:orig_category":"Drukkerijen and copyshops",
    "sg:phone":"+32 15 51 27 00",
    "sg:postcode":"3140",
    "sg:province":"Vlaams-Brabant",
    "wof:name":"Vanmuysen",
    "wof:placetype":"venue"
},
  "geometry": {"coordinates":[4.6281070709,51.0019493103],"type":"Point"}
}