{
  "type": "Feature",
  "properties": {
    "iso:country":"BE",
    "sg:address":"Rue Des Crayats 3",
    "sg:city":"Chimay",
    "sg:orig_category":"Boucheries",
    "sg:phone":"+32 60 21 33 58",
    "sg:postcode":"6464",
    "sg:province":"Hainaut",
    "wof:name":"Martin Staelens",
    "wof:placetype":"venue"
},
  "geometry": {"coordinates":[4.3736200333,50.0288887024],"type":"Point"}
}