{
  "type": "Feature",
  "properties": {
    "addr:full":"Spoorwegstraat 13 Nazareth (eke) Oost-Vlaanderen 9810",
    "addr:housenumber":"13",
    "addr:postcode":"9810",
    "addr:street":"Spoorwegstraat",
    "iso:country":"BE",
    "sg:address":"Spoorwegstraat 13",
    "sg:city":"Nazareth (eke)",
    "sg:classifiers":[
        {
            "category":"Banks & Credit Unions",
            "subcategory":"Investment Brokerage",
            "type":"Services"
        }
    ],
    "sg:phone":"+32 9 384 73 51",
    "sg:postcode":"9810",
    "sg:province":"Oost-Vlaanderen",
    "sg:tags":[
        "auditor"
    ],
    "wof:name":"De Lille J",
    "wof:placetype":"venue"
},
  "geometry": {"coordinates":[3.636464119,50.9457435608],"type":"Point"}
}