{
  "type": "Feature",
  "properties": {
    "addr:full":"Chemin De Thulin 54 Dour Hainaut 7370",
    "addr:housenumber":"54",
    "addr:postcode":"7370",
    "addr:street":"Chemin De Thulin;Hainaut",
    "iso:country":"BE",
    "sg:address":"Chemin De Thulin 54",
    "sg:city":"Dour",
    "sg:classifiers":[
        {
            "category":"Building & Trades",
            "subcategory":"Electrical",
            "type":"Services"
        }
    ],
    "sg:phone":"+32 65 52 92 00",
    "sg:postcode":"7370",
    "sg:province":"Hainaut",
    "sg:tags":[
        "industrial",
        "-",
        "electric",
        "contractor"
    ],
    "wof:name":"Concept Elect Sprl",
    "wof:placetype":"venue"
},
  "geometry": {"coordinates":[3.7711799145,50.4034309387],"type":"Point"}
}