{
  "type": "Feature",
  "properties": {
    "addr:full":"Ekkergemstraat 209 Gent Oost-Vlaanderen 9000",
    "addr:housenumber":"209",
    "addr:postcode":"9000",
    "addr:street":"Ekkergemstraat;Oost-Vlaanderen",
    "iso:country":"BE",
    "sg:address":"Ekkergemstraat 209",
    "sg:city":"Gent",
    "sg:classifiers":[
        {
            "category":"Government",
            "subcategory":"Police Station",
            "type":"Public Place"
        }
    ],
    "sg:phone":"+32 9 266 68 92",
    "sg:postcode":"9000",
    "sg:province":"Oost-Vlaanderen",
    "sg:tags":[
        "gendarmerie"
    ],
    "wof:name":"Federale Politie",
    "wof:placetype":"venue"
},
  "geometry": {"coordinates":[3.7043199539,51.050868988],"type":"Point"}
}