{
  "type": "Feature",
  "properties": {
    "addr:full":"Meerdegatstraat 136ba Alken Limburg 3570",
    "addr:postcode":"3570",
    "addr:street":"Meerdegatstraat",
    "iso:country":"BE",
    "sg:address":"Meerdegatstraat 136ba",
    "sg:city":"Alken",
    "sg:orig_category":"Producteurs de fruits",
    "sg:phone":"+32 11 31 27 59",
    "sg:postcode":"3570",
    "sg:province":"Limburg",
    "wof:name":"Carel Vanelderen",
    "wof:placetype":"venue"
},
  "geometry": {"coordinates":[5.3087520599,50.8877029419],"type":"Point"}
}