{
  "type": "Feature",
  "properties": {
    "iso:country":"BE",
    "sg:address":"Ravenstraat 95",
    "sg:city":"Leuven",
    "sg:classifiers":[
        {
            "category":"Personal",
            "subcategory":"Nail Salon",
            "type":"Services"
        }
    ],
    "sg:phone":"+32 16 23 46 32",
    "sg:postcode":"3000",
    "sg:province":"Vlaams-Brabant",
    "sg:tags":[
        "pedicure"
    ],
    "wof:name":"Jolly Madam's Pedicure",
    "wof:placetype":"venue"
},
  "geometry": {"coordinates":[4.7106909752,50.8796081543],"type":"Point"}
}