{
  "type": "Feature",
  "properties": {
    "addr:full":"Koning Ridderdijk 10 Middelkerke West-Vlaanderen 8434",
    "addr:housenumber":"10",
    "addr:postcode":"8434",
    "addr:street":"Koning Ridderdijk",
    "iso:country":"BE",
    "sg:address":"Koning Ridderdijk 10",
    "sg:city":"Middelkerke",
    "sg:classifiers":[
        {
            "category":"Restaurant",
            "type":"Food & Drink"
        }
    ],
    "sg:phone":"+32 59 30 13 90",
    "sg:postcode":"8434",
    "sg:province":"West-Vlaanderen",
    "wof:name":"Tearoom 't Bretoentje",
    "wof:placetype":"venue"
},
  "geometry": {"coordinates":[2.7569050789,51.1488685608],"type":"Point"}
}