{
  "type": "Feature",
  "properties": {
    "addr:full":"Luikersteenweg 588 Lommel Limburg 3920",
    "addr:housenumber":"588",
    "addr:postcode":"3920",
    "addr:street":"Luikersteenweg",
    "iso:country":"BE",
    "sg:address":"Luikersteenweg 588",
    "sg:city":"Lommel",
    "sg:classifiers":[
        {
            "category":"Home & Garden",
            "subcategory":"Home Furnishings",
            "type":"Retail Goods"
        }
    ],
    "sg:phone":"+32 11 80 18 92",
    "sg:postcode":"3920",
    "sg:province":"Limburg",
    "sg:tags":[
        "interior",
        "decoration"
    ],
    "wof:name":"Vermeulen",
    "wof:placetype":"venue"
},
  "geometry": {"coordinates":[5.3755497932,51.2355194092],"type":"Point"}
}