{
  "type": "Feature",
  "properties": {
    "iso:country":"BE",
    "sg:address":"Veldstraat 15",
    "sg:city":"Begijnendijk",
    "sg:classifiers":[
        {
            "category":"Personal",
            "subcategory":"Beauty Salon",
            "type":"Services"
        }
    ],
    "sg:phone":"+32 16 53 74 40",
    "sg:postcode":"3130",
    "sg:province":"Vlaams-Brabant",
    "wof:name":"Hilde",
    "wof:placetype":"venue"
},
  "geometry": {"coordinates":[4.7926640511,51.0226173401],"type":"Point"}
}