{
  "type": "Feature",
  "properties": {
    "iso:country":"BE",
    "sg:address":"Zomerweg 33",
    "sg:city":"Jabbeke",
    "sg:classifiers":[
        {
            "category":"Animal Shelter",
            "type":"Public Place"
        }
    ],
    "sg:phone":"+32 50 81 14 29",
    "sg:postcode":"8490",
    "sg:province":"West-Vlaanderen",
    "wof:name":"Dogotel",
    "wof:placetype":"venue"
},
  "geometry": {"coordinates":[3.0976769924,51.1727676392],"type":"Point"}
}