{
  "type": "Feature",
  "properties": {
    "addr:full":"Rue D'andrimont 70-72 Dison Li\u00e8ge 4820",
    "addr:postcode":"70-72;4820",
    "addr:street":"Rue D'Andrimont",
    "iso:country":"BE",
    "sg:address":"Rue D'andrimont 70-72",
    "sg:city":"Dison",
    "sg:classifiers":[
        {
            "category":"Bakery",
            "type":"Food & Drink"
        }
    ],
    "sg:phone":"+32 87 35 18 26",
    "sg:postcode":"4820",
    "sg:province":"Li\u00e8ge",
    "sg:tags":[
        "confectioner",
        "baker"
    ],
    "wof:name":"Briamont",
    "wof:placetype":"venue"
},
  "geometry": {"coordinates":[5.8589019775,50.6074829102],"type":"Point"}
}