{
  "type": "Feature",
  "properties": {
    "addr:full":"Vossenlaan 17 Tervuren Vlaams-Brabant 3080",
    "addr:housenumber":"17",
    "addr:postcode":"3080",
    "addr:street":"Vossenlaan",
    "iso:country":"BE",
    "sg:address":"Vossenlaan 17",
    "sg:city":"Tervuren",
    "sg:orig_category":"Persagentschappen",
    "sg:phone":"+32 2 767 28 02",
    "sg:postcode":"3080",
    "sg:province":"Vlaams-Brabant",
    "wof:name":"Michel Smets",
    "wof:placetype":"venue"
},
  "geometry": {"coordinates":[4.5133719444,50.8174133301],"type":"Point"}
}