{
  "type": "Feature",
  "properties": {
    "addr:full":"Aarschotsesteenweg 545 Leuven (wilsele) Vlaams-Brabant 3012",
    "addr:housenumber":"545",
    "addr:postcode":"3012",
    "addr:street":"Aarschotsesteenweg",
    "iso:country":"BE",
    "sg:address":"Aarschotsesteenweg 545",
    "sg:city":"Leuven (wilsele)",
    "sg:classifiers":[
        {
            "category":"Health Services",
            "subcategory":"Health Practitioner",
            "type":"Services"
        }
    ],
    "sg:phone":"+32 16 44 56 04",
    "sg:postcode":"3012",
    "sg:province":"Vlaams-Brabant",
    "sg:tags":[
        "physiotherapist"
    ],
    "wof:name":"Cuppens Greet",
    "wof:placetype":"venue"
},
  "geometry": {"coordinates":[4.7236709595,50.9290733337],"type":"Point"}
}