{
  "type": "Feature",
  "properties": {
    "addr:full":"Kluisdreef 8 Schilde Antwerpen 2970",
    "addr:housenumber":"8",
    "addr:postcode":"2970",
    "addr:street":"Kluisdreef",
    "iso:country":"BE",
    "sg:address":"Kluisdreef 8",
    "sg:city":"Schilde",
    "sg:classifiers":[
        {
            "category":"Professional",
            "subcategory":"Management & Consulting",
            "type":"Services"
        }
    ],
    "sg:phone":"+32 3 231 81 00",
    "sg:postcode":"2970",
    "sg:province":"Antwerpen",
    "sg:tags":[
        "consultant",
        "agency",
        "advertising"
    ],
    "wof:name":"Cavalli Consulting",
    "wof:placetype":"venue"
},
  "geometry": {"coordinates":[4.5649938583,51.2375984192],"type":"Point"}
}