{
  "type": "Feature",
  "properties": {
    "iso:country":"BE",
    "sg:address":"Kapellensteenweg 586",
    "sg:city":"Kalmthout",
    "sg:classifiers":[
        {
            "category":"Professional",
            "type":"Services"
        }
    ],
    "sg:phone":"+32 3 666 41 56",
    "sg:postcode":"2920",
    "sg:province":"Antwerpen",
    "sg:tags":[
        "surveyor",
        "-",
        "valuer"
    ],
    "wof:name":"Matrex Bvba",
    "wof:placetype":"venue"
},
  "geometry": {"coordinates":[4.4614930153,51.3576660156],"type":"Point"}
}