{
  "type": "Feature",
  "properties": {
    "iso:country":"BE",
    "sg:address":"Avenue Paul Pastur 21",
    "sg:city":"Charleroi",
    "sg:orig_category":"Herstellingen and onderhoud van auto's",
    "sg:phone":"+32 71 36 67 56",
    "sg:postcode":"6001",
    "sg:province":"Hainaut",
    "wof:name":"Renault",
    "wof:placetype":"venue"
},
  "geometry": {"coordinates":[4.4325790405,50.4039459229],"type":"Point"}
}