{
  "type": "Feature",
  "properties": {
    "iso:country":"BE",
    "sg:address":"Rue Du Camp 23",
    "sg:city":"Couvin",
    "sg:orig_category":"Transports routiers de marchandises",
    "sg:phone":"+32 60 31 26 33",
    "sg:postcode":"5660",
    "sg:province":"Namur",
    "wof:name":"Somme J",
    "wof:placetype":"venue"
},
  "geometry": {"coordinates":[4.5064821243,50.0749130249],"type":"Point"}
}