{
  "type": "Feature",
  "properties": {
    "addr:full":"Groenestraat 51 Kortemark West-Vlaanderen 8610",
    "addr:housenumber":"51",
    "addr:postcode":"8610",
    "addr:street":"Groenestraat",
    "iso:country":"BE",
    "sg:address":"Groenestraat 51",
    "sg:city":"Kortemark",
    "sg:classifiers":[
        {
            "category":"Personal",
            "subcategory":"Beauty Salon",
            "type":"Services"
        }
    ],
    "sg:phone":"+32 51 70 24 66",
    "sg:postcode":"8610",
    "sg:province":"West-Vlaanderen",
    "sg:tags":[
        "de",
        "coiffure"
    ],
    "wof:name":"Els Bruggeman",
    "wof:placetype":"venue"
},
  "geometry": {"coordinates":[3.0203509331,51.0032920837],"type":"Point"}
}