{
  "type": "Feature",
  "properties": {
    "iso:country":"BE",
    "sg:address":"Desselgemseweg 69",
    "sg:city":"Waregem",
    "sg:orig_category":"Activit\u00e9s d\u00b4action sociale sans h\u00e9bergement",
    "sg:phone":"+32 56 61 34 00",
    "sg:postcode":"8790",
    "sg:province":"West-Vlaanderen",
    "wof:name":"Rode Kruis Waregem",
    "wof:placetype":"venue"
},
  "geometry": {"coordinates":[3.4101090431,50.8812026978],"type":"Point"}
}