{
  "type": "Feature",
  "properties": {
    "addr:full":"Avenue Reine Astrid 38 Waremme Li\u00e8ge 4300",
    "addr:housenumber":"38",
    "addr:postcode":"4300",
    "addr:street":"Avenue Reine Astrid",
    "iso:country":"BE",
    "sg:address":"Avenue Reine Astrid 38",
    "sg:city":"Waremme",
    "sg:orig_category":"Tabac. Journaux",
    "sg:phone":"+32 19 32 52 68",
    "sg:postcode":"4300",
    "sg:province":"Li\u00e8ge",
    "wof:name":"Librairie L'epi",
    "wof:placetype":"venue"
},
  "geometry": {"coordinates":[5.2505860329,50.6951942444],"type":"Point"}
}