{
  "type": "Feature",
  "properties": {
    "addr:full":"Leuvensesteenweg 4 Vilvoorde Vlaams-Brabant 1800",
    "addr:housenumber":"4",
    "addr:postcode":"1800",
    "addr:street":"Leuvensesteenweg",
    "iso:country":"BE",
    "sg:address":"Leuvensesteenweg 4",
    "sg:city":"Vilvoorde",
    "sg:classifiers":[
        {
            "category":"Shopping",
            "subcategory":"Clothing, Apparel, & Fashions",
            "type":"Retail Goods"
        }
    ],
    "sg:phone":"+32 2 252 23 92",
    "sg:postcode":"1800",
    "sg:province":"Vlaams-Brabant",
    "sg:tags":[
        "boutique"
    ],
    "wof:name":"Pastis",
    "wof:placetype":"venue"
},
  "geometry": {"coordinates":[4.4354357719,50.9279556274],"type":"Point"}
}