{
  "type": "Feature",
  "properties": {
    "addr:full":"Hoogstraat 72 Zutendaal Limburg 3690",
    "addr:housenumber":"72",
    "addr:postcode":"3690",
    "addr:street":"Hoogstraat",
    "iso:country":"BE",
    "sg:address":"Hoogstraat 72",
    "sg:city":"Zutendaal",
    "sg:classifiers":[
        {
            "category":"Health Services",
            "subcategory":"Dentist",
            "type":"Services"
        }
    ],
    "sg:phone":"+32 89 61 16 65",
    "sg:postcode":"3690",
    "sg:province":"Limburg",
    "wof:name":"Segers P",
    "wof:placetype":"venue"
},
  "geometry": {"coordinates":[5.5662398338,50.936416626],"type":"Point"}
}