{
  "type": "Feature",
  "properties": {
    "addr:full":"Stationsstraat 19 Rotselaar Vlaams-Brabant 3110",
    "addr:housenumber":"19",
    "addr:postcode":"3110",
    "addr:street":"Stationsstraat",
    "iso:country":"BE",
    "sg:address":"Stationsstraat 19",
    "sg:city":"Rotselaar",
    "sg:orig_category":"Apotheken",
    "sg:phone":"+32 16 44 55 90",
    "sg:postcode":"3110",
    "sg:province":"Vlaams-Brabant",
    "wof:name":"Maria Hensmans",
    "wof:placetype":"venue"
},
  "geometry": {"coordinates":[4.7135081291,50.9495506287],"type":"Point"}
}