{
  "type": "Feature",
  "properties": {
    "addr:full":"Brugsesteenweg 56 Pittem West-Vlaanderen 8740",
    "addr:housenumber":"56",
    "addr:postcode":"8740",
    "addr:street":"Brugsesteenweg",
    "iso:country":"BE",
    "sg:address":"Brugsesteenweg 56",
    "sg:city":"Pittem",
    "sg:classifiers":[
        {
            "category":"Fast Food",
            "type":"Food & Drink"
        }
    ],
    "sg:phone":"+32 51 46 71 96",
    "sg:postcode":"8740",
    "sg:province":"West-Vlaanderen",
    "sg:tags":[
        "\u00c0",
        "restaurants",
        "emporter",
        "restaurant"
    ],
    "wof:name":"Berkenhof",
    "wof:placetype":"venue"
},
  "geometry": {"coordinates":[3.2393798828,50.9863929749],"type":"Point"}
}