{
  "type": "Feature",
  "properties": {
    "iso:country":"BE",
    "sg:address":"Rampe De Floribois 4",
    "sg:city":"Ottignies-louvain-la-neuve (louvain-la-neuve)",
    "sg:classifiers":[
        {
            "category":"Health Services",
            "subcategory":"Health Practitioner",
            "type":"Services"
        }
    ],
    "sg:phone":"+32 10 45 01 54",
    "sg:postcode":"1348",
    "sg:province":"Brabant Wallon",
    "sg:tags":[
        "physiotherapist"
    ],
    "wof:name":"Marion Eliane",
    "wof:placetype":"venue"
},
  "geometry": {"coordinates":[4.6154370308,50.6654396057],"type":"Point"}
}