{
  "type": "Feature",
  "properties": {
    "iso:country":"BE",
    "sg:address":"Gontrodestraat 71",
    "sg:city":"Gent",
    "sg:orig_category":"Schoonmaakbedrijven and ongediertebestrijding Woningbouw",
    "sg:phone":"+32 9 230 06 91",
    "sg:postcode":"9050",
    "sg:province":"Oost-Vlaanderen",
    "wof:name":"Van Den Meersschaut Karweidienst",
    "wof:placetype":"venue"
},
  "geometry": {"coordinates":[3.7547519207,51.0273208618],"type":"Point"}
}