{
  "type": "Feature",
  "properties": {
    "iso:country":"BE",
    "sg:address":"Rue De Liernu 38",
    "sg:city":"Meux",
    "sg:orig_category":"Loodgieterij, verwarming and sanitaire installaties",
    "sg:phone":"+32 81 56 79 46",
    "sg:postcode":"5081",
    "sg:province":"Namur",
    "wof:name":"Jacquet C\u00c9dric",
    "wof:placetype":"venue"
},
  "geometry": {"coordinates":[4.79565382,50.5569763184],"type":"Point"}
}