{
  "type": "Feature",
  "properties": {
    "iso:country":"BE",
    "sg:address":"Hinnenboomstraat 17ba",
    "sg:city":"Hoogstraten",
    "sg:orig_category":"Rundveehouders",
    "sg:phone":"+32 3 314 12 68",
    "sg:postcode":"2320",
    "sg:province":"Antwerpen",
    "wof:name":"Luyckx Marleen",
    "wof:placetype":"venue"
},
  "geometry": {"coordinates":[4.7242717743,51.410736084],"type":"Point"}
}