{
  "type": "Feature",
  "properties": {
    "iso:country":"BE",
    "sg:address":"Rue Billy 3",
    "sg:city":"Li\u00e8ge 1 (grivegn\u00e9e)",
    "sg:classifiers":[
        {
            "category":"Shopping",
            "subcategory":"Jewelry",
            "type":"Retail Goods"
        }
    ],
    "sg:phone":"+32 4 343 98 29",
    "sg:postcode":"4030",
    "sg:province":"Li\u00e8ge",
    "sg:tags":[
        "jeweller",
        "-"
    ],
    "wof:name":"Ferire",
    "wof:placetype":"venue"
},
  "geometry": {"coordinates":[5.5892658234,50.6275596619],"type":"Point"}
}