{
  "type": "Feature",
  "properties": {
    "addr:full":"Lavaux 13 Trois-ponts Li\u00e8ge 4980",
    "addr:housenumber":"13",
    "addr:postcode":"4980",
    "addr:street":"Lavaux",
    "iso:country":"BE",
    "sg:address":"Lavaux 13",
    "sg:city":"Trois-ponts",
    "sg:orig_category":"Houtbewerking and -behandeling",
    "sg:phone":"+32 80 21 45 66",
    "sg:postcode":"4980",
    "sg:province":"Li\u00e8ge",
    "wof:name":"Francis Piette",
    "wof:placetype":"venue"
},
  "geometry": {"coordinates":[5.8710570335,50.3724403381],"type":"Point"}
}