{
  "type": "Feature",
  "properties": {
    "iso:country":"BE",
    "sg:address":"Rue Du Bien-faire 32",
    "sg:city":"Watermaal-bosvoorde/watermael-boitsfort",
    "sg:orig_category":"Entretien and r\u00e9parations de voitures",
    "sg:phone":"+32 2 673 00 33",
    "sg:postcode":"1170",
    "sg:province":"Bruxelles-Capitale",
    "wof:name":"Garage Lefevre",
    "wof:placetype":"venue"
},
  "geometry": {"coordinates":[4.4023871422,50.8071899414],"type":"Point"}
}