{
  "type": "Feature",
  "properties": {
    "iso:country":"BE",
    "sg:address":"Rue Damien 39",
    "sg:city":"Beaumont",
    "sg:orig_category":"Traitement and fa\u00e7onnage de la pierre",
    "sg:phone":"+32 71 58 84 37",
    "sg:postcode":"6500",
    "sg:province":"Hainaut",
    "wof:name":"Charlet Alain",
    "wof:placetype":"venue"
},
  "geometry": {"coordinates":[4.1903147697,50.2260551453],"type":"Point"}
}