{
  "type": "Feature",
  "properties": {
    "iso:country":"BE",
    "sg:address":"Carrefour-de-l\u00b4europe 3",
    "sg:city":"Yvoir",
    "sg:orig_category":"Algemeen secundair onderwijs Technisch and beroeps secundair onderwijs",
    "sg:phone":"+32 82 61 04 00",
    "sg:postcode":"5530",
    "sg:province":"Namur",
    "wof:name":"Coll\u00c8ge De Godinne-burnot",
    "wof:placetype":"venue"
},
  "geometry": {"coordinates":[4.8654799461,50.3453941345],"type":"Point"}
}