{
  "type": "Feature",
  "properties": {
    "addr:full":"Bergstraat 47 Haaltert (kerksken) Oost-Vlaanderen 9451",
    "addr:housenumber":"47",
    "addr:postcode":"9451",
    "addr:street":"Bergstraat",
    "iso:country":"BE",
    "sg:address":"Bergstraat 47",
    "sg:city":"Haaltert (kerksken)",
    "sg:classifiers":[
        {
            "category":"Health Services",
            "subcategory":"Health Practitioner",
            "type":"Services"
        }
    ],
    "sg:phone":"+32 53 84 07 24",
    "sg:postcode":"9451",
    "sg:province":"Oost-Vlaanderen",
    "sg:tags":[
        "physiotherapist"
    ],
    "wof:name":"De Vos Gino",
    "wof:placetype":"venue"
},
  "geometry": {"coordinates":[3.99208498,50.8902664185],"type":"Point"}
}