{
  "type": "Feature",
  "properties": {
    "iso:country":"BE",
    "sg:address":"Av Schlogel 115",
    "sg:city":"Ciney",
    "sg:orig_category":"Construction and Public Works Metallurgy and Metalworking Tools Wood Wood and Furniture",
    "sg:phone":"+32 83 21 31 73",
    "sg:postcode":"5590",
    "sg:province":"Namur",
    "wof:name":"M & G Et Fils Sa",
    "wof:placetype":"venue"
},
  "geometry": {"coordinates":[5.1128292084,50.3019599915],"type":"Point"}
}