{
  "type": "Feature",
  "properties": {
    "addr:full":"Rijksweg 265 Maasmechelen Limburg 3630",
    "addr:housenumber":"265",
    "addr:postcode":"3630",
    "addr:street":"Rijksweg",
    "iso:country":"BE",
    "sg:address":"Rijksweg 265",
    "sg:city":"Maasmechelen",
    "sg:orig_category":"Sportclubs Sportterreinen and installaties behalve sportcentra",
    "sg:phone":"+32 89 77 25 27",
    "sg:postcode":"3630",
    "sg:province":"Limburg",
    "wof:name":"K. Eisden Sportief",
    "wof:placetype":"venue"
},
  "geometry": {"coordinates":[5.6985058784,50.9723587036],"type":"Point"}
}