{
  "type": "Feature",
  "properties": {
    "addr:full":"Holstraat 24 Evergem Oost-Vlaanderen 9940",
    "addr:housenumber":"24",
    "addr:postcode":"9940",
    "addr:street":"Holstraat;Oost-Vlaanderen",
    "iso:country":"BE",
    "sg:address":"Holstraat 24",
    "sg:city":"Evergem",
    "sg:classifiers":[
        {
            "category":"Fast Food",
            "type":"Food & Drink"
        }
    ],
    "sg:phone":"+32 9 344 55 56",
    "sg:postcode":"9940",
    "sg:province":"Oost-Vlaanderen",
    "sg:tags":[
        "\u00c0",
        "restaurants",
        "emporter",
        "restaurant"
    ],
    "wof:name":"Paddenhouck",
    "wof:placetype":"venue"
},
  "geometry": {"coordinates":[3.7391269207,51.1869087219],"type":"Point"}
}