{
  "type": "Feature",
  "properties": {
    "addr:full":"Rue De La Tombelle 92 La Louviere Hainaut 7110",
    "addr:housenumber":"92",
    "addr:postcode":"7110",
    "addr:street":"Rue De La Tombelle",
    "iso:country":"BE",
    "sg:address":"Rue De La Tombelle 92",
    "sg:city":"La Louviere",
    "sg:orig_category":"Production and \u00e9mission de programmes de t\u00e9l\u00e9vision",
    "sg:phone":"+32 64 88 25 25",
    "sg:postcode":"7110",
    "sg:province":"Hainaut",
    "wof:name":"Antenne Centre",
    "wof:placetype":"venue"
},
  "geometry": {"coordinates":[4.1505050659,50.4826698303],"type":"Point"}
}