{
  "type": "Feature",
  "properties": {
    "addr:full":"Chauss\u00c9e De Hannut 150 Jodoigne Brabant Wallon 1370",
    "addr:housenumber":"150",
    "addr:postcode":"1370",
    "addr:street":"Chausse\u0301E De Hannut",
    "iso:country":"BE",
    "sg:address":"Chauss\u00c9e De Hannut 150",
    "sg:city":"Jodoigne",
    "sg:classifiers":[
        {
            "category":"Cafe",
            "type":"Food & Drink"
        }
    ],
    "sg:phone":"+32 10 81 10 95",
    "sg:postcode":"1370",
    "sg:province":"Brabant Wallon",
    "sg:tags":[
        "caf\u00e9s"
    ],
    "wof:name":"Caf\u00c9 Chant Des Oiseaux",
    "wof:placetype":"venue"
},
  "geometry": {"coordinates":[4.8834900856,50.718460083],"type":"Point"}
}