{
  "type": "Feature",
  "properties": {
    "iso:country":"BE",
    "sg:address":"Stationsstraat 1",
    "sg:city":"Overijse",
    "sg:orig_category":"Kapsalons",
    "sg:phone":"+32 2 687 75 65",
    "sg:postcode":"3090",
    "sg:province":"Vlaams-Brabant",
    "wof:name":"Coiffure Patrick",
    "wof:placetype":"venue"
},
  "geometry": {"coordinates":[4.5375199318,50.7723197937],"type":"Point"}
}