{
  "type": "Feature",
  "properties": {
    "iso:country":"BE",
    "sg:address":"Rue Franklin Roosevelt 77",
    "sg:city":"Frameries",
    "sg:classifiers":[
        {
            "category":"Real Estate",
            "subcategory":"Architect",
            "type":"Services"
        }
    ],
    "sg:phone":"+32 65 66 76 93",
    "sg:postcode":"7080",
    "sg:province":"Hainaut",
    "wof:name":"Hupez J",
    "wof:placetype":"venue"
},
  "geometry": {"coordinates":[3.8982419968,50.4099617004],"type":"Point"}
}