{
  "type": "Feature",
  "properties": {
    "addr:full":"Van Den Heckestraat 51 Gent (ledeberg) Oost-Vlaanderen 9050",
    "addr:housenumber":"51",
    "addr:postcode":"9050",
    "addr:street":"Van Den Heckestraat",
    "iso:country":"BE",
    "sg:address":"Van Den Heckestraat 51",
    "sg:city":"Gent (ledeberg)",
    "sg:classifiers":[
        {
            "category":"Retail",
            "subcategory":"Repair Shop",
            "type":"Services"
        }
    ],
    "sg:phone":"+32 9 231 51 34",
    "sg:postcode":"9050",
    "sg:province":"Oost-Vlaanderen",
    "wof:name":"Sandyck D",
    "wof:placetype":"venue"
},
  "geometry": {"coordinates":[3.7453849316,51.0360183716],"type":"Point"}
}