{
  "type": "Feature",
  "properties": {
    "iso:country":"BE",
    "sg:address":"Molenberg 47",
    "sg:city":"Kruibeke",
    "sg:orig_category":"Brood, gebak and snoepgoed",
    "sg:phone":"+32 3 774 15 95",
    "sg:postcode":"9150",
    "sg:province":"Oost-Vlaanderen",
    "wof:name":"Bakkerij Van Hove",
    "wof:placetype":"venue"
},
  "geometry": {"coordinates":[4.2820830345,51.1720352173],"type":"Point"}
}