{
  "type": "Feature",
  "properties": {
    "addr:full":"Oost Eindeken 18 Box 5 Stekene Oost-Vlaanderen 9190",
    "addr:housenumber":"18;5",
    "addr:postcode":"9190",
    "addr:street":"Eindeken;Box",
    "iso:country":"BE",
    "sg:address":"Oost Eindeken 18 Box 5",
    "sg:city":"Stekene",
    "sg:classifiers":[
        {
            "category":"Home & Garden",
            "subcategory":"Carpets & Floor Coverings",
            "type":"Retail Goods"
        }
    ],
    "sg:phone":"+32 3 789 14 66",
    "sg:postcode":"9190",
    "sg:province":"Oost-Vlaanderen",
    "sg:tags":[
        "layer",
        "mosaicists"
    ],
    "wof:name":"Schelvabo Bvba",
    "wof:placetype":"venue"
},
  "geometry": {"coordinates":[4.0459179878,51.2104721069],"type":"Point"}
}