{
  "type": "Feature",
  "properties": {
    "addr:full":"Vroenstraat 5 Hoegaarden Vlaams-Brabant 3320",
    "addr:housenumber":"5",
    "addr:postcode":"3320",
    "addr:street":"Vroenstraat",
    "iso:country":"BE",
    "sg:address":"Vroenstraat 5",
    "sg:city":"Hoegaarden",
    "sg:orig_category":"Salles de conf\u00e9rences and de r\u00e9ceptions. Catering and organisation de f\u00eates",
    "sg:phone":"+32 16 63 17 83",
    "sg:postcode":"3320",
    "sg:province":"Vlaams-Brabant",
    "wof:name":"'t Pachthof",
    "wof:placetype":"venue"
},
  "geometry": {"coordinates":[4.8950910568,50.7781028748],"type":"Point"}
}