{
  "type": "Feature",
  "properties": {
    "iso:country":"BE",
    "sg:address":"Voshollei 43",
    "sg:city":"Brasschaat",
    "sg:classifiers":[
        {
            "category":"Health Services",
            "subcategory":"Doctor",
            "type":"Services"
        }
    ],
    "sg:phone":"+32 3 651 89 89",
    "sg:postcode":"2930",
    "sg:province":"Antwerpen",
    "sg:tags":[
        "medicinephysicians",
        "surgeon"
    ],
    "wof:name":"Lemmens P",
    "wof:placetype":"venue"
},
  "geometry": {"coordinates":[4.4713802338,51.2841949463],"type":"Point"}
}