{
  "type": "Feature",
  "properties": {
    "iso:country":"BE",
    "sg:address":"Rue De Bomer\u00e9e 14",
    "sg:city":"Montigny-le-tilleul",
    "sg:classifiers":[
        {
            "category":"Real Estate",
            "subcategory":"Architect",
            "type":"Services"
        }
    ],
    "sg:phone":"+32 71 51 74 59",
    "sg:postcode":"6110",
    "sg:province":"Hainaut",
    "wof:name":"Houyoux J-p",
    "wof:placetype":"venue"
},
  "geometry": {"coordinates":[4.3804597855,50.3783950806],"type":"Point"}
}