{
  "type": "Feature",
  "properties": {
    "addr:full":"Bruisbeke 81 Sint-lievens-houtem Oost-Vlaanderen 9520",
    "addr:housenumber":"81",
    "addr:postcode":"9520",
    "addr:street":"Bruisbeke",
    "iso:country":"BE",
    "sg:address":"Bruisbeke 81",
    "sg:city":"Sint-lievens-houtem",
    "sg:orig_category":"D\u00e9molition d\u00b4immeubles and terrassements. Mat\u00e9riaux de construction Construction de rev\u00eatements rout",
    "sg:phone":"+32 9 362 75 50",
    "sg:postcode":"9520",
    "sg:province":"Oost-Vlaanderen",
    "wof:name":"Tavernier",
    "wof:placetype":"venue"
},
  "geometry": {"coordinates":[3.8384308815,50.9311256409],"type":"Point"}
}