{
  "type": "Feature",
  "properties": {
    "addr:full":"Sint-aldegondiskaai 60 Antwerpen Antwerpen 2000",
    "addr:housenumber":"60",
    "addr:postcode":"2000",
    "addr:street":"Sint-Aldegondiskaai",
    "iso:country":"BE",
    "sg:address":"Sint-aldegondiskaai 60",
    "sg:city":"Antwerpen",
    "sg:classifiers":[
        {
            "category":"Bars & Pubs",
            "type":"Food & Drink"
        }
    ],
    "sg:phone":"+32 3 232 82 87",
    "sg:postcode":"2000",
    "sg:province":"Antwerpen",
    "wof:name":"Keravicske ('t)",
    "wof:placetype":"venue"
},
  "geometry": {"coordinates":[4.4049310684,51.2278060913],"type":"Point"}
}