{
  "type": "Feature",
  "properties": {
    "iso:country":"BE",
    "sg:address":"Naamsesteenweg 251",
    "sg:city":"Leuven",
    "sg:orig_category":"Imprimeries and copyshops. V\u00eatements, chaussures and accessoires Gr",
    "sg:phone":"+32 16 40 84 83",
    "sg:postcode":"3001",
    "sg:province":"Vlaams-Brabant",
    "wof:name":"T-art",
    "wof:placetype":"venue"
},
  "geometry": {"coordinates":[4.6960949898,50.8609313965],"type":"Point"}
}