{
  "type": "Feature",
  "properties": {
    "iso:country":"BE",
    "sg:address":"Rue Joseph-hodeige 30",
    "sg:city":"Li\u00e8ge 1 (grivegn\u00e9e)",
    "sg:classifiers":[
        {
            "category":"Building & Trades",
            "subcategory":"Electrical",
            "type":"Services"
        }
    ],
    "sg:phone":"+32 4 263 65 44",
    "sg:postcode":"4030",
    "sg:province":"Li\u00e8ge",
    "sg:tags":[
        "-",
        "electric",
        "contractor"
    ],
    "wof:name":"Ottelec",
    "wof:placetype":"venue"
},
  "geometry": {"coordinates":[5.6079630852,50.6198234558],"type":"Point"}
}