{
  "type": "Feature",
  "properties": {
    "iso:country":"BE",
    "sg:address":"Rue Lovinfosse 60",
    "sg:city":"Li\u00e8ge 1 (grivegn\u00e9e)",
    "sg:classifiers":[
        {
            "category":"Social Services",
            "type":"Services"
        }
    ],
    "sg:phone":"+32 4 342 06 66",
    "sg:postcode":"4030",
    "sg:province":"Li\u00e8ge",
    "wof:name":"Main Tendue 2 Asbl",
    "wof:placetype":"venue"
},
  "geometry": {"coordinates":[5.6033511162,50.6215248108],"type":"Point"}
}