{
  "type": "Feature",
  "properties": {
    "iso:country":"BE",
    "sg:address":"Endstraat 8",
    "sg:city":"Balen",
    "sg:classifiers":[
        {
            "category":"Health Services",
            "subcategory":"Hospital",
            "type":"Services"
        }
    ],
    "sg:phone":"+32 14 31 20 20",
    "sg:postcode":"2490",
    "sg:province":"Antwerpen",
    "sg:tags":[
        "ambulance"
    ],
    "wof:name":"Balense Ambulancedienst",
    "wof:placetype":"venue"
},
  "geometry": {"coordinates":[5.2015638351,51.1802520752],"type":"Point"}
}