{
  "type": "Feature",
  "properties": {
    "addr:full":"Kleinesteenweg 6 Antwerpen Antwerpen 2610",
    "addr:housenumber":"6",
    "addr:postcode":"2610",
    "addr:street":"Kleinesteenweg",
    "iso:country":"BE",
    "sg:address":"Kleinesteenweg 6",
    "sg:city":"Antwerpen",
    "sg:orig_category":"Banken and kredietinstellingen",
    "sg:phone":"+32 3 827 12 23",
    "sg:postcode":"2610",
    "sg:province":"Antwerpen",
    "wof:name":"Bbl",
    "wof:placetype":"venue"
},
  "geometry": {"coordinates":[4.40203619,51.2155303955],"type":"Point"}
}