{
  "type": "Feature",
  "properties": {
    "iso:country":"BE",
    "sg:address":"Diesterstraat 46",
    "sg:city":"Tessenderlo",
    "sg:classifiers":[
        {
            "category":"Personal",
            "subcategory":"Beauty Salon",
            "type":"Services"
        }
    ],
    "sg:phone":"+32 13 66 87 59",
    "sg:postcode":"3980",
    "sg:province":"Limburg",
    "wof:name":"Linda Parfumerie",
    "wof:placetype":"venue"
},
  "geometry": {"coordinates":[5.0879797935,51.0652923584],"type":"Point"}
}