{
  "type": "Feature",
  "properties": {
    "iso:country":"BE",
    "sg:address":"Molenstraat 2b",
    "sg:city":"Herenthout",
    "sg:orig_category":"Mutualities",
    "sg:phone":"+32 14 50 29 56",
    "sg:postcode":"2270",
    "sg:province":"Antwerpen",
    "wof:name":"Ziekenfonds Arbeid En Gezondheid",
    "wof:placetype":"venue"
},
  "geometry": {"coordinates":[4.7567229271,51.1393852234],"type":"Point"}
}