{
  "type": "Feature",
  "properties": {
    "iso:country":"BE",
    "sg:address":"Westmeerbeeksesteenweg 103",
    "sg:city":"Herselt",
    "sg:classifiers":[
        {
            "category":"Home & Garden",
            "subcategory":"Building Materials",
            "type":"Retail Goods"
        }
    ],
    "sg:phone":"+32 16 69 61 40",
    "sg:postcode":"2230",
    "sg:province":"Antwerpen",
    "sg:tags":[
        "window"
    ],
    "wof:name":"De Peuter J",
    "wof:placetype":"venue"
},
  "geometry": {"coordinates":[4.8302397728,51.0383300781],"type":"Point"}
}