{
  "type": "Feature",
  "properties": {
    "addr:full":"Antwerpse Heirweg 5bc Eeklo Oost-Vlaanderen 9900",
    "addr:housenumber":"5bc",
    "addr:postcode":"9900",
    "addr:street":"Antwerpse Heirweg",
    "iso:country":"BE",
    "sg:address":"Antwerpse Heirweg 5bc",
    "sg:city":"Eeklo",
    "sg:orig_category":"Sportclubs",
    "sg:phone":"+32 9 378 36 97",
    "sg:postcode":"9900",
    "sg:province":"Oost-Vlaanderen",
    "wof:name":"J.s. De Poorter",
    "wof:placetype":"venue"
},
  "geometry": {"coordinates":[3.5985510349,51.1826095581],"type":"Point"}
}