{
  "type": "Feature",
  "properties": {
    "addr:full":"Middelweg 105 Leuven Vlaams-Brabant 3001",
    "addr:housenumber":"105",
    "addr:postcode":"3001",
    "addr:street":"Middelweg",
    "iso:country":"BE",
    "sg:address":"Middelweg 105",
    "sg:city":"Leuven",
    "sg:orig_category":"Verhuur cateringmateriaal and evenementuitrusting Winkelinrichting and handelsuitrusting Gh",
    "sg:phone":"+32 16 40 42 61",
    "sg:postcode":"3001",
    "sg:province":"Vlaams-Brabant",
    "wof:name":"Janssens",
    "wof:placetype":"venue"
},
  "geometry": {"coordinates":[4.6922869682,50.8573150635],"type":"Point"}
}