{
  "type": "Feature",
  "properties": {
    "addr:full":"Rue Darwin 23 Bruxelles (ixelles) Bruxelles-Capitale 1050",
    "addr:housenumber":"23",
    "addr:postcode":"1050",
    "addr:street":"Rue Darwin",
    "iso:country":"BE",
    "sg:address":"Rue Darwin 23",
    "sg:city":"Bruxelles (ixelles)",
    "sg:classifiers":[
        {
            "category":"Professional",
            "subcategory":"Testing Lab",
            "type":"Services"
        }
    ],
    "sg:phone":"+32 2 347 09 49",
    "sg:postcode":"1050",
    "sg:province":"Bruxelles-Capitale",
    "sg:tags":[
        "chemist"
    ],
    "wof:name":"Preat",
    "wof:placetype":"venue"
},
  "geometry": {"coordinates":[4.3520650864,50.8180541992],"type":"Point"}
}