{
  "type": "Feature",
  "properties": {
    "iso:country":"BE",
    "sg:address":"Square Franklin-delano Roosevelt 2-3",
    "sg:city":"Mons",
    "sg:classifiers":[
        {
            "category":"Health Services",
            "subcategory":"Health Practitioner",
            "type":"Services"
        }
    ],
    "sg:phone":"+32 65 35 12 26",
    "sg:postcode":"7000",
    "sg:province":"Hainaut",
    "sg:tags":[
        "therapist",
        "speech"
    ],
    "wof:name":"Centre M\u00e9dical De R\u00e9\u00e9ducation Logop\u00e9dique",
    "wof:placetype":"venue"
},
  "geometry": {"coordinates":[3.9466750622,50.4540596008],"type":"Point"}
}