{
  "type": "Feature",
  "properties": {
    "addr:full":"Domien Craccostraat 41 Roeselare West-Vlaanderen 8800",
    "addr:housenumber":"41",
    "addr:postcode":"8800",
    "addr:street":"Domien Craccostraat",
    "iso:country":"BE",
    "sg:address":"Domien Craccostraat 41",
    "sg:city":"Roeselare",
    "sg:classifiers":[
        {
            "category":"Health Services",
            "subcategory":"Health Practitioner",
            "type":"Services"
        }
    ],
    "sg:phone":"+32 51 24 77 43",
    "sg:postcode":"8800",
    "sg:province":"West-Vlaanderen",
    "sg:tags":[
        "therapist",
        "speech"
    ],
    "wof:name":"Verlinde N",
    "wof:placetype":"venue"
},
  "geometry": {"coordinates":[3.1054370403,50.9426956177],"type":"Point"}
}