{
  "type": "Feature",
  "properties": {
    "addr:full":"Apostelhuizen 26 Gent Oost-Vlaanderen 9000",
    "addr:housenumber":"26",
    "addr:postcode":"9000",
    "addr:street":"Apostelhuizen;Oost-Vlaanderen",
    "iso:country":"BE",
    "sg:address":"Apostelhuizen 26",
    "sg:city":"Gent",
    "sg:classifiers":[
        {
            "category":"Professional",
            "subcategory":"Accounting & Tax Preparation",
            "type":"Services"
        }
    ],
    "sg:phone":"+32 9 223 69 95",
    "sg:postcode":"9000",
    "sg:province":"Oost-Vlaanderen",
    "sg:tags":[
        "accountant"
    ],
    "wof:name":"Dekegel R",
    "wof:placetype":"venue"
},
  "geometry": {"coordinates":[3.733987093,51.0512962341],"type":"Point"}
}