{
  "type": "Feature",
  "properties": {
    "addr:full":"Rue Andr\u00c9 V\u00c9sale 13 Charleroi Hainaut 6001",
    "addr:housenumber":"13",
    "addr:postcode":"6001",
    "addr:street":"Rue Andre\u0301 Ve\u0301Sale;Hainaut",
    "iso:country":"BE",
    "sg:address":"Rue Andr\u00c9 V\u00c9sale 13",
    "sg:city":"Charleroi",
    "sg:orig_category":"Woningbouw",
    "sg:phone":"+32 71 43 04 04",
    "sg:postcode":"6001",
    "sg:province":"Hainaut",
    "wof:name":"Geamberto Lucentini",
    "wof:placetype":"venue"
},
  "geometry": {"coordinates":[4.4359178543,50.3880844116],"type":"Point"}
}