{
  "type": "Feature",
  "properties": {
    "iso:country":"BE",
    "sg:address":"Einestraat 12",
    "sg:city":"Oudenaarde",
    "sg:classifiers":[
        {
            "category":"Professional",
            "subcategory":"Art Services",
            "type":"Services"
        }
    ],
    "sg:phone":"+32 55 31 00 83",
    "sg:postcode":"9700",
    "sg:province":"Oost-Vlaanderen",
    "sg:tags":[
        "photography",
        "reporting",
        "-"
    ],
    "wof:name":"Foto-myoo",
    "wof:placetype":"venue"
},
  "geometry": {"coordinates":[3.6050510406,50.8437690735],"type":"Point"}
}