{
  "type": "Feature",
  "properties": {
    "addr:full":"Rue D'orleans 32 Komen-waasten/comines-warneton Hainaut 7780",
    "addr:housenumber":"32;7780",
    "addr:street":"Rue D'Orleans",
    "iso:country":"BE",
    "sg:address":"Rue D'orleans 32",
    "sg:city":"Komen-waasten/comines-warneton",
    "sg:orig_category":"Magasins sp\u00e9cialis\u00e9s",
    "sg:phone":"+32 56 55 92 85",
    "sg:postcode":"7780",
    "sg:province":"Hainaut",
    "wof:name":"Mazi Morad",
    "wof:placetype":"venue"
},
  "geometry": {"coordinates":[3.0030910969,50.7708930969],"type":"Point"}
}