{
  "type": "Feature",
  "properties": {
    "iso:country":"BE",
    "sg:address":"Chemin De Neerstalle 119",
    "sg:city":"Bruxelles (forest)",
    "sg:classifiers":[
        {
            "category":"Retail",
            "subcategory":"Animal Services",
            "type":"Services"
        }
    ],
    "sg:phone":"+32 2 332 22 11",
    "sg:postcode":"1190",
    "sg:province":"Bruxelles-Capitale",
    "sg:tags":[
        "grooming",
        "-",
        "dog"
    ],
    "wof:name":"P'ti Lou",
    "wof:placetype":"venue"
},
  "geometry": {"coordinates":[4.3153338432,50.8074798584],"type":"Point"}
}