{
  "type": "Feature",
  "properties": {
    "addr:full":"Rue Du Gard 3-5 Leuze-en-hainaut Hainaut 7900",
    "addr:housenumber":"3-5",
    "addr:postcode":"7900",
    "addr:street":"Rue Du Gard",
    "iso:country":"BE",
    "sg:address":"Rue Du Gard 3-5",
    "sg:city":"Leuze-en-hainaut",
    "sg:orig_category":"Decoratieve kunst and kunstbenodigdheden",
    "sg:phone":"+32 69 66 32 54",
    "sg:postcode":"7900",
    "sg:province":"Hainaut",
    "wof:name":"Art Evasion",
    "wof:placetype":"venue"
},
  "geometry": {"coordinates":[3.620677948,50.6001548767],"type":"Point"}
}