{
  "type": "Feature",
  "properties": {
    "iso:country":"BE",
    "sg:address":"Hooghaag 49",
    "sg:city":"Hamont-achel (achel)",
    "sg:classifiers":[
        {
            "category":"Mining & Drilling",
            "type":"Manufacturing & Wholesale Goods"
        }
    ],
    "sg:phone":"+32 11 64 32 01",
    "sg:postcode":"3930",
    "sg:province":"Limburg",
    "sg:tags":[
        "boring",
        "well"
    ],
    "wof:name":"Vanduffel",
    "wof:placetype":"venue"
},
  "geometry": {"coordinates":[5.4733409882,51.248374939],"type":"Point"}
}