{
  "type": "Feature",
  "properties": {
    "addr:full":"Breugelhoevestraat 37 Nijlen Antwerpen 2560",
    "addr:housenumber":"37",
    "addr:postcode":"2560",
    "addr:street":"Breugelhoevestraat",
    "iso:country":"BE",
    "sg:address":"Breugelhoevestraat 37",
    "sg:city":"Nijlen",
    "sg:orig_category":"Woningbouw",
    "sg:phone":"+32 3 411 11 24",
    "sg:postcode":"2560",
    "sg:province":"Antwerpen",
    "wof:name":"Carolus Palmans",
    "wof:placetype":"venue"
},
  "geometry": {"coordinates":[4.6517701149,51.1644477844],"type":"Point"}
}