{
  "type": "Feature",
  "properties": {
    "iso:country":"BE",
    "sg:address":"Rubensstraat 127",
    "sg:city":"Turnhout",
    "sg:classifiers":[
        {
            "category":"Manufacturing",
            "subcategory":"Glass & Minerals",
            "type":"Manufacturing & Wholesale Goods"
        }
    ],
    "sg:phone":"+32 14 41 20 03",
    "sg:postcode":"2300",
    "sg:province":"Antwerpen",
    "sg:tags":[
        "building",
        "material"
    ],
    "wof:name":"Goossens Glaswerken Bvba",
    "wof:placetype":"venue"
},
  "geometry": {"coordinates":[4.9442281723,51.3144798279],"type":"Point"}
}