{
  "type": "Feature",
  "properties": {
    "addr:full":"Van Der Bekenlaan 25a Oud-turnhout Antwerpen 2360",
    "addr:housenumber":"25a",
    "addr:postcode":"2360",
    "addr:street":"Van Der Bekenlaan",
    "iso:country":"BE",
    "sg:address":"Van Der Bekenlaan 25a",
    "sg:city":"Oud-turnhout",
    "sg:classifiers":[
        {
            "category":"Health Services",
            "subcategory":"Dentist",
            "type":"Services"
        }
    ],
    "sg:phone":"+32 14 45 35 54",
    "sg:postcode":"2360",
    "sg:province":"Antwerpen",
    "wof:name":"Gevers Ferdi",
    "wof:placetype":"venue"
},
  "geometry": {"coordinates":[4.9834318161,51.3193321228],"type":"Point"}
}