{
  "type": "Feature",
  "properties": {
    "addr:full":"Rue Hocheporte 107b12 Li\u00c8ge Li\u00e8ge 4000",
    "addr:housenumber":"107b12",
    "addr:postcode":"4000",
    "addr:street":"Rue Hocheporte",
    "iso:country":"BE",
    "sg:address":"Rue Hocheporte 107b12",
    "sg:city":"Li\u00c8ge",
    "sg:orig_category":"Beheer onroerend goed",
    "sg:phone":"+32 4 226 13 53",
    "sg:postcode":"4000",
    "sg:province":"Li\u00e8ge",
    "wof:name":"Jean Letesson",
    "wof:placetype":"venue"
},
  "geometry": {"coordinates":[5.5640802383,50.6483383179],"type":"Point"}
}