{
  "type": "Feature",
  "properties": {
    "addr:full":"Langedorpweg 1 Zuienkerke West-Vlaanderen 8377",
    "addr:housenumber":"1",
    "addr:postcode":"8377",
    "addr:street":"Langedorpweg",
    "iso:country":"BE",
    "sg:address":"Langedorpweg 1",
    "sg:city":"Zuienkerke",
    "sg:orig_category":"Eleveurs de bovins",
    "sg:phone":"+32 50 31 46 23",
    "sg:postcode":"8377",
    "sg:province":"West-Vlaanderen",
    "wof:name":"Van Den Berghe Ivan",
    "wof:placetype":"venue"
},
  "geometry": {"coordinates":[3.1096000671,51.2285804749],"type":"Point"}
}