{
  "type": "Feature",
  "properties": {
    "iso:country":"BE",
    "sg:address":"Processiestraat 13",
    "sg:city":"Wingene",
    "sg:orig_category":"Woningbouw",
    "sg:phone":"+32 51 61 23 76",
    "sg:postcode":"8750",
    "sg:province":"West-Vlaanderen",
    "wof:name":"Mooyaert",
    "wof:placetype":"venue"
},
  "geometry": {"coordinates":[3.2169849873,51.0381240845],"type":"Point"}
}