{
  "type": "Feature",
  "properties": {
    "addr:full":"Tiensesteenweg 179 Glabbeek Vlaams-Brabant 3380",
    "addr:housenumber":"179",
    "addr:postcode":"3380",
    "addr:street":"Tiensesteenweg",
    "iso:country":"BE",
    "sg:address":"Tiensesteenweg 179",
    "sg:city":"Glabbeek",
    "sg:orig_category":"Herstellingen and onderhoud van auto's",
    "sg:phone":"+32 16 77 71 15",
    "sg:postcode":"3380",
    "sg:province":"Vlaams-Brabant",
    "wof:name":"Julia Hermans",
    "wof:placetype":"venue"
},
  "geometry": {"coordinates":[4.9597492218,50.8701133728],"type":"Point"}
}