{
  "type": "Feature",
  "properties": {
    "iso:country":"BE",
    "sg:address":"Recul\u00c9mont 14",
    "sg:city":"Malmedy/malmedy",
    "sg:orig_category":"Eleveurs de bovins",
    "sg:phone":"+32 80 57 06 88",
    "sg:postcode":"4960",
    "sg:province":"Li\u00e8ge",
    "wof:name":"Josee Jamar",
    "wof:placetype":"venue"
},
  "geometry": {"coordinates":[6.0266089439,50.3812713623],"type":"Point"}
}