{
  "type": "Feature",
  "properties": {
    "iso:country":"BE",
    "sg:address":"Hoekstraat 2",
    "sg:city":"Brussel/bruxelles",
    "sg:orig_category":"Landmeters and schatters",
    "sg:phone":"+32 2 203 30 70",
    "sg:postcode":"1000",
    "sg:province":"Bruxelles-Capitale",
    "wof:name":"Veamo",
    "wof:placetype":"venue"
},
  "geometry": {"coordinates":[4.3518857956,50.8573493958],"type":"Point"}
}