{
  "type": "Feature",
  "properties": {
    "addr:full":"Rue Albert I 70 P\u00e9ruwelz Hainaut 7600",
    "addr:housenumber":"70",
    "addr:postcode":"7600",
    "addr:street":"Rue Albert I",
    "iso:country":"BE",
    "sg:address":"Rue Albert I 70",
    "sg:city":"P\u00e9ruwelz",
    "sg:orig_category":"Non-Classified Establishments",
    "sg:phone":"+32 69 77 12 52",
    "sg:postcode":"7600",
    "sg:province":"Hainaut",
    "wof:name":"Anitex",
    "wof:placetype":"venue"
},
  "geometry": {"coordinates":[3.590280056,50.5075683594],"type":"Point"}
}