{
  "type": "Feature",
  "properties": {
    "addr:full":"Hagenbroeksesteenweg 2 Lier Antwerpen 2500",
    "addr:housenumber":"2",
    "addr:postcode":"2500",
    "addr:street":"Hagenbroeksesteenweg",
    "iso:country":"BE",
    "sg:address":"Hagenbroeksesteenweg 2",
    "sg:city":"Lier",
    "sg:orig_category":"Kapsalons",
    "sg:phone":"+32 3 489 15 04",
    "sg:postcode":"2500",
    "sg:province":"Antwerpen",
    "wof:name":"Coiffure Mantini",
    "wof:placetype":"venue"
},
  "geometry": {"coordinates":[4.5754408836,51.1453590393],"type":"Point"}
}