{
  "type": "Feature",
  "properties": {
    "addr:full":"Route Nationale 5 Charleroi Hainaut 6041",
    "addr:postcode":"6041",
    "addr:street":"Route Nationale 5;Hainaut",
    "iso:country":"BE",
    "sg:address":"Route Nationale 5",
    "sg:city":"Charleroi",
    "sg:orig_category":"Bouwmaterialen Gh Vloer- and muurbekleding",
    "sg:phone":"+32 71 25 65 10",
    "sg:postcode":"6041",
    "sg:province":"Hainaut",
    "wof:name":"Inter-carrelages",
    "wof:placetype":"venue"
},
  "geometry": {"coordinates":[4.4314317703,50.4685935974],"type":"Point"}
}