{
  "type": "Feature",
  "properties": {
    "iso:country":"BE",
    "sg:address":"Heuvelerweg 7",
    "sg:city":"Neerpelt (sint-huibrechts-lille)",
    "sg:classifiers":[
        {
            "category":"Farming",
            "subcategory":"Livestock Farm",
            "type":"Manufacturing & Wholesale Goods"
        }
    ],
    "sg:phone":"+32 11 64 24 34",
    "sg:postcode":"3910",
    "sg:province":"Limburg",
    "sg:tags":[
        "buyer"
    ],
    "wof:name":"Vavar Nv",
    "wof:placetype":"venue"
},
  "geometry": {"coordinates":[5.4789829254,51.235496521],"type":"Point"}
}