{
  "type": "Feature",
  "properties": {
    "addr:full":"Borgeleien 24 Geel Antwerpen 2440",
    "addr:housenumber":"24",
    "addr:postcode":"2440",
    "addr:street":"Borgeleien",
    "iso:country":"BE",
    "sg:address":"Borgeleien 24",
    "sg:city":"Geel",
    "sg:classifiers":[
        {
            "category":"Parking",
            "subcategory":"Lot",
            "type":"Transportation"
        }
    ],
    "sg:phone":"+32 475 60 47 06",
    "sg:postcode":"2440",
    "sg:province":"Antwerpen",
    "sg:tags":[
        "parking-places",
        "laying-out"
    ],
    "wof:name":"Dams Denis",
    "wof:placetype":"venue"
},
  "geometry": {"coordinates":[4.9091210365,51.1895904541],"type":"Point"}
}