{
  "type": "Feature",
  "properties": {
    "addr:full":"Houtum 61 Kasterlee Antwerpen 2460",
    "addr:housenumber":"61",
    "addr:postcode":"2460",
    "addr:street":"Houtum",
    "iso:country":"BE",
    "sg:address":"Houtum 61",
    "sg:city":"Kasterlee",
    "sg:classifiers":[
        {
            "category":"Organizations",
            "subcategory":"Professional Association",
            "type":"Services"
        }
    ],
    "sg:phone":"+32 14 85 23 74",
    "sg:postcode":"2460",
    "sg:province":"Antwerpen",
    "sg:tags":[
        "organisation",
        "seminar"
    ],
    "wof:name":"De Watermolen",
    "wof:placetype":"venue"
},
  "geometry": {"coordinates":[4.976621151,51.2293243408],"type":"Point"}
}