{
  "type": "Feature",
  "properties": {
    "addr:full":"Hazeveld 11 Sint-pieters-leeuw (oudenaken) Vlaams-Brabant 1600",
    "addr:housenumber":"11;1600",
    "addr:street":"Hazeveld;Vlaams-Brabant",
    "iso:country":"BE",
    "sg:address":"Hazeveld 11",
    "sg:city":"Sint-pieters-leeuw (oudenaken)",
    "sg:classifiers":[
        {
            "category":"Shopping",
            "subcategory":"Clothing, Apparel, & Fashions",
            "type":"Retail Goods"
        }
    ],
    "sg:phone":"+32 2 532 55 04",
    "sg:postcode":"1600",
    "sg:province":"Vlaams-Brabant",
    "sg:tags":[
        "designer",
        "stylist"
    ],
    "wof:name":"Jossystijl",
    "wof:placetype":"venue"
},
  "geometry": {"coordinates":[4.2071928978,50.7829322815],"type":"Point"}
}