{
  "type": "Feature",
  "properties": {
    "iso:country":"BE",
    "sg:address":"Rue De La Cambre 78",
    "sg:city":"Bruxelles (woluwe-saint-lambert)",
    "sg:classifiers":[
        {
            "category":"Professional",
            "subcategory":"Management & Consulting",
            "type":"Services"
        }
    ],
    "sg:phone":"+32 2 779 92 52",
    "sg:postcode":"1200",
    "sg:province":"Bruxelles-Capitale",
    "sg:tags":[
        "tax-consultants"
    ],
    "wof:name":"Visiedo M",
    "wof:placetype":"venue"
},
  "geometry": {"coordinates":[4.4231538773,50.8392066956],"type":"Point"}
}