{
  "type": "Feature",
  "properties": {
    "addr:full":"Kerkstraat 18 Berlare (overmere) Oost-Vlaanderen 9290",
    "addr:housenumber":"18",
    "addr:postcode":"9290",
    "addr:street":"Kerkstraat",
    "iso:country":"BE",
    "sg:address":"Kerkstraat 18",
    "sg:city":"Berlare (overmere)",
    "sg:classifiers":[
        {
            "category":"Bakery",
            "type":"Food & Drink"
        }
    ],
    "sg:phone":"+32 9 367 57 54",
    "sg:postcode":"9290",
    "sg:province":"Oost-Vlaanderen",
    "sg:tags":[
        "confectioner",
        "baker"
    ],
    "wof:name":"Meganck",
    "wof:placetype":"venue"
},
  "geometry": {"coordinates":[3.9463789463,51.0476913452],"type":"Point"}
}