{
  "type": "Feature",
  "properties": {
    "addr:full":"Steenweg 229 Gingelom Limburg 3890",
    "addr:housenumber":"229",
    "addr:postcode":"3890",
    "addr:street":"Steenweg",
    "iso:country":"BE",
    "sg:address":"Steenweg 229",
    "sg:city":"Gingelom",
    "sg:orig_category":"Banques and organismes de cr\u00e9dit",
    "sg:phone":"+32 11 88 17 49",
    "sg:postcode":"3890",
    "sg:province":"Limburg",
    "wof:name":"Ippa",
    "wof:placetype":"venue"
},
  "geometry": {"coordinates":[5.1278300285,50.7434616089],"type":"Point"}
}