{
  "type": "Feature",
  "properties": {
    "addr:full":"Onafhankelijkheidstraat 200 Sint-jans-molenbeek/molenbeek-saint-jean Bruxelles-Capitale 1080",
    "addr:housenumber":"200",
    "addr:postcode":"1080",
    "addr:street":"Onafhankelijkheidstraat",
    "iso:country":"BE",
    "sg:address":"Onafhankelijkheidstraat 200",
    "sg:city":"Sint-jans-molenbeek/molenbeek-saint-jean",
    "sg:orig_category":"Industri\u00eble wasserijen and droogkuis",
    "sg:phone":"+32 2 410 36 63",
    "sg:postcode":"1080",
    "sg:province":"Bruxelles-Capitale",
    "wof:name":"Desmet",
    "wof:placetype":"venue"
},
  "geometry": {"coordinates":[4.3263049126,50.8538856506],"type":"Point"}
}