{
  "type": "Feature",
  "properties": {
    "iso:country":"BE",
    "sg:address":"Rue De France 25",
    "sg:city":"Hastiere",
    "sg:orig_category":"Installation \u00e9lectrique r\u00e9sidentielle",
    "sg:phone":"+32 82 64 53 23",
    "sg:postcode":"5544",
    "sg:province":"Namur",
    "wof:name":"Tous Travaux Et R\u00c9gie",
    "wof:placetype":"venue"
},
  "geometry": {"coordinates":[4.8241291046,50.1692390442],"type":"Point"}
}