{
  "type": "Feature",
  "properties": {
    "addr:full":"Gilainstraat 26 Tienen Vlaams-Brabant 3300",
    "addr:housenumber":"26",
    "addr:postcode":"3300",
    "addr:street":"Gilainstraat",
    "iso:country":"BE",
    "sg:address":"Gilainstraat 26",
    "sg:city":"Tienen",
    "sg:classifiers":[
        {
            "category":"Fast Food",
            "type":"Food & Drink"
        }
    ],
    "sg:phone":"+32 16 81 86 05",
    "sg:postcode":"3300",
    "sg:province":"Vlaams-Brabant",
    "sg:tags":[
        "meeneem",
        "restaurant"
    ],
    "wof:name":"Frituur Lydia",
    "wof:placetype":"venue"
},
  "geometry": {"coordinates":[4.9373922348,50.8090133667],"type":"Point"}
}