{
  "type": "Feature",
  "properties": {
    "iso:country":"BE",
    "sg:address":"Rue D'hoves 61",
    "sg:city":"Silly (graty)",
    "sg:classifiers":[
        {
            "category":"Building & Trades",
            "subcategory":"Construction",
            "type":"Services"
        }
    ],
    "sg:phone":"+32 67 45 88 52",
    "sg:postcode":"7830",
    "sg:province":"Hainaut",
    "sg:tags":[
        "installation",
        "-",
        "central",
        "heating"
    ],
    "wof:name":"Hanocq Ets",
    "wof:placetype":"venue"
},
  "geometry": {"coordinates":[3.9975059032,50.6374511719],"type":"Point"}
}