{
  "type": "Feature",
  "properties": {
    "addr:full":"Vollezelestraat 41 Gooik Vlaams-Brabant 1755",
    "addr:housenumber":"41",
    "addr:postcode":"1755",
    "addr:street":"Vollezelestraat",
    "iso:country":"BE",
    "sg:address":"Vollezelestraat 41",
    "sg:city":"Gooik",
    "sg:orig_category":"Reclamebureaus",
    "sg:phone":"+32 54 56 83 81",
    "sg:postcode":"1755",
    "sg:province":"Vlaams-Brabant",
    "wof:name":"Johan Rooseleers",
    "wof:placetype":"venue"
},
  "geometry": {"coordinates":[4.0582947731,50.7721214294],"type":"Point"}
}