{
  "type": "Feature",
  "properties": {
    "addr:full":"Chauss\u00c9e De Bruxelles 197 Nijvel Brabant Wallon 1401",
    "addr:housenumber":"197;1401",
    "addr:street":"Chausse\u0301E De Bruxelles;Brabant Wallon",
    "iso:country":"BE",
    "sg:address":"Chauss\u00c9e De Bruxelles 197",
    "sg:city":"Nijvel",
    "sg:orig_category":"Rev\u00eatements de sols and murs",
    "sg:phone":"+32 67 84 18 04",
    "sg:postcode":"1401",
    "sg:province":"Brabant Wallon",
    "wof:name":"Parqueterie De Nivelles",
    "wof:placetype":"venue"
},
  "geometry": {"coordinates":[4.341190815,50.6170539856],"type":"Point"}
}