{
  "type": "Feature",
  "properties": {
    "iso:country":"BE",
    "sg:address":"Ieperleestraat 6 Box 1",
    "sg:city":"Mechelen",
    "sg:classifiers":[
        {
            "category":"Real Estate",
            "subcategory":"Real Estate Services",
            "type":"Services"
        }
    ],
    "sg:phone":"+32 15 20 16 66",
    "sg:postcode":"2800",
    "sg:province":"Antwerpen",
    "wof:name":"Tikam Bvba",
    "wof:placetype":"venue"
},
  "geometry": {"coordinates":[4.4796390533,51.0386962891],"type":"Point"}
}