{
  "type": "Feature",
  "properties": {
    "addr:full":"Rue Omer Houssi\u00c8re 19 La Louvi\u00c8re Hainaut 7110",
    "addr:housenumber":"19",
    "addr:postcode":"7110",
    "addr:street":"Rue Omer Houssie\u0300Re",
    "iso:country":"BE",
    "sg:address":"Rue Omer Houssi\u00c8re 19",
    "sg:city":"La Louvi\u00c8re",
    "sg:orig_category":"Eclairage et \u00e9quipements du foyer. Jeux and jouets",
    "sg:phone":"+32 64 66 50 66",
    "sg:postcode":"7110",
    "sg:province":"Hainaut",
    "wof:name":"Maison Amiprix",
    "wof:placetype":"venue"
},
  "geometry": {"coordinates":[4.1505050659,50.4826698303],"type":"Point"}
}