{
  "type": "Feature",
  "properties": {
    "addr:full":"Fran\u00e7ois Laurentplein 1 Gent Oost-Vlaanderen 9000",
    "addr:housenumber":"1",
    "addr:postcode":"9000",
    "addr:street":"Oost-Vlaanderen",
    "iso:country":"BE",
    "sg:address":"Fran\u00e7ois Laurentplein 1",
    "sg:city":"Gent",
    "sg:classifiers":[
        {
            "category":"Professional",
            "subcategory":"Management & Consulting",
            "type":"Services"
        }
    ],
    "sg:phone":"+32 9 223 39 98",
    "sg:postcode":"9000",
    "sg:province":"Oost-Vlaanderen",
    "sg:tags":[
        "consultant",
        "agency",
        "advertising"
    ],
    "wof:name":"Magazine-press Bvba",
    "wof:placetype":"venue"
},
  "geometry": {"coordinates":[3.7284560204,51.0512886047],"type":"Point"}
}