{
  "type": "Feature",
  "properties": {
    "iso:country":"BE",
    "sg:address":"Zuidstraat 66",
    "sg:city":"Ichtegem",
    "sg:classifiers":[
        {
            "category":"Building & Trades",
            "subcategory":"Construction",
            "type":"Services"
        }
    ],
    "sg:phone":"+32 51 58 85 55",
    "sg:postcode":"8480",
    "sg:province":"West-Vlaanderen",
    "sg:tags":[
        "stucco",
        "contractor"
    ],
    "wof:name":"Sinnaeve Redgy Bvba",
    "wof:placetype":"venue"
},
  "geometry": {"coordinates":[3.0351099968,51.1055870056],"type":"Point"}
}