{
  "type": "Feature",
  "properties": {
    "addr:full":"Rue Van Artevelde 76 Bruxelles Bruxelles-Capitale 1000",
    "addr:housenumber":"76",
    "addr:postcode":"1000",
    "addr:street":"Rue Van Artevelde",
    "iso:country":"BE",
    "sg:address":"Rue Van Artevelde 76",
    "sg:city":"Bruxelles",
    "sg:classifiers":[
        {
            "category":"Social Services",
            "type":"Services"
        }
    ],
    "sg:phone":"+32 2 511 95 17",
    "sg:postcode":"1000",
    "sg:province":"Bruxelles-Capitale",
    "wof:name":"Wardbal",
    "wof:placetype":"venue"
},
  "geometry": {"coordinates":[4.3451228142,50.847278595],"type":"Point"}
}