{
  "type": "Feature",
  "properties": {
    "addr:full":"Sint-michielstraat 46 Tielt West-Vlaanderen 8700",
    "addr:housenumber":"46",
    "addr:postcode":"8700",
    "addr:street":"Sint-Michielstraat",
    "iso:country":"BE",
    "sg:address":"Sint-michielstraat 46",
    "sg:city":"Tielt",
    "sg:orig_category":"Artiesten and kunstenaars",
    "sg:phone":"+32 51 40 18 22",
    "sg:postcode":"8700",
    "sg:province":"West-Vlaanderen",
    "wof:name":"Luc Tack",
    "wof:placetype":"venue"
},
  "geometry": {"coordinates":[3.3217248917,50.9976615906],"type":"Point"}
}