{
  "type": "Feature",
  "properties": {
    "iso:country":"BE",
    "sg:address":"Rue Edmond Schmidt 2",
    "sg:city":"Gerpinnes",
    "sg:orig_category":"Caf\u00e9s Dranken",
    "sg:phone":"+32 71 50 23 87",
    "sg:postcode":"6280",
    "sg:province":"Hainaut",
    "wof:name":"Minarode",
    "wof:placetype":"venue"
},
  "geometry": {"coordinates":[4.5260038376,50.3370094299],"type":"Point"}
}