{
  "type": "Feature",
  "properties": {
    "addr:full":"Slootstraat 9 Destelbergen (heusden) Oost-Vlaanderen 9070",
    "addr:housenumber":"9",
    "addr:postcode":"9070",
    "addr:street":"Slootstraat",
    "iso:country":"BE",
    "sg:address":"Slootstraat 9",
    "sg:city":"Destelbergen (heusden)",
    "sg:classifiers":[
        {
            "category":"Building & Trades",
            "subcategory":"Landscaping Services",
            "type":"Services"
        }
    ],
    "sg:phone":"+32 9 231 87 30",
    "sg:postcode":"9070",
    "sg:province":"Oost-Vlaanderen",
    "sg:tags":[
        "gardening",
        "garden",
        "maintenance"
    ],
    "wof:name":"Lucas E",
    "wof:placetype":"venue"
},
  "geometry": {"coordinates":[3.8054020405,51.0279045105],"type":"Point"}
}