{
  "type": "Feature",
  "properties": {
    "iso:country":"BE",
    "sg:address":"Hannuitsesteenweg 216",
    "sg:city":"Landen",
    "sg:classifiers":[
        {
            "category":"Health Services",
            "subcategory":"Health Practitioner",
            "type":"Services"
        }
    ],
    "sg:phone":"+32 11 83 26 58",
    "sg:postcode":"3400",
    "sg:province":"Vlaams-Brabant",
    "sg:tags":[
        "psychologist"
    ],
    "wof:name":"Mattheus R",
    "wof:placetype":"venue"
},
  "geometry": {"coordinates":[5.0810899734,50.7415084839],"type":"Point"}
}