{
  "type": "Feature",
  "properties": {
    "addr:full":"Rue Buffon 55 Bruxelles (anderlecht) Bruxelles-Capitale 1070",
    "addr:housenumber":"55",
    "addr:postcode":"1070",
    "addr:street":"Rue Buffon",
    "iso:country":"BE",
    "sg:address":"Rue Buffon 55",
    "sg:city":"Bruxelles (anderlecht)",
    "sg:classifiers":[
        {
            "category":"Professional",
            "subcategory":"Art Services",
            "type":"Services"
        }
    ],
    "sg:phone":"+32 2 521 24 01",
    "sg:postcode":"1070",
    "sg:province":"Bruxelles-Capitale",
    "sg:tags":[
        "interior",
        "designer"
    ],
    "wof:name":"Griffet A",
    "wof:placetype":"venue"
},
  "geometry": {"coordinates":[4.2989068031,50.8399848938],"type":"Point"}
}