{
  "type": "Feature",
  "properties": {
    "iso:country":"BE",
    "sg:address":"Haachtsebaan 27",
    "sg:city":"Keerbergen",
    "sg:orig_category":"Kapsalons",
    "sg:phone":"+32 15 51 28 33",
    "sg:postcode":"3140",
    "sg:province":"Vlaams-Brabant",
    "wof:name":"Hair Fashion",
    "wof:placetype":"venue"
},
  "geometry": {"coordinates":[4.6307191849,51.0040969849],"type":"Point"}
}