{
  "type": "Feature",
  "properties": {
    "iso:country":"BE",
    "sg:address":"Place Fr\u00e9d\u00e9ric 3",
    "sg:city":"Charleroi (roux)",
    "sg:classifiers":[
        {
            "category":"Health Services",
            "subcategory":"Health Practitioner",
            "type":"Services"
        }
    ],
    "sg:phone":"+32 71 46 01 28",
    "sg:postcode":"6044",
    "sg:province":"Hainaut",
    "sg:tags":[
        "physiotherapist"
    ],
    "wof:name":"Napolitano G-b",
    "wof:placetype":"venue"
},
  "geometry": {"coordinates":[4.3837280273,50.4340133667],"type":"Point"}
}