{
  "type": "Feature",
  "properties": {
    "iso:country":"BE",
    "sg:address":"Rue Margot 3",
    "sg:city":"Mont-saint-guibert",
    "sg:orig_category":"M\u00e9decins and sp\u00e9cialistes",
    "sg:phone":"+32 10 65 82 31",
    "sg:postcode":"1435",
    "sg:province":"Brabant Wallon",
    "wof:name":"Ph. Dejonckere",
    "wof:placetype":"venue"
},
  "geometry": {"coordinates":[4.6498451233,50.6423797607],"type":"Point"}
}