{
  "type": "Feature",
  "properties": {
    "addr:full":"Ijslandvaardersstraat 7 Koksijde West-Vlaanderen 8670",
    "addr:housenumber":"7",
    "addr:postcode":"8670",
    "addr:street":"Ijslandvaardersstraat",
    "iso:country":"BE",
    "sg:address":"Ijslandvaardersstraat 7",
    "sg:city":"Koksijde",
    "sg:orig_category":"Tuinen",
    "sg:phone":"+32 58 52 28 50",
    "sg:postcode":"8670",
    "sg:province":"West-Vlaanderen",
    "wof:name":"Erik Monsy",
    "wof:placetype":"venue"
},
  "geometry": {"coordinates":[2.6202731133,51.0974121094],"type":"Point"}
}