{
  "type": "Feature",
  "properties": {
    "addr:full":"Rue De Heusy 66 Verviers Li\u00e8ge 4800",
    "addr:housenumber":"66",
    "addr:postcode":"4800",
    "addr:street":"Rue De Heusy",
    "iso:country":"BE",
    "sg:address":"Rue De Heusy 66",
    "sg:city":"Verviers",
    "sg:classifiers":[
        {
            "category":"Personal",
            "subcategory":"Beauty Salon",
            "type":"Services"
        }
    ],
    "sg:phone":"+32 87 33 59 45",
    "sg:postcode":"4800",
    "sg:province":"Li\u00e8ge",
    "sg:tags":[
        "de",
        "coiffure"
    ],
    "wof:name":"Daniel Danthinne",
    "wof:placetype":"venue"
},
  "geometry": {"coordinates":[5.8669099808,50.5917129517],"type":"Point"}
}