{
  "type": "Feature",
  "properties": {
    "addr:full":"Scheldestraat 7 Hamme (moerzeke) Oost-Vlaanderen 9220",
    "addr:housenumber":"7",
    "addr:postcode":"9220",
    "addr:street":"Scheldestraat",
    "iso:country":"BE",
    "sg:address":"Scheldestraat 7",
    "sg:city":"Hamme (moerzeke)",
    "sg:classifiers":[
        {
            "category":"Personal",
            "subcategory":"Nail Salon",
            "type":"Services"
        }
    ],
    "sg:phone":"+32 52 48 22 20",
    "sg:postcode":"9220",
    "sg:province":"Oost-Vlaanderen",
    "sg:tags":[
        "pedicure"
    ],
    "wof:name":"Buts S",
    "wof:placetype":"venue"
},
  "geometry": {"coordinates":[4.1685991287,51.0491333008],"type":"Point"}
}