{
  "type": "Feature",
  "properties": {
    "addr:full":"Rue Du Six Juin 18 Chatelet Hainaut 6200",
    "addr:housenumber":"18",
    "addr:postcode":"6200",
    "addr:street":"Rue Du Six Juin;Hainaut",
    "iso:country":"BE",
    "sg:address":"Rue Du Six Juin 18",
    "sg:city":"Chatelet",
    "sg:classifiers":[
        {
            "category":"Arena",
            "subcategory":"Sports Club",
            "type":"Entertainment"
        }
    ],
    "sg:phone":"+32 71 38 87 06",
    "sg:postcode":"6200",
    "sg:province":"Hainaut",
    "sg:tags":[
        "terrain",
        "hors",
        "de",
        "installation",
        "sportifs"
    ],
    "wof:name":"Ass. Sportive Chatelineau",
    "wof:placetype":"venue"
},
  "geometry": {"coordinates":[4.5086622238,50.4327735901],"type":"Point"}
}