{
  "type": "Feature",
  "properties": {
    "addr:full":"Zuidlaan 336 Wetteren Oost-Vlaanderen 9230",
    "addr:housenumber":"336",
    "addr:postcode":"9230",
    "addr:street":"Zuidlaan",
    "iso:country":"BE",
    "sg:address":"Zuidlaan 336",
    "sg:city":"Wetteren",
    "sg:classifiers":[
        {
            "category":"Autos & Motor Vehicles",
            "subcategory":"Auto Supplies",
            "type":"Retail Goods"
        }
    ],
    "sg:phone":"+32 9 369 17 41",
    "sg:postcode":"9230",
    "sg:province":"Oost-Vlaanderen",
    "sg:tags":[
        "automobile",
        "absorber",
        "shock",
        "-"
    ],
    "wof:name":"Wetters Uitlaatcenter/ Van Leirsberghe",
    "wof:placetype":"venue"
},
  "geometry": {"coordinates":[3.8503301144,50.9904212952],"type":"Point"}
}