{
  "type": "Feature",
  "properties": {
    "addr:full":"Rue De La Fus\u00e9e 64 Bruxelles Bruxelles-Capitale 1130",
    "addr:housenumber":"64",
    "addr:postcode":"1130",
    "addr:street":"Rue De La Fuse\u0301E",
    "iso:country":"BE",
    "sg:address":"Rue De La Fus\u00e9e 64",
    "sg:city":"Bruxelles",
    "sg:classifiers":[
        {
            "category":"Professional",
            "subcategory":"Computer Services",
            "type":"Services"
        }
    ],
    "sg:phone":"+32 2 726 88 48",
    "sg:postcode":"1130",
    "sg:province":"Bruxelles-Capitale",
    "sg:tags":[
        "-",
        "processing",
        "data",
        "software"
    ],
    "wof:name":"I T S Nv",
    "wof:placetype":"venue"
},
  "geometry": {"coordinates":[4.4203629494,50.8777351379],"type":"Point"}
}