{
  "type": "Feature",
  "properties": {
    "addr:full":"Rue De La Victoire 26 Bruxelles (saint-gilles) Bruxelles-Capitale 1060",
    "addr:housenumber":"26",
    "addr:postcode":"1060",
    "addr:street":"Rue De La",
    "iso:country":"BE",
    "sg:address":"Rue De La Victoire 26",
    "sg:city":"Bruxelles (saint-gilles)",
    "sg:classifiers":[
        {
            "category":"Education",
            "subcategory":"Special Training",
            "type":"Public Place"
        }
    ],
    "sg:phone":"+32 2 543 16 60",
    "sg:postcode":"1060",
    "sg:province":"Bruxelles-Capitale",
    "sg:tags":[
        "professional"
    ],
    "wof:name":"Cenforgil Asbl",
    "wof:placetype":"venue"
},
  "geometry": {"coordinates":[4.3464159966,50.8320159912],"type":"Point"}
}