{
  "type": "Feature",
  "properties": {
    "addr:full":"Lindenlei 34 Schoten Antwerpen 2900",
    "addr:housenumber":"34",
    "addr:postcode":"2900",
    "addr:street":"Lindenlei",
    "iso:country":"BE",
    "sg:address":"Lindenlei 34",
    "sg:city":"Schoten",
    "sg:orig_category":"Parfumeries. Salons de coiffure",
    "sg:phone":"+32 3 658 67 86",
    "sg:postcode":"2900",
    "sg:province":"Antwerpen",
    "wof:name":"M.g. Hairstyling",
    "wof:placetype":"venue"
},
  "geometry": {"coordinates":[4.5149102211,51.2510223389],"type":"Point"}
}