{
  "type": "Feature",
  "properties": {
    "addr:full":"Bas Chemin 193 Comines-warneton (bas-warneton) Hainaut 7784",
    "addr:housenumber":"193",
    "addr:postcode":"7784",
    "addr:street":"Chemin;Bas-Warneton Hainaut",
    "iso:country":"BE",
    "sg:address":"Bas Chemin 193",
    "sg:city":"Comines-warneton (bas-warneton)",
    "sg:classifiers":[
        {
            "category":"Health Services",
            "subcategory":"Health Practitioner",
            "type":"Services"
        }
    ],
    "sg:phone":"+32 56 55 78 20",
    "sg:postcode":"7784",
    "sg:province":"Hainaut",
    "sg:tags":[
        "physiotherapist"
    ],
    "wof:name":"Decourcelle Sylvie",
    "wof:placetype":"venue"
},
  "geometry": {"coordinates":[2.9652299881,50.7542915344],"type":"Point"}
}