{
  "type": "Feature",
  "properties": {
    "iso:country":"BE",
    "sg:address":"Rue Joseph Triffaux 8",
    "sg:city":"Hannut",
    "sg:orig_category":"Boekhouders",
    "sg:phone":"+32 19 63 47 99",
    "sg:postcode":"4280",
    "sg:province":"Li\u00e8ge",
    "wof:name":"Monique De Bes",
    "wof:placetype":"venue"
},
  "geometry": {"coordinates":[5.0148849487,50.6900444031],"type":"Point"}
}