{
  "type": "Feature",
  "properties": {
    "addr:full":"Winterkeer 15 Galmaarden Vlaams-Brabant 1570",
    "addr:housenumber":"15",
    "addr:postcode":"1570",
    "addr:street":"Winterkeer",
    "iso:country":"BE",
    "sg:address":"Winterkeer 15",
    "sg:city":"Galmaarden",
    "sg:orig_category":"Rundveehouders",
    "sg:phone":"+32 54 58 98 44",
    "sg:postcode":"1570",
    "sg:province":"Vlaams-Brabant",
    "wof:name":"August Hugo",
    "wof:placetype":"venue"
},
  "geometry": {"coordinates":[3.9681859016,50.7369995117],"type":"Point"}
}