{
  "type": "Feature",
  "properties": {
    "addr:full":"Chauss\u00c9e De Wavre 559 Grez-doiceau Brabant Wallon 1390",
    "addr:housenumber":"559",
    "addr:postcode":"1390",
    "addr:street":"Chausse\u0301E De Wavre",
    "iso:country":"BE",
    "sg:address":"Chauss\u00c9e De Wavre 559",
    "sg:city":"Grez-doiceau",
    "sg:orig_category":"V\u00eatements pour b\u00e9b\u00e9s and enfants",
    "sg:phone":"+32 10 84 54 19",
    "sg:postcode":"1390",
    "sg:province":"Brabant Wallon",
    "wof:name":"Ingeborg Bouge",
    "wof:placetype":"venue"
},
  "geometry": {"coordinates":[4.6452999115,50.7299613953],"type":"Point"}
}