{
  "type": "Feature",
  "properties": {
    "iso:country":"BE",
    "sg:address":"Veldstraat 21",
    "sg:city":"Oostkamp",
    "sg:orig_category":"Peinture. Rev\u00eatements pour sols and murs",
    "sg:phone":"+32 50 27 76 14",
    "sg:postcode":"8020",
    "sg:province":"West-Vlaanderen",
    "wof:name":"Carrera",
    "wof:placetype":"venue"
},
  "geometry": {"coordinates":[3.2663400173,51.1649703979],"type":"Point"}
}