{
  "type": "Feature",
  "properties": {
    "iso:country":"BE",
    "sg:address":"Rue De Phepet 61",
    "sg:city":"Doische (gochen\u00e9e)",
    "sg:classifiers":[
        {
            "category":"Food & Beverages",
            "subcategory":"Liquor & Beverages",
            "type":"Retail Goods"
        }
    ],
    "sg:phone":"+32 82 67 72 63",
    "sg:postcode":"5680",
    "sg:province":"Namur",
    "sg:tags":[
        "-",
        "spirit",
        "wine"
    ],
    "wof:name":"Laurent P",
    "wof:placetype":"venue"
},
  "geometry": {"coordinates":[4.7607769966,50.1842346191],"type":"Point"}
}