{
  "type": "Feature",
  "properties": {
    "iso:country":"BE",
    "sg:address":"Av Du Progr\u00e8s 9",
    "sg:city":"Alleur",
    "sg:classifiers":[
        {
            "category":"Shopping",
            "type":"Retail Goods"
        }
    ],
    "sg:phone":"+32 4 263 77 28",
    "sg:postcode":"4432",
    "sg:province":"Li\u00e8ge",
    "sg:tags":[
        "metallurgy",
        "finished",
        "-",
        "metalworking",
        "metallic"
    ],
    "wof:name":"Travhydro Sa",
    "wof:placetype":"venue"
},
  "geometry": {"coordinates":[5.5280637741,50.6724205017],"type":"Point"}
}