{
  "type": "Feature",
  "properties": {
    "iso:country":"BE",
    "sg:address":"Avenue Rogier 355",
    "sg:city":"Schaarbeek/schaerbeek",
    "sg:orig_category":"V\u00eatements. V\u00eatements pour Hommes",
    "sg:phone":"+32 2 736 10 67",
    "sg:postcode":"1030",
    "sg:province":"Bruxelles-Capitale",
    "wof:name":"Algotex",
    "wof:placetype":"venue"
},
  "geometry": {"coordinates":[4.3930082321,50.8558082581],"type":"Point"}
}