{
  "type": "Feature",
  "properties": {
    "addr:full":"Spilstraat 2a Maaseik (neeroeteren) Limburg 3680",
    "addr:housenumber":"2a",
    "addr:postcode":"3680",
    "addr:street":"Spilstraat",
    "iso:country":"BE",
    "sg:address":"Spilstraat 2a",
    "sg:city":"Maaseik (neeroeteren)",
    "sg:classifiers":[
        {
            "category":"Bakery",
            "type":"Food & Drink"
        }
    ],
    "sg:phone":"+32 89 86 41 69",
    "sg:postcode":"3680",
    "sg:province":"Limburg",
    "sg:tags":[
        "confectioner",
        "baker"
    ],
    "wof:name":"Buntinx G",
    "wof:placetype":"venue"
},
  "geometry": {"coordinates":[5.791285038,51.0954208374],"type":"Point"}
}