{
  "type": "Feature",
  "properties": {
    "iso:country":"BE",
    "sg:address":"Evendijk West 19",
    "sg:city":"Blankenberge (uitkerke)",
    "sg:classifiers":[
        {
            "category":"Food & Beverages",
            "subcategory":"Fruits & Vegetables",
            "type":"Retail Goods"
        }
    ],
    "sg:phone":"+32 50 41 33 95",
    "sg:postcode":"8370",
    "sg:province":"West-Vlaanderen",
    "sg:tags":[
        "-"
    ],
    "wof:name":"Tanghe-vangoethem Bvba",
    "wof:placetype":"venue"
},
  "geometry": {"coordinates":[3.1370968819,51.305557251],"type":"Point"}
}