{
  "type": "Feature",
  "properties": {
    "addr:full":"Steengroefstraat 40 Koekelberg Bruxelles-Capitale 1081",
    "addr:housenumber":"40",
    "addr:postcode":"1081",
    "addr:street":"Steengroefstraat",
    "iso:country":"BE",
    "sg:address":"Steengroefstraat 40",
    "sg:city":"Koekelberg",
    "sg:orig_category":"Koerierbedrijven",
    "sg:phone":"+32 2 410 17 99",
    "sg:postcode":"1081",
    "sg:province":"Bruxelles-Capitale",
    "wof:name":"El Gibbor\u00b4s Intern. Serv.",
    "wof:placetype":"venue"
},
  "geometry": {"coordinates":[4.3147110939,50.8640213013],"type":"Point"}
}