{
  "type": "Feature",
  "properties": {
    "iso:country":"BE",
    "sg:address":"Rue Jean Deremince 27",
    "sg:city":"Namur",
    "sg:orig_category":"Artiesten and kunstenaars",
    "sg:phone":"+32 81 22 65 65",
    "sg:postcode":"5000",
    "sg:province":"Namur",
    "wof:name":"Guy Longree",
    "wof:placetype":"venue"
},
  "geometry": {"coordinates":[4.9118828773,50.470035553],"type":"Point"}
}