{
  "type": "Feature",
  "properties": {
    "iso:country":"BE",
    "sg:address":"Sint-elooistraat 55",
    "sg:city":"Staden",
    "sg:orig_category":"Producteurs de l\u00e9gumes",
    "sg:phone":"+32 51 70 13 15",
    "sg:postcode":"8840",
    "sg:province":"West-Vlaanderen",
    "wof:name":"Bernadette Pollentier",
    "wof:placetype":"venue"
},
  "geometry": {"coordinates":[2.9876549244,50.9422340393],"type":"Point"}
}