{
  "type": "Feature",
  "properties": {
    "iso:country":"BE",
    "sg:address":"Greefstraat 2",
    "sg:city":"Bocholt",
    "sg:orig_category":"Eleveurs and marchands de porcs",
    "sg:phone":"+32 89 46 55 14",
    "sg:postcode":"3950",
    "sg:province":"Limburg",
    "wof:name":"Theodorus Hendrikx",
    "wof:placetype":"venue"
},
  "geometry": {"coordinates":[5.6100769043,51.1812438965],"type":"Point"}
}