{
  "type": "Feature",
  "properties": {
    "iso:country":"BE",
    "sg:address":"Weidestraat 313",
    "sg:city":"Brugge (assebroek)",
    "sg:classifiers":[
        {
            "category":"Tea Room",
            "subcategory":"None",
            "type":"Food & Drink"
        }
    ],
    "sg:phone":"+32 50 35 40 55",
    "sg:postcode":"8310",
    "sg:province":"West-Vlaanderen",
    "wof:name":"Den Hovenier",
    "wof:placetype":"venue"
},
  "geometry": {"coordinates":[3.2511799335,51.1900100708],"type":"Point"}
}