{
  "type": "Feature",
  "properties": {
    "addr:full":"Hasseltweg 18 Genk Limburg 3600",
    "addr:housenumber":"18",
    "addr:postcode":"3600",
    "addr:street":"Hasseltweg",
    "iso:country":"BE",
    "sg:address":"Hasseltweg 18",
    "sg:city":"Genk",
    "sg:orig_category":"V\u00eatements pour b\u00e9b\u00e9s and enfants. V\u00eatements pour Dames. V\u00eatements pour Hommes",
    "sg:phone":"+32 89 36 29 13",
    "sg:postcode":"3600",
    "sg:province":"Limburg",
    "wof:name":"Jbc Mode",
    "wof:placetype":"venue"
},
  "geometry": {"coordinates":[5.474984169,50.9648399353],"type":"Point"}
}