{
  "type": "Feature",
  "properties": {
    "addr:full":"Rue De Tilleur 29 Li\u00e8ge 1 Li\u00e8ge 4000",
    "addr:housenumber":"29;1",
    "addr:postcode":"4000",
    "addr:street":"Rue De Tilleur",
    "iso:country":"BE",
    "sg:address":"Rue De Tilleur 29",
    "sg:city":"Li\u00e8ge 1",
    "sg:classifiers":[
        {
            "category":"Bakery",
            "type":"Food & Drink"
        }
    ],
    "sg:phone":"+32 4 253 54 53",
    "sg:postcode":"4000",
    "sg:province":"Li\u00e8ge",
    "sg:tags":[
        "confectioner",
        "baker"
    ],
    "wof:name":"Gourmandise (la)",
    "wof:placetype":"venue"
},
  "geometry": {"coordinates":[5.5465731621,50.6315345764],"type":"Point"}
}