{
  "type": "Feature",
  "properties": {
    "iso:country":"BE",
    "sg:address":"Rue P. Mattheussens 60",
    "sg:city":"Evere/evere",
    "sg:orig_category":"Biblioth\u00e8ques and archives publiques",
    "sg:phone":"+32 2 726 87 50",
    "sg:postcode":"1140",
    "sg:province":"Bruxelles-Capitale",
    "wof:name":"Ludo La Boite A Joujoux",
    "wof:placetype":"venue"
},
  "geometry": {"coordinates":[4.3965549469,50.8747673035],"type":"Point"}
}