{
  "type": "Feature",
  "properties": {
    "addr:full":"Crutzenenstraat Hasselt Limburg 3500",
    "addr:postcode":"3500",
    "addr:street":"Crutzenenstraat",
    "iso:country":"BE",
    "sg:address":"Crutzenenstraat",
    "sg:city":"Hasselt",
    "sg:orig_category":"Beheer van afvalopslag- and stortplaatsen",
    "sg:phone":"+32 11 25 45 26",
    "sg:postcode":"3500",
    "sg:province":"Limburg",
    "wof:name":"Containerpark Hasselt",
    "wof:placetype":"venue"
},
  "geometry": {"coordinates":[5.3122601509,50.940120697],"type":"Point"}
}