{
  "type": "Feature",
  "properties": {
    "iso:country":"BE",
    "sg:address":"Magerhillestraat 35",
    "sg:city":"Zedelgem",
    "sg:classifiers":[
        {
            "category":"Communications",
            "type":"Services"
        }
    ],
    "sg:phone":"+32 50 24 09 30",
    "sg:postcode":"8210",
    "sg:province":"West-Vlaanderen",
    "sg:tags":[
        "translator"
    ],
    "wof:name":"Al Suhail A",
    "wof:placetype":"venue"
},
  "geometry": {"coordinates":[3.1458399296,51.1376457214],"type":"Point"}
}