{
  "type": "Feature",
  "properties": {
    "iso:country":"BE",
    "sg:address":"Rue Hardu\u00c9mont 63",
    "sg:city":"Verlaine",
    "sg:orig_category":"Eleveurs and marchands de porcs",
    "sg:phone":"+32 4 259 51 78",
    "sg:postcode":"4537",
    "sg:province":"Li\u00e8ge",
    "wof:name":"Victor Pire",
    "wof:placetype":"venue"
},
  "geometry": {"coordinates":[5.3262968063,50.6288757324],"type":"Point"}
}