{
  "type": "Feature",
  "properties": {
    "addr:full":"Place Bara 14 Bruxelles (anderlecht) Bruxelles-Capitale 1070",
    "addr:housenumber":"14",
    "addr:postcode":"1070",
    "addr:street":"Place Bara",
    "iso:country":"BE",
    "sg:address":"Place Bara 14",
    "sg:city":"Bruxelles (anderlecht)",
    "sg:orig_category":"Non-Classified Establishments",
    "sg:phone":"+32 2 524 39 85",
    "sg:postcode":"1070",
    "sg:province":"Bruxelles-Capitale",
    "wof:name":"Tricot De Bruxelles",
    "wof:placetype":"venue"
},
  "geometry": {"coordinates":[4.3351740837,50.838432312],"type":"Point"}
}