{
  "type": "Feature",
  "properties": {
    "addr:full":"Droogveldstraat 35 Bornem Antwerpen 2880",
    "addr:housenumber":"35",
    "addr:postcode":"2880",
    "addr:street":"Droogveldstraat",
    "iso:country":"BE",
    "sg:address":"Droogveldstraat 35",
    "sg:city":"Bornem",
    "sg:classifiers":[
        {
            "category":"Landmark",
            "subcategory":"Memorial",
            "type":"Public Place"
        }
    ],
    "sg:phone":"+32 52 34 24 37",
    "sg:postcode":"2880",
    "sg:province":"Antwerpen",
    "sg:tags":[
        "-",
        "monument"
    ],
    "wof:name":"Crabbe A",
    "wof:placetype":"venue"
},
  "geometry": {"coordinates":[4.1907191277,51.0675010681],"type":"Point"}
}