{
  "type": "Feature",
  "properties": {
    "iso:country":"BE",
    "sg:address":"Hoge Mauw 7",
    "sg:city":"Arendonk",
    "sg:orig_category":"Goederenvervoer over de weg",
    "sg:phone":"+32 14 67 71 11",
    "sg:postcode":"2370",
    "sg:province":"Antwerpen",
    "wof:name":"Transport Vosters",
    "wof:placetype":"venue"
},
  "geometry": {"coordinates":[5.1114149094,51.3001861572],"type":"Point"}
}