{
  "type": "Feature",
  "properties": {
    "addr:full":"Rue D'orval 170ba Tintigny Luxembourg 6730",
    "addr:postcode":"6730",
    "addr:street":"Rue D'Orval 170Ba",
    "iso:country":"BE",
    "sg:address":"Rue D'orval 170ba",
    "sg:city":"Tintigny",
    "sg:orig_category":"Boissons",
    "sg:phone":"+32 63 44 41 64",
    "sg:postcode":"6730",
    "sg:province":"Luxembourg",
    "wof:name":"Justin Daune-habaru",
    "wof:placetype":"venue"
},
  "geometry": {"coordinates":[5.5135002136,49.6826896667],"type":"Point"}
}