{
  "type": "Feature",
  "properties": {
    "addr:full":"Rue Saint-jacques 3 Tournai Hainaut 7500",
    "addr:housenumber":"3",
    "addr:postcode":"7500",
    "addr:street":"Rue Saint-Jacques",
    "iso:country":"BE",
    "sg:address":"Rue Saint-jacques 3",
    "sg:city":"Tournai",
    "sg:classifiers":[
        {
            "category":"Health Services",
            "subcategory":"Doctor",
            "type":"Services"
        }
    ],
    "sg:phone":"+32 475 68 68 36",
    "sg:postcode":"7500",
    "sg:province":"Hainaut",
    "sg:tags":[
        "medicinephysicians",
        "surgeon"
    ],
    "wof:name":"Delier Caroline",
    "wof:placetype":"venue"
},
  "geometry": {"coordinates":[3.3831529617,50.6098670959],"type":"Point"}
}