{
  "type": "Feature",
  "properties": {
    "addr:full":"Koningsstraat 35 Brussel/bruxelles Bruxelles-Capitale 1000",
    "addr:housenumber":"35",
    "addr:postcode":"1000",
    "addr:street":"Koningsstraat;/",
    "iso:country":"BE",
    "sg:address":"Koningsstraat 35",
    "sg:city":"Brussel/bruxelles",
    "sg:orig_category":"Installatie van houten of kunststof schrijnwerk Vloer- and muurbekleding Woningbouw",
    "sg:phone":"+32 2 219 34 72",
    "sg:postcode":"1000",
    "sg:province":"Bruxelles-Capitale",
    "wof:name":"Profex",
    "wof:placetype":"venue"
},
  "geometry": {"coordinates":[4.3635630608,50.8486061096],"type":"Point"}
}