{
  "type": "Feature",
  "properties": {
    "addr:full":"Doorniksesteenweg 553 Avelgem West-Vlaanderen 8583",
    "addr:housenumber":"553",
    "addr:postcode":"8583",
    "addr:street":"Doorniksesteenweg",
    "iso:country":"BE",
    "sg:address":"Doorniksesteenweg 553",
    "sg:city":"Avelgem",
    "sg:classifiers":[
        {
            "category":"Cafe",
            "type":"Food & Drink"
        }
    ],
    "sg:phone":"+32 56 45 57 03",
    "sg:postcode":"8583",
    "sg:province":"West-Vlaanderen",
    "sg:tags":[
        "caf\u00e9s"
    ],
    "wof:name":"Caf\u00c9 Tijl",
    "wof:placetype":"venue"
},
  "geometry": {"coordinates":[3.4073970318,50.7481842041],"type":"Point"}
}