{
  "type": "Feature",
  "properties": {
    "addr:full":"Nijverheidsweg 85 Ham Limburg 3945",
    "addr:housenumber":"85",
    "addr:postcode":"3945",
    "addr:street":"Nijverheidsweg",
    "iso:country":"BE",
    "sg:address":"Nijverheidsweg 85",
    "sg:city":"Ham",
    "sg:orig_category":"Entretien and r\u00e9parations de voitures. R\u00e9cup\u00e9ration de mati\u00e8res m\u00e9talliques recyclables and d\u00e9moliss",
    "sg:phone":"+32 11 34 59 72",
    "sg:postcode":"3945",
    "sg:province":"Limburg",
    "wof:name":"Hamse Autosloperij",
    "wof:placetype":"venue"
},
  "geometry": {"coordinates":[5.1776199341,51.1046104431],"type":"Point"}
}