{
  "type": "Feature",
  "properties": {
    "iso:country":"BE",
    "sg:address":"Sint-jansstraat 33",
    "sg:city":"Hoegaarden",
    "sg:orig_category":"Entretien and r\u00e9parations de voitures",
    "sg:phone":"+32 16 81 52 97",
    "sg:postcode":"3320",
    "sg:province":"Vlaams-Brabant",
    "wof:name":"Willy Willems",
    "wof:placetype":"venue"
},
  "geometry": {"coordinates":[4.871694088,50.8025665283],"type":"Point"}
}