{
  "type": "Feature",
  "properties": {
    "iso:country":"BE",
    "sg:address":"Baliestraat 28",
    "sg:city":"Gent-centrum",
    "sg:orig_category":"Advocaten and juridische adviseurs Balie van Gent",
    "sg:phone":"+32 9 221 20 15",
    "sg:postcode":"9000",
    "sg:province":"Oost-Vlaanderen",
    "wof:name":"Rummens Mark",
    "wof:placetype":"venue"
},
  "geometry": {"coordinates":[3.7159869671,51.0403785706],"type":"Point"}
}