{
  "type": "Feature",
  "properties": {
    "iso:country":"BE",
    "sg:address":"Avenue G\u00e9n\u00e9ral Dumonceau 15",
    "sg:city":"Bruxelles (forest)",
    "sg:classifiers":[
        {
            "category":"Insurance",
            "subcategory":"Insurance Agent",
            "type":"Services"
        }
    ],
    "sg:phone":"+32 2 376 32 04",
    "sg:postcode":"1190",
    "sg:province":"Bruxelles-Capitale",
    "sg:tags":[
        "broker"
    ],
    "wof:name":"Vanderheyden Et Fils Sprl",
    "wof:placetype":"venue"
},
  "geometry": {"coordinates":[4.3158011436,50.806728363],"type":"Point"}
}