{
  "type": "Feature",
  "properties": {
    "iso:country":"BE",
    "sg:address":"Rue Des Augustins 1",
    "sg:city":"Liege",
    "sg:classifiers":[
        {
            "category":"Restaurant",
            "type":"Food & Drink"
        }
    ],
    "sg:phone":"+32 4 223 12 33",
    "sg:postcode":"4000",
    "sg:province":"Li\u00e8ge",
    "wof:name":"Taverne D'avroy",
    "wof:placetype":"venue"
},
  "geometry": {"coordinates":[5.5673499107,50.6353416443],"type":"Point"}
}