{
  "type": "Feature",
  "properties": {
    "addr:full":"Chauss\u00e9e De Charleroi 90 Charleroi (gilly) Hainaut 6060",
    "addr:housenumber":"90",
    "addr:postcode":"6060",
    "addr:street":"Chausse\u0301E De Charleroi",
    "iso:country":"BE",
    "sg:address":"Chauss\u00e9e De Charleroi 90",
    "sg:city":"Charleroi (gilly)",
    "sg:classifiers":[
        {
            "category":"Personal",
            "subcategory":"Beauty Salon",
            "type":"Services"
        }
    ],
    "sg:phone":"+32 71 41 11 14",
    "sg:postcode":"6060",
    "sg:province":"Hainaut",
    "sg:tags":[
        "lady",
        "-",
        "hairdressing"
    ],
    "wof:name":"Huberty Rolande Sprl",
    "wof:placetype":"venue"
},
  "geometry": {"coordinates":[4.470995903,50.4024276733],"type":"Point"}
}