{
  "type": "Feature",
  "properties": {
    "addr:full":"Dieweg 28 Ukkel/uccle Bruxelles-Capitale 1180",
    "addr:housenumber":"28",
    "addr:postcode":"1180",
    "addr:street":"Dieweg;/",
    "iso:country":"BE",
    "sg:address":"Dieweg 28",
    "sg:city":"Ukkel/uccle",
    "sg:orig_category":"Installation de menuiserie m\u00e9tallique. Appareils de pulv\u00e9risation Fab",
    "sg:phone":"+32 2 375 94 98",
    "sg:postcode":"1180",
    "sg:province":"Bruxelles-Capitale",
    "wof:name":"Safe & Sound",
    "wof:placetype":"venue"
},
  "geometry": {"coordinates":[4.3359088898,50.7919845581],"type":"Point"}
}