{
  "type": "Feature",
  "properties": {
    "iso:country":"BE",
    "sg:address":"Rendries 21",
    "sg:city":"Herne",
    "sg:orig_category":"Eleveurs de bovins",
    "sg:phone":"+32 2 396 20 93",
    "sg:postcode":"1540",
    "sg:province":"Vlaams-Brabant",
    "wof:name":"Colette Durand",
    "wof:placetype":"venue"
},
  "geometry": {"coordinates":[4.0284800529,50.7247543335],"type":"Point"}
}