{
  "type": "Feature",
  "properties": {
    "iso:country":"BE",
    "sg:address":"Chauss\u00e9e D'audenarde 46",
    "sg:city":"Pecq (h\u00e9rinnes-lez-pecq)",
    "sg:classifiers":[
        {
            "category":"Personal",
            "subcategory":"Beauty Salon",
            "type":"Services"
        }
    ],
    "sg:phone":"+32 69 55 71 57",
    "sg:postcode":"7742",
    "sg:province":"Hainaut",
    "wof:name":"Belle Star",
    "wof:placetype":"venue"
},
  "geometry": {"coordinates":[3.3586440086,50.6781234741],"type":"Point"}
}