{
  "type": "Feature",
  "properties": {
    "addr:full":"Rue Neuve 63 Gerpinnes Hainaut 6280",
    "addr:housenumber":"63",
    "addr:postcode":"6280",
    "addr:street":"Rue Neuve;Hainaut",
    "iso:country":"BE",
    "sg:address":"Rue Neuve 63",
    "sg:city":"Gerpinnes",
    "sg:classifiers":[
        {
            "category":"Shopping",
            "subcategory":"Clothing, Apparel, & Fashions",
            "type":"Retail Goods"
        }
    ],
    "sg:phone":"+32 71 45 54 38",
    "sg:postcode":"6280",
    "sg:province":"Hainaut",
    "sg:tags":[
        "-",
        "haberdashery"
    ],
    "wof:name":"Cr\u00e9celle (la)",
    "wof:placetype":"venue"
},
  "geometry": {"coordinates":[4.4711098671,50.3454284668],"type":"Point"}
}