{
  "type": "Feature",
  "properties": {
    "iso:country":"BE",
    "sg:address":"Rue De Chapelle 354",
    "sg:city":"Courcelles (trazegnies)",
    "sg:classifiers":[
        {
            "category":"Retail",
            "subcategory":"Auto Repair",
            "type":"Services"
        }
    ],
    "sg:phone":"+32 64 44 22 26",
    "sg:postcode":"6183",
    "sg:province":"Hainaut",
    "sg:tags":[
        "garage"
    ],
    "wof:name":"Nouwens A Sprl",
    "wof:placetype":"venue"
},
  "geometry": {"coordinates":[4.3051099777,50.4665107727],"type":"Point"}
}