{
  "type": "Feature",
  "properties": {
    "addr:full":"Moorselbaan 150 Aalst Oost-Vlaanderen 9300",
    "addr:housenumber":"150",
    "addr:postcode":"9300",
    "addr:street":"Moorselbaan",
    "iso:country":"BE",
    "sg:address":"Moorselbaan 150",
    "sg:city":"Aalst",
    "sg:orig_category":"Slagers",
    "sg:phone":"+32 53 21 11 44",
    "sg:postcode":"9300",
    "sg:province":"Oost-Vlaanderen",
    "wof:name":"Filip Schout",
    "wof:placetype":"venue"
},
  "geometry": {"coordinates":[4.0530939102,50.9424324036],"type":"Point"}
}