{
  "type": "Feature",
  "properties": {
    "iso:country":"BE",
    "sg:address":"Franchommelaan 22b9",
    "sg:city":"Blankenberge",
    "sg:orig_category":"Herstelling aan huis van huishoudartikelen",
    "sg:phone":"+32 50 42 35 35",
    "sg:postcode":"8370",
    "sg:province":"West-Vlaanderen",
    "wof:name":"Anca Sneldienst",
    "wof:placetype":"venue"
},
  "geometry": {"coordinates":[3.1161949635,51.3126831055],"type":"Point"}
}