{
  "type": "Feature",
  "properties": {
    "iso:country":"BE",
    "sg:address":"Havengeul 10",
    "sg:city":"Nieuwpoort",
    "sg:classifiers":[
        {
            "category":"Bars & Pubs",
            "type":"Food & Drink"
        }
    ],
    "sg:phone":"+32 58 24 18 24",
    "sg:postcode":"8620",
    "sg:province":"West-Vlaanderen",
    "sg:tags":[
        "tavern"
    ],
    "wof:name":"Zeegat ('t)",
    "wof:placetype":"venue"
},
  "geometry": {"coordinates":[2.7394759655,51.1401977539],"type":"Point"}
}