{
  "type": "Feature",
  "properties": {
    "iso:country":"BE",
    "sg:address":"Hanewijk 71",
    "sg:city":"Rotselaar",
    "sg:orig_category":"Producteurs de l\u00e9gumes",
    "sg:phone":"+32 16 60 63 57",
    "sg:postcode":"3118",
    "sg:province":"Vlaams-Brabant",
    "wof:name":"Marc Durinck",
    "wof:placetype":"venue"
},
  "geometry": {"coordinates":[4.6859478951,50.9743232727],"type":"Point"}
}