{
  "type": "Feature",
  "properties": {
    "addr:full":"Colignonplein 10 Schaarbeek/schaerbeek Bruxelles-Capitale 1030",
    "addr:housenumber":"10",
    "addr:postcode":"1030",
    "addr:street":"Colignonplein",
    "iso:country":"BE",
    "sg:address":"Colignonplein 10",
    "sg:city":"Schaarbeek/schaerbeek",
    "sg:orig_category":"Boekhouders",
    "sg:phone":"+32 2 646 28 02",
    "sg:postcode":"1030",
    "sg:province":"Bruxelles-Capitale",
    "wof:name":"Renaud Nicolas",
    "wof:placetype":"venue"
},
  "geometry": {"coordinates":[4.3736901283,50.866859436],"type":"Point"}
}