{
  "type": "Feature",
  "properties": {
    "addr:full":"Mellestraat 244 Kortrijk West-Vlaanderen 8501",
    "addr:housenumber":"244",
    "addr:postcode":"8501",
    "addr:street":"Mellestraat",
    "iso:country":"BE",
    "sg:address":"Mellestraat 244",
    "sg:city":"Kortrijk",
    "sg:orig_category":"Bouwmaterialen Gh Dakwerken",
    "sg:phone":"+32 56 35 12 93",
    "sg:postcode":"8501",
    "sg:province":"West-Vlaanderen",
    "wof:name":"Asphaltex",
    "wof:placetype":"venue"
},
  "geometry": {"coordinates":[3.2261750698,50.856086731],"type":"Point"}
}