{
  "type": "Feature",
  "properties": {
    "iso:country":"BE",
    "sg:address":"Avenue De Longwy 343",
    "sg:city":"Arlon",
    "sg:orig_category":"D\u00e9taillants en pi\u00e8ces and accessoires de voitures. Mat\u00e9riel de T\u00e9l\u00e9communication",
    "sg:phone":"+32 63 22 58 60",
    "sg:postcode":"6700",
    "sg:province":"Luxembourg",
    "wof:name":"Electrauto",
    "wof:placetype":"venue"
},
  "geometry": {"coordinates":[5.824075222,49.6715278625],"type":"Point"}
}