{
  "type": "Feature",
  "properties": {
    "addr:full":"Ch De Tongres 255 Rocourt Li\u00e8ge 4000",
    "addr:housenumber":"255",
    "addr:postcode":"4000",
    "addr:street":"Ch De Tongres",
    "iso:country":"BE",
    "sg:address":"Ch De Tongres 255",
    "sg:city":"Rocourt",
    "sg:classifiers":[
        {
            "category":"Professional",
            "subcategory":"Engineering",
            "type":"Services"
        }
    ],
    "sg:phone":"+32 4 364 00 20",
    "sg:postcode":"4000",
    "sg:province":"Li\u00e8ge",
    "sg:tags":[
        "machine",
        "-",
        "mechanical"
    ],
    "wof:name":"Massart Distribution Sa",
    "wof:placetype":"venue"
},
  "geometry": {"coordinates":[5.5501008034,50.6697731018],"type":"Point"}
}