{
  "type": "Feature",
  "properties": {
    "addr:full":"Rue De L'europe 17 Frameries Hainaut 7080",
    "addr:housenumber":"17",
    "addr:postcode":"7080",
    "addr:street":"Rue De L'Europe",
    "iso:country":"BE",
    "sg:address":"Rue De L'europe 17",
    "sg:city":"Frameries",
    "sg:classifiers":[
        {
            "category":"Transit Center",
            "subcategory":"Freight",
            "type":"Transportation"
        }
    ],
    "sg:phone":"+32 65 61 36 36",
    "sg:postcode":"7080",
    "sg:province":"Hainaut",
    "sg:tags":[
        "metallurgy",
        "pipe",
        "metalworking",
        "sheet"
    ],
    "wof:name":"Pipe Construct Sa",
    "wof:placetype":"venue"
},
  "geometry": {"coordinates":[3.9138469696,50.4098815918],"type":"Point"}
}