{
  "type": "Feature",
  "properties": {
    "addr:full":"Ambachtenstraat 5 Izegem West-Vlaanderen 8870",
    "addr:housenumber":"5",
    "addr:postcode":"8870",
    "addr:street":"Ambachtenstraat",
    "iso:country":"BE",
    "sg:address":"Ambachtenstraat 5",
    "sg:city":"Izegem",
    "sg:classifiers":[
        {
            "category":"Home & Garden",
            "subcategory":"Building Materials",
            "type":"Retail Goods"
        }
    ],
    "sg:postcode":"8870",
    "sg:province":"West-Vlaanderen",
    "sg:tags":[
        "window"
    ],
    "wof:name":"Haki",
    "wof:placetype":"venue"
},
  "geometry": {"coordinates":[3.1865620613,50.9185218811],"type":"Point"}
}