{
  "type": "Feature",
  "properties": {
    "iso:country":"BE",
    "sg:address":"Rue Meuchemen 7",
    "sg:city":"Baelen",
    "sg:orig_category":"Woningbouw",
    "sg:phone":"+32 87 88 07 34",
    "sg:postcode":"4837",
    "sg:province":"Li\u00e8ge",
    "wof:name":"Creutz M",
    "wof:placetype":"venue"
},
  "geometry": {"coordinates":[5.9445290565,50.6458892822],"type":"Point"}
}