{
  "type": "Feature",
  "properties": {
    "iso:country":"BE",
    "sg:address":"Hekkestraat 45",
    "sg:city":"Aalst (hofstade)",
    "sg:classifiers":[
        {
            "category":"Freight",
            "type":"Transportation"
        }
    ],
    "sg:phone":"+32 53 21 22 60",
    "sg:postcode":"9308",
    "sg:province":"Oost-Vlaanderen",
    "sg:tags":[
        "-",
        "transport"
    ],
    "wof:name":"Godaert Transport Bvba",
    "wof:placetype":"venue"
},
  "geometry": {"coordinates":[4.0347590446,50.9603500366],"type":"Point"}
}