{
  "type": "Feature",
  "properties": {
    "addr:full":"Route D'amonines 1 Rendeux (beffe) Luxembourg 6987",
    "addr:housenumber":"1",
    "addr:postcode":"6987",
    "addr:street":"Route D'Amonines",
    "iso:country":"BE",
    "sg:address":"Route D'amonines 1",
    "sg:city":"Rendeux (beffe)",
    "sg:classifiers":[
        {
            "category":"Retail",
            "subcategory":"Animal Services",
            "type":"Services"
        }
    ],
    "sg:phone":"+32 84 47 76 67",
    "sg:postcode":"6987",
    "sg:province":"Luxembourg",
    "sg:tags":[
        "grooming",
        "-",
        "dog"
    ],
    "wof:name":"Cool Dogs",
    "wof:placetype":"venue"
},
  "geometry": {"coordinates":[5.5277662277,50.2508888245],"type":"Point"}
}