{
  "type": "Feature",
  "properties": {
    "addr:full":"Antwerpsesteenweg 26 Lier Antwerpen 2500",
    "addr:housenumber":"26",
    "addr:postcode":"2500",
    "addr:street":"Antwerpsesteenweg",
    "iso:country":"BE",
    "sg:address":"Antwerpsesteenweg 26",
    "sg:city":"Lier",
    "sg:classifiers":[
        {
            "category":"Health Services",
            "subcategory":"Health Practitioner",
            "type":"Services"
        }
    ],
    "sg:phone":"+32 3 480 96 11",
    "sg:postcode":"2500",
    "sg:province":"Antwerpen",
    "sg:tags":[
        "physiotherapist"
    ],
    "wof:name":"De Wachter P",
    "wof:placetype":"venue"
},
  "geometry": {"coordinates":[4.5608692169,51.137298584],"type":"Point"}
}