{
  "type": "Feature",
  "properties": {
    "iso:country":"BE",
    "sg:address":"Stationsstraat 7",
    "sg:city":"Diksmuide",
    "sg:classifiers":[
        {
            "category":"Health Services",
            "subcategory":"Dentist",
            "type":"Services"
        }
    ],
    "sg:phone":"+32 51 50 33 49",
    "sg:postcode":"8600",
    "sg:province":"West-Vlaanderen",
    "wof:name":"Callewaert P",
    "wof:placetype":"venue"
},
  "geometry": {"coordinates":[2.8681468964,51.0331878662],"type":"Point"}
}