{
  "type": "Feature",
  "properties": {
    "iso:country":"BE",
    "sg:address":"Rue Champelet 26b1",
    "sg:city":"La Louviere",
    "sg:orig_category":"Woningbouw",
    "sg:phone":"+32 64 55 92 22",
    "sg:postcode":"7100",
    "sg:province":"Hainaut",
    "wof:name":"Israel Boutet",
    "wof:placetype":"venue"
},
  "geometry": {"coordinates":[4.1850848198,50.4748649597],"type":"Point"}
}