{
  "type": "Feature",
  "properties": {
    "addr:full":"Keistraat 143 De Pinte Oost-Vlaanderen 9840",
    "addr:housenumber":"143",
    "addr:postcode":"9840",
    "addr:street":"Keistraat",
    "iso:country":"BE",
    "sg:address":"Keistraat 143",
    "sg:city":"De Pinte",
    "sg:classifiers":[
        {
            "category":"Professional",
            "subcategory":"Engineering",
            "type":"Services"
        }
    ],
    "sg:phone":"+32 9 385 34 49",
    "sg:postcode":"9840",
    "sg:province":"Oost-Vlaanderen",
    "sg:tags":[
        "-"
    ],
    "wof:name":"A.p.d. Zonnekeyn",
    "wof:placetype":"venue"
},
  "geometry": {"coordinates":[3.6485390663,51.0043296814],"type":"Point"}
}