{
  "type": "Feature",
  "properties": {
    "addr:full":"Grote Veldstraat 181 Staden West-Vlaanderen 8840",
    "addr:housenumber":"181",
    "addr:postcode":"8840",
    "addr:street":"Grote Veldstraat",
    "iso:country":"BE",
    "sg:address":"Grote Veldstraat 181",
    "sg:city":"Staden",
    "sg:orig_category":"Producteurs de l\u00e9gumes",
    "sg:phone":"+32 51 70 13 27",
    "sg:postcode":"8840",
    "sg:province":"West-Vlaanderen",
    "wof:name":"Patrick Obin",
    "wof:placetype":"venue"
},
  "geometry": {"coordinates":[3.0204670429,50.9451446533],"type":"Point"}
}