{
  "type": "Feature",
  "properties": {
    "addr:full":"Meldertsebaan 39 Lummen (meldert) Limburg 3560",
    "addr:housenumber":"39",
    "addr:postcode":"3560",
    "addr:street":"Meldertsebaan",
    "iso:country":"BE",
    "sg:address":"Meldertsebaan 39",
    "sg:city":"Lummen (meldert)",
    "sg:orig_category":"Non-Classified Establishments",
    "sg:phone":"+32 13 31 53 33",
    "sg:postcode":"3560",
    "sg:province":"Limburg",
    "wof:name":"Porters G",
    "wof:placetype":"venue"
},
  "geometry": {"coordinates":[5.1252360344,51.0118980408],"type":"Point"}
}