{
  "type": "Feature",
  "properties": {
    "addr:full":"Reperstraat 191 Izegem West-Vlaanderen 8870",
    "addr:housenumber":"191",
    "addr:postcode":"8870",
    "addr:street":"Reperstraat",
    "iso:country":"BE",
    "sg:address":"Reperstraat 191",
    "sg:city":"Izegem",
    "sg:classifiers":[
        {
            "category":"Building & Trades",
            "subcategory":"Landscaping Services",
            "type":"Services"
        }
    ],
    "sg:phone":"+32 51 30 16 77",
    "sg:postcode":"8870",
    "sg:province":"West-Vlaanderen",
    "sg:tags":[
        "gardening",
        "garden",
        "maintenance"
    ],
    "wof:name":"Vandeweghe Tuinen",
    "wof:placetype":"venue"
},
  "geometry": {"coordinates":[3.2257230282,50.9453392029],"type":"Point"}
}