{
  "type": "Feature",
  "properties": {
    "iso:country":"BE",
    "sg:address":"Hertogweg 25",
    "sg:city":"Wezembeek-oppem",
    "sg:orig_category":"Opsporingsdiensten and detectivebureaus Verzekeringsmakelaars and experts",
    "sg:phone":"+32 2 768 19 80",
    "sg:postcode":"1970",
    "sg:province":"Vlaams-Brabant",
    "wof:name":"Bureau X. Ghion",
    "wof:placetype":"venue"
},
  "geometry": {"coordinates":[4.5008091927,50.8276939392],"type":"Point"}
}