{
  "type": "Feature",
  "properties": {
    "addr:full":"Pol Van Ostaijenstraat 33 Wevelgem (gullegem) West-Vlaanderen 8560",
    "addr:housenumber":"33",
    "addr:postcode":"8560",
    "addr:street":"Van Ostaijenstraat",
    "iso:country":"BE",
    "sg:address":"Pol Van Ostaijenstraat 33",
    "sg:city":"Wevelgem (gullegem)",
    "sg:classifiers":[
        {
            "category":"Professional",
            "subcategory":"Computer Services",
            "type":"Services"
        }
    ],
    "sg:phone":"+32 475 74 30 77",
    "sg:postcode":"8560",
    "sg:province":"West-Vlaanderen",
    "sg:tags":[
        "-",
        "processing",
        "data"
    ],
    "wof:name":"D-e-h-systems",
    "wof:placetype":"venue"
},
  "geometry": {"coordinates":[3.2007501125,50.8352203369],"type":"Point"}
}