{
  "type": "Feature",
  "properties": {
    "iso:country":"BE",
    "sg:address":"Stationsstraat 210",
    "sg:city":"Oostkamp",
    "sg:classifiers":[
        {
            "category":"Building & Trades",
            "subcategory":"Landscaping Services",
            "type":"Services"
        }
    ],
    "sg:phone":"+32 50 82 23 35",
    "sg:postcode":"8020",
    "sg:province":"West-Vlaanderen",
    "sg:tags":[
        "nurseryman"
    ],
    "wof:name":"Standaert-lenaers Bvba",
    "wof:placetype":"venue"
},
  "geometry": {"coordinates":[3.2494499683,51.1531486511],"type":"Point"}
}