{
  "type": "Feature",
  "properties": {
    "iso:country":"BE",
    "sg:address":"Rijt 6",
    "sg:city":"Tessenderlo",
    "sg:orig_category":"Artsen and specialisten",
    "sg:phone":"+32 13 66 89 89",
    "sg:postcode":"3980",
    "sg:province":"Limburg",
    "wof:name":"Robby Thoeng",
    "wof:placetype":"venue"
},
  "geometry": {"coordinates":[5.0887589455,51.0745239258],"type":"Point"}
}