{
  "type": "Feature",
  "properties": {
    "addr:full":"Rue De Verviers 10 Chapelle-lez-herlaimont Hainaut 7160",
    "addr:housenumber":"10",
    "addr:postcode":"7160",
    "addr:street":"Rue De Verviers",
    "iso:country":"BE",
    "sg:address":"Rue De Verviers 10",
    "sg:city":"Chapelle-lez-herlaimont",
    "sg:classifiers":[
        {
            "category":"Education",
            "subcategory":"School",
            "type":"Public Place"
        }
    ],
    "sg:phone":"+32 64 44 78 80",
    "sg:postcode":"7160",
    "sg:province":"Hainaut",
    "sg:tags":[
        "primary"
    ],
    "wof:name":"Ecole Libre",
    "wof:placetype":"venue"
},
  "geometry": {"coordinates":[4.2875738144,50.4665641785],"type":"Point"}
}