{
  "type": "Feature",
  "properties": {
    "addr:full":"Diestsesteenweg 67 Tielt-winge (tielt) Vlaams-Brabant 3390",
    "addr:housenumber":"67",
    "addr:postcode":"3390",
    "addr:street":"Diestsesteenweg",
    "iso:country":"BE",
    "sg:address":"Diestsesteenweg 67",
    "sg:city":"Tielt-winge (tielt)",
    "sg:classifiers":[
        {
            "category":"Building & Trades",
            "subcategory":"Equipment Rental",
            "type":"Services"
        }
    ],
    "sg:phone":"+32 16 64 06 68",
    "sg:postcode":"3390",
    "sg:province":"Vlaams-Brabant",
    "sg:tags":[
        "fried",
        "supply",
        "-",
        "stand",
        "potato"
    ],
    "wof:name":"Grootkeukentechniek V.d.m. Bvba",
    "wof:placetype":"venue"
},
  "geometry": {"coordinates":[4.945702076,50.9368743896],"type":"Point"}
}