{
  "type": "Feature",
  "properties": {
    "iso:country":"BE",
    "sg:address":"Rue Du Cheval Blanc 5",
    "sg:city":"Bassenge (glons)",
    "sg:classifiers":[
        {
            "category":"Banks & Credit Unions",
            "subcategory":"Bank",
            "type":"Services"
        }
    ],
    "sg:phone":"+32 4 286 29 64",
    "sg:postcode":"4690",
    "sg:province":"Li\u00e8ge",
    "sg:tags":[
        "savings-banks"
    ],
    "wof:name":"Dawance M",
    "wof:placetype":"venue"
},
  "geometry": {"coordinates":[5.5645399094,50.7530708313],"type":"Point"}
}