{
  "type": "Feature",
  "properties": {
    "iso:country":"BE",
    "sg:address":"Broekstraat 15",
    "sg:city":"Sint-amands",
    "sg:orig_category":"D\u00e9corateurs d'int\u00e9rieur",
    "sg:phone":"+32 52 33 36 93",
    "sg:postcode":"2890",
    "sg:province":"Antwerpen",
    "wof:name":"Kathleen Duthoo",
    "wof:placetype":"venue"
},
  "geometry": {"coordinates":[4.2629561424,51.0414581299],"type":"Point"}
}