{
  "type": "Feature",
  "properties": {
    "iso:country":"BE",
    "sg:address":"Kalkovenlaan 15",
    "sg:city":"Merchtem",
    "sg:classifiers":[
        {
            "category":"Retail",
            "subcategory":"Veterinary Services",
            "type":"Services"
        }
    ],
    "sg:phone":"+32 52 37 45 82",
    "sg:postcode":"1785",
    "sg:province":"Vlaams-Brabant",
    "sg:tags":[
        "veterinarian"
    ],
    "wof:name":"De Bosscher F",
    "wof:placetype":"venue"
},
  "geometry": {"coordinates":[4.2349061966,50.952129364],"type":"Point"}
}