{
  "type": "Feature",
  "properties": {
    "iso:country":"BE",
    "sg:address":"Wisselstraat 9",
    "sg:city":"Beringen (paal)",
    "sg:classifiers":[
        {
            "category":"Health Services",
            "subcategory":"Health Practitioner",
            "type":"Services"
        }
    ],
    "sg:phone":"+32 475 33 05 45",
    "sg:postcode":"3583",
    "sg:province":"Limburg",
    "sg:tags":[
        "dietitian"
    ],
    "wof:name":"Nijs S",
    "wof:placetype":"venue"
},
  "geometry": {"coordinates":[5.1706700325,51.0389442444],"type":"Point"}
}