{
  "type": "Feature",
  "properties": {
    "iso:country":"BE",
    "sg:address":"Rue Du Saulchoir 56",
    "sg:city":"Tournai",
    "sg:orig_category":"Entreprises de travail adapt\u00e9",
    "sg:phone":"+32 69 23 44 39",
    "sg:postcode":"7540",
    "sg:province":"Hainaut",
    "wof:name":"Les Erables",
    "wof:placetype":"venue"
},
  "geometry": {"coordinates":[3.4015510082,50.6260490417],"type":"Point"}
}