{
  "type": "Feature",
  "properties": {
    "addr:full":"Stationsstraat 40 Eeklo Oost-Vlaanderen 9900",
    "addr:housenumber":"40",
    "addr:postcode":"9900",
    "addr:street":"Stationsstraat",
    "iso:country":"BE",
    "sg:address":"Stationsstraat 40",
    "sg:city":"Eeklo",
    "sg:orig_category":"Pain, p\u00e2tisseries and confiseries",
    "sg:phone":"+32 9 378 24 23",
    "sg:postcode":"9900",
    "sg:province":"Oost-Vlaanderen",
    "wof:name":"T. Dewilde",
    "wof:placetype":"venue"
},
  "geometry": {"coordinates":[3.5697829723,51.1828193665],"type":"Point"}
}