{
  "type": "Feature",
  "properties": {
    "addr:full":"Molenhoekstraat 28 Sint-gillis-waas Oost-Vlaanderen 9170",
    "addr:housenumber":"28",
    "addr:postcode":"9170",
    "addr:street":"Molenhoekstraat",
    "iso:country":"BE",
    "sg:address":"Molenhoekstraat 28",
    "sg:city":"Sint-gillis-waas",
    "sg:orig_category":"Eleveurs de bovins",
    "sg:phone":"+32 3 773 53 66",
    "sg:postcode":"9170",
    "sg:province":"Oost-Vlaanderen",
    "wof:name":"Tom Verhaert",
    "wof:placetype":"venue"
},
  "geometry": {"coordinates":[4.1423239708,51.276260376],"type":"Point"}
}