{
  "type": "Feature",
  "properties": {
    "iso:country":"BE",
    "sg:address":"Hisselsgasse 19",
    "sg:city":"Eupen",
    "sg:classifiers":[
        {
            "category":"Real Estate",
            "subcategory":"Architect",
            "type":"Services"
        }
    ],
    "sg:phone":"+32 87 74 35 09",
    "sg:postcode":"4700",
    "sg:province":"Li\u00e8ge",
    "wof:name":"Korvorst H",
    "wof:placetype":"venue"
},
  "geometry": {"coordinates":[6.0376601219,50.6313018799],"type":"Point"}
}