{
  "type": "Feature",
  "properties": {
    "addr:full":"Kabbeekvest-breughelhof 115 Tienen Vlaams-Brabant 3300",
    "addr:housenumber":"115",
    "addr:postcode":"3300",
    "iso:country":"BE",
    "sg:address":"Kabbeekvest-breughelhof 115",
    "sg:city":"Tienen",
    "sg:orig_category":"Krantenwinkels Rookartikelen",
    "sg:phone":"+32 16 81 80 41",
    "sg:postcode":"3300",
    "sg:province":"Vlaams-Brabant",
    "wof:name":"Monballieu",
    "wof:placetype":"venue"
},
  "geometry": {"coordinates":[4.9390950203,50.8126144409],"type":"Point"}
}