{
  "type": "Feature",
  "properties": {
    "iso:country":"BE",
    "sg:address":"Rue De Wellin 96",
    "sg:city":"Beauraing (pondr\u00f4me)",
    "sg:classifiers":[
        {
            "category":"Health Services",
            "subcategory":"Dentist",
            "type":"Services"
        }
    ],
    "sg:phone":"+32 82 71 32 93",
    "sg:postcode":"5574",
    "sg:province":"Namur",
    "wof:name":"Hanssens Fran\u00e7oise",
    "wof:placetype":"venue"
},
  "geometry": {"coordinates":[5.0176677704,50.0966415405],"type":"Point"}
}