{
  "type": "Feature",
  "properties": {
    "addr:full":"Rue Des Forges 7 Havelange (verl\u00e9e) Namur 5370",
    "addr:housenumber":"7",
    "addr:postcode":"5370",
    "addr:street":"Rue Des Forges",
    "iso:country":"BE",
    "sg:address":"Rue Des Forges 7",
    "sg:city":"Havelange (verl\u00e9e)",
    "sg:classifiers":[
        {
            "category":"Home & Garden",
            "subcategory":"Garden Supply",
            "type":"Retail Goods"
        }
    ],
    "sg:phone":"+32 83 63 34 12",
    "sg:postcode":"5370",
    "sg:province":"Namur",
    "sg:tags":[
        "machine",
        "agricultural",
        "-"
    ],
    "wof:name":"Lecomte Sa",
    "wof:placetype":"venue"
},
  "geometry": {"coordinates":[5.2412161827,50.387878418],"type":"Point"}
}