{
  "type": "Feature",
  "properties": {
    "addr:full":"Nieuwdorp 10 Peer Limburg 3990",
    "addr:housenumber":"10",
    "addr:postcode":"3990",
    "addr:street":"Nieuwdorp",
    "iso:country":"BE",
    "sg:address":"Nieuwdorp 10",
    "sg:city":"Peer",
    "sg:orig_category":"Eleveurs de bovins",
    "sg:phone":"+32 11 79 13 66",
    "sg:postcode":"3990",
    "sg:province":"Limburg",
    "wof:name":"Jacobus Lemmens",
    "wof:placetype":"venue"
},
  "geometry": {"coordinates":[5.4571352005,51.0936851501],"type":"Point"}
}