{
  "type": "Feature",
  "properties": {
    "addr:full":"Rue Emile Vandervelde 68 Celles (borlez) Li\u00e8ge 4317",
    "addr:housenumber":"68",
    "addr:postcode":"4317",
    "addr:street":"Rue Emile Vandervelde",
    "iso:country":"BE",
    "sg:address":"Rue Emile Vandervelde 68",
    "sg:city":"Celles (borlez)",
    "sg:classifiers":[
        {
            "category":"Professional",
            "subcategory":"Computer Services",
            "type":"Services"
        }
    ],
    "sg:phone":"+32 19 56 69 95",
    "sg:postcode":"4317",
    "sg:province":"Li\u00e8ge",
    "sg:tags":[
        "-",
        "processing",
        "data",
        "software"
    ],
    "wof:name":"Archibel",
    "wof:placetype":"venue"
},
  "geometry": {"coordinates":[5.2618951797,50.6657218933],"type":"Point"}
}