{
  "type": "Feature",
  "properties": {
    "iso:country":"BE",
    "sg:address":"Molenveld 55",
    "sg:city":"Heusden-zolder (zolder)",
    "sg:classifiers":[
        {
            "category":"Building & Trades",
            "subcategory":"Landscaping Services",
            "type":"Services"
        }
    ],
    "sg:phone":"+32 11 42 61 11",
    "sg:postcode":"3550",
    "sg:province":"Limburg",
    "sg:tags":[
        "architect",
        "landscape"
    ],
    "wof:name":"Paelinck Viviane",
    "wof:placetype":"venue"
},
  "geometry": {"coordinates":[5.3126449585,51.026966095],"type":"Point"}
}