{
  "type": "Feature",
  "properties": {
    "addr:full":"Rue Des Bluets 55 Charleroi Hainaut 6030",
    "addr:housenumber":"55",
    "addr:postcode":"6030",
    "addr:street":"Rue Des Bluets;Hainaut",
    "iso:country":"BE",
    "sg:address":"Rue Des Bluets 55",
    "sg:city":"Charleroi",
    "sg:classifiers":[
        {
            "category":"Insurance",
            "subcategory":"Insurance Agent",
            "type":"Services"
        }
    ],
    "sg:phone":"+32 71 52 69 33",
    "sg:postcode":"6030",
    "sg:province":"Hainaut",
    "sg:tags":[
        "verzekeringsmakelaars",
        "expert"
    ],
    "wof:name":"Leon Michel",
    "wof:placetype":"venue"
},
  "geometry": {"coordinates":[4.3660511971,50.4093093872],"type":"Point"}
}