{
  "type": "Feature",
  "properties": {
    "addr:full":"Rue Du Commerce 58 Ciney Namur 5590",
    "addr:housenumber":"58",
    "addr:postcode":"5590",
    "addr:street":"Rue Du Commerce",
    "iso:country":"BE",
    "sg:address":"Rue Du Commerce 58",
    "sg:city":"Ciney",
    "sg:orig_category":"M\u00e9decins and sp\u00e9cialistes. Parfumeries. Articles m\u00e9dicaux and orthop\u00e9diques",
    "sg:phone":"+32 83 21 34 60",
    "sg:postcode":"5590",
    "sg:province":"Namur",
    "wof:name":"Medicorps",
    "wof:placetype":"venue"
},
  "geometry": {"coordinates":[5.0980620384,50.2936096191],"type":"Point"}
}