{
  "type": "Feature",
  "properties": {
    "addr:full":"Keyerberg 1b Roosdaal Vlaams-Brabant 1760",
    "addr:housenumber":"1b",
    "addr:postcode":"1760",
    "addr:street":"Keyerberg",
    "iso:country":"BE",
    "sg:address":"Keyerberg 1b",
    "sg:city":"Roosdaal",
    "sg:orig_category":"Verhuur diversen Winkelinrichting and handelsuitrusting Gh",
    "sg:phone":"+32 54 33 28 64",
    "sg:postcode":"1760",
    "sg:province":"Vlaams-Brabant",
    "wof:name":"Animo Prom",
    "wof:placetype":"venue"
},
  "geometry": {"coordinates":[4.1235151291,50.8384437561],"type":"Point"}
}