{
  "type": "Feature",
  "properties": {
    "addr:full":"Vlaamsesteenweg 102 Brussel/bruxelles Bruxelles-Capitale 1000",
    "addr:housenumber":"102",
    "addr:postcode":"1000",
    "addr:street":"Vlaamsesteenweg;/",
    "iso:country":"BE",
    "sg:address":"Vlaamsesteenweg 102",
    "sg:city":"Brussel/bruxelles",
    "sg:orig_category":"Apotheken",
    "sg:phone":"+32 2 513 36 92",
    "sg:postcode":"1000",
    "sg:province":"Bruxelles-Capitale",
    "wof:name":"Khalid Channaoui",
    "wof:placetype":"venue"
},
  "geometry": {"coordinates":[4.3457040787,50.8526382446],"type":"Point"}
}