{
  "type": "Feature",
  "properties": {
    "iso:country":"BE",
    "sg:address":"Jan Van Hortenlaan 3",
    "sg:city":"Tervuren (vossem)",
    "sg:classifiers":[
        {
            "category":"Banks & Credit Unions",
            "subcategory":"Investment Brokerage",
            "type":"Services"
        }
    ],
    "sg:phone":"+32 2 767 93 34",
    "sg:postcode":"3080",
    "sg:province":"Vlaams-Brabant",
    "sg:tags":[
        "auditor"
    ],
    "wof:name":"Morris K",
    "wof:placetype":"venue"
},
  "geometry": {"coordinates":[4.5613098145,50.8407478333],"type":"Point"}
}