{
  "type": "Feature",
  "properties": {
    "addr:full":"Rue De Maredsous 15 Anh\u00e9e (den\u00e9e) Namur 5537",
    "addr:housenumber":"15",
    "addr:postcode":"5537",
    "addr:street":"Rue De Maredsous",
    "iso:country":"BE",
    "sg:address":"Rue De Maredsous 15",
    "sg:city":"Anh\u00e9e (den\u00e9e)",
    "sg:classifiers":[
        {
            "category":"Government",
            "subcategory":"Post Office",
            "type":"Public Place"
        }
    ],
    "sg:phone":"+32 82 69 83 50",
    "sg:postcode":"5537",
    "sg:province":"Namur",
    "sg:tags":[
        "base",
        "data"
    ],
    "wof:name":"Futurtalent Emcma Asbl",
    "wof:placetype":"venue"
},
  "geometry": {"coordinates":[4.7640957832,50.2988243103],"type":"Point"}
}