{
  "type": "Feature",
  "properties": {
    "iso:country":"BE",
    "sg:address":"Herkenrodesingel 10",
    "sg:city":"Hasselt",
    "sg:classifiers":[
        {
            "category":"Communications",
            "subcategory":"Radio Station",
            "type":"Services"
        }
    ],
    "sg:phone":"+32 11 87 83 30",
    "sg:postcode":"3500",
    "sg:province":"Limburg",
    "sg:tags":[
        "diffusion",
        "production",
        "de",
        "programme"
    ],
    "wof:name":"Teletekst/telekrant",
    "wof:placetype":"venue"
},
  "geometry": {"coordinates":[5.3260068893,50.9430122375],"type":"Point"}
}