{
  "type": "Feature",
  "properties": {
    "addr:full":"Kasteeldreef 13 Wielsbeke West-Vlaanderen 8710",
    "addr:housenumber":"13",
    "addr:postcode":"8710",
    "addr:street":"Kasteeldreef;West-Vlaanderen",
    "iso:country":"BE",
    "sg:address":"Kasteeldreef 13",
    "sg:city":"Wielsbeke",
    "sg:classifiers":[
        {
            "category":"Retail",
            "subcategory":"Veterinary Services",
            "type":"Services"
        }
    ],
    "sg:phone":"+32 56 66 68 09",
    "sg:postcode":"8710",
    "sg:province":"West-Vlaanderen",
    "sg:tags":[
        "veterinarian"
    ],
    "wof:name":"Van Daele J",
    "wof:placetype":"venue"
},
  "geometry": {"coordinates":[3.3762829304,50.9088478088],"type":"Point"}
}