{
  "type": "Feature",
  "properties": {
    "iso:country":"BE",
    "sg:address":"Stijn Streuvelsstraat 5",
    "sg:city":"Nazareth (eke)",
    "sg:classifiers":[
        {
            "category":"Retail",
            "subcategory":"Repair Shop",
            "type":"Services"
        }
    ],
    "sg:phone":"+32 9 385 66 25",
    "sg:postcode":"9810",
    "sg:province":"Oost-Vlaanderen",
    "sg:tags":[
        "radio",
        "television",
        "-",
        "maintenance"
    ],
    "wof:name":"Televideom",
    "wof:placetype":"venue"
},
  "geometry": {"coordinates":[3.6398019791,50.9602737427],"type":"Point"}
}