{
  "type": "Feature",
  "properties": {
    "iso:country":"BE",
    "sg:address":"Violierstraat 2",
    "sg:city":"Lendelede",
    "sg:classifiers":[
        {
            "category":"Cafe",
            "type":"Food & Drink"
        }
    ],
    "sg:phone":"+32 51 31 30 46",
    "sg:postcode":"8860",
    "sg:province":"West-Vlaanderen",
    "sg:tags":[
        "caf\u00e9s"
    ],
    "wof:name":"Rita Vanlerberghe",
    "wof:placetype":"venue"
},
  "geometry": {"coordinates":[3.2398290634,50.883769989],"type":"Point"}
}