{
  "type": "Feature",
  "properties": {
    "addr:full":"Grendelbaan 111 Diepenbeek Limburg 3590",
    "addr:housenumber":"111",
    "addr:postcode":"3590",
    "addr:street":"Grendelbaan",
    "iso:country":"BE",
    "sg:address":"Grendelbaan 111",
    "sg:city":"Diepenbeek",
    "sg:classifiers":[
        {
            "category":"Cafe",
            "type":"Food & Drink"
        }
    ],
    "sg:phone":"+32 11 32 33 50",
    "sg:postcode":"3590",
    "sg:province":"Limburg",
    "sg:tags":[
        "caf\u00e9s"
    ],
    "wof:name":"Caf\u00c9 Mona Lisa",
    "wof:placetype":"venue"
},
  "geometry": {"coordinates":[5.443611145,50.9005203247],"type":"Point"}
}