{
  "type": "Feature",
  "properties": {
    "iso:country":"BE",
    "sg:address":"Zeeweg Zuid 4",
    "sg:city":"Zedelgem",
    "sg:orig_category":"Eleveurs de bovins. Eleveurs and marchands de porcs",
    "sg:phone":"+32 50 20 90 40",
    "sg:postcode":"8211",
    "sg:province":"West-Vlaanderen",
    "wof:name":"Camiel Adriaens",
    "wof:placetype":"venue"
},
  "geometry": {"coordinates":[3.0804901123,51.1104316711],"type":"Point"}
}