{
  "type": "Feature",
  "properties": {
    "iso:country":"BE",
    "sg:address":"Sint-godelievestraat 24",
    "sg:city":"Aalter",
    "sg:orig_category":"Enseignement maternel and primaire",
    "sg:phone":"+32 9 374 64 19",
    "sg:postcode":"9880",
    "sg:province":"Oost-Vlaanderen",
    "wof:name":"St.-godelieveschool Wijkafdeling",
    "wof:placetype":"venue"
},
  "geometry": {"coordinates":[3.4253659248,51.1142311096],"type":"Point"}
}