{
  "type": "Feature",
  "properties": {
    "iso:country":"BE",
    "sg:address":"Paleputstraat 25",
    "sg:city":"Torhout",
    "sg:orig_category":"Ordinateurs and \u00e9quipement informatique. Conseils en syst\u00e8mes informatiques",
    "sg:phone":"+32 51 72 37 88",
    "sg:postcode":"8820",
    "sg:province":"West-Vlaanderen",
    "wof:name":"Computer En Netwerk Service",
    "wof:placetype":"venue"
},
  "geometry": {"coordinates":[3.093100071,51.0243988037],"type":"Point"}
}