{
  "type": "Feature",
  "properties": {
    "iso:country":"BE",
    "sg:address":"Avenue G\u00e9n\u00e9ral Gracia 24",
    "sg:city":"Profondeville",
    "sg:classifiers":[
        {
            "category":"Health Services",
            "subcategory":"Nursing And Care Facility",
            "type":"Services"
        }
    ],
    "sg:phone":"+32 81 41 27 10",
    "sg:postcode":"5170",
    "sg:province":"Namur",
    "sg:tags":[
        "home",
        "rest"
    ],
    "wof:name":"Residence Cygnes (les)",
    "wof:placetype":"venue"
},
  "geometry": {"coordinates":[4.877904892,50.3866424561],"type":"Point"}
}