{
  "type": "Feature",
  "properties": {
    "addr:full":"Rue De Tournai 20 Brunehaut (hollain) Hainaut 7620",
    "addr:housenumber":"20",
    "addr:postcode":"7620",
    "addr:street":"Rue De Tournai;Hainaut",
    "iso:country":"BE",
    "sg:address":"Rue De Tournai 20",
    "sg:city":"Brunehaut (hollain)",
    "sg:classifiers":[
        {
            "category":"Utilities",
            "subcategory":"Natural Gas",
            "type":"Services"
        }
    ],
    "sg:phone":"+32 69 34 42 18",
    "sg:postcode":"7620",
    "sg:province":"Hainaut",
    "sg:tags":[
        "industrial",
        "-"
    ],
    "wof:name":"Maison Henneton Sprl",
    "wof:placetype":"venue"
},
  "geometry": {"coordinates":[3.4203300476,50.5198097229],"type":"Point"}
}