{
  "type": "Feature",
  "properties": {
    "addr:full":"Appelboom 16 Maldegem (adegem) Oost-Vlaanderen 9991",
    "addr:housenumber":"16",
    "addr:postcode":"9991",
    "addr:street":"Appelboom",
    "iso:country":"BE",
    "sg:address":"Appelboom 16",
    "sg:city":"Maldegem (adegem)",
    "sg:classifiers":[
        {
            "category":"Structure",
            "subcategory":"Office Building",
            "type":"Public Place"
        }
    ],
    "sg:phone":"+32 9 327 04 14",
    "sg:postcode":"9991",
    "sg:province":"Oost-Vlaanderen",
    "sg:tags":[
        "drawing"
    ],
    "wof:name":"Voet",
    "wof:placetype":"venue"
},
  "geometry": {"coordinates":[3.5068540573,51.1730499268],"type":"Point"}
}