{
  "type": "Feature",
  "properties": {
    "addr:full":"Kattestraat 4 Stekene Oost-Vlaanderen 9190",
    "addr:housenumber":"4",
    "addr:postcode":"9190",
    "addr:street":"Kattestraat",
    "iso:country":"BE",
    "sg:address":"Kattestraat 4",
    "sg:city":"Stekene",
    "sg:orig_category":"Eleveurs and marchands de porcs",
    "sg:phone":"+32 3 789 09 37",
    "sg:postcode":"9190",
    "sg:province":"Oost-Vlaanderen",
    "wof:name":"Kris Van Broeck",
    "wof:placetype":"venue"
},
  "geometry": {"coordinates":[4.0722107887,51.2185516357],"type":"Point"}
}