{
  "type": "Feature",
  "properties": {
    "addr:full":"Chauss\u00c9e De Charleroi 55 Sint-gillis/saint-gilles Bruxelles-Capitale 1060",
    "addr:housenumber":"55",
    "addr:postcode":"1060",
    "addr:street":"Chausse\u0301E De Charleroi",
    "iso:country":"BE",
    "sg:address":"Chauss\u00c9e De Charleroi 55",
    "sg:city":"Sint-gillis/saint-gilles",
    "sg:orig_category":"Pharmaciens",
    "sg:phone":"+32 2 538 05 44",
    "sg:postcode":"1060",
    "sg:province":"Bruxelles-Capitale",
    "wof:name":"Didier Kneyp",
    "wof:placetype":"venue"
},
  "geometry": {"coordinates":[4.3563160896,50.8317108154],"type":"Point"}
}