{
  "type": "Feature",
  "properties": {
    "iso:country":"BE",
    "sg:address":"Groenestraat 6",
    "sg:city":"Kruishoutem",
    "sg:orig_category":"Eleveurs de bovins. Eleveurs and marchands de porcs",
    "sg:phone":"+32 9 383 58 38",
    "sg:postcode":"9770",
    "sg:province":"Oost-Vlaanderen",
    "wof:name":"Michel Vanden Abeele",
    "wof:placetype":"venue"
},
  "geometry": {"coordinates":[3.5466060638,50.9059906006],"type":"Point"}
}