{
  "type": "Feature",
  "properties": {
    "iso:country":"BE",
    "sg:address":"Rue De Lambert 15",
    "sg:city":"Charleroi",
    "sg:orig_category":"Dakwerken",
    "sg:phone":"+32 71 41 30 13",
    "sg:postcode":"6040",
    "sg:province":"Hainaut",
    "wof:name":"Araguez Jos\u00c9",
    "wof:placetype":"venue"
},
  "geometry": {"coordinates":[4.4612169266,50.4411392212],"type":"Point"}
}