{
  "type": "Feature",
  "properties": {
    "addr:full":"Avenue Du Fond Marie Monseu 63 Rixensart Brabant Wallon 1330",
    "addr:housenumber":"63",
    "addr:postcode":"1330",
    "addr:street":"Avenue Du Fond Marie Monseu;Wallon",
    "iso:country":"BE",
    "sg:address":"Avenue Du Fond Marie Monseu 63",
    "sg:city":"Rixensart",
    "sg:classifiers":[
        {
            "category":"Professional",
            "subcategory":"Engineering",
            "type":"Services"
        }
    ],
    "sg:phone":"+32 2 652 25 35",
    "sg:postcode":"1330",
    "sg:province":"Brabant Wallon",
    "sg:tags":[
        "-"
    ],
    "wof:name":"Brahy Ing Ets",
    "wof:placetype":"venue"
},
  "geometry": {"coordinates":[4.5438637733,50.7067222595],"type":"Point"}
}