{
  "type": "Feature",
  "properties": {
    "addr:full":"Bleekhofstraat 22 Antwerpen Antwerpen 2018",
    "addr:housenumber":"22",
    "addr:postcode":"2018",
    "addr:street":"Bleekhofstraat",
    "iso:country":"BE",
    "sg:address":"Bleekhofstraat 22",
    "sg:city":"Antwerpen",
    "sg:orig_category":"Tuinen",
    "sg:phone":"+32 3 234 24 22",
    "sg:postcode":"2018",
    "sg:province":"Antwerpen",
    "wof:name":"Devriendt Ludovic",
    "wof:placetype":"venue"
},
  "geometry": {"coordinates":[4.4271588326,51.2116241455],"type":"Point"}
}