{
  "type": "Feature",
  "properties": {
    "addr:full":"Rue De Malvoisin 26 Gedinne Namur 5575",
    "addr:housenumber":"26",
    "addr:postcode":"5575",
    "addr:street":"Rue De Malvoisin",
    "iso:country":"BE",
    "sg:address":"Rue De Malvoisin 26",
    "sg:city":"Gedinne",
    "sg:orig_category":"Epiceries",
    "sg:phone":"+32 61 58 87 27",
    "sg:postcode":"5575",
    "sg:province":"Namur",
    "wof:name":"Aux Paniers Garnis",
    "wof:placetype":"venue"
},
  "geometry": {"coordinates":[4.9507389069,49.999370575],"type":"Point"}
}