{
  "type": "Feature",
  "properties": {
    "addr:full":"Nieuwpoortlaan 149 De Panne West-Vlaanderen 8660",
    "addr:housenumber":"149",
    "addr:postcode":"8660",
    "addr:street":"Nieuwpoortlaan",
    "iso:country":"BE",
    "sg:address":"Nieuwpoortlaan 149",
    "sg:city":"De Panne",
    "sg:orig_category":"Kampeerterreinen",
    "sg:phone":"+32 58 42 01 38",
    "sg:postcode":"8660",
    "sg:province":"West-Vlaanderen",
    "wof:name":"Camping-zeepark",
    "wof:placetype":"venue"
},
  "geometry": {"coordinates":[2.6004939079,51.1058158875],"type":"Point"}
}