{
  "type": "Feature",
  "properties": {
    "iso:country":"BE",
    "sg:address":"Rue De Neufchateau 21",
    "sg:city":"Bastogne",
    "sg:orig_category":"R\u00e9parations d'appareils \u00e9lectrom\u00e9nagers. Mat\u00e9riel de T\u00e9l\u00e9communication. Fabrication and montage de m",
    "sg:phone":"+32 61 21 29 90",
    "sg:postcode":"6600",
    "sg:province":"Luxembourg",
    "wof:name":"Euro Center",
    "wof:placetype":"venue"
},
  "geometry": {"coordinates":[5.7138562202,49.9997138977],"type":"Point"}
}