{
  "type": "Feature",
  "properties": {
    "addr:full":"Renier Sniedersstraat 60 Turnhout Antwerpen 2300",
    "addr:housenumber":"60",
    "addr:postcode":"2300",
    "addr:street":"Renier Sniedersstraat",
    "iso:country":"BE",
    "sg:address":"Renier Sniedersstraat 60",
    "sg:city":"Turnhout",
    "sg:orig_category":"Eleveurs de bovins",
    "sg:phone":"+32 14 43 52 77",
    "sg:postcode":"2300",
    "sg:province":"Antwerpen",
    "wof:name":"Ludovicus Van Herck",
    "wof:placetype":"venue"
},
  "geometry": {"coordinates":[4.9396271706,51.3248443604],"type":"Point"}
}