{
  "type": "Feature",
  "properties": {
    "iso:country":"BE",
    "sg:address":"Fonteinweg 4",
    "sg:city":"Mechelen",
    "sg:orig_category":"Kapsalons",
    "sg:phone":"+32 15 27 71 18",
    "sg:postcode":"2801",
    "sg:province":"Antwerpen",
    "wof:name":"Coiffure Myriam",
    "wof:placetype":"venue"
},
  "geometry": {"coordinates":[4.4198479652,51.0495109558],"type":"Point"}
}