{
  "type": "Feature",
  "properties": {
    "addr:full":"Hoogstraatsebaan 13 Malle Antwerpen 2390",
    "addr:housenumber":"13",
    "addr:postcode":"2390",
    "addr:street":"Hoogstraatsebaan",
    "iso:country":"BE",
    "sg:address":"Hoogstraatsebaan 13",
    "sg:city":"Malle",
    "sg:orig_category":"Meubelzaken, woning- and keukeninrichting",
    "sg:phone":"+32 3 309 25 53",
    "sg:postcode":"2390",
    "sg:province":"Antwerpen",
    "wof:name":"Malle's Huis",
    "wof:placetype":"venue"
},
  "geometry": {"coordinates":[4.7347888947,51.3029441833],"type":"Point"}
}