{
  "type": "Feature",
  "properties": {
    "addr:full":"Premi\u00c8re Rue Charleroi Hainaut 6040",
    "addr:postcode":"6040",
    "addr:street":"Rue Charleroi Hainaut",
    "iso:country":"BE",
    "sg:address":"Premi\u00c8re Rue",
    "sg:city":"Charleroi",
    "sg:orig_category":"Entreprises de travail adapt\u00e9",
    "sg:phone":"+32 71 35 98 10",
    "sg:postcode":"6040",
    "sg:province":"Hainaut",
    "wof:name":"Atelier Cambier Eddy",
    "wof:placetype":"venue"
},
  "geometry": {"coordinates":[4.4549150467,50.4562835693],"type":"Point"}
}