{
  "type": "Feature",
  "properties": {
    "addr:full":"Kl\u00d6tzerbahn 4 Eupen Li\u00e8ge 4700",
    "addr:housenumber":"4",
    "addr:postcode":"4700",
    "addr:street":"Kloetzerbahn",
    "iso:country":"BE",
    "sg:address":"Kl\u00d6tzerbahn 4",
    "sg:city":"Eupen",
    "sg:orig_category":"Kantoormateriaal Verlichting and huishoudartikelen",
    "sg:phone":"+32 87 55 28 14",
    "sg:postcode":"4700",
    "sg:province":"Li\u00e8ge",
    "wof:name":"Ingehaus",
    "wof:placetype":"venue"
},
  "geometry": {"coordinates":[6.0338931084,50.6303901672],"type":"Point"}
}