{
  "type": "Feature",
  "properties": {
    "addr:full":"Doolhofstraat 104 Moeskroen/mouscron Hainaut 7700",
    "addr:housenumber":"104",
    "addr:postcode":"7700",
    "addr:street":"Doolhofstraat",
    "iso:country":"BE",
    "sg:address":"Doolhofstraat 104",
    "sg:city":"Moeskroen/mouscron",
    "sg:orig_category":"Kapsalons",
    "sg:phone":"+32 56 33 57 40",
    "sg:postcode":"7700",
    "sg:province":"Hainaut",
    "wof:name":"Marie-laure Gaudeix",
    "wof:placetype":"venue"
},
  "geometry": {"coordinates":[3.2323200703,50.7400932312],"type":"Point"}
}