{
  "type": "Feature",
  "properties": {
    "iso:country":"BE",
    "sg:address":"Rue Froide 86",
    "sg:city":"Walcourt",
    "sg:orig_category":"Traitements param\u00e9dicaux",
    "sg:phone":"+32 71 61 39 53",
    "sg:postcode":"5651",
    "sg:province":"Namur",
    "wof:name":"F. Remy",
    "wof:placetype":"venue"
},
  "geometry": {"coordinates":[4.394493103,50.2930831909],"type":"Point"}
}