{
  "type": "Feature",
  "properties": {
    "iso:country":"BE",
    "sg:address":"Slekkenstraat 8",
    "sg:city":"Beveren (melsele)",
    "sg:classifiers":[
        {
            "category":"Wholesale",
            "subcategory":"Books, Periodicals, & Newspapers",
            "type":"Manufacturing & Wholesale Goods"
        }
    ],
    "sg:phone":"+32 3 252 89 23",
    "sg:postcode":"9120",
    "sg:province":"Oost-Vlaanderen",
    "sg:tags":[
        "banner"
    ],
    "wof:name":"Studio Robert Publiciteit Bvba",
    "wof:placetype":"venue"
},
  "geometry": {"coordinates":[4.3144159317,51.2002983093],"type":"Point"}
}