{
  "type": "Feature",
  "properties": {
    "iso:country":"BE",
    "sg:address":"Rue T\u00cate D'argent 3",
    "sg:city":"Tournai",
    "sg:orig_category":"Drukkerijen and copyshops Kantoormateriaal",
    "sg:phone":"+32 69 84 49 90",
    "sg:postcode":"7500",
    "sg:province":"Hainaut",
    "wof:name":"Copy Saint-jacques",
    "wof:placetype":"venue"
},
  "geometry": {"coordinates":[3.3862719536,50.6086349487],"type":"Point"}
}