{
  "type": "Feature",
  "properties": {
    "iso:country":"BE",
    "sg:address":"Rue Mar Foch 21",
    "sg:city":"Flemalle",
    "sg:orig_category":"Fer and acier Fab",
    "sg:phone":"+32 4 234 91 91",
    "sg:postcode":"4400",
    "sg:province":"Li\u00e8ge",
    "wof:name":"Stedic",
    "wof:placetype":"venue"
},
  "geometry": {"coordinates":[5.4724798203,50.5987014771],"type":"Point"}
}