{
  "type": "Feature",
  "properties": {
    "iso:country":"BE",
    "sg:address":"Heldergemstraat 200",
    "sg:city":"Haaltert (heldergem)",
    "sg:classifiers":[
        {
            "category":"Wholesale",
            "subcategory":"Beer",
            "type":"Manufacturing & Wholesale Goods"
        }
    ],
    "sg:phone":"+32 53 62 38 52",
    "sg:postcode":"9450",
    "sg:province":"Oost-Vlaanderen",
    "sg:tags":[
        "ale",
        "-"
    ],
    "wof:name":"Van Cauwenbergh (drankencentrale)",
    "wof:placetype":"venue"
},
  "geometry": {"coordinates":[3.95322299,50.88306427],"type":"Point"}
}