{
  "type": "Feature",
  "properties": {
    "iso:country":"BE",
    "sg:address":"Kalkoenstraat 19",
    "sg:city":"Sint-katelijne-waver",
    "sg:orig_category":"Elektrische installaties voor woningen Huishoudapparaten, televisies and radio's",
    "sg:phone":"+32 15 31 27 66",
    "sg:postcode":"2860",
    "sg:province":"Antwerpen",
    "wof:name":"Marc Wellens",
    "wof:placetype":"venue"
},
  "geometry": {"coordinates":[4.483355999,51.071231842],"type":"Point"}
}