{
  "type": "Feature",
  "properties": {
    "addr:full":"Molenhoek 21 Londerzeel Vlaams-Brabant 1840",
    "addr:housenumber":"21",
    "addr:postcode":"1840",
    "addr:street":"Molenhoek",
    "iso:country":"BE",
    "sg:address":"Molenhoek 21",
    "sg:city":"Londerzeel",
    "sg:orig_category":"Fast food and meeneem restaurants Levering aan huis restaurants Restaurants Ruimtes voor conferentie",
    "sg:phone":"+32 52 30 26 12",
    "sg:postcode":"1840",
    "sg:province":"Vlaams-Brabant",
    "wof:name":"Ter Wilgen",
    "wof:placetype":"venue"
},
  "geometry": {"coordinates":[4.3191070557,51.0220756531],"type":"Point"}
}