{
  "type": "Feature",
  "properties": {
    "addr:full":"Rue Du Tambour 12 Bouillon Luxembourg 6838",
    "addr:housenumber":"12",
    "addr:postcode":"6838",
    "addr:street":"Rue Du Tambour",
    "iso:country":"BE",
    "sg:address":"Rue Du Tambour 12",
    "sg:city":"Bouillon",
    "sg:orig_category":"Maisons de vacances",
    "sg:phone":"+32 61 46 77 08",
    "sg:postcode":"6838",
    "sg:province":"Luxembourg",
    "wof:name":"P.arnould",
    "wof:placetype":"venue"
},
  "geometry": {"coordinates":[5.0071702003,49.7973403931],"type":"Point"}
}