{
  "type": "Feature",
  "properties": {
    "iso:country":"BE",
    "sg:address":"F\u00e9ronstr\u00e9e 135",
    "sg:city":"Li\u00e8ge 1",
    "sg:classifiers":[
        {
            "category":"Home & Garden",
            "subcategory":"Carpets & Floor Coverings",
            "type":"Retail Goods"
        }
    ],
    "sg:phone":"+32 4 223 62 06",
    "sg:postcode":"4000",
    "sg:province":"Li\u00e8ge",
    "sg:tags":[
        "oriental"
    ],
    "wof:name":"Eshraghi Foad",
    "wof:placetype":"venue"
},
  "geometry": {"coordinates":[5.5819768906,50.6472053528],"type":"Point"}
}