{
  "type": "Feature",
  "properties": {
    "iso:country":"BE",
    "sg:address":"Broekdam-zuid 26",
    "sg:city":"Kruibeke",
    "sg:orig_category":"Bloemen and planten Brood, gebak and snoepgoed",
    "sg:phone":"+32 3 774 17 84",
    "sg:postcode":"9150",
    "sg:province":"Oost-Vlaanderen",
    "wof:name":"Rosita's Bloemenhuis",
    "wof:placetype":"venue"
},
  "geometry": {"coordinates":[4.314139843,51.169418335],"type":"Point"}
}