{
  "type": "Feature",
  "properties": {
    "iso:country":"BE",
    "sg:address":"Industrielaan 7",
    "sg:city":"Lichtervelde",
    "sg:classifiers":[
        {
            "category":"Utilities",
            "subcategory":"Natural Gas",
            "type":"Services"
        }
    ],
    "sg:phone":"+32 51 72 90 90",
    "sg:postcode":"8810",
    "sg:province":"West-Vlaanderen",
    "sg:tags":[
        "industrial",
        "-"
    ],
    "wof:name":"Dvh Gas (shell Gas) Nv",
    "wof:placetype":"venue"
},
  "geometry": {"coordinates":[3.1146469116,51.0296936035],"type":"Point"}
}