{
  "type": "Feature",
  "properties": {
    "addr:full":"Kortrijksesteenweg 241a Sint-martens-latem Oost-Vlaanderen 9830",
    "addr:housenumber":"241a",
    "addr:postcode":"9830",
    "addr:street":"Kortrijksesteenweg",
    "iso:country":"BE",
    "sg:address":"Kortrijksesteenweg 241a",
    "sg:city":"Sint-martens-latem",
    "sg:orig_category":"Motorfietsen",
    "sg:phone":"+32 9 281 02 04",
    "sg:postcode":"9830",
    "sg:province":"Oost-Vlaanderen",
    "wof:name":"Bimoto",
    "wof:placetype":"venue"
},
  "geometry": {"coordinates":[3.6274850368,51.0062904358],"type":"Point"}
}