{
  "type": "Feature",
  "properties": {
    "iso:country":"BE",
    "sg:address":"Moleneindstraat 77",
    "sg:city":"Lokeren",
    "sg:orig_category":"Fiduciairies",
    "sg:phone":"+32 9 349 07 46",
    "sg:postcode":"9160",
    "sg:province":"Oost-Vlaanderen",
    "wof:name":"Beirnaert G",
    "wof:placetype":"venue"
},
  "geometry": {"coordinates":[3.9335780144,51.1038665771],"type":"Point"}
}