{
  "type": "Feature",
  "properties": {
    "addr:full":"Rue Paul Pastur 15 Erquelinnes Hainaut 6560",
    "addr:housenumber":"15",
    "addr:postcode":"6560",
    "addr:street":"Rue Paul Pastur",
    "iso:country":"BE",
    "sg:address":"Rue Paul Pastur 15",
    "sg:city":"Erquelinnes",
    "sg:orig_category":"Eleveurs de bovins",
    "sg:phone":"+32 64 77 13 59",
    "sg:postcode":"6560",
    "sg:province":"Hainaut",
    "wof:name":"Vincent Christiaens",
    "wof:placetype":"venue"
},
  "geometry": {"coordinates":[4.1016750336,50.3165588379],"type":"Point"}
}