{
  "type": "Feature",
  "properties": {
    "addr:full":"Geldenaaksevest 110 Leuven Vlaams-Brabant 3000",
    "addr:housenumber":"110",
    "addr:postcode":"3000",
    "addr:street":"Geldenaaksevest",
    "iso:country":"BE",
    "sg:address":"Geldenaaksevest 110",
    "sg:city":"Leuven",
    "sg:classifiers":[
        {
            "category":"Bars & Pubs",
            "type":"Food & Drink"
        }
    ],
    "sg:phone":"+32 16 20 70 75",
    "sg:postcode":"3000",
    "sg:province":"Vlaams-Brabant",
    "wof:name":"Union",
    "wof:placetype":"venue"
},
  "geometry": {"coordinates":[4.708275795,50.8695144653],"type":"Point"}
}