{
  "type": "Feature",
  "properties": {
    "iso:country":"BE",
    "sg:address":"De Stijne 6",
    "sg:city":"Zomergem",
    "sg:orig_category":"Rev\u00eatements pour sols and murs. Peinture",
    "sg:phone":"+32 9 372 06 28",
    "sg:postcode":"9930",
    "sg:province":"Oost-Vlaanderen",
    "wof:name":"Erwin Maes",
    "wof:placetype":"venue"
},
  "geometry": {"coordinates":[3.6035280228,51.1255722046],"type":"Point"}
}