{
  "type": "Feature",
  "properties": {
    "iso:country":"BE",
    "sg:address":"Oever 2 Box 3",
    "sg:city":"Lier",
    "sg:classifiers":[
        {
            "category":"Building & Trades",
            "subcategory":"Construction",
            "type":"Services"
        }
    ],
    "sg:phone":"+32 3 488 24 61",
    "sg:postcode":"2500",
    "sg:province":"Antwerpen",
    "sg:tags":[
        "surveyor",
        "-"
    ],
    "wof:name":"B+ Concept",
    "wof:placetype":"venue"
},
  "geometry": {"coordinates":[4.5755791664,51.1316642761],"type":"Point"}
}