{
  "type": "Feature",
  "properties": {
    "addr:full":"Sint-niklaasstraat 16 Sint-gillis-waas Oost-Vlaanderen 9170",
    "addr:housenumber":"16",
    "addr:postcode":"9170",
    "addr:street":"Sint-Niklaasstraat",
    "iso:country":"BE",
    "sg:address":"Sint-niklaasstraat 16",
    "sg:city":"Sint-gillis-waas",
    "sg:orig_category":"Schoonheidssalons",
    "sg:phone":"+32 3 707 19 96",
    "sg:postcode":"9170",
    "sg:province":"Oost-Vlaanderen",
    "wof:name":"Nele De Rudder",
    "wof:placetype":"venue"
},
  "geometry": {"coordinates":[4.132958889,51.2136497498],"type":"Point"}
}