{
  "type": "Feature",
  "properties": {
    "iso:country":"BE",
    "sg:address":"Rue Achille Bauduin 71",
    "sg:city":"Wavre",
    "sg:orig_category":"Enseignement maternel and primaire",
    "sg:phone":"+32 10 41 02 03",
    "sg:postcode":"1300",
    "sg:province":"Brabant Wallon",
    "wof:name":"Ecole Matern. Communale",
    "wof:placetype":"venue"
},
  "geometry": {"coordinates":[4.5823941231,50.6938056946],"type":"Point"}
}