{
  "type": "Feature",
  "properties": {
    "addr:full":"Kapucijnenvoer 110 Leuven Vlaams-Brabant 3000",
    "addr:housenumber":"110",
    "addr:postcode":"3000",
    "addr:street":"Kapucijnenvoer",
    "iso:country":"BE",
    "sg:address":"Kapucijnenvoer 110",
    "sg:city":"Leuven",
    "sg:orig_category":"Plomberie, chauffage and installations sanitaires. Construction de maisons",
    "sg:phone":"+32 16 22 23 17",
    "sg:postcode":"3000",
    "sg:province":"Vlaams-Brabant",
    "wof:name":"Philippe Gilson",
    "wof:placetype":"venue"
},
  "geometry": {"coordinates":[4.691037178,50.8746185303],"type":"Point"}
}