{
  "type": "Feature",
  "properties": {
    "iso:country":"BE",
    "sg:address":"Oudstrijderslaan 36",
    "sg:city":"Keerbergen",
    "sg:orig_category":"Diverse meubelen Fab Installatie van houten of kunststof schrijnwerk",
    "sg:phone":"+32 15 51 27 93",
    "sg:postcode":"3140",
    "sg:province":"Vlaams-Brabant",
    "wof:name":"Schroons & Zonen",
    "wof:placetype":"venue"
},
  "geometry": {"coordinates":[4.6282958984,51.0025482178],"type":"Point"}
}