{
  "type": "Feature",
  "properties": {
    "addr:full":"Rue Henri Delvaux 35 Ans Li\u00e8ge 4430",
    "addr:housenumber":"35",
    "addr:postcode":"4430",
    "addr:street":"Rue Henri Delvaux",
    "iso:country":"BE",
    "sg:address":"Rue Henri Delvaux 35",
    "sg:city":"Ans",
    "sg:orig_category":"Blanchisseries and teintureries",
    "sg:phone":"+32 4 247 32 28",
    "sg:postcode":"4430",
    "sg:province":"Li\u00e8ge",
    "wof:name":"Salon Lavoir De La Gare",
    "wof:placetype":"venue"
},
  "geometry": {"coordinates":[5.5120491982,50.6617164612],"type":"Point"}
}