{
  "type": "Feature",
  "properties": {
    "iso:country":"BE",
    "sg:address":"Rue De La Chav\u00e9e 37",
    "sg:city":"Chiny (jamoigne)",
    "sg:classifiers":[
        {
            "category":"Home & Garden",
            "subcategory":"Carpets & Floor Coverings",
            "type":"Retail Goods"
        }
    ],
    "sg:phone":"+32 61 32 96 31",
    "sg:postcode":"6810",
    "sg:province":"Luxembourg",
    "sg:tags":[
        "armoring"
    ],
    "wof:name":"Clausse J-m",
    "wof:placetype":"venue"
},
  "geometry": {"coordinates":[5.3405580521,49.7382736206],"type":"Point"}
}