{
  "type": "Feature",
  "properties": {
    "addr:full":"Boogstraat 45 Houthalen-helchteren Limburg 3530",
    "addr:housenumber":"45",
    "addr:postcode":"3530",
    "addr:street":"Boogstraat",
    "iso:country":"BE",
    "sg:address":"Boogstraat 45",
    "sg:city":"Houthalen-helchteren",
    "sg:orig_category":"Traitements param\u00e9dicaux",
    "sg:phone":"+32 11 52 42 29",
    "sg:postcode":"3530",
    "sg:province":"Limburg",
    "wof:name":"Lut Lijnen",
    "wof:placetype":"venue"
},
  "geometry": {"coordinates":[5.3614091873,51.0410690308],"type":"Point"}
}