{
  "type": "Feature",
  "properties": {
    "addr:full":"Sint-jozefstraat 16 Rumst Antwerpen 2840",
    "addr:housenumber":"16",
    "addr:postcode":"2840",
    "addr:street":"Sint-Jozefstraat",
    "iso:country":"BE",
    "sg:address":"Sint-jozefstraat 16",
    "sg:city":"Rumst",
    "sg:orig_category":"D\u00e9molition d\u00b4immeubles and terrassements. Transports routiers de marchandises",
    "sg:phone":"+32 3 888 98 23",
    "sg:postcode":"2840",
    "sg:province":"Antwerpen",
    "wof:name":"Michel",
    "wof:placetype":"venue"
},
  "geometry": {"coordinates":[4.3840479851,51.1110610962],"type":"Point"}
}