{
  "type": "Feature",
  "properties": {
    "iso:country":"BE",
    "sg:address":"Burg. Jos. Chalmetlaan 59",
    "sg:city":"Zelzate",
    "sg:orig_category":"Pain, p\u00e2tisseries and confiseries",
    "sg:phone":"+32 9 345 09 96",
    "sg:postcode":"9060",
    "sg:province":"Oost-Vlaanderen",
    "wof:name":"Kristof De Graeve",
    "wof:placetype":"venue"
},
  "geometry": {"coordinates":[3.8159840107,51.1972618103],"type":"Point"}
}