{
  "type": "Feature",
  "properties": {
    "iso:country":"BE",
    "sg:address":"Hasseltse Beverzakstraat 173",
    "sg:city":"Hasselt",
    "sg:orig_category":"Installation de menuiserie en bois and plastique",
    "sg:phone":"+32 11 82 33 54",
    "sg:postcode":"3500",
    "sg:province":"Limburg",
    "wof:name":"Marc Vandiest",
    "wof:placetype":"venue"
},
  "geometry": {"coordinates":[5.3842291832,50.974067688],"type":"Point"}
}