{
  "type": "Feature",
  "properties": {
    "iso:country":"BE",
    "sg:address":"Place De Pipaix 19",
    "sg:city":"Leuze-en-hainaut",
    "sg:orig_category":"Brood, gebak and snoepgoed",
    "sg:phone":"+32 69 66 58 45",
    "sg:postcode":"7904",
    "sg:province":"Hainaut",
    "wof:name":"P\u00c2tisserie Fontaine",
    "wof:placetype":"venue"
},
  "geometry": {"coordinates":[3.5791180134,50.5836486816],"type":"Point"}
}