{
  "type": "Feature",
  "properties": {
    "iso:country":"BE",
    "sg:address":"Landsdijk 88",
    "sg:city":"Assenede",
    "sg:orig_category":"Electrom\u00e9nager, t\u00e9l\u00e9visions and radios",
    "sg:phone":"+32 9 373 58 78",
    "sg:postcode":"9968",
    "sg:province":"Oost-Vlaanderen",
    "wof:name":"Reinhard D'have",
    "wof:placetype":"venue"
},
  "geometry": {"coordinates":[3.6494350433,51.253036499],"type":"Point"}
}