{
  "type": "Feature",
  "properties": {
    "addr:full":"Abdijstraat 237 Antwerpen Antwerpen 2020",
    "addr:housenumber":"237",
    "addr:postcode":"2020",
    "addr:street":"Abdijstraat",
    "iso:country":"BE",
    "sg:address":"Abdijstraat 237",
    "sg:city":"Antwerpen",
    "sg:orig_category":"Bagage and lederwaren Schoenen",
    "sg:phone":"+32 3 238 69 52",
    "sg:postcode":"2020",
    "sg:province":"Antwerpen",
    "wof:name":"Huis Salamander",
    "wof:placetype":"venue"
},
  "geometry": {"coordinates":[4.3866810799,51.1867485046],"type":"Point"}
}