{
  "type": "Feature",
  "properties": {
    "iso:country":"BE",
    "sg:address":"Korte Veldstraat 7",
    "sg:city":"Diksmuide",
    "sg:orig_category":"Rundveehouders Varkenskwekers",
    "sg:phone":"+32 51 50 02 91",
    "sg:postcode":"8600",
    "sg:province":"West-Vlaanderen",
    "wof:name":"Paul Wullepit",
    "wof:placetype":"venue"
},
  "geometry": {"coordinates":[2.9056611061,51.0189323425],"type":"Point"}
}