{
  "type": "Feature",
  "properties": {
    "addr:full":"Rue Richard Orban 4 Berloz Li\u00e8ge 4257",
    "addr:housenumber":"4",
    "addr:postcode":"4257",
    "addr:street":"Rue Richard Orban",
    "iso:country":"BE",
    "sg:address":"Rue Richard Orban 4",
    "sg:city":"Berloz",
    "sg:classifiers":[
        {
            "category":"Professional",
            "subcategory":"Printing & Photocopies",
            "type":"Services"
        }
    ],
    "sg:phone":"+32 19 32 23 73",
    "sg:postcode":"4257",
    "sg:province":"Li\u00e8ge",
    "sg:tags":[
        "silkscreen",
        "-"
    ],
    "wof:name":"Publi Troosters",
    "wof:placetype":"venue"
},
  "geometry": {"coordinates":[5.2127728462,50.6979598999],"type":"Point"}
}