{
  "type": "Feature",
  "properties": {
    "iso:country":"BE",
    "sg:address":"Sint-krispijnstraat 9",
    "sg:city":"Ieper",
    "sg:classifiers":[
        {
            "category":"Home & Garden",
            "subcategory":"Carpets & Floor Coverings",
            "type":"Retail Goods"
        }
    ],
    "sg:phone":"+32 57 21 68 68",
    "sg:postcode":"8900",
    "sg:province":"West-Vlaanderen",
    "sg:tags":[
        "parquet"
    ],
    "wof:name":"Antiek Bouw Nv",
    "wof:placetype":"venue"
},
  "geometry": {"coordinates":[2.8848218918,50.8770332336],"type":"Point"}
}