{
  "type": "Feature",
  "properties": {
    "iso:country":"BE",
    "sg:address":"Kamstraat 46",
    "sg:city":"Huldenberg (neerijse)",
    "sg:classifiers":[
        {
            "category":"Recreation",
            "subcategory":"Campground",
            "type":"Entertainment"
        }
    ],
    "sg:phone":"+32 16 47 76 36",
    "sg:postcode":"3040",
    "sg:province":"Vlaams-Brabant",
    "sg:tags":[
        "site",
        "camping"
    ],
    "wof:name":"Chalets (les)",
    "wof:placetype":"venue"
},
  "geometry": {"coordinates":[4.622150898,50.8144111633],"type":"Point"}
}