{
  "type": "Feature",
  "properties": {
    "addr:full":"Lijsterstraat 3 Oud-heverlee Vlaams-Brabant 3052",
    "addr:housenumber":"3",
    "addr:postcode":"3052",
    "addr:street":"Lijsterstraat",
    "iso:country":"BE",
    "sg:address":"Lijsterstraat 3",
    "sg:city":"Oud-heverlee",
    "sg:orig_category":"Bois Gr. Quincailleries. Travail and traitement du bois",
    "sg:phone":"+32 16 40 29 02",
    "sg:postcode":"3052",
    "sg:province":"Vlaams-Brabant",
    "wof:name":"Vanautgaerden",
    "wof:placetype":"venue"
},
  "geometry": {"coordinates":[4.7043480873,50.8255233765],"type":"Point"}
}