{
  "type": "Feature",
  "properties": {
    "iso:country":"BE",
    "sg:address":"Hippodroomlaan 193",
    "sg:city":"Zaventem",
    "sg:orig_category":"V\u00e9t\u00e9rinaires",
    "sg:phone":"+32 2 731 18 30",
    "sg:postcode":"1933",
    "sg:province":"Vlaams-Brabant",
    "wof:name":"Erik Pottie",
    "wof:placetype":"venue"
},
  "geometry": {"coordinates":[4.5031499863,50.8521652222],"type":"Point"}
}