{
  "type": "Feature",
  "properties": {
    "iso:country":"BE",
    "sg:address":"Rue De Nazareth 3",
    "sg:city":"Cerfontaine",
    "sg:orig_category":"V\u00e9t\u00e9rinaires",
    "sg:phone":"+32 71 63 34 31",
    "sg:postcode":"5630",
    "sg:province":"Namur",
    "wof:name":"Cabinet V\u00c9t\u00c9rinaire Buyck-polet",
    "wof:placetype":"venue"
},
  "geometry": {"coordinates":[4.4241452217,50.2223701477],"type":"Point"}
}