{
  "type": "Feature",
  "properties": {
    "addr:full":"Rue Buissonni\u00e8re 7 Profondeville Namur 5170",
    "addr:housenumber":"7",
    "addr:postcode":"5170",
    "addr:street":"Rue Buissonnie\u0300Re",
    "iso:country":"BE",
    "sg:address":"Rue Buissonni\u00e8re 7",
    "sg:city":"Profondeville",
    "sg:classifiers":[
        {
            "category":"Health Services",
            "subcategory":"Doctor",
            "type":"Services"
        }
    ],
    "sg:phone":"+32 81 41 34 33",
    "sg:postcode":"5170",
    "sg:province":"Namur",
    "sg:tags":[
        "medicinephysicians",
        "surgeon"
    ],
    "wof:name":"Hanson Philippe",
    "wof:placetype":"venue"
},
  "geometry": {"coordinates":[4.8742928505,50.3748397827],"type":"Point"}
}