{
  "type": "Feature",
  "properties": {
    "iso:country":"BE",
    "sg:address":"Stormestraat 5",
    "sg:city":"Waregem",
    "sg:orig_category":"Opticiens",
    "sg:phone":"+32 56 60 16 27",
    "sg:postcode":"8790",
    "sg:province":"West-Vlaanderen",
    "wof:name":"Oogoptiek",
    "wof:placetype":"venue"
},
  "geometry": {"coordinates":[3.4314410686,50.8864402771],"type":"Point"}
}