{
  "type": "Feature",
  "properties": {
    "addr:full":"Rue Gustave Miroir 5 Saint-ghislain Hainaut 7334",
    "addr:housenumber":"5",
    "addr:postcode":"7334",
    "addr:street":"Rue Gustave Miroir;Hainaut",
    "iso:country":"BE",
    "sg:address":"Rue Gustave Miroir 5",
    "sg:city":"Saint-ghislain",
    "sg:orig_category":"Enseignement maternel and primaire",
    "sg:phone":"+32 65 62 05 60",
    "sg:postcode":"7334",
    "sg:province":"Hainaut",
    "wof:name":"Ecole Fond. Communale",
    "wof:placetype":"venue"
},
  "geometry": {"coordinates":[3.7644500732,50.479675293],"type":"Point"}
}