{
  "type": "Feature",
  "properties": {
    "iso:country":"BE",
    "sg:address":"Rue Hameau Des Bois 12",
    "sg:city":"Pont-\u00e0-celles (buzet)",
    "sg:classifiers":[
        {
            "category":"Building & Trades",
            "subcategory":"Electrical",
            "type":"Services"
        }
    ],
    "sg:phone":"+32 67 22 02 50",
    "sg:postcode":"6230",
    "sg:province":"Hainaut",
    "sg:tags":[
        "electric",
        "-",
        "housewiring",
        "contractor"
    ],
    "wof:name":"Semaille E",
    "wof:placetype":"venue"
},
  "geometry": {"coordinates":[4.3649201393,50.5132751465],"type":"Point"}
}