{
  "type": "Feature",
  "properties": {
    "iso:country":"BE",
    "sg:address":"Constant Montaldlaan 55",
    "sg:city":"Sint-lambrechts-woluwe/woluwe-saint-lambert",
    "sg:orig_category":"Medische apparatuur, orthopedische artikelen and prothesen Fab",
    "sg:phone":"+32 2 770 16 42",
    "sg:postcode":"1200",
    "sg:province":"Bruxelles-Capitale",
    "wof:name":"Labo Pauwels",
    "wof:placetype":"venue"
},
  "geometry": {"coordinates":[4.4202008247,50.8418922424],"type":"Point"}
}