{
  "type": "Feature",
  "properties": {
    "addr:full":"Ingelandgat 8 Gent Oost-Vlaanderen 9000",
    "addr:housenumber":"8",
    "addr:postcode":"9000",
    "addr:street":"Ingelandgat;Oost-Vlaanderen",
    "iso:country":"BE",
    "sg:address":"Ingelandgat 8",
    "sg:city":"Gent",
    "sg:classifiers":[
        {
            "category":"Health Services",
            "subcategory":"Doctor",
            "type":"Services"
        }
    ],
    "sg:phone":"+32 9 225 44 50",
    "sg:postcode":"9000",
    "sg:province":"Oost-Vlaanderen",
    "sg:tags":[
        "medicinephysicians",
        "surgeon"
    ],
    "wof:name":"De Meerleer Elisabeth",
    "wof:placetype":"venue"
},
  "geometry": {"coordinates":[3.7179989815,51.053478241],"type":"Point"}
}