{
  "type": "Feature",
  "properties": {
    "addr:full":"Route De La Pers\u00c9v\u00c9rance 13 Charleroi Hainaut 6061",
    "addr:housenumber":"13",
    "addr:postcode":"6061",
    "addr:street":"Route De La Perse\u0301Ve\u0301Rance;Hainaut",
    "iso:country":"BE",
    "sg:address":"Route De La Pers\u00c9v\u00c9rance 13",
    "sg:city":"Charleroi",
    "sg:orig_category":"Rev\u00eatements de sols and murs",
    "sg:phone":"+32 71 42 03 44",
    "sg:postcode":"6061",
    "sg:province":"Hainaut",
    "wof:name":"Carpet-land",
    "wof:placetype":"venue"
},
  "geometry": {"coordinates":[4.4795150757,50.4009437561],"type":"Point"}
}