{
  "type": "Feature",
  "properties": {
    "addr:full":"Brugse Heirweg 7 Tielt West-Vlaanderen 8700",
    "addr:housenumber":"7",
    "addr:postcode":"8700",
    "addr:street":"Brugse Heirweg",
    "iso:country":"BE",
    "sg:address":"Brugse Heirweg 7",
    "sg:city":"Tielt",
    "sg:orig_category":"Eleveurs de bovins",
    "sg:phone":"+32 51 65 53 62",
    "sg:postcode":"8700",
    "sg:province":"West-Vlaanderen",
    "wof:name":"Marc Popelier",
    "wof:placetype":"venue"
},
  "geometry": {"coordinates":[3.3064320087,51.0349807739],"type":"Point"}
}