{
  "type": "Feature",
  "properties": {
    "iso:country":"BE",
    "sg:address":"Rue Marie Au Broux 8",
    "sg:city":"Walhain (tourinnes-saint-lambert)",
    "sg:classifiers":[
        {
            "category":"Personal",
            "subcategory":"Beauty Salon",
            "type":"Services"
        }
    ],
    "sg:phone":"+32 10 65 87 76",
    "sg:postcode":"1457",
    "sg:province":"Brabant Wallon",
    "sg:tags":[
        "lady",
        "-",
        "hairdressing"
    ],
    "wof:name":"Renier P",
    "wof:placetype":"venue"
},
  "geometry": {"coordinates":[4.7124190331,50.6381797791],"type":"Point"}
}