{
  "type": "Feature",
  "properties": {
    "addr:full":"Kerkstraat 57 De Haan West-Vlaanderen 8420",
    "addr:housenumber":"57",
    "addr:postcode":"8420",
    "addr:street":"Kerkstraat",
    "iso:country":"BE",
    "sg:address":"Kerkstraat 57",
    "sg:city":"De Haan",
    "sg:orig_category":"Schoonheidssalons",
    "sg:phone":"+32 50 42 61 61",
    "sg:postcode":"8420",
    "sg:province":"West-Vlaanderen",
    "wof:name":"Bellini",
    "wof:placetype":"venue"
},
  "geometry": {"coordinates":[3.0811290741,51.2993164062],"type":"Point"}
}