{
  "type": "Feature",
  "properties": {
    "iso:country":"BE",
    "sg:address":"Bd Joseph Tirou 96",
    "sg:city":"Charleroi",
    "sg:classifiers":[
        {
            "category":"Travel",
            "subcategory":"Hotels & Motels",
            "type":"Entertainment"
        }
    ],
    "sg:phone":"+32 71 31 98 11",
    "sg:postcode":"6000",
    "sg:province":"Hainaut",
    "sg:tags":[
        "hotels",
        "business",
        "restaurant"
    ],
    "wof:name":"Hotel Socatel",
    "wof:placetype":"venue"
},
  "geometry": {"coordinates":[4.4445462227,50.4072952271],"type":"Point"}
}