{
  "type": "Feature",
  "properties": {
    "iso:country":"BE",
    "sg:address":"Kerkstraat 14",
    "sg:city":"Ninove",
    "sg:orig_category":"Boucheries",
    "sg:phone":"+32 54 33 10 83",
    "sg:postcode":"9406",
    "sg:province":"Oost-Vlaanderen",
    "wof:name":"C. De Gelas",
    "wof:placetype":"venue"
},
  "geometry": {"coordinates":[3.999735117,50.8415298462],"type":"Point"}
}