{
  "type": "Feature",
  "properties": {
    "addr:full":"Citadellaan 53 Gent-centrum Oost-Vlaanderen 9000",
    "addr:housenumber":"53",
    "addr:postcode":"9000",
    "addr:street":"Citadellaan;Oost-Vlaanderen",
    "iso:country":"BE",
    "sg:address":"Citadellaan 53",
    "sg:city":"Gent-centrum",
    "sg:orig_category":"Advocaten and juridische adviseurs Balie van Gent",
    "sg:phone":"+32 9 222 51 01",
    "sg:postcode":"9000",
    "sg:province":"Oost-Vlaanderen",
    "wof:name":"Dua Anne Marie",
    "wof:placetype":"venue"
},
  "geometry": {"coordinates":[3.727971077,51.0386695862],"type":"Point"}
}