{
  "type": "Feature",
  "properties": {
    "addr:full":"Rue De Waremme 48 Villers-le-bouillet Li\u00e8ge 4530",
    "addr:housenumber":"48",
    "addr:postcode":"4530",
    "addr:street":"Rue De Waremme",
    "iso:country":"BE",
    "sg:address":"Rue De Waremme 48",
    "sg:city":"Villers-le-bouillet",
    "sg:orig_category":"Elektrische installaties voor woningen Gespecialiseerde residenti\u00eble bouw Technische and wetenschapp",
    "sg:phone":"+32 85 23 03 99",
    "sg:postcode":"4530",
    "sg:province":"Li\u00e8ge",
    "wof:name":"Guisse & Fils",
    "wof:placetype":"venue"
},
  "geometry": {"coordinates":[5.266023159,50.5703964233],"type":"Point"}
}