{
  "type": "Feature",
  "properties": {
    "iso:country":"BE",
    "sg:address":"Place De Nicolay 7",
    "sg:city":"Genappe",
    "sg:orig_category":"Advocaten and juridische adviseurs",
    "sg:phone":"+32 67 79 06 62",
    "sg:postcode":"1471",
    "sg:province":"Brabant Wallon",
    "wof:name":"P. Gougnard",
    "wof:placetype":"venue"
},
  "geometry": {"coordinates":[4.4445300102,50.5973358154],"type":"Point"}
}