{
  "type": "Feature",
  "properties": {
    "addr:full":"Cavatinestraat 28 Sint-jans-molenbeek/molenbeek-saint-jean Bruxelles-Capitale 1080",
    "addr:housenumber":"28",
    "addr:postcode":"1080",
    "addr:street":"Cavatinestraat",
    "iso:country":"BE",
    "sg:address":"Cavatinestraat 28",
    "sg:city":"Sint-jans-molenbeek/molenbeek-saint-jean",
    "sg:orig_category":"Kinderopvang",
    "sg:phone":"+32 2 411 63 33",
    "sg:postcode":"1080",
    "sg:province":"Bruxelles-Capitale",
    "wof:name":"Cr\u00c8che Calimero",
    "wof:placetype":"venue"
},
  "geometry": {"coordinates":[4.3006057739,50.8491821289],"type":"Point"}
}