{
  "type": "Feature",
  "properties": {
    "addr:full":"Place Albert-ier 37 Florenville Luxembourg 6820",
    "addr:housenumber":"37",
    "addr:postcode":"6820",
    "addr:street":"Place Albert-Ier",
    "iso:country":"BE",
    "sg:address":"Place Albert-ier 37",
    "sg:city":"Florenville",
    "sg:orig_category":"Meubles D\u00e9taillants, Am\u00e9nagement de B\u00e2timents et de Cuisines. Jeux de hasard. Fabrication and montag",
    "sg:phone":"+32 61 31 10 75",
    "sg:postcode":"6820",
    "sg:province":"Luxembourg",
    "wof:name":"Alain Planchard",
    "wof:placetype":"venue"
},
  "geometry": {"coordinates":[5.3102970123,49.698135376],"type":"Point"}
}