{
  "type": "Feature",
  "properties": {
    "addr:full":"Rue Ren\u00c9 Delhaize 118 Charleroi Hainaut 6043",
    "addr:housenumber":"118",
    "addr:postcode":"6043",
    "addr:street":"Rue Rene\u0301 Delhaize;Hainaut",
    "iso:country":"BE",
    "sg:address":"Rue Ren\u00c9 Delhaize 118",
    "sg:city":"Charleroi",
    "sg:orig_category":"Entretien and r\u00e9parations de voitures. V\u00e9hicules automobiles",
    "sg:phone":"+32 71 35 25 61",
    "sg:postcode":"6043",
    "sg:province":"Hainaut",
    "wof:name":"Garage Nagy",
    "wof:placetype":"venue"
},
  "geometry": {"coordinates":[4.4852371216,50.4644889832],"type":"Point"}
}