{
  "type": "Feature",
  "properties": {
    "addr:full":"Poederleesteenweg 108 Lichtaart Antwerpen 2460",
    "addr:housenumber":"108",
    "addr:postcode":"2460",
    "addr:street":"Poederleesteenweg",
    "iso:country":"BE",
    "sg:address":"Poederleesteenweg 108",
    "sg:city":"Lichtaart",
    "sg:classifiers":[
        {
            "category":"Professional",
            "subcategory":"Printing & Photocopies",
            "type":"Services"
        }
    ],
    "sg:phone":"+32 14 55 34 34",
    "sg:postcode":"2460",
    "sg:province":"Antwerpen",
    "sg:tags":[
        "shop",
        "industrial"
    ],
    "wof:name":"Drukkerij Baudoin & Companie Nv",
    "wof:placetype":"venue"
},
  "geometry": {"coordinates":[4.8984050751,51.2254943848],"type":"Point"}
}