{
  "type": "Feature",
  "properties": {
    "iso:country":"BE",
    "sg:address":"Chauss\u00c9e De Merchtem 113",
    "sg:city":"Wemmel",
    "sg:orig_category":"M\u00e9decins and sp\u00e9cialistes",
    "sg:phone":"+32 2 460 34 17",
    "sg:postcode":"1780",
    "sg:province":"Vlaams-Brabant",
    "wof:name":"S. Rypens",
    "wof:placetype":"venue"
},
  "geometry": {"coordinates":[4.3003997803,50.911239624],"type":"Point"}
}