{
  "type": "Feature",
  "properties": {
    "addr:full":"Zuster Bernardastraat 65 Halle Vlaams-Brabant 1500",
    "addr:housenumber":"65",
    "addr:postcode":"1500",
    "addr:street":"Zuster Bernardastraat",
    "iso:country":"BE",
    "sg:address":"Zuster Bernardastraat 65",
    "sg:city":"Halle",
    "sg:classifiers":[
        {
            "category":"Retail",
            "subcategory":"Repair Shop",
            "type":"Services"
        }
    ],
    "sg:phone":"+32 2 356 22 87",
    "sg:postcode":"1500",
    "sg:province":"Vlaams-Brabant",
    "sg:tags":[
        "radio",
        "television",
        "-",
        "maintenance"
    ],
    "wof:name":"Behets L",
    "wof:placetype":"venue"
},
  "geometry": {"coordinates":[4.231716156,50.7367630005],"type":"Point"}
}