{
  "type": "Feature",
  "properties": {
    "addr:full":"Grand'rue 22-24 Thuin Hainaut 6530",
    "addr:postcode":"22-24;6530",
    "addr:street":"Grand'Rue;Hainaut",
    "iso:country":"BE",
    "sg:address":"Grand'rue 22-24",
    "sg:city":"Thuin",
    "sg:classifiers":[
        {
            "category":"Real Estate",
            "subcategory":"Architect",
            "type":"Services"
        }
    ],
    "sg:phone":"+32 71 59 48 60",
    "sg:postcode":"6530",
    "sg:province":"Hainaut",
    "wof:name":"Joye F",
    "wof:placetype":"venue"
},
  "geometry": {"coordinates":[4.2896828651,50.3388442993],"type":"Point"}
}