{
  "type": "Feature",
  "properties": {
    "addr:full":"Hoogstr 60 Mol Antwerpen 2400",
    "addr:housenumber":"60",
    "addr:postcode":"2400",
    "addr:street":"Hoogstr",
    "iso:country":"BE",
    "sg:address":"Hoogstr 60",
    "sg:city":"Mol",
    "sg:classifiers":[
        {
            "category":"Manufacturing",
            "subcategory":"Building Materials",
            "type":"Manufacturing & Wholesale Goods"
        }
    ],
    "sg:phone":"+32 14 31 12 97",
    "sg:postcode":"2400",
    "sg:province":"Antwerpen",
    "sg:tags":[
        "raw",
        "energy"
    ],
    "wof:name":"Vanhees Metalen Nv",
    "wof:placetype":"venue"
},
  "geometry": {"coordinates":[5.1093149185,51.1827011108],"type":"Point"}
}