{
  "type": "Feature",
  "properties": {
    "addr:full":"Rue Des Montys 44 Louveign\u00e9 Li\u00e8ge 4141",
    "addr:housenumber":"44",
    "addr:postcode":"4141",
    "addr:street":"Rue Des Montys",
    "iso:country":"BE",
    "sg:address":"Rue Des Montys 44",
    "sg:city":"Louveign\u00e9",
    "sg:classifiers":[
        {
            "category":"Manufacturing",
            "subcategory":"Tools & Machinery",
            "type":"Manufacturing & Wholesale Goods"
        }
    ],
    "sg:phone":"+32 4 360 84 17",
    "sg:postcode":"4141",
    "sg:province":"Li\u00e8ge",
    "sg:tags":[
        "clamping"
    ],
    "wof:name":"Ets L. Rutten S.p.r.l.",
    "wof:placetype":"venue"
},
  "geometry": {"coordinates":[5.6994662285,50.5351448059],"type":"Point"}
}