{
  "type": "Feature",
  "properties": {
    "addr:full":"Gerard Davidstraat 1 Brugge West-Vlaanderen 8000",
    "addr:housenumber":"1",
    "addr:postcode":"8000",
    "addr:street":"Gerard Davidstraat",
    "iso:country":"BE",
    "sg:address":"Gerard Davidstraat 1",
    "sg:city":"Brugge",
    "sg:classifiers":[
        {
            "category":"Professional",
            "subcategory":"Lawyer & Legal Services",
            "type":"Services"
        }
    ],
    "sg:phone":"+32 50 31 86 91",
    "sg:postcode":"8000",
    "sg:province":"West-Vlaanderen",
    "wof:name":"De Becker Peter",
    "wof:placetype":"venue"
},
  "geometry": {"coordinates":[3.2079939842,51.2141838074],"type":"Point"}
}