{
  "type": "Feature",
  "properties": {
    "addr:full":"Dreef 25 Hoogstraten (meerle) Antwerpen 2328",
    "addr:housenumber":"25",
    "addr:postcode":"2328",
    "addr:street":"Dreef",
    "iso:country":"BE",
    "sg:address":"Dreef 25",
    "sg:city":"Hoogstraten (meerle)",
    "sg:classifiers":[
        {
            "category":"Farming",
            "subcategory":"Crops",
            "type":"Manufacturing & Wholesale Goods"
        }
    ],
    "sg:phone":"+32 3 315 72 65",
    "sg:postcode":"2328",
    "sg:province":"Antwerpen",
    "sg:tags":[
        "vegetable",
        "fruit",
        "-",
        "grower"
    ],
    "wof:name":"Geerts J",
    "wof:placetype":"venue"
},
  "geometry": {"coordinates":[4.8041949272,51.4741134644],"type":"Point"}
}