{
  "type": "Feature",
  "properties": {
    "addr:full":"Vosselaredorp 45 Nevele (vosselare) Oost-Vlaanderen 9850",
    "addr:housenumber":"45",
    "addr:postcode":"9850",
    "addr:street":"Vosselaredorp",
    "iso:country":"BE",
    "sg:address":"Vosselaredorp 45",
    "sg:city":"Nevele (vosselare)",
    "sg:classifiers":[
        {
            "category":"Bars & Pubs",
            "type":"Food & Drink"
        }
    ],
    "sg:phone":"+32 9 371 70 03",
    "sg:postcode":"9850",
    "sg:province":"Oost-Vlaanderen",
    "wof:name":"Flamingo",
    "wof:placetype":"venue"
},
  "geometry": {"coordinates":[3.5552370548,51.0263938904],"type":"Point"}
}