{
  "type": "Feature",
  "properties": {
    "addr:full":"Tervatestraat 55 Etterbeek Bruxelles-Capitale 1040",
    "addr:housenumber":"55",
    "addr:postcode":"1040",
    "addr:street":"Tervatestraat",
    "iso:country":"BE",
    "sg:address":"Tervatestraat 55",
    "sg:city":"Etterbeek",
    "sg:orig_category":"Zuivelproducten",
    "sg:phone":"+32 2 736 55 83",
    "sg:postcode":"1040",
    "sg:province":"Bruxelles-Capitale",
    "wof:name":"La Baratte",
    "wof:placetype":"venue"
},
  "geometry": {"coordinates":[4.4003601074,50.8304786682],"type":"Point"}
}