{
  "type": "Feature",
  "properties": {
    "addr:full":"Kasteeldreef 8ba Pittem West-Vlaanderen 8740",
    "addr:housenumber":"8ba",
    "addr:postcode":"8740",
    "addr:street":"Kasteeldreef",
    "iso:country":"BE",
    "sg:address":"Kasteeldreef 8ba",
    "sg:city":"Pittem",
    "sg:orig_category":"Woningbouw",
    "sg:phone":"+32 51 46 69 35",
    "sg:postcode":"8740",
    "sg:province":"West-Vlaanderen",
    "wof:name":"Popelier Gebrs",
    "wof:placetype":"venue"
},
  "geometry": {"coordinates":[3.2452349663,51.0127258301],"type":"Point"}
}