{
  "type": "Feature",
  "properties": {
    "iso:country":"BE",
    "sg:address":"Clos De La Rivi\u00e8re 18",
    "sg:city":"Ottignies-louvain-la-neuve (limelette)",
    "sg:classifiers":[
        {
            "category":"Retail",
            "subcategory":"Veterinary Services",
            "type":"Services"
        }
    ],
    "sg:phone":"+32 10 40 12 38",
    "sg:postcode":"1342",
    "sg:province":"Brabant Wallon",
    "sg:tags":[
        "veterinarian"
    ],
    "wof:name":"Charlier P",
    "wof:placetype":"venue"
},
  "geometry": {"coordinates":[4.5745611191,50.6760368347],"type":"Point"}
}