{
  "type": "Feature",
  "properties": {
    "iso:country":"BE",
    "sg:address":"Rue Des D\u00c9port\u00c9s 75",
    "sg:city":"Arlon",
    "sg:orig_category":"Rev\u00eatements pour sols and murs",
    "sg:phone":"+32 63 22 04 45",
    "sg:postcode":"6700",
    "sg:province":"Luxembourg",
    "wof:name":"Marbrerie Pagani",
    "wof:placetype":"venue"
},
  "geometry": {"coordinates":[5.8208508492,49.6791954041],"type":"Point"}
}