{
  "type": "Feature",
  "properties": {
    "addr:full":"Chauss\u00e9e De Bruxelles 378 Waterloo Brabant Wallon 1410",
    "addr:housenumber":"378",
    "addr:postcode":"1410",
    "addr:street":"Chausse\u0301E De Bruxelles",
    "iso:country":"BE",
    "sg:address":"Chauss\u00e9e De Bruxelles 378",
    "sg:city":"Waterloo",
    "sg:classifiers":[
        {
            "category":"Real Estate",
            "subcategory":"Architect",
            "type":"Services"
        }
    ],
    "sg:phone":"+32 2 351 49 95",
    "sg:postcode":"1410",
    "sg:province":"Brabant Wallon",
    "wof:name":"Demarteau & Partners",
    "wof:placetype":"venue"
},
  "geometry": {"coordinates":[4.4008412361,50.7100868225],"type":"Point"}
}