{
  "type": "Feature",
  "properties": {
    "iso:country":"BE",
    "sg:address":"Sint-paulusstraat 53",
    "sg:city":"Mol",
    "sg:orig_category":"Artsen and specialisten",
    "sg:phone":"+32 14 31 26 03",
    "sg:postcode":"2400",
    "sg:province":"Antwerpen",
    "wof:name":"Leo M.j. Belien",
    "wof:placetype":"venue"
},
  "geometry": {"coordinates":[5.1116271019,51.1888961792],"type":"Point"}
}