{
  "type": "Feature",
  "properties": {
    "addr:full":"Bergstrasse 37 Eupen Li\u00e8ge 4700",
    "addr:housenumber":"37",
    "addr:postcode":"4700",
    "addr:street":"Bergstrasse",
    "iso:country":"BE",
    "sg:address":"Bergstrasse 37",
    "sg:city":"Eupen",
    "sg:classifiers":[
        {
            "category":"Shopping",
            "subcategory":"Clothing, Apparel, & Fashions",
            "type":"Retail Goods"
        }
    ],
    "sg:phone":"+32 87 74 30 96",
    "sg:postcode":"4700",
    "sg:province":"Li\u00e8ge",
    "sg:tags":[
        "-",
        "clothing",
        "child"
    ],
    "wof:name":"Boys And Girls",
    "wof:placetype":"venue"
},
  "geometry": {"coordinates":[6.0333838463,50.6291160583],"type":"Point"}
}