{
  "type": "Feature",
  "properties": {
    "addr:full":"Mechelsestraat 7 Leuven Vlaams-Brabant 3000",
    "addr:housenumber":"7",
    "addr:postcode":"3000",
    "addr:street":"Mechelsestraat",
    "iso:country":"BE",
    "sg:address":"Mechelsestraat 7",
    "sg:city":"Leuven",
    "sg:classifiers":[
        {
            "category":"Shopping",
            "subcategory":"Shoes",
            "type":"Retail Goods"
        }
    ],
    "sg:phone":"+32 16 22 14 85",
    "sg:postcode":"3000",
    "sg:province":"Vlaams-Brabant",
    "sg:tags":[
        "slipper",
        "-"
    ],
    "wof:name":"Sumo",
    "wof:placetype":"venue"
},
  "geometry": {"coordinates":[4.7001109123,50.8803939819],"type":"Point"}
}