{
  "type": "Feature",
  "properties": {
    "iso:country":"BE",
    "sg:address":"Vijfseweg 150",
    "sg:city":"Waregem",
    "sg:orig_category":"M\u00e9decins and sp\u00e9cialistes",
    "sg:phone":"+32 56 62 35 46",
    "sg:postcode":"8790",
    "sg:province":"West-Vlaanderen",
    "wof:name":"Beatrijs Geeroms",
    "wof:placetype":"venue"
},
  "geometry": {"coordinates":[3.4170720577,50.8994216919],"type":"Point"}
}