{
  "type": "Feature",
  "properties": {
    "iso:country":"BE",
    "sg:address":"Avenue Fran\u00e7ois Cornesse 28",
    "sg:city":"Aywaille",
    "sg:classifiers":[
        {
            "category":"Banks & Credit Unions",
            "subcategory":"Investment Brokerage",
            "type":"Services"
        }
    ],
    "sg:phone":"+32 4 384 59 88",
    "sg:postcode":"4920",
    "sg:province":"Li\u00e8ge",
    "sg:tags":[
        "jean",
        "casual",
        "wear"
    ],
    "wof:name":"Jeans'rie (la)",
    "wof:placetype":"venue"
},
  "geometry": {"coordinates":[5.6740651131,50.4748306274],"type":"Point"}
}