{
  "type": "Feature",
  "properties": {
    "addr:full":"Rue De Bourgogne 44 Vorst/forest Bruxelles-Capitale 1190",
    "addr:housenumber":"44",
    "addr:postcode":"1190",
    "addr:street":"Rue De Bourgogne;/ Forest",
    "iso:country":"BE",
    "sg:address":"Rue De Bourgogne 44",
    "sg:city":"Vorst/forest",
    "sg:orig_category":"Architectes",
    "sg:phone":"+32 2 347 01 34",
    "sg:postcode":"1190",
    "sg:province":"Bruxelles-Capitale",
    "wof:name":"Dominique Maus",
    "wof:placetype":"venue"
},
  "geometry": {"coordinates":[4.32685709,50.8123397827],"type":"Point"}
}