{
  "type": "Feature",
  "properties": {
    "iso:country":"BE",
    "sg:address":"Herbesthaler Strasse 265bb",
    "sg:city":"Eupen",
    "sg:orig_category":"Bouwmaterialen Gh Loodgieterij and centrale verwarming Gh",
    "sg:phone":"+32 87 59 57 70",
    "sg:postcode":"4700",
    "sg:province":"Li\u00e8ge",
    "wof:name":"Somarco",
    "wof:placetype":"venue"
},
  "geometry": {"coordinates":[6.0133328438,50.641456604],"type":"Point"}
}