{
  "type": "Feature",
  "properties": {
    "iso:country":"BE",
    "sg:address":"Rue De Diekirch 30",
    "sg:city":"Arlon",
    "sg:classifiers":[
        {
            "category":"Cafe",
            "type":"Food & Drink"
        }
    ],
    "sg:phone":"+32 63 21 78 73",
    "sg:postcode":"6700",
    "sg:province":"Luxembourg",
    "sg:tags":[
        "caf\u00e9s"
    ],
    "wof:name":"Caf\u00c9 Le Mercury",
    "wof:placetype":"venue"
},
  "geometry": {"coordinates":[5.8131308556,49.6850242615],"type":"Point"}
}