{
  "type": "Feature",
  "properties": {
    "addr:full":"Place Albert L 32 Courcelles Hainaut 6183",
    "addr:housenumber":"32",
    "addr:postcode":"6183",
    "addr:street":"Place Albert L",
    "iso:country":"BE",
    "sg:address":"Place Albert L 32",
    "sg:city":"Courcelles",
    "sg:classifiers":[
        {
            "category":"Restaurant",
            "type":"Food & Drink"
        }
    ],
    "sg:phone":"+32 71 45 10 66",
    "sg:postcode":"6183",
    "sg:province":"Hainaut",
    "wof:name":"L' Amadeus",
    "wof:placetype":"venue"
},
  "geometry": {"coordinates":[4.3305897713,50.4651794434],"type":"Point"}
}