{
  "type": "Feature",
  "properties": {
    "iso:country":"BE",
    "sg:address":"Rue De Fosses 2-6a",
    "sg:city":"Jemeppe-sur-sambre (ham-sur-sambre)",
    "sg:classifiers":[
        {
            "category":"Professional",
            "subcategory":"Lawyer & Legal Services",
            "type":"Services"
        }
    ],
    "sg:phone":"+32 71 78 79 11",
    "sg:postcode":"5190",
    "sg:province":"Namur",
    "wof:name":"Gobert Jean-marie",
    "wof:placetype":"venue"
},
  "geometry": {"coordinates":[4.6703448296,50.4645042419],"type":"Point"}
}