{
  "type": "Feature",
  "properties": {
    "addr:full":"Rue M\u00e9lart 30 Huy Li\u00e8ge 4500",
    "addr:housenumber":"30",
    "addr:postcode":"4500",
    "addr:street":"Rue Me\u0301Lart",
    "iso:country":"BE",
    "sg:address":"Rue M\u00e9lart 30",
    "sg:city":"Huy",
    "sg:classifiers":[
        {
            "category":"Professional",
            "subcategory":"Accounting & Tax Preparation",
            "type":"Services"
        }
    ],
    "sg:phone":"+32 85 25 33 76",
    "sg:postcode":"4500",
    "sg:province":"Li\u00e8ge",
    "sg:tags":[
        "bookkeeper"
    ],
    "wof:name":"Denis J-f",
    "wof:placetype":"venue"
},
  "geometry": {"coordinates":[5.2285480499,50.5265579224],"type":"Point"}
}