{
  "type": "Feature",
  "properties": {
    "iso:country":"BE",
    "sg:address":"Statiestraat 111",
    "sg:city":"Ternat",
    "sg:orig_category":"Krantenwinkels Rookartikelen",
    "sg:phone":"+32 2 582 32 46",
    "sg:postcode":"1740",
    "sg:province":"Vlaams-Brabant",
    "wof:name":"Boekhandel Patrick",
    "wof:placetype":"venue"
},
  "geometry": {"coordinates":[4.1654458046,50.8743171692],"type":"Point"}
}