{
  "type": "Feature",
  "properties": {
    "iso:country":"BE",
    "sg:address":"Rue Broy\u00e8re 6",
    "sg:city":"Bruxelles (anderlecht)",
    "sg:orig_category":"Chromium Oxide Pigments",
    "sg:phone":"+32 3 825 00 55",
    "sg:postcode":"1070",
    "sg:province":"Bruxelles-Capitale",
    "wof:name":"Anc. Ets. Stoopen En Mee\u00fbs Nv",
    "wof:placetype":"venue"
},
  "geometry": {"coordinates":[4.3416762352,51.1586990356],"type":"Point"}
}