{
  "type": "Feature",
  "properties": {
    "iso:country":"BE",
    "sg:address":"Avenue De La Salm 37",
    "sg:city":"Vielsalm",
    "sg:classifiers":[
        {
            "category":"Shopping",
            "subcategory":"Bicycles & Sporting Goods",
            "type":"Retail Goods"
        }
    ],
    "sg:phone":"+32 80 21 68 94",
    "sg:postcode":"6690",
    "sg:province":"Luxembourg",
    "sg:tags":[
        "sport",
        "-"
    ],
    "wof:name":"Borremans Ets",
    "wof:placetype":"venue"
},
  "geometry": {"coordinates":[5.9120578766,50.2801933289],"type":"Point"}
}