{
  "type": "Feature",
  "properties": {
    "addr:full":"Avenue Jean Sib\u00e9lius 16 Box 3 Bruxelles (anderlecht) Bruxelles-Capitale 1070",
    "addr:housenumber":"16;3",
    "addr:postcode":"1070",
    "addr:street":"Avenue Jean Sibe\u0301Lius;Box",
    "iso:country":"BE",
    "sg:address":"Avenue Jean Sib\u00e9lius 16 Box 3",
    "sg:city":"Bruxelles (anderlecht)",
    "sg:classifiers":[
        {
            "category":"Insurance",
            "subcategory":"Insurance Agent",
            "type":"Services"
        }
    ],
    "sg:phone":"+32 2 527 82 71",
    "sg:postcode":"1070",
    "sg:province":"Bruxelles-Capitale",
    "sg:tags":[
        "broker"
    ],
    "wof:name":"Hannouille & Co Sa",
    "wof:placetype":"venue"
},
  "geometry": {"coordinates":[4.2835187912,50.8302001953],"type":"Point"}
}