{
  "type": "Feature",
  "properties": {
    "addr:full":"Jozef Rommensstraat 11 Beerse Antwerpen 2340",
    "addr:housenumber":"11",
    "addr:postcode":"2340",
    "addr:street":"Jozef Rommensstraat",
    "iso:country":"BE",
    "sg:address":"Jozef Rommensstraat 11",
    "sg:city":"Beerse",
    "sg:classifiers":[
        {
            "category":"Manufacturing",
            "subcategory":"Metals",
            "type":"Manufacturing & Wholesale Goods"
        }
    ],
    "sg:phone":"+32 14 61 89 53",
    "sg:postcode":"2340",
    "sg:province":"Antwerpen",
    "sg:tags":[
        "working"
    ],
    "wof:name":"Henrothy D",
    "wof:placetype":"venue"
},
  "geometry": {"coordinates":[4.858039856,51.323928833],"type":"Point"}
}