{
  "type": "Feature",
  "properties": {
    "addr:full":"Brugstraat 5b11 Antwerpen Antwerpen 2060",
    "addr:housenumber":"5b11",
    "addr:postcode":"2060",
    "addr:street":"Brugstraat",
    "iso:country":"BE",
    "sg:address":"Brugstraat 5b11",
    "sg:city":"Antwerpen",
    "sg:classifiers":[
        {
            "category":"Shopping Center",
            "type":"Public Place"
        }
    ],
    "sg:phone":"+32 3 231 22 60",
    "sg:postcode":"2060",
    "sg:province":"Antwerpen",
    "sg:tags":[
        "enseignement",
        "formation"
    ],
    "wof:name":"Loftware",
    "wof:placetype":"venue"
},
  "geometry": {"coordinates":[4.4183478355,51.2265510559],"type":"Point"}
}