{
  "type": "Feature",
  "properties": {
    "iso:country":"BE",
    "sg:address":"Industrielaan 32",
    "sg:city":"Hoeselt",
    "sg:classifiers":[
        {
            "category":"Organizations",
            "subcategory":"Professional Association",
            "type":"Services"
        }
    ],
    "sg:phone":"+32 475 21 91 95",
    "sg:postcode":"3730",
    "sg:province":"Limburg",
    "sg:tags":[
        "organisation",
        "seminar"
    ],
    "wof:name":"Wpc",
    "wof:placetype":"venue"
},
  "geometry": {"coordinates":[5.4860200882,50.8581008911],"type":"Point"}
}