{
  "type": "Feature",
  "properties": {
    "addr:full":"Lescreve 2 Silly (bassilly) Hainaut 7830",
    "addr:housenumber":"2",
    "addr:postcode":"7830",
    "addr:street":"Lescreve",
    "iso:country":"BE",
    "sg:address":"Lescreve 2",
    "sg:city":"Silly (bassilly)",
    "sg:classifiers":[
        {
            "category":"Travel",
            "subcategory":"Resort",
            "type":"Entertainment"
        }
    ],
    "sg:phone":"+32 68 56 84 55",
    "sg:postcode":"7830",
    "sg:province":"Hainaut",
    "sg:tags":[
        "farm",
        "house",
        "holiday",
        "guest"
    ],
    "wof:name":"Clef Dechamps (la)",
    "wof:placetype":"venue"
},
  "geometry": {"coordinates":[3.9231450558,50.6907043457],"type":"Point"}
}