{
  "type": "Feature",
  "properties": {
    "iso:country":"BE",
    "sg:address":"Stijn Streuvelsstraat 19",
    "sg:city":"Waregem",
    "sg:orig_category":"Stations-service and carburants. V\u00e9hicules automobiles",
    "sg:phone":"+32 56 60 73 73",
    "sg:postcode":"8790",
    "sg:province":"West-Vlaanderen",
    "wof:name":"Frehencar",
    "wof:placetype":"venue"
},
  "geometry": {"coordinates":[3.4165139198,50.8809394836],"type":"Point"}
}