{
  "type": "Feature",
  "properties": {
    "iso:country":"BE",
    "sg:address":"Rue Des B\u00e9gonias 51",
    "sg:city":"Bruxelles (watermael-boitsfort)",
    "sg:classifiers":[
        {
            "category":"Communications",
            "subcategory":"Film & Video Production",
            "type":"Services"
        }
    ],
    "sg:phone":"+32 2 663 50 90",
    "sg:postcode":"1170",
    "sg:province":"Bruxelles-Capitale",
    "sg:tags":[
        "realisation",
        "-"
    ],
    "wof:name":"A.t. Production",
    "wof:placetype":"venue"
},
  "geometry": {"coordinates":[4.4044928551,50.8117523193],"type":"Point"}
}