{
  "type": "Feature",
  "properties": {
    "addr:full":"Rue Saint-m\u00e9dard 18 Jodoigne Brabant Wallon 1370",
    "addr:housenumber":"18",
    "addr:postcode":"1370",
    "addr:street":"Rue Saint-Me\u0301Dard",
    "iso:country":"BE",
    "sg:address":"Rue Saint-m\u00e9dard 18",
    "sg:city":"Jodoigne",
    "sg:classifiers":[
        {
            "category":"Home & Garden",
            "subcategory":"Hardware",
            "type":"Retail Goods"
        }
    ],
    "sg:phone":"+32 10 81 12 27",
    "sg:postcode":"1370",
    "sg:province":"Brabant Wallon",
    "sg:tags":[
        "-"
    ],
    "wof:name":"Gilsoul D",
    "wof:placetype":"venue"
},
  "geometry": {"coordinates":[4.8684821129,50.7226219177],"type":"Point"}
}