{
  "type": "Feature",
  "properties": {
    "addr:full":"Rue De Namur 35 Wavre Brabant Wallon 1300",
    "addr:housenumber":"35;1300",
    "addr:street":"Rue De Namur",
    "iso:country":"BE",
    "sg:address":"Rue De Namur 35",
    "sg:city":"Wavre",
    "sg:orig_category":"Immobili\u00ebnkantoren",
    "sg:phone":"+32 10 22 52 22",
    "sg:postcode":"1300",
    "sg:province":"Brabant Wallon",
    "wof:name":"Era Europimo",
    "wof:placetype":"venue"
},
  "geometry": {"coordinates":[4.611700058,50.7125587463],"type":"Point"}
}