{
  "type": "Feature",
  "properties": {
    "iso:country":"BE",
    "sg:address":"Route De Housse 64",
    "sg:city":"Bl\u00e9gny (housse)",
    "sg:classifiers":[
        {
            "category":"Professional",
            "subcategory":"Accounting & Tax Preparation",
            "type":"Services"
        }
    ],
    "sg:phone":"+32 4 387 76 66",
    "sg:postcode":"4671",
    "sg:province":"Li\u00e8ge",
    "sg:tags":[
        "accountant"
    ],
    "wof:name":"Albert I",
    "wof:placetype":"venue"
},
  "geometry": {"coordinates":[5.6820588112,50.6480712891],"type":"Point"}
}