{
  "type": "Feature",
  "properties": {
    "addr:full":"Woluwedal 18 Brussel Bruxelles-Capitale 1000",
    "addr:housenumber":"18",
    "addr:postcode":"1000",
    "addr:street":"Woluwedal",
    "iso:country":"BE",
    "sg:address":"Woluwedal 18",
    "sg:city":"Brussel",
    "sg:classifiers":[
        {
            "category":"Professional",
            "subcategory":"Accounting & Tax Preparation",
            "type":"Services"
        }
    ],
    "sg:phone":"+32 2 710 70 00",
    "sg:postcode":"1000",
    "sg:province":"Bruxelles-Capitale",
    "sg:tags":[
        "bookkeeping"
    ],
    "wof:name":"Pricewaterhousecoopers Accountants Nv",
    "wof:placetype":"venue"
},
  "geometry": {"coordinates":[4.3496851921,50.8483848572],"type":"Point"}
}