{
  "type": "Feature",
  "properties": {
    "addr:full":"Meierij 45 Geraardsbergen (zandbergen) Oost-Vlaanderen 9506",
    "addr:housenumber":"45",
    "addr:postcode":"9506",
    "addr:street":"Meierij;Zandbergen Oost-Vlaanderen",
    "iso:country":"BE",
    "sg:address":"Meierij 45",
    "sg:city":"Geraardsbergen (zandbergen)",
    "sg:classifiers":[
        {
            "category":"Building & Trades",
            "subcategory":"Construction",
            "type":"Services"
        }
    ],
    "sg:phone":"+32 54 32 63 34",
    "sg:postcode":"9506",
    "sg:province":"Oost-Vlaanderen",
    "sg:tags":[
        "stucco",
        "contractor"
    ],
    "wof:name":"Lupa Bvba",
    "wof:placetype":"venue"
},
  "geometry": {"coordinates":[3.9472839832,50.7854270935],"type":"Point"}
}