{
  "type": "Feature",
  "properties": {
    "addr:full":"Doornikserijksweg 9 Kortrijk West-Vlaanderen 8510",
    "addr:housenumber":"9",
    "addr:postcode":"8510",
    "addr:street":"Doornikserijksweg",
    "iso:country":"BE",
    "sg:address":"Doornikserijksweg 9",
    "sg:city":"Kortrijk",
    "sg:classifiers":[
        {
            "category":"Building & Trades",
            "subcategory":"Construction",
            "type":"Services"
        }
    ],
    "sg:phone":"+32 56 21 82 29",
    "sg:postcode":"8510",
    "sg:province":"West-Vlaanderen",
    "sg:tags":[
        "la",
        "de",
        "\u00e9quipement",
        "pour",
        "machine",
        "location",
        "equipements"
    ],
    "wof:name":"Lauwers Heftruck Service",
    "wof:placetype":"venue"
},
  "geometry": {"coordinates":[3.2925920486,50.7910995483],"type":"Point"}
}