{
  "type": "Feature",
  "properties": {
    "addr:full":"Gentsesteenweg 529 Erpe-mere (erondegem) Oost-Vlaanderen 9420",
    "addr:housenumber":"529",
    "addr:postcode":"9420",
    "addr:street":"Gentsesteenweg",
    "iso:country":"BE",
    "sg:address":"Gentsesteenweg 529",
    "sg:city":"Erpe-mere (erondegem)",
    "sg:classifiers":[
        {
            "category":"Professional",
            "subcategory":"Accounting & Tax Preparation",
            "type":"Services"
        }
    ],
    "sg:phone":"+32 53 80 55 53",
    "sg:postcode":"9420",
    "sg:province":"Oost-Vlaanderen",
    "sg:tags":[
        "accountant"
    ],
    "wof:name":"Van Den Abeele R",
    "wof:placetype":"venue"
},
  "geometry": {"coordinates":[3.9438099861,50.948589325],"type":"Point"}
}