{
  "type": "Feature",
  "properties": {
    "iso:country":"BE",
    "sg:address":"Vilvoordelaan 94 Box 1",
    "sg:city":"Zaventem",
    "sg:classifiers":[
        {
            "category":"Health Services",
            "subcategory":"Health Practitioner",
            "type":"Services"
        }
    ],
    "sg:phone":"+32 2 721 58 38",
    "sg:postcode":"1930",
    "sg:province":"Vlaams-Brabant",
    "sg:tags":[
        "physiotherapist"
    ],
    "wof:name":"Wuyts Frieda",
    "wof:placetype":"venue"
},
  "geometry": {"coordinates":[4.4712738991,50.8892974854],"type":"Point"}
}