{
  "type": "Feature",
  "properties": {
    "addr:full":"Bussegem 12 Sint-lievens-houtem Oost-Vlaanderen 9520",
    "addr:housenumber":"12",
    "addr:postcode":"9520",
    "addr:street":"Bussegem;Oost-Vlaanderen",
    "iso:country":"BE",
    "sg:address":"Bussegem 12",
    "sg:city":"Sint-lievens-houtem",
    "sg:orig_category":"Producteurs de l\u00e9gumes",
    "sg:phone":"+32 9 368 16 56",
    "sg:postcode":"9520",
    "sg:province":"Oost-Vlaanderen",
    "wof:name":"Christian Van Bever",
    "wof:placetype":"venue"
},
  "geometry": {"coordinates":[3.8894119263,50.9489631653],"type":"Point"}
}