{
  "type": "Feature",
  "properties": {
    "iso:country":"BE",
    "sg:address":"Rue Sylvain Gouverneur 37",
    "sg:city":"Ans",
    "sg:orig_category":"Charpentes and couvertures. Plomberie, chauffage and installations sanitaires",
    "sg:phone":"+32 4 263 84 77",
    "sg:postcode":"4430",
    "sg:province":"Li\u00e8ge",
    "wof:name":"Sanit - Chauffe Et Toitures",
    "wof:placetype":"venue"
},
  "geometry": {"coordinates":[5.5384187698,50.6582527161],"type":"Point"}
}