{
  "type": "Feature",
  "properties": {
    "addr:full":"Brusselsestraat 66 Dendermonde Oost-Vlaanderen 9200",
    "addr:housenumber":"66",
    "addr:postcode":"9200",
    "addr:street":"Brusselsestraat;Oost-Vlaanderen",
    "iso:country":"BE",
    "sg:address":"Brusselsestraat 66",
    "sg:city":"Dendermonde",
    "sg:classifiers":[
        {
            "category":"Shopping",
            "subcategory":"Bridal",
            "type":"Retail Goods"
        }
    ],
    "sg:phone":"+32 52 22 63 14",
    "sg:postcode":"9200",
    "sg:province":"Oost-Vlaanderen",
    "sg:tags":[
        "list",
        "-",
        "present",
        "wedding"
    ],
    "wof:name":"Alexander",
    "wof:placetype":"venue"
},
  "geometry": {"coordinates":[4.1002779007,51.0269584656],"type":"Point"}
}