{
  "type": "Feature",
  "properties": {
    "iso:country":"BE",
    "sg:address":"Opitterstraat 19",
    "sg:city":"Bree",
    "sg:classifiers":[
        {
            "category":"Restaurant",
            "type":"Food & Drink"
        }
    ],
    "sg:phone":"+32 89 46 82 73",
    "sg:postcode":"3960",
    "sg:province":"Limburg",
    "wof:name":"Sakkara",
    "wof:placetype":"venue"
},
  "geometry": {"coordinates":[5.5999131203,51.1409568787],"type":"Point"}
}