{
  "type": "Feature",
  "properties": {
    "addr:full":"Chauss\u00c9e De Dinant 84 Namur Namur 5000",
    "addr:housenumber":"84",
    "addr:postcode":"5000",
    "addr:street":"Chausse\u0301E De Dinant",
    "iso:country":"BE",
    "sg:address":"Chauss\u00c9e De Dinant 84",
    "sg:city":"Namur",
    "sg:orig_category":"Banken and kredietinstellingen",
    "sg:phone":"+32 81 22 53 31",
    "sg:postcode":"5000",
    "sg:province":"Namur",
    "wof:name":"Fortis",
    "wof:placetype":"venue"
},
  "geometry": {"coordinates":[4.8563961983,50.4497146606],"type":"Point"}
}