{
  "type": "Feature",
  "properties": {
    "iso:country":"BE",
    "sg:address":"Pieter De Cockelaerestraat 6",
    "sg:city":"Kortrijk",
    "sg:classifiers":[
        {
            "category":"Personal",
            "subcategory":"Beauty Salon",
            "type":"Services"
        }
    ],
    "sg:phone":"+32 56 21 46 16",
    "sg:postcode":"8500",
    "sg:province":"West-Vlaanderen",
    "wof:name":"Billiau",
    "wof:placetype":"venue"
},
  "geometry": {"coordinates":[3.2664549351,50.8286781311],"type":"Point"}
}