{
  "type": "Feature",
  "properties": {
    "addr:full":"Sint-cordulastraat 34 Schoten Antwerpen 2900",
    "addr:housenumber":"34",
    "addr:postcode":"2900",
    "addr:street":"Sint-Cordulastraat",
    "iso:country":"BE",
    "sg:address":"Sint-cordulastraat 34",
    "sg:city":"Schoten",
    "sg:classifiers":[
        {
            "category":"Professional",
            "subcategory":"Advertising",
            "type":"Services"
        }
    ],
    "sg:phone":"+32 3 658 27 74",
    "sg:postcode":"2900",
    "sg:province":"Antwerpen",
    "sg:tags":[
        "item",
        "-",
        "business",
        "gift",
        "promotional"
    ],
    "wof:name":"Old Bacchus Bvba",
    "wof:placetype":"venue"
},
  "geometry": {"coordinates":[4.4990901947,51.2499885559],"type":"Point"}
}