{
  "type": "Feature",
  "properties": {
    "addr:full":"Rue Hamoir 203 La Louvi\u00e8re Hainaut 7100",
    "addr:housenumber":"203",
    "addr:postcode":"7100",
    "addr:street":"Rue Hamoir",
    "iso:country":"BE",
    "sg:address":"Rue Hamoir 203",
    "sg:city":"La Louvi\u00e8re",
    "sg:classifiers":[
        {
            "category":"Professional",
            "subcategory":"Computer Services",
            "type":"Services"
        }
    ],
    "sg:phone":"+32 64 33 53 69",
    "sg:postcode":"7100",
    "sg:province":"Hainaut",
    "sg:tags":[
        "network"
    ],
    "wof:name":"Accis Engineering Sa",
    "wof:placetype":"venue"
},
  "geometry": {"coordinates":[4.1964950562,50.4750061035],"type":"Point"}
}