{
  "type": "Feature",
  "properties": {
    "addr:full":"Avenue De La Couronne 340 Bruxelles (ixelles) Bruxelles-Capitale 1050",
    "addr:housenumber":"340",
    "addr:postcode":"1050",
    "addr:street":"Avenue De La Couronne",
    "iso:country":"BE",
    "sg:address":"Avenue De La Couronne 340",
    "sg:city":"Bruxelles (ixelles)",
    "sg:classifiers":[
        {
            "category":"Professional",
            "subcategory":"Lawyer & Legal Services",
            "type":"Services"
        }
    ],
    "sg:phone":"+32 2 649 94 94",
    "sg:postcode":"1050",
    "sg:province":"Bruxelles-Capitale",
    "wof:name":"Wolff Julien",
    "wof:placetype":"venue"
},
  "geometry": {"coordinates":[4.3865990639,50.8238792419],"type":"Point"}
}