{
  "type": "Feature",
  "properties": {
    "addr:full":"Bredabaan 782 Brasschaat Antwerpen 2930",
    "addr:housenumber":"782",
    "addr:postcode":"2930",
    "addr:street":"Bredabaan",
    "iso:country":"BE",
    "sg:address":"Bredabaan 782",
    "sg:city":"Brasschaat",
    "sg:classifiers":[
        {
            "category":"Bars & Pubs",
            "type":"Food & Drink"
        }
    ],
    "sg:phone":"+32 3 633 35 27",
    "sg:postcode":"2930",
    "sg:province":"Antwerpen",
    "wof:name":"Stad Antwerpen",
    "wof:placetype":"venue"
},
  "geometry": {"coordinates":[4.5202898979,51.3237190247],"type":"Point"}
}