{
  "type": "Feature",
  "properties": {
    "iso:country":"BE",
    "sg:address":"Ridder De Ghellinckstraat 11",
    "sg:city":"Wielsbeke",
    "sg:orig_category":"Non-Classified Establishments",
    "sg:phone":"+32 56 66 30 10",
    "sg:postcode":"8710",
    "sg:province":"West-Vlaanderen",
    "wof:name":"Atex",
    "wof:placetype":"venue"
},
  "geometry": {"coordinates":[3.350425005,50.9098548889],"type":"Point"}
}