{
  "type": "Feature",
  "properties": {
    "addr:full":"Hagelberg 11 - Industriezone 3 'de Heze' Olen Antwerpen 2250",
    "addr:housenumber":"11;3",
    "addr:postcode":"2250",
    "addr:street":"Hagelberg;Industriezone;Heze ' Olen",
    "iso:country":"BE",
    "sg:address":"Hagelberg 11 - Industriezone 3 'de Heze'",
    "sg:city":"Olen",
    "sg:classifiers":[
        {
            "category":"Government",
            "subcategory":"Fire Station",
            "type":"Public Place"
        }
    ],
    "sg:phone":"+32 14 86 16 16",
    "sg:postcode":"2250",
    "sg:province":"Antwerpen",
    "sg:tags":[
        "medium",
        "blast"
    ],
    "wof:name":"Laborex B.v.b.a.",
    "wof:placetype":"venue"
},
  "geometry": {"coordinates":[4.9085221291,51.1487541199],"type":"Point"}
}