{
  "type": "Feature",
  "properties": {
    "addr:full":"Rue Alfred Defuisseaux 67 Charleroi Hainaut 6042",
    "addr:housenumber":"67",
    "addr:postcode":"6042",
    "addr:street":"Rue Alfred Defuisseaux;Hainaut",
    "iso:country":"BE",
    "sg:address":"Rue Alfred Defuisseaux 67",
    "sg:city":"Charleroi",
    "sg:orig_category":"Elektrische installaties voor woningen",
    "sg:phone":"+32 71 31 07 21",
    "sg:postcode":"6042",
    "sg:province":"Hainaut",
    "wof:name":"Martine Piette",
    "wof:placetype":"venue"
},
  "geometry": {"coordinates":[4.4490199089,50.4293518066],"type":"Point"}
}