{
  "type": "Feature",
  "properties": {
    "addr:full":"Boulevard Poincar\u00c9 78 Sint-gillis/saint-gilles Bruxelles-Capitale 1060",
    "addr:housenumber":"78",
    "addr:postcode":"1060",
    "addr:street":"Boulevard Poincare\u0301",
    "iso:country":"BE",
    "sg:address":"Boulevard Poincar\u00c9 78",
    "sg:city":"Sint-gillis/saint-gilles",
    "sg:orig_category":"S\u00e9curit\u00e9 sociale",
    "sg:phone":"+32 2 240 86 67",
    "sg:postcode":"1060",
    "sg:province":"Bruxelles-Capitale",
    "wof:name":"Christelijke Mutualiteit",
    "wof:placetype":"venue"
},
  "geometry": {"coordinates":[4.3400111198,50.8401908875],"type":"Point"}
}