{
  "type": "Feature",
  "properties": {
    "addr:full":"Wondelgemstraat 99 Gent Oost-Vlaanderen 9000",
    "addr:housenumber":"99",
    "addr:postcode":"9000",
    "addr:street":"Wondelgemstraat;Oost-Vlaanderen",
    "iso:country":"BE",
    "sg:address":"Wondelgemstraat 99",
    "sg:city":"Gent",
    "sg:orig_category":"Opticiens",
    "sg:phone":"+32 9 225 02 42",
    "sg:postcode":"9000",
    "sg:province":"Oost-Vlaanderen",
    "wof:name":"Trioptic",
    "wof:placetype":"venue"
},
  "geometry": {"coordinates":[3.7098441124,51.0623664856],"type":"Point"}
}