{
  "type": "Feature",
  "properties": {
    "iso:country":"BE",
    "sg:address":"Wettersesteenweg 39",
    "sg:city":"Sint-lievens-houtem",
    "sg:classifiers":[
        {
            "category":"Personal",
            "subcategory":"Beauty Salon",
            "type":"Services"
        }
    ],
    "sg:phone":"+32 53 62 71 01",
    "sg:postcode":"9520",
    "sg:province":"Oost-Vlaanderen",
    "sg:tags":[
        "lady",
        "-",
        "hairdressing"
    ],
    "wof:name":"Figaro",
    "wof:placetype":"venue"
},
  "geometry": {"coordinates":[3.8500809669,50.9277610779],"type":"Point"}
}