{
  "type": "Feature",
  "properties": {
    "iso:country":"BE",
    "sg:address":"Zevekotestraat 22",
    "sg:city":"Poperinge",
    "sg:orig_category":"Artsen and specialisten",
    "sg:phone":"+32 57 33 35 12",
    "sg:postcode":"8970",
    "sg:province":"West-Vlaanderen",
    "wof:name":"Gerard Desmyter",
    "wof:placetype":"venue"
},
  "geometry": {"coordinates":[2.7650830746,50.815284729],"type":"Point"}
}