{
  "type": "Feature",
  "properties": {
    "iso:country":"BE",
    "sg:address":"Broekstraat",
    "sg:city":"Westerlo",
    "sg:classifiers":[
        {
            "category":"Arena",
            "subcategory":"Sports Club",
            "type":"Entertainment"
        }
    ],
    "sg:phone":"+32 14 54 78 45",
    "sg:postcode":"2260",
    "sg:province":"Antwerpen",
    "wof:name":"Tennisclub Westerlo Vzw",
    "wof:placetype":"venue"
},
  "geometry": {"coordinates":[4.8892531395,51.0797767639],"type":"Point"}
}