{
  "type": "Feature",
  "properties": {
    "iso:country":"BE",
    "sg:address":"Rue Coll\u00c9e 3",
    "sg:city":"Li\u00c8ge",
    "sg:orig_category":"Salles de conf\u00e9rences and de r\u00e9ceptions",
    "sg:phone":"+32 4 367 03 57",
    "sg:postcode":"4031",
    "sg:province":"Li\u00e8ge",
    "wof:name":"Salle St.remi",
    "wof:placetype":"venue"
},
  "geometry": {"coordinates":[5.6021900177,50.6109352112],"type":"Point"}
}