{
  "type": "Feature",
  "properties": {
    "addr:full":"Waverstraat 89 Aalst Oost-Vlaanderen 9310",
    "addr:housenumber":"89",
    "addr:postcode":"9310",
    "addr:street":"Waverstraat",
    "iso:country":"BE",
    "sg:address":"Waverstraat 89",
    "sg:city":"Aalst",
    "sg:orig_category":"Slagers",
    "sg:phone":"+32 53 70 22 02",
    "sg:postcode":"9310",
    "sg:province":"Oost-Vlaanderen",
    "wof:name":"Hendrik Van Den Steen",
    "wof:placetype":"venue"
},
  "geometry": {"coordinates":[4.1004261971,50.9378242493],"type":"Point"}
}