{
  "type": "Feature",
  "properties": {
    "iso:country":"BE",
    "sg:address":"Rue De La Station 77",
    "sg:city":"Charleroi (jumet)",
    "sg:classifiers":[
        {
            "category":"Personal",
            "subcategory":"Barber",
            "type":"Services"
        }
    ],
    "sg:phone":"+32 71 34 09 04",
    "sg:postcode":"6040",
    "sg:province":"Hainaut",
    "sg:tags":[
        "gentleman",
        "salon",
        "-",
        "hairdressing"
    ],
    "wof:name":"Jose",
    "wof:placetype":"venue"
},
  "geometry": {"coordinates":[4.4340629578,50.4416351318],"type":"Point"}
}