{
  "type": "Feature",
  "properties": {
    "iso:country":"BE",
    "sg:address":"Avenue Des Martyrs 243",
    "sg:city":"Fleron",
    "sg:classifiers":[
        {
            "category":"Cafe",
            "type":"Food & Drink"
        }
    ],
    "sg:phone":"+32 4 358 30 34",
    "sg:postcode":"4620",
    "sg:province":"Li\u00e8ge",
    "sg:tags":[
        "caf\u00e9s"
    ],
    "wof:name":"Caf\u00c9 De La Gare",
    "wof:placetype":"venue"
},
  "geometry": {"coordinates":[5.6832108498,50.6148414612],"type":"Point"}
}