{
  "type": "Feature",
  "properties": {
    "iso:country":"BE",
    "sg:address":"Keiemdorpstraat 19",
    "sg:city":"Diksmuide (keiem)",
    "sg:classifiers":[
        {
            "category":"Building & Trades",
            "subcategory":"Construction",
            "type":"Services"
        }
    ],
    "sg:phone":"+32 51 50 25 87",
    "sg:postcode":"8600",
    "sg:province":"West-Vlaanderen",
    "sg:tags":[
        "carpenter"
    ],
    "wof:name":"Marreel",
    "wof:placetype":"venue"
},
  "geometry": {"coordinates":[2.8781850338,51.075340271],"type":"Point"}
}