{
  "type": "Feature",
  "properties": {
    "addr:full":"Paviljoenweg 54 Essen Antwerpen 2910",
    "addr:housenumber":"54",
    "addr:postcode":"2910",
    "addr:street":"Paviljoenweg",
    "iso:country":"BE",
    "sg:address":"Paviljoenweg 54",
    "sg:city":"Essen",
    "sg:orig_category":"Installatie van houten of kunststof schrijnwerk",
    "sg:phone":"+32 3 677 30 16",
    "sg:postcode":"2910",
    "sg:province":"Antwerpen",
    "wof:name":"Deco",
    "wof:placetype":"venue"
},
  "geometry": {"coordinates":[4.4490318298,51.4508132935],"type":"Point"}
}