{
  "type": "Feature",
  "properties": {
    "addr:full":"Rue Du Vivat 2 Arlon (heinsch) Luxembourg 6700",
    "addr:housenumber":"2",
    "addr:postcode":"6700",
    "addr:street":"Rue Du Vivat",
    "iso:country":"BE",
    "sg:address":"Rue Du Vivat 2",
    "sg:city":"Arlon (heinsch)",
    "sg:classifiers":[
        {
            "category":"Personal",
            "subcategory":"Beauty Salon",
            "type":"Services"
        }
    ],
    "sg:phone":"+32 63 23 27 57",
    "sg:postcode":"6700",
    "sg:province":"Luxembourg",
    "sg:tags":[
        "lady",
        "-",
        "hairdressing"
    ],
    "wof:name":"Murielle Coiffure",
    "wof:placetype":"venue"
},
  "geometry": {"coordinates":[5.8126749992,49.6823234558],"type":"Point"}
}