{
  "type": "Feature",
  "properties": {
    "iso:country":"BE",
    "sg:address":"Hoornzeelstraat 4",
    "sg:city":"Tervuren",
    "sg:orig_category":"R\u00e9parations de chaussures and articles en cuir",
    "sg:phone":"+32 2 767 28 60",
    "sg:postcode":"3080",
    "sg:province":"Vlaams-Brabant",
    "wof:name":"Shoe Service",
    "wof:placetype":"venue"
},
  "geometry": {"coordinates":[4.5135412216,50.8226013184],"type":"Point"}
}