{
  "type": "Feature",
  "properties": {
    "iso:country":"BE",
    "sg:address":"Holstraat 16",
    "sg:city":"Heusden-zolder",
    "sg:orig_category":"Kapsalons",
    "sg:phone":"+32 11 53 84 25",
    "sg:postcode":"3550",
    "sg:province":"Limburg",
    "wof:name":"Gerard Houben",
    "wof:placetype":"venue"
},
  "geometry": {"coordinates":[5.3159761429,51.0223121643],"type":"Point"}
}