{
  "type": "Feature",
  "properties": {
    "iso:country":"BE",
    "sg:address":"Rue Du Charme 74",
    "sg:city":"Vresse-sur-semois (nafraiture)",
    "sg:classifiers":[
        {
            "category":"Mining & Drilling",
            "type":"Manufacturing & Wholesale Goods"
        }
    ],
    "sg:phone":"+32 61 50 07 29",
    "sg:postcode":"5550",
    "sg:province":"Namur",
    "sg:tags":[
        "quarry"
    ],
    "wof:name":"Carriere Chateau Du Loup",
    "wof:placetype":"venue"
},
  "geometry": {"coordinates":[4.9336900711,49.8729820251],"type":"Point"}
}