{
  "type": "Feature",
  "properties": {
    "addr:full":"Diesterstraat 44b4 Sint-truiden Limburg 3800",
    "addr:housenumber":"44b4",
    "addr:postcode":"3800",
    "addr:street":"Diesterstraat",
    "iso:country":"BE",
    "sg:address":"Diesterstraat 44b4",
    "sg:city":"Sint-truiden",
    "sg:orig_category":"Alternatieve geneeskunde Fitnesscentra",
    "sg:phone":"+32 11 69 63 18",
    "sg:postcode":"3800",
    "sg:province":"Limburg",
    "wof:name":"Body Styling Sint-truiden",
    "wof:placetype":"venue"
},
  "geometry": {"coordinates":[5.1846189499,50.8175849915],"type":"Point"}
}