{
  "type": "Feature",
  "properties": {
    "iso:country":"BE",
    "sg:address":"Jozef Pierrestraat 62",
    "sg:city":"Leuven",
    "sg:orig_category":"Enseignement secondaire technique and professionnel. Enseignement secondaire g\u00e9n\u00e9ral",
    "sg:phone":"+32 16 25 22 51",
    "sg:postcode":"3010",
    "sg:province":"Vlaams-Brabant",
    "wof:name":"Leerg. Soc. & Pedag. Werk",
    "wof:placetype":"venue"
},
  "geometry": {"coordinates":[4.7223320007,50.8848381042],"type":"Point"}
}