{
  "type": "Feature",
  "properties": {
    "iso:country":"BE",
    "sg:address":"Gasthuisstraat 32",
    "sg:city":"Dendermonde",
    "sg:orig_category":"Landmeters and schatters",
    "sg:phone":"+32 52 22 48 64",
    "sg:postcode":"9200",
    "sg:province":"Oost-Vlaanderen",
    "wof:name":"Akoest.adviesbur. Verhas",
    "wof:placetype":"venue"
},
  "geometry": {"coordinates":[4.0913128853,51.022480011],"type":"Point"}
}