{
  "type": "Feature",
  "properties": {
    "addr:full":"Rue Lamaye 14b Gr\u00e2ce-hollogne (horion-hoz\u00e9mont) Li\u00e8ge 4460",
    "addr:housenumber":"14b",
    "addr:postcode":"4460",
    "addr:street":"Rue Lamaye;Horion-Hoze\u0301Mont",
    "iso:country":"BE",
    "sg:address":"Rue Lamaye 14b",
    "sg:city":"Gr\u00e2ce-hollogne (horion-hoz\u00e9mont)",
    "sg:classifiers":[
        {
            "category":"Professional",
            "subcategory":"Engineering",
            "type":"Services"
        }
    ],
    "sg:phone":"+32 4 250 54 26",
    "sg:postcode":"4460",
    "sg:province":"Li\u00e8ge",
    "sg:tags":[
        "-"
    ],
    "wof:name":"Felix Jordan",
    "wof:placetype":"venue"
},
  "geometry": {"coordinates":[5.3994250298,50.6222877502],"type":"Point"}
}