{
  "type": "Feature",
  "properties": {
    "addr:full":"Place Des Wallons 47 Ottignies-louvain-la-neuve (louvain-la-neuve) Brabant Wallon 1348",
    "addr:housenumber":"47",
    "addr:postcode":"1348",
    "addr:street":"Place Des Wallons",
    "iso:country":"BE",
    "sg:address":"Place Des Wallons 47",
    "sg:city":"Ottignies-louvain-la-neuve (louvain-la-neuve)",
    "sg:classifiers":[
        {
            "category":"Utilities",
            "subcategory":"Mobile Phone",
            "type":"Services"
        }
    ],
    "sg:phone":"+32 10 45 94 60",
    "sg:postcode":"1348",
    "sg:province":"Brabant Wallon",
    "sg:tags":[
        "access",
        "gsm",
        "-",
        "apparatus"
    ],
    "wof:name":"Sit'com",
    "wof:placetype":"venue"
},
  "geometry": {"coordinates":[4.6171569824,50.6685676575],"type":"Point"}
}