{
  "type": "Feature",
  "properties": {
    "iso:country":"BE",
    "sg:address":"Royestraat 9",
    "sg:city":"Meeuwen-gruitrode",
    "sg:classifiers":[
        {
            "category":"Insurance",
            "subcategory":"Life Insurance",
            "type":"Services"
        }
    ],
    "sg:phone":"+32 89 85 30 51",
    "sg:postcode":"3670",
    "sg:province":"Limburg",
    "sg:tags":[
        "assurance"
    ],
    "wof:name":"Luc Jacobs",
    "wof:placetype":"venue"
},
  "geometry": {"coordinates":[5.6113409996,51.1043052673],"type":"Point"}
}