{
  "type": "Feature",
  "properties": {
    "addr:full":"Burg. Van Lindtstraat 65bb1 Overpelt Limburg 3900",
    "addr:postcode":"65bb1;3900",
    "addr:street":"Burg. Van Lindtstraat",
    "iso:country":"BE",
    "sg:address":"Burg. Van Lindtstraat 65bb1",
    "sg:city":"Overpelt",
    "sg:orig_category":"Woningbouw",
    "sg:phone":"+32 11 64 60 47",
    "sg:postcode":"3900",
    "sg:province":"Limburg",
    "wof:name":"Bouwwerken Claes",
    "wof:placetype":"venue"
},
  "geometry": {"coordinates":[5.4195737839,51.2122459412],"type":"Point"}
}