{
  "type": "Feature",
  "properties": {
    "iso:country":"BE",
    "sg:address":"Van Arteveldestraat 17",
    "sg:city":"Antwerpen",
    "sg:orig_category":"Hypotheken and hypotheekbanken Verbruikerskredietinstellingen",
    "sg:phone":"+32 3 220 68 95",
    "sg:postcode":"2060",
    "sg:province":"Antwerpen",
    "wof:name":"Opbouw",
    "wof:placetype":"venue"
},
  "geometry": {"coordinates":[4.4194397926,51.2198905945],"type":"Point"}
}