{
  "type": "Feature",
  "properties": {
    "addr:full":"Torrestraat 172 Wevelgem West-Vlaanderen 8560",
    "addr:housenumber":"172",
    "addr:postcode":"8560",
    "addr:street":"Torrestraat",
    "iso:country":"BE",
    "sg:address":"Torrestraat 172",
    "sg:city":"Wevelgem",
    "sg:orig_category":"R\u00e9paration and restauration de meubles. Rev\u00eatements de sols and murs. Chaises and si\u00e8ges Fab",
    "sg:phone":"+32 56 41 07 16",
    "sg:postcode":"8560",
    "sg:province":"West-Vlaanderen",
    "wof:name":"Daniek",
    "wof:placetype":"venue"
},
  "geometry": {"coordinates":[3.2117431164,50.8564796448],"type":"Point"}
}