{
  "type": "Feature",
  "properties": {
    "addr:full":"Chauss\u00e9e De Beaumont 453 Mons (harmignies) Hainaut 7022",
    "addr:housenumber":"453",
    "addr:postcode":"7022",
    "addr:street":"Chausse\u0301E De Beaumont",
    "iso:country":"BE",
    "sg:address":"Chauss\u00e9e De Beaumont 453",
    "sg:city":"Mons (harmignies)",
    "sg:classifiers":[
        {
            "category":"Health Services",
            "subcategory":"Health Practitioner",
            "type":"Services"
        }
    ],
    "sg:phone":"+32 65 58 61 09",
    "sg:postcode":"7022",
    "sg:province":"Hainaut",
    "sg:tags":[
        "physiotherapist"
    ],
    "wof:name":"Vanlathem J",
    "wof:placetype":"venue"
},
  "geometry": {"coordinates":[4.0181078911,50.4045410156],"type":"Point"}
}