{
  "type": "Feature",
  "properties": {
    "addr:full":"Eldersbroek 29 Tongeren Limburg 3700",
    "addr:housenumber":"29",
    "addr:postcode":"3700",
    "addr:street":"Eldersbroek",
    "iso:country":"BE",
    "sg:address":"Eldersbroek 29",
    "sg:city":"Tongeren",
    "sg:orig_category":"Artsen and specialisten",
    "sg:phone":"+32 12 23 49 52",
    "sg:postcode":"3700",
    "sg:province":"Limburg",
    "wof:name":"Pieter Posen",
    "wof:placetype":"venue"
},
  "geometry": {"coordinates":[5.4769620895,50.7848434448],"type":"Point"}
}