{
  "type": "Feature",
  "properties": {
    "addr:full":"Avenue Prince De Liege 117 Namen Namur 5100",
    "addr:housenumber":"117",
    "addr:postcode":"5100",
    "addr:street":"Avenue Prince De Liege",
    "iso:country":"BE",
    "sg:address":"Avenue Prince De Liege 117",
    "sg:city":"Namen",
    "sg:orig_category":"Schoenen",
    "sg:phone":"+32 81 31 01 62",
    "sg:postcode":"5100",
    "sg:province":"Namur",
    "wof:name":"Brantano",
    "wof:placetype":"venue"
},
  "geometry": {"coordinates":[4.8713750839,50.4566345215],"type":"Point"}
}