{
  "type": "Feature",
  "properties": {
    "addr:full":"Kloosterstraat 168 Antwerpen Antwerpen 2000",
    "addr:housenumber":"168",
    "addr:postcode":"2000",
    "addr:street":"Kloosterstraat",
    "iso:country":"BE",
    "sg:address":"Kloosterstraat 168",
    "sg:city":"Antwerpen",
    "sg:classifiers":[
        {
            "category":"Organizations",
            "subcategory":"Community Association",
            "type":"Services"
        }
    ],
    "sg:phone":"+32 3 248 97 24",
    "sg:postcode":"2000",
    "sg:province":"Antwerpen",
    "sg:tags":[
        "cultural"
    ],
    "wof:name":"Krijtkring (de)",
    "wof:placetype":"venue"
},
  "geometry": {"coordinates":[4.3937058449,51.2122535706],"type":"Point"}
}