{
  "type": "Feature",
  "properties": {
    "addr:full":"Kortrijksestraat 14 Oostkamp West-Vlaanderen 8020",
    "addr:housenumber":"14",
    "addr:postcode":"8020",
    "addr:street":"Kortrijksestraat",
    "iso:country":"BE",
    "sg:address":"Kortrijksestraat 14",
    "sg:city":"Oostkamp",
    "sg:classifiers":[
        {
            "category":"Shopping",
            "subcategory":"Clothing, Apparel, & Fashions",
            "type":"Retail Goods"
        }
    ],
    "sg:phone":"+32 50 82 23 11",
    "sg:postcode":"8020",
    "sg:province":"West-Vlaanderen",
    "sg:tags":[
        "boutique"
    ],
    "wof:name":"Sam & Sieber Bvba",
    "wof:placetype":"venue"
},
  "geometry": {"coordinates":[3.2350080013,51.1538925171],"type":"Point"}
}