{
  "type": "Feature",
  "properties": {
    "addr:full":"Rue De Lille 12 Estaimpuis (saint-l\u00e9ger) Hainaut 7730",
    "addr:housenumber":"12",
    "addr:postcode":"7730",
    "addr:street":"Rue De Lille;Saint-Le\u0301Ger Hainaut",
    "iso:country":"BE",
    "sg:address":"Rue De Lille 12",
    "sg:city":"Estaimpuis (saint-l\u00e9ger)",
    "sg:classifiers":[
        {
            "category":"Airport",
            "subcategory":"International",
            "type":"Transportation"
        }
    ],
    "sg:phone":"+32 56 48 87 59",
    "sg:postcode":"7730",
    "sg:province":"Hainaut",
    "sg:tags":[
        "-",
        "transport"
    ],
    "wof:name":"Lartelier",
    "wof:placetype":"venue"
},
  "geometry": {"coordinates":[3.3116459846,50.7040367126],"type":"Point"}
}