{
  "type": "Feature",
  "properties": {
    "addr:full":"Jonkersstraat 15 Brussel/bruxelles Bruxelles-Capitale 1000",
    "addr:housenumber":"15",
    "addr:postcode":"1000",
    "addr:street":"Jonkersstraat;/",
    "iso:country":"BE",
    "sg:address":"Jonkersstraat 15",
    "sg:city":"Brussel/bruxelles",
    "sg:classifiers":[
        {
            "category":"Restaurant",
            "type":"Food & Drink"
        }
    ],
    "sg:phone":"+32 2 513 25 16",
    "sg:postcode":"1000",
    "sg:province":"Bruxelles-Capitale",
    "sg:tags":[
        "caf\u00e9s"
    ],
    "wof:name":"Taverne Braces",
    "wof:placetype":"venue"
},
  "geometry": {"coordinates":[4.3617258072,50.8474655151],"type":"Point"}
}