{
  "type": "Feature",
  "properties": {
    "iso:country":"BE",
    "sg:address":"Stationsstraat 70",
    "sg:city":"Ichtegem",
    "sg:orig_category":"Sportclubs",
    "sg:phone":"+32 59 29 96 80",
    "sg:postcode":"8480",
    "sg:province":"West-Vlaanderen",
    "wof:name":"B.b.c. Bebita Eernegem",
    "wof:placetype":"venue"
},
  "geometry": {"coordinates":[3.0214378834,51.1298675537],"type":"Point"}
}