{
  "type": "Feature",
  "properties": {
    "addr:full":"Nieuwe Steenweg 229 Heers Limburg 3870",
    "addr:housenumber":"229",
    "addr:postcode":"3870",
    "addr:street":"Nieuwe Steenweg",
    "iso:country":"BE",
    "sg:address":"Nieuwe Steenweg 229",
    "sg:city":"Heers",
    "sg:orig_category":"Producteurs de fruits",
    "sg:phone":"+32 11 48 50 69",
    "sg:postcode":"3870",
    "sg:province":"Limburg",
    "wof:name":"Guillaume Missotten",
    "wof:placetype":"venue"
},
  "geometry": {"coordinates":[5.3047099113,50.7569999695],"type":"Point"}
}