{
  "type": "Feature",
  "properties": {
    "iso:country":"BE",
    "sg:address":"Leuvensesteenweg 286",
    "sg:city":"Brussel/bruxelles",
    "sg:classifiers":[
        {
            "category":"Bars & Pubs",
            "subcategory":"Nightclub",
            "type":"Food & Drink"
        }
    ],
    "sg:phone":"+32 2 733 41 72",
    "sg:postcode":"1000",
    "sg:province":"Bruxelles-Capitale",
    "sg:tags":[
        "nachtclubs",
        "dancing"
    ],
    "wof:name":"Sogedex",
    "wof:placetype":"venue"
},
  "geometry": {"coordinates":[4.3820090294,50.8507270813],"type":"Point"}
}