{
  "type": "Feature",
  "properties": {
    "addr:full":"Kleine Molenstraat 19 Zonnebeke West-Vlaanderen 8980",
    "addr:housenumber":"19",
    "addr:postcode":"8980",
    "addr:street":"Kleine Molenstraat",
    "iso:country":"BE",
    "sg:address":"Kleine Molenstraat 19",
    "sg:city":"Zonnebeke",
    "sg:orig_category":"Travaux d'isolation. Construction de maisons. Constructions r\u00e9sidentielles sp\u00e9cifiques",
    "sg:phone":"+32 51 78 08 85",
    "sg:postcode":"8980",
    "sg:province":"West-Vlaanderen",
    "wof:name":"Luc Vermeersch",
    "wof:placetype":"venue"
},
  "geometry": {"coordinates":[2.9817869663,50.8679504395],"type":"Point"}
}