{
  "type": "Feature",
  "properties": {
    "addr:full":"Langestraat 23 Zele Oost-Vlaanderen 9240",
    "addr:housenumber":"23",
    "addr:postcode":"9240",
    "addr:street":"Langestraat",
    "iso:country":"BE",
    "sg:address":"Langestraat 23",
    "sg:city":"Zele",
    "sg:classifiers":[
        {
            "category":"Health Services",
            "subcategory":"Doctor",
            "type":"Services"
        }
    ],
    "sg:phone":"+32 52 44 53 93",
    "sg:postcode":"9240",
    "sg:province":"Oost-Vlaanderen",
    "sg:tags":[
        "medicinephysicians",
        "surgeon"
    ],
    "wof:name":"De Waele L",
    "wof:placetype":"venue"
},
  "geometry": {"coordinates":[4.0354671478,51.0654220581],"type":"Point"}
}