{
  "type": "Feature",
  "properties": {
    "iso:country":"BE",
    "sg:address":"De Merodelei 39",
    "sg:city":"Turnhout",
    "sg:orig_category":"Antiek",
    "sg:phone":"+32 14 42 27 92",
    "sg:postcode":"2300",
    "sg:province":"Antwerpen",
    "wof:name":"The Antique Shop",
    "wof:placetype":"venue"
},
  "geometry": {"coordinates":[4.9413352013,51.3220214844],"type":"Point"}
}