{
  "type": "Feature",
  "properties": {
    "iso:country":"BE",
    "sg:address":"Rue Des Hamoises 2c",
    "sg:city":"Thuin (thuillies)",
    "sg:classifiers":[
        {
            "category":"Health Services",
            "subcategory":"Health Practitioner",
            "type":"Services"
        }
    ],
    "sg:phone":"+32 71 53 42 44",
    "sg:postcode":"6536",
    "sg:province":"Hainaut",
    "sg:tags":[
        "physiotherapist"
    ],
    "wof:name":"Sabeau J-p",
    "wof:placetype":"venue"
},
  "geometry": {"coordinates":[4.3344831467,50.2983703613],"type":"Point"}
}