{
  "type": "Feature",
  "properties": {
    "iso:country":"BE",
    "sg:address":"Jakob Smitslaan 26",
    "sg:city":"Mol",
    "sg:classifiers":[
        {
            "category":"Health Services",
            "subcategory":"Nursing And Care Facility",
            "type":"Services"
        }
    ],
    "sg:phone":"+32 14 33 00 93",
    "sg:postcode":"2400",
    "sg:province":"Antwerpen",
    "sg:tags":[
        "home",
        "rest"
    ],
    "wof:name":"Ocmw Mol",
    "wof:placetype":"venue"
},
  "geometry": {"coordinates":[5.1084961891,51.1848640442],"type":"Point"}
}