{
  "type": "Feature",
  "properties": {
    "addr:full":"Petit Vin\u00e2ve 15 Malmedy Li\u00e8ge 4960",
    "addr:housenumber":"15",
    "addr:postcode":"4960",
    "addr:street":"Petit Vina\u0302Ve",
    "iso:country":"BE",
    "sg:address":"Petit Vin\u00e2ve 15",
    "sg:city":"Malmedy",
    "sg:classifiers":[
        {
            "category":"Shopping",
            "subcategory":"Books",
            "type":"Retail Goods"
        }
    ],
    "sg:phone":"+32 80 33 81 72",
    "sg:postcode":"4960",
    "sg:province":"Li\u00e8ge",
    "sg:tags":[
        "bookseller"
    ],
    "wof:name":"Masson J.m.",
    "wof:placetype":"venue"
},
  "geometry": {"coordinates":[6.0301961899,50.4259338379],"type":"Point"}
}