{
  "type": "Feature",
  "properties": {
    "iso:country":"BE",
    "sg:address":"L. Herentalsstraat 62-70",
    "sg:city":"Antwerpen",
    "sg:orig_category":"Agences d'exp\u00e9dition",
    "sg:phone":"+32 3 226 55 33",
    "sg:postcode":"2018",
    "sg:province":"Antwerpen",
    "wof:name":"B.d.m. Commidities",
    "wof:placetype":"venue"
},
  "geometry": {"coordinates":[4.4174418449,51.2142486572],"type":"Point"}
}