{
  "type": "Feature",
  "properties": {
    "addr:full":"Lange Venstraat 31a Tremelo (baal) Vlaams-Brabant 3128",
    "addr:housenumber":"31a",
    "addr:postcode":"3128",
    "addr:street":"Lange Venstraat",
    "iso:country":"BE",
    "sg:address":"Lange Venstraat 31a",
    "sg:city":"Tremelo (baal)",
    "sg:classifiers":[
        {
            "category":"Building & Trades",
            "subcategory":"Electrical",
            "type":"Services"
        }
    ],
    "sg:phone":"+32 16 56 45 70",
    "sg:postcode":"3128",
    "sg:province":"Vlaams-Brabant",
    "sg:tags":[
        "electric",
        "-",
        "housewiring",
        "contractor"
    ],
    "wof:name":"Gh-technics",
    "wof:placetype":"venue"
},
  "geometry": {"coordinates":[4.7501330376,51.017036438],"type":"Point"}
}