{
  "type": "Feature",
  "properties": {
    "addr:full":"Rue Ferrer 48 Manage (la Hestre) Hainaut 7170",
    "addr:housenumber":"48",
    "addr:postcode":"7170",
    "addr:street":"Rue Ferrer;La;Hainaut",
    "iso:country":"BE",
    "sg:address":"Rue Ferrer 48",
    "sg:city":"Manage (la Hestre)",
    "sg:classifiers":[
        {
            "category":"Shopping",
            "subcategory":"Books",
            "type":"Retail Goods"
        }
    ],
    "sg:phone":"+32 64 26 27 90",
    "sg:postcode":"7170",
    "sg:province":"Hainaut",
    "sg:tags":[
        "bookseller"
    ],
    "wof:name":"Nouvelles (librairie)",
    "wof:placetype":"venue"
},
  "geometry": {"coordinates":[4.2387862206,50.4767112732],"type":"Point"}
}