{
  "type": "Feature",
  "properties": {
    "iso:country":"BE",
    "sg:address":"Arendstraat 9-11",
    "sg:city":"Antwerpen",
    "sg:classifiers":[
        {
            "category":"Professional",
            "subcategory":"Art Services",
            "type":"Services"
        }
    ],
    "sg:phone":"+32 3 281 31 65",
    "sg:postcode":"2018",
    "sg:province":"Antwerpen",
    "sg:tags":[
        "graphic",
        "designer"
    ],
    "wof:name":"Tulipa Grafische Communicatie Bvba",
    "wof:placetype":"venue"
},
  "geometry": {"coordinates":[4.4269990921,51.20652771],"type":"Point"}
}