{
  "type": "Feature",
  "properties": {
    "addr:full":"Place Saint Sevrin 3 Huy Li\u00e8ge 4500",
    "addr:housenumber":"3",
    "addr:postcode":"4500",
    "addr:street":"Place Saint Sevrin",
    "iso:country":"BE",
    "sg:address":"Place Saint Sevrin 3",
    "sg:city":"Huy",
    "sg:orig_category":"Huishoudapparaten, televisies and radio's",
    "sg:phone":"+32 85 24 02 87",
    "sg:postcode":"4500",
    "sg:province":"Li\u00e8ge",
    "wof:name":"Electro Centre Huy",
    "wof:placetype":"venue"
},
  "geometry": {"coordinates":[5.2400307655,50.5178337097],"type":"Point"}
}