{
  "type": "Feature",
  "properties": {
    "iso:country":"BE",
    "sg:address":"Industriepark 1",
    "sg:city":"Wijnegem",
    "sg:classifiers":[
        {
            "category":"Retail",
            "subcategory":"Auto Repair",
            "type":"Services"
        }
    ],
    "sg:phone":"+32 3 326 26 00",
    "sg:postcode":"2110",
    "sg:province":"Antwerpen",
    "sg:tags":[
        "recapping",
        "-",
        "retreading",
        "tyre"
    ],
    "wof:name":"Donckers-voorheen Luyten Autobanden Bvba",
    "wof:placetype":"venue"
},
  "geometry": {"coordinates":[4.5248470306,51.2279434204],"type":"Point"}
}