{
  "type": "Feature",
  "properties": {
    "addr:full":"Sint-willibrordusplein 19 Heusden-zolder Limburg 3550",
    "addr:housenumber":"19",
    "addr:postcode":"3550",
    "addr:street":"Sint-Willibrordusplein",
    "iso:country":"BE",
    "sg:address":"Sint-willibrordusplein 19",
    "sg:city":"Heusden-zolder",
    "sg:orig_category":"Banques and organismes de cr\u00e9dit",
    "sg:phone":"+32 11 43 55 38",
    "sg:postcode":"3550",
    "sg:province":"Limburg",
    "wof:name":"Groep Argenta",
    "wof:placetype":"venue"
},
  "geometry": {"coordinates":[5.2818341255,51.0332679749],"type":"Point"}
}