{
  "type": "Feature",
  "properties": {
    "addr:full":"Rue Du Parc 69b Li\u00e8ge 1 (li\u00e8ge 2) Li\u00e8ge 4020",
    "addr:housenumber":"69b;1;2",
    "addr:postcode":"4020",
    "addr:street":"Rue Du Parc",
    "iso:country":"BE",
    "sg:address":"Rue Du Parc 69b",
    "sg:city":"Li\u00e8ge 1 (li\u00e8ge 2)",
    "sg:orig_category":"Fiduciairies",
    "sg:phone":"+32 4 341 19 42",
    "sg:postcode":"4020",
    "sg:province":"Li\u00e8ge",
    "wof:name":"Fiduciaire S.o.c.a.f. Sprl",
    "wof:placetype":"venue"
},
  "geometry": {"coordinates":[5.5766811371,50.6302108765],"type":"Point"}
}