{
  "type": "Feature",
  "properties": {
    "iso:country":"BE",
    "sg:address":"Nieuwevaart 118",
    "sg:city":"Gent",
    "sg:orig_category":"Diverse grafische activiteiten Reclamebureaus",
    "sg:phone":"+32 9 234 03 22",
    "sg:postcode":"9000",
    "sg:province":"Oost-Vlaanderen",
    "wof:name":"Lettering",
    "wof:placetype":"venue"
},
  "geometry": {"coordinates":[3.7185819149,51.0674095154],"type":"Point"}
}