{
  "type": "Feature",
  "properties": {
    "iso:country":"BE",
    "sg:address":"Rue Du Petit Fonteny 35",
    "sg:city":"Ch\u00c2telet",
    "sg:orig_category":"Boekhouders",
    "sg:phone":"+32 71 39 14 06",
    "sg:postcode":"6200",
    "sg:province":"Hainaut",
    "wof:name":"A. Collin",
    "wof:placetype":"venue"
},
  "geometry": {"coordinates":[4.5288529396,50.4034957886],"type":"Point"}
}