{
  "type": "Feature",
  "properties": {
    "iso:country":"BE",
    "sg:address":"Van Souststraat 224",
    "sg:city":"Anderlecht/anderlecht",
    "sg:orig_category":"Loodgieterij, verwarming and sanitaire installaties",
    "sg:phone":"+32 2 521 96 23",
    "sg:postcode":"1070",
    "sg:province":"Bruxelles-Capitale",
    "wof:name":"Sanilogi",
    "wof:placetype":"venue"
},
  "geometry": {"coordinates":[4.3023190498,50.8464698792],"type":"Point"}
}