{
  "type": "Feature",
  "properties": {
    "iso:country":"BE",
    "sg:address":"Ambroossteenweg 102",
    "sg:city":"Zemst",
    "sg:orig_category":"Groententeelt",
    "sg:phone":"+32 15 61 12 97",
    "sg:postcode":"1981",
    "sg:province":"Vlaams-Brabant",
    "wof:name":"Robert Demesmaeker",
    "wof:placetype":"venue"
},
  "geometry": {"coordinates":[4.4980020523,50.9947662354],"type":"Point"}
}