{
  "type": "Feature",
  "properties": {
    "iso:country":"BE",
    "sg:address":"Rue Fritz Toussaint 3",
    "sg:city":"Elsene/ixelles",
    "sg:orig_category":"Peinture. Rev\u00eatements pour sols and murs",
    "sg:phone":"+32 2 649 12 77",
    "sg:postcode":"1050",
    "sg:province":"Bruxelles-Capitale",
    "wof:name":"Fouarge Fr\u00c8res",
    "wof:placetype":"venue"
},
  "geometry": {"coordinates":[4.3856949806,50.8238296509],"type":"Point"}
}