{
  "type": "Feature",
  "properties": {
    "iso:country":"BE",
    "sg:address":"Maastrichterstraat 196",
    "sg:city":"Bilzen",
    "sg:orig_category":"Travaux d\u00b4installation divers. Lampes and appareils \u00e9lectriques Fab",
    "sg:phone":"+32 89 41 15 42",
    "sg:postcode":"3740",
    "sg:province":"Limburg",
    "wof:name":"Neoram",
    "wof:placetype":"venue"
},
  "geometry": {"coordinates":[5.5331001282,50.8638000488],"type":"Point"}
}