{
  "type": "Feature",
  "properties": {
    "iso:country":"BE",
    "sg:address":"Rue Du Patch 1a",
    "sg:city":"Rixensart",
    "sg:classifiers":[
        {
            "category":"Arena",
            "subcategory":"Sports Club",
            "type":"Entertainment"
        }
    ],
    "sg:phone":"+32 2 653 14 26",
    "sg:postcode":"1330",
    "sg:province":"Brabant Wallon",
    "sg:tags":[
        "de"
    ],
    "wof:name":"Macareux",
    "wof:placetype":"venue"
},
  "geometry": {"coordinates":[4.5303878784,50.716293335],"type":"Point"}
}