{
  "type": "Feature",
  "properties": {
    "iso:country":"BE",
    "sg:address":"Route De Saint-g\u00c9rard 18",
    "sg:city":"Fosses-la-ville",
    "sg:orig_category":"Paramedische behandelingen",
    "sg:phone":"+32 71 71 22 95",
    "sg:postcode":"5070",
    "sg:province":"Namur",
    "wof:name":"G. Piraux",
    "wof:placetype":"venue"
},
  "geometry": {"coordinates":[4.6999030113,50.3785972595],"type":"Point"}
}