{
  "type": "Feature",
  "properties": {
    "iso:country":"BE",
    "sg:address":"Avenue Auguste Mattagne 49 Box 1",
    "sg:city":"Wavre",
    "sg:classifiers":[
        {
            "category":"Education",
            "subcategory":"School",
            "type":"Public Place"
        }
    ],
    "sg:phone":"+32 10 22 34 30",
    "sg:postcode":"1300",
    "sg:province":"Brabant Wallon",
    "sg:tags":[
        "-",
        "private"
    ],
    "wof:name":"Charlier E",
    "wof:placetype":"venue"
},
  "geometry": {"coordinates":[4.6148872375,50.7176933289],"type":"Point"}
}