{
  "type": "Feature",
  "properties": {
    "addr:full":"Rue Maurice Li\u00c9tart 30 Sint-pieters-woluwe/woluwe-sai Bruxelles-Capitale 1200",
    "addr:housenumber":"30",
    "addr:postcode":"1200",
    "addr:street":"Rue Maurice Lie\u0301Tart",
    "iso:country":"BE",
    "sg:address":"Rue Maurice Li\u00c9tart 30",
    "sg:city":"Sint-pieters-woluwe/woluwe-sai",
    "sg:classifiers":[
        {
            "category":"Restaurant",
            "type":"Food & Drink"
        }
    ],
    "sg:phone":"+32 2 772 36 58",
    "sg:postcode":"1200",
    "sg:province":"Bruxelles-Capitale",
    "wof:name":"Le Fair-play",
    "wof:placetype":"venue"
},
  "geometry": {"coordinates":[4.4311299324,50.8484992981],"type":"Point"}
}