{
  "type": "Feature",
  "properties": {
    "addr:full":"Wingenestraat 19 Aalter Oost-Vlaanderen 9880",
    "addr:housenumber":"19",
    "addr:postcode":"9880",
    "addr:street":"Wingenestraat",
    "iso:country":"BE",
    "sg:address":"Wingenestraat 19",
    "sg:city":"Aalter",
    "sg:orig_category":"Kapsalons",
    "sg:phone":"+32 9 375 15 81",
    "sg:postcode":"9880",
    "sg:province":"Oost-Vlaanderen",
    "wof:name":"Coiffure Karen",
    "wof:placetype":"venue"
},
  "geometry": {"coordinates":[3.3608300686,51.0883102417],"type":"Point"}
}