{
  "type": "Feature",
  "properties": {
    "addr:full":"Quellinstraat 30 Antwerpen Antwerpen 2018",
    "addr:housenumber":"30",
    "addr:postcode":"2018",
    "addr:street":"Quellinstraat",
    "iso:country":"BE",
    "sg:address":"Quellinstraat 30",
    "sg:city":"Antwerpen",
    "sg:classifiers":[
        {
            "category":"Restaurant",
            "type":"Food & Drink"
        }
    ],
    "sg:phone":"+32 3 232 64 67",
    "sg:postcode":"2018",
    "sg:province":"Antwerpen",
    "wof:name":"Faites Simple",
    "wof:placetype":"venue"
},
  "geometry": {"coordinates":[4.4159808159,51.2163314819],"type":"Point"}
}