{
  "type": "Feature",
  "properties": {
    "iso:country":"BE",
    "sg:address":"Rue De L'yser 96",
    "sg:city":"Marche-en-famenne",
    "sg:orig_category":"M\u00e9decins and sp\u00e9cialistes",
    "sg:phone":"+32 84 22 23 00",
    "sg:postcode":"6900",
    "sg:province":"Luxembourg",
    "wof:name":"Brigitte Peret",
    "wof:placetype":"venue"
},
  "geometry": {"coordinates":[5.2751550674,50.1651573181],"type":"Point"}
}