{
  "type": "Feature",
  "properties": {
    "addr:full":"Chauss\u00e9e Romaine 180 Waremme Li\u00e8ge 4300",
    "addr:housenumber":"180",
    "addr:postcode":"4300",
    "addr:street":"Chausse\u0301E Romaine",
    "iso:country":"BE",
    "sg:address":"Chauss\u00e9e Romaine 180",
    "sg:city":"Waremme",
    "sg:classifiers":[
        {
            "category":"Utilities",
            "subcategory":"Electric",
            "type":"Services"
        }
    ],
    "sg:phone":"+32 19 33 92 92",
    "sg:postcode":"4300",
    "sg:province":"Li\u00e8ge",
    "sg:tags":[
        "generator"
    ],
    "wof:name":"Moes Diesel Sa",
    "wof:placetype":"venue"
},
  "geometry": {"coordinates":[5.2709522247,50.6941184998],"type":"Point"}
}