{
  "type": "Feature",
  "properties": {
    "iso:country":"BE",
    "sg:address":"Logen 9",
    "sg:city":"Geel",
    "sg:orig_category":"Fotografen and fotostudio's",
    "sg:phone":"+32 14 58 33 15",
    "sg:postcode":"2440",
    "sg:province":"Antwerpen",
    "wof:name":"Iv-fotoprodukties",
    "wof:placetype":"venue"
},
  "geometry": {"coordinates":[5.0019979477,51.1633262634],"type":"Point"}
}