{
  "type": "Feature",
  "properties": {
    "iso:country":"BE",
    "sg:address":"Rue Des Ecoles 22",
    "sg:city":"Limbourg",
    "sg:orig_category":"Pain, p\u00e2tisseries and confiseries",
    "sg:phone":"+32 87 76 64 19",
    "sg:postcode":"4830",
    "sg:province":"Li\u00e8ge",
    "wof:name":"Boulangerie Rommes",
    "wof:placetype":"venue"
},
  "geometry": {"coordinates":[5.9407401085,50.6112518311],"type":"Point"}
}