{
  "type": "Feature",
  "properties": {
    "addr:full":"Route De Mons 240ba Erquelinnes Hainaut 6560",
    "addr:postcode":"6560",
    "addr:street":"Route De Mons 240Ba;Hainaut",
    "iso:country":"BE",
    "sg:address":"Route De Mons 240ba",
    "sg:city":"Erquelinnes",
    "sg:orig_category":"Benzinestations and brandstoffen",
    "sg:phone":"+32 71 55 65 08",
    "sg:postcode":"6560",
    "sg:province":"Hainaut",
    "wof:name":"Texaco",
    "wof:placetype":"venue"
},
  "geometry": {"coordinates":[4.1405901909,50.3092308044],"type":"Point"}
}