{
  "type": "Feature",
  "properties": {
    "addr:full":"De Knok 1 Lendelede West-Vlaanderen 8860",
    "addr:housenumber":"1",
    "addr:postcode":"8860",
    "addr:street":"De Knok",
    "iso:country":"BE",
    "sg:address":"De Knok 1",
    "sg:city":"Lendelede",
    "sg:classifiers":[
        {
            "category":"Personal",
            "subcategory":"Beauty Salon",
            "type":"Services"
        }
    ],
    "sg:phone":"+32 51 30 97 62",
    "sg:postcode":"8860",
    "sg:province":"West-Vlaanderen",
    "sg:tags":[
        "lady",
        "-",
        "hairdressing"
    ],
    "wof:name":"Divine",
    "wof:placetype":"venue"
},
  "geometry": {"coordinates":[3.2346899509,50.8821716309],"type":"Point"}
}