{
  "type": "Feature",
  "properties": {
    "iso:country":"BE",
    "sg:address":"Chauss\u00c9e D'alsemberg 53",
    "sg:city":"Sint-gillis/saint-gilles",
    "sg:orig_category":"Blanchisseries and teintureries",
    "sg:phone":"+32 2 537 08 74",
    "sg:postcode":"1060",
    "sg:province":"Bruxelles-Capitale",
    "wof:name":"Dirk Van Imschoot",
    "wof:placetype":"venue"
},
  "geometry": {"coordinates":[4.3434510231,50.8251953125],"type":"Point"}
}