{
  "type": "Feature",
  "properties": {
    "addr:full":"Rue Longue 59 Viroinval (nismes) Namur 5670",
    "addr:housenumber":"59",
    "addr:postcode":"5670",
    "addr:street":"Rue Longue",
    "iso:country":"BE",
    "sg:address":"Rue Longue 59",
    "sg:city":"Viroinval (nismes)",
    "sg:classifiers":[
        {
            "category":"Food & Beverages",
            "subcategory":"Candy",
            "type":"Retail Goods"
        }
    ],
    "sg:phone":"+32 60 37 88 38",
    "sg:postcode":"5670",
    "sg:province":"Namur",
    "wof:name":"Espace Fleurs",
    "wof:placetype":"venue"
},
  "geometry": {"coordinates":[4.5484552383,50.0707511902],"type":"Point"}
}