{
  "type": "Feature",
  "properties": {
    "addr:full":"Sint-pauluslaan 63 Tervuren (vossem) Vlaams-Brabant 3080",
    "addr:housenumber":"63",
    "addr:postcode":"3080",
    "addr:street":"Sint-Pauluslaan",
    "iso:country":"BE",
    "sg:address":"Sint-pauluslaan 63",
    "sg:city":"Tervuren (vossem)",
    "sg:classifiers":[
        {
            "category":"Building & Trades",
            "subcategory":"Electrical",
            "type":"Services"
        }
    ],
    "sg:phone":"+32 2 768 04 08",
    "sg:postcode":"3080",
    "sg:province":"Vlaams-Brabant",
    "sg:tags":[
        "-",
        "electric",
        "contractor"
    ],
    "wof:name":"R.e.d. Electric's",
    "wof:placetype":"venue"
},
  "geometry": {"coordinates":[4.5132598877,50.8243637085],"type":"Point"}
}