{
  "type": "Feature",
  "properties": {
    "iso:country":"BE",
    "sg:address":"Kasteelstraat 2",
    "sg:city":"Merelbeke (melsen)",
    "sg:classifiers":[
        {
            "category":"Professional",
            "subcategory":"Accounting & Tax Preparation",
            "type":"Services"
        }
    ],
    "sg:phone":"+32 9 259 13 10",
    "sg:postcode":"9820",
    "sg:province":"Oost-Vlaanderen",
    "sg:tags":[
        "bookkeeper"
    ],
    "wof:name":"Reynaert C",
    "wof:placetype":"venue"
},
  "geometry": {"coordinates":[3.6935501099,50.9552497864],"type":"Point"}
}