{
  "type": "Feature",
  "properties": {
    "iso:country":"BE",
    "sg:address":"Prinsenlaan 28",
    "sg:city":"Ravels",
    "sg:orig_category":"Fleurs and plantes",
    "sg:phone":"+32 14 65 88 95",
    "sg:postcode":"2381",
    "sg:province":"Antwerpen",
    "wof:name":"De Kruijf A",
    "wof:placetype":"venue"
},
  "geometry": {"coordinates":[5.006374836,51.4099845886],"type":"Point"}
}