{
  "type": "Feature",
  "properties": {
    "addr:full":"Hollekenstraat 24 Assenede Oost-Vlaanderen 9960",
    "addr:housenumber":"24",
    "addr:postcode":"9960",
    "addr:street":"Hollekenstraat",
    "iso:country":"BE",
    "sg:address":"Hollekenstraat 24",
    "sg:city":"Assenede",
    "sg:classifiers":[
        {
            "category":"Building & Trades",
            "subcategory":"Cleaning & Sanitation",
            "type":"Services"
        }
    ],
    "sg:phone":"+32 9 345 98 03",
    "sg:postcode":"9960",
    "sg:province":"Oost-Vlaanderen",
    "sg:tags":[
        "janitor"
    ],
    "wof:name":"Sonneville Nv",
    "wof:placetype":"venue"
},
  "geometry": {"coordinates":[3.7572820187,51.2504501343],"type":"Point"}
}