{
  "type": "Feature",
  "properties": {
    "addr:full":"Ginstdreef 78 Merelbeke Oost-Vlaanderen 9820",
    "addr:housenumber":"78",
    "addr:postcode":"9820",
    "addr:street":"Ginstdreef",
    "iso:country":"BE",
    "sg:address":"Ginstdreef 78",
    "sg:city":"Merelbeke",
    "sg:classifiers":[
        {
            "category":"Professional",
            "subcategory":"Accounting & Tax Preparation",
            "type":"Services"
        }
    ],
    "sg:phone":"+32 9 231 65 21",
    "sg:postcode":"9820",
    "sg:province":"Oost-Vlaanderen",
    "sg:tags":[
        "bookkeeper"
    ],
    "wof:name":"Bettens E",
    "wof:placetype":"venue"
},
  "geometry": {"coordinates":[3.7665200233,51.0084075928],"type":"Point"}
}