{
  "type": "Feature",
  "properties": {
    "iso:country":"BE",
    "sg:address":"Grote Amer 3b4",
    "sg:city":"Puurs",
    "sg:orig_category":"Quincailleries. Bois Gr. Travail and traitement du bois",
    "sg:phone":"+32 3 889 00 99",
    "sg:postcode":"2870",
    "sg:province":"Antwerpen",
    "wof:name":"Houtzagerij Peleman",
    "wof:placetype":"venue"
},
  "geometry": {"coordinates":[4.2900910378,51.0829620361],"type":"Point"}
}