{
  "type": "Feature",
  "properties": {
    "addr:full":"Rue De La Marli\u00c8re 50 Ecaussinnes Hainaut 7190",
    "addr:housenumber":"50",
    "addr:postcode":"7190",
    "addr:street":"Rue De La Marlie\u0300Re;Hainaut",
    "iso:country":"BE",
    "sg:address":"Rue De La Marli\u00c8re 50",
    "sg:city":"Ecaussinnes",
    "sg:orig_category":"Pain, p\u00e2tisseries and confiseries",
    "sg:phone":"+32 67 44 32 17",
    "sg:postcode":"7190",
    "sg:province":"Hainaut",
    "wof:name":"Boulangerie R Colinet",
    "wof:placetype":"venue"
},
  "geometry": {"coordinates":[4.1697831154,50.568359375],"type":"Point"}
}