{
  "type": "Feature",
  "properties": {
    "addr:full":"Statiestraat 4 Beerse Antwerpen 2340",
    "addr:housenumber":"4",
    "addr:postcode":"2340",
    "addr:street":"Statiestraat",
    "iso:country":"BE",
    "sg:address":"Statiestraat 4",
    "sg:city":"Beerse",
    "sg:orig_category":"Travaux de pl\u00e2trage",
    "sg:phone":"+32 3 312 56 74",
    "sg:postcode":"2340",
    "sg:province":"Antwerpen",
    "wof:name":"Stefan Jansens",
    "wof:placetype":"venue"
},
  "geometry": {"coordinates":[4.781370163,51.2981185913],"type":"Point"}
}