{
  "type": "Feature",
  "properties": {
    "iso:country":"BE",
    "sg:address":"Haagstraat 37",
    "sg:city":"Gavere",
    "sg:orig_category":"Installation de menuiserie en bois and plastique",
    "sg:phone":"+32 9 384 55 35",
    "sg:postcode":"9890",
    "sg:province":"Oost-Vlaanderen",
    "wof:name":"Willy Beyaert",
    "wof:placetype":"venue"
},
  "geometry": {"coordinates":[3.6587440968,50.9109382629],"type":"Point"}
}