{
  "type": "Feature",
  "properties": {
    "iso:country":"BE",
    "sg:address":"Luxemburger-strasse 68",
    "sg:city":"Sankt Vith/saint-vith",
    "sg:orig_category":"Meubles D\u00e9taillants, Am\u00e9nagement de B\u00e2timents et de Cuisines",
    "sg:phone":"+32 80 22 96 18",
    "sg:postcode":"4780",
    "sg:province":"Li\u00e8ge",
    "wof:name":"M\u00d6bel Remata",
    "wof:placetype":"venue"
},
  "geometry": {"coordinates":[6.0429549217,50.3349761963],"type":"Point"}
}