{
  "type": "Feature",
  "properties": {
    "iso:country":"BE",
    "sg:address":"Darwinstraat 18",
    "sg:city":"Vorst/forest",
    "sg:orig_category":"Werk and personeelsselectie",
    "sg:phone":"+32 2 343 19 54",
    "sg:postcode":"1190",
    "sg:province":"Bruxelles-Capitale",
    "wof:name":"C.p.m.g.",
    "wof:placetype":"venue"
},
  "geometry": {"coordinates":[4.3518080711,50.8183708191],"type":"Point"}
}