{
  "type": "Feature",
  "properties": {
    "iso:country":"BE",
    "sg:address":"Cartuyvelsstraat 6",
    "sg:city":"Linter",
    "sg:orig_category":"Kapsalons",
    "sg:phone":"+32 11 78 09 80",
    "sg:postcode":"3350",
    "sg:province":"Vlaams-Brabant",
    "wof:name":"Yvette Beelen",
    "wof:placetype":"venue"
},
  "geometry": {"coordinates":[5.0404877663,50.841545105],"type":"Point"}
}