{
  "type": "Feature",
  "properties": {
    "addr:full":"Van Eycklaan 0 Arendonk Antwerpen 2370",
    "addr:housenumber":"0",
    "addr:postcode":"2370",
    "addr:street":"Van Eycklaan",
    "iso:country":"BE",
    "sg:address":"Van Eycklaan 0",
    "sg:city":"Arendonk",
    "sg:orig_category":"Kunstonderwijs",
    "sg:phone":"+32 14 67 12 22",
    "sg:postcode":"2370",
    "sg:province":"Antwerpen",
    "wof:name":"Academie Schone Kunsten",
    "wof:placetype":"venue"
},
  "geometry": {"coordinates":[5.0832982063,51.3236732483],"type":"Point"}
}