{
  "type": "Feature",
  "properties": {
    "addr:full":"Heidebloemstraat 7 Sint-niklaas Oost-Vlaanderen 9100",
    "addr:housenumber":"7",
    "addr:postcode":"9100",
    "addr:street":"Heidebloemstraat",
    "iso:country":"BE",
    "sg:address":"Heidebloemstraat 7",
    "sg:city":"Sint-niklaas",
    "sg:classifiers":[
        {
            "category":"Building & Trades",
            "subcategory":"Pest Control",
            "type":"Services"
        }
    ],
    "sg:phone":"+32 3 776 14 10",
    "sg:postcode":"9100",
    "sg:province":"Oost-Vlaanderen",
    "sg:tags":[
        "painting",
        "contractor"
    ],
    "wof:name":"De Witte M",
    "wof:placetype":"venue"
},
  "geometry": {"coordinates":[4.1379871368,51.1749000549],"type":"Point"}
}