{
  "type": "Feature",
  "properties": {
    "iso:country":"BE",
    "sg:address":"Tongerenstraat 20",
    "sg:city":"Etterbeek",
    "sg:orig_category":"Tijdelijke werkgelegenheid and uitzendkantoren",
    "sg:phone":"+32 2 738 04 90",
    "sg:postcode":"1040",
    "sg:province":"Bruxelles-Capitale",
    "wof:name":"Adecco",
    "wof:placetype":"venue"
},
  "geometry": {"coordinates":[4.3995490074,50.8398170471],"type":"Point"}
}