{
  "type": "Feature",
  "properties": {
    "iso:country":"BE",
    "sg:address":"H\u00c9bronval 95",
    "sg:city":"Vielsalm",
    "sg:orig_category":"Rundveehouders",
    "sg:phone":"+32 80 41 87 69",
    "sg:postcode":"6690",
    "sg:province":"Luxembourg",
    "wof:name":"Julien Remy",
    "wof:placetype":"venue"
},
  "geometry": {"coordinates":[5.8170051575,50.2566299438],"type":"Point"}
}