{
  "type": "Feature",
  "properties": {
    "addr:full":"Eeuwfeestlaan 145 Lier Antwerpen 2500",
    "addr:housenumber":"145",
    "addr:postcode":"2500",
    "addr:street":"Eeuwfeestlaan",
    "iso:country":"BE",
    "sg:address":"Eeuwfeestlaan 145",
    "sg:city":"Lier",
    "sg:classifiers":[
        {
            "category":"Professional",
            "subcategory":"Lawyer & Legal Services",
            "type":"Services"
        }
    ],
    "sg:phone":"+32 3 480 64 93",
    "sg:postcode":"2500",
    "sg:province":"Antwerpen",
    "wof:name":"Cools Maria",
    "wof:placetype":"venue"
},
  "geometry": {"coordinates":[4.5646147728,51.13829422],"type":"Point"}
}