{
  "type": "Feature",
  "properties": {
    "iso:country":"BE",
    "sg:address":"Rue Des Aulnes 34",
    "sg:city":"Estaimpuis",
    "sg:orig_category":"Rundveehouders",
    "sg:phone":"+32 69 55 67 18",
    "sg:postcode":"7730",
    "sg:province":"Hainaut",
    "wof:name":"Marcel Timmerman",
    "wof:placetype":"venue"
},
  "geometry": {"coordinates":[3.3024671078,50.6877098083],"type":"Point"}
}