{
  "type": "Feature",
  "properties": {
    "iso:country":"BE",
    "sg:address":"Troka 475ba",
    "sg:city":"Andenne",
    "sg:orig_category":"Electrom\u00e9nager, t\u00e9l\u00e9visions and radios",
    "sg:phone":"+32 4 233 89 85",
    "sg:postcode":"5300",
    "sg:province":"Namur",
    "wof:name":"Alain Fraiture",
    "wof:placetype":"venue"
},
  "geometry": {"coordinates":[5.0982642174,50.4863739014],"type":"Point"}
}