{
  "type": "Feature",
  "properties": {
    "addr:full":"Rue De P\u00e2turages 55 Quaregnon Hainaut 7390",
    "addr:housenumber":"55",
    "addr:postcode":"7390",
    "addr:street":"Rue De Pa\u0302Turages",
    "iso:country":"BE",
    "sg:address":"Rue De P\u00e2turages 55",
    "sg:city":"Quaregnon",
    "sg:classifiers":[
        {
            "category":"Professional",
            "subcategory":"Engineering",
            "type":"Services"
        }
    ],
    "sg:phone":"+32 65 67 15 75",
    "sg:postcode":"7390",
    "sg:province":"Hainaut",
    "sg:tags":[
        "workshop"
    ],
    "wof:name":"Ets Gerard Urbain Maton Sprl",
    "wof:placetype":"venue"
},
  "geometry": {"coordinates":[3.8656330109,50.4244499207],"type":"Point"}
}