{
  "type": "Feature",
  "properties": {
    "iso:country":"BE",
    "sg:address":"118",
    "sg:city":"Rue Du Korenbeek 1080 Bruxelles",
    "sg:classifiers":[
        {
            "category":"Manufacturing",
            "subcategory":"Chemicals & Compounds",
            "type":"Manufacturing & Wholesale Goods"
        }
    ],
    "sg:phone":"+32 2 469 09 90",
    "sg:postcode":"118",
    "sg:tags":[
        "pharmaceutical",
        "chemistry",
        "-",
        "by-product"
    ],
    "wof:name":"Societe Industrielle De Diffusion Benelux Sa",
    "wof:placetype":"venue"
},
  "geometry": {"coordinates":[4.3058462143,50.8577575684],"type":"Point"}
}