{
  "type": "Feature",
  "properties": {
    "addr:full":"Ruilare 178 Lochristi Oost-Vlaanderen 9080",
    "addr:housenumber":"178",
    "addr:postcode":"9080",
    "addr:street":"Ruilare",
    "iso:country":"BE",
    "sg:address":"Ruilare 178",
    "sg:city":"Lochristi",
    "sg:classifiers":[
        {
            "category":"Professional",
            "type":"Services"
        }
    ],
    "sg:phone":"+32 9 355 77 23",
    "sg:postcode":"9080",
    "sg:province":"Oost-Vlaanderen",
    "sg:tags":[
        "transport",
        "road"
    ],
    "wof:name":"Transport Jacques Taillie Nv",
    "wof:placetype":"venue"
},
  "geometry": {"coordinates":[3.8999888897,51.1218338013],"type":"Point"}
}