{
  "type": "Feature",
  "properties": {
    "addr:full":"Klaverbladstraat 13 Lummen Limburg 3560",
    "addr:housenumber":"13",
    "addr:postcode":"3560",
    "addr:street":"Klaverbladstraat",
    "iso:country":"BE",
    "sg:address":"Klaverbladstraat 13",
    "sg:city":"Lummen",
    "sg:orig_category":"Agences d'exp\u00e9dition",
    "sg:phone":"+32 13 52 30 65",
    "sg:postcode":"3560",
    "sg:province":"Limburg",
    "wof:name":"Dume Belgi\u00cb",
    "wof:placetype":"venue"
},
  "geometry": {"coordinates":[5.2281517982,50.9963188171],"type":"Point"}
}