{
  "type": "Feature",
  "properties": {
    "iso:country":"BE",
    "sg:address":"Scheldestraat 22-24",
    "sg:city":"Antwerpen",
    "sg:classifiers":[
        {
            "category":"Arts & Performance",
            "subcategory":"Art Gallery",
            "type":"Entertainment"
        }
    ],
    "sg:phone":"+32 3 257 13 45",
    "sg:postcode":"2000",
    "sg:province":"Antwerpen",
    "wof:name":"De Zilveren Toren",
    "wof:placetype":"venue"
},
  "geometry": {"coordinates":[4.3919582367,51.2128868103],"type":"Point"}
}