{
  "type": "Feature",
  "properties": {
    "iso:country":"BE",
    "sg:address":"Rue Th\u00e9odore Verhaegen 30",
    "sg:city":"Bruxelles (saint-gilles)",
    "sg:classifiers":[
        {
            "category":"Professional",
            "subcategory":"Testing Lab",
            "type":"Services"
        }
    ],
    "sg:phone":"+32 2 537 94 30",
    "sg:postcode":"1060",
    "sg:province":"Bruxelles-Capitale",
    "sg:tags":[
        "chemist"
    ],
    "wof:name":"Laurys A",
    "wof:placetype":"venue"
},
  "geometry": {"coordinates":[4.3421077728,50.8279151917],"type":"Point"}
}