{
  "type": "Feature",
  "properties": {
    "addr:full":"Chauss\u00e9e De Haecht 1774 Bruxelles Bruxelles-Capitale 1130",
    "addr:postcode":"1774;1130",
    "addr:street":"Chausse\u0301E De Haecht",
    "iso:country":"BE",
    "sg:address":"Chauss\u00e9e De Haecht 1774",
    "sg:city":"Bruxelles",
    "sg:classifiers":[
        {
            "category":"Shopping",
            "subcategory":"Computers & Home Electronics",
            "type":"Retail Goods"
        }
    ],
    "sg:phone":"+32 2 705 26 06",
    "sg:postcode":"1130",
    "sg:province":"Bruxelles-Capitale",
    "sg:tags":[
        "personal",
        "-",
        "processing",
        "data"
    ],
    "wof:name":"Run Applications",
    "wof:placetype":"venue"
},
  "geometry": {"coordinates":[4.4246721268,50.8882522583],"type":"Point"}
}