{
  "type": "Feature",
  "properties": {
    "iso:country":"BE",
    "sg:address":"Desmedtstraat 8",
    "sg:city":"Hoogstraten",
    "sg:classifiers":[
        {
            "category":"Insurance",
            "subcategory":"Life Insurance",
            "type":"Services"
        }
    ],
    "sg:phone":"+32 3 314 70 30",
    "sg:postcode":"2322",
    "sg:province":"Antwerpen",
    "sg:tags":[
        "assurance"
    ],
    "wof:name":"Zakenkantoor Desmet",
    "wof:placetype":"venue"
},
  "geometry": {"coordinates":[4.763384819,51.4160041809],"type":"Point"}
}