{
  "type": "Feature",
  "properties": {
    "addr:full":"Rue Des Combattants 32 Seneffe Hainaut 7180",
    "addr:housenumber":"32",
    "addr:postcode":"7180",
    "addr:street":"Rue Des Combattants",
    "iso:country":"BE",
    "sg:address":"Rue Des Combattants 32",
    "sg:city":"Seneffe",
    "sg:orig_category":"Boissons",
    "sg:phone":"+32 64 55 46 40",
    "sg:postcode":"7180",
    "sg:province":"Hainaut",
    "wof:name":"Willy Monty",
    "wof:placetype":"venue"
},
  "geometry": {"coordinates":[4.2546157837,50.5356445312],"type":"Point"}
}