{
  "type": "Feature",
  "properties": {
    "iso:country":"BE",
    "sg:address":"Kortrijksesteenweg 1128",
    "sg:city":"Sint-denijs-westrem",
    "sg:orig_category":"Herstellingen and onderhoud van auto's Voertuigen",
    "sg:phone":"+32 9 222 74 44",
    "sg:postcode":"9051",
    "sg:province":"Oost-Vlaanderen",
    "wof:name":"Intern Automobile Trading",
    "wof:placetype":"venue"
},
  "geometry": {"coordinates":[3.6683819294,51.020690918],"type":"Point"}
}