{
  "type": "Feature",
  "properties": {
    "addr:full":"Rue De Gosselies 174 Courcelles (trazegnies) Hainaut 6183",
    "addr:housenumber":"174",
    "addr:postcode":"6183",
    "addr:street":"Rue De Gosselies",
    "iso:country":"BE",
    "sg:address":"Rue De Gosselies 174",
    "sg:city":"Courcelles (trazegnies)",
    "sg:classifiers":[
        {
            "category":"Professional",
            "subcategory":"Accounting & Tax Preparation",
            "type":"Services"
        }
    ],
    "sg:phone":"+32 71 45 40 67",
    "sg:postcode":"6183",
    "sg:province":"Hainaut",
    "sg:tags":[
        "accountant"
    ],
    "wof:name":"Soc Civile Compta. De Gestion Et De Fiscalit\u00e9 C.g.f. Scrl",
    "wof:placetype":"venue"
},
  "geometry": {"coordinates":[4.3439102173,50.4629707336],"type":"Point"}
}