{
  "type": "Feature",
  "properties": {
    "iso:country":"BE",
    "sg:address":"Rue Neuve Chauss\u00e9e 175",
    "sg:city":"P\u00e9ruwelz",
    "sg:classifiers":[
        {
            "category":"Shopping",
            "subcategory":"Pets & Pet Supplies",
            "type":"Retail Goods"
        }
    ],
    "sg:phone":"+32 69 78 15 72",
    "sg:postcode":"7600",
    "sg:province":"Hainaut",
    "sg:tags":[
        "shop",
        "-"
    ],
    "wof:name":"Aquazone",
    "wof:placetype":"venue"
},
  "geometry": {"coordinates":[3.6016590595,50.5301437378],"type":"Point"}
}