{
  "type": "Feature",
  "properties": {
    "addr:full":"Gebroeders Van Raemdonckstraat 28 Roeselare (rumbeke) West-Vlaanderen 8800",
    "addr:housenumber":"28",
    "addr:postcode":"8800",
    "addr:street":"Gebroeders Van Raemdonckstraat",
    "iso:country":"BE",
    "sg:address":"Gebroeders Van Raemdonckstraat 28",
    "sg:city":"Roeselare (rumbeke)",
    "sg:classifiers":[
        {
            "category":"Insurance",
            "subcategory":"Insurance Agent",
            "type":"Services"
        }
    ],
    "sg:phone":"+32 51 21 01 57",
    "sg:postcode":"8800",
    "sg:province":"West-Vlaanderen",
    "sg:tags":[
        "broker"
    ],
    "wof:name":"Berteloot Myriam Nv",
    "wof:placetype":"venue"
},
  "geometry": {"coordinates":[3.1661739349,50.9282226562],"type":"Point"}
}