{
  "type": "Feature",
  "properties": {
    "iso:country":"BE",
    "sg:address":"Rue De Regniessart 3",
    "sg:city":"Viroinval",
    "sg:orig_category":"Artsen and specialisten",
    "sg:phone":"+32 60 39 94 01",
    "sg:postcode":"5670",
    "sg:province":"Namur",
    "wof:name":"C. Vandevyver",
    "wof:placetype":"venue"
},
  "geometry": {"coordinates":[4.5808758736,50.0150985718],"type":"Point"}
}