{
  "type": "Feature",
  "properties": {
    "iso:country":"BE",
    "sg:address":"Fortstraat 41",
    "sg:city":"Maaseik (opoeteren)",
    "sg:classifiers":[
        {
            "category":"Health Services",
            "subcategory":"Doctor",
            "type":"Services"
        }
    ],
    "sg:phone":"+32 89 86 31 68",
    "sg:postcode":"3680",
    "sg:province":"Limburg",
    "sg:tags":[
        "medicinephysicians",
        "surgeon"
    ],
    "wof:name":"Kuipers Roger",
    "wof:placetype":"venue"
},
  "geometry": {"coordinates":[5.6574001312,51.06615448],"type":"Point"}
}