{
  "type": "Feature",
  "properties": {
    "iso:country":"BE",
    "sg:address":"Moerdijkstraat 56a",
    "sg:city":"Ichtegem",
    "sg:classifiers":[
        {
            "category":"Building & Trades",
            "subcategory":"Landscaping Services",
            "type":"Services"
        }
    ],
    "sg:phone":"+32 51 58 91 29",
    "sg:postcode":"8480",
    "sg:province":"West-Vlaanderen",
    "sg:tags":[
        "gardening",
        "garden",
        "maintenance"
    ],
    "wof:name":"Daene Tuinteam Bvba",
    "wof:placetype":"venue"
},
  "geometry": {"coordinates":[3.0116989613,51.1005363464],"type":"Point"}
}