{
  "type": "Feature",
  "properties": {
    "addr:full":"Chauss\u00c9e De Bruxelles 293 Charleroi Hainaut 6042",
    "addr:housenumber":"293",
    "addr:postcode":"6042",
    "addr:street":"Chausse\u0301E De Bruxelles;Hainaut",
    "iso:country":"BE",
    "sg:address":"Chauss\u00c9e De Bruxelles 293",
    "sg:city":"Charleroi",
    "sg:orig_category":"Motoren, transformatoren and generatoren Fab Verhuur bouwmachines Verhuur doe-het-zelf materiaal",
    "sg:phone":"+32 71 31 20 20",
    "sg:postcode":"6042",
    "sg:province":"Hainaut",
    "wof:name":"Delloue",
    "wof:placetype":"venue"
},
  "geometry": {"coordinates":[4.435587883,50.4456443787],"type":"Point"}
}