{
  "type": "Feature",
  "properties": {
    "addr:full":"Albertwal 2 Tongeren Limburg 3700",
    "addr:housenumber":"2",
    "addr:postcode":"3700",
    "addr:street":"Albertwal",
    "iso:country":"BE",
    "sg:address":"Albertwal 2",
    "sg:city":"Tongeren",
    "sg:orig_category":"Maroquinerie and articles de voyage. Artistes ind\u00e9pendants",
    "sg:phone":"+32 12 23 19 42",
    "sg:postcode":"3700",
    "sg:province":"Limburg",
    "wof:name":"Pierre Jadoulle",
    "wof:placetype":"venue"
},
  "geometry": {"coordinates":[5.4599270821,50.7778816223],"type":"Point"}
}