{
  "type": "Feature",
  "properties": {
    "iso:country":"BE",
    "sg:address":"Rue Saint-michel 2",
    "sg:city":"Saint-hubert",
    "sg:orig_category":"Kapsalons",
    "sg:phone":"+32 61 61 10 01",
    "sg:postcode":"6870",
    "sg:province":"Luxembourg",
    "wof:name":"Coiffure Diminu-tifs",
    "wof:placetype":"venue"
},
  "geometry": {"coordinates":[5.3741350174,50.0282936096],"type":"Point"}
}