{
  "type": "Feature",
  "properties": {
    "addr:full":"Platanenlaan 30 Harelbeke West-Vlaanderen 8530",
    "addr:housenumber":"30",
    "addr:postcode":"8530",
    "addr:street":"Platanenlaan",
    "iso:country":"BE",
    "sg:address":"Platanenlaan 30",
    "sg:city":"Harelbeke",
    "sg:classifiers":[
        {
            "category":"Arena",
            "subcategory":"Sports Club",
            "type":"Entertainment"
        }
    ],
    "sg:phone":"+32 56 70 17 39",
    "sg:postcode":"8530",
    "sg:province":"West-Vlaanderen",
    "sg:tags":[
        "de"
    ],
    "wof:name":"Zwemclub Ursus",
    "wof:placetype":"venue"
},
  "geometry": {"coordinates":[3.3059411049,50.8396644592],"type":"Point"}
}