{
  "type": "Feature",
  "properties": {
    "addr:full":"Hoogton 26 Herentals Antwerpen 2200",
    "addr:housenumber":"26",
    "addr:postcode":"2200",
    "addr:street":"Hoogton",
    "iso:country":"BE",
    "sg:address":"Hoogton 26",
    "sg:city":"Herentals",
    "sg:orig_category":"Graan, zaad and dierenvoeding Gh",
    "sg:phone":"+32 14 26 14 21",
    "sg:postcode":"2200",
    "sg:province":"Antwerpen",
    "wof:name":"Dierenvoedercentrale Eyckmans J.",
    "wof:placetype":"venue"
},
  "geometry": {"coordinates":[4.8349981308,51.124786377],"type":"Point"}
}