{
  "type": "Feature",
  "properties": {
    "addr:full":"Lange Lostraat 98 Leuven (kessel-lo) Vlaams-Brabant 3010",
    "addr:housenumber":"98",
    "addr:postcode":"3010",
    "addr:street":"Lange Lostraat",
    "iso:country":"BE",
    "sg:address":"Lange Lostraat 98",
    "sg:city":"Leuven (kessel-lo)",
    "sg:classifiers":[
        {
            "category":"Food & Beverages",
            "subcategory":"Liquor & Beverages",
            "type":"Retail Goods"
        }
    ],
    "sg:phone":"+32 16 26 06 47",
    "sg:postcode":"3010",
    "sg:province":"Vlaams-Brabant",
    "sg:tags":[
        "-",
        "spirit",
        "wine"
    ],
    "wof:name":"Duerinckx J",
    "wof:placetype":"venue"
},
  "geometry": {"coordinates":[4.7553877831,50.8719711304],"type":"Point"}
}