{
  "type": "Feature",
  "properties": {
    "iso:country":"BE",
    "sg:address":"Grote Baan 598",
    "sg:city":"Houthalen-helchteren",
    "sg:orig_category":"Fournitures de bureau. Souvenirs and objets artisanaux. Librairies. Articles pour b\u00e9b\u00e9s. Jeux and jo",
    "sg:phone":"+32 11 60 17 96",
    "sg:postcode":"3530",
    "sg:province":"Limburg",
    "wof:name":"Droomland Helchteren",
    "wof:placetype":"venue"
},
  "geometry": {"coordinates":[5.3802499771,51.0446510315],"type":"Point"}
}