{
  "type": "Feature",
  "properties": {
    "iso:country":"BE",
    "sg:address":"Guido Gezellestraat 7",
    "sg:city":"Kuurne",
    "sg:orig_category":"Non-Classified Establishments",
    "sg:phone":"+32 56 70 62 99",
    "sg:postcode":"8520",
    "sg:province":"West-Vlaanderen",
    "wof:name":"Vetera Biopharma Bvba",
    "wof:placetype":"venue"
},
  "geometry": {"coordinates":[3.2887969017,50.8522644043],"type":"Point"}
}