{
  "type": "Feature",
  "properties": {
    "addr:full":"Rue Du Pire 9 Braine-le-comte Hainaut 7090",
    "addr:housenumber":"9",
    "addr:postcode":"7090",
    "addr:street":"Rue Du Pire",
    "iso:country":"BE",
    "sg:address":"Rue Du Pire 9",
    "sg:city":"Braine-le-comte",
    "sg:orig_category":"Kapsalons",
    "sg:phone":"+32 67 55 73 79",
    "sg:postcode":"7090",
    "sg:province":"Hainaut",
    "wof:name":"Mireille Panneels",
    "wof:placetype":"venue"
},
  "geometry": {"coordinates":[4.1514029503,50.6189727783],"type":"Point"}
}