{
  "type": "Feature",
  "properties": {
    "addr:full":"Rue Tienne \u00c0 La Justice 7 Ciney Namur 5590",
    "addr:housenumber":"7",
    "addr:postcode":"5590",
    "addr:street":"Rue Tienne A\u0300 La Justice",
    "iso:country":"BE",
    "sg:address":"Rue Tienne \u00c0 La Justice 7",
    "sg:city":"Ciney",
    "sg:orig_category":"Dakwerken",
    "sg:phone":"+32 83 21 54 66",
    "sg:postcode":"5590",
    "sg:province":"Namur",
    "wof:name":"Eric Kinard",
    "wof:placetype":"venue"
},
  "geometry": {"coordinates":[5.108194828,50.2916374207],"type":"Point"}
}