{
  "type": "Feature",
  "properties": {
    "iso:country":"BE",
    "sg:address":"Sentier De Beaumont 3",
    "sg:city":"Esneux",
    "sg:classifiers":[
        {
            "category":"Real Estate",
            "subcategory":"Architect",
            "type":"Services"
        }
    ],
    "sg:phone":"+32 4 380 21 02",
    "sg:postcode":"4130",
    "sg:province":"Li\u00e8ge",
    "wof:name":"Maka M",
    "wof:placetype":"venue"
},
  "geometry": {"coordinates":[5.5648169518,50.5346870422],"type":"Point"}
}