{
  "type": "Feature",
  "properties": {
    "iso:country":"BE",
    "sg:address":"Rue De Bassilly 18",
    "sg:city":"Silly",
    "sg:orig_category":"Eleveurs and marchands de porcs. Eleveurs de bovins",
    "sg:phone":"+32 68 55 15 09",
    "sg:postcode":"7830",
    "sg:province":"Hainaut",
    "wof:name":"Antoine Verschelden",
    "wof:placetype":"venue"
},
  "geometry": {"coordinates":[3.9363250732,50.6577606201],"type":"Point"}
}