{
  "type": "Feature",
  "properties": {
    "addr:full":"Rue Du Monument 16 Durbuy Luxembourg 6940",
    "addr:housenumber":"16",
    "addr:postcode":"6940",
    "addr:street":"Rue Du Monument",
    "iso:country":"BE",
    "sg:address":"Rue Du Monument 16",
    "sg:city":"Durbuy",
    "sg:orig_category":"Magasins sp\u00e9cialis\u00e9s. Rev\u00eatements pour sols and murs. Construction de maisons",
    "sg:phone":"+32 86 21 30 46",
    "sg:postcode":"6940",
    "sg:province":"Luxembourg",
    "wof:name":"Jan Brabant",
    "wof:placetype":"venue"
},
  "geometry": {"coordinates":[5.4156680107,50.3281173706],"type":"Point"}
}