{
  "type": "Feature",
  "properties": {
    "addr:full":"Warmoesstraat 135 Sint-joost-ten-node/saint-josse-ten-noode Bruxelles-Capitale 1210",
    "addr:housenumber":"135",
    "addr:postcode":"1210",
    "addr:street":"Warmoesstraat;Sint-Joost-Ten-Node /",
    "iso:country":"BE",
    "sg:address":"Warmoesstraat 135",
    "sg:city":"Sint-joost-ten-node/saint-josse-ten-noode",
    "sg:orig_category":"Artsen and specialisten",
    "sg:phone":"+32 2 223 17 11",
    "sg:postcode":"1210",
    "sg:province":"Bruxelles-Capitale",
    "wof:name":"Juliette Zinga Bila",
    "wof:placetype":"venue"
},
  "geometry": {"coordinates":[4.3728961945,50.8548126221],"type":"Point"}
}