{
  "type": "Feature",
  "properties": {
    "iso:country":"BE",
    "sg:address":"Derbylaan 57",
    "sg:city":"Elsene/ixelles",
    "sg:orig_category":"Diverse opleidingen and onderwijs",
    "sg:phone":"+32 2 660 03 20",
    "sg:postcode":"1050",
    "sg:province":"Bruxelles-Capitale",
    "wof:name":"Quorum Consult",
    "wof:placetype":"venue"
},
  "geometry": {"coordinates":[4.3904352188,50.8026390076],"type":"Point"}
}