{
  "type": "Feature",
  "properties": {
    "iso:country":"BE",
    "sg:address":"Bergensesteenweg 701",
    "sg:city":"Sint-pieters-leeuw",
    "sg:classifiers":[
        {
            "category":"Manufacturing",
            "subcategory":"Furniture",
            "type":"Manufacturing & Wholesale Goods"
        }
    ],
    "sg:phone":"+32 2 377 73 07",
    "sg:postcode":"1600",
    "sg:province":"Vlaams-Brabant",
    "sg:tags":[
        "armchair",
        "-"
    ],
    "wof:name":"Ideal Salon",
    "wof:placetype":"venue"
},
  "geometry": {"coordinates":[4.2553730011,50.7669525146],"type":"Point"}
}