{
  "type": "Feature",
  "properties": {
    "iso:country":"BE",
    "sg:address":"Rue De La Fonderie 61",
    "sg:city":"La Louvi\u00e8re",
    "sg:classifiers":[
        {
            "category":"Building & Trades",
            "subcategory":"Pest Control",
            "type":"Services"
        }
    ],
    "sg:phone":"+32 64 21 25 15",
    "sg:postcode":"7100",
    "sg:province":"Hainaut",
    "sg:tags":[
        "painting",
        "contractor"
    ],
    "wof:name":"Fontaine G",
    "wof:placetype":"venue"
},
  "geometry": {"coordinates":[4.1849479675,50.4706459045],"type":"Point"}
}