{
  "type": "Feature",
  "properties": {
    "iso:country":"BE",
    "sg:address":"Rue De Musy 8bc",
    "sg:city":"Bastogne",
    "sg:orig_category":"M\u00e9decins and sp\u00e9cialistes",
    "sg:phone":"+32 61 21 26 61",
    "sg:postcode":"6600",
    "sg:province":"Luxembourg",
    "wof:name":"H. Determe",
    "wof:placetype":"venue"
},
  "geometry": {"coordinates":[5.7071108818,50.001121521],"type":"Point"}
}