{
  "type": "Feature",
  "properties": {
    "iso:country":"BE",
    "sg:address":"Place Ferrer 1",
    "sg:city":"Soumagne",
    "sg:classifiers":[
        {
            "category":"Wholesale",
            "subcategory":"Fruits & Vegetables",
            "type":"Manufacturing & Wholesale Goods"
        }
    ],
    "sg:phone":"+32 4 377 37 57",
    "sg:postcode":"4630",
    "sg:province":"Li\u00e8ge",
    "sg:tags":[
        "whol",
        "-"
    ],
    "wof:name":"Pepinster Fr\u00e8res",
    "wof:placetype":"venue"
},
  "geometry": {"coordinates":[5.7480010986,50.6115989685],"type":"Point"}
}