{
  "type": "Feature",
  "properties": {
    "iso:country":"BE",
    "sg:address":"Dauwstraat 6",
    "sg:city":"Anderlecht/anderlecht",
    "sg:orig_category":"Fietsen",
    "sg:phone":"+32 2 521 06 99",
    "sg:postcode":"1070",
    "sg:province":"Bruxelles-Capitale",
    "wof:name":"Maison Plume Sport",
    "wof:placetype":"venue"
},
  "geometry": {"coordinates":[4.337416172,50.8463401794],"type":"Point"}
}