{
  "type": "Feature",
  "properties": {
    "iso:country":"BE",
    "sg:address":"Edewallestraat 129",
    "sg:city":"Kortemark",
    "sg:classifiers":[
        {
            "category":"Utilities",
            "subcategory":"Mobile Phone",
            "type":"Services"
        }
    ],
    "sg:phone":"+32 51 56 69 82",
    "sg:postcode":"8610",
    "sg:province":"West-Vlaanderen",
    "sg:tags":[
        "access",
        "gsm",
        "-",
        "apparatus"
    ],
    "wof:name":"Tierenteyn D",
    "wof:placetype":"venue"
},
  "geometry": {"coordinates":[3.0064299107,51.041469574],"type":"Point"}
}