{
  "type": "Feature",
  "properties": {
    "addr:full":"Sint-martinusplein 25-27 Genk Limburg 3600",
    "addr:postcode":"25-27 genk;3600",
    "iso:country":"BE",
    "sg:address":"Sint-martinusplein 25-27",
    "sg:city":"Genk",
    "sg:orig_category":"Banques and organismes de cr\u00e9dit",
    "sg:phone":"+32 89 35 42 37",
    "sg:postcode":"3600",
    "sg:province":"Limburg",
    "wof:name":"Citibank",
    "wof:placetype":"venue"
},
  "geometry": {"coordinates":[5.4974107742,50.9650268555],"type":"Point"}
}