{
  "type": "Feature",
  "properties": {
    "addr:full":"Rue Aux Saules 64 Genappe Brabant Wallon 1471",
    "addr:housenumber":"64",
    "addr:postcode":"1471",
    "addr:street":"Rue Aux Saules;Wallon",
    "iso:country":"BE",
    "sg:address":"Rue Aux Saules 64",
    "sg:city":"Genappe",
    "sg:orig_category":"HUISBRANDOLIE",
    "sg:phone":"+32 67 77 32 31",
    "sg:postcode":"1471",
    "sg:province":"Brabant Wallon",
    "wof:name":"Francis Charlier",
    "wof:placetype":"venue"
},
  "geometry": {"coordinates":[4.4408750534,50.5894126892],"type":"Point"}
}