{
  "type": "Feature",
  "properties": {
    "addr:full":"Gen. Baron Jacquesstraat 68 Diksmuide West-Vlaanderen 8600",
    "addr:housenumber":"68",
    "addr:postcode":"8600",
    "addr:street":"Gen. Baron Jacquesstraat",
    "iso:country":"BE",
    "sg:address":"Gen. Baron Jacquesstraat 68",
    "sg:city":"Diksmuide",
    "sg:classifiers":[
        {
            "category":"Personal",
            "subcategory":"Beauty Salon",
            "type":"Services"
        }
    ],
    "sg:phone":"+32 51 50 04 72",
    "sg:postcode":"8600",
    "sg:province":"West-Vlaanderen",
    "sg:tags":[
        "de",
        "coiffure"
    ],
    "wof:name":"Joseph Vanacker",
    "wof:placetype":"venue"
},
  "geometry": {"coordinates":[2.8603150845,51.033241272],"type":"Point"}
}