{
  "type": "Feature",
  "properties": {
    "addr:full":"Zandvoordedorpstraat 74 Oostende West-Vlaanderen 8400",
    "addr:housenumber":"74",
    "addr:postcode":"8400",
    "addr:street":"Zandvoordedorpstraat",
    "iso:country":"BE",
    "sg:address":"Zandvoordedorpstraat 74",
    "sg:city":"Oostende",
    "sg:orig_category":"Fietsen Motorfietsen Tuinbenodigdheden",
    "sg:phone":"+32 59 26 77 70",
    "sg:postcode":"8400",
    "sg:province":"West-Vlaanderen",
    "wof:name":"Fietsen Kurt",
    "wof:placetype":"venue"
},
  "geometry": {"coordinates":[2.9383831024,51.2159881592],"type":"Point"}
}