{
  "type": "Feature",
  "properties": {
    "iso:country":"BE",
    "sg:address":"Rue Des Martyrs De Soltau 27",
    "sg:city":"Soignies",
    "sg:classifiers":[
        {
            "category":"Banks & Credit Unions",
            "subcategory":"Financial Services",
            "type":"Services"
        }
    ],
    "sg:phone":"+32 67 41 16 00",
    "sg:postcode":"7060",
    "sg:province":"Hainaut",
    "sg:tags":[
        "financing"
    ],
    "wof:name":"C.a.c.p. Sprl",
    "wof:placetype":"venue"
},
  "geometry": {"coordinates":[4.0696749687,50.5774726868],"type":"Point"}
}