{
  "type": "Feature",
  "properties": {
    "iso:country":"BE",
    "sg:address":"Venelle De La Ram\u00c9e 18",
    "sg:city":"Wavre",
    "sg:orig_category":"Architectes",
    "sg:phone":"+32 10 24 20 16",
    "sg:postcode":"1301",
    "sg:province":"Brabant Wallon",
    "wof:name":"Gaetan Grignard",
    "wof:placetype":"venue"
},
  "geometry": {"coordinates":[4.6169772148,50.7015151978],"type":"Point"}
}