{
  "type": "Feature",
  "properties": {
    "addr:full":"Charneux 66a Jalhay Li\u00e8ge 4845",
    "addr:housenumber":"66a",
    "addr:postcode":"4845",
    "addr:street":"Charneux",
    "iso:country":"BE",
    "sg:address":"Charneux 66a",
    "sg:city":"Jalhay",
    "sg:classifiers":[
        {
            "category":"Building & Trades",
            "subcategory":"Pest Control",
            "type":"Services"
        }
    ],
    "sg:phone":"+32 87 64 73 58",
    "sg:postcode":"4845",
    "sg:province":"Li\u00e8ge",
    "sg:tags":[
        "painting",
        "contractor"
    ],
    "wof:name":"Delrez B",
    "wof:placetype":"venue"
},
  "geometry": {"coordinates":[5.9664101601,50.5517997742],"type":"Point"}
}