{
  "type": "Feature",
  "properties": {
    "addr:full":"Rue De La Station 29 Rixensart Brabant Wallon 1332",
    "addr:housenumber":"29",
    "addr:postcode":"1332",
    "addr:street":"Rue De La Station;Wallon",
    "iso:country":"BE",
    "sg:address":"Rue De La Station 29",
    "sg:city":"Rixensart",
    "sg:classifiers":[
        {
            "category":"Fast Food",
            "type":"Food & Drink"
        }
    ],
    "sg:phone":"+32 2 653 24 78",
    "sg:postcode":"1332",
    "sg:province":"Brabant Wallon",
    "sg:tags":[
        "\u00c0",
        "restaurants",
        "emporter",
        "restaurant"
    ],
    "wof:name":"La Dolce Pasta",
    "wof:placetype":"venue"
},
  "geometry": {"coordinates":[4.514538765,50.7248420715],"type":"Point"}
}