{
  "type": "Feature",
  "properties": {
    "iso:country":"BE",
    "sg:address":"Halveweg 94",
    "sg:city":"Zonhoven",
    "sg:orig_category":"Voertuigen",
    "sg:phone":"+32 11 81 37 75",
    "sg:postcode":"3520",
    "sg:province":"Limburg",
    "wof:name":"Zonhovense Truck & Car",
    "wof:placetype":"venue"
},
  "geometry": {"coordinates":[5.3400640488,50.9954566956],"type":"Point"}
}