{
  "type": "Feature",
  "properties": {
    "addr:full":"Chee.del'europe 21 Couvin Namur 5660",
    "addr:housenumber":"21",
    "addr:postcode":"5660",
    "addr:street":"Chee.Del'Europe",
    "iso:country":"BE",
    "sg:address":"Chee.del'europe 21",
    "sg:city":"Couvin",
    "sg:orig_category":"Plomberie, chauffage and installations sanitaires. Installation de serres, double vitrage and fen\u00eatr",
    "sg:phone":"+32 60 37 72 77",
    "sg:postcode":"5660",
    "sg:province":"Namur",
    "wof:name":"Hollywoof",
    "wof:placetype":"venue"
},
  "geometry": {"coordinates":[4.4537410736,49.9605827332],"type":"Point"}
}