{
  "type": "Feature",
  "properties": {
    "iso:country":"BE",
    "sg:address":"Route D'ohain 12",
    "sg:city":"Lasne",
    "sg:orig_category":"Herstellingen and onderhoud van auto's Voertuigen",
    "sg:phone":"+32 2 633 10 02",
    "sg:postcode":"1380",
    "sg:province":"Brabant Wallon",
    "wof:name":"Lasne Motor",
    "wof:placetype":"venue"
},
  "geometry": {"coordinates":[4.4820179939,50.6873245239],"type":"Point"}
}