{
  "type": "Feature",
  "properties": {
    "addr:full":"Diestsesteenweg 46 Herk-de-stad Limburg 3540",
    "addr:housenumber":"46",
    "addr:postcode":"3540",
    "addr:street":"Diestsesteenweg",
    "iso:country":"BE",
    "sg:address":"Diestsesteenweg 46",
    "sg:city":"Herk-de-stad",
    "sg:orig_category":"Epiceries",
    "sg:phone":"+32 13 55 19 76",
    "sg:postcode":"3540",
    "sg:province":"Limburg",
    "wof:name":"Leon Smeets",
    "wof:placetype":"venue"
},
  "geometry": {"coordinates":[5.1570668221,50.9417800903],"type":"Point"}
}