{
  "type": "Feature",
  "properties": {
    "addr:full":"Meinstraat 6 Sint-truiden Limburg 3800",
    "addr:housenumber":"6",
    "addr:postcode":"3800",
    "addr:street":"Meinstraat",
    "iso:country":"BE",
    "sg:address":"Meinstraat 6",
    "sg:city":"Sint-truiden",
    "sg:orig_category":"Pain, p\u00e2tisseries and confiseries. Cr\u00e9meries",
    "sg:phone":"+32 11 68 21 01",
    "sg:postcode":"3800",
    "sg:province":"Limburg",
    "wof:name":"Bakkerij Nolens A.",
    "wof:placetype":"venue"
},
  "geometry": {"coordinates":[5.1866889,50.8163070679],"type":"Point"}
}