{
  "type": "Feature",
  "properties": {
    "iso:country":"BE",
    "sg:address":"Chee De March\u00e9 77",
    "sg:city":"Assesse",
    "sg:classifiers":[
        {
            "category":"Banks & Credit Unions",
            "subcategory":"Bank",
            "type":"Services"
        }
    ],
    "sg:phone":"+32 83 65 54 17",
    "sg:postcode":"5330",
    "sg:province":"Namur",
    "wof:name":"Aslk-cger Bank",
    "wof:placetype":"venue"
},
  "geometry": {"coordinates":[5.0236301422,50.3698616028],"type":"Point"}
}