{
  "type": "Feature",
  "properties": {
    "addr:full":"Boomgaard 23 Zaventem (nossegem) Vlaams-Brabant 1930",
    "addr:housenumber":"23",
    "addr:postcode":"1930",
    "addr:street":"Boomgaard",
    "iso:country":"BE",
    "sg:address":"Boomgaard 23",
    "sg:city":"Zaventem (nossegem)",
    "sg:classifiers":[
        {
            "category":"Shopping",
            "subcategory":"Pets & Pet Supplies",
            "type":"Retail Goods"
        }
    ],
    "sg:phone":"+32 2 644 26 76",
    "sg:postcode":"1930",
    "sg:province":"Vlaams-Brabant",
    "sg:tags":[
        "shop",
        "-"
    ],
    "wof:name":"Brussels Felinophile Cat Assoc.",
    "wof:placetype":"venue"
},
  "geometry": {"coordinates":[4.5138401985,50.8803710938],"type":"Point"}
}