{
  "type": "Feature",
  "properties": {
    "iso:country":"BE",
    "sg:address":"Rue Hazinelle 2",
    "sg:city":"Li\u00c8ge",
    "sg:orig_category":"Enseignement secondaire g\u00e9n\u00e9ral. Enseignement secondaire technique and professionnel",
    "sg:phone":"+32 4 223 08 73",
    "sg:postcode":"4000",
    "sg:province":"Li\u00e8ge",
    "wof:name":"I.c.e.s. Hazinelle",
    "wof:placetype":"venue"
},
  "geometry": {"coordinates":[5.5698370934,50.6397781372],"type":"Point"}
}