{
  "type": "Feature",
  "properties": {
    "addr:full":"Schijndallaan 9 Brecht (sint-job-in-'t Goor) Antwerpen 2960",
    "addr:housenumber":"9",
    "addr:postcode":"2960",
    "addr:street":"Schijndallaan;' T Goor",
    "iso:country":"BE",
    "sg:address":"Schijndallaan 9",
    "sg:city":"Brecht (sint-job-in-'t Goor)",
    "sg:classifiers":[
        {
            "category":"Freight",
            "type":"Transportation"
        }
    ],
    "sg:phone":"+32 3 636 40 01",
    "sg:postcode":"2960",
    "sg:province":"Antwerpen",
    "sg:tags":[
        "-",
        "transport"
    ],
    "wof:name":"Euro-kado",
    "wof:placetype":"venue"
},
  "geometry": {"coordinates":[4.5777797699,51.2912406921],"type":"Point"}
}