{
  "type": "Feature",
  "properties": {
    "addr:full":"Rue Mattheussens 35 Evere Bruxelles-Capitale 1140",
    "addr:housenumber":"35",
    "addr:postcode":"1140",
    "addr:street":"Rue Mattheussens",
    "iso:country":"BE",
    "sg:address":"Rue Mattheussens 35",
    "sg:city":"Evere",
    "sg:classifiers":[
        {
            "category":"Arena",
            "subcategory":"Sports Club",
            "type":"Entertainment"
        }
    ],
    "sg:phone":"+32 2 242 27 38",
    "sg:postcode":"1140",
    "sg:province":"Bruxelles-Capitale",
    "sg:tags":[
        "de"
    ],
    "wof:name":"Le Logis",
    "wof:placetype":"venue"
},
  "geometry": {"coordinates":[4.3952908516,50.8746566772],"type":"Point"}
}