{
  "type": "Feature",
  "properties": {
    "addr:full":"Rue Flache 36 Viroinval Namur 5670",
    "addr:housenumber":"36",
    "addr:postcode":"5670",
    "addr:street":"Rue Flache",
    "iso:country":"BE",
    "sg:address":"Rue Flache 36",
    "sg:city":"Viroinval",
    "sg:orig_category":"Schoonheidssalons",
    "sg:phone":"+32 60 39 90 94",
    "sg:postcode":"5670",
    "sg:province":"Namur",
    "wof:name":"Patricia Balsacq",
    "wof:placetype":"venue"
},
  "geometry": {"coordinates":[4.6526589394,50.0223197937],"type":"Point"}
}