{
  "type": "Feature",
  "properties": {
    "addr:full":"Rue Bossy 14 Amay Li\u00e8ge 4540",
    "addr:housenumber":"14",
    "addr:postcode":"4540",
    "addr:street":"Rue Bossy",
    "iso:country":"BE",
    "sg:address":"Rue Bossy 14",
    "sg:city":"Amay",
    "sg:orig_category":"R\u00e9parations de chaussures and articles en cuir",
    "sg:phone":"+32 85 31 34 14",
    "sg:postcode":"4540",
    "sg:province":"Li\u00e8ge",
    "wof:name":"Pierre Vaisiere",
    "wof:placetype":"venue"
},
  "geometry": {"coordinates":[5.3107709885,50.5434951782],"type":"Point"}
}