{
  "type": "Feature",
  "properties": {
    "addr:full":"Nieuwstraat 17 Aalst Oost-Vlaanderen 9300",
    "addr:housenumber":"17",
    "addr:postcode":"9300",
    "addr:street":"Nieuwstraat",
    "iso:country":"BE",
    "sg:address":"Nieuwstraat 17",
    "sg:city":"Aalst",
    "sg:orig_category":"Dameskledingzaken",
    "sg:phone":"+32 53 70 11 30",
    "sg:postcode":"9300",
    "sg:province":"Oost-Vlaanderen",
    "wof:name":"Huis Briton",
    "wof:placetype":"venue"
},
  "geometry": {"coordinates":[4.0354328156,50.9372558594],"type":"Point"}
}