{
  "type": "Feature",
  "properties": {
    "addr:full":"Galgevoort 18 Malle Antwerpen 2390",
    "addr:housenumber":"18",
    "addr:postcode":"2390",
    "addr:street":"Galgevoort",
    "iso:country":"BE",
    "sg:address":"Galgevoort 18",
    "sg:city":"Malle",
    "sg:orig_category":"Rundveehouders",
    "sg:phone":"+32 3 312 13 81",
    "sg:postcode":"2390",
    "sg:province":"Antwerpen",
    "wof:name":"Polidoor Van Hove",
    "wof:placetype":"venue"
},
  "geometry": {"coordinates":[4.7054300308,51.3251304626],"type":"Point"}
}