{
  "type": "Feature",
  "properties": {
    "addr:full":"Rue De Mons 155 Qui\u00c9vrain Hainaut 7380",
    "addr:housenumber":"155",
    "addr:postcode":"7380",
    "addr:street":"Rue De Mons",
    "iso:country":"BE",
    "sg:address":"Rue De Mons 155",
    "sg:city":"Qui\u00c9vrain",
    "sg:orig_category":"Entretien and r\u00e9parations de voitures",
    "sg:phone":"+32 65 43 18 96",
    "sg:postcode":"7380",
    "sg:province":"Hainaut",
    "wof:name":"J.m. De Witte",
    "wof:placetype":"venue"
},
  "geometry": {"coordinates":[3.7004480362,50.4100189209],"type":"Point"}
}