{
  "type": "Feature",
  "properties": {
    "addr:full":"L\u00fctticher Strasse 245 Kelmis (neu Moresnet) Li\u00e8ge 4721",
    "addr:housenumber":"245",
    "addr:postcode":"4721",
    "addr:street":"Luetticher Strasse;Neu",
    "iso:country":"BE",
    "sg:address":"L\u00fctticher Strasse 245",
    "sg:city":"Kelmis (neu Moresnet)",
    "sg:orig_category":"Non-Classified Establishments",
    "sg:phone":"+32 87 63 92 50",
    "sg:postcode":"4721",
    "sg:province":"Li\u00e8ge",
    "wof:name":"Rimex",
    "wof:placetype":"venue"
},
  "geometry": {"coordinates":[6.0333528519,50.7261695862],"type":"Point"}
}