{
  "type": "Feature",
  "properties": {
    "addr:full":"Polderstraat 7 Tielt West-Vlaanderen 8700",
    "addr:housenumber":"7",
    "addr:postcode":"8700",
    "addr:street":"Polderstraat",
    "iso:country":"BE",
    "sg:address":"Polderstraat 7",
    "sg:city":"Tielt",
    "sg:orig_category":"Eleveurs de bovins. Eleveurs and marchands de porcs",
    "sg:phone":"+32 51 68 87 45",
    "sg:postcode":"8700",
    "sg:province":"West-Vlaanderen",
    "wof:name":"Pierre Vandeputte",
    "wof:placetype":"venue"
},
  "geometry": {"coordinates":[3.3616130352,51.0270271301],"type":"Point"}
}