{
  "type": "Feature",
  "properties": {
    "addr:full":"Rue O Lef\u00e8vre 17 Charleroi Hainaut 6000",
    "addr:housenumber":"17",
    "addr:postcode":"6000",
    "addr:street":"Rue O Lefe\u0300Vre;Hainaut",
    "iso:country":"BE",
    "sg:address":"Rue O Lef\u00e8vre 17",
    "sg:city":"Charleroi",
    "sg:classifiers":[
        {
            "category":"Banks & Credit Unions",
            "subcategory":"Bank",
            "type":"Services"
        }
    ],
    "sg:phone":"+32 71 41 77 06",
    "sg:postcode":"6000",
    "sg:province":"Hainaut",
    "wof:name":"Banque Bruxelles Lambert Sa",
    "wof:placetype":"venue"
},
  "geometry": {"coordinates":[4.4586000443,50.4217834473],"type":"Point"}
}