{
  "type": "Feature",
  "properties": {
    "iso:country":"BE",
    "sg:address":"Kerkbruggestraat 5",
    "sg:city":"Evergem",
    "sg:classifiers":[
        {
            "category":"Bakery",
            "type":"Food & Drink"
        }
    ],
    "sg:phone":"+32 9 253 54 54",
    "sg:postcode":"9940",
    "sg:province":"Oost-Vlaanderen",
    "sg:tags":[
        "confectioner",
        "baker"
    ],
    "wof:name":"Bakkerij Kris",
    "wof:placetype":"venue"
},
  "geometry": {"coordinates":[3.736125946,51.1242485046],"type":"Point"}
}