{
  "type": "Feature",
  "properties": {
    "iso:country":"BE",
    "sg:address":"Mechelsesteenweg 113",
    "sg:city":"Sint-katelijne-waver",
    "sg:classifiers":[
        {
            "category":"Cafe",
            "type":"Food & Drink"
        }
    ],
    "sg:phone":"+32 15 63 84 96",
    "sg:postcode":"2860",
    "sg:province":"Antwerpen",
    "sg:tags":[
        "snack-bars"
    ],
    "wof:name":"Kruimelke ('t)",
    "wof:placetype":"venue"
},
  "geometry": {"coordinates":[4.5256118774,51.0581207275],"type":"Point"}
}