{
  "type": "Feature",
  "properties": {
    "iso:country":"BE",
    "sg:address":"Sluizenstraat 113",
    "sg:city":"Schoten",
    "sg:classifiers":[
        {
            "category":"Manufacturing",
            "subcategory":"Lumber",
            "type":"Manufacturing & Wholesale Goods"
        }
    ],
    "sg:phone":"+32 3 658 42 81",
    "sg:postcode":"2900",
    "sg:province":"Antwerpen",
    "sg:tags":[
        "timber"
    ],
    "wof:name":"Segers S",
    "wof:placetype":"venue"
},
  "geometry": {"coordinates":[4.5034208298,51.2434844971],"type":"Point"}
}