{
  "type": "Feature",
  "properties": {
    "addr:full":"Kapellestraat 25 Meulebeke West-Vlaanderen 8760",
    "addr:housenumber":"25",
    "addr:postcode":"8760",
    "addr:street":"Kapellestraat",
    "iso:country":"BE",
    "sg:address":"Kapellestraat 25",
    "sg:city":"Meulebeke",
    "sg:classifiers":[
        {
            "category":"Bakery",
            "type":"Food & Drink"
        }
    ],
    "sg:phone":"+32 51 48 41 61",
    "sg:postcode":"8760",
    "sg:province":"West-Vlaanderen",
    "sg:tags":[
        "confectioner",
        "baker"
    ],
    "wof:name":"Maesekes (huis)",
    "wof:placetype":"venue"
},
  "geometry": {"coordinates":[3.2874701023,50.9476966858],"type":"Point"}
}