{
  "type": "Feature",
  "properties": {
    "addr:full":"Place Brouez 2 Quaregnon Hainaut 7390",
    "addr:housenumber":"2",
    "addr:postcode":"7390",
    "addr:street":"Place Brouez",
    "iso:country":"BE",
    "sg:address":"Place Brouez 2",
    "sg:city":"Quaregnon",
    "sg:orig_category":"Pain, p\u00e2tisseries and confiseries",
    "sg:phone":"+32 65 79 29 24",
    "sg:postcode":"7390",
    "sg:province":"Hainaut",
    "wof:name":"Boulangerie Godefroid",
    "wof:placetype":"venue"
},
  "geometry": {"coordinates":[3.8493769169,50.4443855286],"type":"Point"}
}