{
  "type": "Feature",
  "properties": {
    "iso:country":"BE",
    "sg:address":"Eikestraat 102",
    "sg:city":"Mechelen",
    "sg:classifiers":[
        {
            "category":"Utilities",
            "subcategory":"Mobile Phone",
            "type":"Services"
        }
    ],
    "sg:phone":"+32 15 20 23 02",
    "sg:postcode":"2800",
    "sg:province":"Antwerpen",
    "sg:tags":[
        "access",
        "gsm",
        "-",
        "apparatus"
    ],
    "wof:name":"Rickvan",
    "wof:placetype":"venue"
},
  "geometry": {"coordinates":[4.4703421593,51.0436058044],"type":"Point"}
}