{
  "type": "Feature",
  "properties": {
    "addr:full":"Sint-michielsstraat 25 Brussel/bruxelles Bruxelles-Capitale 1000",
    "addr:housenumber":"25",
    "addr:postcode":"1000",
    "addr:street":"Sint-Michielsstraat;/",
    "iso:country":"BE",
    "sg:address":"Sint-michielsstraat 25",
    "sg:city":"Brussel/bruxelles",
    "sg:orig_category":"Kapsalons",
    "sg:phone":"+32 2 219 02 69",
    "sg:postcode":"1000",
    "sg:province":"Bruxelles-Capitale",
    "wof:name":"Coiffure Lisi",
    "wof:placetype":"venue"
},
  "geometry": {"coordinates":[4.3549628258,50.8520812988],"type":"Point"}
}