{
  "type": "Feature",
  "properties": {
    "addr:full":"Kapellelei 14 Mortsel Antwerpen 2640",
    "addr:housenumber":"14",
    "addr:postcode":"2640",
    "addr:street":"Kapellelei",
    "iso:country":"BE",
    "sg:address":"Kapellelei 14",
    "sg:city":"Mortsel",
    "sg:orig_category":"Editeurs de journaux. Editeurs de revues and p\u00e9riodiques",
    "sg:phone":"+32 3 440 56 13",
    "sg:postcode":"2640",
    "sg:province":"Antwerpen",
    "wof:name":"Uitgeverij De Landbode",
    "wof:placetype":"venue"
},
  "geometry": {"coordinates":[4.4516649246,51.1805343628],"type":"Point"}
}