{
  "type": "Feature",
  "properties": {
    "addr:full":"Phoenixstraat 33 Gent Oost-Vlaanderen 9000",
    "addr:housenumber":"33",
    "addr:postcode":"9000",
    "addr:street":"Phoenixstraat;Oost-Vlaanderen",
    "iso:country":"BE",
    "sg:address":"Phoenixstraat 33",
    "sg:city":"Gent",
    "sg:orig_category":"Electrom\u00e9nager, t\u00e9l\u00e9visions and radios",
    "sg:phone":"+32 9 237 02 98",
    "sg:postcode":"9000",
    "sg:province":"Oost-Vlaanderen",
    "wof:name":"Phoenix Elektro",
    "wof:placetype":"venue"
},
  "geometry": {"coordinates":[3.7063660622,51.0577926636],"type":"Point"}
}