{
  "type": "Feature",
  "properties": {
    "addr:full":"Rue C\u00e9sar De Paepe 43-2 Soumagne Li\u00e8ge 4630",
    "addr:housenumber":"43-2",
    "addr:postcode":"4630",
    "addr:street":"Rue Ce\u0301Sar De Paepe",
    "iso:country":"BE",
    "sg:address":"Rue C\u00e9sar De Paepe 43-2",
    "sg:city":"Soumagne",
    "sg:classifiers":[
        {
            "category":"Utilities",
            "subcategory":"Natural Gas",
            "type":"Services"
        }
    ],
    "sg:phone":"+32 4 377 67 16",
    "sg:postcode":"4630",
    "sg:province":"Li\u00e8ge",
    "sg:tags":[
        "welding"
    ],
    "wof:name":"Loly R",
    "wof:placetype":"venue"
},
  "geometry": {"coordinates":[5.7345018387,50.6327400208],"type":"Point"}
}