{
  "type": "Feature",
  "properties": {
    "addr:full":"Rue D'havr\u00c9 125 Mons Hainaut 7000",
    "addr:housenumber":"125",
    "addr:postcode":"7000",
    "addr:street":"Rue D'Havre \u0301;Hainaut",
    "iso:country":"BE",
    "sg:address":"Rue D'havr\u00c9 125",
    "sg:city":"Mons",
    "sg:orig_category":"Traitements param\u00e9dicaux",
    "sg:phone":"+32 65 84 16 09",
    "sg:postcode":"7000",
    "sg:province":"Hainaut",
    "wof:name":"Marie Pierre Selvais",
    "wof:placetype":"venue"
},
  "geometry": {"coordinates":[3.9579820633,50.4540481567],"type":"Point"}
}