{
  "type": "Feature",
  "properties": {
    "iso:country":"BE",
    "sg:address":"Rue De Mulhouse 33b",
    "sg:city":"Li\u00e8ge",
    "sg:classifiers":[
        {
            "category":"Retail",
            "subcategory":"Veterinary Services",
            "type":"Services"
        }
    ],
    "sg:phone":"+32 4 342 31 40",
    "sg:postcode":"4020",
    "sg:province":"Li\u00e8ge",
    "sg:tags":[
        "pharmacy"
    ],
    "wof:name":"Association Pharmaceutique De La Province De Li\u00e8ge",
    "wof:placetype":"venue"
},
  "geometry": {"coordinates":[5.5851039886,50.6325035095],"type":"Point"}
}