{
  "type": "Feature",
  "properties": {
    "iso:country":"BE",
    "sg:address":"Rue Du Couvent 16",
    "sg:city":"Colfontaine",
    "sg:orig_category":"Enseignement maternel and primaire",
    "sg:phone":"+32 65 67 32 17",
    "sg:postcode":"7340",
    "sg:province":"Hainaut",
    "wof:name":"Ecole Fondamentale Libre",
    "wof:placetype":"venue"
},
  "geometry": {"coordinates":[3.8526420593,50.404045105],"type":"Point"}
}