{
  "type": "Feature",
  "properties": {
    "addr:full":"Bel 173 Geel Antwerpen 2440",
    "addr:housenumber":"173",
    "addr:postcode":"2440",
    "addr:street":"Bel",
    "iso:country":"BE",
    "sg:address":"Bel 173",
    "sg:city":"Geel",
    "sg:classifiers":[
        {
            "category":"Health Services",
            "subcategory":"Health Practitioner",
            "type":"Services"
        }
    ],
    "sg:phone":"+32 14 58 28 72",
    "sg:postcode":"2440",
    "sg:province":"Antwerpen",
    "sg:tags":[
        "physiotherapist"
    ],
    "wof:name":"Van Geet Marc",
    "wof:placetype":"venue"
},
  "geometry": {"coordinates":[5.0489997864,51.1636505127],"type":"Point"}
}