{
  "type": "Feature",
  "properties": {
    "iso:country":"BE",
    "sg:address":"Einde 21",
    "sg:city":"Lommel",
    "sg:orig_category":"Catering and organisatie van feesten",
    "sg:phone":"+32 11 54 00 01",
    "sg:postcode":"3920",
    "sg:province":"Limburg",
    "wof:name":"Mille Fiori",
    "wof:placetype":"venue"
},
  "geometry": {"coordinates":[5.3168082237,51.2251091003],"type":"Point"}
}