{
  "type": "Feature",
  "properties": {
    "addr:full":"Alfons Pieterslaan 21 Oostende West-Vlaanderen 8400",
    "addr:housenumber":"21",
    "addr:postcode":"8400",
    "addr:street":"Alfons Pieterslaan",
    "iso:country":"BE",
    "sg:address":"Alfons Pieterslaan 21",
    "sg:city":"Oostende",
    "sg:orig_category":"Enseignement secondaire technique and professionnel",
    "sg:phone":"+32 59 80 24 23",
    "sg:postcode":"8400",
    "sg:province":"West-Vlaanderen",
    "wof:name":"St.jozefsinstituut",
    "wof:placetype":"venue"
},
  "geometry": {"coordinates":[2.9145920277,51.2263641357],"type":"Point"}
}