{
  "type": "Feature",
  "properties": {
    "iso:country":"BE",
    "sg:address":"Rue De La Villa Romaine 7",
    "sg:city":"Houffalize (nadrin)",
    "sg:classifiers":[
        {
            "category":"Insurance",
            "subcategory":"Insurance Agent",
            "type":"Services"
        }
    ],
    "sg:phone":"+32 84 44 00 00",
    "sg:postcode":"6660",
    "sg:province":"Luxembourg",
    "sg:tags":[
        "broker"
    ],
    "wof:name":"Bastin Bureau D'assurances",
    "wof:placetype":"venue"
},
  "geometry": {"coordinates":[5.6815347672,50.1598396301],"type":"Point"}
}