{
  "type": "Feature",
  "properties": {
    "addr:full":"Postbus 44 Tremelo49 Vlaams-Brabant 3120",
    "addr:housenumber":"44",
    "addr:postcode":"3120",
    "addr:street":"Postbus;Vlaams-Brabant",
    "iso:country":"BE",
    "sg:address":"Postbus 44",
    "sg:city":"Tremelo49",
    "sg:classifiers":[
        {
            "category":"Social Services",
            "type":"Services"
        }
    ],
    "sg:phone":"+32 16 53 77 30",
    "sg:postcode":"3120",
    "sg:province":"Vlaams-Brabant",
    "wof:name":"Sca Vlavesca-bel",
    "wof:placetype":"venue"
},
  "geometry": {"coordinates":[4.704969883,50.9902687073],"type":"Point"}
}