{
  "type": "Feature",
  "properties": {
    "addr:full":"Rue Basse 2 Frasnes-lez-anvaing Hainaut 7911",
    "addr:housenumber":"2",
    "addr:postcode":"7911",
    "addr:street":"Rue Basse",
    "iso:country":"BE",
    "sg:address":"Rue Basse 2",
    "sg:city":"Frasnes-lez-anvaing",
    "sg:classifiers":[
        {
            "category":"Cafe",
            "type":"Food & Drink"
        }
    ],
    "sg:phone":"+32 69 86 68 67",
    "sg:postcode":"7911",
    "sg:province":"Hainaut",
    "sg:tags":[
        "caf\u00e9s"
    ],
    "wof:name":"Willy Carlier",
    "wof:placetype":"venue"
},
  "geometry": {"coordinates":[3.6207659245,50.6681022644],"type":"Point"}
}