{
  "type": "Feature",
  "properties": {
    "iso:country":"BE",
    "sg:address":"Jan Baptist Devlemincklaan 92",
    "sg:city":"Zaventem",
    "sg:classifiers":[
        {
            "category":"Banks & Credit Unions",
            "subcategory":"Investment Brokerage",
            "type":"Services"
        }
    ],
    "sg:phone":"+32 475 34 65 99",
    "sg:postcode":"1930",
    "sg:province":"Vlaams-Brabant",
    "sg:tags":[
        "repair",
        "-",
        "installation",
        "sanitary",
        "article"
    ],
    "wof:name":"Lazaro De La Iglesia P",
    "wof:placetype":"venue"
},
  "geometry": {"coordinates":[4.4748620987,50.8751373291],"type":"Point"}
}