{
  "type": "Feature",
  "properties": {
    "iso:country":"BE",
    "sg:address":"Breughelpark 6",
    "sg:city":"Asse (zellik)",
    "sg:classifiers":[
        {
            "category":"Professional",
            "subcategory":"Testing Lab",
            "type":"Services"
        }
    ],
    "sg:phone":"+32 2 466 61 32",
    "sg:postcode":"1731",
    "sg:province":"Vlaams-Brabant",
    "sg:tags":[
        "chemist"
    ],
    "wof:name":"Breughelpark",
    "wof:placetype":"venue"
},
  "geometry": {"coordinates":[4.2718949318,50.8832626343],"type":"Point"}
}