{
  "type": "Feature",
  "properties": {
    "iso:country":"BE",
    "sg:address":"Lokerseweg 43",
    "sg:city":"Poperinge (reningelst)",
    "sg:classifiers":[
        {
            "category":"Building & Trades",
            "subcategory":"Landscaping Services",
            "type":"Services"
        }
    ],
    "sg:phone":"+32 57 33 67 71",
    "sg:postcode":"8970",
    "sg:province":"West-Vlaanderen",
    "sg:tags":[
        "gardening",
        "garden",
        "maintenance"
    ],
    "wof:name":"Meersseman Johan",
    "wof:placetype":"venue"
},
  "geometry": {"coordinates":[2.771089077,50.7998580933],"type":"Point"}
}