{
  "type": "Feature",
  "properties": {
    "iso:country":"BE",
    "sg:address":"Albert I-promenade 53",
    "sg:city":"Oostende",
    "sg:classifiers":[
        {
            "category":"Building & Trades",
            "subcategory":"Cleaning & Sanitation",
            "type":"Services"
        }
    ],
    "sg:phone":"+32 59 80 38 95",
    "sg:postcode":"8400",
    "sg:province":"West-Vlaanderen",
    "sg:tags":[
        "-",
        "rug",
        "carpet"
    ],
    "wof:name":"Clement R J",
    "wof:placetype":"venue"
},
  "geometry": {"coordinates":[2.9130880833,51.2329216003],"type":"Point"}
}