{
  "type": "Feature",
  "properties": {
    "addr:full":"Place Jos\u00c9ph. Charlotte 4 Namur Namur 5100",
    "addr:housenumber":"4",
    "addr:postcode":"5100",
    "addr:street":"Place Jose\u0301Ph Charlotte",
    "iso:country":"BE",
    "sg:address":"Place Jos\u00c9ph. Charlotte 4",
    "sg:city":"Namur",
    "sg:classifiers":[
        {
            "category":"Fast Food",
            "type":"Food & Drink"
        }
    ],
    "sg:phone":"+32 81 30 26 40",
    "sg:postcode":"5100",
    "sg:province":"Namur",
    "sg:tags":[
        "\u00c0",
        "restaurants",
        "emporter",
        "restaurant"
    ],
    "wof:name":"Restaurant Le Souverain",
    "wof:placetype":"venue"
},
  "geometry": {"coordinates":[4.8713750839,50.4566345215],"type":"Point"}
}