{
  "type": "Feature",
  "properties": {
    "iso:country":"BE",
    "sg:address":"Sint-amandsstraat 165",
    "sg:city":"Grimbergen (strombeek-bever)",
    "sg:classifiers":[
        {
            "category":"Real Estate",
            "subcategory":"Architect",
            "type":"Services"
        }
    ],
    "sg:phone":"+32 2 267 80 35",
    "sg:postcode":"1853",
    "sg:province":"Vlaams-Brabant",
    "wof:name":"Debulpaep F",
    "wof:placetype":"venue"
},
  "geometry": {"coordinates":[4.3606109619,50.9044151306],"type":"Point"}
}