{
  "type": "Feature",
  "properties": {
    "addr:full":"Kouterbosstraat 38 Zele Oost-Vlaanderen 9240",
    "addr:housenumber":"38",
    "addr:postcode":"9240",
    "addr:street":"Kouterbosstraat",
    "iso:country":"BE",
    "sg:address":"Kouterbosstraat 38",
    "sg:city":"Zele",
    "sg:orig_category":"Beheer onroerend goed",
    "sg:phone":"+32 52 44 63 57",
    "sg:postcode":"9240",
    "sg:province":"Oost-Vlaanderen",
    "wof:name":"Marcel Certyn",
    "wof:placetype":"venue"
},
  "geometry": {"coordinates":[4.0183639526,51.0610847473],"type":"Point"}
}