{
  "type": "Feature",
  "properties": {
    "addr:full":"Rue Du Dossay 7 Wandre Li\u00e8ge 4020",
    "addr:housenumber":"7",
    "addr:postcode":"4020",
    "addr:street":"Rue Du Dossay",
    "iso:country":"BE",
    "sg:address":"Rue Du Dossay 7",
    "sg:city":"Wandre",
    "sg:classifiers":[
        {
            "category":"Building & Trades",
            "subcategory":"Construction",
            "type":"Services"
        }
    ],
    "sg:phone":"+32 4 370 95 95",
    "sg:postcode":"4020",
    "sg:province":"Li\u00e8ge",
    "sg:tags":[
        "work",
        "welding",
        "mechanical"
    ],
    "wof:name":"M\u00e9canique Mosane S.a.",
    "wof:placetype":"venue"
},
  "geometry": {"coordinates":[5.6446118355,50.6693725586],"type":"Point"}
}