{
  "type": "Feature",
  "properties": {
    "addr:full":"Herendaalstraat 21a Lubbeek Vlaams-Brabant 3210",
    "addr:housenumber":"21a",
    "addr:postcode":"3210",
    "addr:street":"Herendaalstraat",
    "iso:country":"BE",
    "sg:address":"Herendaalstraat 21a",
    "sg:city":"Lubbeek",
    "sg:classifiers":[
        {
            "category":"Building & Trades",
            "subcategory":"Cleaning & Sanitation",
            "type":"Services"
        }
    ],
    "sg:phone":"+32 16 26 26 66",
    "sg:postcode":"3210",
    "sg:province":"Vlaams-Brabant",
    "sg:tags":[
        "cleaner",
        "window"
    ],
    "wof:name":"Syl-venster",
    "wof:placetype":"venue"
},
  "geometry": {"coordinates":[4.8276658058,50.8765296936],"type":"Point"}
}