{
  "type": "Feature",
  "properties": {
    "iso:country":"BE",
    "sg:address":"Kraaiweg 7",
    "sg:city":"Eeklo",
    "sg:orig_category":"Afbraak- and draineerwerken",
    "sg:phone":"+32 475 29 36 86",
    "sg:postcode":"9900",
    "sg:province":"Oost-Vlaanderen",
    "wof:name":"Van Hecke Filip",
    "wof:placetype":"venue"
},
  "geometry": {"coordinates":[3.5723869801,51.1682052612],"type":"Point"}
}