{
  "type": "Feature",
  "properties": {
    "addr:full":"Dorpsstraat 12 Laarne Oost-Vlaanderen 9270",
    "addr:housenumber":"12",
    "addr:postcode":"9270",
    "addr:street":"Dorpsstraat",
    "iso:country":"BE",
    "sg:address":"Dorpsstraat 12",
    "sg:city":"Laarne",
    "sg:classifiers":[
        {
            "category":"Food & Beverages",
            "subcategory":"Groceries & Convenience Stores",
            "type":"Retail Goods"
        }
    ],
    "sg:phone":"+32 9 369 60 86",
    "sg:postcode":"9270",
    "sg:province":"Oost-Vlaanderen",
    "sg:tags":[
        "grocer"
    ],
    "wof:name":"Hoeveken ('t)",
    "wof:placetype":"venue"
},
  "geometry": {"coordinates":[3.8488891125,51.0295410156],"type":"Point"}
}