{
  "type": "Feature",
  "properties": {
    "iso:country":"BE",
    "sg:address":"Pandhoevestraat 14",
    "sg:city":"Tremelo",
    "sg:orig_category":"Landmeters",
    "sg:phone":"+32 16 53 51 72",
    "sg:postcode":"3128",
    "sg:province":"Vlaams-Brabant",
    "wof:name":"Benny Feyaerts",
    "wof:placetype":"venue"
},
  "geometry": {"coordinates":[4.7433958054,51.019405365],"type":"Point"}
}