{
  "type": "Feature",
  "properties": {
    "iso:country":"BE",
    "sg:address":"Sysen 5",
    "sg:city":"Zedelgem (loppem)",
    "sg:classifiers":[
        {
            "category":"Building & Trades",
            "subcategory":"Construction",
            "type":"Services"
        }
    ],
    "sg:phone":"+32 50 39 62 80",
    "sg:postcode":"8210",
    "sg:province":"West-Vlaanderen",
    "sg:tags":[
        "scaffolding"
    ],
    "wof:name":"Daphne Stellingbouw",
    "wof:placetype":"venue"
},
  "geometry": {"coordinates":[3.1458399296,51.1376457214],"type":"Point"}
}