{
  "type": "Feature",
  "properties": {
    "addr:full":"Batterijstraat 9 De Haan West-Vlaanderen 8420",
    "addr:housenumber":"9",
    "addr:postcode":"8420",
    "addr:street":"Batterijstraat",
    "iso:country":"BE",
    "sg:address":"Batterijstraat 9",
    "sg:city":"De Haan",
    "sg:orig_category":"Antiek",
    "sg:phone":"+32 59 23 41 39",
    "sg:postcode":"8420",
    "sg:province":"West-Vlaanderen",
    "wof:name":"Francois Pallen",
    "wof:placetype":"venue"
},
  "geometry": {"coordinates":[3.0062289238,51.2507743835],"type":"Point"}
}