{
  "type": "Feature",
  "properties": {
    "iso:country":"BE",
    "sg:address":"Molenstraat 26 Box 3",
    "sg:city":"Stekene (kemzeke)",
    "sg:classifiers":[
        {
            "category":"Manufacturing",
            "subcategory":"Aerospace",
            "type":"Manufacturing & Wholesale Goods"
        }
    ],
    "sg:phone":"+32 3 779 72 31",
    "sg:postcode":"9190",
    "sg:province":"Oost-Vlaanderen",
    "sg:tags":[
        "equipment",
        "airplane"
    ],
    "wof:name":"Eurospares",
    "wof:placetype":"venue"
},
  "geometry": {"coordinates":[4.0796661377,51.2060127258],"type":"Point"}
}