{
  "type": "Feature",
  "properties": {
    "addr:full":"Wijklaan 17 Maaseik Limburg 3680",
    "addr:housenumber":"17",
    "addr:postcode":"3680",
    "addr:street":"Wijklaan",
    "iso:country":"BE",
    "sg:address":"Wijklaan 17",
    "sg:city":"Maaseik",
    "sg:orig_category":"Woningbouw",
    "sg:phone":"+32 89 86 35 29",
    "sg:postcode":"3680",
    "sg:province":"Limburg",
    "wof:name":"Al Bouw",
    "wof:placetype":"venue"
},
  "geometry": {"coordinates":[5.791285038,51.0954208374],"type":"Point"}
}