{
  "type": "Feature",
  "properties": {
    "iso:country":"BE",
    "sg:address":"Source De La L\u00e8che 27",
    "sg:city":"Chaudfontaine (embourg)",
    "sg:classifiers":[
        {
            "category":"Building & Trades",
            "subcategory":"Construction",
            "type":"Services"
        }
    ],
    "sg:phone":"+32 4 365 09 90",
    "sg:postcode":"4053",
    "sg:province":"Li\u00e8ge",
    "sg:tags":[
        "insulation",
        "thermical",
        "work",
        "acoustical"
    ],
    "wof:name":"Tecnic Isol Sprl",
    "wof:placetype":"venue"
},
  "geometry": {"coordinates":[5.613286972,50.5871086121],"type":"Point"}
}