{
  "type": "Feature",
  "properties": {
    "addr:full":"Dorpshof 45 Heusden-zolder (zolder) Limburg 3550",
    "addr:housenumber":"45",
    "addr:postcode":"3550",
    "addr:street":"Dorpshof",
    "iso:country":"BE",
    "sg:address":"Dorpshof 45",
    "sg:city":"Heusden-zolder (zolder)",
    "sg:classifiers":[
        {
            "category":"Shopping",
            "subcategory":"Optician",
            "type":"Retail Goods"
        }
    ],
    "sg:phone":"+32 11 53 83 63",
    "sg:postcode":"3550",
    "sg:province":"Limburg",
    "sg:tags":[
        "-"
    ],
    "wof:name":"C E Optics Bvba",
    "wof:placetype":"venue"
},
  "geometry": {"coordinates":[5.3128771782,51.0171203613],"type":"Point"}
}