{
  "type": "Feature",
  "properties": {
    "addr:full":"Oude Houtlei 10 Gent Oost-Vlaanderen 9000",
    "addr:housenumber":"10",
    "addr:postcode":"9000",
    "addr:street":"Oude Houtlei;Oost-Vlaanderen",
    "iso:country":"BE",
    "sg:address":"Oude Houtlei 10",
    "sg:city":"Gent",
    "sg:orig_category":"Activit\u00e9s d\u00b4action sociale sans h\u00e9bergement. Activit\u00e9s d\u00b4action sociale sans h\u00e9bergement",
    "sg:phone":"+32 479 90 71 54",
    "sg:postcode":"9000",
    "sg:province":"Oost-Vlaanderen",
    "wof:name":"Centrum Voor Psychoanalyse & Gezinstherapie",
    "wof:placetype":"venue"
},
  "geometry": {"coordinates":[3.7164149284,51.0541114807],"type":"Point"}
}