{
  "type": "Feature",
  "properties": {
    "addr:full":"Boomsesteenweg 124 Willebroek Antwerpen 2830",
    "addr:housenumber":"124",
    "addr:postcode":"2830",
    "addr:street":"Boomsesteenweg",
    "iso:country":"BE",
    "sg:address":"Boomsesteenweg 124",
    "sg:city":"Willebroek",
    "sg:classifiers":[
        {
            "category":"Communications",
            "subcategory":"Film & Video Production",
            "type":"Services"
        }
    ],
    "sg:phone":"+32 3 886 79 20",
    "sg:postcode":"2830",
    "sg:province":"Antwerpen",
    "sg:tags":[
        "realisation",
        "-"
    ],
    "wof:name":"Serras Luc",
    "wof:placetype":"venue"
},
  "geometry": {"coordinates":[4.3610439301,51.072052002],"type":"Point"}
}