{
  "type": "Feature",
  "properties": {
    "iso:country":"BE",
    "sg:address":"Zonnestraat 2",
    "sg:city":"Anzegem",
    "sg:orig_category":"Traitements param\u00e9dicaux",
    "sg:phone":"+32 56 68 80 10",
    "sg:postcode":"8573",
    "sg:province":"West-Vlaanderen",
    "wof:name":"A. Carette",
    "wof:placetype":"venue"
},
  "geometry": {"coordinates":[3.4529650211,50.8064956665],"type":"Point"}
}