{
  "type": "Feature",
  "properties": {
    "addr:full":"Sint-sebastiaansstraat 11 Brugge West-Vlaanderen 8200",
    "addr:housenumber":"11",
    "addr:postcode":"8200",
    "addr:street":"Sint-Sebastiaansstraat",
    "iso:country":"BE",
    "sg:address":"Sint-sebastiaansstraat 11",
    "sg:city":"Brugge",
    "sg:classifiers":[
        {
            "category":"Personal",
            "subcategory":"Beauty Salon",
            "type":"Services"
        }
    ],
    "sg:phone":"+32 50 38 68 29",
    "sg:postcode":"8200",
    "sg:province":"West-Vlaanderen",
    "sg:tags":[
        "de",
        "coiffure"
    ],
    "wof:name":"Coiffure Martine",
    "wof:placetype":"venue"
},
  "geometry": {"coordinates":[3.2029290199,51.2002067566],"type":"Point"}
}