{
  "type": "Feature",
  "properties": {
    "addr:full":"Broekomstraat 9b Borgloon Limburg 3840",
    "addr:housenumber":"9b",
    "addr:postcode":"3840",
    "addr:street":"Broekomstraat",
    "iso:country":"BE",
    "sg:address":"Broekomstraat 9b",
    "sg:city":"Borgloon",
    "sg:orig_category":"Fleurs and plantes",
    "sg:phone":"+32 12 74 38 57",
    "sg:postcode":"3840",
    "sg:province":"Limburg",
    "wof:name":"Bonsa\u00cf Cultuur",
    "wof:placetype":"venue"
},
  "geometry": {"coordinates":[5.3441700935,50.8012466431],"type":"Point"}
}