{
  "type": "Feature",
  "properties": {
    "iso:country":"BE",
    "sg:address":"Rue De La Hurtrie 36",
    "sg:city":"P\u00e9ruwelz",
    "sg:classifiers":[
        {
            "category":"Building & Trades",
            "subcategory":"Cleaning & Sanitation",
            "type":"Services"
        }
    ],
    "sg:phone":"+32 69 77 16 25",
    "sg:postcode":"7600",
    "sg:province":"Hainaut",
    "sg:tags":[
        "room",
        "clean"
    ],
    "wof:name":"Micronclean Belgium",
    "wof:placetype":"venue"
},
  "geometry": {"coordinates":[3.6120419502,50.5126838684],"type":"Point"}
}