{
  "type": "Feature",
  "properties": {
    "iso:country":"BE",
    "sg:address":"Briahan 12",
    "sg:city":"Bouillon",
    "sg:orig_category":"Schoonheidssalons",
    "sg:phone":"+32 61 46 69 60",
    "sg:postcode":"6832",
    "sg:province":"Luxembourg",
    "wof:name":"Olivia Deweirdt",
    "wof:placetype":"venue"
},
  "geometry": {"coordinates":[5.0727958679,49.8251419067],"type":"Point"}
}