{
  "type": "Feature",
  "properties": {
    "addr:full":"Singelstraat 42 Borgloon (bommershoven) Limburg 3840",
    "addr:housenumber":"42",
    "addr:postcode":"3840",
    "addr:street":"Singelstraat",
    "iso:country":"BE",
    "sg:address":"Singelstraat 42",
    "sg:city":"Borgloon (bommershoven)",
    "sg:classifiers":[
        {
            "category":"Real Estate",
            "subcategory":"Architect",
            "type":"Services"
        }
    ],
    "sg:phone":"+32 12 74 27 79",
    "sg:postcode":"3840",
    "sg:province":"Limburg",
    "wof:name":"Posen J",
    "wof:placetype":"venue"
},
  "geometry": {"coordinates":[5.3441700935,50.8012466431],"type":"Point"}
}