{
  "type": "Feature",
  "properties": {
    "iso:country":"BE",
    "sg:address":"Ferdinand Uylenbroeckstraat 11",
    "sg:city":"Sint-pieters-leeuw",
    "sg:classifiers":[
        {
            "category":"Home & Garden",
            "subcategory":"Carpets & Floor Coverings",
            "type":"Retail Goods"
        }
    ],
    "sg:phone":"+32 2 361 05 92",
    "sg:postcode":"1600",
    "sg:province":"Vlaams-Brabant",
    "sg:tags":[
        "tile"
    ],
    "wof:name":"Probelmat Nv",
    "wof:placetype":"venue"
},
  "geometry": {"coordinates":[4.2522969246,50.7636222839],"type":"Point"}
}