{
  "type": "Feature",
  "properties": {
    "addr:full":"Mispellaan 24 Beveren (melsele) Oost-Vlaanderen 9120",
    "addr:housenumber":"24",
    "addr:postcode":"9120",
    "addr:street":"Mispellaan",
    "iso:country":"BE",
    "sg:address":"Mispellaan 24",
    "sg:city":"Beveren (melsele)",
    "sg:classifiers":[
        {
            "category":"Home & Garden",
            "subcategory":"Building Materials",
            "type":"Retail Goods"
        }
    ],
    "sg:phone":"+32 3 775 37 13",
    "sg:postcode":"9120",
    "sg:province":"Oost-Vlaanderen",
    "sg:tags":[
        "house"
    ],
    "wof:name":"Maes Bouwonderneming Bvba",
    "wof:placetype":"venue"
},
  "geometry": {"coordinates":[4.2853999138,51.2160110474],"type":"Point"}
}