{
  "type": "Feature",
  "properties": {
    "iso:country":"BE",
    "sg:address":"Chauss\u00c9e De Bruxelles 400",
    "sg:city":"Waterloo",
    "sg:orig_category":"Instruments de musique",
    "sg:phone":"+32 2 354 68 19",
    "sg:postcode":"1410",
    "sg:province":"Brabant Wallon",
    "wof:name":"Opus 400",
    "wof:placetype":"venue"
},
  "geometry": {"coordinates":[4.4009709358,50.709400177],"type":"Point"}
}