{
  "type": "Feature",
  "properties": {
    "addr:full":"Rue Du Village 13 Beauvechain Brabant Wallon 1320",
    "addr:housenumber":"13",
    "addr:postcode":"1320",
    "addr:street":"Rue Du Village",
    "iso:country":"BE",
    "sg:address":"Rue Du Village 13",
    "sg:city":"Beauvechain",
    "sg:orig_category":"Herstelling leer and schoeisel",
    "sg:phone":"+32 10 86 70 10",
    "sg:postcode":"1320",
    "sg:province":"Brabant Wallon",
    "wof:name":"Jean-pierre Libouton",
    "wof:placetype":"venue"
},
  "geometry": {"coordinates":[4.7756400108,50.783203125],"type":"Point"}
}