{
  "type": "Feature",
  "properties": {
    "addr:full":"Sint-lambertusstraat 9 Leuven (heverlee) Vlaams-Brabant 3001",
    "addr:housenumber":"9",
    "addr:postcode":"3001",
    "addr:street":"Sint-Lambertusstraat",
    "iso:country":"BE",
    "sg:address":"Sint-lambertusstraat 9",
    "sg:city":"Leuven (heverlee)",
    "sg:classifiers":[
        {
            "category":"Professional",
            "subcategory":"Lawyer & Legal Services",
            "type":"Services"
        }
    ],
    "sg:phone":"+32 16 23 37 68",
    "sg:postcode":"3001",
    "sg:province":"Vlaams-Brabant",
    "wof:name":"Delcon Imelda",
    "wof:placetype":"venue"
},
  "geometry": {"coordinates":[4.6943340302,50.8627243042],"type":"Point"}
}