{
  "type": "Feature",
  "properties": {
    "addr:full":"Croix De Poupehan 23 Bouillon (corbion) Luxembourg 6838",
    "addr:housenumber":"23",
    "addr:postcode":"6838",
    "iso:country":"BE",
    "sg:address":"Croix De Poupehan 23",
    "sg:city":"Bouillon (corbion)",
    "sg:classifiers":[
        {
            "category":"Food & Beverages",
            "subcategory":"Liquor & Beverages",
            "type":"Retail Goods"
        }
    ],
    "sg:phone":"+32 61 46 87 52",
    "sg:postcode":"6838",
    "sg:province":"Luxembourg",
    "sg:tags":[
        "-",
        "spirit",
        "wine"
    ],
    "wof:name":"Renard B",
    "wof:placetype":"venue"
},
  "geometry": {"coordinates":[5.0071702003,49.7973403931],"type":"Point"}
}