{
  "type": "Feature",
  "properties": {
    "iso:country":"BE",
    "sg:address":"Boulevard D\u00b4avroy 258",
    "sg:city":"Liege-meuse Nord",
    "sg:orig_category":"Bloemen and planten Fleurop Interflora",
    "sg:phone":"+32 4 252 45 32",
    "sg:postcode":"4000",
    "sg:province":"Li\u00e8ge",
    "wof:name":"Thonnart",
    "wof:placetype":"venue"
},
  "geometry": {"coordinates":[5.5675740242,50.6312408447],"type":"Point"}
}