{
  "type": "Feature",
  "properties": {
    "addr:full":"Tolpoortstrat 31 Deinze Oost-Vlaanderen 9800",
    "addr:housenumber":"31",
    "addr:postcode":"9800",
    "addr:street":"Tolpoortstrat",
    "iso:country":"BE",
    "sg:address":"Tolpoortstrat 31",
    "sg:city":"Deinze",
    "sg:orig_category":"Fleurs and plantes",
    "sg:phone":"+32 9 386 76 08",
    "sg:postcode":"9800",
    "sg:province":"Oost-Vlaanderen",
    "wof:name":"Bloem En Groen",
    "wof:placetype":"venue"
},
  "geometry": {"coordinates":[3.529088974,50.9815444946],"type":"Point"}
}