{
  "type": "Feature",
  "properties": {
    "addr:full":"Bergeneindestraat 17 Geetbets (rummen) Vlaams-Brabant 3454",
    "addr:housenumber":"17",
    "addr:postcode":"3454",
    "addr:street":"Bergeneindestraat",
    "iso:country":"BE",
    "sg:address":"Bergeneindestraat 17",
    "sg:city":"Geetbets (rummen)",
    "sg:classifiers":[
        {
            "category":"Personal",
            "subcategory":"Beauty Salon",
            "type":"Services"
        }
    ],
    "sg:phone":"+32 11 58 96 77",
    "sg:postcode":"3454",
    "sg:province":"Vlaams-Brabant",
    "sg:tags":[
        "lady",
        "-",
        "hairdressing"
    ],
    "wof:name":"Vanessa Kapsalon",
    "wof:placetype":"venue"
},
  "geometry": {"coordinates":[5.1776018143,50.9016914368],"type":"Point"}
}