{
  "type": "Feature",
  "properties": {
    "addr:full":"Leuvense Steenweg 129 Sint-joost-ten-node/saint-josse-ten-noode Bruxelles-Capitale 1210",
    "addr:housenumber":"129",
    "addr:postcode":"1210",
    "addr:street":"Leuvense Steenweg",
    "iso:country":"BE",
    "sg:address":"Leuvense Steenweg 129",
    "sg:city":"Sint-joost-ten-node/saint-josse-ten-noode",
    "sg:orig_category":"Bagage and lederwaren",
    "sg:phone":"+32 2 217 96 17",
    "sg:postcode":"1210",
    "sg:province":"Bruxelles-Capitale",
    "wof:name":"Fe. Wauters",
    "wof:placetype":"venue"
},
  "geometry": {"coordinates":[4.3770260811,50.8499908447],"type":"Point"}
}