{
  "type": "Feature",
  "properties": {
    "iso:country":"BE",
    "sg:address":"Rue Prav\u00e9e 12a",
    "sg:city":"H\u00e9ron (couthuin)",
    "sg:classifiers":[
        {
            "category":"Health Services",
            "subcategory":"Doctor",
            "type":"Services"
        }
    ],
    "sg:phone":"+32 85 71 10 51",
    "sg:postcode":"4218",
    "sg:province":"Li\u00e8ge",
    "sg:tags":[
        "medicinephysicians",
        "surgeon"
    ],
    "wof:name":"Everard R",
    "wof:placetype":"venue"
},
  "geometry": {"coordinates":[5.1327080727,50.5271453857],"type":"Point"}
}