{
  "type": "Feature",
  "properties": {
    "iso:country":"BE",
    "sg:address":"Markt 3b",
    "sg:city":"Dessel",
    "sg:classifiers":[
        {
            "category":"Autos & Motor Vehicles",
            "subcategory":"Boat Sales",
            "type":"Retail Goods"
        }
    ],
    "sg:phone":"+32 14 37 94 50",
    "sg:postcode":"2480",
    "sg:province":"Antwerpen",
    "sg:tags":[
        "automobile",
        "racing",
        "accessory"
    ],
    "wof:name":"Glosso Racing Team",
    "wof:placetype":"venue"
},
  "geometry": {"coordinates":[5.1161680222,51.237159729],"type":"Point"}
}