{
  "type": "Feature",
  "properties": {
    "addr:full":"Mechelsesteenweg 305 Kontich Antwerpen 2550",
    "addr:housenumber":"305",
    "addr:postcode":"2550",
    "addr:street":"Mechelsesteenweg",
    "iso:country":"BE",
    "sg:address":"Mechelsesteenweg 305",
    "sg:city":"Kontich",
    "sg:classifiers":[
        {
            "category":"Home & Garden",
            "subcategory":"Garden Supply",
            "type":"Retail Goods"
        }
    ],
    "sg:phone":"+32 3 457 69 58",
    "sg:postcode":"2550",
    "sg:province":"Antwerpen",
    "sg:tags":[
        "equipment",
        "playground"
    ],
    "wof:name":"Van Den Eynde Bvba",
    "wof:placetype":"venue"
},
  "geometry": {"coordinates":[4.4501571655,51.1216621399],"type":"Point"}
}