{
  "type": "Feature",
  "properties": {
    "iso:country":"BE",
    "sg:address":"Handelsstraat 42",
    "sg:city":"Mol",
    "sg:orig_category":"Bloemen and planten",
    "sg:phone":"+32 14 81 06 69",
    "sg:postcode":"2400",
    "sg:province":"Antwerpen",
    "wof:name":"Kristof Mallants",
    "wof:placetype":"venue"
},
  "geometry": {"coordinates":[5.2108578682,51.1895523071],"type":"Point"}
}