{
  "type": "Feature",
  "properties": {
    "iso:country":"BE",
    "sg:address":"Berkenlaan 53",
    "sg:city":"Londerzeel",
    "sg:classifiers":[
        {
            "category":"Wholesale",
            "subcategory":"Medical Equipment & Supplies",
            "type":"Manufacturing & Wholesale Goods"
        }
    ],
    "sg:phone":"+32 52 30 59 56",
    "sg:postcode":"1840",
    "sg:province":"Vlaams-Brabant",
    "sg:tags":[
        "instrument",
        "apparatus"
    ],
    "wof:name":"Duo Med Nv",
    "wof:placetype":"venue"
},
  "geometry": {"coordinates":[4.3079919815,51.0014152527],"type":"Point"}
}