{
  "type": "Feature",
  "properties": {
    "addr:full":"Tintorettostraat 12 Brussel/bruxelles Bruxelles-Capitale 1000",
    "addr:housenumber":"12",
    "addr:postcode":"1000",
    "addr:street":"Tintorettostraat;/",
    "iso:country":"BE",
    "sg:address":"Tintorettostraat 12",
    "sg:city":"Brussel/bruxelles",
    "sg:orig_category":"Plaatsen van vloer- and muurbekleding Schilders",
    "sg:phone":"+32 2 735 39 41",
    "sg:postcode":"1000",
    "sg:province":"Bruxelles-Capitale",
    "wof:name":"Michel Wolff",
    "wof:placetype":"venue"
},
  "geometry": {"coordinates":[4.3890600204,50.8456687927],"type":"Point"}
}