{
  "type": "Feature",
  "properties": {
    "addr:full":"Rue De Pont 26 Tournai Hainaut 7500",
    "addr:housenumber":"26",
    "addr:postcode":"7500",
    "addr:street":"Rue De Pont",
    "iso:country":"BE",
    "sg:address":"Rue De Pont 26",
    "sg:city":"Tournai",
    "sg:classifiers":[
        {
            "category":"Shopping",
            "subcategory":"Pets & Pet Supplies",
            "type":"Retail Goods"
        }
    ],
    "sg:phone":"+32 69 23 58 05",
    "sg:postcode":"7500",
    "sg:province":"Hainaut",
    "sg:tags":[
        "aquarium",
        "accessory"
    ],
    "wof:name":"Aniquarium",
    "wof:placetype":"venue"
},
  "geometry": {"coordinates":[3.3940610886,50.6074409485],"type":"Point"}
}