{
  "type": "Feature",
  "properties": {
    "addr:full":"Gemene-weideweg-zuid 121 Brugge West-Vlaanderen 8310",
    "addr:housenumber":"121",
    "addr:postcode":"8310",
    "iso:country":"BE",
    "sg:address":"Gemene-weideweg-zuid 121",
    "sg:city":"Brugge",
    "sg:orig_category":"Enseignement maternel and primaire",
    "sg:phone":"+32 50 35 18 48",
    "sg:postcode":"8310",
    "sg:province":"West-Vlaanderen",
    "wof:name":"B.s.g.o. Vossesterd",
    "wof:placetype":"venue"
},
  "geometry": {"coordinates":[3.2620799541,51.2172584534],"type":"Point"}
}