{
  "type": "Feature",
  "properties": {
    "iso:country":"BE",
    "sg:address":"Abeleplein 55",
    "sg:city":"Poperinge",
    "sg:orig_category":"Installation \u00e9lectrique r\u00e9sidentielle",
    "sg:phone":"+32 57 38 86 46",
    "sg:postcode":"8978",
    "sg:province":"West-Vlaanderen",
    "wof:name":"Patrick Hiele",
    "wof:placetype":"venue"
},
  "geometry": {"coordinates":[2.6206049919,50.8592453003],"type":"Point"}
}