{
  "type": "Feature",
  "properties": {
    "addr:full":"Lakstraat 75 Laakdal Antwerpen 2431",
    "addr:housenumber":"75",
    "addr:postcode":"2431",
    "addr:street":"Lakstraat",
    "iso:country":"BE",
    "sg:address":"Lakstraat 75",
    "sg:city":"Laakdal",
    "sg:classifiers":[
        {
            "category":"Cafe",
            "type":"Food & Drink"
        }
    ],
    "sg:phone":"+32 14 84 04 79",
    "sg:postcode":"2431",
    "sg:province":"Antwerpen",
    "sg:tags":[
        "caf\u00e9s"
    ],
    "wof:name":"Magdalena Geyskens",
    "wof:placetype":"venue"
},
  "geometry": {"coordinates":[4.9833650589,51.0551490784],"type":"Point"}
}