{
  "type": "Feature",
  "properties": {
    "addr:full":"Mechelseweg 193 Kapelle-op-den-bos Vlaams-Brabant 1880",
    "addr:housenumber":"193",
    "addr:postcode":"1880",
    "addr:street":"Mechelseweg",
    "iso:country":"BE",
    "sg:address":"Mechelseweg 193",
    "sg:city":"Kapelle-op-den-bos",
    "sg:orig_category":"Journaux. Tabac",
    "sg:phone":"+32 15 71 01 54",
    "sg:postcode":"1880",
    "sg:province":"Vlaams-Brabant",
    "wof:name":"Kerremans",
    "wof:placetype":"venue"
},
  "geometry": {"coordinates":[4.358080864,51.0129547119],"type":"Point"}
}