{
  "type": "Feature",
  "properties": {
    "iso:country":"BE",
    "sg:address":"Oudenaardestraat 110",
    "sg:city":"Anzegem (vichte)",
    "sg:classifiers":[
        {
            "category":"Travel",
            "subcategory":"Hotels & Motels",
            "type":"Entertainment"
        }
    ],
    "sg:phone":"+32 56 77 88 44",
    "sg:postcode":"8570",
    "sg:province":"West-Vlaanderen",
    "sg:tags":[
        "supply",
        "hotels",
        "catering"
    ],
    "wof:name":"A. Byttebier-michels Nv",
    "wof:placetype":"venue"
},
  "geometry": {"coordinates":[3.4164168835,50.840473175],"type":"Point"}
}