{
  "type": "Feature",
  "properties": {
    "addr:full":"Emile Banningstraat 59 Elsene/ixelles Bruxelles-Capitale 1050",
    "addr:housenumber":"59",
    "addr:postcode":"1050",
    "addr:street":"Emile Banningstraat",
    "iso:country":"BE",
    "sg:address":"Emile Banningstraat 59",
    "sg:city":"Elsene/ixelles",
    "sg:orig_category":"Advocaten and juridische adviseurs",
    "sg:phone":"+32 2 413 00 23",
    "sg:postcode":"1050",
    "sg:province":"Bruxelles-Capitale",
    "wof:name":"Val\u00c9rie Therasse",
    "wof:placetype":"venue"
},
  "geometry": {"coordinates":[4.3827719688,50.818977356],"type":"Point"}
}