{
  "type": "Feature",
  "properties": {
    "iso:country":"BE",
    "sg:address":"Molenstraat 97",
    "sg:city":"Destelbergen",
    "sg:classifiers":[
        {
            "category":"Personal",
            "type":"Services"
        }
    ],
    "sg:phone":"+32 9 355 96 36",
    "sg:postcode":"9070",
    "sg:province":"Oost-Vlaanderen",
    "sg:tags":[
        "party",
        "planning"
    ],
    "wof:name":"Molenhof ('t)",
    "wof:placetype":"venue"
},
  "geometry": {"coordinates":[3.8267600536,51.0664825439],"type":"Point"}
}