{
  "type": "Feature",
  "properties": {
    "iso:country":"BE",
    "sg:address":"Weiveldlaan 2",
    "sg:city":"Zaventem",
    "sg:classifiers":[
        {
            "category":"Manufacturing",
            "subcategory":"Aerospace",
            "type":"Manufacturing & Wholesale Goods"
        }
    ],
    "sg:phone":"+32 2 716 06 11",
    "sg:postcode":"1930",
    "sg:province":"Vlaams-Brabant",
    "sg:tags":[
        "equipment",
        "aeronautic",
        "transport",
        "vehicle"
    ],
    "wof:name":"Asco Industries Nv/sa",
    "wof:placetype":"venue"
},
  "geometry": {"coordinates":[4.487475872,50.8712158203],"type":"Point"}
}