{
  "type": "Feature",
  "properties": {
    "addr:full":"Rue Des Bleuets 72 Rixensart Brabant Wallon 1330",
    "addr:housenumber":"72",
    "addr:postcode":"1330",
    "addr:street":"Rue Des Bleuets;Wallon",
    "iso:country":"BE",
    "sg:address":"Rue Des Bleuets 72",
    "sg:city":"Rixensart",
    "sg:classifiers":[
        {
            "category":"Home & Garden",
            "subcategory":"Building Materials",
            "type":"Retail Goods"
        }
    ],
    "sg:phone":"+32 2 653 71 71",
    "sg:postcode":"1330",
    "sg:province":"Brabant Wallon",
    "sg:tags":[
        "house"
    ],
    "wof:name":"Denuit P",
    "wof:placetype":"venue"
},
  "geometry": {"coordinates":[4.541079998,50.7028160095],"type":"Point"}
}