{
  "type": "Feature",
  "properties": {
    "addr:full":"Voogdijstraat 31 Hasselt Limburg 3500",
    "addr:housenumber":"31",
    "addr:postcode":"3500",
    "addr:street":"Voogdijstraat",
    "iso:country":"BE",
    "sg:address":"Voogdijstraat 31",
    "sg:city":"Hasselt",
    "sg:classifiers":[
        {
            "category":"Shopping",
            "subcategory":"Discount & Variety Stores",
            "type":"Retail Goods"
        }
    ],
    "sg:phone":"+32 11 26 36 00",
    "sg:postcode":"3500",
    "sg:province":"Limburg",
    "sg:tags":[
        "warehouse",
        "-",
        "merchandise"
    ],
    "wof:name":"Tds Belgium Nv",
    "wof:placetype":"venue"
},
  "geometry": {"coordinates":[5.3460612297,50.906917572],"type":"Point"}
}