{
  "type": "Feature",
  "properties": {
    "addr:full":"Leestsesteenweg 151 Mechelen Antwerpen 2800",
    "addr:housenumber":"151",
    "addr:postcode":"2800",
    "addr:street":"Leestsesteenweg",
    "iso:country":"BE",
    "sg:address":"Leestsesteenweg 151",
    "sg:city":"Mechelen",
    "sg:orig_category":"Groententeelt",
    "sg:phone":"+32 15 21 15 58",
    "sg:postcode":"2800",
    "sg:province":"Antwerpen",
    "wof:name":"Jozef Jacobs",
    "wof:placetype":"venue"
},
  "geometry": {"coordinates":[4.4269428253,51.0366020203],"type":"Point"}
}