{
  "type": "Feature",
  "properties": {
    "iso:country":"BE",
    "sg:address":"Chauss\u00e9e De Wavre 55",
    "sg:city":"Perwez",
    "sg:classifiers":[
        {
            "category":"Communications",
            "subcategory":"Television Station",
            "type":"Services"
        }
    ],
    "sg:phone":"+32 81 65 65 76",
    "sg:postcode":"1360",
    "sg:province":"Brabant Wallon",
    "sg:tags":[
        "electricity",
        "cabling",
        "wiring",
        "-"
    ],
    "wof:name":"R.g.a. Concept - Mr Galvan",
    "wof:placetype":"venue"
},
  "geometry": {"coordinates":[4.8043971062,50.6275596619],"type":"Point"}
}