{
  "type": "Feature",
  "properties": {
    "iso:country":"BE",
    "sg:address":"Abdis Agnesstraat 1",
    "sg:city":"Kortrijk",
    "sg:orig_category":"Experts-comptables",
    "sg:phone":"+32 56 22 73 66",
    "sg:postcode":"8510",
    "sg:province":"West-Vlaanderen",
    "wof:name":"Rik Naessens",
    "wof:placetype":"venue"
},
  "geometry": {"coordinates":[3.2604389191,50.8049850464],"type":"Point"}
}