{
  "type": "Feature",
  "properties": {
    "addr:full":"Hugo Verriestlaan 75 Wevelgem West-Vlaanderen 8560",
    "addr:housenumber":"75",
    "addr:postcode":"8560",
    "addr:street":"Hugo Verriestlaan",
    "iso:country":"BE",
    "sg:address":"Hugo Verriestlaan 75",
    "sg:city":"Wevelgem",
    "sg:orig_category":"Diverse intermediaire producten Gh Herstelling horloges and juwelen Juwelen and edelstenen Fab Juwel",
    "sg:phone":"+32 56 41 26 44",
    "sg:postcode":"8560",
    "sg:province":"West-Vlaanderen",
    "wof:name":"Huis Foulon",
    "wof:placetype":"venue"
},
  "geometry": {"coordinates":[3.2034990788,50.8377151489],"type":"Point"}
}