{
  "type": "Feature",
  "properties": {
    "addr:full":"Hoekstraat 8 Meeuwen-gruitrode Limburg 3670",
    "addr:housenumber":"8",
    "addr:postcode":"3670",
    "addr:street":"Hoekstraat",
    "iso:country":"BE",
    "sg:address":"Hoekstraat 8",
    "sg:city":"Meeuwen-gruitrode",
    "sg:orig_category":"M\u00e9decins and sp\u00e9cialistes",
    "sg:phone":"+32 11 79 26 76",
    "sg:postcode":"3670",
    "sg:province":"Limburg",
    "wof:name":"J. Jaenen",
    "wof:placetype":"venue"
},
  "geometry": {"coordinates":[5.5187749863,51.0945396423],"type":"Point"}
}