{
  "type": "Feature",
  "properties": {
    "addr:full":"Huldekens 12 Schilde ('s Gravenwezel) Antwerpen 2970",
    "addr:housenumber":"12",
    "addr:postcode":"2970",
    "addr:street":"Huldekens;S",
    "iso:country":"BE",
    "sg:address":"Huldekens 12",
    "sg:city":"Schilde ('s Gravenwezel)",
    "sg:orig_category":"Non-Classified Establishments",
    "sg:phone":"+32 3 384 27 34",
    "sg:postcode":"2970",
    "sg:province":"Antwerpen",
    "wof:name":"Imalex Nv",
    "wof:placetype":"venue"
},
  "geometry": {"coordinates":[4.5715041161,51.2705154419],"type":"Point"}
}