{
  "type": "Feature",
  "properties": {
    "addr:full":"Miksebeekstraat 82 Brasschaat Antwerpen 2930",
    "addr:housenumber":"82",
    "addr:postcode":"2930",
    "addr:street":"Miksebeekstraat",
    "iso:country":"BE",
    "sg:address":"Miksebeekstraat 82",
    "sg:city":"Brasschaat",
    "sg:orig_category":"Installation \u00e9lectrique r\u00e9sidentielle",
    "sg:phone":"+32 3 651 76 74",
    "sg:postcode":"2930",
    "sg:province":"Antwerpen",
    "wof:name":"Electro J.d.b.",
    "wof:placetype":"venue"
},
  "geometry": {"coordinates":[4.5078730583,51.2956581116],"type":"Point"}
}