{
  "type": "Feature",
  "properties": {
    "iso:country":"BE",
    "sg:address":"Const. Neutjensstraat 56",
    "sg:city":"Schoten",
    "sg:orig_category":"Peinture. Rev\u00eatements pour sols and murs",
    "sg:phone":"+32 3 658 67 31",
    "sg:postcode":"2900",
    "sg:province":"Antwerpen",
    "wof:name":"Kets Rudi Schilderwerken",
    "wof:placetype":"venue"
},
  "geometry": {"coordinates":[4.4950361252,51.2520980835],"type":"Point"}
}