{
  "type": "Feature",
  "properties": {
    "iso:country":"BE",
    "sg:address":"Rue De La Gare 26",
    "sg:city":"Ronse/renaix",
    "sg:orig_category":"Fournitures de bureau",
    "sg:phone":"+32 55 21 34 48",
    "sg:postcode":"9600",
    "sg:province":"Oost-Vlaanderen",
    "wof:name":"Huis Derenoncourt",
    "wof:placetype":"venue"
},
  "geometry": {"coordinates":[3.6013200283,50.7434387207],"type":"Point"}
}