{
  "type": "Feature",
  "properties": {
    "addr:full":"Alsembergse Steenweg 130 Sint-gillis/saint-gilles Bruxelles-Capitale 1060",
    "addr:housenumber":"130",
    "addr:postcode":"1060",
    "addr:street":"Alsembergse Steenweg",
    "iso:country":"BE",
    "sg:address":"Alsembergse Steenweg 130",
    "sg:city":"Sint-gillis/saint-gilles",
    "sg:orig_category":"Diverse producten Fab Fotogravure and zetwerk Reclamebureaus",
    "sg:phone":"+32 2 537 05 26",
    "sg:postcode":"1060",
    "sg:province":"Bruxelles-Capitale",
    "wof:name":"Alphastyle",
    "wof:placetype":"venue"
},
  "geometry": {"coordinates":[4.3429479599,50.8227996826],"type":"Point"}
}