{
  "type": "Feature",
  "properties": {
    "addr:full":"Rue De La Buscaille 38 Pont-a-celles Hainaut 6230",
    "addr:housenumber":"38",
    "addr:postcode":"6230",
    "addr:street":"Rue De La Buscaille",
    "iso:country":"BE",
    "sg:address":"Rue De La Buscaille 38",
    "sg:city":"Pont-a-celles",
    "sg:classifiers":[
        {
            "category":"Arena",
            "subcategory":"Sports Club",
            "type":"Entertainment"
        }
    ],
    "sg:phone":"+32 71 84 73 47",
    "sg:postcode":"6230",
    "sg:province":"Hainaut",
    "sg:tags":[
        "de"
    ],
    "wof:name":"Club Cycliste Buzetois",
    "wof:placetype":"venue"
},
  "geometry": {"coordinates":[4.3705019951,50.5319862366],"type":"Point"}
}