{
  "type": "Feature",
  "properties": {
    "addr:full":"Bronstraat 17 Hoeselt (werm) Limburg 3730",
    "addr:housenumber":"17",
    "addr:postcode":"3730",
    "addr:street":"Bronstraat",
    "iso:country":"BE",
    "sg:address":"Bronstraat 17",
    "sg:city":"Hoeselt (werm)",
    "sg:classifiers":[
        {
            "category":"Freight",
            "type":"Transportation"
        }
    ],
    "sg:phone":"+32 12 23 89 50",
    "sg:postcode":"3730",
    "sg:province":"Limburg",
    "sg:tags":[
        "-",
        "transport"
    ],
    "wof:name":"Wagemans R",
    "wof:placetype":"venue"
},
  "geometry": {"coordinates":[5.4760098457,50.8319473267],"type":"Point"}
}