{
  "type": "Feature",
  "properties": {
    "iso:country":"BE",
    "sg:address":"Nieuwstraat 8",
    "sg:city":"Asse",
    "sg:classifiers":[
        {
            "category":"Manufacturing",
            "subcategory":"Textiles",
            "type":"Manufacturing & Wholesale Goods"
        }
    ],
    "sg:phone":"+32 2 452 50 42",
    "sg:postcode":"1730",
    "sg:province":"Vlaams-Brabant",
    "sg:tags":[
        "v\u00eatements",
        "pour",
        "dames"
    ],
    "wof:name":"Ann's House",
    "wof:placetype":"venue"
},
  "geometry": {"coordinates":[4.1961150169,50.9115562439],"type":"Point"}
}