{
  "type": "Feature",
  "properties": {
    "addr:full":"5300 Andenne (groot) Namur 5300",
    "addr:postcode":"5300;5300",
    "addr:street":"Groot Namur",
    "iso:country":"BE",
    "sg:address":"5300",
    "sg:city":"Andenne (groot)",
    "sg:orig_category":"Pharmaciens",
    "sg:phone":"+32 900 10 500",
    "sg:postcode":"5300",
    "sg:province":"Namur",
    "wof:name":"Pharmacies De Garde",
    "wof:placetype":"venue"
},
  "geometry": {"coordinates":[5.0982642174,50.4863739014],"type":"Point"}
}