{
  "type": "Feature",
  "properties": {
    "iso:country":"BE",
    "sg:address":"Rue Arthur Baudhuin 42",
    "sg:city":"Fleurus (lambusart)",
    "sg:classifiers":[
        {
            "category":"Personal",
            "subcategory":"Barber",
            "type":"Services"
        }
    ],
    "sg:phone":"+32 71 81 58 76",
    "sg:postcode":"6220",
    "sg:province":"Hainaut",
    "sg:tags":[
        "gentleman",
        "salon",
        "-",
        "hairdressing"
    ],
    "wof:name":"Coif'actuel",
    "wof:placetype":"venue"
},
  "geometry": {"coordinates":[4.5550341606,50.4572677612],"type":"Point"}
}