{
  "type": "Feature",
  "properties": {
    "iso:country":"BE",
    "sg:address":"Ter Kamerenpad 3",
    "sg:city":"Vilvoorde",
    "sg:orig_category":"DIVERSE RECREATIEVE ACTIVITEITEN",
    "sg:phone":"+32 2 251 16 91",
    "sg:postcode":"1800",
    "sg:province":"Vlaams-Brabant",
    "wof:name":"Vilvoordse Postzegelclub",
    "wof:placetype":"venue"
},
  "geometry": {"coordinates":[4.4692029953,50.9438667297],"type":"Point"}
}