{
  "type": "Feature",
  "properties": {
    "addr:full":"Akkerstraat 2 Beernem West-Vlaanderen 8730",
    "addr:housenumber":"2",
    "addr:postcode":"8730",
    "addr:street":"Akkerstraat",
    "iso:country":"BE",
    "sg:address":"Akkerstraat 2",
    "sg:city":"Beernem",
    "sg:orig_category":"D\u00e9corateurs d'int\u00e9rieur. Meubles D\u00e9taillants, Am\u00e9nagement de B\u00e2timents et de Cuisines",
    "sg:phone":"+32 50 79 01 80",
    "sg:postcode":"8730",
    "sg:province":"West-Vlaanderen",
    "wof:name":"Sigrid Gevaert",
    "wof:placetype":"venue"
},
  "geometry": {"coordinates":[3.3397810459,51.1438140869],"type":"Point"}
}