{
  "type": "Feature",
  "properties": {
    "addr:full":"Acaciastraat 14 Geel Antwerpen 2440",
    "addr:housenumber":"14",
    "addr:postcode":"2440",
    "addr:street":"Acaciastraat",
    "iso:country":"BE",
    "sg:address":"Acaciastraat 14",
    "sg:city":"Geel",
    "sg:classifiers":[
        {
            "category":"Autos & Motor Vehicles",
            "subcategory":"Motorcycle Sales",
            "type":"Retail Goods"
        }
    ],
    "sg:phone":"+32 14 86 87 35",
    "sg:postcode":"2440",
    "sg:province":"Antwerpen",
    "sg:tags":[
        "motorbike"
    ],
    "wof:name":"Bakker's Harley Garage",
    "wof:placetype":"venue"
},
  "geometry": {"coordinates":[5.0130238533,51.1202201843],"type":"Point"}
}