{
  "type": "Feature",
  "properties": {
    "addr:full":"Mechelsesteenweg 144 Dendermonde Oost-Vlaanderen 9200",
    "addr:housenumber":"144",
    "addr:postcode":"9200",
    "addr:street":"Mechelsesteenweg;Oost-Vlaanderen",
    "iso:country":"BE",
    "sg:address":"Mechelsesteenweg 144",
    "sg:city":"Dendermonde",
    "sg:orig_category":"V\u00eatements pour Dames. V\u00eatements pour Hommes",
    "sg:phone":"+32 52 21 53 88",
    "sg:postcode":"9200",
    "sg:province":"Oost-Vlaanderen",
    "wof:name":"E5 Mode",
    "wof:placetype":"venue"
},
  "geometry": {"coordinates":[4.1242499352,51.0370101929],"type":"Point"}
}