{
  "type": "Feature",
  "properties": {
    "iso:country":"BE",
    "sg:address":"Brugsestraat 140",
    "sg:city":"Harelbeke",
    "sg:orig_category":"Diverse grafische activiteiten Drukkerijen and copyshops Fotogravure and zetwerk Secretariaatsdienst",
    "sg:phone":"+32 56 71 58 49",
    "sg:postcode":"8531",
    "sg:province":"West-Vlaanderen",
    "wof:name":"Full Service",
    "wof:placetype":"venue"
},
  "geometry": {"coordinates":[3.3104400635,50.8748130798],"type":"Point"}
}