{
  "type": "Feature",
  "properties": {
    "addr:full":"Stationsplein 8 Herentals Antwerpen 2200",
    "addr:housenumber":"8",
    "addr:postcode":"2200",
    "addr:street":"Stationsplein",
    "iso:country":"BE",
    "sg:address":"Stationsplein 8",
    "sg:city":"Herentals",
    "sg:classifiers":[
        {
            "category":"Professional",
            "subcategory":"Accounting & Tax Preparation",
            "type":"Services"
        }
    ],
    "sg:phone":"+32 14 23 70 87",
    "sg:postcode":"2200",
    "sg:province":"Antwerpen",
    "sg:tags":[
        "accountant"
    ],
    "wof:name":"Afidac Bvba",
    "wof:placetype":"venue"
},
  "geometry": {"coordinates":[4.828248024,51.1804275513],"type":"Point"}
}