{
  "type": "Feature",
  "properties": {
    "addr:full":"Rue Du Pont 37 Hamoir Li\u00e8ge 4180",
    "addr:housenumber":"37",
    "addr:postcode":"4180",
    "addr:street":"Rue Du Pont",
    "iso:country":"BE",
    "sg:address":"Rue Du Pont 37",
    "sg:city":"Hamoir",
    "sg:orig_category":"Pain, p\u00e2tisseries and confiseries",
    "sg:phone":"+32 86 38 87 01",
    "sg:postcode":"4180",
    "sg:province":"Li\u00e8ge",
    "wof:name":"Boulangerie Louviaux",
    "wof:placetype":"venue"
},
  "geometry": {"coordinates":[5.5335988998,50.4263648987],"type":"Point"}
}