{
  "type": "Feature",
  "properties": {
    "iso:country":"BE",
    "sg:address":"Route De Mochamps 2",
    "sg:city":"Tenneville",
    "sg:orig_category":"Services divers aux entreprises. Organisation de salons, expositions and bourses. Salles de conf\u00e9ren",
    "sg:phone":"+32 84 45 57 91",
    "sg:postcode":"6971",
    "sg:province":"Luxembourg",
    "wof:name":"La Converserie",
    "wof:placetype":"venue"
},
  "geometry": {"coordinates":[5.5017828941,50.1076087952],"type":"Point"}
}