{
  "type": "Feature",
  "properties": {
    "addr:full":"Place Tombois 83 Dinant Namur 5500",
    "addr:housenumber":"83",
    "addr:postcode":"5500",
    "addr:street":"Place Tombois",
    "iso:country":"BE",
    "sg:address":"Place Tombois 83",
    "sg:city":"Dinant",
    "sg:orig_category":"Pain, p\u00e2tisseries and confiseries",
    "sg:phone":"+32 82 74 42 58",
    "sg:postcode":"5500",
    "sg:province":"Namur",
    "wof:name":"Roger Lebutte",
    "wof:placetype":"venue"
},
  "geometry": {"coordinates":[4.8927898407,50.2034759521],"type":"Point"}
}