{
  "type": "Feature",
  "properties": {
    "addr:full":"Place Albert I 17 Wavre (limal) Brabant Wallon 1300",
    "addr:housenumber":"17",
    "addr:postcode":"1300",
    "addr:street":"Place Albert I;Wallon",
    "iso:country":"BE",
    "sg:address":"Place Albert I 17",
    "sg:city":"Wavre (limal)",
    "sg:classifiers":[
        {
            "category":"Building & Trades",
            "subcategory":"Landscaping Services",
            "type":"Services"
        }
    ],
    "sg:phone":"+32 10 41 52 92",
    "sg:postcode":"1300",
    "sg:province":"Brabant Wallon",
    "sg:tags":[
        "architect",
        "landscape"
    ],
    "wof:name":"Van Beneden P",
    "wof:placetype":"venue"
},
  "geometry": {"coordinates":[4.6116552353,50.7134132385],"type":"Point"}
}