{
  "type": "Feature",
  "properties": {
    "addr:full":"Ternatsestraat 238 Affligem Vlaams-Brabant 1790",
    "addr:housenumber":"238",
    "addr:postcode":"1790",
    "addr:street":"Ternatsestraat",
    "iso:country":"BE",
    "sg:address":"Ternatsestraat 238",
    "sg:city":"Affligem",
    "sg:orig_category":"Installatie van houten of kunststof schrijnwerk",
    "sg:phone":"+32 2 582 29 36",
    "sg:postcode":"1790",
    "sg:province":"Vlaams-Brabant",
    "wof:name":"Jean-pierre De Thaey",
    "wof:placetype":"venue"
},
  "geometry": {"coordinates":[4.147371769,50.8897209167],"type":"Point"}
}