{
  "type": "Feature",
  "properties": {
    "iso:country":"BE",
    "sg:address":"Stevennekens 39",
    "sg:city":"Rijkevorsel",
    "sg:orig_category":"Betonnen bouwelementen Fab Gespecialiseerde residenti\u00eble bouw",
    "sg:phone":"+32 3 314 44 46",
    "sg:postcode":"2310",
    "sg:province":"Antwerpen",
    "wof:name":"Kleeren",
    "wof:placetype":"venue"
},
  "geometry": {"coordinates":[4.7703142166,51.3400650024],"type":"Point"}
}