{
  "type": "Feature",
  "properties": {
    "addr:full":"Avenue Winston Churchill 160b1 Ukkel/uccle Bruxelles-Capitale 1180",
    "addr:housenumber":"160b1",
    "addr:postcode":"1180",
    "addr:street":"Avenue Winston Churchill;/",
    "iso:country":"BE",
    "sg:address":"Avenue Winston Churchill 160b1",
    "sg:city":"Ukkel/uccle",
    "sg:classifiers":[
        {
            "category":"Insurance",
            "subcategory":"Life Insurance",
            "type":"Services"
        }
    ],
    "sg:phone":"+32 2 343 06 50",
    "sg:postcode":"1180",
    "sg:province":"Bruxelles-Capitale",
    "sg:tags":[
        "assurance"
    ],
    "wof:name":"Troisfontaine",
    "wof:placetype":"venue"
},
  "geometry": {"coordinates":[4.3587617874,50.811580658],"type":"Point"}
}