{
  "type": "Feature",
  "properties": {
    "iso:country":"BE",
    "sg:address":"Boulevard De L'europe 17",
    "sg:city":"Wavre",
    "sg:classifiers":[
        {
            "category":"Transit Center",
            "subcategory":"Passenger",
            "type":"Transportation"
        }
    ],
    "sg:phone":"+32 800 16 666",
    "sg:postcode":"1300",
    "sg:province":"Brabant Wallon",
    "sg:tags":[
        "car",
        "trailer"
    ],
    "wof:name":"Trend-rent",
    "wof:placetype":"venue"
},
  "geometry": {"coordinates":[4.6079602242,50.7127571106],"type":"Point"}
}