{
  "type": "Feature",
  "properties": {
    "addr:full":"Voskenslaan 272 Gent Oost-Vlaanderen 9000",
    "addr:housenumber":"272",
    "addr:postcode":"9000",
    "addr:street":"Voskenslaan;Oost-Vlaanderen",
    "iso:country":"BE",
    "sg:address":"Voskenslaan 272",
    "sg:city":"Gent",
    "sg:classifiers":[
        {
            "category":"Cafe",
            "type":"Food & Drink"
        }
    ],
    "sg:phone":"+32 9 222 92 15",
    "sg:postcode":"9000",
    "sg:province":"Oost-Vlaanderen",
    "sg:tags":[
        "caf\u00e9s"
    ],
    "wof:name":"'t Kwadraat",
    "wof:placetype":"venue"
},
  "geometry": {"coordinates":[3.7061390877,51.0309486389],"type":"Point"}
}