{
  "type": "Feature",
  "properties": {
    "addr:full":"Avenue Edmond Parmentier 137 Sint-pieters-woluwe/woluwe-saint-pierre Bruxelles-Capitale 1150",
    "addr:housenumber":"137",
    "addr:postcode":"1150",
    "addr:street":"Avenue Edmond Parmentier;/",
    "iso:country":"BE",
    "sg:address":"Avenue Edmond Parmentier 137",
    "sg:city":"Sint-pieters-woluwe/woluwe-saint-pierre",
    "sg:orig_category":"M\u00e9decins and sp\u00e9cialistes",
    "sg:phone":"+32 2 771 90 32",
    "sg:postcode":"1150",
    "sg:province":"Bruxelles-Capitale",
    "wof:name":"Genevi\u00c8ve Haucotte",
    "wof:placetype":"venue"
},
  "geometry": {"coordinates":[4.4438281059,50.8314285278],"type":"Point"}
}