{
  "type": "Feature",
  "properties": {
    "iso:country":"BE",
    "sg:address":"Retieseweg 180",
    "sg:city":"Geel",
    "sg:classifiers":[
        {
            "category":"Bars & Pubs",
            "type":"Food & Drink"
        }
    ],
    "sg:phone":"+32 14 58 57 18",
    "sg:postcode":"2440",
    "sg:province":"Antwerpen",
    "sg:tags":[
        "tavern"
    ],
    "wof:name":"Sas Zeven",
    "wof:placetype":"venue"
},
  "geometry": {"coordinates":[5.0391898155,51.2100906372],"type":"Point"}
}