{
  "type": "Feature",
  "properties": {
    "iso:country":"BE",
    "sg:address":"Turkeijensteenweg 18",
    "sg:city":"Pittem",
    "sg:orig_category":"Electrom\u00e9nager, t\u00e9l\u00e9visions and radios. R\u00e9parations d'appareils \u00e9lectrom\u00e9nagers",
    "sg:phone":"+32 51 46 60 17",
    "sg:postcode":"8740",
    "sg:province":"West-Vlaanderen",
    "wof:name":"Lucien Herpoelaert",
    "wof:placetype":"venue"
},
  "geometry": {"coordinates":[3.2761209011,51.0152626038],"type":"Point"}
}