{
  "type": "Feature",
  "properties": {
    "iso:country":"BE",
    "sg:address":"Parklaan 117",
    "sg:city":"Sint-niklaas",
    "sg:orig_category":"Sportterreinen and installaties behalve sportcentra",
    "sg:phone":"+32 3 776 27 12",
    "sg:postcode":"9100",
    "sg:province":"Oost-Vlaanderen",
    "wof:name":"Stedelijk Zwembad",
    "wof:placetype":"venue"
},
  "geometry": {"coordinates":[4.1534371376,51.1564216614],"type":"Point"}
}