{
  "type": "Feature",
  "properties": {
    "addr:full":"Tervuursevest 15-23 Leuven (heverlee) Vlaams-Brabant 3001",
    "addr:postcode":"15-23;3001",
    "addr:street":"Tervuursevest",
    "iso:country":"BE",
    "sg:address":"Tervuursevest 15-23",
    "sg:city":"Leuven (heverlee)",
    "sg:classifiers":[
        {
            "category":"Real Estate",
            "subcategory":"Architect",
            "type":"Services"
        }
    ],
    "sg:phone":"+32 16 22 08 05",
    "sg:postcode":"3001",
    "sg:province":"Vlaams-Brabant",
    "wof:name":"Daems J",
    "wof:placetype":"venue"
},
  "geometry": {"coordinates":[4.6826100349,50.8765678406],"type":"Point"}
}