{
  "type": "Feature",
  "properties": {
    "addr:full":"Rue Saint-jacques 31b Namur Namur 5000",
    "addr:housenumber":"31b",
    "addr:postcode":"5000",
    "addr:street":"Rue Saint-Jacques",
    "iso:country":"BE",
    "sg:address":"Rue Saint-jacques 31b",
    "sg:city":"Namur",
    "sg:classifiers":[
        {
            "category":"Personal",
            "type":"Services"
        }
    ],
    "sg:phone":"+32 81 23 06 93",
    "sg:postcode":"5000",
    "sg:province":"Namur",
    "sg:tags":[
        "clothing",
        "men's",
        "tailor",
        "-"
    ],
    "wof:name":"Steed & Barney's",
    "wof:placetype":"venue"
},
  "geometry": {"coordinates":[4.8637681007,50.4650192261],"type":"Point"}
}