{
  "type": "Feature",
  "properties": {
    "addr:full":"Brugsestraat 59 Aartrijke West-Vlaanderen 8211",
    "addr:housenumber":"59",
    "addr:postcode":"8211",
    "addr:street":"Brugsestraat",
    "iso:country":"BE",
    "sg:address":"Brugsestraat 59",
    "sg:city":"Aartrijke",
    "sg:orig_category":"Computers Fab Computers and computerapparatuur Kantoormateriaal Gh Microsoft Papierwaren and schoolb",
    "sg:phone":"+32 50 24 15 27",
    "sg:postcode":"8211",
    "sg:province":"West-Vlaanderen",
    "wof:name":"Bonte Marc (coma & Soft)",
    "wof:placetype":"venue"
},
  "geometry": {"coordinates":[3.0889649391,51.1200408936],"type":"Point"}
}