{
  "type": "Feature",
  "properties": {
    "addr:full":"Rue Gonoy 82 Mettet Namur 5640",
    "addr:housenumber":"82",
    "addr:postcode":"5640",
    "addr:street":"Rue Gonoy",
    "iso:country":"BE",
    "sg:address":"Rue Gonoy 82",
    "sg:city":"Mettet",
    "sg:orig_category":"Plomberie, chauffage and installations sanitaires",
    "sg:phone":"+32 71 71 48 41",
    "sg:postcode":"5640",
    "sg:province":"Namur",
    "wof:name":"Christophe Liegeois",
    "wof:placetype":"venue"
},
  "geometry": {"coordinates":[4.7112641335,50.372718811],"type":"Point"}
}