{
  "type": "Feature",
  "properties": {
    "iso:country":"BE",
    "sg:address":"Reenstraat 52",
    "sg:city":"Arendonk",
    "sg:classifiers":[
        {
            "category":"Building & Trades",
            "subcategory":"Electrical",
            "type":"Services"
        }
    ],
    "sg:phone":"+32 14 67 81 92",
    "sg:postcode":"2370",
    "sg:province":"Antwerpen",
    "sg:tags":[
        "electric",
        "-",
        "housewiring",
        "contractor"
    ],
    "wof:name":"Elektro Jacobs",
    "wof:placetype":"venue"
},
  "geometry": {"coordinates":[5.0645308495,51.3303222656],"type":"Point"}
}