{
  "type": "Feature",
  "properties": {
    "iso:country":"BE",
    "sg:address":"Ransbeekstraat 49",
    "sg:city":"Brussel/bruxelles",
    "sg:orig_category":"Herstellingen and onderhoud van auto's Voertuigen",
    "sg:phone":"+32 2 268 30 10",
    "sg:postcode":"1120",
    "sg:province":"Bruxelles-Capitale",
    "wof:name":"Garage Ransbeek",
    "wof:placetype":"venue"
},
  "geometry": {"coordinates":[4.3942627907,50.8958892822],"type":"Point"}
}