{
  "type": "Feature",
  "properties": {
    "addr:full":"Rue D'herchies 150 Mons (baudour) Hainaut 7331",
    "addr:housenumber":"150",
    "addr:postcode":"7331",
    "addr:street":"Rue D'Herchies",
    "iso:country":"BE",
    "sg:address":"Rue D'herchies 150",
    "sg:city":"Mons (baudour)",
    "sg:classifiers":[
        {
            "category":"Home & Garden",
            "subcategory":"Hardware",
            "type":"Retail Goods"
        }
    ],
    "sg:phone":"+32 65 64 21 20",
    "sg:postcode":"7331",
    "sg:province":"Hainaut",
    "sg:tags":[
        "-"
    ],
    "wof:name":"Gossuin-winant Sprl",
    "wof:placetype":"venue"
},
  "geometry": {"coordinates":[3.8330130577,50.4934272766],"type":"Point"}
}