{
  "type": "Feature",
  "properties": {
    "addr:full":"Avenue De L\u00b4europe 3bb Leuze-en-hainaut Hainaut 7903",
    "addr:housenumber":"3bb",
    "addr:postcode":"7903",
    "addr:street":"Avenue De L\u00b4Europe",
    "iso:country":"BE",
    "sg:address":"Avenue De L\u00b4europe 3bb",
    "sg:city":"Leuze-en-hainaut",
    "sg:orig_category":"Antiek Tweedehandsgoederen",
    "sg:phone":"+32 69 66 24 44",
    "sg:postcode":"7903",
    "sg:province":"Hainaut",
    "wof:name":"De Knudt Antiquit\u00c9",
    "wof:placetype":"venue"
},
  "geometry": {"coordinates":[3.6515729427,50.6045799255],"type":"Point"}
}