{
  "type": "Feature",
  "properties": {
    "iso:country":"BE",
    "sg:address":"Biezenstraat 95",
    "sg:city":"Roeselare",
    "sg:classifiers":[
        {
            "category":"Bakery",
            "type":"Food & Drink"
        }
    ],
    "sg:phone":"+32 51 24 57 47",
    "sg:postcode":"8800",
    "sg:province":"West-Vlaanderen",
    "sg:tags":[
        "confectioner",
        "baker"
    ],
    "wof:name":"Biezenhof ('t)",
    "wof:placetype":"venue"
},
  "geometry": {"coordinates":[3.1104838848,50.9625892639],"type":"Point"}
}