{
  "type": "Feature",
  "properties": {
    "iso:country":"BE",
    "sg:address":"Rue Des Alli\u00c9s 78",
    "sg:city":"Frameries",
    "sg:orig_category":"Artsen and specialisten Medische and orthopedische apparaten",
    "sg:phone":"+32 65 67 20 62",
    "sg:postcode":"7080",
    "sg:province":"Hainaut",
    "wof:name":"Cludts-fally & Fils",
    "wof:placetype":"venue"
},
  "geometry": {"coordinates":[3.8940639496,50.4088020325],"type":"Point"}
}