{
  "type": "Feature",
  "properties": {
    "addr:full":"Avenue De La Seigneurie 51 Chaumont-gistoux (dion-valmont) Brabant Wallon 1325",
    "addr:housenumber":"51",
    "addr:postcode":"1325",
    "addr:street":"Avenue De La Seigneurie;Wallon",
    "iso:country":"BE",
    "sg:address":"Avenue De La Seigneurie 51",
    "sg:city":"Chaumont-gistoux (dion-valmont)",
    "sg:orig_category":"Fiduciairies",
    "sg:phone":"+32 10 24 88 24",
    "sg:postcode":"1325",
    "sg:province":"Brabant Wallon",
    "wof:name":"Bruynfico",
    "wof:placetype":"venue"
},
  "geometry": {"coordinates":[4.6409440041,50.6884841919],"type":"Point"}
}