{
  "type": "Feature",
  "properties": {
    "addr:full":"Avenue Roi Albert 149 Andenne Namur 5300",
    "addr:housenumber":"149",
    "addr:postcode":"5300",
    "addr:street":"Avenue Roi Albert",
    "iso:country":"BE",
    "sg:address":"Avenue Roi Albert 149",
    "sg:city":"Andenne",
    "sg:classifiers":[
        {
            "category":"Home & Garden",
            "subcategory":"Household Appliances",
            "type":"Retail Goods"
        }
    ],
    "sg:phone":"+32 85 84 25 71",
    "sg:postcode":"5300",
    "sg:province":"Namur",
    "sg:tags":[
        "heating",
        "apparatus"
    ],
    "wof:name":"Comptoir Commercial Du Plastique",
    "wof:placetype":"venue"
},
  "geometry": {"coordinates":[5.1067700386,50.493598938],"type":"Point"}
}