{
  "type": "Feature",
  "properties": {
    "iso:country":"BE",
    "sg:address":"Zeeweg 52",
    "sg:city":"Torhout",
    "sg:orig_category":"Elektrische installaties voor woningen",
    "sg:phone":"+32 50 21 63 08",
    "sg:postcode":"8820",
    "sg:province":"West-Vlaanderen",
    "wof:name":"Luc Boone",
    "wof:placetype":"venue"
},
  "geometry": {"coordinates":[3.0850300789,51.098285675],"type":"Point"}
}