{
  "type": "Feature",
  "properties": {
    "addr:full":"Waverse Steenweg 713 Etterbeek (brussel) Bruxelles-Capitale 1040",
    "addr:housenumber":"713",
    "addr:postcode":"1040",
    "addr:street":"Waverse Steenweg",
    "iso:country":"BE",
    "sg:address":"Waverse Steenweg 713",
    "sg:city":"Etterbeek (brussel)",
    "sg:orig_category":"Kleding Textiel",
    "sg:phone":"+32 2 647 44 77",
    "sg:postcode":"1040",
    "sg:province":"Bruxelles-Capitale",
    "wof:name":"Veritas",
    "wof:placetype":"venue"
},
  "geometry": {"coordinates":[4.3870849609,50.8363609314],"type":"Point"}
}