{
  "type": "Feature",
  "properties": {
    "addr:full":"Vierlinden 24 Evergem Oost-Vlaanderen 9940",
    "addr:housenumber":"24",
    "addr:postcode":"9940",
    "addr:street":"Vierlinden;Oost-Vlaanderen",
    "iso:country":"BE",
    "sg:address":"Vierlinden 24",
    "sg:city":"Evergem",
    "sg:classifiers":[
        {
            "category":"Personal",
            "subcategory":"Beauty Salon",
            "type":"Services"
        }
    ],
    "sg:phone":"+32 9 253 90 80",
    "sg:postcode":"9940",
    "sg:province":"Oost-Vlaanderen",
    "sg:tags":[
        "de",
        "coiffure"
    ],
    "wof:name":"Coiffure Solange",
    "wof:placetype":"venue"
},
  "geometry": {"coordinates":[3.7009010315,51.116443634],"type":"Point"}
}