{
  "type": "Feature",
  "properties": {
    "addr:full":"Faubourg De France 53b1 Bouillon Luxembourg 6830",
    "addr:housenumber":"53b1",
    "addr:postcode":"6830",
    "addr:street":"Faubourg De France",
    "iso:country":"BE",
    "sg:address":"Faubourg De France 53b1",
    "sg:city":"Bouillon",
    "sg:orig_category":"Installatie van houten of kunststof schrijnwerk",
    "sg:phone":"+32 495 78 70 27",
    "sg:postcode":"6830",
    "sg:province":"Luxembourg",
    "wof:name":"Raphael Allard",
    "wof:placetype":"venue"
},
  "geometry": {"coordinates":[5.0649008751,49.7862548828],"type":"Point"}
}