{
  "type": "Feature",
  "properties": {
    "iso:country":"BE",
    "sg:address":"Rempart Des Arquebusiers 41a-b",
    "sg:city":"Vis\u00e9",
    "sg:classifiers":[
        {
            "category":"Bars & Pubs",
            "subcategory":"Wine Bar",
            "type":"Food & Drink"
        }
    ],
    "sg:phone":"+32 4 379 24 38",
    "sg:postcode":"4600",
    "sg:province":"Li\u00e8ge",
    "sg:tags":[
        "cellar",
        "fixture"
    ],
    "wof:name":"Vise-service Sprl",
    "wof:placetype":"venue"
},
  "geometry": {"coordinates":[5.6968860626,50.7338562012],"type":"Point"}
}