{
  "type": "Feature",
  "properties": {
    "addr:full":"Rue De L'h\u00d4pital 19 Andenne Namur 5340",
    "addr:housenumber":"19",
    "addr:postcode":"5340",
    "addr:street":"Rue De L'Ho \u0302Pital",
    "iso:country":"BE",
    "sg:address":"Rue De L'h\u00d4pital 19",
    "sg:city":"Andenne",
    "sg:orig_category":"Rusthuizen and serviceflats",
    "sg:phone":"+32 85 84 36 84",
    "sg:postcode":"5340",
    "sg:province":"Namur",
    "wof:name":"La Qui\u00c9tude",
    "wof:placetype":"venue"
},
  "geometry": {"coordinates":[5.0521998405,50.4178886414],"type":"Point"}
}