{
  "type": "Feature",
  "properties": {
    "iso:country":"BE",
    "sg:address":"Rue Arthur Hardy 8bc",
    "sg:city":"Wavre",
    "sg:orig_category":"Advocaten and juridische adviseurs",
    "sg:phone":"+32 10 41 39 33",
    "sg:postcode":"1300",
    "sg:province":"Brabant Wallon",
    "wof:name":"Marc Bastin",
    "wof:placetype":"venue"
},
  "geometry": {"coordinates":[4.6116552353,50.7134132385],"type":"Point"}
}