{
  "type": "Feature",
  "properties": {
    "iso:country":"BE",
    "sg:address":"Meulesteedsesteenweg 1",
    "sg:city":"Gent",
    "sg:classifiers":[
        {
            "category":"Arena",
            "subcategory":"Sports Club",
            "type":"Entertainment"
        }
    ],
    "sg:phone":"+32 9 259 01 38",
    "sg:postcode":"9000",
    "sg:province":"Oost-Vlaanderen",
    "wof:name":"Rails (de)",
    "wof:placetype":"venue"
},
  "geometry": {"coordinates":[3.7309660912,51.0736236572],"type":"Point"}
}