{
  "type": "Feature",
  "properties": {
    "addr:full":"Rue Major P\u00c9tillon 33 Etterbeek/etterbeek Bruxelles-Capitale 1040",
    "addr:housenumber":"33",
    "addr:postcode":"1040",
    "addr:street":"Rue Major Pe\u0301Tillon",
    "iso:country":"BE",
    "sg:address":"Rue Major P\u00c9tillon 33",
    "sg:city":"Etterbeek/etterbeek",
    "sg:orig_category":"Avocats and conseillers juridiques",
    "sg:phone":"+32 2 645 15 09",
    "sg:postcode":"1040",
    "sg:province":"Bruxelles-Capitale",
    "wof:name":"A. Verheyden",
    "wof:placetype":"venue"
},
  "geometry": {"coordinates":[4.4029350281,50.8272895813],"type":"Point"}
}