{
  "type": "Feature",
  "properties": {
    "iso:country":"BE",
    "sg:address":"Aarselestraat 2",
    "sg:city":"Tielt (aarsele)",
    "sg:classifiers":[
        {
            "category":"Food & Beverages",
            "subcategory":"Groceries & Convenience Stores",
            "type":"Retail Goods"
        }
    ],
    "sg:phone":"+32 51 63 36 87",
    "sg:postcode":"8700",
    "sg:province":"West-Vlaanderen",
    "sg:tags":[
        "grocer"
    ],
    "wof:name":"Verhenne",
    "wof:placetype":"venue"
},
  "geometry": {"coordinates":[3.4218130112,50.9960365295],"type":"Point"}
}