{
  "type": "Feature",
  "properties": {
    "addr:full":"Booischotsestraat 1 Tremelo (baal) Vlaams-Brabant 3128",
    "addr:housenumber":"1",
    "addr:postcode":"3128",
    "addr:street":"Booischotsestraat",
    "iso:country":"BE",
    "sg:address":"Booischotsestraat 1",
    "sg:city":"Tremelo (baal)",
    "sg:classifiers":[
        {
            "category":"Organizations",
            "subcategory":"Professional Association",
            "type":"Services"
        }
    ],
    "sg:phone":"+32 16 53 52 37",
    "sg:postcode":"3128",
    "sg:province":"Vlaams-Brabant",
    "sg:tags":[
        "organisation",
        "seminar"
    ],
    "wof:name":"Lindenhof",
    "wof:placetype":"venue"
},
  "geometry": {"coordinates":[4.7543978691,51.0097541809],"type":"Point"}
}