{
  "type": "Feature",
  "properties": {
    "iso:country":"BE",
    "sg:address":"Maastrichtersteenweg 11b4",
    "sg:city":"Hasselt",
    "sg:orig_category":"Agences d'exp\u00e9dition",
    "sg:phone":"+32 11 23 22 35",
    "sg:postcode":"3500",
    "sg:province":"Limburg",
    "wof:name":"V & A Trading",
    "wof:placetype":"venue"
},
  "geometry": {"coordinates":[5.3452048302,50.9304351807],"type":"Point"}
}