{
  "type": "Feature",
  "properties": {
    "addr:full":"Reningelstsestraat 30 Heuvelland West-Vlaanderen 8956",
    "addr:housenumber":"30",
    "addr:postcode":"8956",
    "addr:street":"Reningelstsestraat",
    "iso:country":"BE",
    "sg:address":"Reningelstsestraat 30",
    "sg:city":"Heuvelland",
    "sg:orig_category":"Banken and kredietinstellingen",
    "sg:phone":"+32 57 44 56 60",
    "sg:postcode":"8956",
    "sg:province":"West-Vlaanderen",
    "wof:name":"Fortis",
    "wof:placetype":"venue"
},
  "geometry": {"coordinates":[2.8277390003,50.7837028503],"type":"Point"}
}