{
  "type": "Feature",
  "properties": {
    "iso:country":"BE",
    "sg:address":"Stockem 19",
    "sg:city":"Eupen",
    "sg:orig_category":"DIVERSE RECREATIEVE ACTIVITEITEN",
    "sg:phone":"+32 87 55 30 19",
    "sg:postcode":"4700",
    "sg:province":"Li\u00e8ge",
    "wof:name":"La Marque Postale",
    "wof:placetype":"venue"
},
  "geometry": {"coordinates":[6.0196070671,50.6292915344],"type":"Point"}
}