{
  "type": "Feature",
  "properties": {
    "iso:country":"BE",
    "sg:address":"Rue Pierre Ouvrard 1",
    "sg:city":"Flobecq",
    "sg:classifiers":[
        {
            "category":"Utilities",
            "subcategory":"Natural Gas",
            "type":"Services"
        }
    ],
    "sg:phone":"+32 68 44 95 72",
    "sg:postcode":"7880",
    "sg:province":"Hainaut",
    "sg:tags":[
        "industrial",
        "-"
    ],
    "wof:name":"Vande Mert P",
    "wof:placetype":"venue"
},
  "geometry": {"coordinates":[3.7387650013,50.7369918823],"type":"Point"}
}