{
  "type": "Feature",
  "properties": {
    "addr:full":"Rue Borgnet 10 Namur Namur 5000",
    "addr:housenumber":"10",
    "addr:postcode":"5000",
    "addr:street":"Rue Borgnet",
    "iso:country":"BE",
    "sg:address":"Rue Borgnet 10",
    "sg:city":"Namur",
    "sg:orig_category":"Avocats and conseillers juridiques",
    "sg:phone":"+32 81 23 17 23",
    "sg:postcode":"5000",
    "sg:province":"Namur",
    "wof:name":"Beno\u00cet Piette",
    "wof:placetype":"venue"
},
  "geometry": {"coordinates":[4.8664398193,50.4681282043],"type":"Point"}
}