{
  "type": "Feature",
  "properties": {
    "addr:full":"Rue Blockmans 7 Sint-pieters-woluwe/woluwe-saint-pierre Bruxelles-Capitale 1150",
    "addr:housenumber":"7",
    "addr:postcode":"1150",
    "addr:street":"Rue Blockmans;/",
    "iso:country":"BE",
    "sg:address":"Rue Blockmans 7",
    "sg:city":"Sint-pieters-woluwe/woluwe-saint-pierre",
    "sg:orig_category":"Fleurs and plantes",
    "sg:phone":"+32 2 770 66 03",
    "sg:postcode":"1150",
    "sg:province":"Bruxelles-Capitale",
    "wof:name":"Maison Etc...",
    "wof:placetype":"venue"
},
  "geometry": {"coordinates":[4.4632320404,50.840221405],"type":"Point"}
}