{
  "type": "Feature",
  "properties": {
    "addr:full":"Avenue H Wauther 5 Tubize Brabant Wallon 1480",
    "addr:housenumber":"5",
    "addr:postcode":"1480",
    "addr:street":"Avenue H Wauther;Wallon",
    "iso:country":"BE",
    "sg:address":"Avenue H Wauther 5",
    "sg:city":"Tubize",
    "sg:orig_category":"Animations diverses",
    "sg:phone":"+32 2 427 29 11",
    "sg:postcode":"1480",
    "sg:province":"Brabant Wallon",
    "wof:name":"A. & T. New Concept Magic Show",
    "wof:placetype":"venue"
},
  "geometry": {"coordinates":[4.204308033,50.6932029724],"type":"Point"}
}