{
  "type": "Feature",
  "properties": {
    "addr:full":"Rue Emmanuel Jacquet 17 Charleroi Hainaut 6044",
    "addr:housenumber":"17",
    "addr:postcode":"6044",
    "addr:street":"Rue Emmanuel Jacquet;Hainaut",
    "iso:country":"BE",
    "sg:address":"Rue Emmanuel Jacquet 17",
    "sg:city":"Charleroi",
    "sg:orig_category":"Pharmaciens",
    "sg:phone":"+32 71 34 10 65",
    "sg:postcode":"6044",
    "sg:province":"Hainaut",
    "wof:name":"Laurent Cawoy",
    "wof:placetype":"venue"
},
  "geometry": {"coordinates":[4.3968820572,50.4374732971],"type":"Point"}
}