{
  "type": "Feature",
  "properties": {
    "addr:full":"Remi Van De Sandelaan 1 Haacht Vlaams-Brabant 3150",
    "addr:housenumber":"1",
    "addr:postcode":"3150",
    "addr:street":"Remi Van De Sandelaan",
    "iso:country":"BE",
    "sg:address":"Remi Van De Sandelaan 1",
    "sg:city":"Haacht",
    "sg:classifiers":[
        {
            "category":"Government",
            "subcategory":"Police Station",
            "type":"Public Place"
        }
    ],
    "sg:phone":"+32 16 60 88 12",
    "sg:postcode":"3150",
    "sg:province":"Vlaams-Brabant",
    "sg:tags":[
        "gendarmerie"
    ],
    "wof:name":"Federale Politie",
    "wof:placetype":"venue"
},
  "geometry": {"coordinates":[4.6364798546,50.9739723206],"type":"Point"}
}