{
  "type": "Feature",
  "properties": {
    "iso:country":"BE",
    "sg:address":"Postbaan 195",
    "sg:city":"Diest (schaffen)",
    "sg:classifiers":[
        {
            "category":"Professional",
            "subcategory":"Accounting & Tax Preparation",
            "type":"Services"
        }
    ],
    "sg:phone":"+32 13 32 38 50",
    "sg:postcode":"3290",
    "sg:province":"Vlaams-Brabant",
    "sg:tags":[
        "bookkeeper"
    ],
    "wof:name":"Brems H",
    "wof:placetype":"venue"
},
  "geometry": {"coordinates":[5.1023960114,51.0019607544],"type":"Point"}
}