{
  "type": "Feature",
  "properties": {
    "addr:full":"Transportcent.lar Blok K 21 Menen West-Vlaanderen 8930",
    "addr:housenumber":"21",
    "addr:postcode":"8930",
    "iso:country":"BE",
    "sg:address":"Transportcent.lar Blok K 21",
    "sg:city":"Menen",
    "sg:orig_category":"Agences en douane",
    "sg:phone":"+32 56 40 28 15",
    "sg:postcode":"8930",
    "sg:province":"West-Vlaanderen",
    "wof:name":"D. + T.b.",
    "wof:placetype":"venue"
},
  "geometry": {"coordinates":[3.1209149361,50.7961845398],"type":"Point"}
}