{
  "type": "Feature",
  "properties": {
    "iso:country":"BE",
    "sg:address":"March\u00c9 Aux Herbes 2",
    "sg:city":"Mons",
    "sg:orig_category":"Drogisterijen",
    "sg:phone":"+32 65 35 27 69",
    "sg:postcode":"7000",
    "sg:province":"Hainaut",
    "wof:name":"Pierre Kieffer",
    "wof:placetype":"venue"
},
  "geometry": {"coordinates":[3.9531960487,50.452583313],"type":"Point"}
}