{
  "type": "Feature",
  "properties": {
    "addr:full":"Mercatorstraat 154 Sint-niklaas Oost-Vlaanderen 9100",
    "addr:housenumber":"154",
    "addr:postcode":"9100",
    "addr:street":"Mercatorstraat",
    "iso:country":"BE",
    "sg:address":"Mercatorstraat 154",
    "sg:city":"Sint-niklaas",
    "sg:orig_category":"Epiceries",
    "sg:phone":"+32 3 765 17 33",
    "sg:postcode":"9100",
    "sg:province":"Oost-Vlaanderen",
    "wof:name":"Eda",
    "wof:placetype":"venue"
},
  "geometry": {"coordinates":[4.1508507729,51.1687278748],"type":"Point"}
}