{
  "type": "Feature",
  "properties": {
    "addr:full":"Schepenenlaan 11 Hoeselt Limburg 3730",
    "addr:housenumber":"11",
    "addr:postcode":"3730",
    "addr:street":"Schepenenlaan",
    "iso:country":"BE",
    "sg:address":"Schepenenlaan 11",
    "sg:city":"Hoeselt",
    "sg:classifiers":[
        {
            "category":"Bars & Pubs",
            "type":"Food & Drink"
        }
    ],
    "sg:phone":"+32 89 41 20 33",
    "sg:postcode":"3730",
    "sg:province":"Limburg",
    "wof:name":"Bij Kiewit",
    "wof:placetype":"venue"
},
  "geometry": {"coordinates":[5.4864048958,50.8491668701],"type":"Point"}
}