{
  "type": "Feature",
  "properties": {
    "iso:country":"BE",
    "sg:address":"Molenstraat 23",
    "sg:city":"Geraardsbergen",
    "sg:orig_category":"Woningbouw",
    "sg:phone":"+32 54 41 26 13",
    "sg:postcode":"9500",
    "sg:province":"Oost-Vlaanderen",
    "wof:name":"Bouwwerken Vanderstockt",
    "wof:placetype":"venue"
},
  "geometry": {"coordinates":[3.8812990189,50.7706069946],"type":"Point"}
}