{
  "type": "Feature",
  "properties": {
    "addr:full":"Paul Deschanellaan 5 Schaarbeek/schaerbeek Bruxelles-Capitale 1030",
    "addr:housenumber":"5",
    "addr:postcode":"1030",
    "addr:street":"Paul Deschanellaan",
    "iso:country":"BE",
    "sg:address":"Paul Deschanellaan 5",
    "sg:city":"Schaarbeek/schaerbeek",
    "sg:orig_category":"Etalage- and showroomontwerpers",
    "sg:phone":"+32 2 215 64 29",
    "sg:postcode":"1030",
    "sg:province":"Bruxelles-Capitale",
    "wof:name":"Emmanuelle Lemaire",
    "wof:placetype":"venue"
},
  "geometry": {"coordinates":[4.3875050545,50.8582344055],"type":"Point"}
}