{
  "type": "Feature",
  "properties": {
    "addr:full":"Dorp 81 Berlare Oost-Vlaanderen 9290",
    "addr:housenumber":"81",
    "addr:postcode":"9290",
    "addr:street":"Dorp",
    "iso:country":"BE",
    "sg:address":"Dorp 81",
    "sg:city":"Berlare",
    "sg:orig_category":"Location de machines-outils and de mat\u00e9riel de bricolage",
    "sg:phone":"+32 52 42 41 56",
    "sg:postcode":"9290",
    "sg:province":"Oost-Vlaanderen",
    "wof:name":"Transport Bauwens",
    "wof:placetype":"venue"
},
  "geometry": {"coordinates":[4.0071759224,51.0252494812],"type":"Point"}
}