{
  "type": "Feature",
  "properties": {
    "addr:full":"Tiegemberg 32 Anzegem (tiegem) West-Vlaanderen 8573",
    "addr:housenumber":"32",
    "addr:postcode":"8573",
    "addr:street":"Tiegemberg",
    "iso:country":"BE",
    "sg:address":"Tiegemberg 32",
    "sg:city":"Anzegem (tiegem)",
    "sg:classifiers":[
        {
            "category":"Bars & Pubs",
            "type":"Food & Drink"
        }
    ],
    "sg:phone":"+32 56 68 15 78",
    "sg:postcode":"8573",
    "sg:province":"West-Vlaanderen",
    "wof:name":"Charly's",
    "wof:placetype":"venue"
},
  "geometry": {"coordinates":[3.4621651173,50.8181533813],"type":"Point"}
}