{
  "type": "Feature",
  "properties": {
    "iso:country":"BE",
    "sg:address":"Margrietendreef 109",
    "sg:city":"Enghien",
    "sg:classifiers":[
        {
            "category":"Insurance",
            "subcategory":"Insurance Agent",
            "type":"Services"
        }
    ],
    "sg:phone":"+32 2 395 30 31",
    "sg:postcode":"7850",
    "sg:province":"Hainaut",
    "sg:tags":[
        "verzekeringsmakelaars",
        "expert"
    ],
    "wof:name":"Verzekeringskantoor Johan Pint",
    "wof:placetype":"venue"
},
  "geometry": {"coordinates":[4.0334649086,50.6914863586],"type":"Point"}
}