{
  "type": "Feature",
  "properties": {
    "iso:country":"BE",
    "sg:address":"Chauss\u00c9e De Dinant 54",
    "sg:city":"Anhee",
    "sg:orig_category":"M\u00e9decins and sp\u00e9cialistes",
    "sg:phone":"+32 82 61 30 60",
    "sg:postcode":"5537",
    "sg:province":"Namur",
    "wof:name":"V. Rouard",
    "wof:placetype":"venue"
},
  "geometry": {"coordinates":[4.8832840919,50.3067703247],"type":"Point"}
}