{
  "type": "Feature",
  "properties": {
    "addr:full":"Clos Robinson 11 Vis\u00e9 Li\u00e8ge 4600",
    "addr:housenumber":"11",
    "addr:postcode":"4600",
    "addr:street":"Clos Robinson",
    "iso:country":"BE",
    "sg:address":"Clos Robinson 11",
    "sg:city":"Vis\u00e9",
    "sg:classifiers":[
        {
            "category":"Professional",
            "subcategory":"Lawyer & Legal Services",
            "type":"Services"
        }
    ],
    "sg:phone":"+32 4 379 14 78",
    "sg:postcode":"4600",
    "sg:province":"Li\u00e8ge",
    "wof:name":"Henry Dominique",
    "wof:placetype":"venue"
},
  "geometry": {"coordinates":[5.6839299202,50.7334365845],"type":"Point"}
}