{
  "type": "Feature",
  "properties": {
    "addr:full":"Rue Sur Les Bruy\u00c8res 657c Trooz Li\u00e8ge 4870",
    "addr:housenumber":"657c",
    "addr:postcode":"4870",
    "addr:street":"Rue Sur Les Bruye\u0300Res",
    "iso:country":"BE",
    "sg:address":"Rue Sur Les Bruy\u00c8res 657c",
    "sg:city":"Trooz",
    "sg:orig_category":"Plomberie, chauffage and installations sanitaires",
    "sg:phone":"+32 4 351 70 45",
    "sg:postcode":"4870",
    "sg:province":"Li\u00e8ge",
    "wof:name":"Coletti",
    "wof:placetype":"venue"
},
  "geometry": {"coordinates":[5.7142801285,50.5611877441],"type":"Point"}
}