{
  "type": "Feature",
  "properties": {
    "addr:full":"Route Du Lac De Warfa 21 Jalhay (sart) Li\u00e8ge 4845",
    "addr:housenumber":"21",
    "addr:postcode":"4845",
    "addr:street":"Route Du Lac De Warfa;Sart Lie\u0300Ge",
    "iso:country":"BE",
    "sg:address":"Route Du Lac De Warfa 21",
    "sg:city":"Jalhay (sart)",
    "sg:classifiers":[
        {
            "category":"Food & Beverages",
            "subcategory":"Groceries & Convenience Stores",
            "type":"Retail Goods"
        }
    ],
    "sg:phone":"+32 87 27 50 31",
    "sg:postcode":"4845",
    "sg:province":"Li\u00e8ge",
    "sg:tags":[
        "grocer"
    ],
    "wof:name":"Laval",
    "wof:placetype":"venue"
},
  "geometry": {"coordinates":[5.9826211929,50.5540084839],"type":"Point"}
}