{
  "type": "Feature",
  "properties": {
    "addr:full":"Polderstraat 97 Merelbeke Oost-Vlaanderen 9820",
    "addr:housenumber":"97",
    "addr:postcode":"9820",
    "addr:street":"Polderstraat",
    "iso:country":"BE",
    "sg:address":"Polderstraat 97",
    "sg:city":"Merelbeke",
    "sg:classifiers":[
        {
            "category":"Health Services",
            "subcategory":"Doctor",
            "type":"Services"
        }
    ],
    "sg:phone":"+32 9 231 90 77",
    "sg:postcode":"9820",
    "sg:province":"Oost-Vlaanderen",
    "sg:tags":[
        "medicinephysicians",
        "surgeon"
    ],
    "wof:name":"Debekker Els",
    "wof:placetype":"venue"
},
  "geometry": {"coordinates":[3.7419390678,50.9905662537],"type":"Point"}
}