{
  "type": "Feature",
  "properties": {
    "addr:full":"J.b.-stessensstraat 4 Geel Antwerpen 2440",
    "addr:housenumber":"4",
    "addr:postcode":"2440",
    "addr:street":"J.B.-Stessensstraat",
    "iso:country":"BE",
    "sg:address":"J.b.-stessensstraat 4",
    "sg:city":"Geel",
    "sg:orig_category":"Maisons de repos and r\u00e9sidences",
    "sg:phone":"+32 14 58 74 63",
    "sg:postcode":"2440",
    "sg:province":"Antwerpen",
    "wof:name":"Rusthuis Wedbos",
    "wof:placetype":"venue"
},
  "geometry": {"coordinates":[4.9906659126,51.1610794067],"type":"Point"}
}