{
  "type": "Feature",
  "properties": {
    "addr:full":"Rue Des B\u00e9gonias 75 Namur (bouge) Namur 5004",
    "addr:housenumber":"75",
    "addr:postcode":"5004",
    "addr:street":"Rue Des Be\u0301Gonias",
    "iso:country":"BE",
    "sg:address":"Rue Des B\u00e9gonias 75",
    "sg:city":"Namur (bouge)",
    "sg:classifiers":[
        {
            "category":"Health Services",
            "subcategory":"Doctor",
            "type":"Services"
        }
    ],
    "sg:phone":"+32 81 21 07 00",
    "sg:postcode":"5004",
    "sg:province":"Namur",
    "sg:tags":[
        "medicinephysicians",
        "surgeon"
    ],
    "wof:name":"Garrino Maria-grazia",
    "wof:placetype":"venue"
},
  "geometry": {"coordinates":[4.8912858963,50.4716720581],"type":"Point"}
}