{
  "type": "Feature",
  "properties": {
    "iso:country":"BE",
    "sg:address":"Rue De La Plaide 6",
    "sg:city":"Paliseul",
    "sg:orig_category":"Vakantiehuizen",
    "sg:phone":"+32 61 53 48 19",
    "sg:postcode":"6856",
    "sg:province":"Luxembourg",
    "wof:name":"Le M\u00c9nil",
    "wof:placetype":"venue"
},
  "geometry": {"coordinates":[5.1613841057,49.8675041199],"type":"Point"}
}