{
  "type": "Feature",
  "properties": {
    "addr:full":"Oostmolenstraat 5 Aalter Oost-Vlaanderen 9880",
    "addr:housenumber":"5",
    "addr:postcode":"9880",
    "addr:street":"Oostmolenstraat",
    "iso:country":"BE",
    "sg:address":"Oostmolenstraat 5",
    "sg:city":"Aalter",
    "sg:classifiers":[
        {
            "category":"Bars & Pubs",
            "type":"Food & Drink"
        }
    ],
    "sg:phone":"+32 9 374 10 04",
    "sg:postcode":"9880",
    "sg:province":"Oost-Vlaanderen",
    "wof:name":"Paradijs",
    "wof:placetype":"venue"
},
  "geometry": {"coordinates":[3.4462170601,51.0929260254],"type":"Point"}
}