{
  "type": "Feature",
  "properties": {
    "addr:full":"Rue De La Ch\u00eanaie 23 Chaudfontaine Li\u00e8ge 4050",
    "addr:housenumber":"23",
    "addr:postcode":"4050",
    "addr:street":"Rue De La Che\u0302Naie",
    "iso:country":"BE",
    "sg:address":"Rue De La Ch\u00eanaie 23",
    "sg:city":"Chaudfontaine",
    "sg:classifiers":[
        {
            "category":"Professional",
            "subcategory":"Accounting & Tax Preparation",
            "type":"Services"
        }
    ],
    "sg:phone":"+32 4 368 57 27",
    "sg:postcode":"4050",
    "sg:province":"Li\u00e8ge",
    "sg:tags":[
        "bookkeeper"
    ],
    "wof:name":"Lecloux X",
    "wof:placetype":"venue"
},
  "geometry": {"coordinates":[5.6417021751,50.5824317932],"type":"Point"}
}