{
  "type": "Feature",
  "properties": {
    "addr:full":"Mijlstraat 256 Duffel Antwerpen 2570",
    "addr:housenumber":"256",
    "addr:postcode":"2570",
    "addr:street":"Mijlstraat",
    "iso:country":"BE",
    "sg:address":"Mijlstraat 256",
    "sg:city":"Duffel",
    "sg:orig_category":"Artsen and specialisten",
    "sg:phone":"+32 3 489 13 23",
    "sg:postcode":"2570",
    "sg:province":"Antwerpen",
    "wof:name":"Martine A.e. Van Kerckvoorde",
    "wof:placetype":"venue"
},
  "geometry": {"coordinates":[4.5462231636,51.1058998108],"type":"Point"}
}