{
  "type": "Feature",
  "properties": {
    "addr:full":"Place De La Halle 37 Thimister-clermont (clermont) Li\u00e8ge 4890",
    "addr:housenumber":"37",
    "addr:postcode":"4890",
    "addr:street":"Place De La Halle",
    "iso:country":"BE",
    "sg:address":"Place De La Halle 37",
    "sg:city":"Thimister-clermont (clermont)",
    "sg:classifiers":[
        {
            "category":"Arts & Performance",
            "subcategory":"Art Gallery",
            "type":"Entertainment"
        }
    ],
    "sg:phone":"+32 87 44 57 29",
    "sg:postcode":"4890",
    "sg:province":"Li\u00e8ge",
    "wof:name":"Galerie Clermont",
    "wof:placetype":"venue"
},
  "geometry": {"coordinates":[5.8840408325,50.6593093872],"type":"Point"}
}