{
  "type": "Feature",
  "properties": {
    "iso:country":"BE",
    "sg:address":"Rue De La Magr\u00e9e 29",
    "sg:city":"Anthisnes (tavier)",
    "sg:classifiers":[
        {
            "category":"Professional",
            "subcategory":"Art Services",
            "type":"Services"
        }
    ],
    "sg:phone":"+32 4 257 62 75",
    "sg:postcode":"4163",
    "sg:province":"Li\u00e8ge",
    "sg:tags":[
        "graphic",
        "designer"
    ],
    "wof:name":"Schyns P",
    "wof:placetype":"venue"
},
  "geometry": {"coordinates":[5.4688448906,50.4944534302],"type":"Point"}
}