{
  "type": "Feature",
  "properties": {
    "addr:full":"Sparrestraat 36 Moorslede West-Vlaanderen 8890",
    "addr:housenumber":"36",
    "addr:postcode":"8890",
    "addr:street":"Sparrestraat",
    "iso:country":"BE",
    "sg:address":"Sparrestraat 36",
    "sg:city":"Moorslede",
    "sg:classifiers":[
        {
            "category":"Insurance",
            "subcategory":"Life Insurance",
            "type":"Services"
        }
    ],
    "sg:phone":"+32 51 77 85 65",
    "sg:postcode":"8890",
    "sg:province":"West-Vlaanderen",
    "sg:tags":[
        "assurance"
    ],
    "wof:name":"C. Leclercq",
    "wof:placetype":"venue"
},
  "geometry": {"coordinates":[3.0619459152,50.8889312744],"type":"Point"}
}