{
  "type": "Feature",
  "properties": {
    "addr:full":"Oude Bruglaan 114 Lokeren Oost-Vlaanderen 9160",
    "addr:housenumber":"114",
    "addr:postcode":"9160",
    "addr:street":"Oude Bruglaan",
    "iso:country":"BE",
    "sg:address":"Oude Bruglaan 114",
    "sg:city":"Lokeren",
    "sg:classifiers":[
        {
            "category":"Health Services",
            "subcategory":"Dentist",
            "type":"Services"
        }
    ],
    "sg:phone":"+32 9 349 18 24",
    "sg:postcode":"9160",
    "sg:province":"Oost-Vlaanderen",
    "wof:name":"Van Hoecke Yann",
    "wof:placetype":"venue"
},
  "geometry": {"coordinates":[4.004119873,51.1053733826],"type":"Point"}
}