{
  "type": "Feature",
  "properties": {
    "iso:country":"BE",
    "sg:address":"Processieweg 19",
    "sg:city":"Herentals (morkhoven)",
    "sg:classifiers":[
        {
            "category":"Building & Trades",
            "subcategory":"Construction",
            "type":"Services"
        }
    ],
    "sg:phone":"+32 14 26 76 12",
    "sg:postcode":"2200",
    "sg:province":"Antwerpen",
    "sg:tags":[
        "carpenter"
    ],
    "wof:name":"Csk",
    "wof:placetype":"venue"
},
  "geometry": {"coordinates":[4.8143382072,51.1209945679],"type":"Point"}
}