{
  "type": "Feature",
  "properties": {
    "addr:full":"Rue Edouard Sarlet 30 Chaudfontaine Li\u00e8ge 4051",
    "addr:housenumber":"30",
    "addr:postcode":"4051",
    "addr:street":"Rue Edouard Sarlet",
    "iso:country":"BE",
    "sg:address":"Rue Edouard Sarlet 30",
    "sg:city":"Chaudfontaine",
    "sg:orig_category":"Installation de menuiserie en bois and plastique. Rev\u00eatements de sols and murs",
    "sg:phone":"+32 4 367 26 92",
    "sg:postcode":"4051",
    "sg:province":"Li\u00e8ge",
    "wof:name":"Gabriel Raskin",
    "wof:placetype":"venue"
},
  "geometry": {"coordinates":[5.6290478706,50.6071434021],"type":"Point"}
}