{
  "type": "Feature",
  "properties": {
    "iso:country":"BE",
    "sg:address":"Ancien Chemin De Wellin 102a",
    "sg:city":"Daverdisse (haut-fays)",
    "sg:classifiers":[
        {
            "category":"Building & Trades",
            "subcategory":"Construction",
            "type":"Services"
        }
    ],
    "sg:phone":"+32 61 58 89 72",
    "sg:postcode":"6929",
    "sg:province":"Luxembourg",
    "sg:tags":[
        "asphalt",
        "contractor"
    ],
    "wof:name":"Entreprises Colleaux Sa Sa",
    "wof:placetype":"venue"
},
  "geometry": {"coordinates":[5.0231962204,50.0043296814],"type":"Point"}
}