{
  "type": "Feature",
  "properties": {
    "addr:full":"Fabriekstraat 2 Beveren (kallo) Oost-Vlaanderen 9120",
    "addr:housenumber":"2",
    "addr:postcode":"9120",
    "addr:street":"Fabriekstraat",
    "iso:country":"BE",
    "sg:address":"Fabriekstraat 2",
    "sg:city":"Beveren (kallo)",
    "sg:classifiers":[
        {
            "category":"Utilities",
            "subcategory":"Fuel Oil & Lpg",
            "type":"Services"
        }
    ],
    "sg:phone":"+32 3 575 04 86",
    "sg:postcode":"9120",
    "sg:province":"Oost-Vlaanderen",
    "wof:name":"Van Den Bossche",
    "wof:placetype":"venue"
},
  "geometry": {"coordinates":[4.2771201134,51.2526702881],"type":"Point"}
}