{
  "type": "Feature",
  "properties": {
    "addr:full":"Congostraat 8 Hasselt Limburg 3500",
    "addr:housenumber":"8",
    "addr:postcode":"3500",
    "addr:street":"Congostraat",
    "iso:country":"BE",
    "sg:address":"Congostraat 8",
    "sg:city":"Hasselt",
    "sg:classifiers":[
        {
            "category":"Cafe",
            "type":"Food & Drink"
        }
    ],
    "sg:phone":"+32 11 22 20 79",
    "sg:postcode":"3500",
    "sg:province":"Limburg",
    "sg:tags":[
        "caf\u00e9s"
    ],
    "wof:name":"Freddy Konings",
    "wof:placetype":"venue"
},
  "geometry": {"coordinates":[5.3465189934,50.9327697754],"type":"Point"}
}