{
  "type": "Feature",
  "properties": {
    "addr:full":"Avenue G\u00e9n\u00e9ral Eisenhower 38 Bruxelles (schaerbeek) Bruxelles-Capitale 1030",
    "addr:housenumber":"38",
    "addr:postcode":"1030",
    "addr:street":"Avenue Ge\u0301Ne\u0301Ral Eisenhower",
    "iso:country":"BE",
    "sg:address":"Avenue G\u00e9n\u00e9ral Eisenhower 38",
    "sg:city":"Bruxelles (schaerbeek)",
    "sg:classifiers":[
        {
            "category":"Health Services",
            "subcategory":"Health Practitioner",
            "type":"Services"
        }
    ],
    "sg:phone":"+32 478 91 06 49",
    "sg:postcode":"1030",
    "sg:province":"Bruxelles-Capitale",
    "sg:tags":[
        "psychologist"
    ],
    "wof:name":"Dubus J",
    "wof:placetype":"venue"
},
  "geometry": {"coordinates":[4.3832011223,50.8594512939],"type":"Point"}
}