{
  "type": "Feature",
  "properties": {
    "iso:country":"BE",
    "sg:address":"Zeedijk 69-70",
    "sg:city":"Nieuwpoort",
    "sg:classifiers":[
        {
            "category":"Tea Room",
            "subcategory":"None",
            "type":"Food & Drink"
        }
    ],
    "sg:phone":"+32 58 23 17 47",
    "sg:postcode":"8620",
    "sg:province":"West-Vlaanderen",
    "wof:name":"Tiramisu",
    "wof:placetype":"venue"
},
  "geometry": {"coordinates":[2.7117590904,51.1471786499],"type":"Point"}
}