{
  "type": "Feature",
  "properties": {
    "iso:country":"BE",
    "sg:address":"Mariakerksesteenweg 9",
    "sg:city":"Gent (drongen)",
    "sg:classifiers":[
        {
            "category":"Health Services",
            "subcategory":"Health Practitioner",
            "type":"Services"
        }
    ],
    "sg:phone":"+32 9 227 32 51",
    "sg:postcode":"9031",
    "sg:province":"Oost-Vlaanderen",
    "sg:tags":[
        "physiotherapist"
    ],
    "wof:name":"De Roo Vicky",
    "wof:placetype":"venue"
},
  "geometry": {"coordinates":[3.6623430252,51.0517158508],"type":"Point"}
}