{
  "type": "Feature",
  "properties": {
    "addr:full":"Hoogstraat 4 Hechtel-eksel Limburg 3940",
    "addr:housenumber":"4",
    "addr:postcode":"3940",
    "addr:street":"Hoogstraat",
    "iso:country":"BE",
    "sg:address":"Hoogstraat 4",
    "sg:city":"Hechtel-eksel",
    "sg:orig_category":"Travaux de pl\u00e2trage",
    "sg:phone":"+32 11 73 31 94",
    "sg:postcode":"3940",
    "sg:province":"Limburg",
    "wof:name":"Vanhees",
    "wof:placetype":"venue"
},
  "geometry": {"coordinates":[5.364795208,51.1255340576],"type":"Point"}
}