{
  "type": "Feature",
  "properties": {
    "iso:country":"BE",
    "sg:address":"Wechelsebaan 25",
    "sg:city":"Lille",
    "sg:classifiers":[
        {
            "category":"Professional",
            "type":"Services"
        }
    ],
    "sg:phone":"+32 14 88 17 07",
    "sg:postcode":"2275",
    "sg:province":"Antwerpen",
    "sg:tags":[
        "transport",
        "road"
    ],
    "wof:name":"Vandenbroeck-van Hooghten Bvba",
    "wof:placetype":"venue"
},
  "geometry": {"coordinates":[4.8212628365,51.2440795898],"type":"Point"}
}