{
  "type": "Feature",
  "properties": {
    "iso:country":"BE",
    "sg:address":"Kempenstraat 129",
    "sg:city":"Diepenbeek",
    "sg:classifiers":[
        {
            "category":"Manufacturing",
            "subcategory":"Textiles",
            "type":"Manufacturing & Wholesale Goods"
        }
    ],
    "sg:phone":"+32 11 32 17 97",
    "sg:postcode":"3590",
    "sg:province":"Limburg",
    "sg:tags":[
        "retail",
        "-"
    ],
    "wof:name":"Lambrichts",
    "wof:placetype":"venue"
},
  "geometry": {"coordinates":[5.4326839447,50.9264831543],"type":"Point"}
}