{
  "type": "Feature",
  "properties": {
    "addr:full":"Dorp 94 Herselt Antwerpen 2230",
    "addr:housenumber":"94",
    "addr:postcode":"2230",
    "addr:street":"Dorp",
    "iso:country":"BE",
    "sg:address":"Dorp 94",
    "sg:city":"Herselt",
    "sg:orig_category":"Meubelzaken, woning- and keukeninrichting Textiel Verlichting and huishoudartikelen",
    "sg:phone":"+32 14 54 81 63",
    "sg:postcode":"2230",
    "sg:province":"Antwerpen",
    "wof:name":"Huis De Nieuwe Stempel",
    "wof:placetype":"venue"
},
  "geometry": {"coordinates":[4.884619236,51.0550537109],"type":"Point"}
}