{
  "type": "Feature",
  "properties": {
    "iso:country":"BE",
    "sg:address":"Negende Linielaan 24",
    "sg:city":"Middelkerke",
    "sg:orig_category":"Sportclubs",
    "sg:phone":"+32 58 23 62 60",
    "sg:postcode":"8434",
    "sg:province":"West-Vlaanderen",
    "wof:name":"V.c. Blue White Westende",
    "wof:placetype":"venue"
},
  "geometry": {"coordinates":[2.7591300011,51.1481704712],"type":"Point"}
}