{
  "type": "Feature",
  "properties": {
    "addr:full":"Paviljoenweg 69 Mol Antwerpen 2400",
    "addr:housenumber":"69",
    "addr:postcode":"2400",
    "addr:street":"Paviljoenweg",
    "iso:country":"BE",
    "sg:address":"Paviljoenweg 69",
    "sg:city":"Mol",
    "sg:orig_category":"Woningbouw",
    "sg:phone":"+32 14 81 06 14",
    "sg:postcode":"2400",
    "sg:province":"Antwerpen",
    "wof:name":"Mattheuwsen",
    "wof:placetype":"venue"
},
  "geometry": {"coordinates":[5.1907348633,51.2074928284],"type":"Point"}
}