{
  "type": "Feature",
  "properties": {
    "iso:country":"BE",
    "sg:address":"Place Du Perron 39",
    "sg:city":"Theux",
    "sg:orig_category":"Librairies",
    "sg:phone":"+32 87 54 15 89",
    "sg:postcode":"4910",
    "sg:province":"Li\u00e8ge",
    "wof:name":"Boutet",
    "wof:placetype":"venue"
},
  "geometry": {"coordinates":[5.8130698204,50.5348701477],"type":"Point"}
}