{
  "type": "Feature",
  "properties": {
    "iso:country":"BE",
    "sg:address":"Gontrode Heirweg 74",
    "sg:city":"Merelbeke",
    "sg:classifiers":[
        {
            "category":"Food & Beverages",
            "subcategory":"Fruits & Vegetables",
            "type":"Retail Goods"
        }
    ],
    "sg:phone":"+32 9 230 63 04",
    "sg:postcode":"9820",
    "sg:province":"Oost-Vlaanderen",
    "sg:tags":[
        "-"
    ],
    "wof:name":"Pic Nic",
    "wof:placetype":"venue"
},
  "geometry": {"coordinates":[3.7640891075,51.0170288086],"type":"Point"}
}