{
  "type": "Feature",
  "properties": {
    "addr:full":"Avenue Roi Albert 241 Andenne Namur 5300",
    "addr:housenumber":"241",
    "addr:postcode":"5300",
    "addr:street":"Avenue Roi Albert",
    "iso:country":"BE",
    "sg:address":"Avenue Roi Albert 241",
    "sg:city":"Andenne",
    "sg:orig_category":"Brood, gebak and snoepgoed",
    "sg:phone":"+32 85 84 19 09",
    "sg:postcode":"5300",
    "sg:province":"Namur",
    "wof:name":"Au Caprice",
    "wof:placetype":"venue"
},
  "geometry": {"coordinates":[5.112112999,50.4950180054],"type":"Point"}
}