{
  "type": "Feature",
  "properties": {
    "addr:full":"Apostelstraat 17b2 Sint-niklaas Oost-Vlaanderen 9100",
    "addr:housenumber":"17b2",
    "addr:postcode":"9100",
    "addr:street":"Apostelstraat",
    "iso:country":"BE",
    "sg:address":"Apostelstraat 17b2",
    "sg:city":"Sint-niklaas",
    "sg:classifiers":[
        {
            "category":"Cafe",
            "type":"Food & Drink"
        }
    ],
    "sg:phone":"+32 3 766 35 37",
    "sg:postcode":"9100",
    "sg:province":"Oost-Vlaanderen",
    "sg:tags":[
        "caf\u00e9s"
    ],
    "wof:name":"Brasserie Sinte Marie",
    "wof:placetype":"venue"
},
  "geometry": {"coordinates":[4.1425080299,51.1639862061],"type":"Point"}
}