{
  "type": "Feature",
  "properties": {
    "addr:full":"Langendam 39a Evergem Oost-Vlaanderen 9940",
    "addr:housenumber":"39a",
    "addr:postcode":"9940",
    "addr:street":"Langendam;Oost-Vlaanderen",
    "iso:country":"BE",
    "sg:address":"Langendam 39a",
    "sg:city":"Evergem",
    "sg:orig_category":"Installation de menuiserie en bois and plastique",
    "sg:phone":"+32 9 357 38 60",
    "sg:postcode":"9940",
    "sg:province":"Oost-Vlaanderen",
    "wof:name":"Fa. Welvaert M. & Zn",
    "wof:placetype":"venue"
},
  "geometry": {"coordinates":[3.6556138992,51.1381454468],"type":"Point"}
}