{
  "type": "Feature",
  "properties": {
    "addr:full":"Slabbaardstraat-zuid 17 Izegem West-Vlaanderen 8870",
    "addr:housenumber":"17",
    "addr:postcode":"8870",
    "addr:street":"Slabbaardstraat-Zuid",
    "iso:country":"BE",
    "sg:address":"Slabbaardstraat-zuid 17",
    "sg:city":"Izegem",
    "sg:orig_category":"Brood, gebak and snoepgoed",
    "sg:phone":"+32 51 30 52 59",
    "sg:postcode":"8870",
    "sg:province":"West-Vlaanderen",
    "wof:name":"Marnix Cuypers",
    "wof:placetype":"venue"
},
  "geometry": {"coordinates":[3.2112720013,50.907371521],"type":"Point"}
}