{
  "type": "Feature",
  "properties": {
    "addr:full":"Itterbeekse Laan 59 Anderlecht Bruxelles-Capitale 1070",
    "addr:housenumber":"59",
    "addr:postcode":"1070",
    "addr:street":"Laan",
    "iso:country":"BE",
    "sg:address":"Itterbeekse Laan 59",
    "sg:city":"Anderlecht",
    "sg:orig_category":"Woningbouw",
    "sg:phone":"+32 2 523 38 39",
    "sg:postcode":"1070",
    "sg:province":"Bruxelles-Capitale",
    "wof:name":"P.a.r.",
    "wof:placetype":"venue"
},
  "geometry": {"coordinates":[4.2961769104,50.8357696533],"type":"Point"}
}