{
  "type": "Feature",
  "properties": {
    "iso:country":"BE",
    "sg:address":"Lindesteenweg 3",
    "sg:city":"Lo-reninge (pollinkhove)",
    "sg:classifiers":[
        {
            "category":"Building & Trades",
            "subcategory":"Landscaping Services",
            "type":"Services"
        }
    ],
    "sg:phone":"+32 58 28 82 42",
    "sg:postcode":"8647",
    "sg:province":"West-Vlaanderen",
    "sg:tags":[
        "architect",
        "landscape"
    ],
    "wof:name":"Robbe W",
    "wof:placetype":"venue"
},
  "geometry": {"coordinates":[2.7276740074,50.96434021],"type":"Point"}
}