{
  "type": "Feature",
  "properties": {
    "iso:country":"BE",
    "sg:address":"Rue Du Palais 1",
    "sg:city":"Verviers",
    "sg:orig_category":"Reliure and finition",
    "sg:phone":"+32 87 22 62 70",
    "sg:postcode":"4800",
    "sg:province":"Li\u00e8ge",
    "wof:name":"Michel Pirnay",
    "wof:placetype":"venue"
},
  "geometry": {"coordinates":[5.8648781776,50.5905075073],"type":"Point"}
}