{
  "type": "Feature",
  "properties": {
    "iso:country":"BE",
    "sg:address":"Binnenweg 13",
    "sg:city":"Duffel",
    "sg:classifiers":[
        {
            "category":"Manufacturing",
            "subcategory":"Metals",
            "type":"Manufacturing & Wholesale Goods"
        }
    ],
    "sg:phone":"+32 15 31 33 69",
    "sg:postcode":"2570",
    "sg:province":"Antwerpen",
    "sg:tags":[
        "ironwork"
    ],
    "wof:name":"Siersmederij Daems",
    "wof:placetype":"venue"
},
  "geometry": {"coordinates":[4.5143709183,51.0964660645],"type":"Point"}
}