{
  "type": "Feature",
  "properties": {
    "addr:full":"Brusselsesteenweg 382 Mechelen Antwerpen 2800",
    "addr:housenumber":"382",
    "addr:postcode":"2800",
    "addr:street":"Brusselsesteenweg",
    "iso:country":"BE",
    "sg:address":"Brusselsesteenweg 382",
    "sg:city":"Mechelen",
    "sg:orig_category":"Dierenartsen",
    "sg:phone":"+32 15 41 29 39",
    "sg:postcode":"2800",
    "sg:province":"Antwerpen",
    "wof:name":"Sara Geerens",
    "wof:placetype":"venue"
},
  "geometry": {"coordinates":[4.4740381241,51.0032806396],"type":"Point"}
}