{
  "type": "Feature",
  "properties": {
    "iso:country":"BE",
    "sg:address":"Rue Du Centre 54",
    "sg:city":"Sprimont",
    "sg:classifiers":[
        {
            "category":"Shopping",
            "subcategory":"Books",
            "type":"Retail Goods"
        }
    ],
    "sg:phone":"+32 4 382 22 67",
    "sg:postcode":"4140",
    "sg:province":"Li\u00e8ge",
    "sg:tags":[
        "bookseller"
    ],
    "wof:name":"Centre (librairie Papeterie Du)",
    "wof:placetype":"venue"
},
  "geometry": {"coordinates":[5.6619820595,50.5032043457],"type":"Point"}
}