{
  "type": "Feature",
  "properties": {
    "iso:country":"BE",
    "sg:address":"Weg Naar De Grauwe Steen 118",
    "sg:city":"Heusden-zolder",
    "sg:orig_category":"Slagers",
    "sg:phone":"+32 11 57 30 58",
    "sg:postcode":"3550",
    "sg:province":"Limburg",
    "wof:name":"Christien Schoofs",
    "wof:placetype":"venue"
},
  "geometry": {"coordinates":[5.3199119568,51.0568962097],"type":"Point"}
}