{
  "type": "Feature",
  "properties": {
    "addr:full":"Jules Moretuslei 480 Wilrijk Antwerpen 2610",
    "addr:housenumber":"480",
    "addr:postcode":"2610",
    "addr:street":"Jules Moretuslei;Antwerpen",
    "iso:country":"BE",
    "sg:address":"Jules Moretuslei 480",
    "sg:city":"Wilrijk",
    "sg:orig_category":"Rev\u00eatements de sols and murs. Traitement and fa\u00e7onnage de la pierre",
    "sg:phone":"+32 3 827 10 47",
    "sg:postcode":"2610",
    "sg:province":"Antwerpen",
    "wof:name":"F Opdebeeck",
    "wof:placetype":"venue"
},
  "geometry": {"coordinates":[4.3979091644,51.1725082397],"type":"Point"}
}