{
  "type": "Feature",
  "properties": {
    "addr:full":"Hillestraat 11 Maldegem Oost-Vlaanderen 9991",
    "addr:housenumber":"11",
    "addr:postcode":"9991",
    "addr:street":"Hillestraat",
    "iso:country":"BE",
    "sg:address":"Hillestraat 11",
    "sg:city":"Maldegem",
    "sg:classifiers":[
        {
            "category":"Insurance",
            "subcategory":"Life Insurance",
            "type":"Services"
        }
    ],
    "sg:phone":"+32 50 71 72 90",
    "sg:postcode":"9991",
    "sg:province":"Oost-Vlaanderen",
    "sg:tags":[
        "assurance"
    ],
    "wof:name":"Fa. Goethals",
    "wof:placetype":"venue"
},
  "geometry": {"coordinates":[3.49051404,51.2026672363],"type":"Point"}
}