{
  "type": "Feature",
  "properties": {
    "iso:country":"BE",
    "sg:address":"Sint-kristoffelstraat 6",
    "sg:city":"Londerzeel",
    "sg:classifiers":[
        {
            "category":"Wholesale",
            "subcategory":"Plants",
            "type":"Manufacturing & Wholesale Goods"
        }
    ],
    "sg:phone":"+32 52 30 91 21",
    "sg:postcode":"1840",
    "sg:province":"Vlaams-Brabant",
    "sg:tags":[
        "whol",
        "flower",
        "-",
        "grower"
    ],
    "wof:name":"De Pauw Gebr",
    "wof:placetype":"venue"
},
  "geometry": {"coordinates":[4.3090629578,51.0061759949],"type":"Point"}
}