{
  "type": "Feature",
  "properties": {
    "addr:full":"Rue De L'industrie 197 Frameries (la Bouverie) Hainaut 7080",
    "addr:housenumber":"197",
    "addr:postcode":"7080",
    "addr:street":"Rue De L'Industrie",
    "iso:country":"BE",
    "sg:address":"Rue De L'industrie 197",
    "sg:city":"Frameries (la Bouverie)",
    "sg:classifiers":[
        {
            "category":"Utilities",
            "subcategory":"Fuel Oil & Lpg",
            "type":"Services"
        }
    ],
    "sg:phone":"+32 65 67 27 39",
    "sg:postcode":"7080",
    "sg:province":"Hainaut",
    "wof:name":"S.a. Deberghes Et Fils Sa",
    "wof:placetype":"venue"
},
  "geometry": {"coordinates":[3.8860599995,50.4084243774],"type":"Point"}
}