{
  "type": "Feature",
  "properties": {
    "addr:full":"Boulevard Alfred De Fontaine 7 Charleroi Hainaut 6000",
    "addr:housenumber":"7",
    "addr:postcode":"6000",
    "addr:street":"Boulevard Alfred De Fontaine;Hainaut",
    "iso:country":"BE",
    "sg:address":"Boulevard Alfred De Fontaine 7",
    "sg:city":"Charleroi",
    "sg:orig_category":"Immobili\u00ebnkantoren",
    "sg:phone":"+32 71 33 13 62",
    "sg:postcode":"6000",
    "sg:province":"Hainaut",
    "wof:name":"Immobili\u00c8re Du Parc",
    "wof:placetype":"venue"
},
  "geometry": {"coordinates":[4.4461841583,50.4101104736],"type":"Point"}
}