{
  "type": "Feature",
  "properties": {
    "iso:country":"BE",
    "sg:address":"Kartuizersvest 99",
    "sg:city":"Lier",
    "sg:classifiers":[
        {
            "category":"Food & Beverages",
            "subcategory":"Groceries & Convenience Stores",
            "type":"Retail Goods"
        }
    ],
    "sg:phone":"+32 3 480 14 29",
    "sg:postcode":"2500",
    "sg:province":"Antwerpen",
    "sg:tags":[
        "grocer"
    ],
    "wof:name":"Claes J",
    "wof:placetype":"venue"
},
  "geometry": {"coordinates":[4.5707449913,51.1348152161],"type":"Point"}
}