{
  "type": "Feature",
  "properties": {
    "iso:country":"BE",
    "sg:address":"Albertstraat 7",
    "sg:city":"Merksplas",
    "sg:classifiers":[
        {
            "category":"Health Services",
            "subcategory":"Doctor",
            "type":"Services"
        }
    ],
    "sg:phone":"+32 14 63 32 94",
    "sg:postcode":"2330",
    "sg:province":"Antwerpen",
    "sg:tags":[
        "medicinephysicians",
        "surgeon"
    ],
    "wof:name":"De Sterck Walter",
    "wof:placetype":"venue"
},
  "geometry": {"coordinates":[4.8631868362,51.3565406799],"type":"Point"}
}