{
  "type": "Feature",
  "properties": {
    "addr:full":"Rue Thier Du Moulin 10ba Villers-le-bouillet Li\u00e8ge 4530",
    "addr:housenumber":"10ba",
    "addr:postcode":"4530",
    "addr:street":"Rue Thier Du Moulin",
    "iso:country":"BE",
    "sg:address":"Rue Thier Du Moulin 10ba",
    "sg:city":"Villers-le-bouillet",
    "sg:orig_category":"Elektrische installaties voor woningen",
    "sg:phone":"+32 85 21 61 53",
    "sg:postcode":"4530",
    "sg:province":"Li\u00e8ge",
    "wof:name":"Jacques Houpresse",
    "wof:placetype":"venue"
},
  "geometry": {"coordinates":[5.2780518532,50.5644340515],"type":"Point"}
}