{
  "type": "Feature",
  "properties": {
    "addr:full":"Boulevard Du Centenaire 1 Philippeville Namur 5600",
    "addr:housenumber":"1",
    "addr:postcode":"5600",
    "addr:street":"Boulevard Du Centenaire",
    "iso:country":"BE",
    "sg:address":"Boulevard Du Centenaire 1",
    "sg:city":"Philippeville",
    "sg:orig_category":"Newspapers, magazines, periodicals - Publishers",
    "sg:postcode":"5600",
    "sg:province":"Namur",
    "wof:name":"Vers L'avenir-le Rappel",
    "wof:placetype":"venue"
},
  "geometry": {"coordinates":[4.5394330025,50.195438385],"type":"Point"}
}