{
  "type": "Feature",
  "properties": {
    "iso:country":"BE",
    "sg:address":"Sijselestraat 48ba",
    "sg:city":"Beernem",
    "sg:orig_category":"Quincailleries. Fleurs and plantes. Souvenirs and objets artisanaux. Articles de jardin",
    "sg:phone":"+32 50 79 06 30",
    "sg:postcode":"8730",
    "sg:province":"West-Vlaanderen",
    "wof:name":"Tuinhobby St.marie",
    "wof:placetype":"venue"
},
  "geometry": {"coordinates":[3.3385639191,51.1746559143],"type":"Point"}
}