{
  "type": "Feature",
  "properties": {
    "addr:full":"Vrijheidslaan 12 Koekelberg/koekelberg Bruxelles-Capitale 1081",
    "addr:housenumber":"12",
    "addr:postcode":"1081",
    "addr:street":"Vrijheidslaan",
    "iso:country":"BE",
    "sg:address":"Vrijheidslaan 12",
    "sg:city":"Koekelberg/koekelberg",
    "sg:orig_category":"Artsen and specialisten",
    "sg:phone":"+32 2 420 12 10",
    "sg:postcode":"1081",
    "sg:province":"Bruxelles-Capitale",
    "wof:name":"Sophie Vercruysse",
    "wof:placetype":"venue"
},
  "geometry": {"coordinates":[4.3253440857,50.8627700806],"type":"Point"}
}