{
  "type": "Feature",
  "properties": {
    "iso:country":"BE",
    "sg:address":"Provinciestraat 1",
    "sg:city":"Duffel",
    "sg:classifiers":[
        {
            "category":"Insurance",
            "subcategory":"Insurance Agent",
            "type":"Services"
        }
    ],
    "sg:phone":"+32 15 31 61 82",
    "sg:postcode":"2570",
    "sg:province":"Antwerpen",
    "sg:tags":[
        "verzekeringsmakelaars",
        "expert"
    ],
    "wof:name":"Ph. Van De Poll",
    "wof:placetype":"venue"
},
  "geometry": {"coordinates":[4.5143280029,51.0940933228],"type":"Point"}
}