{
  "type": "Feature",
  "properties": {
    "iso:country":"BE",
    "sg:address":"Bokkerijdersweg 36",
    "sg:city":"Maaseik",
    "sg:orig_category":"Installatie van houten of kunststof schrijnwerk",
    "sg:phone":"+32 89 56 54 80",
    "sg:postcode":"3680",
    "sg:province":"Limburg",
    "wof:name":"Peter Verstappen",
    "wof:placetype":"venue"
},
  "geometry": {"coordinates":[5.7609171867,51.0854377747],"type":"Point"}
}