{
  "type": "Feature",
  "properties": {
    "iso:country":"BE",
    "sg:address":"Rue De L\u00b4aqueduc 8",
    "sg:city":"Brussel/bruxelles",
    "sg:orig_category":"Drukkerijen and copyshops",
    "sg:phone":"+32 2 538 05 04",
    "sg:postcode":"1060",
    "sg:province":"Bruxelles-Capitale",
    "wof:name":"Best Copy Shop",
    "wof:placetype":"venue"
},
  "geometry": {"coordinates":[4.3557958603,50.8254623413],"type":"Point"}
}