{
  "type": "Feature",
  "properties": {
    "addr:full":"Waverse Steenweg 1792 Oudergem/auderghem Bruxelles-Capitale 1160",
    "addr:postcode":"1792;1160",
    "addr:street":"Waverse Steenweg",
    "iso:country":"BE",
    "sg:address":"Waverse Steenweg 1792",
    "sg:city":"Oudergem/auderghem",
    "sg:orig_category":"Industri\u00eble wasserijen and droogkuis",
    "sg:phone":"+32 2 672 40 38",
    "sg:postcode":"1160",
    "sg:province":"Bruxelles-Capitale",
    "wof:name":"Nettoyage \u00c0 Sec Willems",
    "wof:placetype":"venue"
},
  "geometry": {"coordinates":[4.4332051277,50.8148345947],"type":"Point"}
}