{
  "type": "Feature",
  "properties": {
    "iso:country":"BE",
    "sg:address":"Veldstraat 233",
    "sg:city":"Brasschaat",
    "sg:classifiers":[
        {
            "category":"Building & Trades",
            "subcategory":"Construction",
            "type":"Services"
        }
    ],
    "sg:phone":"+32 3 722 01 23",
    "sg:postcode":"2930",
    "sg:province":"Antwerpen",
    "sg:tags":[
        "carpenter's",
        "work",
        "supraregional"
    ],
    "wof:name":"De Tender B.v.b.a.",
    "wof:placetype":"venue"
},
  "geometry": {"coordinates":[4.0922222137,51.1434135437],"type":"Point"}
}