{
  "type": "Feature",
  "properties": {
    "iso:country":"BE",
    "sg:address":"Quai De La Boverie 101",
    "sg:city":"Li\u00e8ge 1 (li\u00e8ge 2)",
    "sg:classifiers":[
        {
            "category":"Professional",
            "type":"Services"
        }
    ],
    "sg:phone":"+32 4 343 23 23",
    "sg:postcode":"4020",
    "sg:province":"Li\u00e8ge",
    "sg:tags":[
        "surveyor",
        "-",
        "valuer"
    ],
    "wof:name":"Culemme Fr",
    "wof:placetype":"venue"
},
  "geometry": {"coordinates":[5.5774011612,50.6301651001],"type":"Point"}
}