{
  "type": "Feature",
  "properties": {
    "addr:full":"Rue Des Grands Terrains 10 Namur Namur 5100",
    "addr:housenumber":"10",
    "addr:postcode":"5100",
    "addr:street":"Rue Des Grands Terrains",
    "iso:country":"BE",
    "sg:address":"Rue Des Grands Terrains 10",
    "sg:city":"Namur",
    "sg:orig_category":"Supermarkten",
    "sg:phone":"+32 81 74 19 02",
    "sg:postcode":"5100",
    "sg:province":"Namur",
    "wof:name":"Disnam",
    "wof:placetype":"venue"
},
  "geometry": {"coordinates":[4.8608698845,50.4262161255],"type":"Point"}
}