{
  "type": "Feature",
  "properties": {
    "iso:country":"BE",
    "sg:address":"Avenue S.m. Glorieux 5",
    "sg:city":"Ronse/renaix",
    "sg:orig_category":"Notaires",
    "sg:phone":"+32 55 21 89 06",
    "sg:postcode":"9600",
    "sg:province":"Oost-Vlaanderen",
    "wof:name":"Philippe Henrist",
    "wof:placetype":"venue"
},
  "geometry": {"coordinates":[3.5992999077,50.7470397949],"type":"Point"}
}