{
  "type": "Feature",
  "properties": {
    "addr:full":"Rue Albert I. 7 Eugies 7250",
    "addr:housenumber":"7",
    "addr:postcode":"7250",
    "addr:street":"Rue Albert I.",
    "iso:country":"BE",
    "sg:address":"Rue Albert I. 7",
    "sg:city":"Eugies",
    "sg:classifiers":[
        {
            "category":"Banks & Credit Unions",
            "subcategory":"Bank",
            "type":"Services"
        }
    ],
    "sg:phone":"+32 65 67 53 17",
    "sg:postcode":"7250",
    "wof:name":"Aslk-cger Bank",
    "wof:placetype":"venue"
},
  "geometry": {"coordinates":[3.8692040443,50.3925628662],"type":"Point"}
}