{
  "type": "Feature",
  "properties": {
    "addr:full":"Rue De L\u00b4yser 32 Tournai Hainaut 7500",
    "addr:housenumber":"32",
    "addr:postcode":"7500",
    "addr:street":"Rue De L\u00b4Yser",
    "iso:country":"BE",
    "sg:address":"Rue De L\u00b4yser 32",
    "sg:city":"Tournai",
    "sg:orig_category":"Art and fournitures artistiques",
    "sg:phone":"+32 69 84 69 72",
    "sg:postcode":"7500",
    "sg:province":"Hainaut",
    "wof:name":"Point Cadres",
    "wof:placetype":"venue"
},
  "geometry": {"coordinates":[3.3861999512,50.6073417664],"type":"Point"}
}