{
  "type": "Feature",
  "properties": {
    "iso:country":"BE",
    "sg:address":"Bevrijdingslaan 165",
    "sg:city":"Dendermonde",
    "sg:orig_category":"Chaussures. Maroquinerie and articles de voyage. V\u00eatements pour b\u00e9b\u00e9s and enfants. Articles de campi",
    "sg:phone":"+32 52 22 57 63",
    "sg:postcode":"9200",
    "sg:province":"Oost-Vlaanderen",
    "wof:name":"Huis Van Herreweghe",
    "wof:placetype":"venue"
},
  "geometry": {"coordinates":[4.052175045,51.0239562988],"type":"Point"}
}