{
  "type": "Feature",
  "properties": {
    "addr:full":"Omgeving Rooigem Zwembad Gent Oost-Vlaanderen 9000",
    "addr:postcode":"9000",
    "addr:street":"Oost-Vlaanderen",
    "iso:country":"BE",
    "sg:address":"Omgeving Rooigem Zwembad",
    "sg:city":"Gent",
    "sg:orig_category":"Etablissements Erotiques",
    "sg:phone":"+32 478 32 68 34",
    "sg:postcode":"9000",
    "sg:province":"Oost-Vlaanderen",
    "wof:name":"Kathie",
    "wof:placetype":"venue"
},
  "geometry": {"coordinates":[3.7057299614,51.0896453857],"type":"Point"}
}