{
  "type": "Feature",
  "properties": {
    "iso:country":"BE",
    "sg:address":"Rue De Louveign\u00c9 58",
    "sg:city":"Beaufays",
    "sg:orig_category":"Bloemen and planten Gh",
    "sg:phone":"+32 4 368 69 64",
    "sg:postcode":"4052",
    "sg:province":"Li\u00e8ge",
    "wof:name":"Sud Fleurs - Schepers",
    "wof:placetype":"venue"
},
  "geometry": {"coordinates":[5.644329071,50.5570487976],"type":"Point"}
}