{
  "type": "Feature",
  "properties": {
    "addr:full":"Prinses Clementinalaan 93 Gent Oost-Vlaanderen 9000",
    "addr:housenumber":"93",
    "addr:postcode":"9000",
    "addr:street":"Prinses Clementinalaan;Oost-Vlaanderen",
    "iso:country":"BE",
    "sg:address":"Prinses Clementinalaan 93",
    "sg:city":"Gent",
    "sg:classifiers":[
        {
            "category":"Health Services",
            "subcategory":"Health Practitioner",
            "type":"Services"
        }
    ],
    "sg:phone":"+32 9 221 06 51",
    "sg:postcode":"9000",
    "sg:province":"Oost-Vlaanderen",
    "sg:tags":[
        "psychologist"
    ],
    "wof:name":"Haesaert Peter",
    "wof:placetype":"venue"
},
  "geometry": {"coordinates":[3.7143609524,51.0351066589],"type":"Point"}
}