{
  "type": "Feature",
  "properties": {
    "addr:full":"Rue Saint-gilles 17 Li\u00c8ge Li\u00e8ge 4000",
    "addr:housenumber":"17",
    "addr:postcode":"4000",
    "addr:street":"Rue Saint-Gilles",
    "iso:country":"BE",
    "sg:address":"Rue Saint-gilles 17",
    "sg:city":"Li\u00c8ge",
    "sg:classifiers":[
        {
            "category":"Restaurant",
            "type":"Food & Drink"
        }
    ],
    "sg:phone":"+32 4 222 01 36",
    "sg:postcode":"4000",
    "sg:province":"Li\u00e8ge",
    "wof:name":"Aux Pates Fraiches",
    "wof:placetype":"venue"
},
  "geometry": {"coordinates":[5.5677099228,50.6396331787],"type":"Point"}
}