{
  "type": "Feature",
  "properties": {
    "addr:full":"Kapellestraat 34 Aartselaar Antwerpen 2630",
    "addr:housenumber":"34",
    "addr:postcode":"2630",
    "addr:street":"Kapellestraat",
    "iso:country":"BE",
    "sg:address":"Kapellestraat 34",
    "sg:city":"Aartselaar",
    "sg:classifiers":[
        {
            "category":"Sports & Exercise",
            "subcategory":"Sports Center",
            "type":"Entertainment"
        }
    ],
    "sg:phone":"+32 3 887 16 05",
    "sg:postcode":"2630",
    "sg:province":"Antwerpen",
    "sg:tags":[
        "de",
        "fitness"
    ],
    "wof:name":"Action Club Moving",
    "wof:placetype":"venue"
},
  "geometry": {"coordinates":[4.388548851,51.132484436],"type":"Point"}
}