{
  "type": "Feature",
  "properties": {
    "addr:full":"Heirbaan 107 Beveren (melsele) Oost-Vlaanderen 9120",
    "addr:housenumber":"107",
    "addr:postcode":"9120",
    "addr:street":"Heirbaan",
    "iso:country":"BE",
    "sg:address":"Heirbaan 107",
    "sg:city":"Beveren (melsele)",
    "sg:classifiers":[
        {
            "category":"Arts & Performance",
            "subcategory":"Art Gallery",
            "type":"Entertainment"
        }
    ],
    "sg:phone":"+32 3 755 17 48",
    "sg:postcode":"9120",
    "sg:province":"Oost-Vlaanderen",
    "wof:name":"Den Es",
    "wof:placetype":"venue"
},
  "geometry": {"coordinates":[4.2948870659,51.1901626587],"type":"Point"}
}