{
  "type": "Feature",
  "properties": {
    "addr:full":"Vossebeekstraat 21 Ichtegem West-Vlaanderen 8480",
    "addr:housenumber":"21",
    "addr:postcode":"8480",
    "addr:street":"Vossebeekstraat",
    "iso:country":"BE",
    "sg:address":"Vossebeekstraat 21",
    "sg:city":"Ichtegem",
    "sg:orig_category":"Diverse opleidingen and onderwijs Reisbureaus",
    "sg:phone":"+32 51 58 12 28",
    "sg:postcode":"8480",
    "sg:province":"West-Vlaanderen",
    "wof:name":"Cerfs-volants-english Playschool",
    "wof:placetype":"venue"
},
  "geometry": {"coordinates":[3.0210011005,51.0974578857],"type":"Point"}
}