{
  "type": "Feature",
  "properties": {
    "iso:country":"BE",
    "sg:address":"Nieuwlandstraat 33",
    "sg:city":"Zulte",
    "sg:classifiers":[
        {
            "category":"Food & Beverages",
            "subcategory":"Meat & Fish",
            "type":"Retail Goods"
        }
    ],
    "sg:phone":"+32 9 388 62 30",
    "sg:postcode":"9870",
    "sg:province":"Oost-Vlaanderen",
    "sg:tags":[
        "vi",
        "zeevruchten"
    ],
    "wof:name":"Bart Verstaen",
    "wof:placetype":"venue"
},
  "geometry": {"coordinates":[3.4657790661,50.9331321716],"type":"Point"}
}