{
  "type": "Feature",
  "properties": {
    "iso:country":"BE",
    "sg:address":"Rue Courtejoie 7-9",
    "sg:city":"Ciney",
    "sg:classifiers":[
        {
            "category":"Retail",
            "subcategory":"Laundry & Dry Cleaning",
            "type":"Services"
        }
    ],
    "sg:phone":"+32 83 21 27 09",
    "sg:postcode":"5590",
    "sg:province":"Namur",
    "sg:tags":[
        "dyer",
        "cleaner"
    ],
    "wof:name":"Vit-o-net",
    "wof:placetype":"venue"
},
  "geometry": {"coordinates":[5.1007289886,50.2951889038],"type":"Point"}
}