{
  "type": "Feature",
  "properties": {
    "iso:country":"BE",
    "sg:address":"Rue Louis De Brouck\u00c8re 47",
    "sg:city":"La Louvi\u00c8re",
    "sg:orig_category":"Schoonheidssalons",
    "sg:phone":"+32 64 22 00 41",
    "sg:postcode":"7100",
    "sg:province":"Hainaut",
    "wof:name":"Michel Forges",
    "wof:placetype":"venue"
},
  "geometry": {"coordinates":[4.189948082,50.4795074463],"type":"Point"}
}