{
  "type": "Feature",
  "properties": {
    "iso:country":"BE",
    "sg:address":"Fort Ii Straat 3",
    "sg:city":"Wommelgem",
    "sg:orig_category":"Mus\u00e9es and patrimoine culturel",
    "sg:phone":"+32 3 322 12 66",
    "sg:postcode":"2160",
    "sg:province":"Antwerpen",
    "wof:name":"Politiemuseum",
    "wof:placetype":"venue"
},
  "geometry": {"coordinates":[4.4911551476,51.2004013062],"type":"Point"}
}