{
  "type": "Feature",
  "properties": {
    "addr:full":"Shop.cent. Ronse/renaix Oost-Vlaanderen 9600",
    "addr:postcode":"9600",
    "addr:street":"Shop.Cent.",
    "iso:country":"BE",
    "sg:address":"Shop.cent.",
    "sg:city":"Ronse/renaix",
    "sg:orig_category":"Kapsalons",
    "sg:phone":"+32 55 21 62 04",
    "sg:postcode":"9600",
    "sg:province":"Oost-Vlaanderen",
    "wof:name":"Coiffure Sylviane",
    "wof:placetype":"venue"
},
  "geometry": {"coordinates":[3.5937650204,50.7490997314],"type":"Point"}
}