{
  "type": "Feature",
  "properties": {
    "addr:full":"Postweg 153 Sint-pieters-leeuw Vlaams-Brabant 1602",
    "addr:housenumber":"153",
    "addr:postcode":"1602",
    "addr:street":"Postweg",
    "iso:country":"BE",
    "sg:address":"Postweg 153",
    "sg:city":"Sint-pieters-leeuw",
    "sg:orig_category":"Banques and organismes de cr\u00e9dit",
    "sg:phone":"+32 2 569 07 76",
    "sg:postcode":"1602",
    "sg:province":"Vlaams-Brabant",
    "wof:name":"Bbl",
    "wof:placetype":"venue"
},
  "geometry": {"coordinates":[4.2333421707,50.8082046509],"type":"Point"}
}