{
  "type": "Feature",
  "properties": {
    "iso:country":"BE",
    "sg:address":"Rijselstraat 278",
    "sg:city":"Menen",
    "sg:classifiers":[
        {
            "category":"Shopping",
            "subcategory":"Tobacco",
            "type":"Retail Goods"
        }
    ],
    "sg:phone":"+32 56 51 22 49",
    "sg:postcode":"8930",
    "sg:province":"West-Vlaanderen",
    "sg:tags":[
        "cigarette",
        "-",
        "cigars"
    ],
    "wof:name":"Demuynck C",
    "wof:placetype":"venue"
},
  "geometry": {"coordinates":[3.127243042,50.7874107361],"type":"Point"}
}