{
  "type": "Feature",
  "properties": {
    "iso:country":"BE",
    "sg:address":"Ekselsebaan 39",
    "sg:city":"Hechtel-eksel (hechtel)",
    "sg:classifiers":[
        {
            "category":"Home & Garden",
            "subcategory":"Home Furnishings",
            "type":"Retail Goods"
        }
    ],
    "sg:phone":"+32 11 73 12 04",
    "sg:postcode":"3940",
    "sg:province":"Limburg",
    "sg:tags":[
        "-",
        "furniture"
    ],
    "wof:name":"Macolux Bvba",
    "wof:placetype":"venue"
},
  "geometry": {"coordinates":[5.364795208,51.1255340576],"type":"Point"}
}