{
  "type": "Feature",
  "properties": {
    "addr:full":"Chauss\u00c9e De Haecht 1265 Brussel/bruxelles Bruxelles-Capitale 1130",
    "addr:postcode":"1265;/ bruxelles;1130",
    "addr:street":"Chausse\u0301E De Haecht",
    "iso:country":"BE",
    "sg:address":"Chauss\u00c9e De Haecht 1265",
    "sg:city":"Brussel/bruxelles",
    "sg:classifiers":[
        {
            "category":"Autos & Motor Vehicles",
            "subcategory":"Fuel & Gas Station",
            "type":"Retail Goods"
        }
    ],
    "sg:phone":"+32 2 245 42 51",
    "sg:postcode":"1130",
    "sg:province":"Bruxelles-Capitale",
    "sg:tags":[
        "stations-service",
        "carburants"
    ],
    "wof:name":"Esso",
    "wof:placetype":"venue"
},
  "geometry": {"coordinates":[4.4145150185,50.8805847168],"type":"Point"}
}