{
  "type": "Feature",
  "properties": {
    "addr:full":"Pl De Brouck\u00e8re 15 Bruxelles Bruxelles-Capitale 1000",
    "addr:housenumber":"15",
    "addr:postcode":"1000",
    "addr:street":"Pl De Broucke\u0300Re",
    "iso:country":"BE",
    "sg:address":"Pl De Brouck\u00e8re 15",
    "sg:city":"Bruxelles",
    "sg:classifiers":[
        {
            "category":"Travel",
            "subcategory":"Hotels & Motels",
            "type":"Entertainment"
        }
    ],
    "sg:phone":"+32 2 219 09 23",
    "sg:postcode":"1000",
    "sg:province":"Bruxelles-Capitale",
    "sg:tags":[
        "hotels",
        "business",
        "restaurant"
    ],
    "wof:name":"Western Steak Houses Europe Sa",
    "wof:placetype":"venue"
},
  "geometry": {"coordinates":[4.3529529572,50.8511428833],"type":"Point"}
}