{
  "type": "Feature",
  "properties": {
    "addr:full":"Weeldestraat 57 Ravels (weelde) Antwerpen 2381",
    "addr:housenumber":"57",
    "addr:postcode":"2381",
    "addr:street":"Weeldestraat",
    "iso:country":"BE",
    "sg:address":"Weeldestraat 57",
    "sg:city":"Ravels (weelde)",
    "sg:classifiers":[
        {
            "category":"Professional",
            "subcategory":"Printing & Photocopies",
            "type":"Services"
        }
    ],
    "sg:phone":"+32 14 65 02 27",
    "sg:postcode":"2381",
    "sg:province":"Antwerpen",
    "sg:tags":[
        "silkscreen",
        "-"
    ],
    "wof:name":"Profisign",
    "wof:placetype":"venue"
},
  "geometry": {"coordinates":[5.006374836,51.4099845886],"type":"Point"}
}