{
  "type": "Feature",
  "properties": {
    "addr:full":"Aarschotsesteenweg 201 Rotselaar Vlaams-Brabant 3111",
    "addr:housenumber":"201",
    "addr:postcode":"3111",
    "addr:street":"Aarschotsesteenweg",
    "iso:country":"BE",
    "sg:address":"Aarschotsesteenweg 201",
    "sg:city":"Rotselaar",
    "sg:orig_category":"Banques and organismes de cr\u00e9dit",
    "sg:phone":"+32 16 58 91 10",
    "sg:postcode":"3111",
    "sg:province":"Vlaams-Brabant",
    "wof:name":"Kbc",
    "wof:placetype":"venue"
},
  "geometry": {"coordinates":[4.7529411316,50.9482460022],"type":"Point"}
}