{
  "type": "Feature",
  "properties": {
    "addr:full":"Rue Sylvain Guyaux 48 La Louvi\u00e8re Hainaut 7100",
    "addr:housenumber":"48",
    "addr:postcode":"7100",
    "addr:street":"Rue Sylvain Guyaux",
    "iso:country":"BE",
    "sg:address":"Rue Sylvain Guyaux 48",
    "sg:city":"La Louvi\u00e8re",
    "sg:classifiers":[
        {
            "category":"Food & Beverages",
            "subcategory":"Groceries & Convenience Stores",
            "type":"Retail Goods"
        }
    ],
    "sg:phone":"+32 64 22 91 98",
    "sg:postcode":"7100",
    "sg:province":"Hainaut",
    "sg:tags":[
        "grocer"
    ],
    "wof:name":"Mercatone Sprl",
    "wof:placetype":"venue"
},
  "geometry": {"coordinates":[4.1846551895,50.4755935669],"type":"Point"}
}