{
  "type": "Feature",
  "properties": {
    "addr:full":"Olmenbosstraat 25 Kuringen Limburg 3511",
    "addr:housenumber":"25",
    "addr:postcode":"3511",
    "addr:street":"Olmenbosstraat",
    "iso:country":"BE",
    "sg:address":"Olmenbosstraat 25",
    "sg:city":"Kuringen",
    "sg:classifiers":[
        {
            "category":"Social Services",
            "subcategory":"Job Training",
            "type":"Services"
        }
    ],
    "sg:phone":"+32 11 25 22 48",
    "sg:postcode":"3511",
    "sg:province":"Limburg",
    "sg:tags":[
        "tiling",
        "fa\u00e7ade"
    ],
    "wof:name":"Knaepen Gevelbepleisteringen B.v.b.a.",
    "wof:placetype":"venue"
},
  "geometry": {"coordinates":[5.3034238815,50.9432487488],"type":"Point"}
}