{
  "type": "Feature",
  "properties": {
    "iso:country":"BE",
    "sg:address":"Marie-louiselaan 24/1",
    "sg:city":"Dilbeek",
    "sg:orig_category":"Loodgieterij, verwarming and sanitaire installaties",
    "sg:phone":"+32 75893892",
    "sg:postcode":"1700",
    "sg:province":"Vlaams-Brabant",
    "wof:name":"Dubois J-cl.",
    "wof:placetype":"venue"
},
  "geometry": {"coordinates":[4.2831559181,50.8484611511],"type":"Point"}
}