{
  "type": "Feature",
  "properties": {
    "iso:country":"BE",
    "sg:address":"Vijfstraten 2",
    "sg:city":"Sint-niklaas",
    "sg:orig_category":"R\u00e9parations d'appareils \u00e9lectrom\u00e9nagers. Electrom\u00e9nager, t\u00e9l\u00e9visions and radios. Plomberie, chauffag",
    "sg:phone":"+32 3 776 15 05",
    "sg:postcode":"9100",
    "sg:province":"Oost-Vlaanderen",
    "wof:name":"Huis Cogen & Van Hove",
    "wof:placetype":"venue"
},
  "geometry": {"coordinates":[4.1507902145,51.1732559204],"type":"Point"}
}