{
  "type": "Feature",
  "properties": {
    "addr:full":"Tinhoutstraat 137 Beernem West-Vlaanderen 8730",
    "addr:housenumber":"137",
    "addr:postcode":"8730",
    "addr:street":"Tinhoutstraat",
    "iso:country":"BE",
    "sg:address":"Tinhoutstraat 137",
    "sg:city":"Beernem",
    "sg:orig_category":"Enseignement maternel and primaire",
    "sg:phone":"+32 50 79 04 54",
    "sg:postcode":"8730",
    "sg:province":"West-Vlaanderen",
    "wof:name":"Vrije Basisschool",
    "wof:placetype":"venue"
},
  "geometry": {"coordinates":[3.3917019367,51.1618232727],"type":"Point"}
}