{
  "type": "Feature",
  "properties": {
    "iso:country":"BE",
    "sg:address":"Rue Du Calvaire 57",
    "sg:city":"Floreffe (frani\u00e8re)",
    "sg:classifiers":[
        {
            "category":"Parking",
            "subcategory":"Lot",
            "type":"Transportation"
        }
    ],
    "sg:phone":"+32 81 44 15 46",
    "sg:postcode":"5150",
    "sg:province":"Namur",
    "sg:tags":[
        "armoured",
        "door",
        "fireproof"
    ],
    "wof:name":"Kbs Systems",
    "wof:placetype":"venue"
},
  "geometry": {"coordinates":[4.7222251892,50.4354782104],"type":"Point"}
}