{
  "type": "Feature",
  "properties": {
    "iso:country":"BE",
    "sg:address":"Wallenhof 3",
    "sg:city":"Sint-gillis-waas",
    "sg:orig_category":"Elektrische installaties voor woningen",
    "sg:phone":"+32 3 766 57 93",
    "sg:postcode":"9170",
    "sg:province":"Oost-Vlaanderen",
    "wof:name":"Van Acker Jan",
    "wof:placetype":"venue"
},
  "geometry": {"coordinates":[4.0963249207,51.1923065186],"type":"Point"}
}