{
  "type": "Feature",
  "properties": {
    "addr:full":"Streepstraat 121 Kapellen Antwerpen 2950",
    "addr:housenumber":"121",
    "addr:postcode":"2950",
    "addr:street":"Streepstraat",
    "iso:country":"BE",
    "sg:address":"Streepstraat 121",
    "sg:city":"Kapellen",
    "sg:classifiers":[
        {
            "category":"Home & Garden",
            "subcategory":"Home Furnishings",
            "type":"Retail Goods"
        }
    ],
    "sg:phone":"+32 3 605 44 84",
    "sg:postcode":"2950",
    "sg:province":"Antwerpen",
    "sg:tags":[
        "interior",
        "decoration"
    ],
    "wof:name":"Soetewey Woondecoratie",
    "wof:placetype":"venue"
},
  "geometry": {"coordinates":[4.4200158119,51.3170013428],"type":"Point"}
}