{
  "type": "Feature",
  "properties": {
    "addr:full":"Chauss\u00e9e De Mons 5b Box 26 Nivelles Brabant Wallon 1400",
    "addr:housenumber":"5b box 26",
    "addr:postcode":"1400",
    "addr:street":"Chausse\u0301E De Mons",
    "iso:country":"BE",
    "sg:address":"Chauss\u00e9e De Mons 5b Box 26",
    "sg:city":"Nivelles",
    "sg:classifiers":[
        {
            "category":"Professional",
            "subcategory":"Lawyer & Legal Services",
            "type":"Services"
        }
    ],
    "sg:phone":"+32 67 33 64 55",
    "sg:postcode":"1400",
    "sg:province":"Brabant Wallon",
    "wof:name":"Colautti St\u00e9phanie",
    "wof:placetype":"venue"
},
  "geometry": {"coordinates":[4.3142609596,50.5899963379],"type":"Point"}
}