{
  "type": "Feature",
  "properties": {
    "iso:country":"BE",
    "sg:address":"Albrecht Rodenbachstraat",
    "sg:city":"Oostkamp",
    "sg:classifiers":[
        {
            "category":"Arena",
            "subcategory":"Sports Club",
            "type":"Entertainment"
        }
    ],
    "sg:phone":"+32 50 82 44 64",
    "sg:postcode":"8020",
    "sg:province":"West-Vlaanderen",
    "wof:name":"S V Oostkamp",
    "wof:placetype":"venue"
},
  "geometry": {"coordinates":[3.2357521057,51.160369873],"type":"Point"}
}