{
  "type": "Feature",
  "properties": {
    "iso:country":"BE",
    "sg:address":"Rue De Messines 2",
    "sg:city":"Comines-warneton (ploegsteert)",
    "sg:classifiers":[
        {
            "category":"Bakery",
            "type":"Food & Drink"
        }
    ],
    "sg:phone":"+32 56 58 95 18",
    "sg:postcode":"7782",
    "sg:province":"Hainaut",
    "sg:tags":[
        "confectioner",
        "baker"
    ],
    "wof:name":"Isabelle",
    "wof:placetype":"venue"
},
  "geometry": {"coordinates":[2.8795371056,50.7278747559],"type":"Point"}
}