{
  "type": "Feature",
  "properties": {
    "iso:country":"BE",
    "sg:address":"An Der Lei 8",
    "sg:city":"B\u00dctgenbach/b\u00dctgenbach",
    "sg:orig_category":"Elektrische installaties voor woningen",
    "sg:phone":"+32 80 44 72 56",
    "sg:postcode":"4750",
    "sg:province":"Li\u00e8ge",
    "wof:name":"Elmar Sarlette",
    "wof:placetype":"venue"
},
  "geometry": {"coordinates":[6.2206501961,50.457408905],"type":"Point"}
}