{
  "type": "Feature",
  "properties": {
    "addr:full":"Schambraken 9e Olen Antwerpen 2250",
    "addr:housenumber":"9e",
    "addr:postcode":"2250",
    "addr:street":"Schambraken",
    "iso:country":"BE",
    "sg:address":"Schambraken 9e",
    "sg:city":"Olen",
    "sg:classifiers":[
        {
            "category":"Building & Trades",
            "subcategory":"Construction",
            "type":"Services"
        }
    ],
    "sg:phone":"+32 14 22 37 13",
    "sg:postcode":"2250",
    "sg:province":"Antwerpen",
    "sg:tags":[
        "stucco",
        "contractor"
    ],
    "wof:name":"De Prins Jan Plafonneerwerken Bvba",
    "wof:placetype":"venue"
},
  "geometry": {"coordinates":[4.9066100121,51.1580200195],"type":"Point"}
}