{
  "type": "Feature",
  "properties": {
    "iso:country":"BE",
    "sg:address":"Avenue Coghen 29",
    "sg:city":"Ukkel/uccle",
    "sg:orig_category":"Architectes",
    "sg:phone":"+32 2 343 06 01",
    "sg:postcode":"1180",
    "sg:province":"Bruxelles-Capitale",
    "wof:name":"Laurent Van Eyck",
    "wof:placetype":"venue"
},
  "geometry": {"coordinates":[4.3400149345,50.8127403259],"type":"Point"}
}