{
  "type": "Feature",
  "properties": {
    "iso:country":"BE",
    "sg:address":"Zeldonkstraat 40",
    "sg:city":"Beernem",
    "sg:orig_category":"Plomberie, chauffage and installations sanitaires",
    "sg:phone":"+32 50 78 93 65",
    "sg:postcode":"8730",
    "sg:province":"West-Vlaanderen",
    "wof:name":"Fa. Vandenbussche G. & Zn",
    "wof:placetype":"venue"
},
  "geometry": {"coordinates":[3.3813779354,51.1417655945],"type":"Point"}
}