{
  "type": "Feature",
  "properties": {
    "iso:country":"BE",
    "sg:address":"Smetledesteenweg 301",
    "sg:city":"Wetteren",
    "sg:orig_category":"P\u00e9pini\u00e9ristes",
    "sg:phone":"+32 9 369 52 55",
    "sg:postcode":"9230",
    "sg:province":"Oost-Vlaanderen",
    "wof:name":"Marc Goeman",
    "wof:placetype":"venue"
},
  "geometry": {"coordinates":[3.9068579674,50.9806632996],"type":"Point"}
}