{
  "type": "Feature",
  "properties": {
    "addr:full":"Rue De La Sambre 52 Erquelinnes Hainaut 6560",
    "addr:housenumber":"52",
    "addr:postcode":"6560",
    "addr:street":"Rue De La Sambre",
    "iso:country":"BE",
    "sg:address":"Rue De La Sambre 52",
    "sg:city":"Erquelinnes",
    "sg:classifiers":[
        {
            "category":"Manufacturing",
            "subcategory":"Metals",
            "type":"Manufacturing & Wholesale Goods"
        }
    ],
    "sg:phone":"+32 71 55 39 00",
    "sg:postcode":"6560",
    "sg:province":"Hainaut",
    "sg:tags":[
        "ornamental",
        "work",
        "-"
    ],
    "wof:name":"Dartevelle J",
    "wof:placetype":"venue"
},
  "geometry": {"coordinates":[4.1336731911,50.3099594116],"type":"Point"}
}