{
  "type": "Feature",
  "properties": {
    "addr:full":"Rue Des Deux Eglises 26 Bruxelles Bruxelles-Capitale 1000",
    "addr:housenumber":"26",
    "addr:postcode":"1000",
    "addr:street":"Rue Des Deux Eglises",
    "iso:country":"BE",
    "sg:address":"Rue Des Deux Eglises 26",
    "sg:city":"Bruxelles",
    "sg:classifiers":[
        {
            "category":"Utilities",
            "subcategory":"Cable",
            "type":"Services"
        }
    ],
    "sg:phone":"+32 2 226 52 11",
    "sg:postcode":"1000",
    "sg:province":"Bruxelles-Capitale",
    "sg:tags":[
        "tv",
        "installation"
    ],
    "wof:name":"Coditel S.a.",
    "wof:placetype":"venue"
},
  "geometry": {"coordinates":[4.3724789619,50.8463287354],"type":"Point"}
}