{
  "type": "Feature",
  "properties": {
    "iso:country":"BE",
    "sg:address":"Rue De Wavre 21",
    "sg:city":"Beauvechain",
    "sg:classifiers":[
        {
            "category":"Health Services",
            "subcategory":"Health Practitioner",
            "type":"Services"
        }
    ],
    "sg:phone":"+32 10 86 04 95",
    "sg:postcode":"1320",
    "sg:province":"Brabant Wallon",
    "sg:tags":[
        "physiotherapist"
    ],
    "wof:name":"Boils R",
    "wof:placetype":"venue"
},
  "geometry": {"coordinates":[4.7838978767,50.7757530212],"type":"Point"}
}