{
  "type": "Feature",
  "properties": {
    "addr:full":"Turnhoutsebaan 328a Schilde Antwerpen 2970",
    "addr:housenumber":"328a",
    "addr:postcode":"2970",
    "addr:street":"Turnhoutsebaan",
    "iso:country":"BE",
    "sg:address":"Turnhoutsebaan 328a",
    "sg:city":"Schilde",
    "sg:classifiers":[
        {
            "category":"Food & Beverages",
            "subcategory":"Cheese",
            "type":"Retail Goods"
        }
    ],
    "sg:phone":"+32 3 385 39 77",
    "sg:postcode":"2970",
    "sg:province":"Antwerpen",
    "sg:tags":[
        "-"
    ],
    "wof:name":"Martens Kaasmeester",
    "wof:placetype":"venue"
},
  "geometry": {"coordinates":[4.5851659775,51.2414169312],"type":"Point"}
}