{
  "type": "Feature",
  "properties": {
    "iso:country":"BE",
    "sg:address":"Rozenstraat 145",
    "sg:city":"Lokeren",
    "sg:orig_category":"Salles de billard and snooker",
    "sg:phone":"+32 9 348 82 24",
    "sg:postcode":"9160",
    "sg:province":"Oost-Vlaanderen",
    "wof:name":"Snookerhal De Roos",
    "wof:placetype":"venue"
},
  "geometry": {"coordinates":[4.014857769,51.1139678955],"type":"Point"}
}