{
  "type": "Feature",
  "properties": {
    "addr:full":"Rue Houtart 28 La Louvi\u00e8re (houdeng-goegnies) Hainaut 7110",
    "addr:housenumber":"28",
    "addr:postcode":"7110",
    "addr:street":"Rue Houtart",
    "iso:country":"BE",
    "sg:address":"Rue Houtart 28",
    "sg:city":"La Louvi\u00e8re (houdeng-goegnies)",
    "sg:classifiers":[
        {
            "category":"Professional",
            "subcategory":"Lawyer & Legal Services",
            "type":"Services"
        }
    ],
    "sg:phone":"+32 64 22 13 52",
    "sg:postcode":"7110",
    "sg:province":"Hainaut",
    "sg:tags":[
        "notary"
    ],
    "wof:name":"Bricout Th",
    "wof:placetype":"venue"
},
  "geometry": {"coordinates":[4.1505050659,50.4826698303],"type":"Point"}
}