{
  "type": "Feature",
  "properties": {
    "addr:full":"Testeltsesteenweg 237 Aarschot Vlaams-Brabant 3201",
    "addr:housenumber":"237",
    "addr:postcode":"3201",
    "addr:street":"Testeltsesteenweg",
    "iso:country":"BE",
    "sg:address":"Testeltsesteenweg 237",
    "sg:city":"Aarschot",
    "sg:orig_category":"Rundveehouders",
    "sg:phone":"+32 16 56 71 08",
    "sg:postcode":"3201",
    "sg:province":"Vlaams-Brabant",
    "wof:name":"Ronny Serre",
    "wof:placetype":"venue"
},
  "geometry": {"coordinates":[4.9112510681,51.0065002441],"type":"Point"}
}