{
  "type": "Feature",
  "properties": {
    "iso:country":"BE",
    "sg:address":"Stationplein 38",
    "sg:city":"Moeskroen/mouscron",
    "sg:classifiers":[
        {
            "category":"Restaurant",
            "type":"Food & Drink"
        }
    ],
    "sg:phone":"+32 56 34 45 67",
    "sg:postcode":"7700",
    "sg:province":"Hainaut",
    "sg:tags":[
        "caf\u00e9s"
    ],
    "wof:name":"Snack-bar Pyramide",
    "wof:placetype":"venue"
},
  "geometry": {"coordinates":[3.2323200703,50.7400932312],"type":"Point"}
}