{
  "type": "Feature",
  "properties": {
    "iso:country":"BE",
    "sg:address":"Bruggestraat 16",
    "sg:city":"Staden",
    "sg:classifiers":[
        {
            "category":"Retail",
            "subcategory":"Auto Repair",
            "type":"Services"
        }
    ],
    "sg:phone":"+32 51 70 10 92",
    "sg:postcode":"8840",
    "sg:province":"West-Vlaanderen",
    "sg:tags":[
        "garage"
    ],
    "wof:name":"Vandermeulen G",
    "wof:placetype":"venue"
},
  "geometry": {"coordinates":[3.0165960789,50.9748916626],"type":"Point"}
}