{
  "type": "Feature",
  "properties": {
    "iso:country":"BE",
    "sg:address":"Tremelobaan 122",
    "sg:city":"Keerbergen",
    "sg:classifiers":[
        {
            "category":"Professional",
            "subcategory":"Accounting & Tax Preparation",
            "type":"Services"
        }
    ],
    "sg:phone":"+32 16 53 61 90",
    "sg:postcode":"3140",
    "sg:province":"Vlaams-Brabant",
    "sg:tags":[
        "bookkeeper"
    ],
    "wof:name":"Baumans-beukenhout & Partners Bvba",
    "wof:placetype":"venue"
},
  "geometry": {"coordinates":[4.6705980301,50.9961013794],"type":"Point"}
}