{
  "type": "Feature",
  "properties": {
    "addr:full":"Sint-antoniusplein 3 Oostende West-Vlaanderen 8400",
    "addr:housenumber":"3",
    "addr:postcode":"8400",
    "addr:street":"Sint-Antoniusplein",
    "iso:country":"BE",
    "sg:address":"Sint-antoniusplein 3",
    "sg:city":"Oostende",
    "sg:classifiers":[
        {
            "category":"Health Services",
            "subcategory":"Health Practitioner",
            "type":"Services"
        }
    ],
    "sg:phone":"+32 59 33 00 08",
    "sg:postcode":"8400",
    "sg:province":"West-Vlaanderen",
    "sg:tags":[
        "physiotherapist"
    ],
    "wof:name":"Boucart C",
    "wof:placetype":"venue"
},
  "geometry": {"coordinates":[2.9430530071,51.2311668396],"type":"Point"}
}