{
  "type": "Feature",
  "properties": {
    "iso:country":"BE",
    "sg:address":"Parc De La Gotte 89",
    "sg:city":"Nandrin",
    "sg:classifiers":[
        {
            "category":"Insurance",
            "subcategory":"Insurance Agent",
            "type":"Services"
        }
    ],
    "sg:phone":"+32 4 372 02 79",
    "sg:postcode":"4550",
    "sg:province":"Li\u00e8ge",
    "sg:tags":[
        "verzekeringsmakelaars",
        "expert"
    ],
    "wof:name":"Michel De Biolley",
    "wof:placetype":"venue"
},
  "geometry": {"coordinates":[5.4325098991,50.5249710083],"type":"Point"}
}