{
  "type": "Feature",
  "properties": {
    "addr:full":"Aartrijkestraat 24 Ichtegem West-Vlaanderen 8480",
    "addr:housenumber":"24",
    "addr:postcode":"8480",
    "addr:street":"Aartrijkestraat",
    "iso:country":"BE",
    "sg:address":"Aartrijkestraat 24",
    "sg:city":"Ichtegem",
    "sg:orig_category":"Apotheken",
    "sg:phone":"+32 59 29 92 72",
    "sg:postcode":"8480",
    "sg:province":"West-Vlaanderen",
    "wof:name":"Marie-rose Langerock",
    "wof:placetype":"venue"
},
  "geometry": {"coordinates":[3.0286779404,51.1278953552],"type":"Point"}
}