{
  "type": "Feature",
  "properties": {
    "addr:full":"Rozenlaan 5 Wachtebeke Oost-Vlaanderen 9185",
    "addr:housenumber":"5",
    "addr:postcode":"9185",
    "addr:street":"Rozenlaan",
    "iso:country":"BE",
    "sg:address":"Rozenlaan 5",
    "sg:city":"Wachtebeke",
    "sg:classifiers":[
        {
            "category":"Shopping",
            "subcategory":"Clothing, Apparel, & Fashions",
            "type":"Retail Goods"
        }
    ],
    "sg:phone":"+32 9 345 02 87",
    "sg:postcode":"9185",
    "sg:province":"Oost-Vlaanderen",
    "sg:tags":[
        "leather",
        "-",
        "buckskin",
        "clothing"
    ],
    "wof:name":"Descamps O",
    "wof:placetype":"venue"
},
  "geometry": {"coordinates":[3.8599290848,51.1724357605],"type":"Point"}
}