{
  "type": "Feature",
  "properties": {
    "addr:full":"Rue Des B\u00e9guines 42-46 Bruxelles Bruxelles-Capitale 1080",
    "addr:housenumber":"42-46",
    "addr:postcode":"1080",
    "addr:street":"Rue Des Be\u0301Guines",
    "iso:country":"BE",
    "sg:address":"Rue Des B\u00e9guines 42-46",
    "sg:city":"Bruxelles",
    "sg:classifiers":[
        {
            "category":"Autos & Motor Vehicles",
            "subcategory":"Automobile Sales",
            "type":"Retail Goods"
        }
    ],
    "sg:phone":"+32 2 268 00 00",
    "sg:postcode":"1080",
    "sg:province":"Bruxelles-Capitale",
    "sg:tags":[
        "equipment",
        "motor-cars",
        "transport"
    ],
    "wof:name":"Blue Cabs Sa",
    "wof:placetype":"venue"
},
  "geometry": {"coordinates":[4.3169960976,50.8574829102],"type":"Point"}
}