{
  "type": "Feature",
  "properties": {
    "addr:full":"Rue St\u00e9phanie 63 Bruxelles Bruxelles-Capitale 1020",
    "addr:housenumber":"63",
    "addr:postcode":"1020",
    "addr:street":"Rue Ste\u0301Phanie",
    "iso:country":"BE",
    "sg:address":"Rue St\u00e9phanie 63",
    "sg:city":"Bruxelles",
    "sg:classifiers":[
        {
            "category":"Health Services",
            "subcategory":"Doctor",
            "type":"Services"
        }
    ],
    "sg:phone":"+32 2 426 44 12",
    "sg:postcode":"1020",
    "sg:province":"Bruxelles-Capitale",
    "sg:tags":[
        "medicinephysicians",
        "surgeon"
    ],
    "wof:name":"De Smet Ghislaine",
    "wof:placetype":"venue"
},
  "geometry": {"coordinates":[4.3534722328,50.8772621155],"type":"Point"}
}