{
  "type": "Feature",
  "properties": {
    "addr:full":"Rue De La Station 9 Ans Li\u00e8ge 4430",
    "addr:housenumber":"9",
    "addr:postcode":"4430",
    "addr:street":"Rue De La Station",
    "iso:country":"BE",
    "sg:address":"Rue De La Station 9",
    "sg:city":"Ans",
    "sg:classifiers":[
        {
            "category":"Shopping",
            "subcategory":"Clothing, Apparel, & Fashions",
            "type":"Retail Goods"
        }
    ],
    "sg:phone":"+32 4 263 77 76",
    "sg:postcode":"4430",
    "sg:province":"Li\u00e8ge",
    "sg:tags":[
        "underwear",
        "lingerie",
        "-"
    ],
    "wof:name":"Socks And Co",
    "wof:placetype":"venue"
},
  "geometry": {"coordinates":[5.5113658905,50.6635322571],"type":"Point"}
}