{
  "type": "Feature",
  "properties": {
    "addr:full":"Avenue De La Brise 9 Braine-l`alleud Brabant Wallon 1420",
    "addr:housenumber":"9",
    "addr:postcode":"1420",
    "addr:street":"Avenue De La Brise;Brabant Wallon",
    "iso:country":"BE",
    "sg:address":"Avenue De La Brise 9",
    "sg:city":"Braine-l`alleud",
    "sg:orig_category":"Diverse bedrijfsbeheeradviesbureaus",
    "sg:phone":"+32 2 354 19 47",
    "sg:postcode":"1420",
    "sg:province":"Brabant Wallon",
    "wof:name":"Socathi",
    "wof:placetype":"venue"
},
  "geometry": {"coordinates":[5.8036999702,45.9799995422],"type":"Point"}
}