{
  "type": "Feature",
  "properties": {
    "iso:country":"BE",
    "sg:address":"Oscar Verschuerestraat 40 Box 3",
    "sg:city":"Waregem",
    "sg:classifiers":[
        {
            "category":"Professional",
            "subcategory":"Employment Agencies",
            "type":"Services"
        }
    ],
    "sg:phone":"+32 56 71 08 82",
    "sg:postcode":"8790",
    "sg:province":"West-Vlaanderen",
    "sg:tags":[
        "model",
        "modelling"
    ],
    "wof:name":"Modellenbureau Taelman",
    "wof:placetype":"venue"
},
  "geometry": {"coordinates":[3.4292020798,50.8867759705],"type":"Point"}
}