{
  "type": "Feature",
  "properties": {
    "addr:full":"Kruisstraat 33 Sint-niklaas (belsele) Oost-Vlaanderen 9111",
    "addr:housenumber":"33",
    "addr:postcode":"9111",
    "addr:street":"Kruisstraat",
    "iso:country":"BE",
    "sg:address":"Kruisstraat 33",
    "sg:city":"Sint-niklaas (belsele)",
    "sg:classifiers":[
        {
            "category":"Banks & Credit Unions",
            "subcategory":"Investment Brokerage",
            "type":"Services"
        }
    ],
    "sg:phone":"+32 3 772 62 94",
    "sg:postcode":"9111",
    "sg:province":"Oost-Vlaanderen",
    "sg:tags":[
        "repair",
        "-",
        "installation",
        "sanitary",
        "article"
    ],
    "wof:name":"Roof",
    "wof:placetype":"venue"
},
  "geometry": {"coordinates":[4.0671720505,51.1723823547],"type":"Point"}
}