{
  "type": "Feature",
  "properties": {
    "addr:full":"Bollestraat 55 Overijse Vlaams-Brabant 3090",
    "addr:housenumber":"55",
    "addr:postcode":"3090",
    "addr:street":"Bollestraat",
    "iso:country":"BE",
    "sg:address":"Bollestraat 55",
    "sg:city":"Overijse",
    "sg:orig_category":"Kapsalons",
    "sg:phone":"+32 16 77 71 63",
    "sg:postcode":"3090",
    "sg:province":"Vlaams-Brabant",
    "wof:name":"Imelda Verheyden",
    "wof:placetype":"venue"
},
  "geometry": {"coordinates":[4.5914998055,50.7695808411],"type":"Point"}
}