{
  "type": "Feature",
  "properties": {
    "iso:country":"BE",
    "sg:address":"Langestraat 39",
    "sg:city":"Oostende",
    "sg:orig_category":"Bioscopen",
    "sg:phone":"+32 59 70 61 58",
    "sg:postcode":"8400",
    "sg:province":"West-Vlaanderen",
    "wof:name":"Cin\u00c9 Rialto",
    "wof:placetype":"venue"
},
  "geometry": {"coordinates":[2.9151248932,51.2320518494],"type":"Point"}
}