{
  "type": "Feature",
  "properties": {
    "addr:full":"Bld E Bockstael 218 Bruxelles Bruxelles-Capitale 1020",
    "addr:housenumber":"218",
    "addr:postcode":"1020",
    "addr:street":"Bld E Bockstael",
    "iso:country":"BE",
    "sg:address":"Bld E Bockstael 218",
    "sg:city":"Bruxelles",
    "sg:orig_category":"Kapsalons",
    "sg:phone":"+32 2 428 35 05",
    "sg:postcode":"1020",
    "sg:province":"Bruxelles-Capitale",
    "wof:name":"Boite A Coiffure (la)",
    "wof:placetype":"venue"
},
  "geometry": {"coordinates":[4.3473072052,50.8750534058],"type":"Point"}
}