{
  "type": "Feature",
  "properties": {
    "addr:full":"Hollestraat 55 Galmaarden Vlaams-Brabant 1570",
    "addr:housenumber":"55",
    "addr:postcode":"1570",
    "addr:street":"Hollestraat",
    "iso:country":"BE",
    "sg:address":"Hollestraat 55",
    "sg:city":"Galmaarden",
    "sg:classifiers":[
        {
            "category":"Insurance",
            "subcategory":"Insurance Agent",
            "type":"Services"
        }
    ],
    "sg:phone":"+32 54 58 82 37",
    "sg:postcode":"1570",
    "sg:province":"Vlaams-Brabant",
    "sg:tags":[
        "verzekeringsmakelaars",
        "expert"
    ],
    "wof:name":"Fiduc. Ost & Deneyer",
    "wof:placetype":"venue"
},
  "geometry": {"coordinates":[3.991863966,50.7525749207],"type":"Point"}
}