{
  "type": "Feature",
  "properties": {
    "addr:full":"Schransstraat 15 Grobbendonk Antwerpen 2280",
    "addr:housenumber":"15",
    "addr:postcode":"2280",
    "addr:street":"Schransstraat",
    "iso:country":"BE",
    "sg:address":"Schransstraat 15",
    "sg:city":"Grobbendonk",
    "sg:classifiers":[
        {
            "category":"Building & Trades",
            "subcategory":"Construction",
            "type":"Services"
        }
    ],
    "sg:phone":"+32 477 75 60 79",
    "sg:postcode":"2280",
    "sg:province":"Antwerpen",
    "sg:tags":[
        "carpenter"
    ],
    "wof:name":"Jocam Bvba",
    "wof:placetype":"venue"
},
  "geometry": {"coordinates":[4.7399587631,51.1929016113],"type":"Point"}
}