{
  "type": "Feature",
  "properties": {
    "iso:country":"BE",
    "sg:address":"Rue Des Religieuses 14ba",
    "sg:city":"Philippeville",
    "sg:classifiers":[
        {
            "category":"Health Services",
            "subcategory":"Nursing And Care Facility",
            "type":"Services"
        }
    ],
    "sg:phone":"+32 71 66 71 77",
    "sg:postcode":"5600",
    "sg:province":"Namur",
    "sg:tags":[
        "public"
    ],
    "wof:name":"Admin. Contrib. Directes",
    "wof:placetype":"venue"
},
  "geometry": {"coordinates":[4.544962883,50.1967468262],"type":"Point"}
}