{
  "type": "Feature",
  "properties": {
    "addr:full":"Rue Des Bl\u00e9s 21 Attert Luxembourg 6717",
    "addr:housenumber":"21",
    "addr:postcode":"6717",
    "addr:street":"Rue Des Ble\u0301S",
    "iso:country":"BE",
    "sg:address":"Rue Des Bl\u00e9s 21",
    "sg:city":"Attert",
    "sg:classifiers":[
        {
            "category":"Wholesale",
            "subcategory":"Fruits & Vegetables",
            "type":"Manufacturing & Wholesale Goods"
        }
    ],
    "sg:phone":"+32 63 22 56 96",
    "sg:postcode":"6717",
    "sg:province":"Luxembourg",
    "sg:tags":[
        "whol",
        "-",
        "potato"
    ],
    "wof:name":"Kohl Fres",
    "wof:placetype":"venue"
},
  "geometry": {"coordinates":[5.7557058334,49.7663803101],"type":"Point"}
}