{
  "type": "Feature",
  "properties": {
    "iso:country":"BE",
    "sg:address":"Route De Philippeville 269",
    "sg:city":"Charleroi (couillet)",
    "sg:classifiers":[
        {
            "category":"Shopping",
            "subcategory":"Bicycles & Sporting Goods",
            "type":"Retail Goods"
        }
    ],
    "sg:phone":"+32 71 47 77 53",
    "sg:postcode":"6010",
    "sg:province":"Hainaut",
    "sg:tags":[
        "-"
    ],
    "wof:name":"Free Bike",
    "wof:placetype":"venue"
},
  "geometry": {"coordinates":[4.4632678032,50.3856658936],"type":"Point"}
}