{
  "type": "Feature",
  "properties": {
    "addr:full":"Gentsestraat 79 Brakel Oost-Vlaanderen 9660",
    "addr:housenumber":"79",
    "addr:postcode":"9660",
    "addr:street":"Gentsestraat",
    "iso:country":"BE",
    "sg:address":"Gentsestraat 79",
    "sg:city":"Brakel",
    "sg:classifiers":[
        {
            "category":"Autos & Motor Vehicles",
            "subcategory":"Fuel & Gas Station",
            "type":"Retail Goods"
        }
    ],
    "sg:phone":"+32 55 42 39 02",
    "sg:postcode":"9660",
    "sg:province":"Oost-Vlaanderen",
    "sg:tags":[
        "stations-service",
        "carburants"
    ],
    "wof:name":"Georges Manssens",
    "wof:placetype":"venue"
},
  "geometry": {"coordinates":[3.7341370583,50.8195648193],"type":"Point"}
}