{
  "type": "Feature",
  "properties": {
    "addr:full":"Avenue De L'observatoire 21 Ukkel/uccle Bruxelles-Capitale 1180",
    "addr:housenumber":"21",
    "addr:postcode":"1180",
    "addr:street":"Avenue De L'Observatoire;/",
    "iso:country":"BE",
    "sg:address":"Avenue De L'observatoire 21",
    "sg:city":"Ukkel/uccle",
    "sg:orig_category":"Artistes ind\u00e9pendants",
    "sg:phone":"+32 2 374 13 72",
    "sg:postcode":"1180",
    "sg:province":"Bruxelles-Capitale",
    "wof:name":"Isabelle Glorie",
    "wof:placetype":"venue"
},
  "geometry": {"coordinates":[4.3695378304,50.8021965027],"type":"Point"}
}