{
  "type": "Feature",
  "properties": {
    "addr:full":"Molenstraat 102bc Kluisbergen Oost-Vlaanderen 9690",
    "addr:housenumber":"102bc",
    "addr:postcode":"9690",
    "addr:street":"Molenstraat",
    "iso:country":"BE",
    "sg:address":"Molenstraat 102bc",
    "sg:city":"Kluisbergen",
    "sg:classifiers":[
        {
            "category":"Insurance",
            "subcategory":"Life Insurance",
            "type":"Services"
        }
    ],
    "sg:phone":"+32 55 38 94 43",
    "sg:postcode":"9690",
    "sg:province":"Oost-Vlaanderen",
    "sg:tags":[
        "assurance"
    ],
    "wof:name":"B. Vanopbroeke",
    "wof:placetype":"venue"
},
  "geometry": {"coordinates":[3.5028350353,50.7871208191],"type":"Point"}
}