{
  "type": "Feature",
  "properties": {
    "iso:country":"BE",
    "sg:address":"Sint-catharinapolderstr. 41",
    "sg:city":"Oostende",
    "sg:classifiers":[
        {
            "category":"Arena",
            "subcategory":"Sports Club",
            "type":"Entertainment"
        }
    ],
    "sg:phone":"+32 59 50 71 16",
    "sg:postcode":"8400",
    "sg:province":"West-Vlaanderen",
    "sg:tags":[
        "de"
    ],
    "wof:name":"K.v.g. Raco '75",
    "wof:placetype":"venue"
},
  "geometry": {"coordinates":[2.9055230618,51.2197113037],"type":"Point"}
}