{
  "type": "Feature",
  "properties": {
    "iso:country":"BE",
    "sg:address":"Rue De L'egalit\u00c9 24",
    "sg:city":"Quaregnon",
    "sg:orig_category":"Artsen and specialisten",
    "sg:phone":"+32 65 79 20 72",
    "sg:postcode":"7390",
    "sg:province":"Hainaut",
    "wof:name":"Nazia Asmaoui",
    "wof:placetype":"venue"
},
  "geometry": {"coordinates":[3.863961935,50.4409637451],"type":"Point"}
}