{
  "type": "Feature",
  "properties": {
    "addr:full":"Chauss\u00e9e De Wavre 1526 Bruxelles (auderghem) Bruxelles-Capitale 1160",
    "addr:postcode":"1526;1160",
    "addr:street":"Chausse\u0301E De Wavre",
    "iso:country":"BE",
    "sg:address":"Chauss\u00e9e De Wavre 1526",
    "sg:city":"Bruxelles (auderghem)",
    "sg:classifiers":[
        {
            "category":"Health Services",
            "subcategory":"Dentist",
            "type":"Services"
        }
    ],
    "sg:phone":"+32 2 675 51 69",
    "sg:postcode":"1160",
    "sg:province":"Bruxelles-Capitale",
    "wof:name":"Jonquin Pierre",
    "wof:placetype":"venue"
},
  "geometry": {"coordinates":[4.4210672379,50.8176193237],"type":"Point"}
}