{
  "type": "Feature",
  "properties": {
    "addr:full":"Monseigneur Koningsstr. 10 Maaseik Limburg 3680",
    "addr:housenumber":"10",
    "addr:postcode":"3680",
    "addr:street":"Monseigneur Koningsstr.",
    "iso:country":"BE",
    "sg:address":"Monseigneur Koningsstr. 10",
    "sg:city":"Maaseik",
    "sg:orig_category":"Ziekenhuizen and zorginstellingen",
    "sg:phone":"+32 89 56 02 00",
    "sg:postcode":"3680",
    "sg:province":"Limburg",
    "wof:name":"Med. Centrum N.o.-limburg",
    "wof:placetype":"venue"
},
  "geometry": {"coordinates":[5.7951607704,51.0954322815],"type":"Point"}
}