{
  "type": "Feature",
  "properties": {
    "addr:full":"Rue Claessens 25 Bruxelles Bruxelles-Capitale 1020",
    "addr:housenumber":"25",
    "addr:postcode":"1020",
    "addr:street":"Rue Claessens",
    "iso:country":"BE",
    "sg:address":"Rue Claessens 25",
    "sg:city":"Bruxelles",
    "sg:classifiers":[
        {
            "category":"Bars & Pubs",
            "type":"Food & Drink"
        }
    ],
    "sg:phone":"+32 2 424 17 30",
    "sg:postcode":"1020",
    "sg:province":"Bruxelles-Capitale",
    "wof:name":"Lo Stivale",
    "wof:placetype":"venue"
},
  "geometry": {"coordinates":[4.3576898575,50.8727684021],"type":"Point"}
}