{
  "type": "Feature",
  "properties": {
    "addr:full":"Galeistraat 4 Brugge (zeebrugge - Lissewege) West-Vlaanderen 8380",
    "addr:housenumber":"4",
    "addr:postcode":"8380",
    "addr:street":"Galeistraat",
    "iso:country":"BE",
    "sg:address":"Galeistraat 4",
    "sg:city":"Brugge (zeebrugge - Lissewege)",
    "sg:classifiers":[
        {
            "category":"Shopping",
            "subcategory":"Discount & Variety Stores",
            "type":"Retail Goods"
        }
    ],
    "sg:phone":"+32 50 27 07 90",
    "sg:postcode":"8380",
    "sg:province":"West-Vlaanderen",
    "sg:tags":[
        "warehouse",
        "-",
        "merchandise"
    ],
    "wof:name":"Middlegate Europe",
    "wof:placetype":"venue"
},
  "geometry": {"coordinates":[3.2288448811,51.2742958069],"type":"Point"}
}