{
  "type": "Feature",
  "properties": {
    "addr:full":"Rue De La Loi 44 Bruxelles (etterbeek) Bruxelles-Capitale 1040",
    "addr:housenumber":"44",
    "addr:postcode":"1040",
    "addr:street":"Rue De La Loi",
    "iso:country":"BE",
    "sg:address":"Rue De La Loi 44",
    "sg:city":"Bruxelles (etterbeek)",
    "sg:classifiers":[
        {
            "category":"Retail",
            "subcategory":"Auto Repair",
            "type":"Services"
        }
    ],
    "sg:phone":"+32 2 233 22 11",
    "sg:postcode":"1040",
    "sg:province":"Bruxelles-Capitale",
    "sg:tags":[
        "breakdown",
        "automobile",
        "-",
        "recovery"
    ],
    "wof:name":"Touring Nv",
    "wof:placetype":"venue"
},
  "geometry": {"coordinates":[4.3708162308,50.8452415466],"type":"Point"}
}