{
  "type": "Feature",
  "properties": {
    "addr:full":"Rue De Nil 62 Chastre Brabant Wallon 1450",
    "addr:housenumber":"62",
    "addr:postcode":"1450",
    "addr:street":"Rue De Nil",
    "iso:country":"BE",
    "sg:address":"Rue De Nil 62",
    "sg:city":"Chastre",
    "sg:orig_category":"Architectes",
    "sg:phone":"+32 10 65 05 52",
    "sg:postcode":"1450",
    "sg:province":"Brabant Wallon",
    "wof:name":"Andy Corlier",
    "wof:placetype":"venue"
},
  "geometry": {"coordinates":[4.6441688538,50.6263389587],"type":"Point"}
}