{
  "type": "Feature",
  "properties": {
    "iso:country":"BE",
    "sg:address":"Kauter 5",
    "sg:city":"Beernem (sint-joris)",
    "sg:classifiers":[
        {
            "category":"Transit Center",
            "subcategory":"Freight",
            "type":"Transportation"
        }
    ],
    "sg:phone":"+32 50 78 91 31",
    "sg:postcode":"8730",
    "sg:province":"West-Vlaanderen",
    "sg:tags":[
        "tanker",
        "-",
        "transport"
    ],
    "wof:name":"Plovie Transport Bvba",
    "wof:placetype":"venue"
},
  "geometry": {"coordinates":[3.3780601025,51.1277656555],"type":"Point"}
}