{
  "type": "Feature",
  "properties": {
    "iso:country":"BE",
    "sg:address":"De Merodelei 128",
    "sg:city":"Turnhout",
    "sg:classifiers":[
        {
            "category":"Social Services",
            "type":"Services"
        }
    ],
    "sg:phone":"+32 14 42 99 67",
    "sg:postcode":"2300",
    "sg:province":"Antwerpen",
    "wof:name":"Jwt Educatiefhuis",
    "wof:placetype":"venue"
},
  "geometry": {"coordinates":[4.9358930588,51.3215675354],"type":"Point"}
}