{
  "type": "Feature",
  "properties": {
    "iso:country":"BE",
    "sg:address":"Markt 4",
    "sg:city":"Merchtem",
    "sg:orig_category":"Vis and zeevruchten Voedingsspeciaalzaken",
    "sg:phone":"+32 52 37 64 61",
    "sg:postcode":"1785",
    "sg:province":"Vlaams-Brabant",
    "wof:name":"Traiteur De Nys",
    "wof:placetype":"venue"
},
  "geometry": {"coordinates":[4.2312960625,50.9589004517],"type":"Point"}
}