{
  "type": "Feature",
  "properties": {
    "addr:full":"Merelstraat 25 Izegem West-Vlaanderen 8870",
    "addr:housenumber":"25",
    "addr:postcode":"8870",
    "addr:street":"Merelstraat",
    "iso:country":"BE",
    "sg:address":"Merelstraat 25",
    "sg:city":"Izegem",
    "sg:classifiers":[
        {
            "category":"Personal",
            "subcategory":"Beauty Salon",
            "type":"Services"
        }
    ],
    "sg:phone":"+32 51 31 54 88",
    "sg:postcode":"8870",
    "sg:province":"West-Vlaanderen",
    "sg:tags":[
        "lady",
        "-",
        "hairdressing"
    ],
    "wof:name":"Nancy",
    "wof:placetype":"venue"
},
  "geometry": {"coordinates":[3.2256550789,50.9279403687],"type":"Point"}
}