{
  "type": "Feature",
  "properties": {
    "iso:country":"BE",
    "sg:address":"Ontvangersstraat 3",
    "sg:city":"Brugge",
    "sg:orig_category":"Enregistrements sonores",
    "sg:phone":"+32 50 33 08 86",
    "sg:postcode":"8000",
    "sg:province":"West-Vlaanderen",
    "wof:name":"Hans Van Daele",
    "wof:placetype":"venue"
},
  "geometry": {"coordinates":[3.2199099064,51.2080459595],"type":"Point"}
}