{
  "type": "Feature",
  "properties": {
    "iso:country":"BE",
    "sg:address":"Paepevelden 17",
    "sg:city":"Schelle",
    "sg:orig_category":"Loodgieterij, verwarming and sanitaire installaties",
    "sg:phone":"+32 3 887 63 97",
    "sg:postcode":"2627",
    "sg:province":"Antwerpen",
    "wof:name":"Brati",
    "wof:placetype":"venue"
},
  "geometry": {"coordinates":[4.3376579285,51.1182556152],"type":"Point"}
}