{
  "type": "Feature",
  "properties": {
    "iso:country":"BE",
    "sg:address":"Centre Heracles Zami 2",
    "sg:city":"Gilly",
    "sg:classifiers":[
        {
            "category":"Manufacturing",
            "subcategory":"Tools & Machinery",
            "type":"Manufacturing & Wholesale Goods"
        }
    ],
    "sg:phone":"+32 71 28 77 20",
    "sg:postcode":"6060",
    "sg:province":"Hainaut",
    "sg:tags":[
        "diamond"
    ],
    "wof:name":"Diarotech Sa",
    "wof:placetype":"venue"
},
  "geometry": {"coordinates":[4.4880981445,50.4251937866],"type":"Point"}
}