{
  "type": "Feature",
  "properties": {
    "addr:full":"Avenue De L'horizon 88 Genepien Brabant Wallon 1470",
    "addr:housenumber":"88",
    "addr:postcode":"1470",
    "addr:street":"Avenue De L'Horizon;Brabant Wallon",
    "iso:country":"BE",
    "sg:address":"Avenue De L'horizon 88",
    "sg:city":"Genepien",
    "sg:classifiers":[
        {
            "category":"Arena",
            "subcategory":"Sports Club",
            "type":"Entertainment"
        }
    ],
    "sg:phone":"+32 10 61 45 60",
    "sg:postcode":"1470",
    "sg:province":"Brabant Wallon",
    "sg:tags":[
        "de"
    ],
    "wof:name":"Union Cycliste Tilly-villers Sport",
    "wof:placetype":"venue"
},
  "geometry": {"coordinates":[4.5289258957,50.62758255],"type":"Point"}
}