{
  "type": "Feature",
  "properties": {
    "addr:full":"Maalse Steenweg 92 Brugge (sint-kruis) West-Vlaanderen 8310",
    "addr:housenumber":"92",
    "addr:postcode":"8310",
    "addr:street":"Maalse Steenweg",
    "iso:country":"BE",
    "sg:address":"Maalse Steenweg 92",
    "sg:city":"Brugge (sint-kruis)",
    "sg:classifiers":[
        {
            "category":"Health Services",
            "subcategory":"Health Practitioner",
            "type":"Services"
        }
    ],
    "sg:phone":"+32 50 35 80 90",
    "sg:postcode":"8310",
    "sg:province":"West-Vlaanderen",
    "sg:tags":[
        "physiotherapist"
    ],
    "wof:name":"Vanpachtenbeke Frank",
    "wof:placetype":"venue"
},
  "geometry": {"coordinates":[3.2460570335,51.2106170654],"type":"Point"}
}