{
  "type": "Feature",
  "properties": {
    "iso:country":"BE",
    "sg:address":"Leuvensesteenweg 202",
    "sg:city":"Zaventem (sint-stevens-woluwe)",
    "sg:classifiers":[
        {
            "category":"Personal",
            "subcategory":"Beauty Salon",
            "type":"Services"
        }
    ],
    "sg:phone":"+32 2 725 97 80",
    "sg:postcode":"1932",
    "sg:province":"Vlaams-Brabant",
    "wof:name":"Beautycenter Caro-line",
    "wof:placetype":"venue"
},
  "geometry": {"coordinates":[4.4675021172,50.8715705872],"type":"Point"}
}