{
  "type": "Feature",
  "properties": {
    "addr:full":"Nachtegaallaan 15 Asse Vlaams-Brabant 1731",
    "addr:housenumber":"15",
    "addr:postcode":"1731",
    "addr:street":"Nachtegaallaan",
    "iso:country":"BE",
    "sg:address":"Nachtegaallaan 15",
    "sg:city":"Asse",
    "sg:orig_category":"D\u00e9corateurs d'int\u00e9rieur. Meubles D\u00e9taillants, Am\u00e9nagement de B\u00e2timents et de Cuisines",
    "sg:phone":"+32 2 466 16 17",
    "sg:postcode":"1731",
    "sg:province":"Vlaams-Brabant",
    "wof:name":"Andre Ossieur",
    "wof:placetype":"venue"
},
  "geometry": {"coordinates":[4.2776470184,50.8853340149],"type":"Point"}
}