{
  "type": "Feature",
  "properties": {
    "iso:country":"BE",
    "sg:address":"Oude Ieperstraat 32",
    "sg:city":"Wevelgem (gullegem)",
    "sg:classifiers":[
        {
            "category":"Professional",
            "subcategory":"Management & Consulting",
            "type":"Services"
        }
    ],
    "sg:phone":"+32 56 42 52 20",
    "sg:postcode":"8560",
    "sg:province":"West-Vlaanderen",
    "sg:tags":[
        "tax-consultants"
    ],
    "wof:name":"Verbeke J",
    "wof:placetype":"venue"
},
  "geometry": {"coordinates":[3.1087899208,50.8370018005],"type":"Point"}
}