{
  "type": "Feature",
  "properties": {
    "addr:full":"Parc Industriel Chastres Namur 5650",
    "addr:postcode":"5650",
    "iso:country":"BE",
    "sg:address":"Parc Industriel",
    "sg:city":"Chastres",
    "sg:orig_category":"Non-Classified Establishments",
    "sg:phone":"+32 71 61 17 97",
    "sg:postcode":"5650",
    "sg:province":"Namur",
    "wof:name":"Gastronome (au)",
    "wof:placetype":"venue"
},
  "geometry": {"coordinates":[4.4313349724,50.2514762878],"type":"Point"}
}