{
  "type": "Feature",
  "properties": {
    "addr:full":"Elverdingestraat 2 Vleteren (woesten) West-Vlaanderen 8640",
    "addr:housenumber":"2",
    "addr:postcode":"8640",
    "addr:street":"Elverdingestraat",
    "iso:country":"BE",
    "sg:address":"Elverdingestraat 2",
    "sg:city":"Vleteren (woesten)",
    "sg:classifiers":[
        {
            "category":"Bars & Pubs",
            "type":"Food & Drink"
        }
    ],
    "sg:phone":"+32 57 42 20 62",
    "sg:postcode":"8640",
    "sg:province":"West-Vlaanderen",
    "wof:name":"Catteeu R",
    "wof:placetype":"venue"
},
  "geometry": {"coordinates":[2.7906999588,50.8993988037],"type":"Point"}
}