{
  "type": "Feature",
  "properties": {
    "iso:country":"BE",
    "sg:address":"Oostlaan 19",
    "sg:city":"Ardooie",
    "sg:classifiers":[
        {
            "category":"Manufacturing",
            "subcategory":"Tools & Machinery",
            "type":"Manufacturing & Wholesale Goods"
        }
    ],
    "sg:phone":"+32 51 74 72 51",
    "sg:postcode":"8850",
    "sg:province":"West-Vlaanderen",
    "sg:tags":[
        "builder"
    ],
    "wof:name":"Muylle Engineering",
    "wof:placetype":"venue"
},
  "geometry": {"coordinates":[3.2029440403,50.9742660522],"type":"Point"}
}