{
  "type": "Feature",
  "properties": {
    "iso:country":"BE",
    "sg:address":"Vosakkerslaan 48",
    "sg:city":"Dendermonde",
    "sg:orig_category":"Bloemen and planten",
    "sg:phone":"+32 52 21 87 29",
    "sg:postcode":"9200",
    "sg:province":"Oost-Vlaanderen",
    "wof:name":"Thierry Maes",
    "wof:placetype":"venue"
},
  "geometry": {"coordinates":[4.097837925,51.0495147705],"type":"Point"}
}