{
  "type": "Feature",
  "properties": {
    "iso:country":"BE",
    "sg:address":"Grote Heerweg 33",
    "sg:city":"Waregem (beveren-leie)",
    "sg:classifiers":[
        {
            "category":"Shopping",
            "type":"Retail Goods"
        }
    ],
    "sg:phone":"+32 56 71 90 82",
    "sg:postcode":"8791",
    "sg:province":"West-Vlaanderen",
    "sg:tags":[
        "product",
        "cleaning",
        "maintenance"
    ],
    "wof:name":"Pivan Cleaner",
    "wof:placetype":"venue"
},
  "geometry": {"coordinates":[3.3274240494,50.8715820312],"type":"Point"}
}