{
  "type": "Feature",
  "properties": {
    "iso:country":"BE",
    "sg:address":"Lei 7",
    "sg:city":"Leuven",
    "sg:classifiers":[
        {
            "category":"Health Services",
            "subcategory":"Doctor",
            "type":"Services"
        }
    ],
    "sg:phone":"+32 16 29 31 31",
    "sg:postcode":"3000",
    "sg:province":"Vlaams-Brabant",
    "sg:tags":[
        "medicinephysicians",
        "surgeon"
    ],
    "wof:name":"Mannaerts G-opdebeeck H",
    "wof:placetype":"venue"
},
  "geometry": {"coordinates":[4.6961560249,50.8807983398],"type":"Point"}
}