{
  "type": "Feature",
  "properties": {
    "iso:country":"BE",
    "sg:address":"Broekstraat 62",
    "sg:city":"Balen",
    "sg:orig_category":"Woningbouw",
    "sg:phone":"+32 14 30 97 47",
    "sg:postcode":"2491",
    "sg:province":"Antwerpen",
    "wof:name":"Willy Eyckmans",
    "wof:placetype":"venue"
},
  "geometry": {"coordinates":[5.1626901627,51.1420707703],"type":"Point"}
}