{
  "type": "Feature",
  "properties": {
    "iso:country":"BE",
    "sg:address":"Henri Van Zuylenstraat 54",
    "sg:city":"Ukkel/uccle",
    "sg:orig_category":"Belastingconsulenten Diverse juridische dienstverlening",
    "sg:phone":"+32 2 376 95 55",
    "sg:postcode":"1180",
    "sg:province":"Bruxelles-Capitale",
    "wof:name":"Mauro Giffoni",
    "wof:placetype":"venue"
},
  "geometry": {"coordinates":[4.3396167755,50.7977790833],"type":"Point"}
}