{
  "type": "Feature",
  "properties": {
    "addr:full":"Socialestraat 4 Genk Limburg 3600",
    "addr:housenumber":"4",
    "addr:postcode":"3600",
    "addr:street":"Socialestraat",
    "iso:country":"BE",
    "sg:address":"Socialestraat 4",
    "sg:city":"Genk",
    "sg:orig_category":"Rusthuizen and serviceflats",
    "sg:phone":"+32 89 38 01 57",
    "sg:postcode":"3600",
    "sg:province":"Limburg",
    "wof:name":"Huize Uilenspiegel",
    "wof:placetype":"venue"
},
  "geometry": {"coordinates":[5.5088949203,51.0114784241],"type":"Point"}
}