{
  "type": "Feature",
  "properties": {
    "iso:country":"BE",
    "sg:address":"Westkade 19",
    "sg:city":"Zelzate",
    "sg:orig_category":"Advocaten and juridische adviseurs",
    "sg:phone":"+32 9 345 76 46",
    "sg:postcode":"9060",
    "sg:province":"Oost-Vlaanderen",
    "wof:name":"Nathalie Van Peteghem",
    "wof:placetype":"venue"
},
  "geometry": {"coordinates":[3.8086700439,51.1992225647],"type":"Point"}
}