{
  "type": "Feature",
  "properties": {
    "addr:full":"Carembergstraat 12 Edingen/enghien Hainaut 7850",
    "addr:housenumber":"12",
    "addr:postcode":"7850",
    "addr:street":"Carembergstraat",
    "iso:country":"BE",
    "sg:address":"Carembergstraat 12",
    "sg:city":"Edingen/enghien",
    "sg:orig_category":"Schoonheidssalons",
    "sg:phone":"+32 2 395 32 14",
    "sg:postcode":"7850",
    "sg:province":"Hainaut",
    "wof:name":"G Demeulder",
    "wof:placetype":"venue"
},
  "geometry": {"coordinates":[4.0691599846,50.6924057007],"type":"Point"}
}