{
  "type": "Feature",
  "properties": {
    "addr:full":"Rue Voie-de-messe 2b Houffalize Luxembourg 6660",
    "addr:housenumber":"2b",
    "addr:postcode":"6660",
    "addr:street":"Rue Voie-De-Messe",
    "iso:country":"BE",
    "sg:address":"Rue Voie-de-messe 2b",
    "sg:city":"Houffalize",
    "sg:classifiers":[
        {
            "category":"Insurance",
            "subcategory":"Insurance Agent",
            "type":"Services"
        }
    ],
    "sg:phone":"+32 61 28 98 38",
    "sg:postcode":"6660",
    "sg:province":"Luxembourg",
    "sg:tags":[
        "verzekeringsmakelaars",
        "expert"
    ],
    "wof:name":"Bureau Otto G\u00c9rard",
    "wof:placetype":"venue"
},
  "geometry": {"coordinates":[5.7895750999,50.132396698],"type":"Point"}
}