{
  "type": "Feature",
  "properties": {
    "iso:country":"BE",
    "sg:address":"Avenue De Jette 228",
    "sg:city":"Bruxelles (jette)",
    "sg:classifiers":[
        {
            "category":"Autos & Motor Vehicles",
            "subcategory":"Automobile Sales",
            "type":"Retail Goods"
        }
    ],
    "sg:phone":"+32 2 424 05 31",
    "sg:postcode":"1090",
    "sg:province":"Bruxelles-Capitale",
    "sg:tags":[
        "ceremony",
        "car"
    ],
    "wof:name":"Oxford-prophils",
    "wof:placetype":"venue"
},
  "geometry": {"coordinates":[4.3251509666,50.8706054688],"type":"Point"}
}