{
  "type": "Feature",
  "properties": {
    "iso:country":"BE",
    "sg:address":"Stationsstraat 48",
    "sg:city":"Liedekerke",
    "sg:classifiers":[
        {
            "category":"Banks & Credit Unions",
            "subcategory":"Investment Brokerage",
            "type":"Services"
        }
    ],
    "sg:phone":"+32 53 66 83 89",
    "sg:postcode":"1770",
    "sg:province":"Vlaams-Brabant",
    "sg:tags":[
        "printing",
        "-"
    ],
    "wof:name":"Cobbaert J",
    "wof:placetype":"venue"
},
  "geometry": {"coordinates":[4.0841932297,50.8724555969],"type":"Point"}
}