{
  "type": "Feature",
  "properties": {
    "addr:full":"Abdijstraat 247 Antwerpen Antwerpen 2020",
    "addr:housenumber":"247",
    "addr:postcode":"2020",
    "addr:street":"Abdijstraat",
    "iso:country":"BE",
    "sg:address":"Abdijstraat 247",
    "sg:city":"Antwerpen",
    "sg:orig_category":"Huisdieren and benodigdheden Royal Canin",
    "sg:phone":"+32 3 238 71 63",
    "sg:postcode":"2020",
    "sg:province":"Antwerpen",
    "wof:name":"Huysmans",
    "wof:placetype":"venue"
},
  "geometry": {"coordinates":[4.3872551918,51.1864776611],"type":"Point"}
}