{
  "type": "Feature",
  "properties": {
    "addr:full":"Rue D'herlaimont 13 Chapelle-lez-herlaimont Hainaut 7160",
    "addr:housenumber":"13",
    "addr:postcode":"7160",
    "addr:street":"Rue D'Herlaimont",
    "iso:country":"BE",
    "sg:address":"Rue D'herlaimont 13",
    "sg:city":"Chapelle-lez-herlaimont",
    "sg:classifiers":[
        {
            "category":"Sports & Exercise",
            "subcategory":"Sports Center",
            "type":"Entertainment"
        }
    ],
    "sg:phone":"+32 64 44 27 02",
    "sg:postcode":"7160",
    "sg:province":"Hainaut",
    "sg:tags":[
        "terrain",
        "hors",
        "de",
        "installation",
        "sportifs"
    ],
    "wof:name":"Ecurie D'herlaimont",
    "wof:placetype":"venue"
},
  "geometry": {"coordinates":[4.2836642265,50.4663238525],"type":"Point"}
}