{
  "type": "Feature",
  "properties": {
    "iso:country":"BE",
    "sg:address":"Dr.-van De Perrestraat 127",
    "sg:city":"Geel",
    "sg:orig_category":"Dierenartsen",
    "sg:phone":"+32 14 58 17 81",
    "sg:postcode":"2440",
    "sg:province":"Antwerpen",
    "wof:name":"Willy Dams",
    "wof:placetype":"venue"
},
  "geometry": {"coordinates":[4.9871401787,51.1741790771],"type":"Point"}
}