{
  "type": "Feature",
  "properties": {
    "addr:full":"Driehoekstraat 36 Haaltert Oost-Vlaanderen 9451",
    "addr:housenumber":"36",
    "addr:postcode":"9451",
    "addr:street":"Driehoekstraat",
    "iso:country":"BE",
    "sg:address":"Driehoekstraat 36",
    "sg:city":"Haaltert",
    "sg:orig_category":"Herstellingen and onderhoud van auto's",
    "sg:phone":"+32 53 83 71 54",
    "sg:postcode":"9451",
    "sg:province":"Oost-Vlaanderen",
    "wof:name":"Garage Van Melkebeke",
    "wof:placetype":"venue"
},
  "geometry": {"coordinates":[3.9841520786,50.8873939514],"type":"Point"}
}