{
  "type": "Feature",
  "properties": {
    "iso:country":"BE",
    "sg:address":"Aarschotsestraat 4",
    "sg:city":"Bierbeek",
    "sg:orig_category":"Dierentuinen, botanische tuinen, sterrenwachten and natuurreservaten",
    "sg:phone":"+32 16 73 42 27",
    "sg:postcode":"3360",
    "sg:province":"Vlaams-Brabant",
    "wof:name":"Blauwschuurbroek",
    "wof:placetype":"venue"
},
  "geometry": {"coordinates":[4.7951622009,50.8177986145],"type":"Point"}
}