{
  "type": "Feature",
  "properties": {
    "addr:full":"Bekestraat 10 Zingem Oost-Vlaanderen 9750",
    "addr:housenumber":"10",
    "addr:postcode":"9750",
    "addr:street":"Bekestraat;Oost-Vlaanderen",
    "iso:country":"BE",
    "sg:address":"Bekestraat 10",
    "sg:city":"Zingem",
    "sg:orig_category":"Installatie van houten of kunststof schrijnwerk",
    "sg:phone":"+32 9 384 72 74",
    "sg:postcode":"9750",
    "sg:province":"Oost-Vlaanderen",
    "wof:name":"Dirk Deroose",
    "wof:placetype":"venue"
},
  "geometry": {"coordinates":[3.6351509094,50.9085731506],"type":"Point"}
}