{
  "type": "Feature",
  "properties": {
    "addr:full":"Peerderbaan 108 Hechtel-eksel Limburg 3940",
    "addr:housenumber":"108",
    "addr:postcode":"3940",
    "addr:street":"Peerderbaan",
    "iso:country":"BE",
    "sg:address":"Peerderbaan 108",
    "sg:city":"Hechtel-eksel",
    "sg:classifiers":[
        {
            "category":"Manufacturing",
            "subcategory":"Rubber & Plastics",
            "type":"Manufacturing & Wholesale Goods"
        }
    ],
    "sg:phone":"+32 11 73 30 81",
    "sg:postcode":"3940",
    "sg:province":"Limburg",
    "sg:tags":[
        "article"
    ],
    "wof:name":"Multidop Nv",
    "wof:placetype":"venue"
},
  "geometry": {"coordinates":[5.364795208,51.1255340576],"type":"Point"}
}