{
  "type": "Feature",
  "properties": {
    "addr:full":"Geraardsbergsestraat 2 Ninove Oost-Vlaanderen 9400",
    "addr:housenumber":"2",
    "addr:postcode":"9400",
    "addr:street":"Geraardsbergsestraat",
    "iso:country":"BE",
    "sg:address":"Geraardsbergsestraat 2",
    "sg:city":"Ninove",
    "sg:classifiers":[
        {
            "category":"Restaurant",
            "type":"Food & Drink"
        }
    ],
    "sg:phone":"+32 54 34 17 26",
    "sg:postcode":"9400",
    "sg:province":"Oost-Vlaanderen",
    "wof:name":"Hank\u00b4s Place",
    "wof:placetype":"venue"
},
  "geometry": {"coordinates":[4.0171098709,50.8363990784],"type":"Point"}
}