{
  "type": "Feature",
  "properties": {
    "addr:full":"Rue Winston-churchill 251 Li\u00c8ge Li\u00e8ge 4020",
    "addr:housenumber":"251",
    "addr:postcode":"4020",
    "addr:street":"Rue Winston-Churchill",
    "iso:country":"BE",
    "sg:address":"Rue Winston-churchill 251",
    "sg:city":"Li\u00c8ge",
    "sg:orig_category":"Entretien and r\u00e9parations de voitures. D\u00e9chets and d\u00e9bris R\u00e9cup\u00e9ration de mati\u00e8res m\u00e9talliques recyc",
    "sg:phone":"+32 4 343 39 59",
    "sg:postcode":"4020",
    "sg:province":"Li\u00e8ge",
    "wof:name":"Ets. Medart Eric",
    "wof:placetype":"venue"
},
  "geometry": {"coordinates":[5.6149902344,50.6427307129],"type":"Point"}
}