{
  "type": "Feature",
  "properties": {
    "iso:country":"BE",
    "sg:address":"Rue Sainte-brigitte 102",
    "sg:city":"Beloeil",
    "sg:classifiers":[
        {
            "category":"Restaurant",
            "type":"Food & Drink"
        }
    ],
    "sg:phone":"+32 69 77 35 51",
    "sg:postcode":"7971",
    "sg:province":"Hainaut",
    "wof:name":"Restaurant Les Ailes",
    "wof:placetype":"venue"
},
  "geometry": {"coordinates":[3.6156949997,50.5397949219],"type":"Point"}
}