{
  "type": "Feature",
  "properties": {
    "addr:full":"4730 Raeren (groot) Li\u00e8ge 4730",
    "addr:postcode":"4730;4730",
    "addr:street":"Groot Lie\u0300Ge",
    "iso:country":"BE",
    "sg:address":"4730",
    "sg:city":"Raeren (groot)",
    "sg:orig_category":"Pharmaciens",
    "sg:phone":"+32 900 10 500",
    "sg:postcode":"4730",
    "sg:province":"Li\u00e8ge",
    "wof:name":"Pharmacies De Garde",
    "wof:placetype":"venue"
},
  "geometry": {"coordinates":[6.1511101723,50.650188446],"type":"Point"}
}