{
  "type": "Feature",
  "properties": {
    "iso:country":"BE",
    "sg:address":"Molendreef 62",
    "sg:city":"Anzegem",
    "sg:orig_category":"Beautyfarms, relaxatie and lichamelijk welzijn Schoonheidssalons",
    "sg:phone":"+32 56 77 47 28",
    "sg:postcode":"8570",
    "sg:province":"West-Vlaanderen",
    "wof:name":"Aaricia",
    "wof:placetype":"venue"
},
  "geometry": {"coordinates":[3.400384903,50.840637207],"type":"Point"}
}