{
  "type": "Feature",
  "properties": {
    "iso:country":"BE",
    "sg:address":"Rue Du Roi Albert 3",
    "sg:city":"Clavier",
    "sg:orig_category":"Boomkwekerijen Tuinen",
    "sg:phone":"+32 86 34 40 29",
    "sg:postcode":"4560",
    "sg:province":"Li\u00e8ge",
    "wof:name":"Philippe Pierre",
    "wof:placetype":"venue"
},
  "geometry": {"coordinates":[5.3577880859,50.4269561768],"type":"Point"}
}