{
  "type": "Feature",
  "properties": {
    "addr:full":"Pastoor Slossestraat 4 Kortrijk West-Vlaanderen 8510",
    "addr:housenumber":"4",
    "addr:postcode":"8510",
    "addr:street":"Pastoor Slossestraat",
    "iso:country":"BE",
    "sg:address":"Pastoor Slossestraat 4",
    "sg:city":"Kortrijk",
    "sg:orig_category":"Woningbouw",
    "sg:phone":"+32 56 22 54 03",
    "sg:postcode":"8510",
    "sg:province":"West-Vlaanderen",
    "wof:name":"Franky Quidousse",
    "wof:placetype":"venue"
},
  "geometry": {"coordinates":[3.2233951092,50.8045196533],"type":"Point"}
}