{
  "type": "Feature",
  "properties": {
    "addr:full":"Harensesteenweg 543 Vilvoorde Vlaams-Brabant 1800",
    "addr:housenumber":"543",
    "addr:postcode":"1800",
    "addr:street":"Harensesteenweg",
    "iso:country":"BE",
    "sg:address":"Harensesteenweg 543",
    "sg:city":"Vilvoorde",
    "sg:orig_category":"Peinture. Rev\u00eatements pour sols and murs",
    "sg:phone":"+32 2 251 00 94",
    "sg:postcode":"1800",
    "sg:province":"Vlaams-Brabant",
    "wof:name":"Kenitex Belgium",
    "wof:placetype":"venue"
},
  "geometry": {"coordinates":[4.4130458832,50.9073677063],"type":"Point"}
}