{
  "type": "Feature",
  "properties": {
    "addr:full":"Roeselarestraat 4 Hooglede West-Vlaanderen 8830",
    "addr:housenumber":"4",
    "addr:postcode":"8830",
    "addr:street":"Roeselarestraat",
    "iso:country":"BE",
    "sg:address":"Roeselarestraat 4",
    "sg:city":"Hooglede",
    "sg:classifiers":[
        {
            "category":"Structure",
            "subcategory":"Building",
            "type":"Public Place"
        }
    ],
    "sg:phone":"+32 51 24 30 56",
    "sg:postcode":"8830",
    "sg:province":"West-Vlaanderen",
    "sg:tags":[
        "door"
    ],
    "wof:name":"S.d.a.",
    "wof:placetype":"venue"
},
  "geometry": {"coordinates":[3.0829000473,50.9775657654],"type":"Point"}
}