{
  "type": "Feature",
  "properties": {
    "addr:full":"Rue De Tournai 13 Mouscron Hainaut 7700",
    "addr:housenumber":"13",
    "addr:postcode":"7700",
    "addr:street":"Rue De Tournai",
    "iso:country":"BE",
    "sg:address":"Rue De Tournai 13",
    "sg:city":"Mouscron",
    "sg:classifiers":[
        {
            "category":"Shopping",
            "subcategory":"Clothing, Apparel, & Fashions",
            "type":"Retail Goods"
        }
    ],
    "sg:phone":"+32 56 33 12 92",
    "sg:postcode":"7700",
    "sg:province":"Hainaut",
    "sg:tags":[
        "boutique"
    ],
    "wof:name":"Y R",
    "wof:placetype":"venue"
},
  "geometry": {"coordinates":[3.2167670727,50.7439575195],"type":"Point"}
}