{
  "type": "Feature",
  "properties": {
    "addr:full":"Rue Du Docteur Cailleau 19 Anderlues Hainaut 6150",
    "addr:housenumber":"19",
    "addr:postcode":"6150",
    "addr:street":"Rue Du Docteur Cailleau",
    "iso:country":"BE",
    "sg:address":"Rue Du Docteur Cailleau 19",
    "sg:city":"Anderlues",
    "sg:orig_category":"M\u00e9decins and sp\u00e9cialistes",
    "sg:phone":"+32 71 52 34 10",
    "sg:postcode":"6150",
    "sg:province":"Hainaut",
    "wof:name":"Georges Dossin",
    "wof:placetype":"venue"
},
  "geometry": {"coordinates":[4.2622117996,50.4139556885],"type":"Point"}
}