{
  "type": "Feature",
  "properties": {
    "addr:full":"Kasteelkaai 3 Kortrijk West-Vlaanderen 8500",
    "addr:housenumber":"3",
    "addr:postcode":"8500",
    "addr:street":"Kasteelkaai",
    "iso:country":"BE",
    "sg:address":"Kasteelkaai 3",
    "sg:city":"Kortrijk",
    "sg:orig_category":"Fleurs and plantes",
    "sg:phone":"+32 56 20 55 01",
    "sg:postcode":"8500",
    "sg:province":"West-Vlaanderen",
    "wof:name":"Huis Amaranthus",
    "wof:placetype":"venue"
},
  "geometry": {"coordinates":[3.2619080544,50.829208374],"type":"Point"}
}