{
  "type": "Feature",
  "properties": {
    "addr:full":"Rue Faider 90 Bruxelles (ixelles) Bruxelles-Capitale 1050",
    "addr:housenumber":"90",
    "addr:postcode":"1050",
    "addr:street":"Rue Faider",
    "iso:country":"BE",
    "sg:address":"Rue Faider 90",
    "sg:city":"Bruxelles (ixelles)",
    "sg:classifiers":[
        {
            "category":"Sports & Exercise",
            "subcategory":"Sports Center",
            "type":"Entertainment"
        }
    ],
    "sg:phone":"+32 2 646 97 70",
    "sg:postcode":"1050",
    "sg:province":"Bruxelles-Capitale",
    "sg:tags":[
        "holiday",
        "language"
    ],
    "wof:name":"Languages Et Travel",
    "wof:placetype":"venue"
},
  "geometry": {"coordinates":[4.360874176,50.8262519836],"type":"Point"}
}