{
  "type": "Feature",
  "properties": {
    "addr:full":"Jean Volderslaan 17b13 Sint-gillis/saint-gilles Bruxelles-Capitale 1060",
    "addr:housenumber":"17b13",
    "addr:postcode":"1060",
    "addr:street":"Jean Volderslaan",
    "iso:country":"BE",
    "sg:address":"Jean Volderslaan 17b13",
    "sg:city":"Sint-gillis/saint-gilles",
    "sg:orig_category":"Artsen and specialisten",
    "sg:phone":"+32 2 534 45 21",
    "sg:postcode":"1060",
    "sg:province":"Bruxelles-Capitale",
    "wof:name":"Julia Lopez Rodriguez",
    "wof:placetype":"venue"
},
  "geometry": {"coordinates":[4.3429250717,50.8322067261],"type":"Point"}
}