{
  "type": "Feature",
  "properties": {
    "addr:full":"Rue Adolphe Sax 1a Dinant Namur 5500",
    "addr:housenumber":"1a",
    "addr:postcode":"5500",
    "addr:street":"Rue Adolphe Sax",
    "iso:country":"BE",
    "sg:address":"Rue Adolphe Sax 1a",
    "sg:city":"Dinant",
    "sg:classifiers":[
        {
            "category":"Travel",
            "subcategory":"Hotels & Motels",
            "type":"Entertainment"
        }
    ],
    "sg:phone":"+32 82 22 24 41",
    "sg:postcode":"5500",
    "sg:province":"Namur",
    "wof:name":"Couronne (la)",
    "wof:placetype":"venue"
},
  "geometry": {"coordinates":[4.9116930962,50.2613601685],"type":"Point"}
}