{
  "type": "Feature",
  "properties": {
    "addr:full":"Vrijheid 13 Arendonk Antwerpen 2370",
    "addr:housenumber":"13",
    "addr:postcode":"2370",
    "addr:street":"Vrijheid",
    "iso:country":"BE",
    "sg:address":"Vrijheid 13",
    "sg:city":"Arendonk",
    "sg:orig_category":"Textiel",
    "sg:phone":"+32 14 67 93 32",
    "sg:postcode":"2370",
    "sg:province":"Antwerpen",
    "wof:name":"Stoffencenter",
    "wof:placetype":"venue"
},
  "geometry": {"coordinates":[5.0858960152,51.320400238],"type":"Point"}
}