{
  "type": "Feature",
  "properties": {
    "iso:country":"BE",
    "sg:address":"Dokter De Drijverestraat 47",
    "sg:city":"Brakel (nederbrakel)",
    "sg:classifiers":[
        {
            "category":"Personal",
            "subcategory":"Beauty Salon",
            "type":"Services"
        }
    ],
    "sg:phone":"+32 55 42 34 65",
    "sg:postcode":"9660",
    "sg:province":"Oost-Vlaanderen",
    "sg:tags":[
        "lady",
        "-",
        "hairdressing"
    ],
    "wof:name":"Annie",
    "wof:placetype":"venue"
},
  "geometry": {"coordinates":[3.7684819698,50.801158905],"type":"Point"}
}