{
  "type": "Feature",
  "properties": {
    "iso:country":"BE",
    "sg:address":"Geraarsbergsesteenweg 79",
    "sg:city":"Herne",
    "sg:classifiers":[
        {
            "category":"Restaurant",
            "type":"Food & Drink"
        }
    ],
    "sg:phone":"+32 2 396 10 73",
    "sg:postcode":"1541",
    "sg:province":"Vlaams-Brabant",
    "wof:name":"El Rancho",
    "wof:placetype":"venue"
},
  "geometry": {"coordinates":[3.9915280342,50.7171211243],"type":"Point"}
}