{
  "type": "Feature",
  "properties": {
    "iso:country":"BE",
    "sg:address":"Rue Bouteille 24",
    "sg:city":"Seraing",
    "sg:orig_category":"Salons de coiffure. Instituts de beaut\u00e9. Centres de relaxation and bien-\u00eatre",
    "sg:phone":"+32 4 336 11 50",
    "sg:postcode":"4100",
    "sg:province":"Li\u00e8ge",
    "wof:name":"Coiffure G\u00c9raldine",
    "wof:placetype":"venue"
},
  "geometry": {"coordinates":[5.5040259361,50.5863227844],"type":"Point"}
}