{
  "type": "Feature",
  "properties": {
    "addr:full":"Avenue Albert Ier 283 Rixensart Brabant Wallon 1332",
    "addr:housenumber":"283",
    "addr:postcode":"1332",
    "addr:street":"Avenue Albert Ier;Wallon",
    "iso:country":"BE",
    "sg:address":"Avenue Albert Ier 283",
    "sg:city":"Rixensart",
    "sg:orig_category":"Agences de publicit\u00e9",
    "sg:phone":"+32 2 653 38 15",
    "sg:postcode":"1332",
    "sg:province":"Brabant Wallon",
    "wof:name":"White Spirit",
    "wof:placetype":"venue"
},
  "geometry": {"coordinates":[4.4974551201,50.7170753479],"type":"Point"}
}