{
  "type": "Feature",
  "properties": {
    "addr:full":"Place Quinet 20 Fleurus Hainaut 6220",
    "addr:housenumber":"20",
    "addr:postcode":"6220",
    "addr:street":"Place Quinet",
    "iso:country":"BE",
    "sg:address":"Place Quinet 20",
    "sg:city":"Fleurus",
    "sg:orig_category":"Artsen and specialisten",
    "sg:phone":"+32 71 81 57 56",
    "sg:postcode":"6220",
    "sg:province":"Hainaut",
    "wof:name":"Y. Reumont",
    "wof:placetype":"venue"
},
  "geometry": {"coordinates":[4.5496749878,50.4825363159],"type":"Point"}
}