{
  "type": "Feature",
  "properties": {
    "addr:full":"Paalsesteenweg 343 Beringen Limburg 3583",
    "addr:housenumber":"343",
    "addr:postcode":"3583",
    "addr:street":"Paalsesteenweg",
    "iso:country":"BE",
    "sg:address":"Paalsesteenweg 343",
    "sg:city":"Beringen",
    "sg:orig_category":"Banken and kredietinstellingen",
    "sg:phone":"+32 11 42 06 93",
    "sg:postcode":"3583",
    "sg:province":"Limburg",
    "wof:name":"Dexia",
    "wof:placetype":"venue"
},
  "geometry": {"coordinates":[5.1706700325,51.0389442444],"type":"Point"}
}