{
  "type": "Feature",
  "properties": {
    "iso:country":"BE",
    "sg:address":"Markt 3",
    "sg:city":"Zottegem",
    "sg:classifiers":[
        {
            "category":"Fast Food",
            "type":"Food & Drink"
        }
    ],
    "sg:phone":"+32 9 360 90 45",
    "sg:postcode":"9620",
    "sg:province":"Oost-Vlaanderen",
    "sg:tags":[
        "\u00c0",
        "restaurants",
        "emporter",
        "restaurant"
    ],
    "wof:name":"Restaurant Old Sotteghem",
    "wof:placetype":"venue"
},
  "geometry": {"coordinates":[3.8107180595,50.8698654175],"type":"Point"}
}