{
  "type": "Feature",
  "properties": {
    "addr:full":"Bergensesteenweg 421 Box 11 Sint-pieters-leeuw Vlaams-Brabant 1600",
    "addr:housenumber":"421 box 11",
    "addr:postcode":"1600",
    "addr:street":"Bergensesteenweg",
    "iso:country":"BE",
    "sg:address":"Bergensesteenweg 421 Box 11",
    "sg:city":"Sint-pieters-leeuw",
    "sg:classifiers":[
        {
            "category":"Professional",
            "subcategory":"Management & Consulting",
            "type":"Services"
        }
    ],
    "sg:phone":"+32 2 334 15 80",
    "sg:postcode":"1600",
    "sg:province":"Vlaams-Brabant",
    "sg:tags":[
        "tax-consultants"
    ],
    "wof:name":"Al&t Cvba",
    "wof:placetype":"venue"
},
  "geometry": {"coordinates":[4.2774610519,50.7856864929],"type":"Point"}
}