{
  "type": "Feature",
  "properties": {
    "addr:full":"Veldstraat 166 Brasschaat Antwerpen 2930",
    "addr:housenumber":"166",
    "addr:postcode":"2930",
    "addr:street":"Veldstraat",
    "iso:country":"BE",
    "sg:address":"Veldstraat 166",
    "sg:city":"Brasschaat",
    "sg:orig_category":"Installation de menuiserie en bois and plastique",
    "sg:phone":"+32 3 652 02 43",
    "sg:postcode":"2930",
    "sg:province":"Antwerpen",
    "wof:name":"Victor Cox",
    "wof:placetype":"venue"
},
  "geometry": {"coordinates":[4.4854388237,51.2946777344],"type":"Point"}
}