{
  "type": "Feature",
  "properties": {
    "addr:full":"Rue Albert Libiez 12 Frameries (eugies) Hainaut 7080",
    "addr:housenumber":"12",
    "addr:postcode":"7080",
    "addr:street":"Rue Albert Libiez",
    "iso:country":"BE",
    "sg:address":"Rue Albert Libiez 12",
    "sg:city":"Frameries (eugies)",
    "sg:classifiers":[
        {
            "category":"Real Estate",
            "subcategory":"Architect",
            "type":"Services"
        }
    ],
    "sg:phone":"+32 65 66 72 84",
    "sg:postcode":"7080",
    "sg:province":"Hainaut",
    "wof:name":"Houx S",
    "wof:placetype":"venue"
},
  "geometry": {"coordinates":[3.8632900715,50.395111084],"type":"Point"}
}