{
  "type": "Feature",
  "properties": {
    "iso:country":"BE",
    "sg:address":"Fran\u00e7ois Spaestraat 36a",
    "sg:city":"Melle",
    "sg:classifiers":[
        {
            "category":"Building & Trades",
            "subcategory":"Construction",
            "type":"Services"
        }
    ],
    "sg:phone":"+32 9 230 61 61",
    "sg:postcode":"9090",
    "sg:province":"Oost-Vlaanderen",
    "sg:tags":[
        "carpenter"
    ],
    "wof:name":"Van Riet R",
    "wof:placetype":"venue"
},
  "geometry": {"coordinates":[3.7723879814,51.0234680176],"type":"Point"}
}