{
  "type": "Feature",
  "properties": {
    "iso:country":"BE",
    "sg:address":"Rue Th\u00c9o-toussaint 8",
    "sg:city":"Gembloux",
    "sg:orig_category":"Foto-uitrusting Fotografen and fotostudio's",
    "sg:phone":"+32 81 61 51 22",
    "sg:postcode":"5030",
    "sg:province":"Namur",
    "wof:name":"Studio Contre-jours",
    "wof:placetype":"venue"
},
  "geometry": {"coordinates":[4.691660881,50.5596351624],"type":"Point"}
}