{
  "type": "Feature",
  "properties": {
    "addr:full":"Rue De La Cit\u00e9 12 Mettet Namur 5640",
    "addr:housenumber":"12",
    "addr:postcode":"5640",
    "addr:street":"Rue De La Cite\u0301",
    "iso:country":"BE",
    "sg:address":"Rue De La Cit\u00e9 12",
    "sg:city":"Mettet",
    "sg:classifiers":[
        {
            "category":"Health Services",
            "subcategory":"Doctor",
            "type":"Services"
        }
    ],
    "sg:phone":"+32 71 72 87 53",
    "sg:postcode":"5640",
    "sg:province":"Namur",
    "sg:tags":[
        "medicinephysicians",
        "surgeon"
    ],
    "wof:name":"Henry I",
    "wof:placetype":"venue"
},
  "geometry": {"coordinates":[4.6667461395,50.3409957886],"type":"Point"}
}