{
  "type": "Feature",
  "properties": {
    "iso:country":"BE",
    "sg:address":"Avenue Van Volxem 122",
    "sg:city":"Vorst/forest",
    "sg:orig_category":"Cr\u00e8ches and garderies d'enfants",
    "sg:phone":"+32 2 346 27 21",
    "sg:postcode":"1190",
    "sg:province":"Bruxelles-Capitale",
    "wof:name":"Cr\u00c8che Boules De Gomme",
    "wof:placetype":"venue"
},
  "geometry": {"coordinates":[4.3248929977,50.816860199],"type":"Point"}
}