{
  "type": "Feature",
  "properties": {
    "addr:full":"Altembrouck 361 Voeren/fourons Limburg 3798",
    "addr:housenumber":"361",
    "addr:postcode":"3798",
    "addr:street":"Altembrouck",
    "iso:country":"BE",
    "sg:address":"Altembrouck 361",
    "sg:city":"Voeren/fourons",
    "sg:orig_category":"Producteurs de fruits",
    "sg:phone":"+32 4 381 05 25",
    "sg:postcode":"3798",
    "sg:province":"Limburg",
    "wof:name":"Hubert Heggen",
    "wof:placetype":"venue"
},
  "geometry": {"coordinates":[5.7979297638,50.7615814209],"type":"Point"}
}