{
  "type": "Feature",
  "properties": {
    "iso:country":"BE",
    "sg:address":"86",
    "sg:city":"Rue Victor Besme 4800 Verviers",
    "sg:classifiers":[
        {
            "category":"Wholesale",
            "subcategory":"Machinery & Supplies",
            "type":"Manufacturing & Wholesale Goods"
        }
    ],
    "sg:phone":"+32 87 32 15 10",
    "sg:postcode":"86",
    "sg:tags":[
        "handling",
        "material",
        "-",
        "machine",
        "equipment",
        "engineering",
        "mechanical"
    ],
    "wof:name":"Pauly Sprl",
    "wof:placetype":"venue"
},
  "geometry": {"coordinates":[5.8484501839,50.5846405029],"type":"Point"}
}