{
  "type": "Feature",
  "properties": {
    "iso:country":"BE",
    "sg:address":"Veilinglaan 14",
    "sg:city":"Meise",
    "sg:orig_category":"Journaux",
    "sg:phone":"+32 2 270 13 57",
    "sg:postcode":"1861",
    "sg:province":"Vlaams-Brabant",
    "wof:name":"'t Krantje",
    "wof:placetype":"venue"
},
  "geometry": {"coordinates":[4.3040690422,50.9565124512],"type":"Point"}
}