{
  "type": "Feature",
  "properties": {
    "iso:country":"BE",
    "sg:address":"Rue Des Vignes 20",
    "sg:city":"Li\u00c8ge",
    "sg:orig_category":"Entretien and r\u00e9parations de voitures",
    "sg:phone":"+32 4 227 44 84",
    "sg:postcode":"4000",
    "sg:province":"Li\u00e8ge",
    "wof:name":"Garage Think Twice",
    "wof:placetype":"venue"
},
  "geometry": {"coordinates":[5.6013660431,50.6560668945],"type":"Point"}
}