{
  "type": "Feature",
  "properties": {
    "addr:full":"Chauss\u00c9e D\u00b4alsemberg 341 Ukkel/uccle Bruxelles-Capitale 1180",
    "addr:housenumber":"341",
    "addr:postcode":"1180",
    "addr:street":"Chausse\u0301E D\u00b4Alsemberg;/",
    "iso:country":"BE",
    "sg:address":"Chauss\u00c9e D\u00b4alsemberg 341",
    "sg:city":"Ukkel/uccle",
    "sg:orig_category":"Herstelling aan huis van huishoudartikelen Herstelling leer and schoeisel Herstellingswinkels voor d",
    "sg:phone":"+32 2 343 03 06",
    "sg:postcode":"1180",
    "sg:province":"Bruxelles-Capitale",
    "wof:name":"Europa Serrures",
    "wof:placetype":"venue"
},
  "geometry": {"coordinates":[4.3394899368,50.8150100708],"type":"Point"}
}