{
  "type": "Feature",
  "properties": {
    "iso:country":"BE",
    "sg:address":"Engerstraat 7",
    "sg:city":"Kortenberg",
    "sg:orig_category":"Persagentschappen",
    "sg:phone":"+32 2 757 60 21",
    "sg:postcode":"3071",
    "sg:province":"Vlaams-Brabant",
    "wof:name":"Jolande Janzing",
    "wof:placetype":"venue"
},
  "geometry": {"coordinates":[4.5595531464,50.9018058777],"type":"Point"}
}