{
  "type": "Feature",
  "properties": {
    "addr:full":"Poelkenswegel 13 Zulte Oost-Vlaanderen 9870",
    "addr:housenumber":"13",
    "addr:postcode":"9870",
    "addr:street":"Poelkenswegel",
    "iso:country":"BE",
    "sg:address":"Poelkenswegel 13",
    "sg:city":"Zulte",
    "sg:orig_category":"Rev\u00eatements pour sols and murs",
    "sg:phone":"+32 9 388 93 68",
    "sg:postcode":"9870",
    "sg:province":"Oost-Vlaanderen",
    "wof:name":"Michel De Mulder",
    "wof:placetype":"venue"
},
  "geometry": {"coordinates":[3.4609749317,50.9328804016],"type":"Point"}
}