{
  "type": "Feature",
  "properties": {
    "addr:full":"Gaversstraat 56 Harelbeke West-Vlaanderen 8530",
    "addr:housenumber":"56",
    "addr:postcode":"8530",
    "addr:street":"Gaversstraat",
    "iso:country":"BE",
    "sg:address":"Gaversstraat 56",
    "sg:city":"Harelbeke",
    "sg:orig_category":"Plomberie, chauffage and installations sanitaires",
    "sg:phone":"+32 56 72 70 25",
    "sg:postcode":"8530",
    "sg:province":"West-Vlaanderen",
    "wof:name":"I.d. Service",
    "wof:placetype":"venue"
},
  "geometry": {"coordinates":[3.3161931038,50.8538322449],"type":"Point"}
}