{
  "type": "Feature",
  "properties": {
    "iso:country":"BE",
    "sg:address":"Bilzersteenweg 11ba",
    "sg:city":"Hoeselt",
    "sg:orig_category":"Chaussures",
    "sg:phone":"+32 89 50 34 70",
    "sg:postcode":"3730",
    "sg:province":"Limburg",
    "wof:name":"Brantano",
    "wof:placetype":"venue"
},
  "geometry": {"coordinates":[5.4922380447,50.8509521484],"type":"Point"}
}