{
  "type": "Feature",
  "properties": {
    "addr:full":"Kasterleesteenweg 71 Kasterlee Antwerpen 2460",
    "addr:housenumber":"71",
    "addr:postcode":"2460",
    "addr:street":"Kasterleesteenweg",
    "iso:country":"BE",
    "sg:address":"Kasterleesteenweg 71",
    "sg:city":"Kasterlee",
    "sg:classifiers":[
        {
            "category":"Cafe",
            "type":"Food & Drink"
        }
    ],
    "sg:phone":"+32 14 55 65 15",
    "sg:postcode":"2460",
    "sg:province":"Antwerpen",
    "sg:tags":[
        "caf\u00e9s"
    ],
    "wof:name":"Jose Van Der Linden",
    "wof:placetype":"venue"
},
  "geometry": {"coordinates":[4.9671049118,51.2406616211],"type":"Point"}
}