{
  "type": "Feature",
  "properties": {
    "addr:full":"Fotografielaan 6-10 Antwerpen (wilrijk) Antwerpen 2610",
    "addr:housenumber":"6-10",
    "addr:postcode":"2610",
    "addr:street":"Fotografielaan;Antwerpen",
    "iso:country":"BE",
    "sg:address":"Fotografielaan 6-10",
    "sg:city":"Antwerpen (wilrijk)",
    "sg:classifiers":[
        {
            "category":"Travel",
            "subcategory":"Hotels & Motels",
            "type":"Entertainment"
        }
    ],
    "sg:phone":"+32 3 887 34 75",
    "sg:postcode":"2610",
    "sg:province":"Antwerpen",
    "sg:tags":[
        "equipment",
        "installation",
        "hotels"
    ],
    "wof:name":"Deco-bel",
    "wof:placetype":"venue"
},
  "geometry": {"coordinates":[4.4036598206,51.1615409851],"type":"Point"}
}