{
  "type": "Feature",
  "properties": {
    "iso:country":"BE",
    "sg:address":"Oplintersesteenweg 374",
    "sg:city":"Tienen",
    "sg:classifiers":[
        {
            "category":"Retail",
            "subcategory":"Auto Repair",
            "type":"Services"
        }
    ],
    "sg:phone":"+32 16 81 22 41",
    "sg:postcode":"3300",
    "sg:province":"Vlaams-Brabant",
    "sg:tags":[
        "garage"
    ],
    "wof:name":"Buttiens Garage Nv",
    "wof:placetype":"venue"
},
  "geometry": {"coordinates":[4.9496798515,50.8199691772],"type":"Point"}
}