{
  "type": "Feature",
  "properties": {
    "addr:full":"Rue De Nivelles 21 Braine-le-ch\u00e2teau Brabant Wallon 1440",
    "addr:housenumber":"21",
    "addr:postcode":"1440",
    "addr:street":"Rue De Nivelles",
    "iso:country":"BE",
    "sg:address":"Rue De Nivelles 21",
    "sg:city":"Braine-le-ch\u00e2teau",
    "sg:classifiers":[
        {
            "category":"Bars & Pubs",
            "type":"Food & Drink"
        }
    ],
    "sg:phone":"+32 2 366 91 21",
    "sg:postcode":"1440",
    "sg:province":"Brabant Wallon",
    "sg:tags":[
        "tavern"
    ],
    "wof:name":"Botte (la)",
    "wof:placetype":"venue"
},
  "geometry": {"coordinates":[4.2733869553,50.6818580627],"type":"Point"}
}