{
  "type": "Feature",
  "properties": {
    "addr:full":"Herbesthaler Strasse 158 Eupen Li\u00e8ge 4700",
    "addr:housenumber":"158",
    "addr:postcode":"4700",
    "addr:street":"Herbesthaler Strasse",
    "iso:country":"BE",
    "sg:address":"Herbesthaler Strasse 158",
    "sg:city":"Eupen",
    "sg:classifiers":[
        {
            "category":"Home & Garden",
            "subcategory":"Building Materials",
            "type":"Retail Goods"
        }
    ],
    "sg:phone":"+32 87 56 03 50",
    "sg:postcode":"4700",
    "sg:province":"Li\u00e8ge",
    "sg:tags":[
        "bathroom",
        "installation",
        "accessory"
    ],
    "wof:name":"Sanitherme Sa",
    "wof:placetype":"venue"
},
  "geometry": {"coordinates":[6.0091671944,50.6438331604],"type":"Point"}
}