{
  "type": "Feature",
  "properties": {
    "iso:country":"BE",
    "sg:address":"Tulpstraat 3",
    "sg:city":"Sint-truiden",
    "sg:classifiers":[
        {
            "category":"Organizations",
            "subcategory":"Community Association",
            "type":"Services"
        }
    ],
    "sg:phone":"+32 11 67 17 67",
    "sg:postcode":"3800",
    "sg:province":"Limburg",
    "sg:tags":[
        "organisation"
    ],
    "wof:name":"Chiromeisjes Sint-rita",
    "wof:placetype":"venue"
},
  "geometry": {"coordinates":[5.1790919304,50.8244972229],"type":"Point"}
}