{
  "type": "Feature",
  "properties": {
    "addr:full":"Kerkstraat 6 Oostende West-Vlaanderen 8400",
    "addr:housenumber":"6",
    "addr:postcode":"8400",
    "addr:street":"Kerkstraat",
    "iso:country":"BE",
    "sg:address":"Kerkstraat 6",
    "sg:city":"Oostende",
    "sg:classifiers":[
        {
            "category":"Restaurant",
            "type":"Food & Drink"
        }
    ],
    "sg:phone":"+32 59 50 45 19",
    "sg:postcode":"8400",
    "sg:province":"West-Vlaanderen",
    "sg:tags":[
        "caf\u00e9s"
    ],
    "wof:name":"Taverne Fats Domino",
    "wof:placetype":"venue"
},
  "geometry": {"coordinates":[2.9188010693,51.2318649292],"type":"Point"}
}