{
  "type": "Feature",
  "properties": {
    "addr:full":"Sperlekestraat 5 Kortrijk (marke) West-Vlaanderen 8510",
    "addr:housenumber":"5",
    "addr:postcode":"8510",
    "addr:street":"Sperlekestraat",
    "iso:country":"BE",
    "sg:address":"Sperlekestraat 5",
    "sg:city":"Kortrijk (marke)",
    "sg:orig_category":"Non-Classified Establishments",
    "sg:phone":"+32 56 44 09 30",
    "sg:postcode":"8510",
    "sg:province":"West-Vlaanderen",
    "wof:name":"Sanimar Nv",
    "wof:placetype":"venue"
},
  "geometry": {"coordinates":[3.2482500076,50.8035469055],"type":"Point"}
}