{
  "type": "Feature",
  "properties": {
    "iso:country":"BE",
    "sg:address":"Rue Coleau 66",
    "sg:city":"Waterloo",
    "sg:classifiers":[
        {
            "category":"Health Services",
            "subcategory":"Health Practitioner",
            "type":"Services"
        }
    ],
    "sg:phone":"+32 2 387 08 05",
    "sg:postcode":"1410",
    "sg:province":"Brabant Wallon",
    "sg:tags":[
        "physiotherapist"
    ],
    "wof:name":"Speltens J-m",
    "wof:placetype":"venue"
},
  "geometry": {"coordinates":[4.3998761177,50.6928367615],"type":"Point"}
}