{
  "type": "Feature",
  "properties": {
    "addr:full":"Democratiestraat 76 Anderlecht Bruxelles-Capitale 1070",
    "addr:housenumber":"76",
    "addr:postcode":"1070",
    "addr:street":"Democratiestraat",
    "iso:country":"BE",
    "sg:address":"Democratiestraat 76",
    "sg:city":"Anderlecht",
    "sg:orig_category":"Boekhouders",
    "sg:phone":"+32 2 521 55 26",
    "sg:postcode":"1070",
    "sg:province":"Bruxelles-Capitale",
    "wof:name":"Michel Meys",
    "wof:placetype":"venue"
},
  "geometry": {"coordinates":[4.3095850945,50.8321914673],"type":"Point"}
}