{
  "type": "Feature",
  "properties": {
    "iso:country":"BE",
    "sg:address":"Rue Sainte-marguerite 8",
    "sg:city":"Li\u00e8ge 1",
    "sg:classifiers":[
        {
            "category":"Shopping",
            "subcategory":"Antiques",
            "type":"Retail Goods"
        }
    ],
    "sg:phone":"+32 475 37 45 09",
    "sg:postcode":"4000",
    "sg:province":"Li\u00e8ge",
    "wof:name":"Aaaz Scris",
    "wof:placetype":"venue"
},
  "geometry": {"coordinates":[5.562792778,50.6457252502],"type":"Point"}
}