{
  "type": "Feature",
  "properties": {
    "addr:full":"Rue Du Parc 7 Vielsalm Luxembourg 6690",
    "addr:housenumber":"7",
    "addr:postcode":"6690",
    "addr:street":"Rue Du Parc",
    "iso:country":"BE",
    "sg:address":"Rue Du Parc 7",
    "sg:city":"Vielsalm",
    "sg:orig_category":"Artsen and specialisten",
    "sg:phone":"+32 80 21 41 84",
    "sg:postcode":"6690",
    "sg:province":"Luxembourg",
    "wof:name":"Jean-paul Delcominette",
    "wof:placetype":"venue"
},
  "geometry": {"coordinates":[5.9163608551,50.2837219238],"type":"Point"}
}