{
  "type": "Feature",
  "properties": {
    "iso:country":"BE",
    "sg:address":"Sint-hubertusplein 11",
    "sg:city":"Niel",
    "sg:classifiers":[
        {
            "category":"Food & Beverages",
            "subcategory":"Fruits & Vegetables",
            "type":"Retail Goods"
        }
    ],
    "sg:phone":"+32 3 888 88 13",
    "sg:postcode":"2845",
    "sg:province":"Antwerpen",
    "sg:tags":[
        "groenten"
    ],
    "wof:name":"Bij Jaak & Nancy",
    "wof:placetype":"venue"
},
  "geometry": {"coordinates":[4.3270959854,51.1105461121],"type":"Point"}
}