{
  "type": "Feature",
  "properties": {
    "iso:country":"BE",
    "sg:address":"Capucienenlaan 49",
    "sg:city":"Aalst",
    "sg:classifiers":[
        {
            "category":"Social Services",
            "subcategory":"Job Training",
            "type":"Services"
        }
    ],
    "sg:phone":"+32 53 76 76 20",
    "sg:postcode":"9300",
    "sg:province":"Oost-Vlaanderen",
    "sg:tags":[
        "personnel",
        "-selection",
        "recruitment"
    ],
    "wof:name":"Pharma Support",
    "wof:placetype":"venue"
},
  "geometry": {"coordinates":[4.0287098885,50.9354705811],"type":"Point"}
}