{
  "type": "Feature",
  "properties": {
    "iso:country":"BE",
    "sg:address":"Place Du M\u00d4le 5",
    "sg:city":"Braine-l'alleud (grand)",
    "sg:orig_category":"Sociale secretariaten Verplichte sociale verzekeringen",
    "sg:phone":"+32 2 389 08 80",
    "sg:postcode":"1420",
    "sg:province":"Brabant Wallon",
    "wof:name":"Partena",
    "wof:placetype":"venue"
},
  "geometry": {"coordinates":[-0.7004899979,47.369140625],"type":"Point"}
}