{
  "type": "Feature",
  "properties": {
    "addr:full":"A. Vandenpeereboomplein 21 Ieper West-Vlaanderen 8900",
    "addr:housenumber":"21",
    "addr:postcode":"8900",
    "addr:street":"Vandenpeereboomplein",
    "iso:country":"BE",
    "sg:address":"A. Vandenpeereboomplein 21",
    "sg:city":"Ieper",
    "sg:classifiers":[
        {
            "category":"Cafe",
            "type":"Food & Drink"
        }
    ],
    "sg:phone":"+32 57 20 11 42",
    "sg:postcode":"8900",
    "sg:province":"West-Vlaanderen",
    "sg:tags":[
        "caf\u00e9s"
    ],
    "wof:name":"Caf\u00c9 Boerenhol",
    "wof:placetype":"venue"
},
  "geometry": {"coordinates":[2.8837120533,50.8514442444],"type":"Point"}
}