{
  "type": "Feature",
  "properties": {
    "iso:country":"BE",
    "sg:address":"Mechelsesteenweg 136",
    "sg:city":"Bonheiden",
    "sg:orig_category":"Librairies. Editeurs de livres",
    "sg:phone":"+32 15 33 01 66",
    "sg:postcode":"2820",
    "sg:province":"Antwerpen",
    "wof:name":"Uitgeverij Den Arend",
    "wof:placetype":"venue"
},
  "geometry": {"coordinates":[4.5394701958,51.0252304077],"type":"Point"}
}