{
  "type": "Feature",
  "properties": {
    "iso:country":"BE",
    "sg:address":"Sur Le Spinet 62",
    "sg:city":"Libramont-chevigny",
    "sg:orig_category":"Landbouwmachines Gh",
    "sg:phone":"+32 61 22 50 70",
    "sg:postcode":"6800",
    "sg:province":"Luxembourg",
    "wof:name":"Goedert",
    "wof:placetype":"venue"
},
  "geometry": {"coordinates":[5.3761348724,49.9199943542],"type":"Point"}
}