{
  "type": "Feature",
  "properties": {
    "addr:full":"Cielle 31b La Roche-en-ardenne Luxembourg 6980",
    "addr:housenumber":"31b",
    "addr:postcode":"6980",
    "addr:street":"Cielle",
    "iso:country":"BE",
    "sg:address":"Cielle 31b",
    "sg:city":"La Roche-en-ardenne",
    "sg:orig_category":"Editeurs de livres",
    "sg:phone":"+32 84 41 10 58",
    "sg:postcode":"6980",
    "sg:province":"Luxembourg",
    "wof:name":"Elsa C\u00c9lis",
    "wof:placetype":"venue"
},
  "geometry": {"coordinates":[5.5589699745,50.1943702698],"type":"Point"}
}