{
  "type": "Feature",
  "properties": {
    "iso:country":"BE",
    "sg:address":"Rue Du Chaufour 18",
    "sg:city":"Jemeppe-sur-sambre",
    "sg:orig_category":"V\u00e9t\u00e9rinaires",
    "sg:phone":"+32 71 78 67 17",
    "sg:postcode":"5190",
    "sg:province":"Namur",
    "wof:name":"Pierre Mathieu",
    "wof:placetype":"venue"
},
  "geometry": {"coordinates":[4.699420929,50.4891662598],"type":"Point"}
}