{
  "type": "Feature",
  "properties": {
    "addr:full":"Noord-brabantlaan 12 Turnhout Antwerpen 2300",
    "addr:housenumber":"12",
    "addr:postcode":"2300",
    "addr:street":"Noord-Brabantlaan",
    "iso:country":"BE",
    "sg:address":"Noord-brabantlaan 12",
    "sg:city":"Turnhout",
    "sg:classifiers":[
        {
            "category":"Military Area",
            "subcategory":"Coast Guard Base",
            "type":"Public Place"
        }
    ],
    "sg:phone":"+32 14 46 24 24",
    "sg:postcode":"2300",
    "sg:province":"Antwerpen",
    "sg:tags":[
        "cleaner",
        "industrial",
        "vacuum"
    ],
    "wof:name":"Wijnen J Bvba",
    "wof:placetype":"venue"
},
  "geometry": {"coordinates":[4.9669089317,51.3259086609],"type":"Point"}
}