{
  "type": "Feature",
  "properties": {
    "iso:country":"BE",
    "sg:address":"Volkstraat 26",
    "sg:city":"Antwerpen",
    "sg:classifiers":[
        {
            "category":"Professional",
            "subcategory":"Testing Lab",
            "type":"Services"
        }
    ],
    "sg:phone":"+32 3 238 51 59",
    "sg:postcode":"2000",
    "sg:province":"Antwerpen",
    "sg:tags":[
        "chemist"
    ],
    "wof:name":"De Witte H",
    "wof:placetype":"venue"
},
  "geometry": {"coordinates":[4.3962111473,51.2114601135],"type":"Point"}
}