{
  "type": "Feature",
  "properties": {
    "addr:full":"Turnhoutsebaan 267 Wijnegem Antwerpen 2110",
    "addr:housenumber":"267",
    "addr:postcode":"2110",
    "addr:street":"Turnhoutsebaan",
    "iso:country":"BE",
    "sg:address":"Turnhoutsebaan 267",
    "sg:city":"Wijnegem",
    "sg:classifiers":[
        {
            "category":"Communications",
            "subcategory":"Newspaper",
            "type":"Services"
        }
    ],
    "sg:phone":"+32 3 324 31 76",
    "sg:postcode":"2110",
    "sg:province":"Antwerpen",
    "sg:tags":[
        "paper",
        "local",
        "free"
    ],
    "wof:name":"Publi-pers",
    "wof:placetype":"venue"
},
  "geometry": {"coordinates":[4.5176539421,51.2266578674],"type":"Point"}
}