{
  "type": "Feature",
  "properties": {
    "addr:full":"Route De Surister 59 Jalhay Li\u00e8ge 4845",
    "addr:housenumber":"59",
    "addr:postcode":"4845",
    "addr:street":"Route De Surister",
    "iso:country":"BE",
    "sg:address":"Route De Surister 59",
    "sg:city":"Jalhay",
    "sg:classifiers":[
        {
            "category":"Building & Trades",
            "subcategory":"Electrical",
            "type":"Services"
        }
    ],
    "sg:phone":"+32 87 64 77 58",
    "sg:postcode":"4845",
    "sg:province":"Li\u00e8ge",
    "sg:tags":[
        "electric",
        "-",
        "housewiring",
        "contractor"
    ],
    "wof:name":"Linze J-m",
    "wof:placetype":"venue"
},
  "geometry": {"coordinates":[5.922770977,50.552772522],"type":"Point"}
}