{
  "type": "Feature",
  "properties": {
    "addr:full":"Toekomstlaan 15ba Neerpelt Limburg 3910",
    "addr:housenumber":"15ba",
    "addr:postcode":"3910",
    "addr:street":"Toekomstlaan",
    "iso:country":"BE",
    "sg:address":"Toekomstlaan 15ba",
    "sg:city":"Neerpelt",
    "sg:orig_category":"M\u00e9decins and sp\u00e9cialistes",
    "sg:phone":"+32 11 44 60 76",
    "sg:postcode":"3910",
    "sg:province":"Limburg",
    "wof:name":"Luc Ectors",
    "wof:placetype":"venue"
},
  "geometry": {"coordinates":[5.42456007,51.233089447],"type":"Point"}
}