{
  "type": "Feature",
  "properties": {
    "iso:country":"BE",
    "sg:address":"Rue Du Roy 46",
    "sg:city":"Gouvy (limerl\u00e9)",
    "sg:orig_category":"Autombile concessionaires",
    "sg:phone":"+32 80 51 72 10",
    "sg:postcode":"6670",
    "sg:province":"Luxembourg",
    "wof:name":"Gar R Piron",
    "wof:placetype":"venue"
},
  "geometry": {"coordinates":[5.9258089066,50.1549720764],"type":"Point"}
}