{
  "type": "Feature",
  "properties": {
    "addr:full":"Place Du Grand Sablon 41 Brussel/bruxelles Bruxelles-Capitale 1000",
    "addr:housenumber":"41",
    "addr:postcode":"1000",
    "addr:street":"Place Du Grand Sablon;/",
    "iso:country":"BE",
    "sg:address":"Place Du Grand Sablon 41",
    "sg:city":"Brussel/bruxelles",
    "sg:classifiers":[
        {
            "category":"Professional",
            "subcategory":"Business Services",
            "type":"Services"
        }
    ],
    "sg:phone":"+32 2 512 15 78",
    "sg:postcode":"1000",
    "sg:province":"Bruxelles-Capitale",
    "sg:tags":[
        "aux",
        "diver",
        "entreprises"
    ],
    "wof:name":"Tony Cammaert",
    "wof:placetype":"venue"
},
  "geometry": {"coordinates":[4.3542628288,50.8411865234],"type":"Point"}
}