{
  "type": "Feature",
  "properties": {
    "addr:full":"Augustijnslei 56 Brasschaat Antwerpen 2930",
    "addr:housenumber":"56",
    "addr:postcode":"2930",
    "addr:street":"Augustijnslei",
    "iso:country":"BE",
    "sg:address":"Augustijnslei 56",
    "sg:city":"Brasschaat",
    "sg:orig_category":"Meubles D\u00e9taillants, Am\u00e9nagement de B\u00e2timents et de Cuisines",
    "sg:phone":"+32 3 653 45 70",
    "sg:postcode":"2930",
    "sg:province":"Antwerpen",
    "wof:name":"Ferenc Henczl",
    "wof:placetype":"venue"
},
  "geometry": {"coordinates":[4.4900999069,51.2933273315],"type":"Point"}
}