{
  "type": "Feature",
  "properties": {
    "addr:full":"Guido Gezellelaan 28a Bonheiden Antwerpen 2820",
    "addr:housenumber":"28a",
    "addr:postcode":"2820",
    "addr:street":"Guido Gezellelaan",
    "iso:country":"BE",
    "sg:address":"Guido Gezellelaan 28a",
    "sg:city":"Bonheiden",
    "sg:orig_category":"Salons de coiffure. Centres de relaxation and bien-\u00eatre",
    "sg:phone":"+32 15 51 62 21",
    "sg:postcode":"2820",
    "sg:province":"Antwerpen",
    "wof:name":"Hairstyling Nancy",
    "wof:placetype":"venue"
},
  "geometry": {"coordinates":[4.549973011,51.0210762024],"type":"Point"}
}