{
  "type": "Feature",
  "properties": {
    "addr:full":"Rue Grande 36 Saint-ghislain Hainaut 7330",
    "addr:housenumber":"36",
    "addr:postcode":"7330",
    "addr:street":"Rue Grande;Hainaut",
    "iso:country":"BE",
    "sg:address":"Rue Grande 36",
    "sg:city":"Saint-ghislain",
    "sg:classifiers":[
        {
            "category":"Shopping",
            "subcategory":"Clothing, Apparel, & Fashions",
            "type":"Retail Goods"
        }
    ],
    "sg:phone":"+32 65 78 39 21",
    "sg:postcode":"7330",
    "sg:province":"Hainaut",
    "sg:tags":[
        "lingerie",
        "sous-v\u00eatements"
    ],
    "wof:name":"Maison Scarlett",
    "wof:placetype":"venue"
},
  "geometry": {"coordinates":[3.8199729919,50.4462432861],"type":"Point"}
}