{
  "type": "Feature",
  "properties": {
    "iso:country":"BE",
    "sg:address":"Rue De Joie 56",
    "sg:city":"Li\u00c8ge",
    "sg:orig_category":"Avocats and conseillers juridiques",
    "sg:phone":"+32 4 252 74 29",
    "sg:postcode":"4000",
    "sg:province":"Li\u00e8ge",
    "wof:name":"Beno\u00cet Delacroix",
    "wof:placetype":"venue"
},
  "geometry": {"coordinates":[5.5591850281,50.6288833618],"type":"Point"}
}