{
  "type": "Feature",
  "properties": {
    "addr:full":"Avenue Charbo 35 Bruxelles (schaerbeek) Bruxelles-Capitale 1030",
    "addr:housenumber":"35",
    "addr:postcode":"1030",
    "addr:street":"Avenue Charbo",
    "iso:country":"BE",
    "sg:address":"Avenue Charbo 35",
    "sg:city":"Bruxelles (schaerbeek)",
    "sg:classifiers":[
        {
            "category":"Health Services",
            "subcategory":"Doctor",
            "type":"Services"
        }
    ],
    "sg:phone":"+32 2 733 43 34",
    "sg:postcode":"1030",
    "sg:province":"Bruxelles-Capitale",
    "sg:tags":[
        "psychotherapist",
        "psychoanalyst"
    ],
    "wof:name":"T.i.e.r.s Centre Psychologique Et Social Asbl",
    "wof:placetype":"venue"
},
  "geometry": {"coordinates":[4.3885960579,50.8506736755],"type":"Point"}
}