{
  "type": "Feature",
  "properties": {
    "iso:country":"BE",
    "sg:address":"Kortrijksestraat 186",
    "sg:city":"Kortrijk",
    "sg:orig_category":"Cr\u00e8ches and garderies d'enfants",
    "sg:phone":"+32 56 37 14 73",
    "sg:postcode":"8501",
    "sg:province":"West-Vlaanderen",
    "wof:name":"N.d.o. Kinderopv. W.-vl.",
    "wof:placetype":"venue"
},
  "geometry": {"coordinates":[3.2436709404,50.8369979858],"type":"Point"}
}