{
  "type": "Feature",
  "properties": {
    "iso:country":"BE",
    "sg:address":"Groot-gelmenlaan 86",
    "sg:city":"Sint-truiden",
    "sg:orig_category":"Fruitteelt",
    "sg:phone":"+32 11 48 50 74",
    "sg:postcode":"3800",
    "sg:province":"Limburg",
    "wof:name":"Piet Demeester",
    "wof:placetype":"venue"
},
  "geometry": {"coordinates":[5.1863641739,50.8153343201],"type":"Point"}
}