{
  "type": "Feature",
  "properties": {
    "iso:country":"BE",
    "sg:address":"Jannestraat 43",
    "sg:city":"Hasselt",
    "sg:orig_category":"Installation \u00e9lectrique r\u00e9sidentielle",
    "sg:phone":"+32 11 59 10 42",
    "sg:postcode":"3512",
    "sg:province":"Limburg",
    "wof:name":"Jozef Ottenburgs",
    "wof:placetype":"venue"
},
  "geometry": {"coordinates":[5.2378439903,50.9119873047],"type":"Point"}
}