{
  "type": "Feature",
  "properties": {
    "iso:country":"BE",
    "sg:address":"Runkstersteenweg 16",
    "sg:city":"Hasselt",
    "sg:classifiers":[
        {
            "category":"Cafe",
            "type":"Food & Drink"
        }
    ],
    "sg:phone":"+32 11 27 58 72",
    "sg:postcode":"3500",
    "sg:province":"Limburg",
    "sg:tags":[
        "caf\u00e9s"
    ],
    "wof:name":"Club Hispano - Belga",
    "wof:placetype":"venue"
},
  "geometry": {"coordinates":[5.3304429054,50.929058075],"type":"Point"}
}