{
  "type": "Feature",
  "properties": {
    "addr:full":"Wijnendalestraat 190 Roeselare West-Vlaanderen 8800",
    "addr:housenumber":"190",
    "addr:postcode":"8800",
    "addr:street":"Wijnendalestraat",
    "iso:country":"BE",
    "sg:address":"Wijnendalestraat 190",
    "sg:city":"Roeselare",
    "sg:classifiers":[
        {
            "category":"Government",
            "subcategory":"Customs House",
            "type":"Public Place"
        }
    ],
    "sg:phone":"+32 3 620 18 18",
    "sg:postcode":"8800",
    "sg:province":"West-Vlaanderen",
    "sg:tags":[
        "solutions",
        "custom-made",
        "automation"
    ],
    "wof:name":"E.d.& A. Nv",
    "wof:placetype":"venue"
},
  "geometry": {"coordinates":[4.502245903,51.3554039001],"type":"Point"}
}