{
  "type": "Feature",
  "properties": {
    "addr:full":"Lierselei 56 Malle Antwerpen 2390",
    "addr:housenumber":"56",
    "addr:postcode":"2390",
    "addr:street":"Lierselei",
    "iso:country":"BE",
    "sg:address":"Lierselei 56",
    "sg:city":"Malle",
    "sg:orig_category":"Peinture. Rev\u00eatements pour sols and murs",
    "sg:phone":"+32 3 311 65 36",
    "sg:postcode":"2390",
    "sg:province":"Antwerpen",
    "wof:name":"Arnold Verbraken",
    "wof:placetype":"venue"
},
  "geometry": {"coordinates":[4.7310180664,51.2954406738],"type":"Point"}
}