{
  "type": "Feature",
  "properties": {
    "iso:country":"BE",
    "sg:address":"Rue De L'eglise 2",
    "sg:city":"Houyet",
    "sg:classifiers":[
        {
            "category":"Cafe",
            "type":"Food & Drink"
        }
    ],
    "sg:phone":"+32 82 66 72 42",
    "sg:postcode":"5560",
    "sg:province":"Namur",
    "sg:tags":[
        "caf\u00e9s"
    ],
    "wof:name":"Caf\u00c9 Le Carcan",
    "wof:placetype":"venue"
},
  "geometry": {"coordinates":[5.0115699768,50.1847610474],"type":"Point"}
}