{
  "type": "Feature",
  "properties": {
    "iso:country":"BE",
    "sg:address":"Ruelle Des Capucins 1",
    "sg:city":"Malmedy",
    "sg:classifiers":[
        {
            "category":"Education",
            "subcategory":"Music School",
            "type":"Public Place"
        }
    ],
    "sg:phone":"+32 80 33 89 25",
    "sg:postcode":"4960",
    "sg:province":"Li\u00e8ge",
    "sg:tags":[
        "-",
        "teacher",
        "private"
    ],
    "wof:name":"Acad\u00e9mie De Musique",
    "wof:placetype":"venue"
},
  "geometry": {"coordinates":[6.0304551125,50.4249458313],"type":"Point"}
}