{
  "type": "Feature",
  "properties": {
    "iso:country":"BE",
    "sg:address":"Italielei 124b74",
    "sg:city":"Antwerpen",
    "sg:orig_category":"Agences d'exp\u00e9dition",
    "sg:phone":"+32 3 234 88 11",
    "sg:postcode":"2000",
    "sg:province":"Antwerpen",
    "wof:name":"Oocl Benelux",
    "wof:placetype":"venue"
},
  "geometry": {"coordinates":[4.4157271385,51.2201080322],"type":"Point"}
}