{
  "type": "Feature",
  "properties": {
    "addr:full":"Chauss\u00e9e De Wavre Perwez Brabant Wallon 1360",
    "addr:postcode":"1360",
    "addr:street":"Chausse\u0301E De Wavre",
    "iso:country":"BE",
    "sg:address":"Chauss\u00e9e De Wavre",
    "sg:city":"Perwez",
    "sg:classifiers":[
        {
            "category":"Building & Trades",
            "subcategory":"Construction",
            "type":"Services"
        }
    ],
    "sg:phone":"+32 81 65 42 30",
    "sg:postcode":"1360",
    "sg:province":"Brabant Wallon",
    "sg:tags":[
        "fork",
        "lift",
        "truck"
    ],
    "wof:name":"Manitou B\u00e9n\u00e9lux",
    "wof:placetype":"venue"
},
  "geometry": {"coordinates":[4.8045802116,50.6276512146],"type":"Point"}
}