{
  "type": "Feature",
  "properties": {
    "addr:full":"Terne Coupette 63a Thuin Hainaut 6531",
    "addr:housenumber":"63a",
    "addr:postcode":"6531",
    "addr:street":"Coupette",
    "iso:country":"BE",
    "sg:address":"Terne Coupette 63a",
    "sg:city":"Thuin",
    "sg:orig_category":"Woningbouw",
    "sg:phone":"+32 71 59 59 38",
    "sg:postcode":"6531",
    "sg:province":"Hainaut",
    "wof:name":"Paul Leclercq",
    "wof:placetype":"venue"
},
  "geometry": {"coordinates":[4.3134760857,50.3200912476],"type":"Point"}
}