{
  "type": "Feature",
  "properties": {
    "addr:full":"Tessenderlosesteenweg 111 Beringen (paal) Limburg 3583",
    "addr:housenumber":"111",
    "addr:postcode":"3583",
    "addr:street":"Tessenderlosesteenweg",
    "iso:country":"BE",
    "sg:address":"Tessenderlosesteenweg 111",
    "sg:city":"Beringen (paal)",
    "sg:classifiers":[
        {
            "category":"Shopping",
            "subcategory":"Pets & Pet Supplies",
            "type":"Retail Goods"
        }
    ],
    "sg:phone":"+32 11 42 20 42",
    "sg:postcode":"3583",
    "sg:province":"Limburg",
    "sg:tags":[
        "shop",
        "-"
    ],
    "wof:name":"Ceunen L",
    "wof:placetype":"venue"
},
  "geometry": {"coordinates":[5.1706700325,51.0389442444],"type":"Point"}
}