{
  "type": "Feature",
  "properties": {
    "addr:full":"Gestelsesteenweg 105 Meerhout Antwerpen 2450",
    "addr:housenumber":"105",
    "addr:postcode":"2450",
    "addr:street":"Gestelsesteenweg",
    "iso:country":"BE",
    "sg:address":"Gestelsesteenweg 105",
    "sg:city":"Meerhout",
    "sg:classifiers":[
        {
            "category":"Food & Beverages",
            "subcategory":"Supermarket",
            "type":"Retail Goods"
        }
    ],
    "sg:phone":"+32 14 30 03 23",
    "sg:postcode":"2450",
    "sg:province":"Antwerpen",
    "sg:tags":[
        "department",
        "store"
    ],
    "wof:name":"Spar Supermarkt",
    "wof:placetype":"venue"
},
  "geometry": {"coordinates":[5.0917100906,51.1197013855],"type":"Point"}
}