{
  "type": "Feature",
  "properties": {
    "iso:country":"BE",
    "sg:address":"Gentstraat 317",
    "sg:city":"Meulebeke",
    "sg:orig_category":"Non-Classified Establishments",
    "sg:phone":"+32 51 40 59 54",
    "sg:postcode":"8760",
    "sg:province":"West-Vlaanderen",
    "wof:name":"Lefebre Nv",
    "wof:placetype":"venue"
},
  "geometry": {"coordinates":[3.3479070663,50.9531173706],"type":"Point"}
}