{
  "type": "Feature",
  "properties": {
    "addr:full":"Oever 5 Antwerpen Antwerpen 2000",
    "addr:housenumber":"5",
    "addr:postcode":"2000",
    "addr:street":"Oever",
    "iso:country":"BE",
    "sg:address":"Oever 5",
    "sg:city":"Antwerpen",
    "sg:orig_category":"Salles de spectacles",
    "sg:phone":"+32 3 225 08 11",
    "sg:postcode":"2000",
    "sg:province":"Antwerpen",
    "wof:name":"Artistan Galerij",
    "wof:placetype":"venue"
},
  "geometry": {"coordinates":[4.3968229294,51.2176895142],"type":"Point"}
}