{
  "type": "Feature",
  "properties": {
    "iso:country":"BE",
    "sg:address":"Thier Saint-leonard 91",
    "sg:city":"Grace-hollogne",
    "sg:orig_category":"M\u00e9decins and sp\u00e9cialistes",
    "sg:phone":"+32 4 234 15 59",
    "sg:postcode":"4460",
    "sg:province":"Li\u00e8ge",
    "wof:name":"Fabienne Joannes",
    "wof:placetype":"venue"
},
  "geometry": {"coordinates":[5.4656100273,50.6291542053],"type":"Point"}
}