{
  "type": "Feature",
  "properties": {
    "addr:full":"Engelstraat 57 Ichtegem West-Vlaanderen 8480",
    "addr:housenumber":"57",
    "addr:postcode":"8480",
    "addr:street":"Engelstraat",
    "iso:country":"BE",
    "sg:address":"Engelstraat 57",
    "sg:city":"Ichtegem",
    "sg:orig_category":"Supermarkten Warenhuizen",
    "sg:phone":"+32 51 58 92 22",
    "sg:postcode":"8480",
    "sg:province":"West-Vlaanderen",
    "wof:name":"Unic",
    "wof:placetype":"venue"
},
  "geometry": {"coordinates":[3.0152039528,51.0933151245],"type":"Point"}
}