{
  "type": "Feature",
  "properties": {
    "iso:country":"BE",
    "sg:address":"Grootheide 82",
    "sg:city":"Bornem",
    "sg:classifiers":[
        {
            "category":"Restaurant",
            "type":"Food & Drink"
        }
    ],
    "sg:phone":"+32 3 889 55 78",
    "sg:postcode":"2880",
    "sg:province":"Antwerpen",
    "sg:tags":[
        "caf\u00e9s"
    ],
    "wof:name":"Het Gildenhuis",
    "wof:placetype":"venue"
},
  "geometry": {"coordinates":[4.2216892242,51.0893440247],"type":"Point"}
}