{
  "type": "Feature",
  "properties": {
    "addr:full":"Xavier De Cocklaan 44 Sint-martens-latem Oost-Vlaanderen 9831",
    "addr:housenumber":"44",
    "addr:postcode":"9831",
    "addr:street":"Xavier De Cocklaan",
    "iso:country":"BE",
    "sg:address":"Xavier De Cocklaan 44",
    "sg:city":"Sint-martens-latem",
    "sg:orig_category":"HERSTELLING ELEKTRISCHE HUISHOUDAPPARATEN Huishoudapparaten, televisies and radio's",
    "sg:phone":"+32 9 282 94 59",
    "sg:postcode":"9831",
    "sg:province":"Oost-Vlaanderen",
    "wof:name":"Eldi",
    "wof:placetype":"venue"
},
  "geometry": {"coordinates":[3.6166980267,51.0021133423],"type":"Point"}
}