{
  "type": "Feature",
  "properties": {
    "addr:full":"Gentsesteenweg 93 Wetteren (groot) Oost-Vlaanderen 9230",
    "addr:housenumber":"93",
    "addr:postcode":"9230",
    "addr:street":"Gentsesteenweg;Groot Oost-Vlaanderen",
    "iso:country":"BE",
    "sg:address":"Gentsesteenweg 93",
    "sg:city":"Wetteren (groot)",
    "sg:orig_category":"Supermarch\u00e9s",
    "sg:phone":"+32 9 369 33 80",
    "sg:postcode":"9230",
    "sg:province":"Oost-Vlaanderen",
    "wof:name":"Colruyt",
    "wof:placetype":"venue"
},
  "geometry": {"coordinates":[3.8732609749,51.0005378723],"type":"Point"}
}