{
  "type": "Feature",
  "properties": {
    "iso:country":"BE",
    "sg:address":"Kerkstraat 14",
    "sg:city":"Lille",
    "sg:orig_category":"Artsen and specialisten",
    "sg:phone":"+32 14 88 01 57",
    "sg:postcode":"2275",
    "sg:province":"Antwerpen",
    "wof:name":"R. Van Der Straeten",
    "wof:placetype":"venue"
},
  "geometry": {"coordinates":[4.8228998184,51.2384338379],"type":"Point"}
}