{
  "type": "Feature",
  "properties": {
    "addr:full":"Rue Th\u00e9odore Roosevelt 56 Bruxelles (schaerbeek) Bruxelles-Capitale 1030",
    "addr:housenumber":"56",
    "addr:postcode":"1030",
    "addr:street":"Rue The\u0301Odore Roosevelt",
    "iso:country":"BE",
    "sg:address":"Rue Th\u00e9odore Roosevelt 56",
    "sg:city":"Bruxelles (schaerbeek)",
    "sg:classifiers":[
        {
            "category":"Professional",
            "subcategory":"Lawyer & Legal Services",
            "type":"Services"
        }
    ],
    "sg:phone":"+32 2 736 38 68",
    "sg:postcode":"1030",
    "sg:province":"Bruxelles-Capitale",
    "wof:name":"Monseu Anne",
    "wof:placetype":"venue"
},
  "geometry": {"coordinates":[4.3972949982,50.8454704285],"type":"Point"}
}