{
  "type": "Feature",
  "properties": {
    "iso:country":"BE",
    "sg:address":"Gierlebaan 131",
    "sg:city":"Lille",
    "sg:classifiers":[
        {
            "category":"Retail",
            "subcategory":"Veterinary Services",
            "type":"Services"
        }
    ],
    "sg:phone":"+32 14 88 15 02",
    "sg:postcode":"2275",
    "sg:province":"Antwerpen",
    "sg:tags":[
        "veterinarian"
    ],
    "wof:name":"Cooremans S",
    "wof:placetype":"venue"
},
  "geometry": {"coordinates":[4.8501191139,51.2563819885],"type":"Point"}
}