{
  "type": "Feature",
  "properties": {
    "addr:full":"Rue Des Combattants 11 La Hulpe Brabant Wallon 1310",
    "addr:housenumber":"11",
    "addr:postcode":"1310",
    "addr:street":"Rue Des Combattants",
    "iso:country":"BE",
    "sg:address":"Rue Des Combattants 11",
    "sg:city":"La Hulpe",
    "sg:classifiers":[
        {
            "category":"Personal",
            "subcategory":"Barber",
            "type":"Services"
        }
    ],
    "sg:phone":"+32 2 653 21 00",
    "sg:postcode":"1310",
    "sg:province":"Brabant Wallon",
    "sg:tags":[
        "gentleman",
        "salon",
        "-",
        "hairdressing"
    ],
    "wof:name":"Depierreux L",
    "wof:placetype":"venue"
},
  "geometry": {"coordinates":[4.4921770096,50.7325668335],"type":"Point"}
}