{
  "type": "Feature",
  "properties": {
    "addr:full":"Processiestraat 11 Meerhout Antwerpen 2450",
    "addr:housenumber":"11",
    "addr:postcode":"2450",
    "addr:street":"Processiestraat",
    "iso:country":"BE",
    "sg:address":"Processiestraat 11",
    "sg:city":"Meerhout",
    "sg:orig_category":"Pain, p\u00e2tisseries and confiseries",
    "sg:phone":"+32 14 30 92 30",
    "sg:postcode":"2450",
    "sg:province":"Antwerpen",
    "wof:name":"Bakkerij Wittock",
    "wof:placetype":"venue"
},
  "geometry": {"coordinates":[5.0736131668,51.1322669983],"type":"Point"}
}