{
  "type": "Feature",
  "properties": {
    "iso:country":"BE",
    "sg:address":"Vennestraat 2-1",
    "sg:city":"Herk-de-stad (donk)",
    "sg:classifiers":[
        {
            "category":"Retail",
            "subcategory":"Animal Services",
            "type":"Services"
        }
    ],
    "sg:phone":"+32 13 46 16 20",
    "sg:postcode":"3540",
    "sg:province":"Limburg",
    "sg:tags":[
        "training",
        "dog"
    ],
    "wof:name":"Hondenschool Olmenhof Herk De Stad Vzw",
    "wof:placetype":"venue"
},
  "geometry": {"coordinates":[5.1418128014,50.9331855774],"type":"Point"}
}