{
  "type": "Feature",
  "properties": {
    "iso:country":"BE",
    "sg:address":"Bois D'olne 22bh",
    "sg:city":"Olne",
    "sg:classifiers":[
        {
            "category":"Shopping",
            "subcategory":"Clothing, Apparel, & Fashions",
            "type":"Retail Goods"
        }
    ],
    "sg:phone":"+32 87 26 78 86",
    "sg:postcode":"4877",
    "sg:province":"Li\u00e8ge",
    "sg:tags":[
        "ondergoed",
        "lingerie"
    ],
    "wof:name":"Roland Crosset",
    "wof:placetype":"venue"
},
  "geometry": {"coordinates":[5.7662529945,50.582862854],"type":"Point"}
}