{
  "type": "Feature",
  "properties": {
    "addr:full":"Stuivenbergplein 37 Antwerpen Antwerpen 2060",
    "addr:housenumber":"37",
    "addr:postcode":"2060",
    "addr:street":"Stuivenbergplein",
    "iso:country":"BE",
    "sg:address":"Stuivenbergplein 37",
    "sg:city":"Antwerpen",
    "sg:orig_category":"Enseignement maternel and primaire",
    "sg:phone":"+32 3 236 43 19",
    "sg:postcode":"2060",
    "sg:province":"Antwerpen",
    "wof:name":"Stedelijke Lagere School",
    "wof:placetype":"venue"
},
  "geometry": {"coordinates":[4.4308800697,51.2278404236],"type":"Point"}
}