{
  "type": "Feature",
  "properties": {
    "addr:full":"Rue De Haerne 82-84 Etterbeek/etterbeek Bruxelles-Capitale 1040",
    "addr:postcode":"82-84;1040",
    "addr:street":"Rue De Haerne",
    "iso:country":"BE",
    "sg:address":"Rue De Haerne 82-84",
    "sg:city":"Etterbeek/etterbeek",
    "sg:orig_category":"Secr\u00e9tariats",
    "sg:phone":"+32 2 640 47 00",
    "sg:postcode":"1040",
    "sg:province":"Bruxelles-Capitale",
    "wof:name":"Pica",
    "wof:placetype":"venue"
},
  "geometry": {"coordinates":[4.3831009865,50.8305435181],"type":"Point"}
}