{
  "type": "Feature",
  "properties": {
    "addr:full":"Rue Albert I 275 Binche (leval-trahegnies) Hainaut 7134",
    "addr:housenumber":"275",
    "addr:postcode":"7134",
    "addr:street":"Rue Albert I",
    "iso:country":"BE",
    "sg:address":"Rue Albert I 275",
    "sg:city":"Binche (leval-trahegnies)",
    "sg:classifiers":[
        {
            "category":"Home & Garden",
            "subcategory":"Garden Supply",
            "type":"Retail Goods"
        }
    ],
    "sg:phone":"+32 64 33 65 04",
    "sg:postcode":"7134",
    "sg:province":"Hainaut",
    "sg:tags":[
        "lawn",
        "mower"
    ],
    "wof:name":"Vincent Ets (tondeuses)",
    "wof:placetype":"venue"
},
  "geometry": {"coordinates":[4.2212629318,50.4248771667],"type":"Point"}
}