{
  "type": "Feature",
  "properties": {
    "iso:country":"BE",
    "sg:address":"Kapellestraat 89",
    "sg:city":"Tervuren",
    "sg:orig_category":"Mat\u00e9riel de T\u00e9l\u00e9communication. Electrom\u00e9nager, t\u00e9l\u00e9visions and radios. R\u00e9parations d'appareils \u00e9lect",
    "sg:phone":"+32 2 305 01 01",
    "sg:postcode":"3080",
    "sg:province":"Vlaams-Brabant",
    "wof:name":"B.v.k. Elektro Media",
    "wof:placetype":"venue"
},
  "geometry": {"coordinates":[4.5068058968,50.820400238],"type":"Point"}
}