{
  "type": "Feature",
  "properties": {
    "iso:country":"BE",
    "sg:address":"Lendeleedsestraat 70",
    "sg:city":"Izegem",
    "sg:classifiers":[
        {
            "category":"Real Estate",
            "subcategory":"Architect",
            "type":"Services"
        }
    ],
    "sg:phone":"+32 51 30 78 91",
    "sg:postcode":"8870",
    "sg:province":"West-Vlaanderen",
    "wof:name":"Vergote J",
    "wof:placetype":"venue"
},
  "geometry": {"coordinates":[3.2276740074,50.9133682251],"type":"Point"}
}