{
  "type": "Feature",
  "properties": {
    "iso:country":"BE",
    "sg:address":"Vilvoordsesteenweg 101",
    "sg:city":"Meise",
    "sg:classifiers":[
        {
            "category":"Professional",
            "subcategory":"Lawyer & Legal Services",
            "type":"Services"
        }
    ],
    "sg:phone":"+32 2 270 27 90",
    "sg:postcode":"1860",
    "sg:province":"Vlaams-Brabant",
    "wof:name":"Flamend Carine",
    "wof:placetype":"venue"
},
  "geometry": {"coordinates":[4.3361778259,50.9423522949],"type":"Point"}
}