{
  "type": "Feature",
  "properties": {
    "iso:country":"BE",
    "sg:address":"Tieltseweg 76",
    "sg:city":"Aarschot",
    "sg:classifiers":[
        {
            "category":"Bars & Pubs",
            "subcategory":"Nightclub",
            "type":"Food & Drink"
        }
    ],
    "sg:phone":"+32 16 50 15 83",
    "sg:postcode":"3202",
    "sg:province":"Vlaams-Brabant",
    "sg:tags":[
        "nachtclubs",
        "dancing"
    ],
    "wof:name":"Discotheek The Sound",
    "wof:placetype":"venue"
},
  "geometry": {"coordinates":[4.8936581612,50.9702568054],"type":"Point"}
}