{
  "type": "Feature",
  "properties": {
    "iso:country":"BE",
    "sg:address":"Vlierbeekberg 53",
    "sg:city":"Overijse",
    "sg:classifiers":[
        {
            "category":"Communications",
            "type":"Services"
        }
    ],
    "sg:phone":"+32 2 657 18 96",
    "sg:postcode":"3090",
    "sg:province":"Vlaams-Brabant",
    "sg:tags":[
        "translator"
    ],
    "wof:name":"Amb International",
    "wof:placetype":"venue"
},
  "geometry": {"coordinates":[4.4899821281,50.7726707458],"type":"Point"}
}