{
  "type": "Feature",
  "properties": {
    "addr:full":"St-jansln 10 Kortrijk West-Vlaanderen 8500",
    "addr:housenumber":"10",
    "addr:postcode":"8500",
    "addr:street":"St-Jansln",
    "iso:country":"BE",
    "sg:address":"St-jansln 10",
    "sg:city":"Kortrijk",
    "sg:classifiers":[
        {
            "category":"Banks & Credit Unions",
            "subcategory":"Financial Services",
            "type":"Services"
        }
    ],
    "sg:phone":"+32 78 15 01 75",
    "sg:postcode":"8500",
    "sg:province":"West-Vlaanderen",
    "sg:tags":[
        "banking",
        "finance",
        "insurance"
    ],
    "wof:name":"Verbond Der Kristelijke Ziekenfondsen Mut",
    "wof:placetype":"venue"
},
  "geometry": {"coordinates":[3.2731559277,50.825756073],"type":"Point"}
}