{
  "type": "Feature",
  "properties": {
    "addr:full":"Vrijdagmarkt 47 Gent Oost-Vlaanderen 9000",
    "addr:housenumber":"47",
    "addr:postcode":"9000",
    "addr:street":"Vrijdagmarkt;Oost-Vlaanderen",
    "iso:country":"BE",
    "sg:address":"Vrijdagmarkt 47",
    "sg:city":"Gent",
    "sg:classifiers":[
        {
            "category":"Restaurant",
            "type":"Food & Drink"
        }
    ],
    "sg:phone":"+32 9 225 86 33",
    "sg:postcode":"9000",
    "sg:province":"Oost-Vlaanderen",
    "wof:name":"Keizershof",
    "wof:placetype":"venue"
},
  "geometry": {"coordinates":[3.7253649235,51.0565223694],"type":"Point"}
}