{
  "type": "Feature",
  "properties": {
    "addr:full":"Galgestraat 11 Koekelare West-Vlaanderen 8680",
    "addr:housenumber":"11",
    "addr:postcode":"8680",
    "addr:street":"Galgestraat",
    "iso:country":"BE",
    "sg:address":"Galgestraat 11",
    "sg:city":"Koekelare",
    "sg:orig_category":"Dansscholen",
    "sg:phone":"+32 51 58 84 83",
    "sg:postcode":"8680",
    "sg:province":"West-Vlaanderen",
    "wof:name":"Arlequino",
    "wof:placetype":"venue"
},
  "geometry": {"coordinates":[2.9848070145,51.0909614563],"type":"Point"}
}