{
  "type": "Feature",
  "properties": {
    "addr:full":"Waterpoolstraat 52 Beersel Vlaams-Brabant 1652",
    "addr:housenumber":"52",
    "addr:postcode":"1652",
    "addr:street":"Waterpoolstraat",
    "iso:country":"BE",
    "sg:address":"Waterpoolstraat 52",
    "sg:city":"Beersel",
    "sg:orig_category":"Charpentes and couvertures",
    "sg:phone":"+32 2 381 00 87",
    "sg:postcode":"1652",
    "sg:province":"Vlaams-Brabant",
    "wof:name":"Christian Kindekens",
    "wof:placetype":"venue"
},
  "geometry": {"coordinates":[4.3227419853,50.7447242737],"type":"Point"}
}