{
  "type": "Feature",
  "properties": {
    "addr:full":"Sportlaan 11 Tessenderlo Limburg 3980",
    "addr:housenumber":"11",
    "addr:postcode":"3980",
    "addr:street":"Sportlaan",
    "iso:country":"BE",
    "sg:address":"Sportlaan 11",
    "sg:city":"Tessenderlo",
    "sg:orig_category":"Elektrische installaties voor woningen",
    "sg:phone":"+32 13 66 20 75",
    "sg:postcode":"3980",
    "sg:province":"Limburg",
    "wof:name":"Josephus Hermans",
    "wof:placetype":"venue"
},
  "geometry": {"coordinates":[5.0865459442,51.0759239197],"type":"Point"}
}