{
  "type": "Feature",
  "properties": {
    "iso:country":"BE",
    "sg:address":"Lange Leemstraat 399",
    "sg:city":"Antwerpen",
    "sg:orig_category":"Non-Classified Establishments",
    "sg:phone":"+32 3 239 18 96",
    "sg:postcode":"2018",
    "sg:province":"Antwerpen",
    "wof:name":"Diata Bvba",
    "wof:placetype":"venue"
},
  "geometry": {"coordinates":[4.4264597893,51.2038536072],"type":"Point"}
}