{
  "type": "Feature",
  "properties": {
    "addr:full":"Museumstraat 46 Antwerpen Antwerpen 2000",
    "addr:housenumber":"46",
    "addr:postcode":"2000",
    "addr:street":"Museumstraat",
    "iso:country":"BE",
    "sg:address":"Museumstraat 46",
    "sg:city":"Antwerpen",
    "sg:classifiers":[
        {
            "category":"Restaurant",
            "type":"Food & Drink"
        }
    ],
    "sg:phone":"+32 3 238 09 95",
    "sg:postcode":"2000",
    "sg:province":"Antwerpen",
    "wof:name":"Den Artist",
    "wof:placetype":"venue"
},
  "geometry": {"coordinates":[4.3934397697,51.209148407],"type":"Point"}
}