{
  "type": "Feature",
  "properties": {
    "addr:full":"Edgard Tinelstraat 78 Sint-niklaas Oost-Vlaanderen 9112",
    "addr:housenumber":"78",
    "addr:postcode":"9112",
    "addr:street":"Edgard Tinelstraat",
    "iso:country":"BE",
    "sg:address":"Edgard Tinelstraat 78",
    "sg:city":"Sint-niklaas",
    "sg:orig_category":"Rundveehouders Varkenskwekers",
    "sg:phone":"+32 3 772 56 95",
    "sg:postcode":"9112",
    "sg:province":"Oost-Vlaanderen",
    "wof:name":"Hugo Dullaert",
    "wof:placetype":"venue"
},
  "geometry": {"coordinates":[4.0435461998,51.1632881165],"type":"Point"}
}