{
  "type": "Feature",
  "properties": {
    "addr:full":"Rue Grandes Ruelles 1 Wanze Li\u00e8ge 4520",
    "addr:housenumber":"1",
    "addr:postcode":"4520",
    "addr:street":"Rue Grandes Ruelles",
    "iso:country":"BE",
    "sg:address":"Rue Grandes Ruelles 1",
    "sg:city":"Wanze",
    "sg:classifiers":[
        {
            "category":"Cafe",
            "type":"Food & Drink"
        }
    ],
    "sg:phone":"+32 85 23 68 81",
    "sg:postcode":"4520",
    "sg:province":"Li\u00e8ge",
    "sg:tags":[
        "caf\u00e9s"
    ],
    "wof:name":"Brigitte Ramet",
    "wof:placetype":"venue"
},
  "geometry": {"coordinates":[5.2249369621,50.5433235168],"type":"Point"}
}