{
  "type": "Feature",
  "properties": {
    "addr:full":"R L Coenen 7 Saint-gilles (bruxelles) Bruxelles-Capitale 1060",
    "addr:housenumber":"7",
    "addr:postcode":"1060",
    "addr:street":"Saint-Gilles Bruxelles",
    "iso:country":"BE",
    "sg:address":"R L Coenen 7",
    "sg:city":"Saint-gilles (bruxelles)",
    "sg:classifiers":[
        {
            "category":"Personal",
            "subcategory":"Beauty Salon",
            "type":"Services"
        }
    ],
    "sg:phone":"+32 2 537 32 99",
    "sg:postcode":"1060",
    "sg:province":"Bruxelles-Capitale",
    "sg:tags":[
        "de",
        "coiffure"
    ],
    "wof:name":"Mitch",
    "wof:placetype":"venue"
},
  "geometry": {"coordinates":[4.3448047638,50.8287620544],"type":"Point"}
}