{
  "type": "Feature",
  "properties": {
    "iso:country":"BE",
    "sg:address":"Erfprinslaan 185",
    "sg:city":"Sint-lambrechts-woluwe/woluwe-saint-lambert",
    "sg:orig_category":"Plaatsen van vloer- and muurbekleding Schilders",
    "sg:phone":"+32 2 733 63 75",
    "sg:postcode":"1200",
    "sg:province":"Bruxelles-Capitale",
    "wof:name":"Destoop",
    "wof:placetype":"venue"
},
  "geometry": {"coordinates":[4.4082350731,50.8471946716],"type":"Point"}
}