{
  "type": "Feature",
  "properties": {
    "iso:country":"BE",
    "sg:address":"Merolserheide 5",
    "sg:city":"Eupen",
    "sg:orig_category":"Eleveurs de bovins",
    "sg:phone":"+32 87 86 61 52",
    "sg:postcode":"4701",
    "sg:province":"Li\u00e8ge",
    "wof:name":"Josef Klinkenberg",
    "wof:placetype":"venue"
},
  "geometry": {"coordinates":[6.0461649895,50.6460838318],"type":"Point"}
}