{
  "type": "Feature",
  "properties": {
    "iso:country":"BE",
    "sg:address":"Dudzeelse Steenweg 84",
    "sg:city":"Brugge",
    "sg:classifiers":[
        {
            "category":"Retail",
            "subcategory":"Auto Repair",
            "type":"Services"
        }
    ],
    "sg:phone":"+32 50 34 42 45",
    "sg:postcode":"8000",
    "sg:province":"West-Vlaanderen",
    "sg:tags":[
        "garage"
    ],
    "wof:name":"Corty",
    "wof:placetype":"venue"
},
  "geometry": {"coordinates":[3.2281699181,51.2267951965],"type":"Point"}
}