{
  "type": "Feature",
  "properties": {
    "addr:full":"Rue Du Sart-thiri 50 Grace-hollogne Li\u00e8ge 4460",
    "addr:housenumber":"50",
    "addr:postcode":"4460",
    "addr:street":"Rue Du Sart-Thiri",
    "iso:country":"BE",
    "sg:address":"Rue Du Sart-thiri 50",
    "sg:city":"Grace-hollogne",
    "sg:orig_category":"Kapsalons",
    "sg:phone":"+32 4 250 12 29",
    "sg:postcode":"4460",
    "sg:province":"Li\u00e8ge",
    "wof:name":"Coiffure Myriam",
    "wof:placetype":"venue"
},
  "geometry": {"coordinates":[5.3960051537,50.6218681335],"type":"Point"}
}