{
  "type": "Feature",
  "properties": {
    "addr:full":"Rijselstraat 40 Brugge West-Vlaanderen 8200",
    "addr:housenumber":"40",
    "addr:postcode":"8200",
    "addr:street":"Rijselstraat",
    "iso:country":"BE",
    "sg:address":"Rijselstraat 40",
    "sg:city":"Brugge",
    "sg:orig_category":"Boucheries",
    "sg:phone":"+32 50 38 27 10",
    "sg:postcode":"8200",
    "sg:province":"West-Vlaanderen",
    "wof:name":"Marcel Decloedt",
    "wof:placetype":"venue"
},
  "geometry": {"coordinates":[3.2120358944,51.1896820068],"type":"Point"}
}