{
  "type": "Feature",
  "properties": {
    "addr:full":"Petite Rue 29 Mouscron Hainaut 7700",
    "addr:housenumber":"29",
    "addr:postcode":"7700",
    "addr:street":"Petite Rue",
    "iso:country":"BE",
    "sg:address":"Petite Rue 29",
    "sg:city":"Mouscron",
    "sg:classifiers":[
        {
            "category":"Health Services",
            "subcategory":"Optometrist",
            "type":"Services"
        }
    ],
    "sg:postcode":"7700",
    "sg:province":"Hainaut",
    "wof:name":"Pearle Opticiens",
    "wof:placetype":"venue"
},
  "geometry": {"coordinates":[3.2125959396,50.7443122864],"type":"Point"}
}