{
  "type": "Feature",
  "properties": {
    "addr:full":"Slagmolenstraat 0 Sint-truiden Limburg 3800",
    "addr:housenumber":"0",
    "addr:postcode":"3800",
    "addr:street":"Slagmolenstraat",
    "iso:country":"BE",
    "sg:address":"Slagmolenstraat 0",
    "sg:city":"Sint-truiden",
    "sg:orig_category":"Enseignement maternel and primaire",
    "sg:phone":"+32 11 68 38 14",
    "sg:postcode":"3800",
    "sg:province":"Limburg",
    "wof:name":"K.s.g.o. St.pieter",
    "wof:placetype":"venue"
},
  "geometry": {"coordinates":[5.1841402054,50.8110160828],"type":"Point"}
}