{
  "type": "Feature",
  "properties": {
    "addr:full":"Itegembaan 176 Berlaar Antwerpen 2590",
    "addr:housenumber":"176",
    "addr:postcode":"2590",
    "addr:street":"Itegembaan",
    "iso:country":"BE",
    "sg:address":"Itegembaan 176",
    "sg:city":"Berlaar",
    "sg:classifiers":[
        {
            "category":"Professional",
            "subcategory":"Management & Consulting",
            "type":"Services"
        }
    ],
    "sg:phone":"+32 3 482 02 40",
    "sg:postcode":"2590",
    "sg:province":"Antwerpen",
    "sg:tags":[
        "marketing",
        "-",
        "consultant"
    ],
    "wof:name":"Fimaco",
    "wof:placetype":"venue"
},
  "geometry": {"coordinates":[4.6730217934,51.1096076965],"type":"Point"}
}