{
  "type": "Feature",
  "properties": {
    "iso:country":"BE",
    "sg:address":"No\u00ebl Schoorensstraat 29",
    "sg:city":"Nazareth (eke)",
    "sg:classifiers":[
        {
            "category":"Professional",
            "subcategory":"Management & Consulting",
            "type":"Services"
        }
    ],
    "sg:phone":"+32 9 328 67 07",
    "sg:postcode":"9810",
    "sg:province":"Oost-Vlaanderen",
    "sg:tags":[
        "consultant",
        "law"
    ],
    "wof:name":"Fiduciaire Tedege",
    "wof:placetype":"venue"
},
  "geometry": {"coordinates":[3.6429591179,50.9565582275],"type":"Point"}
}