{
  "type": "Feature",
  "properties": {
    "iso:country":"BE",
    "sg:address":"Stationsstraat 164",
    "sg:city":"Berlaar",
    "sg:orig_category":"Epiceries",
    "sg:phone":"+32 3 482 11 77",
    "sg:postcode":"2590",
    "sg:province":"Antwerpen",
    "wof:name":"Huis Roothooft",
    "wof:placetype":"venue"
},
  "geometry": {"coordinates":[4.6432609558,51.1145210266],"type":"Point"}
}