{
  "type": "Feature",
  "properties": {
    "iso:country":"BE",
    "sg:address":"Rue Des Trois Ch\u00eanes 6",
    "sg:city":"Soumagne (ayeneux)",
    "sg:classifiers":[
        {
            "category":"Building & Trades",
            "subcategory":"Construction",
            "type":"Services"
        }
    ],
    "sg:phone":"+32 4 358 34 53",
    "sg:postcode":"4630",
    "sg:province":"Li\u00e8ge",
    "sg:tags":[
        "carpenter"
    ],
    "wof:name":"Gardier & Fils Sprl",
    "wof:placetype":"venue"
},
  "geometry": {"coordinates":[5.7062158585,50.6122512817],"type":"Point"}
}