{
  "type": "Feature",
  "properties": {
    "iso:country":"BE",
    "sg:address":"Leopoldlaan 22",
    "sg:city":"De Haan",
    "sg:orig_category":"Brood, gebak and snoepgoed",
    "sg:phone":"+32 59 23 54 64",
    "sg:postcode":"8420",
    "sg:province":"West-Vlaanderen",
    "wof:name":"Austr.home Made Ice Cream",
    "wof:placetype":"venue"
},
  "geometry": {"coordinates":[3.0304260254,51.2748794556],"type":"Point"}
}