{
  "type": "Feature",
  "properties": {
    "iso:country":"BE",
    "sg:address":"Onderwijslaan 100",
    "sg:city":"Diepenbeek",
    "sg:classifiers":[
        {
            "category":"Organizations",
            "subcategory":"Professional Association",
            "type":"Services"
        }
    ],
    "sg:phone":"+32 11 32 40 96",
    "sg:postcode":"3590",
    "sg:province":"Limburg",
    "sg:tags":[
        "trade-union",
        "federation"
    ],
    "wof:name":"Grootkeukenkoks Limburg Vzw",
    "wof:placetype":"venue"
},
  "geometry": {"coordinates":[5.4647197723,50.9253082275],"type":"Point"}
}