{
  "type": "Feature",
  "properties": {
    "iso:country":"BE",
    "sg:address":"Hellestraat 14a",
    "sg:city":"Stekene",
    "sg:orig_category":"Kapsalons",
    "sg:phone":"+32 3 779 78 32",
    "sg:postcode":"9190",
    "sg:province":"Oost-Vlaanderen",
    "wof:name":"Coiffure Sabine",
    "wof:placetype":"venue"
},
  "geometry": {"coordinates":[4.0351009369,51.2243690491],"type":"Point"}
}