{
  "type": "Feature",
  "properties": {
    "iso:country":"BE",
    "sg:address":"Route De Coo 28",
    "sg:city":"Stavelot",
    "sg:orig_category":"Eleveurs de bovins",
    "sg:phone":"+32 80 86 31 45",
    "sg:postcode":"4970",
    "sg:province":"Li\u00e8ge",
    "wof:name":"Lucien Hurlet",
    "wof:placetype":"venue"
},
  "geometry": {"coordinates":[5.879281044,50.3964614868],"type":"Point"}
}