{
  "type": "Feature",
  "properties": {
    "iso:country":"BE",
    "sg:address":"Gentsesteenweg 85",
    "sg:city":"Kortrijk",
    "sg:classifiers":[
        {
            "category":"Cafe",
            "type":"Food & Drink"
        }
    ],
    "sg:phone":"+32 56 20 34 00",
    "sg:postcode":"8500",
    "sg:province":"West-Vlaanderen",
    "sg:tags":[
        "caf\u00e9s"
    ],
    "wof:name":"Lucienne Deweerdt",
    "wof:placetype":"venue"
},
  "geometry": {"coordinates":[3.2745549679,50.8310089111],"type":"Point"}
}