{
  "type": "Feature",
  "properties": {
    "addr:full":"Dorpsstraat 22 Bekkevoort Vlaams-Brabant 3460",
    "addr:housenumber":"22",
    "addr:postcode":"3460",
    "addr:street":"Dorpsstraat",
    "iso:country":"BE",
    "sg:address":"Dorpsstraat 22",
    "sg:city":"Bekkevoort",
    "sg:classifiers":[
        {
            "category":"Cafe",
            "type":"Food & Drink"
        }
    ],
    "sg:phone":"+32 13 31 37 06",
    "sg:postcode":"3460",
    "sg:province":"Vlaams-Brabant",
    "sg:tags":[
        "caf\u00e9s"
    ],
    "wof:name":"Caf\u00c9 Congo",
    "wof:placetype":"venue"
},
  "geometry": {"coordinates":[4.975605011,50.9449462891],"type":"Point"}
}