{
  "type": "Feature",
  "properties": {
    "iso:country":"BE",
    "sg:address":"Bredabaan 696",
    "sg:city":"Brasschaat",
    "sg:orig_category":"Assistances juridiques",
    "sg:phone":"+32 3 633 00 75",
    "sg:postcode":"2930",
    "sg:province":"Antwerpen",
    "wof:name":"Wetswinkel",
    "wof:placetype":"venue"
},
  "geometry": {"coordinates":[4.5165500641,51.3161697388],"type":"Point"}
}