{
  "type": "Feature",
  "properties": {
    "addr:full":"Bronnestraat 3 Maarkedal Oost-Vlaanderen 9680",
    "addr:housenumber":"3",
    "addr:postcode":"9680",
    "addr:street":"Bronnestraat",
    "iso:country":"BE",
    "sg:address":"Bronnestraat 3",
    "sg:city":"Maarkedal",
    "sg:orig_category":"Boissons Gr",
    "sg:phone":"+32 55 31 28 31",
    "sg:postcode":"9680",
    "sg:province":"Oost-Vlaanderen",
    "wof:name":"Louis Van Der Donckt",
    "wof:placetype":"venue"
},
  "geometry": {"coordinates":[3.6092019081,50.8012924194],"type":"Point"}
}