{
  "type": "Feature",
  "properties": {
    "addr:full":"Hortensiastraat 107ba Gent Oost-Vlaanderen 9000",
    "addr:housenumber":"107ba",
    "addr:postcode":"9000",
    "addr:street":"Hortensiastraat;Oost-Vlaanderen",
    "iso:country":"BE",
    "sg:address":"Hortensiastraat 107ba",
    "sg:city":"Gent",
    "sg:orig_category":"Verhuur televisie- and audiovisuele apparatuur",
    "sg:phone":"+32 9 227 53 92",
    "sg:postcode":"9000",
    "sg:province":"Oost-Vlaanderen",
    "wof:name":"Fa. Junkhead Productions",
    "wof:placetype":"venue"
},
  "geometry": {"coordinates":[3.7046580315,51.0696144104],"type":"Point"}
}