{
  "type": "Feature",
  "properties": {
    "iso:country":"BE",
    "sg:address":"Rue Du Hameau 170",
    "sg:city":"Sint-genesius-rode/rhode-saint-genese",
    "sg:orig_category":"Enseignement maternel and primaire",
    "sg:phone":"+32 2 358 24 27",
    "sg:postcode":"1640",
    "sg:province":"Vlaams-Brabant",
    "wof:name":"Vrije Kleuterschool",
    "wof:placetype":"venue"
},
  "geometry": {"coordinates":[4.3711800575,50.7384490967],"type":"Point"}
}