{
  "type": "Feature",
  "properties": {
    "addr:full":"Jonker Janlaan 3 Landen Vlaams-Brabant 3404",
    "addr:housenumber":"3",
    "addr:postcode":"3404",
    "addr:street":"Jonker Janlaan",
    "iso:country":"BE",
    "sg:address":"Jonker Janlaan 3",
    "sg:city":"Landen",
    "sg:orig_category":"Enseignement maternel and primaire",
    "sg:phone":"+32 11 83 14 69",
    "sg:postcode":"3404",
    "sg:province":"Vlaams-Brabant",
    "wof:name":"Vrije Basisschool",
    "wof:placetype":"venue"
},
  "geometry": {"coordinates":[5.0965061188,50.7706451416],"type":"Point"}
}