{
  "type": "Feature",
  "properties": {
    "addr:full":"Leopold I Straat 371 Jette Bruxelles-Capitale 1090",
    "addr:housenumber":"371",
    "addr:postcode":"1090",
    "addr:street":"Leopold I Straat",
    "iso:country":"BE",
    "sg:address":"Leopold I Straat 371",
    "sg:city":"Jette",
    "sg:orig_category":"Kapsalons",
    "sg:phone":"+32 2 428 30 51",
    "sg:postcode":"1090",
    "sg:province":"Bruxelles-Capitale",
    "wof:name":"Hairstyling",
    "wof:placetype":"venue"
},
  "geometry": {"coordinates":[4.3349590302,50.8753662109],"type":"Point"}
}