{
  "type": "Feature",
  "properties": {
    "iso:country":"BE",
    "sg:address":"Budasteenweg 2b",
    "sg:city":"Machelen",
    "sg:classifiers":[
        {
            "category":"Professional",
            "type":"Services"
        }
    ],
    "sg:phone":"+32 2 253 25 50",
    "sg:postcode":"1830",
    "sg:province":"Vlaams-Brabant",
    "sg:tags":[
        "transport",
        "road"
    ],
    "wof:name":"Trans Euro Worldwide Movers (belgium) Nv",
    "wof:placetype":"venue"
},
  "geometry": {"coordinates":[4.4173679352,50.9062995911],"type":"Point"}
}