{
  "type": "Feature",
  "properties": {
    "iso:country":"BE",
    "sg:address":"Rue Des Fosses 2",
    "sg:city":"Momignies",
    "sg:orig_category":"Rundveehouders",
    "sg:phone":"+32 60 51 15 15",
    "sg:postcode":"6596",
    "sg:province":"Hainaut",
    "wof:name":"Jean Parent",
    "wof:placetype":"venue"
},
  "geometry": {"coordinates":[4.246336937,49.9770469666],"type":"Point"}
}