{
  "type": "Feature",
  "properties": {
    "iso:country":"BE",
    "sg:address":"Roeselaarsestraat 259",
    "sg:city":"Izegem",
    "sg:orig_category":"Boucheries",
    "sg:phone":"+32 51 30 10 18",
    "sg:postcode":"8870",
    "sg:province":"West-Vlaanderen",
    "wof:name":"W. Demuynck",
    "wof:placetype":"venue"
},
  "geometry": {"coordinates":[3.2010760307,50.9212799072],"type":"Point"}
}