{
  "type": "Feature",
  "properties": {
    "iso:country":"BE",
    "sg:address":"Rijselstraat 163",
    "sg:city":"Menen",
    "sg:orig_category":"Brood, gebak and snoepgoed",
    "sg:phone":"+32 56 51 74 53",
    "sg:postcode":"8930",
    "sg:province":"West-Vlaanderen",
    "wof:name":"Huis Caprice",
    "wof:placetype":"venue"
},
  "geometry": {"coordinates":[3.1259839535,50.7894325256],"type":"Point"}
}