{
  "type": "Feature",
  "properties": {
    "iso:country":"BE",
    "sg:address":"Kastelein 35",
    "sg:city":"Turnhout",
    "sg:orig_category":"Dierenartsen",
    "sg:phone":"+32 14 42 28 73",
    "sg:postcode":"2300",
    "sg:province":"Antwerpen",
    "wof:name":"M. Van Eemeren",
    "wof:placetype":"venue"
},
  "geometry": {"coordinates":[4.9453940392,51.3345947266],"type":"Point"}
}