{
  "type": "Feature",
  "properties": {
    "iso:country":"BE",
    "sg:address":"Burg. Van Gansberghelaan 47",
    "sg:city":"Merelbeke",
    "sg:orig_category":"Sportclubs",
    "sg:phone":"+32 9 362 40 96",
    "sg:postcode":"9820",
    "sg:province":"Oost-Vlaanderen",
    "wof:name":"Ijshockeyclub Misstral",
    "wof:placetype":"venue"
},
  "geometry": {"coordinates":[3.7737998962,50.9786186218],"type":"Point"}
}