{
  "type": "Feature",
  "properties": {
    "iso:country":"BE",
    "sg:address":"Rue Gustave Schildknecht 74",
    "sg:city":"Brussel/bruxelles",
    "sg:orig_category":"Artistes ind\u00e9pendants",
    "sg:phone":"+32 2 424 22 91",
    "sg:postcode":"1020",
    "sg:province":"Bruxelles-Capitale",
    "wof:name":"Willy Cox",
    "wof:placetype":"venue"
},
  "geometry": {"coordinates":[4.3472189903,50.8738441467],"type":"Point"}
}