{
  "type": "Feature",
  "properties": {
    "addr:full":"Klein Tegelrijstraat 100 Nieuwerkerken Limburg 3850",
    "addr:housenumber":"100",
    "addr:postcode":"3850",
    "addr:street":"Klein Tegelrijstraat",
    "iso:country":"BE",
    "sg:address":"Klein Tegelrijstraat 100",
    "sg:city":"Nieuwerkerken",
    "sg:classifiers":[
        {
            "category":"Professional",
            "subcategory":"Art Services",
            "type":"Services"
        }
    ],
    "sg:phone":"+32 11 59 79 93",
    "sg:postcode":"3850",
    "sg:province":"Limburg",
    "sg:tags":[
        "-",
        "mailing",
        "lettershops",
        "direct",
        "mail"
    ],
    "wof:name":"P & L Publiciteitsonderneming",
    "wof:placetype":"venue"
},
  "geometry": {"coordinates":[5.1885042191,50.8799591064],"type":"Point"}
}