{
  "type": "Feature",
  "properties": {
    "addr:full":"Rue De Coquelet 199 Namur (bouge) Namur 5004",
    "addr:housenumber":"199",
    "addr:postcode":"5004",
    "addr:street":"Rue De Coquelet",
    "iso:country":"BE",
    "sg:address":"Rue De Coquelet 199",
    "sg:city":"Namur (bouge)",
    "sg:classifiers":[
        {
            "category":"Shopping",
            "subcategory":"Computers & Home Electronics",
            "type":"Retail Goods"
        }
    ],
    "sg:phone":"+32 81 21 02 41",
    "sg:postcode":"5004",
    "sg:province":"Namur",
    "sg:tags":[
        "plate",
        "name"
    ],
    "wof:name":"Synoptiques Jacobs",
    "wof:placetype":"venue"
},
  "geometry": {"coordinates":[4.8819141388,50.4729499817],"type":"Point"}
}