{
  "type": "Feature",
  "properties": {
    "iso:country":"BE",
    "sg:address":"Goethalsstraat 12",
    "sg:city":"Eeklo",
    "sg:orig_category":"Kapsalons",
    "sg:phone":"+32 9 377 81 47",
    "sg:postcode":"9900",
    "sg:province":"Oost-Vlaanderen",
    "wof:name":"Den Artiest",
    "wof:placetype":"venue"
},
  "geometry": {"coordinates":[3.556415081,51.1885147095],"type":"Point"}
}