{
  "type": "Feature",
  "properties": {
    "iso:country":"BE",
    "sg:address":"Rue Edouard Stuckens 126",
    "sg:city":"Bruxelles (evere)",
    "sg:classifiers":[
        {
            "category":"Building & Trades",
            "subcategory":"Cleaning & Sanitation",
            "type":"Services"
        }
    ],
    "sg:phone":"+32 2 242 06 16",
    "sg:postcode":"1140",
    "sg:province":"Bruxelles-Capitale",
    "sg:tags":[
        "-",
        "rug",
        "carpet"
    ],
    "wof:name":"Sobelnet Maintenance Scrl",
    "wof:placetype":"venue"
},
  "geometry": {"coordinates":[4.3983578682,50.8761482239],"type":"Point"}
}