{
  "type": "Feature",
  "properties": {
    "addr:full":"Meidoornlaan 10b1 Kapellen Antwerpen 2950",
    "addr:housenumber":"10b1",
    "addr:postcode":"2950",
    "addr:street":"Meidoornlaan",
    "iso:country":"BE",
    "sg:address":"Meidoornlaan 10b1",
    "sg:city":"Kapellen",
    "sg:orig_category":"M\u00e9decins and sp\u00e9cialistes",
    "sg:phone":"+32 3 605 00 89",
    "sg:postcode":"2950",
    "sg:province":"Antwerpen",
    "wof:name":"Dominique Denil",
    "wof:placetype":"venue"
},
  "geometry": {"coordinates":[4.431871891,51.3209762573],"type":"Point"}
}