{
  "type": "Feature",
  "properties": {
    "iso:country":"BE",
    "sg:address":"Visstraat 1-3",
    "sg:city":"Eeklo",
    "sg:orig_category":"Rev\u00eatements de sols and murs. Eclairage et \u00e9quipements du foyer. Peinture. Rev\u00eatements pour sols and",
    "sg:phone":"+32 9 377 37 80",
    "sg:postcode":"9900",
    "sg:province":"Oost-Vlaanderen",
    "wof:name":"Filip - Bert Decoratie",
    "wof:placetype":"venue"
},
  "geometry": {"coordinates":[3.573168993,51.180305481],"type":"Point"}
}