{
  "type": "Feature",
  "properties": {
    "iso:country":"BE",
    "sg:address":"8",
    "sg:city":"President Kennedypark 8500 Kortrijk",
    "sg:classifiers":[
        {
            "category":"Food & Beverages",
            "subcategory":"Groceries & Convenience Stores",
            "type":"Retail Goods"
        }
    ],
    "sg:phone":"+32 56 23 21 11",
    "sg:postcode":"8",
    "sg:tags":[
        "product",
        "related"
    ],
    "wof:name":"Vandemoortele Coordination Center Nv",
    "wof:placetype":"venue"
},
  "geometry": {"coordinates":[3.2716150284,50.798286438],"type":"Point"}
}