{
  "type": "Feature",
  "properties": {
    "addr:full":"Schensbossen 15 Rumst (reet) Antwerpen 2840",
    "addr:housenumber":"15",
    "addr:postcode":"2840",
    "addr:street":"Schensbossen",
    "iso:country":"BE",
    "sg:address":"Schensbossen 15",
    "sg:city":"Rumst (reet)",
    "sg:orig_category":"Non-Classified Establishments",
    "sg:phone":"+32 3 844 35 33",
    "sg:postcode":"2840",
    "sg:province":"Antwerpen",
    "wof:name":"Actual Systems Bvba",
    "wof:placetype":"venue"
},
  "geometry": {"coordinates":[4.4031271935,51.105670929],"type":"Point"}
}