{
  "type": "Feature",
  "properties": {
    "iso:country":"BE",
    "sg:address":"Klokstraat 7",
    "sg:city":"Genk",
    "sg:orig_category":"V\u00eatements pour b\u00e9b\u00e9s and enfants",
    "sg:phone":"+32 89 30 30 34",
    "sg:postcode":"3600",
    "sg:province":"Limburg",
    "wof:name":"Huis Petissimo",
    "wof:placetype":"venue"
},
  "geometry": {"coordinates":[5.4998598099,50.9645347595],"type":"Point"}
}