{
  "type": "Feature",
  "properties": {
    "iso:country":"BE",
    "sg:address":"Dolfijnenstraat 2",
    "sg:city":"Sint-jans-molenbeek/molenbeek-saint-jean",
    "sg:orig_category":"Foto-uitrusting Fotografen and fotostudio's Fotogravure and zetwerk Fotolaboratoria",
    "sg:phone":"+32 2 414 95 25",
    "sg:postcode":"1080",
    "sg:province":"Bruxelles-Capitale",
    "wof:name":"J. Duquesne",
    "wof:placetype":"venue"
},
  "geometry": {"coordinates":[4.3105998039,50.8526954651],"type":"Point"}
}