{
  "type": "Feature",
  "properties": {
    "iso:country":"BE",
    "sg:address":"Boommeerstraat 18",
    "sg:city":"Genk",
    "sg:classifiers":[
        {
            "category":"Cafe",
            "type":"Food & Drink"
        }
    ],
    "sg:phone":"+32 89 38 48 98",
    "sg:postcode":"3600",
    "sg:province":"Limburg",
    "sg:tags":[
        "caf\u00e9s"
    ],
    "wof:name":"Medlak",
    "wof:placetype":"venue"
},
  "geometry": {"coordinates":[5.5406842232,50.9893417358],"type":"Point"}
}