{
  "type": "Feature",
  "properties": {
    "addr:full":"Kerkweg 23 Lommel Limburg 3920",
    "addr:housenumber":"23",
    "addr:postcode":"3920",
    "addr:street":"Kerkweg",
    "iso:country":"BE",
    "sg:address":"Kerkweg 23",
    "sg:city":"Lommel",
    "sg:orig_category":"Herstelling leer and schoeisel",
    "sg:phone":"+32 11 34 39 00",
    "sg:postcode":"3920",
    "sg:province":"Limburg",
    "wof:name":"Schoenmakerij Michel",
    "wof:placetype":"venue"
},
  "geometry": {"coordinates":[5.3142318726,51.2286338806],"type":"Point"}
}