{
  "type": "Feature",
  "properties": {
    "iso:country":"BE",
    "sg:address":"Grand Route 106-5",
    "sg:city":"Sprimont (rouvreux)",
    "sg:classifiers":[
        {
            "category":"Home & Garden",
            "subcategory":"Carpets & Floor Coverings",
            "type":"Retail Goods"
        }
    ],
    "sg:phone":"+32 89 75 51 82",
    "sg:postcode":"4140",
    "sg:province":"Li\u00e8ge",
    "sg:tags":[
        "tile"
    ],
    "wof:name":"Belstone Bvba",
    "wof:placetype":"venue"
},
  "geometry": {"coordinates":[5.6684727669,50.4860916138],"type":"Point"}
}