{
  "type": "Feature",
  "properties": {
    "iso:country":"BE",
    "sg:address":"Am Waisenbuschen 6",
    "sg:city":"Eupen",
    "sg:orig_category":"Vertalers and tolken",
    "sg:phone":"+32 87 55 73 72",
    "sg:postcode":"4700",
    "sg:province":"Li\u00e8ge",
    "wof:name":"Nix D. Cbtip/bkvtf",
    "wof:placetype":"venue"
},
  "geometry": {"coordinates":[6.0284152031,50.6219711304],"type":"Point"}
}