{
  "type": "Feature",
  "properties": {
    "addr:full":"Rue Auguste Scohy 262 Aiseau-presles (pont-de-loup) Hainaut 6250",
    "addr:housenumber":"262",
    "addr:postcode":"6250",
    "addr:street":"Rue Auguste Scohy;Pont-De-Loup Hainaut",
    "iso:country":"BE",
    "sg:address":"Rue Auguste Scohy 262",
    "sg:city":"Aiseau-presles (pont-de-loup)",
    "sg:classifiers":[
        {
            "category":"Building & Trades",
            "subcategory":"Construction",
            "type":"Services"
        }
    ],
    "sg:phone":"+32 71 39 35 33",
    "sg:postcode":"6250",
    "sg:province":"Hainaut",
    "sg:tags":[
        "carpenter"
    ],
    "wof:name":"Deyonghe D",
    "wof:placetype":"venue"
},
  "geometry": {"coordinates":[4.5582108498,50.4125862122],"type":"Point"}
}