{
  "type": "Feature",
  "properties": {
    "addr:full":"Ninoofsesteenweg 13 Halle Vlaams-Brabant 1500",
    "addr:housenumber":"13",
    "addr:postcode":"1500",
    "addr:street":"Ninoofsesteenweg",
    "iso:country":"BE",
    "sg:address":"Ninoofsesteenweg 13",
    "sg:city":"Halle",
    "sg:orig_category":"Tijdelijke werkgelegenheid and uitzendkantoren",
    "sg:phone":"+32 2 361 60 81",
    "sg:postcode":"1500",
    "sg:province":"Vlaams-Brabant",
    "wof:name":"T Interim",
    "wof:placetype":"venue"
},
  "geometry": {"coordinates":[4.2356038094,50.7366027832],"type":"Point"}
}