{
  "type": "Feature",
  "properties": {
    "addr:full":"Oostlaan 10 Poperinge West-Vlaanderen 8970",
    "addr:housenumber":"10",
    "addr:postcode":"8970",
    "addr:street":"Oostlaan",
    "iso:country":"BE",
    "sg:address":"Oostlaan 10",
    "sg:city":"Poperinge",
    "sg:classifiers":[
        {
            "category":"Autos & Motor Vehicles",
            "subcategory":"Automobile Sales",
            "type":"Retail Goods"
        }
    ],
    "sg:phone":"+32 57 30 18 98",
    "sg:postcode":"8970",
    "sg:province":"West-Vlaanderen",
    "sg:tags":[
        "distributor",
        "independent",
        "-"
    ],
    "wof:name":"Demeester D",
    "wof:placetype":"venue"
},
  "geometry": {"coordinates":[2.744314909,50.8556137085],"type":"Point"}
}