{
  "type": "Feature",
  "properties": {
    "addr:full":". La Louviere Hainaut 7100",
    "addr:postcode":"7100",
    "iso:country":"BE",
    "sg:address":".",
    "sg:city":"La Louviere",
    "sg:classifiers":[
        {
            "category":"Taxi",
            "type":"Transportation"
        }
    ],
    "sg:phone":"+32 64 84 92 92",
    "sg:postcode":"7100",
    "sg:province":"Hainaut",
    "sg:tags":[
        "taxi's"
    ],
    "wof:name":"Taxi Chapelois",
    "wof:placetype":"venue"
},
  "geometry": {"coordinates":[4.1850848198,50.4748649597],"type":"Point"}
}