{
  "type": "Feature",
  "properties": {
    "addr:full":"Sint-pietersstraat 2 Izegem West-Vlaanderen 8870",
    "addr:housenumber":"2",
    "addr:postcode":"8870",
    "addr:street":"Sint-Pietersstraat",
    "iso:country":"BE",
    "sg:address":"Sint-pietersstraat 2",
    "sg:city":"Izegem",
    "sg:orig_category":"Effectenmakelaars and vermogensbeheer",
    "sg:phone":"+32 51 30 05 76",
    "sg:postcode":"8870",
    "sg:province":"West-Vlaanderen",
    "wof:name":"Gevaert - Vynckier",
    "wof:placetype":"venue"
},
  "geometry": {"coordinates":[3.2144091129,50.916557312],"type":"Point"}
}