{
  "type": "Feature",
  "properties": {
    "iso:country":"BE",
    "sg:address":"Rue Emile Verhaeren 13",
    "sg:city":"Boussu",
    "sg:orig_category":"Apotheken",
    "sg:phone":"+32 65 65 24 27",
    "sg:postcode":"7300",
    "sg:province":"Hainaut",
    "wof:name":"Pharmacie St.joseph",
    "wof:placetype":"venue"
},
  "geometry": {"coordinates":[3.7942690849,50.4128494263],"type":"Point"}
}