{
  "type": "Feature",
  "properties": {
    "iso:country":"BE",
    "sg:address":"Roanne 11",
    "sg:city":"Stoumont",
    "sg:orig_category":"Rundveehouders",
    "sg:phone":"+32 80 78 54 79",
    "sg:postcode":"4987",
    "sg:province":"Li\u00e8ge",
    "wof:name":"Hubert Starck",
    "wof:placetype":"venue"
},
  "geometry": {"coordinates":[5.8717889786,50.4163703918],"type":"Point"}
}