{
  "type": "Feature",
  "properties": {
    "addr:full":"Heiken 17 Brecht (sint-lenaarts) Antwerpen 2960",
    "addr:housenumber":"17",
    "addr:postcode":"2960",
    "addr:street":"Heiken",
    "iso:country":"BE",
    "sg:address":"Heiken 17",
    "sg:city":"Brecht (sint-lenaarts)",
    "sg:classifiers":[
        {
            "category":"Utilities",
            "subcategory":"Natural Gas",
            "type":"Services"
        }
    ],
    "sg:phone":"+32 3 313 83 64",
    "sg:postcode":"2960",
    "sg:province":"Antwerpen",
    "sg:tags":[
        "industrial",
        "-"
    ],
    "wof:name":"Vos Handelsonderneming Pvba",
    "wof:placetype":"venue"
},
  "geometry": {"coordinates":[4.567056179,51.3036308289],"type":"Point"}
}