{
  "type": "Feature",
  "properties": {
    "addr:full":"Lange Kievitstraat 73 Antwerpen Antwerpen 2018",
    "addr:housenumber":"73",
    "addr:postcode":"2018",
    "addr:street":"Lange Kievitstraat",
    "iso:country":"BE",
    "sg:address":"Lange Kievitstraat 73",
    "sg:city":"Antwerpen",
    "sg:orig_category":"Imprimeries and copyshops",
    "sg:phone":"+32 3 233 61 21",
    "sg:postcode":"2018",
    "sg:province":"Antwerpen",
    "wof:name":"Akiba Schreiber",
    "wof:placetype":"venue"
},
  "geometry": {"coordinates":[4.4201397896,51.2130279541],"type":"Point"}
}