{
  "type": "Feature",
  "properties": {
    "addr:full":"Rue Du Planois 44ba Mettet Namur 5640",
    "addr:housenumber":"44ba",
    "addr:postcode":"5640",
    "addr:street":"Rue Du Planois",
    "iso:country":"BE",
    "sg:address":"Rue Du Planois 44ba",
    "sg:city":"Mettet",
    "sg:orig_category":"Epiceries",
    "sg:phone":"+32 71 72 74 47",
    "sg:postcode":"5640",
    "sg:province":"Namur",
    "wof:name":"Maison Beaurain",
    "wof:placetype":"venue"
},
  "geometry": {"coordinates":[4.6578397751,50.3198051453],"type":"Point"}
}