{
  "type": "Feature",
  "properties": {
    "addr:full":"Rue Victor Rauter 42 Bruxelles (anderlecht) Bruxelles-Capitale 1070",
    "addr:housenumber":"42",
    "addr:postcode":"1070",
    "addr:street":"Rue Victor Rauter",
    "iso:country":"BE",
    "sg:address":"Rue Victor Rauter 42",
    "sg:city":"Bruxelles (anderlecht)",
    "sg:classifiers":[
        {
            "category":"Building & Trades",
            "subcategory":"Pest Control",
            "type":"Services"
        }
    ],
    "sg:phone":"+32 2 347 77 60",
    "sg:postcode":"1070",
    "sg:province":"Bruxelles-Capitale",
    "sg:tags":[
        "machine",
        "vending"
    ],
    "wof:name":"Select Vending",
    "wof:placetype":"venue"
},
  "geometry": {"coordinates":[4.3128728867,50.8350791931],"type":"Point"}
}