{
  "type": "Feature",
  "properties": {
    "addr:full":"Rue Du Canal 19 Antoing (p\u00e9ronnes-lez-antoing) Hainaut 7640",
    "addr:housenumber":"19",
    "addr:postcode":"7640",
    "addr:street":"Rue Du Canal;Hainaut",
    "iso:country":"BE",
    "sg:address":"Rue Du Canal 19",
    "sg:city":"Antoing (p\u00e9ronnes-lez-antoing)",
    "sg:classifiers":[
        {
            "category":"Bars & Pubs",
            "type":"Food & Drink"
        }
    ],
    "sg:phone":"+32 69 44 12 95",
    "sg:postcode":"7640",
    "sg:province":"Hainaut",
    "wof:name":"P\u00eacheurs (caf\u00e9 Des)",
    "wof:placetype":"venue"
},
  "geometry": {"coordinates":[3.4633779526,50.548160553],"type":"Point"}
}