{
  "type": "Feature",
  "properties": {
    "addr:full":"H\u00fctte 11 Eupen Li\u00e8ge 4700",
    "addr:housenumber":"11",
    "addr:postcode":"4700",
    "addr:street":"Huette",
    "iso:country":"BE",
    "sg:address":"H\u00fctte 11",
    "sg:city":"Eupen",
    "sg:classifiers":[
        {
            "category":"Building & Trades",
            "subcategory":"Electrical",
            "type":"Services"
        }
    ],
    "sg:phone":"+32 87 56 97 16",
    "sg:postcode":"4700",
    "sg:province":"Li\u00e8ge",
    "sg:tags":[
        "industrial",
        "-",
        "electric",
        "contractor"
    ],
    "wof:name":"Elektro Scheen",
    "wof:placetype":"venue"
},
  "geometry": {"coordinates":[6.0107979774,50.6334266663],"type":"Point"}
}