{
  "type": "Feature",
  "properties": {
    "iso:country":"BE",
    "sg:address":"Lepelstraat 2",
    "sg:city":"Lokeren",
    "sg:classifiers":[
        {
            "category":"Professional",
            "subcategory":"Testing Lab",
            "type":"Services"
        }
    ],
    "sg:phone":"+32 9 348 14 50",
    "sg:postcode":"9160",
    "sg:province":"Oost-Vlaanderen",
    "sg:tags":[
        "laboratory",
        "-"
    ],
    "wof:name":"Scheikundig Centrum",
    "wof:placetype":"venue"
},
  "geometry": {"coordinates":[4.0002279282,51.1018486023],"type":"Point"}
}