{
  "type": "Feature",
  "properties": {
    "iso:country":"BE",
    "sg:address":"Adolf Mortelmansstraat 4",
    "sg:city":"Wommelgem",
    "sg:orig_category":"Mat\u00e9riel de T\u00e9l\u00e9communication. Syst\u00e8mes de t\u00e9l\u00e9communications",
    "sg:phone":"+32 3 355 20 30",
    "sg:postcode":"2160",
    "sg:province":"Antwerpen",
    "wof:name":"Peetermans Telecom",
    "wof:placetype":"venue"
},
  "geometry": {"coordinates":[4.522813797,51.2045288086],"type":"Point"}
}