{
  "type": "Feature",
  "properties": {
    "addr:full":"Rue Godefroid Kurth 2 Saint-leger Luxembourg 6747",
    "addr:housenumber":"2",
    "addr:postcode":"6747",
    "addr:street":"Rue Godefroid Kurth",
    "iso:country":"BE",
    "sg:address":"Rue Godefroid Kurth 2",
    "sg:city":"Saint-leger",
    "sg:orig_category":"Kruideniers Slagers Zuivelproducten",
    "sg:phone":"+32 63 23 94 26",
    "sg:postcode":"6747",
    "sg:province":"Luxembourg",
    "wof:name":"Spar",
    "wof:placetype":"venue"
},
  "geometry": {"coordinates":[5.6565618515,49.6118392944],"type":"Point"}
}