{
  "type": "Feature",
  "properties": {
    "addr:full":"Rue Saint-l\u00c9onard 167 Li\u00c8ge Li\u00e8ge 4000",
    "addr:housenumber":"167",
    "addr:postcode":"4000",
    "addr:street":"Rue Saint-Le\u0301Onard",
    "iso:country":"BE",
    "sg:address":"Rue Saint-l\u00c9onard 167",
    "sg:city":"Li\u00c8ge",
    "sg:orig_category":"R\u00e9parations d'appareils \u00e9lectrom\u00e9nagers. Electrom\u00e9nager, t\u00e9l\u00e9visions and radios",
    "sg:phone":"+32 4 227 92 05",
    "sg:postcode":"4000",
    "sg:province":"Li\u00e8ge",
    "wof:name":"Electro Service",
    "wof:placetype":"venue"
},
  "geometry": {"coordinates":[5.5933952332,50.6502876282],"type":"Point"}
}