{
  "type": "Feature",
  "properties": {
    "iso:country":"BE",
    "sg:address":"Hagenbroeksesteenweg 141",
    "sg:city":"Lier",
    "sg:classifiers":[
        {
            "category":"Professional",
            "subcategory":"Accounting & Tax Preparation",
            "type":"Services"
        }
    ],
    "sg:phone":"+32 3 489 39 25",
    "sg:postcode":"2500",
    "sg:province":"Antwerpen",
    "sg:tags":[
        "bookkeeper"
    ],
    "wof:name":"Mortelmans Luc Nv",
    "wof:placetype":"venue"
},
  "geometry": {"coordinates":[4.5680699348,51.1481018066],"type":"Point"}
}