{
  "type": "Feature",
  "properties": {
    "addr:full":"Rue Des Ch\u00c2teaux 31 Bi\u00c8vre Namur 5555",
    "addr:housenumber":"31",
    "addr:postcode":"5555",
    "addr:street":"Rue Des Cha\u0302Teaux",
    "iso:country":"BE",
    "sg:address":"Rue Des Ch\u00c2teaux 31",
    "sg:city":"Bi\u00c8vre",
    "sg:orig_category":"Sportclubs",
    "sg:phone":"+32 61 51 17 10",
    "sg:postcode":"5555",
    "sg:province":"Namur",
    "wof:name":"Badminton Club Bad 2000",
    "wof:placetype":"venue"
},
  "geometry": {"coordinates":[5.0244259834,49.9347457886],"type":"Point"}
}