{
  "type": "Feature",
  "properties": {
    "iso:country":"BE",
    "sg:address":"Boskant 3",
    "sg:city":"Lubbeek",
    "sg:orig_category":"Boomkwekerijen Tuinbenodigdheden Tuinen",
    "sg:phone":"+32 16 73 48 09",
    "sg:postcode":"3210",
    "sg:province":"Vlaams-Brabant",
    "wof:name":"Bureau Herba",
    "wof:placetype":"venue"
},
  "geometry": {"coordinates":[4.8167991638,50.8693885803],"type":"Point"}
}