{
  "type": "Feature",
  "properties": {
    "addr:full":"Heizel Esplanade B48 Brussel/bruxelles Bruxelles-Capitale 1020",
    "addr:postcode":"b48;/ bruxelles;1020",
    "addr:street":"Heizel Esplanade",
    "iso:country":"BE",
    "sg:address":"Heizel Esplanade B48",
    "sg:city":"Brussel/bruxelles",
    "sg:orig_category":"Ordinateurs and \u00e9quipement informatique",
    "sg:phone":"+32 2 475 31 30",
    "sg:postcode":"1020",
    "sg:province":"Bruxelles-Capitale",
    "wof:name":"Expert",
    "wof:placetype":"venue"
},
  "geometry": {"coordinates":[4.3462300301,50.8855514526],"type":"Point"}
}