{
  "type": "Feature",
  "properties": {
    "iso:country":"BE",
    "sg:address":"Meilaan 181",
    "sg:city":"Sint-lambrechts-woluwe/woluwe-saint-lambert",
    "sg:orig_category":"Projectontwikkelaars",
    "sg:phone":"+32 2 772 28 78",
    "sg:postcode":"1200",
    "sg:province":"Bruxelles-Capitale",
    "wof:name":"F.l.t. Contractors",
    "wof:placetype":"venue"
},
  "geometry": {"coordinates":[4.415186882,50.8483467102],"type":"Point"}
}