{
  "type": "Feature",
  "properties": {
    "addr:full":"Rue Grand Vin\u00e2ve 34-36 Seraing (jemeppe-sur-meuse) Li\u00e8ge 4101",
    "addr:postcode":"34-36;4101",
    "addr:street":"Rue Grand Vina\u0302Ve",
    "iso:country":"BE",
    "sg:address":"Rue Grand Vin\u00e2ve 34-36",
    "sg:city":"Seraing (jemeppe-sur-meuse)",
    "sg:classifiers":[
        {
            "category":"Shopping",
            "subcategory":"Shoes",
            "type":"Retail Goods"
        }
    ],
    "sg:phone":"+32 4 235 68 96",
    "sg:postcode":"4101",
    "sg:province":"Li\u00e8ge",
    "sg:tags":[
        "slipper",
        "-"
    ],
    "wof:name":"Rene Collard-espace Jeune",
    "wof:placetype":"venue"
},
  "geometry": {"coordinates":[5.5063309669,50.6165962219],"type":"Point"}
}