{
  "type": "Feature",
  "properties": {
    "iso:country":"BE",
    "sg:address":"Gentstraat 54",
    "sg:city":"Beveren (beveren-waas)",
    "sg:classifiers":[
        {
            "category":"Personal",
            "subcategory":"Beauty Salon",
            "type":"Services"
        }
    ],
    "sg:phone":"+32 3 775 44 49",
    "sg:postcode":"9120",
    "sg:province":"Oost-Vlaanderen",
    "wof:name":"Colibri",
    "wof:placetype":"venue"
},
  "geometry": {"coordinates":[4.2759518623,51.2121200562],"type":"Point"}
}