{
  "type": "Feature",
  "properties": {
    "iso:country":"BE",
    "sg:address":"Kapelstraat 46",
    "sg:city":"Lummen",
    "sg:orig_category":"Studios photographiques",
    "sg:phone":"+32 13 44 33 88",
    "sg:postcode":"3560",
    "sg:province":"Limburg",
    "wof:name":"Studio Mechelmans",
    "wof:placetype":"venue"
},
  "geometry": {"coordinates":[5.1408319473,50.97423172],"type":"Point"}
}