{
  "type": "Feature",
  "properties": {
    "addr:full":"Kempische Steenweg 9 Hasselt Limburg 3500",
    "addr:housenumber":"9",
    "addr:postcode":"3500",
    "addr:street":"Kempische Steenweg",
    "iso:country":"BE",
    "sg:address":"Kempische Steenweg 9",
    "sg:city":"Hasselt",
    "sg:classifiers":[
        {
            "category":"Professional",
            "subcategory":"Printing & Photocopies",
            "type":"Services"
        }
    ],
    "sg:phone":"+32 11 24 31 22",
    "sg:postcode":"3500",
    "sg:province":"Limburg",
    "sg:tags":[
        "silkscreen",
        "-"
    ],
    "wof:name":"J & S Design",
    "wof:placetype":"venue"
},
  "geometry": {"coordinates":[5.3384819031,50.9350662231],"type":"Point"}
}