{
  "type": "Feature",
  "properties": {
    "addr:full":"Rue De Ninane 3bb Chaudfontaine Li\u00e8ge 4052",
    "addr:housenumber":"3bb",
    "addr:postcode":"4052",
    "addr:street":"Rue De Ninane",
    "iso:country":"BE",
    "sg:address":"Rue De Ninane 3bb",
    "sg:city":"Chaudfontaine",
    "sg:orig_category":"Paramedische behandelingen",
    "sg:phone":"+32 4 368 56 47",
    "sg:postcode":"4052",
    "sg:province":"Li\u00e8ge",
    "wof:name":"A. Crits",
    "wof:placetype":"venue"
},
  "geometry": {"coordinates":[5.6392202377,50.5586051941],"type":"Point"}
}