{
  "type": "Feature",
  "properties": {
    "addr:full":"Devosstraat 15 Oudenaarde Oost-Vlaanderen 9700",
    "addr:housenumber":"15",
    "addr:postcode":"9700",
    "addr:street":"Devosstraat",
    "iso:country":"BE",
    "sg:address":"Devosstraat 15",
    "sg:city":"Oudenaarde",
    "sg:orig_category":"Artsen and specialisten",
    "sg:phone":"+32 55 30 36 86",
    "sg:postcode":"9700",
    "sg:province":"Oost-Vlaanderen",
    "wof:name":"Peter Van Baelen",
    "wof:placetype":"venue"
},
  "geometry": {"coordinates":[3.6041810513,50.8469314575],"type":"Point"}
}