{
  "type": "Feature",
  "properties": {
    "iso:country":"BE",
    "sg:address":"Colomastraat 47",
    "sg:city":"Mechelen",
    "sg:orig_category":"Entretien and r\u00e9parations de machines de bureau and ordinateurs. R\u00e9alisation de programmes and logic",
    "sg:phone":"+32 15 42 33 32",
    "sg:postcode":"2800",
    "sg:province":"Antwerpen",
    "wof:name":"Profcom International",
    "wof:placetype":"venue"
},
  "geometry": {"coordinates":[4.4805951118,51.0189857483],"type":"Point"}
}