{
  "type": "Feature",
  "properties": {
    "addr:full":"Stuyvenberg 68 Sint-pieters-woluwe/woluwe-sai Bruxelles-Capitale 1150",
    "addr:housenumber":"68",
    "addr:postcode":"1150",
    "addr:street":"Stuyvenberg",
    "iso:country":"BE",
    "sg:address":"Stuyvenberg 68",
    "sg:city":"Sint-pieters-woluwe/woluwe-sai",
    "sg:orig_category":"Woningbouw",
    "sg:phone":"+32 2 772 43 20",
    "sg:postcode":"1150",
    "sg:province":"Bruxelles-Capitale",
    "wof:name":"Abidts Pierre",
    "wof:placetype":"venue"
},
  "geometry": {"coordinates":[4.4611501694,50.8428497314],"type":"Point"}
}