{
  "type": "Feature",
  "properties": {
    "addr:full":"Kapelstraat 100 Sint-niklaas Oost-Vlaanderen 9100",
    "addr:housenumber":"100",
    "addr:postcode":"9100",
    "addr:street":"Kapelstraat",
    "iso:country":"BE",
    "sg:address":"Kapelstraat 100",
    "sg:city":"Sint-niklaas",
    "sg:orig_category":"Ordinateurs and \u00e9quipement informatique. Jeux and jouets. Entretien and r\u00e9parations de machines de b",
    "sg:phone":"+32 3 766 56 90",
    "sg:postcode":"9100",
    "sg:province":"Oost-Vlaanderen",
    "wof:name":"Softwareshop",
    "wof:placetype":"venue"
},
  "geometry": {"coordinates":[4.1548528671,51.1511993408],"type":"Point"}
}