{
  "type": "Feature",
  "properties": {
    "addr:full":"Colbersstraat 3 Kinrooi Limburg 3640",
    "addr:housenumber":"3",
    "addr:postcode":"3640",
    "addr:street":"Colbersstraat",
    "iso:country":"BE",
    "sg:address":"Colbersstraat 3",
    "sg:city":"Kinrooi",
    "sg:orig_category":"Eleveurs de bovins",
    "sg:phone":"+32 89 70 11 78",
    "sg:postcode":"3640",
    "sg:province":"Limburg",
    "wof:name":"Jaak Creemers",
    "wof:placetype":"venue"
},
  "geometry": {"coordinates":[5.7409291267,51.1813316345],"type":"Point"}
}