{
  "type": "Feature",
  "properties": {
    "addr:full":"Veldhoekstraat 30 Maldegem Oost-Vlaanderen 9990",
    "addr:housenumber":"30",
    "addr:postcode":"9990",
    "addr:street":"Veldhoekstraat",
    "iso:country":"BE",
    "sg:address":"Veldhoekstraat 30",
    "sg:city":"Maldegem",
    "sg:orig_category":"Varkenskwekers",
    "sg:phone":"+32 50 71 56 35",
    "sg:postcode":"9990",
    "sg:province":"Oost-Vlaanderen",
    "wof:name":"N Vanhulle",
    "wof:placetype":"venue"
},
  "geometry": {"coordinates":[3.3840000629,51.2016410828],"type":"Point"}
}