{
  "type": "Feature",
  "properties": {
    "addr:full":"Sint-blasiusstraat 49 Roeselare (rumbeke) West-Vlaanderen 8800",
    "addr:housenumber":"49",
    "addr:postcode":"8800",
    "addr:street":"Sint-Blasiusstraat",
    "iso:country":"BE",
    "sg:address":"Sint-blasiusstraat 49",
    "sg:city":"Roeselare (rumbeke)",
    "sg:classifiers":[
        {
            "category":"Bakery",
            "type":"Food & Drink"
        }
    ],
    "sg:phone":"+32 51 22 42 90",
    "sg:postcode":"8800",
    "sg:province":"West-Vlaanderen",
    "sg:tags":[
        "confectioner",
        "baker"
    ],
    "wof:name":"Geldhof K",
    "wof:placetype":"venue"
},
  "geometry": {"coordinates":[3.1483139992,50.937587738],"type":"Point"}
}