{
  "type": "Feature",
  "properties": {
    "addr:full":"Rue Hodiamont 13 Verviers Li\u00e8ge 4802",
    "addr:housenumber":"13",
    "addr:postcode":"4802",
    "addr:street":"Rue Hodiamont",
    "iso:country":"BE",
    "sg:address":"Rue Hodiamont 13",
    "sg:city":"Verviers",
    "sg:classifiers":[
        {
            "category":"Restaurant",
            "type":"Food & Drink"
        }
    ],
    "sg:phone":"+32 87 22 68 39",
    "sg:postcode":"4802",
    "sg:province":"Li\u00e8ge",
    "sg:tags":[
        "organisatie",
        "feesten",
        "van",
        "catering"
    ],
    "wof:name":"La Croustade",
    "wof:placetype":"venue"
},
  "geometry": {"coordinates":[5.8671250343,50.5714111328],"type":"Point"}
}