{
  "type": "Feature",
  "properties": {
    "addr:full":"Rue Des Eglantiers 25 Li\u00c8ge Li\u00e8ge 4000",
    "addr:housenumber":"25",
    "addr:postcode":"4000",
    "addr:street":"Rue Des Eglantiers",
    "iso:country":"BE",
    "sg:address":"Rue Des Eglantiers 25",
    "sg:city":"Li\u00c8ge",
    "sg:orig_category":"Artiesten and kunstenaars",
    "sg:phone":"+32 4 226 30 24",
    "sg:postcode":"4000",
    "sg:province":"Li\u00e8ge",
    "wof:name":"Louis Janssen Dit Loujan",
    "wof:placetype":"venue"
},
  "geometry": {"coordinates":[5.5654020309,50.6526908875],"type":"Point"}
}