{
  "type": "Feature",
  "properties": {
    "addr:full":"Tweekerkenstraat 6 Erpe-mere (burst) Oost-Vlaanderen 9420",
    "addr:housenumber":"6",
    "addr:postcode":"9420",
    "addr:street":"Tweekerkenstraat",
    "iso:country":"BE",
    "sg:address":"Tweekerkenstraat 6",
    "sg:city":"Erpe-mere (burst)",
    "sg:classifiers":[
        {
            "category":"Shopping",
            "subcategory":"Florist",
            "type":"Retail Goods"
        }
    ],
    "sg:phone":"+32 53 62 23 99",
    "sg:postcode":"9420",
    "sg:province":"Oost-Vlaanderen",
    "wof:name":"Van Wesemael C",
    "wof:placetype":"venue"
},
  "geometry": {"coordinates":[3.9219169617,50.9159698486],"type":"Point"}
}