{
  "type": "Feature",
  "properties": {
    "addr:full":"Nieuwstadstraat 9 Box 4 Bree Limburg 3960",
    "addr:housenumber":"9;4",
    "addr:postcode":"3960",
    "addr:street":"Nieuwstadstraat;Box",
    "iso:country":"BE",
    "sg:address":"Nieuwstadstraat 9 Box 4",
    "sg:city":"Bree",
    "sg:classifiers":[
        {
            "category":"Banks & Credit Unions",
            "subcategory":"Investment Brokerage",
            "type":"Services"
        }
    ],
    "sg:phone":"+32 11 79 33 32",
    "sg:postcode":"3960",
    "sg:province":"Limburg",
    "sg:tags":[
        "printing",
        "-"
    ],
    "wof:name":"Symons Hugo Drukwerken",
    "wof:placetype":"venue"
},
  "geometry": {"coordinates":[5.5956678391,51.1410675049],"type":"Point"}
}