{
  "type": "Feature",
  "properties": {
    "addr:full":"Rue Raymond Geenen 44 Li\u00c8ge Li\u00e8ge 4020",
    "addr:housenumber":"44",
    "addr:postcode":"4020",
    "addr:street":"Rue Raymond Geenen",
    "iso:country":"BE",
    "sg:address":"Rue Raymond Geenen 44",
    "sg:city":"Li\u00c8ge",
    "sg:classifiers":[
        {
            "category":"Building & Trades",
            "subcategory":"Plumbing",
            "type":"Services"
        }
    ],
    "sg:phone":"+32 4 342 59 63",
    "sg:postcode":"4020",
    "sg:province":"Li\u00e8ge",
    "sg:tags":[
        "diver",
        "commerce",
        "gr",
        "pour",
        "equipement"
    ],
    "wof:name":"Fa. Werner Lagae Danon",
    "wof:placetype":"venue"
},
  "geometry": {"coordinates":[5.5960869789,50.6441078186],"type":"Point"}
}