{
  "type": "Feature",
  "properties": {
    "addr:full":"Kaaskerkestraat 79 Diksmuide West-Vlaanderen 8600",
    "addr:housenumber":"79",
    "addr:postcode":"8600",
    "addr:street":"Kaaskerkestraat",
    "iso:country":"BE",
    "sg:address":"Kaaskerkestraat 79",
    "sg:city":"Diksmuide",
    "sg:orig_category":"Peinture. Rev\u00eatements pour sols and murs",
    "sg:phone":"+32 51 50 29 76",
    "sg:postcode":"8600",
    "sg:province":"West-Vlaanderen",
    "wof:name":"Laurent Vanhoutte",
    "wof:placetype":"venue"
},
  "geometry": {"coordinates":[2.8304400444,51.0372085571],"type":"Point"}
}