{
  "type": "Feature",
  "properties": {
    "addr:full":"Merodestraat 25 Duffel Antwerpen 2570",
    "addr:housenumber":"25",
    "addr:postcode":"2570",
    "addr:street":"Merodestraat",
    "iso:country":"BE",
    "sg:address":"Merodestraat 25",
    "sg:city":"Duffel",
    "sg:classifiers":[
        {
            "category":"Health Services",
            "subcategory":"Health Practitioner",
            "type":"Services"
        }
    ],
    "sg:phone":"+32 15 31 52 34",
    "sg:postcode":"2570",
    "sg:province":"Antwerpen",
    "sg:tags":[
        "physiotherapist"
    ],
    "wof:name":"Verhavert I",
    "wof:placetype":"venue"
},
  "geometry": {"coordinates":[4.5018758774,51.0972366333],"type":"Point"}
}