{
  "type": "Feature",
  "properties": {
    "addr:full":"Wilgenstraat 90bb Roeselare West-Vlaanderen 8800",
    "addr:housenumber":"90bb",
    "addr:postcode":"8800",
    "addr:street":"Wilgenstraat",
    "iso:country":"BE",
    "sg:address":"Wilgenstraat 90bb",
    "sg:city":"Roeselare",
    "sg:classifiers":[
        {
            "category":"Insurance",
            "subcategory":"Life Insurance",
            "type":"Services"
        }
    ],
    "sg:phone":"+32 51 24 15 94",
    "sg:postcode":"8800",
    "sg:province":"West-Vlaanderen",
    "sg:tags":[
        "assurance"
    ],
    "wof:name":"Dienstbetoon Van Collie",
    "wof:placetype":"venue"
},
  "geometry": {"coordinates":[3.1176199913,50.937877655],"type":"Point"}
}