{
  "type": "Feature",
  "properties": {
    "addr:full":"Aarledijk 51 Ravels Antwerpen 2382",
    "addr:housenumber":"51",
    "addr:postcode":"2382",
    "addr:street":"Aarledijk",
    "iso:country":"BE",
    "sg:address":"Aarledijk 51",
    "sg:city":"Ravels",
    "sg:orig_category":"Agences immobili\u00e8res",
    "sg:phone":"+32 14 65 91 59",
    "sg:postcode":"2382",
    "sg:province":"Antwerpen",
    "wof:name":"Jan Bertens",
    "wof:placetype":"venue"
},
  "geometry": {"coordinates":[5.041768074,51.4469108582],"type":"Point"}
}