{
  "type": "Feature",
  "properties": {
    "iso:country":"BE",
    "sg:address":"Armentierestraat 334",
    "sg:city":"Komen-waasten/comines-warneton",
    "sg:orig_category":"Caf\u00e9s Dameskledingzaken Herenkledingzaken Restaurants",
    "sg:phone":"+32 56 58 85 50",
    "sg:postcode":"7783",
    "sg:province":"Hainaut",
    "wof:name":"La Chaise \u00c0 3 Pattes",
    "wof:placetype":"venue"
},
  "geometry": {"coordinates":[2.8828949928,50.7069244385],"type":"Point"}
}