{
  "type": "Feature",
  "properties": {
    "iso:country":"BE",
    "sg:address":"Onkerzelestraat 280",
    "sg:city":"Geraardsbergen",
    "sg:orig_category":"Maisons de vacances. Auberges de jeunesse and refuges. Terrains de camping. Activit\u00e9s r\u00e9cr\u00e9atives di",
    "sg:phone":"+32 54 41 63 24",
    "sg:postcode":"9500",
    "sg:province":"Oost-Vlaanderen",
    "wof:name":"De Gavers",
    "wof:placetype":"venue"
},
  "geometry": {"coordinates":[3.8943850994,50.7744750977],"type":"Point"}
}