{
  "type": "Feature",
  "properties": {
    "iso:country":"BE",
    "sg:address":"Putstraat 28",
    "sg:city":"Maasmechelen",
    "sg:classifiers":[
        {
            "category":"Health Services",
            "subcategory":"Nursing And Care Facility",
            "type":"Services"
        }
    ],
    "sg:phone":"+32 89 77 18 95",
    "sg:postcode":"3630",
    "sg:province":"Limburg",
    "sg:tags":[
        "home"
    ],
    "wof:name":"Noten Jeanne",
    "wof:placetype":"venue"
},
  "geometry": {"coordinates":[5.6814918518,50.9774627686],"type":"Point"}
}