{
  "type": "Feature",
  "properties": {
    "addr:full":"Koolmijnlaan 262 Beringen Limburg 3582",
    "addr:housenumber":"262",
    "addr:postcode":"3582",
    "addr:street":"Koolmijnlaan",
    "iso:country":"BE",
    "sg:address":"Koolmijnlaan 262",
    "sg:city":"Beringen",
    "sg:orig_category":"Epiceries",
    "sg:phone":"+32 11 42 83 32",
    "sg:postcode":"3582",
    "sg:province":"Limburg",
    "wof:name":"Supermarkt Anko",
    "wof:placetype":"venue"
},
  "geometry": {"coordinates":[5.2199392319,51.0733413696],"type":"Point"}
}