{
  "type": "Feature",
  "properties": {
    "iso:country":"BE",
    "sg:address":"Rue Des Enhauts 23",
    "sg:city":"Le Roeulx (ville-sur-haine)",
    "sg:classifiers":[
        {
            "category":"Health Services",
            "subcategory":"Health Practitioner",
            "type":"Services"
        }
    ],
    "sg:phone":"+32 65 87 36 19",
    "sg:postcode":"7070",
    "sg:province":"Hainaut",
    "sg:tags":[
        "physiotherapist"
    ],
    "wof:name":"Nicoletti Nathalie",
    "wof:placetype":"venue"
},
  "geometry": {"coordinates":[4.0653319359,50.477722168],"type":"Point"}
}