{
  "type": "Feature",
  "properties": {
    "addr:full":"Rue Alo\u00cfs Den Reep 1ba Moeskroen/mouscron Hainaut 7700",
    "addr:housenumber":"1ba",
    "addr:postcode":"7700",
    "addr:street":"Rue Aloi\u0308S Den Reep",
    "iso:country":"BE",
    "sg:address":"Rue Alo\u00cfs Den Reep 1ba",
    "sg:city":"Moeskroen/mouscron",
    "sg:orig_category":"S\u00e9curit\u00e9 sociale",
    "sg:phone":"+32 56 33 04 55",
    "sg:postcode":"7700",
    "sg:province":"Hainaut",
    "wof:name":"La Concorde",
    "wof:placetype":"venue"
},
  "geometry": {"coordinates":[3.2323200703,50.7400932312],"type":"Point"}
}