{
  "type": "Feature",
  "properties": {
    "addr:full":"Grotstraat 91 Moeskroen/mouscron Hainaut 7700",
    "addr:housenumber":"91",
    "addr:postcode":"7700",
    "addr:street":"Grotstraat",
    "iso:country":"BE",
    "sg:address":"Grotstraat 91",
    "sg:city":"Moeskroen/mouscron",
    "sg:orig_category":"Dakwerken Woningbouw",
    "sg:phone":"+32 56 84 02 41",
    "sg:postcode":"7700",
    "sg:province":"Hainaut",
    "wof:name":"Villefroy J.",
    "wof:placetype":"venue"
},
  "geometry": {"coordinates":[3.2323200703,50.7400932312],"type":"Point"}
}