{
  "type": "Feature",
  "properties": {
    "addr:full":"Slabbaardstraat-noord 55 Izegem West-Vlaanderen 8870",
    "addr:housenumber":"55",
    "addr:postcode":"8870",
    "addr:street":"Slabbaardstraat-Noord",
    "iso:country":"BE",
    "sg:address":"Slabbaardstraat-noord 55",
    "sg:city":"Izegem",
    "sg:classifiers":[
        {
            "category":"Real Estate",
            "subcategory":"Architect",
            "type":"Services"
        }
    ],
    "sg:phone":"+32 51 30 21 25",
    "sg:postcode":"8870",
    "sg:province":"West-Vlaanderen",
    "wof:name":"Werbrouck B",
    "wof:placetype":"venue"
},
  "geometry": {"coordinates":[3.2130498886,50.912311554],"type":"Point"}
}