{
  "type": "Feature",
  "properties": {
    "iso:country":"BE",
    "sg:address":"Nachtegaallaan 19",
    "sg:city":"Retie",
    "sg:orig_category":"Activit\u00e9s diverses d'imprimerie",
    "sg:phone":"+32 14 37 23 58",
    "sg:postcode":"2470",
    "sg:province":"Antwerpen",
    "wof:name":"R. Otten",
    "wof:placetype":"venue"
},
  "geometry": {"coordinates":[5.1348819733,51.2640304565],"type":"Point"}
}