{
  "type": "Feature",
  "properties": {
    "addr:full":"Eikestraat 20 Herzele Oost-Vlaanderen 9550",
    "addr:housenumber":"20",
    "addr:postcode":"9550",
    "addr:street":"Eikestraat;Oost-Vlaanderen",
    "iso:country":"BE",
    "sg:address":"Eikestraat 20",
    "sg:city":"Herzele",
    "sg:classifiers":[
        {
            "category":"Cafe",
            "type":"Food & Drink"
        }
    ],
    "sg:phone":"+32 54 50 08 68",
    "sg:postcode":"9550",
    "sg:province":"Oost-Vlaanderen",
    "sg:tags":[
        "caf\u00e9s"
    ],
    "wof:name":"Rosette Van Waesberge",
    "wof:placetype":"venue"
},
  "geometry": {"coordinates":[3.8917291164,50.8374252319],"type":"Point"}
}