{
  "type": "Feature",
  "properties": {
    "iso:country":"BE",
    "sg:address":"Rue Du March\u00c9 Aux Fromages 4",
    "sg:city":"Brussel/bruxelles",
    "sg:classifiers":[
        {
            "category":"Fast Food",
            "type":"Food & Drink"
        }
    ],
    "sg:phone":"+32 2 512 01 20",
    "sg:postcode":"1000",
    "sg:province":"Bruxelles-Capitale",
    "sg:tags":[
        "meeneem",
        "restaurant"
    ],
    "wof:name":"Hellas",
    "wof:placetype":"venue"
},
  "geometry": {"coordinates":[4.3528470993,50.8459663391],"type":"Point"}
}