{
  "type": "Feature",
  "properties": {
    "addr:full":"Rue De L'orbette 1 Mons (ghlin) Hainaut 7011",
    "addr:housenumber":"1",
    "addr:postcode":"7011",
    "addr:street":"Rue De L'Orbette",
    "iso:country":"BE",
    "sg:address":"Rue De L'orbette 1",
    "sg:city":"Mons (ghlin)",
    "sg:classifiers":[
        {
            "category":"Home & Garden",
            "subcategory":"Building Materials",
            "type":"Retail Goods"
        }
    ],
    "sg:phone":"+32 65 34 86 68",
    "sg:postcode":"7011",
    "sg:province":"Hainaut",
    "sg:tags":[
        "insulation",
        "thermical"
    ],
    "wof:name":"Isola-laine Sa",
    "wof:placetype":"venue"
},
  "geometry": {"coordinates":[3.8941469193,50.4830551147],"type":"Point"}
}