{
  "type": "Feature",
  "properties": {
    "iso:country":"BE",
    "sg:address":"Antwerpsesteenweg 67",
    "sg:city":"Malle",
    "sg:orig_category":"Enseignement secondaire technique and professionnel. Enseignement secondaire g\u00e9n\u00e9ral",
    "sg:phone":"+32 3 312 02 33",
    "sg:postcode":"2390",
    "sg:province":"Antwerpen",
    "wof:name":"Instituut Maris Stella",
    "wof:placetype":"venue"
},
  "geometry": {"coordinates":[4.7205858231,51.2996826172],"type":"Point"}
}