{
  "type": "Feature",
  "properties": {
    "addr:full":"Rue De La Monnaie 13 Namur Namur 5000",
    "addr:housenumber":"13",
    "addr:postcode":"5000",
    "addr:street":"Rue De La Monnaie",
    "iso:country":"BE",
    "sg:address":"Rue De La Monnaie 13",
    "sg:city":"Namur",
    "sg:orig_category":"Textiel",
    "sg:phone":"+32 81 26 30 15",
    "sg:postcode":"5000",
    "sg:province":"Namur",
    "wof:name":"Y. Delorme",
    "wof:placetype":"venue"
},
  "geometry": {"coordinates":[4.8667421341,50.4630889893],"type":"Point"}
}