{
  "type": "Feature",
  "properties": {
    "iso:country":"BE",
    "sg:address":"Bodemstraat 3",
    "sg:city":"Wellen",
    "sg:classifiers":[
        {
            "category":"Health Services",
            "subcategory":"Nursing And Care Facility",
            "type":"Services"
        }
    ],
    "sg:phone":"+32 11 59 34 83",
    "sg:postcode":"3830",
    "sg:province":"Limburg",
    "sg:tags":[
        "home"
    ],
    "wof:name":"Breugelmans A",
    "wof:placetype":"venue"
},
  "geometry": {"coordinates":[5.3356590271,50.8607063293],"type":"Point"}
}