{
  "type": "Feature",
  "properties": {
    "iso:country":"BE",
    "sg:address":"Avenue Arthur Blaivie 4",
    "sg:city":"Kraainem",
    "sg:classifiers":[
        {
            "category":"Shopping Center",
            "type":"Public Place"
        }
    ],
    "sg:phone":"+32 2 782 18 50",
    "sg:postcode":"1950",
    "sg:province":"Vlaams-Brabant",
    "sg:tags":[
        "enseignement",
        "formation"
    ],
    "wof:name":"Language Workshop",
    "wof:placetype":"venue"
},
  "geometry": {"coordinates":[4.4760489464,50.8376045227],"type":"Point"}
}