{
  "type": "Feature",
  "properties": {
    "addr:full":"Hellegatstraat 24a Puurs Antwerpen 2870",
    "addr:housenumber":"24a",
    "addr:postcode":"2870",
    "addr:street":"Hellegatstraat",
    "iso:country":"BE",
    "sg:address":"Hellegatstraat 24a",
    "sg:city":"Puurs",
    "sg:orig_category":"Installation de menuiserie en bois and plastique",
    "sg:phone":"+32 3 886 94 72",
    "sg:postcode":"2870",
    "sg:province":"Antwerpen",
    "wof:name":"Verbeeck Pieter",
    "wof:placetype":"venue"
},
  "geometry": {"coordinates":[4.3298039436,51.0906562805],"type":"Point"}
}