{
  "type": "Feature",
  "properties": {
    "addr:full":"Chauss\u00c9e De Namur 20 Gembloux Namur 5030",
    "addr:housenumber":"20",
    "addr:postcode":"5030",
    "addr:street":"Chausse\u0301E De Namur;Namur",
    "iso:country":"BE",
    "sg:address":"Chauss\u00c9e De Namur 20",
    "sg:city":"Gembloux",
    "sg:orig_category":"Speelgoed",
    "sg:phone":"+32 81 61 50 08",
    "sg:postcode":"5030",
    "sg:province":"Namur",
    "wof:name":"Euro Jouets",
    "wof:placetype":"venue"
},
  "geometry": {"coordinates":[4.6993989944,50.5717048645],"type":"Point"}
}