{
  "type": "Feature",
  "properties": {
    "addr:full":"Rue Albert B\u00c9riot 213 Saint-ghislain Hainaut 7332",
    "addr:housenumber":"213",
    "addr:postcode":"7332",
    "addr:street":"Rue Albert Be\u0301Riot;Hainaut",
    "iso:country":"BE",
    "sg:address":"Rue Albert B\u00c9riot 213",
    "sg:city":"Saint-ghislain",
    "sg:orig_category":"Woningbouw",
    "sg:phone":"+32 65 62 07 72",
    "sg:postcode":"7332",
    "sg:province":"Hainaut",
    "wof:name":"Gabriel Lefebvre",
    "wof:placetype":"venue"
},
  "geometry": {"coordinates":[3.786839962,50.5054969788],"type":"Point"}
}