{
  "type": "Feature",
  "properties": {
    "iso:country":"BE",
    "sg:address":"Smidsestraat 31",
    "sg:city":"Leuven (kessel-lo)",
    "sg:classifiers":[
        {
            "category":"Education",
            "subcategory":"School",
            "type":"Public Place"
        }
    ],
    "sg:phone":"+32 16 25 36 19",
    "sg:postcode":"3010",
    "sg:province":"Vlaams-Brabant",
    "sg:tags":[
        "supply"
    ],
    "wof:name":"Mecurius - Gnomen",
    "wof:placetype":"venue"
},
  "geometry": {"coordinates":[4.7304501534,50.889755249],"type":"Point"}
}