{
  "type": "Feature",
  "properties": {
    "iso:country":"BE",
    "sg:address":"Place D' Oeudeghien 6",
    "sg:city":"Frasnes-lez-anvaing",
    "sg:orig_category":"Artsen and specialisten",
    "sg:phone":"+32 68 64 64 24",
    "sg:postcode":"7911",
    "sg:province":"Hainaut",
    "wof:name":"A. Loir",
    "wof:placetype":"venue"
},
  "geometry": {"coordinates":[3.7117960453,50.6771011353],"type":"Point"}
}