{
  "type": "Feature",
  "properties": {
    "addr:full":"De Merodedreef 100 Westerlo Antwerpen 2260",
    "addr:housenumber":"100",
    "addr:postcode":"2260",
    "addr:street":"De Merodedreef",
    "iso:country":"BE",
    "sg:address":"De Merodedreef 100",
    "sg:city":"Westerlo",
    "sg:orig_category":"Belastingconsulenten Diverse juridische dienstverlening",
    "sg:phone":"+32 14 54 53 01",
    "sg:postcode":"2260",
    "sg:province":"Antwerpen",
    "wof:name":"Ncmv",
    "wof:placetype":"venue"
},
  "geometry": {"coordinates":[4.9180150032,51.0905303955],"type":"Point"}
}