{
  "type": "Feature",
  "properties": {
    "iso:country":"BE",
    "sg:address":"Cockerillkaai 3",
    "sg:city":"Antwerpen",
    "sg:classifiers":[
        {
            "category":"Home & Garden",
            "subcategory":"Building Materials",
            "type":"Retail Goods"
        }
    ],
    "sg:phone":"+32 53 78 69 08",
    "sg:postcode":"2000",
    "sg:province":"Antwerpen",
    "sg:tags":[
        "wooden",
        "stair"
    ],
    "wof:name":"Trappen Van Hecke Nv",
    "wof:placetype":"venue"
},
  "geometry": {"coordinates":[4.0417661667,50.9645843506],"type":"Point"}
}