{
  "type": "Feature",
  "properties": {
    "iso:country":"BE",
    "sg:address":"Chaus\u00c9e De Gand 500",
    "sg:city":"Molenbeek-saint-jean (bruxelles)",
    "sg:classifiers":[
        {
            "category":"Personal",
            "subcategory":"Beauty Salon",
            "type":"Services"
        }
    ],
    "sg:phone":"+32 2 414 40 08",
    "sg:postcode":"1080",
    "sg:province":"Bruxelles-Capitale",
    "sg:tags":[
        "de",
        "coiffure"
    ],
    "wof:name":"Claude",
    "wof:placetype":"venue"
},
  "geometry": {"coordinates":[4.3144140244,50.8583831787],"type":"Point"}
}