{
  "type": "Feature",
  "properties": {
    "addr:full":"Renaat De Rudderstraat 10 Diksmuide West-Vlaanderen 8600",
    "addr:housenumber":"10",
    "addr:postcode":"8600",
    "addr:street":"Renaat De Rudderstraat",
    "iso:country":"BE",
    "sg:address":"Renaat De Rudderstraat 10",
    "sg:city":"Diksmuide",
    "sg:classifiers":[
        {
            "category":"Personal",
            "subcategory":"Nail Salon",
            "type":"Services"
        }
    ],
    "sg:phone":"+32 51 50 35 76",
    "sg:postcode":"8600",
    "sg:province":"West-Vlaanderen",
    "sg:tags":[
        "pedicure"
    ],
    "wof:name":"Leliana",
    "wof:placetype":"venue"
},
  "geometry": {"coordinates":[2.8688490391,51.021697998],"type":"Point"}
}