{
  "type": "Feature",
  "properties": {
    "addr:full":"Avenue De La Ferme Rose 1 Bruxelles (uccle) Bruxelles-Capitale 1180",
    "addr:housenumber":"1",
    "addr:postcode":"1180",
    "addr:street":"Avenue De La Ferme Rose",
    "iso:country":"BE",
    "sg:address":"Avenue De La Ferme Rose 1",
    "sg:city":"Bruxelles (uccle)",
    "sg:classifiers":[
        {
            "category":"Health Services",
            "subcategory":"Dentist",
            "type":"Services"
        }
    ],
    "sg:phone":"+32 2 345 19 70",
    "sg:postcode":"1180",
    "sg:province":"Bruxelles-Capitale",
    "wof:name":"Berkenboom Mich\u00e8le",
    "wof:placetype":"venue"
},
  "geometry": {"coordinates":[4.3483581543,50.8073501587],"type":"Point"}
}