{
  "type": "Feature",
  "properties": {
    "addr:full":"Iepersestraat 11 Kortrijk West-Vlaanderen 8500",
    "addr:housenumber":"11",
    "addr:postcode":"8500",
    "addr:street":"Iepersestraat",
    "iso:country":"BE",
    "sg:address":"Iepersestraat 11",
    "sg:city":"Kortrijk",
    "sg:classifiers":[
        {
            "category":"Personal",
            "subcategory":"Beauty Salon",
            "type":"Services"
        }
    ],
    "sg:phone":"+32 56 35 19 26",
    "sg:postcode":"8500",
    "sg:province":"West-Vlaanderen",
    "sg:tags":[
        "lady",
        "-",
        "hairdressing"
    ],
    "wof:name":"Darline",
    "wof:placetype":"venue"
},
  "geometry": {"coordinates":[3.2579169273,50.8420143127],"type":"Point"}
}