{
  "type": "Feature",
  "properties": {
    "addr:full":"Kolmenstraat 139 Hasselt (stevoort) Limburg 3512",
    "addr:housenumber":"139",
    "addr:postcode":"3512",
    "addr:street":"Kolmenstraat",
    "iso:country":"BE",
    "sg:address":"Kolmenstraat 139",
    "sg:city":"Hasselt (stevoort)",
    "sg:classifiers":[
        {
            "category":"Building & Trades",
            "subcategory":"Construction",
            "type":"Services"
        }
    ],
    "sg:phone":"+32 11 31 20 86",
    "sg:postcode":"3512",
    "sg:province":"Limburg",
    "sg:tags":[
        "carpenter"
    ],
    "wof:name":"Thoelen Interieurbouw",
    "wof:placetype":"venue"
},
  "geometry": {"coordinates":[5.2312188148,50.9201507568],"type":"Point"}
}