{
  "type": "Feature",
  "properties": {
    "iso:country":"BE",
    "sg:address":"Rue Mitoyenne 356",
    "sg:city":"Lontzen",
    "sg:orig_category":"Installation de menuiserie en bois and plastique. Rev\u00eatements de sols and murs. Meubles D\u00e9taillants,",
    "sg:phone":"+32 87 88 19 71",
    "sg:postcode":"4710",
    "sg:province":"Li\u00e8ge",
    "wof:name":"Vandegaar",
    "wof:placetype":"venue"
},
  "geometry": {"coordinates":[5.9656300545,50.6769104004],"type":"Point"}
}