{
  "type": "Feature",
  "properties": {
    "iso:country":"BE",
    "sg:address":"Rue Martin Lindekens 32",
    "sg:city":"Bruxelles (woluwe-saint-pierre)",
    "sg:classifiers":[
        {
            "category":"Health Services",
            "subcategory":"Health Practitioner",
            "type":"Services"
        }
    ],
    "sg:phone":"+32 2 762 10 08",
    "sg:postcode":"1150",
    "sg:province":"Bruxelles-Capitale",
    "sg:tags":[
        "psychologist"
    ],
    "wof:name":"Angistriotu D",
    "wof:placetype":"venue"
},
  "geometry": {"coordinates":[4.4247169495,50.8367729187],"type":"Point"}
}