{
  "type": "Feature",
  "properties": {
    "iso:country":"BE",
    "sg:address":"Chemin Du Stocquoy 1",
    "sg:city":"Wavre",
    "sg:orig_category":"Avocats and conseillers juridiques",
    "sg:phone":"+32 10 45 46 00",
    "sg:postcode":"1300",
    "sg:province":"Brabant Wallon",
    "wof:name":"Philippe Castiaux",
    "wof:placetype":"venue"
},
  "geometry": {"coordinates":[4.6157569885,50.6898498535],"type":"Point"}
}