{
  "type": "Feature",
  "properties": {
    "addr:full":"Rue De L'intendant 161 Bruxelles (molenbeek-saint-jean) Bruxelles-Capitale 1080",
    "addr:housenumber":"161",
    "addr:postcode":"1080",
    "addr:street":"Rue De L'Intendant",
    "iso:country":"BE",
    "sg:address":"Rue De L'intendant 161",
    "sg:city":"Bruxelles (molenbeek-saint-jean)",
    "sg:classifiers":[
        {
            "category":"Shopping",
            "subcategory":"Discount & Variety Stores",
            "type":"Retail Goods"
        }
    ],
    "sg:phone":"+32 2 428 68 09",
    "sg:postcode":"1080",
    "sg:province":"Bruxelles-Capitale",
    "sg:tags":[
        "shop",
        "night"
    ],
    "wof:name":"Kabul",
    "wof:placetype":"venue"
},
  "geometry": {"coordinates":[4.3375329971,50.8630485535],"type":"Point"}
}