{
  "type": "Feature",
  "properties": {
    "iso:country":"BE",
    "sg:address":"Handboogstraat 8",
    "sg:city":"Kortrijk",
    "sg:classifiers":[
        {
            "category":"Personal",
            "subcategory":"Beauty Salon",
            "type":"Services"
        }
    ],
    "sg:phone":"+32 56 20 36 82",
    "sg:postcode":"8500",
    "sg:province":"West-Vlaanderen",
    "sg:tags":[
        "de",
        "coiffure"
    ],
    "wof:name":"Coiffure Maxim",
    "wof:placetype":"venue"
},
  "geometry": {"coordinates":[3.2646501064,50.8294372559],"type":"Point"}
}