{
  "type": "Feature",
  "properties": {
    "addr:full":"Gaarveldstraat 89ba Hasselt Limburg 3500",
    "addr:housenumber":"89ba",
    "addr:postcode":"3500",
    "addr:street":"Gaarveldstraat",
    "iso:country":"BE",
    "sg:address":"Gaarveldstraat 89ba",
    "sg:city":"Hasselt",
    "sg:orig_category":"Pharmaciens",
    "sg:phone":"+32 11 27 17 30",
    "sg:postcode":"3500",
    "sg:province":"Limburg",
    "wof:name":"Apotheek Van Elewyck",
    "wof:placetype":"venue"
},
  "geometry": {"coordinates":[5.3262767792,50.9258766174],"type":"Point"}
}