{
  "type": "Feature",
  "properties": {
    "iso:country":"BE",
    "sg:address":"Bollestraat 30",
    "sg:city":"Overijse",
    "sg:orig_category":"Producteurs de fruits",
    "sg:phone":"+32 16 47 26 79",
    "sg:postcode":"3090",
    "sg:province":"Vlaams-Brabant",
    "wof:name":"Jose Muyldermans",
    "wof:placetype":"venue"
},
  "geometry": {"coordinates":[4.5914998055,50.7695808411],"type":"Point"}
}