{
  "type": "Feature",
  "properties": {
    "addr:full":"Rue Artan 128 Bruxelles (schaerbeek) Bruxelles-Capitale 1030",
    "addr:housenumber":"128",
    "addr:postcode":"1030",
    "addr:street":"Rue Artan",
    "iso:country":"BE",
    "sg:address":"Rue Artan 128",
    "sg:city":"Bruxelles (schaerbeek)",
    "sg:classifiers":[
        {
            "category":"Professional",
            "subcategory":"Management & Consulting",
            "type":"Services"
        }
    ],
    "sg:phone":"+32 2 736 93 58",
    "sg:postcode":"1030",
    "sg:province":"Bruxelles-Capitale",
    "sg:tags":[
        "consultant"
    ],
    "wof:name":"H-r-h",
    "wof:placetype":"venue"
},
  "geometry": {"coordinates":[4.3836150169,50.8530845642],"type":"Point"}
}