{
  "type": "Feature",
  "properties": {
    "addr:full":"Molenstraat 175 Reet Antwerpen 2840",
    "addr:housenumber":"175",
    "addr:postcode":"2840",
    "addr:street":"Molenstraat",
    "iso:country":"BE",
    "sg:address":"Molenstraat 175",
    "sg:city":"Reet",
    "sg:classifiers":[
        {
            "category":"Autos & Motor Vehicles",
            "subcategory":"Fuel & Gas Station",
            "type":"Retail Goods"
        }
    ],
    "sg:phone":"+32 3 844 77 61",
    "sg:postcode":"2840",
    "sg:province":"Antwerpen",
    "sg:tags":[
        "machine",
        "sealing",
        "filling"
    ],
    "wof:name":"Multivac B.v.",
    "wof:placetype":"venue"
},
  "geometry": {"coordinates":[4.3985791206,51.1006965637],"type":"Point"}
}