{
  "type": "Feature",
  "properties": {
    "iso:country":"BE",
    "sg:address":"Rue Du Centre 10",
    "sg:city":"Bievre",
    "sg:orig_category":"Fietsen Motorfietsen",
    "sg:phone":"+32 61 51 16 63",
    "sg:postcode":"5555",
    "sg:province":"Namur",
    "wof:name":"Maison Gaussin",
    "wof:placetype":"venue"
},
  "geometry": {"coordinates":[5.0185098648,49.9410552979],"type":"Point"}
}