{
  "type": "Feature",
  "properties": {
    "addr:full":"Zavelstr 35 Stekene Oost-Vlaanderen 9190",
    "addr:housenumber":"35",
    "addr:postcode":"9190",
    "addr:street":"Zavelstr",
    "iso:country":"BE",
    "sg:address":"Zavelstr 35",
    "sg:city":"Stekene",
    "sg:orig_category":"Miscellaneous Products",
    "sg:phone":"+32 3 789 09 94",
    "sg:postcode":"9190",
    "sg:province":"Oost-Vlaanderen",
    "wof:name":"Verhuurbedrijf Sjaak Moens Bvba",
    "wof:placetype":"venue"
},
  "geometry": {"coordinates":[4.0529718399,51.2101783752],"type":"Point"}
}