{
  "type": "Feature",
  "properties": {
    "iso:country":"BE",
    "sg:address":"Sint-gummarusstraat 43-45",
    "sg:city":"Antwerpen",
    "sg:classifiers":[
        {
            "category":"Shopping",
            "subcategory":"Shoes",
            "type":"Retail Goods"
        }
    ],
    "sg:phone":"+32 3 233 71 97",
    "sg:postcode":"2060",
    "sg:province":"Antwerpen",
    "sg:tags":[
        "slipper",
        "-"
    ],
    "wof:name":"Ara-vago",
    "wof:placetype":"venue"
},
  "geometry": {"coordinates":[4.4211039543,51.224899292],"type":"Point"}
}