{
  "type": "Feature",
  "properties": {
    "addr:full":"Square De L\u00e9opoldville 17 Bruxelles (etterbeek) Bruxelles-Capitale 1040",
    "addr:housenumber":"17",
    "addr:postcode":"1040",
    "addr:street":"Square De Le\u0301Opoldville",
    "iso:country":"BE",
    "sg:address":"Square De L\u00e9opoldville 17",
    "sg:city":"Bruxelles (etterbeek)",
    "sg:classifiers":[
        {
            "category":"Health Services",
            "subcategory":"Health Practitioner",
            "type":"Services"
        }
    ],
    "sg:phone":"+32 2 646 07 62",
    "sg:postcode":"1040",
    "sg:province":"Bruxelles-Capitale",
    "sg:tags":[
        "physiotherapist"
    ],
    "wof:name":"George P",
    "wof:placetype":"venue"
},
  "geometry": {"coordinates":[4.3836731911,50.8283157349],"type":"Point"}
}