{
  "type": "Feature",
  "properties": {
    "addr:full":"Nieuwstraat 17 Box 3 Sint-niklaas Oost-Vlaanderen 9100",
    "addr:housenumber":"17;3",
    "addr:postcode":"9100",
    "addr:street":"Nieuwstraat;Box",
    "iso:country":"BE",
    "sg:address":"Nieuwstraat 17 Box 3",
    "sg:city":"Sint-niklaas",
    "sg:classifiers":[
        {
            "category":"Professional",
            "subcategory":"Art Services",
            "type":"Services"
        }
    ],
    "sg:phone":"+32 3 776 69 08",
    "sg:postcode":"9100",
    "sg:province":"Oost-Vlaanderen",
    "sg:tags":[
        "photographer"
    ],
    "wof:name":"Hercule",
    "wof:placetype":"venue"
},
  "geometry": {"coordinates":[4.1387472153,51.1636505127],"type":"Point"}
}