{
  "type": "Feature",
  "properties": {
    "addr:full":"Chemin Broctiaux 23 Braine L'alleud (braine-l'alleud) Brabant Wallon 1420",
    "addr:housenumber":"23",
    "addr:postcode":"1420",
    "addr:street":"Chemin Broctiaux",
    "iso:country":"BE",
    "sg:address":"Chemin Broctiaux 23",
    "sg:city":"Braine L'alleud (braine-l'alleud)",
    "sg:classifiers":[
        {
            "category":"Communications",
            "subcategory":"Film & Video Production",
            "type":"Services"
        }
    ],
    "sg:phone":"+32 475 64 62 51",
    "sg:postcode":"1420",
    "sg:province":"Brabant Wallon",
    "sg:tags":[
        "producer",
        "realizators"
    ],
    "wof:name":"Lamy Films Sprl",
    "wof:placetype":"venue"
},
  "geometry": {"coordinates":[-0.7004899979,47.369140625],"type":"Point"}
}