{
  "type": "Feature",
  "properties": {
    "iso:country":"BE",
    "sg:address":"Droogstraat 43",
    "sg:city":"Linter",
    "sg:orig_category":"Traitements param\u00e9dicaux",
    "sg:phone":"+32 11 78 46 09",
    "sg:postcode":"3350",
    "sg:province":"Vlaams-Brabant",
    "wof:name":"M. Everaerts",
    "wof:placetype":"venue"
},
  "geometry": {"coordinates":[5.0643911362,50.8061676025],"type":"Point"}
}