{
  "type": "Feature",
  "properties": {
    "addr:full":"Chauss\u00e9e De Lille 41 Tournai (orcq - Marquain - Lamain) Hainaut 7501",
    "addr:housenumber":"41",
    "addr:postcode":"7501",
    "addr:street":"Chausse\u0301E De Lille;Hainaut",
    "iso:country":"BE",
    "sg:address":"Chauss\u00e9e De Lille 41",
    "sg:city":"Tournai (orcq - Marquain - Lamain)",
    "sg:classifiers":[
        {
            "category":"Bars & Pubs",
            "type":"Food & Drink"
        }
    ],
    "sg:phone":"+32 69 22 27 57",
    "sg:postcode":"7501",
    "sg:province":"Hainaut",
    "wof:name":"Coeur Joyeux (au)",
    "wof:placetype":"venue"
},
  "geometry": {"coordinates":[3.3731899261,50.6050643921],"type":"Point"}
}