{
  "type": "Feature",
  "properties": {
    "iso:country":"BE",
    "sg:address":"Emile Wautersstraat 2",
    "sg:city":"Brussel/bruxelles",
    "sg:orig_category":"Huishoudapparaten, televisies and radio's",
    "sg:phone":"+32 2 478 66 88",
    "sg:postcode":"1020",
    "sg:province":"Bruxelles-Capitale",
    "wof:name":"Elect.brico-shop Schenkel",
    "wof:placetype":"venue"
},
  "geometry": {"coordinates":[4.3427610397,50.8854560852],"type":"Point"}
}