{
  "type": "Feature",
  "properties": {
    "addr:full":"Chauss\u00e9e Du Roeulx 1382 Mons (havr\u00e9) Hainaut 7021",
    "addr:housenumber":"1382",
    "addr:postcode":"7021",
    "addr:street":"Chausse\u0301E Du Roeulx",
    "iso:country":"BE",
    "sg:address":"Chauss\u00e9e Du Roeulx 1382",
    "sg:city":"Mons (havr\u00e9)",
    "sg:classifiers":[
        {
            "category":"Banks & Credit Unions",
            "subcategory":"Investment Brokerage",
            "type":"Services"
        }
    ],
    "sg:phone":"+32 65 87 14 04",
    "sg:postcode":"7021",
    "sg:province":"Hainaut",
    "sg:tags":[
        "fence"
    ],
    "wof:name":"Siraut J",
    "wof:placetype":"venue"
},
  "geometry": {"coordinates":[4.0592241287,50.4701385498],"type":"Point"}
}