{
  "type": "Feature",
  "properties": {
    "addr:full":"Stationsstraat 26 Genk Limburg 3600",
    "addr:housenumber":"26",
    "addr:postcode":"3600",
    "addr:street":"Stationsstraat",
    "iso:country":"BE",
    "sg:address":"Stationsstraat 26",
    "sg:city":"Genk",
    "sg:orig_category":"Pharmaciens",
    "sg:phone":"+32 89 36 32 83",
    "sg:postcode":"3600",
    "sg:province":"Limburg",
    "wof:name":"Gerrit Decoster",
    "wof:placetype":"venue"
},
  "geometry": {"coordinates":[5.5005288124,50.9649391174],"type":"Point"}
}