{
  "type": "Feature",
  "properties": {
    "addr:full":"Dorpsstraat 24-26 Diepenbeek Limburg 3590",
    "addr:postcode":"24-26 diepenbeek;3590",
    "addr:street":"Dorpsstraat",
    "iso:country":"BE",
    "sg:address":"Dorpsstraat 24-26",
    "sg:city":"Diepenbeek",
    "sg:orig_category":"Banques and organismes de cr\u00e9dit",
    "sg:phone":"+32 11 35 01 90",
    "sg:postcode":"3590",
    "sg:province":"Limburg",
    "wof:name":"Dexia",
    "wof:placetype":"venue"
},
  "geometry": {"coordinates":[5.4206662178,50.9083175659],"type":"Point"}
}