{
  "type": "Feature",
  "properties": {
    "iso:country":"BE",
    "sg:address":"Rue De La Fosse Au Sable 52",
    "sg:city":"Braine-l'alleud",
    "sg:classifiers":[
        {
            "category":"Arena",
            "subcategory":"Sports Club",
            "type":"Entertainment"
        }
    ],
    "sg:phone":"+32 2 384 83 39",
    "sg:postcode":"1420",
    "sg:province":"Brabant Wallon",
    "sg:tags":[
        "de"
    ],
    "wof:name":"P.c. Le Paradis",
    "wof:placetype":"venue"
},
  "geometry": {"coordinates":[-83.3254165649,44.4110298157],"type":"Point"}
}