{
  "type": "Feature",
  "properties": {
    "addr:full":"Sentier Du Berger 2 Rebecq Brabant Wallon 1430",
    "addr:housenumber":"2",
    "addr:postcode":"1430",
    "addr:street":"Sentier Du Berger",
    "iso:country":"BE",
    "sg:address":"Sentier Du Berger 2",
    "sg:city":"Rebecq",
    "sg:orig_category":"Woningbouw",
    "sg:phone":"+32 67 63 81 33",
    "sg:postcode":"1430",
    "sg:province":"Brabant Wallon",
    "wof:name":"Hoss & Co",
    "wof:placetype":"venue"
},
  "geometry": {"coordinates":[4.106139183,50.6540336609],"type":"Point"}
}