{
  "type": "Feature",
  "properties": {
    "iso:country":"BE",
    "sg:address":"Maasstraat 80",
    "sg:city":"Scherpenheuvel-zichem (messelbroek)",
    "sg:classifiers":[
        {
            "category":"Building & Trades",
            "subcategory":"Construction",
            "type":"Services"
        }
    ],
    "sg:phone":"+32 13 78 31 25",
    "sg:postcode":"3272",
    "sg:province":"Vlaams-Brabant",
    "sg:tags":[
        "carpenter"
    ],
    "wof:name":"Sterckx & Co Nv",
    "wof:placetype":"venue"
},
  "geometry": {"coordinates":[4.9398789406,50.9959945679],"type":"Point"}
}