{
  "type": "Feature",
  "properties": {
    "iso:country":"BE",
    "sg:address":"Industrielaan 6",
    "sg:city":"Menen",
    "sg:orig_category":"Aardappelproducten Gh Groenten and fruit Gh",
    "sg:phone":"+32 56 53 15 34",
    "sg:postcode":"8930",
    "sg:province":"West-Vlaanderen",
    "wof:name":"Vebena",
    "wof:placetype":"venue"
},
  "geometry": {"coordinates":[3.1051619053,50.7925109863],"type":"Point"}
}