{
  "type": "Feature",
  "properties": {
    "iso:country":"BE",
    "sg:address":"Avenue Des Ch\u00c2teaux 116",
    "sg:city":"Comines-warneton",
    "sg:orig_category":"HUISBRANDOLIE",
    "sg:phone":"+32 56 55 40 73",
    "sg:postcode":"7780",
    "sg:province":"Hainaut",
    "wof:name":"Ecco Coal & Oil",
    "wof:placetype":"venue"
},
  "geometry": {"coordinates":[2.998914957,50.7775382996],"type":"Point"}
}