{
  "type": "Feature",
  "properties": {
    "iso:country":"BE",
    "sg:address":"Avenue Du Monceau 4",
    "sg:city":"Esneux (tilff)",
    "sg:classifiers":[
        {
            "category":"Professional",
            "subcategory":"Management & Consulting",
            "type":"Services"
        }
    ],
    "sg:phone":"+32 4 388 14 97",
    "sg:postcode":"4130",
    "sg:province":"Li\u00e8ge",
    "sg:tags":[
        "-",
        "processing",
        "data",
        "consultant"
    ],
    "wof:name":"Amicorp",
    "wof:placetype":"venue"
},
  "geometry": {"coordinates":[5.5865387917,50.5471305847],"type":"Point"}
}