{
  "type": "Feature",
  "properties": {
    "addr:full":"Laagsimsestraat 9 Alken Limburg 3570",
    "addr:housenumber":"9",
    "addr:postcode":"3570",
    "addr:street":"Laagsimsestraat",
    "iso:country":"BE",
    "sg:address":"Laagsimsestraat 9",
    "sg:city":"Alken",
    "sg:orig_category":"Eleveurs de volaille",
    "sg:phone":"+32 11 59 33 03",
    "sg:postcode":"3570",
    "sg:province":"Limburg",
    "wof:name":"Mussen",
    "wof:placetype":"venue"
},
  "geometry": {"coordinates":[5.2921757698,50.8644714355],"type":"Point"}
}