{
  "type": "Feature",
  "properties": {
    "addr:full":"Grote Baan 1 Linkebeek/linkebeek Vlaams-Brabant 1630",
    "addr:housenumber":"1",
    "addr:postcode":"1630",
    "addr:street":"Grote Baan",
    "iso:country":"BE",
    "sg:address":"Grote Baan 1",
    "sg:city":"Linkebeek/linkebeek",
    "sg:orig_category":"Benzinestations and brandstoffen Herstellingen and onderhoud van auto's Voertuigen",
    "sg:phone":"+32 2 377 01 36",
    "sg:postcode":"1630",
    "sg:province":"Vlaams-Brabant",
    "wof:name":"Vandergucht En Zonen",
    "wof:placetype":"venue"
},
  "geometry": {"coordinates":[4.3255991936,50.774597168],"type":"Point"}
}