{
  "type": "Feature",
  "properties": {
    "addr:full":"Herentalsebaan 331 Antwerpen (groot) Antwerpen 2100",
    "addr:housenumber":"331",
    "addr:postcode":"2100",
    "addr:street":"Herentalsebaan;Groot Antwerpen",
    "iso:country":"BE",
    "sg:address":"Herentalsebaan 331",
    "sg:city":"Antwerpen (groot)",
    "sg:orig_category":"Banques and organismes de cr\u00e9dit",
    "sg:phone":"+32 3 321 19 98",
    "sg:postcode":"2100",
    "sg:province":"Antwerpen",
    "wof:name":"Bbl",
    "wof:placetype":"venue"
},
  "geometry": {"coordinates":[4.4586100578,51.2203941345],"type":"Point"}
}