{
  "type": "Feature",
  "properties": {
    "iso:country":"BE",
    "sg:address":"Koningslaan 242",
    "sg:city":"Knokke-heist",
    "sg:orig_category":"Alimentation sp\u00e9cialis\u00e9e. Poissonniers and \u00e9caillers",
    "sg:phone":"+32 50 60 26 53",
    "sg:postcode":"8300",
    "sg:province":"West-Vlaanderen",
    "wof:name":"Giraldo Firmin",
    "wof:placetype":"venue"
},
  "geometry": {"coordinates":[3.2848498821,51.3465614319],"type":"Point"}
}