{
  "type": "Feature",
  "properties": {
    "iso:country":"BE",
    "sg:address":"Vuntlaan 15",
    "sg:city":"Leuven (wilsele)",
    "sg:classifiers":[
        {
            "category":"Health Services",
            "subcategory":"Doctor",
            "type":"Services"
        }
    ],
    "sg:phone":"+32 16 44 84 43",
    "sg:postcode":"3012",
    "sg:province":"Vlaams-Brabant",
    "sg:tags":[
        "medicinephysicians",
        "surgeon"
    ],
    "wof:name":"D'hooge D",
    "wof:placetype":"venue"
},
  "geometry": {"coordinates":[4.7117729187,50.9208488464],"type":"Point"}
}