{
  "type": "Feature",
  "properties": {
    "addr:full":"Thier De Hodimont 48 Verviers (petit-rechain) Li\u00e8ge 4800",
    "addr:housenumber":"48",
    "addr:postcode":"4800",
    "addr:street":"Thier De Hodimont",
    "iso:country":"BE",
    "sg:address":"Thier De Hodimont 48",
    "sg:city":"Verviers (petit-rechain)",
    "sg:classifiers":[
        {
            "category":"Building & Trades",
            "subcategory":"Construction",
            "type":"Services"
        }
    ],
    "sg:phone":"+32 87 31 65 50",
    "sg:postcode":"4800",
    "sg:province":"Li\u00e8ge",
    "sg:tags":[
        "carpenter"
    ],
    "wof:name":"Gillessen Jp",
    "wof:placetype":"venue"
},
  "geometry": {"coordinates":[5.8594508171,50.5917663574],"type":"Point"}
}