{
  "type": "Feature",
  "properties": {
    "iso:country":"BE",
    "sg:address":"Jules Van Praetstraat 19",
    "sg:city":"Brussel/bruxelles",
    "sg:classifiers":[
        {
            "category":"Fast Food",
            "type":"Food & Drink"
        }
    ],
    "sg:phone":"+32 2 502 48 28",
    "sg:postcode":"1000",
    "sg:province":"Bruxelles-Capitale",
    "sg:tags":[
        "\u00c0",
        "restaurants",
        "emporter",
        "restaurant"
    ],
    "wof:name":"R\u00cave Asie",
    "wof:placetype":"venue"
},
  "geometry": {"coordinates":[4.3484988213,50.8483581543],"type":"Point"}
}