{
  "type": "Feature",
  "properties": {
    "iso:country":"BE",
    "sg:address":"Vaartstraat 28",
    "sg:city":"Balen",
    "sg:orig_category":"Huishoudapparaten, televisies and radio's Telecommunicatieapparaten",
    "sg:phone":"+32 14 81 51 01",
    "sg:postcode":"2490",
    "sg:province":"Antwerpen",
    "wof:name":"Cts",
    "wof:placetype":"venue"
},
  "geometry": {"coordinates":[5.166041851,51.1713218689],"type":"Point"}
}