{
  "type": "Feature",
  "properties": {
    "iso:country":"BE",
    "sg:address":"Rue Des Raines 65",
    "sg:city":"Verviers",
    "sg:classifiers":[
        {
            "category":"Community Center",
            "type":"Public Place"
        }
    ],
    "sg:phone":"+32 87 31 62 90",
    "sg:postcode":"4800",
    "sg:province":"Li\u00e8ge",
    "sg:tags":[
        "medical"
    ],
    "wof:name":"Maison Medicale Mosaique",
    "wof:placetype":"venue"
},
  "geometry": {"coordinates":[5.8669199944,50.5943222046],"type":"Point"}
}