{
  "type": "Feature",
  "properties": {
    "addr:full":"Rue Ch\u00c9ri 40b14 Li\u00c8ge Li\u00e8ge 4000",
    "addr:housenumber":"40b14",
    "addr:postcode":"4000",
    "addr:street":"Rue Che\u0301Ri",
    "iso:country":"BE",
    "sg:address":"Rue Ch\u00c9ri 40b14",
    "sg:city":"Li\u00c8ge",
    "sg:orig_category":"Advocaten and juridische adviseurs",
    "sg:phone":"+32 4 227 45 20",
    "sg:postcode":"4000",
    "sg:province":"Li\u00e8ge",
    "wof:name":"Marc Luyten",
    "wof:placetype":"venue"
},
  "geometry": {"coordinates":[5.5885338783,50.6506462097],"type":"Point"}
}