{
  "type": "Feature",
  "properties": {
    "iso:country":"BE",
    "sg:address":"Mechelsesteenweg 127",
    "sg:city":"Bonheiden",
    "sg:orig_category":"Pharmaciens",
    "sg:phone":"+32 15 55 05 04",
    "sg:postcode":"2820",
    "sg:province":"Antwerpen",
    "wof:name":"Apotheek De Volksmacht",
    "wof:placetype":"venue"
},
  "geometry": {"coordinates":[4.5396418571,51.025177002],"type":"Point"}
}