{
  "type": "Feature",
  "properties": {
    "iso:country":"BE",
    "sg:address":"Rue Des Aub\u00e9pines 17",
    "sg:city":"Bastogne",
    "sg:classifiers":[
        {
            "category":"Health Services",
            "subcategory":"Health Practitioner",
            "type":"Services"
        }
    ],
    "sg:phone":"+32 61 21 95 25",
    "sg:postcode":"6600",
    "sg:province":"Luxembourg",
    "sg:tags":[
        "physiotherapist"
    ],
    "wof:name":"Bouchez Donatienne",
    "wof:placetype":"venue"
},
  "geometry": {"coordinates":[5.7148008347,50.0081253052],"type":"Point"}
}