{
  "type": "Feature",
  "properties": {
    "addr:full":"Langemarkstraat 10 Zonnebeke West-Vlaanderen 8980",
    "addr:housenumber":"10",
    "addr:postcode":"8980",
    "addr:street":"Langemarkstraat",
    "iso:country":"BE",
    "sg:address":"Langemarkstraat 10",
    "sg:city":"Zonnebeke",
    "sg:classifiers":[
        {
            "category":"Health Services",
            "subcategory":"Nursing And Care Facility",
            "type":"Services"
        }
    ],
    "sg:phone":"+32 51 77 92 71",
    "sg:postcode":"8980",
    "sg:province":"West-Vlaanderen",
    "sg:tags":[
        "public"
    ],
    "wof:name":"O.c.m.w.",
    "wof:placetype":"venue"
},
  "geometry": {"coordinates":[2.9863879681,50.8734931946],"type":"Point"}
}