{
  "type": "Feature",
  "properties": {
    "iso:country":"BE",
    "sg:address":"Avenue Des Combattants 70",
    "sg:city":"Genappe",
    "sg:classifiers":[
        {
            "category":"Cafe",
            "type":"Food & Drink"
        }
    ],
    "sg:phone":"+32 67 77 37 91",
    "sg:postcode":"1470",
    "sg:province":"Brabant Wallon",
    "sg:tags":[
        "caf\u00e9s"
    ],
    "wof:name":"Caf\u00c9 L'escale",
    "wof:placetype":"venue"
},
  "geometry": {"coordinates":[4.508108139,50.6158294678],"type":"Point"}
}