{
  "type": "Feature",
  "properties": {
    "iso:country":"BE",
    "sg:address":"Stationstraat 111",
    "sg:city":"Lommel",
    "sg:orig_category":"Gespecialiseerde niet-residenti\u00eble bouw",
    "sg:phone":"+32 477 32 28 60",
    "sg:postcode":"3900",
    "sg:province":"Limburg",
    "wof:name":"De Sleuvenkapper",
    "wof:placetype":"venue"
},
  "geometry": {"coordinates":[5.3141517639,51.2229614258],"type":"Point"}
}