{
  "type": "Feature",
  "properties": {
    "iso:country":"BE",
    "sg:address":"Stokstraat 55",
    "sg:city":"Halen",
    "sg:orig_category":"Producteurs de fruits",
    "sg:phone":"+32 13 44 11 57",
    "sg:postcode":"3545",
    "sg:province":"Limburg",
    "wof:name":"Richard Severijns",
    "wof:placetype":"venue"
},
  "geometry": {"coordinates":[5.0543417931,50.9260215759],"type":"Point"}
}