{
  "type": "Feature",
  "properties": {
    "iso:country":"BE",
    "sg:address":"Breendonkstraat 22",
    "sg:city":"Londerzeel",
    "sg:classifiers":[
        {
            "category":"Professional",
            "subcategory":"Management & Consulting",
            "type":"Services"
        }
    ],
    "sg:phone":"+32 52 30 32 51",
    "sg:postcode":"1840",
    "sg:province":"Vlaams-Brabant",
    "sg:tags":[
        "consultant"
    ],
    "wof:name":"De Borger Consult Bvba",
    "wof:placetype":"venue"
},
  "geometry": {"coordinates":[4.2951421738,51.0253372192],"type":"Point"}
}