{
  "type": "Feature",
  "properties": {
    "iso:country":"BE",
    "sg:address":"Place Des Peuples 12",
    "sg:city":"Colfontaine (p\u00e2turages)",
    "sg:classifiers":[
        {
            "category":"Personal",
            "subcategory":"Nail Salon",
            "type":"Services"
        }
    ],
    "sg:phone":"+32 65 67 22 11",
    "sg:postcode":"7340",
    "sg:province":"Hainaut",
    "sg:tags":[
        "pedicure"
    ],
    "wof:name":"Institut Tina",
    "wof:placetype":"venue"
},
  "geometry": {"coordinates":[3.8601870537,50.4103240967],"type":"Point"}
}