{
  "type": "Feature",
  "properties": {
    "addr:full":"Gentsesteenweg 49 Aalst Oost-Vlaanderen 9300",
    "addr:housenumber":"49",
    "addr:postcode":"9300",
    "addr:street":"Gentsesteenweg",
    "iso:country":"BE",
    "sg:address":"Gentsesteenweg 49",
    "sg:city":"Aalst",
    "sg:classifiers":[
        {
            "category":"Professional",
            "subcategory":"Testing Lab",
            "type":"Services"
        }
    ],
    "sg:phone":"+32 53 21 43 84",
    "sg:postcode":"9300",
    "sg:province":"Oost-Vlaanderen",
    "sg:tags":[
        "chemist"
    ],
    "wof:name":"Bouqu\u00e9",
    "wof:placetype":"venue"
},
  "geometry": {"coordinates":[4.0251860619,50.9381828308],"type":"Point"}
}