{
  "type": "Feature",
  "properties": {
    "iso:country":"BE",
    "sg:address":"M. Lippenslaan 25",
    "sg:city":"Knokke-heist",
    "sg:orig_category":"Transports ferroviaires",
    "sg:phone":"+32 50 60 33 14",
    "sg:postcode":"8300",
    "sg:province":"West-Vlaanderen",
    "wof:name":"Station Knokke",
    "wof:placetype":"venue"
},
  "geometry": {"coordinates":[3.2873549461,51.3421707153],"type":"Point"}
}