{
  "type": "Feature",
  "properties": {
    "addr:full":"Haachtsesteenweg 380 Kampenhout Vlaams-Brabant 1910",
    "addr:housenumber":"380",
    "addr:postcode":"1910",
    "addr:street":"Haachtsesteenweg",
    "iso:country":"BE",
    "sg:address":"Haachtsesteenweg 380",
    "sg:city":"Kampenhout",
    "sg:orig_category":"Plomberie, chauffage and installations sanitaires",
    "sg:phone":"+32 16 65 64 75",
    "sg:postcode":"1910",
    "sg:province":"Vlaams-Brabant",
    "wof:name":"Smets Eddy",
    "wof:placetype":"venue"
},
  "geometry": {"coordinates":[4.5668888092,50.9441337585],"type":"Point"}
}