{
  "type": "Feature",
  "properties": {
    "iso:country":"BE",
    "sg:address":"Keibergstraat 2b1",
    "sg:city":"Leuven",
    "sg:orig_category":"S\u00e9curit\u00e9 sociale",
    "sg:phone":"+32 16 20 01 06",
    "sg:postcode":"3001",
    "sg:province":"Vlaams-Brabant",
    "wof:name":"Kristelijk Ziekenfonds",
    "wof:placetype":"venue"
},
  "geometry": {"coordinates":[4.6708421707,50.8730659485],"type":"Point"}
}