{
  "type": "Feature",
  "properties": {
    "iso:country":"BE",
    "sg:address":"Onze Lieve Vrouwstraat 2",
    "sg:city":"Beringen",
    "sg:orig_category":"V\u00eatements pour Hommes",
    "sg:phone":"+32 11 42 35 30",
    "sg:postcode":"3580",
    "sg:province":"Limburg",
    "wof:name":"Herenmode Cristoff",
    "wof:placetype":"venue"
},
  "geometry": {"coordinates":[5.2200341225,51.0481529236],"type":"Point"}
}