{
  "type": "Feature",
  "properties": {
    "iso:country":"BE",
    "sg:address":"Rue Du Travail 5",
    "sg:city":"Gr\u00e2ce-hollogne (gr\u00e2ce-berleur)",
    "sg:classifiers":[
        {
            "category":"Professional",
            "type":"Services"
        }
    ],
    "sg:phone":"+32 4 247 64 19",
    "sg:postcode":"4460",
    "sg:province":"Li\u00e8ge",
    "sg:tags":[
        "industrial",
        "automation"
    ],
    "wof:name":"C.a.i. Sa",
    "wof:placetype":"venue"
},
  "geometry": {"coordinates":[5.4984397888,50.6567993164],"type":"Point"}
}