{
  "type": "Feature",
  "properties": {
    "addr:full":"Nieuwlandstraat 31 Zemst Vlaams-Brabant 1982",
    "addr:housenumber":"31",
    "addr:postcode":"1982",
    "addr:street":"Nieuwlandstraat;Vlaams-Brabant",
    "iso:country":"BE",
    "sg:address":"Nieuwlandstraat 31",
    "sg:city":"Zemst",
    "sg:orig_category":"Installation \u00e9lectrique r\u00e9sidentielle",
    "sg:phone":"+32 15 61 14 86",
    "sg:postcode":"1982",
    "sg:province":"Vlaams-Brabant",
    "wof:name":"Michel Guerin",
    "wof:placetype":"venue"
},
  "geometry": {"coordinates":[4.5130000114,50.9622688293],"type":"Point"}
}