{
  "type": "Feature",
  "properties": {
    "iso:country":"BE",
    "sg:address":"Rue De Mons 139b2",
    "sg:city":"Tubize",
    "sg:orig_category":"Installatie van houten of kunststof schrijnwerk",
    "sg:phone":"+32 2 355 42 79",
    "sg:postcode":"1480",
    "sg:province":"Brabant Wallon",
    "wof:name":"Ets. Rauwens Frederic",
    "wof:placetype":"venue"
},
  "geometry": {"coordinates":[4.2007632256,50.6890258789],"type":"Point"}
}