{
  "type": "Feature",
  "properties": {
    "iso:country":"BE",
    "sg:address":"Binnenbeekstraat 3",
    "sg:city":"Zemst",
    "sg:classifiers":[
        {
            "category":"Communications",
            "subcategory":"Film & Video Production",
            "type":"Services"
        }
    ],
    "sg:phone":"+32 15 61 09 56",
    "sg:postcode":"1982",
    "sg:province":"Vlaams-Brabant",
    "sg:tags":[
        "platen",
        "cassette",
        "cd's"
    ],
    "wof:name":"Jean Dehennin",
    "wof:placetype":"venue"
},
  "geometry": {"coordinates":[4.5048279762,50.9628372192],"type":"Point"}
}