{
  "type": "Feature",
  "properties": {
    "addr:full":"Hollestraat 7 Kruibeke Oost-Vlaanderen 9150",
    "addr:housenumber":"7",
    "addr:postcode":"9150",
    "addr:street":"Hollestraat",
    "iso:country":"BE",
    "sg:address":"Hollestraat 7",
    "sg:city":"Kruibeke",
    "sg:orig_category":"Rundveehouders Varkenskwekers",
    "sg:phone":"+32 3 774 26 75",
    "sg:postcode":"9150",
    "sg:province":"Oost-Vlaanderen",
    "wof:name":"Rene De Ryck",
    "wof:placetype":"venue"
},
  "geometry": {"coordinates":[4.3110260963,51.1818656921],"type":"Point"}
}