{
  "type": "Feature",
  "properties": {
    "addr:full":"Steenweg Op Leopoldsburg 1 Balen Antwerpen 2490",
    "addr:housenumber":"1",
    "addr:postcode":"2490",
    "addr:street":"Steenweg Op Leopoldsburg",
    "iso:country":"BE",
    "sg:address":"Steenweg Op Leopoldsburg 1",
    "sg:city":"Balen",
    "sg:orig_category":"Metaalbehandeling and -bekleding",
    "sg:phone":"+32 14 31 20 45",
    "sg:postcode":"2490",
    "sg:province":"Antwerpen",
    "wof:name":"De Meester W",
    "wof:placetype":"venue"
},
  "geometry": {"coordinates":[5.2375102043,51.1349487305],"type":"Point"}
}