{
  "type": "Feature",
  "properties": {
    "addr:full":"Passage Pieter Van Aelst 8 Aalst Oost-Vlaanderen 9300",
    "addr:housenumber":"8",
    "addr:postcode":"9300",
    "addr:street":"Passage Pieter Van Aelst",
    "iso:country":"BE",
    "sg:address":"Passage Pieter Van Aelst 8",
    "sg:city":"Aalst",
    "sg:orig_category":"V\u00eatements. Textiles",
    "sg:phone":"+32 53 70 34 97",
    "sg:postcode":"9300",
    "sg:province":"Oost-Vlaanderen",
    "wof:name":"Phildar",
    "wof:placetype":"venue"
},
  "geometry": {"coordinates":[4.0370321274,50.939125061],"type":"Point"}
}