{
  "type": "Feature",
  "properties": {
    "addr:full":"Schaagstraat 2 Kruishoutem Oost-Vlaanderen 9771",
    "addr:housenumber":"2",
    "addr:postcode":"9771",
    "addr:street":"Schaagstraat",
    "iso:country":"BE",
    "sg:address":"Schaagstraat 2",
    "sg:city":"Kruishoutem",
    "sg:classifiers":[
        {
            "category":"Building & Trades",
            "subcategory":"Construction",
            "type":"Services"
        }
    ],
    "sg:phone":"+32 56 60 32 64",
    "sg:postcode":"9771",
    "sg:province":"Oost-Vlaanderen",
    "sg:tags":[
        "granite",
        "working"
    ],
    "wof:name":"Steenimex Nv",
    "wof:placetype":"venue"
},
  "geometry": {"coordinates":[3.5096099377,50.885684967],"type":"Point"}
}