{
  "type": "Feature",
  "properties": {
    "iso:country":"BE",
    "sg:address":"All\u00c9e Centrale 17",
    "sg:city":"Fleron",
    "sg:orig_category":"Sportclubs",
    "sg:phone":"+32 4 358 93 61",
    "sg:postcode":"4620",
    "sg:province":"Li\u00e8ge",
    "wof:name":"Club V\u00c9lodrome De Rocourt",
    "wof:placetype":"venue"
},
  "geometry": {"coordinates":[5.6894922256,50.616809845],"type":"Point"}
}