{
  "type": "Feature",
  "properties": {
    "addr:full":"Henry Van Heurckstraat 24 Antwerpen Antwerpen 2000",
    "addr:housenumber":"24",
    "addr:postcode":"2000",
    "addr:street":"Henry;Heurckstraat",
    "iso:country":"BE",
    "sg:address":"Henry Van Heurckstraat 24",
    "sg:city":"Antwerpen",
    "sg:orig_category":"Erotische- and Escortediensten Huwelijks- and Relatiebureaus",
    "sg:phone":"+32 3 288 10 53",
    "sg:postcode":"2000",
    "sg:province":"Antwerpen",
    "wof:name":"Meerdere Gay Jongens",
    "wof:placetype":"venue"
},
  "geometry": {"coordinates":[4.4088020325,51.2137985229],"type":"Point"}
}