{
  "type": "Feature",
  "properties": {
    "addr:full":"Avenue De La Chasse 180 Bruxelles (etterbeek) Bruxelles-Capitale 1040",
    "addr:housenumber":"180",
    "addr:postcode":"1040",
    "addr:street":"Avenue De La Chasse",
    "iso:country":"BE",
    "sg:address":"Avenue De La Chasse 180",
    "sg:city":"Bruxelles (etterbeek)",
    "sg:classifiers":[
        {
            "category":"Banks & Credit Unions",
            "subcategory":"Bureau De Change",
            "type":"Services"
        }
    ],
    "sg:phone":"+32 2 732 91 73",
    "sg:postcode":"1040",
    "sg:province":"Bruxelles-Capitale",
    "sg:tags":[
        "measuring",
        "control",
        "apparatus"
    ],
    "wof:name":"Lamba Instruments",
    "wof:placetype":"venue"
},
  "geometry": {"coordinates":[4.3942818642,50.8356781006],"type":"Point"}
}