{
  "type": "Feature",
  "properties": {
    "addr:full":"Tiensesteenweg 145 Bierbeek Vlaams-Brabant 3360",
    "addr:housenumber":"145",
    "addr:postcode":"3360",
    "addr:street":"Tiensesteenweg",
    "iso:country":"BE",
    "sg:address":"Tiensesteenweg 145",
    "sg:city":"Bierbeek",
    "sg:orig_category":"Sportclubs",
    "sg:phone":"+32 16 46 18 57",
    "sg:postcode":"3360",
    "sg:province":"Vlaams-Brabant",
    "wof:name":"V.c. Marvoc",
    "wof:placetype":"venue"
},
  "geometry": {"coordinates":[4.7662591934,50.8617782593],"type":"Point"}
}