{
  "type": "Feature",
  "properties": {
    "iso:country":"BE",
    "sg:address":"Rue P\u00c9trelle 19",
    "sg:city":"Philippeville",
    "sg:orig_category":"Rundveehouders",
    "sg:phone":"+32 71 66 61 19",
    "sg:postcode":"5600",
    "sg:province":"Namur",
    "wof:name":"Bayet Rene Et Michel",
    "wof:placetype":"venue"
},
  "geometry": {"coordinates":[4.5331110954,50.1773033142],"type":"Point"}
}