{
  "type": "Feature",
  "properties": {
    "addr:full":"Grand Route 86 Tournai (gaurain-ramecroix) Hainaut 7530",
    "addr:postcode":"7530",
    "addr:street":"Grand Route 86",
    "iso:country":"BE",
    "sg:address":"Grand Route 86",
    "sg:city":"Tournai (gaurain-ramecroix)",
    "sg:classifiers":[
        {
            "category":"Farming",
            "subcategory":"Livestock Farm",
            "type":"Manufacturing & Wholesale Goods"
        }
    ],
    "sg:phone":"+32 69 54 62 53",
    "sg:postcode":"7530",
    "sg:province":"Hainaut",
    "sg:tags":[
        "buyer"
    ],
    "wof:name":"Delm\u00e9e J M Et Fils",
    "wof:placetype":"venue"
},
  "geometry": {"coordinates":[3.4516570568,50.5990371704],"type":"Point"}
}