{
  "type": "Feature",
  "properties": {
    "addr:full":"Herenweg 6 Knokke-heist West-Vlaanderen 8300",
    "addr:housenumber":"6",
    "addr:postcode":"8300",
    "addr:street":"Herenweg",
    "iso:country":"BE",
    "sg:address":"Herenweg 6",
    "sg:city":"Knokke-heist",
    "sg:orig_category":"Fabrication and montage de mobilier. Meubles D\u00e9taillants, Am\u00e9nagement de B\u00e2timents et de Cuisines. F",
    "sg:phone":"+32 50 60 90 09",
    "sg:postcode":"8300",
    "sg:province":"West-Vlaanderen",
    "wof:name":"Debbaut N.v.",
    "wof:placetype":"venue"
},
  "geometry": {"coordinates":[3.287694931,51.3467254639],"type":"Point"}
}