{
  "type": "Feature",
  "properties": {
    "addr:full":"Guido Gezellelaan 63 Mechelen Antwerpen 2800",
    "addr:housenumber":"63",
    "addr:postcode":"2800",
    "addr:street":"Guido Gezellelaan",
    "iso:country":"BE",
    "sg:address":"Guido Gezellelaan 63",
    "sg:city":"Mechelen",
    "sg:classifiers":[
        {
            "category":"Professional",
            "subcategory":"Accounting & Tax Preparation",
            "type":"Services"
        }
    ],
    "sg:phone":"+32 15 27 46 33",
    "sg:postcode":"2800",
    "sg:province":"Antwerpen",
    "sg:tags":[
        "bookkeeper"
    ],
    "wof:name":"Ellegeest M",
    "wof:placetype":"venue"
},
  "geometry": {"coordinates":[4.4726090431,51.0309524536],"type":"Point"}
}