{
  "type": "Feature",
  "properties": {
    "addr:full":"Cockstraat 22 Staden (oostnieuwkerke) West-Vlaanderen 8840",
    "addr:housenumber":"22",
    "addr:postcode":"8840",
    "addr:street":"Cockstraat",
    "iso:country":"BE",
    "sg:address":"Cockstraat 22",
    "sg:city":"Staden (oostnieuwkerke)",
    "sg:classifiers":[
        {
            "category":"Health Services",
            "subcategory":"Health Practitioner",
            "type":"Services"
        }
    ],
    "sg:phone":"+32 51 24 13 41",
    "sg:postcode":"8840",
    "sg:province":"West-Vlaanderen",
    "sg:tags":[
        "physiotherapist"
    ],
    "wof:name":"Gheldof Marika",
    "wof:placetype":"venue"
},
  "geometry": {"coordinates":[3.0558431149,50.9391441345],"type":"Point"}
}