{
  "type": "Feature",
  "properties": {
    "iso:country":"BE",
    "sg:address":"Markgravestraat 19",
    "sg:city":"Antwerpen",
    "sg:orig_category":"Cr\u00e8ches and garderies d'enfants",
    "sg:phone":"+32 3 231 63 02",
    "sg:postcode":"2000",
    "sg:province":"Antwerpen",
    "wof:name":"Kribbe Baby Boom",
    "wof:placetype":"venue"
},
  "geometry": {"coordinates":[4.4076957703,51.220035553],"type":"Point"}
}