{
  "type": "Feature",
  "properties": {
    "addr:full":"Route De Macon 5 Momignies Hainaut 6590",
    "addr:housenumber":"5",
    "addr:postcode":"6590",
    "addr:street":"Route De Macon;Hainaut",
    "iso:country":"BE",
    "sg:address":"Route De Macon 5",
    "sg:city":"Momignies",
    "sg:classifiers":[
        {
            "category":"Organizations",
            "subcategory":"Community Association",
            "type":"Services"
        }
    ],
    "sg:phone":"+32 60 51 24 60",
    "sg:postcode":"6590",
    "sg:province":"Hainaut",
    "sg:tags":[
        "cultural"
    ],
    "wof:name":"Centre Culturel Local De Momignies",
    "wof:placetype":"venue"
},
  "geometry": {"coordinates":[4.1665592194,50.0309715271],"type":"Point"}
}