{
  "type": "Feature",
  "properties": {
    "iso:country":"BE",
    "sg:address":"Oude Boekhoutestraat 16",
    "sg:city":"Assenede",
    "sg:orig_category":"Eleveurs and marchands de porcs",
    "sg:phone":"+32 9 373 93 53",
    "sg:postcode":"9968",
    "sg:province":"Oost-Vlaanderen",
    "wof:name":"Jozef De Smet",
    "wof:placetype":"venue"
},
  "geometry": {"coordinates":[3.6919939518,51.2398681641],"type":"Point"}
}