{
  "type": "Feature",
  "properties": {
    "iso:country":"BE",
    "sg:address":"Avenue De Scailmont 96",
    "sg:city":"Manage",
    "sg:classifiers":[
        {
            "category":"Organizations",
            "subcategory":"Community Association",
            "type":"Services"
        }
    ],
    "sg:phone":"+32 64 54 03 46",
    "sg:postcode":"7170",
    "sg:province":"Hainaut",
    "sg:tags":[
        "cultural"
    ],
    "wof:name":"Centre Culturel De Scailmont",
    "wof:placetype":"venue"
},
  "geometry": {"coordinates":[4.2394380569,50.5005073547],"type":"Point"}
}