{
  "type": "Feature",
  "properties": {
    "addr:full":"Rue Charles-magnette 2bc013 Li\u00c8ge Li\u00e8ge 4000",
    "addr:postcode":"2bc013;4000",
    "addr:street":"Rue Charles-Magnette",
    "iso:country":"BE",
    "sg:address":"Rue Charles-magnette 2bc013",
    "sg:city":"Li\u00c8ge",
    "sg:orig_category":"Avocats and conseillers juridiques",
    "sg:phone":"+32 4 222 27 63",
    "sg:postcode":"4000",
    "sg:province":"Li\u00e8ge",
    "wof:name":"Nathalie Gobin",
    "wof:placetype":"venue"
},
  "geometry": {"coordinates":[5.5743618011,50.64112854],"type":"Point"}
}