{
  "type": "Feature",
  "properties": {
    "addr:full":"Amblfvestraat 31 Oudergem/auderghem Bruxelles-Capitale 1160",
    "addr:housenumber":"31",
    "addr:postcode":"1160",
    "addr:street":"Amblfvestraat;/",
    "iso:country":"BE",
    "sg:address":"Amblfvestraat 31",
    "sg:city":"Oudergem/auderghem",
    "sg:orig_category":"Diverse grafische activiteiten",
    "sg:phone":"+32 2 734 09 40",
    "sg:postcode":"1160",
    "sg:province":"Bruxelles-Capitale",
    "wof:name":"Christian Vanhoeter",
    "wof:placetype":"venue"
},
  "geometry": {"coordinates":[4.4035592079,50.8241958618],"type":"Point"}
}