{
  "type": "Feature",
  "properties": {
    "iso:country":"BE",
    "sg:address":"Rue Surbruy\u00c8re 108",
    "sg:city":"Andenne",
    "sg:orig_category":"Enseignement maternel and primaire",
    "sg:phone":"+32 81 58 88 43",
    "sg:postcode":"5300",
    "sg:province":"Namur",
    "wof:name":"Ecole Fondamentale Libre",
    "wof:placetype":"venue"
},
  "geometry": {"coordinates":[5.0853328705,50.4606208801],"type":"Point"}
}