{
  "type": "Feature",
  "properties": {
    "addr:full":"Wijngaardstraat 38 Tielt-winge Vlaams-Brabant 3390",
    "addr:housenumber":"38",
    "addr:postcode":"3390",
    "addr:street":"Wijngaardstraat",
    "iso:country":"BE",
    "sg:address":"Wijngaardstraat 38",
    "sg:city":"Tielt-winge",
    "sg:orig_category":"Eleveurs d'animaux domestiques",
    "sg:phone":"+32 16 63 33 32",
    "sg:postcode":"3390",
    "sg:province":"Vlaams-Brabant",
    "wof:name":"Kennel Van 't Argenhof",
    "wof:placetype":"venue"
},
  "geometry": {"coordinates":[4.8647789955,50.9452705383],"type":"Point"}
}