{
  "type": "Feature",
  "properties": {
    "addr:full":"Rijksweg 62 Bornem Antwerpen 2880",
    "addr:housenumber":"62",
    "addr:postcode":"2880",
    "addr:street":"Rijksweg",
    "iso:country":"BE",
    "sg:address":"Rijksweg 62",
    "sg:city":"Bornem",
    "sg:orig_category":"Meubles D\u00e9taillants, Am\u00e9nagement de B\u00e2timents et de Cuisines. Agences d'exp\u00e9dition. Meubles Fab",
    "sg:phone":"+32 3 889 59 58",
    "sg:postcode":"2880",
    "sg:province":"Antwerpen",
    "wof:name":"Country-line",
    "wof:placetype":"venue"
},
  "geometry": {"coordinates":[4.2510180473,51.0997772217],"type":"Point"}
}