{
  "type": "Feature",
  "properties": {
    "addr:full":"Kuipersberg 7 Bertem Vlaams-Brabant 3060",
    "addr:housenumber":"7",
    "addr:postcode":"3060",
    "addr:street":"Kuipersberg",
    "iso:country":"BE",
    "sg:address":"Kuipersberg 7",
    "sg:city":"Bertem",
    "sg:classifiers":[
        {
            "category":"Building & Trades",
            "subcategory":"Landscaping Services",
            "type":"Services"
        }
    ],
    "sg:phone":"+32 16 48 05 48",
    "sg:postcode":"3060",
    "sg:province":"Vlaams-Brabant",
    "sg:tags":[
        "-",
        "lopping",
        "work",
        "tree",
        "felling"
    ],
    "wof:name":"Vrebos L",
    "wof:placetype":"venue"
},
  "geometry": {"coordinates":[4.6092782021,50.8589286804],"type":"Point"}
}