{
  "type": "Feature",
  "properties": {
    "iso:country":"BE",
    "sg:address":"Meusegemstraat 64",
    "sg:city":"Meise",
    "sg:classifiers":[
        {
            "category":"Wholesale",
            "subcategory":"Farm Supplies",
            "type":"Manufacturing & Wholesale Goods"
        }
    ],
    "sg:phone":"+32 2 269 36 38",
    "sg:postcode":"186",
    "sg:tags":[
        "machine",
        "agricoles",
        "mat\u00e9riel",
        "gr"
    ],
    "wof:name":"Firma Stuyck Frans",
    "wof:placetype":"venue"
},
  "geometry": {"coordinates":[4.2878050804,50.9572601318],"type":"Point"}
}