{
  "type": "Feature",
  "properties": {
    "iso:country":"BE",
    "sg:address":"Europark 2039",
    "sg:city":"Houthalen",
    "sg:classifiers":[
        {
            "category":"Retail",
            "subcategory":"Car Wash",
            "type":"Services"
        }
    ],
    "sg:phone":"+32 11 52 00 20",
    "sg:postcode":"3530",
    "sg:province":"Limburg",
    "sg:tags":[
        "polishing",
        "product",
        "cleaning"
    ],
    "wof:name":"Chemoplast Nv",
    "wof:placetype":"venue"
},
  "geometry": {"coordinates":[5.3971891403,51.0415763855],"type":"Point"}
}