{
  "type": "Feature",
  "properties": {
    "addr:full":"Vis\u00c9 Voie 224 Herstal Li\u00e8ge 4041",
    "addr:housenumber":"224",
    "addr:postcode":"4041",
    "addr:street":"Voie",
    "iso:country":"BE",
    "sg:address":"Vis\u00c9 Voie 224",
    "sg:city":"Herstal",
    "sg:orig_category":"Banques and organismes de cr\u00e9dit",
    "sg:phone":"+32 4 227 98 78",
    "sg:postcode":"4041",
    "sg:province":"Li\u00e8ge",
    "wof:name":"Banque Epargne Patriotiq.",
    "wof:placetype":"venue"
},
  "geometry": {"coordinates":[5.5761637688,50.6702728271],"type":"Point"}
}