{
  "type": "Feature",
  "properties": {
    "addr:full":"Nijverheidsstraat 28 Gavere Oost-Vlaanderen 9890",
    "addr:housenumber":"28",
    "addr:postcode":"9890",
    "addr:street":"Nijverheidsstraat",
    "iso:country":"BE",
    "sg:address":"Nijverheidsstraat 28",
    "sg:city":"Gavere",
    "sg:orig_category":"Elektrische installaties voor woningen",
    "sg:phone":"+32 9 384 99 10",
    "sg:postcode":"9890",
    "sg:province":"Oost-Vlaanderen",
    "wof:name":"Wim Van Bellingen",
    "wof:placetype":"venue"
},
  "geometry": {"coordinates":[3.6852660179,50.9186553955],"type":"Point"}
}