{
  "type": "Feature",
  "properties": {
    "iso:country":"BE",
    "sg:address":"Jan Hammeneckerstraat 37",
    "sg:city":"Meise",
    "sg:orig_category":"Groententeelt",
    "sg:phone":"+32 52 30 15 15",
    "sg:postcode":"1861",
    "sg:province":"Vlaams-Brabant",
    "wof:name":"Emiel Bogemans",
    "wof:placetype":"venue"
},
  "geometry": {"coordinates":[4.324901104,50.9907226562],"type":"Point"}
}