{
  "type": "Feature",
  "properties": {
    "addr:full":"Waregemstraat 87 Deerlijk West-Vlaanderen 8540",
    "addr:housenumber":"87",
    "addr:postcode":"8540",
    "addr:street":"Waregemstraat",
    "iso:country":"BE",
    "sg:address":"Waregemstraat 87",
    "sg:city":"Deerlijk",
    "sg:orig_category":"Installation \u00e9lectrique r\u00e9sidentielle",
    "sg:phone":"+32 56 71 44 28",
    "sg:postcode":"8540",
    "sg:province":"West-Vlaanderen",
    "wof:name":"Hendrik Derammelaere",
    "wof:placetype":"venue"
},
  "geometry": {"coordinates":[3.3652439117,50.8557167053],"type":"Point"}
}