{
  "type": "Feature",
  "properties": {
    "iso:country":"BE",
    "sg:address":"Rue D'eghez\u00e9e 14",
    "sg:city":"Sambreville (auvelais)",
    "sg:classifiers":[
        {
            "category":"Bars & Pubs",
            "type":"Food & Drink"
        }
    ],
    "sg:phone":"+32 71 77 37 80",
    "sg:postcode":"5060",
    "sg:province":"Namur",
    "wof:name":"Pont (du)",
    "wof:placetype":"venue"
},
  "geometry": {"coordinates":[4.6353111267,50.4513931274],"type":"Point"}
}