{
  "type": "Feature",
  "properties": {
    "addr:full":"Posterijlaan 4 Bis Pittem West-Vlaanderen 8740",
    "addr:housenumber":"4 bis",
    "addr:postcode":"8740",
    "addr:street":"Posterijlaan",
    "iso:country":"BE",
    "sg:address":"Posterijlaan 4 Bis",
    "sg:city":"Pittem",
    "sg:orig_category":"Bloemen and planten Huisdieren and benodigdheden Royal Canin Tuinbenodigdheden",
    "sg:phone":"+32 51 46 68 53",
    "sg:postcode":"8740",
    "sg:province":"West-Vlaanderen",
    "wof:name":"Aveve Lannoo",
    "wof:placetype":"venue"
},
  "geometry": {"coordinates":[3.2563700676,50.9911727905],"type":"Point"}
}