{
  "type": "Feature",
  "properties": {
    "iso:country":"BE",
    "sg:address":"Deinsesteenweg 73",
    "sg:city":"Tielt",
    "sg:orig_category":"Groententeelt",
    "sg:phone":"+32 51 40 27 11",
    "sg:postcode":"8700",
    "sg:province":"West-Vlaanderen",
    "wof:name":"Andr\u00c9 Tanghe",
    "wof:placetype":"venue"
},
  "geometry": {"coordinates":[3.3817849159,50.9935951233],"type":"Point"}
}