{
  "type": "Feature",
  "properties": {
    "addr:full":"Grootloonstraat 17bb Borgloon Limburg 3840",
    "addr:housenumber":"17bb",
    "addr:postcode":"3840",
    "addr:street":"Grootloonstraat",
    "iso:country":"BE",
    "sg:address":"Grootloonstraat 17bb",
    "sg:city":"Borgloon",
    "sg:orig_category":"Tuinen",
    "sg:phone":"+32 12 74 66 69",
    "sg:postcode":"3840",
    "sg:province":"Limburg",
    "wof:name":"Wathion Bert",
    "wof:placetype":"venue"
},
  "geometry": {"coordinates":[5.3574991226,50.7970619202],"type":"Point"}
}