{
  "type": "Feature",
  "properties": {
    "iso:country":"BE",
    "sg:address":"Zonnekestr 13",
    "sg:city":"Kortrijk",
    "sg:orig_category":"Goods handling - material and equipment Health - equipments and instruments Mechanical Engineering -",
    "sg:phone":"+32 56 36 11 54",
    "sg:postcode":"8501",
    "sg:province":"West-Vlaanderen",
    "wof:name":"Vlietra Nv",
    "wof:placetype":"venue"
},
  "geometry": {"coordinates":[3.2336709499,50.8435592651],"type":"Point"}
}