{
  "type": "Feature",
  "properties": {
    "addr:full":"Kortemarkstraat 53 Ichtegem West-Vlaanderen 8480",
    "addr:housenumber":"53",
    "addr:postcode":"8480",
    "addr:street":"Kortemarkstraat",
    "iso:country":"BE",
    "sg:address":"Kortemarkstraat 53",
    "sg:city":"Ichtegem",
    "sg:classifiers":[
        {
            "category":"Farming",
            "subcategory":"Farm & Veterinary Services",
            "type":"Manufacturing & Wholesale Goods"
        }
    ],
    "sg:phone":"+32 51 54 41 60",
    "sg:postcode":"8480",
    "sg:province":"West-Vlaanderen",
    "sg:tags":[
        "agricultural",
        "contractor"
    ],
    "wof:name":"Staelens J",
    "wof:placetype":"venue"
},
  "geometry": {"coordinates":[3.0278789997,51.0758171082],"type":"Point"}
}