{
  "type": "Feature",
  "properties": {
    "iso:country":"BE",
    "sg:address":"Chemin De Rhecq 3",
    "sg:city":"Ath",
    "sg:orig_category":"Drukkerijen and copyshops Reclamebureaus",
    "sg:phone":"+32 68 64 62 52",
    "sg:postcode":"7812",
    "sg:province":"Hainaut",
    "wof:name":"Beuse Graphic",
    "wof:placetype":"venue"
},
  "geometry": {"coordinates":[3.7483150959,50.6626396179],"type":"Point"}
}