{
  "type": "Feature",
  "properties": {
    "addr:full":"Kemmelstraat 34 Heuvelland West-Vlaanderen 8956",
    "addr:housenumber":"34",
    "addr:postcode":"8956",
    "addr:street":"Kemmelstraat",
    "iso:country":"BE",
    "sg:address":"Kemmelstraat 34",
    "sg:city":"Heuvelland",
    "sg:classifiers":[
        {
            "category":"Food & Beverages",
            "subcategory":"Fruits & Vegetables",
            "type":"Retail Goods"
        }
    ],
    "sg:phone":"+32 57 44 45 78",
    "sg:postcode":"8956",
    "sg:province":"West-Vlaanderen",
    "sg:tags":[
        "l\u00e9gumes"
    ],
    "wof:name":"Huis De Polka",
    "wof:placetype":"venue"
},
  "geometry": {"coordinates":[2.7997829914,50.7808265686],"type":"Point"}
}