{
  "type": "Feature",
  "properties": {
    "iso:country":"BE",
    "sg:address":"Kapellestraat 53",
    "sg:city":"Laarne (kalken)",
    "sg:classifiers":[
        {
            "category":"Insurance",
            "subcategory":"Insurance Agent",
            "type":"Services"
        }
    ],
    "sg:phone":"+32 9 369 45 19",
    "sg:postcode":"9270",
    "sg:province":"Oost-Vlaanderen",
    "sg:tags":[
        "-",
        "representative"
    ],
    "wof:name":"Van Hoorde & Co",
    "wof:placetype":"venue"
},
  "geometry": {"coordinates":[3.8871319294,51.0257568359],"type":"Point"}
}