{
  "type": "Feature",
  "properties": {
    "iso:country":"BE",
    "sg:address":"Hookstrasse 23",
    "sg:city":"Eupen",
    "sg:classifiers":[
        {
            "category":"Shopping",
            "subcategory":"Florist",
            "type":"Retail Goods"
        }
    ],
    "sg:phone":"+32 87 74 24 61",
    "sg:postcode":"4700",
    "sg:province":"Li\u00e8ge",
    "wof:name":"Kreusch",
    "wof:placetype":"venue"
},
  "geometry": {"coordinates":[6.0371022224,50.6338844299],"type":"Point"}
}