{
  "type": "Feature",
  "properties": {
    "iso:country":"BE",
    "sg:address":"Blondieaustraat 11",
    "sg:city":"Vilvoorde",
    "sg:orig_category":"Installatie van houten of kunststof schrijnwerk Installatie van metalen schrijnwerk",
    "sg:phone":"+32 2 251 07 76",
    "sg:postcode":"1800",
    "sg:province":"Vlaams-Brabant",
    "wof:name":"Stiro Plastic Center",
    "wof:placetype":"venue"
},
  "geometry": {"coordinates":[4.4323101044,50.926235199],"type":"Point"}
}