{
  "type": "Feature",
  "properties": {
    "iso:country":"BE",
    "sg:address":"Atletenstraat 51",
    "sg:city":"Antwerpen",
    "sg:orig_category":"Informaticaconsulenten",
    "sg:phone":"+32 3 248 49 27",
    "sg:postcode":"2020",
    "sg:province":"Antwerpen",
    "wof:name":"Cornelis It",
    "wof:placetype":"venue"
},
  "geometry": {"coordinates":[4.3833398819,51.1843261719],"type":"Point"}
}