{
  "type": "Feature",
  "properties": {
    "iso:country":"BE",
    "sg:address":"Markt 1",
    "sg:city":"Gavere",
    "sg:orig_category":"Werk and personeelsselectie",
    "sg:phone":"+32 9 384 14 91",
    "sg:postcode":"9890",
    "sg:province":"Oost-Vlaanderen",
    "wof:name":"Vdab",
    "wof:placetype":"venue"
},
  "geometry": {"coordinates":[3.6598091125,50.9282646179],"type":"Point"}
}