{
  "type": "Feature",
  "properties": {
    "addr:full":"Place De Beclers 10 Tournai Hainaut 7532",
    "addr:housenumber":"10",
    "addr:postcode":"7532",
    "addr:street":"Place De Beclers",
    "iso:country":"BE",
    "sg:address":"Place De Beclers 10",
    "sg:city":"Tournai",
    "sg:orig_category":"Travail and traitement du bois. Installation de menuiserie en bois and plastique",
    "sg:phone":"+32 69 54 72 50",
    "sg:postcode":"7532",
    "sg:province":"Hainaut",
    "wof:name":"Dervaux Jean Luc & Claude",
    "wof:placetype":"venue"
},
  "geometry": {"coordinates":[3.5041089058,50.6212768555],"type":"Point"}
}