{
  "type": "Feature",
  "properties": {
    "addr:full":"Stapelstraat 18 Sint Truiden Limburg 3800",
    "addr:housenumber":"18",
    "addr:postcode":"3800",
    "addr:street":"Stapelstraat",
    "iso:country":"BE",
    "sg:address":"Stapelstraat 18",
    "sg:city":"Sint Truiden",
    "sg:orig_category":"Mat\u00e9riel de T\u00e9l\u00e9communication",
    "sg:phone":"+32 11 70 76 08",
    "sg:postcode":"3800",
    "sg:province":"Limburg",
    "wof:name":"Point O",
    "wof:placetype":"venue"
},
  "geometry": {"coordinates":[5.1832351685,50.8153038025],"type":"Point"}
}