{
  "type": "Feature",
  "properties": {
    "iso:country":"BE",
    "sg:address":"Boulevard Du Nord 40",
    "sg:city":"Namur",
    "sg:classifiers":[
        {
            "category":"Personal",
            "subcategory":"Beauty Salon",
            "type":"Services"
        }
    ],
    "sg:phone":"+32 81 22 17 99",
    "sg:postcode":"5000",
    "sg:province":"Namur",
    "sg:tags":[
        "de",
        "coiffure"
    ],
    "wof:name":"Guy Haudry",
    "wof:placetype":"venue"
},
  "geometry": {"coordinates":[4.865044117,50.4702949524],"type":"Point"}
}