{
  "type": "Feature",
  "properties": {
    "iso:country":"BE",
    "sg:address":"Chauss\u00c9e De Tervuren 84",
    "sg:city":"Waterloo",
    "sg:orig_category":"Traitements param\u00e9dicaux",
    "sg:phone":"+32 2 351 19 35",
    "sg:postcode":"1410",
    "sg:province":"Brabant Wallon",
    "wof:name":"V. Delmez",
    "wof:placetype":"venue"
},
  "geometry": {"coordinates":[4.4042258263,50.7042617798],"type":"Point"}
}