{
  "type": "Feature",
  "properties": {
    "addr:full":"Stationsstr 57 Wetteren Oost-Vlaanderen 9200",
    "addr:housenumber":"57",
    "addr:postcode":"9200",
    "addr:street":"Stationsstr",
    "iso:country":"BE",
    "sg:address":"Stationsstr 57",
    "sg:city":"Wetteren",
    "sg:classifiers":[
        {
            "category":"Banks & Credit Unions",
            "subcategory":"Bank",
            "type":"Services"
        }
    ],
    "sg:phone":"+32 53 69 02 10",
    "sg:postcode":"9200",
    "sg:province":"Oost-Vlaanderen",
    "wof:name":"G\u00e9n\u00e9rale De Banque Sa",
    "wof:placetype":"venue"
},
  "geometry": {"coordinates":[4.0079159737,51.0029029846],"type":"Point"}
}