{
  "type": "Feature",
  "properties": {
    "iso:country":"BE",
    "sg:address":"Joseph Smeetslaan 4",
    "sg:city":"Maasmechelen",
    "sg:classifiers":[
        {
            "category":"Retail",
            "subcategory":"Auto Repair",
            "type":"Services"
        }
    ],
    "sg:phone":"+32 89 76 48 62",
    "sg:postcode":"3630",
    "sg:province":"Limburg",
    "sg:tags":[
        "automobile",
        "servic",
        "electrical",
        "-"
    ],
    "wof:name":"Auto-electro Goossens M",
    "wof:placetype":"venue"
},
  "geometry": {"coordinates":[5.6950941086,50.9641532898],"type":"Point"}
}