{
  "type": "Feature",
  "properties": {
    "addr:full":"Meulebekestraat 4 Dentergem West-Vlaanderen 8720",
    "addr:housenumber":"4",
    "addr:postcode":"8720",
    "addr:street":"Meulebekestraat",
    "iso:country":"BE",
    "sg:address":"Meulebekestraat 4",
    "sg:city":"Dentergem",
    "sg:orig_category":"Varkenskwekers",
    "sg:phone":"+32 51 63 38 47",
    "sg:postcode":"8720",
    "sg:province":"West-Vlaanderen",
    "wof:name":"Herman Vanhollebeke",
    "wof:placetype":"venue"
},
  "geometry": {"coordinates":[3.382930994,50.9583587646],"type":"Point"}
}