{
  "type": "Feature",
  "properties": {
    "addr:full":"Chee De Mons 18 Nijvel Brabant Wallon 1400",
    "addr:housenumber":"18",
    "addr:postcode":"1400",
    "addr:street":"Chee;Mons;Brabant Wallon",
    "iso:country":"BE",
    "sg:address":"Chee De Mons 18",
    "sg:city":"Nijvel",
    "sg:orig_category":"V\u00eatements pour Hommes",
    "sg:phone":"+32 67 44 34 14",
    "sg:postcode":"1400",
    "sg:province":"Brabant Wallon",
    "wof:name":"Celio",
    "wof:placetype":"venue"
},
  "geometry": {"coordinates":[4.318939209,50.5941696167],"type":"Point"}
}