{
  "type": "Feature",
  "properties": {
    "addr:full":"Rue L\u00e9on Delacroix 1 Bruxelles (anderlecht) Bruxelles-Capitale 1070",
    "addr:housenumber":"1",
    "addr:postcode":"1070",
    "addr:street":"Rue Le\u0301On Delacroix",
    "iso:country":"BE",
    "sg:address":"Rue L\u00e9on Delacroix 1",
    "sg:city":"Bruxelles (anderlecht)",
    "sg:classifiers":[
        {
            "category":"Bars & Pubs",
            "type":"Food & Drink"
        }
    ],
    "sg:phone":"+32 2 520 96 31",
    "sg:postcode":"1070",
    "sg:province":"Bruxelles-Capitale",
    "sg:tags":[
        "tavern"
    ],
    "wof:name":"Alriwane",
    "wof:placetype":"venue"
},
  "geometry": {"coordinates":[4.3306818008,50.8425064087],"type":"Point"}
}