{
  "type": "Feature",
  "properties": {
    "addr:full":"Delaerestraat 2b Roeselare West-Vlaanderen 8800",
    "addr:housenumber":"2b",
    "addr:postcode":"8800",
    "addr:street":"Delaerestraat",
    "iso:country":"BE",
    "sg:address":"Delaerestraat 2b",
    "sg:city":"Roeselare",
    "sg:classifiers":[
        {
            "category":"Shopping",
            "subcategory":"Clothing, Apparel, & Fashions",
            "type":"Retail Goods"
        }
    ],
    "sg:phone":"+32 51 22 88 98",
    "sg:postcode":"8800",
    "sg:province":"West-Vlaanderen",
    "sg:tags":[
        "lady",
        "clothing",
        "-"
    ],
    "wof:name":"Celeste",
    "wof:placetype":"venue"
},
  "geometry": {"coordinates":[3.1277348995,50.94688797],"type":"Point"}
}