{
  "type": "Feature",
  "properties": {
    "iso:country":"BE",
    "sg:address":"Rue Franklin Roosevelt 255",
    "sg:city":"Trooz",
    "sg:orig_category":"Plomberie, chauffage and installations sanitaires. Air conditionn\u00e9 and ventilation",
    "sg:phone":"+32 87 26 73 69",
    "sg:postcode":"4870",
    "sg:province":"Li\u00e8ge",
    "wof:name":"Ino-technique",
    "wof:placetype":"venue"
},
  "geometry": {"coordinates":[5.7391982079,50.571521759],"type":"Point"}
}