{
  "type": "Feature",
  "properties": {
    "addr:full":"Molenstraat 53 Kluisbergen Oost-Vlaanderen 9690",
    "addr:housenumber":"53",
    "addr:postcode":"9690",
    "addr:street":"Molenstraat",
    "iso:country":"BE",
    "sg:address":"Molenstraat 53",
    "sg:city":"Kluisbergen",
    "sg:classifiers":[
        {
            "category":"Shopping",
            "subcategory":"Clothing, Apparel, & Fashions",
            "type":"Retail Goods"
        }
    ],
    "sg:phone":"+32 55 38 76 94",
    "sg:postcode":"9690",
    "sg:province":"Oost-Vlaanderen",
    "sg:tags":[
        "ondergoed",
        "lingerie"
    ],
    "wof:name":"Lingerie Mil\u00c8ne",
    "wof:placetype":"venue"
},
  "geometry": {"coordinates":[3.5062301159,50.7886886597],"type":"Point"}
}