{
  "type": "Feature",
  "properties": {
    "addr:full":"Rue De La Passerelle 4 Sambreville (tamines) Namur 5060",
    "addr:housenumber":"4",
    "addr:postcode":"5060",
    "addr:street":"Rue De La Passerelle",
    "iso:country":"BE",
    "sg:address":"Rue De La Passerelle 4",
    "sg:city":"Sambreville (tamines)",
    "sg:classifiers":[
        {
            "category":"Travel",
            "subcategory":"Travel Agent",
            "type":"Entertainment"
        }
    ],
    "sg:phone":"+32 71 74 28 00",
    "sg:postcode":"5060",
    "sg:province":"Namur",
    "sg:tags":[
        "agency"
    ],
    "wof:name":"Michaux",
    "wof:placetype":"venue"
},
  "geometry": {"coordinates":[4.6285200119,50.4448738098],"type":"Point"}
}