{
  "type": "Feature",
  "properties": {
    "iso:country":"BE",
    "sg:address":"Bruggesteenweg 55a",
    "sg:city":"Hooglede (gits)",
    "sg:classifiers":[
        {
            "category":"Home & Garden",
            "subcategory":"Garden Supply",
            "type":"Retail Goods"
        }
    ],
    "sg:phone":"+32 51 72 41 84",
    "sg:postcode":"8830",
    "sg:province":"West-Vlaanderen",
    "wof:name":"Robinia",
    "wof:placetype":"venue"
},
  "geometry": {"coordinates":[3.0878529549,50.9799919128],"type":"Point"}
}