{
  "type": "Feature",
  "properties": {
    "addr:full":"Hendrik Kanorastraat 22 Antwerpen Antwerpen 2180",
    "addr:housenumber":"22",
    "addr:postcode":"2180",
    "addr:street":"Hendrik Kanorastraat",
    "iso:country":"BE",
    "sg:address":"Hendrik Kanorastraat 22",
    "sg:city":"Antwerpen",
    "sg:classifiers":[
        {
            "category":"Insurance",
            "subcategory":"Insurance Agent",
            "type":"Services"
        }
    ],
    "sg:phone":"+32 3 664 57 18",
    "sg:postcode":"2180",
    "sg:province":"Antwerpen",
    "sg:tags":[
        "verzekeringsmakelaars",
        "expert"
    ],
    "wof:name":"Bur. Boomans-delarivi\u00c8re",
    "wof:placetype":"venue"
},
  "geometry": {"coordinates":[4.4182572365,51.2778625488],"type":"Point"}
}