{
  "type": "Feature",
  "properties": {
    "iso:country":"BE",
    "sg:address":"Otterstraat 112 - 114",
    "sg:city":"Turnhout",
    "sg:orig_category":"MBK. R\u00e9parations and entretien de motos. Motos",
    "sg:phone":"+32 14 42 08 08",
    "sg:postcode":"2300",
    "sg:province":"Antwerpen",
    "wof:name":"Delta Motors",
    "wof:placetype":"venue"
},
  "geometry": {"coordinates":[4.9558601379,51.3216018677],"type":"Point"}
}