{
  "type": "Feature",
  "properties": {
    "iso:country":"BE",
    "sg:address":"Rue Winston Churchill 440",
    "sg:city":"Courcelles",
    "sg:classifiers":[
        {
            "category":"Utilities",
            "subcategory":"Fuel Oil & Lpg",
            "type":"Services"
        }
    ],
    "sg:phone":"+32 71 46 89 09",
    "sg:postcode":"6180",
    "sg:province":"Hainaut",
    "wof:name":"Hainaut Tanking Sa",
    "wof:placetype":"venue"
},
  "geometry": {"coordinates":[4.400179863,50.4614295959],"type":"Point"}
}