{
  "type": "Feature",
  "properties": {
    "addr:full":"Ninoofsesteenweg 8 Dilbeek Vlaams-Brabant 1700",
    "addr:housenumber":"8",
    "addr:postcode":"1700",
    "addr:street":"Ninoofsesteenweg",
    "iso:country":"BE",
    "sg:address":"Ninoofsesteenweg 8",
    "sg:city":"Dilbeek",
    "sg:classifiers":[
        {
            "category":"Sports & Exercise",
            "subcategory":"Ice Rink",
            "type":"Entertainment"
        }
    ],
    "sg:phone":"+32 2 466 32 29",
    "sg:postcode":"1700",
    "sg:province":"Vlaams-Brabant",
    "sg:tags":[
        "machine",
        "making"
    ],
    "wof:name":"Boudart S",
    "wof:placetype":"venue"
},
  "geometry": {"coordinates":[4.2785201073,50.8451881409],"type":"Point"}
}