{
  "type": "Feature",
  "properties": {
    "addr:full":"Rue Hors-ch\u00c2teau 16 Li\u00c8ge Li\u00e8ge 4000",
    "addr:housenumber":"16",
    "addr:postcode":"4000",
    "addr:street":"Rue Hors-Cha\u0302Teau",
    "iso:country":"BE",
    "sg:address":"Rue Hors-ch\u00c2teau 16",
    "sg:city":"Li\u00c8ge",
    "sg:orig_category":"Biens d'occasion",
    "sg:phone":"+32 4 223 56 37",
    "sg:postcode":"4000",
    "sg:province":"Li\u00e8ge",
    "wof:name":"Librairie Eureka-garweg",
    "wof:placetype":"venue"
},
  "geometry": {"coordinates":[5.5767889023,50.6465454102],"type":"Point"}
}