{
  "type": "Feature",
  "properties": {
    "iso:country":"BE",
    "sg:address":"Toekomststraat 8",
    "sg:city":"Lommel",
    "sg:classifiers":[
        {
            "category":"Cafe",
            "type":"Food & Drink"
        }
    ],
    "sg:phone":"+32 11 40 17 46",
    "sg:postcode":"3920",
    "sg:province":"Limburg",
    "sg:tags":[
        "caf\u00e9s"
    ],
    "wof:name":"Julien Stans",
    "wof:placetype":"venue"
},
  "geometry": {"coordinates":[5.2696638107,51.1652565002],"type":"Point"}
}