{
  "type": "Feature",
  "properties": {
    "iso:country":"BE",
    "sg:address":"Plezierstraat 21",
    "sg:city":"Gent",
    "sg:orig_category":"Articles m\u00e9talliques ouvr\u00e9s divers Fab. Quincailleries. Bois Gr",
    "sg:phone":"+32 9 380 17 18",
    "sg:postcode":"9030",
    "sg:province":"Oost-Vlaanderen",
    "wof:name":"Aannemingen De Groote",
    "wof:placetype":"venue"
},
  "geometry": {"coordinates":[3.6745951176,51.072933197],"type":"Point"}
}