{
  "type": "Feature",
  "properties": {
    "iso:country":"BE",
    "sg:address":"Rue Aux G\u00e2des 28",
    "sg:city":"Ath",
    "sg:classifiers":[
        {
            "category":"Education",
            "subcategory":"School",
            "type":"Public Place"
        }
    ],
    "sg:phone":"+32 68 26 51 20",
    "sg:postcode":"7800",
    "sg:province":"Hainaut",
    "sg:tags":[
        "secondary"
    ],
    "wof:name":"Inst. Saint-francois De Sales",
    "wof:placetype":"venue"
},
  "geometry": {"coordinates":[3.7758440971,50.6300086975],"type":"Point"}
}