{
  "type": "Feature",
  "properties": {
    "addr:full":"R\u00e9sidence La Prairie 39 Mons (ghlin) Hainaut 7011",
    "addr:housenumber":"39",
    "addr:postcode":"7011",
    "addr:street":"La Prairie",
    "iso:country":"BE",
    "sg:address":"R\u00e9sidence La Prairie 39",
    "sg:city":"Mons (ghlin)",
    "sg:classifiers":[
        {
            "category":"Food & Beverages",
            "subcategory":"Dairy",
            "type":"Retail Goods"
        }
    ],
    "sg:phone":"+32 65 31 59 20",
    "sg:postcode":"7011",
    "sg:province":"Hainaut",
    "sg:tags":[
        "product",
        "-"
    ],
    "wof:name":"Lemiez",
    "wof:placetype":"venue"
},
  "geometry": {"coordinates":[3.912539959,50.4712982178],"type":"Point"}
}