{
  "type": "Feature",
  "properties": {
    "iso:country":"BE",
    "sg:address":"Chauss\u00c9e D'ixelles 74",
    "sg:city":"Elsene/ixelles",
    "sg:orig_category":"R\u00e9parations d'horloges, montres and bijoux",
    "sg:phone":"+32 2 512 84 74",
    "sg:postcode":"1050",
    "sg:province":"Bruxelles-Capitale",
    "wof:name":"Jacky Quartz",
    "wof:placetype":"venue"
},
  "geometry": {"coordinates":[4.3631491661,50.8362998962],"type":"Point"}
}