{
  "type": "Feature",
  "properties": {
    "addr:full":"Interleuvenlaan 62a Leuven (heverlee) Vlaams-Brabant 3001",
    "addr:housenumber":"62a",
    "addr:postcode":"3001",
    "addr:street":"Interleuvenlaan",
    "iso:country":"BE",
    "sg:address":"Interleuvenlaan 62a",
    "sg:city":"Leuven (heverlee)",
    "sg:classifiers":[
        {
            "category":"Arts & Performance",
            "subcategory":"Symphony",
            "type":"Entertainment"
        }
    ],
    "sg:phone":"+32 16 40 60 00",
    "sg:postcode":"3001",
    "sg:province":"Vlaams-Brabant",
    "sg:tags":[
        "orchestra"
    ],
    "wof:name":"Prima La Musica",
    "wof:placetype":"venue"
},
  "geometry": {"coordinates":[4.7360210419,50.849067688],"type":"Point"}
}