{
  "type": "Feature",
  "properties": {
    "addr:full":"Rue De Marche 83ba Bastogne Luxembourg 6600",
    "addr:postcode":"6600",
    "addr:street":"Rue De Marche 83Ba",
    "iso:country":"BE",
    "sg:address":"Rue De Marche 83ba",
    "sg:city":"Bastogne",
    "sg:orig_category":"Artsen and specialisten",
    "sg:phone":"+32 61 21 61 04",
    "sg:postcode":"6600",
    "sg:province":"Luxembourg",
    "wof:name":"Phuong-than Tran Thi",
    "wof:placetype":"venue"
},
  "geometry": {"coordinates":[5.7083120346,50.0016441345],"type":"Point"}
}