{
  "type": "Feature",
  "properties": {
    "addr:full":"Rue Heyvaert 76 Bruxelles (anderlecht) Bruxelles-Capitale 1070",
    "addr:housenumber":"76",
    "addr:postcode":"1070",
    "addr:street":"Rue Heyvaert",
    "iso:country":"BE",
    "sg:address":"Rue Heyvaert 76",
    "sg:city":"Bruxelles (anderlecht)",
    "sg:classifiers":[
        {
            "category":"Autos & Motor Vehicles",
            "subcategory":"Auto Supplies",
            "type":"Retail Goods"
        }
    ],
    "sg:phone":"+32 2 522 51 81",
    "sg:postcode":"1070",
    "sg:province":"Bruxelles-Capitale",
    "sg:tags":[
        "access",
        "automobile",
        "part",
        "-"
    ],
    "wof:name":"Auto 32 Plus",
    "wof:placetype":"venue"
},
  "geometry": {"coordinates":[4.3333449364,50.8474884033],"type":"Point"}
}