{
  "type": "Feature",
  "properties": {
    "addr:full":"Rue De Renory 101 Li\u00e8ge 1 (angleur) Li\u00e8ge 4031",
    "addr:housenumber":"101;1",
    "addr:postcode":"4031",
    "addr:street":"Rue De Renory",
    "iso:country":"BE",
    "sg:address":"Rue De Renory 101",
    "sg:city":"Li\u00e8ge 1 (angleur)",
    "sg:classifiers":[
        {
            "category":"Education",
            "subcategory":"School",
            "type":"Public Place"
        }
    ],
    "sg:phone":"+32 4 344 97 47",
    "sg:postcode":"4031",
    "sg:province":"Li\u00e8ge",
    "sg:tags":[
        "secondary"
    ],
    "wof:name":"Institut Maria Goretti",
    "wof:placetype":"venue"
},
  "geometry": {"coordinates":[5.5787758827,50.6129264832],"type":"Point"}
}