{
  "type": "Feature",
  "properties": {
    "iso:country":"BE",
    "sg:address":"Bleekstraat 10b3",
    "sg:city":"Mechelen",
    "sg:classifiers":[
        {
            "category":"Arena",
            "subcategory":"Sports Club",
            "type":"Entertainment"
        }
    ],
    "sg:phone":"+32 15 21 85 03",
    "sg:postcode":"2800",
    "sg:province":"Antwerpen",
    "sg:tags":[
        "terrain",
        "hors",
        "de",
        "installation",
        "sportifs"
    ],
    "wof:name":"K.s.k. Hoboken",
    "wof:placetype":"venue"
},
  "geometry": {"coordinates":[4.4868888855,51.0274963379],"type":"Point"}
}