{
  "type": "Feature",
  "properties": {
    "iso:country":"BE",
    "sg:address":"39",
    "sg:city":"Beverce Ferme Libe 4960 Malmedy",
    "sg:classifiers":[
        {
            "category":"Travel",
            "subcategory":"Hotels & Motels",
            "type":"Entertainment"
        }
    ],
    "sg:phone":"+32 80 33 02 47",
    "sg:postcode":"39",
    "sg:tags":[
        "hotels",
        "business",
        "restaurant"
    ],
    "wof:name":"Thomas Hubert Pierre & Therese M.",
    "wof:placetype":"venue"
},
  "geometry": {"coordinates":[6.034632206,50.4457092285],"type":"Point"}
}