{
  "type": "Feature",
  "properties": {
    "addr:full":"Rue De Bosnie 49 Bruxelles (saint-gilles) Bruxelles-Capitale 1060",
    "addr:housenumber":"49",
    "addr:postcode":"1060",
    "addr:street":"Rue De Bosnie",
    "iso:country":"BE",
    "sg:address":"Rue De Bosnie 49",
    "sg:city":"Bruxelles (saint-gilles)",
    "sg:classifiers":[
        {
            "category":"Communications",
            "subcategory":"Film & Video Production",
            "type":"Services"
        }
    ],
    "sg:phone":"+32 2 534 37 34",
    "sg:postcode":"1060",
    "sg:province":"Bruxelles-Capitale",
    "sg:tags":[
        "sound",
        "recording",
        "studio"
    ],
    "wof:name":"Arcadia",
    "wof:placetype":"venue"
},
  "geometry": {"coordinates":[4.3358798027,50.8283004761],"type":"Point"}
}