{
  "type": "Feature",
  "properties": {
    "addr:full":"Rue De Tournai 54 Brunehaut Hainaut 7620",
    "addr:housenumber":"54",
    "addr:postcode":"7620",
    "addr:street":"Rue De Tournai;Hainaut",
    "iso:country":"BE",
    "sg:address":"Rue De Tournai 54",
    "sg:city":"Brunehaut",
    "sg:classifiers":[
        {
            "category":"Cafe",
            "type":"Food & Drink"
        }
    ],
    "sg:phone":"+32 69 34 44 72",
    "sg:postcode":"7620",
    "sg:province":"Hainaut",
    "sg:tags":[
        "caf\u00e9s"
    ],
    "wof:name":"Caf\u00c9 Quart De 12 Heures",
    "wof:placetype":"venue"
},
  "geometry": {"coordinates":[3.4203300476,50.5198097229],"type":"Point"}
}