{
  "type": "Feature",
  "properties": {
    "addr:full":"Kolvestraat 16 Brugge West-Vlaanderen 8000",
    "addr:housenumber":"16",
    "addr:postcode":"8000",
    "addr:street":"Kolvestraat",
    "iso:country":"BE",
    "sg:address":"Kolvestraat 16",
    "sg:city":"Brugge",
    "sg:classifiers":[
        {
            "category":"Manufacturing",
            "subcategory":"Metals",
            "type":"Manufacturing & Wholesale Goods"
        }
    ],
    "sg:phone":"+32 475 83 91 97",
    "sg:postcode":"8000",
    "sg:province":"West-Vlaanderen",
    "sg:tags":[
        "work",
        "sheet"
    ],
    "wof:name":"Vermander D",
    "wof:placetype":"venue"
},
  "geometry": {"coordinates":[3.1999340057,51.2420272827],"type":"Point"}
}