{
  "type": "Feature",
  "properties": {
    "addr:full":"Borreberg 12 Anzegem West-Vlaanderen 8570",
    "addr:housenumber":"12",
    "addr:postcode":"8570",
    "addr:street":"Borreberg",
    "iso:country":"BE",
    "sg:address":"Borreberg 12",
    "sg:city":"Anzegem",
    "sg:classifiers":[
        {
            "category":"Insurance",
            "subcategory":"Life Insurance",
            "type":"Services"
        }
    ],
    "sg:phone":"+32 56 68 98 10",
    "sg:postcode":"8570",
    "sg:province":"West-Vlaanderen",
    "sg:tags":[
        "assurance"
    ],
    "wof:name":"R. Daene",
    "wof:placetype":"venue"
},
  "geometry": {"coordinates":[3.4796130657,50.8339004517],"type":"Point"}
}