{
  "type": "Feature",
  "properties": {
    "iso:country":"BE",
    "sg:address":"Rue Jean-baptiste Vanp\u00c9 26",
    "sg:city":"Forest (bruxelles)",
    "sg:orig_category":"V\u00eatements pour b\u00e9b\u00e9s and enfants",
    "sg:phone":"+32 2 331 53 11",
    "sg:postcode":"1190",
    "sg:province":"Bruxelles-Capitale",
    "wof:name":"Planet Kid's",
    "wof:placetype":"venue"
},
  "geometry": {"coordinates":[4.3183579445,50.8098831177],"type":"Point"}
}