{
  "type": "Feature",
  "properties": {
    "addr:full":"Nijverheidsstraat 53 Beringen Limburg 3580",
    "addr:housenumber":"53",
    "addr:postcode":"3580",
    "addr:street":"Nijverheidsstraat",
    "iso:country":"BE",
    "sg:address":"Nijverheidsstraat 53",
    "sg:city":"Beringen",
    "sg:classifiers":[
        {
            "category":"Professional",
            "subcategory":"Printing & Photocopies",
            "type":"Services"
        }
    ],
    "sg:phone":"+32 11 42 37 86",
    "sg:postcode":"3580",
    "sg:province":"Limburg",
    "sg:tags":[
        "silkscreen",
        "-"
    ],
    "wof:name":"Schroyen J",
    "wof:placetype":"venue"
},
  "geometry": {"coordinates":[5.216296196,51.051197052],"type":"Point"}
}