{
  "type": "Feature",
  "properties": {
    "iso:country":"BE",
    "sg:address":"Grote Veldstraat 84",
    "sg:city":"Staden",
    "sg:orig_category":"Slagers",
    "sg:phone":"+32 51 57 05 54",
    "sg:postcode":"8840",
    "sg:province":"West-Vlaanderen",
    "wof:name":"Guido Maddelein",
    "wof:placetype":"venue"
},
  "geometry": {"coordinates":[3.0192871094,50.9687843323],"type":"Point"}
}