{
  "type": "Feature",
  "properties": {
    "addr:full":"Dijleweg 48a Bonheiden (rijmenam) Antwerpen 2820",
    "addr:housenumber":"48a",
    "addr:postcode":"2820",
    "addr:street":"Dijleweg",
    "iso:country":"BE",
    "sg:address":"Dijleweg 48a",
    "sg:city":"Bonheiden (rijmenam)",
    "sg:classifiers":[
        {
            "category":"Building & Trades",
            "subcategory":"Construction",
            "type":"Services"
        }
    ],
    "sg:phone":"+32 15 51 53 31",
    "sg:postcode":"2820",
    "sg:province":"Antwerpen",
    "sg:tags":[
        "stucco",
        "contractor"
    ],
    "wof:name":"Geets M",
    "wof:placetype":"venue"
},
  "geometry": {"coordinates":[4.5496602058,51.0218009949],"type":"Point"}
}