{
  "type": "Feature",
  "properties": {
    "iso:country":"BE",
    "sg:address":"Kerkskenhoek 51",
    "sg:city":"Haaltert",
    "sg:classifiers":[
        {
            "category":"Home & Garden",
            "subcategory":"Home Furnishings",
            "type":"Retail Goods"
        }
    ],
    "sg:phone":"+32 53 83 26 21",
    "sg:postcode":"9450",
    "sg:province":"Oost-Vlaanderen",
    "sg:tags":[
        "-",
        "bed",
        "mattress"
    ],
    "wof:name":"Lucas Meubelen",
    "wof:placetype":"venue"
},
  "geometry": {"coordinates":[3.995732069,50.8926200867],"type":"Point"}
}