{
  "type": "Feature",
  "properties": {
    "iso:country":"BE",
    "sg:address":"Rue Des Coteaux 331",
    "sg:city":"Bruxelles",
    "sg:orig_category":"Jardinage",
    "sg:phone":"+32 2 215 12 26",
    "sg:postcode":"1030",
    "sg:province":"Bruxelles-Capitale",
    "wof:name":"Egtj.",
    "wof:placetype":"venue"
},
  "geometry": {"coordinates":[4.3793988228,50.8626213074],"type":"Point"}
}