{
  "type": "Feature",
  "properties": {
    "iso:country":"BE",
    "sg:address":"Franklin Rooseveltlaan 93",
    "sg:city":"Vilvoorde",
    "sg:orig_category":"Kapsalons",
    "sg:phone":"+32 2 252 08 23",
    "sg:postcode":"1800",
    "sg:province":"Vlaams-Brabant",
    "wof:name":"Paulette",
    "wof:placetype":"venue"
},
  "geometry": {"coordinates":[4.4270758629,50.929901123],"type":"Point"}
}