{
  "type": "Feature",
  "properties": {
    "addr:full":"Chaus\u00c9e D'ath 242 Edingen Hainaut 7850",
    "addr:housenumber":"242",
    "addr:postcode":"7850",
    "addr:street":"Chause\u0301E D'Ath",
    "iso:country":"BE",
    "sg:address":"Chaus\u00c9e D'ath 242",
    "sg:city":"Edingen",
    "sg:orig_category":"Software ontwikkeling and ontwerp",
    "sg:phone":"+32 2 397 02 12",
    "sg:postcode":"7850",
    "sg:province":"Hainaut",
    "wof:name":"Neosys",
    "wof:placetype":"venue"
},
  "geometry": {"coordinates":[3.9902288914,50.6814041138],"type":"Point"}
}