{
  "type": "Feature",
  "properties": {
    "iso:country":"BE",
    "sg:address":"Weg Naar Ellikom 201",
    "sg:city":"Meeuwen-gruitrode",
    "sg:orig_category":"Paramedische behandelingen",
    "sg:phone":"+32 11 63 40 07",
    "sg:postcode":"3670",
    "sg:province":"Limburg",
    "wof:name":"M. Bloemen",
    "wof:placetype":"venue"
},
  "geometry": {"coordinates":[5.5212798119,51.117149353],"type":"Point"}
}