{
  "type": "Feature",
  "properties": {
    "addr:full":"Rue Albert Ier 121 Farciennes Hainaut 6240",
    "addr:housenumber":"121",
    "addr:postcode":"6240",
    "addr:street":"Rue Albert Ier",
    "iso:country":"BE",
    "sg:address":"Rue Albert Ier 121",
    "sg:city":"Farciennes",
    "sg:orig_category":"Charpentes and couvertures",
    "sg:phone":"+32 71 38 81 59",
    "sg:postcode":"6240",
    "sg:province":"Hainaut",
    "wof:name":"Beppino Biasizzo",
    "wof:placetype":"venue"
},
  "geometry": {"coordinates":[4.5408849716,50.4245948792],"type":"Point"}
}