{
  "type": "Feature",
  "properties": {
    "iso:country":"BE",
    "sg:address":"Bourgognestraat 7",
    "sg:city":"Zonnebeke",
    "sg:orig_category":"Eleveurs and marchands de porcs",
    "sg:phone":"+32 57 46 72 70",
    "sg:postcode":"8980",
    "sg:province":"West-Vlaanderen",
    "wof:name":"Michel Dewitte",
    "wof:placetype":"venue"
},
  "geometry": {"coordinates":[2.9592859745,50.8670272827],"type":"Point"}
}