{
  "type": "Feature",
  "properties": {
    "addr:full":"Rue Dautzenberg 64 Bruxelles (ixelles) Bruxelles-Capitale 1050",
    "addr:housenumber":"64",
    "addr:postcode":"1050",
    "addr:street":"Rue Dautzenberg",
    "iso:country":"BE",
    "sg:address":"Rue Dautzenberg 64",
    "sg:city":"Bruxelles (ixelles)",
    "sg:classifiers":[
        {
            "category":"Health Services",
            "subcategory":"Doctor",
            "type":"Services"
        }
    ],
    "sg:phone":"+32 2 646 33 13",
    "sg:postcode":"1050",
    "sg:province":"Bruxelles-Capitale",
    "sg:tags":[
        "medicinephysicians",
        "surgeon"
    ],
    "wof:name":"Golstein M-a",
    "wof:placetype":"venue"
},
  "geometry": {"coordinates":[4.367169857,50.8263511658],"type":"Point"}
}