{
  "type": "Feature",
  "properties": {
    "iso:country":"BE",
    "sg:address":"Bosstraat 67",
    "sg:city":"Maaseik",
    "sg:orig_category":"Cr\u00e9dits divers",
    "sg:postcode":"3680",
    "sg:province":"Limburg",
    "wof:name":"Bancontact-mister Cash",
    "wof:placetype":"venue"
},
  "geometry": {"coordinates":[5.7877178192,51.0955619812],"type":"Point"}
}