{
  "type": "Feature",
  "properties": {
    "addr:full":"Torhoutsesteenweg 124 Zedelgem West-Vlaanderen 8210",
    "addr:housenumber":"124",
    "addr:postcode":"8210",
    "addr:street":"Torhoutsesteenweg",
    "iso:country":"BE",
    "sg:address":"Torhoutsesteenweg 124",
    "sg:city":"Zedelgem",
    "sg:orig_category":"Banques and organismes de cr\u00e9dit",
    "sg:phone":"+32 50 20 14 06",
    "sg:postcode":"8210",
    "sg:province":"West-Vlaanderen",
    "wof:name":"Bank Van Roeselare",
    "wof:placetype":"venue"
},
  "geometry": {"coordinates":[3.1576468945,51.1365127563],"type":"Point"}
}