{
  "type": "Feature",
  "properties": {
    "addr:full":"Chauss\u00e9e De Renaix 23 Mont-de-l'enclus (russeignies) Hainaut 7750",
    "addr:housenumber":"23",
    "addr:postcode":"7750",
    "addr:street":"Chausse\u0301E De Renaix;Russeignies Hainaut",
    "iso:country":"BE",
    "sg:address":"Chauss\u00e9e De Renaix 23",
    "sg:city":"Mont-de-l'enclus (russeignies)",
    "sg:classifiers":[
        {
            "category":"Retail",
            "subcategory":"Auto Repair",
            "type":"Services"
        }
    ],
    "sg:phone":"+32 69 76 86 99",
    "sg:postcode":"7750",
    "sg:province":"Hainaut",
    "sg:tags":[
        "automobile-body"
    ],
    "wof:name":"Dewolf Cl",
    "wof:placetype":"venue"
},
  "geometry": {"coordinates":[4.9165067673,50.3185577393],"type":"Point"}
}