{
  "type": "Feature",
  "properties": {
    "addr:full":"Andre Dumontlaan 139 Genk Limburg 3600",
    "addr:housenumber":"139",
    "addr:postcode":"3600",
    "addr:street":"Dumontlaan",
    "iso:country":"BE",
    "sg:address":"Andre Dumontlaan 139",
    "sg:city":"Genk",
    "sg:orig_category":"Benzinestations and brandstoffen",
    "sg:phone":"+32 89 38 14 91",
    "sg:postcode":"3600",
    "sg:province":"Limburg",
    "wof:name":"Garage Gullo",
    "wof:placetype":"venue"
},
  "geometry": {"coordinates":[5.5330581665,50.99376297],"type":"Point"}
}