{
  "type": "Feature",
  "properties": {
    "addr:full":"Bieststraat 284 Boortmeerbeek Vlaams-Brabant 3191",
    "addr:housenumber":"284",
    "addr:postcode":"3191",
    "addr:street":"Bieststraat",
    "iso:country":"BE",
    "sg:address":"Bieststraat 284",
    "sg:city":"Boortmeerbeek",
    "sg:orig_category":"Boucheries",
    "sg:phone":"+32 15 61 11 90",
    "sg:postcode":"3191",
    "sg:province":"Vlaams-Brabant",
    "wof:name":"Bruynseels",
    "wof:placetype":"venue"
},
  "geometry": {"coordinates":[4.5490899086,50.9831085205],"type":"Point"}
}