{
  "type": "Feature",
  "properties": {
    "addr:full":"Botermelkstraat 32 Erpe-mere (erpe) Oost-Vlaanderen 9420",
    "addr:housenumber":"32",
    "addr:postcode":"9420",
    "addr:street":"Botermelkstraat",
    "iso:country":"BE",
    "sg:address":"Botermelkstraat 32",
    "sg:city":"Erpe-mere (erpe)",
    "sg:classifiers":[
        {
            "category":"Building & Trades",
            "subcategory":"Equipment Rental",
            "type":"Services"
        }
    ],
    "sg:phone":"+32 53 82 80 80",
    "sg:postcode":"9420",
    "sg:province":"Oost-Vlaanderen",
    "sg:tags":[
        "lighting",
        "-",
        "fixture"
    ],
    "wof:name":"K-light",
    "wof:placetype":"venue"
},
  "geometry": {"coordinates":[3.9869759083,50.9426956177],"type":"Point"}
}