{
  "type": "Feature",
  "properties": {
    "iso:country":"BE",
    "sg:address":"Donkweg 77",
    "sg:city":"Essen",
    "sg:classifiers":[
        {
            "category":"Shopping",
            "subcategory":"Florist",
            "type":"Retail Goods"
        }
    ],
    "sg:phone":"+32 3 667 70 98",
    "sg:postcode":"2910",
    "sg:province":"Antwerpen",
    "wof:name":"Den Donk",
    "wof:placetype":"venue"
},
  "geometry": {"coordinates":[4.4565258026,51.4488220215],"type":"Point"}
}