{
  "type": "Feature",
  "properties": {
    "iso:country":"BE",
    "sg:address":"Bergbosstraat 193",
    "sg:city":"Merelbeke",
    "sg:classifiers":[
        {
            "category":"Wholesale",
            "subcategory":"Plants",
            "type":"Manufacturing & Wholesale Goods"
        }
    ],
    "sg:phone":"+32 9 230 70 97",
    "sg:postcode":"9820",
    "sg:province":"Oost-Vlaanderen",
    "sg:tags":[
        "whol",
        "flower",
        "-",
        "grower"
    ],
    "wof:name":"Van Den Meersschaut C",
    "wof:placetype":"venue"
},
  "geometry": {"coordinates":[3.731306076,50.9823455811],"type":"Point"}
}