{
  "type": "Feature",
  "properties": {
    "addr:full":"Berkenstraat 83 Houthalen-helchteren (houthalen) Limburg 3530",
    "addr:housenumber":"83",
    "addr:postcode":"3530",
    "addr:street":"Berkenstraat",
    "iso:country":"BE",
    "sg:address":"Berkenstraat 83",
    "sg:city":"Houthalen-helchteren (houthalen)",
    "sg:classifiers":[
        {
            "category":"Professional",
            "subcategory":"Management & Consulting",
            "type":"Services"
        }
    ],
    "sg:phone":"+32 89 24 01 83",
    "sg:postcode":"3530",
    "sg:province":"Limburg",
    "sg:tags":[
        "consultant",
        "law"
    ],
    "wof:name":"Claessens L",
    "wof:placetype":"venue"
},
  "geometry": {"coordinates":[5.4710259438,51.029964447],"type":"Point"}
}