{
  "type": "Feature",
  "properties": {
    "iso:country":"BE",
    "sg:address":"Rue Marie De Bourgogne 30",
    "sg:city":"Bruxelles",
    "sg:classifiers":[
        {
            "category":"Government",
            "subcategory":"Embassy",
            "type":"Public Place"
        }
    ],
    "sg:phone":"+32 2 513 66 10",
    "sg:postcode":"1000",
    "sg:province":"Bruxelles-Capitale",
    "sg:tags":[
        "consulate"
    ],
    "wof:name":"R\u00e9publique D\u00e9mocratique Du Congo (ambassade De La)",
    "wof:placetype":"venue"
},
  "geometry": {"coordinates":[4.371254921,50.840423584],"type":"Point"}
}