{
  "type": "Feature",
  "properties": {
    "iso:country":"BE",
    "sg:address":"Chauss\u00c9e De Li\u00c8ge 137",
    "sg:city":"Hamois",
    "sg:orig_category":"Herstellingen and onderhoud van auto's Voertuigen",
    "sg:phone":"+32 83 61 28 93",
    "sg:postcode":"5360",
    "sg:province":"Namur",
    "wof:name":"A.b. Motors",
    "wof:placetype":"venue"
},
  "geometry": {"coordinates":[5.1729221344,50.3566856384],"type":"Point"}
}