{
  "type": "Feature",
  "properties": {
    "iso:country":"BE",
    "sg:address":"Gebr. Van Raemdonckstr. 25",
    "sg:city":"Nijlen",
    "sg:orig_category":"Boissons",
    "sg:phone":"+32 3 481 86 98",
    "sg:postcode":"2560",
    "sg:province":"Antwerpen",
    "wof:name":"Fa. Cambre",
    "wof:placetype":"venue"
},
  "geometry": {"coordinates":[4.6671757698,51.1646080017],"type":"Point"}
}