{
  "type": "Feature",
  "properties": {
    "addr:full":"Stormestraat 121 Waregem West-Vlaanderen 8790",
    "addr:housenumber":"121",
    "addr:postcode":"8790",
    "addr:street":"Stormestraat",
    "iso:country":"BE",
    "sg:address":"Stormestraat 121",
    "sg:city":"Waregem",
    "sg:orig_category":"Kapsalons",
    "sg:phone":"+32 56 60 44 24",
    "sg:postcode":"8790",
    "sg:province":"West-Vlaanderen",
    "wof:name":"Coiffure Figaro",
    "wof:placetype":"venue"
},
  "geometry": {"coordinates":[3.4272809029,50.8848953247],"type":"Point"}
}