{
  "type": "Feature",
  "properties": {
    "iso:country":"BE",
    "sg:address":"Rue Du Chateau D\u00b4ab\u00c9e 37",
    "sg:city":"Tinlot",
    "sg:orig_category":"Ruimtes voor conferenties, recepties and feesten",
    "sg:phone":"+32 85 51 11 84",
    "sg:postcode":"4557",
    "sg:province":"Li\u00e8ge",
    "wof:name":"Le Grenier",
    "wof:placetype":"venue"
},
  "geometry": {"coordinates":[5.3639497757,50.4769172668],"type":"Point"}
}