{
  "type": "Feature",
  "properties": {
    "iso:country":"BE",
    "sg:address":"Rue Reine Astrid 32",
    "sg:city":"Welkenraedt/welkenraedt",
    "sg:orig_category":"Plomberie, chauffage and installations sanitaires",
    "sg:phone":"+32 87 88 10 87",
    "sg:postcode":"4840",
    "sg:province":"Li\u00e8ge",
    "wof:name":"Eugene Poensgen",
    "wof:placetype":"venue"
},
  "geometry": {"coordinates":[5.9796700478,50.6616210938],"type":"Point"}
}