{
  "type": "Feature",
  "properties": {
    "iso:country":"BE",
    "sg:address":"Bergstraat 8ba",
    "sg:city":"Koekelare",
    "sg:orig_category":"Rundveehouders",
    "sg:phone":"+32 51 58 86 95",
    "sg:postcode":"8680",
    "sg:province":"West-Vlaanderen",
    "wof:name":"Erik Logghe",
    "wof:placetype":"venue"
},
  "geometry": {"coordinates":[3.008865118,51.0761871338],"type":"Point"}
}