{
  "type": "Feature",
  "properties": {
    "iso:country":"BE",
    "sg:address":"Rue Fontaine 92",
    "sg:city":"Walcourt",
    "sg:orig_category":"Kapsalons",
    "sg:phone":"+32 71 65 52 26",
    "sg:postcode":"5650",
    "sg:province":"Namur",
    "wof:name":"Renee Devos",
    "wof:placetype":"venue"
},
  "geometry": {"coordinates":[4.4313349724,50.2514762878],"type":"Point"}
}