{
  "type": "Feature",
  "properties": {
    "addr:full":"Stichelen 68 Haaltert Oost-Vlaanderen 9450",
    "addr:housenumber":"68",
    "addr:postcode":"9450",
    "addr:street":"Stichelen",
    "iso:country":"BE",
    "sg:address":"Stichelen 68",
    "sg:city":"Haaltert",
    "sg:orig_category":"D\u00e9corateurs d'int\u00e9rieur",
    "sg:phone":"+32 53 83 58 51",
    "sg:postcode":"9450",
    "sg:province":"Oost-Vlaanderen",
    "wof:name":"Bart Bogaert",
    "wof:placetype":"venue"
},
  "geometry": {"coordinates":[4.0016298294,50.8833503723],"type":"Point"}
}