{
  "type": "Feature",
  "properties": {
    "addr:full":"Rue Babotterie 87 Charleroi Hainaut 6001",
    "addr:housenumber":"87",
    "addr:postcode":"6001",
    "addr:street":"Rue Babotterie;Hainaut",
    "iso:country":"BE",
    "sg:address":"Rue Babotterie 87",
    "sg:city":"Charleroi",
    "sg:orig_category":"Artsen and specialisten",
    "sg:phone":"+32 71 31 73 48",
    "sg:postcode":"6001",
    "sg:province":"Hainaut",
    "wof:name":"Moulaert",
    "wof:placetype":"venue"
},
  "geometry": {"coordinates":[4.4485287666,50.3902053833],"type":"Point"}
}