{
  "type": "Feature",
  "properties": {
    "addr:full":"Rue Arthur Defoin 203 Dinant Namur 5500",
    "addr:housenumber":"203",
    "addr:postcode":"5500",
    "addr:street":"Rue Arthur Defoin",
    "iso:country":"BE",
    "sg:address":"Rue Arthur Defoin 203",
    "sg:city":"Dinant",
    "sg:classifiers":[
        {
            "category":"Home & Garden",
            "subcategory":"Household Appliances",
            "type":"Retail Goods"
        }
    ],
    "sg:phone":"+32 82 22 54 17",
    "sg:postcode":"5500",
    "sg:province":"Namur",
    "sg:tags":[
        "heating",
        "apparatus"
    ],
    "wof:name":"Louis F",
    "wof:placetype":"venue"
},
  "geometry": {"coordinates":[4.9211401939,50.2453613281],"type":"Point"}
}