{
  "type": "Feature",
  "properties": {
    "iso:country":"BE",
    "sg:address":"Voie De Li\u00e8ge 2",
    "sg:city":"Chaudfontaine (embourg)",
    "sg:classifiers":[
        {
            "category":"Professional",
            "subcategory":"Management & Consulting",
            "type":"Services"
        }
    ],
    "sg:phone":"+32 4 361 64 64",
    "sg:postcode":"4053",
    "sg:province":"Li\u00e8ge",
    "sg:tags":[
        "consultant",
        "agency",
        "advertising"
    ],
    "wof:name":"T\u00e9l\u00e9scope",
    "wof:placetype":"venue"
},
  "geometry": {"coordinates":[5.6148338318,50.599357605],"type":"Point"}
}