{
  "type": "Feature",
  "properties": {
    "iso:country":"BE",
    "sg:address":"All\u00e9e Du Jaquemart 4 Box 21",
    "sg:city":"Nivelles",
    "sg:classifiers":[
        {
            "category":"Professional",
            "subcategory":"Engineering",
            "type":"Services"
        }
    ],
    "sg:phone":"+32 67 89 49 24",
    "sg:postcode":"1400",
    "sg:province":"Brabant Wallon",
    "sg:tags":[
        "-"
    ],
    "wof:name":"Stmb Project Sprl",
    "wof:placetype":"venue"
},
  "geometry": {"coordinates":[4.3376059532,50.5927658081],"type":"Point"}
}