{
  "type": "Feature",
  "properties": {
    "iso:country":"BE",
    "sg:address":"Rue Evrard-tricot 1ba",
    "sg:city":"Nivelles",
    "sg:classifiers":[
        {
            "category":"Insurance",
            "subcategory":"Life Insurance",
            "type":"Services"
        }
    ],
    "sg:phone":"+32 67 21 83 37",
    "sg:postcode":"1404",
    "sg:province":"Brabant Wallon",
    "sg:tags":[
        "assurance"
    ],
    "wof:name":"J.m. Haegeman",
    "wof:placetype":"venue"
},
  "geometry": {"coordinates":[4.2663431168,50.6050605774],"type":"Point"}
}