{
  "type": "Feature",
  "properties": {
    "iso:country":"BE",
    "sg:address":"Dynastiestraat 29",
    "sg:city":"Menen",
    "sg:classifiers":[
        {
            "category":"Arena",
            "subcategory":"Sports Club",
            "type":"Entertainment"
        }
    ],
    "sg:phone":"+32 56 51 53 13",
    "sg:postcode":"8930",
    "sg:province":"West-Vlaanderen",
    "sg:tags":[
        "de"
    ],
    "wof:name":"'t Vooruitzicht",
    "wof:placetype":"venue"
},
  "geometry": {"coordinates":[3.1321721077,50.7898826599],"type":"Point"}
}