{
  "type": "Feature",
  "properties": {
    "addr:full":"Luikersteenweg 234 Sint-truiden Limburg 3800",
    "addr:housenumber":"234",
    "addr:postcode":"sint-truiden;3800",
    "addr:street":"Luikersteenweg",
    "iso:country":"BE",
    "sg:address":"Luikersteenweg 234",
    "sg:city":"Sint-truiden",
    "sg:classifiers":[
        {
            "category":"Shopping",
            "subcategory":"Gifts & Souvenirs",
            "type":"Retail Goods"
        }
    ],
    "sg:phone":"+32 11 68 61 36",
    "sg:postcode":"3800",
    "sg:province":"Limburg",
    "sg:tags":[
        "-"
    ],
    "wof:name":"Brocatel",
    "wof:placetype":"venue"
},
  "geometry": {"coordinates":[5.2029700279,50.8036193848],"type":"Point"}
}