{
  "type": "Feature",
  "properties": {
    "iso:country":"BE",
    "sg:address":"Haantjeslei 157",
    "sg:city":"Antwerpen",
    "sg:orig_category":"Artistes ind\u00e9pendants",
    "sg:phone":"+32 3 238 61 87",
    "sg:postcode":"2018",
    "sg:province":"Antwerpen",
    "wof:name":"Blommaert",
    "wof:placetype":"venue"
},
  "geometry": {"coordinates":[4.4033770561,51.2017326355],"type":"Point"}
}