{
  "type": "Feature",
  "properties": {
    "addr:full":"Sint-jobstraat 42 Antwerpen Antwerpen 2060",
    "addr:housenumber":"42",
    "addr:postcode":"2060",
    "addr:street":"Sint-Jobstraat",
    "iso:country":"BE",
    "sg:address":"Sint-jobstraat 42",
    "sg:city":"Antwerpen",
    "sg:classifiers":[
        {
            "category":"Building & Trades",
            "subcategory":"Pest Control",
            "type":"Services"
        }
    ],
    "sg:phone":"+32 3 213 36 90",
    "sg:postcode":"2060",
    "sg:province":"Antwerpen",
    "sg:tags":[
        "painting",
        "contractor"
    ],
    "wof:name":"Akay Nv",
    "wof:placetype":"venue"
},
  "geometry": {"coordinates":[4.4233651161,51.2287406921],"type":"Point"}
}