{
  "type": "Feature",
  "properties": {
    "iso:country":"BE",
    "sg:address":"Ruddervoordestraat 30",
    "sg:city":"Wingene (zwevezele)",
    "sg:classifiers":[
        {
            "category":"Home & Garden",
            "subcategory":"Building Materials",
            "type":"Retail Goods"
        }
    ],
    "sg:phone":"+32 51 61 11 18",
    "sg:postcode":"8750",
    "sg:province":"West-Vlaanderen",
    "sg:tags":[
        "cutting",
        "laser",
        "welding"
    ],
    "wof:name":"De Vos Plaatbewerking",
    "wof:placetype":"venue"
},
  "geometry": {"coordinates":[3.2073750496,51.0522727966],"type":"Point"}
}