{
  "type": "Feature",
  "properties": {
    "iso:country":"BE",
    "sg:address":"Rue Grand'ry Wegnez 60",
    "sg:city":"Pepinster (wegnez)",
    "sg:classifiers":[
        {
            "category":"Building & Trades",
            "subcategory":"Plumbing",
            "type":"Services"
        }
    ],
    "sg:phone":"+32 87 34 11 60",
    "sg:postcode":"4860",
    "sg:province":"Li\u00e8ge",
    "sg:tags":[
        "contractor"
    ],
    "wof:name":"Lenz G Sprl",
    "wof:placetype":"venue"
},
  "geometry": {"coordinates":[5.8023428917,50.5637588501],"type":"Point"}
}