{
  "type": "Feature",
  "properties": {
    "iso:country":"BE",
    "sg:address":"L\u00e9on Schreursvest 67",
    "sg:city":"Leuven (heverlee)",
    "sg:classifiers":[
        {
            "category":"Recreation",
            "subcategory":"Boat Charter",
            "type":"Entertainment"
        }
    ],
    "sg:phone":"+32 16 29 19 91",
    "sg:postcode":"3001",
    "sg:province":"Vlaams-Brabant",
    "sg:tags":[
        "-",
        "builder",
        "yacht",
        "pleasure"
    ],
    "wof:name":"Trimax Trimaran Yachts",
    "wof:placetype":"venue"
},
  "geometry": {"coordinates":[4.7127609253,50.8714561462],"type":"Point"}
}