{
  "type": "Feature",
  "properties": {
    "iso:country":"BE",
    "sg:address":"Ed. Schelfhoutstraat 181",
    "sg:city":"Liedekerke",
    "sg:classifiers":[
        {
            "category":"Freight",
            "type":"Transportation"
        }
    ],
    "sg:phone":"+32 53 66 64 60",
    "sg:postcode":"1770",
    "sg:province":"Vlaams-Brabant",
    "sg:tags":[
        "-",
        "transport"
    ],
    "wof:name":"Transport Hubert",
    "wof:placetype":"venue"
},
  "geometry": {"coordinates":[4.1062531471,50.8636245728],"type":"Point"}
}