{
  "type": "Feature",
  "properties": {
    "addr:full":"Ridderstraat 12 Dendermonde Oost-Vlaanderen 9200",
    "addr:housenumber":"12",
    "addr:postcode":"9200",
    "addr:street":"Ridderstraat;Oost-Vlaanderen",
    "iso:country":"BE",
    "sg:address":"Ridderstraat 12",
    "sg:city":"Dendermonde",
    "sg:classifiers":[
        {
            "category":"Cinema",
            "subcategory":"Movie Rental",
            "type":"Entertainment"
        }
    ],
    "sg:phone":"+32 52 22 57 93",
    "sg:postcode":"9200",
    "sg:province":"Oost-Vlaanderen",
    "sg:tags":[
        "de",
        "cassette",
        "location",
        "vid\u00e9o",
        "audio"
    ],
    "wof:name":"Movie Max",
    "wof:placetype":"venue"
},
  "geometry": {"coordinates":[4.0982460976,51.0306243896],"type":"Point"}
}