{
  "type": "Feature",
  "properties": {
    "iso:country":"BE",
    "sg:address":"Boulevard Des Anglais 282",
    "sg:city":"Ronse/renaix",
    "sg:classifiers":[
        {
            "category":"Personal",
            "subcategory":"Beauty Salon",
            "type":"Services"
        }
    ],
    "sg:phone":"+32 55 21 02 12",
    "sg:postcode":"9600",
    "sg:province":"Oost-Vlaanderen",
    "sg:tags":[
        "de",
        "coiffure"
    ],
    "wof:name":"Kapsalon Ann",
    "wof:placetype":"venue"
},
  "geometry": {"coordinates":[3.5780661106,50.7414207458],"type":"Point"}
}