{
  "type": "Feature",
  "properties": {
    "iso:country":"BE",
    "sg:address":"Schuiferskapelsesteenweg 69",
    "sg:city":"Tielt",
    "sg:orig_category":"Non-Classified Establishments",
    "sg:phone":"+32 51 40 54 39",
    "sg:postcode":"8700",
    "sg:province":"West-Vlaanderen",
    "wof:name":"Verhulst F",
    "wof:placetype":"venue"
},
  "geometry": {"coordinates":[3.3369469643,51.0231742859],"type":"Point"}
}