{
  "type": "Feature",
  "properties": {
    "addr:full":"Kapucijnenplein 1 Lommel Limburg 3920",
    "addr:housenumber":"1",
    "addr:postcode":"3920",
    "addr:street":"Kapucijnenplein",
    "iso:country":"BE",
    "sg:address":"Kapucijnenplein 1",
    "sg:city":"Lommel",
    "sg:classifiers":[
        {
            "category":"Home & Garden",
            "subcategory":"Building Materials",
            "type":"Retail Goods"
        }
    ],
    "sg:phone":"+32 11 55 34 71",
    "sg:postcode":"3920",
    "sg:province":"Limburg",
    "sg:tags":[
        "window"
    ],
    "wof:name":"Euroraam Alvera",
    "wof:placetype":"venue"
},
  "geometry": {"coordinates":[5.261341095,51.2208633423],"type":"Point"}
}