{
  "type": "Feature",
  "properties": {
    "iso:country":"BE",
    "sg:address":"Koningin Astridlaan 21a",
    "sg:city":"Bredene",
    "sg:classifiers":[
        {
            "category":"Farming",
            "subcategory":"Fish & Marine Products",
            "type":"Manufacturing & Wholesale Goods"
        }
    ],
    "sg:phone":"+32 59 33 35 15",
    "sg:postcode":"8450",
    "sg:province":"West-Vlaanderen",
    "sg:tags":[
        "retail",
        "-",
        "shellfish"
    ],
    "wof:name":"Florida",
    "wof:placetype":"venue"
},
  "geometry": {"coordinates":[2.9706039429,51.2499389648],"type":"Point"}
}