{
  "type": "Feature",
  "properties": {
    "iso:country":"BE",
    "sg:address":"Rue De L'aire 4",
    "sg:city":"Soignies (horrues)",
    "sg:classifiers":[
        {
            "category":"Insurance",
            "subcategory":"Insurance Agent",
            "type":"Services"
        }
    ],
    "sg:phone":"+32 67 33 96 34",
    "sg:postcode":"7060",
    "sg:province":"Hainaut",
    "sg:tags":[
        "broker"
    ],
    "wof:name":"S.n.c.i.",
    "wof:placetype":"venue"
},
  "geometry": {"coordinates":[4.0447301865,50.6089096069],"type":"Point"}
}