{
  "type": "Feature",
  "properties": {
    "addr:full":"Quai L\u00c9on Monnoyer 11 Brussel/bruxelles Bruxelles-Capitale 1000",
    "addr:housenumber":"11",
    "addr:postcode":"1000",
    "addr:street":"Quai Le\u0301On Monnoyer;/",
    "iso:country":"BE",
    "sg:address":"Quai L\u00c9on Monnoyer 11",
    "sg:city":"Brussel/bruxelles",
    "sg:orig_category":"Agences d'exp\u00e9dition",
    "sg:phone":"+32 2 216 37 03",
    "sg:postcode":"1000",
    "sg:province":"Bruxelles-Capitale",
    "wof:name":"Fe. Ideal Freight",
    "wof:placetype":"venue"
},
  "geometry": {"coordinates":[4.3513898849,50.8584594727],"type":"Point"}
}