{
  "type": "Feature",
  "properties": {
    "iso:country":"BE",
    "sg:address":"Rooiaarde 51",
    "sg:city":"Meerhout",
    "sg:orig_category":"Rundveehouders",
    "sg:phone":"+32 14 30 91 11",
    "sg:postcode":"2450",
    "sg:province":"Antwerpen",
    "wof:name":"Herman Beerten",
    "wof:placetype":"venue"
},
  "geometry": {"coordinates":[5.0983610153,51.1337051392],"type":"Point"}
}