{
  "type": "Feature",
  "properties": {
    "addr:full":"Chauss\u00e9e D'ypres 23 Comines-warneton (warneton) Hainaut 7784",
    "addr:housenumber":"23",
    "addr:postcode":"7784",
    "addr:street":"Chausse\u0301E D'Ypres",
    "iso:country":"BE",
    "sg:address":"Chauss\u00e9e D'ypres 23",
    "sg:city":"Comines-warneton (warneton)",
    "sg:classifiers":[
        {
            "category":"Home & Garden",
            "subcategory":"Garden Supply",
            "type":"Retail Goods"
        }
    ],
    "sg:phone":"+32 56 55 51 95",
    "sg:postcode":"7784",
    "sg:province":"Hainaut",
    "sg:tags":[
        "machine",
        "agricultural",
        "-"
    ],
    "wof:name":"Gillebert F",
    "wof:placetype":"venue"
},
  "geometry": {"coordinates":[2.9480700493,50.7536430359],"type":"Point"}
}