{
  "type": "Feature",
  "properties": {
    "iso:country":"BE",
    "sg:address":"Chauss\u00c9e De Louvain 382",
    "sg:city":"Namur",
    "sg:orig_category":"Pain, p\u00e2tisseries and confiseries",
    "sg:phone":"+32 81 21 40 54",
    "sg:postcode":"5004",
    "sg:province":"Namur",
    "wof:name":"P\u00c2tisserie Jacques Rouard",
    "wof:placetype":"venue"
},
  "geometry": {"coordinates":[4.8825011253,50.4805450439],"type":"Point"}
}