{
  "type": "Feature",
  "properties": {
    "iso:country":"BE",
    "sg:address":"Rue Villa Romaine 23",
    "sg:city":"Houffalize",
    "sg:orig_category":"Pain, p\u00e2tisseries and confiseries",
    "sg:phone":"+32 84 44 41 03",
    "sg:postcode":"6660",
    "sg:province":"Luxembourg",
    "wof:name":"Francis Thoumsin",
    "wof:placetype":"venue"
},
  "geometry": {"coordinates":[5.6805391312,50.1617584229],"type":"Point"}
}