{
  "type": "Feature",
  "properties": {
    "addr:full":"Waterloopstraat 3 Turnhout Antwerpen 2300",
    "addr:housenumber":"3",
    "addr:postcode":"2300",
    "addr:street":"Waterloopstraat",
    "iso:country":"BE",
    "sg:address":"Waterloopstraat 3",
    "sg:city":"Turnhout",
    "sg:classifiers":[
        {
            "category":"Building & Trades",
            "subcategory":"Pest Control",
            "type":"Services"
        }
    ],
    "sg:phone":"+32 14 43 78 47",
    "sg:postcode":"2300",
    "sg:province":"Antwerpen",
    "sg:tags":[
        "painting",
        "contractor"
    ],
    "wof:name":"Gevers P",
    "wof:placetype":"venue"
},
  "geometry": {"coordinates":[4.9314370155,51.3300361633],"type":"Point"}
}