{
  "type": "Feature",
  "properties": {
    "addr:full":"Chauss\u00c9e De Bascoup 222 Anderlues Hainaut 6150",
    "addr:housenumber":"222",
    "addr:postcode":"6150",
    "addr:street":"Chausse\u0301E De Bascoup",
    "iso:country":"BE",
    "sg:address":"Chauss\u00c9e De Bascoup 222",
    "sg:city":"Anderlues",
    "sg:orig_category":"Equipement photographique. Studios photographiques",
    "sg:phone":"+32 71 52 86 42",
    "sg:postcode":"6150",
    "sg:province":"Hainaut",
    "wof:name":"Joelle Oostens",
    "wof:placetype":"venue"
},
  "geometry": {"coordinates":[4.2813429832,50.426071167],"type":"Point"}
}