{
  "type": "Feature",
  "properties": {
    "iso:country":"BE",
    "sg:address":"Rue La Belle-jardini\u00c8re 501b1",
    "sg:city":"Li\u00c8ge",
    "sg:classifiers":[
        {
            "category":"Arena",
            "subcategory":"Sports Club",
            "type":"Entertainment"
        }
    ],
    "sg:phone":"+32 4 366 19 78",
    "sg:postcode":"4031",
    "sg:province":"Li\u00e8ge",
    "sg:tags":[
        "terrain",
        "hors",
        "de",
        "installation",
        "sportifs"
    ],
    "wof:name":"F.c. Boliden Cuivre Zinc",
    "wof:placetype":"venue"
},
  "geometry": {"coordinates":[5.5782899857,50.5935516357],"type":"Point"}
}