{
  "type": "Feature",
  "properties": {
    "iso:country":"BE",
    "sg:address":"Dorpsstraat 145",
    "sg:city":"Damme",
    "sg:orig_category":"Sportclubs",
    "sg:phone":"+32 50 35 29 27",
    "sg:postcode":"8340",
    "sg:province":"West-Vlaanderen",
    "wof:name":"T.c. Damme",
    "wof:placetype":"venue"
},
  "geometry": {"coordinates":[3.3196370602,51.2019844055],"type":"Point"}
}