{
  "type": "Feature",
  "properties": {
    "addr:full":"Rue Valduc 297 Bruxelles (auderghem) Bruxelles-Capitale 1160",
    "addr:housenumber":"297",
    "addr:postcode":"1160",
    "addr:street":"Rue Valduc",
    "iso:country":"BE",
    "sg:address":"Rue Valduc 297",
    "sg:city":"Bruxelles (auderghem)",
    "sg:classifiers":[
        {
            "category":"Professional",
            "subcategory":"Advertising",
            "type":"Services"
        }
    ],
    "sg:phone":"+32 2 673 45 98",
    "sg:postcode":"1160",
    "sg:province":"Bruxelles-Capitale",
    "sg:tags":[
        "item",
        "-",
        "business",
        "gift",
        "promotional"
    ],
    "wof:name":"Vinalgros Sa",
    "wof:placetype":"venue"
},
  "geometry": {"coordinates":[4.4116902351,50.8208427429],"type":"Point"}
}