{
  "type": "Feature",
  "properties": {
    "iso:country":"BE",
    "sg:address":"Alsembergse Steenweg 986",
    "sg:city":"Ukkel/uccle",
    "sg:orig_category":"Drukkerijen and copyshops",
    "sg:phone":"+32 2 376 15 34",
    "sg:postcode":"1180",
    "sg:province":"Bruxelles-Capitale",
    "wof:name":"Imprim. Pinkers-graphic",
    "wof:placetype":"venue"
},
  "geometry": {"coordinates":[4.3332638741,50.7922515869],"type":"Point"}
}