{
  "type": "Feature",
  "properties": {
    "addr:full":"Keiweg 10 Brakel (zegelsem) Oost-Vlaanderen 9660",
    "addr:housenumber":"10",
    "addr:postcode":"9660",
    "addr:street":"Keiweg",
    "iso:country":"BE",
    "sg:address":"Keiweg 10",
    "sg:city":"Brakel (zegelsem)",
    "sg:classifiers":[
        {
            "category":"Real Estate",
            "subcategory":"Architect",
            "type":"Services"
        }
    ],
    "sg:phone":"+32 55 42 50 75",
    "sg:postcode":"9660",
    "sg:province":"Oost-Vlaanderen",
    "wof:name":"Matthys P",
    "wof:placetype":"venue"
},
  "geometry": {"coordinates":[3.7145800591,50.827796936],"type":"Point"}
}