{
  "type": "Feature",
  "properties": {
    "addr:full":"Avenue Hansen-soulie 8 Etterbeek/etterbeek Bruxelles-Capitale 1040",
    "addr:housenumber":"8",
    "addr:postcode":"1040",
    "addr:street":"Avenue Hansen-Soulie",
    "iso:country":"BE",
    "sg:address":"Avenue Hansen-soulie 8",
    "sg:city":"Etterbeek/etterbeek",
    "sg:orig_category":"Tabac. Librairies. Journaux",
    "sg:phone":"+32 2 735 29 39",
    "sg:postcode":"1040",
    "sg:province":"Bruxelles-Capitale",
    "wof:name":"Librairie Roi Chevalier",
    "wof:placetype":"venue"
},
  "geometry": {"coordinates":[4.3982620239,50.8318977356],"type":"Point"}
}