{
  "type": "Feature",
  "properties": {
    "addr:full":"Tennisbaanstraat 70 Gent Oost-Vlaanderen 9000",
    "addr:housenumber":"70",
    "addr:postcode":"9000",
    "addr:street":"Tennisbaanstraat;Oost-Vlaanderen",
    "iso:country":"BE",
    "sg:address":"Tennisbaanstraat 70",
    "sg:city":"Gent",
    "sg:classifiers":[
        {
            "category":"Shopping",
            "subcategory":"Gifts & Souvenirs",
            "type":"Retail Goods"
        }
    ],
    "sg:phone":"+32 9 222 56 26",
    "sg:postcode":"9000",
    "sg:province":"Oost-Vlaanderen",
    "sg:tags":[
        "-"
    ],
    "wof:name":"Ravenala",
    "wof:placetype":"venue"
},
  "geometry": {"coordinates":[3.7087841034,51.0418167114],"type":"Point"}
}