{
  "type": "Feature",
  "properties": {
    "addr:full":"Chemin Rue 38 Malm\u00c9dy Li\u00e8ge 4960",
    "addr:housenumber":"38",
    "addr:postcode":"4960",
    "addr:street":"Chemin Rue",
    "iso:country":"BE",
    "sg:address":"Chemin Rue 38",
    "sg:city":"Malm\u00c9dy",
    "sg:orig_category":"Centres de relaxation and bien-\u00eatre. V\u00eatements",
    "sg:phone":"+32 80 33 81 58",
    "sg:postcode":"4960",
    "sg:province":"Li\u00e8ge",
    "wof:name":"Blue White",
    "wof:placetype":"venue"
},
  "geometry": {"coordinates":[6.0266628265,50.4257659912],"type":"Point"}
}