{
  "type": "Feature",
  "properties": {
    "addr:full":"Rue Saint-gilles 180 Li\u00c8ge Li\u00e8ge 4000",
    "addr:housenumber":"180",
    "addr:postcode":"4000",
    "addr:street":"Rue Saint-Gilles",
    "iso:country":"BE",
    "sg:address":"Rue Saint-gilles 180",
    "sg:city":"Li\u00c8ge",
    "sg:classifiers":[
        {
            "category":"Cafe",
            "type":"Food & Drink"
        }
    ],
    "sg:phone":"+32 4 223 31 26",
    "sg:postcode":"4000",
    "sg:province":"Li\u00e8ge",
    "sg:tags":[
        "caf\u00e9s"
    ],
    "wof:name":"Caf\u00c9 Chez Guillaume",
    "wof:placetype":"venue"
},
  "geometry": {"coordinates":[5.5624771118,50.6379165649],"type":"Point"}
}