{
  "type": "Feature",
  "properties": {
    "iso:country":"BE",
    "sg:address":"Galerie Cora",
    "sg:city":"La Louviere",
    "sg:orig_category":"Herstelling horloges and juwelen Juwelen and horloges Swatch",
    "sg:phone":"+32 64 22 96 81",
    "sg:postcode":"7100",
    "sg:province":"Hainaut",
    "wof:name":"Soci\u00c9t\u00c9 Nouvelle De Bijouterie",
    "wof:placetype":"venue"
},
  "geometry": {"coordinates":[4.1850848198,50.4748649597],"type":"Point"}
}