{
  "type": "Feature",
  "properties": {
    "addr:full":"Hemelrijken 9 Sint-amands Antwerpen 2890",
    "addr:housenumber":"9",
    "addr:postcode":"2890",
    "addr:street":"Hemelrijken",
    "iso:country":"BE",
    "sg:address":"Hemelrijken 9",
    "sg:city":"Sint-amands",
    "sg:classifiers":[
        {
            "category":"Manufacturing",
            "subcategory":"Motor Vehicles & Parts",
            "type":"Manufacturing & Wholesale Goods"
        }
    ],
    "sg:phone":"+32 52 33 66 44",
    "sg:postcode":"2890",
    "sg:province":"Antwerpen",
    "sg:tags":[
        "body",
        "automobile",
        "construction",
        "-"
    ],
    "wof:name":"Carrosserie Leemans J.",
    "wof:placetype":"venue"
},
  "geometry": {"coordinates":[4.2158050537,51.0600776672],"type":"Point"}
}