{
  "type": "Feature",
  "properties": {
    "addr:full":"Rue Du Pr\u00e9sident Allende 43 Chapelle-lez-herlaimont (godarville) Hainaut 7160",
    "addr:housenumber":"43",
    "addr:postcode":"7160",
    "addr:street":"Rue Du Pre\u0301Sident Allende",
    "iso:country":"BE",
    "sg:address":"Rue Du Pr\u00e9sident Allende 43",
    "sg:city":"Chapelle-lez-herlaimont (godarville)",
    "sg:classifiers":[
        {
            "category":"Bars & Pubs",
            "type":"Food & Drink"
        }
    ],
    "sg:phone":"+32 64 44 81 70",
    "sg:postcode":"7160",
    "sg:province":"Hainaut",
    "wof:name":"Carlo (chez)",
    "wof:placetype":"venue"
},
  "geometry": {"coordinates":[4.2881479263,50.4935684204],"type":"Point"}
}