{
  "type": "Feature",
  "properties": {
    "iso:country":"BE",
    "sg:address":"Lindenweg 6",
    "sg:city":"Moorslede",
    "sg:orig_category":"Varkenskwekers",
    "sg:phone":"+32 51 77 92 10",
    "sg:postcode":"8890",
    "sg:province":"West-Vlaanderen",
    "wof:name":"Luc Persoon",
    "wof:placetype":"venue"
},
  "geometry": {"coordinates":[3.0859589577,50.918006897],"type":"Point"}
}