{
  "type": "Feature",
  "properties": {
    "iso:country":"BE",
    "sg:address":"Liersesteenweg 145",
    "sg:city":"Mortsel",
    "sg:classifiers":[
        {
            "category":"Fast Food",
            "type":"Food & Drink"
        }
    ],
    "sg:phone":"+32 3 440 40 67",
    "sg:postcode":"2640",
    "sg:province":"Antwerpen",
    "sg:tags":[
        "\u00c0",
        "emporter",
        "restaurants"
    ],
    "wof:name":"Claver's Snackhut",
    "wof:placetype":"venue"
},
  "geometry": {"coordinates":[4.4662871361,51.1692390442],"type":"Point"}
}