{
  "type": "Feature",
  "properties": {
    "iso:country":"BE",
    "sg:address":"Rue Du Champ Du Moulin 10",
    "sg:city":"Soignies",
    "sg:classifiers":[
        {
            "category":"Real Estate",
            "subcategory":"Architect",
            "type":"Services"
        }
    ],
    "sg:phone":"+32 67 33 32 99",
    "sg:postcode":"7060",
    "sg:province":"Hainaut",
    "wof:name":"Ferain G",
    "wof:placetype":"venue"
},
  "geometry": {"coordinates":[4.0568118095,50.5768928528],"type":"Point"}
}