{
  "type": "Feature",
  "properties": {
    "addr:full":"Arthur Verhaegenstraat 23 Gent Oost-Vlaanderen 9000",
    "addr:housenumber":"23",
    "addr:postcode":"9000",
    "addr:street":"Arthur Verhaegenstraat;Oost-Vlaanderen",
    "iso:country":"BE",
    "sg:address":"Arthur Verhaegenstraat 23",
    "sg:city":"Gent",
    "sg:classifiers":[
        {
            "category":"Communications",
            "subcategory":"Film & Video Production",
            "type":"Services"
        }
    ],
    "sg:phone":"+32 475 26 85 60",
    "sg:postcode":"9000",
    "sg:province":"Oost-Vlaanderen",
    "sg:tags":[
        "realisation",
        "-"
    ],
    "wof:name":"Lou Demeyere",
    "wof:placetype":"venue"
},
  "geometry": {"coordinates":[3.7057600021,51.0262145996],"type":"Point"}
}