{
  "type": "Feature",
  "properties": {
    "addr:full":"Chauss\u00c9e De Wavre 1 Elsene/ixelles Bruxelles-Capitale 1050",
    "addr:housenumber":"1",
    "addr:postcode":"1050",
    "addr:street":"Chausse\u0301E De Wavre",
    "iso:country":"BE",
    "sg:address":"Chauss\u00c9e De Wavre 1",
    "sg:city":"Elsene/ixelles",
    "sg:orig_category":"Blanchisseries and teintureries",
    "sg:phone":"+32 2 512 56 11",
    "sg:postcode":"1050",
    "sg:province":"Bruxelles-Capitale",
    "wof:name":"La Com\u00c8te",
    "wof:placetype":"venue"
},
  "geometry": {"coordinates":[4.3621268272,50.8374443054],"type":"Point"}
}