{
  "type": "Feature",
  "properties": {
    "addr:full":"Crapaurue 135 Verviers Li\u00e8ge 4800",
    "addr:housenumber":"135",
    "addr:postcode":"4800",
    "iso:country":"BE",
    "sg:address":"Crapaurue 135",
    "sg:city":"Verviers",
    "sg:classifiers":[
        {
            "category":"Shopping",
            "subcategory":"Books",
            "type":"Retail Goods"
        }
    ],
    "sg:phone":"+32 87 31 23 74",
    "sg:postcode":"4800",
    "sg:province":"Li\u00e8ge",
    "sg:tags":[
        "bookseller"
    ],
    "wof:name":"Carabin Ph",
    "wof:placetype":"venue"
},
  "geometry": {"coordinates":[5.8632698059,50.5926246643],"type":"Point"}
}