{
  "type": "Feature",
  "properties": {
    "iso:country":"BE",
    "sg:address":"Rue Henri Vieuxtemps 46",
    "sg:city":"Bruxelles (anderlecht)",
    "sg:classifiers":[
        {
            "category":"Health Services",
            "subcategory":"Health Practitioner",
            "type":"Services"
        }
    ],
    "sg:phone":"+32 2 520 06 78",
    "sg:postcode":"1070",
    "sg:province":"Bruxelles-Capitale",
    "sg:tags":[
        "physiotherapist"
    ],
    "wof:name":"De Cuypere P",
    "wof:placetype":"venue"
},
  "geometry": {"coordinates":[4.301940918,50.8304405212],"type":"Point"}
}