{
  "type": "Feature",
  "properties": {
    "addr:full":"Rue Fontenelle 2 Orp-jauche Brabant Wallon 1350",
    "addr:housenumber":"2",
    "addr:postcode":"1350",
    "addr:street":"Rue Fontenelle",
    "iso:country":"BE",
    "sg:address":"Rue Fontenelle 2",
    "sg:city":"Orp-jauche",
    "sg:orig_category":"Studios photographiques",
    "sg:phone":"+32 19 63 32 28",
    "sg:postcode":"1350",
    "sg:province":"Brabant Wallon",
    "wof:name":"Kalut Vincent",
    "wof:placetype":"venue"
},
  "geometry": {"coordinates":[4.97920084,50.6738891602],"type":"Point"}
}