{
  "type": "Feature",
  "properties": {
    "iso:country":"BE",
    "sg:address":"Rue De Namur 138",
    "sg:city":"Charleroi",
    "sg:orig_category":"Warenhuizen",
    "sg:phone":"+32 71 37 44 57",
    "sg:postcode":"6041",
    "sg:province":"Hainaut",
    "wof:name":"Dinod\u00b4ungo",
    "wof:placetype":"venue"
},
  "geometry": {"coordinates":[4.4314317703,50.4685935974],"type":"Point"}
}