{
  "type": "Feature",
  "properties": {
    "addr:full":"Heuvelstraat 61 Heusden-zolder (heusden) Limburg 3550",
    "addr:housenumber":"61",
    "addr:postcode":"3550",
    "addr:street":"Heuvelstraat",
    "iso:country":"BE",
    "sg:address":"Heuvelstraat 61",
    "sg:city":"Heusden-zolder (heusden)",
    "sg:classifiers":[
        {
            "category":"Building & Trades",
            "subcategory":"Construction",
            "type":"Services"
        }
    ],
    "sg:phone":"+32 11 57 01 00",
    "sg:postcode":"3550",
    "sg:province":"Limburg",
    "sg:tags":[
        "glazier"
    ],
    "wof:name":"Glas Ceyssens Nv",
    "wof:placetype":"venue"
},
  "geometry": {"coordinates":[5.2921319008,51.0422592163],"type":"Point"}
}