{
  "type": "Feature",
  "properties": {
    "addr:full":"Dr\u00c8ve Richelle 150 Waterloo Brabant Wallon 1410",
    "addr:housenumber":"150",
    "addr:postcode":"1410",
    "addr:street":"Dre\u0300Ve Richelle",
    "iso:country":"BE",
    "sg:address":"Dr\u00c8ve Richelle 150",
    "sg:city":"Waterloo",
    "sg:orig_category":"Epiceries",
    "sg:phone":"+32 2 351 37 11",
    "sg:postcode":"1410",
    "sg:province":"Brabant Wallon",
    "wof:name":"Framboise Et Myrtille",
    "wof:placetype":"venue"
},
  "geometry": {"coordinates":[4.4149141312,50.7053184509],"type":"Point"}
}