{
  "type": "Feature",
  "properties": {
    "iso:country":"BE",
    "sg:address":"Juniorslaan 80",
    "sg:city":"Mechelen",
    "sg:classifiers":[
        {
            "category":"Cafe",
            "type":"Food & Drink"
        }
    ],
    "sg:phone":"+32 15 71 35 44",
    "sg:postcode":"2811",
    "sg:province":"Antwerpen",
    "sg:tags":[
        "caf\u00e9s"
    ],
    "wof:name":"Caf\u00c9 De Prins",
    "wof:placetype":"venue"
},
  "geometry": {"coordinates":[4.3955521584,51.031879425],"type":"Point"}
}