{
  "type": "Feature",
  "properties": {
    "iso:country":"BE",
    "sg:address":"Begijnendreef 38",
    "sg:city":"Turnhout",
    "sg:classifiers":[
        {
            "category":"Home & Garden",
            "subcategory":"Hardware",
            "type":"Retail Goods"
        }
    ],
    "sg:phone":"+32 14 41 18 24",
    "sg:postcode":"2300",
    "sg:province":"Antwerpen",
    "sg:tags":[
        "quincailleries",
        "bois",
        "gr"
    ],
    "wof:name":"Janssens-govaerts",
    "wof:placetype":"venue"
},
  "geometry": {"coordinates":[4.9429249763,51.3280563354],"type":"Point"}
}