{
  "type": "Feature",
  "properties": {
    "addr:full":"Lammerdries 14a Olen Antwerpen 2250",
    "addr:housenumber":"14a",
    "addr:postcode":"2250",
    "addr:street":"Lammerdries",
    "iso:country":"BE",
    "sg:address":"Lammerdries 14a",
    "sg:city":"Olen",
    "sg:classifiers":[
        {
            "category":"Banks & Credit Unions",
            "subcategory":"Bureau De Change",
            "type":"Services"
        }
    ],
    "sg:phone":"+32 14 24 81 81",
    "sg:postcode":"2250",
    "sg:province":"Antwerpen",
    "sg:tags":[
        "regulating",
        "system"
    ],
    "wof:name":"Gefran Benelux",
    "wof:placetype":"venue"
},
  "geometry": {"coordinates":[4.9147100449,51.1488685608],"type":"Point"}
}