{
  "type": "Feature",
  "properties": {
    "iso:country":"BE",
    "sg:address":"Smalvoortstraat 44",
    "sg:city":"Turnhout",
    "sg:orig_category":"Woningbouw",
    "sg:phone":"+32 14 42 59 38",
    "sg:postcode":"2300",
    "sg:province":"Antwerpen",
    "wof:name":"Renobau",
    "wof:placetype":"venue"
},
  "geometry": {"coordinates":[4.9530310631,51.3160057068],"type":"Point"}
}