{
  "type": "Feature",
  "properties": {
    "addr:full":"Beernemsteenweg 63 Wingene West-Vlaanderen 8750",
    "addr:housenumber":"63",
    "addr:postcode":"8750",
    "addr:street":"Beernemsteenweg",
    "iso:country":"BE",
    "sg:address":"Beernemsteenweg 63",
    "sg:city":"Wingene",
    "sg:orig_category":"Enseignement maternel and primaire",
    "sg:phone":"+32 51 65 75 57",
    "sg:postcode":"8750",
    "sg:province":"West-Vlaanderen",
    "wof:name":"Vrije Basisschool",
    "wof:placetype":"venue"
},
  "geometry": {"coordinates":[3.277905941,51.0627708435],"type":"Point"}
}