{
  "type": "Feature",
  "properties": {
    "iso:country":"BE",
    "sg:address":"Rue De La Montagne 9",
    "sg:city":"Eupen",
    "sg:orig_category":"Pain, p\u00e2tisseries and confiseries",
    "sg:phone":"+32 87 74 29 64",
    "sg:postcode":"4700",
    "sg:province":"Li\u00e8ge",
    "wof:name":"Kelleter",
    "wof:placetype":"venue"
},
  "geometry": {"coordinates":[6.0331859589,50.6298942566],"type":"Point"}
}