{
  "type": "Feature",
  "properties": {
    "addr:full":"Oude Stationstraat 7 Tielt West-Vlaanderen 8700",
    "addr:housenumber":"7",
    "addr:postcode":"8700",
    "addr:street":"Oude Stationstraat",
    "iso:country":"BE",
    "sg:address":"Oude Stationstraat 7",
    "sg:city":"Tielt",
    "sg:orig_category":"Services de Nettoyage and de D\u00e9sinfection",
    "sg:phone":"+32 51 40 72 64",
    "sg:postcode":"8700",
    "sg:province":"West-Vlaanderen",
    "wof:name":"Fa. Vitro-clean",
    "wof:placetype":"venue"
},
  "geometry": {"coordinates":[3.3263978958,50.9951515198],"type":"Point"}
}