{
  "type": "Feature",
  "properties": {
    "iso:country":"BE",
    "sg:address":"Place De L'europe 5",
    "sg:city":"Ottignies-louvain-la-neuve (limelette)",
    "sg:classifiers":[
        {
            "category":"Building & Trades",
            "subcategory":"Electrical",
            "type":"Services"
        }
    ],
    "sg:phone":"+32 10 41 28 43",
    "sg:postcode":"1342",
    "sg:province":"Brabant Wallon",
    "sg:tags":[
        "electric",
        "-",
        "housewiring",
        "contractor"
    ],
    "wof:name":"F M Fusion",
    "wof:placetype":"venue"
},
  "geometry": {"coordinates":[5.8755340576,50.5953216553],"type":"Point"}
}