{
  "type": "Feature",
  "properties": {
    "iso:country":"BE",
    "sg:address":"Rue Du Cugn\u00c9 10",
    "sg:city":"Virton",
    "sg:orig_category":"Instituts de beaut\u00e9",
    "sg:phone":"+32 63 57 86 49",
    "sg:postcode":"6760",
    "sg:province":"Luxembourg",
    "wof:name":"Institut Oc\u00c9ane",
    "wof:placetype":"venue"
},
  "geometry": {"coordinates":[5.5276079178,49.5751152039],"type":"Point"}
}