{
  "type": "Feature",
  "properties": {
    "addr:full":"Avenue De Vianden 47 Huy Li\u00e8ge 4500",
    "addr:housenumber":"47",
    "addr:postcode":"4500",
    "addr:street":"Avenue De Vianden",
    "iso:country":"BE",
    "sg:address":"Avenue De Vianden 47",
    "sg:city":"Huy",
    "sg:classifiers":[
        {
            "category":"Health Services",
            "subcategory":"Health Practitioner",
            "type":"Services"
        }
    ],
    "sg:phone":"+32 495 21 83 90",
    "sg:postcode":"4500",
    "sg:province":"Li\u00e8ge",
    "sg:tags":[
        "physiotherapist"
    ],
    "wof:name":"Gaillard Sandrina",
    "wof:placetype":"venue"
},
  "geometry": {"coordinates":[5.2548251152,50.5224189758],"type":"Point"}
}