{
  "type": "Feature",
  "properties": {
    "addr:full":"Rue De Grimod\u00e9 9 Habay (rulles) Luxembourg 6724",
    "addr:housenumber":"9",
    "addr:postcode":"6724",
    "addr:street":"Rue De Grimode\u0301",
    "iso:country":"BE",
    "sg:address":"Rue De Grimod\u00e9 9",
    "sg:city":"Habay (rulles)",
    "sg:classifiers":[
        {
            "category":"Retail",
            "subcategory":"Repair Shop",
            "type":"Services"
        }
    ],
    "sg:phone":"+32 63 41 16 93",
    "sg:postcode":"6724",
    "sg:province":"Luxembourg",
    "wof:name":"Depannage Mds",
    "wof:placetype":"venue"
},
  "geometry": {"coordinates":[5.5597100258,49.7180557251],"type":"Point"}
}