{
  "type": "Feature",
  "properties": {
    "addr:full":"Noordakkerstraat 28 Wingene West-Vlaanderen 8750",
    "addr:housenumber":"28",
    "addr:postcode":"8750",
    "addr:street":"Noordakkerstraat",
    "iso:country":"BE",
    "sg:address":"Noordakkerstraat 28",
    "sg:city":"Wingene",
    "sg:orig_category":"Rundveehouders Varkenskwekers",
    "sg:phone":"+32 51 65 67 17",
    "sg:postcode":"8750",
    "sg:province":"West-Vlaanderen",
    "wof:name":"Carlos De Craene",
    "wof:placetype":"venue"
},
  "geometry": {"coordinates":[3.2708110809,51.0745620728],"type":"Point"}
}