{
  "type": "Feature",
  "properties": {
    "addr:full":"Europalaan 29 Tielt West-Vlaanderen 8700",
    "addr:housenumber":"29",
    "addr:postcode":"8700",
    "addr:street":"Europalaan",
    "iso:country":"BE",
    "sg:address":"Europalaan 29",
    "sg:city":"Tielt",
    "sg:orig_category":"R\u00e9parations de chaussures and articles en cuir",
    "sg:phone":"+32 51 40 39 38",
    "sg:postcode":"8700",
    "sg:province":"West-Vlaanderen",
    "wof:name":"Andre Van Quickelberghe",
    "wof:placetype":"venue"
},
  "geometry": {"coordinates":[3.3324179649,51.0005302429],"type":"Point"}
}