{
  "type": "Feature",
  "properties": {
    "addr:full":"Lindestraat 59 Waregem West-Vlaanderen 8790",
    "addr:housenumber":"59",
    "addr:postcode":"8790",
    "addr:street":"Lindestraat",
    "iso:country":"BE",
    "sg:address":"Lindestraat 59",
    "sg:city":"Waregem",
    "sg:classifiers":[
        {
            "category":"Professional",
            "subcategory":"Detective & Security Services",
            "type":"Services"
        }
    ],
    "sg:phone":"+32 9 346 86 62",
    "sg:postcode":"8790",
    "sg:province":"West-Vlaanderen",
    "sg:tags":[
        "installation",
        "alarm",
        "-",
        "system"
    ],
    "wof:name":"Radatech Nv",
    "wof:placetype":"venue"
},
  "geometry": {"coordinates":[3.4106600285,50.8951072693],"type":"Point"}
}