{
  "type": "Feature",
  "properties": {
    "addr:full":"Kraaienhorst 1b Brecht (sint-lenaarts) Antwerpen 2960",
    "addr:housenumber":"1b",
    "addr:postcode":"2960",
    "addr:street":"Kraaienhorst",
    "iso:country":"BE",
    "sg:address":"Kraaienhorst 1b",
    "sg:city":"Brecht (sint-lenaarts)",
    "sg:classifiers":[
        {
            "category":"Home & Garden",
            "subcategory":"Garden Supply",
            "type":"Retail Goods"
        }
    ],
    "sg:phone":"+32 3 313 95 00",
    "sg:postcode":"2960",
    "sg:province":"Antwerpen",
    "sg:tags":[
        "machine",
        "agricultural",
        "-"
    ],
    "wof:name":"Vermeiren",
    "wof:placetype":"venue"
},
  "geometry": {"coordinates":[4.6415200233,51.3512115479],"type":"Point"}
}