{
  "type": "Feature",
  "properties": {
    "addr:full":"Batterijstraat 16 Oostende West-Vlaanderen 8400",
    "addr:housenumber":"16",
    "addr:postcode":"8400",
    "addr:street":"Batterijstraat",
    "iso:country":"BE",
    "sg:address":"Batterijstraat 16",
    "sg:city":"Oostende",
    "sg:orig_category":"Advocaten and juridische adviseurs",
    "sg:phone":"+32 59 51 16 06",
    "sg:postcode":"8400",
    "sg:province":"West-Vlaanderen",
    "wof:name":"Wim Geldof",
    "wof:placetype":"venue"
},
  "geometry": {"coordinates":[2.9021379948,51.2123527527],"type":"Point"}
}