{
  "type": "Feature",
  "properties": {
    "addr:full":"Vennen 35 Herentals Antwerpen 2200",
    "addr:housenumber":"35",
    "addr:postcode":"2200",
    "addr:street":"Vennen",
    "iso:country":"BE",
    "sg:address":"Vennen 35",
    "sg:city":"Herentals",
    "sg:classifiers":[
        {
            "category":"Sports & Exercise",
            "subcategory":"Sports Center",
            "type":"Entertainment"
        }
    ],
    "sg:phone":"+32 14 22 40 42",
    "sg:postcode":"2200",
    "sg:province":"Antwerpen",
    "sg:tags":[
        "installation",
        "sportifs",
        "de",
        "terrain",
        "hors",
        "caf\u00e9s"
    ],
    "wof:name":"Bowling 't Ven",
    "wof:placetype":"venue"
},
  "geometry": {"coordinates":[4.8452100754,51.164768219],"type":"Point"}
}