{
  "type": "Feature",
  "properties": {
    "addr:full":"Avenue De La Couronne 311 Elsene/ixelles Bruxelles-Capitale 1050",
    "addr:housenumber":"311",
    "addr:postcode":"1050",
    "addr:street":"Avenue De La Couronne",
    "iso:country":"BE",
    "sg:address":"Avenue De La Couronne 311",
    "sg:city":"Elsene/ixelles",
    "sg:orig_category":"Agences d\u00b4interim and personnel temporaire",
    "sg:phone":"+32 2 643 47 90",
    "sg:postcode":"1050",
    "sg:province":"Bruxelles-Capitale",
    "wof:name":"Mailprofs Belgium Sa",
    "wof:placetype":"venue"
},
  "geometry": {"coordinates":[4.3911919594,50.8193855286],"type":"Point"}
}