{
  "type": "Feature",
  "properties": {
    "iso:country":"BE",
    "sg:address":"Avenue Marius Meur\u00c9e 47ba",
    "sg:city":"Charleroi",
    "sg:orig_category":"Plomberie, chauffage and installations sanitaires",
    "sg:phone":"+32 71 36 10 45",
    "sg:postcode":"6001",
    "sg:province":"Hainaut",
    "wof:name":"R.l.v.",
    "wof:placetype":"venue"
},
  "geometry": {"coordinates":[4.446680069,50.4009475708],"type":"Point"}
}