{
  "type": "Feature",
  "properties": {
    "addr:full":"Sint-maartensplein 17 Koekelare West-Vlaanderen 8680",
    "addr:housenumber":"17",
    "addr:postcode":"8680",
    "addr:street":"Sint-Maartensplein",
    "iso:country":"BE",
    "sg:address":"Sint-maartensplein 17",
    "sg:city":"Koekelare",
    "sg:orig_category":"Banken and kredietinstellingen",
    "sg:phone":"+32 51 58 81 47",
    "sg:postcode":"8680",
    "sg:province":"West-Vlaanderen",
    "wof:name":"Dexia",
    "wof:placetype":"venue"
},
  "geometry": {"coordinates":[2.9788548946,51.0891609192],"type":"Point"}
}