{
  "type": "Feature",
  "properties": {
    "iso:country":"BE",
    "sg:address":"Boulevard De L'humanit\u00c9 415",
    "sg:city":"Vorst/forest",
    "sg:orig_category":"Timbres, monnaies and troph\u00e9es",
    "sg:phone":"+32 2 376 42 48",
    "sg:postcode":"1190",
    "sg:province":"Bruxelles-Capitale",
    "wof:name":"Eurocollect",
    "wof:placetype":"venue"
},
  "geometry": {"coordinates":[4.3121328354,50.8200950623],"type":"Point"}
}