{
  "type": "Feature",
  "properties": {
    "iso:country":"BE",
    "sg:address":"Rue Alfred Derval 73",
    "sg:city":"Binche (waudrez)",
    "sg:classifiers":[
        {
            "category":"Personal",
            "type":"Services"
        }
    ],
    "sg:phone":"+32 64 33 28 74",
    "sg:postcode":"7131",
    "sg:province":"Hainaut",
    "sg:tags":[
        "clothing",
        "men's",
        "tailor",
        "-"
    ],
    "wof:name":"Besanger",
    "wof:placetype":"venue"
},
  "geometry": {"coordinates":[4.1517601013,50.4148521423],"type":"Point"}
}