{
  "type": "Feature",
  "properties": {
    "iso:country":"BE",
    "sg:address":"Salvialaan 27",
    "sg:city":"Temse (steendorp)",
    "sg:classifiers":[
        {
            "category":"Banks & Credit Unions",
            "subcategory":"Investment Brokerage",
            "type":"Services"
        }
    ],
    "sg:phone":"+32 3 774 01 35",
    "sg:postcode":"9140",
    "sg:province":"Oost-Vlaanderen",
    "sg:tags":[
        "auditor"
    ],
    "wof:name":"Van Der Jeught E",
    "wof:placetype":"venue"
},
  "geometry": {"coordinates":[4.2738418579,51.1333274841],"type":"Point"}
}