{
  "type": "Feature",
  "properties": {
    "iso:country":"BE",
    "sg:address":"Korenmarkt 12",
    "sg:city":"Mechelen",
    "sg:orig_category":"Biens d'occasion",
    "sg:phone":"+32 15 26 12 53",
    "sg:postcode":"2800",
    "sg:province":"Antwerpen",
    "wof:name":"Kringloopateljee",
    "wof:placetype":"venue"
},
  "geometry": {"coordinates":[4.4759988785,51.0248222351],"type":"Point"}
}