{
  "type": "Feature",
  "properties": {
    "iso:country":"BE",
    "sg:address":"Rue Du Roussart 65",
    "sg:city":"Waterloo",
    "sg:orig_category":"Drukkerijen and copyshops",
    "sg:phone":"+32 2 354 70 02",
    "sg:postcode":"1410",
    "sg:province":"Brabant Wallon",
    "wof:name":"L'echo De Waterloo",
    "wof:placetype":"venue"
},
  "geometry": {"coordinates":[4.4049048424,50.7018623352],"type":"Point"}
}