{
  "type": "Feature",
  "properties": {
    "iso:country":"BE",
    "sg:address":"Europark Zuid 2",
    "sg:city":"Sint-niklaas",
    "sg:orig_category":"Herstellingen and onderhoud van auto's Mazda Voertuigen",
    "sg:phone":"+32 3 766 29 69",
    "sg:postcode":"9100",
    "sg:province":"Oost-Vlaanderen",
    "wof:name":"Hugo De Smet B.v.b.a.",
    "wof:placetype":"venue"
},
  "geometry": {"coordinates":[4.1709909439,51.1624984741],"type":"Point"}
}