{
  "type": "Feature",
  "properties": {
    "addr:full":"Kiezelweg 80 Lanaken Limburg 3620",
    "addr:housenumber":"80",
    "addr:postcode":"3620",
    "addr:street":"Kiezelweg",
    "iso:country":"BE",
    "sg:address":"Kiezelweg 80",
    "sg:city":"Lanaken",
    "sg:classifiers":[
        {
            "category":"Fast Food",
            "type":"Food & Drink"
        }
    ],
    "sg:phone":"+32 89 71 10 40",
    "sg:postcode":"3620",
    "sg:province":"Limburg",
    "sg:tags":[
        "\u00c0",
        "restaurants",
        "emporter",
        "restaurant"
    ],
    "wof:name":"China",
    "wof:placetype":"venue"
},
  "geometry": {"coordinates":[5.6303129196,50.8812713623],"type":"Point"}
}