{
  "type": "Feature",
  "properties": {
    "addr:full":"Tarwestraat 9 Schoten Antwerpen 2900",
    "addr:housenumber":"9",
    "addr:postcode":"2900",
    "addr:street":"Tarwestraat",
    "iso:country":"BE",
    "sg:address":"Tarwestraat 9",
    "sg:city":"Schoten",
    "sg:classifiers":[
        {
            "category":"Shopping",
            "subcategory":"Gifts & Souvenirs",
            "type":"Retail Goods"
        }
    ],
    "sg:phone":"+32 3 685 16 15",
    "sg:postcode":"2900",
    "sg:province":"Antwerpen",
    "sg:tags":[
        "geschenken"
    ],
    "wof:name":"Zet",
    "wof:placetype":"venue"
},
  "geometry": {"coordinates":[4.4990940094,51.2552566528],"type":"Point"}
}