{
  "type": "Feature",
  "properties": {
    "addr:full":"Rue De Bossut 26 Grez-doiceau Brabant Wallon 1390",
    "addr:housenumber":"26",
    "addr:postcode":"1390",
    "addr:street":"Rue De Bossut",
    "iso:country":"BE",
    "sg:address":"Rue De Bossut 26",
    "sg:city":"Grez-doiceau",
    "sg:classifiers":[
        {
            "category":"Personal",
            "subcategory":"Beauty Salon",
            "type":"Services"
        }
    ],
    "sg:phone":"+32 10 86 03 16",
    "sg:postcode":"1390",
    "sg:province":"Brabant Wallon",
    "sg:tags":[
        "de",
        "coiffure"
    ],
    "wof:name":"Marina Michiels",
    "wof:placetype":"venue"
},
  "geometry": {"coordinates":[4.6746139526,50.7831077576],"type":"Point"}
}