{
  "type": "Feature",
  "properties": {
    "addr:full":"Bellestraat 51 Poperinge West-Vlaanderen 8970",
    "addr:housenumber":"51",
    "addr:postcode":"8970",
    "addr:street":"Bellestraat",
    "iso:country":"BE",
    "sg:address":"Bellestraat 51",
    "sg:city":"Poperinge",
    "sg:classifiers":[
        {
            "category":"Professional",
            "subcategory":"Art Services",
            "type":"Services"
        }
    ],
    "sg:phone":"+32 57 33 80 21",
    "sg:postcode":"8970",
    "sg:province":"West-Vlaanderen",
    "sg:tags":[
        "interior",
        "designer"
    ],
    "wof:name":"Planning En Interieurstudie Bureau",
    "wof:placetype":"venue"
},
  "geometry": {"coordinates":[2.7217350006,50.8471870422],"type":"Point"}
}