{
  "type": "Feature",
  "properties": {
    "addr:full":"Clos Du Lodaal 16 Bruxelles Bruxelles-Capitale 1020",
    "addr:housenumber":"16",
    "addr:postcode":"1020",
    "addr:street":"Clos Du Lodaal",
    "iso:country":"BE",
    "sg:address":"Clos Du Lodaal 16",
    "sg:city":"Bruxelles",
    "sg:classifiers":[
        {
            "category":"Professional",
            "subcategory":"Lawyer & Legal Services",
            "type":"Services"
        }
    ],
    "sg:phone":"+32 2 268 39 98",
    "sg:postcode":"1020",
    "sg:province":"Bruxelles-Capitale",
    "wof:name":"Schmidt Jean-pol",
    "wof:placetype":"venue"
},
  "geometry": {"coordinates":[4.3715701103,50.897354126],"type":"Point"}
}