{
  "type": "Feature",
  "properties": {
    "iso:country":"BE",
    "sg:address":"Kolisbos 12",
    "sg:city":"Neerpelt",
    "sg:orig_category":"Eleveurs de bovins. Eleveurs and marchands de porcs",
    "sg:phone":"+32 11 64 72 31",
    "sg:postcode":"3910",
    "sg:province":"Limburg",
    "wof:name":"Stefan Foets",
    "wof:placetype":"venue"
},
  "geometry": {"coordinates":[5.4645328522,51.1938285828],"type":"Point"}
}