{
  "type": "Feature",
  "properties": {
    "iso:country":"BE",
    "sg:address":"Waverstraat 47",
    "sg:city":"Sint-katelijne-waver",
    "sg:classifiers":[
        {
            "category":"Farming",
            "subcategory":"Crops",
            "type":"Manufacturing & Wholesale Goods"
        }
    ],
    "sg:phone":"+32 15 31 50 31",
    "sg:postcode":"2860",
    "sg:province":"Antwerpen",
    "sg:tags":[
        "vegetable",
        "fruit",
        "-",
        "grower"
    ],
    "wof:name":"De Groof H",
    "wof:placetype":"venue"
},
  "geometry": {"coordinates":[4.5461730957,51.0622558594],"type":"Point"}
}