{
  "type": "Feature",
  "properties": {
    "addr:full":"Kijkuitstraat 23 Wevelgem West-Vlaanderen 8560",
    "addr:housenumber":"23",
    "addr:postcode":"8560",
    "addr:street":"Kijkuitstraat",
    "iso:country":"BE",
    "sg:address":"Kijkuitstraat 23",
    "sg:city":"Wevelgem",
    "sg:classifiers":[
        {
            "category":"Bars & Pubs",
            "type":"Food & Drink"
        }
    ],
    "sg:phone":"+32 56 42 15 43",
    "sg:postcode":"8560",
    "sg:province":"West-Vlaanderen",
    "wof:name":"Devijvers",
    "wof:placetype":"venue"
},
  "geometry": {"coordinates":[3.1705760956,50.8104934692],"type":"Point"}
}