{
  "type": "Feature",
  "properties": {
    "addr:full":"Rue C\u00c9sar Franck 72 Plombieres Li\u00e8ge 4851",
    "addr:housenumber":"72",
    "addr:postcode":"4851",
    "addr:street":"Rue Ce\u0301Sar Franck",
    "iso:country":"BE",
    "sg:address":"Rue C\u00c9sar Franck 72",
    "sg:city":"Plombieres",
    "sg:orig_category":"Enseignement maternel and primaire",
    "sg:phone":"+32 87 78 42 26",
    "sg:postcode":"4851",
    "sg:province":"Li\u00e8ge",
    "wof:name":"Ecole Fond. Communale",
    "wof:placetype":"venue"
},
  "geometry": {"coordinates":[5.991932869,50.744594574],"type":"Point"}
}