{
  "type": "Feature",
  "properties": {
    "iso:country":"BE",
    "sg:address":"Langemunt 176",
    "sg:city":"Erpe-mere",
    "sg:orig_category":"Eleveurs de bovins",
    "sg:phone":"+32 53 62 45 84",
    "sg:postcode":"9420",
    "sg:province":"Oost-Vlaanderen",
    "wof:name":"Honore Van Boxstael",
    "wof:placetype":"venue"
},
  "geometry": {"coordinates":[3.9394800663,50.905090332],"type":"Point"}
}