{
  "type": "Feature",
  "properties": {
    "addr:full":"Kwakkelstraat 14 Deinze (grammene) Oost-Vlaanderen 9800",
    "addr:housenumber":"14",
    "addr:postcode":"9800",
    "addr:street":"Kwakkelstraat",
    "iso:country":"BE",
    "sg:address":"Kwakkelstraat 14",
    "sg:city":"Deinze (grammene)",
    "sg:classifiers":[
        {
            "category":"Farming",
            "subcategory":"Livestock Farm",
            "type":"Manufacturing & Wholesale Goods"
        }
    ],
    "sg:phone":"+32 51 63 40 95",
    "sg:postcode":"9800",
    "sg:province":"Oost-Vlaanderen",
    "sg:tags":[
        "buyer"
    ],
    "wof:name":"Hobby Voeders Marcel",
    "wof:placetype":"venue"
},
  "geometry": {"coordinates":[3.530174017,50.9863166809],"type":"Point"}
}