{
  "type": "Feature",
  "properties": {
    "addr:full":"Heinrich-bischoff-str. 36 Raeren/raeren Li\u00e8ge 4731",
    "addr:housenumber":"36",
    "addr:postcode":"4731",
    "addr:street":"Heinrich-Bischoff-Str.",
    "iso:country":"BE",
    "sg:address":"Heinrich-bischoff-str. 36",
    "sg:city":"Raeren/raeren",
    "sg:orig_category":"Effectenmakelaars and vermogensbeheer Immobili\u00ebnkantoren",
    "sg:phone":"+32 87 65 74 00",
    "sg:postcode":"4731",
    "sg:province":"Li\u00e8ge",
    "wof:name":"Heutz Immobilien",
    "wof:placetype":"venue"
},
  "geometry": {"coordinates":[6.0920181274,50.7107887268],"type":"Point"}
}