{
  "type": "Feature",
  "properties": {
    "addr:full":"Avenue Du Parc 31 Terhulpen Brabant Wallon 1310",
    "addr:housenumber":"31;1310",
    "addr:street":"Avenue Du Parc;Brabant Wallon",
    "iso:country":"BE",
    "sg:address":"Avenue Du Parc 31",
    "sg:city":"Terhulpen",
    "sg:orig_category":"Produits chimiques Gr",
    "sg:phone":"+32 2 653 78 95",
    "sg:postcode":"1310",
    "sg:province":"Brabant Wallon",
    "wof:name":"Circograf-belgique",
    "wof:placetype":"venue"
},
  "geometry": {"coordinates":[4.5110487938,50.7328643799],"type":"Point"}
}