{
  "type": "Feature",
  "properties": {
    "addr:full":"Rue Du Brou 61 Verviers Li\u00e8ge 4800",
    "addr:housenumber":"61",
    "addr:postcode":"4800",
    "addr:street":"Rue Du Brou",
    "iso:country":"BE",
    "sg:address":"Rue Du Brou 61",
    "sg:city":"Verviers",
    "sg:classifiers":[
        {
            "category":"Shopping",
            "subcategory":"Clothing, Apparel, & Fashions",
            "type":"Retail Goods"
        }
    ],
    "sg:phone":"+32 87 35 26 47",
    "sg:postcode":"4800",
    "sg:province":"Li\u00e8ge",
    "sg:tags":[
        "ondergoed",
        "lingerie"
    ],
    "wof:name":"Etam Lingerie",
    "wof:placetype":"venue"
},
  "geometry": {"coordinates":[5.8583250046,50.5921401978],"type":"Point"}
}