{
  "type": "Feature",
  "properties": {
    "addr:full":"Chauss\u00e9e De Namur 168 Gembloux-sur-orneau (gembloux) Namur 5030",
    "addr:housenumber":"168",
    "addr:postcode":"5030",
    "addr:street":"Chausse\u0301E De Namur;Namur",
    "iso:country":"BE",
    "sg:address":"Chauss\u00e9e De Namur 168",
    "sg:city":"Gembloux-sur-orneau (gembloux)",
    "sg:classifiers":[
        {
            "category":"Airport",
            "subcategory":"International",
            "type":"Transportation"
        }
    ],
    "sg:phone":"+32 81 61 19 92",
    "sg:postcode":"5030",
    "sg:province":"Namur",
    "sg:tags":[
        "-",
        "transport"
    ],
    "wof:name":"Denis & Cie",
    "wof:placetype":"venue"
},
  "geometry": {"coordinates":[4.7139191628,50.549407959],"type":"Point"}
}