{
  "type": "Feature",
  "properties": {
    "iso:country":"BE",
    "sg:address":"Leuvensebaan 51",
    "sg:city":"Huldenberg",
    "sg:orig_category":"Diverse zakelijke dienstverlening",
    "sg:phone":"+32 16 47 40 05",
    "sg:postcode":"3040",
    "sg:province":"Vlaams-Brabant",
    "wof:name":"Malfliet S.e.p.",
    "wof:placetype":"venue"
},
  "geometry": {"coordinates":[4.615737915,50.7504272461],"type":"Point"}
}