{
  "type": "Feature",
  "properties": {
    "iso:country":"BE",
    "sg:address":"Rue Trois Bourdons 14",
    "sg:city":"Welkenraedt",
    "sg:classifiers":[
        {
            "category":"Utilities",
            "subcategory":"Natural Gas",
            "type":"Services"
        }
    ],
    "sg:phone":"+32 87 89 11 09",
    "sg:postcode":"4840",
    "sg:province":"Li\u00e8ge",
    "sg:tags":[
        "filter",
        "-",
        "liquid"
    ],
    "wof:name":"C.s. Filtration",
    "wof:placetype":"venue"
},
  "geometry": {"coordinates":[5.9771962166,50.6583862305],"type":"Point"}
}