{
  "type": "Feature",
  "properties": {
    "iso:country":"BE",
    "sg:address":"Brandstraat 9",
    "sg:city":"Temse",
    "sg:orig_category":"Groententeelt",
    "sg:phone":"+32 3 766 66 01",
    "sg:postcode":"9140",
    "sg:province":"Oost-Vlaanderen",
    "wof:name":"Marc De Pauw",
    "wof:placetype":"venue"
},
  "geometry": {"coordinates":[4.1913189888,51.1538238525],"type":"Point"}
}