{
  "type": "Feature",
  "properties": {
    "addr:full":"Avenue De L'atlantique 98a Bruxelles (woluwe-saint-pierre) Bruxelles-Capitale 1150",
    "addr:housenumber":"98a",
    "addr:postcode":"1150",
    "addr:street":"Avenue De L'Atlantique",
    "iso:country":"BE",
    "sg:address":"Avenue De L'atlantique 98a",
    "sg:city":"Bruxelles (woluwe-saint-pierre)",
    "sg:classifiers":[
        {
            "category":"Professional",
            "subcategory":"Computer Services",
            "type":"Services"
        }
    ],
    "sg:phone":"+32 478 55 72 88",
    "sg:postcode":"1150",
    "sg:province":"Bruxelles-Capitale",
    "sg:tags":[
        "webdesign",
        "-",
        "internet"
    ],
    "wof:name":"Prior Hugh",
    "wof:placetype":"venue"
},
  "geometry": {"coordinates":[4.4185628891,50.828956604],"type":"Point"}
}