{
  "type": "Feature",
  "properties": {
    "iso:country":"BE",
    "sg:address":"Voie De Meuniers 17",
    "sg:city":"Verlaine",
    "sg:classifiers":[
        {
            "category":"Health Services",
            "subcategory":"Doctor",
            "type":"Services"
        }
    ],
    "sg:phone":"+32 4 259 63 63",
    "sg:postcode":"4537",
    "sg:province":"Li\u00e8ge",
    "sg:tags":[
        "medicinephysicians",
        "surgeon"
    ],
    "wof:name":"Desselle J-l",
    "wof:placetype":"venue"
},
  "geometry": {"coordinates":[5.313644886,50.6025733948],"type":"Point"}
}