{
  "type": "Feature",
  "properties": {
    "addr:full":"Bel Air 5dn Beauraing (dion) Namur 5570",
    "addr:postcode":"5570",
    "iso:country":"BE",
    "sg:address":"Bel Air 5dn",
    "sg:city":"Beauraing (dion)",
    "sg:classifiers":[
        {
            "category":"Professional",
            "subcategory":"Accounting & Tax Preparation",
            "type":"Services"
        }
    ],
    "sg:phone":"+32 82 71 32 57",
    "sg:postcode":"5570",
    "sg:province":"Namur",
    "sg:tags":[
        "bookkeeper"
    ],
    "wof:name":"Guerin G",
    "wof:placetype":"venue"
},
  "geometry": {"coordinates":[4.8781270981,50.1207008362],"type":"Point"}
}