{
  "type": "Feature",
  "properties": {
    "addr:full":"Rue Des Clouteries 32 Fontaine-l\u00b4ev\u00caque Hainaut 6140",
    "addr:housenumber":"32",
    "addr:postcode":"6140",
    "addr:street":"Rue Des Clouteries;Hainaut",
    "iso:country":"BE",
    "sg:address":"Rue Des Clouteries 32",
    "sg:city":"Fontaine-l\u00b4ev\u00caque",
    "sg:orig_category":"Drogueries. Eclairage et \u00e9quipements du foyer. Textiles",
    "sg:phone":"+32 71 54 22 29",
    "sg:postcode":"6140",
    "sg:province":"Hainaut",
    "wof:name":"Le Coin Maison",
    "wof:placetype":"venue"
},
  "geometry": {"coordinates":[4.3307671547,50.4118537903],"type":"Point"}
}