{
  "type": "Feature",
  "properties": {
    "addr:full":"Rue Boucaut 11 Leuze-en-hainaut Hainaut 7900",
    "addr:housenumber":"11",
    "addr:postcode":"7900",
    "addr:street":"Rue Boucaut",
    "iso:country":"BE",
    "sg:address":"Rue Boucaut 11",
    "sg:city":"Leuze-en-hainaut",
    "sg:orig_category":"Rundveehouders",
    "sg:phone":"+32 69 66 27 13",
    "sg:postcode":"7900",
    "sg:province":"Hainaut",
    "wof:name":"Maurice Pomme",
    "wof:placetype":"venue"
},
  "geometry": {"coordinates":[3.6493570805,50.6228942871],"type":"Point"}
}