{
  "type": "Feature",
  "properties": {
    "iso:country":"BE",
    "sg:address":"Hondzochtstraat 43",
    "sg:city":"Pepingen",
    "sg:orig_category":"Producteurs de fruits",
    "sg:phone":"+32 2 360 21 44",
    "sg:postcode":"1674",
    "sg:province":"Vlaams-Brabant",
    "wof:name":"Fa. De Schrijver",
    "wof:placetype":"venue"
},
  "geometry": {"coordinates":[4.1628079414,50.727558136],"type":"Point"}
}