{
  "type": "Feature",
  "properties": {
    "addr:full":"Chauss\u00c9e Brunehaut 315 Juprelle Li\u00e8ge 4453",
    "addr:housenumber":"315",
    "addr:postcode":"4453",
    "addr:street":"Chausse\u0301E Brunehaut",
    "iso:country":"BE",
    "sg:address":"Chauss\u00c9e Brunehaut 315",
    "sg:city":"Juprelle",
    "sg:orig_category":"Jardinage",
    "sg:phone":"+32 4 278 66 72",
    "sg:postcode":"4453",
    "sg:province":"Li\u00e8ge",
    "wof:name":"Reynders",
    "wof:placetype":"venue"
},
  "geometry": {"coordinates":[5.5404701233,50.7101402283],"type":"Point"}
}