{
  "type": "Feature",
  "properties": {
    "addr:full":"Chauss\u00c9e Paul Houtart 268 La Louviere Hainaut 7110",
    "addr:housenumber":"268",
    "addr:postcode":"7110",
    "addr:street":"Chausse\u0301E Paul Houtart",
    "iso:country":"BE",
    "sg:address":"Chauss\u00c9e Paul Houtart 268",
    "sg:city":"La Louviere",
    "sg:orig_category":"Diverse kredietdiensten",
    "sg:postcode":"7110",
    "sg:province":"Hainaut",
    "wof:name":"Bancontact-mister Cash",
    "wof:placetype":"venue"
},
  "geometry": {"coordinates":[4.1581501961,50.4865036011],"type":"Point"}
}