{
  "type": "Feature",
  "properties": {
    "addr:full":"Rue Du Garinet 10-12 Bertrix Luxembourg 6880",
    "addr:housenumber":"10-12",
    "addr:postcode":"6880",
    "addr:street":"Rue Du Garinet",
    "iso:country":"BE",
    "sg:address":"Rue Du Garinet 10-12",
    "sg:city":"Bertrix",
    "sg:orig_category":"Plomberie, chauffage and installations sanitaires. Services de Nettoyage and de D\u00e9sinfection",
    "sg:phone":"+32 61 41 16 12",
    "sg:postcode":"6880",
    "sg:province":"Luxembourg",
    "wof:name":"Guy Piquard",
    "wof:placetype":"venue"
},
  "geometry": {"coordinates":[5.2589440346,49.8528366089],"type":"Point"}
}