{
  "type": "Feature",
  "properties": {
    "addr:full":"Lombaardstraat 9 Ieper West-Vlaanderen 8900",
    "addr:housenumber":"9",
    "addr:postcode":"8900",
    "addr:street":"Lombaardstraat",
    "iso:country":"BE",
    "sg:address":"Lombaardstraat 9",
    "sg:city":"Ieper",
    "sg:classifiers":[
        {
            "category":"Health Services",
            "subcategory":"Doctor",
            "type":"Services"
        }
    ],
    "sg:phone":"+32 57 46 90 00",
    "sg:postcode":"8900",
    "sg:province":"West-Vlaanderen",
    "sg:tags":[
        "medicinephysicians",
        "surgeon"
    ],
    "wof:name":"Leroy Wim",
    "wof:placetype":"venue"
},
  "geometry": {"coordinates":[2.8872699738,50.84765625],"type":"Point"}
}