{
  "type": "Feature",
  "properties": {
    "addr:full":"Familie De Cockstraat 31 Tremelo Vlaams-Brabant 3128",
    "addr:housenumber":"31",
    "addr:postcode":"3128",
    "addr:street":"Familie De Cockstraat",
    "iso:country":"BE",
    "sg:address":"Familie De Cockstraat 31",
    "sg:city":"Tremelo",
    "sg:orig_category":"Rev\u00eatements pour sols and murs",
    "sg:phone":"+32 16 53 12 11",
    "sg:postcode":"3128",
    "sg:province":"Vlaams-Brabant",
    "wof:name":"Van Bael Corcus",
    "wof:placetype":"venue"
},
  "geometry": {"coordinates":[4.7413849831,50.9930839539],"type":"Point"}
}