{
  "type": "Feature",
  "properties": {
    "addr:full":"Kerkstraat 35 Kaprijke (lembeke) Oost-Vlaanderen 9971",
    "addr:housenumber":"35",
    "addr:postcode":"9971",
    "addr:street":"Kerkstraat",
    "iso:country":"BE",
    "sg:address":"Kerkstraat 35",
    "sg:city":"Kaprijke (lembeke)",
    "sg:classifiers":[
        {
            "category":"Manufacturing",
            "subcategory":"Glass & Minerals",
            "type":"Manufacturing & Wholesale Goods"
        }
    ],
    "sg:phone":"+32 9 377 11 74",
    "sg:postcode":"9971",
    "sg:province":"Oost-Vlaanderen",
    "sg:tags":[
        "automobile",
        "-"
    ],
    "wof:name":"Melar Nv",
    "wof:placetype":"venue"
},
  "geometry": {"coordinates":[3.6410830021,51.2012367249],"type":"Point"}
}