{
  "type": "Feature",
  "properties": {
    "addr:full":"Place L'h\u00d4tel De Ville 3 Walcourt Namur 5650",
    "addr:housenumber":"3",
    "addr:postcode":"5650",
    "addr:street":"Place L'Ho \u0302Tel De Ville",
    "iso:country":"BE",
    "sg:address":"Place L'h\u00d4tel De Ville 3",
    "sg:city":"Walcourt",
    "sg:orig_category":"S\u00e9lection de personnel and placement",
    "sg:phone":"+32 71 61 06 17",
    "sg:postcode":"5650",
    "sg:province":"Namur",
    "wof:name":"Ale",
    "wof:placetype":"venue"
},
  "geometry": {"coordinates":[4.4154701233,50.2493095398],"type":"Point"}
}