{
  "type": "Feature",
  "properties": {
    "iso:country":"BE",
    "sg:address":"Rue Jardon 18",
    "sg:city":"Verviers",
    "sg:orig_category":"Newspapers, magazines, periodicals - Publishers",
    "sg:phone":"+32 87 39 39 40",
    "sg:postcode":"4800",
    "sg:province":"Li\u00e8ge",
    "wof:name":"Les Echos Sa",
    "wof:placetype":"venue"
},
  "geometry": {"coordinates":[5.8570590019,50.591255188],"type":"Point"}
}