{
  "type": "Feature",
  "properties": {
    "addr:full":"Avenue De Nivelles 39 Wavre Brabant Wallon 1300",
    "addr:housenumber":"39;1300",
    "addr:street":"Avenue De Nivelles",
    "iso:country":"BE",
    "sg:address":"Avenue De Nivelles 39",
    "sg:city":"Wavre",
    "sg:classifiers":[
        {
            "category":"Insurance",
            "subcategory":"Insurance Agent",
            "type":"Services"
        }
    ],
    "sg:phone":"+32 10 40 02 43",
    "sg:postcode":"1300",
    "sg:province":"Brabant Wallon",
    "sg:tags":[
        "verzekeringsmakelaars",
        "expert"
    ],
    "wof:name":"Fegarbel",
    "wof:placetype":"venue"
},
  "geometry": {"coordinates":[4.6076278687,50.715057373],"type":"Point"}
}