{
  "type": "Feature",
  "properties": {
    "addr:full":"Herpelstraat 13 Zwalm (roborst) Oost-Vlaanderen 9630",
    "addr:housenumber":"13",
    "addr:postcode":"9630",
    "addr:street":"Herpelstraat;Roborst",
    "iso:country":"BE",
    "sg:address":"Herpelstraat 13",
    "sg:city":"Zwalm (roborst)",
    "sg:classifiers":[
        {
            "category":"Home & Garden",
            "subcategory":"Furniture",
            "type":"Retail Goods"
        }
    ],
    "sg:phone":"+32 486 79 29 42",
    "sg:postcode":"9630",
    "sg:province":"Oost-Vlaanderen",
    "sg:tags":[
        "bamboo",
        "cane",
        "wickerwork"
    ],
    "wof:name":"De Spiegeleer",
    "wof:placetype":"venue"
},
  "geometry": {"coordinates":[3.7493829727,50.8692321777],"type":"Point"}
}