{
  "type": "Feature",
  "properties": {
    "iso:country":"BE",
    "sg:address":"Keukeldam 56",
    "sg:city":"Waregem",
    "sg:classifiers":[
        {
            "category":"Professional",
            "subcategory":"Lawyer & Legal Services",
            "type":"Services"
        }
    ],
    "sg:phone":"+32 56 60 04 66",
    "sg:postcode":"8790",
    "sg:province":"West-Vlaanderen",
    "wof:name":"Kestens C",
    "wof:placetype":"venue"
},
  "geometry": {"coordinates":[3.4358930588,50.8877754211],"type":"Point"}
}