{
  "type": "Feature",
  "properties": {
    "iso:country":"BE",
    "sg:address":"Rue C\u00c9lestin-hastir 88",
    "sg:city":"Floreffe",
    "sg:orig_category":"Openbare veiligheid",
    "sg:phone":"+32 81 45 00 06",
    "sg:postcode":"5150",
    "sg:province":"Namur",
    "wof:name":"Police F\u00c9d\u00c9rale/federale Politie",
    "wof:placetype":"venue"
},
  "geometry": {"coordinates":[4.7642378807,50.4433364868],"type":"Point"}
}