{
  "type": "Feature",
  "properties": {
    "addr:full":"Groenplaats 15 Antwerpen Antwerpen 2000",
    "addr:housenumber":"15",
    "addr:postcode":"2000",
    "addr:street":"Groenplaats",
    "iso:country":"BE",
    "sg:address":"Groenplaats 15",
    "sg:city":"Antwerpen",
    "sg:classifiers":[
        {
            "category":"Bars & Pubs",
            "type":"Food & Drink"
        }
    ],
    "sg:phone":"+32 3 232 67 13",
    "sg:postcode":"2000",
    "sg:province":"Antwerpen",
    "wof:name":"Bolleke ('t)",
    "wof:placetype":"venue"
},
  "geometry": {"coordinates":[4.4008831978,51.2197799683],"type":"Point"}
}