{
  "type": "Feature",
  "properties": {
    "addr:full":"Hogeweg 22 Gent Oost-Vlaanderen 9000",
    "addr:housenumber":"22",
    "addr:postcode":"9000",
    "addr:street":"Hogeweg;Oost-Vlaanderen",
    "iso:country":"BE",
    "sg:address":"Hogeweg 22",
    "sg:city":"Gent",
    "sg:classifiers":[
        {
            "category":"Retail",
            "subcategory":"Repair Shop",
            "type":"Services"
        }
    ],
    "sg:phone":"+32 9 251 17 98",
    "sg:postcode":"9000",
    "sg:province":"Oost-Vlaanderen",
    "sg:tags":[
        "upholsterer"
    ],
    "wof:name":"Geldolf M",
    "wof:placetype":"venue"
},
  "geometry": {"coordinates":[3.7470710278,51.0737876892],"type":"Point"}
}