{
  "type": "Feature",
  "properties": {
    "iso:country":"BE",
    "sg:address":"Lijsterstraat 33",
    "sg:city":"Oud-heverlee",
    "sg:orig_category":"Diverse bouwafwerking and reiniging Gespecialiseerde residenti\u00eble bouw",
    "sg:phone":"+32 16 40 35 55",
    "sg:postcode":"3052",
    "sg:province":"Vlaams-Brabant",
    "wof:name":"All Construct",
    "wof:placetype":"venue"
},
  "geometry": {"coordinates":[4.7032752037,50.8238372803],"type":"Point"}
}