{
  "type": "Feature",
  "properties": {
    "iso:country":"BE",
    "sg:address":"Bois Du Chap\u00eetre 13",
    "sg:city":"Ittre",
    "sg:classifiers":[
        {
            "category":"Professional",
            "subcategory":"Employment Agencies",
            "type":"Services"
        }
    ],
    "sg:phone":"+32 67 64 88 48",
    "sg:postcode":"1460",
    "sg:province":"Brabant Wallon",
    "sg:tags":[
        "-",
        "processing",
        "data"
    ],
    "wof:name":"Data Movers",
    "wof:placetype":"venue"
},
  "geometry": {"coordinates":[4.2448439598,50.6613616943],"type":"Point"}
}