{
  "type": "Feature",
  "properties": {
    "iso:country":"BE",
    "sg:address":"Rue De L'ornoy 26",
    "sg:city":"Mont-saint-guibert",
    "sg:orig_category":"Peinture. Rev\u00eatements pour sols and murs",
    "sg:phone":"+32 10 65 83 10",
    "sg:postcode":"1435",
    "sg:province":"Brabant Wallon",
    "wof:name":"T R A D I - P E I N T",
    "wof:placetype":"venue"
},
  "geometry": {"coordinates":[4.6066842079,50.6319313049],"type":"Point"}
}