{
  "type": "Feature",
  "properties": {
    "iso:country":"BE",
    "sg:address":"Stationsstraat 27",
    "sg:city":"Aalter",
    "sg:orig_category":"Meubelzaken, woning- and keukeninrichting",
    "sg:phone":"+32 9 374 33 38",
    "sg:postcode":"9880",
    "sg:province":"Oost-Vlaanderen",
    "wof:name":"Alphonse Goeminne",
    "wof:placetype":"venue"
},
  "geometry": {"coordinates":[3.4479730129,51.0850563049],"type":"Point"}
}