{
  "type": "Feature",
  "properties": {
    "iso:country":"BE",
    "sg:address":"Rue Haut Vin\u00e2ve 5",
    "sg:city":"Seraing (jemeppe-sur-meuse)",
    "sg:classifiers":[
        {
            "category":"Professional",
            "subcategory":"Advertising",
            "type":"Services"
        }
    ],
    "sg:phone":"+32 4 234 94 84",
    "sg:postcode":"4101",
    "sg:province":"Li\u00e8ge",
    "sg:tags":[
        "bill",
        "-",
        "posting"
    ],
    "wof:name":"Vison-visu",
    "wof:placetype":"venue"
},
  "geometry": {"coordinates":[5.5043420792,50.6159477234],"type":"Point"}
}