{
  "type": "Feature",
  "properties": {
    "addr:full":"Molenstraat 26 Oosterzele Oost-Vlaanderen 9860",
    "addr:housenumber":"26",
    "addr:postcode":"9860",
    "addr:street":"Molenstraat;Oost-Vlaanderen",
    "iso:country":"BE",
    "sg:address":"Molenstraat 26",
    "sg:city":"Oosterzele",
    "sg:orig_category":"Postkantoren Verzekeringsmakelaars and experts",
    "sg:phone":"+32 9 362 55 57",
    "sg:postcode":"9860",
    "sg:province":"Oost-Vlaanderen",
    "wof:name":"De Post",
    "wof:placetype":"venue"
},
  "geometry": {"coordinates":[3.7977919579,50.9227371216],"type":"Point"}
}