{
  "type": "Feature",
  "properties": {
    "iso:country":"BE",
    "sg:address":"Ledehof 52",
    "sg:city":"Lokeren",
    "sg:classifiers":[
        {
            "category":"Real Estate",
            "subcategory":"Surveying",
            "type":"Services"
        }
    ],
    "sg:phone":"+32 9 348 64 72",
    "sg:postcode":"9160",
    "sg:province":"Oost-Vlaanderen",
    "sg:tags":[
        "surveyor",
        "land"
    ],
    "wof:name":"Van Doorsselaere H",
    "wof:placetype":"venue"
},
  "geometry": {"coordinates":[3.9682769775,51.0999946594],"type":"Point"}
}