{
  "type": "Feature",
  "properties": {
    "addr:full":"Chauss\u00c9e D'alsemberg 480 Ukkel/uccle Bruxelles-Capitale 1180",
    "addr:housenumber":"480",
    "addr:postcode":"1180",
    "addr:street":"Chausse\u0301E D'Alsemberg;/",
    "iso:country":"BE",
    "sg:address":"Chauss\u00c9e D'alsemberg 480",
    "sg:city":"Ukkel/uccle",
    "sg:orig_category":"Fleurs and plantes",
    "sg:phone":"+32 2 343 69 73",
    "sg:postcode":"1180",
    "sg:province":"Bruxelles-Capitale",
    "wof:name":"Desir Floral",
    "wof:placetype":"venue"
},
  "geometry": {"coordinates":[4.3377189636,50.8100585938],"type":"Point"}
}