{
  "type": "Feature",
  "properties": {
    "iso:country":"BE",
    "sg:address":"Bondgenotenstraat 316",
    "sg:city":"Vorst/forest",
    "sg:orig_category":"Technisch and beroeps secundair onderwijs",
    "sg:phone":"+32 2 735 81 10",
    "sg:postcode":"1190",
    "sg:province":"Bruxelles-Capitale",
    "wof:name":"Institut St.joseph",
    "wof:placetype":"venue"
},
  "geometry": {"coordinates":[4.3273878098,50.8237533569],"type":"Point"}
}