{
  "type": "Feature",
  "properties": {
    "addr:full":"Avenue Joseph Wuidar 78 Seraing (ougr\u00e9e) Li\u00e8ge 4102",
    "addr:housenumber":"78",
    "addr:postcode":"4102",
    "addr:street":"Avenue Joseph Wuidar",
    "iso:country":"BE",
    "sg:address":"Avenue Joseph Wuidar 78",
    "sg:city":"Seraing (ougr\u00e9e)",
    "sg:classifiers":[
        {
            "category":"Personal",
            "subcategory":"Beauty Salon",
            "type":"Services"
        }
    ],
    "sg:phone":"+32 4 336 46 44",
    "sg:postcode":"4102",
    "sg:province":"Li\u00e8ge",
    "sg:tags":[
        "lady",
        "-",
        "hairdressing"
    ],
    "wof:name":"Dany",
    "wof:placetype":"venue"
},
  "geometry": {"coordinates":[5.5415048599,50.5881538391],"type":"Point"}
}