{
  "type": "Feature",
  "properties": {
    "iso:country":"BE",
    "sg:address":"Chemin Des Rieux De Perquiesse 3",
    "sg:city":"Ath (rebaix)",
    "sg:classifiers":[
        {
            "category":"Bakery",
            "type":"Food & Drink"
        }
    ],
    "sg:phone":"+32 68 33 53 78",
    "sg:postcode":"7804",
    "sg:province":"Hainaut",
    "sg:tags":[
        "confectioner",
        "baker"
    ],
    "wof:name":"Chevrebaix",
    "wof:placetype":"venue"
},
  "geometry": {"coordinates":[3.7832849026,50.6607551575],"type":"Point"}
}