{
  "type": "Feature",
  "properties": {
    "addr:full":"Kerkstraat 34 De Haan West-Vlaanderen 8420",
    "addr:housenumber":"34",
    "addr:postcode":"8420",
    "addr:street":"Kerkstraat",
    "iso:country":"BE",
    "sg:address":"Kerkstraat 34",
    "sg:city":"De Haan",
    "sg:orig_category":"Catering and organisatie van feesten Hotels Restaurants Ruimtes voor conferenties, recepties and fee",
    "sg:phone":"+32 50 41 36 90",
    "sg:postcode":"8420",
    "sg:province":"West-Vlaanderen",
    "wof:name":"Odette",
    "wof:placetype":"venue"
},
  "geometry": {"coordinates":[3.0805940628,51.3001899719],"type":"Point"}
}