{
  "type": "Feature",
  "properties": {
    "iso:country":"BE",
    "sg:address":"Rue Du Cimeti\u00c8re 4",
    "sg:city":"Awans",
    "sg:classifiers":[
        {
            "category":"Arena",
            "subcategory":"Sports Club",
            "type":"Entertainment"
        }
    ],
    "sg:phone":"+32 4 257 58 27",
    "sg:postcode":"4340",
    "sg:province":"Li\u00e8ge",
    "sg:tags":[
        "de"
    ],
    "wof:name":"P.c. Li\u00c8ge Citadelle",
    "wof:placetype":"venue"
},
  "geometry": {"coordinates":[5.4676251411,50.715713501],"type":"Point"}
}