{
  "type": "Feature",
  "properties": {
    "iso:country":"BE",
    "sg:address":"Rue De La Scierie 15a",
    "sg:city":"L\u00c9glise",
    "sg:orig_category":"Kapsalons",
    "sg:phone":"+32 63 60 15 05",
    "sg:postcode":"6860",
    "sg:province":"Luxembourg",
    "wof:name":"Coiffure Franc Style",
    "wof:placetype":"venue"
},
  "geometry": {"coordinates":[5.5934262276,49.8546333313],"type":"Point"}
}