{
  "type": "Feature",
  "properties": {
    "iso:country":"BE",
    "sg:address":"Av Du Football 1",
    "sg:city":"Bruxelles",
    "sg:classifiers":[
        {
            "category":"Professional",
            "subcategory":"Business Services",
            "type":"Services"
        }
    ],
    "sg:phone":"+32 2 474 13 11",
    "sg:postcode":"1020",
    "sg:province":"Bruxelles-Capitale",
    "sg:tags":[
        "travel",
        "fair"
    ],
    "wof:name":"Mini Europe Sa",
    "wof:placetype":"venue"
},
  "geometry": {"coordinates":[4.3369650841,50.8939399719],"type":"Point"}
}