{
  "type": "Feature",
  "properties": {
    "iso:country":"BE",
    "sg:address":"Brugsesteenweg 68-70",
    "sg:city":"Harelbeke (hulste)",
    "sg:classifiers":[
        {
            "category":"Building & Trades",
            "subcategory":"Electrical",
            "type":"Services"
        }
    ],
    "sg:phone":"+32 51 30 04 16",
    "sg:postcode":"8531",
    "sg:province":"West-Vlaanderen",
    "sg:tags":[
        "tool",
        "electric"
    ],
    "wof:name":"De Bruyne Nv",
    "wof:placetype":"venue"
},
  "geometry": {"coordinates":[3.2692689896,50.8941230774],"type":"Point"}
}