{
  "type": "Feature",
  "properties": {
    "iso:country":"BE",
    "sg:address":"Koningin Elisabethlaan 10",
    "sg:city":"Sint-niklaas",
    "sg:orig_category":"Orphelinats. Instituts pour enfants en difficult\u00e9",
    "sg:phone":"+32 3 766 12 96",
    "sg:postcode":"9100",
    "sg:province":"Oost-Vlaanderen",
    "wof:name":"Dagcentrum Triangel",
    "wof:placetype":"venue"
},
  "geometry": {"coordinates":[4.1527380943,51.1715240479],"type":"Point"}
}