{
  "type": "Feature",
  "properties": {
    "addr:full":"Rue De Marche 43 Bastogne Luxembourg 6600",
    "addr:housenumber":"43",
    "addr:postcode":"6600",
    "addr:street":"Rue De Marche",
    "iso:country":"BE",
    "sg:address":"Rue De Marche 43",
    "sg:city":"Bastogne",
    "sg:classifiers":[
        {
            "category":"Taxi",
            "type":"Transportation"
        }
    ],
    "sg:phone":"+32 61 21 10 60",
    "sg:postcode":"6600",
    "sg:province":"Luxembourg",
    "sg:tags":[
        "taxicab"
    ],
    "wof:name":"Gaudron M",
    "wof:placetype":"venue"
},
  "geometry": {"coordinates":[5.7119350433,50.0015258789],"type":"Point"}
}