{
  "type": "Feature",
  "properties": {
    "addr:full":"Rechtstraat 347 Lokeren Oost-Vlaanderen 9160",
    "addr:housenumber":"347",
    "addr:postcode":"9160",
    "addr:street":"Rechtstraat",
    "iso:country":"BE",
    "sg:address":"Rechtstraat 347",
    "sg:city":"Lokeren",
    "sg:orig_category":"Installation de menuiserie en bois and plastique",
    "sg:phone":"+32 9 346 98 81",
    "sg:postcode":"9160",
    "sg:province":"Oost-Vlaanderen",
    "wof:name":"Dhooge",
    "wof:placetype":"venue"
},
  "geometry": {"coordinates":[3.9864850044,51.1047401428],"type":"Point"}
}