{
  "type": "Feature",
  "properties": {
    "iso:country":"BE",
    "sg:address":"Schuiterstraat 35",
    "sg:city":"Gent (drongen)",
    "sg:classifiers":[
        {
            "category":"Health Services",
            "subcategory":"Health Practitioner",
            "type":"Services"
        }
    ],
    "sg:phone":"+32 9 236 60 20",
    "sg:postcode":"9031",
    "sg:province":"Oost-Vlaanderen",
    "sg:tags":[
        "physiotherapist"
    ],
    "wof:name":"Vyncke Mien",
    "wof:placetype":"venue"
},
  "geometry": {"coordinates":[3.6487839222,51.0470848083],"type":"Point"}
}