{
  "type": "Feature",
  "properties": {
    "iso:country":"BE",
    "sg:address":"Onze-lieve-vrouwestraat 59-63",
    "sg:city":"Mechelen",
    "sg:classifiers":[
        {
            "category":"Home & Garden",
            "subcategory":"Carpets & Floor Coverings",
            "type":"Retail Goods"
        }
    ],
    "sg:phone":"+32 15 42 24 01",
    "sg:postcode":"2800",
    "sg:province":"Antwerpen",
    "sg:tags":[
        "parquet"
    ],
    "wof:name":"Van Der Poorten Bvba",
    "wof:placetype":"venue"
},
  "geometry": {"coordinates":[4.4785442352,51.0239524841],"type":"Point"}
}