{
  "type": "Feature",
  "properties": {
    "addr:full":"Baasrodestraat 1 Lebbeke Oost-Vlaanderen 9280",
    "addr:housenumber":"1",
    "addr:postcode":"9280",
    "addr:street":"Baasrodestraat",
    "iso:country":"BE",
    "sg:address":"Baasrodestraat 1",
    "sg:city":"Lebbeke",
    "sg:orig_category":"Services pour animaux domestiques",
    "sg:phone":"+32 52 41 16 29",
    "sg:postcode":"9280",
    "sg:province":"Oost-Vlaanderen",
    "wof:name":"Nadine Ide",
    "wof:placetype":"venue"
},
  "geometry": {"coordinates":[4.1345171928,51.0053443909],"type":"Point"}
}