{
  "type": "Feature",
  "properties": {
    "iso:country":"BE",
    "sg:address":"Rue Des Bruy\u00e8res 89",
    "sg:city":"Bertrix (assenois)",
    "sg:classifiers":[
        {
            "category":"Building & Trades",
            "subcategory":"Landscaping Services",
            "type":"Services"
        }
    ],
    "sg:phone":"+32 63 43 37 22",
    "sg:postcode":"6860",
    "sg:province":"Luxembourg",
    "sg:tags":[
        "-",
        "lopping",
        "work",
        "tree",
        "felling"
    ],
    "wof:name":"D'ansembourg E",
    "wof:placetype":"venue"
},
  "geometry": {"coordinates":[5.5349779129,49.7996826172],"type":"Point"}
}