{
  "type": "Feature",
  "properties": {
    "iso:country":"BE",
    "sg:address":"Parc Artisanal De Blegny 11-13-c",
    "sg:city":"Barchon",
    "sg:orig_category":"Cd-Rom Data Preparation",
    "sg:phone":"+32 4 387 88 40",
    "sg:postcode":"4671",
    "sg:province":"Li\u00e8ge",
    "wof:name":"Reality Media S.a.",
    "wof:placetype":"venue"
},
  "geometry": {"coordinates":[5.7002310753,50.6576881409],"type":"Point"}
}