{
  "type": "Feature",
  "properties": {
    "addr:full":"Leemweg 71 Sint-laureins Oost-Vlaanderen 9980",
    "addr:housenumber":"71",
    "addr:postcode":"9980",
    "addr:street":"Leemweg",
    "iso:country":"BE",
    "sg:address":"Leemweg 71",
    "sg:city":"Sint-laureins",
    "sg:classifiers":[
        {
            "category":"Real Estate",
            "subcategory":"Architect",
            "type":"Services"
        }
    ],
    "sg:phone":"+32 9 379 94 85",
    "sg:postcode":"9980",
    "sg:province":"Oost-Vlaanderen",
    "wof:name":"Groosman Luc",
    "wof:placetype":"venue"
},
  "geometry": {"coordinates":[3.5222280025,51.2369651794],"type":"Point"}
}