{
  "type": "Feature",
  "properties": {
    "addr:full":"Chauss\u00c9e De Charleroi 15 Namur Namur 5000",
    "addr:housenumber":"15",
    "addr:postcode":"5000",
    "addr:street":"Chausse\u0301E De Charleroi",
    "iso:country":"BE",
    "sg:address":"Chauss\u00c9e De Charleroi 15",
    "sg:city":"Namur",
    "sg:orig_category":"Artsen and specialisten",
    "sg:phone":"+32 81 73 69 34",
    "sg:postcode":"5000",
    "sg:province":"Namur",
    "wof:name":"Jean-claude Dewez",
    "wof:placetype":"venue"
},
  "geometry": {"coordinates":[4.83893013,50.4610786438],"type":"Point"}
}