{
  "type": "Feature",
  "properties": {
    "iso:country":"BE",
    "sg:address":"Place De La Coll\u00e9giale 5",
    "sg:city":"Vis\u00e9",
    "sg:classifiers":[
        {
            "category":"Health Services",
            "subcategory":"Health Practitioner",
            "type":"Services"
        }
    ],
    "sg:phone":"+32 4 379 30 36",
    "sg:postcode":"4600",
    "sg:province":"Li\u00e8ge",
    "sg:tags":[
        "physiotherapist"
    ],
    "wof:name":"Mullenders Ghislaine",
    "wof:placetype":"venue"
},
  "geometry": {"coordinates":[5.695731163,50.7334594727],"type":"Point"}
}