{
  "type": "Feature",
  "properties": {
    "addr:full":"Rue M Duchatto 29-31 Herstal Li\u00e8ge 4040",
    "addr:postcode":"29-31;4040",
    "addr:street":"Rue M Duchatto",
    "iso:country":"BE",
    "sg:address":"Rue M Duchatto 29-31",
    "sg:city":"Herstal",
    "sg:orig_category":"SMEEDWERK, METAALBEWERKING AND POEDERMETALLURGIE",
    "sg:phone":"+32 4 264 26 35",
    "sg:postcode":"4040",
    "sg:province":"Li\u00e8ge",
    "wof:name":"Ferolux",
    "wof:placetype":"venue"
},
  "geometry": {"coordinates":[5.6226520538,50.6573181152],"type":"Point"}
}