{
  "type": "Feature",
  "properties": {
    "iso:country":"BE",
    "sg:address":"Avenue Rogier 109",
    "sg:city":"Bruxelles (schaerbeek)",
    "sg:classifiers":[
        {
            "category":"Communications",
            "subcategory":"Film & Video Production",
            "type":"Services"
        }
    ],
    "sg:phone":"+32 2 245 46 61",
    "sg:postcode":"1030",
    "sg:province":"Bruxelles-Capitale",
    "sg:tags":[
        "hiring",
        "-"
    ],
    "wof:name":"Fun Vid\u00e9o Top Sprl",
    "wof:placetype":"venue"
},
  "geometry": {"coordinates":[4.3767127991,50.8594703674],"type":"Point"}
}