{
  "type": "Feature",
  "properties": {
    "iso:country":"BE",
    "sg:address":"Doorniksesteenweg 338",
    "sg:city":"Avelgem",
    "sg:classifiers":[
        {
            "category":"Bars & Pubs",
            "type":"Food & Drink"
        }
    ],
    "sg:phone":"+32 56 64 50 18",
    "sg:postcode":"8580",
    "sg:province":"West-Vlaanderen",
    "wof:name":"Garage",
    "wof:placetype":"venue"
},
  "geometry": {"coordinates":[3.4399769306,50.7645187378],"type":"Point"}
}