{
  "type": "Feature",
  "properties": {
    "addr:full":"Rue De Marcinelle 87 Charleroi Hainaut 6000",
    "addr:housenumber":"87",
    "addr:postcode":"6000",
    "addr:street":"Rue De Marcinelle;Hainaut",
    "iso:country":"BE",
    "sg:address":"Rue De Marcinelle 87",
    "sg:city":"Charleroi",
    "sg:classifiers":[
        {
            "category":"Shopping",
            "subcategory":"Pets & Pet Supplies",
            "type":"Retail Goods"
        }
    ],
    "sg:phone":"+32 71 31 24 70",
    "sg:postcode":"6000",
    "sg:province":"Hainaut",
    "sg:tags":[
        "aquarium",
        "accessory"
    ],
    "wof:name":"Aqua Fish",
    "wof:placetype":"venue"
},
  "geometry": {"coordinates":[4.4462900162,50.4055023193],"type":"Point"}
}