{
  "type": "Feature",
  "properties": {
    "addr:full":"Scheldestraat 29 Nazareth (eke) Oost-Vlaanderen 9810",
    "addr:housenumber":"29",
    "addr:postcode":"9810",
    "addr:street":"Scheldestraat",
    "iso:country":"BE",
    "sg:address":"Scheldestraat 29",
    "sg:city":"Nazareth (eke)",
    "sg:classifiers":[
        {
            "category":"Wholesale",
            "subcategory":"Books, Periodicals, & Newspapers",
            "type":"Manufacturing & Wholesale Goods"
        }
    ],
    "sg:phone":"+32 9 384 52 96",
    "sg:postcode":"9810",
    "sg:province":"Oost-Vlaanderen",
    "sg:tags":[
        "publisher"
    ],
    "wof:name":"Industrie Advertenties",
    "wof:placetype":"venue"
},
  "geometry": {"coordinates":[3.6404440403,50.9451179504],"type":"Point"}
}