{
  "type": "Feature",
  "properties": {
    "addr:full":"Phoenixstraat 73 Gent Oost-Vlaanderen 9000",
    "addr:housenumber":"73",
    "addr:postcode":"9000",
    "addr:street":"Phoenixstraat;Oost-Vlaanderen",
    "iso:country":"BE",
    "sg:address":"Phoenixstraat 73",
    "sg:city":"Gent",
    "sg:orig_category":"Bloemen and planten",
    "sg:phone":"+32 9 227 26 47",
    "sg:postcode":"9000",
    "sg:province":"Oost-Vlaanderen",
    "wof:name":"Huis Blue-nimf",
    "wof:placetype":"venue"
},
  "geometry": {"coordinates":[3.7054278851,51.058139801],"type":"Point"}
}