{
  "type": "Feature",
  "properties": {
    "iso:country":"BE",
    "sg:address":"Leuvensesteenweg 53",
    "sg:city":"Zaventem (sint-stevens-woluwe)",
    "sg:classifiers":[
        {
            "category":"Retail",
            "subcategory":"Auto Repair",
            "type":"Services"
        }
    ],
    "sg:phone":"+32 2 720 76 59",
    "sg:postcode":"1932",
    "sg:province":"Vlaams-Brabant",
    "sg:tags":[
        "garage"
    ],
    "wof:name":"Saint Michel Cars Sprl",
    "wof:placetype":"venue"
},
  "geometry": {"coordinates":[4.4675021172,50.8715705872],"type":"Point"}
}