{
  "type": "Feature",
  "properties": {
    "iso:country":"BE",
    "sg:address":"Gruitroderstraat 45",
    "sg:city":"Bree",
    "sg:orig_category":"Advocaten and juridische adviseurs",
    "sg:phone":"+32 89 46 32 89",
    "sg:postcode":"3960",
    "sg:province":"Limburg",
    "wof:name":"Leo Deckers",
    "wof:placetype":"venue"
},
  "geometry": {"coordinates":[5.5948958397,51.1347541809],"type":"Point"}
}