{
  "type": "Feature",
  "properties": {
    "addr:full":"Willekensmolenstraat 120 Hasselt Limburg 3500",
    "addr:housenumber":"120",
    "addr:postcode":"3500",
    "addr:street":"Willekensmolenstraat",
    "iso:country":"BE",
    "sg:address":"Willekensmolenstraat 120",
    "sg:city":"Hasselt",
    "sg:orig_category":"Protection civile",
    "sg:phone":"+32 11 22 49 26",
    "sg:postcode":"3500",
    "sg:province":"Limburg",
    "wof:name":"Brandweerkazerne",
    "wof:placetype":"venue"
},
  "geometry": {"coordinates":[5.3510160446,50.9323120117],"type":"Point"}
}