{
  "type": "Feature",
  "properties": {
    "iso:country":"BE",
    "sg:address":"Keienvenstraat 43",
    "sg:city":"Wuustwezel",
    "sg:classifiers":[
        {
            "category":"Home & Garden",
            "subcategory":"Home Furnishings",
            "type":"Retail Goods"
        }
    ],
    "sg:phone":"+32 3 663 19 21",
    "sg:postcode":"2990",
    "sg:province":"Antwerpen",
    "sg:tags":[
        "interior",
        "decoration"
    ],
    "wof:name":"Lambrechts L Bvba",
    "wof:placetype":"venue"
},
  "geometry": {"coordinates":[4.547273159,51.3486785889],"type":"Point"}
}