{
  "type": "Feature",
  "properties": {
    "addr:full":"Keizerslaan 3 Brussel/bruxelles Bruxelles-Capitale 1000",
    "addr:housenumber":"3",
    "addr:postcode":"1000",
    "addr:street":"Keizerslaan;/",
    "iso:country":"BE",
    "sg:address":"Keizerslaan 3",
    "sg:city":"Brussel/bruxelles",
    "sg:orig_category":"Advocaten and juridische adviseurs",
    "sg:phone":"+32 2 551 15 15",
    "sg:postcode":"1000",
    "sg:province":"Bruxelles-Capitale",
    "wof:name":"O. Neirynck",
    "wof:placetype":"venue"
},
  "geometry": {"coordinates":[4.3546919823,50.8438568115],"type":"Point"}
}