{
  "type": "Feature",
  "properties": {
    "addr:full":"Gentsesteenweg 40-44 Zele Oost-Vlaanderen 9240",
    "addr:housenumber":"40-44",
    "addr:postcode":"9240",
    "addr:street":"Gentsesteenweg",
    "iso:country":"BE",
    "sg:address":"Gentsesteenweg 40-44",
    "sg:city":"Zele",
    "sg:orig_category":"Supermarch\u00e9s",
    "sg:postcode":"9240",
    "sg:province":"Oost-Vlaanderen",
    "wof:name":"Aldi",
    "wof:placetype":"venue"
},
  "geometry": {"coordinates":[4.023501873,51.0626449585],"type":"Point"}
}