{
  "type": "Feature",
  "properties": {
    "addr:full":"Rue Sainte-germaine 119 Mouscron Hainaut 7700",
    "addr:housenumber":"119",
    "addr:postcode":"7700",
    "addr:street":"Rue Sainte-Germaine",
    "iso:country":"BE",
    "sg:address":"Rue Sainte-germaine 119",
    "sg:city":"Mouscron",
    "sg:classifiers":[
        {
            "category":"Health Services",
            "subcategory":"Doctor",
            "type":"Services"
        }
    ],
    "sg:phone":"+32 56 33 20 68",
    "sg:postcode":"7700",
    "sg:province":"Hainaut",
    "sg:tags":[
        "medicinephysicians",
        "surgeon"
    ],
    "wof:name":"Marquette Freddy",
    "wof:placetype":"venue"
},
  "geometry": {"coordinates":[3.2087600231,50.7453231812],"type":"Point"}
}