{
  "type": "Feature",
  "properties": {
    "iso:country":"BE",
    "sg:address":"Eendebroekstraat 59",
    "sg:city":"Leuven (wilsele)",
    "sg:classifiers":[
        {
            "category":"Education",
            "subcategory":"Special Training",
            "type":"Public Place"
        }
    ],
    "sg:phone":"+32 16 44 58 37",
    "sg:postcode":"3012",
    "sg:province":"Vlaams-Brabant",
    "sg:tags":[
        "school",
        "flying"
    ],
    "wof:name":"Aircal Bvba",
    "wof:placetype":"venue"
},
  "geometry": {"coordinates":[4.7302122116,50.9298553467],"type":"Point"}
}