{
  "type": "Feature",
  "properties": {
    "iso:country":"BE",
    "sg:address":"Grootzand 133",
    "sg:city":"Dendermonde (grembergen)",
    "sg:classifiers":[
        {
            "category":"Fast Food",
            "type":"Food & Drink"
        }
    ],
    "sg:phone":"+32 52 21 80 27",
    "sg:postcode":"9200",
    "sg:province":"Oost-Vlaanderen",
    "sg:tags":[
        "fried",
        "stand",
        "potato"
    ],
    "wof:name":"Statie",
    "wof:placetype":"venue"
},
  "geometry": {"coordinates":[4.1028909683,51.0417938232],"type":"Point"}
}