{
  "type": "Feature",
  "properties": {
    "addr:full":"Akkerlaan 31 Schoten Antwerpen 2900",
    "addr:housenumber":"31",
    "addr:postcode":"2900",
    "addr:street":"Akkerlaan",
    "iso:country":"BE",
    "sg:address":"Akkerlaan 31",
    "sg:city":"Schoten",
    "sg:classifiers":[
        {
            "category":"Real Estate",
            "subcategory":"Surveying",
            "type":"Services"
        }
    ],
    "sg:phone":"+32 3 658 88 89",
    "sg:postcode":"2900",
    "sg:province":"Antwerpen",
    "sg:tags":[
        "surveyor",
        "land"
    ],
    "wof:name":"Vermeiren E",
    "wof:placetype":"venue"
},
  "geometry": {"coordinates":[4.5083398819,51.246887207],"type":"Point"}
}