{
  "type": "Feature",
  "properties": {
    "addr:full":"Chauss\u00c9e De Wavre 1268 Auderghem Bruxelles-Capitale 1160",
    "addr:postcode":"1268;1160",
    "addr:street":"Chausse\u0301E De Wavre",
    "iso:country":"BE",
    "sg:address":"Chauss\u00c9e De Wavre 1268",
    "sg:city":"Auderghem",
    "sg:orig_category":"R\u00e9parations \u00e0 domicile d'appareils \u00e9lectriques. R\u00e9parations d'appareils \u00e9lectrom\u00e9nagers",
    "sg:phone":"+32 2 673 89 89",
    "sg:postcode":"1160",
    "sg:province":"Bruxelles-Capitale",
    "wof:name":"Tobie",
    "wof:placetype":"venue"
},
  "geometry": {"coordinates":[4.4098157883,50.8206863403],"type":"Point"}
}