{
  "type": "Feature",
  "properties": {
    "addr:full":"Chauss\u00c9e De Theux 55 (super Gb) Verviers Li\u00e8ge 4802",
    "addr:housenumber":"55",
    "addr:postcode":"4802",
    "addr:street":"Chausse\u0301E De Theux",
    "iso:country":"BE",
    "sg:address":"Chauss\u00c9e De Theux 55 (super Gb)",
    "sg:city":"Verviers",
    "sg:orig_category":"Kapsalons",
    "sg:phone":"+32 87 23 11 61",
    "sg:postcode":"4802",
    "sg:province":"Li\u00e8ge",
    "wof:name":"Coiffure Gentry",
    "wof:placetype":"venue"
},
  "geometry": {"coordinates":[5.8671250343,50.5714111328],"type":"Point"}
}