{
  "type": "Feature",
  "properties": {
    "addr:full":"Avenue Des Sapins 21 Mons Hainaut 7020",
    "addr:housenumber":"21",
    "addr:postcode":"7020",
    "addr:street":"Avenue Des Sapins;Hainaut",
    "iso:country":"BE",
    "sg:address":"Avenue Des Sapins 21",
    "sg:city":"Mons",
    "sg:classifiers":[
        {
            "category":"Cafe",
            "type":"Food & Drink"
        }
    ],
    "sg:phone":"+32 65 33 85 22",
    "sg:postcode":"7020",
    "sg:province":"Hainaut",
    "sg:tags":[
        "caf\u00e9s"
    ],
    "wof:name":"Caf\u00c9 Le Moderne",
    "wof:placetype":"venue"
},
  "geometry": {"coordinates":[3.9553449154,50.4761772156],"type":"Point"}
}