{
  "type": "Feature",
  "properties": {
    "iso:country":"BE",
    "sg:address":"Place Capitaine-mostenne 13",
    "sg:city":"Marche-en-famenne",
    "sg:orig_category":"Enseignement maternel and primaire",
    "sg:phone":"+32 84 21 12 10",
    "sg:postcode":"6900",
    "sg:province":"Luxembourg",
    "wof:name":"Ecole Fondamentale Libre",
    "wof:placetype":"venue"
},
  "geometry": {"coordinates":[5.2869868279,50.1723747253],"type":"Point"}
}