{
  "type": "Feature",
  "properties": {
    "iso:country":"BE",
    "sg:address":"Scheldemolenstraat 0",
    "sg:city":"Beveren",
    "sg:classifiers":[
        {
            "category":"Building & Trades",
            "subcategory":"Electrical",
            "type":"Services"
        }
    ],
    "sg:phone":"+32 78 35 35 35",
    "sg:postcode":"9130",
    "sg:province":"Oost-Vlaanderen",
    "sg:tags":[
        "distribution",
        "production",
        "d'\u00e9lectricit\u00e9"
    ],
    "wof:name":"Electrabel Doel",
    "wof:placetype":"venue"
},
  "geometry": {"coordinates":[4.2646250725,51.3149909973],"type":"Point"}
}