{
  "type": "Feature",
  "properties": {
    "iso:country":"BE",
    "sg:address":"Avenue Jean Derave 12",
    "sg:city":"Binche",
    "sg:classifiers":[
        {
            "category":"Building & Trades",
            "subcategory":"Equipment Rental",
            "type":"Services"
        }
    ],
    "sg:phone":"+32 64 37 05 62",
    "sg:postcode":"7130",
    "sg:province":"Hainaut",
    "sg:tags":[
        "safety",
        "collective",
        "individual",
        "-"
    ],
    "wof:name":"Cordier D",
    "wof:placetype":"venue"
},
  "geometry": {"coordinates":[4.1728510857,50.4099464417],"type":"Point"}
}