{
  "type": "Feature",
  "properties": {
    "addr:full":"Sint-trudoplein 7 Houthalen-helchteren (helchteren) Limburg 3530",
    "addr:housenumber":"7",
    "addr:postcode":"3530",
    "addr:street":"Sint-Trudoplein",
    "iso:country":"BE",
    "sg:address":"Sint-trudoplein 7",
    "sg:city":"Houthalen-helchteren (helchteren)",
    "sg:classifiers":[
        {
            "category":"Shopping",
            "subcategory":"Bicycles & Sporting Goods",
            "type":"Retail Goods"
        }
    ],
    "sg:phone":"+32 11 52 14 38",
    "sg:postcode":"3530",
    "sg:province":"Limburg",
    "sg:tags":[
        "-"
    ],
    "wof:name":"Vanharen (fietsen)",
    "wof:placetype":"venue"
},
  "geometry": {"coordinates":[5.3719201088,51.0310020447],"type":"Point"}
}