{
  "type": "Feature",
  "properties": {
    "addr:full":"Leermarkt 14 Mechelen Antwerpen 2800",
    "addr:housenumber":"14",
    "addr:postcode":"2800",
    "addr:street":"Leermarkt",
    "iso:country":"BE",
    "sg:address":"Leermarkt 14",
    "sg:city":"Mechelen",
    "sg:classifiers":[
        {
            "category":"Parking",
            "subcategory":"Bicycle",
            "type":"Transportation"
        }
    ],
    "sg:phone":"+32 15 21 19 38",
    "sg:postcode":"2800",
    "sg:province":"Antwerpen",
    "sg:tags":[
        "chiropodist"
    ],
    "wof:name":"Van Den Camp A",
    "wof:placetype":"venue"
},
  "geometry": {"coordinates":[4.4823770523,51.0263404846],"type":"Point"}
}