{
  "type": "Feature",
  "properties": {
    "addr:full":"Centrum 17 Herne Vlaams-Brabant 1540",
    "addr:housenumber":"17",
    "addr:postcode":"1540",
    "addr:street":"Centrum",
    "iso:country":"BE",
    "sg:address":"Centrum 17",
    "sg:city":"Herne",
    "sg:orig_category":"Openbare veiligheid",
    "sg:phone":"+32 2 396 17 31",
    "sg:postcode":"1540",
    "sg:province":"Vlaams-Brabant",
    "wof:name":"Federale Politie",
    "wof:placetype":"venue"
},
  "geometry": {"coordinates":[4.0285181999,50.7248878479],"type":"Point"}
}