{
  "type": "Feature",
  "properties": {
    "addr:full":"Rue Aux Oies 7 Ouffet Li\u00e8ge 4590",
    "addr:housenumber":"7",
    "addr:postcode":"4590",
    "addr:street":"Rue Aux Oies",
    "iso:country":"BE",
    "sg:address":"Rue Aux Oies 7",
    "sg:city":"Ouffet",
    "sg:orig_category":"Rundveehouders",
    "sg:phone":"+32 86 36 67 03",
    "sg:postcode":"4590",
    "sg:province":"Li\u00e8ge",
    "wof:name":"Charles Defays",
    "wof:placetype":"venue"
},
  "geometry": {"coordinates":[5.457611084,50.4387016296],"type":"Point"}
}