{
  "type": "Feature",
  "properties": {
    "iso:country":"BE",
    "sg:address":"Avenue Des Ormeaux 24b3",
    "sg:city":"Ukkel/uccle",
    "sg:classifiers":[
        {
            "category":"Arena",
            "subcategory":"Sports Club",
            "type":"Entertainment"
        }
    ],
    "sg:phone":"+32 2 344 98 72",
    "sg:postcode":"1180",
    "sg:province":"Bruxelles-Capitale",
    "sg:tags":[
        "de"
    ],
    "wof:name":"P.c. Uccle Centre",
    "wof:placetype":"venue"
},
  "geometry": {"coordinates":[4.3478617668,50.811126709],"type":"Point"}
}