{
  "type": "Feature",
  "properties": {
    "iso:country":"BE",
    "sg:address":"Dorpsstraat 25",
    "sg:city":"Herk-de-stad",
    "sg:orig_category":"Paramedische behandelingen",
    "sg:phone":"+32 13 44 28 67",
    "sg:postcode":"3540",
    "sg:province":"Limburg",
    "wof:name":"N. Kimps",
    "wof:placetype":"venue"
},
  "geometry": {"coordinates":[5.1339859962,50.9387283325],"type":"Point"}
}