{
  "type": "Feature",
  "properties": {
    "iso:country":"BE",
    "sg:address":"Avenue Du Capricorne 199",
    "sg:city":"Bruxelles",
    "sg:orig_category":"Centres sportifs",
    "sg:phone":"+32 2 772 62 49",
    "sg:postcode":"1200",
    "sg:province":"Bruxelles-Capitale",
    "wof:name":"Yoga Club",
    "wof:placetype":"venue"
},
  "geometry": {"coordinates":[4.4217729568,50.8534812927],"type":"Point"}
}