{
  "type": "Feature",
  "properties": {
    "iso:country":"BE",
    "sg:address":"Jozef De Bomstraat 59",
    "sg:city":"Antwerpen",
    "sg:classifiers":[
        {
            "category":"Real Estate",
            "subcategory":"Architect",
            "type":"Services"
        }
    ],
    "sg:phone":"+32 3 216 10 65",
    "sg:postcode":"2018",
    "sg:province":"Antwerpen",
    "wof:name":"Marrannes J",
    "wof:placetype":"venue"
},
  "geometry": {"coordinates":[4.4061551094,51.2063941956],"type":"Point"}
}