{
  "type": "Feature",
  "properties": {
    "addr:full":"Luikerstraat 47 Sint-truiden Limburg 3800",
    "addr:housenumber":"47",
    "addr:postcode":"3800",
    "addr:street":"Luikerstraat",
    "iso:country":"BE",
    "sg:address":"Luikerstraat 47",
    "sg:city":"Sint-truiden",
    "sg:orig_category":"Mat\u00e9riel de T\u00e9l\u00e9communication",
    "sg:phone":"+32 11 48 56 98",
    "sg:postcode":"3800",
    "sg:province":"Limburg",
    "wof:name":"Belcompany",
    "wof:placetype":"venue"
},
  "geometry": {"coordinates":[5.1882481575,50.8140449524],"type":"Point"}
}