{
  "type": "Feature",
  "properties": {
    "iso:country":"BE",
    "sg:address":"Tervuursesteenweg 260",
    "sg:city":"Steenokkerzeel",
    "sg:classifiers":[
        {
            "category":"Personal",
            "subcategory":"Beauty Salon",
            "type":"Services"
        }
    ],
    "sg:phone":"+32 2 751 96 91",
    "sg:postcode":"1820",
    "sg:province":"Vlaams-Brabant",
    "sg:tags":[
        "lady",
        "-",
        "hairdressing"
    ],
    "wof:name":"Kappersteam Guy",
    "wof:placetype":"venue"
},
  "geometry": {"coordinates":[4.5036158562,50.9178314209],"type":"Point"}
}