{
  "type": "Feature",
  "properties": {
    "addr:full":"Brugsesteenweg 255 Gent Oost-Vlaanderen 9000",
    "addr:housenumber":"255",
    "addr:postcode":"9000",
    "addr:street":"Brugsesteenweg;Oost-Vlaanderen",
    "iso:country":"BE",
    "sg:address":"Brugsesteenweg 255",
    "sg:city":"Gent",
    "sg:orig_category":"Afval and schroot Gh",
    "sg:phone":"+32 9 226 59 26",
    "sg:postcode":"9000",
    "sg:province":"Oost-Vlaanderen",
    "wof:name":"Andre Poelman",
    "wof:placetype":"venue"
},
  "geometry": {"coordinates":[3.6874558926,51.0668525696],"type":"Point"}
}