{
  "type": "Feature",
  "properties": {
    "addr:full":"Jules Sermonstraat 15 Sint-pieters-leeuw Vlaams-Brabant 1600",
    "addr:housenumber":"15",
    "addr:postcode":"1600",
    "addr:street":"Sermonstraat",
    "iso:country":"BE",
    "sg:address":"Jules Sermonstraat 15",
    "sg:city":"Sint-pieters-leeuw",
    "sg:orig_category":"Enseignement maternel and primaire",
    "sg:phone":"+32 2 377 32 35",
    "sg:postcode":"1600",
    "sg:province":"Vlaams-Brabant",
    "wof:name":"Vrije Lagere School",
    "wof:placetype":"venue"
},
  "geometry": {"coordinates":[4.242910862,50.7774238586],"type":"Point"}
}