{
  "type": "Feature",
  "properties": {
    "addr:full":"Rue Adolphe Bastin 3 Huy Li\u00e8ge 4500",
    "addr:housenumber":"3",
    "addr:postcode":"4500",
    "addr:street":"Rue Adolphe Bastin",
    "iso:country":"BE",
    "sg:address":"Rue Adolphe Bastin 3",
    "sg:city":"Huy",
    "sg:classifiers":[
        {
            "category":"Health Services",
            "subcategory":"Doctor",
            "type":"Services"
        }
    ],
    "sg:phone":"+32 85 23 36 40",
    "sg:postcode":"4500",
    "sg:province":"Li\u00e8ge",
    "sg:tags":[
        "medicinephysicians",
        "surgeon"
    ],
    "wof:name":"Kunsch J-m",
    "wof:placetype":"venue"
},
  "geometry": {"coordinates":[5.2424139977,50.5253219604],"type":"Point"}
}