{
  "type": "Feature",
  "properties": {
    "iso:country":"BE",
    "sg:address":"Liefdestraat 53b3",
    "sg:city":"Tienen",
    "sg:orig_category":"M\u00e9decins and sp\u00e9cialistes",
    "sg:phone":"+32 16 81 77 55",
    "sg:postcode":"3300",
    "sg:province":"Vlaams-Brabant",
    "wof:name":"S. Melchior",
    "wof:placetype":"venue"
},
  "geometry": {"coordinates":[4.9454088211,50.8081741333],"type":"Point"}
}