{
  "type": "Feature",
  "properties": {
    "iso:country":"BE",
    "sg:address":"Rue De La Vall\u00c9e 21",
    "sg:city":"Ham-sur-heure-nalinnes",
    "sg:orig_category":"Technische studies and ingenieursactiviteiten",
    "sg:phone":"+32 71 21 38 53",
    "sg:postcode":"6120",
    "sg:province":"Hainaut",
    "wof:name":"Ledent T",
    "wof:placetype":"venue"
},
  "geometry": {"coordinates":[4.4683938026,50.3431434631],"type":"Point"}
}