{
  "type": "Feature",
  "properties": {
    "addr:full":"Rue Des Alli\u00c9s 46 Charleroi Hainaut 6030",
    "addr:housenumber":"46",
    "addr:postcode":"6030",
    "addr:street":"Rue Des Allie\u0301S;Hainaut",
    "iso:country":"BE",
    "sg:address":"Rue Des Alli\u00c9s 46",
    "sg:city":"Charleroi",
    "sg:classifiers":[
        {
            "category":"Insurance",
            "subcategory":"Life Insurance",
            "type":"Services"
        }
    ],
    "sg:phone":"+32 71 52 47 95",
    "sg:postcode":"6030",
    "sg:province":"Hainaut",
    "sg:tags":[
        "assurance"
    ],
    "wof:name":"Assurances Van Den Berg",
    "wof:placetype":"venue"
},
  "geometry": {"coordinates":[4.3625822067,50.409954071],"type":"Point"}
}