{
  "type": "Feature",
  "properties": {
    "addr:full":"Rue Haute 2 Aubange (athus) Luxembourg 6791",
    "addr:housenumber":"2",
    "addr:postcode":"6791",
    "addr:street":"Rue Haute",
    "iso:country":"BE",
    "sg:address":"Rue Haute 2",
    "sg:city":"Aubange (athus)",
    "sg:classifiers":[
        {
            "category":"Personal",
            "subcategory":"Beauty Salon",
            "type":"Services"
        }
    ],
    "sg:phone":"+32 63 37 16 65",
    "sg:postcode":"6791",
    "sg:province":"Luxembourg",
    "wof:name":"Centre Naturo-esth\u00e9tique",
    "wof:placetype":"venue"
},
  "geometry": {"coordinates":[5.8316249847,49.5617332458],"type":"Point"}
}