{
  "type": "Feature",
  "properties": {
    "addr:full":"Kelbergenstraat 2 Diest Vlaams-Brabant 3290",
    "addr:housenumber":"2",
    "addr:postcode":"3290",
    "addr:street":"Kelbergenstraat",
    "iso:country":"BE",
    "sg:address":"Kelbergenstraat 2",
    "sg:city":"Diest",
    "sg:orig_category":"Boomkwekerijen",
    "sg:phone":"+32 13 32 73 93",
    "sg:postcode":"3290",
    "sg:province":"Vlaams-Brabant",
    "wof:name":"Fa. Dirix-van Bel",
    "wof:placetype":"venue"
},
  "geometry": {"coordinates":[5.0511350632,50.9845848083],"type":"Point"}
}