{
  "type": "Feature",
  "properties": {
    "iso:country":"BE",
    "sg:address":"Rue Des Campeaux 29",
    "sg:city":"Tournai",
    "sg:classifiers":[
        {
            "category":"Social Services",
            "type":"Services"
        }
    ],
    "sg:phone":"+32 69 84 22 52",
    "sg:postcode":"7500",
    "sg:province":"Hainaut",
    "sg:tags":[
        "handicapped",
        "-"
    ],
    "wof:name":"Foyer Jeunes Travailleurs Asbl",
    "wof:placetype":"venue"
},
  "geometry": {"coordinates":[3.3928129673,50.6082305908],"type":"Point"}
}