{
  "type": "Feature",
  "properties": {
    "iso:country":"BE",
    "sg:address":"Edmond Machtenslaan 125",
    "sg:city":"Sint-jans-molenbeek/molenbeek-saint-jean",
    "sg:orig_category":"Artsen and specialisten",
    "sg:phone":"+32 2 410 11 32",
    "sg:postcode":"1080",
    "sg:province":"Bruxelles-Capitale",
    "wof:name":"K. Ilunga",
    "wof:placetype":"venue"
},
  "geometry": {"coordinates":[4.3060641289,50.8509712219],"type":"Point"}
}