{
  "type": "Feature",
  "properties": {
    "addr:full":"Route Des Fagnes 7 Ferrieres Li\u00e8ge 4190",
    "addr:housenumber":"7",
    "addr:postcode":"4190",
    "addr:street":"Route Des Fagnes",
    "iso:country":"BE",
    "sg:address":"Route Des Fagnes 7",
    "sg:city":"Ferrieres",
    "sg:orig_category":"Aanleg van wegen, sportterreinen and vliegvelden Dansscholen Gespecialiseerde residenti\u00eble bouw Huis",
    "sg:phone":"+32 86 40 02 97",
    "sg:postcode":"4190",
    "sg:province":"Li\u00e8ge",
    "wof:name":"Henry Ernest",
    "wof:placetype":"venue"
},
  "geometry": {"coordinates":[5.5863218307,50.4147834778],"type":"Point"}
}