{
  "type": "Feature",
  "properties": {
    "addr:full":"Rijselsestraat 18 Ieper West-Vlaanderen 8900",
    "addr:housenumber":"18",
    "addr:postcode":"8900",
    "addr:street":"Rijselsestraat",
    "iso:country":"BE",
    "sg:address":"Rijselsestraat 18",
    "sg:city":"Ieper",
    "sg:classifiers":[
        {
            "category":"Shopping",
            "subcategory":"Clothing, Apparel, & Fashions",
            "type":"Retail Goods"
        }
    ],
    "sg:phone":"+32 57 20 58 83",
    "sg:postcode":"8900",
    "sg:province":"West-Vlaanderen",
    "sg:tags":[
        "ondergoed",
        "lingerie"
    ],
    "wof:name":"\u00b4t Linnenhuis",
    "wof:placetype":"venue"
},
  "geometry": {"coordinates":[2.8857719898,50.8502502441],"type":"Point"}
}