{
  "type": "Feature",
  "properties": {
    "iso:country":"BE",
    "sg:address":"Bondgenotenlaan 4",
    "sg:city":"Leuven",
    "sg:classifiers":[
        {
            "category":"Government",
            "subcategory":"Fire Station",
            "type":"Public Place"
        }
    ],
    "sg:phone":"+32 16 23 95 85",
    "sg:postcode":"3000",
    "sg:province":"Vlaams-Brabant",
    "sg:tags":[
        "packard",
        "nec",
        "bell"
    ],
    "wof:name":"Exell Leuven",
    "wof:placetype":"venue"
},
  "geometry": {"coordinates":[4.703494072,50.879283905],"type":"Point"}
}