{
  "type": "Feature",
  "properties": {
    "iso:country":"BE",
    "sg:address":"Luttrebruglaan 12",
    "sg:city":"Vorst/forest",
    "sg:orig_category":"Woningbouw",
    "sg:phone":"+32 2 346 60 80",
    "sg:postcode":"1190",
    "sg:province":"Bruxelles-Capitale",
    "wof:name":"Constr. Pereira Mesquita",
    "wof:placetype":"venue"
},
  "geometry": {"coordinates":[4.3211288452,50.8211135864],"type":"Point"}
}