{
  "type": "Feature",
  "properties": {
    "addr:full":"Rue Vandervelde 32 Thuin Hainaut 6534",
    "addr:housenumber":"32",
    "addr:postcode":"6534",
    "addr:street":"Rue Vandervelde",
    "iso:country":"BE",
    "sg:address":"Rue Vandervelde 32",
    "sg:city":"Thuin",
    "sg:orig_category":"M\u00e9decins and sp\u00e9cialistes",
    "sg:phone":"+32 71 56 14 80",
    "sg:postcode":"6534",
    "sg:province":"Hainaut",
    "wof:name":"Sophie Chartier",
    "wof:placetype":"venue"
},
  "geometry": {"coordinates":[4.3528618813,50.342250824],"type":"Point"}
}