{
  "type": "Feature",
  "properties": {
    "addr:full":"Sportstraat 5 Oosterzele Oost-Vlaanderen 9860",
    "addr:housenumber":"5",
    "addr:postcode":"9860",
    "addr:street":"Sportstraat;Oost-Vlaanderen",
    "iso:country":"BE",
    "sg:address":"Sportstraat 5",
    "sg:city":"Oosterzele",
    "sg:classifiers":[
        {
            "category":"Communications",
            "subcategory":"Radio Station",
            "type":"Services"
        }
    ],
    "sg:phone":"+32 9 362 43 33",
    "sg:postcode":"9860",
    "sg:province":"Oost-Vlaanderen",
    "sg:tags":[
        "diffusion",
        "production",
        "de",
        "programme"
    ],
    "wof:name":"Radio Impuls",
    "wof:placetype":"venue"
},
  "geometry": {"coordinates":[3.7941069603,50.940776825],"type":"Point"}
}