{
  "type": "Feature",
  "properties": {
    "addr:full":"Heufkensstraat 146 Zwalm Oost-Vlaanderen 9630",
    "addr:housenumber":"146",
    "addr:postcode":"9630",
    "addr:street":"Heufkensstraat;Oost-Vlaanderen",
    "iso:country":"BE",
    "sg:address":"Heufkensstraat 146",
    "sg:city":"Zwalm",
    "sg:classifiers":[
        {
            "category":"Cafe",
            "type":"Food & Drink"
        }
    ],
    "sg:phone":"+32 55 49 67 89",
    "sg:postcode":"9630",
    "sg:province":"Oost-Vlaanderen",
    "sg:tags":[
        "caf\u00e9s"
    ],
    "wof:name":"Anne-marie De Smet",
    "wof:placetype":"venue"
},
  "geometry": {"coordinates":[3.6985089779,50.8739204407],"type":"Point"}
}