{
  "type": "Feature",
  "properties": {
    "iso:country":"BE",
    "sg:address":"Rue De Verviers 16",
    "sg:city":"Li\u00c8ge",
    "sg:orig_category":"Location d'appareils audio-visuels",
    "sg:phone":"+32 4 341 35 76",
    "sg:postcode":"4020",
    "sg:province":"Li\u00e8ge",
    "wof:name":"S.l.t.",
    "wof:placetype":"venue"
},
  "geometry": {"coordinates":[5.5845761299,50.6232032776],"type":"Point"}
}