{
  "type": "Feature",
  "properties": {
    "addr:full":"Chauss\u00c9e D\u00b4alsemberg 486 Braine-l\u00b4alleud Brabant Wallon 1420",
    "addr:housenumber":"486",
    "addr:postcode":"1420",
    "addr:street":"Chausse\u0301E D\u00b4Alsemberg;Brabant Wallon",
    "iso:country":"BE",
    "sg:address":"Chauss\u00c9e D\u00b4alsemberg 486",
    "sg:city":"Braine-l\u00b4alleud",
    "sg:orig_category":"Herstellingen and onderhoud van auto's",
    "sg:phone":"+32 2 384 47 38",
    "sg:postcode":"1420",
    "sg:province":"Brabant Wallon",
    "wof:name":"De Greef-van Den Bulcke",
    "wof:placetype":"venue"
},
  "geometry": {"coordinates":[4.3510050774,50.7156105042],"type":"Point"}
}