{
  "type": "Feature",
  "properties": {
    "addr:full":"Rue Du Calvaire 57 Verviers Li\u00e8ge 4800",
    "addr:housenumber":"57",
    "addr:postcode":"4800",
    "addr:street":"Rue Du Calvaire",
    "iso:country":"BE",
    "sg:address":"Rue Du Calvaire 57",
    "sg:city":"Verviers",
    "sg:orig_category":"Eleveurs de bovins",
    "sg:phone":"+32 87 33 15 85",
    "sg:postcode":"4800",
    "sg:province":"Li\u00e8ge",
    "wof:name":"Bernard Dourcy",
    "wof:placetype":"venue"
},
  "geometry": {"coordinates":[5.8594508171,50.5917663574],"type":"Point"}
}