{
  "type": "Feature",
  "properties": {
    "addr:full":"De Regenboog 11 Mechelen Antwerpen 2800",
    "addr:housenumber":"11",
    "addr:postcode":"2800",
    "addr:street":"De Regenboog",
    "iso:country":"BE",
    "sg:address":"De Regenboog 11",
    "sg:city":"Mechelen",
    "sg:classifiers":[
        {
            "category":"Building & Trades",
            "subcategory":"Construction",
            "type":"Services"
        }
    ],
    "sg:phone":"+32 15 40 01 00",
    "sg:postcode":"2800",
    "sg:province":"Antwerpen",
    "sg:tags":[
        "ventilating",
        "system"
    ],
    "wof:name":"Somati Psb",
    "wof:placetype":"venue"
},
  "geometry": {"coordinates":[4.4632849693,51.0067939758],"type":"Point"}
}