{
  "type": "Feature",
  "properties": {
    "iso:country":"BE",
    "sg:address":"Rue De La Belle Jardini\u00e8re 383",
    "sg:city":"Li\u00e8ge 1 (angleur)",
    "sg:classifiers":[
        {
            "category":"Communications",
            "subcategory":"Film & Video Production",
            "type":"Services"
        }
    ],
    "sg:phone":"+32 4 361 02 51",
    "sg:postcode":"4031",
    "sg:province":"Li\u00e8ge",
    "sg:tags":[
        "producer",
        "realizators"
    ],
    "wof:name":"Pixanima",
    "wof:placetype":"venue"
},
  "geometry": {"coordinates":[5.5793762207,50.5939712524],"type":"Point"}
}