{
  "type": "Feature",
  "properties": {
    "iso:country":"BE",
    "sg:address":"Iepersteenweg 7",
    "sg:city":"Houthulst (merkem)",
    "sg:classifiers":[
        {
            "category":"Wholesale",
            "subcategory":"Machinery & Supplies",
            "type":"Manufacturing & Wholesale Goods"
        }
    ],
    "sg:phone":"+32 51 54 40 47",
    "sg:postcode":"8650",
    "sg:province":"West-Vlaanderen",
    "sg:tags":[
        "agricultural",
        "tractor"
    ],
    "wof:name":"Maelfeyt L",
    "wof:placetype":"venue"
},
  "geometry": {"coordinates":[2.8693199158,50.9711914062],"type":"Point"}
}