{
  "type": "Feature",
  "properties": {
    "addr:full":"Rue Des Conf\u00e9d\u00e9r\u00e9s 89 Bruxelles Bruxelles-Capitale 1000",
    "addr:housenumber":"89",
    "addr:postcode":"1000",
    "addr:street":"Rue Des Confe\u0301De\u0301Re\u0301S",
    "iso:country":"BE",
    "sg:address":"Rue Des Conf\u00e9d\u00e9r\u00e9s 89",
    "sg:city":"Bruxelles",
    "sg:classifiers":[
        {
            "category":"Food & Beverages",
            "subcategory":"Groceries & Convenience Stores",
            "type":"Retail Goods"
        }
    ],
    "sg:phone":"+32 2 733 25 25",
    "sg:postcode":"1000",
    "sg:province":"Bruxelles-Capitale",
    "sg:tags":[
        "grocer"
    ],
    "wof:name":"Edip Sprl",
    "wof:placetype":"venue"
},
  "geometry": {"coordinates":[4.387362957,50.8481941223],"type":"Point"}
}