{
  "type": "Feature",
  "properties": {
    "addr:full":"Haachtsesteenweg 164b Steenokkerzeel (melsbroek) Vlaams-Brabant 1820",
    "addr:housenumber":"164b",
    "addr:postcode":"1820",
    "addr:street":"Haachtsesteenweg",
    "iso:country":"BE",
    "sg:address":"Haachtsesteenweg 164b",
    "sg:city":"Steenokkerzeel (melsbroek)",
    "sg:classifiers":[
        {
            "category":"Home & Garden",
            "subcategory":"Carpets & Floor Coverings",
            "type":"Retail Goods"
        }
    ],
    "sg:phone":"+32 2 751 42 26",
    "sg:postcode":"1820",
    "sg:province":"Vlaams-Brabant",
    "sg:tags":[
        "tile"
    ],
    "wof:name":"Agma Nv",
    "wof:placetype":"venue"
},
  "geometry": {"coordinates":[4.4942522049,50.916267395],"type":"Point"}
}