{
  "type": "Feature",
  "properties": {
    "addr:full":"Wolvertemsesteenweg 317 Grimbergen Vlaams-Brabant 1850",
    "addr:housenumber":"317",
    "addr:postcode":"1850",
    "addr:street":"Wolvertemsesteenweg",
    "iso:country":"BE",
    "sg:address":"Wolvertemsesteenweg 317",
    "sg:city":"Grimbergen",
    "sg:orig_category":"Meubles D\u00e9taillants, Am\u00e9nagement de B\u00e2timents et de Cuisines. Installation de menuiserie en bois and",
    "sg:phone":"+32 2 269 09 06",
    "sg:postcode":"1850",
    "sg:province":"Vlaams-Brabant",
    "wof:name":"Mafran",
    "wof:placetype":"venue"
},
  "geometry": {"coordinates":[4.350590229,50.9389610291],"type":"Point"}
}