{
  "type": "Feature",
  "properties": {
    "addr:full":"Hijftestraat 8 Lochristi Oost-Vlaanderen 9080",
    "addr:housenumber":"8",
    "addr:postcode":"9080",
    "addr:street":"Hijftestraat",
    "iso:country":"BE",
    "sg:address":"Hijftestraat 8",
    "sg:city":"Lochristi",
    "sg:classifiers":[
        {
            "category":"Building & Trades",
            "subcategory":"Cleaning & Sanitation",
            "type":"Services"
        }
    ],
    "sg:phone":"+32 9 355 11 32",
    "sg:postcode":"9080",
    "sg:province":"Oost-Vlaanderen",
    "sg:tags":[
        "cleaner",
        "window"
    ],
    "wof:name":"Glazenwasserij Lo",
    "wof:placetype":"venue"
},
  "geometry": {"coordinates":[3.8215761185,51.0958366394],"type":"Point"}
}