{
  "type": "Feature",
  "properties": {
    "addr:full":"Meugenslaan 24 Leuven (kessel-lo) Vlaams-Brabant 3010",
    "addr:housenumber":"24",
    "addr:postcode":"3010",
    "addr:street":"Meugenslaan",
    "iso:country":"BE",
    "sg:address":"Meugenslaan 24",
    "sg:city":"Leuven (kessel-lo)",
    "sg:classifiers":[
        {
            "category":"School Buses",
            "type":"Transportation"
        }
    ],
    "sg:phone":"+32 16 29 05 88",
    "sg:postcode":"3010",
    "sg:province":"Vlaams-Brabant",
    "sg:tags":[
        "homeopathy"
    ],
    "wof:name":"Gielis R",
    "wof:placetype":"venue"
},
  "geometry": {"coordinates":[4.7304501534,50.889755249],"type":"Point"}
}