{
  "type": "Feature",
  "properties": {
    "addr:full":"Keizerstraat 35ba Ternat Vlaams-Brabant 1740",
    "addr:housenumber":"35ba",
    "addr:postcode":"1740",
    "addr:street":"Keizerstraat",
    "iso:country":"BE",
    "sg:address":"Keizerstraat 35ba",
    "sg:city":"Ternat",
    "sg:orig_category":"Kinderopvang",
    "sg:phone":"+32 2 582 72 62",
    "sg:postcode":"1740",
    "sg:province":"Vlaams-Brabant",
    "wof:name":"Cent.buitensch.kinderopv.",
    "wof:placetype":"venue"
},
  "geometry": {"coordinates":[4.1838269234,50.8677444458],"type":"Point"}
}