{
  "type": "Feature",
  "properties": {
    "addr:full":"Gitsestraat 1 Roeselare West-Vlaanderen 8800",
    "addr:housenumber":"1",
    "addr:postcode":"8800",
    "addr:street":"Gitsestraat",
    "iso:country":"BE",
    "sg:address":"Gitsestraat 1",
    "sg:city":"Roeselare",
    "sg:orig_category":"Cr\u00e9dits divers",
    "sg:postcode":"8800",
    "sg:province":"West-Vlaanderen",
    "wof:name":"Bancontact-mister Cash",
    "wof:placetype":"venue"
},
  "geometry": {"coordinates":[3.1193430424,50.9519195557],"type":"Point"}
}