{
  "type": "Feature",
  "properties": {
    "addr:full":"Rue Du Lombart 42 Namur Namur 5000",
    "addr:housenumber":"42",
    "addr:postcode":"5000",
    "addr:street":"Rue Du Lombart",
    "iso:country":"BE",
    "sg:address":"Rue Du Lombart 42",
    "sg:city":"Namur",
    "sg:classifiers":[
        {
            "category":"Restaurant",
            "type":"Food & Drink"
        }
    ],
    "sg:phone":"+32 81 22 82 82",
    "sg:postcode":"5000",
    "sg:province":"Namur",
    "wof:name":"Colaianni Mauro & Miranda",
    "wof:placetype":"venue"
},
  "geometry": {"coordinates":[4.8713951111,50.4654121399],"type":"Point"}
}