{
  "type": "Feature",
  "properties": {
    "addr:full":"Rue De Huy 44 Waremme Li\u00e8ge 4300",
    "addr:housenumber":"44",
    "addr:postcode":"4300",
    "addr:street":"Rue De Huy",
    "iso:country":"BE",
    "sg:address":"Rue De Huy 44",
    "sg:city":"Waremme",
    "sg:orig_category":"M\u00e9decins and sp\u00e9cialistes",
    "sg:phone":"+32 19 33 02 37",
    "sg:postcode":"4300",
    "sg:province":"Li\u00e8ge",
    "wof:name":"J. Sterkendries",
    "wof:placetype":"venue"
},
  "geometry": {"coordinates":[5.2509422302,50.6919822693],"type":"Point"}
}