{
  "type": "Feature",
  "properties": {
    "addr:full":"Poelgoedstraat 6 Alken Limburg 3570",
    "addr:housenumber":"6",
    "addr:postcode":"3570",
    "addr:street":"Poelgoedstraat",
    "iso:country":"BE",
    "sg:address":"Poelgoedstraat 6",
    "sg:city":"Alken",
    "sg:orig_category":"Agences de publicit\u00e9",
    "sg:phone":"+32 11 31 62 14",
    "sg:postcode":"3570",
    "sg:province":"Limburg",
    "wof:name":"Publi Tony",
    "wof:placetype":"venue"
},
  "geometry": {"coordinates":[5.3095450401,50.8635635376],"type":"Point"}
}