{
  "type": "Feature",
  "properties": {
    "addr:full":"Boulevard De L\u00b4europe 2 Wavre Brabant Wallon 1300",
    "addr:housenumber":"2;1300",
    "addr:street":"Boulevard De L\u00b4Europe",
    "iso:country":"BE",
    "sg:address":"Boulevard De L\u00b4europe 2",
    "sg:city":"Wavre",
    "sg:orig_category":"R\u00e9parations d'horloges, montres and bijoux",
    "sg:phone":"+32 10 22 91 19",
    "sg:postcode":"1300",
    "sg:province":"Brabant Wallon",
    "wof:name":"Digit-import",
    "wof:placetype":"venue"
},
  "geometry": {"coordinates":[4.61059618,50.7141685486],"type":"Point"}
}