{
  "type": "Feature",
  "properties": {
    "addr:full":"Place E. Rongvaux 14 Waremme Li\u00e8ge 4300",
    "addr:housenumber":"14",
    "addr:postcode":"4300",
    "addr:street":"Place",
    "iso:country":"BE",
    "sg:address":"Place E. Rongvaux 14",
    "sg:city":"Waremme",
    "sg:orig_category":"Treinen and spoorwegen",
    "sg:phone":"+32 19 32 28 11",
    "sg:postcode":"4300",
    "sg:province":"Li\u00e8ge",
    "wof:name":"Gare De Waremme",
    "wof:placetype":"venue"
},
  "geometry": {"coordinates":[5.2495059967,50.6947479248],"type":"Point"}
}