{
  "type": "Feature",
  "properties": {
    "iso:country":"BE",
    "sg:address":"Boeschepestraat 99",
    "sg:city":"Poperinge",
    "sg:classifiers":[
        {
            "category":"Insurance",
            "subcategory":"Life Insurance",
            "type":"Services"
        }
    ],
    "sg:phone":"+32 57 33 60 01",
    "sg:postcode":"8970",
    "sg:province":"West-Vlaanderen",
    "sg:tags":[
        "assurance"
    ],
    "wof:name":"Bureau Delanote",
    "wof:placetype":"venue"
},
  "geometry": {"coordinates":[2.7210988998,50.8501434326],"type":"Point"}
}