{
  "type": "Feature",
  "properties": {
    "addr:full":"Leistraat 13 Kasterlee Antwerpen 2460",
    "addr:housenumber":"13",
    "addr:postcode":"2460",
    "addr:street":"Leistraat",
    "iso:country":"BE",
    "sg:address":"Leistraat 13",
    "sg:city":"Kasterlee",
    "sg:orig_category":"Film-, tv- and videoproductie Software ontwikkeling and ontwerp",
    "sg:phone":"+32 14 55 82 82",
    "sg:postcode":"2460",
    "sg:province":"Antwerpen",
    "wof:name":"Ami-productions",
    "wof:placetype":"venue"
},
  "geometry": {"coordinates":[4.92334795,51.2251358032],"type":"Point"}
}