{
  "type": "Feature",
  "properties": {
    "addr:full":"Provedroux 27 Vielsalm Luxembourg 6690",
    "addr:housenumber":"27",
    "addr:postcode":"6690",
    "addr:street":"Provedroux",
    "iso:country":"BE",
    "sg:address":"Provedroux 27",
    "sg:city":"Vielsalm",
    "sg:orig_category":"Overheidsdiensten",
    "sg:phone":"+32 80 21 41 85",
    "sg:postcode":"6690",
    "sg:province":"Luxembourg",
    "wof:name":"C.p.a.s.",
    "wof:placetype":"venue"
},
  "geometry": {"coordinates":[5.8957519531,50.2514533997],"type":"Point"}
}