{
  "type": "Feature",
  "properties": {
    "addr:full":"Rue Fran\u00e7ois Desmedt 56 Bruxelles (woluwe-saint-pierre) Bruxelles-Capitale 1150",
    "addr:housenumber":"56",
    "addr:postcode":"1150",
    "addr:street":"Rue Franc\u0327Ois Desmedt",
    "iso:country":"BE",
    "sg:address":"Rue Fran\u00e7ois Desmedt 56",
    "sg:city":"Bruxelles (woluwe-saint-pierre)",
    "sg:classifiers":[
        {
            "category":"Health Services",
            "subcategory":"Health Practitioner",
            "type":"Services"
        }
    ],
    "sg:phone":"+32 477 31 20 68",
    "sg:postcode":"1150",
    "sg:province":"Bruxelles-Capitale",
    "sg:tags":[
        "physiotherapist"
    ],
    "wof:name":"Dewame Michel",
    "wof:placetype":"venue"
},
  "geometry": {"coordinates":[4.4631052017,50.8433952332],"type":"Point"}
}