{
  "type": "Feature",
  "properties": {
    "addr:full":"Donkereweg 16 Ranst Antwerpen 2520",
    "addr:housenumber":"16",
    "addr:postcode":"2520",
    "addr:street":"Donkereweg",
    "iso:country":"BE",
    "sg:address":"Donkereweg 16",
    "sg:city":"Ranst",
    "sg:classifiers":[
        {
            "category":"Food Court",
            "type":"Food & Drink"
        }
    ],
    "sg:phone":"+32 3 485 58 92",
    "sg:postcode":"2520",
    "sg:province":"Antwerpen",
    "sg:tags":[
        "colourants",
        "liquid"
    ],
    "wof:name":"De Olifant B.v.b.a.",
    "wof:placetype":"venue"
},
  "geometry": {"coordinates":[4.5751547813,51.1931152344],"type":"Point"}
}