{
  "type": "Feature",
  "properties": {
    "addr:full":"Kamiel Wautersstraat 4 Temse Oost-Vlaanderen 9140",
    "addr:housenumber":"4",
    "addr:postcode":"9140",
    "addr:street":"Kamiel Wautersstraat",
    "iso:country":"BE",
    "sg:address":"Kamiel Wautersstraat 4",
    "sg:city":"Temse",
    "sg:orig_category":"Industri\u00eble wasserijen and droogkuis",
    "sg:phone":"+32 3 771 33 28",
    "sg:postcode":"9140",
    "sg:province":"Oost-Vlaanderen",
    "wof:name":"O.k. Shop",
    "wof:placetype":"venue"
},
  "geometry": {"coordinates":[4.2123808861,51.1246376038],"type":"Point"}
}