{
  "type": "Feature",
  "properties": {
    "addr:full":"Zwaluwbeekstraat 15 Kruibeke Oost-Vlaanderen 9150",
    "addr:housenumber":"15",
    "addr:postcode":"9150",
    "addr:street":"Zwaluwbeekstraat",
    "iso:country":"BE",
    "sg:address":"Zwaluwbeekstraat 15",
    "sg:city":"Kruibeke",
    "sg:orig_category":"Non-Classified Establishments",
    "sg:phone":"+32 3 253 00 63",
    "sg:postcode":"9150",
    "sg:province":"Oost-Vlaanderen",
    "wof:name":"Verba Nv",
    "wof:placetype":"venue"
},
  "geometry": {"coordinates":[4.3154201508,51.1957969666],"type":"Point"}
}