{
  "type": "Feature",
  "properties": {
    "addr:full":"Sint-vincentstraat Heusden-zolder (zolder) Limburg 3550",
    "addr:postcode":"3550",
    "iso:country":"BE",
    "sg:address":"Sint-vincentstraat",
    "sg:city":"Heusden-zolder (zolder)",
    "sg:classifiers":[
        {
            "category":"Retail",
            "subcategory":"Event Space",
            "type":"Services"
        }
    ],
    "sg:phone":"+32 11 57 38 92",
    "sg:postcode":"3550",
    "sg:province":"Limburg",
    "sg:tags":[
        "rental",
        "-",
        "hall"
    ],
    "wof:name":"St-vincent Vzw",
    "wof:placetype":"venue"
},
  "geometry": {"coordinates":[5.336812973,51.0365486145],"type":"Point"}
}