{
  "type": "Feature",
  "properties": {
    "addr:full":"Walleken 17 Wetteren Oost-Vlaanderen 9230",
    "addr:housenumber":"17",
    "addr:postcode":"9230",
    "addr:street":"Walleken",
    "iso:country":"BE",
    "sg:address":"Walleken 17",
    "sg:city":"Wetteren",
    "sg:orig_category":"Catering and organisation de f\u00eates",
    "sg:phone":"+32 9 366 23 65",
    "sg:postcode":"9230",
    "sg:province":"Oost-Vlaanderen",
    "wof:name":"'t Cuisientje Traiteur",
    "wof:placetype":"venue"
},
  "geometry": {"coordinates":[3.8815710545,51.0177688599],"type":"Point"}
}