{
  "type": "Feature",
  "properties": {
    "addr:full":"Dokter Spitaelslaan 1 Halle Vlaams-Brabant 1502",
    "addr:housenumber":"1;1502",
    "addr:street":"Dokter Spitaelslaan",
    "iso:country":"BE",
    "sg:address":"Dokter Spitaelslaan 1",
    "sg:city":"Halle",
    "sg:classifiers":[
        {
            "category":"Cafe",
            "type":"Food & Drink"
        }
    ],
    "sg:phone":"+32 2 361 06 08",
    "sg:postcode":"1502",
    "sg:province":"Vlaams-Brabant",
    "sg:tags":[
        "caf\u00e9s"
    ],
    "wof:name":"Alphonse Naveau",
    "wof:placetype":"venue"
},
  "geometry": {"coordinates":[4.2241029739,50.7092475891],"type":"Point"}
}