{
  "type": "Feature",
  "properties": {
    "iso:country":"BE",
    "sg:address":"Holleweg 79b",
    "sg:city":"Tongeren (vreren)",
    "sg:classifiers":[
        {
            "category":"Personal",
            "subcategory":"Beauty Salon",
            "type":"Services"
        }
    ],
    "sg:phone":"+32 12 23 01 41",
    "sg:postcode":"3700",
    "sg:province":"Limburg",
    "sg:tags":[
        "equipment",
        "hairdressing",
        "-",
        "supply"
    ],
    "wof:name":"Dighneef Haircosmetics Nv Groep",
    "wof:placetype":"venue"
},
  "geometry": {"coordinates":[5.4980611801,50.7515182495],"type":"Point"}
}