{
  "type": "Feature",
  "properties": {
    "addr:full":"Kerkstraat 1 Wemmel Vlaams-Brabant 1780",
    "addr:housenumber":"1",
    "addr:postcode":"1780",
    "addr:street":"Kerkstraat;Vlaams-Brabant",
    "iso:country":"BE",
    "sg:address":"Kerkstraat 1",
    "sg:city":"Wemmel",
    "sg:orig_category":"Telecommunicatieapparaten",
    "sg:phone":"+32 2 461 24 42",
    "sg:postcode":"1780",
    "sg:province":"Vlaams-Brabant",
    "wof:name":"Mit",
    "wof:placetype":"venue"
},
  "geometry": {"coordinates":[4.3030428886,50.9096450806],"type":"Point"}
}