{
  "type": "Feature",
  "properties": {
    "iso:country":"BE",
    "sg:address":"Pastoor Paquaylaan 20",
    "sg:city":"Heusden-zolder",
    "sg:orig_category":"Epiceries",
    "sg:phone":"+32 11 57 51 34",
    "sg:postcode":"3550",
    "sg:province":"Limburg",
    "wof:name":"Supermarkt Anko",
    "wof:placetype":"venue"
},
  "geometry": {"coordinates":[5.3139648438,51.0231018066],"type":"Point"}
}