{
  "type": "Feature",
  "properties": {
    "addr:full":"Avenue Du Pont De Luttre 19 Vorst/forest Bruxelles-Capitale 1190",
    "addr:housenumber":"19",
    "addr:postcode":"1190",
    "addr:street":"Avenue Du Pont De Luttre;/ Forest",
    "iso:country":"BE",
    "sg:address":"Avenue Du Pont De Luttre 19",
    "sg:city":"Vorst/forest",
    "sg:orig_category":"Disquaires",
    "sg:phone":"+32 2 343 98 60",
    "sg:postcode":"1190",
    "sg:province":"Bruxelles-Capitale",
    "wof:name":"Dureco Belgium/music Net Belgium",
    "wof:placetype":"venue"
},
  "geometry": {"coordinates":[4.3216161728,50.8208122253],"type":"Point"}
}