{
  "type": "Feature",
  "properties": {
    "addr:full":"Generaal Merjaylaan 60 Oudergem/auderghem Bruxelles-Capitale 1160",
    "addr:housenumber":"60",
    "addr:postcode":"1160",
    "addr:street":"Generaal Merjaylaan;/",
    "iso:country":"BE",
    "sg:address":"Generaal Merjaylaan 60",
    "sg:city":"Oudergem/auderghem",
    "sg:orig_category":"Rusthuizen and serviceflats",
    "sg:phone":"+32 2 672 73 77",
    "sg:postcode":"1160",
    "sg:province":"Bruxelles-Capitale",
    "wof:name":"Home Bruy\u00c8res Ii",
    "wof:placetype":"venue"
},
  "geometry": {"coordinates":[4.4255199432,50.811050415],"type":"Point"}
}