{
  "type": "Feature",
  "properties": {
    "iso:country":"BE",
    "sg:address":"Cypriaan Verhavertstraat 39",
    "sg:city":"Halle",
    "sg:orig_category":"Boucheries",
    "sg:phone":"+32 2 356 44 57",
    "sg:postcode":"1500",
    "sg:province":"Vlaams-Brabant",
    "wof:name":"Alex Springael",
    "wof:placetype":"venue"
},
  "geometry": {"coordinates":[4.2332601547,50.737953186],"type":"Point"}
}