{
  "type": "Feature",
  "properties": {
    "addr:full":"Parklaan 37 Sint-niklaas Oost-Vlaanderen 9100",
    "addr:housenumber":"37",
    "addr:postcode":"9100",
    "addr:street":"Parklaan",
    "iso:country":"BE",
    "sg:address":"Parklaan 37",
    "sg:city":"Sint-niklaas",
    "sg:orig_category":"Artsen and specialisten",
    "sg:phone":"+32 3 780 91 91",
    "sg:postcode":"9100",
    "sg:province":"Oost-Vlaanderen",
    "wof:name":"Christine Van Der Borght",
    "wof:placetype":"venue"
},
  "geometry": {"coordinates":[4.1450328827,51.1614837646],"type":"Point"}
}