{
  "type": "Feature",
  "properties": {
    "iso:country":"BE",
    "sg:address":"Square Ambiorix 46",
    "sg:city":"Brussel/bruxelles",
    "sg:orig_category":"M\u00e9decins and sp\u00e9cialistes",
    "sg:phone":"+32 2 230 32 42",
    "sg:postcode":"1000",
    "sg:province":"Bruxelles-Capitale",
    "wof:name":"Hugo Brems",
    "wof:placetype":"venue"
},
  "geometry": {"coordinates":[4.38210392,50.846446991],"type":"Point"}
}