{
  "type": "Feature",
  "properties": {
    "iso:country":"BE",
    "sg:address":"Scheibeek 8",
    "sg:city":"Edegem",
    "sg:classifiers":[
        {
            "category":"Professional",
            "subcategory":"Accounting & Tax Preparation",
            "type":"Services"
        }
    ],
    "sg:phone":"+32 3 458 21 16",
    "sg:postcode":"2650",
    "sg:province":"Antwerpen",
    "sg:tags":[
        "accountant"
    ],
    "wof:name":"Antoine De Winter",
    "wof:placetype":"venue"
},
  "geometry": {"coordinates":[4.4491419792,51.1464920044],"type":"Point"}
}