{
  "type": "Feature",
  "properties": {
    "iso:country":"BE",
    "sg:address":"Tabakstraat 64",
    "sg:city":"Sint-niklaas",
    "sg:orig_category":"Kapsalons",
    "sg:phone":"+32 3 777 26 46",
    "sg:postcode":"9100",
    "sg:province":"Oost-Vlaanderen",
    "wof:name":"Coiffure Isabelle",
    "wof:placetype":"venue"
},
  "geometry": {"coordinates":[4.1484851837,51.1719932556],"type":"Point"}
}