{
  "type": "Feature",
  "properties": {
    "addr:full":"Avenue Fr\u00c8re Orban 9 Mons Hainaut 7000",
    "addr:housenumber":"9",
    "addr:postcode":"7000",
    "addr:street":"Avenue Fre\u0300Re Orban;Hainaut",
    "iso:country":"BE",
    "sg:address":"Avenue Fr\u00c8re Orban 9",
    "sg:city":"Mons",
    "sg:orig_category":"Banques and organismes de cr\u00e9dit",
    "sg:phone":"+32 65 40 73 11",
    "sg:postcode":"7000",
    "sg:province":"Hainaut",
    "wof:name":"Fortis",
    "wof:placetype":"venue"
},
  "geometry": {"coordinates":[3.9553520679,50.450668335],"type":"Point"}
}