{
  "type": "Feature",
  "properties": {
    "addr:full":"Koulaak 6 Herentals Antwerpen 2200",
    "addr:housenumber":"6",
    "addr:postcode":"2200",
    "addr:street":"Koulaak",
    "iso:country":"BE",
    "sg:address":"Koulaak 6",
    "sg:city":"Herentals",
    "sg:classifiers":[
        {
            "category":"Bars & Pubs",
            "type":"Food & Drink"
        }
    ],
    "sg:phone":"+32 14 21 10 38",
    "sg:postcode":"2200",
    "sg:province":"Antwerpen",
    "wof:name":"Sportkring",
    "wof:placetype":"venue"
},
  "geometry": {"coordinates":[4.8424448967,51.1884536743],"type":"Point"}
}