{
  "type": "Feature",
  "properties": {
    "iso:country":"BE",
    "sg:address":"Rue De La Gare 50",
    "sg:city":"Plombi\u00c8res",
    "sg:orig_category":"Goederenvervoer over de weg",
    "sg:phone":"+32 87 78 77 03",
    "sg:postcode":"4850",
    "sg:province":"Li\u00e8ge",
    "wof:name":"Transjohn",
    "wof:placetype":"venue"
},
  "geometry": {"coordinates":[5.962269783,50.7189102173],"type":"Point"}
}