{
  "type": "Feature",
  "properties": {
    "addr:full":"Rue Roche Aux Corneilles 67 Chatelet Hainaut 6200",
    "addr:housenumber":"67",
    "addr:postcode":"6200",
    "addr:street":"Rue Roche Aux Corneilles;Hainaut",
    "iso:country":"BE",
    "sg:address":"Rue Roche Aux Corneilles 67",
    "sg:city":"Chatelet",
    "sg:orig_category":"D\u00e9molition d\u00b4immeubles and terrassements. Mat\u00e9riaux de construction Gr",
    "sg:phone":"+32 71 39 23 69",
    "sg:postcode":"6200",
    "sg:province":"Hainaut",
    "wof:name":"J.c.b.",
    "wof:placetype":"venue"
},
  "geometry": {"coordinates":[4.5423169136,50.3947639465],"type":"Point"}
}