{
  "type": "Feature",
  "properties": {
    "addr:full":"St.niklaasberg 28 Aarschot Vlaams-Brabant 3200",
    "addr:housenumber":"28",
    "addr:postcode":"3200",
    "addr:street":"St.Niklaasberg",
    "iso:country":"BE",
    "sg:address":"St.niklaasberg 28",
    "sg:city":"Aarschot",
    "sg:orig_category":"Royal Canin. Services pour animaux domestiques",
    "sg:phone":"+32 16 56 16 33",
    "sg:postcode":"3200",
    "sg:province":"Vlaams-Brabant",
    "wof:name":"Willems",
    "wof:placetype":"venue"
},
  "geometry": {"coordinates":[4.8293399811,50.9835281372],"type":"Point"}
}