{
  "type": "Feature",
  "properties": {
    "addr:full":"Steenweg Op Blaasveld 13 Mechelen Antwerpen 2801",
    "addr:housenumber":"13",
    "addr:postcode":"2801",
    "addr:street":"Steenweg Op Blaasveld",
    "iso:country":"BE",
    "sg:address":"Steenweg Op Blaasveld 13",
    "sg:city":"Mechelen",
    "sg:orig_category":"Beautyfarms, relaxatie and lichamelijk welzijn Schoonheidssalons",
    "sg:phone":"+32 15 27 25 89",
    "sg:postcode":"2801",
    "sg:province":"Antwerpen",
    "wof:name":"Beauty-farm Imelda",
    "wof:placetype":"venue"
},
  "geometry": {"coordinates":[4.4184617996,51.0462188721],"type":"Point"}
}