{
  "type": "Feature",
  "properties": {
    "addr:full":"Bo\u00eete Postale 56 Ixelles6 Bruxelles-Capitale 1050",
    "addr:housenumber":"56",
    "addr:postcode":"1050",
    "addr:street":"Ixelles6",
    "iso:country":"BE",
    "sg:address":"Bo\u00eete Postale 56",
    "sg:city":"Ixelles6",
    "sg:classifiers":[
        {
            "category":"Airline",
            "type":"Transportation"
        }
    ],
    "sg:phone":"+32 2 752 31 37",
    "sg:postcode":"1050",
    "sg:province":"Bruxelles-Capitale",
    "wof:name":"Inter Aviation Services Bvba",
    "wof:placetype":"venue"
},
  "geometry": {"coordinates":[4.4327301979,50.9123344421],"type":"Point"}
}