{
  "type": "Feature",
  "properties": {
    "addr:full":"Gouverneur Verwilghensingel 13 Hasselt Limburg 3500",
    "addr:housenumber":"13",
    "addr:postcode":"3500",
    "addr:street":"Gouverneur Verwilghensingel",
    "iso:country":"BE",
    "sg:address":"Gouverneur Verwilghensingel 13",
    "sg:city":"Hasselt",
    "sg:classifiers":[
        {
            "category":"Arena",
            "subcategory":"Sports Club",
            "type":"Entertainment"
        }
    ],
    "sg:phone":"+32 11 30 08 00",
    "sg:postcode":"3500",
    "sg:province":"Limburg",
    "wof:name":"Bloso-ijshal de Schaverdijn",
    "wof:placetype":"venue"
},
  "geometry": {"coordinates":[5.3552107811,50.9370918274],"type":"Point"}
}