{
  "type": "Feature",
  "properties": {
    "iso:country":"BE",
    "sg:address":"Korhoenstraat 9",
    "sg:city":"Gent",
    "sg:orig_category":"Ordinateurs and \u00e9quipement informatique",
    "sg:phone":"+32 9 227 93 32",
    "sg:postcode":"9000",
    "sg:province":"Oost-Vlaanderen",
    "wof:name":"Eddy De Roos",
    "wof:placetype":"venue"
},
  "geometry": {"coordinates":[3.6990439892,51.0550498962],"type":"Point"}
}