{
  "type": "Feature",
  "properties": {
    "iso:country":"BE",
    "sg:address":"Rue Morte Eau 240",
    "sg:city":"Donceel",
    "sg:orig_category":"Fruitteelt GROENTEN AND FRUIT",
    "sg:phone":"+32 4 259 54 64",
    "sg:postcode":"4357",
    "sg:province":"Li\u00e8ge",
    "wof:name":"Maison Galet & Fils",
    "wof:placetype":"venue"
},
  "geometry": {"coordinates":[5.3175601959,50.6334915161],"type":"Point"}
}