{
  "type": "Feature",
  "properties": {
    "iso:country":"BE",
    "sg:address":"Schoorstraat 40",
    "sg:city":"Heist-op-den-berg",
    "sg:classifiers":[
        {
            "category":"Building & Trades",
            "subcategory":"Construction",
            "type":"Services"
        }
    ],
    "sg:phone":"+32 15 25 06 00",
    "sg:postcode":"2220",
    "sg:province":"Antwerpen",
    "sg:tags":[
        "la",
        "de",
        "\u00e9quipement",
        "pour",
        "machine",
        "location"
    ],
    "wof:name":"P.van Egdom-marien & Co",
    "wof:placetype":"venue"
},
  "geometry": {"coordinates":[4.7139787674,51.0589103699],"type":"Point"}
}