{
  "type": "Feature",
  "properties": {
    "iso:country":"BE",
    "sg:address":"Boudewijnlaan 68",
    "sg:city":"Aalst",
    "sg:classifiers":[
        {
            "category":"Health Services",
            "subcategory":"Dentist",
            "type":"Services"
        }
    ],
    "sg:phone":"+32 53 70 56 56",
    "sg:postcode":"9300",
    "sg:province":"Oost-Vlaanderen",
    "wof:name":"De Dijcker Els",
    "wof:placetype":"venue"
},
  "geometry": {"coordinates":[4.0204930305,50.9433059692],"type":"Point"}
}