{
  "type": "Feature",
  "properties": {
    "iso:country":"BE",
    "sg:address":"Koninginnelaan 8",
    "sg:city":"Schaarbeek/schaerbeek",
    "sg:orig_category":"Artsen and specialisten",
    "sg:phone":"+32 2 216 54 11",
    "sg:postcode":"1030",
    "sg:province":"Bruxelles-Capitale",
    "wof:name":"Jamil Obeid",
    "wof:placetype":"venue"
},
  "geometry": {"coordinates":[4.3659830093,50.864692688],"type":"Point"}
}