{
  "type": "Feature",
  "properties": {
    "addr:full":"Gentstraat 43 Deinze Oost-Vlaanderen 9800",
    "addr:housenumber":"43",
    "addr:postcode":"9800",
    "addr:street":"Gentstraat",
    "iso:country":"BE",
    "sg:address":"Gentstraat 43",
    "sg:city":"Deinze",
    "sg:classifiers":[
        {
            "category":"Retail",
            "subcategory":"Laundry & Dry Cleaning",
            "type":"Services"
        }
    ],
    "sg:phone":"+32 9 380 87 78",
    "sg:postcode":"9800",
    "sg:province":"Oost-Vlaanderen",
    "sg:tags":[
        "dyer",
        "cleaner"
    ],
    "wof:name":"Strijkwinkel Karine",
    "wof:placetype":"venue"
},
  "geometry": {"coordinates":[3.5335319042,50.9798469543],"type":"Point"}
}