{
  "type": "Feature",
  "properties": {
    "iso:country":"BE",
    "sg:address":"Dorpsstraat 12",
    "sg:city":"De Panne",
    "sg:orig_category":"Banques and organismes de cr\u00e9dit",
    "sg:phone":"+32 58 41 17 36",
    "sg:postcode":"8660",
    "sg:province":"West-Vlaanderen",
    "wof:name":"Kbc",
    "wof:placetype":"venue"
},
  "geometry": {"coordinates":[2.6017711163,51.0747833252],"type":"Point"}
}