{
  "type": "Feature",
  "properties": {
    "iso:country":"BE",
    "sg:address":"Koeisteert 23",
    "sg:city":"Londerzeel",
    "sg:orig_category":"Plomberie, chauffage and installations sanitaires",
    "sg:phone":"+32 52 30 98 33",
    "sg:postcode":"1840",
    "sg:province":"Vlaams-Brabant",
    "wof:name":"Guns",
    "wof:placetype":"venue"
},
  "geometry": {"coordinates":[4.2968702316,51.0333595276],"type":"Point"}
}