{
  "type": "Feature",
  "properties": {
    "addr:full":"Rue De Neufchateau 1 Libramont-chevigny Luxembourg 6800",
    "addr:housenumber":"1",
    "addr:postcode":"6800",
    "addr:street":"Rue De Neufchateau",
    "iso:country":"BE",
    "sg:address":"Rue De Neufchateau 1",
    "sg:city":"Libramont-chevigny",
    "sg:orig_category":"Benzinestations and brandstoffen",
    "sg:phone":"+32 61 22 46 80",
    "sg:postcode":"6800",
    "sg:province":"Luxembourg",
    "wof:name":"Esso",
    "wof:placetype":"venue"
},
  "geometry": {"coordinates":[5.3761348724,49.9199943542],"type":"Point"}
}