{
  "type": "Feature",
  "properties": {
    "iso:country":"BE",
    "sg:address":"Avenue Van Crombrugghe 28",
    "sg:city":"Sint-pieters-woluwe/woluwe-saint-pierre",
    "sg:orig_category":"M\u00e9decins and sp\u00e9cialistes",
    "sg:phone":"+32 2 762 09 45",
    "sg:postcode":"1150",
    "sg:province":"Bruxelles-Capitale",
    "wof:name":"Andr\u00c9 Hanon",
    "wof:placetype":"venue"
},
  "geometry": {"coordinates":[4.4575490952,50.8272628784],"type":"Point"}
}