{
  "type": "Feature",
  "properties": {
    "addr:full":"Venelle Des Marronniers 29 Wavre (bierges) Brabant Wallon 1301",
    "addr:housenumber":"29;1301",
    "addr:street":"Venelle Des Marronniers",
    "iso:country":"BE",
    "sg:address":"Venelle Des Marronniers 29",
    "sg:city":"Wavre (bierges)",
    "sg:classifiers":[
        {
            "category":"Health Services",
            "subcategory":"Doctor",
            "type":"Services"
        }
    ],
    "sg:phone":"+32 10 22 84 87",
    "sg:postcode":"1301",
    "sg:province":"Brabant Wallon",
    "sg:tags":[
        "psychotherapist",
        "psychoanalyst"
    ],
    "wof:name":"Bertrand C",
    "wof:placetype":"venue"
},
  "geometry": {"coordinates":[4.6182727814,50.6995353699],"type":"Point"}
}