{
  "type": "Feature",
  "properties": {
    "addr:full":"Rue Masses Diarbois 115 Charleroi Hainaut 6043",
    "addr:housenumber":"115",
    "addr:postcode":"6043",
    "addr:street":"Rue Masses Diarbois;Hainaut",
    "iso:country":"BE",
    "sg:address":"Rue Masses Diarbois 115",
    "sg:city":"Charleroi",
    "sg:orig_category":"Banken and kredietinstellingen",
    "sg:phone":"+32 71 34 98 00",
    "sg:postcode":"6043",
    "sg:province":"Hainaut",
    "wof:name":"Dexia",
    "wof:placetype":"venue"
},
  "geometry": {"coordinates":[4.4839549065,50.4479637146],"type":"Point"}
}