{
  "type": "Feature",
  "properties": {
    "addr:full":"Stokerijdreef 7a Koekelare West-Vlaanderen 8680",
    "addr:housenumber":"7a",
    "addr:postcode":"8680",
    "addr:street":"Stokerijdreef",
    "iso:country":"BE",
    "sg:address":"Stokerijdreef 7a",
    "sg:city":"Koekelare",
    "sg:classifiers":[
        {
            "category":"Shopping",
            "subcategory":"Clothing, Apparel, & Fashions",
            "type":"Retail Goods"
        }
    ],
    "sg:phone":"+32 59 27 48 16",
    "sg:postcode":"8680",
    "sg:province":"West-Vlaanderen",
    "sg:tags":[
        "lady",
        "clothing",
        "-"
    ],
    "wof:name":"Deco-style",
    "wof:placetype":"venue"
},
  "geometry": {"coordinates":[2.976457119,51.1239356995],"type":"Point"}
}