{
  "type": "Feature",
  "properties": {
    "addr:full":"Sint-bernadettestraat 197 Gent Oost-Vlaanderen 9000",
    "addr:housenumber":"197",
    "addr:postcode":"9000",
    "addr:street":"Oost-Vlaanderen",
    "iso:country":"BE",
    "sg:address":"Sint-bernadettestraat 197",
    "sg:city":"Gent",
    "sg:orig_category":"Zuivelproducten",
    "sg:phone":"+32 9 251 06 08",
    "sg:postcode":"9000",
    "sg:province":"Oost-Vlaanderen",
    "wof:name":"Andr\u00c9 De Maesschalck",
    "wof:placetype":"venue"
},
  "geometry": {"coordinates":[3.7521400452,51.0743675232],"type":"Point"}
}