{
  "type": "Feature",
  "properties": {
    "addr:full":"Sinaaidorp 15 Sint-niklaas (sinaai) Oost-Vlaanderen 9112",
    "addr:housenumber":"15",
    "addr:postcode":"9112",
    "addr:street":"Sinaaidorp;Oost-Vlaanderen",
    "iso:country":"BE",
    "sg:address":"Sinaaidorp 15",
    "sg:city":"Sint-niklaas (sinaai)",
    "sg:classifiers":[
        {
            "category":"Shopping",
            "subcategory":"Florist",
            "type":"Retail Goods"
        }
    ],
    "sg:phone":"+32 3 772 36 66",
    "sg:postcode":"9112",
    "sg:province":"Oost-Vlaanderen",
    "sg:tags":[
        "-",
        "supply"
    ],
    "wof:name":"Europack-smet",
    "wof:placetype":"venue"
},
  "geometry": {"coordinates":[4.0391769409,51.157333374],"type":"Point"}
}