{
  "type": "Feature",
  "properties": {
    "addr:full":"Grote Steenweg 119a Zulte (olsene) Oost-Vlaanderen 9870",
    "addr:housenumber":"119a",
    "addr:postcode":"9870",
    "addr:street":"Grote Steenweg",
    "iso:country":"BE",
    "sg:address":"Grote Steenweg 119a",
    "sg:city":"Zulte (olsene)",
    "sg:classifiers":[
        {
            "category":"Professional",
            "subcategory":"Management & Consulting",
            "type":"Services"
        }
    ],
    "sg:phone":"+32 9 388 39 01",
    "sg:postcode":"9870",
    "sg:province":"Oost-Vlaanderen",
    "sg:tags":[
        "-",
        "processing",
        "data",
        "consultant"
    ],
    "wof:name":"Fks Consulting",
    "wof:placetype":"venue"
},
  "geometry": {"coordinates":[3.4629778862,50.9343681335],"type":"Point"}
}