{
  "type": "Feature",
  "properties": {
    "addr:full":"Rue De La Poste 21 Eghezee Namur 5310",
    "addr:housenumber":"21",
    "addr:postcode":"5310",
    "addr:street":"Rue De La Poste;Namur",
    "iso:country":"BE",
    "sg:address":"Rue De La Poste 21",
    "sg:city":"Eghezee",
    "sg:classifiers":[
        {
            "category":"Arena",
            "subcategory":"Sports Club",
            "type":"Entertainment"
        }
    ],
    "sg:phone":"+32 81 51 13 93",
    "sg:postcode":"5310",
    "sg:province":"Namur",
    "sg:tags":[
        "de"
    ],
    "wof:name":"L'hirondelle",
    "wof:placetype":"venue"
},
  "geometry": {"coordinates":[4.9053139687,50.5581932068],"type":"Point"}
}