{
  "type": "Feature",
  "properties": {
    "addr:full":"Rue De Maestricht 94 Vis\u00e9 Li\u00e8ge 4600",
    "addr:housenumber":"94",
    "addr:postcode":"4600",
    "addr:street":"Rue De Maestricht",
    "iso:country":"BE",
    "sg:address":"Rue De Maestricht 94",
    "sg:city":"Vis\u00e9",
    "sg:classifiers":[
        {
            "category":"Retail",
            "subcategory":"Auto Repair",
            "type":"Services"
        }
    ],
    "sg:phone":"+32 4 379 64 92",
    "sg:postcode":"4600",
    "sg:province":"Li\u00e8ge",
    "sg:tags":[
        "garage"
    ],
    "wof:name":"Donnay Sa",
    "wof:placetype":"venue"
},
  "geometry": {"coordinates":[5.7032179832,50.7459449768],"type":"Point"}
}