{
  "type": "Feature",
  "properties": {
    "iso:country":"BE",
    "sg:address":"Sterrebeekstraat 163",
    "sg:city":"Zaventem",
    "sg:classifiers":[
        {
            "category":"Home & Garden",
            "subcategory":"Hardware",
            "type":"Retail Goods"
        }
    ],
    "sg:phone":"+32 2 720 92 12",
    "sg:postcode":"1930",
    "sg:province":"Vlaams-Brabant",
    "sg:tags":[
        "equipment"
    ],
    "wof:name":"Markt (belgium) Nv-sa",
    "wof:placetype":"venue"
},
  "geometry": {"coordinates":[4.4858298302,50.8726081848],"type":"Point"}
}