{
  "type": "Feature",
  "properties": {
    "iso:country":"BE",
    "sg:address":"Willem De Blockstraat 2",
    "sg:city":"Bornem",
    "sg:orig_category":"Kapsalons",
    "sg:phone":"+32 3 889 04 12",
    "sg:postcode":"2880",
    "sg:province":"Antwerpen",
    "wof:name":"Coiffure Van Den Eynde",
    "wof:placetype":"venue"
},
  "geometry": {"coordinates":[4.2987132072,51.1064758301],"type":"Point"}
}