{
  "type": "Feature",
  "properties": {
    "addr:full":"Sint-michielsplein 15bc Westerlo Antwerpen 2260",
    "addr:housenumber":"15bc",
    "addr:postcode":"2260",
    "addr:street":"Sint-Michielsplein",
    "iso:country":"BE",
    "sg:address":"Sint-michielsplein 15bc",
    "sg:city":"Westerlo",
    "sg:orig_category":"Levensverzekeringsmaatschappijen Verzekeringen vastgoed",
    "sg:phone":"+32 14 21 71 80",
    "sg:postcode":"2260",
    "sg:province":"Antwerpen",
    "wof:name":"Hamburg Mannheimer Cons.",
    "wof:placetype":"venue"
},
  "geometry": {"coordinates":[4.9058508873,51.1392173767],"type":"Point"}
}