{
  "type": "Feature",
  "properties": {
    "addr:full":"Neerveldlaan 16 Box 7 Dilbeek Vlaams-Brabant 1700",
    "addr:housenumber":"16;7",
    "addr:postcode":"1700",
    "addr:street":"Neerveldlaan;Box",
    "iso:country":"BE",
    "sg:address":"Neerveldlaan 16 Box 7",
    "sg:city":"Dilbeek",
    "sg:classifiers":[
        {
            "category":"Professional",
            "subcategory":"Printing & Photocopies",
            "type":"Services"
        }
    ],
    "sg:phone":"+32 2 569 72 52",
    "sg:postcode":"1700",
    "sg:province":"Vlaams-Brabant",
    "sg:tags":[
        "-",
        "publishing",
        "desktop"
    ],
    "wof:name":"Solution Cvba",
    "wof:placetype":"venue"
},
  "geometry": {"coordinates":[4.2682437897,50.8377113342],"type":"Point"}
}