{
  "type": "Feature",
  "properties": {
    "addr:full":"Oudenaardsestraat 78 Brakel Oost-Vlaanderen 9660",
    "addr:housenumber":"78",
    "addr:postcode":"9660",
    "addr:street":"Oudenaardsestraat",
    "iso:country":"BE",
    "sg:address":"Oudenaardsestraat 78",
    "sg:city":"Brakel",
    "sg:classifiers":[
        {
            "category":"Autos & Motor Vehicles",
            "subcategory":"Fuel & Gas Station",
            "type":"Retail Goods"
        }
    ],
    "sg:phone":"+32 55 42 28 43",
    "sg:postcode":"9660",
    "sg:province":"Oost-Vlaanderen",
    "sg:tags":[
        "stations-service",
        "carburants"
    ],
    "wof:name":"Jet",
    "wof:placetype":"venue"
},
  "geometry": {"coordinates":[3.7253119946,50.817527771],"type":"Point"}
}