{
  "type": "Feature",
  "properties": {
    "addr:full":"Rue De La Montagne 22 Verviers Li\u00e8ge 4800",
    "addr:housenumber":"22",
    "addr:postcode":"4800",
    "addr:street":"Rue De La Montagne",
    "iso:country":"BE",
    "sg:address":"Rue De La Montagne 22",
    "sg:city":"Verviers",
    "sg:orig_category":"Pain, p\u00e2tisseries and confiseries",
    "sg:phone":"+32 87 33 34 52",
    "sg:postcode":"4800",
    "sg:province":"Li\u00e8ge",
    "wof:name":"Boulangerie Kapadokya",
    "wof:placetype":"venue"
},
  "geometry": {"coordinates":[5.881538868,50.5960655212],"type":"Point"}
}