{
  "type": "Feature",
  "properties": {
    "addr:full":"Rue Caisse 11 Charleroi Hainaut 6032",
    "addr:housenumber":"11",
    "addr:postcode":"6032",
    "addr:street":"Rue Caisse;Hainaut",
    "iso:country":"BE",
    "sg:address":"Rue Caisse 11",
    "sg:city":"Charleroi",
    "sg:classifiers":[
        {
            "category":"Insurance",
            "subcategory":"Life Insurance",
            "type":"Services"
        }
    ],
    "sg:phone":"+32 71 36 67 82",
    "sg:postcode":"6032",
    "sg:province":"Hainaut",
    "sg:tags":[
        "assurance"
    ],
    "wof:name":"Bureau Roulet",
    "wof:placetype":"venue"
},
  "geometry": {"coordinates":[4.4040927887,50.3906402588],"type":"Point"}
}