{
  "type": "Feature",
  "properties": {
    "iso:country":"BE",
    "sg:address":"Rue De Bertaimont 50b15",
    "sg:city":"Mons",
    "sg:orig_category":"Activit\u00e9s r\u00e9cr\u00e9atives diverses",
    "sg:phone":"+32 65 31 12 09",
    "sg:postcode":"7000",
    "sg:province":"Hainaut",
    "wof:name":"A.s.a. Bauffe",
    "wof:placetype":"venue"
},
  "geometry": {"coordinates":[3.9484300613,50.4475822449],"type":"Point"}
}