{
  "type": "Feature",
  "properties": {
    "iso:country":"BE",
    "sg:address":"Culliganlaan 2c",
    "sg:city":"Machelen (diegem)",
    "sg:classifiers":[
        {
            "category":"Banks & Credit Unions",
            "subcategory":"Investment Brokerage",
            "type":"Services"
        }
    ],
    "sg:phone":"+32 2 610 03 00",
    "sg:postcode":"1831",
    "sg:province":"Vlaams-Brabant",
    "wof:name":"Nesbic Belgium Nv",
    "wof:placetype":"venue"
},
  "geometry": {"coordinates":[4.4504752159,50.8849449158],"type":"Point"}
}