{
  "type": "Feature",
  "properties": {
    "addr:full":"Rue Du Major Sabbe 24 Pecq Hainaut 7740",
    "addr:housenumber":"24",
    "addr:postcode":"7740",
    "addr:street":"Rue Du Major Sabbe",
    "iso:country":"BE",
    "sg:address":"Rue Du Major Sabbe 24",
    "sg:city":"Pecq",
    "sg:classifiers":[
        {
            "category":"Arena",
            "subcategory":"Sports Club",
            "type":"Entertainment"
        }
    ],
    "sg:phone":"+32 69 55 74 05",
    "sg:postcode":"7740",
    "sg:province":"Hainaut",
    "sg:tags":[
        "de"
    ],
    "wof:name":"Entente Pecquoise",
    "wof:placetype":"venue"
},
  "geometry": {"coordinates":[3.3371670246,50.6841163635],"type":"Point"}
}