{
  "type": "Feature",
  "properties": {
    "addr:full":"Spieveldstraat 75 Sint-niklaas Oost-Vlaanderen 9100",
    "addr:housenumber":"75",
    "addr:postcode":"9100",
    "addr:street":"Spieveldstraat",
    "iso:country":"BE",
    "sg:address":"Spieveldstraat 75",
    "sg:city":"Sint-niklaas",
    "sg:classifiers":[
        {
            "category":"Shopping",
            "subcategory":"Clothing, Apparel, & Fashions",
            "type":"Retail Goods"
        }
    ],
    "sg:phone":"+32 3 776 03 41",
    "sg:postcode":"9100",
    "sg:province":"Oost-Vlaanderen",
    "sg:tags":[
        "boutique"
    ],
    "wof:name":"Riamo",
    "wof:placetype":"venue"
},
  "geometry": {"coordinates":[4.1266479492,51.1878509521],"type":"Point"}
}