{
  "type": "Feature",
  "properties": {
    "addr:full":"Luitenant Jacopsstraat 54bc Lennik Vlaams-Brabant 1750",
    "addr:housenumber":"54bc;1750",
    "addr:street":"Luitenant Jacopsstraat;Vlaams-Brabant",
    "iso:country":"BE",
    "sg:address":"Luitenant Jacopsstraat 54bc",
    "sg:city":"Lennik",
    "sg:orig_category":"Slagers",
    "sg:phone":"+32 2 582 10 86",
    "sg:postcode":"1750",
    "sg:province":"Vlaams-Brabant",
    "wof:name":"Jozeph Segers",
    "wof:placetype":"venue"
},
  "geometry": {"coordinates":[4.1363611221,50.8338317871],"type":"Point"}
}