{
  "type": "Feature",
  "properties": {
    "addr:full":"Rue Chapelle \u00c0 La Lice 27a Fl\u00c9ron Li\u00e8ge 4621",
    "addr:housenumber":"27a",
    "addr:postcode":"4621",
    "addr:street":"Rue Chapelle A\u0300 La Lice",
    "iso:country":"BE",
    "sg:address":"Rue Chapelle \u00c0 La Lice 27a",
    "sg:city":"Fl\u00c9ron",
    "sg:orig_category":"Betonnen bouwelementen Fab Installatie van metalen schrijnwerk Pleisterwerk",
    "sg:phone":"+32 4 355 17 08",
    "sg:postcode":"4621",
    "sg:province":"Li\u00e8ge",
    "wof:name":"Moisse & Cie",
    "wof:placetype":"venue"
},
  "geometry": {"coordinates":[5.6963891983,50.628704071],"type":"Point"}
}