{
  "type": "Feature",
  "properties": {
    "addr:full":"Parc Du Peterbos 9b9 Anderlecht Bruxelles-Capitale 1070",
    "addr:housenumber":"9b9",
    "addr:postcode":"1070",
    "addr:street":"Parc Du Peterbos",
    "iso:country":"BE",
    "sg:address":"Parc Du Peterbos 9b9",
    "sg:city":"Anderlecht",
    "sg:orig_category":"Production de films, t\u00e9l\u00e9films and vid\u00e9os",
    "sg:phone":"+32 2 521 94 85",
    "sg:postcode":"1070",
    "sg:province":"Bruxelles-Capitale",
    "wof:name":"Regjep Ahmetaj",
    "wof:placetype":"venue"
},
  "geometry": {"coordinates":[4.294588089,50.8417739868],"type":"Point"}
}