{
  "type": "Feature",
  "properties": {
    "addr:full":"Chauss\u00c9e De Ninove 527 Sint-jans-molenbeek/molenbeek- Bruxelles-Capitale 1080",
    "addr:housenumber":"527",
    "addr:postcode":"1080",
    "addr:street":"Chausse\u0301E De Ninove;Molenbeek",
    "iso:country":"BE",
    "sg:address":"Chauss\u00c9e De Ninove 527",
    "sg:city":"Sint-jans-molenbeek/molenbeek-",
    "sg:orig_category":"Bloemen and planten",
    "sg:phone":"+32 2 410 70 91",
    "sg:postcode":"1080",
    "sg:province":"Bruxelles-Capitale",
    "wof:name":"Gini Fleurs",
    "wof:placetype":"venue"
},
  "geometry": {"coordinates":[4.3159198761,50.8483505249],"type":"Point"}
}