{
  "type": "Feature",
  "properties": {
    "addr:full":"Boulevard Edmond Machtens 125 Bruxelles (molenbeek-saint-jean) Bruxelles-Capitale 1080",
    "addr:housenumber":"125",
    "addr:postcode":"1080",
    "addr:street":"Boulevard Edmond Machtens",
    "iso:country":"BE",
    "sg:address":"Boulevard Edmond Machtens 125",
    "sg:city":"Bruxelles (molenbeek-saint-jean)",
    "sg:classifiers":[
        {
            "category":"Health Services",
            "subcategory":"Health Practitioner",
            "type":"Services"
        }
    ],
    "sg:phone":"+32 2 410 35 44",
    "sg:postcode":"1080",
    "sg:province":"Bruxelles-Capitale",
    "sg:tags":[
        "osteopath"
    ],
    "wof:name":"Reniers B (d.o.)",
    "wof:placetype":"venue"
},
  "geometry": {"coordinates":[4.3060641289,50.8509712219],"type":"Point"}
}