{
  "type": "Feature",
  "properties": {
    "addr:full":"Chemin De La Valli\u00e8re 42 Mons Hainaut 7000",
    "addr:housenumber":"42",
    "addr:postcode":"7000",
    "addr:street":"Chemin De La Vallie\u0300Re;Hainaut",
    "iso:country":"BE",
    "sg:address":"Chemin De La Valli\u00e8re 42",
    "sg:city":"Mons",
    "sg:classifiers":[
        {
            "category":"Manufacturing",
            "subcategory":"Printing",
            "type":"Manufacturing & Wholesale Goods"
        }
    ],
    "sg:phone":"+32 65 31 60 35",
    "sg:postcode":"7000",
    "sg:province":"Hainaut",
    "sg:tags":[
        "textile",
        "-"
    ],
    "wof:name":"Art Color Sprl",
    "wof:placetype":"venue"
},
  "geometry": {"coordinates":[3.9494259357,50.4416847229],"type":"Point"}
}