{
  "type": "Feature",
  "properties": {
    "addr:full":"Rue Martin-sandron 124 Doische Namur 5680",
    "addr:housenumber":"124",
    "addr:postcode":"5680",
    "addr:street":"Rue Martin-Sandron",
    "iso:country":"BE",
    "sg:address":"Rue Martin-sandron 124",
    "sg:city":"Doische",
    "sg:orig_category":"Toeristische diensten",
    "sg:phone":"+32 82 67 81 15",
    "sg:postcode":"5680",
    "sg:province":"Namur",
    "wof:name":"Syndicat D'initiative",
    "wof:placetype":"venue"
},
  "geometry": {"coordinates":[4.7442641258,50.1358261108],"type":"Point"}
}