{
  "type": "Feature",
  "properties": {
    "addr:full":"Avenue De Waterloo 54 Charleroi Hainaut 6000",
    "addr:housenumber":"54",
    "addr:postcode":"6000",
    "addr:street":"Avenue De Waterloo;Hainaut",
    "iso:country":"BE",
    "sg:address":"Avenue De Waterloo 54",
    "sg:city":"Charleroi",
    "sg:classifiers":[
        {
            "category":"Health Services",
            "subcategory":"Doctor",
            "type":"Services"
        }
    ],
    "sg:phone":"+32 71 31 33 42",
    "sg:postcode":"6000",
    "sg:province":"Hainaut",
    "sg:tags":[
        "psychotherapist",
        "psychoanalyst"
    ],
    "wof:name":"Lesuisses D",
    "wof:placetype":"venue"
},
  "geometry": {"coordinates":[4.4484272003,50.4156188965],"type":"Point"}
}