{
  "type": "Feature",
  "properties": {
    "iso:country":"BE",
    "sg:address":"Grand Rue 97",
    "sg:city":"Sivry-rance (rance)",
    "sg:classifiers":[
        {
            "category":"Building & Trades",
            "subcategory":"Construction",
            "type":"Services"
        }
    ],
    "sg:phone":"+32 60 41 21 09",
    "sg:postcode":"6470",
    "sg:province":"Hainaut",
    "sg:tags":[
        "carpenter"
    ],
    "wof:name":"Yves-moreau-lalmant Sprl",
    "wof:placetype":"venue"
},
  "geometry": {"coordinates":[4.2757711411,50.1424331665],"type":"Point"}
}