{
  "type": "Feature",
  "properties": {
    "addr:full":"Place Th\u00c9odore Gobert 1 Li\u00c8ge Li\u00e8ge 4020",
    "addr:housenumber":"1",
    "addr:postcode":"4020",
    "addr:street":"Place The\u0301Odore Gobert",
    "iso:country":"BE",
    "sg:address":"Place Th\u00c9odore Gobert 1",
    "sg:city":"Li\u00c8ge",
    "sg:orig_category":"Pharmaciens",
    "sg:phone":"+32 4 343 25 76",
    "sg:postcode":"4020",
    "sg:province":"Li\u00e8ge",
    "wof:name":"M. Bouillon",
    "wof:placetype":"venue"
},
  "geometry": {"coordinates":[5.586493969,50.6385574341],"type":"Point"}
}