{
  "type": "Feature",
  "properties": {
    "iso:country":"BE",
    "sg:address":"Rue De Petit-roeulx 1",
    "sg:city":"Pont-a-celles",
    "sg:orig_category":"Rundveehouders",
    "sg:phone":"+32 67 87 75 45",
    "sg:postcode":"6230",
    "sg:province":"Hainaut",
    "wof:name":"Dany Teetaert",
    "wof:placetype":"venue"
},
  "geometry": {"coordinates":[4.3273220062,50.5383453369],"type":"Point"}
}