{
  "type": "Feature",
  "properties": {
    "addr:full":"Chauss\u00e9e De Wavre 1208 Box 12 Bruxelles (auderghem) Bruxelles-Capitale 1160",
    "addr:housenumber":"1208 box 12",
    "addr:postcode":"1160",
    "addr:street":"Chausse\u0301E De Wavre",
    "iso:country":"BE",
    "sg:address":"Chauss\u00e9e De Wavre 1208 Box 12",
    "sg:city":"Bruxelles (auderghem)",
    "sg:classifiers":[
        {
            "category":"Health Services",
            "subcategory":"Doctor",
            "type":"Services"
        }
    ],
    "sg:phone":"+32 2 672 20 02",
    "sg:postcode":"1160",
    "sg:province":"Bruxelles-Capitale",
    "sg:tags":[
        "medicinephysicians",
        "surgeon"
    ],
    "wof:name":"Galea Fernandez J",
    "wof:placetype":"venue"
},
  "geometry": {"coordinates":[4.407020092,50.8215103149],"type":"Point"}
}