{
  "type": "Feature",
  "properties": {
    "iso:country":"BE",
    "sg:address":"Rue De La Fraternit\u00e9 25",
    "sg:city":"Aubange (halanzy)",
    "sg:classifiers":[
        {
            "category":"Shopping",
            "subcategory":"Musical Instruments",
            "type":"Retail Goods"
        }
    ],
    "sg:phone":"+32 63 67 51 62",
    "sg:postcode":"6792",
    "sg:province":"Luxembourg",
    "sg:tags":[
        "optical"
    ],
    "wof:name":"Optilook",
    "wof:placetype":"venue"
},
  "geometry": {"coordinates":[5.7447781563,49.5596046448],"type":"Point"}
}