{
  "type": "Feature",
  "properties": {
    "addr:full":"Van Dijcklaan 22 Zaventem Vlaams-Brabant 1930",
    "addr:housenumber":"22",
    "addr:postcode":"1930",
    "addr:street":"Van Dijcklaan",
    "iso:country":"BE",
    "sg:address":"Van Dijcklaan 22",
    "sg:city":"Zaventem",
    "sg:classifiers":[
        {
            "category":"Retail",
            "subcategory":"Veterinary Services",
            "type":"Services"
        }
    ],
    "sg:phone":"+32 2 721 30 46",
    "sg:postcode":"1930",
    "sg:province":"Vlaams-Brabant",
    "sg:tags":[
        "veterinarian"
    ],
    "wof:name":"Van Rossem W",
    "wof:placetype":"venue"
},
  "geometry": {"coordinates":[4.4740548134,50.8869018555],"type":"Point"}
}