{
  "type": "Feature",
  "properties": {
    "iso:country":"BE",
    "sg:address":"Diesterstraat 61-63",
    "sg:city":"Tessenderlo",
    "sg:classifiers":[
        {
            "category":"Wholesale",
            "subcategory":"Machinery & Supplies",
            "type":"Manufacturing & Wholesale Goods"
        }
    ],
    "sg:phone":"+32 13 66 70 06",
    "sg:postcode":"3980",
    "sg:province":"Limburg",
    "sg:tags":[
        "retail",
        "-",
        "electric"
    ],
    "wof:name":"Electro Meyen",
    "wof:placetype":"venue"
},
  "geometry": {"coordinates":[5.0887651443,51.064239502],"type":"Point"}
}