{
  "type": "Feature",
  "properties": {
    "iso:country":"BE",
    "sg:address":"Rue Frans Hals 27",
    "sg:city":"Anderlecht",
    "sg:orig_category":"Services pour animaux domestiques. Animaux domestiques and accessoires",
    "sg:phone":"+32 2 523 69 03",
    "sg:postcode":"1070",
    "sg:province":"Bruxelles-Capitale",
    "wof:name":"Doggy-coiff",
    "wof:placetype":"venue"
},
  "geometry": {"coordinates":[4.2934980392,50.8243293762],"type":"Point"}
}