{
  "type": "Feature",
  "properties": {
    "iso:country":"BE",
    "sg:address":"Veststraat 20",
    "sg:city":"Scherpenheuvel-zichem",
    "sg:orig_category":"Rev\u00eatements pour sols and murs",
    "sg:phone":"+32 13 77 69 95",
    "sg:postcode":"3271",
    "sg:province":"Vlaams-Brabant",
    "wof:name":"Algemene Bouwwerken B M J",
    "wof:placetype":"venue"
},
  "geometry": {"coordinates":[4.9891471863,50.9981765747],"type":"Point"}
}