{
  "type": "Feature",
  "properties": {
    "iso:country":"BE",
    "sg:address":"Rue Emile Cuvelier 26",
    "sg:city":"Namur",
    "sg:classifiers":[
        {
            "category":"Cafe",
            "type":"Food & Drink"
        }
    ],
    "sg:phone":"+32 81 22 15 94",
    "sg:postcode":"5000",
    "sg:province":"Namur",
    "sg:tags":[
        "snack-bars"
    ],
    "wof:name":"Miam",
    "wof:placetype":"venue"
},
  "geometry": {"coordinates":[4.8665390015,50.4646873474],"type":"Point"}
}