{
  "type": "Feature",
  "properties": {
    "addr:full":"Reinpadstraat 11b17 Genk Limburg 3600",
    "addr:housenumber":"11b17",
    "addr:postcode":"3600",
    "addr:street":"Reinpadstraat",
    "iso:country":"BE",
    "sg:address":"Reinpadstraat 11b17",
    "sg:city":"Genk",
    "sg:orig_category":"Advocaten and juridische adviseurs",
    "sg:phone":"+32 89 30 67 77",
    "sg:postcode":"3600",
    "sg:province":"Limburg",
    "wof:name":"V. Paulissen",
    "wof:placetype":"venue"
},
  "geometry": {"coordinates":[5.5041570663,50.9679870605],"type":"Point"}
}