{
  "type": "Feature",
  "properties": {
    "iso:country":"BE",
    "sg:address":"Eduard Hammanstraat 44",
    "sg:city":"Oostende",
    "sg:classifiers":[
        {
            "category":"Professional",
            "subcategory":"Testing Lab",
            "type":"Services"
        }
    ],
    "sg:phone":"+32 59 33 26 68",
    "sg:postcode":"8400",
    "sg:province":"West-Vlaanderen",
    "sg:tags":[
        "chemist"
    ],
    "wof:name":"Degraeve",
    "wof:placetype":"venue"
},
  "geometry": {"coordinates":[2.944247961,51.2289505005],"type":"Point"}
}