{
  "type": "Feature",
  "properties": {
    "addr:full":"Langerei 22 Brugge West-Vlaanderen 8000",
    "addr:housenumber":"22",
    "addr:postcode":"8000",
    "addr:street":"Langerei",
    "iso:country":"BE",
    "sg:address":"Langerei 22",
    "sg:city":"Brugge",
    "sg:classifiers":[
        {
            "category":"Professional",
            "subcategory":"Management & Consulting",
            "type":"Services"
        }
    ],
    "sg:phone":"+32 50 33 50 99",
    "sg:postcode":"8000",
    "sg:province":"West-Vlaanderen",
    "sg:tags":[
        "tax-consultants"
    ],
    "wof:name":"Vermeulen C",
    "wof:placetype":"venue"
},
  "geometry": {"coordinates":[3.2286090851,51.2153358459],"type":"Point"}
}