{
  "type": "Feature",
  "properties": {
    "iso:country":"BE",
    "sg:address":"Bruggesteenweg 157",
    "sg:city":"Hooglede (gits)",
    "sg:classifiers":[
        {
            "category":"Retail",
            "subcategory":"Auto Repair",
            "type":"Services"
        }
    ],
    "sg:phone":"+32 51 72 53 95",
    "sg:postcode":"8830",
    "sg:province":"West-Vlaanderen",
    "sg:tags":[
        "garage"
    ],
    "wof:name":"Caen-pollet Bvba",
    "wof:placetype":"venue"
},
  "geometry": {"coordinates":[3.1184930801,50.9825897217],"type":"Point"}
}