{
  "type": "Feature",
  "properties": {
    "addr:full":"Westdijk 16 Kapelle-op-den-bos Vlaams-Brabant 1880",
    "addr:housenumber":"16",
    "addr:postcode":"1880",
    "addr:street":"Westdijk",
    "iso:country":"BE",
    "sg:address":"Westdijk 16",
    "sg:city":"Kapelle-op-den-bos",
    "sg:classifiers":[
        {
            "category":"Manufacturing",
            "subcategory":"Jewelry",
            "type":"Manufacturing & Wholesale Goods"
        }
    ],
    "sg:phone":"+32 15 71 38 80",
    "sg:postcode":"1880",
    "sg:province":"Vlaams-Brabant",
    "sg:tags":[
        "plating",
        "silver",
        "gold"
    ],
    "wof:name":"Beurghs Galvano Techniek",
    "wof:placetype":"venue"
},
  "geometry": {"coordinates":[4.3634119034,51.0130653381],"type":"Point"}
}