{
  "type": "Feature",
  "properties": {
    "addr:full":"Ellestraat 26bb Herent Vlaams-Brabant 3020",
    "addr:housenumber":"26bb",
    "addr:postcode":"3020",
    "addr:street":"Ellestraat",
    "iso:country":"BE",
    "sg:address":"Ellestraat 26bb",
    "sg:city":"Herent",
    "sg:orig_category":"Loodgieterij, verwarming and sanitaire installaties",
    "sg:phone":"+32 16 48 25 87",
    "sg:postcode":"3020",
    "sg:province":"Vlaams-Brabant",
    "wof:name":"Fa. Beulens & Zn",
    "wof:placetype":"venue"
},
  "geometry": {"coordinates":[4.6749200821,50.9079055786],"type":"Point"}
}