{
  "type": "Feature",
  "properties": {
    "addr:full":"Kattestraat 32 Ham Limburg 3945",
    "addr:housenumber":"32",
    "addr:postcode":"3945",
    "addr:street":"Kattestraat",
    "iso:country":"BE",
    "sg:address":"Kattestraat 32",
    "sg:city":"Ham",
    "sg:orig_category":"Woningbouw",
    "sg:phone":"+32 11 34 71 46",
    "sg:postcode":"3945",
    "sg:province":"Limburg",
    "wof:name":"Johny Van Olmen",
    "wof:placetype":"venue"
},
  "geometry": {"coordinates":[5.1776199341,51.1046104431],"type":"Point"}
}