{
  "type": "Feature",
  "properties": {
    "iso:country":"BE",
    "sg:address":"Gaverstraat 35",
    "sg:city":"Geraardsbergen (overboelare)",
    "sg:classifiers":[
        {
            "category":"Manufacturing",
            "subcategory":"Rubber & Plastics",
            "type":"Manufacturing & Wholesale Goods"
        }
    ],
    "sg:phone":"+32 54 41 45 45",
    "sg:postcode":"9500",
    "sg:province":"Oost-Vlaanderen",
    "sg:tags":[
        "industrial",
        "-"
    ],
    "wof:name":"Fostham Nv",
    "wof:placetype":"venue"
},
  "geometry": {"coordinates":[3.8796401024,50.7635993958],"type":"Point"}
}