{
  "type": "Feature",
  "properties": {
    "addr:full":"Kouterstraat 123 Zele Oost-Vlaanderen 9240",
    "addr:housenumber":"123",
    "addr:postcode":"9240",
    "addr:street":"Kouterstraat",
    "iso:country":"BE",
    "sg:address":"Kouterstraat 123",
    "sg:city":"Zele",
    "sg:classifiers":[
        {
            "category":"Insurance",
            "subcategory":"Insurance Agent",
            "type":"Services"
        }
    ],
    "sg:phone":"+32 52 44 40 18",
    "sg:postcode":"9240",
    "sg:province":"Oost-Vlaanderen",
    "sg:tags":[
        "broker"
    ],
    "wof:name":"Assurfinance Van Kerckhove Bvba",
    "wof:placetype":"venue"
},
  "geometry": {"coordinates":[4.0272798538,51.06457901],"type":"Point"}
}