{
  "type": "Feature",
  "properties": {
    "iso:country":"BE",
    "sg:address":"Damstraat 60",
    "sg:city":"Hamme",
    "sg:orig_category":"Fietsen Motorfietsen",
    "sg:phone":"+32 52 47 66 66",
    "sg:postcode":"9220",
    "sg:province":"Oost-Vlaanderen",
    "wof:name":"Wauters",
    "wof:placetype":"venue"
},
  "geometry": {"coordinates":[4.1357121468,51.0902252197],"type":"Point"}
}