{
  "type": "Feature",
  "properties": {
    "iso:country":"BE",
    "sg:address":"Hovaerestraat 27",
    "sg:city":"Koekelare",
    "sg:orig_category":"Woningbouw",
    "sg:phone":"+32 51 58 15 13",
    "sg:postcode":"8680",
    "sg:province":"West-Vlaanderen",
    "wof:name":"Peter Bossy",
    "wof:placetype":"venue"
},
  "geometry": {"coordinates":[2.9712510109,51.0927314758],"type":"Point"}
}