{
  "type": "Feature",
  "properties": {
    "iso:country":"BE",
    "sg:address":"Place Verte 20",
    "sg:city":"Tournai",
    "sg:orig_category":"M\u00e9decins and sp\u00e9cialistes",
    "sg:phone":"+32 69 23 55 86",
    "sg:postcode":"7500",
    "sg:province":"Hainaut",
    "wof:name":"Vincent Hamoir",
    "wof:placetype":"venue"
},
  "geometry": {"coordinates":[3.3906810284,50.6114845276],"type":"Point"}
}