{
  "type": "Feature",
  "properties": {
    "iso:country":"BE",
    "sg:address":"Chauss\u00e9e De Mons 31",
    "sg:city":"Tournai (barry - Maulde)",
    "sg:classifiers":[
        {
            "category":"Professional",
            "subcategory":"Art Services",
            "type":"Services"
        }
    ],
    "sg:phone":"+32 69 54 85 77",
    "sg:postcode":"7534",
    "sg:province":"Hainaut",
    "sg:tags":[
        "interior",
        "designer"
    ],
    "wof:name":"Volume",
    "wof:placetype":"venue"
},
  "geometry": {"coordinates":[3.539910078,50.5897483826],"type":"Point"}
}