{
  "type": "Feature",
  "properties": {
    "addr:full":"Rue Omer Lescot 1 Saint-ghislain (hautrage) Hainaut 7334",
    "addr:housenumber":"1",
    "addr:postcode":"7334",
    "addr:street":"Rue Omer Lescot",
    "iso:country":"BE",
    "sg:address":"Rue Omer Lescot 1",
    "sg:city":"Saint-ghislain (hautrage)",
    "sg:classifiers":[
        {
            "category":"Personal",
            "subcategory":"Beauty Salon",
            "type":"Services"
        }
    ],
    "sg:phone":"+32 65 62 07 54",
    "sg:postcode":"7334",
    "sg:province":"Hainaut",
    "sg:tags":[
        "lady",
        "-",
        "hairdressing"
    ],
    "wof:name":"Hairnice Coiffure",
    "wof:placetype":"venue"
},
  "geometry": {"coordinates":[3.7644500732,50.479675293],"type":"Point"}
}