{
  "type": "Feature",
  "properties": {
    "addr:full":"Hospitaalstraat 13 Sint-niklaas Oost-Vlaanderen 9100",
    "addr:housenumber":"13",
    "addr:postcode":"9100",
    "addr:street":"Hospitaalstraat",
    "iso:country":"BE",
    "sg:address":"Hospitaalstraat 13",
    "sg:city":"Sint-niklaas",
    "sg:orig_category":"Apotheken",
    "sg:phone":"+32 3 776 10 64",
    "sg:postcode":"9100",
    "sg:province":"Oost-Vlaanderen",
    "wof:name":"Jozef Schutyser",
    "wof:placetype":"venue"
},
  "geometry": {"coordinates":[4.1491179466,51.1625213623],"type":"Point"}
}