{
  "type": "Feature",
  "properties": {
    "iso:country":"BE",
    "sg:address":"Diksmuidseweg 491",
    "sg:city":"Ieper",
    "sg:orig_category":"Installatie van houten of kunststof schrijnwerk Installatie van metalen schrijnwerk Vloer- and muurb",
    "sg:phone":"+32 57 42 20 16",
    "sg:postcode":"8904",
    "sg:province":"West-Vlaanderen",
    "wof:name":"Vanderjeugt",
    "wof:placetype":"venue"
},
  "geometry": {"coordinates":[2.8498198986,50.9014091492],"type":"Point"}
}