{
  "type": "Feature",
  "properties": {
    "iso:country":"BE",
    "sg:address":"Drijhoek 33",
    "sg:city":"Rijkevorsel",
    "sg:orig_category":"Entretien and r\u00e9parations de voitures. V\u00e9hicules automobiles",
    "sg:phone":"+32 3 314 48 62",
    "sg:postcode":"2310",
    "sg:province":"Antwerpen",
    "wof:name":"Garage Putex",
    "wof:placetype":"venue"
},
  "geometry": {"coordinates":[4.768476963,51.3457336426],"type":"Point"}
}