{
  "type": "Feature",
  "properties": {
    "iso:country":"BE",
    "sg:address":"Blekerijstraat 18",
    "sg:city":"Ardooie",
    "sg:classifiers":[
        {
            "category":"Banks & Credit Unions",
            "subcategory":"Bank",
            "type":"Services"
        }
    ],
    "sg:phone":"+32 51 74 65 31",
    "sg:postcode":"8850",
    "sg:province":"West-Vlaanderen",
    "sg:tags":[
        "savings-banks"
    ],
    "wof:name":"Dipo",
    "wof:placetype":"venue"
},
  "geometry": {"coordinates":[3.2000648975,50.9744796753],"type":"Point"}
}