{
  "type": "Feature",
  "properties": {
    "iso:country":"BE",
    "sg:address":"Kruisstraat 22a",
    "sg:city":"Affligem (hekelgem)",
    "sg:classifiers":[
        {
            "category":"Wholesale",
            "subcategory":"Home Furnishings",
            "type":"Manufacturing & Wholesale Goods"
        }
    ],
    "sg:phone":"+32 53 66 16 77",
    "sg:postcode":"1790",
    "sg:province":"Vlaams-Brabant",
    "sg:tags":[
        "storage",
        "-",
        "furniture"
    ],
    "wof:name":"Bornauw W",
    "wof:placetype":"venue"
},
  "geometry": {"coordinates":[4.1068601608,50.9156608582],"type":"Point"}
}