{
  "type": "Feature",
  "properties": {
    "addr:full":"Van Aumalestraat 22 Anderlecht Bruxelles-Capitale 1070",
    "addr:housenumber":"22",
    "addr:postcode":"1070",
    "addr:street":"Aumalestraat",
    "iso:country":"BE",
    "sg:address":"Van Aumalestraat 22",
    "sg:city":"Anderlecht",
    "sg:classifiers":[
        {
            "category":"Restaurant",
            "type":"Food & Drink"
        }
    ],
    "sg:phone":"+32 2 520 79 36",
    "sg:postcode":"1070",
    "sg:province":"Bruxelles-Capitale",
    "wof:name":"Le Crouton",
    "wof:placetype":"venue"
},
  "geometry": {"coordinates":[4.3078608513,50.8372001648],"type":"Point"}
}