{
  "type": "Feature",
  "properties": {
    "addr:full":"Zaterdagplein 6 Brussel/bruxelles Bruxelles-Capitale 1000",
    "addr:housenumber":"6",
    "addr:postcode":"1000",
    "addr:street":"Zaterdagplein;/",
    "iso:country":"BE",
    "sg:address":"Zaterdagplein 6",
    "sg:city":"Brussel/bruxelles",
    "sg:orig_category":"Drukkerijen and copyshops",
    "sg:phone":"+32 2 227 00 90",
    "sg:postcode":"1000",
    "sg:province":"Bruxelles-Capitale",
    "wof:name":"Valan Printing",
    "wof:placetype":"venue"
},
  "geometry": {"coordinates":[4.3498311043,50.8514976501],"type":"Point"}
}