{
  "type": "Feature",
  "properties": {
    "iso:country":"BE",
    "sg:address":"Watertorenstraat 5b2",
    "sg:city":"Tongeren",
    "sg:orig_category":"Enseignement maternel and primaire",
    "sg:phone":"+32 12 23 23 64",
    "sg:postcode":"3700",
    "sg:province":"Limburg",
    "wof:name":"Vrije Basisschool",
    "wof:placetype":"venue"
},
  "geometry": {"coordinates":[5.459980011,50.7810783386],"type":"Point"}
}