{
  "type": "Feature",
  "properties": {
    "addr:full":"Batterijstraat 78 Bredene West-Vlaanderen 8450",
    "addr:housenumber":"78",
    "addr:postcode":"8450",
    "addr:street":"Batterijstraat",
    "iso:country":"BE",
    "sg:address":"Batterijstraat 78",
    "sg:city":"Bredene",
    "sg:orig_category":"Schoenen",
    "sg:phone":"+32 59 33 16 24",
    "sg:postcode":"8450",
    "sg:province":"West-Vlaanderen",
    "wof:name":"F.a.k.",
    "wof:placetype":"venue"
},
  "geometry": {"coordinates":[2.9977018833,51.2469673157],"type":"Point"}
}