{
  "type": "Feature",
  "properties": {
    "iso:country":"BE",
    "sg:address":"Boslaan 21",
    "sg:city":"Zoersel",
    "sg:orig_category":"Woningbouw",
    "sg:phone":"+32 3 383 67 24",
    "sg:postcode":"2980",
    "sg:province":"Antwerpen",
    "wof:name":"B.k.l.",
    "wof:placetype":"venue"
},
  "geometry": {"coordinates":[4.6688380241,51.270942688],"type":"Point"}
}