{
  "type": "Feature",
  "properties": {
    "iso:country":"BE",
    "sg:address":"Chauss\u00c9e De Bruxelles 21",
    "sg:city":"Mons",
    "sg:orig_category":"Travaux de pl\u00e2trage",
    "sg:phone":"+32 65 33 76 63",
    "sg:postcode":"7000",
    "sg:province":"Hainaut",
    "wof:name":"Master Platre",
    "wof:placetype":"venue"
},
  "geometry": {"coordinates":[3.9574320316,50.4663238525],"type":"Point"}
}