{
  "type": "Feature",
  "properties": {
    "addr:full":"Liersesteenweg 226 Sint-katelijne-waver Antwerpen 2860",
    "addr:housenumber":"226",
    "addr:postcode":"2860",
    "addr:street":"Liersesteenweg",
    "iso:country":"BE",
    "sg:address":"Liersesteenweg 226",
    "sg:city":"Sint-katelijne-waver",
    "sg:classifiers":[
        {
            "category":"Health Services",
            "subcategory":"Health Practitioner",
            "type":"Services"
        }
    ],
    "sg:phone":"+32 15 41 69 65",
    "sg:postcode":"2860",
    "sg:province":"Antwerpen",
    "sg:tags":[
        "osteopath"
    ],
    "wof:name":"De Ryck Peter",
    "wof:placetype":"venue"
},
  "geometry": {"coordinates":[4.4865298271,51.0689849854],"type":"Point"}
}