{
  "type": "Feature",
  "properties": {
    "iso:country":"BE",
    "sg:address":"Nieuwe Landing 4",
    "sg:city":"Ieper (vlamertinge)",
    "sg:classifiers":[
        {
            "category":"Personal",
            "subcategory":"Beauty Salon",
            "type":"Services"
        }
    ],
    "sg:phone":"+32 57 20 30 37",
    "sg:postcode":"8908",
    "sg:province":"West-Vlaanderen",
    "sg:tags":[
        "lady",
        "-",
        "hairdressing"
    ],
    "wof:name":"Heidi",
    "wof:placetype":"venue"
},
  "geometry": {"coordinates":[2.8293390274,50.853515625],"type":"Point"}
}