{
  "type": "Feature",
  "properties": {
    "addr:full":"Hoogstraat 11 Lede Oost-Vlaanderen 9340",
    "addr:housenumber":"11",
    "addr:postcode":"9340",
    "addr:street":"Hoogstraat",
    "iso:country":"BE",
    "sg:address":"Hoogstraat 11",
    "sg:city":"Lede",
    "sg:orig_category":"Activit\u00e9s r\u00e9cr\u00e9atives diverses",
    "sg:phone":"+32 53 80 60 22",
    "sg:postcode":"9340",
    "sg:province":"Oost-Vlaanderen",
    "wof:name":"Postzegelkring Leda",
    "wof:placetype":"venue"
},
  "geometry": {"coordinates":[3.9769508839,50.9639587402],"type":"Point"}
}