{
  "type": "Feature",
  "properties": {
    "addr:full":"Stationsstraat 127 Gavere Oost-Vlaanderen 9890",
    "addr:housenumber":"127",
    "addr:postcode":"9890",
    "addr:street":"Stationsstraat",
    "iso:country":"BE",
    "sg:address":"Stationsstraat 127",
    "sg:city":"Gavere",
    "sg:orig_category":"Baby Pram And Buggy Frames",
    "sg:phone":"+32 9 384 13 46",
    "sg:postcode":"9890",
    "sg:province":"Oost-Vlaanderen",
    "wof:name":"Galvano Chroom B.v.b.a.",
    "wof:placetype":"venue"
},
  "geometry": {"coordinates":[3.6481730938,50.9292221069],"type":"Point"}
}