{
  "type": "Feature",
  "properties": {
    "iso:country":"BE",
    "sg:address":"Rue Du Fourneau 97",
    "sg:city":"Marchin",
    "sg:orig_category":"Voertuigen",
    "sg:phone":"+32 85 21 52 35",
    "sg:postcode":"4570",
    "sg:province":"Li\u00e8ge",
    "wof:name":"Patrick Gregoire",
    "wof:placetype":"venue"
},
  "geometry": {"coordinates":[5.2418107986,50.4820594788],"type":"Point"}
}