{
  "type": "Feature",
  "properties": {
    "addr:full":"Klokkeputstraat 61 Roeselare West-Vlaanderen 8800",
    "addr:housenumber":"61",
    "addr:postcode":"8800",
    "addr:street":"Klokkeputstraat",
    "iso:country":"BE",
    "sg:address":"Klokkeputstraat 61",
    "sg:city":"Roeselare",
    "sg:orig_category":"DIVERSE RECREATIEVE ACTIVITEITEN",
    "sg:phone":"+32 51 26 32 10",
    "sg:postcode":"8800",
    "sg:province":"West-Vlaanderen",
    "wof:name":"De Kleine Postiljon",
    "wof:placetype":"venue"
},
  "geometry": {"coordinates":[3.1051249504,50.9621162415],"type":"Point"}
}