{
  "type": "Feature",
  "properties": {
    "addr:full":"Rue Saint-denis 164 Bruxelles (forest) Bruxelles-Capitale 1190",
    "addr:housenumber":"164",
    "addr:postcode":"1190",
    "addr:street":"Rue Saint-Denis",
    "iso:country":"BE",
    "sg:address":"Rue Saint-denis 164",
    "sg:city":"Bruxelles (forest)",
    "sg:classifiers":[
        {
            "category":"Landmark",
            "subcategory":"Ruins",
            "type":"Public Place"
        }
    ],
    "sg:phone":"+32 2 346 44 22",
    "sg:postcode":"1190",
    "sg:province":"Bruxelles-Capitale",
    "sg:tags":[
        "conservation",
        "-",
        "archive",
        "destruction"
    ],
    "wof:name":"M C A Destruction & Recycling",
    "wof:placetype":"venue"
},
  "geometry": {"coordinates":[4.3205871582,50.8188819885],"type":"Point"}
}