{
  "type": "Feature",
  "properties": {
    "addr:full":"Patronaatstraat 21 Edegem Antwerpen 2650",
    "addr:housenumber":"21",
    "addr:postcode":"2650",
    "addr:street":"Patronaatstraat",
    "iso:country":"BE",
    "sg:address":"Patronaatstraat 21",
    "sg:city":"Edegem",
    "sg:orig_category":"Enseignement maternel and primaire",
    "sg:phone":"+32 3 457 22 84",
    "sg:postcode":"2650",
    "sg:province":"Antwerpen",
    "wof:name":"Vrije Basisschool",
    "wof:placetype":"venue"
},
  "geometry": {"coordinates":[4.4420552254,51.1596336365],"type":"Point"}
}