{
  "type": "Feature",
  "properties": {
    "addr:full":"Rue Du Boqueteau 3 Li\u00c8ge Li\u00e8ge 4000",
    "addr:housenumber":"3",
    "addr:postcode":"4000",
    "addr:street":"Rue Du Boqueteau",
    "iso:country":"BE",
    "sg:address":"Rue Du Boqueteau 3",
    "sg:city":"Li\u00c8ge",
    "sg:orig_category":"Boekhouders",
    "sg:phone":"+32 4 252 44 28",
    "sg:postcode":"4000",
    "sg:province":"Li\u00e8ge",
    "wof:name":"Georges Lemaire",
    "wof:placetype":"venue"
},
  "geometry": {"coordinates":[5.5574069023,50.6212997437],"type":"Point"}
}