{
  "type": "Feature",
  "properties": {
    "iso:country":"BE",
    "sg:address":"Sanatorialaan 39",
    "sg:city":"Halle (buizingen)",
    "sg:classifiers":[
        {
            "category":"Health Services",
            "subcategory":"Doctor",
            "type":"Services"
        }
    ],
    "sg:phone":"+32 2 356 64 39",
    "sg:postcode":"1501",
    "sg:province":"Vlaams-Brabant",
    "sg:tags":[
        "medicinephysicians",
        "surgeon"
    ],
    "wof:name":"Ghyselinck Astrid",
    "wof:placetype":"venue"
},
  "geometry": {"coordinates":[4.2688221931,50.739654541],"type":"Point"}
}