{
  "type": "Feature",
  "properties": {
    "addr:full":"Lange Herentalsestraat 50 Antwerpen Antwerpen 2018",
    "addr:housenumber":"50",
    "addr:postcode":"2018",
    "addr:street":"Lange Herentalsestraat",
    "iso:country":"BE",
    "sg:address":"Lange Herentalsestraat 50",
    "sg:city":"Antwerpen",
    "sg:classifiers":[
        {
            "category":"Banks & Credit Unions",
            "subcategory":"Financial Services",
            "type":"Services"
        }
    ],
    "sg:phone":"+32 3 233 47 50",
    "sg:postcode":"2018",
    "sg:province":"Antwerpen",
    "sg:tags":[
        "group"
    ],
    "wof:name":"Anchis Nv",
    "wof:placetype":"venue"
},
  "geometry": {"coordinates":[4.4173169136,51.2148284912],"type":"Point"}
}