{
  "type": "Feature",
  "properties": {
    "iso:country":"BE",
    "sg:address":"Hasseltsesteenweg 366",
    "sg:city":"Sint-truiden",
    "sg:orig_category":"Fruitteelt",
    "sg:phone":"+32 11 68 47 53",
    "sg:postcode":"3800",
    "sg:province":"Limburg",
    "wof:name":"Jacques Eddy En Rohnny",
    "wof:placetype":"venue"
},
  "geometry": {"coordinates":[5.2024002075,50.8291053772],"type":"Point"}
}