{
  "type": "Feature",
  "properties": {
    "addr:full":"Place Des Quatre Grands 2 Jemeppe-sur-sambre Li\u00e8ge 4900",
    "addr:housenumber":"2",
    "addr:postcode":"4900",
    "addr:street":"Place Des Quatre Grands",
    "iso:country":"BE",
    "sg:address":"Place Des Quatre Grands 2",
    "sg:city":"Jemeppe-sur-sambre",
    "sg:classifiers":[
        {
            "category":"Taxi",
            "type":"Transportation"
        }
    ],
    "sg:phone":"+32 4 234 30 30",
    "sg:postcode":"4900",
    "sg:province":"Li\u00e8ge",
    "wof:name":"Taxis De Seraing",
    "wof:placetype":"venue"
},
  "geometry": {"coordinates":[5.8635501862,50.4911689758],"type":"Point"}
}