{
  "type": "Feature",
  "properties": {
    "addr:full":"Rue Du Flosse 2 Libramont-chevigny (recogne) Luxembourg 6800",
    "addr:housenumber":"2",
    "addr:postcode":"6800",
    "addr:street":"Rue Du Flosse",
    "iso:country":"BE",
    "sg:address":"Rue Du Flosse 2",
    "sg:city":"Libramont-chevigny (recogne)",
    "sg:classifiers":[
        {
            "category":"Shopping",
            "subcategory":"Pets & Pet Supplies",
            "type":"Retail Goods"
        }
    ],
    "sg:phone":"+32 61 23 42 51",
    "sg:postcode":"6800",
    "sg:province":"Luxembourg",
    "sg:tags":[
        "shop",
        "-"
    ],
    "wof:name":"Tom & Co",
    "wof:placetype":"venue"
},
  "geometry": {"coordinates":[5.3678350449,49.9124565125],"type":"Point"}
}