{
  "type": "Feature",
  "properties": {
    "iso:country":"BE",
    "sg:address":"Murissonstraat 260",
    "sg:city":"Menen",
    "sg:classifiers":[
        {
            "category":"Organizations",
            "subcategory":"Community Association",
            "type":"Services"
        }
    ],
    "sg:phone":"+32 56 41 12 01",
    "sg:postcode":"8930",
    "sg:province":"West-Vlaanderen",
    "sg:tags":[
        "cultural"
    ],
    "wof:name":"Stichting Ons Erfdeel",
    "wof:placetype":"venue"
},
  "geometry": {"coordinates":[3.1532800198,50.7858886719],"type":"Point"}
}