{
  "type": "Feature",
  "properties": {
    "iso:country":"BE",
    "sg:address":"Bredabaan 666",
    "sg:city":"Wuustwezel",
    "sg:orig_category":"Huisdierenkwekers",
    "sg:phone":"+32 3 669 72 40",
    "sg:postcode":"2990",
    "sg:province":"Antwerpen",
    "wof:name":"A.a.c. Linda's Farm",
    "wof:placetype":"venue"
},
  "geometry": {"coordinates":[4.5731291771,51.3751335144],"type":"Point"}
}