{
  "type": "Feature",
  "properties": {
    "addr:full":"Rumbeeksesteenweg 131 Roeselare West-Vlaanderen 8800",
    "addr:housenumber":"131",
    "addr:postcode":"8800",
    "addr:street":"Rumbeeksesteenweg",
    "iso:country":"BE",
    "sg:address":"Rumbeeksesteenweg 131",
    "sg:city":"Roeselare",
    "sg:classifiers":[
        {
            "category":"Insurance",
            "subcategory":"Insurance Agent",
            "type":"Services"
        }
    ],
    "sg:phone":"+32 51 24 24 77",
    "sg:postcode":"8800",
    "sg:province":"West-Vlaanderen",
    "sg:tags":[
        "verzekeringsmakelaars",
        "expert"
    ],
    "wof:name":"Deroo Johan Zakenkantoor",
    "wof:placetype":"venue"
},
  "geometry": {"coordinates":[3.1301429272,50.9399032593],"type":"Point"}
}