{
  "type": "Feature",
  "properties": {
    "addr:full":"Mechelsestraat 111 Leuven Vlaams-Brabant 3000",
    "addr:housenumber":"111",
    "addr:postcode":"3000",
    "addr:street":"Mechelsestraat",
    "iso:country":"BE",
    "sg:address":"Mechelsestraat 111",
    "sg:city":"Leuven",
    "sg:classifiers":[
        {
            "category":"Organizations",
            "subcategory":"Community Association",
            "type":"Services"
        }
    ],
    "sg:phone":"+32 16 22 81 07",
    "sg:postcode":"3000",
    "sg:province":"Vlaams-Brabant",
    "sg:tags":[
        "cultural"
    ],
    "wof:name":"C.c.oratori\u00ebnhof Vzw",
    "wof:placetype":"venue"
},
  "geometry": {"coordinates":[4.6982932091,50.8826446533],"type":"Point"}
}