{
  "type": "Feature",
  "properties": {
    "iso:country":"BE",
    "sg:address":"Mesenstraat 35",
    "sg:city":"Heuvelland (wijtschate)",
    "sg:classifiers":[
        {
            "category":"Health Services",
            "subcategory":"Health Practitioner",
            "type":"Services"
        }
    ],
    "sg:phone":"+32 57 44 55 72",
    "sg:postcode":"8953",
    "sg:province":"West-Vlaanderen",
    "sg:tags":[
        "physiotherapist"
    ],
    "wof:name":"Delplace S",
    "wof:placetype":"venue"
},
  "geometry": {"coordinates":[2.8626461029,50.7586517334],"type":"Point"}
}