{
  "type": "Feature",
  "properties": {
    "addr:full":"Rue Du Choeur 47 Bruxelles (molenbeek-saint-jean) Bruxelles-Capitale 1080",
    "addr:housenumber":"47",
    "addr:postcode":"1080",
    "addr:street":"Rue Du Choeur",
    "iso:country":"BE",
    "sg:address":"Rue Du Choeur 47",
    "sg:city":"Bruxelles (molenbeek-saint-jean)",
    "sg:classifiers":[
        {
            "category":"Manufacturing",
            "subcategory":"Building Materials",
            "type":"Manufacturing & Wholesale Goods"
        }
    ],
    "sg:postcode":"1080",
    "sg:province":"Bruxelles-Capitale",
    "sg:tags":[
        "fixture",
        "store"
    ],
    "wof:name":"Alexandria",
    "wof:placetype":"venue"
},
  "geometry": {"coordinates":[4.3413720131,50.8583869934],"type":"Point"}
}