{
  "type": "Feature",
  "properties": {
    "addr:full":"Zwaaikomstraat 34 Roeselare West-Vlaanderen 8800",
    "addr:housenumber":"34",
    "addr:postcode":"8800",
    "addr:street":"Zwaaikomstraat",
    "iso:country":"BE",
    "sg:address":"Zwaaikomstraat 34",
    "sg:city":"Roeselare",
    "sg:classifiers":[
        {
            "category":"Structure",
            "subcategory":"Building",
            "type":"Public Place"
        }
    ],
    "sg:phone":"+32 51 26 43 80",
    "sg:postcode":"8800",
    "sg:province":"West-Vlaanderen",
    "sg:tags":[
        "apartment"
    ],
    "wof:name":"Verstraete Nv",
    "wof:placetype":"venue"
},
  "geometry": {"coordinates":[3.1506299973,50.9508514404],"type":"Point"}
}