{
  "type": "Feature",
  "properties": {
    "iso:country":"BE",
    "sg:address":"Rijfstraat 2",
    "sg:city":"Antwerpen",
    "sg:classifiers":[
        {
            "category":"Professional",
            "subcategory":"Art Services",
            "type":"Services"
        }
    ],
    "sg:phone":"+32 3 225 17 01",
    "sg:postcode":"2018",
    "sg:province":"Antwerpen",
    "sg:tags":[
        "-",
        "valuer"
    ],
    "wof:name":"Juweelexpertise",
    "wof:placetype":"venue"
},
  "geometry": {"coordinates":[4.4194908142,51.2161407471],"type":"Point"}
}