{
  "type": "Feature",
  "properties": {
    "addr:full":"Graaf Van Egmontstraat 5 Mechelen Antwerpen 2800",
    "addr:housenumber":"5",
    "addr:postcode":"2800",
    "addr:street":"Graaf Van Egmontstraat",
    "iso:country":"BE",
    "sg:address":"Graaf Van Egmontstraat 5",
    "sg:city":"Mechelen",
    "sg:orig_category":"Dameskledingzaken",
    "sg:phone":"+32 15 41 62 21",
    "sg:postcode":"2800",
    "sg:province":"Antwerpen",
    "wof:name":"Mian",
    "wof:placetype":"venue"
},
  "geometry": {"coordinates":[4.4821949005,51.0223884583],"type":"Point"}
}