{
  "type": "Feature",
  "properties": {
    "addr:full":"Kloosterstraat 1 Merksplas Antwerpen 2330",
    "addr:housenumber":"1",
    "addr:postcode":"2330",
    "addr:street":"Kloosterstraat",
    "iso:country":"BE",
    "sg:address":"Kloosterstraat 1",
    "sg:city":"Merksplas",
    "sg:orig_category":"Antiquit\u00e9s",
    "sg:phone":"+32 14 63 26 93",
    "sg:postcode":"2330",
    "sg:province":"Antwerpen",
    "wof:name":"Huis Merksplas",
    "wof:placetype":"venue"
},
  "geometry": {"coordinates":[4.8639001846,51.3599281311],"type":"Point"}
}