{
  "type": "Feature",
  "properties": {
    "addr:full":"Oudestraat 107 Boortmeerbeek Vlaams-Brabant 3190",
    "addr:housenumber":"107",
    "addr:postcode":"3190",
    "addr:street":"Oudestraat",
    "iso:country":"BE",
    "sg:address":"Oudestraat 107",
    "sg:city":"Boortmeerbeek",
    "sg:classifiers":[
        {
            "category":"Bakery",
            "type":"Food & Drink"
        }
    ],
    "sg:phone":"+32 16 60 49 65",
    "sg:postcode":"3190",
    "sg:province":"Vlaams-Brabant",
    "sg:tags":[
        "confectioner",
        "baker"
    ],
    "wof:name":"Bosmans Brood & Banket Bvba",
    "wof:placetype":"venue"
},
  "geometry": {"coordinates":[4.5975499153,50.9626617432],"type":"Point"}
}