{
  "type": "Feature",
  "properties": {
    "iso:country":"BE",
    "sg:address":"Rue De L'eglise 21",
    "sg:city":"Frasnes-lez-anvaing",
    "sg:orig_category":"Rundveehouders",
    "sg:phone":"+32 69 76 83 14",
    "sg:postcode":"7912",
    "sg:province":"Hainaut",
    "wof:name":"Roger Debode",
    "wof:placetype":"venue"
},
  "geometry": {"coordinates":[3.5683009624,50.7129364014],"type":"Point"}
}