{
  "type": "Feature",
  "properties": {
    "addr:full":"Rijksweg 38 Maasmechelen (leut) Limburg 3630",
    "addr:housenumber":"38",
    "addr:postcode":"3630",
    "addr:street":"Rijksweg",
    "iso:country":"BE",
    "sg:address":"Rijksweg 38",
    "sg:city":"Maasmechelen (leut)",
    "sg:classifiers":[
        {
            "category":"Home & Garden",
            "subcategory":"Building Materials",
            "type":"Retail Goods"
        }
    ],
    "sg:phone":"+32 89 75 51 28",
    "sg:postcode":"3630",
    "sg:province":"Limburg",
    "sg:tags":[
        "granite",
        "stone",
        "natural",
        "marble"
    ],
    "wof:name":"Schepers",
    "wof:placetype":"venue"
},
  "geometry": {"coordinates":[5.7015500069,50.9793891907],"type":"Point"}
}