{
  "type": "Feature",
  "properties": {
    "addr:full":"Chauss\u00c9e Bara 154 Braine-l'alleud Brabant Wallon 1420",
    "addr:housenumber":"154",
    "addr:postcode":"1420",
    "addr:street":"Chausse\u0301E Bara",
    "iso:country":"BE",
    "sg:address":"Chauss\u00c9e Bara 154",
    "sg:city":"Braine-l'alleud",
    "sg:orig_category":"Brood, gebak and snoepgoed",
    "sg:phone":"+32 2 384 27 37",
    "sg:postcode":"1420",
    "sg:province":"Brabant Wallon",
    "wof:name":"Nancy Bernard",
    "wof:placetype":"venue"
},
  "geometry": {"coordinates":[-0.7711730003,47.3931159973],"type":"Point"}
}