{
  "type": "Feature",
  "properties": {
    "addr:full":"Kraaiveldstraat 9e Zonnebeke (passendale) West-Vlaanderen 8980",
    "addr:housenumber":"9e",
    "addr:postcode":"8980",
    "addr:street":"Kraaiveldstraat",
    "iso:country":"BE",
    "sg:address":"Kraaiveldstraat 9e",
    "sg:city":"Zonnebeke (passendale)",
    "sg:classifiers":[
        {
            "category":"Health Services",
            "subcategory":"Doctor",
            "type":"Services"
        }
    ],
    "sg:phone":"+32 51 78 00 36",
    "sg:postcode":"8980",
    "sg:province":"West-Vlaanderen",
    "sg:tags":[
        "medicinephysicians",
        "surgeon"
    ],
    "wof:name":"Ingelaere Jan",
    "wof:placetype":"venue"
},
  "geometry": {"coordinates":[2.9872550964,50.8730812073],"type":"Point"}
}