{
  "type": "Feature",
  "properties": {
    "iso:country":"BE",
    "sg:address":"Westelsebaan 144",
    "sg:city":"Scherpenheuvel-zichem",
    "sg:orig_category":"Rev\u00eatements de sols and murs",
    "sg:phone":"+32 13 77 12 09",
    "sg:postcode":"3271",
    "sg:province":"Vlaams-Brabant",
    "wof:name":"Claes H",
    "wof:placetype":"venue"
},
  "geometry": {"coordinates":[4.9817018509,51.0276947021],"type":"Point"}
}