{
  "type": "Feature",
  "properties": {
    "addr:full":"Honingstraat 17 Olen Antwerpen 2250",
    "addr:housenumber":"17",
    "addr:postcode":"2250",
    "addr:street":"Honingstraat",
    "iso:country":"BE",
    "sg:address":"Honingstraat 17",
    "sg:city":"Olen",
    "sg:orig_category":"Autombile concessionaires",
    "sg:phone":"+32 14 21 37 71",
    "sg:postcode":"2250",
    "sg:province":"Antwerpen",
    "wof:name":"Gar Van Olmen",
    "wof:placetype":"venue"
},
  "geometry": {"coordinates":[4.865664959,51.1512184143],"type":"Point"}
}