{
  "type": "Feature",
  "properties": {
    "iso:country":"BE",
    "sg:address":"Brusselbaan 239",
    "sg:city":"Affligem (hekelgem)",
    "sg:classifiers":[
        {
            "category":"Professional",
            "subcategory":"Management & Consulting",
            "type":"Services"
        }
    ],
    "sg:phone":"+32 53 68 18 16",
    "sg:postcode":"1790",
    "sg:province":"Vlaams-Brabant",
    "sg:tags":[
        "consultant",
        "agency",
        "advertising"
    ],
    "wof:name":"Estaloca Design",
    "wof:placetype":"venue"
},
  "geometry": {"coordinates":[4.117454052,50.9123191833],"type":"Point"}
}