{
  "type": "Feature",
  "properties": {
    "iso:country":"BE",
    "sg:address":"Legeweg 229",
    "sg:city":"Oostkamp",
    "sg:orig_category":"Plaatsen van vloer- and muurbekleding Schilders",
    "sg:phone":"+32 50 35 76 73",
    "sg:postcode":"8020",
    "sg:province":"West-Vlaanderen",
    "wof:name":"Peter Taveirne",
    "wof:placetype":"venue"
},
  "geometry": {"coordinates":[3.2390320301,51.1775588989],"type":"Point"}
}