{
  "type": "Feature",
  "properties": {
    "iso:country":"BE",
    "sg:address":"Bus 7",
    "sg:city":"Eeklo",
    "sg:orig_category":"Rundveehouders",
    "sg:phone":"+32 9 378 19 16",
    "sg:postcode":"9900",
    "sg:province":"Oost-Vlaanderen",
    "wof:name":"De Baets Chr.& P.",
    "wof:placetype":"venue"
},
  "geometry": {"coordinates":[3.584966898,51.2023506165],"type":"Point"}
}