{
  "type": "Feature",
  "properties": {
    "iso:country":"BE",
    "sg:address":"Rue Tr\u00e9mouroux 9",
    "sg:city":"Gembloux-sur-orneau (gembloux)",
    "sg:classifiers":[
        {
            "category":"Personal",
            "subcategory":"Psychics & Astrologers",
            "type":"Services"
        }
    ],
    "sg:phone":"+32 2 384 72 57",
    "sg:postcode":"5030",
    "sg:province":"Namur",
    "sg:tags":[
        "astrology"
    ],
    "wof:name":"Centre D'etudes Astrologiques Asbl",
    "wof:placetype":"venue"
},
  "geometry": {"coordinates":[4.6774902344,50.5893592834],"type":"Point"}
}