{
  "type": "Feature",
  "properties": {
    "addr:full":"Rue De La Soye 4 Tintigny (saint-vincent) Luxembourg 6730",
    "addr:housenumber":"4",
    "addr:postcode":"6730",
    "addr:street":"Rue De La Soye;Saint-Vincent",
    "iso:country":"BE",
    "sg:address":"Rue De La Soye 4",
    "sg:city":"Tintigny (saint-vincent)",
    "sg:classifiers":[
        {
            "category":"Building & Trades",
            "subcategory":"Landscaping Services",
            "type":"Services"
        }
    ],
    "sg:phone":"+32 63 44 41 37",
    "sg:postcode":"6730",
    "sg:province":"Luxembourg",
    "sg:tags":[
        "forestry"
    ],
    "wof:name":"Van Der Werf Bois Sprl",
    "wof:placetype":"venue"
},
  "geometry": {"coordinates":[5.5135030746,49.6826934814],"type":"Point"}
}