{
  "type": "Feature",
  "properties": {
    "addr:full":"Vlamertingseweg 21 Poperinge West-Vlaanderen 8970",
    "addr:housenumber":"21",
    "addr:postcode":"8970",
    "addr:street":"Vlamertingseweg",
    "iso:country":"BE",
    "sg:address":"Vlamertingseweg 21",
    "sg:city":"Poperinge",
    "sg:orig_category":"Pluimveekwekers Rundveehouders Varkenskwekers",
    "sg:phone":"+32 57 33 43 29",
    "sg:postcode":"8970",
    "sg:province":"West-Vlaanderen",
    "wof:name":"Gery Beirnaert",
    "wof:placetype":"venue"
},
  "geometry": {"coordinates":[2.7815721035,50.824256897],"type":"Point"}
}