{
  "type": "Feature",
  "properties": {
    "iso:country":"BE",
    "sg:address":"Drie Hofveldenlaan 44",
    "sg:city":"Dilbeek",
    "sg:orig_category":"Plaatsen van vloer- and muurbekleding Schilders",
    "sg:phone":"+32 2 582 72 23",
    "sg:postcode":"1700",
    "sg:province":"Vlaams-Brabant",
    "wof:name":"Christiaan Banckaert",
    "wof:placetype":"venue"
},
  "geometry": {"coordinates":[4.2073049545,50.8754005432],"type":"Point"}
}