{
  "type": "Feature",
  "properties": {
    "addr:full":"Statiestraat 9 Zonnebeke (passendale) West-Vlaanderen 8980",
    "addr:housenumber":"9",
    "addr:postcode":"8980",
    "addr:street":"Statiestraat",
    "iso:country":"BE",
    "sg:address":"Statiestraat 9",
    "sg:city":"Zonnebeke (passendale)",
    "sg:classifiers":[
        {
            "category":"Professional",
            "subcategory":"Art Services",
            "type":"Services"
        }
    ],
    "sg:phone":"+32 51 77 91 26",
    "sg:postcode":"8980",
    "sg:province":"West-Vlaanderen",
    "sg:tags":[
        "photographer"
    ],
    "wof:name":"Jos Studio (douchy)",
    "wof:placetype":"venue"
},
  "geometry": {"coordinates":[3.0223948956,50.8994407654],"type":"Point"}
}