{
  "type": "Feature",
  "properties": {
    "iso:country":"BE",
    "sg:address":"Rue De Franchimont 54",
    "sg:city":"Florennes",
    "sg:orig_category":"Huisdierenkwekers",
    "sg:phone":"+32 71 68 60 64",
    "sg:postcode":"5620",
    "sg:province":"Namur",
    "wof:name":"Elevage Of Sweetheartfellows",
    "wof:placetype":"venue"
},
  "geometry": {"coordinates":[4.6179738045,50.2271499634],"type":"Point"}
}