{
  "type": "Feature",
  "properties": {
    "addr:full":"9 Rue Du Bassin Collecteur 1130 Haren Bruxelles 9",
    "addr:housenumber":"9;1130",
    "addr:street":"Rue Du Bassin Collecteur",
    "iso:country":"BE",
    "sg:address":"9",
    "sg:city":"Rue Du Bassin Collecteur 1130 Haren Bruxelles",
    "sg:classifiers":[
        {
            "category":"Utilities",
            "subcategory":"Telephone",
            "type":"Services"
        }
    ],
    "sg:phone":"+32 2 215 13 00",
    "sg:postcode":"9",
    "sg:tags":[
        "telecommunication"
    ],
    "wof:name":"Copel Sa",
    "wof:placetype":"venue"
},
  "geometry": {"coordinates":[4.4206228256,50.8851318359],"type":"Point"}
}