{
  "type": "Feature",
  "properties": {
    "addr:full":"Ruisbroeksesteenweg 188 Sint-pieters-leeuw Vlaams-Brabant 1601",
    "addr:housenumber":"188",
    "addr:postcode":"1601",
    "addr:street":"Ruisbroeksesteenweg",
    "iso:country":"BE",
    "sg:address":"Ruisbroeksesteenweg 188",
    "sg:city":"Sint-pieters-leeuw",
    "sg:orig_category":"Fleurs and plantes",
    "sg:phone":"+32 2 378 35 39",
    "sg:postcode":"1601",
    "sg:province":"Vlaams-Brabant",
    "wof:name":"Guy Borremans",
    "wof:placetype":"venue"
},
  "geometry": {"coordinates":[4.2896380424,50.789276123],"type":"Point"}
}