{
  "type": "Feature",
  "properties": {
    "addr:full":"Clos Des Jonquilles 20 Moeskroen/mouscron Hainaut 7712",
    "addr:housenumber":"20",
    "addr:postcode":"7712",
    "addr:street":"Clos Des Jonquilles",
    "iso:country":"BE",
    "sg:address":"Clos Des Jonquilles 20",
    "sg:city":"Moeskroen/mouscron",
    "sg:classifiers":[
        {
            "category":"Arena",
            "subcategory":"Sports Club",
            "type":"Entertainment"
        }
    ],
    "sg:phone":"+32 56 33 19 61",
    "sg:postcode":"7712",
    "sg:province":"Hainaut",
    "sg:tags":[
        "terrain",
        "hors",
        "de",
        "installation",
        "sportifs"
    ],
    "wof:name":"R.u.s. Herseautoise",
    "wof:placetype":"venue"
},
  "geometry": {"coordinates":[3.2535879612,50.714931488],"type":"Point"}
}