{
  "type": "Feature",
  "properties": {
    "addr:full":"Karel Govaertsstraat 13bb Heist-op-den-berg Antwerpen 2222",
    "addr:housenumber":"13bb",
    "addr:postcode":"2222",
    "addr:street":"Karel Govaertsstraat",
    "iso:country":"BE",
    "sg:address":"Karel Govaertsstraat 13bb",
    "sg:city":"Heist-op-den-berg",
    "sg:orig_category":"Meubles D\u00e9taillants, Am\u00e9nagement de B\u00e2timents et de Cuisines. Eclairage et \u00e9quipements du foyer",
    "sg:phone":"+32 15 24 63 68",
    "sg:postcode":"2222",
    "sg:province":"Antwerpen",
    "wof:name":"Leenbakker",
    "wof:placetype":"venue"
},
  "geometry": {"coordinates":[4.7292399406,51.1032218933],"type":"Point"}
}