{
  "type": "Feature",
  "properties": {
    "addr:full":"Avenue Des Etriers 11 Bruxelles (woluwe-saint-pierre) Bruxelles-Capitale 1150",
    "addr:housenumber":"11",
    "addr:postcode":"1150",
    "addr:street":"Avenue Des Etriers",
    "iso:country":"BE",
    "sg:address":"Avenue Des Etriers 11",
    "sg:city":"Bruxelles (woluwe-saint-pierre)",
    "sg:classifiers":[
        {
            "category":"Social Services",
            "subcategory":"Job Training",
            "type":"Services"
        }
    ],
    "sg:phone":"+32 2 771 98 22",
    "sg:postcode":"1150",
    "sg:province":"Bruxelles-Capitale",
    "sg:tags":[
        "personnel"
    ],
    "wof:name":"Assertifuture",
    "wof:placetype":"venue"
},
  "geometry": {"coordinates":[4.464838028,50.8364830017],"type":"Point"}
}