{
  "type": "Feature",
  "properties": {
    "addr:full":"Rue Du Pont 35 Bouillon Luxembourg 6830",
    "addr:housenumber":"35",
    "addr:postcode":"6830",
    "addr:street":"Rue Du Pont",
    "iso:country":"BE",
    "sg:address":"Rue Du Pont 35",
    "sg:city":"Bouillon",
    "sg:orig_category":"Tabac",
    "sg:phone":"+32 61 46 64 39",
    "sg:postcode":"6830",
    "sg:province":"Luxembourg",
    "wof:name":"Denis - Martial Tabacs",
    "wof:placetype":"venue"
},
  "geometry": {"coordinates":[5.0699849129,49.7954597473],"type":"Point"}
}