{
  "type": "Feature",
  "properties": {
    "iso:country":"BE",
    "sg:address":"Rue De La Tombe 100",
    "sg:city":"Charleroi",
    "sg:orig_category":"Openbare veiligheid",
    "sg:phone":"+32 71 43 74 72",
    "sg:postcode":"6001",
    "sg:province":"Hainaut",
    "wof:name":"Police F\u00c9d\u00c9rale/federale Politie",
    "wof:placetype":"venue"
},
  "geometry": {"coordinates":[4.4448251724,50.3973655701],"type":"Point"}
}