{
  "type": "Feature",
  "properties": {
    "iso:country":"BE",
    "sg:address":"Rue De La 4\u00c8me Ecluse 0",
    "sg:city":"Charleroi (grand)",
    "sg:orig_category":"Mat\u00e9riaux de construction Gr",
    "sg:phone":"+32 71 20 60 00",
    "sg:postcode":"6044",
    "sg:province":"Hainaut",
    "wof:name":"Meusagra",
    "wof:placetype":"venue"
},
  "geometry": {"coordinates":[4.3966817856,50.4354782104],"type":"Point"}
}