{
  "type": "Feature",
  "properties": {
    "iso:country":"BE",
    "sg:address":"Noorderlaan 32",
    "sg:city":"Antwerpen",
    "sg:classifiers":[
        {
            "category":"Autos & Motor Vehicles",
            "subcategory":"Automobile Sales",
            "type":"Retail Goods"
        }
    ],
    "sg:phone":"+32 3 220 99 11",
    "sg:postcode":"2060",
    "sg:province":"Antwerpen",
    "sg:tags":[
        "car",
        "used",
        "-"
    ],
    "wof:name":"Gman-verbeeck",
    "wof:placetype":"venue"
},
  "geometry": {"coordinates":[4.4209651947,51.2371253967],"type":"Point"}
}