{
  "type": "Feature",
  "properties": {
    "addr:full":"Grand-rue 41-43 Arlon Luxembourg 6700",
    "addr:postcode":"41-43;6700",
    "addr:street":"Grand-Rue",
    "iso:country":"BE",
    "sg:address":"Grand-rue 41-43",
    "sg:city":"Arlon",
    "sg:classifiers":[
        {
            "category":"Professional",
            "subcategory":"Testing Lab",
            "type":"Services"
        }
    ],
    "sg:phone":"+32 63 22 40 54",
    "sg:postcode":"6700",
    "sg:province":"Luxembourg",
    "sg:tags":[
        "chemist"
    ],
    "wof:name":"Kieffer Ph",
    "wof:placetype":"venue"
},
  "geometry": {"coordinates":[5.8154249191,49.6829681396],"type":"Point"}
}