{
  "type": "Feature",
  "properties": {
    "iso:country":"BE",
    "sg:address":"Voormezelestraat 4",
    "sg:city":"Heuvelland",
    "sg:orig_category":"Rundveehouders Varkenskwekers",
    "sg:phone":"+32 57 44 43 55",
    "sg:postcode":"8953",
    "sg:province":"West-Vlaanderen",
    "wof:name":"Jaak Degroote",
    "wof:placetype":"venue"
},
  "geometry": {"coordinates":[2.8750538826,50.8022155762],"type":"Point"}
}