{
  "type": "Feature",
  "properties": {
    "addr:full":"Place Des Peintres 5 Louvain Brabant Wallon 1348",
    "addr:housenumber":"5",
    "addr:postcode":"1348",
    "addr:street":"Place Des Peintres",
    "iso:country":"BE",
    "sg:address":"Place Des Peintres 5",
    "sg:city":"Louvain",
    "sg:orig_category":"Architecten",
    "sg:phone":"+32 10 45 17 49",
    "sg:postcode":"1348",
    "sg:province":"Brabant Wallon",
    "wof:name":"Mertens",
    "wof:placetype":"venue"
},
  "geometry": {"coordinates":[4.6072559357,50.6662826538],"type":"Point"}
}