{
  "type": "Feature",
  "properties": {
    "iso:country":"BE",
    "sg:address":"Immerzeeldreef 62",
    "sg:city":"Aalst",
    "sg:orig_category":"D\u00e9taillants en pi\u00e8ces and accessoires de voitures",
    "sg:phone":"+32 53 21 15 64",
    "sg:postcode":"9300",
    "sg:province":"Oost-Vlaanderen",
    "wof:name":"D'hondt",
    "wof:placetype":"venue"
},
  "geometry": {"coordinates":[4.0687770844,50.929523468],"type":"Point"}
}