{
  "type": "Feature",
  "properties": {
    "iso:country":"BE",
    "sg:address":"Lindekensstraat 41",
    "sg:city":"Lebbeke",
    "sg:classifiers":[
        {
            "category":"Real Estate",
            "subcategory":"Developer",
            "type":"Services"
        }
    ],
    "sg:phone":"+32 52 35 67 26",
    "sg:postcode":"9280",
    "sg:province":"Oost-Vlaanderen",
    "sg:tags":[
        "plomberie",
        "chauffage",
        "mat\u00e9riel",
        "gr",
        "pour"
    ],
    "wof:name":"Dande",
    "wof:placetype":"venue"
},
  "geometry": {"coordinates":[4.1537089348,50.9980621338],"type":"Point"}
}