{
  "type": "Feature",
  "properties": {
    "iso:country":"BE",
    "sg:address":"Molenberg 11",
    "sg:city":"Dilbeek",
    "sg:classifiers":[
        {
            "category":"Insurance",
            "subcategory":"Insurance Agent",
            "type":"Services"
        }
    ],
    "sg:phone":"+32 2 466 78 79",
    "sg:postcode":"1702",
    "sg:province":"Vlaams-Brabant",
    "sg:tags":[
        "verzekeringsmakelaars",
        "expert"
    ],
    "wof:name":"Jean Richard",
    "wof:placetype":"venue"
},
  "geometry": {"coordinates":[4.2446107864,50.8717536926],"type":"Point"}
}