{
  "type": "Feature",
  "properties": {
    "iso:country":"BE",
    "sg:address":"Rue Gr\u00e9goire Wincqz 90",
    "sg:city":"Soignies",
    "sg:classifiers":[
        {
            "category":"Retail",
            "subcategory":"Auto Repair",
            "type":"Services"
        }
    ],
    "sg:phone":"+32 67 33 16 88",
    "sg:postcode":"7060",
    "sg:province":"Hainaut",
    "sg:tags":[
        "garage"
    ],
    "wof:name":"Varley Ets",
    "wof:placetype":"venue"
},
  "geometry": {"coordinates":[4.0747637749,50.5758628845],"type":"Point"}
}