{
  "type": "Feature",
  "properties": {
    "iso:country":"BE",
    "sg:address":"Wouwersdreef 17",
    "sg:city":"Schoten",
    "sg:orig_category":"Quincailleries",
    "sg:phone":"+32 3 685 20 00",
    "sg:postcode":"2900",
    "sg:province":"Antwerpen",
    "wof:name":"Heritage Buildings",
    "wof:placetype":"venue"
},
  "geometry": {"coordinates":[4.5429410934,51.26820755],"type":"Point"}
}