{
  "type": "Feature",
  "properties": {
    "addr:full":"Baron J. De Dixmudestr. 37 Hoeilaart Vlaams-Brabant 1560",
    "addr:housenumber":"37",
    "addr:postcode":"1560",
    "addr:street":"Baron J. De Dixmudestr.",
    "iso:country":"BE",
    "sg:address":"Baron J. De Dixmudestr. 37",
    "sg:city":"Hoeilaart",
    "sg:orig_category":"Epiceries",
    "sg:phone":"+32 2 657 58 23",
    "sg:postcode":"1560",
    "sg:province":"Vlaams-Brabant",
    "wof:name":"Victor Huysman",
    "wof:placetype":"venue"
},
  "geometry": {"coordinates":[4.4711260796,50.7571258545],"type":"Point"}
}