{
  "type": "Feature",
  "properties": {
    "addr:full":"Dillenburgstraat 34 Diest (webbekom) Vlaams-Brabant 3290",
    "addr:housenumber":"34",
    "addr:postcode":"3290",
    "addr:street":"Dillenburgstraat",
    "iso:country":"BE",
    "sg:address":"Dillenburgstraat 34",
    "sg:city":"Diest (webbekom)",
    "sg:classifiers":[
        {
            "category":"Real Estate",
            "subcategory":"Architect",
            "type":"Services"
        }
    ],
    "sg:phone":"+32 13 33 64 29",
    "sg:postcode":"3290",
    "sg:province":"Vlaams-Brabant",
    "wof:name":"Beerten S",
    "wof:placetype":"venue"
},
  "geometry": {"coordinates":[5.0412650108,50.9726333618],"type":"Point"}
}