{
  "type": "Feature",
  "properties": {
    "iso:country":"BE",
    "sg:address":"Zandputlaan 58",
    "sg:city":"Mol",
    "sg:classifiers":[
        {
            "category":"Personal",
            "subcategory":"Beauty Salon",
            "type":"Services"
        }
    ],
    "sg:phone":"+32 14 31 24 48",
    "sg:postcode":"2400",
    "sg:province":"Antwerpen",
    "sg:tags":[
        "lady",
        "-",
        "hairdressing"
    ],
    "wof:name":"Paula",
    "wof:placetype":"venue"
},
  "geometry": {"coordinates":[5.1135249138,51.215511322],"type":"Point"}
}