{
  "type": "Feature",
  "properties": {
    "iso:country":"BE",
    "sg:address":"Chauss\u00e9e De Maubeuge 430",
    "sg:city":"Mons (hyon)",
    "sg:classifiers":[
        {
            "category":"Organizations",
            "subcategory":"Community Association",
            "type":"Services"
        }
    ],
    "sg:phone":"+32 65 31 76 07",
    "sg:postcode":"7022",
    "sg:province":"Hainaut",
    "sg:tags":[
        "cultural"
    ],
    "wof:name":"Jeunesses Musicales De Mons-borinage",
    "wof:placetype":"venue"
},
  "geometry": {"coordinates":[3.9466969967,50.4302558899],"type":"Point"}
}