{
  "type": "Feature",
  "properties": {
    "addr:full":"Boulevard G\u00e9n\u00e9ral Wahis 238 Bruxelles (schaerbeek) Bruxelles-Capitale 1030",
    "addr:housenumber":"238",
    "addr:postcode":"1030",
    "addr:street":"Boulevard Ge\u0301Ne\u0301Ral Wahis",
    "iso:country":"BE",
    "sg:address":"Boulevard G\u00e9n\u00e9ral Wahis 238",
    "sg:city":"Bruxelles (schaerbeek)",
    "sg:classifiers":[
        {
            "category":"Professional",
            "subcategory":"Lawyer & Legal Services",
            "type":"Services"
        }
    ],
    "sg:phone":"+32 2 705 39 10",
    "sg:postcode":"1030",
    "sg:province":"Bruxelles-Capitale",
    "wof:name":"Henry Alain",
    "wof:placetype":"venue"
},
  "geometry": {"coordinates":[4.3983778954,50.8564834595],"type":"Point"}
}