{
  "type": "Feature",
  "properties": {
    "addr:full":"Rue De Belle-vue 147b1 La Louviere Hainaut 7100",
    "addr:housenumber":"147b1",
    "addr:postcode":"7100",
    "addr:street":"Rue De Belle-Vue",
    "iso:country":"BE",
    "sg:address":"Rue De Belle-vue 147b1",
    "sg:city":"La Louviere",
    "sg:orig_category":"Advocaten and juridische adviseurs",
    "sg:phone":"+32 64 26 37 91",
    "sg:postcode":"7100",
    "sg:province":"Hainaut",
    "wof:name":"Rosamaria Pavoncelli",
    "wof:placetype":"venue"
},
  "geometry": {"coordinates":[4.1900072098,50.4714164734],"type":"Point"}
}