{
  "type": "Feature",
  "properties": {
    "addr:full":"Rue De La Coquinie 13 Mouscron Hainaut 7700",
    "addr:housenumber":"13",
    "addr:postcode":"7700",
    "addr:street":"Rue De La Coquinie",
    "iso:country":"BE",
    "sg:address":"Rue De La Coquinie 13",
    "sg:city":"Mouscron",
    "sg:orig_category":"Sportclubs",
    "sg:phone":"+32 56 33 02 52",
    "sg:postcode":"7700",
    "sg:province":"Hainaut",
    "wof:name":"C.a.m",
    "wof:placetype":"venue"
},
  "geometry": {"coordinates":[3.2182500362,50.7489356995],"type":"Point"}
}