{
  "type": "Feature",
  "properties": {
    "iso:country":"BE",
    "sg:address":"Hasseltsesteenweg 69",
    "sg:city":"Tongeren",
    "sg:orig_category":"Paramedische behandelingen",
    "sg:phone":"+32 12 23 88 11",
    "sg:postcode":"3700",
    "sg:province":"Limburg",
    "wof:name":"Ch. Radlgruber",
    "wof:placetype":"venue"
},
  "geometry": {"coordinates":[5.4573020935,50.7835350037],"type":"Point"}
}