{
  "type": "Feature",
  "properties": {
    "addr:full":"Kloosterplein 2 Balen Antwerpen 2490",
    "addr:housenumber":"2",
    "addr:postcode":"2490",
    "addr:street":"Kloosterplein",
    "iso:country":"BE",
    "sg:address":"Kloosterplein 2",
    "sg:city":"Balen",
    "sg:orig_category":"Banken and kredietinstellingen",
    "sg:phone":"+32 14 82 01 95",
    "sg:postcode":"2490",
    "sg:province":"Antwerpen",
    "wof:name":"Groep Argenta",
    "wof:placetype":"venue"
},
  "geometry": {"coordinates":[5.2289409637,51.1958427429],"type":"Point"}
}