{
  "type": "Feature",
  "properties": {
    "addr:full":"Avenue Reine Astrid 10 Huy Li\u00e8ge 4500",
    "addr:housenumber":"10",
    "addr:postcode":"4500",
    "addr:street":"Avenue Reine Astrid",
    "iso:country":"BE",
    "sg:address":"Avenue Reine Astrid 10",
    "sg:city":"Huy",
    "sg:classifiers":[
        {
            "category":"Autos & Motor Vehicles",
            "subcategory":"Fuel & Gas Station",
            "type":"Retail Goods"
        }
    ],
    "sg:phone":"+32 85 21 33 36",
    "sg:postcode":"4500",
    "sg:province":"Li\u00e8ge",
    "wof:name":"Esso Linden",
    "wof:placetype":"venue"
},
  "geometry": {"coordinates":[5.2296791077,50.5255966187],"type":"Point"}
}