{
  "type": "Feature",
  "properties": {
    "iso:country":"BE",
    "sg:address":"Stuivenberg 17",
    "sg:city":"Keerbergen",
    "sg:classifiers":[
        {
            "category":"Arts & Performance",
            "subcategory":"Symphony",
            "type":"Entertainment"
        }
    ],
    "sg:phone":"+32 15 52 95 85",
    "sg:postcode":"3140",
    "sg:province":"Vlaams-Brabant",
    "sg:tags":[
        "orchestra"
    ],
    "wof:name":"Vermeulen P",
    "wof:placetype":"venue"
},
  "geometry": {"coordinates":[4.6179380417,51.0092163086],"type":"Point"}
}