{
  "type": "Feature",
  "properties": {
    "addr:full":"Rue Du Village 44 Aubange Luxembourg 6790",
    "addr:housenumber":"44",
    "addr:postcode":"6790",
    "addr:street":"Rue Du Village",
    "iso:country":"BE",
    "sg:address":"Rue Du Village 44",
    "sg:city":"Aubange",
    "sg:orig_category":"Textiel",
    "sg:phone":"+32 63 38 58 28",
    "sg:postcode":"6790",
    "sg:province":"Luxembourg",
    "wof:name":"Joelle Gerard",
    "wof:placetype":"venue"
},
  "geometry": {"coordinates":[5.8088331223,49.5670700073],"type":"Point"}
}