{
  "type": "Feature",
  "properties": {
    "addr:full":"Dr\u00c8ve Du Ch\u00c2teau 52 Ganshoren Bruxelles-Capitale 1083",
    "addr:housenumber":"52",
    "addr:postcode":"1083",
    "addr:street":"Dre\u0300Ve Du Cha\u0302Teau",
    "iso:country":"BE",
    "sg:address":"Dr\u00c8ve Du Ch\u00c2teau 52",
    "sg:city":"Ganshoren",
    "sg:classifiers":[
        {
            "category":"Arena",
            "subcategory":"Sports Club",
            "type":"Entertainment"
        }
    ],
    "sg:phone":"+32 2 428 66 66",
    "sg:postcode":"1083",
    "sg:province":"Bruxelles-Capitale",
    "sg:tags":[
        "de"
    ],
    "wof:name":"Aikido Club Besace",
    "wof:placetype":"venue"
},
  "geometry": {"coordinates":[4.3143200874,50.8765258789],"type":"Point"}
}