{
  "type": "Feature",
  "properties": {
    "addr:full":"Bronstraat 37 Dilbeek Vlaams-Brabant 1700",
    "addr:housenumber":"37",
    "addr:postcode":"1700",
    "addr:street":"Bronstraat",
    "iso:country":"BE",
    "sg:address":"Bronstraat 37",
    "sg:city":"Dilbeek",
    "sg:classifiers":[
        {
            "category":"Professional",
            "subcategory":"Art Services",
            "type":"Services"
        }
    ],
    "sg:phone":"+32 2 569 28 43",
    "sg:postcode":"1700",
    "sg:province":"Vlaams-Brabant",
    "sg:tags":[
        "designer",
        "cr\u00e9ateurs"
    ],
    "wof:name":"Els Sienaert",
    "wof:placetype":"venue"
},
  "geometry": {"coordinates":[4.2646751404,50.8387107849],"type":"Point"}
}