{
  "type": "Feature",
  "properties": {
    "iso:country":"BE",
    "sg:address":"Maarschalk Frenchlaan 8bis",
    "sg:city":"Ieper",
    "sg:classifiers":[
        {
            "category":"Professional",
            "type":"Services"
        }
    ],
    "sg:phone":"+32 57 20 28 55",
    "sg:postcode":"8900",
    "sg:province":"West-Vlaanderen",
    "sg:tags":[
        "auction",
        "room"
    ],
    "wof:name":"Menenpoort",
    "wof:placetype":"venue"
},
  "geometry": {"coordinates":[2.892553091,50.8522148132],"type":"Point"}
}