{
  "type": "Feature",
  "properties": {
    "addr:full":"Meensestraat 26 Ieper West-Vlaanderen 8900",
    "addr:housenumber":"26",
    "addr:postcode":"8900",
    "addr:street":"Meensestraat",
    "iso:country":"BE",
    "sg:address":"Meensestraat 26",
    "sg:city":"Ieper",
    "sg:classifiers":[
        {
            "category":"Shopping",
            "subcategory":"Clothing, Apparel, & Fashions",
            "type":"Retail Goods"
        }
    ],
    "sg:phone":"+32 57 20 67 54",
    "sg:postcode":"8900",
    "sg:province":"West-Vlaanderen",
    "sg:tags":[
        "boutique"
    ],
    "wof:name":"Abbey Road",
    "wof:placetype":"venue"
},
  "geometry": {"coordinates":[2.8894031048,50.8515586853],"type":"Point"}
}