{
  "type": "Feature",
  "properties": {
    "addr:full":"Claventweg 62 Gistel West-Vlaanderen 8470",
    "addr:housenumber":"62",
    "addr:postcode":"8470",
    "addr:street":"Claventweg",
    "iso:country":"BE",
    "sg:address":"Claventweg 62",
    "sg:city":"Gistel",
    "sg:classifiers":[
        {
            "category":"Landmark",
            "subcategory":"City Walls",
            "type":"Public Place"
        }
    ],
    "sg:phone":"+32 59 27 44 27",
    "sg:postcode":"8470",
    "sg:province":"West-Vlaanderen",
    "sg:tags":[
        "shed",
        "open",
        "hangar"
    ],
    "wof:name":"Van Hee P",
    "wof:placetype":"venue"
},
  "geometry": {"coordinates":[2.9450340271,51.1458435059],"type":"Point"}
}