{
  "type": "Feature",
  "properties": {
    "addr:full":"Kortrijksesteenweg 201 Harelbeke West-Vlaanderen 8530",
    "addr:housenumber":"201",
    "addr:postcode":"8530",
    "addr:street":"Kortrijksesteenweg",
    "iso:country":"BE",
    "sg:address":"Kortrijksesteenweg 201",
    "sg:city":"Harelbeke",
    "sg:classifiers":[
        {
            "category":"Professional",
            "subcategory":"Management & Consulting",
            "type":"Services"
        }
    ],
    "sg:phone":"+32 56 71 09 47",
    "sg:postcode":"8530",
    "sg:province":"West-Vlaanderen",
    "sg:tags":[
        "consultant",
        "agency",
        "advertising"
    ],
    "wof:name":"Grafiek Atelier Huysentruyt Bvba",
    "wof:placetype":"venue"
},
  "geometry": {"coordinates":[3.2972090244,50.846496582],"type":"Point"}
}