{
  "type": "Feature",
  "properties": {
    "addr:full":"Legerlaan 138ba Etterbeek/etterbeek Bruxelles-Capitale 1040",
    "addr:postcode":"1040",
    "addr:street":"Legerlaan",
    "iso:country":"BE",
    "sg:address":"Legerlaan 138ba",
    "sg:city":"Etterbeek/etterbeek",
    "sg:orig_category":"Diverse kredietdiensten",
    "sg:postcode":"1040",
    "sg:province":"Bruxelles-Capitale",
    "wof:name":"Bancontact-mister Cash",
    "wof:placetype":"venue"
},
  "geometry": {"coordinates":[4.4026789665,50.8336524963],"type":"Point"}
}