{
  "type": "Feature",
  "properties": {
    "addr:full":"Rue Des Roses Tr\u00e9mi\u00e8res 35 Namur (vedrin - Daussoulx) Namur 5020",
    "addr:housenumber":"35",
    "addr:postcode":"5020",
    "addr:street":"Rue Des Roses Tre\u0301Mie\u0300Res",
    "iso:country":"BE",
    "sg:address":"Rue Des Roses Tr\u00e9mi\u00e8res 35",
    "sg:city":"Namur (vedrin - Daussoulx)",
    "sg:classifiers":[
        {
            "category":"Health Services",
            "subcategory":"Health Practitioner",
            "type":"Services"
        }
    ],
    "sg:phone":"+32 81 21 14 96",
    "sg:postcode":"5020",
    "sg:province":"Namur",
    "sg:tags":[
        "physiotherapist"
    ],
    "wof:name":"Orban Oph\u00e9lie",
    "wof:placetype":"venue"
},
  "geometry": {"coordinates":[4.7952418327,50.4352035522],"type":"Point"}
}