{
  "type": "Feature",
  "properties": {
    "iso:country":"BE",
    "sg:address":"Wachtebekestraat 193",
    "sg:city":"Zelzate",
    "sg:classifiers":[
        {
            "category":"Retail",
            "subcategory":"Auto Repair",
            "type":"Services"
        }
    ],
    "sg:phone":"+32 9 345 56 91",
    "sg:postcode":"9060",
    "sg:province":"Oost-Vlaanderen",
    "sg:tags":[
        "garage"
    ],
    "wof:name":"Ciac Zelzate",
    "wof:placetype":"venue"
},
  "geometry": {"coordinates":[3.8247990608,51.1956062317],"type":"Point"}
}