{
  "type": "Feature",
  "properties": {
    "iso:country":"BE",
    "sg:address":"Rue Du Vicinal 17",
    "sg:city":"Dalhem (neufch\u00e2teau (lez-vis\u00e9))",
    "sg:classifiers":[
        {
            "category":"Retail",
            "subcategory":"Event Space",
            "type":"Services"
        }
    ],
    "sg:phone":"+32 4 376 65 64",
    "sg:postcode":"4608",
    "sg:province":"Li\u00e8ge",
    "sg:tags":[
        "rental",
        "-",
        "hall"
    ],
    "wof:name":"Chaume (la) Sa",
    "wof:placetype":"venue"
},
  "geometry": {"coordinates":[5.7779669762,50.7188148499],"type":"Point"}
}