{
  "type": "Feature",
  "properties": {
    "iso:country":"BE",
    "sg:address":"Rue Marie-th\u00e9r\u00e8se 22",
    "sg:city":"Weismes (faymonville)",
    "sg:classifiers":[
        {
            "category":"Home & Garden",
            "subcategory":"Carpets & Floor Coverings",
            "type":"Retail Goods"
        }
    ],
    "sg:phone":"+32 80 67 88 40",
    "sg:postcode":"4950",
    "sg:province":"Li\u00e8ge",
    "sg:tags":[
        "tile"
    ],
    "wof:name":"Scholzen J",
    "wof:placetype":"venue"
},
  "geometry": {"coordinates":[6.1359581947,50.4063987732],"type":"Point"}
}