{
  "type": "Feature",
  "properties": {
    "iso:country":"BE",
    "sg:address":"Warande 15a",
    "sg:city":"Sint-laureins (sint-jan-in-eremo)",
    "sg:classifiers":[
        {
            "category":"Professional",
            "subcategory":"Art Services",
            "type":"Services"
        }
    ],
    "sg:phone":"+32 495 26 91 29",
    "sg:postcode":"9982",
    "sg:province":"Oost-Vlaanderen",
    "sg:tags":[
        "interior",
        "designer"
    ],
    "wof:name":"Muylle R",
    "wof:placetype":"venue"
},
  "geometry": {"coordinates":[3.5907709599,51.2458992004],"type":"Point"}
}