{
  "type": "Feature",
  "properties": {
    "addr:full":"Route De Mons 3 Sivry-rance (rance) Hainaut 6470",
    "addr:housenumber":"3",
    "addr:postcode":"6470",
    "addr:street":"Route De Mons;Rance Hainaut",
    "iso:country":"BE",
    "sg:address":"Route De Mons 3",
    "sg:city":"Sivry-rance (rance)",
    "sg:classifiers":[
        {
            "category":"Building & Trades",
            "subcategory":"Construction",
            "type":"Services"
        }
    ],
    "sg:phone":"+32 60 45 52 21",
    "sg:postcode":"6470",
    "sg:province":"Hainaut",
    "sg:tags":[
        "carpenter"
    ],
    "wof:name":"Devergnies D",
    "wof:placetype":"venue"
},
  "geometry": {"coordinates":[4.220870018,50.184009552],"type":"Point"}
}