{
  "type": "Feature",
  "properties": {
    "iso:country":"BE",
    "sg:address":"Stationsstraat 41",
    "sg:city":"Ichtegem",
    "sg:orig_category":"Pharmaciens",
    "sg:phone":"+32 59 29 92 25",
    "sg:postcode":"8480",
    "sg:province":"West-Vlaanderen",
    "wof:name":"M. Buyse",
    "wof:placetype":"venue"
},
  "geometry": {"coordinates":[3.0239710808,51.1293945312],"type":"Point"}
}