{
  "type": "Feature",
  "properties": {
    "addr:full":"Vijversstraat 55 Hasselt Limburg 3500",
    "addr:housenumber":"55",
    "addr:postcode":"3500",
    "addr:street":"Vijversstraat",
    "iso:country":"BE",
    "sg:address":"Vijversstraat 55",
    "sg:city":"Hasselt",
    "sg:classifiers":[
        {
            "category":"Social Services",
            "type":"Services"
        }
    ],
    "sg:phone":"+32 11 21 04 83",
    "sg:postcode":"3500",
    "sg:province":"Limburg",
    "wof:name":"Sopeh Dienst Voor Pleegzorg Vz Vzw",
    "wof:placetype":"venue"
},
  "geometry": {"coordinates":[5.3524808884,50.963722229],"type":"Point"}
}