{
  "type": "Feature",
  "properties": {
    "iso:country":"BE",
    "sg:address":"Route D'eghez\u00c9e 182",
    "sg:city":"Jemeppe-sur-sambre",
    "sg:orig_category":"Entretien and r\u00e9parations de voitures",
    "sg:phone":"+32 71 78 83 58",
    "sg:postcode":"5190",
    "sg:province":"Namur",
    "wof:name":"Garage Orneau",
    "wof:placetype":"venue"
},
  "geometry": {"coordinates":[4.6714458466,50.4711036682],"type":"Point"}
}