{
  "type": "Feature",
  "properties": {
    "addr:full":"Chauss\u00c9e De Louvain 422 Schaarbeek/schaerbeek Bruxelles-Capitale 1030",
    "addr:housenumber":"422",
    "addr:postcode":"1030",
    "addr:street":"Chausse\u0301E De Louvain",
    "iso:country":"BE",
    "sg:address":"Chauss\u00c9e De Louvain 422",
    "sg:city":"Schaarbeek/schaerbeek",
    "sg:classifiers":[
        {
            "category":"Autos & Motor Vehicles",
            "subcategory":"Fuel & Gas Station",
            "type":"Retail Goods"
        }
    ],
    "sg:phone":"+32 2 736 07 86",
    "sg:postcode":"1030",
    "sg:province":"Bruxelles-Capitale",
    "sg:tags":[
        "stations-service",
        "carburants"
    ],
    "wof:name":"Q8",
    "wof:placetype":"venue"
},
  "geometry": {"coordinates":[4.3891220093,50.8525886536],"type":"Point"}
}