{
  "type": "Feature",
  "properties": {
    "iso:country":"BE",
    "sg:address":"Kusterstraat 19",
    "sg:city":"Gingelom",
    "sg:orig_category":"Epiceries",
    "sg:phone":"+32 11 83 21 89",
    "sg:postcode":"3891",
    "sg:province":"Limburg",
    "wof:name":"Huis Van Camp",
    "wof:placetype":"venue"
},
  "geometry": {"coordinates":[5.2149648666,50.7555809021],"type":"Point"}
}