{
  "type": "Feature",
  "properties": {
    "addr:full":"Bredabaan 312 Brasschaat Antwerpen 2930",
    "addr:housenumber":"312",
    "addr:postcode":"2930",
    "addr:street":"Bredabaan",
    "iso:country":"BE",
    "sg:address":"Bredabaan 312",
    "sg:city":"Brasschaat",
    "sg:orig_category":"Herenkledingzaken",
    "sg:phone":"+32 3 651 57 42",
    "sg:postcode":"2930",
    "sg:province":"Antwerpen",
    "wof:name":"Niels",
    "wof:placetype":"venue"
},
  "geometry": {"coordinates":[4.4932198524,51.291519165],"type":"Point"}
}