{
  "type": "Feature",
  "properties": {
    "addr:full":"Vieille Voie De Tongres 17 Juprelle (voroux-lez-liers) Li\u00e8ge 4451",
    "addr:housenumber":"17",
    "addr:postcode":"4451",
    "addr:street":"Vieille Voie De Tongres;Voroux-Lez-Liers",
    "iso:country":"BE",
    "sg:address":"Vieille Voie De Tongres 17",
    "sg:city":"Juprelle (voroux-lez-liers)",
    "sg:classifiers":[
        {
            "category":"Health Services",
            "subcategory":"Nursing And Care Facility",
            "type":"Services"
        }
    ],
    "sg:phone":"+32 4 278 68 37",
    "sg:postcode":"4451",
    "sg:province":"Li\u00e8ge",
    "sg:tags":[
        "home"
    ],
    "wof:name":"Barbier M",
    "wof:placetype":"venue"
},
  "geometry": {"coordinates":[5.5549402237,50.6893081665],"type":"Point"}
}