{
  "type": "Feature",
  "properties": {
    "addr:full":"Avenue Des Platanes 140 Herve (grand-rechain) Li\u00e8ge 4650",
    "addr:housenumber":"140",
    "addr:postcode":"4650",
    "addr:street":"Avenue Des Platanes;Grand-Rechain",
    "iso:country":"BE",
    "sg:address":"Avenue Des Platanes 140",
    "sg:city":"Herve (grand-rechain)",
    "sg:classifiers":[
        {
            "category":"Professional",
            "subcategory":"Engineering",
            "type":"Services"
        }
    ],
    "sg:phone":"+32 87 33 25 38",
    "sg:postcode":"4650",
    "sg:province":"Li\u00e8ge",
    "sg:tags":[
        "-"
    ],
    "wof:name":"Bcde",
    "wof:placetype":"venue"
},
  "geometry": {"coordinates":[5.8121781349,50.6080703735],"type":"Point"}
}