{
  "type": "Feature",
  "properties": {
    "addr:full":"Koning Albertlaan 47/1 Neerpelt Limburg 3910",
    "addr:housenumber":"47 / 1",
    "addr:postcode":"3910",
    "addr:street":"Koning Albertlaan",
    "iso:country":"BE",
    "sg:address":"Koning Albertlaan 47/1",
    "sg:city":"Neerpelt",
    "sg:orig_category":"Mat\u00e9riel de T\u00e9l\u00e9communication. Syst\u00e8mes de t\u00e9l\u00e9communications",
    "sg:phone":"+32 11 80 94 94",
    "sg:postcode":"3910",
    "sg:province":"Limburg",
    "wof:name":"Essec Telecom Center",
    "wof:placetype":"venue"
},
  "geometry": {"coordinates":[5.4304699898,51.2262115479],"type":"Point"}
}