{
  "type": "Feature",
  "properties": {
    "addr:full":"Veerledorp 39 Laakdal Antwerpen 2431",
    "addr:housenumber":"39",
    "addr:postcode":"2431",
    "addr:street":"Veerledorp",
    "iso:country":"BE",
    "sg:address":"Veerledorp 39",
    "sg:city":"Laakdal",
    "sg:orig_category":"Enseignement maternel and primaire",
    "sg:phone":"+32 14 84 13 96",
    "sg:postcode":"2431",
    "sg:province":"Antwerpen",
    "wof:name":"Vrije Basisschool",
    "wof:placetype":"venue"
},
  "geometry": {"coordinates":[4.985877037,51.0699996948],"type":"Point"}
}