{
  "type": "Feature",
  "properties": {
    "iso:country":"BE",
    "sg:address":"Linnerveldstraat 17",
    "sg:city":"Bilzen",
    "sg:classifiers":[
        {
            "category":"Cafe",
            "type":"Food & Drink"
        }
    ],
    "sg:phone":"+32 11 41 50 12",
    "sg:postcode":"3742",
    "sg:province":"Limburg",
    "sg:tags":[
        "caf\u00e9s"
    ],
    "wof:name":"Martenslinde V.v.",
    "wof:placetype":"venue"
},
  "geometry": {"coordinates":[5.5304198265,50.8533973694],"type":"Point"}
}