{
  "type": "Feature",
  "properties": {
    "iso:country":"BE",
    "sg:address":"Putsesteenweg 57",
    "sg:city":"Sint-katelijne-waver",
    "sg:classifiers":[
        {
            "category":"Social Services",
            "subcategory":"Child Care",
            "type":"Services"
        }
    ],
    "sg:phone":"+32 15 55 33 60",
    "sg:postcode":"2860",
    "sg:province":"Antwerpen",
    "sg:tags":[
        "baby",
        "nursery",
        "day",
        "sitting"
    ],
    "wof:name":"De Ofifantjes",
    "wof:placetype":"venue"
},
  "geometry": {"coordinates":[4.5118632317,51.0347862244],"type":"Point"}
}