{
  "type": "Feature",
  "properties": {
    "iso:country":"BE",
    "sg:address":"Sint-annastraat 4",
    "sg:city":"Zottegem",
    "sg:classifiers":[
        {
            "category":"Professional",
            "subcategory":"Art Services",
            "type":"Services"
        }
    ],
    "sg:phone":"+32 9 360 61 72",
    "sg:postcode":"9620",
    "sg:province":"Oost-Vlaanderen",
    "sg:tags":[
        "interior",
        "designer"
    ],
    "wof:name":"Gevaert Bvba",
    "wof:placetype":"venue"
},
  "geometry": {"coordinates":[3.8119089603,50.8673706055],"type":"Point"}
}