{
  "type": "Feature",
  "properties": {
    "addr:full":"Rue De Bouvy 127 La Louviere Hainaut 7100",
    "addr:housenumber":"127",
    "addr:postcode":"7100",
    "addr:street":"Rue De Bouvy",
    "iso:country":"BE",
    "sg:address":"Rue De Bouvy 127",
    "sg:city":"La Louviere",
    "sg:orig_category":"Kinderopvang",
    "sg:phone":"+32 64 26 46 01",
    "sg:postcode":"7100",
    "sg:province":"Hainaut",
    "wof:name":"Les Joyeux Turlutins",
    "wof:placetype":"venue"
},
  "geometry": {"coordinates":[4.1816091537,50.4702072144],"type":"Point"}
}