{
  "type": "Feature",
  "properties": {
    "addr:full":"Smissen 4 Sint-amands Antwerpen 2890",
    "addr:housenumber":"4",
    "addr:postcode":"2890",
    "addr:street":"Smissen",
    "iso:country":"BE",
    "sg:address":"Smissen 4",
    "sg:city":"Sint-amands",
    "sg:orig_category":"Groententeelt",
    "sg:phone":"+32 52 34 13 51",
    "sg:postcode":"2890",
    "sg:province":"Antwerpen",
    "wof:name":"Kristiaan Lanckpaep",
    "wof:placetype":"venue"
},
  "geometry": {"coordinates":[4.2270789146,51.0459060669],"type":"Point"}
}