{
  "type": "Feature",
  "properties": {
    "iso:country":"BE",
    "sg:address":"Noordlaan 170",
    "sg:city":"Wetteren",
    "sg:orig_category":"Location de voitures. Entretien and r\u00e9parations de voitures",
    "sg:phone":"+32 9 369 14 44",
    "sg:postcode":"9230",
    "sg:province":"Oost-Vlaanderen",
    "wof:name":"Delta Car & Truck Rental",
    "wof:placetype":"venue"
},
  "geometry": {"coordinates":[3.8646149635,51.0007743835],"type":"Point"}
}