{
  "type": "Feature",
  "properties": {
    "iso:country":"BE",
    "sg:address":"Albert I Promenade 44",
    "sg:city":"Oostende",
    "sg:orig_category":"Boissons",
    "sg:phone":"+32 59 70 19 60",
    "sg:postcode":"8400",
    "sg:province":"West-Vlaanderen",
    "wof:name":"Daniel Masure",
    "wof:placetype":"venue"
},
  "geometry": {"coordinates":[2.9146049023,51.233669281],"type":"Point"}
}