{
  "type": "Feature",
  "properties": {
    "iso:country":"BE",
    "sg:address":"Route De Mons 320",
    "sg:city":"Binche",
    "sg:orig_category":"Architectes",
    "sg:phone":"+32 64 33 23 30",
    "sg:postcode":"7130",
    "sg:province":"Hainaut",
    "wof:name":"Bureau Dessart",
    "wof:placetype":"venue"
},
  "geometry": {"coordinates":[4.1599001884,50.4136390686],"type":"Point"}
}