{
  "type": "Feature",
  "properties": {
    "iso:country":"BE",
    "sg:address":"Rue De Tournai 311a",
    "sg:city":"Beloeil (stambruges)",
    "sg:classifiers":[
        {
            "category":"Building & Trades",
            "subcategory":"Construction",
            "type":"Services"
        }
    ],
    "sg:phone":"+32 69 59 08 59",
    "sg:postcode":"7973",
    "sg:province":"Hainaut",
    "sg:tags":[
        "installation",
        "-",
        "central",
        "heating"
    ],
    "wof:name":"Tarasconi Service Plus",
    "wof:placetype":"venue"
},
  "geometry": {"coordinates":[3.7138879299,50.4964447021],"type":"Point"}
}