{
  "type": "Feature",
  "properties": {
    "addr:full":"Beverensestraat 81 Ardooie West-Vlaanderen 8850",
    "addr:housenumber":"81",
    "addr:postcode":"8850",
    "addr:street":"Beverensestraat",
    "iso:country":"BE",
    "sg:address":"Beverensestraat 81",
    "sg:city":"Ardooie",
    "sg:orig_category":"Produits chimiques Gr",
    "sg:phone":"+32 51 74 40 31",
    "sg:postcode":"8850",
    "sg:province":"West-Vlaanderen",
    "wof:name":"Vandecappelle",
    "wof:placetype":"venue"
},
  "geometry": {"coordinates":[3.1756379604,50.9772758484],"type":"Point"}
}