{
  "type": "Feature",
  "properties": {
    "addr:full":"Outerstraat 13 Ninove Oost-Vlaanderen 9400",
    "addr:housenumber":"13",
    "addr:postcode":"9400",
    "addr:street":"Outerstraat",
    "iso:country":"BE",
    "sg:address":"Outerstraat 13",
    "sg:city":"Ninove",
    "sg:orig_category":"Epiceries",
    "sg:phone":"+32 54 33 26 23",
    "sg:postcode":"9400",
    "sg:province":"Oost-Vlaanderen",
    "wof:name":"Patrik Wauters",
    "wof:placetype":"venue"
},
  "geometry": {"coordinates":[4.0070648193,50.8375511169],"type":"Point"}
}