{
  "type": "Feature",
  "properties": {
    "addr:full":"Rue Des Fr\u00c8res Taymans 89 Tubize Brabant Wallon 1480",
    "addr:housenumber":"89",
    "addr:postcode":"1480",
    "addr:street":"Rue Des Fre\u0300Res Taymans;Wallon",
    "iso:country":"BE",
    "sg:address":"Rue Des Fr\u00c8res Taymans 89",
    "sg:city":"Tubize",
    "sg:orig_category":"V\u00e9t\u00e9rinaires",
    "sg:phone":"+32 2 355 89 18",
    "sg:postcode":"1480",
    "sg:province":"Brabant Wallon",
    "wof:name":"Philippe Vancutsem",
    "wof:placetype":"venue"
},
  "geometry": {"coordinates":[4.2065958977,50.6876144409],"type":"Point"}
}