{
  "type": "Feature",
  "properties": {
    "iso:country":"BE",
    "sg:address":"Isabellastraat 11",
    "sg:city":"Dilbeek (schepdaal)",
    "sg:classifiers":[
        {
            "category":"Home & Garden",
            "subcategory":"Kitchen Supply",
            "type":"Retail Goods"
        }
    ],
    "sg:phone":"+32 2 567 14 47",
    "sg:postcode":"1703",
    "sg:province":"Vlaams-Brabant",
    "sg:tags":[
        "installation"
    ],
    "wof:name":"Kitcheneering",
    "wof:placetype":"venue"
},
  "geometry": {"coordinates":[4.2071409225,50.8263282776],"type":"Point"}
}