{
  "type": "Feature",
  "properties": {
    "addr:full":"Kasteelstraat 76 Dilbeek Vlaams-Brabant 1700",
    "addr:housenumber":"76",
    "addr:postcode":"1700",
    "addr:street":"Kasteelstraat",
    "iso:country":"BE",
    "sg:address":"Kasteelstraat 76",
    "sg:city":"Dilbeek",
    "sg:orig_category":"Enseignement maternel and primaire",
    "sg:phone":"+32 2 569 39 47",
    "sg:postcode":"1700",
    "sg:province":"Vlaams-Brabant",
    "wof:name":"Basisschool",
    "wof:placetype":"venue"
},
  "geometry": {"coordinates":[4.2570500374,50.8472747803],"type":"Point"}
}