{
  "type": "Feature",
  "properties": {
    "addr:full":"Hoogstraat 64 Puurs Antwerpen 2870",
    "addr:housenumber":"64",
    "addr:postcode":"2870",
    "addr:street":"Hoogstraat",
    "iso:country":"BE",
    "sg:address":"Hoogstraat 64",
    "sg:city":"Puurs",
    "sg:orig_category":"Baby- and kinderkleding Babyspullen",
    "sg:phone":"+32 3 899 16 91",
    "sg:postcode":"2870",
    "sg:province":"Antwerpen",
    "wof:name":"Le Duc",
    "wof:placetype":"venue"
},
  "geometry": {"coordinates":[4.2804279327,51.0758361816],"type":"Point"}
}