{
  "type": "Feature",
  "properties": {
    "addr:full":"Rue D'ellezelles 87 Ronse/renaix Oost-Vlaanderen 9600",
    "addr:housenumber":"87",
    "addr:postcode":"9600",
    "addr:street":"Rue D'Ellezelles",
    "iso:country":"BE",
    "sg:address":"Rue D'ellezelles 87",
    "sg:city":"Ronse/renaix",
    "sg:orig_category":"Banques and organismes de cr\u00e9dit",
    "sg:phone":"+32 55 21 38 88",
    "sg:postcode":"9600",
    "sg:province":"Oost-Vlaanderen",
    "wof:name":"Fortis",
    "wof:placetype":"venue"
},
  "geometry": {"coordinates":[3.6140999794,50.7427940369],"type":"Point"}
}