{
  "type": "Feature",
  "properties": {
    "addr:full":"Moorselestraat 107 Wevelgem West-Vlaanderen 8560",
    "addr:housenumber":"107",
    "addr:postcode":"8560",
    "addr:street":"Moorselestraat",
    "iso:country":"BE",
    "sg:address":"Moorselestraat 107",
    "sg:city":"Wevelgem",
    "sg:classifiers":[
        {
            "category":"Food & Beverages",
            "subcategory":"Groceries & Convenience Stores",
            "type":"Retail Goods"
        }
    ],
    "sg:phone":"+32 56 41 63 49",
    "sg:postcode":"8560",
    "sg:province":"West-Vlaanderen",
    "sg:tags":[
        "grocer"
    ],
    "wof:name":"Kiwi (de)",
    "wof:placetype":"venue"
},
  "geometry": {"coordinates":[3.1719579697,50.810382843],"type":"Point"}
}