{
  "type": "Feature",
  "properties": {
    "addr:full":"Waversesteenweg 365 Overijse Vlaams-Brabant 3090",
    "addr:housenumber":"365",
    "addr:postcode":"3090",
    "addr:street":"Waversesteenweg",
    "iso:country":"BE",
    "sg:address":"Waversesteenweg 365",
    "sg:city":"Overijse",
    "sg:classifiers":[
        {
            "category":"Health Services",
            "subcategory":"Nursing And Care Facility",
            "type":"Services"
        }
    ],
    "sg:phone":"+32 2 687 99 18",
    "sg:postcode":"3090",
    "sg:province":"Vlaams-Brabant",
    "sg:tags":[
        "home",
        "rest"
    ],
    "wof:name":"Acacia Vzw",
    "wof:placetype":"venue"
},
  "geometry": {"coordinates":[4.5715332031,50.747844696],"type":"Point"}
}