{
  "type": "Feature",
  "properties": {
    "iso:country":"BE",
    "sg:address":"Bakkershoflaan 4",
    "sg:city":"Zedelgem (loppem)",
    "sg:classifiers":[
        {
            "category":"Professional",
            "type":"Services"
        }
    ],
    "sg:phone":"+32 50 82 41 23",
    "sg:postcode":"8210",
    "sg:province":"West-Vlaanderen",
    "sg:tags":[
        "surveyor",
        "-",
        "valuer"
    ],
    "wof:name":"De Vilder R",
    "wof:placetype":"venue"
},
  "geometry": {"coordinates":[3.1458399296,51.1376457214],"type":"Point"}
}