{
  "type": "Feature",
  "properties": {
    "iso:country":"BE",
    "sg:address":"Tiensestraat 35",
    "sg:city":"Landen",
    "sg:classifiers":[
        {
            "category":"Shopping",
            "subcategory":"Florist",
            "type":"Retail Goods"
        }
    ],
    "sg:phone":"+32 11 88 51 59",
    "sg:postcode":"3400",
    "sg:province":"Vlaams-Brabant",
    "wof:name":"Jeugdig Groen ('t)",
    "wof:placetype":"venue"
},
  "geometry": {"coordinates":[5.0796561241,50.7563056946],"type":"Point"}
}