{
  "type": "Feature",
  "properties": {
    "iso:country":"BE",
    "sg:address":"Houte 65",
    "sg:city":"Oosterzele (balegem)",
    "sg:classifiers":[
        {
            "category":"Building & Trades",
            "subcategory":"Landscaping Services",
            "type":"Services"
        }
    ],
    "sg:phone":"+32 9 362 06 33",
    "sg:postcode":"9860",
    "sg:province":"Oost-Vlaanderen",
    "sg:tags":[
        "gardening",
        "garden",
        "maintenance"
    ],
    "wof:name":"D'hondt D",
    "wof:placetype":"venue"
},
  "geometry": {"coordinates":[3.8257009983,50.9393043518],"type":"Point"}
}