{
  "type": "Feature",
  "properties": {
    "addr:full":"Rue Pierre Longin 12 Anderlecht/anderlecht Bruxelles-Capitale 1070",
    "addr:housenumber":"12",
    "addr:postcode":"1070",
    "addr:street":"Rue Pierre Longin",
    "iso:country":"BE",
    "sg:address":"Rue Pierre Longin 12",
    "sg:city":"Anderlecht/anderlecht",
    "sg:orig_category":"M\u00e9decins and sp\u00e9cialistes",
    "sg:phone":"+32 2 524 13 41",
    "sg:postcode":"1070",
    "sg:province":"Bruxelles-Capitale",
    "wof:name":"Roselyne Allard",
    "wof:placetype":"venue"
},
  "geometry": {"coordinates":[4.2909808159,50.8289756775],"type":"Point"}
}