{
  "type": "Feature",
  "properties": {
    "addr:full":"Vijverhoek 41b43 Kuurne West-Vlaanderen 8520",
    "addr:housenumber":"41b43",
    "addr:postcode":"8520",
    "addr:street":"Vijverhoek",
    "iso:country":"BE",
    "sg:address":"Vijverhoek 41b43",
    "sg:city":"Kuurne",
    "sg:orig_category":"V\u00eatements pour b\u00e9b\u00e9s and enfants",
    "sg:phone":"+32 56 35 76 56",
    "sg:postcode":"8520",
    "sg:province":"West-Vlaanderen",
    "wof:name":"Huis Tric",
    "wof:placetype":"venue"
},
  "geometry": {"coordinates":[3.2671051025,50.8593826294],"type":"Point"}
}