{
  "type": "Feature",
  "properties": {
    "addr:full":"Aveschoot 17 Kaprijke (lembeke) Oost-Vlaanderen 9971",
    "addr:housenumber":"17",
    "addr:postcode":"9971",
    "addr:street":"Aveschoot",
    "iso:country":"BE",
    "sg:address":"Aveschoot 17",
    "sg:city":"Kaprijke (lembeke)",
    "sg:classifiers":[
        {
            "category":"Retail",
            "subcategory":"Funeral Services",
            "type":"Services"
        }
    ],
    "sg:phone":"+32 9 378 03 51",
    "sg:postcode":"9971",
    "sg:province":"Oost-Vlaanderen",
    "sg:tags":[
        "director"
    ],
    "wof:name":"Borgonjon J",
    "wof:placetype":"venue"
},
  "geometry": {"coordinates":[3.6289169788,51.1935691833],"type":"Point"}
}