{
  "type": "Feature",
  "properties": {
    "addr:full":"Mezestraat 10 Oostrozebeke West-Vlaanderen 8780",
    "addr:housenumber":"10",
    "addr:postcode":"8780",
    "addr:street":"Mezestraat",
    "iso:country":"BE",
    "sg:address":"Mezestraat 10",
    "sg:city":"Oostrozebeke",
    "sg:classifiers":[
        {
            "category":"Utilities",
            "subcategory":"Natural Gas",
            "type":"Services"
        }
    ],
    "sg:phone":"+32 56 66 58 12",
    "sg:postcode":"8780",
    "sg:province":"West-Vlaanderen",
    "sg:tags":[
        "welding"
    ],
    "wof:name":"Saelens R",
    "wof:placetype":"venue"
},
  "geometry": {"coordinates":[3.3421399593,50.9267234802],"type":"Point"}
}