{
  "type": "Feature",
  "properties": {
    "iso:country":"BE",
    "sg:address":"Val-du-bronze 1ba",
    "sg:city":"La Roche-en-ardenne",
    "sg:orig_category":"Artiesten and kunstenaars Diverse grafische activiteiten Reclamebureaus",
    "sg:phone":"+32 84 41 21 25",
    "sg:postcode":"6980",
    "sg:province":"Luxembourg",
    "wof:name":"Agence Cr\u00c9ation",
    "wof:placetype":"venue"
},
  "geometry": {"coordinates":[5.5766119957,50.1787338257],"type":"Point"}
}