{
  "type": "Feature",
  "properties": {
    "iso:country":"BE",
    "sg:address":"Liersesteenweg 2",
    "sg:city":"Nijlen",
    "sg:orig_category":"Plaatsen van vloer- and muurbekleding Vloer- and muurbekleding",
    "sg:phone":"+32 3 480 35 94",
    "sg:postcode":"2560",
    "sg:province":"Antwerpen",
    "wof:name":"De Kesselse Vloerhandel",
    "wof:placetype":"venue"
},
  "geometry": {"coordinates":[4.6250920296,51.1391868591],"type":"Point"}
}