{
  "type": "Feature",
  "properties": {
    "iso:country":"BE",
    "sg:address":"Route De Mons 51",
    "sg:city":"Mons",
    "sg:orig_category":"Plaatsen van vloer- and muurbekleding Schilders",
    "sg:phone":"+32 65 31 72 88",
    "sg:postcode":"7011",
    "sg:province":"Hainaut",
    "wof:name":"Jean Millet",
    "wof:placetype":"venue"
},
  "geometry": {"coordinates":[3.912539959,50.4712982178],"type":"Point"}
}