{
  "type": "Feature",
  "properties": {
    "addr:full":"Elsdreef 56 Waregem West-Vlaanderen 8790",
    "addr:housenumber":"56",
    "addr:postcode":"8790",
    "addr:street":"Elsdreef",
    "iso:country":"BE",
    "sg:address":"Elsdreef 56",
    "sg:city":"Waregem",
    "sg:orig_category":"V\u00eatements pour b\u00e9b\u00e9s and enfants",
    "sg:phone":"+32 56 77 23 86",
    "sg:postcode":"8790",
    "sg:province":"West-Vlaanderen",
    "wof:name":"Olivier Lottin",
    "wof:placetype":"venue"
},
  "geometry": {"coordinates":[3.4132399559,50.8504142761],"type":"Point"}
}