{
  "type": "Feature",
  "properties": {
    "addr:full":"Avenue Des Acacias 3 Waterloo Brabant Wallon 1410",
    "addr:housenumber":"3",
    "addr:postcode":"1410",
    "addr:street":"Avenue Des Acacias",
    "iso:country":"BE",
    "sg:address":"Avenue Des Acacias 3",
    "sg:city":"Waterloo",
    "sg:classifiers":[
        {
            "category":"Professional",
            "subcategory":"Engineering",
            "type":"Services"
        }
    ],
    "sg:phone":"+32 2 351 47 30",
    "sg:postcode":"1410",
    "sg:province":"Brabant Wallon",
    "sg:tags":[
        "-"
    ],
    "wof:name":"Engenious Sprl",
    "wof:placetype":"venue"
},
  "geometry": {"coordinates":[4.3854699135,50.728515625],"type":"Point"}
}