{
  "type": "Feature",
  "properties": {
    "addr:full":"Henri Zamanlaan 3 Tubize Brabant Wallon 1480",
    "addr:housenumber":"3",
    "addr:postcode":"1480",
    "addr:street":"Henri Zamanlaan;Wallon",
    "iso:country":"BE",
    "sg:address":"Henri Zamanlaan 3",
    "sg:city":"Tubize",
    "sg:classifiers":[
        {
            "category":"Autos & Motor Vehicles",
            "subcategory":"Auto Supplies",
            "type":"Retail Goods"
        }
    ],
    "sg:phone":"+32 2 334 89 11",
    "sg:postcode":"1480",
    "sg:province":"Brabant Wallon",
    "sg:tags":[
        "automobile",
        "accessory"
    ],
    "wof:name":"Impex Benelux Nv",
    "wof:placetype":"venue"
},
  "geometry": {"coordinates":[4.1727399826,50.7081718445],"type":"Point"}
}