{
  "type": "Feature",
  "properties": {
    "iso:country":"BE",
    "sg:address":"Steenbakkersstraat 49",
    "sg:city":"Kortrijk",
    "sg:orig_category":"Artistes ind\u00e9pendants",
    "sg:phone":"+32 56 22 48 12",
    "sg:postcode":"8500",
    "sg:province":"West-Vlaanderen",
    "wof:name":"Herman Hertogs",
    "wof:placetype":"venue"
},
  "geometry": {"coordinates":[3.2869849205,50.804523468],"type":"Point"}
}