{
  "type": "Feature",
  "properties": {
    "addr:full":"Rozenstraat 63 Wevelgem (groot) West-Vlaanderen 8560",
    "addr:housenumber":"63",
    "addr:postcode":"8560",
    "addr:street":"Rozenstraat;Groot West-Vlaanderen",
    "iso:country":"BE",
    "sg:address":"Rozenstraat 63",
    "sg:city":"Wevelgem (groot)",
    "sg:orig_category":"Kapsalons",
    "sg:postcode":"8560",
    "sg:province":"West-Vlaanderen",
    "wof:name":"Nancy",
    "wof:placetype":"venue"
},
  "geometry": {"coordinates":[3.1675329208,50.8422698975],"type":"Point"}
}