{
  "type": "Feature",
  "properties": {
    "iso:country":"BE",
    "sg:address":"Ieperstraat 166",
    "sg:city":"Menen",
    "sg:orig_category":"Boucheries",
    "sg:phone":"+32 56 51 17 46",
    "sg:postcode":"8930",
    "sg:province":"West-Vlaanderen",
    "wof:name":"Karel Catry",
    "wof:placetype":"venue"
},
  "geometry": {"coordinates":[3.1114759445,50.7989616394],"type":"Point"}
}