{
  "type": "Feature",
  "properties": {
    "addr:full":"Rue Sylvain Bawin 46 Orp-jauche Brabant Wallon 1350",
    "addr:housenumber":"46",
    "addr:postcode":"1350",
    "addr:street":"Rue Sylvain Bawin",
    "iso:country":"BE",
    "sg:address":"Rue Sylvain Bawin 46",
    "sg:city":"Orp-jauche",
    "sg:orig_category":"Openbare veiligheid",
    "sg:phone":"+32 19 63 32 61",
    "sg:postcode":"1350",
    "sg:province":"Brabant Wallon",
    "wof:name":"Police F\u00c9d\u00c9rale",
    "wof:placetype":"venue"
},
  "geometry": {"coordinates":[4.9886670113,50.7036094666],"type":"Point"}
}