{
  "type": "Feature",
  "properties": {
    "addr:full":"Markt 17 Sint-katelijne-waver Antwerpen 2860",
    "addr:housenumber":"17",
    "addr:postcode":"2860",
    "addr:street":"Markt",
    "iso:country":"BE",
    "sg:address":"Markt 17",
    "sg:city":"Sint-katelijne-waver",
    "sg:classifiers":[
        {
            "category":"Cafe",
            "type":"Food & Drink"
        }
    ],
    "sg:phone":"+32 15 32 10 10",
    "sg:postcode":"2860",
    "sg:province":"Antwerpen",
    "sg:tags":[
        "caf\u00e9s"
    ],
    "wof:name":"Francis Diricx",
    "wof:placetype":"venue"
},
  "geometry": {"coordinates":[4.5313940048,51.0701332092],"type":"Point"}
}