{
  "type": "Feature",
  "properties": {
    "iso:country":"BE",
    "sg:address":"Gentsesteenweg 16",
    "sg:city":"Zingem (huise)",
    "sg:classifiers":[
        {
            "category":"Health Services",
            "subcategory":"Health Practitioner",
            "type":"Services"
        }
    ],
    "sg:phone":"+32 9 384 42 14",
    "sg:postcode":"9750",
    "sg:province":"Oost-Vlaanderen",
    "sg:tags":[
        "physiotherapist"
    ],
    "wof:name":"Vanheuverswyn Bibian",
    "wof:placetype":"venue"
},
  "geometry": {"coordinates":[3.6168870926,50.9003334045],"type":"Point"}
}