{
  "type": "Feature",
  "properties": {
    "addr:full":"Torhoutsesteenweg 28 Oostende West-Vlaanderen 8400",
    "addr:housenumber":"28",
    "addr:postcode":"8400",
    "addr:street":"Torhoutsesteenweg",
    "iso:country":"BE",
    "sg:address":"Torhoutsesteenweg 28",
    "sg:city":"Oostende",
    "sg:orig_category":"Editeurs de journaux. Editeurs de revues and p\u00e9riodiques",
    "sg:phone":"+32 59 51 04 11",
    "sg:postcode":"8400",
    "sg:province":"West-Vlaanderen",
    "wof:name":"Fa. Echo",
    "wof:placetype":"venue"
},
  "geometry": {"coordinates":[2.9099059105,51.2265815735],"type":"Point"}
}