{
  "type": "Feature",
  "properties": {
    "addr:full":"Woluwedal 12 Box 93 Zaventem (sint-stevens-woluwe) Vlaams-Brabant 1932",
    "addr:housenumber":"12 box 93",
    "addr:postcode":"1932",
    "addr:street":"Woluwedal",
    "iso:country":"BE",
    "sg:address":"Woluwedal 12 Box 93",
    "sg:city":"Zaventem (sint-stevens-woluwe)",
    "sg:classifiers":[
        {
            "category":"Professional",
            "subcategory":"Advertising",
            "type":"Services"
        }
    ],
    "sg:phone":"+32 2 725 23 05",
    "sg:postcode":"1932",
    "sg:province":"Vlaams-Brabant",
    "sg:tags":[
        "item",
        "-",
        "business",
        "gift",
        "promotional"
    ],
    "wof:name":"For You Too",
    "wof:placetype":"venue"
},
  "geometry": {"coordinates":[4.4477062225,50.8571853638],"type":"Point"}
}