{
  "type": "Feature",
  "properties": {
    "iso:country":"BE",
    "sg:address":"Rue De Meeffe 13",
    "sg:city":"Fernelmont",
    "sg:orig_category":"Dierenartsen",
    "sg:phone":"+32 81 85 54 09",
    "sg:postcode":"5380",
    "sg:province":"Namur",
    "wof:name":"Jacques Montulet",
    "wof:placetype":"venue"
},
  "geometry": {"coordinates":[4.9861078262,50.5531463623],"type":"Point"}
}