{
  "type": "Feature",
  "properties": {
    "addr:full":"Kortrijkstraat 52 Wevelgem West-Vlaanderen 8560",
    "addr:housenumber":"52",
    "addr:postcode":"8560",
    "addr:street":"Kortrijkstraat",
    "iso:country":"BE",
    "sg:address":"Kortrijkstraat 52",
    "sg:city":"Wevelgem",
    "sg:orig_category":"M\u00e9decins and sp\u00e9cialistes",
    "sg:phone":"+32 56 41 16 22",
    "sg:postcode":"8560",
    "sg:province":"West-Vlaanderen",
    "wof:name":"Ghislain Van Der Meeren",
    "wof:placetype":"venue"
},
  "geometry": {"coordinates":[3.1877129078,50.809879303],"type":"Point"}
}