{
  "type": "Feature",
  "properties": {
    "iso:country":"BE",
    "sg:address":"Kaai 5",
    "sg:city":"Diest",
    "sg:classifiers":[
        {
            "category":"Cafe",
            "type":"Food & Drink"
        }
    ],
    "sg:phone":"+32 13 33 74 44",
    "sg:postcode":"3290",
    "sg:province":"Vlaams-Brabant",
    "sg:tags":[
        "caf\u00e9s"
    ],
    "wof:name":"De Diestse Kaai",
    "wof:placetype":"venue"
},
  "geometry": {"coordinates":[5.0493512154,50.9847640991],"type":"Point"}
}