{
  "type": "Feature",
  "properties": {
    "addr:full":"Avenue Paul Pastur 264 Charleroi (mont-sur-marchienne) Hainaut 6032",
    "addr:housenumber":"264",
    "addr:postcode":"6032",
    "addr:street":"Avenue Paul Pastur",
    "iso:country":"BE",
    "sg:address":"Avenue Paul Pastur 264",
    "sg:city":"Charleroi (mont-sur-marchienne)",
    "sg:classifiers":[
        {
            "category":"Health Services",
            "subcategory":"Dentist",
            "type":"Services"
        }
    ],
    "sg:phone":"+32 71 36 74 04",
    "sg:postcode":"6032",
    "sg:province":"Hainaut",
    "wof:name":"Flament J-c",
    "wof:placetype":"venue"
},
  "geometry": {"coordinates":[4.4149708748,50.394493103],"type":"Point"}
}