{
  "type": "Feature",
  "properties": {
    "addr:full":"Avenue Du Br\u00e9sil 15 Bruxelles Bruxelles-Capitale 1000",
    "addr:housenumber":"15",
    "addr:postcode":"1000",
    "addr:street":"Avenue Du Bre\u0301Sil",
    "iso:country":"BE",
    "sg:address":"Avenue Du Br\u00e9sil 15",
    "sg:city":"Bruxelles",
    "sg:classifiers":[
        {
            "category":"Professional",
            "subcategory":"Art Services",
            "type":"Services"
        }
    ],
    "sg:phone":"+32 2 672 87 39",
    "sg:postcode":"1000",
    "sg:province":"Bruxelles-Capitale",
    "sg:tags":[
        "-",
        "valuer"
    ],
    "wof:name":"Van Eyll J-j",
    "wof:placetype":"venue"
},
  "geometry": {"coordinates":[4.3896679878,50.8027420044],"type":"Point"}
}