{
  "type": "Feature",
  "properties": {
    "addr:full":"Avenue L\u00e9o Errera 66 Bruxelles (uccle) Bruxelles-Capitale 1180",
    "addr:housenumber":"66",
    "addr:postcode":"1180",
    "addr:street":"Avenue Le\u0301O Errera",
    "iso:country":"BE",
    "sg:address":"Avenue L\u00e9o Errera 66",
    "sg:city":"Bruxelles (uccle)",
    "sg:classifiers":[
        {
            "category":"Health Services",
            "subcategory":"Doctor",
            "type":"Services"
        }
    ],
    "sg:phone":"+32 2 345 12 69",
    "sg:postcode":"1180",
    "sg:province":"Bruxelles-Capitale",
    "sg:tags":[
        "medicinephysicians",
        "surgeon"
    ],
    "wof:name":"Lammens Pierre",
    "wof:placetype":"venue"
},
  "geometry": {"coordinates":[4.354514122,50.8088684082],"type":"Point"}
}