{
  "type": "Feature",
  "properties": {
    "addr:full":"Rue Saint-gangulphe 20 Florennes Namur 5620",
    "addr:housenumber":"20",
    "addr:postcode":"5620",
    "addr:street":"Rue Saint-Gangulphe",
    "iso:country":"BE",
    "sg:address":"Rue Saint-gangulphe 20",
    "sg:city":"Florennes",
    "sg:orig_category":"Instituts pour adultes moins valides",
    "sg:phone":"+32 71 68 84 26",
    "sg:postcode":"5620",
    "sg:province":"Namur",
    "wof:name":"I.m.p. St.dominique",
    "wof:placetype":"venue"
},
  "geometry": {"coordinates":[4.6028399467,50.2517051697],"type":"Point"}
}