{
  "type": "Feature",
  "properties": {
    "iso:country":"BE",
    "sg:address":"Route De Charleroi 210",
    "sg:city":"Binche",
    "sg:orig_category":"Quincailleries. Mat\u00e9riaux de construction Gr",
    "sg:phone":"+32 64 33 43 54",
    "sg:postcode":"7134",
    "sg:province":"Hainaut",
    "wof:name":"Basselier-rochez",
    "wof:placetype":"venue"
},
  "geometry": {"coordinates":[4.2175779343,50.4159622192],"type":"Point"}
}