{
  "type": "Feature",
  "properties": {
    "addr:full":"Richard Vandeveldestraat 96 Schaarbeek/schaerbeek Bruxelles-Capitale 1030",
    "addr:housenumber":"96",
    "addr:postcode":"1030",
    "addr:street":"Richard Vandeveldestraat",
    "iso:country":"BE",
    "sg:address":"Richard Vandeveldestraat 96",
    "sg:city":"Schaarbeek/schaerbeek",
    "sg:orig_category":"Banken and kredietinstellingen",
    "sg:phone":"+32 2 242 92 00",
    "sg:postcode":"1030",
    "sg:province":"Bruxelles-Capitale",
    "wof:name":"Citibank",
    "wof:placetype":"venue"
},
  "geometry": {"coordinates":[4.3911380768,50.8721923828],"type":"Point"}
}