{
  "type": "Feature",
  "properties": {
    "iso:country":"BE",
    "sg:address":"Kerkstraat 24",
    "sg:city":"Overijse",
    "sg:classifiers":[
        {
            "category":"Personal",
            "subcategory":"Sauna",
            "type":"Services"
        }
    ],
    "sg:phone":"+32 2 688 16 88",
    "sg:postcode":"3090",
    "sg:province":"Vlaams-Brabant",
    "sg:tags":[
        "installation",
        "-"
    ],
    "wof:name":"Domestic Solutions Bvba",
    "wof:placetype":"venue"
},
  "geometry": {"coordinates":[4.5676980019,50.7536773682],"type":"Point"}
}