{
  "type": "Feature",
  "properties": {
    "iso:country":"BE",
    "sg:address":"Gelindestraat 58",
    "sg:city":"Heers",
    "sg:orig_category":"Activit\u00e9s d\u00b4action sociale sans h\u00e9bergement",
    "sg:phone":"+32 11 48 26 76",
    "sg:postcode":"3870",
    "sg:province":"Limburg",
    "wof:name":"Rode Kruis Heers",
    "wof:placetype":"venue"
},
  "geometry": {"coordinates":[5.2601270676,50.7444992065],"type":"Point"}
}