{
  "type": "Feature",
  "properties": {
    "iso:country":"BE",
    "sg:address":"Rue De Landen 78",
    "sg:city":"Lincent (racour)",
    "sg:classifiers":[
        {
            "category":"Building & Trades",
            "subcategory":"Cleaning & Sanitation",
            "type":"Services"
        }
    ],
    "sg:phone":"+32 19 51 54 83",
    "sg:postcode":"4287",
    "sg:province":"Li\u00e8ge",
    "sg:tags":[
        "mainten",
        "-",
        "boiler"
    ],
    "wof:name":"Marechal K",
    "wof:placetype":"venue"
},
  "geometry": {"coordinates":[5.0335931778,50.7406616211],"type":"Point"}
}