{
  "type": "Feature",
  "properties": {
    "iso:country":"BE",
    "sg:address":"Keukelstraat 10",
    "sg:city":"Wingene",
    "sg:classifiers":[
        {
            "category":"Shopping",
            "subcategory":"Discount & Variety Stores",
            "type":"Retail Goods"
        }
    ],
    "sg:phone":"+32 473 43 40 48",
    "sg:postcode":"8750",
    "sg:province":"West-Vlaanderen",
    "sg:tags":[
        "shop",
        "clearers",
        "curiosity",
        "furniture"
    ],
    "wof:name":"Taelman",
    "wof:placetype":"venue"
},
  "geometry": {"coordinates":[3.3058300018,51.0636825562],"type":"Point"}
}