{
  "type": "Feature",
  "properties": {
    "addr:full":"Rue Bosseler 11 Aubange Luxembourg 6790",
    "addr:housenumber":"11",
    "addr:postcode":"6790",
    "addr:street":"Rue Bosseler",
    "iso:country":"BE",
    "sg:address":"Rue Bosseler 11",
    "sg:city":"Aubange",
    "sg:orig_category":"Notaires",
    "sg:phone":"+32 63 38 83 30",
    "sg:postcode":"6790",
    "sg:province":"Luxembourg",
    "wof:name":"M. Vanderhoven",
    "wof:placetype":"venue"
},
  "geometry": {"coordinates":[5.8048791885,49.5697212219],"type":"Point"}
}