{
  "type": "Feature",
  "properties": {
    "addr:full":"Sylvain Dupuislaan 191 Anderlecht Bruxelles-Capitale 1070",
    "addr:housenumber":"191",
    "addr:postcode":"1070",
    "addr:street":"Sylvain Dupuislaan",
    "iso:country":"BE",
    "sg:address":"Sylvain Dupuislaan 191",
    "sg:city":"Anderlecht",
    "sg:orig_category":"Banken and kredietinstellingen",
    "sg:phone":"+32 2 521 58 29",
    "sg:postcode":"1070",
    "sg:province":"Bruxelles-Capitale",
    "wof:name":"Kbc",
    "wof:placetype":"venue"
},
  "geometry": {"coordinates":[4.2967162132,50.8371086121],"type":"Point"}
}