{
  "type": "Feature",
  "properties": {
    "addr:full":"Driftweg 2a De Haan West-Vlaanderen 8420",
    "addr:housenumber":"2a",
    "addr:postcode":"8420",
    "addr:street":"Driftweg",
    "iso:country":"BE",
    "sg:address":"Driftweg 2a",
    "sg:city":"De Haan",
    "sg:orig_category":"Immobili\u00ebnkantoren Vakantiehuizen",
    "sg:phone":"+32 59 23 35 17",
    "sg:postcode":"8420",
    "sg:province":"West-Vlaanderen",
    "wof:name":"Agence Cambre",
    "wof:placetype":"venue"
},
  "geometry": {"coordinates":[3.0334630013,51.2721672058],"type":"Point"}
}