{
  "type": "Feature",
  "properties": {
    "iso:country":"BE",
    "sg:address":"Grotstraat 38",
    "sg:city":"Zutendaal",
    "sg:classifiers":[
        {
            "category":"Professional",
            "subcategory":"Detective & Security Services",
            "type":"Services"
        }
    ],
    "sg:phone":"+32 89 61 45 80",
    "sg:postcode":"3690",
    "sg:province":"Limburg",
    "sg:tags":[
        "installation",
        "alarm",
        "-",
        "system"
    ],
    "wof:name":"Ad & C",
    "wof:placetype":"venue"
},
  "geometry": {"coordinates":[5.555109024,50.9497528076],"type":"Point"}
}