{
  "type": "Feature",
  "properties": {
    "iso:country":"BE",
    "sg:address":"Koningin Astridplein 12",
    "sg:city":"Antwerpen",
    "sg:orig_category":"Agents artistiques",
    "sg:phone":"+32 3 226 75 75",
    "sg:postcode":"2018",
    "sg:province":"Antwerpen",
    "wof:name":"Lipstick International Broadcast Productions",
    "wof:placetype":"venue"
},
  "geometry": {"coordinates":[4.4218959808,51.218460083],"type":"Point"}
}