{
  "type": "Feature",
  "properties": {
    "addr:full":"Rue Lamberts 10 Welkenraedt Li\u00e8ge 4840",
    "addr:housenumber":"10",
    "addr:postcode":"4840",
    "addr:street":"Rue Lamberts",
    "iso:country":"BE",
    "sg:address":"Rue Lamberts 10",
    "sg:city":"Welkenraedt",
    "sg:classifiers":[
        {
            "category":"Bakery",
            "type":"Food & Drink"
        }
    ],
    "sg:phone":"+32 87 88 01 75",
    "sg:postcode":"4840",
    "sg:province":"Li\u00e8ge",
    "sg:tags":[
        "confectioner",
        "baker"
    ],
    "wof:name":"Lennertz A",
    "wof:placetype":"venue"
},
  "geometry": {"coordinates":[5.9742708206,50.6606636047],"type":"Point"}
}