{
  "type": "Feature",
  "properties": {
    "addr:full":"De Bergen 38 Dilbeek Vlaams-Brabant 1700",
    "addr:housenumber":"38",
    "addr:postcode":"1700",
    "addr:street":"De Bergen",
    "iso:country":"BE",
    "sg:address":"De Bergen 38",
    "sg:city":"Dilbeek",
    "sg:classifiers":[
        {
            "category":"Home & Garden",
            "subcategory":"Building Materials",
            "type":"Retail Goods"
        }
    ],
    "sg:phone":"+32 2 466 48 36",
    "sg:postcode":"1700",
    "sg:province":"Vlaams-Brabant",
    "sg:tags":[
        "shutter"
    ],
    "wof:name":"Van Den Driesch R",
    "wof:placetype":"venue"
},
  "geometry": {"coordinates":[4.2785329819,50.8544197083],"type":"Point"}
}