{
  "type": "Feature",
  "properties": {
    "addr:full":"Schoonheidsplein 11 Bruxelles (anderlecht) Bruxelles-Capitale 1070",
    "addr:housenumber":"11",
    "addr:postcode":"1070",
    "addr:street":"Schoonheidsplein",
    "iso:country":"BE",
    "sg:address":"Schoonheidsplein 11",
    "sg:city":"Bruxelles (anderlecht)",
    "sg:classifiers":[
        {
            "category":"Retail",
            "subcategory":"Auto Repair",
            "type":"Services"
        }
    ],
    "sg:phone":"+32 2 522 48 74",
    "sg:postcode":"1070",
    "sg:province":"Bruxelles-Capitale",
    "sg:tags":[
        "garage"
    ],
    "wof:name":"Beaut\u00e8 Garage Sprl",
    "wof:placetype":"venue"
},
  "geometry": {"coordinates":[4.3070368767,50.8394813538],"type":"Point"}
}