{
  "type": "Feature",
  "properties": {
    "addr:full":"Pontstraat 34 Aalst Oost-Vlaanderen 9300",
    "addr:housenumber":"34",
    "addr:postcode":"9300",
    "addr:street":"Pontstraat",
    "iso:country":"BE",
    "sg:address":"Pontstraat 34",
    "sg:city":"Aalst",
    "sg:orig_category":"Baby- and kinderkleding Dameskledingzaken Herenkledingzaken",
    "sg:phone":"+32 53 77 72 14",
    "sg:postcode":"9300",
    "sg:province":"Oost-Vlaanderen",
    "wof:name":"Superconfex",
    "wof:placetype":"venue"
},
  "geometry": {"coordinates":[4.0815548897,50.9648284912],"type":"Point"}
}