{
  "type": "Feature",
  "properties": {
    "addr:full":"Vleurgatsesteenweg 282b1 Elsene/ixelles Bruxelles-Capitale 1050",
    "addr:housenumber":"282b1",
    "addr:postcode":"1050",
    "addr:street":"Vleurgatsesteenweg",
    "iso:country":"BE",
    "sg:address":"Vleurgatsesteenweg 282b1",
    "sg:city":"Elsene/ixelles",
    "sg:orig_category":"Architecten",
    "sg:phone":"+32 2 644 28 88",
    "sg:postcode":"1050",
    "sg:province":"Bruxelles-Capitale",
    "wof:name":"Hubert Debiesme",
    "wof:placetype":"venue"
},
  "geometry": {"coordinates":[4.3664479256,50.8187522888],"type":"Point"}
}