{
  "type": "Feature",
  "properties": {
    "addr:full":"Le Routi 22 Bouillon Luxembourg 6830",
    "addr:housenumber":"22",
    "addr:postcode":"6830",
    "iso:country":"BE",
    "sg:address":"Le Routi 22",
    "sg:city":"Bouillon",
    "sg:classifiers":[
        {
            "category":"Fast Food",
            "type":"Food & Drink"
        }
    ],
    "sg:phone":"+32 61 46 86 20",
    "sg:postcode":"6830",
    "sg:province":"Luxembourg",
    "sg:tags":[
        "meeneem",
        "restaurant"
    ],
    "wof:name":"Le Monte Cristo",
    "wof:placetype":"venue"
},
  "geometry": {"coordinates":[5.0699849129,49.7954597473],"type":"Point"}
}