{
  "type": "Feature",
  "properties": {
    "iso:country":"BE",
    "sg:address":"Kerkstraat 227",
    "sg:city":"Deerlijk",
    "sg:orig_category":"Boucheries",
    "sg:phone":"+32 56 77 70 76",
    "sg:postcode":"8540",
    "sg:province":"West-Vlaanderen",
    "wof:name":"Bruno Mahieu",
    "wof:placetype":"venue"
},
  "geometry": {"coordinates":[3.3854339123,50.8298187256],"type":"Point"}
}