{
  "type": "Feature",
  "properties": {
    "addr:full":"Rue Auguste Donnay 47 Li\u00e8ge 1 Li\u00e8ge 4000",
    "addr:housenumber":"47;1",
    "addr:postcode":"4000",
    "addr:street":"Rue Auguste Donnay",
    "iso:country":"BE",
    "sg:address":"Rue Auguste Donnay 47",
    "sg:city":"Li\u00e8ge 1",
    "sg:classifiers":[
        {
            "category":"Home & Garden",
            "subcategory":"Home Furnishings",
            "type":"Retail Goods"
        }
    ],
    "sg:phone":"+32 4 224 14 61",
    "sg:postcode":"4000",
    "sg:province":"Li\u00e8ge",
    "sg:tags":[
        "interior",
        "decoration"
    ],
    "wof:name":"De Ruytter J",
    "wof:placetype":"venue"
},
  "geometry": {"coordinates":[5.5645360947,50.6539535522],"type":"Point"}
}