{
  "type": "Feature",
  "properties": {
    "addr:full":"Baarledorp 26 Drongen Oost-Vlaanderen 9031",
    "addr:housenumber":"26",
    "addr:postcode":"9031",
    "addr:street":"Baarledorp",
    "iso:country":"BE",
    "sg:address":"Baarledorp 26",
    "sg:city":"Drongen",
    "sg:classifiers":[
        {
            "category":"Banks & Credit Unions",
            "subcategory":"Bank",
            "type":"Services"
        }
    ],
    "sg:phone":"+32 9 281 08 81",
    "sg:postcode":"9031",
    "sg:province":"Oost-Vlaanderen",
    "wof:name":"Banque Bruxelles Lambert Sa",
    "wof:placetype":"venue"
},
  "geometry": {"coordinates":[3.6181590557,51.0371513367],"type":"Point"}
}