{
  "type": "Feature",
  "properties": {
    "addr:full":"Rue Jamodenne 14 Marche-en-famenne Luxembourg 6900",
    "addr:housenumber":"14",
    "addr:postcode":"6900",
    "addr:street":"Rue Jamodenne",
    "iso:country":"BE",
    "sg:address":"Rue Jamodenne 14",
    "sg:city":"Marche-en-famenne",
    "sg:orig_category":"Sportclubs Sportterreinen and installaties behalve sportcentra",
    "sg:phone":"+32 84 31 23 72",
    "sg:postcode":"6900",
    "sg:province":"Luxembourg",
    "wof:name":"R. Jeunesse Reunie D\u00b4aye",
    "wof:placetype":"venue"
},
  "geometry": {"coordinates":[5.3430151939,50.2273483276],"type":"Point"}
}