{
  "type": "Feature",
  "properties": {
    "addr:full":"Boulevard Sylvain Dupuis 423 Anderlecht/anderlecht Bruxelles-Capitale 1070",
    "addr:housenumber":"423",
    "addr:postcode":"1070",
    "addr:street":"Boulevard Sylvain Dupuis",
    "iso:country":"BE",
    "sg:address":"Boulevard Sylvain Dupuis 423",
    "sg:city":"Anderlecht/anderlecht",
    "sg:orig_category":"V\u00eatements pour b\u00e9b\u00e9s and enfants",
    "sg:phone":"+32 2 523 48 84",
    "sg:postcode":"1070",
    "sg:province":"Bruxelles-Capitale",
    "wof:name":"Kid Cool",
    "wof:placetype":"venue"
},
  "geometry": {"coordinates":[4.2860651016,50.8380088806],"type":"Point"}
}