{
  "type": "Feature",
  "properties": {
    "addr:full":"Leopoldlaan 75 Ninove Oost-Vlaanderen 9400",
    "addr:housenumber":"75",
    "addr:postcode":"9400",
    "addr:street":"Leopoldlaan",
    "iso:country":"BE",
    "sg:address":"Leopoldlaan 75",
    "sg:city":"Ninove",
    "sg:classifiers":[
        {
            "category":"Health Services",
            "subcategory":"Health Practitioner",
            "type":"Services"
        }
    ],
    "sg:phone":"+32 54 34 42 90",
    "sg:postcode":"9400",
    "sg:province":"Oost-Vlaanderen",
    "sg:tags":[
        "physiotherapist"
    ],
    "wof:name":"Roosens Greet",
    "wof:placetype":"venue"
},
  "geometry": {"coordinates":[4.0198922157,50.8261413574],"type":"Point"}
}