{
  "type": "Feature",
  "properties": {
    "iso:country":"BE",
    "sg:address":"Oosterzelestraat 17",
    "sg:city":"Wetteren",
    "sg:orig_category":"Textiel",
    "sg:phone":"+32 9 366 59 33",
    "sg:postcode":"9230",
    "sg:province":"Oost-Vlaanderen",
    "wof:name":"Cl. Moreels",
    "wof:placetype":"venue"
},
  "geometry": {"coordinates":[3.8433070183,50.979221344],"type":"Point"}
}