{
  "type": "Feature",
  "properties": {
    "iso:country":"BE",
    "sg:address":"Merksplasseweg 66",
    "sg:city":"Beerse",
    "sg:orig_category":"Salles de conf\u00e9rences and de r\u00e9ceptions. Catering and organisation de f\u00eates",
    "sg:phone":"+32 14 61 39 77",
    "sg:postcode":"2340",
    "sg:province":"Antwerpen",
    "wof:name":"Feestzaal Beerse Hoeve",
    "wof:placetype":"venue"
},
  "geometry": {"coordinates":[4.8563351631,51.334690094],"type":"Point"}
}