{
  "type": "Feature",
  "properties": {
    "iso:country":"BE",
    "sg:address":"Onze-lieve-vrouwplein 7",
    "sg:city":"Sint-niklaas",
    "sg:classifiers":[
        {
            "category":"Shopping",
            "subcategory":"Bicycles & Sporting Goods",
            "type":"Retail Goods"
        }
    ],
    "sg:phone":"+32 3 776 18 39",
    "sg:postcode":"9100",
    "sg:province":"Oost-Vlaanderen",
    "sg:tags":[
        "sport",
        "-"
    ],
    "wof:name":"De Pijl-sport",
    "wof:placetype":"venue"
},
  "geometry": {"coordinates":[4.1363902092,51.1659584045],"type":"Point"}
}