{
  "type": "Feature",
  "properties": {
    "addr:full":"Le-hortrez 1 Florenville Luxembourg 6820",
    "addr:housenumber":"1",
    "addr:postcode":"6820",
    "addr:street":"Le-Hortrez",
    "iso:country":"BE",
    "sg:address":"Le-hortrez 1",
    "sg:city":"Florenville",
    "sg:orig_category":"Gespecialiseerde niet-residenti\u00eble bouw",
    "sg:phone":"+32 61 31 19 97",
    "sg:postcode":"6820",
    "sg:province":"Luxembourg",
    "wof:name":"Muller",
    "wof:placetype":"venue"
},
  "geometry": {"coordinates":[5.304502964,49.6977386475],"type":"Point"}
}