{
  "type": "Feature",
  "properties": {
    "iso:country":"BE",
    "sg:address":"Rue Van Artevelde 78-80",
    "sg:city":"Brussel/bruxelles",
    "sg:orig_category":"Fournitures de bureau. Agences de publicit\u00e9",
    "sg:phone":"+32 2 511 50 89",
    "sg:postcode":"1000",
    "sg:province":"Bruxelles-Capitale",
    "wof:name":"S'jongers",
    "wof:placetype":"venue"
},
  "geometry": {"coordinates":[4.3450698853,50.8472480774],"type":"Point"}
}