{
  "type": "Feature",
  "properties": {
    "iso:country":"BE",
    "sg:address":"Kattestraat 5a",
    "sg:city":"Aalst",
    "sg:orig_category":"Centres de relaxation and bien-\u00eatre. Parfumeries. Instituts de beaut\u00e9",
    "sg:phone":"+32 53 78 76 11",
    "sg:postcode":"9300",
    "sg:province":"Oost-Vlaanderen",
    "wof:name":"Yves Rocher",
    "wof:placetype":"venue"
},
  "geometry": {"coordinates":[4.0389652252,50.9384689331],"type":"Point"}
}