{
  "type": "Feature",
  "properties": {
    "iso:country":"BE",
    "sg:address":"Les-hayons 5",
    "sg:city":"Florenville",
    "sg:orig_category":"V\u00e9t\u00e9rinaires",
    "sg:phone":"+32 61 31 38 95",
    "sg:postcode":"6820",
    "sg:province":"Luxembourg",
    "wof:name":"Christine Pr\u00c9vot",
    "wof:placetype":"venue"
},
  "geometry": {"coordinates":[5.3266639709,49.6882209778],"type":"Point"}
}