{
  "type": "Feature",
  "properties": {
    "addr:full":"Rue Des Bruy\u00c8res 157 Mons Hainaut 7034",
    "addr:housenumber":"157",
    "addr:postcode":"7034",
    "addr:street":"Rue Des Bruye\u0300Res;Hainaut",
    "iso:country":"BE",
    "sg:address":"Rue Des Bruy\u00c8res 157",
    "sg:city":"Mons",
    "sg:classifiers":[
        {
            "category":"Personal",
            "subcategory":"Beauty Salon",
            "type":"Services"
        }
    ],
    "sg:phone":"+32 65 72 30 84",
    "sg:postcode":"7034",
    "sg:province":"Hainaut",
    "sg:tags":[
        "de",
        "coiffure"
    ],
    "wof:name":"Coiffure Martine",
    "wof:placetype":"venue"
},
  "geometry": {"coordinates":[4.0086159706,50.4765396118],"type":"Point"}
}