{
  "type": "Feature",
  "properties": {
    "addr:full":"Sar\u00e9mont 21 Herve (bolland) Li\u00e8ge 4653",
    "addr:housenumber":"21",
    "addr:postcode":"4653",
    "addr:street":"Sare\u0301Mont;Bolland",
    "iso:country":"BE",
    "sg:address":"Sar\u00e9mont 21",
    "sg:city":"Herve (bolland)",
    "sg:classifiers":[
        {
            "category":"Arts & Performance",
            "subcategory":"Symphony",
            "type":"Entertainment"
        }
    ],
    "sg:phone":"+32 87 67 51 37",
    "sg:postcode":"4653",
    "sg:province":"Li\u00e8ge",
    "sg:tags":[
        "orchestra"
    ],
    "wof:name":"Sauvage J.l.",
    "wof:placetype":"venue"
},
  "geometry": {"coordinates":[5.7589969635,50.661365509],"type":"Point"}
}