{
  "type": "Feature",
  "properties": {
    "addr:full":"Kruikstraat 28 Antwerpen Antwerpen 2018",
    "addr:housenumber":"28",
    "addr:postcode":"2018",
    "addr:street":"Kruikstraat",
    "iso:country":"BE",
    "sg:address":"Kruikstraat 28",
    "sg:city":"Antwerpen",
    "sg:classifiers":[
        {
            "category":"Personal",
            "subcategory":"Massage",
            "type":"Services"
        }
    ],
    "sg:phone":"+32 3 383 38 28",
    "sg:postcode":"2018",
    "sg:province":"Antwerpen",
    "wof:name":"Massage Hilde Koninckx",
    "wof:placetype":"venue"
},
  "geometry": {"coordinates":[4.4260401726,51.2088356018],"type":"Point"}
}