{
  "type": "Feature",
  "properties": {
    "iso:country":"BE",
    "sg:address":"Drabstraat 42",
    "sg:city":"Gent",
    "sg:classifiers":[
        {
            "category":"Education",
            "subcategory":"School",
            "type":"Public Place"
        }
    ],
    "sg:phone":"+32 9 225 74 45",
    "sg:postcode":"9000",
    "sg:province":"Oost-Vlaanderen",
    "sg:tags":[
        "secondary"
    ],
    "wof:name":"Kunsthumaniora Muziek-dans",
    "wof:placetype":"venue"
},
  "geometry": {"coordinates":[3.7187149525,51.055355072],"type":"Point"}
}