{
  "type": "Feature",
  "properties": {
    "addr:full":"Nieuwstraat 12 Wetteren Oost-Vlaanderen 9230",
    "addr:housenumber":"12",
    "addr:postcode":"9230",
    "addr:street":"Nieuwstraat",
    "iso:country":"BE",
    "sg:address":"Nieuwstraat 12",
    "sg:city":"Wetteren",
    "sg:classifiers":[
        {
            "category":"Cafe",
            "type":"Food & Drink"
        }
    ],
    "sg:phone":"+32 9 369 35 49",
    "sg:postcode":"9230",
    "sg:province":"Oost-Vlaanderen",
    "sg:tags":[
        "caf\u00e9s"
    ],
    "wof:name":"Caf\u00c9 De Vriendschap",
    "wof:placetype":"venue"
},
  "geometry": {"coordinates":[3.8807170391,51.0029830933],"type":"Point"}
}