{
  "type": "Feature",
  "properties": {
    "addr:full":"Koningsstraat 2 Oostende West-Vlaanderen 8400",
    "addr:housenumber":"2",
    "addr:postcode":"8400",
    "addr:street":"Koningsstraat",
    "iso:country":"BE",
    "sg:address":"Koningsstraat 2",
    "sg:city":"Oostende",
    "sg:orig_category":"Promoteurs immobiliers. Agences immobili\u00e8res",
    "sg:phone":"+32 59 80 55 97",
    "sg:postcode":"8400",
    "sg:province":"West-Vlaanderen",
    "wof:name":"Chateau Residenties",
    "wof:placetype":"venue"
},
  "geometry": {"coordinates":[2.9131789207,51.2304382324],"type":"Point"}
}