{
  "type": "Feature",
  "properties": {
    "iso:country":"BE",
    "sg:address":"Lu-p'tite-voye 0",
    "sg:city":"Saint-hubert",
    "sg:orig_category":"Dierenartsen",
    "sg:phone":"+32 61 21 61 40",
    "sg:postcode":"6870",
    "sg:province":"Luxembourg",
    "wof:name":"Armand Sternotte",
    "wof:placetype":"venue"
},
  "geometry": {"coordinates":[5.3783578873,50.0336723328],"type":"Point"}
}