{
  "type": "Feature",
  "properties": {
    "addr:full":"Rue De La Bruy\u00c8re 50 Mons Hainaut 7021",
    "addr:housenumber":"50",
    "addr:postcode":"7021",
    "addr:street":"Rue De La Bruye\u0300Re;Hainaut",
    "iso:country":"BE",
    "sg:address":"Rue De La Bruy\u00c8re 50",
    "sg:city":"Mons",
    "sg:orig_category":"Dakwerken",
    "sg:phone":"+32 65 87 22 36",
    "sg:postcode":"7021",
    "sg:province":"Hainaut",
    "wof:name":"Ren\u00c9 Flament",
    "wof:placetype":"venue"
},
  "geometry": {"coordinates":[4.0456829071,50.4640655518],"type":"Point"}
}