{
  "type": "Feature",
  "properties": {
    "addr:full":"Persijzerstraat 21 Lochristi Oost-Vlaanderen 9080",
    "addr:housenumber":"21",
    "addr:postcode":"9080",
    "addr:street":"Persijzerstraat",
    "iso:country":"BE",
    "sg:address":"Persijzerstraat 21",
    "sg:city":"Lochristi",
    "sg:orig_category":"SMEEDWERK, METAALBEWERKING AND POEDERMETALLURGIE",
    "sg:phone":"+32 9 355 09 09",
    "sg:postcode":"9080",
    "sg:province":"Oost-Vlaanderen",
    "wof:name":"D. Van Kerkvoorde",
    "wof:placetype":"venue"
},
  "geometry": {"coordinates":[3.8850269318,51.1269340515],"type":"Point"}
}