{
  "type": "Feature",
  "properties": {
    "iso:country":"BE",
    "sg:address":"Bredestraat 127",
    "sg:city":"Gent",
    "sg:orig_category":"Emballages en plastique Fab",
    "sg:phone":"+32 9 251 05 37",
    "sg:postcode":"9041",
    "sg:province":"Oost-Vlaanderen",
    "wof:name":"Janssens Plastics",
    "wof:placetype":"venue"
},
  "geometry": {"coordinates":[3.7743721008,51.1035804749],"type":"Point"}
}