{
  "type": "Feature",
  "properties": {
    "addr:full":"Heerle 13 Hoogstraten Antwerpen 2322",
    "addr:housenumber":"13",
    "addr:postcode":"2322",
    "addr:street":"Heerle",
    "iso:country":"BE",
    "sg:address":"Heerle 13",
    "sg:city":"Hoogstraten",
    "sg:classifiers":[
        {
            "category":"Insurance",
            "subcategory":"Insurance Agent",
            "type":"Services"
        }
    ],
    "sg:phone":"+32 3 314 70 30",
    "sg:postcode":"2322",
    "sg:province":"Antwerpen",
    "sg:tags":[
        "verzekeringsmakelaars",
        "expert"
    ],
    "wof:name":"Coenegrachts-desmedt",
    "wof:placetype":"venue"
},
  "geometry": {"coordinates":[4.763384819,51.4160041809],"type":"Point"}
}