{
  "type": "Feature",
  "properties": {
    "iso:country":"BE",
    "sg:address":"Koningsgalerij 5",
    "sg:city":"Brussel/bruxelles",
    "sg:orig_category":"Fotografen and fotostudio's",
    "sg:phone":"+32 2 502 41 00",
    "sg:postcode":"1000",
    "sg:province":"Bruxelles-Capitale",
    "wof:name":"Thierry Van Biesen",
    "wof:placetype":"venue"
},
  "geometry": {"coordinates":[4.3596301079,50.8420333862],"type":"Point"}
}