{
  "type": "Feature",
  "properties": {
    "iso:country":"BE",
    "sg:address":"Van Den Nestlaan 107a",
    "sg:city":"Ranst",
    "sg:orig_category":"Bloemen and planten",
    "sg:phone":"+32 3 485 68 55",
    "sg:postcode":"2520",
    "sg:province":"Antwerpen",
    "wof:name":"Van Nuffelen",
    "wof:placetype":"venue"
},
  "geometry": {"coordinates":[4.5800499916,51.1769332886],"type":"Point"}
}