{
  "type": "Feature",
  "properties": {
    "addr:full":"Mechelsesteenweg 1 Leuven Vlaams-Brabant 3012",
    "addr:housenumber":"1",
    "addr:postcode":"3012",
    "addr:street":"Mechelsesteenweg",
    "iso:country":"BE",
    "sg:address":"Mechelsesteenweg 1",
    "sg:city":"Leuven",
    "sg:orig_category":"Banques and organismes de cr\u00e9dit",
    "sg:phone":"+32 16 20 21 65",
    "sg:postcode":"3012",
    "sg:province":"Vlaams-Brabant",
    "wof:name":"Fortis",
    "wof:placetype":"venue"
},
  "geometry": {"coordinates":[4.694893837,50.8896751404],"type":"Point"}
}