{
  "type": "Feature",
  "properties": {
    "addr:full":"Tervuursesteenweg 46 Bertem Vlaams-Brabant 3060",
    "addr:housenumber":"46",
    "addr:postcode":"3060",
    "addr:street":"Tervuursesteenweg",
    "iso:country":"BE",
    "sg:address":"Tervuursesteenweg 46",
    "sg:city":"Bertem",
    "sg:orig_category":"M\u00e9decins and sp\u00e9cialistes",
    "sg:phone":"+32 16 49 07 17",
    "sg:postcode":"3060",
    "sg:province":"Vlaams-Brabant",
    "wof:name":"Ann Putseys",
    "wof:placetype":"venue"
},
  "geometry": {"coordinates":[4.6398720741,50.8678474426],"type":"Point"}
}