{
  "type": "Feature",
  "properties": {
    "iso:country":"BE",
    "sg:address":"Yzerhand 28",
    "sg:city":"Beveren",
    "sg:orig_category":"R\u00e9parations d'appareils \u00e9lectrom\u00e9nagers. Electrom\u00e9nager, t\u00e9l\u00e9visions and radios. Installation \u00e9lectr",
    "sg:phone":"+32 3 775 88 07",
    "sg:postcode":"9120",
    "sg:province":"Oost-Vlaanderen",
    "wof:name":"De Munck Electro & Kado",
    "wof:placetype":"venue"
},
  "geometry": {"coordinates":[4.2519860268,51.2159805298],"type":"Point"}
}