{
  "type": "Feature",
  "properties": {
    "addr:full":"Rue Des Censes 25 Weismes (robertville) Li\u00e8ge 4950",
    "addr:housenumber":"25",
    "addr:postcode":"4950",
    "addr:street":"Rue Des Censes;Robertville",
    "iso:country":"BE",
    "sg:address":"Rue Des Censes 25",
    "sg:city":"Weismes (robertville)",
    "sg:classifiers":[
        {
            "category":"Freight",
            "type":"Transportation"
        }
    ],
    "sg:phone":"+32 495 28 05 80",
    "sg:postcode":"4950",
    "sg:province":"Li\u00e8ge",
    "sg:tags":[
        "-",
        "transport"
    ],
    "wof:name":"M.b. Transports",
    "wof:placetype":"venue"
},
  "geometry": {"coordinates":[6.1306729317,50.4700965881],"type":"Point"}
}