{
  "type": "Feature",
  "properties": {
    "addr:full":"Cit\u00c9 Chasseurs Ardennais 4 Herbeumont Luxembourg 6887",
    "addr:housenumber":"4",
    "addr:postcode":"6887",
    "addr:street":"Cite\u0301 Chasseurs Ardennais",
    "iso:country":"BE",
    "sg:address":"Cit\u00c9 Chasseurs Ardennais 4",
    "sg:city":"Herbeumont",
    "sg:orig_category":"Artsen and specialisten",
    "sg:phone":"+32 61 41 34 85",
    "sg:postcode":"6887",
    "sg:province":"Luxembourg",
    "wof:name":"Michel Lambert",
    "wof:placetype":"venue"
},
  "geometry": {"coordinates":[5.2362008095,49.7843437195],"type":"Point"}
}