{
  "type": "Feature",
  "properties": {
    "addr:full":"Heerweg 51 Wevelgem West-Vlaanderen 8560",
    "addr:housenumber":"51",
    "addr:postcode":"8560",
    "addr:street":"Heerweg",
    "iso:country":"BE",
    "sg:address":"Heerweg 51",
    "sg:city":"Wevelgem",
    "sg:orig_category":"Mat\u00e9riel m\u00e9dical and orthop\u00e9dique and proth\u00e8ses Fab",
    "sg:phone":"+32 56 41 27 20",
    "sg:postcode":"8560",
    "sg:province":"West-Vlaanderen",
    "wof:name":"Jaak Bridelance",
    "wof:placetype":"venue"
},
  "geometry": {"coordinates":[3.1711990833,50.8384170532],"type":"Point"}
}