{
  "type": "Feature",
  "properties": {
    "addr:full":"Zavelstraat 81 Dilbeek (sint-ulriks-kapelle) Vlaams-Brabant 1700",
    "addr:housenumber":"81",
    "addr:postcode":"1700",
    "addr:street":"Zavelstraat",
    "iso:country":"BE",
    "sg:address":"Zavelstraat 81",
    "sg:city":"Dilbeek (sint-ulriks-kapelle)",
    "sg:classifiers":[
        {
            "category":"Professional",
            "subcategory":"Management & Consulting",
            "type":"Services"
        }
    ],
    "sg:phone":"+32 2 582 67 55",
    "sg:postcode":"1700",
    "sg:province":"Vlaams-Brabant",
    "sg:tags":[
        "tax-consultants"
    ],
    "wof:name":"Truyts J",
    "wof:placetype":"venue"
},
  "geometry": {"coordinates":[4.2241449356,50.871509552],"type":"Point"}
}