{
  "type": "Feature",
  "properties": {
    "addr:full":"Sint-kwintensstraat 21 Linter (wommersom) Vlaams-Brabant 3350",
    "addr:housenumber":"21",
    "addr:postcode":"3350",
    "addr:street":"Sint-Kwintensstraat",
    "iso:country":"BE",
    "sg:address":"Sint-kwintensstraat 21",
    "sg:city":"Linter (wommersom)",
    "sg:classifiers":[
        {
            "category":"Bars & Pubs",
            "type":"Food & Drink"
        }
    ],
    "sg:phone":"+32 16 78 80 33",
    "sg:postcode":"3350",
    "sg:province":"Vlaams-Brabant",
    "wof:name":"Carlo",
    "wof:placetype":"venue"
},
  "geometry": {"coordinates":[5.0184941292,50.8126106262],"type":"Point"}
}