{
  "type": "Feature",
  "properties": {
    "iso:country":"BE",
    "sg:address":"Kriekenstraat 18",
    "sg:city":"Lier",
    "sg:classifiers":[
        {
            "category":"Banks & Credit Unions",
            "subcategory":"Investment Brokerage",
            "type":"Services"
        }
    ],
    "sg:phone":"+32 3 480 24 37",
    "sg:postcode":"2500",
    "sg:province":"Antwerpen",
    "sg:tags":[
        "repair",
        "-",
        "installation",
        "sanitary",
        "article"
    ],
    "wof:name":"Aqua-verca Bvba",
    "wof:placetype":"venue"
},
  "geometry": {"coordinates":[4.5932598114,51.1464767456],"type":"Point"}
}