{
  "type": "Feature",
  "properties": {
    "iso:country":"BE",
    "sg:address":"Rue L\u00e9on Dop\u00e9r\u00e9 78",
    "sg:city":"Bruxelles (jette)",
    "sg:classifiers":[
        {
            "category":"Social Services",
            "subcategory":"Child Care",
            "type":"Services"
        }
    ],
    "sg:phone":"+32 2 428 52 05",
    "sg:postcode":"1090",
    "sg:province":"Bruxelles-Capitale",
    "sg:tags":[
        "baby",
        "nursery",
        "day",
        "sitting"
    ],
    "wof:name":"B\u00e9be Nuage",
    "wof:placetype":"venue"
},
  "geometry": {"coordinates":[4.321764946,50.8750648499],"type":"Point"}
}