{
  "type": "Feature",
  "properties": {
    "iso:country":"BE",
    "sg:address":"Brugstraat 52",
    "sg:city":"Stekene",
    "sg:orig_category":"V\u00e9t\u00e9rinaires",
    "sg:phone":"+32 3 779 68 49",
    "sg:postcode":"9190",
    "sg:province":"Oost-Vlaanderen",
    "wof:name":"Maria Vermeiren",
    "wof:placetype":"venue"
},
  "geometry": {"coordinates":[4.0332341194,51.2007293701],"type":"Point"}
}