{
  "type": "Feature",
  "properties": {
    "addr:full":"Chauss\u00c9e De Namur 27 Nivelles Brabant Wallon 1400",
    "addr:housenumber":"27",
    "addr:postcode":"1400",
    "addr:street":"Chausse\u0301E De Namur",
    "iso:country":"BE",
    "sg:address":"Chauss\u00c9e De Namur 27",
    "sg:city":"Nivelles",
    "sg:orig_category":"Drogisterijen",
    "sg:phone":"+32 67 22 01 36",
    "sg:postcode":"1400",
    "sg:province":"Brabant Wallon",
    "wof:name":"Paul Pigeon",
    "wof:placetype":"venue"
},
  "geometry": {"coordinates":[4.3469228745,50.5992507935],"type":"Point"}
}