{
  "type": "Feature",
  "properties": {
    "addr:full":"Ketelpoort 1 Gent Oost-Vlaanderen 9000",
    "addr:housenumber":"1",
    "addr:postcode":"9000",
    "addr:street":"Ketelpoort;Oost-Vlaanderen",
    "iso:country":"BE",
    "sg:address":"Ketelpoort 1",
    "sg:city":"Gent",
    "sg:classifiers":[
        {
            "category":"Bars & Pubs",
            "type":"Food & Drink"
        }
    ],
    "sg:phone":"+32 9 223 73 50",
    "sg:postcode":"9000",
    "sg:province":"Oost-Vlaanderen",
    "sg:tags":[
        "tavern"
    ],
    "wof:name":"Mistral Bvba",
    "wof:placetype":"venue"
},
  "geometry": {"coordinates":[3.7211740017,51.0488052368],"type":"Point"}
}