{
  "type": "Feature",
  "properties": {
    "addr:full":"Muilemlaan 64 Ternat (sint-katherina-lombeek) Vlaams-Brabant 1742",
    "addr:housenumber":"64",
    "addr:postcode":"1742",
    "addr:street":"Muilemlaan",
    "iso:country":"BE",
    "sg:address":"Muilemlaan 64",
    "sg:city":"Ternat (sint-katherina-lombeek)",
    "sg:classifiers":[
        {
            "category":"Banks & Credit Unions",
            "subcategory":"Investment Brokerage",
            "type":"Services"
        }
    ],
    "sg:phone":"+32 2 582 43 74",
    "sg:postcode":"1742",
    "sg:province":"Vlaams-Brabant",
    "sg:tags":[
        "printing",
        "-"
    ],
    "wof:name":"Goessens A",
    "wof:placetype":"venue"
},
  "geometry": {"coordinates":[4.1438808441,50.8766136169],"type":"Point"}
}