{
  "type": "Feature",
  "properties": {
    "addr:full":"Hazenfonteinstraat 33 Oud-heverlee Vlaams-Brabant 3050",
    "addr:housenumber":"33",
    "addr:postcode":"3050",
    "addr:street":"Hazenfonteinstraat",
    "iso:country":"BE",
    "sg:address":"Hazenfonteinstraat 33",
    "sg:city":"Oud-heverlee",
    "sg:classifiers":[
        {
            "category":"Building & Trades",
            "subcategory":"Electrical",
            "type":"Services"
        }
    ],
    "sg:phone":"+32 16 40 70 62",
    "sg:postcode":"3050",
    "sg:province":"Vlaams-Brabant",
    "sg:tags":[
        "electric",
        "-",
        "housewiring",
        "contractor"
    ],
    "wof:name":"Evers Elektro Bvba",
    "wof:placetype":"venue"
},
  "geometry": {"coordinates":[4.6673932076,50.8470039368],"type":"Point"}
}