{
  "type": "Feature",
  "properties": {
    "iso:country":"BE",
    "sg:address":"Grasmarkt 20",
    "sg:city":"Brussel/bruxelles",
    "sg:orig_category":"Schoenen",
    "sg:phone":"+32 2 218 11 69",
    "sg:postcode":"1000",
    "sg:province":"Bruxelles-Capitale",
    "wof:name":"Gontier Diffusion",
    "wof:placetype":"venue"
},
  "geometry": {"coordinates":[4.3522782326,50.8480796814],"type":"Point"}
}