{
  "type": "Feature",
  "properties": {
    "addr:full":"Chauss\u00e9e Du Long Bout 182 Mouscron (herseaux) Hainaut 7712",
    "addr:housenumber":"182",
    "addr:postcode":"7712",
    "addr:street":"Chausse\u0301E Du Long Bout",
    "iso:country":"BE",
    "sg:address":"Chauss\u00e9e Du Long Bout 182",
    "sg:city":"Mouscron (herseaux)",
    "sg:classifiers":[
        {
            "category":"Food & Beverages",
            "subcategory":"Fruits & Vegetables",
            "type":"Retail Goods"
        }
    ],
    "sg:phone":"+32 56 34 39 21",
    "sg:postcode":"7712",
    "sg:province":"Hainaut",
    "sg:tags":[
        "-"
    ],
    "wof:name":"Mas Bell Sprl",
    "wof:placetype":"venue"
},
  "geometry": {"coordinates":[3.2558848858,50.7237434387],"type":"Point"}
}