{
  "type": "Feature",
  "properties": {
    "addr:full":"Chauss\u00e9e Du Risquons-tout 147 Mouscron Hainaut 7700",
    "addr:housenumber":"147",
    "addr:postcode":"7700",
    "addr:street":"Chausse\u0301E Du Risquons-Tout",
    "iso:country":"BE",
    "sg:address":"Chauss\u00e9e Du Risquons-tout 147",
    "sg:city":"Mouscron",
    "sg:classifiers":[
        {
            "category":"Food & Beverages",
            "subcategory":"Liquor & Beverages",
            "type":"Retail Goods"
        }
    ],
    "sg:phone":"+32 56 34 21 34",
    "sg:postcode":"7700",
    "sg:province":"Hainaut",
    "sg:tags":[
        "-",
        "spirit",
        "wine"
    ],
    "wof:name":"Aux Vins De France",
    "wof:placetype":"venue"
},
  "geometry": {"coordinates":[3.2010519505,50.745223999],"type":"Point"}
}