{
  "type": "Feature",
  "properties": {
    "iso:country":"BE",
    "sg:address":"Dr\u00c8ve Richelle 161",
    "sg:city":"Waterloo",
    "sg:orig_category":"Imprimeries and copyshops",
    "sg:phone":"+32 2 352 05 50",
    "sg:postcode":"1410",
    "sg:province":"Brabant Wallon",
    "wof:name":"M.a. Hanna Company",
    "wof:placetype":"venue"
},
  "geometry": {"coordinates":[4.4104981422,50.7075843811],"type":"Point"}
}