{
  "type": "Feature",
  "properties": {
    "iso:country":"BE",
    "sg:address":"Bergenstraat 136",
    "sg:city":"Oud-heverlee",
    "sg:orig_category":"Beheer onroerend goed",
    "sg:phone":"+32 16 40 14 04",
    "sg:postcode":"3052",
    "sg:province":"Vlaams-Brabant",
    "wof:name":"Johanna Decoster",
    "wof:placetype":"venue"
},
  "geometry": {"coordinates":[4.7251219749,50.8249053955],"type":"Point"}
}