{
  "type": "Feature",
  "properties": {
    "iso:country":"BE",
    "sg:address":"Rue Dieu De Piti\u00c9 64",
    "sg:city":"Fleurus",
    "sg:orig_category":"Electrom\u00e9nager, t\u00e9l\u00e9visions and radios",
    "sg:phone":"+32 71 81 51 11",
    "sg:postcode":"6220",
    "sg:province":"Hainaut",
    "wof:name":"Desire Mahaux",
    "wof:placetype":"venue"
},
  "geometry": {"coordinates":[4.5490350723,50.4932365417],"type":"Point"}
}