{
  "type": "Feature",
  "properties": {
    "addr:full":"Tiensestraat 93 Hoegaarden Vlaams-Brabant 3320",
    "addr:housenumber":"93",
    "addr:postcode":"3320",
    "addr:street":"Tiensestraat",
    "iso:country":"BE",
    "sg:address":"Tiensestraat 93",
    "sg:city":"Hoegaarden",
    "sg:orig_category":"Elektrische installaties voor woningen Huishoudapparaten, televisies and radio's",
    "sg:phone":"+32 16 76 64 20",
    "sg:postcode":"3320",
    "sg:province":"Vlaams-Brabant",
    "wof:name":"Lucien De Bruyn",
    "wof:placetype":"venue"
},
  "geometry": {"coordinates":[4.8940658569,50.7778549194],"type":"Point"}
}