{
  "type": "Feature",
  "properties": {
    "iso:country":"BE",
    "sg:address":"Beaulieustraat 12",
    "sg:city":"Machelen (groot)",
    "sg:orig_category":"Herstellingen and onderhoud aan huis voor voertuigen Metaalafval, schrootrecyclage and sloperijen On",
    "sg:phone":"+32 2 252 55 50",
    "sg:postcode":"1830",
    "sg:province":"Vlaams-Brabant",
    "wof:name":"B.p.l. Louis Julien",
    "wof:placetype":"venue"
},
  "geometry": {"coordinates":[4.4252018929,50.9068222046],"type":"Point"}
}