{
  "type": "Feature",
  "properties": {
    "addr:full":"Markt Deinze Oost-Vlaanderen 9800",
    "addr:postcode":"9800",
    "addr:street":"Markt",
    "iso:country":"BE",
    "sg:address":"Markt",
    "sg:city":"Deinze",
    "sg:orig_category":"Musea and historische gebouwen",
    "sg:phone":"+32 9 381 95 10",
    "sg:postcode":"9800",
    "sg:province":"Oost-Vlaanderen",
    "wof:name":"Onze-lieve-vrouwekerk",
    "wof:placetype":"venue"
},
  "geometry": {"coordinates":[3.5270628929,50.9839782715],"type":"Point"}
}