{
  "type": "Feature",
  "properties": {
    "addr:full":"Rue Maurice-toussaint 9 Floreffe Namur 5150",
    "addr:housenumber":"9",
    "addr:postcode":"5150",
    "addr:street":"Rue Maurice-Toussaint",
    "iso:country":"BE",
    "sg:address":"Rue Maurice-toussaint 9",
    "sg:city":"Floreffe",
    "sg:orig_category":"Enseignement maternel and primaire",
    "sg:phone":"+32 81 44 06 30",
    "sg:postcode":"5150",
    "sg:province":"Namur",
    "wof:name":"Ecole Fondamentale Libre",
    "wof:placetype":"venue"
},
  "geometry": {"coordinates":[4.7536969185,50.423992157],"type":"Point"}
}