{
  "type": "Feature",
  "properties": {
    "iso:country":"BE",
    "sg:address":"Rue De Gougnies 59",
    "sg:city":"Mettet",
    "sg:orig_category":"Plaatsen van vloer- and muurbekleding",
    "sg:phone":"+32 71 50 51 87",
    "sg:postcode":"5640",
    "sg:province":"Namur",
    "wof:name":"Danny Boldrin",
    "wof:placetype":"venue"
},
  "geometry": {"coordinates":[4.6578397751,50.3198051453],"type":"Point"}
}