{
  "type": "Feature",
  "properties": {
    "addr:full":"Rue De La Westr\u00c9e 11 Oreye Li\u00e8ge 4360",
    "addr:housenumber":"11",
    "addr:postcode":"4360",
    "addr:street":"Rue De La Westre\u0301E",
    "iso:country":"BE",
    "sg:address":"Rue De La Westr\u00c9e 11",
    "sg:city":"Oreye",
    "sg:orig_category":"Installation de menuiserie m\u00e9tallique. Mat\u00e9riaux de construction Gr",
    "sg:phone":"+32 19 67 70 70",
    "sg:postcode":"4360",
    "sg:province":"Li\u00e8ge",
    "wof:name":"Bonnech\u00c8re",
    "wof:placetype":"venue"
},
  "geometry": {"coordinates":[5.3532981873,50.7285346985],"type":"Point"}
}