{
  "type": "Feature",
  "properties": {
    "iso:country":"BE",
    "sg:address":"Avenue De La Libert\u00e9 48",
    "sg:city":"Colfontaine (wasmes)",
    "sg:classifiers":[
        {
            "category":"Professional",
            "subcategory":"Accounting & Tax Preparation",
            "type":"Services"
        }
    ],
    "sg:phone":"+32 65 76 66 10",
    "sg:postcode":"7340",
    "sg:province":"Hainaut",
    "sg:tags":[
        "accountant"
    ],
    "wof:name":"Leriche M",
    "wof:placetype":"venue"
},
  "geometry": {"coordinates":[3.8514070511,50.4141159058],"type":"Point"}
}