{
  "type": "Feature",
  "properties": {
    "addr:full":"Bevrijdingslaan 194 Meerhout Antwerpen 2450",
    "addr:housenumber":"194",
    "addr:postcode":"2450",
    "addr:street":"Bevrijdingslaan",
    "iso:country":"BE",
    "sg:address":"Bevrijdingslaan 194",
    "sg:city":"Meerhout",
    "sg:orig_category":"Pain, p\u00e2tisseries and confiseries",
    "sg:phone":"+32 14 30 03 64",
    "sg:postcode":"2450",
    "sg:province":"Antwerpen",
    "wof:name":"Bakkerij Van Houtven",
    "wof:placetype":"venue"
},
  "geometry": {"coordinates":[5.0597701073,51.1228408813],"type":"Point"}
}