{
  "type": "Feature",
  "properties": {
    "addr:full":"Dr\u00c8ve Du Tumulus 48 Villers-la-ville Brabant Wallon 1495",
    "addr:housenumber":"48",
    "addr:postcode":"1495",
    "addr:street":"Dre\u0300Ve Du Tumulus",
    "iso:country":"BE",
    "sg:address":"Dr\u00c8ve Du Tumulus 48",
    "sg:city":"Villers-la-ville",
    "sg:orig_category":"Agences d'exp\u00e9dition",
    "sg:phone":"+32 71 87 42 50",
    "sg:postcode":"1495",
    "sg:province":"Brabant Wallon",
    "wof:name":"Insideco",
    "wof:placetype":"venue"
},
  "geometry": {"coordinates":[4.5475502014,50.5780906677],"type":"Point"}
}