{
  "type": "Feature",
  "properties": {
    "iso:country":"BE",
    "sg:address":"Rue Ransy 35",
    "sg:city":"Chaudfontaine (vaux-sous-ch\u00e8vremont)",
    "sg:classifiers":[
        {
            "category":"Insurance",
            "subcategory":"Insurance Agent",
            "type":"Services"
        }
    ],
    "sg:phone":"+32 4 365 41 18",
    "sg:postcode":"4051",
    "sg:province":"Li\u00e8ge",
    "sg:tags":[
        "broker"
    ],
    "wof:name":"Garnier D",
    "wof:placetype":"venue"
},
  "geometry": {"coordinates":[5.6305189133,50.608833313],"type":"Point"}
}