{
  "type": "Feature",
  "properties": {
    "addr:full":"Reebokweg 29ba Overijse Vlaams-Brabant 3090",
    "addr:housenumber":"29ba",
    "addr:postcode":"3090",
    "addr:street":"Reebokweg",
    "iso:country":"BE",
    "sg:address":"Reebokweg 29ba",
    "sg:city":"Overijse",
    "sg:orig_category":"Marktonderzoekbureaus Reclamebureaus",
    "sg:phone":"+32 2 657 32 45",
    "sg:postcode":"3090",
    "sg:province":"Vlaams-Brabant",
    "wof:name":"C. In C.",
    "wof:placetype":"venue"
},
  "geometry": {"coordinates":[4.4940438271,50.7920608521],"type":"Point"}
}