{
  "type": "Feature",
  "properties": {
    "addr:full":"Steenwinkelstraat 49 Schelle Antwerpen 2627",
    "addr:housenumber":"49",
    "addr:postcode":"2627",
    "addr:street":"Steenwinkelstraat",
    "iso:country":"BE",
    "sg:address":"Steenwinkelstraat 49",
    "sg:city":"Schelle",
    "sg:classifiers":[
        {
            "category":"Fast Food",
            "type":"Food & Drink"
        }
    ],
    "sg:phone":"+32 3 887 86 27",
    "sg:postcode":"2627",
    "sg:province":"Antwerpen",
    "sg:tags":[
        "de",
        "restaurant",
        "organisation",
        "\u00c0",
        "catering",
        "emporter",
        "f\u00cates",
        "restaurants"
    ],
    "wof:name":"In De Vos",
    "wof:placetype":"venue"
},
  "geometry": {"coordinates":[4.3418989182,51.1249732971],"type":"Point"}
}