{
  "type": "Feature",
  "properties": {
    "iso:country":"BE",
    "sg:address":"Chauss\u00c9e De Redemont 153",
    "sg:city":"La Louviere",
    "sg:orig_category":"Avocats and conseillers juridiques",
    "sg:phone":"+32 64 21 34 40",
    "sg:postcode":"7100",
    "sg:province":"Hainaut",
    "wof:name":"A. Doclot",
    "wof:placetype":"venue"
},
  "geometry": {"coordinates":[4.2071900368,50.4667510986],"type":"Point"}
}