{
  "type": "Feature",
  "properties": {
    "iso:country":"BE",
    "sg:address":"Kasteeldreef 53",
    "sg:city":"Lubbeek",
    "sg:classifiers":[
        {
            "category":"Insurance",
            "subcategory":"Life Insurance",
            "type":"Services"
        }
    ],
    "sg:phone":"+32 16 26 01 07",
    "sg:postcode":"3210",
    "sg:province":"Vlaams-Brabant",
    "sg:tags":[
        "assurance"
    ],
    "wof:name":"Service Groep Theys",
    "wof:placetype":"venue"
},
  "geometry": {"coordinates":[4.7604827881,50.9041404724],"type":"Point"}
}