{
  "type": "Feature",
  "properties": {
    "addr:full":"Adolf Papeleustraat 25 Wetteren Oost-Vlaanderen 9230",
    "addr:housenumber":"25",
    "addr:postcode":"9230",
    "addr:street":"Papeleustraat",
    "iso:country":"BE",
    "sg:address":"Adolf Papeleustraat 25",
    "sg:city":"Wetteren",
    "sg:classifiers":[
        {
            "category":"Building & Trades",
            "subcategory":"Landscaping Services",
            "type":"Services"
        }
    ],
    "sg:phone":"+32 9 369 51 98",
    "sg:postcode":"9230",
    "sg:province":"Oost-Vlaanderen",
    "sg:tags":[
        "nurseryman"
    ],
    "wof:name":"Duytschaever M",
    "wof:placetype":"venue"
},
  "geometry": {"coordinates":[3.9073600769,50.9900398254],"type":"Point"}
}