{
  "type": "Feature",
  "properties": {
    "iso:country":"BE",
    "sg:address":"Chauss\u00c9e De Tournai 4b2",
    "sg:city":"Tournai",
    "sg:orig_category":"Enseignement secondaire g\u00e9n\u00e9ral",
    "sg:phone":"+32 69 22 41 61",
    "sg:postcode":"7520",
    "sg:province":"Hainaut",
    "wof:name":"Institut St.andr\u00c9",
    "wof:placetype":"venue"
},
  "geometry": {"coordinates":[3.3591609001,50.6304512024],"type":"Point"}
}