{
  "type": "Feature",
  "properties": {
    "addr:full":"Coupure Rechts 864 Gent Oost-Vlaanderen 9000",
    "addr:housenumber":"864",
    "addr:postcode":"9000",
    "addr:street":"Coupure Rechts;Oost-Vlaanderen",
    "iso:country":"BE",
    "sg:address":"Coupure Rechts 864",
    "sg:city":"Gent",
    "sg:classifiers":[
        {
            "category":"Professional",
            "subcategory":"Lawyer & Legal Services",
            "type":"Services"
        }
    ],
    "sg:phone":"+32 9 233 28 10",
    "sg:postcode":"9000",
    "sg:province":"Oost-Vlaanderen",
    "wof:name":"De Winter Mireille",
    "wof:placetype":"venue"
},
  "geometry": {"coordinates":[3.7093551159,51.0558013916],"type":"Point"}
}