{
  "type": "Feature",
  "properties": {
    "addr:full":"Dijk 55 Sint-katelijne-waver (onze-lieve-vrouw-waver) Antwerpen 2861",
    "addr:housenumber":"55",
    "addr:postcode":"2861",
    "addr:street":"Dijk",
    "iso:country":"BE",
    "sg:address":"Dijk 55",
    "sg:city":"Sint-katelijne-waver (onze-lieve-vrouw-waver)",
    "sg:classifiers":[
        {
            "category":"Health Services",
            "subcategory":"Dentist",
            "type":"Services"
        }
    ],
    "sg:phone":"+32 15 75 47 09",
    "sg:postcode":"2861",
    "sg:province":"Antwerpen",
    "wof:name":"Sprengers Minne",
    "wof:placetype":"venue"
},
  "geometry": {"coordinates":[4.5742349625,51.0567474365],"type":"Point"}
}