{
  "type": "Feature",
  "properties": {
    "iso:country":"BE",
    "sg:address":"Gentsestraat 60b1",
    "sg:city":"Aalst",
    "sg:orig_category":"Avocats and conseillers juridiques",
    "sg:phone":"+32 53 78 00 20",
    "sg:postcode":"9300",
    "sg:province":"Oost-Vlaanderen",
    "wof:name":"Lutgart Gillis",
    "wof:placetype":"venue"
},
  "geometry": {"coordinates":[4.0299921036,50.9374771118],"type":"Point"}
}