{
  "type": "Feature",
  "properties": {
    "addr:full":"Rue De Hesbaye 209 Li\u00c8ge Li\u00e8ge 4000",
    "addr:housenumber":"209",
    "addr:postcode":"4000",
    "addr:street":"Rue De Hesbaye",
    "iso:country":"BE",
    "sg:address":"Rue De Hesbaye 209",
    "sg:city":"Li\u00c8ge",
    "sg:orig_category":"Textiel",
    "sg:phone":"+32 4 226 39 82",
    "sg:postcode":"4000",
    "sg:province":"Li\u00e8ge",
    "wof:name":"Soner Erdogan",
    "wof:placetype":"venue"
},
  "geometry": {"coordinates":[5.549200058,50.6499252319],"type":"Point"}
}