{
  "type": "Feature",
  "properties": {
    "addr:full":"Antwerpsestweg 56 Aartselaar Antwerpen 2630",
    "addr:housenumber":"56",
    "addr:postcode":"2630",
    "addr:street":"Antwerpsestweg",
    "iso:country":"BE",
    "sg:address":"Antwerpsestweg 56",
    "sg:city":"Aartselaar",
    "sg:classifiers":[
        {
            "category":"Arena",
            "subcategory":"Sports Club",
            "type":"Entertainment"
        }
    ],
    "sg:phone":"+32 3 887 45 62",
    "sg:postcode":"2630",
    "sg:province":"Antwerpen",
    "sg:tags":[
        "de"
    ],
    "wof:name":"World Kun Tai",
    "wof:placetype":"venue"
},
  "geometry": {"coordinates":[4.3797230721,51.1414604187],"type":"Point"}
}