{
  "type": "Feature",
  "properties": {
    "iso:country":"BE",
    "sg:address":"Rue Provinciale 470",
    "sg:city":"Juprelle (fexhe-slins)",
    "sg:classifiers":[
        {
            "category":"Professional",
            "subcategory":"Testing Lab",
            "type":"Services"
        }
    ],
    "sg:phone":"+32 4 278 50 05",
    "sg:postcode":"4458",
    "sg:province":"Li\u00e8ge",
    "sg:tags":[
        "chemist"
    ],
    "wof:name":"Pharmacie De Fexhe-slins",
    "wof:placetype":"venue"
},
  "geometry": {"coordinates":[5.5669198036,50.7078514099],"type":"Point"}
}