{
  "type": "Feature",
  "properties": {
    "iso:country":"BE",
    "sg:address":"Kwakkelstraat 49",
    "sg:city":"Turnhout",
    "sg:classifiers":[
        {
            "category":"Home & Garden",
            "subcategory":"Garden Supply",
            "type":"Retail Goods"
        }
    ],
    "sg:phone":"+32 14 42 35 74",
    "sg:postcode":"2300",
    "sg:province":"Antwerpen",
    "sg:tags":[
        "equipment",
        "playground"
    ],
    "wof:name":"Portael Fr",
    "wof:placetype":"venue"
},
  "geometry": {"coordinates":[4.9537339211,51.3213424683],"type":"Point"}
}