{
  "type": "Feature",
  "properties": {
    "addr:full":"Handelslei 120 Zoersel Antwerpen 2980",
    "addr:housenumber":"120",
    "addr:postcode":"2980",
    "iso:country":"BE",
    "sg:address":"Handelslei 120",
    "sg:city":"Zoersel",
    "sg:classifiers":[
        {
            "category":"Cinema",
            "subcategory":"Movie Rental",
            "type":"Entertainment"
        }
    ],
    "sg:phone":"+32 3 385 11 49",
    "sg:postcode":"2980",
    "sg:province":"Antwerpen",
    "sg:tags":[
        "de",
        "cassette",
        "location",
        "vid\u00e9o",
        "audio"
    ],
    "wof:name":"Videotheek Kozi",
    "wof:placetype":"venue"
},
  "geometry": {"coordinates":[4.6484470367,51.2730941772],"type":"Point"}
}