{
  "type": "Feature",
  "properties": {
    "iso:country":"BE",
    "sg:address":"Rue Englebert Lescrenier 20",
    "sg:city":"Awans",
    "sg:orig_category":"Fruitteelt",
    "sg:phone":"+32 4 257 68 62",
    "sg:postcode":"4340",
    "sg:province":"Li\u00e8ge",
    "wof:name":"Philippe Marc",
    "wof:placetype":"venue"
},
  "geometry": {"coordinates":[5.4697461128,50.7087631226],"type":"Point"}
}