{
  "type": "Feature",
  "properties": {
    "iso:country":"BE",
    "sg:address":"Stationsstraat 101",
    "sg:city":"Oostrozebeke",
    "sg:orig_category":"Instituts de beaut\u00e9",
    "sg:phone":"+32 56 66 50 13",
    "sg:postcode":"8780",
    "sg:province":"West-Vlaanderen",
    "wof:name":"A. Declerck",
    "wof:placetype":"venue"
},
  "geometry": {"coordinates":[3.3326408863,50.9152603149],"type":"Point"}
}