{
  "type": "Feature",
  "properties": {
    "iso:country":"BE",
    "sg:address":"Rue Andr\u00e9 Dumont 5",
    "sg:city":"Li\u00e8ge 1",
    "sg:classifiers":[
        {
            "category":"Shopping",
            "subcategory":"Clothing, Apparel, & Fashions",
            "type":"Retail Goods"
        }
    ],
    "sg:phone":"+32 4 222 23 81",
    "sg:postcode":"4000",
    "sg:province":"Li\u00e8ge",
    "sg:tags":[
        "lady",
        "clothing",
        "-"
    ],
    "wof:name":"Marie-jeanne",
    "wof:placetype":"venue"
},
  "geometry": {"coordinates":[5.57498312,50.6387023926],"type":"Point"}
}