{
  "type": "Feature",
  "properties": {
    "addr:full":"Langenberg 30 Hoogstraten (wortel) Antwerpen 2323",
    "addr:housenumber":"30",
    "addr:postcode":"2323",
    "addr:street":"Langenberg",
    "iso:country":"BE",
    "sg:address":"Langenberg 30",
    "sg:city":"Hoogstraten (wortel)",
    "sg:classifiers":[
        {
            "category":"Farming",
            "subcategory":"Livestock Farm",
            "type":"Manufacturing & Wholesale Goods"
        }
    ],
    "sg:phone":"+32 3 314 55 15",
    "sg:postcode":"2323",
    "sg:province":"Antwerpen",
    "sg:tags":[
        "buyer"
    ],
    "wof:name":"De Meester A",
    "wof:placetype":"venue"
},
  "geometry": {"coordinates":[4.7957539558,51.3966712952],"type":"Point"}
}