{
  "type": "Feature",
  "properties": {
    "iso:country":"BE",
    "sg:address":"Baron Van Ertbornstraat 6b",
    "sg:city":"Aartselaar",
    "sg:orig_category":"Plomberie, chauffage and installations sanitaires",
    "sg:phone":"+32 3 887 12 65",
    "sg:postcode":"2630",
    "sg:province":"Antwerpen",
    "wof:name":"Robert Daisomont",
    "wof:placetype":"venue"
},
  "geometry": {"coordinates":[4.3880648613,51.1346168518],"type":"Point"}
}