{
  "type": "Feature",
  "properties": {
    "iso:country":"BE",
    "sg:address":"Hofeinde 10",
    "sg:city":"Merksplas",
    "sg:orig_category":"Traitement de donn\u00e9es",
    "sg:phone":"+32 14 63 90 90",
    "sg:postcode":"2330",
    "sg:province":"Antwerpen",
    "wof:name":"Bm Computeradvies",
    "wof:placetype":"venue"
},
  "geometry": {"coordinates":[4.8637480736,51.363571167],"type":"Point"}
}