{
  "type": "Feature",
  "properties": {
    "addr:full":"Lendedreef 51 Anzegem West-Vlaanderen 8570",
    "addr:housenumber":"51",
    "addr:postcode":"8570",
    "addr:street":"Lendedreef",
    "iso:country":"BE",
    "sg:address":"Lendedreef 51",
    "sg:city":"Anzegem",
    "sg:orig_category":"Elektrische installaties voor woningen",
    "sg:phone":"+32 56 77 16 32",
    "sg:postcode":"8570",
    "sg:province":"West-Vlaanderen",
    "wof:name":"Frank Samyn",
    "wof:placetype":"venue"
},
  "geometry": {"coordinates":[3.3891570568,50.836856842],"type":"Point"}
}