{
  "type": "Feature",
  "properties": {
    "iso:country":"BE",
    "sg:address":"Dosweg 6",
    "sg:city":"Nevele",
    "sg:orig_category":"Groenten and fruit Gh",
    "sg:phone":"+32 9 371 53 84",
    "sg:postcode":"9850",
    "sg:province":"Oost-Vlaanderen",
    "wof:name":"Lucien Vleurick",
    "wof:placetype":"venue"
},
  "geometry": {"coordinates":[3.5594270229,51.0761108398],"type":"Point"}
}