{
  "type": "Feature",
  "properties": {
    "addr:full":"Voie Di M\u00c8sse 8 Anthisnes Li\u00e8ge 4163",
    "addr:housenumber":"8",
    "addr:postcode":"4163",
    "addr:street":"Voie Di Me\u0300Sse",
    "iso:country":"BE",
    "sg:address":"Voie Di M\u00c8sse 8",
    "sg:city":"Anthisnes",
    "sg:orig_category":"Verhuur cateringmateriaal and evenementuitrusting Winkelinrichting and handelsuitrusting Gh",
    "sg:phone":"+32 4 383 78 80",
    "sg:postcode":"4163",
    "sg:province":"Li\u00e8ge",
    "wof:name":"Fe. Mobitentes",
    "wof:placetype":"venue"
},
  "geometry": {"coordinates":[5.473441124,50.4986038208],"type":"Point"}
}