{
  "type": "Feature",
  "properties": {
    "addr:full":"Av De L'industrie 20 Braine-l'alleud Brabant Wallon 1420",
    "addr:housenumber":"20",
    "addr:postcode":"1420",
    "addr:street":"Av De L'Industrie",
    "iso:country":"BE",
    "sg:address":"Av De L'industrie 20",
    "sg:city":"Braine-l'alleud",
    "sg:classifiers":[
        {
            "category":"Food & Beverages",
            "subcategory":"Groceries & Convenience Stores",
            "type":"Retail Goods"
        }
    ],
    "sg:phone":"+32 2 384 60 77",
    "sg:postcode":"1420",
    "sg:province":"Brabant Wallon",
    "sg:tags":[
        "product",
        "related"
    ],
    "wof:name":"International Spice & Food Import Sa",
    "wof:placetype":"venue"
},
  "geometry": {"coordinates":[15.2195005417,40.783657074],"type":"Point"}
}