{
  "type": "Feature",
  "properties": {
    "iso:country":"BE",
    "sg:address":"Tongersesteenweg 109",
    "sg:city":"Sint-truiden",
    "sg:classifiers":[
        {
            "category":"Professional",
            "subcategory":"Engineering",
            "type":"Services"
        }
    ],
    "sg:phone":"+32 11 69 10 20",
    "sg:postcode":"3800",
    "sg:province":"Limburg",
    "sg:tags":[
        "lighting",
        "-"
    ],
    "wof:name":"Lumidee Verlichting Bvba",
    "wof:placetype":"venue"
},
  "geometry": {"coordinates":[5.1981282234,50.8111495972],"type":"Point"}
}