{
  "type": "Feature",
  "properties": {
    "addr:full":"Avenue Sainte-th\u00e9r\u00e8se 6 Rhode-saint-gen\u00e8se Vlaams-Brabant 1640",
    "addr:housenumber":"6",
    "addr:postcode":"1640",
    "addr:street":"Avenue Sainte-The\u0301Re\u0300Se",
    "iso:country":"BE",
    "sg:address":"Avenue Sainte-th\u00e9r\u00e8se 6",
    "sg:city":"Rhode-saint-gen\u00e8se",
    "sg:classifiers":[
        {
            "category":"Professional",
            "subcategory":"Management & Consulting",
            "type":"Services"
        }
    ],
    "sg:phone":"+32 2 358 53 20",
    "sg:postcode":"1640",
    "sg:province":"Vlaams-Brabant",
    "sg:tags":[
        "-",
        "processing",
        "data",
        "consultant"
    ],
    "wof:name":"Micrology Sprl",
    "wof:placetype":"venue"
},
  "geometry": {"coordinates":[4.3904547691,50.7393608093],"type":"Point"}
}