{
  "type": "Feature",
  "properties": {
    "iso:country":"BE",
    "sg:address":"Loofblommestraat 26",
    "sg:city":"Gent",
    "sg:orig_category":"Banques and organismes de cr\u00e9dit",
    "sg:phone":"+32 9 221 35 99",
    "sg:postcode":"9051",
    "sg:province":"Oost-Vlaanderen",
    "wof:name":"Kbc",
    "wof:placetype":"venue"
},
  "geometry": {"coordinates":[3.6688320637,51.0225067139],"type":"Point"}
}