{
  "type": "Feature",
  "properties": {
    "iso:country":"BE",
    "sg:address":"Grimbergsesteenweg 101",
    "sg:city":"Vilvoorde",
    "sg:classifiers":[
        {
            "category":"Fast Food",
            "type":"Food & Drink"
        }
    ],
    "sg:phone":"+32 2 253 61 96",
    "sg:postcode":"1800",
    "sg:province":"Vlaams-Brabant",
    "sg:tags":[
        "fried",
        "stand",
        "potato"
    ],
    "wof:name":"Therese",
    "wof:placetype":"venue"
},
  "geometry": {"coordinates":[4.4112811089,50.9250297546],"type":"Point"}
}