{
  "type": "Feature",
  "properties": {
    "iso:country":"BE",
    "sg:address":"Flierendries 12",
    "sg:city":"Ninove",
    "sg:orig_category":"M\u00e9decins and sp\u00e9cialistes",
    "sg:phone":"+32 54 32 07 46",
    "sg:postcode":"9400",
    "sg:province":"Oost-Vlaanderen",
    "wof:name":"Jan Raes",
    "wof:placetype":"venue"
},
  "geometry": {"coordinates":[3.9929740429,50.8086776733],"type":"Point"}
}