{
  "type": "Feature",
  "properties": {
    "addr:full":"Kruiskenslei 6 Boom Antwerpen 2850",
    "addr:housenumber":"6",
    "addr:postcode":"2850",
    "addr:street":"Kruiskenslei",
    "iso:country":"BE",
    "sg:address":"Kruiskenslei 6",
    "sg:city":"Boom",
    "sg:orig_category":"Enseignement maternel and primaire",
    "sg:phone":"+32 3 844 20 22",
    "sg:postcode":"2850",
    "sg:province":"Antwerpen",
    "wof:name":"Basisschool",
    "wof:placetype":"venue"
},
  "geometry": {"coordinates":[4.3652029037,51.1008071899],"type":"Point"}
}