{
  "type": "Feature",
  "properties": {
    "iso:country":"BE",
    "sg:address":"Alice Nahonlei 45",
    "sg:city":"Schoten",
    "sg:classifiers":[
        {
            "category":"Building & Trades",
            "subcategory":"Landscaping Services",
            "type":"Services"
        }
    ],
    "sg:phone":"+32 3 685 00 79",
    "sg:postcode":"2900",
    "sg:province":"Antwerpen",
    "sg:tags":[
        "gardening",
        "garden",
        "maintenance"
    ],
    "wof:name":"De Open Ruimte",
    "wof:placetype":"venue"
},
  "geometry": {"coordinates":[4.537293911,51.2620315552],"type":"Point"}
}