{
  "type": "Feature",
  "properties": {
    "iso:country":"BE",
    "sg:address":"Industriepark 6",
    "sg:city":"Diest (webbekom)",
    "sg:classifiers":[
        {
            "category":"Restaurant",
            "type":"Food & Drink"
        }
    ],
    "sg:phone":"+32 13 31 27 14",
    "sg:postcode":"3290",
    "sg:province":"Vlaams-Brabant",
    "sg:tags":[
        "industrial",
        "kitchen",
        "catering"
    ],
    "wof:name":"Buvens Nv",
    "wof:placetype":"venue"
},
  "geometry": {"coordinates":[5.0731592178,50.9659233093],"type":"Point"}
}