{
  "type": "Feature",
  "properties": {
    "addr:full":"Grand'place 17 Chievres Hainaut 7950",
    "addr:housenumber":"17",
    "addr:postcode":"7950",
    "addr:street":"Grand'Place;Hainaut",
    "iso:country":"BE",
    "sg:address":"Grand'place 17",
    "sg:city":"Chievres",
    "sg:orig_category":"Rusthuizen and serviceflats",
    "sg:phone":"+32 68 65 83 72",
    "sg:postcode":"7950",
    "sg:province":"Hainaut",
    "wof:name":"R\u00c9sidence Comte D'egmont",
    "wof:placetype":"venue"
},
  "geometry": {"coordinates":[3.8079679012,50.587223053],"type":"Point"}
}