{
  "type": "Feature",
  "properties": {
    "addr:full":"Bld Emile Bockstael 122 Brussel/bruxelles Bruxelles-Capitale 1020",
    "addr:housenumber":"122",
    "addr:postcode":"1020",
    "addr:street":"Bld Emile Bockstael;/",
    "iso:country":"BE",
    "sg:address":"Bld Emile Bockstael 122",
    "sg:city":"Brussel/bruxelles",
    "sg:orig_category":"Produits pharmaceutiques Fab",
    "sg:phone":"+32 2 422 27 11",
    "sg:postcode":"1020",
    "sg:province":"Bruxelles-Capitale",
    "wof:name":"Solvay-pharma & Cie",
    "wof:placetype":"venue"
},
  "geometry": {"coordinates":[4.3453741074,50.8729362488],"type":"Point"}
}