{
  "type": "Feature",
  "properties": {
    "iso:country":"BE",
    "sg:address":"Rue De L'alliance 83",
    "sg:city":"Tubize (clabecq)",
    "sg:classifiers":[
        {
            "category":"Real Estate",
            "subcategory":"Architect",
            "type":"Services"
        }
    ],
    "sg:phone":"+32 2 512 93 21",
    "sg:postcode":"1480",
    "sg:province":"Brabant Wallon",
    "wof:name":"Deghorain A",
    "wof:placetype":"venue"
},
  "geometry": {"coordinates":[4.2277421951,50.679485321],"type":"Point"}
}