{
  "type": "Feature",
  "properties": {
    "addr:full":"Della Faillestraat 15 Brasschaat Antwerpen 2930",
    "addr:housenumber":"15",
    "addr:postcode":"2930",
    "addr:street":"Della Faillestraat",
    "iso:country":"BE",
    "sg:address":"Della Faillestraat 15",
    "sg:city":"Brasschaat",
    "sg:orig_category":"Imprimeries and copyshops",
    "sg:phone":"+32 3 663 09 36",
    "sg:postcode":"2930",
    "sg:province":"Antwerpen",
    "wof:name":"Marc Van Buggenhout",
    "wof:placetype":"venue"
},
  "geometry": {"coordinates":[4.520816803,51.3219795227],"type":"Point"}
}