{
  "type": "Feature",
  "properties": {
    "iso:country":"BE",
    "sg:address":"Rue Voli\u00c8re 47",
    "sg:city":"Li\u00c8ge",
    "sg:orig_category":"Salles de spectacles",
    "sg:phone":"+32 4 222 42 65",
    "sg:postcode":"4000",
    "sg:province":"Li\u00e8ge",
    "wof:name":"Th\u00c9\u00c2tre Zoo",
    "wof:placetype":"venue"
},
  "geometry": {"coordinates":[5.5721621513,50.6479148865],"type":"Point"}
}