{
  "type": "Feature",
  "properties": {
    "addr:full":"Chateau 1 Ciney Namur 5590",
    "addr:housenumber":"1",
    "addr:postcode":"5590",
    "addr:street":"Chateau",
    "iso:country":"BE",
    "sg:address":"Chateau 1",
    "sg:city":"Ciney",
    "sg:orig_category":"Villages de vacances. Maisons de vacances. Luna-parks and parcs de r\u00e9cr\u00e9ation",
    "sg:phone":"+32 83 68 72 11",
    "sg:postcode":"5590",
    "sg:province":"Namur",
    "wof:name":"Domaine Provincial Val\u00c9ry Cousin",
    "wof:placetype":"venue"
},
  "geometry": {"coordinates":[5.1022520065,50.297088623],"type":"Point"}
}