{
  "type": "Feature",
  "properties": {
    "iso:country":"BE",
    "sg:address":"Kloosterstraat 40b3",
    "sg:city":"Peer",
    "sg:orig_category":"Instellingen voor probleemkinderen Kindertehuizen",
    "sg:phone":"+32 11 63 49 31",
    "sg:postcode":"3990",
    "sg:province":"Limburg",
    "wof:name":"De Hummeltjes",
    "wof:placetype":"venue"
},
  "geometry": {"coordinates":[5.4519019127,51.1320915222],"type":"Point"}
}