{
  "type": "Feature",
  "properties": {
    "addr:full":"Rue Nouvelle Perc\u00c9e 13 Remicourt Li\u00e8ge 4350",
    "addr:housenumber":"13",
    "addr:postcode":"4350",
    "addr:street":"Rue Nouvelle Perce\u0301E",
    "iso:country":"BE",
    "sg:address":"Rue Nouvelle Perc\u00c9e 13",
    "sg:city":"Remicourt",
    "sg:orig_category":"Vertalers and tolken",
    "sg:phone":"+32 19 54 57 72",
    "sg:postcode":"4350",
    "sg:province":"Li\u00e8ge",
    "wof:name":"Midr\u00c9-wertz C. Cbtip/bkvtf",
    "wof:placetype":"venue"
},
  "geometry": {"coordinates":[5.3219561577,50.6779289246],"type":"Point"}
}