{
  "type": "Feature",
  "properties": {
    "addr:full":"Grand Rue 47 Comines-warneton (comines) Hainaut 7780",
    "addr:housenumber":"47",
    "addr:postcode":"7780",
    "addr:street":"Grand Rue",
    "iso:country":"BE",
    "sg:address":"Grand Rue 47",
    "sg:city":"Comines-warneton (comines)",
    "sg:classifiers":[
        {
            "category":"Personal",
            "subcategory":"Beauty Salon",
            "type":"Services"
        }
    ],
    "sg:phone":"+32 56 55 66 12",
    "sg:postcode":"7780",
    "sg:province":"Hainaut",
    "sg:tags":[
        "lady",
        "-",
        "hairdressing"
    ],
    "wof:name":"Fabienne",
    "wof:placetype":"venue"
},
  "geometry": {"coordinates":[3.0028290749,50.7929916382],"type":"Point"}
}