{
  "type": "Feature",
  "properties": {
    "iso:country":"BE",
    "sg:address":"Quai Aux Briques 54",
    "sg:city":"Bruxelles",
    "sg:classifiers":[
        {
            "category":"Health Services",
            "subcategory":"Health Practitioner",
            "type":"Services"
        }
    ],
    "sg:phone":"+32 2 513 52 52",
    "sg:postcode":"1000",
    "sg:province":"Bruxelles-Capitale",
    "sg:tags":[
        "physiotherapist"
    ],
    "wof:name":"Segers J",
    "wof:placetype":"venue"
},
  "geometry": {"coordinates":[4.3471798897,50.852355957],"type":"Point"}
}