{
  "type": "Feature",
  "properties": {
    "addr:full":"Industrieterrein Kolmen 1308 Alken Limburg 3570",
    "addr:housenumber":"1308",
    "addr:postcode":"3570",
    "addr:street":"Industrieterrein Kolmen",
    "iso:country":"BE",
    "sg:address":"Industrieterrein Kolmen 1308",
    "sg:city":"Alken",
    "sg:orig_category":"Autokeuringen",
    "sg:phone":"+32 11 31 39 52",
    "sg:postcode":"3570",
    "sg:province":"Limburg",
    "wof:name":"Autokeuring",
    "wof:placetype":"venue"
},
  "geometry": {"coordinates":[5.2982168198,50.8869247437],"type":"Point"}
}