{
  "type": "Feature",
  "properties": {
    "iso:country":"BE",
    "sg:address":"Tongersesteenweg 301",
    "sg:city":"Sint-truiden",
    "sg:orig_category":"Bois Gr. Quincailleries. Articles de jardin",
    "sg:phone":"+32 11 68 47 66",
    "sg:postcode":"3800",
    "sg:province":"Limburg",
    "wof:name":"Gregoir Gentiel",
    "wof:placetype":"venue"
},
  "geometry": {"coordinates":[5.2143378258,50.8103065491],"type":"Point"}
}