{
  "type": "Feature",
  "properties": {
    "addr:full":"Grand Rue 25 Morlanwelz (morlanwelz-mariemont) Hainaut 7140",
    "addr:housenumber":"25",
    "addr:postcode":"7140",
    "addr:street":"Grand Rue",
    "iso:country":"BE",
    "sg:address":"Grand Rue 25",
    "sg:city":"Morlanwelz (morlanwelz-mariemont)",
    "sg:classifiers":[
        {
            "category":"Shopping",
            "subcategory":"Music",
            "type":"Retail Goods"
        }
    ],
    "sg:phone":"+32 64 45 93 25",
    "sg:postcode":"7140",
    "sg:province":"Hainaut",
    "sg:tags":[
        "-",
        "cd's",
        "recorded",
        "cassette"
    ],
    "wof:name":"Music Box",
    "wof:placetype":"venue"
},
  "geometry": {"coordinates":[4.2445850372,50.455291748],"type":"Point"}
}