{
  "type": "Feature",
  "properties": {
    "addr:full":"Rue Des Fripiers 23 Brussel/bruxelles Bruxelles-Capitale 1000",
    "addr:housenumber":"23",
    "addr:postcode":"1000",
    "addr:street":"Rue Des Fripiers;/",
    "iso:country":"BE",
    "sg:address":"Rue Des Fripiers 23",
    "sg:city":"Brussel/bruxelles",
    "sg:orig_category":"Chaussures. Maroquinerie and articles de voyage",
    "sg:phone":"+32 2 217 92 44",
    "sg:postcode":"1000",
    "sg:province":"Bruxelles-Capitale",
    "wof:name":"Lautrec Chaussures",
    "wof:placetype":"venue"
},
  "geometry": {"coordinates":[4.3524861336,50.8488235474],"type":"Point"}
}