{
  "type": "Feature",
  "properties": {
    "iso:country":"BE",
    "sg:address":"Rue G-j Leclercq 10",
    "sg:city":"Oudergem",
    "sg:orig_category":"Agences d'exp\u00e9dition",
    "sg:phone":"+32 2 675 44 60",
    "sg:postcode":"1160",
    "sg:province":"Bruxelles-Capitale",
    "wof:name":"Hethimex",
    "wof:placetype":"venue"
},
  "geometry": {"coordinates":[4.4087381363,50.8222961426],"type":"Point"}
}