{
  "type": "Feature",
  "properties": {
    "addr:full":"Noordzandstraat 52-56 Brugge West-Vlaanderen 8000",
    "addr:postcode":"52-56;8000",
    "addr:street":"Noordzandstraat",
    "iso:country":"BE",
    "sg:address":"Noordzandstraat 52-56",
    "sg:city":"Brugge",
    "sg:classifiers":[
        {
            "category":"Shopping",
            "subcategory":"Computers & Home Electronics",
            "type":"Retail Goods"
        }
    ],
    "sg:phone":"+32 50 44 40 10",
    "sg:postcode":"8000",
    "sg:province":"West-Vlaanderen",
    "sg:tags":[
        "-",
        "television",
        "radio"
    ],
    "wof:name":"Tuyttens Nv",
    "wof:placetype":"venue"
},
  "geometry": {"coordinates":[3.2195799351,51.2070922852],"type":"Point"}
}