{
  "type": "Feature",
  "properties": {
    "addr:full":"Rue Auguste Laloux 2 Yvoir (dorinne) Namur 5530",
    "addr:housenumber":"2",
    "addr:postcode":"5530",
    "addr:street":"Rue Auguste Laloux",
    "iso:country":"BE",
    "sg:address":"Rue Auguste Laloux 2",
    "sg:city":"Yvoir (dorinne)",
    "sg:classifiers":[
        {
            "category":"Bars & Pubs",
            "type":"Food & Drink"
        }
    ],
    "sg:phone":"+32 83 69 95 79",
    "sg:postcode":"5530",
    "sg:province":"Namur",
    "wof:name":"As De Pique",
    "wof:placetype":"venue"
},
  "geometry": {"coordinates":[4.9731001854,50.3176269531],"type":"Point"}
}