{
  "type": "Feature",
  "properties": {
    "iso:country":"BE",
    "sg:address":"Chauss\u00c9e De Waterloo 472-476",
    "sg:city":"Elsene",
    "sg:orig_category":"D\u00e9m\u00e9nagements",
    "sg:phone":"+32 2 538 41 62",
    "sg:postcode":"1050",
    "sg:province":"Bruxelles-Capitale",
    "wof:name":"Vermeulen",
    "wof:placetype":"venue"
},
  "geometry": {"coordinates":[4.3577480316,50.8210983276],"type":"Point"}
}