{
  "type": "Feature",
  "properties": {
    "addr:full":"Rue Saint-pie 24 Binche Hainaut 7134",
    "addr:housenumber":"24",
    "addr:postcode":"7134",
    "addr:street":"Rue Saint-Pie",
    "iso:country":"BE",
    "sg:address":"Rue Saint-pie 24",
    "sg:city":"Binche",
    "sg:classifiers":[
        {
            "category":"Arena",
            "subcategory":"Sports Club",
            "type":"Entertainment"
        }
    ],
    "sg:phone":"+32 64 33 29 09",
    "sg:postcode":"7134",
    "sg:province":"Hainaut",
    "sg:tags":[
        "de"
    ],
    "wof:name":"Maison Colombo. Binchoise",
    "wof:placetype":"venue"
},
  "geometry": {"coordinates":[4.1855230331,50.4123802185],"type":"Point"}
}