{
  "type": "Feature",
  "properties": {
    "iso:country":"BE",
    "sg:address":"Rue Pr\u00c9-des-velus 65",
    "sg:city":"Viroinval",
    "sg:orig_category":"HUISBRANDOLIE",
    "sg:phone":"+32 60 39 93 74",
    "sg:postcode":"5670",
    "sg:province":"Namur",
    "wof:name":"Joseph Dussenne",
    "wof:placetype":"venue"
},
  "geometry": {"coordinates":[4.6079158783,50.0667533875],"type":"Point"}
}