{
  "type": "Feature",
  "properties": {
    "addr:full":"Herfstlei 11 Edegem Antwerpen 2650",
    "addr:housenumber":"11",
    "addr:postcode":"2650",
    "addr:street":"Herfstlei",
    "iso:country":"BE",
    "sg:address":"Herfstlei 11",
    "sg:city":"Edegem",
    "sg:classifiers":[
        {
            "category":"Real Estate",
            "subcategory":"Architect",
            "type":"Services"
        }
    ],
    "sg:phone":"+32 3 458 44 75",
    "sg:postcode":"2650",
    "sg:province":"Antwerpen",
    "wof:name":"Landtmeters L",
    "wof:placetype":"venue"
},
  "geometry": {"coordinates":[4.4520468712,51.1553649902],"type":"Point"}
}