{
  "type": "Feature",
  "properties": {
    "iso:country":"BE",
    "sg:address":"Mandellaan 22b",
    "sg:city":"Roeselare",
    "sg:classifiers":[
        {
            "category":"Education",
            "subcategory":"Dance Studio",
            "type":"Public Place"
        }
    ],
    "sg:phone":"+32 51 20 18 90",
    "sg:postcode":"8800",
    "sg:province":"West-Vlaanderen",
    "sg:tags":[
        "school",
        "dancing"
    ],
    "wof:name":"Induce Vzw",
    "wof:placetype":"venue"
},
  "geometry": {"coordinates":[3.1613259315,50.9375152588],"type":"Point"}
}