{
  "type": "Feature",
  "properties": {
    "addr:full":"'s Gravenstraat 48 Nazareth Oost-Vlaanderen 9810",
    "addr:housenumber":"48",
    "addr:postcode":"9810",
    "addr:street":"' S Gravenstraat",
    "iso:country":"BE",
    "sg:address":"'s Gravenstraat 48",
    "sg:city":"Nazareth",
    "sg:classifiers":[
        {
            "category":"Health Services",
            "subcategory":"Doctor",
            "type":"Services"
        }
    ],
    "sg:phone":"+32 9 385 81 56",
    "sg:postcode":"9810",
    "sg:province":"Oost-Vlaanderen",
    "sg:tags":[
        "medicinephysicians",
        "surgeon"
    ],
    "wof:name":"Deslypere J-p",
    "wof:placetype":"venue"
},
  "geometry": {"coordinates":[3.595277071,50.9607810974],"type":"Point"}
}