{
  "type": "Feature",
  "properties": {
    "iso:country":"BE",
    "sg:address":"Ringlaan 42",
    "sg:city":"Zandhoven",
    "sg:orig_category":"Diverse bouwafwerking and reiniging Plaatsen van vloer- and muurbekleding Schilders",
    "sg:phone":"+32 3 484 32 31",
    "sg:postcode":"2240",
    "sg:province":"Antwerpen",
    "wof:name":"Schilderwerken Bosselaers",
    "wof:placetype":"venue"
},
  "geometry": {"coordinates":[4.6591048241,51.2102966309],"type":"Point"}
}