{
  "type": "Feature",
  "properties": {
    "addr:full":"Lauweplaats 3 Box 1 Menen (lauwe) West-Vlaanderen 8930",
    "addr:housenumber":"3;1",
    "addr:postcode":"8930",
    "addr:street":"Lauweplaats;Box",
    "iso:country":"BE",
    "sg:address":"Lauweplaats 3 Box 1",
    "sg:city":"Menen (lauwe)",
    "sg:classifiers":[
        {
            "category":"Insurance",
            "subcategory":"Insurance Agent",
            "type":"Services"
        }
    ],
    "sg:phone":"+32 56 42 51 60",
    "sg:postcode":"8930",
    "sg:province":"West-Vlaanderen",
    "sg:tags":[
        "broker"
    ],
    "wof:name":"Haghedoorn Bvba",
    "wof:placetype":"venue"
},
  "geometry": {"coordinates":[3.1637148857,50.7851371765],"type":"Point"}
}