{
  "type": "Feature",
  "properties": {
    "addr:full":"Bosstraat 35 Zottegem (leeuwergem) Oost-Vlaanderen 9620",
    "addr:housenumber":"35",
    "addr:postcode":"9620",
    "addr:street":"Bosstraat",
    "iso:country":"BE",
    "sg:address":"Bosstraat 35",
    "sg:city":"Zottegem (leeuwergem)",
    "sg:classifiers":[
        {
            "category":"Personal",
            "subcategory":"Beauty Salon",
            "type":"Services"
        }
    ],
    "sg:phone":"+32 9 360 32 12",
    "sg:postcode":"9620",
    "sg:province":"Oost-Vlaanderen",
    "sg:tags":[
        "lady",
        "-",
        "hairdressing"
    ],
    "wof:name":"Capelli",
    "wof:placetype":"venue"
},
  "geometry": {"coordinates":[3.8261620998,50.8853416443],"type":"Point"}
}