{
  "type": "Feature",
  "properties": {
    "addr:full":"Carnotstraat 9 Antwerpen Antwerpen 2060",
    "addr:housenumber":"9",
    "addr:postcode":"2060",
    "addr:street":"Carnotstraat",
    "iso:country":"BE",
    "sg:address":"Carnotstraat 9",
    "sg:city":"Antwerpen",
    "sg:orig_category":"Geschenken and souvenirs Speelgoed Verlichting and huishoudartikelen",
    "sg:phone":"+32 3 225 21 99",
    "sg:postcode":"2060",
    "sg:province":"Antwerpen",
    "wof:name":"Blokker",
    "wof:placetype":"venue"
},
  "geometry": {"coordinates":[4.422109127,51.2190361023],"type":"Point"}
}