{
  "type": "Feature",
  "properties": {
    "iso:country":"BE",
    "sg:address":"Albert I Laan 267",
    "sg:city":"Nieuwpoort",
    "sg:classifiers":[
        {
            "category":"Banks & Credit Unions",
            "subcategory":"Investment Brokerage",
            "type":"Services"
        }
    ],
    "sg:phone":"+32 58 23 80 58",
    "sg:postcode":"8620",
    "sg:province":"West-Vlaanderen",
    "sg:tags":[
        "jean",
        "casual",
        "wear"
    ],
    "wof:name":"Birgit Fashion Bvba",
    "wof:placetype":"venue"
},
  "geometry": {"coordinates":[2.7116179466,51.1463241577],"type":"Point"}
}