{
  "type": "Feature",
  "properties": {
    "iso:country":"BE",
    "sg:address":"Sint-jorisstraat 50",
    "sg:city":"Brugge",
    "sg:classifiers":[
        {
            "category":"Bakery",
            "type":"Food & Drink"
        }
    ],
    "sg:phone":"+32 50 33 62 54",
    "sg:postcode":"8000",
    "sg:province":"West-Vlaanderen",
    "sg:tags":[
        "confectioner",
        "baker"
    ],
    "wof:name":"Focquaert J",
    "wof:placetype":"venue"
},
  "geometry": {"coordinates":[3.2216670513,51.214389801],"type":"Point"}
}