{
  "type": "Feature",
  "properties": {
    "addr:full":"Pr. Clementinalaan 12 Gent Oost-Vlaanderen 9000",
    "addr:housenumber":"12",
    "addr:postcode":"9000",
    "addr:street":"Pr. Clementinalaan;Oost-Vlaanderen",
    "iso:country":"BE",
    "sg:address":"Pr. Clementinalaan 12",
    "sg:city":"Gent",
    "sg:orig_category":"Electrom\u00e9nager, t\u00e9l\u00e9visions and radios. Conseils en syst\u00e8mes informatiques. Eclairage et \u00e9quipements",
    "sg:phone":"+32 9 221 81 69",
    "sg:postcode":"9000",
    "sg:province":"Oost-Vlaanderen",
    "wof:name":"Gentronics",
    "wof:placetype":"venue"
},
  "geometry": {"coordinates":[3.7156600952,51.0349960327],"type":"Point"}
}