{
  "type": "Feature",
  "properties": {
    "addr:full":"Antoon Sanderusstraat 46ba Gent Oost-Vlaanderen 9000",
    "addr:housenumber":"46ba",
    "addr:postcode":"9000",
    "addr:street":"Antoon Sanderusstraat;Oost-Vlaanderen",
    "iso:country":"BE",
    "sg:address":"Antoon Sanderusstraat 46ba",
    "sg:city":"Gent",
    "sg:orig_category":"Diensten voor huisdieren Diverse organisaties and verenigingen",
    "sg:phone":"+32 9 224 11 65",
    "sg:postcode":"9000",
    "sg:province":"Oost-Vlaanderen",
    "wof:name":"Dierenbescherming Snuffel",
    "wof:placetype":"venue"
},
  "geometry": {"coordinates":[3.7274489403,51.0642967224],"type":"Point"}
}