{
  "type": "Feature",
  "properties": {
    "iso:country":"BE",
    "sg:address":"Oostlaan 6",
    "sg:city":"Wevelgem (gullegem)",
    "sg:orig_category":"Non-Classified Establishments",
    "sg:phone":"+32 56 40 11 88",
    "sg:postcode":"8560",
    "sg:province":"West-Vlaanderen",
    "wof:name":"Districo Cvba",
    "wof:placetype":"venue"
},
  "geometry": {"coordinates":[3.184705019,50.8534812927],"type":"Point"}
}