{
  "type": "Feature",
  "properties": {
    "addr:full":"Schaliehoevestraat 71 Heist-op-den-berg Antwerpen 2220",
    "addr:housenumber":"71",
    "addr:postcode":"2220",
    "addr:street":"Schaliehoevestraat",
    "iso:country":"BE",
    "sg:address":"Schaliehoevestraat 71",
    "sg:city":"Heist-op-den-berg",
    "sg:classifiers":[
        {
            "category":"Arena",
            "subcategory":"Sports Club",
            "type":"Entertainment"
        }
    ],
    "sg:phone":"+32 15 24 93 66",
    "sg:postcode":"2220",
    "sg:province":"Antwerpen",
    "sg:tags":[
        "de"
    ],
    "wof:name":"Galicia Technical Diving",
    "wof:placetype":"venue"
},
  "geometry": {"coordinates":[4.7057900429,51.0543708801],"type":"Point"}
}