{
  "type": "Feature",
  "properties": {
    "addr:full":"Oosterzonneplein 1 Zutendaal Limburg 3690",
    "addr:housenumber":"1",
    "addr:postcode":"3690",
    "addr:street":"Oosterzonneplein",
    "iso:country":"BE",
    "sg:address":"Oosterzonneplein 1",
    "sg:city":"Zutendaal",
    "sg:orig_category":"Openbare veiligheid",
    "sg:phone":"+32 89 61 17 47",
    "sg:postcode":"3690",
    "sg:province":"Limburg",
    "wof:name":"Federale Politie",
    "wof:placetype":"venue"
},
  "geometry": {"coordinates":[5.5724601746,50.9335517883],"type":"Point"}
}