{
  "type": "Feature",
  "properties": {
    "addr:full":"Bosduiflaan 3 Kapellen Antwerpen 2950",
    "addr:housenumber":"3",
    "addr:postcode":"2950",
    "addr:street":"Bosduiflaan",
    "iso:country":"BE",
    "sg:address":"Bosduiflaan 3",
    "sg:city":"Kapellen",
    "sg:orig_category":"Ordinateurs and \u00e9quipement informatique",
    "sg:phone":"+32 3 605 20 82",
    "sg:postcode":"2950",
    "sg:province":"Antwerpen",
    "wof:name":"R.b.c.",
    "wof:placetype":"venue"
},
  "geometry": {"coordinates":[4.4363808632,51.3279151917],"type":"Point"}
}