{
  "type": "Feature",
  "properties": {
    "addr:full":"Rue Fr\u00c8res Bieva 29 Namur Namur 5020",
    "addr:housenumber":"29",
    "addr:postcode":"5020",
    "addr:street":"Rue Fre\u0300Res Bieva",
    "iso:country":"BE",
    "sg:address":"Rue Fr\u00c8res Bieva 29",
    "sg:city":"Namur",
    "sg:orig_category":"Installation de menuiserie m\u00e9tallique",
    "sg:phone":"+32 81 21 33 11",
    "sg:postcode":"5020",
    "sg:province":"Namur",
    "wof:name":"Naniot M.",
    "wof:placetype":"venue"
},
  "geometry": {"coordinates":[4.8765082359,50.4902915955],"type":"Point"}
}