{
  "type": "Feature",
  "properties": {
    "addr:full":"Rue De L'eglise 55 Fernelmont (pontillas) Namur 5380",
    "addr:housenumber":"55",
    "addr:postcode":"5380",
    "addr:street":"Rue De L'Eglise",
    "iso:country":"BE",
    "sg:address":"Rue De L'eglise 55",
    "sg:city":"Fernelmont (pontillas)",
    "sg:classifiers":[
        {
            "category":"Building & Trades",
            "subcategory":"Construction",
            "type":"Services"
        }
    ],
    "sg:phone":"+32 81 83 45 12",
    "sg:postcode":"5380",
    "sg:province":"Namur",
    "sg:tags":[
        "ecological"
    ],
    "wof:name":"Buchet J F",
    "wof:placetype":"venue"
},
  "geometry": {"coordinates":[5.0170440674,50.5507736206],"type":"Point"}
}