{
  "type": "Feature",
  "properties": {
    "iso:country":"BE",
    "sg:address":"Rue Franklin 53",
    "sg:city":"Bruxelles",
    "sg:classifiers":[
        {
            "category":"Personal",
            "subcategory":"Barber",
            "type":"Services"
        }
    ],
    "sg:phone":"+32 2 734 96 89",
    "sg:postcode":"1000",
    "sg:province":"Bruxelles-Capitale",
    "sg:tags":[
        "gentleman",
        "salon",
        "-",
        "hairdressing"
    ],
    "wof:name":"Tony",
    "wof:placetype":"venue"
},
  "geometry": {"coordinates":[4.3863639832,50.8449821472],"type":"Point"}
}