{
  "type": "Feature",
  "properties": {
    "iso:country":"BE",
    "sg:address":"Mechelsesteenweg 315",
    "sg:city":"Kontich",
    "sg:orig_category":"Eclairage et \u00e9quipements du foyer",
    "sg:phone":"+32 3 457 58 14",
    "sg:postcode":"2550",
    "sg:province":"Antwerpen",
    "wof:name":"Huis Kocoon",
    "wof:placetype":"venue"
},
  "geometry": {"coordinates":[4.4501800537,51.1179008484],"type":"Point"}
}