{
  "type": "Feature",
  "properties": {
    "iso:country":"BE",
    "sg:address":"Van Bladelstraat 29",
    "sg:city":"Herent",
    "sg:orig_category":"Enseignement maternel and primaire",
    "sg:phone":"+32 16 20 82 74",
    "sg:postcode":"3020",
    "sg:province":"Vlaams-Brabant",
    "wof:name":"Vrije Kleuter- En Basisschool",
    "wof:placetype":"venue"
},
  "geometry": {"coordinates":[4.6703472137,50.907459259],"type":"Point"}
}