{
  "type": "Feature",
  "properties": {
    "addr:full":"Brugsesteenweg 105 De Haan West-Vlaanderen 8420",
    "addr:housenumber":"105",
    "addr:postcode":"8420",
    "addr:street":"Brugsesteenweg",
    "iso:country":"BE",
    "sg:address":"Brugsesteenweg 105",
    "sg:city":"De Haan",
    "sg:orig_category":"Produits chimiques Gr",
    "sg:phone":"+32 50 42 99 16",
    "sg:postcode":"8420",
    "sg:province":"West-Vlaanderen",
    "wof:name":"Dewaele",
    "wof:placetype":"venue"
},
  "geometry": {"coordinates":[3.0871829987,51.2923049927],"type":"Point"}
}