{
  "type": "Feature",
  "properties": {
    "addr:full":"Rue De Nevremont 103 Fosses-la-ville Namur 5070",
    "addr:housenumber":"103",
    "addr:postcode":"5070",
    "addr:street":"Rue De Nevremont",
    "iso:country":"BE",
    "sg:address":"Rue De Nevremont 103",
    "sg:city":"Fosses-la-ville",
    "sg:orig_category":"Electrom\u00e9nager, t\u00e9l\u00e9visions and radios. R\u00e9parations d'appareils \u00e9lectrom\u00e9nagers",
    "sg:phone":"+32 71 71 27 10",
    "sg:postcode":"5070",
    "sg:province":"Namur",
    "wof:name":"Leclerq",
    "wof:placetype":"venue"
},
  "geometry": {"coordinates":[4.6727881432,50.4065513611],"type":"Point"}
}