{
  "type": "Feature",
  "properties": {
    "addr:full":"Rue B\u00e9guinage 1 Nivelles Brabant Wallon 1400",
    "addr:housenumber":"1",
    "addr:postcode":"1400",
    "addr:street":"Rue Be\u0301Guinage",
    "iso:country":"BE",
    "sg:address":"Rue B\u00e9guinage 1",
    "sg:city":"Nivelles",
    "sg:classifiers":[
        {
            "category":"Education",
            "subcategory":"School",
            "type":"Public Place"
        }
    ],
    "sg:phone":"+32 67 84 04 57",
    "sg:postcode":"1400",
    "sg:province":"Brabant Wallon",
    "sg:tags":[
        "primary"
    ],
    "wof:name":"Ecole Du B\u00e9guinage",
    "wof:placetype":"venue"
},
  "geometry": {"coordinates":[4.3205299377,50.5980110168],"type":"Point"}
}