{
  "type": "Feature",
  "properties": {
    "iso:country":"BE",
    "sg:address":"Place Joseph Meunier 26",
    "sg:city":"Mettet",
    "sg:classifiers":[
        {
            "category":"Cafe",
            "type":"Food & Drink"
        }
    ],
    "sg:phone":"+32 71 72 59 27",
    "sg:postcode":"5640",
    "sg:province":"Namur",
    "sg:tags":[
        "caf\u00e9s"
    ],
    "wof:name":"Caf\u00c9 Le Vivaldy",
    "wof:placetype":"venue"
},
  "geometry": {"coordinates":[4.6579751968,50.3199195862],"type":"Point"}
}