{
  "type": "Feature",
  "properties": {
    "addr:full":"Avenue Du Progres 10 Alleur Li\u00e8ge 4432",
    "addr:housenumber":"10",
    "addr:postcode":"4432",
    "addr:street":"Avenue Du Progres",
    "iso:country":"BE",
    "sg:address":"Avenue Du Progres 10",
    "sg:city":"Alleur",
    "sg:classifiers":[
        {
            "category":"Manufacturing",
            "subcategory":"Motor Vehicles & Parts",
            "type":"Manufacturing & Wholesale Goods"
        }
    ],
    "sg:phone":"+32 4 247 36 37",
    "sg:postcode":"4432",
    "sg:province":"Li\u00e8ge",
    "sg:tags":[
        "production",
        "system",
        "automation"
    ],
    "wof:name":"Procim Industrie S.a.",
    "wof:placetype":"venue"
},
  "geometry": {"coordinates":[5.5253558159,50.6730155945],"type":"Point"}
}