{
  "type": "Feature",
  "properties": {
    "addr:full":"Rue Pouplin 6 Li\u00e8ge 1 Li\u00e8ge 4000",
    "addr:housenumber":"6;1",
    "addr:postcode":"4000",
    "addr:street":"Rue Pouplin",
    "iso:country":"BE",
    "sg:address":"Rue Pouplin 6",
    "sg:city":"Li\u00e8ge 1",
    "sg:classifiers":[
        {
            "category":"Real Estate",
            "subcategory":"Architect",
            "type":"Services"
        }
    ],
    "sg:phone":"+32 4 221 39 64",
    "sg:postcode":"4000",
    "sg:province":"Li\u00e8ge",
    "wof:name":"Heuschling D",
    "wof:placetype":"venue"
},
  "geometry": {"coordinates":[5.5615539551,50.640209198],"type":"Point"}
}