{
  "type": "Feature",
  "properties": {
    "iso:country":"BE",
    "sg:address":"Brouwersstraat 1 Box 8",
    "sg:city":"Leuven",
    "sg:classifiers":[
        {
            "category":"Banks & Credit Unions",
            "subcategory":"Investment Brokerage",
            "type":"Services"
        }
    ],
    "sg:phone":"+32 16 22 09 40",
    "sg:postcode":"3000",
    "sg:province":"Vlaams-Brabant",
    "sg:tags":[
        "auditor"
    ],
    "wof:name":"Cardyn P",
    "wof:placetype":"venue"
},
  "geometry": {"coordinates":[4.6954951286,50.8825798035],"type":"Point"}
}