{
  "type": "Feature",
  "properties": {
    "addr:full":"Rue Des Grands-champs 1ba Assesse Namur 5334",
    "addr:postcode":"1ba;5334",
    "addr:street":"Rue Des Grands-Champs",
    "iso:country":"BE",
    "sg:address":"Rue Des Grands-champs 1ba",
    "sg:city":"Assesse",
    "sg:orig_category":"Eleveurs de bovins",
    "sg:phone":"+32 83 65 53 85",
    "sg:postcode":"5334",
    "sg:province":"Namur",
    "wof:name":"Henri Housiaux",
    "wof:placetype":"venue"
},
  "geometry": {"coordinates":[5.0645799637,50.3661880493],"type":"Point"}
}