{
  "type": "Feature",
  "properties": {
    "iso:country":"BE",
    "sg:address":"Pastoor Frederickxstraat 40ba",
    "sg:city":"Lummen",
    "sg:orig_category":"M\u00e9decins and sp\u00e9cialistes",
    "sg:phone":"+32 13 53 15 00",
    "sg:postcode":"3560",
    "sg:province":"Limburg",
    "wof:name":"Bert Blommen",
    "wof:placetype":"venue"
},
  "geometry": {"coordinates":[5.1958599091,50.9848098755],"type":"Point"}
}