{
  "type": "Feature",
  "properties": {
    "iso:country":"BE",
    "sg:address":"Olsensesteenweg 67",
    "sg:city":"Kruishoutem",
    "sg:classifiers":[
        {
            "category":"Wholesale",
            "subcategory":"Machinery & Supplies",
            "type":"Manufacturing & Wholesale Goods"
        }
    ],
    "sg:phone":"+32 9 388 84 11",
    "sg:postcode":"9770",
    "sg:province":"Oost-Vlaanderen",
    "sg:tags":[
        "agricultural",
        "tractor"
    ],
    "wof:name":"Vanthuyne Bvba",
    "wof:placetype":"venue"
},
  "geometry": {"coordinates":[3.4900360107,50.9178466797],"type":"Point"}
}