{
  "type": "Feature",
  "properties": {
    "iso:country":"BE",
    "sg:address":"Bergakker 28",
    "sg:city":"Vosselaar",
    "sg:orig_category":"Sportclubs",
    "sg:phone":"+32 14 61 70 64",
    "sg:postcode":"2350",
    "sg:province":"Antwerpen",
    "wof:name":"J.c. Vosselaar",
    "wof:placetype":"venue"
},
  "geometry": {"coordinates":[4.886578083,51.3090591431],"type":"Point"}
}