{
  "type": "Feature",
  "properties": {
    "iso:country":"BE",
    "sg:address":"Brabantstraat 153",
    "sg:city":"Schaarbeek/schaerbeek",
    "sg:orig_category":"Huishoudapparaten, televisies and radio's",
    "sg:phone":"+32 2 215 09 78",
    "sg:postcode":"1030",
    "sg:province":"Bruxelles-Capitale",
    "wof:name":"Radio-tele/radio T\u00c9l\u00c9",
    "wof:placetype":"venue"
},
  "geometry": {"coordinates":[4.3650460243,50.8626098633],"type":"Point"}
}