{
  "type": "Feature",
  "properties": {
    "iso:country":"BE",
    "sg:address":"Rue Rivi\u00c8re 5",
    "sg:city":"Lessines",
    "sg:orig_category":"Eleveurs de bovins. Eleveurs and marchands de porcs. Fruits and l\u00e9gumes Gr",
    "sg:phone":"+32 68 44 85 84",
    "sg:postcode":"7862",
    "sg:province":"Hainaut",
    "wof:name":"Versavel Elevage",
    "wof:placetype":"venue"
},
  "geometry": {"coordinates":[3.7672030926,50.7165489197],"type":"Point"}
}