{
  "type": "Feature",
  "properties": {
    "addr:full":"Rue De La Cible 64-68 Bruxelles (schaerbeek) Bruxelles-Capitale 1030",
    "addr:housenumber":"64-68",
    "addr:postcode":"1030",
    "addr:street":"Rue De La Cible",
    "iso:country":"BE",
    "sg:address":"Rue De La Cible 64-68",
    "sg:city":"Bruxelles (schaerbeek)",
    "sg:orig_category":"Solar protection - Outside",
    "sg:phone":"+32 2 735 20 20",
    "sg:postcode":"1030",
    "sg:province":"Bruxelles-Capitale",
    "wof:name":"Fabima Sa",
    "wof:placetype":"venue"
},
  "geometry": {"coordinates":[4.3827581406,50.8519897461],"type":"Point"}
}