{
  "type": "Feature",
  "properties": {
    "addr:full":"Place De La Trinit\u00c9 1 Lens Hainaut 7870",
    "addr:housenumber":"1",
    "addr:postcode":"7870",
    "addr:street":"Place De La Trinite\u0301",
    "iso:country":"BE",
    "sg:address":"Place De La Trinit\u00c9 1",
    "sg:city":"Lens",
    "sg:classifiers":[
        {
            "category":"Government",
            "subcategory":"Police Station",
            "type":"Public Place"
        }
    ],
    "sg:phone":"+32 65 22 04 20",
    "sg:postcode":"7870",
    "sg:province":"Hainaut",
    "sg:tags":[
        "gendarmerie"
    ],
    "wof:name":"Police F\u00c9d\u00c9rale/federale Politie",
    "wof:placetype":"venue"
},
  "geometry": {"coordinates":[3.9017961025,50.5562973022],"type":"Point"}
}