{
  "type": "Feature",
  "properties": {
    "addr:full":"Kleine Waregemsestraat 9 Harelbeke West-Vlaanderen 8530",
    "addr:housenumber":"9",
    "addr:postcode":"8530",
    "addr:street":"Waregemsestraat",
    "iso:country":"BE",
    "sg:address":"Kleine Waregemsestraat 9",
    "sg:city":"Harelbeke",
    "sg:orig_category":"Non-Classified Establishments",
    "sg:phone":"+32 56 71 57 56",
    "sg:postcode":"8530",
    "sg:province":"West-Vlaanderen",
    "wof:name":"Debaere Interieur Nv",
    "wof:placetype":"venue"
},
  "geometry": {"coordinates":[3.3288199902,50.8592185974],"type":"Point"}
}