{
  "type": "Feature",
  "properties": {
    "iso:country":"BE",
    "sg:address":"Basse Chauss\u00c9e 1",
    "sg:city":"Hannut",
    "sg:orig_category":"Eleveurs de bovins",
    "sg:phone":"+32 19 69 97 94",
    "sg:postcode":"4280",
    "sg:province":"Li\u00e8ge",
    "wof:name":"Alfred Bossy",
    "wof:placetype":"venue"
},
  "geometry": {"coordinates":[5.0912871361,50.6331977844],"type":"Point"}
}