{
  "type": "Feature",
  "properties": {
    "addr:full":"Grand-route 119 Bassenge Li\u00e8ge 4690",
    "addr:housenumber":"119",
    "addr:postcode":"4690",
    "addr:street":"Grand-Route",
    "iso:country":"BE",
    "sg:address":"Grand-route 119",
    "sg:city":"Bassenge",
    "sg:orig_category":"Journaux. Tabac",
    "sg:phone":"+32 4 286 16 84",
    "sg:postcode":"4690",
    "sg:province":"Li\u00e8ge",
    "wof:name":"Au Quotidien",
    "wof:placetype":"venue"
},
  "geometry": {"coordinates":[5.6180701256,50.7608184814],"type":"Point"}
}