{
  "type": "Feature",
  "properties": {
    "addr:full":"Eikendreef 40 Rijkevorsel Antwerpen 2310",
    "addr:housenumber":"40",
    "addr:postcode":"2310",
    "addr:street":"Eikendreef",
    "iso:country":"BE",
    "sg:address":"Eikendreef 40",
    "sg:city":"Rijkevorsel",
    "sg:classifiers":[
        {
            "category":"Building & Trades",
            "subcategory":"Construction",
            "type":"Services"
        }
    ],
    "sg:phone":"+32 3 311 74 65",
    "sg:postcode":"2310",
    "sg:province":"Antwerpen",
    "sg:tags":[
        "insulation",
        "thermical",
        "work",
        "acoustical"
    ],
    "wof:name":"Freemac Bvba",
    "wof:placetype":"venue"
},
  "geometry": {"coordinates":[4.7913331985,51.3318862915],"type":"Point"}
}