{
  "type": "Feature",
  "properties": {
    "iso:country":"BE",
    "sg:address":"Rue Saint-georges 21",
    "sg:city":"Nivelles",
    "sg:orig_category":"Banques and organismes de cr\u00e9dit",
    "sg:phone":"+32 67 21 80 24",
    "sg:postcode":"1400",
    "sg:province":"Brabant Wallon",
    "wof:name":"Cr\u00c9dit Agricole",
    "wof:placetype":"venue"
},
  "geometry": {"coordinates":[4.3262009621,50.597278595],"type":"Point"}
}