{
  "type": "Feature",
  "properties": {
    "iso:country":"BE",
    "sg:address":"Gentstraat 177",
    "sg:city":"Meulebeke",
    "sg:orig_category":"Paramedische behandelingen",
    "sg:phone":"+32 51 48 79 22",
    "sg:postcode":"8760",
    "sg:province":"West-Vlaanderen",
    "wof:name":"Geldhof Rita",
    "wof:placetype":"venue"
},
  "geometry": {"coordinates":[3.3035130501,50.9486885071],"type":"Point"}
}