{
  "type": "Feature",
  "properties": {
    "addr:full":"Sinaaidorp 8 Sint-niklaas (sinaai) Oost-Vlaanderen 9112",
    "addr:housenumber":"8",
    "addr:postcode":"9112",
    "addr:street":"Sinaaidorp;Oost-Vlaanderen",
    "iso:country":"BE",
    "sg:address":"Sinaaidorp 8",
    "sg:city":"Sint-niklaas (sinaai)",
    "sg:classifiers":[
        {
            "category":"Retail",
            "subcategory":"Laundry & Dry Cleaning",
            "type":"Services"
        }
    ],
    "sg:phone":"+32 3 772 41 65",
    "sg:postcode":"9112",
    "sg:province":"Oost-Vlaanderen",
    "sg:tags":[
        "dyer",
        "cleaner"
    ],
    "wof:name":"Best Shop",
    "wof:placetype":"venue"
},
  "geometry": {"coordinates":[4.0400938988,51.1574058533],"type":"Point"}
}