{
  "type": "Feature",
  "properties": {
    "addr:full":"Rue De La Poire D'or 22 Cuesmes Hainaut 7033",
    "addr:housenumber":"22",
    "addr:postcode":"7033",
    "addr:street":"Rue De La Poire D'Or",
    "iso:country":"BE",
    "sg:address":"Rue De La Poire D'or 22",
    "sg:city":"Cuesmes",
    "sg:classifiers":[
        {
            "category":"Utilities",
            "subcategory":"Water",
            "type":"Services"
        }
    ],
    "sg:phone":"+32 65 34 91 66",
    "sg:postcode":"7033",
    "sg:province":"Hainaut",
    "sg:tags":[
        "screw",
        "dy"
    ],
    "wof:name":"Techmat S.a.",
    "wof:placetype":"venue"
},
  "geometry": {"coordinates":[0.7899209857,46.1248016357],"type":"Point"}
}