{
  "type": "Feature",
  "properties": {
    "iso:country":"BE",
    "sg:address":"Kasteelstraat 8",
    "sg:city":"Duffel",
    "sg:orig_category":"M\u00e9decins and sp\u00e9cialistes",
    "sg:phone":"+32 15 31 63 53",
    "sg:postcode":"2570",
    "sg:province":"Antwerpen",
    "wof:name":"Jozef Bresseleers",
    "wof:placetype":"venue"
},
  "geometry": {"coordinates":[4.4986948967,51.0973091125],"type":"Point"}
}