{
  "type": "Feature",
  "properties": {
    "iso:country":"BE",
    "sg:address":"Rue Du Poncia 152",
    "sg:city":"Sambreville",
    "sg:orig_category":"Afval and schroot Gh",
    "sg:phone":"+32 71 77 52 65",
    "sg:postcode":"5060",
    "sg:province":"Namur",
    "wof:name":"Robert Rossini",
    "wof:placetype":"venue"
},
  "geometry": {"coordinates":[4.5887970924,50.4454307556],"type":"Point"}
}