{
  "type": "Feature",
  "properties": {
    "iso:country":"BE",
    "sg:address":"Vijfseweg 158",
    "sg:city":"Waregem",
    "sg:orig_category":"V\u00e9t\u00e9rinaires",
    "sg:phone":"+32 56 60 14 32",
    "sg:postcode":"8790",
    "sg:province":"West-Vlaanderen",
    "wof:name":"Luc Coucke",
    "wof:placetype":"venue"
},
  "geometry": {"coordinates":[3.4156680107,50.900554657],"type":"Point"}
}