{
  "type": "Feature",
  "properties": {
    "addr:full":"Zeelaan 195 Koksijde West-Vlaanderen 8670",
    "addr:housenumber":"195",
    "addr:postcode":"8670",
    "addr:street":"Zeelaan",
    "iso:country":"BE",
    "sg:address":"Zeelaan 195",
    "sg:city":"Koksijde",
    "sg:orig_category":"Avocats and conseillers juridiques",
    "sg:phone":"+32 58 51 65 16",
    "sg:postcode":"8670",
    "sg:province":"West-Vlaanderen",
    "wof:name":"Dirk Dawyndt",
    "wof:placetype":"venue"
},
  "geometry": {"coordinates":[2.639029026,51.1147117615],"type":"Point"}
}