{
  "type": "Feature",
  "properties": {
    "addr:full":"Moortelstraat 26 Hamme Oost-Vlaanderen 9220",
    "addr:housenumber":"26",
    "addr:postcode":"9220",
    "addr:street":"Moortelstraat",
    "iso:country":"BE",
    "sg:address":"Moortelstraat 26",
    "sg:city":"Hamme",
    "sg:classifiers":[
        {
            "category":"Food & Beverages",
            "subcategory":"Fruits & Vegetables",
            "type":"Retail Goods"
        }
    ],
    "sg:phone":"+32 52 47 98 78",
    "sg:postcode":"9220",
    "sg:province":"Oost-Vlaanderen",
    "sg:tags":[
        "l\u00e9gumes",
        "gr"
    ],
    "wof:name":"De Coensel",
    "wof:placetype":"venue"
},
  "geometry": {"coordinates":[4.0745167732,51.0976753235],"type":"Point"}
}