{
  "type": "Feature",
  "properties": {
    "addr:full":"Rue Jean Jaur\u00c8s 148 Li\u00c8ge Li\u00e8ge 4020",
    "addr:housenumber":"148",
    "addr:postcode":"4020",
    "addr:street":"Rue Jean Jaure\u0300S",
    "iso:country":"BE",
    "sg:address":"Rue Jean Jaur\u00c8s 148",
    "sg:city":"Li\u00c8ge",
    "sg:orig_category":"Entretien and r\u00e9parations de voitures",
    "sg:phone":"+32 4 247 28 49",
    "sg:postcode":"4020",
    "sg:province":"Li\u00e8ge",
    "wof:name":"Car-wash D\u00b4ans",
    "wof:placetype":"venue"
},
  "geometry": {"coordinates":[5.6261701584,50.6412582397],"type":"Point"}
}