{
  "type": "Feature",
  "properties": {
    "iso:country":"BE",
    "sg:address":"Avenue L. Lepoutre 29",
    "sg:city":"Ixelles",
    "sg:orig_category":"Huwelijks- and Relatiebureaus",
    "sg:phone":"+32 2 347 25 61",
    "sg:postcode":"1050",
    "sg:province":"Bruxelles-Capitale",
    "wof:name":"Kalinka",
    "wof:placetype":"venue"
},
  "geometry": {"coordinates":[4.3581857681,50.8195991516],"type":"Point"}
}