{
  "type": "Feature",
  "properties": {
    "iso:country":"BE",
    "sg:address":"Rue Du Roi Albert 15",
    "sg:city":"Clavier",
    "sg:classifiers":[
        {
            "category":"Building & Trades",
            "subcategory":"Electrical",
            "type":"Services"
        }
    ],
    "sg:phone":"+32 86 34 40 70",
    "sg:postcode":"4560",
    "sg:province":"Li\u00e8ge",
    "sg:tags":[
        "electric",
        "-",
        "housewiring",
        "contractor"
    ],
    "wof:name":"Fraipont J",
    "wof:placetype":"venue"
},
  "geometry": {"coordinates":[5.3591389656,50.4279975891],"type":"Point"}
}