{
  "type": "Feature",
  "properties": {
    "addr:full":"Industriepark 26 Diest Vlaams-Brabant 3290",
    "addr:housenumber":"26",
    "addr:postcode":"3290",
    "addr:street":"Industriepark",
    "iso:country":"BE",
    "sg:address":"Industriepark 26",
    "sg:city":"Diest",
    "sg:classifiers":[
        {
            "category":"Building & Trades",
            "subcategory":"Locksmith",
            "type":"Services"
        }
    ],
    "sg:phone":"+32 13 31 49 79",
    "sg:postcode":"3290",
    "sg:province":"Vlaams-Brabant",
    "sg:tags":[
        "roofing",
        "industrial"
    ],
    "wof:name":"Euro Bati 92 B.v.b.a.",
    "wof:placetype":"venue"
},
  "geometry": {"coordinates":[5.0731592178,50.9659233093],"type":"Point"}
}