{
  "type": "Feature",
  "properties": {
    "iso:country":"BE",
    "sg:address":"Rue De La Haute Bise 10",
    "sg:city":"Lobbes (mont-sainte-genevi\u00e8ve)",
    "sg:classifiers":[
        {
            "category":"Utilities",
            "subcategory":"Natural Gas",
            "type":"Services"
        }
    ],
    "sg:phone":"+32 71 59 42 64",
    "sg:postcode":"6540",
    "sg:province":"Hainaut",
    "sg:tags":[
        "welding"
    ],
    "wof:name":"Stiernon Sa",
    "wof:placetype":"venue"
},
  "geometry": {"coordinates":[4.2294259071,50.378276825],"type":"Point"}
}