{
  "type": "Feature",
  "properties": {
    "addr:full":"Stationsstraat 130 Liedekerke Vlaams-Brabant 1770",
    "addr:housenumber":"130",
    "addr:postcode":"1770",
    "addr:street":"Stationsstraat;Vlaams-Brabant",
    "iso:country":"BE",
    "sg:address":"Stationsstraat 130",
    "sg:city":"Liedekerke",
    "sg:orig_category":"Plaatsen van vloer- and muurbekleding Schilders",
    "sg:phone":"+32 53 66 80 63",
    "sg:postcode":"1770",
    "sg:province":"Vlaams-Brabant",
    "wof:name":"Rufin Boriau",
    "wof:placetype":"venue"
},
  "geometry": {"coordinates":[4.0883731842,50.8744010925],"type":"Point"}
}