{
  "type": "Feature",
  "properties": {
    "iso:country":"BE",
    "sg:address":"Wolvendreef 26",
    "sg:city":"Kortrijk",
    "sg:classifiers":[
        {
            "category":"Taxi",
            "type":"Transportation"
        }
    ],
    "sg:phone":"+32 56 21 81 43",
    "sg:postcode":"8500",
    "sg:province":"West-Vlaanderen",
    "sg:tags":[
        "taxi's"
    ],
    "wof:name":"A.t.s.",
    "wof:placetype":"venue"
},
  "geometry": {"coordinates":[3.2622559071,50.8099708557],"type":"Point"}
}