{
  "type": "Feature",
  "properties": {
    "addr:full":"Molenstraat 73 Genk Limburg 3600",
    "addr:housenumber":"73",
    "addr:postcode":"3600",
    "addr:street":"Molenstraat",
    "iso:country":"BE",
    "sg:address":"Molenstraat 73",
    "sg:city":"Genk",
    "sg:classifiers":[
        {
            "category":"Home & Garden",
            "subcategory":"Home Furnishings",
            "type":"Retail Goods"
        }
    ],
    "sg:phone":"+32 89 35 30 43",
    "sg:postcode":"3600",
    "sg:province":"Limburg",
    "sg:tags":[
        "interior",
        "decoration"
    ],
    "wof:name":"Gumienny R",
    "wof:placetype":"venue"
},
  "geometry": {"coordinates":[5.5046420097,50.9642868042],"type":"Point"}
}