{
  "type": "Feature",
  "properties": {
    "iso:country":"BE",
    "sg:address":"Sportlaan 7",
    "sg:city":"Dilsen-stokkem (dilsen)",
    "sg:classifiers":[
        {
            "category":"Education",
            "subcategory":"Special Training",
            "type":"Public Place"
        }
    ],
    "sg:phone":"+32 89 79 35 41",
    "sg:postcode":"3650",
    "sg:province":"Limburg",
    "sg:tags":[
        "school",
        "language"
    ],
    "wof:name":"Phillips P",
    "wof:placetype":"venue"
},
  "geometry": {"coordinates":[5.7089190483,51.0373764038],"type":"Point"}
}