{
  "type": "Feature",
  "properties": {
    "addr:full":"Groenstraat 40 Hamont-achel Limburg 3930",
    "addr:housenumber":"40",
    "addr:postcode":"3930",
    "addr:street":"Groenstraat",
    "iso:country":"BE",
    "sg:address":"Groenstraat 40",
    "sg:city":"Hamont-achel",
    "sg:classifiers":[
        {
            "category":"Cafe",
            "type":"Food & Drink"
        }
    ],
    "sg:phone":"+32 11 44 80 86",
    "sg:postcode":"3930",
    "sg:province":"Limburg",
    "sg:tags":[
        "caf\u00e9s"
    ],
    "wof:name":"Antoine Joosten",
    "wof:placetype":"venue"
},
  "geometry": {"coordinates":[5.5450549126,51.2511863708],"type":"Point"}
}