{
  "type": "Feature",
  "properties": {
    "addr:full":"Europark-noord 45 Sint-niklaas Oost-Vlaanderen 9100",
    "addr:housenumber":"45",
    "addr:postcode":"9100",
    "addr:street":"Europark-Noord",
    "iso:country":"BE",
    "sg:address":"Europark-noord 45",
    "sg:city":"Sint-niklaas",
    "sg:orig_category":"HUISBRANDOLIE",
    "sg:phone":"+32 3 776 34 91",
    "sg:postcode":"9100",
    "sg:province":"Oost-Vlaanderen",
    "wof:name":"Succes Produkten",
    "wof:placetype":"venue"
},
  "geometry": {"coordinates":[4.1658320427,51.1701164246],"type":"Point"}
}