{
  "type": "Feature",
  "properties": {
    "iso:country":"BE",
    "sg:address":"Franciscuslaan 32",
    "sg:city":"Sint-niklaas",
    "sg:orig_category":"Tuinen",
    "sg:phone":"+32 3 772 17 72",
    "sg:postcode":"9112",
    "sg:province":"Oost-Vlaanderen",
    "wof:name":"Huysentruit",
    "wof:placetype":"venue"
},
  "geometry": {"coordinates":[4.0450100899,51.1590385437],"type":"Point"}
}