{
  "type": "Feature",
  "properties": {
    "iso:country":"BE",
    "sg:address":"Grand'place 13",
    "sg:city":"Orp-jauche",
    "sg:classifiers":[
        {
            "category":"Cafe",
            "type":"Food & Drink"
        }
    ],
    "sg:phone":"+32 19 63 44 38",
    "sg:postcode":"1350",
    "sg:province":"Brabant Wallon",
    "sg:tags":[
        "caf\u00e9s"
    ],
    "wof:name":"Eliane Mayeur",
    "wof:placetype":"venue"
},
  "geometry": {"coordinates":[4.9555640221,50.6817398071],"type":"Point"}
}