{
  "type": "Feature",
  "properties": {
    "addr:full":"Rue Moulin De Spiennes 11bb Mons Hainaut 7032",
    "addr:housenumber":"11bb",
    "addr:postcode":"7032",
    "addr:street":"Rue Moulin De Spiennes;Hainaut",
    "iso:country":"BE",
    "sg:address":"Rue Moulin De Spiennes 11bb",
    "sg:city":"Mons",
    "sg:orig_category":"Jardinage",
    "sg:phone":"+32 65 34 64 54",
    "sg:postcode":"7032",
    "sg:province":"Hainaut",
    "wof:name":"Noel",
    "wof:placetype":"venue"
},
  "geometry": {"coordinates":[3.9869709015,50.4255142212],"type":"Point"}
}