{
  "type": "Feature",
  "properties": {
    "addr:full":"Rue Du Faubourg 36 Walcourt (berz\u00e9e) Namur 5651",
    "addr:housenumber":"36",
    "addr:postcode":"5651",
    "addr:street":"Rue Du Faubourg",
    "iso:country":"BE",
    "sg:address":"Rue Du Faubourg 36",
    "sg:city":"Walcourt (berz\u00e9e)",
    "sg:classifiers":[
        {
            "category":"Professional",
            "subcategory":"Art Services",
            "type":"Services"
        }
    ],
    "sg:phone":"+32 71 61 48 00",
    "sg:postcode":"5651",
    "sg:province":"Namur",
    "sg:tags":[
        "decorative",
        "joinery"
    ],
    "wof:name":"Minadeo",
    "wof:placetype":"venue"
},
  "geometry": {"coordinates":[4.4048051834,50.2877731323],"type":"Point"}
}