{
  "type": "Feature",
  "properties": {
    "addr:full":"Gasthuisstraat 25-27 Brussel/bruxelles Bruxelles-Capitale 1000",
    "addr:postcode":"25-27;/ bruxelles;1000",
    "addr:street":"Gasthuisstraat",
    "iso:country":"BE",
    "sg:address":"Gasthuisstraat 25-27",
    "sg:city":"Brussel/bruxelles",
    "sg:orig_category":"IJzerwaren, bouw- and verfmaterialen Verlichting and huishoudartikelen Vloer- and muurbekleding",
    "sg:phone":"+32 2 513 58 92",
    "sg:postcode":"1000",
    "sg:province":"Bruxelles-Capitale",
    "wof:name":"Noir D'ivoire",
    "wof:placetype":"venue"
},
  "geometry": {"coordinates":[4.3535089493,50.8439445496],"type":"Point"}
}