{
  "type": "Feature",
  "properties": {
    "addr:full":"Zandstraat 118 Zoersel Antwerpen 2980",
    "addr:housenumber":"118",
    "addr:postcode":"2980",
    "addr:street":"Zandstraat",
    "iso:country":"BE",
    "sg:address":"Zandstraat 118",
    "sg:city":"Zoersel",
    "sg:orig_category":"Loodgieterij, verwarming and sanitaire installaties",
    "sg:phone":"+32 3 312 19 00",
    "sg:postcode":"2980",
    "sg:province":"Antwerpen",
    "wof:name":"Schenck Rik",
    "wof:placetype":"venue"
},
  "geometry": {"coordinates":[4.7107329369,51.260017395],"type":"Point"}
}