{
  "type": "Feature",
  "properties": {
    "addr:full":"Hoevepoort 8 Gent (mariakerke) Oost-Vlaanderen 9030",
    "addr:housenumber":"8",
    "addr:postcode":"9030",
    "addr:street":"Hoevepoort",
    "iso:country":"BE",
    "sg:address":"Hoevepoort 8",
    "sg:city":"Gent (mariakerke)",
    "sg:classifiers":[
        {
            "category":"Professional",
            "subcategory":"Management & Consulting",
            "type":"Services"
        }
    ],
    "sg:phone":"+32 9 226 51 14",
    "sg:postcode":"9030",
    "sg:province":"Oost-Vlaanderen",
    "sg:tags":[
        "consultant"
    ],
    "wof:name":"De Boodt P",
    "wof:placetype":"venue"
},
  "geometry": {"coordinates":[3.6792590618,51.0808601379],"type":"Point"}
}