{
  "type": "Feature",
  "properties": {
    "addr:full":"Hanegoor 56 Grobbendonk Antwerpen 2288",
    "addr:housenumber":"56",
    "addr:postcode":"2288",
    "addr:street":"Hanegoor",
    "iso:country":"BE",
    "sg:address":"Hanegoor 56",
    "sg:city":"Grobbendonk",
    "sg:orig_category":"Installatie van houten of kunststof schrijnwerk Installatie van metalen schrijnwerk",
    "sg:phone":"+32 14 51 16 99",
    "sg:postcode":"2288",
    "sg:province":"Antwerpen",
    "wof:name":"Nys L.",
    "wof:placetype":"venue"
},
  "geometry": {"coordinates":[4.74421978,51.1572113037],"type":"Point"}
}