{
  "type": "Feature",
  "properties": {
    "addr:full":"Industrieweg 7 Beerse Antwerpen 2340",
    "addr:housenumber":"7",
    "addr:postcode":"2340",
    "addr:street":"Industrieweg",
    "iso:country":"BE",
    "sg:address":"Industrieweg 7",
    "sg:city":"Beerse",
    "sg:classifiers":[
        {
            "category":"Government",
            "subcategory":"Customs House",
            "type":"Public Place"
        }
    ],
    "sg:phone":"+32 14 61 54 60",
    "sg:postcode":"2340",
    "sg:province":"Antwerpen",
    "sg:tags":[
        "packing"
    ],
    "wof:name":"Ghiant Aerosols Nv",
    "wof:placetype":"venue"
},
  "geometry": {"coordinates":[4.8361091614,51.2989768982],"type":"Point"}
}