{
  "type": "Feature",
  "properties": {
    "iso:country":"BE",
    "sg:address":"Noord-brabantlaan 16",
    "sg:city":"Turnhout",
    "sg:classifiers":[
        {
            "category":"Manufacturing",
            "subcategory":"Rubber & Plastics",
            "type":"Manufacturing & Wholesale Goods"
        }
    ],
    "sg:phone":"+32 14 45 37 96",
    "sg:postcode":"2300",
    "sg:province":"Antwerpen",
    "sg:tags":[
        "pipe",
        "-"
    ],
    "wof:name":"Janssens-geerinck Thule Nv",
    "wof:placetype":"venue"
},
  "geometry": {"coordinates":[4.9667639732,51.3261756897],"type":"Point"}
}