{
  "type": "Feature",
  "properties": {
    "iso:country":"BE",
    "sg:address":"Chauss\u00c9e De Charleroi 112",
    "sg:city":"Jodoigne",
    "sg:orig_category":"SMEEDWERK, METAALBEWERKING AND POEDERMETALLURGIE",
    "sg:phone":"+32 10 65 56 73",
    "sg:postcode":"1370",
    "sg:province":"Brabant Wallon",
    "wof:name":"Caillou D.",
    "wof:placetype":"venue"
},
  "geometry": {"coordinates":[4.8667788506,50.7173881531],"type":"Point"}
}