{
  "type": "Feature",
  "properties": {
    "iso:country":"BE",
    "sg:address":"Oude Desselgemstraat 14",
    "sg:city":"Waregem",
    "sg:classifiers":[
        {
            "category":"Health Services",
            "subcategory":"Hospital",
            "type":"Services"
        }
    ],
    "sg:phone":"+32 56 60 76 34",
    "sg:postcode":"8790",
    "sg:province":"West-Vlaanderen",
    "sg:tags":[
        "ambulance"
    ],
    "wof:name":"Rescue Team Ambulancecentrum",
    "wof:placetype":"venue"
},
  "geometry": {"coordinates":[3.4092569351,50.8809432983],"type":"Point"}
}