{
  "type": "Feature",
  "properties": {
    "addr:full":"Rue De Rouillon 22 Anhee Namur 5537",
    "addr:housenumber":"22",
    "addr:postcode":"5537",
    "addr:street":"Rue De Rouillon",
    "iso:country":"BE",
    "sg:address":"Rue De Rouillon 22",
    "sg:city":"Anhee",
    "sg:orig_category":"Dierenartsen",
    "sg:phone":"+32 71 79 89 27",
    "sg:postcode":"5537",
    "sg:province":"Namur",
    "wof:name":"Fabrice Pironet",
    "wof:placetype":"venue"
},
  "geometry": {"coordinates":[4.8035678864,50.3341445923],"type":"Point"}
}