{
  "type": "Feature",
  "properties": {
    "iso:country":"BE",
    "sg:address":"Zoning Industriel 1",
    "sg:city":"Fleurus",
    "sg:classifiers":[
        {
            "category":"Professional",
            "subcategory":"Printing & Photocopies",
            "type":"Services"
        }
    ],
    "sg:phone":"+32 71 25 36 11",
    "sg:postcode":"6220",
    "sg:province":"Hainaut",
    "sg:tags":[
        "print",
        "security"
    ],
    "wof:name":"Dry Print Graphing S.a.",
    "wof:placetype":"venue"
},
  "geometry": {"coordinates":[4.5555500984,50.4610710144],"type":"Point"}
}