{
  "type": "Feature",
  "properties": {
    "addr:full":"Rue De L'entreville 90 Lobbes Hainaut 6540",
    "addr:housenumber":"90",
    "addr:postcode":"6540",
    "addr:street":"Rue De L'Entreville",
    "iso:country":"BE",
    "sg:address":"Rue De L'entreville 90",
    "sg:city":"Lobbes",
    "sg:orig_category":"Boucheries",
    "sg:phone":"+32 71 59 02 52",
    "sg:postcode":"6540",
    "sg:province":"Hainaut",
    "wof:name":"Yvon Hanoteaux",
    "wof:placetype":"venue"
},
  "geometry": {"coordinates":[4.2679572105,50.3535614014],"type":"Point"}
}