{
  "type": "Feature",
  "properties": {
    "iso:country":"BE",
    "sg:address":"Malibranstraat 17",
    "sg:city":"Elsene/ixelles",
    "sg:classifiers":[
        {
            "category":"Fast Food",
            "type":"Food & Drink"
        }
    ],
    "sg:phone":"+32 2 648 03 06",
    "sg:postcode":"1050",
    "sg:province":"Bruxelles-Capitale",
    "sg:tags":[
        "meeneem",
        "restaurant"
    ],
    "wof:name":"Pide Sibel",
    "wof:placetype":"venue"
},
  "geometry": {"coordinates":[4.3737440109,50.8294029236],"type":"Point"}
}