{
  "type": "Feature",
  "properties": {
    "iso:country":"BE",
    "sg:address":"Rue Carache 16",
    "sg:city":"Jurbise",
    "sg:orig_category":"M\u00e9decins and sp\u00e9cialistes",
    "sg:phone":"+32 65 22 65 59",
    "sg:postcode":"7050",
    "sg:province":"Hainaut",
    "wof:name":"Anna-maria Tarko",
    "wof:placetype":"venue"
},
  "geometry": {"coordinates":[3.8961749077,50.5145874023],"type":"Point"}
}