{
  "type": "Feature",
  "properties": {
    "addr:full":"Rue De L'industrie 33 Namur Namur 5002",
    "addr:housenumber":"33",
    "addr:postcode":"5002",
    "addr:street":"Rue De L'Industrie",
    "iso:country":"BE",
    "sg:address":"Rue De L'industrie 33",
    "sg:city":"Namur",
    "sg:orig_category":"Mat\u00e9riaux de construction Gr",
    "sg:phone":"+32 81 74 13 96",
    "sg:postcode":"5002",
    "sg:province":"Namur",
    "wof:name":"Leponce C.t.p.",
    "wof:placetype":"venue"
},
  "geometry": {"coordinates":[4.8536062241,50.4746856689],"type":"Point"}
}