{
  "type": "Feature",
  "properties": {
    "iso:country":"BE",
    "sg:address":"Rue Du Tultay 5",
    "sg:city":"Sprimont",
    "sg:orig_category":"Eleveurs de bovins",
    "sg:phone":"+32 4 382 17 37",
    "sg:postcode":"4140",
    "sg:province":"Li\u00e8ge",
    "wof:name":"Fabrice Pirard",
    "wof:placetype":"venue"
},
  "geometry": {"coordinates":[5.6675958633,50.510269165],"type":"Point"}
}