{
  "type": "Feature",
  "properties": {
    "addr:full":"Kerkstraat 24 Sint-gillis-waas Oost-Vlaanderen 9170",
    "addr:housenumber":"24",
    "addr:postcode":"9170",
    "addr:street":"Kerkstraat",
    "iso:country":"BE",
    "sg:address":"Kerkstraat 24",
    "sg:city":"Sint-gillis-waas",
    "sg:classifiers":[
        {
            "category":"Health Services",
            "subcategory":"Dentist",
            "type":"Services"
        }
    ],
    "sg:phone":"+32 3 770 70 75",
    "sg:postcode":"9170",
    "sg:province":"Oost-Vlaanderen",
    "wof:name":"Eloot Anouk",
    "wof:placetype":"venue"
},
  "geometry": {"coordinates":[4.1306247711,51.2152671814],"type":"Point"}
}