{
  "type": "Feature",
  "properties": {
    "addr:full":"Rue Du Fourchufoss\u00c9 7 Li\u00c8ge Li\u00e8ge 4031",
    "addr:housenumber":"7",
    "addr:postcode":"4031",
    "addr:street":"Rue Du Fourchufosse\u0301",
    "iso:country":"BE",
    "sg:address":"Rue Du Fourchufoss\u00c9 7",
    "sg:city":"Li\u00c8ge",
    "sg:orig_category":"Instituts de beaut\u00e9",
    "sg:phone":"+32 4 365 33 66",
    "sg:postcode":"4031",
    "sg:province":"Li\u00e8ge",
    "wof:name":"Institut Privil\u00c8ge",
    "wof:placetype":"venue"
},
  "geometry": {"coordinates":[5.5913977623,50.613899231],"type":"Point"}
}