{
  "type": "Feature",
  "properties": {
    "addr:full":"Kermisstraat 62 Roeselare West-Vlaanderen 8800",
    "addr:housenumber":"62",
    "addr:postcode":"8800",
    "addr:street":"Kermisstraat",
    "iso:country":"BE",
    "sg:address":"Kermisstraat 62",
    "sg:city":"Roeselare",
    "sg:classifiers":[
        {
            "category":"Cafe",
            "type":"Food & Drink"
        }
    ],
    "sg:phone":"+32 51 24 32 52",
    "sg:postcode":"8800",
    "sg:province":"West-Vlaanderen",
    "sg:tags":[
        "caf\u00e9s"
    ],
    "wof:name":"Vercoutter & Depoortere",
    "wof:placetype":"venue"
},
  "geometry": {"coordinates":[3.1190578938,50.9427108765],"type":"Point"}
}