{
  "type": "Feature",
  "properties": {
    "addr:full":"Stationsstraat 46 Maldegem Oost-Vlaanderen 9990",
    "addr:housenumber":"46",
    "addr:postcode":"9990",
    "addr:street":"Stationsstraat",
    "iso:country":"BE",
    "sg:address":"Stationsstraat 46",
    "sg:city":"Maldegem",
    "sg:orig_category":"Pain, p\u00e2tisseries and confiseries",
    "sg:phone":"+32 50 71 14 53",
    "sg:postcode":"9990",
    "sg:province":"Oost-Vlaanderen",
    "wof:name":"Bakkerij Chris",
    "wof:placetype":"venue"
},
  "geometry": {"coordinates":[3.4482541084,51.2077674866],"type":"Point"}
}