{
  "type": "Feature",
  "properties": {
    "addr:full":"Boulevard International 55 Bruxelles (anderlecht) Bruxelles-Capitale 1070",
    "addr:housenumber":"55",
    "addr:postcode":"1070",
    "addr:street":"Boulevard International",
    "iso:country":"BE",
    "sg:address":"Boulevard International 55",
    "sg:city":"Bruxelles (anderlecht)",
    "sg:classifiers":[
        {
            "category":"Manufacturing",
            "subcategory":"Chemicals & Compounds",
            "type":"Manufacturing & Wholesale Goods"
        }
    ],
    "sg:phone":"+32 2 558 07 11",
    "sg:postcode":"1070",
    "sg:province":"Bruxelles-Capitale",
    "sg:tags":[
        "pharmaceutical",
        "product"
    ],
    "wof:name":"Yamanouchi Pharma Bv",
    "wof:placetype":"venue"
},
  "geometry": {"coordinates":[4.3070678711,50.8159446716],"type":"Point"}
}