{
  "type": "Feature",
  "properties": {
    "addr:full":"Kirchbusch 87 Lontzen Li\u00e8ge 4711",
    "addr:housenumber":"87",
    "addr:postcode":"4711",
    "addr:street":"Kirchbusch",
    "iso:country":"BE",
    "sg:address":"Kirchbusch 87",
    "sg:city":"Lontzen",
    "sg:orig_category":"Forge, Moulage and Profilage des M\u00e9taux",
    "sg:phone":"+32 87 65 92 55",
    "sg:postcode":"4711",
    "sg:province":"Li\u00e8ge",
    "wof:name":"Janssens",
    "wof:placetype":"venue"
},
  "geometry": {"coordinates":[6.047369957,50.6752853394],"type":"Point"}
}