{
  "type": "Feature",
  "properties": {
    "iso:country":"BE",
    "sg:address":"Ketterijstraat 80",
    "sg:city":"Sint-jan-in-eremo",
    "sg:orig_category":"Royal Canin",
    "sg:phone":"+32 9 378 89 73",
    "sg:postcode":"9982",
    "sg:province":"Oost-Vlaanderen",
    "wof:name":"Noteboom",
    "wof:placetype":"venue"
},
  "geometry": {"coordinates":[3.6125841141,51.2503318787],"type":"Point"}
}