{
  "type": "Feature",
  "properties": {
    "addr:full":"Vogelzang 7 Kuurne West-Vlaanderen 8520",
    "addr:housenumber":"7",
    "addr:postcode":"8520",
    "addr:street":"Vogelzang",
    "iso:country":"BE",
    "sg:address":"Vogelzang 7",
    "sg:city":"Kuurne",
    "sg:orig_category":"Erotische Etablissementen",
    "sg:phone":"+32 56 72 88 80",
    "sg:postcode":"8520",
    "sg:province":"West-Vlaanderen",
    "wof:name":"Astrid Bauwens",
    "wof:placetype":"venue"
},
  "geometry": {"coordinates":[3.2764909267,50.8629074097],"type":"Point"}
}