{
  "type": "Feature",
  "properties": {
    "iso:country":"BE",
    "sg:address":"Tieltse Baan 141",
    "sg:city":"Aarschot",
    "sg:classifiers":[
        {
            "category":"Cafe",
            "type":"Food & Drink"
        }
    ],
    "sg:phone":"+32 16 56 62 82",
    "sg:postcode":"3200",
    "sg:province":"Vlaams-Brabant",
    "sg:tags":[
        "caf\u00e9s"
    ],
    "wof:name":"Caf\u00c9 Bij Paula",
    "wof:placetype":"venue"
},
  "geometry": {"coordinates":[4.8494138718,50.9693984985],"type":"Point"}
}