{
  "type": "Feature",
  "properties": {
    "iso:country":"BE",
    "sg:address":"Rue Des Ecoles 55",
    "sg:city":"Comblain-au-pont",
    "sg:orig_category":"Services fun\u00e9raires",
    "sg:phone":"+32 4 365 68 51",
    "sg:postcode":"4171",
    "sg:province":"Li\u00e8ge",
    "wof:name":"Fun\u00c9railles Delperdange",
    "wof:placetype":"venue"
},
  "geometry": {"coordinates":[5.5834341049,50.5097770691],"type":"Point"}
}