{
  "type": "Feature",
  "properties": {
    "iso:country":"BE",
    "sg:address":"Nieuwpoortkeiweg 11",
    "sg:city":"Veurne",
    "sg:classifiers":[
        {
            "category":"Airport",
            "subcategory":"International",
            "type":"Transportation"
        }
    ],
    "sg:phone":"+32 58 31 63 73",
    "sg:postcode":"8630",
    "sg:province":"West-Vlaanderen",
    "sg:tags":[
        "-",
        "transport"
    ],
    "wof:name":"Patricktrans Bvba",
    "wof:placetype":"venue"
},
  "geometry": {"coordinates":[2.6681089401,51.0743408203],"type":"Point"}
}