{
  "type": "Feature",
  "properties": {
    "iso:country":"BE",
    "sg:address":"Emiel Claeyslaan 8",
    "sg:city":"Gent",
    "sg:classifiers":[
        {
            "category":"Sports & Exercise",
            "subcategory":"Sports Center",
            "type":"Entertainment"
        }
    ],
    "sg:phone":"+32 9 231 13 67",
    "sg:postcode":"9050",
    "sg:province":"Oost-Vlaanderen",
    "sg:tags":[
        "de",
        "fitness"
    ],
    "wof:name":"Jan Boone",
    "wof:placetype":"venue"
},
  "geometry": {"coordinates":[3.7716939449,51.0447769165],"type":"Point"}
}