{
  "type": "Feature",
  "properties": {
    "iso:country":"BE",
    "sg:address":"Galgeveldstraat 41",
    "sg:city":"Leuven",
    "sg:classifiers":[
        {
            "category":"Arena",
            "subcategory":"Sports Club",
            "type":"Entertainment"
        }
    ],
    "sg:phone":"+32 16 29 80 42",
    "sg:postcode":"3000",
    "sg:province":"Vlaams-Brabant",
    "sg:tags":[
        "terrain",
        "hors",
        "de",
        "installation",
        "sportifs"
    ],
    "wof:name":"Lovanium Tennis & Squash Club",
    "wof:placetype":"venue"
},
  "geometry": {"coordinates":[4.7036700249,50.8793869019],"type":"Point"}
}