{
  "type": "Feature",
  "properties": {
    "addr:full":"Rue De La Motte 20 Soignies Hainaut 7061",
    "addr:housenumber":"20",
    "addr:postcode":"7061",
    "addr:street":"Rue De La Motte",
    "iso:country":"BE",
    "sg:address":"Rue De La Motte 20",
    "sg:city":"Soignies",
    "sg:classifiers":[
        {
            "category":"Personal",
            "subcategory":"Beauty Salon",
            "type":"Services"
        }
    ],
    "sg:phone":"+32 65 72 44 49",
    "sg:postcode":"7061",
    "sg:province":"Hainaut",
    "sg:tags":[
        "de",
        "coiffure"
    ],
    "wof:name":"Coiffure Nouvelle Vague",
    "wof:placetype":"venue"
},
  "geometry": {"coordinates":[4.0133500099,50.5159416199],"type":"Point"}
}