{
  "type": "Feature",
  "properties": {
    "iso:country":"BE",
    "sg:address":"Hazeschransstraat 15",
    "sg:city":"Edegem",
    "sg:classifiers":[
        {
            "category":"Cafe",
            "type":"Food & Drink"
        }
    ],
    "sg:phone":"+32 3 449 94 21",
    "sg:postcode":"2650",
    "sg:province":"Antwerpen",
    "sg:tags":[
        "caf\u00e9s"
    ],
    "wof:name":"Inter-medium",
    "wof:placetype":"venue"
},
  "geometry": {"coordinates":[4.4249868393,51.1653709412],"type":"Point"}
}