{
  "type": "Feature",
  "properties": {
    "addr:full":"Schipstraat 38 Zonnebeke (passendale) West-Vlaanderen 8980",
    "addr:housenumber":"38",
    "addr:postcode":"8980",
    "addr:street":"Schipstraat",
    "iso:country":"BE",
    "sg:address":"Schipstraat 38",
    "sg:city":"Zonnebeke (passendale)",
    "sg:classifiers":[
        {
            "category":"Farming",
            "subcategory":"Crops",
            "type":"Manufacturing & Wholesale Goods"
        }
    ],
    "sg:phone":"+32 51 77 83 71",
    "sg:postcode":"8980",
    "sg:province":"West-Vlaanderen",
    "sg:tags":[
        "vegetable",
        "fruit",
        "-",
        "grower"
    ],
    "wof:name":"Vanlerberghe F",
    "wof:placetype":"venue"
},
  "geometry": {"coordinates":[2.9981470108,50.8820343018],"type":"Point"}
}