{
  "type": "Feature",
  "properties": {
    "iso:country":"BE",
    "sg:address":"Rue Jules Hoyois 7",
    "sg:city":"Mons (hyon)",
    "sg:classifiers":[
        {
            "category":"Communications",
            "subcategory":"Film & Video Production",
            "type":"Services"
        }
    ],
    "sg:phone":"+32 475 65 72 10",
    "sg:postcode":"7022",
    "sg:province":"Hainaut",
    "sg:tags":[
        "sound",
        "recording",
        "studio"
    ],
    "wof:name":"Oke Production",
    "wof:placetype":"venue"
},
  "geometry": {"coordinates":[3.96230793,50.4409179688],"type":"Point"}
}