{
  "type": "Feature",
  "properties": {
    "addr:full":"Chauss\u00e9e Roosevelt 42a Amay Li\u00e8ge 4540",
    "addr:housenumber":"42a",
    "addr:postcode":"4540",
    "addr:street":"Chausse\u0301E Roosevelt",
    "iso:country":"BE",
    "sg:address":"Chauss\u00e9e Roosevelt 42a",
    "sg:city":"Amay",
    "sg:classifiers":[
        {
            "category":"Personal",
            "subcategory":"Beauty Salon",
            "type":"Services"
        }
    ],
    "sg:phone":"+32 85 31 61 01",
    "sg:postcode":"4540",
    "sg:province":"Li\u00e8ge",
    "sg:tags":[
        "lady",
        "-",
        "hairdressing"
    ],
    "wof:name":"Cynthia Creation",
    "wof:placetype":"venue"
},
  "geometry": {"coordinates":[5.3151788712,50.5467376709],"type":"Point"}
}