{
  "type": "Feature",
  "properties": {
    "iso:country":"BE",
    "sg:address":"Meulevijverstraat 2",
    "sg:city":"Stekene",
    "sg:orig_category":"Groententeelt",
    "sg:phone":"+32 3 789 09 81",
    "sg:postcode":"9190",
    "sg:province":"Oost-Vlaanderen",
    "wof:name":"Gery Persoon",
    "wof:placetype":"venue"
},
  "geometry": {"coordinates":[4.0141658783,51.1842193604],"type":"Point"}
}