{
  "type": "Feature",
  "properties": {
    "iso:country":"BE",
    "sg:address":"Gasstraat 35",
    "sg:city":"Lokeren",
    "sg:orig_category":"Instituts de beaut\u00e9. Salons de coiffure",
    "sg:phone":"+32 9 348 27 15",
    "sg:postcode":"9160",
    "sg:province":"Oost-Vlaanderen",
    "wof:name":"Studio Marlou",
    "wof:placetype":"venue"
},
  "geometry": {"coordinates":[3.9841890335,51.1055297852],"type":"Point"}
}