{
  "type": "Feature",
  "properties": {
    "addr:full":"Pont Saint-laurent 10 Verviers Li\u00e8ge 4800",
    "addr:housenumber":"10",
    "addr:postcode":"4800",
    "addr:street":"Pont Saint-Laurent",
    "iso:country":"BE",
    "sg:address":"Pont Saint-laurent 10",
    "sg:city":"Verviers",
    "sg:classifiers":[
        {
            "category":"Restaurant",
            "type":"Food & Drink"
        }
    ],
    "sg:phone":"+32 87 33 39 50",
    "sg:postcode":"4800",
    "sg:province":"Li\u00e8ge",
    "sg:tags":[
        "caf\u00e9s"
    ],
    "wof:name":"Taverne The Red Ball",
    "wof:placetype":"venue"
},
  "geometry": {"coordinates":[5.8600330353,50.5928268433],"type":"Point"}
}