{
  "type": "Feature",
  "properties": {
    "iso:country":"BE",
    "sg:address":"Zevekotestraat 33",
    "sg:city":"Izegem",
    "sg:classifiers":[
        {
            "category":"Personal",
            "subcategory":"Nail Salon",
            "type":"Services"
        }
    ],
    "sg:phone":"+32 51 30 48 96",
    "sg:postcode":"8870",
    "sg:province":"West-Vlaanderen",
    "sg:tags":[
        "pedicure"
    ],
    "wof:name":"Demeester M",
    "wof:placetype":"venue"
},
  "geometry": {"coordinates":[3.2293300629,50.9154205322],"type":"Point"}
}