{
  "type": "Feature",
  "properties": {
    "addr:full":"Alphonse Claeys-bou\u00fcaertlaan 38 Gent (mariakerke) Oost-Vlaanderen 9030",
    "addr:housenumber":"38",
    "addr:postcode":"9030",
    "iso:country":"BE",
    "sg:address":"Alphonse Claeys-bou\u00fcaertlaan 38",
    "sg:city":"Gent (mariakerke)",
    "sg:classifiers":[
        {
            "category":"Health Services",
            "subcategory":"Dentist",
            "type":"Services"
        }
    ],
    "sg:phone":"+32 9 226 63 65",
    "sg:postcode":"9030",
    "sg:province":"Oost-Vlaanderen",
    "wof:name":"Vanhee M",
    "wof:placetype":"venue"
},
  "geometry": {"coordinates":[3.6767730713,51.0737304688],"type":"Point"}
}