{
  "type": "Feature",
  "properties": {
    "addr:full":"Recollettenstraat 47 Nieuwpoort West-Vlaanderen 8620",
    "addr:housenumber":"47",
    "addr:postcode":"8620",
    "addr:street":"Recollettenstraat",
    "iso:country":"BE",
    "sg:address":"Recollettenstraat 47",
    "sg:city":"Nieuwpoort",
    "sg:classifiers":[
        {
            "category":"Bars & Pubs",
            "type":"Food & Drink"
        }
    ],
    "sg:phone":"+32 58 23 05 70",
    "sg:postcode":"8620",
    "sg:province":"West-Vlaanderen",
    "wof:name":"'t Klavertje Vier",
    "wof:placetype":"venue"
},
  "geometry": {"coordinates":[2.7508199215,51.1297798157],"type":"Point"}
}