{
  "type": "Feature",
  "properties": {
    "iso:country":"BE",
    "sg:address":"Boomstraat 140",
    "sg:city":"Voeren/fourons",
    "sg:orig_category":"Groenten and fruit Gh",
    "sg:phone":"+32 4 381 14 57",
    "sg:postcode":"3798",
    "sg:province":"Limburg",
    "wof:name":"Fe. Heggen",
    "wof:placetype":"venue"
},
  "geometry": {"coordinates":[5.7603330612,50.7581443787],"type":"Point"}
}