{
  "type": "Feature",
  "properties": {
    "addr:full":"Avenue Jean Lambert 107 Verviers Li\u00e8ge 4801",
    "addr:housenumber":"107",
    "addr:postcode":"4801",
    "addr:street":"Avenue Jean Lambert",
    "iso:country":"BE",
    "sg:address":"Avenue Jean Lambert 107",
    "sg:city":"Verviers",
    "sg:orig_category":"Dansscholen",
    "sg:phone":"+32 87 23 11 67",
    "sg:postcode":"4801",
    "sg:province":"Li\u00e8ge",
    "wof:name":"Ecole De Danse Sart Swing",
    "wof:placetype":"venue"
},
  "geometry": {"coordinates":[5.8873229027,50.585899353],"type":"Point"}
}