{
  "type": "Feature",
  "properties": {
    "iso:country":"BE",
    "sg:address":"Rue Supexhe 87",
    "sg:city":"Blegny",
    "sg:orig_category":"Dakwerken Loodgieterij, verwarming and sanitaire installaties",
    "sg:phone":"+32 4 387 59 94",
    "sg:postcode":"4672",
    "sg:province":"Li\u00e8ge",
    "wof:name":"Franck Et Fils",
    "wof:placetype":"venue"
},
  "geometry": {"coordinates":[5.7018008232,50.6961021423],"type":"Point"}
}