{
  "type": "Feature",
  "properties": {
    "addr:full":"Kouter 29 Gent Oost-Vlaanderen 9000",
    "addr:housenumber":"29",
    "addr:postcode":"9000",
    "addr:street":"Kouter;Oost-Vlaanderen",
    "iso:country":"BE",
    "sg:address":"Kouter 29",
    "sg:city":"Gent",
    "sg:classifiers":[
        {
            "category":"Organizations",
            "subcategory":"Community Association",
            "type":"Services"
        }
    ],
    "sg:phone":"+32 9 265 91 63",
    "sg:postcode":"9000",
    "sg:province":"Oost-Vlaanderen",
    "sg:tags":[
        "cultural"
    ],
    "wof:name":"Noordstarfonds Vzw",
    "wof:placetype":"venue"
},
  "geometry": {"coordinates":[3.7228550911,51.0497283936],"type":"Point"}
}