{
  "type": "Feature",
  "properties": {
    "addr:full":"Kernemelkputstraat 2 Lichtervelde West-Vlaanderen 8810",
    "addr:housenumber":"2",
    "addr:postcode":"8810",
    "addr:street":"Kernemelkputstraat",
    "iso:country":"BE",
    "sg:address":"Kernemelkputstraat 2",
    "sg:city":"Lichtervelde",
    "sg:orig_category":"Groententeelt",
    "sg:phone":"+32 51 72 48 30",
    "sg:postcode":"8810",
    "sg:province":"West-Vlaanderen",
    "wof:name":"Gino De Smet",
    "wof:placetype":"venue"
},
  "geometry": {"coordinates":[3.1029579639,51.0207176208],"type":"Point"}
}