{
  "type": "Feature",
  "properties": {
    "iso:country":"BE",
    "sg:address":"Chauss\u00e9e Du Roeulx 1278",
    "sg:city":"Mons (havr\u00e9)",
    "sg:classifiers":[
        {
            "category":"Personal",
            "subcategory":"Nail Salon",
            "type":"Services"
        }
    ],
    "sg:phone":"+32 65 87 19 95",
    "sg:postcode":"7021",
    "sg:province":"Hainaut",
    "sg:tags":[
        "pedicure"
    ],
    "wof:name":"Colpaert S",
    "wof:placetype":"venue"
},
  "geometry": {"coordinates":[4.0562500954,50.4683494568],"type":"Point"}
}