{
  "type": "Feature",
  "properties": {
    "iso:country":"BE",
    "sg:address":"Rue De Bouvy 22",
    "sg:city":"La Louvi\u00e8re",
    "sg:classifiers":[
        {
            "category":"Health Services",
            "subcategory":"Health Practitioner",
            "type":"Services"
        }
    ],
    "sg:phone":"+32 64 26 69 78",
    "sg:postcode":"7100",
    "sg:province":"Hainaut",
    "sg:tags":[
        "physiotherapist"
    ],
    "wof:name":"Thomas Anne",
    "wof:placetype":"venue"
},
  "geometry": {"coordinates":[4.1855640411,50.4738578796],"type":"Point"}
}