{
  "type": "Feature",
  "properties": {
    "addr:full":"Rue Georges Truffaut 115 Ans Li\u00e8ge 4432",
    "addr:housenumber":"115",
    "addr:postcode":"4432",
    "addr:street":"Rue Georges Truffaut",
    "iso:country":"BE",
    "sg:address":"Rue Georges Truffaut 115",
    "sg:city":"Ans",
    "sg:classifiers":[
        {
            "category":"Insurance",
            "subcategory":"Insurance Agent",
            "type":"Services"
        }
    ],
    "sg:phone":"+32 4 263 68 88",
    "sg:postcode":"4432",
    "sg:province":"Li\u00e8ge",
    "sg:tags":[
        "verzekeringsmakelaars",
        "expert"
    ],
    "wof:name":"Georges Paques Et Fils",
    "wof:placetype":"venue"
},
  "geometry": {"coordinates":[5.5152001381,50.6771125793],"type":"Point"}
}