{
  "type": "Feature",
  "properties": {
    "addr:full":"Lodewijk Maesstraat 30 Kortenberg Vlaams-Brabant 3070",
    "addr:housenumber":"30",
    "addr:postcode":"3070",
    "addr:street":"Lodewijk Maesstraat;Vlaams-Brabant",
    "iso:country":"BE",
    "sg:address":"Lodewijk Maesstraat 30",
    "sg:city":"Kortenberg",
    "sg:orig_category":"Tabac. Journaux",
    "sg:phone":"+32 2 759 65 90",
    "sg:postcode":"3070",
    "sg:province":"Vlaams-Brabant",
    "wof:name":"Dagbladhandel Karter",
    "wof:placetype":"venue"
},
  "geometry": {"coordinates":[4.5394330025,50.886844635],"type":"Point"}
}