{
  "type": "Feature",
  "properties": {
    "addr:full":"Place 8 Incourt Brabant Wallon 1315",
    "addr:housenumber":"8",
    "addr:postcode":"1315",
    "iso:country":"BE",
    "sg:address":"Place 8",
    "sg:city":"Incourt",
    "sg:orig_category":"Enseignement maternel and primaire",
    "sg:phone":"+32 10 88 94 02",
    "sg:postcode":"1315",
    "sg:province":"Brabant Wallon",
    "wof:name":"Ecole Fond. Communale",
    "wof:placetype":"venue"
},
  "geometry": {"coordinates":[4.7959899902,50.6823196411],"type":"Point"}
}