{
  "type": "Feature",
  "properties": {
    "iso:country":"BE",
    "sg:address":"Hundelgemsesteenweg 1024bb",
    "sg:city":"Merelbeke",
    "sg:orig_category":"Herstellingen and onderhoud van auto's",
    "sg:phone":"+32 9 362 69 90",
    "sg:postcode":"9820",
    "sg:province":"Oost-Vlaanderen",
    "wof:name":"Antoine De Keukeleire",
    "wof:placetype":"venue"
},
  "geometry": {"coordinates":[3.7367539406,50.9729690552],"type":"Point"}
}