{
  "type": "Feature",
  "properties": {
    "iso:country":"BE",
    "sg:address":"Solterbosstraat 35",
    "sg:city":"Maaseik (neeroeteren)",
    "sg:classifiers":[
        {
            "category":"Wholesale",
            "subcategory":"Fruits & Vegetables",
            "type":"Manufacturing & Wholesale Goods"
        }
    ],
    "sg:phone":"+32 89 86 82 72",
    "sg:postcode":"3680",
    "sg:province":"Limburg",
    "sg:tags":[
        "whol",
        "-"
    ],
    "wof:name":"Linthe Bvba",
    "wof:placetype":"venue"
},
  "geometry": {"coordinates":[5.791285038,51.0954208374],"type":"Point"}
}