{
  "type": "Feature",
  "properties": {
    "iso:country":"BE",
    "sg:address":"Klabbeeksesteenweg 281",
    "sg:city":"Halle",
    "sg:orig_category":"Rev\u00eatements de sols and murs. Quincailleries",
    "sg:phone":"+32 2 361 01 86",
    "sg:postcode":"1502",
    "sg:province":"Vlaams-Brabant",
    "wof:name":"Budex",
    "wof:placetype":"venue"
},
  "geometry": {"coordinates":[4.2172598839,50.7040710449],"type":"Point"}
}