{
  "type": "Feature",
  "properties": {
    "addr:full":"Vestenstraat 17 Tervuren Vlaams-Brabant 3080",
    "addr:housenumber":"17",
    "addr:postcode":"3080",
    "addr:street":"Vestenstraat",
    "iso:country":"BE",
    "sg:address":"Vestenstraat 17",
    "sg:city":"Tervuren",
    "sg:classifiers":[
        {
            "category":"Utilities",
            "subcategory":"Natural Gas",
            "type":"Services"
        }
    ],
    "sg:phone":"+32 2 767 31 84",
    "sg:postcode":"3080",
    "sg:province":"Vlaams-Brabant",
    "sg:tags":[
        "hide",
        "skin"
    ],
    "wof:name":"Agimbo-m Bossuyt",
    "wof:placetype":"venue"
},
  "geometry": {"coordinates":[4.5041298866,50.8224258423],"type":"Point"}
}