{
  "type": "Feature",
  "properties": {
    "iso:country":"BE",
    "sg:address":"Chauss\u00c9e D\u00b4ixelles 19",
    "sg:city":"Elsene/ixelles",
    "sg:orig_category":"Opticiens",
    "sg:phone":"+32 2 513 24 46",
    "sg:postcode":"1050",
    "sg:province":"Bruxelles-Capitale",
    "wof:name":"Pearle Vision Center",
    "wof:placetype":"venue"
},
  "geometry": {"coordinates":[4.3621292114,50.8376274109],"type":"Point"}
}