{
  "type": "Feature",
  "properties": {
    "addr:full":"Chemin Des Ecoliers 1 Welkenraedt Li\u00e8ge 4841",
    "addr:housenumber":"1",
    "addr:postcode":"4841",
    "addr:street":"Chemin Des Ecoliers",
    "iso:country":"BE",
    "sg:address":"Chemin Des Ecoliers 1",
    "sg:city":"Welkenraedt",
    "sg:orig_category":"Enseignement maternel and primaire",
    "sg:phone":"+32 87 88 01 39",
    "sg:postcode":"4841",
    "sg:province":"Li\u00e8ge",
    "wof:name":"Ecole Fond. Communale",
    "wof:placetype":"venue"
},
  "geometry": {"coordinates":[5.9305949211,50.6758232117],"type":"Point"}
}