{
  "type": "Feature",
  "properties": {
    "addr:full":"Dorpstraat 80 Lierde (sint-maria-lierde) Oost-Vlaanderen 9570",
    "addr:housenumber":"80",
    "addr:postcode":"9570",
    "addr:street":"Dorpstraat",
    "iso:country":"BE",
    "sg:address":"Dorpstraat 80",
    "sg:city":"Lierde (sint-maria-lierde)",
    "sg:classifiers":[
        {
            "category":"Professional",
            "subcategory":"Engineering",
            "type":"Services"
        }
    ],
    "sg:phone":"+32 55 42 49 40",
    "sg:postcode":"9570",
    "sg:province":"Oost-Vlaanderen",
    "sg:tags":[
        "industrial",
        "-",
        "automation"
    ],
    "wof:name":"Hd-engineering Bvba",
    "wof:placetype":"venue"
},
  "geometry": {"coordinates":[3.8449780941,50.8222503662],"type":"Point"}
}