{
  "type": "Feature",
  "properties": {
    "iso:country":"BE",
    "sg:address":"Rue Houdret 27",
    "sg:city":"Ans",
    "sg:classifiers":[
        {
            "category":"Arena",
            "subcategory":"Sports Club",
            "type":"Entertainment"
        }
    ],
    "sg:phone":"+32 4 226 99 56",
    "sg:postcode":"4430",
    "sg:province":"Li\u00e8ge",
    "sg:tags":[
        "terrain",
        "hors",
        "de",
        "installation",
        "sportifs"
    ],
    "wof:name":"Union Communale D'ans",
    "wof:placetype":"venue"
},
  "geometry": {"coordinates":[5.5405349731,50.6511306763],"type":"Point"}
}