{
  "type": "Feature",
  "properties": {
    "iso:country":"BE",
    "sg:address":"Rue Albert Ier 159",
    "sg:city":"Erquelinnes",
    "sg:orig_category":"Pharmaciens",
    "sg:phone":"+32 71 55 55 62",
    "sg:postcode":"6560",
    "sg:province":"Hainaut",
    "wof:name":"Pharmacie Vanderick-bruyr",
    "wof:placetype":"venue"
},
  "geometry": {"coordinates":[4.1169528961,50.3070602417],"type":"Point"}
}