{
  "type": "Feature",
  "properties": {
    "addr:full":"Boezingepad 21 Blankenberge West-Vlaanderen 8370",
    "addr:housenumber":"21",
    "addr:postcode":"8370",
    "addr:street":"Boezingepad",
    "iso:country":"BE",
    "sg:address":"Boezingepad 21",
    "sg:city":"Blankenberge",
    "sg:classifiers":[
        {
            "category":"Food & Beverages",
            "subcategory":"Meat & Fish",
            "type":"Retail Goods"
        }
    ],
    "sg:phone":"+32 50 41 36 58",
    "sg:postcode":"8370",
    "sg:province":"West-Vlaanderen",
    "sg:tags":[
        "vi",
        "zeevruchten"
    ],
    "wof:name":"Anna Van Hyfte",
    "wof:placetype":"venue"
},
  "geometry": {"coordinates":[3.1205189228,51.3063850403],"type":"Point"}
}