{
  "type": "Feature",
  "properties": {
    "iso:country":"BE",
    "sg:address":"Rue De Fooz 200",
    "sg:city":"Fexhe-le-haut-clocher",
    "sg:classifiers":[
        {
            "category":"Communications",
            "subcategory":"Film & Video Production",
            "type":"Services"
        }
    ],
    "sg:phone":"+32 4 250 48 75",
    "sg:postcode":"4347",
    "sg:province":"Li\u00e8ge",
    "sg:tags":[
        "realisation",
        "-"
    ],
    "wof:name":"Huc B",
    "wof:placetype":"venue"
},
  "geometry": {"coordinates":[5.4037499428,50.6683006287],"type":"Point"}
}