{
  "type": "Feature",
  "properties": {
    "iso:country":"BE",
    "sg:address":"Casinostraat 22",
    "sg:city":"Sint-niklaas",
    "sg:orig_category":"Architecten",
    "sg:phone":"+32 3 778 09 34",
    "sg:postcode":"9100",
    "sg:province":"Oost-Vlaanderen",
    "wof:name":"Vandecappelle P.",
    "wof:placetype":"venue"
},
  "geometry": {"coordinates":[4.1396350861,51.1691703796],"type":"Point"}
}