{
  "type": "Feature",
  "properties": {
    "addr:full":"Krekelstraat 47 Zwalm Oost-Vlaanderen 9630",
    "addr:housenumber":"47",
    "addr:postcode":"9630",
    "addr:street":"Krekelstraat;Oost-Vlaanderen",
    "iso:country":"BE",
    "sg:address":"Krekelstraat 47",
    "sg:city":"Zwalm",
    "sg:classifiers":[
        {
            "category":"Cafe",
            "type":"Food & Drink"
        }
    ],
    "sg:phone":"+32 55 49 71 67",
    "sg:postcode":"9630",
    "sg:province":"Oost-Vlaanderen",
    "sg:tags":[
        "caf\u00e9s"
    ],
    "wof:name":"Eddy De Neve",
    "wof:placetype":"venue"
},
  "geometry": {"coordinates":[3.7477560043,50.8810348511],"type":"Point"}
}