{
  "type": "Feature",
  "properties": {
    "iso:country":"BE",
    "sg:address":"Rene Colaertplein 11",
    "sg:city":"Ieper",
    "sg:orig_category":"M\u00e9decins and sp\u00e9cialistes",
    "sg:phone":"+32 57 20 09 18",
    "sg:postcode":"8900",
    "sg:province":"West-Vlaanderen",
    "wof:name":"Henri-albert Lamiroy",
    "wof:placetype":"venue"
},
  "geometry": {"coordinates":[2.8774719238,50.8492431641],"type":"Point"}
}