{
  "type": "Feature",
  "properties": {
    "iso:country":"BE",
    "sg:address":"'s-heer Boudewijnsburg 69a",
    "sg:city":"Brugge (assebroek)",
    "sg:classifiers":[
        {
            "category":"Airport",
            "subcategory":"International",
            "type":"Transportation"
        }
    ],
    "sg:phone":"+32 50 54 82 93",
    "sg:postcode":"8310",
    "sg:province":"West-Vlaanderen",
    "sg:tags":[
        "-",
        "transport"
    ],
    "wof:name":"Robbetrans Bvba",
    "wof:placetype":"venue"
},
  "geometry": {"coordinates":[3.2463879585,51.1878356934],"type":"Point"}
}