{
  "type": "Feature",
  "properties": {
    "addr:full":"Hinnenboomstraat 26 Hoogstraten Antwerpen 2320",
    "addr:housenumber":"26",
    "addr:postcode":"2320",
    "addr:street":"Hinnenboomstraat",
    "iso:country":"BE",
    "sg:address":"Hinnenboomstraat 26",
    "sg:city":"Hoogstraten",
    "sg:orig_category":"Transports routiers de marchandises",
    "sg:phone":"+32 3 314 51 36",
    "sg:postcode":"2320",
    "sg:province":"Antwerpen",
    "wof:name":"C En J Transport",
    "wof:placetype":"venue"
},
  "geometry": {"coordinates":[4.7242507935,51.4064331055],"type":"Point"}
}