{
  "type": "Feature",
  "properties": {
    "addr:full":"Grand-place De Feluy 3 Seneffe Hainaut 7181",
    "addr:housenumber":"3",
    "addr:postcode":"7181",
    "addr:street":"Grand-Place;Feluy",
    "iso:country":"BE",
    "sg:address":"Grand-place De Feluy 3",
    "sg:city":"Seneffe",
    "sg:orig_category":"Woningbouw",
    "sg:phone":"+32 67 87 95 18",
    "sg:postcode":"7181",
    "sg:province":"Hainaut",
    "wof:name":"Reno-d\u00c9cor",
    "wof:placetype":"venue"
},
  "geometry": {"coordinates":[4.2507171631,50.5634117126],"type":"Point"}
}