{
  "type": "Feature",
  "properties": {
    "addr:full":"Aarschotseweg 2 Herentals Antwerpen 2200",
    "addr:housenumber":"2",
    "addr:postcode":"2200",
    "addr:street":"Aarschotseweg",
    "iso:country":"BE",
    "sg:address":"Aarschotseweg 2",
    "sg:city":"Herentals",
    "sg:orig_category":"Afbraak- and draineerwerken",
    "sg:phone":"+32 14 21 14 91",
    "sg:postcode":"2200",
    "sg:province":"Antwerpen",
    "wof:name":"De Cnodder",
    "wof:placetype":"venue"
},
  "geometry": {"coordinates":[4.8471398354,51.1667404175],"type":"Point"}
}