{
  "type": "Feature",
  "properties": {
    "addr:full":"Schriekstraat 72 Laarne (kalken) Oost-Vlaanderen 9270",
    "addr:housenumber":"72",
    "addr:postcode":"9270",
    "addr:street":"Schriekstraat",
    "iso:country":"BE",
    "sg:address":"Schriekstraat 72",
    "sg:city":"Laarne (kalken)",
    "sg:classifiers":[
        {
            "category":"Autos & Motor Vehicles",
            "subcategory":"Motorcycle Sales",
            "type":"Retail Goods"
        }
    ],
    "sg:phone":"+32 9 357 49 36",
    "sg:postcode":"9270",
    "sg:province":"Oost-Vlaanderen",
    "sg:tags":[
        "motorbike"
    ],
    "wof:name":"Off-road Center",
    "wof:placetype":"venue"
},
  "geometry": {"coordinates":[3.910531044,51.049156189],"type":"Point"}
}