{
  "type": "Feature",
  "properties": {
    "addr:full":"Grote Markt 4 Sint-niklaas Oost-Vlaanderen 9100",
    "addr:housenumber":"4",
    "addr:postcode":"9100",
    "addr:street":"Grote Markt",
    "iso:country":"BE",
    "sg:address":"Grote Markt 4",
    "sg:city":"Sint-niklaas",
    "sg:orig_category":"Winkelinrichting and handelsuitrusting Gh",
    "sg:phone":"+32 3 777 86 40",
    "sg:postcode":"9100",
    "sg:province":"Oost-Vlaanderen",
    "wof:name":"Pro-duo",
    "wof:placetype":"venue"
},
  "geometry": {"coordinates":[4.1389260292,51.1642227173],"type":"Point"}
}