{
  "type": "Feature",
  "properties": {
    "addr:full":"Zandvoordestraat 28 Oostende West-Vlaanderen 8400",
    "addr:housenumber":"28",
    "addr:postcode":"8400",
    "addr:street":"Zandvoordestraat",
    "iso:country":"BE",
    "sg:address":"Zandvoordestraat 28",
    "sg:city":"Oostende",
    "sg:classifiers":[
        {
            "category":"Food & Beverages",
            "subcategory":"Fruits & Vegetables",
            "type":"Retail Goods"
        }
    ],
    "sg:phone":"+32 59 50 59 11",
    "sg:postcode":"8400",
    "sg:province":"West-Vlaanderen",
    "sg:tags":[
        "-"
    ],
    "wof:name":"Fruithoek (de)",
    "wof:placetype":"venue"
},
  "geometry": {"coordinates":[2.9365670681,51.2165031433],"type":"Point"}
}