{
  "type": "Feature",
  "properties": {
    "addr:full":"Rue Rabelais 18 Louvain-la-neuve Brabant Wallon 1340",
    "addr:housenumber":"18",
    "addr:postcode":"1340",
    "addr:street":"Rue Rabelais",
    "iso:country":"BE",
    "sg:address":"Rue Rabelais 18",
    "sg:city":"Louvain-la-neuve",
    "sg:classifiers":[
        {
            "category":"Restaurant",
            "type":"Food & Drink"
        }
    ],
    "sg:phone":"+32 10 41 45 32",
    "sg:postcode":"1340",
    "sg:province":"Brabant Wallon",
    "wof:name":"La Couscousi\u00c8re",
    "wof:placetype":"venue"
},
  "geometry": {"coordinates":[4.6129808426,50.669254303],"type":"Point"}
}