{
  "type": "Feature",
  "properties": {
    "addr:full":"Oude Zandstraat 98 Beveren Oost-Vlaanderen 9120",
    "addr:housenumber":"98",
    "addr:postcode":"9120",
    "addr:street":"Oude Zandstraat",
    "iso:country":"BE",
    "sg:address":"Oude Zandstraat 98",
    "sg:city":"Beveren",
    "sg:orig_category":"Maisons de repos and r\u00e9sidences",
    "sg:phone":"+32 3 750 92 00",
    "sg:postcode":"9120",
    "sg:province":"Oost-Vlaanderen",
    "wof:name":"Rustoord De Notelaar",
    "wof:placetype":"venue"
},
  "geometry": {"coordinates":[4.2498512268,51.2101860046],"type":"Point"}
}