{
  "type": "Feature",
  "properties": {
    "iso:country":"BE",
    "sg:address":"Large Voie 124",
    "sg:city":"Herstal",
    "sg:classifiers":[
        {
            "category":"Wholesale",
            "subcategory":"Medical Equipment & Supplies",
            "type":"Manufacturing & Wholesale Goods"
        }
    ],
    "sg:phone":"+32 4 248 12 44",
    "sg:postcode":"4040",
    "sg:province":"Li\u00e8ge",
    "sg:tags":[
        "instrument",
        "health",
        "-",
        "precision"
    ],
    "wof:name":"Dangelo Giuseppe M.",
    "wof:placetype":"venue"
},
  "geometry": {"coordinates":[5.6353211403,50.6672210693],"type":"Point"}
}