{
  "type": "Feature",
  "properties": {
    "iso:country":"BE",
    "sg:address":"Nijvelsesteenweg 438",
    "sg:city":"Halle",
    "sg:classifiers":[
        {
            "category":"Personal",
            "subcategory":"Massage",
            "type":"Services"
        }
    ],
    "sg:phone":"+32 2 356 79 62",
    "sg:postcode":"1500",
    "sg:province":"Vlaams-Brabant",
    "wof:name":"Salon De Massage",
    "wof:placetype":"venue"
},
  "geometry": {"coordinates":[4.2498221397,50.7215957642],"type":"Point"}
}