{
  "type": "Feature",
  "properties": {
    "iso:country":"BE",
    "sg:address":"Diepenbekerweg 10",
    "sg:city":"Hasselt",
    "sg:orig_category":"Diverse opleidingen and onderwijs",
    "sg:phone":"+32 11 26 59 99",
    "sg:postcode":"3500",
    "sg:province":"Limburg",
    "wof:name":"Vidaq",
    "wof:placetype":"venue"
},
  "geometry": {"coordinates":[5.3620529175,50.925994873],"type":"Point"}
}