{
  "type": "Feature",
  "properties": {
    "addr:full":"Rue Velbruck 4 Li\u00c8ge Li\u00e8ge 4000",
    "addr:housenumber":"4",
    "addr:postcode":"4000",
    "addr:street":"Rue Velbruck",
    "iso:country":"BE",
    "sg:address":"Rue Velbruck 4",
    "sg:city":"Li\u00c8ge",
    "sg:orig_category":"Agences immobili\u00e8res",
    "sg:phone":"+32 4 232 31 20",
    "sg:postcode":"4000",
    "sg:province":"Li\u00e8ge",
    "wof:name":"B.r.i.c.",
    "wof:placetype":"venue"
},
  "geometry": {"coordinates":[5.5793509483,50.6469078064],"type":"Point"}
}