{
  "type": "Feature",
  "properties": {
    "addr:full":"Sti\u00e9niha 36 Marchin Li\u00e8ge 4570",
    "addr:housenumber":"36",
    "addr:postcode":"4570",
    "addr:street":"Stie\u0301Niha",
    "iso:country":"BE",
    "sg:address":"Sti\u00e9niha 36",
    "sg:city":"Marchin",
    "sg:classifiers":[
        {
            "category":"Professional",
            "subcategory":"Printing & Photocopies",
            "type":"Services"
        }
    ],
    "sg:phone":"+32 85 23 53 50",
    "sg:postcode":"4570",
    "sg:province":"Li\u00e8ge",
    "sg:tags":[
        "trophy",
        "medal"
    ],
    "wof:name":"Bibloterie (la)",
    "wof:placetype":"venue"
},
  "geometry": {"coordinates":[5.2289562225,50.4887046814],"type":"Point"}
}