{
  "type": "Feature",
  "properties": {
    "addr:full":"Avenue Reine-astrid 27 Nivelles Brabant Wallon 1401",
    "addr:housenumber":"27;1401",
    "addr:street":"Avenue Reine-Astrid",
    "iso:country":"BE",
    "sg:address":"Avenue Reine-astrid 27",
    "sg:city":"Nivelles",
    "sg:orig_category":"V\u00e9t\u00e9rinaires",
    "sg:phone":"+32 67 21 36 63",
    "sg:postcode":"1401",
    "sg:province":"Brabant Wallon",
    "wof:name":"Isabelle Donnay",
    "wof:placetype":"venue"
},
  "geometry": {"coordinates":[4.3463630676,50.6060943604],"type":"Point"}
}