{
  "type": "Feature",
  "properties": {
    "iso:country":"BE",
    "sg:address":"Place De Molenbaix 24",
    "sg:city":"Celles",
    "sg:orig_category":"Sportclubs Sportterreinen and installaties behalve sportcentra",
    "sg:phone":"+32 69 45 49 50",
    "sg:postcode":"7760",
    "sg:province":"Hainaut",
    "wof:name":"F.c. Molenbaix",
    "wof:placetype":"venue"
},
  "geometry": {"coordinates":[3.4301600456,50.6927490234],"type":"Point"}
}