{
  "type": "Feature",
  "properties": {
    "iso:country":"BE",
    "sg:address":"Eygenweg 80",
    "sg:city":"Beringen (beverlo)",
    "sg:classifiers":[
        {
            "category":"Health Services",
            "subcategory":"Health Practitioner",
            "type":"Services"
        }
    ],
    "sg:phone":"+32 11 34 34 67",
    "sg:postcode":"3581",
    "sg:province":"Limburg",
    "sg:tags":[
        "psychologist"
    ],
    "wof:name":"Vandermeeren R",
    "wof:placetype":"venue"
},
  "geometry": {"coordinates":[5.2073521614,51.086807251],"type":"Point"}
}