{
  "type": "Feature",
  "properties": {
    "iso:country":"BE",
    "sg:address":"Rue De La Concorde 10",
    "sg:city":"Charleroi (marcinelle)",
    "sg:orig_category":"Non-Classified Establishments",
    "sg:phone":"+32 71 36 21 33",
    "sg:postcode":"6001",
    "sg:province":"Hainaut",
    "wof:name":"Coq Import Sprl",
    "wof:placetype":"venue"
},
  "geometry": {"coordinates":[4.4689822197,50.4169578552],"type":"Point"}
}