{
  "type": "Feature",
  "properties": {
    "addr:full":"Roosendaalsebaan 153 Kalmthout Antwerpen 2920",
    "addr:housenumber":"153",
    "addr:postcode":"2920",
    "addr:street":"Roosendaalsebaan",
    "iso:country":"BE",
    "sg:address":"Roosendaalsebaan 153",
    "sg:city":"Kalmthout",
    "sg:orig_category":"Non-Classified Establishments",
    "sg:phone":"+32 3 666 16 75",
    "sg:postcode":"2920",
    "sg:province":"Antwerpen",
    "wof:name":"Los A Handelsonderneming",
    "wof:placetype":"venue"
},
  "geometry": {"coordinates":[4.495467186,51.4125518799],"type":"Point"}
}