{
  "type": "Feature",
  "properties": {
    "addr:full":"Provincieweg 324 Herzele Oost-Vlaanderen 9550",
    "addr:housenumber":"324",
    "addr:postcode":"9550",
    "addr:street":"Provincieweg;Oost-Vlaanderen",
    "iso:country":"BE",
    "sg:address":"Provincieweg 324",
    "sg:city":"Herzele",
    "sg:classifiers":[
        {
            "category":"Communications",
            "subcategory":"Television Station",
            "type":"Services"
        }
    ],
    "sg:phone":"+32 53 62 74 78",
    "sg:postcode":"9550",
    "sg:province":"Oost-Vlaanderen",
    "sg:tags":[
        "report",
        "video"
    ],
    "wof:name":"Van Droogenbroeck G",
    "wof:placetype":"venue"
},
  "geometry": {"coordinates":[3.8787400723,50.8998908997],"type":"Point"}
}