{
  "type": "Feature",
  "properties": {
    "iso:country":"BE",
    "sg:address":"Aartrijkestraat 115",
    "sg:city":"Torhout",
    "sg:classifiers":[
        {
            "category":"Personal",
            "subcategory":"Beauty Salon",
            "type":"Services"
        }
    ],
    "sg:phone":"+32 50 22 01 95",
    "sg:postcode":"8820",
    "sg:province":"West-Vlaanderen",
    "sg:tags":[
        "lady",
        "-",
        "hairdressing"
    ],
    "wof:name":"Vansteelandt",
    "wof:placetype":"venue"
},
  "geometry": {"coordinates":[3.0981070995,51.0774917603],"type":"Point"}
}