{
  "type": "Feature",
  "properties": {
    "addr:full":"Rode Kruislaan 309a Bilzen (rijkhoven) Limburg 3740",
    "addr:housenumber":"309a",
    "addr:postcode":"3740",
    "addr:street":"Rode Kruislaan",
    "iso:country":"BE",
    "sg:address":"Rode Kruislaan 309a",
    "sg:city":"Bilzen (rijkhoven)",
    "sg:classifiers":[
        {
            "category":"Shopping",
            "subcategory":"Jewelry",
            "type":"Retail Goods"
        }
    ],
    "sg:phone":"+32 12 23 71 73",
    "sg:postcode":"3740",
    "sg:province":"Limburg",
    "sg:tags":[
        "jeweller",
        "-"
    ],
    "wof:name":"Motten R&l",
    "wof:placetype":"venue"
},
  "geometry": {"coordinates":[5.5219898224,50.8243598938],"type":"Point"}
}