{
  "type": "Feature",
  "properties": {
    "iso:country":"BE",
    "sg:address":"Rijksweg 589",
    "sg:city":"Maasmechelen",
    "sg:classifiers":[
        {
            "category":"Home & Garden",
            "subcategory":"Carpets & Floor Coverings",
            "type":"Retail Goods"
        }
    ],
    "sg:phone":"+32 89 76 25 49",
    "sg:postcode":"3630",
    "sg:province":"Limburg",
    "sg:tags":[
        "tile"
    ],
    "wof:name":"Dalemans Exclusief Bvba",
    "wof:placetype":"venue"
},
  "geometry": {"coordinates":[5.6945180893,50.9554595947],"type":"Point"}
}