{
  "type": "Feature",
  "properties": {
    "addr:full":"Rue Mosselman 19 Li\u00e8ge 1 Li\u00e8ge 4000",
    "addr:housenumber":"19;1",
    "addr:postcode":"4000",
    "addr:street":"Rue Mosselman",
    "iso:country":"BE",
    "sg:address":"Rue Mosselman 19",
    "sg:city":"Li\u00e8ge 1",
    "sg:classifiers":[
        {
            "category":"Personal",
            "subcategory":"Beauty Salon",
            "type":"Services"
        }
    ],
    "sg:phone":"+32 4 227 28 26",
    "sg:postcode":"4000",
    "sg:province":"Li\u00e8ge",
    "sg:tags":[
        "lady",
        "-",
        "hairdressing"
    ],
    "wof:name":"Claudine",
    "wof:placetype":"venue"
},
  "geometry": {"coordinates":[5.5916361809,50.6499938965],"type":"Point"}
}