{
  "type": "Feature",
  "properties": {
    "addr:full":"Zwarte Nonnenstraat 16 Veurne West-Vlaanderen 8630",
    "addr:housenumber":"16",
    "addr:postcode":"8630",
    "addr:street":"Zwarte Nonnenstraat",
    "iso:country":"BE",
    "sg:address":"Zwarte Nonnenstraat 16",
    "sg:city":"Veurne",
    "sg:orig_category":"Artsen and specialisten",
    "sg:phone":"+32 58 31 14 43",
    "sg:postcode":"8630",
    "sg:province":"West-Vlaanderen",
    "wof:name":"Edgard Verschelden",
    "wof:placetype":"venue"
},
  "geometry": {"coordinates":[2.6589820385,51.0731239319],"type":"Point"}
}