{
  "type": "Feature",
  "properties": {
    "iso:country":"BE",
    "sg:address":"Rue Des Tomballes 74",
    "sg:city":"Seraing (jemeppe-sur-meuse)",
    "sg:classifiers":[
        {
            "category":"Health Services",
            "subcategory":"Health Practitioner",
            "type":"Services"
        }
    ],
    "sg:phone":"+32 4 234 38 58",
    "sg:postcode":"4101",
    "sg:province":"Li\u00e8ge",
    "sg:tags":[
        "physiotherapist"
    ],
    "wof:name":"Scarinci Ferdinand",
    "wof:placetype":"venue"
},
  "geometry": {"coordinates":[5.4954571724,50.6206169128],"type":"Point"}
}