{
  "type": "Feature",
  "properties": {
    "addr:full":"Salvatorstraat 20 Hasselt Limburg 3500",
    "addr:housenumber":"20",
    "addr:postcode":"3500",
    "addr:street":"Salvatorstraat",
    "iso:country":"BE",
    "sg:address":"Salvatorstraat 20",
    "sg:city":"Hasselt",
    "sg:classifiers":[
        {
            "category":"Health Services",
            "subcategory":"Hospital",
            "type":"Services"
        }
    ],
    "sg:phone":"+32 11 28 91 11",
    "sg:postcode":"3500",
    "sg:province":"Limburg",
    "wof:name":"Christelijk Algemeen Ziekenhuis Midden-limburg",
    "wof:placetype":"venue"
},
  "geometry": {"coordinates":[5.344534874,50.9130706787],"type":"Point"}
}