{
  "type": "Feature",
  "properties": {
    "iso:country":"BE",
    "sg:address":"Sweden House - Rue Du Luxembourg 3 -",
    "sg:city":"Brussels",
    "sg:classifiers":[
        {
            "category":"Professional",
            "subcategory":"Art Services",
            "type":"Services"
        }
    ],
    "sg:phone":"+32 2 289 57 60",
    "sg:postcode":"1000",
    "sg:province":"Bruxelles-Capitale",
    "sg:tags":[
        "export-import"
    ],
    "wof:name":"Sweden Embassy",
    "wof:placetype":"venue"
},
  "geometry": {"coordinates":[4.3662691116,50.8403511047],"type":"Point"}
}