{
  "type": "Feature",
  "properties": {
    "addr:full":"Rue De Haerne 126 Etterbeek/etterbeek Bruxelles-Capitale 1040",
    "addr:housenumber":"126",
    "addr:postcode":"1040",
    "addr:street":"Rue De Haerne",
    "iso:country":"BE",
    "sg:address":"Rue De Haerne 126",
    "sg:city":"Etterbeek/etterbeek",
    "sg:classifiers":[
        {
            "category":"Personal",
            "subcategory":"Beauty Salon",
            "type":"Services"
        }
    ],
    "sg:phone":"+32 2 648 10 73",
    "sg:postcode":"1040",
    "sg:province":"Bruxelles-Capitale",
    "sg:tags":[
        "de",
        "coiffure"
    ],
    "wof:name":"Coiffure Martinot",
    "wof:placetype":"venue"
},
  "geometry": {"coordinates":[4.3838381767,50.829246521],"type":"Point"}
}