{
  "type": "Feature",
  "properties": {
    "addr:full":"Industriestraat 29 Ruiselede West-Vlaanderen 8750",
    "addr:housenumber":"29",
    "addr:postcode":"8750",
    "addr:street":"Industriestraat",
    "iso:country":"BE",
    "sg:address":"Industriestraat 29",
    "sg:city":"Ruiselede",
    "sg:classifiers":[
        {
            "category":"Manufacturing",
            "subcategory":"Paper Products",
            "type":"Manufacturing & Wholesale Goods"
        }
    ],
    "sg:phone":"+32 51 68 74 74",
    "sg:postcode":"8750",
    "sg:province":"West-Vlaanderen",
    "sg:tags":[
        "packaging",
        "material",
        "-",
        "cardboard"
    ],
    "wof:name":"Kartonnage Van Acker Marcel Bvba",
    "wof:placetype":"venue"
},
  "geometry": {"coordinates":[3.4082329273,51.0467567444],"type":"Point"}
}