{
  "type": "Feature",
  "properties": {
    "iso:country":"BE",
    "sg:address":"Rue Mitant Des Camps 127",
    "sg:city":"La Louviere",
    "sg:orig_category":"Boucheries",
    "sg:phone":"+32 64 21 36 99",
    "sg:postcode":"7100",
    "sg:province":"Hainaut",
    "wof:name":"Vitale Baiardo",
    "wof:placetype":"venue"
},
  "geometry": {"coordinates":[4.1863279343,50.4678382874],"type":"Point"}
}