{
  "type": "Feature",
  "properties": {
    "addr:full":"Steenweg 24 Mechelen Antwerpen 2800",
    "addr:housenumber":"24",
    "addr:postcode":"2800",
    "addr:street":"Steenweg",
    "iso:country":"BE",
    "sg:address":"Steenweg 24",
    "sg:city":"Mechelen",
    "sg:classifiers":[
        {
            "category":"Retail",
            "subcategory":"Laundry & Dry Cleaning",
            "type":"Services"
        }
    ],
    "sg:phone":"+32 15 20 72 15",
    "sg:postcode":"2800",
    "sg:province":"Antwerpen",
    "sg:tags":[
        "dyer",
        "cleaner"
    ],
    "wof:name":"Royal Clean",
    "wof:placetype":"venue"
},
  "geometry": {"coordinates":[4.4788408279,51.0282478333],"type":"Point"}
}