{
  "type": "Feature",
  "properties": {
    "iso:country":"BE",
    "sg:address":"Grote Moerstraat 78",
    "sg:city":"Brugge",
    "sg:orig_category":"Binnenhuisarchitecten Diverse grafische activiteiten Film-, tv- and videoproductie Secretariaatsdien",
    "sg:phone":"+32 50 31 60 52",
    "sg:postcode":"8200",
    "sg:province":"West-Vlaanderen",
    "wof:name":"Studio Kontrast",
    "wof:placetype":"venue"
},
  "geometry": {"coordinates":[3.1575660706,51.2068481445],"type":"Point"}
}