{
  "type": "Feature",
  "properties": {
    "addr:full":"Chauss\u00c9e D'eghez\u00c9e 64 La Bruyere Namur 5081",
    "addr:housenumber":"64",
    "addr:postcode":"5081",
    "addr:street":"Chausse\u0301E D'Egheze \u0301E;La Bruyere",
    "iso:country":"BE",
    "sg:address":"Chauss\u00c9e D'eghez\u00c9e 64",
    "sg:city":"La Bruyere",
    "sg:orig_category":"V\u00e9t\u00e9rinaires",
    "sg:phone":"+32 81 56 61 20",
    "sg:postcode":"5081",
    "sg:province":"Namur",
    "wof:name":"Ernest Lambert",
    "wof:placetype":"venue"
},
  "geometry": {"coordinates":[4.7865719795,50.5369911194],"type":"Point"}
}