{
  "type": "Feature",
  "properties": {
    "iso:country":"BE",
    "sg:address":"Chauss\u00e9e De Louvain 815",
    "sg:city":"Bruxelles (evere)",
    "sg:classifiers":[
        {
            "category":"Bars & Pubs",
            "type":"Food & Drink"
        }
    ],
    "sg:phone":"+32 2 726 56 49",
    "sg:postcode":"1140",
    "sg:province":"Bruxelles-Capitale",
    "wof:name":"Mascotte (la)",
    "wof:placetype":"venue"
},
  "geometry": {"coordinates":[4.4147720337,50.8592605591],"type":"Point"}
}