{
  "type": "Feature",
  "properties": {
    "addr:full":"Houlteau 42 Thimister-clermont Li\u00e8ge 4890",
    "addr:housenumber":"42",
    "addr:postcode":"4890",
    "addr:street":"Houlteau",
    "iso:country":"BE",
    "sg:address":"Houlteau 42",
    "sg:city":"Thimister-clermont",
    "sg:orig_category":"Entretien and r\u00e9parations de voitures",
    "sg:phone":"+32 87 44 66 15",
    "sg:postcode":"4890",
    "sg:province":"Li\u00e8ge",
    "wof:name":"Garage Mecatruck",
    "wof:placetype":"venue"
},
  "geometry": {"coordinates":[5.86338377,50.6361122131],"type":"Point"}
}