{
  "type": "Feature",
  "properties": {
    "addr:full":"Olmenweg 3 Maaseik Limburg 3680",
    "addr:housenumber":"3",
    "addr:postcode":"3680",
    "addr:street":"Olmenweg",
    "iso:country":"BE",
    "sg:address":"Olmenweg 3",
    "sg:city":"Maaseik",
    "sg:classifiers":[
        {
            "category":"Autos & Motor Vehicles",
            "subcategory":"Auto Supplies",
            "type":"Retail Goods"
        }
    ],
    "sg:phone":"+32 89 56 49 55",
    "sg:postcode":"3680",
    "sg:province":"Limburg",
    "sg:tags":[
        "semi-trailers",
        "industrial",
        "-",
        "trailer"
    ],
    "wof:name":"A.t.m. Nv-sa",
    "wof:placetype":"venue"
},
  "geometry": {"coordinates":[5.7831168175,51.1016044617],"type":"Point"}
}