{
  "type": "Feature",
  "properties": {
    "iso:country":"BE",
    "sg:address":"Sportlaan 1",
    "sg:city":"De Panne",
    "sg:orig_category":"Banken and kredietinstellingen",
    "sg:phone":"+32 58 42 15 15",
    "sg:postcode":"8660",
    "sg:province":"West-Vlaanderen",
    "wof:name":"Ippa",
    "wof:placetype":"venue"
},
  "geometry": {"coordinates":[2.61241889,51.0932922363],"type":"Point"}
}