{
  "type": "Feature",
  "properties": {
    "iso:country":"BE",
    "sg:address":"Kielenstraat 73",
    "sg:city":"Tongeren",
    "sg:classifiers":[
        {
            "category":"Health Services",
            "subcategory":"Doctor",
            "type":"Services"
        }
    ],
    "sg:phone":"+32 12 23 42 65",
    "sg:postcode":"3700",
    "sg:province":"Limburg",
    "sg:tags":[
        "medicinephysicians",
        "surgeon"
    ],
    "wof:name":"Marchoul Jean-claude",
    "wof:placetype":"venue"
},
  "geometry": {"coordinates":[5.4692120552,50.7799453735],"type":"Point"}
}