{
  "type": "Feature",
  "properties": {
    "addr:full":"Vlierboomstraat 11 Tervuren Vlaams-Brabant 3080",
    "addr:housenumber":"11",
    "addr:postcode":"3080",
    "addr:street":"Vlierboomstraat",
    "iso:country":"BE",
    "sg:address":"Vlierboomstraat 11",
    "sg:city":"Tervuren",
    "sg:classifiers":[
        {
            "category":"Restaurant",
            "type":"Food & Drink"
        }
    ],
    "sg:phone":"+32 2 767 28 95",
    "sg:postcode":"3080",
    "sg:province":"Vlaams-Brabant",
    "sg:tags":[
        "industrial",
        "kitchen",
        "catering"
    ],
    "wof:name":"Brueghel",
    "wof:placetype":"venue"
},
  "geometry": {"coordinates":[4.5083370209,50.8148345947],"type":"Point"}
}