{
  "type": "Feature",
  "properties": {
    "addr:full":"Tolstraat 57 Antwerpen Antwerpen 2000",
    "addr:housenumber":"57",
    "addr:postcode":"2000",
    "addr:street":"Tolstraat",
    "iso:country":"BE",
    "sg:address":"Tolstraat 57",
    "sg:city":"Antwerpen",
    "sg:classifiers":[
        {
            "category":"Professional",
            "subcategory":"Accounting & Tax Preparation",
            "type":"Services"
        }
    ],
    "sg:phone":"+32 3 238 59 84",
    "sg:postcode":"2000",
    "sg:province":"Antwerpen",
    "sg:tags":[
        "accountant"
    ],
    "wof:name":"Luc Van Passel",
    "wof:placetype":"venue"
},
  "geometry": {"coordinates":[4.40041399,51.2095794678],"type":"Point"}
}