{
  "type": "Feature",
  "properties": {
    "addr:full":"Boekbindersweg 21 Lommel Limburg 3920",
    "addr:housenumber":"21",
    "addr:postcode":"3920",
    "addr:street":"Boekbindersweg",
    "iso:country":"BE",
    "sg:address":"Boekbindersweg 21",
    "sg:city":"Lommel",
    "sg:orig_category":"Immobili\u00ebnkantoren",
    "sg:phone":"+32 11 54 22 41",
    "sg:postcode":"3920",
    "sg:province":"Limburg",
    "wof:name":"Woon- En Adviescenter",
    "wof:placetype":"venue"
},
  "geometry": {"coordinates":[5.3566741943,51.2392959595],"type":"Point"}
}