{
  "type": "Feature",
  "properties": {
    "addr:full":"Neerveldstraat 101 Sint-lambrechts-woluwe/woluwe-saint-lambert Bruxelles-Capitale 1200",
    "addr:housenumber":"101",
    "addr:postcode":"1200",
    "addr:street":"Neerveldstraat",
    "iso:country":"BE",
    "sg:address":"Neerveldstraat 101",
    "sg:city":"Sint-lambrechts-woluwe/woluwe-saint-lambert",
    "sg:orig_category":"Advocaten and juridische adviseurs",
    "sg:phone":"+32 2 773 40 00",
    "sg:postcode":"1200",
    "sg:province":"Bruxelles-Capitale",
    "wof:name":"Walter Verlinden",
    "wof:placetype":"venue"
},
  "geometry": {"coordinates":[4.4409351349,50.851524353],"type":"Point"}
}