{
  "type": "Feature",
  "properties": {
    "addr:full":"Chauss\u00c9e De March\u00c9 80 Neupre Li\u00e8ge 4121",
    "addr:housenumber":"80",
    "addr:postcode":"4121",
    "addr:street":"Chausse\u0301E De Marche\u0301",
    "iso:country":"BE",
    "sg:address":"Chauss\u00c9e De March\u00c9 80",
    "sg:city":"Neupre",
    "sg:orig_category":"Textiel",
    "sg:phone":"+32 4 371 49 17",
    "sg:postcode":"4121",
    "sg:province":"Li\u00e8ge",
    "wof:name":"Maison L'aiguille D'or",
    "wof:placetype":"venue"
},
  "geometry": {"coordinates":[5.4499602318,50.5516586304],"type":"Point"}
}