{
  "type": "Feature",
  "properties": {
    "iso:country":"BE",
    "sg:address":"Shopping Center I",
    "sg:city":"Genk",
    "sg:classifiers":[
        {
            "category":"Personal",
            "subcategory":"Beauty Salon",
            "type":"Services"
        }
    ],
    "sg:phone":"+32 89 36 38 35",
    "sg:postcode":"3600",
    "sg:province":"Limburg",
    "sg:tags":[
        "lady",
        "-",
        "hairdressing"
    ],
    "wof:name":"Coiffure Riggio",
    "wof:placetype":"venue"
},
  "geometry": {"coordinates":[5.4931697845,50.9654083252],"type":"Point"}
}