{
  "type": "Feature",
  "properties": {
    "iso:country":"BE",
    "sg:address":"Potaardestraat 74",
    "sg:city":"Niel",
    "sg:classifiers":[
        {
            "category":"Building & Trades",
            "subcategory":"Construction",
            "type":"Services"
        }
    ],
    "sg:phone":"+32 3 888 95 40",
    "sg:postcode":"2845",
    "sg:province":"Antwerpen",
    "sg:tags":[
        "la",
        "de",
        "\u00e9quipement",
        "pour",
        "machine",
        "location"
    ],
    "wof:name":"Special Lifting Services",
    "wof:placetype":"venue"
},
  "geometry": {"coordinates":[4.3609418869,51.1059036255],"type":"Point"}
}