{
  "type": "Feature",
  "properties": {
    "iso:country":"BE",
    "sg:address":"Rue De La Vaulx 125",
    "sg:city":"Fleron",
    "sg:orig_category":"Pain, p\u00e2tisseries and confiseries",
    "sg:phone":"+32 4 358 32 11",
    "sg:postcode":"4621",
    "sg:province":"Li\u00e8ge",
    "wof:name":"Leon Denoel",
    "wof:placetype":"venue"
},
  "geometry": {"coordinates":[5.698264122,50.6299476624],"type":"Point"}
}