{
  "type": "Feature",
  "properties": {
    "addr:full":"Sint-truidersteenweg 375 Borgloon Limburg 3840",
    "addr:housenumber":"375",
    "addr:postcode":"3840",
    "addr:street":"Sint-Truidersteenweg",
    "iso:country":"BE",
    "sg:address":"Sint-truidersteenweg 375",
    "sg:city":"Borgloon",
    "sg:classifiers":[
        {
            "category":"Personal",
            "subcategory":"Beauty Salon",
            "type":"Services"
        }
    ],
    "sg:phone":"+32 12 74 51 39",
    "sg:postcode":"3840",
    "sg:province":"Limburg",
    "sg:tags":[
        "de",
        "coiffure"
    ],
    "wof:name":"Paul Wathion",
    "wof:placetype":"venue"
},
  "geometry": {"coordinates":[5.2891769409,50.8063545227],"type":"Point"}
}