{
  "type": "Feature",
  "properties": {
    "addr:full":"Boelenstraat 6 Overpelt Limburg 3900",
    "addr:housenumber":"6",
    "addr:postcode":"3900",
    "addr:street":"Boelenstraat",
    "iso:country":"BE",
    "sg:address":"Boelenstraat 6",
    "sg:city":"Overpelt",
    "sg:classifiers":[
        {
            "category":"Professional",
            "subcategory":"Management & Consulting",
            "type":"Services"
        }
    ],
    "sg:phone":"+32 11 64 71 20",
    "sg:postcode":"3900",
    "sg:province":"Limburg",
    "sg:tags":[
        "tax-consultants"
    ],
    "wof:name":"Willemyns M-a",
    "wof:placetype":"venue"
},
  "geometry": {"coordinates":[5.4202241898,51.2078170776],"type":"Point"}
}