{
  "type": "Feature",
  "properties": {
    "iso:country":"BE",
    "sg:address":"Rue Du Trieu-kaisin 1b78",
    "sg:city":"Chatelet",
    "sg:classifiers":[
        {
            "category":"Wholesale",
            "subcategory":"Sporting Goods",
            "type":"Manufacturing & Wholesale Goods"
        }
    ],
    "sg:phone":"+32 71 40 45 89",
    "sg:postcode":"6200",
    "sg:province":"Hainaut",
    "sg:tags":[
        "sport-",
        "kampeermateriaal"
    ],
    "wof:name":"Sport Corner",
    "wof:placetype":"venue"
},
  "geometry": {"coordinates":[4.4989500046,50.4061737061],"type":"Point"}
}