{
  "type": "Feature",
  "properties": {
    "addr:full":"Rue Sous-le-ch\u00c2teau 4 Huy Li\u00e8ge 4500",
    "addr:housenumber":"4",
    "addr:postcode":"4500",
    "addr:street":"Rue Sous-Le-Cha\u0302Teau",
    "iso:country":"BE",
    "sg:address":"Rue Sous-le-ch\u00c2teau 4",
    "sg:city":"Huy",
    "sg:orig_category":"Banken and kredietinstellingen",
    "sg:phone":"+32 85 21 37 69",
    "sg:postcode":"4500",
    "sg:province":"Li\u00e8ge",
    "wof:name":"Cr\u00c9dit Professionnel",
    "wof:placetype":"venue"
},
  "geometry": {"coordinates":[5.2389259338,50.5184516907],"type":"Point"}
}