{
  "type": "Feature",
  "properties": {
    "iso:country":"BE",
    "sg:address":"Voltairelaan 3",
    "sg:city":"Schaarbeek/schaerbeek",
    "sg:orig_category":"Installatie van houten of kunststof schrijnwerk Installatie van metalen schrijnwerk Isolatiewerk",
    "sg:phone":"+32 475 45 97 62",
    "sg:postcode":"1030",
    "sg:province":"Bruxelles-Capitale",
    "wof:name":"Burolux",
    "wof:placetype":"venue"
},
  "geometry": {"coordinates":[4.3750572205,50.8696937561],"type":"Point"}
}