{
  "type": "Feature",
  "properties": {
    "addr:full":"Kwadestraat 44 Waregem West-Vlaanderen 8792",
    "addr:housenumber":"44",
    "addr:postcode":"8792",
    "addr:street":"Kwadestraat",
    "iso:country":"BE",
    "sg:address":"Kwadestraat 44",
    "sg:city":"Waregem",
    "sg:orig_category":"Epiceries",
    "sg:phone":"+32 56 77 09 18",
    "sg:postcode":"8792",
    "sg:province":"West-Vlaanderen",
    "wof:name":"J Vercruysse",
    "wof:placetype":"venue"
},
  "geometry": {"coordinates":[3.3753569126,50.8839492798],"type":"Point"}
}