{
  "type": "Feature",
  "properties": {
    "addr:full":"Egypteveldstraat 27 Aalter Oost-Vlaanderen 9880",
    "addr:housenumber":"27",
    "addr:postcode":"9880",
    "addr:street":"Egypteveldstraat",
    "iso:country":"BE",
    "sg:address":"Egypteveldstraat 27",
    "sg:city":"Aalter",
    "sg:classifiers":[
        {
            "category":"Retail",
            "subcategory":"Veterinary Services",
            "type":"Services"
        }
    ],
    "sg:phone":"+32 9 375 17 75",
    "sg:postcode":"9880",
    "sg:province":"Oost-Vlaanderen",
    "sg:tags":[
        "veterinarian"
    ],
    "wof:name":"Coppenolle F",
    "wof:placetype":"venue"
},
  "geometry": {"coordinates":[3.3689730167,51.0920448303],"type":"Point"}
}