{
  "type": "Feature",
  "properties": {
    "iso:country":"BE",
    "sg:address":"Rue De La Coll\u00c9giale 2",
    "sg:city":"Huy",
    "sg:orig_category":"Kapsalons",
    "sg:phone":"+32 85 21 23 26",
    "sg:postcode":"4500",
    "sg:province":"Li\u00e8ge",
    "wof:name":"Coiffure Paraph'v",
    "wof:placetype":"venue"
},
  "geometry": {"coordinates":[5.238296032,50.5188674927],"type":"Point"}
}