{
  "type": "Feature",
  "properties": {
    "iso:country":"BE",
    "sg:address":"Tongerenstraat 49",
    "sg:city":"Etterbeek/etterbeek",
    "sg:orig_category":"Industri\u00eble wasserijen and droogkuis",
    "sg:phone":"+32 2 733 13 70",
    "sg:postcode":"1040",
    "sg:province":"Bruxelles-Capitale",
    "wof:name":"Sea Horse-varteks",
    "wof:placetype":"venue"
},
  "geometry": {"coordinates":[4.4006361961,50.84009552],"type":"Point"}
}