{
  "type": "Feature",
  "properties": {
    "addr:full":"Rue De Perwez 8 Andenne Namur 5300",
    "addr:housenumber":"8",
    "addr:postcode":"5300",
    "addr:street":"Rue De Perwez",
    "iso:country":"BE",
    "sg:address":"Rue De Perwez 8",
    "sg:city":"Andenne",
    "sg:classifiers":[
        {
            "category":"Personal",
            "subcategory":"Beauty Salon",
            "type":"Services"
        }
    ],
    "sg:phone":"+32 85 84 37 16",
    "sg:postcode":"5300",
    "sg:province":"Namur",
    "sg:tags":[
        "de",
        "coiffure"
    ],
    "wof:name":"Patricia Collin",
    "wof:placetype":"venue"
},
  "geometry": {"coordinates":[5.1143069267,50.492149353],"type":"Point"}
}