{
  "type": "Feature",
  "properties": {
    "addr:full":"Grote Markt 25 Mechelen Antwerpen 2800",
    "addr:housenumber":"25",
    "addr:postcode":"2800",
    "addr:street":"Grote Markt",
    "iso:country":"BE",
    "sg:address":"Grote Markt 25",
    "sg:city":"Mechelen",
    "sg:orig_category":"Brood, gebak and snoepgoed",
    "sg:phone":"+32 15 20 24 83",
    "sg:postcode":"2800",
    "sg:province":"Antwerpen",
    "wof:name":"Leonidas",
    "wof:placetype":"venue"
},
  "geometry": {"coordinates":[4.4804668427,51.0276641846],"type":"Point"}
}