{
  "type": "Feature",
  "properties": {
    "iso:country":"BE",
    "sg:address":"Chauss\u00c9e De Wavre 504",
    "sg:city":"Graven",
    "sg:orig_category":"Equipement divers pour commerces Equipements divers pour l\u00b4industrie Gr. Quincailleries",
    "sg:phone":"+32 10 84 17 98",
    "sg:postcode":"1390",
    "sg:province":"Brabant Wallon",
    "wof:name":"Kew-beltools",
    "wof:placetype":"venue"
},
  "geometry": {"coordinates":[4.6466069221,50.7328109741],"type":"Point"}
}