{
  "type": "Feature",
  "properties": {
    "iso:country":"BE",
    "sg:address":"Kerkstraat 7",
    "sg:city":"Steenokkerzeel",
    "sg:classifiers":[
        {
            "category":"Autos & Motor Vehicles",
            "subcategory":"Automobile Sales",
            "type":"Retail Goods"
        }
    ],
    "sg:phone":"+32 2 753 00 40",
    "sg:postcode":"1820",
    "sg:province":"Vlaams-Brabant",
    "sg:tags":[
        "brake",
        "system"
    ],
    "wof:name":"H. Francois - Maintenance & Supplies Company Nv",
    "wof:placetype":"venue"
},
  "geometry": {"coordinates":[4.4781041145,50.9156684875],"type":"Point"}
}