{
  "type": "Feature",
  "properties": {
    "iso:country":"BE",
    "sg:address":"Tiensestraat 19",
    "sg:city":"Sint-truiden",
    "sg:orig_category":"Cr\u00e9dits divers",
    "sg:postcode":"3800",
    "sg:province":"Limburg",
    "wof:name":"Postomat Sint-truiden",
    "wof:placetype":"venue"
},
  "geometry": {"coordinates":[5.1797318459,50.8152313232],"type":"Point"}
}