{
  "type": "Feature",
  "properties": {
    "iso:country":"BE",
    "sg:address":"Zandstraat 236",
    "sg:city":"Sint-gillis-waas",
    "sg:orig_category":"RESTAURANTS: SALLES DE CONF\u00c9RENCES AND DE R\u00c9CEPTIONS",
    "sg:phone":"+32 3 779 91 23",
    "sg:postcode":"9170",
    "sg:province":"Oost-Vlaanderen",
    "wof:name":"La Pignata",
    "wof:placetype":"venue"
},
  "geometry": {"coordinates":[4.0768961906,51.2041397095],"type":"Point"}
}