{
  "type": "Feature",
  "properties": {
    "addr:full":"Hoevensebaan 267 Kapellen Antwerpen 2950",
    "addr:housenumber":"267",
    "addr:postcode":"2950",
    "addr:street":"Hoevensebaan",
    "iso:country":"BE",
    "sg:address":"Hoevensebaan 267",
    "sg:city":"Kapellen",
    "sg:classifiers":[
        {
            "category":"Government",
            "subcategory":"Department Of Motor Vehicles",
            "type":"Public Place"
        }
    ],
    "sg:phone":"+32 3 660 14 60",
    "sg:postcode":"2950",
    "sg:province":"Antwerpen",
    "sg:tags":[
        "equipment",
        "industrial",
        "transport",
        "motor-cars"
    ],
    "wof:name":"Internat Trading Systems Bvba",
    "wof:placetype":"venue"
},
  "geometry": {"coordinates":[4.4165439606,51.3102111816],"type":"Point"}
}