{
  "type": "Feature",
  "properties": {
    "iso:country":"BE",
    "sg:address":"Rue Des Renards 71",
    "sg:city":"Herstal",
    "sg:orig_category":"Entretien and r\u00e9parations de voitures",
    "sg:phone":"+32 4 248 31 97",
    "sg:postcode":"4040",
    "sg:province":"Li\u00e8ge",
    "wof:name":"Claude Corin",
    "wof:placetype":"venue"
},
  "geometry": {"coordinates":[5.6161580086,50.6601371765],"type":"Point"}
}