{
  "type": "Feature",
  "properties": {
    "iso:country":"BE",
    "sg:address":"Lammerdries 6",
    "sg:city":"Olen",
    "sg:orig_category":"V\u00eatements, chaussures and accessoires Gr",
    "sg:phone":"+32 14 21 13 60",
    "sg:postcode":"2250",
    "sg:province":"Antwerpen",
    "wof:name":"Van De Water G",
    "wof:placetype":"venue"
},
  "geometry": {"coordinates":[4.9147100449,51.1488685608],"type":"Point"}
}