{
  "type": "Feature",
  "properties": {
    "addr:full":"Ploegsebaan 17 Brasschaat Antwerpen 2930",
    "addr:housenumber":"17",
    "addr:postcode":"2930",
    "addr:street":"Ploegsebaan",
    "iso:country":"BE",
    "sg:address":"Ploegsebaan 17",
    "sg:city":"Brasschaat",
    "sg:orig_category":"Verhuur bouwmachines Verhuur doe-het-zelf materiaal",
    "sg:phone":"+32 3 663 46 65",
    "sg:postcode":"2930",
    "sg:province":"Antwerpen",
    "wof:name":"Marcel Van Poucke",
    "wof:placetype":"venue"
},
  "geometry": {"coordinates":[4.5073599815,51.3096542358],"type":"Point"}
}