{
  "type": "Feature",
  "properties": {
    "iso:country":"BE",
    "sg:address":"Eenbeekstraat 60",
    "sg:city":"Destelbergen",
    "sg:classifiers":[
        {
            "category":"Professional",
            "subcategory":"Lawyer & Legal Services",
            "type":"Services"
        }
    ],
    "sg:phone":"+32 9 228 61 68",
    "sg:postcode":"9070",
    "sg:province":"Oost-Vlaanderen",
    "wof:name":"Beuselinck Sophie",
    "wof:placetype":"venue"
},
  "geometry": {"coordinates":[3.7751040459,51.056350708],"type":"Point"}
}