{
  "type": "Feature",
  "properties": {
    "iso:country":"BE",
    "sg:address":"Olifant 14",
    "sg:city":"Rotselaar",
    "sg:orig_category":"Diensten voor huisdieren Diverse organisaties and verenigingen",
    "sg:phone":"+32 16 53 47 07",
    "sg:postcode":"3118",
    "sg:province":"Vlaams-Brabant",
    "wof:name":"Dieren In Nood - Dierenbesch. & Ambulance",
    "wof:placetype":"venue"
},
  "geometry": {"coordinates":[4.6940898895,50.970489502],"type":"Point"}
}