{
  "type": "Feature",
  "properties": {
    "addr:full":"Steenovenstraat 40 Waregem West-Vlaanderen 8790",
    "addr:housenumber":"40",
    "addr:postcode":"8790",
    "addr:street":"Steenovenstraat",
    "iso:country":"BE",
    "sg:address":"Steenovenstraat 40",
    "sg:city":"Waregem",
    "sg:orig_category":"Rev\u00eatements de sols and murs",
    "sg:phone":"+32 56 60 06 64",
    "sg:postcode":"8790",
    "sg:province":"West-Vlaanderen",
    "wof:name":"Vecatex",
    "wof:placetype":"venue"
},
  "geometry": {"coordinates":[3.4472229481,50.8689956665],"type":"Point"}
}