{
  "type": "Feature",
  "properties": {
    "iso:country":"BE",
    "sg:address":"Hertogenweg 10",
    "sg:city":"Tervuren",
    "sg:classifiers":[
        {
            "category":"Utilities",
            "subcategory":"Telephone",
            "type":"Services"
        }
    ],
    "sg:phone":"+32 2 768 04 22",
    "sg:postcode":"3080",
    "sg:province":"Vlaams-Brabant",
    "sg:tags":[
        "installation"
    ],
    "wof:name":"Kites Sa",
    "wof:placetype":"venue"
},
  "geometry": {"coordinates":[4.5040931702,50.8265953064],"type":"Point"}
}