{
  "type": "Feature",
  "properties": {
    "iso:country":"BE",
    "sg:address":"Sint-antoniusstraat 10",
    "sg:city":"Ranst",
    "sg:classifiers":[
        {
            "category":"Professional",
            "subcategory":"Management & Consulting",
            "type":"Services"
        }
    ],
    "sg:phone":"+32 3 485 62 51",
    "sg:postcode":"2520",
    "sg:province":"Antwerpen",
    "sg:tags":[
        "consultant"
    ],
    "wof:name":"Van Haeren Jan Ir Bvba",
    "wof:placetype":"venue"
},
  "geometry": {"coordinates":[4.5487399101,51.1863174438],"type":"Point"}
}