{
  "type": "Feature",
  "properties": {
    "addr:full":"Boulevard L\u00c9opold 85 Molenbeek-saint-jean (bruxelles) Bruxelles-Capitale 1080",
    "addr:housenumber":"85",
    "addr:postcode":"1080",
    "addr:street":"Boulevard Le\u0301Opold",
    "iso:country":"BE",
    "sg:address":"Boulevard L\u00c9opold 85",
    "sg:city":"Molenbeek-saint-jean (bruxelles)",
    "sg:classifiers":[
        {
            "category":"Fast Food",
            "type":"Food & Drink"
        }
    ],
    "sg:phone":"+32 2 420 05 73",
    "sg:postcode":"1080",
    "sg:province":"Bruxelles-Capitale",
    "sg:tags":[
        "huis",
        "aan",
        "levering",
        "meeneem",
        "restaurant"
    ],
    "wof:name":"Pizzeria Esma Piknik",
    "wof:placetype":"venue"
},
  "geometry": {"coordinates":[4.3409090042,50.8605422974],"type":"Point"}
}