{
  "type": "Feature",
  "properties": {
    "iso:country":"BE",
    "sg:address":"Ameiveld 22",
    "sg:city":"Ninove",
    "sg:orig_category":"Etalage- and showroomontwerpers",
    "sg:phone":"+32 54 32 11 41",
    "sg:postcode":"9400",
    "sg:province":"Oost-Vlaanderen",
    "wof:name":"Evy De Jonge",
    "wof:placetype":"venue"
},
  "geometry": {"coordinates":[4.0122041702,50.834274292],"type":"Point"}
}