{
  "type": "Feature",
  "properties": {
    "addr:full":"Rue Ferdinand Hendschel 0 Andenne Namur 5300",
    "addr:housenumber":"0",
    "addr:postcode":"5300",
    "addr:street":"Rue Ferdinand Hendschel",
    "iso:country":"BE",
    "sg:address":"Rue Ferdinand Hendschel 0",
    "sg:city":"Andenne",
    "sg:orig_category":"Installations and terrains de sport hors centres sportifs. Centres sportifs",
    "sg:phone":"+32 85 82 59 16",
    "sg:postcode":"5300",
    "sg:province":"Namur",
    "wof:name":"Complexe Sportif",
    "wof:placetype":"venue"
},
  "geometry": {"coordinates":[5.0982642174,50.4863739014],"type":"Point"}
}