{
  "type": "Feature",
  "properties": {
    "iso:country":"BE",
    "sg:address":"Zoning Industriel",
    "sg:city":"Hannut",
    "sg:orig_category":"Non-Classified Establishments",
    "sg:phone":"+32 19 51 20 48",
    "sg:postcode":"4280",
    "sg:province":"Li\u00e8ge",
    "wof:name":"Hougardy Ets",
    "wof:placetype":"venue"
},
  "geometry": {"coordinates":[5.0775651932,50.672290802],"type":"Point"}
}