{
  "type": "Feature",
  "properties": {
    "addr:full":"Chauss\u00e9e De Vilvorde 15 Bruxelles Bruxelles-Capitale 1020",
    "addr:housenumber":"15",
    "addr:postcode":"1020",
    "addr:street":"Chausse\u0301E De Vilvorde",
    "iso:country":"BE",
    "sg:address":"Chauss\u00e9e De Vilvorde 15",
    "sg:city":"Bruxelles",
    "sg:classifiers":[
        {
            "category":"Harbor",
            "type":"Transportation"
        }
    ],
    "sg:phone":"+32 2 216 67 34",
    "sg:postcode":"1020",
    "sg:province":"Bruxelles-Capitale",
    "sg:tags":[
        "port",
        "facility"
    ],
    "wof:name":"Riga Natie",
    "wof:placetype":"venue"
},
  "geometry": {"coordinates":[4.3748860359,50.8825416565],"type":"Point"}
}