{
  "type": "Feature",
  "properties": {
    "iso:country":"BE",
    "sg:address":"Gentstraat 38ba",
    "sg:city":"Oostrozebeke",
    "sg:orig_category":"D\u00e9corateurs d'int\u00e9rieur",
    "sg:phone":"+32 51 40 84 96",
    "sg:postcode":"8780",
    "sg:province":"West-Vlaanderen",
    "wof:name":"Koen Dierckens",
    "wof:placetype":"venue"
},
  "geometry": {"coordinates":[3.3673920631,50.9584617615],"type":"Point"}
}