{
  "type": "Feature",
  "properties": {
    "addr:full":"Patattestraat 23 Londerzeel Vlaams-Brabant 1840",
    "addr:housenumber":"23",
    "addr:postcode":"1840",
    "addr:street":"Patattestraat",
    "iso:country":"BE",
    "sg:address":"Patattestraat 23",
    "sg:city":"Londerzeel",
    "sg:orig_category":"Paramedische behandelingen",
    "sg:phone":"+32 52 30 21 42",
    "sg:postcode":"1840",
    "sg:province":"Vlaams-Brabant",
    "wof:name":"M. Boeykens",
    "wof:placetype":"venue"
},
  "geometry": {"coordinates":[4.2916650772,51.0357246399],"type":"Point"}
}