{
  "type": "Feature",
  "properties": {
    "addr:full":"Rue De Namur 53 Chatelet Hainaut 6200",
    "addr:housenumber":"53",
    "addr:postcode":"6200",
    "addr:street":"Rue De Namur;Hainaut",
    "iso:country":"BE",
    "sg:address":"Rue De Namur 53",
    "sg:city":"Chatelet",
    "sg:orig_category":"Hypotheken and hypotheekbanken Verzekeringsmakelaars and experts",
    "sg:phone":"+32 71 38 27 30",
    "sg:postcode":"6200",
    "sg:province":"Hainaut",
    "wof:name":"Baumal Henri",
    "wof:placetype":"venue"
},
  "geometry": {"coordinates":[4.5314788818,50.4001045227],"type":"Point"}
}