{
  "type": "Feature",
  "properties": {
    "iso:country":"BE",
    "sg:address":"Hofstraat 1",
    "sg:city":"Kinrooi",
    "sg:orig_category":"Boucheries",
    "sg:phone":"+32 89 56 44 20",
    "sg:postcode":"3640",
    "sg:province":"Limburg",
    "wof:name":"Johannes Verstraeten",
    "wof:placetype":"venue"
},
  "geometry": {"coordinates":[5.7222738266,51.1651496887],"type":"Point"}
}