{
  "type": "Feature",
  "properties": {
    "iso:country":"BE",
    "sg:address":"Rue Soeurs-de-hasque 19",
    "sg:city":"Li\u00e8ge 1",
    "sg:classifiers":[
        {
            "category":"Health Services",
            "subcategory":"Dentist",
            "type":"Services"
        }
    ],
    "sg:phone":"+32 4 222 31 98",
    "sg:postcode":"4000",
    "sg:province":"Li\u00e8ge",
    "wof:name":"Lhonneux D",
    "wof:placetype":"venue"
},
  "geometry": {"coordinates":[5.5729899406,50.64012146],"type":"Point"}
}