{
  "type": "Feature",
  "properties": {
    "iso:country":"BE",
    "sg:address":"Veneti\u00eblaan 45",
    "sg:city":"Harelbeke",
    "sg:classifiers":[
        {
            "category":"Building & Trades",
            "subcategory":"Plumbing",
            "type":"Services"
        }
    ],
    "sg:phone":"+32 56 42 31 29",
    "sg:postcode":"8530",
    "sg:province":"West-Vlaanderen",
    "sg:tags":[
        "contractor"
    ],
    "wof:name":"De Busschere Gebr Bvba",
    "wof:placetype":"venue"
},
  "geometry": {"coordinates":[3.2994720936,50.8331108093],"type":"Point"}
}