{
  "type": "Feature",
  "properties": {
    "addr:full":"Bloemstraat 2ba Gent Oost-Vlaanderen 9050",
    "addr:housenumber":"2ba",
    "addr:postcode":"9050",
    "addr:street":"Bloemstraat;Oost-Vlaanderen",
    "iso:country":"BE",
    "sg:address":"Bloemstraat 2ba",
    "sg:city":"Gent",
    "sg:orig_category":"Parfumeries",
    "sg:phone":"+32 9 230 60 72",
    "sg:postcode":"9050",
    "sg:province":"Oost-Vlaanderen",
    "wof:name":"Parfumerie Chris",
    "wof:placetype":"venue"
},
  "geometry": {"coordinates":[3.7642760277,51.0196228027],"type":"Point"}
}