{
  "type": "Feature",
  "properties": {
    "addr:full":"Gijmelsesteenweg 268 Aarschot Vlaams-Brabant 3201",
    "addr:housenumber":"268",
    "addr:postcode":"3201",
    "addr:street":"Gijmelsesteenweg",
    "iso:country":"BE",
    "sg:address":"Gijmelsesteenweg 268",
    "sg:city":"Aarschot",
    "sg:orig_category":"Rev\u00eatements de sols and murs. Mat\u00e9riaux de construction Gr",
    "sg:phone":"+32 16 56 67 88",
    "sg:postcode":"3201",
    "sg:province":"Vlaams-Brabant",
    "wof:name":"Luyten-thiels Edmond",
    "wof:placetype":"venue"
},
  "geometry": {"coordinates":[4.8603157997,51.0090370178],"type":"Point"}
}