{
  "type": "Feature",
  "properties": {
    "addr:full":"Avenue Adolphe Buyl 41 Elsene/ixelles Bruxelles-Capitale 1050",
    "addr:housenumber":"41",
    "addr:postcode":"1050",
    "addr:street":"Avenue Adolphe Buyl",
    "iso:country":"BE",
    "sg:address":"Avenue Adolphe Buyl 41",
    "sg:city":"Elsene/ixelles",
    "sg:orig_category":"Art and fournitures artistiques. Activit\u00e9s diverses d'imprimerie",
    "sg:phone":"+32 2 649 12 79",
    "sg:postcode":"1050",
    "sg:province":"Bruxelles-Capitale",
    "wof:name":"Pyramid Graphics",
    "wof:placetype":"venue"
},
  "geometry": {"coordinates":[4.3808379173,50.8171463013],"type":"Point"}
}