{
  "type": "Feature",
  "properties": {
    "iso:country":"BE",
    "sg:address":"Bazelstraat 1",
    "sg:city":"Kruibeke",
    "sg:orig_category":"M\u00e9decins and sp\u00e9cialistes",
    "sg:phone":"+32 3 774 52 31",
    "sg:postcode":"9150",
    "sg:province":"Oost-Vlaanderen",
    "wof:name":"P. Chardome",
    "wof:placetype":"venue"
},
  "geometry": {"coordinates":[4.3120799065,51.1705856323],"type":"Point"}
}