{
  "type": "Feature",
  "properties": {
    "iso:country":"BE",
    "sg:address":"Karel De Grotelaan 50",
    "sg:city":"Brussel/bruxelles",
    "sg:orig_category":"Hotels Ruimtes voor conferenties, recepties and feesten",
    "sg:phone":"+32 2 230 00 10",
    "sg:postcode":"1000",
    "sg:province":"Bruxelles-Capitale",
    "wof:name":"H\u00d4tel Euroflat",
    "wof:placetype":"venue"
},
  "geometry": {"coordinates":[4.3820371628,50.8449783325],"type":"Point"}
}