{
  "type": "Feature",
  "properties": {
    "addr:full":"Dorpsstraat 25 Stekene Oost-Vlaanderen 9190",
    "addr:housenumber":"25",
    "addr:postcode":"9190",
    "addr:street":"Dorpsstraat",
    "iso:country":"BE",
    "sg:address":"Dorpsstraat 25",
    "sg:city":"Stekene",
    "sg:orig_category":"Verplichte sociale verzekeringen",
    "sg:phone":"+32 3 779 65 68",
    "sg:postcode":"9190",
    "sg:province":"Oost-Vlaanderen",
    "wof:name":"Liberale Mutualiteit",
    "wof:placetype":"venue"
},
  "geometry": {"coordinates":[4.0400090218,51.2050437927],"type":"Point"}
}