{
  "type": "Feature",
  "properties": {
    "iso:country":"BE",
    "sg:address":"Reinaertstraat 5",
    "sg:city":"Ieper",
    "sg:orig_category":"Drogisterijen",
    "sg:phone":"+32 57 20 89 91",
    "sg:postcode":"8900",
    "sg:province":"West-Vlaanderen",
    "wof:name":"Johanna Vandamme",
    "wof:placetype":"venue"
},
  "geometry": {"coordinates":[2.8668699265,50.8406715393],"type":"Point"}
}