{
  "type": "Feature",
  "properties": {
    "addr:full":"Tervuursestraat 138 Leuven Vlaams-Brabant 3000",
    "addr:housenumber":"138",
    "addr:postcode":"3000",
    "addr:street":"Tervuursestraat",
    "iso:country":"BE",
    "sg:address":"Tervuursestraat 138",
    "sg:city":"Leuven",
    "sg:orig_category":"Editeurs de livres",
    "sg:phone":"+32 16 23 84 34",
    "sg:postcode":"3000",
    "sg:province":"Vlaams-Brabant",
    "wof:name":"Jan Van Helmont",
    "wof:placetype":"venue"
},
  "geometry": {"coordinates":[4.6854400635,50.8776855469],"type":"Point"}
}