{
  "type": "Feature",
  "properties": {
    "addr:full":"Hollebekestraat 8ba Zedelgem West-Vlaanderen 8210",
    "addr:postcode":"8210",
    "addr:street":"Hollebekestraat",
    "iso:country":"BE",
    "sg:address":"Hollebekestraat 8ba",
    "sg:city":"Zedelgem",
    "sg:orig_category":"Eleveurs and marchands de porcs",
    "sg:phone":"+32 50 20 02 10",
    "sg:postcode":"8210",
    "sg:province":"West-Vlaanderen",
    "wof:name":"Jaak Demeyere Isaacq",
    "wof:placetype":"venue"
},
  "geometry": {"coordinates":[3.1404559612,51.1493225098],"type":"Point"}
}