{
  "type": "Feature",
  "properties": {
    "iso:country":"BE",
    "sg:address":"Meirestraat 13",
    "sg:city":"Kruishoutem",
    "sg:classifiers":[
        {
            "category":"Parking",
            "subcategory":"Lot",
            "type":"Transportation"
        }
    ],
    "sg:phone":"+32 9 388 53 17",
    "sg:postcode":"9770",
    "sg:province":"Oost-Vlaanderen",
    "sg:tags":[
        "parking-places",
        "laying-out"
    ],
    "wof:name":"Grondwerken Glk Bvba",
    "wof:placetype":"venue"
},
  "geometry": {"coordinates":[3.4716451168,50.9001083374],"type":"Point"}
}