{
  "type": "Feature",
  "properties": {
    "addr:full":"Naamsestw 163 Heverlee 3030",
    "addr:housenumber":"163",
    "addr:postcode":"3030",
    "iso:country":"BE",
    "sg:address":"Naamsestw 163",
    "sg:city":"Heverlee",
    "sg:classifiers":[
        {
            "category":"Banks & Credit Unions",
            "subcategory":"Bank",
            "type":"Services"
        }
    ],
    "sg:phone":"+32 16 23 37 97",
    "sg:postcode":"3030",
    "wof:name":"Aslk-cger Bank",
    "wof:placetype":"venue"
},
  "geometry": {"coordinates":[4.6959400177,50.8633499146],"type":"Point"}
}