{
  "type": "Feature",
  "properties": {
    "addr:full":"Rue Roosendael 148 Vorst/forest Bruxelles-Capitale 1190",
    "addr:housenumber":"148",
    "addr:postcode":"1190",
    "addr:street":"Rue Roosendael;/ Forest",
    "iso:country":"BE",
    "sg:address":"Rue Roosendael 148",
    "sg:city":"Vorst/forest",
    "sg:orig_category":"Editeurs de livres. Enregistrements sonores",
    "sg:phone":"+32 2 345 80 58",
    "sg:postcode":"1190",
    "sg:province":"Bruxelles-Capitale",
    "wof:name":"Universyn",
    "wof:placetype":"venue"
},
  "geometry": {"coordinates":[4.3328928947,50.8091430664],"type":"Point"}
}