{
  "type": "Feature",
  "properties": {
    "iso:country":"BE",
    "sg:address":"Molendries 24",
    "sg:city":"Aalst",
    "sg:orig_category":"Slagers",
    "sg:phone":"+32 53 71 07 48",
    "sg:postcode":"9300",
    "sg:province":"Oost-Vlaanderen",
    "wof:name":"Slagerij Van Den Eeckhout",
    "wof:placetype":"venue"
},
  "geometry": {"coordinates":[4.0442137718,50.9416847229],"type":"Point"}
}