{
  "type": "Feature",
  "properties": {
    "addr:full":"Kleppestraat 106 Moorslede (dadizele) West-Vlaanderen 8890",
    "addr:housenumber":"106",
    "addr:postcode":"8890",
    "addr:street":"Kleppestraat",
    "iso:country":"BE",
    "sg:address":"Kleppestraat 106",
    "sg:city":"Moorslede (dadizele)",
    "sg:classifiers":[
        {
            "category":"Building & Trades",
            "subcategory":"Pest Control",
            "type":"Services"
        }
    ],
    "sg:phone":"+32 56 50 59 92",
    "sg:postcode":"8890",
    "sg:province":"West-Vlaanderen",
    "sg:tags":[
        "painting",
        "contractor"
    ],
    "wof:name":"All Round",
    "wof:placetype":"venue"
},
  "geometry": {"coordinates":[3.1089138985,50.850528717],"type":"Point"}
}