{
  "type": "Feature",
  "properties": {
    "iso:country":"BE",
    "sg:address":"Scheldestraat 65",
    "sg:city":"Temse",
    "sg:orig_category":"Plaatsen van vloer- and muurbekleding Schilders Schoenen",
    "sg:phone":"+32 3 771 11 71",
    "sg:postcode":"9140",
    "sg:province":"Oost-Vlaanderen",
    "wof:name":"Jan Meersman",
    "wof:placetype":"venue"
},
  "geometry": {"coordinates":[4.216750145,51.1266517639],"type":"Point"}
}