{
  "type": "Feature",
  "properties": {
    "iso:country":"BE",
    "sg:address":"Rue Lucien-burnotte 59",
    "sg:city":"Neufch\u00e2teau",
    "sg:classifiers":[
        {
            "category":"Shopping",
            "subcategory":"Clothing, Apparel, & Fashions",
            "type":"Retail Goods"
        }
    ],
    "sg:phone":"+32 61 27 77 74",
    "sg:postcode":"6840",
    "sg:province":"Luxembourg",
    "sg:tags":[
        "textile",
        "clothing",
        "clothes"
    ],
    "wof:name":"Goosse Et Fils Sprl",
    "wof:placetype":"venue"
},
  "geometry": {"coordinates":[5.4373202324,49.8418197632],"type":"Point"}
}