{
  "type": "Feature",
  "properties": {
    "iso:country":"BE",
    "sg:address":"Leopold I-laan 72",
    "sg:city":"Brugge",
    "sg:orig_category":"Pain, p\u00e2tisseries and confiseries",
    "sg:phone":"+32 50 32 06 96",
    "sg:postcode":"8000",
    "sg:province":"West-Vlaanderen",
    "wof:name":"Bakkerij De Sloovere",
    "wof:placetype":"venue"
},
  "geometry": {"coordinates":[3.2090880871,51.2157554626],"type":"Point"}
}