{
  "type": "Feature",
  "properties": {
    "addr:full":"Courte Rue De La Station 6 Braine-le-chateau Brabant Wallon 1440",
    "addr:housenumber":"6",
    "addr:postcode":"1440",
    "addr:street":"Rue De La Station;Brabant Wallon",
    "iso:country":"BE",
    "sg:address":"Courte Rue De La Station 6",
    "sg:city":"Braine-le-chateau",
    "sg:orig_category":"Tabac. Journaux",
    "sg:phone":"+32 2 366 32 66",
    "sg:postcode":"1440",
    "sg:province":"Brabant Wallon",
    "wof:name":"Librairie Du Livre D'or",
    "wof:placetype":"venue"
},
  "geometry": {"coordinates":[4.2695388794,50.6820144653],"type":"Point"}
}