{
  "type": "Feature",
  "properties": {
    "iso:country":"BE",
    "sg:address":"Ruiterstraat 21",
    "sg:city":"Bornem",
    "sg:orig_category":"Rev\u00eatements pour sols and murs. Installation de menuiserie en bois and plastique. Peinture",
    "sg:phone":"+32 3 889 41 32",
    "sg:postcode":"2880",
    "sg:province":"Antwerpen",
    "wof:name":"Rottiers",
    "wof:placetype":"venue"
},
  "geometry": {"coordinates":[4.2327828407,51.0983695984],"type":"Point"}
}