{
  "type": "Feature",
  "properties": {
    "iso:country":"BE",
    "sg:address":"Kronemolenstraat 33",
    "sg:city":"Zedelgem (veldegem)",
    "sg:classifiers":[
        {
            "category":"Retail",
            "subcategory":"Animal Services",
            "type":"Services"
        }
    ],
    "sg:phone":"+32 50 27 55 98",
    "sg:postcode":"8210",
    "sg:province":"West-Vlaanderen",
    "sg:tags":[
        "farrier"
    ],
    "wof:name":"Reynaert J",
    "wof:placetype":"venue"
},
  "geometry": {"coordinates":[3.1458399296,51.1376457214],"type":"Point"}
}