{
  "type": "Feature",
  "properties": {
    "iso:country":"BE",
    "sg:address":"Bosstraat 37",
    "sg:city":"Putte (beerzel)",
    "sg:classifiers":[
        {
            "category":"Real Estate",
            "subcategory":"Architect",
            "type":"Services"
        }
    ],
    "sg:phone":"+32 15 75 62 89",
    "sg:postcode":"2580",
    "sg:province":"Antwerpen",
    "wof:name":"Baeten A",
    "wof:placetype":"venue"
},
  "geometry": {"coordinates":[4.6590299606,51.0638198853],"type":"Point"}
}