{
  "type": "Feature",
  "properties": {
    "addr:full":"Sleidingedorp 3 Evergem Oost-Vlaanderen 9940",
    "addr:housenumber":"3",
    "addr:postcode":"9940",
    "addr:street":"Sleidingedorp;Oost-Vlaanderen",
    "iso:country":"BE",
    "sg:address":"Sleidingedorp 3",
    "sg:city":"Evergem",
    "sg:orig_category":"Bouwmaterialen Gh Vloer- and muurbekleding",
    "sg:phone":"+32 9 357 35 37",
    "sg:postcode":"9940",
    "sg:province":"Oost-Vlaanderen",
    "wof:name":"Leus Bouwmaterialen",
    "wof:placetype":"venue"
},
  "geometry": {"coordinates":[3.6784300804,51.1319503784],"type":"Point"}
}