{
  "type": "Feature",
  "properties": {
    "addr:full":"Legen Heirweg 59 Gavere (asper) Oost-Vlaanderen 9890",
    "addr:housenumber":"59",
    "addr:postcode":"9890",
    "addr:street":"Legen Heirweg",
    "iso:country":"BE",
    "sg:address":"Legen Heirweg 59",
    "sg:city":"Gavere (asper)",
    "sg:classifiers":[
        {
            "category":"Professional",
            "subcategory":"Computer Services",
            "type":"Services"
        }
    ],
    "sg:phone":"+32 9 382 94 24",
    "sg:postcode":"9890",
    "sg:province":"Oost-Vlaanderen",
    "sg:tags":[
        "rental",
        "processing",
        "-",
        "data"
    ],
    "wof:name":"Mediapolis",
    "wof:placetype":"venue"
},
  "geometry": {"coordinates":[3.6438479424,50.9347953796],"type":"Point"}
}