{
  "type": "Feature",
  "properties": {
    "iso:country":"BE",
    "sg:address":"Place Cardinal Mercier 14",
    "sg:city":"Wavre",
    "sg:classifiers":[
        {
            "category":"Shopping",
            "subcategory":"Clothing, Apparel, & Fashions",
            "type":"Retail Goods"
        }
    ],
    "sg:phone":"+32 10 22 61 83",
    "sg:postcode":"1300",
    "sg:province":"Brabant Wallon",
    "sg:tags":[
        "lady",
        "clothing",
        "-"
    ],
    "wof:name":"Aquamarine",
    "wof:placetype":"venue"
},
  "geometry": {"coordinates":[4.6107869148,50.7169723511],"type":"Point"}
}