{
  "type": "Feature",
  "properties": {
    "iso:country":"BE",
    "sg:address":"Rue Albert I 43",
    "sg:city":"Erquelinnes",
    "sg:orig_category":"Metaalbehandeling and -bekleding",
    "sg:phone":"+32 71 55 42 62",
    "sg:postcode":"6560",
    "sg:province":"Hainaut",
    "wof:name":"Amelia",
    "wof:placetype":"venue"
},
  "geometry": {"coordinates":[4.1221399307,50.3100776672],"type":"Point"}
}