{
  "type": "Feature",
  "properties": {
    "addr:full":"Markt 5 Tielt West-Vlaanderen 8700",
    "addr:housenumber":"5",
    "addr:postcode":"8700",
    "addr:street":"Markt",
    "iso:country":"BE",
    "sg:address":"Markt 5",
    "sg:city":"Tielt",
    "sg:classifiers":[
        {
            "category":"Shopping",
            "subcategory":"Clothing, Apparel, & Fashions",
            "type":"Retail Goods"
        }
    ],
    "sg:phone":"+32 51 40 03 87",
    "sg:postcode":"8700",
    "sg:province":"West-Vlaanderen",
    "sg:tags":[
        "lady",
        "clothing",
        "-"
    ],
    "wof:name":"Caty Bvba",
    "wof:placetype":"venue"
},
  "geometry": {"coordinates":[3.3262069225,51.000202179],"type":"Point"}
}