{
  "type": "Feature",
  "properties": {
    "iso:country":"BE",
    "sg:address":"Rue Gregoire Chapuis 2",
    "sg:city":"Seraing",
    "sg:classifiers":[
        {
            "category":"Banks & Credit Unions",
            "subcategory":"Bank",
            "type":"Services"
        }
    ],
    "sg:phone":"+32 41374652",
    "sg:postcode":"4100",
    "sg:province":"Li\u00e8ge",
    "wof:name":"Banque Nagelmackers",
    "wof:placetype":"venue"
},
  "geometry": {"coordinates":[5.5113787651,50.5986251831],"type":"Point"}
}