{
  "type": "Feature",
  "properties": {
    "addr:full":"Groenstraat 31 Boechout Antwerpen 2530",
    "addr:housenumber":"31",
    "addr:postcode":"2530",
    "addr:street":"Groenstraat",
    "iso:country":"BE",
    "sg:address":"Groenstraat 31",
    "sg:city":"Boechout",
    "sg:classifiers":[
        {
            "category":"Banks & Credit Unions",
            "subcategory":"Investment Brokerage",
            "type":"Services"
        }
    ],
    "sg:phone":"+32 3 455 14 97",
    "sg:postcode":"2530",
    "sg:province":"Antwerpen",
    "sg:tags":[
        "auditor"
    ],
    "wof:name":"Vercammen M",
    "wof:placetype":"venue"
},
  "geometry": {"coordinates":[4.5065960884,51.1694030762],"type":"Point"}
}