{
  "type": "Feature",
  "properties": {
    "addr:full":"Bessemstraat 65 Waregem West-Vlaanderen 8790",
    "addr:housenumber":"65",
    "addr:postcode":"8790",
    "addr:street":"Bessemstraat",
    "iso:country":"BE",
    "sg:address":"Bessemstraat 65",
    "sg:city":"Waregem",
    "sg:orig_category":"GROENTEN AND FRUIT Groententeelt Rundveehouders",
    "sg:phone":"+32 56 61 43 88",
    "sg:postcode":"8790",
    "sg:province":"West-Vlaanderen",
    "wof:name":"Philip Van Overbeke",
    "wof:placetype":"venue"
},
  "geometry": {"coordinates":[3.455053091,50.8859901428],"type":"Point"}
}