{
  "type": "Feature",
  "properties": {
    "addr:full":"Ninoofsesteenweg 15 Pepingen Vlaams-Brabant 1670",
    "addr:housenumber":"15",
    "addr:postcode":"1670",
    "addr:street":"Ninoofsesteenweg",
    "iso:country":"BE",
    "sg:address":"Ninoofsesteenweg 15",
    "sg:city":"Pepingen",
    "sg:classifiers":[
        {
            "category":"Cafe",
            "type":"Food & Drink"
        }
    ],
    "sg:phone":"+32 2 361 51 96",
    "sg:postcode":"1670",
    "sg:province":"Vlaams-Brabant",
    "sg:tags":[
        "caf\u00e9s"
    ],
    "wof:name":"Delarivi\u00c8re-de Bosscher",
    "wof:placetype":"venue"
},
  "geometry": {"coordinates":[4.1845588684,50.7508049011],"type":"Point"}
}