{
  "type": "Feature",
  "properties": {
    "iso:country":"BE",
    "sg:address":"Breisemstraat 48",
    "sg:city":"Tienen",
    "sg:orig_category":"Drogisterijen Verlichting and huishoudartikelen",
    "sg:phone":"+32 16 81 19 68",
    "sg:postcode":"3300",
    "sg:province":"Vlaams-Brabant",
    "wof:name":"Huis Magda",
    "wof:placetype":"venue"
},
  "geometry": {"coordinates":[4.9258418083,50.8133811951],"type":"Point"}
}