{
  "type": "Feature",
  "properties": {
    "iso:country":"BE",
    "sg:address":"Krommenelststraat 32",
    "sg:city":"Ieper",
    "sg:orig_category":"Eleveurs de bovins",
    "sg:phone":"+32 57 20 21 92",
    "sg:postcode":"8908",
    "sg:province":"West-Vlaanderen",
    "wof:name":"Michel Desmedt",
    "wof:placetype":"venue"
},
  "geometry": {"coordinates":[2.8381779194,50.8426742554],"type":"Point"}
}