{
  "type": "Feature",
  "properties": {
    "addr:full":"Rue Pav\u00e9 Du Roeulx.z.i Str\u00e9py-bracquegnies Hainaut 7110",
    "addr:postcode":"7110",
    "addr:street":"Rue Pave\u0301 Du Roeulx.Z.I Stre\u0301Py-Bracquegnies Hainaut",
    "iso:country":"BE",
    "sg:address":"Rue Pav\u00e9 Du Roeulx.z.i",
    "sg:city":"Str\u00e9py-bracquegnies",
    "sg:classifiers":[
        {
            "category":"Autos & Motor Vehicles",
            "subcategory":"Auto Supplies",
            "type":"Retail Goods"
        }
    ],
    "sg:phone":"+32 64 67 17 00",
    "sg:postcode":"7110",
    "sg:province":"Hainaut",
    "sg:tags":[
        "body",
        "car",
        "truck",
        "trailer",
        "superstructure"
    ],
    "wof:name":"Nicod\u00e8me S.a.",
    "wof:placetype":"venue"
},
  "geometry": {"coordinates":[4.1505050659,50.4826698303],"type":"Point"}
}