{
  "type": "Feature",
  "properties": {
    "iso:country":"BE",
    "sg:address":"Rue Fr. Roosevelt 54",
    "sg:city":"Seraing",
    "sg:orig_category":"Traitements param\u00e9dicaux",
    "sg:phone":"+32 4 337 17 95",
    "sg:postcode":"4102",
    "sg:province":"Li\u00e8ge",
    "wof:name":"A. Waty",
    "wof:placetype":"venue"
},
  "geometry": {"coordinates":[5.5358119011,50.6015319824],"type":"Point"}
}