{
  "type": "Feature",
  "properties": {
    "addr:full":"Fazantenlaan 21b8 Meise Vlaams-Brabant 1860",
    "addr:housenumber":"21b8",
    "addr:postcode":"1860",
    "addr:street":"Fazantenlaan",
    "iso:country":"BE",
    "sg:address":"Fazantenlaan 21b8",
    "sg:city":"Meise",
    "sg:orig_category":"Kapsalons",
    "sg:phone":"+32 2 270 19 15",
    "sg:postcode":"1860",
    "sg:province":"Vlaams-Brabant",
    "wof:name":"Hair - Studio Marcoo",
    "wof:placetype":"venue"
},
  "geometry": {"coordinates":[4.341509819,50.9252891541],"type":"Point"}
}