{
  "type": "Feature",
  "properties": {
    "addr:full":"Meutelstraat 8 Bekkevoort Vlaams-Brabant 3460",
    "addr:housenumber":"8",
    "addr:postcode":"3460",
    "addr:street":"Meutelstraat",
    "iso:country":"BE",
    "sg:address":"Meutelstraat 8",
    "sg:city":"Bekkevoort",
    "sg:classifiers":[
        {
            "category":"Health Services",
            "subcategory":"Health Practitioner",
            "type":"Services"
        }
    ],
    "sg:phone":"+32 16 63 04 96",
    "sg:postcode":"3460",
    "sg:province":"Vlaams-Brabant",
    "sg:tags":[
        "therapist",
        "speech"
    ],
    "wof:name":"De Rijk K",
    "wof:placetype":"venue"
},
  "geometry": {"coordinates":[4.9501562119,50.9484367371],"type":"Point"}
}