{
  "type": "Feature",
  "properties": {
    "addr:full":"Rue Du Pont 12 Theux Li\u00e8ge 4910",
    "addr:housenumber":"12",
    "addr:postcode":"4910",
    "addr:street":"Rue Du Pont",
    "iso:country":"BE",
    "sg:address":"Rue Du Pont 12",
    "sg:city":"Theux",
    "sg:classifiers":[
        {
            "category":"Building & Trades",
            "subcategory":"Electrical",
            "type":"Services"
        }
    ],
    "sg:phone":"+32 87 53 02 95",
    "sg:postcode":"4910",
    "sg:province":"Li\u00e8ge",
    "sg:tags":[
        "industrial",
        "-",
        "electric",
        "contractor"
    ],
    "wof:name":"Delfosse P Electricite",
    "wof:placetype":"venue"
},
  "geometry": {"coordinates":[5.813849926,50.5367393494],"type":"Point"}
}