{
  "type": "Feature",
  "properties": {
    "iso:country":"BE",
    "sg:address":"Nieuw Dreef 5",
    "sg:city":"Hoogstraten",
    "sg:orig_category":"Pleisterwerk",
    "sg:phone":"+32 3 315 75 27",
    "sg:postcode":"2328",
    "sg:province":"Antwerpen",
    "wof:name":"Bastiaansen A.",
    "wof:placetype":"venue"
},
  "geometry": {"coordinates":[4.7713871002,51.4995651245],"type":"Point"}
}