{
  "type": "Feature",
  "properties": {
    "iso:country":"BE",
    "sg:address":"Keizersplein 66ba",
    "sg:city":"Aalst",
    "sg:orig_category":"Artsen and specialisten",
    "sg:phone":"+32 53 78 46 01",
    "sg:postcode":"9300",
    "sg:province":"Oost-Vlaanderen",
    "wof:name":"Jan Van De Velde",
    "wof:placetype":"venue"
},
  "geometry": {"coordinates":[4.0381579399,50.9357185364],"type":"Point"}
}