{
  "type": "Feature",
  "properties": {
    "addr:full":"Vijf Kruisenstraat 17 Riemst (valmeer) Limburg 3770",
    "addr:housenumber":"17",
    "addr:postcode":"3770",
    "addr:street":"Kruisenstraat",
    "iso:country":"BE",
    "sg:address":"Vijf Kruisenstraat 17",
    "sg:city":"Riemst (valmeer)",
    "sg:classifiers":[
        {
            "category":"Building & Trades",
            "subcategory":"Landscaping Services",
            "type":"Services"
        }
    ],
    "sg:phone":"+32 12 45 46 72",
    "sg:postcode":"3770",
    "sg:province":"Limburg",
    "sg:tags":[
        "gardening",
        "garden",
        "maintenance"
    ],
    "wof:name":"Flora Design Bvba",
    "wof:placetype":"venue"
},
  "geometry": {"coordinates":[5.6017508507,50.7806434631],"type":"Point"}
}