{
  "type": "Feature",
  "properties": {
    "addr:full":"Rue Auguste Lev\u00eaque 4 Nivelles Brabant Wallon 1400",
    "addr:housenumber":"4",
    "addr:postcode":"1400",
    "addr:street":"Rue Auguste Leve\u0302Que",
    "iso:country":"BE",
    "sg:address":"Rue Auguste Lev\u00eaque 4",
    "sg:city":"Nivelles",
    "sg:classifiers":[
        {
            "category":"Bars & Pubs",
            "type":"Food & Drink"
        }
    ],
    "sg:phone":"+32 67 21 38 94",
    "sg:postcode":"1400",
    "sg:province":"Brabant Wallon",
    "wof:name":"Quatre Colonnes (les)",
    "wof:placetype":"venue"
},
  "geometry": {"coordinates":[4.3381118774,50.6029510498],"type":"Point"}
}