{
  "type": "Feature",
  "properties": {
    "iso:country":"BE",
    "sg:address":"Rue De La Digue 1",
    "sg:city":"Oupeye",
    "sg:orig_category":"Benzinestations and brandstoffen",
    "sg:phone":"+32 4 248 30 44",
    "sg:postcode":"4683",
    "sg:province":"Li\u00e8ge",
    "wof:name":"Jumbo Service",
    "wof:placetype":"venue"
},
  "geometry": {"coordinates":[5.6495499611,50.6958198547],"type":"Point"}
}