{
  "type": "Feature",
  "properties": {
    "iso:country":"BE",
    "sg:address":"Grensstraat 60",
    "sg:city":"Bilzen",
    "sg:orig_category":"Woningbouw",
    "sg:phone":"+32 11 58 29 26",
    "sg:postcode":"3740",
    "sg:province":"Limburg",
    "wof:name":"Bouwbedrijf Epa",
    "wof:placetype":"venue"
},
  "geometry": {"coordinates":[5.4693207741,50.9163322449],"type":"Point"}
}