{
  "type": "Feature",
  "properties": {
    "addr:full":"Rue Henri Neuman 51 Braine-le-comte Hainaut 7090",
    "addr:housenumber":"51",
    "addr:postcode":"7090",
    "addr:street":"Rue Henri Neuman",
    "iso:country":"BE",
    "sg:address":"Rue Henri Neuman 51",
    "sg:city":"Braine-le-comte",
    "sg:classifiers":[
        {
            "category":"Military Area",
            "subcategory":"Air Force Base",
            "type":"Public Place"
        }
    ],
    "sg:phone":"+32 67 55 38 18",
    "sg:postcode":"7090",
    "sg:province":"Hainaut",
    "sg:tags":[
        "herb",
        "-",
        "medicinal"
    ],
    "wof:name":"Mere Nature Scrl",
    "wof:placetype":"venue"
},
  "geometry": {"coordinates":[4.1395277977,50.6098442078],"type":"Point"}
}