{
  "type": "Feature",
  "properties": {
    "addr:full":"De Meulenaerstraat 27 Sint-niklaas Oost-Vlaanderen 9100",
    "addr:housenumber":"27",
    "addr:postcode":"9100",
    "addr:street":"Meulenaerstraat",
    "iso:country":"BE",
    "sg:address":"De Meulenaerstraat 27",
    "sg:city":"Sint-niklaas",
    "sg:classifiers":[
        {
            "category":"Professional",
            "subcategory":"Art Services",
            "type":"Services"
        }
    ],
    "sg:phone":"+32 16 81 21 28",
    "sg:postcode":"9100",
    "sg:province":"Oost-Vlaanderen",
    "sg:tags":[
        "picture",
        "framer"
    ],
    "wof:name":"Van Bellegem E",
    "wof:placetype":"venue"
},
  "geometry": {"coordinates":[4.1622219086,51.151802063],"type":"Point"}
}