{
  "type": "Feature",
  "properties": {
    "addr:full":"Stadionstraat 27 Stekene Oost-Vlaanderen 9190",
    "addr:housenumber":"27",
    "addr:postcode":"9190",
    "addr:street":"Stadionstraat",
    "iso:country":"BE",
    "sg:address":"Stadionstraat 27",
    "sg:city":"Stekene",
    "sg:classifiers":[
        {
            "category":"Insurance",
            "subcategory":"Insurance Agent",
            "type":"Services"
        }
    ],
    "sg:phone":"+32 3 779 73 92",
    "sg:postcode":"9190",
    "sg:province":"Oost-Vlaanderen",
    "sg:tags":[
        "verzekeringsmakelaars",
        "expert"
    ],
    "wof:name":"Edmond Dubelloy",
    "wof:placetype":"venue"
},
  "geometry": {"coordinates":[4.0419111252,51.2052993774],"type":"Point"}
}