{
  "type": "Feature",
  "properties": {
    "addr:full":"Rue Dusquenoy 11 Tournai Hainaut 7500",
    "addr:housenumber":"11",
    "addr:postcode":"7500",
    "addr:street":"Rue Dusquenoy",
    "iso:country":"BE",
    "sg:address":"Rue Dusquenoy 11",
    "sg:city":"Tournai",
    "sg:classifiers":[
        {
            "category":"Bars & Pubs",
            "type":"Food & Drink"
        }
    ],
    "sg:phone":"+32 69 23 30 05",
    "sg:postcode":"7500",
    "sg:province":"Hainaut",
    "wof:name":"Stefen\u00b4s Caf\u00c9",
    "wof:placetype":"venue"
},
  "geometry": {"coordinates":[3.3867199421,50.606098175],"type":"Point"}
}