{
  "type": "Feature",
  "properties": {
    "addr:full":"Vuntlaan 62 Leuven (wilsele) Vlaams-Brabant 3012",
    "addr:housenumber":"62",
    "addr:postcode":"3012",
    "addr:street":"Vuntlaan",
    "iso:country":"BE",
    "sg:address":"Vuntlaan 62",
    "sg:city":"Leuven (wilsele)",
    "sg:classifiers":[
        {
            "category":"Wholesale",
            "subcategory":"Poultry",
            "type":"Manufacturing & Wholesale Goods"
        }
    ],
    "sg:phone":"+32 16 44 35 58",
    "sg:postcode":"3012",
    "sg:province":"Vlaams-Brabant",
    "sg:tags":[
        "whol",
        "-",
        "egg"
    ],
    "wof:name":"Borgers J",
    "wof:placetype":"venue"
},
  "geometry": {"coordinates":[4.7134780884,50.9216651917],"type":"Point"}
}