{
  "type": "Feature",
  "properties": {
    "addr:full":"Chauss\u00e9e De Merchtem 238 Wemmel Vlaams-Brabant 1780",
    "addr:housenumber":"238",
    "addr:postcode":"1780",
    "addr:street":"Chausse\u0301E De Merchtem;Vlaams-Brabant",
    "iso:country":"BE",
    "sg:address":"Chauss\u00e9e De Merchtem 238",
    "sg:city":"Wemmel",
    "sg:classifiers":[
        {
            "category":"Building & Trades",
            "subcategory":"Cleaning & Sanitation",
            "type":"Services"
        }
    ],
    "sg:phone":"+32 2 460 37 35",
    "sg:postcode":"1780",
    "sg:province":"Vlaams-Brabant",
    "sg:tags":[
        "cleaner",
        "window"
    ],
    "wof:name":"Bekkers A",
    "wof:placetype":"venue"
},
  "geometry": {"coordinates":[4.3003997803,50.911239624],"type":"Point"}
}