{
  "type": "Feature",
  "properties": {
    "iso:country":"BE",
    "sg:address":"Baasrodeveerstraat 57",
    "sg:city":"Hamme",
    "sg:orig_category":"Producteurs de l\u00e9gumes",
    "sg:phone":"+32 52 48 31 22",
    "sg:postcode":"9220",
    "sg:province":"Oost-Vlaanderen",
    "wof:name":"Alex Nobels",
    "wof:placetype":"venue"
},
  "geometry": {"coordinates":[4.1696138382,51.0453796387],"type":"Point"}
}