{
  "type": "Feature",
  "properties": {
    "addr:full":"Rue Albert I 12 Hannut Li\u00e8ge 4280",
    "addr:housenumber":"12",
    "addr:postcode":"4280",
    "addr:street":"Rue Albert I",
    "iso:country":"BE",
    "sg:address":"Rue Albert I 12",
    "sg:city":"Hannut",
    "sg:classifiers":[
        {
            "category":"Professional",
            "subcategory":"Art Services",
            "type":"Services"
        }
    ],
    "sg:phone":"+32 19 51 51 51",
    "sg:postcode":"4280",
    "sg:province":"Li\u00e8ge",
    "sg:tags":[
        "picture",
        "framer"
    ],
    "wof:name":"Cadre Et Graph",
    "wof:placetype":"venue"
},
  "geometry": {"coordinates":[5.0801420212,50.6710472107],"type":"Point"}
}