{
  "type": "Feature",
  "properties": {
    "iso:country":"BE",
    "sg:address":"Geuzestraat 12ba",
    "sg:city":"Knesselare",
    "sg:orig_category":"Installation \u00e9lectrique r\u00e9sidentielle",
    "sg:phone":"+32 9 374 53 38",
    "sg:postcode":"9910",
    "sg:province":"Oost-Vlaanderen",
    "wof:name":"Freddy Claeys",
    "wof:placetype":"venue"
},
  "geometry": {"coordinates":[3.4096999168,51.1503295898],"type":"Point"}
}