{
  "type": "Feature",
  "properties": {
    "iso:country":"BE",
    "sg:address":"Rivierstraat 59",
    "sg:city":"Lochristi",
    "sg:orig_category":"Plantes and fleurs Gr",
    "sg:phone":"+32 9 355 66 58",
    "sg:postcode":"9080",
    "sg:province":"Oost-Vlaanderen",
    "wof:name":"Rombaut-bettens",
    "wof:placetype":"venue"
},
  "geometry": {"coordinates":[3.8817090988,51.0734977722],"type":"Point"}
}