{
  "type": "Feature",
  "properties": {
    "iso:country":"BE",
    "sg:address":"Rundershoek 12",
    "sg:city":"Laakdal (eindhout)",
    "sg:classifiers":[
        {
            "category":"Retail",
            "subcategory":"Animal Services",
            "type":"Services"
        }
    ],
    "sg:phone":"+32 14 86 93 75",
    "sg:postcode":"2430",
    "sg:province":"Antwerpen",
    "sg:tags":[
        "grooming",
        "-",
        "dog"
    ],
    "wof:name":"Ujbarati Trimsalon",
    "wof:placetype":"venue"
},
  "geometry": {"coordinates":[5.0687851906,51.0857543945],"type":"Point"}
}