{
  "type": "Feature",
  "properties": {
    "addr:full":"Thonissenlaan 86 Hasselt Limburg 3500",
    "addr:housenumber":"86",
    "addr:postcode":"3500",
    "addr:street":"Thonissenlaan",
    "iso:country":"BE",
    "sg:address":"Thonissenlaan 86",
    "sg:city":"Hasselt",
    "sg:classifiers":[
        {
            "category":"Health Services",
            "subcategory":"Health Practitioner",
            "type":"Services"
        }
    ],
    "sg:phone":"+32 11 20 19 02",
    "sg:postcode":"3500",
    "sg:province":"Limburg",
    "sg:tags":[
        "alternative",
        "therapy",
        "treatment"
    ],
    "wof:name":"Zonnepoort (de)",
    "wof:placetype":"venue"
},
  "geometry": {"coordinates":[5.3362550735,50.9340019226],"type":"Point"}
}