{
  "type": "Feature",
  "properties": {
    "iso:country":"BE",
    "sg:address":"Dikkebusseweg 576",
    "sg:city":"Ieper (dikkebus)",
    "sg:classifiers":[
        {
            "category":"Farming",
            "subcategory":"Livestock Farm",
            "type":"Manufacturing & Wholesale Goods"
        }
    ],
    "sg:phone":"+32 57 20 33 45",
    "sg:postcode":"8900",
    "sg:province":"West-Vlaanderen",
    "sg:tags":[
        "buyer"
    ],
    "wof:name":"Vanhoorneweder H",
    "wof:placetype":"venue"
},
  "geometry": {"coordinates":[2.8651199341,50.8389701843],"type":"Point"}
}