{
  "type": "Feature",
  "properties": {
    "addr:full":"Sint-elisabethplein 10 Gent Oost-Vlaanderen 9000",
    "addr:housenumber":"10",
    "addr:postcode":"9000",
    "addr:street":"Sint-Elisabethplein;Oost-Vlaanderen",
    "iso:country":"BE",
    "sg:address":"Sint-elisabethplein 10",
    "sg:city":"Gent",
    "sg:orig_category":"Studios photographiques",
    "sg:phone":"+32 9 223 19 00",
    "sg:postcode":"9000",
    "sg:province":"Oost-Vlaanderen",
    "wof:name":"Christian Kirschen",
    "wof:placetype":"venue"
},
  "geometry": {"coordinates":[3.7142400742,51.0567092896],"type":"Point"}
}