{
  "type": "Feature",
  "properties": {
    "iso:country":"BE",
    "sg:address":"Afrikalaan 48",
    "sg:city":"Gent",
    "sg:classifiers":[
        {
            "category":"Train Station",
            "subcategory":"Rail",
            "type":"Transportation"
        }
    ],
    "sg:phone":"+32 9 233 95 20",
    "sg:postcode":"9000",
    "sg:province":"Oost-Vlaanderen",
    "sg:tags":[
        "ship",
        "chandler"
    ],
    "wof:name":"New Generation Shipstores",
    "wof:placetype":"venue"
},
  "geometry": {"coordinates":[3.7393100262,51.0646095276],"type":"Point"}
}