{
  "type": "Feature",
  "properties": {
    "addr:full":"Nieuwstraat 21 Peer Limburg 3990",
    "addr:housenumber":"21",
    "addr:postcode":"3990",
    "addr:street":"Nieuwstraat",
    "iso:country":"BE",
    "sg:address":"Nieuwstraat 21",
    "sg:city":"Peer",
    "sg:classifiers":[
        {
            "category":"Building & Trades",
            "subcategory":"Electrical",
            "type":"Services"
        }
    ],
    "sg:phone":"+32 11 63 21 73",
    "sg:postcode":"3990",
    "sg:province":"Limburg",
    "sg:tags":[
        "electric",
        "-",
        "housewiring",
        "contractor"
    ],
    "wof:name":"Lichtpunt Bvba",
    "wof:placetype":"venue"
},
  "geometry": {"coordinates":[5.4550509453,51.1333770752],"type":"Point"}
}