{
  "type": "Feature",
  "properties": {
    "addr:full":"Kroonstraat 23 Borgloon Limburg 3840",
    "addr:housenumber":"23",
    "addr:postcode":"3840",
    "addr:street":"Kroonstraat",
    "iso:country":"BE",
    "sg:address":"Kroonstraat 23",
    "sg:city":"Borgloon",
    "sg:orig_category":"V\u00e9t\u00e9rinaires",
    "sg:phone":"+32 12 74 18 70",
    "sg:postcode":"3840",
    "sg:province":"Limburg",
    "wof:name":"Remigius Vrancken",
    "wof:placetype":"venue"
},
  "geometry": {"coordinates":[5.3452758789,50.8024368286],"type":"Point"}
}