{
  "type": "Feature",
  "properties": {
    "addr:full":"Rue De Goz\u00e9e 470 Montigny-le-tilleul Hainaut 6110",
    "addr:housenumber":"470",
    "addr:postcode":"6110",
    "addr:street":"Rue De Goze\u0301E",
    "iso:country":"BE",
    "sg:address":"Rue De Goz\u00e9e 470",
    "sg:city":"Montigny-le-tilleul",
    "sg:classifiers":[
        {
            "category":"Personal",
            "subcategory":"Beauty Salon",
            "type":"Services"
        }
    ],
    "sg:phone":"+32 71 51 18 51",
    "sg:postcode":"6110",
    "sg:province":"Hainaut",
    "sg:tags":[
        "lady",
        "-",
        "hairdressing"
    ],
    "wof:name":"Stud'hair",
    "wof:placetype":"venue"
},
  "geometry": {"coordinates":[4.3682889938,50.3754997253],"type":"Point"}
}