{
  "type": "Feature",
  "properties": {
    "addr:full":"Herderstraat 6 Sint-truiden (brustem) Limburg 3800",
    "addr:housenumber":"6",
    "addr:postcode":"3800",
    "addr:street":"Herderstraat",
    "iso:country":"BE",
    "sg:address":"Herderstraat 6",
    "sg:city":"Sint-truiden (brustem)",
    "sg:classifiers":[
        {
            "category":"Building & Trades",
            "subcategory":"Construction",
            "type":"Services"
        }
    ],
    "sg:phone":"+32 11 70 75 35",
    "sg:postcode":"3800",
    "sg:province":"Limburg",
    "sg:tags":[
        "installation",
        "-",
        "central",
        "heating"
    ],
    "wof:name":"Lacroix S",
    "wof:placetype":"venue"
},
  "geometry": {"coordinates":[5.2216739655,50.8020553589],"type":"Point"}
}