{
  "type": "Feature",
  "properties": {
    "addr:full":"Chauss\u00c9e De Tongres 269 Li\u00c8ge Li\u00e8ge 4000",
    "addr:housenumber":"269",
    "addr:postcode":"4000",
    "addr:street":"Chausse\u0301E De Tongres",
    "iso:country":"BE",
    "sg:address":"Chauss\u00c9e De Tongres 269",
    "sg:city":"Li\u00c8ge",
    "sg:classifiers":[
        {
            "category":"Restaurant",
            "type":"Food & Drink"
        }
    ],
    "sg:phone":"+32 3 314 87 08",
    "sg:postcode":"4000",
    "sg:province":"Li\u00e8ge",
    "wof:name":"Ac Restaurant",
    "wof:placetype":"venue"
},
  "geometry": {"coordinates":[4.4110541344,51.1906738281],"type":"Point"}
}