{
  "type": "Feature",
  "properties": {
    "addr:full":"Erasme Ruelensvest 177 Leuven Vlaams-Brabant 3001",
    "addr:housenumber":"177",
    "addr:postcode":"3001",
    "addr:street":"Erasme Ruelensvest",
    "iso:country":"BE",
    "sg:address":"Erasme Ruelensvest 177",
    "sg:city":"Leuven",
    "sg:classifiers":[
        {
            "category":"Insurance",
            "subcategory":"Insurance Agent",
            "type":"Services"
        }
    ],
    "sg:phone":"+32 16 29 30 33",
    "sg:postcode":"3001",
    "sg:province":"Vlaams-Brabant",
    "sg:tags":[
        "verzekeringsmakelaars",
        "expert"
    ],
    "wof:name":"Cockx Piet",
    "wof:placetype":"venue"
},
  "geometry": {"coordinates":[4.7071218491,50.8686332703],"type":"Point"}
}