{
  "type": "Feature",
  "properties": {
    "addr:full":"Rue De Marette 8 La Bruy\u00e8re (bovesse) Namur 5081",
    "addr:housenumber":"8",
    "addr:postcode":"5081",
    "addr:street":"Rue De Marette",
    "iso:country":"BE",
    "sg:address":"Rue De Marette 8",
    "sg:city":"La Bruy\u00e8re (bovesse)",
    "sg:classifiers":[
        {
            "category":"Building & Trades",
            "subcategory":"Landscaping Services",
            "type":"Services"
        }
    ],
    "sg:phone":"+32 81 56 83 33",
    "sg:postcode":"5081",
    "sg:province":"Namur",
    "sg:tags":[
        "gardening",
        "garden",
        "maintenance"
    ],
    "wof:name":"Rowet E",
    "wof:placetype":"venue"
},
  "geometry": {"coordinates":[4.7674279213,50.5095100403],"type":"Point"}
}