{
  "type": "Feature",
  "properties": {
    "iso:country":"BE",
    "sg:address":"Avenue Seigneurie De Spontin 17",
    "sg:city":"Wavre",
    "sg:orig_category":"Rev\u00eatements pour sols and murs. Peinture",
    "sg:phone":"+32 10 22 54 81",
    "sg:postcode":"1300",
    "sg:province":"Brabant Wallon",
    "wof:name":"Nicolas Courtois",
    "wof:placetype":"venue"
},
  "geometry": {"coordinates":[4.6309990883,50.7155036926],"type":"Point"}
}