{
  "type": "Feature",
  "properties": {
    "addr:full":"Rostynedreef 32 Aalter Oost-Vlaanderen 9880",
    "addr:housenumber":"32",
    "addr:postcode":"9880",
    "addr:street":"Rostynedreef",
    "iso:country":"BE",
    "sg:address":"Rostynedreef 32",
    "sg:city":"Aalter",
    "sg:classifiers":[
        {
            "category":"Professional",
            "subcategory":"Management & Consulting",
            "type":"Services"
        }
    ],
    "sg:phone":"+32 9 325 00 75",
    "sg:postcode":"9880",
    "sg:province":"Oost-Vlaanderen",
    "sg:tags":[
        "consultant"
    ],
    "wof:name":"S & O Advice Bvba",
    "wof:placetype":"venue"
},
  "geometry": {"coordinates":[3.4717299938,51.0762405396],"type":"Point"}
}