{
  "type": "Feature",
  "properties": {
    "addr:full":"Avenue Des Lilas 32 Wezembeek-oppem/wezembeek-oppem Vlaams-Brabant 1970",
    "addr:housenumber":"32",
    "addr:postcode":"1970",
    "addr:street":"Avenue Des Lilas",
    "iso:country":"BE",
    "sg:address":"Avenue Des Lilas 32",
    "sg:city":"Wezembeek-oppem/wezembeek-oppem",
    "sg:orig_category":"M\u00e9decins and sp\u00e9cialistes",
    "sg:phone":"+32 2 731 29 26",
    "sg:postcode":"1970",
    "sg:province":"Vlaams-Brabant",
    "wof:name":"Geoffroy De Granges De Surg\u00c8res",
    "wof:placetype":"venue"
},
  "geometry": {"coordinates":[4.5025048256,50.848739624],"type":"Point"}
}