{
  "type": "Feature",
  "properties": {
    "iso:country":"BE",
    "sg:address":"Place G\u00e9neral Mac Auliffe 6",
    "sg:city":"Bastogne",
    "sg:classifiers":[
        {
            "category":"Food & Beverages",
            "subcategory":"Fruits & Vegetables",
            "type":"Retail Goods"
        }
    ],
    "sg:phone":"+32 61 21 14 00",
    "sg:postcode":"6600",
    "sg:province":"Luxembourg",
    "sg:tags":[
        "-"
    ],
    "wof:name":"Petit Rungis",
    "wof:placetype":"venue"
},
  "geometry": {"coordinates":[5.7153759003,50.0011978149],"type":"Point"}
}