{
  "type": "Feature",
  "properties": {
    "addr:full":"Rue De La Lib\u00c9ration 1a Anh\u00c9e Namur 5537",
    "addr:housenumber":"1a",
    "addr:postcode":"5537",
    "addr:street":"Rue De La Libe\u0301Ration",
    "iso:country":"BE",
    "sg:address":"Rue De La Lib\u00c9ration 1a",
    "sg:city":"Anh\u00c9e",
    "sg:orig_category":"Kampeerterreinen",
    "sg:phone":"+32 82 69 90 90",
    "sg:postcode":"5537",
    "sg:province":"Namur",
    "wof:name":"Les Deux Vall\u00c9es",
    "wof:placetype":"venue"
},
  "geometry": {"coordinates":[4.87586689,50.3140220642],"type":"Point"}
}