{
  "type": "Feature",
  "properties": {
    "addr:full":"Oudenaardsestraat 233 Geraardsbergen Oost-Vlaanderen 9500",
    "addr:housenumber":"233",
    "addr:postcode":"9500",
    "addr:street":"Oudenaardsestraat",
    "iso:country":"BE",
    "sg:address":"Oudenaardsestraat 233",
    "sg:city":"Geraardsbergen",
    "sg:classifiers":[
        {
            "category":"Retail",
            "subcategory":"Funeral Services",
            "type":"Services"
        }
    ],
    "sg:phone":"+32 54 41 58 23",
    "sg:postcode":"9500",
    "sg:province":"Oost-Vlaanderen",
    "sg:tags":[
        "director"
    ],
    "wof:name":"Moulart & Herregodts Begrafenisonderneming Bvba",
    "wof:placetype":"venue"
},
  "geometry": {"coordinates":[3.8688800335,50.7724113464],"type":"Point"}
}