{
  "type": "Feature",
  "properties": {
    "iso:country":"BE",
    "sg:address":"Kasteelstraat 37",
    "sg:city":"Temse",
    "sg:orig_category":"Apotheken",
    "sg:phone":"+32 3 771 06 26",
    "sg:postcode":"9140",
    "sg:province":"Oost-Vlaanderen",
    "wof:name":"Multipharma",
    "wof:placetype":"venue"
},
  "geometry": {"coordinates":[4.2162227631,51.1243476868],"type":"Point"}
}