{
  "type": "Feature",
  "properties": {
    "addr:full":"Crapaurue 14 Verviers Li\u00e8ge 4800",
    "addr:housenumber":"14",
    "addr:postcode":"4800",
    "addr:street":"Crapaurue",
    "iso:country":"BE",
    "sg:address":"Crapaurue 14",
    "sg:city":"Verviers",
    "sg:orig_category":"Banken and kredietinstellingen",
    "sg:phone":"+32 87 31 49 29",
    "sg:postcode":"4800",
    "sg:province":"Li\u00e8ge",
    "wof:name":"Dexia",
    "wof:placetype":"venue"
},
  "geometry": {"coordinates":[5.8664288521,50.5929641724],"type":"Point"}
}