{
  "type": "Feature",
  "properties": {
    "iso:country":"BE",
    "sg:address":"Provincialebaan 136",
    "sg:city":"Buggenhout",
    "sg:classifiers":[
        {
            "category":"Home & Garden",
            "subcategory":"Hardware",
            "type":"Retail Goods"
        }
    ],
    "sg:phone":"+32 52 33 24 09",
    "sg:postcode":"9255",
    "sg:province":"Oost-Vlaanderen",
    "sg:tags":[
        "soldering",
        "equipment",
        "welding",
        "-",
        "supply"
    ],
    "wof:name":"De Kinder Hardware Nv",
    "wof:placetype":"venue"
},
  "geometry": {"coordinates":[4.1914110184,51.0306549072],"type":"Point"}
}