{
  "type": "Feature",
  "properties": {
    "iso:country":"BE",
    "sg:address":"Putsebaan 27",
    "sg:city":"Antwerpen",
    "sg:orig_category":"Pain, p\u00e2tisseries and confiseries",
    "sg:phone":"+32 3 568 61 24",
    "sg:postcode":"2040",
    "sg:province":"Antwerpen",
    "wof:name":"Patrick Cocquyt",
    "wof:placetype":"venue"
},
  "geometry": {"coordinates":[4.3311300278,51.3580284119],"type":"Point"}
}