{
  "type": "Feature",
  "properties": {
    "iso:country":"BE",
    "sg:address":"Kleine Steenstraat 22",
    "sg:city":"Erpe-mere (mere)",
    "sg:classifiers":[
        {
            "category":"Professional",
            "subcategory":"Art Services",
            "type":"Services"
        }
    ],
    "sg:phone":"+32 53 83 91 49",
    "sg:postcode":"9420",
    "sg:province":"Oost-Vlaanderen",
    "sg:tags":[
        "interior",
        "designer"
    ],
    "wof:name":"De Doncker E",
    "wof:placetype":"venue"
},
  "geometry": {"coordinates":[3.9694778919,50.9216003418],"type":"Point"}
}