{
  "type": "Feature",
  "properties": {
    "iso:country":"BE",
    "sg:address":"Carnotstraat 47 Box 1",
    "sg:city":"Antwerpen",
    "sg:classifiers":[
        {
            "category":"Social Services",
            "type":"Services"
        }
    ],
    "sg:phone":"+32 3 233 50 72",
    "sg:postcode":"2060",
    "sg:province":"Antwerpen",
    "wof:name":"Vlaams Verbond Voor Gepensioneerden",
    "wof:placetype":"venue"
},
  "geometry": {"coordinates":[4.4239521027,51.2186737061],"type":"Point"}
}