{
  "type": "Feature",
  "properties": {
    "iso:country":"BE",
    "sg:address":"Rue De La Promenade 39",
    "sg:city":"Messancy",
    "sg:classifiers":[
        {
            "category":"Airport",
            "subcategory":"International",
            "type":"Transportation"
        }
    ],
    "sg:phone":"+32 63 38 88 15",
    "sg:postcode":"6780",
    "sg:province":"Luxembourg",
    "sg:tags":[
        "-",
        "transport"
    ],
    "wof:name":"Watry",
    "wof:placetype":"venue"
},
  "geometry": {"coordinates":[5.8212041855,49.5972290039],"type":"Point"}
}