{
  "type": "Feature",
  "properties": {
    "addr:full":"Muntstraat 40 Leuven Vlaams-Brabant 3000",
    "addr:housenumber":"40",
    "addr:postcode":"3000",
    "addr:street":"Muntstraat",
    "iso:country":"BE",
    "sg:address":"Muntstraat 40",
    "sg:city":"Leuven",
    "sg:orig_category":"Ordinateurs and \u00e9quipement informatique. Entretien and r\u00e9parations de machines de bureau and ordinat",
    "sg:phone":"+32 16 23 57 44",
    "sg:postcode":"3000",
    "sg:province":"Vlaams-Brabant",
    "wof:name":"Personal Computer Suppl.",
    "wof:placetype":"venue"
},
  "geometry": {"coordinates":[4.7030229568,50.8778915405],"type":"Point"}
}