{
  "type": "Feature",
  "properties": {
    "iso:country":"BE",
    "sg:address":"Route De Bavay 180",
    "sg:city":"Frameries",
    "sg:classifiers":[
        {
            "category":"Cafe",
            "type":"Food & Drink"
        }
    ],
    "sg:phone":"+32 65 66 58 38",
    "sg:postcode":"7080",
    "sg:province":"Hainaut",
    "sg:tags":[
        "caf\u00e9s"
    ],
    "wof:name":"Vito Micciche",
    "wof:placetype":"venue"
},
  "geometry": {"coordinates":[3.9189360142,50.4040336609],"type":"Point"}
}