{
  "type": "Feature",
  "properties": {
    "addr:full":"Hagelandstraat 30 Halen Limburg 3545",
    "addr:housenumber":"30",
    "addr:postcode":"3545",
    "addr:street":"Hagelandstraat",
    "iso:country":"BE",
    "sg:address":"Hagelandstraat 30",
    "sg:city":"Halen",
    "sg:classifiers":[
        {
            "category":"Manufacturing",
            "subcategory":"Lumber",
            "type":"Manufacturing & Wholesale Goods"
        }
    ],
    "sg:phone":"+32 13 46 02 80",
    "sg:postcode":"3545",
    "sg:province":"Limburg",
    "sg:tags":[
        "timber"
    ],
    "wof:name":"Brems Products",
    "wof:placetype":"venue"
},
  "geometry": {"coordinates":[5.0579819679,50.9326667786],"type":"Point"}
}