{
  "type": "Feature",
  "properties": {
    "iso:country":"BE",
    "sg:address":"Werf 13",
    "sg:city":"Lier",
    "sg:orig_category":"Boissons",
    "sg:phone":"+32 3 480 75 95",
    "sg:postcode":"2500",
    "sg:province":"Antwerpen",
    "wof:name":"Australian Fine Wines",
    "wof:placetype":"venue"
},
  "geometry": {"coordinates":[4.57143116,51.1292610168],"type":"Point"}
}