{
  "type": "Feature",
  "properties": {
    "addr:full":"Rue Jules Destr\u00e9e 425 Quaregnon Hainaut 7390",
    "addr:housenumber":"425",
    "addr:postcode":"7390",
    "addr:street":"Rue Jules Destre\u0301E",
    "iso:country":"BE",
    "sg:address":"Rue Jules Destr\u00e9e 425",
    "sg:city":"Quaregnon",
    "sg:classifiers":[
        {
            "category":"Utilities",
            "subcategory":"Telephone",
            "type":"Services"
        }
    ],
    "sg:phone":"+32 65 78 30 05",
    "sg:postcode":"7390",
    "sg:province":"Hainaut",
    "sg:tags":[
        "-",
        "internet"
    ],
    "wof:name":"Ypaq System",
    "wof:placetype":"venue"
},
  "geometry": {"coordinates":[3.854927063,50.4424858093],"type":"Point"}
}