{
  "type": "Feature",
  "properties": {
    "addr:full":"Leuvensesteenweg 88 Diest Vlaams-Brabant 3290",
    "addr:housenumber":"88",
    "addr:postcode":"3290",
    "addr:street":"Leuvensesteenweg",
    "iso:country":"BE",
    "sg:address":"Leuvensesteenweg 88",
    "sg:city":"Diest",
    "sg:classifiers":[
        {
            "category":"Shopping",
            "subcategory":"Clothing, Apparel, & Fashions",
            "type":"Retail Goods"
        }
    ],
    "sg:phone":"+32 13 31 46 78",
    "sg:postcode":"3290",
    "sg:province":"Vlaams-Brabant",
    "sg:tags":[
        "lady",
        "clothing",
        "-"
    ],
    "wof:name":"E 5 Mode",
    "wof:placetype":"venue"
},
  "geometry": {"coordinates":[5.0439658165,50.9771080017],"type":"Point"}
}