{
  "type": "Feature",
  "properties": {
    "addr:full":"Rue Albert I 30 P\u00e9ruwelz Hainaut 7600",
    "addr:housenumber":"30",
    "addr:postcode":"7600",
    "addr:street":"Rue Albert I",
    "iso:country":"BE",
    "sg:address":"Rue Albert I 30",
    "sg:city":"P\u00e9ruwelz",
    "sg:classifiers":[
        {
            "category":"Shopping",
            "subcategory":"Pharmacy",
            "type":"Retail Goods"
        }
    ],
    "sg:phone":"+32 69 77 22 89",
    "sg:postcode":"7600",
    "sg:province":"Hainaut",
    "sg:tags":[
        "store",
        "drug"
    ],
    "wof:name":"De Weireld Sprl",
    "wof:placetype":"venue"
},
  "geometry": {"coordinates":[3.5911960602,50.5087890625],"type":"Point"}
}