{
  "type": "Feature",
  "properties": {
    "iso:country":"BE",
    "sg:address":"Universitaire Campus",
    "sg:city":"Diepenbeek",
    "sg:classifiers":[
        {
            "category":"Education",
            "subcategory":"University",
            "type":"Public Place"
        }
    ],
    "sg:phone":"+32 11 23 07 90",
    "sg:postcode":"3590",
    "sg:province":"Limburg",
    "sg:tags":[
        "higher"
    ],
    "wof:name":"Katholieke Hogeschool Limburg",
    "wof:placetype":"venue"
},
  "geometry": {"coordinates":[5.3969478607,50.9298744202],"type":"Point"}
}