{
  "type": "Feature",
  "properties": {
    "addr:full":"Rue Boutonville 12 Chimay Hainaut 6464",
    "addr:housenumber":"12",
    "addr:postcode":"6464",
    "addr:street":"Rue Boutonville",
    "iso:country":"BE",
    "sg:address":"Rue Boutonville 12",
    "sg:city":"Chimay",
    "sg:orig_category":"Eleveurs de bovins",
    "sg:phone":"+32 60 21 19 07",
    "sg:postcode":"6464",
    "sg:province":"Hainaut",
    "wof:name":"Achille Bertrand",
    "wof:placetype":"venue"
},
  "geometry": {"coordinates":[4.3915948868,50.0375900269],"type":"Point"}
}