{
  "type": "Feature",
  "properties": {
    "addr:full":"Aarschotsesteenweg 468 Tienen Vlaams-Brabant 3300",
    "addr:housenumber":"468",
    "addr:postcode":"3300",
    "addr:street":"Aarschotsesteenweg",
    "iso:country":"BE",
    "sg:address":"Aarschotsesteenweg 468",
    "sg:city":"Tienen",
    "sg:classifiers":[
        {
            "category":"Insurance",
            "subcategory":"Insurance Agent",
            "type":"Services"
        }
    ],
    "sg:phone":"+32 16 81 08 83",
    "sg:postcode":"3300",
    "sg:province":"Vlaams-Brabant",
    "sg:tags":[
        "broker"
    ],
    "wof:name":"Van Gucht Verzekeringen",
    "wof:placetype":"venue"
},
  "geometry": {"coordinates":[4.9231991768,50.8262557983],"type":"Point"}
}