{
  "type": "Feature",
  "properties": {
    "iso:country":"BE",
    "sg:address":"Kerklei 8",
    "sg:city":"Brecht",
    "sg:classifiers":[
        {
            "category":"Restaurant",
            "type":"Food & Drink"
        }
    ],
    "sg:phone":"+32 3 636 24 92",
    "sg:postcode":"2960",
    "sg:province":"Antwerpen",
    "sg:tags":[
        "caf\u00e9s"
    ],
    "wof:name":"Taverne Yellow Stone",
    "wof:placetype":"venue"
},
  "geometry": {"coordinates":[4.5790672302,51.2921905518],"type":"Point"}
}