{
  "type": "Feature",
  "properties": {
    "addr:full":"Ottegemstraat 17 Zwevegem West-Vlaanderen 8550",
    "addr:housenumber":"17",
    "addr:postcode":"8550",
    "addr:street":"Ottegemstraat",
    "iso:country":"BE",
    "sg:address":"Ottegemstraat 17",
    "sg:city":"Zwevegem",
    "sg:orig_category":"Eclairage et \u00e9quipements du foyer. Jeux and jouets. Souvenirs and objets artisanaux",
    "sg:phone":"+32 56 75 96 62",
    "sg:postcode":"8550",
    "sg:province":"West-Vlaanderen",
    "wof:name":"Blokker",
    "wof:placetype":"venue"
},
  "geometry": {"coordinates":[3.3352689743,50.8129577637],"type":"Point"}
}