{
  "type": "Feature",
  "properties": {
    "iso:country":"BE",
    "sg:address":"Ramselsesteenweg 117",
    "sg:city":"Herselt",
    "sg:orig_category":"Fotografen and fotostudio's",
    "sg:phone":"+32 16 69 99 61",
    "sg:postcode":"2230",
    "sg:province":"Antwerpen",
    "wof:name":"Peter Slaets",
    "wof:placetype":"venue"
},
  "geometry": {"coordinates":[4.8427610397,51.0370826721],"type":"Point"}
}