{
  "type": "Feature",
  "properties": {
    "addr:full":"Vooruitgangsstraat 119 Willebroek Antwerpen 2830",
    "addr:housenumber":"119",
    "addr:postcode":"2830",
    "addr:street":"Vooruitgangsstraat",
    "iso:country":"BE",
    "sg:address":"Vooruitgangsstraat 119",
    "sg:city":"Willebroek",
    "sg:orig_category":"Boekhouders",
    "sg:phone":"+32 3 886 97 22",
    "sg:postcode":"2830",
    "sg:province":"Antwerpen",
    "wof:name":"Kurt De Decker",
    "wof:placetype":"venue"
},
  "geometry": {"coordinates":[4.3581972122,51.0570220947],"type":"Point"}
}