{
  "type": "Feature",
  "properties": {
    "addr:full":"Grand-route 135 Amay Li\u00e8ge 4540",
    "addr:housenumber":"135",
    "addr:postcode":"4540",
    "addr:street":"Grand-Route",
    "iso:country":"BE",
    "sg:address":"Grand-route 135",
    "sg:city":"Amay",
    "sg:classifiers":[
        {
            "category":"Cafe",
            "type":"Food & Drink"
        }
    ],
    "sg:phone":"+32 85 31 35 45",
    "sg:postcode":"4540",
    "sg:province":"Li\u00e8ge",
    "sg:tags":[
        "caf\u00e9s"
    ],
    "wof:name":"Le Relais Chez Marita",
    "wof:placetype":"venue"
},
  "geometry": {"coordinates":[5.3200559616,50.5351448059],"type":"Point"}
}