{
  "type": "Feature",
  "properties": {
    "addr:full":"Boskens 10 Merksplas Antwerpen 2330",
    "addr:housenumber":"10",
    "addr:postcode":"2330",
    "addr:street":"Boskens",
    "iso:country":"BE",
    "sg:address":"Boskens 10",
    "sg:city":"Merksplas",
    "sg:orig_category":"Voedingsspeciaalzaken",
    "sg:phone":"+32 14 63 39 55",
    "sg:postcode":"2330",
    "sg:province":"Antwerpen",
    "wof:name":"Herboristerie Betonie",
    "wof:placetype":"venue"
},
  "geometry": {"coordinates":[4.8531007767,51.3637084961],"type":"Point"}
}