{
  "type": "Feature",
  "properties": {
    "iso:country":"BE",
    "sg:address":"Rue Winston Churchill 14",
    "sg:city":"Courcelles",
    "sg:orig_category":"Textiel",
    "sg:phone":"+32 71 45 20 12",
    "sg:postcode":"6180",
    "sg:province":"Hainaut",
    "wof:name":"Maison Le Grillon",
    "wof:placetype":"venue"
},
  "geometry": {"coordinates":[4.3918800354,50.462890625],"type":"Point"}
}