{
  "type": "Feature",
  "properties": {
    "iso:country":"BE",
    "sg:address":"A Van Cauwelaertlaan 999",
    "sg:city":"Antwerpen",
    "sg:classifiers":[
        {
            "category":"Arena",
            "subcategory":"Sports Club",
            "type":"Entertainment"
        }
    ],
    "sg:phone":"+32 3 219 68 20",
    "sg:postcode":"2030",
    "sg:province":"Antwerpen",
    "sg:tags":[
        "terrain",
        "hors",
        "de",
        "installation",
        "sportifs"
    ],
    "wof:name":"Sport En Speelterrein",
    "wof:placetype":"venue"
},
  "geometry": {"coordinates":[4.3283500671,51.2774391174],"type":"Point"}
}