{
  "type": "Feature",
  "properties": {
    "iso:country":"BE",
    "sg:address":"Rue De Lille 55",
    "sg:city":"Comines-warneton (warneton)",
    "sg:classifiers":[
        {
            "category":"Real Estate",
            "subcategory":"Architect",
            "type":"Services"
        }
    ],
    "sg:phone":"+32 56 58 70 90",
    "sg:postcode":"7784",
    "sg:province":"Hainaut",
    "wof:name":"Windels L",
    "wof:placetype":"venue"
},
  "geometry": {"coordinates":[2.9483098984,50.752620697],"type":"Point"}
}