{
  "type": "Feature",
  "properties": {
    "iso:country":"BE",
    "sg:address":"Avenue Moli\u00e8re 171",
    "sg:city":"Bruxelles (forest)",
    "sg:classifiers":[
        {
            "category":"Social Services",
            "subcategory":"Child Care",
            "type":"Services"
        }
    ],
    "sg:phone":"+32 2 345 73 67",
    "sg:postcode":"1190",
    "sg:province":"Bruxelles-Capitale",
    "sg:tags":[
        "baby",
        "nursery",
        "day",
        "sitting"
    ],
    "wof:name":"Le Pre En Bulle Asbl",
    "wof:placetype":"venue"
},
  "geometry": {"coordinates":[4.3490362167,50.816116333],"type":"Point"}
}