{
  "type": "Feature",
  "properties": {
    "addr:full":"Gaffelstraat 81 Geraardsbergen Oost-Vlaanderen 9500",
    "addr:housenumber":"81",
    "addr:postcode":"9500",
    "addr:street":"Gaffelstraat",
    "iso:country":"BE",
    "sg:address":"Gaffelstraat 81",
    "sg:city":"Geraardsbergen",
    "sg:classifiers":[
        {
            "category":"Personal",
            "subcategory":"Beauty Salon",
            "type":"Services"
        }
    ],
    "sg:phone":"+32 54 41 30 31",
    "sg:postcode":"9500",
    "sg:province":"Oost-Vlaanderen",
    "sg:tags":[
        "de",
        "coiffure"
    ],
    "wof:name":"Coiffure Denise",
    "wof:placetype":"venue"
},
  "geometry": {"coordinates":[3.8756630421,50.7741470337],"type":"Point"}
}