{
  "type": "Feature",
  "properties": {
    "addr:full":"Asserweg 124 Zutendaal Limburg 3690",
    "addr:housenumber":"124",
    "addr:postcode":"3690",
    "addr:street":"Asserweg",
    "iso:country":"BE",
    "sg:address":"Asserweg 124",
    "sg:city":"Zutendaal",
    "sg:classifiers":[
        {
            "category":"Government",
            "subcategory":"Fire Station",
            "type":"Public Place"
        }
    ],
    "sg:phone":"+32 89 61 19 09",
    "sg:postcode":"3690",
    "sg:province":"Limburg",
    "sg:tags":[
        "installation",
        "-",
        "air conditioning"
    ],
    "wof:name":"Dolmans E",
    "wof:placetype":"venue"
},
  "geometry": {"coordinates":[5.564209938,50.9630584717],"type":"Point"}
}