{
  "type": "Feature",
  "properties": {
    "iso:country":"BE",
    "sg:address":"Route Nationale Cinq 171",
    "sg:city":"Charleroi",
    "sg:orig_category":"Clubs de sport. Centres de fitness. Installations and terrains de sport hors centres sportifs",
    "sg:phone":"+32 71 34 58 88",
    "sg:postcode":"6041",
    "sg:province":"Hainaut",
    "wof:name":"Les Grenadiers",
    "wof:placetype":"venue"
},
  "geometry": {"coordinates":[4.4314317703,50.4685935974],"type":"Point"}
}