{
  "type": "Feature",
  "properties": {
    "addr:full":"All\u00c9e Des Hortensias 13 Waremme Li\u00e8ge 4300",
    "addr:housenumber":"13",
    "addr:postcode":"4300",
    "addr:street":"Alle\u0301E Des Hortensias",
    "iso:country":"BE",
    "sg:address":"All\u00c9e Des Hortensias 13",
    "sg:city":"Waremme",
    "sg:orig_category":"Sociale huisvestingsmaatschappijen",
    "sg:phone":"+32 19 32 26 90",
    "sg:postcode":"4300",
    "sg:province":"Li\u00e8ge",
    "wof:name":"Hesbaye Soc. Reg. D'habit",
    "wof:placetype":"venue"
},
  "geometry": {"coordinates":[5.2622828484,50.7002410889],"type":"Point"}
}