{
  "type": "Feature",
  "properties": {
    "addr:full":"Kloosterstraat 160 Antwerpen Antwerpen 2000",
    "addr:housenumber":"160",
    "addr:postcode":"2000",
    "addr:street":"Kloosterstraat",
    "iso:country":"BE",
    "sg:address":"Kloosterstraat 160",
    "sg:city":"Antwerpen",
    "sg:orig_category":"Zalen voor culturele evenementen",
    "sg:phone":"+32 3 257 20 20",
    "sg:postcode":"2000",
    "sg:province":"Antwerpen",
    "wof:name":"Bookshop Blow Up",
    "wof:placetype":"venue"
},
  "geometry": {"coordinates":[4.3939042091,51.2124214172],"type":"Point"}
}