{
  "type": "Feature",
  "properties": {
    "addr:full":"Doornstraat 29 Boutersem Vlaams-Brabant 3370",
    "addr:housenumber":"29",
    "addr:postcode":"3370",
    "addr:street":"Doornstraat",
    "iso:country":"BE",
    "sg:address":"Doornstraat 29",
    "sg:city":"Boutersem",
    "sg:orig_category":"Charpentes and couvertures",
    "sg:phone":"+32 16 73 52 10",
    "sg:postcode":"3370",
    "sg:province":"Vlaams-Brabant",
    "wof:name":"Sidak Operation System",
    "wof:placetype":"venue"
},
  "geometry": {"coordinates":[4.8358650208,50.8039665222],"type":"Point"}
}