{
  "type": "Feature",
  "properties": {
    "iso:country":"BE",
    "sg:address":"Sint-remigiusweg 3",
    "sg:city":"Haacht",
    "sg:classifiers":[
        {
            "category":"Shopping",
            "subcategory":"Florist",
            "type":"Retail Goods"
        }
    ],
    "sg:phone":"+32 16 60 11 11",
    "sg:postcode":"3150",
    "sg:province":"Vlaams-Brabant",
    "wof:name":"Bloemen Pari",
    "wof:placetype":"venue"
},
  "geometry": {"coordinates":[4.6371002197,50.9784164429],"type":"Point"}
}