{
  "type": "Feature",
  "properties": {
    "addr:full":"Louizalaan 500 Elsene Bruxelles-Capitale 1050",
    "addr:housenumber":"500",
    "addr:postcode":"1050",
    "addr:street":"Louizalaan",
    "iso:country":"BE",
    "sg:address":"Louizalaan 500",
    "sg:city":"Elsene",
    "sg:orig_category":"Offices du tourisme",
    "sg:phone":"+32 2 644 49 40",
    "sg:postcode":"1050",
    "sg:province":"Bruxelles-Capitale",
    "wof:name":"Bureau Des Renseignements Du Tourisme Hongrois",
    "wof:placetype":"venue"
},
  "geometry": {"coordinates":[4.3573069572,50.8343505859],"type":"Point"}
}