{
  "type": "Feature",
  "properties": {
    "iso:country":"BE",
    "sg:address":"Rue Alfred Bequet 4",
    "sg:city":"Namur",
    "sg:orig_category":"Librairies. Tabac. Journaux. Fournitures de bureau",
    "sg:phone":"+32 81 74 52 69",
    "sg:postcode":"5000",
    "sg:province":"Namur",
    "wof:name":"Emile Blaise",
    "wof:placetype":"venue"
},
  "geometry": {"coordinates":[4.838572979,50.4614257812],"type":"Point"}
}