{
  "type": "Feature",
  "properties": {
    "iso:country":"BE",
    "sg:address":"Rue De La Station 4 Box 1",
    "sg:city":"Braine-le-ch\u00e2teau",
    "sg:classifiers":[
        {
            "category":"Health Services",
            "subcategory":"Health Practitioner",
            "type":"Services"
        }
    ],
    "sg:phone":"+32 2 355 15 10",
    "sg:postcode":"1440",
    "sg:province":"Brabant Wallon",
    "sg:tags":[
        "physiotherapist"
    ],
    "wof:name":"Marin Deborah",
    "wof:placetype":"venue"
},
  "geometry": {"coordinates":[4.2695021629,50.6820716858],"type":"Point"}
}