{
  "type": "Feature",
  "properties": {
    "addr:full":"Quai Winston Churchill 6bd Li\u00c8ge Li\u00e8ge 4020",
    "addr:housenumber":"6bd",
    "addr:postcode":"4020",
    "addr:street":"Quai Winston Churchill",
    "iso:country":"BE",
    "sg:address":"Quai Winston Churchill 6bd",
    "sg:city":"Li\u00c8ge",
    "sg:orig_category":"Boekhouders",
    "sg:postcode":"4020",
    "sg:province":"Li\u00e8ge",
    "wof:name":"Alain Lodrini",
    "wof:placetype":"venue"
},
  "geometry": {"coordinates":[5.5772299767,50.6367111206],"type":"Point"}
}