{
  "type": "Feature",
  "properties": {
    "addr:full":"Gulden-vlieslaan 28 Brugge West-Vlaanderen 8000",
    "addr:housenumber":"28",
    "addr:postcode":"8000",
    "addr:street":"Gulden-Vlieslaan",
    "iso:country":"BE",
    "sg:address":"Gulden-vlieslaan 28",
    "sg:city":"Brugge",
    "sg:classifiers":[
        {
            "category":"Health Services",
            "subcategory":"Chiropractor",
            "type":"Services"
        }
    ],
    "sg:phone":"+32 50 33 09 34",
    "sg:postcode":"8000",
    "sg:province":"West-Vlaanderen",
    "wof:name":"Claes D'erckenteel P",
    "wof:placetype":"venue"
},
  "geometry": {"coordinates":[3.2145590782,51.2116127014],"type":"Point"}
}