{
  "type": "Feature",
  "properties": {
    "addr:full":"Voie De La Fourche 8 Seraing Li\u00e8ge 4100",
    "addr:housenumber":"8",
    "addr:postcode":"4100",
    "addr:street":"Voie De La Fourche",
    "iso:country":"BE",
    "sg:address":"Voie De La Fourche 8",
    "sg:city":"Seraing",
    "sg:classifiers":[
        {
            "category":"Insurance",
            "subcategory":"Life Insurance",
            "type":"Services"
        }
    ],
    "sg:phone":"+32 4 337 93 22",
    "sg:postcode":"4100",
    "sg:province":"Li\u00e8ge",
    "sg:tags":[
        "assurance"
    ],
    "wof:name":"C. Lione",
    "wof:placetype":"venue"
},
  "geometry": {"coordinates":[5.5135030746,50.6105766296],"type":"Point"}
}