{
  "type": "Feature",
  "properties": {
    "addr:full":"Rue Jules Hoebeke 15 Les Bons Villers (frasnes-lez-gosselies) Hainaut 6210",
    "addr:housenumber":"15",
    "addr:postcode":"6210",
    "addr:street":"Rue Jules Hoebeke",
    "iso:country":"BE",
    "sg:address":"Rue Jules Hoebeke 15",
    "sg:city":"Les Bons Villers (frasnes-lez-gosselies)",
    "sg:classifiers":[
        {
            "category":"Home & Garden",
            "subcategory":"Building Materials",
            "type":"Retail Goods"
        }
    ],
    "sg:phone":"+32 475 73 19 45",
    "sg:postcode":"6210",
    "sg:province":"Hainaut",
    "sg:tags":[
        "bathroom",
        "installation",
        "accessory"
    ],
    "wof:name":"Plomberie Maeck Sprl",
    "wof:placetype":"venue"
},
  "geometry": {"coordinates":[4.4511561394,50.5378227234],"type":"Point"}
}