{
  "type": "Feature",
  "properties": {
    "iso:country":"BE",
    "sg:address":"Chauss\u00c9e De Wavre 1421",
    "sg:city":"Oudergem/auderghem",
    "sg:orig_category":"Fleurs and plantes",
    "sg:phone":"+32 2 660 01 56",
    "sg:postcode":"1160",
    "sg:province":"Bruxelles-Capitale",
    "wof:name":"Gaillard Alexandra",
    "wof:placetype":"venue"
},
  "geometry": {"coordinates":[4.4136629105,50.8192825317],"type":"Point"}
}