{
  "type": "Feature",
  "properties": {
    "iso:country":"BE",
    "sg:address":"Franslaan 31",
    "sg:city":"Nieuwpoort",
    "sg:orig_category":"Brood, gebak and snoepgoed",
    "sg:phone":"+32 58 23 27 22",
    "sg:postcode":"8620",
    "sg:province":"West-Vlaanderen",
    "wof:name":"Huis Nadine",
    "wof:placetype":"venue"
},
  "geometry": {"coordinates":[2.7190101147,51.1489944458],"type":"Point"}
}