{
  "type": "Feature",
  "properties": {
    "addr:full":"Vredestraat 19 Kapellen Antwerpen 2950",
    "addr:housenumber":"19",
    "addr:postcode":"2950",
    "addr:street":"Vredestraat",
    "iso:country":"BE",
    "sg:address":"Vredestraat 19",
    "sg:city":"Kapellen",
    "sg:classifiers":[
        {
            "category":"Cafe",
            "type":"Food & Drink"
        }
    ],
    "sg:phone":"+32 3 605 38 75",
    "sg:postcode":"2950",
    "sg:province":"Antwerpen",
    "sg:tags":[
        "snack-bars"
    ],
    "wof:name":"La Baguette",
    "wof:placetype":"venue"
},
  "geometry": {"coordinates":[4.4283018112,51.3140449524],"type":"Point"}
}