{
  "type": "Feature",
  "properties": {
    "iso:country":"BE",
    "sg:address":"Chauss\u00e9e De Dinant 199",
    "sg:city":"Namur",
    "sg:classifiers":[
        {
            "category":"Shopping",
            "subcategory":"Books",
            "type":"Retail Goods"
        }
    ],
    "sg:phone":"+32 81 22 54 16",
    "sg:postcode":"5000",
    "sg:province":"Namur",
    "sg:tags":[
        "bookseller"
    ],
    "wof:name":"St-pierre",
    "wof:placetype":"venue"
},
  "geometry": {"coordinates":[4.8561959267,50.4458198547],"type":"Point"}
}