{
  "type": "Feature",
  "properties": {
    "iso:country":"BE",
    "sg:address":"Rue D'octobre 8",
    "sg:city":"Bruxelles (woluwe-saint-lambert)",
    "sg:classifiers":[
        {
            "category":"Building & Trades",
            "subcategory":"Construction",
            "type":"Services"
        }
    ],
    "sg:phone":"+32 2 762 91 99",
    "sg:postcode":"1200",
    "sg:province":"Bruxelles-Capitale",
    "sg:tags":[
        "carpenter"
    ],
    "wof:name":"Van Heste D",
    "wof:placetype":"venue"
},
  "geometry": {"coordinates":[4.4198012352,50.8492012024],"type":"Point"}
}