{
  "type": "Feature",
  "properties": {
    "iso:country":"BE",
    "sg:address":"Rue Trichon 39",
    "sg:city":"Gembloux (grand)",
    "sg:classifiers":[
        {
            "category":"Personal",
            "subcategory":"Beauty Salon",
            "type":"Services"
        }
    ],
    "sg:phone":"+32 81 61 04 90",
    "sg:postcode":"5030",
    "sg:province":"Namur",
    "sg:tags":[
        "de",
        "coiffure"
    ],
    "wof:name":"Betsy",
    "wof:placetype":"venue"
},
  "geometry": {"coordinates":[4.7140722275,50.5740776062],"type":"Point"}
}