{
  "type": "Feature",
  "properties": {
    "iso:country":"BE",
    "sg:address":"Scandinavi\u00ebstraat 1",
    "sg:city":"Gent",
    "sg:classifiers":[
        {
            "category":"Personal",
            "subcategory":"Beauty Salon",
            "type":"Services"
        }
    ],
    "sg:phone":"+32 9 358 78 79",
    "sg:postcode":"9000",
    "sg:province":"Oost-Vlaanderen",
    "sg:tags":[
        "lady",
        "-",
        "hairdressing"
    ],
    "wof:name":"Ronny",
    "wof:placetype":"venue"
},
  "geometry": {"coordinates":[3.7382199764,51.0698699951],"type":"Point"}
}