{
  "type": "Feature",
  "properties": {
    "addr:full":"Sluisstraat 18 Diepenbeek Limburg 3590",
    "addr:housenumber":"18",
    "addr:postcode":"3590",
    "addr:street":"Sluisstraat",
    "iso:country":"BE",
    "sg:address":"Sluisstraat 18",
    "sg:city":"Diepenbeek",
    "sg:classifiers":[
        {
            "category":"Health Services",
            "subcategory":"Health Practitioner",
            "type":"Services"
        }
    ],
    "sg:phone":"+32 11 22 30 18",
    "sg:postcode":"3590",
    "sg:province":"Limburg",
    "sg:tags":[
        "dietitian"
    ],
    "wof:name":"Narinx-driessen",
    "wof:placetype":"venue"
},
  "geometry": {"coordinates":[5.4255428314,50.9415588379],"type":"Point"}
}