{
  "type": "Feature",
  "properties": {
    "addr:full":"Bosstraat 66 Tongeren (lauw) Limburg 3700",
    "addr:housenumber":"66",
    "addr:postcode":"3700",
    "addr:street":"Bosstraat",
    "iso:country":"BE",
    "sg:address":"Bosstraat 66",
    "sg:city":"Tongeren (lauw)",
    "sg:classifiers":[
        {
            "category":"Wholesale",
            "subcategory":"Machinery & Supplies",
            "type":"Manufacturing & Wholesale Goods"
        }
    ],
    "sg:phone":"+32 12 23 64 52",
    "sg:postcode":"3700",
    "sg:province":"Limburg",
    "sg:tags":[
        "refrigeration",
        "-",
        "industrial",
        "commercial",
        "equipment"
    ],
    "wof:name":"Haling Eric",
    "wof:placetype":"venue"
},
  "geometry": {"coordinates":[5.4158420563,50.7345848083],"type":"Point"}
}