{
  "type": "Feature",
  "properties": {
    "iso:country":"BE",
    "sg:address":"Heistraat 2",
    "sg:city":"Geel",
    "sg:orig_category":"Dakwerken",
    "sg:phone":"+32 14 59 05 04",
    "sg:postcode":"2440",
    "sg:province":"Antwerpen",
    "wof:name":"Luc Wijns",
    "wof:placetype":"venue"
},
  "geometry": {"coordinates":[4.9887042046,51.1691894531],"type":"Point"}
}