{
  "type": "Feature",
  "properties": {
    "iso:country":"BE",
    "sg:address":"Rue De La Roche 26",
    "sg:city":"Wavre",
    "sg:orig_category":"Artiesten and kunstenaars",
    "sg:phone":"+32 10 41 92 44",
    "sg:postcode":"1301",
    "sg:province":"Brabant Wallon",
    "wof:name":"Willy Desaegher",
    "wof:placetype":"venue"
},
  "geometry": {"coordinates":[4.5793781281,50.7107925415],"type":"Point"}
}