{
  "type": "Feature",
  "properties": {
    "iso:country":"BE",
    "sg:address":"Diksmuidsestraat 87",
    "sg:city":"Ieper",
    "sg:orig_category":"Slagers",
    "sg:phone":"+32 57 20 10 54",
    "sg:postcode":"8900",
    "sg:province":"West-Vlaanderen",
    "wof:name":"Rik Plancke",
    "wof:placetype":"venue"
},
  "geometry": {"coordinates":[2.8864378929,50.8544082642],"type":"Point"}
}