{
  "type": "Feature",
  "properties": {
    "iso:country":"BE",
    "sg:address":"Rue Marquesses 15a",
    "sg:city":"Amay",
    "sg:orig_category":"Rev\u00eatements pour sols and murs. Peinture",
    "sg:phone":"+32 85 31 18 73",
    "sg:postcode":"4540",
    "sg:province":"Li\u00e8ge",
    "wof:name":"Daniel Mossoux",
    "wof:placetype":"venue"
},
  "geometry": {"coordinates":[5.3014888763,50.5418663025],"type":"Point"}
}