{
  "type": "Feature",
  "properties": {
    "iso:country":"BE",
    "sg:address":"Rue Laoureux 21",
    "sg:city":"Verviers",
    "sg:orig_category":"M\u00e9decines alternatives",
    "sg:phone":"+32 87 30 01 07",
    "sg:postcode":"4800",
    "sg:province":"Li\u00e8ge",
    "wof:name":"Ost\u00c9opathe Krupp A.",
    "wof:placetype":"venue"
},
  "geometry": {"coordinates":[5.8644762039,50.5919799805],"type":"Point"}
}