{
  "type": "Feature",
  "properties": {
    "addr:full":"Rue De L'etoile 7 Morlanwelz (morlanwelz-mariemont) Hainaut 7140",
    "addr:housenumber":"7",
    "addr:postcode":"7140",
    "addr:street":"Rue De L'Etoile",
    "iso:country":"BE",
    "sg:address":"Rue De L'etoile 7",
    "sg:city":"Morlanwelz (morlanwelz-mariemont)",
    "sg:classifiers":[
        {
            "category":"Manufacturing",
            "subcategory":"Signs",
            "type":"Manufacturing & Wholesale Goods"
        }
    ],
    "sg:phone":"+32 64 44 96 60",
    "sg:postcode":"7140",
    "sg:province":"Hainaut",
    "sg:tags":[
        "signalling",
        "yard",
        "road"
    ],
    "wof:name":"L.a.s.i.m.a.g. Sprl",
    "wof:placetype":"venue"
},
  "geometry": {"coordinates":[4.2585082054,50.4674835205],"type":"Point"}
}