{
  "type": "Feature",
  "properties": {
    "iso:country":"BE",
    "sg:address":"Kerkstraat 94",
    "sg:city":"Berlare",
    "sg:orig_category":"Voedingsspeciaalzaken",
    "sg:phone":"+32 9 367 95 75",
    "sg:postcode":"9290",
    "sg:province":"Oost-Vlaanderen",
    "wof:name":"De Zonnepit",
    "wof:placetype":"venue"
},
  "geometry": {"coordinates":[3.9477651119,51.0539321899],"type":"Point"}
}