{
  "type": "Feature",
  "properties": {
    "iso:country":"BE",
    "sg:address":"Koningin Elisabethstraat 9",
    "sg:city":"Kuurne",
    "sg:orig_category":"Boucheries",
    "sg:phone":"+32 56 71 13 90",
    "sg:postcode":"8520",
    "sg:province":"West-Vlaanderen",
    "wof:name":"Beenhouwerij Stijn",
    "wof:placetype":"venue"
},
  "geometry": {"coordinates":[3.2858319283,50.8508262634],"type":"Point"}
}