{
  "type": "Feature",
  "properties": {
    "addr:full":"Rue De La Tournerie 5z Malmedy (beverc\u00e9) Li\u00e8ge 4960",
    "addr:housenumber":"5z",
    "addr:postcode":"4960",
    "addr:street":"Rue De La Tournerie",
    "iso:country":"BE",
    "sg:address":"Rue De La Tournerie 5z",
    "sg:city":"Malmedy (beverc\u00e9)",
    "sg:classifiers":[
        {
            "category":"Arena",
            "subcategory":"Sports Club",
            "type":"Entertainment"
        }
    ],
    "sg:phone":"+32 80 77 18 50",
    "sg:postcode":"4960",
    "sg:province":"Li\u00e8ge",
    "wof:name":"Gym Club Fagnard Asbl",
    "wof:placetype":"venue"
},
  "geometry": {"coordinates":[6.0716848373,50.4579811096],"type":"Point"}
}