{
  "type": "Feature",
  "properties": {
    "iso:country":"BE",
    "sg:address":"Rue Des D\u00e9port\u00e9s 14a",
    "sg:city":"Sivry-rance (rance)",
    "sg:classifiers":[
        {
            "category":"Parking",
            "subcategory":"Garage",
            "type":"Transportation"
        }
    ],
    "sg:phone":"+32 60 41 16 80",
    "sg:postcode":"6470",
    "sg:province":"Hainaut",
    "sg:tags":[
        "truck",
        "-",
        "dump",
        "transport"
    ],
    "wof:name":"Transport Honore J-ph",
    "wof:placetype":"venue"
},
  "geometry": {"coordinates":[4.2644290924,50.1437110901],"type":"Point"}
}