{
  "type": "Feature",
  "properties": {
    "iso:country":"BE",
    "sg:address":"Schauwegemstraat 93",
    "sg:city":"Melle",
    "sg:classifiers":[
        {
            "category":"Home & Garden",
            "subcategory":"Kitchen Supply",
            "type":"Retail Goods"
        }
    ],
    "sg:phone":"+32 9 252 12 22",
    "sg:postcode":"9090",
    "sg:province":"Oost-Vlaanderen",
    "sg:tags":[
        "installation"
    ],
    "wof:name":"Van Gansberghe",
    "wof:placetype":"venue"
},
  "geometry": {"coordinates":[3.8013670444,50.9967918396],"type":"Point"}
}