{
  "type": "Feature",
  "properties": {
    "iso:country":"BE",
    "sg:address":"Chauss\u00e9e De Wavre 504-34",
    "sg:city":"Grez-doiceau",
    "sg:orig_category":"Electric transformers, rectifiers, converters",
    "sg:phone":"+32 10 84 20 49",
    "sg:postcode":"1390",
    "sg:province":"Brabant Wallon",
    "wof:name":"Reo Engineering Service Sa",
    "wof:placetype":"venue"
},
  "geometry": {"coordinates":[4.6466069221,50.7328109741],"type":"Point"}
}