{
  "type": "Feature",
  "properties": {
    "iso:country":"BE",
    "sg:address":"Rue Stroobants 8",
    "sg:city":"Bruxelles (evere)",
    "sg:classifiers":[
        {
            "category":"Professional",
            "subcategory":"Accounting & Tax Preparation",
            "type":"Services"
        }
    ],
    "sg:phone":"+32 2 242 33 34",
    "sg:postcode":"1140",
    "sg:province":"Bruxelles-Capitale",
    "sg:tags":[
        "bookkeeper"
    ],
    "wof:name":"A.c.r. Sprl",
    "wof:placetype":"venue"
},
  "geometry": {"coordinates":[4.3907938004,50.8786010742],"type":"Point"}
}