{
  "type": "Feature",
  "properties": {
    "iso:country":"BE",
    "sg:address":"Betekomsesteenweg 37",
    "sg:city":"Aarschot",
    "sg:classifiers":[
        {
            "category":"Wholesale",
            "subcategory":"Chemicals & Plastics",
            "type":"Manufacturing & Wholesale Goods"
        }
    ],
    "sg:phone":"+32 16 55 37 30",
    "sg:postcode":"3200",
    "sg:province":"Vlaams-Brabant",
    "sg:tags":[
        "packing"
    ],
    "wof:name":"Bwa",
    "wof:placetype":"venue"
},
  "geometry": {"coordinates":[4.823029995,50.9881095886],"type":"Point"}
}