{
  "type": "Feature",
  "properties": {
    "addr:full":"Ernest Allardstraat 17 Brussel/bruxelles Bruxelles-Capitale 1000",
    "addr:housenumber":"17",
    "addr:postcode":"1000",
    "addr:street":"Ernest Allardstraat;/",
    "iso:country":"BE",
    "sg:address":"Ernest Allardstraat 17",
    "sg:city":"Brussel/bruxelles",
    "sg:orig_category":"Antiek Verlichting and huishoudartikelen",
    "sg:phone":"+32 2 512 46 79",
    "sg:postcode":"1000",
    "sg:province":"Bruxelles-Capitale",
    "wof:name":"Ritter",
    "wof:placetype":"venue"
},
  "geometry": {"coordinates":[4.3543701172,50.8400382996],"type":"Point"}
}