{
  "type": "Feature",
  "properties": {
    "addr:full":"Gentsestraat 84 Burst Oost-Vlaanderen 9420",
    "addr:housenumber":"84",
    "addr:postcode":"9420",
    "addr:street":"Gentsestraat",
    "iso:country":"BE",
    "sg:address":"Gentsestraat 84",
    "sg:city":"Burst",
    "sg:orig_category":"Huisdieren and benodigdheden Royal Canin",
    "sg:phone":"+32 53 62 39 61",
    "sg:postcode":"9420",
    "sg:province":"Oost-Vlaanderen",
    "wof:name":"De Meerleer",
    "wof:placetype":"venue"
},
  "geometry": {"coordinates":[3.9144070148,50.9159851074],"type":"Point"}
}