{
  "type": "Feature",
  "properties": {
    "iso:country":"BE",
    "sg:address":"Ronde Van Vlaanderenstr. 12",
    "sg:city":"Kluisbergen",
    "sg:classifiers":[
        {
            "category":"Food & Beverages",
            "subcategory":"Fruits & Vegetables",
            "type":"Retail Goods"
        }
    ],
    "sg:phone":"+32 55 38 77 11",
    "sg:postcode":"9690",
    "sg:province":"Oost-Vlaanderen",
    "sg:tags":[
        "l\u00e9gumes",
        "gr"
    ],
    "wof:name":"Willequet",
    "wof:placetype":"venue"
},
  "geometry": {"coordinates":[3.5404779911,50.7646713257],"type":"Point"}
}