{
  "type": "Feature",
  "properties": {
    "addr:full":"Fabriekstraat 40 Ruisbroek 1610",
    "addr:housenumber":"40",
    "addr:postcode":"1610",
    "addr:street":"Fabriekstraat",
    "iso:country":"BE",
    "sg:address":"Fabriekstraat 40",
    "sg:city":"Ruisbroek",
    "sg:classifiers":[
        {
            "category":"Banks & Credit Unions",
            "subcategory":"Bank",
            "type":"Services"
        }
    ],
    "sg:phone":"+32 2 378 39 90",
    "sg:postcode":"1610",
    "wof:name":"Aslk-cger Bank",
    "wof:placetype":"venue"
},
  "geometry": {"coordinates":[4.2952990532,50.785949707],"type":"Point"}
}