{
  "type": "Feature",
  "properties": {
    "iso:country":"BE",
    "sg:address":"Charles Madouxlaan 36",
    "sg:city":"Oudergem/auderghem",
    "sg:orig_category":"Brood, gebak and snoepgoed",
    "sg:phone":"+32 2 733 69 83",
    "sg:postcode":"1160",
    "sg:province":"Bruxelles-Capitale",
    "wof:name":"P\u00c2tisserie L'epis D'or",
    "wof:placetype":"venue"
},
  "geometry": {"coordinates":[4.4023241997,50.8248329163],"type":"Point"}
}