{
  "type": "Feature",
  "properties": {
    "iso:country":"BE",
    "sg:address":"Antonius - Eik 6",
    "sg:city":"Anzegem (ingooigem)",
    "sg:classifiers":[
        {
            "category":"Professional",
            "subcategory":"Management & Consulting",
            "type":"Services"
        }
    ],
    "sg:phone":"+32 56 77 53 57",
    "sg:postcode":"8570",
    "sg:province":"West-Vlaanderen",
    "sg:tags":[
        "consultant",
        "promotion",
        "-",
        "sale"
    ],
    "wof:name":"Time-out",
    "wof:placetype":"venue"
},
  "geometry": {"coordinates":[3.4347310066,50.8217277527],"type":"Point"}
}