{
  "type": "Feature",
  "properties": {
    "iso:country":"BE",
    "sg:address":"Steenweg Op Aalst 1021",
    "sg:city":"Aalst",
    "sg:orig_category":"Jardinage",
    "sg:phone":"+32 475 85 34 26",
    "sg:postcode":"9308",
    "sg:province":"Oost-Vlaanderen",
    "wof:name":"De Schutter Filip",
    "wof:placetype":"venue"
},
  "geometry": {"coordinates":[4.0347590446,50.9603500366],"type":"Point"}
}