{
  "type": "Feature",
  "properties": {
    "addr:full":"Rue Ren\u00c9 Detiste 17 Hannut Li\u00e8ge 4280",
    "addr:housenumber":"17",
    "addr:postcode":"4280",
    "addr:street":"Rue Rene\u0301 Detiste",
    "iso:country":"BE",
    "sg:address":"Rue Ren\u00c9 Detiste 17",
    "sg:city":"Hannut",
    "sg:orig_category":"Landbouwmachines Gh",
    "sg:phone":"+32 19 63 36 60",
    "sg:postcode":"4280",
    "sg:province":"Li\u00e8ge",
    "wof:name":"Philippe Lambrechts",
    "wof:placetype":"venue"
},
  "geometry": {"coordinates":[5.0350952148,50.694568634],"type":"Point"}
}