{
  "type": "Feature",
  "properties": {
    "addr:full":"Sur Les Heids 32 Chaudfontaine (embourg) Li\u00e8ge 4053",
    "addr:housenumber":"32",
    "addr:postcode":"4053",
    "addr:street":"Sur Les Heids",
    "iso:country":"BE",
    "sg:address":"Sur Les Heids 32",
    "sg:city":"Chaudfontaine (embourg)",
    "sg:classifiers":[
        {
            "category":"Health Services",
            "subcategory":"Health Practitioner",
            "type":"Services"
        }
    ],
    "sg:phone":"+32 4 365 17 81",
    "sg:postcode":"4053",
    "sg:province":"Li\u00e8ge",
    "sg:tags":[
        "physiotherapist"
    ],
    "wof:name":"Colinet-delcour Nicole",
    "wof:placetype":"venue"
},
  "geometry": {"coordinates":[5.5968117714,50.5949554443],"type":"Point"}
}