{
  "type": "Feature",
  "properties": {
    "addr:full":"Verbrandhofstraat 1b3 Aalst Oost-Vlaanderen 9300",
    "addr:housenumber":"1b3",
    "addr:postcode":"9300",
    "addr:street":"Verbrandhofstraat",
    "iso:country":"BE",
    "sg:address":"Verbrandhofstraat 1b3",
    "sg:city":"Aalst",
    "sg:orig_category":"Installation de menuiserie en bois and plastique",
    "sg:phone":"+32 53 70 09 46",
    "sg:postcode":"9300",
    "sg:province":"Oost-Vlaanderen",
    "wof:name":"Hartmut B\u00d6ttcher",
    "wof:placetype":"venue"
},
  "geometry": {"coordinates":[4.0407037735,50.9482192993],"type":"Point"}
}