{
  "type": "Feature",
  "properties": {
    "iso:country":"BE",
    "sg:address":"Nederen Heirweg 21bb",
    "sg:city":"Gistel",
    "sg:orig_category":"Artsen and specialisten",
    "sg:phone":"+32 59 27 92 78",
    "sg:postcode":"8470",
    "sg:province":"West-Vlaanderen",
    "wof:name":"Els Yperman",
    "wof:placetype":"venue"
},
  "geometry": {"coordinates":[2.9560689926,51.152885437],"type":"Point"}
}