{
  "type": "Feature",
  "properties": {
    "addr:full":"Schopdriesweg 26 Zonhoven Limburg 3520",
    "addr:housenumber":"26",
    "addr:postcode":"3520",
    "addr:street":"Schopdriesweg",
    "iso:country":"BE",
    "sg:address":"Schopdriesweg 26",
    "sg:city":"Zonhoven",
    "sg:classifiers":[
        {
            "category":"Personal",
            "subcategory":"Beauty Salon",
            "type":"Services"
        }
    ],
    "sg:phone":"+32 11 82 58 33",
    "sg:postcode":"3520",
    "sg:province":"Limburg",
    "sg:tags":[
        "lady",
        "-",
        "hairdressing"
    ],
    "wof:name":"Saskia",
    "wof:placetype":"venue"
},
  "geometry": {"coordinates":[5.3435258865,50.9947357178],"type":"Point"}
}