{
  "type": "Feature",
  "properties": {
    "iso:country":"BE",
    "sg:address":"Tiensestraat 131b2",
    "sg:city":"Leuven",
    "sg:orig_category":"Architecten",
    "sg:phone":"+32 16 22 36 44",
    "sg:postcode":"3000",
    "sg:province":"Vlaams-Brabant",
    "wof:name":"Sven Cappan",
    "wof:placetype":"venue"
},
  "geometry": {"coordinates":[4.7090139389,50.8756332397],"type":"Point"}
}