{
  "type": "Feature",
  "properties": {
    "addr:full":"Kuipersstraat 14 Brugge West-Vlaanderen 8000",
    "addr:housenumber":"14",
    "addr:postcode":"8000",
    "addr:street":"Kuipersstraat",
    "iso:country":"BE",
    "sg:address":"Kuipersstraat 14",
    "sg:city":"Brugge",
    "sg:classifiers":[
        {
            "category":"Cafe",
            "type":"Food & Drink"
        }
    ],
    "sg:phone":"+32 50 33 45 36",
    "sg:postcode":"8000",
    "sg:province":"West-Vlaanderen",
    "sg:tags":[
        "caf\u00e9s"
    ],
    "wof:name":"Grand Caf\u00c9 Du Th\u00c9\u00c2tre",
    "wof:placetype":"venue"
},
  "geometry": {"coordinates":[3.2168331146,51.2082481384],"type":"Point"}
}