{
  "type": "Feature",
  "properties": {
    "addr:full":"Georges Wittouckstraat 14 Sint-pieters-leeuw Vlaams-Brabant 1600",
    "addr:housenumber":"14",
    "addr:postcode":"1600",
    "addr:street":"Georges Wittouckstraat",
    "iso:country":"BE",
    "sg:address":"Georges Wittouckstraat 14",
    "sg:city":"Sint-pieters-leeuw",
    "sg:classifiers":[
        {
            "category":"Cemetery",
            "type":"Public Place"
        }
    ],
    "sg:phone":"+32 2 331 39 45",
    "sg:postcode":"1600",
    "sg:province":"Vlaams-Brabant",
    "sg:tags":[
        "crematory"
    ],
    "wof:name":"Heymans",
    "wof:placetype":"venue"
},
  "geometry": {"coordinates":[4.2811870575,50.7920188904],"type":"Point"}
}