{
  "type": "Feature",
  "properties": {
    "iso:country":"BE",
    "sg:address":"Place Jean Jaur\u00c8s 35",
    "sg:city":"Herstal",
    "sg:orig_category":"Sportclubs",
    "sg:phone":"+32 4 248 44 70",
    "sg:postcode":"4040",
    "sg:province":"Li\u00e8ge",
    "wof:name":"H.c. Herstal",
    "wof:placetype":"venue"
},
  "geometry": {"coordinates":[5.630739212,50.6657371521],"type":"Point"}
}