{
  "type": "Feature",
  "properties": {
    "addr:full":"Groenstraat 213 Leuven (heverlee) Vlaams-Brabant 3001",
    "addr:housenumber":"213",
    "addr:postcode":"3001",
    "addr:street":"Groenstraat",
    "iso:country":"BE",
    "sg:address":"Groenstraat 213",
    "sg:city":"Leuven (heverlee)",
    "sg:classifiers":[
        {
            "category":"Professional",
            "subcategory":"Accounting & Tax Preparation",
            "type":"Services"
        }
    ],
    "sg:phone":"+32 16 40 00 05",
    "sg:postcode":"3001",
    "sg:province":"Vlaams-Brabant",
    "sg:tags":[
        "accountant"
    ],
    "wof:name":"Schroeders F",
    "wof:placetype":"venue"
},
  "geometry": {"coordinates":[4.6964039803,50.8585281372],"type":"Point"}
}