{
  "type": "Feature",
  "properties": {
    "addr:full":"Monseigneur Callewaertlaan 16 Zwevegem West-Vlaanderen 8550",
    "addr:housenumber":"16",
    "addr:postcode":"8550",
    "addr:street":"Monseigneur Callewaertlaan",
    "iso:country":"BE",
    "sg:address":"Monseigneur Callewaertlaan 16",
    "sg:city":"Zwevegem",
    "sg:classifiers":[
        {
            "category":"Professional",
            "subcategory":"Management & Consulting",
            "type":"Services"
        }
    ],
    "sg:phone":"+32 56 75 53 86",
    "sg:postcode":"8550",
    "sg:province":"West-Vlaanderen",
    "sg:tags":[
        "consultant"
    ],
    "wof:name":"Maximise Consulting Bvba",
    "wof:placetype":"venue"
},
  "geometry": {"coordinates":[3.3290610313,50.8151168823],"type":"Point"}
}