{
  "type": "Feature",
  "properties": {
    "addr:full":"Industrielaan 16 Deinze (petegem-aan-de-leie) Oost-Vlaanderen 9800",
    "addr:housenumber":"16",
    "addr:postcode":"9800",
    "addr:street":"Industrielaan;Oost-Vlaanderen",
    "iso:country":"BE",
    "sg:address":"Industrielaan 16",
    "sg:city":"Deinze (petegem-aan-de-leie)",
    "sg:classifiers":[
        {
            "category":"Shopping",
            "subcategory":"Clothing, Apparel, & Fashions",
            "type":"Retail Goods"
        }
    ],
    "sg:phone":"+32 9 386 12 18",
    "sg:postcode":"9800",
    "sg:province":"Oost-Vlaanderen",
    "sg:tags":[
        "zipper"
    ],
    "wof:name":"Alfatex-klittenband Nv",
    "wof:placetype":"venue"
},
  "geometry": {"coordinates":[3.530174017,50.9863166809],"type":"Point"}
}