{
  "type": "Feature",
  "properties": {
    "iso:country":"BE",
    "sg:address":"Baaistraat 4",
    "sg:city":"Kortenaken (ransberg)",
    "sg:classifiers":[
        {
            "category":"Professional",
            "subcategory":"Computer Services",
            "type":"Services"
        }
    ],
    "sg:phone":"+32 11 58 26 79",
    "sg:postcode":"3470",
    "sg:province":"Vlaams-Brabant",
    "sg:tags":[
        "network"
    ],
    "wof:name":"Hupko Gebr Bvba",
    "wof:placetype":"venue"
},
  "geometry": {"coordinates":[5.0369138718,50.8902854919],"type":"Point"}
}