{
  "type": "Feature",
  "properties": {
    "addr:full":"Flor\u00e9al 267 Renaix Oost-Vlaanderen 9600",
    "addr:housenumber":"267",
    "addr:postcode":"renaix;9600",
    "addr:street":"Flore\u0301Al",
    "iso:country":"BE",
    "sg:address":"Flor\u00e9al 267",
    "sg:city":"Renaix",
    "sg:classifiers":[
        {
            "category":"Social Services",
            "subcategory":"Retirement Home",
            "type":"Services"
        }
    ],
    "sg:phone":"+32 55 21 60 71",
    "sg:postcode":"9600",
    "sg:province":"Oost-Vlaanderen",
    "sg:tags":[
        "society",
        "protection",
        "animal"
    ],
    "wof:name":"Vlaamse Ardennen Vzw",
    "wof:placetype":"venue"
},
  "geometry": {"coordinates":[3.5793869495,50.7432327271],"type":"Point"}
}