{
  "type": "Feature",
  "properties": {
    "iso:country":"BE",
    "sg:address":"Hoogstraat 74",
    "sg:city":"Meise (wolvertem)",
    "sg:classifiers":[
        {
            "category":"Professional",
            "subcategory":"Accounting & Tax Preparation",
            "type":"Services"
        }
    ],
    "sg:phone":"+32 2 269 10 81",
    "sg:postcode":"1861",
    "sg:province":"Vlaams-Brabant",
    "sg:tags":[
        "bookkeeper"
    ],
    "wof:name":"Goldberg A",
    "wof:placetype":"venue"
},
  "geometry": {"coordinates":[4.3137278557,50.9547615051],"type":"Point"}
}