{
  "type": "Feature",
  "properties": {
    "iso:country":"BE",
    "sg:address":"Berkendaalstraat 132",
    "sg:city":"Elsene/ixelles",
    "sg:orig_category":"Elektrische installaties voor woningen",
    "sg:phone":"+32 2 343 49 99",
    "sg:postcode":"1050",
    "sg:province":"Bruxelles-Capitale",
    "wof:name":"Etn. Roco",
    "wof:placetype":"venue"
},
  "geometry": {"coordinates":[4.3532547951,50.8169784546],"type":"Point"}
}