{
  "type": "Feature",
  "properties": {
    "iso:country":"BE",
    "sg:address":"Avenue De Maire 201",
    "sg:city":"Tournai",
    "sg:classifiers":[
        {
            "category":"Home & Garden",
            "subcategory":"Home Furnishings",
            "type":"Retail Goods"
        }
    ],
    "sg:phone":"+32 69 84 78 38",
    "sg:postcode":"7500",
    "sg:province":"Hainaut",
    "sg:tags":[
        "-",
        "bed",
        "mattress"
    ],
    "wof:name":"Environnement Sommeil",
    "wof:placetype":"venue"
},
  "geometry": {"coordinates":[3.3703079224,50.6206741333],"type":"Point"}
}