{
  "type": "Feature",
  "properties": {
    "iso:country":"BE",
    "sg:address":"Rue Porte-grumsel 1",
    "sg:city":"Li\u00e8ge 1 (li\u00e8ge 2)",
    "sg:classifiers":[
        {
            "category":"Fast Food",
            "type":"Food & Drink"
        }
    ],
    "sg:phone":"+32 4 343 29 14",
    "sg:postcode":"4020",
    "sg:province":"Li\u00e8ge",
    "sg:tags":[
        "fried",
        "stand",
        "potato"
    ],
    "wof:name":"Genin",
    "wof:placetype":"venue"
},
  "geometry": {"coordinates":[5.5836920738,50.6392059326],"type":"Point"}
}