{
  "type": "Feature",
  "properties": {
    "iso:country":"BE",
    "sg:address":"Wipstraat 14",
    "sg:city":"Lommel",
    "sg:orig_category":"Artsen and specialisten",
    "sg:phone":"+32 11 54 43 85",
    "sg:postcode":"3920",
    "sg:province":"Limburg",
    "wof:name":"L. Demilie",
    "wof:placetype":"venue"
},
  "geometry": {"coordinates":[5.3167510033,51.2236595154],"type":"Point"}
}