{
  "type": "Feature",
  "properties": {
    "addr:full":"Boulevard Zo\u00e9 Drion 1 Charleroi Hainaut 6000",
    "addr:housenumber":"1",
    "addr:postcode":"6000",
    "addr:street":"Boulevard Zoe\u0301 Drion;Hainaut",
    "iso:country":"BE",
    "sg:address":"Boulevard Zo\u00e9 Drion 1",
    "sg:city":"Charleroi",
    "sg:classifiers":[
        {
            "category":"Social Services",
            "type":"Services"
        }
    ],
    "sg:phone":"+32 71 32 18 70",
    "sg:postcode":"6000",
    "sg:province":"Hainaut",
    "wof:name":"Op\u00e9ration Village Roumain International",
    "wof:placetype":"venue"
},
  "geometry": {"coordinates":[4.452381134,50.4130592346],"type":"Point"}
}