{
  "type": "Feature",
  "properties": {
    "addr:full":"Maaseikerbaan 54 Bree Limburg 3960",
    "addr:housenumber":"54",
    "addr:postcode":"3960",
    "addr:street":"Maaseikerbaan",
    "iso:country":"BE",
    "sg:address":"Maaseikerbaan 54",
    "sg:city":"Bree",
    "sg:orig_category":"HERSTELLING ELEKTRISCHE HUISHOUDAPPARATEN Huishoudapparaten, televisies and radio's Telecommunicatie",
    "sg:phone":"+32 89 86 69 70",
    "sg:postcode":"3960",
    "sg:province":"Limburg",
    "wof:name":"Govaers Tony",
    "wof:placetype":"venue"
},
  "geometry": {"coordinates":[5.6650700569,51.1140213013],"type":"Point"}
}