{
  "type": "Feature",
  "properties": {
    "iso:country":"BE",
    "sg:address":"Staatsbaan 48 B",
    "sg:city":"Kortemark",
    "sg:orig_category":"Boissons",
    "sg:phone":"+32 51 57 08 61",
    "sg:postcode":"8610",
    "sg:province":"West-Vlaanderen",
    "wof:name":"Rojo",
    "wof:placetype":"venue"
},
  "geometry": {"coordinates":[3.038173914,51.0220985413],"type":"Point"}
}