{
  "type": "Feature",
  "properties": {
    "addr:full":"Rooigem 23 Oudenaarde Oost-Vlaanderen 9700",
    "addr:housenumber":"23",
    "addr:postcode":"9700",
    "addr:street":"Rooigem",
    "iso:country":"BE",
    "sg:address":"Rooigem 23",
    "sg:city":"Oudenaarde",
    "sg:orig_category":"Varkenskwekers",
    "sg:phone":"+32 9 383 85 84",
    "sg:postcode":"9700",
    "sg:province":"Oost-Vlaanderen",
    "wof:name":"Van Rijckeghem Luc & Nico",
    "wof:placetype":"venue"
},
  "geometry": {"coordinates":[3.6014180183,50.8910942078],"type":"Point"}
}