{
  "type": "Feature",
  "properties": {
    "addr:full":"President Kennedypark 16bd Kortrijk West-Vlaanderen 8500",
    "addr:housenumber":"16bd",
    "addr:postcode":"8500",
    "addr:street":"President Kennedypark",
    "iso:country":"BE",
    "sg:address":"President Kennedypark 16bd",
    "sg:city":"Kortrijk",
    "sg:orig_category":"Vakbonden",
    "sg:phone":"+32 56 23 55 11",
    "sg:postcode":"8500",
    "sg:province":"West-Vlaanderen",
    "wof:name":"A.c.v.",
    "wof:placetype":"venue"
},
  "geometry": {"coordinates":[3.272521019,50.8000564575],"type":"Point"}
}