{
  "type": "Feature",
  "properties": {
    "addr:full":"G\u00e9rimont 1 Sainte-ode (tillet) Luxembourg 6680",
    "addr:housenumber":"1",
    "addr:postcode":"6680",
    "addr:street":"Ge\u0301Rimont;Sainte-Ode Tillet",
    "iso:country":"BE",
    "sg:address":"G\u00e9rimont 1",
    "sg:city":"Sainte-ode (tillet)",
    "sg:classifiers":[
        {
            "category":"Building & Trades",
            "subcategory":"Landscaping Services",
            "type":"Services"
        }
    ],
    "sg:phone":"+32 61 68 80 44",
    "sg:postcode":"6680",
    "sg:province":"Luxembourg",
    "sg:tags":[
        "nurseryman"
    ],
    "wof:name":"Le Temps Des Fleurs Sprl",
    "wof:placetype":"venue"
},
  "geometry": {"coordinates":[5.5337228775,50.0025863647],"type":"Point"}
}