{
  "type": "Feature",
  "properties": {
    "addr:full":"Lilsedijk 22 Beerse Antwerpen 2340",
    "addr:housenumber":"22",
    "addr:postcode":"2340",
    "addr:street":"Lilsedijk",
    "iso:country":"BE",
    "sg:address":"Lilsedijk 22",
    "sg:city":"Beerse",
    "sg:classifiers":[
        {
            "category":"Ice Cream",
            "type":"Food & Drink"
        }
    ],
    "sg:phone":"+32 14 60 17 11",
    "sg:postcode":"2340",
    "sg:province":"Antwerpen",
    "wof:name":"Sch\u00f6ller Nv",
    "wof:placetype":"venue"
},
  "geometry": {"coordinates":[4.8400421143,51.3038101196],"type":"Point"}
}