{
  "type": "Feature",
  "properties": {
    "iso:country":"BE",
    "sg:address":"Veldeken 7a",
    "sg:city":"Zele",
    "sg:classifiers":[
        {
            "category":"Professional",
            "subcategory":"Accounting & Tax Preparation",
            "type":"Services"
        }
    ],
    "sg:phone":"+32 52 44 49 16",
    "sg:postcode":"9240",
    "sg:province":"Oost-Vlaanderen",
    "sg:tags":[
        "bookkeeper"
    ],
    "wof:name":"De Winningen Cvba",
    "wof:placetype":"venue"
},
  "geometry": {"coordinates":[4.0563797951,51.0572624207],"type":"Point"}
}