{
  "type": "Feature",
  "properties": {
    "addr:full":"Rue Des Roses Tremieres 20 Namur Namur 5020",
    "addr:housenumber":"20",
    "addr:postcode":"5020",
    "addr:street":"Rue Des Roses Tremieres",
    "iso:country":"BE",
    "sg:address":"Rue Des Roses Tremieres 20",
    "sg:city":"Namur",
    "sg:orig_category":"Boekbinderijen and afwerking",
    "sg:phone":"+32 81 21 20 99",
    "sg:postcode":"5020",
    "sg:province":"Namur",
    "wof:name":"Parent J. & J.",
    "wof:placetype":"venue"
},
  "geometry": {"coordinates":[4.7952418327,50.4352035522],"type":"Point"}
}