{
  "type": "Feature",
  "properties": {
    "addr:full":"Rue Ferme Blanche 41 Charleroi Hainaut 6060",
    "addr:housenumber":"41",
    "addr:postcode":"6060",
    "addr:street":"Rue Ferme Blanche;Hainaut",
    "iso:country":"BE",
    "sg:address":"Rue Ferme Blanche 41",
    "sg:city":"Charleroi",
    "sg:classifiers":[
        {
            "category":"Communications",
            "subcategory":"Film & Video Production",
            "type":"Services"
        }
    ],
    "sg:phone":"+32 71 41 08 37",
    "sg:postcode":"6060",
    "sg:province":"Hainaut",
    "sg:tags":[
        "platen",
        "cassette",
        "cd's"
    ],
    "wof:name":"Jeannine Lambrechs",
    "wof:placetype":"venue"
},
  "geometry": {"coordinates":[4.4880981445,50.4251937866],"type":"Point"}
}