{
  "type": "Feature",
  "properties": {
    "iso:country":"BE",
    "sg:address":"Sint-lambertuslaan 33",
    "sg:city":"Mechelen",
    "sg:orig_category":"Woningbouw",
    "sg:phone":"+32 15 41 40 30",
    "sg:postcode":"2812",
    "sg:province":"Antwerpen",
    "wof:name":"Bouwwerken Geens",
    "wof:placetype":"venue"
},
  "geometry": {"coordinates":[4.5124459267,51.0111312866],"type":"Point"}
}