{
  "type": "Feature",
  "properties": {
    "addr:full":"Boulevard Auguste Reyers 155 Bruxelles (schaerbeek) Bruxelles-Capitale 1030",
    "addr:housenumber":"155",
    "addr:postcode":"1030",
    "addr:street":"Boulevard Auguste Reyers",
    "iso:country":"BE",
    "sg:address":"Boulevard Auguste Reyers 155",
    "sg:city":"Bruxelles (schaerbeek)",
    "sg:classifiers":[
        {
            "category":"Professional",
            "subcategory":"Lawyer & Legal Services",
            "type":"Services"
        }
    ],
    "sg:phone":"+32 2 743 07 10",
    "sg:postcode":"1030",
    "sg:province":"Bruxelles-Capitale",
    "wof:name":"Schnitzler C",
    "wof:placetype":"venue"
},
  "geometry": {"coordinates":[4.4039897919,50.8470497131],"type":"Point"}
}