{
  "type": "Feature",
  "properties": {
    "addr:full":"Kruibeeksesteenweg 69 Zwijndrecht (burcht) Antwerpen 2070",
    "addr:housenumber":"69",
    "addr:postcode":"2070",
    "addr:street":"Kruibeeksesteenweg;Burcht",
    "iso:country":"BE",
    "sg:address":"Kruibeeksesteenweg 69",
    "sg:city":"Zwijndrecht (burcht)",
    "sg:classifiers":[
        {
            "category":"Personal",
            "subcategory":"Beauty Salon",
            "type":"Services"
        }
    ],
    "sg:phone":"+32 3 252 72 31",
    "sg:postcode":"2070",
    "sg:province":"Antwerpen",
    "sg:tags":[
        "lady",
        "-",
        "hairdressing"
    ],
    "wof:name":"Cockx F",
    "wof:placetype":"venue"
},
  "geometry": {"coordinates":[4.3276262283,51.1969299316],"type":"Point"}
}