{
  "type": "Feature",
  "properties": {
    "addr:full":"Maria-joannalaan 10ba Sint-genesius-rode/rhode-saint-genese Vlaams-Brabant 1640",
    "addr:postcode":"1640",
    "addr:street":"Maria-Joannalaan;Vlaams-Brabant",
    "iso:country":"BE",
    "sg:address":"Maria-joannalaan 10ba",
    "sg:city":"Sint-genesius-rode/rhode-saint-genese",
    "sg:orig_category":"Artiesten and kunstenaars",
    "sg:phone":"+32 2 358 10 73",
    "sg:postcode":"1640",
    "sg:province":"Vlaams-Brabant",
    "wof:name":"Francois",
    "wof:placetype":"venue"
},
  "geometry": {"coordinates":[4.3930969238,50.7373962402],"type":"Point"}
}