{
  "type": "Feature",
  "properties": {
    "addr:full":"Bo\u00eete Postale 66 Jumet1 Hainaut 6040",
    "addr:housenumber":"66",
    "addr:postcode":"6040",
    "addr:street":"Jumet1 Hainaut",
    "iso:country":"BE",
    "sg:address":"Bo\u00eete Postale 66",
    "sg:city":"Jumet1",
    "sg:classifiers":[
        {
            "category":"Arts & Performance",
            "subcategory":"Theater",
            "type":"Entertainment"
        }
    ],
    "sg:phone":"+32 71 35 65 72",
    "sg:postcode":"6040",
    "sg:province":"Hainaut",
    "sg:tags":[
        "theatrical",
        "agency"
    ],
    "wof:name":"Agence Moreau",
    "wof:placetype":"venue"
},
  "geometry": {"coordinates":[4.4273500443,50.4482917786],"type":"Point"}
}