{
  "type": "Feature",
  "properties": {
    "addr:full":"Mechelsesteenweg 370 Lier Antwerpen 2500",
    "addr:housenumber":"370",
    "addr:postcode":"2500",
    "addr:street":"Mechelsesteenweg",
    "iso:country":"BE",
    "sg:address":"Mechelsesteenweg 370",
    "sg:city":"Lier",
    "sg:classifiers":[
        {
            "category":"Farming",
            "subcategory":"Livestock Farm",
            "type":"Manufacturing & Wholesale Goods"
        }
    ],
    "sg:phone":"+32 15 31 15 89",
    "sg:postcode":"2500",
    "sg:province":"Antwerpen",
    "sg:tags":[
        "buyer"
    ],
    "wof:name":"Leys Nv",
    "wof:placetype":"venue"
},
  "geometry": {"coordinates":[4.5293898582,51.1120033264],"type":"Point"}
}