{
  "type": "Feature",
  "properties": {
    "iso:country":"BE",
    "sg:address":"Plezantstraat 2",
    "sg:city":"Kruibeke",
    "sg:classifiers":[
        {
            "category":"Food & Beverages",
            "subcategory":"Fruits & Vegetables",
            "type":"Retail Goods"
        }
    ],
    "sg:phone":"+32 3 774 04 05",
    "sg:postcode":"9150",
    "sg:province":"Oost-Vlaanderen",
    "sg:tags":[
        "groenten"
    ],
    "wof:name":"Walter D'hondt",
    "wof:placetype":"venue"
},
  "geometry": {"coordinates":[4.2991518974,51.1472740173],"type":"Point"}
}