{
  "type": "Feature",
  "properties": {
    "addr:full":"Elisabethlaan 204 Antwerpen (berchem) Antwerpen 2600",
    "addr:housenumber":"204",
    "addr:postcode":"2600",
    "addr:street":"Elisabethlaan;Antwerpen",
    "iso:country":"BE",
    "sg:address":"Elisabethlaan 204",
    "sg:city":"Antwerpen (berchem)",
    "sg:classifiers":[
        {
            "category":"Home & Garden",
            "subcategory":"Furniture",
            "type":"Retail Goods"
        }
    ],
    "sg:phone":"+32 3 230 03 63",
    "sg:postcode":"2600",
    "sg:province":"Antwerpen",
    "sg:tags":[
        "-"
    ],
    "wof:name":"T & Bm Bvba",
    "wof:placetype":"venue"
},
  "geometry": {"coordinates":[4.4232978821,51.1821250916],"type":"Point"}
}