{
  "type": "Feature",
  "properties": {
    "addr:full":"Rue Entre Les Ponts 19 Verviers (lambermont) Li\u00e8ge 4800",
    "addr:housenumber":"19",
    "addr:postcode":"4800",
    "addr:street":"Rue Entre Les Ponts;Lambermont",
    "iso:country":"BE",
    "sg:address":"Rue Entre Les Ponts 19",
    "sg:city":"Verviers (lambermont)",
    "sg:classifiers":[
        {
            "category":"Education",
            "subcategory":"Library",
            "type":"Public Place"
        }
    ],
    "sg:phone":"+32 87 33 49 04",
    "sg:postcode":"4800",
    "sg:province":"Li\u00e8ge",
    "wof:name":"Clarisses (librairie Des)",
    "wof:placetype":"venue"
},
  "geometry": {"coordinates":[5.8447098732,50.5884399414],"type":"Point"}
}