{
  "type": "Feature",
  "properties": {
    "addr:full":"Groenstraat 163 Ninove Oost-Vlaanderen 9406",
    "addr:housenumber":"163",
    "addr:postcode":"9406",
    "addr:street":"Groenstraat",
    "iso:country":"BE",
    "sg:address":"Groenstraat 163",
    "sg:city":"Ninove",
    "sg:orig_category":"Rundveehouders",
    "sg:phone":"+32 54 33 71 48",
    "sg:postcode":"9406",
    "sg:province":"Oost-Vlaanderen",
    "wof:name":"Robert Goeman",
    "wof:placetype":"venue"
},
  "geometry": {"coordinates":[3.970733881,50.8633003235],"type":"Point"}
}