{
  "type": "Feature",
  "properties": {
    "addr:full":"Birven 22 Aubel Li\u00e8ge 4880",
    "addr:housenumber":"22",
    "addr:postcode":"4880",
    "addr:street":"Birven",
    "iso:country":"BE",
    "sg:address":"Birven 22",
    "sg:city":"Aubel",
    "sg:classifiers":[
        {
            "category":"Farming",
            "subcategory":"Farm & Veterinary Services",
            "type":"Manufacturing & Wholesale Goods"
        }
    ],
    "sg:phone":"+32 87 68 66 62",
    "sg:postcode":"4880",
    "sg:province":"Li\u00e8ge",
    "sg:tags":[
        "agricultural",
        "contractor"
    ],
    "wof:name":"Guillaume J N",
    "wof:placetype":"venue"
},
  "geometry": {"coordinates":[5.9077000618,50.688495636],"type":"Point"}
}