{
  "type": "Feature",
  "properties": {
    "addr:full":"Menenstraat 87 Moorslede West-Vlaanderen 8890",
    "addr:housenumber":"87",
    "addr:postcode":"8890",
    "addr:street":"Menenstraat",
    "iso:country":"BE",
    "sg:address":"Menenstraat 87",
    "sg:city":"Moorslede",
    "sg:orig_category":"Elektrische installaties voor woningen",
    "sg:phone":"+32 56 50 25 20",
    "sg:postcode":"8890",
    "sg:province":"West-Vlaanderen",
    "wof:name":"Frans Vandenberghe",
    "wof:placetype":"venue"
},
  "geometry": {"coordinates":[3.1050000191,50.8398742676],"type":"Point"}
}