{
  "type": "Feature",
  "properties": {
    "addr:full":"Tweekerkenstraat 60 Zottegem Oost-Vlaanderen 9620",
    "addr:housenumber":"60",
    "addr:postcode":"9620",
    "addr:street":"Tweekerkenstraat",
    "iso:country":"BE",
    "sg:address":"Tweekerkenstraat 60",
    "sg:city":"Zottegem",
    "sg:orig_category":"Elektrische installaties voor woningen",
    "sg:phone":"+32 9 360 80 55",
    "sg:postcode":"9620",
    "sg:province":"Oost-Vlaanderen",
    "wof:name":"Luc Van Damme",
    "wof:placetype":"venue"
},
  "geometry": {"coordinates":[3.8112111092,50.871181488],"type":"Point"}
}