{
  "type": "Feature",
  "properties": {
    "addr:full":"Beenstraat 19 Nazareth Oost-Vlaanderen 9810",
    "addr:housenumber":"19",
    "addr:postcode":"9810",
    "addr:street":"Beenstraat",
    "iso:country":"BE",
    "sg:address":"Beenstraat 19",
    "sg:city":"Nazareth",
    "sg:orig_category":"Rundveehouders Varkenskwekers",
    "sg:phone":"+32 9 386 18 21",
    "sg:postcode":"9810",
    "sg:province":"Oost-Vlaanderen",
    "wof:name":"Jordaan Moyaert",
    "wof:placetype":"venue"
},
  "geometry": {"coordinates":[3.5781540871,50.9508552551],"type":"Point"}
}