{
  "type": "Feature",
  "properties": {
    "addr:full":"Diksmuidelaan 15 Brussel/bruxelles Bruxelles-Capitale 1000",
    "addr:housenumber":"15",
    "addr:postcode":"1000",
    "addr:street":"Diksmuidelaan;/",
    "iso:country":"BE",
    "sg:address":"Diksmuidelaan 15",
    "sg:city":"Brussel/bruxelles",
    "sg:orig_category":"Groenten and fruit Gh",
    "sg:phone":"+32 2 218 37 15",
    "sg:postcode":"1000",
    "sg:province":"Bruxelles-Capitale",
    "wof:name":"M. Lahaye",
    "wof:placetype":"venue"
},
  "geometry": {"coordinates":[4.3455457687,50.856464386],"type":"Point"}
}