{
  "type": "Feature",
  "properties": {
    "addr:full":"Wolvertemsesteenweg 97b1 Grimbergen Vlaams-Brabant 1850",
    "addr:housenumber":"97b1",
    "addr:postcode":"1850",
    "addr:street":"Wolvertemsesteenweg",
    "iso:country":"BE",
    "sg:address":"Wolvertemsesteenweg 97b1",
    "sg:city":"Grimbergen",
    "sg:orig_category":"Baby- and kinderkleding",
    "sg:phone":"+32 2 270 21 24",
    "sg:postcode":"1850",
    "sg:province":"Vlaams-Brabant",
    "wof:name":"Kid's House",
    "wof:placetype":"venue"
},
  "geometry": {"coordinates":[4.3654360771,50.9357376099],"type":"Point"}
}