{
  "type": "Feature",
  "properties": {
    "addr:full":"Otterstraat 151a Turnhout Antwerpen 2300",
    "addr:housenumber":"151a",
    "addr:postcode":"2300",
    "addr:street":"Otterstraat",
    "iso:country":"BE",
    "sg:address":"Otterstraat 151a",
    "sg:city":"Turnhout",
    "sg:classifiers":[
        {
            "category":"Banks & Credit Unions",
            "subcategory":"Bank",
            "type":"Services"
        }
    ],
    "sg:phone":"+32 14 42 69 29",
    "sg:postcode":"2300",
    "sg:province":"Antwerpen",
    "sg:tags":[
        "savings-banks"
    ],
    "wof:name":"Edak Zakenkantoor",
    "wof:placetype":"venue"
},
  "geometry": {"coordinates":[4.9567317963,51.3215103149],"type":"Point"}
}