{
  "type": "Feature",
  "properties": {
    "iso:country":"BE",
    "sg:address":"Rue Des Francs Arquebusiers 2",
    "sg:city":"Vis\u00e9",
    "sg:classifiers":[
        {
            "category":"Shopping",
            "subcategory":"Computers & Home Electronics",
            "type":"Retail Goods"
        }
    ],
    "sg:phone":"+32 4 379 58 66",
    "sg:postcode":"4600",
    "sg:province":"Li\u00e8ge",
    "sg:tags":[
        "-",
        "television",
        "radio"
    ],
    "wof:name":"Phillippsen Ets",
    "wof:placetype":"venue"
},
  "geometry": {"coordinates":[5.6938929558,50.7378196716],"type":"Point"}
}