{
  "type": "Feature",
  "properties": {
    "addr:full":"Rolweg 40 Brugge West-Vlaanderen 8000",
    "addr:housenumber":"40",
    "addr:postcode":"8000",
    "addr:street":"Rolweg",
    "iso:country":"BE",
    "sg:address":"Rolweg 40",
    "sg:city":"Brugge",
    "sg:orig_category":"Musea and historische gebouwen",
    "sg:phone":"+32 50 44 87 64",
    "sg:postcode":"8000",
    "sg:province":"West-Vlaanderen",
    "wof:name":"Museum Voor Volkskunde",
    "wof:placetype":"venue"
},
  "geometry": {"coordinates":[3.233314991,51.2136611938],"type":"Point"}
}