{
  "type": "Feature",
  "properties": {
    "iso:country":"BE",
    "sg:address":"Rue Jolibois 14",
    "sg:city":"Anderlues",
    "sg:orig_category":"Afbraak- and draineerwerken Gespecialiseerde residenti\u00eble bouw Woningbouw",
    "sg:phone":"+32 71 52 77 93",
    "sg:postcode":"6150",
    "sg:province":"Hainaut",
    "wof:name":"Sadin Beudin",
    "wof:placetype":"venue"
},
  "geometry": {"coordinates":[4.2873630524,50.4058952332],"type":"Point"}
}