{
  "type": "Feature",
  "properties": {
    "addr:full":"Rue De La Station 51 Ans Li\u00e8ge 4430",
    "addr:housenumber":"51",
    "addr:postcode":"4430",
    "addr:street":"Rue De La Station",
    "iso:country":"BE",
    "sg:address":"Rue De La Station 51",
    "sg:city":"Ans",
    "sg:classifiers":[
        {
            "category":"Shopping",
            "subcategory":"Clothing, Apparel, & Fashions",
            "type":"Retail Goods"
        }
    ],
    "sg:phone":"+32 4 239 16 60",
    "sg:postcode":"4430",
    "sg:province":"Li\u00e8ge",
    "sg:tags":[
        "boutique"
    ],
    "wof:name":"Allure",
    "wof:placetype":"venue"
},
  "geometry": {"coordinates":[5.5107531548,50.6624794006],"type":"Point"}
}