{
  "type": "Feature",
  "properties": {
    "iso:country":"BE",
    "sg:address":"Hemelaerstraat 25",
    "sg:city":"Sint-niklaas",
    "sg:classifiers":[
        {
            "category":"Communications",
            "type":"Services"
        }
    ],
    "sg:phone":"+32 3 766 45 87",
    "sg:postcode":"9100",
    "sg:province":"Oost-Vlaanderen",
    "sg:tags":[
        "translator"
    ],
    "wof:name":"Van Gavere Vertaalbureau",
    "wof:placetype":"venue"
},
  "geometry": {"coordinates":[4.1365981102,51.1640319824],"type":"Point"}
}