{
  "type": "Feature",
  "properties": {
    "iso:country":"BE",
    "sg:address":"Molenwalstraat 8",
    "sg:city":"Gent",
    "sg:orig_category":"Verplichte sociale verzekeringen",
    "sg:phone":"+32 9 227 86 13",
    "sg:postcode":"9030",
    "sg:province":"Oost-Vlaanderen",
    "wof:name":"Liberale Mutualiteit",
    "wof:placetype":"venue"
},
  "geometry": {"coordinates":[3.6961989403,51.0732688904],"type":"Point"}
}