{
  "type": "Feature",
  "properties": {
    "iso:country":"BE",
    "sg:address":"Avenue Carton De Wiart 27",
    "sg:city":"Bruxelles (jette)",
    "sg:classifiers":[
        {
            "category":"Retail",
            "subcategory":"Auto Repair",
            "type":"Services"
        }
    ],
    "sg:phone":"+32 2 427 71 40",
    "sg:postcode":"1090",
    "sg:province":"Bruxelles-Capitale",
    "sg:tags":[
        "garage"
    ],
    "wof:name":"Porsche Gaban",
    "wof:placetype":"venue"
},
  "geometry": {"coordinates":[4.3330230713,50.8680534363],"type":"Point"}
}