{
  "type": "Feature",
  "properties": {
    "addr:full":"Avenue De L'echevinage 20 Bruxelles (uccle) Bruxelles-Capitale 1180",
    "addr:housenumber":"20",
    "addr:postcode":"1180",
    "addr:street":"Avenue De L'Echevinage",
    "iso:country":"BE",
    "sg:address":"Avenue De L'echevinage 20",
    "sg:city":"Bruxelles (uccle)",
    "sg:classifiers":[
        {
            "category":"Health Services",
            "subcategory":"Doctor",
            "type":"Services"
        }
    ],
    "sg:phone":"+32 2 375 04 80",
    "sg:postcode":"1180",
    "sg:province":"Bruxelles-Capitale",
    "sg:tags":[
        "medicinephysicians",
        "surgeon"
    ],
    "wof:name":"Cock L",
    "wof:placetype":"venue"
},
  "geometry": {"coordinates":[4.3437180519,50.8041801453],"type":"Point"}
}