{
  "type": "Feature",
  "properties": {
    "addr:full":"Grand Scley 1 Havelange (m\u00e9an) Namur 5372",
    "addr:housenumber":"1",
    "addr:postcode":"5372",
    "iso:country":"BE",
    "sg:address":"Grand Scley 1",
    "sg:city":"Havelange (m\u00e9an)",
    "sg:classifiers":[
        {
            "category":"Arena",
            "subcategory":"Sports Club",
            "type":"Entertainment"
        }
    ],
    "sg:phone":"+32 86 32 32 32",
    "sg:postcode":"5372",
    "sg:province":"Namur",
    "wof:name":"Five Nations Golf Club",
    "wof:placetype":"venue"
},
  "geometry": {"coordinates":[5.3338699341,50.3617362976],"type":"Point"}
}