{
  "type": "Feature",
  "properties": {
    "addr:full":"Groebbe 2 Wezembeek-oppem Vlaams-Brabant 1970",
    "addr:housenumber":"2",
    "addr:postcode":"1970",
    "addr:street":"Groebbe",
    "iso:country":"BE",
    "sg:address":"Groebbe 2",
    "sg:city":"Wezembeek-oppem",
    "sg:classifiers":[
        {
            "category":"Building & Trades",
            "subcategory":"Landscaping Services",
            "type":"Services"
        }
    ],
    "sg:phone":"+32 2 305 69 10",
    "sg:postcode":"1970",
    "sg:province":"Vlaams-Brabant",
    "sg:tags":[
        "gardening",
        "garden",
        "maintenance"
    ],
    "wof:name":"Jardi-services",
    "wof:placetype":"venue"
},
  "geometry": {"coordinates":[4.4965219498,50.8339958191],"type":"Point"}
}