{
  "type": "Feature",
  "properties": {
    "iso:country":"BE",
    "sg:address":"Rue De Berneau",
    "sg:city":"Vise",
    "sg:orig_category":"Huisdieren and benodigdheden Royal Canin",
    "sg:phone":"+32 4 379 16 20",
    "sg:postcode":"4600",
    "sg:province":"Li\u00e8ge",
    "wof:name":"Villers",
    "wof:placetype":"venue"
},
  "geometry": {"coordinates":[5.7036390305,50.7366676331],"type":"Point"}
}