{
  "type": "Feature",
  "properties": {
    "addr:full":"Rue Surfoss\u00c9 20 Fleron Li\u00e8ge 4621",
    "addr:housenumber":"20",
    "addr:postcode":"4621",
    "addr:street":"Rue Surfosse\u0301",
    "iso:country":"BE",
    "sg:address":"Rue Surfoss\u00c9 20",
    "sg:city":"Fleron",
    "sg:orig_category":"Entretien and r\u00e9parations de voitures",
    "sg:phone":"+32 4 358 31 33",
    "sg:postcode":"4621",
    "sg:province":"Li\u00e8ge",
    "wof:name":"Garage Wesphal",
    "wof:placetype":"venue"
},
  "geometry": {"coordinates":[5.7030630112,50.6350860596],"type":"Point"}
}