{
  "type": "Feature",
  "properties": {
    "addr:full":"Rue De La Roche 15 Virton Luxembourg 6760",
    "addr:housenumber":"15",
    "addr:postcode":"6760",
    "addr:street":"Rue De La",
    "iso:country":"BE",
    "sg:address":"Rue De La Roche 15",
    "sg:city":"Virton",
    "sg:orig_category":"Electrom\u00e9nager, t\u00e9l\u00e9visions and radios. R\u00e9parations d'appareils \u00e9lectrom\u00e9nagers",
    "sg:phone":"+32 63 57 97 05",
    "sg:postcode":"6760",
    "sg:province":"Luxembourg",
    "wof:name":"Breda P.",
    "wof:placetype":"venue"
},
  "geometry": {"coordinates":[5.5312290192,49.5683135986],"type":"Point"}
}