{
  "type": "Feature",
  "properties": {
    "iso:country":"BE",
    "sg:address":"Grote Markt Koning Albert I 25-27",
    "sg:city":"Ieper",
    "sg:orig_category":"Non-Classified Establishments",
    "sg:phone":"+32 57 21 73 31",
    "sg:postcode":"8900",
    "sg:province":"West-Vlaanderen",
    "wof:name":"Delboo Interior Bvba",
    "wof:placetype":"venue"
},
  "geometry": {"coordinates":[2.8878269196,50.8513641357],"type":"Point"}
}