{
  "type": "Feature",
  "properties": {
    "iso:country":"BE",
    "sg:address":"Oude Siemerstraat 19",
    "sg:city":"Bilzen",
    "sg:orig_category":"Warenhuizen",
    "sg:phone":"+32 89 41 29 49",
    "sg:postcode":"3740",
    "sg:province":"Limburg",
    "wof:name":"Mathijs Vandecaetsbeek",
    "wof:placetype":"venue"
},
  "geometry": {"coordinates":[5.5229039192,50.8979415894],"type":"Point"}
}