{
  "type": "Feature",
  "properties": {
    "addr:full":"Roeselarestraat 1 Wevelgem West-Vlaanderen 8560",
    "addr:housenumber":"1",
    "addr:postcode":"8560",
    "addr:street":"Roeselarestraat",
    "iso:country":"BE",
    "sg:address":"Roeselarestraat 1",
    "sg:city":"Wevelgem",
    "sg:orig_category":"Herstelling horloges and juwelen Juwelen and horloges",
    "sg:phone":"+32 56 41 25 29",
    "sg:postcode":"8560",
    "sg:province":"West-Vlaanderen",
    "wof:name":"Huis Boury",
    "wof:placetype":"venue"
},
  "geometry": {"coordinates":[3.1813468933,50.8105888367],"type":"Point"}
}