{
  "type": "Feature",
  "properties": {
    "iso:country":"BE",
    "sg:address":"Rue Grande 40",
    "sg:city":"Quievrain",
    "sg:orig_category":"Kapsalons",
    "sg:phone":"+32 65 45 79 39",
    "sg:postcode":"7380",
    "sg:province":"Hainaut",
    "wof:name":"Coiffure Jean Pol",
    "wof:placetype":"venue"
},
  "geometry": {"coordinates":[3.6825289726,50.4063415527],"type":"Point"}
}