{
  "type": "Feature",
  "properties": {
    "addr:full":"Rue Du Partiau 22 Honnelles (angre) Hainaut 7387",
    "addr:housenumber":"22",
    "addr:postcode":"7387",
    "addr:street":"Rue Du Partiau",
    "iso:country":"BE",
    "sg:address":"Rue Du Partiau 22",
    "sg:city":"Honnelles (angre)",
    "sg:classifiers":[
        {
            "category":"Health Services",
            "subcategory":"Doctor",
            "type":"Services"
        }
    ],
    "sg:phone":"+32 65 75 90 38",
    "sg:postcode":"7387",
    "sg:province":"Hainaut",
    "sg:tags":[
        "medicinephysicians",
        "surgeon"
    ],
    "wof:name":"Carton Michel",
    "wof:placetype":"venue"
},
  "geometry": {"coordinates":[3.6943569183,50.3646621704],"type":"Point"}
}