{
  "type": "Feature",
  "properties": {
    "iso:country":"BE",
    "sg:address":"Leuvensesteenweg 287",
    "sg:city":"Kortenberg",
    "sg:classifiers":[
        {
            "category":"Building & Trades",
            "subcategory":"Construction",
            "type":"Services"
        }
    ],
    "sg:phone":"+32 2 759 87 96",
    "sg:postcode":"3070",
    "sg:province":"Vlaams-Brabant",
    "sg:tags":[
        "la",
        "de",
        "\u00e9quipement",
        "pour",
        "machine",
        "location"
    ],
    "wof:name":"Vranckx",
    "wof:placetype":"venue"
},
  "geometry": {"coordinates":[4.5371179581,50.8865890503],"type":"Point"}
}