{
  "type": "Feature",
  "properties": {
    "iso:country":"BE",
    "sg:address":"Kerkstraat 1",
    "sg:city":"Wemmel",
    "sg:orig_category":"G\u00e9nie hydraulique",
    "sg:phone":"+32 2 460 12 88",
    "sg:postcode":"1780",
    "sg:province":"Vlaams-Brabant",
    "wof:name":"Judo Wasseraufbereitung",
    "wof:placetype":"venue"
},
  "geometry": {"coordinates":[4.3030428886,50.9096450806],"type":"Point"}
}