{
  "type": "Feature",
  "properties": {
    "addr:full":"Boulevard Henri Rolin 5 B Waterloo Brabant Wallon 1410",
    "addr:housenumber":"5 b",
    "addr:postcode":"1410",
    "addr:street":"Boulevard Henri Rolin",
    "iso:country":"BE",
    "sg:address":"Boulevard Henri Rolin 5 B",
    "sg:city":"Waterloo",
    "sg:orig_category":"Muziekinstrumenten",
    "sg:phone":"+32 2 354 59 61",
    "sg:postcode":"1410",
    "sg:province":"Brabant Wallon",
    "wof:name":"Piano Creasons",
    "wof:placetype":"venue"
},
  "geometry": {"coordinates":[4.3998417854,50.7115440369],"type":"Point"}
}