{
  "type": "Feature",
  "properties": {
    "iso:country":"BE",
    "sg:address":"Sint-truiderstraat 15b1",
    "sg:city":"Tongeren",
    "sg:orig_category":"Cosmetica and toiletartikelen Winkelinrichting and handelsuitrusting Gh",
    "sg:phone":"+32 12 26 41 16",
    "sg:postcode":"3700",
    "sg:province":"Limburg",
    "wof:name":"Florale",
    "wof:placetype":"venue"
},
  "geometry": {"coordinates":[5.4620838165,50.7805633545],"type":"Point"}
}