{
  "type": "Feature",
  "properties": {
    "iso:country":"BE",
    "sg:address":"Steenweg 73",
    "sg:city":"Zoutleeuw",
    "sg:orig_category":"Industri\u00eble and commerci\u00eble bouw",
    "sg:phone":"+32 11 78 24 66",
    "sg:postcode":"3440",
    "sg:province":"Vlaams-Brabant",
    "wof:name":"Genef",
    "wof:placetype":"venue"
},
  "geometry": {"coordinates":[5.0745711327,50.8375434875],"type":"Point"}
}