{
  "type": "Feature",
  "properties": {
    "iso:country":"BE",
    "sg:address":"Geerdegemdries 27",
    "sg:city":"Mechelen",
    "sg:classifiers":[
        {
            "category":"Social Services",
            "subcategory":"Job Training",
            "type":"Services"
        }
    ],
    "sg:phone":"+32 15 41 56 62",
    "sg:postcode":"2800",
    "sg:province":"Antwerpen",
    "sg:tags":[
        "coordinator",
        "safety"
    ],
    "wof:name":"De Schryver Karel Bvba",
    "wof:placetype":"venue"
},
  "geometry": {"coordinates":[4.4694910049,51.004989624],"type":"Point"}
}