{
  "type": "Feature",
  "properties": {
    "iso:country":"BE",
    "sg:address":"Ninoofsesteenweg 38",
    "sg:city":"Haaltert",
    "sg:orig_category":"Dakwerken Installatie van houten of kunststof schrijnwerk Plaatsen van vloer- and muurbekleding Plei",
    "sg:phone":"+32 54 34 19 26",
    "sg:postcode":"9450",
    "sg:province":"Oost-Vlaanderen",
    "wof:name":"Asselman",
    "wof:placetype":"venue"
},
  "geometry": {"coordinates":[4.0186061859,50.8664932251],"type":"Point"}
}