{
  "type": "Feature",
  "properties": {
    "addr:full":"Nieuwlandlaan 28 Box 105 Aarschot Vlaams-Brabant 3200",
    "addr:housenumber":"28",
    "addr:postcode":"3200",
    "addr:street":"Nieuwlandlaan;Box 105;Vlaams-Brabant",
    "iso:country":"BE",
    "sg:address":"Nieuwlandlaan 28 Box 105",
    "sg:city":"Aarschot",
    "sg:classifiers":[
        {
            "category":"Landmark",
            "subcategory":"Memorial",
            "type":"Public Place"
        }
    ],
    "sg:phone":"+32 16 56 70 63",
    "sg:postcode":"3200",
    "sg:province":"Vlaams-Brabant",
    "sg:tags":[
        "-",
        "monument"
    ],
    "wof:name":"Rabo Nv",
    "wof:placetype":"venue"
},
  "geometry": {"coordinates":[4.8058400154,50.9789581299],"type":"Point"}
}