{
  "type": "Feature",
  "properties": {
    "iso:country":"BE",
    "sg:address":"Warande 131",
    "sg:city":"Laarne",
    "sg:orig_category":"Boekhouders",
    "sg:phone":"+32 9 366 45 40",
    "sg:postcode":"9270",
    "sg:province":"Oost-Vlaanderen",
    "wof:name":"Rita De Vos",
    "wof:placetype":"venue"
},
  "geometry": {"coordinates":[3.8490929604,51.0267181396],"type":"Point"}
}