{
  "type": "Feature",
  "properties": {
    "addr:full":"Avenue Reine Astrid 100 Spa Li\u00e8ge 4900",
    "addr:housenumber":"100",
    "addr:postcode":"4900",
    "addr:street":"Avenue Reine Astrid",
    "iso:country":"BE",
    "sg:address":"Avenue Reine Astrid 100",
    "sg:city":"Spa",
    "sg:orig_category":"Brood, gebak and snoepgoed",
    "sg:phone":"+32 87 77 13 75",
    "sg:postcode":"4900",
    "sg:province":"Li\u00e8ge",
    "wof:name":"Marcel Muller",
    "wof:placetype":"venue"
},
  "geometry": {"coordinates":[5.8576312065,50.4916191101],"type":"Point"}
}