{
  "type": "Feature",
  "properties": {
    "iso:country":"BE",
    "sg:address":"552-554 Brugsesteenweg",
    "sg:city":"Roeselare",
    "sg:classifiers":[
        {
            "category":"Farming",
            "subcategory":"Livestock Farm",
            "type":"Manufacturing & Wholesale Goods"
        }
    ],
    "sg:phone":"+32 51 24 49 70",
    "sg:postcode":"8800",
    "sg:province":"West-Vlaanderen",
    "sg:tags":[
        "breeding",
        "agriculture",
        "animal"
    ],
    "wof:name":"Gastro Fish Nv",
    "wof:placetype":"venue"
},
  "geometry": {"coordinates":[3.1216299534,50.956161499],"type":"Point"}
}