{
  "type": "Feature",
  "properties": {
    "iso:country":"BE",
    "sg:address":"Kolonel Bourgstraat 120",
    "sg:city":"Evere",
    "sg:orig_category":"Autoverhuur",
    "sg:phone":"+32 2 706 41 11",
    "sg:postcode":"1140",
    "sg:province":"Bruxelles-Capitale",
    "wof:name":"Axus Belgium",
    "wof:placetype":"venue"
},
  "geometry": {"coordinates":[4.4132900238,50.8541183472],"type":"Point"}
}