{
  "type": "Feature",
  "properties": {
    "iso:country":"BE",
    "sg:address":"Rue Grande 90",
    "sg:city":"Dour",
    "sg:classifiers":[
        {
            "category":"Communications",
            "type":"Services"
        }
    ],
    "sg:phone":"+32 477 61 46 84",
    "sg:postcode":"7370",
    "sg:province":"Hainaut",
    "sg:tags":[
        "translator"
    ],
    "wof:name":"Waroquier E",
    "wof:placetype":"venue"
},
  "geometry": {"coordinates":[3.7814590931,50.3996543884],"type":"Point"}
}