{
  "type": "Feature",
  "properties": {
    "addr:full":"Herbert Hooverplein 3 Leuven Vlaams-Brabant 3000",
    "addr:housenumber":"3",
    "addr:postcode":"3000",
    "iso:country":"BE",
    "sg:address":"Herbert Hooverplein 3",
    "sg:city":"Leuven",
    "sg:classifiers":[
        {
            "category":"Shopping",
            "subcategory":"Clothing, Apparel, & Fashions",
            "type":"Retail Goods"
        }
    ],
    "sg:phone":"+32 16 22 43 83",
    "sg:postcode":"3000",
    "sg:province":"Vlaams-Brabant",
    "sg:tags":[
        "clothing",
        "-",
        "gentleman"
    ],
    "wof:name":"Vandeven Tailor Nv",
    "wof:placetype":"venue"
},
  "geometry": {"coordinates":[4.7055039406,50.8772315979],"type":"Point"}
}