{
  "type": "Feature",
  "properties": {
    "iso:country":"BE",
    "sg:address":"Place Albert I 6",
    "sg:city":"Courcelles (trazegnies)",
    "sg:classifiers":[
        {
            "category":"Bars & Pubs",
            "type":"Food & Drink"
        }
    ],
    "sg:phone":"+32 71 45 73 97",
    "sg:postcode":"6183",
    "sg:province":"Hainaut",
    "wof:name":"Caf\u00e9 Des Sports",
    "wof:placetype":"venue"
},
  "geometry": {"coordinates":[4.3305897713,50.4651794434],"type":"Point"}
}