{
  "type": "Feature",
  "properties": {
    "addr:full":"Avenue De Roodebeek 5 Bruxelles (schaerbeek) Bruxelles-Capitale 1030",
    "addr:housenumber":"5",
    "addr:postcode":"1030",
    "addr:street":"Avenue De Roodebeek",
    "iso:country":"BE",
    "sg:address":"Avenue De Roodebeek 5",
    "sg:city":"Bruxelles (schaerbeek)",
    "sg:classifiers":[
        {
            "category":"Education",
            "subcategory":"School",
            "type":"Public Place"
        }
    ],
    "sg:phone":"+32 2 736 74 36",
    "sg:postcode":"1030",
    "sg:province":"Bruxelles-Capitale",
    "sg:tags":[
        "-",
        "private"
    ],
    "wof:name":"Abc Langues",
    "wof:placetype":"venue"
},
  "geometry": {"coordinates":[4.3960180283,50.8473548889],"type":"Point"}
}