{
  "type": "Feature",
  "properties": {
    "addr:full":"Jozef Reusenslei 28 Borsbeek Antwerpen 2150",
    "addr:housenumber":"28",
    "addr:postcode":"2150",
    "addr:street":"Jozef Reusenslei",
    "iso:country":"BE",
    "sg:address":"Jozef Reusenslei 28",
    "sg:city":"Borsbeek",
    "sg:orig_category":"Kapsalons",
    "sg:phone":"+32 3 366 57 12",
    "sg:postcode":"2150",
    "sg:province":"Antwerpen",
    "wof:name":"Walter Vingerhoets",
    "wof:placetype":"venue"
},
  "geometry": {"coordinates":[4.4882850647,51.1938743591],"type":"Point"}
}