{
  "type": "Feature",
  "properties": {
    "iso:country":"BE",
    "sg:address":"Provincieweg 252",
    "sg:city":"Herzele",
    "sg:orig_category":"Rusthuizen and serviceflats",
    "sg:phone":"+32 53 63 09 09",
    "sg:postcode":"9550",
    "sg:province":"Oost-Vlaanderen",
    "wof:name":"Residentie \u00b4t Rusthofje",
    "wof:placetype":"venue"
},
  "geometry": {"coordinates":[3.8787400723,50.8998908997],"type":"Point"}
}