{
  "type": "Feature",
  "properties": {
    "addr:full":"Hundelgemsesteenweg 321 Merelbeke Oost-Vlaanderen 9820",
    "addr:housenumber":"321",
    "addr:postcode":"9820",
    "addr:street":"Hundelgemsesteenweg",
    "iso:country":"BE",
    "sg:address":"Hundelgemsesteenweg 321",
    "sg:city":"Merelbeke",
    "sg:orig_category":"Location de v\u00eatements, chaussures and textiles",
    "sg:phone":"+32 9 230 41 00",
    "sg:postcode":"9820",
    "sg:province":"Oost-Vlaanderen",
    "wof:name":"J.m. Topkleding",
    "wof:placetype":"venue"
},
  "geometry": {"coordinates":[3.7457299232,50.9953842163],"type":"Point"}
}