{
  "type": "Feature",
  "properties": {
    "addr:full":"Berchemweg 216 Oudenaarde Oost-Vlaanderen 9700",
    "addr:housenumber":"216",
    "addr:postcode":"9700",
    "iso:country":"BE",
    "sg:address":"Berchemweg 216",
    "sg:city":"Oudenaarde",
    "sg:orig_category":"Slagers",
    "sg:phone":"+32 55 30 91 26",
    "sg:postcode":"9700",
    "sg:province":"Oost-Vlaanderen",
    "wof:name":"Slagerij Bart",
    "wof:placetype":"venue"
},
  "geometry": {"coordinates":[3.5771789551,50.8200302124],"type":"Point"}
}