{
  "type": "Feature",
  "properties": {
    "iso:country":"BE",
    "sg:address":"L.a. Schockaertstraat 59",
    "sg:city":"Sint-pieters-leeuw",
    "sg:orig_category":"Location d'appareils audio-visuels",
    "sg:phone":"+32 2 371 03 90",
    "sg:postcode":"1600",
    "sg:province":"Vlaams-Brabant",
    "wof:name":"Flashlight Company Bruss.",
    "wof:placetype":"venue"
},
  "geometry": {"coordinates":[4.282640934,50.8029022217],"type":"Point"}
}