{
  "type": "Feature",
  "properties": {
    "addr:full":"Moerkerkse Steenweg 28 Brugge West-Vlaanderen 8310",
    "addr:housenumber":"28",
    "addr:postcode":"8310",
    "addr:street":"Moerkerkse Steenweg",
    "iso:country":"BE",
    "sg:address":"Moerkerkse Steenweg 28",
    "sg:city":"Brugge",
    "sg:orig_category":"Kansspelen Krantenwinkels Rookartikelen",
    "sg:phone":"+32 50 35 28 70",
    "sg:postcode":"8310",
    "sg:province":"West-Vlaanderen",
    "wof:name":"Boekhandel Flupke",
    "wof:placetype":"venue"
},
  "geometry": {"coordinates":[3.2435200214,51.2129974365],"type":"Point"}
}