{
  "type": "Feature",
  "properties": {
    "iso:country":"BE",
    "sg:address":"De B\u00c9riotstraat 59",
    "sg:city":"Sint-joost-ten-node/saint-josse-ten-noode",
    "sg:classifiers":[
        {
            "category":"Restaurant",
            "type":"Food & Drink"
        }
    ],
    "sg:phone":"+32 2 223 72 30",
    "sg:postcode":"1210",
    "sg:province":"Bruxelles-Capitale",
    "sg:tags":[
        "caf\u00e9s"
    ],
    "wof:name":"Nelson\u00b4s Taverne",
    "wof:placetype":"venue"
},
  "geometry": {"coordinates":[4.3720068932,50.8506622314],"type":"Point"}
}