{
  "type": "Feature",
  "properties": {
    "addr:full":"Dorp 3 Grobbendonk Antwerpen 2288",
    "addr:housenumber":"3",
    "addr:postcode":"2288",
    "addr:street":"Dorp",
    "iso:country":"BE",
    "sg:address":"Dorp 3",
    "sg:city":"Grobbendonk",
    "sg:orig_category":"Plaatsen van vloer- and muurbekleding Schilders",
    "sg:phone":"+32 14 51 13 87",
    "sg:postcode":"2288",
    "sg:province":"Antwerpen",
    "wof:name":"L. Van Thielen",
    "wof:placetype":"venue"
},
  "geometry": {"coordinates":[4.7416939735,51.1719970703],"type":"Point"}
}