{
  "type": "Feature",
  "properties": {
    "addr:full":"Rue T. De Baisieux 120 Jette Bruxelles-Capitale 1090",
    "addr:housenumber":"120",
    "addr:postcode":"1090",
    "addr:street":"Rue T. De Baisieux",
    "iso:country":"BE",
    "sg:address":"Rue T. De Baisieux 120",
    "sg:city":"Jette",
    "sg:orig_category":"Traitement and rev\u00eatement des m\u00e9taux",
    "sg:phone":"+32 2 478 81 45",
    "sg:postcode":"1090",
    "sg:province":"Bruxelles-Capitale",
    "wof:name":"Metal Industrie",
    "wof:placetype":"venue"
},
  "geometry": {"coordinates":[4.3355817795,50.8861656189],"type":"Point"}
}