{
  "type": "Feature",
  "properties": {
    "iso:country":"BE",
    "sg:address":"Avenue Doyen Roger Woine 38",
    "sg:city":"Yvoir",
    "sg:classifiers":[
        {
            "category":"Health Services",
            "subcategory":"Doctor",
            "type":"Services"
        }
    ],
    "sg:phone":"+32 82 61 47 17",
    "sg:postcode":"5530",
    "sg:province":"Namur",
    "sg:tags":[
        "medicinephysicians",
        "surgeon"
    ],
    "wof:name":"Deborsu N",
    "wof:placetype":"venue"
},
  "geometry": {"coordinates":[4.8732829094,50.3301620483],"type":"Point"}
}