{
  "type": "Feature",
  "properties": {
    "addr:full":"Rue Des Honnelles 26 Dour (wih\u00e9ries) Hainaut 7370",
    "addr:housenumber":"26",
    "addr:postcode":"7370",
    "addr:street":"Rue Des Honnelles;Wihe\u0301Ries Hainaut",
    "iso:country":"BE",
    "sg:address":"Rue Des Honnelles 26",
    "sg:city":"Dour (wih\u00e9ries)",
    "sg:classifiers":[
        {
            "category":"Health Services",
            "subcategory":"Nursing And Care Facility",
            "type":"Services"
        }
    ],
    "sg:phone":"+32 65 65 10 22",
    "sg:postcode":"7370",
    "sg:province":"Hainaut",
    "sg:tags":[
        "home"
    ],
    "wof:name":"Bernier N",
    "wof:placetype":"venue"
},
  "geometry": {"coordinates":[3.7515809536,50.3830108643],"type":"Point"}
}