{
  "type": "Feature",
  "properties": {
    "iso:country":"BE",
    "sg:address":"Rue Du Bilemont 184",
    "sg:city":"Mouscron",
    "sg:classifiers":[
        {
            "category":"Home & Garden",
            "subcategory":"Carpets & Floor Coverings",
            "type":"Retail Goods"
        }
    ],
    "sg:phone":"+32 56 33 53 06",
    "sg:postcode":"7700",
    "sg:province":"Hainaut",
    "sg:tags":[
        "layer",
        "mosaicists"
    ],
    "wof:name":"Vandendorpe M",
    "wof:placetype":"venue"
},
  "geometry": {"coordinates":[3.2144908905,50.7366065979],"type":"Point"}
}