{
  "type": "Feature",
  "properties": {
    "iso:country":"BE",
    "sg:address":"Vermeulenstraat 17",
    "sg:city":"Tongeren",
    "sg:classifiers":[
        {
            "category":"Organizations",
            "subcategory":"Community Association",
            "type":"Services"
        }
    ],
    "sg:phone":"+32 12 23 71 67",
    "sg:postcode":"3700",
    "sg:province":"Limburg",
    "sg:tags":[
        "organisation"
    ],
    "wof:name":"Tongers Jongerencentrum",
    "wof:placetype":"venue"
},
  "geometry": {"coordinates":[5.4635281563,50.7829780579],"type":"Point"}
}