{
  "type": "Feature",
  "properties": {
    "iso:country":"BE",
    "sg:address":"Goetsenhovenplein 2",
    "sg:city":"Tienen",
    "sg:orig_category":"Banques and organismes de cr\u00e9dit",
    "sg:phone":"+32 16 82 23 64",
    "sg:postcode":"3300",
    "sg:province":"Vlaams-Brabant",
    "wof:name":"Bielen",
    "wof:placetype":"venue"
},
  "geometry": {"coordinates":[4.930077076,50.8096694946],"type":"Point"}
}