{
  "type": "Feature",
  "properties": {
    "addr:full":"Avenue Edouard B\u00e9n\u00e8s 197 Bruxelles (molenbeek-saint-jean) Bruxelles-Capitale 1080",
    "addr:housenumber":"197",
    "addr:postcode":"1080",
    "addr:street":"Avenue Edouard Be\u0301Ne\u0300S",
    "iso:country":"BE",
    "sg:address":"Avenue Edouard B\u00e9n\u00e8s 197",
    "sg:city":"Bruxelles (molenbeek-saint-jean)",
    "sg:classifiers":[
        {
            "category":"Arts & Performance",
            "subcategory":"Music",
            "type":"Entertainment"
        }
    ],
    "sg:phone":"+32 2 414 57 92",
    "sg:postcode":"1080",
    "sg:province":"Bruxelles-Capitale",
    "sg:tags":[
        "freelance",
        "musician"
    ],
    "wof:name":"Decae P",
    "wof:placetype":"venue"
},
  "geometry": {"coordinates":[4.3121981621,50.8638496399],"type":"Point"}
}