{
  "type": "Feature",
  "properties": {
    "addr:full":"Rue L\u00e9on-castilhon 46 Arlon Luxembourg 6700",
    "addr:housenumber":"46",
    "addr:postcode":"6700",
    "addr:street":"Rue Le\u0301On-Castilhon",
    "iso:country":"BE",
    "sg:address":"Rue L\u00e9on-castilhon 46",
    "sg:city":"Arlon",
    "sg:classifiers":[
        {
            "category":"Health Services",
            "subcategory":"Health Practitioner",
            "type":"Services"
        }
    ],
    "sg:phone":"+32 63 22 59 11",
    "sg:postcode":"6700",
    "sg:province":"Luxembourg",
    "sg:tags":[
        "physiotherapist"
    ],
    "wof:name":"Collignon Pascale",
    "wof:placetype":"venue"
},
  "geometry": {"coordinates":[5.8078250885,49.6833496094],"type":"Point"}
}