{
  "type": "Feature",
  "properties": {
    "iso:country":"BE",
    "sg:address":"Chaussee De Tongres 427",
    "sg:city":"Juprelle",
    "sg:orig_category":"Disneyland Parijs",
    "sg:phone":"+32 4 278 02 03",
    "sg:postcode":"4450",
    "sg:province":"Li\u00e8ge",
    "wof:name":"Perfect Travel",
    "wof:placetype":"venue"
},
  "geometry": {"coordinates":[5.5242190361,50.709274292],"type":"Point"}
}