{
  "type": "Feature",
  "properties": {
    "iso:country":"BE",
    "sg:address":"Kerselaarstraat 1",
    "sg:city":"Alveringem (leisele)",
    "sg:orig_category":"Non-Classified Establishments",
    "sg:phone":"+32 58 29 80 11",
    "sg:postcode":"8691",
    "sg:province":"West-Vlaanderen",
    "wof:name":"Verbrugghe Nv",
    "wof:placetype":"venue"
},
  "geometry": {"coordinates":[2.6305069923,50.9821014404],"type":"Point"}
}