{
  "type": "Feature",
  "properties": {
    "iso:country":"BE",
    "sg:address":"Route De Mons 237",
    "sg:city":"Erquelinnes",
    "sg:orig_category":"Openbare veiligheid",
    "sg:phone":"+32 71 55 50 19",
    "sg:postcode":"6560",
    "sg:province":"Hainaut",
    "wof:name":"Police F\u00c9d\u00c9rale/federale Politie",
    "wof:placetype":"venue"
},
  "geometry": {"coordinates":[4.1347208023,50.3124237061],"type":"Point"}
}