{
  "type": "Feature",
  "properties": {
    "addr:full":"Moli\u00c8relaan 86 Vorst/forest Bruxelles-Capitale 1190",
    "addr:housenumber":"86",
    "addr:postcode":"1190",
    "addr:street":"Molie\u0300Relaan;/ Forest",
    "iso:country":"BE",
    "sg:address":"Moli\u00c8relaan 86",
    "sg:city":"Vorst/forest",
    "sg:classifiers":[
        {
            "category":"Recreation",
            "type":"Entertainment"
        }
    ],
    "sg:phone":"+32 2 346 10 25",
    "sg:postcode":"1190",
    "sg:province":"Bruxelles-Capitale",
    "sg:tags":[
        "diver",
        "amusement"
    ],
    "wof:name":"Charles Kleinberg",
    "wof:placetype":"venue"
},
  "geometry": {"coordinates":[4.346394062,50.816444397],"type":"Point"}
}