{
  "type": "Feature",
  "properties": {
    "iso:country":"BE",
    "sg:address":"Gebroeders Naudtslaan 56",
    "sg:city":"Wachtebeke",
    "sg:orig_category":"Plomberie, chauffage and installations sanitaires. Ramassage and traitement des d\u00e9chets agricoles, i",
    "sg:phone":"+32 9 342 84 39",
    "sg:postcode":"9185",
    "sg:province":"Oost-Vlaanderen",
    "wof:name":"Watco Industrial Cleaning Olen",
    "wof:placetype":"venue"
},
  "geometry": {"coordinates":[3.8393929005,51.1787528992],"type":"Point"}
}