{
  "type": "Feature",
  "properties": {
    "iso:country":"BE",
    "sg:address":"Bleyveld 14",
    "sg:city":"Hoegaarden",
    "sg:classifiers":[
        {
            "category":"Professional",
            "subcategory":"Art Services",
            "type":"Services"
        }
    ],
    "sg:phone":"+32 479 36 14 22",
    "sg:postcode":"3320",
    "sg:province":"Vlaams-Brabant",
    "sg:tags":[
        "interior",
        "designer"
    ],
    "wof:name":"K.n.i. Bvba",
    "wof:placetype":"venue"
},
  "geometry": {"coordinates":[4.9040470123,50.7738456726],"type":"Point"}
}