{
  "type": "Feature",
  "properties": {
    "addr:full":"Provinciale Steenweg 317 Schelle Antwerpen 2627",
    "addr:housenumber":"317",
    "addr:postcode":"2627",
    "addr:street":"Provinciale Steenweg",
    "iso:country":"BE",
    "sg:address":"Provinciale Steenweg 317",
    "sg:city":"Schelle",
    "sg:classifiers":[
        {
            "category":"Retail",
            "subcategory":"Auto Repair",
            "type":"Services"
        }
    ],
    "sg:phone":"+32 3 887 99 60",
    "sg:postcode":"2627",
    "sg:province":"Antwerpen",
    "sg:tags":[
        "garage"
    ],
    "wof:name":"Dietens T",
    "wof:placetype":"venue"
},
  "geometry": {"coordinates":[4.3368802071,51.1204376221],"type":"Point"}
}