{
  "type": "Feature",
  "properties": {
    "iso:country":"BE",
    "sg:address":"Chauss\u00e9e De Mons 39",
    "sg:city":"Soignies",
    "sg:classifiers":[
        {
            "category":"Real Estate",
            "subcategory":"Real Estate Services",
            "type":"Services"
        }
    ],
    "sg:phone":"+32 67 69 34 69",
    "sg:postcode":"7060",
    "sg:province":"Hainaut",
    "wof:name":"Devel Et Cie Sprl",
    "wof:placetype":"venue"
},
  "geometry": {"coordinates":[4.0658688545,50.5708312988],"type":"Point"}
}