{
  "type": "Feature",
  "properties": {
    "iso:country":"BE",
    "sg:address":"Rue Adolphe Damseaux 6",
    "sg:city":"Gembloux-sur-orneau (gembloux)",
    "sg:classifiers":[
        {
            "category":"Shopping",
            "subcategory":"Musical Instruments",
            "type":"Retail Goods"
        }
    ],
    "sg:phone":"+32 81 61 15 34",
    "sg:postcode":"5030",
    "sg:province":"Namur",
    "sg:tags":[
        "piano",
        "-",
        "tuning"
    ],
    "wof:name":"De Sauvage D",
    "wof:placetype":"venue"
},
  "geometry": {"coordinates":[4.6921401024,50.5612640381],"type":"Point"}
}