{
  "type": "Feature",
  "properties": {
    "iso:country":"BE",
    "sg:address":"Rue Principale 49ba",
    "sg:city":"Fexhe-le-haut-clocher",
    "sg:classifiers":[
        {
            "category":"Arena",
            "subcategory":"Sports Club",
            "type":"Entertainment"
        }
    ],
    "sg:phone":"+32 4 250 32 99",
    "sg:postcode":"4347",
    "sg:province":"Li\u00e8ge",
    "sg:tags":[
        "de"
    ],
    "wof:name":"Le Progr\u00c8s",
    "wof:placetype":"venue"
},
  "geometry": {"coordinates":[5.3813099861,50.6582374573],"type":"Point"}
}