{
  "type": "Feature",
  "properties": {
    "addr:full":"Chemin D'hollaye 18 Mont-de-l'enclus Hainaut 7750",
    "addr:housenumber":"18",
    "addr:postcode":"7750",
    "addr:street":"Chemin D'Hollaye;Hainaut",
    "iso:country":"BE",
    "sg:address":"Chemin D'hollaye 18",
    "sg:city":"Mont-de-l'enclus",
    "sg:orig_category":"Rundveehouders",
    "sg:phone":"+32 69 45 41 33",
    "sg:postcode":"7750",
    "sg:province":"Hainaut",
    "wof:name":"Paul Degroote",
    "wof:placetype":"venue"
},
  "geometry": {"coordinates":[2.6025109291,46.3370933533],"type":"Point"}
}