{
  "type": "Feature",
  "properties": {
    "iso:country":"BE",
    "sg:address":"Korenbloemlaan 39",
    "sg:city":"Schoten",
    "sg:classifiers":[
        {
            "category":"Insurance",
            "subcategory":"Insurance Agent",
            "type":"Services"
        }
    ],
    "sg:phone":"+32 3 658 31 84",
    "sg:postcode":"2900",
    "sg:province":"Antwerpen",
    "sg:tags":[
        "broker"
    ],
    "wof:name":"Perfinco Bvba",
    "wof:placetype":"venue"
},
  "geometry": {"coordinates":[4.5089430809,51.2623596191],"type":"Point"}
}