{
  "type": "Feature",
  "properties": {
    "iso:country":"BE",
    "sg:address":"Rue Jules Bary 24",
    "sg:city":"Vielsalm",
    "sg:classifiers":[
        {
            "category":"Military Area",
            "subcategory":"Air Force Base",
            "type":"Public Place"
        }
    ],
    "sg:phone":"+32 80 21 59 15",
    "sg:postcode":"6690",
    "sg:province":"Luxembourg",
    "sg:tags":[
        "fire",
        "protection"
    ],
    "wof:name":"Fire Protect S.a",
    "wof:placetype":"venue"
},
  "geometry": {"coordinates":[5.9212441444,50.2841949463],"type":"Point"}
}