{
  "type": "Feature",
  "properties": {
    "iso:country":"BE",
    "sg:address":"R\u00e9sidence Du Ch\u00e2teau 8",
    "sg:city":"La Louvi\u00e8re (str\u00e9py-bracquegnies)",
    "sg:classifiers":[
        {
            "category":"Education",
            "subcategory":"Special Training",
            "type":"Public Place"
        }
    ],
    "sg:phone":"+32 477 58 17 51",
    "sg:postcode":"7110",
    "sg:province":"Hainaut",
    "sg:tags":[
        "school",
        "sailing"
    ],
    "wof:name":"Marivoile",
    "wof:placetype":"venue"
},
  "geometry": {"coordinates":[4.1505050659,50.4826698303],"type":"Point"}
}