{
  "type": "Feature",
  "properties": {
    "iso:country":"BE",
    "sg:address":"Leewerkstraat 2",
    "sg:city":"Heuvelland",
    "sg:orig_category":"Eleveurs de bovins",
    "sg:phone":"+32 57 44 59 23",
    "sg:postcode":"8950",
    "sg:province":"West-Vlaanderen",
    "wof:name":"Michel Verhee",
    "wof:placetype":"venue"
},
  "geometry": {"coordinates":[2.825979948,50.74634552],"type":"Point"}
}