{
  "type": "Feature",
  "properties": {
    "addr:full":"Maastrichterstraat 13 Hasselt Limburg 3500",
    "addr:housenumber":"13",
    "addr:postcode":"3500",
    "addr:street":"Maastrichterstraat",
    "iso:country":"BE",
    "sg:address":"Maastrichterstraat 13",
    "sg:city":"Hasselt",
    "sg:orig_category":"Disneyland Parijs Reisbureaus",
    "sg:phone":"+32 11 41 98 80",
    "sg:postcode":"3500",
    "sg:province":"Limburg",
    "wof:name":"Ticket Bbl Travel",
    "wof:placetype":"venue"
},
  "geometry": {"coordinates":[5.338452816,50.9290542603],"type":"Point"}
}