{
  "type": "Feature",
  "properties": {
    "iso:country":"BE",
    "sg:address":"Broekhofstraat 1a",
    "sg:city":"Dilsen-stokkem (lanklaar)",
    "sg:classifiers":[
        {
            "category":"Professional",
            "subcategory":"Lawyer & Legal Services",
            "type":"Services"
        }
    ],
    "sg:phone":"+32 89 81 24 94",
    "sg:postcode":"3650",
    "sg:province":"Limburg",
    "wof:name":"Peeters L",
    "wof:placetype":"venue"
},
  "geometry": {"coordinates":[5.727396965,51.0364189148],"type":"Point"}
}