{
  "type": "Feature",
  "properties": {
    "iso:country":"BE",
    "sg:address":"Bergensestweg 16",
    "sg:city":"Sint-pieters-leeuw",
    "sg:orig_category":"Herstellingen and onderhoud van auto's",
    "sg:phone":"+32 2 377 21 02",
    "sg:postcode":"1600",
    "sg:province":"Vlaams-Brabant",
    "wof:name":"Kce Motors",
    "wof:placetype":"venue"
},
  "geometry": {"coordinates":[4.2887091637,50.8074417114],"type":"Point"}
}