{
  "type": "Feature",
  "properties": {
    "addr:full":"Rue Paix Dieu 4 Amay Li\u00e8ge 4540",
    "addr:housenumber":"4",
    "addr:postcode":"4540",
    "addr:street":"Rue Paix Dieu",
    "iso:country":"BE",
    "sg:address":"Rue Paix Dieu 4",
    "sg:city":"Amay",
    "sg:orig_category":"Paramedische behandelingen",
    "sg:phone":"+32 85 31 25 68",
    "sg:postcode":"4540",
    "sg:province":"Li\u00e8ge",
    "wof:name":"Hella",
    "wof:placetype":"venue"
},
  "geometry": {"coordinates":[5.2963337898,50.5701141357],"type":"Point"}
}