{
  "type": "Feature",
  "properties": {
    "iso:country":"BE",
    "sg:address":"Fabriekstraat 12",
    "sg:city":"Brasschaat",
    "sg:orig_category":"Elektrische installaties voor woningen",
    "sg:phone":"+32 3 605 16 13",
    "sg:postcode":"2930",
    "sg:province":"Antwerpen",
    "wof:name":"Wim De Schutter",
    "wof:placetype":"venue"
},
  "geometry": {"coordinates":[4.4568161964,51.3008308411],"type":"Point"}
}