{
  "type": "Feature",
  "properties": {
    "iso:country":"BE",
    "sg:address":"Lolliestraat 6b39",
    "sg:city":"Moorslede",
    "sg:orig_category":"Herstellingen and onderhoud van auto's",
    "sg:phone":"+32 51 77 71 78",
    "sg:postcode":"8890",
    "sg:province":"West-Vlaanderen",
    "wof:name":"Occamat",
    "wof:placetype":"venue"
},
  "geometry": {"coordinates":[3.0734159946,50.9171142578],"type":"Point"}
}