{
  "type": "Feature",
  "properties": {
    "addr:full":"Ernest Claeslaan 7 Sint-niklaas (belsele) Oost-Vlaanderen 9111",
    "addr:housenumber":"7",
    "addr:postcode":"9111",
    "addr:street":"Ernest Claeslaan",
    "iso:country":"BE",
    "sg:address":"Ernest Claeslaan 7",
    "sg:city":"Sint-niklaas (belsele)",
    "sg:classifiers":[
        {
            "category":"Banks & Credit Unions",
            "subcategory":"Investment Brokerage",
            "type":"Services"
        }
    ],
    "sg:phone":"+32 3 777 09 08",
    "sg:postcode":"9111",
    "sg:province":"Oost-Vlaanderen",
    "sg:tags":[
        "repair",
        "-",
        "installation",
        "sanitary",
        "article"
    ],
    "wof:name":"John Bvba",
    "wof:placetype":"venue"
},
  "geometry": {"coordinates":[4.1224308014,51.1658096313],"type":"Point"}
}