{
  "type": "Feature",
  "properties": {
    "addr:full":"Rue P\u00c8re-heugens 32 Philippeville Namur 5600",
    "addr:housenumber":"32",
    "addr:postcode":"5600",
    "addr:street":"Rue Pe\u0300Re-Heugens",
    "iso:country":"BE",
    "sg:address":"Rue P\u00c8re-heugens 32",
    "sg:city":"Philippeville",
    "sg:orig_category":"Pain, p\u00e2tisseries and confiseries",
    "sg:phone":"+32 71 66 62 48",
    "sg:postcode":"5600",
    "sg:province":"Namur",
    "wof:name":"Frederic Godfriaux",
    "wof:placetype":"venue"
},
  "geometry": {"coordinates":[4.6077890396,50.191783905],"type":"Point"}
}