{
  "type": "Feature",
  "properties": {
    "addr:full":"Rue Des Wallons 25 Li\u00e8ge 1 Li\u00e8ge 4000",
    "addr:housenumber":"25;1",
    "addr:postcode":"4000",
    "addr:street":"Rue Des Wallons",
    "iso:country":"BE",
    "sg:address":"Rue Des Wallons 25",
    "sg:city":"Li\u00e8ge 1",
    "sg:classifiers":[
        {
            "category":"Professional",
            "subcategory":"Computer Services",
            "type":"Services"
        }
    ],
    "sg:phone":"+32 4 253 49 01",
    "sg:postcode":"4000",
    "sg:province":"Li\u00e8ge",
    "sg:tags":[
        "-",
        "processing",
        "data"
    ],
    "wof:name":"Dh Soft Soda & Co",
    "wof:placetype":"venue"
},
  "geometry": {"coordinates":[5.5594501495,50.6310844421],"type":"Point"}
}