{
  "type": "Feature",
  "properties": {
    "iso:country":"BE",
    "sg:address":"Rue Sainte-catherine 81",
    "sg:city":"Jodoigne",
    "sg:orig_category":"Salles de conf\u00e9rences and de r\u00e9ceptions",
    "sg:phone":"+32 10 81 17 87",
    "sg:postcode":"1370",
    "sg:province":"Brabant Wallon",
    "wof:name":"Ferme Des Glycines",
    "wof:placetype":"venue"
},
  "geometry": {"coordinates":[4.916806221,50.7078857422],"type":"Point"}
}