{
  "type": "Feature",
  "properties": {
    "iso:country":"BE",
    "sg:address":"Rue Aux Laines 20",
    "sg:city":"Bruxelles",
    "sg:classifiers":[
        {
            "category":"Arts & Performance",
            "subcategory":"Symphony",
            "type":"Entertainment"
        }
    ],
    "sg:phone":"+32 2 512 07 25",
    "sg:postcode":"1000",
    "sg:province":"Bruxelles-Capitale",
    "sg:tags":[
        "orchestra"
    ],
    "wof:name":"Jonge Filharmonie (de)",
    "wof:placetype":"venue"
},
  "geometry": {"coordinates":[4.3562598228,50.8384246826],"type":"Point"}
}