{
  "type": "Feature",
  "properties": {
    "iso:country":"BE",
    "sg:address":"Boulevard 12 \u00c8me De Liege 1",
    "sg:city":"Liege",
    "sg:orig_category":"Opticiens",
    "sg:phone":"+32 4 224 05 75",
    "sg:postcode":"4000",
    "sg:province":"Li\u00e8ge",
    "wof:name":"Optique Citadelle-labo",
    "wof:placetype":"venue"
},
  "geometry": {"coordinates":[5.5753188133,50.6516685486],"type":"Point"}
}