{
  "type": "Feature",
  "properties": {
    "addr:full":"Place Pr. Elisabeth 8 Brussel/bruxelles Bruxelles-Capitale 1030",
    "addr:housenumber":"8",
    "addr:postcode":"1030",
    "addr:street":"Place Pr. Elisabeth;/",
    "iso:country":"BE",
    "sg:address":"Place Pr. Elisabeth 8",
    "sg:city":"Brussel/bruxelles",
    "sg:orig_category":"Electrom\u00e9nager, t\u00e9l\u00e9visions and radios. Mat\u00e9riel de T\u00e9l\u00e9communication. Fabrication and montage de mo",
    "sg:phone":"+32 2 241 15 33",
    "sg:postcode":"1030",
    "sg:province":"Bruxelles-Capitale",
    "wof:name":"Electro-cash",
    "wof:placetype":"venue"
},
  "geometry": {"coordinates":[4.3749351501,50.8680000305],"type":"Point"}
}