{
  "type": "Feature",
  "properties": {
    "addr:full":"Diksmuidseweg 482a Ieper (boezinge) West-Vlaanderen 8904",
    "addr:housenumber":"482a",
    "addr:postcode":"8904",
    "iso:country":"BE",
    "sg:address":"Diksmuidseweg 482a",
    "sg:city":"Ieper (boezinge)",
    "sg:classifiers":[
        {
            "category":"Health Services",
            "subcategory":"Doctor",
            "type":"Services"
        }
    ],
    "sg:phone":"+32 57 42 28 87",
    "sg:postcode":"8904",
    "sg:province":"West-Vlaanderen",
    "sg:tags":[
        "medicinephysicians",
        "surgeon"
    ],
    "wof:name":"Bode J",
    "wof:placetype":"venue"
},
  "geometry": {"coordinates":[2.8521580696,50.8991928101],"type":"Point"}
}