{
  "type": "Feature",
  "properties": {
    "addr:full":"Nieuwstraat 32 Aalst Oost-Vlaanderen 9300",
    "addr:housenumber":"32",
    "addr:postcode":"9300",
    "addr:street":"Nieuwstraat",
    "iso:country":"BE",
    "sg:address":"Nieuwstraat 32",
    "sg:city":"Aalst",
    "sg:orig_category":"Baby- and kinderkleding Herenkledingzaken",
    "sg:phone":"+32 53 78 31 18",
    "sg:postcode":"9300",
    "sg:province":"Oost-Vlaanderen",
    "wof:name":"We Men",
    "wof:placetype":"venue"
},
  "geometry": {"coordinates":[4.035255909,50.9382247925],"type":"Point"}
}