{
  "type": "Feature",
  "properties": {
    "iso:country":"BE",
    "sg:address":"Blandenstraat 196",
    "sg:city":"Oud-heverlee",
    "sg:orig_category":"Beautyfarms, relaxatie and lichamelijk welzijn Schoonheidssalons",
    "sg:phone":"+32 16 40 53 53",
    "sg:postcode":"3053",
    "sg:province":"Vlaams-Brabant",
    "wof:name":"Instituur Annick",
    "wof:placetype":"venue"
},
  "geometry": {"coordinates":[4.7198328972,50.8306732178],"type":"Point"}
}