{
  "type": "Feature",
  "properties": {
    "addr:full":"Rijksweg 346 Maasmechelen Limburg 3630",
    "addr:housenumber":"346",
    "addr:postcode":"3630",
    "addr:street":"Rijksweg",
    "iso:country":"BE",
    "sg:address":"Rijksweg 346",
    "sg:city":"Maasmechelen",
    "sg:orig_category":"Catering and organisation de f\u00eates. Restaurants. Restaurants livraison \u00e0 domicile. Restaurants fast ",
    "sg:phone":"+32 89 77 31 18",
    "sg:postcode":"3630",
    "sg:province":"Limburg",
    "wof:name":"Manna",
    "wof:placetype":"venue"
},
  "geometry": {"coordinates":[5.6971421242,50.9688606262],"type":"Point"}
}