{
  "type": "Feature",
  "properties": {
    "addr:full":"Chauss\u00e9e De Mons 35 Soignies Hainaut 7060",
    "addr:housenumber":"35",
    "addr:postcode":"7060",
    "addr:street":"Chausse\u0301E De Mons",
    "iso:country":"BE",
    "sg:address":"Chauss\u00e9e De Mons 35",
    "sg:city":"Soignies",
    "sg:classifiers":[
        {
            "category":"Health Services",
            "subcategory":"Doctor",
            "type":"Services"
        }
    ],
    "sg:phone":"+32 67 33 59 74",
    "sg:postcode":"7060",
    "sg:province":"Hainaut",
    "sg:tags":[
        "medicinephysicians",
        "surgeon"
    ],
    "wof:name":"Dendal Thierry",
    "wof:placetype":"venue"
},
  "geometry": {"coordinates":[4.0659599304,50.5709609985],"type":"Point"}
}