{
  "type": "Feature",
  "properties": {
    "iso:country":"BE",
    "sg:address":"Hundelgemsesteenweg 486",
    "sg:city":"Merelbeke",
    "sg:classifiers":[
        {
            "category":"Insurance",
            "subcategory":"Life Insurance",
            "type":"Services"
        }
    ],
    "sg:phone":"+32 9 231 30 94",
    "sg:postcode":"9820",
    "sg:province":"Oost-Vlaanderen",
    "sg:tags":[
        "assurance"
    ],
    "wof:name":"Wauters & Co",
    "wof:placetype":"venue"
},
  "geometry": {"coordinates":[3.7512331009,51.0016975403],"type":"Point"}
}