{
  "type": "Feature",
  "properties": {
    "addr:full":"Nederstraat 38 Oudenaarde Oost-Vlaanderen 9700",
    "addr:housenumber":"38",
    "addr:postcode":"9700",
    "addr:street":"Nederstraat",
    "iso:country":"BE",
    "sg:address":"Nederstraat 38",
    "sg:city":"Oudenaarde",
    "sg:classifiers":[
        {
            "category":"Shopping",
            "subcategory":"Clothing, Apparel, & Fashions",
            "type":"Retail Goods"
        }
    ],
    "sg:phone":"+32 55 31 24 14",
    "sg:postcode":"9700",
    "sg:province":"Oost-Vlaanderen",
    "sg:tags":[
        "boutique"
    ],
    "wof:name":"Marinka",
    "wof:placetype":"venue"
},
  "geometry": {"coordinates":[3.6029539108,50.8449172974],"type":"Point"}
}