{
  "type": "Feature",
  "properties": {
    "iso:country":"BE",
    "sg:address":"Herrestraat 29",
    "sg:city":"Diest (molenstede)",
    "sg:orig_category":"Fa\u00e7ade covering",
    "sg:phone":"+32 13 31 15 26",
    "sg:postcode":"3294",
    "sg:province":"Vlaams-Brabant",
    "wof:name":"Splen Nv",
    "wof:placetype":"venue"
},
  "geometry": {"coordinates":[5.0133299828,51.0038795471],"type":"Point"}
}