{
  "type": "Feature",
  "properties": {
    "addr:full":"Tiensesteenweg 185 Leuven Vlaams-Brabant 3010",
    "addr:housenumber":"185",
    "addr:postcode":"3010",
    "addr:street":"Tiensesteenweg",
    "iso:country":"BE",
    "sg:address":"Tiensesteenweg 185",
    "sg:city":"Leuven",
    "sg:orig_category":"Secretariaatsdiensten",
    "sg:phone":"+32 16 35 65 68",
    "sg:postcode":"3010",
    "sg:province":"Vlaams-Brabant",
    "wof:name":"D.m. Desktop Publishing",
    "wof:placetype":"venue"
},
  "geometry": {"coordinates":[4.7332701683,50.8693008423],"type":"Point"}
}