{
  "type": "Feature",
  "properties": {
    "iso:country":"BE",
    "sg:address":"Rue De Herve 123",
    "sg:city":"Herve",
    "sg:orig_category":"Installatie van houten of kunststof schrijnwerk Tweedehandsgoederen",
    "sg:phone":"+32 87 67 43 71",
    "sg:postcode":"4651",
    "sg:province":"Li\u00e8ge",
    "wof:name":"Jean Englebert",
    "wof:placetype":"venue"
},
  "geometry": {"coordinates":[5.8058772087,50.6453208923],"type":"Point"}
}