{
  "type": "Feature",
  "properties": {
    "addr:full":"Rue De Hotton 41 Rendeux Luxembourg 6987",
    "addr:housenumber":"41",
    "addr:postcode":"6987",
    "addr:street":"Rue De Hotton",
    "iso:country":"BE",
    "sg:address":"Rue De Hotton 41",
    "sg:city":"Rendeux",
    "sg:orig_category":"Activit\u00e9s diverses d'imprimerie",
    "sg:phone":"+32 84 47 83 60",
    "sg:postcode":"6987",
    "sg:province":"Luxembourg",
    "wof:name":"Paul Burton",
    "wof:placetype":"venue"
},
  "geometry": {"coordinates":[5.5046601295,50.2384185791],"type":"Point"}
}