{
  "type": "Feature",
  "properties": {
    "addr:full":"Rue Des Bach\u00e8res 1 Tamines Namur 5060",
    "addr:housenumber":"1",
    "addr:postcode":"5060",
    "addr:street":"Rue Des Bache\u0300Res",
    "iso:country":"BE",
    "sg:address":"Rue Des Bach\u00e8res 1",
    "sg:city":"Tamines",
    "sg:classifiers":[
        {
            "category":"Professional",
            "subcategory":"Printing & Photocopies",
            "type":"Services"
        }
    ],
    "sg:phone":"+32 71 77 29 66",
    "sg:postcode":"5060",
    "sg:province":"Namur",
    "sg:tags":[
        "publishing"
    ],
    "wof:name":"Edition Du Hainault Sa",
    "wof:placetype":"venue"
},
  "geometry": {"coordinates":[4.6082401276,50.4334983826],"type":"Point"}
}