{
  "type": "Feature",
  "properties": {
    "addr:full":"Dorpsstraat 117 Knokke-heist West-Vlaanderen 8300",
    "addr:housenumber":"117",
    "addr:postcode":"8300",
    "addr:street":"Dorpsstraat",
    "iso:country":"BE",
    "sg:address":"Dorpsstraat 117",
    "sg:city":"Knokke-heist",
    "sg:orig_category":"M\u00e9decins and sp\u00e9cialistes",
    "sg:phone":"+32 50 60 65 65",
    "sg:postcode":"8300",
    "sg:province":"West-Vlaanderen",
    "wof:name":"Pierre Lambert",
    "wof:placetype":"venue"
},
  "geometry": {"coordinates":[3.287694931,51.3467254639],"type":"Point"}
}