{
  "type": "Feature",
  "properties": {
    "iso:country":"BE",
    "sg:address":"Dr. Van De Perrestraat 140a",
    "sg:city":"Geel",
    "sg:classifiers":[
        {
            "category":"Professional",
            "subcategory":"Testing Lab",
            "type":"Services"
        }
    ],
    "sg:phone":"+32 14 58 37 07",
    "sg:postcode":"2440",
    "sg:province":"Antwerpen",
    "sg:tags":[
        "chemist"
    ],
    "wof:name":"Van Hoof J",
    "wof:placetype":"venue"
},
  "geometry": {"coordinates":[4.9866862297,51.1742553711],"type":"Point"}
}