{
  "type": "Feature",
  "properties": {
    "addr:full":"Eenmeilaan 42 Leuven Vlaams-Brabant 3010",
    "addr:housenumber":"42",
    "addr:postcode":"3010",
    "addr:street":"Eenmeilaan",
    "iso:country":"BE",
    "sg:address":"Eenmeilaan 42",
    "sg:city":"Leuven",
    "sg:orig_category":"Agences immobili\u00e8res. Promoteurs immobiliers",
    "sg:phone":"+32 16 25 73 90",
    "sg:postcode":"3010",
    "sg:province":"Vlaams-Brabant",
    "wof:name":"Hageland-bouw",
    "wof:placetype":"venue"
},
  "geometry": {"coordinates":[4.7304501534,50.889755249],"type":"Point"}
}