{
  "type": "Feature",
  "properties": {
    "addr:full":"Fruitmarkt 3-5 Hasselt Limburg 3500",
    "addr:housenumber":"3-5",
    "addr:postcode":"3500",
    "addr:street":"Fruitmarkt",
    "iso:country":"BE",
    "sg:address":"Fruitmarkt 3-5",
    "sg:city":"Hasselt",
    "sg:classifiers":[
        {
            "category":"Shopping",
            "subcategory":"Clothing, Apparel, & Fashions",
            "type":"Retail Goods"
        }
    ],
    "sg:phone":"+32 11 22 63 09",
    "sg:postcode":"3500",
    "sg:province":"Limburg",
    "sg:tags":[
        "boutique"
    ],
    "wof:name":"Bobo Bvba",
    "wof:placetype":"venue"
},
  "geometry": {"coordinates":[5.3382501602,50.9300994873],"type":"Point"}
}