{
  "type": "Feature",
  "properties": {
    "iso:country":"BE",
    "sg:address":"Markt 7",
    "sg:city":"Torhout",
    "sg:orig_category":"V\u00eatements pour Dames. Jeux and jouets. Chaussures",
    "sg:phone":"+32 50 22 28 03",
    "sg:postcode":"8820",
    "sg:province":"West-Vlaanderen",
    "wof:name":"Plena Luna",
    "wof:placetype":"venue"
},
  "geometry": {"coordinates":[3.1012279987,51.0647468567],"type":"Point"}
}