{
  "type": "Feature",
  "properties": {
    "addr:full":"Bruggestraat 20 Wingene (zwevezele) West-Vlaanderen 8750",
    "addr:housenumber":"20",
    "addr:postcode":"8750",
    "addr:street":"Bruggestraat",
    "iso:country":"BE",
    "sg:address":"Bruggestraat 20",
    "sg:city":"Wingene (zwevezele)",
    "sg:classifiers":[
        {
            "category":"Bakery",
            "type":"Food & Drink"
        }
    ],
    "sg:phone":"+32 51 61 17 38",
    "sg:postcode":"8750",
    "sg:province":"West-Vlaanderen",
    "sg:tags":[
        "confectioner",
        "baker"
    ],
    "wof:name":"Vermeersch J",
    "wof:placetype":"venue"
},
  "geometry": {"coordinates":[3.2767078876,51.0584030151],"type":"Point"}
}