{
  "type": "Feature",
  "properties": {
    "addr:full":"Rue De Dochamps 14 Rendeux Luxembourg 6987",
    "addr:housenumber":"14",
    "addr:postcode":"6987",
    "addr:street":"Rue De Dochamps",
    "iso:country":"BE",
    "sg:address":"Rue De Dochamps 14",
    "sg:city":"Rendeux",
    "sg:orig_category":"Rundveehouders",
    "sg:phone":"+32 84 47 70 63",
    "sg:postcode":"6987",
    "sg:province":"Luxembourg",
    "wof:name":"Andree Carlier",
    "wof:placetype":"venue"
},
  "geometry": {"coordinates":[5.5543990135,50.2414665222],"type":"Point"}
}