{
  "type": "Feature",
  "properties": {
    "iso:country":"BE",
    "sg:address":"Boendaelsesteenweg 445",
    "sg:city":"Elsene/ixelles",
    "sg:classifiers":[
        {
            "category":"Restaurant",
            "type":"Food & Drink"
        }
    ],
    "sg:phone":"+32 2 640 71 91",
    "sg:postcode":"1050",
    "sg:province":"Bruxelles-Capitale",
    "wof:name":"Le Tavernier",
    "wof:placetype":"venue"
},
  "geometry": {"coordinates":[4.3888850212,50.8166656494],"type":"Point"}
}