{
  "type": "Feature",
  "properties": {
    "addr:full":"Rue Croix Vis\u00c9 9 Beyne-heusay Li\u00e8ge 4610",
    "addr:housenumber":"9",
    "addr:postcode":"4610",
    "addr:street":"Rue Croix Vise\u0301",
    "iso:country":"BE",
    "sg:address":"Rue Croix Vis\u00c9 9",
    "sg:city":"Beyne-heusay",
    "sg:orig_category":"Elektrische installaties voor woningen",
    "sg:phone":"+32 4 367 10 89",
    "sg:postcode":"4610",
    "sg:province":"Li\u00e8ge",
    "wof:name":"Electricite Star",
    "wof:placetype":"venue"
},
  "geometry": {"coordinates":[5.6550369263,50.6278495789],"type":"Point"}
}