{
  "type": "Feature",
  "properties": {
    "addr:full":"Stationsstraat 22c Duffel Antwerpen 2570",
    "addr:housenumber":"22c",
    "addr:postcode":"2570",
    "addr:street":"Stationsstraat",
    "iso:country":"BE",
    "sg:address":"Stationsstraat 22c",
    "sg:city":"Duffel",
    "sg:classifiers":[
        {
            "category":"Health Services",
            "subcategory":"Hospital",
            "type":"Services"
        }
    ],
    "sg:phone":"+32 15 30 30 60",
    "sg:postcode":"2570",
    "sg:province":"Antwerpen",
    "sg:tags":[
        "ambulance"
    ],
    "wof:name":"Emmaus",
    "wof:placetype":"venue"
},
  "geometry": {"coordinates":[4.4979262352,51.0918006897],"type":"Point"}
}