{
  "type": "Feature",
  "properties": {
    "addr:full":"Luxemburger Strasse 49 Sankt Vith Li\u00e8ge 4780",
    "addr:housenumber":"49",
    "addr:postcode":"4780",
    "addr:street":"Luxemburger Strasse",
    "iso:country":"BE",
    "sg:address":"Luxemburger Strasse 49",
    "sg:city":"Sankt Vith",
    "sg:classifiers":[
        {
            "category":"Bakery",
            "type":"Food & Drink"
        }
    ],
    "sg:phone":"+32 80 22 72 14",
    "sg:postcode":"4780",
    "sg:province":"Li\u00e8ge",
    "sg:tags":[
        "confectioner",
        "baker"
    ],
    "wof:name":"Huppertz M",
    "wof:placetype":"venue"
},
  "geometry": {"coordinates":[6.1215500832,50.2763290405],"type":"Point"}
}