{
  "type": "Feature",
  "properties": {
    "addr:full":"Tunnelweg 12 Niel Antwerpen 2845",
    "addr:housenumber":"12",
    "addr:postcode":"2845",
    "addr:street":"Tunnelweg",
    "iso:country":"BE",
    "sg:address":"Tunnelweg 12",
    "sg:city":"Niel",
    "sg:orig_category":"Metaalbehandeling and -bekleding",
    "sg:phone":"+32 3 844 73 43",
    "sg:postcode":"2845",
    "sg:province":"Antwerpen",
    "wof:name":"Ryngaert Bvba",
    "wof:placetype":"venue"
},
  "geometry": {"coordinates":[4.3491930962,51.100189209],"type":"Point"}
}