{
  "type": "Feature",
  "properties": {
    "iso:country":"BE",
    "sg:address":"Drapstraat 37",
    "sg:city":"Nazareth",
    "sg:classifiers":[
        {
            "category":"Shopping",
            "subcategory":"Shoes",
            "type":"Retail Goods"
        }
    ],
    "sg:phone":"+32 9 385 43 28",
    "sg:postcode":"9810",
    "sg:province":"Oost-Vlaanderen",
    "sg:tags":[
        "slipper",
        "-"
    ],
    "wof:name":"Crispina",
    "wof:placetype":"venue"
},
  "geometry": {"coordinates":[3.6032700539,50.9596862793],"type":"Point"}
}