{
  "type": "Feature",
  "properties": {
    "addr:full":"Rue De Campine 17 Li\u00c8ge Li\u00e8ge 4000",
    "addr:housenumber":"17",
    "addr:postcode":"4000",
    "addr:street":"Rue De Campine",
    "iso:country":"BE",
    "sg:address":"Rue De Campine 17",
    "sg:city":"Li\u00c8ge",
    "sg:orig_category":"Artsen and specialisten",
    "sg:phone":"+32 4 226 07 28",
    "sg:postcode":"4000",
    "sg:province":"Li\u00e8ge",
    "wof:name":"Philippe Chevalier",
    "wof:placetype":"venue"
},
  "geometry": {"coordinates":[5.5659489632,50.6480369568],"type":"Point"}
}