{
  "type": "Feature",
  "properties": {
    "addr:full":"Steenweg 221 Alken Limburg 3570",
    "addr:housenumber":"221",
    "addr:postcode":"3570",
    "addr:street":"Steenweg",
    "iso:country":"BE",
    "sg:address":"Steenweg 221",
    "sg:city":"Alken",
    "sg:orig_category":"Kapsalons",
    "sg:phone":"+32 495 63 11 59",
    "sg:postcode":"3570",
    "sg:province":"Limburg",
    "wof:name":"Katty Coiffure",
    "wof:placetype":"venue"
},
  "geometry": {"coordinates":[5.2779011726,50.8823852539],"type":"Point"}
}