{
  "type": "Feature",
  "properties": {
    "addr:full":"Coupure Rechts 162 Gent-centrum Oost-Vlaanderen 9000",
    "addr:housenumber":"162",
    "addr:postcode":"9000",
    "addr:street":"Coupure Rechts;Oost-Vlaanderen",
    "iso:country":"BE",
    "sg:address":"Coupure Rechts 162",
    "sg:city":"Gent-centrum",
    "sg:orig_category":"Advocaten and juridische adviseurs Balie van Gent",
    "sg:phone":"+32 9 265 95 95",
    "sg:postcode":"9000",
    "sg:province":"Oost-Vlaanderen",
    "wof:name":"Leaerts Jeroen",
    "wof:placetype":"venue"
},
  "geometry": {"coordinates":[3.7141768932,51.0482215881],"type":"Point"}
}