{
  "type": "Feature",
  "properties": {
    "iso:country":"BE",
    "sg:address":"Blauwstraat 82",
    "sg:city":"Boom",
    "sg:orig_category":"Pain, p\u00e2tisseries and confiseries",
    "sg:phone":"+32 3 888 07 53",
    "sg:postcode":"2850",
    "sg:province":"Antwerpen",
    "wof:name":"Pauls Bakkerij",
    "wof:placetype":"venue"
},
  "geometry": {"coordinates":[4.3690671921,51.0865402222],"type":"Point"}
}