{
  "type": "Feature",
  "properties": {
    "iso:country":"BE",
    "sg:address":"Vaartstraat 60",
    "sg:city":"Leuven",
    "sg:orig_category":"Avocats and conseillers juridiques",
    "sg:phone":"+32 16 31 01 31",
    "sg:postcode":"3000",
    "sg:province":"Vlaams-Brabant",
    "wof:name":"S. Stijns",
    "wof:placetype":"venue"
},
  "geometry": {"coordinates":[4.7011699677,50.8837738037],"type":"Point"}
}