{
  "type": "Feature",
  "properties": {
    "addr:full":"Groendijk 9 Blankenberge West-Vlaanderen 8370",
    "addr:housenumber":"9",
    "addr:postcode":"8370",
    "addr:street":"Groendijk",
    "iso:country":"BE",
    "sg:address":"Groendijk 9",
    "sg:city":"Blankenberge",
    "sg:orig_category":"Rundveehouders",
    "sg:phone":"+32 50 54 58 84",
    "sg:postcode":"8370",
    "sg:province":"West-Vlaanderen",
    "wof:name":"Marcel Huys",
    "wof:placetype":"venue"
},
  "geometry": {"coordinates":[3.1701879501,51.3132858276],"type":"Point"}
}