{
  "type": "Feature",
  "properties": {
    "addr:full":"Rosier 21-23 Antwerpen Antwerpen 2000",
    "addr:postcode":"21-23;2000",
    "addr:street":"Rosier",
    "iso:country":"BE",
    "sg:address":"Rosier 21-23",
    "sg:city":"Antwerpen",
    "sg:classifiers":[
        {
            "category":"Shopping",
            "subcategory":"Antiques",
            "type":"Retail Goods"
        }
    ],
    "sg:phone":"+32 3 225 01 08",
    "sg:postcode":"2000",
    "sg:province":"Antwerpen",
    "wof:name":"Binnenhuys ('t) Nv",
    "wof:placetype":"venue"
},
  "geometry": {"coordinates":[4.4029707909,51.2140846252],"type":"Point"}
}