{
  "type": "Feature",
  "properties": {
    "addr:full":"Broodstraat 32 Sint-niklaas Oost-Vlaanderen 9100",
    "addr:housenumber":"32",
    "addr:postcode":"9100",
    "addr:street":"Broodstraat",
    "iso:country":"BE",
    "sg:address":"Broodstraat 32",
    "sg:city":"Sint-niklaas",
    "sg:orig_category":"Boekhouders",
    "sg:phone":"+32 3 776 90 85",
    "sg:postcode":"9100",
    "sg:province":"Oost-Vlaanderen",
    "wof:name":"Sabine Strybol",
    "wof:placetype":"venue"
},
  "geometry": {"coordinates":[4.140130043,51.1698646545],"type":"Point"}
}