{
  "type": "Feature",
  "properties": {
    "addr:full":"Zwepe 2ba Maldegem Oost-Vlaanderen 9991",
    "addr:postcode":"9991",
    "addr:street":"Zwepe;Oost-Vlaanderen",
    "iso:country":"BE",
    "sg:address":"Zwepe 2ba",
    "sg:city":"Maldegem",
    "sg:classifiers":[
        {
            "category":"Building & Trades",
            "subcategory":"Construction",
            "type":"Services"
        }
    ],
    "sg:phone":"+32 9 377 75 85",
    "sg:postcode":"9991",
    "sg:province":"Oost-Vlaanderen",
    "sg:tags":[
        "la",
        "de",
        "\u00e9quipement",
        "pour",
        "machine",
        "location"
    ],
    "wof:name":"Almeco Steigers",
    "wof:placetype":"venue"
},
  "geometry": {"coordinates":[3.5134100914,51.1528244019],"type":"Point"}
}