{
  "type": "Feature",
  "properties": {
    "addr:full":"Rue Pierre Curie 107 Soumagne Li\u00e8ge 4630",
    "addr:housenumber":"107",
    "addr:postcode":"4630",
    "addr:street":"Rue Pierre Curie",
    "iso:country":"BE",
    "sg:address":"Rue Pierre Curie 107",
    "sg:city":"Soumagne",
    "sg:orig_category":"Gespecialiseerde residenti\u00eble bouw",
    "sg:phone":"+32 4 377 19 19",
    "sg:postcode":"4630",
    "sg:province":"Li\u00e8ge",
    "wof:name":"Christophe Krichel",
    "wof:placetype":"venue"
},
  "geometry": {"coordinates":[5.7509741783,50.6092262268],"type":"Point"}
}