{
  "type": "Feature",
  "properties": {
    "addr:full":"Rekkemstraat 84 Oudenaarde Oost-Vlaanderen 9700",
    "addr:housenumber":"84",
    "addr:postcode":"9700",
    "addr:street":"Rekkemstraat",
    "iso:country":"BE",
    "sg:address":"Rekkemstraat 84",
    "sg:city":"Oudenaarde",
    "sg:orig_category":"Kapsalons Schoonheidssalons",
    "sg:phone":"+32 55 31 59 29",
    "sg:postcode":"9700",
    "sg:province":"Oost-Vlaanderen",
    "wof:name":"Kapsalon Lydie",
    "wof:placetype":"venue"
},
  "geometry": {"coordinates":[3.6283380985,50.8442764282],"type":"Point"}
}