{
  "type": "Feature",
  "properties": {
    "iso:country":"BE",
    "sg:address":"Marktplein 27",
    "sg:city":"Sint-lievens-houtem",
    "sg:classifiers":[
        {
            "category":"Fast Food",
            "type":"Food & Drink"
        }
    ],
    "sg:phone":"+32 53 62 17 02",
    "sg:postcode":"9520",
    "sg:province":"Oost-Vlaanderen",
    "sg:tags":[
        "meeneem",
        "restaurant"
    ],
    "wof:name":"Frit-uurtje",
    "wof:placetype":"venue"
},
  "geometry": {"coordinates":[3.8570899963,50.9201545715],"type":"Point"}
}