{
  "type": "Feature",
  "properties": {
    "iso:country":"BE",
    "sg:address":"Rue De Nivelles 21",
    "sg:city":"Braine-le-chateau",
    "sg:classifiers":[
        {
            "category":"Restaurant",
            "type":"Food & Drink"
        }
    ],
    "sg:phone":"+32 2 366 91 21",
    "sg:postcode":"1440",
    "sg:province":"Brabant Wallon",
    "sg:tags":[
        "caf\u00e9s"
    ],
    "wof:name":"Taverne Jean & Lydia",
    "wof:placetype":"venue"
},
  "geometry": {"coordinates":[4.2733869553,50.6818580627],"type":"Point"}
}