{
  "type": "Feature",
  "properties": {
    "iso:country":"BE",
    "sg:address":"Avenue De La Basilique 87",
    "sg:city":"P\u00e9ruwelz (bon-secours)",
    "sg:classifiers":[
        {
            "category":"Social Services",
            "type":"Services"
        }
    ],
    "sg:phone":"+32 69 77 19 25",
    "sg:postcode":"7603",
    "sg:province":"Hainaut",
    "wof:name":"Maison Pour Enfants Le Moulin",
    "wof:placetype":"venue"
},
  "geometry": {"coordinates":[3.603053093,50.4998054504],"type":"Point"}
}