{
  "type": "Feature",
  "properties": {
    "addr:full":"Waalse Kaai 14 Antwerpen Antwerpen 2000",
    "addr:housenumber":"14",
    "addr:postcode":"2000",
    "addr:street":"Kaai",
    "iso:country":"BE",
    "sg:address":"Waalse Kaai 14",
    "sg:city":"Antwerpen",
    "sg:classifiers":[
        {
            "category":"Bars & Pubs",
            "type":"Food & Drink"
        }
    ],
    "sg:phone":"+32 3 248 20 42",
    "sg:postcode":"2000",
    "sg:province":"Antwerpen",
    "wof:name":"Zuiderpershuis Foyer",
    "wof:placetype":"venue"
},
  "geometry": {"coordinates":[4.3911280632,51.2116928101],"type":"Point"}
}