{
  "type": "Feature",
  "properties": {
    "addr:full":"Mispelaarstraat 9 Houthalen-helchteren Limburg 3530",
    "addr:housenumber":"9",
    "addr:postcode":"3530",
    "addr:street":"Mispelaarstraat",
    "iso:country":"BE",
    "sg:address":"Mispelaarstraat 9",
    "sg:city":"Houthalen-helchteren",
    "sg:orig_category":"Kapsalons",
    "sg:phone":"+32 89 84 13 27",
    "sg:postcode":"3530",
    "sg:province":"Limburg",
    "wof:name":"Haarmode",
    "wof:placetype":"venue"
},
  "geometry": {"coordinates":[5.4643259048,51.0288505554],"type":"Point"}
}