{
  "type": "Feature",
  "properties": {
    "addr:full":"Rue Cav\u00c9e 6 Antoing Hainaut 7643",
    "addr:housenumber":"6",
    "addr:postcode":"7643",
    "addr:street":"Rue Cave\u0301E",
    "iso:country":"BE",
    "sg:address":"Rue Cav\u00c9e 6",
    "sg:city":"Antoing",
    "sg:classifiers":[
        {
            "category":"Personal",
            "subcategory":"Beauty Salon",
            "type":"Services"
        }
    ],
    "sg:phone":"+32 69 44 20 76",
    "sg:postcode":"7643",
    "sg:province":"Hainaut",
    "sg:tags":[
        "de",
        "coiffure"
    ],
    "wof:name":"Coiffure Marie-lise",
    "wof:placetype":"venue"
},
  "geometry": {"coordinates":[3.4680020809,50.566608429],"type":"Point"}
}