{
  "type": "Feature",
  "properties": {
    "iso:country":"BE",
    "sg:address":"Ieperweg 73",
    "sg:city":"Roeselare",
    "sg:classifiers":[
        {
            "category":"Personal",
            "subcategory":"Beauty Salon",
            "type":"Services"
        }
    ],
    "sg:phone":"+32 51 20 66 90",
    "sg:postcode":"8800",
    "sg:province":"West-Vlaanderen",
    "sg:tags":[
        "de",
        "coiffure"
    ],
    "wof:name":"Coiffure Ginette",
    "wof:placetype":"venue"
},
  "geometry": {"coordinates":[3.1213319302,50.9007911682],"type":"Point"}
}