{
  "type": "Feature",
  "properties": {
    "iso:country":"BE",
    "sg:address":"Rue Du Baty 3",
    "sg:city":"Fleurus",
    "sg:classifiers":[
        {
            "category":"Arena",
            "subcategory":"Sports Club",
            "type":"Entertainment"
        }
    ],
    "sg:phone":"+32 71 81 91 20",
    "sg:postcode":"6224",
    "sg:province":"Hainaut",
    "sg:tags":[
        "de"
    ],
    "wof:name":"J.s. Baulet",
    "wof:placetype":"venue"
},
  "geometry": {"coordinates":[4.5805358887,50.4667053223],"type":"Point"}
}