{
  "type": "Feature",
  "properties": {
    "addr:full":"Blauwe-reigerlaan 3 Wingene West-Vlaanderen 8750",
    "addr:housenumber":"3",
    "addr:postcode":"8750",
    "addr:street":"Blauwe-Reigerlaan",
    "iso:country":"BE",
    "sg:address":"Blauwe-reigerlaan 3",
    "sg:city":"Wingene",
    "sg:orig_category":"Databeheer and gegevensverwerking Opinieonderzoekbureaus",
    "sg:phone":"+32 51 65 82 62",
    "sg:postcode":"8750",
    "sg:province":"West-Vlaanderen",
    "wof:name":"Thilco",
    "wof:placetype":"venue"
},
  "geometry": {"coordinates":[3.2698049545,51.0541648865],"type":"Point"}
}