{
  "type": "Feature",
  "properties": {
    "addr:full":"Bld Des Gerardchamps 0 Verviers Li\u00e8ge 4800",
    "addr:housenumber":"0",
    "addr:postcode":"4800",
    "addr:street":"Bld Des Gerardchamps",
    "iso:country":"BE",
    "sg:address":"Bld Des Gerardchamps 0",
    "sg:city":"Verviers",
    "sg:orig_category":"Baby- and kinderkleding Dameskledingzaken Herenkledingzaken",
    "sg:phone":"+32 87 31 26 78",
    "sg:postcode":"4800",
    "sg:province":"Li\u00e8ge",
    "wof:name":"Superconfex",
    "wof:placetype":"venue"
},
  "geometry": {"coordinates":[5.8493452072,50.5867996216],"type":"Point"}
}