{
  "type": "Feature",
  "properties": {
    "addr:full":"Nieuwstraat 37 Dilsen-stokkem Limburg 3650",
    "addr:housenumber":"37",
    "addr:postcode":"3650",
    "addr:street":"Nieuwstraat",
    "iso:country":"BE",
    "sg:address":"Nieuwstraat 37",
    "sg:city":"Dilsen-stokkem",
    "sg:classifiers":[
        {
            "category":"Fast Food",
            "type":"Food & Drink"
        }
    ],
    "sg:phone":"+32 89 75 23 75",
    "sg:postcode":"3650",
    "sg:province":"Limburg",
    "sg:tags":[
        "meeneem",
        "restaurant"
    ],
    "wof:name":"Frituur Het Pleintje",
    "wof:placetype":"venue"
},
  "geometry": {"coordinates":[5.7209329605,51.0137405396],"type":"Point"}
}