{
  "type": "Feature",
  "properties": {
    "iso:country":"BE",
    "sg:address":"Baksteenkaai 76",
    "sg:city":"Brussel/bruxelles",
    "sg:orig_category":"Dranken",
    "sg:phone":"+32 2 512 43 50",
    "sg:postcode":"1000",
    "sg:province":"Bruxelles-Capitale",
    "wof:name":"Nielsvins",
    "wof:placetype":"venue"
},
  "geometry": {"coordinates":[4.3467650414,50.8530235291],"type":"Point"}
}