{
  "type": "Feature",
  "properties": {
    "addr:full":"Terhulpsesteenweg 1 Hoeilaart Vlaams-Brabant 1560",
    "addr:housenumber":"1",
    "addr:postcode":"1560",
    "addr:street":"Terhulpsesteenweg",
    "iso:country":"BE",
    "sg:address":"Terhulpsesteenweg 1",
    "sg:city":"Hoeilaart",
    "sg:classifiers":[
        {
            "category":"Taxi",
            "type":"Transportation"
        }
    ],
    "sg:phone":"+32 2 657 44 09",
    "sg:postcode":"1560",
    "sg:province":"Vlaams-Brabant",
    "sg:tags":[
        "taxi's"
    ],
    "wof:name":"Hautin",
    "wof:placetype":"venue"
},
  "geometry": {"coordinates":[4.4485821724,50.7652130127],"type":"Point"}
}