{
  "type": "Feature",
  "properties": {
    "addr:full":"Rue Winston Churchill 4 Courcelles Hainaut 6180",
    "addr:housenumber":"4",
    "addr:postcode":"6180",
    "addr:street":"Rue Winston Churchill",
    "iso:country":"BE",
    "sg:address":"Rue Winston Churchill 4",
    "sg:city":"Courcelles",
    "sg:classifiers":[
        {
            "category":"Shopping",
            "subcategory":"Florist",
            "type":"Retail Goods"
        }
    ],
    "sg:phone":"+32 71 46 33 13",
    "sg:postcode":"6180",
    "sg:province":"Hainaut",
    "wof:name":"Arthur Fleurs",
    "wof:placetype":"venue"
},
  "geometry": {"coordinates":[4.3918800354,50.462890625],"type":"Point"}
}