{
  "type": "Feature",
  "properties": {
    "addr:full":"Ceulstraat 15 Begijnendijk Vlaams-Brabant 3130",
    "addr:housenumber":"15",
    "addr:postcode":"3130",
    "addr:street":"Ceulstraat",
    "iso:country":"BE",
    "sg:address":"Ceulstraat 15",
    "sg:city":"Begijnendijk",
    "sg:classifiers":[
        {
            "category":"Building & Trades",
            "subcategory":"Construction",
            "type":"Services"
        }
    ],
    "sg:phone":"+32 16 53 78 35",
    "sg:postcode":"3130",
    "sg:province":"Vlaams-Brabant",
    "sg:tags":[
        "ceiling"
    ],
    "wof:name":"Vermeulen R",
    "wof:placetype":"venue"
},
  "geometry": {"coordinates":[4.7643270493,51.0145149231],"type":"Point"}
}