{
  "type": "Feature",
  "properties": {
    "addr:full":"Rue De La Place 5 Binche Hainaut 7133",
    "addr:housenumber":"5",
    "addr:postcode":"7133",
    "addr:street":"Rue De La Place",
    "iso:country":"BE",
    "sg:address":"Rue De La Place 5",
    "sg:city":"Binche",
    "sg:orig_category":"Pharmaciens",
    "sg:phone":"+32 64 34 09 05",
    "sg:postcode":"7133",
    "sg:province":"Hainaut",
    "wof:name":"Monique Lardinois",
    "wof:placetype":"venue"
},
  "geometry": {"coordinates":[4.2089209557,50.3880348206],"type":"Point"}
}