{
  "type": "Feature",
  "properties": {
    "iso:country":"BE",
    "sg:address":"Rue Des Perdrix 44",
    "sg:city":"Mouscron",
    "sg:classifiers":[
        {
            "category":"Professional",
            "subcategory":"Accounting & Tax Preparation",
            "type":"Services"
        }
    ],
    "sg:phone":"+32 56 34 43 16",
    "sg:postcode":"7700",
    "sg:province":"Hainaut",
    "sg:tags":[
        "bookkeeper"
    ],
    "wof:name":"H.b. Organisation Sprl",
    "wof:placetype":"venue"
},
  "geometry": {"coordinates":[3.2191898823,50.756778717],"type":"Point"}
}