{
  "type": "Feature",
  "properties": {
    "addr:full":"Avenue Ren\u00c9 Comhaire 1b6 Sint-agatha-berchem/berchem-sainte-agathe Bruxelles-Capitale 1082",
    "addr:housenumber":"1b6 sint-agatha-berchem / berchem-sainte-agathe",
    "addr:postcode":"1082",
    "addr:street":"Avenue Rene\u0301 Comhaire",
    "iso:country":"BE",
    "sg:address":"Avenue Ren\u00c9 Comhaire 1b6",
    "sg:city":"Sint-agatha-berchem/berchem-sainte-agathe",
    "sg:classifiers":[
        {
            "category":"Personal",
            "subcategory":"Beauty Salon",
            "type":"Services"
        }
    ],
    "sg:phone":"+32 2 468 35 48",
    "sg:postcode":"1082",
    "sg:province":"Bruxelles-Capitale",
    "sg:tags":[
        "de",
        "coiffure"
    ],
    "wof:name":"Coiffure Michel",
    "wof:placetype":"venue"
},
  "geometry": {"coordinates":[4.2950100899,50.8604660034],"type":"Point"}
}