{
  "type": "Feature",
  "properties": {
    "addr:full":"Pand 240 Waregem West-Vlaanderen 8790",
    "addr:housenumber":"240",
    "addr:postcode":"8790",
    "addr:street":"Pand",
    "iso:country":"BE",
    "sg:address":"Pand 240",
    "sg:city":"Waregem",
    "sg:orig_category":"Imprimeries and copyshops",
    "sg:phone":"+32 56 60 50 43",
    "sg:postcode":"8790",
    "sg:province":"West-Vlaanderen",
    "wof:name":"Drukkerij Apple Print",
    "wof:placetype":"venue"
},
  "geometry": {"coordinates":[3.4313519001,50.886302948],"type":"Point"}
}