{
  "type": "Feature",
  "properties": {
    "iso:country":"BE",
    "sg:address":"Avenue De Laeken 43",
    "sg:city":"Jette",
    "sg:orig_category":"Architectes",
    "sg:phone":"+32 2 428 53 37",
    "sg:postcode":"1090",
    "sg:province":"Bruxelles-Capitale",
    "wof:name":"Frank Kerkhofs",
    "wof:placetype":"venue"
},
  "geometry": {"coordinates":[4.3226828575,50.870891571],"type":"Point"}
}