{
  "type": "Feature",
  "properties": {
    "iso:country":"BE",
    "sg:address":"Rabotstraat 54",
    "sg:city":"Gent",
    "sg:orig_category":"Explosifs Fab",
    "sg:phone":"+32 9 233 10 44",
    "sg:postcode":"9000",
    "sg:province":"Oost-Vlaanderen",
    "wof:name":"Universal Firework",
    "wof:placetype":"venue"
},
  "geometry": {"coordinates":[3.7140979767,51.0585021973],"type":"Point"}
}