{
  "type": "Feature",
  "properties": {
    "addr:full":"Rue Tumelaire 99 Charleroi Hainaut 6000",
    "addr:housenumber":"99",
    "addr:postcode":"6000",
    "addr:street":"Rue Tumelaire;Hainaut",
    "iso:country":"BE",
    "sg:address":"Rue Tumelaire 99",
    "sg:city":"Charleroi",
    "sg:classifiers":[
        {
            "category":"Insurance",
            "subcategory":"Life Insurance",
            "type":"Services"
        }
    ],
    "sg:phone":"+32 71 20 71 10",
    "sg:postcode":"6000",
    "sg:province":"Hainaut",
    "sg:tags":[
        "assurance"
    ],
    "wof:name":"Dvp",
    "wof:placetype":"venue"
},
  "geometry": {"coordinates":[4.4521098137,50.4090805054],"type":"Point"}
}