{
  "type": "Feature",
  "properties": {
    "addr:full":"Excelsiorlaan 5 Zaventem Vlaams-Brabant 1930",
    "addr:housenumber":"5",
    "addr:postcode":"1930",
    "addr:street":"Excelsiorlaan",
    "iso:country":"BE",
    "sg:address":"Excelsiorlaan 5",
    "sg:city":"Zaventem",
    "sg:classifiers":[
        {
            "category":"Professional",
            "subcategory":"Engineering",
            "type":"Services"
        }
    ],
    "sg:phone":"+32 2 719 90 20",
    "sg:postcode":"1930",
    "sg:province":"Vlaams-Brabant",
    "sg:tags":[
        "-"
    ],
    "wof:name":"Inttos",
    "wof:placetype":"venue"
},
  "geometry": {"coordinates":[4.4566979408,50.8813362122],"type":"Point"}
}