{
  "type": "Feature",
  "properties": {
    "addr:full":"Boulevard Du Tivoli 37 Box 1 La Louvi\u00e8re Hainaut 7100",
    "addr:housenumber":"37;1",
    "addr:postcode":"7100",
    "addr:street":"Boulevard Du Tivoli;Box",
    "iso:country":"BE",
    "sg:address":"Boulevard Du Tivoli 37 Box 1",
    "sg:city":"La Louvi\u00e8re",
    "sg:classifiers":[
        {
            "category":"Professional",
            "subcategory":"Accounting & Tax Preparation",
            "type":"Services"
        }
    ],
    "sg:phone":"+32 64 28 38 55",
    "sg:postcode":"7100",
    "sg:province":"Hainaut",
    "sg:tags":[
        "bookkeeper"
    ],
    "wof:name":"Cabinet Comptable Et Fiscal A Malbecq Sprl",
    "wof:placetype":"venue"
},
  "geometry": {"coordinates":[4.1987857819,50.4776115417],"type":"Point"}
}