{
  "type": "Feature",
  "properties": {
    "iso:country":"BE",
    "sg:address":"Kortrijksestraat 56",
    "sg:city":"Moorslede",
    "sg:orig_category":"Rundveehouders",
    "sg:phone":"+32 56 50 16 85",
    "sg:postcode":"8890",
    "sg:province":"West-Vlaanderen",
    "wof:name":"Marc Ghesquiere",
    "wof:placetype":"venue"
},
  "geometry": {"coordinates":[3.120445013,50.8495521545],"type":"Point"}
}