{
  "type": "Feature",
  "properties": {
    "iso:country":"BE",
    "sg:address":"Statiestraat 56",
    "sg:city":"Antwerpen (berchem)",
    "sg:classifiers":[
        {
            "category":"Sports & Exercise",
            "subcategory":"Gym",
            "type":"Entertainment"
        }
    ],
    "sg:phone":"+32 3 457 24 00",
    "sg:postcode":"2600",
    "sg:province":"Antwerpen",
    "sg:tags":[
        "access",
        "gymnastics",
        "-",
        "apparatus",
        "fitness"
    ],
    "wof:name":"Concept 2",
    "wof:placetype":"venue"
},
  "geometry": {"coordinates":[4.4197869301,51.217956543],"type":"Point"}
}