{
  "type": "Feature",
  "properties": {
    "addr:full":"Roeselaarsestraat 203 Izegem West-Vlaanderen 8870",
    "addr:housenumber":"203",
    "addr:postcode":"8870",
    "addr:street":"Roeselaarsestraat",
    "iso:country":"BE",
    "sg:address":"Roeselaarsestraat 203",
    "sg:city":"Izegem",
    "sg:orig_category":"Maatkleding Fab",
    "sg:phone":"+32 51 30 31 46",
    "sg:postcode":"8870",
    "sg:province":"West-Vlaanderen",
    "wof:name":"Nadia Rondelez",
    "wof:placetype":"venue"
},
  "geometry": {"coordinates":[3.202673912,50.9208183289],"type":"Point"}
}