{
  "type": "Feature",
  "properties": {
    "addr:full":"Avenue Bouvier 2a Virton Luxembourg 6760",
    "addr:housenumber":"2a",
    "addr:postcode":"6760",
    "addr:street":"Avenue Bouvier",
    "iso:country":"BE",
    "sg:address":"Avenue Bouvier 2a",
    "sg:city":"Virton",
    "sg:orig_category":"Banken and kredietinstellingen",
    "sg:phone":"+32 63 58 89 90",
    "sg:postcode":"6760",
    "sg:province":"Luxembourg",
    "wof:name":"Dexia",
    "wof:placetype":"venue"
},
  "geometry": {"coordinates":[5.530834198,49.5673103333],"type":"Point"}
}