{
  "type": "Feature",
  "properties": {
    "addr:full":"Rue Cachine 36 Villers-le-bouillet Li\u00e8ge 4530",
    "addr:housenumber":"36",
    "addr:postcode":"4530",
    "addr:street":"Rue Cachine",
    "iso:country":"BE",
    "sg:address":"Rue Cachine 36",
    "sg:city":"Villers-le-bouillet",
    "sg:classifiers":[
        {
            "category":"Personal",
            "subcategory":"Nail Salon",
            "type":"Services"
        }
    ],
    "sg:phone":"+32 85 23 45 42",
    "sg:postcode":"4530",
    "sg:province":"Li\u00e8ge",
    "sg:tags":[
        "pedicure"
    ],
    "wof:name":"Carol M",
    "wof:placetype":"venue"
},
  "geometry": {"coordinates":[5.257545948,50.5683059692],"type":"Point"}
}