{
  "type": "Feature",
  "properties": {
    "addr:full":"Nieuwpoortsesteenweg 132 Oostende West-Vlaanderen 8400",
    "addr:housenumber":"132",
    "addr:postcode":"8400",
    "addr:street":"Nieuwpoortsesteenweg",
    "iso:country":"BE",
    "sg:address":"Nieuwpoortsesteenweg 132",
    "sg:city":"Oostende",
    "sg:classifiers":[
        {
            "category":"Bars & Pubs",
            "type":"Food & Drink"
        }
    ],
    "sg:phone":"+32 59 51 11 96",
    "sg:postcode":"8400",
    "sg:province":"West-Vlaanderen",
    "wof:name":"De Zoeten Inval",
    "wof:placetype":"venue"
},
  "geometry": {"coordinates":[2.9033210278,51.2219314575],"type":"Point"}
}