{
  "type": "Feature",
  "properties": {
    "iso:country":"BE",
    "sg:address":"Zandweg Naar Zerkegem 14",
    "sg:city":"Jabbeke (snellegem)",
    "sg:classifiers":[
        {
            "category":"Building & Trades",
            "subcategory":"Pest Control",
            "type":"Services"
        }
    ],
    "sg:phone":"+32 50 81 60 07",
    "sg:postcode":"8490",
    "sg:province":"West-Vlaanderen",
    "sg:tags":[
        "painting",
        "contractor"
    ],
    "wof:name":"Decoteam Cvba",
    "wof:placetype":"venue"
},
  "geometry": {"coordinates":[3.0856831074,51.178352356],"type":"Point"}
}