{
  "type": "Feature",
  "properties": {
    "iso:country":"BE",
    "sg:address":"Bergensesteenweg 574",
    "sg:city":"Halle",
    "sg:orig_category":"Huishoudapparaten, televisies and radio's Loodgieterij, verwarming and sanitaire installaties",
    "sg:phone":"+32 2 356 60 26",
    "sg:postcode":"1502",
    "sg:province":"Vlaams-Brabant",
    "wof:name":"Denayer L",
    "wof:placetype":"venue"
},
  "geometry": {"coordinates":[4.221241951,50.7165908813],"type":"Point"}
}