{
  "type": "Feature",
  "properties": {
    "addr:full":"Nadorst 50 Oud-turnhout Antwerpen 2360",
    "addr:housenumber":"50",
    "addr:postcode":"2360",
    "addr:street":"Nadorst",
    "iso:country":"BE",
    "sg:address":"Nadorst 50",
    "sg:city":"Oud-turnhout",
    "sg:classifiers":[
        {
            "category":"Home & Garden",
            "subcategory":"Furniture",
            "type":"Retail Goods"
        }
    ],
    "sg:phone":"+32 14 45 31 15",
    "sg:postcode":"2360",
    "sg:province":"Antwerpen",
    "sg:tags":[
        "fab",
        "meubelen",
        "diverse"
    ],
    "wof:name":"Design Meubelen G. & G.",
    "wof:placetype":"venue"
},
  "geometry": {"coordinates":[4.9755239487,51.3214683533],"type":"Point"}
}