{
  "type": "Feature",
  "properties": {
    "iso:country":"BE",
    "sg:address":"Industriepark E 17/2",
    "sg:city":"Lokeren",
    "sg:orig_category":"Software For Repair Accounting",
    "sg:phone":"+32 9 349 37 60",
    "sg:postcode":"9160",
    "sg:province":"Oost-Vlaanderen",
    "wof:name":"Vds-computing Nv",
    "wof:placetype":"venue"
},
  "geometry": {"coordinates":[3.9864850044,51.1047401428],"type":"Point"}
}