{
  "type": "Feature",
  "properties": {
    "iso:country":"BE",
    "sg:address":"Rue Saint-nicolas 32",
    "sg:city":"Messancy",
    "sg:classifiers":[
        {
            "category":"Wholesale",
            "subcategory":"Farm Supplies",
            "type":"Manufacturing & Wholesale Goods"
        }
    ],
    "sg:phone":"+32 63 22 41 26",
    "sg:postcode":"6780",
    "sg:province":"Luxembourg",
    "sg:tags":[
        "machine",
        "agricoles",
        "mat\u00e9riel",
        "gr"
    ],
    "wof:name":"Michel Molitor",
    "wof:placetype":"venue"
},
  "geometry": {"coordinates":[5.8361477852,49.6368026733],"type":"Point"}
}