{
  "type": "Feature",
  "properties": {
    "iso:country":"BE",
    "sg:address":"Rue De L'alliance 61",
    "sg:city":"La Louvi\u00e8re (haine-saint-pierre)",
    "sg:classifiers":[
        {
            "category":"Health Services",
            "subcategory":"Doctor",
            "type":"Services"
        }
    ],
    "sg:phone":"+32 64 44 80 33",
    "sg:postcode":"7100",
    "sg:province":"Hainaut",
    "sg:tags":[
        "medicinephysicians",
        "surgeon"
    ],
    "wof:name":"Lechien Ph",
    "wof:placetype":"venue"
},
  "geometry": {"coordinates":[4.2147631645,50.4644012451],"type":"Point"}
}