{
  "type": "Feature",
  "properties": {
    "iso:country":"BE",
    "sg:address":"Ch No\u00ebl Ledouble 80",
    "sg:city":"Awans",
    "sg:classifiers":[
        {
            "category":"Government",
            "subcategory":"Department Of Motor Vehicles",
            "type":"Public Place"
        }
    ],
    "sg:phone":"+32 4 257 54 63",
    "sg:postcode":"4340",
    "sg:province":"Li\u00e8ge",
    "sg:tags":[
        "equipment",
        "industrial",
        "transport",
        "motor-cars"
    ],
    "wof:name":"Carrosserie Verhelle-rubias Sprl",
    "wof:placetype":"venue"
},
  "geometry": {"coordinates":[5.4373760223,50.6935043335],"type":"Point"}
}