{
  "type": "Feature",
  "properties": {
    "addr:full":"Meir 80-82 Antwerpen-centrum Antwerpen 2000",
    "addr:housenumber":"80-82",
    "addr:postcode":"2000",
    "addr:street":"Meir",
    "iso:country":"BE",
    "sg:address":"Meir 80-82",
    "sg:city":"Antwerpen-centrum",
    "sg:orig_category":"Opticiens Pearle Opticiens",
    "sg:phone":"+32 3 233 19 01",
    "sg:postcode":"2000",
    "sg:province":"Antwerpen",
    "wof:name":"Pearle Opticiens",
    "wof:placetype":"venue"
},
  "geometry": {"coordinates":[4.4118318558,51.2180023193],"type":"Point"}
}