{
  "type": "Feature",
  "properties": {
    "addr:full":"Mechelsebaan 27 Keerbergen Vlaams-Brabant 3140",
    "addr:housenumber":"27",
    "addr:postcode":"3140",
    "addr:street":"Mechelsebaan",
    "iso:country":"BE",
    "sg:address":"Mechelsebaan 27",
    "sg:city":"Keerbergen",
    "sg:classifiers":[
        {
            "category":"Health Services",
            "subcategory":"Health Practitioner",
            "type":"Services"
        }
    ],
    "sg:phone":"+32 15 52 83 66",
    "sg:postcode":"3140",
    "sg:province":"Vlaams-Brabant",
    "sg:tags":[
        "physiotherapist"
    ],
    "wof:name":"Rix Peggy",
    "wof:placetype":"venue"
},
  "geometry": {"coordinates":[4.626636982,51.004108429],"type":"Point"}
}