{
  "type": "Feature",
  "properties": {
    "iso:country":"BE",
    "sg:address":"Tentrappenstraat 41",
    "sg:city":"Hoeilaart",
    "sg:orig_category":"Services de Nettoyage and de D\u00e9sinfection. Plomberie, chauffage and installations sanitaires",
    "sg:phone":"+32 2 657 52 36",
    "sg:postcode":"1560",
    "sg:province":"Vlaams-Brabant",
    "wof:name":"Centrale Verwarming Huyberechts",
    "wof:placetype":"venue"
},
  "geometry": {"coordinates":[4.4972000122,50.7628593445],"type":"Point"}
}