{
  "type": "Feature",
  "properties": {
    "iso:country":"BE",
    "sg:address":"Van Kerckhovenstraat 61",
    "sg:city":"Antwerpen",
    "sg:classifiers":[
        {
            "category":"Bakery",
            "type":"Food & Drink"
        }
    ],
    "sg:phone":"+32 3 232 80 75",
    "sg:postcode":"2060",
    "sg:province":"Antwerpen",
    "sg:tags":[
        "confectioner",
        "baker"
    ],
    "wof:name":"Boerjan G",
    "wof:placetype":"venue"
},
  "geometry": {"coordinates":[4.4251818657,51.2261009216],"type":"Point"}
}