{
  "type": "Feature",
  "properties": {
    "iso:country":"BE",
    "sg:address":"Engelstraat 77",
    "sg:city":"Gent",
    "sg:orig_category":"Schoonmaakbedrijven and ongediertebestrijding",
    "sg:phone":"+32 9 228 54 46",
    "sg:postcode":"9040",
    "sg:province":"Oost-Vlaanderen",
    "wof:name":"Deventer",
    "wof:placetype":"venue"
},
  "geometry": {"coordinates":[3.7507328987,51.0550498962],"type":"Point"}
}