{
  "type": "Feature",
  "properties": {
    "iso:country":"BE",
    "sg:address":"Hertenstraat 11bb",
    "sg:city":"Wellen",
    "sg:orig_category":"Fruitteelt",
    "sg:phone":"+32 12 74 13 23",
    "sg:postcode":"3831",
    "sg:province":"Limburg",
    "wof:name":"Christophe Billen",
    "wof:placetype":"venue"
},
  "geometry": {"coordinates":[5.3349080086,50.8340454102],"type":"Point"}
}