{
  "type": "Feature",
  "properties": {
    "addr:full":"Rue Des Bouchers 66a Bruxelles Bruxelles-Capitale 1000",
    "addr:housenumber":"66a",
    "addr:postcode":"1000",
    "addr:street":"Rue Des Bouchers",
    "iso:country":"BE",
    "sg:address":"Rue Des Bouchers 66a",
    "sg:city":"Bruxelles",
    "sg:classifiers":[
        {
            "category":"Personal",
            "subcategory":"Nail Salon",
            "type":"Services"
        }
    ],
    "sg:phone":"+32 2 514 07 39",
    "sg:postcode":"1000",
    "sg:province":"Bruxelles-Capitale",
    "sg:tags":[
        "pedicure"
    ],
    "wof:name":"Tchou Maurice",
    "wof:placetype":"venue"
},
  "geometry": {"coordinates":[4.355984211,50.8474121094],"type":"Point"}
}