{
  "type": "Feature",
  "properties": {
    "addr:full":"Mechelsesteenweg 176 Kontich Antwerpen 2550",
    "addr:housenumber":"176",
    "addr:postcode":"2550",
    "addr:street":"Mechelsesteenweg",
    "iso:country":"BE",
    "sg:address":"Mechelsesteenweg 176",
    "sg:city":"Kontich",
    "sg:classifiers":[
        {
            "category":"Real Estate",
            "subcategory":"Architect",
            "type":"Services"
        }
    ],
    "sg:phone":"+32 3 457 76 08",
    "sg:postcode":"2550",
    "sg:province":"Antwerpen",
    "wof:name":"De Corte L",
    "wof:placetype":"venue"
},
  "geometry": {"coordinates":[4.4628500938,51.1470909119],"type":"Point"}
}