{
  "type": "Feature",
  "properties": {
    "addr:full":"H\u00c9domont 1 Malmedy Li\u00e8ge 4960",
    "addr:housenumber":"1",
    "addr:postcode":"4960",
    "addr:street":"He\u0301Domont",
    "iso:country":"BE",
    "sg:address":"H\u00c9domont 1",
    "sg:city":"Malmedy",
    "sg:orig_category":"Enseignement maternel and primaire",
    "sg:phone":"+32 80 33 93 02",
    "sg:postcode":"4960",
    "sg:province":"Li\u00e8ge",
    "wof:name":"Ecole Prim. Communale",
    "wof:placetype":"venue"
},
  "geometry": {"coordinates":[6.038315773,50.4060745239],"type":"Point"}
}