{
  "type": "Feature",
  "properties": {
    "iso:country":"BE",
    "sg:address":"Rue Des Tr\u00e8fles 11",
    "sg:city":"Bruxelles (anderlecht)",
    "sg:classifiers":[
        {
            "category":"Wholesale",
            "subcategory":"Scrap",
            "type":"Manufacturing & Wholesale Goods"
        }
    ],
    "sg:phone":"+32 2 521 74 12",
    "sg:postcode":"1070",
    "sg:province":"Bruxelles-Capitale",
    "sg:tags":[
        "metal"
    ],
    "wof:name":"Roobaert E Anc Ets Peeters J",
    "wof:placetype":"venue"
},
  "geometry": {"coordinates":[4.291741848,50.8192939758],"type":"Point"}
}