{
  "type": "Feature",
  "properties": {
    "iso:country":"BE",
    "sg:address":"Markt 6",
    "sg:city":"De Panne",
    "sg:classifiers":[
        {
            "category":"Travel",
            "subcategory":"Hotels & Motels",
            "type":"Entertainment"
        }
    ],
    "sg:phone":"+32 58 41 10 53",
    "sg:postcode":"8660",
    "sg:province":"West-Vlaanderen",
    "sg:tags":[
        "restaurant"
    ],
    "wof:name":"Hotel Vivaldi",
    "wof:placetype":"venue"
},
  "geometry": {"coordinates":[2.5925590992,51.0983848572],"type":"Point"}
}