{
  "type": "Feature",
  "properties": {
    "addr:full":"Burrelstraat 5b Sint-niklaas Oost-Vlaanderen 9100",
    "addr:housenumber":"5b",
    "addr:postcode":"9100",
    "addr:street":"Burrelstraat",
    "iso:country":"BE",
    "sg:address":"Burrelstraat 5b",
    "sg:city":"Sint-niklaas",
    "sg:orig_category":"Non-Classified Establishments",
    "sg:phone":"+32 3 776 62 71",
    "sg:postcode":"9100",
    "sg:province":"Oost-Vlaanderen",
    "wof:name":"Contrast",
    "wof:placetype":"venue"
},
  "geometry": {"coordinates":[4.1411790848,51.144744873],"type":"Point"}
}