{
  "type": "Feature",
  "properties": {
    "addr:full":"Oudenaardsesteenweg 193 Deinze Oost-Vlaanderen 9800",
    "addr:housenumber":"193",
    "addr:postcode":"9800",
    "addr:street":"Oudenaardsesteenweg",
    "iso:country":"BE",
    "sg:address":"Oudenaardsesteenweg 193",
    "sg:city":"Deinze",
    "sg:orig_category":"Installation \u00e9lectrique r\u00e9sidentielle",
    "sg:phone":"+32 9 386 42 93",
    "sg:postcode":"9800",
    "sg:province":"Oost-Vlaanderen",
    "wof:name":"Depoortere Johan",
    "wof:placetype":"venue"
},
  "geometry": {"coordinates":[3.530174017,50.9863166809],"type":"Point"}
}