{
  "type": "Feature",
  "properties": {
    "iso:country":"BE",
    "sg:address":"Rue Des Meuniers 35",
    "sg:city":"Beloeil",
    "sg:orig_category":"Baby- and kinderkleding Kleding",
    "sg:phone":"+32 69 57 62 67",
    "sg:postcode":"7973",
    "sg:province":"Hainaut",
    "wof:name":"Derby Loisirs",
    "wof:placetype":"venue"
},
  "geometry": {"coordinates":[3.7188699245,50.5087738037],"type":"Point"}
}