{
  "type": "Feature",
  "properties": {
    "iso:country":"BE",
    "sg:address":"Hoeledensebaan 170",
    "sg:city":"Kortenaken (hoeleden)",
    "sg:classifiers":[
        {
            "category":"Utilities",
            "subcategory":"Fuel Oil & Lpg",
            "type":"Services"
        }
    ],
    "sg:phone":"+32 16 77 71 30",
    "sg:postcode":"3471",
    "sg:province":"Vlaams-Brabant",
    "sg:tags":[
        "product"
    ],
    "wof:name":"Hognoul & Zn Bvba",
    "wof:placetype":"venue"
},
  "geometry": {"coordinates":[4.9983401299,50.8740501404],"type":"Point"}
}