{
  "type": "Feature",
  "properties": {
    "addr:full":"Boulevard Louis Hillier 1 Li\u00e8ge 1 Li\u00e8ge 4000",
    "addr:housenumber":"1;1",
    "addr:postcode":"4000",
    "addr:street":"Boulevard Louis Hillier",
    "iso:country":"BE",
    "sg:address":"Boulevard Louis Hillier 1",
    "sg:city":"Li\u00e8ge 1",
    "sg:classifiers":[
        {
            "category":"Home & Garden",
            "subcategory":"Furniture",
            "type":"Retail Goods"
        }
    ],
    "sg:phone":"+32 4 223 25 48",
    "sg:postcode":"4000",
    "sg:province":"Li\u00e8ge",
    "sg:tags":[
        "bamboo",
        "cane",
        "wickerwork"
    ],
    "wof:name":"La Lumiere (entreprise De Travail Adapt\u00e9)",
    "wof:placetype":"venue"
},
  "geometry": {"coordinates":[5.5480070114,50.6310806274],"type":"Point"}
}