{
  "type": "Feature",
  "properties": {
    "addr:full":"Avenue Saint-pie X 5 Ottignies-louvain-la-neuve Brabant Wallon 1340",
    "addr:postcode":"1340",
    "addr:street":"Avenue;Ottignies-Louvain-La-Neuve Brabant",
    "iso:country":"BE",
    "sg:address":"Avenue Saint-pie X 5",
    "sg:city":"Ottignies-louvain-la-neuve",
    "sg:orig_category":"Enseignement maternel and primaire",
    "sg:phone":"+32 10 41 45 98",
    "sg:postcode":"1340",
    "sg:province":"Brabant Wallon",
    "wof:name":"Ecole Fondamentale Libre",
    "wof:placetype":"venue"
},
  "geometry": {"coordinates":[4.5543551445,50.6740531921],"type":"Point"}
}