{
  "type": "Feature",
  "properties": {
    "iso:country":"BE",
    "sg:address":"Quai De L'ourthe 13",
    "sg:city":"Li\u00e8ge 1 (li\u00e8ge 2)",
    "sg:classifiers":[
        {
            "category":"Real Estate",
            "subcategory":"Architect",
            "type":"Services"
        }
    ],
    "sg:phone":"+32 4 341 27 51",
    "sg:postcode":"4020",
    "sg:province":"Li\u00e8ge",
    "wof:name":"Deberg Y",
    "wof:placetype":"venue"
},
  "geometry": {"coordinates":[5.5847458839,50.6376419067],"type":"Point"}
}