{
  "type": "Feature",
  "properties": {
    "iso:country":"BE",
    "sg:address":"Raerener Strasse 22",
    "sg:city":"Raeren (eynatten)",
    "sg:classifiers":[
        {
            "category":"Food & Beverages",
            "subcategory":"Supermarket",
            "type":"Retail Goods"
        }
    ],
    "sg:phone":"+32 87 86 63 77",
    "sg:postcode":"4731",
    "sg:province":"Li\u00e8ge",
    "sg:tags":[
        "department",
        "store"
    ],
    "wof:name":"Mipri Ii Grenzmarkt",
    "wof:placetype":"venue"
},
  "geometry": {"coordinates":[6.0816879272,50.6914367676],"type":"Point"}
}