{
  "type": "Feature",
  "properties": {
    "addr:full":"Dorpstraat 29 Ichtegem West-Vlaanderen 8480",
    "addr:housenumber":"29",
    "addr:postcode":"8480",
    "addr:street":"Dorpstraat",
    "iso:country":"BE",
    "sg:address":"Dorpstraat 29",
    "sg:city":"Ichtegem",
    "sg:orig_category":"Quincailleries",
    "sg:phone":"+32 50 81 37 54",
    "sg:postcode":"8480",
    "sg:province":"West-Vlaanderen",
    "wof:name":"Huis Christine",
    "wof:placetype":"venue"
},
  "geometry": {"coordinates":[3.0502030849,51.1589393616],"type":"Point"}
}