{
  "type": "Feature",
  "properties": {
    "iso:country":"BE",
    "sg:address":"Chauss\u00c9e De Nivelles 107",
    "sg:city":"Manage",
    "sg:classifiers":[
        {
            "category":"Personal",
            "subcategory":"Beauty Salon",
            "type":"Services"
        }
    ],
    "sg:postcode":"7170",
    "sg:province":"Hainaut",
    "sg:tags":[
        "de",
        "coiffure"
    ],
    "wof:name":"Mireille Chiera",
    "wof:placetype":"venue"
},
  "geometry": {"coordinates":[4.2432899475,50.5115013123],"type":"Point"}
}