{
  "type": "Feature",
  "properties": {
    "iso:country":"BE",
    "sg:address":"Rue Willebrord Van Perck 64",
    "sg:city":"Evere",
    "sg:orig_category":"Dranken",
    "sg:phone":"+32 2 245 45 05",
    "sg:postcode":"1140",
    "sg:province":"Bruxelles-Capitale",
    "wof:name":"Covinex",
    "wof:placetype":"venue"
},
  "geometry": {"coordinates":[4.3954491615,50.8738136292],"type":"Point"}
}