{
  "type": "Feature",
  "properties": {
    "addr:full":"Lippenslaan 48 Knokke-heist (knokke) West-Vlaanderen 8300",
    "addr:housenumber":"48",
    "addr:postcode":"8300",
    "addr:street":"Lippenslaan",
    "iso:country":"BE",
    "sg:address":"Lippenslaan 48",
    "sg:city":"Knokke-heist (knokke)",
    "sg:classifiers":[
        {
            "category":"Building & Trades",
            "subcategory":"Pest Control",
            "type":"Services"
        }
    ],
    "sg:phone":"+32 497 43 91 69",
    "sg:postcode":"8300",
    "sg:province":"West-Vlaanderen",
    "sg:tags":[
        "painting",
        "contractor"
    ],
    "wof:name":"Freelance Service",
    "wof:placetype":"venue"
},
  "geometry": {"coordinates":[3.2879700661,51.3426742554],"type":"Point"}
}