{
  "type": "Feature",
  "properties": {
    "addr:full":"Landuitstraat 151 Denderleeuw Oost-Vlaanderen 9470",
    "addr:housenumber":"151",
    "addr:postcode":"9470",
    "addr:street":"Landuitstraat",
    "iso:country":"BE",
    "sg:address":"Landuitstraat 151",
    "sg:city":"Denderleeuw",
    "sg:classifiers":[
        {
            "category":"Bars & Pubs",
            "type":"Food & Drink"
        }
    ],
    "sg:phone":"+32 53 67 14 81",
    "sg:postcode":"9470",
    "sg:province":"Oost-Vlaanderen",
    "wof:name":"Van Der Borght M",
    "wof:placetype":"venue"
},
  "geometry": {"coordinates":[4.066421032,50.8772964478],"type":"Point"}
}