{
  "type": "Feature",
  "properties": {
    "addr:full":"Rue De L'abevreye 7 Sprimont Li\u00e8ge 4140",
    "addr:housenumber":"7",
    "addr:postcode":"4140",
    "addr:street":"Rue De L'Abevreye",
    "iso:country":"BE",
    "sg:address":"Rue De L'abevreye 7",
    "sg:city":"Sprimont",
    "sg:orig_category":"Eleveurs de bovins",
    "sg:phone":"+32 4 382 13 37",
    "sg:postcode":"4140",
    "sg:province":"Li\u00e8ge",
    "wof:name":"Joseph Ponthier",
    "wof:placetype":"venue"
},
  "geometry": {"coordinates":[5.624268055,50.4956893921],"type":"Point"}
}