{
  "type": "Feature",
  "properties": {
    "iso:country":"BE",
    "sg:address":"Rue Maurice Wilmotte 10a",
    "sg:city":"Bruxelles",
    "sg:classifiers":[
        {
            "category":"Manufacturing",
            "subcategory":"Paper Products",
            "type":"Manufacturing & Wholesale Goods"
        }
    ],
    "sg:phone":"+32 2 538 62 53",
    "sg:postcode":"1060",
    "sg:province":"Bruxelles-Capitale",
    "sg:tags":[
        "finished",
        "cardboard",
        "-"
    ],
    "wof:name":"Omnigrafic Sa",
    "wof:placetype":"venue"
},
  "geometry": {"coordinates":[4.3500089645,50.825012207],"type":"Point"}
}