{
  "type": "Feature",
  "properties": {
    "iso:country":"BE",
    "sg:address":"Kuilenweg 17",
    "sg:city":"Bilzen",
    "sg:orig_category":"Produits surgel\u00e9s Cr\u00e9meries",
    "sg:phone":"+32 89 41 27 15",
    "sg:postcode":"3740",
    "sg:province":"Limburg",
    "wof:name":"Vries Shop Nijssen",
    "wof:placetype":"venue"
},
  "geometry": {"coordinates":[5.5065398216,50.8946228027],"type":"Point"}
}