{
  "type": "Feature",
  "properties": {
    "addr:full":"Cherain 32b Gouvy Luxembourg 6673",
    "addr:housenumber":"32b",
    "addr:postcode":"6673",
    "addr:street":"Cherain",
    "iso:country":"BE",
    "sg:address":"Cherain 32b",
    "sg:city":"Gouvy",
    "sg:orig_category":"Kampeerterreinen",
    "sg:phone":"+32 80 51 76 65",
    "sg:postcode":"6673",
    "sg:province":"Luxembourg",
    "wof:name":"Camping Moulin Du Bistain",
    "wof:placetype":"venue"
},
  "geometry": {"coordinates":[5.8639779091,50.1810760498],"type":"Point"}
}