{
  "type": "Feature",
  "properties": {
    "addr:full":"Rue Des Puits L'eau 42 Tournai Hainaut 7500",
    "addr:housenumber":"42",
    "addr:postcode":"7500",
    "addr:street":"Rue Des Puits L'Eau",
    "iso:country":"BE",
    "sg:address":"Rue Des Puits L'eau 42",
    "sg:city":"Tournai",
    "sg:orig_category":"Tijdelijke werkgelegenheid and uitzendkantoren",
    "sg:phone":"+32 69 89 14 40",
    "sg:postcode":"7500",
    "sg:province":"Hainaut",
    "wof:name":"Manpower",
    "wof:placetype":"venue"
},
  "geometry": {"coordinates":[3.3916809559,50.6056785583],"type":"Point"}
}