{
  "type": "Feature",
  "properties": {
    "addr:full":"Eglegemweg 3 Mechelen (hombeek) Antwerpen 2811",
    "addr:housenumber":"3",
    "addr:postcode":"2811",
    "addr:street":"Eglegemweg",
    "iso:country":"BE",
    "sg:address":"Eglegemweg 3",
    "sg:city":"Mechelen (hombeek)",
    "sg:classifiers":[
        {
            "category":"Professional",
            "subcategory":"Secretarial Services",
            "type":"Services"
        }
    ],
    "sg:phone":"+32 15 41 29 52",
    "sg:postcode":"2811",
    "sg:province":"Antwerpen",
    "sg:tags":[
        "firm"
    ],
    "wof:name":"Nice Bvba",
    "wof:placetype":"venue"
},
  "geometry": {"coordinates":[4.4443998337,51.014541626],"type":"Point"}
}