{
  "type": "Feature",
  "properties": {
    "iso:country":"BE",
    "sg:address":"Hoogstraat 14",
    "sg:city":"Zemst",
    "sg:orig_category":"M\u00e9decins and sp\u00e9cialistes",
    "sg:phone":"+32 15 61 55 66",
    "sg:postcode":"1980",
    "sg:province":"Vlaams-Brabant",
    "wof:name":"Luc Ghyselen",
    "wof:placetype":"venue"
},
  "geometry": {"coordinates":[4.4635567665,50.985748291],"type":"Point"}
}