{
  "type": "Feature",
  "properties": {
    "iso:country":"BE",
    "sg:address":"Rue De Courcelles 1",
    "sg:city":"Pont-a-celles",
    "sg:orig_category":"M\u00e9decins and sp\u00e9cialistes",
    "sg:phone":"+32 71 84 67 46",
    "sg:postcode":"6230",
    "sg:province":"Hainaut",
    "wof:name":"Isabelle Reflet",
    "wof:placetype":"venue"
},
  "geometry": {"coordinates":[4.3565101624,50.5071792603],"type":"Point"}
}