{
  "type": "Feature",
  "properties": {
    "addr:full":"Lintbaan 133 Grimbergen Vlaams-Brabant 1850",
    "addr:housenumber":"133",
    "addr:postcode":"1850",
    "iso:country":"BE",
    "sg:address":"Lintbaan 133",
    "sg:city":"Grimbergen",
    "sg:orig_category":"Verplichte sociale verzekeringen",
    "sg:phone":"+32 2 270 84 22",
    "sg:postcode":"1850",
    "sg:province":"Vlaams-Brabant",
    "wof:name":"Euromut",
    "wof:placetype":"venue"
},
  "geometry": {"coordinates":[4.3851571083,50.9427108765],"type":"Point"}
}