{
  "type": "Feature",
  "properties": {
    "iso:country":"BE",
    "sg:address":"Rue De La Malaise 32",
    "sg:city":"Eghezee",
    "sg:orig_category":"Eleveurs and marchands de porcs. Eleveurs de bovins",
    "sg:phone":"+32 81 51 13 83",
    "sg:postcode":"5310",
    "sg:province":"Namur",
    "wof:name":"Gaston Leers",
    "wof:placetype":"venue"
},
  "geometry": {"coordinates":[4.9123840332,50.5337982178],"type":"Point"}
}