{
  "type": "Feature",
  "properties": {
    "iso:country":"BE",
    "sg:address":"Rue De Cond\u00c9 85",
    "sg:city":"Bernissart",
    "sg:orig_category":"Dakwerken Loodgieterij, verwarming and sanitaire installaties Woningbouw",
    "sg:phone":"+32 69 56 23 22",
    "sg:postcode":"7321",
    "sg:province":"Hainaut",
    "wof:name":"V.s. Toitures",
    "wof:placetype":"venue"
},
  "geometry": {"coordinates":[3.6611618996,50.5015869141],"type":"Point"}
}