{
  "type": "Feature",
  "properties": {
    "iso:country":"BE",
    "sg:address":"Krekelenbergweg 34",
    "sg:city":"Sint-katelijne-waver",
    "sg:orig_category":"Producteurs de l\u00e9gumes",
    "sg:phone":"+32 15 31 39 53",
    "sg:postcode":"2860",
    "sg:province":"Antwerpen",
    "wof:name":"Marcel Smans",
    "wof:placetype":"venue"
},
  "geometry": {"coordinates":[4.5275201797,51.0837631226],"type":"Point"}
}