{
  "type": "Feature",
  "properties": {
    "iso:country":"BE",
    "sg:address":"G. Mertensstraat 19",
    "sg:city":"Liedekerke",
    "sg:classifiers":[
        {
            "category":"Health Services",
            "subcategory":"Health Practitioner",
            "type":"Services"
        }
    ],
    "sg:phone":"+32 53 67 07 32",
    "sg:postcode":"1770",
    "sg:province":"Vlaams-Brabant",
    "sg:tags":[
        "dietitian"
    ],
    "wof:name":"De Zonnebloem-coppens",
    "wof:placetype":"venue"
},
  "geometry": {"coordinates":[4.0808181763,50.8702087402],"type":"Point"}
}