{
  "type": "Feature",
  "properties": {
    "addr:full":"Vierbunderstraat 20 Oosterzele (scheldewindeke) Oost-Vlaanderen 9860",
    "addr:housenumber":"20",
    "addr:postcode":"9860",
    "addr:street":"Vierbunderstraat",
    "iso:country":"BE",
    "sg:address":"Vierbunderstraat 20",
    "sg:city":"Oosterzele (scheldewindeke)",
    "sg:classifiers":[
        {
            "category":"Professional",
            "subcategory":"Lawyer & Legal Services",
            "type":"Services"
        }
    ],
    "sg:phone":"+32 9 362 12 66",
    "sg:postcode":"9860",
    "sg:province":"Oost-Vlaanderen",
    "wof:name":"Fiers Jan",
    "wof:placetype":"venue"
},
  "geometry": {"coordinates":[3.7917900085,50.9394226074],"type":"Point"}
}