{
  "type": "Feature",
  "properties": {
    "iso:country":"BE",
    "sg:address":"Vaartstraat 119",
    "sg:city":"Leuven",
    "sg:orig_category":"Pain, p\u00e2tisseries and confiseries",
    "sg:phone":"+32 16 22 33 70",
    "sg:postcode":"3000",
    "sg:province":"Vlaams-Brabant",
    "wof:name":"Luc Uyttebroeck",
    "wof:placetype":"venue"
},
  "geometry": {"coordinates":[4.7006578445,50.8855514526],"type":"Point"}
}