{
  "type": "Feature",
  "properties": {
    "iso:country":"BE",
    "sg:address":"Stationsstraat 28",
    "sg:city":"Oostkamp",
    "sg:orig_category":"Verplichte sociale verzekeringen",
    "sg:phone":"+32 50 84 16 89",
    "sg:postcode":"8020",
    "sg:province":"West-Vlaanderen",
    "wof:name":"Vlaams Neutraal Ziekenf.",
    "wof:placetype":"venue"
},
  "geometry": {"coordinates":[3.2377340794,51.1540336609],"type":"Point"}
}