{
  "type": "Feature",
  "properties": {
    "addr:full":"Avenue De La M\u00e9trologie 2 Bruxelles Bruxelles-Capitale 1130",
    "addr:housenumber":"2",
    "addr:postcode":"1130",
    "addr:street":"Avenue De La Me\u0301Trologie",
    "iso:country":"BE",
    "sg:address":"Avenue De La M\u00e9trologie 2",
    "sg:city":"Bruxelles",
    "sg:classifiers":[
        {
            "category":"Insurance",
            "subcategory":"Insurance Agent",
            "type":"Services"
        }
    ],
    "sg:phone":"+32 2 244 22 11",
    "sg:postcode":"1130",
    "sg:province":"Bruxelles-Capitale",
    "sg:tags":[
        "-",
        "representative"
    ],
    "wof:name":"Corona Direct",
    "wof:placetype":"venue"
},
  "geometry": {"coordinates":[4.4294981956,50.8939285278],"type":"Point"}
}