{
  "type": "Feature",
  "properties": {
    "addr:full":"Sint Lambertusstraat 135 Brussel/bruxelles Bruxelles-Capitale 1200",
    "addr:housenumber":"135",
    "addr:postcode":"1200",
    "addr:street":"Sint Lambertusstraat;/",
    "iso:country":"BE",
    "sg:address":"Sint Lambertusstraat 135",
    "sg:city":"Brussel/bruxelles",
    "sg:orig_category":"Telecommunicatieapparaten",
    "sg:phone":"+32 2 779 51 71",
    "sg:postcode":"1200",
    "sg:province":"Bruxelles-Capitale",
    "wof:name":"Bel Concept",
    "wof:placetype":"venue"
},
  "geometry": {"coordinates":[4.4354119301,50.845085144],"type":"Point"}
}