{
  "type": "Feature",
  "properties": {
    "addr:full":"Place Fran\u00c7ois Faniel 16 Wanze Li\u00e8ge 4520",
    "addr:housenumber":"16",
    "addr:postcode":"4520",
    "addr:street":"Place Franc\u0327Ois Faniel",
    "iso:country":"BE",
    "sg:address":"Place Fran\u00c7ois Faniel 16",
    "sg:city":"Wanze",
    "sg:orig_category":"Banken and kredietinstellingen",
    "sg:phone":"+32 85 21 41 29",
    "sg:postcode":"4520",
    "sg:province":"Li\u00e8ge",
    "wof:name":"Fortis",
    "wof:placetype":"venue"
},
  "geometry": {"coordinates":[5.2154607773,50.5357208252],"type":"Point"}
}