{
  "type": "Feature",
  "properties": {
    "iso:country":"BE",
    "sg:address":"Capucienessenstraat 8",
    "sg:city":"Sint-truiden",
    "sg:orig_category":"Salles de spectacles",
    "sg:phone":"+32 11 69 39 90",
    "sg:postcode":"3800",
    "sg:province":"Limburg",
    "wof:name":"Cult. Centrum De Bogaard",
    "wof:placetype":"venue"
},
  "geometry": {"coordinates":[5.1873087883,50.8133087158],"type":"Point"}
}