{
  "type": "Feature",
  "properties": {
    "addr:full":"Kerkhoflaan 99 Aalst Oost-Vlaanderen 9300",
    "addr:housenumber":"99",
    "addr:postcode":"9300",
    "addr:street":"Kerkhoflaan",
    "iso:country":"BE",
    "sg:address":"Kerkhoflaan 99",
    "sg:city":"Aalst",
    "sg:classifiers":[
        {
            "category":"Real Estate",
            "subcategory":"Architect",
            "type":"Services"
        }
    ],
    "sg:phone":"+32 53 78 50 87",
    "sg:postcode":"9300",
    "sg:province":"Oost-Vlaanderen",
    "wof:name":"De Rijck J",
    "wof:placetype":"venue"
},
  "geometry": {"coordinates":[4.0315041542,50.9294090271],"type":"Point"}
}