{
  "type": "Feature",
  "properties": {
    "iso:country":"BE",
    "sg:address":"Vleeshouwersstraat 15",
    "sg:city":"Sint-niklaas",
    "sg:orig_category":"Boucheries",
    "sg:phone":"+32 3 772 30 41",
    "sg:postcode":"9112",
    "sg:province":"Oost-Vlaanderen",
    "wof:name":"Fernand Dekimpe",
    "wof:placetype":"venue"
},
  "geometry": {"coordinates":[4.0455460548,51.1581420898],"type":"Point"}
}