{
  "type": "Feature",
  "properties": {
    "addr:full":"Heren Van Witthemlaan 1 Beersel Vlaams-Brabant 1650",
    "addr:housenumber":"1",
    "addr:postcode":"1650",
    "addr:street":"Heren;Witthemlaan",
    "iso:country":"BE",
    "sg:address":"Heren Van Witthemlaan 1",
    "sg:city":"Beersel",
    "sg:orig_category":"Plaatsen van vloer- and muurbekleding Schilders",
    "sg:phone":"+32 2 377 09 98",
    "sg:postcode":"1650",
    "sg:province":"Vlaams-Brabant",
    "wof:name":"L Style",
    "wof:placetype":"venue"
},
  "geometry": {"coordinates":[4.3027410507,50.7626495361],"type":"Point"}
}