{
  "type": "Feature",
  "properties": {
    "addr:full":"Rue De La Basilique 7 Walcourt Namur 5650",
    "addr:housenumber":"7",
    "addr:postcode":"5650",
    "addr:street":"Rue De La Basilique",
    "iso:country":"BE",
    "sg:address":"Rue De La Basilique 7",
    "sg:city":"Walcourt",
    "sg:orig_category":"Herstelling and restauratie van meubelen",
    "sg:phone":"+32 71 61 21 07",
    "sg:postcode":"5650",
    "sg:province":"Namur",
    "wof:name":"Andre Michel",
    "wof:placetype":"venue"
},
  "geometry": {"coordinates":[4.4320321083,50.2510757446],"type":"Point"}
}