{
  "type": "Feature",
  "properties": {
    "addr:full":"Route De Bertrix 2ba Neufchateau Luxembourg 6840",
    "addr:housenumber":"2ba",
    "addr:postcode":"6840",
    "addr:street":"Route De Bertrix",
    "iso:country":"BE",
    "sg:address":"Route De Bertrix 2ba",
    "sg:city":"Neufchateau",
    "sg:orig_category":"Woningbouw",
    "sg:phone":"+32 61 27 71 68",
    "sg:postcode":"6840",
    "sg:province":"Luxembourg",
    "wof:name":"Christophe Hardy",
    "wof:placetype":"venue"
},
  "geometry": {"coordinates":[5.4315500259,49.8418998718],"type":"Point"}
}