{
  "type": "Feature",
  "properties": {
    "addr:full":"Krekelstraat 250a Izegem West-Vlaanderen 8870",
    "addr:housenumber":"250a",
    "addr:postcode":"8870",
    "addr:street":"Krekelstraat",
    "iso:country":"BE",
    "sg:address":"Krekelstraat 250a",
    "sg:city":"Izegem",
    "sg:classifiers":[
        {
            "category":"Fast Food",
            "type":"Food & Drink"
        }
    ],
    "sg:phone":"+32 51 31 48 59",
    "sg:postcode":"8870",
    "sg:province":"West-Vlaanderen",
    "sg:tags":[
        "fried",
        "stand",
        "potato"
    ],
    "wof:name":"Hoeksken ('t)",
    "wof:placetype":"venue"
},
  "geometry": {"coordinates":[3.2011780739,50.9128952026],"type":"Point"}
}