{
  "type": "Feature",
  "properties": {
    "iso:country":"BE",
    "sg:address":"Valkenstraat 12",
    "sg:city":"Gent",
    "sg:classifiers":[
        {
            "category":"Insurance",
            "subcategory":"Life Insurance",
            "type":"Services"
        }
    ],
    "sg:phone":"+32 9 228 48 25",
    "sg:postcode":"9040",
    "sg:province":"Oost-Vlaanderen",
    "sg:tags":[
        "assurance"
    ],
    "wof:name":"Bureau De Lange-iterbeke",
    "wof:placetype":"venue"
},
  "geometry": {"coordinates":[3.7736010551,51.0655326843],"type":"Point"}
}