{
  "type": "Feature",
  "properties": {
    "addr:full":"Veldlaan 3 Kalmthout Antwerpen 2920",
    "addr:housenumber":"3",
    "addr:postcode":"2920",
    "addr:street":"Veldlaan",
    "iso:country":"BE",
    "sg:address":"Veldlaan 3",
    "sg:city":"Kalmthout",
    "sg:classifiers":[
        {
            "category":"Professional",
            "subcategory":"Computer Services",
            "type":"Services"
        }
    ],
    "sg:phone":"+32 479 35 57 47",
    "sg:postcode":"2920",
    "sg:province":"Antwerpen",
    "sg:tags":[
        "-",
        "processing",
        "data"
    ],
    "wof:name":"Software Engineer",
    "wof:placetype":"venue"
},
  "geometry": {"coordinates":[4.4693050385,51.3845481873],"type":"Point"}
}