{
  "type": "Feature",
  "properties": {
    "addr:full":"Sterrebos 18 Hasselt Limburg 3512",
    "addr:housenumber":"18",
    "addr:postcode":"3512",
    "addr:street":"Sterrebos",
    "iso:country":"BE",
    "sg:address":"Sterrebos 18",
    "sg:city":"Hasselt",
    "sg:orig_category":"Producteurs de fruits",
    "sg:phone":"+32 11 59 63 22",
    "sg:postcode":"3512",
    "sg:province":"Limburg",
    "wof:name":"Luc Windmolders",
    "wof:placetype":"venue"
},
  "geometry": {"coordinates":[5.2597670555,50.919719696],"type":"Point"}
}