{
  "type": "Feature",
  "properties": {
    "addr:full":"Lijsternest 14 Kuurne West-Vlaanderen 8520",
    "addr:housenumber":"14",
    "addr:postcode":"8520",
    "addr:street":"Lijsternest",
    "iso:country":"BE",
    "sg:address":"Lijsternest 14",
    "sg:city":"Kuurne",
    "sg:classifiers":[
        {
            "category":"Building & Trades",
            "subcategory":"Construction",
            "type":"Services"
        }
    ],
    "sg:phone":"+32 56 70 53 98",
    "sg:postcode":"8520",
    "sg:province":"West-Vlaanderen",
    "sg:tags":[
        "paper",
        "hanger"
    ],
    "wof:name":"Derhore J",
    "wof:placetype":"venue"
},
  "geometry": {"coordinates":[3.2761950493,50.8618621826],"type":"Point"}
}