{
  "type": "Feature",
  "properties": {
    "addr:full":"Heidehoeven 8 Zoersel (halle) Antwerpen 2980",
    "addr:housenumber":"8",
    "addr:postcode":"2980",
    "addr:street":"Heidehoeven",
    "iso:country":"BE",
    "sg:address":"Heidehoeven 8",
    "sg:city":"Zoersel (halle)",
    "sg:classifiers":[
        {
            "category":"Insurance",
            "subcategory":"Insurance Agent",
            "type":"Services"
        }
    ],
    "sg:phone":"+32 3 383 64 69",
    "sg:postcode":"2980",
    "sg:province":"Antwerpen",
    "sg:tags":[
        "broker"
    ],
    "wof:name":"M S C Bvba",
    "wof:placetype":"venue"
},
  "geometry": {"coordinates":[4.6426239014,51.2585258484],"type":"Point"}
}