{
  "type": "Feature",
  "properties": {
    "addr:full":"Rue De Gaet 32ba Beauvechain Brabant Wallon 1320",
    "addr:housenumber":"32ba",
    "addr:postcode":"1320",
    "addr:street":"Rue De Gaet",
    "iso:country":"BE",
    "sg:address":"Rue De Gaet 32ba",
    "sg:city":"Beauvechain",
    "sg:orig_category":"HUISBRANDOLIE",
    "sg:phone":"+32 10 86 62 25",
    "sg:postcode":"1320",
    "sg:province":"Brabant Wallon",
    "wof:name":"Guy Bamps",
    "wof:placetype":"venue"
},
  "geometry": {"coordinates":[4.8113598824,50.7761306763],"type":"Point"}
}