{
  "type": "Feature",
  "properties": {
    "addr:full":"Ieperse Heerweg 7 Torhout West-Vlaanderen 8820",
    "addr:housenumber":"7",
    "addr:postcode":"8820",
    "addr:street":"Heerweg",
    "iso:country":"BE",
    "sg:address":"Ieperse Heerweg 7",
    "sg:city":"Torhout",
    "sg:orig_category":"Eleveurs and marchands de porcs. Eleveurs de bovins",
    "sg:phone":"+32 50 21 14 76",
    "sg:postcode":"8820",
    "sg:province":"West-Vlaanderen",
    "wof:name":"Gerard Vanclooster",
    "wof:placetype":"venue"
},
  "geometry": {"coordinates":[3.0956559181,51.0539131165],"type":"Point"}
}