{
  "type": "Feature",
  "properties": {
    "addr:full":"Rue De Saint-lazare 50 Mons Hainaut 7000",
    "addr:housenumber":"50",
    "addr:postcode":"7000",
    "addr:street":"Rue De Saint-Lazare;Hainaut",
    "iso:country":"BE",
    "sg:address":"Rue De Saint-lazare 50",
    "sg:city":"Mons",
    "sg:orig_category":"Boekenuitgeverijen",
    "sg:phone":"+32 65 84 26 55",
    "sg:postcode":"7000",
    "sg:province":"Hainaut",
    "wof:name":"Editions Chryss' Intern.",
    "wof:placetype":"venue"
},
  "geometry": {"coordinates":[3.9602539539,50.4636306763],"type":"Point"}
}