{
  "type": "Feature",
  "properties": {
    "addr:full":"Vijfhuishoekstraat 20 Torhout West-Vlaanderen 8820",
    "addr:housenumber":"20",
    "addr:postcode":"8820",
    "addr:street":"Vijfhuishoekstraat",
    "iso:country":"BE",
    "sg:address":"Vijfhuishoekstraat 20",
    "sg:city":"Torhout",
    "sg:orig_category":"Rundveehouders Varkenskwekers",
    "sg:phone":"+32 50 21 26 88",
    "sg:postcode":"8820",
    "sg:province":"West-Vlaanderen",
    "wof:name":"Luc Deruyter",
    "wof:placetype":"venue"
},
  "geometry": {"coordinates":[3.0729980469,51.0441474915],"type":"Point"}
}