{
  "type": "Feature",
  "properties": {
    "addr:full":"Oudenaardsesteenweg 364 Avelgem West-Vlaanderen 8581",
    "addr:housenumber":"364",
    "addr:postcode":"8581",
    "addr:street":"Oudenaardsesteenweg",
    "iso:country":"BE",
    "sg:address":"Oudenaardsesteenweg 364",
    "sg:city":"Avelgem",
    "sg:orig_category":"Reclamebureaus",
    "sg:phone":"+32 55 38 60 99",
    "sg:postcode":"8581",
    "sg:province":"West-Vlaanderen",
    "wof:name":"Herman Naessens",
    "wof:placetype":"venue"
},
  "geometry": {"coordinates":[3.4851169586,50.790851593],"type":"Point"}
}