{
  "type": "Feature",
  "properties": {
    "iso:country":"BE",
    "sg:address":"De Meanstraat 8",
    "sg:city":"Riemst",
    "sg:orig_category":"Meubles D\u00e9taillants, Am\u00e9nagement de B\u00e2timents et de Cuisines. P\u00e9pini\u00e9ristes",
    "sg:phone":"+32 12 45 48 75",
    "sg:postcode":"3770",
    "sg:province":"Limburg",
    "wof:name":"Fa. Golden Goddess",
    "wof:placetype":"venue"
},
  "geometry": {"coordinates":[5.5969901085,50.8109016418],"type":"Point"}
}