{
  "type": "Feature",
  "properties": {
    "iso:country":"BE",
    "sg:address":"Rue Ernest Malvoz 85",
    "sg:city":"Beyne-heusay",
    "sg:orig_category":"G\u00e2teaux, p\u00e2tisserie and biscuits Fab",
    "sg:phone":"+32 4 367 11 83",
    "sg:postcode":"4610",
    "sg:province":"Li\u00e8ge",
    "wof:name":"Fe. Haccour-malherbe",
    "wof:placetype":"venue"
},
  "geometry": {"coordinates":[5.6567759514,50.628162384],"type":"Point"}
}