{
  "type": "Feature",
  "properties": {
    "iso:country":"BE",
    "sg:address":"Chauss\u00c9e De Waterloo 351",
    "sg:city":"Sint-gillis/saint-gilles",
    "sg:orig_category":"Agences de publicit\u00e9",
    "sg:phone":"+32 2 544 66 56",
    "sg:postcode":"1060",
    "sg:province":"Bruxelles-Capitale",
    "wof:name":"Pakulski Communication",
    "wof:placetype":"venue"
},
  "geometry": {"coordinates":[4.3530907631,50.8229179382],"type":"Point"}
}