{
  "type": "Feature",
  "properties": {
    "iso:country":"BE",
    "sg:address":"Rue De Haerne 31",
    "sg:city":"Bruxelles (etterbeek)",
    "sg:classifiers":[
        {
            "category":"Manufacturing",
            "subcategory":"Metals",
            "type":"Manufacturing & Wholesale Goods"
        }
    ],
    "sg:phone":"+32 2 648 94 19",
    "sg:postcode":"1040",
    "sg:province":"Bruxelles-Capitale",
    "sg:tags":[
        "ornamental",
        "work",
        "-"
    ],
    "wof:name":"Creation Metallique Feremans",
    "wof:placetype":"venue"
},
  "geometry": {"coordinates":[4.382226944,50.8319091797],"type":"Point"}
}