{
  "type": "Feature",
  "properties": {
    "iso:country":"BE",
    "sg:address":"Battelsesteenweg 455 Geb. E",
    "sg:city":"Mechelen",
    "sg:classifiers":[
        {
            "category":"Manufacturing",
            "subcategory":"Paper Products",
            "type":"Manufacturing & Wholesale Goods"
        }
    ],
    "sg:phone":"+32 3 771 58 31",
    "sg:postcode":"2800",
    "sg:province":"Antwerpen",
    "sg:tags":[
        "packaging",
        "material",
        "-",
        "cardboard"
    ],
    "wof:name":"Gosselin Export Packers Nv",
    "wof:placetype":"venue"
},
  "geometry": {"coordinates":[4.1589288712,51.1146697998],"type":"Point"}
}