{
  "type": "Feature",
  "properties": {
    "iso:country":"BE",
    "sg:address":"Place Communale 49",
    "sg:city":"Rixensart",
    "sg:orig_category":"Speelgoed",
    "sg:phone":"+32 2 652 07 62",
    "sg:postcode":"1332",
    "sg:province":"Brabant Wallon",
    "wof:name":"La D\u00c9couverte",
    "wof:placetype":"venue"
},
  "geometry": {"coordinates":[4.4990081787,50.7160644531],"type":"Point"}
}