{
  "type": "Feature",
  "properties": {
    "iso:country":"BE",
    "sg:address":"Rue Elisa Dumonceau 75",
    "sg:city":"Herstal",
    "sg:classifiers":[
        {
            "category":"Education",
            "subcategory":"School",
            "type":"Public Place"
        }
    ],
    "sg:phone":"+32 4 264 41 78",
    "sg:postcode":"4040",
    "sg:province":"Li\u00e8ge",
    "sg:tags":[
        "secondary"
    ],
    "wof:name":"D.o.a. Notre Dame St-lambert - St-laurent",
    "wof:placetype":"venue"
},
  "geometry": {"coordinates":[5.6292557716,50.6631088257],"type":"Point"}
}