{
  "type": "Feature",
  "properties": {
    "addr:full":"Doelestraat 20 Lennik Vlaams-Brabant 1750",
    "addr:housenumber":"20;1750",
    "addr:street":"Doelestraat;Vlaams-Brabant",
    "iso:country":"BE",
    "sg:address":"Doelestraat 20",
    "sg:city":"Lennik",
    "sg:orig_category":"Epiceries. Supermarch\u00e9s",
    "sg:phone":"+32 2 532 23 35",
    "sg:postcode":"1750",
    "sg:province":"Vlaams-Brabant",
    "wof:name":"Delhaize",
    "wof:placetype":"venue"
},
  "geometry": {"coordinates":[4.1681690216,50.813621521],"type":"Point"}
}