{
  "type": "Feature",
  "properties": {
    "iso:country":"BE",
    "sg:address":"Avenue Emile De Beco 109",
    "sg:city":"Bruxelles (ixelles)",
    "sg:classifiers":[
        {
            "category":"Organizations",
            "subcategory":"Professional Association",
            "type":"Services"
        }
    ],
    "sg:phone":"+32 2 626 21 80",
    "sg:postcode":"1050",
    "sg:province":"Bruxelles-Capitale",
    "sg:tags":[
        "trade-union",
        "federation"
    ],
    "wof:name":"F\u00e9d\u00e9ration Europ\u00e9enne Des Syndicats Des Mines,de La Chimie Et De L'energie",
    "wof:placetype":"venue"
},
  "geometry": {"coordinates":[4.3838100433,50.8213233948],"type":"Point"}
}