{
  "type": "Feature",
  "properties": {
    "iso:country":"BE",
    "sg:address":"Rue Francisco Ferrer 71",
    "sg:city":"Courcelles (gouy-lez-pi\u00e9ton)",
    "sg:classifiers":[
        {
            "category":"Building & Trades",
            "subcategory":"Pest Control",
            "type":"Services"
        }
    ],
    "sg:phone":"+32 71 84 48 17",
    "sg:postcode":"6181",
    "sg:province":"Hainaut",
    "sg:tags":[
        "painting",
        "contractor"
    ],
    "wof:name":"Mabille",
    "wof:placetype":"venue"
},
  "geometry": {"coordinates":[4.3267760277,50.4922943115],"type":"Point"}
}