{
  "type": "Feature",
  "properties": {
    "iso:country":"BE",
    "sg:address":"Avenue De Stassart 18b15",
    "sg:city":"Namur",
    "sg:orig_category":"Boekhouders",
    "sg:phone":"+32 81 73 01 17",
    "sg:postcode":"5000",
    "sg:province":"Namur",
    "wof:name":"Am\u00c9lia Rossi",
    "wof:placetype":"venue"
},
  "geometry": {"coordinates":[4.8547849655,50.4669914246],"type":"Point"}
}