{
  "type": "Feature",
  "properties": {
    "addr:full":"Rue Du Mus\u00e9e 10 Arlon Luxembourg 6700",
    "addr:housenumber":"10",
    "addr:postcode":"6700",
    "addr:street":"Rue Du Muse\u0301E",
    "iso:country":"BE",
    "sg:address":"Rue Du Mus\u00e9e 10",
    "sg:city":"Arlon",
    "sg:classifiers":[
        {
            "category":"Building & Trades",
            "subcategory":"Construction",
            "type":"Services"
        }
    ],
    "sg:phone":"+32 63 22 14 33",
    "sg:postcode":"6700",
    "sg:province":"Luxembourg",
    "sg:tags":[
        "ceiling"
    ],
    "wof:name":"Barrisol Sa",
    "wof:placetype":"venue"
},
  "geometry": {"coordinates":[5.8117799759,49.6852302551],"type":"Point"}
}