{
  "type": "Feature",
  "properties": {
    "addr:full":"Rue Montoyer 6 Bruxelles Bruxelles-Capitale 1000",
    "addr:housenumber":"6",
    "addr:postcode":"1000",
    "addr:street":"Rue Montoyer",
    "iso:country":"BE",
    "sg:address":"Rue Montoyer 6",
    "sg:city":"Bruxelles",
    "sg:classifiers":[
        {
            "category":"Social Services",
            "subcategory":"Job Training",
            "type":"Services"
        }
    ],
    "sg:phone":"+32 2 503 08 81",
    "sg:postcode":"1000",
    "sg:province":"Bruxelles-Capitale",
    "sg:tags":[
        "interpreter"
    ],
    "wof:name":"Translations Tradutec Belgium",
    "wof:placetype":"venue"
},
  "geometry": {"coordinates":[4.3676328659,50.8418312073],"type":"Point"}
}