{
  "type": "Feature",
  "properties": {
    "iso:country":"BE",
    "sg:address":"Rue Du Rivage 16",
    "sg:city":"Sprimont",
    "sg:classifiers":[
        {
            "category":"Organizations",
            "subcategory":"Community Association",
            "type":"Services"
        }
    ],
    "sg:phone":"+32 4 369 21 77",
    "sg:postcode":"4140",
    "sg:province":"Li\u00e8ge",
    "sg:tags":[
        "organisation"
    ],
    "wof:name":"Centre Cooper. Educative",
    "wof:placetype":"venue"
},
  "geometry": {"coordinates":[5.5848841667,50.488658905],"type":"Point"}
}