{
  "type": "Feature",
  "properties": {
    "addr:full":"Smissestraat 26 Meerhout Antwerpen 2450",
    "addr:housenumber":"26",
    "addr:postcode":"2450",
    "addr:street":"Smissestraat",
    "iso:country":"BE",
    "sg:address":"Smissestraat 26",
    "sg:city":"Meerhout",
    "sg:orig_category":"Sportclubs",
    "sg:phone":"+32 14 30 03 10",
    "sg:postcode":"2450",
    "sg:province":"Antwerpen",
    "wof:name":"Turnkring Meerhout",
    "wof:placetype":"venue"
},
  "geometry": {"coordinates":[5.0731229782,51.1349906921],"type":"Point"}
}