{
  "type": "Feature",
  "properties": {
    "addr:full":"Dokter Roosensplein 43 Brasschaat Antwerpen 2930",
    "addr:housenumber":"43",
    "addr:postcode":"2930",
    "addr:street":"Dokter Roosensplein",
    "iso:country":"BE",
    "sg:address":"Dokter Roosensplein 43",
    "sg:city":"Brasschaat",
    "sg:classifiers":[
        {
            "category":"Shopping",
            "subcategory":"Clothing, Apparel, & Fashions",
            "type":"Retail Goods"
        }
    ],
    "sg:phone":"+32 3 651 86 17",
    "sg:postcode":"2930",
    "sg:province":"Antwerpen",
    "sg:tags":[
        "underwear",
        "lingerie",
        "-"
    ],
    "wof:name":"Caress",
    "wof:placetype":"venue"
},
  "geometry": {"coordinates":[4.4858131409,51.2874641418],"type":"Point"}
}