{
  "type": "Feature",
  "properties": {
    "iso:country":"BE",
    "sg:address":"'s Hertogenbos 15",
    "sg:city":"Beersel (dworp)",
    "sg:classifiers":[
        {
            "category":"Professional",
            "subcategory":"Printing & Photocopies",
            "type":"Services"
        }
    ],
    "sg:phone":"+32 2 380 88 55",
    "sg:postcode":"1653",
    "sg:province":"Vlaams-Brabant",
    "sg:tags":[
        "silkscreen",
        "-"
    ],
    "wof:name":"Ann",
    "wof:placetype":"venue"
},
  "geometry": {"coordinates":[4.2754302025,50.7231826782],"type":"Point"}
}