{
  "type": "Feature",
  "properties": {
    "addr:full":"Rue De Bruxelles 61 Namur Namur 5000",
    "addr:housenumber":"61",
    "addr:postcode":"5000",
    "addr:street":"Rue De Bruxelles",
    "iso:country":"BE",
    "sg:address":"Rue De Bruxelles 61",
    "sg:city":"Namur",
    "sg:orig_category":"Enseignement sup\u00e9rieur",
    "sg:phone":"+32 81 72 43 38",
    "sg:postcode":"5000",
    "sg:province":"Namur",
    "wof:name":"Fundp-dep. Of Pharmacy",
    "wof:placetype":"venue"
},
  "geometry": {"coordinates":[4.8594961166,50.4667167664],"type":"Point"}
}