{
  "type": "Feature",
  "properties": {
    "addr:full":"Schalkstraat 4 Willebroek Antwerpen 2830",
    "addr:housenumber":"4",
    "addr:postcode":"2830",
    "addr:street":"Schalkstraat",
    "iso:country":"BE",
    "sg:address":"Schalkstraat 4",
    "sg:city":"Willebroek",
    "sg:orig_category":"Sportterreinen and installaties behalve sportcentra",
    "sg:phone":"+32 3 886 33 67",
    "sg:postcode":"2830",
    "sg:province":"Antwerpen",
    "wof:name":"De Schalk",
    "wof:placetype":"venue"
},
  "geometry": {"coordinates":[4.3426399231,51.0609397888],"type":"Point"}
}