{
  "type": "Feature",
  "properties": {
    "addr:full":"Sentier Du Li\u00c8vre 92 Chaudfontaine Li\u00e8ge 4053",
    "addr:housenumber":"92",
    "addr:postcode":"4053",
    "addr:street":"Sentier Du Lie\u0300Vre",
    "iso:country":"BE",
    "sg:address":"Sentier Du Li\u00c8vre 92",
    "sg:city":"Chaudfontaine",
    "sg:classifiers":[
        {
            "category":"Arena",
            "subcategory":"Sports Club",
            "type":"Entertainment"
        }
    ],
    "sg:phone":"+32 4 365 73 68",
    "sg:postcode":"4053",
    "sg:province":"Li\u00e8ge",
    "sg:tags":[
        "de"
    ],
    "wof:name":"Les Marcheurs De L\u00b4ourthe",
    "wof:placetype":"venue"
},
  "geometry": {"coordinates":[5.5982608795,50.5972671509],"type":"Point"}
}