{
  "type": "Feature",
  "properties": {
    "addr:full":"Rue Dragon-paul-fisseux 80 Tellin Luxembourg 6927",
    "addr:housenumber":"80",
    "addr:postcode":"6927",
    "addr:street":"Rue Dragon-Paul-Fisseux",
    "iso:country":"BE",
    "sg:address":"Rue Dragon-paul-fisseux 80",
    "sg:city":"Tellin",
    "sg:orig_category":"Herstellingen and onderhoud van auto's",
    "sg:phone":"+32 84 36 62 32",
    "sg:postcode":"6927",
    "sg:province":"Luxembourg",
    "wof:name":"Louis Clement",
    "wof:placetype":"venue"
},
  "geometry": {"coordinates":[5.2833580971,50.0904273987],"type":"Point"}
}