{
  "type": "Feature",
  "properties": {
    "iso:country":"BE",
    "sg:address":"Breughellaan 15",
    "sg:city":"De Pinte",
    "sg:classifiers":[
        {
            "category":"Health Services",
            "subcategory":"Health Practitioner",
            "type":"Services"
        }
    ],
    "sg:phone":"+32 9 281 14 33",
    "sg:postcode":"9840",
    "sg:province":"Oost-Vlaanderen",
    "sg:tags":[
        "physiotherapist"
    ],
    "wof:name":"Geltmeyer Sofie",
    "wof:placetype":"venue"
},
  "geometry": {"coordinates":[3.6418180466,50.9930725098],"type":"Point"}
}