{
  "type": "Feature",
  "properties": {
    "addr:full":"Avenue Louise 391 Brussel/bruxelles Bruxelles-Capitale 1050",
    "addr:housenumber":"391",
    "addr:postcode":"1050",
    "addr:street":"Avenue Louise;/",
    "iso:country":"BE",
    "sg:address":"Avenue Louise 391",
    "sg:city":"Brussel/bruxelles",
    "sg:orig_category":"Avocats and conseillers juridiques",
    "sg:phone":"+32 2 646 51 20",
    "sg:postcode":"1050",
    "sg:province":"Bruxelles-Capitale",
    "wof:name":"Menno Meeldijk",
    "wof:placetype":"venue"
},
  "geometry": {"coordinates":[4.355919838,50.8357810974],"type":"Point"}
}