{
  "type": "Feature",
  "properties": {
    "addr:full":"Avenue De Broqueville 113 Bruxelles (woluwe-saint-lambert) Bruxelles-Capitale 1200",
    "addr:housenumber":"113",
    "addr:postcode":"1200",
    "addr:street":"Avenue De Broqueville",
    "iso:country":"BE",
    "sg:address":"Avenue De Broqueville 113",
    "sg:city":"Bruxelles (woluwe-saint-lambert)",
    "sg:classifiers":[
        {
            "category":"Communications",
            "subcategory":"Television Station",
            "type":"Services"
        }
    ],
    "sg:phone":"+32 2 736 55 60",
    "sg:postcode":"1200",
    "sg:province":"Bruxelles-Capitale",
    "sg:tags":[
        "report",
        "video"
    ],
    "wof:name":"Iavs",
    "wof:placetype":"venue"
},
  "geometry": {"coordinates":[4.4149417877,50.8415985107],"type":"Point"}
}