{
  "type": "Feature",
  "properties": {
    "addr:full":"Grote Markt 31 Diest Vlaams-Brabant 3290",
    "addr:housenumber":"31",
    "addr:postcode":"3290",
    "addr:street":"Grote Markt",
    "iso:country":"BE",
    "sg:address":"Grote Markt 31",
    "sg:city":"Diest",
    "sg:classifiers":[
        {
            "category":"Community Center",
            "type":"Public Place"
        }
    ],
    "sg:phone":"+32 13 33 41 62",
    "sg:postcode":"3290",
    "sg:province":"Vlaams-Brabant",
    "sg:tags":[
        "medical"
    ],
    "wof:name":"C\u00e9sar De Paepe Vzw",
    "wof:placetype":"venue"
},
  "geometry": {"coordinates":[5.0505099297,50.9844055176],"type":"Point"}
}