{
  "type": "Feature",
  "properties": {
    "addr:full":"Tereken 70 Sint-niklaas Oost-Vlaanderen 9100",
    "addr:housenumber":"70",
    "addr:postcode":"9100",
    "addr:street":"Tereken",
    "iso:country":"BE",
    "sg:address":"Tereken 70",
    "sg:city":"Sint-niklaas",
    "sg:orig_category":"Installation \u00e9lectrique r\u00e9sidentielle",
    "sg:phone":"+32 3 777 96 98",
    "sg:postcode":"9100",
    "sg:province":"Oost-Vlaanderen",
    "wof:name":"Baetens",
    "wof:placetype":"venue"
},
  "geometry": {"coordinates":[4.1484279633,51.1527824402],"type":"Point"}
}