{
  "type": "Feature",
  "properties": {
    "iso:country":"BE",
    "sg:address":"Konijnenpijp 89",
    "sg:city":"Lommel",
    "sg:orig_category":"Taxis services sp\u00e9ciaux. Taxis. Messageries",
    "sg:phone":"+32 11 54 18 08",
    "sg:postcode":"3920",
    "sg:province":"Limburg",
    "wof:name":"Engelen Car Service",
    "wof:placetype":"venue"
},
  "geometry": {"coordinates":[5.341714859,51.2392539978],"type":"Point"}
}