{
  "type": "Feature",
  "properties": {
    "iso:country":"BE",
    "sg:address":"Rue Des Croisettes 21",
    "sg:city":"Verlaine",
    "sg:orig_category":"Kapsalons",
    "sg:phone":"+32 4 259 55 84",
    "sg:postcode":"4537",
    "sg:province":"Li\u00e8ge",
    "wof:name":"Coiffure Nicole",
    "wof:placetype":"venue"
},
  "geometry": {"coordinates":[5.3215808868,50.612071991],"type":"Point"}
}