{
  "type": "Feature",
  "properties": {
    "addr:full":"Schoolstraat 104 Beveren Oost-Vlaanderen 9120",
    "addr:housenumber":"104",
    "addr:postcode":"9120",
    "addr:street":"Schoolstraat",
    "iso:country":"BE",
    "sg:address":"Schoolstraat 104",
    "sg:city":"Beveren",
    "sg:orig_category":"V\u00e9hicules automobiles. Entretien and r\u00e9parations de voitures",
    "sg:phone":"+32 3 775 30 40",
    "sg:postcode":"9120",
    "sg:province":"Oost-Vlaanderen",
    "wof:name":"Carrosserie Bellon",
    "wof:placetype":"venue"
},
  "geometry": {"coordinates":[4.2784118652,51.223903656],"type":"Point"}
}