{
  "type": "Feature",
  "properties": {
    "addr:full":"Baron R. De Vironlaan 130 Dilbeek Vlaams-Brabant 1700",
    "addr:housenumber":"130",
    "addr:postcode":"1700",
    "addr:street":"Baron R. De Vironlaan",
    "iso:country":"BE",
    "sg:address":"Baron R. De Vironlaan 130",
    "sg:city":"Dilbeek",
    "sg:orig_category":"Banken and kredietinstellingen",
    "sg:phone":"+32 2 569 77 86",
    "sg:postcode":"1700",
    "sg:province":"Vlaams-Brabant",
    "wof:name":"Citibank",
    "wof:placetype":"venue"
},
  "geometry": {"coordinates":[4.2736959457,50.8457717896],"type":"Point"}
}