{
  "type": "Feature",
  "properties": {
    "iso:country":"BE",
    "sg:address":"Rue De La Haie Himbe 12",
    "sg:city":"Durbuy",
    "sg:classifiers":[
        {
            "category":"Real Estate",
            "subcategory":"Architect",
            "type":"Services"
        }
    ],
    "sg:phone":"+32 86 21 33 27",
    "sg:postcode":"6940",
    "sg:province":"Luxembourg",
    "wof:name":"Constant J",
    "wof:placetype":"venue"
},
  "geometry": {"coordinates":[5.4512310028,50.352142334],"type":"Point"}
}