{
  "type": "Feature",
  "properties": {
    "addr:full":"Rue De L'attrape 10 Bernissart Hainaut 7321",
    "addr:housenumber":"10",
    "addr:postcode":"7321",
    "addr:street":"Rue De L'Attrape",
    "iso:country":"BE",
    "sg:address":"Rue De L'attrape 10",
    "sg:city":"Bernissart",
    "sg:orig_category":"Sportclubs",
    "sg:phone":"+32 69 57 54 11",
    "sg:postcode":"7321",
    "sg:province":"Hainaut",
    "wof:name":"Corail Club Bernissart",
    "wof:placetype":"venue"
},
  "geometry": {"coordinates":[3.6722970009,50.479309082],"type":"Point"}
}