{
  "type": "Feature",
  "properties": {
    "iso:country":"BE",
    "sg:address":"Rijselstraat 3",
    "sg:city":"Roeselare",
    "sg:orig_category":"V\u00eatements sur mesure Fab",
    "sg:phone":"+32 51 20 42 55",
    "sg:postcode":"8800",
    "sg:province":"West-Vlaanderen",
    "wof:name":"Gerard Dewachtere",
    "wof:placetype":"venue"
},
  "geometry": {"coordinates":[3.1238429546,50.9408912659],"type":"Point"}
}