{
  "type": "Feature",
  "properties": {
    "iso:country":"BE",
    "sg:address":"Ketelaarstraat 12",
    "sg:city":"Beerse",
    "sg:classifiers":[
        {
            "category":"Wholesale",
            "subcategory":"Vending Machines",
            "type":"Manufacturing & Wholesale Goods"
        }
    ],
    "sg:phone":"+32 14 61 60 31",
    "sg:postcode":"2340",
    "sg:province":"Antwerpen",
    "sg:tags":[
        "filling",
        "sealing"
    ],
    "wof:name":"Sneyders Machineconstructie Nv",
    "wof:placetype":"venue"
},
  "geometry": {"coordinates":[4.8273501396,51.3252983093],"type":"Point"}
}