{
  "type": "Feature",
  "properties": {
    "addr:full":"116 Quai Des Ardennes 4031 Li\u00e8ge 116",
    "addr:housenumber":"116;116",
    "addr:postcode":"4031",
    "addr:street":"Quai Des Ardennes",
    "iso:country":"BE",
    "sg:address":"116",
    "sg:city":"Quai Des Ardennes 4031 Li\u00e8ge",
    "sg:classifiers":[
        {
            "category":"Manufacturing",
            "subcategory":"Tools & Machinery",
            "type":"Manufacturing & Wholesale Goods"
        }
    ],
    "sg:phone":"+32 4 365 39 68",
    "sg:postcode":"116",
    "sg:tags":[
        "metallurgy",
        "metalworking"
    ],
    "wof:name":"Fran\u00c7ois Leclercq Sprl",
    "wof:placetype":"venue"
},
  "geometry": {"coordinates":[5.6050748825,50.6152458191],"type":"Point"}
}