{
  "type": "Feature",
  "properties": {
    "addr:full":"Groenestraat 23 Kortrijk West-Vlaanderen 8501",
    "addr:housenumber":"23",
    "addr:postcode":"8501",
    "addr:street":"Groenestraat",
    "iso:country":"BE",
    "sg:address":"Groenestraat 23",
    "sg:city":"Kortrijk",
    "sg:orig_category":"Tuinen",
    "sg:phone":"+32 56 35 21 18",
    "sg:postcode":"8501",
    "sg:province":"West-Vlaanderen",
    "wof:name":"Lagae E",
    "wof:placetype":"venue"
},
  "geometry": {"coordinates":[3.2418251038,50.8589439392],"type":"Point"}
}