{
  "type": "Feature",
  "properties": {
    "iso:country":"BE",
    "sg:address":"Vlaanderenstraat 3",
    "sg:city":"Oostende",
    "sg:orig_category":"Ice-cream parlours",
    "sg:phone":"+32 59 50 38 26",
    "sg:postcode":"8400",
    "sg:province":"West-Vlaanderen",
    "wof:name":"Australian Home Made Ice-cream",
    "wof:placetype":"venue"
},
  "geometry": {"coordinates":[2.9170238972,51.2322845459],"type":"Point"}
}