{
  "type": "Feature",
  "properties": {
    "addr:full":"Place Fran\u00e7ois Bossuet 5 Bruxelles (saint-josse-ten-noode) Bruxelles-Capitale 1210",
    "addr:housenumber":"5",
    "addr:postcode":"1210",
    "addr:street":"Place Franc\u0327Ois Bossuet",
    "iso:country":"BE",
    "sg:address":"Place Fran\u00e7ois Bossuet 5",
    "sg:city":"Bruxelles (saint-josse-ten-noode)",
    "sg:classifiers":[
        {
            "category":"Education",
            "subcategory":"Dance Studio",
            "type":"Public Place"
        }
    ],
    "sg:phone":"+32 2 217 97 53",
    "sg:postcode":"1210",
    "sg:province":"Bruxelles-Capitale",
    "sg:tags":[
        "school",
        "dancing"
    ],
    "wof:name":"P\u00eale-m\u00eale (danse)",
    "wof:placetype":"venue"
},
  "geometry": {"coordinates":[4.373336792,50.854095459],"type":"Point"}
}