{
  "type": "Feature",
  "properties": {
    "iso:country":"BE",
    "sg:address":"Roeselaarsestraat 20",
    "sg:city":"Kortrijk",
    "sg:orig_category":"Woningbouw",
    "sg:phone":"+32 56 35 81 80",
    "sg:postcode":"8501",
    "sg:province":"West-Vlaanderen",
    "wof:name":"Tom Vandecaveye",
    "wof:placetype":"venue"
},
  "geometry": {"coordinates":[3.2240059376,50.8484268188],"type":"Point"}
}