{
  "type": "Feature",
  "properties": {
    "addr:full":"Avenue Des Chrysanth\u00c8mes 1 La Louviere Hainaut 7100",
    "addr:housenumber":"1",
    "addr:postcode":"7100",
    "addr:street":"Avenue Des Chrysanthe\u0300Mes",
    "iso:country":"BE",
    "sg:address":"Avenue Des Chrysanth\u00c8mes 1",
    "sg:city":"La Louviere",
    "sg:orig_category":"Bouwmaterialen Gh Plaatsen van vloer- and muurbekleding",
    "sg:phone":"+32 64 21 44 57",
    "sg:postcode":"7100",
    "sg:province":"Hainaut",
    "wof:name":"Christian Pint",
    "wof:placetype":"venue"
},
  "geometry": {"coordinates":[4.2028799057,50.4812660217],"type":"Point"}
}