{
  "type": "Feature",
  "properties": {
    "addr:full":"Distellaan 76 Middelkerke (westende) West-Vlaanderen 8434",
    "addr:housenumber":"76",
    "addr:postcode":"8434",
    "addr:street":"Distellaan",
    "iso:country":"BE",
    "sg:address":"Distellaan 76",
    "sg:city":"Middelkerke (westende)",
    "sg:classifiers":[
        {
            "category":"Food & Beverages",
            "subcategory":"Supermarket",
            "type":"Retail Goods"
        }
    ],
    "sg:phone":"+32 59 30 63 43",
    "sg:postcode":"8434",
    "sg:province":"West-Vlaanderen",
    "sg:tags":[
        "department",
        "store"
    ],
    "wof:name":"Spar",
    "wof:placetype":"venue"
},
  "geometry": {"coordinates":[2.7569050789,51.1488685608],"type":"Point"}
}