{
  "type": "Feature",
  "properties": {
    "addr:full":"Pollarebaan 88 Ninove Oost-Vlaanderen 9401",
    "addr:housenumber":"88",
    "addr:postcode":"9401",
    "addr:street":"Pollarebaan",
    "iso:country":"BE",
    "sg:address":"Pollarebaan 88",
    "sg:city":"Ninove",
    "sg:orig_category":"Boucheries",
    "sg:phone":"+32 54 33 61 50",
    "sg:postcode":"9401",
    "sg:province":"Oost-Vlaanderen",
    "wof:name":"Norbert Van Vreckem",
    "wof:placetype":"venue"
},
  "geometry": {"coordinates":[4.0219550133,50.8279533386],"type":"Point"}
}