{
  "type": "Feature",
  "properties": {
    "addr:full":"Rue Saint-hilaire 6 Malmedy/malmedy Li\u00e8ge 4960",
    "addr:housenumber":"6",
    "addr:postcode":"4960",
    "addr:street":"Rue Saint-Hilaire",
    "iso:country":"BE",
    "sg:address":"Rue Saint-hilaire 6",
    "sg:city":"Malmedy/malmedy",
    "sg:orig_category":"Meubelzaken, woning- and keukeninrichting",
    "sg:phone":"+32 80 33 88 47",
    "sg:postcode":"4960",
    "sg:province":"Li\u00e8ge",
    "wof:name":"Francis Marquet",
    "wof:placetype":"venue"
},
  "geometry": {"coordinates":[5.9989891052,50.4260444641],"type":"Point"}
}