{
  "type": "Feature",
  "properties": {
    "addr:full":"Rue Des Grands Joncs 18 Assesse Namur 5336",
    "addr:housenumber":"18",
    "addr:postcode":"5336",
    "addr:street":"Rue Des Grands Joncs",
    "iso:country":"BE",
    "sg:address":"Rue Des Grands Joncs 18",
    "sg:city":"Assesse",
    "sg:orig_category":"Drogisterijen",
    "sg:phone":"+32 83 65 60 48",
    "sg:postcode":"5336",
    "sg:province":"Namur",
    "wof:name":"Marie Campin",
    "wof:placetype":"venue"
},
  "geometry": {"coordinates":[4.9846668243,50.3978500366],"type":"Point"}
}