{
  "type": "Feature",
  "properties": {
    "addr:full":"Dr\u00e8ve Du Corps De Garde 130 Enghien (petit-enghien) Hainaut 7850",
    "addr:housenumber":"130",
    "addr:postcode":"7850",
    "addr:street":"Dre\u0300Ve Du Corps De Garde",
    "iso:country":"BE",
    "sg:address":"Dr\u00e8ve Du Corps De Garde 130",
    "sg:city":"Enghien (petit-enghien)",
    "sg:classifiers":[
        {
            "category":"Professional",
            "subcategory":"Engineering",
            "type":"Services"
        }
    ],
    "sg:phone":"+32 2 395 63 52",
    "sg:postcode":"7850",
    "sg:province":"Hainaut",
    "sg:tags":[
        "technical",
        "equipment",
        "offices-"
    ],
    "wof:name":"Engipro Bvba, Engineering & Project Consultancy Bvba",
    "wof:placetype":"venue"
},
  "geometry": {"coordinates":[4.0896701813,50.7001266479],"type":"Point"}
}