{
  "type": "Feature",
  "properties": {
    "addr:full":"Boulevard Emile Bockstael 22 Bruxelles Bruxelles-Capitale 1020",
    "addr:housenumber":"22",
    "addr:postcode":"1020",
    "addr:street":"Boulevard Emile Bockstael",
    "iso:country":"BE",
    "sg:address":"Boulevard Emile Bockstael 22",
    "sg:city":"Bruxelles",
    "sg:classifiers":[
        {
            "category":"Building & Trades",
            "subcategory":"Plumbing",
            "type":"Services"
        }
    ],
    "sg:phone":"+32 2 567 00 00",
    "sg:postcode":"1020",
    "sg:province":"Bruxelles-Capitale",
    "sg:tags":[
        "repair",
        "mainten",
        "-",
        "central",
        "heating"
    ],
    "wof:name":"M.c.m. Entreprise",
    "wof:placetype":"venue"
},
  "geometry": {"coordinates":[4.3433670998,50.870765686],"type":"Point"}
}