{
  "type": "Feature",
  "properties": {
    "addr:full":"Rue De L'amiti\u00c9 194 Herstal Li\u00e8ge 4041",
    "addr:housenumber":"194",
    "addr:postcode":"4041",
    "addr:street":"Rue De L'Amitie \u0301",
    "iso:country":"BE",
    "sg:address":"Rue De L'amiti\u00c9 194",
    "sg:city":"Herstal",
    "sg:orig_category":"M\u00e9decins and sp\u00e9cialistes",
    "sg:phone":"+32 4 278 68 67",
    "sg:postcode":"4041",
    "sg:province":"Li\u00e8ge",
    "wof:name":"Salvatore Valle",
    "wof:placetype":"venue"
},
  "geometry": {"coordinates":[5.5975718498,50.6840896606],"type":"Point"}
}