{
  "type": "Feature",
  "properties": {
    "addr:full":"Rue Haute 312 Brussel/bruxelles Bruxelles-Capitale 1000",
    "addr:housenumber":"312",
    "addr:postcode":"1000",
    "addr:street":"Rue Haute;/",
    "iso:country":"BE",
    "sg:address":"Rue Haute 312",
    "sg:city":"Brussel/bruxelles",
    "sg:orig_category":"Ordinateurs and \u00e9quipement informatique",
    "sg:phone":"+32 2 538 38 91",
    "sg:postcode":"1000",
    "sg:province":"Bruxelles-Capitale",
    "wof:name":"Talk Me",
    "wof:placetype":"venue"
},
  "geometry": {"coordinates":[4.3462381363,50.8345985413],"type":"Point"}
}