{
  "type": "Feature",
  "properties": {
    "iso:country":"BE",
    "sg:address":"Place Du Centenaire 6",
    "sg:city":"Honnelles",
    "sg:classifiers":[
        {
            "category":"Insurance",
            "subcategory":"Life Insurance",
            "type":"Services"
        }
    ],
    "sg:phone":"+32 65 75 93 30",
    "sg:postcode":"7387",
    "sg:province":"Hainaut",
    "sg:tags":[
        "assurance"
    ],
    "wof:name":"Bur. Abrassart-verbrugge",
    "wof:placetype":"venue"
},
  "geometry": {"coordinates":[3.6986029148,50.3679695129],"type":"Point"}
}