{
  "type": "Feature",
  "properties": {
    "iso:country":"BE",
    "sg:address":"Cathilleweg 46",
    "sg:city":"Jabbeke (stalhille)",
    "sg:classifiers":[
        {
            "category":"Banks & Credit Unions",
            "subcategory":"Investment Brokerage",
            "type":"Services"
        }
    ],
    "sg:phone":"+32 50 81 16 77",
    "sg:postcode":"8490",
    "sg:province":"West-Vlaanderen",
    "sg:tags":[
        "repair",
        "-",
        "installation",
        "sanitary",
        "article"
    ],
    "wof:name":"Depree-dewulf Bvba",
    "wof:placetype":"venue"
},
  "geometry": {"coordinates":[3.0755391121,51.2117500305],"type":"Point"}
}