{
  "type": "Feature",
  "properties": {
    "addr:full":"Dageraadstraat 32 Brussel/bruxelles Bruxelles-Capitale 1000",
    "addr:housenumber":"32",
    "addr:postcode":"1000",
    "addr:street":"Dageraadstraat;/",
    "iso:country":"BE",
    "sg:address":"Dageraadstraat 32",
    "sg:city":"Brussel/bruxelles",
    "sg:orig_category":"Artsen and specialisten",
    "sg:phone":"+32 2 647 49 54",
    "sg:postcode":"1000",
    "sg:province":"Bruxelles-Capitale",
    "wof:name":"Pierre Mahy",
    "wof:placetype":"venue"
},
  "geometry": {"coordinates":[4.3725748062,50.8193664551],"type":"Point"}
}