{
  "type": "Feature",
  "properties": {
    "addr:full":"Chauss\u00e9e De Bruxelles 15 Tournai Hainaut 7500",
    "addr:housenumber":"15",
    "addr:postcode":"7500",
    "addr:street":"Chausse\u0301E De Bruxelles",
    "iso:country":"BE",
    "sg:address":"Chauss\u00e9e De Bruxelles 15",
    "sg:city":"Tournai",
    "sg:classifiers":[
        {
            "category":"Autos & Motor Vehicles",
            "subcategory":"Fuel & Gas Station",
            "type":"Retail Goods"
        }
    ],
    "sg:phone":"+32 69 22 49 04",
    "sg:postcode":"7500",
    "sg:province":"Hainaut",
    "wof:name":"Aral Sa",
    "wof:placetype":"venue"
},
  "geometry": {"coordinates":[3.4057240486,50.6054725647],"type":"Point"}
}