{
  "type": "Feature",
  "properties": {
    "addr:full":"Lovenjoelsestraat 7ba Bierbeek Vlaams-Brabant 3360",
    "addr:housenumber":"7ba",
    "addr:postcode":"3360",
    "addr:street":"Lovenjoelsestraat",
    "iso:country":"BE",
    "sg:address":"Lovenjoelsestraat 7ba",
    "sg:city":"Bierbeek",
    "sg:orig_category":"M\u00e9decins and sp\u00e9cialistes",
    "sg:phone":"+32 16 46 16 65",
    "sg:postcode":"3360",
    "sg:province":"Vlaams-Brabant",
    "wof:name":"B. Shivalkar",
    "wof:placetype":"venue"
},
  "geometry": {"coordinates":[4.7862029076,50.8281402588],"type":"Point"}
}