{
  "type": "Feature",
  "properties": {
    "iso:country":"BE",
    "sg:address":"Rue Des Maquisards 7",
    "sg:city":"Bi\u00c8vre",
    "sg:classifiers":[
        {
            "category":"Arena",
            "subcategory":"Sports Club",
            "type":"Entertainment"
        }
    ],
    "sg:phone":"+32 61 53 39 33",
    "sg:postcode":"5555",
    "sg:province":"Namur",
    "sg:tags":[
        "terrain",
        "hors",
        "de",
        "installation",
        "sportifs"
    ],
    "wof:name":"Ent. Sp. Naome",
    "wof:placetype":"venue"
},
  "geometry": {"coordinates":[5.0882749557,49.9209976196],"type":"Point"}
}