{
  "type": "Feature",
  "properties": {
    "addr:full":"Mayerlei 80 Mortsel Antwerpen 2640",
    "addr:housenumber":"80",
    "addr:postcode":"2640",
    "addr:street":"Mayerlei",
    "iso:country":"BE",
    "sg:address":"Mayerlei 80",
    "sg:city":"Mortsel",
    "sg:classifiers":[
        {
            "category":"Food & Beverages",
            "subcategory":"Groceries & Convenience Stores",
            "type":"Retail Goods"
        }
    ],
    "sg:phone":"+32 3 455 37 81",
    "sg:postcode":"2640",
    "sg:province":"Antwerpen",
    "sg:tags":[
        "grocer"
    ],
    "wof:name":"Supra",
    "wof:placetype":"venue"
},
  "geometry": {"coordinates":[4.4732117653,51.1643028259],"type":"Point"}
}