{
  "type": "Feature",
  "properties": {
    "addr:full":"Vredelaan 41 Halle Vlaams-Brabant 1502",
    "addr:housenumber":"41;1502",
    "addr:street":"Vredelaan",
    "iso:country":"BE",
    "sg:address":"Vredelaan 41",
    "sg:city":"Halle",
    "sg:orig_category":"Gedistilleerde dranken and aperitieven Fab Wijnen Fab",
    "sg:phone":"+32 2 356 51 78",
    "sg:postcode":"1502",
    "sg:province":"Vlaams-Brabant",
    "wof:name":"Johnny Sterck",
    "wof:placetype":"venue"
},
  "geometry": {"coordinates":[4.2098379135,50.7155151367],"type":"Point"}
}