{
  "type": "Feature",
  "properties": {
    "iso:country":"BE",
    "sg:address":"Avenue Simonne 9",
    "sg:city":"Rhode-saint-gen\u00e8se",
    "sg:classifiers":[
        {
            "category":"Arts & Performance",
            "subcategory":"Theater",
            "type":"Entertainment"
        }
    ],
    "sg:phone":"+32 2 735 01 70",
    "sg:postcode":"1640",
    "sg:province":"Vlaams-Brabant",
    "sg:tags":[
        "theatrical",
        "agency"
    ],
    "wof:name":"Arti-show Sprl",
    "wof:placetype":"venue"
},
  "geometry": {"coordinates":[4.3924970627,50.7429084778],"type":"Point"}
}