{
  "type": "Feature",
  "properties": {
    "iso:country":"BE",
    "sg:address":"Rue Sous Le Ch\u00e2teau 1",
    "sg:city":"Rochefort",
    "sg:classifiers":[
        {
            "category":"Utilities",
            "subcategory":"Fuel Oil & Lpg",
            "type":"Services"
        }
    ],
    "sg:phone":"+32 84 21 11 87",
    "sg:postcode":"5580",
    "sg:province":"Namur",
    "wof:name":"Comburoche Sa",
    "wof:placetype":"venue"
},
  "geometry": {"coordinates":[5.2185649872,50.1570358276],"type":"Point"}
}