{
  "type": "Feature",
  "properties": {
    "addr:full":"Minnaersstraat 1 Veurne West-Vlaanderen 8630",
    "addr:housenumber":"1",
    "addr:postcode":"8630",
    "addr:street":"Minnaersstraat",
    "iso:country":"BE",
    "sg:address":"Minnaersstraat 1",
    "sg:city":"Veurne",
    "sg:orig_category":"Eleveurs and marchands de porcs. Eleveurs de bovins",
    "sg:phone":"+32 58 31 17 38",
    "sg:postcode":"8630",
    "sg:province":"West-Vlaanderen",
    "wof:name":"Joel Vandenbroucke",
    "wof:placetype":"venue"
},
  "geometry": {"coordinates":[2.7116999626,51.0457801819],"type":"Point"}
}