{
  "type": "Feature",
  "properties": {
    "addr:full":"Belleboslaan 32 Ichtegem West-Vlaanderen 8480",
    "addr:housenumber":"32",
    "addr:postcode":"8480",
    "addr:street":"Belleboslaan",
    "iso:country":"BE",
    "sg:address":"Belleboslaan 32",
    "sg:city":"Ichtegem",
    "sg:orig_category":"Activit\u00e9s d\u00b4action sociale sans h\u00e9bergement",
    "sg:phone":"+32 59 29 81 40",
    "sg:postcode":"8480",
    "sg:province":"West-Vlaanderen",
    "wof:name":"Rode Kruis Ichtegem",
    "wof:placetype":"venue"
},
  "geometry": {"coordinates":[3.0313260555,51.1327514648],"type":"Point"}
}