{
  "type": "Feature",
  "properties": {
    "iso:country":"BE",
    "sg:address":"Jacobuslei 90",
    "sg:city":"Brasschaat",
    "sg:classifiers":[
        {
            "category":"Health Services",
            "subcategory":"Health Practitioner",
            "type":"Services"
        }
    ],
    "sg:phone":"+32 3 664 47 77",
    "sg:postcode":"2930",
    "sg:province":"Antwerpen",
    "sg:tags":[
        "physiotherapist"
    ],
    "wof:name":"Vrints Nathalie",
    "wof:placetype":"venue"
},
  "geometry": {"coordinates":[4.4532527924,51.2950935364],"type":"Point"}
}