{
  "type": "Feature",
  "properties": {
    "iso:country":"BE",
    "sg:address":"Oude Ramp 23",
    "sg:city":"Neerpelt",
    "sg:orig_category":"Afbraak- and draineerwerken",
    "sg:phone":"+32 11 64 32 28",
    "sg:postcode":"3910",
    "sg:province":"Limburg",
    "wof:name":"T. Wijnen",
    "wof:placetype":"venue"
},
  "geometry": {"coordinates":[5.450717926,51.2352104187],"type":"Point"}
}