{
  "type": "Feature",
  "properties": {
    "iso:country":"BE",
    "sg:address":"Gentstraat 52",
    "sg:city":"Kaprijke (lembeke)",
    "sg:orig_category":"Non-Classified Establishments",
    "sg:phone":"+32 9 263 19 90",
    "sg:postcode":"9971",
    "sg:province":"Oost-Vlaanderen",
    "wof:name":"Lotus Bakeries Nv",
    "wof:placetype":"venue"
},
  "geometry": {"coordinates":[3.6373140812,51.1939888],"type":"Point"}
}