{
  "type": "Feature",
  "properties": {
    "addr:full":"Kapelstraat 54 Duffel Antwerpen 2570",
    "addr:housenumber":"54",
    "addr:postcode":"2570",
    "addr:street":"Kapelstraat",
    "iso:country":"BE",
    "sg:address":"Kapelstraat 54",
    "sg:city":"Duffel",
    "sg:classifiers":[
        {
            "category":"Professional",
            "subcategory":"Lawyer & Legal Services",
            "type":"Services"
        }
    ],
    "sg:phone":"+32 15 32 34 40",
    "sg:postcode":"2570",
    "sg:province":"Antwerpen",
    "wof:name":"Van Den Bergh D",
    "wof:placetype":"venue"
},
  "geometry": {"coordinates":[4.511177063,51.0930862427],"type":"Point"}
}