{
  "type": "Feature",
  "properties": {
    "iso:country":"BE",
    "sg:address":"Hoekskensstraat 118",
    "sg:city":"Lochristi",
    "sg:orig_category":"Plantes and fleurs Gr",
    "sg:phone":"+32 9 355 07 90",
    "sg:postcode":"9080",
    "sg:province":"Oost-Vlaanderen",
    "wof:name":"Van Rysselberghe A",
    "wof:placetype":"venue"
},
  "geometry": {"coordinates":[3.8353219032,51.1154403687],"type":"Point"}
}