{
  "type": "Feature",
  "properties": {
    "addr:full":"Rue Beckers 66 Etterbeek/etterbeek Bruxelles-Capitale 1040",
    "addr:housenumber":"66",
    "addr:postcode":"1040",
    "addr:street":"Rue Beckers",
    "iso:country":"BE",
    "sg:address":"Rue Beckers 66",
    "sg:city":"Etterbeek/etterbeek",
    "sg:classifiers":[
        {
            "category":"Manufacturing",
            "subcategory":"Textiles",
            "type":"Manufacturing & Wholesale Goods"
        }
    ],
    "sg:phone":"+32 2 649 24 30",
    "sg:postcode":"1040",
    "sg:province":"Bruxelles-Capitale",
    "wof:name":"Tissages Brumelaine",
    "wof:placetype":"venue"
},
  "geometry": {"coordinates":[4.3843331337,50.8280410767],"type":"Point"}
}