{
  "type": "Feature",
  "properties": {
    "addr:full":"Rue Kelle 41 Sint-pieters-woluwe/woluwe-saint-pierre Bruxelles-Capitale 1150",
    "addr:housenumber":"41",
    "addr:postcode":"1150",
    "addr:street":"Rue Kelle;/",
    "iso:country":"BE",
    "sg:address":"Rue Kelle 41",
    "sg:city":"Sint-pieters-woluwe/woluwe-saint-pierre",
    "sg:orig_category":"Production de films, t\u00e9l\u00e9films and vid\u00e9os",
    "sg:phone":"+32 2 770 03 81",
    "sg:postcode":"1150",
    "sg:province":"Bruxelles-Capitale",
    "wof:name":"Bernard Fourmarier",
    "wof:placetype":"venue"
},
  "geometry": {"coordinates":[4.439658165,50.83385849],"type":"Point"}
}