{
  "type": "Feature",
  "properties": {
    "addr:full":"Rue Du Village 14 Blegny Li\u00e8ge 4670",
    "addr:housenumber":"14",
    "addr:postcode":"4670",
    "addr:street":"Rue Du Village",
    "iso:country":"BE",
    "sg:address":"Rue Du Village 14",
    "sg:city":"Blegny",
    "sg:orig_category":"Installation de menuiserie en bois and plastique. Meubles D\u00e9taillants, Am\u00e9nagement de B\u00e2timents et d",
    "sg:phone":"+32 4 387 40 57",
    "sg:postcode":"4670",
    "sg:province":"Li\u00e8ge",
    "wof:name":"Collard Louis",
    "wof:placetype":"venue"
},
  "geometry": {"coordinates":[5.7720341682,50.6846733093],"type":"Point"}
}