{
  "type": "Feature",
  "properties": {
    "addr:full":"Karel Keymolenstraat 27 Lennik (sint-kwintens-lennik) Vlaams-Brabant 1750",
    "addr:housenumber":"27",
    "addr:postcode":"1750",
    "addr:street":"Karel Keymolenstraat",
    "iso:country":"BE",
    "sg:address":"Karel Keymolenstraat 27",
    "sg:city":"Lennik (sint-kwintens-lennik)",
    "sg:classifiers":[
        {
            "category":"Wholesale",
            "subcategory":"Fruits & Vegetables",
            "type":"Manufacturing & Wholesale Goods"
        }
    ],
    "sg:phone":"+32 2 532 16 67",
    "sg:postcode":"1750",
    "sg:province":"Vlaams-Brabant",
    "sg:tags":[
        "whol",
        "-"
    ],
    "wof:name":"De Smet J Bvba",
    "wof:placetype":"venue"
},
  "geometry": {"coordinates":[4.1523561478,50.8073348999],"type":"Point"}
}