{
  "type": "Feature",
  "properties": {
    "addr:full":"Driftweg 193 Bredene West-Vlaanderen 8450",
    "addr:housenumber":"193",
    "addr:postcode":"8450",
    "addr:street":"Driftweg",
    "iso:country":"BE",
    "sg:address":"Driftweg 193",
    "sg:city":"Bredene",
    "sg:orig_category":"M\u00e9decins and sp\u00e9cialistes",
    "sg:phone":"+32 59 32 36 42",
    "sg:postcode":"8450",
    "sg:province":"West-Vlaanderen",
    "wof:name":"Roger Van Den Berghe",
    "wof:placetype":"venue"
},
  "geometry": {"coordinates":[2.9603629112,51.2472496033],"type":"Point"}
}