{
  "type": "Feature",
  "properties": {
    "addr:full":"Rue Porte-basse 2ba Marche-en-famenne Luxembourg 6900",
    "addr:housenumber":"2ba",
    "addr:postcode":"6900",
    "addr:street":"Rue Porte-Basse",
    "iso:country":"BE",
    "sg:address":"Rue Porte-basse 2ba",
    "sg:city":"Marche-en-famenne",
    "sg:orig_category":"Beheer onroerend goed",
    "sg:phone":"+32 84 43 35 88",
    "sg:postcode":"6900",
    "sg:province":"Luxembourg",
    "wof:name":"Condrogest",
    "wof:placetype":"venue"
},
  "geometry": {"coordinates":[5.3443131447,50.2286224365],"type":"Point"}
}