{
  "type": "Feature",
  "properties": {
    "addr:full":"Vakekerkweg 166 Maldegem Oost-Vlaanderen 9990",
    "addr:housenumber":"166",
    "addr:postcode":"9990",
    "iso:country":"BE",
    "sg:address":"Vakekerkweg 166",
    "sg:city":"Maldegem",
    "sg:classifiers":[
        {
            "category":"Building & Trades",
            "subcategory":"Landscaping Services",
            "type":"Services"
        }
    ],
    "sg:phone":"+32 50 71 25 07",
    "sg:postcode":"9990",
    "sg:province":"Oost-Vlaanderen",
    "sg:tags":[
        "gardening",
        "garden",
        "maintenance"
    ],
    "wof:name":"De Bruycker G",
    "wof:placetype":"venue"
},
  "geometry": {"coordinates":[3.4348390102,51.2132759094],"type":"Point"}
}