{
  "type": "Feature",
  "properties": {
    "addr:full":"Bld Jacques Bertrand 20 Charleroi Hainaut 6000",
    "addr:housenumber":"20",
    "addr:postcode":"6000",
    "addr:street":"Bld Jacques Bertrand;Hainaut",
    "iso:country":"BE",
    "sg:address":"Bld Jacques Bertrand 20",
    "sg:city":"Charleroi",
    "sg:classifiers":[
        {
            "category":"Insurance",
            "subcategory":"Life Insurance",
            "type":"Services"
        }
    ],
    "sg:phone":"+32 71 30 40 15",
    "sg:postcode":"6000",
    "sg:province":"Hainaut",
    "sg:tags":[
        "assurance"
    ],
    "wof:name":"Pantano - Watelet",
    "wof:placetype":"venue"
},
  "geometry": {"coordinates":[4.441136837,50.4115447998],"type":"Point"}
}