{
  "type": "Feature",
  "properties": {
    "iso:country":"BE",
    "sg:address":"Rue De La V\u00c9nerie 14",
    "sg:city":"Watermaal-bosvoorde/watermael-boitsfort",
    "sg:classifiers":[
        {
            "category":"Restaurant",
            "type":"Food & Drink"
        }
    ],
    "sg:phone":"+32 2 673 43 79",
    "sg:postcode":"1170",
    "sg:province":"Bruxelles-Capitale",
    "wof:name":"Drina",
    "wof:placetype":"venue"
},
  "geometry": {"coordinates":[4.4190649986,50.7976150513],"type":"Point"}
}