{
  "type": "Feature",
  "properties": {
    "iso:country":"BE",
    "sg:address":"Panhovenstraat 46",
    "sg:city":"Peer",
    "sg:orig_category":"Diverse bouwafwerking and reiniging Gespecialiseerde residenti\u00eble bouw Woningbouw",
    "sg:phone":"+32 11 63 43 94",
    "sg:postcode":"3990",
    "sg:province":"Limburg",
    "wof:name":"Pinxten- De Wit",
    "wof:placetype":"venue"
},
  "geometry": {"coordinates":[5.4891200066,51.150718689],"type":"Point"}
}