{
  "type": "Feature",
  "properties": {
    "addr:full":"Kerkstraat 69 Vilvoorde Vlaams-Brabant 1800",
    "addr:housenumber":"69",
    "addr:postcode":"1800",
    "addr:street":"Kerkstraat",
    "iso:country":"BE",
    "sg:address":"Kerkstraat 69",
    "sg:city":"Vilvoorde",
    "sg:orig_category":"Apotheken",
    "sg:phone":"+32 2 251 12 25",
    "sg:postcode":"1800",
    "sg:province":"Vlaams-Brabant",
    "wof:name":"Louis Dewinkeler",
    "wof:placetype":"venue"
},
  "geometry": {"coordinates":[4.454559803,50.9281997681],"type":"Point"}
}