{
  "type": "Feature",
  "properties": {
    "addr:full":"Fritz Vinckelaan 78 Bredene West-Vlaanderen 8450",
    "addr:housenumber":"78",
    "addr:postcode":"8450",
    "addr:street":"Vinckelaan",
    "iso:country":"BE",
    "sg:address":"Fritz Vinckelaan 78",
    "sg:city":"Bredene",
    "sg:classifiers":[
        {
            "category":"Food & Beverages",
            "subcategory":"Supermarket",
            "type":"Retail Goods"
        }
    ],
    "sg:phone":"+32 59 32 42 04",
    "sg:postcode":"8450",
    "sg:province":"West-Vlaanderen",
    "sg:tags":[
        "department",
        "store"
    ],
    "wof:name":"Devooght",
    "wof:placetype":"venue"
},
  "geometry": {"coordinates":[2.9644269943,51.2259254456],"type":"Point"}
}