{
  "type": "Feature",
  "properties": {
    "addr:full":"Lierbaan 208 Putte Antwerpen 2580",
    "addr:housenumber":"208",
    "addr:postcode":"2580",
    "addr:street":"Lierbaan",
    "iso:country":"BE",
    "sg:address":"Lierbaan 208",
    "sg:city":"Putte",
    "sg:classifiers":[
        {
            "category":"Wholesale",
            "subcategory":"Plants",
            "type":"Manufacturing & Wholesale Goods"
        }
    ],
    "sg:phone":"+32 3 482 08 35",
    "sg:postcode":"2580",
    "sg:province":"Antwerpen",
    "sg:tags":[
        "whol",
        "flower",
        "-",
        "grower"
    ],
    "wof:name":"Van Roosbroeck Gebr",
    "wof:placetype":"venue"
},
  "geometry": {"coordinates":[4.6167750359,51.0842666626],"type":"Point"}
}