{
  "type": "Feature",
  "properties": {
    "iso:country":"BE",
    "sg:address":"Tervuursevest 17 Box 3",
    "sg:city":"Leuven (heverlee)",
    "sg:classifiers":[
        {
            "category":"Shopping",
            "subcategory":"Florist",
            "type":"Retail Goods"
        }
    ],
    "sg:phone":"+32 16 22 35 22",
    "sg:postcode":"3001",
    "sg:province":"Vlaams-Brabant",
    "wof:name":"Blauwe Lotus (de)",
    "wof:placetype":"venue"
},
  "geometry": {"coordinates":[4.6825327873,50.8765487671],"type":"Point"}
}