{
  "type": "Feature",
  "properties": {
    "addr:full":"Bredabaan 345 Brasschaat Antwerpen 2930",
    "addr:housenumber":"345",
    "addr:postcode":"2930",
    "addr:street":"Bredabaan",
    "iso:country":"BE",
    "sg:address":"Bredabaan 345",
    "sg:city":"Brasschaat",
    "sg:orig_category":"Herenkledingzaken",
    "sg:phone":"+32 3 651 66 79",
    "sg:postcode":"2930",
    "sg:province":"Antwerpen",
    "wof:name":"Caro Fashion",
    "wof:placetype":"venue"
},
  "geometry": {"coordinates":[4.4902739525,51.2893066406],"type":"Point"}
}