{
  "type": "Feature",
  "properties": {
    "iso:country":"BE",
    "sg:address":"De Paepestraat 79",
    "sg:city":"Herentals",
    "sg:orig_category":"M\u00e9decins and sp\u00e9cialistes",
    "sg:phone":"+32 14 22 31 75",
    "sg:postcode":"2200",
    "sg:province":"Antwerpen",
    "wof:name":"Luc Geysels",
    "wof:placetype":"venue"
},
  "geometry": {"coordinates":[4.8371968269,51.1738471985],"type":"Point"}
}