{
  "type": "Feature",
  "properties": {
    "addr:full":"Rue Du Heysel 3 Bruxelles Bruxelles-Capitale 1020",
    "addr:housenumber":"3",
    "addr:postcode":"1020",
    "addr:street":"Rue Du Heysel",
    "iso:country":"BE",
    "sg:address":"Rue Du Heysel 3",
    "sg:city":"Bruxelles",
    "sg:classifiers":[
        {
            "category":"Health Services",
            "subcategory":"Nursing And Care Facility",
            "type":"Services"
        }
    ],
    "sg:phone":"+32 2 475 55 11",
    "sg:postcode":"1020",
    "sg:province":"Bruxelles-Capitale",
    "sg:tags":[
        "home",
        "rest"
    ],
    "wof:name":"Centre De R\u00e9adaptation Heysel-g Brugmann",
    "wof:placetype":"venue"
},
  "geometry": {"coordinates":[4.3416152,50.8914222717],"type":"Point"}
}