{
  "type": "Feature",
  "properties": {
    "iso:country":"BE",
    "sg:address":"Hoevenstraat 19",
    "sg:city":"Herselt (ramsel)",
    "sg:classifiers":[
        {
            "category":"Building & Trades",
            "subcategory":"Construction",
            "type":"Services"
        }
    ],
    "sg:phone":"+32 16 69 94 43",
    "sg:postcode":"2230",
    "sg:province":"Antwerpen",
    "sg:tags":[
        "installation",
        "-",
        "central",
        "heating"
    ],
    "wof:name":"Peeters Roger En Zoon Bvba",
    "wof:placetype":"venue"
},
  "geometry": {"coordinates":[4.8205809593,51.0286178589],"type":"Point"}
}