{
  "type": "Feature",
  "properties": {
    "iso:country":"BE",
    "sg:address":"Rue De La Jonction 1",
    "sg:city":"Bertrix",
    "sg:orig_category":"Caf\u00e9s Restaurants Verhuur video and audio Warenhuizen",
    "sg:phone":"+32 61 41 38 20",
    "sg:postcode":"6880",
    "sg:province":"Luxembourg",
    "wof:name":"Shopping Center",
    "wof:placetype":"venue"
},
  "geometry": {"coordinates":[5.254483223,49.855342865],"type":"Point"}
}