{
  "type": "Feature",
  "properties": {
    "addr:full":"Brusselsesteenweg 214 Wetteren Oost-Vlaanderen 9230",
    "addr:housenumber":"214",
    "addr:postcode":"9230",
    "addr:street":"Brusselsesteenweg",
    "iso:country":"BE",
    "sg:address":"Brusselsesteenweg 214",
    "sg:city":"Wetteren",
    "sg:classifiers":[
        {
            "category":"Manufacturing",
            "subcategory":"Glass & Minerals",
            "type":"Manufacturing & Wholesale Goods"
        }
    ],
    "sg:phone":"+32 9 366 43 80",
    "sg:postcode":"9230",
    "sg:province":"Oost-Vlaanderen",
    "sg:tags":[
        "automobile",
        "-"
    ],
    "wof:name":"A.b.s.",
    "wof:placetype":"venue"
},
  "geometry": {"coordinates":[3.8451399803,50.9841995239],"type":"Point"}
}