{
  "type": "Feature",
  "properties": {
    "addr:full":"Heerweg-noord 2 Gent (zwijnaarde) Oost-Vlaanderen 9052",
    "addr:housenumber":"2",
    "addr:postcode":"9052",
    "addr:street":"Heerweg-Noord",
    "iso:country":"BE",
    "sg:address":"Heerweg-noord 2",
    "sg:city":"Gent (zwijnaarde)",
    "sg:classifiers":[
        {
            "category":"Bars & Pubs",
            "type":"Food & Drink"
        }
    ],
    "sg:phone":"+32 9 222 42 31",
    "sg:postcode":"9052",
    "sg:province":"Oost-Vlaanderen",
    "sg:tags":[
        "tavern"
    ],
    "wof:name":"Oud Gemeentehuis Taverne",
    "wof:placetype":"venue"
},
  "geometry": {"coordinates":[3.7096459866,51.0568847656],"type":"Point"}
}