{
  "type": "Feature",
  "properties": {
    "iso:country":"BE",
    "sg:address":"Rue Du Pont 6",
    "sg:city":"Incourt",
    "sg:orig_category":"Eleveurs de bovins",
    "sg:phone":"+32 10 88 83 21",
    "sg:postcode":"1315",
    "sg:province":"Brabant Wallon",
    "wof:name":"Paul Decloux",
    "wof:placetype":"venue"
},
  "geometry": {"coordinates":[4.8007178307,50.6805801392],"type":"Point"}
}