{
  "type": "Feature",
  "properties": {
    "addr:full":"Frankrijklei 16 Antwerpen Antwerpen 2000",
    "addr:housenumber":"16",
    "addr:postcode":"2000",
    "addr:street":"Frankrijklei",
    "iso:country":"BE",
    "sg:address":"Frankrijklei 16",
    "sg:city":"Antwerpen",
    "sg:classifiers":[
        {
            "category":"Insurance",
            "subcategory":"Insurance Agent",
            "type":"Services"
        }
    ],
    "sg:phone":"+32 3 227 38 37",
    "sg:postcode":"2000",
    "sg:province":"Antwerpen",
    "sg:tags":[
        "broker"
    ],
    "wof:name":"Metrofin Bvba",
    "wof:placetype":"venue"
},
  "geometry": {"coordinates":[4.4152951241,51.2189712524],"type":"Point"}
}