{
  "type": "Feature",
  "properties": {
    "addr:full":"Industrieterrein Veurne West-Vlaanderen 8630",
    "addr:postcode":"8630",
    "addr:street":"Industrieterrein Veurne West-Vlaanderen",
    "iso:country":"BE",
    "sg:address":"Industrieterrein",
    "sg:city":"Veurne",
    "sg:orig_category":"Solar protection - Outside",
    "sg:phone":"+32 58 31 37 67",
    "sg:postcode":"8630",
    "sg:province":"West-Vlaanderen",
    "wof:name":"Goens-lootvoet",
    "wof:placetype":"venue"
},
  "geometry": {"coordinates":[2.6617588997,51.072681427],"type":"Point"}
}