{
  "type": "Feature",
  "properties": {
    "addr:full":"Hoogstraat 55 Haaltert Oost-Vlaanderen 9450",
    "addr:housenumber":"55",
    "addr:postcode":"9450",
    "addr:street":"Hoogstraat",
    "iso:country":"BE",
    "sg:address":"Hoogstraat 55",
    "sg:city":"Haaltert",
    "sg:orig_category":"Imprimeries and copyshops",
    "sg:phone":"+32 53 83 44 45",
    "sg:postcode":"9450",
    "sg:province":"Oost-Vlaanderen",
    "wof:name":"Garage Schepens",
    "wof:placetype":"venue"
},
  "geometry": {"coordinates":[4.0038661957,50.8995094299],"type":"Point"}
}