{
  "type": "Feature",
  "properties": {
    "iso:country":"BE",
    "sg:address":"Venweg 51",
    "sg:city":"Tongeren",
    "sg:orig_category":"Fruitteelt Varkenskwekers",
    "sg:phone":"+32 12 23 78 64",
    "sg:postcode":"3700",
    "sg:province":"Limburg",
    "wof:name":"Erard Mouha",
    "wof:placetype":"venue"
},
  "geometry": {"coordinates":[5.500992775,50.7576828003],"type":"Point"}
}