{
  "type": "Feature",
  "properties": {
    "addr:full":"Leuvensestraat 13 Vilvoorde Vlaams-Brabant 1800",
    "addr:housenumber":"13",
    "addr:postcode":"1800",
    "addr:street":"Leuvensestraat",
    "iso:country":"BE",
    "sg:address":"Leuvensestraat 13",
    "sg:city":"Vilvoorde",
    "sg:orig_category":"Apotheken",
    "sg:phone":"+32 2 251 20 21",
    "sg:postcode":"1800",
    "sg:province":"Vlaams-Brabant",
    "wof:name":"Erik Goovaerts",
    "wof:placetype":"venue"
},
  "geometry": {"coordinates":[4.4250488281,50.9287948608],"type":"Point"}
}