{
  "type": "Feature",
  "properties": {
    "addr:full":"Avenue Du Silence 9 Bruxelles (uccle) Bruxelles-Capitale 1180",
    "addr:housenumber":"9",
    "addr:postcode":"1180",
    "addr:street":"Avenue Du Silence",
    "iso:country":"BE",
    "sg:address":"Avenue Du Silence 9",
    "sg:city":"Bruxelles (uccle)",
    "sg:classifiers":[
        {
            "category":"Building & Trades",
            "subcategory":"Construction",
            "type":"Services"
        }
    ],
    "sg:phone":"+32 2 376 19 73",
    "sg:postcode":"1180",
    "sg:province":"Bruxelles-Capitale",
    "sg:tags":[
        "installation",
        "-",
        "central",
        "heating"
    ],
    "wof:name":"Pci Sa",
    "wof:placetype":"venue"
},
  "geometry": {"coordinates":[4.3286361694,50.7846107483],"type":"Point"}
}