{
  "type": "Feature",
  "properties": {
    "addr:full":"Venwei 8 Wuustwezel Antwerpen 2990",
    "addr:housenumber":"8",
    "addr:postcode":"2990",
    "addr:street":"Venwei",
    "iso:country":"BE",
    "sg:address":"Venwei 8",
    "sg:city":"Wuustwezel",
    "sg:orig_category":"Tuinen",
    "sg:phone":"+32 3 669 73 07",
    "sg:postcode":"2990",
    "sg:province":"Antwerpen",
    "wof:name":"Tuinaanleg En Onderhoud Goetstouwers",
    "wof:placetype":"venue"
},
  "geometry": {"coordinates":[4.6038608551,51.3896026611],"type":"Point"}
}