{
  "type": "Feature",
  "properties": {
    "iso:country":"BE",
    "sg:address":"Liersebaan 183",
    "sg:city":"Zandhoven",
    "sg:orig_category":"Pharmaciens",
    "sg:phone":"+32 3 484 54 40",
    "sg:postcode":"2240",
    "sg:province":"Antwerpen",
    "wof:name":"Patrick Willems",
    "wof:placetype":"venue"
},
  "geometry": {"coordinates":[4.6530098915,51.2075691223],"type":"Point"}
}