{
  "type": "Feature",
  "properties": {
    "iso:country":"BE",
    "sg:address":"Perzikstraat 7",
    "sg:city":"Gent",
    "sg:classifiers":[
        {
            "category":"Personal",
            "subcategory":"Beauty Salon",
            "type":"Services"
        }
    ],
    "sg:phone":"+32 9 226 17 21",
    "sg:postcode":"9000",
    "sg:province":"Oost-Vlaanderen",
    "sg:tags":[
        "de",
        "coiffure"
    ],
    "wof:name":"Modern Salon",
    "wof:placetype":"venue"
},
  "geometry": {"coordinates":[3.6906869411,51.0634002686],"type":"Point"}
}