{
  "type": "Feature",
  "properties": {
    "iso:country":"BE",
    "sg:address":"Rue Van Winghen 1",
    "sg:city":"Bruxelles (anderlecht)",
    "sg:classifiers":[
        {
            "category":"Education",
            "subcategory":"School",
            "type":"Public Place"
        }
    ],
    "sg:phone":"+32 2 521 20 26",
    "sg:postcode":"1070",
    "sg:province":"Bruxelles-Capitale",
    "sg:tags":[
        "primary"
    ],
    "wof:name":"Enseignement Communal Anderlecht",
    "wof:placetype":"venue"
},
  "geometry": {"coordinates":[4.3288788795,50.8395500183],"type":"Point"}
}