{
  "type": "Feature",
  "properties": {
    "addr:full":"Troonstraat 75 Oostende West-Vlaanderen 8400",
    "addr:housenumber":"75",
    "addr:postcode":"8400",
    "addr:street":"Troonstraat",
    "iso:country":"BE",
    "sg:address":"Troonstraat 75",
    "sg:city":"Oostende",
    "sg:orig_category":"Slagers",
    "sg:phone":"+32 59 80 21 52",
    "sg:postcode":"8400",
    "sg:province":"West-Vlaanderen",
    "wof:name":"Johnny Dekien",
    "wof:placetype":"venue"
},
  "geometry": {"coordinates":[2.8880579472,51.2198829651],"type":"Point"}
}