{
  "type": "Feature",
  "properties": {
    "addr:full":"St-galmelstraat 247 Liedekerke Vlaams-Brabant 1770",
    "addr:housenumber":"247",
    "addr:postcode":"1770",
    "addr:street":"Vlaams-Brabant",
    "iso:country":"BE",
    "sg:address":"St-galmelstraat 247",
    "sg:city":"Liedekerke",
    "sg:orig_category":"Mat\u00e9riel de T\u00e9l\u00e9communication",
    "sg:phone":"+32 53 66 92 16",
    "sg:postcode":"1770",
    "sg:province":"Vlaams-Brabant",
    "wof:name":"Electro Depetter",
    "wof:placetype":"venue"
},
  "geometry": {"coordinates":[4.0844211578,50.8643569946],"type":"Point"}
}