{
  "type": "Feature",
  "properties": {
    "iso:country":"BE",
    "sg:address":"Av Everard 40",
    "sg:city":"Bruxelles",
    "sg:classifiers":[
        {
            "category":"Professional",
            "subcategory":"Engineering",
            "type":"Services"
        }
    ],
    "sg:phone":"+32 2 344 35 17",
    "sg:postcode":"1190",
    "sg:province":"Bruxelles-Capitale",
    "sg:tags":[
        "-",
        "household",
        "appliance",
        "machine",
        "equipment",
        "electrical",
        "mechanical",
        "electronic"
    ],
    "wof:name":"R Van Den Berg Sa",
    "wof:placetype":"venue"
},
  "geometry": {"coordinates":[4.3390197754,50.8159103394],"type":"Point"}
}