{
  "type": "Feature",
  "properties": {
    "iso:country":"BE",
    "sg:address":"Schalmei 16",
    "sg:city":"Schilde",
    "sg:orig_category":"Binnenhuisarchitecten",
    "sg:phone":"+32 3 383 54 92",
    "sg:postcode":"2970",
    "sg:province":"Antwerpen",
    "wof:name":"Bureau Dobbelaere",
    "wof:placetype":"venue"
},
  "geometry": {"coordinates":[4.5786790848,51.2573127747],"type":"Point"}
}