{
  "type": "Feature",
  "properties": {
    "addr:full":"Meensesteenweg 28 Moorslede West-Vlaanderen 8890",
    "addr:housenumber":"28",
    "addr:postcode":"8890",
    "addr:street":"Meensesteenweg",
    "iso:country":"BE",
    "sg:address":"Meensesteenweg 28",
    "sg:city":"Moorslede",
    "sg:orig_category":"Meubles D\u00e9taillants, Am\u00e9nagement de B\u00e2timents et de Cuisines",
    "sg:phone":"+32 56 50 94 16",
    "sg:postcode":"8890",
    "sg:province":"West-Vlaanderen",
    "wof:name":"Samyn",
    "wof:placetype":"venue"
},
  "geometry": {"coordinates":[3.1134700775,50.8889160156],"type":"Point"}
}