{
  "type": "Feature",
  "properties": {
    "iso:country":"BE",
    "sg:address":"Potterstraat 25",
    "sg:city":"Sint-gillis-waas (sint-pauwels)",
    "sg:classifiers":[
        {
            "category":"Building & Trades",
            "subcategory":"Landscaping Services",
            "type":"Services"
        }
    ],
    "sg:phone":"+32 3 605 46 87",
    "sg:postcode":"9170",
    "sg:province":"Oost-Vlaanderen",
    "sg:tags":[
        "architect",
        "landscape"
    ],
    "wof:name":"De Groene Ruimte",
    "wof:placetype":"venue"
},
  "geometry": {"coordinates":[4.0996642113,51.1924057007],"type":"Point"}
}