{
  "type": "Feature",
  "properties": {
    "iso:country":"BE",
    "sg:address":"Brakkebos 9",
    "sg:city":"Zoersel (halle)",
    "sg:classifiers":[
        {
            "category":"Health Services",
            "subcategory":"Health Practitioner",
            "type":"Services"
        }
    ],
    "sg:phone":"+32 3 384 37 28",
    "sg:postcode":"2980",
    "sg:province":"Antwerpen",
    "sg:tags":[
        "alternative",
        "therapy",
        "treatment"
    ],
    "wof:name":"Bernaerts D",
    "wof:placetype":"venue"
},
  "geometry": {"coordinates":[4.6488800049,51.2366867065],"type":"Point"}
}