{
  "type": "Feature",
  "properties": {
    "addr:full":"Nijverheidstraat 17 Lokeren Oost-Vlaanderen 9160",
    "addr:housenumber":"17",
    "addr:postcode":"9160",
    "addr:street":"Nijverheidstraat",
    "iso:country":"BE",
    "sg:address":"Nijverheidstraat 17",
    "sg:city":"Lokeren",
    "sg:orig_category":"Jeugdherbergen and berghutten",
    "sg:phone":"+32 9 348 64 27",
    "sg:postcode":"9160",
    "sg:province":"Oost-Vlaanderen",
    "wof:name":"Kasteel Verloren Bos",
    "wof:placetype":"venue"
},
  "geometry": {"coordinates":[3.9953970909,51.1110839844],"type":"Point"}
}