{
  "type": "Feature",
  "properties": {
    "addr:full":"Ketelbuizerstraat 21a Lichtervelde West-Vlaanderen 8810",
    "addr:housenumber":"21a",
    "addr:postcode":"8810",
    "addr:street":"Ketelbuizerstraat",
    "iso:country":"BE",
    "sg:address":"Ketelbuizerstraat 21a",
    "sg:city":"Lichtervelde",
    "sg:classifiers":[
        {
            "category":"Home & Garden",
            "subcategory":"Carpets & Floor Coverings",
            "type":"Retail Goods"
        }
    ],
    "sg:phone":"+32 51 72 21 56",
    "sg:postcode":"8810",
    "sg:province":"West-Vlaanderen",
    "sg:tags":[
        "layer",
        "mosaicists"
    ],
    "wof:name":"Baree J",
    "wof:placetype":"venue"
},
  "geometry": {"coordinates":[3.1278998852,51.0263900757],"type":"Point"}
}