{
  "type": "Feature",
  "properties": {
    "addr:full":"Marvie 162ba Bastogne Luxembourg 6600",
    "addr:postcode":"6600",
    "iso:country":"BE",
    "sg:address":"Marvie 162ba",
    "sg:city":"Bastogne",
    "sg:orig_category":"Herstellingen and onderhoud van auto's",
    "sg:phone":"+32 61 21 35 85",
    "sg:postcode":"6600",
    "sg:province":"Luxembourg",
    "wof:name":"Gerard Parthoens",
    "wof:placetype":"venue"
},
  "geometry": {"coordinates":[5.7455182076,49.9813766479],"type":"Point"}
}