{
  "type": "Feature",
  "properties": {
    "iso:country":"BE",
    "sg:address":"Kruisbulckstraat 15",
    "sg:city":"Deinze",
    "sg:orig_category":"Tuinen",
    "sg:phone":"+32 9 386 31 54",
    "sg:postcode":"9800",
    "sg:province":"Oost-Vlaanderen",
    "wof:name":"Cordons",
    "wof:placetype":"venue"
},
  "geometry": {"coordinates":[3.4869370461,51.0160865784],"type":"Point"}
}