{
  "type": "Feature",
  "properties": {
    "iso:country":"BE",
    "sg:address":"Steenweg Op Turnhout 87",
    "sg:city":"Merksplas",
    "sg:classifiers":[
        {
            "category":"Retail",
            "subcategory":"Auto Repair",
            "type":"Services"
        }
    ],
    "sg:phone":"+32 14 63 31 17",
    "sg:postcode":"2330",
    "sg:province":"Antwerpen",
    "sg:tags":[
        "garage"
    ],
    "wof:name":"Wiljan Autohandel Bvba",
    "wof:placetype":"venue"
},
  "geometry": {"coordinates":[4.8708610535,51.3516426086],"type":"Point"}
}