{
  "type": "Feature",
  "properties": {
    "iso:country":"BE",
    "sg:address":"Avenue De L'hippodrome 26",
    "sg:city":"Ixelles",
    "sg:orig_category":"Sportclubs",
    "sg:phone":"+32 2 648 27 61",
    "sg:postcode":"1050",
    "sg:province":"Bruxelles-Capitale",
    "wof:name":"Royal Alpa Ixelles",
    "wof:placetype":"venue"
},
  "geometry": {"coordinates":[4.3748569489,50.8230628967],"type":"Point"}
}