{
  "type": "Feature",
  "properties": {
    "addr:full":"Rue De La Cath\u00c9drale 79 Li\u00c8ge Li\u00e8ge 4000",
    "addr:housenumber":"79",
    "addr:postcode":"4000",
    "addr:street":"Rue De La Cathe\u0301Drale",
    "iso:country":"BE",
    "sg:address":"Rue De La Cath\u00c9drale 79",
    "sg:city":"Li\u00c8ge",
    "sg:classifiers":[
        {
            "category":"Shopping",
            "subcategory":"Clothing, Apparel, & Fashions",
            "type":"Retail Goods"
        }
    ],
    "sg:phone":"+32 4 232 05 50",
    "sg:postcode":"4000",
    "sg:province":"Li\u00e8ge",
    "sg:tags":[
        "v\u00eatements",
        "pour",
        "dame"
    ],
    "wof:name":"Maison H\u00c9t\u00c9roclite",
    "wof:placetype":"venue"
},
  "geometry": {"coordinates":[5.5734920502,50.6419029236],"type":"Point"}
}