{
  "type": "Feature",
  "properties": {
    "iso:country":"BE",
    "sg:address":"Rue Des Pierres \u00c0 Fusil 29",
    "sg:city":"Jurbise",
    "sg:classifiers":[
        {
            "category":"Cafe",
            "type":"Food & Drink"
        }
    ],
    "sg:phone":"+32 65 72 85 72",
    "sg:postcode":"7050",
    "sg:province":"Hainaut",
    "sg:tags":[
        "caf\u00e9s"
    ],
    "wof:name":"Caf\u00c9 Le Flor\u00c9al",
    "wof:placetype":"venue"
},
  "geometry": {"coordinates":[3.9314661026,50.5037765503],"type":"Point"}
}