{
  "type": "Feature",
  "properties": {
    "iso:country":"BE",
    "sg:address":"Rue Des Martyrs 37",
    "sg:city":"Verviers",
    "sg:orig_category":"D\u00e9corateurs d'int\u00e9rieur",
    "sg:phone":"+32 87 31 24 75",
    "sg:postcode":"4800",
    "sg:province":"Li\u00e8ge",
    "wof:name":"Michel De Cock",
    "wof:placetype":"venue"
},
  "geometry": {"coordinates":[5.8633670807,50.5913581848],"type":"Point"}
}