{
  "type": "Feature",
  "properties": {
    "iso:country":"BE",
    "sg:address":"Geldmunt 15",
    "sg:city":"Gent",
    "sg:classifiers":[
        {
            "category":"Insurance",
            "subcategory":"Insurance Agent",
            "type":"Services"
        }
    ],
    "sg:phone":"+32 9 223 36 82",
    "sg:postcode":"9000",
    "sg:province":"Oost-Vlaanderen",
    "sg:tags":[
        "broker"
    ],
    "wof:name":"Beek Jacqueline",
    "wof:placetype":"venue"
},
  "geometry": {"coordinates":[3.7285690308,51.0556335449],"type":"Point"}
}