{
  "type": "Feature",
  "properties": {
    "addr:full":"Floridastraat 62 Willebroek Antwerpen 2830",
    "addr:housenumber":"62",
    "addr:postcode":"2830",
    "addr:street":"Floridastraat",
    "iso:country":"BE",
    "sg:address":"Floridastraat 62",
    "sg:city":"Willebroek",
    "sg:orig_category":"Benzinestations and brandstoffen",
    "sg:phone":"+32 3 886 68 82",
    "sg:postcode":"2830",
    "sg:province":"Antwerpen",
    "wof:name":"Fa. Aerts",
    "wof:placetype":"venue"
},
  "geometry": {"coordinates":[4.3609790802,51.0585594177],"type":"Point"}
}