{
  "type": "Feature",
  "properties": {
    "addr:full":"Franz Schollaertstraat 32b23 Leuven Vlaams-Brabant 3010",
    "addr:housenumber":"32b23",
    "addr:postcode":"3010",
    "addr:street":"Franz Schollaertstraat",
    "iso:country":"BE",
    "sg:address":"Franz Schollaertstraat 32b23",
    "sg:city":"Leuven",
    "sg:orig_category":"Fotografen and fotostudio's",
    "sg:phone":"+32 16 35 62 11",
    "sg:postcode":"3010",
    "sg:province":"Vlaams-Brabant",
    "wof:name":"Christian Wolfs",
    "wof:placetype":"venue"
},
  "geometry": {"coordinates":[4.7304501534,50.889755249],"type":"Point"}
}