{
  "type": "Feature",
  "properties": {
    "iso:country":"BE",
    "sg:address":"Rue D\u00b4 Ensival 2",
    "sg:city":"Verviers",
    "sg:classifiers":[
        {
            "category":"Fast Food",
            "type":"Food & Drink"
        }
    ],
    "sg:phone":"+32 87 35 47 35",
    "sg:postcode":"4800",
    "sg:province":"Li\u00e8ge",
    "sg:tags":[
        "meeneem",
        "restaurant"
    ],
    "wof:name":"Friterie De La Gare",
    "wof:placetype":"venue"
},
  "geometry": {"coordinates":[5.8550300598,50.5887908936],"type":"Point"}
}