{
  "type": "Feature",
  "properties": {
    "addr:full":"Maandagstraat 25 Brakel (everbeek) Oost-Vlaanderen 9660",
    "addr:housenumber":"25",
    "addr:postcode":"9660",
    "addr:street":"Maandagstraat",
    "iso:country":"BE",
    "sg:address":"Maandagstraat 25",
    "sg:city":"Brakel (everbeek)",
    "sg:classifiers":[
        {
            "category":"Home & Garden",
            "subcategory":"Home Furnishings",
            "type":"Retail Goods"
        }
    ],
    "sg:phone":"+32 55 42 12 82",
    "sg:postcode":"9660",
    "sg:province":"Oost-Vlaanderen",
    "sg:tags":[
        "interior",
        "decoration"
    ],
    "wof:name":"Interieurprojecten Bradt Rudy",
    "wof:placetype":"venue"
},
  "geometry": {"coordinates":[3.7642250061,50.8031082153],"type":"Point"}
}