{
  "type": "Feature",
  "properties": {
    "addr:full":"Rue D\u00b4anvers 13 Verviers Li\u00e8ge 4800",
    "addr:housenumber":"13",
    "addr:postcode":"4800",
    "addr:street":"Rue D\u00b4Anvers",
    "iso:country":"BE",
    "sg:address":"Rue D\u00b4anvers 13",
    "sg:city":"Verviers",
    "sg:orig_category":"Baby- and kinderkleding",
    "sg:phone":"+32 87 22 52 53",
    "sg:postcode":"4800",
    "sg:province":"Li\u00e8ge",
    "wof:name":"Infor 400",
    "wof:placetype":"venue"
},
  "geometry": {"coordinates":[5.8543128967,50.5857048035],"type":"Point"}
}