{
  "type": "Feature",
  "properties": {
    "addr:full":"Kloosterstraat 28 Dilbeek Vlaams-Brabant 1702",
    "addr:housenumber":"28",
    "addr:postcode":"1702",
    "addr:street":"Kloosterstraat",
    "iso:country":"BE",
    "sg:address":"Kloosterstraat 28",
    "sg:city":"Dilbeek",
    "sg:orig_category":"Diverse grafische activiteiten Drukkerijen and copyshops Marktonderzoekbureaus Reclamebureaus",
    "sg:phone":"+32 2 466 56 41",
    "sg:postcode":"1702",
    "sg:province":"Vlaams-Brabant",
    "wof:name":"Vision & Factory",
    "wof:placetype":"venue"
},
  "geometry": {"coordinates":[4.2547101974,50.8658790588],"type":"Point"}
}