{
  "type": "Feature",
  "properties": {
    "iso:country":"BE",
    "sg:address":"Noorweegsekaai 15",
    "sg:city":"Brugge",
    "sg:orig_category":"Bouwmaterialen Gh",
    "sg:phone":"+32 50 33 62 32",
    "sg:postcode":"8000",
    "sg:province":"West-Vlaanderen",
    "wof:name":"Perquy Plastic",
    "wof:placetype":"venue"
},
  "geometry": {"coordinates":[3.2350389957,51.222366333],"type":"Point"}
}