{
  "type": "Feature",
  "properties": {
    "iso:country":"BE",
    "sg:address":"Rue De La Clef 54",
    "sg:city":"Fl\u00e9ron",
    "sg:classifiers":[
        {
            "category":"Health Services",
            "subcategory":"Dentist",
            "type":"Services"
        }
    ],
    "sg:phone":"+32 4 358 41 77",
    "sg:postcode":"4620",
    "sg:province":"Li\u00e8ge",
    "wof:name":"Roth S",
    "wof:placetype":"venue"
},
  "geometry": {"coordinates":[5.6950368881,50.6175193787],"type":"Point"}
}