{
  "type": "Feature",
  "properties": {
    "addr:full":"Genebroekstraat 94 Beverlo Limburg 3581",
    "addr:housenumber":"94",
    "addr:postcode":"3581",
    "addr:street":"Genebroekstraat",
    "iso:country":"BE",
    "sg:address":"Genebroekstraat 94",
    "sg:city":"Beverlo",
    "sg:orig_category":"Glass Instruments",
    "sg:phone":"+32 11 34 05 50",
    "sg:postcode":"3581",
    "sg:province":"Limburg",
    "wof:name":"Dingens - Bg B.v.b.a.",
    "wof:placetype":"venue"
},
  "geometry": {"coordinates":[5.2228298187,51.0881996155],"type":"Point"}
}