{
  "type": "Feature",
  "properties": {
    "addr:full":"Broekstraat 1 Buggenhout Oost-Vlaanderen 9255",
    "addr:housenumber":"1",
    "addr:postcode":"9255",
    "addr:street":"Broekstraat",
    "iso:country":"BE",
    "sg:address":"Broekstraat 1",
    "sg:city":"Buggenhout",
    "sg:classifiers":[
        {
            "category":"Shopping",
            "subcategory":"Baby Store",
            "type":"Retail Goods"
        }
    ],
    "sg:phone":"+32 52 35 59 09",
    "sg:postcode":"9255",
    "sg:province":"Oost-Vlaanderen",
    "sg:tags":[
        "article",
        "b\u00e9b\u00e9s",
        "pour"
    ],
    "wof:name":"J. De Backer",
    "wof:placetype":"venue"
},
  "geometry": {"coordinates":[4.1677398682,50.988368988],"type":"Point"}
}