{
  "type": "Feature",
  "properties": {
    "addr:full":"Rue G\u00e9n\u00e9ral Wangerm\u00e9e 40 Bruxelles (etterbeek) Bruxelles-Capitale 1040",
    "addr:housenumber":"40",
    "addr:postcode":"1040",
    "addr:street":"Rue Ge\u0301Ne\u0301Ral Wangerme\u0301E",
    "iso:country":"BE",
    "sg:address":"Rue G\u00e9n\u00e9ral Wangerm\u00e9e 40",
    "sg:city":"Bruxelles (etterbeek)",
    "sg:classifiers":[
        {
            "category":"Building & Trades",
            "subcategory":"Plumbing",
            "type":"Services"
        }
    ],
    "sg:phone":"+32 2 736 54 39",
    "sg:postcode":"1040",
    "sg:province":"Bruxelles-Capitale",
    "sg:tags":[
        "contractor"
    ],
    "wof:name":"Engelborghs Ets",
    "wof:placetype":"venue"
},
  "geometry": {"coordinates":[4.3942499161,50.8331451416],"type":"Point"}
}