{
  "type": "Feature",
  "properties": {
    "addr:full":"Avenue Coghen 45 Bruxelles (uccle) Bruxelles-Capitale 1180",
    "addr:housenumber":"45",
    "addr:postcode":"1180",
    "addr:street":"Avenue Coghen",
    "iso:country":"BE",
    "sg:address":"Avenue Coghen 45",
    "sg:city":"Bruxelles (uccle)",
    "sg:classifiers":[
        {
            "category":"Health Services",
            "subcategory":"Health Practitioner",
            "type":"Services"
        }
    ],
    "sg:phone":"+32 477 68 14 97",
    "sg:postcode":"1180",
    "sg:province":"Bruxelles-Capitale",
    "sg:tags":[
        "physiotherapist"
    ],
    "wof:name":"Mallefait Nicole",
    "wof:placetype":"venue"
},
  "geometry": {"coordinates":[4.3403902054,50.8121948242],"type":"Point"}
}