{
  "type": "Feature",
  "properties": {
    "addr:full":"Amersveldestraat 53 Kortemark West-Vlaanderen 8610",
    "addr:housenumber":"53",
    "addr:postcode":"8610",
    "addr:street":"Amersveldestraat",
    "iso:country":"BE",
    "sg:address":"Amersveldestraat 53",
    "sg:city":"Kortemark",
    "sg:orig_category":"Eleveurs de bovins. Eleveurs and marchands de porcs",
    "sg:phone":"+32 51 57 05 72",
    "sg:postcode":"8610",
    "sg:province":"West-Vlaanderen",
    "wof:name":"Ludovicus Aernoudt",
    "wof:placetype":"venue"
},
  "geometry": {"coordinates":[3.014950037,51.011341095],"type":"Point"}
}