{
  "type": "Feature",
  "properties": {
    "addr:full":"Rue De Petit-wasmes 276 Colfontaine Hainaut 7340",
    "addr:housenumber":"276",
    "addr:postcode":"7340",
    "addr:street":"Rue De Petit-Wasmes",
    "iso:country":"BE",
    "sg:address":"Rue De Petit-wasmes 276",
    "sg:city":"Colfontaine",
    "sg:orig_category":"Brood, gebak and snoepgoed",
    "sg:phone":"+32 65 67 26 16",
    "sg:postcode":"7340",
    "sg:province":"Hainaut",
    "wof:name":"Leon Fally",
    "wof:placetype":"venue"
},
  "geometry": {"coordinates":[3.8294711113,50.4034080505],"type":"Point"}
}