{
  "type": "Feature",
  "properties": {
    "addr:full":"Stationslaan 31 Tongeren Limburg 3700",
    "addr:housenumber":"31",
    "addr:postcode":"3700",
    "addr:street":"Stationslaan",
    "iso:country":"BE",
    "sg:address":"Stationslaan 31",
    "sg:city":"Tongeren",
    "sg:orig_category":"Centres de relaxation and bien-\u00eatre",
    "sg:phone":"+32 12 26 38 55",
    "sg:postcode":"3700",
    "sg:province":"Limburg",
    "wof:name":"City Sun Zonnestudio",
    "wof:placetype":"venue"
},
  "geometry": {"coordinates":[5.4723181725,50.7835083008],"type":"Point"}
}