{
  "type": "Feature",
  "properties": {
    "addr:full":"Rue Joseph Dekeyn 21 Sint-joost-ten-node/saint-joss Bruxelles-Capitale 1210",
    "addr:housenumber":"21",
    "addr:postcode":"1210",
    "addr:street":"Rue Joseph Dekeyn",
    "iso:country":"BE",
    "sg:address":"Rue Joseph Dekeyn 21",
    "sg:city":"Sint-joost-ten-node/saint-joss",
    "sg:orig_category":"Jardinage",
    "sg:phone":"+32 2 735 55 09",
    "sg:postcode":"1210",
    "sg:province":"Bruxelles-Capitale",
    "wof:name":"Alberty Guy",
    "wof:placetype":"venue"
},
  "geometry": {"coordinates":[4.3796420097,50.8511581421],"type":"Point"}
}