{
  "type": "Feature",
  "properties": {
    "iso:country":"BE",
    "sg:address":"Rue Laid Burmiat 3",
    "sg:city":"Louvainlaneuve",
    "sg:classifiers":[
        {
            "category":"Manufacturing",
            "subcategory":"Chemicals & Compounds",
            "type":"Manufacturing & Wholesale Goods"
        }
    ],
    "sg:phone":"+32 10 48 12 11",
    "sg:postcode":"1348",
    "sg:province":"Brabant Wallon",
    "sg:tags":[
        "pharmaceutical",
        "chemistry"
    ],
    "wof:name":"Solutia Europe Sa",
    "wof:placetype":"venue"
},
  "geometry": {"coordinates":[4.6171450615,50.670124054],"type":"Point"}
}