{
  "type": "Feature",
  "properties": {
    "iso:country":"BE",
    "sg:address":"Excelsiorlaan 3",
    "sg:city":"Zaventem",
    "sg:classifiers":[
        {
            "category":"Real Estate",
            "subcategory":"Surveying",
            "type":"Services"
        }
    ],
    "sg:phone":"+32 2 709 13 11",
    "sg:postcode":"1930",
    "sg:province":"Vlaams-Brabant",
    "sg:tags":[
        "raw",
        "material",
        "-",
        "plastic"
    ],
    "wof:name":"Evc Benelux-france",
    "wof:placetype":"venue"
},
  "geometry": {"coordinates":[4.4566020966,50.8813362122],"type":"Point"}
}