{
  "type": "Feature",
  "properties": {
    "addr:full":"Rue De La Gare 25a Lierneux Li\u00e8ge 4990",
    "addr:housenumber":"25a",
    "addr:postcode":"4990",
    "addr:street":"Rue De La Gare",
    "iso:country":"BE",
    "sg:address":"Rue De La Gare 25a",
    "sg:city":"Lierneux",
    "sg:orig_category":"Journaux. Fournitures de bureau. Tabac. Librairies",
    "sg:phone":"+32 80 31 82 30",
    "sg:postcode":"4990",
    "sg:province":"Li\u00e8ge",
    "wof:name":"Maison L'aurore",
    "wof:placetype":"venue"
},
  "geometry": {"coordinates":[5.7949409485,50.2858009338],"type":"Point"}
}