{
  "type": "Feature",
  "properties": {
    "iso:country":"BE",
    "sg:address":"Musettestraat 5",
    "sg:city":"Moeskroen/mouscron",
    "sg:orig_category":"Herstelling and restauratie van meubelen Meubelzaken, woning- and keukeninrichting",
    "sg:phone":"+32 56 34 88 69",
    "sg:postcode":"7700",
    "sg:province":"Hainaut",
    "wof:name":"Denis Lepere",
    "wof:placetype":"venue"
},
  "geometry": {"coordinates":[3.2323200703,50.7400932312],"type":"Point"}
}