{
  "type": "Feature",
  "properties": {
    "addr:full":"Postbus 86 Ronse Oost-Vlaanderen 9600",
    "addr:housenumber":"86",
    "addr:postcode":"9600",
    "addr:street":"Postbus",
    "iso:country":"BE",
    "sg:address":"Postbus 86",
    "sg:city":"Ronse",
    "sg:classifiers":[
        {
            "category":"Shopping",
            "subcategory":"Clothing, Apparel, & Fashions",
            "type":"Retail Goods"
        }
    ],
    "sg:phone":"+32 55 21 26 04",
    "sg:postcode":"9600",
    "sg:province":"Oost-Vlaanderen",
    "sg:tags":[
        "zipper"
    ],
    "wof:name":"Wallaert Benelux Nv",
    "wof:placetype":"venue"
},
  "geometry": {"coordinates":[3.5993049145,50.7470397949],"type":"Point"}
}