{
  "type": "Feature",
  "properties": {
    "addr:full":"Stapelhuisstraat 3 Leuven Vlaams-Brabant 3000",
    "addr:housenumber":"3",
    "addr:postcode":"3000",
    "addr:street":"Stapelhuisstraat",
    "iso:country":"BE",
    "sg:address":"Stapelhuisstraat 3",
    "sg:city":"Leuven",
    "sg:classifiers":[
        {
            "category":"Home & Garden",
            "subcategory":"Building Materials",
            "type":"Retail Goods"
        }
    ],
    "sg:phone":"+32 16 20 29 59",
    "sg:postcode":"3000",
    "sg:province":"Vlaams-Brabant",
    "sg:tags":[
        "veranda"
    ],
    "wof:name":"Van Velthem",
    "wof:placetype":"venue"
},
  "geometry": {"coordinates":[4.7053470612,50.8865280151],"type":"Point"}
}