{
  "type": "Feature",
  "properties": {
    "addr:full":"Frankrijklei 34 Antwerpen Antwerpen 2000",
    "addr:housenumber":"34",
    "addr:postcode":"2000",
    "addr:street":"Frankrijklei",
    "iso:country":"BE",
    "sg:address":"Frankrijklei 34",
    "sg:city":"Antwerpen",
    "sg:classifiers":[
        {
            "category":"Personal",
            "subcategory":"Beauty Salon",
            "type":"Services"
        }
    ],
    "sg:phone":"+32 3 231 84 01",
    "sg:postcode":"2000",
    "sg:province":"Antwerpen",
    "sg:tags":[
        "lady",
        "-",
        "hairdressing"
    ],
    "wof:name":"Kreatos",
    "wof:placetype":"venue"
},
  "geometry": {"coordinates":[4.4149842262,51.2183036804],"type":"Point"}
}