{
  "type": "Feature",
  "properties": {
    "iso:country":"BE",
    "sg:address":"Uitbreidingsstraat 11",
    "sg:city":"Westerlo (oevel)",
    "sg:classifiers":[
        {
            "category":"Food & Beverages",
            "subcategory":"Groceries & Convenience Stores",
            "type":"Retail Goods"
        }
    ],
    "sg:phone":"+32 14 23 41 08",
    "sg:postcode":"2260",
    "sg:province":"Antwerpen",
    "sg:tags":[
        "grocer"
    ],
    "wof:name":"Van Geel J",
    "wof:placetype":"venue"
},
  "geometry": {"coordinates":[4.9081068039,51.1379966736],"type":"Point"}
}