{
  "type": "Feature",
  "properties": {
    "iso:country":"BE",
    "sg:address":"Rue Victor Monoyer 25",
    "sg:city":"La Louviere",
    "sg:orig_category":"Traitements param\u00e9dicaux",
    "sg:phone":"+32 64 66 24 06",
    "sg:postcode":"7110",
    "sg:province":"Hainaut",
    "wof:name":"Petrone",
    "wof:placetype":"venue"
},
  "geometry": {"coordinates":[4.1505050659,50.4826698303],"type":"Point"}
}