{
  "type": "Feature",
  "properties": {
    "addr:full":"Dorpstraat 64 Zwijndrecht Antwerpen 2070",
    "addr:housenumber":"64",
    "addr:postcode":"2070",
    "addr:street":"Dorpstraat",
    "iso:country":"BE",
    "sg:address":"Dorpstraat 64",
    "sg:city":"Zwijndrecht",
    "sg:orig_category":"Begrafeniswezen",
    "sg:phone":"+32 3 252 71 62",
    "sg:postcode":"2070",
    "sg:province":"Antwerpen",
    "wof:name":"Rouwcentrum Van Bogaert",
    "wof:placetype":"venue"
},
  "geometry": {"coordinates":[4.3223648071,51.2189369202],"type":"Point"}
}