{
  "type": "Feature",
  "properties": {
    "addr:full":"Postweg 38 Lanaken Limburg 3620",
    "addr:housenumber":"38",
    "addr:postcode":"3620",
    "addr:street":"Postweg",
    "iso:country":"BE",
    "sg:address":"Postweg 38",
    "sg:city":"Lanaken",
    "sg:orig_category":"Slagers",
    "sg:phone":"+32 89 71 59 58",
    "sg:postcode":"3620",
    "sg:province":"Limburg",
    "wof:name":"Jos Leen",
    "wof:placetype":"venue"
},
  "geometry": {"coordinates":[5.6373062134,50.8957443237],"type":"Point"}
}