{
  "type": "Feature",
  "properties": {
    "addr:full":"Rue Fleur En Champs 100 Ham-sur-heure-nalinnes (ham-sur-heure) Hainaut 6120",
    "addr:housenumber":"100",
    "addr:postcode":"6120",
    "addr:street":"Rue Fleur En Champs",
    "iso:country":"BE",
    "sg:address":"Rue Fleur En Champs 100",
    "sg:city":"Ham-sur-heure-nalinnes (ham-sur-heure)",
    "sg:classifiers":[
        {
            "category":"Retail",
            "subcategory":"Veterinary Services",
            "type":"Services"
        }
    ],
    "sg:phone":"+32 71 21 76 81",
    "sg:postcode":"6120",
    "sg:province":"Hainaut",
    "sg:tags":[
        "veterinarian"
    ],
    "wof:name":"Pr\u00e9vost A",
    "wof:placetype":"venue"
},
  "geometry": {"coordinates":[4.3872900009,50.3219146729],"type":"Point"}
}