{
  "type": "Feature",
  "properties": {
    "iso:country":"BE",
    "sg:address":"Chauss\u00c9e De Ninove 603",
    "sg:city":"Anderlecht/anderlecht",
    "sg:orig_category":"M\u00e9decins and sp\u00e9cialistes",
    "sg:phone":"+32 2 411 00 57",
    "sg:postcode":"1070",
    "sg:province":"Bruxelles-Capitale",
    "wof:name":"Roger Dethier",
    "wof:placetype":"venue"
},
  "geometry": {"coordinates":[4.2994771004,50.8470840454],"type":"Point"}
}