{
  "type": "Feature",
  "properties": {
    "addr:full":"Korte Heistraat 50 Mechelen Antwerpen 2800",
    "addr:housenumber":"50",
    "addr:postcode":"2800",
    "addr:street":"Korte Heistraat",
    "iso:country":"BE",
    "sg:address":"Korte Heistraat 50",
    "sg:city":"Mechelen",
    "sg:classifiers":[
        {
            "category":"Professional",
            "subcategory":"Lawyer & Legal Services",
            "type":"Services"
        }
    ],
    "sg:phone":"+32 15 44 64 80",
    "sg:postcode":"2800",
    "sg:province":"Antwerpen",
    "wof:name":"Longr\u00e9e Veerle",
    "wof:placetype":"venue"
},
  "geometry": {"coordinates":[4.4702558517,51.0268745422],"type":"Point"}
}