{
  "type": "Feature",
  "properties": {
    "iso:country":"BE",
    "sg:address":"Hogebergstraat 47",
    "sg:city":"Hasselt",
    "sg:orig_category":"Woningbouw",
    "sg:phone":"+32 11 59 35 20",
    "sg:postcode":"3500",
    "sg:province":"Limburg",
    "wof:name":"C & C Constructies",
    "wof:placetype":"venue"
},
  "geometry": {"coordinates":[5.2985749245,50.9041557312],"type":"Point"}
}