{
  "type": "Feature",
  "properties": {
    "iso:country":"BE",
    "sg:address":"Pronkenbergstraat 29bc",
    "sg:city":"Kontich",
    "sg:orig_category":"Fotolaboratoria",
    "sg:phone":"+32 3 457 78 20",
    "sg:postcode":"2550",
    "sg:province":"Antwerpen",
    "wof:name":"Rainbow Color",
    "wof:placetype":"venue"
},
  "geometry": {"coordinates":[4.4674301147,51.1273384094],"type":"Point"}
}