{
  "type": "Feature",
  "properties": {
    "addr:full":"Tongersesteenweg 24/1 Riemst 012455943",
    "addr:housenumber":"24 / 1",
    "addr:postcode":"012455943",
    "addr:street":"Tongersesteenweg",
    "iso:country":"BE",
    "sg:address":"Tongersesteenweg 24/1",
    "sg:city":"Riemst",
    "sg:orig_category":"Huisdieren and benodigdheden Royal Canin",
    "sg:phone":"+32 12 45 59 43",
    "sg:postcode":"012455943",
    "wof:name":"Brepoels Eddy",
    "wof:placetype":"venue"
},
  "geometry": {"coordinates":[5.5969901085,50.8109016418],"type":"Point"}
}