{
  "type": "Feature",
  "properties": {
    "iso:country":"BE",
    "sg:address":"Carnotstraat 60",
    "sg:city":"Antwerpen",
    "sg:classifiers":[
        {
            "category":"Bars & Pubs",
            "type":"Food & Drink"
        }
    ],
    "sg:phone":"+32 3 234 06 88",
    "sg:postcode":"2060",
    "sg:province":"Antwerpen",
    "wof:name":"Nieuwe Carnot",
    "wof:placetype":"venue"
},
  "geometry": {"coordinates":[4.4245729446,51.2182388306],"type":"Point"}
}