{
  "type": "Feature",
  "properties": {
    "iso:country":"BE",
    "sg:address":"Krombeekseweg 40",
    "sg:city":"Poperinge",
    "sg:orig_category":"Woningbouw",
    "sg:phone":"+32 57 33 67 64",
    "sg:postcode":"8970",
    "sg:province":"West-Vlaanderen",
    "wof:name":"Gery Desender",
    "wof:placetype":"venue"
},
  "geometry": {"coordinates":[2.7121651173,50.8696212769],"type":"Point"}
}