{
  "type": "Feature",
  "properties": {
    "iso:country":"BE",
    "sg:address":"Chauss\u00e9e Brunehault 95",
    "sg:city":"Morlanwelz (morlanwelz-mariemont)",
    "sg:orig_category":"Non-Classified Establishments",
    "sg:phone":"+32 64 44 46 53",
    "sg:postcode":"7140",
    "sg:province":"Hainaut",
    "wof:name":"Night System Sonorisation",
    "wof:placetype":"venue"
},
  "geometry": {"coordinates":[4.2134900093,50.438999176],"type":"Point"}
}