{
  "type": "Feature",
  "properties": {
    "iso:country":"BE",
    "sg:address":"Groenestraat 19",
    "sg:city":"Zedelgem",
    "sg:classifiers":[
        {
            "category":"Shopping",
            "subcategory":"Clothing, Apparel, & Fashions",
            "type":"Retail Goods"
        }
    ],
    "sg:phone":"+32 50 20 84 09",
    "sg:postcode":"8210",
    "sg:province":"West-Vlaanderen",
    "sg:tags":[
        "v\u00eatements",
        "pour",
        "dame"
    ],
    "wof:name":"Boetiek Lut",
    "wof:placetype":"venue"
},
  "geometry": {"coordinates":[3.1375761032,51.1414718628],"type":"Point"}
}