{
  "type": "Feature",
  "properties": {
    "iso:country":"BE",
    "sg:address":"Rue De La Station 8",
    "sg:city":"Waterloo",
    "sg:orig_category":"Industri\u00eble wasserijen and droogkuis",
    "sg:phone":"+32 2 351 58 53",
    "sg:postcode":"1410",
    "sg:province":"Brabant Wallon",
    "wof:name":"Wash Center",
    "wof:placetype":"venue"
},
  "geometry": {"coordinates":[4.3958120346,50.7178077698],"type":"Point"}
}