{
  "type": "Feature",
  "properties": {
    "addr:full":"Rue De La Province 17 Li\u00e8ge 1 (li\u00e8ge 2) Li\u00e8ge 4020",
    "addr:housenumber":"17;1;2",
    "addr:postcode":"4020",
    "addr:street":"Rue De La Province",
    "iso:country":"BE",
    "sg:address":"Rue De La Province 17",
    "sg:city":"Li\u00e8ge 1 (li\u00e8ge 2)",
    "sg:classifiers":[
        {
            "category":"Health Services",
            "subcategory":"Health Practitioner",
            "type":"Services"
        }
    ],
    "sg:phone":"+32 4 343 84 94",
    "sg:postcode":"4020",
    "sg:province":"Li\u00e8ge",
    "sg:tags":[
        "physiotherapist"
    ],
    "wof:name":"Sacr\u00e9 Beno\u00eet",
    "wof:placetype":"venue"
},
  "geometry": {"coordinates":[5.5875787735,50.6431846619],"type":"Point"}
}