{
  "type": "Feature",
  "properties": {
    "iso:country":"BE",
    "sg:address":"Hoevenstraat 23",
    "sg:city":"Herselt (ramsel)",
    "sg:classifiers":[
        {
            "category":"Professional",
            "subcategory":"Accounting & Tax Preparation",
            "type":"Services"
        }
    ],
    "sg:phone":"+32 16 69 62 11",
    "sg:postcode":"2230",
    "sg:province":"Antwerpen",
    "sg:tags":[
        "bookkeeper"
    ],
    "wof:name":"Wittockx Bvba",
    "wof:placetype":"venue"
},
  "geometry": {"coordinates":[4.8206968307,51.0282478333],"type":"Point"}
}