{
  "type": "Feature",
  "properties": {
    "iso:country":"BE",
    "sg:address":"Meirenstraat 11",
    "sg:city":"Bornem",
    "sg:orig_category":"Sportclubs",
    "sg:phone":"+32 3 889 28 89",
    "sg:postcode":"2880",
    "sg:province":"Antwerpen",
    "wof:name":"W.c. Scheldevrienden",
    "wof:placetype":"venue"
},
  "geometry": {"coordinates":[4.2007040977,51.0780677795],"type":"Point"}
}