{
  "type": "Feature",
  "properties": {
    "addr:full":"Rue De La Roche 9 Bastogne Luxembourg 6600",
    "addr:housenumber":"9",
    "addr:postcode":"6600",
    "addr:street":"Rue De La Roche",
    "iso:country":"BE",
    "sg:address":"Rue De La Roche 9",
    "sg:city":"Bastogne",
    "sg:classifiers":[
        {
            "category":"Arena",
            "subcategory":"Sports Club",
            "type":"Entertainment"
        }
    ],
    "sg:phone":"+32 61 21 90 14",
    "sg:postcode":"6600",
    "sg:province":"Luxembourg",
    "sg:tags":[
        "federation"
    ],
    "wof:name":"F\u00e9d\u00e9ration Belge Des Caisses \u00e0 Savon",
    "wof:placetype":"venue"
},
  "geometry": {"coordinates":[5.7188777924,50.007648468],"type":"Point"}
}