{
  "type": "Feature",
  "properties": {
    "iso:country":"BE",
    "sg:address":"Grotekapellelaan 86",
    "sg:city":"Lede",
    "sg:orig_category":"ACCOUNTANTS Boekhouders",
    "sg:phone":"+32 53 80 06 86",
    "sg:postcode":"9340",
    "sg:province":"Oost-Vlaanderen",
    "wof:name":"Sam Brondeel",
    "wof:placetype":"venue"
},
  "geometry": {"coordinates":[3.9747669697,50.9604606628],"type":"Point"}
}