{
  "type": "Feature",
  "properties": {
    "iso:country":"BE",
    "sg:address":"Kunstdal 8",
    "sg:city":"Eeklo",
    "sg:orig_category":"Ramassage and traitement des d\u00e9chets m\u00e9nagers",
    "sg:phone":"+32 800 99 087",
    "sg:postcode":"9900",
    "sg:province":"Oost-Vlaanderen",
    "wof:name":"Belgium Recycle Network",
    "wof:placetype":"venue"
},
  "geometry": {"coordinates":[3.5295219421,51.1975975037],"type":"Point"}
}