{
  "type": "Feature",
  "properties": {
    "iso:country":"BE",
    "sg:address":"Durmenbaan 129",
    "sg:city":"Zele",
    "sg:orig_category":"Cr\u00e9meries",
    "sg:phone":"+32 52 44 56 98",
    "sg:postcode":"9240",
    "sg:province":"Oost-Vlaanderen",
    "wof:name":"Geerinck",
    "wof:placetype":"venue"
},
  "geometry": {"coordinates":[4.0482311249,51.083366394],"type":"Point"}
}