{
  "type": "Feature",
  "properties": {
    "iso:country":"BE",
    "sg:address":"Dokter Verhaeghestraat 99",
    "sg:city":"Oostende",
    "sg:orig_category":"Diverse persoonlijke diensten",
    "sg:phone":"+32 59 80 57 25",
    "sg:postcode":"8400",
    "sg:province":"West-Vlaanderen",
    "wof:name":"Jef Vandamme",
    "wof:placetype":"venue"
},
  "geometry": {"coordinates":[2.8962180614,51.218006134],"type":"Point"}
}