{
  "type": "Feature",
  "properties": {
    "iso:country":"BE",
    "sg:address":"Hooiestraat 13",
    "sg:city":"Wielsbeke (sint-baafs-vijve)",
    "sg:classifiers":[
        {
            "category":"Building & Trades",
            "subcategory":"Electrical",
            "type":"Services"
        }
    ],
    "sg:phone":"+32 56 60 16 68",
    "sg:postcode":"8710",
    "sg:province":"West-Vlaanderen",
    "sg:tags":[
        "electric",
        "-",
        "housewiring",
        "contractor"
    ],
    "wof:name":"Verhoye B",
    "wof:placetype":"venue"
},
  "geometry": {"coordinates":[3.4092509747,50.9153404236],"type":"Point"}
}