{
  "type": "Feature",
  "properties": {
    "iso:country":"BE",
    "sg:address":"Steenweg 310",
    "sg:city":"Nazareth",
    "sg:orig_category":"HUISBRANDOLIE",
    "sg:phone":"+32 9 385 41 65",
    "sg:postcode":"9810",
    "sg:province":"Oost-Vlaanderen",
    "wof:name":"Mariette Verliefden",
    "wof:placetype":"venue"
},
  "geometry": {"coordinates":[3.6666851044,50.9736442566],"type":"Point"}
}