{
  "type": "Feature",
  "properties": {
    "addr:full":"Bredabaan 483 Brasschaat Antwerpen 2930",
    "addr:housenumber":"483",
    "addr:postcode":"2930",
    "addr:street":"Bredabaan",
    "iso:country":"BE",
    "sg:address":"Bredabaan 483",
    "sg:city":"Brasschaat",
    "sg:classifiers":[
        {
            "category":"Deli",
            "type":"Food & Drink"
        }
    ],
    "sg:phone":"+32 3 651 86 76",
    "sg:postcode":"2930",
    "sg:province":"Antwerpen",
    "sg:tags":[
        "delicatessen"
    ],
    "wof:name":"(vercruysse) Rab Delicatessen",
    "wof:placetype":"venue"
},
  "geometry": {"coordinates":[4.4958600998,51.2940101624],"type":"Point"}
}