{
  "type": "Feature",
  "properties": {
    "addr:full":"Withof 1 Hoogstraten Antwerpen 2322",
    "addr:housenumber":"1",
    "addr:postcode":"2322",
    "addr:street":"Withof",
    "iso:country":"BE",
    "sg:address":"Withof 1",
    "sg:city":"Hoogstraten",
    "sg:orig_category":"Rundveehouders Varkenskwekers",
    "sg:phone":"+32 3 314 56 49",
    "sg:postcode":"2322",
    "sg:province":"Antwerpen",
    "wof:name":"Henri Vermeiren",
    "wof:placetype":"venue"
},
  "geometry": {"coordinates":[4.763384819,51.4160041809],"type":"Point"}
}