{
  "type": "Feature",
  "properties": {
    "addr:full":"Rue Ardenelle 35 Sombreffe Namur 5140",
    "addr:housenumber":"35",
    "addr:postcode":"5140",
    "addr:street":"Rue Ardenelle",
    "iso:country":"BE",
    "sg:address":"Rue Ardenelle 35",
    "sg:city":"Sombreffe",
    "sg:orig_category":"Rusthuizen and serviceflats",
    "sg:phone":"+32 71 88 82 84",
    "sg:postcode":"5140",
    "sg:province":"Namur",
    "wof:name":"Etrier D'argent",
    "wof:placetype":"venue"
},
  "geometry": {"coordinates":[4.6267590523,50.5600013733],"type":"Point"}
}