{
  "type": "Feature",
  "properties": {
    "addr:full":"Koning Albertlaan 3 Maaseik Limburg 3680",
    "addr:housenumber":"3",
    "addr:postcode":"3680",
    "addr:street":"Koning Albertlaan",
    "iso:country":"BE",
    "sg:address":"Koning Albertlaan 3",
    "sg:city":"Maaseik",
    "sg:classifiers":[
        {
            "category":"Personal",
            "subcategory":"Beauty Salon",
            "type":"Services"
        }
    ],
    "sg:phone":"+32 89 56 56 93",
    "sg:postcode":"3680",
    "sg:province":"Limburg",
    "sg:tags":[
        "lady",
        "-",
        "hairdressing"
    ],
    "wof:name":"Liliane",
    "wof:placetype":"venue"
},
  "geometry": {"coordinates":[5.7849740982,51.0963287354],"type":"Point"}
}