{
  "type": "Feature",
  "properties": {
    "iso:country":"BE",
    "sg:address":"Nassaustraat 21-25",
    "sg:city":"Antwerpen",
    "sg:orig_category":"Transports terrestres de voyageurs. Agences de voyages",
    "sg:phone":"+32 3 231 62 42",
    "sg:postcode":"2000",
    "sg:province":"Antwerpen",
    "wof:name":"Metropole",
    "wof:placetype":"venue"
},
  "geometry": {"coordinates":[4.4056792259,51.2304496765],"type":"Point"}
}