{
  "type": "Feature",
  "properties": {
    "addr:full":"Sas Vi Mol Antwerpen 2400",
    "addr:postcode":"2400",
    "addr:street":"Sas Vi",
    "iso:country":"BE",
    "sg:address":"Sas Vi",
    "sg:city":"Mol",
    "sg:classifiers":[
        {
            "category":"Bars & Pubs",
            "type":"Food & Drink"
        }
    ],
    "sg:phone":"+32 14 31 96 80",
    "sg:postcode":"2400",
    "sg:province":"Antwerpen",
    "wof:name":"Sas 6",
    "wof:placetype":"venue"
},
  "geometry": {"coordinates":[5.0938749313,51.2236251831],"type":"Point"}
}