{
  "type": "Feature",
  "properties": {
    "addr:full":"Tolstraat 100 Herzele Oost-Vlaanderen 9550",
    "addr:housenumber":"100",
    "addr:postcode":"9550",
    "addr:street":"Tolstraat;Oost-Vlaanderen",
    "iso:country":"BE",
    "sg:address":"Tolstraat 100",
    "sg:city":"Herzele",
    "sg:orig_category":"Avocats and conseillers juridiques",
    "sg:phone":"+32 54 50 22 23",
    "sg:postcode":"9550",
    "sg:province":"Oost-Vlaanderen",
    "wof:name":"Marc A. Van Den Berghe",
    "wof:placetype":"venue"
},
  "geometry": {"coordinates":[3.8791100979,50.8363304138],"type":"Point"}
}