{
  "type": "Feature",
  "properties": {
    "addr:full":"Jardin De Wallonie 7 Pont-a-celles Hainaut 6230",
    "addr:housenumber":"7",
    "addr:postcode":"6230",
    "addr:street":"Pont-A-Celles Hainaut",
    "iso:country":"BE",
    "sg:address":"Jardin De Wallonie 7",
    "sg:city":"Pont-a-celles",
    "sg:orig_category":"Sociale huisvestingsmaatschappijen",
    "sg:phone":"+32 71 84 37 73",
    "sg:postcode":"6230",
    "sg:province":"Hainaut",
    "wof:name":"Le Foyer Pont-\u00c0-cellois",
    "wof:placetype":"venue"
},
  "geometry": {"coordinates":[4.3707361221,50.507106781],"type":"Point"}
}