{
  "type": "Feature",
  "properties": {
    "addr:full":"Rue Van Artevelde 33 Brussel/bruxelles Bruxelles-Capitale 1000",
    "addr:housenumber":"33",
    "addr:postcode":"1000",
    "addr:street":"Rue Van Artevelde;/",
    "iso:country":"BE",
    "sg:address":"Rue Van Artevelde 33",
    "sg:city":"Brussel/bruxelles",
    "sg:orig_category":"S\u00e9curit\u00e9 sociale",
    "sg:phone":"+32 2 511 82 25",
    "sg:postcode":"1000",
    "sg:province":"Bruxelles-Capitale",
    "wof:name":"Mutualit\u00c9 Lib\u00c9rale",
    "wof:placetype":"venue"
},
  "geometry": {"coordinates":[4.3465270996,50.8483886719],"type":"Point"}
}