{
  "type": "Feature",
  "properties": {
    "iso:country":"BE",
    "sg:address":"Rue Des Bach\u00c8res 1",
    "sg:city":"Sambreville",
    "sg:orig_category":"Editeurs de journaux. Editeurs de revues and p\u00e9riodiques",
    "sg:phone":"+32 71 77 29 66",
    "sg:postcode":"5060",
    "sg:province":"Namur",
    "wof:name":"L'echo Editions Du Hainaut",
    "wof:placetype":"venue"
},
  "geometry": {"coordinates":[4.5887608528,50.4374885559],"type":"Point"}
}