{
  "type": "Feature",
  "properties": {
    "iso:country":"BE",
    "sg:address":"Chauss\u00e9e De Waterloo 359",
    "sg:city":"Bruxelles (saint-gilles)",
    "sg:classifiers":[
        {
            "category":"Shopping",
            "subcategory":"Florist",
            "type":"Retail Goods"
        }
    ],
    "sg:phone":"+32 2 539 45 54",
    "sg:postcode":"1060",
    "sg:province":"Bruxelles-Capitale",
    "wof:name":"Fleurs De Ma Campagne",
    "wof:placetype":"venue"
},
  "geometry": {"coordinates":[4.3533811569,50.8227882385],"type":"Point"}
}