{
  "type": "Feature",
  "properties": {
    "iso:country":"BE",
    "sg:address":"Emiel Vloorsstraat 2",
    "sg:city":"Antwerpen (hoboken)",
    "sg:classifiers":[
        {
            "category":"Retail",
            "subcategory":"Auto Repair",
            "type":"Services"
        }
    ],
    "sg:phone":"+32 3 238 60 00",
    "sg:postcode":"2660",
    "sg:province":"Antwerpen",
    "sg:tags":[
        "breakdown",
        "automobile",
        "-",
        "recovery"
    ],
    "wof:name":"Depannage 2000",
    "wof:placetype":"venue"
},
  "geometry": {"coordinates":[4.3691658974,51.1914215088],"type":"Point"}
}