{
  "type": "Feature",
  "properties": {
    "iso:country":"BE",
    "sg:address":"Drossaard Van Ophemlaan 45",
    "sg:city":"Zaventem",
    "sg:classifiers":[
        {
            "category":"Building & Trades",
            "subcategory":"Plumbing",
            "type":"Services"
        }
    ],
    "sg:phone":"+32 2 720 38 92",
    "sg:postcode":"1930",
    "sg:province":"Vlaams-Brabant",
    "sg:tags":[
        "repair",
        "mainten",
        "-",
        "central",
        "heating"
    ],
    "wof:name":"Van Tongelen D",
    "wof:placetype":"venue"
},
  "geometry": {"coordinates":[4.4827251434,50.8742828369],"type":"Point"}
}