{
  "type": "Feature",
  "properties": {
    "iso:country":"BE",
    "sg:address":"Wisselstraat 20",
    "sg:city":"Schilde",
    "sg:orig_category":"Boekhouders",
    "sg:phone":"+32 3 383 55 63",
    "sg:postcode":"2970",
    "sg:province":"Antwerpen",
    "wof:name":"Ronald Van Den Abeel",
    "wof:placetype":"venue"
},
  "geometry": {"coordinates":[4.587346077,51.2436943054],"type":"Point"}
}