{
  "type": "Feature",
  "properties": {
    "addr:full":"Diksmuidseweg 392 Ieper (boezinge) West-Vlaanderen 8904",
    "addr:housenumber":"392",
    "addr:postcode":"8904",
    "iso:country":"BE",
    "sg:address":"Diksmuidseweg 392",
    "sg:city":"Ieper (boezinge)",
    "sg:classifiers":[
        {
            "category":"Professional",
            "subcategory":"Art Services",
            "type":"Services"
        }
    ],
    "sg:phone":"+32 57 42 40 65",
    "sg:postcode":"8904",
    "sg:province":"West-Vlaanderen",
    "sg:tags":[
        "photography",
        "reporting",
        "-"
    ],
    "wof:name":"Fotografie Heidi Pype",
    "wof:placetype":"venue"
},
  "geometry": {"coordinates":[2.8584508896,50.8946685791],"type":"Point"}
}