{
  "type": "Feature",
  "properties": {
    "iso:country":"BE",
    "sg:address":"Walstraat 50c",
    "sg:city":"Gent",
    "sg:orig_category":"Formation and enseignement. Conseils en syst\u00e8mes informatiques",
    "sg:phone":"+32 9 330 89 16",
    "sg:postcode":"9050",
    "sg:province":"Oost-Vlaanderen",
    "wof:name":"Emmpact",
    "wof:placetype":"venue"
},
  "geometry": {"coordinates":[3.7473399639,51.0337104797],"type":"Point"}
}