{
  "type": "Feature",
  "properties": {
    "iso:country":"BE",
    "sg:address":"Brugsesteenweg 170",
    "sg:city":"Pittem",
    "sg:orig_category":"Non-Classified Establishments",
    "sg:phone":"+32 51 46 07 01",
    "sg:postcode":"8740",
    "sg:province":"West-Vlaanderen",
    "wof:name":"Ampe Steenbakkerij Nv",
    "wof:placetype":"venue"
},
  "geometry": {"coordinates":[3.2359199524,51.004699707],"type":"Point"}
}