{
  "type": "Feature",
  "properties": {
    "iso:country":"BE",
    "sg:address":"Kasteelstraat 37",
    "sg:city":"Lennik",
    "sg:orig_category":"Catering and organisatie van feesten Restaurants Ruimtes voor conferenties, recepties and feesten",
    "sg:phone":"+32 2 532 23 84",
    "sg:postcode":"1750",
    "sg:province":"Vlaams-Brabant",
    "wof:name":"Oud Gaasbeek",
    "wof:placetype":"venue"
},
  "geometry": {"coordinates":[4.2040581703,50.8000068665],"type":"Point"}
}