{
  "type": "Feature",
  "properties": {
    "iso:country":"BE",
    "sg:address":"Dorpsstraat 8ba",
    "sg:city":"Haacht",
    "sg:orig_category":"Diverse opleidingen and onderwijs",
    "sg:phone":"+32 16 60 89 15",
    "sg:postcode":"3150",
    "sg:province":"Vlaams-Brabant",
    "wof:name":"D'hondt Gerene Partn.",
    "wof:placetype":"venue"
},
  "geometry": {"coordinates":[4.6429648399,50.9429512024],"type":"Point"}
}