{
  "type": "Feature",
  "properties": {
    "addr:full":"Haasstrasse 6 Eupen Li\u00e8ge 4700",
    "addr:housenumber":"6",
    "addr:postcode":"4700",
    "addr:street":"Haasstrasse",
    "iso:country":"BE",
    "sg:address":"Haasstrasse 6",
    "sg:city":"Eupen",
    "sg:classifiers":[
        {
            "category":"Professional",
            "subcategory":"Testing Lab",
            "type":"Services"
        }
    ],
    "sg:phone":"+32 87 74 21 39",
    "sg:postcode":"4700",
    "sg:province":"Li\u00e8ge",
    "sg:tags":[
        "chemist"
    ],
    "wof:name":"Bosten-bocken A",
    "wof:placetype":"venue"
},
  "geometry": {"coordinates":[6.03729105,50.6239013672],"type":"Point"}
}