{
  "type": "Feature",
  "properties": {
    "addr:full":"Rue De Bouvy 142 La Louviere Hainaut 7100",
    "addr:housenumber":"142",
    "addr:postcode":"7100",
    "addr:street":"Rue De Bouvy",
    "iso:country":"BE",
    "sg:address":"Rue De Bouvy 142",
    "sg:city":"La Louviere",
    "sg:orig_category":"Quincailleries. Drogueries. Rev\u00eatements de sols and murs. Eclairage et \u00e9quipements du foyer",
    "sg:phone":"+32 64 22 28 34",
    "sg:postcode":"7100",
    "sg:province":"Hainaut",
    "wof:name":"Maison Peint Clair",
    "wof:placetype":"venue"
},
  "geometry": {"coordinates":[4.1816468239,50.4708061218],"type":"Point"}
}