{
  "type": "Feature",
  "properties": {
    "iso:country":"BE",
    "sg:address":"Alloenestraat 4",
    "sg:city":"Veurne",
    "sg:orig_category":"Varkenskwekers",
    "sg:phone":"+32 58 31 15 99",
    "sg:postcode":"8630",
    "sg:province":"West-Vlaanderen",
    "wof:name":"Willy Dequidt",
    "wof:placetype":"venue"
},
  "geometry": {"coordinates":[2.6873509884,51.0705757141],"type":"Point"}
}