{
  "type": "Feature",
  "properties": {
    "addr:full":"Chauss\u00e9e De Marche 464 Namur (erpent) Namur 5101",
    "addr:housenumber":"464",
    "addr:postcode":"5101",
    "addr:street":"Chausse\u0301E De Marche",
    "iso:country":"BE",
    "sg:address":"Chauss\u00e9e De Marche 464",
    "sg:city":"Namur (erpent)",
    "sg:classifiers":[
        {
            "category":"Retail",
            "subcategory":"Auto Repair",
            "type":"Services"
        }
    ],
    "sg:phone":"+32 81 30 02 14",
    "sg:postcode":"5101",
    "sg:province":"Namur",
    "sg:tags":[
        "garage"
    ],
    "wof:name":"Hesbois Sprl",
    "wof:placetype":"venue"
},
  "geometry": {"coordinates":[4.8977937698,50.4464569092],"type":"Point"}
}