{
  "type": "Feature",
  "properties": {
    "iso:country":"BE",
    "sg:address":"Paddevijverstraat 69",
    "sg:city":"Ieper",
    "sg:classifiers":[
        {
            "category":"Building & Trades",
            "subcategory":"Cleaning & Sanitation",
            "type":"Services"
        }
    ],
    "sg:phone":"+32 57 21 82 50",
    "sg:postcode":"8900",
    "sg:province":"West-Vlaanderen",
    "sg:tags":[
        "fa\u00e7ade",
        "maintenance"
    ],
    "wof:name":"Cherchye Bvba",
    "wof:placetype":"venue"
},
  "geometry": {"coordinates":[2.8849298954,50.8655891418],"type":"Point"}
}