{
  "type": "Feature",
  "properties": {
    "addr:full":"Constantin Meunierstraat 49 Leuven Vlaams-Brabant 3000",
    "addr:housenumber":"49",
    "addr:postcode":"3000",
    "addr:street":"Constantin Meunierstraat",
    "iso:country":"BE",
    "sg:address":"Constantin Meunierstraat 49",
    "sg:city":"Leuven",
    "sg:orig_category":"Maatschappelijke dienstverlening",
    "sg:phone":"+32 16 23 98 00",
    "sg:postcode":"3000",
    "sg:province":"Vlaams-Brabant",
    "wof:name":"Vclb-centrum",
    "wof:placetype":"venue"
},
  "geometry": {"coordinates":[4.7018737793,50.8706474304],"type":"Point"}
}