{
  "type": "Feature",
  "properties": {
    "iso:country":"BE",
    "sg:address":"Fort Sint-donaas 2",
    "sg:city":"Damme (lapscheure)",
    "sg:classifiers":[
        {
            "category":"Utilities",
            "subcategory":"Telephone",
            "type":"Services"
        }
    ],
    "sg:phone":"+32 50 50 19 49",
    "sg:postcode":"8340",
    "sg:province":"West-Vlaanderen",
    "sg:tags":[
        "karting",
        "accessory"
    ],
    "wof:name":"Route 49",
    "wof:placetype":"venue"
},
  "geometry": {"coordinates":[3.3415811062,51.2895584106],"type":"Point"}
}