{
  "type": "Feature",
  "properties": {
    "iso:country":"BE",
    "sg:address":"Hijftestraat 118",
    "sg:city":"Lochristi",
    "sg:orig_category":"Plantes and fleurs Gr",
    "sg:phone":"+32 9 355 67 54",
    "sg:postcode":"9080",
    "sg:province":"Oost-Vlaanderen",
    "wof:name":"Van Hoecke L",
    "wof:placetype":"venue"
},
  "geometry": {"coordinates":[3.8130979538,51.1071434021],"type":"Point"}
}