{
  "type": "Feature",
  "properties": {
    "iso:country":"BE",
    "sg:address":"Rue De M\u00c9rode 53",
    "sg:city":"Ronse/renaix",
    "sg:orig_category":"Installation de menuiserie en bois and plastique",
    "sg:phone":"+32 55 20 75 10",
    "sg:postcode":"9600",
    "sg:province":"Oost-Vlaanderen",
    "wof:name":"Alu-therm",
    "wof:placetype":"venue"
},
  "geometry": {"coordinates":[3.5992999077,50.7470397949],"type":"Point"}
}