{
  "type": "Feature",
  "properties": {
    "iso:country":"BE",
    "sg:address":"Viooltjesstraat 18",
    "sg:city":"Laakdal",
    "sg:orig_category":"Sportclubs Sportterreinen and installaties behalve sportcentra",
    "sg:phone":"+32 14 86 73 78",
    "sg:postcode":"2430",
    "sg:province":"Antwerpen",
    "wof:name":"F.c. Netezonen Eindhout",
    "wof:placetype":"venue"
},
  "geometry": {"coordinates":[5.0687851906,51.0857543945],"type":"Point"}
}