{
  "type": "Feature",
  "properties": {
    "addr:full":"Kleine Bruanestraat 20 Roeselare West-Vlaanderen 8800",
    "addr:housenumber":"20",
    "addr:postcode":"8800",
    "addr:street":"Bruanestraat",
    "iso:country":"BE",
    "sg:address":"Kleine Bruanestraat 20",
    "sg:city":"Roeselare",
    "sg:orig_category":"Woningbouw",
    "sg:phone":"+32 51 20 37 59",
    "sg:postcode":"8800",
    "sg:province":"West-Vlaanderen",
    "wof:name":"Wilfried Callens",
    "wof:placetype":"venue"
},
  "geometry": {"coordinates":[3.1362709999,50.9483032227],"type":"Point"}
}