{
  "type": "Feature",
  "properties": {
    "addr:full":"Kortrijksestraat 4 Kortrijk West-Vlaanderen 8501",
    "addr:housenumber":"4",
    "addr:postcode":"8501",
    "addr:street":"Kortrijksestraat",
    "iso:country":"BE",
    "sg:address":"Kortrijksestraat 4",
    "sg:city":"Kortrijk",
    "sg:classifiers":[
        {
            "category":"Personal",
            "subcategory":"Beauty Salon",
            "type":"Services"
        }
    ],
    "sg:phone":"+32 56 35 71 70",
    "sg:postcode":"8501",
    "sg:province":"West-Vlaanderen",
    "sg:tags":[
        "de",
        "coiffure"
    ],
    "wof:name":"Coiffure Eddy",
    "wof:placetype":"venue"
},
  "geometry": {"coordinates":[3.234621048,50.8424835205],"type":"Point"}
}