{
  "type": "Feature",
  "properties": {
    "addr:full":"Albertlaan 211b3 Vorst/forest Bruxelles-Capitale 1190",
    "addr:housenumber":"211b3",
    "addr:postcode":"1190",
    "addr:street":"Albertlaan;/ Forest",
    "iso:country":"BE",
    "sg:address":"Albertlaan 211b3",
    "sg:city":"Vorst/forest",
    "sg:orig_category":"Beheer onroerend goed",
    "sg:phone":"+32 2 346 55 08",
    "sg:postcode":"1190",
    "sg:province":"Bruxelles-Capitale",
    "wof:name":"R\u00c9sidence Auteuil",
    "wof:placetype":"venue"
},
  "geometry": {"coordinates":[4.3462710381,50.8165245056],"type":"Point"}
}