{
  "type": "Feature",
  "properties": {
    "addr:full":"Begijnhof 21 Aarschot Vlaams-Brabant 3200",
    "addr:housenumber":"21",
    "addr:postcode":"3200",
    "addr:street":"Begijnhof",
    "iso:country":"BE",
    "sg:address":"Begijnhof 21",
    "sg:city":"Aarschot",
    "sg:classifiers":[
        {
            "category":"Health Services",
            "subcategory":"Nursing And Care Facility",
            "type":"Services"
        }
    ],
    "sg:phone":"+32 16 55 07 00",
    "sg:postcode":"3200",
    "sg:province":"Vlaams-Brabant",
    "sg:tags":[
        "public"
    ],
    "wof:name":"O.c.m.w.",
    "wof:placetype":"venue"
},
  "geometry": {"coordinates":[4.8290100098,50.9853858948],"type":"Point"}
}