{
  "type": "Feature",
  "properties": {
    "iso:country":"BE",
    "sg:address":"Bd Du Gal Jacques 135",
    "sg:city":"Bruxelles",
    "sg:classifiers":[
        {
            "category":"Manufacturing",
            "subcategory":"Printing",
            "type":"Manufacturing & Wholesale Goods"
        }
    ],
    "sg:phone":"+32 2 649 39 54",
    "sg:postcode":"1050",
    "sg:province":"Bruxelles-Capitale",
    "sg:tags":[
        "publishing"
    ],
    "wof:name":"Bcd Express Sa",
    "wof:placetype":"venue"
},
  "geometry": {"coordinates":[4.3834681511,50.8198738098],"type":"Point"}
}