{
  "type": "Feature",
  "properties": {
    "addr:full":"Avenue Jules De Trooz 56 Bruxelles (woluwe-saint-pierre) Bruxelles-Capitale 1150",
    "addr:housenumber":"56",
    "addr:postcode":"1150",
    "addr:street":"Avenue Jules De Trooz",
    "iso:country":"BE",
    "sg:address":"Avenue Jules De Trooz 56",
    "sg:city":"Bruxelles (woluwe-saint-pierre)",
    "sg:classifiers":[
        {
            "category":"Shopping",
            "subcategory":"Books",
            "type":"Retail Goods"
        }
    ],
    "sg:phone":"+32 2 770 27 29",
    "sg:postcode":"1150",
    "sg:province":"Bruxelles-Capitale",
    "sg:tags":[
        "bookseller"
    ],
    "wof:name":"Papyrus Laf Sa",
    "wof:placetype":"venue"
},
  "geometry": {"coordinates":[4.4292230606,50.8368034363],"type":"Point"}
}