{
  "type": "Feature",
  "properties": {
    "addr:full":"Avenue De Jette 102 Bruxelles (koekelberg) Bruxelles-Capitale 1081",
    "addr:housenumber":"102",
    "addr:postcode":"1081",
    "addr:street":"Avenue De Jette",
    "iso:country":"BE",
    "sg:address":"Avenue De Jette 102",
    "sg:city":"Bruxelles (koekelberg)",
    "sg:classifiers":[
        {
            "category":"Retail",
            "subcategory":"Auto Repair",
            "type":"Services"
        }
    ],
    "sg:phone":"+32 2 426 79 51",
    "sg:postcode":"1081",
    "sg:province":"Bruxelles-Capitale",
    "sg:tags":[
        "garage"
    ],
    "wof:name":"Aris",
    "wof:placetype":"venue"
},
  "geometry": {"coordinates":[4.3275661469,50.8669700623],"type":"Point"}
}