{
  "type": "Feature",
  "properties": {
    "iso:country":"BE",
    "sg:address":"Donk 68",
    "sg:city":"Mol",
    "sg:classifiers":[
        {
            "category":"Shopping",
            "subcategory":"Bicycles & Sporting Goods",
            "type":"Retail Goods"
        }
    ],
    "sg:phone":"+32 14 32 14 36",
    "sg:postcode":"2400",
    "sg:province":"Antwerpen",
    "sg:tags":[
        "article",
        "de",
        "sport",
        "camping"
    ],
    "wof:name":"Runners Service",
    "wof:placetype":"venue"
},
  "geometry": {"coordinates":[5.1153149605,51.2107467651],"type":"Point"}
}