{
  "type": "Feature",
  "properties": {
    "iso:country":"BE",
    "sg:address":"Chemin Du Diable 3",
    "sg:city":"Helecine",
    "sg:orig_category":"Producteurs de fruits",
    "sg:phone":"+32 19 65 53 16",
    "sg:postcode":"1357",
    "sg:province":"Brabant Wallon",
    "wof:name":"Jacques Morre",
    "wof:placetype":"venue"
},
  "geometry": {"coordinates":[4.9968280792,50.7503585815],"type":"Point"}
}