{
  "type": "Feature",
  "properties": {
    "addr:full":"Rue Du Croiseau 52 Ittre Brabant Wallon 1460",
    "addr:housenumber":"52;1460",
    "addr:street":"Rue Du Croiseau",
    "iso:country":"BE",
    "sg:address":"Rue Du Croiseau 52",
    "sg:city":"Ittre",
    "sg:classifiers":[
        {
            "category":"Professional",
            "subcategory":"Printing & Photocopies",
            "type":"Services"
        }
    ],
    "sg:phone":"+32 67 84 20 72",
    "sg:postcode":"1460",
    "sg:province":"Brabant Wallon",
    "sg:tags":[
        "digital"
    ],
    "wof:name":"Berger G",
    "wof:placetype":"venue"
},
  "geometry": {"coordinates":[4.2486667633,50.6355934143],"type":"Point"}
}