{
  "type": "Feature",
  "properties": {
    "addr:full":"Legestraat 11 Ardooie West-Vlaanderen 8850",
    "addr:housenumber":"11",
    "addr:postcode":"8850",
    "addr:street":"Legestraat",
    "iso:country":"BE",
    "sg:address":"Legestraat 11",
    "sg:city":"Ardooie",
    "sg:orig_category":"Rundveehouders Varkenskwekers",
    "sg:phone":"+32 51 74 46 24",
    "sg:postcode":"8850",
    "sg:province":"West-Vlaanderen",
    "wof:name":"Luc Vanhaverbeke",
    "wof:placetype":"venue"
},
  "geometry": {"coordinates":[3.2225289345,50.9818840027],"type":"Point"}
}