{
  "type": "Feature",
  "properties": {
    "addr:full":"Avenue Du Touquet 7 Rixensart Brabant Wallon 1330",
    "addr:housenumber":"7",
    "addr:postcode":"1330",
    "addr:street":"Avenue Du Touquet;Wallon",
    "iso:country":"BE",
    "sg:address":"Avenue Du Touquet 7",
    "sg:city":"Rixensart",
    "sg:classifiers":[
        {
            "category":"Sports & Exercise",
            "subcategory":"Sports Center",
            "type":"Entertainment"
        }
    ],
    "sg:phone":"+32 2 653 26 23",
    "sg:postcode":"1330",
    "sg:province":"Brabant Wallon",
    "sg:tags":[
        "de",
        "fitness"
    ],
    "wof:name":"Centre Touquetligne",
    "wof:placetype":"venue"
},
  "geometry": {"coordinates":[4.5322909355,50.7059135437],"type":"Point"}
}