{
  "type": "Feature",
  "properties": {
    "iso:country":"BE",
    "sg:address":"Rue Joseph Lef\u00e8vre 68",
    "sg:city":"Charleroi (marchienne-au-pont)",
    "sg:classifiers":[
        {
            "category":"Building & Trades",
            "subcategory":"Construction",
            "type":"Services"
        }
    ],
    "sg:phone":"+32 71 51 85 38",
    "sg:postcode":"6030",
    "sg:province":"Hainaut",
    "sg:tags":[
        "paper",
        "hanger"
    ],
    "wof:name":"Plaire",
    "wof:placetype":"venue"
},
  "geometry": {"coordinates":[4.3927049637,50.4031295776],"type":"Point"}
}