{
  "type": "Feature",
  "properties": {
    "iso:country":"BE",
    "sg:address":"Rue Louvrex 83",
    "sg:city":"Li\u00c8ge",
    "sg:orig_category":"Werk and personeelsselectie",
    "sg:phone":"+32 4 222 41 41",
    "sg:postcode":"4000",
    "sg:province":"Li\u00e8ge",
    "wof:name":"Edit",
    "wof:placetype":"venue"
},
  "geometry": {"coordinates":[5.5642399788,50.6342468262],"type":"Point"}
}