{
  "type": "Feature",
  "properties": {
    "iso:country":"BE",
    "sg:address":"G. Vandenheuvelstr. 104",
    "sg:city":"Herselt",
    "sg:orig_category":"Kapsalons",
    "sg:phone":"+32 16 69 73 40",
    "sg:postcode":"2230",
    "sg:province":"Antwerpen",
    "wof:name":"Coiffure Marleen",
    "wof:placetype":"venue"
},
  "geometry": {"coordinates":[4.8341259956,51.029750824],"type":"Point"}
}