{
  "type": "Feature",
  "properties": {
    "addr:full":"Sint-katarinaplein 22 Hasselt Limburg 3500",
    "addr:housenumber":"22",
    "addr:postcode":"3500",
    "addr:street":"Sint-Katarinaplein",
    "iso:country":"BE",
    "sg:address":"Sint-katarinaplein 22",
    "sg:city":"Hasselt",
    "sg:orig_category":"Verplichte sociale verzekeringen",
    "sg:phone":"+32 11 22 73 42",
    "sg:postcode":"3500",
    "sg:province":"Limburg",
    "wof:name":"Christelijke Mutualiteit",
    "wof:placetype":"venue"
},
  "geometry": {"coordinates":[5.3499560356,50.9263687134],"type":"Point"}
}