{
  "type": "Feature",
  "properties": {
    "iso:country":"BE",
    "sg:address":"Museumlaan 101",
    "sg:city":"Tervuren",
    "sg:classifiers":[
        {
            "category":"Professional",
            "subcategory":"Accounting & Tax Preparation",
            "type":"Services"
        }
    ],
    "sg:phone":"+32 2 767 73 55",
    "sg:postcode":"3080",
    "sg:province":"Vlaams-Brabant",
    "sg:tags":[
        "bookkeeper"
    ],
    "wof:name":"Pintelon O",
    "wof:placetype":"venue"
},
  "geometry": {"coordinates":[4.5264120102,50.837387085],"type":"Point"}
}