{
  "type": "Feature",
  "properties": {
    "addr:full":"Lge Steenstraat 23 Kortrijk West-Vlaanderen 8500",
    "addr:housenumber":"23",
    "addr:postcode":"8500",
    "addr:street":"Lge Steenstraat",
    "iso:country":"BE",
    "sg:address":"Lge Steenstraat 23",
    "sg:city":"Kortrijk",
    "sg:orig_category":"Schoonheidssalons",
    "sg:phone":"+32 56 21 65 16",
    "sg:postcode":"8500",
    "sg:province":"West-Vlaanderen",
    "wof:name":"Yves Rocher",
    "wof:placetype":"venue"
},
  "geometry": {"coordinates":[3.2699429989,50.8273696899],"type":"Point"}
}