{
  "type": "Feature",
  "properties": {
    "iso:country":"BE",
    "sg:address":"Vermorgenstraat 39",
    "sg:city":"Sint-niklaas",
    "sg:orig_category":"Ladies' Knitwear",
    "sg:phone":"+32 3 776 11 05",
    "sg:postcode":"9100",
    "sg:province":"Oost-Vlaanderen",
    "wof:name":"Struyf En Zoon B.v.b.a.",
    "wof:placetype":"venue"
},
  "geometry": {"coordinates":[4.1456050873,51.1697731018],"type":"Point"}
}