{
  "type": "Feature",
  "properties": {
    "addr:full":"Rue Saint-pierre 12 Mouscron Hainaut 7700",
    "addr:housenumber":"12",
    "addr:postcode":"7700",
    "addr:street":"Rue Saint-Pierre",
    "iso:country":"BE",
    "sg:address":"Rue Saint-pierre 12",
    "sg:city":"Mouscron",
    "sg:classifiers":[
        {
            "category":"Shopping",
            "subcategory":"Bicycles & Sporting Goods",
            "type":"Retail Goods"
        }
    ],
    "sg:phone":"+32 56 33 21 14",
    "sg:postcode":"7700",
    "sg:province":"Hainaut",
    "sg:tags":[
        "sport",
        "-"
    ],
    "wof:name":"Intersport",
    "wof:placetype":"venue"
},
  "geometry": {"coordinates":[3.214204073,50.7426300049],"type":"Point"}
}