{
  "type": "Feature",
  "properties": {
    "addr:full":"Diestsestraat 66 Leuven Vlaams-Brabant 3000",
    "addr:housenumber":"66",
    "addr:postcode":"3000",
    "addr:street":"Diestsestraat",
    "iso:country":"BE",
    "sg:address":"Diestsestraat 66",
    "sg:city":"Leuven",
    "sg:classifiers":[
        {
            "category":"Government",
            "subcategory":"Post Office",
            "type":"Public Place"
        }
    ],
    "sg:phone":"+32 16 23 84 86",
    "sg:postcode":"3000",
    "sg:province":"Vlaams-Brabant",
    "sg:tags":[
        "poster"
    ],
    "wof:name":"Expo",
    "wof:placetype":"venue"
},
  "geometry": {"coordinates":[4.7059950829,50.8802947998],"type":"Point"}
}