{
  "type": "Feature",
  "properties": {
    "addr:full":"Steenweg 92 Lanaken Limburg 3621",
    "addr:housenumber":"92",
    "addr:postcode":"3621",
    "addr:street":"Steenweg",
    "iso:country":"BE",
    "sg:address":"Steenweg 92",
    "sg:city":"Lanaken",
    "sg:orig_category":"Installation de menuiserie m\u00e9tallique. Mat\u00e9riaux de construction Installation de menuiserie en bois ",
    "sg:phone":"+32 89 71 44 37",
    "sg:postcode":"3621",
    "sg:province":"Limburg",
    "wof:name":"Vliegen Plastics",
    "wof:placetype":"venue"
},
  "geometry": {"coordinates":[5.6850662231,50.9198951721],"type":"Point"}
}