{
  "type": "Feature",
  "properties": {
    "addr:full":"Dendermondebaan 94 Zele Oost-Vlaanderen 9240",
    "addr:housenumber":"94",
    "addr:postcode":"9240",
    "addr:street":"Dendermondebaan",
    "iso:country":"BE",
    "sg:address":"Dendermondebaan 94",
    "sg:city":"Zele",
    "sg:orig_category":"Rev\u00eatements pour sols and murs. Peinture",
    "sg:phone":"+32 52 44 50 49",
    "sg:postcode":"9240",
    "sg:province":"Oost-Vlaanderen",
    "wof:name":"Baert M. & M.",
    "wof:placetype":"venue"
},
  "geometry": {"coordinates":[4.0499978065,51.0656318665],"type":"Point"}
}