{
  "type": "Feature",
  "properties": {
    "iso:country":"BE",
    "sg:address":"Boulevard Anspach 66",
    "sg:city":"Brussel/bruxelles",
    "sg:orig_category":"Biens d'occasion. Ordinateurs and \u00e9quipement informatique",
    "sg:phone":"+32 2 511 21 28",
    "sg:postcode":"1000",
    "sg:province":"Bruxelles-Capitale",
    "wof:name":"Install 1 & 2",
    "wof:placetype":"venue"
},
  "geometry": {"coordinates":[4.3503890038,50.8488082886],"type":"Point"}
}