{
  "type": "Feature",
  "properties": {
    "iso:country":"BE",
    "sg:address":"Rue Du Hameau 187",
    "sg:city":"Sint-genesius-rode/rhode-saint-genese",
    "sg:orig_category":"Journaux. Tabac",
    "sg:phone":"+32 2 358 38 69",
    "sg:postcode":"1640",
    "sg:province":"Vlaams-Brabant",
    "wof:name":"Huis De Hoek",
    "wof:placetype":"venue"
},
  "geometry": {"coordinates":[4.3721032143,50.7389945984],"type":"Point"}
}