{
  "type": "Feature",
  "properties": {
    "addr:full":"Ooievaarstraat 13 Tienen Vlaams-Brabant 3300",
    "addr:housenumber":"13",
    "addr:postcode":"3300",
    "addr:street":"Ooievaarstraat",
    "iso:country":"BE",
    "sg:address":"Ooievaarstraat 13",
    "sg:city":"Tienen",
    "sg:classifiers":[
        {
            "category":"Health Services",
            "subcategory":"Dentist",
            "type":"Services"
        }
    ],
    "sg:phone":"+32 16 81 94 52",
    "sg:postcode":"3300",
    "sg:province":"Vlaams-Brabant",
    "wof:name":"Vermoote Patrick",
    "wof:placetype":"venue"
},
  "geometry": {"coordinates":[4.9395952225,50.8073577881],"type":"Point"}
}