{
  "type": "Feature",
  "properties": {
    "iso:country":"BE",
    "sg:address":"Moleneinde 21",
    "sg:city":"Ravels",
    "sg:orig_category":"Travail and traitement du bois",
    "sg:phone":"+32 14 65 95 38",
    "sg:postcode":"2381",
    "sg:province":"Antwerpen",
    "wof:name":"Bols & Zoon",
    "wof:placetype":"venue"
},
  "geometry": {"coordinates":[5.0126228333,51.4026794434],"type":"Point"}
}