{
  "type": "Feature",
  "properties": {
    "iso:country":"BE",
    "sg:address":"Vlinderlaan 1d",
    "sg:city":"Bierbeek",
    "sg:orig_category":"Cr\u00e9dits divers",
    "sg:postcode":"3360",
    "sg:province":"Vlaams-Brabant",
    "wof:name":"Bancontact-mister Cash",
    "wof:placetype":"venue"
},
  "geometry": {"coordinates":[4.7468290329,50.8650817871],"type":"Point"}
}