{
  "type": "Feature",
  "properties": {
    "addr:full":"Vennestraat 22 Wetteren Oost-Vlaanderen 9230",
    "addr:housenumber":"22",
    "addr:postcode":"9230",
    "addr:street":"Vennestraat",
    "iso:country":"BE",
    "sg:address":"Vennestraat 22",
    "sg:city":"Wetteren",
    "sg:classifiers":[
        {
            "category":"Recreation",
            "subcategory":"Gun Range",
            "type":"Entertainment"
        }
    ],
    "sg:phone":"+32 9 369 11 41",
    "sg:postcode":"9230",
    "sg:province":"Oost-Vlaanderen",
    "sg:tags":[
        "ammunition",
        "-",
        "retail"
    ],
    "wof:name":"Maes J-m-dima",
    "wof:placetype":"venue"
},
  "geometry": {"coordinates":[3.8795111179,51.0123558044],"type":"Point"}
}