{
  "type": "Feature",
  "properties": {
    "addr:full":"Lombardenvest 22 Antwerpen Antwerpen 2000",
    "addr:housenumber":"22",
    "addr:postcode":"2000",
    "addr:street":"Lombardenvest",
    "iso:country":"BE",
    "sg:address":"Lombardenvest 22",
    "sg:city":"Antwerpen",
    "sg:orig_category":"Avocats and conseillers juridiques",
    "sg:phone":"+32 3 231 71 32",
    "sg:postcode":"2000",
    "sg:province":"Antwerpen",
    "wof:name":"H. Talhaoui",
    "wof:placetype":"venue"
},
  "geometry": {"coordinates":[4.4013991356,51.2175254822],"type":"Point"}
}