{
  "type": "Feature",
  "properties": {
    "addr:full":"Rue Du Maillet 14 Frasnes-lez-anvaing Hainaut 7910",
    "addr:housenumber":"14",
    "addr:postcode":"7910",
    "addr:street":"Rue Du Maillet",
    "iso:country":"BE",
    "sg:address":"Rue Du Maillet 14",
    "sg:city":"Frasnes-lez-anvaing",
    "sg:orig_category":"M\u00e9decins and sp\u00e9cialistes",
    "sg:phone":"+32 69 85 95 65",
    "sg:postcode":"7910",
    "sg:province":"Hainaut",
    "wof:name":"Christophe Buron",
    "wof:placetype":"venue"
},
  "geometry": {"coordinates":[3.5463850498,50.6690864563],"type":"Point"}
}