{
  "type": "Feature",
  "properties": {
    "iso:country":"BE",
    "sg:address":"Tiensesteenweg 56",
    "sg:city":"Bierbeek",
    "sg:orig_category":"Syst\u00e8mes de t\u00e9l\u00e9communications. E-activit\u00e9s",
    "sg:phone":"+32 16 46 12 88",
    "sg:postcode":"3360",
    "sg:province":"Vlaams-Brabant",
    "wof:name":"Bausch Datacom",
    "wof:placetype":"venue"
},
  "geometry": {"coordinates":[4.7588210106,50.8632202148],"type":"Point"}
}