{
  "type": "Feature",
  "properties": {
    "iso:country":"BE",
    "sg:address":"Weg Naar Zwartberg 406",
    "sg:city":"Opglabbeek",
    "sg:classifiers":[
        {
            "category":"Manufacturing",
            "subcategory":"Metals",
            "type":"Manufacturing & Wholesale Goods"
        }
    ],
    "sg:phone":"+32 89 41 81 98",
    "sg:postcode":"3660",
    "sg:province":"Limburg",
    "sg:tags":[
        "tube"
    ],
    "wof:name":"Knoops Bvba",
    "wof:placetype":"venue"
},
  "geometry": {"coordinates":[5.5326800346,51.028049469],"type":"Point"}
}