{
  "type": "Feature",
  "properties": {
    "addr:full":"Eeuwfeestlaan 62 Lier Antwerpen 2500",
    "addr:housenumber":"62",
    "addr:postcode":"2500",
    "addr:street":"Eeuwfeestlaan",
    "iso:country":"BE",
    "sg:address":"Eeuwfeestlaan 62",
    "sg:city":"Lier",
    "sg:classifiers":[
        {
            "category":"Cafe",
            "type":"Food & Drink"
        }
    ],
    "sg:phone":"+32 3 489 04 35",
    "sg:postcode":"2500",
    "sg:province":"Antwerpen",
    "sg:tags":[
        "caf\u00e9s"
    ],
    "wof:name":"Parochiehuis H Hart",
    "wof:placetype":"venue"
},
  "geometry": {"coordinates":[4.5607271194,51.1385879517],"type":"Point"}
}