{
  "type": "Feature",
  "properties": {
    "addr:full":"Route Du Vieux Campinaire 40 Fleurus Hainaut 6220",
    "addr:housenumber":"40",
    "addr:postcode":"6220",
    "addr:street":"Route Du Vieux Campinaire",
    "iso:country":"BE",
    "sg:address":"Route Du Vieux Campinaire 40",
    "sg:city":"Fleurus",
    "sg:classifiers":[
        {
            "category":"Wholesale",
            "subcategory":"Office Equipment",
            "type":"Manufacturing & Wholesale Goods"
        }
    ],
    "sg:phone":"+32 71 81 24 17",
    "sg:postcode":"6220",
    "sg:province":"Hainaut",
    "sg:tags":[
        "dust",
        "removing"
    ],
    "wof:name":"Stiwal Bvb Sa",
    "wof:placetype":"venue"
},
  "geometry": {"coordinates":[4.5289030075,50.4550437927],"type":"Point"}
}