{
  "type": "Feature",
  "properties": {
    "iso:country":"BE",
    "sg:address":"Avenue Iris Crahay 48",
    "sg:city":"Esneux",
    "sg:classifiers":[
        {
            "category":"Arena",
            "subcategory":"Sports Club",
            "type":"Entertainment"
        }
    ],
    "sg:phone":"+32 4 380 21 09",
    "sg:postcode":"4130",
    "sg:province":"Li\u00e8ge",
    "sg:tags":[
        "de"
    ],
    "wof:name":"T.c. Esneux",
    "wof:placetype":"venue"
},
  "geometry": {"coordinates":[5.5616497993,50.5263977051],"type":"Point"}
}