{
  "type": "Feature",
  "properties": {
    "addr:full":"Maaltebruggestraat 267 Gent Oost-Vlaanderen 9000",
    "addr:housenumber":"267",
    "addr:postcode":"9000",
    "addr:street":"Maaltebruggestraat;Oost-Vlaanderen",
    "iso:country":"BE",
    "sg:address":"Maaltebruggestraat 267",
    "sg:city":"Gent",
    "sg:orig_category":"Rusthuizen and serviceflats",
    "sg:phone":"+32 9 222 30 01",
    "sg:postcode":"9000",
    "sg:province":"Oost-Vlaanderen",
    "wof:name":"Francois Creyelman",
    "wof:placetype":"venue"
},
  "geometry": {"coordinates":[3.7081329823,51.0267868042],"type":"Point"}
}