{
  "type": "Feature",
  "properties": {
    "addr:full":"Sint-niklaasstraat 31 Meerhout Antwerpen 2450",
    "addr:housenumber":"31",
    "addr:postcode":"2450",
    "addr:street":"Sint-Niklaasstraat",
    "iso:country":"BE",
    "sg:address":"Sint-niklaasstraat 31",
    "sg:city":"Meerhout",
    "sg:orig_category":"Pleisterwerk",
    "sg:phone":"+32 14 86 72 94",
    "sg:postcode":"2450",
    "sg:province":"Antwerpen",
    "wof:name":"Rudy Wellens",
    "wof:placetype":"venue"
},
  "geometry": {"coordinates":[5.039440155,51.1086807251],"type":"Point"}
}