{
  "type": "Feature",
  "properties": {
    "addr:full":"Rue Am\u00e9ricaine 84 Bruxelles (ixelles) Bruxelles-Capitale 1050",
    "addr:housenumber":"84",
    "addr:postcode":"1050",
    "addr:street":"Rue Ame\u0301Ricaine",
    "iso:country":"BE",
    "sg:address":"Rue Am\u00e9ricaine 84",
    "sg:city":"Bruxelles (ixelles)",
    "sg:classifiers":[
        {
            "category":"Professional",
            "subcategory":"Lawyer & Legal Services",
            "type":"Services"
        }
    ],
    "sg:phone":"+32 2 538 28 30",
    "sg:postcode":"1050",
    "sg:province":"Bruxelles-Capitale",
    "wof:name":"Van Praet Martine",
    "wof:placetype":"venue"
},
  "geometry": {"coordinates":[4.3585600853,50.8235359192],"type":"Point"}
}