{
  "type": "Feature",
  "properties": {
    "iso:country":"BE",
    "sg:address":"Chauss\u00c9e De Li\u00c8ge",
    "sg:city":"Grace-hollogne",
    "sg:orig_category":"Huisdieren and benodigdheden Royal Canin",
    "sg:phone":"+32 4 246 49 07",
    "sg:postcode":"4460",
    "sg:province":"Li\u00e8ge",
    "wof:name":"M.muselle Joseph",
    "wof:placetype":"venue"
},
  "geometry": {"coordinates":[5.4754710197,50.6495819092],"type":"Point"}
}