{
  "type": "Feature",
  "properties": {
    "addr:full":"Marcottedreef 37 Kapellen Antwerpen 2950",
    "addr:housenumber":"37",
    "addr:postcode":"2950",
    "addr:street":"Marcottedreef",
    "iso:country":"BE",
    "sg:address":"Marcottedreef 37",
    "sg:city":"Kapellen",
    "sg:classifiers":[
        {
            "category":"Fast Food",
            "type":"Food & Drink"
        }
    ],
    "sg:phone":"+32 3 666 51 11",
    "sg:postcode":"2950",
    "sg:province":"Antwerpen",
    "sg:tags":[
        "meeneem",
        "restaurant"
    ],
    "wof:name":"Taverne De Bosduif",
    "wof:placetype":"venue"
},
  "geometry": {"coordinates":[4.4350919724,51.3488883972],"type":"Point"}
}