{
  "type": "Feature",
  "properties": {
    "iso:country":"BE",
    "sg:address":"Rue Barri\u00c8re De Fer 118",
    "sg:city":"Moeskroen/mouscron",
    "sg:classifiers":[
        {
            "category":"Cinema",
            "subcategory":"Movie Rental",
            "type":"Entertainment"
        }
    ],
    "sg:phone":"+32 56 48 71 11",
    "sg:postcode":"7711",
    "sg:province":"Hainaut",
    "sg:tags":[
        "de",
        "cassette",
        "location",
        "vid\u00e9o",
        "audio"
    ],
    "wof:name":"Michel Kalmar",
    "wof:placetype":"venue"
},
  "geometry": {"coordinates":[3.3091130257,50.7240333557],"type":"Point"}
}