{
  "type": "Feature",
  "properties": {
    "addr:full":"Rue De Baili\u00c8vre 2 Sivry-rance Hainaut 6470",
    "addr:housenumber":"2",
    "addr:postcode":"6470",
    "addr:street":"Rue De Bailie\u0300Vre",
    "iso:country":"BE",
    "sg:address":"Rue De Baili\u00c8vre 2",
    "sg:city":"Sivry-rance",
    "sg:orig_category":"V\u00e9t\u00e9rinaires",
    "sg:phone":"+32 60 41 19 05",
    "sg:postcode":"6470",
    "sg:province":"Hainaut",
    "wof:name":"Didier Bienaime",
    "wof:placetype":"venue"
},
  "geometry": {"coordinates":[4.2256970406,50.1317024231],"type":"Point"}
}