{
  "type": "Feature",
  "properties": {
    "addr:full":"Noulaertsplein 12 Edegem Antwerpen 2650",
    "addr:housenumber":"12",
    "addr:postcode":"2650",
    "addr:street":"Noulaertsplein",
    "iso:country":"BE",
    "sg:address":"Noulaertsplein 12",
    "sg:city":"Edegem",
    "sg:orig_category":"V\u00e9t\u00e9rinaires",
    "sg:phone":"+32 3 448 37 91",
    "sg:postcode":"2650",
    "sg:province":"Antwerpen",
    "wof:name":"Nathalie Jacobs",
    "wof:placetype":"venue"
},
  "geometry": {"coordinates":[4.4321980476,51.1584281921],"type":"Point"}
}