{
  "type": "Feature",
  "properties": {
    "iso:country":"BE",
    "sg:address":"Oostkaai 50",
    "sg:city":"Ieper",
    "sg:classifiers":[
        {
            "category":"Professional",
            "subcategory":"Printing & Photocopies",
            "type":"Services"
        }
    ],
    "sg:phone":"+32 57 22 13 50",
    "sg:postcode":"8900",
    "sg:province":"West-Vlaanderen",
    "sg:tags":[
        "machine",
        "equipment"
    ],
    "wof:name":"Strobbe Graphics Nv",
    "wof:placetype":"venue"
},
  "geometry": {"coordinates":[2.8846380711,50.8590621948],"type":"Point"}
}