{
  "type": "Feature",
  "properties": {
    "addr:full":"Biest 26b2 Brecht Antwerpen 2960",
    "addr:housenumber":"26b2",
    "addr:postcode":"2960",
    "addr:street":"Biest",
    "iso:country":"BE",
    "sg:address":"Biest 26b2",
    "sg:city":"Brecht",
    "sg:orig_category":"Diverse persoonlijke diensten",
    "sg:phone":"+32 3 313 00 67",
    "sg:postcode":"2960",
    "sg:province":"Antwerpen",
    "wof:name":"Ren\u00c9 Kamphuys",
    "wof:placetype":"venue"
},
  "geometry": {"coordinates":[4.6413002014,51.3509941101],"type":"Point"}
}