{
  "type": "Feature",
  "properties": {
    "iso:country":"BE",
    "sg:address":"Avenue Albert I 83",
    "sg:city":"Namur",
    "sg:classifiers":[
        {
            "category":"Bars & Pubs",
            "type":"Food & Drink"
        }
    ],
    "sg:phone":"+32 81 23 01 92",
    "sg:postcode":"5000",
    "sg:province":"Namur",
    "wof:name":"L'inattendu",
    "wof:placetype":"venue"
},
  "geometry": {"coordinates":[4.8818869591,50.4669914246],"type":"Point"}
}