{
  "type": "Feature",
  "properties": {
    "addr:full":"Potaardestraat 105 Kraainem/kraainem Vlaams-Brabant 1950",
    "addr:housenumber":"105",
    "addr:postcode":"1950",
    "addr:street":"Potaardestraat",
    "iso:country":"BE",
    "sg:address":"Potaardestraat 105",
    "sg:city":"Kraainem/kraainem",
    "sg:orig_category":"Schoonheidssalons",
    "sg:phone":"+32 2 731 70 65",
    "sg:postcode":"1950",
    "sg:province":"Vlaams-Brabant",
    "wof:name":"Anne Vossaert",
    "wof:placetype":"venue"
},
  "geometry": {"coordinates":[4.4720802307,50.838886261],"type":"Point"}
}