{
  "type": "Feature",
  "properties": {
    "iso:country":"BE",
    "sg:address":"Avenue De Wisterz\u00e9e 7",
    "sg:city":"Court-saint-etienne",
    "sg:classifiers":[
        {
            "category":"Communications",
            "subcategory":"Film & Video Production",
            "type":"Services"
        }
    ],
    "sg:phone":"+32 10 61 50 52",
    "sg:postcode":"1490",
    "sg:province":"Brabant Wallon",
    "sg:tags":[
        "professional",
        "material",
        "-"
    ],
    "wof:name":"A Video Warehouse Sa",
    "wof:placetype":"venue"
},
  "geometry": {"coordinates":[4.5651330948,50.6466636658],"type":"Point"}
}