{
  "type": "Feature",
  "properties": {
    "addr:full":"Rue Fran\u00e7ois Beeckmans 31 Bruxelles (ganshoren) Bruxelles-Capitale 1083",
    "addr:housenumber":"31",
    "addr:postcode":"1083",
    "addr:street":"Rue Franc\u0327Ois Beeckmans",
    "iso:country":"BE",
    "sg:address":"Rue Fran\u00e7ois Beeckmans 31",
    "sg:city":"Bruxelles (ganshoren)",
    "sg:classifiers":[
        {
            "category":"Professional",
            "subcategory":"Testing Lab",
            "type":"Services"
        }
    ],
    "sg:phone":"+32 2 427 61 72",
    "sg:postcode":"1083",
    "sg:province":"Bruxelles-Capitale",
    "sg:tags":[
        "chemist"
    ],
    "wof:name":"Maricot A",
    "wof:placetype":"venue"
},
  "geometry": {"coordinates":[4.3111181259,50.870349884],"type":"Point"}
}