{
  "type": "Feature",
  "properties": {
    "iso:country":"BE",
    "sg:address":"Avenue De L\u00b4et\u00c9 42",
    "sg:city":"Waterloo",
    "sg:classifiers":[
        {
            "category":"Professional",
            "subcategory":"Business Services",
            "type":"Services"
        }
    ],
    "sg:phone":"+32 2 351 23 60",
    "sg:postcode":"1410",
    "sg:province":"Brabant Wallon",
    "sg:tags":[
        "aux",
        "diver",
        "entreprises"
    ],
    "wof:name":"V\u00c9ronique Barazzoni",
    "wof:placetype":"venue"
},
  "geometry": {"coordinates":[4.3926091194,50.7099685669],"type":"Point"}
}