{
  "type": "Feature",
  "properties": {
    "iso:country":"BE",
    "sg:address":"Rue Joseph Stallaert 23b1",
    "sg:city":"Elsene/ixelles",
    "sg:orig_category":"M\u00e9decins and sp\u00e9cialistes",
    "sg:phone":"+32 2 345 08 00",
    "sg:postcode":"1050",
    "sg:province":"Bruxelles-Capitale",
    "wof:name":"Ph. Mahillon",
    "wof:placetype":"venue"
},
  "geometry": {"coordinates":[4.355328083,50.8157806396],"type":"Point"}
}