{
  "type": "Feature",
  "properties": {
    "iso:country":"BE",
    "sg:address":"Bovenrij 50ba",
    "sg:city":"Herentals",
    "sg:classifiers":[
        {
            "category":"Communications",
            "subcategory":"Radio Station",
            "type":"Services"
        }
    ],
    "sg:phone":"+32 14 23 17 00",
    "sg:postcode":"2200",
    "sg:province":"Antwerpen",
    "sg:tags":[
        "diffusion",
        "production",
        "de",
        "programme"
    ],
    "wof:name":"Radio Contact Herentals",
    "wof:placetype":"venue"
},
  "geometry": {"coordinates":[4.8378868103,51.1749038696],"type":"Point"}
}