{
  "type": "Feature",
  "properties": {
    "addr:full":"Bloemenstraat 20 Tienen Vlaams-Brabant 3300",
    "addr:housenumber":"20",
    "addr:postcode":"3300",
    "addr:street":"Bloemenstraat",
    "iso:country":"BE",
    "sg:address":"Bloemenstraat 20",
    "sg:city":"Tienen",
    "sg:classifiers":[
        {
            "category":"Arena",
            "subcategory":"Sports Club",
            "type":"Entertainment"
        }
    ],
    "sg:phone":"+32 16 81 47 68",
    "sg:postcode":"3300",
    "sg:province":"Vlaams-Brabant",
    "sg:tags":[
        "de"
    ],
    "wof:name":"Wielerpromotieclub olympia Vzw",
    "wof:placetype":"venue"
},
  "geometry": {"coordinates":[4.930077076,50.8096694946],"type":"Point"}
}