{
  "type": "Feature",
  "properties": {
    "addr:full":"Eendenstraat 1ba Linter Vlaams-Brabant 3350",
    "addr:housenumber":"1ba",
    "addr:postcode":"3350",
    "addr:street":"Eendenstraat;Vlaams-Brabant",
    "iso:country":"BE",
    "sg:address":"Eendenstraat 1ba",
    "sg:city":"Linter",
    "sg:orig_category":"Sportclubs Sportterreinen and installaties behalve sportcentra",
    "sg:phone":"+32 11 78 23 51",
    "sg:postcode":"3350",
    "sg:province":"Vlaams-Brabant",
    "wof:name":"K.stormvogels Drieslinter",
    "wof:placetype":"venue"
},
  "geometry": {"coordinates":[5.0401711464,50.8417243958],"type":"Point"}
}