{
  "type": "Feature",
  "properties": {
    "addr:full":"Koningin Astridlaan 17b1 Brugge West-Vlaanderen 8200",
    "addr:housenumber":"17b1",
    "addr:postcode":"8200",
    "addr:street":"Koningin Astridlaan",
    "iso:country":"BE",
    "sg:address":"Koningin Astridlaan 17b1",
    "sg:city":"Brugge",
    "sg:orig_category":"Industri\u00eble elektrische installaties Onderdelen and accessoires voor auto's Technische and wetenscha",
    "sg:phone":"+32 50 33 80 48",
    "sg:postcode":"8200",
    "sg:province":"West-Vlaanderen",
    "wof:name":"Argus Alarm Systems",
    "wof:placetype":"venue"
},
  "geometry": {"coordinates":[3.2480800152,51.2002639771],"type":"Point"}
}