{
  "type": "Feature",
  "properties": {
    "addr:full":"Rue De La Sucrerie 12 Ath Hainaut 7800",
    "addr:housenumber":"12",
    "addr:postcode":"7800",
    "addr:street":"Rue De La Sucrerie",
    "iso:country":"BE",
    "sg:address":"Rue De La Sucrerie 12",
    "sg:city":"Ath",
    "sg:orig_category":"Souvenirs and objets artisanaux. Meubles D\u00e9taillants, Am\u00e9nagement de B\u00e2timents et de Cuisines",
    "sg:phone":"+32 68 28 20 62",
    "sg:postcode":"7800",
    "sg:province":"Hainaut",
    "wof:name":"La Sucrerie",
    "wof:placetype":"venue"
},
  "geometry": {"coordinates":[3.7767899036,50.6250076294],"type":"Point"}
}