{
  "type": "Feature",
  "properties": {
    "addr:full":"Avenue Charles-quint 93 Ganshoren/ganshoren Bruxelles-Capitale 1083",
    "addr:housenumber":"93",
    "addr:postcode":"1083",
    "addr:street":"Avenue Charles-Quint",
    "iso:country":"BE",
    "sg:address":"Avenue Charles-quint 93",
    "sg:city":"Ganshoren/ganshoren",
    "sg:orig_category":"Pharmaciens",
    "sg:phone":"+32 2 425 15 83",
    "sg:postcode":"1083",
    "sg:province":"Bruxelles-Capitale",
    "wof:name":"Jacques Schmitz",
    "wof:placetype":"venue"
},
  "geometry": {"coordinates":[4.3113999367,50.8685264587],"type":"Point"}
}