{
  "type": "Feature",
  "properties": {
    "addr:full":"Graaf De Smet De Naeyerlaan 73 Kortrijk West-Vlaanderen 8500",
    "addr:housenumber":"73",
    "addr:postcode":"8500",
    "addr:street":"Graaf De Smet De Naeyerlaan",
    "iso:country":"BE",
    "sg:address":"Graaf De Smet De Naeyerlaan 73",
    "sg:city":"Kortrijk",
    "sg:classifiers":[
        {
            "category":"Shopping",
            "subcategory":"Jewelry",
            "type":"Retail Goods"
        }
    ],
    "sg:phone":"+32 56 35 21 01",
    "sg:postcode":"8500",
    "sg:province":"West-Vlaanderen",
    "sg:tags":[
        "diamond",
        "-"
    ],
    "wof:name":"Kortrijkse Goudsmederij",
    "wof:placetype":"venue"
},
  "geometry": {"coordinates":[3.2563869953,50.8345680237],"type":"Point"}
}