{
  "type": "Feature",
  "properties": {
    "iso:country":"BE",
    "sg:address":"Albrechtlaan 24b1",
    "sg:city":"Aalst",
    "sg:classifiers":[
        {
            "category":"Building & Trades",
            "subcategory":"Landscaping Services",
            "type":"Services"
        }
    ],
    "sg:phone":"+32 53 77 04 20",
    "sg:postcode":"9300",
    "sg:province":"Oost-Vlaanderen",
    "sg:tags":[
        "earth",
        "moving"
    ],
    "wof:name":"Ondernemingen I.r. De Jonghe En Zoon Nv",
    "wof:placetype":"venue"
},
  "geometry": {"coordinates":[4.0545988083,50.9345932007],"type":"Point"}
}