{
  "type": "Feature",
  "properties": {
    "iso:country":"BE",
    "sg:address":"Kazernestraat 34",
    "sg:city":"Lokeren",
    "sg:classifiers":[
        {
            "category":"Insurance",
            "subcategory":"Insurance Agent",
            "type":"Services"
        }
    ],
    "sg:phone":"+32 9 349 12 92",
    "sg:postcode":"9160",
    "sg:province":"Oost-Vlaanderen",
    "sg:tags":[
        "verzekeringsmakelaars",
        "expert"
    ],
    "wof:name":"Maes Verzekeringen",
    "wof:placetype":"venue"
},
  "geometry": {"coordinates":[3.9898591042,51.1005134583],"type":"Point"}
}