{
  "type": "Feature",
  "properties": {
    "addr:full":"Rue D\u00b4ostende 71 Sint-jans-molenbeek/molenbeek-saint-jean Bruxelles-Capitale 1080",
    "addr:housenumber":"71",
    "addr:postcode":"1080",
    "addr:street":"Rue D\u00b4Ostende",
    "iso:country":"BE",
    "sg:address":"Rue D\u00b4ostende 71",
    "sg:city":"Sint-jans-molenbeek/molenbeek-saint-jean",
    "sg:orig_category":"Entretien and r\u00e9parations de voitures",
    "sg:phone":"+32 2 414 20 08",
    "sg:postcode":"1080",
    "sg:province":"Bruxelles-Capitale",
    "wof:name":"Garage Allal",
    "wof:placetype":"venue"
},
  "geometry": {"coordinates":[4.3307118416,50.8556938171],"type":"Point"}
}