{
  "type": "Feature",
  "properties": {
    "iso:country":"BE",
    "sg:address":"Centrum-zuid 2034",
    "sg:city":"Houthalen-helchteren",
    "sg:orig_category":"Bouwmaterialen Gh",
    "sg:phone":"+32 11 60 38 17",
    "sg:postcode":"3530",
    "sg:province":"Limburg",
    "wof:name":"C.v. Import",
    "wof:placetype":"venue"
},
  "geometry": {"coordinates":[5.3656749725,51.0173110962],"type":"Point"}
}