{
  "type": "Feature",
  "properties": {
    "addr:full":"Rue De Fontaine 112ba Binche Hainaut 7134",
    "addr:postcode":"7134",
    "addr:street":"Rue De Fontaine 112Ba;Hainaut",
    "iso:country":"BE",
    "sg:address":"Rue De Fontaine 112ba",
    "sg:city":"Binche",
    "sg:classifiers":[
        {
            "category":"Professional",
            "subcategory":"Accounting & Tax Preparation",
            "type":"Services"
        }
    ],
    "sg:phone":"+32 64 33 99 23",
    "sg:postcode":"7134",
    "sg:province":"Hainaut",
    "sg:tags":[
        "accountant"
    ],
    "wof:name":"Agostino Scozzari",
    "wof:placetype":"venue"
},
  "geometry": {"coordinates":[4.2009301186,50.4122314453],"type":"Point"}
}