{
  "type": "Feature",
  "properties": {
    "addr:full":"Avenue Jos\u00c8phe Wauters 7 Huy Li\u00e8ge 4500",
    "addr:housenumber":"7",
    "addr:postcode":"4500",
    "addr:street":"Avenue Jose\u0300Phe Wauters",
    "iso:country":"BE",
    "sg:address":"Avenue Jos\u00c8phe Wauters 7",
    "sg:city":"Huy",
    "sg:orig_category":"Jeux and jouets",
    "sg:phone":"+32 85 21 70 13",
    "sg:postcode":"4500",
    "sg:province":"Li\u00e8ge",
    "wof:name":"Laruelle P. & Rousseau A.",
    "wof:placetype":"venue"
},
  "geometry": {"coordinates":[5.2565350533,50.5233917236],"type":"Point"}
}