{
  "type": "Feature",
  "properties": {
    "iso:country":"BE",
    "sg:address":"Tintange 12",
    "sg:city":"Fauvillers",
    "sg:orig_category":"Eleveurs de bovins",
    "sg:phone":"+32 63 60 00 69",
    "sg:postcode":"6637",
    "sg:province":"Luxembourg",
    "wof:name":"Emile Godfroid",
    "wof:placetype":"venue"
},
  "geometry": {"coordinates":[5.7512040138,49.8796920776],"type":"Point"}
}