{
  "type": "Feature",
  "properties": {
    "addr:full":"Beningstraat 36 Herselt Antwerpen 2230",
    "addr:housenumber":"36",
    "addr:postcode":"2230",
    "addr:street":"Beningstraat",
    "iso:country":"BE",
    "sg:address":"Beningstraat 36",
    "sg:city":"Herselt",
    "sg:orig_category":"Groententeelt",
    "sg:phone":"+32 16 69 72 80",
    "sg:postcode":"2230",
    "sg:province":"Antwerpen",
    "wof:name":"Ludovicus Pauwels",
    "wof:placetype":"venue"
},
  "geometry": {"coordinates":[4.8805141449,51.0376358032],"type":"Point"}
}