{
  "type": "Feature",
  "properties": {
    "iso:country":"BE",
    "sg:address":"Markt 18",
    "sg:city":"Pittem",
    "sg:classifiers":[
        {
            "category":"Bars & Pubs",
            "type":"Food & Drink"
        }
    ],
    "sg:phone":"+32 51 46 56 15",
    "sg:postcode":"8740",
    "sg:province":"West-Vlaanderen",
    "wof:name":"Kroon (de)",
    "wof:placetype":"venue"
},
  "geometry": {"coordinates":[3.2669410706,50.9941101074],"type":"Point"}
}