{
  "type": "Feature",
  "properties": {
    "iso:country":"BE",
    "sg:address":"Vaartstraat 92",
    "sg:city":"Ranst",
    "sg:orig_category":"Software ontwikkeling and ontwerp",
    "sg:phone":"+32 3 475 19 98",
    "sg:postcode":"2520",
    "sg:province":"Antwerpen",
    "wof:name":"Studios Sky 4",
    "wof:placetype":"venue"
},
  "geometry": {"coordinates":[4.5690069199,51.2018318176],"type":"Point"}
}