{
  "type": "Feature",
  "properties": {
    "iso:country":"BE",
    "sg:address":"Kerkstraat 46",
    "sg:city":"Kasterlee (tielen)",
    "sg:classifiers":[
        {
            "category":"Building & Trades",
            "subcategory":"Construction",
            "type":"Services"
        }
    ],
    "sg:phone":"+32 14 55 69 28",
    "sg:postcode":"2460",
    "sg:province":"Antwerpen",
    "sg:tags":[
        "carpenter"
    ],
    "wof:name":"Nuyts Gebr",
    "wof:placetype":"venue"
},
  "geometry": {"coordinates":[4.9006609917,51.2429351807],"type":"Point"}
}