{
  "type": "Feature",
  "properties": {
    "addr:full":"Schuttersvest 21 Mechelen Antwerpen 2800",
    "addr:housenumber":"21",
    "addr:postcode":"2800",
    "addr:street":"Schuttersvest",
    "iso:country":"BE",
    "sg:address":"Schuttersvest 21",
    "sg:city":"Mechelen",
    "sg:orig_category":"Artsen and specialisten",
    "sg:phone":"+32 15 41 42 12",
    "sg:postcode":"2800",
    "sg:province":"Antwerpen",
    "wof:name":"H. Van De Put",
    "wof:placetype":"venue"
},
  "geometry": {"coordinates":[4.4784097672,51.0210533142],"type":"Point"}
}