{
  "type": "Feature",
  "properties": {
    "iso:country":"BE",
    "sg:address":"Rue De Tongres 8",
    "sg:city":"Vis\u00e9",
    "sg:orig_category":"Non-Classified Establishments",
    "sg:phone":"+32 4 379 34 78",
    "sg:postcode":"4600",
    "sg:province":"Li\u00e8ge",
    "wof:name":"Gar Raffay Stephane & Etienne",
    "wof:placetype":"venue"
},
  "geometry": {"coordinates":[5.682612896,50.737991333],"type":"Point"}
}