{
  "type": "Feature",
  "properties": {
    "iso:country":"BE",
    "sg:address":"Chauss\u00e9e De Tongres 486",
    "sg:city":"Juprelle",
    "sg:classifiers":[
        {
            "category":"Health Services",
            "subcategory":"Health Practitioner",
            "type":"Services"
        }
    ],
    "sg:phone":"+32 4 278 02 02",
    "sg:postcode":"4450",
    "sg:province":"Li\u00e8ge",
    "sg:tags":[
        "physiotherapist"
    ],
    "wof:name":"Vercoutere Catherine",
    "wof:placetype":"venue"
},
  "geometry": {"coordinates":[5.5212359428,50.7146492004],"type":"Point"}
}