{
  "type": "Feature",
  "properties": {
    "iso:country":"BE",
    "sg:address":"Oudenaardsesteenweg 25",
    "sg:city":"Gent",
    "sg:orig_category":"Installation de menuiserie en bois and plastique. Installation de menuiserie m\u00e9tallique",
    "sg:phone":"+32 9 220 87 45",
    "sg:postcode":"9000",
    "sg:province":"Oost-Vlaanderen",
    "wof:name":"Belisol",
    "wof:placetype":"venue"
},
  "geometry": {"coordinates":[3.7092609406,51.0216217041],"type":"Point"}
}