{
  "type": "Feature",
  "properties": {
    "addr:full":"Place Du Doyenn\u00e9 28 Gr\u00e2ce-hollogne (horion-hoz\u00e9mont) Li\u00e8ge 4460",
    "addr:housenumber":"28",
    "addr:postcode":"4460",
    "addr:street":"Place Du Doyenne\u0301;Horion-Hoze\u0301Mont",
    "iso:country":"BE",
    "sg:address":"Place Du Doyenn\u00e9 28",
    "sg:city":"Gr\u00e2ce-hollogne (horion-hoz\u00e9mont)",
    "sg:classifiers":[
        {
            "category":"Bars & Pubs",
            "type":"Food & Drink"
        }
    ],
    "sg:phone":"+32 4 250 12 99",
    "sg:postcode":"4460",
    "sg:province":"Li\u00e8ge",
    "wof:name":"Amicale (caf\u00e9 \u00e0 L')",
    "wof:placetype":"venue"
},
  "geometry": {"coordinates":[5.3976798058,50.6241912842],"type":"Point"}
}