{
  "type": "Feature",
  "properties": {
    "addr:full":"Olivierstraat 41 Rotselaar Vlaams-Brabant 3111",
    "addr:housenumber":"41",
    "addr:postcode":"3111",
    "addr:street":"Olivierstraat",
    "iso:country":"BE",
    "sg:address":"Olivierstraat 41",
    "sg:city":"Rotselaar",
    "sg:orig_category":"Boekhouders",
    "sg:phone":"+32 16 58 05 67",
    "sg:postcode":"3111",
    "sg:province":"Vlaams-Brabant",
    "wof:name":"Pieter Kestens",
    "wof:placetype":"venue"
},
  "geometry": {"coordinates":[4.7574939728,50.9546928406],"type":"Point"}
}