{
  "type": "Feature",
  "properties": {
    "addr:full":"Henrilei 22 Brasschaat Antwerpen 2930",
    "addr:housenumber":"22",
    "addr:postcode":"2930",
    "addr:street":"Henrilei",
    "iso:country":"BE",
    "sg:address":"Henrilei 22",
    "sg:city":"Brasschaat",
    "sg:classifiers":[
        {
            "category":"Professional",
            "subcategory":"Management & Consulting",
            "type":"Services"
        }
    ],
    "sg:phone":"+32 3 773 37 32",
    "sg:postcode":"2930",
    "sg:province":"Antwerpen",
    "sg:tags":[
        "-",
        "processing",
        "data",
        "consultant"
    ],
    "wof:name":"Ensee Bvba",
    "wof:placetype":"venue"
},
  "geometry": {"coordinates":[4.4529190063,51.2969512939],"type":"Point"}
}