{
  "type": "Feature",
  "properties": {
    "addr:full":"Rue Des Ecoles 2ba Florennes Namur 5620",
    "addr:housenumber":"2ba",
    "addr:postcode":"5620",
    "addr:street":"Rue Des Ecoles",
    "iso:country":"BE",
    "sg:address":"Rue Des Ecoles 2ba",
    "sg:city":"Florennes",
    "sg:orig_category":"Schoenen",
    "sg:phone":"+32 71 68 89 78",
    "sg:postcode":"5620",
    "sg:province":"Namur",
    "wof:name":"Shoes In The Box",
    "wof:placetype":"venue"
},
  "geometry": {"coordinates":[4.6060090065,50.2506370544],"type":"Point"}
}