{
  "type": "Feature",
  "properties": {
    "iso:country":"BE",
    "sg:address":"Rue De Battice 103",
    "sg:city":"Aubel",
    "sg:orig_category":"V\u00e9hicules automobiles",
    "sg:phone":"+32 87 68 72 48",
    "sg:postcode":"4880",
    "sg:province":"Li\u00e8ge",
    "wof:name":"Aubel Motors",
    "wof:placetype":"venue"
},
  "geometry": {"coordinates":[5.8539700508,50.6899909973],"type":"Point"}
}