{
  "type": "Feature",
  "properties": {
    "addr:full":"Avenue De La Seigneurerie 27 Chaumont-gistoux Brabant Wallon 1325",
    "addr:housenumber":"27",
    "addr:postcode":"1325",
    "addr:street":"Avenue De La Seigneurerie",
    "iso:country":"BE",
    "sg:address":"Avenue De La Seigneurerie 27",
    "sg:city":"Chaumont-gistoux",
    "sg:orig_category":"Ordinateurs and \u00e9quipement informatique",
    "sg:phone":"+32 10 22 33 54",
    "sg:postcode":"1325",
    "sg:province":"Brabant Wallon",
    "wof:name":"Fabco Electronics & Computing",
    "wof:placetype":"venue"
},
  "geometry": {"coordinates":[4.6405439377,50.6907691956],"type":"Point"}
}