{
  "type": "Feature",
  "properties": {
    "addr:full":"Rue De Gembloux 26 La Bruy\u00e8re (rhisnes) Namur 5080",
    "addr:housenumber":"26",
    "addr:postcode":"5080",
    "addr:street":"Rue De Gembloux",
    "iso:country":"BE",
    "sg:address":"Rue De Gembloux 26",
    "sg:city":"La Bruy\u00e8re (rhisnes)",
    "sg:classifiers":[
        {
            "category":"Health Services",
            "subcategory":"Health Practitioner",
            "type":"Services"
        }
    ],
    "sg:phone":"+32 81 56 03 69",
    "sg:postcode":"5080",
    "sg:province":"Namur",
    "sg:tags":[
        "physiotherapist"
    ],
    "wof:name":"Casier Dominique",
    "wof:placetype":"venue"
},
  "geometry": {"coordinates":[4.7958269119,50.4999046326],"type":"Point"}
}