{
  "type": "Feature",
  "properties": {
    "iso:country":"BE",
    "sg:address":"Clos Des M\u00e9sanges 47",
    "sg:city":"Ottignies-louvain-la-neuve (limelette)",
    "sg:classifiers":[
        {
            "category":"Professional",
            "subcategory":"Accounting & Tax Preparation",
            "type":"Services"
        }
    ],
    "sg:phone":"+32 10 41 18 57",
    "sg:postcode":"1342",
    "sg:province":"Brabant Wallon",
    "sg:tags":[
        "accountant"
    ],
    "wof:name":"Leclercq W",
    "wof:placetype":"venue"
},
  "geometry": {"coordinates":[4.5566282272,50.6764717102],"type":"Point"}
}