{
  "type": "Feature",
  "properties": {
    "iso:country":"BE",
    "sg:address":"Schoolstraat 34",
    "sg:city":"Bonheiden",
    "sg:classifiers":[
        {
            "category":"Professional",
            "subcategory":"Management & Consulting",
            "type":"Services"
        }
    ],
    "sg:phone":"+32 15 33 77 80",
    "sg:postcode":"2820",
    "sg:province":"Antwerpen",
    "sg:tags":[
        "-",
        "processing",
        "data",
        "consultant"
    ],
    "wof:name":"Biz 21",
    "wof:placetype":"venue"
},
  "geometry": {"coordinates":[4.5450811386,51.0212898254],"type":"Point"}
}