{
  "type": "Feature",
  "properties": {
    "addr:full":"Kasteelstraat 68 Ronse Oost-Vlaanderen 9600",
    "addr:housenumber":"68",
    "addr:postcode":"9600",
    "addr:street":"Kasteelstraat",
    "iso:country":"BE",
    "sg:address":"Kasteelstraat 68",
    "sg:city":"Ronse",
    "sg:orig_category":"Assistances juridiques",
    "sg:phone":"+32 55 21 91 38",
    "sg:postcode":"9600",
    "sg:province":"Oost-Vlaanderen",
    "wof:name":"T'kint J.",
    "wof:placetype":"venue"
},
  "geometry": {"coordinates":[3.5965559483,50.7471313477],"type":"Point"}
}