{
  "type": "Feature",
  "properties": {
    "addr:full":"Lange Dijkstraat 14 Antwerpen Antwerpen 2060",
    "addr:housenumber":"14",
    "addr:postcode":"2060",
    "addr:street":"Lange Dijkstraat",
    "iso:country":"BE",
    "sg:address":"Lange Dijkstraat 14",
    "sg:city":"Antwerpen",
    "sg:classifiers":[
        {
            "category":"Professional",
            "subcategory":"Art Services",
            "type":"Services"
        }
    ],
    "sg:phone":"+32 3 233 92 82",
    "sg:postcode":"2060",
    "sg:province":"Antwerpen",
    "sg:tags":[
        "graphic",
        "designer"
    ],
    "wof:name":"Twee Vormgevers",
    "wof:placetype":"venue"
},
  "geometry": {"coordinates":[4.4182691574,51.2267608643],"type":"Point"}
}