{
  "type": "Feature",
  "properties": {
    "iso:country":"BE",
    "sg:address":"Steenweg 11",
    "sg:city":"Asse",
    "sg:classifiers":[
        {
            "category":"Home & Garden",
            "subcategory":"Home Furnishings",
            "type":"Retail Goods"
        }
    ],
    "sg:phone":"+32 2 452 63 10",
    "sg:postcode":"1730",
    "sg:province":"Vlaams-Brabant",
    "sg:tags":[
        "curtain",
        "-",
        "fixture"
    ],
    "wof:name":"De Landtsheer J",
    "wof:placetype":"venue"
},
  "geometry": {"coordinates":[4.1984810829,50.9107437134],"type":"Point"}
}