{
  "type": "Feature",
  "properties": {
    "addr:full":"Charles Gilisquetlaan 16 Schaarbeek/schaerbeek Bruxelles-Capitale 1030",
    "addr:housenumber":"16",
    "addr:postcode":"1030",
    "addr:street":"Gilisquetlaan",
    "iso:country":"BE",
    "sg:address":"Charles Gilisquetlaan 16",
    "sg:city":"Schaarbeek/schaerbeek",
    "sg:orig_category":"Boekhouders",
    "sg:phone":"+32 2 215 48 05",
    "sg:postcode":"1030",
    "sg:province":"Bruxelles-Capitale",
    "wof:name":"Henri Mejblum",
    "wof:placetype":"venue"
},
  "geometry": {"coordinates":[4.3926959038,50.863067627],"type":"Point"}
}