{
  "type": "Feature",
  "properties": {
    "iso:country":"BE",
    "sg:address":"Rue Henri Wafelaerts 47",
    "sg:city":"Sint-gillis/saint-gilles",
    "sg:orig_category":"Avocats and conseillers juridiques",
    "sg:phone":"+32 2 533 53 51",
    "sg:postcode":"1060",
    "sg:province":"Bruxelles-Capitale",
    "wof:name":"Liesbeth Denys",
    "wof:placetype":"venue"
},
  "geometry": {"coordinates":[4.3501310349,50.8213272095],"type":"Point"}
}