{
  "type": "Feature",
  "properties": {
    "iso:country":"BE",
    "sg:address":"Rue Albert I 38",
    "sg:city":"Tournai (froidmont)",
    "sg:classifiers":[
        {
            "category":"Professional",
            "type":"Services"
        }
    ],
    "sg:phone":"+32 69 64 70 65",
    "sg:postcode":"7504",
    "sg:province":"Hainaut",
    "sg:tags":[
        "equipment",
        "installation",
        "restaurants"
    ],
    "wof:name":"Cuisiwan Sprl",
    "wof:placetype":"venue"
},
  "geometry": {"coordinates":[3.3283588886,50.57654953],"type":"Point"}
}