{
  "type": "Feature",
  "properties": {
    "iso:country":"BE",
    "sg:address":"Rue De L'alouette 6",
    "sg:city":"Anderlues",
    "sg:orig_category":"Eleveurs de bovins. Eleveurs and marchands de porcs",
    "sg:phone":"+32 64 33 77 92",
    "sg:postcode":"6150",
    "sg:province":"Hainaut",
    "wof:name":"Philippe Bienfait",
    "wof:placetype":"venue"
},
  "geometry": {"coordinates":[4.2416090965,50.4008369446],"type":"Point"}
}