{
  "type": "Feature",
  "properties": {
    "iso:country":"BE",
    "sg:address":"Rue Jules Tison 7",
    "sg:city":"La Louviere",
    "sg:orig_category":"Entretien and r\u00e9parations de voitures",
    "sg:phone":"+32 64 22 22 27",
    "sg:postcode":"7100",
    "sg:province":"Hainaut",
    "wof:name":"L. Wery",
    "wof:placetype":"venue"
},
  "geometry": {"coordinates":[4.1828198433,50.4698677063],"type":"Point"}
}