{
  "type": "Feature",
  "properties": {
    "iso:country":"BE",
    "sg:address":"Rue De Boncelles 185",
    "sg:city":"Seraing (ougr\u00e9e)",
    "sg:classifiers":[
        {
            "category":"Professional",
            "subcategory":"Printing & Photocopies",
            "type":"Services"
        }
    ],
    "sg:phone":"+32 4 336 61 02",
    "sg:postcode":"4102",
    "sg:province":"Li\u00e8ge",
    "sg:tags":[
        "silkscreen",
        "-"
    ],
    "wof:name":"Europrint Sprl",
    "wof:placetype":"venue"
},
  "geometry": {"coordinates":[5.5342059135,50.6013221741],"type":"Point"}
}