{
  "type": "Feature",
  "properties": {
    "addr:full":"Rue Des Poiriers 2 Gembloux Namur 5030",
    "addr:housenumber":"2",
    "addr:postcode":"5030",
    "addr:street":"Rue Des Poiriers;Namur",
    "iso:country":"BE",
    "sg:address":"Rue Des Poiriers 2",
    "sg:city":"Gembloux",
    "sg:classifiers":[
        {
            "category":"Shopping",
            "subcategory":"Stationery & Office Supplies",
            "type":"Retail Goods"
        }
    ],
    "sg:phone":"+32 81 60 14 01",
    "sg:postcode":"5030",
    "sg:province":"Namur",
    "sg:tags":[
        "fab",
        "carton",
        "en",
        "papier",
        "emballages"
    ],
    "wof:name":"Charlier-brison",
    "wof:placetype":"venue"
},
  "geometry": {"coordinates":[4.6979699135,50.5615348816],"type":"Point"}
}