{
  "type": "Feature",
  "properties": {
    "addr:full":"Rue De G\u00e9ronsart 302 Namur (jambes) Namur 5100",
    "addr:housenumber":"302",
    "addr:postcode":"5100",
    "addr:street":"Rue De Ge\u0301Ronsart",
    "iso:country":"BE",
    "sg:address":"Rue De G\u00e9ronsart 302",
    "sg:city":"Namur (jambes)",
    "sg:classifiers":[
        {
            "category":"Health Services",
            "subcategory":"Health Practitioner",
            "type":"Services"
        }
    ],
    "sg:phone":"+32 81 30 14 77",
    "sg:postcode":"5100",
    "sg:province":"Namur",
    "sg:tags":[
        "therapist",
        "speech"
    ],
    "wof:name":"Grevisse M",
    "wof:placetype":"venue"
},
  "geometry": {"coordinates":[4.8713750839,50.4566345215],"type":"Point"}
}