{
  "type": "Feature",
  "properties": {
    "addr:full":"Brugse Mettenstraat 22 Brugge (sint-kruis) West-Vlaanderen 8310",
    "addr:housenumber":"22",
    "addr:postcode":"8310",
    "addr:street":"Brugse Mettenstraat",
    "iso:country":"BE",
    "sg:address":"Brugse Mettenstraat 22",
    "sg:city":"Brugge (sint-kruis)",
    "sg:classifiers":[
        {
            "category":"Health Services",
            "subcategory":"Health Practitioner",
            "type":"Services"
        }
    ],
    "sg:phone":"+32 50 37 10 83",
    "sg:postcode":"8310",
    "sg:province":"West-Vlaanderen",
    "sg:tags":[
        "dietitian"
    ],
    "wof:name":"Corstjens E",
    "wof:placetype":"venue"
},
  "geometry": {"coordinates":[3.2429111004,51.2136154175],"type":"Point"}
}