{
  "type": "Feature",
  "properties": {
    "addr:full":"Rue De La Station 103 Mouscron Hainaut 7700",
    "addr:housenumber":"103",
    "addr:postcode":"7700",
    "addr:street":"Rue De La Station",
    "iso:country":"BE",
    "sg:address":"Rue De La Station 103",
    "sg:city":"Mouscron",
    "sg:orig_category":"Agences immobili\u00e8res",
    "sg:phone":"+32 56 33 58 39",
    "sg:postcode":"7700",
    "sg:province":"Hainaut",
    "wof:name":"Andre Gilmet",
    "wof:placetype":"venue"
},
  "geometry": {"coordinates":[3.2236659527,50.7434005737],"type":"Point"}
}