{
  "type": "Feature",
  "properties": {
    "addr:full":"Dendermondse Steenweg 1bc Aalst Oost-Vlaanderen 9300",
    "addr:housenumber":"1bc",
    "addr:postcode":"9300",
    "addr:street":"Steenweg",
    "iso:country":"BE",
    "sg:address":"Dendermondse Steenweg 1bc",
    "sg:city":"Aalst",
    "sg:orig_category":"Disquaires",
    "sg:phone":"+32 53 21 39 35",
    "sg:postcode":"9300",
    "sg:province":"Oost-Vlaanderen",
    "wof:name":"Yellow Cab",
    "wof:placetype":"venue"
},
  "geometry": {"coordinates":[4.0355291367,50.9418067932],"type":"Point"}
}