{
  "type": "Feature",
  "properties": {
    "addr:full":"Postbus 30 Hoogstraten Antwerpen 2320",
    "addr:housenumber":"30",
    "addr:postcode":"2320",
    "addr:street":"Postbus",
    "iso:country":"BE",
    "sg:address":"Postbus 30",
    "sg:city":"Hoogstraten",
    "sg:classifiers":[
        {
            "category":"Professional",
            "subcategory":"Management & Consulting",
            "type":"Services"
        }
    ],
    "sg:phone":"+32 3 314 03 26",
    "sg:postcode":"2320",
    "sg:province":"Antwerpen",
    "sg:tags":[
        "consultant",
        "law"
    ],
    "wof:name":"Van Velzen Cs Belgium Bvba",
    "wof:placetype":"venue"
},
  "geometry": {"coordinates":[4.7613801956,51.4013137817],"type":"Point"}
}