{
  "type": "Feature",
  "properties": {
    "iso:country":"BE",
    "sg:address":"Appeldijkstraat 24",
    "sg:city":"Bornem",
    "sg:orig_category":"Diverse bedrijfsbeheeradviesbureaus",
    "sg:phone":"+32 3 899 43 15",
    "sg:postcode":"2880",
    "sg:province":"Antwerpen",
    "wof:name":"Coaching Consult",
    "wof:placetype":"venue"
},
  "geometry": {"coordinates":[4.1932301521,51.0904388428],"type":"Point"}
}