{
  "type": "Feature",
  "properties": {
    "iso:country":"BE",
    "sg:address":"Kleine Lijkstraat 16ba",
    "sg:city":"Aalter",
    "sg:orig_category":"Woningbouw",
    "sg:phone":"+32 9 371 56 77",
    "sg:postcode":"9880",
    "sg:province":"Oost-Vlaanderen",
    "wof:name":"B & G Bouw",
    "wof:placetype":"venue"
},
  "geometry": {"coordinates":[3.4783399105,51.0434379578],"type":"Point"}
}