{
  "type": "Feature",
  "properties": {
    "addr:full":"Amedeus Stockmanslei 67 Mortsel Antwerpen 2640",
    "addr:housenumber":"67",
    "addr:postcode":"2640",
    "addr:street":"Amedeus Stockmanslei",
    "iso:country":"BE",
    "sg:address":"Amedeus Stockmanslei 67",
    "sg:city":"Mortsel",
    "sg:classifiers":[
        {
            "category":"Professional",
            "type":"Services"
        }
    ],
    "sg:phone":"+32 3 449 41 42",
    "sg:postcode":"2640",
    "sg:province":"Antwerpen",
    "sg:tags":[
        "surveyor",
        "-",
        "valuer"
    ],
    "wof:name":"Brinckman",
    "wof:placetype":"venue"
},
  "geometry": {"coordinates":[4.4514908791,51.1781539917],"type":"Point"}
}