{
  "type": "Feature",
  "properties": {
    "iso:country":"BE",
    "sg:address":"Rue Pisonchamps 48",
    "sg:city":"Flemalle",
    "sg:orig_category":"Entretien and r\u00e9parations de voitures",
    "sg:phone":"+32 4 233 62 59",
    "sg:postcode":"4400",
    "sg:province":"Li\u00e8ge",
    "wof:name":"Jean Dejardin",
    "wof:placetype":"venue"
},
  "geometry": {"coordinates":[5.4659581184,50.617351532],"type":"Point"}
}