{
  "type": "Feature",
  "properties": {
    "addr:full":"Rue G\u00e9n\u00e9ral Lotz 103 Box 10 Bruxelles (uccle) Bruxelles-Capitale 1180",
    "addr:housenumber":"103 box 10",
    "addr:postcode":"1180",
    "addr:street":"Rue Ge\u0301Ne\u0301Ral Lotz",
    "iso:country":"BE",
    "sg:address":"Rue G\u00e9n\u00e9ral Lotz 103 Box 10",
    "sg:city":"Bruxelles (uccle)",
    "sg:classifiers":[
        {
            "category":"Communications",
            "subcategory":"News Services",
            "type":"Services"
        }
    ],
    "sg:phone":"+32 2 343 86 70",
    "sg:postcode":"1180",
    "sg:province":"Bruxelles-Capitale",
    "sg:tags":[
        "agency"
    ],
    "wof:name":"Itar-tass (agence)",
    "wof:placetype":"venue"
},
  "geometry": {"coordinates":[4.3586797714,50.8116950989],"type":"Point"}
}