{
  "type": "Feature",
  "properties": {
    "addr:full":"Bld De La Constitution 42 Li\u00c8ge Li\u00e8ge 4020",
    "addr:housenumber":"42",
    "addr:postcode":"4020",
    "addr:street":"Bld De La Constitution",
    "iso:country":"BE",
    "sg:address":"Bld De La Constitution 42",
    "sg:city":"Li\u00c8ge",
    "sg:orig_category":"Cr\u00e9dit \u00e0 la consommation. Assurances",
    "sg:phone":"+32 4 342 75 80",
    "sg:postcode":"4020",
    "sg:province":"Li\u00e8ge",
    "wof:name":"Bureau Poulet",
    "wof:placetype":"venue"
},
  "geometry": {"coordinates":[5.5857419968,50.643283844],"type":"Point"}
}