{
  "type": "Feature",
  "properties": {
    "iso:country":"BE",
    "sg:address":"Wittenonnenstraat 25",
    "sg:city":"Oostende",
    "sg:classifiers":[
        {
            "category":"Shopping",
            "subcategory":"Clothing, Apparel, & Fashions",
            "type":"Retail Goods"
        }
    ],
    "sg:phone":"+32 59 70 52 46",
    "sg:postcode":"8400",
    "sg:province":"West-Vlaanderen",
    "sg:tags":[
        "boutique"
    ],
    "wof:name":"Idee Fix Bvba",
    "wof:placetype":"venue"
},
  "geometry": {"coordinates":[2.917427063,51.2309036255],"type":"Point"}
}