{
  "type": "Feature",
  "properties": {
    "iso:country":"BE",
    "sg:address":"Heirbaan 60 Postbus 2",
    "sg:city":"Mortsel",
    "sg:classifiers":[
        {
            "category":"Food & Beverages",
            "subcategory":"Groceries & Convenience Stores",
            "type":"Retail Goods"
        }
    ],
    "sg:phone":"+32 3 448 24 84",
    "sg:postcode":"2640",
    "sg:province":"Antwerpen",
    "sg:tags":[
        "product",
        "related"
    ],
    "wof:name":"Horecaservice Verbraecken Bvba",
    "wof:placetype":"venue"
},
  "geometry": {"coordinates":[4.4631719589,51.1791877747],"type":"Point"}
}