{
  "type": "Feature",
  "properties": {
    "addr:full":"Rue Joseph Wauters 32 Waremme Li\u00e8ge 4300",
    "addr:housenumber":"32",
    "addr:postcode":"4300",
    "addr:street":"Rue Joseph Wauters",
    "iso:country":"BE",
    "sg:address":"Rue Joseph Wauters 32",
    "sg:city":"Waremme",
    "sg:orig_category":"Herstelling horloges and juwelen Juwelen and edelstenen Fab Juwelen and horloges",
    "sg:phone":"+32 19 32 64 10",
    "sg:postcode":"4300",
    "sg:province":"Li\u00e8ge",
    "wof:name":"Fe. Temps & Or",
    "wof:placetype":"venue"
},
  "geometry": {"coordinates":[5.2547411919,50.6974220276],"type":"Point"}
}