{
  "type": "Feature",
  "properties": {
    "iso:country":"BE",
    "sg:address":"Rue De Maou 7",
    "sg:city":"Habay",
    "sg:orig_category":"Landmeters",
    "sg:phone":"+32 63 42 33 46",
    "sg:postcode":"6721",
    "sg:province":"Luxembourg",
    "wof:name":"Jacques Deom",
    "wof:placetype":"venue"
},
  "geometry": {"coordinates":[5.6207308769,49.772605896],"type":"Point"}
}