{
  "type": "Feature",
  "properties": {
    "addr:full":"Katstraat 41 Lede Oost-Vlaanderen 9340",
    "addr:housenumber":"41",
    "addr:postcode":"9340",
    "addr:street":"Katstraat",
    "iso:country":"BE",
    "sg:address":"Katstraat 41",
    "sg:city":"Lede",
    "sg:classifiers":[
        {
            "category":"Utilities",
            "subcategory":"Fuel Oil & Lpg",
            "type":"Services"
        }
    ],
    "sg:phone":"+32 53 80 51 64",
    "sg:postcode":"9340",
    "sg:province":"Oost-Vlaanderen",
    "wof:name":"Roels G",
    "wof:placetype":"venue"
},
  "geometry": {"coordinates":[3.9795720577,50.963924408],"type":"Point"}
}