{
  "type": "Feature",
  "properties": {
    "addr:full":"Rue De Dison 82 Verviers Li\u00e8ge 4800",
    "addr:housenumber":"82",
    "addr:postcode":"4800",
    "addr:street":"Rue De Dison",
    "iso:country":"BE",
    "sg:address":"Rue De Dison 82",
    "sg:city":"Verviers",
    "sg:classifiers":[
        {
            "category":"Cafe",
            "type":"Food & Drink"
        }
    ],
    "sg:phone":"+32 87 33 26 84",
    "sg:postcode":"4800",
    "sg:province":"Li\u00e8ge",
    "sg:tags":[
        "caf\u00e9s"
    ],
    "wof:name":"Kiriaki Tsoutzidou",
    "wof:placetype":"venue"
},
  "geometry": {"coordinates":[5.8594508171,50.5917663574],"type":"Point"}
}