{
  "type": "Feature",
  "properties": {
    "iso:country":"BE",
    "sg:address":"Obbeekstraat 20",
    "sg:city":"Heusden-zolder",
    "sg:classifiers":[
        {
            "category":"Food & Beverages",
            "subcategory":"Fruits & Vegetables",
            "type":"Retail Goods"
        }
    ],
    "sg:phone":"+32 11 42 60 78",
    "sg:postcode":"3550",
    "sg:province":"Limburg",
    "wof:name":"Inveg Nv",
    "wof:placetype":"venue"
},
  "geometry": {"coordinates":[5.2697668076,51.0236854553],"type":"Point"}
}