{
  "type": "Feature",
  "properties": {
    "iso:country":"BE",
    "sg:address":"Rue Docteur Albert Hustin 55",
    "sg:city":"Virton (ethe)",
    "sg:classifiers":[
        {
            "category":"Bakery",
            "type":"Food & Drink"
        }
    ],
    "sg:phone":"+32 63 57 72 46",
    "sg:postcode":"6760",
    "sg:province":"Luxembourg",
    "sg:tags":[
        "confectioner",
        "baker"
    ],
    "wof:name":"Baillot Fr\u00e8res",
    "wof:placetype":"venue"
},
  "geometry": {"coordinates":[5.5842189789,49.5798377991],"type":"Point"}
}