{
  "type": "Feature",
  "properties": {
    "addr:full":"Lichterveldestraat 18 Pittem West-Vlaanderen 8740",
    "addr:housenumber":"18",
    "addr:postcode":"8740",
    "addr:street":"Lichterveldestraat",
    "iso:country":"BE",
    "sg:address":"Lichterveldestraat 18",
    "sg:city":"Pittem",
    "sg:orig_category":"Producteurs de l\u00e9gumes",
    "sg:phone":"+32 51 46 60 92",
    "sg:postcode":"8740",
    "sg:province":"West-Vlaanderen",
    "wof:name":"Marc Jacobs",
    "wof:placetype":"venue"
},
  "geometry": {"coordinates":[3.2286760807,50.9994812012],"type":"Point"}
}