{
  "type": "Feature",
  "properties": {
    "addr:full":"Gullegemsestraat 219 Ledegem (sint-eloois-winkel) West-Vlaanderen 8880",
    "addr:housenumber":"219",
    "addr:postcode":"8880",
    "addr:street":"Gullegemsestraat",
    "iso:country":"BE",
    "sg:address":"Gullegemsestraat 219",
    "sg:city":"Ledegem (sint-eloois-winkel)",
    "sg:classifiers":[
        {
            "category":"Building & Trades",
            "subcategory":"Landscaping Services",
            "type":"Services"
        }
    ],
    "sg:phone":"+32 56 50 40 60",
    "sg:postcode":"8880",
    "sg:province":"West-Vlaanderen",
    "sg:tags":[
        "-",
        "lopping",
        "work",
        "tree",
        "felling"
    ],
    "wof:name":"Vandendriessche K",
    "wof:placetype":"venue"
},
  "geometry": {"coordinates":[3.1836779118,50.8611335754],"type":"Point"}
}