{
  "type": "Feature",
  "properties": {
    "addr:full":"Kiezelweg 12 Mol Antwerpen 2400",
    "addr:housenumber":"12",
    "addr:postcode":"2400",
    "addr:street":"Kiezelweg",
    "iso:country":"BE",
    "sg:address":"Kiezelweg 12",
    "sg:city":"Mol",
    "sg:classifiers":[
        {
            "category":"Restaurant",
            "type":"Food & Drink"
        }
    ],
    "sg:phone":"+32 14 81 35 25",
    "sg:postcode":"2400",
    "sg:province":"Antwerpen",
    "sg:tags":[
        "organisation",
        "de",
        "f\u00eates",
        "catering"
    ],
    "wof:name":"'t Neerhof",
    "wof:placetype":"venue"
},
  "geometry": {"coordinates":[5.1824297905,51.2125701904],"type":"Point"}
}