{
  "type": "Feature",
  "properties": {
    "addr:full":"L\u00fctticher Strasse 292 Kelmis Li\u00e8ge 4720",
    "addr:housenumber":"292",
    "addr:postcode":"4720",
    "addr:street":"Luetticher Strasse",
    "iso:country":"BE",
    "sg:address":"L\u00fctticher Strasse 292",
    "sg:city":"Kelmis",
    "sg:classifiers":[
        {
            "category":"Autos & Motor Vehicles",
            "subcategory":"Automobile Sales",
            "type":"Retail Goods"
        }
    ],
    "sg:phone":"+32 87 65 82 85",
    "sg:postcode":"4720",
    "sg:province":"Li\u00e8ge",
    "sg:tags":[
        "delivery",
        "-",
        "used",
        "van",
        "truck"
    ],
    "wof:name":"Autorog Sprl",
    "wof:placetype":"venue"
},
  "geometry": {"coordinates":[6.0088858604,50.7116775513],"type":"Point"}
}