{
  "type": "Feature",
  "properties": {
    "iso:country":"BE",
    "sg:address":"Ingelmunstersteenweg 45",
    "sg:city":"Oostrozebeke",
    "sg:orig_category":"Royal Canin Tuinbenodigdheden",
    "sg:phone":"+32 56 66 78 38",
    "sg:postcode":"8780",
    "sg:province":"West-Vlaanderen",
    "wof:name":"Bvba Aveve Veys",
    "wof:placetype":"venue"
},
  "geometry": {"coordinates":[3.3203949928,50.9195976257],"type":"Point"}
}