{
  "type": "Feature",
  "properties": {
    "iso:country":"BE",
    "sg:address":"Magdalenastraat 34",
    "sg:city":"Kortrijk",
    "sg:orig_category":"Agences immobili\u00e8res",
    "sg:phone":"+32 56 22 69 49",
    "sg:postcode":"8500",
    "sg:province":"West-Vlaanderen",
    "wof:name":"Imgest",
    "wof:placetype":"venue"
},
  "geometry": {"coordinates":[3.2566640377,50.8251724243],"type":"Point"}
}