{
  "type": "Feature",
  "properties": {
    "addr:full":"Quai De L'ourthe 17 La Roche-en-ardenne Luxembourg 6980",
    "addr:housenumber":"17",
    "addr:postcode":"6980",
    "addr:street":"Quai De L'Ourthe",
    "iso:country":"BE",
    "sg:address":"Quai De L'ourthe 17",
    "sg:city":"La Roche-en-ardenne",
    "sg:classifiers":[
        {
            "category":"Banks & Credit Unions",
            "subcategory":"Investment Brokerage",
            "type":"Services"
        }
    ],
    "sg:phone":"+32 84 41 13 50",
    "sg:postcode":"6980",
    "sg:province":"Luxembourg",
    "sg:tags":[
        "repair",
        "-",
        "installation",
        "sanitary",
        "article"
    ],
    "wof:name":"Dewalque Yves Sa",
    "wof:placetype":"venue"
},
  "geometry": {"coordinates":[5.5745711327,50.1818962097],"type":"Point"}
}