{
  "type": "Feature",
  "properties": {
    "addr:full":"Larumseweg 151 Geel Antwerpen 2440",
    "addr:housenumber":"151",
    "addr:postcode":"2440",
    "addr:street":"Larumseweg",
    "iso:country":"BE",
    "sg:address":"Larumseweg 151",
    "sg:city":"Geel",
    "sg:orig_category":"V\u00e9t\u00e9rinaires",
    "sg:phone":"+32 14 58 01 65",
    "sg:postcode":"2440",
    "sg:province":"Antwerpen",
    "wof:name":"L. Heuvelmans",
    "wof:placetype":"venue"
},
  "geometry": {"coordinates":[4.9481101036,51.1650619507],"type":"Point"}
}