{
  "type": "Feature",
  "properties": {
    "iso:country":"BE",
    "sg:address":"Faubourg De Lille 47",
    "sg:city":"Comines-warneton",
    "sg:orig_category":"Epiceries",
    "sg:phone":"+32 56 55 74 94",
    "sg:postcode":"7784",
    "sg:province":"Hainaut",
    "wof:name":"A La Douve",
    "wof:placetype":"venue"
},
  "geometry": {"coordinates":[2.9414350986,50.7495651245],"type":"Point"}
}