{
  "type": "Feature",
  "properties": {
    "addr:full":"Oudenaardsesteenweg 70 Gent Oost-Vlaanderen 9000",
    "addr:housenumber":"70",
    "addr:postcode":"9000",
    "addr:street":"Oudenaardsesteenweg;Oost-Vlaanderen",
    "iso:country":"BE",
    "sg:address":"Oudenaardsesteenweg 70",
    "sg:city":"Gent",
    "sg:orig_category":"Journaux. Stations-service and carburants",
    "sg:phone":"+32 9 221 31 27",
    "sg:postcode":"9000",
    "sg:province":"Oost-Vlaanderen",
    "wof:name":"Esso",
    "wof:placetype":"venue"
},
  "geometry": {"coordinates":[3.7090549469,51.0213737488],"type":"Point"}
}