{
  "type": "Feature",
  "properties": {
    "addr:full":"Rue De L'ang\u00c9lique 6 Ottignies-louvain-la-neuve Brabant Wallon 1348",
    "addr:housenumber":"6",
    "addr:postcode":"1348",
    "addr:street":"Rue De L'Ange \u0301Lique",
    "iso:country":"BE",
    "sg:address":"Rue De L'ang\u00c9lique 6",
    "sg:city":"Ottignies-louvain-la-neuve",
    "sg:orig_category":"Artsen and specialisten",
    "sg:phone":"+32 10 45 18 25",
    "sg:postcode":"1348",
    "sg:province":"Brabant Wallon",
    "wof:name":"Jacques Courtois",
    "wof:placetype":"venue"
},
  "geometry": {"coordinates":[4.6167030334,50.662109375],"type":"Point"}
}