{
  "type": "Feature",
  "properties": {
    "addr:full":"Pieter Vinckestraat 93 Kuurne West-Vlaanderen 8520",
    "addr:housenumber":"93",
    "addr:postcode":"8520",
    "addr:street":"Pieter Vinckestraat",
    "iso:country":"BE",
    "sg:address":"Pieter Vinckestraat 93",
    "sg:city":"Kuurne",
    "sg:classifiers":[
        {
            "category":"Professional",
            "subcategory":"Management & Consulting",
            "type":"Services"
        }
    ],
    "sg:phone":"+32 56 71 47 75",
    "sg:postcode":"8520",
    "sg:province":"West-Vlaanderen",
    "sg:tags":[
        "consultant"
    ],
    "wof:name":"Alcrea Bvba",
    "wof:placetype":"venue"
},
  "geometry": {"coordinates":[3.2668790817,50.8725280762],"type":"Point"}
}