{
  "type": "Feature",
  "properties": {
    "addr:full":"Chauss\u00c9e De Beaumont 10bb Mons Hainaut 7000",
    "addr:housenumber":"10bb",
    "addr:postcode":"7000",
    "addr:street":"Chausse\u0301E De Beaumont;Hainaut",
    "iso:country":"BE",
    "sg:address":"Chauss\u00c9e De Beaumont 10bb",
    "sg:city":"Mons",
    "sg:orig_category":"Boekhouders",
    "sg:phone":"+32 65 31 99 34",
    "sg:postcode":"7000",
    "sg:province":"Hainaut",
    "wof:name":"Dominique Kerteux",
    "wof:placetype":"venue"
},
  "geometry": {"coordinates":[3.9810550213,50.4499702454],"type":"Point"}
}