{
  "type": "Feature",
  "properties": {
    "iso:country":"BE",
    "sg:address":"Gentstraat 28",
    "sg:city":"Oostrozebeke",
    "sg:orig_category":"Eleveurs de bovins. Eleveurs and marchands de porcs",
    "sg:phone":"+32 51 40 08 16",
    "sg:postcode":"8780",
    "sg:province":"West-Vlaanderen",
    "wof:name":"Arsene Claerhout",
    "wof:placetype":"venue"
},
  "geometry": {"coordinates":[3.3613190651,50.9563140869],"type":"Point"}
}