{
  "type": "Feature",
  "properties": {
    "addr:full":"Siegersveldstraat 1ba Hasselt Limburg 3500",
    "addr:housenumber":"1ba",
    "addr:postcode":"3500",
    "addr:street":"Siegersveldstraat",
    "iso:country":"BE",
    "sg:address":"Siegersveldstraat 1ba",
    "sg:city":"Hasselt",
    "sg:orig_category":"Travaux de pl\u00e2trage",
    "sg:phone":"+32 11 31 59 89",
    "sg:postcode":"3500",
    "sg:province":"Limburg",
    "wof:name":"Limb. Plafoneringswerken",
    "wof:placetype":"venue"
},
  "geometry": {"coordinates":[5.3394827843,50.8997879028],"type":"Point"}
}