{
  "type": "Feature",
  "properties": {
    "iso:country":"BE",
    "sg:address":"Lagestraat 16",
    "sg:city":"Gingelom (vorsen)",
    "sg:classifiers":[
        {
            "category":"Shopping",
            "subcategory":"Bicycles & Sporting Goods",
            "type":"Retail Goods"
        }
    ],
    "sg:phone":"+32 11 88 64 29",
    "sg:postcode":"3890",
    "sg:province":"Limburg",
    "sg:tags":[
        "-"
    ],
    "wof:name":"J.b.s.",
    "wof:placetype":"venue"
},
  "geometry": {"coordinates":[5.1698551178,50.7025146484],"type":"Point"}
}