{
  "type": "Feature",
  "properties": {
    "iso:country":"BE",
    "sg:address":"Beringstraat 84",
    "sg:city":"Boortmeerbeek",
    "sg:orig_category":"M\u00e9decins and sp\u00e9cialistes",
    "sg:phone":"+32 15 51 30 27",
    "sg:postcode":"3190",
    "sg:province":"Vlaams-Brabant",
    "wof:name":"Filiep Bettens",
    "wof:placetype":"venue"
},
  "geometry": {"coordinates":[4.5689911842,50.9747428894],"type":"Point"}
}