{
  "type": "Feature",
  "properties": {
    "iso:country":"BE",
    "sg:address":"Avenue De Beersel 33",
    "sg:city":"Bruxelles (uccle)",
    "sg:classifiers":[
        {
            "category":"Building & Trades",
            "subcategory":"Pest Control",
            "type":"Services"
        }
    ],
    "sg:phone":"+32 2 376 67 40",
    "sg:postcode":"1180",
    "sg:province":"Bruxelles-Capitale",
    "sg:tags":[
        "painting",
        "contractor"
    ],
    "wof:name":"Parkintex-palomo Lopez",
    "wof:placetype":"venue"
},
  "geometry": {"coordinates":[4.3259129524,50.7856559753],"type":"Point"}
}