{
  "type": "Feature",
  "properties": {
    "addr:full":"17 Rue Piessevaux Saint Mard Luxembourg 6762",
    "addr:housenumber":"17",
    "addr:postcode":"6762",
    "addr:street":"Rue Piessevaux Saint Mard",
    "iso:country":"BE",
    "sg:address":"17 Rue Piessevaux",
    "sg:city":"Saint Mard",
    "sg:classifiers":[
        {
            "category":"Communications",
            "subcategory":"Television Station",
            "type":"Services"
        }
    ],
    "sg:phone":"+32 63 58 19 68",
    "sg:postcode":"6762",
    "sg:province":"Luxembourg",
    "sg:tags":[
        "video",
        "audio",
        "verhuur"
    ],
    "wof:name":"Magic World Cin\u00c9ma",
    "wof:placetype":"venue"
},
  "geometry": {"coordinates":[5.525829792,49.558555603],"type":"Point"}
}