{
  "type": "Feature",
  "properties": {
    "addr:full":"Pastorijstraat 3 Houthalen-helchteren (houthalen) Limburg 3530",
    "addr:housenumber":"3",
    "addr:postcode":"3530",
    "addr:street":"Pastorijstraat",
    "iso:country":"BE",
    "sg:address":"Pastorijstraat 3",
    "sg:city":"Houthalen-helchteren (houthalen)",
    "sg:classifiers":[
        {
            "category":"Food & Beverages",
            "subcategory":"Fruits & Vegetables",
            "type":"Retail Goods"
        }
    ],
    "sg:phone":"+32 11 60 25 44",
    "sg:postcode":"3530",
    "sg:province":"Limburg",
    "sg:tags":[
        "-"
    ],
    "wof:name":"Klokhuis ('t)",
    "wof:placetype":"venue"
},
  "geometry": {"coordinates":[5.3725042343,51.0304450989],"type":"Point"}
}