{
  "type": "Feature",
  "properties": {
    "iso:country":"BE",
    "sg:address":"Durentijdlei 144",
    "sg:city":"Brasschaat",
    "sg:classifiers":[
        {
            "category":"Health Services",
            "subcategory":"Doctor",
            "type":"Services"
        }
    ],
    "sg:phone":"+32 3 663 56 22",
    "sg:postcode":"2930",
    "sg:province":"Antwerpen",
    "sg:tags":[
        "medicinephysicians",
        "surgeon"
    ],
    "wof:name":"Bunarto J",
    "wof:placetype":"venue"
},
  "geometry": {"coordinates":[4.5283398628,51.3231506348],"type":"Point"}
}