{
  "type": "Feature",
  "properties": {
    "iso:country":"BE",
    "sg:address":"Rollebaanstraat 48",
    "sg:city":"Beernem",
    "sg:orig_category":"Plaatsen van vloer- and muurbekleding Woningbouw",
    "sg:phone":"+32 50 78 82 67",
    "sg:postcode":"8730",
    "sg:province":"West-Vlaanderen",
    "wof:name":"Compernolle Robert",
    "wof:placetype":"venue"
},
  "geometry": {"coordinates":[3.3447771072,51.1364173889],"type":"Point"}
}