{
  "type": "Feature",
  "properties": {
    "iso:country":"BE",
    "sg:address":"Graanmarkt 9",
    "sg:city":"Kortrijk",
    "sg:classifiers":[
        {
            "category":"Cafe",
            "type":"Food & Drink"
        }
    ],
    "sg:phone":"+32 56 21 91 51",
    "sg:postcode":"8500",
    "sg:province":"West-Vlaanderen",
    "sg:tags":[
        "caf\u00e9s"
    ],
    "wof:name":"Copper Kettle Inn",
    "wof:placetype":"venue"
},
  "geometry": {"coordinates":[3.265360117,50.8267974854],"type":"Point"}
}