{
  "type": "Feature",
  "properties": {
    "addr:full":"Mareydestraat 14 Sint-pieters-woluwe/woluwe-saint-pierre Bruxelles-Capitale 1150",
    "addr:housenumber":"14",
    "addr:postcode":"1150",
    "addr:street":"Mareydestraat;/",
    "iso:country":"BE",
    "sg:address":"Mareydestraat 14",
    "sg:city":"Sint-pieters-woluwe/woluwe-saint-pierre",
    "sg:orig_category":"Artsen and specialisten",
    "sg:phone":"+32 2 762 67 54",
    "sg:postcode":"1150",
    "sg:province":"Bruxelles-Capitale",
    "wof:name":"Danielle Taes",
    "wof:placetype":"venue"
},
  "geometry": {"coordinates":[4.4464387894,50.8316726685],"type":"Point"}
}