{
  "type": "Feature",
  "properties": {
    "iso:country":"BE",
    "sg:address":"Korenbloemstraat 7",
    "sg:city":"Oostkamp",
    "sg:orig_category":"Textiel Verlichting and huishoudartikelen",
    "sg:phone":"+32 50 82 52 84",
    "sg:postcode":"8020",
    "sg:province":"West-Vlaanderen",
    "wof:name":"Liliane Claeys",
    "wof:placetype":"venue"
},
  "geometry": {"coordinates":[3.2279961109,51.1569976807],"type":"Point"}
}