{
  "type": "Feature",
  "properties": {
    "addr:full":"Diestsestraat 133 Leuven Vlaams-Brabant 3000",
    "addr:housenumber":"133",
    "addr:postcode":"3000",
    "addr:street":"Diestsestraat",
    "iso:country":"BE",
    "sg:address":"Diestsestraat 133",
    "sg:city":"Leuven",
    "sg:classifiers":[
        {
            "category":"Restaurant",
            "type":"Food & Drink"
        }
    ],
    "sg:phone":"+32 16 30 95 34",
    "sg:postcode":"3000",
    "sg:province":"Vlaams-Brabant",
    "wof:name":"Tearoom La Finesse",
    "wof:placetype":"venue"
},
  "geometry": {"coordinates":[4.7077407837,50.8810348511],"type":"Point"}
}