{
  "type": "Feature",
  "properties": {
    "iso:country":"BE",
    "sg:address":"Sint-rochusstraat 15",
    "sg:city":"Nieuwerkerken",
    "sg:classifiers":[
        {
            "category":"Manufacturing",
            "subcategory":"Paper Products",
            "type":"Manufacturing & Wholesale Goods"
        }
    ],
    "sg:phone":"+32 80 22 80 84",
    "sg:postcode":"9320",
    "sg:province":"Oost-Vlaanderen",
    "sg:tags":[
        "finished",
        "cardboard",
        "-"
    ],
    "wof:name":"Gmbh Dell Walter",
    "wof:placetype":"venue"
},
  "geometry": {"coordinates":[6.122838974,50.2836952209],"type":"Point"}
}