{
  "type": "Feature",
  "properties": {
    "iso:country":"BE",
    "sg:address":"Lodewijk Dosfelstraat 3",
    "sg:city":"Izegem",
    "sg:orig_category":"Koerierbedrijven",
    "sg:phone":"+32 51 31 65 30",
    "sg:postcode":"8870",
    "sg:province":"West-Vlaanderen",
    "wof:name":"Blancke-debuck",
    "wof:placetype":"venue"
},
  "geometry": {"coordinates":[3.2284150124,50.9274177551],"type":"Point"}
}