{
  "type": "Feature",
  "properties": {
    "iso:country":"BE",
    "sg:address":"Bosstraat 3",
    "sg:city":"Bree",
    "sg:orig_category":"Artistes ind\u00e9pendants",
    "sg:phone":"+32 89 86 30 41",
    "sg:postcode":"3960",
    "sg:province":"Limburg",
    "wof:name":"R. Philipsen",
    "wof:placetype":"venue"
},
  "geometry": {"coordinates":[5.656539917,51.1269454956],"type":"Point"}
}