{
  "type": "Feature",
  "properties": {
    "addr:full":"Polydoor De Paepestraat 20b1 Aalst Oost-Vlaanderen 9300",
    "addr:housenumber":"20b1",
    "addr:postcode":"9300",
    "addr:street":"Paepestraat",
    "iso:country":"BE",
    "sg:address":"Polydoor De Paepestraat 20b1",
    "sg:city":"Aalst",
    "sg:classifiers":[
        {
            "category":"Communications",
            "subcategory":"Radio Station",
            "type":"Services"
        }
    ],
    "sg:phone":"+32 53 21 12 82",
    "sg:postcode":"9300",
    "sg:province":"Oost-Vlaanderen",
    "sg:tags":[
        "diffusion",
        "production",
        "de",
        "programme"
    ],
    "wof:name":"Radio Shaba Oldies",
    "wof:placetype":"venue"
},
  "geometry": {"coordinates":[4.0481328964,50.9459342957],"type":"Point"}
}