{
  "type": "Feature",
  "properties": {
    "iso:country":"BE",
    "sg:address":"Hollestraat 4",
    "sg:city":"Meise",
    "sg:classifiers":[
        {
            "category":"Arts & Performance",
            "subcategory":"Music",
            "type":"Entertainment"
        }
    ],
    "sg:phone":"+32 2 269 44 40",
    "sg:postcode":"1860",
    "sg:province":"Vlaams-Brabant",
    "sg:tags":[
        "freelance",
        "musician"
    ],
    "wof:name":"Terra Music Bvba",
    "wof:placetype":"venue"
},
  "geometry": {"coordinates":[4.3392009735,50.9382667542],"type":"Point"}
}