{
  "type": "Feature",
  "properties": {
    "addr:full":"Donkersteeg 22 Gent Oost-Vlaanderen 9000",
    "addr:housenumber":"22",
    "addr:postcode":"9000",
    "addr:street":"Donkersteeg;Oost-Vlaanderen",
    "iso:country":"BE",
    "sg:address":"Donkersteeg 22",
    "sg:city":"Gent",
    "sg:orig_category":"Rev\u00eatements de sols and murs",
    "sg:phone":"+32 9 225 89 11",
    "sg:postcode":"9000",
    "sg:province":"Oost-Vlaanderen",
    "wof:name":"Matmata",
    "wof:placetype":"venue"
},
  "geometry": {"coordinates":[3.7237670422,51.0544624329],"type":"Point"}
}