{
  "type": "Feature",
  "properties": {
    "addr:full":"Bercheux 28 Vaux-sur-s\u00dbre Luxembourg 6640",
    "addr:housenumber":"28",
    "addr:postcode":"6640",
    "addr:street":"Bercheux",
    "iso:country":"BE",
    "sg:address":"Bercheux 28",
    "sg:city":"Vaux-sur-s\u00dbre",
    "sg:orig_category":"Herstellingen and onderhoud van auto's",
    "sg:phone":"+32 61 25 52 66",
    "sg:postcode":"6640",
    "sg:province":"Luxembourg",
    "wof:name":"Richard Thirion",
    "wof:placetype":"venue"
},
  "geometry": {"coordinates":[5.5671000481,49.91065979],"type":"Point"}
}