{
  "type": "Feature",
  "properties": {
    "addr:full":"Rue De L'etang 4ba Fleurus Hainaut 6223",
    "addr:postcode":"4ba;6223",
    "addr:street":"Rue De L'Etang;Hainaut",
    "iso:country":"BE",
    "sg:address":"Rue De L'etang 4ba",
    "sg:city":"Fleurus",
    "sg:orig_category":"Travaux d'isolation",
    "sg:phone":"+32 71 81 34 42",
    "sg:postcode":"6223",
    "sg:province":"Hainaut",
    "wof:name":"Entret. S\u00c9curite Energie",
    "wof:placetype":"venue"
},
  "geometry": {"coordinates":[4.5271501541,50.5224304199],"type":"Point"}
}