{
  "type": "Feature",
  "properties": {
    "addr:full":"Rue Du Marais 15b1 La Louviere Hainaut 7110",
    "addr:housenumber":"15b1",
    "addr:postcode":"7110",
    "addr:street":"Rue Du Marais",
    "iso:country":"BE",
    "sg:address":"Rue Du Marais 15b1",
    "sg:city":"La Louviere",
    "sg:orig_category":"Bouwmaterialen Gh Vloer- and muurbekleding",
    "sg:phone":"+32 64 22 01 06",
    "sg:postcode":"7110",
    "sg:province":"Hainaut",
    "wof:name":"Fe. Salamone",
    "wof:placetype":"venue"
},
  "geometry": {"coordinates":[4.1505050659,50.4826698303],"type":"Point"}
}