{
  "type": "Feature",
  "properties": {
    "iso:country":"BE",
    "sg:address":"Rue De Namur 179",
    "sg:city":"Nivelles",
    "sg:orig_category":"Librairies. Tabac. Journaux",
    "sg:phone":"+32 67 21 35 50",
    "sg:postcode":"1400",
    "sg:province":"Brabant Wallon",
    "wof:name":"Librairie De La Gare",
    "wof:placetype":"venue"
},
  "geometry": {"coordinates":[4.3336420059,50.5995674133],"type":"Point"}
}