{
  "type": "Feature",
  "properties": {
    "addr:full":"Brusselsesteenweg 10 Herent Vlaams-Brabant 3020",
    "addr:housenumber":"10",
    "addr:postcode":"3020",
    "addr:street":"Brusselsesteenweg",
    "iso:country":"BE",
    "sg:address":"Brusselsesteenweg 10",
    "sg:city":"Herent",
    "sg:classifiers":[
        {
            "category":"Shopping",
            "subcategory":"Crafts & Fabrics",
            "type":"Retail Goods"
        }
    ],
    "sg:phone":"+32 16 23 14 31",
    "sg:postcode":"3020",
    "sg:province":"Vlaams-Brabant",
    "sg:tags":[
        "paints",
        "varnish",
        "-",
        "lacquers",
        "enamel"
    ],
    "wof:name":"Thiry Paul Paints",
    "wof:placetype":"venue"
},
  "geometry": {"coordinates":[4.6696820259,50.8863296509],"type":"Point"}
}