{
  "type": "Feature",
  "properties": {
    "addr:full":"Hi\u00e8rdavoie 5 Chaudfontaine Li\u00e8ge 4050",
    "addr:housenumber":"5",
    "addr:postcode":"4050",
    "addr:street":"Hie\u0300Rdavoie",
    "iso:country":"BE",
    "sg:address":"Hi\u00e8rdavoie 5",
    "sg:city":"Chaudfontaine",
    "sg:classifiers":[
        {
            "category":"Building & Trades",
            "subcategory":"Pest Control",
            "type":"Services"
        }
    ],
    "sg:phone":"+32 4 368 84 49",
    "sg:postcode":"4050",
    "sg:province":"Li\u00e8ge",
    "sg:tags":[
        "painting",
        "contractor"
    ],
    "wof:name":"Perr\u00e9e L",
    "wof:placetype":"venue"
},
  "geometry": {"coordinates":[5.6383738518,50.5757141113],"type":"Point"}
}