{
  "type": "Feature",
  "properties": {
    "iso:country":"BE",
    "sg:address":"Biesemstraat 21",
    "sg:city":"Geetbets",
    "sg:orig_category":"Producteurs de l\u00e9gumes",
    "sg:phone":"+32 11 58 12 47",
    "sg:postcode":"3454",
    "sg:province":"Vlaams-Brabant",
    "wof:name":"Emile Gijsens",
    "wof:placetype":"venue"
},
  "geometry": {"coordinates":[5.1571650505,50.8980751038],"type":"Point"}
}