{
  "type": "Feature",
  "properties": {
    "addr:full":"Grote Moerstraat 103 Brugge (sint-andries) West-Vlaanderen 8200",
    "addr:housenumber":"103",
    "addr:postcode":"8200",
    "addr:street":"Grote Moerstraat",
    "iso:country":"BE",
    "sg:address":"Grote Moerstraat 103",
    "sg:city":"Brugge (sint-andries)",
    "sg:classifiers":[
        {
            "category":"Professional",
            "subcategory":"Accounting & Tax Preparation",
            "type":"Services"
        }
    ],
    "sg:phone":"+32 50 32 03 32",
    "sg:postcode":"8200",
    "sg:province":"West-Vlaanderen",
    "sg:tags":[
        "bookkeeper"
    ],
    "wof:name":"Hermans I",
    "wof:placetype":"venue"
},
  "geometry": {"coordinates":[3.1575660706,51.2068481445],"type":"Point"}
}