{
  "type": "Feature",
  "properties": {
    "addr:full":"Rue Des Alouettes 12 Hotton Luxembourg 6990",
    "addr:housenumber":"12",
    "addr:postcode":"6990",
    "addr:street":"Rue Des Alouettes",
    "iso:country":"BE",
    "sg:address":"Rue Des Alouettes 12",
    "sg:city":"Hotton",
    "sg:classifiers":[
        {
            "category":"Recreation",
            "type":"Entertainment"
        }
    ],
    "sg:phone":"+32 84 46 68 74",
    "sg:postcode":"6990",
    "sg:province":"Luxembourg",
    "sg:tags":[
        "diver",
        "amusement"
    ],
    "wof:name":"D.j. Honeymoon",
    "wof:placetype":"venue"
},
  "geometry": {"coordinates":[5.4352607727,50.265827179],"type":"Point"}
}