{
  "type": "Feature",
  "properties": {
    "iso:country":"BE",
    "sg:address":"Rue Joseph Lescrenier 31",
    "sg:city":"Awans (oth\u00e9e)",
    "sg:classifiers":[
        {
            "category":"Building & Trades",
            "subcategory":"Landscaping Services",
            "type":"Services"
        }
    ],
    "sg:phone":"+32 495 17 13 87",
    "sg:postcode":"4340",
    "sg:province":"Li\u00e8ge",
    "sg:tags":[
        "-",
        "lopping",
        "work",
        "tree",
        "felling"
    ],
    "wof:name":"Agri Dany Scevenels",
    "wof:placetype":"venue"
},
  "geometry": {"coordinates":[5.4704051018,50.7177963257],"type":"Point"}
}