{
  "type": "Feature",
  "properties": {
    "addr:full":"Kolonel Begaultlaan 15 Leuven Vlaams-Brabant 3012",
    "addr:housenumber":"15",
    "addr:postcode":"3012",
    "addr:street":"Kolonel Begaultlaan",
    "iso:country":"BE",
    "sg:address":"Kolonel Begaultlaan 15",
    "sg:city":"Leuven",
    "sg:orig_category":"Baby- and kinderkleding Dameskledingzaken Herenkledingzaken",
    "sg:phone":"+32 16 23 70 77",
    "sg:postcode":"3012",
    "sg:province":"Vlaams-Brabant",
    "wof:name":"Superconfex",
    "wof:placetype":"venue"
},
  "geometry": {"coordinates":[4.7059540749,50.8914337158],"type":"Point"}
}