{
  "type": "Feature",
  "properties": {
    "addr:full":"Rue De L\u00b4amende 21 Walhain Brabant Wallon 1457",
    "addr:housenumber":"21;1457",
    "addr:street":"Rue De L\u00b4Amende",
    "iso:country":"BE",
    "sg:address":"Rue De L\u00b4amende 21",
    "sg:city":"Walhain",
    "sg:orig_category":"Installation de menuiserie en bois and plastique. Plomberie, chauffage and installations sanitaires.",
    "sg:phone":"+32 10 65 66 89",
    "sg:postcode":"1457",
    "sg:province":"Brabant Wallon",
    "wof:name":"Menuiserie D.s.r.",
    "wof:placetype":"venue"
},
  "geometry": {"coordinates":[4.6928248405,50.6106987],"type":"Point"}
}