{
  "type": "Feature",
  "properties": {
    "addr:full":"Monacoplein 1 Oostende West-Vlaanderen 8400",
    "addr:housenumber":"1",
    "addr:postcode":"8400",
    "addr:street":"Monacoplein",
    "iso:country":"BE",
    "sg:address":"Monacoplein 1",
    "sg:city":"Oostende",
    "sg:orig_category":"Dierenartsen",
    "sg:phone":"+32 59 51 36 15",
    "sg:postcode":"8400",
    "sg:province":"West-Vlaanderen",
    "wof:name":"Irene Benoot",
    "wof:placetype":"venue"
},
  "geometry": {"coordinates":[2.9125471115,51.2313194275],"type":"Point"}
}