{
  "type": "Feature",
  "properties": {
    "addr:full":"Rue Caulier 91 Soignies (neufvilles) Hainaut 7063",
    "addr:housenumber":"91",
    "addr:postcode":"7063",
    "addr:street":"Rue Caulier",
    "iso:country":"BE",
    "sg:address":"Rue Caulier 91",
    "sg:city":"Soignies (neufvilles)",
    "sg:classifiers":[
        {
            "category":"Personal",
            "subcategory":"Beauty Salon",
            "type":"Services"
        }
    ],
    "sg:phone":"+32 67 33 56 44",
    "sg:postcode":"7063",
    "sg:province":"Hainaut",
    "sg:tags":[
        "lady",
        "-",
        "hairdressing"
    ],
    "wof:name":"Chantal",
    "wof:placetype":"venue"
},
  "geometry": {"coordinates":[3.993940115,50.5837898254],"type":"Point"}
}