{
  "type": "Feature",
  "properties": {
    "iso:country":"BE",
    "sg:address":"Koning - Albertstraat 26",
    "sg:city":"Geel",
    "sg:classifiers":[
        {
            "category":"Real Estate",
            "subcategory":"Real Estate Services",
            "type":"Services"
        }
    ],
    "sg:phone":"+32 14 58 00 82",
    "sg:postcode":"2440",
    "sg:province":"Antwerpen",
    "wof:name":"Imco Vastgoedmakelaar",
    "wof:placetype":"venue"
},
  "geometry": {"coordinates":[4.9832811356,51.1463088989],"type":"Point"}
}