{
  "type": "Feature",
  "properties": {
    "addr:full":"Outre-cour 32bd Herve Li\u00e8ge 4651",
    "addr:housenumber":"32bd",
    "addr:postcode":"4651",
    "addr:street":"Outre-Cour",
    "iso:country":"BE",
    "sg:address":"Outre-cour 32bd",
    "sg:city":"Herve",
    "sg:orig_category":"Dakwerken",
    "sg:phone":"+32 87 67 80 46",
    "sg:postcode":"4651",
    "sg:province":"Li\u00e8ge",
    "wof:name":"Louis Toitures",
    "wof:placetype":"venue"
},
  "geometry": {"coordinates":[5.7796068192,50.638885498],"type":"Point"}
}