{
  "type": "Feature",
  "properties": {
    "addr:full":"Rue De Gilly 162 Couillet Hainaut 6010",
    "addr:housenumber":"162",
    "addr:postcode":"6010",
    "addr:street":"Rue De Gilly",
    "iso:country":"BE",
    "sg:address":"Rue De Gilly 162",
    "sg:city":"Couillet",
    "sg:orig_category":"RESTAURANTS: BARS",
    "sg:phone":"+32 71 47 71 71",
    "sg:postcode":"6010",
    "sg:province":"Hainaut",
    "wof:name":"Taverne Club F1",
    "wof:placetype":"venue"
},
  "geometry": {"coordinates":[4.4704651833,50.3909263611],"type":"Point"}
}