{
  "type": "Feature",
  "properties": {
    "addr:full":"Sint-bavostraat 66 Wilrijk Antwerpen 2610",
    "addr:housenumber":"66",
    "addr:postcode":"2610",
    "addr:street":"Sint-Bavostraat;Antwerpen",
    "iso:country":"BE",
    "sg:address":"Sint-bavostraat 66",
    "sg:city":"Wilrijk",
    "sg:classifiers":[
        {
            "category":"Professional",
            "subcategory":"Printing & Photocopies",
            "type":"Services"
        }
    ],
    "sg:phone":"+32 3 821 09 00",
    "sg:postcode":"2610",
    "sg:province":"Antwerpen",
    "sg:tags":[
        "paper",
        "raw",
        "material",
        "-",
        "cardboard"
    ],
    "wof:name":"L. Lacroix & Fils Nv",
    "wof:placetype":"venue"
},
  "geometry": {"coordinates":[4.4059038162,51.1714172363],"type":"Point"}
}