{
  "type": "Feature",
  "properties": {
    "iso:country":"BE",
    "sg:address":"Lieven Bauwensstraat 3",
    "sg:city":"Brugge",
    "sg:orig_category":"Mat\u00e9riaux de construction Travaux d'isolation",
    "sg:phone":"+32 50 31 34 05",
    "sg:postcode":"8200",
    "sg:province":"West-Vlaanderen",
    "wof:name":"F.i.m.",
    "wof:placetype":"venue"
},
  "geometry": {"coordinates":[3.1990439892,51.2132720947],"type":"Point"}
}