{
  "type": "Feature",
  "properties": {
    "iso:country":"BE",
    "sg:address":"Place De Bal\u00e2tre 120-123",
    "sg:city":"Jemeppe-sur-sambre (bal\u00e2tre)",
    "sg:classifiers":[
        {
            "category":"Organizations",
            "subcategory":"Professional Association",
            "type":"Services"
        }
    ],
    "sg:phone":"+32 81 63 40 04",
    "sg:postcode":"5190",
    "sg:province":"Namur",
    "sg:tags":[
        "organisation",
        "seminar"
    ],
    "wof:name":"Campagnette (la)",
    "wof:placetype":"venue"
},
  "geometry": {"coordinates":[4.6703448296,50.4645042419],"type":"Point"}
}