{
  "type": "Feature",
  "properties": {
    "iso:country":"BE",
    "sg:address":"Ikaroslaan 13",
    "sg:city":"Zaventem",
    "sg:classifiers":[
        {
            "category":"Professional",
            "subcategory":"Computer Services",
            "type":"Services"
        }
    ],
    "sg:phone":"+32 2 757 00 20",
    "sg:postcode":"1930",
    "sg:province":"Vlaams-Brabant",
    "sg:tags":[
        "-",
        "processing",
        "data",
        "software"
    ],
    "wof:name":"National Instruments Belgium Nv",
    "wof:placetype":"venue"
},
  "geometry": {"coordinates":[4.4920759201,50.8753395081],"type":"Point"}
}