{
  "type": "Feature",
  "properties": {
    "addr:full":"Rue L\u00e9on Delacroix 15 Bruxelles (anderlecht) Bruxelles-Capitale 1070",
    "addr:housenumber":"15",
    "addr:postcode":"1070",
    "addr:street":"Rue Le\u0301On Delacroix",
    "iso:country":"BE",
    "sg:address":"Rue L\u00e9on Delacroix 15",
    "sg:city":"Bruxelles (anderlecht)",
    "sg:classifiers":[
        {
            "category":"Food & Beverages",
            "subcategory":"Groceries & Convenience Stores",
            "type":"Retail Goods"
        }
    ],
    "sg:phone":"+32 2 523 41 54",
    "sg:postcode":"1070",
    "sg:province":"Bruxelles-Capitale",
    "sg:tags":[
        "grocer"
    ],
    "wof:name":"Sitar Sprl",
    "wof:placetype":"venue"
},
  "geometry": {"coordinates":[4.3300552368,50.8428344727],"type":"Point"}
}