{
  "type": "Feature",
  "properties": {
    "iso:country":"BE",
    "sg:address":"Peperstraat 24",
    "sg:city":"Beveren",
    "sg:orig_category":"Boekhouders",
    "sg:phone":"+32 3 755 59 66",
    "sg:postcode":"9120",
    "sg:province":"Oost-Vlaanderen",
    "wof:name":"Alain Rombaut",
    "wof:placetype":"venue"
},
  "geometry": {"coordinates":[4.256360054,51.2114677429],"type":"Point"}
}