{
  "type": "Feature",
  "properties": {
    "addr:full":"Rue Des V\u00e9hinnes 20 Lierneux Li\u00e8ge 4990",
    "addr:housenumber":"20",
    "addr:postcode":"4990",
    "addr:street":"Rue Des Ve\u0301Hinnes",
    "iso:country":"BE",
    "sg:address":"Rue Des V\u00e9hinnes 20",
    "sg:city":"Lierneux",
    "sg:classifiers":[
        {
            "category":"Home & Garden",
            "subcategory":"Building Materials",
            "type":"Retail Goods"
        }
    ],
    "sg:phone":"+32 80 31 95 65",
    "sg:postcode":"4990",
    "sg:province":"Li\u00e8ge",
    "sg:tags":[
        "window"
    ],
    "wof:name":"Denis J C Sprl",
    "wof:placetype":"venue"
},
  "geometry": {"coordinates":[5.7932181358,50.2856826782],"type":"Point"}
}