{
  "type": "Feature",
  "properties": {
    "iso:country":"BE",
    "sg:address":"St Annastraat 13",
    "sg:city":"Lubbeek",
    "sg:orig_category":"Entretien and r\u00e9parations de voitures",
    "sg:phone":"+32 16 62 22 30",
    "sg:postcode":"3210",
    "sg:province":"Vlaams-Brabant",
    "wof:name":"Albert Everaerts",
    "wof:placetype":"venue"
},
  "geometry": {"coordinates":[4.8377380371,50.8930587769],"type":"Point"}
}