{
  "type": "Feature",
  "properties": {
    "iso:country":"BE",
    "sg:address":"Heidestraat 12",
    "sg:city":"Wichelen",
    "sg:orig_category":"Vakantiehuizen",
    "sg:phone":"+32 9 369 31 58",
    "sg:postcode":"9260",
    "sg:province":"Oost-Vlaanderen",
    "wof:name":"De Zonnebloem",
    "wof:placetype":"venue"
},
  "geometry": {"coordinates":[3.9771161079,50.9866905212],"type":"Point"}
}