{
  "type": "Feature",
  "properties": {
    "addr:full":"J. De Sint-genoisstraat 91 Gent Oost-Vlaanderen 9050",
    "addr:housenumber":"91",
    "addr:postcode":"9050",
    "addr:street":"J. De Sint-Genoisstraat;Oost-Vlaanderen",
    "iso:country":"BE",
    "sg:address":"J. De Sint-genoisstraat 91",
    "sg:city":"Gent",
    "sg:orig_category":"Cr\u00e8ches and garderies d'enfants",
    "sg:phone":"+32 9 230 71 71",
    "sg:postcode":"9050",
    "sg:province":"Oost-Vlaanderen",
    "wof:name":"Stedelijke Peutertuin",
    "wof:placetype":"venue"
},
  "geometry": {"coordinates":[3.7577409744,51.0287284851],"type":"Point"}
}