{
  "type": "Feature",
  "properties": {
    "addr:full":"Rue Sotteni\u00c8re 2 Lessines Hainaut 7862",
    "addr:housenumber":"2",
    "addr:postcode":"7862",
    "addr:street":"Rue Sottenie\u0300Re;Hainaut",
    "iso:country":"BE",
    "sg:address":"Rue Sotteni\u00c8re 2",
    "sg:city":"Lessines",
    "sg:orig_category":"Rundveehouders",
    "sg:phone":"+32 68 44 78 39",
    "sg:postcode":"7862",
    "sg:province":"Hainaut",
    "wof:name":"Jacques Mouligneau",
    "wof:placetype":"venue"
},
  "geometry": {"coordinates":[3.7770729065,50.7332267761],"type":"Point"}
}