{
  "type": "Feature",
  "properties": {
    "addr:full":"Chauss\u00e9e De Marche 584 Namur (erpent) Namur 5101",
    "addr:housenumber":"584",
    "addr:postcode":"5101",
    "addr:street":"Chausse\u0301E De Marche",
    "iso:country":"BE",
    "sg:address":"Chauss\u00e9e De Marche 584",
    "sg:city":"Namur (erpent)",
    "sg:classifiers":[
        {
            "category":"Farming",
            "subcategory":"Farm & Veterinary Services",
            "type":"Manufacturing & Wholesale Goods"
        }
    ],
    "sg:phone":"+32 81 30 09 21",
    "sg:postcode":"5101",
    "sg:province":"Namur",
    "sg:tags":[
        "material",
        "cattle-breeding"
    ],
    "wof:name":"Marchal Sprl",
    "wof:placetype":"venue"
},
  "geometry": {"coordinates":[4.9053220749,50.441493988],"type":"Point"}
}