{
  "type": "Feature",
  "properties": {
    "iso:country":"BE",
    "sg:address":"Avenue Des Tarins 6a",
    "sg:city":"Wavre (bierges)",
    "sg:classifiers":[
        {
            "category":"Professional",
            "type":"Services"
        }
    ],
    "sg:phone":"+32 10 41 73 52",
    "sg:postcode":"1301",
    "sg:province":"Brabant Wallon",
    "sg:tags":[
        "surveyor",
        "-",
        "valuer"
    ],
    "wof:name":"Probatex",
    "wof:placetype":"venue"
},
  "geometry": {"coordinates":[4.565489769,50.7220878601],"type":"Point"}
}