{
  "type": "Feature",
  "properties": {
    "addr:full":"Rue De Tr\u00c8ves 25 Brussel/bruxelles Bruxelles-Capitale 1040",
    "addr:housenumber":"25",
    "addr:postcode":"1040",
    "addr:street":"Rue De Tre\u0300Ves;/",
    "iso:country":"BE",
    "sg:address":"Rue De Tr\u00c8ves 25",
    "sg:city":"Brussel/bruxelles",
    "sg:orig_category":"Pr\u00eats hypoth\u00e9caires and cr\u00e9dits immobiliers. Cr\u00e9dit \u00e0 la consommation. Banques and organismes de cr\u00e9",
    "sg:phone":"+32 2 285 20 20",
    "sg:postcode":"1040",
    "sg:province":"Bruxelles-Capitale",
    "wof:name":"Bacob",
    "wof:placetype":"venue"
},
  "geometry": {"coordinates":[4.3870849609,50.8363609314],"type":"Point"}
}