{
  "type": "Feature",
  "properties": {
    "iso:country":"BE",
    "sg:address":"Donksesteenweg 212b22",
    "sg:city":"Brasschaat",
    "sg:classifiers":[
        {
            "category":"Manufacturing",
            "subcategory":"Watercraft",
            "type":"Manufacturing & Wholesale Goods"
        }
    ],
    "sg:phone":"+32 3 542 51 60",
    "sg:postcode":"2930",
    "sg:province":"Antwerpen",
    "sg:tags":[
        "expert"
    ],
    "wof:name":"Incomacs Limited Nv",
    "wof:placetype":"venue"
},
  "geometry": {"coordinates":[4.4540362358,51.2810211182],"type":"Point"}
}