{
  "type": "Feature",
  "properties": {
    "addr:full":"Rue Charraux 3 Profondeville Namur 5170",
    "addr:housenumber":"3",
    "addr:postcode":"5170",
    "addr:street":"Rue Charraux",
    "iso:country":"BE",
    "sg:address":"Rue Charraux 3",
    "sg:city":"Profondeville",
    "sg:classifiers":[
        {
            "category":"Recreation",
            "type":"Entertainment"
        }
    ],
    "sg:phone":"+32 81 43 37 23",
    "sg:postcode":"5170",
    "sg:province":"Namur",
    "sg:tags":[
        "diver",
        "amusement"
    ],
    "wof:name":"Ecole Du Cirque De Jodoigne",
    "wof:placetype":"venue"
},
  "geometry": {"coordinates":[4.8674049377,50.3786392212],"type":"Point"}
}