{
  "type": "Feature",
  "properties": {
    "addr:full":"Halensebaan 49 Bekkevoort Vlaams-Brabant 3461",
    "addr:housenumber":"49",
    "addr:postcode":"3461",
    "addr:street":"Halensebaan",
    "iso:country":"BE",
    "sg:address":"Halensebaan 49",
    "sg:city":"Bekkevoort",
    "sg:orig_category":"Rundveehouders",
    "sg:phone":"+32 16 77 99 42",
    "sg:postcode":"3461",
    "sg:province":"Vlaams-Brabant",
    "wof:name":"Rene Claes",
    "wof:placetype":"venue"
},
  "geometry": {"coordinates":[4.9589829445,50.9208869934],"type":"Point"}
}