{
  "type": "Feature",
  "properties": {
    "addr:full":"Turnhoutsebaan 179 Dessel Antwerpen 2480",
    "addr:housenumber":"179",
    "addr:postcode":"2480",
    "addr:street":"Turnhoutsebaan",
    "iso:country":"BE",
    "sg:address":"Turnhoutsebaan 179",
    "sg:city":"Dessel",
    "sg:classifiers":[
        {
            "category":"Autos & Motor Vehicles",
            "subcategory":"Automobile Sales",
            "type":"Retail Goods"
        }
    ],
    "sg:phone":"+32 14 37 29 38",
    "sg:postcode":"2480",
    "sg:province":"Antwerpen",
    "sg:tags":[
        "car",
        "used",
        "-"
    ],
    "wof:name":"Special Cars Stappers R",
    "wof:placetype":"venue"
},
  "geometry": {"coordinates":[5.107667923,51.2509422302],"type":"Point"}
}