{
  "type": "Feature",
  "properties": {
    "addr:full":"Rue Royale 10 Bruxelles Bruxelles-Capitale 1000",
    "addr:housenumber":"10",
    "addr:postcode":"1000",
    "addr:street":"Rue Royale",
    "iso:country":"BE",
    "sg:address":"Rue Royale 10",
    "sg:city":"Bruxelles",
    "sg:classifiers":[
        {
            "category":"Arts & Performance",
            "subcategory":"Theater",
            "type":"Entertainment"
        }
    ],
    "sg:phone":"+32 2 507 82 00",
    "sg:postcode":"1000",
    "sg:province":"Bruxelles-Capitale",
    "sg:tags":[
        "concert-halls",
        "theatre"
    ],
    "wof:name":"Paleis Voor Schone Kunsten (het)",
    "wof:placetype":"venue"
},
  "geometry": {"coordinates":[4.3603219986,50.8430595398],"type":"Point"}
}