{
  "type": "Feature",
  "properties": {
    "addr:full":"Haasdonkse Steenweg 131 Sint-niklaas Oost-Vlaanderen 9100",
    "addr:housenumber":"131",
    "addr:postcode":"9100",
    "addr:street":"Steenweg",
    "iso:country":"BE",
    "sg:address":"Haasdonkse Steenweg 131",
    "sg:city":"Sint-niklaas",
    "sg:classifiers":[
        {
            "category":"Professional",
            "subcategory":"Accounting & Tax Preparation",
            "type":"Services"
        }
    ],
    "sg:phone":"+32 3 771 47 66",
    "sg:postcode":"9100",
    "sg:province":"Oost-Vlaanderen",
    "sg:tags":[
        "accountant",
        "diverse",
        "bedrijfsbeheeradviesbureaus"
    ],
    "wof:name":"Poppe R.",
    "wof:placetype":"venue"
},
  "geometry": {"coordinates":[4.2116041183,51.1686782837],"type":"Point"}
}