{
  "type": "Feature",
  "properties": {
    "addr:full":"Eikelstraat 20 Lier Antwerpen 2500",
    "addr:housenumber":"20",
    "addr:postcode":"2500",
    "addr:street":"Eikelstraat",
    "iso:country":"BE",
    "sg:address":"Eikelstraat 20",
    "sg:city":"Lier",
    "sg:classifiers":[
        {
            "category":"Bars & Pubs",
            "type":"Food & Drink"
        }
    ],
    "sg:phone":"+32 3 480 20 03",
    "sg:postcode":"2500",
    "sg:province":"Antwerpen",
    "wof:name":"Caf\u00c9 Blanch\u00c9",
    "wof:placetype":"venue"
},
  "geometry": {"coordinates":[4.5689997673,51.1302185059],"type":"Point"}
}