{
  "type": "Feature",
  "properties": {
    "iso:country":"BE",
    "sg:address":"Itali\u00eblei 46",
    "sg:city":"Antwerpen",
    "sg:classifiers":[
        {
            "category":"Health Services",
            "subcategory":"Doctor",
            "type":"Services"
        }
    ],
    "sg:phone":"+32 475 41 80 81",
    "sg:postcode":"2000",
    "sg:province":"Antwerpen",
    "sg:tags":[
        "medicinephysicians",
        "surgeon"
    ],
    "wof:name":"De Beule Jurgen",
    "wof:placetype":"venue"
},
  "geometry": {"coordinates":[4.4148011208,51.2242965698],"type":"Point"}
}