{
  "type": "Feature",
  "properties": {
    "addr:full":"Bavikhoofsestraat 144 Kuurne West-Vlaanderen 8520",
    "addr:housenumber":"144",
    "addr:postcode":"8520",
    "addr:street":"Bavikhoofsestraat",
    "iso:country":"BE",
    "sg:address":"Bavikhoofsestraat 144",
    "sg:city":"Kuurne",
    "sg:classifiers":[
        {
            "category":"Food & Beverages",
            "subcategory":"Groceries & Convenience Stores",
            "type":"Retail Goods"
        }
    ],
    "sg:phone":"+32 56 72 26 56",
    "sg:postcode":"8520",
    "sg:province":"West-Vlaanderen",
    "sg:tags":[
        "grocer"
    ],
    "wof:name":"'t Smulderke",
    "wof:placetype":"venue"
},
  "geometry": {"coordinates":[3.2938899994,50.8570899963],"type":"Point"}
}