{
  "type": "Feature",
  "properties": {
    "iso:country":"BE",
    "sg:address":"Terkamerenboslaan 187",
    "sg:city":"Elsene/ixelles",
    "sg:orig_category":"Artiesten and kunstenaars",
    "sg:phone":"+32 2 649 09 96",
    "sg:postcode":"1050",
    "sg:province":"Bruxelles-Capitale",
    "wof:name":"Michel Vanderlinden",
    "wof:placetype":"venue"
},
  "geometry": {"coordinates":[4.3902449608,50.8069267273],"type":"Point"}
}