{
  "type": "Feature",
  "properties": {
    "addr:full":"Cabocheriestraat 74 Moeskroen/mouscron Hainaut 7711",
    "addr:housenumber":"74",
    "addr:postcode":"7711",
    "addr:street":"Cabocheriestraat",
    "iso:country":"BE",
    "sg:address":"Cabocheriestraat 74",
    "sg:city":"Moeskroen/mouscron",
    "sg:orig_category":"Plaatsen van vloer- and muurbekleding Schilders Verlichting and huishoudartikelen",
    "sg:phone":"+32 56 48 64 95",
    "sg:postcode":"7711",
    "sg:province":"Hainaut",
    "wof:name":"Luc Theuninck",
    "wof:placetype":"venue"
},
  "geometry": {"coordinates":[3.322259903,50.7312355042],"type":"Point"}
}