{
  "type": "Feature",
  "properties": {
    "addr:full":"Hameau De Xhignesse 10 Hamoir Li\u00e8ge 4180",
    "addr:housenumber":"10",
    "addr:postcode":"4180",
    "addr:street":"Hameau De Xhignesse",
    "iso:country":"BE",
    "sg:address":"Hameau De Xhignesse 10",
    "sg:city":"Hamoir",
    "sg:classifiers":[
        {
            "category":"Building & Trades",
            "subcategory":"Electrical",
            "type":"Services"
        }
    ],
    "sg:phone":"+32 86 38 80 87",
    "sg:postcode":"4180",
    "sg:province":"Li\u00e8ge",
    "sg:tags":[
        "electric",
        "-",
        "housewiring",
        "contractor"
    ],
    "wof:name":"Angot F",
    "wof:placetype":"venue"
},
  "geometry": {"coordinates":[5.5420222282,50.4285926819],"type":"Point"}
}