{
  "type": "Feature",
  "properties": {
    "addr:full":"Avenue Henri Bourgys 14 Waterloo Brabant Wallon 1410",
    "addr:housenumber":"14",
    "addr:postcode":"1410",
    "addr:street":"Avenue Henri Bourgys",
    "iso:country":"BE",
    "sg:address":"Avenue Henri Bourgys 14",
    "sg:city":"Waterloo",
    "sg:orig_category":"V\u00e9t\u00e9rinaires",
    "sg:phone":"+32 2 353 09 75",
    "sg:postcode":"1410",
    "sg:province":"Brabant Wallon",
    "wof:name":"Renaud Vander Elst",
    "wof:placetype":"venue"
},
  "geometry": {"coordinates":[4.3980789185,50.7287406921],"type":"Point"}
}