{
  "type": "Feature",
  "properties": {
    "iso:country":"BE",
    "sg:address":"Rue Laurent Heirbaut 14",
    "sg:city":"Ganshoren",
    "sg:classifiers":[
        {
            "category":"Arena",
            "subcategory":"Sports Club",
            "type":"Entertainment"
        }
    ],
    "sg:phone":"+32 2 465 92 44",
    "sg:postcode":"1083",
    "sg:province":"Bruxelles-Capitale",
    "sg:tags":[
        "de"
    ],
    "wof:name":"B.c. Fresh Air Jette",
    "wof:placetype":"venue"
},
  "geometry": {"coordinates":[4.3052840233,50.8697319031],"type":"Point"}
}