{
  "type": "Feature",
  "properties": {
    "addr:full":"Leliestraat 8 Lovendegem Oost-Vlaanderen 9920",
    "addr:housenumber":"8",
    "addr:postcode":"9920",
    "addr:street":"Leliestraat",
    "iso:country":"BE",
    "sg:address":"Leliestraat 8",
    "sg:city":"Lovendegem",
    "sg:classifiers":[
        {
            "category":"Health Services",
            "subcategory":"Dentist",
            "type":"Services"
        }
    ],
    "sg:phone":"+32 9 372 52 21",
    "sg:postcode":"9920",
    "sg:province":"Oost-Vlaanderen",
    "wof:name":"Cocquyt J",
    "wof:placetype":"venue"
},
  "geometry": {"coordinates":[3.6324019432,51.1060256958],"type":"Point"}
}