{
  "type": "Feature",
  "properties": {
    "iso:country":"BE",
    "sg:address":"Turnhoutsebaan 34",
    "sg:city":"Malle (oostmalle)",
    "sg:classifiers":[
        {
            "category":"Health Services",
            "subcategory":"Health Practitioner",
            "type":"Services"
        }
    ],
    "sg:phone":"+32 3 309 09 25",
    "sg:postcode":"2390",
    "sg:province":"Antwerpen",
    "sg:tags":[
        "physiotherapist"
    ],
    "wof:name":"Onsia Inne",
    "wof:placetype":"venue"
},
  "geometry": {"coordinates":[4.7368922234,51.3011131287],"type":"Point"}
}