{
  "type": "Feature",
  "properties": {
    "iso:country":"BE",
    "sg:address":"Wollemarkt 5",
    "sg:city":"Mechelen",
    "sg:orig_category":"Antiquit\u00e9s",
    "sg:phone":"+32 15 29 11 73",
    "sg:postcode":"2800",
    "sg:province":"Antwerpen",
    "wof:name":"Richard Boudwijns",
    "wof:placetype":"venue"
},
  "geometry": {"coordinates":[4.4787249565,51.0296478271],"type":"Point"}
}