{
  "type": "Feature",
  "properties": {
    "addr:full":"Parkstraat 180 Leuven Vlaams-Brabant 3000",
    "addr:housenumber":"180",
    "addr:postcode":"3000",
    "addr:street":"Parkstraat",
    "iso:country":"BE",
    "sg:address":"Parkstraat 180",
    "sg:city":"Leuven",
    "sg:orig_category":"D\u00e9m\u00e9nagements",
    "sg:phone":"+32 16 23 92 22",
    "sg:postcode":"3000",
    "sg:province":"Vlaams-Brabant",
    "wof:name":"A. Romulus",
    "wof:placetype":"venue"
},
  "geometry": {"coordinates":[4.7065858841,50.8699493408],"type":"Point"}
}