{
  "type": "Feature",
  "properties": {
    "addr:full":"Viooltjesstraat 4 Wevelgem West-Vlaanderen 8560",
    "addr:housenumber":"4",
    "addr:postcode":"8560",
    "addr:street":"Viooltjesstraat",
    "iso:country":"BE",
    "sg:address":"Viooltjesstraat 4",
    "sg:city":"Wevelgem",
    "sg:classifiers":[
        {
            "category":"Food & Beverages",
            "subcategory":"Fruits & Vegetables",
            "type":"Retail Goods"
        }
    ],
    "sg:phone":"+32 56 40 40 19",
    "sg:postcode":"8560",
    "sg:province":"West-Vlaanderen",
    "sg:tags":[
        "-"
    ],
    "wof:name":"Glorieux-feys",
    "wof:placetype":"venue"
},
  "geometry": {"coordinates":[3.1743779182,50.8161125183],"type":"Point"}
}