{
  "type": "Feature",
  "properties": {
    "iso:country":"BE",
    "sg:address":"Camp Et Haie 41",
    "sg:city":"Ellezelles",
    "sg:classifiers":[
        {
            "category":"Wholesale",
            "subcategory":"Machinery & Supplies",
            "type":"Manufacturing & Wholesale Goods"
        }
    ],
    "sg:phone":"+32 68 54 38 39",
    "sg:postcode":"7890",
    "sg:province":"Hainaut",
    "sg:tags":[
        "refrigeration",
        "-",
        "industrial",
        "commercial",
        "equipment"
    ],
    "wof:name":"Techno-cool Sprl",
    "wof:placetype":"venue"
},
  "geometry": {"coordinates":[3.668790102,50.7249298096],"type":"Point"}
}