{
  "type": "Feature",
  "properties": {
    "iso:country":"BE",
    "sg:address":"Franklin Rooseveltlaan 350e",
    "sg:city":"Gent",
    "sg:classifiers":[
        {
            "category":"Professional",
            "type":"Services"
        }
    ],
    "sg:phone":"+32 9 330 57 52",
    "sg:postcode":"9000",
    "sg:province":"Oost-Vlaanderen",
    "sg:tags":[
        "industrial",
        "automation"
    ],
    "wof:name":"Exterma Bvba",
    "wof:placetype":"venue"
},
  "geometry": {"coordinates":[3.730989933,51.0456314087],"type":"Point"}
}