{
  "type": "Feature",
  "properties": {
    "iso:country":"BE",
    "sg:address":"Rue Cour Boisacq 106",
    "sg:city":"Wavre (bierges)",
    "sg:classifiers":[
        {
            "category":"Building & Trades",
            "subcategory":"Construction",
            "type":"Services"
        }
    ],
    "sg:phone":"+32 10 24 26 24",
    "sg:postcode":"1301",
    "sg:province":"Brabant Wallon",
    "sg:tags":[
        "carpenter"
    ],
    "wof:name":"Verstraelen (ets)",
    "wof:placetype":"venue"
},
  "geometry": {"coordinates":[4.5824360847,50.7090492249],"type":"Point"}
}