{
  "type": "Feature",
  "properties": {
    "addr:full":"Borrekent 85 Haaltert (denderhoutem) Oost-Vlaanderen 9450",
    "addr:housenumber":"85",
    "addr:postcode":"9450",
    "addr:street":"Borrekent",
    "iso:country":"BE",
    "sg:address":"Borrekent 85",
    "sg:city":"Haaltert (denderhoutem)",
    "sg:classifiers":[
        {
            "category":"Building & Trades",
            "subcategory":"Pest Control",
            "type":"Services"
        }
    ],
    "sg:phone":"+32 54 33 07 62",
    "sg:postcode":"9450",
    "sg:province":"Oost-Vlaanderen",
    "sg:tags":[
        "painting",
        "contractor"
    ],
    "wof:name":"Ghysels M",
    "wof:placetype":"venue"
},
  "geometry": {"coordinates":[4.0007491112,50.8742103577],"type":"Point"}
}