{
  "type": "Feature",
  "properties": {
    "addr:full":"Stokstraat 1ba Wellen Limburg 3830",
    "addr:housenumber":"1ba",
    "addr:postcode":"3830",
    "addr:street":"Stokstraat",
    "iso:country":"BE",
    "sg:address":"Stokstraat 1ba",
    "sg:city":"Wellen",
    "sg:orig_category":"Banken and kredietinstellingen",
    "sg:phone":"+32 12 74 27 38",
    "sg:postcode":"3830",
    "sg:province":"Limburg",
    "wof:name":"Fortis",
    "wof:placetype":"venue"
},
  "geometry": {"coordinates":[5.3367447853,50.8412246704],"type":"Point"}
}