{
  "type": "Feature",
  "properties": {
    "iso:country":"BE",
    "sg:address":"Schriekbos 7",
    "sg:city":"Zoersel",
    "sg:classifiers":[
        {
            "category":"Communications",
            "subcategory":"Film & Video Production",
            "type":"Services"
        }
    ],
    "sg:phone":"+32 3 383 35 33",
    "sg:postcode":"2980",
    "sg:province":"Antwerpen",
    "sg:tags":[
        "realisation",
        "-"
    ],
    "wof:name":"Explo Report",
    "wof:placetype":"venue"
},
  "geometry": {"coordinates":[4.6882982254,51.2682151794],"type":"Point"}
}