{
  "type": "Feature",
  "properties": {
    "addr:full":"Rue Philippe Monnoyer 88 Courcelles Hainaut 6180",
    "addr:housenumber":"88",
    "addr:postcode":"6180",
    "addr:street":"Rue Philippe Monnoyer",
    "iso:country":"BE",
    "sg:address":"Rue Philippe Monnoyer 88",
    "sg:city":"Courcelles",
    "sg:classifiers":[
        {
            "category":"Real Estate",
            "subcategory":"Real Estate Services",
            "type":"Services"
        }
    ],
    "sg:phone":"+32 71 46 06 10",
    "sg:postcode":"6180",
    "sg:province":"Hainaut",
    "wof:name":"Immo 1000r",
    "wof:placetype":"venue"
},
  "geometry": {"coordinates":[4.3743700981,50.4565086365],"type":"Point"}
}