{
  "type": "Feature",
  "properties": {
    "addr:full":"Rue Saivelette 8 Housse Li\u00e8ge 4671",
    "addr:housenumber":"8",
    "addr:postcode":"4671",
    "addr:street":"Rue Saivelette",
    "iso:country":"BE",
    "sg:address":"Rue Saivelette 8",
    "sg:city":"Housse",
    "sg:classifiers":[
        {
            "category":"Restaurant",
            "type":"Food & Drink"
        }
    ],
    "sg:phone":"+32 4 387 42 11",
    "sg:postcode":"4671",
    "sg:province":"Li\u00e8ge",
    "wof:name":"Le Jardin De Caroline",
    "wof:placetype":"venue"
},
  "geometry": {"coordinates":[5.6916890144,50.6788330078],"type":"Point"}
}