{
  "type": "Feature",
  "properties": {
    "iso:country":"BE",
    "sg:address":"Gemeentelijk Godshuisstr 1",
    "sg:city":"Watermaal-bosvoorde/watermael-",
    "sg:orig_category":"Banken and kredietinstellingen",
    "sg:phone":"+32 2 660 70 58",
    "sg:postcode":"1170",
    "sg:province":"Bruxelles-Capitale",
    "wof:name":"Fortis",
    "wof:placetype":"venue"
},
  "geometry": {"coordinates":[4.4185090065,50.7992782593],"type":"Point"}
}