{
  "type": "Feature",
  "properties": {
    "iso:country":"BE",
    "sg:address":"Hoeverweg 87",
    "sg:city":"Opglabbeek",
    "sg:classifiers":[
        {
            "category":"Retail",
            "subcategory":"Event Space",
            "type":"Services"
        }
    ],
    "sg:phone":"+32 89 81 00 19",
    "sg:postcode":"3660",
    "sg:province":"Limburg",
    "sg:tags":[
        "rental",
        "-",
        "hall"
    ],
    "wof:name":"Wilhelm Tell",
    "wof:placetype":"venue"
},
  "geometry": {"coordinates":[5.5978770256,51.0284423828],"type":"Point"}
}