{
  "type": "Feature",
  "properties": {
    "iso:country":"BE",
    "sg:address":"Hurtebise 2",
    "sg:city":"Saint-hubert",
    "sg:orig_category":"Rundveehouders",
    "sg:phone":"+32 61 61 14 20",
    "sg:postcode":"6870",
    "sg:province":"Luxembourg",
    "wof:name":"Julien Evrard",
    "wof:placetype":"venue"
},
  "geometry": {"coordinates":[5.418489933,50.0313262939],"type":"Point"}
}