{
  "type": "Feature",
  "properties": {
    "addr:full":"Lucien Reychlerstraat 32 Waasmunster Oost-Vlaanderen 9250",
    "addr:housenumber":"32",
    "addr:postcode":"9250",
    "addr:street":"Lucien Reychlerstraat",
    "iso:country":"BE",
    "sg:address":"Lucien Reychlerstraat 32",
    "sg:city":"Waasmunster",
    "sg:orig_category":"Zalen voor culturele evenementen",
    "sg:phone":"+32 52 46 37 14",
    "sg:postcode":"9250",
    "sg:province":"Oost-Vlaanderen",
    "wof:name":"Lex",
    "wof:placetype":"venue"
},
  "geometry": {"coordinates":[4.1002840996,51.1162452698],"type":"Point"}
}