{
  "type": "Feature",
  "properties": {
    "iso:country":"BE",
    "sg:address":"Emile Braunplein 13",
    "sg:city":"Gent",
    "sg:classifiers":[
        {
            "category":"Fast Food",
            "type":"Food & Drink"
        }
    ],
    "sg:phone":"+32 9 233 89 58",
    "sg:postcode":"9000",
    "sg:province":"Oost-Vlaanderen",
    "sg:tags":[
        "meeneem",
        "restaurant"
    ],
    "wof:name":"Ponte Vecchio",
    "wof:placetype":"venue"
},
  "geometry": {"coordinates":[3.7233700752,51.0535697937],"type":"Point"}
}