{
  "type": "Feature",
  "properties": {
    "addr:full":"Simarstrasse 34 Eupen Li\u00e8ge 4700",
    "addr:housenumber":"34",
    "addr:postcode":"4700",
    "addr:street":"Simarstrasse",
    "iso:country":"BE",
    "sg:address":"Simarstrasse 34",
    "sg:city":"Eupen",
    "sg:classifiers":[
        {
            "category":"Landmark",
            "subcategory":"Memorial",
            "type":"Public Place"
        }
    ],
    "sg:phone":"+32 87 74 26 84",
    "sg:postcode":"4700",
    "sg:province":"Li\u00e8ge",
    "sg:tags":[
        "-",
        "monument"
    ],
    "wof:name":"Bosch A",
    "wof:placetype":"venue"
},
  "geometry": {"coordinates":[6.0288481712,50.6348075867],"type":"Point"}
}