{
  "type": "Feature",
  "properties": {
    "iso:country":"BE",
    "sg:address":"Heilig Grafstraat 34",
    "sg:city":"Eeklo",
    "sg:orig_category":"Diverse persoonlijke diensten",
    "sg:phone":"+32 9 378 12 74",
    "sg:postcode":"9900",
    "sg:province":"Oost-Vlaanderen",
    "wof:name":"Koen De Beule",
    "wof:placetype":"venue"
},
  "geometry": {"coordinates":[3.5552120209,51.1915893555],"type":"Point"}
}