{
  "type": "Feature",
  "properties": {
    "iso:country":"BE",
    "sg:address":"Denderdreve 74",
    "sg:city":"Zelzate",
    "sg:orig_category":"Elektrische installaties voor woningen",
    "sg:phone":"+32 9 344 65 48",
    "sg:postcode":"9060",
    "sg:province":"Oost-Vlaanderen",
    "wof:name":"Gino Poppe",
    "wof:placetype":"venue"
},
  "geometry": {"coordinates":[3.7932391167,51.2068023682],"type":"Point"}
}