{
  "type": "Feature",
  "properties": {
    "addr:full":"Deken De Bostraat 34 Waregem West-Vlaanderen 8791",
    "addr:housenumber":"34",
    "addr:postcode":"8791",
    "addr:street":"Deken De Bostraat",
    "iso:country":"BE",
    "sg:address":"Deken De Bostraat 34",
    "sg:city":"Waregem",
    "sg:orig_category":"Metaalafval, schrootrecyclage and sloperijen",
    "sg:phone":"+32 56 70 46 26",
    "sg:postcode":"8791",
    "sg:province":"West-Vlaanderen",
    "wof:name":"Fa. Debaere",
    "wof:placetype":"venue"
},
  "geometry": {"coordinates":[3.3489840031,50.8792037964],"type":"Point"}
}