{
  "type": "Feature",
  "properties": {
    "addr:full":"Stijn Streuvelslaan 24 De Haan (vlissegem) West-Vlaanderen 8421",
    "addr:housenumber":"24;8421",
    "addr:street":"Stijn Streuvelslaan",
    "iso:country":"BE",
    "sg:address":"Stijn Streuvelslaan 24",
    "sg:city":"De Haan (vlissegem)",
    "sg:classifiers":[
        {
            "category":"Professional",
            "subcategory":"Testing Lab",
            "type":"Services"
        }
    ],
    "sg:phone":"+32 59 23 33 75",
    "sg:postcode":"8421",
    "sg:province":"West-Vlaanderen",
    "sg:tags":[
        "laboratory",
        "photographic",
        "film"
    ],
    "wof:name":"Jumbocolor Bvba",
    "wof:placetype":"venue"
},
  "geometry": {"coordinates":[3.047096014,51.2709121704],"type":"Point"}
}