{
  "type": "Feature",
  "properties": {
    "addr:full":"Sint-rumoldusstraat 41 Gingelom (montenaken) Limburg 3890",
    "addr:housenumber":"41",
    "addr:postcode":"3890",
    "addr:street":"Sint-Rumoldusstraat",
    "iso:country":"BE",
    "sg:address":"Sint-rumoldusstraat 41",
    "sg:city":"Gingelom (montenaken)",
    "sg:classifiers":[
        {
            "category":"Utilities",
            "subcategory":"Fuel Oil & Lpg",
            "type":"Services"
        }
    ],
    "sg:phone":"+32 11 88 10 85",
    "sg:postcode":"3890",
    "sg:province":"Limburg",
    "wof:name":"Coenegrachts R",
    "wof:placetype":"venue"
},
  "geometry": {"coordinates":[5.1390318871,50.7200927734],"type":"Point"}
}