{
  "type": "Feature",
  "properties": {
    "iso:country":"BE",
    "sg:address":"Brouwersstraat 18 Bus 1",
    "sg:city":"Neerpelt",
    "sg:orig_category":"Installation \u00e9lectrique r\u00e9sidentielle",
    "sg:phone":"+32 11 66 19 79",
    "sg:postcode":"3910",
    "sg:province":"Limburg",
    "wof:name":"Electro Gero",
    "wof:placetype":"venue"
},
  "geometry": {"coordinates":[5.427781105,51.2285919189],"type":"Point"}
}