{
  "type": "Feature",
  "properties": {
    "addr:full":"Rue De La Goulette 123 Ch\u00e2telet (bouffioulx) Hainaut 6200",
    "addr:housenumber":"123",
    "addr:postcode":"6200",
    "addr:street":"Rue De La;Bouffioulx Hainaut",
    "iso:country":"BE",
    "sg:address":"Rue De La Goulette 123",
    "sg:city":"Ch\u00e2telet (bouffioulx)",
    "sg:classifiers":[
        {
            "category":"Building & Trades",
            "subcategory":"Construction",
            "type":"Services"
        }
    ],
    "sg:phone":"+32 71 39 60 12",
    "sg:postcode":"6200",
    "sg:province":"Hainaut",
    "sg:tags":[
        "roofing",
        "material",
        "-"
    ],
    "wof:name":"Sani-cover Sprl",
    "wof:placetype":"venue"
},
  "geometry": {"coordinates":[4.5274329185,50.3881568909],"type":"Point"}
}