{
  "type": "Feature",
  "properties": {
    "addr:full":"Herentalsebaan 22 Ranst Antwerpen 2520",
    "addr:housenumber":"22",
    "addr:postcode":"2520",
    "addr:street":"Herentalsebaan",
    "iso:country":"BE",
    "sg:address":"Herentalsebaan 22",
    "sg:city":"Ranst",
    "sg:classifiers":[
        {
            "category":"Professional",
            "subcategory":"Management & Consulting",
            "type":"Services"
        }
    ],
    "sg:phone":"+32 3 475 13 03",
    "sg:postcode":"2520",
    "sg:province":"Antwerpen",
    "sg:tags":[
        "consultant"
    ],
    "wof:name":"Beli (etn) Bvba",
    "wof:placetype":"venue"
},
  "geometry": {"coordinates":[4.5523138046,51.1816139221],"type":"Point"}
}