{
  "type": "Feature",
  "properties": {
    "addr:full":"Elizabetlaan 305 Knokke-heist West-Vlaanderen 8301",
    "addr:housenumber":"305",
    "addr:postcode":"8301",
    "addr:street":"Elizabetlaan",
    "iso:country":"BE",
    "sg:address":"Elizabetlaan 305",
    "sg:city":"Knokke-heist",
    "sg:orig_category":"H\u00f4tels",
    "sg:phone":"+32 50 51 39 32",
    "sg:postcode":"8301",
    "sg:province":"West-Vlaanderen",
    "wof:name":"Pauls Hotel",
    "wof:placetype":"venue"
},
  "geometry": {"coordinates":[3.2593541145,51.3408737183],"type":"Point"}
}