{
  "type": "Feature",
  "properties": {
    "addr:full":"Krugerstraat 249 Antwerpen (hoboken) Antwerpen 2660",
    "addr:housenumber":"249",
    "addr:postcode":"2660",
    "addr:street":"Krugerstraat",
    "iso:country":"BE",
    "sg:address":"Krugerstraat 249",
    "sg:city":"Antwerpen (hoboken)",
    "sg:classifiers":[
        {
            "category":"Utilities",
            "subcategory":"Mobile Phone",
            "type":"Services"
        }
    ],
    "sg:phone":"+32 3 230 21 73",
    "sg:postcode":"2660",
    "sg:province":"Antwerpen",
    "sg:tags":[
        "moulding"
    ],
    "wof:name":"Jef Coremans Bvba",
    "wof:placetype":"venue"
},
  "geometry": {"coordinates":[4.3624801636,51.1890487671],"type":"Point"}
}