{
  "type": "Feature",
  "properties": {
    "iso:country":"BE",
    "sg:address":"Naamsevest 12",
    "sg:city":"Leuven",
    "sg:classifiers":[
        {
            "category":"Professional",
            "subcategory":"Testing Lab",
            "type":"Services"
        }
    ],
    "sg:phone":"+32 16 22 16 51",
    "sg:postcode":"3000",
    "sg:province":"Vlaams-Brabant",
    "sg:tags":[
        "chemist"
    ],
    "wof:name":"Leblus",
    "wof:placetype":"venue"
},
  "geometry": {"coordinates":[4.6993498802,50.8686637878],"type":"Point"}
}