{
  "type": "Feature",
  "properties": {
    "iso:country":"BE",
    "sg:address":"Vuilputstraat 3",
    "sg:city":"Ingelmunster",
    "sg:orig_category":"Metaalbehandeling and -bekleding",
    "sg:phone":"+32 56 66 30 99",
    "sg:postcode":"8770",
    "sg:province":"West-Vlaanderen",
    "wof:name":"Verdometal",
    "wof:placetype":"venue"
},
  "geometry": {"coordinates":[3.2860879898,50.9202232361],"type":"Point"}
}