{
  "type": "Feature",
  "properties": {
    "addr:full":"Breidelstraat 2 Brugge West-Vlaanderen 8000",
    "addr:housenumber":"2",
    "addr:postcode":"8000",
    "addr:street":"Breidelstraat",
    "iso:country":"BE",
    "sg:address":"Breidelstraat 2",
    "sg:city":"Brugge",
    "sg:orig_category":"Bagage and lederwaren",
    "sg:phone":"+32 50 49 01 31",
    "sg:postcode":"8000",
    "sg:province":"West-Vlaanderen",
    "wof:name":"Huis Delvaux",
    "wof:placetype":"venue"
},
  "geometry": {"coordinates":[3.2251300812,51.2084159851],"type":"Point"}
}