{
  "type": "Feature",
  "properties": {
    "iso:country":"BE",
    "sg:address":"Route De Neufch\u00e2teau 551",
    "sg:city":"Arlon (heinsch)",
    "sg:classifiers":[
        {
            "category":"Autos & Motor Vehicles",
            "subcategory":"Auto Supplies",
            "type":"Retail Goods"
        }
    ],
    "sg:phone":"+32 63 22 11 13",
    "sg:postcode":"6700",
    "sg:province":"Luxembourg",
    "sg:tags":[
        "access",
        "automobile",
        "part",
        "-"
    ],
    "wof:name":"Pougin G Ets",
    "wof:placetype":"venue"
},
  "geometry": {"coordinates":[5.8042387962,49.689666748],"type":"Point"}
}