{
  "type": "Feature",
  "properties": {
    "addr:full":"Eikenlaan 43 Liedekerke Vlaams-Brabant 1770",
    "addr:housenumber":"43",
    "addr:postcode":"1770",
    "addr:street":"Eikenlaan;Vlaams-Brabant",
    "iso:country":"BE",
    "sg:address":"Eikenlaan 43",
    "sg:city":"Liedekerke",
    "sg:classifiers":[
        {
            "category":"Personal",
            "subcategory":"Beauty Salon",
            "type":"Services"
        }
    ],
    "sg:phone":"+32 53 66 69 22",
    "sg:postcode":"1770",
    "sg:province":"Vlaams-Brabant",
    "sg:tags":[
        "lady",
        "-",
        "hairdressing"
    ],
    "wof:name":"Maggy",
    "wof:placetype":"venue"
},
  "geometry": {"coordinates":[4.0995230675,50.8631896973],"type":"Point"}
}