{
  "type": "Feature",
  "properties": {
    "iso:country":"BE",
    "sg:address":"Stationstraat 57",
    "sg:city":"Overijse",
    "sg:orig_category":"Huisdieren and benodigdheden Royal Canin",
    "sg:phone":"+32 2 687 73 57",
    "sg:postcode":"3090",
    "sg:province":"Vlaams-Brabant",
    "wof:name":"Bvba Taymans",
    "wof:placetype":"venue"
},
  "geometry": {"coordinates":[4.5345678329,50.770816803],"type":"Point"}
}