{
  "type": "Feature",
  "properties": {
    "iso:country":"BE",
    "sg:address":"Toekomststraat 21",
    "sg:city":"Denderleeuw",
    "sg:orig_category":"HERSTELLING ELEKTRISCHE HUISHOUDAPPARATEN Huishoudapparaten, televisies and radio's",
    "sg:phone":"+32 53 66 97 23",
    "sg:postcode":"9470",
    "sg:province":"Oost-Vlaanderen",
    "wof:name":"Hans Jacques",
    "wof:placetype":"venue"
},
  "geometry": {"coordinates":[4.0744199753,50.8795967102],"type":"Point"}
}