{
  "type": "Feature",
  "properties": {
    "addr:full":"Steenweg Naar As 2 Maasmechelen Limburg 3630",
    "addr:housenumber":"2",
    "addr:postcode":"3630",
    "addr:street":"Steenweg Naar As",
    "iso:country":"BE",
    "sg:address":"Steenweg Naar As 2",
    "sg:city":"Maasmechelen",
    "sg:orig_category":"Huisvuilophaling and -verwerking",
    "sg:phone":"+32 89 65 11 11",
    "sg:postcode":"3630",
    "sg:province":"Limburg",
    "wof:name":"Stevens",
    "wof:placetype":"venue"
},
  "geometry": {"coordinates":[5.6287298203,50.9888381958],"type":"Point"}
}