{
  "type": "Feature",
  "properties": {
    "addr:full":"Oude Baan 163 Maasmechelen Limburg 3630",
    "addr:housenumber":"163",
    "addr:postcode":"3630",
    "addr:street":"Oude Baan",
    "iso:country":"BE",
    "sg:address":"Oude Baan 163",
    "sg:city":"Maasmechelen",
    "sg:classifiers":[
        {
            "category":"Restaurant",
            "type":"Food & Drink"
        }
    ],
    "sg:phone":"+32 89 77 65 34",
    "sg:postcode":"3630",
    "sg:province":"Limburg",
    "wof:name":"V. Akbudak",
    "wof:placetype":"venue"
},
  "geometry": {"coordinates":[5.6928348541,50.9833297729],"type":"Point"}
}