{
  "type": "Feature",
  "properties": {
    "addr:full":"Kerkeneind 1 Essen Antwerpen 2910",
    "addr:housenumber":"1",
    "addr:postcode":"2910",
    "addr:street":"Kerkeneind",
    "iso:country":"BE",
    "sg:address":"Kerkeneind 1",
    "sg:city":"Essen",
    "sg:classifiers":[
        {
            "category":"Social Services",
            "type":"Services"
        }
    ],
    "sg:phone":"+32 3 667 29 65",
    "sg:postcode":"2910",
    "sg:province":"Antwerpen",
    "wof:name":"Kind En Gezin",
    "wof:placetype":"venue"
},
  "geometry": {"coordinates":[4.4686121941,51.4676551819],"type":"Point"}
}