{
  "type": "Feature",
  "properties": {
    "addr:full":"Rue De La Broucheterre 4 Charleroi Hainaut 6000",
    "addr:housenumber":"4",
    "addr:postcode":"6000",
    "addr:street":"Rue De La Broucheterre;Hainaut",
    "iso:country":"BE",
    "sg:address":"Rue De La Broucheterre 4",
    "sg:city":"Charleroi",
    "sg:orig_category":"Epiceries",
    "sg:phone":"+32 71 30 32 69",
    "sg:postcode":"6000",
    "sg:province":"Hainaut",
    "wof:name":"Asmat",
    "wof:placetype":"venue"
},
  "geometry": {"coordinates":[4.4455947876,50.4182319641],"type":"Point"}
}