{
  "type": "Feature",
  "properties": {
    "addr:full":"Rue De Crespin 51-53 Hensies Hainaut 7350",
    "addr:housenumber":"51-53",
    "addr:postcode":"7350",
    "addr:street":"Rue De Crespin",
    "iso:country":"BE",
    "sg:address":"Rue De Crespin 51-53",
    "sg:city":"Hensies",
    "sg:classifiers":[
        {
            "category":"Health Services",
            "subcategory":"Health Practitioner",
            "type":"Services"
        }
    ],
    "sg:phone":"+32 65 46 06 64",
    "sg:postcode":"7350",
    "sg:province":"Hainaut",
    "sg:tags":[
        "physiotherapist"
    ],
    "wof:name":"Lefebvre Yves",
    "wof:placetype":"venue"
},
  "geometry": {"coordinates":[3.6809439659,50.4294548035],"type":"Point"}
}