{
  "type": "Feature",
  "properties": {
    "addr:full":"Rue De L'echauffour\u00e9e Mouscron Hainaut 7700",
    "addr:postcode":"7700",
    "addr:street":"Rue De L'Echauffoure \u0301E;Hainaut",
    "iso:country":"BE",
    "sg:address":"Rue De L'echauffour\u00e9e",
    "sg:city":"Mouscron",
    "sg:classifiers":[
        {
            "category":"Professional",
            "subcategory":"Business Services",
            "type":"Services"
        }
    ],
    "sg:phone":"+32 56 34 95 89",
    "sg:postcode":"7700",
    "sg:province":"Hainaut",
    "sg:tags":[
        "consultant",
        "custom"
    ],
    "wof:name":"Roussel Fres Sprl",
    "wof:placetype":"venue"
},
  "geometry": {"coordinates":[3.1822490692,50.7528762817],"type":"Point"}
}