{
  "type": "Feature",
  "properties": {
    "iso:country":"BE",
    "sg:address":"Waterhoekweg 10",
    "sg:city":"Torhout",
    "sg:orig_category":"GROENTEN AND FRUIT Groenten and fruit Gh",
    "sg:phone":"+32 50 21 14 23",
    "sg:postcode":"8820",
    "sg:province":"West-Vlaanderen",
    "wof:name":"Vanbiervliet",
    "wof:placetype":"venue"
},
  "geometry": {"coordinates":[3.0877010822,51.0709953308],"type":"Point"}
}