{
  "type": "Feature",
  "properties": {
    "iso:country":"BE",
    "sg:address":"Putsesteenweg 6",
    "sg:city":"Bonheiden",
    "sg:classifiers":[
        {
            "category":"Professional",
            "subcategory":"Management & Consulting",
            "type":"Services"
        }
    ],
    "sg:phone":"+32 478 69 77 20",
    "sg:postcode":"2820",
    "sg:province":"Antwerpen",
    "sg:tags":[
        "consultant",
        "agency",
        "advertising"
    ],
    "wof:name":"Imagine",
    "wof:placetype":"venue"
},
  "geometry": {"coordinates":[4.5161271095,51.0347213745],"type":"Point"}
}