{
  "type": "Feature",
  "properties": {
    "iso:country":"BE",
    "sg:address":"Rue Des Papeteries 11",
    "sg:city":"Chaumont-gistoux",
    "sg:orig_category":"Marketingbureaus",
    "sg:phone":"+32 10 68 85 96",
    "sg:postcode":"1325",
    "sg:province":"Brabant Wallon",
    "wof:name":"A\u00c9rograf Sprl",
    "wof:placetype":"venue"
},
  "geometry": {"coordinates":[4.6967878342,50.6791877747],"type":"Point"}
}