{
  "type": "Feature",
  "properties": {
    "iso:country":"BE",
    "sg:address":"Waverse Steenweg 1085",
    "sg:city":"Oudergem/auderghem",
    "sg:orig_category":"Installatie van metalen schrijnwerk",
    "sg:phone":"+32 2 640 60 55",
    "sg:postcode":"1160",
    "sg:province":"Bruxelles-Capitale",
    "wof:name":"Fe. Minerva",
    "wof:placetype":"venue"
},
  "geometry": {"coordinates":[4.3998708725,50.8243408203],"type":"Point"}
}