{
  "type": "Feature",
  "properties": {
    "addr:full":"Krijgslaan 2 Gent Oost-Vlaanderen 9000",
    "addr:housenumber":"2",
    "addr:postcode":"9000",
    "addr:street":"Krijgslaan;Oost-Vlaanderen",
    "iso:country":"BE",
    "sg:address":"Krijgslaan 2",
    "sg:city":"Gent",
    "sg:orig_category":"Sondages and enqu\u00eates. Banques de donn\u00e9es. Bureaux d'\u00e9tudes de march\u00e9. Agences de marketing. Agences",
    "sg:phone":"+32 9 221 22 33",
    "sg:postcode":"9000",
    "sg:province":"Oost-Vlaanderen",
    "wof:name":"Bureau Aida Link",
    "wof:placetype":"venue"
},
  "geometry": {"coordinates":[3.7199308872,51.0348358154],"type":"Point"}
}