{
  "type": "Feature",
  "properties": {
    "iso:country":"BE",
    "sg:address":"Route De Philippeville 429",
    "sg:city":"Charleroi (couillet)",
    "sg:classifiers":[
        {
            "category":"Health Services",
            "subcategory":"Dentist",
            "type":"Services"
        }
    ],
    "sg:phone":"+32 71 36 60 54",
    "sg:postcode":"6010",
    "sg:province":"Hainaut",
    "wof:name":"Gesnot Vincent",
    "wof:placetype":"venue"
},
  "geometry": {"coordinates":[4.4660711288,50.3793106079],"type":"Point"}
}