{
  "type": "Feature",
  "properties": {
    "addr:full":"Rue Ferdinand Lenoir 21 Bruxelles (jette) Bruxelles-Capitale 1090",
    "addr:housenumber":"21",
    "addr:postcode":"1090",
    "addr:street":"Rue Ferdinand Lenoir",
    "iso:country":"BE",
    "sg:address":"Rue Ferdinand Lenoir 21",
    "sg:city":"Bruxelles (jette)",
    "sg:classifiers":[
        {
            "category":"Bakery",
            "type":"Food & Drink"
        }
    ],
    "sg:phone":"+32 2 411 86 72",
    "sg:postcode":"1090",
    "sg:province":"Bruxelles-Capitale",
    "sg:tags":[
        "confectioner",
        "baker"
    ],
    "wof:name":"Gavilan (boulangerie)",
    "wof:placetype":"venue"
},
  "geometry": {"coordinates":[4.3292341232,50.8764648438],"type":"Point"}
}