{
  "type": "Feature",
  "properties": {
    "iso:country":"BE",
    "sg:address":"Route De Poix 35",
    "sg:city":"Saint-hubert",
    "sg:classifiers":[
        {
            "category":"Travel",
            "subcategory":"Resort",
            "type":"Entertainment"
        }
    ],
    "sg:phone":"+32 61 61 16 14",
    "sg:postcode":"6870",
    "sg:province":"Luxembourg",
    "sg:tags":[
        "rental",
        "accomodation",
        "holiday",
        "-"
    ],
    "wof:name":"Vaillant N",
    "wof:placetype":"venue"
},
  "geometry": {"coordinates":[5.3544259071,50.0245628357],"type":"Point"}
}