{
  "type": "Feature",
  "properties": {
    "iso:country":"BE",
    "sg:address":"Rue L\u00b4apleit 15",
    "sg:city":"Huy",
    "sg:orig_category":"Kinderopvang",
    "sg:phone":"+32 85 25 41 76",
    "sg:postcode":"4500",
    "sg:province":"Li\u00e8ge",
    "wof:name":"Maison De L\u00b4enfant",
    "wof:placetype":"venue"
},
  "geometry": {"coordinates":[5.240986824,50.5195846558],"type":"Point"}
}