{
  "type": "Feature",
  "properties": {
    "iso:country":"BE",
    "sg:address":"Boekweitstraat 11",
    "sg:city":"Herentals (noorderwijk)",
    "sg:classifiers":[
        {
            "category":"Retail",
            "subcategory":"Veterinary Services",
            "type":"Services"
        }
    ],
    "sg:phone":"+32 14 26 75 22",
    "sg:postcode":"2200",
    "sg:province":"Antwerpen",
    "sg:tags":[
        "veterinarian"
    ],
    "wof:name":"Van Huele K",
    "wof:placetype":"venue"
},
  "geometry": {"coordinates":[4.8360137939,51.1453437805],"type":"Point"}
}