{
  "type": "Feature",
  "properties": {
    "addr:full":"Lamorinierestraat 174 Antwerpen Antwerpen 2018",
    "addr:housenumber":"174",
    "addr:postcode":"2018",
    "addr:street":"Lamorinierestraat",
    "iso:country":"BE",
    "sg:address":"Lamorinierestraat 174",
    "sg:city":"Antwerpen",
    "sg:classifiers":[
        {
            "category":"Professional",
            "subcategory":"Lawyer & Legal Services",
            "type":"Services"
        }
    ],
    "sg:phone":"+32 3 218 58 64",
    "sg:postcode":"2018",
    "sg:province":"Antwerpen",
    "wof:name":"Keirsebelik A",
    "wof:placetype":"venue"
},
  "geometry": {"coordinates":[4.4199638367,51.2030334473],"type":"Point"}
}