{
  "type": "Feature",
  "properties": {
    "iso:country":"BE",
    "sg:address":"Pastoriestraat 29",
    "sg:city":"Kontich (waarloos)",
    "sg:classifiers":[
        {
            "category":"Professional",
            "subcategory":"Art Services",
            "type":"Services"
        }
    ],
    "sg:phone":"+32 15 31 73 12",
    "sg:postcode":"2550",
    "sg:province":"Antwerpen",
    "sg:tags":[
        "sculptor"
    ],
    "wof:name":"Van Ransbeeck B",
    "wof:placetype":"venue"
},
  "geometry": {"coordinates":[4.4564099312,51.1076393127],"type":"Point"}
}