{
  "type": "Feature",
  "properties": {
    "addr:full":"Rue Des Echelles 5 Mons Hainaut 7000",
    "addr:housenumber":"5",
    "addr:postcode":"7000",
    "addr:street":"Rue Des Echelles;Hainaut",
    "iso:country":"BE",
    "sg:address":"Rue Des Echelles 5",
    "sg:city":"Mons",
    "sg:orig_category":"Diverse grafische activiteiten",
    "sg:phone":"+32 65 34 65 28",
    "sg:postcode":"7000",
    "sg:province":"Hainaut",
    "wof:name":"Cycl\u00c9ode Publicit\u00c9",
    "wof:placetype":"venue"
},
  "geometry": {"coordinates":[3.9521989822,50.4573020935],"type":"Point"}
}