{
  "type": "Feature",
  "properties": {
    "iso:country":"BE",
    "sg:address":"Rue D'oignies 196",
    "sg:city":"Aiseau-presles",
    "sg:orig_category":"M\u00e9decins and sp\u00e9cialistes",
    "sg:phone":"+32 71 77 55 88",
    "sg:postcode":"6250",
    "sg:province":"Hainaut",
    "wof:name":"Jacques Sory",
    "wof:placetype":"venue"
},
  "geometry": {"coordinates":[4.6118321419,50.4285926819],"type":"Point"}
}