{
  "type": "Feature",
  "properties": {
    "addr:full":"Avenue De La Bride 10 Wavre Brabant Wallon 1300",
    "addr:housenumber":"10;1300",
    "addr:street":"Avenue De La Bride",
    "iso:country":"BE",
    "sg:address":"Avenue De La Bride 10",
    "sg:city":"Wavre",
    "sg:orig_category":"Meubles D\u00e9taillants, Am\u00e9nagement de B\u00e2timents et de Cuisines",
    "sg:phone":"+32 10 22 68 99",
    "sg:postcode":"1300",
    "sg:province":"Brabant Wallon",
    "wof:name":"Fe. Lescrenier Strati",
    "wof:placetype":"venue"
},
  "geometry": {"coordinates":[4.6272411346,50.7078590393],"type":"Point"}
}