{
  "type": "Feature",
  "properties": {
    "iso:country":"BE",
    "sg:address":"Keurvorst Karel Theodoorstraat 16",
    "sg:city":"Brugge (sint-andries)",
    "sg:classifiers":[
        {
            "category":"Health Services",
            "subcategory":"Doctor",
            "type":"Services"
        }
    ],
    "sg:phone":"+32 50 39 37 65",
    "sg:postcode":"8200",
    "sg:province":"West-Vlaanderen",
    "sg:tags":[
        "psychotherapist",
        "psychoanalyst"
    ],
    "wof:name":"Oceanos Vzw",
    "wof:placetype":"venue"
},
  "geometry": {"coordinates":[3.1904699802,51.1992111206],"type":"Point"}
}