{
  "type": "Feature",
  "properties": {
    "addr:full":"Rue Jacquet 23 Rochefort Namur 5580",
    "addr:housenumber":"23",
    "addr:postcode":"5580",
    "addr:street":"Rue Jacquet",
    "iso:country":"BE",
    "sg:address":"Rue Jacquet 23",
    "sg:city":"Rochefort",
    "sg:classifiers":[
        {
            "category":"Personal",
            "subcategory":"Beauty Salon",
            "type":"Services"
        }
    ],
    "sg:phone":"+32 84 21 11 86",
    "sg:postcode":"5580",
    "sg:province":"Namur",
    "sg:tags":[
        "lady",
        "-",
        "hairdressing"
    ],
    "wof:name":"Roger Coiffure",
    "wof:placetype":"venue"
},
  "geometry": {"coordinates":[5.2226028442,50.1566886902],"type":"Point"}
}