{
  "type": "Feature",
  "properties": {
    "addr:full":"Avenue Nestor Plissart 95 Bruxelles (woluwe-saint-pierre) Bruxelles-Capitale 1150",
    "addr:housenumber":"95",
    "addr:postcode":"1150",
    "addr:street":"Avenue Nestor Plissart",
    "iso:country":"BE",
    "sg:address":"Avenue Nestor Plissart 95",
    "sg:city":"Bruxelles (woluwe-saint-pierre)",
    "sg:classifiers":[
        {
            "category":"Home & Garden",
            "subcategory":"Home Furnishings",
            "type":"Retail Goods"
        }
    ],
    "sg:phone":"+32 2 763 29 76",
    "sg:postcode":"1150",
    "sg:province":"Bruxelles-Capitale",
    "sg:tags":[
        "interior",
        "decoration"
    ],
    "wof:name":"Sabli And Co Sprl",
    "wof:placetype":"venue"
},
  "geometry": {"coordinates":[4.4109601974,50.8324165344],"type":"Point"}
}