{
  "type": "Feature",
  "properties": {
    "iso:country":"BE",
    "sg:address":"Schraaienstraat 76",
    "sg:city":"Nazareth",
    "sg:orig_category":"Projectontwikkelaars Woningbouw",
    "sg:phone":"+32 9 385 54 42",
    "sg:postcode":"9810",
    "sg:province":"Oost-Vlaanderen",
    "wof:name":"Speybroeck Antoine Aannemersbedrijf",
    "wof:placetype":"venue"
},
  "geometry": {"coordinates":[3.6165568829,50.9488563538],"type":"Point"}
}