{
  "type": "Feature",
  "properties": {
    "addr:full":"Rue De M\u00e8ves 11 Chaumont-gistoux (corroy-le-grand) Brabant Wallon 1325",
    "addr:housenumber":"11",
    "addr:postcode":"1325",
    "addr:street":"Rue De Me\u0300Ves",
    "iso:country":"BE",
    "sg:address":"Rue De M\u00e8ves 11",
    "sg:city":"Chaumont-gistoux (corroy-le-grand)",
    "sg:classifiers":[
        {
            "category":"Health Services",
            "subcategory":"Health Practitioner",
            "type":"Services"
        }
    ],
    "sg:phone":"+32 10 68 01 36",
    "sg:postcode":"1325",
    "sg:province":"Brabant Wallon",
    "sg:tags":[
        "psychologist"
    ],
    "wof:name":"Uyttenhove B",
    "wof:placetype":"venue"
},
  "geometry": {"coordinates":[4.6427369118,50.6783027649],"type":"Point"}
}