{
  "type": "Feature",
  "properties": {
    "addr:full":"Volpestraat 15 Halle Vlaams-Brabant 1500",
    "addr:housenumber":"15",
    "addr:postcode":"1500",
    "addr:street":"Volpestraat",
    "iso:country":"BE",
    "sg:address":"Volpestraat 15",
    "sg:city":"Halle",
    "sg:classifiers":[
        {
            "category":"Shopping",
            "subcategory":"Shoes",
            "type":"Retail Goods"
        }
    ],
    "sg:phone":"+32 2 356 04 35",
    "sg:postcode":"1500",
    "sg:province":"Vlaams-Brabant",
    "sg:tags":[
        "slipper",
        "-"
    ],
    "wof:name":"New Joseph",
    "wof:placetype":"venue"
},
  "geometry": {"coordinates":[4.2356767654,50.7357597351],"type":"Point"}
}