{
  "type": "Feature",
  "properties": {
    "addr:full":"Kortrijkse Heerweg 129 Deerlijk West-Vlaanderen 8540",
    "addr:housenumber":"129",
    "addr:postcode":"8540",
    "addr:street":"Heerweg",
    "iso:country":"BE",
    "sg:address":"Kortrijkse Heerweg 129",
    "sg:city":"Deerlijk",
    "sg:orig_category":"Secretariaatsdiensten Taxi's Taxi's speciale diensten",
    "sg:phone":"+32 56 71 62 84",
    "sg:postcode":"8540",
    "sg:province":"West-Vlaanderen",
    "wof:name":"Comborfisc",
    "wof:placetype":"venue"
},
  "geometry": {"coordinates":[3.3384749889,50.8513908386],"type":"Point"}
}