{
  "type": "Feature",
  "properties": {
    "iso:country":"BE",
    "sg:address":"Dorp 33",
    "sg:city":"Nazareth",
    "sg:classifiers":[
        {
            "category":"Home & Garden",
            "subcategory":"Household Appliances",
            "type":"Retail Goods"
        }
    ],
    "sg:phone":"+32 9 385 57 82",
    "sg:postcode":"9810",
    "sg:province":"Oost-Vlaanderen",
    "sg:tags":[
        "repair",
        "mainten",
        "-",
        "electric"
    ],
    "wof:name":"Demurie",
    "wof:placetype":"venue"
},
  "geometry": {"coordinates":[3.5957710743,50.9590148926],"type":"Point"}
}