{
  "type": "Feature",
  "properties": {
    "iso:country":"BE",
    "sg:address":"Beustereind 114",
    "sg:city":"Laakdal (forest)",
    "sg:classifiers":[
        {
            "category":"Bars & Pubs",
            "type":"Food & Drink"
        }
    ],
    "sg:phone":"+32 13 66 13 28",
    "sg:postcode":"2430",
    "sg:province":"Antwerpen",
    "wof:name":"Mijnwerker (de)",
    "wof:placetype":"venue"
},
  "geometry": {"coordinates":[5.0447030067,51.0851287842],"type":"Point"}
}