{
  "type": "Feature",
  "properties": {
    "iso:country":"BE",
    "sg:address":"Dorpsplein 18",
    "sg:city":"Rotselaar",
    "sg:orig_category":"Schoenen",
    "sg:phone":"+32 16 44 59 05",
    "sg:postcode":"3110",
    "sg:province":"Vlaams-Brabant",
    "wof:name":"Schoenen Vercammen",
    "wof:placetype":"venue"
},
  "geometry": {"coordinates":[4.7084717751,50.9514427185],"type":"Point"}
}