{
  "type": "Feature",
  "properties": {
    "iso:country":"BE",
    "sg:address":"Stationsstraat 36",
    "sg:city":"Sint-katelijne-waver",
    "sg:classifiers":[
        {
            "category":"Personal",
            "subcategory":"Beauty Salon",
            "type":"Services"
        }
    ],
    "sg:phone":"+32 15 31 31 00",
    "sg:postcode":"2860",
    "sg:province":"Antwerpen",
    "sg:tags":[
        "de",
        "coiffure"
    ],
    "wof:name":"Coiffure Ellen",
    "wof:placetype":"venue"
},
  "geometry": {"coordinates":[4.529291153,51.0707969666],"type":"Point"}
}