{
  "type": "Feature",
  "properties": {
    "addr:full":"Aarschotsebaan 15 Boortmeerbeek Vlaams-Brabant 3190",
    "addr:housenumber":"15",
    "addr:postcode":"3190",
    "addr:street":"Aarschotsebaan",
    "iso:country":"BE",
    "sg:address":"Aarschotsebaan 15",
    "sg:city":"Boortmeerbeek",
    "sg:classifiers":[
        {
            "category":"Quarry",
            "type":"Physical Feature"
        }
    ],
    "sg:phone":"+32 15 61 00 75",
    "sg:postcode":"3190",
    "sg:province":"Vlaams-Brabant",
    "sg:tags":[
        "granite",
        "work",
        "marble"
    ],
    "wof:name":"Floridor M",
    "wof:placetype":"venue"
},
  "geometry": {"coordinates":[4.5580921173,50.9747428894],"type":"Point"}
}