{
  "type": "Feature",
  "properties": {
    "iso:country":"BE",
    "sg:address":"Avenue Charles Schaller 17",
    "sg:city":"Oudergem/auderghem",
    "sg:orig_category":"M\u00e9decins and sp\u00e9cialistes",
    "sg:phone":"+32 2 672 51 70",
    "sg:postcode":"1160",
    "sg:province":"Bruxelles-Capitale",
    "wof:name":"Vincent Dassy",
    "wof:placetype":"venue"
},
  "geometry": {"coordinates":[4.4370107651,50.8088569641],"type":"Point"}
}