{
  "type": "Feature",
  "properties": {
    "addr:full":"Ambachtenlaan 30 Tienen Vlaams-Brabant 3300",
    "addr:housenumber":"30",
    "addr:postcode":"3300",
    "addr:street":"Ambachtenlaan",
    "iso:country":"BE",
    "sg:address":"Ambachtenlaan 30",
    "sg:city":"Tienen",
    "sg:orig_category":"Bouwmaterialen Gh Loodgieterij and centrale verwarming Gh",
    "sg:phone":"+32 16 82 20 40",
    "sg:postcode":"3300",
    "sg:province":"Vlaams-Brabant",
    "wof:name":"Walraven",
    "wof:placetype":"venue"
},
  "geometry": {"coordinates":[4.9732289314,50.8019676208],"type":"Point"}
}