{
  "type": "Feature",
  "properties": {
    "addr:full":"Rue Sylvain Guyaux 8 La Louvi\u00c8re Hainaut 7100",
    "addr:housenumber":"8",
    "addr:postcode":"7100",
    "addr:street":"Rue Sylvain Guyaux",
    "iso:country":"BE",
    "sg:address":"Rue Sylvain Guyaux 8",
    "sg:city":"La Louvi\u00c8re",
    "sg:classifiers":[
        {
            "category":"Fast Food",
            "type":"Food & Drink"
        }
    ],
    "sg:phone":"+32 64 28 40 95",
    "sg:postcode":"7100",
    "sg:province":"Hainaut",
    "sg:tags":[
        "meeneem",
        "restaurant"
    ],
    "wof:name":"L\u00c9on 1893",
    "wof:placetype":"venue"
},
  "geometry": {"coordinates":[4.1866140366,50.4749755859],"type":"Point"}
}