{
  "type": "Feature",
  "properties": {
    "iso:country":"BE",
    "sg:address":"Kunstambachtslaan 7",
    "sg:city":"Mortsel",
    "sg:classifiers":[
        {
            "category":"Government",
            "subcategory":"Post Office",
            "type":"Public Place"
        }
    ],
    "sg:phone":"+32 3 449 62 81",
    "sg:postcode":"2640",
    "sg:province":"Antwerpen",
    "sg:tags":[
        "yoga"
    ],
    "wof:name":"Zenmeditatie Ho-sen-dojo",
    "wof:placetype":"venue"
},
  "geometry": {"coordinates":[4.4484248161,51.1763114929],"type":"Point"}
}