{
  "type": "Feature",
  "properties": {
    "addr:full":"Rue Gabrielle Petit 4 Box 9 Bruxelles (molenbeek-saint-jean) Bruxelles-Capitale 1080",
    "addr:housenumber":"4;9",
    "addr:postcode":"1080",
    "addr:street":"Rue Gabrielle Petit;Box",
    "iso:country":"BE",
    "sg:address":"Rue Gabrielle Petit 4 Box 9",
    "sg:city":"Bruxelles (molenbeek-saint-jean)",
    "sg:classifiers":[
        {
            "category":"Wholesale",
            "subcategory":"Medical Equipment & Supplies",
            "type":"Manufacturing & Wholesale Goods"
        }
    ],
    "sg:phone":"+32 2 420 52 00",
    "sg:postcode":"1080",
    "sg:province":"Bruxelles-Capitale",
    "sg:tags":[
        "-",
        "chemist"
    ],
    "wof:name":"Feton International Sa Sa",
    "wof:placetype":"venue"
},
  "geometry": {"coordinates":[4.3405170441,50.8681182861],"type":"Point"}
}