{
  "type": "Feature",
  "properties": {
    "iso:country":"BE",
    "sg:address":"Avenue Franklin Roosevelt 27",
    "sg:city":"Vis\u00e9",
    "sg:classifiers":[
        {
            "category":"Professional",
            "subcategory":"Testing Lab",
            "type":"Services"
        }
    ],
    "sg:phone":"+32 4 374 26 64",
    "sg:postcode":"4600",
    "sg:province":"Li\u00e8ge",
    "sg:tags":[
        "laboratory",
        "-"
    ],
    "wof:name":"Metrodim Sprl",
    "wof:placetype":"venue"
},
  "geometry": {"coordinates":[5.6857948303,50.7373695374],"type":"Point"}
}