{
  "type": "Feature",
  "properties": {
    "iso:country":"BE",
    "sg:address":"Rue Bassidaine 16",
    "sg:city":"Viroinval",
    "sg:classifiers":[
        {
            "category":"Cafe",
            "type":"Food & Drink"
        }
    ],
    "sg:phone":"+32 60 31 30 44",
    "sg:postcode":"5670",
    "sg:province":"Namur",
    "sg:tags":[
        "caf\u00e9s"
    ],
    "wof:name":"Caf\u00c9 La Vieille Forge",
    "wof:placetype":"venue"
},
  "geometry": {"coordinates":[4.5471668243,50.0749664307],"type":"Point"}
}