{
  "type": "Feature",
  "properties": {
    "addr:full":"Cipalstraat 3 Geel Antwerpen 2440",
    "addr:housenumber":"3",
    "addr:postcode":"2440",
    "addr:street":"Cipalstraat",
    "iso:country":"BE",
    "sg:address":"Cipalstraat 3",
    "sg:city":"Geel",
    "sg:classifiers":[
        {
            "category":"Real Estate",
            "subcategory":"Real Estate Services",
            "type":"Services"
        }
    ],
    "sg:phone":"+32 14 57 05 70",
    "sg:postcode":"2440",
    "sg:province":"Antwerpen",
    "wof:name":"Technologiehuis-innotek",
    "wof:placetype":"venue"
},
  "geometry": {"coordinates":[4.9965848923,51.1526641846],"type":"Point"}
}