{
  "type": "Feature",
  "properties": {
    "addr:full":"Rue Des Fa\u00cenes 92 Brussel/bruxelles Bruxelles-Capitale 1120",
    "addr:housenumber":"92",
    "addr:postcode":"1120",
    "addr:street":"Rue Des Fai\u0302Nes;/",
    "iso:country":"BE",
    "sg:address":"Rue Des Fa\u00cenes 92",
    "sg:city":"Brussel/bruxelles",
    "sg:orig_category":"Rev\u00eatements pour sols and murs",
    "sg:phone":"+32 2 268 56 24",
    "sg:postcode":"1120",
    "sg:province":"Bruxelles-Capitale",
    "wof:name":"Carrelages Yves",
    "wof:placetype":"venue"
},
  "geometry": {"coordinates":[4.3893380165,50.8931121826],"type":"Point"}
}