{
  "type": "Feature",
  "properties": {
    "iso:country":"BE",
    "sg:address":"Lange Akkerstraat 36",
    "sg:city":"Deinze (meigem)",
    "sg:classifiers":[
        {
            "category":"Retail",
            "subcategory":"Veterinary Services",
            "type":"Services"
        }
    ],
    "sg:phone":"+32 9 380 42 52",
    "sg:postcode":"9800",
    "sg:province":"Oost-Vlaanderen",
    "sg:tags":[
        "veterinarian"
    ],
    "wof:name":"Mattheeuws G",
    "wof:placetype":"venue"
},
  "geometry": {"coordinates":[3.5381360054,51.0118484497],"type":"Point"}
}