{
  "type": "Feature",
  "properties": {
    "addr:full":"Rijksweg 368 Maasmechelen Limburg 3630",
    "addr:housenumber":"368",
    "addr:postcode":"3630",
    "addr:street":"Rijksweg",
    "iso:country":"BE",
    "sg:address":"Rijksweg 368",
    "sg:city":"Maasmechelen",
    "sg:orig_category":"Rev\u00eatements pour sols and murs. Eclairage et \u00e9quipements du foyer. Quincailleries. Biens d'occasion.",
    "sg:phone":"+32 89 76 42 92",
    "sg:postcode":"3630",
    "sg:province":"Limburg",
    "wof:name":"Meubelen St.jan",
    "wof:placetype":"venue"
},
  "geometry": {"coordinates":[5.6965460777,50.9658584595],"type":"Point"}
}