{
  "type": "Feature",
  "properties": {
    "addr:full":"Nieuwe Kouterstraat 31 Bornem Antwerpen 2880",
    "addr:housenumber":"31",
    "addr:postcode":"2880",
    "addr:street":"Nieuwe Kouterstraat",
    "iso:country":"BE",
    "sg:address":"Nieuwe Kouterstraat 31",
    "sg:city":"Bornem",
    "sg:orig_category":"HERSTELLING ELEKTRISCHE HUISHOUDAPPARATEN Huishoudapparaten, televisies and radio's Telecommunicatie",
    "sg:phone":"+32 3 889 16 24",
    "sg:postcode":"2880",
    "sg:province":"Antwerpen",
    "wof:name":"Elektro Hifi Van Steen",
    "wof:placetype":"venue"
},
  "geometry": {"coordinates":[4.2384328842,51.0985031128],"type":"Point"}
}