{
  "type": "Feature",
  "properties": {
    "addr:full":"Ferdinand De Deckerstr. 11 Zwijndrecht Antwerpen 2070",
    "addr:housenumber":"11",
    "addr:postcode":"2070",
    "addr:street":"Ferdinand",
    "iso:country":"BE",
    "sg:address":"Ferdinand De Deckerstr. 11",
    "sg:city":"Zwijndrecht",
    "sg:orig_category":"Artsen and specialisten",
    "sg:phone":"+32 3 252 93 37",
    "sg:postcode":"2070",
    "sg:province":"Antwerpen",
    "wof:name":"Raphael Madou",
    "wof:placetype":"venue"
},
  "geometry": {"coordinates":[4.3221688271,51.2188644409],"type":"Point"}
}