{
  "type": "Feature",
  "properties": {
    "addr:full":"Rue De Merbes 170 Binche Hainaut 7130",
    "addr:housenumber":"170",
    "addr:postcode":"7130",
    "addr:street":"Rue De Merbes",
    "iso:country":"BE",
    "sg:address":"Rue De Merbes 170",
    "sg:city":"Binche",
    "sg:orig_category":"Rusthuizen and serviceflats",
    "sg:phone":"+32 64 33 99 78",
    "sg:postcode":"7130",
    "sg:province":"Hainaut",
    "wof:name":"R\u00c9sidence Le Marais",
    "wof:placetype":"venue"
},
  "geometry": {"coordinates":[4.1710681915,50.4056282043],"type":"Point"}
}