{
  "type": "Feature",
  "properties": {
    "iso:country":"BE",
    "sg:address":"Belgi\u00cblei 153",
    "sg:city":"Antwerpen",
    "sg:orig_category":"Cr\u00e9dit \u00e0 la consommation. Banques and organismes de cr\u00e9dit",
    "sg:phone":"+32 3 230 10 05",
    "sg:postcode":"2018",
    "sg:province":"Antwerpen",
    "wof:name":"Zetel Bank Corluy",
    "wof:placetype":"venue"
},
  "geometry": {"coordinates":[4.4157991409,51.203830719],"type":"Point"}
}