{
  "type": "Feature",
  "properties": {
    "iso:country":"BE",
    "sg:address":"Geldmuntstraat 11",
    "sg:city":"Brugge",
    "sg:orig_category":"Royal Canin. Animaux domestiques and accessoires",
    "sg:phone":"+32 50 33 01 02",
    "sg:postcode":"8000",
    "sg:province":"West-Vlaanderen",
    "wof:name":"M. De Coninck",
    "wof:placetype":"venue"
},
  "geometry": {"coordinates":[3.2225620747,51.2089157104],"type":"Point"}
}