{
  "type": "Feature",
  "properties": {
    "iso:country":"BE",
    "sg:address":"Rue Charles Dupret 1",
    "sg:city":"Charleroi",
    "sg:classifiers":[
        {
            "category":"Health Services",
            "subcategory":"Dentist",
            "type":"Services"
        }
    ],
    "sg:phone":"+32 71 32 60 71",
    "sg:postcode":"6000",
    "sg:province":"Hainaut",
    "wof:name":"Laurent Pierre",
    "wof:placetype":"venue"
},
  "geometry": {"coordinates":[4.4424099922,50.4075202942],"type":"Point"}
}