{
  "type": "Feature",
  "properties": {
    "iso:country":"BE",
    "sg:address":"Place P Werrie 20",
    "sg:city":"Jette",
    "sg:orig_category":"Blanchisseries and teintureries",
    "sg:phone":"+32 2 426 03 64",
    "sg:postcode":"1090",
    "sg:province":"Bruxelles-Capitale",
    "wof:name":"Pop Cleaners",
    "wof:placetype":"venue"
},
  "geometry": {"coordinates":[4.3247032166,50.8777427673],"type":"Point"}
}