{
  "type": "Feature",
  "properties": {
    "iso:country":"BE",
    "sg:address":"Rue Du Commerce 1",
    "sg:city":"Ch\u00e2telet",
    "sg:classifiers":[
        {
            "category":"Health Services",
            "subcategory":"Doctor",
            "type":"Services"
        }
    ],
    "sg:phone":"+32 71 39 55 42",
    "sg:postcode":"6200",
    "sg:province":"Hainaut",
    "sg:tags":[
        "medicinephysicians",
        "surgeon"
    ],
    "wof:name":"Demaret A",
    "wof:placetype":"venue"
},
  "geometry": {"coordinates":[4.5216431618,50.4046287537],"type":"Point"}
}