{
  "type": "Feature",
  "properties": {
    "addr:full":"Leuken 89 Lommel Limburg 3920",
    "addr:housenumber":"89",
    "addr:postcode":"3920",
    "addr:street":"Leuken",
    "iso:country":"BE",
    "sg:address":"Leuken 89",
    "sg:city":"Lommel",
    "sg:classifiers":[
        {
            "category":"Personal",
            "subcategory":"Beauty Salon",
            "type":"Services"
        }
    ],
    "sg:phone":"+32 11 64 02 71",
    "sg:postcode":"3920",
    "sg:province":"Limburg",
    "sg:tags":[
        "lady",
        "-",
        "hairdressing"
    ],
    "wof:name":"Monique",
    "wof:placetype":"venue"
},
  "geometry": {"coordinates":[5.372795105,51.2351531982],"type":"Point"}
}