{
  "type": "Feature",
  "properties": {
    "iso:country":"BE",
    "sg:address":"Rue De Doue 65b",
    "sg:city":"Quievrain",
    "sg:orig_category":"Sociale huisvestingsmaatschappijen",
    "sg:phone":"+32 65 45 87 55",
    "sg:postcode":"7380",
    "sg:province":"Hainaut",
    "wof:name":"Le Foyer Qui\u00c9vrainois",
    "wof:placetype":"venue"
},
  "geometry": {"coordinates":[3.6914429665,50.4069099426],"type":"Point"}
}