{
  "type": "Feature",
  "properties": {
    "addr:full":"Rue Vanderdussen 74 Brussel/bruxelles Bruxelles-Capitale 1080",
    "addr:housenumber":"74",
    "addr:postcode":"1080",
    "addr:street":"Rue Vanderdussen;/",
    "iso:country":"BE",
    "sg:address":"Rue Vanderdussen 74",
    "sg:city":"Brussel/bruxelles",
    "sg:orig_category":"Mat\u00e9riaux de construction Gr",
    "sg:phone":"+32 2 410 87 92",
    "sg:postcode":"1080",
    "sg:province":"Bruxelles-Capitale",
    "wof:name":"Plexi-creation",
    "wof:placetype":"venue"
},
  "geometry": {"coordinates":[4.3295068741,50.8541526794],"type":"Point"}
}