{
  "type": "Feature",
  "properties": {
    "iso:country":"BE",
    "sg:address":"Wipstraat 79",
    "sg:city":"Brasschaat",
    "sg:orig_category":"R\u00e9paration and restauration de meubles. Equipement divers pour commerces Gr",
    "sg:phone":"+32 3 633 16 80",
    "sg:postcode":"2930",
    "sg:province":"Antwerpen",
    "wof:name":"Huis Nietvelt",
    "wof:placetype":"venue"
},
  "geometry": {"coordinates":[4.521876812,51.3185539246],"type":"Point"}
}