{
  "type": "Feature",
  "properties": {
    "addr:full":"M. Van Torhoutstraat 82 Oudenaarde Oost-Vlaanderen 9700",
    "addr:housenumber":"82",
    "addr:postcode":"9700",
    "addr:street":"M. Van Torhoutstraat",
    "iso:country":"BE",
    "sg:address":"M. Van Torhoutstraat 82",
    "sg:city":"Oudenaarde",
    "sg:orig_category":"Poissonniers and \u00e9caillers. Commerces alimentaires sp\u00e9cialis\u00e9s Gr",
    "sg:phone":"+32 55 31 89 18",
    "sg:postcode":"9700",
    "sg:province":"Oost-Vlaanderen",
    "wof:name":"Fontaine",
    "wof:placetype":"venue"
},
  "geometry": {"coordinates":[3.6240270138,50.8493881226],"type":"Point"}
}