{
  "type": "Feature",
  "properties": {
    "addr:full":"Sentier Du D\u00e9tournement 39 Charleroi (gilly) Hainaut 6060",
    "addr:housenumber":"39",
    "addr:postcode":"6060",
    "addr:street":"Sentier Du De\u0301Tournement",
    "iso:country":"BE",
    "sg:address":"Sentier Du D\u00e9tournement 39",
    "sg:city":"Charleroi (gilly)",
    "sg:classifiers":[
        {
            "category":"Manufacturing",
            "subcategory":"Metals",
            "type":"Manufacturing & Wholesale Goods"
        }
    ],
    "sg:phone":"+32 71 41 47 51",
    "sg:postcode":"6060",
    "sg:province":"Hainaut",
    "sg:tags":[
        "turning"
    ],
    "wof:name":"Thays R",
    "wof:placetype":"venue"
},
  "geometry": {"coordinates":[4.4880981445,50.4251937866],"type":"Point"}
}