{
  "type": "Feature",
  "properties": {
    "addr:full":"Kortemarkstraat 43 Lichtervelde West-Vlaanderen 8810",
    "addr:housenumber":"43",
    "addr:postcode":"8810",
    "addr:street":"Kortemarkstraat",
    "iso:country":"BE",
    "sg:address":"Kortemarkstraat 43",
    "sg:city":"Lichtervelde",
    "sg:orig_category":"Plaatsen van vloer- and muurbekleding",
    "sg:phone":"+32 51 72 55 89",
    "sg:postcode":"8810",
    "sg:province":"West-Vlaanderen",
    "wof:name":"Rudi Dewilde",
    "wof:placetype":"venue"
},
  "geometry": {"coordinates":[3.1240029335,51.0238876343],"type":"Point"}
}