{
  "type": "Feature",
  "properties": {
    "addr:full":"Blekerijstraat 5 Ardooie West-Vlaanderen 8850",
    "addr:housenumber":"5",
    "addr:postcode":"8850",
    "addr:street":"Blekerijstraat",
    "iso:country":"BE",
    "sg:address":"Blekerijstraat 5",
    "sg:city":"Ardooie",
    "sg:orig_category":"Enseignement maternel and primaire. Enseignement secondaire g\u00e9n\u00e9ral",
    "sg:phone":"+32 51 74 68 98",
    "sg:postcode":"8850",
    "sg:province":"West-Vlaanderen",
    "wof:name":"Vrije Basisschool",
    "wof:placetype":"venue"
},
  "geometry": {"coordinates":[3.2005400658,50.9754219055],"type":"Point"}
}