{
  "type": "Feature",
  "properties": {
    "addr:full":"H\u00c9bronval 26 Vielsalm Luxembourg 6690",
    "addr:housenumber":"26",
    "addr:postcode":"6690",
    "addr:street":"He\u0301Bronval",
    "iso:country":"BE",
    "sg:address":"H\u00c9bronval 26",
    "sg:city":"Vielsalm",
    "sg:orig_category":"Eclairage et \u00e9quipements du foyer",
    "sg:phone":"+32 80 41 87 41",
    "sg:postcode":"6690",
    "sg:province":"Luxembourg",
    "wof:name":"Monfort Decor Home",
    "wof:placetype":"venue"
},
  "geometry": {"coordinates":[5.8119587898,50.2535476685],"type":"Point"}
}