{
  "type": "Feature",
  "properties": {
    "iso:country":"BE",
    "sg:address":"Ijzerenmolenstraat 32b3414",
    "sg:city":"Leuven",
    "sg:orig_category":"Dakwerken",
    "sg:phone":"+32 16 48 15 11",
    "sg:postcode":"3001",
    "sg:province":"Vlaams-Brabant",
    "wof:name":"Fa. Vercammen",
    "wof:placetype":"venue"
},
  "geometry": {"coordinates":[4.6871471405,50.8719444275],"type":"Point"}
}