{
  "type": "Feature",
  "properties": {
    "iso:country":"BE",
    "sg:address":"Brandheide 50",
    "sg:city":"Bornem",
    "sg:classifiers":[
        {
            "category":"Personal",
            "subcategory":"Beauty Salon",
            "type":"Services"
        }
    ],
    "sg:phone":"+32 3 889 65 30",
    "sg:postcode":"2880",
    "sg:province":"Antwerpen",
    "sg:tags":[
        "de",
        "coiffure"
    ],
    "wof:name":"Nicole Van Barel",
    "wof:placetype":"venue"
},
  "geometry": {"coordinates":[4.2188358307,51.0896453857],"type":"Point"}
}