{
  "type": "Feature",
  "properties": {
    "addr:full":"Kerkplein 1 Waregem West-Vlaanderen 8791",
    "addr:housenumber":"1",
    "addr:postcode":"8791",
    "addr:street":"Kerkplein",
    "iso:country":"BE",
    "sg:address":"Kerkplein 1",
    "sg:city":"Waregem",
    "sg:orig_category":"Banques and organismes de cr\u00e9dit",
    "sg:phone":"+32 56 70 59 46",
    "sg:postcode":"8791",
    "sg:province":"West-Vlaanderen",
    "wof:name":"Centea",
    "wof:placetype":"venue"
},
  "geometry": {"coordinates":[3.3455719948,50.8748855591],"type":"Point"}
}