{
  "type": "Feature",
  "properties": {
    "iso:country":"BE",
    "sg:address":"Frankrijkstraat 6",
    "sg:city":"Moeskroen/mouscron",
    "sg:orig_category":"Dakwerken",
    "sg:phone":"+32 56 48 93 22",
    "sg:postcode":"7711",
    "sg:province":"Hainaut",
    "wof:name":"Toutoit",
    "wof:placetype":"venue"
},
  "geometry": {"coordinates":[3.302877903,50.7274665833],"type":"Point"}
}