{
  "type": "Feature",
  "properties": {
    "iso:country":"BE",
    "sg:address":"Papbosstraat 1",
    "sg:city":"Brecht",
    "sg:orig_category":"Maisons de repos and r\u00e9sidences",
    "sg:phone":"+32 3 313 71 36",
    "sg:postcode":"2960",
    "sg:province":"Antwerpen",
    "wof:name":"Residentie Boshoeve",
    "wof:placetype":"venue"
},
  "geometry": {"coordinates":[4.6313409805,51.3601760864],"type":"Point"}
}