{
  "type": "Feature",
  "properties": {
    "iso:country":"BE",
    "sg:address":"Duinhoekstraat 11",
    "sg:city":"De Panne",
    "sg:classifiers":[
        {
            "category":"Sports & Exercise",
            "subcategory":"Stables",
            "type":"Entertainment"
        }
    ],
    "sg:phone":"+32 58 41 52 02",
    "sg:postcode":"8660",
    "sg:province":"West-Vlaanderen",
    "sg:tags":[
        "riding",
        "school"
    ],
    "wof:name":"Peerd Manege ('t)",
    "wof:placetype":"venue"
},
  "geometry": {"coordinates":[2.5978829861,51.0848464966],"type":"Point"}
}