{
  "type": "Feature",
  "properties": {
    "addr:full":"Lembergsesteenweg 153a Merelbeke Oost-Vlaanderen 9820",
    "addr:housenumber":"153a",
    "addr:postcode":"9820",
    "addr:street":"Lembergsesteenweg",
    "iso:country":"BE",
    "sg:address":"Lembergsesteenweg 153a",
    "sg:city":"Merelbeke",
    "sg:classifiers":[
        {
            "category":"Building & Trades",
            "subcategory":"Electrical",
            "type":"Services"
        }
    ],
    "sg:phone":"+32 9 231 51 73",
    "sg:postcode":"9820",
    "sg:province":"Oost-Vlaanderen",
    "sg:tags":[
        "electric",
        "-",
        "housewiring",
        "contractor"
    ],
    "wof:name":"Van Baeveghem Bvba",
    "wof:placetype":"venue"
},
  "geometry": {"coordinates":[3.7602419853,50.992351532],"type":"Point"}
}