{
  "type": "Feature",
  "properties": {
    "addr:full":"Thier M\u00c8re-dieu 3 Verviers Li\u00e8ge 4800",
    "addr:housenumber":"3",
    "addr:postcode":"4800",
    "addr:street":"Thier Me\u0300Re-Dieu",
    "iso:country":"BE",
    "sg:address":"Thier M\u00c8re-dieu 3",
    "sg:city":"Verviers",
    "sg:orig_category":"Apotheken",
    "sg:phone":"+32 87 33 19 95",
    "sg:postcode":"4800",
    "sg:province":"Li\u00e8ge",
    "wof:name":"Pharmacie Mourad",
    "wof:placetype":"venue"
},
  "geometry": {"coordinates":[5.8678212166,50.5929527283],"type":"Point"}
}