{
  "type": "Feature",
  "properties": {
    "addr:full":"Begijnhofdries 53 Gent Oost-Vlaanderen 9000",
    "addr:housenumber":"53",
    "addr:postcode":"9000",
    "addr:street":"Begijnhofdries;Oost-Vlaanderen",
    "iso:country":"BE",
    "sg:address":"Begijnhofdries 53",
    "sg:city":"Gent",
    "sg:classifiers":[
        {
            "category":"Health Services",
            "subcategory":"Dentist",
            "type":"Services"
        }
    ],
    "sg:phone":"+32 9 225 03 68",
    "sg:postcode":"9000",
    "sg:province":"Oost-Vlaanderen",
    "wof:name":"De Borchgrave Ph",
    "wof:placetype":"venue"
},
  "geometry": {"coordinates":[3.7137329578,51.0571289062],"type":"Point"}
}