{
  "type": "Feature",
  "properties": {
    "iso:country":"BE",
    "sg:address":"Place Des Fran\u00c7ais 4",
    "sg:city":"Hensies",
    "sg:orig_category":"Artsen and specialisten",
    "sg:phone":"+32 65 65 23 07",
    "sg:postcode":"7350",
    "sg:province":"Hainaut",
    "wof:name":"Emile Degaute",
    "wof:placetype":"venue"
},
  "geometry": {"coordinates":[3.7376880646,50.4272651672],"type":"Point"}
}