{
  "type": "Feature",
  "properties": {
    "iso:country":"BE",
    "sg:address":"Rue Des Alli\u00c9s 93",
    "sg:city":"Frameries",
    "sg:orig_category":"Meubles D\u00e9taillants, Am\u00e9nagement de B\u00e2timents et de Cuisines. Meubles Fab. Fabrication and montage d",
    "sg:phone":"+32 65 66 91 60",
    "sg:postcode":"7080",
    "sg:province":"Hainaut",
    "wof:name":"Home Confort Frameries",
    "wof:placetype":"venue"
},
  "geometry": {"coordinates":[3.8938999176,50.4074287415],"type":"Point"}
}