{
  "type": "Feature",
  "properties": {
    "addr:full":"Rue Du Cheval Blanc 30b Bassenge (glons) Li\u00e8ge 4690",
    "addr:housenumber":"30b",
    "addr:postcode":"4690",
    "addr:street":"Rue Du Cheval Blanc;Glons",
    "iso:country":"BE",
    "sg:address":"Rue Du Cheval Blanc 30b",
    "sg:city":"Bassenge (glons)",
    "sg:classifiers":[
        {
            "category":"Shopping",
            "subcategory":"Bicycles & Sporting Goods",
            "type":"Retail Goods"
        }
    ],
    "sg:phone":"+32 4 286 16 39",
    "sg:postcode":"4690",
    "sg:province":"Li\u00e8ge",
    "sg:tags":[
        "tyre"
    ],
    "wof:name":"Bastin Garage Sa",
    "wof:placetype":"venue"
},
  "geometry": {"coordinates":[5.5622220039,50.7526397705],"type":"Point"}
}