{
  "type": "Feature",
  "properties": {
    "addr:full":"Gentstraat 9b1 Oudenaarde Oost-Vlaanderen 9700",
    "addr:housenumber":"9b1",
    "addr:postcode":"9700",
    "addr:street":"Gentstraat",
    "iso:country":"BE",
    "sg:address":"Gentstraat 9b1",
    "sg:city":"Oudenaarde",
    "sg:orig_category":"Imprimeries and copyshops",
    "sg:phone":"+32 55 31 34 64",
    "sg:postcode":"9700",
    "sg:province":"Oost-Vlaanderen",
    "wof:name":"Kamer Bouwbedrijf Z-o-vl.",
    "wof:placetype":"venue"
},
  "geometry": {"coordinates":[3.5985600948,50.8497543335],"type":"Point"}
}