{
  "type": "Feature",
  "properties": {
    "iso:country":"BE",
    "sg:address":"Rue Lesbroussart 88",
    "sg:city":"Elsene/ixelles",
    "sg:orig_category":"Activit\u00e9s r\u00e9cr\u00e9atives diverses",
    "sg:phone":"+32 2 648 39 95",
    "sg:postcode":"1050",
    "sg:province":"Bruxelles-Capitale",
    "wof:name":"B.c. Royal Uccle Sport",
    "wof:placetype":"venue"
},
  "geometry": {"coordinates":[4.3668851852,50.8275299072],"type":"Point"}
}