{
  "type": "Feature",
  "properties": {
    "addr:full":"Oud Gasthuisstraat 15 Tervuren Vlaams-Brabant 3080",
    "addr:housenumber":"15",
    "addr:postcode":"3080",
    "addr:street":"Oud Gasthuisstraat",
    "iso:country":"BE",
    "sg:address":"Oud Gasthuisstraat 15",
    "sg:city":"Tervuren",
    "sg:classifiers":[
        {
            "category":"Animal Shelter",
            "type":"Public Place"
        }
    ],
    "sg:phone":"+32 2 768 01 97",
    "sg:postcode":"3080",
    "sg:province":"Vlaams-Brabant",
    "wof:name":"Stassin V",
    "wof:placetype":"venue"
},
  "geometry": {"coordinates":[4.5091462135,50.8209533691],"type":"Point"}
}