{
  "type": "Feature",
  "properties": {
    "addr:full":"Gaversesteenweg 518 Merelbeke Oost-Vlaanderen 9820",
    "addr:housenumber":"518",
    "addr:postcode":"9820",
    "addr:street":"Gaversesteenweg",
    "iso:country":"BE",
    "sg:address":"Gaversesteenweg 518",
    "sg:city":"Merelbeke",
    "sg:orig_category":"Enseignement maternel and primaire",
    "sg:phone":"+32 9 362 60 41",
    "sg:postcode":"9820",
    "sg:province":"Oost-Vlaanderen",
    "wof:name":"Vrije Basisschool",
    "wof:placetype":"venue"
},
  "geometry": {"coordinates":[3.7139439583,50.9706192017],"type":"Point"}
}