{
  "type": "Feature",
  "properties": {
    "addr:full":"Sint-truidensesteenweg 4 Tienen Vlaams-Brabant 3300",
    "addr:housenumber":"4",
    "addr:postcode":"3300",
    "addr:street":"Sint-Truidensesteenweg",
    "iso:country":"BE",
    "sg:address":"Sint-truidensesteenweg 4",
    "sg:city":"Tienen",
    "sg:orig_category":"Pain, p\u00e2tisseries and confiseries",
    "sg:phone":"+32 16 81 21 16",
    "sg:postcode":"3300",
    "sg:province":"Vlaams-Brabant",
    "wof:name":"Freddy Geyskens",
    "wof:placetype":"venue"
},
  "geometry": {"coordinates":[4.9540910721,50.8012084961],"type":"Point"}
}