{
  "type": "Feature",
  "properties": {
    "addr:full":"Beukenlaan 18 Beveren Oost-Vlaanderen 9130",
    "addr:housenumber":"18",
    "addr:postcode":"9130",
    "addr:street":"Beukenlaan",
    "iso:country":"BE",
    "sg:address":"Beukenlaan 18",
    "sg:city":"Beveren",
    "sg:orig_category":"S\u00e9curit\u00e9 sociale",
    "sg:phone":"+32 3 773 49 65",
    "sg:postcode":"9130",
    "sg:province":"Oost-Vlaanderen",
    "wof:name":"Christelijke Mutualiteit",
    "wof:placetype":"venue"
},
  "geometry": {"coordinates":[4.1771941185,51.2902832031],"type":"Point"}
}