{
  "type": "Feature",
  "properties": {
    "iso:country":"BE",
    "sg:address":"Avenue Du Parc 82",
    "sg:city":"Sint-gillis",
    "sg:orig_category":"Agences d'exp\u00e9dition",
    "sg:phone":"+32 2 539 38 61",
    "sg:postcode":"1060",
    "sg:province":"Bruxelles-Capitale",
    "wof:name":"Cox's International",
    "wof:placetype":"venue"
},
  "geometry": {"coordinates":[4.3410058022,50.8257217407],"type":"Point"}
}