{
  "type": "Feature",
  "properties": {
    "iso:country":"BE",
    "sg:address":"Zone Artisanale 1",
    "sg:city":"Chiny (jamoigne)",
    "sg:classifiers":[
        {
            "category":"Shopping",
            "subcategory":"Bicycles & Sporting Goods",
            "type":"Retail Goods"
        }
    ],
    "sg:phone":"+32 61 32 52 10",
    "sg:postcode":"6810",
    "sg:province":"Luxembourg",
    "sg:tags":[
        "tyre"
    ],
    "wof:name":"Herbeuval Pneus Center",
    "wof:placetype":"venue"
},
  "geometry": {"coordinates":[5.3405580521,49.7382736206],"type":"Point"}
}