{
  "type": "Feature",
  "properties": {
    "iso:country":"BE",
    "sg:address":"Beernaardstraat 36",
    "sg:city":"Haaltert",
    "sg:classifiers":[
        {
            "category":"Farming",
            "subcategory":"Livestock Farm",
            "type":"Manufacturing & Wholesale Goods"
        }
    ],
    "sg:phone":"+32 53 83 82 35",
    "sg:postcode":"9450",
    "sg:province":"Oost-Vlaanderen",
    "sg:tags":[
        "poultry",
        "rabbit"
    ],
    "wof:name":"Provost E",
    "wof:placetype":"venue"
},
  "geometry": {"coordinates":[3.9817349911,50.891002655],"type":"Point"}
}