{
  "type": "Feature",
  "properties": {
    "iso:country":"BE",
    "sg:address":"Bergstraat 63",
    "sg:city":"Aarschot",
    "sg:orig_category":"Producteurs de l\u00e9gumes. Producteurs de fruits",
    "sg:phone":"+32 16 56 34 49",
    "sg:postcode":"3200",
    "sg:province":"Vlaams-Brabant",
    "wof:name":"Ivo Elsen",
    "wof:placetype":"venue"
},
  "geometry": {"coordinates":[4.7989888191,50.968296051],"type":"Point"}
}