{
  "type": "Feature",
  "properties": {
    "addr:full":"Vaderlandstraat 49 Gent Oost-Vlaanderen 9000",
    "addr:housenumber":"49",
    "addr:postcode":"9000",
    "addr:street":"Vaderlandstraat;Oost-Vlaanderen",
    "iso:country":"BE",
    "sg:address":"Vaderlandstraat 49",
    "sg:city":"Gent",
    "sg:orig_category":"M\u00e9decins and sp\u00e9cialistes",
    "sg:phone":"+32 9 222 40 89",
    "sg:postcode":"9000",
    "sg:province":"Oost-Vlaanderen",
    "wof:name":"Sofie Gevaert",
    "wof:placetype":"venue"
},
  "geometry": {"coordinates":[3.7189149857,51.0300941467],"type":"Point"}
}