{
  "type": "Feature",
  "properties": {
    "addr:full":"Rue Des Alli\u00c9s 180ba Geraardsbergen Oost-Vlaanderen 9506",
    "addr:postcode":"180ba;9506",
    "addr:street":"Rue Des Allie\u0301S",
    "iso:country":"BE",
    "sg:address":"Rue Des Alli\u00c9s 180ba",
    "sg:city":"Geraardsbergen",
    "sg:orig_category":"Boucheries",
    "sg:phone":"+32 54 33 05 15",
    "sg:postcode":"9506",
    "sg:province":"Oost-Vlaanderen",
    "wof:name":"Beenhouwerij Christiaan",
    "wof:placetype":"venue"
},
  "geometry": {"coordinates":[3.8985300064,50.7987060547],"type":"Point"}
}