{
  "type": "Feature",
  "properties": {
    "addr:full":"Bezemstraat 3 Meulebeke West-Vlaanderen 8760",
    "addr:housenumber":"3",
    "addr:postcode":"8760",
    "addr:street":"Bezemstraat",
    "iso:country":"BE",
    "sg:address":"Bezemstraat 3",
    "sg:city":"Meulebeke",
    "sg:classifiers":[
        {
            "category":"Building & Trades",
            "subcategory":"Construction",
            "type":"Services"
        }
    ],
    "sg:phone":"+32 51 48 80 48",
    "sg:postcode":"8760",
    "sg:province":"West-Vlaanderen",
    "sg:tags":[
        "carpenter"
    ],
    "wof:name":"Louvaert M",
    "wof:placetype":"venue"
},
  "geometry": {"coordinates":[3.2891631126,50.9522018433],"type":"Point"}
}