{
  "type": "Feature",
  "properties": {
    "addr:full":"Boulevard Cuivre Et Zinc 19 Liege Li\u00e8ge 4030",
    "addr:housenumber":"19",
    "addr:postcode":"4030",
    "addr:street":"Boulevard Cuivre Et Zinc",
    "iso:country":"BE",
    "sg:address":"Boulevard Cuivre Et Zinc 19",
    "sg:city":"Liege",
    "sg:orig_category":"Geschenken and souvenirs Speelgoed Verlichting and huishoudartikelen",
    "sg:phone":"+32 4 344 29 15",
    "sg:postcode":"4030",
    "sg:province":"Li\u00e8ge",
    "wof:name":"Blokker",
    "wof:placetype":"venue"
},
  "geometry": {"coordinates":[5.6046648026,50.6188240051],"type":"Point"}
}