{
  "type": "Feature",
  "properties": {
    "addr:full":"Sparrenweg 220 Tessenderlo Limburg 3980",
    "addr:housenumber":"220",
    "addr:postcode":"3980",
    "addr:street":"Sparrenweg",
    "iso:country":"BE",
    "sg:address":"Sparrenweg 220",
    "sg:city":"Tessenderlo",
    "sg:classifiers":[
        {
            "category":"Retail",
            "subcategory":"Auto Repair",
            "type":"Services"
        }
    ],
    "sg:phone":"+32 13 67 46 69",
    "sg:postcode":"3980",
    "sg:province":"Limburg",
    "sg:tags":[
        "garage"
    ],
    "wof:name":"Thys Motors",
    "wof:placetype":"venue"
},
  "geometry": {"coordinates":[5.0487818718,51.0537872314],"type":"Point"}
}