{
  "type": "Feature",
  "properties": {
    "iso:country":"BE",
    "sg:address":"Louis De Camoenslaan 6",
    "sg:city":"De Haan",
    "sg:orig_category":"Orphelinats. Instituts pour enfants en difficult\u00e9",
    "sg:phone":"+32 59 23 33 71",
    "sg:postcode":"8420",
    "sg:province":"West-Vlaanderen",
    "wof:name":"Huize De Biekorf",
    "wof:placetype":"venue"
},
  "geometry": {"coordinates":[3.0294640064,51.2733840942],"type":"Point"}
}