{
  "type": "Feature",
  "properties": {
    "addr:full":"Heikantstraat 128 Schoten Antwerpen 2900",
    "addr:housenumber":"128",
    "addr:postcode":"2900",
    "addr:street":"Heikantstraat",
    "iso:country":"BE",
    "sg:address":"Heikantstraat 128",
    "sg:city":"Schoten",
    "sg:classifiers":[
        {
            "category":"Wholesale",
            "subcategory":"Medical Equipment & Supplies",
            "type":"Manufacturing & Wholesale Goods"
        }
    ],
    "sg:phone":"+32 3 685 07 23",
    "sg:postcode":"2900",
    "sg:province":"Antwerpen",
    "sg:tags":[
        "instrument",
        "apparatus"
    ],
    "wof:name":"Ecce Medical Bvba",
    "wof:placetype":"venue"
},
  "geometry": {"coordinates":[4.5100898743,51.2566604614],"type":"Point"}
}