{
  "type": "Feature",
  "properties": {
    "addr:full":"Walenstraat 71 Hasselt Limburg 3500",
    "addr:housenumber":"71",
    "addr:postcode":"3500",
    "addr:street":"Walenstraat",
    "iso:country":"BE",
    "sg:address":"Walenstraat 71",
    "sg:city":"Hasselt",
    "sg:classifiers":[
        {
            "category":"Communications",
            "subcategory":"Newspaper",
            "type":"Services"
        }
    ],
    "sg:phone":"+32 11 37 93 11",
    "sg:postcode":"3500",
    "sg:province":"Limburg",
    "sg:tags":[
        "paper",
        "local",
        "free"
    ],
    "wof:name":"De Weekkrant/de Streekkrant",
    "wof:placetype":"venue"
},
  "geometry": {"coordinates":[5.3594059944,50.9538574219],"type":"Point"}
}