{
  "type": "Feature",
  "properties": {
    "addr:full":"Chemin Des Soeurs 22 Beauvechain (nodebais) Brabant Wallon 1320",
    "addr:housenumber":"22",
    "addr:postcode":"1320",
    "addr:street":"Chemin Des Soeurs;Wallon",
    "iso:country":"BE",
    "sg:address":"Chemin Des Soeurs 22",
    "sg:city":"Beauvechain (nodebais)",
    "sg:classifiers":[
        {
            "category":"Real Estate",
            "subcategory":"Architect",
            "type":"Services"
        }
    ],
    "sg:phone":"+32 10 86 10 58",
    "sg:postcode":"1320",
    "sg:province":"Brabant Wallon",
    "wof:name":"Hecht Ariane",
    "wof:placetype":"venue"
},
  "geometry": {"coordinates":[4.7393631935,50.7690086365],"type":"Point"}
}