{
  "type": "Feature",
  "properties": {
    "iso:country":"BE",
    "sg:address":"Diesterstw 44",
    "sg:city":"Paal",
    "sg:classifiers":[
        {
            "category":"Professional",
            "subcategory":"Computer Services",
            "type":"Services"
        }
    ],
    "sg:phone":"+32 11 72 55 59",
    "sg:postcode":"3583",
    "sg:province":"Limburg",
    "sg:tags":[
        "information",
        "technology",
        "software"
    ],
    "wof:name":"Gieren-reynders",
    "wof:placetype":"venue"
},
  "geometry": {"coordinates":[5.168820858,51.0379486084],"type":"Point"}
}