{
  "type": "Feature",
  "properties": {
    "iso:country":"BE",
    "sg:address":"Houffalizeplein 24",
    "sg:city":"Schaarbeek/schaerbeek",
    "sg:classifiers":[
        {
            "category":"Communications",
            "subcategory":"Television Station",
            "type":"Services"
        }
    ],
    "sg:phone":"+32 2 215 21 68",
    "sg:postcode":"1030",
    "sg:province":"Bruxelles-Capitale",
    "sg:tags":[
        "video",
        "audio",
        "verhuur"
    ],
    "wof:name":"New Yvan Vid\u00c9o",
    "wof:placetype":"venue"
},
  "geometry": {"coordinates":[4.3777050972,50.8649101257],"type":"Point"}
}