{
  "type": "Feature",
  "properties": {
    "addr:full":"Beliestraat 111 Essen Antwerpen 2910",
    "addr:housenumber":"111",
    "addr:postcode":"2910",
    "addr:street":"Beliestraat",
    "iso:country":"BE",
    "sg:address":"Beliestraat 111",
    "sg:city":"Essen",
    "sg:orig_category":"Artsen and specialisten",
    "sg:phone":"+32 3 667 63 15",
    "sg:postcode":"2910",
    "sg:province":"Antwerpen",
    "wof:name":"J. Van Meel",
    "wof:placetype":"venue"
},
  "geometry": {"coordinates":[4.4638910294,51.4622192383],"type":"Point"}
}