{
  "type": "Feature",
  "properties": {
    "iso:country":"BE",
    "sg:address":"Franklin Rooseveltplein 12",
    "sg:city":"Ronse/renaix",
    "sg:orig_category":"Huishoudapparaten, televisies and radio's",
    "sg:phone":"+32 55 21 15 41",
    "sg:postcode":"9600",
    "sg:province":"Oost-Vlaanderen",
    "wof:name":"Fa. Huysman",
    "wof:placetype":"venue"
},
  "geometry": {"coordinates":[3.5992779732,50.7467498779],"type":"Point"}
}