{
  "type": "Feature",
  "properties": {
    "iso:country":"BE",
    "sg:address":"Rue Godelet 2",
    "sg:city":"Huy",
    "sg:classifiers":[
        {
            "category":"Food & Beverages",
            "subcategory":"Groceries & Convenience Stores",
            "type":"Retail Goods"
        }
    ],
    "sg:phone":"+32 85 23 53 44",
    "sg:postcode":"4500",
    "sg:province":"Li\u00e8ge",
    "sg:tags":[
        "grocer"
    ],
    "wof:name":"Champion Groupe Mestdagh Sa",
    "wof:placetype":"venue"
},
  "geometry": {"coordinates":[5.2345480919,50.5209197998],"type":"Point"}
}