{
  "type": "Feature",
  "properties": {
    "addr:full":"Rue Ma\u00efeur Carlot 11 Honnelles (fayt-le-franc) Hainaut 7387",
    "addr:housenumber":"11",
    "addr:postcode":"7387",
    "addr:street":"Rue Mai\u0308Eur Carlot",
    "iso:country":"BE",
    "sg:address":"Rue Ma\u00efeur Carlot 11",
    "sg:city":"Honnelles (fayt-le-franc)",
    "sg:classifiers":[
        {
            "category":"Health Services",
            "subcategory":"Health Practitioner",
            "type":"Services"
        }
    ],
    "sg:phone":"+32 65 63 31 20",
    "sg:postcode":"7387",
    "sg:province":"Hainaut",
    "sg:tags":[
        "physiotherapist"
    ],
    "wof:name":"Henaut M-c",
    "wof:placetype":"venue"
},
  "geometry": {"coordinates":[3.7736120224,50.3558235168],"type":"Point"}
}