{
  "type": "Feature",
  "properties": {
    "iso:country":"BE",
    "sg:address":"Rue De Dour 585",
    "sg:city":"Boussu",
    "sg:orig_category":"D\u00e9corateurs d'int\u00e9rieur",
    "sg:phone":"+32 65 65 31 44",
    "sg:postcode":"7300",
    "sg:province":"Hainaut",
    "wof:name":"Hayez L.",
    "wof:placetype":"venue"
},
  "geometry": {"coordinates":[3.7864499092,50.4198112488],"type":"Point"}
}