{
  "type": "Feature",
  "properties": {
    "iso:country":"BE",
    "sg:address":"Source De La L\u00e8che 32",
    "sg:city":"Chaudfontaine (embourg)",
    "sg:classifiers":[
        {
            "category":"Professional",
            "subcategory":"Accounting & Tax Preparation",
            "type":"Services"
        }
    ],
    "sg:phone":"+32 4 365 78 89",
    "sg:postcode":"4053",
    "sg:province":"Li\u00e8ge",
    "sg:tags":[
        "bookkeeper"
    ],
    "wof:name":"Blanpin D",
    "wof:placetype":"venue"
},
  "geometry": {"coordinates":[5.6116828918,50.5885047913],"type":"Point"}
}