{
  "type": "Feature",
  "properties": {
    "addr:full":"Rue De Monsville 275 Quaregnon Hainaut 7390",
    "addr:housenumber":"275",
    "addr:postcode":"7390",
    "addr:street":"Rue De Monsville",
    "iso:country":"BE",
    "sg:address":"Rue De Monsville 275",
    "sg:city":"Quaregnon",
    "sg:orig_category":"Pain, p\u00e2tisseries and confiseries. Caf\u00e9s",
    "sg:phone":"+32 65 79 42 86",
    "sg:postcode":"7390",
    "sg:province":"Hainaut",
    "wof:name":"Francine Guerit",
    "wof:placetype":"venue"
},
  "geometry": {"coordinates":[3.8632071018,50.4347190857],"type":"Point"}
}