{
  "type": "Feature",
  "properties": {
    "addr:full":"De Tilbourgstraat 7 Zemst Vlaams-Brabant 1981",
    "addr:housenumber":"7",
    "addr:postcode":"1981",
    "addr:street":"De Tilbourgstraat;Vlaams-Brabant",
    "iso:country":"BE",
    "sg:address":"De Tilbourgstraat 7",
    "sg:city":"Zemst",
    "sg:orig_category":"Rev\u00eatements de sols and murs. Rev\u00eatements pour sols and murs. Peinture",
    "sg:phone":"+32 15 61 71 57",
    "sg:postcode":"1981",
    "sg:province":"Vlaams-Brabant",
    "wof:name":"Salence Deco",
    "wof:placetype":"venue"
},
  "geometry": {"coordinates":[4.4953141212,50.989780426],"type":"Point"}
}