{
  "type": "Feature",
  "properties": {
    "iso:country":"BE",
    "sg:address":"Kortrijksestraat 103",
    "sg:city":"Oostkamp",
    "sg:classifiers":[
        {
            "category":"Food & Beverages",
            "subcategory":"Supermarket",
            "type":"Retail Goods"
        }
    ],
    "sg:phone":"+32 50 82 48 71",
    "sg:postcode":"8020",
    "sg:province":"West-Vlaanderen",
    "sg:tags":[
        "department",
        "store"
    ],
    "wof:name":"Ad-delhaize",
    "wof:placetype":"venue"
},
  "geometry": {"coordinates":[3.2332689762,51.1496047974],"type":"Point"}
}