{
  "type": "Feature",
  "properties": {
    "iso:country":"BE",
    "sg:address":"Beauloup 6",
    "sg:city":"Stoumont (la Gleize)",
    "sg:classifiers":[
        {
            "category":"Building & Trades",
            "subcategory":"Landscaping Services",
            "type":"Services"
        }
    ],
    "sg:postcode":"4987",
    "sg:province":"Li\u00e8ge",
    "sg:tags":[
        "gardening",
        "garden",
        "maintenance"
    ],
    "wof:name":"De Heide Hoeve",
    "wof:placetype":"venue"
},
  "geometry": {"coordinates":[4.6811962128,51.5354995728],"type":"Point"}
}