{
  "type": "Feature",
  "properties": {
    "addr:full":"Achterstraat 37 Ichtegem (eernegem) West-Vlaanderen 8480",
    "addr:housenumber":"37",
    "addr:postcode":"8480",
    "addr:street":"Achterstraat",
    "iso:country":"BE",
    "sg:address":"Achterstraat 37",
    "sg:city":"Ichtegem (eernegem)",
    "sg:classifiers":[
        {
            "category":"Retail",
            "subcategory":"Veterinary Services",
            "type":"Services"
        }
    ],
    "sg:phone":"+32 59 29 94 58",
    "sg:postcode":"8480",
    "sg:province":"West-Vlaanderen",
    "sg:tags":[
        "veterinarian"
    ],
    "wof:name":"Meyns M",
    "wof:placetype":"venue"
},
  "geometry": {"coordinates":[3.0331869125,51.1262779236],"type":"Point"}
}