{
  "type": "Feature",
  "properties": {
    "iso:country":"BE",
    "sg:address":"Rue Achille Debacker 92",
    "sg:city":"Mouscron",
    "sg:orig_category":"Overheidsdiensten",
    "sg:phone":"+32 56 33 10 02",
    "sg:postcode":"7700",
    "sg:province":"Hainaut",
    "wof:name":"C.a.p.a.c",
    "wof:placetype":"venue"
},
  "geometry": {"coordinates":[3.2205688953,50.7408714294],"type":"Point"}
}