{
  "type": "Feature",
  "properties": {
    "addr:full":"Ijzerlei 5 Leopoldsburg Limburg 3970",
    "addr:housenumber":"5",
    "addr:postcode":"3970",
    "addr:street":"Ijzerlei",
    "iso:country":"BE",
    "sg:address":"Ijzerlei 5",
    "sg:city":"Leopoldsburg",
    "sg:orig_category":"Advocaten and juridische adviseurs",
    "sg:phone":"+32 11 34 89 56",
    "sg:postcode":"3970",
    "sg:province":"Limburg",
    "wof:name":"Luc Cox",
    "wof:placetype":"venue"
},
  "geometry": {"coordinates":[5.2571501732,51.1166572571],"type":"Point"}
}