{
  "type": "Feature",
  "properties": {
    "addr:full":"Tiensesteenweg 121 Sint-truiden Limburg 3800",
    "addr:housenumber":"121",
    "addr:postcode":"3800",
    "addr:street":"Tiensesteenweg",
    "iso:country":"BE",
    "sg:address":"Tiensesteenweg 121",
    "sg:city":"Sint-truiden",
    "sg:orig_category":"Herstellingen and onderhoud van auto's Metaalafval, schrootrecyclage and sloperijen",
    "sg:phone":"+32 11 68 39 41",
    "sg:postcode":"3800",
    "sg:province":"Limburg",
    "wof:name":"Garage Milou & Michel",
    "wof:placetype":"venue"
},
  "geometry": {"coordinates":[5.174487114,50.8151664734],"type":"Point"}
}