{
  "type": "Feature",
  "properties": {
    "iso:country":"BE",
    "sg:address":"Hoogkasterstraat 18",
    "sg:city":"Wetteren",
    "sg:classifiers":[
        {
            "category":"Food & Beverages",
            "subcategory":"Meat & Fish",
            "type":"Retail Goods"
        }
    ],
    "sg:phone":"+32 9 369 29 68",
    "sg:postcode":"9230",
    "sg:province":"Oost-Vlaanderen",
    "sg:tags":[
        "-",
        "livestock"
    ],
    "wof:name":"Verhoeve A",
    "wof:placetype":"venue"
},
  "geometry": {"coordinates":[3.890141964,51.0146560669],"type":"Point"}
}