{
  "type": "Feature",
  "properties": {
    "iso:country":"BE",
    "sg:address":"Voordestraat 8",
    "sg:city":"Lovendegem",
    "sg:orig_category":"Eleveurs and marchands de porcs",
    "sg:phone":"+32 9 372 83 78",
    "sg:postcode":"9920",
    "sg:province":"Oost-Vlaanderen",
    "wof:name":"Carlos De Cuyper",
    "wof:placetype":"venue"
},
  "geometry": {"coordinates":[3.6200459003,51.119594574],"type":"Point"}
}