{
  "type": "Feature",
  "properties": {
    "addr:full":"Ronsenheerweg 3 Oudenaarde Oost-Vlaanderen 9700",
    "addr:housenumber":"3",
    "addr:postcode":"9700",
    "addr:street":"Ronsenheerweg",
    "iso:country":"BE",
    "sg:address":"Ronsenheerweg 3",
    "sg:city":"Oudenaarde",
    "sg:orig_category":"Installatie van houten of kunststof schrijnwerk",
    "sg:phone":"+32 55 49 69 45",
    "sg:postcode":"9700",
    "sg:province":"Oost-Vlaanderen",
    "wof:name":"Schrijnwerkerij Baert",
    "wof:placetype":"venue"
},
  "geometry": {"coordinates":[3.6722159386,50.8670921326],"type":"Point"}
}