{
  "type": "Feature",
  "properties": {
    "iso:country":"BE",
    "sg:address":"Rue Louis De Brouck\u00e8re 39 Box 35",
    "sg:city":"Quaregnon",
    "sg:classifiers":[
        {
            "category":"Organizations",
            "subcategory":"Community Association",
            "type":"Services"
        }
    ],
    "sg:phone":"+32 65 77 91 05",
    "sg:postcode":"7390",
    "sg:province":"Hainaut",
    "sg:tags":[
        "cultural"
    ],
    "wof:name":"Maison Des Jeunes Mjt",
    "wof:placetype":"venue"
},
  "geometry": {"coordinates":[3.8644559383,50.4340667725],"type":"Point"}
}