{
  "type": "Feature",
  "properties": {
    "iso:country":"BE",
    "sg:address":"Schaffelkantstraat 33",
    "sg:city":"Herent",
    "sg:orig_category":"Woningbouw",
    "sg:phone":"+32 16 20 23 53",
    "sg:postcode":"3020",
    "sg:province":"Vlaams-Brabant",
    "wof:name":"Vandermeeren",
    "wof:placetype":"venue"
},
  "geometry": {"coordinates":[4.6780228615,50.8993453979],"type":"Point"}
}