{
  "type": "Feature",
  "properties": {
    "iso:country":"BE",
    "sg:address":"Ertbuerhoek 7",
    "sg:city":"Lochristi (beervelde)",
    "sg:classifiers":[
        {
            "category":"Retail",
            "subcategory":"Repair Shop",
            "type":"Services"
        }
    ],
    "sg:phone":"+32 9 355 27 85",
    "sg:postcode":"9080",
    "sg:province":"Oost-Vlaanderen",
    "wof:name":"De Jaeger G",
    "wof:placetype":"venue"
},
  "geometry": {"coordinates":[3.8605349064,51.0695343018],"type":"Point"}
}