{
  "type": "Feature",
  "properties": {
    "addr:full":"Place D\u00b4armes 7 Philippeville Namur 5600",
    "addr:housenumber":"7",
    "addr:postcode":"5600",
    "addr:street":"Place D\u00b4Armes",
    "iso:country":"BE",
    "sg:address":"Place D\u00b4armes 7",
    "sg:city":"Philippeville",
    "sg:classifiers":[
        {
            "category":"Fast Food",
            "type":"Food & Drink"
        }
    ],
    "sg:phone":"+32 71 66 87 00",
    "sg:postcode":"5600",
    "sg:province":"Namur",
    "sg:tags":[
        "meeneem",
        "restaurant"
    ],
    "wof:name":"Pizza La Renaissance",
    "wof:placetype":"venue"
},
  "geometry": {"coordinates":[4.5438718796,50.1965293884],"type":"Point"}
}