{
  "type": "Feature",
  "properties": {
    "addr:full":"Westlaan 358 Roeselare West-Vlaanderen 8800",
    "addr:housenumber":"358",
    "addr:postcode":"8800",
    "addr:street":"Westlaan",
    "iso:country":"BE",
    "sg:address":"Westlaan 358",
    "sg:city":"Roeselare",
    "sg:classifiers":[
        {
            "category":"Professional",
            "subcategory":"Lawyer & Legal Services",
            "type":"Services"
        }
    ],
    "sg:phone":"+32 51 25 28 85",
    "sg:postcode":"8800",
    "sg:province":"West-Vlaanderen",
    "wof:name":"Coppens Alain",
    "wof:placetype":"venue"
},
  "geometry": {"coordinates":[3.112308979,50.949962616],"type":"Point"}
}