{
  "type": "Feature",
  "properties": {
    "iso:country":"BE",
    "sg:address":"Rue D'h\u00c9rinnes 24",
    "sg:city":"Edingen/enghien",
    "sg:orig_category":"Blanchisseries and teintureries",
    "sg:phone":"+32 2 395 32 40",
    "sg:postcode":"7850",
    "sg:province":"Hainaut",
    "wof:name":"P. Decuyper",
    "wof:placetype":"venue"
},
  "geometry": {"coordinates":[4.038795948,50.6941833496],"type":"Point"}
}