{
  "type": "Feature",
  "properties": {
    "iso:country":"BE",
    "sg:address":"Landbouwerstraat 12",
    "sg:city":"Moeskroen/mouscron",
    "sg:orig_category":"Boekenuitgeverijen",
    "sg:phone":"+32 56 34 70 31",
    "sg:postcode":"7700",
    "sg:province":"Hainaut",
    "wof:name":"Cathy De Keukeleire",
    "wof:placetype":"venue"
},
  "geometry": {"coordinates":[3.2323200703,50.7400932312],"type":"Point"}
}