{
  "type": "Feature",
  "properties": {
    "addr:full":"Rue Du Relais Sacr\u00c9 10 Koekelberg/koekelberg Bruxelles-Capitale 1081",
    "addr:housenumber":"10",
    "addr:postcode":"1081",
    "addr:street":"Rue Du Relais Sacre\u0301",
    "iso:country":"BE",
    "sg:address":"Rue Du Relais Sacr\u00c9 10",
    "sg:city":"Koekelberg/koekelberg",
    "sg:orig_category":"Blanchisseries and teintureries",
    "sg:phone":"+32 2 414 13 08",
    "sg:postcode":"1081",
    "sg:province":"Bruxelles-Capitale",
    "wof:name":"Nettoyage \u00c0 Sec Lessivit",
    "wof:placetype":"venue"
},
  "geometry": {"coordinates":[4.3330731392,50.8606567383],"type":"Point"}
}