{
  "type": "Feature",
  "properties": {
    "iso:country":"BE",
    "sg:address":"Vis\u00c9laan 6",
    "sg:city":"Watermaal-bosvoorde/watermael-boitsfort",
    "sg:orig_category":"Installatie van houten of kunststof schrijnwerk",
    "sg:phone":"+32 2 675 11 69",
    "sg:postcode":"1170",
    "sg:province":"Bruxelles-Capitale",
    "wof:name":"Olivier Van Gijsegem",
    "wof:placetype":"venue"
},
  "geometry": {"coordinates":[4.3983597755,50.8097915649],"type":"Point"}
}