{
  "type": "Feature",
  "properties": {
    "addr:full":"Route De Fosses 56 Presles Hainaut 6250",
    "addr:housenumber":"56",
    "addr:postcode":"6250",
    "addr:street":"Route De Fosses;Hainaut",
    "iso:country":"BE",
    "sg:address":"Route De Fosses 56",
    "sg:city":"Presles",
    "sg:orig_category":"Sprockets",
    "sg:phone":"+32 71 39 72 55",
    "sg:postcode":"6250",
    "sg:province":"Hainaut",
    "wof:name":"Kit Cross S.p.r.l.",
    "wof:placetype":"venue"
},
  "geometry": {"coordinates":[4.5822119713,50.381980896],"type":"Point"}
}