{
  "type": "Feature",
  "properties": {
    "addr:full":"Heidsiebaan 22 Malle Antwerpen 2390",
    "addr:housenumber":"22",
    "addr:postcode":"2390",
    "addr:street":"Heidsiebaan",
    "iso:country":"BE",
    "sg:address":"Heidsiebaan 22",
    "sg:city":"Malle",
    "sg:orig_category":"Groententeelt",
    "sg:phone":"+32 3 312 46 31",
    "sg:postcode":"2390",
    "sg:province":"Antwerpen",
    "wof:name":"Godfried Bervoets",
    "wof:placetype":"venue"
},
  "geometry": {"coordinates":[4.6728758812,51.3088111877],"type":"Point"}
}