{
  "type": "Feature",
  "properties": {
    "iso:country":"BE",
    "sg:address":"Spoorwegstraat 2",
    "sg:city":"Aarschot",
    "sg:classifiers":[
        {
            "category":"Home & Garden",
            "subcategory":"Home Furnishings",
            "type":"Retail Goods"
        }
    ],
    "sg:phone":"+32 16 56 32 84",
    "sg:postcode":"3200",
    "sg:province":"Vlaams-Brabant",
    "sg:tags":[
        "-",
        "bed",
        "mattress"
    ],
    "wof:name":"Beets-patteet",
    "wof:placetype":"venue"
},
  "geometry": {"coordinates":[4.8276629448,50.9899406433],"type":"Point"}
}