{
  "type": "Feature",
  "properties": {
    "addr:full":"Rue Au Vin 68 Renaix Oost-Vlaanderen 9600",
    "addr:housenumber":"68",
    "addr:postcode":"9600",
    "addr:street":"Rue Au Vin",
    "iso:country":"BE",
    "sg:address":"Rue Au Vin 68",
    "sg:city":"Renaix",
    "sg:classifiers":[
        {
            "category":"Bakery",
            "type":"Food & Drink"
        }
    ],
    "sg:phone":"+32 55 21 26 09",
    "sg:postcode":"9600",
    "sg:province":"Oost-Vlaanderen",
    "sg:tags":[
        "confectioner",
        "baker"
    ],
    "wof:name":"Drossens J",
    "wof:placetype":"venue"
},
  "geometry": {"coordinates":[3.5967619419,50.7498283386],"type":"Point"}
}