{
  "type": "Feature",
  "properties": {
    "iso:country":"BE",
    "sg:address":"Rue Du Lombard 9b1",
    "sg:city":"Brussel/bruxelles",
    "sg:orig_category":"Timbres, monnaies and troph\u00e9es",
    "sg:phone":"+32 2 514 52 92",
    "sg:postcode":"1000",
    "sg:province":"Bruxelles-Capitale",
    "wof:name":"Huis Campo-rodan",
    "wof:placetype":"venue"
},
  "geometry": {"coordinates":[4.3491292,50.8461112976],"type":"Point"}
}