{
  "type": "Feature",
  "properties": {
    "addr:full":"Marktplatz 9 Eupen Li\u00e8ge 4700",
    "addr:housenumber":"9",
    "addr:postcode":"4700",
    "addr:street":"Marktplatz",
    "iso:country":"BE",
    "sg:address":"Marktplatz 9",
    "sg:city":"Eupen",
    "sg:classifiers":[
        {
            "category":"Home & Garden",
            "subcategory":"Carpets & Floor Coverings",
            "type":"Retail Goods"
        }
    ],
    "sg:phone":"+32 87 74 00 07",
    "sg:postcode":"4700",
    "sg:province":"Li\u00e8ge",
    "sg:tags":[
        "-",
        "rug"
    ],
    "wof:name":"Ispahan Sprlu",
    "wof:placetype":"venue"
},
  "geometry": {"coordinates":[6.0316548347,50.6303977966],"type":"Point"}
}