{
  "type": "Feature",
  "properties": {
    "addr:full":"All\u00c9e Des Fauvettes 10 Ans Li\u00e8ge 4432",
    "addr:housenumber":"10",
    "addr:postcode":"4432",
    "addr:street":"Alle\u0301E Des Fauvettes",
    "iso:country":"BE",
    "sg:address":"All\u00c9e Des Fauvettes 10",
    "sg:city":"Ans",
    "sg:orig_category":"Huisdieren and benodigdheden",
    "sg:phone":"+32 4 246 17 19",
    "sg:postcode":"4432",
    "sg:province":"Li\u00e8ge",
    "wof:name":"Chatterie Al Trappe",
    "wof:placetype":"venue"
},
  "geometry": {"coordinates":[5.498000145,50.6807098389],"type":"Point"}
}