{
  "type": "Feature",
  "properties": {
    "iso:country":"BE",
    "sg:address":"Rue Oborne 15",
    "sg:city":"Bassenge",
    "sg:orig_category":"Begrafeniswezen Installatie van houten of kunststof schrijnwerk",
    "sg:phone":"+32 4 286 18 72",
    "sg:postcode":"4690",
    "sg:province":"Li\u00e8ge",
    "wof:name":"Maison Malpas",
    "wof:placetype":"venue"
},
  "geometry": {"coordinates":[5.5359749794,50.7535324097],"type":"Point"}
}