{
  "type": "Feature",
  "properties": {
    "addr:full":"Rue Du Sablon 205 Bastogne Luxembourg 6600",
    "addr:housenumber":"205",
    "addr:postcode":"6600",
    "addr:street":"Rue Du Sablon",
    "iso:country":"BE",
    "sg:address":"Rue Du Sablon 205",
    "sg:city":"Bastogne",
    "sg:classifiers":[
        {
            "category":"Shopping",
            "subcategory":"Music",
            "type":"Retail Goods"
        }
    ],
    "sg:phone":"+32 61 21 41 61",
    "sg:postcode":"6600",
    "sg:province":"Luxembourg",
    "sg:tags":[
        "-",
        "cd's",
        "recorded",
        "cassette"
    ],
    "wof:name":"Art & Music",
    "wof:placetype":"venue"
},
  "geometry": {"coordinates":[5.7207589149,50.0049591064],"type":"Point"}
}