{
  "type": "Feature",
  "properties": {
    "addr:full":"Rue D'opprebais 79 Perwez (mal\u00e8ves-sainte-marie-wastines) Brabant Wallon 1360",
    "addr:housenumber":"79",
    "addr:postcode":"1360",
    "addr:street":"Rue D'Opprebais;Wallon",
    "iso:country":"BE",
    "sg:address":"Rue D'opprebais 79",
    "sg:city":"Perwez (mal\u00e8ves-sainte-marie-wastines)",
    "sg:classifiers":[
        {
            "category":"Farming",
            "subcategory":"Farm & Veterinary Services",
            "type":"Manufacturing & Wholesale Goods"
        }
    ],
    "sg:phone":"+32 10 88 83 88",
    "sg:postcode":"1360",
    "sg:province":"Brabant Wallon",
    "sg:tags":[
        "agricultural",
        "contractor"
    ],
    "wof:name":"Pi\u00e9rard R",
    "wof:placetype":"venue"
},
  "geometry": {"coordinates":[4.7919540405,50.6645317078],"type":"Point"}
}