{
  "type": "Feature",
  "properties": {
    "addr:full":"Rue Albert Ier 84 Hannut Li\u00e8ge 4280",
    "addr:housenumber":"84",
    "addr:postcode":"4280",
    "addr:street":"Rue Albert Ier",
    "iso:country":"BE",
    "sg:address":"Rue Albert Ier 84",
    "sg:city":"Hannut",
    "sg:orig_category":"Overheidsdiensten",
    "sg:phone":"+32 19 51 12 01",
    "sg:postcode":"4280",
    "sg:province":"Li\u00e8ge",
    "wof:name":"Admin. Contrib. Directes",
    "wof:placetype":"venue"
},
  "geometry": {"coordinates":[5.0823922157,50.6703491211],"type":"Point"}
}