{
  "type": "Feature",
  "properties": {
    "addr:full":"Malibranstraat 22 Elsene/ixelles Bruxelles-Capitale 1050",
    "addr:housenumber":"22",
    "addr:postcode":"1050",
    "addr:street":"Malibranstraat",
    "iso:country":"BE",
    "sg:address":"Malibranstraat 22",
    "sg:city":"Elsene/ixelles",
    "sg:classifiers":[
        {
            "category":"Restaurant",
            "type":"Food & Drink"
        }
    ],
    "sg:phone":"+32 2 647 07 72",
    "sg:postcode":"1050",
    "sg:province":"Bruxelles-Capitale",
    "wof:name":"Zorba",
    "wof:placetype":"venue"
},
  "geometry": {"coordinates":[4.372428894,50.8293800354],"type":"Point"}
}