{
  "type": "Feature",
  "properties": {
    "addr:full":"Kerkstraat 52 Maasmechelen (opgrimbie) Limburg 3630",
    "addr:housenumber":"52",
    "addr:postcode":"3630",
    "addr:street":"Kerkstraat",
    "iso:country":"BE",
    "sg:address":"Kerkstraat 52",
    "sg:city":"Maasmechelen (opgrimbie)",
    "sg:classifiers":[
        {
            "category":"Wholesale",
            "subcategory":"Meat",
            "type":"Manufacturing & Wholesale Goods"
        }
    ],
    "sg:phone":"+32 89 76 00 33",
    "sg:postcode":"3630",
    "sg:province":"Limburg",
    "sg:tags":[
        "whol",
        "-"
    ],
    "wof:name":"Pierre Marx Nv",
    "wof:placetype":"venue"
},
  "geometry": {"coordinates":[5.6839728355,50.9390068054],"type":"Point"}
}