{
  "type": "Feature",
  "properties": {
    "iso:country":"BE",
    "sg:address":"Aststraat 250",
    "sg:city":"Tienen (goetsenhoven)",
    "sg:classifiers":[
        {
            "category":"Autos & Motor Vehicles",
            "subcategory":"Automobile Sales",
            "type":"Retail Goods"
        }
    ],
    "sg:phone":"+32 16 82 37 80",
    "sg:postcode":"3300",
    "sg:province":"Vlaams-Brabant",
    "sg:tags":[
        "car",
        "used",
        "-"
    ],
    "wof:name":"Best Budget Car",
    "wof:placetype":"venue"
},
  "geometry": {"coordinates":[4.930077076,50.8096694946],"type":"Point"}
}