{
  "type": "Feature",
  "properties": {
    "addr:full":"Geeneindestraat 72 Lummen (meldert) Limburg 3560",
    "addr:housenumber":"72",
    "addr:postcode":"3560",
    "addr:street":"Geeneindestraat",
    "iso:country":"BE",
    "sg:address":"Geeneindestraat 72",
    "sg:city":"Lummen (meldert)",
    "sg:classifiers":[
        {
            "category":"Personal",
            "subcategory":"Beauty Salon",
            "type":"Services"
        }
    ],
    "sg:phone":"+32 13 31 24 38",
    "sg:postcode":"3560",
    "sg:province":"Limburg",
    "sg:tags":[
        "lady",
        "-",
        "hairdressing"
    ],
    "wof:name":"Wim Haarstylist",
    "wof:placetype":"venue"
},
  "geometry": {"coordinates":[5.1928048134,50.9866790771],"type":"Point"}
}