{
  "type": "Feature",
  "properties": {
    "iso:country":"BE",
    "sg:address":"Rue De Sart-dames-avelines 73",
    "sg:city":"Les Bons Villers",
    "sg:orig_category":"Woningbouw",
    "sg:phone":"+32 71 85 32 04",
    "sg:postcode":"6210",
    "sg:province":"Hainaut",
    "wof:name":"Dominique Danneels",
    "wof:placetype":"venue"
},
  "geometry": {"coordinates":[4.4511561394,50.5378227234],"type":"Point"}
}