{
  "type": "Feature",
  "properties": {
    "iso:country":"BE",
    "sg:address":"Industrieterrein Vostert 1109",
    "sg:city":"Bree",
    "sg:classifiers":[
        {
            "category":"Manufacturing",
            "subcategory":"Glass & Minerals",
            "type":"Manufacturing & Wholesale Goods"
        }
    ],
    "sg:phone":"+32 89 46 73 33",
    "sg:postcode":"3960",
    "sg:province":"Limburg",
    "sg:tags":[
        "automobile",
        "-"
    ],
    "wof:name":"Autoglass J & M",
    "wof:placetype":"venue"
},
  "geometry": {"coordinates":[5.5890097618,51.1217918396],"type":"Point"}
}