{
  "type": "Feature",
  "properties": {
    "addr:full":"Engelbr\u00fccke 233 Amel Li\u00e8ge 4770",
    "addr:housenumber":"233",
    "addr:postcode":"4770",
    "iso:country":"BE",
    "sg:address":"Engelbr\u00fccke 233",
    "sg:city":"Amel",
    "sg:classifiers":[
        {
            "category":"Professional",
            "subcategory":"Testing Lab",
            "type":"Services"
        }
    ],
    "sg:phone":"+32 80 34 00 43",
    "sg:postcode":"4770",
    "sg:province":"Li\u00e8ge",
    "sg:tags":[
        "chemist"
    ],
    "wof:name":"Hardy Sa",
    "wof:placetype":"venue"
},
  "geometry": {"coordinates":[6.1712031364,50.3489723206],"type":"Point"}
}