{
  "type": "Feature",
  "properties": {
    "iso:country":"BE",
    "sg:address":"Spoormakersstraat 12",
    "sg:city":"Brussel/bruxelles",
    "sg:orig_category":"Speelgoed",
    "sg:phone":"+32 2 512 47 59",
    "sg:postcode":"1000",
    "sg:province":"Bruxelles-Capitale",
    "wof:name":"La Courte Echelle",
    "wof:placetype":"venue"
},
  "geometry": {"coordinates":[4.3543329239,50.8459777832],"type":"Point"}
}