{
  "type": "Feature",
  "properties": {
    "addr:full":"Dorpsstraat 8 Laarne Oost-Vlaanderen 9270",
    "addr:housenumber":"8",
    "addr:postcode":"9270",
    "addr:street":"Dorpsstraat",
    "iso:country":"BE",
    "sg:address":"Dorpsstraat 8",
    "sg:city":"Laarne",
    "sg:classifiers":[
        {
            "category":"Bars & Pubs",
            "type":"Food & Drink"
        }
    ],
    "sg:phone":"+32 9 369 18 08",
    "sg:postcode":"9270",
    "sg:province":"Oost-Vlaanderen",
    "wof:name":"St-hubert",
    "wof:placetype":"venue"
},
  "geometry": {"coordinates":[3.8485488892,51.0294914246],"type":"Point"}
}