{
  "type": "Feature",
  "properties": {
    "iso:country":"BE",
    "sg:address":"Riemsterweg 302",
    "sg:city":"Bilzen",
    "sg:classifiers":[
        {
            "category":"Professional",
            "subcategory":"Testing Lab",
            "type":"Services"
        }
    ],
    "sg:phone":"+32 89 41 27 75",
    "sg:postcode":"3740",
    "sg:province":"Limburg",
    "sg:tags":[
        "chemist"
    ],
    "wof:name":"Vangronsveld H",
    "wof:placetype":"venue"
},
  "geometry": {"coordinates":[5.5292901993,50.8601989746],"type":"Point"}
}