{
  "type": "Feature",
  "properties": {
    "addr:full":"J. Moensstraat 52 Machelen Vlaams-Brabant 1830",
    "addr:housenumber":"52",
    "addr:postcode":"1830",
    "addr:street":"J. Moensstraat",
    "iso:country":"BE",
    "sg:address":"J. Moensstraat 52",
    "sg:city":"Machelen",
    "sg:classifiers":[
        {
            "category":"Autos & Motor Vehicles",
            "subcategory":"Automobile Sales",
            "type":"Retail Goods"
        }
    ],
    "sg:phone":"+32 2 253 06 78",
    "sg:postcode":"1830",
    "sg:province":"Vlaams-Brabant",
    "sg:tags":[
        "car",
        "used",
        "-"
    ],
    "wof:name":"Fernandez Diaz",
    "wof:placetype":"venue"
},
  "geometry": {"coordinates":[4.4403920174,50.9179458618],"type":"Point"}
}