{
  "type": "Feature",
  "properties": {
    "iso:country":"BE",
    "sg:address":"Rue Du Foyer Schaerbeekois 23",
    "sg:city":"Bruxelles (schaerbeek)",
    "sg:classifiers":[
        {
            "category":"Parking",
            "subcategory":"Bicycle",
            "type":"Transportation"
        }
    ],
    "sg:phone":"+32 2 216 33 97",
    "sg:postcode":"1030",
    "sg:province":"Bruxelles-Capitale",
    "sg:tags":[
        "chiropodist"
    ],
    "wof:name":"Brichart R",
    "wof:placetype":"venue"
},
  "geometry": {"coordinates":[4.3864898682,50.8713989258],"type":"Point"}
}