{
  "type": "Feature",
  "properties": {
    "addr:full":"Rue L\u00c9opold I 84 Brussel/bruxelles Bruxelles-Capitale 1020",
    "addr:housenumber":"84",
    "addr:postcode":"1020",
    "addr:street":"Rue Le\u0301Opold I;/",
    "iso:country":"BE",
    "sg:address":"Rue L\u00c9opold I 84",
    "sg:city":"Brussel/bruxelles",
    "sg:orig_category":"Entretien and r\u00e9parations de voitures",
    "sg:phone":"+32 2 428 05 70",
    "sg:postcode":"1020",
    "sg:province":"Bruxelles-Capitale",
    "wof:name":"Auto-goossens",
    "wof:placetype":"venue"
},
  "geometry": {"coordinates":[4.3511152267,50.8785476685],"type":"Point"}
}