{
  "type": "Feature",
  "properties": {
    "iso:country":"BE",
    "sg:address":"Rijschoolstraat 48",
    "sg:city":"Sint-truiden",
    "sg:orig_category":"Advocaten and juridische adviseurs",
    "sg:phone":"+32 11 68 05 98",
    "sg:postcode":"3800",
    "sg:province":"Limburg",
    "wof:name":"Heidi Bormans",
    "wof:placetype":"venue"
},
  "geometry": {"coordinates":[5.1810112,50.8173446655],"type":"Point"}
}