{
  "type": "Feature",
  "properties": {
    "iso:country":"BE",
    "sg:address":"Berendrechtstraat 83",
    "sg:city":"Antwerpen",
    "sg:orig_category":"M\u00e9decins and sp\u00e9cialistes",
    "sg:phone":"+32 3 216 03 27",
    "sg:postcode":"2020",
    "sg:province":"Antwerpen",
    "wof:name":"B. Ledegen",
    "wof:placetype":"venue"
},
  "geometry": {"coordinates":[4.3853268623,51.1862831116],"type":"Point"}
}