{
  "type": "Feature",
  "properties": {
    "addr:full":"Graaf D'ursellaan 47 Knokke-heist (heist-aan-zee) West-Vlaanderen 8301",
    "addr:housenumber":"47",
    "addr:postcode":"8301",
    "addr:street":"Graaf D'Ursellaan",
    "iso:country":"BE",
    "sg:address":"Graaf D'ursellaan 47",
    "sg:city":"Knokke-heist (heist-aan-zee)",
    "sg:classifiers":[
        {
            "category":"Real Estate",
            "subcategory":"Surveying",
            "type":"Services"
        }
    ],
    "sg:phone":"+32 50 51 51 72",
    "sg:postcode":"8301",
    "sg:province":"West-Vlaanderen",
    "sg:tags":[
        "surveyor",
        "land"
    ],
    "wof:name":"Vandromme H",
    "wof:placetype":"venue"
},
  "geometry": {"coordinates":[3.2455050945,51.3404159546],"type":"Point"}
}