{
  "type": "Feature",
  "properties": {
    "addr:full":"Warrimont 174b Herve Li\u00e8ge 4654",
    "addr:housenumber":"174b",
    "addr:postcode":"4654",
    "addr:street":"Warrimont",
    "iso:country":"BE",
    "sg:address":"Warrimont 174b",
    "sg:city":"Herve",
    "sg:orig_category":"Transports routiers de marchandises",
    "sg:phone":"+32 87 67 58 12",
    "sg:postcode":"4654",
    "sg:province":"Li\u00e8ge",
    "wof:name":"Rene Simons",
    "wof:placetype":"venue"
},
  "geometry": {"coordinates":[5.8042421341,50.6694908142],"type":"Point"}
}