{
  "type": "Feature",
  "properties": {
    "addr:full":"Brusselsesteenweg 158b3 Mechelen Antwerpen 2800",
    "addr:housenumber":"158b3",
    "addr:postcode":"2800",
    "addr:street":"Brusselsesteenweg",
    "iso:country":"BE",
    "sg:address":"Brusselsesteenweg 158b3",
    "sg:city":"Mechelen",
    "sg:classifiers":[
        {
            "category":"Wholesale",
            "subcategory":"Sporting Goods",
            "type":"Manufacturing & Wholesale Goods"
        }
    ],
    "sg:phone":"+32 15 43 03 05",
    "sg:postcode":"2800",
    "sg:province":"Antwerpen",
    "sg:tags":[
        "sport-",
        "kampeermateriaal"
    ],
    "wof:name":"Elite",
    "wof:placetype":"venue"
},
  "geometry": {"coordinates":[4.472548008,51.0163269043],"type":"Point"}
}