{
  "type": "Feature",
  "properties": {
    "addr:full":"Chauss\u00c9e De Bruxelles 1 Casteau Hainaut 7061",
    "addr:housenumber":"1",
    "addr:postcode":"7061",
    "addr:street":"Chausse\u0301E De Bruxelles;Hainaut",
    "iso:country":"BE",
    "sg:address":"Chauss\u00c9e De Bruxelles 1",
    "sg:city":"Casteau",
    "sg:orig_category":"H\u00f4tels. Restaurants. Salles de conf\u00e9rences and de r\u00e9ceptions",
    "sg:phone":"+32 65 73 15 46",
    "sg:postcode":"7061",
    "sg:province":"Hainaut",
    "wof:name":"Le Medicis",
    "wof:placetype":"venue"
},
  "geometry": {"coordinates":[3.9983870983,50.5050849915],"type":"Point"}
}