{
  "type": "Feature",
  "properties": {
    "addr:full":"Andr\u00e9 Dumontlaan 48 Genk (waterschei) Limburg 3600",
    "addr:housenumber":"48",
    "addr:postcode":"3600",
    "addr:street":"Dumontlaan",
    "iso:country":"BE",
    "sg:address":"Andr\u00e9 Dumontlaan 48",
    "sg:city":"Genk (waterschei)",
    "sg:classifiers":[
        {
            "category":"Professional",
            "subcategory":"Testing Lab",
            "type":"Services"
        }
    ],
    "sg:phone":"+32 89 38 04 28",
    "sg:postcode":"3600",
    "sg:province":"Limburg",
    "sg:tags":[
        "chemist"
    ],
    "wof:name":"Quintiens E",
    "wof:placetype":"venue"
},
  "geometry": {"coordinates":[5.5315980911,50.994808197],"type":"Point"}
}