{
  "type": "Feature",
  "properties": {
    "addr:full":"Heiveld 17 Opwijk Vlaams-Brabant 1745",
    "addr:housenumber":"17",
    "addr:postcode":"1745",
    "addr:street":"Heiveld",
    "iso:country":"BE",
    "sg:address":"Heiveld 17",
    "sg:city":"Opwijk",
    "sg:orig_category":"Drukkerijen and copyshops",
    "sg:phone":"+32 52 36 50 07",
    "sg:postcode":"1745",
    "sg:province":"Vlaams-Brabant",
    "wof:name":"Grafisch Centrum",
    "wof:placetype":"venue"
},
  "geometry": {"coordinates":[4.1857690811,50.9709892273],"type":"Point"}
}