{
  "type": "Feature",
  "properties": {
    "iso:country":"BE",
    "sg:address":"De Bosschaertstraat 306",
    "sg:city":"Antwerpen",
    "sg:classifiers":[
        {
            "category":"Personal",
            "subcategory":"Shoe Repair & Shine",
            "type":"Services"
        }
    ],
    "sg:phone":"+32 3 238 61 91",
    "sg:postcode":"2020",
    "sg:province":"Antwerpen",
    "sg:tags":[
        "shoemaker"
    ],
    "wof:name":"Swenters R",
    "wof:placetype":"venue"
},
  "geometry": {"coordinates":[4.3868279457,51.1848678589],"type":"Point"}
}