{
  "type": "Feature",
  "properties": {
    "iso:country":"BE",
    "sg:address":"Kattenbos 52",
    "sg:city":"Lennik",
    "sg:orig_category":"Fruitteelt",
    "sg:phone":"+32 2 532 52 27",
    "sg:postcode":"1750",
    "sg:province":"Vlaams-Brabant",
    "wof:name":"Victor Mattens",
    "wof:placetype":"venue"
},
  "geometry": {"coordinates":[4.1520900726,50.8307418823],"type":"Point"}
}