{
  "type": "Feature",
  "properties": {
    "iso:country":"BE",
    "sg:address":"Waversesteenweg 4",
    "sg:city":"Putte",
    "sg:classifiers":[
        {
            "category":"Home & Garden",
            "subcategory":"Building Materials",
            "type":"Retail Goods"
        }
    ],
    "sg:phone":"+32 15 75 24 30",
    "sg:postcode":"2580",
    "sg:province":"Antwerpen",
    "sg:tags":[
        "article",
        "-",
        "do-it-yourself"
    ],
    "wof:name":"Doe-het-zelf Van Wunsel Bvba",
    "wof:placetype":"venue"
},
  "geometry": {"coordinates":[4.6271800995,51.0591812134],"type":"Point"}
}