{
  "type": "Feature",
  "properties": {
    "addr:full":"Baron Van Caloenlaan 2 De Haan (vlissegem) West-Vlaanderen 8421",
    "addr:housenumber":"2;8421",
    "addr:street":"Baron Van Caloenlaan",
    "iso:country":"BE",
    "sg:address":"Baron Van Caloenlaan 2",
    "sg:city":"De Haan (vlissegem)",
    "sg:classifiers":[
        {
            "category":"Retail",
            "subcategory":"Laundry & Dry Cleaning",
            "type":"Services"
        }
    ],
    "sg:phone":"+32 59 23 63 78",
    "sg:postcode":"8421",
    "sg:province":"West-Vlaanderen",
    "sg:tags":[
        "self",
        "-"
    ],
    "wof:name":"Witte Duve (de)",
    "wof:placetype":"venue"
},
  "geometry": {"coordinates":[3.0378770828,51.2712478638],"type":"Point"}
}