{
  "type": "Feature",
  "properties": {
    "addr:full":"Avenue G\u00e9ronhaies 10 Charleroi (marcinelle) Hainaut 6001",
    "addr:housenumber":"10",
    "addr:postcode":"6001",
    "addr:street":"Avenue Ge\u0301Ronhaies",
    "iso:country":"BE",
    "sg:address":"Avenue G\u00e9ronhaies 10",
    "sg:city":"Charleroi (marcinelle)",
    "sg:classifiers":[
        {
            "category":"Professional",
            "subcategory":"Art Services",
            "type":"Services"
        }
    ],
    "sg:phone":"+32 71 47 74 47",
    "sg:postcode":"6001",
    "sg:province":"Hainaut",
    "sg:tags":[
        "-",
        "painter",
        "artist"
    ],
    "wof:name":"Binsfeld N",
    "wof:placetype":"venue"
},
  "geometry": {"coordinates":[4.4283452034,50.3995628357],"type":"Point"}
}