{
  "type": "Feature",
  "properties": {
    "iso:country":"BE",
    "sg:address":"Sint-amanduslaan 3",
    "sg:city":"Beernem",
    "sg:classifiers":[
        {
            "category":"Building & Trades",
            "subcategory":"Construction",
            "type":"Services"
        }
    ],
    "sg:phone":"+32 50 78 85 93",
    "sg:postcode":"8730",
    "sg:province":"West-Vlaanderen",
    "sg:tags":[
        "glazier"
    ],
    "wof:name":"Cleeren J",
    "wof:placetype":"venue"
},
  "geometry": {"coordinates":[3.3256320953,51.1254501343],"type":"Point"}
}