{
  "type": "Feature",
  "properties": {
    "addr:full":"Zur Ochsenbaracke 8 Sankt Vith (recht) Li\u00e8ge 4780",
    "addr:housenumber":"8",
    "addr:postcode":"4780",
    "addr:street":"Zur Ochsenbaracke",
    "iso:country":"BE",
    "sg:address":"Zur Ochsenbaracke 8",
    "sg:city":"Sankt Vith (recht)",
    "sg:classifiers":[
        {
            "category":"Professional",
            "subcategory":"Computer Services",
            "type":"Services"
        }
    ],
    "sg:phone":"+32 80 57 02 58",
    "sg:postcode":"4780",
    "sg:province":"Li\u00e8ge",
    "sg:tags":[
        "repair",
        "processing",
        "-",
        "maintenance",
        "data"
    ],
    "wof:name":"Lenges-hensius G",
    "wof:placetype":"venue"
},
  "geometry": {"coordinates":[6.1256680489,50.2810821533],"type":"Point"}
}