{
  "type": "Feature",
  "properties": {
    "addr:full":"Rodendries 53b1 Waasmunster Oost-Vlaanderen 9250",
    "addr:housenumber":"53b1",
    "addr:postcode":"9250",
    "addr:street":"Rodendries",
    "iso:country":"BE",
    "sg:address":"Rodendries 53b1",
    "sg:city":"Waasmunster",
    "sg:orig_category":"Artiesten and kunstenaars",
    "sg:phone":"+32 52 47 90 97",
    "sg:postcode":"9250",
    "sg:province":"Oost-Vlaanderen",
    "wof:name":"Lieve Cornelis",
    "wof:placetype":"venue"
},
  "geometry": {"coordinates":[4.088449955,51.0955810547],"type":"Point"}
}