{
  "type": "Feature",
  "properties": {
    "addr:full":"Rue Try Al Vigne 30 Gembloux-sur-orneau (gembloux) Namur 5030",
    "addr:housenumber":"30",
    "addr:postcode":"5030",
    "addr:street":"Rue Try Al Vigne;Namur",
    "iso:country":"BE",
    "sg:address":"Rue Try Al Vigne 30",
    "sg:city":"Gembloux-sur-orneau (gembloux)",
    "sg:classifiers":[
        {
            "category":"Retail",
            "subcategory":"Event Space",
            "type":"Services"
        }
    ],
    "sg:phone":"+32 81 61 41 15",
    "sg:postcode":"5030",
    "sg:province":"Namur",
    "sg:tags":[
        "rental",
        "-",
        "hall"
    ],
    "wof:name":"Domaine De L'orneau (le)",
    "wof:placetype":"venue"
},
  "geometry": {"coordinates":[4.6979699135,50.5615348816],"type":"Point"}
}