{
  "type": "Feature",
  "properties": {
    "iso:country":"BE",
    "sg:address":"Rue De Gilly 185",
    "sg:city":"Charleroi (couillet)",
    "sg:classifiers":[
        {
            "category":"Health Services",
            "subcategory":"Dentist",
            "type":"Services"
        }
    ],
    "sg:phone":"+32 71 43 95 34",
    "sg:postcode":"6010",
    "sg:province":"Hainaut",
    "wof:name":"Leroy Johanne",
    "wof:placetype":"venue"
},
  "geometry": {"coordinates":[4.4701709747,50.3902778625],"type":"Point"}
}