{
  "type": "Feature",
  "properties": {
    "addr:full":"Rue Du Centre 32 Ciney Namur 5590",
    "addr:housenumber":"32",
    "addr:postcode":"5590",
    "addr:street":"Rue Du Centre",
    "iso:country":"BE",
    "sg:address":"Rue Du Centre 32",
    "sg:city":"Ciney",
    "sg:orig_category":"Banques and organismes de cr\u00e9dit",
    "sg:phone":"+32 83 21 31 71",
    "sg:postcode":"5590",
    "sg:province":"Namur",
    "wof:name":"Cr\u00c9dit \u00c0 L\u00b4industrie",
    "wof:placetype":"venue"
},
  "geometry": {"coordinates":[5.1006598473,50.2961502075],"type":"Point"}
}