{
  "type": "Feature",
  "properties": {
    "addr:full":"Chemin De L'epinois 61 Soignies Hainaut 7060",
    "addr:housenumber":"61",
    "addr:postcode":"7060",
    "addr:street":"Chemin De L'Epinois",
    "iso:country":"BE",
    "sg:address":"Chemin De L'epinois 61",
    "sg:city":"Soignies",
    "sg:classifiers":[
        {
            "category":"Education",
            "subcategory":"School",
            "type":"Public Place"
        }
    ],
    "sg:phone":"+32 67 34 04 31",
    "sg:postcode":"7060",
    "sg:province":"Hainaut",
    "sg:tags":[
        "primary"
    ],
    "wof:name":"Institut D'enseignement Special",
    "wof:placetype":"venue"
},
  "geometry": {"coordinates":[4.0635519028,50.5829544067],"type":"Point"}
}