{
  "type": "Feature",
  "properties": {
    "iso:country":"BE",
    "sg:address":"Place Des Combattants 12",
    "sg:city":"Couvin",
    "sg:orig_category":"Kruideniers Slagers",
    "sg:phone":"+32 60 34 53 45",
    "sg:postcode":"5660",
    "sg:province":"Namur",
    "wof:name":"Courtheoux",
    "wof:placetype":"venue"
},
  "geometry": {"coordinates":[4.4265642166,50.0358924866],"type":"Point"}
}