{
  "type": "Feature",
  "properties": {
    "addr:full":"Koninginnelaan 52b14 Oostende West-Vlaanderen 8400",
    "addr:housenumber":"52b14",
    "addr:postcode":"8400",
    "addr:street":"Koninginnelaan",
    "iso:country":"BE",
    "sg:address":"Koninginnelaan 52b14",
    "sg:city":"Oostende",
    "sg:orig_category":"Ordinateurs and \u00e9quipement informatique",
    "sg:phone":"+32 59 70 80 16",
    "sg:postcode":"8400",
    "sg:province":"West-Vlaanderen",
    "wof:name":"Tanguy Janssens",
    "wof:placetype":"venue"
},
  "geometry": {"coordinates":[2.9081990719,51.2249641418],"type":"Point"}
}