{
  "type": "Feature",
  "properties": {
    "addr:full":"Voisinage Renaut 7b1 Flemalle Li\u00e8ge 4400",
    "addr:housenumber":"7b1",
    "addr:postcode":"4400",
    "addr:street":"Renaut",
    "iso:country":"BE",
    "sg:address":"Voisinage Renaut 7b1",
    "sg:city":"Flemalle",
    "sg:orig_category":"Sportclubs Sportterreinen and installaties behalve sportcentra",
    "sg:phone":"+32 4 275 71 42",
    "sg:postcode":"4400",
    "sg:province":"Li\u00e8ge",
    "wof:name":"S.c. Li\u00c8ge-seraing",
    "wof:placetype":"venue"
},
  "geometry": {"coordinates":[5.4388899803,50.5987701416],"type":"Point"}
}