{
  "type": "Feature",
  "properties": {
    "iso:country":"BE",
    "sg:address":"Rue D'armenti\u00e8res 415a",
    "sg:city":"Comines-warneton (bizet)",
    "sg:classifiers":[
        {
            "category":"Bakery",
            "type":"Food & Drink"
        }
    ],
    "sg:phone":"+32 56 58 88 68",
    "sg:postcode":"7783",
    "sg:province":"Hainaut",
    "sg:tags":[
        "confectioner",
        "baker"
    ],
    "wof:name":"Patissier (au)",
    "wof:placetype":"venue"
},
  "geometry": {"coordinates":[2.8837659359,50.7062568665],"type":"Point"}
}