{
  "type": "Feature",
  "properties": {
    "addr:full":"Rue Saint-donat 26 Walcourt Namur 5650",
    "addr:housenumber":"26",
    "addr:postcode":"5650",
    "addr:street":"Rue Saint-Donat",
    "iso:country":"BE",
    "sg:address":"Rue Saint-donat 26",
    "sg:city":"Walcourt",
    "sg:orig_category":"Rusthuizen and serviceflats",
    "sg:phone":"+32 71 61 21 92",
    "sg:postcode":"5650",
    "sg:province":"Namur",
    "wof:name":"Home St-donat",
    "wof:placetype":"venue"
},
  "geometry": {"coordinates":[4.4567899704,50.2660217285],"type":"Point"}
}