{
  "type": "Feature",
  "properties": {
    "addr:full":"Tinnenpotstraat 1 Izegem West-Vlaanderen 8870",
    "addr:housenumber":"1",
    "addr:postcode":"8870",
    "addr:street":"Tinnenpotstraat",
    "iso:country":"BE",
    "sg:address":"Tinnenpotstraat 1",
    "sg:city":"Izegem",
    "sg:orig_category":"Eleveurs and marchands de porcs",
    "sg:phone":"+32 51 30 28 78",
    "sg:postcode":"8870",
    "sg:province":"West-Vlaanderen",
    "wof:name":"Marc Stove",
    "wof:placetype":"venue"
},
  "geometry": {"coordinates":[3.2106320858,50.9337501526],"type":"Point"}
}