{
  "type": "Feature",
  "properties": {
    "iso:country":"BE",
    "sg:address":"Lindenstraat 49",
    "sg:city":"Tessenderlo",
    "sg:orig_category":"Woningbouw",
    "sg:phone":"+32 13 33 49 21",
    "sg:postcode":"3980",
    "sg:province":"Limburg",
    "wof:name":"Awj Alimco",
    "wof:placetype":"venue"
},
  "geometry": {"coordinates":[5.0875849724,51.0672340393],"type":"Point"}
}