{
  "type": "Feature",
  "properties": {
    "addr:full":"Rue Emile Vandervelde 383 Beyne-heusay (bellaire) Li\u00e8ge 4610",
    "addr:housenumber":"383",
    "addr:postcode":"4610",
    "addr:street":"Rue Emile Vandervelde",
    "iso:country":"BE",
    "sg:address":"Rue Emile Vandervelde 383",
    "sg:city":"Beyne-heusay (bellaire)",
    "sg:classifiers":[
        {
            "category":"Real Estate",
            "subcategory":"Architect",
            "type":"Services"
        }
    ],
    "sg:phone":"+32 4 362 57 94",
    "sg:postcode":"4610",
    "sg:province":"Li\u00e8ge",
    "wof:name":"Baruffolo I",
    "wof:placetype":"venue"
},
  "geometry": {"coordinates":[5.666082859,50.6428642273],"type":"Point"}
}