{
  "type": "Feature",
  "properties": {
    "iso:country":"BE",
    "sg:address":"Orveiestraat 24",
    "sg:city":"Zwevegem (moen)",
    "sg:classifiers":[
        {
            "category":"Arts & Performance",
            "subcategory":"Music",
            "type":"Entertainment"
        }
    ],
    "sg:phone":"+32 56 75 72 25",
    "sg:postcode":"8552",
    "sg:tags":[
        "disc-jockeys"
    ],
    "wof:name":"Studio Pink Panter",
    "wof:placetype":"venue"
},
  "geometry": {"coordinates":[3.363008976,50.7954063416],"type":"Point"}
}