{
  "type": "Feature",
  "properties": {
    "addr:full":"Karel-pinxtln 11 Overpelt Limburg 3900",
    "addr:housenumber":"11",
    "addr:postcode":"3900",
    "addr:street":"Karel-Pinxtln",
    "iso:country":"BE",
    "sg:address":"Karel-pinxtln 11",
    "sg:city":"Overpelt",
    "sg:classifiers":[
        {
            "category":"Home & Garden",
            "subcategory":"Furniture",
            "type":"Retail Goods"
        }
    ],
    "sg:phone":"+32 11 64 32 59",
    "sg:postcode":"3900",
    "sg:province":"Limburg",
    "sg:tags":[
        "household",
        "wood"
    ],
    "wof:name":"Interior Design Collections Nv",
    "wof:placetype":"venue"
},
  "geometry": {"coordinates":[5.3728590012,51.2188796997],"type":"Point"}
}