{
  "type": "Feature",
  "properties": {
    "addr:full":"Rue Gr\u00e9goire N\u00e9lis 16b Jodoigne Brabant Wallon 1370",
    "addr:housenumber":"16b",
    "addr:postcode":"1370",
    "addr:street":"Rue Gre\u0301Goire Ne\u0301Lis",
    "iso:country":"BE",
    "sg:address":"Rue Gr\u00e9goire N\u00e9lis 16b",
    "sg:city":"Jodoigne",
    "sg:classifiers":[
        {
            "category":"Health Services",
            "subcategory":"Doctor",
            "type":"Services"
        }
    ],
    "sg:phone":"+32 10 81 46 76",
    "sg:postcode":"1370",
    "sg:province":"Brabant Wallon",
    "sg:tags":[
        "psychotherapist",
        "psychoanalyst"
    ],
    "wof:name":"Mariani P",
    "wof:placetype":"venue"
},
  "geometry": {"coordinates":[4.8682160378,50.723526001],"type":"Point"}
}