{
  "type": "Feature",
  "properties": {
    "iso:country":"BE",
    "sg:address":"Rue Montante 5",
    "sg:city":"Ciney",
    "sg:orig_category":"Installatie van houten of kunststof schrijnwerk",
    "sg:phone":"+32 83 68 84 39",
    "sg:postcode":"5590",
    "sg:province":"Namur",
    "wof:name":"D. Lissoir",
    "wof:placetype":"venue"
},
  "geometry": {"coordinates":[5.1022520065,50.297088623],"type":"Point"}
}