{
  "type": "Feature",
  "properties": {
    "iso:country":"BE",
    "sg:address":"Avenue Des Glycines 42",
    "sg:city":"Bruxelles (schaerbeek)",
    "sg:classifiers":[
        {
            "category":"Arts & Performance",
            "subcategory":"Arts Center",
            "type":"Entertainment"
        }
    ],
    "sg:phone":"+32 2 240 03 50",
    "sg:postcode":"1030",
    "sg:province":"Bruxelles-Capitale",
    "sg:tags":[
        "inspection",
        "automobile",
        "-",
        "examination"
    ],
    "wof:name":"Centrum Voor Technische Automobieltransport",
    "wof:placetype":"venue"
},
  "geometry": {"coordinates":[4.3894100189,50.8662109375],"type":"Point"}
}