{
  "type": "Feature",
  "properties": {
    "addr:full":"Kruishoutemsesteenweg 144 Zingem Oost-Vlaanderen 9750",
    "addr:housenumber":"144",
    "addr:postcode":"9750",
    "addr:street":"Kruishoutemsesteenweg;Oost-Vlaanderen",
    "iso:country":"BE",
    "sg:address":"Kruishoutemsesteenweg 144",
    "sg:city":"Zingem",
    "sg:orig_category":"Eleveurs de bovins",
    "sg:phone":"+32 9 384 23 54",
    "sg:postcode":"9750",
    "sg:province":"Oost-Vlaanderen",
    "wof:name":"Eric Van Huylenbrouck",
    "wof:placetype":"venue"
},
  "geometry": {"coordinates":[3.6381878853,50.9093513489],"type":"Point"}
}