{
  "type": "Feature",
  "properties": {
    "addr:full":"Chemin De Suargeon 1 La Bruyere Namur 5081",
    "addr:housenumber":"1",
    "addr:postcode":"5081",
    "addr:street":"Chemin De Suargeon;La Bruyere",
    "iso:country":"BE",
    "sg:address":"Chemin De Suargeon 1",
    "sg:city":"La Bruyere",
    "sg:orig_category":"Fruitteelt",
    "sg:phone":"+32 81 56 81 80",
    "sg:postcode":"5081",
    "sg:province":"Namur",
    "wof:name":"Yves Cornet D'elzius",
    "wof:placetype":"venue"
},
  "geometry": {"coordinates":[4.7665839195,50.5260314941],"type":"Point"}
}