{
  "type": "Feature",
  "properties": {
    "iso:country":"BE",
    "sg:address":"Berlaarbaan 41",
    "sg:city":"Putte",
    "sg:orig_category":"Producteurs de l\u00e9gumes",
    "sg:phone":"+32 15 75 71 66",
    "sg:postcode":"2580",
    "sg:province":"Antwerpen",
    "wof:name":"Freddy Verbeeck",
    "wof:placetype":"venue"
},
  "geometry": {"coordinates":[4.6543331146,51.0749931335],"type":"Point"}
}