{
  "type": "Feature",
  "properties": {
    "iso:country":"BE",
    "sg:address":"Wijnegembaan 41a",
    "sg:city":"Schoten",
    "sg:classifiers":[
        {
            "category":"Real Estate",
            "subcategory":"Developer",
            "type":"Services"
        }
    ],
    "sg:phone":"+32 3 685 56 96",
    "sg:postcode":"2900",
    "sg:province":"Antwerpen",
    "sg:tags":[
        "project"
    ],
    "wof:name":"K I Nv",
    "wof:placetype":"venue"
},
  "geometry": {"coordinates":[4.5020570755,51.2423248291],"type":"Point"}
}