{
  "type": "Feature",
  "properties": {
    "addr:full":"Place De L'etang 11bd Marche-en-famenne Luxembourg 6900",
    "addr:housenumber":"11bd",
    "addr:postcode":"6900",
    "addr:street":"Place De L'Etang",
    "iso:country":"BE",
    "sg:address":"Place De L'etang 11bd",
    "sg:city":"Marche-en-famenne",
    "sg:orig_category":"Belastingconsulenten Diverse juridische dienstverlening",
    "sg:phone":"+32 84 31 32 46",
    "sg:postcode":"6900",
    "sg:province":"Luxembourg",
    "wof:name":"Fiduc. Belgo-luxembourg.",
    "wof:placetype":"venue"
},
  "geometry": {"coordinates":[5.3430099487,50.2273483276],"type":"Point"}
}