{
  "type": "Feature",
  "properties": {
    "addr:full":"Groot Veerle 25 Brecht Antwerpen 2960",
    "addr:housenumber":"25",
    "addr:postcode":"2960",
    "addr:street":"Groot Veerle",
    "iso:country":"BE",
    "sg:address":"Groot Veerle 25",
    "sg:city":"Brecht",
    "sg:orig_category":"Huisdieren and benodigdheden",
    "sg:phone":"+32 3 313 91 09",
    "sg:postcode":"2960",
    "sg:province":"Antwerpen",
    "wof:name":"August Maes",
    "wof:placetype":"venue"
},
  "geometry": {"coordinates":[4.6754999161,51.3293037415],"type":"Point"}
}