{
  "type": "Feature",
  "properties": {
    "iso:country":"BE",
    "sg:address":"Vise Voie 1",
    "sg:city":"Li\u00c8ge",
    "sg:orig_category":"Boekhouders",
    "sg:postcode":"4000",
    "sg:province":"Li\u00e8ge",
    "wof:name":"Marc Neuville",
    "wof:placetype":"venue"
},
  "geometry": {"coordinates":[5.5622291565,50.6641082764],"type":"Point"}
}