{
  "type": "Feature",
  "properties": {
    "addr:full":"Place A. Nouille 9 Flobecq Hainaut 7880",
    "addr:housenumber":"9",
    "addr:postcode":"7880",
    "addr:street":"Place A. Nouille;Hainaut",
    "iso:country":"BE",
    "sg:address":"Place A. Nouille 9",
    "sg:city":"Flobecq",
    "sg:orig_category":"Scenery Stage-, film-, and television",
    "sg:phone":"+32 68 44 65 65",
    "sg:postcode":"7880",
    "sg:province":"Hainaut",
    "wof:name":"Sine Qua Non Sprl",
    "wof:placetype":"venue"
},
  "geometry": {"coordinates":[3.7400100231,50.7361412048],"type":"Point"}
}