{
  "type": "Feature",
  "properties": {
    "iso:country":"BE",
    "sg:address":"Leuvensesteenweg 62",
    "sg:city":"Tervuren",
    "sg:orig_category":"Fleurs and plantes",
    "sg:phone":"+32 2 768 18 68",
    "sg:postcode":"3080",
    "sg:province":"Vlaams-Brabant",
    "wof:name":"Hortus",
    "wof:placetype":"venue"
},
  "geometry": {"coordinates":[4.5259709358,50.834236145],"type":"Point"}
}