{
  "type": "Feature",
  "properties": {
    "iso:country":"BE",
    "sg:address":"Klosterstrasse 23",
    "sg:city":"Eupen",
    "sg:classifiers":[
        {
            "category":"Shopping",
            "subcategory":"Optician",
            "type":"Retail Goods"
        }
    ],
    "sg:phone":"+32 87 74 38 88",
    "sg:postcode":"4700",
    "sg:province":"Li\u00e8ge",
    "sg:tags":[
        "-"
    ],
    "wof:name":"Pankert C. Optique",
    "wof:placetype":"venue"
},
  "geometry": {"coordinates":[6.0310578346,50.6312599182],"type":"Point"}
}