{
  "type": "Feature",
  "properties": {
    "iso:country":"BE",
    "sg:address":"Heieinde 54",
    "sg:city":"Westerlo",
    "sg:orig_category":"M\u00e9decins and sp\u00e9cialistes",
    "sg:phone":"+32 14 23 40 27",
    "sg:postcode":"2260",
    "sg:province":"Antwerpen",
    "wof:name":"M. Van De Cruys",
    "wof:placetype":"venue"
},
  "geometry": {"coordinates":[4.9117879868,51.1339797974],"type":"Point"}
}