{
  "type": "Feature",
  "properties": {
    "addr:full":"Vlasgaardstraat 4 Assenede Oost-Vlaanderen 9968",
    "addr:housenumber":"4",
    "addr:postcode":"9968",
    "addr:street":"Vlasgaardstraat",
    "iso:country":"BE",
    "sg:address":"Vlasgaardstraat 4",
    "sg:city":"Assenede",
    "sg:orig_category":"Gespecialiseerde residenti\u00eble bouw",
    "sg:phone":"+32 9 373 91 35",
    "sg:postcode":"9968",
    "sg:province":"Oost-Vlaanderen",
    "wof:name":"Fa. De Graeve S. & Zn",
    "wof:placetype":"venue"
},
  "geometry": {"coordinates":[3.7045109272,51.1902999878],"type":"Point"}
}