{
  "type": "Feature",
  "properties": {
    "addr:full":"Place De La Monnaie 18 Brussel/bruxelles Bruxelles-Capitale 1000",
    "addr:housenumber":"18",
    "addr:postcode":"1000",
    "addr:street":"Place De La Monnaie;/",
    "iso:country":"BE",
    "sg:address":"Place De La Monnaie 18",
    "sg:city":"Brussel/bruxelles",
    "sg:classifiers":[
        {
            "category":"Shopping",
            "subcategory":"Clothing, Apparel, & Fashions",
            "type":"Retail Goods"
        }
    ],
    "sg:phone":"+32 2 218 62 50",
    "sg:postcode":"1000",
    "sg:province":"Bruxelles-Capitale",
    "sg:tags":[
        "lingerie",
        "sous-v\u00eatements"
    ],
    "wof:name":"Damart",
    "wof:placetype":"venue"
},
  "geometry": {"coordinates":[4.3537797928,50.8505401611],"type":"Point"}
}