{
  "type": "Feature",
  "properties": {
    "addr:full":"Rue Albert Ier 23 Mettet Namur 5640",
    "addr:housenumber":"23",
    "addr:postcode":"5640",
    "addr:street":"Rue Albert Ier",
    "iso:country":"BE",
    "sg:address":"Rue Albert Ier 23",
    "sg:city":"Mettet",
    "sg:orig_category":"Diverse meubelen Fab Meubelzaken, woning- and keukeninrichting",
    "sg:phone":"+32 71 72 70 99",
    "sg:postcode":"5640",
    "sg:province":"Namur",
    "wof:name":"Ebenisterie D'art Barbier",
    "wof:placetype":"venue"
},
  "geometry": {"coordinates":[4.6583971977,50.3222923279],"type":"Point"}
}