{
  "type": "Feature",
  "properties": {
    "addr:full":"Emiel Jacqueslaan 68 Moorslede West-Vlaanderen 8890",
    "addr:housenumber":"68",
    "addr:postcode":"8890",
    "addr:street":"Emiel Jacqueslaan",
    "iso:country":"BE",
    "sg:address":"Emiel Jacqueslaan 68",
    "sg:city":"Moorslede",
    "sg:classifiers":[
        {
            "category":"Communications",
            "type":"Services"
        }
    ],
    "sg:phone":"+32 51 77 27 06",
    "sg:postcode":"8890",
    "sg:province":"West-Vlaanderen",
    "sg:tags":[
        "translator"
    ],
    "wof:name":"Guzecka E",
    "wof:placetype":"venue"
},
  "geometry": {"coordinates":[3.0633730888,50.888217926],"type":"Point"}
}