{
  "type": "Feature",
  "properties": {
    "addr:full":"Rue Saint-joseph 14 Couvin Namur 5660",
    "addr:housenumber":"14",
    "addr:postcode":"5660",
    "addr:street":"Rue Saint-Joseph",
    "iso:country":"BE",
    "sg:address":"Rue Saint-joseph 14",
    "sg:city":"Couvin",
    "sg:orig_category":"Enseignement maternel and primaire",
    "sg:phone":"+32 60 31 19 81",
    "sg:postcode":"5660",
    "sg:province":"Namur",
    "wof:name":"Ecole Fondamentale Libre",
    "wof:placetype":"venue"
},
  "geometry": {"coordinates":[4.5015912056,50.0753669739],"type":"Point"}
}