{
  "type": "Feature",
  "properties": {
    "iso:country":"BE",
    "sg:address":"Markekerkstraat 51",
    "sg:city":"Kortrijk",
    "sg:orig_category":"Electrom\u00e9nager, t\u00e9l\u00e9visions and radios",
    "sg:phone":"+32 56 22 29 41",
    "sg:postcode":"8510",
    "sg:province":"West-Vlaanderen",
    "wof:name":"Dirk Lievens",
    "wof:placetype":"venue"
},
  "geometry": {"coordinates":[3.2310750484,50.8082695007],"type":"Point"}
}