{
  "type": "Feature",
  "properties": {
    "iso:country":"BE",
    "sg:address":"Chauss\u00c9e De Haecht 1830",
    "sg:city":"Brussel/bruxelles",
    "sg:orig_category":"Notaires",
    "sg:phone":"+32 2 705 42 81",
    "sg:postcode":"1130",
    "sg:province":"Bruxelles-Capitale",
    "wof:name":"Soinne G.",
    "wof:placetype":"venue"
},
  "geometry": {"coordinates":[4.4254589081,50.88904953],"type":"Point"}
}