{
  "type": "Feature",
  "properties": {
    "iso:country":"BE",
    "sg:address":"Cederlaan 15",
    "sg:city":"Zele",
    "sg:orig_category":"Slagers",
    "sg:phone":"+32 52 44 44 81",
    "sg:postcode":"9240",
    "sg:province":"Oost-Vlaanderen",
    "wof:name":"Jozef Van Der Slycken",
    "wof:placetype":"venue"
},
  "geometry": {"coordinates":[4.0307378769,51.0757255554],"type":"Point"}
}