{
  "type": "Feature",
  "properties": {
    "addr:full":"Rue De La Claudine 2 Lasne (maransart) Brabant Wallon 1380",
    "addr:housenumber":"2",
    "addr:postcode":"1380",
    "addr:street":"Rue De La Claudine",
    "iso:country":"BE",
    "sg:address":"Rue De La Claudine 2",
    "sg:city":"Lasne (maransart)",
    "sg:classifiers":[
        {
            "category":"Arena",
            "subcategory":"Sports Club",
            "type":"Entertainment"
        }
    ],
    "sg:phone":"+32 10 61 59 41",
    "sg:postcode":"1380",
    "sg:province":"Brabant Wallon",
    "sg:tags":[
        "federation"
    ],
    "wof:name":"Association R\u00e9gional Du Tourisme Equestre",
    "wof:placetype":"venue"
},
  "geometry": {"coordinates":[4.483235836,50.6850166321],"type":"Point"}
}