{
  "type": "Feature",
  "properties": {
    "addr:full":"Parklaan 1 Ninove Oost-Vlaanderen 9400",
    "addr:housenumber":"1",
    "addr:postcode":"9400",
    "addr:street":"Parklaan",
    "iso:country":"BE",
    "sg:address":"Parklaan 1",
    "sg:city":"Ninove",
    "sg:orig_category":"Sportterreinen and installaties behalve sportcentra",
    "sg:phone":"+32 54 33 40 64",
    "sg:postcode":"9400",
    "sg:province":"Oost-Vlaanderen",
    "wof:name":"Stedelijk Zwembad",
    "wof:placetype":"venue"
},
  "geometry": {"coordinates":[4.0171108246,50.828704834],"type":"Point"}
}