{
  "type": "Feature",
  "properties": {
    "addr:full":"Chauss\u00c9e De Charleroi 58 Charleroi Hainaut 6060",
    "addr:housenumber":"58",
    "addr:postcode":"6060",
    "addr:street":"Chausse\u0301E De Charleroi;Hainaut",
    "iso:country":"BE",
    "sg:address":"Chauss\u00c9e De Charleroi 58",
    "sg:city":"Charleroi",
    "sg:classifiers":[
        {
            "category":"Insurance",
            "subcategory":"Life Insurance",
            "type":"Services"
        }
    ],
    "sg:phone":"+32 71 41 72 57",
    "sg:postcode":"6060",
    "sg:province":"Hainaut",
    "sg:tags":[
        "assurance"
    ],
    "wof:name":"M. Leunis",
    "wof:placetype":"venue"
},
  "geometry": {"coordinates":[4.4755821228,50.4015884399],"type":"Point"}
}