{
  "type": "Feature",
  "properties": {
    "iso:country":"BE",
    "sg:address":"Kloosterstraat 70",
    "sg:city":"Essen",
    "sg:classifiers":[
        {
            "category":"Education",
            "subcategory":"School",
            "type":"Public Place"
        }
    ],
    "sg:phone":"+32 3 667 31 63",
    "sg:postcode":"2910",
    "sg:province":"Antwerpen",
    "sg:tags":[
        "secondary"
    ],
    "wof:name":"Don Bosco Mariaberg Instituut",
    "wof:placetype":"venue"
},
  "geometry": {"coordinates":[4.4611759186,51.4689407349],"type":"Point"}
}