{
  "type": "Feature",
  "properties": {
    "addr:full":"Naamsesteenweg 305 Leuven Vlaams-Brabant 3001",
    "addr:housenumber":"305",
    "addr:postcode":"3001",
    "addr:street":"Naamsesteenweg",
    "iso:country":"BE",
    "sg:address":"Naamsesteenweg 305",
    "sg:city":"Leuven",
    "sg:orig_category":"Boucheries",
    "sg:phone":"+32 16 40 72 78",
    "sg:postcode":"3001",
    "sg:province":"Vlaams-Brabant",
    "wof:name":"Beenhouwerij Vianda",
    "wof:placetype":"venue"
},
  "geometry": {"coordinates":[4.696059227,50.8593139648],"type":"Point"}
}