{
  "type": "Feature",
  "properties": {
    "addr:full":"La Minerie 9ba Thimister-clermont Li\u00e8ge 4890",
    "addr:postcode":"4890",
    "addr:street":"Minerie",
    "iso:country":"BE",
    "sg:address":"La Minerie 9ba",
    "sg:city":"Thimister-clermont",
    "sg:orig_category":"Plaatsen van vloer- and muurbekleding Schilders",
    "sg:phone":"+32 87 44 63 13",
    "sg:postcode":"4890",
    "sg:province":"Li\u00e8ge",
    "wof:name":"Fe. Jacob",
    "wof:placetype":"venue"
},
  "geometry": {"coordinates":[5.8476510048,50.6643562317],"type":"Point"}
}