{
  "type": "Feature",
  "properties": {
    "addr:full":"Lierselei 55 Malle (oostmalle) Antwerpen 2390",
    "addr:housenumber":"55",
    "addr:postcode":"2390",
    "addr:street":"Lierselei",
    "iso:country":"BE",
    "sg:address":"Lierselei 55",
    "sg:city":"Malle (oostmalle)",
    "sg:classifiers":[
        {
            "category":"Shopping",
            "subcategory":"Music",
            "type":"Retail Goods"
        }
    ],
    "sg:phone":"+32 3 312 39 84",
    "sg:postcode":"2390",
    "sg:province":"Antwerpen",
    "sg:tags":[
        "-",
        "cd's",
        "recorded",
        "cassette"
    ],
    "wof:name":"De Cd-hoek",
    "wof:placetype":"venue"
},
  "geometry": {"coordinates":[4.7323141098,51.297744751],"type":"Point"}
}