{
  "type": "Feature",
  "properties": {
    "addr:full":"Rue De M\u00e9rode 310 Bruxelles (forest) Bruxelles-Capitale 1190",
    "addr:housenumber":"310",
    "addr:postcode":"1190",
    "addr:street":"Rue De Me\u0301Rode",
    "iso:country":"BE",
    "sg:address":"Rue De M\u00e9rode 310",
    "sg:city":"Bruxelles (forest)",
    "sg:classifiers":[
        {
            "category":"Transit Center",
            "subcategory":"Freight",
            "type":"Transportation"
        }
    ],
    "sg:phone":"+32 2 538 85 91",
    "sg:postcode":"1190",
    "sg:province":"Bruxelles-Capitale",
    "sg:tags":[
        "import",
        "export",
        "-"
    ],
    "wof:name":"King Bazar",
    "wof:placetype":"venue"
},
  "geometry": {"coordinates":[4.3303790092,50.8276748657],"type":"Point"}
}