{
  "type": "Feature",
  "properties": {
    "addr:full":"Bochtlaan 25b Genk Limburg 3600",
    "addr:housenumber":"25b",
    "addr:postcode":"3600",
    "addr:street":"Bochtlaan",
    "iso:country":"BE",
    "sg:address":"Bochtlaan 25b",
    "sg:city":"Genk",
    "sg:classifiers":[
        {
            "category":"Personal",
            "subcategory":"Beauty Salon",
            "type":"Services"
        }
    ],
    "sg:phone":"+32 89 35 13 80",
    "sg:postcode":"3600",
    "sg:province":"Limburg",
    "sg:tags":[
        "equipment",
        "hairdressing",
        "-",
        "supply"
    ],
    "wof:name":"Intercap",
    "wof:placetype":"venue"
},
  "geometry": {"coordinates":[5.5024571419,50.9681816101],"type":"Point"}
}