{
  "type": "Feature",
  "properties": {
    "iso:country":"BE",
    "sg:address":"Rue De Ch\u00c2telet 14",
    "sg:city":"Gerpinnes",
    "sg:orig_category":"Eleveurs de bovins",
    "sg:phone":"+32 71 50 10 48",
    "sg:postcode":"6280",
    "sg:province":"Hainaut",
    "wof:name":"Francois Andre",
    "wof:placetype":"venue"
},
  "geometry": {"coordinates":[4.573390007,50.3552894592],"type":"Point"}
}