{
  "type": "Feature",
  "properties": {
    "addr:full":"Dorpstraat 38 Hasselt Limburg 3500",
    "addr:housenumber":"38",
    "addr:postcode":"3500",
    "addr:street":"Dorpstraat",
    "iso:country":"BE",
    "sg:address":"Dorpstraat 38",
    "sg:city":"Hasselt",
    "sg:orig_category":"Souvenirs and objets artisanaux. Librairies",
    "sg:phone":"+32 11 22 71 39",
    "sg:postcode":"3500",
    "sg:province":"Limburg",
    "wof:name":"Autoboeken Roadrunner",
    "wof:placetype":"venue"
},
  "geometry": {"coordinates":[5.3355851173,50.9323883057],"type":"Point"}
}