{
  "type": "Feature",
  "properties": {
    "iso:country":"BE",
    "sg:address":"De Schaggelen 22",
    "sg:city":"Malle",
    "sg:orig_category":"Electrom\u00e9nager, t\u00e9l\u00e9visions and radios. R\u00e9parations d'appareils \u00e9lectrom\u00e9nagers",
    "sg:phone":"+32 3 311 61 88",
    "sg:postcode":"2390",
    "sg:province":"Antwerpen",
    "wof:name":"Roger Kloeck",
    "wof:placetype":"venue"
},
  "geometry": {"coordinates":[4.6903247833,51.2954673767],"type":"Point"}
}