{
  "type": "Feature",
  "properties": {
    "addr:full":"Kaullillerweg 23 Peer Limburg 3990",
    "addr:housenumber":"23",
    "addr:postcode":"3990",
    "addr:street":"Kaullillerweg",
    "iso:country":"BE",
    "sg:address":"Kaullillerweg 23",
    "sg:city":"Peer",
    "sg:orig_category":"HUISBRANDOLIE Loodgieterij, verwarming and sanitaire installaties",
    "sg:phone":"+32 11 63 69 10",
    "sg:postcode":"3990",
    "sg:province":"Limburg",
    "wof:name":"L & M",
    "wof:placetype":"venue"
},
  "geometry": {"coordinates":[5.5074491501,51.1566925049],"type":"Point"}
}