{
  "type": "Feature",
  "properties": {
    "iso:country":"BE",
    "sg:address":"Vrijheid 169",
    "sg:city":"Hoogstraten",
    "sg:classifiers":[
        {
            "category":"Insurance",
            "subcategory":"Life Insurance",
            "type":"Services"
        }
    ],
    "sg:phone":"+32 3 314 71 41",
    "sg:postcode":"2320",
    "sg:province":"Antwerpen",
    "sg:tags":[
        "assurance"
    ],
    "wof:name":"Aertsen",
    "wof:placetype":"venue"
},
  "geometry": {"coordinates":[4.7608551979,51.4000091553],"type":"Point"}
}