{
  "type": "Feature",
  "properties": {
    "addr:full":"Rue Du Coq 106 Bruxelles (uccle) Bruxelles-Capitale 1180",
    "addr:housenumber":"106",
    "addr:postcode":"1180",
    "addr:street":"Rue Du Coq",
    "iso:country":"BE",
    "sg:address":"Rue Du Coq 106",
    "sg:city":"Bruxelles (uccle)",
    "sg:classifiers":[
        {
            "category":"Communications",
            "type":"Services"
        }
    ],
    "sg:phone":"+32 2 372 17 40",
    "sg:postcode":"1180",
    "sg:province":"Bruxelles-Capitale",
    "sg:tags":[
        "translator"
    ],
    "wof:name":"Tournon Genevi\u00e8ve",
    "wof:placetype":"venue"
},
  "geometry": {"coordinates":[4.3351449966,50.7937583923],"type":"Point"}
}