{
  "type": "Feature",
  "properties": {
    "addr:full":"Pelikaanstr 54 Antwerpen Antwerpen 2018",
    "addr:housenumber":"54",
    "addr:postcode":"2018",
    "addr:street":"Pelikaanstr",
    "iso:country":"BE",
    "sg:address":"Pelikaanstr 54",
    "sg:city":"Antwerpen",
    "sg:classifiers":[
        {
            "category":"Banks & Credit Unions",
            "subcategory":"Bank",
            "type":"Services"
        }
    ],
    "sg:phone":"+32 3 546 08 08",
    "sg:postcode":"2018",
    "sg:province":"Antwerpen",
    "wof:name":"Arfin Krediet Spaarbank Cv/sc",
    "wof:placetype":"venue"
},
  "geometry": {"coordinates":[4.4182572365,51.2778625488],"type":"Point"}
}