{
  "type": "Feature",
  "properties": {
    "iso:country":"BE",
    "sg:address":"Gutschovenstraat 20",
    "sg:city":"Heers",
    "sg:classifiers":[
        {
            "category":"Professional",
            "subcategory":"Accounting & Tax Preparation",
            "type":"Services"
        }
    ],
    "sg:phone":"+32 11 82 11 41",
    "sg:postcode":"3870",
    "sg:province":"Limburg",
    "sg:tags":[
        "accountant"
    ],
    "wof:name":"Willy Lambermon",
    "wof:placetype":"venue"
},
  "geometry": {"coordinates":[5.3196549416,50.7764320374],"type":"Point"}
}