{
  "type": "Feature",
  "properties": {
    "iso:country":"BE",
    "sg:address":"Eglantierlaan 75 Box 3",
    "sg:city":"Antwerpen (wilrijk)",
    "sg:classifiers":[
        {
            "category":"Professional",
            "type":"Services"
        }
    ],
    "sg:postcode":"2610",
    "sg:province":"Antwerpen",
    "sg:tags":[
        "entertainer"
    ],
    "wof:name":"Centre De La Danse Du Ventre",
    "wof:placetype":"venue"
},
  "geometry": {"coordinates":[6.0409388542,50.8674468994],"type":"Point"}
}