{
  "type": "Feature",
  "properties": {
    "addr:full":"Ganzenstraat 53 Brugge West-Vlaanderen 8000",
    "addr:housenumber":"53",
    "addr:postcode":"8000",
    "addr:street":"Ganzenstraat",
    "iso:country":"BE",
    "sg:address":"Ganzenstraat 53",
    "sg:city":"Brugge",
    "sg:classifiers":[
        {
            "category":"Professional",
            "subcategory":"Art Services",
            "type":"Services"
        }
    ],
    "sg:phone":"+32 50 33 38 31",
    "sg:postcode":"8000",
    "sg:province":"West-Vlaanderen",
    "sg:tags":[
        "interior",
        "designer"
    ],
    "wof:name":"Diadema Bvba",
    "wof:placetype":"venue"
},
  "geometry": {"coordinates":[3.2358870506,51.208404541],"type":"Point"}
}