{
  "type": "Feature",
  "properties": {
    "addr:full":"Rue Des Trieux 5 Eghezee Namur 5310",
    "addr:housenumber":"5",
    "addr:postcode":"5310",
    "addr:street":"Rue Des Trieux;Namur",
    "iso:country":"BE",
    "sg:address":"Rue Des Trieux 5",
    "sg:city":"Eghezee",
    "sg:orig_category":"Plomberie, chauffage and installations sanitaires. Charpentes and couvertures",
    "sg:phone":"+32 81 65 70 54",
    "sg:postcode":"5310",
    "sg:province":"Namur",
    "wof:name":"Alain Vandenbruggen",
    "wof:placetype":"venue"
},
  "geometry": {"coordinates":[4.830370903,50.5812149048],"type":"Point"}
}