{
  "type": "Feature",
  "properties": {
    "iso:country":"BE",
    "sg:address":"Hezerheiweg 16",
    "sg:city":"Diest (schaffen)",
    "sg:classifiers":[
        {
            "category":"Utilities",
            "subcategory":"Recycling",
            "type":"Services"
        }
    ],
    "sg:phone":"+32 13 31 24 57",
    "sg:postcode":"3290",
    "sg:province":"Vlaams-Brabant",
    "wof:name":"Enkels Vic Bvba",
    "wof:placetype":"venue"
},
  "geometry": {"coordinates":[5.0885691643,50.9907531738],"type":"Point"}
}