{
  "type": "Feature",
  "properties": {
    "iso:country":"BE",
    "sg:address":"Broekstraat 15",
    "sg:city":"Anzegem (kaster)",
    "sg:classifiers":[
        {
            "category":"Health Services",
            "subcategory":"Health Practitioner",
            "type":"Services"
        }
    ],
    "sg:phone":"+32 479 84 42 35",
    "sg:postcode":"8572",
    "sg:province":"West-Vlaanderen",
    "sg:tags":[
        "alternative",
        "therapy",
        "treatment"
    ],
    "wof:name":"Hypno T.c.b.",
    "wof:placetype":"venue"
},
  "geometry": {"coordinates":[3.5078990459,50.81640625],"type":"Point"}
}