{
  "type": "Feature",
  "properties": {
    "iso:country":"BE",
    "sg:address":"Rue Du Peignage 13",
    "sg:city":"Verviers",
    "sg:orig_category":"Plomberie, chauffage and installations sanitaires",
    "sg:phone":"+32 87 33 80 57",
    "sg:postcode":"4800",
    "sg:province":"Li\u00e8ge",
    "wof:name":"Fe. B.g.",
    "wof:placetype":"venue"
},
  "geometry": {"coordinates":[5.8463068008,50.5904922485],"type":"Point"}
}