{
  "type": "Feature",
  "properties": {
    "addr:full":"Heikantstraat 117 Kalmthout Antwerpen 2920",
    "addr:housenumber":"117",
    "addr:postcode":"2920",
    "addr:street":"Heikantstraat",
    "iso:country":"BE",
    "sg:address":"Heikantstraat 117",
    "sg:city":"Kalmthout",
    "sg:orig_category":"Rundveehouders Varkenskwekers",
    "sg:phone":"+32 3 666 80 06",
    "sg:postcode":"2920",
    "sg:province":"Antwerpen",
    "wof:name":"Jozef Matthijssen",
    "wof:placetype":"venue"
},
  "geometry": {"coordinates":[4.4908409119,51.3713150024],"type":"Point"}
}