{
  "type": "Feature",
  "properties": {
    "addr:full":"Avenue Des D\u00c9port\u00c9s 105 Fontaine-l\u00b4ev\u00caque Hainaut 6140",
    "addr:housenumber":"105",
    "addr:postcode":"6140",
    "addr:street":"Avenue Des De\u0301Porte\u0301S;Hainaut",
    "iso:country":"BE",
    "sg:address":"Avenue Des D\u00c9port\u00c9s 105",
    "sg:city":"Fontaine-l\u00b4ev\u00caque",
    "sg:orig_category":"Meubles D\u00e9taillants, Am\u00e9nagement de B\u00e2timents et de Cuisines",
    "sg:phone":"+32 71 54 32 22",
    "sg:postcode":"6140",
    "sg:province":"Hainaut",
    "wof:name":"Mobili 22",
    "wof:placetype":"venue"
},
  "geometry": {"coordinates":[4.3340301514,50.4079399109],"type":"Point"}
}