{
  "type": "Feature",
  "properties": {
    "iso:country":"BE",
    "sg:address":"Rue Du Culot 60",
    "sg:city":"Beauvechain",
    "sg:orig_category":"Rundveehouders",
    "sg:phone":"+32 10 86 64 01",
    "sg:postcode":"1320",
    "sg:province":"Brabant Wallon",
    "wof:name":"Evrard Paul Et Lucie",
    "wof:placetype":"venue"
},
  "geometry": {"coordinates":[4.7505521774,50.7939682007],"type":"Point"}
}