{
  "type": "Feature",
  "properties": {
    "iso:country":"BE",
    "sg:address":"Rue Vieux-martin 34",
    "sg:city":"Florennes",
    "sg:classifiers":[
        {
            "category":"Cafe",
            "type":"Food & Drink"
        }
    ],
    "sg:phone":"+32 71 50 33 47",
    "sg:postcode":"5621",
    "sg:province":"Namur",
    "sg:tags":[
        "caf\u00e9s"
    ],
    "wof:name":"Caf\u00c9 L'urgence",
    "wof:placetype":"venue"
},
  "geometry": {"coordinates":[4.5432071686,50.3129615784],"type":"Point"}
}