{
  "type": "Feature",
  "properties": {
    "addr:full":"Stationsstraat 43 Brugge (zeebrugge - Lissewege) West-Vlaanderen 8380",
    "addr:housenumber":"43",
    "addr:postcode":"8380",
    "addr:street":"Stationsstraat",
    "iso:country":"BE",
    "sg:address":"Stationsstraat 43",
    "sg:city":"Brugge (zeebrugge - Lissewege)",
    "sg:classifiers":[
        {
            "category":"Insurance",
            "subcategory":"Insurance Agent",
            "type":"Services"
        }
    ],
    "sg:phone":"+32 50 27 06 66",
    "sg:postcode":"8380",
    "sg:province":"West-Vlaanderen",
    "sg:tags":[
        "broker"
    ],
    "wof:name":"Barremaecker K",
    "wof:placetype":"venue"
},
  "geometry": {"coordinates":[3.2139921188,51.1991004944],"type":"Point"}
}