{
  "type": "Feature",
  "properties": {
    "iso:country":"BE",
    "sg:address":"Rue De La Technologie 65",
    "sg:city":"Sint-agatha-berchem/berchem-sainte-agathe",
    "sg:orig_category":"Ordinateurs and \u00e9quipement informatique",
    "sg:phone":"+32 2 468 50 76",
    "sg:postcode":"1082",
    "sg:province":"Bruxelles-Capitale",
    "wof:name":"I.d.g.-hardware Service",
    "wof:placetype":"venue"
},
  "geometry": {"coordinates":[4.2919940948,50.8743858337],"type":"Point"}
}