{
  "type": "Feature",
  "properties": {
    "iso:country":"BE",
    "sg:address":"Marktplein 36",
    "sg:city":"Diepenbeek",
    "sg:classifiers":[
        {
            "category":"Arena",
            "subcategory":"Sports Club",
            "type":"Entertainment"
        }
    ],
    "sg:phone":"+32 11 32 45 45",
    "sg:postcode":"3590",
    "sg:province":"Limburg",
    "sg:tags":[
        "terrain",
        "hors",
        "de",
        "installation",
        "sportifs"
    ],
    "wof:name":"Diepenbeek V.v.",
    "wof:placetype":"venue"
},
  "geometry": {"coordinates":[5.4188528061,50.9074935913],"type":"Point"}
}