{
  "type": "Feature",
  "properties": {
    "addr:full":"Rue Du Roitelet 10 Bruxelles (watermael-boitsfort) Bruxelles-Capitale 1170",
    "addr:housenumber":"10",
    "addr:postcode":"1170",
    "addr:street":"Rue Du Roitelet",
    "iso:country":"BE",
    "sg:address":"Rue Du Roitelet 10",
    "sg:city":"Bruxelles (watermael-boitsfort)",
    "sg:classifiers":[
        {
            "category":"Retail",
            "subcategory":"Animal Services",
            "type":"Services"
        }
    ],
    "sg:phone":"+32 2 673 73 67",
    "sg:postcode":"1170",
    "sg:province":"Bruxelles-Capitale",
    "sg:tags":[
        "grooming",
        "-",
        "dog"
    ],
    "wof:name":"Passiflore (la)",
    "wof:placetype":"venue"
},
  "geometry": {"coordinates":[4.401930809,50.8091468811],"type":"Point"}
}