{
  "type": "Feature",
  "properties": {
    "iso:country":"BE",
    "sg:address":"Rue L\u00c9opold I 88",
    "sg:city":"Brussel/bruxelles",
    "sg:orig_category":"Cr\u00e8ches and garderies d'enfants",
    "sg:phone":"+32 2 424 14 42",
    "sg:postcode":"1020",
    "sg:province":"Bruxelles-Capitale",
    "wof:name":"Les Schtroumps",
    "wof:placetype":"venue"
},
  "geometry": {"coordinates":[4.3468198776,50.8775215149],"type":"Point"}
}