{
  "type": "Feature",
  "properties": {
    "addr:full":"Kasteeldreef 7 Melle Oost-Vlaanderen 9090",
    "addr:housenumber":"7",
    "addr:postcode":"9090",
    "addr:street":"Kasteeldreef",
    "iso:country":"BE",
    "sg:address":"Kasteeldreef 7",
    "sg:city":"Melle",
    "sg:orig_category":"Decoratieve kunst and kunstbenodigdheden",
    "sg:phone":"+32 9 230 97 73",
    "sg:postcode":"9090",
    "sg:province":"Oost-Vlaanderen",
    "wof:name":"Elie Rigelle",
    "wof:placetype":"venue"
},
  "geometry": {"coordinates":[3.7752420902,51.0241737366],"type":"Point"}
}