{
  "type": "Feature",
  "properties": {
    "addr:full":"Rue De La Station 35 Gembloux Namur 5030",
    "addr:housenumber":"35",
    "addr:postcode":"5030",
    "addr:street":"Rue De La Station;Namur",
    "iso:country":"BE",
    "sg:address":"Rue De La Station 35",
    "sg:city":"Gembloux",
    "sg:orig_category":"Loodgieterij, verwarming and sanitaire installaties",
    "sg:phone":"+32 81 56 91 44",
    "sg:postcode":"5030",
    "sg:province":"Namur",
    "wof:name":"Ets. Trefois Eric",
    "wof:placetype":"venue"
},
  "geometry": {"coordinates":[4.746694088,50.5337905884],"type":"Point"}
}