{
  "type": "Feature",
  "properties": {
    "addr:full":"Halstraat 5 Heusden-zolder Limburg 3550",
    "addr:housenumber":"5",
    "addr:postcode":"3550",
    "addr:street":"Halstraat",
    "iso:country":"BE",
    "sg:address":"Halstraat 5",
    "sg:city":"Heusden-zolder",
    "sg:classifiers":[
        {
            "category":"Cafe",
            "type":"Food & Drink"
        }
    ],
    "sg:phone":"+32 11 57 27 59",
    "sg:postcode":"3550",
    "sg:province":"Limburg",
    "sg:tags":[
        "caf\u00e9s"
    ],
    "wof:name":"Irma Vanhove",
    "wof:placetype":"venue"
},
  "geometry": {"coordinates":[5.2967238426,51.0445632935],"type":"Point"}
}