{
  "type": "Feature",
  "properties": {
    "iso:country":"BE",
    "sg:address":"Leopoldlei 9",
    "sg:city":"Heist-op-den-berg",
    "sg:classifiers":[
        {
            "category":"Professional",
            "subcategory":"Art Services",
            "type":"Services"
        }
    ],
    "sg:phone":"+32 15 24 89 09",
    "sg:postcode":"2220",
    "sg:province":"Antwerpen",
    "sg:tags":[
        "picture",
        "framer"
    ],
    "wof:name":"Kaderke ('t)",
    "wof:placetype":"venue"
},
  "geometry": {"coordinates":[4.7266850471,51.0764732361],"type":"Point"}
}