{
  "type": "Feature",
  "properties": {
    "addr:full":"Place L\u00e9opold 1 Chimay Hainaut 6460",
    "addr:housenumber":"1",
    "addr:postcode":"6460",
    "addr:street":"Place Le\u0301Opold",
    "iso:country":"BE",
    "sg:address":"Place L\u00e9opold 1",
    "sg:city":"Chimay",
    "sg:classifiers":[
        {
            "category":"Health Services",
            "subcategory":"Hospital",
            "type":"Services"
        }
    ],
    "sg:phone":"+32 60 21 54 48",
    "sg:postcode":"6460",
    "sg:province":"Hainaut",
    "sg:tags":[
        "ambulance"
    ],
    "wof:name":"Croix Rouge De Belgique",
    "wof:placetype":"venue"
},
  "geometry": {"coordinates":[4.3187308311,50.0475120544],"type":"Point"}
}