{
  "type": "Feature",
  "properties": {
    "iso:country":"BE",
    "sg:address":"Rue Wahenge 19",
    "sg:city":"Beauvechain",
    "sg:orig_category":"Eleveurs and marchands de porcs. Eleveurs de bovins",
    "sg:phone":"+32 10 86 65 68",
    "sg:postcode":"1320",
    "sg:province":"Brabant Wallon",
    "wof:name":"Romain Lefevre",
    "wof:placetype":"venue"
},
  "geometry": {"coordinates":[4.7983779907,50.7644462585],"type":"Point"}
}