{
  "type": "Feature",
  "properties": {
    "addr:full":"Guytjensstraat 15 Meeuwen-gruitrode Limburg 3670",
    "addr:housenumber":"15",
    "addr:postcode":"3670",
    "addr:street":"Guytjensstraat",
    "iso:country":"BE",
    "sg:address":"Guytjensstraat 15",
    "sg:city":"Meeuwen-gruitrode",
    "sg:orig_category":"Pluimveekwekers",
    "sg:phone":"+32 11 79 21 18",
    "sg:postcode":"3670",
    "sg:province":"Limburg",
    "wof:name":"Paesen",
    "wof:placetype":"venue"
},
  "geometry": {"coordinates":[5.5309119225,51.0902137756],"type":"Point"}
}