{
  "type": "Feature",
  "properties": {
    "addr:full":"Brugsesteenweg 200 Maldegem Oost-Vlaanderen 9990",
    "addr:housenumber":"200",
    "addr:postcode":"9990",
    "addr:street":"Brugsesteenweg",
    "iso:country":"BE",
    "sg:address":"Brugsesteenweg 200",
    "sg:city":"Maldegem",
    "sg:classifiers":[
        {
            "category":"Restaurant",
            "type":"Food & Drink"
        }
    ],
    "sg:phone":"+32 50 71 55 95",
    "sg:postcode":"9990",
    "sg:province":"Oost-Vlaanderen",
    "wof:name":"Beukenhof",
    "wof:placetype":"venue"
},
  "geometry": {"coordinates":[3.4123370647,51.2070770264],"type":"Point"}
}