{
  "type": "Feature",
  "properties": {
    "addr:full":"Avenue Rommelaere 249 Jette/jette Bruxelles-Capitale 1090",
    "addr:housenumber":"249",
    "addr:postcode":"1090",
    "addr:street":"Avenue Rommelaere",
    "iso:country":"BE",
    "sg:address":"Avenue Rommelaere 249",
    "sg:city":"Jette/jette",
    "sg:orig_category":"Activit\u00e9s r\u00e9cr\u00e9atives diverses",
    "sg:phone":"+32 2 478 43 58",
    "sg:postcode":"1090",
    "sg:province":"Bruxelles-Capitale",
    "wof:name":"B.c. Royal Primerose",
    "wof:placetype":"venue"
},
  "geometry": {"coordinates":[4.3253350258,50.8911819458],"type":"Point"}
}