{
  "type": "Feature",
  "properties": {
    "iso:country":"BE",
    "sg:address":"Lissewallestraat 2",
    "sg:city":"Ieper",
    "sg:orig_category":"Eleveurs and marchands de porcs. Eleveurs de bovins",
    "sg:phone":"+32 57 20 18 11",
    "sg:postcode":"8908",
    "sg:province":"West-Vlaanderen",
    "wof:name":"Etienne Vandeputte",
    "wof:placetype":"venue"
},
  "geometry": {"coordinates":[2.8117129803,50.8493766785],"type":"Point"}
}