{
  "type": "Feature",
  "properties": {
    "addr:full":"Koninklijke Baan 146 Koksijde West-Vlaanderen 8670",
    "addr:housenumber":"146",
    "addr:postcode":"8670",
    "addr:street":"Koninklijke Baan",
    "iso:country":"BE",
    "sg:address":"Koninklijke Baan 146",
    "sg:city":"Koksijde",
    "sg:classifiers":[
        {
            "category":"Bakery",
            "type":"Food & Drink"
        }
    ],
    "sg:phone":"+32 58 51 01 41",
    "sg:postcode":"8670",
    "sg:province":"West-Vlaanderen",
    "sg:tags":[
        "confectioner",
        "baker"
    ],
    "wof:name":"Nicholas",
    "wof:placetype":"venue"
},
  "geometry": {"coordinates":[2.6335320473,51.1201477051],"type":"Point"}
}