{
  "type": "Feature",
  "properties": {
    "addr:full":"Kampstraat 59 Geraardsbergen Oost-Vlaanderen 9500",
    "addr:housenumber":"59",
    "addr:postcode":"9500",
    "addr:street":"Kampstraat",
    "iso:country":"BE",
    "sg:address":"Kampstraat 59",
    "sg:city":"Geraardsbergen",
    "sg:orig_category":"Auberges de jeunesse and refuges",
    "sg:phone":"+32 54 41 61 89",
    "sg:postcode":"9500",
    "sg:province":"Oost-Vlaanderen",
    "wof:name":"'t Schipke",
    "wof:placetype":"venue"
},
  "geometry": {"coordinates":[3.8843801022,50.7716445923],"type":"Point"}
}