{
  "type": "Feature",
  "properties": {
    "addr:full":"Raadstraat 13 Elsene/ixelles Bruxelles-Capitale 1050",
    "addr:housenumber":"13",
    "addr:postcode":"1050",
    "addr:street":"Raadstraat",
    "iso:country":"BE",
    "sg:address":"Raadstraat 13",
    "sg:city":"Elsene/ixelles",
    "sg:orig_category":"Persagentschappen",
    "sg:phone":"+32 2 660 62 00",
    "sg:postcode":"1050",
    "sg:province":"Bruxelles-Capitale",
    "wof:name":"Philippe Candaele",
    "wof:placetype":"venue"
},
  "geometry": {"coordinates":[4.3678212166,50.8335342407],"type":"Point"}
}