{
  "type": "Feature",
  "properties": {
    "iso:country":"BE",
    "sg:address":"Rue Du Pont D\u00b4erez\u00c9e 3",
    "sg:city":"Erezee",
    "sg:orig_category":"Dranken",
    "sg:phone":"+32 86 47 75 06",
    "sg:postcode":"6997",
    "sg:province":"Luxembourg",
    "wof:name":"Lefevre Jean-marie",
    "wof:placetype":"venue"
},
  "geometry": {"coordinates":[5.5588469505,50.2911453247],"type":"Point"}
}