{
  "type": "Feature",
  "properties": {
    "addr:full":"Nieuwstraat 32 Zottegem Oost-Vlaanderen 9620",
    "addr:housenumber":"32",
    "addr:postcode":"9620",
    "addr:street":"Nieuwstraat",
    "iso:country":"BE",
    "sg:address":"Nieuwstraat 32",
    "sg:city":"Zottegem",
    "sg:classifiers":[
        {
            "category":"Personal",
            "subcategory":"Beauty Salon",
            "type":"Services"
        }
    ],
    "sg:phone":"+32 9 360 11 38",
    "sg:postcode":"9620",
    "sg:province":"Oost-Vlaanderen",
    "sg:tags":[
        "lady",
        "-",
        "hairdressing"
    ],
    "wof:name":"Ann",
    "wof:placetype":"venue"
},
  "geometry": {"coordinates":[3.8120930195,50.8686790466],"type":"Point"}
}