{
  "type": "Feature",
  "properties": {
    "addr:full":"Rue Edouard Colson 297 Ans (loncin) Li\u00e8ge 4431",
    "addr:housenumber":"297",
    "addr:postcode":"4431",
    "addr:street":"Rue Edouard Colson",
    "iso:country":"BE",
    "sg:address":"Rue Edouard Colson 297",
    "sg:city":"Ans (loncin)",
    "sg:classifiers":[
        {
            "category":"Retail",
            "subcategory":"Auto Repair",
            "type":"Services"
        }
    ],
    "sg:phone":"+32 4 247 41 47",
    "sg:postcode":"4431",
    "sg:province":"Li\u00e8ge",
    "sg:tags":[
        "garage"
    ],
    "wof:name":"Schyns",
    "wof:placetype":"venue"
},
  "geometry": {"coordinates":[5.4915800095,50.6715545654],"type":"Point"}
}