{
  "type": "Feature",
  "properties": {
    "addr:full":"Rue De La Fontaine 231 Flemalle Li\u00e8ge 4400",
    "addr:housenumber":"231",
    "addr:postcode":"4400",
    "addr:street":"Rue De La Fontaine",
    "iso:country":"BE",
    "sg:address":"Rue De La Fontaine 231",
    "sg:city":"Flemalle",
    "sg:classifiers":[
        {
            "category":"Arena",
            "subcategory":"Sports Club",
            "type":"Entertainment"
        }
    ],
    "sg:phone":"+32 4 233 25 86",
    "sg:postcode":"4400",
    "sg:province":"Li\u00e8ge",
    "sg:tags":[
        "de"
    ],
    "wof:name":"R.o.c. Fl\u00c9malle",
    "wof:placetype":"venue"
},
  "geometry": {"coordinates":[5.4752759933,50.6136245728],"type":"Point"}
}