{
  "type": "Feature",
  "properties": {
    "addr:full":"Vervierser Strasse 10 Eupen Li\u00e8ge 4700",
    "addr:housenumber":"10",
    "addr:postcode":"4700",
    "addr:street":"Vervierser Strasse",
    "iso:country":"BE",
    "sg:address":"Vervierser Strasse 10",
    "sg:city":"Eupen",
    "sg:classifiers":[
        {
            "category":"Professional",
            "subcategory":"Lawyer & Legal Services",
            "type":"Services"
        }
    ],
    "sg:phone":"+32 87 74 09 23",
    "sg:postcode":"4700",
    "sg:province":"Li\u00e8ge",
    "wof:name":"Noirfalise V",
    "wof:placetype":"venue"
},
  "geometry": {"coordinates":[6.0273017883,50.6315231323],"type":"Point"}
}