{
  "type": "Feature",
  "properties": {
    "iso:country":"BE",
    "sg:address":"Gospertstrasse 41",
    "sg:city":"Eupen",
    "sg:classifiers":[
        {
            "category":"Food & Beverages",
            "subcategory":"Chocolate",
            "type":"Retail Goods"
        }
    ],
    "sg:phone":"+32 87 55 50 52",
    "sg:postcode":"4700",
    "sg:province":"Li\u00e8ge",
    "sg:tags":[
        "confectionery",
        "-"
    ],
    "wof:name":"Leonidas Eupen",
    "wof:placetype":"venue"
},
  "geometry": {"coordinates":[6.0347390175,50.6316184998],"type":"Point"}
}