{
  "type": "Feature",
  "properties": {
    "iso:country":"BE",
    "sg:address":"Hondstraat 2",
    "sg:city":"Kontich",
    "sg:classifiers":[
        {
            "category":"Retail",
            "subcategory":"Auto Rental",
            "type":"Services"
        }
    ],
    "sg:phone":"+32 2 257 04 04",
    "sg:postcode":"2550",
    "sg:province":"Antwerpen",
    "sg:tags":[
        "automobile",
        "-",
        "car",
        "self-drive"
    ],
    "wof:name":"A.n.t. Rent Nv",
    "wof:placetype":"venue"
},
  "geometry": {"coordinates":[4.4406599998,51.1129188538],"type":"Point"}
}