{
  "type": "Feature",
  "properties": {
    "iso:country":"BE",
    "sg:address":"Avenue R. Vandendriessche 6",
    "sg:city":"Sint-pieters-woluwe/woluwe-saint-pierre",
    "sg:orig_category":"Eclairage et \u00e9quipements du foyer. Textiles",
    "sg:phone":"+32 2 762 50 85",
    "sg:postcode":"1150",
    "sg:province":"Bruxelles-Capitale",
    "wof:name":"Les Caves De Th\u00c9r\u00c8se",
    "wof:placetype":"venue"
},
  "geometry": {"coordinates":[4.414689064,50.8348236084],"type":"Point"}
}