{
  "type": "Feature",
  "properties": {
    "iso:country":"BE",
    "sg:address":"Havermarkt 15",
    "sg:city":"Hasselt",
    "sg:classifiers":[
        {
            "category":"Home & Garden",
            "subcategory":"Home Furnishings",
            "type":"Retail Goods"
        }
    ],
    "sg:phone":"+32 11 22 34 29",
    "sg:postcode":"3500",
    "sg:province":"Limburg",
    "sg:tags":[
        "curtain",
        "-",
        "fixture"
    ],
    "wof:name":"Finestra",
    "wof:placetype":"venue"
},
  "geometry": {"coordinates":[5.335996151,50.9293937683],"type":"Point"}
}