{
  "type": "Feature",
  "properties": {
    "addr:full":"Rue De Tourcoing 45 Mouscron Hainaut 7700",
    "addr:housenumber":"45",
    "addr:postcode":"7700",
    "addr:street":"Rue De Tourcoing",
    "iso:country":"BE",
    "sg:address":"Rue De Tourcoing 45",
    "sg:city":"Mouscron",
    "sg:orig_category":"Non-Classified Establishments",
    "sg:phone":"+32 56 33 02 11",
    "sg:postcode":"7700",
    "sg:province":"Hainaut",
    "wof:name":"Rousselle",
    "wof:placetype":"venue"
},
  "geometry": {"coordinates":[3.2114510536,50.7444229126],"type":"Point"}
}