{
  "type": "Feature",
  "properties": {
    "addr:full":"De Arend 18 Zedelgem West-Vlaanderen 8210",
    "addr:housenumber":"18",
    "addr:postcode":"8210",
    "addr:street":"De Arend",
    "iso:country":"BE",
    "sg:address":"De Arend 18",
    "sg:city":"Zedelgem",
    "sg:classifiers":[
        {
            "category":"Professional",
            "subcategory":"Engineering",
            "type":"Services"
        }
    ],
    "sg:phone":"+32 10 45 18 18",
    "sg:postcode":"8210",
    "sg:province":"West-Vlaanderen",
    "sg:tags":[
        "machine",
        "-",
        "mechanical"
    ],
    "wof:name":"Bepa Sa",
    "wof:placetype":"venue"
},
  "geometry": {"coordinates":[4.6171450615,50.670124054],"type":"Point"}
}