{
  "type": "Feature",
  "properties": {
    "iso:country":"BE",
    "sg:address":"Polenstraat 36",
    "sg:city":"Evergem",
    "sg:orig_category":"Architecten",
    "sg:phone":"+32 9 357 78 10",
    "sg:postcode":"9940",
    "sg:province":"Oost-Vlaanderen",
    "wof:name":"Vereeken Nicole",
    "wof:placetype":"venue"
},
  "geometry": {"coordinates":[3.6793839931,51.1319732666],"type":"Point"}
}