{
  "type": "Feature",
  "properties": {
    "iso:country":"BE",
    "sg:address":"Avenue Des M\u00e9sanges 36",
    "sg:city":"Waterloo",
    "sg:classifiers":[
        {
            "category":"Health Services",
            "subcategory":"Doctor",
            "type":"Services"
        }
    ],
    "sg:phone":"+32 2 351 42 47",
    "sg:postcode":"1410",
    "sg:province":"Brabant Wallon",
    "sg:tags":[
        "medicinephysicians",
        "surgeon"
    ],
    "wof:name":"Huard A",
    "wof:placetype":"venue"
},
  "geometry": {"coordinates":[4.4099760056,50.7213859558],"type":"Point"}
}