{
  "type": "Feature",
  "properties": {
    "iso:country":"BE",
    "sg:address":"Tulpenlaan 18",
    "sg:city":"Zandhoven",
    "sg:orig_category":"Benzinestations and brandstoffen",
    "sg:phone":"+32 3 464 04 26",
    "sg:postcode":"2240",
    "sg:province":"Antwerpen",
    "wof:name":"Serv.station Massenhoven",
    "wof:placetype":"venue"
},
  "geometry": {"coordinates":[4.6428427696,51.2013778687],"type":"Point"}
}