{
  "type": "Feature",
  "properties": {
    "addr:full":"Onze Lieve Vrouwstraat 6 Turnhout Antwerpen 2300",
    "addr:housenumber":"6",
    "addr:postcode":"2300",
    "addr:street":"Onze Lieve Vrouwstraat",
    "iso:country":"BE",
    "sg:address":"Onze Lieve Vrouwstraat 6",
    "sg:city":"Turnhout",
    "sg:orig_category":"Artsen and specialisten",
    "sg:phone":"+32 14 43 50 80",
    "sg:postcode":"2300",
    "sg:province":"Antwerpen",
    "wof:name":"Danny Labbeke",
    "wof:placetype":"venue"
},
  "geometry": {"coordinates":[4.9316010475,51.3210639954],"type":"Point"}
}