{
  "type": "Feature",
  "properties": {
    "addr:full":"Avenue Marie De Hongrie 18 Box 7 Bruxelles (ganshoren) Bruxelles-Capitale 1083",
    "addr:housenumber":"18;7",
    "addr:postcode":"1083",
    "addr:street":"Avenue Marie De Hongrie;Box",
    "iso:country":"BE",
    "sg:address":"Avenue Marie De Hongrie 18 Box 7",
    "sg:city":"Bruxelles (ganshoren)",
    "sg:classifiers":[
        {
            "category":"Professional",
            "subcategory":"Lawyer & Legal Services",
            "type":"Services"
        }
    ],
    "sg:phone":"+32 2 465 82 61",
    "sg:postcode":"1083",
    "sg:province":"Bruxelles-Capitale",
    "wof:name":"Deroy Pierre",
    "wof:placetype":"venue"
},
  "geometry": {"coordinates":[4.307199955,50.871219635],"type":"Point"}
}