{
  "type": "Feature",
  "properties": {
    "addr:full":"Rue Notre-dame-de-graces 80 Marche-en-famenne Luxembourg 6900",
    "addr:housenumber":"80",
    "addr:postcode":"6900",
    "addr:street":"Rue Notre-Dame-De-Graces",
    "iso:country":"BE",
    "sg:address":"Rue Notre-dame-de-graces 80",
    "sg:city":"Marche-en-famenne",
    "sg:orig_category":"Instituts de beaut\u00e9",
    "sg:phone":"+32 84 31 24 28",
    "sg:postcode":"6900",
    "sg:province":"Luxembourg",
    "wof:name":"Institut Michel-adam",
    "wof:placetype":"venue"
},
  "geometry": {"coordinates":[5.3367781639,50.2289505005],"type":"Point"}
}