{
  "type": "Feature",
  "properties": {
    "addr:full":"Avenue Brugmann 489 Bruxelles (uccle) Bruxelles-Capitale 1180",
    "addr:housenumber":"489",
    "addr:postcode":"1180",
    "addr:street":"Avenue Brugmann",
    "iso:country":"BE",
    "sg:address":"Avenue Brugmann 489",
    "sg:city":"Bruxelles (uccle)",
    "sg:classifiers":[
        {
            "category":"Education",
            "subcategory":"University",
            "type":"Public Place"
        }
    ],
    "sg:phone":"+32 2 344 65 70",
    "sg:postcode":"1180",
    "sg:province":"Bruxelles-Capitale",
    "sg:tags":[
        "higher"
    ],
    "wof:name":"Universit\u00e9 Europ\u00e9enne D'ecriture",
    "wof:placetype":"venue"
},
  "geometry": {"coordinates":[4.3419098854,50.8042831421],"type":"Point"}
}