{
  "type": "Feature",
  "properties": {
    "addr:full":"Elzeelsesteenweg 88 Ronse Oost-Vlaanderen 9600",
    "addr:housenumber":"88",
    "addr:postcode":"9600",
    "addr:street":"Elzeelsesteenweg",
    "iso:country":"BE",
    "sg:address":"Elzeelsesteenweg 88",
    "sg:city":"Ronse",
    "sg:orig_category":"Hout and afgeleiden Gh IJzerwaren, bouw- and verfmaterialen Verhuur doe-het-zelf materiaal",
    "sg:phone":"+32 55 20 77 80",
    "sg:postcode":"9600",
    "sg:province":"Oost-Vlaanderen",
    "wof:name":"Gamma",
    "wof:placetype":"venue"
},
  "geometry": {"coordinates":[3.6125900745,50.7436408997],"type":"Point"}
}