{
  "type": "Feature",
  "properties": {
    "addr:full":"Chauss\u00c9e De La Hulpe 305 Watermael-boitsfort Bruxelles-Capitale 1170",
    "addr:housenumber":"305",
    "addr:postcode":"1170",
    "addr:street":"Chausse\u0301E De La Hulpe",
    "iso:country":"BE",
    "sg:address":"Chauss\u00c9e De La Hulpe 305",
    "sg:city":"Watermael-boitsfort",
    "sg:orig_category":"Diverse bedrijfsbeheeradviesbureaus",
    "sg:phone":"+32 2 660 05 26",
    "sg:postcode":"1170",
    "sg:province":"Bruxelles-Capitale",
    "wof:name":"Organisation Consulting",
    "wof:placetype":"venue"
},
  "geometry": {"coordinates":[4.4202327728,50.7924423218],"type":"Point"}
}