{
  "type": "Feature",
  "properties": {
    "addr:full":"Gentse Steenweg 155 Zottegem Oost-Vlaanderen 9620",
    "addr:housenumber":"155",
    "addr:postcode":"9620",
    "addr:street":"Gentse Steenweg",
    "iso:country":"BE",
    "sg:address":"Gentse Steenweg 155",
    "sg:city":"Zottegem",
    "sg:classifiers":[
        {
            "category":"Arena",
            "subcategory":"Sports Club",
            "type":"Entertainment"
        }
    ],
    "sg:phone":"+32 9 360 32 88",
    "sg:postcode":"9620",
    "sg:province":"Oost-Vlaanderen",
    "sg:tags":[
        "terrain",
        "hors",
        "de",
        "installation",
        "sportifs"
    ],
    "wof:name":"Eendr. Grotenberge",
    "wof:placetype":"venue"
},
  "geometry": {"coordinates":[3.8335878849,50.8746757507],"type":"Point"}
}