{
  "type": "Feature",
  "properties": {
    "iso:country":"BE",
    "sg:address":"Zandakkerlaan 4",
    "sg:city":"Destelbergen",
    "sg:orig_category":"Banken and kredietinstellingen",
    "sg:phone":"+32 9 230 71 17",
    "sg:postcode":"9070",
    "sg:province":"Oost-Vlaanderen",
    "wof:name":"V.d.k. Spaarbank",
    "wof:placetype":"venue"
},
  "geometry": {"coordinates":[3.8023281097,51.0286140442],"type":"Point"}
}