{
  "type": "Feature",
  "properties": {
    "addr:full":"Rue Haymont 41 Namur (erpent) Namur 5101",
    "addr:housenumber":"41",
    "addr:postcode":"5101",
    "addr:street":"Rue Haymont",
    "iso:country":"BE",
    "sg:address":"Rue Haymont 41",
    "sg:city":"Namur (erpent)",
    "sg:classifiers":[
        {
            "category":"Real Estate",
            "subcategory":"Architect",
            "type":"Services"
        }
    ],
    "sg:phone":"+32 81 30 81 90",
    "sg:postcode":"5101",
    "sg:province":"Namur",
    "wof:name":"Dutrieux F",
    "wof:placetype":"venue"
},
  "geometry": {"coordinates":[4.907913208,50.4474258423],"type":"Point"}
}