{
  "type": "Feature",
  "properties": {
    "iso:country":"BE",
    "sg:address":"Nijverh. Begijnenmeers 37",
    "sg:city":"Liedekerke",
    "sg:classifiers":[
        {
            "category":"Manufacturing",
            "subcategory":"Chemicals & Compounds",
            "type":"Manufacturing & Wholesale Goods"
        }
    ],
    "sg:phone":"+32 53 66 21 42",
    "sg:postcode":"1770",
    "sg:province":"Vlaams-Brabant",
    "sg:tags":[
        "pharmaceutical",
        "chemistry",
        "-",
        "by-product"
    ],
    "wof:name":"Chemion Bvba",
    "wof:placetype":"venue"
},
  "geometry": {"coordinates":[4.0872578621,50.885433197],"type":"Point"}
}