{
  "type": "Feature",
  "properties": {
    "addr:full":"Laan Op Heusden 67 Beringen (koersel) Limburg 3582",
    "addr:housenumber":"67",
    "addr:postcode":"3582",
    "addr:street":"Laan Op Heusden",
    "iso:country":"BE",
    "sg:address":"Laan Op Heusden 67",
    "sg:city":"Beringen (koersel)",
    "sg:classifiers":[
        {
            "category":"Health Services",
            "subcategory":"Doctor",
            "type":"Services"
        }
    ],
    "sg:phone":"+32 11 42 80 81",
    "sg:postcode":"3582",
    "sg:province":"Limburg",
    "sg:tags":[
        "medicinephysicians",
        "surgeon"
    ],
    "wof:name":"Knuts D",
    "wof:placetype":"venue"
},
  "geometry": {"coordinates":[5.2708749771,51.0595359802],"type":"Point"}
}