{
  "type": "Feature",
  "properties": {
    "addr:full":"Pl Albert I 1 Sambreville Namur 5060",
    "addr:housenumber":"1",
    "addr:postcode":"5060",
    "addr:street":"Pl Albert I",
    "iso:country":"BE",
    "sg:address":"Pl Albert I 1",
    "sg:city":"Sambreville",
    "sg:classifiers":[
        {
            "category":"Cafe",
            "type":"Food & Drink"
        }
    ],
    "sg:phone":"+32 71 74 02 62",
    "sg:postcode":"5060",
    "sg:province":"Namur",
    "sg:tags":[
        "caf\u00e9s"
    ],
    "wof:name":"Caf\u00c9 Les Neuf Provinces",
    "wof:placetype":"venue"
},
  "geometry": {"coordinates":[4.6209888458,50.4187850952],"type":"Point"}
}