{
  "type": "Feature",
  "properties": {
    "iso:country":"BE",
    "sg:address":"Molenstraat 49",
    "sg:city":"Wetteren",
    "sg:orig_category":"Woningbouw",
    "sg:phone":"+32 9 369 57 58",
    "sg:postcode":"9230",
    "sg:province":"Oost-Vlaanderen",
    "wof:name":"De Wilde",
    "wof:placetype":"venue"
},
  "geometry": {"coordinates":[3.8881819248,51.005355835],"type":"Point"}
}