{
  "type": "Feature",
  "properties": {
    "iso:country":"BE",
    "sg:address":"Rue Ferrer 2-4",
    "sg:city":"Fleurus",
    "sg:orig_category":"Fournitures de bureau. Librairies. Journaux. Tabac",
    "sg:phone":"+32 71 81 19 68",
    "sg:postcode":"6224",
    "sg:province":"Hainaut",
    "wof:name":"A Lecolier",
    "wof:placetype":"venue"
},
  "geometry": {"coordinates":[4.5845551491,50.4668388367],"type":"Point"}
}