{
  "type": "Feature",
  "properties": {
    "addr:full":"Provinciale Steenweg 379 Schelle Antwerpen 2627",
    "addr:housenumber":"379",
    "addr:postcode":"2627",
    "addr:street":"Provinciale Steenweg",
    "iso:country":"BE",
    "sg:address":"Provinciale Steenweg 379",
    "sg:city":"Schelle",
    "sg:classifiers":[
        {
            "category":"Building & Trades",
            "subcategory":"Pest Control",
            "type":"Services"
        }
    ],
    "sg:phone":"+32 475 69 52 74",
    "sg:postcode":"2627",
    "sg:province":"Antwerpen",
    "sg:tags":[
        "machine",
        "vending"
    ],
    "wof:name":"Distrimats",
    "wof:placetype":"venue"
},
  "geometry": {"coordinates":[4.3348298073,51.1186828613],"type":"Point"}
}