{
  "type": "Feature",
  "properties": {
    "addr:full":"Mollestraat 20 Asse Vlaams-Brabant 1730",
    "addr:housenumber":"20",
    "addr:postcode":"1730",
    "addr:street":"Mollestraat",
    "iso:country":"BE",
    "sg:address":"Mollestraat 20",
    "sg:city":"Asse",
    "sg:orig_category":"Schoonheidssalons",
    "sg:phone":"+32 2 452 91 02",
    "sg:postcode":"1730",
    "sg:province":"Vlaams-Brabant",
    "wof:name":"Rosa Fieremans",
    "wof:placetype":"venue"
},
  "geometry": {"coordinates":[4.198445797,50.9125556946],"type":"Point"}
}