{
  "type": "Feature",
  "properties": {
    "iso:country":"BE",
    "sg:address":"Brieversweg 326",
    "sg:city":"Sint-kruis",
    "sg:orig_category":"Magasins sp\u00e9cialis\u00e9s",
    "sg:phone":"+32 50 35 31 46",
    "sg:postcode":"8310",
    "sg:province":"West-Vlaanderen",
    "wof:name":"Roger Van Dale",
    "wof:placetype":"venue"
},
  "geometry": {"coordinates":[3.2658200264,51.2125816345],"type":"Point"}
}