{
  "type": "Feature",
  "properties": {
    "addr:full":"Olivierstraat 43 Rotselaar Vlaams-Brabant 3111",
    "addr:housenumber":"43",
    "addr:postcode":"3111",
    "addr:street":"Olivierstraat",
    "iso:country":"BE",
    "sg:address":"Olivierstraat 43",
    "sg:city":"Rotselaar",
    "sg:orig_category":"Diverse organisaties and verenigingen",
    "sg:phone":"+32 16 44 49 14",
    "sg:postcode":"3111",
    "sg:province":"Vlaams-Brabant",
    "wof:name":"J.m.a. Wezemaal",
    "wof:placetype":"venue"
},
  "geometry": {"coordinates":[4.7577729225,50.9548416138],"type":"Point"}
}