{
  "type": "Feature",
  "properties": {
    "iso:country":"BE",
    "sg:address":"Rue D'alconval 31",
    "sg:city":"Braine L'alleud (braine-l'alleud)",
    "sg:classifiers":[
        {
            "category":"Professional",
            "subcategory":"Management & Consulting",
            "type":"Services"
        }
    ],
    "sg:phone":"+32 2 386 01 70",
    "sg:postcode":"1420",
    "sg:province":"Brabant Wallon",
    "sg:tags":[
        "consultant",
        "relation",
        "public"
    ],
    "wof:name":"Watson",
    "wof:placetype":"venue"
},
  "geometry": {"coordinates":[-75.60595703120001,37.7877616882],"type":"Point"}
}