{
  "type": "Feature",
  "properties": {
    "addr:full":"Kortrijkstraat 29 Tielt West-Vlaanderen 8700",
    "addr:housenumber":"29",
    "addr:postcode":"8700",
    "addr:street":"Kortrijkstraat",
    "iso:country":"BE",
    "sg:address":"Kortrijkstraat 29",
    "sg:city":"Tielt",
    "sg:orig_category":"Telecommunicatieapparaten",
    "sg:phone":"+32 800 22 800",
    "sg:postcode":"8700",
    "sg:province":"West-Vlaanderen",
    "wof:name":"Teleboetiek",
    "wof:placetype":"venue"
},
  "geometry": {"coordinates":[3.326654911,50.9987983704],"type":"Point"}
}