{
  "type": "Feature",
  "properties": {
    "addr:full":"Domstraat 52 Tremelo Vlaams-Brabant 3128",
    "addr:housenumber":"52",
    "addr:postcode":"3128",
    "addr:street":"Domstraat",
    "iso:country":"BE",
    "sg:address":"Domstraat 52",
    "sg:city":"Tremelo",
    "sg:classifiers":[
        {
            "category":"Insurance",
            "subcategory":"Insurance Agent",
            "type":"Services"
        }
    ],
    "sg:phone":"+32 16 53 22 99",
    "sg:postcode":"3128",
    "sg:province":"Vlaams-Brabant",
    "sg:tags":[
        "verzekeringsmakelaars",
        "expert"
    ],
    "wof:name":"Verhaegen",
    "wof:placetype":"venue"
},
  "geometry": {"coordinates":[4.7392568588,50.9883880615],"type":"Point"}
}