{
  "type": "Feature",
  "properties": {
    "addr:full":"Place Emile-de-lalieux 24 Nivelles Brabant Wallon 1400",
    "addr:housenumber":"24",
    "addr:postcode":"1400",
    "addr:street":"Place Emile-De-Lalieux",
    "iso:country":"BE",
    "sg:address":"Place Emile-de-lalieux 24",
    "sg:city":"Nivelles",
    "sg:classifiers":[
        {
            "category":"Cafe",
            "type":"Food & Drink"
        }
    ],
    "sg:phone":"+32 67 84 28 28",
    "sg:postcode":"1400",
    "sg:province":"Brabant Wallon",
    "sg:tags":[
        "caf\u00e9s"
    ],
    "wof:name":"Caf\u00c9 La Mandarine",
    "wof:placetype":"venue"
},
  "geometry": {"coordinates":[4.3282141685,50.5980911255],"type":"Point"}
}