{
  "type": "Feature",
  "properties": {
    "iso:country":"BE",
    "sg:address":"Kasteelstraat 1",
    "sg:city":"Ronse",
    "sg:classifiers":[
        {
            "category":"Fast Food",
            "type":"Food & Drink"
        }
    ],
    "sg:phone":"+32 55 20 74 83",
    "sg:postcode":"9600",
    "sg:province":"Oost-Vlaanderen",
    "sg:tags":[
        "meeneem",
        "restaurant"
    ],
    "wof:name":"Pita Pyramide",
    "wof:placetype":"venue"
},
  "geometry": {"coordinates":[3.5939199924,50.7470092773],"type":"Point"}
}