{
  "type": "Feature",
  "properties": {
    "iso:country":"BE",
    "sg:address":"Rue Matefosse 52",
    "sg:city":"Soumagne",
    "sg:orig_category":"Artsen and specialisten",
    "sg:phone":"+32 4 377 43 78",
    "sg:postcode":"4631",
    "sg:province":"Li\u00e8ge",
    "wof:name":"Christian Montrieux",
    "wof:placetype":"venue"
},
  "geometry": {"coordinates":[5.7049541473,50.6531028748],"type":"Point"}
}