{
  "type": "Feature",
  "properties": {
    "addr:full":"Poseidonlaan 1 Box 42 De Haan (wenduine) West-Vlaanderen 8420",
    "addr:housenumber":"1 box 42",
    "addr:postcode":"8420",
    "addr:street":"Poseidonlaan",
    "iso:country":"BE",
    "sg:address":"Poseidonlaan 1 Box 42",
    "sg:city":"De Haan (wenduine)",
    "sg:classifiers":[
        {
            "category":"Autos & Motor Vehicles",
            "subcategory":"Recreational Vehicle Sales",
            "type":"Retail Goods"
        }
    ],
    "sg:phone":"+32 50 41 39 11",
    "sg:postcode":"8420",
    "sg:province":"West-Vlaanderen",
    "sg:tags":[
        "caravan",
        "accessory"
    ],
    "wof:name":"Tackaert D",
    "wof:placetype":"venue"
},
  "geometry": {"coordinates":[3.1076319218,51.3035392761],"type":"Point"}
}