{
  "type": "Feature",
  "properties": {
    "addr:full":"Nieuwe Steenweg 210 De Haan (klemskerke) West-Vlaanderen 8420",
    "addr:housenumber":"210",
    "addr:postcode":"8420",
    "addr:street":"Nieuwe Steenweg",
    "iso:country":"BE",
    "sg:address":"Nieuwe Steenweg 210",
    "sg:city":"De Haan (klemskerke)",
    "sg:classifiers":[
        {
            "category":"Travel",
            "subcategory":"Hotels & Motels",
            "type":"Entertainment"
        }
    ],
    "sg:phone":"+32 59 23 57 77",
    "sg:postcode":"8420",
    "sg:province":"West-Vlaanderen",
    "wof:name":"Arcato (hotel)",
    "wof:placetype":"venue"
},
  "geometry": {"coordinates":[3.0334899426,51.2691116333],"type":"Point"}
}