{
  "type": "Feature",
  "properties": {
    "iso:country":"BE",
    "sg:address":"Planciusplein 8",
    "sg:city":"Heuvelland (dranouter)",
    "sg:classifiers":[
        {
            "category":"Bakery",
            "type":"Food & Drink"
        }
    ],
    "sg:phone":"+32 57 44 62 00",
    "sg:postcode":"8951",
    "sg:province":"West-Vlaanderen",
    "sg:tags":[
        "confectioner",
        "baker"
    ],
    "wof:name":"Poissonnier G",
    "wof:placetype":"venue"
},
  "geometry": {"coordinates":[2.7828159332,50.7658805847],"type":"Point"}
}