{
  "type": "Feature",
  "properties": {
    "addr:full":"Dr\u00e8ve Gustave Fache 1 Mouscron (luingne) Hainaut 7700",
    "addr:housenumber":"1",
    "addr:postcode":"7700",
    "addr:street":"Dre\u0300Ve Gustave Fache",
    "iso:country":"BE",
    "sg:address":"Dr\u00e8ve Gustave Fache 1",
    "sg:city":"Mouscron (luingne)",
    "sg:classifiers":[
        {
            "category":"Airport",
            "subcategory":"General Aviation",
            "type":"Transportation"
        }
    ],
    "sg:phone":"+32 56 85 25 26",
    "sg:postcode":"7700",
    "sg:province":"Hainaut",
    "sg:tags":[
        "transport"
    ],
    "wof:name":"Ats",
    "wof:placetype":"venue"
},
  "geometry": {"coordinates":[3.2145800591,50.7437934875],"type":"Point"}
}