{
  "type": "Feature",
  "properties": {
    "addr:full":"O.-l.-vrouwemarkt 2 Roeselare West-Vlaanderen 8800",
    "addr:housenumber":"2",
    "addr:postcode":"8800",
    "addr:street":"O.-L.-Vrouwemarkt",
    "iso:country":"BE",
    "sg:address":"O.-l.-vrouwemarkt 2",
    "sg:city":"Roeselare",
    "sg:orig_category":"Imprimeries and copyshops. Etudes techniques and ing\u00e9nierie",
    "sg:phone":"+32 51 22 26 66",
    "sg:postcode":"8800",
    "sg:province":"West-Vlaanderen",
    "wof:name":"Alfa-studie-home",
    "wof:placetype":"venue"
},
  "geometry": {"coordinates":[3.1224160194,50.9445381165],"type":"Point"}
}