{
  "type": "Feature",
  "properties": {
    "iso:country":"BE",
    "sg:address":"Zandvleuge 144",
    "sg:city":"Eeklo",
    "sg:orig_category":"Eleveurs and marchands de porcs. Eleveurs de bovins",
    "sg:phone":"+32 9 377 68 86",
    "sg:postcode":"9900",
    "sg:province":"Oost-Vlaanderen",
    "wof:name":"Gerrit Dobbelaere",
    "wof:placetype":"venue"
},
  "geometry": {"coordinates":[3.55885005,51.1929016113],"type":"Point"}
}