{
  "type": "Feature",
  "properties": {
    "addr:full":"Veldstraat 41 Laakdal Antwerpen 2430",
    "addr:housenumber":"41",
    "addr:postcode":"2430",
    "addr:street":"Veldstraat",
    "iso:country":"BE",
    "sg:address":"Veldstraat 41",
    "sg:city":"Laakdal",
    "sg:orig_category":"Sportclubs Sportterreinen and installaties behalve sportcentra",
    "sg:phone":"+32 13 66 69 48",
    "sg:postcode":"2430",
    "sg:province":"Antwerpen",
    "wof:name":"K.f.c. Standaard Vorst",
    "wof:placetype":"venue"
},
  "geometry": {"coordinates":[5.0164289474,51.07837677],"type":"Point"}
}