{
  "type": "Feature",
  "properties": {
    "addr:full":"Kraaienhoflaan 44 Zwijndrecht Antwerpen 2070",
    "addr:housenumber":"44",
    "addr:postcode":"2070",
    "addr:street":"Kraaienhoflaan",
    "iso:country":"BE",
    "sg:address":"Kraaienhoflaan 44",
    "sg:city":"Zwijndrecht",
    "sg:orig_category":"Experts-comptables",
    "sg:phone":"+32 3 252 95 38",
    "sg:postcode":"2070",
    "sg:province":"Antwerpen",
    "wof:name":"Willy De Vos",
    "wof:placetype":"venue"
},
  "geometry": {"coordinates":[4.3448958397,51.2092704773],"type":"Point"}
}