{
  "type": "Feature",
  "properties": {
    "iso:country":"BE",
    "sg:address":"Sint-barbarastraat 45",
    "sg:city":"Diepenbeek",
    "sg:classifiers":[
        {
            "category":"Retail",
            "subcategory":"Auto Repair",
            "type":"Services"
        }
    ],
    "sg:phone":"+32 11 32 31 79",
    "sg:postcode":"3590",
    "sg:province":"Limburg",
    "sg:tags":[
        "automobile",
        "-",
        "wrecking"
    ],
    "wof:name":"Haesevoets Autopark",
    "wof:placetype":"venue"
},
  "geometry": {"coordinates":[5.4460420609,50.92786026],"type":"Point"}
}