{
  "type": "Feature",
  "properties": {
    "addr:full":"Velle 59 Temse Oost-Vlaanderen 9140",
    "addr:housenumber":"59",
    "addr:postcode":"9140",
    "addr:street":"Velle",
    "iso:country":"BE",
    "sg:address":"Velle 59",
    "sg:city":"Temse",
    "sg:orig_category":"Installation de menuiserie en bois and plastique",
    "sg:phone":"+32 3 771 20 67",
    "sg:postcode":"9140",
    "sg:province":"Oost-Vlaanderen",
    "wof:name":"Andre Vercauteren",
    "wof:placetype":"venue"
},
  "geometry": {"coordinates":[4.205701828,51.1591377258],"type":"Point"}
}