{
  "type": "Feature",
  "properties": {
    "addr:full":"Middelmolenlaan 94-96 Deurne Antwerpen 2100",
    "addr:postcode":"94-96;2100",
    "addr:street":"Middelmolenlaan",
    "iso:country":"BE",
    "sg:address":"Middelmolenlaan 94-96",
    "sg:city":"Deurne",
    "sg:orig_category":"Installation de menuiserie en bois and plastique. Construction de maisons",
    "sg:phone":"+32 3 324 44 33",
    "sg:postcode":"2100",
    "sg:province":"Antwerpen",
    "wof:name":"Alg. Bouwwerken Simons & Zoon",
    "wof:placetype":"venue"
},
  "geometry": {"coordinates":[4.4727478027,51.2364006042],"type":"Point"}
}