{
  "type": "Feature",
  "properties": {
    "addr:full":"Generaal De Wittelaan 9 Mechelen Antwerpen 2800",
    "addr:housenumber":"9",
    "addr:postcode":"2800",
    "addr:street":"Generaal De Wittelaan",
    "iso:country":"BE",
    "sg:address":"Generaal De Wittelaan 9",
    "sg:city":"Mechelen",
    "sg:classifiers":[
        {
            "category":"Banks & Credit Unions",
            "subcategory":"Investment Brokerage",
            "type":"Services"
        }
    ],
    "sg:phone":"+32 15 29 33 90",
    "sg:postcode":"2800",
    "sg:province":"Antwerpen",
    "wof:name":"Winx Capital House Nv",
    "wof:placetype":"venue"
},
  "geometry": {"coordinates":[4.4518809319,51.0549049377],"type":"Point"}
}