{
  "type": "Feature",
  "properties": {
    "addr:full":"Brusselstraat 474 Dilbeek Vlaams-Brabant 1702",
    "addr:housenumber":"474",
    "addr:postcode":"1702",
    "addr:street":"Brusselstraat",
    "iso:country":"BE",
    "sg:address":"Brusselstraat 474",
    "sg:city":"Dilbeek",
    "sg:orig_category":"Mat\u00e9riel m\u00e9dical and orthop\u00e9dique and proth\u00e8ses Fab",
    "sg:phone":"+32 2 463 15 74",
    "sg:postcode":"1702",
    "sg:province":"Vlaams-Brabant",
    "wof:name":"Bernard Kerkhove",
    "wof:placetype":"venue"
},
  "geometry": {"coordinates":[4.2434668541,50.8743782043],"type":"Point"}
}