{
  "type": "Feature",
  "properties": {
    "iso:country":"BE",
    "sg:address":"Wilsonstraat 28ba",
    "sg:city":"Sint-katelijne-waver",
    "sg:orig_category":"Cr\u00e8ches and garderies d'enfants",
    "sg:phone":"+32 15 32 00 91",
    "sg:postcode":"2860",
    "sg:province":"Antwerpen",
    "wof:name":"Kinderopvangdienst",
    "wof:placetype":"venue"
},
  "geometry": {"coordinates":[4.5346307755,51.0728034973],"type":"Point"}
}