{
  "type": "Feature",
  "properties": {
    "iso:country":"BE",
    "sg:address":"Grote Heerweg 171",
    "sg:city":"Waregem",
    "sg:orig_category":"Binnenhuisarchitecten Meubelzaken, woning- and keukeninrichting",
    "sg:phone":"+32 56 71 45 25",
    "sg:postcode":"8791",
    "sg:province":"West-Vlaanderen",
    "wof:name":"Krive",
    "wof:placetype":"venue"
},
  "geometry": {"coordinates":[3.3394219875,50.8811302185],"type":"Point"}
}