{
  "type": "Feature",
  "properties": {
    "addr:full":"Gare Autoroutiere La Louviere Hainaut 7110",
    "addr:postcode":"7110",
    "iso:country":"BE",
    "sg:address":"Gare Autoroutiere",
    "sg:city":"La Louviere",
    "sg:orig_category":"Openbare bibliotheken and archieven",
    "sg:phone":"+32 64 26 29 54",
    "sg:postcode":"7110",
    "sg:province":"Hainaut",
    "wof:name":"Centrale Provinciale Du Hainaut",
    "wof:placetype":"venue"
},
  "geometry": {"coordinates":[4.1505050659,50.4826698303],"type":"Point"}
}