{
  "type": "Feature",
  "properties": {
    "addr:full":"Kleitkalseide 57ba1 Maldegem Oost-Vlaanderen 9990",
    "addr:postcode":"9990",
    "addr:street":"Oost-Vlaanderen",
    "iso:country":"BE",
    "sg:address":"Kleitkalseide 57ba1",
    "sg:city":"Maldegem",
    "sg:orig_category":"Banken and kredietinstellingen",
    "sg:phone":"+32 50 71 42 73",
    "sg:postcode":"9990",
    "sg:province":"Oost-Vlaanderen",
    "wof:name":"Landbouwkrediet",
    "wof:placetype":"venue"
},
  "geometry": {"coordinates":[3.4534299374,51.1875991821],"type":"Point"}
}