{
  "type": "Feature",
  "properties": {
    "iso:country":"BE",
    "sg:address":"Van Arteveldestraat 58",
    "sg:city":"Antwerpen",
    "sg:classifiers":[
        {
            "category":"Bars & Pubs",
            "type":"Food & Drink"
        }
    ],
    "sg:phone":"+32 3 475 29 61",
    "sg:postcode":"2060",
    "sg:province":"Antwerpen",
    "wof:name":"Ba M",
    "wof:placetype":"venue"
},
  "geometry": {"coordinates":[4.4201002121,51.220954895],"type":"Point"}
}