{
  "type": "Feature",
  "properties": {
    "addr:full":"Roodbos 35 Voeren/fourons Limburg 3791",
    "addr:housenumber":"35",
    "addr:postcode":"3791",
    "addr:street":"Roodbos",
    "iso:country":"BE",
    "sg:address":"Roodbos 35",
    "sg:city":"Voeren/fourons",
    "sg:orig_category":"Kampeerterreinen Restaurants Sportterreinen and installaties behalve sportcentra",
    "sg:phone":"+32 4 381 01 76",
    "sg:postcode":"3791",
    "sg:province":"Limburg",
    "wof:name":"Hacienda",
    "wof:placetype":"venue"
},
  "geometry": {"coordinates":[5.8673157692,50.7290534973],"type":"Point"}
}