{
  "type": "Feature",
  "properties": {
    "iso:country":"BE",
    "sg:address":"Rue D'assaut 2",
    "sg:city":"Charleroi",
    "sg:classifiers":[
        {
            "category":"Education",
            "subcategory":"Dance Studio",
            "type":"Public Place"
        }
    ],
    "sg:phone":"+32 71 31 48 30",
    "sg:postcode":"6000",
    "sg:province":"Hainaut",
    "sg:tags":[
        "ballet",
        "school"
    ],
    "wof:name":"Savouret A",
    "wof:placetype":"venue"
},
  "geometry": {"coordinates":[4.4443669319,50.4160881042],"type":"Point"}
}