{
  "type": "Feature",
  "properties": {
    "addr:full":"Avenue Des H\u00e9liotropes 35 Bruxelles (schaerbeek) Bruxelles-Capitale 1030",
    "addr:housenumber":"35",
    "addr:postcode":"1030",
    "addr:street":"Avenue Des He\u0301Liotropes",
    "iso:country":"BE",
    "sg:address":"Avenue Des H\u00e9liotropes 35",
    "sg:city":"Bruxelles (schaerbeek)",
    "sg:classifiers":[
        {
            "category":"Travel",
            "subcategory":"Hotels & Motels",
            "type":"Entertainment"
        }
    ],
    "sg:phone":"+32 2 247 08 11",
    "sg:postcode":"1030",
    "sg:province":"Bruxelles-Capitale",
    "wof:name":"Flathotel Lambertmont",
    "wof:placetype":"venue"
},
  "geometry": {"coordinates":[4.3896360397,50.8640785217],"type":"Point"}
}