{
  "type": "Feature",
  "properties": {
    "addr:full":"Rue Albert I 1 Tournai (rumillies - Mourcourt) Hainaut 7540",
    "addr:housenumber":"1",
    "addr:postcode":"7540",
    "addr:street":"Rue Albert I;Hainaut",
    "iso:country":"BE",
    "sg:address":"Rue Albert I 1",
    "sg:city":"Tournai (rumillies - Mourcourt)",
    "sg:classifiers":[
        {
            "category":"Bakery",
            "type":"Food & Drink"
        }
    ],
    "sg:postcode":"7540",
    "sg:province":"Hainaut",
    "sg:tags":[
        "confectioner",
        "baker"
    ],
    "wof:name":"Maes",
    "wof:placetype":"venue"
},
  "geometry": {"coordinates":[3.389480114,50.6276397705],"type":"Point"}
}