{
  "type": "Feature",
  "properties": {
    "iso:country":"BE",
    "sg:address":"Ballonssteenweg 445",
    "sg:city":"Moeskroen/mouscron",
    "sg:orig_category":"Groenten and fruit Gh",
    "sg:phone":"+32 56 33 32 70",
    "sg:postcode":"7712",
    "sg:province":"Hainaut",
    "wof:name":"Werner Vergote",
    "wof:placetype":"venue"
},
  "geometry": {"coordinates":[3.2179059982,50.7151756287],"type":"Point"}
}