{
  "type": "Feature",
  "properties": {
    "addr:full":"Javanastraat 97 Maaseik Limburg 3680",
    "addr:housenumber":"97",
    "addr:postcode":"3680",
    "addr:street":"Javanastraat",
    "iso:country":"BE",
    "sg:address":"Javanastraat 97",
    "sg:city":"Maaseik",
    "sg:orig_category":"Video-Equipment - Mainten. and Repair",
    "sg:phone":"+32 89 56 31 37",
    "sg:postcode":"3680",
    "sg:province":"Limburg",
    "wof:name":"Bruninx J",
    "wof:placetype":"venue"
},
  "geometry": {"coordinates":[5.7937321663,51.1090316772],"type":"Point"}
}