{
  "type": "Feature",
  "properties": {
    "iso:country":"BE",
    "sg:address":"Rue Basse Pr\u00c9alle 115",
    "sg:city":"Herstal",
    "sg:orig_category":"Enseignement maternel and primaire",
    "sg:phone":"+32 4 264 19 39",
    "sg:postcode":"4040",
    "sg:province":"Li\u00e8ge",
    "wof:name":"Ecole Primaire Libre",
    "wof:placetype":"venue"
},
  "geometry": {"coordinates":[5.6123828888,50.6659126282],"type":"Point"}
}