{
  "type": "Feature",
  "properties": {
    "addr:full":"Rue Des Bl\u00c9s 50 Attert Luxembourg 6717",
    "addr:housenumber":"50",
    "addr:postcode":"6717",
    "addr:street":"Rue Des Ble\u0301S",
    "iso:country":"BE",
    "sg:address":"Rue Des Bl\u00c9s 50",
    "sg:city":"Attert",
    "sg:orig_category":"Herstellingen and onderhoud van auto's",
    "sg:phone":"+32 475 68 43 43",
    "sg:postcode":"6717",
    "sg:province":"Luxembourg",
    "wof:name":"Jean-louis Meyer",
    "wof:placetype":"venue"
},
  "geometry": {"coordinates":[5.7557058334,49.7663803101],"type":"Point"}
}