{
  "type": "Feature",
  "properties": {
    "iso:country":"BE",
    "sg:address":"59",
    "sg:city":"Schrieksebaan 3120 Tremelo",
    "sg:classifiers":[
        {
            "category":"Travel",
            "subcategory":"Hotels & Motels",
            "type":"Entertainment"
        }
    ],
    "sg:phone":"+32 16 53 77 38",
    "sg:postcode":"59",
    "sg:tags":[
        "hotels",
        "business",
        "restaurant"
    ],
    "wof:name":"Gekko Bvba",
    "wof:placetype":"venue"
},
  "geometry": {"coordinates":[4.7082839012,51.0072402954],"type":"Point"}
}