{
  "type": "Feature",
  "properties": {
    "addr:full":"Beverlosesteenweg 455 Beringen Limburg 3583",
    "addr:housenumber":"455",
    "addr:postcode":"3583",
    "addr:street":"Beverlosesteenweg",
    "iso:country":"BE",
    "sg:address":"Beverlosesteenweg 455",
    "sg:city":"Beringen",
    "sg:orig_category":"Enseignement maternel and primaire",
    "sg:phone":"+32 11 42 82 92",
    "sg:postcode":"3583",
    "sg:province":"Limburg",
    "wof:name":"Vrije Basisschool",
    "wof:placetype":"venue"
},
  "geometry": {"coordinates":[5.2085199356,51.0692901611],"type":"Point"}
}