{
  "type": "Feature",
  "properties": {
    "addr:full":"Zandvoordestraat 268a Oostende West-Vlaanderen 8400",
    "addr:housenumber":"268a",
    "addr:postcode":"8400",
    "addr:street":"Zandvoordestraat",
    "iso:country":"BE",
    "sg:address":"Zandvoordestraat 268a",
    "sg:city":"Oostende",
    "sg:orig_category":"Installation \u00e9lectrique r\u00e9sidentielle",
    "sg:phone":"+32 59 50 63 53",
    "sg:postcode":"8400",
    "sg:province":"West-Vlaanderen",
    "wof:name":"Soreyn Joris",
    "wof:placetype":"venue"
},
  "geometry": {"coordinates":[2.9468500614,51.2129516602],"type":"Point"}
}