{
  "type": "Feature",
  "properties": {
    "iso:country":"BE",
    "sg:address":"Rue De Bayemont 28ba",
    "sg:city":"Charleroi",
    "sg:orig_category":"Bloemen and planten",
    "sg:phone":"+32 71 31 69 37",
    "sg:postcode":"6040",
    "sg:province":"Hainaut",
    "wof:name":"Paolo Antonacci",
    "wof:placetype":"venue"
},
  "geometry": {"coordinates":[4.4096250534,50.4302482605],"type":"Point"}
}