{
  "type": "Feature",
  "properties": {
    "addr:full":"Brenjerstraat 2 Kinrooi Limburg 3640",
    "addr:housenumber":"2",
    "addr:postcode":"3640",
    "addr:street":"Brenjerstraat",
    "iso:country":"BE",
    "sg:address":"Brenjerstraat 2",
    "sg:city":"Kinrooi",
    "sg:classifiers":[
        {
            "category":"Building & Trades",
            "subcategory":"Construction",
            "type":"Services"
        }
    ],
    "sg:phone":"+32 89 86 17 31",
    "sg:postcode":"3640",
    "sg:province":"Limburg",
    "sg:tags":[
        "stair"
    ],
    "wof:name":"Vanderheyden",
    "wof:placetype":"venue"
},
  "geometry": {"coordinates":[5.7367758751,51.1366920471],"type":"Point"}
}