{
  "type": "Feature",
  "properties": {
    "addr:full":"Schaapsdreef 8b Wingene West-Vlaanderen 8750",
    "addr:housenumber":"8b",
    "addr:postcode":"8750",
    "addr:street":"Schaapsdreef",
    "iso:country":"BE",
    "sg:address":"Schaapsdreef 8b",
    "sg:city":"Wingene",
    "sg:classifiers":[
        {
            "category":"Government",
            "subcategory":"Department Of Motor Vehicles",
            "type":"Public Place"
        }
    ],
    "sg:phone":"+32 51 65 75 41",
    "sg:postcode":"8750",
    "sg:province":"West-Vlaanderen",
    "sg:tags":[
        "planing",
        "wood",
        "sawing"
    ],
    "wof:name":"Oosterlinck",
    "wof:placetype":"venue"
},
  "geometry": {"coordinates":[3.2920570374,51.078994751],"type":"Point"}
}