{
  "type": "Feature",
  "properties": {
    "addr:full":"P Vinckestraat 52 Kuurne West-Vlaanderen 8520",
    "addr:housenumber":"52",
    "addr:postcode":"8520",
    "addr:street":"P Vinckestraat",
    "iso:country":"BE",
    "sg:address":"P Vinckestraat 52",
    "sg:city":"Kuurne",
    "sg:orig_category":"Verlichting and huishoudartikelen",
    "sg:phone":"+32 56 37 08 32",
    "sg:postcode":"8520",
    "sg:province":"West-Vlaanderen",
    "wof:name":"Castel-decor",
    "wof:placetype":"venue"
},
  "geometry": {"coordinates":[3.2583110332,50.8710861206],"type":"Point"}
}