{
  "type": "Feature",
  "properties": {
    "iso:country":"BE",
    "sg:address":"Rue Hazinelle 10",
    "sg:city":"Li\u00c8ge",
    "sg:orig_category":"Kapsalons",
    "sg:phone":"+32 4 222 02 81",
    "sg:postcode":"4000",
    "sg:province":"Li\u00e8ge",
    "wof:name":"Coiffure Sculpt\u00b4hair",
    "wof:placetype":"venue"
},
  "geometry": {"coordinates":[5.5691270828,50.6396560669],"type":"Point"}
}