{
  "type": "Feature",
  "properties": {
    "iso:country":"BE",
    "sg:address":"Koning-albertlaan 196",
    "sg:city":"Lochristi",
    "sg:orig_category":"Plaatsen van vloer- and muurbekleding Schilders",
    "sg:phone":"+32 9 355 64 10",
    "sg:postcode":"9080",
    "sg:province":"Oost-Vlaanderen",
    "wof:name":"Eliano-de Wispelaere",
    "wof:placetype":"venue"
},
  "geometry": {"coordinates":[3.8156421185,51.1095352173],"type":"Point"}
}