{
  "type": "Feature",
  "properties": {
    "addr:full":"Rue De La Grattine 6 La Louviere Hainaut 7100",
    "addr:housenumber":"6",
    "addr:postcode":"7100",
    "addr:street":"Rue De La Grattine",
    "iso:country":"BE",
    "sg:address":"Rue De La Grattine 6",
    "sg:city":"La Louviere",
    "sg:orig_category":"Diepvriesproducten Gh",
    "sg:phone":"+32 64 26 01 83",
    "sg:postcode":"7100",
    "sg:province":"Hainaut",
    "wof:name":"Covee",
    "wof:placetype":"venue"
},
  "geometry": {"coordinates":[4.2020101547,50.4837913513],"type":"Point"}
}