{
  "type": "Feature",
  "properties": {
    "iso:country":"BE",
    "sg:address":"St.truidensesteenweg 392",
    "sg:city":"Hoepertingen",
    "sg:orig_category":"Huisdieren and benodigdheden",
    "sg:phone":"+32 12 74 25 87",
    "sg:postcode":"3840",
    "sg:province":"Limburg",
    "wof:name":"Bex-claus",
    "wof:placetype":"venue"
},
  "geometry": {"coordinates":[5.2878289223,50.8066978455],"type":"Point"}
}