{
  "type": "Feature",
  "properties": {
    "addr:full":"Blauwe Paal 51 Wetteren Oost-Vlaanderen 9230",
    "addr:housenumber":"51",
    "addr:postcode":"9230",
    "addr:street":"Blauwe Paal",
    "iso:country":"BE",
    "sg:address":"Blauwe Paal 51",
    "sg:city":"Wetteren",
    "sg:orig_category":"Herstellingen and onderhoud van auto's",
    "sg:phone":"+32 9 368 08 44",
    "sg:postcode":"9230",
    "sg:province":"Oost-Vlaanderen",
    "wof:name":"Ludo Mercie",
    "wof:placetype":"venue"
},
  "geometry": {"coordinates":[3.853730917,50.9872970581],"type":"Point"}
}