{
  "type": "Feature",
  "properties": {
    "iso:country":"BE",
    "sg:address":"Leffingestraat 297",
    "sg:city":"Oostende",
    "sg:orig_category":"Electrom\u00e9nager, t\u00e9l\u00e9visions and radios. Eclairage et \u00e9quipements du foyer. R\u00e9parations d'appareils \u00e9",
    "sg:phone":"+32 59 80 18 21",
    "sg:postcode":"8400",
    "sg:province":"West-Vlaanderen",
    "wof:name":"E.l.g.b.",
    "wof:placetype":"venue"
},
  "geometry": {"coordinates":[2.9003410339,51.2150611877],"type":"Point"}
}