{
  "type": "Feature",
  "properties": {
    "iso:country":"BE",
    "sg:address":"Oberhausen 2ba",
    "sg:city":"Burg-reuland/burg-reuland",
    "sg:orig_category":"Rundveehouders",
    "sg:phone":"+32 80 32 90 66",
    "sg:postcode":"4790",
    "sg:province":"Li\u00e8ge",
    "wof:name":"Anton Wangen",
    "wof:placetype":"venue"
},
  "geometry": {"coordinates":[6.1390500069,50.1560401917],"type":"Point"}
}