{
  "type": "Feature",
  "properties": {
    "iso:country":"BE",
    "sg:address":"Place Du W\u00c9rixhet 20",
    "sg:city":"Fleron",
    "sg:orig_category":"Slagers",
    "sg:phone":"+32 4 358 34 49",
    "sg:postcode":"4620",
    "sg:province":"Li\u00e8ge",
    "wof:name":"Joseph Goffard",
    "wof:placetype":"venue"
},
  "geometry": {"coordinates":[5.6867718697,50.6205673218],"type":"Point"}
}