{
  "type": "Feature",
  "properties": {
    "addr:full":"Kelestraat 49 Asse Vlaams-Brabant 1730",
    "addr:housenumber":"49",
    "addr:postcode":"1730",
    "addr:street":"Kelestraat",
    "iso:country":"BE",
    "sg:address":"Kelestraat 49",
    "sg:city":"Asse",
    "sg:classifiers":[
        {
            "category":"Transit Center",
            "subcategory":"Freight",
            "type":"Transportation"
        }
    ],
    "sg:phone":"+32 2 453 93 19",
    "sg:postcode":"1730",
    "sg:province":"Vlaams-Brabant",
    "sg:tags":[
        "import",
        "export",
        "-"
    ],
    "wof:name":"Jarour Trading",
    "wof:placetype":"venue"
},
  "geometry": {"coordinates":[4.1852068901,50.9208259583],"type":"Point"}
}