{
  "type": "Feature",
  "properties": {
    "iso:country":"BE",
    "sg:address":"Rue Louis De Brouck\u00e8re 72",
    "sg:city":"La Louvi\u00e8re",
    "sg:classifiers":[
        {
            "category":"Shopping",
            "subcategory":"Stationery & Office Supplies",
            "type":"Retail Goods"
        }
    ],
    "sg:phone":"+32 64 22 22 96",
    "sg:postcode":"7100",
    "sg:province":"Hainaut",
    "wof:name":"Carlier B",
    "wof:placetype":"venue"
},
  "geometry": {"coordinates":[4.1910190582,50.4800071716],"type":"Point"}
}