{
  "type": "Feature",
  "properties": {
    "addr:full":"Avenue Paul Pastur 217 Charleroi Hainaut 6032",
    "addr:housenumber":"217",
    "addr:postcode":"6032",
    "addr:street":"Avenue Paul Pastur;Hainaut",
    "iso:country":"BE",
    "sg:address":"Avenue Paul Pastur 217",
    "sg:city":"Charleroi",
    "sg:classifiers":[
        {
            "category":"Personal",
            "subcategory":"Beauty Salon",
            "type":"Services"
        }
    ],
    "sg:phone":"+32 71 43 11 54",
    "sg:postcode":"6032",
    "sg:province":"Hainaut",
    "sg:tags":[
        "de",
        "coiffure"
    ],
    "wof:name":"Top Coiffure",
    "wof:placetype":"venue"
},
  "geometry": {"coordinates":[4.4137878418,50.3934669495],"type":"Point"}
}