{
  "type": "Feature",
  "properties": {
    "addr:full":"Rijksweg 542 Maasmechelen Limburg 3630",
    "addr:housenumber":"542",
    "addr:postcode":"3630",
    "addr:street":"Rijksweg",
    "iso:country":"BE",
    "sg:address":"Rijksweg 542",
    "sg:city":"Maasmechelen",
    "sg:classifiers":[
        {
            "category":"Autos & Motor Vehicles",
            "subcategory":"Fuel & Gas Station",
            "type":"Retail Goods"
        }
    ],
    "sg:phone":"+32 89 76 00 30",
    "sg:postcode":"3630",
    "sg:province":"Limburg",
    "sg:tags":[
        "stations-service",
        "carburants"
    ],
    "wof:name":"Texaco",
    "wof:placetype":"venue"
},
  "geometry": {"coordinates":[5.6942400932,50.956161499],"type":"Point"}
}