{
  "type": "Feature",
  "properties": {
    "iso:country":"BE",
    "sg:address":"Avenue De Wezembeek 66",
    "sg:city":"Kraainem/kraainem",
    "sg:orig_category":"Fleurs and plantes",
    "sg:phone":"+32 2 305 31 80",
    "sg:postcode":"1950",
    "sg:province":"Vlaams-Brabant",
    "wof:name":"Equateur Flowers",
    "wof:placetype":"venue"
},
  "geometry": {"coordinates":[4.4656038284,50.8484535217],"type":"Point"}
}