{
  "type": "Feature",
  "properties": {
    "addr:full":"Ninoofsesteenweg 90 Lennik (sint-kwintens-lennik) Vlaams-Brabant 1750",
    "addr:housenumber":"90",
    "addr:postcode":"1750",
    "addr:street":"Ninoofsesteenweg",
    "iso:country":"BE",
    "sg:address":"Ninoofsesteenweg 90",
    "sg:city":"Lennik (sint-kwintens-lennik)",
    "sg:classifiers":[
        {
            "category":"Building & Trades",
            "subcategory":"Construction",
            "type":"Services"
        }
    ],
    "sg:phone":"+32 2 581 01 57",
    "sg:postcode":"1750",
    "sg:province":"Vlaams-Brabant",
    "sg:tags":[
        "glazier"
    ],
    "wof:name":"Chantraine",
    "wof:placetype":"venue"
},
  "geometry": {"coordinates":[4.1463189125,50.8348503113],"type":"Point"}
}