{
  "type": "Feature",
  "properties": {
    "iso:country":"BE",
    "sg:address":"Kapellestraat 234",
    "sg:city":"Aartselaar",
    "sg:classifiers":[
        {
            "category":"Retail",
            "subcategory":"Veterinary Services",
            "type":"Services"
        }
    ],
    "sg:phone":"+32 3 887 88 18",
    "sg:postcode":"2630",
    "sg:province":"Antwerpen",
    "sg:tags":[
        "veterinarian"
    ],
    "wof:name":"Van Rompaey Th",
    "wof:placetype":"venue"
},
  "geometry": {"coordinates":[4.3890018463,51.125453949],"type":"Point"}
}