{
  "type": "Feature",
  "properties": {
    "addr:full":"Rue D'audregnies 73 P\u00e9ruwelz (wiers) Hainaut 7608",
    "addr:housenumber":"73",
    "addr:postcode":"7608",
    "addr:street":"Rue D'Audregnies",
    "iso:country":"BE",
    "sg:address":"Rue D'audregnies 73",
    "sg:city":"P\u00e9ruwelz (wiers)",
    "sg:classifiers":[
        {
            "category":"Retail",
            "subcategory":"Repair Shop",
            "type":"Services"
        }
    ],
    "sg:phone":"+32 69 77 64 03",
    "sg:postcode":"7608",
    "sg:province":"Hainaut",
    "sg:tags":[
        "jobbing",
        "tailoring",
        "-"
    ],
    "wof:name":"Marigot H",
    "wof:placetype":"venue"
},
  "geometry": {"coordinates":[3.5172219276,50.5101661682],"type":"Point"}
}