{
  "type": "Feature",
  "properties": {
    "addr:full":"Achter Het Dorp 10 Linter Vlaams-Brabant 3350",
    "addr:housenumber":"10",
    "addr:postcode":"3350",
    "addr:street":"Achter Het Dorp;Vlaams-Brabant",
    "iso:country":"BE",
    "sg:address":"Achter Het Dorp 10",
    "sg:city":"Linter",
    "sg:orig_category":"Entretien and r\u00e9parations de voitures",
    "sg:phone":"+32 16 78 85 00",
    "sg:postcode":"3350",
    "sg:province":"Vlaams-Brabant",
    "wof:name":"Alphonse Courtois",
    "wof:placetype":"venue"
},
  "geometry": {"coordinates":[5.0506591797,50.7910270691],"type":"Point"}
}