{
  "type": "Feature",
  "properties": {
    "iso:country":"BE",
    "sg:address":"Avenue De Fr\u00e9 96 Box 2",
    "sg:city":"Bruxelles (uccle)",
    "sg:classifiers":[
        {
            "category":"Health Services",
            "subcategory":"Dentist",
            "type":"Services"
        }
    ],
    "sg:phone":"+32 478 27 18 78",
    "sg:postcode":"1180",
    "sg:province":"Bruxelles-Capitale",
    "wof:name":"Mahieu M",
    "wof:placetype":"venue"
},
  "geometry": {"coordinates":[4.3578119278,50.8043136597],"type":"Point"}
}