{
  "type": "Feature",
  "properties": {
    "addr:full":"De Beaulieulaan 12b12 Oudergem/auderghem Bruxelles-Capitale 1160",
    "addr:housenumber":"12b12",
    "addr:postcode":"1160",
    "addr:street":"De Beaulieulaan;/",
    "iso:country":"BE",
    "sg:address":"De Beaulieulaan 12b12",
    "sg:city":"Oudergem/auderghem",
    "sg:orig_category":"Advocaten and juridische adviseurs",
    "sg:phone":"+32 2 662 21 41",
    "sg:postcode":"1160",
    "sg:province":"Bruxelles-Capitale",
    "wof:name":"A. Merckx",
    "wof:placetype":"venue"
},
  "geometry": {"coordinates":[4.4133148193,50.8139648438],"type":"Point"}
}