{
  "type": "Feature",
  "properties": {
    "iso:country":"BE",
    "sg:address":"Rue Delbory 5",
    "sg:city":"Saint-ghislain (hautrage)",
    "sg:classifiers":[
        {
            "category":"Social Services",
            "type":"Services"
        }
    ],
    "sg:phone":"+32 65 62 03 87",
    "sg:postcode":"7334",
    "sg:province":"Hainaut",
    "wof:name":"Chez Nous Asbl",
    "wof:placetype":"venue"
},
  "geometry": {"coordinates":[3.7644500732,50.479675293],"type":"Point"}
}