{
  "type": "Feature",
  "properties": {
    "iso:country":"BE",
    "sg:address":"Otletstraat 30",
    "sg:city":"Anderlecht/anderlecht",
    "sg:orig_category":"Drukkerijen and copyshops",
    "sg:phone":"+32 2 523 72 31",
    "sg:postcode":"1070",
    "sg:province":"Bruxelles-Capitale",
    "wof:name":"De Koninck Drukkerij/imprimerie De Koninck",
    "wof:placetype":"venue"
},
  "geometry": {"coordinates":[4.3364500999,50.8428192139],"type":"Point"}
}