{
  "type": "Feature",
  "properties": {
    "addr:full":"Rue Pont D'avroy 16 Li\u00e8ge 1 Li\u00e8ge 4000",
    "addr:housenumber":"16;1",
    "addr:postcode":"4000",
    "addr:street":"Rue Pont D'Avroy",
    "iso:country":"BE",
    "sg:address":"Rue Pont D'avroy 16",
    "sg:city":"Li\u00e8ge 1",
    "sg:orig_category":"Solariums",
    "sg:phone":"+32 4 223 31 35",
    "sg:postcode":"4000",
    "sg:province":"Li\u00e8ge",
    "wof:name":"Centre De Bronzage Magic",
    "wof:placetype":"venue"
},
  "geometry": {"coordinates":[5.570171833,50.6408462524],"type":"Point"}
}