{
  "type": "Feature",
  "properties": {
    "addr:full":"Stationsstraat 2 Hamme Oost-Vlaanderen 9220",
    "addr:housenumber":"2",
    "addr:postcode":"9220",
    "addr:street":"Stationsstraat",
    "iso:country":"BE",
    "sg:address":"Stationsstraat 2",
    "sg:city":"Hamme",
    "sg:classifiers":[
        {
            "category":"Cafe",
            "type":"Food & Drink"
        }
    ],
    "sg:phone":"+32 52 48 09 34",
    "sg:postcode":"9220",
    "sg:province":"Oost-Vlaanderen",
    "sg:tags":[
        "caf\u00e9s"
    ],
    "wof:name":"Genclik Club",
    "wof:placetype":"venue"
},
  "geometry": {"coordinates":[4.1291751862,51.09740448],"type":"Point"}
}