{
  "type": "Feature",
  "properties": {
    "iso:country":"BE",
    "sg:address":"Hundelgemsesteenweg 271",
    "sg:city":"Merelbeke",
    "sg:orig_category":"Slagers",
    "sg:phone":"+32 9 231 23 67",
    "sg:postcode":"9820",
    "sg:province":"Oost-Vlaanderen",
    "wof:name":"De Parelhoen",
    "wof:placetype":"venue"
},
  "geometry": {"coordinates":[3.7488958836,50.9978904724],"type":"Point"}
}