{
  "type": "Feature",
  "properties": {
    "addr:full":"Neuville Haut 59 Vielsalm Luxembourg 6690",
    "addr:housenumber":"59",
    "addr:postcode":"6690",
    "addr:street":"Haut",
    "iso:country":"BE",
    "sg:address":"Neuville Haut 59",
    "sg:city":"Vielsalm",
    "sg:orig_category":"Plomberie, chauffage and installations sanitaires",
    "sg:phone":"+32 80 21 56 82",
    "sg:postcode":"6690",
    "sg:province":"Luxembourg",
    "wof:name":"Henri Lebecque",
    "wof:placetype":"venue"
},
  "geometry": {"coordinates":[5.9373087883,50.280582428],"type":"Point"}
}