{
  "type": "Feature",
  "properties": {
    "iso:country":"BE",
    "sg:address":"Vilvoordsesteenweg 211",
    "sg:city":"Meise",
    "sg:orig_category":"Non-Classified Establishments",
    "sg:phone":"+32 2 269 87 27",
    "sg:postcode":"1860",
    "sg:province":"Vlaams-Brabant",
    "wof:name":"Dianna David Nv",
    "wof:placetype":"venue"
},
  "geometry": {"coordinates":[4.3238501549,50.9455337524],"type":"Point"}
}