{
  "type": "Feature",
  "properties": {
    "addr:full":"Rue Dewez 18 Namur Namur 5000",
    "addr:housenumber":"18",
    "addr:postcode":"5000",
    "addr:street":"Rue Dewez",
    "iso:country":"BE",
    "sg:address":"Rue Dewez 18",
    "sg:city":"Namur",
    "sg:classifiers":[
        {
            "category":"Manufacturing",
            "subcategory":"Tools & Machinery",
            "type":"Manufacturing & Wholesale Goods"
        }
    ],
    "sg:phone":"+32 81 25 50 04",
    "sg:postcode":"5000",
    "sg:province":"Namur",
    "sg:tags":[
        "equipment",
        "measurement",
        "-",
        "precision",
        "instrument"
    ],
    "wof:name":"Normalab Analis Belgium Sa",
    "wof:placetype":"venue"
},
  "geometry": {"coordinates":[4.8709321022,50.4678382874],"type":"Point"}
}