{
  "type": "Feature",
  "properties": {
    "iso:country":"BE",
    "sg:address":"Kerkhofstraat 7",
    "sg:city":"Lebbeke",
    "sg:orig_category":"M\u00e9decins and sp\u00e9cialistes",
    "sg:phone":"+32 53 77 43 17",
    "sg:postcode":"9280",
    "sg:province":"Oost-Vlaanderen",
    "wof:name":"Kathleen Scharpe",
    "wof:placetype":"venue"
},
  "geometry": {"coordinates":[4.0839829445,50.9804267883],"type":"Point"}
}