{
  "type": "Feature",
  "properties": {
    "addr:full":"Mechelsesteenweg 484 Herent Vlaams-Brabant 3020",
    "addr:housenumber":"484",
    "addr:postcode":"3020",
    "addr:street":"Mechelsesteenweg",
    "iso:country":"BE",
    "sg:address":"Mechelsesteenweg 484",
    "sg:city":"Herent",
    "sg:orig_category":"Brood, gebak and snoepgoed",
    "sg:phone":"+32 16 23 51 15",
    "sg:postcode":"3020",
    "sg:province":"Vlaams-Brabant",
    "wof:name":"Mark Van Minsel",
    "wof:placetype":"venue"
},
  "geometry": {"coordinates":[4.6686477661,50.906955719],"type":"Point"}
}