{
  "type": "Feature",
  "properties": {
    "addr:full":"Jan Pieter De Nayerlaan 9 Sint-katelijne-waver Antwerpen 2860",
    "addr:housenumber":"9",
    "addr:postcode":"2860",
    "addr:street":"Jan Pieter De Nayerlaan",
    "iso:country":"BE",
    "sg:address":"Jan Pieter De Nayerlaan 9",
    "sg:city":"Sint-katelijne-waver",
    "sg:classifiers":[
        {
            "category":"Professional",
            "subcategory":"Testing Lab",
            "type":"Services"
        }
    ],
    "sg:phone":"+32 15 32 17 75",
    "sg:postcode":"2860",
    "sg:province":"Antwerpen",
    "sg:tags":[
        "laboratory",
        "-",
        "machines",
        "apparatus",
        "supply"
    ],
    "wof:name":"S T A G",
    "wof:placetype":"venue"
},
  "geometry": {"coordinates":[4.5013737679,51.0701560974],"type":"Point"}
}