{
  "type": "Feature",
  "properties": {
    "addr:full":"Kapellestraat 111 Bredene West-Vlaanderen 8450",
    "addr:housenumber":"111",
    "addr:postcode":"8450",
    "addr:street":"Kapellestraat",
    "iso:country":"BE",
    "sg:address":"Kapellestraat 111",
    "sg:city":"Bredene",
    "sg:classifiers":[
        {
            "category":"Social Services",
            "subcategory":"Job Training",
            "type":"Services"
        }
    ],
    "sg:phone":"+32 59 32 04 20",
    "sg:postcode":"8450",
    "sg:province":"West-Vlaanderen",
    "sg:tags":[
        "de",
        "terrain",
        "camping"
    ],
    "wof:name":"Bien Venue",
    "wof:placetype":"venue"
},
  "geometry": {"coordinates":[2.9673960209,51.2497062683],"type":"Point"}
}