{
  "type": "Feature",
  "properties": {
    "iso:country":"BE",
    "sg:address":"Rue Ferrer 196",
    "sg:city":"La Louviere",
    "sg:orig_category":"Artsen and specialisten",
    "sg:phone":"+32 64 28 46 69",
    "sg:postcode":"7100",
    "sg:province":"Hainaut",
    "wof:name":"Consultations Nourrissons",
    "wof:placetype":"venue"
},
  "geometry": {"coordinates":[4.2158098221,50.4753799438],"type":"Point"}
}