{
  "type": "Feature",
  "properties": {
    "addr:full":"Guldenroedestraat 16 Gent (mariakerke) Oost-Vlaanderen 9030",
    "addr:housenumber":"16",
    "addr:postcode":"9030",
    "addr:street":"Guldenroedestraat",
    "iso:country":"BE",
    "sg:address":"Guldenroedestraat 16",
    "sg:city":"Gent (mariakerke)",
    "sg:classifiers":[
        {
            "category":"Insurance",
            "subcategory":"Insurance Agent",
            "type":"Services"
        }
    ],
    "sg:phone":"+32 9 226 43 07",
    "sg:postcode":"9030",
    "sg:province":"Oost-Vlaanderen",
    "sg:tags":[
        "broker"
    ],
    "wof:name":"Vanhecke M",
    "wof:placetype":"venue"
},
  "geometry": {"coordinates":[3.6864960194,51.0757217407],"type":"Point"}
}