{
  "type": "Feature",
  "properties": {
    "addr:full":"Grasmarkt 39-41 Brussel/bruxelles Bruxelles-Capitale 1000",
    "addr:postcode":"39-41;/ bruxelles;1000",
    "addr:street":"Grasmarkt",
    "iso:country":"BE",
    "sg:address":"Grasmarkt 39-41",
    "sg:city":"Brussel/bruxelles",
    "sg:orig_category":"Kapsalons",
    "sg:phone":"+32 2 514 09 69",
    "sg:postcode":"1000",
    "sg:province":"Bruxelles-Capitale",
    "wof:name":"Tchip Coiffure",
    "wof:placetype":"venue"
},
  "geometry": {"coordinates":[4.3525600433,50.8475036621],"type":"Point"}
}