{
  "type": "Feature",
  "properties": {
    "iso:country":"BE",
    "sg:address":"Euster 110",
    "sg:city":"Duffel",
    "sg:orig_category":"Eleveurs de bovins",
    "sg:phone":"+32 3 480 38 60",
    "sg:postcode":"2570",
    "sg:province":"Antwerpen",
    "wof:name":"Jan Peeters",
    "wof:placetype":"venue"
},
  "geometry": {"coordinates":[4.5643138885,51.0990562439],"type":"Point"}
}