{
  "type": "Feature",
  "properties": {
    "addr:full":"Lindenlaan 48 Beerse Antwerpen 2340",
    "addr:housenumber":"48",
    "addr:postcode":"2340",
    "addr:street":"Lindenlaan",
    "iso:country":"BE",
    "sg:address":"Lindenlaan 48",
    "sg:city":"Beerse",
    "sg:classifiers":[
        {
            "category":"Professional",
            "subcategory":"Computer Services",
            "type":"Services"
        }
    ],
    "sg:phone":"+32 14 61 70 58",
    "sg:postcode":"2340",
    "sg:province":"Antwerpen",
    "sg:tags":[
        "-",
        "processing",
        "data"
    ],
    "wof:name":"Computers Van Bouwel Bvba",
    "wof:placetype":"venue"
},
  "geometry": {"coordinates":[4.8517799377,51.3192176819],"type":"Point"}
}