{
  "type": "Feature",
  "properties": {
    "addr:full":"Rue Des Scailleux 38 Binche (leval-trahegnies) Hainaut 7134",
    "addr:housenumber":"38",
    "addr:postcode":"7134",
    "addr:street":"Rue Des Scailleux",
    "iso:country":"BE",
    "sg:address":"Rue Des Scailleux 38",
    "sg:city":"Binche (leval-trahegnies)",
    "sg:classifiers":[
        {
            "category":"Insurance",
            "subcategory":"Insurance Agent",
            "type":"Services"
        }
    ],
    "sg:phone":"+32 64 33 53 18",
    "sg:postcode":"7134",
    "sg:province":"Hainaut",
    "sg:tags":[
        "broker"
    ],
    "wof:name":"Peruzzi B",
    "wof:placetype":"venue"
},
  "geometry": {"coordinates":[4.2247190475,50.4149093628],"type":"Point"}
}