{
  "type": "Feature",
  "properties": {
    "iso:country":"BE",
    "sg:address":"Gijmelsesteenweg 308b2",
    "sg:city":"Aarschot",
    "sg:classifiers":[
        {
            "category":"Insurance",
            "subcategory":"Life Insurance",
            "type":"Services"
        }
    ],
    "sg:phone":"+32 16 57 05 05",
    "sg:postcode":"3201",
    "sg:province":"Vlaams-Brabant",
    "sg:tags":[
        "assurance"
    ],
    "wof:name":"Verzekeringen Theys",
    "wof:placetype":"venue"
},
  "geometry": {"coordinates":[4.8646950722,51.011264801],"type":"Point"}
}