{
  "type": "Feature",
  "properties": {
    "iso:country":"BE",
    "sg:address":"Stationsstraat 84",
    "sg:city":"Geel",
    "sg:orig_category":"Textiles. Eclairage et \u00e9quipements du foyer. Articles de jardin. Meubles D\u00e9taillants, Am\u00e9nagement de",
    "sg:phone":"+32 14 59 23 96",
    "sg:postcode":"2440",
    "sg:province":"Antwerpen",
    "wof:name":"Holten Interiors",
    "wof:placetype":"venue"
},
  "geometry": {"coordinates":[4.9890332222,51.1659088135],"type":"Point"}
}