{
  "type": "Feature",
  "properties": {
    "iso:country":"BE",
    "sg:address":"Rossemdorp 46",
    "sg:city":"Meise",
    "sg:orig_category":"Boekhouders",
    "sg:phone":"+32 52 37 48 93",
    "sg:postcode":"1861",
    "sg:province":"Vlaams-Brabant",
    "wof:name":"Eric Troch",
    "wof:placetype":"venue"
},
  "geometry": {"coordinates":[4.3091049194,50.9506645203],"type":"Point"}
}