{
  "type": "Feature",
  "properties": {
    "addr:full":"Rue Rogier 35 Namur Namur 5000",
    "addr:housenumber":"35",
    "addr:postcode":"5000",
    "addr:street":"Rue Rogier",
    "iso:country":"BE",
    "sg:address":"Rue Rogier 35",
    "sg:city":"Namur",
    "sg:classifiers":[
        {
            "category":"Restaurant",
            "type":"Food & Drink"
        }
    ],
    "sg:phone":"+32 81 26 19 36",
    "sg:postcode":"5000",
    "sg:province":"Namur",
    "sg:tags":[
        "caf\u00e9s"
    ],
    "wof:name":"Caf\u00c9 Le Crasset",
    "wof:placetype":"venue"
},
  "geometry": {"coordinates":[4.8669800758,50.4676856995],"type":"Point"}
}