{
  "type": "Feature",
  "properties": {
    "addr:full":"Grote Hoolstraat 92 Herk-de-stad Limburg 3540",
    "addr:housenumber":"92",
    "addr:postcode":"3540",
    "addr:street":"Grote Hoolstraat",
    "iso:country":"BE",
    "sg:address":"Grote Hoolstraat 92",
    "sg:city":"Herk-de-stad",
    "sg:orig_category":"Eleveurs de bovins",
    "sg:phone":"+32 13 55 26 18",
    "sg:postcode":"3540",
    "sg:province":"Limburg",
    "wof:name":"Andre Peetersem",
    "wof:placetype":"venue"
},
  "geometry": {"coordinates":[5.1547369957,50.9374465942],"type":"Point"}
}