{
  "type": "Feature",
  "properties": {
    "iso:country":"BE",
    "sg:address":"Driesstraat 167",
    "sg:city":"Zele",
    "sg:classifiers":[
        {
            "category":"Building & Trades",
            "subcategory":"Construction",
            "type":"Services"
        }
    ],
    "sg:phone":"+32 52 45 07 00",
    "sg:postcode":"9240",
    "sg:province":"Oost-Vlaanderen",
    "sg:tags":[
        "duct",
        "underground",
        "ducting"
    ],
    "wof:name":"Koze Nv",
    "wof:placetype":"venue"
},
  "geometry": {"coordinates":[4.022758007,51.0657577515],"type":"Point"}
}