{
  "type": "Feature",
  "properties": {
    "iso:country":"BE",
    "sg:address":"Kapittelstraat 6",
    "sg:city":"Lebbeke",
    "sg:classifiers":[
        {
            "category":"Train Station",
            "subcategory":"Light Rail",
            "type":"Transportation"
        }
    ],
    "sg:phone":"+32 53 79 05 67",
    "sg:postcode":"9280",
    "sg:province":"Oost-Vlaanderen",
    "sg:tags":[
        "switch"
    ],
    "wof:name":"Gira Belgi\u00eb",
    "wof:placetype":"venue"
},
  "geometry": {"coordinates":[4.0846118927,50.9780006409],"type":"Point"}
}