{
  "type": "Feature",
  "properties": {
    "iso:country":"BE",
    "sg:address":"Titecastraat 120",
    "sg:city":"Brugge",
    "sg:orig_category":"Dakwerken Loodgieterij, verwarming and sanitaire installaties",
    "sg:phone":"+32 50 39 28 89",
    "sg:postcode":"8200",
    "sg:province":"West-Vlaanderen",
    "wof:name":"De Gryse",
    "wof:placetype":"venue"
},
  "geometry": {"coordinates":[3.2034699917,51.1934318542],"type":"Point"}
}