{
  "type": "Feature",
  "properties": {
    "iso:country":"BE",
    "sg:address":"Rue B\u00e2tonnier Braffort 53",
    "sg:city":"Bruxelles (etterbeek)",
    "sg:classifiers":[
        {
            "category":"Real Estate",
            "subcategory":"Architect",
            "type":"Services"
        }
    ],
    "sg:phone":"+32 2 648 71 93",
    "sg:postcode":"1040",
    "sg:province":"Bruxelles-Capitale",
    "wof:name":"Henrard Th",
    "wof:placetype":"venue"
},
  "geometry": {"coordinates":[4.4043731689,50.8394203186],"type":"Point"}
}