{
  "type": "Feature",
  "properties": {
    "addr:full":"Rue De L'agasse 36 Gembloux-sur-orneau (gembloux) Namur 5030",
    "addr:housenumber":"36",
    "addr:postcode":"5030",
    "addr:street":"Rue De L'Agasse;Namur",
    "iso:country":"BE",
    "sg:address":"Rue De L'agasse 36",
    "sg:city":"Gembloux-sur-orneau (gembloux)",
    "sg:classifiers":[
        {
            "category":"Health Services",
            "subcategory":"Health Practitioner",
            "type":"Services"
        }
    ],
    "sg:phone":"+32 81 61 39 45",
    "sg:postcode":"5030",
    "sg:province":"Namur",
    "sg:tags":[
        "alternative",
        "therapy",
        "treatment"
    ],
    "wof:name":"Callewaert C",
    "wof:placetype":"venue"
},
  "geometry": {"coordinates":[4.6861009598,50.5700798035],"type":"Point"}
}