{
  "type": "Feature",
  "properties": {
    "iso:country":"BE",
    "sg:address":"Jan Van Ruusbroeclaan 4",
    "sg:city":"Kortrijk",
    "sg:classifiers":[
        {
            "category":"Professional",
            "subcategory":"Engineering",
            "type":"Services"
        }
    ],
    "sg:phone":"+32 56 25 57 61",
    "sg:postcode":"8500",
    "sg:province":"West-Vlaanderen",
    "sg:tags":[
        "-"
    ],
    "wof:name":"Vandeputte",
    "wof:placetype":"venue"
},
  "geometry": {"coordinates":[3.2934401035,50.7970809937],"type":"Point"}
}