{
  "type": "Feature",
  "properties": {
    "iso:country":"BE",
    "sg:address":"Heidestraat 105",
    "sg:city":"Beringen",
    "sg:orig_category":"Instituts de beaut\u00e9",
    "sg:phone":"+32 11 34 71 04",
    "sg:postcode":"3581",
    "sg:province":"Limburg",
    "wof:name":"Annette Janssens",
    "wof:placetype":"venue"
},
  "geometry": {"coordinates":[5.2228298187,51.0881996155],"type":"Point"}
}