{
  "type": "Feature",
  "properties": {
    "addr:full":"Hasselt-ten-broek 8 Sint-lievens-houtem Oost-Vlaanderen 9521",
    "addr:housenumber":"8",
    "addr:postcode":"9521",
    "addr:street":"Hasselt-Ten-Broek;Oost-Vlaanderen",
    "iso:country":"BE",
    "sg:address":"Hasselt-ten-broek 8",
    "sg:city":"Sint-lievens-houtem",
    "sg:orig_category":"Varkenskwekers",
    "sg:phone":"+32 53 62 15 67",
    "sg:postcode":"9521",
    "sg:province":"Oost-Vlaanderen",
    "wof:name":"Henri Van Der Biest",
    "wof:placetype":"venue"
},
  "geometry": {"coordinates":[3.8803539276,50.9379348755],"type":"Point"}
}