{
  "type": "Feature",
  "properties": {
    "iso:country":"BE",
    "sg:address":"Rue Du Midi 12",
    "sg:city":"Ronse/renaix",
    "sg:orig_category":"M\u00e9decins and sp\u00e9cialistes",
    "sg:phone":"+32 55 21 92 85",
    "sg:postcode":"9600",
    "sg:province":"Oost-Vlaanderen",
    "wof:name":"Y. Louis",
    "wof:placetype":"venue"
},
  "geometry": {"coordinates":[3.6037650108,50.7462539673],"type":"Point"}
}