{
  "type": "Feature",
  "properties": {
    "iso:country":"BE",
    "sg:address":"Paleizenstraat 297",
    "sg:city":"Bruxelles",
    "sg:classifiers":[
        {
            "category":"Retail",
            "subcategory":"Auto Repair",
            "type":"Services"
        }
    ],
    "sg:phone":"+32 2 203 90 33",
    "sg:postcode":"1000",
    "sg:province":"Bruxelles-Capitale",
    "sg:tags":[
        "garage"
    ],
    "wof:name":"Demcar",
    "wof:placetype":"venue"
},
  "geometry": {"coordinates":[4.3629188538,50.8713340759],"type":"Point"}
}