{
  "type": "Feature",
  "properties": {
    "addr:full":"Rue Des Volontaires 3 Esneux Li\u00e8ge 4130",
    "addr:housenumber":"3",
    "addr:postcode":"4130",
    "addr:street":"Rue Des Volontaires",
    "iso:country":"BE",
    "sg:address":"Rue Des Volontaires 3",
    "sg:city":"Esneux",
    "sg:classifiers":[
        {
            "category":"Cafe",
            "type":"Food & Drink"
        }
    ],
    "sg:phone":"+32 4 380 39 36",
    "sg:postcode":"4130",
    "sg:province":"Li\u00e8ge",
    "sg:tags":[
        "caf\u00e9s"
    ],
    "wof:name":"Brasserie De La Place",
    "wof:placetype":"venue"
},
  "geometry": {"coordinates":[5.5674681664,50.534198761],"type":"Point"}
}