{
  "type": "Feature",
  "properties": {
    "iso:country":"BE",
    "sg:address":"Postbus 54",
    "sg:city":"Waregem1",
    "sg:classifiers":[
        {
            "category":"Tea Room",
            "subcategory":"None",
            "type":"Food & Drink"
        }
    ],
    "sg:phone":"+32 56 72 71 80",
    "sg:postcode":"8790",
    "sg:province":"West-Vlaanderen",
    "sg:tags":[
        "plaster"
    ],
    "wof:name":"Fermacell Gipsvezelplaten",
    "wof:placetype":"venue"
},
  "geometry": {"coordinates":[170.94201660159999,-44.5585098267],"type":"Point"}
}