{
  "type": "Feature",
  "properties": {
    "addr:full":"Krekelput 13 Oudenaarde Oost-Vlaanderen 9700",
    "addr:housenumber":"13",
    "addr:postcode":"9700",
    "addr:street":"Krekelput",
    "iso:country":"BE",
    "sg:address":"Krekelput 13",
    "sg:city":"Oudenaarde",
    "sg:orig_category":"Disneyland Parijs Reisbureaus",
    "sg:phone":"+32 55 31 77 23",
    "sg:postcode":"9700",
    "sg:province":"Oost-Vlaanderen",
    "wof:name":"Neckermann",
    "wof:placetype":"venue"
},
  "geometry": {"coordinates":[3.6068201065,50.8432617188],"type":"Point"}
}