{
  "type": "Feature",
  "properties": {
    "addr:full":"Kastanjedreef 34a Heist-op-den-berg Antwerpen 2220",
    "addr:housenumber":"34a",
    "addr:postcode":"2220",
    "addr:street":"Kastanjedreef",
    "iso:country":"BE",
    "sg:address":"Kastanjedreef 34a",
    "sg:city":"Heist-op-den-berg",
    "sg:classifiers":[
        {
            "category":"Health Services",
            "subcategory":"Dentist",
            "type":"Services"
        }
    ],
    "sg:phone":"+32 15 24 05 55",
    "sg:postcode":"2220",
    "sg:province":"Antwerpen",
    "wof:name":"De Haes Celine",
    "wof:placetype":"venue"
},
  "geometry": {"coordinates":[4.6899838448,51.0637016296],"type":"Point"}
}