{
  "type": "Feature",
  "properties": {
    "iso:country":"BE",
    "sg:address":"Leuvensesteenweg 2",
    "sg:city":"Tielt-winge",
    "sg:orig_category":"Eleveurs de bovins",
    "sg:phone":"+32 16 63 30 53",
    "sg:postcode":"3390",
    "sg:province":"Vlaams-Brabant",
    "wof:name":"Alfons Taverniers",
    "wof:placetype":"venue"
},
  "geometry": {"coordinates":[4.8991470337,50.9160423279],"type":"Point"}
}