{
  "type": "Feature",
  "properties": {
    "addr:full":"Burght 2 Bever Vlaams-Brabant 1547",
    "addr:housenumber":"2",
    "addr:postcode":"1547",
    "addr:street":"Burght;Vlaams-Brabant",
    "iso:country":"BE",
    "sg:address":"Burght 2",
    "sg:city":"Bever",
    "sg:orig_category":"Quincailleries",
    "sg:phone":"+32 54 58 76 11",
    "sg:postcode":"1547",
    "sg:province":"Vlaams-Brabant",
    "wof:name":"Thibaut Patrick",
    "wof:placetype":"venue"
},
  "geometry": {"coordinates":[3.9231359959,50.7161026001],"type":"Point"}
}