{
  "type": "Feature",
  "properties": {
    "iso:country":"BE",
    "sg:address":"Bellevaux 19a",
    "sg:city":"Malmedy/malmedy",
    "sg:orig_category":"Bloemen and planten Gh Groententeelt",
    "sg:phone":"+32 80 33 75 34",
    "sg:postcode":"4960",
    "sg:province":"Li\u00e8ge",
    "wof:name":"Daniel Schmitz",
    "wof:placetype":"venue"
},
  "geometry": {"coordinates":[6.0104761124,50.3876342773],"type":"Point"}
}