{
  "type": "Feature",
  "properties": {
    "addr:full":"Zuiderdijk 7 Rijkevorsel Antwerpen 2310",
    "addr:housenumber":"7",
    "addr:postcode":"2310",
    "addr:street":"Zuiderdijk",
    "iso:country":"BE",
    "sg:address":"Zuiderdijk 7",
    "sg:city":"Rijkevorsel",
    "sg:orig_category":"Sportclubs",
    "sg:phone":"+32 3 311 66 57",
    "sg:postcode":"2310",
    "sg:province":"Antwerpen",
    "wof:name":"V.c. Rijkevoc-rijkevorsel",
    "wof:placetype":"venue"
},
  "geometry": {"coordinates":[4.7595419884,51.3500099182],"type":"Point"}
}