{
  "type": "Feature",
  "properties": {
    "addr:full":"Biesemstraat 90 Geetbets Vlaams-Brabant 3454",
    "addr:housenumber":"90",
    "addr:postcode":"3454",
    "addr:street":"Biesemstraat",
    "iso:country":"BE",
    "sg:address":"Biesemstraat 90",
    "sg:city":"Geetbets",
    "sg:orig_category":"Installatie van houten of kunststof schrijnwerk",
    "sg:phone":"+32 11 58 97 85",
    "sg:postcode":"3454",
    "sg:province":"Vlaams-Brabant",
    "wof:name":"J.k.",
    "wof:placetype":"venue"
},
  "geometry": {"coordinates":[5.1592121124,50.9096984863],"type":"Point"}
}