{
  "type": "Feature",
  "properties": {
    "addr:full":"Borgersteinlei 100 Sint-katelijne-waver Antwerpen 2860",
    "addr:housenumber":"100",
    "addr:postcode":"2860",
    "addr:street":"Borgersteinlei",
    "iso:country":"BE",
    "sg:address":"Borgersteinlei 100",
    "sg:city":"Sint-katelijne-waver",
    "sg:orig_category":"S\u00e9curit\u00e9 sociale",
    "sg:phone":"+32 15 55 55 68",
    "sg:postcode":"2860",
    "sg:province":"Antwerpen",
    "wof:name":"Socialist. Mutualiteiten",
    "wof:placetype":"venue"
},
  "geometry": {"coordinates":[4.5077600479,51.0404090881],"type":"Point"}
}