{
  "type": "Feature",
  "properties": {
    "addr:full":"Rue Des Palais Outre-ponts 422 Laeken Bruxelles-Capitale 1020",
    "addr:housenumber":"422",
    "addr:postcode":"1020",
    "addr:street":"Rue Des Palais Outre-Ponts",
    "iso:country":"BE",
    "sg:address":"Rue Des Palais Outre-ponts 422",
    "sg:city":"Laeken",
    "sg:orig_category":"Drukkerijen and copyshops",
    "sg:phone":"+32 2 478 06 31",
    "sg:postcode":"1020",
    "sg:province":"Bruxelles-Capitale",
    "wof:name":"Picto.s",
    "wof:placetype":"venue"
},
  "geometry": {"coordinates":[4.3604202271,50.8758773804],"type":"Point"}
}