{
  "type": "Feature",
  "properties": {
    "addr:full":"Koning - Albertstraat 26 Geel Antwerpen 2440",
    "addr:housenumber":"26",
    "addr:postcode":"2440",
    "addr:street":"Koning Albertstraat",
    "iso:country":"BE",
    "sg:address":"Koning - Albertstraat 26",
    "sg:city":"Geel",
    "sg:classifiers":[
        {
            "category":"Health Services",
            "subcategory":"Doctor",
            "type":"Services"
        }
    ],
    "sg:phone":"+32 14 58 80 83",
    "sg:postcode":"2440",
    "sg:province":"Antwerpen",
    "sg:tags":[
        "medicinephysicians",
        "surgeon"
    ],
    "wof:name":"Degroote M",
    "wof:placetype":"venue"
},
  "geometry": {"coordinates":[4.9832811356,51.1463088989],"type":"Point"}
}