{
  "type": "Feature",
  "properties": {
    "iso:country":"BE",
    "sg:address":"Rue V Romain 14",
    "sg:city":"La Louviere",
    "sg:orig_category":"Metaalafval, schrootrecyclage and sloperijen",
    "sg:phone":"+32 64 84 21 21",
    "sg:postcode":"7100",
    "sg:province":"Hainaut",
    "wof:name":"Carrosserie Sprl",
    "wof:placetype":"venue"
},
  "geometry": {"coordinates":[4.1850848198,50.4748649597],"type":"Point"}
}