{
  "type": "Feature",
  "properties": {
    "addr:full":"Rue De Frameries 54 Quevy Hainaut 7040",
    "addr:housenumber":"54",
    "addr:postcode":"7040",
    "addr:street":"Rue De Frameries;Hainaut",
    "iso:country":"BE",
    "sg:address":"Rue De Frameries 54",
    "sg:city":"Quevy",
    "sg:classifiers":[
        {
            "category":"Wholesale",
            "subcategory":"Farm Supplies",
            "type":"Manufacturing & Wholesale Goods"
        }
    ],
    "sg:phone":"+32 65 56 87 62",
    "sg:postcode":"7040",
    "sg:province":"Hainaut",
    "sg:tags":[
        "machine",
        "agricoles",
        "mat\u00e9riel",
        "gr"
    ],
    "wof:name":"Ateliers Glorieux Raoul",
    "wof:placetype":"venue"
},
  "geometry": {"coordinates":[3.9298169613,50.3710250854],"type":"Point"}
}