{
  "type": "Feature",
  "properties": {
    "iso:country":"BE",
    "sg:address":"Markt 14",
    "sg:city":"Aalter",
    "sg:classifiers":[
        {
            "category":"Restaurant",
            "type":"Food & Drink"
        }
    ],
    "sg:phone":"+32 9 375 34 30",
    "sg:postcode":"9880",
    "sg:province":"Oost-Vlaanderen",
    "wof:name":"Restaurant De Genieter",
    "wof:placetype":"venue"
},
  "geometry": {"coordinates":[3.4489400387,51.0839004517],"type":"Point"}
}