{
  "type": "Feature",
  "properties": {
    "iso:country":"BE",
    "sg:address":"Kasteelstraat 55",
    "sg:city":"Antwerpen",
    "sg:classifiers":[
        {
            "category":"Professional",
            "subcategory":"Testing Lab",
            "type":"Services"
        }
    ],
    "sg:phone":"+32 3 238 52 05",
    "sg:postcode":"2000",
    "sg:province":"Antwerpen",
    "sg:tags":[
        "laboratory",
        "photographic",
        "film"
    ],
    "wof:name":"Foto Schelfhout",
    "wof:placetype":"venue"
},
  "geometry": {"coordinates":[4.3927960396,51.2063522339],"type":"Point"}
}