{
  "type": "Feature",
  "properties": {
    "addr:full":"Rue Jean Lefebvre 19bis Estaimpuis Hainaut 7730",
    "addr:housenumber":"19bis",
    "addr:postcode":"7730",
    "addr:street":"Rue Jean Lefebvre;Hainaut",
    "iso:country":"BE",
    "sg:address":"Rue Jean Lefebvre 19bis",
    "sg:city":"Estaimpuis",
    "sg:classifiers":[
        {
            "category":"Insurance",
            "subcategory":"Insurance Agent",
            "type":"Services"
        }
    ],
    "sg:phone":"+32 56 48 84 94",
    "sg:postcode":"7730",
    "sg:province":"Hainaut",
    "sg:tags":[
        "broker"
    ],
    "wof:name":"Reheul J-m",
    "wof:placetype":"venue"
},
  "geometry": {"coordinates":[3.2649619579,50.7051849365],"type":"Point"}
}