{
  "type": "Feature",
  "properties": {
    "addr:full":"Pater Damiaanlaan 12 Zandhoven Antwerpen 2240",
    "addr:housenumber":"12",
    "addr:postcode":"2240",
    "addr:street":"Pater Damiaanlaan",
    "iso:country":"BE",
    "sg:address":"Pater Damiaanlaan 12",
    "sg:city":"Zandhoven",
    "sg:orig_category":"G\u00e9om\u00e8tres",
    "sg:phone":"+32 3 464 20 18",
    "sg:postcode":"2240",
    "sg:province":"Antwerpen",
    "wof:name":"Michel Van Den Bossche",
    "wof:placetype":"venue"
},
  "geometry": {"coordinates":[4.66441679,51.2194824219],"type":"Point"}
}