{
  "type": "Feature",
  "properties": {
    "addr:full":"Rue Saint-fiacre 24 Arlon Luxembourg 6706",
    "addr:housenumber":"24",
    "addr:postcode":"6706",
    "addr:street":"Rue Saint-Fiacre",
    "iso:country":"BE",
    "sg:address":"Rue Saint-fiacre 24",
    "sg:city":"Arlon",
    "sg:orig_category":"Installation de menuiserie en bois and plastique. D\u00e9corateurs d'int\u00e9rieur",
    "sg:phone":"+32 63 22 78 29",
    "sg:postcode":"6706",
    "sg:province":"Luxembourg",
    "wof:name":"Francoise Pierson",
    "wof:placetype":"venue"
},
  "geometry": {"coordinates":[5.8720259666,49.6499214172],"type":"Point"}
}