{
  "type": "Feature",
  "properties": {
    "addr:full":"Zuivelmarkt 4 Hasselt Limburg 3500",
    "addr:housenumber":"4",
    "addr:postcode":"3500",
    "addr:street":"Zuivelmarkt",
    "iso:country":"BE",
    "sg:address":"Zuivelmarkt 4",
    "sg:city":"Hasselt",
    "sg:classifiers":[
        {
            "category":"Restaurant",
            "type":"Food & Drink"
        }
    ],
    "sg:phone":"+32 11 23 15 05",
    "sg:postcode":"3500",
    "sg:province":"Limburg",
    "wof:name":"La Vache Qui Suisse",
    "wof:placetype":"venue"
},
  "geometry": {"coordinates":[5.3391880989,50.930606842],"type":"Point"}
}