{
  "type": "Feature",
  "properties": {
    "iso:country":"BE",
    "sg:address":"Cote-marie-th\u00c9r\u00c8se 86b8",
    "sg:city":"Dinant (groot)",
    "sg:orig_category":"Bierproductie and Brouwerijen",
    "sg:phone":"+32 82 74 40 80",
    "sg:postcode":"5500",
    "sg:province":"Namur",
    "wof:name":"Brasserie La Caracole",
    "wof:placetype":"venue"
},
  "geometry": {"coordinates":[4.8912901878,50.2024765015],"type":"Point"}
}