{
  "type": "Feature",
  "properties": {
    "iso:country":"BE",
    "sg:address":"Rue Wilmus 36",
    "sg:city":"Courcelles",
    "sg:orig_category":"Installation de menuiserie en bois and plastique",
    "sg:phone":"+32 71 46 23 20",
    "sg:postcode":"6180",
    "sg:province":"Hainaut",
    "wof:name":"Damiano Vinci",
    "wof:placetype":"venue"
},
  "geometry": {"coordinates":[4.3916730881,50.4673728943],"type":"Point"}
}