{
  "type": "Feature",
  "properties": {
    "addr:full":"Grijsbulckstraat 48 Deinze (grammene) Oost-Vlaanderen 9800",
    "addr:housenumber":"48",
    "addr:postcode":"9800",
    "addr:street":"Grijsbulckstraat",
    "iso:country":"BE",
    "sg:address":"Grijsbulckstraat 48",
    "sg:city":"Deinze (grammene)",
    "sg:classifiers":[
        {
            "category":"Banks & Credit Unions",
            "subcategory":"Bureau De Change",
            "type":"Services"
        }
    ],
    "sg:phone":"+32 51 63 34 07",
    "sg:postcode":"9800",
    "sg:province":"Oost-Vlaanderen",
    "sg:tags":[
        "melting",
        "grease",
        "-"
    ],
    "wof:name":"Profat Tm",
    "wof:placetype":"venue"
},
  "geometry": {"coordinates":[3.4601800442,50.988483429],"type":"Point"}
}