{
  "type": "Feature",
  "properties": {
    "addr:full":"Meulenweg 8 Lanaken Limburg 3620",
    "addr:housenumber":"8",
    "addr:postcode":"3620",
    "addr:street":"Meulenweg",
    "iso:country":"BE",
    "sg:address":"Meulenweg 8",
    "sg:city":"Lanaken",
    "sg:classifiers":[
        {
            "category":"Arena",
            "subcategory":"Sports Club",
            "type":"Entertainment"
        }
    ],
    "sg:phone":"+32 12 45 77 27",
    "sg:postcode":"3620",
    "sg:province":"Limburg",
    "sg:tags":[
        "terrain",
        "hors",
        "de",
        "installation",
        "sportifs"
    ],
    "wof:name":"V.v. Kanne",
    "wof:placetype":"venue"
},
  "geometry": {"coordinates":[5.6551351547,50.8912277222],"type":"Point"}
}