{
  "type": "Feature",
  "properties": {
    "addr:full":"Amelberga Truymanstraat 6 Stekene Oost-Vlaanderen 9190",
    "addr:housenumber":"6",
    "addr:postcode":"9190",
    "addr:street":"Truymanstraat",
    "iso:country":"BE",
    "sg:address":"Amelberga Truymanstraat 6",
    "sg:city":"Stekene",
    "sg:classifiers":[
        {
            "category":"Social Services",
            "subcategory":"Job Training",
            "type":"Services"
        }
    ],
    "sg:phone":"+32 475 32 86 43",
    "sg:postcode":"9190",
    "sg:province":"Oost-Vlaanderen",
    "sg:tags":[
        "coordinator",
        "safety"
    ],
    "wof:name":"Dfm",
    "wof:placetype":"venue"
},
  "geometry": {"coordinates":[4.0386390686,51.2112312317],"type":"Point"}
}