{
  "type": "Feature",
  "properties": {
    "iso:country":"BE",
    "sg:address":"Sijslostraat 84",
    "sg:city":"Oostkamp",
    "sg:orig_category":"Eleveurs and marchands de porcs",
    "sg:phone":"+32 50 27 95 23",
    "sg:postcode":"8020",
    "sg:province":"West-Vlaanderen",
    "wof:name":"Vandenberghe A",
    "wof:placetype":"venue"
},
  "geometry": {"coordinates":[3.1944200993,51.0997390747],"type":"Point"}
}