{
  "type": "Feature",
  "properties": {
    "addr:full":"Rue Des Minimes 7 Brussel/bruxelles Bruxelles-Capitale 1000",
    "addr:housenumber":"7",
    "addr:postcode":"1000",
    "addr:street":"Rue Des Minimes;/",
    "iso:country":"BE",
    "sg:address":"Rue Des Minimes 7",
    "sg:city":"Brussel/bruxelles",
    "sg:orig_category":"Antiquit\u00e9s",
    "sg:phone":"+32 2 513 42 62",
    "sg:postcode":"1000",
    "sg:province":"Bruxelles-Capitale",
    "wof:name":"Millers English Antiques",
    "wof:placetype":"venue"
},
  "geometry": {"coordinates":[4.3535709381,50.8412475586],"type":"Point"}
}