{
  "type": "Feature",
  "properties": {
    "addr:full":"Rue Des D\u00e9port\u00e9s 4 Tournai (blandain - Hertain) Hainaut 7522",
    "addr:housenumber":"4",
    "addr:postcode":"7522",
    "addr:street":"Rue Des De\u0301Porte\u0301S;Hainaut",
    "iso:country":"BE",
    "sg:address":"Rue Des D\u00e9port\u00e9s 4",
    "sg:city":"Tournai (blandain - Hertain)",
    "sg:classifiers":[
        {
            "category":"Bakery",
            "type":"Food & Drink"
        }
    ],
    "sg:phone":"+32 69 35 22 51",
    "sg:postcode":"7522",
    "sg:province":"Hainaut",
    "sg:tags":[
        "confectioner",
        "baker"
    ],
    "wof:name":"Dupriez R",
    "wof:placetype":"venue"
},
  "geometry": {"coordinates":[3.4003939629,50.6112365723],"type":"Point"}
}