{
  "type": "Feature",
  "properties": {
    "iso:country":"BE",
    "sg:address":"Ruiseleedsesteenweg 66",
    "sg:city":"Tielt",
    "sg:orig_category":"Activit\u00e9s d\u00b4action sociale sans h\u00e9bergement",
    "sg:phone":"+32 51 40 36 25",
    "sg:postcode":"8700",
    "sg:province":"West-Vlaanderen",
    "wof:name":"Rode Kruis Tielt",
    "wof:placetype":"venue"
},
  "geometry": {"coordinates":[3.3650910854,51.0142745972],"type":"Point"}
}