{
  "type": "Feature",
  "properties": {
    "iso:country":"BE",
    "sg:address":"Robaardstraat 17",
    "sg:city":"Roeselare",
    "sg:orig_category":"Gespecialiseerde niet-residenti\u00eble bouw Gespecialiseerde residenti\u00eble bouw",
    "sg:phone":"+32 51 25 32 86",
    "sg:postcode":"8800",
    "sg:province":"West-Vlaanderen",
    "wof:name":"Vandewalle Wim",
    "wof:placetype":"venue"
},
  "geometry": {"coordinates":[3.1176719666,50.970249176],"type":"Point"}
}