{
  "type": "Feature",
  "properties": {
    "addr:full":"Chauss\u00e9e De W\u00e9gimont 25a Soumagne (ayeneux) Li\u00e8ge 4630",
    "addr:housenumber":"25a",
    "addr:postcode":"4630",
    "addr:street":"Chausse\u0301E De We\u0301Gimont",
    "iso:country":"BE",
    "sg:address":"Chauss\u00e9e De W\u00e9gimont 25a",
    "sg:city":"Soumagne (ayeneux)",
    "sg:classifiers":[
        {
            "category":"Building & Trades",
            "subcategory":"Landscaping Services",
            "type":"Services"
        }
    ],
    "sg:phone":"+32 4 377 50 50",
    "sg:postcode":"4630",
    "sg:province":"Li\u00e8ge",
    "sg:tags":[
        "equipment",
        "swimming",
        "-",
        "pool",
        "contractor"
    ],
    "wof:name":"A\u00e9rofleet Sa",
    "wof:placetype":"venue"
},
  "geometry": {"coordinates":[5.7440490723,50.6114883423],"type":"Point"}
}