{
  "type": "Feature",
  "properties": {
    "addr:full":"Avenue Marius Meur\u00e9e 22 Charleroi (marcinelle) Hainaut 6001",
    "addr:housenumber":"22",
    "addr:postcode":"6001",
    "addr:street":"Avenue Marius Meure\u0301E",
    "iso:country":"BE",
    "sg:address":"Avenue Marius Meur\u00e9e 22",
    "sg:city":"Charleroi (marcinelle)",
    "sg:classifiers":[
        {
            "category":"Personal",
            "subcategory":"Beauty Salon",
            "type":"Services"
        }
    ],
    "sg:phone":"+32 71 43 44 15",
    "sg:postcode":"6001",
    "sg:province":"Hainaut",
    "sg:tags":[
        "lady",
        "-",
        "hairdressing"
    ],
    "wof:name":"Christelle M",
    "wof:placetype":"venue"
},
  "geometry": {"coordinates":[4.4477181435,50.40076828],"type":"Point"}
}