{
  "type": "Feature",
  "properties": {
    "addr:full":"Rue Du Cr\u00c9tinier 214 Moeskroen/mouscron Hainaut 7712",
    "addr:housenumber":"214",
    "addr:postcode":"7712",
    "addr:street":"Rue Du Cre\u0301Tinier",
    "iso:country":"BE",
    "sg:address":"Rue Du Cr\u00c9tinier 214",
    "sg:city":"Moeskroen/mouscron",
    "sg:classifiers":[
        {
            "category":"Personal",
            "subcategory":"Beauty Salon",
            "type":"Services"
        }
    ],
    "sg:phone":"+32 56 33 08 44",
    "sg:postcode":"7712",
    "sg:province":"Hainaut",
    "sg:tags":[
        "de",
        "coiffure"
    ],
    "wof:name":"Coiffure Ren\u00c9e",
    "wof:placetype":"venue"
},
  "geometry": {"coordinates":[3.2083499432,50.7123947144],"type":"Point"}
}