{
  "type": "Feature",
  "properties": {
    "addr:full":"Pastoor Weytslaan 13-4 Kalmthout Antwerpen 2920",
    "addr:housenumber":"13-4",
    "addr:postcode":"2920",
    "addr:street":"Pastoor Weytslaan",
    "iso:country":"BE",
    "sg:address":"Pastoor Weytslaan 13-4",
    "sg:city":"Kalmthout",
    "sg:classifiers":[
        {
            "category":"Shopping",
            "subcategory":"Clothing, Apparel, & Fashions",
            "type":"Retail Goods"
        }
    ],
    "sg:phone":"+32 3 666 56 76",
    "sg:postcode":"2920",
    "sg:province":"Antwerpen",
    "sg:tags":[
        "purchase",
        "clothing",
        "-",
        "sale",
        "second-hand"
    ],
    "wof:name":"Mini Binni",
    "wof:placetype":"venue"
},
  "geometry": {"coordinates":[4.4726481438,51.3927230835],"type":"Point"}
}