{
  "type": "Feature",
  "properties": {
    "iso:country":"BE",
    "sg:address":"Reepstraat 98",
    "sg:city":"Sint-gillis-waas",
    "sg:orig_category":"Schoonmaakbedrijven and ongediertebestrijding",
    "sg:phone":"+32 3 707 01 98",
    "sg:postcode":"9170",
    "sg:province":"Oost-Vlaanderen",
    "wof:name":"Van Den Heede",
    "wof:placetype":"venue"
},
  "geometry": {"coordinates":[4.1080389023,51.2267036438],"type":"Point"}
}