{
  "type": "Feature",
  "properties": {
    "addr:full":"Zuidstraat 129 Brussel/bruxelles Bruxelles-Capitale 1000",
    "addr:housenumber":"129",
    "addr:postcode":"1000",
    "addr:street":"Zuidstraat;/",
    "iso:country":"BE",
    "sg:address":"Zuidstraat 129",
    "sg:city":"Brussel/bruxelles",
    "sg:orig_category":"Postzegels, munten and trofee\u00ebn",
    "sg:phone":"+32 2 513 78 24",
    "sg:postcode":"1000",
    "sg:province":"Bruxelles-Capitale",
    "wof:name":"Philat.corneille Soeteman",
    "wof:placetype":"venue"
},
  "geometry": {"coordinates":[4.3429517746,50.8352661133],"type":"Point"}
}