{
  "type": "Feature",
  "properties": {
    "addr:full":"Emile Maxlaan 65 Schaarbeek/schaerbeek Bruxelles-Capitale 1030",
    "addr:housenumber":"65",
    "addr:postcode":"1030",
    "addr:street":"Emile Maxlaan",
    "iso:country":"BE",
    "sg:address":"Emile Maxlaan 65",
    "sg:city":"Schaarbeek/schaerbeek",
    "sg:orig_category":"Artsen and specialisten",
    "sg:phone":"+32 2 734 27 70",
    "sg:postcode":"1030",
    "sg:province":"Bruxelles-Capitale",
    "wof:name":"Jean S'jongers",
    "wof:placetype":"venue"
},
  "geometry": {"coordinates":[4.3927979469,50.8498077393],"type":"Point"}
}