{
  "type": "Feature",
  "properties": {
    "iso:country":"BE",
    "sg:address":"Biezestraat 20",
    "sg:city":"Nevele (merendree)",
    "sg:classifiers":[
        {
            "category":"Health Services",
            "subcategory":"Medical Lab",
            "type":"Services"
        }
    ],
    "sg:phone":"+32 9 371 64 44",
    "sg:postcode":"9850",
    "sg:province":"Oost-Vlaanderen",
    "sg:tags":[
        "laboratory",
        "dental"
    ],
    "wof:name":"Novodent Bvba",
    "wof:placetype":"venue"
},
  "geometry": {"coordinates":[3.5906360149,51.0757904053],"type":"Point"}
}