{
  "type": "Feature",
  "properties": {
    "addr:full":"Sint-jansplein 1a Kontich Antwerpen 2550",
    "addr:housenumber":"1a",
    "addr:postcode":"2550",
    "addr:street":"Sint-Jansplein",
    "iso:country":"BE",
    "sg:address":"Sint-jansplein 1a",
    "sg:city":"Kontich",
    "sg:classifiers":[
        {
            "category":"Food & Beverages",
            "subcategory":"Specialty",
            "type":"Retail Goods"
        }
    ],
    "sg:phone":"+32 3 458 38 00",
    "sg:postcode":"2550",
    "sg:province":"Antwerpen",
    "sg:tags":[
        "health",
        "dietary",
        "-",
        "biological"
    ],
    "wof:name":"Eko-winkel",
    "wof:placetype":"venue"
},
  "geometry": {"coordinates":[4.4455399513,51.1338729858],"type":"Point"}
}