{
  "type": "Feature",
  "properties": {
    "iso:country":"BE",
    "sg:address":"4\u00e8me Avenue 45",
    "sg:city":"Herstal",
    "sg:classifiers":[
        {
            "category":"Shopping",
            "subcategory":"Stationery & Office Supplies",
            "type":"Retail Goods"
        }
    ],
    "sg:phone":"+32 4 240 58 74",
    "sg:postcode":"4040",
    "sg:province":"Li\u00e8ge",
    "sg:tags":[
        "partition"
    ],
    "wof:name":"Co-terre Safs",
    "wof:placetype":"venue"
},
  "geometry": {"coordinates":[5.6207761765,50.6997451782],"type":"Point"}
}