{
  "type": "Feature",
  "properties": {
    "addr:full":"Hollebekestraat 21 Heuvelland West-Vlaanderen 8953",
    "addr:housenumber":"21",
    "addr:postcode":"8953",
    "addr:street":"Hollebekestraat",
    "iso:country":"BE",
    "sg:address":"Hollebekestraat 21",
    "sg:city":"Heuvelland",
    "sg:orig_category":"Varkenskwekers",
    "sg:phone":"+32 57 20 14 18",
    "sg:postcode":"8953",
    "sg:province":"West-Vlaanderen",
    "wof:name":"Luc Masson",
    "wof:placetype":"venue"
},
  "geometry": {"coordinates":[2.9167098999,50.7985076904],"type":"Point"}
}