{
  "type": "Feature",
  "properties": {
    "addr:full":"Avenue Des Bouleaux 10 Mont-saint-guibert Brabant Wallon 1435",
    "addr:housenumber":"10",
    "addr:postcode":"1435",
    "addr:street":"Avenue Des Bouleaux",
    "iso:country":"BE",
    "sg:address":"Avenue Des Bouleaux 10",
    "sg:city":"Mont-saint-guibert",
    "sg:classifiers":[
        {
            "category":"Professional",
            "subcategory":"Printing & Photocopies",
            "type":"Services"
        }
    ],
    "sg:phone":"+32 10 45 26 50",
    "sg:postcode":"1435",
    "sg:province":"Brabant Wallon",
    "sg:tags":[
        "-",
        "publishing",
        "desktop"
    ],
    "wof:name":"Lean Sprl",
    "wof:placetype":"venue"
},
  "geometry": {"coordinates":[4.6006321907,50.6562194824],"type":"Point"}
}