{
  "type": "Feature",
  "properties": {
    "addr:full":"Chauss\u00e9e De Tervuren 4 Waterloo Brabant Wallon 1410",
    "addr:housenumber":"4",
    "addr:postcode":"1410",
    "addr:street":"Chausse\u0301E De Tervuren",
    "iso:country":"BE",
    "sg:address":"Chauss\u00e9e De Tervuren 4",
    "sg:city":"Waterloo",
    "sg:classifiers":[
        {
            "category":"Bars & Pubs",
            "type":"Food & Drink"
        }
    ],
    "sg:phone":"+32 2 351 26 88",
    "sg:postcode":"1410",
    "sg:province":"Brabant Wallon",
    "sg:tags":[
        "tavern"
    ],
    "wof:name":"Arcelle (l')",
    "wof:placetype":"venue"
},
  "geometry": {"coordinates":[4.4025659561,50.7014045715],"type":"Point"}
}