{
  "type": "Feature",
  "properties": {
    "iso:country":"BE",
    "sg:address":"Klapdorp 60",
    "sg:city":"Sint-gillis-waas",
    "sg:orig_category":"Rev\u00eatements pour sols and murs. Construction de maisons. Rev\u00eatements de sols and murs",
    "sg:phone":"+32 3 766 27 17",
    "sg:postcode":"9170",
    "sg:province":"Oost-Vlaanderen",
    "wof:name":"De Stobbeleir",
    "wof:placetype":"venue"
},
  "geometry": {"coordinates":[4.0908899307,51.1897201538],"type":"Point"}
}