{
  "type": "Feature",
  "properties": {
    "addr:full":"Avenue De L'europe 17 Charleroi Hainaut 6000",
    "addr:housenumber":"17",
    "addr:postcode":"6000",
    "addr:street":"Avenue De L'Europe;Hainaut",
    "iso:country":"BE",
    "sg:address":"Avenue De L'europe 17",
    "sg:city":"Charleroi",
    "sg:classifiers":[
        {
            "category":"Personal",
            "subcategory":"Beauty Salon",
            "type":"Services"
        }
    ],
    "sg:phone":"+32 71 31 65 02",
    "sg:postcode":"6000",
    "sg:province":"Hainaut",
    "sg:tags":[
        "equipment",
        "hairdressing",
        "-",
        "supply"
    ],
    "wof:name":"Commerciale Europa",
    "wof:placetype":"venue"
},
  "geometry": {"coordinates":[4.4363341331,50.40990448],"type":"Point"}
}