{
  "type": "Feature",
  "properties": {
    "addr:full":"Chauss\u00c9e De Bruxelles 37-39 Bruxelles Bruxelles-Capitale 1000",
    "addr:postcode":"37-39;1000",
    "addr:street":"Chausse\u0301E De Bruxelles",
    "iso:country":"BE",
    "sg:address":"Chauss\u00c9e De Bruxelles 37-39",
    "sg:city":"Bruxelles",
    "sg:orig_category":"Meubles D\u00e9taillants, Am\u00e9nagement de B\u00e2timents et de Cuisines",
    "sg:phone":"+32 2 511 73 79",
    "sg:postcode":"1000",
    "sg:province":"Bruxelles-Capitale",
    "wof:name":"Compass Meuble",
    "wof:placetype":"venue"
},
  "geometry": {"coordinates":[4.3182368279,50.8107261658],"type":"Point"}
}