{
  "type": "Feature",
  "properties": {
    "iso:country":"BE",
    "sg:address":"Guldensporenlei 67",
    "sg:city":"Turnhout",
    "sg:orig_category":"Baby- and kinderkleding Babyspullen",
    "sg:phone":"+32 14 42 29 36",
    "sg:postcode":"2300",
    "sg:province":"Antwerpen",
    "wof:name":"Huis Pagaderke",
    "wof:placetype":"venue"
},
  "geometry": {"coordinates":[4.934899807,51.3259124756],"type":"Point"}
}