{
  "type": "Feature",
  "properties": {
    "addr:full":"Rue De Turenne 28 Braine-le-comte (steenkerque) Hainaut 7090",
    "addr:housenumber":"28",
    "addr:postcode":"7090",
    "addr:street":"Rue De Turenne;Hainaut",
    "iso:country":"BE",
    "sg:address":"Rue De Turenne 28",
    "sg:city":"Braine-le-comte (steenkerque)",
    "sg:classifiers":[
        {
            "category":"Professional",
            "subcategory":"Management & Consulting",
            "type":"Services"
        }
    ],
    "sg:phone":"+32 67 63 78 69",
    "sg:postcode":"7090",
    "sg:province":"Hainaut",
    "sg:tags":[
        "consultant",
        "relation",
        "public"
    ],
    "wof:name":"Ferminne M",
    "wof:placetype":"venue"
},
  "geometry": {"coordinates":[4.0676298141,50.6410636902],"type":"Point"}
}