{
  "type": "Feature",
  "properties": {
    "iso:country":"BE",
    "sg:address":"Lanestraat 18",
    "sg:city":"Overijse",
    "sg:classifiers":[
        {
            "category":"Building & Trades",
            "subcategory":"Pest Control",
            "type":"Services"
        }
    ],
    "sg:phone":"+32 2 687 55 90",
    "sg:postcode":"3090",
    "sg:province":"Vlaams-Brabant",
    "sg:tags":[
        "painting",
        "contractor"
    ],
    "wof:name":"Gil Decor",
    "wof:placetype":"venue"
},
  "geometry": {"coordinates":[4.5716300011,50.7513885498],"type":"Point"}
}