{
  "type": "Feature",
  "properties": {
    "addr:full":"Lokerenbaan 20 Zele Oost-Vlaanderen 9240",
    "addr:housenumber":"20",
    "addr:postcode":"9240",
    "addr:street":"Lokerenbaan",
    "iso:country":"BE",
    "sg:address":"Lokerenbaan 20",
    "sg:city":"Zele",
    "sg:orig_category":"Supermarkten Warenhuizen",
    "sg:phone":"+32 52 44 48 94",
    "sg:postcode":"9240",
    "sg:province":"Oost-Vlaanderen",
    "wof:name":"Unic",
    "wof:placetype":"venue"
},
  "geometry": {"coordinates":[4.0405869484,51.0744438171],"type":"Point"}
}