{
  "type": "Feature",
  "properties": {
    "addr:full":"Kruiskalsijdestraat 4 Ieper West-Vlaanderen 8900",
    "addr:housenumber":"4",
    "addr:postcode":"8900",
    "addr:street":"Kruiskalsijdestraat",
    "iso:country":"BE",
    "sg:address":"Kruiskalsijdestraat 4",
    "sg:city":"Ieper",
    "sg:orig_category":"V\u00e9hicules automobiles",
    "sg:phone":"+32 57 20 01 05",
    "sg:postcode":"8900",
    "sg:province":"West-Vlaanderen",
    "wof:name":"Carrosserie Gamme",
    "wof:placetype":"venue"
},
  "geometry": {"coordinates":[2.9131228924,50.8590736389],"type":"Point"}
}