{
  "type": "Feature",
  "properties": {
    "iso:country":"BE",
    "sg:address":"Moerkerkse Steenweg 297",
    "sg:city":"Brugge",
    "sg:orig_category":"Boucheries",
    "sg:phone":"+32 50 35 77 14",
    "sg:postcode":"8310",
    "sg:province":"West-Vlaanderen",
    "wof:name":"Beenhouwerij Meire",
    "wof:placetype":"venue"
},
  "geometry": {"coordinates":[3.2555921078,51.2139205933],"type":"Point"}
}