{
  "type": "Feature",
  "properties": {
    "addr:full":"Wijkstraat 16bb Diepenbeek Limburg 3590",
    "addr:housenumber":"16bb",
    "addr:postcode":"3590",
    "addr:street":"Wijkstraat",
    "iso:country":"BE",
    "sg:address":"Wijkstraat 16bb",
    "sg:city":"Diepenbeek",
    "sg:classifiers":[
        {
            "category":"Health Services",
            "subcategory":"Nursing And Care Facility",
            "type":"Services"
        }
    ],
    "sg:phone":"+32 11 33 23 33",
    "sg:postcode":"3590",
    "sg:province":"Limburg",
    "sg:tags":[
        "public"
    ],
    "wof:name":"Limb.intercom.milieubeh.",
    "wof:placetype":"venue"
},
  "geometry": {"coordinates":[5.4217400551,50.9076423645],"type":"Point"}
}