{
  "type": "Feature",
  "properties": {
    "addr:full":"Mijlstraat 309 Duffel Antwerpen 2570",
    "addr:housenumber":"309",
    "addr:postcode":"2570",
    "addr:street":"Mijlstraat",
    "iso:country":"BE",
    "sg:address":"Mijlstraat 309",
    "sg:city":"Duffel",
    "sg:classifiers":[
        {
            "category":"Building & Trades",
            "subcategory":"Cleaning & Sanitation",
            "type":"Services"
        }
    ],
    "sg:phone":"+32 475 39 37 11",
    "sg:postcode":"2570",
    "sg:province":"Antwerpen",
    "sg:tags":[
        "sweep",
        "chimney"
    ],
    "wof:name":"Pintens Frank",
    "wof:placetype":"venue"
},
  "geometry": {"coordinates":[4.5466709137,51.1048088074],"type":"Point"}
}