{
  "type": "Feature",
  "properties": {
    "iso:country":"BE",
    "sg:address":"Rue Des Douze Hommes 32",
    "sg:city":"Sprimont (louveign\u00e9)",
    "sg:classifiers":[
        {
            "category":"Building & Trades",
            "subcategory":"Construction",
            "type":"Services"
        }
    ],
    "sg:phone":"+32 4 360 97 24",
    "sg:postcode":"4141",
    "sg:province":"Li\u00e8ge",
    "sg:tags":[
        "stucco",
        "contractor"
    ],
    "wof:name":"Bragard Alain",
    "wof:placetype":"venue"
},
  "geometry": {"coordinates":[5.7448840141,50.5409202576],"type":"Point"}
}