{
  "type": "Feature",
  "properties": {
    "iso:country":"BE",
    "sg:address":"Grand-rue 20",
    "sg:city":"Aubange",
    "sg:orig_category":"Apotheken",
    "sg:phone":"+32 63 38 81 28",
    "sg:postcode":"6791",
    "sg:province":"Luxembourg",
    "wof:name":"Pharmathus",
    "wof:placetype":"venue"
},
  "geometry": {"coordinates":[5.8368549347,49.5628395081],"type":"Point"}
}