{
  "type": "Feature",
  "properties": {
    "addr:full":"Grote Baan 242 Lovendegem Oost-Vlaanderen 9920",
    "addr:housenumber":"242",
    "addr:postcode":"9920",
    "addr:street":"Grote Baan",
    "iso:country":"BE",
    "sg:address":"Grote Baan 242",
    "sg:city":"Lovendegem",
    "sg:orig_category":"Afval and schroot Gh",
    "sg:phone":"+32 9 372 89 54",
    "sg:postcode":"9920",
    "sg:province":"Oost-Vlaanderen",
    "wof:name":"Roland Goossens",
    "wof:placetype":"venue"
},
  "geometry": {"coordinates":[3.6124300957,51.1129226685],"type":"Point"}
}