{
  "type": "Feature",
  "properties": {
    "addr:full":"Avenue Des Erables 12 Braine L'alleud (braine-l'alleud) Brabant Wallon 1420",
    "addr:housenumber":"12",
    "addr:postcode":"1420",
    "addr:street":"Avenue Des Erables",
    "iso:country":"BE",
    "sg:address":"Avenue Des Erables 12",
    "sg:city":"Braine L'alleud (braine-l'alleud)",
    "sg:classifiers":[
        {
            "category":"Banks & Credit Unions",
            "subcategory":"Investment Brokerage",
            "type":"Services"
        }
    ],
    "sg:phone":"+32 2 387 30 63",
    "sg:postcode":"1420",
    "sg:province":"Brabant Wallon",
    "sg:tags":[
        "auditor"
    ],
    "wof:name":"Doyen X",
    "wof:placetype":"venue"
},
  "geometry": {"coordinates":[-0.6972190142,47.4308052063],"type":"Point"}
}