{
  "type": "Feature",
  "properties": {
    "addr:full":"Jacob Van Maerlantstraat 3 Damme West-Vlaanderen 8340",
    "addr:housenumber":"3",
    "addr:postcode":"8340",
    "addr:street":"Jacob Van Maerlantstraat",
    "iso:country":"BE",
    "sg:address":"Jacob Van Maerlantstraat 3",
    "sg:city":"Damme",
    "sg:orig_category":"Musea and historische gebouwen",
    "sg:phone":"+32 50 35 33 19",
    "sg:postcode":"8340",
    "sg:province":"West-Vlaanderen",
    "wof:name":"Uilenspiegel-maerlantmus.",
    "wof:placetype":"venue"
},
  "geometry": {"coordinates":[3.2817249298,51.2513046265],"type":"Point"}
}