{
  "type": "Feature",
  "properties": {
    "iso:country":"BE",
    "sg:address":"Koningin Elisabethlaan 86",
    "sg:city":"Sint-niklaas",
    "sg:classifiers":[
        {
            "category":"Cafe",
            "type":"Food & Drink"
        }
    ],
    "sg:phone":"+32 3 777 76 26",
    "sg:postcode":"9100",
    "sg:province":"Oost-Vlaanderen",
    "sg:tags":[
        "caf\u00e9s"
    ],
    "wof:name":"Zed",
    "wof:placetype":"venue"
},
  "geometry": {"coordinates":[4.155875206,51.1704444885],"type":"Point"}
}