{
  "type": "Feature",
  "properties": {
    "addr:full":"Comberg 29b Fourons (fouron-st.-martin) Limburg 3790",
    "addr:housenumber":"29b",
    "addr:postcode":"3790",
    "addr:street":"Comberg;Limburg",
    "iso:country":"BE",
    "sg:address":"Comberg 29b",
    "sg:city":"Fourons (fouron-st.-martin)",
    "sg:classifiers":[
        {
            "category":"Community Center",
            "subcategory":"Youth",
            "type":"Public Place"
        }
    ],
    "sg:phone":"+32 4 381 11 10",
    "sg:postcode":"3790",
    "sg:province":"Limburg",
    "sg:tags":[
        "club"
    ],
    "wof:name":"Veurs (de) - Jeugdherberg",
    "wof:placetype":"venue"
},
  "geometry": {"coordinates":[5.8144469261,50.7511444092],"type":"Point"}
}