{
  "type": "Feature",
  "properties": {
    "addr:full":"Avenue Brugmann 30 Sint-gillis/saint-gilles Bruxelles-Capitale 1060",
    "addr:housenumber":"30",
    "addr:postcode":"1060",
    "addr:street":"Avenue Brugmann",
    "iso:country":"BE",
    "sg:address":"Avenue Brugmann 30",
    "sg:city":"Sint-gillis/saint-gilles",
    "sg:orig_category":"Administration d'immeubles",
    "sg:phone":"+32 2 344 17 97",
    "sg:postcode":"1060",
    "sg:province":"Bruxelles-Capitale",
    "wof:name":"Bur. La Gestion Immeubles",
    "wof:placetype":"venue"
},
  "geometry": {"coordinates":[4.3528938293,50.8211708069],"type":"Point"}
}