{
  "type": "Feature",
  "properties": {
    "iso:country":"BE",
    "sg:address":"Avenues Des Hauts De Meuse 54",
    "sg:city":"Namur",
    "sg:classifiers":[
        {
            "category":"Insurance",
            "subcategory":"Insurance Agent",
            "type":"Services"
        }
    ],
    "sg:phone":"+32 81 30 42 60",
    "sg:postcode":"5101",
    "sg:province":"Namur",
    "sg:tags":[
        "verzekeringsmakelaars",
        "expert"
    ],
    "wof:name":"Denis J.l.",
    "wof:placetype":"venue"
},
  "geometry": {"coordinates":[4.8960251808,50.4327087402],"type":"Point"}
}