{
  "type": "Feature",
  "properties": {
    "addr:full":"Rue Du Longpr\u00e9 6 Fleurus (saint-amand) Hainaut 6221",
    "addr:housenumber":"6",
    "addr:postcode":"6221",
    "addr:street":"Rue Du Longpre\u0301",
    "iso:country":"BE",
    "sg:address":"Rue Du Longpr\u00e9 6",
    "sg:city":"Fleurus (saint-amand)",
    "sg:orig_category":"Non-Classified Establishments",
    "sg:phone":"+32 71 81 83 54",
    "sg:postcode":"6221",
    "sg:province":"Hainaut",
    "wof:name":"Taillefer B",
    "wof:placetype":"venue"
},
  "geometry": {"coordinates":[4.5451278687,50.5142593384],"type":"Point"}
}