{
  "type": "Feature",
  "properties": {
    "iso:country":"BE",
    "sg:address":"Chauss\u00e9e De Dinant 485b",
    "sg:city":"Namur",
    "sg:classifiers":[
        {
            "category":"Health Services",
            "subcategory":"Doctor",
            "type":"Services"
        }
    ],
    "sg:phone":"+32 81 30 85 75",
    "sg:postcode":"5000",
    "sg:province":"Namur",
    "sg:tags":[
        "psychotherapist",
        "psychoanalyst"
    ],
    "wof:name":"Leurquin C",
    "wof:placetype":"venue"
},
  "geometry": {"coordinates":[4.8617630005,50.4657287598],"type":"Point"}
}