{
  "type": "Feature",
  "properties": {
    "iso:country":"BE",
    "sg:address":"Rue De La Butte 9",
    "sg:city":"Braine-le-comte (hennuy\u00e8res)",
    "sg:classifiers":[
        {
            "category":"Food & Beverages",
            "subcategory":"Groceries & Convenience Stores",
            "type":"Retail Goods"
        }
    ],
    "sg:phone":"+32 67 56 13 43",
    "sg:postcode":"7090",
    "sg:province":"Hainaut",
    "sg:tags":[
        "grocer"
    ],
    "wof:name":"Battard",
    "wof:placetype":"venue"
},
  "geometry": {"coordinates":[4.1702919006,50.6389083862],"type":"Point"}
}