{
  "type": "Feature",
  "properties": {
    "iso:country":"BE",
    "sg:address":"Route De Neufchateau 67a",
    "sg:city":"Hompre",
    "sg:classifiers":[
        {
            "category":"Government",
            "subcategory":"Department Of Motor Vehicles",
            "type":"Public Place"
        }
    ],
    "sg:phone":"+32 61 25 61 71",
    "sg:postcode":"6640",
    "sg:province":"Luxembourg",
    "sg:tags":[
        "planing",
        "wood",
        "sawing"
    ],
    "wof:name":"Faber-mercier Scierie",
    "wof:placetype":"venue"
},
  "geometry": {"coordinates":[5.5269980431,49.8988456726],"type":"Point"}
}