{
  "type": "Feature",
  "properties": {
    "addr:full":"Platanenlaan 12 Grimbergen Vlaams-Brabant 1850",
    "addr:housenumber":"12",
    "addr:postcode":"1850",
    "addr:street":"Platanenlaan",
    "iso:country":"BE",
    "sg:address":"Platanenlaan 12",
    "sg:city":"Grimbergen",
    "sg:orig_category":"Woningbouw",
    "sg:phone":"+32 2 270 90 14",
    "sg:postcode":"1850",
    "sg:province":"Vlaams-Brabant",
    "wof:name":"Carl Maton",
    "wof:placetype":"venue"
},
  "geometry": {"coordinates":[4.3760271072,50.9293174744],"type":"Point"}
}