{
  "type": "Feature",
  "properties": {
    "addr:full":"Rue De Stalle 175 Bruxelles (uccle) Bruxelles-Capitale 1180",
    "addr:housenumber":"175",
    "addr:postcode":"1180",
    "addr:street":"Rue De Stalle",
    "iso:country":"BE",
    "sg:address":"Rue De Stalle 175",
    "sg:city":"Bruxelles (uccle)",
    "sg:classifiers":[
        {
            "category":"Professional",
            "subcategory":"Art Services",
            "type":"Services"
        }
    ],
    "sg:phone":"+32 477 91 25 91",
    "sg:postcode":"1180",
    "sg:province":"Bruxelles-Capitale",
    "sg:tags":[
        "photographer"
    ],
    "wof:name":"Mouchaers K",
    "wof:placetype":"venue"
},
  "geometry": {"coordinates":[4.3222551346,50.7962760925],"type":"Point"}
}