{
  "type": "Feature",
  "properties": {
    "addr:full":"Dr\u00c8ve Firmin Carpentier 11 Gesves Namur 5340",
    "addr:housenumber":"11",
    "addr:postcode":"5340",
    "addr:street":"Dre\u0300Ve Firmin Carpentier",
    "iso:country":"BE",
    "sg:address":"Dr\u00c8ve Firmin Carpentier 11",
    "sg:city":"Gesves",
    "sg:orig_category":"Antiek",
    "sg:phone":"+32 81 57 05 55",
    "sg:postcode":"5340",
    "sg:province":"Namur",
    "wof:name":"Maison Meuse Antique",
    "wof:placetype":"venue"
},
  "geometry": {"coordinates":[5.0143728256,50.4422569275],"type":"Point"}
}