{
  "type": "Feature",
  "properties": {
    "addr:full":"Gouden Leeuwstraat 92 Sint-niklaas (belsele) Oost-Vlaanderen 9111",
    "addr:housenumber":"92",
    "addr:postcode":"9111",
    "addr:street":"Gouden Leeuwstraat",
    "iso:country":"BE",
    "sg:address":"Gouden Leeuwstraat 92",
    "sg:city":"Sint-niklaas (belsele)",
    "sg:classifiers":[
        {
            "category":"Real Estate",
            "subcategory":"Real Estate Services",
            "type":"Services"
        }
    ],
    "sg:phone":"+32 3 772 53 55",
    "sg:postcode":"9111",
    "sg:province":"Oost-Vlaanderen",
    "wof:name":"Dhollander G",
    "wof:placetype":"venue"
},
  "geometry": {"coordinates":[4.0671591759,51.1601638794],"type":"Point"}
}