{
  "type": "Feature",
  "properties": {
    "iso:country":"BE",
    "sg:address":"Rue De Marche 60",
    "sg:city":"Bastogne",
    "sg:classifiers":[
        {
            "category":"Insurance",
            "subcategory":"Insurance Agent",
            "type":"Services"
        }
    ],
    "sg:phone":"+32 61 21 16 07",
    "sg:postcode":"6600",
    "sg:province":"Luxembourg",
    "sg:tags":[
        "verzekeringsmakelaars",
        "expert"
    ],
    "wof:name":"Bureau Nagassur",
    "wof:placetype":"venue"
},
  "geometry": {"coordinates":[5.7094349861,50.0018501282],"type":"Point"}
}