{
  "type": "Feature",
  "properties": {
    "iso:country":"BE",
    "sg:address":"Rue Du Moulin 75bl",
    "sg:city":"Ohey",
    "sg:classifiers":[
        {
            "category":"Cafe",
            "type":"Food & Drink"
        }
    ],
    "sg:phone":"+32 85 61 19 63",
    "sg:postcode":"5351",
    "sg:province":"Namur",
    "sg:tags":[
        "caf\u00e9s"
    ],
    "wof:name":"Michel Massy",
    "wof:placetype":"venue"
},
  "geometry": {"coordinates":[5.1375851631,50.4386177063],"type":"Point"}
}