{
  "type": "Feature",
  "properties": {
    "addr:full":"Rue E. Cuvelier 26 Namur Namur 5000",
    "addr:housenumber":"26",
    "addr:postcode":"5000",
    "addr:street":"Rue E. Cuvelier",
    "iso:country":"BE",
    "sg:address":"Rue E. Cuvelier 26",
    "sg:city":"Namur",
    "sg:orig_category":"V\u00eatements",
    "sg:phone":"+32 81 22 13 59",
    "sg:postcode":"5000",
    "sg:province":"Namur",
    "wof:name":"Chipito Jeans",
    "wof:placetype":"venue"
},
  "geometry": {"coordinates":[4.8665390015,50.4646873474],"type":"Point"}
}