{
  "type": "Feature",
  "properties": {
    "addr:full":"Rue D'arlon 10 Messancy Luxembourg 6780",
    "addr:housenumber":"10",
    "addr:postcode":"6780",
    "addr:street":"Rue D'Arlon",
    "iso:country":"BE",
    "sg:address":"Rue D'arlon 10",
    "sg:city":"Messancy",
    "sg:orig_category":"Geschenken and souvenirs Verlichting and huishoudartikelen",
    "sg:phone":"+32 63 38 76 29",
    "sg:postcode":"6780",
    "sg:province":"Luxembourg",
    "wof:name":"Casa",
    "wof:placetype":"venue"
},
  "geometry": {"coordinates":[5.8132858276,49.5964508057],"type":"Point"}
}