{
  "type": "Feature",
  "properties": {
    "iso:country":"BE",
    "sg:address":"Jan Lindtsstraat 10",
    "sg:city":"Hoeilaart",
    "sg:classifiers":[
        {
            "category":"Professional",
            "subcategory":"Advertising",
            "type":"Services"
        }
    ],
    "sg:phone":"+32 2 657 90 70",
    "sg:postcode":"1560",
    "sg:province":"Vlaams-Brabant",
    "sg:tags":[
        "bill",
        "-",
        "posting"
    ],
    "wof:name":"Verhulst Sprl",
    "wof:placetype":"venue"
},
  "geometry": {"coordinates":[4.4662971497,50.7777824402],"type":"Point"}
}