{
  "type": "Feature",
  "properties": {
    "iso:country":"BE",
    "sg:address":"Oostendelaan 195",
    "sg:city":"Middelkerke",
    "sg:orig_category":"Kampeerterreinen",
    "sg:phone":"+32 59 31 07 88",
    "sg:postcode":"8430",
    "sg:province":"West-Vlaanderen",
    "wof:name":"Camping Duinenvallei",
    "wof:placetype":"venue"
},
  "geometry": {"coordinates":[2.822439909,51.1859397888],"type":"Point"}
}