{
  "type": "Feature",
  "properties": {
    "addr:full":"Lichttorenplein 8 Knokke-heist West-Vlaanderen 8300",
    "addr:housenumber":"8",
    "addr:postcode":"8300",
    "addr:street":"Lichttorenplein",
    "iso:country":"BE",
    "sg:address":"Lichttorenplein 8",
    "sg:city":"Knokke-heist",
    "sg:classifiers":[
        {
            "category":"Personal",
            "subcategory":"Beauty Salon",
            "type":"Services"
        }
    ],
    "sg:phone":"+32 50 60 49 87",
    "sg:postcode":"8300",
    "sg:province":"West-Vlaanderen",
    "sg:tags":[
        "de",
        "coiffure"
    ],
    "wof:name":"Jacques Dessange",
    "wof:placetype":"venue"
},
  "geometry": {"coordinates":[3.287694931,51.3467254639],"type":"Point"}
}