{
  "type": "Feature",
  "properties": {
    "iso:country":"BE",
    "sg:address":"Hector Henneaulaan 366",
    "sg:city":"Zaventem",
    "sg:orig_category":"Wasserijen, Reiniging and Droogkuis",
    "sg:phone":"+32 2 261 02 44",
    "sg:postcode":"1930",
    "sg:province":"Vlaams-Brabant",
    "wof:name":"Chem-dry",
    "wof:placetype":"venue"
},
  "geometry": {"coordinates":[4.4667410851,50.8808898926],"type":"Point"}
}