{
  "type": "Feature",
  "properties": {
    "iso:country":"BE",
    "sg:address":"Lutticher Strasse 123",
    "sg:city":"Kelmis/la Calamine",
    "sg:orig_category":"Drukkerijen and copyshops",
    "sg:phone":"+32 87 65 78 72",
    "sg:postcode":"4721",
    "sg:province":"Li\u00e8ge",
    "wof:name":"Franz Heidenthal",
    "wof:placetype":"venue"
},
  "geometry": {"coordinates":[6.0195021629,50.7176475525],"type":"Point"}
}