{
  "type": "Feature",
  "properties": {
    "iso:country":"BE",
    "sg:address":"Rue De Wervicq 9",
    "sg:city":"Comines-warneton (comines)",
    "sg:classifiers":[
        {
            "category":"Shopping",
            "subcategory":"Clothing, Apparel, & Fashions",
            "type":"Retail Goods"
        }
    ],
    "sg:phone":"+32 56 55 73 44",
    "sg:postcode":"7780",
    "sg:province":"Hainaut",
    "sg:tags":[
        "purchase",
        "clothing",
        "-",
        "sale",
        "second-hand"
    ],
    "wof:name":"Euro Bazar",
    "wof:placetype":"venue"
},
  "geometry": {"coordinates":[3.002974987,50.7696495056],"type":"Point"}
}