{
  "type": "Feature",
  "properties": {
    "iso:country":"BE",
    "sg:address":"Rue Lambert Dewonck 167",
    "sg:city":"Ans",
    "sg:orig_category":"Epiceries",
    "sg:phone":"+32 4 263 40 94",
    "sg:postcode":"4432",
    "sg:province":"Li\u00e8ge",
    "wof:name":"Mathias Waleffe",
    "wof:placetype":"venue"
},
  "geometry": {"coordinates":[5.5131750107,50.6658096313],"type":"Point"}
}