{
  "type": "Feature",
  "properties": {
    "addr:full":"Halmstraat 4 Genk (waterschei) Limburg 3600",
    "addr:housenumber":"4",
    "addr:postcode":"3600",
    "addr:street":"Halmstraat",
    "iso:country":"BE",
    "sg:address":"Halmstraat 4",
    "sg:city":"Genk (waterschei)",
    "sg:classifiers":[
        {
            "category":"Social Services",
            "type":"Services"
        }
    ],
    "sg:phone":"+32 89 84 44 95",
    "sg:postcode":"3600",
    "sg:province":"Limburg",
    "wof:name":"De Sluis Vzw",
    "wof:placetype":"venue"
},
  "geometry": {"coordinates":[5.5114088058,50.9993591309],"type":"Point"}
}