{
  "type": "Feature",
  "properties": {
    "addr:full":"Rue Du Centre 54a Clavier (les Avins) Li\u00e8ge 4560",
    "addr:housenumber":"54a",
    "addr:postcode":"4560",
    "addr:street":"Rue Du Centre",
    "iso:country":"BE",
    "sg:address":"Rue Du Centre 54a",
    "sg:city":"Clavier (les Avins)",
    "sg:classifiers":[
        {
            "category":"Real Estate",
            "subcategory":"Architect",
            "type":"Services"
        }
    ],
    "sg:phone":"+32 85 41 15 12",
    "sg:postcode":"4560",
    "sg:province":"Li\u00e8ge",
    "wof:name":"Cr\u00e8vecoeur Ph",
    "wof:placetype":"venue"
},
  "geometry": {"coordinates":[5.3014497757,50.4160499573],"type":"Point"}
}