{
  "type": "Feature",
  "properties": {
    "iso:country":"BE",
    "sg:address":"Saneveldstraat 3a",
    "sg:city":"Zoutleeuw",
    "sg:orig_category":"Animations diverses",
    "sg:phone":"+32 11 58 11 15",
    "sg:postcode":"3440",
    "sg:province":"Vlaams-Brabant",
    "wof:name":"Gerry Leenders",
    "wof:placetype":"venue"
},
  "geometry": {"coordinates":[5.0752182007,50.8629455566],"type":"Point"}
}