{
  "type": "Feature",
  "properties": {
    "addr:full":"Nieuwstraat 30 Kaprijke Oost-Vlaanderen 9971",
    "addr:housenumber":"30",
    "addr:postcode":"9971",
    "addr:street":"Nieuwstraat",
    "iso:country":"BE",
    "sg:address":"Nieuwstraat 30",
    "sg:city":"Kaprijke",
    "sg:orig_category":"Dierenartsen",
    "sg:phone":"+32 9 377 38 37",
    "sg:postcode":"9971",
    "sg:province":"Oost-Vlaanderen",
    "wof:name":"Antoine De Keyster",
    "wof:placetype":"venue"
},
  "geometry": {"coordinates":[3.6237869263,51.1947822571],"type":"Point"}
}