{
  "type": "Feature",
  "properties": {
    "addr:full":"Avenue De La Motte 18 Genappe (bousval) Brabant Wallon 1470",
    "addr:housenumber":"18",
    "addr:postcode":"1470",
    "addr:street":"Avenue De La Motte;Wallon",
    "iso:country":"BE",
    "sg:address":"Avenue De La Motte 18",
    "sg:city":"Genappe (bousval)",
    "sg:classifiers":[
        {
            "category":"Insurance",
            "subcategory":"Insurance Agent",
            "type":"Services"
        }
    ],
    "sg:phone":"+32 10 61 51 09",
    "sg:postcode":"1470",
    "sg:province":"Brabant Wallon",
    "sg:tags":[
        "broker"
    ],
    "wof:name":"A.p.i. Consult Sprl",
    "wof:placetype":"venue"
},
  "geometry": {"coordinates":[4.5282478333,50.6383094788],"type":"Point"}
}