{
  "type": "Feature",
  "properties": {
    "addr:full":"Terhulpensesteenweg 13 Ukkel/uccle Bruxelles-Capitale 1180",
    "addr:housenumber":"13",
    "addr:postcode":"1180",
    "addr:street":"Terhulpensesteenweg;/",
    "iso:country":"BE",
    "sg:address":"Terhulpensesteenweg 13",
    "sg:city":"Ukkel/uccle",
    "sg:orig_category":"Reclamebureaus",
    "sg:phone":"+32 2 374 07 28",
    "sg:postcode":"1180",
    "sg:province":"Bruxelles-Capitale",
    "wof:name":"M\u00c9dia Conseil",
    "wof:placetype":"venue"
},
  "geometry": {"coordinates":[4.3766469955,50.79945755],"type":"Point"}
}