{
  "type": "Feature",
  "properties": {
    "iso:country":"BE",
    "sg:address":"Bruneaustraat 901",
    "sg:city":"Gooik",
    "sg:orig_category":"Transports routiers de marchandises",
    "sg:phone":"+32 54 56 65 11",
    "sg:postcode":"1755",
    "sg:province":"Vlaams-Brabant",
    "wof:name":"De Vuyst",
    "wof:placetype":"venue"
},
  "geometry": {"coordinates":[4.1131100655,50.7618217468],"type":"Point"}
}