{
  "type": "Feature",
  "properties": {
    "iso:country":"BE",
    "sg:address":"Industrieweg 11",
    "sg:city":"Roeselare",
    "sg:classifiers":[
        {
            "category":"Banks & Credit Unions",
            "subcategory":"Investment Brokerage",
            "type":"Services"
        }
    ],
    "sg:phone":"+32 87 89 99 11",
    "sg:postcode":"8800",
    "sg:province":"West-Vlaanderen",
    "sg:tags":[
        "-",
        "transport",
        "related"
    ],
    "wof:name":"Transport Jean Heck",
    "wof:placetype":"venue"
},
  "geometry": {"coordinates":[6.0461602211,50.6460800171],"type":"Point"}
}