{
  "type": "Feature",
  "properties": {
    "iso:country":"BE",
    "sg:address":"Kannootdries 16",
    "sg:city":"Zwevegem",
    "sg:orig_category":"Entretien and r\u00e9parations de voitures",
    "sg:phone":"+32 56 45 61 00",
    "sg:postcode":"8554",
    "sg:province":"West-Vlaanderen",
    "wof:name":"Garage Debaere",
    "wof:placetype":"venue"
},
  "geometry": {"coordinates":[3.3706920147,50.7496185303],"type":"Point"}
}