{
  "type": "Feature",
  "properties": {
    "addr:full":"Rue Joseph Dufrane 39 Frameries Hainaut 7080",
    "addr:housenumber":"39",
    "addr:postcode":"7080",
    "addr:street":"Rue Joseph Dufrane",
    "iso:country":"BE",
    "sg:address":"Rue Joseph Dufrane 39",
    "sg:city":"Frameries",
    "sg:orig_category":"Bloemen and planten",
    "sg:phone":"+32 65 66 36 48",
    "sg:postcode":"7080",
    "sg:province":"Hainaut",
    "wof:name":"Le Bouquet Romantique",
    "wof:placetype":"venue"
},
  "geometry": {"coordinates":[3.8904850483,50.4074134827],"type":"Point"}
}