{
  "type": "Feature",
  "properties": {
    "addr:full":"Rue Du Trieu Kaisin 58 Ch\u00e2telet (ch\u00e2telineau) Hainaut 6200",
    "addr:housenumber":"58",
    "addr:postcode":"6200",
    "addr:street":"Rue Du Trieu Kaisin",
    "iso:country":"BE",
    "sg:address":"Rue Du Trieu Kaisin 58",
    "sg:city":"Ch\u00e2telet (ch\u00e2telineau)",
    "sg:classifiers":[
        {
            "category":"Shopping",
            "subcategory":"Shoes",
            "type":"Retail Goods"
        }
    ],
    "sg:phone":"+32 71 40 26 00",
    "sg:postcode":"6200",
    "sg:province":"Hainaut",
    "sg:tags":[
        "slipper",
        "-"
    ],
    "wof:name":"San Marina",
    "wof:placetype":"venue"
},
  "geometry": {"coordinates":[4.4989500046,50.4061737061],"type":"Point"}
}