{
  "type": "Feature",
  "properties": {
    "iso:country":"BE",
    "sg:address":"Kamerdellelaan 15",
    "sg:city":"Ukkel/uccle",
    "sg:orig_category":"Maatschappelijke dienstverlening",
    "sg:phone":"+32 2 374 89 10",
    "sg:postcode":"1180",
    "sg:province":"Bruxelles-Capitale",
    "wof:name":"Centre P.m.s.",
    "wof:placetype":"venue"
},
  "geometry": {"coordinates":[4.3466758728,50.8027038574],"type":"Point"}
}