{
  "type": "Feature",
  "properties": {
    "addr:full":"Sint-annalaan 159 Sint-genesius-rode/rhode-saint-genese Vlaams-Brabant 1640",
    "addr:housenumber":"159",
    "addr:postcode":"1640",
    "addr:street":"Sint-Annalaan",
    "iso:country":"BE",
    "sg:address":"Sint-annalaan 159",
    "sg:city":"Sint-genesius-rode/rhode-saint-genese",
    "sg:orig_category":"Fotografen and fotostudio's",
    "sg:phone":"+32 2 358 24 14",
    "sg:postcode":"1640",
    "sg:province":"Vlaams-Brabant",
    "wof:name":"Catherine Lacroix",
    "wof:placetype":"venue"
},
  "geometry": {"coordinates":[4.3749079704,50.7510261536],"type":"Point"}
}