{
  "type": "Feature",
  "properties": {
    "addr:full":"Afrikaansestraat 5 Sint-gillis/saint-gilles Bruxelles-Capitale 1060",
    "addr:housenumber":"5",
    "addr:postcode":"1060",
    "addr:street":"Afrikaansestraat",
    "iso:country":"BE",
    "sg:address":"Afrikaansestraat 5",
    "sg:city":"Sint-gillis/saint-gilles",
    "sg:orig_category":"Film-, tv- and videoproductie Installatie van houten of kunststof schrijnwerk",
    "sg:phone":"+32 2 215 54 28",
    "sg:postcode":"1060",
    "sg:province":"Bruxelles-Capitale",
    "wof:name":"Fe. Palladio",
    "wof:placetype":"venue"
},
  "geometry": {"coordinates":[4.3564620018,50.824131012],"type":"Point"}
}