{
  "type": "Feature",
  "properties": {
    "iso:country":"BE",
    "sg:address":"Middeldonk 2",
    "sg:city":"Grobbendonk",
    "sg:orig_category":"Eleveurs de bovins",
    "sg:phone":"+32 14 51 29 59",
    "sg:postcode":"2288",
    "sg:province":"Antwerpen",
    "wof:name":"Jozef Van Den Bulck",
    "wof:placetype":"venue"
},
  "geometry": {"coordinates":[4.7359938622,51.1555519104],"type":"Point"}
}