{
  "type": "Feature",
  "properties": {
    "iso:country":"BE",
    "sg:address":"Luxor Parc 18",
    "sg:city":"Bruxelles (auderghem)",
    "sg:classifiers":[
        {
            "category":"Communications",
            "subcategory":"Radio Station",
            "type":"Services"
        }
    ],
    "sg:phone":"+32 2 672 52 54",
    "sg:postcode":"1160",
    "sg:province":"Bruxelles-Capitale",
    "sg:tags":[
        "telephony"
    ],
    "wof:name":"Garmin-formar Electronics",
    "wof:placetype":"venue"
},
  "geometry": {"coordinates":[4.4298291206,50.8245887756],"type":"Point"}
}