{
  "type": "Feature",
  "properties": {
    "addr:full":"Knodbaan 10d Ranst Antwerpen 2520",
    "addr:housenumber":"10d",
    "addr:postcode":"2520",
    "addr:street":"Knodbaan",
    "iso:country":"BE",
    "sg:address":"Knodbaan 10d",
    "sg:city":"Ranst",
    "sg:orig_category":"Instituts de beaut\u00e9",
    "sg:phone":"+32 3 384 16 48",
    "sg:postcode":"2520",
    "sg:province":"Antwerpen",
    "wof:name":"Marianne Loosen",
    "wof:placetype":"venue"
},
  "geometry": {"coordinates":[4.5927810669,51.2177429199],"type":"Point"}
}