{
  "type": "Feature",
  "properties": {
    "iso:country":"BE",
    "sg:address":"Rue Grande 43",
    "sg:city":"Farciennes",
    "sg:orig_category":"Services de Nettoyage and de D\u00e9sinfection",
    "sg:phone":"+32 71 39 27 39",
    "sg:postcode":"6240",
    "sg:province":"Hainaut",
    "wof:name":"Jean-pol Gretzer",
    "wof:placetype":"venue"
},
  "geometry": {"coordinates":[4.5516600609,50.426700592],"type":"Point"}
}