{
  "type": "Feature",
  "properties": {
    "addr:full":"Chaamseweg 13 Baarle-hertog Antwerpen 2387",
    "addr:housenumber":"13",
    "addr:postcode":"2387",
    "addr:street":"Chaamseweg",
    "iso:country":"BE",
    "sg:address":"Chaamseweg 13",
    "sg:city":"Baarle-hertog",
    "sg:classifiers":[
        {
            "category":"Fast Food",
            "type":"Food & Drink"
        }
    ],
    "sg:phone":"+32 14 69 91 75",
    "sg:postcode":"2387",
    "sg:province":"Antwerpen",
    "sg:tags":[
        "fried",
        "stand",
        "potato"
    ],
    "wof:name":"De Koning",
    "wof:placetype":"venue"
},
  "geometry": {"coordinates":[4.9228491783,51.4452857971],"type":"Point"}
}