{
  "type": "Feature",
  "properties": {
    "addr:full":"Hofstraat 12b5 Oostende West-Vlaanderen 8400",
    "addr:housenumber":"12b5",
    "addr:postcode":"8400",
    "addr:street":"Hofstraat",
    "iso:country":"BE",
    "sg:address":"Hofstraat 12b5",
    "sg:city":"Oostende",
    "sg:orig_category":"M\u00e9decins and sp\u00e9cialistes",
    "sg:phone":"+32 59 80 14 63",
    "sg:postcode":"8400",
    "sg:province":"West-Vlaanderen",
    "wof:name":"Henri Raveschot",
    "wof:placetype":"venue"
},
  "geometry": {"coordinates":[2.9184660912,51.2343673706],"type":"Point"}
}