{
  "type": "Feature",
  "properties": {
    "addr:full":"Leeuwkensstraat 2 Waregem West-Vlaanderen 8790",
    "addr:housenumber":"2",
    "addr:postcode":"8790",
    "addr:street":"Leeuwkensstraat",
    "iso:country":"BE",
    "sg:address":"Leeuwkensstraat 2",
    "sg:city":"Waregem",
    "sg:orig_category":"Kansspelen",
    "sg:phone":"+32 56 60 23 78",
    "sg:postcode":"8790",
    "sg:province":"West-Vlaanderen",
    "wof:name":"Joklarama",
    "wof:placetype":"venue"
},
  "geometry": {"coordinates":[3.4314749241,50.8873558044],"type":"Point"}
}