{
  "type": "Feature",
  "properties": {
    "addr:full":"Industriepark 13b Heist-op-den-berg Antwerpen 2220",
    "addr:housenumber":"13b",
    "addr:postcode":"2220",
    "addr:street":"Industriepark",
    "iso:country":"BE",
    "sg:address":"Industriepark 13b",
    "sg:city":"Heist-op-den-berg",
    "sg:classifiers":[
        {
            "category":"Building & Trades",
            "subcategory":"Electrical",
            "type":"Services"
        }
    ],
    "sg:phone":"+32 15 25 03 78",
    "sg:postcode":"2220",
    "sg:province":"Antwerpen",
    "sg:tags":[
        "work",
        "installation"
    ],
    "wof:name":"Paul De Meutter C.v.",
    "wof:placetype":"venue"
},
  "geometry": {"coordinates":[4.7251381874,51.061756134],"type":"Point"}
}