{
  "type": "Feature",
  "properties": {
    "addr:full":"Thonissenlaan 31 Hasselt Limburg 3500",
    "addr:housenumber":"31",
    "addr:postcode":"3500",
    "addr:street":"Thonissenlaan",
    "iso:country":"BE",
    "sg:address":"Thonissenlaan 31",
    "sg:city":"Hasselt",
    "sg:orig_category":"MEUBELONTWERP AND -INSTALLATIE",
    "sg:phone":"+32 11 22 80 70",
    "sg:postcode":"3500",
    "sg:province":"Limburg",
    "wof:name":"Keukens Bulthaup",
    "wof:placetype":"venue"
},
  "geometry": {"coordinates":[5.334859848,50.9326782227],"type":"Point"}
}