{
  "type": "Feature",
  "properties": {
    "addr:full":"Rue De Moriensart 10 Lasne (lasne-chapelle-saint-lambert) Brabant Wallon 1380",
    "addr:housenumber":"10",
    "addr:postcode":"1380",
    "addr:street":"Rue De Moriensart;Wallon",
    "iso:country":"BE",
    "sg:address":"Rue De Moriensart 10",
    "sg:city":"Lasne (lasne-chapelle-saint-lambert)",
    "sg:classifiers":[
        {
            "category":"Brewery",
            "type":"Food & Drink"
        }
    ],
    "sg:phone":"+32 2 633 37 18",
    "sg:postcode":"1380",
    "sg:province":"Brabant Wallon",
    "sg:tags":[
        "-",
        "ingredient"
    ],
    "wof:name":"Hoed J",
    "wof:placetype":"venue"
},
  "geometry": {"coordinates":[4.5052242279,50.6752166748],"type":"Point"}
}