{
  "type": "Feature",
  "properties": {
    "addr:full":"Avenue D'auderghem 225 Bruxelles (etterbeek) Bruxelles-Capitale 1040",
    "addr:housenumber":"225",
    "addr:postcode":"1040",
    "addr:street":"Avenue D'Auderghem",
    "iso:country":"BE",
    "sg:address":"Avenue D'auderghem 225",
    "sg:city":"Bruxelles (etterbeek)",
    "sg:classifiers":[
        {
            "category":"Building & Trades",
            "subcategory":"Electrical",
            "type":"Services"
        }
    ],
    "sg:phone":"+32 2 640 65 02",
    "sg:postcode":"1040",
    "sg:province":"Bruxelles-Capitale",
    "sg:tags":[
        "electric",
        "-",
        "housewiring",
        "contractor"
    ],
    "wof:name":"Marc Electricite",
    "wof:placetype":"venue"
},
  "geometry": {"coordinates":[4.3883771896,50.8335990906],"type":"Point"}
}