{
  "type": "Feature",
  "properties": {
    "addr:full":"Peter Benoitstraat 32 Izegem West-Vlaanderen 8870",
    "addr:housenumber":"32",
    "addr:postcode":"8870",
    "addr:street":"Peter Benoitstraat",
    "iso:country":"BE",
    "sg:address":"Peter Benoitstraat 32",
    "sg:city":"Izegem",
    "sg:classifiers":[
        {
            "category":"Professional",
            "subcategory":"Computer Services",
            "type":"Services"
        }
    ],
    "sg:postcode":"8870",
    "sg:province":"West-Vlaanderen",
    "sg:tags":[
        "repair",
        "processing",
        "-",
        "maintenance",
        "data"
    ],
    "wof:name":"Pehasys",
    "wof:placetype":"venue"
},
  "geometry": {"coordinates":[3.22199893,50.9244155884],"type":"Point"}
}