{
  "type": "Feature",
  "properties": {
    "iso:country":"BE",
    "sg:address":"Technologiepark 3",
    "sg:city":"Gent",
    "sg:orig_category":"Bedrijvencentra and kantoordiensten",
    "sg:phone":"+32 9 241 56 11",
    "sg:postcode":"9052",
    "sg:province":"Oost-Vlaanderen",
    "wof:name":"Innovatiecentrum",
    "wof:placetype":"venue"
},
  "geometry": {"coordinates":[3.7167270184,51.0002937317],"type":"Point"}
}