{
  "type": "Feature",
  "properties": {
    "addr:full":"Im Himmelchen B\u00fctgenbach Li\u00e8ge 4750",
    "addr:postcode":"4750",
    "addr:street":"Im Himmelchen",
    "iso:country":"BE",
    "sg:address":"Im Himmelchen",
    "sg:city":"B\u00fctgenbach",
    "sg:classifiers":[
        {
            "category":"Landmark",
            "subcategory":"Tourist Attraction",
            "type":"Public Place"
        }
    ],
    "sg:phone":"+32 80 44 46 22",
    "sg:postcode":"4750",
    "sg:province":"Li\u00e8ge",
    "sg:tags":[
        "-",
        "tourism",
        "interest",
        "sight"
    ],
    "wof:name":"Ski Club Weywertz",
    "wof:placetype":"venue"
},
  "geometry": {"coordinates":[6.1651320457,50.4479370117],"type":"Point"}
}