{
  "type": "Feature",
  "properties": {
    "addr:full":"Gebroeders De Winterstraat 2 Lille Antwerpen 2275",
    "addr:housenumber":"2",
    "addr:postcode":"2275",
    "addr:street":"Gebroeders De Winterstraat",
    "iso:country":"BE",
    "sg:address":"Gebroeders De Winterstraat 2",
    "sg:city":"Lille",
    "sg:classifiers":[
        {
            "category":"Bars & Pubs",
            "type":"Food & Drink"
        }
    ],
    "sg:phone":"+32 3 312 25 84",
    "sg:postcode":"2275",
    "sg:province":"Antwerpen",
    "wof:name":"De Kroon",
    "wof:placetype":"venue"
},
  "geometry": {"coordinates":[4.7859559059,51.2636260986],"type":"Point"}
}