{
  "type": "Feature",
  "properties": {
    "iso:country":"BE",
    "sg:address":"Rijgerstraat 63",
    "sg:city":"Aalst (moorsel)",
    "sg:classifiers":[
        {
            "category":"Freight",
            "type":"Transportation"
        }
    ],
    "sg:phone":"+32 53 21 30 69",
    "sg:postcode":"9310",
    "sg:province":"Oost-Vlaanderen",
    "sg:tags":[
        "-",
        "transport"
    ],
    "wof:name":"Karel Koerierdienst",
    "wof:placetype":"venue"
},
  "geometry": {"coordinates":[4.0853180885,50.9502487183],"type":"Point"}
}