{
  "type": "Feature",
  "properties": {
    "addr:full":"Rue Grande 57 Anhee Namur 5537",
    "addr:housenumber":"57",
    "addr:postcode":"5537",
    "addr:street":"Rue Grande;Namur",
    "iso:country":"BE",
    "sg:address":"Rue Grande 57",
    "sg:city":"Anhee",
    "sg:orig_category":"Enseignement maternel and primaire",
    "sg:phone":"+32 82 61 14 31",
    "sg:postcode":"5537",
    "sg:province":"Namur",
    "wof:name":"Ecole Fondamentale",
    "wof:placetype":"venue"
},
  "geometry": {"coordinates":[4.8767619133,50.3115196228],"type":"Point"}
}