{
  "type": "Feature",
  "properties": {
    "addr:full":"Rue Du Canard 5 Jurbise Hainaut 7050",
    "addr:housenumber":"5",
    "addr:postcode":"7050",
    "addr:street":"Rue Du Canard",
    "iso:country":"BE",
    "sg:address":"Rue Du Canard 5",
    "sg:city":"Jurbise",
    "sg:orig_category":"Plaatsen van vloer- and muurbekleding Schilders Verlichting and huishoudartikelen",
    "sg:phone":"+32 65 22 79 72",
    "sg:postcode":"7050",
    "sg:province":"Hainaut",
    "wof:name":"Maxi-decor",
    "wof:placetype":"venue"
},
  "geometry": {"coordinates":[3.8777871132,50.5089454651],"type":"Point"}
}