{
  "type": "Feature",
  "properties": {
    "iso:country":"BE",
    "sg:address":"Blindestraat 37",
    "sg:city":"Antwerpen",
    "sg:classifiers":[
        {
            "category":"Cafe",
            "type":"Food & Drink"
        }
    ],
    "sg:phone":"+32 3 233 11 89",
    "sg:postcode":"2000",
    "sg:province":"Antwerpen",
    "sg:tags":[
        "caf\u00e9s"
    ],
    "wof:name":"Jan Adams",
    "wof:placetype":"venue"
},
  "geometry": {"coordinates":[4.4080400467,51.2226219177],"type":"Point"}
}