{
  "type": "Feature",
  "properties": {
    "addr:full":"Drie Eikenstraat 95 Edegem Antwerpen 2650",
    "addr:housenumber":"95",
    "addr:postcode":"2650",
    "addr:street":"Drie Eikenstraat",
    "iso:country":"BE",
    "sg:address":"Drie Eikenstraat 95",
    "sg:city":"Edegem",
    "sg:orig_category":"Plomberie, chauffage and installations sanitaires",
    "sg:phone":"+32 3 457 63 36",
    "sg:postcode":"2650",
    "sg:province":"Antwerpen",
    "wof:name":"Verwarming Keersmaekers",
    "wof:placetype":"venue"
},
  "geometry": {"coordinates":[4.4385452271,51.1562194824],"type":"Point"}
}