{
  "type": "Feature",
  "properties": {
    "addr:full":"Rue De La Station 30-1 Mouscron Hainaut 7700",
    "addr:housenumber":"30-1",
    "addr:postcode":"7700",
    "addr:street":"Rue De La Station",
    "iso:country":"BE",
    "sg:address":"Rue De La Station 30-1",
    "sg:city":"Mouscron",
    "sg:classifiers":[
        {
            "category":"Health Services",
            "subcategory":"Dentist",
            "type":"Services"
        }
    ],
    "sg:phone":"+32 56 84 57 37",
    "sg:postcode":"7700",
    "sg:province":"Hainaut",
    "wof:name":"Di Tullio Bruno",
    "wof:placetype":"venue"
},
  "geometry": {"coordinates":[3.2191510201,50.7434844971],"type":"Point"}
}