{
  "type": "Feature",
  "properties": {
    "iso:country":"BE",
    "sg:address":"Roumont 6",
    "sg:city":"Libin",
    "sg:orig_category":"Jardinage",
    "sg:phone":"+32 61 22 43 17",
    "sg:postcode":"6890",
    "sg:province":"Luxembourg",
    "wof:name":"Henri Geraerts",
    "wof:placetype":"venue"
},
  "geometry": {"coordinates":[5.2491359711,49.9588813782],"type":"Point"}
}