{
  "type": "Feature",
  "properties": {
    "iso:country":"BE",
    "sg:address":"Broekmanstraat 128",
    "sg:city":"Heist-op-den-berg",
    "sg:classifiers":[
        {
            "category":"Building & Trades",
            "subcategory":"Plumbing",
            "type":"Services"
        }
    ],
    "sg:phone":"+32 15 22 40 51",
    "sg:postcode":"2220",
    "sg:province":"Antwerpen",
    "sg:tags":[
        "diver",
        "commerce",
        "gr",
        "pour",
        "equipement"
    ],
    "wof:name":"Van Woensel Paul & Co",
    "wof:placetype":"venue"
},
  "geometry": {"coordinates":[4.7460021973,51.0378952026],"type":"Point"}
}