{
  "type": "Feature",
  "properties": {
    "addr:full":"Bellestraat 13 Lebbeke Oost-Vlaanderen 9280",
    "addr:housenumber":"13",
    "addr:postcode":"9280",
    "addr:street":"Bellestraat",
    "iso:country":"BE",
    "sg:address":"Bellestraat 13",
    "sg:city":"Lebbeke",
    "sg:orig_category":"Eleveurs de bovins",
    "sg:phone":"+32 52 41 10 35",
    "sg:postcode":"9280",
    "sg:province":"Oost-Vlaanderen",
    "wof:name":"Marc Vinck",
    "wof:placetype":"venue"
},
  "geometry": {"coordinates":[4.1209659576,50.9988327026],"type":"Point"}
}