{
  "type": "Feature",
  "properties": {
    "iso:country":"BE",
    "sg:address":"Chause\u00c9 De Stockel 290",
    "sg:city":"Brussel/bruxelles",
    "sg:orig_category":"Fleurs and plantes",
    "sg:phone":"+32 2 770 25 56",
    "sg:postcode":"1200",
    "sg:province":"Bruxelles-Capitale",
    "wof:name":"Art Florist",
    "wof:placetype":"venue"
},
  "geometry": {"coordinates":[4.4503002167,50.8415908813],"type":"Point"}
}