{
  "type": "Feature",
  "properties": {
    "addr:full":"Charleslei 5 Brasschaat Antwerpen 2930",
    "addr:housenumber":"5",
    "addr:postcode":"2930",
    "addr:street":"Charleslei",
    "iso:country":"BE",
    "sg:address":"Charleslei 5",
    "sg:city":"Brasschaat",
    "sg:classifiers":[
        {
            "category":"Health Services",
            "subcategory":"Doctor",
            "type":"Services"
        }
    ],
    "sg:phone":"+32 3 651 34 15",
    "sg:postcode":"2930",
    "sg:province":"Antwerpen",
    "sg:tags":[
        "medicinephysicians",
        "surgeon"
    ],
    "wof:name":"Martens J",
    "wof:placetype":"venue"
},
  "geometry": {"coordinates":[4.4768052101,51.2909317017],"type":"Point"}
}