{
  "type": "Feature",
  "properties": {
    "addr:full":"Pieter Breugellaan 44 Peer Limburg 3990",
    "addr:housenumber":"44",
    "addr:postcode":"3990",
    "addr:street":"Pieter Breugellaan",
    "iso:country":"BE",
    "sg:address":"Pieter Breugellaan 44",
    "sg:city":"Peer",
    "sg:orig_category":"Journaux",
    "sg:phone":"+32 11 73 67 31",
    "sg:postcode":"3990",
    "sg:province":"Limburg",
    "wof:name":"Leppens Magdalena",
    "wof:placetype":"venue"
},
  "geometry": {"coordinates":[5.4533009529,51.1329536438],"type":"Point"}
}