{
  "type": "Feature",
  "properties": {
    "addr:full":"Rue Renory 50 Angleur Li\u00e8ge 4900",
    "addr:housenumber":"50",
    "addr:postcode":"4900",
    "addr:street":"Rue Renory",
    "iso:country":"BE",
    "sg:address":"Rue Renory 50",
    "sg:city":"Angleur",
    "sg:classifiers":[
        {
            "category":"Banks & Credit Unions",
            "subcategory":"Bank",
            "type":"Services"
        }
    ],
    "sg:phone":"+32 41433924",
    "sg:postcode":"4900",
    "sg:province":"Li\u00e8ge",
    "wof:name":"Aslk-cger Bank",
    "wof:placetype":"venue"
},
  "geometry": {"coordinates":[5.5790781975,50.6138496399],"type":"Point"}
}