{
  "type": "Feature",
  "properties": {
    "addr:full":"All\u00c9e Des Tilleuls 27 Ch\u00c2telet Hainaut 6200",
    "addr:housenumber":"27",
    "addr:postcode":"6200",
    "addr:street":"Alle\u0301E Des Tilleuls",
    "iso:country":"BE",
    "sg:address":"All\u00c9e Des Tilleuls 27",
    "sg:city":"Ch\u00c2telet",
    "sg:classifiers":[
        {
            "category":"Arena",
            "subcategory":"Sports Club",
            "type":"Entertainment"
        }
    ],
    "sg:phone":"+32 475 38 04 17",
    "sg:postcode":"6200",
    "sg:province":"Hainaut",
    "sg:tags":[
        "de"
    ],
    "wof:name":"Tc Palais Exp. Charleroi",
    "wof:placetype":"venue"
},
  "geometry": {"coordinates":[4.516977787,50.4253463745],"type":"Point"}
}