{
  "type": "Feature",
  "properties": {
    "iso:country":"BE",
    "sg:address":"Boudewijnlaan 137 Box 11",
    "sg:city":"Aalst",
    "sg:classifiers":[
        {
            "category":"Professional",
            "subcategory":"Art Services",
            "type":"Services"
        }
    ],
    "sg:phone":"+32 53 78 02 92",
    "sg:postcode":"9300",
    "sg:province":"Oost-Vlaanderen",
    "sg:tags":[
        "designer",
        "display"
    ],
    "wof:name":"Etabe Bvba",
    "wof:placetype":"venue"
},
  "geometry": {"coordinates":[4.0225191116,50.9455604553],"type":"Point"}
}