{
  "type": "Feature",
  "properties": {
    "addr:full":"Kerkstraat 18b1 Londerzeel Vlaams-Brabant 1840",
    "addr:housenumber":"18b1",
    "addr:postcode":"1840",
    "addr:street":"Kerkstraat",
    "iso:country":"BE",
    "sg:address":"Kerkstraat 18b1",
    "sg:city":"Londerzeel",
    "sg:orig_category":"Parfumeries",
    "sg:phone":"+32 52 31 19 17",
    "sg:postcode":"1840",
    "sg:province":"Vlaams-Brabant",
    "wof:name":"Kruidvat",
    "wof:placetype":"venue"
},
  "geometry": {"coordinates":[4.3020820618,51.0026245117],"type":"Point"}
}