{
  "type": "Feature",
  "properties": {
    "addr:full":"Boulevard G\u00c9n\u00c9ral Wahis 20 Schaarbeek/schaerbeek Bruxelles-Capitale 1030",
    "addr:housenumber":"20",
    "addr:postcode":"1030",
    "addr:street":"Boulevard Ge\u0301Ne\u0301Ral Wahis",
    "iso:country":"BE",
    "sg:address":"Boulevard G\u00c9n\u00c9ral Wahis 20",
    "sg:city":"Schaarbeek/schaerbeek",
    "sg:orig_category":"Cabinets d\u00b4huissiers",
    "sg:phone":"+32 2 706 04 80",
    "sg:postcode":"1030",
    "sg:province":"Bruxelles-Capitale",
    "wof:name":"Pierre Crabbe",
    "wof:placetype":"venue"
},
  "geometry": {"coordinates":[4.3954620361,50.8595237732],"type":"Point"}
}