{
  "type": "Feature",
  "properties": {
    "addr:full":"Wilgenstraat 8 Ingelmunster West-Vlaanderen 8770",
    "addr:housenumber":"8",
    "addr:postcode":"8770",
    "addr:street":"Wilgenstraat",
    "iso:country":"BE",
    "sg:address":"Wilgenstraat 8",
    "sg:city":"Ingelmunster",
    "sg:orig_category":"Bijouteries and horlogeries",
    "sg:phone":"+32 51 31 14 26",
    "sg:postcode":"8770",
    "sg:province":"West-Vlaanderen",
    "wof:name":"Nathalie Schaessens",
    "wof:placetype":"venue"
},
  "geometry": {"coordinates":[3.2423079014,50.9266815186],"type":"Point"}
}