{
  "type": "Feature",
  "properties": {
    "iso:country":"BE",
    "sg:address":"Hermans-lybaertstraat 1",
    "sg:city":"Knokke-heist (heist-aan-zee)",
    "sg:classifiers":[
        {
            "category":"Health Services",
            "subcategory":"Dentist",
            "type":"Services"
        }
    ],
    "sg:phone":"+32 50 51 32 98",
    "sg:postcode":"8301",
    "sg:province":"West-Vlaanderen",
    "wof:name":"Pieters Roch",
    "wof:placetype":"venue"
},
  "geometry": {"coordinates":[3.2639000416,51.3396911621],"type":"Point"}
}