{
  "type": "Feature",
  "properties": {
    "addr:full":"Place Fernand Cocq 4 Bruxelles (ixelles) Bruxelles-Capitale 1050",
    "addr:housenumber":"4",
    "addr:postcode":"1050",
    "addr:street":"Place Fernand Cocq",
    "iso:country":"BE",
    "sg:address":"Place Fernand Cocq 4",
    "sg:city":"Bruxelles (ixelles)",
    "sg:classifiers":[
        {
            "category":"Shopping",
            "subcategory":"Florist",
            "type":"Retail Goods"
        }
    ],
    "sg:phone":"+32 2 513 67 56",
    "sg:postcode":"1050",
    "sg:province":"Bruxelles-Capitale",
    "wof:name":"Katsura",
    "wof:placetype":"venue"
},
  "geometry": {"coordinates":[4.3661198616,50.8333091736],"type":"Point"}
}