{
  "type": "Feature",
  "properties": {
    "iso:country":"BE",
    "sg:address":"Geelseweg 8",
    "sg:city":"Olen",
    "sg:orig_category":"Eleveurs de bovins",
    "sg:phone":"+32 14 21 30 54",
    "sg:postcode":"2250",
    "sg:province":"Antwerpen",
    "wof:name":"Gebroeders Helsen",
    "wof:placetype":"venue"
},
  "geometry": {"coordinates":[4.8688750267,51.1640815735],"type":"Point"}
}