{
  "type": "Feature",
  "properties": {
    "iso:country":"BE",
    "sg:address":"Begijnenstraat 1",
    "sg:city":"Diest",
    "sg:classifiers":[
        {
            "category":"Professional",
            "subcategory":"Art Services",
            "type":"Services"
        }
    ],
    "sg:phone":"+32 13 31 15 29",
    "sg:postcode":"3290",
    "sg:province":"Vlaams-Brabant",
    "sg:tags":[
        "picture",
        "framer"
    ],
    "wof:name":"Galery Esschius",
    "wof:placetype":"venue"
},
  "geometry": {"coordinates":[5.0569849014,50.9873847961],"type":"Point"}
}