{
  "type": "Feature",
  "properties": {
    "addr:full":"Rue De La Fontaine 9 Somme-leuze (sinsin) Namur 5377",
    "addr:housenumber":"9",
    "addr:postcode":"5377",
    "addr:street":"Rue De La Fontaine;Sinsin",
    "iso:country":"BE",
    "sg:address":"Rue De La Fontaine 9",
    "sg:city":"Somme-leuze (sinsin)",
    "sg:classifiers":[
        {
            "category":"Insurance",
            "subcategory":"Insurance Agent",
            "type":"Services"
        }
    ],
    "sg:phone":"+32 83 68 88 36",
    "sg:postcode":"5377",
    "sg:province":"Namur",
    "sg:tags":[
        "broker"
    ],
    "wof:name":"Meunier C",
    "wof:placetype":"venue"
},
  "geometry": {"coordinates":[5.2630710602,50.2757263184],"type":"Point"}
}