{
  "type": "Feature",
  "properties": {
    "addr:full":"Grote Markt 74 Zelzate Oost-Vlaanderen 9060",
    "addr:housenumber":"74",
    "addr:postcode":"9060",
    "addr:street":"Grote Markt",
    "iso:country":"BE",
    "sg:address":"Grote Markt 74",
    "sg:city":"Zelzate",
    "sg:classifiers":[
        {
            "category":"Building & Trades",
            "subcategory":"Construction",
            "type":"Services"
        }
    ],
    "sg:phone":"+32 9 344 00 05",
    "sg:postcode":"9060",
    "sg:province":"Oost-Vlaanderen",
    "sg:tags":[
        "carpenter"
    ],
    "wof:name":"Van Acker A",
    "wof:placetype":"venue"
},
  "geometry": {"coordinates":[3.8108210564,51.1999740601],"type":"Point"}
}