{
  "type": "Feature",
  "properties": {
    "iso:country":"BE",
    "sg:address":"Chemin De Fontaine L'ev\u00eaque 15",
    "sg:city":"Nivelles",
    "sg:classifiers":[
        {
            "category":"Insurance",
            "subcategory":"Insurance Agent",
            "type":"Services"
        }
    ],
    "sg:phone":"+32 67 89 35 70",
    "sg:postcode":"1400",
    "sg:province":"Brabant Wallon",
    "sg:tags":[
        "broker"
    ],
    "wof:name":"De Longueville A",
    "wof:placetype":"venue"
},
  "geometry": {"coordinates":[4.3162198067,50.5856628418],"type":"Point"}
}