{
  "type": "Feature",
  "properties": {
    "iso:country":"BE",
    "sg:address":"Rue De Flemalle-grande 320",
    "sg:city":"Flemalle",
    "sg:orig_category":"Bagage and lederwaren Fab SMEEDWERK, METAALBEWERKING AND POEDERMETALLURGIE",
    "sg:phone":"+32 4 235 65 19",
    "sg:postcode":"4400",
    "sg:province":"Li\u00e8ge",
    "wof:name":"Thierry Zihla",
    "wof:placetype":"venue"
},
  "geometry": {"coordinates":[5.4772639275,50.6149291992],"type":"Point"}
}