{
  "type": "Feature",
  "properties": {
    "iso:country":"BE",
    "sg:address":"Berkenlaan 11",
    "sg:city":"Halle (buizingen)",
    "sg:classifiers":[
        {
            "category":"Building & Trades",
            "subcategory":"Landscaping Services",
            "type":"Services"
        }
    ],
    "sg:phone":"+32 2 381 38 39",
    "sg:postcode":"1501",
    "sg:province":"Vlaams-Brabant",
    "sg:tags":[
        "access",
        "pond",
        "laying-out",
        "-"
    ],
    "wof:name":"Debrie J",
    "wof:placetype":"venue"
},
  "geometry": {"coordinates":[4.2711281776,50.7254295349],"type":"Point"}
}