{
  "type": "Feature",
  "properties": {
    "iso:country":"BE",
    "sg:address":"Rue Tienne Saint-gilles 92",
    "sg:city":"Charleroi",
    "sg:orig_category":"Boissons",
    "sg:phone":"+32 71 43 58 48",
    "sg:postcode":"6010",
    "sg:province":"Hainaut",
    "wof:name":"Drink St.gilles",
    "wof:placetype":"venue"
},
  "geometry": {"coordinates":[4.4548177719,50.3893470764],"type":"Point"}
}