{
  "type": "Feature",
  "properties": {
    "addr:full":"Korkentapstraat 29 Koekelare West-Vlaanderen 8680",
    "addr:housenumber":"29",
    "addr:postcode":"8680",
    "addr:street":"Korkentapstraat",
    "iso:country":"BE",
    "sg:address":"Korkentapstraat 29",
    "sg:city":"Koekelare",
    "sg:orig_category":"Rundveehouders Varkenskwekers",
    "sg:phone":"+32 51 58 04 71",
    "sg:postcode":"8680",
    "sg:province":"West-Vlaanderen",
    "wof:name":"Jozef Pollentier",
    "wof:placetype":"venue"
},
  "geometry": {"coordinates":[2.9781599045,51.0901832581],"type":"Point"}
}