{
  "type": "Feature",
  "properties": {
    "addr:full":"Snepdijk 22 Gent Oost-Vlaanderen 9000",
    "addr:housenumber":"22",
    "addr:postcode":"9000",
    "addr:street":"Snepdijk;Oost-Vlaanderen",
    "iso:country":"BE",
    "sg:address":"Snepdijk 22",
    "sg:city":"Gent",
    "sg:classifiers":[
        {
            "category":"Arena",
            "subcategory":"Sports Club",
            "type":"Entertainment"
        }
    ],
    "sg:phone":"+32 9 220 44 24",
    "sg:postcode":"9000",
    "sg:province":"Oost-Vlaanderen",
    "wof:name":"V.v.w. Gent-leie",
    "wof:placetype":"venue"
},
  "geometry": {"coordinates":[3.6917800903,51.039188385],"type":"Point"}
}