{
  "type": "Feature",
  "properties": {
    "addr:full":"Chauss\u00e9e De Mons 8a Anderlues Hainaut 6150",
    "addr:housenumber":"8a",
    "addr:postcode":"6150",
    "addr:street":"Chausse\u0301E De Mons",
    "iso:country":"BE",
    "sg:address":"Chauss\u00e9e De Mons 8a",
    "sg:city":"Anderlues",
    "sg:classifiers":[
        {
            "category":"Retail",
            "subcategory":"Storage",
            "type":"Services"
        }
    ],
    "sg:phone":"+32 71 52 58 70",
    "sg:postcode":"6150",
    "sg:province":"Hainaut",
    "sg:tags":[
        "rack",
        "system"
    ],
    "wof:name":"Top Montage Sprl",
    "wof:placetype":"venue"
},
  "geometry": {"coordinates":[4.2286968231,50.4077949524],"type":"Point"}
}