{
  "type": "Feature",
  "properties": {
    "iso:country":"BE",
    "sg:address":"Madestraat 1",
    "sg:city":"Herselt",
    "sg:orig_category":"Boomkwekerijen",
    "sg:phone":"+32 16 56 98 04",
    "sg:postcode":"2230",
    "sg:province":"Antwerpen",
    "wof:name":"H. Van Dijck",
    "wof:placetype":"venue"
},
  "geometry": {"coordinates":[4.823846817,51.0189208984],"type":"Point"}
}