{
  "type": "Feature",
  "properties": {
    "addr:full":"Koninklijkebaan 19b3 De Haan West-Vlaanderen 8420",
    "addr:housenumber":"19b3",
    "addr:postcode":"8420",
    "addr:street":"Koninklijkebaan",
    "iso:country":"BE",
    "sg:address":"Koninklijkebaan 19b3",
    "sg:city":"De Haan",
    "sg:orig_category":"Epiceries",
    "sg:phone":"+32 59 23 37 90",
    "sg:postcode":"8420",
    "sg:province":"West-Vlaanderen",
    "wof:name":"Superette Luc",
    "wof:placetype":"venue"
},
  "geometry": {"coordinates":[3.0738298893,51.2974700928],"type":"Point"}
}