{
  "type": "Feature",
  "properties": {
    "iso:country":"BE",
    "sg:address":"Kontichsesteenweg 52",
    "sg:city":"Aartselaar",
    "sg:orig_category":"Non-Classified Establishments",
    "sg:phone":"+32 3 451 24 24",
    "sg:postcode":"2630",
    "sg:province":"Antwerpen",
    "wof:name":"Orcon Nv-sa",
    "wof:placetype":"venue"
},
  "geometry": {"coordinates":[4.390414238,51.1442298889],"type":"Point"}
}