{
  "type": "Feature",
  "properties": {
    "addr:full":"Houwaartstraat 153 Scherpenheuvel-zichem Vlaams-Brabant 3270",
    "addr:housenumber":"153",
    "addr:postcode":"3270",
    "addr:street":"Houwaartstraat",
    "iso:country":"BE",
    "sg:address":"Houwaartstraat 153",
    "sg:city":"Scherpenheuvel-zichem",
    "sg:orig_category":"V\u00e9hicules automobiles",
    "sg:phone":"+32 13 77 82 17",
    "sg:postcode":"3270",
    "sg:province":"Vlaams-Brabant",
    "wof:name":"Garage Bottelbergs",
    "wof:placetype":"venue"
},
  "geometry": {"coordinates":[4.9579057693,50.9660568237],"type":"Point"}
}