{
  "type": "Feature",
  "properties": {
    "iso:country":"BE",
    "sg:address":"Oostrozebekestraat 82",
    "sg:city":"Meulebeke",
    "sg:orig_category":"Electrom\u00e9nager, t\u00e9l\u00e9visions and radios. Installation \u00e9lectrique r\u00e9sidentielle",
    "sg:phone":"+32 51 48 89 88",
    "sg:postcode":"8760",
    "sg:province":"West-Vlaanderen",
    "wof:name":"Rudiger Verhelst",
    "wof:placetype":"venue"
},
  "geometry": {"coordinates":[3.2913138866,50.9468765259],"type":"Point"}
}