{
  "type": "Feature",
  "properties": {
    "addr:full":"Rue Isidore Hoton 11 Ath Hainaut 7800",
    "addr:housenumber":"11",
    "addr:postcode":"7800",
    "addr:street":"Rue Isidore Hoton",
    "iso:country":"BE",
    "sg:address":"Rue Isidore Hoton 11",
    "sg:city":"Ath",
    "sg:classifiers":[
        {
            "category":"Health Services",
            "subcategory":"Health Practitioner",
            "type":"Services"
        }
    ],
    "sg:phone":"+32 68 28 72 56",
    "sg:postcode":"7800",
    "sg:province":"Hainaut",
    "sg:tags":[
        "physiotherapist"
    ],
    "wof:name":"Dierick Sabrina",
    "wof:placetype":"venue"
},
  "geometry": {"coordinates":[3.7810959816,50.6327095032],"type":"Point"}
}