{
  "type": "Feature",
  "properties": {
    "iso:country":"BE",
    "sg:address":"Rue De Gueldre 15",
    "sg:city":"Liege",
    "sg:orig_category":"Epiceries",
    "sg:phone":"+32 4 221 36 35",
    "sg:postcode":"4000",
    "sg:province":"Li\u00e8ge",
    "wof:name":"Kausar Night Shop",
    "wof:placetype":"venue"
},
  "geometry": {"coordinates":[5.5763611794,50.6437911987],"type":"Point"}
}