{
  "type": "Feature",
  "properties": {
    "addr:full":"Eduard Robeynslaan 102 Diest Vlaams-Brabant 3290",
    "addr:housenumber":"102",
    "addr:postcode":"3290",
    "addr:street":"Robeynslaan",
    "iso:country":"BE",
    "sg:address":"Eduard Robeynslaan 102",
    "sg:city":"Diest",
    "sg:orig_category":"D\u00e9taillants en pi\u00e8ces and accessoires de voitures",
    "sg:phone":"+32 13 31 17 57",
    "sg:postcode":"3290",
    "sg:province":"Vlaams-Brabant",
    "wof:name":"Accu Service",
    "wof:placetype":"venue"
},
  "geometry": {"coordinates":[5.0615367889,50.976360321],"type":"Point"}
}