{
  "type": "Feature",
  "properties": {
    "addr:full":"Dorpsstraat 57 Box C Dilsen-stokkem (lanklaar) Limburg 3650",
    "addr:housenumber":"57 box c",
    "addr:postcode":"3650",
    "addr:street":"Dorpsstraat;Dilsen-Stokkem Lanklaar Limburg",
    "iso:country":"BE",
    "sg:address":"Dorpsstraat 57 Box C",
    "sg:city":"Dilsen-stokkem (lanklaar)",
    "sg:classifiers":[
        {
            "category":"Utilities",
            "subcategory":"Natural Gas",
            "type":"Services"
        }
    ],
    "sg:postcode":"3650",
    "sg:province":"Limburg",
    "sg:tags":[
        "control",
        "tank"
    ],
    "wof:name":"Thone Jos",
    "wof:placetype":"venue"
},
  "geometry": {"coordinates":[5.727396965,51.0364189148],"type":"Point"}
}