{
  "type": "Feature",
  "properties": {
    "iso:country":"BE",
    "sg:address":"Rue Grande 36",
    "sg:city":"Tellin",
    "sg:orig_category":"Rusthuizen and serviceflats",
    "sg:phone":"+32 84 36 67 44",
    "sg:postcode":"6927",
    "sg:province":"Luxembourg",
    "wof:name":"Les Alouins",
    "wof:placetype":"venue"
},
  "geometry": {"coordinates":[5.2209420204,50.0817871094],"type":"Point"}
}