{
  "type": "Feature",
  "properties": {
    "iso:country":"BE",
    "sg:address":"Rue De La Bach\u00c9e 2",
    "sg:city":"Lasne",
    "sg:orig_category":"Boekbinderijen and afwerking",
    "sg:phone":"+32 2 633 13 03",
    "sg:postcode":"1380",
    "sg:province":"Brabant Wallon",
    "wof:name":"Fe. Guequier",
    "wof:placetype":"venue"
},
  "geometry": {"coordinates":[4.4299521446,50.659614563],"type":"Point"}
}