{
  "type": "Feature",
  "properties": {
    "addr:full":"Burgemeester Bertenplein 15 Poperinge West-Vlaanderen 8970",
    "addr:housenumber":"15",
    "addr:postcode":"8970",
    "addr:street":"Burgemeester Bertenplein",
    "iso:country":"BE",
    "sg:address":"Burgemeester Bertenplein 15",
    "sg:city":"Poperinge",
    "sg:orig_category":"Brood, gebak and snoepgoed",
    "sg:phone":"+32 57 33 32 41",
    "sg:postcode":"8970",
    "sg:province":"West-Vlaanderen",
    "wof:name":"Patrick Truant",
    "wof:placetype":"venue"
},
  "geometry": {"coordinates":[2.7251369953,50.854221344],"type":"Point"}
}