{
  "type": "Feature",
  "properties": {
    "iso:country":"BE",
    "sg:address":"Rue Renier De Brialmont 7",
    "sg:city":"Malmedy",
    "sg:orig_category":"Boekhouders",
    "sg:phone":"+32 80 86 43 50",
    "sg:postcode":"4960",
    "sg:province":"Li\u00e8ge",
    "wof:name":"Jean-claude Mathonet",
    "wof:placetype":"venue"
},
  "geometry": {"coordinates":[6.0690751076,50.4571723938],"type":"Point"}
}