{
  "type": "Feature",
  "properties": {
    "addr:full":"Avenue Louise 65-2 Bruxelles (ixelles) Bruxelles-Capitale 1050",
    "addr:housenumber":"65-2",
    "addr:postcode":"1050",
    "addr:street":"Avenue Louise",
    "iso:country":"BE",
    "sg:address":"Avenue Louise 65-2",
    "sg:city":"Bruxelles (ixelles)",
    "sg:classifiers":[
        {
            "category":"Professional",
            "subcategory":"Lawyer & Legal Services",
            "type":"Services"
        }
    ],
    "sg:phone":"+32 2 533 59 11",
    "sg:postcode":"1050",
    "sg:province":"Bruxelles-Capitale",
    "wof:name":"Clifford Chance Punder",
    "wof:placetype":"venue"
},
  "geometry": {"coordinates":[4.3577671051,50.8326416016],"type":"Point"}
}