{
  "type": "Feature",
  "properties": {
    "addr:full":"Rue Des Alli\u00c9s 98 Charleroi Hainaut 6044",
    "addr:housenumber":"98",
    "addr:postcode":"6044",
    "addr:street":"Rue Des Allie\u0301S;Hainaut",
    "iso:country":"BE",
    "sg:address":"Rue Des Alli\u00c9s 98",
    "sg:city":"Charleroi",
    "sg:orig_category":"Krantenwinkels Rookartikelen",
    "sg:phone":"+32 71 45 26 54",
    "sg:postcode":"6044",
    "sg:province":"Hainaut",
    "wof:name":"Librairie De Plomcot",
    "wof:placetype":"venue"
},
  "geometry": {"coordinates":[4.3870639801,50.4393119812],"type":"Point"}
}