{
  "type": "Feature",
  "properties": {
    "addr:full":"Rue Denis Deceuster 38 Rixensart Brabant Wallon 1330",
    "addr:housenumber":"38",
    "addr:postcode":"1330",
    "addr:street":"Rue Denis Deceuster;Wallon",
    "iso:country":"BE",
    "sg:address":"Rue Denis Deceuster 38",
    "sg:city":"Rixensart",
    "sg:orig_category":"Immobili\u00ebnkantoren",
    "sg:phone":"+32 2 653 09 90",
    "sg:postcode":"1330",
    "sg:province":"Brabant Wallon",
    "wof:name":"Immobili\u00c8re Martine Decoo",
    "wof:placetype":"venue"
},
  "geometry": {"coordinates":[4.5163087845,50.7154998779],"type":"Point"}
}