{
  "type": "Feature",
  "properties": {
    "addr:full":"Rue Francois Lef\u00e8bvre 119 Li\u00e8ge 1 (rocourt) Li\u00e8ge 4000",
    "addr:housenumber":"119;1",
    "addr:postcode":"4000",
    "addr:street":"Rue Francois Lefe\u0300Bvre",
    "iso:country":"BE",
    "sg:address":"Rue Francois Lef\u00e8bvre 119",
    "sg:city":"Li\u00e8ge 1 (rocourt)",
    "sg:classifiers":[
        {
            "category":"Professional",
            "subcategory":"Detective & Security Services",
            "type":"Services"
        }
    ],
    "sg:phone":"+32 4 263 06 38",
    "sg:postcode":"4000",
    "sg:province":"Li\u00e8ge",
    "sg:tags":[
        "door",
        "videophones",
        "operating",
        "equipment"
    ],
    "wof:name":"Micromeca",
    "wof:placetype":"venue"
},
  "geometry": {"coordinates":[5.5482430458,50.681476593],"type":"Point"}
}