{
  "type": "Feature",
  "properties": {
    "iso:country":"BE",
    "sg:address":"Rue Des Malheurs 1",
    "sg:city":"H\u00e9ron",
    "sg:classifiers":[
        {
            "category":"Real Estate",
            "subcategory":"Surveying",
            "type":"Services"
        }
    ],
    "sg:phone":"+32 85 71 25 43",
    "sg:postcode":"4217",
    "sg:province":"Li\u00e8ge",
    "sg:tags":[
        "surveyor",
        "land"
    ],
    "wof:name":"Rigot J-l",
    "wof:placetype":"venue"
},
  "geometry": {"coordinates":[5.0968909264,50.5428504944],"type":"Point"}
}