{
  "type": "Feature",
  "properties": {
    "iso:country":"BE",
    "sg:address":"Leegstraat 195",
    "sg:city":"Oostrozebeke",
    "sg:orig_category":"Eleveurs de bovins",
    "sg:phone":"+32 56 66 62 52",
    "sg:postcode":"8780",
    "sg:province":"West-Vlaanderen",
    "wof:name":"Eric Lannoo",
    "wof:placetype":"venue"
},
  "geometry": {"coordinates":[3.3104860783,50.9168395996],"type":"Point"}
}