{
  "type": "Feature",
  "properties": {
    "iso:country":"BE",
    "sg:address":"Boulevard Joseph Tirou 17b48",
    "sg:city":"Charleroi (grand)",
    "sg:classifiers":[
        {
            "category":"Insurance",
            "subcategory":"Life Insurance",
            "type":"Services"
        }
    ],
    "sg:phone":"+32 71 31 64 61",
    "sg:postcode":"6000",
    "sg:province":"Hainaut",
    "sg:tags":[
        "assurance"
    ],
    "wof:name":"Belcogest",
    "wof:placetype":"venue"
},
  "geometry": {"coordinates":[4.4380922318,50.4086761475],"type":"Point"}
}