{
  "type": "Feature",
  "properties": {
    "iso:country":"BE",
    "sg:address":"Attenhovendreef 19",
    "sg:city":"Holsbeek",
    "sg:classifiers":[
        {
            "category":"Professional",
            "subcategory":"Management & Consulting",
            "type":"Services"
        }
    ],
    "sg:phone":"+32 16 44 91 33",
    "sg:postcode":"3220",
    "sg:province":"Vlaams-Brabant",
    "sg:tags":[
        "consultant"
    ],
    "wof:name":"M.a.m. & Co Bvba",
    "wof:placetype":"venue"
},
  "geometry": {"coordinates":[4.739590168,50.9130592346],"type":"Point"}
}