{
  "type": "Feature",
  "properties": {
    "addr:full":"Gouden Kruispunt 74 Tielt-winge Vlaams-Brabant 3390",
    "addr:housenumber":"74",
    "addr:postcode":"3390",
    "iso:country":"BE",
    "sg:address":"Gouden Kruispunt 74",
    "sg:city":"Tielt-winge",
    "sg:orig_category":"Jeux and jouets. Souvenirs and objets artisanaux. Eclairage et \u00e9quipements du foyer. Electrom\u00e9nager,",
    "sg:phone":"+32 16 64 05 41",
    "sg:postcode":"3390",
    "sg:province":"Vlaams-Brabant",
    "wof:name":"Blokker",
    "wof:placetype":"venue"
},
  "geometry": {"coordinates":[4.8709931374,50.9050102234],"type":"Point"}
}