{
  "type": "Feature",
  "properties": {
    "iso:country":"BE",
    "sg:address":"Rue Chap. Des Fran\u00c7ais 17",
    "sg:city":"Honnelles",
    "sg:orig_category":"Rundveehouders",
    "sg:phone":"+32 65 75 91 22",
    "sg:postcode":"7387",
    "sg:province":"Hainaut",
    "wof:name":"Albert Dutrecq",
    "wof:placetype":"venue"
},
  "geometry": {"coordinates":[3.714812994,50.3269996643],"type":"Point"}
}