{
  "type": "Feature",
  "properties": {
    "addr:full":"Avenue Bouvier Virton (grand) Luxembourg 6760",
    "addr:postcode":"6760",
    "addr:street":"Avenue Bouvier Virton",
    "iso:country":"BE",
    "sg:address":"Avenue Bouvier",
    "sg:city":"Virton (grand)",
    "sg:orig_category":"Kapsalons",
    "sg:phone":"+32 63 57 05 09",
    "sg:postcode":"6760",
    "sg:province":"Luxembourg",
    "wof:name":"Clin D'oeil Coiffure",
    "wof:placetype":"venue"
},
  "geometry": {"coordinates":[5.5303201675,49.566986084],"type":"Point"}
}