{
  "type": "Feature",
  "properties": {
    "addr:full":"Tenbosch 9 Brussel/bruxelles Bruxelles-Capitale 1000",
    "addr:housenumber":"9",
    "addr:postcode":"1000",
    "addr:street":"Tenbosch;/",
    "iso:country":"BE",
    "sg:address":"Tenbosch 9",
    "sg:city":"Brussel/bruxelles",
    "sg:orig_category":"S\u00e9lection de personnel and placement",
    "sg:phone":"+32 2 639 68 39",
    "sg:postcode":"1000",
    "sg:province":"Bruxelles-Capitale",
    "wof:name":"Alexander Hughes",
    "wof:placetype":"venue"
},
  "geometry": {"coordinates":[4.3662772179,50.8240470886],"type":"Point"}
}