{
  "type": "Feature",
  "properties": {
    "addr:full":"Oudestraat 19 Kampenhout Vlaams-Brabant 1910",
    "addr:housenumber":"19",
    "addr:postcode":"1910",
    "addr:street":"Oudestraat",
    "iso:country":"BE",
    "sg:address":"Oudestraat 19",
    "sg:city":"Kampenhout",
    "sg:classifiers":[
        {
            "category":"Professional",
            "subcategory":"Advertising",
            "type":"Services"
        }
    ],
    "sg:phone":"+32 16 60 00 85",
    "sg:postcode":"1910",
    "sg:province":"Vlaams-Brabant",
    "sg:tags":[
        "matter",
        "printed",
        "matters"
    ],
    "wof:name":"Drukkerij Artoos Nv",
    "wof:placetype":"venue"
},
  "geometry": {"coordinates":[4.6008400917,50.9607696533],"type":"Point"}
}