{
  "type": "Feature",
  "properties": {
    "addr:full":"Opitterkiezel 221 Bree (opitter) Limburg 3960",
    "addr:housenumber":"221",
    "addr:postcode":"3960",
    "addr:street":"Opitterkiezel",
    "iso:country":"BE",
    "sg:address":"Opitterkiezel 221",
    "sg:city":"Bree (opitter)",
    "sg:classifiers":[
        {
            "category":"Health Services",
            "subcategory":"Dentist",
            "type":"Services"
        }
    ],
    "sg:phone":"+32 89 86 60 44",
    "sg:postcode":"3960",
    "sg:province":"Limburg",
    "wof:name":"Kerkhofs T",
    "wof:placetype":"venue"
},
  "geometry": {"coordinates":[5.6181402206,51.1316413879],"type":"Point"}
}