{
  "type": "Feature",
  "properties": {
    "iso:country":"BE",
    "sg:address":"Rue Des Ruelles 8",
    "sg:city":"Beyne-heusay",
    "sg:orig_category":"Dakwerken Loodgieterij, verwarming and sanitaire installaties",
    "sg:phone":"+32 4 358 80 58",
    "sg:postcode":"4610",
    "sg:province":"Li\u00e8ge",
    "wof:name":"Mexher Jose",
    "wof:placetype":"venue"
},
  "geometry": {"coordinates":[5.6605758667,50.6248550415],"type":"Point"}
}