{
  "type": "Feature",
  "properties": {
    "addr:full":"Visserskaai 44bb Oostende West-Vlaanderen 8400",
    "addr:housenumber":"44bb",
    "addr:postcode":"8400",
    "addr:street":"Visserskaai",
    "iso:country":"BE",
    "sg:address":"Visserskaai 44bb",
    "sg:city":"Oostende",
    "sg:classifiers":[
        {
            "category":"Restaurant",
            "type":"Food & Drink"
        }
    ],
    "sg:phone":"+32 59 50 56 21",
    "sg:postcode":"8400",
    "sg:province":"West-Vlaanderen",
    "wof:name":"Restaurant Pier 44",
    "wof:placetype":"venue"
},
  "geometry": {"coordinates":[2.921432972,51.2341918945],"type":"Point"}
}