{
  "type": "Feature",
  "properties": {
    "addr:full":"Rue Victor Rauter 4 Bruxelles (anderlecht) Bruxelles-Capitale 1070",
    "addr:housenumber":"4",
    "addr:postcode":"1070",
    "addr:street":"Rue Victor Rauter",
    "iso:country":"BE",
    "sg:address":"Rue Victor Rauter 4",
    "sg:city":"Bruxelles (anderlecht)",
    "sg:classifiers":[
        {
            "category":"Retail",
            "subcategory":"Laundry & Dry Cleaning",
            "type":"Services"
        }
    ],
    "sg:phone":"+32 2 522 08 36",
    "sg:postcode":"1070",
    "sg:province":"Bruxelles-Capitale",
    "sg:tags":[
        "self",
        "-"
    ],
    "wof:name":"D.d. Wash",
    "wof:placetype":"venue"
},
  "geometry": {"coordinates":[4.3140158653,50.8342933655],"type":"Point"}
}