{
  "type": "Feature",
  "properties": {
    "addr:full":"Paternosterstraat 38 Aalst Oost-Vlaanderen 9300",
    "addr:housenumber":"38",
    "addr:postcode":"9300",
    "addr:street":"Paternosterstraat",
    "iso:country":"BE",
    "sg:address":"Paternosterstraat 38",
    "sg:city":"Aalst",
    "sg:orig_category":"Equipements pour la construction D\u00e9molition d\u00b4immeubles and terrassements",
    "sg:phone":"+32 53 70 38 57",
    "sg:postcode":"9300",
    "sg:province":"Oost-Vlaanderen",
    "wof:name":"Maurice Cherrette",
    "wof:placetype":"venue"
},
  "geometry": {"coordinates":[4.0009021759,50.9443740845],"type":"Point"}
}