{
  "type": "Feature",
  "properties": {
    "addr:full":"Langestraat 47 Scherpenheuvel-zichem (averbode) Vlaams-Brabant 3271",
    "addr:housenumber":"47",
    "addr:postcode":"3271",
    "addr:street":"Langestraat",
    "iso:country":"BE",
    "sg:address":"Langestraat 47",
    "sg:city":"Scherpenheuvel-zichem (averbode)",
    "sg:classifiers":[
        {
            "category":"Banks & Credit Unions",
            "subcategory":"Investment Brokerage",
            "type":"Services"
        }
    ],
    "sg:phone":"+32 13 78 57 19",
    "sg:postcode":"3271",
    "sg:province":"Vlaams-Brabant",
    "sg:tags":[
        "repair",
        "-",
        "installation",
        "sanitary",
        "article"
    ],
    "wof:name":"Loockx Installatiebedrijf Bvba",
    "wof:placetype":"venue"
},
  "geometry": {"coordinates":[4.9558358192,51.0380783081],"type":"Point"}
}