{
  "type": "Feature",
  "properties": {
    "addr:full":"Netestraat 27 Grobbendonk Antwerpen 2280",
    "addr:housenumber":"27",
    "addr:postcode":"2280",
    "addr:street":"Netestraat",
    "iso:country":"BE",
    "sg:address":"Netestraat 27",
    "sg:city":"Grobbendonk",
    "sg:orig_category":"Blanchisseries and teintureries",
    "sg:phone":"+32 14 51 22 20",
    "sg:postcode":"2280",
    "sg:province":"Antwerpen",
    "wof:name":"Wasserette",
    "wof:placetype":"venue"
},
  "geometry": {"coordinates":[4.7400779724,51.1870651245],"type":"Point"}
}