{
  "type": "Feature",
  "properties": {
    "addr:full":"Chauss\u00c9e De Mons 424 Tubize Brabant Wallon 1480",
    "addr:housenumber":"424",
    "addr:postcode":"1480",
    "addr:street":"Chausse\u0301E De Mons;Wallon",
    "iso:country":"BE",
    "sg:address":"Chauss\u00c9e De Mons 424",
    "sg:city":"Tubize",
    "sg:orig_category":"Installation \u00e9lectrique r\u00e9sidentielle",
    "sg:phone":"+32 2 355 74 70",
    "sg:postcode":"1480",
    "sg:province":"Brabant Wallon",
    "wof:name":"Mario Faiella",
    "wof:placetype":"venue"
},
  "geometry": {"coordinates":[4.1907758713,50.6785049438],"type":"Point"}
}