{
  "type": "Feature",
  "properties": {
    "iso:country":"BE",
    "sg:address":"Stokt 75",
    "sg:city":"Mol",
    "sg:classifiers":[
        {
            "category":"Professional",
            "subcategory":"Computer Services",
            "type":"Services"
        }
    ],
    "sg:phone":"+32 14 70 71 21",
    "sg:postcode":"2400",
    "sg:province":"Antwerpen",
    "sg:tags":[
        "-",
        "processing",
        "data",
        "software"
    ],
    "wof:name":"Ease Bvba",
    "wof:placetype":"venue"
},
  "geometry": {"coordinates":[5.0620670319,51.1900482178],"type":"Point"}
}