{
  "type": "Feature",
  "properties": {
    "addr:full":"Hofstraat 24 Box 3 Kontich Antwerpen 2550",
    "addr:housenumber":"24;3",
    "addr:postcode":"2550",
    "addr:street":"Hofstraat;Box",
    "iso:country":"BE",
    "sg:address":"Hofstraat 24 Box 3",
    "sg:city":"Kontich",
    "sg:classifiers":[
        {
            "category":"Personal",
            "subcategory":"Beauty Salon",
            "type":"Services"
        }
    ],
    "sg:phone":"+32 3 457 02 12",
    "sg:postcode":"2550",
    "sg:province":"Antwerpen",
    "wof:name":"Deti\u00e8ge N",
    "wof:placetype":"venue"
},
  "geometry": {"coordinates":[4.4499840736,51.135345459],"type":"Point"}
}