{
  "type": "Feature",
  "properties": {
    "addr:full":"Bouwelsesteenweg 107 Nijlen Antwerpen 2560",
    "addr:housenumber":"107",
    "addr:postcode":"2560",
    "addr:street":"Bouwelsesteenweg",
    "iso:country":"BE",
    "sg:address":"Bouwelsesteenweg 107",
    "sg:city":"Nijlen",
    "sg:orig_category":"V\u00e9hicules automobiles",
    "sg:phone":"+32 3 411 04 94",
    "sg:postcode":"2560",
    "sg:province":"Antwerpen",
    "wof:name":"P. Bellens",
    "wof:placetype":"venue"
},
  "geometry": {"coordinates":[4.683093071,51.1651306152],"type":"Point"}
}