{
  "type": "Feature",
  "properties": {
    "iso:country":"BE",
    "sg:address":"Avenue Winston Churchill 76",
    "sg:city":"Morlanwelz (morlanwelz-mariemont)",
    "sg:classifiers":[
        {
            "category":"Building & Trades",
            "subcategory":"Cleaning & Sanitation",
            "type":"Services"
        }
    ],
    "sg:phone":"+32 64 21 36 26",
    "sg:postcode":"7140",
    "sg:province":"Hainaut",
    "sg:tags":[
        "janitor"
    ],
    "wof:name":"Vg Net",
    "wof:placetype":"venue"
},
  "geometry": {"coordinates":[4.2282991409,50.4570465088],"type":"Point"}
}