{
  "type": "Feature",
  "properties": {
    "iso:country":"BE",
    "sg:address":"Boeschepestraat 46",
    "sg:city":"Poperinge",
    "sg:orig_category":"Enseignement secondaire g\u00e9n\u00e9ral",
    "sg:phone":"+32 57 33 51 56",
    "sg:postcode":"8970",
    "sg:province":"West-Vlaanderen",
    "wof:name":"Buso",
    "wof:placetype":"venue"
},
  "geometry": {"coordinates":[2.7224240303,50.8510284424],"type":"Point"}
}