{
  "type": "Feature",
  "properties": {
    "iso:country":"BE",
    "sg:address":"Rue De La Station 13",
    "sg:city":"Fleurus",
    "sg:classifiers":[
        {
            "category":"Cafe",
            "type":"Food & Drink"
        }
    ],
    "sg:phone":"+32 71 80 00 80",
    "sg:postcode":"6220",
    "sg:province":"Hainaut",
    "sg:tags":[
        "snack-bars"
    ],
    "wof:name":"Croc'n Roll",
    "wof:placetype":"venue"
},
  "geometry": {"coordinates":[4.549243927,50.4826622009],"type":"Point"}
}