{
  "type": "Feature",
  "properties": {
    "iso:country":"BE",
    "sg:address":"Grobbendonkseweg 40",
    "sg:city":"Nijlen",
    "sg:orig_category":"Pain, p\u00e2tisseries and confiseries",
    "sg:phone":"+32 3 481 93 54",
    "sg:postcode":"2560",
    "sg:province":"Antwerpen",
    "wof:name":"Daniel Peeters",
    "wof:placetype":"venue"
},
  "geometry": {"coordinates":[4.6898488998,51.1661720276],"type":"Point"}
}