{
  "type": "Feature",
  "properties": {
    "iso:country":"BE",
    "sg:address":"Kleine Dam 46",
    "sg:city":"Lokeren",
    "sg:orig_category":"Solariums",
    "sg:phone":"+32 9 349 25 05",
    "sg:postcode":"9160",
    "sg:province":"Oost-Vlaanderen",
    "wof:name":"Suncity",
    "wof:placetype":"venue"
},
  "geometry": {"coordinates":[3.9851560593,51.1023178101],"type":"Point"}
}