{
  "type": "Feature",
  "properties": {
    "iso:country":"BE",
    "sg:address":"Rue Des Ecoles 79",
    "sg:city":"Limbourg",
    "sg:classifiers":[
        {
            "category":"Government",
            "subcategory":"Fire Station",
            "type":"Public Place"
        }
    ],
    "sg:phone":"+32 80 67 20 30",
    "sg:postcode":"4830",
    "sg:province":"Li\u00e8ge",
    "sg:tags":[
        "water",
        "restoration",
        "damage"
    ],
    "wof:name":"Global Clean Sprl",
    "wof:placetype":"venue"
},
  "geometry": {"coordinates":[5.9407401085,50.6112518311],"type":"Point"}
}