{
  "type": "Feature",
  "properties": {
    "iso:country":"BE",
    "sg:address":"Rijsenbergstraat 404",
    "sg:city":"Gent",
    "sg:classifiers":[
        {
            "category":"Health Services",
            "subcategory":"Health Practitioner",
            "type":"Services"
        }
    ],
    "sg:phone":"+32 9 222 82 49",
    "sg:postcode":"9000",
    "sg:province":"Oost-Vlaanderen",
    "sg:tags":[
        "physiotherapist"
    ],
    "wof:name":"Hoozee R",
    "wof:placetype":"venue"
},
  "geometry": {"coordinates":[3.702080965,51.0427818298],"type":"Point"}
}