{
  "type": "Feature",
  "properties": {
    "addr:full":"Rue Alexandre Daoust 14 Dinant Namur 5500",
    "addr:housenumber":"14",
    "addr:postcode":"5500",
    "addr:street":"Rue Alexandre Daoust",
    "iso:country":"BE",
    "sg:address":"Rue Alexandre Daoust 14",
    "sg:city":"Dinant",
    "sg:classifiers":[
        {
            "category":"Health Services",
            "subcategory":"Doctor",
            "type":"Services"
        }
    ],
    "sg:phone":"+32 82 22 41 51",
    "sg:postcode":"5500",
    "sg:province":"Namur",
    "sg:tags":[
        "medicinephysicians",
        "surgeon"
    ],
    "wof:name":"Groupe M\u00e9decine G\u00e9n\u00e9rale",
    "wof:placetype":"venue"
},
  "geometry": {"coordinates":[4.9173498154,50.2538986206],"type":"Point"}
}