{
  "type": "Feature",
  "properties": {
    "iso:country":"BE",
    "sg:address":"Av. Commandants Borl\u00c9e 72",
    "sg:city":"Jodoigne",
    "sg:orig_category":"Immobili\u00ebnkantoren",
    "sg:phone":"+32 10 81 42 32",
    "sg:postcode":"1370",
    "sg:province":"Brabant Wallon",
    "wof:name":"Immobili\u00c8re De Wallonie",
    "wof:placetype":"venue"
},
  "geometry": {"coordinates":[4.8752250671,50.7219085693],"type":"Point"}
}