{
  "type": "Feature",
  "properties": {
    "addr:full":"Kraaistraat 30 Geetbets Vlaams-Brabant 3454",
    "addr:housenumber":"30",
    "addr:postcode":"3454",
    "addr:street":"Kraaistraat",
    "iso:country":"BE",
    "sg:address":"Kraaistraat 30",
    "sg:city":"Geetbets",
    "sg:orig_category":"Producteurs de fruits",
    "sg:phone":"+32 11 58 80 91",
    "sg:postcode":"3454",
    "sg:province":"Vlaams-Brabant",
    "wof:name":"Omer Vandenborne",
    "wof:placetype":"venue"
},
  "geometry": {"coordinates":[5.171312809,50.8897476196],"type":"Point"}
}