{
  "type": "Feature",
  "properties": {
    "addr:full":"Rue De L'eglise 2 Lasne Brabant Wallon 1380",
    "addr:housenumber":"2",
    "addr:postcode":"1380",
    "addr:street":"Rue De L'Eglise",
    "iso:country":"BE",
    "sg:address":"Rue De L'eglise 2",
    "sg:city":"Lasne",
    "sg:orig_category":"Chaussures",
    "sg:phone":"+32 2 633 10 25",
    "sg:postcode":"1380",
    "sg:province":"Brabant Wallon",
    "wof:name":"Le Godillot",
    "wof:placetype":"venue"
},
  "geometry": {"coordinates":[4.4834299088,50.6849784851],"type":"Point"}
}