{
  "type": "Feature",
  "properties": {
    "addr:full":"Nieuwheidestraat 2 As Limburg 3668",
    "addr:housenumber":"as",
    "addr:postcode":"3668",
    "addr:street":"Nieuwheidestraat;Limburg",
    "iso:country":"BE",
    "sg:address":"Nieuwheidestraat 2",
    "sg:city":"As",
    "sg:classifiers":[
        {
            "category":"Arena",
            "subcategory":"Sports Club",
            "type":"Entertainment"
        }
    ],
    "sg:phone":"+32 89 65 92 75",
    "sg:postcode":"3668",
    "sg:province":"Limburg",
    "sg:tags":[
        "terrain",
        "hors",
        "de",
        "installation",
        "sportifs"
    ],
    "wof:name":"Niel S.k.",
    "wof:placetype":"venue"
},
  "geometry": {"coordinates":[5.6141810417,51.026008606],"type":"Point"}
}