{
  "type": "Feature",
  "properties": {
    "iso:country":"BE",
    "sg:address":"Kapelstraat 41",
    "sg:city":"Schelle",
    "sg:classifiers":[
        {
            "category":"Health Services",
            "subcategory":"Health Practitioner",
            "type":"Services"
        }
    ],
    "sg:phone":"+32 3 887 16 44",
    "sg:postcode":"2627",
    "sg:province":"Antwerpen",
    "sg:tags":[
        "dietitian"
    ],
    "wof:name":"Van Boxem A",
    "wof:placetype":"venue"
},
  "geometry": {"coordinates":[4.3358697891,51.1234474182],"type":"Point"}
}