{
  "type": "Feature",
  "properties": {
    "addr:full":"Rue Puissant 169bd Charleroi Hainaut 6040",
    "addr:postcode":"169bd;6040",
    "addr:street":"Rue Puissant;Hainaut",
    "iso:country":"BE",
    "sg:address":"Rue Puissant 169bd",
    "sg:city":"Charleroi",
    "sg:orig_category":"Woningbouw",
    "sg:phone":"+32 71 32 72 49",
    "sg:postcode":"6040",
    "sg:province":"Hainaut",
    "wof:name":"Maurice Koekaerts",
    "wof:placetype":"venue"
},
  "geometry": {"coordinates":[4.4295520782,50.4340209961],"type":"Point"}
}