{
  "type": "Feature",
  "properties": {
    "iso:country":"BE",
    "sg:address":"Rue Forgeur 17-21",
    "sg:city":"Li\u00e8ge 1",
    "sg:classifiers":[
        {
            "category":"Banks & Credit Unions",
            "subcategory":"Bank",
            "type":"Services"
        }
    ],
    "sg:postcode":"4000",
    "sg:province":"Li\u00e8ge",
    "wof:name":"Rentacas Sc",
    "wof:placetype":"venue"
},
  "geometry": {"coordinates":[4.3496851921,50.8483848572],"type":"Point"}
}