{
  "type": "Feature",
  "properties": {
    "iso:country":"BE",
    "sg:address":"Acaciastraat 28",
    "sg:city":"Zedelgem",
    "sg:orig_category":"Magasins de r\u00e9parations d'articles personnels et m\u00e9nagers divers",
    "sg:phone":"+32 50 27 93 14",
    "sg:postcode":"8210",
    "sg:province":"West-Vlaanderen",
    "wof:name":"Nelly Nemegeer",
    "wof:placetype":"venue"
},
  "geometry": {"coordinates":[3.1458399296,51.1376457214],"type":"Point"}
}