{
  "type": "Feature",
  "properties": {
    "addr:full":"Rue D'andrimont 206 Dison (andrimont) Li\u00e8ge 4821",
    "addr:housenumber":"206",
    "addr:postcode":"4821",
    "addr:street":"Rue D'Andrimont",
    "iso:country":"BE",
    "sg:address":"Rue D'andrimont 206",
    "sg:city":"Dison (andrimont)",
    "sg:classifiers":[
        {
            "category":"Professional",
            "subcategory":"Art Services",
            "type":"Services"
        }
    ],
    "sg:phone":"+32 87 33 40 90",
    "sg:postcode":"4821",
    "sg:province":"Li\u00e8ge",
    "sg:tags":[
        "sculptor"
    ],
    "wof:name":"Faniel P",
    "wof:placetype":"venue"
},
  "geometry": {"coordinates":[5.8646888733,50.6093788147],"type":"Point"}
}