{
  "type": "Feature",
  "properties": {
    "addr:full":"Wetstraat 17 Antwerpen Antwerpen 2060",
    "addr:housenumber":"17",
    "addr:postcode":"2060",
    "addr:street":"Wetstraat",
    "iso:country":"BE",
    "sg:address":"Wetstraat 17",
    "sg:city":"Antwerpen",
    "sg:classifiers":[
        {
            "category":"Health Services",
            "subcategory":"Dentist",
            "type":"Services"
        }
    ],
    "sg:phone":"+32 3 271 18 95",
    "sg:postcode":"2060",
    "sg:province":"Antwerpen",
    "wof:name":"Heyde A",
    "wof:placetype":"venue"
},
  "geometry": {"coordinates":[4.4283018112,51.2209892273],"type":"Point"}
}