{
  "type": "Feature",
  "properties": {
    "addr:full":"Vrijheid 63 Arendonk Antwerpen 2370",
    "addr:housenumber":"63",
    "addr:postcode":"2370",
    "addr:street":"Vrijheid",
    "iso:country":"BE",
    "sg:address":"Vrijheid 63",
    "sg:city":"Arendonk",
    "sg:orig_category":"Imprimeries and copyshops",
    "sg:phone":"+32 14 67 70 52",
    "sg:postcode":"2370",
    "sg:province":"Antwerpen",
    "wof:name":"Lavrijsen",
    "wof:placetype":"venue"
},
  "geometry": {"coordinates":[5.0896148682,51.3214302063],"type":"Point"}
}