{
  "type": "Feature",
  "properties": {
    "addr:full":"Vlienderhaag 2 Damme West-Vlaanderen 8340",
    "addr:housenumber":"2",
    "addr:postcode":"8340",
    "addr:street":"Vlienderhaag",
    "iso:country":"BE",
    "sg:address":"Vlienderhaag 2",
    "sg:city":"Damme",
    "sg:orig_category":"Eleveurs and marchands de porcs. Eleveurs de bovins",
    "sg:phone":"+32 50 50 02 73",
    "sg:postcode":"8340",
    "sg:province":"West-Vlaanderen",
    "wof:name":"Dirk Claeys",
    "wof:placetype":"venue"
},
  "geometry": {"coordinates":[3.3194849491,51.2650680542],"type":"Point"}
}