{
  "type": "Feature",
  "properties": {
    "addr:full":"Rue Bollinckx 205 Bruxelles (anderlecht) Bruxelles-Capitale 1070",
    "addr:housenumber":"205",
    "addr:postcode":"1070",
    "addr:street":"Rue Bollinckx",
    "iso:country":"BE",
    "sg:address":"Rue Bollinckx 205",
    "sg:city":"Bruxelles (anderlecht)",
    "sg:classifiers":[
        {
            "category":"Manufacturing",
            "subcategory":"Tools & Machinery",
            "type":"Manufacturing & Wholesale Goods"
        }
    ],
    "sg:phone":"+32 2 524 10 60",
    "sg:postcode":"1070",
    "sg:province":"Bruxelles-Capitale",
    "sg:tags":[
        "diamond"
    ],
    "wof:name":"Spit",
    "wof:placetype":"venue"
},
  "geometry": {"coordinates":[4.3064098358,50.8147125244],"type":"Point"}
}