{
  "type": "Feature",
  "properties": {
    "addr:full":"Ertveldesteenweg 52 Assenede (oosteeklo) Oost-Vlaanderen 9968",
    "addr:housenumber":"52",
    "addr:postcode":"9968",
    "addr:street":"Ertveldesteenweg",
    "iso:country":"BE",
    "sg:address":"Ertveldesteenweg 52",
    "sg:city":"Assenede (oosteeklo)",
    "sg:classifiers":[
        {
            "category":"Autos & Motor Vehicles",
            "subcategory":"Automobile Sales",
            "type":"Retail Goods"
        }
    ],
    "sg:phone":"+32 9 373 70 97",
    "sg:postcode":"9968",
    "sg:province":"Oost-Vlaanderen",
    "sg:tags":[
        "ceremony",
        "car"
    ],
    "wof:name":"Taxi Daisy",
    "wof:placetype":"venue"
},
  "geometry": {"coordinates":[3.6958010197,51.1907615662],"type":"Point"}
}