{
  "type": "Feature",
  "properties": {
    "addr:full":"Rue De L'etuve 6 Brussel/bruxelles Bruxelles-Capitale 1000",
    "addr:housenumber":"6",
    "addr:postcode":"1000",
    "addr:street":"Rue De L'Etuve;/",
    "iso:country":"BE",
    "sg:address":"Rue De L'etuve 6",
    "sg:city":"Brussel/bruxelles",
    "sg:orig_category":"Pain, p\u00e2tisseries and confiseries",
    "sg:phone":"+32 2 512 29 95",
    "sg:postcode":"1000",
    "sg:province":"Bruxelles-Capitale",
    "wof:name":"Le Temps Du Sucre",
    "wof:placetype":"venue"
},
  "geometry": {"coordinates":[4.3515110016,50.8458061218],"type":"Point"}
}