{
  "type": "Feature",
  "properties": {
    "iso:country":"BE",
    "sg:address":"Alsembergse Steenweg 121",
    "sg:city":"Sint-gillis/saint-gilles",
    "sg:orig_category":"Herstellingswinkels voor diverse persoonlijke and huishoudartikelen Vloer- and muurbekleding",
    "sg:phone":"+32 2 534 80 31",
    "sg:postcode":"1060",
    "sg:province":"Bruxelles-Capitale",
    "wof:name":"Kal Tapis",
    "wof:placetype":"venue"
},
  "geometry": {"coordinates":[4.3425970078,50.8229751587],"type":"Point"}
}