{
  "type": "Feature",
  "properties": {
    "addr:full":"Gemeenteplein 10 Keerbergen Vlaams-Brabant 3140",
    "addr:housenumber":"10",
    "addr:postcode":"3140",
    "addr:street":"Gemeenteplein",
    "iso:country":"BE",
    "sg:address":"Gemeenteplein 10",
    "sg:city":"Keerbergen",
    "sg:classifiers":[
        {
            "category":"Health Services",
            "subcategory":"Nursing And Care Facility",
            "type":"Services"
        }
    ],
    "sg:phone":"+32 15 50 90 10",
    "sg:postcode":"3140",
    "sg:province":"Vlaams-Brabant",
    "sg:tags":[
        "public"
    ],
    "wof:name":"Gemeentebestuur",
    "wof:placetype":"venue"
},
  "geometry": {"coordinates":[4.6295819283,51.0034217834],"type":"Point"}
}