{
  "type": "Feature",
  "properties": {
    "addr:full":"Keiemdorpstraat 96 Diksmuide (keiem) West-Vlaanderen 8600",
    "addr:housenumber":"96",
    "addr:postcode":"8600",
    "addr:street":"Keiemdorpstraat",
    "iso:country":"BE",
    "sg:address":"Keiemdorpstraat 96",
    "sg:city":"Diksmuide (keiem)",
    "sg:classifiers":[
        {
            "category":"Bars & Pubs",
            "type":"Food & Drink"
        }
    ],
    "sg:phone":"+32 51 50 55 11",
    "sg:postcode":"8600",
    "sg:province":"West-Vlaanderen",
    "wof:name":"St-hubert",
    "wof:placetype":"venue"
},
  "geometry": {"coordinates":[2.8821880817,51.0802307129],"type":"Point"}
}