{
  "type": "Feature",
  "properties": {
    "addr:full":"Monnikenwerve 175 Brugge West-Vlaanderen 8000",
    "addr:housenumber":"175",
    "addr:postcode":"8000",
    "addr:street":"Monnikenwerve",
    "iso:country":"BE",
    "sg:address":"Monnikenwerve 175",
    "sg:city":"Brugge",
    "sg:orig_category":"Entretien and r\u00e9parations de voitures",
    "sg:phone":"+32 50 31 45 85",
    "sg:postcode":"8000",
    "sg:province":"West-Vlaanderen",
    "wof:name":"Dirk Deburchgraeve",
    "wof:placetype":"venue"
},
  "geometry": {"coordinates":[3.2048699856,51.2453613281],"type":"Point"}
}