{
  "type": "Feature",
  "properties": {
    "addr:full":"Rue Albert Asou 25 Tournai Hainaut 7500",
    "addr:housenumber":"25",
    "addr:postcode":"7500",
    "addr:street":"Rue Albert Asou",
    "iso:country":"BE",
    "sg:address":"Rue Albert Asou 25",
    "sg:city":"Tournai",
    "sg:classifiers":[
        {
            "category":"Health Services",
            "subcategory":"Doctor",
            "type":"Services"
        }
    ],
    "sg:phone":"+32 69 22 24 07",
    "sg:postcode":"7500",
    "sg:province":"Hainaut",
    "sg:tags":[
        "psychotherapist",
        "psychoanalyst"
    ],
    "wof:name":"Deleruelle D",
    "wof:placetype":"venue"
},
  "geometry": {"coordinates":[3.3953149319,50.6015815735],"type":"Point"}
}