{
  "type": "Feature",
  "properties": {
    "iso:country":"BE",
    "sg:address":"Rue De La Franco-belge 28",
    "sg:city":"La Louvi\u00e8re",
    "sg:classifiers":[
        {
            "category":"Shopping",
            "subcategory":"Optician",
            "type":"Retail Goods"
        }
    ],
    "sg:phone":"+32 64 26 31 27",
    "sg:postcode":"7100",
    "sg:province":"Hainaut",
    "sg:tags":[
        "-"
    ],
    "wof:name":"D'jobri Optic Sprl",
    "wof:placetype":"venue"
},
  "geometry": {"coordinates":[4.206633091,50.4872627258],"type":"Point"}
}