{
  "type": "Feature",
  "properties": {
    "addr:full":"Faubourg D'arrival Virton Luxembourg 6760",
    "addr:postcode":"6760",
    "addr:street":"Faubourg D'Arrival",
    "iso:country":"BE",
    "sg:address":"Faubourg D'arrival",
    "sg:city":"Virton",
    "sg:orig_category":"Supermarkten",
    "sg:postcode":"6760",
    "sg:province":"Luxembourg",
    "wof:name":"Aldi",
    "wof:placetype":"venue"
},
  "geometry": {"coordinates":[5.5318541527,49.5651473999],"type":"Point"}
}