{
  "type": "Feature",
  "properties": {
    "iso:country":"BE",
    "sg:address":"Hypolite Limbourglaan 3",
    "sg:city":"Anderlecht/anderlecht",
    "sg:orig_category":"Artsen and specialisten",
    "sg:phone":"+32 2 520 38 91",
    "sg:postcode":"1070",
    "sg:province":"Bruxelles-Capitale",
    "wof:name":"Anne Bidon",
    "wof:placetype":"venue"
},
  "geometry": {"coordinates":[4.2921800613,50.8291702271],"type":"Point"}
}