{
  "type": "Feature",
  "properties": {
    "iso:country":"BE",
    "sg:address":"Everselkiezel 120",
    "sg:city":"Heusden-zolder (heusden)",
    "sg:classifiers":[
        {
            "category":"Shopping",
            "subcategory":"Crafts & Fabrics",
            "type":"Retail Goods"
        }
    ],
    "sg:phone":"+32 11 42 55 48",
    "sg:postcode":"3550",
    "sg:province":"Limburg",
    "sg:tags":[
        "hi-fi",
        "equipment",
        "stereophonic",
        "-"
    ],
    "wof:name":"Schroeyen Nv",
    "wof:placetype":"venue"
},
  "geometry": {"coordinates":[5.2550501823,51.0297012329],"type":"Point"}
}