{
  "type": "Feature",
  "properties": {
    "iso:country":"BE",
    "sg:address":"Buisstraat 106",
    "sg:city":"Sint-amands",
    "sg:orig_category":"Voertuigen",
    "sg:phone":"+32 52 34 01 96",
    "sg:postcode":"2890",
    "sg:province":"Antwerpen",
    "wof:name":"Garage Yuruk Ramazan",
    "wof:placetype":"venue"
},
  "geometry": {"coordinates":[4.2113881111,51.0544013977],"type":"Point"}
}