{
  "type": "Feature",
  "properties": {
    "addr:full":"Sint-benedictusstraat 1 Mortsel Antwerpen 2640",
    "addr:housenumber":"1",
    "addr:postcode":"2640",
    "addr:street":"Sint-Benedictusstraat",
    "iso:country":"BE",
    "sg:address":"Sint-benedictusstraat 1",
    "sg:city":"Mortsel",
    "sg:orig_category":"Slagers",
    "sg:phone":"+32 3 449 87 34",
    "sg:postcode":"2640",
    "sg:province":"Antwerpen",
    "wof:name":"Herman Aertssens",
    "wof:placetype":"venue"
},
  "geometry": {"coordinates":[4.4625649452,51.1655349731],"type":"Point"}
}