{
  "type": "Feature",
  "properties": {
    "iso:country":"BE",
    "sg:address":"Abdijstraat 205",
    "sg:city":"Antwerpen",
    "sg:classifiers":[
        {
            "category":"Shopping",
            "subcategory":"Optician",
            "type":"Retail Goods"
        }
    ],
    "sg:phone":"+32 3 237 74 55",
    "sg:postcode":"2020",
    "sg:province":"Antwerpen",
    "sg:tags":[
        "-"
    ],
    "wof:name":"Eeraerts Opticiens Bvba",
    "wof:placetype":"venue"
},
  "geometry": {"coordinates":[4.3855028152,51.1873016357],"type":"Point"}
}