{
  "type": "Feature",
  "properties": {
    "addr:full":"Waterstraat 284 Gent Oost-Vlaanderen 9041",
    "addr:housenumber":"284",
    "addr:postcode":"9041",
    "addr:street":"Waterstraat;Oost-Vlaanderen",
    "iso:country":"BE",
    "sg:address":"Waterstraat 284",
    "sg:city":"Gent",
    "sg:orig_category":"Epiceries",
    "sg:phone":"+32 9 259 09 79",
    "sg:postcode":"9041",
    "sg:province":"Oost-Vlaanderen",
    "wof:name":"Paulus Dieleman",
    "wof:placetype":"venue"
},
  "geometry": {"coordinates":[3.7658789158,51.0766410828],"type":"Point"}
}