{
  "type": "Feature",
  "properties": {
    "iso:country":"BE",
    "sg:address":"Rue De France 13",
    "sg:city":"Rochefort",
    "sg:orig_category":"Maisons de repos and r\u00e9sidences",
    "sg:phone":"+32 84 22 06 70",
    "sg:postcode":"5580",
    "sg:province":"Namur",
    "wof:name":"Maison Retraite Rochefort",
    "wof:placetype":"venue"
},
  "geometry": {"coordinates":[5.2220368385,50.1575813293],"type":"Point"}
}