{
  "type": "Feature",
  "properties": {
    "addr:full":"Rue De France 2-2a Rochefort Namur 5580",
    "addr:housenumber":"2-2a",
    "addr:postcode":"5580",
    "addr:street":"Rue De France",
    "iso:country":"BE",
    "sg:address":"Rue De France 2-2a",
    "sg:city":"Rochefort",
    "sg:classifiers":[
        {
            "category":"Shopping",
            "subcategory":"Clothing, Apparel, & Fashions",
            "type":"Retail Goods"
        }
    ],
    "sg:phone":"+32 84 21 16 98",
    "sg:postcode":"5580",
    "sg:province":"Namur",
    "sg:tags":[
        "lady",
        "clothing",
        "-"
    ],
    "wof:name":"Stingry",
    "wof:placetype":"venue"
},
  "geometry": {"coordinates":[5.2227621078,50.1574783325],"type":"Point"}
}