{
  "type": "Feature",
  "properties": {
    "addr:full":"Rue De Cond\u00e9 41 Leuze-en-hainaut Hainaut 7900",
    "addr:housenumber":"41",
    "addr:postcode":"7900",
    "addr:street":"Rue De Conde\u0301",
    "iso:country":"BE",
    "sg:address":"Rue De Cond\u00e9 41",
    "sg:city":"Leuze-en-hainaut",
    "sg:classifiers":[
        {
            "category":"Bars & Pubs",
            "type":"Food & Drink"
        }
    ],
    "sg:phone":"+32 69 66 20 80",
    "sg:postcode":"7900",
    "sg:province":"Hainaut",
    "wof:name":"Patria",
    "wof:placetype":"venue"
},
  "geometry": {"coordinates":[3.6175739765,50.5962677002],"type":"Point"}
}