{
  "type": "Feature",
  "properties": {
    "addr:full":"Oude Molenstraat 3 Malle (westmalle) Antwerpen 2390",
    "addr:housenumber":"3",
    "addr:postcode":"2390",
    "addr:street":"Oude Molenstraat",
    "iso:country":"BE",
    "sg:address":"Oude Molenstraat 3",
    "sg:city":"Malle (westmalle)",
    "sg:classifiers":[
        {
            "category":"Personal",
            "subcategory":"Barber",
            "type":"Services"
        }
    ],
    "sg:phone":"+32 3 312 21 66",
    "sg:postcode":"2390",
    "sg:province":"Antwerpen",
    "sg:tags":[
        "gentleman",
        "salon",
        "-",
        "hairdressing"
    ],
    "wof:name":"Proost J",
    "wof:placetype":"venue"
},
  "geometry": {"coordinates":[4.6897878647,51.3037757874],"type":"Point"}
}