{
  "type": "Feature",
  "properties": {
    "addr:full":"Rue Saint-pierre 14 Floreffe Namur 5150",
    "addr:housenumber":"14",
    "addr:postcode":"5150",
    "addr:street":"Rue Saint-Pierre",
    "iso:country":"BE",
    "sg:address":"Rue Saint-pierre 14",
    "sg:city":"Floreffe",
    "sg:classifiers":[
        {
            "category":"Shopping",
            "subcategory":"Jewelry",
            "type":"Retail Goods"
        }
    ],
    "sg:phone":"+32 81 44 13 43",
    "sg:postcode":"5150",
    "sg:province":"Namur",
    "sg:tags":[
        "fab",
        "bijou"
    ],
    "wof:name":"Guy Badoux",
    "wof:placetype":"venue"
},
  "geometry": {"coordinates":[4.7313981056,50.4337387085],"type":"Point"}
}