{
  "type": "Feature",
  "properties": {
    "iso:country":"BE",
    "sg:address":"Vierschaarstraat 16",
    "sg:city":"Avelgem",
    "sg:orig_category":"Plaatsen van vloer- and muurbekleding",
    "sg:phone":"+32 55 38 86 37",
    "sg:postcode":"8581",
    "sg:province":"West-Vlaanderen",
    "wof:name":"Urbain Messeeuw",
    "wof:placetype":"venue"
},
  "geometry": {"coordinates":[3.5000200272,50.7991867065],"type":"Point"}
}