{
  "type": "Feature",
  "properties": {
    "addr:full":"'t Hoog 21 Hamme (moerzeke) Oost-Vlaanderen 9220",
    "addr:housenumber":"21",
    "addr:postcode":"9220",
    "addr:street":"' T Hoog",
    "iso:country":"BE",
    "sg:address":"'t Hoog 21",
    "sg:city":"Hamme (moerzeke)",
    "sg:classifiers":[
        {
            "category":"Building & Trades",
            "subcategory":"Construction",
            "type":"Services"
        }
    ],
    "sg:phone":"+32 52 48 34 91",
    "sg:postcode":"9220",
    "sg:province":"Oost-Vlaanderen",
    "sg:tags":[
        "stair"
    ],
    "wof:name":"De Lamper",
    "wof:placetype":"venue"
},
  "geometry": {"coordinates":[4.1644911766,51.0505561829],"type":"Point"}
}