{
  "type": "Feature",
  "properties": {
    "addr:full":"Groteweg 151 Geraardsbergen Oost-Vlaanderen 9500",
    "addr:housenumber":"151",
    "addr:postcode":"9500",
    "addr:street":"Groteweg",
    "iso:country":"BE",
    "sg:address":"Groteweg 151",
    "sg:city":"Geraardsbergen",
    "sg:orig_category":"Kapsalons",
    "sg:phone":"+32 54 42 19 82",
    "sg:postcode":"9500",
    "sg:province":"Oost-Vlaanderen",
    "wof:name":"Kapsalon Ilse",
    "wof:placetype":"venue"
},
  "geometry": {"coordinates":[3.8703799248,50.767539978],"type":"Point"}
}