{
  "type": "Feature",
  "properties": {
    "iso:country":"BE",
    "sg:address":"Sur Le Ti\u00c8ge 13",
    "sg:city":"Malmedy",
    "sg:classifiers":[
        {
            "category":"Arena",
            "subcategory":"Sports Club",
            "type":"Entertainment"
        }
    ],
    "sg:phone":"+32 80 57 06 08",
    "sg:postcode":"4960",
    "sg:province":"Li\u00e8ge",
    "sg:tags":[
        "de"
    ],
    "wof:name":"Club Marcheurs Bellevaux",
    "wof:placetype":"venue"
},
  "geometry": {"coordinates":[6.0645489693,50.3759727478],"type":"Point"}
}