{
  "type": "Feature",
  "properties": {
    "addr:full":"Rue Cardinal Mercier 22 Soumagne Li\u00e8ge 4633",
    "addr:housenumber":"22",
    "addr:postcode":"4633",
    "addr:street":"Rue Cardinal Mercier",
    "iso:country":"BE",
    "sg:address":"Rue Cardinal Mercier 22",
    "sg:city":"Soumagne",
    "sg:orig_category":"Installatie van houten of kunststof schrijnwerk",
    "sg:phone":"+32 4 377 19 22",
    "sg:postcode":"4633",
    "sg:province":"Li\u00e8ge",
    "wof:name":"Torun",
    "wof:placetype":"venue"
},
  "geometry": {"coordinates":[5.7365121841,50.6348953247],"type":"Point"}
}