{
  "type": "Feature",
  "properties": {
    "addr:full":"Rue De Hollogne 204 Jemeppe Li\u00e8ge 4101",
    "addr:housenumber":"204",
    "addr:postcode":"4101",
    "addr:street":"Rue De Hollogne",
    "iso:country":"BE",
    "sg:address":"Rue De Hollogne 204",
    "sg:city":"Jemeppe",
    "sg:classifiers":[
        {
            "category":"Sports & Exercise",
            "subcategory":"Sports Center",
            "type":"Entertainment"
        }
    ],
    "sg:phone":"+32 4 233 82 23",
    "sg:postcode":"4101",
    "sg:province":"Li\u00e8ge",
    "sg:tags":[
        "article",
        "de",
        "camping",
        "yamaha"
    ],
    "wof:name":"Laeremans F Garage Sprl",
    "wof:placetype":"venue"
},
  "geometry": {"coordinates":[5.4876899719,50.6256713867],"type":"Point"}
}