{
  "type": "Feature",
  "properties": {
    "iso:country":"BE",
    "sg:address":"Rue Joseph Heusdens 33",
    "sg:city":"Grace-hollogne",
    "sg:classifiers":[
        {
            "category":"Fast Food",
            "type":"Food & Drink"
        }
    ],
    "sg:phone":"+32 4 233 71 16",
    "sg:postcode":"4460",
    "sg:province":"Li\u00e8ge",
    "sg:tags":[
        "\u00c0",
        "emporter",
        "restaurants"
    ],
    "wof:name":"Friterie Cri-cri",
    "wof:placetype":"venue"
},
  "geometry": {"coordinates":[5.506360054,50.642490387],"type":"Point"}
}