{
  "type": "Feature",
  "properties": {
    "addr:full":"Merehoekstraat 58 Herzele Oost-Vlaanderen 9550",
    "addr:housenumber":"58",
    "addr:postcode":"9550",
    "addr:street":"Merehoekstraat;Oost-Vlaanderen",
    "iso:country":"BE",
    "sg:address":"Merehoekstraat 58",
    "sg:city":"Herzele",
    "sg:orig_category":"Artsen and specialisten",
    "sg:phone":"+32 9 360 07 07",
    "sg:postcode":"9550",
    "sg:province":"Oost-Vlaanderen",
    "wof:name":"C. Magerman",
    "wof:placetype":"venue"
},
  "geometry": {"coordinates":[3.8616480827,50.9003791809],"type":"Point"}
}