{
  "type": "Feature",
  "properties": {
    "iso:country":"BE",
    "sg:address":"Rue De La Station 55",
    "sg:city":"Wellin",
    "sg:classifiers":[
        {
            "category":"Professional",
            "subcategory":"Printing & Photocopies",
            "type":"Services"
        }
    ],
    "sg:phone":"+32 84 38 87 68",
    "sg:postcode":"6920",
    "sg:province":"Luxembourg",
    "sg:tags":[
        "-",
        "offset"
    ],
    "wof:name":"Imprimerie Banneux Sa",
    "wof:placetype":"venue"
},
  "geometry": {"coordinates":[5.122877121,50.07995224],"type":"Point"}
}