{
  "type": "Feature",
  "properties": {
    "iso:country":"BE",
    "sg:address":"Scav\u00c9e Du Bi\u00c9reau 36",
    "sg:city":"Ottignies-louvain-la-neuve",
    "sg:orig_category":"Sportclubs",
    "sg:phone":"+32 10 45 17 05",
    "sg:postcode":"1348",
    "sg:province":"Brabant Wallon",
    "wof:name":"Badminton Club Walhain 87",
    "wof:placetype":"venue"
},
  "geometry": {"coordinates":[4.6158099174,50.666305542],"type":"Point"}
}