{
  "type": "Feature",
  "properties": {
    "addr:full":"Drieselken 16 Denderleeuw Oost-Vlaanderen 9473",
    "addr:housenumber":"16",
    "addr:postcode":"9473",
    "addr:street":"Drieselken",
    "iso:country":"BE",
    "sg:address":"Drieselken 16",
    "sg:city":"Denderleeuw",
    "sg:orig_category":"Plaatsen van vloer- and muurbekleding Woningbouw",
    "sg:phone":"+32 53 68 13 40",
    "sg:postcode":"9473",
    "sg:province":"Oost-Vlaanderen",
    "wof:name":"Roger De Putter",
    "wof:placetype":"venue"
},
  "geometry": {"coordinates":[4.0439729691,50.8948631287],"type":"Point"}
}