{
  "type": "Feature",
  "properties": {
    "addr:full":"Rue Des Tiennes 351 Andenne Namur 5300",
    "addr:housenumber":"351",
    "addr:postcode":"5300",
    "addr:street":"Rue Des Tiennes",
    "iso:country":"BE",
    "sg:address":"Rue Des Tiennes 351",
    "sg:city":"Andenne",
    "sg:orig_category":"Beschutte werkplaatsen",
    "sg:phone":"+32 81 58 19 17",
    "sg:postcode":"5300",
    "sg:province":"Namur",
    "wof:name":"Le Fournil Des Tiennes",
    "wof:placetype":"venue"
},
  "geometry": {"coordinates":[5.0373601913,50.4890708923],"type":"Point"}
}