{
  "type": "Feature",
  "properties": {
    "addr:full":"Rue De La Montagne 45 Charleroi Hainaut 6000",
    "addr:housenumber":"45",
    "addr:postcode":"6000",
    "addr:street":"Rue De La Montagne;Hainaut",
    "iso:country":"BE",
    "sg:address":"Rue De La Montagne 45",
    "sg:city":"Charleroi",
    "sg:orig_category":"Dameskledingzaken",
    "sg:phone":"+32 71 32 74 54",
    "sg:postcode":"6000",
    "sg:province":"Hainaut",
    "wof:name":"M&s Mode",
    "wof:placetype":"venue"
},
  "geometry": {"coordinates":[4.4429140091,50.4098892212],"type":"Point"}
}