{
  "type": "Feature",
  "properties": {
    "addr:full":"Rue Saint-hubert 27 Mons (nimy) Hainaut 7020",
    "addr:housenumber":"27",
    "addr:postcode":"7020",
    "addr:street":"Rue Saint-Hubert",
    "iso:country":"BE",
    "sg:address":"Rue Saint-hubert 27",
    "sg:city":"Mons (nimy)",
    "sg:classifiers":[
        {
            "category":"Real Estate",
            "subcategory":"Architect",
            "type":"Services"
        }
    ],
    "sg:phone":"+32 65 33 75 03",
    "sg:postcode":"7020",
    "sg:province":"Hainaut",
    "wof:name":"Brouillard H",
    "wof:placetype":"venue"
},
  "geometry": {"coordinates":[3.9553449154,50.4761772156],"type":"Point"}
}