{
  "type": "Feature",
  "properties": {
    "iso:country":"BE",
    "sg:address":"Arkestraat 35",
    "sg:city":"Sint-niklaas (belsele)",
    "sg:classifiers":[
        {
            "category":"Retail",
            "subcategory":"Animal Services",
            "type":"Services"
        }
    ],
    "sg:phone":"+32 3 772 47 70",
    "sg:postcode":"9111",
    "sg:province":"Oost-Vlaanderen",
    "sg:tags":[
        "breeding",
        "selling",
        "-",
        "dog"
    ],
    "wof:name":"Chenil De Rialfo",
    "wof:placetype":"venue"
},
  "geometry": {"coordinates":[4.1036090851,51.1368713379],"type":"Point"}
}