{
  "type": "Feature",
  "properties": {
    "iso:country":"BE",
    "sg:address":"Isabellastraat 83",
    "sg:city":"Dilbeek",
    "sg:orig_category":"Eleveurs de bovins. Producteurs de fruits",
    "sg:phone":"+32 2 569 71 69",
    "sg:postcode":"1703",
    "sg:province":"Vlaams-Brabant",
    "wof:name":"Renatus Sergeant",
    "wof:placetype":"venue"
},
  "geometry": {"coordinates":[4.2161049843,50.827709198],"type":"Point"}
}