{
  "type": "Feature",
  "properties": {
    "iso:country":"BE",
    "sg:address":"Dorpstraat 252",
    "sg:city":"Bertem",
    "sg:orig_category":"Agences immobili\u00e8res",
    "sg:phone":"+32 16 48 15 35",
    "sg:postcode":"3061",
    "sg:province":"Vlaams-Brabant",
    "wof:name":"Bouw- En Immo Service",
    "wof:placetype":"venue"
},
  "geometry": {"coordinates":[4.6107029915,50.8569793701],"type":"Point"}
}