{
  "type": "Feature",
  "properties": {
    "addr:full":"Muilemstraat 310 Liedekerke Vlaams-Brabant 1770",
    "addr:housenumber":"310",
    "addr:postcode":"1770",
    "addr:street":"Muilemstraat;Vlaams-Brabant",
    "iso:country":"BE",
    "sg:address":"Muilemstraat 310",
    "sg:city":"Liedekerke",
    "sg:orig_category":"Kapsalons",
    "sg:phone":"+32 53 66 45 16",
    "sg:postcode":"1770",
    "sg:province":"Vlaams-Brabant",
    "wof:name":"An Stockmans",
    "wof:placetype":"venue"
},
  "geometry": {"coordinates":[4.1062521935,50.8800392151],"type":"Point"}
}