{
  "type": "Feature",
  "properties": {
    "addr:full":"Acht Eeuwenlaan 51 Edegem Antwerpen 2650",
    "addr:housenumber":"51",
    "addr:postcode":"2650",
    "addr:street":"Acht Eeuwenlaan",
    "iso:country":"BE",
    "sg:address":"Acht Eeuwenlaan 51",
    "sg:city":"Edegem",
    "sg:orig_category":"M\u00e9decins and sp\u00e9cialistes",
    "sg:phone":"+32 3 457 55 75",
    "sg:postcode":"2650",
    "sg:province":"Antwerpen",
    "wof:name":"Veerle Peeters",
    "wof:placetype":"venue"
},
  "geometry": {"coordinates":[4.4344768524,51.1538352966],"type":"Point"}
}