{
  "type": "Feature",
  "properties": {
    "addr:full":"Paalstraat 381 Schoten Antwerpen 2900",
    "addr:housenumber":"381",
    "addr:postcode":"2900",
    "addr:street":"Paalstraat",
    "iso:country":"BE",
    "sg:address":"Paalstraat 381",
    "sg:city":"Schoten",
    "sg:orig_category":"Plomberie, chauffage and installations sanitaires",
    "sg:phone":"+32 3 685 12 76",
    "sg:postcode":"2900",
    "sg:province":"Antwerpen",
    "wof:name":"Fa. Adriaensen",
    "wof:placetype":"venue"
},
  "geometry": {"coordinates":[4.508243084,51.2626457214],"type":"Point"}
}