{
  "type": "Feature",
  "properties": {
    "iso:country":"BE",
    "sg:address":"Dijk 2",
    "sg:city":"Balen",
    "sg:classifiers":[
        {
            "category":"Cafe",
            "type":"Food & Drink"
        }
    ],
    "sg:phone":"+32 14 30 87 27",
    "sg:postcode":"2491",
    "sg:province":"Antwerpen",
    "sg:tags":[
        "caf\u00e9s"
    ],
    "wof:name":"Olmen Sport",
    "wof:placetype":"venue"
},
  "geometry": {"coordinates":[5.1519889832,51.1487197876],"type":"Point"}
}