{
  "type": "Feature",
  "properties": {
    "iso:country":"BE",
    "sg:address":"Poeldendries 30",
    "sg:city":"Nevele (landegem)",
    "sg:classifiers":[
        {
            "category":"Professional",
            "subcategory":"Lawyer & Legal Services",
            "type":"Services"
        }
    ],
    "sg:phone":"+32 9 371 71 85",
    "sg:postcode":"9850",
    "sg:province":"Oost-Vlaanderen",
    "wof:name":"Ducheyne Francis",
    "wof:placetype":"venue"
},
  "geometry": {"coordinates":[3.5792629719,51.0597763062],"type":"Point"}
}