{
  "type": "Feature",
  "properties": {
    "iso:country":"BE",
    "sg:address":"Rue Du Village 52",
    "sg:city":"Gembloux",
    "sg:orig_category":"Rev\u00eatements pour sols and murs. Peinture",
    "sg:phone":"+32 81 61 13 00",
    "sg:postcode":"5030",
    "sg:province":"Namur",
    "wof:name":"Leopold Frennet",
    "wof:placetype":"venue"
},
  "geometry": {"coordinates":[4.7262592316,50.5846328735],"type":"Point"}
}