{
  "type": "Feature",
  "properties": {
    "addr:full":"Stationstraat 67 Machelen Vlaams-Brabant 1831",
    "addr:housenumber":"67",
    "addr:postcode":"1831",
    "addr:street":"Stationstraat",
    "iso:country":"BE",
    "sg:address":"Stationstraat 67",
    "sg:city":"Machelen",
    "sg:orig_category":"Animations diverses",
    "sg:phone":"+32 2 725 59 57",
    "sg:postcode":"1831",
    "sg:province":"Vlaams-Brabant",
    "wof:name":"Remy Ray",
    "wof:placetype":"venue"
},
  "geometry": {"coordinates":[4.4398899078,50.8916358948],"type":"Point"}
}