{
  "type": "Feature",
  "properties": {
    "addr:full":"Rue De L'eglise De Barry 19 Tournai Hainaut 7534",
    "addr:housenumber":"19",
    "addr:postcode":"7534",
    "addr:street":"Rue De L'Eglise De Barry",
    "iso:country":"BE",
    "sg:address":"Rue De L'eglise De Barry 19",
    "sg:city":"Tournai",
    "sg:orig_category":"Enseignement maternel and primaire",
    "sg:phone":"+32 69 54 61 82",
    "sg:postcode":"7534",
    "sg:province":"Hainaut",
    "wof:name":"Ecole Maternelle Libre",
    "wof:placetype":"venue"
},
  "geometry": {"coordinates":[3.3942399025,50.6224517822],"type":"Point"}
}