{
  "type": "Feature",
  "properties": {
    "addr:full":"Avenue Carton De Wiart 79 Bruxelles (jette) Bruxelles-Capitale 1090",
    "addr:housenumber":"79",
    "addr:postcode":"1090",
    "addr:street":"Avenue Carton De Wiart",
    "iso:country":"BE",
    "sg:address":"Avenue Carton De Wiart 79",
    "sg:city":"Bruxelles (jette)",
    "sg:classifiers":[
        {
            "category":"Wholesale",
            "subcategory":"Auto Parts",
            "type":"Manufacturing & Wholesale Goods"
        }
    ],
    "sg:phone":"+32 2 421 01 70",
    "sg:postcode":"1090",
    "sg:province":"Bruxelles-Capitale",
    "sg:tags":[
        "refrigerating"
    ],
    "wof:name":"Dehon Service Belgium Sa",
    "wof:placetype":"venue"
},
  "geometry": {"coordinates":[4.3296890259,50.8678703308],"type":"Point"}
}