{
  "type": "Feature",
  "properties": {
    "addr:full":"Patersweg 7 Sint-katelijne-waver Antwerpen 2860",
    "addr:housenumber":"7",
    "addr:postcode":"2860",
    "addr:street":"Patersweg",
    "iso:country":"BE",
    "sg:address":"Patersweg 7",
    "sg:city":"Sint-katelijne-waver",
    "sg:classifiers":[
        {
            "category":"Building & Trades",
            "subcategory":"Landscaping Services",
            "type":"Services"
        }
    ],
    "sg:phone":"+32 15 55 18 19",
    "sg:postcode":"2860",
    "sg:province":"Antwerpen",
    "sg:tags":[
        "gardening",
        "garden",
        "maintenance"
    ],
    "wof:name":"Van Den Zegel R",
    "wof:placetype":"venue"
},
  "geometry": {"coordinates":[4.5415692329,51.0547218323],"type":"Point"}
}