{
  "type": "Feature",
  "properties": {
    "iso:country":"BE",
    "sg:address":"Leuvensestraat 48",
    "sg:city":"Tienen",
    "sg:orig_category":"Studios photographiques. Equipement photographique",
    "sg:phone":"+32 16 81 59 18",
    "sg:postcode":"3300",
    "sg:province":"Vlaams-Brabant",
    "wof:name":"August Vandermolen",
    "wof:placetype":"venue"
},
  "geometry": {"coordinates":[4.9342050552,50.8089141846],"type":"Point"}
}