{
  "type": "Feature",
  "properties": {
    "iso:country":"BE",
    "sg:address":"Groenstraat 103",
    "sg:city":"Aalst (erembodegem)",
    "sg:classifiers":[
        {
            "category":"Professional",
            "subcategory":"Art Services",
            "type":"Services"
        }
    ],
    "sg:phone":"+32 53 84 08 68",
    "sg:postcode":"9320",
    "sg:province":"Oost-Vlaanderen",
    "sg:tags":[
        "photographer"
    ],
    "wof:name":"Fotostudio Sas",
    "wof:placetype":"venue"
},
  "geometry": {"coordinates":[4.0522418022,50.9438896179],"type":"Point"}
}