{
  "type": "Feature",
  "properties": {
    "addr:full":"Bremstraat 76 Lanaken Limburg 3620",
    "addr:housenumber":"76",
    "addr:postcode":"3620",
    "addr:street":"Bremstraat",
    "iso:country":"BE",
    "sg:address":"Bremstraat 76",
    "sg:city":"Lanaken",
    "sg:orig_category":"Industri\u00eble and commerci\u00eble bouw Woningbouw",
    "sg:phone":"+32 89 71 26 65",
    "sg:postcode":"3620",
    "sg:province":"Limburg",
    "wof:name":"Bobema Belgie",
    "wof:placetype":"venue"
},
  "geometry": {"coordinates":[5.6227731705,50.8969154358],"type":"Point"}
}