{
  "type": "Feature",
  "properties": {
    "iso:country":"BE",
    "sg:address":"Het Geleeg 29",
    "sg:city":"Wuustwezel",
    "sg:classifiers":[
        {
            "category":"Building & Trades",
            "subcategory":"Electrical",
            "type":"Services"
        }
    ],
    "sg:phone":"+32 3 644 78 19",
    "sg:postcode":"2990",
    "sg:province":"Antwerpen",
    "sg:tags":[
        "electric",
        "-",
        "housewiring",
        "contractor"
    ],
    "wof:name":"Belka Bvba",
    "wof:placetype":"venue"
},
  "geometry": {"coordinates":[4.5499649048,51.3609428406],"type":"Point"}
}