{
  "type": "Feature",
  "properties": {
    "addr:full":"Paardestraat 6bbis Pittem West-Vlaanderen 8740",
    "addr:postcode":"8740",
    "addr:street":"Paardestraat",
    "iso:country":"BE",
    "sg:address":"Paardestraat 6bbis",
    "sg:city":"Pittem",
    "sg:orig_category":"Dranken Gh",
    "sg:phone":"+32 51 46 50 19",
    "sg:postcode":"8740",
    "sg:province":"West-Vlaanderen",
    "wof:name":"Peter Coopman",
    "wof:placetype":"venue"
},
  "geometry": {"coordinates":[3.2612299919,51.0156211853],"type":"Point"}
}