{
  "type": "Feature",
  "properties": {
    "addr:full":"Weg Naar Zwartberg 214 Opglabbeek Limburg 3660",
    "addr:housenumber":"214",
    "addr:postcode":"3660",
    "addr:street":"Weg Naar Zwartberg",
    "iso:country":"BE",
    "sg:address":"Weg Naar Zwartberg 214",
    "sg:city":"Opglabbeek",
    "sg:classifiers":[
        {
            "category":"Utilities",
            "subcategory":"Telephone",
            "type":"Services"
        }
    ],
    "sg:phone":"+32 89 81 08 81",
    "sg:postcode":"3660",
    "sg:province":"Limburg",
    "sg:tags":[
        "installation"
    ],
    "wof:name":"Jojo Elektronica",
    "wof:placetype":"venue"
},
  "geometry": {"coordinates":[5.5619101524,51.0374488831],"type":"Point"}
}