{
  "type": "Feature",
  "properties": {
    "addr:full":"Tieltse Baan 22 Aarschot Vlaams-Brabant 3200",
    "addr:housenumber":"22",
    "addr:postcode":"3200",
    "addr:street":"Tieltse Baan",
    "iso:country":"BE",
    "sg:address":"Tieltse Baan 22",
    "sg:city":"Aarschot",
    "sg:classifiers":[
        {
            "category":"Building & Trades",
            "subcategory":"Electrical",
            "type":"Services"
        }
    ],
    "sg:phone":"+32 475 61 74 18",
    "sg:postcode":"3200",
    "sg:province":"Vlaams-Brabant",
    "sg:tags":[
        "electric",
        "-",
        "housewiring",
        "contractor"
    ],
    "wof:name":"Relek Bvba",
    "wof:placetype":"venue"
},
  "geometry": {"coordinates":[4.8421030045,50.9760932922],"type":"Point"}
}