{
  "type": "Feature",
  "properties": {
    "addr:full":"Rue Nouvelle 31 Libin Luxembourg 6890",
    "addr:housenumber":"31",
    "addr:postcode":"6890",
    "addr:street":"Rue Nouvelle",
    "iso:country":"BE",
    "sg:address":"Rue Nouvelle 31",
    "sg:city":"Libin",
    "sg:orig_category":"Woningbouw",
    "sg:phone":"+32 61 65 58 07",
    "sg:postcode":"6890",
    "sg:province":"Luxembourg",
    "wof:name":"Patrice Kauffman",
    "wof:placetype":"venue"
},
  "geometry": {"coordinates":[5.2562999725,49.9827537537],"type":"Point"}
}