{
  "type": "Feature",
  "properties": {
    "iso:country":"BE",
    "sg:address":"Chemin Du Lefa 8",
    "sg:city":"Malmedy/malmedy",
    "sg:orig_category":"Machines and mat\u00e9riel agricoles Jardinage",
    "sg:phone":"+32 80 33 80 34",
    "sg:postcode":"4960",
    "sg:province":"Li\u00e8ge",
    "wof:name":"Espaces Verts Jamar",
    "wof:placetype":"venue"
},
  "geometry": {"coordinates":[6.0570931435,50.4068603516],"type":"Point"}
}