{
  "type": "Feature",
  "properties": {
    "addr:full":"Chauss\u00e9e D'audenarde 157 Pecq (h\u00e9rinnes-lez-pecq) Hainaut 7742",
    "addr:housenumber":"157",
    "addr:postcode":"7742",
    "addr:street":"Chausse\u0301E D'Audenarde",
    "iso:country":"BE",
    "sg:address":"Chauss\u00e9e D'audenarde 157",
    "sg:city":"Pecq (h\u00e9rinnes-lez-pecq)",
    "sg:classifiers":[
        {
            "category":"Health Services",
            "subcategory":"Doctor",
            "type":"Services"
        }
    ],
    "sg:phone":"+32 69 55 66 07",
    "sg:postcode":"7742",
    "sg:province":"Hainaut",
    "sg:tags":[
        "medicinephysicians",
        "surgeon"
    ],
    "wof:name":"Leroy Bernard",
    "wof:placetype":"venue"
},
  "geometry": {"coordinates":[3.3613779545,50.6910896301],"type":"Point"}
}