{
  "type": "Feature",
  "properties": {
    "addr:full":"Dorp 6 Berlare Oost-Vlaanderen 9290",
    "addr:housenumber":"6",
    "addr:postcode":"9290",
    "addr:street":"Dorp",
    "iso:country":"BE",
    "sg:address":"Dorp 6",
    "sg:city":"Berlare",
    "sg:classifiers":[
        {
            "category":"Banks & Credit Unions",
            "subcategory":"Bank",
            "type":"Services"
        }
    ],
    "sg:phone":"+32 52 42 39 46",
    "sg:postcode":"9290",
    "sg:province":"Oost-Vlaanderen",
    "wof:name":"Gemeentekrediet",
    "wof:placetype":"venue"
},
  "geometry": {"coordinates":[4.0044059753,51.0251312256],"type":"Point"}
}