{
  "type": "Feature",
  "properties": {
    "addr:full":"Rue Albert I 66 Fernelmont (noville-les-bois) Namur 5380",
    "addr:housenumber":"66",
    "addr:postcode":"5380",
    "addr:street":"Rue Albert I",
    "iso:country":"BE",
    "sg:address":"Rue Albert I 66",
    "sg:city":"Fernelmont (noville-les-bois)",
    "sg:classifiers":[
        {
            "category":"Shopping",
            "subcategory":"Musical Instruments",
            "type":"Retail Goods"
        }
    ],
    "sg:phone":"+32 81 83 48 05",
    "sg:postcode":"5380",
    "sg:province":"Namur",
    "sg:tags":[
        "-"
    ],
    "wof:name":"Atelier De Lutherie",
    "wof:placetype":"venue"
},
  "geometry": {"coordinates":[4.9774899483,50.5461235046],"type":"Point"}
}