{
  "type": "Feature",
  "properties": {
    "iso:country":"BE",
    "sg:address":"Weitingstraat 2",
    "sg:city":"Aalter",
    "sg:orig_category":"Installatie van houten of kunststof schrijnwerk",
    "sg:phone":"+32 9 374 15 58",
    "sg:postcode":"9881",
    "sg:province":"Oost-Vlaanderen",
    "wof:name":"Fa. Lambrecht G. & Zn",
    "wof:placetype":"venue"
},
  "geometry": {"coordinates":[3.502491951,51.0773086548],"type":"Point"}
}