{
  "type": "Feature",
  "properties": {
    "iso:country":"BE",
    "sg:address":"Stationsstraat 9b6",
    "sg:city":"Beveren",
    "sg:orig_category":"Diverse persoonlijke diensten",
    "sg:phone":"+32 3 755 21 23",
    "sg:postcode":"9120",
    "sg:province":"Oost-Vlaanderen",
    "wof:name":"Kris Van De Sompel",
    "wof:placetype":"venue"
},
  "geometry": {"coordinates":[4.2574629784,51.2115364075],"type":"Point"}
}