{
  "type": "Feature",
  "properties": {
    "addr:full":"Industrielaan 7 Ternat Vlaams-Brabant 1740",
    "addr:housenumber":"7",
    "addr:postcode":"1740",
    "addr:street":"Industrielaan",
    "iso:country":"BE",
    "sg:address":"Industrielaan 7",
    "sg:city":"Ternat",
    "sg:classifiers":[
        {
            "category":"Banks & Credit Unions",
            "subcategory":"Investment Brokerage",
            "type":"Services"
        }
    ],
    "sg:phone":"+32 2 583 00 40",
    "sg:postcode":"1740",
    "sg:province":"Vlaams-Brabant",
    "sg:tags":[
        "pipe",
        "fitting",
        "coupling"
    ],
    "wof:name":"Sanha Fittings Bvba",
    "wof:placetype":"venue"
},
  "geometry": {"coordinates":[4.1781978607,50.887424469],"type":"Point"}
}