{
  "type": "Feature",
  "properties": {
    "addr:full":"Rue Reimond Stijns 2 Bruxelles (molenbeek-saint-jean) Bruxelles-Capitale 1080",
    "addr:housenumber":"2",
    "addr:postcode":"1080",
    "addr:street":"Rue Reimond Stijns",
    "iso:country":"BE",
    "sg:address":"Rue Reimond Stijns 2",
    "sg:city":"Bruxelles (molenbeek-saint-jean)",
    "sg:classifiers":[
        {
            "category":"Professional",
            "subcategory":"Management & Consulting",
            "type":"Services"
        }
    ],
    "sg:phone":"+32 2 414 05 93",
    "sg:postcode":"1080",
    "sg:province":"Bruxelles-Capitale",
    "sg:tags":[
        "consultant"
    ],
    "wof:name":"Revitaliser Karreveld",
    "wof:placetype":"venue"
},
  "geometry": {"coordinates":[4.3151898384,50.8583297729],"type":"Point"}
}