{
  "type": "Feature",
  "properties": {
    "addr:full":"Chauss\u00e9e De Mons 62 Manage Hainaut 7170",
    "addr:housenumber":"62",
    "addr:postcode":"7170",
    "addr:street":"Chausse\u0301E De Mons",
    "iso:country":"BE",
    "sg:address":"Chauss\u00e9e De Mons 62",
    "sg:city":"Manage",
    "sg:classifiers":[
        {
            "category":"Health Services",
            "subcategory":"Health Practitioner",
            "type":"Services"
        }
    ],
    "sg:phone":"+32 64 54 03 36",
    "sg:postcode":"7170",
    "sg:province":"Hainaut",
    "sg:tags":[
        "therapist",
        "speech"
    ],
    "wof:name":"Nisolle A-m",
    "wof:placetype":"venue"
},
  "geometry": {"coordinates":[4.2268638611,50.4950485229],"type":"Point"}
}