{
  "type": "Feature",
  "properties": {
    "addr:full":"Avenue Jean-baptiste Nothomb 10 Arlon Luxembourg 6700",
    "addr:housenumber":"10",
    "addr:postcode":"6700",
    "addr:street":"Avenue Jean-Baptiste Nothomb",
    "iso:country":"BE",
    "sg:address":"Avenue Jean-baptiste Nothomb 10",
    "sg:city":"Arlon",
    "sg:classifiers":[
        {
            "category":"Organizations",
            "subcategory":"Professional Association",
            "type":"Services"
        }
    ],
    "sg:phone":"+32 63 22 06 07",
    "sg:postcode":"6700",
    "sg:province":"Luxembourg",
    "sg:tags":[
        "trade-union",
        "federation"
    ],
    "wof:name":"Ucm-feclalux",
    "wof:placetype":"venue"
},
  "geometry": {"coordinates":[5.8113899231,49.6821327209],"type":"Point"}
}