{
  "type": "Feature",
  "properties": {
    "iso:country":"BE",
    "sg:address":"Lodewijk De Raetlaan 5",
    "sg:city":"Overpelt",
    "sg:classifiers":[
        {
            "category":"Arts & Performance",
            "subcategory":"Art Gallery",
            "type":"Entertainment"
        }
    ],
    "sg:phone":"+32 11 80 03 70",
    "sg:postcode":"3900",
    "sg:province":"Limburg",
    "sg:tags":[
        "photoengravers"
    ],
    "wof:name":"Catalpa Belgi\u00eb",
    "wof:placetype":"venue"
},
  "geometry": {"coordinates":[5.3785161972,51.2229881287],"type":"Point"}
}