{
  "type": "Feature",
  "properties": {
    "iso:country":"BE",
    "sg:address":"Haachtsesteenweg 11",
    "sg:city":"Steenokkerzeel",
    "sg:orig_category":"V\u00e9hicules automobiles",
    "sg:phone":"+32 16 65 10 85",
    "sg:postcode":"1820",
    "sg:province":"Vlaams-Brabant",
    "wof:name":"East-west Motors",
    "wof:placetype":"venue"
},
  "geometry": {"coordinates":[4.5181908607,50.9252586365],"type":"Point"}
}