{
  "type": "Feature",
  "properties": {
    "addr:full":"Kortrijksestraat 151 Kortrijk West-Vlaanderen 8501",
    "addr:housenumber":"151",
    "addr:postcode":"8501",
    "addr:street":"Kortrijksestraat",
    "iso:country":"BE",
    "sg:address":"Kortrijksestraat 151",
    "sg:city":"Kortrijk",
    "sg:classifiers":[
        {
            "category":"Communications",
            "subcategory":"Television Station",
            "type":"Services"
        }
    ],
    "sg:phone":"+32 56 37 19 99",
    "sg:postcode":"8501",
    "sg:province":"West-Vlaanderen",
    "sg:tags":[
        "video",
        "audio",
        "verhuur"
    ],
    "wof:name":"Video 99",
    "wof:placetype":"venue"
},
  "geometry": {"coordinates":[3.2409660816,50.8377342224],"type":"Point"}
}