{
  "type": "Feature",
  "properties": {
    "iso:country":"BE",
    "sg:address":"Kammenstraat 89",
    "sg:city":"Antwerpen",
    "sg:orig_category":"Animaux domestiques and accessoires. Services pour animaux domestiques",
    "sg:phone":"+32 3 233 49 96",
    "sg:postcode":"2000",
    "sg:province":"Antwerpen",
    "wof:name":"Den Terrier",
    "wof:placetype":"venue"
},
  "geometry": {"coordinates":[4.4019150734,51.2159767151],"type":"Point"}
}