{
  "type": "Feature",
  "properties": {
    "iso:country":"BE",
    "sg:address":"Rue Neuve 22",
    "sg:city":"Brussel/bruxelles",
    "sg:orig_category":"Mat\u00e9riel de T\u00e9l\u00e9communication",
    "sg:phone":"+32 2 223 11 37",
    "sg:postcode":"1000",
    "sg:province":"Bruxelles-Capitale",
    "wof:name":"Bel Concept",
    "wof:placetype":"venue"
},
  "geometry": {"coordinates":[4.3540668488,50.851108551],"type":"Point"}
}