{
  "type": "Feature",
  "properties": {
    "iso:country":"BE",
    "sg:address":"Rue Du Moulin 45",
    "sg:city":"Honnelles",
    "sg:orig_category":"Kampeerterreinen",
    "sg:phone":"+32 65 75 91 46",
    "sg:postcode":"7387",
    "sg:province":"Hainaut",
    "wof:name":"Camping Emile Verhaeren",
    "wof:placetype":"venue"
},
  "geometry": {"coordinates":[3.6959199905,50.3683853149],"type":"Point"}
}