{
  "type": "Feature",
  "properties": {
    "addr:full":"Rue Voie Des Vaux 277 Saint-nicolas (montegn\u00e9e) Li\u00e8ge 4420",
    "addr:housenumber":"277",
    "addr:postcode":"4420",
    "addr:street":"Rue Voie Des Vaux;Montegne\u0301E",
    "iso:country":"BE",
    "sg:address":"Rue Voie Des Vaux 277",
    "sg:city":"Saint-nicolas (montegn\u00e9e)",
    "sg:classifiers":[
        {
            "category":"Building & Trades",
            "subcategory":"Construction",
            "type":"Services"
        }
    ],
    "sg:phone":"+32 4 233 56 83",
    "sg:postcode":"4420",
    "sg:province":"Li\u00e8ge",
    "sg:tags":[
        "scaffolding"
    ],
    "wof:name":"Speed Plaque",
    "wof:placetype":"venue"
},
  "geometry": {"coordinates":[5.5089898109,50.6332054138],"type":"Point"}
}