{
  "type": "Feature",
  "properties": {
    "addr:full":"Rue De Flostoy 14 Hamois Namur 5364",
    "addr:housenumber":"14",
    "addr:postcode":"5364",
    "addr:street":"Rue De Flostoy",
    "iso:country":"BE",
    "sg:address":"Rue De Flostoy 14",
    "sg:city":"Hamois",
    "sg:orig_category":"Installation de menuiserie en bois and plastique",
    "sg:phone":"+32 83 61 17 96",
    "sg:postcode":"5364",
    "sg:province":"Namur",
    "wof:name":"Gueutal Yvan",
    "wof:placetype":"venue"
},
  "geometry": {"coordinates":[5.1259250641,50.3596916199],"type":"Point"}
}