{
  "type": "Feature",
  "properties": {
    "addr:full":"Neuerweg 16 B\u00dctgenbach/b\u00dctgenbach Li\u00e8ge 4750",
    "addr:housenumber":"16",
    "addr:postcode":"4750",
    "addr:street":"Neuerweg",
    "iso:country":"BE",
    "sg:address":"Neuerweg 16",
    "sg:city":"B\u00dctgenbach/b\u00dctgenbach",
    "sg:orig_category":"Boucheries",
    "sg:phone":"+32 80 44 56 26",
    "sg:postcode":"4750",
    "sg:province":"Li\u00e8ge",
    "wof:name":"Karl-heinz Mertes",
    "wof:placetype":"venue"
},
  "geometry": {"coordinates":[6.2206501961,50.457408905],"type":"Point"}
}