{
  "type": "Feature",
  "properties": {
    "iso:country":"BE",
    "sg:address":"Valerius De Saedeleerstraat 54",
    "sg:city":"Aalst",
    "sg:classifiers":[
        {
            "category":"Cafe",
            "type":"Food & Drink"
        }
    ],
    "sg:phone":"+32 53 78 98 24",
    "sg:postcode":"9300",
    "sg:province":"Oost-Vlaanderen",
    "sg:tags":[
        "snack-bars"
    ],
    "wof:name":"Aad Oljst",
    "wof:placetype":"venue"
},
  "geometry": {"coordinates":[4.0316791534,50.9441490173],"type":"Point"}
}