{
  "type": "Feature",
  "properties": {
    "addr:full":"Rue De Bau 2 Chastre Brabant Wallon 1450",
    "addr:housenumber":"2",
    "addr:postcode":"1450",
    "addr:street":"Rue De Bau",
    "iso:country":"BE",
    "sg:address":"Rue De Bau 2",
    "sg:city":"Chastre",
    "sg:orig_category":"Editeurs de journaux. Secr\u00e9tariats. Editeurs de revues and p\u00e9riodiques",
    "sg:phone":"+32 10 65 03 87",
    "sg:postcode":"1450",
    "sg:province":"Brabant Wallon",
    "wof:name":"Editions Saffran",
    "wof:placetype":"venue"
},
  "geometry": {"coordinates":[4.6391019821,50.6248321533],"type":"Point"}
}