{
  "type": "Feature",
  "properties": {
    "iso:country":"BE",
    "sg:address":"Legen Heirweg 67",
    "sg:city":"Gavere",
    "sg:orig_category":"Entretien and r\u00e9parations de voitures",
    "sg:phone":"+32 9 384 17 79",
    "sg:postcode":"9890",
    "sg:province":"Oost-Vlaanderen",
    "wof:name":"Dhondt",
    "wof:placetype":"venue"
},
  "geometry": {"coordinates":[3.6467978954,50.9334487915],"type":"Point"}
}