{
  "type": "Feature",
  "properties": {
    "iso:country":"BE",
    "sg:address":"Kattestraat 15",
    "sg:city":"Diksmuide",
    "sg:orig_category":"Eleveurs and marchands de porcs",
    "sg:phone":"+32 51 50 12 19",
    "sg:postcode":"8600",
    "sg:province":"West-Vlaanderen",
    "wof:name":"Pol Demaeght",
    "wof:placetype":"venue"
},
  "geometry": {"coordinates":[2.9043769836,51.0112228394],"type":"Point"}
}