{
  "type": "Feature",
  "properties": {
    "iso:country":"BE",
    "sg:address":"Rue De L\u00b4arsenal 2bb",
    "sg:city":"Namur",
    "sg:orig_category":"Artsen and specialisten",
    "sg:phone":"+32 81 73 52 06",
    "sg:postcode":"5000",
    "sg:province":"Namur",
    "wof:name":"Pierre Nihard",
    "wof:placetype":"venue"
},
  "geometry": {"coordinates":[4.8590531349,50.4637756348],"type":"Point"}
}