{
  "type": "Feature",
  "properties": {
    "iso:country":"BE",
    "sg:address":"Slijpstraat 13",
    "sg:city":"Houthulst",
    "sg:orig_category":"Eleveurs de bovins",
    "sg:phone":"+32 51 70 15 30",
    "sg:postcode":"8650",
    "sg:province":"West-Vlaanderen",
    "wof:name":"Oswald Jaecques",
    "wof:placetype":"venue"
},
  "geometry": {"coordinates":[2.9422860146,50.9902801514],"type":"Point"}
}