{
  "type": "Feature",
  "properties": {
    "addr:full":"Rue Paul Pastur 47 Charleroi Hainaut 6042",
    "addr:housenumber":"47",
    "addr:postcode":"6042",
    "addr:street":"Rue Paul Pastur;Hainaut",
    "iso:country":"BE",
    "sg:address":"Rue Paul Pastur 47",
    "sg:city":"Charleroi",
    "sg:orig_category":"Postkantoren Verzekeringsmakelaars and experts",
    "sg:phone":"+32 71 31 31 09",
    "sg:postcode":"6042",
    "sg:province":"Hainaut",
    "wof:name":"La Poste",
    "wof:placetype":"venue"
},
  "geometry": {"coordinates":[4.4183659554,50.4416275024],"type":"Point"}
}