{
  "type": "Feature",
  "properties": {
    "iso:country":"BE",
    "sg:address":"Cuylitshofstraat 47",
    "sg:city":"Kalmthout",
    "sg:classifiers":[
        {
            "category":"Communications",
            "subcategory":"Film & Video Production",
            "type":"Services"
        }
    ],
    "sg:phone":"+32 3 666 30 44",
    "sg:postcode":"2920",
    "sg:province":"Antwerpen",
    "sg:tags":[
        "producer",
        "realizators"
    ],
    "wof:name":"Kriteria-films",
    "wof:placetype":"venue"
},
  "geometry": {"coordinates":[4.4562411308,51.380859375],"type":"Point"}
}