{
  "type": "Feature",
  "properties": {
    "iso:country":"BE",
    "sg:address":"Van Pouckestraat 2",
    "sg:city":"Diksmuide",
    "sg:classifiers":[
        {
            "category":"Health Services",
            "subcategory":"Nursing And Care Facility",
            "type":"Services"
        }
    ],
    "sg:phone":"+32 51 51 16 30",
    "sg:postcode":"8600",
    "sg:province":"West-Vlaanderen",
    "sg:tags":[
        "home"
    ],
    "wof:name":"Sit Diksmuide-veurne",
    "wof:placetype":"venue"
},
  "geometry": {"coordinates":[2.8989260197,51.0669784546],"type":"Point"}
}