{
  "type": "Feature",
  "properties": {
    "iso:country":"BE",
    "sg:address":"Staatsbaan 187a",
    "sg:city":"Kortemark (handzame)",
    "sg:classifiers":[
        {
            "category":"Building & Trades",
            "subcategory":"Cleaning & Sanitation",
            "type":"Services"
        }
    ],
    "sg:phone":"+32 51 57 18 27",
    "sg:postcode":"8610",
    "sg:province":"West-Vlaanderen",
    "sg:tags":[
        "janitor"
    ],
    "wof:name":"Roney",
    "wof:placetype":"venue"
},
  "geometry": {"coordinates":[3.0162580013,51.0216026306],"type":"Point"}
}