{
  "type": "Feature",
  "properties": {
    "addr:full":"Grand Route 17 Neupr\u00c9 Li\u00e8ge 4122",
    "addr:postcode":"4122",
    "addr:street":"Grand Route 17",
    "iso:country":"BE",
    "sg:address":"Grand Route 17",
    "sg:city":"Neupr\u00c9",
    "sg:orig_category":"Services de Nettoyage and de D\u00e9sinfection. Travaux de finition and nettoyage de b\u00e2timents",
    "sg:phone":"+32 4 372 07 09",
    "sg:postcode":"4122",
    "sg:province":"Li\u00e8ge",
    "wof:name":"Fe. Eurosablage",
    "wof:placetype":"venue"
},
  "geometry": {"coordinates":[5.524725914,50.5453186035],"type":"Point"}
}