{
  "type": "Feature",
  "properties": {
    "iso:country":"BE",
    "sg:address":"Oudenaardsesteenweg 224",
    "sg:city":"Avelgem",
    "sg:classifiers":[
        {
            "category":"Insurance",
            "subcategory":"Insurance Agent",
            "type":"Services"
        }
    ],
    "sg:phone":"+32 56 64 82 86",
    "sg:postcode":"8580",
    "sg:province":"West-Vlaanderen",
    "sg:tags":[
        "-",
        "representative"
    ],
    "wof:name":"Vanrenterghem F",
    "wof:placetype":"venue"
},
  "geometry": {"coordinates":[3.4647541046,50.7832603455],"type":"Point"}
}