{
  "type": "Feature",
  "properties": {
    "addr:full":"Boulevard Saint-michel 6 Box 4 Bruxelles (etterbeek) Bruxelles-Capitale 1040",
    "addr:housenumber":"6;4",
    "addr:postcode":"1040",
    "addr:street":"Boulevard Saint-Michel;Box",
    "iso:country":"BE",
    "sg:address":"Boulevard Saint-michel 6 Box 4",
    "sg:city":"Bruxelles (etterbeek)",
    "sg:classifiers":[
        {
            "category":"Real Estate",
            "subcategory":"Surveying",
            "type":"Services"
        }
    ],
    "sg:phone":"+32 2 733 64 01",
    "sg:postcode":"1040",
    "sg:province":"Bruxelles-Capitale",
    "sg:tags":[
        "surveyor",
        "land"
    ],
    "wof:name":"Alexandre M",
    "wof:placetype":"venue"
},
  "geometry": {"coordinates":[4.4064941406,50.8343505859],"type":"Point"}
}