{
  "type": "Feature",
  "properties": {
    "addr:full":"Rijselstraat 69 Menen West-Vlaanderen 8930",
    "addr:housenumber":"69",
    "addr:postcode":"8930",
    "addr:street":"Rijselstraat",
    "iso:country":"BE",
    "sg:address":"Rijselstraat 69",
    "sg:city":"Menen",
    "sg:classifiers":[
        {
            "category":"Tea Room",
            "subcategory":"None",
            "type":"Food & Drink"
        }
    ],
    "sg:phone":"+32 56 51 25 40",
    "sg:postcode":"8930",
    "sg:province":"West-Vlaanderen",
    "wof:name":"Cari-mali",
    "wof:placetype":"venue"
},
  "geometry": {"coordinates":[3.122781992,50.7929458618],"type":"Point"}
}