{
  "type": "Feature",
  "properties": {
    "iso:country":"BE",
    "sg:address":"Meensesteenweg 129",
    "sg:city":"Roeselare",
    "sg:classifiers":[
        {
            "category":"Restaurant",
            "type":"Food & Drink"
        }
    ],
    "sg:phone":"+32 51 20 83 34",
    "sg:postcode":"8800",
    "sg:province":"West-Vlaanderen",
    "wof:name":"Sanderus",
    "wof:placetype":"venue"
},
  "geometry": {"coordinates":[3.121737957,50.9383468628],"type":"Point"}
}