{
  "type": "Feature",
  "properties": {
    "iso:country":"BE",
    "sg:address":"Rue Edouard Dinot 32",
    "sg:city":"Ciney",
    "sg:orig_category":"Pharmaciens",
    "sg:phone":"+32 83 23 12 11",
    "sg:postcode":"5590",
    "sg:province":"Namur",
    "wof:name":"Epece",
    "wof:placetype":"venue"
},
  "geometry": {"coordinates":[5.1003761292,50.2923812866],"type":"Point"}
}