{
  "type": "Feature",
  "properties": {
    "iso:country":"BE",
    "sg:address":"Kolveniersvest 21",
    "sg:city":"Lier",
    "sg:classifiers":[
        {
            "category":"Health Services",
            "subcategory":"Doctor",
            "type":"Services"
        }
    ],
    "sg:phone":"+32 3 480 81 40",
    "sg:postcode":"2500",
    "sg:province":"Antwerpen",
    "sg:tags":[
        "medicinephysicians",
        "surgeon"
    ],
    "wof:name":"Jans Paul",
    "wof:placetype":"venue"
},
  "geometry": {"coordinates":[4.5670251846,51.1322746277],"type":"Point"}
}