{
  "type": "Feature",
  "properties": {
    "iso:country":"BE",
    "sg:address":"Oude Gentweg 27",
    "sg:city":"Aalter",
    "sg:classifiers":[
        {
            "category":"Real Estate",
            "subcategory":"Architect",
            "type":"Services"
        }
    ],
    "sg:phone":"+32 9 375 01 97",
    "sg:postcode":"9880",
    "sg:province":"Oost-Vlaanderen",
    "wof:name":"Deceuninck Ph",
    "wof:placetype":"venue"
},
  "geometry": {"coordinates":[3.4774680138,51.0792732239],"type":"Point"}
}