{
  "type": "Feature",
  "properties": {
    "addr:full":"Tramstraat 9 Vosselaar Antwerpen 2350",
    "addr:housenumber":"9",
    "addr:postcode":"2350",
    "addr:street":"Tramstraat",
    "iso:country":"BE",
    "sg:address":"Tramstraat 9",
    "sg:city":"Vosselaar",
    "sg:classifiers":[
        {
            "category":"Bars & Pubs",
            "type":"Food & Drink"
        }
    ],
    "sg:phone":"+32 14 61 60 35",
    "sg:postcode":"2350",
    "sg:province":"Antwerpen",
    "wof:name":"Dreef (de)",
    "wof:placetype":"venue"
},
  "geometry": {"coordinates":[4.8880300522,51.313709259],"type":"Point"}
}