{
  "type": "Feature",
  "properties": {
    "iso:country":"BE",
    "sg:address":"Vuilenbosstraat 4",
    "sg:city":"Bierbeek",
    "sg:orig_category":"Fruitteelt",
    "sg:phone":"+32 16 46 38 41",
    "sg:postcode":"3360",
    "sg:province":"Vlaams-Brabant",
    "wof:name":"Dirk Janssens",
    "wof:placetype":"venue"
},
  "geometry": {"coordinates":[4.7712368965,50.8188896179],"type":"Point"}
}