{
  "type": "Feature",
  "properties": {
    "iso:country":"BE",
    "sg:address":"Oude Tiensebaan 62",
    "sg:city":"Bekkevoort",
    "sg:orig_category":"Fruitteelt",
    "sg:phone":"+32 16 63 37 15",
    "sg:postcode":"3460",
    "sg:province":"Vlaams-Brabant",
    "wof:name":"Robeyns Guido & Ivan",
    "wof:placetype":"venue"
},
  "geometry": {"coordinates":[4.9749708176,50.9031448364],"type":"Point"}
}