{
  "type": "Feature",
  "properties": {
    "addr:full":"Lodewijk De Raetlaan 36 Izegem West-Vlaanderen 8870",
    "addr:housenumber":"36",
    "addr:postcode":"8870",
    "addr:street":"Lodewijk De Raetlaan",
    "iso:country":"BE",
    "sg:address":"Lodewijk De Raetlaan 36",
    "sg:city":"Izegem",
    "sg:orig_category":"Installation de menuiserie en bois and plastique",
    "sg:phone":"+32 51 30 74 49",
    "sg:postcode":"8870",
    "sg:province":"West-Vlaanderen",
    "wof:name":"G.s.i.",
    "wof:placetype":"venue"
},
  "geometry": {"coordinates":[3.1955571175,50.9300384521],"type":"Point"}
}