{
  "type": "Feature",
  "properties": {
    "addr:full":"De Pannelaan 6 De Panne (adinkerke) West-Vlaanderen 8660",
    "addr:housenumber":"6",
    "addr:postcode":"8660",
    "addr:street":"De Pannelaan",
    "iso:country":"BE",
    "sg:address":"De Pannelaan 6",
    "sg:city":"De Panne (adinkerke)",
    "sg:classifiers":[
        {
            "category":"Health Services",
            "subcategory":"Dentist",
            "type":"Services"
        }
    ],
    "sg:phone":"+32 58 41 43 17",
    "sg:postcode":"8660",
    "sg:province":"West-Vlaanderen",
    "wof:name":"Dupuis Ga\u00ebtan",
    "wof:placetype":"venue"
},
  "geometry": {"coordinates":[2.6027719975,51.0778656006],"type":"Point"}
}