{
  "type": "Feature",
  "properties": {
    "addr:full":"Obroek 78 Retie Antwerpen 2470",
    "addr:housenumber":"78",
    "addr:postcode":"2470",
    "addr:street":"Obroek",
    "iso:country":"BE",
    "sg:address":"Obroek 78",
    "sg:city":"Retie",
    "sg:classifiers":[
        {
            "category":"Freight",
            "type":"Transportation"
        }
    ],
    "sg:phone":"+32 14 37 14 92",
    "sg:postcode":"2470",
    "sg:province":"Antwerpen",
    "sg:tags":[
        "-",
        "transport"
    ],
    "wof:name":"Transport Retie Bvba",
    "wof:placetype":"venue"
},
  "geometry": {"coordinates":[5.0792012215,51.282245636],"type":"Point"}
}