{
  "type": "Feature",
  "properties": {
    "iso:country":"BE",
    "sg:address":"Kerkstraat 115",
    "sg:city":"Blankenberge",
    "sg:orig_category":"Voedingsspeciaalzaken Zuivelproducten",
    "sg:phone":"+32 50 41 13 20",
    "sg:postcode":"8370",
    "sg:province":"West-Vlaanderen",
    "wof:name":"Digi Savarin",
    "wof:placetype":"venue"
},
  "geometry": {"coordinates":[3.1307730675,51.3136329651],"type":"Point"}
}