{
  "type": "Feature",
  "properties": {
    "iso:country":"BE",
    "sg:address":"Euphrosina Beernaertstraat 45",
    "sg:city":"Oostende",
    "sg:classifiers":[
        {
            "category":"Health Services",
            "subcategory":"Dentist",
            "type":"Services"
        }
    ],
    "sg:phone":"+32 59 70 83 65",
    "sg:postcode":"8400",
    "sg:province":"West-Vlaanderen",
    "wof:name":"Quataert G",
    "wof:placetype":"venue"
},
  "geometry": {"coordinates":[2.9120790958,51.2270507812],"type":"Point"}
}