{
  "type": "Feature",
  "properties": {
    "addr:full":"Rue De La Portelette 12 Morlanwelz Hainaut 7140",
    "addr:housenumber":"12",
    "addr:postcode":"7140",
    "addr:street":"Rue De La Portelette",
    "iso:country":"BE",
    "sg:address":"Rue De La Portelette 12",
    "sg:city":"Morlanwelz",
    "sg:orig_category":"M\u00e9decins and sp\u00e9cialistes",
    "sg:phone":"+32 64 44 24 60",
    "sg:postcode":"7140",
    "sg:province":"Hainaut",
    "wof:name":"Michel Henne",
    "wof:placetype":"venue"
},
  "geometry": {"coordinates":[4.239689827,50.4559555054],"type":"Point"}
}