{
  "type": "Feature",
  "properties": {
    "addr:full":"Avenue Du Prince R\u00c9gent 30 Waremme Li\u00e8ge 4300",
    "addr:housenumber":"30",
    "addr:postcode":"4300",
    "addr:street":"Avenue Du Prince Re\u0301Gent",
    "iso:country":"BE",
    "sg:address":"Avenue Du Prince R\u00c9gent 30",
    "sg:city":"Waremme",
    "sg:orig_category":"Algemeen secundair onderwijs Technisch and beroeps secundair onderwijs",
    "sg:phone":"+32 19 32 24 84",
    "sg:postcode":"4300",
    "sg:province":"Li\u00e8ge",
    "wof:name":"Institut St.louis",
    "wof:placetype":"venue"
},
  "geometry": {"coordinates":[5.2470078468,50.6900978088],"type":"Point"}
}