{
  "type": "Feature",
  "properties": {
    "addr:full":"Kortrijksestraat 2 Oostkamp West-Vlaanderen 8020",
    "addr:housenumber":"2",
    "addr:postcode":"8020",
    "addr:street":"Kortrijksestraat",
    "iso:country":"BE",
    "sg:address":"Kortrijksestraat 2",
    "sg:city":"Oostkamp",
    "sg:classifiers":[
        {
            "category":"Shopping",
            "subcategory":"Clothing, Apparel, & Fashions",
            "type":"Retail Goods"
        }
    ],
    "sg:phone":"+32 50 82 21 54",
    "sg:postcode":"8020",
    "sg:province":"West-Vlaanderen",
    "sg:tags":[
        "lady",
        "clothing",
        "-"
    ],
    "wof:name":"Decotex-d Couture",
    "wof:placetype":"venue"
},
  "geometry": {"coordinates":[3.2351651192,51.1543197632],"type":"Point"}
}