{
  "type": "Feature",
  "properties": {
    "iso:country":"BE",
    "sg:address":"Koning Albertstraat 13",
    "sg:city":"Ravels (weelde)",
    "sg:classifiers":[
        {
            "category":"Home & Garden",
            "subcategory":"Garden Supply",
            "type":"Retail Goods"
        }
    ],
    "sg:phone":"+32 14 65 52 49",
    "sg:postcode":"2381",
    "sg:province":"Antwerpen",
    "wof:name":"De Koster Zaadhandel Bvba",
    "wof:placetype":"venue"
},
  "geometry": {"coordinates":[5.0131449699,51.4125137329],"type":"Point"}
}