{
  "type": "Feature",
  "properties": {
    "iso:country":"BE",
    "sg:address":"Rue Du Ch\u00e2teau 13",
    "sg:city":"Estaimpuis",
    "sg:classifiers":[
        {
            "category":"Health Services",
            "subcategory":"Doctor",
            "type":"Services"
        }
    ],
    "sg:phone":"+32 56 48 73 35",
    "sg:postcode":"7730",
    "sg:province":"Hainaut",
    "sg:tags":[
        "medicinephysicians",
        "surgeon"
    ],
    "wof:name":"De Reuse Johan",
    "wof:placetype":"venue"
},
  "geometry": {"coordinates":[3.2666919231,50.7053184509],"type":"Point"}
}