{
  "type": "Feature",
  "properties": {
    "iso:country":"BE",
    "sg:address":"De Bergskens 7",
    "sg:city":"Vosselaar",
    "sg:orig_category":"Non-Classified Establishments",
    "sg:phone":"+32 14 61 22 88",
    "sg:postcode":"2350",
    "sg:province":"Antwerpen",
    "wof:name":"Vertongen",
    "wof:placetype":"venue"
},
  "geometry": {"coordinates":[4.8721041679,51.3107910156],"type":"Point"}
}