{
  "type": "Feature",
  "properties": {
    "iso:country":"BE",
    "sg:address":"Kerkstraat 89c",
    "sg:city":"Puurs (ruisbroek)",
    "sg:classifiers":[
        {
            "category":"Professional",
            "subcategory":"Art Services",
            "type":"Services"
        }
    ],
    "sg:phone":"+32 3 866 05 96",
    "sg:postcode":"2870",
    "sg:province":"Antwerpen",
    "sg:tags":[
        "graphic",
        "designer"
    ],
    "wof:name":"Grafisch Buro Verdonck",
    "wof:placetype":"venue"
},
  "geometry": {"coordinates":[4.3230838776,51.0826034546],"type":"Point"}
}