{
  "type": "Feature",
  "properties": {
    "iso:country":"BE",
    "sg:address":"Zonnebekestraat 73a",
    "sg:city":"Langemark-poelkapelle (langemark)",
    "sg:classifiers":[
        {
            "category":"Health Services",
            "subcategory":"Health Practitioner",
            "type":"Services"
        }
    ],
    "sg:phone":"+32 57 48 88 50",
    "sg:postcode":"8920",
    "sg:province":"West-Vlaanderen",
    "sg:tags":[
        "physiotherapist"
    ],
    "wof:name":"Verbrugghe Marc",
    "wof:placetype":"venue"
},
  "geometry": {"coordinates":[2.919770956,50.9132423401],"type":"Point"}
}