{
  "type": "Feature",
  "properties": {
    "addr:full":"Oude Gentbaan 61 Aalst Oost-Vlaanderen 9300",
    "addr:housenumber":"61",
    "addr:postcode":"9300",
    "addr:street":"Oude Gentbaan",
    "iso:country":"BE",
    "sg:address":"Oude Gentbaan 61",
    "sg:city":"Aalst",
    "sg:classifiers":[
        {
            "category":"Health Services",
            "subcategory":"Doctor",
            "type":"Services"
        }
    ],
    "sg:phone":"+32 53 41 01 92",
    "sg:postcode":"9300",
    "sg:province":"Oost-Vlaanderen",
    "sg:tags":[
        "psychotherapist",
        "psychoanalyst"
    ],
    "wof:name":"Verreycken M",
    "wof:placetype":"venue"
},
  "geometry": {"coordinates":[4.0134902,50.9413146973],"type":"Point"}
}