{
  "type": "Feature",
  "properties": {
    "addr:full":"Bierenberg 7 Sint-genesius-rode Vlaams-Brabant 1640",
    "addr:housenumber":"7",
    "addr:postcode":"1640",
    "addr:street":"Bierenberg",
    "iso:country":"BE",
    "sg:address":"Bierenberg 7",
    "sg:city":"Sint-genesius-rode",
    "sg:classifiers":[
        {
            "category":"Organizations",
            "subcategory":"Community Association",
            "type":"Services"
        }
    ],
    "sg:phone":"+32 2 358 48 19",
    "sg:postcode":"1640",
    "sg:province":"Vlaams-Brabant",
    "sg:tags":[
        "organisation"
    ],
    "wof:name":"Vnf Calopteryx",
    "wof:placetype":"venue"
},
  "geometry": {"coordinates":[4.372344017,50.7427444458],"type":"Point"}
}