{
  "type": "Feature",
  "properties": {
    "addr:full":"Heilige-geestbos 1 Tervuren (vossem) Vlaams-Brabant 3080",
    "addr:housenumber":"1",
    "addr:postcode":"3080",
    "addr:street":"Heilige-Geestbos",
    "iso:country":"BE",
    "sg:address":"Heilige-geestbos 1",
    "sg:city":"Tervuren (vossem)",
    "sg:classifiers":[
        {
            "category":"Professional",
            "subcategory":"Computer Services",
            "type":"Services"
        }
    ],
    "sg:phone":"+32 2 768 23 58",
    "sg:postcode":"3080",
    "sg:province":"Vlaams-Brabant",
    "sg:tags":[
        "webdesign",
        "-",
        "internet"
    ],
    "wof:name":"Vision Tales",
    "wof:placetype":"venue"
},
  "geometry": {"coordinates":[4.5566678047,50.8410339355],"type":"Point"}
}