{
  "type": "Feature",
  "properties": {
    "iso:country":"BE",
    "sg:address":"Dr\u00e8ve Micheline 44",
    "sg:city":"Genappe (bousval)",
    "sg:classifiers":[
        {
            "category":"Real Estate",
            "subcategory":"Architect",
            "type":"Services"
        }
    ],
    "sg:phone":"+32 10 61 68 59",
    "sg:postcode":"1470",
    "sg:province":"Brabant Wallon",
    "wof:name":"Lauwers T",
    "wof:placetype":"venue"
},
  "geometry": {"coordinates":[4.5369381905,50.6390457153],"type":"Point"}
}