{
  "type": "Feature",
  "properties": {
    "iso:country":"BE",
    "sg:address":"Rue Albert Asou 14",
    "sg:city":"Tournai",
    "sg:orig_category":"Imprimeries and copyshops",
    "sg:phone":"+32 69 23 25 92",
    "sg:postcode":"7500",
    "sg:province":"Hainaut",
    "wof:name":"Michel Dransart",
    "wof:placetype":"venue"
},
  "geometry": {"coordinates":[3.3954789639,50.6013183594],"type":"Point"}
}