{
  "type": "Feature",
  "properties": {
    "iso:country":"BE",
    "sg:address":"Avenue Mascaux 250",
    "sg:city":"Charleroi",
    "sg:orig_category":"V\u00eatements pour Dames. V\u00eatements pour Hommes. V\u00eatements pour b\u00e9b\u00e9s and enfants. Chaussures",
    "sg:phone":"+32 71 43 17 27",
    "sg:postcode":"6001",
    "sg:province":"Hainaut",
    "wof:name":"Shoe Discount",
    "wof:placetype":"venue"
},
  "geometry": {"coordinates":[4.439702034,50.3930130005],"type":"Point"}
}