{
  "type": "Feature",
  "properties": {
    "addr:full":"Tervuursevest 15 Leuven Vlaams-Brabant 3001",
    "addr:housenumber":"15",
    "addr:postcode":"3001",
    "addr:street":"Tervuursevest",
    "iso:country":"BE",
    "sg:address":"Tervuursevest 15",
    "sg:city":"Leuven",
    "sg:orig_category":"Instituts de beaut\u00e9. Parfumeries. Centres de relaxation and bien-\u00eatre",
    "sg:phone":"+32 16 23 21 87",
    "sg:postcode":"3001",
    "sg:province":"Vlaams-Brabant",
    "wof:name":"Instituut Kalomed",
    "wof:placetype":"venue"
},
  "geometry": {"coordinates":[4.6826100349,50.8765678406],"type":"Point"}
}