{
  "type": "Feature",
  "properties": {
    "iso:country":"BE",
    "sg:address":"Rue Des Ecoles 7",
    "sg:city":"Beloeil (bas\u00e8cles)",
    "sg:classifiers":[
        {
            "category":"Professional",
            "subcategory":"Engineering",
            "type":"Services"
        }
    ],
    "sg:phone":"+32 69 57 53 50",
    "sg:postcode":"7971",
    "sg:province":"Hainaut",
    "sg:tags":[
        "environmental",
        "technique",
        "-"
    ],
    "wof:name":"Incitec",
    "wof:placetype":"venue"
},
  "geometry": {"coordinates":[3.6487538815,50.5250778198],"type":"Point"}
}