{
  "type": "Feature",
  "properties": {
    "iso:country":"BE",
    "sg:address":"Statiestraat 22",
    "sg:city":"Lint",
    "sg:orig_category":"S\u00e9curit\u00e9 sociale",
    "sg:phone":"+32 3 455 81 42",
    "sg:postcode":"2547",
    "sg:province":"Antwerpen",
    "wof:name":"Christelijke Mutualiteit",
    "wof:placetype":"venue"
},
  "geometry": {"coordinates":[4.4972019196,51.1282615662],"type":"Point"}
}