{
  "type": "Feature",
  "properties": {
    "iso:country":"BE",
    "sg:address":"Zilversparstraat 14",
    "sg:city":"Roeselare",
    "sg:orig_category":"Dansscholen",
    "sg:phone":"+32 51 22 68 01",
    "sg:postcode":"8800",
    "sg:province":"West-Vlaanderen",
    "wof:name":"Stars Danssport Club",
    "wof:placetype":"venue"
},
  "geometry": {"coordinates":[3.129144907,50.9274253845],"type":"Point"}
}