{
  "type": "Feature",
  "properties": {
    "addr:full":"Hoogboomsteenweg 170 Kapellen Antwerpen 2950",
    "addr:housenumber":"170",
    "addr:postcode":"2950",
    "addr:street":"Hoogboomsteenweg",
    "iso:country":"BE",
    "sg:address":"Hoogboomsteenweg 170",
    "sg:city":"Kapellen",
    "sg:orig_category":"Centres de relaxation and bien-\u00eatre. Instituts de beaut\u00e9",
    "sg:phone":"+32 3 664 61 33",
    "sg:postcode":"2950",
    "sg:province":"Antwerpen",
    "wof:name":"Instituut Antigua",
    "wof:placetype":"venue"
},
  "geometry": {"coordinates":[4.4533290863,51.3129577637],"type":"Point"}
}