{
  "type": "Feature",
  "properties": {
    "iso:country":"BE",
    "sg:address":"Rue De La Justice 246",
    "sg:city":"Chatelet",
    "sg:classifiers":[
        {
            "category":"Insurance",
            "subcategory":"Insurance Agent",
            "type":"Services"
        }
    ],
    "sg:phone":"+32 71 39 10 59",
    "sg:postcode":"6200",
    "sg:province":"Hainaut",
    "sg:tags":[
        "verzekeringsmakelaars",
        "expert"
    ],
    "wof:name":"Ficheroulle",
    "wof:placetype":"venue"
},
  "geometry": {"coordinates":[4.5396251678,50.3927574158],"type":"Point"}
}