{
  "type": "Feature",
  "properties": {
    "iso:country":"BE",
    "sg:address":"Rue De La Motte 5",
    "sg:city":"Court-saint-etienne",
    "sg:orig_category":"M\u00e9decins and sp\u00e9cialistes",
    "sg:phone":"+32 10 61 20 71",
    "sg:postcode":"1490",
    "sg:province":"Brabant Wallon",
    "wof:name":"Anne Lecloux",
    "wof:placetype":"venue"
},
  "geometry": {"coordinates":[4.5361299515,50.651058197],"type":"Point"}
}