{
  "type": "Feature",
  "properties": {
    "addr:full":"Waversesteenweg 43 Bierbeek (honsem) Vlaams-Brabant 3360",
    "addr:housenumber":"43",
    "addr:postcode":"3360",
    "addr:street":"Waversesteenweg",
    "iso:country":"BE",
    "sg:address":"Waversesteenweg 43",
    "sg:city":"Bierbeek (honsem)",
    "sg:classifiers":[
        {
            "category":"Military Area",
            "subcategory":"Air Force Base",
            "type":"Public Place"
        }
    ],
    "sg:phone":"+32 16 73 56 48",
    "sg:postcode":"3360",
    "sg:province":"Vlaams-Brabant",
    "sg:tags":[
        "wall",
        "painting"
    ],
    "wof:name":"Fesco",
    "wof:placetype":"venue"
},
  "geometry": {"coordinates":[4.7864518166,50.8096046448],"type":"Point"}
}