{
  "type": "Feature",
  "properties": {
    "addr:full":"Boulevard Maurice Lemonnier 99 Bruxelles Bruxelles-Capitale 1000",
    "addr:housenumber":"99",
    "addr:postcode":"1000",
    "addr:street":"Boulevard Maurice Lemonnier",
    "iso:country":"BE",
    "sg:address":"Boulevard Maurice Lemonnier 99",
    "sg:city":"Bruxelles",
    "sg:classifiers":[
        {
            "category":"Utilities",
            "subcategory":"Mobile Phone",
            "type":"Services"
        }
    ],
    "sg:phone":"+32 2 502 60 69",
    "sg:postcode":"1000",
    "sg:province":"Bruxelles-Capitale",
    "sg:tags":[
        "access",
        "gsm",
        "-",
        "apparatus"
    ],
    "wof:name":"Midi Com Services Sprl",
    "wof:placetype":"venue"
},
  "geometry": {"coordinates":[4.3439278603,50.8430328369],"type":"Point"}
}