{
  "type": "Feature",
  "properties": {
    "addr:full":"Avenue Brugmann 265 Box 3 Bruxelles (uccle) Bruxelles-Capitale 1180",
    "addr:housenumber":"265;3",
    "addr:postcode":"1180",
    "addr:street":"Avenue Brugmann;Box",
    "iso:country":"BE",
    "sg:address":"Avenue Brugmann 265 Box 3",
    "sg:city":"Bruxelles (uccle)",
    "sg:classifiers":[
        {
            "category":"Communications",
            "subcategory":"Film & Video Production",
            "type":"Services"
        }
    ],
    "sg:phone":"+32 2 345 94 10",
    "sg:postcode":"1180",
    "sg:province":"Bruxelles-Capitale",
    "sg:tags":[
        "sound",
        "recording",
        "studio"
    ],
    "wof:name":"Mayard J",
    "wof:placetype":"venue"
},
  "geometry": {"coordinates":[4.3472371101,50.8128814697],"type":"Point"}
}