{
  "type": "Feature",
  "properties": {
    "iso:country":"BE",
    "sg:address":"Rue De Villers 9",
    "sg:city":"Braives (avennes)",
    "sg:classifiers":[
        {
            "category":"Building & Trades",
            "subcategory":"Cleaning & Sanitation",
            "type":"Services"
        }
    ],
    "sg:phone":"+32 19 69 79 22",
    "sg:postcode":"4260",
    "sg:province":"Li\u00e8ge",
    "sg:tags":[
        "cleaner",
        "window"
    ],
    "wof:name":"Clean-house Sprl",
    "wof:placetype":"venue"
},
  "geometry": {"coordinates":[5.10983181,50.6312599182],"type":"Point"}
}