{
  "type": "Feature",
  "properties": {
    "iso:country":"BE",
    "sg:address":"Rue Fourneau St.-michel 40",
    "sg:city":"Saint-hubert",
    "sg:orig_category":"Traitements param\u00e9dicaux",
    "sg:phone":"+32 84 36 62 12",
    "sg:postcode":"6870",
    "sg:province":"Luxembourg",
    "wof:name":"Pecheur",
    "wof:placetype":"venue"
},
  "geometry": {"coordinates":[5.3726649284,50.0285377502],"type":"Point"}
}