{
  "type": "Feature",
  "properties": {
    "iso:country":"BE",
    "sg:address":"Chauss\u00c9e De Douai 31bb",
    "sg:city":"Tournai",
    "sg:orig_category":"Metaalafval, schrootrecyclage and sloperijen Voertuigen",
    "sg:phone":"+32 69 64 09 24",
    "sg:postcode":"7500",
    "sg:province":"Hainaut",
    "wof:name":"Auto Pi\u00c8ces Plus",
    "wof:placetype":"venue"
},
  "geometry": {"coordinates":[3.380384922,50.6001625061],"type":"Point"}
}