{
  "type": "Feature",
  "properties": {
    "iso:country":"BE",
    "sg:address":"Doornpark 25",
    "sg:city":"Beveren (beveren-waas)",
    "sg:orig_category":"Non-Classified Establishments",
    "sg:phone":"+32 3 775 96 80",
    "sg:postcode":"9120",
    "sg:province":"Oost-Vlaanderen",
    "wof:name":"Van Meirvenne Trading Nv",
    "wof:placetype":"venue"
},
  "geometry": {"coordinates":[4.2174730301,51.195728302],"type":"Point"}
}