{
  "type": "Feature",
  "properties": {
    "addr:full":"Waterstraat 66 Bilzen Limburg 3740",
    "addr:housenumber":"66",
    "addr:postcode":"3740",
    "addr:street":"Waterstraat",
    "iso:country":"BE",
    "sg:address":"Waterstraat 66",
    "sg:city":"Bilzen",
    "sg:orig_category":"Installation \u00e9lectrique r\u00e9sidentielle",
    "sg:phone":"+32 89 41 19 57",
    "sg:postcode":"3740",
    "sg:province":"Limburg",
    "wof:name":"Jean Broux",
    "wof:placetype":"venue"
},
  "geometry": {"coordinates":[5.5249829292,50.8971862793],"type":"Point"}
}