{
  "type": "Feature",
  "properties": {
    "iso:country":"BE",
    "sg:address":"Walstraat 19",
    "sg:city":"Maaseik",
    "sg:orig_category":"Paramedische behandelingen",
    "sg:phone":"+32 89 56 22 54",
    "sg:postcode":"3680",
    "sg:province":"Limburg",
    "wof:name":"Wit-gele Kruis",
    "wof:placetype":"venue"
},
  "geometry": {"coordinates":[5.7908902168,51.0936317444],"type":"Point"}
}