{
  "type": "Feature",
  "properties": {
    "iso:country":"BE",
    "sg:address":"Rue Du Broek 12b",
    "sg:city":"Anderlecht",
    "sg:orig_category":"Sportclubs",
    "sg:phone":"+32 2 524 11 08",
    "sg:postcode":"1070",
    "sg:province":"Bruxelles-Capitale",
    "wof:name":"Les Pecheurs De L'orphelinat",
    "wof:placetype":"venue"
},
  "geometry": {"coordinates":[4.3047652245,50.8381538391],"type":"Point"}
}