{
  "type": "Feature",
  "properties": {
    "addr:full":"Rue Du Midi 40 Brussel/bruxelles Bruxelles-Capitale 1000",
    "addr:housenumber":"40",
    "addr:postcode":"1000",
    "addr:street":"Rue Du Midi;/",
    "iso:country":"BE",
    "sg:address":"Rue Du Midi 40",
    "sg:city":"Brussel/bruxelles",
    "sg:orig_category":"V\u00eatements pour b\u00e9b\u00e9s and enfants. Articles pour b\u00e9b\u00e9s",
    "sg:phone":"+32 2 513 05 28",
    "sg:postcode":"1000",
    "sg:province":"Bruxelles-Capitale",
    "wof:name":"Maison Peau D'z\u00c8bre",
    "wof:placetype":"venue"
},
  "geometry": {"coordinates":[4.350479126,50.8466682434],"type":"Point"}
}