{
  "type": "Feature",
  "properties": {
    "iso:country":"BE",
    "sg:address":"Rue Bouch\u00c8re 16",
    "sg:city":"Chimay",
    "sg:orig_category":"Artsen and specialisten",
    "sg:phone":"+32 60 21 40 64",
    "sg:postcode":"6460",
    "sg:province":"Hainaut",
    "wof:name":"Jean Brisbois",
    "wof:placetype":"venue"
},
  "geometry": {"coordinates":[4.3106827736,50.0494232178],"type":"Point"}
}