{
  "type": "Feature",
  "properties": {
    "addr:full":"Veerstraat 1-3 Dendermonde Oost-Vlaanderen 9200",
    "addr:housenumber":"1-3",
    "addr:postcode":"9200",
    "addr:street":"Veerstraat;Oost-Vlaanderen",
    "iso:country":"BE",
    "sg:address":"Veerstraat 1-3",
    "sg:city":"Dendermonde",
    "sg:orig_category":"Alimentation sp\u00e9cialis\u00e9e. Cr\u00e9meries",
    "sg:phone":"+32 52 22 05 30",
    "sg:postcode":"9200",
    "sg:province":"Oost-Vlaanderen",
    "wof:name":"Finesse",
    "wof:placetype":"venue"
},
  "geometry": {"coordinates":[4.101995945,51.032371521],"type":"Point"}
}