{
  "type": "Feature",
  "properties": {
    "addr:full":"Rue Joseph Wauters 26 Fleurus Hainaut 6224",
    "addr:housenumber":"26",
    "addr:postcode":"6224",
    "addr:street":"Rue Joseph Wauters",
    "iso:country":"BE",
    "sg:address":"Rue Joseph Wauters 26",
    "sg:city":"Fleurus",
    "sg:classifiers":[
        {
            "category":"Insurance",
            "subcategory":"Life Insurance",
            "type":"Services"
        }
    ],
    "sg:phone":"+32 71 81 22 76",
    "sg:postcode":"6224",
    "sg:province":"Hainaut",
    "sg:tags":[
        "assurance"
    ],
    "wof:name":"Bureau Feron",
    "wof:placetype":"venue"
},
  "geometry": {"coordinates":[4.5846290588,50.4644546509],"type":"Point"}
}