{
  "type": "Feature",
  "properties": {
    "addr:full":"Pikkeleerstraat 14 Herk-de-stad Limburg 3540",
    "addr:housenumber":"14",
    "addr:postcode":"3540",
    "addr:street":"Pikkeleerstraat",
    "iso:country":"BE",
    "sg:address":"Pikkeleerstraat 14",
    "sg:city":"Herk-de-stad",
    "sg:classifiers":[
        {
            "category":"Landmark",
            "subcategory":"Tourist Attraction",
            "type":"Public Place"
        }
    ],
    "sg:phone":"+32 13 55 38 11",
    "sg:postcode":"3540",
    "sg:province":"Limburg",
    "sg:tags":[
        "-",
        "tourism",
        "interest",
        "sight"
    ],
    "wof:name":"Domein Olmenhof",
    "wof:placetype":"venue"
},
  "geometry": {"coordinates":[5.1661472321,50.9366455078],"type":"Point"}
}