{
  "type": "Feature",
  "properties": {
    "iso:country":"BE",
    "sg:address":"Rue Haut Cornillon 1",
    "sg:city":"Juprelle",
    "sg:orig_category":"Artsen and specialisten",
    "sg:phone":"+32 4 246 46 62",
    "sg:postcode":"4450",
    "sg:province":"Li\u00e8ge",
    "wof:name":"Eug\u00c8ne Dehalleux",
    "wof:placetype":"venue"
},
  "geometry": {"coordinates":[5.5250411034,50.6932296753],"type":"Point"}
}