{
  "type": "Feature",
  "properties": {
    "addr:full":"De Brulen 6 Arendonk Antwerpen 2370",
    "addr:housenumber":"6",
    "addr:postcode":"2370",
    "addr:street":"De Brulen",
    "iso:country":"BE",
    "sg:address":"De Brulen 6",
    "sg:city":"Arendonk",
    "sg:classifiers":[
        {
            "category":"Communications",
            "type":"Services"
        }
    ],
    "sg:phone":"+32 14 67 72 21",
    "sg:postcode":"2370",
    "sg:province":"Antwerpen",
    "sg:tags":[
        "translator"
    ],
    "wof:name":"Bouw U.",
    "wof:placetype":"venue"
},
  "geometry": {"coordinates":[5.1008558273,51.3381881714],"type":"Point"}
}