{
  "type": "Feature",
  "properties": {
    "addr:full":"Avenue Du Roi Chevalier 50 Bruxelles (woluwe-saint-lambert) Bruxelles-Capitale 1200",
    "addr:housenumber":"50",
    "addr:postcode":"1200",
    "addr:street":"Avenue Du Roi Chevalier",
    "iso:country":"BE",
    "sg:address":"Avenue Du Roi Chevalier 50",
    "sg:city":"Bruxelles (woluwe-saint-lambert)",
    "sg:classifiers":[
        {
            "category":"Professional",
            "subcategory":"Art Services",
            "type":"Services"
        }
    ],
    "sg:phone":"+32 2 772 00 74",
    "sg:postcode":"1200",
    "sg:province":"Bruxelles-Capitale",
    "sg:tags":[
        "technical",
        "photographer",
        "industrial",
        "-"
    ],
    "wof:name":"Bogaert Cl",
    "wof:placetype":"venue"
},
  "geometry": {"coordinates":[4.4177761078,50.844783783],"type":"Point"}
}