{
  "type": "Feature",
  "properties": {
    "addr:full":"Kasteelstraat 40 Zemst Vlaams-Brabant 1982",
    "addr:housenumber":"40",
    "addr:postcode":"1982",
    "addr:street":"Kasteelstraat;Vlaams-Brabant",
    "iso:country":"BE",
    "sg:address":"Kasteelstraat 40",
    "sg:city":"Zemst",
    "sg:orig_category":"Travaux de finition and nettoyage de b\u00e2timents",
    "sg:phone":"+32 15 61 29 09",
    "sg:postcode":"1982",
    "sg:province":"Vlaams-Brabant",
    "wof:name":"Karel Gotemans",
    "wof:placetype":"venue"
},
  "geometry": {"coordinates":[4.5008640289,50.96824646],"type":"Point"}
}