{
  "type": "Feature",
  "properties": {
    "addr:full":"Tervuursesteenweg 319 Leuven (heverlee) Vlaams-Brabant 3001",
    "addr:housenumber":"319",
    "addr:postcode":"3001",
    "addr:street":"Tervuursesteenweg",
    "iso:country":"BE",
    "sg:address":"Tervuursesteenweg 319",
    "sg:city":"Leuven (heverlee)",
    "sg:classifiers":[
        {
            "category":"Professional",
            "subcategory":"Advertising",
            "type":"Services"
        }
    ],
    "sg:phone":"+32 16 22 47 26",
    "sg:postcode":"3001",
    "sg:province":"Vlaams-Brabant",
    "sg:tags":[
        "painter"
    ],
    "wof:name":"Huybrechts Reklame",
    "wof:placetype":"venue"
},
  "geometry": {"coordinates":[4.6707057953,50.874004364],"type":"Point"}
}