{
  "type": "Feature",
  "properties": {
    "addr:full":"Diestersteenweg 73 Nieuwerkerken Limburg 3850",
    "addr:housenumber":"73",
    "addr:postcode":"3850",
    "addr:street":"Diestersteenweg",
    "iso:country":"BE",
    "sg:address":"Diestersteenweg 73",
    "sg:city":"Nieuwerkerken",
    "sg:classifiers":[
        {
            "category":"Structure",
            "subcategory":"Office Building",
            "type":"Public Place"
        }
    ],
    "sg:phone":"+32 11 68 48 29",
    "sg:postcode":"3850",
    "sg:province":"Limburg",
    "sg:tags":[
        "-",
        "type",
        "door",
        "sliding",
        "overhead"
    ],
    "wof:name":"Poortservice Marcel",
    "wof:placetype":"venue"
},
  "geometry": {"coordinates":[5.1884078979,50.8615379333],"type":"Point"}
}