{
  "type": "Feature",
  "properties": {
    "iso:country":"BE",
    "sg:address":"Av Wolfers 21",
    "sg:city":"La Hulpe",
    "sg:orig_category":"Elektrische installaties voor woningen",
    "sg:phone":"+32 2 653 45 22",
    "sg:postcode":"1310",
    "sg:province":"Brabant Wallon",
    "wof:name":"Taymans-multi-elec",
    "wof:placetype":"venue"
},
  "geometry": {"coordinates":[4.5003461838,50.7382164001],"type":"Point"}
}