{
  "type": "Feature",
  "properties": {
    "iso:country":"BE",
    "sg:address":"Burgemeester Pyckestraat 23ba",
    "sg:city":"Kortrijk",
    "sg:orig_category":"Artsen and specialisten",
    "sg:phone":"+32 56 20 50 76",
    "sg:postcode":"8500",
    "sg:province":"West-Vlaanderen",
    "wof:name":"B. Crevits",
    "wof:placetype":"venue"
},
  "geometry": {"coordinates":[3.2672250271,50.8206977844],"type":"Point"}
}