{
  "type": "Feature",
  "properties": {
    "addr:full":"Rue De Li\u00c8ge 29 Somme-leuze Namur 5377",
    "addr:housenumber":"29",
    "addr:postcode":"5377",
    "addr:street":"Rue De Lie\u0300Ge",
    "iso:country":"BE",
    "sg:address":"Rue De Li\u00c8ge 29",
    "sg:city":"Somme-leuze",
    "sg:orig_category":"Banken and kredietinstellingen",
    "sg:phone":"+32 86 32 26 11",
    "sg:postcode":"5377",
    "sg:province":"Namur",
    "wof:name":"Dexia",
    "wof:placetype":"venue"
},
  "geometry": {"coordinates":[5.3670620918,50.3372688293],"type":"Point"}
}