{
  "type": "Feature",
  "properties": {
    "iso:country":"BE",
    "sg:address":"Chauss\u00c9e D'ath 242",
    "sg:city":"Edingen/enghien",
    "sg:orig_category":"Agences de mannequins and h\u00f4tesses",
    "sg:phone":"+32 2 397 02 39",
    "sg:postcode":"7850",
    "sg:province":"Hainaut",
    "wof:name":"Baps",
    "wof:placetype":"venue"
},
  "geometry": {"coordinates":[3.9902288914,50.6814041138],"type":"Point"}
}