{
  "type": "Feature",
  "properties": {
    "addr:full":"Montoyerstraat 18bb Brussel/bruxelles Bruxelles-Capitale 1000",
    "addr:housenumber":"18bb",
    "addr:postcode":"1000",
    "addr:street":"Montoyerstraat;/",
    "iso:country":"BE",
    "sg:address":"Montoyerstraat 18bb",
    "sg:city":"Brussel/bruxelles",
    "sg:orig_category":"Marktonderzoekbureaus",
    "sg:phone":"+32 2 280 00 74",
    "sg:postcode":"1000",
    "sg:province":"Bruxelles-Capitale",
    "wof:name":"Bur. Direct Soc. Commun.",
    "wof:placetype":"venue"
},
  "geometry": {"coordinates":[4.3696198463,50.8413848877],"type":"Point"}
}