{
  "type": "Feature",
  "properties": {
    "addr:full":"Limburgstraat 37 Verviers (groot) Li\u00e8ge 4800",
    "addr:housenumber":"37",
    "addr:postcode":"4800",
    "addr:street":"Limburgstraat;Groot Lie\u0300Ge",
    "iso:country":"BE",
    "sg:address":"Limburgstraat 37",
    "sg:city":"Verviers (groot)",
    "sg:orig_category":"Werk and personeelsselectie",
    "sg:phone":"+32 87 32 54 55",
    "sg:postcode":"4800",
    "sg:province":"Li\u00e8ge",
    "wof:name":"Centre Vervietois De Formation Permanente",
    "wof:placetype":"venue"
},
  "geometry": {"coordinates":[5.8761582375,50.5962982178],"type":"Point"}
}