{
  "type": "Feature",
  "properties": {
    "addr:full":"Rue De Burhaimont 128 Bertrix Luxembourg 6880",
    "addr:housenumber":"128",
    "addr:postcode":"6880",
    "addr:street":"Rue De Burhaimont",
    "iso:country":"BE",
    "sg:address":"Rue De Burhaimont 128",
    "sg:city":"Bertrix",
    "sg:orig_category":"H\u00f4tels",
    "sg:phone":"+32 61 41 14 22",
    "sg:postcode":"6880",
    "sg:province":"Luxembourg",
    "wof:name":"Petite Chatelaine",
    "wof:placetype":"venue"
},
  "geometry": {"coordinates":[5.254971981,49.8623733521],"type":"Point"}
}