{
  "type": "Feature",
  "properties": {
    "iso:country":"BE",
    "sg:address":"Statielei 13",
    "sg:city":"Mortsel",
    "sg:orig_category":"Peinture. Rev\u00eatements pour sols and murs. Textiles. Eclairage et \u00e9quipements du foyer. Rev\u00eatements d",
    "sg:phone":"+32 3 440 33 87",
    "sg:postcode":"2640",
    "sg:province":"Antwerpen",
    "wof:name":"Nuance",
    "wof:placetype":"venue"
},
  "geometry": {"coordinates":[4.4501399994,51.1707992554],"type":"Point"}
}