{
  "type": "Feature",
  "properties": {
    "iso:country":"BE",
    "sg:address":"Rue Sart-dames-avelines 10",
    "sg:city":"Les Bons Villers",
    "sg:orig_category":"Artsen and specialisten",
    "sg:phone":"+32 71 85 29 30",
    "sg:postcode":"6210",
    "sg:province":"Hainaut",
    "wof:name":"Philippe Watillon",
    "wof:placetype":"venue"
},
  "geometry": {"coordinates":[4.4511561394,50.5378227234],"type":"Point"}
}