{
  "type": "Feature",
  "properties": {
    "addr:full":"Clos Saint-martin 31 Somme-leuze (hogne) Namur 5377",
    "addr:housenumber":"31",
    "addr:postcode":"5377",
    "addr:street":"Clos Saint-Martin;Hogne",
    "iso:country":"BE",
    "sg:address":"Clos Saint-martin 31",
    "sg:city":"Somme-leuze (hogne)",
    "sg:classifiers":[
        {
            "category":"Health Services",
            "subcategory":"Doctor",
            "type":"Services"
        }
    ],
    "sg:phone":"+32 84 31 46 11",
    "sg:postcode":"5377",
    "sg:province":"Namur",
    "sg:tags":[
        "medicinephysicians",
        "surgeon"
    ],
    "wof:name":"Boutefeu Jean-marie",
    "wof:placetype":"venue"
},
  "geometry": {"coordinates":[5.2989068031,50.2434272766],"type":"Point"}
}