{
  "type": "Feature",
  "properties": {
    "addr:full":"Osseghemstraat 158bb Sint-jans-molenbeek/molenbeek-saint-jean Bruxelles-Capitale 1080",
    "addr:housenumber":"158bb",
    "addr:postcode":"1080",
    "addr:street":"Osseghemstraat",
    "iso:country":"BE",
    "sg:address":"Osseghemstraat 158bb",
    "sg:city":"Sint-jans-molenbeek/molenbeek-saint-jean",
    "sg:orig_category":"Dranken",
    "sg:phone":"+32 2 410 18 93",
    "sg:postcode":"1080",
    "sg:province":"Bruxelles-Capitale",
    "wof:name":"Italbere",
    "wof:placetype":"venue"
},
  "geometry": {"coordinates":[4.3142781258,50.8530654907],"type":"Point"}
}