{
  "type": "Feature",
  "properties": {
    "addr:full":"Platte Lostraat 65 Leuven (kessel-lo) Vlaams-Brabant 3010",
    "addr:housenumber":"65",
    "addr:postcode":"3010",
    "addr:street":"Platte Lostraat",
    "iso:country":"BE",
    "sg:address":"Platte Lostraat 65",
    "sg:city":"Leuven (kessel-lo)",
    "sg:classifiers":[
        {
            "category":"Health Services",
            "subcategory":"Health Practitioner",
            "type":"Services"
        }
    ],
    "sg:phone":"+32 16 26 00 12",
    "sg:postcode":"3010",
    "sg:province":"Vlaams-Brabant",
    "sg:tags":[
        "alternative",
        "therapy",
        "treatment"
    ],
    "wof:name":"Gilis V",
    "wof:placetype":"venue"
},
  "geometry": {"coordinates":[4.742205143,50.8782424927],"type":"Point"}
}