{
  "type": "Feature",
  "properties": {
    "addr:full":"Rue De Belle-vue 24 Virton (ethe) Luxembourg 6760",
    "addr:housenumber":"24",
    "addr:postcode":"6760",
    "addr:street":"Rue De Belle-Vue",
    "iso:country":"BE",
    "sg:address":"Rue De Belle-vue 24",
    "sg:city":"Virton (ethe)",
    "sg:classifiers":[
        {
            "category":"Building & Trades",
            "subcategory":"Construction",
            "type":"Services"
        }
    ],
    "sg:phone":"+32 496 50 74 72",
    "sg:postcode":"6760",
    "sg:province":"Luxembourg",
    "sg:tags":[
        "carpenter"
    ],
    "wof:name":"Magnette J",
    "wof:placetype":"venue"
},
  "geometry": {"coordinates":[5.5700798035,49.5853500366],"type":"Point"}
}