{
  "type": "Feature",
  "properties": {
    "addr:full":"Groenstraat 120 Herent (veltem-beisem) Vlaams-Brabant 3020",
    "addr:housenumber":"120",
    "addr:postcode":"3020",
    "addr:street":"Groenstraat",
    "iso:country":"BE",
    "sg:address":"Groenstraat 120",
    "sg:city":"Herent (veltem-beisem)",
    "sg:classifiers":[
        {
            "category":"Building & Trades",
            "subcategory":"Landscaping Services",
            "type":"Services"
        }
    ],
    "sg:phone":"+32 16 48 97 89",
    "sg:postcode":"3020",
    "sg:province":"Vlaams-Brabant",
    "sg:tags":[
        "gardening",
        "garden",
        "maintenance"
    ],
    "wof:name":"Evba Het Groenparadijs",
    "wof:placetype":"venue"
},
  "geometry": {"coordinates":[4.6599397659,50.9282112122],"type":"Point"}
}