{
  "type": "Feature",
  "properties": {
    "iso:country":"BE",
    "sg:address":"Menenstraat 64",
    "sg:city":"Moorslede",
    "sg:orig_category":"Activit\u00e9s d\u00b4action sociale sans h\u00e9bergement",
    "sg:phone":"+32 56 50 13 19",
    "sg:postcode":"8890",
    "sg:province":"West-Vlaanderen",
    "wof:name":"Rode Kruis Moorslede",
    "wof:placetype":"venue"
},
  "geometry": {"coordinates":[3.1011641026,50.8457221985],"type":"Point"}
}