{
  "type": "Feature",
  "properties": {
    "addr:full":"Chauss\u00c9e De Bruxelles 440b42 Tournai Hainaut 7500",
    "addr:housenumber":"440b42",
    "addr:postcode":"7500",
    "addr:street":"Chausse\u0301E De Bruxelles",
    "iso:country":"BE",
    "sg:address":"Chauss\u00c9e De Bruxelles 440b42",
    "sg:city":"Tournai",
    "sg:orig_category":"Autokeuringen Rijscholen",
    "sg:phone":"+32 69 22 56 35",
    "sg:postcode":"7500",
    "sg:province":"Hainaut",
    "wof:name":"Inspection Automobile",
    "wof:placetype":"venue"
},
  "geometry": {"coordinates":[3.4388380051,50.6009788513],"type":"Point"}
}