{
  "type": "Feature",
  "properties": {
    "addr:full":"Waterstraat 30a Merelbeke Oost-Vlaanderen 9820",
    "addr:housenumber":"30a",
    "addr:postcode":"9820",
    "addr:street":"Waterstraat",
    "iso:country":"BE",
    "sg:address":"Waterstraat 30a",
    "sg:city":"Merelbeke",
    "sg:classifiers":[
        {
            "category":"Retail",
            "subcategory":"Auto Repair",
            "type":"Services"
        }
    ],
    "sg:phone":"+32 9 230 78 18",
    "sg:postcode":"9820",
    "sg:province":"Oost-Vlaanderen",
    "sg:tags":[
        "breakdown",
        "automobile",
        "-",
        "recovery"
    ],
    "wof:name":"Van Den Broecke W",
    "wof:placetype":"venue"
},
  "geometry": {"coordinates":[3.7489690781,51.0018234253],"type":"Point"}
}