{
  "type": "Feature",
  "properties": {
    "iso:country":"BE",
    "sg:address":"Livingstonelaan 6",
    "sg:city":"Brussels",
    "sg:classifiers":[
        {
            "category":"Banks & Credit Unions",
            "subcategory":"Bank",
            "type":"Services"
        }
    ],
    "sg:postcode":"1040",
    "sg:province":"Bruxelles-Capitale",
    "wof:name":"Beran Nv",
    "wof:placetype":"venue"
},
  "geometry": {"coordinates":[4.4174098969,51.1974411011],"type":"Point"}
}