{
  "type": "Feature",
  "properties": {
    "iso:country":"BE",
    "sg:address":"Nerenhoek 50",
    "sg:city":"Lochristi",
    "sg:orig_category":"Rundveehouders Varkenskwekers",
    "sg:phone":"+32 9 355 92 82",
    "sg:postcode":"9080",
    "sg:province":"Oost-Vlaanderen",
    "wof:name":"Marleen De Ronne",
    "wof:placetype":"venue"
},
  "geometry": {"coordinates":[3.8435499668,51.1303901672],"type":"Point"}
}