{
  "type": "Feature",
  "properties": {
    "iso:country":"BE",
    "sg:address":"Bois Du Foyau 104",
    "sg:city":"Braine-le-ch\u00e2teau",
    "sg:classifiers":[
        {
            "category":"Professional",
            "subcategory":"Management & Consulting",
            "type":"Services"
        }
    ],
    "sg:phone":"+32 2 366 39 99",
    "sg:postcode":"1440",
    "sg:province":"Brabant Wallon",
    "sg:tags":[
        "-",
        "processing",
        "data",
        "consultant"
    ],
    "wof:name":"N-clusion Consulting Sprl",
    "wof:placetype":"venue"
},
  "geometry": {"coordinates":[4.2822852135,50.6731300354],"type":"Point"}
}