{
  "type": "Feature",
  "properties": {
    "addr:full":"Avenue Brillat Savarin 49 Elsene (brussel) Bruxelles-Capitale 1050",
    "addr:housenumber":"49",
    "addr:postcode":"1050",
    "addr:street":"Avenue Brillat Savarin",
    "iso:country":"BE",
    "sg:address":"Avenue Brillat Savarin 49",
    "sg:city":"Elsene (brussel)",
    "sg:orig_category":"Avocats and conseillers juridiques",
    "sg:phone":"+32 2 626 19 00",
    "sg:postcode":"1050",
    "sg:province":"Bruxelles-Capitale",
    "wof:name":"Dennis Oswell",
    "wof:placetype":"venue"
},
  "geometry": {"coordinates":[4.3854060173,50.8165168762],"type":"Point"}
}