{
  "type": "Feature",
  "properties": {
    "addr:full":"Bloemsehoeve 80 Aarschot Vlaams-Brabant 3200",
    "addr:housenumber":"80",
    "addr:postcode":"3200",
    "addr:street":"Bloemsehoeve",
    "iso:country":"BE",
    "sg:address":"Bloemsehoeve 80",
    "sg:city":"Aarschot",
    "sg:orig_category":"Kapsalons",
    "sg:phone":"+32 16 56 16 71",
    "sg:postcode":"3200",
    "sg:province":"Vlaams-Brabant",
    "wof:name":"Coiffure Anni",
    "wof:placetype":"venue"
},
  "geometry": {"coordinates":[4.8213720322,51.0012321472],"type":"Point"}
}