{
  "type": "Feature",
  "properties": {
    "addr:full":"Robert Klingstraat 17a Wervik West-Vlaanderen 8940",
    "addr:housenumber":"17a",
    "addr:postcode":"8940",
    "addr:street":"Robert Klingstraat",
    "iso:country":"BE",
    "sg:address":"Robert Klingstraat 17a",
    "sg:city":"Wervik",
    "sg:classifiers":[
        {
            "category":"Retail",
            "subcategory":"Car Wash",
            "type":"Services"
        }
    ],
    "sg:phone":"+32 56 31 12 89",
    "sg:postcode":"8940",
    "sg:province":"West-Vlaanderen",
    "sg:tags":[
        "automobile",
        "product",
        "-",
        "cleaning",
        "maintenance"
    ],
    "wof:name":"Dejan Bvba",
    "wof:placetype":"venue"
},
  "geometry": {"coordinates":[3.0528850555,50.7854042053],"type":"Point"}
}