{
  "type": "Feature",
  "properties": {
    "addr:full":"Netelaarstraat 3 Wommelgem Antwerpen 2160",
    "addr:housenumber":"3",
    "addr:postcode":"2160",
    "addr:street":"Netelaarstraat",
    "iso:country":"BE",
    "sg:address":"Netelaarstraat 3",
    "sg:city":"Wommelgem",
    "sg:classifiers":[
        {
            "category":"Wholesale",
            "subcategory":"Plants",
            "type":"Manufacturing & Wholesale Goods"
        }
    ],
    "sg:phone":"+32 3 354 39 68",
    "sg:postcode":"2160",
    "sg:province":"Antwerpen",
    "sg:tags":[
        "whol",
        "flower",
        "-",
        "grower"
    ],
    "wof:name":"Somers Schefflera Bvba",
    "wof:placetype":"venue"
},
  "geometry": {"coordinates":[4.5101008415,51.1928520203],"type":"Point"}
}