{
  "type": "Feature",
  "properties": {
    "addr:full":"Rue D'hoves 119 Enghien Hainaut 7850",
    "addr:housenumber":"119",
    "addr:postcode":"7850",
    "addr:street":"Rue D'Hoves",
    "iso:country":"BE",
    "sg:address":"Rue D'hoves 119",
    "sg:city":"Enghien",
    "sg:classifiers":[
        {
            "category":"Shopping",
            "subcategory":"Clothing, Apparel, & Fashions",
            "type":"Retail Goods"
        }
    ],
    "sg:phone":"+32 2 395 84 42",
    "sg:postcode":"7850",
    "sg:province":"Hainaut",
    "sg:tags":[
        "lady",
        "clothing",
        "-"
    ],
    "wof:name":"Komode",
    "wof:placetype":"venue"
},
  "geometry": {"coordinates":[4.0327548981,50.6911659241],"type":"Point"}
}