{
  "type": "Feature",
  "properties": {
    "iso:country":"BE",
    "sg:address":"Luikersteenweg 67",
    "sg:city":"Hasselt",
    "sg:classifiers":[
        {
            "category":"Home & Garden",
            "subcategory":"Hardware",
            "type":"Retail Goods"
        }
    ],
    "sg:phone":"+32 11 22 22 48",
    "sg:postcode":"3500",
    "sg:province":"Limburg",
    "sg:tags":[
        "-"
    ],
    "wof:name":"Moosen",
    "wof:placetype":"venue"
},
  "geometry": {"coordinates":[5.3387827873,50.9244041443],"type":"Point"}
}