{
  "type": "Feature",
  "properties": {
    "addr:full":"Avenue Albert Ier 12 Gerpinnes Hainaut 6280",
    "addr:housenumber":"12",
    "addr:postcode":"6280",
    "addr:street":"Avenue Albert Ier;Hainaut",
    "iso:country":"BE",
    "sg:address":"Avenue Albert Ier 12",
    "sg:city":"Gerpinnes",
    "sg:orig_category":"Alimentation sp\u00e9cialis\u00e9e. Boucheries",
    "sg:phone":"+32 71 50 31 19",
    "sg:postcode":"6280",
    "sg:province":"Hainaut",
    "wof:name":"Boucherie-traiteur Lust",
    "wof:placetype":"venue"
},
  "geometry": {"coordinates":[4.5276851654,50.3365364075],"type":"Point"}
}