{
  "type": "Feature",
  "properties": {
    "addr:full":"Waregemstraat 13 Deerlijk West-Vlaanderen 8540",
    "addr:housenumber":"13",
    "addr:postcode":"8540",
    "addr:street":"Waregemstraat",
    "iso:country":"BE",
    "sg:address":"Waregemstraat 13",
    "sg:city":"Deerlijk",
    "sg:orig_category":"Charpentes and couvertures",
    "sg:phone":"+32 56 72 80 10",
    "sg:postcode":"8540",
    "sg:province":"West-Vlaanderen",
    "wof:name":"Kurt Maes",
    "wof:placetype":"venue"
},
  "geometry": {"coordinates":[3.3614590168,50.8549499512],"type":"Point"}
}