{
  "type": "Feature",
  "properties": {
    "iso:country":"BE",
    "sg:address":"Hooiveld 76",
    "sg:city":"Puurs",
    "sg:classifiers":[
        {
            "category":"Home & Garden",
            "subcategory":"Building Materials",
            "type":"Retail Goods"
        }
    ],
    "sg:phone":"+32 3 889 12 14",
    "sg:postcode":"2870",
    "sg:province":"Antwerpen",
    "sg:tags":[
        "window"
    ],
    "wof:name":"Rousseau J",
    "wof:placetype":"venue"
},
  "geometry": {"coordinates":[4.2771930695,51.0720596313],"type":"Point"}
}