{
  "type": "Feature",
  "properties": {
    "iso:country":"BE",
    "sg:address":"Grand\u00b4 Place 51",
    "sg:city":"Saint-ghislain",
    "sg:orig_category":"Bloemen and planten",
    "sg:phone":"+32 65 78 33 19",
    "sg:postcode":"7330",
    "sg:province":"Hainaut",
    "wof:name":"Fleurs Cathy",
    "wof:placetype":"venue"
},
  "geometry": {"coordinates":[3.8201899529,50.448059082],"type":"Point"}
}