{
  "type": "Feature",
  "properties": {
    "addr:full":"Boshoek 278 Boechout Antwerpen 2530",
    "addr:housenumber":"278",
    "addr:postcode":"2530",
    "addr:street":"Boshoek",
    "iso:country":"BE",
    "sg:address":"Boshoek 278",
    "sg:city":"Boechout",
    "sg:orig_category":"Art and fournitures artistiques",
    "sg:phone":"+32 3 455 46 92",
    "sg:postcode":"2530",
    "sg:province":"Antwerpen",
    "wof:name":"Christa Sluys",
    "wof:placetype":"venue"
},
  "geometry": {"coordinates":[4.5155158043,51.1371498108],"type":"Point"}
}