{
  "type": "Feature",
  "properties": {
    "addr:full":"Rue Du Try Bara 13 Lasne (ohain) Brabant Wallon 1380",
    "addr:housenumber":"13",
    "addr:postcode":"1380",
    "addr:street":"Rue Du Try Bara;Wallon",
    "iso:country":"BE",
    "sg:address":"Rue Du Try Bara 13",
    "sg:city":"Lasne (ohain)",
    "sg:classifiers":[
        {
            "category":"Exhibition Hall",
            "type":"Public Place"
        }
    ],
    "sg:phone":"+32 2 633 12 10",
    "sg:postcode":"1380",
    "sg:province":"Brabant Wallon",
    "sg:tags":[
        "stand"
    ],
    "wof:name":"New Space",
    "wof:placetype":"venue"
},
  "geometry": {"coordinates":[4.4675931931,50.700466156],"type":"Point"}
}