{
  "type": "Feature",
  "properties": {
    "addr:full":"Hoogbuul 42 Olen Antwerpen 2250",
    "addr:housenumber":"42",
    "addr:postcode":"2250",
    "addr:street":"Hoogbuul",
    "iso:country":"BE",
    "sg:address":"Hoogbuul 42",
    "sg:city":"Olen",
    "sg:classifiers":[
        {
            "category":"Wholesale",
            "subcategory":"Sporting Goods",
            "type":"Manufacturing & Wholesale Goods"
        }
    ],
    "sg:phone":"+32 14 23 16 94",
    "sg:postcode":"2250",
    "sg:province":"Antwerpen",
    "sg:tags":[
        "sport-",
        "kampeermateriaal"
    ],
    "wof:name":"Mondial Fishing",
    "wof:placetype":"venue"
},
  "geometry": {"coordinates":[4.8886418343,51.1492042542],"type":"Point"}
}