{
  "type": "Feature",
  "properties": {
    "addr:full":"Rue De L'h\u00f4pital 3 Pont-\u00e0-celles (viesville) Hainaut 6230",
    "addr:housenumber":"3",
    "addr:postcode":"6230",
    "addr:street":"Rue De L'Ho \u0302Pital;Viesville Hainaut",
    "iso:country":"BE",
    "sg:address":"Rue De L'h\u00f4pital 3",
    "sg:city":"Pont-\u00e0-celles (viesville)",
    "sg:classifiers":[
        {
            "category":"Utilities",
            "subcategory":"Natural Gas",
            "type":"Services"
        }
    ],
    "sg:phone":"+32 71 35 14 67",
    "sg:postcode":"6230",
    "sg:province":"Hainaut",
    "sg:tags":[
        "apiculture",
        "accessory"
    ],
    "wof:name":"Wylock J-p",
    "wof:placetype":"venue"
},
  "geometry": {"coordinates":[4.4053301811,50.5153388977],"type":"Point"}
}