{
  "type": "Feature",
  "properties": {
    "iso:country":"BE",
    "sg:address":"Overleiestraat 1ba",
    "sg:city":"Kortrijk",
    "sg:orig_category":"Apotheken",
    "sg:phone":"+32 56 35 18 84",
    "sg:postcode":"8500",
    "sg:province":"West-Vlaanderen",
    "wof:name":"Dierick En Verleyen",
    "wof:placetype":"venue"
},
  "geometry": {"coordinates":[3.2612450123,50.8316383362],"type":"Point"}
}