{
  "type": "Feature",
  "properties": {
    "iso:country":"BE",
    "sg:address":"Lange Heistraat 26",
    "sg:city":"Mechelen",
    "sg:orig_category":"Artistes ind\u00e9pendants",
    "sg:phone":"+32 15 21 86 36",
    "sg:postcode":"2800",
    "sg:province":"Antwerpen",
    "wof:name":"Marnix Rosseel",
    "wof:placetype":"venue"
},
  "geometry": {"coordinates":[4.4710249901,51.0260505676],"type":"Point"}
}