{
  "type": "Feature",
  "properties": {
    "iso:country":"BE",
    "sg:address":"Kortrijksesteenweg 142",
    "sg:city":"Sint-martens-latem",
    "sg:orig_category":"Pain, p\u00e2tisseries and confiseries",
    "sg:phone":"+32 9 282 34 66",
    "sg:postcode":"9830",
    "sg:province":"Oost-Vlaanderen",
    "wof:name":"Bakkerij De Kroon",
    "wof:placetype":"venue"
},
  "geometry": {"coordinates":[3.6310529709,51.0082702637],"type":"Point"}
}