{
  "type": "Feature",
  "properties": {
    "addr:full":"Chauss\u00e9e De Louvain 300 Namur (bouge) Namur 5004",
    "addr:housenumber":"300",
    "addr:postcode":"5004",
    "addr:street":"Chausse\u0301E De Louvain",
    "iso:country":"BE",
    "sg:address":"Chauss\u00e9e De Louvain 300",
    "sg:city":"Namur (bouge)",
    "sg:classifiers":[
        {
            "category":"Professional",
            "subcategory":"Accounting & Tax Preparation",
            "type":"Services"
        }
    ],
    "sg:phone":"+32 81 20 13 81",
    "sg:postcode":"5004",
    "sg:province":"Namur",
    "sg:tags":[
        "bookkeeper"
    ],
    "wof:name":"Bothy P",
    "wof:placetype":"venue"
},
  "geometry": {"coordinates":[4.8778581619,50.4774627686],"type":"Point"}
}