{
  "type": "Feature",
  "properties": {
    "addr:full":"Molenstraat 24 Baarle-hertog Antwerpen 2387",
    "addr:housenumber":"24",
    "addr:postcode":"2387",
    "addr:street":"Molenstraat",
    "iso:country":"BE",
    "sg:address":"Molenstraat 24",
    "sg:city":"Baarle-hertog",
    "sg:classifiers":[
        {
            "category":"Fast Food",
            "type":"Food & Drink"
        }
    ],
    "sg:phone":"+32 14 69 94 77",
    "sg:postcode":"2387",
    "sg:province":"Antwerpen",
    "sg:tags":[
        "meeneem",
        "restaurant"
    ],
    "wof:name":"The Peacock",
    "wof:placetype":"venue"
},
  "geometry": {"coordinates":[4.9317121506,51.4413757324],"type":"Point"}
}