{
  "type": "Feature",
  "properties": {
    "addr:full":"Jokweg 2ba Koekelare West-Vlaanderen 8680",
    "addr:housenumber":"2ba",
    "addr:postcode":"8680",
    "addr:street":"Jokweg",
    "iso:country":"BE",
    "sg:address":"Jokweg 2ba",
    "sg:city":"Koekelare",
    "sg:orig_category":"Eleveurs and marchands de porcs",
    "sg:phone":"+32 59 27 61 59",
    "sg:postcode":"8680",
    "sg:province":"West-Vlaanderen",
    "wof:name":"Dirk Gadeyne",
    "wof:placetype":"venue"
},
  "geometry": {"coordinates":[2.9813079834,51.1262893677],"type":"Point"}
}