{
  "type": "Feature",
  "properties": {
    "addr:full":"Rue Grande 17 Saint-ghislain Hainaut 7330",
    "addr:housenumber":"17",
    "addr:postcode":"7330",
    "addr:street":"Rue Grande;Hainaut",
    "iso:country":"BE",
    "sg:address":"Rue Grande 17",
    "sg:city":"Saint-ghislain",
    "sg:orig_category":"Artistes ind\u00e9pendants",
    "sg:phone":"+32 65 79 33 23",
    "sg:postcode":"7330",
    "sg:province":"Hainaut",
    "wof:name":"Roger Liberton",
    "wof:placetype":"venue"
},
  "geometry": {"coordinates":[3.8203129768,50.446598053],"type":"Point"}
}