{
  "type": "Feature",
  "properties": {
    "iso:country":"BE",
    "sg:address":"Weibroekdreef 45b4",
    "sg:city":"Aalter",
    "sg:orig_category":"Meubelzaken, woning- and keukeninrichting",
    "sg:phone":"+32 9 375 17 47",
    "sg:postcode":"9880",
    "sg:province":"Oost-Vlaanderen",
    "wof:name":"Verimo",
    "wof:placetype":"venue"
},
  "geometry": {"coordinates":[3.4561998844,51.0897407532],"type":"Point"}
}