{
  "type": "Feature",
  "properties": {
    "iso:country":"BE",
    "sg:address":"Kerkhoflaan 58",
    "sg:city":"Aalst",
    "sg:classifiers":[
        {
            "category":"Social Services",
            "type":"Services"
        }
    ],
    "sg:phone":"+32 53 77 30 30",
    "sg:postcode":"9300",
    "sg:province":"Oost-Vlaanderen",
    "wof:name":"Kaos-kma-gezinsplaatsing",
    "wof:placetype":"venue"
},
  "geometry": {"coordinates":[4.0326299667,50.9295845032],"type":"Point"}
}