{
  "type": "Feature",
  "properties": {
    "iso:country":"BE",
    "sg:address":"Centrum-zuid 2046",
    "sg:city":"Houthalen",
    "sg:classifiers":[
        {
            "category":"Wholesale",
            "subcategory":"Meat",
            "type":"Manufacturing & Wholesale Goods"
        }
    ],
    "sg:phone":"+32 11 52 36 37",
    "sg:postcode":"3530",
    "sg:province":"Limburg",
    "sg:tags":[
        "chicken"
    ],
    "wof:name":"Buva Vleeswaren B.v.b.a.",
    "wof:placetype":"venue"
},
  "geometry": {"coordinates":[5.3657011986,51.015914917],"type":"Point"}
}