{
  "type": "Feature",
  "properties": {
    "addr:full":"Walestraat 15 Beveren Oost-Vlaanderen 9130",
    "addr:housenumber":"15",
    "addr:postcode":"9130",
    "addr:street":"Walestraat",
    "iso:country":"BE",
    "sg:address":"Walestraat 15",
    "sg:city":"Beveren",
    "sg:orig_category":"Instituts de beaut\u00e9",
    "sg:phone":"+32 3 773 50 76",
    "sg:postcode":"9130",
    "sg:province":"Oost-Vlaanderen",
    "wof:name":"M Lardenoit",
    "wof:placetype":"venue"
},
  "geometry": {"coordinates":[4.1771950722,51.2536811829],"type":"Point"}
}