{
  "type": "Feature",
  "properties": {
    "addr:full":"Braambeslei 7 Kapellen Antwerpen 2950",
    "addr:housenumber":"7",
    "addr:postcode":"2950",
    "addr:street":"Braambeslei",
    "iso:country":"BE",
    "sg:address":"Braambeslei 7",
    "sg:city":"Kapellen",
    "sg:classifiers":[
        {
            "category":"Professional",
            "subcategory":"Printing & Photocopies",
            "type":"Services"
        }
    ],
    "sg:phone":"+32 3 666 45 79",
    "sg:postcode":"2950",
    "sg:province":"Antwerpen",
    "sg:tags":[
        "-",
        "publishing",
        "desktop"
    ],
    "wof:name":"A.m.v. Reprostudio",
    "wof:placetype":"venue"
},
  "geometry": {"coordinates":[4.4542131424,51.3522720337],"type":"Point"}
}