{
  "type": "Feature",
  "properties": {
    "iso:country":"BE",
    "sg:address":"Westdijk 21",
    "sg:city":"Oostkamp",
    "sg:orig_category":"Dierenartsen",
    "sg:phone":"+32 50 35 85 74",
    "sg:postcode":"8020",
    "sg:province":"West-Vlaanderen",
    "wof:name":"Christiane De Grande",
    "wof:placetype":"venue"
},
  "geometry": {"coordinates":[3.2590329647,51.1605529785],"type":"Point"}
}