{
  "type": "Feature",
  "properties": {
    "iso:country":"BE",
    "sg:address":"Christinastraat 44",
    "sg:city":"Oostende",
    "sg:classifiers":[
        {
            "category":"Travel",
            "subcategory":"Travel Agent",
            "type":"Entertainment"
        }
    ],
    "sg:phone":"+32 59 51 42 42",
    "sg:postcode":"8400",
    "sg:province":"West-Vlaanderen",
    "sg:tags":[
        "agency"
    ],
    "wof:name":"Delsun Travel",
    "wof:placetype":"venue"
},
  "geometry": {"coordinates":[2.9164938927,51.2314071655],"type":"Point"}
}