{
  "type": "Feature",
  "properties": {
    "addr:full":"Chauss\u00c9e Churchill 72 Saint-nicolas Li\u00e8ge 4420",
    "addr:housenumber":"72",
    "addr:postcode":"4420",
    "addr:street":"Chausse\u0301E Churchill",
    "iso:country":"BE",
    "sg:address":"Chauss\u00c9e Churchill 72",
    "sg:city":"Saint-nicolas",
    "sg:orig_category":"Brood, gebak and snoepgoed",
    "sg:phone":"+32 4 239 04 71",
    "sg:postcode":"4420",
    "sg:province":"Li\u00e8ge",
    "wof:name":"Reseau Broca",
    "wof:placetype":"venue"
},
  "geometry": {"coordinates":[5.5244197845,50.6453590393],"type":"Point"}
}