{
  "type": "Feature",
  "properties": {
    "iso:country":"BE",
    "sg:address":"Rue De La D\u00c9mocratie 89",
    "sg:city":"Seraing",
    "sg:orig_category":"Activit\u00e9s r\u00e9cr\u00e9atives diverses",
    "sg:phone":"+32 4 337 41 57",
    "sg:postcode":"4102",
    "sg:province":"Li\u00e8ge",
    "wof:name":"Atelier D'art Et D'expression",
    "wof:placetype":"venue"
},
  "geometry": {"coordinates":[5.536670208,50.6004905701],"type":"Point"}
}