{
  "type": "Feature",
  "properties": {
    "iso:country":"BE",
    "sg:address":"Avenue Du Cheret 19",
    "sg:city":"Chaudfontaine",
    "sg:orig_category":"Artsen and specialisten",
    "sg:phone":"+32 4 367 24 94",
    "sg:postcode":"4053",
    "sg:province":"Li\u00e8ge",
    "wof:name":"Luc Vandendael",
    "wof:placetype":"venue"
},
  "geometry": {"coordinates":[5.5984067917,50.5853691101],"type":"Point"}
}