{
  "type": "Feature",
  "properties": {
    "addr:full":"Fruitmarkt 2 Genk Limburg 3600",
    "addr:housenumber":"2",
    "addr:postcode":"3600",
    "addr:street":"Fruitmarkt",
    "iso:country":"BE",
    "sg:address":"Fruitmarkt 2",
    "sg:city":"Genk",
    "sg:orig_category":"Transports terrestres de voyageurs",
    "sg:phone":"+32 89 38 00 93",
    "sg:postcode":"3600",
    "sg:province":"Limburg",
    "wof:name":"De Nachtegaal",
    "wof:placetype":"venue"
},
  "geometry": {"coordinates":[5.4998588562,50.9654426575],"type":"Point"}
}