{
  "type": "Feature",
  "properties": {
    "addr:full":"Korte Groenweg 147 Brussel/bruxelles Bruxelles-Capitale 1120",
    "addr:housenumber":"147",
    "addr:postcode":"1120",
    "addr:street":"Korte Groenweg;/",
    "iso:country":"BE",
    "sg:address":"Korte Groenweg 147",
    "sg:city":"Brussel/bruxelles",
    "sg:orig_category":"Alternatieve geneeskunde",
    "sg:phone":"+32 2 268 56 77",
    "sg:postcode":"1120",
    "sg:province":"Bruxelles-Capitale",
    "wof:name":"Linda De Boeck",
    "wof:placetype":"venue"
},
  "geometry": {"coordinates":[4.3925309181,50.9023704529],"type":"Point"}
}