{
  "type": "Feature",
  "properties": {
    "iso:country":"BE",
    "sg:address":"Elzeelsesteenweg 382",
    "sg:city":"Ronse/renaix",
    "sg:classifiers":[
        {
            "category":"Food & Beverages",
            "subcategory":"Fruits & Vegetables",
            "type":"Retail Goods"
        }
    ],
    "sg:phone":"+32 55 21 04 28",
    "sg:postcode":"9600",
    "sg:province":"Oost-Vlaanderen",
    "sg:tags":[
        "groenten"
    ],
    "wof:name":"Marnic Vanden Dorpe",
    "wof:placetype":"venue"
},
  "geometry": {"coordinates":[3.6233570576,50.7383918762],"type":"Point"}
}