{
  "type": "Feature",
  "properties": {
    "addr:full":"Rue De L'yser 22 Tournai Hainaut 7500",
    "addr:housenumber":"22",
    "addr:postcode":"7500",
    "addr:street":"Rue De L'Yser",
    "iso:country":"BE",
    "sg:address":"Rue De L'yser 22",
    "sg:city":"Tournai",
    "sg:orig_category":"Artiesten and kunstenaars",
    "sg:phone":"+32 69 21 37 13",
    "sg:postcode":"7500",
    "sg:province":"Hainaut",
    "wof:name":"Bertrand",
    "wof:placetype":"venue"
},
  "geometry": {"coordinates":[3.3861670494,50.6075286865],"type":"Point"}
}