{
  "type": "Feature",
  "properties": {
    "iso:country":"BE",
    "sg:address":"Rue De La Fraternit\u00c9 55",
    "sg:city":"Bernissart",
    "sg:orig_category":"Bloemen and planten",
    "sg:phone":"+32 69 57 71 09",
    "sg:postcode":"7321",
    "sg:province":"Hainaut",
    "wof:name":"Vinchent - Desirs",
    "wof:placetype":"venue"
},
  "geometry": {"coordinates":[3.6611618996,50.5015869141],"type":"Point"}
}