{
  "type": "Feature",
  "properties": {
    "addr:full":"Rue De Valenciennes 2 Bernissart Hainaut 7320",
    "addr:housenumber":"2",
    "addr:postcode":"7320",
    "addr:street":"Rue De Valenciennes",
    "iso:country":"BE",
    "sg:address":"Rue De Valenciennes 2",
    "sg:city":"Bernissart",
    "sg:orig_category":"Rundveehouders",
    "sg:phone":"+32 69 56 28 22",
    "sg:postcode":"7320",
    "sg:province":"Hainaut",
    "wof:name":"Albert Olivier",
    "wof:placetype":"venue"
},
  "geometry": {"coordinates":[3.6657979488,50.4819717407],"type":"Point"}
}