{
  "type": "Feature",
  "properties": {
    "addr:full":"Rozengaard 19 Kontich Antwerpen 2550",
    "addr:housenumber":"19",
    "addr:postcode":"2550",
    "addr:street":"Rozengaard",
    "iso:country":"BE",
    "sg:address":"Rozengaard 19",
    "sg:city":"Kontich",
    "sg:classifiers":[
        {
            "category":"Professional",
            "subcategory":"Computer Services",
            "type":"Services"
        }
    ],
    "sg:phone":"+32 477 22 23 60",
    "sg:postcode":"2550",
    "sg:province":"Antwerpen",
    "sg:tags":[
        "-",
        "processing",
        "data",
        "software"
    ],
    "wof:name":"Brusoft",
    "wof:placetype":"venue"
},
  "geometry": {"coordinates":[4.478468895,51.1274681091],"type":"Point"}
}