{
  "type": "Feature",
  "properties": {
    "addr:full":"Engelendalelaan 140 Brugge (assebroek) West-Vlaanderen 8310",
    "addr:housenumber":"140",
    "addr:postcode":"8310",
    "addr:street":"Engelendalelaan",
    "iso:country":"BE",
    "sg:address":"Engelendalelaan 140",
    "sg:city":"Brugge (assebroek)",
    "sg:classifiers":[
        {
            "category":"Building & Trades",
            "subcategory":"Landscaping Services",
            "type":"Services"
        }
    ],
    "sg:phone":"+32 50 67 82 01",
    "sg:postcode":"8310",
    "sg:province":"West-Vlaanderen",
    "sg:tags":[
        "access",
        "pond",
        "laying-out",
        "-"
    ],
    "wof:name":"Aquajoy",
    "wof:placetype":"venue"
},
  "geometry": {"coordinates":[3.2796599865,51.2128486633],"type":"Point"}
}