{
  "type": "Feature",
  "properties": {
    "iso:country":"BE",
    "sg:address":"5 Rue Carli",
    "sg:city":"Bruxelles",
    "sg:classifiers":[
        {
            "category":"Health Services",
            "subcategory":"Medical Lab",
            "type":"Services"
        }
    ],
    "sg:phone":"+32 2 245 83 70",
    "sg:postcode":"1040",
    "sg:province":"Bruxelles-Capitale",
    "sg:tags":[
        "chemical",
        "pharmaceutical",
        "pharmacy"
    ],
    "wof:name":"Dolisos",
    "wof:placetype":"venue"
},
  "geometry": {"coordinates":[4.3924598694,50.8795852661],"type":"Point"}
}