{
  "type": "Feature",
  "properties": {
    "addr:full":"Chauss\u00c9e De Charleroi 72 Waterloo Brabant Wallon 1410",
    "addr:housenumber":"72",
    "addr:postcode":"1410",
    "addr:street":"Chausse\u0301E De Charleroi",
    "iso:country":"BE",
    "sg:address":"Chauss\u00c9e De Charleroi 72",
    "sg:city":"Waterloo",
    "sg:classifiers":[
        {
            "category":"Restaurant",
            "type":"Food & Drink"
        }
    ],
    "sg:phone":"+32 2 387 17 78",
    "sg:postcode":"1410",
    "sg:province":"Brabant Wallon",
    "wof:name":"Le Grill De L'empereur",
    "wof:placetype":"venue"
},
  "geometry": {"coordinates":[4.4102859497,50.6834106445],"type":"Point"}
}