{
  "type": "Feature",
  "properties": {
    "addr:full":"Hazelarenstraat 8 Antwerpen Antwerpen 2020",
    "addr:housenumber":"8",
    "addr:postcode":"2020",
    "addr:street":"Hazelarenstraat",
    "iso:country":"BE",
    "sg:address":"Hazelarenstraat 8",
    "sg:city":"Antwerpen",
    "sg:classifiers":[
        {
            "category":"Health Services",
            "subcategory":"Doctor",
            "type":"Services"
        }
    ],
    "sg:phone":"+32 3 238 55 10",
    "sg:postcode":"2020",
    "sg:province":"Antwerpen",
    "sg:tags":[
        "medicinephysicians",
        "surgeon"
    ],
    "wof:name":"De Leersnyder Diederik",
    "wof:placetype":"venue"
},
  "geometry": {"coordinates":[4.3923768997,51.1855163574],"type":"Point"}
}