{
  "type": "Feature",
  "properties": {
    "addr:full":"Rue Du Faubourg 66 Komen-waasten/comines-warneton Hainaut 7780",
    "addr:housenumber":"66;7780",
    "addr:street":"Rue Du Faubourg",
    "iso:country":"BE",
    "sg:address":"Rue Du Faubourg 66",
    "sg:city":"Komen-waasten/comines-warneton",
    "sg:orig_category":"Equipement photographique. Jeux and jouets. Eclairage et \u00e9quipements du foyer. Articles de camping a",
    "sg:phone":"+32 56 55 78 73",
    "sg:postcode":"7780",
    "sg:province":"Hainaut",
    "wof:name":"Blokker",
    "wof:placetype":"venue"
},
  "geometry": {"coordinates":[3.0025498867,50.7670783997],"type":"Point"}
}