{
  "type": "Feature",
  "properties": {
    "addr:full":"Tulpenstraat 4 Brugge (assebroek) West-Vlaanderen 8310",
    "addr:housenumber":"4",
    "addr:postcode":"8310",
    "addr:street":"Tulpenstraat",
    "iso:country":"BE",
    "sg:address":"Tulpenstraat 4",
    "sg:city":"Brugge (assebroek)",
    "sg:classifiers":[
        {
            "category":"Shopping",
            "subcategory":"Antiques",
            "type":"Retail Goods"
        }
    ],
    "sg:phone":"+32 50 37 27 76",
    "sg:postcode":"8310",
    "sg:province":"West-Vlaanderen",
    "wof:name":"The African Connection Bvba",
    "wof:placetype":"venue"
},
  "geometry": {"coordinates":[3.237598896,51.1940002441],"type":"Point"}
}