{
  "type": "Feature",
  "properties": {
    "iso:country":"BE",
    "sg:address":"Industriepark 56",
    "sg:city":"Hulshout",
    "sg:classifiers":[
        {
            "category":"Building & Trades",
            "subcategory":"Construction",
            "type":"Services"
        }
    ],
    "sg:phone":"+32 15 22 80 08",
    "sg:postcode":"2235",
    "sg:province":"Antwerpen",
    "sg:tags":[
        "carpenter"
    ],
    "wof:name":"Betrabo Bvba",
    "wof:placetype":"venue"
},
  "geometry": {"coordinates":[4.8132228851,51.080619812],"type":"Point"}
}