{
  "type": "Feature",
  "properties": {
    "addr:full":"Dorpsstraat 3 Herstappe/herstappe Limburg 3717",
    "addr:housenumber":"3",
    "addr:postcode":"3717",
    "addr:street":"Dorpsstraat",
    "iso:country":"BE",
    "sg:address":"Dorpsstraat 3",
    "sg:city":"Herstappe/herstappe",
    "sg:orig_category":"Rundveehouders Varkenskwekers",
    "sg:phone":"+32 12 23 55 63",
    "sg:postcode":"3717",
    "sg:province":"Limburg",
    "wof:name":"Albert Renard",
    "wof:placetype":"venue"
},
  "geometry": {"coordinates":[5.4273872375,50.7259902954],"type":"Point"}
}