{
  "type": "Feature",
  "properties": {
    "addr:full":"Durmen 175 Zele Oost-Vlaanderen 9240",
    "addr:housenumber":"175",
    "addr:postcode":"9240",
    "addr:street":"Durmen",
    "iso:country":"BE",
    "sg:address":"Durmen 175",
    "sg:city":"Zele",
    "sg:classifiers":[
        {
            "category":"Utilities",
            "subcategory":"Fuel Oil & Lpg",
            "type":"Services"
        }
    ],
    "sg:phone":"+32 52 44 95 51",
    "sg:postcode":"9240",
    "sg:province":"Oost-Vlaanderen",
    "wof:name":"Van Driessche-de Caluwe Bvba",
    "wof:placetype":"venue"
},
  "geometry": {"coordinates":[4.0497050285,51.0839157104],"type":"Point"}
}