{
  "type": "Feature",
  "properties": {
    "addr:full":"Notarisstraat 1 Gent Oost-Vlaanderen 9000",
    "addr:housenumber":"1",
    "addr:postcode":"9000",
    "addr:street":"Notarisstraat;Oost-Vlaanderen",
    "iso:country":"BE",
    "sg:address":"Notarisstraat 1",
    "sg:city":"Gent",
    "sg:classifiers":[
        {
            "category":"Real Estate",
            "subcategory":"Architect",
            "type":"Services"
        }
    ],
    "sg:phone":"+32 9 223 79 73",
    "sg:postcode":"9000",
    "sg:province":"Oost-Vlaanderen",
    "wof:name":"Architectenbureau De Witte, Claeys & Partners Bvba",
    "wof:placetype":"venue"
},
  "geometry": {"coordinates":[3.7296071053,51.0511932373],"type":"Point"}
}