{
  "type": "Feature",
  "properties": {
    "iso:country":"BE",
    "sg:address":"Herckenrodedreef 55",
    "sg:city":"Hasselt",
    "sg:classifiers":[
        {
            "category":"Cafe",
            "type":"Food & Drink"
        }
    ],
    "sg:phone":"+32 11 25 03 13",
    "sg:postcode":"3511",
    "sg:province":"Limburg",
    "sg:tags":[
        "caf\u00e9s"
    ],
    "wof:name":"Gerba",
    "wof:placetype":"venue"
},
  "geometry": {"coordinates":[5.3034238815,50.9432487488],"type":"Point"}
}