{
  "type": "Feature",
  "properties": {
    "iso:country":"BE",
    "sg:address":"Rue Edouard Colson 7",
    "sg:city":"Ans",
    "sg:orig_category":"Schoonheidssalons",
    "sg:phone":"+32 4 263 60 99",
    "sg:postcode":"4431",
    "sg:province":"Li\u00e8ge",
    "wof:name":"Josiane Pirotte",
    "wof:placetype":"venue"
},
  "geometry": {"coordinates":[5.5052099228,50.6663017273],"type":"Point"}
}