{
  "type": "Feature",
  "properties": {
    "addr:full":"9800 Deinze (groot) Oost-Vlaanderen 9800",
    "addr:postcode":"9800;9800",
    "addr:street":"Groot Oost-Vlaanderen",
    "iso:country":"BE",
    "sg:address":"9800",
    "sg:city":"Deinze (groot)",
    "sg:orig_category":"Pharmaciens",
    "sg:phone":"+32 900 10 500",
    "sg:postcode":"9800",
    "sg:province":"Oost-Vlaanderen",
    "wof:name":"Pharmacies De Garde",
    "wof:placetype":"venue"
},
  "geometry": {"coordinates":[3.530174017,50.9863166809],"type":"Point"}
}