{
  "type": "Feature",
  "properties": {
    "addr:full":"Avenue Du Diamant 132 Bruxelles (schaerbeek) Bruxelles-Capitale 1030",
    "addr:housenumber":"132",
    "addr:postcode":"1030",
    "addr:street":"Avenue Du Diamant",
    "iso:country":"BE",
    "sg:address":"Avenue Du Diamant 132",
    "sg:city":"Bruxelles (schaerbeek)",
    "sg:orig_category":"Non-Classified Establishments",
    "sg:phone":"+32 2 733 89 60",
    "sg:postcode":"1030",
    "sg:province":"Bruxelles-Capitale",
    "wof:name":"I.d. Etc",
    "wof:placetype":"venue"
},
  "geometry": {"coordinates":[4.3978199959,50.8505249023],"type":"Point"}
}