{
  "type": "Feature",
  "properties": {
    "addr:full":"Roeselaarsestraat 35 Izegem West-Vlaanderen 8870",
    "addr:housenumber":"35",
    "addr:postcode":"8870",
    "addr:street":"Roeselaarsestraat",
    "iso:country":"BE",
    "sg:address":"Roeselaarsestraat 35",
    "sg:city":"Izegem",
    "sg:orig_category":"Drukkerijen and copyshops",
    "sg:phone":"+32 51 30 96 11",
    "sg:postcode":"8870",
    "sg:province":"West-Vlaanderen",
    "wof:name":"Pico Bello",
    "wof:placetype":"venue"
},
  "geometry": {"coordinates":[3.2120709419,50.9182891846],"type":"Point"}
}