{
  "type": "Feature",
  "properties": {
    "addr:full":"Kon Leopold 3-in 37 Kortrijk West-Vlaanderen 8500",
    "addr:housenumber":"37",
    "addr:postcode":"8500",
    "addr:street":"Kon Leopold 3-In",
    "iso:country":"BE",
    "sg:address":"Kon Leopold 3-in 37",
    "sg:city":"Kortrijk",
    "sg:orig_category":"Diverse bedrijfsbeheeradviesbureaus",
    "sg:phone":"+32 56 35 05 94",
    "sg:postcode":"8500",
    "sg:province":"West-Vlaanderen",
    "wof:name":"Advieskantoor Vdw",
    "wof:placetype":"venue"
},
  "geometry": {"coordinates":[3.2671499252,50.8402023315],"type":"Point"}
}