{
  "type": "Feature",
  "properties": {
    "iso:country":"BE",
    "sg:address":"Avenue Albert Ier 251",
    "sg:city":"Namur",
    "sg:orig_category":"Administration d'immeubles",
    "sg:phone":"+32 81 22 49 76",
    "sg:postcode":"5000",
    "sg:province":"Namur",
    "wof:name":"Pierre Jallay",
    "wof:placetype":"venue"
},
  "geometry": {"coordinates":[4.8922419548,50.4674873352],"type":"Point"}
}