{
  "type": "Feature",
  "properties": {
    "addr:full":"Poperingseweg 308 Ieper West-Vlaanderen 8908",
    "addr:housenumber":"308",
    "addr:postcode":"8908",
    "addr:street":"Poperingseweg",
    "iso:country":"BE",
    "sg:address":"Poperingseweg 308",
    "sg:city":"Ieper",
    "sg:orig_category":"Bouwmaterialen Gh Plaatsen van vloer- and muurbekleding Woningbouw",
    "sg:phone":"+32 57 20 47 58",
    "sg:postcode":"8908",
    "sg:province":"West-Vlaanderen",
    "wof:name":"Paul Deweerdt",
    "wof:placetype":"venue"
},
  "geometry": {"coordinates":[2.8120961189,50.8545227051],"type":"Point"}
}