{
  "type": "Feature",
  "properties": {
    "addr:full":"Chauss\u00c9e De Mons 55 Anderlecht/anderlecht Bruxelles-Capitale 1070",
    "addr:housenumber":"55",
    "addr:postcode":"1070",
    "addr:street":"Chausse\u0301E De Mons",
    "iso:country":"BE",
    "sg:address":"Chauss\u00c9e De Mons 55",
    "sg:city":"Anderlecht/anderlecht",
    "sg:orig_category":"Auto-\u00e9coles",
    "sg:phone":"+32 2 522 13 76",
    "sg:postcode":"1070",
    "sg:province":"Bruxelles-Capitale",
    "wof:name":"Auto Pilott",
    "wof:placetype":"venue"
},
  "geometry": {"coordinates":[4.3354687691,50.8439674377],"type":"Point"}
}