{
  "type": "Feature",
  "properties": {
    "iso:country":"BE",
    "sg:address":"Lepelstraat 19",
    "sg:city":"Laarne",
    "sg:orig_category":"HUISBRANDOLIE",
    "sg:phone":"+32 9 369 09 89",
    "sg:postcode":"9270",
    "sg:province":"Oost-Vlaanderen",
    "wof:name":"Paelinck",
    "wof:placetype":"venue"
},
  "geometry": {"coordinates":[3.8523030281,51.0304450989],"type":"Point"}
}