{
  "type": "Feature",
  "properties": {
    "iso:country":"BE",
    "sg:address":"Rue De La Coul\u00e9e 20",
    "sg:city":"Trois-ponts - Fosse (basse-bodeux)",
    "sg:classifiers":[
        {
            "category":"Freight",
            "type":"Transportation"
        }
    ],
    "sg:phone":"+32 80 68 41 61",
    "sg:postcode":"4983",
    "sg:province":"Li\u00e8ge",
    "sg:tags":[
        "-",
        "transport"
    ],
    "wof:name":"Tobri Sa",
    "wof:placetype":"venue"
},
  "geometry": {"coordinates":[5.8255419731,50.3567047119],"type":"Point"}
}