{
  "type": "Feature",
  "properties": {
    "iso:country":"BE",
    "sg:address":"Avenue De Ramelot 5",
    "sg:city":"Tubize (saintes)",
    "sg:classifiers":[
        {
            "category":"Manufacturing",
            "subcategory":"Paper Products",
            "type":"Manufacturing & Wholesale Goods"
        }
    ],
    "sg:phone":"+32 2 331 19 60",
    "sg:postcode":"1480",
    "sg:province":"Brabant Wallon",
    "sg:tags":[
        "bookbinding"
    ],
    "wof:name":"Maxy-broches Sc",
    "wof:placetype":"venue"
},
  "geometry": {"coordinates":[4.204308033,50.6932029724],"type":"Point"}
}