{
  "type": "Feature",
  "properties": {
    "addr:full":"Looi 3 Rijkevorsel Antwerpen 2310",
    "addr:housenumber":"3",
    "addr:postcode":"2310",
    "addr:street":"Looi",
    "iso:country":"BE",
    "sg:address":"Looi 3",
    "sg:city":"Rijkevorsel",
    "sg:orig_category":"Enseignement maternel and primaire",
    "sg:phone":"+32 3 309 21 44",
    "sg:postcode":"2310",
    "sg:province":"Antwerpen",
    "wof:name":"Vrije Kleuterschool",
    "wof:placetype":"venue"
},
  "geometry": {"coordinates":[4.7550621033,51.3327789307],"type":"Point"}
}