{
  "type": "Feature",
  "properties": {
    "addr:full":"Nekkerspoel Borcht Mechelen Antwerpen 2800",
    "addr:postcode":"2800",
    "addr:street":"Borcht",
    "iso:country":"BE",
    "sg:address":"Nekkerspoel Borcht",
    "sg:city":"Mechelen",
    "sg:orig_category":"Fairs, shows, exhibitions",
    "sg:phone":"+32 15 55 10 01",
    "sg:postcode":"2800",
    "sg:province":"Antwerpen",
    "wof:name":"Nekkerhal (de)",
    "wof:placetype":"venue"
},
  "geometry": {"coordinates":[4.4913139343,51.0287475586],"type":"Point"}
}