{
  "type": "Feature",
  "properties": {
    "iso:country":"BE",
    "sg:address":"Ch\u00cane \u00c0 Han 1",
    "sg:city":"Grandhan",
    "sg:orig_category":"H\u00f4tels. Restaurants",
    "sg:phone":"+32 86 32 21 21",
    "sg:postcode":"6940",
    "sg:province":"Luxembourg",
    "wof:name":"Restaurant La Passerelle",
    "wof:placetype":"venue"
},
  "geometry": {"coordinates":[5.4067921638,50.3312644958],"type":"Point"}
}