{
  "type": "Feature",
  "properties": {
    "iso:country":"BE",
    "sg:address":"Meiselaan 71",
    "sg:city":"Kapelle-op-den-bos",
    "sg:orig_category":"M\u00e9decins and sp\u00e9cialistes",
    "sg:phone":"+32 15 71 28 51",
    "sg:postcode":"1880",
    "sg:province":"Vlaams-Brabant",
    "wof:name":"P. Meersman",
    "wof:placetype":"venue"
},
  "geometry": {"coordinates":[4.3494968414,50.9769020081],"type":"Point"}
}