{
  "type": "Feature",
  "properties": {
    "iso:country":"BE",
    "sg:address":"Brusselsestraat 156",
    "sg:city":"Leuven",
    "sg:orig_category":"Voedingsspeciaalzaken",
    "sg:phone":"+32 16 23 76 71",
    "sg:postcode":"3000",
    "sg:province":"Vlaams-Brabant",
    "wof:name":"Huis Nectar",
    "wof:placetype":"venue"
},
  "geometry": {"coordinates":[4.6927509308,50.8808479309],"type":"Point"}
}