{
  "type": "Feature",
  "properties": {
    "addr:full":"Malmedyer Strasse 5 Sankt Vith Li\u00e8ge 4780",
    "addr:housenumber":"5",
    "addr:postcode":"4780",
    "addr:street":"Malmedyer Strasse",
    "iso:country":"BE",
    "sg:address":"Malmedyer Strasse 5",
    "sg:city":"Sankt Vith",
    "sg:classifiers":[
        {
            "category":"Arts & Performance",
            "subcategory":"Art Gallery",
            "type":"Entertainment"
        }
    ],
    "sg:phone":"+32 80 39 95 45",
    "sg:postcode":"4780",
    "sg:province":"Li\u00e8ge",
    "wof:name":"St.vither Kunstladen",
    "wof:placetype":"venue"
},
  "geometry": {"coordinates":[6.123942852,50.2826652527],"type":"Point"}
}