{
  "type": "Feature",
  "properties": {
    "iso:country":"BE",
    "sg:address":"Westmeerbeeksesteenweg 74",
    "sg:city":"Herselt",
    "sg:orig_category":"MEUBELONTWERP AND -INSTALLATIE",
    "sg:phone":"+32 16 69 83 42",
    "sg:postcode":"2230",
    "sg:province":"Antwerpen",
    "wof:name":"Richard Vermeylen",
    "wof:placetype":"venue"
},
  "geometry": {"coordinates":[4.8293399811,51.0405197144],"type":"Point"}
}