{
  "type": "Feature",
  "properties": {
    "iso:country":"BE",
    "sg:address":"Hilarius Bertolfstraat 79",
    "sg:city":"Gent",
    "sg:orig_category":"Artsen and specialisten",
    "sg:phone":"+32 9 230 43 93",
    "sg:postcode":"9050",
    "sg:province":"Oost-Vlaanderen",
    "wof:name":"W. Laureys",
    "wof:placetype":"venue"
},
  "geometry": {"coordinates":[3.746721983,51.0358276367],"type":"Point"}
}