{
  "type": "Feature",
  "properties": {
    "addr:full":"Uilenbaan 194 Wommelgem Antwerpen 2160",
    "addr:housenumber":"194",
    "addr:postcode":"2160",
    "iso:country":"BE",
    "sg:address":"Uilenbaan 194",
    "sg:city":"Wommelgem",
    "sg:classifiers":[
        {
            "category":"Train Station",
            "subcategory":"Light Rail",
            "type":"Transportation"
        }
    ],
    "sg:phone":"+32 3 321 28 77",
    "sg:postcode":"2160",
    "sg:province":"Antwerpen",
    "sg:tags":[
        "luminous",
        "score-boards",
        "display"
    ],
    "wof:name":"Neopaul-acryl-neon Bvba",
    "wof:placetype":"venue"
},
  "geometry": {"coordinates":[4.5257821083,51.2140464783],"type":"Point"}
}