{
  "type": "Feature",
  "properties": {
    "iso:country":"BE",
    "sg:address":"Sentier Malaquin 2b",
    "sg:city":"Mons",
    "sg:orig_category":"Maatschappelijke dienstverlening",
    "sg:phone":"+32 65 34 63 77",
    "sg:postcode":"7000",
    "sg:province":"Hainaut",
    "wof:name":"Restos Du Coeur",
    "wof:placetype":"venue"
},
  "geometry": {"coordinates":[3.9594070911,50.4656486511],"type":"Point"}
}