{
  "type": "Feature",
  "properties": {
    "addr:full":"Zelebaan 61 Lokeren Oost-Vlaanderen 9160",
    "addr:housenumber":"61",
    "addr:postcode":"9160",
    "addr:street":"Zelebaan",
    "iso:country":"BE",
    "sg:address":"Zelebaan 61",
    "sg:city":"Lokeren",
    "sg:orig_category":"Meubelzaken, woning- and keukeninrichting Verlichting and huishoudartikelen",
    "sg:phone":"+32 9 349 20 81",
    "sg:postcode":"9160",
    "sg:province":"Oost-Vlaanderen",
    "wof:name":"Leenbakker",
    "wof:placetype":"venue"
},
  "geometry": {"coordinates":[4.0142841339,51.0931434631],"type":"Point"}
}