{
  "type": "Feature",
  "properties": {
    "iso:country":"BE",
    "sg:address":"Vlaamsekunstlaan 70",
    "sg:city":"Antwerpen",
    "sg:classifiers":[
        {
            "category":"Real Estate",
            "subcategory":"Architect",
            "type":"Services"
        }
    ],
    "sg:phone":"+32 3 257 09 89",
    "sg:postcode":"2020",
    "sg:province":"Antwerpen",
    "wof:name":"Vermoesen A",
    "wof:placetype":"venue"
},
  "geometry": {"coordinates":[4.3895010948,51.1903572083],"type":"Point"}
}