{
  "type": "Feature",
  "properties": {
    "iso:country":"BE",
    "sg:address":"Kapelstraat 71",
    "sg:city":"Beveren-waas (melsele)",
    "sg:orig_category":"Fotografen and fotostudio's",
    "sg:phone":"+32 477 51 46 78",
    "sg:postcode":"9120",
    "sg:province":"Oost-Vlaanderen",
    "wof:name":"Fotostudio Dirk Van Dosselaer",
    "wof:placetype":"venue"
},
  "geometry": {"coordinates":[4.2650279999,51.2241096497],"type":"Point"}
}