{
  "type": "Feature",
  "properties": {
    "iso:country":"BE",
    "sg:address":"Tweebruggenpln 3",
    "sg:city":"Hamme (groot)",
    "sg:classifiers":[
        {
            "category":"Personal",
            "subcategory":"Beauty Salon",
            "type":"Services"
        }
    ],
    "sg:phone":"+32 52 47 84 17",
    "sg:postcode":"9220",
    "sg:province":"Oost-Vlaanderen",
    "sg:tags":[
        "de",
        "coiffure"
    ],
    "wof:name":"Magda",
    "wof:placetype":"venue"
},
  "geometry": {"coordinates":[4.1436028481,51.0950698853],"type":"Point"}
}