{
  "type": "Feature",
  "properties": {
    "addr:full":"Ellestraat 22 Zwevegem West-Vlaanderen 8550",
    "addr:housenumber":"22",
    "addr:postcode":"8550",
    "addr:street":"Ellestraat",
    "iso:country":"BE",
    "sg:address":"Ellestraat 22",
    "sg:city":"Zwevegem",
    "sg:orig_category":"Slagers",
    "sg:phone":"+32 56 75 58 79",
    "sg:postcode":"8550",
    "sg:province":"West-Vlaanderen",
    "wof:name":"Kristof Schotte",
    "wof:placetype":"venue"
},
  "geometry": {"coordinates":[3.3587539196,50.804107666],"type":"Point"}
}