{
  "type": "Feature",
  "properties": {
    "iso:country":"BE",
    "sg:address":"Rue De L'armee Grouchy 9",
    "sg:city":"Namur",
    "sg:orig_category":"Drogisterijen IJzerwaren, bouw- and verfmaterialen Textiel Verlichting and huishoudartikelen",
    "sg:phone":"+32 81 74 00 88",
    "sg:postcode":"5000",
    "sg:province":"Namur",
    "wof:name":"L'etoile D'or",
    "wof:placetype":"venue"
},
  "geometry": {"coordinates":[4.8547101021,50.4691200256],"type":"Point"}
}