{
  "type": "Feature",
  "properties": {
    "iso:country":"BE",
    "sg:address":"Middeldorpe 14",
    "sg:city":"Sint-laureins",
    "sg:orig_category":"P\u00e9pini\u00e9ristes",
    "sg:phone":"+32 9 379 98 89",
    "sg:postcode":"9980",
    "sg:province":"Oost-Vlaanderen",
    "wof:name":"Hoste Boomkwekerij",
    "wof:placetype":"venue"
},
  "geometry": {"coordinates":[3.4929459095,51.2359733582],"type":"Point"}
}