{
  "type": "Feature",
  "properties": {
    "iso:country":"BE",
    "sg:address":"Wuustwezelseweg 156",
    "sg:city":"Wuustwezel",
    "sg:orig_category":"Dakwerken",
    "sg:phone":"+32 3 669 98 55",
    "sg:postcode":"2990",
    "sg:province":"Antwerpen",
    "wof:name":"C.j. Rasenberg",
    "wof:placetype":"venue"
},
  "geometry": {"coordinates":[4.6183700562,51.4074058533],"type":"Point"}
}