{
  "type": "Feature",
  "properties": {
    "addr:full":"Leopoldlaan 92 Aalst Oost-Vlaanderen 9300",
    "addr:housenumber":"92",
    "addr:postcode":"9300",
    "addr:street":"Leopoldlaan",
    "iso:country":"BE",
    "sg:address":"Leopoldlaan 92",
    "sg:city":"Aalst",
    "sg:classifiers":[
        {
            "category":"Retail",
            "subcategory":"Laundry & Dry Cleaning",
            "type":"Services"
        }
    ],
    "sg:phone":"+32 53 70 47 65",
    "sg:postcode":"9300",
    "sg:province":"Oost-Vlaanderen",
    "sg:tags":[
        "dyer",
        "cleaner"
    ],
    "wof:name":"Christal Cleaning",
    "wof:placetype":"venue"
},
  "geometry": {"coordinates":[4.0499720573,50.9461555481],"type":"Point"}
}