{
  "type": "Feature",
  "properties": {
    "addr:full":"Droefstraat 11 Tongeren Limburg 3700",
    "addr:housenumber":"11",
    "addr:postcode":"3700",
    "addr:street":"Droefstraat",
    "iso:country":"BE",
    "sg:address":"Droefstraat 11",
    "sg:city":"Tongeren",
    "sg:orig_category":"Drogisterijen",
    "sg:phone":"+32 12 23 43 69",
    "sg:postcode":"3700",
    "sg:province":"Limburg",
    "wof:name":"G Mertens",
    "wof:placetype":"venue"
},
  "geometry": {"coordinates":[5.491133213,50.7512397766],"type":"Point"}
}