{
  "type": "Feature",
  "properties": {
    "addr:full":"Rue Du Village 2 Edingen/enghien Hainaut 7850",
    "addr:housenumber":"2",
    "addr:postcode":"7850",
    "addr:street":"Rue Du Village",
    "iso:country":"BE",
    "sg:address":"Rue Du Village 2",
    "sg:city":"Edingen/enghien",
    "sg:orig_category":"Enseignement maternel and primaire",
    "sg:phone":"+32 2 395 39 08",
    "sg:postcode":"7850",
    "sg:province":"Hainaut",
    "wof:name":"Ecole Matern. Communale",
    "wof:placetype":"venue"
},
  "geometry": {"coordinates":[4.017095089,50.6877746582],"type":"Point"}
}