{
  "type": "Feature",
  "properties": {
    "iso:country":"BE",
    "sg:address":"Neerstraat 128",
    "sg:city":"Hamme",
    "sg:classifiers":[
        {
            "category":"Professional",
            "type":"Services"
        }
    ],
    "sg:phone":"+32 52 48 44 68",
    "sg:postcode":"9220",
    "sg:province":"Oost-Vlaanderen",
    "sg:tags":[
        "entertainer"
    ],
    "wof:name":"Surprise Music",
    "wof:placetype":"venue"
},
  "geometry": {"coordinates":[4.1445269585,51.0792198181],"type":"Point"}
}