{
  "type": "Feature",
  "properties": {
    "addr:full":"Rue Des Pinsonniers 31 Thimister-clermont (thimister) Li\u00e8ge 4890",
    "addr:housenumber":"31",
    "addr:postcode":"4890",
    "addr:street":"Rue Des Pinsonniers",
    "iso:country":"BE",
    "sg:address":"Rue Des Pinsonniers 31",
    "sg:city":"Thimister-clermont (thimister)",
    "sg:classifiers":[
        {
            "category":"Building & Trades",
            "subcategory":"Electrical",
            "type":"Services"
        }
    ],
    "sg:phone":"+32 87 44 53 43",
    "sg:postcode":"4890",
    "sg:province":"Li\u00e8ge",
    "sg:tags":[
        "electric",
        "-",
        "housewiring",
        "contractor"
    ],
    "wof:name":"Jacob J",
    "wof:placetype":"venue"
},
  "geometry": {"coordinates":[5.8419132233,50.667755127],"type":"Point"}
}