{
  "type": "Feature",
  "properties": {
    "iso:country":"BE",
    "sg:address":"Rue Du Marais 320",
    "sg:city":"Tournai",
    "sg:orig_category":"Rundveehouders",
    "sg:phone":"+32 69 54 62 91",
    "sg:postcode":"7531",
    "sg:province":"Hainaut",
    "wof:name":"Ghislain Delhaye",
    "wof:placetype":"venue"
},
  "geometry": {"coordinates":[3.4616699219,50.6152877808],"type":"Point"}
}