{
  "type": "Feature",
  "properties": {
    "addr:full":"Hondschotestraat 98 Wevelgem (gullegem) West-Vlaanderen 8560",
    "addr:housenumber":"98",
    "addr:postcode":"8560",
    "addr:street":"Hondschotestraat",
    "iso:country":"BE",
    "sg:address":"Hondschotestraat 98",
    "sg:city":"Wevelgem (gullegem)",
    "sg:classifiers":[
        {
            "category":"Retail",
            "subcategory":"Auto Repair",
            "type":"Services"
        }
    ],
    "sg:phone":"+32 56 42 51 23",
    "sg:postcode":"8560",
    "sg:province":"West-Vlaanderen",
    "sg:tags":[
        "truck-body"
    ],
    "wof:name":"Hanssens Jan Carrosserie",
    "wof:placetype":"venue"
},
  "geometry": {"coordinates":[3.1909201145,50.8445014954],"type":"Point"}
}