{
  "type": "Feature",
  "properties": {
    "iso:country":"BE",
    "sg:address":"Heilig Bloedlaan 246",
    "sg:city":"Hoogstraten",
    "sg:orig_category":"Eclairage et \u00e9quipements du foyer. Rev\u00eatements pour sols and murs. Peinture. Rev\u00eatements de sols and",
    "sg:phone":"+32 3 314 48 47",
    "sg:postcode":"2320",
    "sg:province":"Antwerpen",
    "wof:name":"Doms",
    "wof:placetype":"venue"
},
  "geometry": {"coordinates":[4.7584261894,51.3970527649],"type":"Point"}
}