{
  "type": "Feature",
  "properties": {
    "addr:full":"Chauss\u00c9e D'alsemberg 638 Ukkel/uccle Bruxelles-Capitale 1180",
    "addr:housenumber":"638",
    "addr:postcode":"1180",
    "addr:street":"Chausse\u0301E D'Alsemberg;/",
    "iso:country":"BE",
    "sg:address":"Chauss\u00c9e D'alsemberg 638",
    "sg:city":"Ukkel/uccle",
    "sg:orig_category":"Entretien and r\u00e9parations de voitures",
    "sg:phone":"+32 2 346 40 94",
    "sg:postcode":"1180",
    "sg:province":"Bruxelles-Capitale",
    "wof:name":"Nicosia Fr\u00c8res",
    "wof:placetype":"venue"
},
  "geometry": {"coordinates":[4.3369688988,50.8042488098],"type":"Point"}
}