{
  "type": "Feature",
  "properties": {
    "addr:full":"Dries 7 Bruxelles (watermael-boitsfort) Bruxelles-Capitale 1170",
    "addr:housenumber":"7",
    "addr:postcode":"1170",
    "addr:street":"Dries",
    "iso:country":"BE",
    "sg:address":"Dries 7",
    "sg:city":"Bruxelles (watermael-boitsfort)",
    "sg:classifiers":[
        {
            "category":"Professional",
            "subcategory":"Credit Reporting & Collection",
            "type":"Services"
        }
    ],
    "sg:phone":"+32 2 675 38 49",
    "sg:postcode":"1170",
    "sg:province":"Bruxelles-Capitale",
    "sg:tags":[
        "bailiff"
    ],
    "wof:name":"Devosse J-m",
    "wof:placetype":"venue"
},
  "geometry": {"coordinates":[4.3971500397,50.8015518188],"type":"Point"}
}