{
  "type": "Feature",
  "properties": {
    "addr:full":"Merenweg 3 Hoogstraten Antwerpen 2321",
    "addr:housenumber":"3",
    "addr:postcode":"2321",
    "addr:street":"Merenweg",
    "iso:country":"BE",
    "sg:address":"Merenweg 3",
    "sg:city":"Hoogstraten",
    "sg:orig_category":"Varkenskwekers",
    "sg:phone":"+32 3 315 75 81",
    "sg:postcode":"2321",
    "sg:province":"Antwerpen",
    "wof:name":"Marleen Vermeiren",
    "wof:placetype":"venue"
},
  "geometry": {"coordinates":[4.7102432251,51.4465332031],"type":"Point"}
}