{
  "type": "Feature",
  "properties": {
    "addr:full":"Route De L'etat 272 Lasne Brabant Wallon 1380",
    "addr:housenumber":"272",
    "addr:postcode":"1380",
    "addr:street":"Route De L'Etat",
    "iso:country":"BE",
    "sg:address":"Route De L'etat 272",
    "sg:city":"Lasne",
    "sg:orig_category":"Fleurs and plantes",
    "sg:phone":"+32 2 633 63 68",
    "sg:postcode":"1380",
    "sg:province":"Brabant Wallon",
    "wof:name":"Patrick Schauwers",
    "wof:placetype":"venue"
},
  "geometry": {"coordinates":[4.4633312225,50.663269043],"type":"Point"}
}