{
  "type": "Feature",
  "properties": {
    "addr:full":"Waterloose Steenweg 1332 Ukkel/uccle Bruxelles-Capitale 1180",
    "addr:postcode":"1332;1180",
    "addr:street":"Waterloose Steenweg",
    "iso:country":"BE",
    "sg:address":"Waterloose Steenweg 1332",
    "sg:city":"Ukkel/uccle",
    "sg:orig_category":"Dameskledingzaken",
    "sg:phone":"+32 2 375 05 86",
    "sg:postcode":"1180",
    "sg:province":"Bruxelles-Capitale",
    "wof:name":"Maison Vogue",
    "wof:placetype":"venue"
},
  "geometry": {"coordinates":[4.3751330376,50.7903289795],"type":"Point"}
}