{
  "type": "Feature",
  "properties": {
    "addr:full":"Brandstraat 14 Lokeren Oost-Vlaanderen 9160",
    "addr:housenumber":"14",
    "addr:postcode":"9160",
    "addr:street":"Brandstraat",
    "iso:country":"BE",
    "sg:address":"Brandstraat 14",
    "sg:city":"Lokeren",
    "sg:orig_category":"G\u00e2teaux, p\u00e2tisserie and biscuits Fab",
    "sg:phone":"+32 9 340 58 80",
    "sg:postcode":"9160",
    "sg:province":"Oost-Vlaanderen",
    "wof:name":"Corona-lotus",
    "wof:placetype":"venue"
},
  "geometry": {"coordinates":[4.00912714,51.0826797485],"type":"Point"}
}