{
  "type": "Feature",
  "properties": {
    "iso:country":"BE",
    "sg:address":"Chauss\u00e9e De Wavre 214d",
    "sg:city":"Bruxelles (ixelles)",
    "sg:classifiers":[
        {
            "category":"Organizations",
            "subcategory":"Non-profit Organization",
            "type":"Services"
        }
    ],
    "sg:phone":"+32 2 512 00 53",
    "sg:postcode":"1050",
    "sg:province":"Bruxelles-Capitale",
    "sg:tags":[
        "international",
        "organisation"
    ],
    "wof:name":"J.e.f. Jeunes Europeens Federalistes",
    "wof:placetype":"venue"
},
  "geometry": {"coordinates":[4.3725161552,50.8360748291],"type":"Point"}
}