{
  "type": "Feature",
  "properties": {
    "addr:full":"Hoogstraat 22 Oostrozebeke West-Vlaanderen 8780",
    "addr:housenumber":"22",
    "addr:postcode":"8780",
    "addr:street":"Hoogstraat",
    "iso:country":"BE",
    "sg:address":"Hoogstraat 22",
    "sg:city":"Oostrozebeke",
    "sg:orig_category":"Banken and kredietinstellingen",
    "sg:phone":"+32 56 66 64 19",
    "sg:postcode":"8780",
    "sg:province":"West-Vlaanderen",
    "wof:name":"Bbl",
    "wof:placetype":"venue"
},
  "geometry": {"coordinates":[3.3331310749,50.9200172424],"type":"Point"}
}