{
  "type": "Feature",
  "properties": {
    "addr:full":"Victor Driessensstraat 33 Antwerpen Antwerpen 2018",
    "addr:housenumber":"33",
    "addr:postcode":"2018",
    "addr:street":"Victor Driessensstraat",
    "iso:country":"BE",
    "sg:address":"Victor Driessensstraat 33",
    "sg:city":"Antwerpen",
    "sg:classifiers":[
        {
            "category":"Parking",
            "subcategory":"Garage",
            "type":"Transportation"
        }
    ],
    "sg:phone":"+32 3 248 13 77",
    "sg:postcode":"2018",
    "sg:province":"Antwerpen",
    "wof:name":"De Vos-godet Nv",
    "wof:placetype":"venue"
},
  "geometry": {"coordinates":[4.393116951,51.1998710632],"type":"Point"}
}