{
  "type": "Feature",
  "properties": {
    "addr:full":"Verschansingstraat 46 Antwerpen Antwerpen 2000",
    "addr:housenumber":"46",
    "addr:postcode":"2000",
    "addr:street":"Verschansingstraat",
    "iso:country":"BE",
    "sg:address":"Verschansingstraat 46",
    "sg:city":"Antwerpen",
    "sg:orig_category":"Bagage and lederwaren GROENTEN AND FRUIT",
    "sg:phone":"+32 3 216 99 63",
    "sg:postcode":"2000",
    "sg:province":"Antwerpen",
    "wof:name":"Hittimex",
    "wof:placetype":"venue"
},
  "geometry": {"coordinates":[4.3899049759,51.2083778381],"type":"Point"}
}