{
  "type": "Feature",
  "properties": {
    "addr:full":". Etalle (groot) Luxembourg 6740",
    "addr:postcode":"6740",
    "addr:street":"Groot Luxembourg",
    "iso:country":"BE",
    "sg:address":".",
    "sg:city":"Etalle (groot)",
    "sg:orig_category":"Apotheken",
    "sg:phone":"+32 900 10 500",
    "sg:postcode":"6740",
    "sg:province":"Luxembourg",
    "wof:name":"Apothekers Van Wacht",
    "wof:placetype":"venue"
},
  "geometry": {"coordinates":[5.6007847786,49.6738510132],"type":"Point"}
}