{
  "type": "Feature",
  "properties": {
    "addr:full":"Fosselstraat 126 Affligem Vlaams-Brabant 1790",
    "addr:housenumber":"126",
    "addr:postcode":"1790",
    "addr:street":"Fosselstraat",
    "iso:country":"BE",
    "sg:address":"Fosselstraat 126",
    "sg:city":"Affligem",
    "sg:orig_category":"Royal Canin Verhuur voertuigen behalve auto's",
    "sg:phone":"+32 53 66 96 39",
    "sg:postcode":"1790",
    "sg:province":"Vlaams-Brabant",
    "wof:name":"De Brandt Patrick",
    "wof:placetype":"venue"
},
  "geometry": {"coordinates":[4.1097898483,50.9095649719],"type":"Point"}
}