{
  "type": "Feature",
  "properties": {
    "addr:full":"Hoogstraat 170 As Limburg 3665",
    "addr:housenumber":"170",
    "addr:postcode":"3665",
    "addr:street":"Hoogstraat",
    "iso:country":"BE",
    "sg:address":"Hoogstraat 170",
    "sg:city":"As",
    "sg:classifiers":[
        {
            "category":"Shopping",
            "subcategory":"Clothing, Apparel, & Fashions",
            "type":"Retail Goods"
        }
    ],
    "sg:phone":"+32 89 65 70 68",
    "sg:postcode":"3665",
    "sg:province":"Limburg",
    "sg:tags":[
        "lady",
        "clothing",
        "-"
    ],
    "wof:name":"Berghs",
    "wof:placetype":"venue"
},
  "geometry": {"coordinates":[5.593334198,51.0103492737],"type":"Point"}
}