{
  "type": "Feature",
  "properties": {
    "iso:country":"BE",
    "sg:address":"Herentalse Steenweg 65a",
    "sg:city":"Grobbendonk",
    "sg:classifiers":[
        {
            "category":"Home & Garden",
            "subcategory":"Building Materials",
            "type":"Retail Goods"
        }
    ],
    "sg:phone":"+32 14 51 33 23",
    "sg:postcode":"2280",
    "sg:province":"Antwerpen",
    "sg:tags":[
        "granite",
        "stone",
        "natural",
        "marble"
    ],
    "wof:name":"I.s.t.i. Bvba",
    "wof:placetype":"venue"
},
  "geometry": {"coordinates":[4.7788009644,51.1761360168],"type":"Point"}
}