{
  "type": "Feature",
  "properties": {
    "iso:country":"BE",
    "sg:address":"Rijselstraat 31",
    "sg:city":"Brugge (sint-michiels)",
    "sg:classifiers":[
        {
            "category":"Utilities",
            "subcategory":"Mobile Phone",
            "type":"Services"
        }
    ],
    "sg:phone":"+32 50 40 04 95",
    "sg:postcode":"8200",
    "sg:province":"West-Vlaanderen",
    "sg:tags":[
        "-",
        "gsm"
    ],
    "wof:name":"Teleboetiek Brugge St-michiels",
    "wof:placetype":"venue"
},
  "geometry": {"coordinates":[3.2122321129,51.1901092529],"type":"Point"}
}