{
  "type": "Feature",
  "properties": {
    "iso:country":"BE",
    "sg:address":"Place De Nimy 212bc",
    "sg:city":"Mons",
    "sg:orig_category":"Laboratoires photographiques. Studios photographiques",
    "sg:phone":"+32 65 36 40 49",
    "sg:postcode":"7020",
    "sg:province":"Hainaut",
    "wof:name":"Labo Photo Prodia",
    "wof:placetype":"venue"
},
  "geometry": {"coordinates":[3.9553449154,50.4761772156],"type":"Point"}
}