{
  "type": "Feature",
  "properties": {
    "addr:full":"Heuvelstraat 58-60 Boechout Antwerpen 2530",
    "addr:housenumber":"58-60",
    "addr:postcode":"2530",
    "addr:street":"Heuvelstraat",
    "iso:country":"BE",
    "sg:address":"Heuvelstraat 58-60",
    "sg:city":"Boechout",
    "sg:classifiers":[
        {
            "category":"Real Estate",
            "subcategory":"Architect",
            "type":"Services"
        }
    ],
    "sg:phone":"+32 3 455 72 69",
    "sg:postcode":"2530",
    "sg:province":"Antwerpen",
    "wof:name":"Architektenbureau Saldien T Bvba",
    "wof:placetype":"venue"
},
  "geometry": {"coordinates":[4.4916238785,51.1622276306],"type":"Point"}
}