{
  "type": "Feature",
  "properties": {
    "addr:full":"Rue Du Parc 24 Eghezee Namur 5310",
    "addr:housenumber":"24",
    "addr:postcode":"5310",
    "addr:street":"Rue Du Parc;Namur",
    "iso:country":"BE",
    "sg:address":"Rue Du Parc 24",
    "sg:city":"Eghezee",
    "sg:orig_category":"Elektrische installaties voor woningen Industri\u00eble elektrische installaties",
    "sg:phone":"+32 81 85 53 66",
    "sg:postcode":"5310",
    "sg:province":"Namur",
    "wof:name":"St-moulin Jean-beno\u00cet",
    "wof:placetype":"venue"
},
  "geometry": {"coordinates":[4.9577960968,50.618396759],"type":"Point"}
}