{
  "type": "Feature",
  "properties": {
    "iso:country":"BE",
    "sg:address":"Route De Florennes 15",
    "sg:city":"Gerpinnes",
    "sg:orig_category":"Installation \u00e9lectrique industrielle. Installation \u00e9lectrique r\u00e9sidentielle",
    "sg:phone":"+32 71 50 53 63",
    "sg:postcode":"6280",
    "sg:province":"Hainaut",
    "wof:name":"Rouge",
    "wof:placetype":"venue"
},
  "geometry": {"coordinates":[4.5345301628,50.3199882507],"type":"Point"}
}