{
  "type": "Feature",
  "properties": {
    "addr:full":"Rue Des Balkans 7 Bruxelles (uccle) Bruxelles-Capitale 1180",
    "addr:housenumber":"7",
    "addr:postcode":"1180",
    "addr:street":"Rue Des Balkans",
    "iso:country":"BE",
    "sg:address":"Rue Des Balkans 7",
    "sg:city":"Bruxelles (uccle)",
    "sg:classifiers":[
        {
            "category":"Health Services",
            "subcategory":"Health Practitioner",
            "type":"Services"
        }
    ],
    "sg:phone":"+32 2 347 03 57",
    "sg:postcode":"1180",
    "sg:province":"Bruxelles-Capitale",
    "sg:tags":[
        "physiotherapist"
    ],
    "wof:name":"Berliner Sophie",
    "wof:placetype":"venue"
},
  "geometry": {"coordinates":[4.3432059288,50.809173584],"type":"Point"}
}