{
  "type": "Feature",
  "properties": {
    "iso:country":"BE",
    "sg:address":"Perspectieflaan 23",
    "sg:city":"Sint-pieters-woluwe/woluwe-saint-pierre",
    "sg:orig_category":"Schoonmaakbedrijven and ongediertebestrijding",
    "sg:phone":"+32 2 772 01 18",
    "sg:postcode":"1150",
    "sg:province":"Bruxelles-Capitale",
    "wof:name":"Entreprise De Nettoyage Huppertz",
    "wof:placetype":"venue"
},
  "geometry": {"coordinates":[4.4605269432,50.8445968628],"type":"Point"}
}