{
  "type": "Feature",
  "properties": {
    "iso:country":"BE",
    "sg:address":"Martelaarsplein 22",
    "sg:city":"Brussel/bruxelles",
    "sg:orig_category":"Zalen voor culturele evenementen",
    "sg:phone":"+32 2 227 50 02",
    "sg:postcode":"1000",
    "sg:province":"Bruxelles-Capitale",
    "wof:name":"Compagnie Point Zero",
    "wof:placetype":"venue"
},
  "geometry": {"coordinates":[4.3560757637,50.8520126343],"type":"Point"}
}