{
  "type": "Feature",
  "properties": {
    "iso:country":"BE",
    "sg:address":"Baan Naar Bree 114",
    "sg:city":"Peer",
    "sg:classifiers":[
        {
            "category":"Retail",
            "subcategory":"Auto Repair",
            "type":"Services"
        }
    ],
    "sg:phone":"+32 11 63 13 76",
    "sg:postcode":"3990",
    "sg:province":"Limburg",
    "sg:tags":[
        "garage"
    ],
    "wof:name":"Albert",
    "wof:placetype":"venue"
},
  "geometry": {"coordinates":[5.4739041328,51.1337165833],"type":"Point"}
}