{
  "type": "Feature",
  "properties": {
    "addr:full":"Sint-jansstraat 72 Staden West-Vlaanderen 8840",
    "addr:housenumber":"72",
    "addr:postcode":"8840",
    "addr:street":"Sint-Jansstraat",
    "iso:country":"BE",
    "sg:address":"Sint-jansstraat 72",
    "sg:city":"Staden",
    "sg:orig_category":"Meubles D\u00e9taillants, Am\u00e9nagement de B\u00e2timents et de Cuisines. Installation de menuiserie en bois and",
    "sg:phone":"+32 51 70 20 79",
    "sg:postcode":"8840",
    "sg:province":"West-Vlaanderen",
    "wof:name":"Geert Gouwy",
    "wof:placetype":"venue"
},
  "geometry": {"coordinates":[3.0156478882,50.9737434387],"type":"Point"}
}