{
  "type": "Feature",
  "properties": {
    "iso:country":"BE",
    "sg:address":"Avenue Des Combattants 83",
    "sg:city":"Court-saint-etienne",
    "sg:classifiers":[
        {
            "category":"Banks & Credit Unions",
            "subcategory":"Investment Brokerage",
            "type":"Services"
        }
    ],
    "sg:phone":"+32 10 61 63 07",
    "sg:postcode":"1490",
    "sg:province":"Brabant Wallon",
    "sg:tags":[
        "fence"
    ],
    "wof:name":"Alfa Doorway & Fourniture",
    "wof:placetype":"venue"
},
  "geometry": {"coordinates":[4.5630779266,50.647731781],"type":"Point"}
}