{
  "type": "Feature",
  "properties": {
    "iso:country":"BE",
    "sg:address":"Torhoutsesteenweg 168",
    "sg:city":"Zedelgem",
    "sg:orig_category":"RESTAURANTS: RESTAURANTS LIVRAISON \u00c0 DOMICILE. SALLES DE CONF\u00c9RENCES AND DE R\u00c9CEPTIONS. CATERING AND",
    "sg:phone":"+32 50 20 01 97",
    "sg:postcode":"8210",
    "sg:province":"West-Vlaanderen",
    "wof:name":"Restaurant Ter Leepe",
    "wof:placetype":"venue"
},
  "geometry": {"coordinates":[3.1576468945,51.1365127563],"type":"Point"}
}