{
  "type": "Feature",
  "properties": {
    "addr:full":"Solleveld 12 Herzele Oost-Vlaanderen 9550",
    "addr:housenumber":"12",
    "addr:postcode":"9550",
    "addr:street":"Solleveld;Oost-Vlaanderen",
    "iso:country":"BE",
    "sg:address":"Solleveld 12",
    "sg:city":"Herzele",
    "sg:classifiers":[
        {
            "category":"Health Services",
            "subcategory":"Dentist",
            "type":"Services"
        }
    ],
    "sg:phone":"+32 53 62 70 59",
    "sg:postcode":"9550",
    "sg:province":"Oost-Vlaanderen",
    "wof:name":"Van Liedekerke M",
    "wof:placetype":"venue"
},
  "geometry": {"coordinates":[3.8886630535,50.8823623657],"type":"Point"}
}