{
  "type": "Feature",
  "properties": {
    "iso:country":"BE",
    "sg:address":"Av. G\u00c9ner. Med. Derache 49",
    "sg:city":"Elsene/ixelles",
    "sg:orig_category":"M\u00e9decins and sp\u00e9cialistes",
    "sg:phone":"+32 2 649 55 96",
    "sg:postcode":"1050",
    "sg:province":"Bruxelles-Capitale",
    "wof:name":"Jacques Ramaekers",
    "wof:placetype":"venue"
},
  "geometry": {"coordinates":[4.3864498138,50.8161239624],"type":"Point"}
}