{
  "type": "Feature",
  "properties": {
    "addr:full":"Hoogleedsesteenweg 192 Roeselare West-Vlaanderen 8800",
    "addr:housenumber":"192",
    "addr:postcode":"8800",
    "addr:street":"Hoogleedsesteenweg",
    "iso:country":"BE",
    "sg:address":"Hoogleedsesteenweg 192",
    "sg:city":"Roeselare",
    "sg:classifiers":[
        {
            "category":"Building & Trades",
            "subcategory":"Landscaping Services",
            "type":"Services"
        }
    ],
    "sg:phone":"+32 51 22 32 32",
    "sg:postcode":"8800",
    "sg:province":"West-Vlaanderen",
    "sg:tags":[
        "gardening",
        "garden",
        "maintenance"
    ],
    "wof:name":"Deceuninck L",
    "wof:placetype":"venue"
},
  "geometry": {"coordinates":[3.1133620739,50.9549865723],"type":"Point"}
}