{
  "type": "Feature",
  "properties": {
    "addr:full":"Ridder Walter Van Havrelaan 115-12 Schoten Antwerpen 2900",
    "addr:postcode":"115-12;2900",
    "addr:street":"Ridder Walter Van Havrelaan",
    "iso:country":"BE",
    "sg:address":"Ridder Walter Van Havrelaan 115-12",
    "sg:city":"Schoten",
    "sg:classifiers":[
        {
            "category":"Home & Garden",
            "subcategory":"Kitchen Supply",
            "type":"Retail Goods"
        }
    ],
    "sg:phone":"+32 3 658 25 26",
    "sg:postcode":"2900",
    "sg:province":"Antwerpen",
    "sg:tags":[
        "installation"
    ],
    "wof:name":"Siematic Belgi\u00eb Comm.",
    "wof:placetype":"venue"
},
  "geometry": {"coordinates":[4.4922881126,51.2542152405],"type":"Point"}
}