{
  "type": "Feature",
  "properties": {
    "iso:country":"BE",
    "sg:address":"Rue De La Bruy\u00e8re 16",
    "sg:city":"Braine L'alleud (lillois-witterz\u00e9e)",
    "sg:orig_category":"Non-Classified Establishments",
    "sg:phone":"+32 2 384 01 51",
    "sg:postcode":"1428",
    "sg:province":"Brabant Wallon",
    "wof:name":"Trebor",
    "wof:placetype":"venue"
},
  "geometry": {"coordinates":[-0.643862009,47.3907432556],"type":"Point"}
}