{
  "type": "Feature",
  "properties": {
    "addr:full":"Avenue Georges Henri 294 Sint-lambrechts-woluwe/woluwe-saint-lambert Bruxelles-Capitale 1200",
    "addr:housenumber":"294;/",
    "addr:postcode":"1200",
    "addr:street":"Avenue Georges Henri;Sint-Lambrechts-Woluwe",
    "iso:country":"BE",
    "sg:address":"Avenue Georges Henri 294",
    "sg:city":"Sint-lambrechts-woluwe/woluwe-saint-lambert",
    "sg:classifiers":[
        {
            "category":"Restaurant",
            "type":"Food & Drink"
        }
    ],
    "sg:phone":"+32 2 733 00 63",
    "sg:postcode":"1200",
    "sg:province":"Bruxelles-Capitale",
    "wof:name":"Restaurant Al Carso",
    "wof:placetype":"venue"
},
  "geometry": {"coordinates":[4.4108982086,50.8435707092],"type":"Point"}
}