{
  "type": "Feature",
  "properties": {
    "addr:full":"Rue D'arlon 220 Messancy Luxembourg 6780",
    "addr:housenumber":"220",
    "addr:postcode":"6780",
    "addr:street":"Rue D'Arlon",
    "iso:country":"BE",
    "sg:address":"Rue D'arlon 220",
    "sg:city":"Messancy",
    "sg:classifiers":[
        {
            "category":"Shopping",
            "subcategory":"Clothing, Apparel, & Fashions",
            "type":"Retail Goods"
        }
    ],
    "sg:phone":"+32 63 38 59 70",
    "sg:postcode":"6780",
    "sg:province":"Luxembourg",
    "sg:tags":[
        "lingerie",
        "sous-v\u00eatements"
    ],
    "wof:name":"Maison Charmes & Passions",
    "wof:placetype":"venue"
},
  "geometry": {"coordinates":[5.812169075,49.6142578125],"type":"Point"}
}