{
  "type": "Feature",
  "properties": {
    "addr:full":"Kosterijstraat 30 Kontich Antwerpen 2550",
    "addr:housenumber":"30",
    "addr:postcode":"2550",
    "addr:street":"Kosterijstraat",
    "iso:country":"BE",
    "sg:address":"Kosterijstraat 30",
    "sg:city":"Kontich",
    "sg:orig_category":"Experts-comptables",
    "sg:phone":"+32 3 457 34 98",
    "sg:postcode":"2550",
    "sg:province":"Antwerpen",
    "wof:name":"Yves Vuylsteke De Laps",
    "wof:placetype":"venue"
},
  "geometry": {"coordinates":[4.4544382095,51.1359519958],"type":"Point"}
}