{
  "type": "Feature",
  "properties": {
    "iso:country":"BE",
    "sg:address":"Rue Des Bas Sarts 192",
    "sg:city":"Seraing",
    "sg:classifiers":[
        {
            "category":"Health Services",
            "subcategory":"Dentist",
            "type":"Services"
        }
    ],
    "sg:phone":"+32 4 385 10 15",
    "sg:postcode":"4100",
    "sg:province":"Li\u00e8ge",
    "wof:name":"Soumoy Bernard",
    "wof:placetype":"venue"
},
  "geometry": {"coordinates":[5.4923400879,50.5948219299],"type":"Point"}
}