{
  "type": "Feature",
  "properties": {
    "addr:full":"Rue De Profondrieux 8b10 Seneffe Hainaut 7180",
    "addr:housenumber":"8b10",
    "addr:postcode":"7180",
    "addr:street":"Rue De Profondrieux",
    "iso:country":"BE",
    "sg:address":"Rue De Profondrieux 8b10",
    "sg:city":"Seneffe",
    "sg:classifiers":[
        {
            "category":"Sports & Exercise",
            "subcategory":"Sports Center",
            "type":"Entertainment"
        }
    ],
    "sg:phone":"+32 64 54 18 91",
    "sg:postcode":"7180",
    "sg:province":"Hainaut",
    "sg:tags":[
        "terrain",
        "hors",
        "de",
        "installation",
        "sportifs"
    ],
    "wof:name":"G. Ducos",
    "wof:placetype":"venue"
},
  "geometry": {"coordinates":[4.2879290581,50.5346374512],"type":"Point"}
}