{
  "type": "Feature",
  "properties": {
    "iso:country":"BE",
    "sg:address":"Rue De L'harmonie 11",
    "sg:city":"Arlon",
    "sg:orig_category":"Postkantoren Verzekeringsmakelaars and experts",
    "sg:phone":"+32 63 22 55 50",
    "sg:postcode":"6700",
    "sg:province":"Luxembourg",
    "wof:name":"La Poste",
    "wof:placetype":"venue"
},
  "geometry": {"coordinates":[5.7699317932,49.6860122681],"type":"Point"}
}