{
  "type": "Feature",
  "properties": {
    "addr:full":"Avenue Jean Sobieski 38 Bruxelles Bruxelles-Capitale 1020",
    "addr:housenumber":"38",
    "addr:postcode":"1020",
    "addr:street":"Avenue Jean Sobieski",
    "iso:country":"BE",
    "sg:address":"Avenue Jean Sobieski 38",
    "sg:city":"Bruxelles",
    "sg:classifiers":[
        {
            "category":"Science Facility",
            "type":"Public Place"
        }
    ],
    "sg:phone":"+32 2 479 19 29",
    "sg:postcode":"1020",
    "sg:province":"Bruxelles-Capitale",
    "sg:tags":[
        "-",
        "management",
        "data",
        "processing"
    ],
    "wof:name":"Siriusconsult Sprl",
    "wof:placetype":"venue"
},
  "geometry": {"coordinates":[4.3445100784,50.8884277344],"type":"Point"}
}