{
  "type": "Feature",
  "properties": {
    "addr:full":"Ziepstraat 17 Maaseik (neeroeteren) Limburg 3680",
    "addr:housenumber":"17",
    "addr:postcode":"3680",
    "addr:street":"Ziepstraat",
    "iso:country":"BE",
    "sg:address":"Ziepstraat 17",
    "sg:city":"Maaseik (neeroeteren)",
    "sg:classifiers":[
        {
            "category":"Manufacturing",
            "subcategory":"Lumber",
            "type":"Manufacturing & Wholesale Goods"
        }
    ],
    "sg:phone":"+32 89 86 44 17",
    "sg:postcode":"3680",
    "sg:province":"Limburg",
    "sg:tags":[
        "timber"
    ],
    "wof:name":"Swennen R",
    "wof:placetype":"venue"
},
  "geometry": {"coordinates":[5.6668519974,51.1144371033],"type":"Point"}
}