{
  "type": "Feature",
  "properties": {
    "addr:full":"Chemin De La Folie 24 Ham-sur-heure-nalinnes (ham-sur-heure) Hainaut 6120",
    "addr:housenumber":"24",
    "addr:postcode":"6120",
    "addr:street":"Chemin De La Folie;Ham-Sur-Heure Hainaut",
    "iso:country":"BE",
    "sg:address":"Chemin De La Folie 24",
    "sg:city":"Ham-sur-heure-nalinnes (ham-sur-heure)",
    "sg:classifiers":[
        {
            "category":"Organizations",
            "subcategory":"Professional Association",
            "type":"Services"
        }
    ],
    "sg:phone":"+32 71 21 56 09",
    "sg:postcode":"6120",
    "sg:province":"Hainaut",
    "sg:tags":[
        "organisation",
        "seminar"
    ],
    "wof:name":"Pr\u00e9 Vert (le)",
    "wof:placetype":"venue"
},
  "geometry": {"coordinates":[4.3872900009,50.3219146729],"type":"Point"}
}