{
  "type": "Feature",
  "properties": {
    "addr:full":"Rue Gabrielle 38 Ukkel/uccle Bruxelles-Capitale 1180",
    "addr:housenumber":"38",
    "addr:postcode":"1180",
    "addr:street":"Rue Gabrielle;/",
    "iso:country":"BE",
    "sg:address":"Rue Gabrielle 38",
    "sg:city":"Ukkel/uccle",
    "sg:orig_category":"Blanchisseries and teintureries",
    "sg:phone":"+32 2 344 79 32",
    "sg:postcode":"1180",
    "sg:province":"Bruxelles-Capitale",
    "wof:name":"Andre Donck",
    "wof:placetype":"venue"
},
  "geometry": {"coordinates":[4.3597230911,50.8141403198],"type":"Point"}
}