{
  "type": "Feature",
  "properties": {
    "addr:full":"Chauss\u00c9e De Bruxelles 458 Ath Hainaut 7822",
    "addr:housenumber":"458",
    "addr:postcode":"7822",
    "addr:street":"Chausse\u0301E De Bruxelles",
    "iso:country":"BE",
    "sg:address":"Chauss\u00c9e De Bruxelles 458",
    "sg:city":"Ath",
    "sg:classifiers":[
        {
            "category":"Autos & Motor Vehicles",
            "subcategory":"Fuel & Gas Station",
            "type":"Retail Goods"
        }
    ],
    "sg:phone":"+32 68 55 13 56",
    "sg:postcode":"7822",
    "sg:province":"Hainaut",
    "sg:tags":[
        "stations-service",
        "carburants"
    ],
    "wof:name":"Fe. Aux Quatre Vents",
    "wof:placetype":"venue"
},
  "geometry": {"coordinates":[3.8858850002,50.6560249329],"type":"Point"}
}