{
  "type": "Feature",
  "properties": {
    "iso:country":"BE",
    "sg:address":"Achterstraat 45",
    "sg:city":"Peer (wijchmaal)",
    "sg:classifiers":[
        {
            "category":"Home & Garden",
            "subcategory":"Carpets & Floor Coverings",
            "type":"Retail Goods"
        }
    ],
    "sg:phone":"+32 11 63 32 81",
    "sg:postcode":"3990",
    "sg:province":"Limburg",
    "sg:tags":[
        "layer",
        "mosaicists"
    ],
    "wof:name":"Cuyvers Jean",
    "wof:placetype":"venue"
},
  "geometry": {"coordinates":[5.4208321571,51.1215515137],"type":"Point"}
}