{
  "type": "Feature",
  "properties": {
    "iso:country":"BE",
    "sg:address":"Rue Du Glatimont 13",
    "sg:city":"Soignies (naast)",
    "sg:classifiers":[
        {
            "category":"Health Services",
            "subcategory":"Health Practitioner",
            "type":"Services"
        }
    ],
    "sg:phone":"+32 67 33 44 21",
    "sg:postcode":"7062",
    "sg:province":"Hainaut",
    "sg:tags":[
        "physiotherapist"
    ],
    "wof:name":"Nicaise Fr\u00e9d\u00e9ric",
    "wof:placetype":"venue"
},
  "geometry": {"coordinates":[4.0996851921,50.5541000366],"type":"Point"}
}