{
  "type": "Feature",
  "properties": {
    "addr:full":"Remy Soetensstraat 6 Jette/jette Bruxelles-Capitale 1090",
    "addr:housenumber":"6",
    "addr:postcode":"1090",
    "addr:street":"Soetensstraat",
    "iso:country":"BE",
    "sg:address":"Remy Soetensstraat 6",
    "sg:city":"Jette/jette",
    "sg:orig_category":"Artiesten and kunstenaars",
    "sg:phone":"+32 2 478 01 83",
    "sg:postcode":"1090",
    "sg:province":"Bruxelles-Capitale",
    "wof:name":"Etienne Matagne",
    "wof:placetype":"venue"
},
  "geometry": {"coordinates":[4.3194317818,50.8852729797],"type":"Point"}
}