{
  "type": "Feature",
  "properties": {
    "iso:country":"BE",
    "sg:address":"Sentier De Montignies 9",
    "sg:city":"Dour (wih\u00e9ries)",
    "sg:classifiers":[
        {
            "category":"Real Estate",
            "subcategory":"Architect",
            "type":"Services"
        }
    ],
    "sg:phone":"+32 65 78 68 76",
    "sg:postcode":"7370",
    "sg:province":"Hainaut",
    "wof:name":"Oreins H",
    "wof:placetype":"venue"
},
  "geometry": {"coordinates":[3.7496750355,50.3810005188],"type":"Point"}
}