{
  "type": "Feature",
  "properties": {
    "iso:country":"BE",
    "sg:address":"Vooruitzichtstraat 42",
    "sg:city":"Hasselt",
    "sg:classifiers":[
        {
            "category":"Wholesale",
            "subcategory":"Books, Periodicals, & Newspapers",
            "type":"Manufacturing & Wholesale Goods"
        }
    ],
    "sg:phone":"+32 11 28 68 68",
    "sg:postcode":"3500",
    "sg:province":"Limburg",
    "sg:tags":[
        "publisher"
    ],
    "wof:name":"Clavis Uitgeverij Bvba",
    "wof:placetype":"venue"
},
  "geometry": {"coordinates":[5.33233881,50.9241027832],"type":"Point"}
}