{
  "type": "Feature",
  "properties": {
    "addr:full":"Chauss\u00e9e Du Roeulx 1108 Mons (havr\u00e9) Hainaut 7021",
    "addr:housenumber":"1108",
    "addr:postcode":"7021",
    "addr:street":"Chausse\u0301E Du Roeulx",
    "iso:country":"BE",
    "sg:address":"Chauss\u00e9e Du Roeulx 1108",
    "sg:city":"Mons (havr\u00e9)",
    "sg:classifiers":[
        {
            "category":"Parking",
            "subcategory":"Lot",
            "type":"Transportation"
        }
    ],
    "sg:phone":"+32 65 87 24 06",
    "sg:postcode":"7021",
    "sg:province":"Hainaut",
    "sg:tags":[
        "parking-places",
        "laying-out"
    ],
    "wof:name":"Hoyas Marcel & Fils Sa",
    "wof:placetype":"venue"
},
  "geometry": {"coordinates":[4.0562500954,50.4683494568],"type":"Point"}
}