{
  "type": "Feature",
  "properties": {
    "addr:full":"Diestersteenweg 15 Sint-truiden Limburg 3800",
    "addr:housenumber":"15",
    "addr:postcode":"3800",
    "addr:street":"Diestersteenweg",
    "iso:country":"BE",
    "sg:address":"Diestersteenweg 15",
    "sg:city":"Sint-truiden",
    "sg:classifiers":[
        {
            "category":"Shopping",
            "subcategory":"Florist",
            "type":"Retail Goods"
        }
    ],
    "sg:phone":"+32 11 68 43 93",
    "sg:postcode":"3800",
    "sg:province":"Limburg",
    "wof:name":"Sint-jozef",
    "wof:placetype":"venue"
},
  "geometry": {"coordinates":[5.1851930618,50.8215675354],"type":"Point"}
}