{
  "type": "Feature",
  "properties": {
    "iso:country":"BE",
    "sg:address":"Kipdorpvest 40-42",
    "sg:city":"Antwerpen",
    "sg:orig_category":"Agences d'exp\u00e9dition. Fruits and l\u00e9gumes Gr",
    "sg:phone":"+32 3 226 40 94",
    "sg:postcode":"2000",
    "sg:province":"Antwerpen",
    "wof:name":"I. & P.",
    "wof:placetype":"venue"
},
  "geometry": {"coordinates":[4.4139318466,51.2178421021],"type":"Point"}
}