{
  "type": "Feature",
  "properties": {
    "addr:full":"Dorpsstraat 38 Brecht Antwerpen 2960",
    "addr:housenumber":"38",
    "addr:postcode":"2960",
    "addr:street":"Dorpsstraat",
    "iso:country":"BE",
    "sg:address":"Dorpsstraat 38",
    "sg:city":"Brecht",
    "sg:orig_category":"Banken and kredietinstellingen",
    "sg:phone":"+32 3 313 44 55",
    "sg:postcode":"2960",
    "sg:province":"Antwerpen",
    "wof:name":"Groep Argenta",
    "wof:placetype":"venue"
},
  "geometry": {"coordinates":[4.6415200233,51.3512115479],"type":"Point"}
}