{
  "type": "Feature",
  "properties": {
    "addr:full":"Korte Hofstraat 49 Houthalen-helchteren Limburg 3530",
    "addr:housenumber":"49",
    "addr:postcode":"3530",
    "addr:street":"Korte Hofstraat",
    "iso:country":"BE",
    "sg:address":"Korte Hofstraat 49",
    "sg:city":"Houthalen-helchteren",
    "sg:orig_category":"Groententeelt",
    "sg:phone":"+32 11 52 37 28",
    "sg:postcode":"3530",
    "sg:province":"Limburg",
    "wof:name":"Kurt Bogaerts",
    "wof:placetype":"venue"
},
  "geometry": {"coordinates":[5.3856940269,51.0262374878],"type":"Point"}
}