{
  "type": "Feature",
  "properties": {
    "addr:full":"Rue Des Deportes 15 Sirault 7990",
    "addr:housenumber":"15",
    "addr:postcode":"7990",
    "addr:street":"Rue Des Deportes",
    "iso:country":"BE",
    "sg:address":"Rue Des Deportes 15",
    "sg:city":"Sirault",
    "sg:classifiers":[
        {
            "category":"Banks & Credit Unions",
            "subcategory":"Bank",
            "type":"Services"
        }
    ],
    "sg:phone":"+32 65 62 07 47",
    "sg:postcode":"7990",
    "wof:name":"Aslk-cger Bank",
    "wof:placetype":"venue"
},
  "geometry": {"coordinates":[170.92332458499999,-43.668258667],"type":"Point"}
}