{
  "type": "Feature",
  "properties": {
    "iso:country":"BE",
    "sg:address":"Plezantstraat 3",
    "sg:city":"Sint-niklaas",
    "sg:classifiers":[
        {
            "category":"Food & Beverages",
            "subcategory":"Specialty",
            "type":"Retail Goods"
        }
    ],
    "sg:phone":"+32 3 778 07 65",
    "sg:postcode":"9100",
    "sg:province":"Oost-Vlaanderen",
    "sg:tags":[
        "health",
        "dietary",
        "-",
        "biological"
    ],
    "wof:name":"Potpourri Natuurcenter",
    "wof:placetype":"venue"
},
  "geometry": {"coordinates":[4.1361699104,51.1661872864],"type":"Point"}
}