{
  "type": "Feature",
  "properties": {
    "iso:country":"BE",
    "sg:address":"Avenue Jeanne 10bb",
    "sg:city":"Elsene/ixelles",
    "sg:classifiers":[
        {
            "category":"Insurance",
            "subcategory":"Life Insurance",
            "type":"Services"
        }
    ],
    "sg:phone":"+32 2 640 86 86",
    "sg:postcode":"1050",
    "sg:province":"Bruxelles-Capitale",
    "sg:tags":[
        "assurance"
    ],
    "wof:name":"Cabinet Inter Assurances",
    "wof:placetype":"venue"
},
  "geometry": {"coordinates":[4.3817329407,50.8158226013],"type":"Point"}
}