{
  "type": "Feature",
  "properties": {
    "addr:full":"Rue Des Augustins 35 Li\u00e8ge 1 Li\u00e8ge 4000",
    "addr:housenumber":"35;1",
    "addr:postcode":"4000",
    "addr:street":"Rue Des Augustins",
    "iso:country":"BE",
    "sg:address":"Rue Des Augustins 35",
    "sg:city":"Li\u00e8ge 1",
    "sg:classifiers":[
        {
            "category":"Arts & Performance",
            "subcategory":"Theater",
            "type":"Entertainment"
        }
    ],
    "sg:phone":"+32 4 223 64 45",
    "sg:postcode":"4000",
    "sg:province":"Li\u00e8ge",
    "sg:tags":[
        "theatrical",
        "agency"
    ],
    "wof:name":"Productions Et Marketing",
    "wof:placetype":"venue"
},
  "geometry": {"coordinates":[5.5655260086,50.6352424622],"type":"Point"}
}