{
  "type": "Feature",
  "properties": {
    "iso:country":"BE",
    "sg:address":"Ave Charles Woeste 280",
    "sg:city":"Jette",
    "sg:classifiers":[
        {
            "category":"Banks & Credit Unions",
            "subcategory":"Bank",
            "type":"Services"
        }
    ],
    "sg:phone":"+32 2 426 52 32",
    "sg:postcode":"1090",
    "sg:province":"Bruxelles-Capitale",
    "wof:name":"G\u00e9n\u00e9rale De Banque Sa",
    "wof:placetype":"venue"
},
  "geometry": {"coordinates":[4.3355669975,50.868309021],"type":"Point"}
}