{
  "type": "Feature",
  "properties": {
    "iso:country":"BE",
    "sg:address":"Witmeerstraat 7",
    "sg:city":"Genk",
    "sg:classifiers":[
        {
            "category":"Government",
            "subcategory":"Department Of Motor Vehicles",
            "type":"Public Place"
        }
    ],
    "sg:phone":"+32 89 30 83 34",
    "sg:postcode":"3600",
    "sg:province":"Limburg",
    "sg:tags":[
        "planing",
        "wood",
        "sawing"
    ],
    "wof:name":"Bollen Bvba",
    "wof:placetype":"venue"
},
  "geometry": {"coordinates":[5.4824299812,50.9296264648],"type":"Point"}
}