{
  "type": "Feature",
  "properties": {
    "addr:full":"Place Rouppe 31 Bruxelles Bruxelles-Capitale 1000",
    "addr:housenumber":"31",
    "addr:postcode":"1000",
    "addr:street":"Place Rouppe",
    "iso:country":"BE",
    "sg:address":"Place Rouppe 31",
    "sg:city":"Bruxelles",
    "sg:classifiers":[
        {
            "category":"Shopping",
            "subcategory":"Books",
            "type":"Retail Goods"
        }
    ],
    "sg:phone":"+32 2 512 96 89",
    "sg:postcode":"1000",
    "sg:province":"Bruxelles-Capitale",
    "sg:tags":[
        "bookseller"
    ],
    "wof:name":"Eliniko",
    "wof:placetype":"venue"
},
  "geometry": {"coordinates":[4.3453149796,50.8427085876],"type":"Point"}
}