{
  "type": "Feature",
  "properties": {
    "iso:country":"BE",
    "sg:address":"Onze-lieve-vrouwemarkt 24",
    "sg:city":"Roeselare",
    "sg:classifiers":[
        {
            "category":"Health Services",
            "subcategory":"Chiropractor",
            "type":"Services"
        }
    ],
    "sg:phone":"+32 51 24 89 81",
    "sg:postcode":"8800",
    "sg:province":"West-Vlaanderen",
    "wof:name":"Bertrand B",
    "wof:placetype":"venue"
},
  "geometry": {"coordinates":[3.1350049973,50.947681427],"type":"Point"}
}