{
  "type": "Feature",
  "properties": {
    "addr:full":"Rue Du Chaffour 2 Paliseul Luxembourg 6850",
    "addr:housenumber":"2",
    "addr:postcode":"6850",
    "addr:street":"Rue Du Chaffour",
    "iso:country":"BE",
    "sg:address":"Rue Du Chaffour 2",
    "sg:city":"Paliseul",
    "sg:classifiers":[
        {
            "category":"Home & Garden",
            "subcategory":"Kitchen Supply",
            "type":"Retail Goods"
        }
    ],
    "sg:phone":"+32 61 53 53 03",
    "sg:postcode":"6850",
    "sg:province":"Luxembourg",
    "sg:tags":[
        "installation"
    ],
    "wof:name":"Pauporte M",
    "wof:placetype":"venue"
},
  "geometry": {"coordinates":[5.133866787,49.9035835266],"type":"Point"}
}