{
  "type": "Feature",
  "properties": {
    "iso:country":"BE",
    "sg:address":"Rue Fonds-de-la-chapelle 8",
    "sg:city":"Florennes",
    "sg:orig_category":"V\u00e9hicules automobiles",
    "sg:phone":"+32 71 68 89 32",
    "sg:postcode":"5620",
    "sg:province":"Namur",
    "wof:name":"Garage Georges Francis",
    "wof:placetype":"venue"
},
  "geometry": {"coordinates":[4.6074171066,50.2536087036],"type":"Point"}
}