{
  "type": "Feature",
  "properties": {
    "iso:country":"BE",
    "sg:address":"Trappenstraat 28",
    "sg:city":"Maasmechelen",
    "sg:classifiers":[
        {
            "category":"Building & Trades",
            "subcategory":"Electrical",
            "type":"Services"
        }
    ],
    "sg:phone":"+32 89 76 55 82",
    "sg:postcode":"3630",
    "sg:province":"Limburg",
    "sg:tags":[
        "electric",
        "-",
        "housewiring",
        "contractor"
    ],
    "wof:name":"Tulleners Jean",
    "wof:placetype":"venue"
},
  "geometry": {"coordinates":[5.7039880753,50.9660224915],"type":"Point"}
}