{
  "type": "Feature",
  "properties": {
    "addr:full":"Oudenhovestraat 10 Zottegem (sint-maria-oudenhove) Oost-Vlaanderen 9620",
    "addr:housenumber":"10",
    "addr:postcode":"9620",
    "addr:street":"Oudenhovestraat",
    "iso:country":"BE",
    "sg:address":"Oudenhovestraat 10",
    "sg:city":"Zottegem (sint-maria-oudenhove)",
    "sg:classifiers":[
        {
            "category":"Personal",
            "subcategory":"Beauty Salon",
            "type":"Services"
        }
    ],
    "sg:phone":"+32 9 361 02 66",
    "sg:postcode":"9620",
    "sg:province":"Oost-Vlaanderen",
    "sg:tags":[
        "lady",
        "-",
        "hairdressing"
    ],
    "wof:name":"Martine",
    "wof:placetype":"venue"
},
  "geometry": {"coordinates":[3.8112111092,50.871181488],"type":"Point"}
}