{
  "type": "Feature",
  "properties": {
    "addr:full":"Rue Albert 25bd Tournai Hainaut 7548",
    "addr:postcode":"7548",
    "addr:street":"Rue Albert 25Bd;Hainaut",
    "iso:country":"BE",
    "sg:address":"Rue Albert 25bd",
    "sg:city":"Tournai",
    "sg:orig_category":"Production and transformation de viande",
    "sg:phone":"+32 69 22 46 32",
    "sg:postcode":"7548",
    "sg:province":"Hainaut",
    "wof:name":"Au Poulet D'or",
    "wof:placetype":"venue"
},
  "geometry": {"coordinates":[3.39032197,50.6253051758],"type":"Point"}
}