{
  "type": "Feature",
  "properties": {
    "iso:country":"BE",
    "sg:address":"Violierstraat 13 Box 3",
    "sg:city":"Antwerpen",
    "sg:classifiers":[
        {
            "category":"Social Services",
            "type":"Services"
        }
    ],
    "sg:phone":"+32 3 232 70 23",
    "sg:postcode":"2060",
    "sg:province":"Antwerpen",
    "wof:name":"Streepje Zon Vzw",
    "wof:placetype":"venue"
},
  "geometry": {"coordinates":[4.4174098969,51.2221183777],"type":"Point"}
}