{
  "type": "Feature",
  "properties": {
    "addr:full":"Rue De L'echauffour\u00e9e 33 Mouscron Hainaut 7700",
    "addr:housenumber":"33",
    "addr:postcode":"7700",
    "addr:street":"Rue De L'Echauffoure \u0301E",
    "iso:country":"BE",
    "sg:address":"Rue De L'echauffour\u00e9e 33",
    "sg:city":"Mouscron",
    "sg:classifiers":[
        {
            "category":"Airport",
            "subcategory":"International",
            "type":"Transportation"
        }
    ],
    "sg:phone":"+32 56 33 01 20",
    "sg:postcode":"7700",
    "sg:province":"Hainaut",
    "sg:tags":[
        "-",
        "transport"
    ],
    "wof:name":"Vanzeveren Transport-transit Sa",
    "wof:placetype":"venue"
},
  "geometry": {"coordinates":[3.1822490692,50.7528762817],"type":"Point"}
}