{
  "type": "Feature",
  "properties": {
    "iso:country":"BE",
    "sg:address":"Olmenstraat 53",
    "sg:city":"Oostkamp",
    "sg:classifiers":[
        {
            "category":"Professional",
            "subcategory":"Art Services",
            "type":"Services"
        }
    ],
    "sg:phone":"+32 50 35 81 93",
    "sg:postcode":"8020",
    "sg:province":"West-Vlaanderen",
    "sg:tags":[
        "-",
        "painter",
        "artist"
    ],
    "wof:name":"De Man R",
    "wof:placetype":"venue"
},
  "geometry": {"coordinates":[3.2427310944,51.1787986755],"type":"Point"}
}