{
  "type": "Feature",
  "properties": {
    "iso:country":"BE",
    "sg:address":"Sloesveldstraat 34",
    "sg:city":"Hoeilaart",
    "sg:orig_category":"Diverse bedrijfsbeheeradviesbureaus",
    "sg:phone":"+32 2 657 55 31",
    "sg:postcode":"1560",
    "sg:province":"Vlaams-Brabant",
    "wof:name":"Development Consulting Group",
    "wof:placetype":"venue"
},
  "geometry": {"coordinates":[4.492166996,50.7640075684],"type":"Point"}
}