{
  "type": "Feature",
  "properties": {
    "iso:country":"BE",
    "sg:address":"Godveerdegemstraat 147",
    "sg:city":"Zottegem",
    "sg:classifiers":[
        {
            "category":"Insurance",
            "subcategory":"Insurance Agent",
            "type":"Services"
        }
    ],
    "sg:phone":"+32 9 361 35 20",
    "sg:postcode":"9620",
    "sg:province":"Oost-Vlaanderen",
    "sg:tags":[
        "verzekeringsmakelaars",
        "expert"
    ],
    "wof:name":"Zakenkantoor De Loor",
    "wof:placetype":"venue"
},
  "geometry": {"coordinates":[3.8229849339,50.8641319275],"type":"Point"}
}