{
  "type": "Feature",
  "properties": {
    "iso:country":"BE",
    "sg:address":"Rue Waelhem 68",
    "sg:city":"Bruxelles (schaerbeek)",
    "sg:classifiers":[
        {
            "category":"Building & Trades",
            "subcategory":"Construction",
            "type":"Services"
        }
    ],
    "sg:phone":"+32 2 247 39 20",
    "sg:postcode":"1030",
    "sg:province":"Bruxelles-Capitale",
    "sg:tags":[
        "carpenter"
    ],
    "wof:name":"Loftware",
    "wof:placetype":"venue"
},
  "geometry": {"coordinates":[4.3794617653,50.8707504272],"type":"Point"}
}