{
  "type": "Feature",
  "properties": {
    "addr:full":"Rue Du Fort 42 Namur Namur 5024",
    "addr:housenumber":"42",
    "addr:postcode":"5024",
    "addr:street":"Rue Du Fort",
    "iso:country":"BE",
    "sg:address":"Rue Du Fort 42",
    "sg:city":"Namur",
    "sg:classifiers":[
        {
            "category":"Taxi",
            "type":"Transportation"
        }
    ],
    "sg:phone":"+32 81 47 01 51",
    "sg:postcode":"5024",
    "sg:province":"Namur",
    "wof:name":"Taxi Economic's",
    "wof:placetype":"venue"
},
  "geometry": {"coordinates":[4.9728078842,50.493221283],"type":"Point"}
}