{
  "type": "Feature",
  "properties": {
    "addr:full":"Vennestraat 27 Waregem West-Vlaanderen 8790",
    "addr:housenumber":"27",
    "addr:postcode":"8790",
    "addr:street":"Vennestraat",
    "iso:country":"BE",
    "sg:address":"Vennestraat 27",
    "sg:city":"Waregem",
    "sg:classifiers":[
        {
            "category":"Personal",
            "subcategory":"Beauty Salon",
            "type":"Services"
        }
    ],
    "sg:phone":"+32 56 60 08 22",
    "sg:postcode":"8790",
    "sg:province":"West-Vlaanderen",
    "sg:tags":[
        "lady",
        "-",
        "hairdressing"
    ],
    "wof:name":"Hair-studio Line",
    "wof:placetype":"venue"
},
  "geometry": {"coordinates":[3.4240560532,50.8855361938],"type":"Point"}
}