{
  "type": "Feature",
  "properties": {
    "addr:full":"Weversstraat 11 Gent Oost-Vlaanderen 9000",
    "addr:housenumber":"11",
    "addr:postcode":"9000",
    "addr:street":"Weversstraat;Oost-Vlaanderen",
    "iso:country":"BE",
    "sg:address":"Weversstraat 11",
    "sg:city":"Gent",
    "sg:orig_category":"Elektrische installaties voor woningen",
    "sg:phone":"+32 9 226 77 09",
    "sg:postcode":"9000",
    "sg:province":"Oost-Vlaanderen",
    "wof:name":"Lucien Berteloot",
    "wof:placetype":"venue"
},
  "geometry": {"coordinates":[3.7039809227,51.0586051941],"type":"Point"}
}