{
  "type": "Feature",
  "properties": {
    "addr:full":"Generaal Eisenhowerstraat 56 Kuurne West-Vlaanderen 8520",
    "addr:housenumber":"56",
    "addr:postcode":"8520",
    "addr:street":"Generaal Eisenhowerstraat",
    "iso:country":"BE",
    "sg:address":"Generaal Eisenhowerstraat 56",
    "sg:city":"Kuurne",
    "sg:classifiers":[
        {
            "category":"Food & Beverages",
            "subcategory":"Supermarket",
            "type":"Retail Goods"
        }
    ],
    "sg:phone":"+32 56 70 22 42",
    "sg:postcode":"8520",
    "sg:province":"West-Vlaanderen",
    "sg:tags":[
        "department",
        "store"
    ],
    "wof:name":"Spar Supermarkt",
    "wof:placetype":"venue"
},
  "geometry": {"coordinates":[3.284252882,50.8490905762],"type":"Point"}
}