{
  "type": "Feature",
  "properties": {
    "addr:full":"Steenweg Op Turnhout 20 Oud-turnhout Antwerpen 2360",
    "addr:housenumber":"20",
    "addr:postcode":"2360",
    "addr:street":"Steenweg Op Turnhout",
    "iso:country":"BE",
    "sg:address":"Steenweg Op Turnhout 20",
    "sg:city":"Oud-turnhout",
    "sg:classifiers":[
        {
            "category":"Cafe",
            "type":"Food & Drink"
        }
    ],
    "sg:phone":"+32 14 45 39 06",
    "sg:postcode":"2360",
    "sg:province":"Antwerpen",
    "sg:tags":[
        "caf\u00e9s"
    ],
    "wof:name":"Brouwershuis",
    "wof:placetype":"venue"
},
  "geometry": {"coordinates":[4.9799079895,51.3189811707],"type":"Point"}
}