{
  "type": "Feature",
  "properties": {
    "addr:full":"Postbus 133 Lanaken1 Limburg 3620",
    "addr:housenumber":"133",
    "addr:postcode":"lanaken1;3620",
    "addr:street":"Postbus",
    "iso:country":"BE",
    "sg:address":"Postbus 133",
    "sg:city":"Lanaken1",
    "sg:classifiers":[
        {
            "category":"Communications",
            "subcategory":"Radio Station",
            "type":"Services"
        }
    ],
    "sg:phone":"+32 89 72 12 56",
    "sg:postcode":"3620",
    "sg:province":"Limburg",
    "sg:tags":[
        "local"
    ],
    "wof:name":"Maasvallei Radio",
    "wof:placetype":"venue"
},
  "geometry": {"coordinates":[5.6551299095,50.8912200928],"type":"Point"}
}