{
  "type": "Feature",
  "properties": {
    "iso:country":"BE",
    "sg:address":"Avenue Blonden 13",
    "sg:city":"Li\u00e8ge 1",
    "sg:classifiers":[
        {
            "category":"Professional",
            "subcategory":"Lawyer & Legal Services",
            "type":"Services"
        }
    ],
    "sg:phone":"+32 4 252 27 76",
    "sg:postcode":"4000",
    "sg:province":"Li\u00e8ge",
    "wof:name":"Wolf Guy",
    "wof:placetype":"venue"
},
  "geometry": {"coordinates":[5.5698637962,50.6298789978],"type":"Point"}
}