{
  "type": "Feature",
  "properties": {
    "iso:country":"BE",
    "sg:address":"Langstraat 5",
    "sg:city":"Herenthout",
    "sg:classifiers":[
        {
            "category":"Manufacturing",
            "subcategory":"Textiles",
            "type":"Manufacturing & Wholesale Goods"
        }
    ],
    "sg:phone":"+32 14 51 74 00",
    "sg:postcode":"2270",
    "sg:province":"Antwerpen",
    "wof:name":"Maria Vercammen",
    "wof:placetype":"venue"
},
  "geometry": {"coordinates":[4.7606921196,51.1315536499],"type":"Point"}
}