{
  "type": "Feature",
  "properties": {
    "addr:full":"Excelsiorlaan 79-81 Zaventem Vlaams-Brabant 1930",
    "addr:housenumber":"79-81",
    "addr:postcode":"1930",
    "addr:street":"Excelsiorlaan",
    "iso:country":"BE",
    "sg:address":"Excelsiorlaan 79-81",
    "sg:city":"Zaventem",
    "sg:classifiers":[
        {
            "category":"Education",
            "subcategory":"Special Training",
            "type":"Public Place"
        }
    ],
    "sg:phone":"+32 2 720 71 65",
    "sg:postcode":"1930",
    "sg:province":"Vlaams-Brabant",
    "sg:tags":[
        "-",
        "processing",
        "data"
    ],
    "wof:name":"Givi Nv",
    "wof:placetype":"venue"
},
  "geometry": {"coordinates":[4.4542021751,50.8831672668],"type":"Point"}
}