{
  "type": "Feature",
  "properties": {
    "addr:full":"Avenue Eug\u00e8ne Mascaux 558 Charleroi (marcinelle) Hainaut 6001",
    "addr:housenumber":"558",
    "addr:postcode":"6001",
    "addr:street":"Avenue Euge\u0300Ne Mascaux",
    "iso:country":"BE",
    "sg:address":"Avenue Eug\u00e8ne Mascaux 558",
    "sg:city":"Charleroi (marcinelle)",
    "sg:classifiers":[
        {
            "category":"Health Services",
            "subcategory":"Health Practitioner",
            "type":"Services"
        }
    ],
    "sg:phone":"+32 71 36 51 87",
    "sg:postcode":"6001",
    "sg:province":"Hainaut",
    "sg:tags":[
        "physiotherapist"
    ],
    "wof:name":"Fondu B",
    "wof:placetype":"venue"
},
  "geometry": {"coordinates":[4.4318180084,50.3859443665],"type":"Point"}
}