{
  "type": "Feature",
  "properties": {
    "addr:full":"Rue Joseph Francis 17 Wavre Brabant Wallon 1301",
    "addr:housenumber":"17;1301",
    "addr:street":"Rue Joseph Francis",
    "iso:country":"BE",
    "sg:address":"Rue Joseph Francis 17",
    "sg:city":"Wavre",
    "sg:classifiers":[
        {
            "category":"Insurance",
            "subcategory":"Life Insurance",
            "type":"Services"
        }
    ],
    "sg:phone":"+32 10 41 71 09",
    "sg:postcode":"1301",
    "sg:province":"Brabant Wallon",
    "sg:tags":[
        "assurance"
    ],
    "wof:name":"Mignon",
    "wof:placetype":"venue"
},
  "geometry": {"coordinates":[4.5886969566,50.7102851868],"type":"Point"}
}