{
  "type": "Feature",
  "properties": {
    "iso:country":"BE",
    "sg:address":"R Des Cottages 73",
    "sg:city":"Bruxelles",
    "sg:classifiers":[
        {
            "category":"Home & Garden",
            "subcategory":"Furniture",
            "type":"Retail Goods"
        }
    ],
    "sg:phone":"+32 2 343 30 00",
    "sg:postcode":"1180",
    "sg:province":"Bruxelles-Capitale",
    "sg:tags":[
        "household",
        "wood"
    ],
    "wof:name":"Alphonse Coopmans Sprl",
    "wof:placetype":"venue"
},
  "geometry": {"coordinates":[4.3425951004,50.8114433289],"type":"Point"}
}