{
  "type": "Feature",
  "properties": {
    "addr:full":"Chauss\u00c9e De Waterloo 578 Elsene/ixelles Bruxelles-Capitale 1050",
    "addr:housenumber":"578",
    "addr:postcode":"1050",
    "addr:street":"Chausse\u0301E De Waterloo",
    "iso:country":"BE",
    "sg:address":"Chauss\u00c9e De Waterloo 578",
    "sg:city":"Elsene/ixelles",
    "sg:classifiers":[
        {
            "category":"Restaurant",
            "type":"Food & Drink"
        }
    ],
    "sg:phone":"+32 2 346 47 41",
    "sg:postcode":"1050",
    "sg:province":"Bruxelles-Capitale",
    "wof:name":"En Face De Parachute",
    "wof:placetype":"venue"
},
  "geometry": {"coordinates":[4.362929821,50.8185997009],"type":"Point"}
}