{
  "type": "Feature",
  "properties": {
    "iso:country":"BE",
    "sg:address":"Sas 21",
    "sg:city":"Dendermonde",
    "sg:classifiers":[
        {
            "category":"Professional",
            "subcategory":"Accounting & Tax Preparation",
            "type":"Services"
        }
    ],
    "sg:phone":"+32 52 21 82 73",
    "sg:postcode":"9200",
    "sg:province":"Oost-Vlaanderen",
    "sg:tags":[
        "accountant"
    ],
    "wof:name":"Petrus Willems",
    "wof:placetype":"venue"
},
  "geometry": {"coordinates":[4.0946269035,51.0299491882],"type":"Point"}
}