{
  "type": "Feature",
  "properties": {
    "addr:full":"Voskenslaan 33 Genk Limburg 3600",
    "addr:housenumber":"33",
    "addr:postcode":"3600",
    "addr:street":"Voskenslaan",
    "iso:country":"BE",
    "sg:address":"Voskenslaan 33",
    "sg:city":"Genk",
    "sg:classifiers":[
        {
            "category":"Landmark",
            "subcategory":"Scenic View",
            "type":"Public Place"
        }
    ],
    "sg:phone":"+32 89 30 84 24",
    "sg:postcode":"3600",
    "sg:province":"Limburg",
    "sg:tags":[
        "setting",
        "photographic"
    ],
    "wof:name":"Hagi Bvba",
    "wof:placetype":"venue"
},
  "geometry": {"coordinates":[5.5291728973,50.982635498],"type":"Point"}
}