{
  "type": "Feature",
  "properties": {
    "addr:full":"Rue De La Vecqu\u00c9e 414 Seraing Li\u00e8ge 4100",
    "addr:housenumber":"414",
    "addr:postcode":"4100",
    "addr:street":"Rue De La Vecque\u0301E",
    "iso:country":"BE",
    "sg:address":"Rue De La Vecqu\u00c9e 414",
    "sg:city":"Seraing",
    "sg:classifiers":[
        {
            "category":"Manufacturing",
            "subcategory":"Textiles",
            "type":"Manufacturing & Wholesale Goods"
        }
    ],
    "sg:phone":"+32 4 336 51 64",
    "sg:postcode":"4100",
    "sg:province":"Li\u00e8ge",
    "wof:name":"Claude Gielens",
    "wof:placetype":"venue"
},
  "geometry": {"coordinates":[5.5181570053,50.5881004333],"type":"Point"}
}