{
  "type": "Feature",
  "properties": {
    "addr:full":"Chemin D'arville 25 Gesves Namur 5340",
    "addr:housenumber":"25",
    "addr:postcode":"5340",
    "addr:street":"Chemin D'Arville",
    "iso:country":"BE",
    "sg:address":"Chemin D'arville 25",
    "sg:city":"Gesves",
    "sg:orig_category":"Eleveurs de bovins",
    "sg:phone":"+32 81 57 06 87",
    "sg:postcode":"5340",
    "sg:province":"Namur",
    "wof:name":"Henri Rasquin",
    "wof:placetype":"venue"
},
  "geometry": {"coordinates":[4.9955739975,50.4256515503],"type":"Point"}
}