{
  "type": "Feature",
  "properties": {
    "iso:country":"BE",
    "sg:address":"Turnhoutsebaan 190",
    "sg:city":"Malle",
    "sg:orig_category":"Gespecialiseerde residenti\u00eble bouw",
    "sg:phone":"+32 3 312 42 12",
    "sg:postcode":"2390",
    "sg:province":"Antwerpen",
    "wof:name":"Gebrs Van De Mierop",
    "wof:placetype":"venue"
},
  "geometry": {"coordinates":[4.7693271637,51.3015098572],"type":"Point"}
}