{
  "type": "Feature",
  "properties": {
    "addr:full":"Rue Bois Sainte-marie 109 Sambreville Namur 5060",
    "addr:housenumber":"109",
    "addr:postcode":"5060",
    "addr:street":"Rue Bois Sainte-Marie",
    "iso:country":"BE",
    "sg:address":"Rue Bois Sainte-marie 109",
    "sg:city":"Sambreville",
    "sg:orig_category":"Sportclubs Sportterreinen and installaties behalve sportcentra",
    "sg:phone":"+32 71 76 09 72",
    "sg:postcode":"5060",
    "sg:province":"Namur",
    "wof:name":"Union Sarthoise Auvelais",
    "wof:placetype":"venue"
},
  "geometry": {"coordinates":[4.6417150497,50.4526062012],"type":"Point"}
}