{
  "type": "Feature",
  "properties": {
    "addr:full":"Neerveld 9 Kontich Antwerpen 2550",
    "addr:housenumber":"9",
    "addr:postcode":"2550",
    "addr:street":"Neerveld",
    "iso:country":"BE",
    "sg:address":"Neerveld 9",
    "sg:city":"Kontich",
    "sg:orig_category":"Imprimeries and copyshops",
    "sg:phone":"+32 3 457 70 70",
    "sg:postcode":"2550",
    "sg:province":"Antwerpen",
    "wof:name":"Enfa",
    "wof:placetype":"venue"
},
  "geometry": {"coordinates":[4.4527769089,51.1205177307],"type":"Point"}
}