{
  "type": "Feature",
  "properties": {
    "addr:full":"Ravenshout 4 Bedrijf 210 Tessenderlo Limburg 3980",
    "addr:housenumber":"4;210",
    "addr:postcode":"3980",
    "addr:street":"Ravenshout;Bedrijf",
    "iso:country":"BE",
    "sg:address":"Ravenshout 4 Bedrijf 210",
    "sg:city":"Tessenderlo",
    "sg:classifiers":[
        {
            "category":"Manufacturing",
            "subcategory":"Chemicals & Compounds",
            "type":"Manufacturing & Wholesale Goods"
        }
    ],
    "sg:phone":"+32 13 67 05 11",
    "sg:postcode":"3980",
    "sg:province":"Limburg",
    "sg:tags":[
        "pharmaceutical",
        "chemistry",
        "-",
        "by-product"
    ],
    "wof:name":"Ecolab Nv",
    "wof:placetype":"venue"
},
  "geometry": {"coordinates":[5.0875849724,51.0672340393],"type":"Point"}
}