{
  "type": "Feature",
  "properties": {
    "iso:country":"BE",
    "sg:address":"Rue Charles Lejeune 2",
    "sg:city":"Waremme",
    "sg:classifiers":[
        {
            "category":"Social Services",
            "type":"Services"
        }
    ],
    "sg:phone":"+32 19 33 26 11",
    "sg:postcode":"4300",
    "sg:province":"Li\u00e8ge",
    "sg:tags":[
        "handicapped",
        "-"
    ],
    "wof:name":"Long Champ (le)",
    "wof:placetype":"venue"
},
  "geometry": {"coordinates":[5.2562561035,50.6972541809],"type":"Point"}
}