{
  "type": "Feature",
  "properties": {
    "iso:country":"BE",
    "sg:address":"Mechelsesteenweg 107",
    "sg:city":"Hove",
    "sg:orig_category":"Kapsalons",
    "sg:phone":"+32 3 455 91 50",
    "sg:postcode":"2540",
    "sg:province":"Antwerpen",
    "wof:name":"Kreatos",
    "wof:placetype":"venue"
},
  "geometry": {"coordinates":[4.4636540413,51.1511535645],"type":"Point"}
}