{
  "type": "Feature",
  "properties": {
    "addr:full":"Place Albert Ier 21 Anderlues Hainaut 6150",
    "addr:housenumber":"21",
    "addr:postcode":"6150",
    "addr:street":"Place Albert Ier",
    "iso:country":"BE",
    "sg:address":"Place Albert Ier 21",
    "sg:city":"Anderlues",
    "sg:orig_category":"S\u00e9lection de personnel and placement",
    "sg:phone":"+32 71 54 40 07",
    "sg:postcode":"6150",
    "sg:province":"Hainaut",
    "wof:name":"Ale",
    "wof:placetype":"venue"
},
  "geometry": {"coordinates":[4.2712101936,50.4070510864],"type":"Point"}
}