{
  "type": "Feature",
  "properties": {
    "iso:country":"BE",
    "sg:address":"Zavelput 46",
    "sg:city":"Gent (sint-amandsberg)",
    "sg:classifiers":[
        {
            "category":"Building & Trades",
            "subcategory":"Construction",
            "type":"Services"
        }
    ],
    "sg:phone":"+32 9 229 29 01",
    "sg:postcode":"9040",
    "sg:province":"Oost-Vlaanderen",
    "sg:tags":[
        "installation",
        "-",
        "central",
        "heating"
    ],
    "wof:name":"Moreau",
    "wof:placetype":"venue"
},
  "geometry": {"coordinates":[3.7607479095,51.0653381348],"type":"Point"}
}