{
  "type": "Feature",
  "properties": {
    "addr:full":"Jockeystraat 2 Gent Oost-Vlaanderen 9000",
    "addr:housenumber":"2",
    "addr:postcode":"9000",
    "addr:street":"Jockeystraat;Oost-Vlaanderen",
    "iso:country":"BE",
    "sg:address":"Jockeystraat 2",
    "sg:city":"Gent",
    "sg:classifiers":[
        {
            "category":"Health Services",
            "subcategory":"Doctor",
            "type":"Services"
        }
    ],
    "sg:phone":"+32 9 221 82 31",
    "sg:postcode":"9000",
    "sg:province":"Oost-Vlaanderen",
    "sg:tags":[
        "medicinephysicians",
        "surgeon"
    ],
    "wof:name":"Colle Gaston",
    "wof:placetype":"venue"
},
  "geometry": {"coordinates":[3.7088749409,51.0247840881],"type":"Point"}
}