{
  "type": "Feature",
  "properties": {
    "addr:full":"Haut Rejet 1 Celles Hainaut 7760",
    "addr:housenumber":"1",
    "addr:postcode":"7760",
    "addr:street":"Haut Rejet",
    "iso:country":"BE",
    "sg:address":"Haut Rejet 1",
    "sg:city":"Celles",
    "sg:orig_category":"Rundveehouders",
    "sg:phone":"+32 69 85 81 61",
    "sg:postcode":"7760",
    "sg:province":"Hainaut",
    "wof:name":"Degroote Bernard Et Marc",
    "wof:placetype":"venue"
},
  "geometry": {"coordinates":[3.5015349388,50.6843185425],"type":"Point"}
}