{
  "type": "Feature",
  "properties": {
    "iso:country":"BE",
    "sg:address":"Eggestraat 13",
    "sg:city":"Vosselaar",
    "sg:orig_category":"Plomberie, chauffage and installations sanitaires",
    "sg:phone":"+32 477 55 93 25",
    "sg:postcode":"2350",
    "sg:province":"Antwerpen",
    "wof:name":"Ab&c",
    "wof:placetype":"venue"
},
  "geometry": {"coordinates":[4.8912291527,51.3045845032],"type":"Point"}
}