{
  "type": "Feature",
  "properties": {
    "addr:full":"Doornveld 15 Asse (zellik) Vlaams-Brabant 1731",
    "addr:postcode":"1731",
    "addr:street":"Doornveld 15",
    "iso:country":"BE",
    "sg:address":"Doornveld 15",
    "sg:city":"Asse (zellik)",
    "sg:classifiers":[
        {
            "category":"Government",
            "subcategory":"Customs House",
            "type":"Public Place"
        }
    ],
    "sg:phone":"+32 2 466 21 44",
    "sg:postcode":"1731",
    "sg:province":"Vlaams-Brabant",
    "sg:tags":[
        "packing"
    ],
    "wof:name":"Wraping Sprl",
    "wof:placetype":"venue"
},
  "geometry": {"coordinates":[4.2738099098,50.8845901489],"type":"Point"}
}