{
  "type": "Feature",
  "properties": {
    "iso:country":"BE",
    "sg:address":"Rue Des Beguines 42-46",
    "sg:city":"Bruxelles",
    "sg:classifiers":[
        {
            "category":"Autos & Motor Vehicles",
            "subcategory":"Automobile Sales",
            "type":"Retail Goods"
        }
    ],
    "sg:phone":"+32 2 479 02 66",
    "sg:postcode":"1080",
    "sg:province":"Bruxelles-Capitale",
    "sg:tags":[
        "equipment",
        "industrial",
        "transport"
    ],
    "wof:name":"A.d. Depannage Sa",
    "wof:placetype":"venue"
},
  "geometry": {"coordinates":[4.3169960976,50.8574829102],"type":"Point"}
}