{
  "type": "Feature",
  "properties": {
    "addr:full":"Rue De La Station 10 Edingen/enghien Hainaut 7850",
    "addr:housenumber":"10",
    "addr:postcode":"7850",
    "addr:street":"Rue De La Station",
    "iso:country":"BE",
    "sg:address":"Rue De La Station 10",
    "sg:city":"Edingen/enghien",
    "sg:orig_category":"Producteurs de fruits",
    "sg:phone":"+32 2 395 57 10",
    "sg:postcode":"7850",
    "sg:province":"Hainaut",
    "wof:name":"Ronald Vanbiervliet",
    "wof:placetype":"venue"
},
  "geometry": {"coordinates":[4.0439720154,50.6957588196],"type":"Point"}
}