{
  "type": "Feature",
  "properties": {
    "iso:country":"BE",
    "sg:address":"Herentalsebaan 645",
    "sg:city":"Wommelgem",
    "sg:classifiers":[
        {
            "category":"Professional",
            "subcategory":"Computer Services",
            "type":"Services"
        }
    ],
    "sg:phone":"+32 3 354 09 79",
    "sg:postcode":"2160",
    "sg:province":"Antwerpen",
    "sg:tags":[
        "-",
        "processing",
        "data",
        "software"
    ],
    "wof:name":"Smart Solutions Nv",
    "wof:placetype":"venue"
},
  "geometry": {"coordinates":[4.52059412,51.1975784302],"type":"Point"}
}