{
  "type": "Feature",
  "properties": {
    "addr:full":"Hulst 134 Opwijk Vlaams-Brabant 1745",
    "addr:housenumber":"134",
    "addr:postcode":"1745",
    "addr:street":"Hulst",
    "iso:country":"BE",
    "sg:address":"Hulst 134",
    "sg:city":"Opwijk",
    "sg:orig_category":"Salons de coiffure. Producteurs de l\u00e9gumes",
    "sg:phone":"+32 52 35 50 90",
    "sg:postcode":"1745",
    "sg:province":"Vlaams-Brabant",
    "wof:name":"Marleen De Mol",
    "wof:placetype":"venue"
},
  "geometry": {"coordinates":[4.1859779358,50.9596328735],"type":"Point"}
}