{
  "type": "Feature",
  "properties": {
    "addr:full":"Vrombautstraat 21 Eeklo Oost-Vlaanderen 9900",
    "addr:housenumber":"21",
    "addr:postcode":"9900",
    "addr:street":"Vrombautstraat",
    "iso:country":"BE",
    "sg:address":"Vrombautstraat 21",
    "sg:city":"Eeklo",
    "sg:orig_category":"Woningbouw",
    "sg:phone":"+32 9 378 34 60",
    "sg:postcode":"9900",
    "sg:province":"Oost-Vlaanderen",
    "wof:name":"Jean-paul Nuyt",
    "wof:placetype":"venue"
},
  "geometry": {"coordinates":[3.5750160217,51.1921806335],"type":"Point"}
}