{
  "type": "Feature",
  "properties": {
    "addr:full":"Rue Du Centre 13 Sprimont Li\u00e8ge 4140",
    "addr:housenumber":"13",
    "addr:postcode":"4140",
    "addr:street":"Rue Du Centre",
    "iso:country":"BE",
    "sg:address":"Rue Du Centre 13",
    "sg:city":"Sprimont",
    "sg:orig_category":"Banques and organismes de cr\u00e9dit",
    "sg:phone":"+32 4 382 10 15",
    "sg:postcode":"4140",
    "sg:province":"Li\u00e8ge",
    "wof:name":"Bbl",
    "wof:placetype":"venue"
},
  "geometry": {"coordinates":[5.6618537903,50.5042304993],"type":"Point"}
}