{
  "type": "Feature",
  "properties": {
    "addr:full":"Gildestraat 25 Kruibeke Oost-Vlaanderen 9150",
    "addr:housenumber":"25",
    "addr:postcode":"9150",
    "addr:street":"Gildestraat",
    "iso:country":"BE",
    "sg:address":"Gildestraat 25",
    "sg:city":"Kruibeke",
    "sg:orig_category":"Industri\u00eble wasserijen and droogkuis",
    "sg:phone":"+32 3 774 13 14",
    "sg:postcode":"9150",
    "sg:province":"Oost-Vlaanderen",
    "wof:name":"Wasserij Moderna",
    "wof:placetype":"venue"
},
  "geometry": {"coordinates":[4.3126149178,51.1754798889],"type":"Point"}
}