{
  "type": "Feature",
  "properties": {
    "iso:country":"BE",
    "sg:address":"'s Hertogenlaan 48",
    "sg:city":"Leuven",
    "sg:orig_category":"Diverse bedrijfsbeheeradviesbureaus",
    "sg:phone":"+32 16 29 17 49",
    "sg:postcode":"3000",
    "sg:province":"Vlaams-Brabant",
    "wof:name":"Adviesbureau Lowette",
    "wof:placetype":"venue"
},
  "geometry": {"coordinates":[4.6854481697,50.8870277405],"type":"Point"}
}