{
  "type": "Feature",
  "properties": {
    "addr:full":"Rue Jules Destr\u00c9e 243 Quaregnon Hainaut 7390",
    "addr:housenumber":"243",
    "addr:postcode":"7390",
    "addr:street":"Rue Jules Destre\u0301E",
    "iso:country":"BE",
    "sg:address":"Rue Jules Destr\u00c9e 243",
    "sg:city":"Quaregnon",
    "sg:orig_category":"M\u00e9decins and sp\u00e9cialistes",
    "sg:phone":"+32 65 78 40 41",
    "sg:postcode":"7390",
    "sg:province":"Hainaut",
    "wof:name":"P. Lehette",
    "wof:placetype":"venue"
},
  "geometry": {"coordinates":[3.8633890152,50.4442901611],"type":"Point"}
}