{
  "type": "Feature",
  "properties": {
    "addr:full":"Sint-ewoudsstraat 5 Brugge West-Vlaanderen 8200",
    "addr:housenumber":"5",
    "addr:postcode":"8200",
    "addr:street":"Sint-Ewoudsstraat",
    "iso:country":"BE",
    "sg:address":"Sint-ewoudsstraat 5",
    "sg:city":"Brugge",
    "sg:orig_category":"Services de Nettoyage and de D\u00e9sinfection",
    "sg:phone":"+32 50 38 84 71",
    "sg:postcode":"8200",
    "sg:province":"West-Vlaanderen",
    "wof:name":"Jean Knop",
    "wof:placetype":"venue"
},
  "geometry": {"coordinates":[3.2042930126,51.2015151978],"type":"Point"}
}