{
  "type": "Feature",
  "properties": {
    "addr:full":"Dorp 25 Sint-katelijne-waver (onze-lieve-vrouw-waver) Antwerpen 2861",
    "addr:housenumber":"25",
    "addr:postcode":"2861",
    "addr:street":"Dorp",
    "iso:country":"BE",
    "sg:address":"Dorp 25",
    "sg:city":"Sint-katelijne-waver (onze-lieve-vrouw-waver)",
    "sg:classifiers":[
        {
            "category":"Personal",
            "subcategory":"Beauty Salon",
            "type":"Services"
        }
    ],
    "sg:phone":"+32 15 75 59 82",
    "sg:postcode":"2861",
    "sg:province":"Antwerpen",
    "sg:tags":[
        "lady",
        "-",
        "hairdressing"
    ],
    "wof:name":"De Preter-dijck",
    "wof:placetype":"venue"
},
  "geometry": {"coordinates":[4.5801768303,51.0631752014],"type":"Point"}
}