{
  "type": "Feature",
  "properties": {
    "iso:country":"BE",
    "sg:address":"Gentsestraat 94",
    "sg:city":"Harelbeke",
    "sg:orig_category":"Bagage and lederwaren Schoenen",
    "sg:phone":"+32 56 71 00 35",
    "sg:postcode":"8530",
    "sg:province":"West-Vlaanderen",
    "wof:name":"Jean Viaene",
    "wof:placetype":"venue"
},
  "geometry": {"coordinates":[3.3167490959,50.8595123291],"type":"Point"}
}