{
  "type": "Feature",
  "properties": {
    "iso:country":"BE",
    "sg:address":"Montgomerystraat 3",
    "sg:city":"Edingen/enghien",
    "sg:orig_category":"Drukkerijen and copyshops Kantoormateriaal Papierwaren",
    "sg:phone":"+32 2 395 31 88",
    "sg:postcode":"7850",
    "sg:province":"Hainaut",
    "wof:name":"Maison Papyrus",
    "wof:placetype":"venue"
},
  "geometry": {"coordinates":[4.0384778976,50.6933860779],"type":"Point"}
}