{
  "type": "Feature",
  "properties": {
    "addr:full":"Grand'place 4 Soignies Hainaut 7060",
    "addr:housenumber":"4",
    "addr:postcode":"7060",
    "addr:street":"Grand'Place",
    "iso:country":"BE",
    "sg:address":"Grand'place 4",
    "sg:city":"Soignies",
    "sg:classifiers":[
        {
            "category":"Bars & Pubs",
            "type":"Food & Drink"
        }
    ],
    "sg:phone":"+32 67 33 99 44",
    "sg:postcode":"7060",
    "sg:province":"Hainaut",
    "sg:tags":[
        "tavern"
    ],
    "wof:name":"Heaume Du Roy (le)",
    "wof:placetype":"venue"
},
  "geometry": {"coordinates":[4.0699257851,50.5796279907],"type":"Point"}
}