{
  "type": "Feature",
  "properties": {
    "addr:full":"G\u00c9romont 99 Comblain-au-pont Li\u00e8ge 4170",
    "addr:housenumber":"99",
    "addr:postcode":"4170",
    "addr:street":"Ge\u0301Romont",
    "iso:country":"BE",
    "sg:address":"G\u00c9romont 99",
    "sg:city":"Comblain-au-pont",
    "sg:orig_category":"Sportclubs Sportterreinen and installaties behalve sportcentra",
    "sg:phone":"+32 4 369 10 45",
    "sg:postcode":"4170",
    "sg:province":"Li\u00e8ge",
    "wof:name":"R. Mont F.c.",
    "wof:placetype":"venue"
},
  "geometry": {"coordinates":[5.5736298561,50.4693603516],"type":"Point"}
}