{
  "type": "Feature",
  "properties": {
    "addr:full":"Rue Du Pr\u00e9 De La Haye 131 Oupeye Li\u00e8ge 4680",
    "addr:housenumber":"131",
    "addr:postcode":"4680",
    "addr:street":"Rue Du Pre\u0301 De La Haye",
    "iso:country":"BE",
    "sg:address":"Rue Du Pr\u00e9 De La Haye 131",
    "sg:city":"Oupeye",
    "sg:classifiers":[
        {
            "category":"Building & Trades",
            "subcategory":"Electrical",
            "type":"Services"
        }
    ],
    "sg:phone":"+32 4 248 26 51",
    "sg:postcode":"4680",
    "sg:province":"Li\u00e8ge",
    "sg:tags":[
        "electric",
        "-",
        "housewiring",
        "contractor"
    ],
    "wof:name":"Cata Elec Constructions Sprl",
    "wof:placetype":"venue"
},
  "geometry": {"coordinates":[5.6411581039,50.7033500671],"type":"Point"}
}