{
  "type": "Feature",
  "properties": {
    "addr:full":"Rue Saint-jean 4 Arlon Luxembourg 6700",
    "addr:housenumber":"4",
    "addr:postcode":"6700",
    "addr:street":"Rue Saint-Jean",
    "iso:country":"BE",
    "sg:address":"Rue Saint-jean 4",
    "sg:city":"Arlon",
    "sg:orig_category":"Fitnesscentra",
    "sg:phone":"+32 63 21 81 75",
    "sg:postcode":"6700",
    "sg:province":"Luxembourg",
    "wof:name":"Athletic Center",
    "wof:placetype":"venue"
},
  "geometry": {"coordinates":[5.8171901703,49.6829605103],"type":"Point"}
}