{
  "type": "Feature",
  "properties": {
    "addr:full":"Bollisstraat 11 Peer (wijchmaal) Limburg 3990",
    "addr:housenumber":"11",
    "addr:postcode":"3990",
    "addr:street":"Bollisstraat",
    "iso:country":"BE",
    "sg:address":"Bollisstraat 11",
    "sg:city":"Peer (wijchmaal)",
    "sg:classifiers":[
        {
            "category":"Communications",
            "subcategory":"Film & Video Production",
            "type":"Services"
        }
    ],
    "sg:phone":"+32 11 63 71 33",
    "sg:postcode":"3990",
    "sg:province":"Limburg",
    "sg:tags":[
        "multimedia",
        "-",
        "system"
    ],
    "wof:name":"Androide Interactive Multi-media",
    "wof:placetype":"venue"
},
  "geometry": {"coordinates":[5.411550045,51.1347999573],"type":"Point"}
}