{
  "type": "Feature",
  "properties": {
    "iso:country":"BE",
    "sg:address":"Leenakkerstraat 4",
    "sg:city":"Waregem",
    "sg:classifiers":[
        {
            "category":"Insurance",
            "subcategory":"Insurance Agent",
            "type":"Services"
        }
    ],
    "sg:phone":"+32 56 71 65 91",
    "sg:postcode":"8791",
    "sg:province":"West-Vlaanderen",
    "sg:tags":[
        "verzekeringsmakelaars",
        "expert"
    ],
    "wof:name":"Assuro & Callens",
    "wof:placetype":"venue"
},
  "geometry": {"coordinates":[3.3371129036,50.8688926697],"type":"Point"}
}