{
  "type": "Feature",
  "properties": {
    "addr:full":"Korenveld 4 Merksplas Antwerpen 2330",
    "addr:housenumber":"4",
    "addr:postcode":"2330",
    "addr:street":"Korenveld",
    "iso:country":"BE",
    "sg:address":"Korenveld 4",
    "sg:city":"Merksplas",
    "sg:orig_category":"Gespecialiseerde residenti\u00eble bouw",
    "sg:phone":"+32 14 63 49 08",
    "sg:postcode":"2330",
    "sg:province":"Antwerpen",
    "wof:name":"Druyts Jan",
    "wof:placetype":"venue"
},
  "geometry": {"coordinates":[4.8459210396,51.360824585],"type":"Point"}
}