{
  "type": "Feature",
  "properties": {
    "iso:country":"BE",
    "sg:address":"Kruineikestraat 13",
    "sg:city":"Haacht",
    "sg:orig_category":"M\u00e9decins and sp\u00e9cialistes",
    "sg:phone":"+32 16 60 21 92",
    "sg:postcode":"3150",
    "sg:province":"Vlaams-Brabant",
    "wof:name":"Vanderborght An",
    "wof:placetype":"venue"
},
  "geometry": {"coordinates":[4.6450619698,50.9452514648],"type":"Point"}
}