{
  "type": "Feature",
  "properties": {
    "iso:country":"BE",
    "sg:address":"Rue De Tramaka 39",
    "sg:city":"Andenne",
    "sg:orig_category":"Huishoudapparaten, televisies and radio's",
    "sg:phone":"+32 85 82 50 17",
    "sg:postcode":"5300",
    "sg:province":"Namur",
    "wof:name":"Maison Herber",
    "wof:placetype":"venue"
},
  "geometry": {"coordinates":[5.0982642174,50.4863739014],"type":"Point"}
}