{
  "type": "Feature",
  "properties": {
    "iso:country":"BE",
    "sg:address":"Rue Petite Aise 13",
    "sg:city":"Charleroi",
    "sg:classifiers":[
        {
            "category":"Organizations",
            "subcategory":"Community Association",
            "type":"Services"
        }
    ],
    "sg:phone":"+32 71 41 47 39",
    "sg:postcode":"6061",
    "sg:province":"Hainaut",
    "sg:tags":[
        "organisation"
    ],
    "wof:name":"O.c.f.e.j.",
    "wof:placetype":"venue"
},
  "geometry": {"coordinates":[4.4656858444,50.4226531982],"type":"Point"}
}