{
  "type": "Feature",
  "properties": {
    "addr:full":"Bogaerdstraat 9 Merchtem Vlaams-Brabant 1785",
    "addr:housenumber":"9",
    "addr:postcode":"1785",
    "addr:street":"Bogaerdstraat",
    "iso:country":"BE",
    "sg:address":"Bogaerdstraat 9",
    "sg:city":"Merchtem",
    "sg:classifiers":[
        {
            "category":"Sports & Exercise",
            "subcategory":"Gym",
            "type":"Entertainment"
        }
    ],
    "sg:phone":"+32 52 37 23 90",
    "sg:postcode":"1785",
    "sg:province":"Vlaams-Brabant",
    "sg:tags":[
        "fitness"
    ],
    "wof:name":"De Grauwe H",
    "wof:placetype":"venue"
},
  "geometry": {"coordinates":[4.2326450348,50.9582061768],"type":"Point"}
}