{
  "type": "Feature",
  "properties": {
    "addr:full":"Sint-lenaartseweg 11-13 Hoogstraten Antwerpen 2320",
    "addr:housenumber":"11-13",
    "addr:postcode":"2320",
    "iso:country":"BE",
    "sg:address":"Sint-lenaartseweg 11-13",
    "sg:city":"Hoogstraten",
    "sg:classifiers":[
        {
            "category":"Personal",
            "subcategory":"Beauty Salon",
            "type":"Services"
        }
    ],
    "sg:phone":"+32 3 314 93 57",
    "sg:postcode":"2320",
    "sg:province":"Antwerpen",
    "sg:tags":[
        "lady",
        "-",
        "hairdressing"
    ],
    "wof:name":"Sandra Haarmode",
    "wof:placetype":"venue"
},
  "geometry": {"coordinates":[4.7531151772,51.3911933899],"type":"Point"}
}