{
  "type": "Feature",
  "properties": {
    "addr:full":"Stationsstraat 47 Herzele Oost-Vlaanderen 9550",
    "addr:housenumber":"47",
    "addr:postcode":"9550",
    "addr:street":"Stationsstraat;Oost-Vlaanderen",
    "iso:country":"BE",
    "sg:address":"Stationsstraat 47",
    "sg:city":"Herzele",
    "sg:orig_category":"Slagers",
    "sg:phone":"+32 53 62 22 07",
    "sg:postcode":"9550",
    "sg:province":"Oost-Vlaanderen",
    "wof:name":"Jan Vlaeminck",
    "wof:placetype":"venue"
},
  "geometry": {"coordinates":[3.8879299164,50.8902626038],"type":"Point"}
}