{
  "type": "Feature",
  "properties": {
    "addr:full":"Rue Notre-dame 61 Namur Namur 5000",
    "addr:housenumber":"61",
    "addr:postcode":"5000",
    "addr:street":"Rue Notre-Dame",
    "iso:country":"BE",
    "sg:address":"Rue Notre-dame 61",
    "sg:city":"Namur",
    "sg:orig_category":"Epiceries",
    "sg:phone":"+32 81 22 22 00",
    "sg:postcode":"5000",
    "sg:province":"Namur",
    "wof:name":"Veronique Rigaux",
    "wof:placetype":"venue"
},
  "geometry": {"coordinates":[4.8662018776,50.4597206116],"type":"Point"}
}