{
  "type": "Feature",
  "properties": {
    "iso:country":"BE",
    "sg:address":"Fu\u00c9risonplaats 18",
    "sg:city":"Steenokkerzeel",
    "sg:classifiers":[
        {
            "category":"Health Services",
            "subcategory":"Nursing And Care Facility",
            "type":"Services"
        }
    ],
    "sg:phone":"+32 2 758 01 72",
    "sg:postcode":"1820",
    "sg:province":"Vlaams-Brabant",
    "sg:tags":[
        "public"
    ],
    "wof:name":"Gemeentebestuur",
    "wof:placetype":"venue"
},
  "geometry": {"coordinates":[4.5130228996,50.9094390869],"type":"Point"}
}