{
  "type": "Feature",
  "properties": {
    "addr:full":"Cremerdijk 18 Peer Limburg 3990",
    "addr:housenumber":"18",
    "addr:postcode":"3990",
    "addr:street":"Cremerdijk",
    "iso:country":"BE",
    "sg:address":"Cremerdijk 18",
    "sg:city":"Peer",
    "sg:orig_category":"Plomberie, chauffage and installations sanitaires",
    "sg:phone":"+32 11 79 13 72",
    "sg:postcode":"3990",
    "sg:province":"Limburg",
    "wof:name":"Leopold Jonkers",
    "wof:placetype":"venue"
},
  "geometry": {"coordinates":[5.4533691406,51.0970458984],"type":"Point"}
}