{
  "type": "Feature",
  "properties": {
    "iso:country":"BE",
    "sg:address":"Rue Vital Rousseau 15",
    "sg:city":"Genappe (vieux-genappe)",
    "sg:classifiers":[
        {
            "category":"Shopping",
            "subcategory":"Computers & Home Electronics",
            "type":"Retail Goods"
        }
    ],
    "sg:phone":"+32 67 77 30 29",
    "sg:postcode":"1472",
    "sg:province":"Brabant Wallon",
    "sg:tags":[
        "-",
        "peripheral",
        "processing",
        "data",
        "equipment"
    ],
    "wof:name":"Bis Partners",
    "wof:placetype":"venue"
},
  "geometry": {"coordinates":[4.3915901184,50.6288833618],"type":"Point"}
}