{
  "type": "Feature",
  "properties": {
    "iso:country":"BE",
    "sg:address":"Veerstraat 11",
    "sg:city":"Temse",
    "sg:classifiers":[
        {
            "category":"Professional",
            "subcategory":"Testing Lab",
            "type":"Services"
        }
    ],
    "sg:phone":"+32 495 27 27 73",
    "sg:postcode":"9140",
    "sg:province":"Oost-Vlaanderen",
    "sg:tags":[
        "laboratory",
        "medical"
    ],
    "wof:name":"Labo Morfopat Bvba",
    "wof:placetype":"venue"
},
  "geometry": {"coordinates":[4.2162408829,51.1239242554],"type":"Point"}
}