{
  "type": "Feature",
  "properties": {
    "iso:country":"BE",
    "sg:address":"Avenue Plasky 157",
    "sg:city":"Bruxelles",
    "sg:classifiers":[
        {
            "category":"Banks & Credit Unions",
            "subcategory":"Investment Brokerage",
            "type":"Services"
        }
    ],
    "sg:phone":"+32 2 736 89 11",
    "sg:postcode":"1030",
    "sg:province":"Bruxelles-Capitale",
    "sg:tags":[
        "consulting"
    ],
    "wof:name":"Eft Consultants S.a.",
    "wof:placetype":"venue"
},
  "geometry": {"coordinates":[4.3974671364,50.8526153564],"type":"Point"}
}