{
  "type": "Feature",
  "properties": {
    "iso:country":"BE",
    "sg:address":"Onze-lieve-vrouwstraat 37",
    "sg:city":"Lebbeke",
    "sg:classifiers":[
        {
            "category":"Health Services",
            "subcategory":"Dentist",
            "type":"Services"
        }
    ],
    "sg:phone":"+32 52 41 16 52",
    "sg:postcode":"9280",
    "sg:province":"Oost-Vlaanderen",
    "wof:name":"De Schutter Georges",
    "wof:placetype":"venue"
},
  "geometry": {"coordinates":[4.1315999031,51.0007553101],"type":"Point"}
}