{
  "type": "Feature",
  "properties": {
    "iso:country":"BE",
    "sg:address":"Beukenlaan 24",
    "sg:city":"Bredene",
    "sg:orig_category":"Elektrische installaties voor woningen Verlichting and huishoudartikelen",
    "sg:phone":"+32 59 32 22 07",
    "sg:postcode":"8450",
    "sg:province":"West-Vlaanderen",
    "wof:name":"Fa. Bil",
    "wof:placetype":"venue"
},
  "geometry": {"coordinates":[2.9631109238,51.2424087524],"type":"Point"}
}