{
  "type": "Feature",
  "properties": {
    "addr:full":"Rue Du Pluvinage 49 Chievres Hainaut 7950",
    "addr:housenumber":"49",
    "addr:postcode":"7950",
    "addr:street":"Rue Du Pluvinage;Hainaut",
    "iso:country":"BE",
    "sg:address":"Rue Du Pluvinage 49",
    "sg:city":"Chievres",
    "sg:orig_category":"Eleveurs de bovins",
    "sg:phone":"+32 69 68 87 74",
    "sg:postcode":"7950",
    "sg:province":"Hainaut",
    "wof:name":"Paulette Dupuis",
    "wof:placetype":"venue"
},
  "geometry": {"coordinates":[3.7411410809,50.5632095337],"type":"Point"}
}