{
  "type": "Feature",
  "properties": {
    "addr:full":"Grand\u00b4rue 38 Virton Luxembourg 6760",
    "addr:housenumber":"38",
    "addr:postcode":"6760",
    "addr:street":"Grand\u00b4Rue",
    "iso:country":"BE",
    "sg:address":"Grand\u00b4rue 38",
    "sg:city":"Virton",
    "sg:orig_category":"Dameskledingzaken Herenkledingzaken",
    "sg:phone":"+32 63 57 83 30",
    "sg:postcode":"6760",
    "sg:province":"Luxembourg",
    "wof:name":"Maison Masculin-f\u00c9minin",
    "wof:placetype":"venue"
},
  "geometry": {"coordinates":[5.532143116,49.5684242249],"type":"Point"}
}