{
  "type": "Feature",
  "properties": {
    "iso:country":"BE",
    "sg:address":"Rue Lieutenant Liedel 46",
    "sg:city":"Bruxelles (anderlecht)",
    "sg:classifiers":[
        {
            "category":"Retail",
            "subcategory":"Auto Repair",
            "type":"Services"
        }
    ],
    "sg:postcode":"1070",
    "sg:province":"Bruxelles-Capitale",
    "sg:tags":[
        "rental",
        "-",
        "industrial",
        "clothing"
    ],
    "wof:name":"Hades Elis (elis) Sa",
    "wof:placetype":"venue"
},
  "geometry": {"coordinates":[4.3036899567,50.8310546875],"type":"Point"}
}