{
  "type": "Feature",
  "properties": {
    "addr:full":"Sainlez 13 Fauvillers Luxembourg 6637",
    "addr:housenumber":"13",
    "addr:postcode":"6637",
    "addr:street":"Sainlez",
    "iso:country":"BE",
    "sg:address":"Sainlez 13",
    "sg:city":"Fauvillers",
    "sg:orig_category":"Rundveehouders",
    "sg:phone":"+32 61 21 31 89",
    "sg:postcode":"6637",
    "sg:province":"Luxembourg",
    "wof:name":"Joseph Glesner",
    "wof:placetype":"venue"
},
  "geometry": {"coordinates":[5.7091507912,49.9224205017],"type":"Point"}
}