{
  "type": "Feature",
  "properties": {
    "iso:country":"BE",
    "sg:address":"Lierseweg 190",
    "sg:city":"Herentals",
    "sg:classifiers":[
        {
            "category":"Arena",
            "subcategory":"Sports Club",
            "type":"Entertainment"
        }
    ],
    "sg:phone":"+32 14 23 35 81",
    "sg:postcode":"2200",
    "sg:province":"Antwerpen",
    "sg:tags":[
        "de"
    ],
    "wof:name":"Moto Endurance Trophy",
    "wof:placetype":"venue"
},
  "geometry": {"coordinates":[4.8195161819,51.1749610901],"type":"Point"}
}