{
  "type": "Feature",
  "properties": {
    "addr:full":"Stokerijstraat 35 Wijnegem Antwerpen 2110",
    "addr:housenumber":"35",
    "addr:postcode":"2110",
    "addr:street":"Stokerijstraat",
    "iso:country":"BE",
    "sg:address":"Stokerijstraat 35",
    "sg:city":"Wijnegem",
    "sg:classifiers":[
        {
            "category":"Manufacturing",
            "subcategory":"Metals",
            "type":"Manufacturing & Wholesale Goods"
        }
    ],
    "sg:phone":"+32 3 353 26 89",
    "sg:postcode":"2110",
    "sg:province":"Antwerpen",
    "sg:tags":[
        "aluminium"
    ],
    "wof:name":"Blommaert B.v.b.a.",
    "wof:placetype":"venue"
},
  "geometry": {"coordinates":[4.5350279808,51.2266273499],"type":"Point"}
}