{
  "type": "Feature",
  "properties": {
    "addr:full":"Dellenstraat 3 Butgenbach Li\u00e8ge 4750",
    "addr:housenumber":"3",
    "addr:postcode":"4750",
    "addr:street":"Dellenstraat",
    "iso:country":"BE",
    "sg:address":"Dellenstraat 3",
    "sg:city":"Butgenbach",
    "sg:orig_category":"Quincailleries",
    "sg:phone":"+32 80 44 60 36",
    "sg:postcode":"4750",
    "sg:province":"Li\u00e8ge",
    "wof:name":"Krings E",
    "wof:placetype":"venue"
},
  "geometry": {"coordinates":[6.2043948174,50.4263038635],"type":"Point"}
}