{
  "type": "Feature",
  "properties": {
    "addr:full":"Schoolstraat 3 Ranst Antwerpen 2520",
    "addr:housenumber":"3",
    "addr:postcode":"2520",
    "addr:street":"Schoolstraat",
    "iso:country":"BE",
    "sg:address":"Schoolstraat 3",
    "sg:city":"Ranst",
    "sg:orig_category":"Postkantoren Verzekeringsmakelaars and experts",
    "sg:phone":"+32 3 485 50 22",
    "sg:postcode":"2520",
    "sg:province":"Antwerpen",
    "wof:name":"De Post",
    "wof:placetype":"venue"
},
  "geometry": {"coordinates":[4.5609998703,51.1906776428],"type":"Point"}
}