{
  "type": "Feature",
  "properties": {
    "addr:full":"Ambachtsweg 16 Merelbeke Oost-Vlaanderen 9820",
    "addr:housenumber":"16",
    "addr:postcode":"9820",
    "addr:street":"Ambachtsweg",
    "iso:country":"BE",
    "sg:address":"Ambachtsweg 16",
    "sg:city":"Merelbeke",
    "sg:orig_category":"Onderdelen and accessoires voertuigen Gh",
    "sg:phone":"+32 9 252 52 03",
    "sg:postcode":"9820",
    "sg:province":"Oost-Vlaanderen",
    "wof:name":"Dabrav",
    "wof:placetype":"venue"
},
  "geometry": {"coordinates":[3.7653110027,50.9929580688],"type":"Point"}
}