{
  "type": "Feature",
  "properties": {
    "addr:full":"Dworpsestraat 38 Beersel (lot) Vlaams-Brabant 1651",
    "addr:housenumber":"38",
    "addr:postcode":"1651",
    "addr:street":"Dworpsestraat",
    "iso:country":"BE",
    "sg:address":"Dworpsestraat 38",
    "sg:city":"Beersel (lot)",
    "sg:classifiers":[
        {
            "category":"Bars & Pubs",
            "type":"Food & Drink"
        }
    ],
    "sg:phone":"+32 2 305 35 06",
    "sg:postcode":"1651",
    "sg:province":"Vlaams-Brabant",
    "wof:name":"Rick's Caf\u00e9",
    "wof:placetype":"venue"
},
  "geometry": {"coordinates":[4.2724809647,50.761013031],"type":"Point"}
}