{
  "type": "Feature",
  "properties": {
    "addr:full":"Charles Coppensstraat 13 Hoeilaart Vlaams-Brabant 1560",
    "addr:housenumber":"13",
    "addr:postcode":"1560",
    "addr:street":"Charles Coppensstraat",
    "iso:country":"BE",
    "sg:address":"Charles Coppensstraat 13",
    "sg:city":"Hoeilaart",
    "sg:orig_category":"Avocats and conseillers juridiques",
    "sg:phone":"+32 2 657 99 31",
    "sg:postcode":"1560",
    "sg:province":"Vlaams-Brabant",
    "wof:name":"A. De Winter",
    "wof:placetype":"venue"
},
  "geometry": {"coordinates":[4.471971035,50.762096405],"type":"Point"}
}