{
  "type": "Feature",
  "properties": {
    "addr:full":"Chauss\u00c9e De Mons 560 La Louvi\u00c8re (groot) Hainaut 7100",
    "addr:housenumber":"560",
    "addr:postcode":"7100",
    "addr:street":"Chausse\u0301E De Mons;Hainaut",
    "iso:country":"BE",
    "sg:address":"Chauss\u00c9e De Mons 560",
    "sg:city":"La Louvi\u00c8re (groot)",
    "sg:orig_category":"Baby- and kinderkleding Dameskledingzaken Herenkledingzaken",
    "sg:phone":"+32 64 28 41 48",
    "sg:postcode":"7100",
    "sg:province":"Hainaut",
    "wof:name":"Jbc Mode",
    "wof:placetype":"venue"
},
  "geometry": {"coordinates":[4.1995410919,50.4645805359],"type":"Point"}
}