{
  "type": "Feature",
  "properties": {
    "addr:full":"Rue Strimelle Emile 5 Charleroi (jumet) Hainaut 6040",
    "addr:housenumber":"5",
    "addr:postcode":"6040",
    "addr:street":"Rue Strimelle Emile",
    "iso:country":"BE",
    "sg:address":"Rue Strimelle Emile 5",
    "sg:city":"Charleroi (jumet)",
    "sg:classifiers":[
        {
            "category":"Professional",
            "subcategory":"Accounting & Tax Preparation",
            "type":"Services"
        }
    ],
    "sg:phone":"+32 71 34 30 06",
    "sg:postcode":"6040",
    "sg:province":"Hainaut",
    "sg:tags":[
        "bookkeeper"
    ],
    "wof:name":"Pilette J-p",
    "wof:placetype":"venue"
},
  "geometry": {"coordinates":[4.4159169197,50.4349021912],"type":"Point"}
}