{
  "type": "Feature",
  "properties": {
    "addr:full":"Rue Emile Vandervelde 62 Marchienne-au-pont Hainaut 6030",
    "addr:housenumber":"62",
    "addr:postcode":"6030",
    "addr:street":"Rue Emile Vandervelde",
    "iso:country":"BE",
    "sg:address":"Rue Emile Vandervelde 62",
    "sg:city":"Marchienne-au-pont",
    "sg:orig_category":"Bloemen and planten Fleurop Interflora Tuinen",
    "sg:phone":"+32 71 32 68 08",
    "sg:postcode":"6030",
    "sg:province":"Hainaut",
    "wof:name":"Art Floral Janny",
    "wof:placetype":"venue"
},
  "geometry": {"coordinates":[4.3936200142,50.4099578857],"type":"Point"}
}