{
  "type": "Feature",
  "properties": {
    "addr:full":"Prins Boudewijnlaan 1 Kontich Antwerpen 2550",
    "addr:housenumber":"1",
    "addr:postcode":"2550",
    "addr:street":"Prins Boudewijnlaan",
    "iso:country":"BE",
    "sg:address":"Prins Boudewijnlaan 1",
    "sg:city":"Kontich",
    "sg:classifiers":[
        {
            "category":"Shopping",
            "subcategory":"Baby Store",
            "type":"Retail Goods"
        }
    ],
    "sg:phone":"+32 3 457 78 73",
    "sg:postcode":"2550",
    "sg:province":"Antwerpen",
    "sg:tags":[
        "children's",
        "sock"
    ],
    "wof:name":"Trompenaars B.v.b.a.",
    "wof:placetype":"venue"
},
  "geometry": {"coordinates":[4.437983036,51.1393547058],"type":"Point"}
}