{
  "type": "Feature",
  "properties": {
    "addr:full":"Rue Jean D'ardenne 14 Bruxelles (ixelles) Bruxelles-Capitale 1050",
    "addr:housenumber":"14",
    "addr:postcode":"1050",
    "addr:street":"Rue Jean D'Ardenne",
    "iso:country":"BE",
    "sg:address":"Rue Jean D'ardenne 14",
    "sg:city":"Bruxelles (ixelles)",
    "sg:classifiers":[
        {
            "category":"Real Estate",
            "subcategory":"Architect",
            "type":"Services"
        }
    ],
    "sg:phone":"+32 2 514 17 43",
    "sg:postcode":"1050",
    "sg:province":"Bruxelles-Capitale",
    "wof:name":"Atelier D'architecture Serge Roose Sprlu",
    "wof:placetype":"venue"
},
  "geometry": {"coordinates":[4.3631148338,50.8325004578],"type":"Point"}
}