{
  "type": "Feature",
  "properties": {
    "addr:full":"Rue De Tillier 45 Fernelmont Namur 5380",
    "addr:housenumber":"45",
    "addr:postcode":"5380",
    "addr:street":"Rue De Tillier",
    "iso:country":"BE",
    "sg:address":"Rue De Tillier 45",
    "sg:city":"Fernelmont",
    "sg:orig_category":"Gespecialiseerde residenti\u00eble bouw",
    "sg:phone":"+32 81 21 09 33",
    "sg:postcode":"5380",
    "sg:province":"Namur",
    "wof:name":"Jean-michel Beaume",
    "wof:placetype":"venue"
},
  "geometry": {"coordinates":[4.9454579353,50.5289535522],"type":"Point"}
}