{
  "type": "Feature",
  "properties": {
    "iso:country":"BE",
    "sg:address":"Kerkstraat 2",
    "sg:city":"Koksijde",
    "sg:orig_category":"Instituts de beaut\u00e9",
    "sg:phone":"+32 58 51 59 74",
    "sg:postcode":"8670",
    "sg:province":"West-Vlaanderen",
    "wof:name":"Freddy Lowagie",
    "wof:placetype":"venue"
},
  "geometry": {"coordinates":[2.6510369778,51.1034011841],"type":"Point"}
}