{
  "type": "Feature",
  "properties": {
    "addr:full":"Chauss\u00c9e De Waterloo 608 Elsene/ixelles Bruxelles-Capitale 1050",
    "addr:housenumber":"608",
    "addr:postcode":"1050",
    "addr:street":"Chausse\u0301E De Waterloo",
    "iso:country":"BE",
    "sg:address":"Chauss\u00c9e De Waterloo 608",
    "sg:city":"Elsene/ixelles",
    "sg:classifiers":[
        {
            "category":"Organizations",
            "subcategory":"Community Association",
            "type":"Services"
        }
    ],
    "sg:phone":"+32 2 340 09 99",
    "sg:postcode":"1050",
    "sg:province":"Bruxelles-Capitale",
    "sg:tags":[
        "organisation"
    ],
    "wof:name":"W.w.f. Belgium",
    "wof:placetype":"venue"
},
  "geometry": {"coordinates":[4.3646101952,50.8180122375],"type":"Point"}
}