{
  "type": "Feature",
  "properties": {
    "iso:country":"BE",
    "sg:address":"Lievekenshoek 10",
    "sg:city":"Merksplas",
    "sg:orig_category":"Eleveurs and marchands de porcs",
    "sg:phone":"+32 14 63 31 39",
    "sg:postcode":"2330",
    "sg:province":"Antwerpen",
    "wof:name":"Christiaan Jansen",
    "wof:placetype":"venue"
},
  "geometry": {"coordinates":[4.9011511803,51.3619346619],"type":"Point"}
}