{
  "type": "Feature",
  "properties": {
    "addr:full":"Stadsbeemd 1215 Halen Limburg 3545",
    "addr:postcode":"1215 halen;3545",
    "addr:street":"Stadsbeemd",
    "iso:country":"BE",
    "sg:address":"Stadsbeemd 1215",
    "sg:city":"Halen",
    "sg:orig_category":"V\u00eatements",
    "sg:phone":"+32 13 46 17 16",
    "sg:postcode":"3545",
    "sg:province":"Limburg",
    "wof:name":"Ontwerpatelier R G",
    "wof:placetype":"venue"
},
  "geometry": {"coordinates":[5.1010789871,50.9514961243],"type":"Point"}
}