{
  "type": "Feature",
  "properties": {
    "addr:full":"Zeelaan 301 Koksijde West-Vlaanderen 8670",
    "addr:housenumber":"301",
    "addr:postcode":"8670",
    "addr:street":"Zeelaan",
    "iso:country":"BE",
    "sg:address":"Zeelaan 301",
    "sg:city":"Koksijde",
    "sg:orig_category":"V\u00eatements pour Hommes",
    "sg:phone":"+32 58 52 13 04",
    "sg:postcode":"8670",
    "sg:province":"West-Vlaanderen",
    "wof:name":"Rufus Men's Wear",
    "wof:placetype":"venue"
},
  "geometry": {"coordinates":[2.6354329586,51.1184997559],"type":"Point"}
}