{
  "type": "Feature",
  "properties": {
    "addr:full":"Ten Boschstraat 20 Edegem Antwerpen 2650",
    "addr:housenumber":"20",
    "addr:postcode":"2650",
    "addr:street":"Ten Boschstraat",
    "iso:country":"BE",
    "sg:address":"Ten Boschstraat 20",
    "sg:city":"Edegem",
    "sg:orig_category":"Artsen and specialisten",
    "sg:phone":"+32 3 449 93 94",
    "sg:postcode":"2650",
    "sg:province":"Antwerpen",
    "wof:name":"J. De Moor",
    "wof:placetype":"venue"
},
  "geometry": {"coordinates":[4.4275789261,51.1575012207],"type":"Point"}
}