{
  "type": "Feature",
  "properties": {
    "iso:country":"BE",
    "sg:address":"Alphonse De Wittestraat 26a",
    "sg:city":"Elsene/ixelles",
    "sg:orig_category":"Zalen voor culturele evenementen",
    "sg:phone":"+32 2 649 58 88",
    "sg:postcode":"1050",
    "sg:province":"Bruxelles-Capitale",
    "wof:name":"Th\u00c9\u00c2tre La Soupape",
    "wof:placetype":"venue"
},
  "geometry": {"coordinates":[4.3733830452,50.8261909485],"type":"Point"}
}