{
  "type": "Feature",
  "properties": {
    "addr:full":"Avenue Des Ch\u00canes 6 Sint-genesius-rode Vlaams-Brabant 1640",
    "addr:housenumber":"6",
    "addr:postcode":"1640",
    "addr:street":"Avenue Des Che\u0302Nes",
    "iso:country":"BE",
    "sg:address":"Avenue Des Ch\u00canes 6",
    "sg:city":"Sint-genesius-rode",
    "sg:orig_category":"Jardinage",
    "sg:phone":"+32 2 358 20 05",
    "sg:postcode":"1640",
    "sg:province":"Vlaams-Brabant",
    "wof:name":"Sorel",
    "wof:placetype":"venue"
},
  "geometry": {"coordinates":[4.3859238625,50.7566413879],"type":"Point"}
}