{
  "type": "Feature",
  "properties": {
    "iso:country":"BE",
    "sg:address":"Kerkstraat 18",
    "sg:city":"Dendermonde",
    "sg:classifiers":[
        {
            "category":"Health Services",
            "subcategory":"Dentist",
            "type":"Services"
        }
    ],
    "sg:phone":"+32 52 21 37 49",
    "sg:postcode":"9200",
    "sg:province":"Oost-Vlaanderen",
    "wof:name":"De Saeger Jan",
    "wof:placetype":"venue"
},
  "geometry": {"coordinates":[4.0980801582,51.031627655],"type":"Point"}
}