{
  "type": "Feature",
  "properties": {
    "addr:full":"Boogschutterslaan 35 Brugge (sint-kruis) West-Vlaanderen 8310",
    "addr:housenumber":"35",
    "addr:postcode":"8310",
    "addr:street":"Boogschutterslaan",
    "iso:country":"BE",
    "sg:address":"Boogschutterslaan 35",
    "sg:city":"Brugge (sint-kruis)",
    "sg:classifiers":[
        {
            "category":"Health Services",
            "subcategory":"Health Practitioner",
            "type":"Services"
        }
    ],
    "sg:phone":"+32 50 36 44 98",
    "sg:postcode":"8310",
    "sg:province":"West-Vlaanderen",
    "sg:tags":[
        "physiotherapist"
    ],
    "wof:name":"No\u00ebl Ghislain",
    "wof:placetype":"venue"
},
  "geometry": {"coordinates":[3.2479538918,51.2154006958],"type":"Point"}
}