{
  "type": "Feature",
  "properties": {
    "iso:country":"BE",
    "sg:address":"Roeselaarsestraat 171",
    "sg:city":"Moorslede",
    "sg:orig_category":"Gespecialiseerde niet-residenti\u00eble bouw",
    "sg:phone":"+32 51 77 70 36",
    "sg:postcode":"8890",
    "sg:province":"West-Vlaanderen",
    "wof:name":"Demaitere",
    "wof:placetype":"venue"
},
  "geometry": {"coordinates":[3.0693058968,50.9014472961],"type":"Point"}
}