{
  "type": "Feature",
  "properties": {
    "iso:country":"BE",
    "sg:address":"Rue Albert-raty 9",
    "sg:city":"Vresse-sur-semois",
    "sg:orig_category":"Epiceries",
    "sg:phone":"+32 61 50 08 25",
    "sg:postcode":"5550",
    "sg:province":"Namur",
    "wof:name":"H. Dion-monmart",
    "wof:placetype":"venue"
},
  "geometry": {"coordinates":[4.9313931465,49.8719482422],"type":"Point"}
}