{
  "type": "Feature",
  "properties": {
    "iso:country":"BE",
    "sg:address":"Eekhofstraat 27",
    "sg:city":"Ieper",
    "sg:orig_category":"Rundveehouders Varkenskwekers",
    "sg:phone":"+32 57 20 23 07",
    "sg:postcode":"8902",
    "sg:province":"West-Vlaanderen",
    "wof:name":"Carine Louwyck",
    "wof:placetype":"venue"
},
  "geometry": {"coordinates":[2.9056329727,50.8063926697],"type":"Point"}
}