{
  "type": "Feature",
  "properties": {
    "iso:country":"BE",
    "sg:address":"Halsestw 392",
    "sg:city":"Neigem",
    "sg:classifiers":[
        {
            "category":"Banks & Credit Unions",
            "subcategory":"Bank",
            "type":"Services"
        }
    ],
    "sg:phone":"+32 54 33 21 33",
    "sg:postcode":"9403",
    "sg:province":"Oost-Vlaanderen",
    "wof:name":"Gemeentekrediet",
    "wof:placetype":"venue"
},
  "geometry": {"coordinates":[4.0594549179,50.8027954102],"type":"Point"}
}