{
  "type": "Feature",
  "properties": {
    "addr:full":"Sterstraat 37 Ukkel/uccle Bruxelles-Capitale 1180",
    "addr:housenumber":"37",
    "addr:postcode":"1180",
    "addr:street":"Sterstraat;/",
    "iso:country":"BE",
    "sg:address":"Sterstraat 37",
    "sg:city":"Ukkel/uccle",
    "sg:orig_category":"Gespecialiseerde residenti\u00eble bouw",
    "sg:phone":"+32 2 376 46 82",
    "sg:postcode":"1180",
    "sg:province":"Bruxelles-Capitale",
    "wof:name":"J.p. Santarossa",
    "wof:placetype":"venue"
},
  "geometry": {"coordinates":[4.321149826,50.7949104309],"type":"Point"}
}