{
  "type": "Feature",
  "properties": {
    "iso:country":"BE",
    "sg:address":"Rue Frans Hals 143",
    "sg:city":"Bruxelles (anderlecht)",
    "sg:classifiers":[
        {
            "category":"Bars & Pubs",
            "type":"Food & Drink"
        }
    ],
    "sg:phone":"+32 2 521 74 98",
    "sg:postcode":"1070",
    "sg:province":"Bruxelles-Capitale",
    "wof:name":"Etangs (des)",
    "wof:placetype":"venue"
},
  "geometry": {"coordinates":[4.2906451225,50.8260154724],"type":"Point"}
}