{
  "type": "Feature",
  "properties": {
    "iso:country":"BE",
    "sg:address":"Moerplas 29",
    "sg:city":"Puurs",
    "sg:classifiers":[
        {
            "category":"Farming",
            "subcategory":"Crops",
            "type":"Manufacturing & Wholesale Goods"
        }
    ],
    "sg:phone":"+32 3 889 09 38",
    "sg:postcode":"2870",
    "sg:province":"Antwerpen",
    "sg:tags":[
        "vegetable",
        "fruit",
        "-",
        "grower"
    ],
    "wof:name":"Oss\u00e9 J",
    "wof:placetype":"venue"
},
  "geometry": {"coordinates":[4.3080840111,51.0801124573],"type":"Point"}
}