{
  "type": "Feature",
  "properties": {
    "addr:full":"Rue Saint-etienne 5 Li\u00c8ge Li\u00e8ge 4000",
    "addr:housenumber":"5",
    "addr:postcode":"4000",
    "addr:street":"Rue Saint-Etienne",
    "iso:country":"BE",
    "sg:address":"Rue Saint-etienne 5",
    "sg:city":"Li\u00c8ge",
    "sg:classifiers":[
        {
            "category":"Cafe",
            "type":"Food & Drink"
        }
    ],
    "sg:phone":"+32 4 221 07 81",
    "sg:postcode":"4000",
    "sg:province":"Li\u00e8ge",
    "sg:tags":[
        "caf\u00e9s"
    ],
    "wof:name":"Sarja",
    "wof:placetype":"venue"
},
  "geometry": {"coordinates":[5.5745840073,50.6434593201],"type":"Point"}
}