{
  "type": "Feature",
  "properties": {
    "addr:full":"Egemstraat 1 Pittem West-Vlaanderen 8740",
    "addr:housenumber":"1",
    "addr:postcode":"8740",
    "addr:street":"Egemstraat",
    "iso:country":"BE",
    "sg:address":"Egemstraat 1",
    "sg:city":"Pittem",
    "sg:orig_category":"Diverse bouwafwerking and reiniging Gespecialiseerde residenti\u00eble bouw",
    "sg:phone":"+32 51 46 71 48",
    "sg:postcode":"8740",
    "sg:province":"West-Vlaanderen",
    "wof:name":"Frank Goethals",
    "wof:placetype":"venue"
},
  "geometry": {"coordinates":[3.2677609921,50.9950561523],"type":"Point"}
}