{
  "type": "Feature",
  "properties": {
    "iso:country":"BE",
    "sg:address":"Route De L\u00b4abbaye 66",
    "sg:city":"Chaudfontaine",
    "sg:orig_category":"Installation \u00e9lectrique r\u00e9sidentielle",
    "sg:phone":"+32 4 368 52 44",
    "sg:postcode":"4052",
    "sg:province":"Li\u00e8ge",
    "wof:name":"Masson Electricit\u00c9 G\u00c9n.",
    "wof:placetype":"venue"
},
  "geometry": {"coordinates":[5.6441488266,50.5642700195],"type":"Point"}
}