{
  "type": "Feature",
  "properties": {
    "iso:country":"BE",
    "sg:address":"Rue Du Touquet 66",
    "sg:city":"Komen-waasten/comines-warneton",
    "sg:orig_category":"Fleurs and plantes",
    "sg:phone":"+32 56 58 87 93",
    "sg:postcode":"7783",
    "sg:province":"Hainaut",
    "wof:name":"Botanic",
    "wof:placetype":"venue"
},
  "geometry": {"coordinates":[2.8828949928,50.7069244385],"type":"Point"}
}