{
  "type": "Feature",
  "properties": {
    "iso:country":"BE",
    "sg:address":"Rue De La Senne 21",
    "sg:city":"Bruxelles",
    "sg:classifiers":[
        {
            "category":"Manufacturing",
            "subcategory":"Rubber & Plastics",
            "type":"Manufacturing & Wholesale Goods"
        }
    ],
    "sg:phone":"+32 2 512 91 35",
    "sg:postcode":"1000",
    "sg:province":"Bruxelles-Capitale",
    "sg:tags":[
        "-",
        "machinery"
    ],
    "wof:name":"M E C",
    "wof:placetype":"venue"
},
  "geometry": {"coordinates":[4.3403840065,50.8481330872],"type":"Point"}
}