{
  "type": "Feature",
  "properties": {
    "iso:country":"BE",
    "sg:address":"Mellestraat 164",
    "sg:city":"Kortrijk",
    "sg:orig_category":"D\u00e9chets and d\u00e9bris Gr",
    "sg:phone":"+32 56 35 06 53",
    "sg:postcode":"8501",
    "sg:province":"West-Vlaanderen",
    "wof:name":"Belrey",
    "wof:placetype":"venue"
},
  "geometry": {"coordinates":[3.228605032,50.8515281677],"type":"Point"}
}