{
  "type": "Feature",
  "properties": {
    "addr:full":"Avenue De Flor\u00e9al 156 Bruxelles (uccle) Bruxelles-Capitale 1180",
    "addr:housenumber":"156",
    "addr:postcode":"1180",
    "addr:street":"Avenue De Flore\u0301Al",
    "iso:country":"BE",
    "sg:address":"Avenue De Flor\u00e9al 156",
    "sg:city":"Bruxelles (uccle)",
    "sg:classifiers":[
        {
            "category":"Organizations",
            "subcategory":"Professional Association",
            "type":"Services"
        }
    ],
    "sg:phone":"+32 2 346 04 69",
    "sg:postcode":"1180",
    "sg:province":"Bruxelles-Capitale",
    "sg:tags":[
        "trade-union",
        "federation"
    ],
    "wof:name":"Association Des Industries De L'alarme",
    "wof:placetype":"venue"
},
  "geometry": {"coordinates":[4.3433089256,50.8091316223],"type":"Point"}
}