{
  "type": "Feature",
  "properties": {
    "addr:full":"Herfstlei 12 Edegem Antwerpen 2650",
    "addr:housenumber":"12",
    "addr:postcode":"2650",
    "addr:street":"Herfstlei",
    "iso:country":"BE",
    "sg:address":"Herfstlei 12",
    "sg:city":"Edegem",
    "sg:orig_category":"Secr\u00e9tariats",
    "sg:phone":"+32 3 457 39 34",
    "sg:postcode":"2650",
    "sg:province":"Antwerpen",
    "wof:name":"Zetterij R.g.",
    "wof:placetype":"venue"
},
  "geometry": {"coordinates":[4.4524698257,51.1554107666],"type":"Point"}
}