{
  "type": "Feature",
  "properties": {
    "addr:full":"Paalseweg 25 Tessenderlo Limburg 3980",
    "addr:housenumber":"25",
    "addr:postcode":"3980",
    "addr:street":"Paalseweg",
    "iso:country":"BE",
    "sg:address":"Paalseweg 25",
    "sg:city":"Tessenderlo",
    "sg:orig_category":"Epiceries",
    "sg:phone":"+32 13 67 50 25",
    "sg:postcode":"3980",
    "sg:province":"Limburg",
    "wof:name":"Hilde Verheyen",
    "wof:placetype":"venue"
},
  "geometry": {"coordinates":[5.1421399117,51.0624504089],"type":"Point"}
}