{
  "type": "Feature",
  "properties": {
    "addr:full":"Chemin Du Hielert 6 Stockem Luxembourg 6700",
    "addr:housenumber":"6",
    "addr:postcode":"6700",
    "addr:street":"Chemin Du Hielert",
    "iso:country":"BE",
    "sg:address":"Chemin Du Hielert 6",
    "sg:city":"Stockem",
    "sg:classifiers":[
        {
            "category":"Building & Trades",
            "subcategory":"Cleaning & Sanitation",
            "type":"Services"
        }
    ],
    "sg:phone":"+32 63 21 70 48",
    "sg:postcode":"6700",
    "sg:province":"Luxembourg",
    "sg:tags":[
        "fa\u00e7ade",
        "maintenance"
    ],
    "wof:name":"Mortier M",
    "wof:placetype":"venue"
},
  "geometry": {"coordinates":[5.7717938423,49.6845741272],"type":"Point"}
}