{
  "type": "Feature",
  "properties": {
    "addr:full":"Rue Darchis 38 Li\u00c8ge Li\u00e8ge 4000",
    "addr:housenumber":"38",
    "addr:postcode":"4000",
    "addr:street":"Rue Darchis",
    "iso:country":"BE",
    "sg:address":"Rue Darchis 38",
    "sg:city":"Li\u00c8ge",
    "sg:orig_category":"Antiquit\u00e9s. Eclairage et \u00e9quipements du foyer. Services divers aux entreprises",
    "sg:phone":"+32 4 223 55 42",
    "sg:postcode":"4000",
    "sg:province":"Li\u00e8ge",
    "wof:name":"Francine Mooren",
    "wof:placetype":"venue"
},
  "geometry": {"coordinates":[5.5646061897,50.6372032166],"type":"Point"}
}