{
  "type": "Feature",
  "properties": {
    "addr:full":"Heisbroekstraat 18 Berlare Oost-Vlaanderen 9290",
    "addr:housenumber":"18",
    "addr:postcode":"9290",
    "addr:street":"Heisbroekstraat",
    "iso:country":"BE",
    "sg:address":"Heisbroekstraat 18",
    "sg:city":"Berlare",
    "sg:orig_category":"Sportclubs",
    "sg:phone":"+32 9 367 59 70",
    "sg:postcode":"9290",
    "sg:province":"Oost-Vlaanderen",
    "wof:name":"Rap Of Niets",
    "wof:placetype":"venue"
},
  "geometry": {"coordinates":[3.9535150528,51.0198516846],"type":"Point"}
}