{
  "type": "Feature",
  "properties": {
    "iso:country":"BE",
    "sg:address":"Hernestraat 34",
    "sg:city":"Opwijk",
    "sg:orig_category":"Imprimeries and copyshops",
    "sg:phone":"+32 54 58 68 76",
    "sg:postcode":"1745",
    "sg:province":"Vlaams-Brabant",
    "wof:name":"Drukkerij Deneef",
    "wof:placetype":"venue"
},
  "geometry": {"coordinates":[4.1880807877,50.9718856812],"type":"Point"}
}