{
  "type": "Feature",
  "properties": {
    "addr:full":"Rue Patenier 18 Namur Namur 5000",
    "addr:housenumber":"18",
    "addr:postcode":"5000",
    "addr:street":"Rue Patenier",
    "iso:country":"BE",
    "sg:address":"Rue Patenier 18",
    "sg:city":"Namur",
    "sg:orig_category":"Machines \u00e0 coudre and tricoter",
    "sg:phone":"+32 475 64 50 04",
    "sg:postcode":"5000",
    "sg:province":"Namur",
    "wof:name":"Bernina Center",
    "wof:placetype":"venue"
},
  "geometry": {"coordinates":[4.8472499847,50.4640312195],"type":"Point"}
}