{
  "type": "Feature",
  "properties": {
    "addr:full":"Emiel Verhaerenlaan 86 Gent Oost-Vlaanderen 9050",
    "addr:housenumber":"86",
    "addr:postcode":"9050",
    "addr:street":"Emiel Verhaerenlaan;Oost-Vlaanderen",
    "iso:country":"BE",
    "sg:address":"Emiel Verhaerenlaan 86",
    "sg:city":"Gent",
    "sg:orig_category":"V\u00e9t\u00e9rinaires",
    "sg:phone":"+32 9 230 00 81",
    "sg:postcode":"9050",
    "sg:province":"Oost-Vlaanderen",
    "wof:name":"Chantal Vanhuyse",
    "wof:placetype":"venue"
},
  "geometry": {"coordinates":[3.7678759098,51.0333061218],"type":"Point"}
}