{
  "type": "Feature",
  "properties": {
    "iso:country":"BE",
    "sg:address":"Rue De L'avenir 13",
    "sg:city":"Quevy",
    "sg:orig_category":"Kapsalons",
    "sg:phone":"+32 65 56 90 41",
    "sg:postcode":"7040",
    "sg:province":"Hainaut",
    "wof:name":"Studio 13",
    "wof:placetype":"venue"
},
  "geometry": {"coordinates":[3.905903101,50.3395767212],"type":"Point"}
}