{
  "type": "Feature",
  "properties": {
    "iso:country":"BE",
    "sg:address":"Filip De Pillecynstraat 19",
    "sg:city":"Zele",
    "sg:classifiers":[
        {
            "category":"Building & Trades",
            "subcategory":"Construction",
            "type":"Services"
        }
    ],
    "sg:phone":"+32 52 44 75 30",
    "sg:postcode":"9240",
    "sg:province":"Oost-Vlaanderen",
    "sg:tags":[
        "carpenter"
    ],
    "wof:name":"Pennewaert E",
    "wof:placetype":"venue"
},
  "geometry": {"coordinates":[4.034719944,51.0582008362],"type":"Point"}
}