{
  "type": "Feature",
  "properties": {
    "iso:country":"BE",
    "sg:address":"Meerspoort 47b3",
    "sg:city":"Oudenaarde",
    "sg:orig_category":"Activit\u00e9s r\u00e9cr\u00e9atives diverses",
    "sg:phone":"+32 55 31 73 28",
    "sg:postcode":"9700",
    "sg:province":"Oost-Vlaanderen",
    "wof:name":"Koninklijke Philaclub",
    "wof:placetype":"venue"
},
  "geometry": {"coordinates":[3.6011600494,50.840511322],"type":"Point"}
}