{
  "type": "Feature",
  "properties": {
    "iso:country":"BE",
    "sg:address":"Rue Des Vieilles-prisons 22",
    "sg:city":"Nivelles",
    "sg:orig_category":"Advocaten and juridische adviseurs",
    "sg:phone":"+32 67 84 33 39",
    "sg:postcode":"1400",
    "sg:province":"Brabant Wallon",
    "wof:name":"S. Janssens",
    "wof:placetype":"venue"
},
  "geometry": {"coordinates":[4.3259191513,50.597278595],"type":"Point"}
}