{
  "type": "Feature",
  "properties": {
    "iso:country":"BE",
    "sg:address":"Kerkstraat 25",
    "sg:city":"Zomergem",
    "sg:orig_category":"Installation \u00e9lectrique r\u00e9sidentielle",
    "sg:phone":"+32 9 372 63 46",
    "sg:postcode":"9930",
    "sg:province":"Oost-Vlaanderen",
    "wof:name":"Luc De Baets",
    "wof:placetype":"venue"
},
  "geometry": {"coordinates":[3.5565121174,51.1181144714],"type":"Point"}
}