{
  "type": "Feature",
  "properties": {
    "addr:full":"Route De Mons 24 Binche Hainaut 7130",
    "addr:housenumber":"24",
    "addr:postcode":"7130",
    "addr:street":"Route De Mons",
    "iso:country":"BE",
    "sg:address":"Route De Mons 24",
    "sg:city":"Binche",
    "sg:classifiers":[
        {
            "category":"Shopping",
            "subcategory":"Bridal",
            "type":"Retail Goods"
        }
    ],
    "sg:phone":"+32 64 33 50 74",
    "sg:postcode":"7130",
    "sg:province":"Hainaut",
    "sg:tags":[
        "list",
        "-",
        "present",
        "wedding"
    ],
    "wof:name":"Lebeau",
    "wof:placetype":"venue"
},
  "geometry": {"coordinates":[4.1647529602,50.4128837585],"type":"Point"}
}