{
  "type": "Feature",
  "properties": {
    "addr:full":"Issegem 8 Oosterzele Oost-Vlaanderen 9860",
    "addr:housenumber":"8",
    "addr:postcode":"9860",
    "addr:street":"Issegem;Oost-Vlaanderen",
    "iso:country":"BE",
    "sg:address":"Issegem 8",
    "sg:city":"Oosterzele",
    "sg:orig_category":"Eleveurs and marchands de porcs. Eleveurs de bovins",
    "sg:phone":"+32 9 362 60 13",
    "sg:postcode":"9860",
    "sg:province":"Oost-Vlaanderen",
    "wof:name":"Raphael De Paepe",
    "wof:placetype":"venue"
},
  "geometry": {"coordinates":[3.803344965,50.9291534424],"type":"Point"}
}