{
  "type": "Feature",
  "properties": {
    "addr:full":"Rue De La Station 148 Sint-genesius-rode/rhode-saint-genese Vlaams-Brabant 1640",
    "addr:housenumber":"148",
    "addr:postcode":"1640",
    "addr:street":"Rue De La Station",
    "iso:country":"BE",
    "sg:address":"Rue De La Station 148",
    "sg:city":"Sint-genesius-rode/rhode-saint-genese",
    "sg:orig_category":"Boucheries",
    "sg:phone":"+32 2 380 96 59",
    "sg:postcode":"1640",
    "sg:province":"Vlaams-Brabant",
    "wof:name":"F. Swaelens",
    "wof:placetype":"venue"
},
  "geometry": {"coordinates":[4.3585948944,50.7488861084],"type":"Point"}
}