{
  "type": "Feature",
  "properties": {
    "addr:full":"Godfried Kurthstraat 1ba6 Asse Vlaams-Brabant 1730",
    "addr:postcode":"1730",
    "addr:street":"Godfried Kurthstraat 1Ba6",
    "iso:country":"BE",
    "sg:address":"Godfried Kurthstraat 1ba6",
    "sg:city":"Asse",
    "sg:orig_category":"Services de recherches and bureaux de d\u00e9tectives",
    "sg:phone":"+32 54 58 07 96",
    "sg:postcode":"1730",
    "sg:province":"Vlaams-Brabant",
    "wof:name":"Patrick Meskens",
    "wof:placetype":"venue"
},
  "geometry": {"coordinates":[4.1932821274,50.9139938354],"type":"Point"}
}