{
  "type": "Feature",
  "properties": {
    "iso:country":"BE",
    "sg:address":"Boulevard De L'europe 3",
    "sg:city":"Wavre",
    "sg:classifiers":[
        {
            "category":"Shopping",
            "subcategory":"Florist",
            "type":"Retail Goods"
        }
    ],
    "sg:phone":"+32 10 68 17 33",
    "sg:postcode":"1300",
    "sg:province":"Brabant Wallon",
    "wof:name":"Tristun & Lola",
    "wof:placetype":"venue"
},
  "geometry": {"coordinates":[4.6100921631,50.7142791748],"type":"Point"}
}