{
  "type": "Feature",
  "properties": {
    "iso:country":"BE",
    "sg:address":"Square Ren\u00c9 Larcier 7",
    "sg:city":"Tubize",
    "sg:orig_category":"Enseignement maternel and primaire",
    "sg:phone":"+32 2 355 65 32",
    "sg:postcode":"1480",
    "sg:province":"Brabant Wallon",
    "wof:name":"Ecole Fond. Communale",
    "wof:placetype":"venue"
},
  "geometry": {"coordinates":[4.225230217,50.6869659424],"type":"Point"}
}