{
  "type": "Feature",
  "properties": {
    "addr:full":"Hoekstraat 21 Bocholt Limburg 3950",
    "addr:housenumber":"21",
    "addr:postcode":"3950",
    "addr:street":"Hoekstraat",
    "iso:country":"BE",
    "sg:address":"Hoekstraat 21",
    "sg:city":"Bocholt",
    "sg:orig_category":"Catering and organisatie van feesten Voedingsspeciaalzaken",
    "sg:phone":"+32 89 47 25 33",
    "sg:postcode":"3950",
    "sg:province":"Limburg",
    "wof:name":"La Petite Gastronomie",
    "wof:placetype":"venue"
},
  "geometry": {"coordinates":[5.5921411514,51.1901473999],"type":"Point"}
}