{
  "type": "Feature",
  "properties": {
    "addr:full":"Rue Albert L. 175 Erquelinnes Hainaut 6560",
    "addr:housenumber":"175",
    "addr:postcode":"6560",
    "addr:street":"Rue Albert L.",
    "iso:country":"BE",
    "sg:address":"Rue Albert L. 175",
    "sg:city":"Erquelinnes",
    "sg:classifiers":[
        {
            "category":"Banks & Credit Unions",
            "subcategory":"Bank",
            "type":"Services"
        }
    ],
    "sg:phone":"+32 81 55 67 55",
    "sg:postcode":"6560",
    "sg:province":"Hainaut",
    "wof:name":"Cr\u00e9dit Communal",
    "wof:placetype":"venue"
},
  "geometry": {"coordinates":[4.1163201332,50.3063735962],"type":"Point"}
}