{
  "type": "Feature",
  "properties": {
    "iso:country":"BE",
    "sg:address":"Kortrijkseweg 160",
    "sg:city":"Waregem (beveren-leie)",
    "sg:orig_category":"Non-Classified Establishments",
    "sg:phone":"+32 56 71 38 89",
    "sg:postcode":"8791",
    "sg:province":"West-Vlaanderen",
    "wof:name":"Debel M-deprez",
    "wof:placetype":"venue"
},
  "geometry": {"coordinates":[3.3427519798,50.8719825745],"type":"Point"}
}