{
  "type": "Feature",
  "properties": {
    "addr:full":"Nonnenstraat 12 Turnhout Antwerpen 2300",
    "addr:housenumber":"12",
    "addr:postcode":"2300",
    "addr:street":"Nonnenstraat",
    "iso:country":"BE",
    "sg:address":"Nonnenstraat 12",
    "sg:city":"Turnhout",
    "sg:classifiers":[
        {
            "category":"Personal",
            "subcategory":"Beauty Salon",
            "type":"Services"
        }
    ],
    "sg:phone":"+32 14 41 32 83",
    "sg:postcode":"2300",
    "sg:province":"Antwerpen",
    "wof:name":"Babs Schoonheidsinstituut",
    "wof:placetype":"venue"
},
  "geometry": {"coordinates":[4.9544382095,51.3196296692],"type":"Point"}
}