{
  "type": "Feature",
  "properties": {
    "iso:country":"BE",
    "sg:address":"Stationsstraat 20",
    "sg:city":"Dilbeek",
    "sg:orig_category":"Chemicali\u00ebn Gh Winkelinrichting and handelsuitrusting Gh",
    "sg:phone":"+32 2 481 70 20",
    "sg:postcode":"1702",
    "sg:province":"Vlaams-Brabant",
    "wof:name":"Fa. Kortman Intradal",
    "wof:placetype":"venue"
},
  "geometry": {"coordinates":[4.2738242149,50.8692131042],"type":"Point"}
}