{
  "type": "Feature",
  "properties": {
    "iso:country":"BE",
    "sg:address":"Rue Des Hambeaux 17",
    "sg:city":"Bi\u00e8vre (monceau-en-ardenne)",
    "sg:orig_category":"Non-Classified Establishments",
    "sg:phone":"+32 61 51 34 71",
    "sg:postcode":"5555",
    "sg:province":"Namur",
    "wof:name":"Bergerie De Bellefontaine",
    "wof:placetype":"venue"
},
  "geometry": {"coordinates":[4.975030899,49.9179534912],"type":"Point"}
}