{
  "type": "Feature",
  "properties": {
    "addr:full":"Le Pays Li\u00c8ge 33 Namur Namur 5020",
    "addr:housenumber":"33",
    "addr:postcode":"5020",
    "iso:country":"BE",
    "sg:address":"Le Pays Li\u00c8ge 33",
    "sg:city":"Namur",
    "sg:orig_category":"Assistances juridiques. Conseillers fiscaux. Comptables",
    "sg:phone":"+32 81 44 60 54",
    "sg:postcode":"5020",
    "sg:province":"Namur",
    "wof:name":"Massaut",
    "wof:placetype":"venue"
},
  "geometry": {"coordinates":[4.8121848106,50.4292907715],"type":"Point"}
}