{
  "type": "Feature",
  "properties": {
    "iso:country":"BE",
    "sg:address":"Rempart Des Arquebusiers 25",
    "sg:city":"Vise",
    "sg:orig_category":"M\u00e9decins and sp\u00e9cialistes. M\u00e9decines alternatives",
    "sg:phone":"+32 4 379 77 74",
    "sg:postcode":"4600",
    "sg:province":"Li\u00e8ge",
    "wof:name":"Pierre Jacquemart",
    "wof:placetype":"venue"
},
  "geometry": {"coordinates":[5.6967859268,50.7346153259],"type":"Point"}
}