{
  "type": "Feature",
  "properties": {
    "iso:country":"BE",
    "sg:address":"Grote Zavel 3",
    "sg:city":"Brussel/bruxelles",
    "sg:orig_category":"Zalen voor culturele evenementen",
    "sg:phone":"+32 2 513 52 19",
    "sg:postcode":"1000",
    "sg:province":"Bruxelles-Capitale",
    "wof:name":"Galerie Lorelei",
    "wof:placetype":"venue"
},
  "geometry": {"coordinates":[4.354282856,50.8415145874],"type":"Point"}
}