{
  "type": "Feature",
  "properties": {
    "addr:full":"Rue Brouck Au Tilleul 15a Bassenge (glons) Li\u00e8ge 4690",
    "addr:housenumber":"15a",
    "addr:postcode":"4690",
    "addr:street":"Rue Brouck Au Tilleul;Glons",
    "iso:country":"BE",
    "sg:address":"Rue Brouck Au Tilleul 15a",
    "sg:city":"Bassenge (glons)",
    "sg:classifiers":[
        {
            "category":"Food & Beverages",
            "subcategory":"Liquor & Beverages",
            "type":"Retail Goods"
        }
    ],
    "sg:phone":"+32 4 286 15 54",
    "sg:postcode":"4690",
    "sg:province":"Li\u00e8ge",
    "sg:tags":[
        "-",
        "spirit",
        "wine"
    ],
    "wof:name":"Maloir Et Fils Sprl",
    "wof:placetype":"venue"
},
  "geometry": {"coordinates":[5.5446481705,50.75548172],"type":"Point"}
}