{
  "type": "Feature",
  "properties": {
    "iso:country":"BE",
    "sg:address":"Chauss\u00c9e De Charleroi 46",
    "sg:city":"Nivelles",
    "sg:orig_category":"Plomberie, chauffage and installations sanitaires",
    "sg:phone":"+32 67 21 85 90",
    "sg:postcode":"1400",
    "sg:province":"Brabant Wallon",
    "wof:name":"Chauffage & Sanitaire Yvan",
    "wof:placetype":"venue"
},
  "geometry": {"coordinates":[4.3380918503,50.5825805664],"type":"Point"}
}