{
  "type": "Feature",
  "properties": {
    "iso:country":"BE",
    "sg:address":"Eugenie Terlinckplein 13",
    "sg:city":"Koksijde",
    "sg:classifiers":[
        {
            "category":"Restaurant",
            "type":"Food & Drink"
        }
    ],
    "sg:phone":"+32 58 51 36 71",
    "sg:postcode":"8670",
    "sg:province":"West-Vlaanderen",
    "wof:name":"Piccolo",
    "wof:placetype":"venue"
},
  "geometry": {"coordinates":[2.6334519386,51.1202430725],"type":"Point"}
}