{
  "type": "Feature",
  "properties": {
    "iso:country":"BE",
    "sg:address":"Drieslaan 54",
    "sg:city":"Wevelgem (groot)",
    "sg:classifiers":[
        {
            "category":"Building & Trades",
            "subcategory":"Construction",
            "type":"Services"
        }
    ],
    "sg:phone":"+32 56 42 49 33",
    "sg:postcode":"8560",
    "sg:province":"West-Vlaanderen",
    "sg:tags":[
        "gr",
        "la",
        "de",
        "\u00e9quipement",
        "pour",
        "machine",
        "location",
        "equipements"
    ],
    "wof:name":"Alain Durnez",
    "wof:placetype":"venue"
},
  "geometry": {"coordinates":[3.1773190498,50.8470001221],"type":"Point"}
}