{
  "type": "Feature",
  "properties": {
    "iso:country":"BE",
    "sg:address":"Vuurkruisenlaan 12",
    "sg:city":"Koksijde",
    "sg:classifiers":[
        {
            "category":"Arena",
            "subcategory":"Sports Club",
            "type":"Entertainment"
        }
    ],
    "sg:phone":"+32 58 52 14 01",
    "sg:postcode":"8670",
    "sg:province":"West-Vlaanderen",
    "sg:tags":[
        "martial art",
        "accessory"
    ],
    "wof:name":"Aikido Traditionnel Ko Budo",
    "wof:placetype":"venue"
},
  "geometry": {"coordinates":[2.6173610687,51.1083602905],"type":"Point"}
}