{
  "type": "Feature",
  "properties": {
    "iso:country":"BE",
    "sg:address":"Izegemsestraat 36",
    "sg:city":"Roeselare",
    "sg:orig_category":"Instituts de beaut\u00e9. Centres de relaxation and bien-\u00eatre",
    "sg:phone":"+32 51 24 43 55",
    "sg:postcode":"8800",
    "sg:province":"West-Vlaanderen",
    "wof:name":"Braeye D.",
    "wof:placetype":"venue"
},
  "geometry": {"coordinates":[3.158509016,50.9319953918],"type":"Point"}
}