{
  "type": "Feature",
  "properties": {
    "addr:full":"Kranenburgstraat 22 Scherpenheuvel-zichem (zichem) Vlaams-Brabant 3271",
    "addr:housenumber":"22",
    "addr:postcode":"3271",
    "addr:street":"Kranenburgstraat",
    "iso:country":"BE",
    "sg:address":"Kranenburgstraat 22",
    "sg:city":"Scherpenheuvel-zichem (zichem)",
    "sg:classifiers":[
        {
            "category":"Insurance",
            "subcategory":"Insurance Agent",
            "type":"Services"
        }
    ],
    "sg:phone":"+32 13 77 19 14",
    "sg:postcode":"3271",
    "sg:province":"Vlaams-Brabant",
    "sg:tags":[
        "broker"
    ],
    "wof:name":"Van Dingenen P",
    "wof:placetype":"venue"
},
  "geometry": {"coordinates":[4.9884490967,51.0006217957],"type":"Point"}
}