{
  "type": "Feature",
  "properties": {
    "addr:full":"Klaveren Aas 19 Beveren (beveren-waas) Oost-Vlaanderen 9120",
    "addr:housenumber":"19",
    "addr:postcode":"9120",
    "addr:street":"Aas;Oost-Vlaanderen",
    "iso:country":"BE",
    "sg:address":"Klaveren Aas 19",
    "sg:city":"Beveren (beveren-waas)",
    "sg:classifiers":[
        {
            "category":"Health Services",
            "subcategory":"Health Practitioner",
            "type":"Services"
        }
    ],
    "sg:phone":"+32 3 755 35 90",
    "sg:postcode":"9120",
    "sg:province":"Oost-Vlaanderen",
    "sg:tags":[
        "physiotherapist"
    ],
    "wof:name":"De Cock Kristof",
    "wof:placetype":"venue"
},
  "geometry": {"coordinates":[4.2277431488,51.2075271606],"type":"Point"}
}