{
  "type": "Feature",
  "properties": {
    "addr:full":"Raversijdestraat 16 Oostende West-Vlaanderen 8400",
    "addr:housenumber":"16",
    "addr:postcode":"8400",
    "addr:street":"Raversijdestraat",
    "iso:country":"BE",
    "sg:address":"Raversijdestraat 16",
    "sg:city":"Oostende",
    "sg:orig_category":"Boucheries",
    "sg:phone":"+32 59 70 80 83",
    "sg:postcode":"8400",
    "sg:province":"West-Vlaanderen",
    "wof:name":"Beenhouwerij Peter",
    "wof:placetype":"venue"
},
  "geometry": {"coordinates":[2.9126999378,51.2312583923],"type":"Point"}
}