{
  "type": "Feature",
  "properties": {
    "iso:country":"BE",
    "sg:address":"Breulstraat 62",
    "sg:city":"Moorslede",
    "sg:orig_category":"Kapsalons",
    "sg:phone":"+32 51 78 07 17",
    "sg:postcode":"8890",
    "sg:province":"West-Vlaanderen",
    "wof:name":"Heidy Kuypers",
    "wof:placetype":"venue"
},
  "geometry": {"coordinates":[3.0679121017,50.8900260925],"type":"Point"}
}