{
  "type": "Feature",
  "properties": {
    "addr:full":"Au Fonds R\u00e2ce 38 Waremme Li\u00e8ge 4300",
    "addr:housenumber":"38",
    "addr:postcode":"4300",
    "addr:street":"Ra\u0302Ce",
    "iso:country":"BE",
    "sg:address":"Au Fonds R\u00e2ce 38",
    "sg:city":"Waremme",
    "sg:classifiers":[
        {
            "category":"Wholesale",
            "subcategory":"Computers",
            "type":"Manufacturing & Wholesale Goods"
        }
    ],
    "sg:phone":"+32 19 33 01 52",
    "sg:postcode":"4300",
    "sg:province":"Li\u00e8ge",
    "sg:tags":[
        "cabling",
        "processing",
        "-",
        "data"
    ],
    "wof:name":"N.c.s.-network Cabling Solutions",
    "wof:placetype":"venue"
},
  "geometry": {"coordinates":[5.2633738518,50.6934585571],"type":"Point"}
}