{
  "type": "Feature",
  "properties": {
    "addr:full":"Ambachtenstraat 52 Izegem West-Vlaanderen 8870",
    "addr:housenumber":"52",
    "addr:postcode":"8870",
    "addr:street":"Ambachtenstraat",
    "iso:country":"BE",
    "sg:address":"Ambachtenstraat 52",
    "sg:city":"Izegem",
    "sg:classifiers":[
        {
            "category":"Home & Garden",
            "subcategory":"Furniture",
            "type":"Retail Goods"
        }
    ],
    "sg:phone":"+32 51 30 40 82",
    "sg:postcode":"8870",
    "sg:province":"West-Vlaanderen",
    "sg:tags":[
        "fab",
        "meubelen",
        "diverse"
    ],
    "wof:name":"Vandecasteele Marc & Co",
    "wof:placetype":"venue"
},
  "geometry": {"coordinates":[3.1859440804,50.9208030701],"type":"Point"}
}