{
  "type": "Feature",
  "properties": {
    "addr:full":"Lebeaustraat 75 Brussel/bruxelles Bruxelles-Capitale 1000",
    "addr:housenumber":"75",
    "addr:postcode":"1000",
    "addr:street":"Lebeaustraat;/",
    "iso:country":"BE",
    "sg:address":"Lebeaustraat 75",
    "sg:city":"Brussel/bruxelles",
    "sg:classifiers":[
        {
            "category":"Restaurant",
            "type":"Food & Drink"
        }
    ],
    "sg:phone":"+32 2 512 01 70",
    "sg:postcode":"1000",
    "sg:province":"Bruxelles-Capitale",
    "wof:name":"Restaurant Cap Sablon",
    "wof:placetype":"venue"
},
  "geometry": {"coordinates":[4.3539838791,50.8417358398],"type":"Point"}
}