{
  "type": "Feature",
  "properties": {
    "iso:country":"BE",
    "sg:address":"All\u00e9e Du Ploche 2",
    "sg:city":"Nivelles",
    "sg:classifiers":[
        {
            "category":"Health Services",
            "subcategory":"Doctor",
            "type":"Services"
        }
    ],
    "sg:phone":"+32 67 22 05 99",
    "sg:postcode":"1400",
    "sg:province":"Brabant Wallon",
    "sg:tags":[
        "medicinephysicians",
        "surgeon"
    ],
    "wof:name":"Cambier Chantal",
    "wof:placetype":"venue"
},
  "geometry": {"coordinates":[4.3184080124,50.5904846191],"type":"Point"}
}