{
  "type": "Feature",
  "properties": {
    "addr:full":"Ardooisesteenweg 12 Roeselare West-Vlaanderen 8800",
    "addr:housenumber":"12",
    "addr:postcode":"8800",
    "addr:street":"Ardooisesteenweg",
    "iso:country":"BE",
    "sg:address":"Ardooisesteenweg 12",
    "sg:city":"Roeselare",
    "sg:orig_category":"V\u00eatements",
    "sg:phone":"+32 51 24 14 40",
    "sg:postcode":"8800",
    "sg:province":"West-Vlaanderen",
    "wof:name":"Kells Irish Woollens",
    "wof:placetype":"venue"
},
  "geometry": {"coordinates":[3.1313409805,50.9487953186],"type":"Point"}
}