{
  "type": "Feature",
  "properties": {
    "addr:full":"Rue Des Carri\u00c8res 83 Jemeppe-sur-sambre Namur 5190",
    "addr:housenumber":"83",
    "addr:postcode":"5190",
    "addr:street":"Rue Des Carrie\u0300Res",
    "iso:country":"BE",
    "sg:address":"Rue Des Carri\u00c8res 83",
    "sg:city":"Jemeppe-sur-sambre",
    "sg:orig_category":"Mat\u00e9riaux de construction D\u00e9molition d\u00b4immeubles and terrassements",
    "sg:phone":"+32 81 63 42 73",
    "sg:postcode":"5190",
    "sg:province":"Namur",
    "wof:name":"Claude Debry",
    "wof:placetype":"venue"
},
  "geometry": {"coordinates":[4.6703448296,50.4645042419],"type":"Point"}
}