{
  "type": "Feature",
  "properties": {
    "addr:full":"Ophovenstraat 21 Maaseik (neeroeteren) Limburg 3680",
    "addr:housenumber":"21",
    "addr:postcode":"3680",
    "addr:street":"Ophovenstraat",
    "iso:country":"BE",
    "sg:address":"Ophovenstraat 21",
    "sg:city":"Maaseik (neeroeteren)",
    "sg:classifiers":[
        {
            "category":"Health Services",
            "subcategory":"Dentist",
            "type":"Services"
        }
    ],
    "sg:phone":"+32 89 86 64 45",
    "sg:postcode":"3680",
    "sg:province":"Limburg",
    "wof:name":"Janssen Rina",
    "wof:placetype":"venue"
},
  "geometry": {"coordinates":[5.791285038,51.0954208374],"type":"Point"}
}