{
  "type": "Feature",
  "properties": {
    "addr:full":"Turnhoutsebaan 186 Wijnegem Antwerpen 2110",
    "addr:housenumber":"186",
    "addr:postcode":"2110",
    "addr:street":"Turnhoutsebaan",
    "iso:country":"BE",
    "sg:address":"Turnhoutsebaan 186",
    "sg:city":"Wijnegem",
    "sg:orig_category":"Avocats and conseillers juridiques",
    "sg:phone":"+32 3 354 42 20",
    "sg:postcode":"2110",
    "sg:province":"Antwerpen",
    "wof:name":"Hilde Van Den Bogaert",
    "wof:placetype":"venue"
},
  "geometry": {"coordinates":[4.511297226,51.2258682251],"type":"Point"}
}