{
  "type": "Feature",
  "properties": {
    "iso:country":"BE",
    "sg:address":"Dwarsstraat 18",
    "sg:city":"Diksmuide",
    "sg:orig_category":"Eleveurs and marchands de porcs. Eleveurs de bovins",
    "sg:phone":"+32 51 50 04 54",
    "sg:postcode":"8600",
    "sg:province":"West-Vlaanderen",
    "wof:name":"Gilbert Inghelbrecht",
    "wof:placetype":"venue"
},
  "geometry": {"coordinates":[2.9120810032,51.1057815552],"type":"Point"}
}