{
  "type": "Feature",
  "properties": {
    "iso:country":"BE",
    "sg:address":"Koksijdestraat 9",
    "sg:city":"Veurne",
    "sg:classifiers":[
        {
            "category":"Manufacturing",
            "subcategory":"Building Materials",
            "type":"Manufacturing & Wholesale Goods"
        }
    ],
    "sg:phone":"+32 58 31 19 44",
    "sg:postcode":"8630",
    "sg:province":"West-Vlaanderen",
    "sg:tags":[
        "fixture",
        "store"
    ],
    "wof:name":"Metaalinterieur Aernoudt",
    "wof:placetype":"venue"
},
  "geometry": {"coordinates":[2.6422629356,51.0824813843],"type":"Point"}
}