{
  "type": "Feature",
  "properties": {
    "iso:country":"BE",
    "sg:address":"Rue De Termonde 51",
    "sg:city":"Sint-agatha-berchem/berchem-sainte-agathe",
    "sg:orig_category":"Cr\u00e8ches and garderies d'enfants",
    "sg:phone":"+32 2 465 03 86",
    "sg:postcode":"1082",
    "sg:province":"Bruxelles-Capitale",
    "wof:name":"Chenapans (les)",
    "wof:placetype":"venue"
},
  "geometry": {"coordinates":[4.3032851219,50.8694343567],"type":"Point"}
}