{
  "type": "Feature",
  "properties": {
    "addr:full":"Soldatendreef 1a Beveren (beveren-waas) Oost-Vlaanderen 9120",
    "addr:housenumber":"1a",
    "addr:postcode":"9120",
    "addr:street":"Soldatendreef;Oost-Vlaanderen",
    "iso:country":"BE",
    "sg:address":"Soldatendreef 1a",
    "sg:city":"Beveren (beveren-waas)",
    "sg:classifiers":[
        {
            "category":"Retail",
            "subcategory":"Auto Repair",
            "type":"Services"
        }
    ],
    "sg:phone":"+32 3 775 87 86",
    "sg:postcode":"9120",
    "sg:province":"Oost-Vlaanderen",
    "sg:tags":[
        "garage"
    ],
    "wof:name":"De Ridder - Verhulst",
    "wof:placetype":"venue"
},
  "geometry": {"coordinates":[4.2596750259,51.217716217],"type":"Point"}
}