{
  "type": "Feature",
  "properties": {
    "addr:full":"Gentsesteenweg 1430 Sint-agatha-berchem/berchem-sa Bruxelles-Capitale 1082",
    "addr:housenumber":"1430",
    "addr:postcode":"1082",
    "addr:street":"Gentsesteenweg",
    "iso:country":"BE",
    "sg:address":"Gentsesteenweg 1430",
    "sg:city":"Sint-agatha-berchem/berchem-sa",
    "sg:classifiers":[
        {
            "category":"Fast Food",
            "type":"Food & Drink"
        }
    ],
    "sg:phone":"+32 2 469 10 09",
    "sg:postcode":"1082",
    "sg:province":"Bruxelles-Capitale",
    "sg:tags":[
        "meeneem",
        "restaurant"
    ],
    "wof:name":"Brasserie De La Gare",
    "wof:placetype":"venue"
},
  "geometry": {"coordinates":[4.2896928787,50.8719902039],"type":"Point"}
}