{
  "type": "Feature",
  "properties": {
    "iso:country":"BE",
    "sg:address":"Grootstraat 114",
    "sg:city":"Alken",
    "sg:orig_category":"Fruitteelt",
    "sg:phone":"+32 11 31 25 55",
    "sg:postcode":"3570",
    "sg:province":"Limburg",
    "wof:name":"Jos Piccart",
    "wof:placetype":"venue"
},
  "geometry": {"coordinates":[5.3271141052,50.8794937134],"type":"Point"}
}