{
  "type": "Feature",
  "properties": {
    "addr:full":"Rue Des Banni\u00e8res 12 Bruxelles (woluwe-saint-pierre) Bruxelles-Capitale 1150",
    "addr:housenumber":"12",
    "addr:postcode":"1150",
    "addr:street":"Rue Des Bannie\u0300Res",
    "iso:country":"BE",
    "sg:address":"Rue Des Banni\u00e8res 12",
    "sg:city":"Bruxelles (woluwe-saint-pierre)",
    "sg:classifiers":[
        {
            "category":"Health Services",
            "subcategory":"Health Practitioner",
            "type":"Services"
        }
    ],
    "sg:phone":"+32 2 772 30 18",
    "sg:postcode":"1150",
    "sg:province":"Bruxelles-Capitale",
    "sg:tags":[
        "physiotherapist"
    ],
    "wof:name":"Libotte Sylvie",
    "wof:placetype":"venue"
},
  "geometry": {"coordinates":[4.4331030846,50.8397483826],"type":"Point"}
}