{
  "type": "Feature",
  "properties": {
    "iso:country":"BE",
    "sg:address":"Rue Floris 61",
    "sg:city":"Bruxelles (schaerbeek)",
    "sg:classifiers":[
        {
            "category":"Personal",
            "subcategory":"Hair Removal",
            "type":"Services"
        }
    ],
    "sg:phone":"+32 2 216 49 45",
    "sg:postcode":"1030",
    "sg:province":"Bruxelles-Capitale",
    "sg:tags":[
        "whol",
        "-",
        "fur"
    ],
    "wof:name":"Berger D Sprl",
    "wof:placetype":"venue"
},
  "geometry": {"coordinates":[4.3704972267,50.8684005737],"type":"Point"}
}