{
  "type": "Feature",
  "properties": {
    "iso:country":"BE",
    "sg:address":"Rue Gustave Bo\u00cbl 69",
    "sg:city":"La Louviere",
    "sg:orig_category":"Boissons Gr",
    "sg:phone":"+32 64 22 69 56",
    "sg:postcode":"7100",
    "sg:province":"Hainaut",
    "wof:name":"Centrabra",
    "wof:placetype":"venue"
},
  "geometry": {"coordinates":[4.1725029945,50.4794082642],"type":"Point"}
}