{
  "type": "Feature",
  "properties": {
    "addr:full":"Brusselsesteenweg 117 Gent (ledeberg) Oost-Vlaanderen 9050",
    "addr:housenumber":"117",
    "addr:postcode":"9050",
    "addr:street":"Brusselsesteenweg",
    "iso:country":"BE",
    "sg:address":"Brusselsesteenweg 117",
    "sg:city":"Gent (ledeberg)",
    "sg:classifiers":[
        {
            "category":"Parking",
            "subcategory":"Lot",
            "type":"Transportation"
        }
    ],
    "sg:phone":"+32 9 225 70 67",
    "sg:postcode":"9050",
    "sg:province":"Oost-Vlaanderen",
    "sg:tags":[
        "armoured",
        "door",
        "fireproof"
    ],
    "wof:name":"Beco",
    "wof:placetype":"venue"
},
  "geometry": {"coordinates":[3.7453389168,51.0395011902],"type":"Point"}
}