{
  "type": "Feature",
  "properties": {
    "iso:country":"BE",
    "sg:address":"Rue Du Centre 4",
    "sg:city":"Anh\u00e9e",
    "sg:classifiers":[
        {
            "category":"Health Services",
            "subcategory":"Nursing And Care Facility",
            "type":"Services"
        }
    ],
    "sg:phone":"+32 82 61 13 55",
    "sg:postcode":"5537",
    "sg:province":"Namur",
    "sg:tags":[
        "home"
    ],
    "wof:name":"Laloux B",
    "wof:placetype":"venue"
},
  "geometry": {"coordinates":[4.8428702354,50.305065155],"type":"Point"}
}