{
  "type": "Feature",
  "properties": {
    "addr:full":"Rue De Baume 4 La Louviere Hainaut 7100",
    "addr:housenumber":"4",
    "addr:postcode":"7100",
    "addr:street":"Rue De Baume",
    "iso:country":"BE",
    "sg:address":"Rue De Baume 4",
    "sg:city":"La Louviere",
    "sg:orig_category":"Librairies. Journaux. Tabac. Fournitures de bureau",
    "sg:phone":"+32 64 22 35 40",
    "sg:postcode":"7100",
    "sg:province":"Hainaut",
    "wof:name":"Librairie Tecni Tivoli",
    "wof:placetype":"venue"
},
  "geometry": {"coordinates":[4.1976528168,50.4746894836],"type":"Point"}
}