{
  "type": "Feature",
  "properties": {
    "iso:country":"BE",
    "sg:address":"Stationsstraat 110",
    "sg:city":"Essen",
    "sg:classifiers":[
        {
            "category":"Building & Trades",
            "subcategory":"Plumbing",
            "type":"Services"
        }
    ],
    "sg:phone":"+32 3 667 27 28",
    "sg:postcode":"2910",
    "sg:province":"Antwerpen",
    "sg:tags":[
        "contractor"
    ],
    "wof:name":"Van Tilburg & Zn Bvba",
    "wof:placetype":"venue"
},
  "geometry": {"coordinates":[4.460395813,51.4653167725],"type":"Point"}
}