{
  "type": "Feature",
  "properties": {
    "addr:full":"Keizershof 7 Beerse Antwerpen 2340",
    "addr:housenumber":"7",
    "addr:postcode":"2340",
    "addr:street":"Keizershof",
    "iso:country":"BE",
    "sg:address":"Keizershof 7",
    "sg:city":"Beerse",
    "sg:orig_category":"D\u00e9molition d\u00b4immeubles and terrassements",
    "sg:phone":"+32 14 61 42 38",
    "sg:postcode":"2340",
    "sg:province":"Antwerpen",
    "wof:name":"Andre Van Echelpoel",
    "wof:placetype":"venue"
},
  "geometry": {"coordinates":[4.8378920555,51.3329620361],"type":"Point"}
}