{
  "type": "Feature",
  "properties": {
    "iso:country":"BE",
    "sg:address":"Molenstraat 33",
    "sg:city":"Merelbeke",
    "sg:orig_category":"Rundveehouders",
    "sg:phone":"+32 9 362 94 47",
    "sg:postcode":"9820",
    "sg:province":"Oost-Vlaanderen",
    "wof:name":"Antoine Vandriessche",
    "wof:placetype":"venue"
},
  "geometry": {"coordinates":[3.7319729328,50.9667701721],"type":"Point"}
}