{
  "type": "Feature",
  "properties": {
    "addr:full":"Rue Neuve 17 Stavelot Li\u00e8ge 4970",
    "addr:housenumber":"17",
    "addr:postcode":"4970",
    "addr:street":"Rue Neuve",
    "iso:country":"BE",
    "sg:address":"Rue Neuve 17",
    "sg:city":"Stavelot",
    "sg:orig_category":"Drogueries",
    "sg:phone":"+32 80 86 20 46",
    "sg:postcode":"4970",
    "sg:province":"Li\u00e8ge",
    "wof:name":"L'arc En Ciel",
    "wof:placetype":"venue"
},
  "geometry": {"coordinates":[5.9257321358,50.3919334412],"type":"Point"}
}