{
  "type": "Feature",
  "properties": {
    "iso:country":"BE",
    "sg:address":"Bruggenhoofdweg 10",
    "sg:city":"Geel",
    "sg:classifiers":[
        {
            "category":"Building & Trades",
            "subcategory":"Landscaping Services",
            "type":"Services"
        }
    ],
    "sg:phone":"+32 14 58 94 47",
    "sg:postcode":"2440",
    "sg:province":"Antwerpen",
    "sg:tags":[
        "gardening",
        "garden",
        "maintenance"
    ],
    "wof:name":"Remy",
    "wof:placetype":"venue"
},
  "geometry": {"coordinates":[4.9609060287,51.1326255798],"type":"Point"}
}