{
  "type": "Feature",
  "properties": {
    "addr:full":"Nijvelsebaan 36 Huldenberg Vlaams-Brabant 3040",
    "addr:housenumber":"36",
    "addr:postcode":"3040",
    "addr:street":"Nijvelsebaan",
    "iso:country":"BE",
    "sg:address":"Nijvelsebaan 36",
    "sg:city":"Huldenberg",
    "sg:orig_category":"Bloemen and planten",
    "sg:phone":"+32 16 47 75 16",
    "sg:postcode":"3040",
    "sg:province":"Vlaams-Brabant",
    "wof:name":"Edgard Schauwers",
    "wof:placetype":"venue"
},
  "geometry": {"coordinates":[4.6144900322,50.7983703613],"type":"Point"}
}