{
  "type": "Feature",
  "properties": {
    "addr:full":"Avenue D'italie 42 Bruxelles (ixelles) Bruxelles-Capitale 1050",
    "addr:housenumber":"42",
    "addr:postcode":"1050",
    "addr:street":"Avenue D'Italie",
    "iso:country":"BE",
    "sg:address":"Avenue D'italie 42",
    "sg:city":"Bruxelles (ixelles)",
    "sg:classifiers":[
        {
            "category":"Professional",
            "subcategory":"Lawyer & Legal Services",
            "type":"Services"
        }
    ],
    "sg:phone":"+32 2 673 29 65",
    "sg:postcode":"1050",
    "sg:province":"Bruxelles-Capitale",
    "wof:name":"Weyten Edmond",
    "wof:placetype":"venue"
},
  "geometry": {"coordinates":[4.3935480118,50.8035774231],"type":"Point"}
}