{
  "type": "Feature",
  "properties": {
    "addr:full":"Rue Fran\u00c7ois Hellinckx 19 Koekelberg Bruxelles-Capitale 1081",
    "addr:housenumber":"19",
    "addr:postcode":"1081",
    "addr:street":"Rue Franc\u0327Ois Hellinckx",
    "iso:country":"BE",
    "sg:address":"Rue Fran\u00c7ois Hellinckx 19",
    "sg:city":"Koekelberg",
    "sg:orig_category":"Elektrische installaties voor woningen",
    "sg:phone":"+32 495 51 27 82",
    "sg:postcode":"1081",
    "sg:province":"Bruxelles-Capitale",
    "wof:name":"Electrimo",
    "wof:placetype":"venue"
},
  "geometry": {"coordinates":[4.326821804,50.8577270508],"type":"Point"}
}