{
  "type": "Feature",
  "properties": {
    "iso:country":"BE",
    "sg:address":"A.z. O.l.v. Ter Linden",
    "sg:city":"Knokke",
    "sg:classifiers":[
        {
            "category":"Health Services",
            "subcategory":"Doctor",
            "type":"Services"
        }
    ],
    "sg:phone":"+32 50 60 07 34",
    "sg:postcode":"8300",
    "sg:province":"West-Vlaanderen",
    "sg:tags":[
        "medicinephysicians",
        "surgeon"
    ],
    "wof:name":"Geerinckx Paul",
    "wof:placetype":"venue"
},
  "geometry": {"coordinates":[3.2888350487,51.3460388184],"type":"Point"}
}