{
  "type": "Feature",
  "properties": {
    "iso:country":"BE",
    "sg:address":"Stationstraat 98",
    "sg:city":"Houthalen-helchteren",
    "sg:classifiers":[
        {
            "category":"Personal",
            "subcategory":"Beauty Salon",
            "type":"Services"
        }
    ],
    "sg:phone":"+32 11 52 45 73",
    "sg:postcode":"3530",
    "sg:province":"Limburg",
    "sg:tags":[
        "de",
        "coiffure"
    ],
    "wof:name":"Coiffure Anny",
    "wof:placetype":"venue"
},
  "geometry": {"coordinates":[5.3553299904,51.0262145996],"type":"Point"}
}