{
  "type": "Feature",
  "properties": {
    "addr:full":"Sleeuwagen 62 Merchtem Vlaams-Brabant 1785",
    "addr:housenumber":"62",
    "addr:postcode":"1785",
    "addr:street":"Sleeuwagen",
    "iso:country":"BE",
    "sg:address":"Sleeuwagen 62",
    "sg:city":"Merchtem",
    "sg:orig_category":"Varkenskwekers",
    "sg:phone":"+32 52 37 67 06",
    "sg:postcode":"1785",
    "sg:province":"Vlaams-Brabant",
    "wof:name":"Georges Michiels",
    "wof:placetype":"venue"
},
  "geometry": {"coordinates":[4.2185602188,50.9433517456],"type":"Point"}
}