{
  "type": "Feature",
  "properties": {
    "addr:full":"Pierre Corneliskaai 15a Aalst Oost-Vlaanderen 9300",
    "addr:housenumber":"15a",
    "addr:postcode":"9300",
    "iso:country":"BE",
    "sg:address":"Pierre Corneliskaai 15a",
    "sg:city":"Aalst",
    "sg:classifiers":[
        {
            "category":"Home & Garden",
            "subcategory":"Garden Supply",
            "type":"Retail Goods"
        }
    ],
    "sg:phone":"+32 53 70 66 31",
    "sg:postcode":"9300",
    "sg:province":"Oost-Vlaanderen",
    "wof:name":"Aveve T.c. Aalst",
    "wof:placetype":"venue"
},
  "geometry": {"coordinates":[4.0407547951,50.9442405701],"type":"Point"}
}