{
  "type": "Feature",
  "properties": {
    "addr:full":"Rue M\u00c9an 12 Li\u00c8ge Li\u00e8ge 4020",
    "addr:housenumber":"12",
    "addr:postcode":"4020",
    "addr:street":"Rue Me\u0301An",
    "iso:country":"BE",
    "sg:address":"Rue M\u00c9an 12",
    "sg:city":"Li\u00c8ge",
    "sg:orig_category":"Schoonheidssalons",
    "sg:phone":"+32 4 343 20 84",
    "sg:postcode":"4020",
    "sg:province":"Li\u00e8ge",
    "wof:name":"Institut Aqualine",
    "wof:placetype":"venue"
},
  "geometry": {"coordinates":[5.5804901123,50.6380119324],"type":"Point"}
}