{
  "type": "Feature",
  "properties": {
    "iso:country":"BE",
    "sg:address":"Groendalstraat 10",
    "sg:city":"Antwerpen",
    "sg:orig_category":"Instituts de beaut\u00e9",
    "sg:phone":"+32 3 231 96 63",
    "sg:postcode":"2000",
    "sg:province":"Antwerpen",
    "wof:name":"Anne Ostyn",
    "wof:placetype":"venue"
},
  "geometry": {"coordinates":[4.4045891762,51.2174110413],"type":"Point"}
}