{
  "type": "Feature",
  "properties": {
    "addr:full":"Aanaardingsstraat 46 Brussel/bruxelles Bruxelles-Capitale 1000",
    "addr:housenumber":"46",
    "addr:postcode":"1000",
    "addr:street":"Aanaardingsstraat;/",
    "iso:country":"BE",
    "sg:address":"Aanaardingsstraat 46",
    "sg:city":"Brussel/bruxelles",
    "sg:orig_category":"Dranken",
    "sg:phone":"+32 2 534 29 09",
    "sg:postcode":"1000",
    "sg:province":"Bruxelles-Capitale",
    "wof:name":"Lusovins",
    "wof:placetype":"venue"
},
  "geometry": {"coordinates":[4.3445158005,50.8337249756],"type":"Point"}
}