{
  "type": "Feature",
  "properties": {
    "iso:country":"BE",
    "sg:address":"Tempelsstraat 5",
    "sg:city":"Beringen (paal)",
    "sg:classifiers":[
        {
            "category":"Building & Trades",
            "subcategory":"Construction",
            "type":"Services"
        }
    ],
    "sg:phone":"+32 13 66 67 23",
    "sg:postcode":"3583",
    "sg:province":"Limburg",
    "sg:tags":[
        "installation",
        "-",
        "central",
        "heating"
    ],
    "wof:name":"Vanhaeren Bvba",
    "wof:placetype":"venue"
},
  "geometry": {"coordinates":[5.1706700325,51.0389442444],"type":"Point"}
}