{
  "type": "Feature",
  "properties": {
    "addr:full":"Kortrijksesteenweg 653 Gent Oost-Vlaanderen 9000",
    "addr:housenumber":"653",
    "addr:postcode":"9000",
    "addr:street":"Kortrijksesteenweg;Oost-Vlaanderen",
    "iso:country":"BE",
    "sg:address":"Kortrijksesteenweg 653",
    "sg:city":"Gent",
    "sg:classifiers":[
        {
            "category":"Health Services",
            "subcategory":"Doctor",
            "type":"Services"
        }
    ],
    "sg:phone":"+32 9 222 29 65",
    "sg:postcode":"9000",
    "sg:province":"Oost-Vlaanderen",
    "sg:tags":[
        "medicinephysicians",
        "surgeon"
    ],
    "wof:name":"De Cock G",
    "wof:placetype":"venue"
},
  "geometry": {"coordinates":[3.7165100574,51.0352516174],"type":"Point"}
}