{
  "type": "Feature",
  "properties": {
    "addr:full":"Rue Des Combattants 50 La Louvi\u00e8re (haine-saint-pierre) Hainaut 7100",
    "addr:housenumber":"50",
    "addr:postcode":"7100",
    "addr:street":"Rue Des Combattants",
    "iso:country":"BE",
    "sg:address":"Rue Des Combattants 50",
    "sg:city":"La Louvi\u00e8re (haine-saint-pierre)",
    "sg:classifiers":[
        {
            "category":"Professional",
            "subcategory":"Lawyer & Legal Services",
            "type":"Services"
        }
    ],
    "sg:phone":"+32 64 22 26 44",
    "sg:postcode":"7100",
    "sg:province":"Hainaut",
    "sg:tags":[
        "notary"
    ],
    "wof:name":"Bruy\u00e8re M",
    "wof:placetype":"venue"
},
  "geometry": {"coordinates":[4.1850848198,50.4748649597],"type":"Point"}
}