{
  "type": "Feature",
  "properties": {
    "iso:country":"BE",
    "sg:address":"Bohemen 101c",
    "sg:city":"Wichelen",
    "sg:orig_category":"Installation de menuiserie en bois and plastique. Charpentes and couvertures",
    "sg:phone":"+32 52 42 57 39",
    "sg:postcode":"9260",
    "sg:province":"Oost-Vlaanderen",
    "wof:name":"Derde Geert",
    "wof:placetype":"venue"
},
  "geometry": {"coordinates":[3.9922790527,51.001991272],"type":"Point"}
}