{
  "type": "Feature",
  "properties": {
    "iso:country":"BE",
    "sg:address":"Route D'arlon 220",
    "sg:city":"Messancy",
    "sg:orig_category":"Chaussures",
    "sg:phone":"+32 63 38 56 84",
    "sg:postcode":"6780",
    "sg:province":"Luxembourg",
    "wof:name":"Mach 3",
    "wof:placetype":"venue"
},
  "geometry": {"coordinates":[5.812169075,49.6142578125],"type":"Point"}
}