{
  "type": "Feature",
  "properties": {
    "iso:country":"BE",
    "sg:address":"Fr. Verbeekstraat 186",
    "sg:city":"Overijse",
    "sg:classifiers":[
        {
            "category":"Real Estate",
            "subcategory":"Surveying",
            "type":"Services"
        }
    ],
    "sg:phone":"+32 2 657 91 77",
    "sg:postcode":"3090",
    "sg:province":"Vlaams-Brabant",
    "sg:tags":[
        "surveyor",
        "land"
    ],
    "wof:name":"Van Orshoven E",
    "wof:placetype":"venue"
},
  "geometry": {"coordinates":[4.4972820282,50.7699394226],"type":"Point"}
}