{
  "type": "Feature",
  "properties": {
    "addr:full":"Cit\u00c9 Des Fr\u00c8res R\u00c9unis 44 Ch\u00c2telet Hainaut 6200",
    "addr:housenumber":"44",
    "addr:postcode":"6200",
    "addr:street":"Cite\u0301 Des Fre\u0300Res Re\u0301Unis",
    "iso:country":"BE",
    "sg:address":"Cit\u00c9 Des Fr\u00c8res R\u00c9unis 44",
    "sg:city":"Ch\u00c2telet",
    "sg:orig_category":"Sportclubs",
    "sg:phone":"+32 71 39 14 56",
    "sg:postcode":"6200",
    "sg:province":"Hainaut",
    "wof:name":"Les P\u00c9leux",
    "wof:placetype":"venue"
},
  "geometry": {"coordinates":[4.5159068108,50.4185905457],"type":"Point"}
}