{
  "type": "Feature",
  "properties": {
    "addr:full":"Quai Saint-l\u00c9onard 44 Li\u00c8ge Li\u00e8ge 4000",
    "addr:housenumber":"44",
    "addr:postcode":"4000",
    "addr:street":"Quai Saint-Le\u0301Onard",
    "iso:country":"BE",
    "sg:address":"Quai Saint-l\u00c9onard 44",
    "sg:city":"Li\u00c8ge",
    "sg:classifiers":[
        {
            "category":"Shopping Center",
            "type":"Public Place"
        }
    ],
    "sg:phone":"+32 4 227 90 85",
    "sg:postcode":"4000",
    "sg:province":"Li\u00e8ge",
    "sg:tags":[
        "enseignement",
        "formation"
    ],
    "wof:name":"E.n.a.i.p.",
    "wof:placetype":"venue"
},
  "geometry": {"coordinates":[5.5936360359,50.6487159729],"type":"Point"}
}