{
  "type": "Feature",
  "properties": {
    "iso:country":"BE",
    "sg:address":"Dorp 31",
    "sg:city":"Berlare",
    "sg:classifiers":[
        {
            "category":"Bars & Pubs",
            "type":"Food & Drink"
        }
    ],
    "sg:phone":"+32 52 42 29 58",
    "sg:postcode":"9290",
    "sg:province":"Oost-Vlaanderen",
    "wof:name":"Klokke (de)",
    "wof:placetype":"venue"
},
  "geometry": {"coordinates":[4.0037899017,51.025138855],"type":"Point"}
}