{
  "type": "Feature",
  "properties": {
    "iso:country":"BE",
    "sg:address":"Coupure Rechts 170",
    "sg:city":"Gent",
    "sg:classifiers":[
        {
            "category":"Health Services",
            "subcategory":"Dentist",
            "type":"Services"
        }
    ],
    "sg:phone":"+32 9 225 45 25",
    "sg:postcode":"9000",
    "sg:province":"Oost-Vlaanderen",
    "wof:name":"De Smedt V",
    "wof:placetype":"venue"
},
  "geometry": {"coordinates":[3.7136290073,51.0486297607],"type":"Point"}
}