{
  "type": "Feature",
  "properties": {
    "iso:country":"BE",
    "sg:address":"Rue Haute 371-375",
    "sg:city":"Bruxelles",
    "sg:classifiers":[
        {
            "category":"Cemetery",
            "type":"Public Place"
        }
    ],
    "sg:phone":"+32 2 538 35 93",
    "sg:postcode":"1000",
    "sg:province":"Bruxelles-Capitale",
    "sg:tags":[
        "crematory"
    ],
    "wof:name":"Deneyer F",
    "wof:placetype":"venue"
},
  "geometry": {"coordinates":[4.3451747894,50.8341941833],"type":"Point"}
}