{
  "type": "Feature",
  "properties": {
    "addr:full":"Resterheidestraat 8 Hechtel-eksel (hechtel) Limburg 3940",
    "addr:housenumber":"8",
    "addr:postcode":"3940",
    "addr:street":"Resterheidestraat",
    "iso:country":"BE",
    "sg:address":"Resterheidestraat 8",
    "sg:city":"Hechtel-eksel (hechtel)",
    "sg:classifiers":[
        {
            "category":"Transit Center",
            "subcategory":"Freight",
            "type":"Transportation"
        }
    ],
    "sg:phone":"+32 11 73 02 00",
    "sg:postcode":"3940",
    "sg:province":"Limburg",
    "sg:tags":[
        "import",
        "export",
        "-"
    ],
    "wof:name":"Kwimex Trading Company Nv",
    "wof:placetype":"venue"
},
  "geometry": {"coordinates":[5.364795208,51.1255340576],"type":"Point"}
}