{
  "type": "Feature",
  "properties": {
    "iso:country":"BE",
    "sg:address":"Rue De Paepe C\u00e9sar 19",
    "sg:city":"Charleroi (marcinelle)",
    "sg:classifiers":[
        {
            "category":"Education",
            "subcategory":"Special Training",
            "type":"Public Place"
        }
    ],
    "sg:phone":"+32 71 43 58 71",
    "sg:postcode":"6001",
    "sg:province":"Hainaut",
    "sg:tags":[
        "school",
        "language"
    ],
    "wof:name":"Eres Sprl",
    "wof:placetype":"venue"
},
  "geometry": {"coordinates":[4.4434261322,50.4009437561],"type":"Point"}
}