{
  "type": "Feature",
  "properties": {
    "iso:country":"BE",
    "sg:address":"Elsense Steenweg 300",
    "sg:city":"Elsene/ixelles",
    "sg:orig_category":"Antiek",
    "sg:phone":"+32 2 646 26 75",
    "sg:postcode":"1050",
    "sg:province":"Bruxelles-Capitale",
    "wof:name":"Maison Prestige",
    "wof:placetype":"venue"
},
  "geometry": {"coordinates":[4.3710198402,50.8286399841],"type":"Point"}
}