{
  "type": "Feature",
  "properties": {
    "addr:full":"Boulevard Georges Deryck 124 Tubize Brabant Wallon 1480",
    "addr:housenumber":"124",
    "addr:postcode":"1480",
    "addr:street":"Boulevard Georges Deryck;Wallon",
    "iso:country":"BE",
    "sg:address":"Boulevard Georges Deryck 124",
    "sg:city":"Tubize",
    "sg:orig_category":"Salles de spectacles",
    "sg:phone":"+32 2 355 98 95",
    "sg:postcode":"1480",
    "sg:province":"Brabant Wallon",
    "wof:name":"Foyer Culturel",
    "wof:placetype":"venue"
},
  "geometry": {"coordinates":[4.2007198334,50.691028595],"type":"Point"}
}