{
  "type": "Feature",
  "properties": {
    "addr:full":"Antwerpsesteenweg 169 Leopoldsburg Limburg 3970",
    "addr:housenumber":"169",
    "addr:postcode":"3970",
    "addr:street":"Antwerpsesteenweg",
    "iso:country":"BE",
    "sg:address":"Antwerpsesteenweg 169",
    "sg:city":"Leopoldsburg",
    "sg:orig_category":"Rev\u00eatements de sols and murs",
    "sg:phone":"+32 11 34 32 44",
    "sg:postcode":"3970",
    "sg:province":"Limburg",
    "wof:name":"Quadrifoglio",
    "wof:placetype":"venue"
},
  "geometry": {"coordinates":[5.2440500259,51.1315994263],"type":"Point"}
}