{
  "type": "Feature",
  "properties": {
    "iso:country":"BE",
    "sg:address":"Avenue G\u00e9n\u00e9ral M\u00e9decin Derache 117",
    "sg:city":"Bruxelles (ixelles)",
    "sg:classifiers":[
        {
            "category":"Communications",
            "type":"Services"
        }
    ],
    "sg:phone":"+32 2 647 27 62",
    "sg:postcode":"1050",
    "sg:province":"Bruxelles-Capitale",
    "sg:tags":[
        "translator"
    ],
    "wof:name":"Safi M-ch",
    "wof:placetype":"venue"
},
  "geometry": {"coordinates":[4.388299942,50.8139305115],"type":"Point"}
}