{
  "type": "Feature",
  "properties": {
    "addr:full":"Overleiestraat 112 Harelbeke West-Vlaanderen 8530",
    "addr:housenumber":"112",
    "addr:postcode":"8530",
    "addr:street":"Overleiestraat",
    "iso:country":"BE",
    "sg:address":"Overleiestraat 112",
    "sg:city":"Harelbeke",
    "sg:classifiers":[
        {
            "category":"Health Services",
            "subcategory":"Dentist",
            "type":"Services"
        }
    ],
    "sg:phone":"+32 56 44 07 06",
    "sg:postcode":"8530",
    "sg:province":"West-Vlaanderen",
    "wof:name":"Claus Inne",
    "wof:placetype":"venue"
},
  "geometry": {"coordinates":[3.3043649197,50.861038208],"type":"Point"}
}