{
  "type": "Feature",
  "properties": {
    "addr:full":"Rue De Fourchuposse 5 Liege Li\u00e8ge 4031",
    "addr:housenumber":"5",
    "addr:postcode":"4031",
    "addr:street":"Rue De Fourchuposse",
    "iso:country":"BE",
    "sg:address":"Rue De Fourchuposse 5",
    "sg:city":"Liege",
    "sg:orig_category":"Graphologues, astrologues, voyants and radiesth\u00e9sistes",
    "sg:phone":"+32 4 366 04 93",
    "sg:postcode":"4031",
    "sg:province":"Li\u00e8ge",
    "wof:name":"Gregoire",
    "wof:placetype":"venue"
},
  "geometry": {"coordinates":[5.599583149,50.6115036011],"type":"Point"}
}