{
  "type": "Feature",
  "properties": {
    "addr:full":"Rive Gauche Du Canal 22 Mons Hainaut 7011",
    "addr:housenumber":"22",
    "addr:postcode":"7011",
    "addr:street":"Hainaut",
    "iso:country":"BE",
    "sg:address":"Rive Gauche Du Canal 22",
    "sg:city":"Mons",
    "sg:orig_category":"Instituts de beaut\u00e9",
    "sg:phone":"+32 65 31 52 80",
    "sg:postcode":"7011",
    "sg:province":"Hainaut",
    "wof:name":"Nicole Demoustier",
    "wof:placetype":"venue"
},
  "geometry": {"coordinates":[3.912539959,50.4712982178],"type":"Point"}
}