{
  "type": "Feature",
  "properties": {
    "iso:country":"BE",
    "sg:address":"Berkenlaan 3",
    "sg:city":"Harelbeke",
    "sg:orig_category":"Dameskledingzaken",
    "sg:phone":"+32 56 71 83 55",
    "sg:postcode":"8530",
    "sg:province":"West-Vlaanderen",
    "wof:name":"Huis Daisy",
    "wof:placetype":"venue"
},
  "geometry": {"coordinates":[3.3059399128,50.8457717896],"type":"Point"}
}