{
  "type": "Feature",
  "properties": {
    "addr:full":"Oude Postbaan 62 Houthalen-helchteren Limburg 3530",
    "addr:housenumber":"62",
    "addr:postcode":"3530",
    "addr:street":"Oude Postbaan",
    "iso:country":"BE",
    "sg:address":"Oude Postbaan 62",
    "sg:city":"Houthalen-helchteren",
    "sg:orig_category":"Rundveehouders Varkenskwekers",
    "sg:phone":"+32 11 52 12 61",
    "sg:postcode":"3530",
    "sg:province":"Limburg",
    "wof:name":"Paul Nelis-cillen",
    "wof:placetype":"venue"
},
  "geometry": {"coordinates":[5.3719201088,51.0310020447],"type":"Point"}
}