{
  "type": "Feature",
  "properties": {
    "addr:full":"Linkhoutstraat 154 Lummen (linkhout) Limburg 3560",
    "addr:housenumber":"154",
    "addr:postcode":"3560",
    "addr:street":"Linkhoutstraat",
    "iso:country":"BE",
    "sg:address":"Linkhoutstraat 154",
    "sg:city":"Lummen (linkhout)",
    "sg:classifiers":[
        {
            "category":"Food & Beverages",
            "subcategory":"Groceries & Convenience Stores",
            "type":"Retail Goods"
        }
    ],
    "sg:phone":"+32 13 44 48 30",
    "sg:postcode":"3560",
    "sg:province":"Limburg",
    "sg:tags":[
        "grocer"
    ],
    "wof:name":"Supra Nadia",
    "wof:placetype":"venue"
},
  "geometry": {"coordinates":[5.1429162025,50.9660835266],"type":"Point"}
}