{
  "type": "Feature",
  "properties": {
    "addr:full":"Urselseweg 127 Knesselare Oost-Vlaanderen 9910",
    "addr:housenumber":"127",
    "addr:postcode":"9910",
    "addr:street":"Oost-Vlaanderen",
    "iso:country":"BE",
    "sg:address":"Urselseweg 127",
    "sg:city":"Knesselare",
    "sg:classifiers":[
        {
            "category":"Building & Trades",
            "subcategory":"Construction",
            "type":"Services"
        }
    ],
    "sg:phone":"+32 9 375 06 76",
    "sg:postcode":"9910",
    "sg:province":"Oost-Vlaanderen",
    "sg:tags":[
        "stucco",
        "contractor"
    ],
    "wof:name":"De Loof P",
    "wof:placetype":"venue"
},
  "geometry": {"coordinates":[3.4382650852,51.1332740784],"type":"Point"}
}