{
  "type": "Feature",
  "properties": {
    "addr:full":"Hernestraat 62 Edingen/enghien Hainaut 7850",
    "addr:housenumber":"62",
    "addr:postcode":"7850",
    "addr:street":"Hernestraat",
    "iso:country":"BE",
    "sg:address":"Hernestraat 62",
    "sg:city":"Edingen/enghien",
    "sg:orig_category":"Brood, gebak and snoepgoed",
    "sg:phone":"+32 2 395 49 58",
    "sg:postcode":"7850",
    "sg:province":"Hainaut",
    "wof:name":"Michel Demets",
    "wof:placetype":"venue"
},
  "geometry": {"coordinates":[4.0380620956,50.6948890686],"type":"Point"}
}