{
  "type": "Feature",
  "properties": {
    "iso:country":"BE",
    "sg:address":"Crete De Bouxhmont 34",
    "sg:city":"Herve",
    "sg:orig_category":"Herstellingen and onderhoud van auto's",
    "sg:phone":"+32 87 67 87 32",
    "sg:postcode":"4651",
    "sg:province":"Li\u00e8ge",
    "wof:name":"Ateliers J. Beckers",
    "wof:placetype":"venue"
},
  "geometry": {"coordinates":[5.8242440224,50.6525001526],"type":"Point"}
}