{
  "type": "Feature",
  "properties": {
    "iso:country":"BE",
    "sg:address":"Beilen 12-14",
    "sg:city":"Olen",
    "sg:orig_category":"Supermarch\u00e9s. Alimentation sp\u00e9cialis\u00e9e. Boucheries. Explosifs Fab. Articles de f\u00eate, farces and attr",
    "sg:phone":"+32 14 21 10 90",
    "sg:postcode":"2250",
    "sg:province":"Antwerpen",
    "wof:name":"Verbinnen",
    "wof:placetype":"venue"
},
  "geometry": {"coordinates":[4.8921451569,51.1654510498],"type":"Point"}
}