{
  "type": "Feature",
  "properties": {
    "addr:full":"Rue Alphonse Robert 62 Incourt (opprebais) Brabant Wallon 1315",
    "addr:housenumber":"62",
    "addr:postcode":"1315",
    "addr:street":"Rue Alphonse Robert;Wallon",
    "iso:country":"BE",
    "sg:address":"Rue Alphonse Robert 62",
    "sg:city":"Incourt (opprebais)",
    "sg:classifiers":[
        {
            "category":"Manufacturing",
            "subcategory":"Paper Products",
            "type":"Manufacturing & Wholesale Goods"
        }
    ],
    "sg:phone":"+32 10 88 84 98",
    "sg:postcode":"1315",
    "sg:province":"Brabant Wallon",
    "sg:tags":[
        "bookbinding"
    ],
    "wof:name":"Mr. Kervyn De Meerendre",
    "wof:placetype":"venue"
},
  "geometry": {"coordinates":[4.7625498772,50.6798591614],"type":"Point"}
}