{
  "type": "Feature",
  "properties": {
    "iso:country":"BE",
    "sg:address":"Houtemsesteenweg 330",
    "sg:city":"Vilvoorde (groot)",
    "sg:orig_category":"Elektrische installaties voor woningen",
    "sg:phone":"+32 2 253 71 10",
    "sg:postcode":"1800",
    "sg:province":"Vlaams-Brabant",
    "wof:name":"De Meester P",
    "wof:placetype":"venue"
},
  "geometry": {"coordinates":[4.4530000687,50.9348716736],"type":"Point"}
}