{
  "type": "Feature",
  "properties": {
    "iso:country":"BE",
    "sg:address":"Rue Alfred Defuisseaux N\u00b026",
    "sg:city":"Awans",
    "sg:orig_category":"Bloemen and planten Dameskledingzaken",
    "sg:phone":"+32 486 29 16 80",
    "sg:postcode":"4340",
    "sg:province":"Li\u00e8ge",
    "wof:name":"Vrancken",
    "wof:placetype":"venue"
},
  "geometry": {"coordinates":[5.4620018005,50.663772583],"type":"Point"}
}