{
  "type": "Feature",
  "properties": {
    "addr:full":"Rue Hayi 96 Grace-hollogne Li\u00e8ge 4460",
    "addr:housenumber":"96",
    "addr:postcode":"4460",
    "addr:street":"Rue Hayi",
    "iso:country":"BE",
    "sg:address":"Rue Hayi 96",
    "sg:city":"Grace-hollogne",
    "sg:orig_category":"Agences de presse",
    "sg:phone":"+32 4 234 26 82",
    "sg:postcode":"4460",
    "sg:province":"Li\u00e8ge",
    "wof:name":"St\u00c9phane Thirion",
    "wof:placetype":"venue"
},
  "geometry": {"coordinates":[5.4801421165,50.6399421692],"type":"Point"}
}