{
  "type": "Feature",
  "properties": {
    "addr:full":"Schipstraat 6 Puurs Antwerpen 2870",
    "addr:housenumber":"6",
    "addr:postcode":"2870",
    "addr:street":"Schipstraat",
    "iso:country":"BE",
    "sg:address":"Schipstraat 6",
    "sg:city":"Puurs",
    "sg:orig_category":"Boekhandels Krantenwinkels Rookartikelen",
    "sg:phone":"+32 3 889 97 63",
    "sg:postcode":"2870",
    "sg:province":"Antwerpen",
    "wof:name":"De Cirkel",
    "wof:placetype":"venue"
},
  "geometry": {"coordinates":[4.2772698402,51.0763244629],"type":"Point"}
}