{
  "type": "Feature",
  "properties": {
    "addr:full":"Heerstraat 53 Hasselt Limburg 3510",
    "addr:housenumber":"53",
    "addr:postcode":"3510",
    "addr:street":"Heerstraat",
    "iso:country":"BE",
    "sg:address":"Heerstraat 53",
    "sg:city":"Hasselt",
    "sg:orig_category":"Loodgieterij, verwarming and sanitaire installaties",
    "sg:phone":"+32 11 25 33 38",
    "sg:postcode":"3510",
    "sg:province":"Limburg",
    "wof:name":"Paul Janssens",
    "wof:placetype":"venue"
},
  "geometry": {"coordinates":[5.2531552315,50.9474906921],"type":"Point"}
}