{
  "type": "Feature",
  "properties": {
    "addr:full":"Hundelgemsesteenweg 403 Merelbeke Oost-Vlaanderen 9820",
    "addr:housenumber":"403",
    "addr:postcode":"9820",
    "addr:street":"Hundelgemsesteenweg",
    "iso:country":"BE",
    "sg:address":"Hundelgemsesteenweg 403",
    "sg:city":"Merelbeke",
    "sg:orig_category":"Kapsalons",
    "sg:phone":"+32 9 230 97 27",
    "sg:postcode":"9820",
    "sg:province":"Oost-Vlaanderen",
    "wof:name":"Hairstudio Lea",
    "wof:placetype":"venue"
},
  "geometry": {"coordinates":[3.7467119694,50.9921112061],"type":"Point"}
}