{
  "type": "Feature",
  "properties": {
    "iso:country":"BE",
    "sg:address":"Rue De Tournai 19",
    "sg:city":"Peruwelz",
    "sg:orig_category":"Verplichte sociale verzekeringen",
    "sg:phone":"+32 69 77 43 04",
    "sg:postcode":"7604",
    "sg:province":"Hainaut",
    "wof:name":"S\u00c9curit\u00c9 Et Avenir",
    "wof:placetype":"venue"
},
  "geometry": {"coordinates":[3.5258738995,50.5290031433],"type":"Point"}
}