{
  "type": "Feature",
  "properties": {
    "iso:country":"BE",
    "sg:address":"Bondgenotenlaan 125",
    "sg:city":"Leuven",
    "sg:orig_category":"Meubles D\u00e9taillants, Am\u00e9nagement de B\u00e2timents et de Cuisines. Eclairage et \u00e9quipements du foyer",
    "sg:phone":"+32 16 23 19 44",
    "sg:postcode":"3000",
    "sg:province":"Vlaams-Brabant",
    "wof:name":"Deco Gift Store",
    "wof:placetype":"venue"
},
  "geometry": {"coordinates":[4.7111201286,50.8807449341],"type":"Point"}
}