{
  "type": "Feature",
  "properties": {
    "iso:country":"BE",
    "sg:address":"Ophaalbrugstraat 42",
    "sg:city":"Sint-lambrechts-woluwe/woluwe-saint-lambert",
    "sg:orig_category":"Zalen voor culturele evenementen",
    "sg:phone":"+32 2 732 50 44",
    "sg:postcode":"1200",
    "sg:province":"Bruxelles-Capitale",
    "wof:name":"Compagnie Biloxi 48",
    "wof:placetype":"venue"
},
  "geometry": {"coordinates":[4.4138221741,50.8423194885],"type":"Point"}
}