{
  "type": "Feature",
  "properties": {
    "addr:full":"Rue De L'eglise Sainte-anne 74 Koekelberg Bruxelles-Capitale 1081",
    "addr:housenumber":"74",
    "addr:postcode":"1081",
    "addr:street":"Rue De L'Eglise Sainte-Anne",
    "iso:country":"BE",
    "sg:address":"Rue De L'eglise Sainte-anne 74",
    "sg:city":"Koekelberg",
    "sg:classifiers":[
        {
            "category":"Personal",
            "subcategory":"Beauty Salon",
            "type":"Services"
        }
    ],
    "sg:phone":"+32 2 411 89 25",
    "sg:postcode":"1081",
    "sg:province":"Bruxelles-Capitale",
    "sg:tags":[
        "de",
        "coiffure"
    ],
    "wof:name":"Coiffure Lydjo",
    "wof:placetype":"venue"
},
  "geometry": {"coordinates":[4.331428051,50.8599777222],"type":"Point"}
}