{
  "type": "Feature",
  "properties": {
    "addr:full":"Rue Saint-donat 6 Waimes Li\u00e8ge 4950",
    "addr:housenumber":"6",
    "addr:postcode":"4950",
    "addr:street":"Rue Saint-Donat",
    "iso:country":"BE",
    "sg:address":"Rue Saint-donat 6",
    "sg:city":"Waimes",
    "sg:classifiers":[
        {
            "category":"Cafe",
            "type":"Food & Drink"
        }
    ],
    "sg:phone":"+32 80 67 98 58",
    "sg:postcode":"4950",
    "sg:province":"Li\u00e8ge",
    "sg:tags":[
        "caf\u00e9s"
    ],
    "wof:name":"Francine Marichal",
    "wof:placetype":"venue"
},
  "geometry": {"coordinates":[6.1198611259,50.3898963928],"type":"Point"}
}