{
  "type": "Feature",
  "properties": {
    "iso:country":"BE",
    "sg:address":"Rue De L'elevage 4",
    "sg:city":"Ottignies-louvain-la-neuve (ottignies)",
    "sg:classifiers":[
        {
            "category":"Real Estate",
            "subcategory":"Architect",
            "type":"Services"
        }
    ],
    "sg:phone":"+32 10 45 07 64",
    "sg:postcode":"1340",
    "sg:province":"Brabant Wallon",
    "wof:name":"Brutsaert G",
    "wof:placetype":"venue"
},
  "geometry": {"coordinates":[4.6029038429,50.6591835022],"type":"Point"}
}