{
  "type": "Feature",
  "properties": {
    "addr:full":"Rue Taille D'harscamps 20 Assesse (sart-bernard) Namur 5330",
    "addr:housenumber":"20",
    "addr:postcode":"5330",
    "addr:street":"Rue Taille D'Harscamps",
    "iso:country":"BE",
    "sg:address":"Rue Taille D'harscamps 20",
    "sg:city":"Assesse (sart-bernard)",
    "sg:classifiers":[
        {
            "category":"Professional",
            "subcategory":"Accounting & Tax Preparation",
            "type":"Services"
        }
    ],
    "sg:phone":"+32 81 40 12 73",
    "sg:postcode":"5330",
    "sg:province":"Namur",
    "sg:tags":[
        "bookkeeper"
    ],
    "wof:name":"Vandenhaute M",
    "wof:placetype":"venue"
},
  "geometry": {"coordinates":[4.9541301727,50.3992614746],"type":"Point"}
}