{
  "type": "Feature",
  "properties": {
    "addr:full":"Avenue Du Baleau 3 Wavre (limal) Brabant Wallon 1300",
    "addr:housenumber":"3",
    "addr:postcode":"1300",
    "addr:street":"Avenue Du Baleau;Wallon",
    "iso:country":"BE",
    "sg:address":"Avenue Du Baleau 3",
    "sg:city":"Wavre (limal)",
    "sg:classifiers":[
        {
            "category":"Home & Garden",
            "subcategory":"Home Furnishings",
            "type":"Retail Goods"
        }
    ],
    "sg:phone":"+32 10 41 07 81",
    "sg:postcode":"1300",
    "sg:province":"Brabant Wallon",
    "sg:tags":[
        "interior",
        "decoration"
    ],
    "wof:name":"International Trade",
    "wof:placetype":"venue"
},
  "geometry": {"coordinates":[4.5468678474,50.691280365],"type":"Point"}
}