{
  "type": "Feature",
  "properties": {
    "addr:full":"Gerstestraat 16 Gistel West-Vlaanderen 8470",
    "addr:housenumber":"16",
    "addr:postcode":"8470",
    "addr:street":"Gerstestraat",
    "iso:country":"BE",
    "sg:address":"Gerstestraat 16",
    "sg:city":"Gistel",
    "sg:orig_category":"Woningbouw",
    "sg:phone":"+32 59 27 66 66",
    "sg:postcode":"8470",
    "sg:province":"West-Vlaanderen",
    "wof:name":"Dirk Borret",
    "wof:placetype":"venue"
},
  "geometry": {"coordinates":[2.9384989738,51.1741218567],"type":"Point"}
}