{
  "type": "Feature",
  "properties": {
    "iso:country":"BE",
    "sg:address":"Koeketerstraat 31",
    "sg:city":"Lommel",
    "sg:classifiers":[
        {
            "category":"Home & Garden",
            "subcategory":"Carpets & Floor Coverings",
            "type":"Retail Goods"
        }
    ],
    "sg:phone":"+32 11 55 38 15",
    "sg:postcode":"3920",
    "sg:province":"Limburg",
    "sg:tags":[
        "industrial",
        "-"
    ],
    "wof:name":"Brusselaers P",
    "wof:placetype":"venue"
},
  "geometry": {"coordinates":[5.289498806,51.2252883911],"type":"Point"}
}