{
  "type": "Feature",
  "properties": {
    "addr:full":"Rue Docteur S\u00e9verin 18 Sambreville (velaine-sur-sambre) Namur 5060",
    "addr:housenumber":"18",
    "addr:postcode":"5060",
    "addr:street":"Rue Docteur Se\u0301Verin",
    "iso:country":"BE",
    "sg:address":"Rue Docteur S\u00e9verin 18",
    "sg:city":"Sambreville (velaine-sur-sambre)",
    "sg:classifiers":[
        {
            "category":"Health Services",
            "subcategory":"Nursing And Care Facility",
            "type":"Services"
        }
    ],
    "sg:phone":"+32 71 77 52 81",
    "sg:postcode":"5060",
    "sg:province":"Namur",
    "sg:tags":[
        "home",
        "rest"
    ],
    "wof:name":"Retraite Fleurie (la)",
    "wof:placetype":"venue"
},
  "geometry": {"coordinates":[4.6285200119,50.4448738098],"type":"Point"}
}