{
  "type": "Feature",
  "properties": {
    "iso:country":"BE",
    "sg:address":"Rode Kruislaan 54",
    "sg:city":"Bree",
    "sg:orig_category":"Jeux and jouets. Mat\u00e9riel de T\u00e9l\u00e9communication. Papeterie and fournitures de bureau Entretien and r\u00e9",
    "sg:phone":"+32 89 46 13 32",
    "sg:postcode":"3960",
    "sg:province":"Limburg",
    "wof:name":"Mobital Kantooruitrustingen",
    "wof:placetype":"venue"
},
  "geometry": {"coordinates":[5.6057062149,51.1376342773],"type":"Point"}
}