{
  "type": "Feature",
  "properties": {
    "addr:full":"Brusselsesteenweg 267b-271 Halle Vlaams-Brabant 1500",
    "addr:housenumber":"267b-271",
    "addr:postcode":"1500",
    "addr:street":"Brusselsesteenweg",
    "iso:country":"BE",
    "sg:address":"Brusselsesteenweg 267b-271",
    "sg:city":"Halle",
    "sg:classifiers":[
        {
            "category":"Home & Garden",
            "subcategory":"Building Materials",
            "type":"Retail Goods"
        }
    ],
    "sg:phone":"+32 2 361 13 15",
    "sg:postcode":"1500",
    "sg:province":"Vlaams-Brabant",
    "sg:tags":[
        "bathroom",
        "installation",
        "accessory"
    ],
    "wof:name":"Interl\u00fckk Design",
    "wof:placetype":"venue"
},
  "geometry": {"coordinates":[4.2421011925,50.7452163696],"type":"Point"}
}