{
  "type": "Feature",
  "properties": {
    "addr:full":"Wettersesteenweg 177a Sint-lievens-houtem Oost-Vlaanderen 9520",
    "addr:housenumber":"177a",
    "addr:postcode":"9520",
    "addr:street":"Wettersesteenweg",
    "iso:country":"BE",
    "sg:address":"Wettersesteenweg 177a",
    "sg:city":"Sint-lievens-houtem",
    "sg:classifiers":[
        {
            "category":"Building & Trades",
            "subcategory":"Construction",
            "type":"Services"
        }
    ],
    "sg:phone":"+32 9 362 18 50",
    "sg:postcode":"9520",
    "sg:province":"Oost-Vlaanderen",
    "sg:tags":[
        "carpenter"
    ],
    "wof:name":"Verliefde P",
    "wof:placetype":"venue"
},
  "geometry": {"coordinates":[3.852809906,50.9333496094],"type":"Point"}
}