{
  "type": "Feature",
  "properties": {
    "iso:country":"BE",
    "sg:address":"Rue Du March\u00e9 Au Charbon 95-103",
    "sg:city":"Bruxelles",
    "sg:classifiers":[
        {
            "category":"Communications",
            "subcategory":"Film & Video Production",
            "type":"Services"
        }
    ],
    "sg:phone":"+32 2 503 41 20",
    "sg:postcode":"1000",
    "sg:province":"Bruxelles-Capitale",
    "sg:tags":[
        "sound",
        "installation",
        "material",
        "-",
        "recording",
        "studio"
    ],
    "wof:name":"Orbit Studio & Musical Equipment Sprl",
    "wof:placetype":"venue"
},
  "geometry": {"coordinates":[4.3473558426,50.8454971313],"type":"Point"}
}