{
  "type": "Feature",
  "properties": {
    "addr:full":"Rue De Rocroi 12 Chimay Hainaut 6464",
    "addr:housenumber":"12",
    "addr:postcode":"6464",
    "addr:street":"Rue De Rocroi",
    "iso:country":"BE",
    "sg:address":"Rue De Rocroi 12",
    "sg:city":"Chimay",
    "sg:orig_category":"Eleveurs de bovins",
    "sg:phone":"+32 60 21 18 93",
    "sg:postcode":"6464",
    "sg:province":"Hainaut",
    "wof:name":"Jean-louis Marchal",
    "wof:placetype":"venue"
},
  "geometry": {"coordinates":[4.3732299805,50.0295295715],"type":"Point"}
}