{
  "type": "Feature",
  "properties": {
    "addr:full":"Brugstraat 49 Hoegaarden Vlaams-Brabant 3321",
    "addr:housenumber":"49",
    "addr:postcode":"3321",
    "addr:street":"Brugstraat",
    "iso:country":"BE",
    "sg:address":"Brugstraat 49",
    "sg:city":"Hoegaarden",
    "sg:orig_category":"Charpentes and couvertures",
    "sg:phone":"+32 16 76 61 20",
    "sg:postcode":"3321",
    "sg:province":"Vlaams-Brabant",
    "wof:name":"Eddy Deferm",
    "wof:placetype":"venue"
},
  "geometry": {"coordinates":[4.9216938019,50.768787384],"type":"Point"}
}