{
  "type": "Feature",
  "properties": {
    "iso:country":"BE",
    "sg:address":"Scheldelaan 480-haven 647",
    "sg:city":"Antwerpen",
    "sg:classifiers":[
        {
            "category":"Manufacturing",
            "subcategory":"Chemicals & Compounds",
            "type":"Manufacturing & Wholesale Goods"
        }
    ],
    "sg:phone":"+32 3 560 50 11",
    "sg:postcode":"2040",
    "sg:province":"Antwerpen",
    "sg:tags":[
        "pharmaceutical"
    ],
    "wof:name":"Solvay Nv",
    "wof:placetype":"venue"
},
  "geometry": {"coordinates":[4.2869548798,51.3234062195],"type":"Point"}
}