{
  "type": "Feature",
  "properties": {
    "addr:full":"Kautershoek 1 Diest Vlaams-Brabant 3290",
    "addr:housenumber":"1",
    "addr:postcode":"3290",
    "addr:street":"Kautershoek",
    "iso:country":"BE",
    "sg:address":"Kautershoek 1",
    "sg:city":"Diest",
    "sg:orig_category":"RESTAURANTS: BOISSONS",
    "sg:phone":"+32 13 32 63 43",
    "sg:postcode":"3290",
    "sg:province":"Vlaams-Brabant",
    "wof:name":"Casa Iberico",
    "wof:placetype":"venue"
},
  "geometry": {"coordinates":[5.0537800789,50.9805831909],"type":"Point"}
}