{
  "type": "Feature",
  "properties": {
    "iso:country":"BE",
    "sg:address":"Groenestraat 244a",
    "sg:city":"Roeselare",
    "sg:classifiers":[
        {
            "category":"Exhibition Hall",
            "type":"Public Place"
        }
    ],
    "sg:phone":"+32 51 25 34 50",
    "sg:postcode":"8800",
    "sg:province":"West-Vlaanderen",
    "sg:tags":[
        "stand"
    ],
    "wof:name":"Xtension Bvba",
    "wof:placetype":"venue"
},
  "geometry": {"coordinates":[3.1021258831,50.940372467],"type":"Point"}
}