{
  "type": "Feature",
  "properties": {
    "addr:full":"Bassebeekwegel 15 Gent (drongen) Oost-Vlaanderen 9031",
    "addr:housenumber":"15",
    "addr:postcode":"9031",
    "addr:street":"Bassebeekwegel",
    "iso:country":"BE",
    "sg:address":"Bassebeekwegel 15",
    "sg:city":"Gent (drongen)",
    "sg:classifiers":[
        {
            "category":"Building & Trades",
            "subcategory":"Pest Control",
            "type":"Services"
        }
    ],
    "sg:phone":"+32 9 232 29 19",
    "sg:postcode":"9031",
    "sg:province":"Oost-Vlaanderen",
    "sg:tags":[
        "painting",
        "contractor"
    ],
    "wof:name":"De Buck F",
    "wof:placetype":"venue"
},
  "geometry": {"coordinates":[3.6593770981,51.0550117493],"type":"Point"}
}