{
  "type": "Feature",
  "properties": {
    "iso:country":"BE",
    "sg:address":"Minister Tacklaan 3",
    "sg:city":"Kortrijk",
    "sg:classifiers":[
        {
            "category":"Health Services",
            "subcategory":"Dentist",
            "type":"Services"
        }
    ],
    "sg:phone":"+32 56 20 38 87",
    "sg:postcode":"8500",
    "sg:province":"West-Vlaanderen",
    "wof:name":"Beel E",
    "wof:placetype":"venue"
},
  "geometry": {"coordinates":[3.2678239346,50.8237991333],"type":"Point"}
}