{
  "type": "Feature",
  "properties": {
    "iso:country":"BE",
    "sg:address":"Chauss\u00e9e De Bruxelles 261",
    "sg:city":"Enghien (petit-enghien)",
    "sg:classifiers":[
        {
            "category":"Organizations",
            "subcategory":"Professional Association",
            "type":"Services"
        }
    ],
    "sg:phone":"+32 2 395 55 88",
    "sg:postcode":"7850",
    "sg:province":"Hainaut",
    "sg:tags":[
        "organisation",
        "seminar"
    ],
    "wof:name":"R\u00e9serve (la)",
    "wof:placetype":"venue"
},
  "geometry": {"coordinates":[4.0618882179,50.6892738342],"type":"Point"}
}