{
  "type": "Feature",
  "properties": {
    "iso:country":"BE",
    "sg:address":"Park De Rode Poort 68",
    "sg:city":"Brugge",
    "sg:orig_category":"M\u00e9decins and sp\u00e9cialistes",
    "sg:phone":"+32 50 38 56 98",
    "sg:postcode":"8200",
    "sg:province":"West-Vlaanderen",
    "wof:name":"F. Deklerck",
    "wof:placetype":"venue"
},
  "geometry": {"coordinates":[3.2362968922,51.2111625671],"type":"Point"}
}