{
  "type": "Feature",
  "properties": {
    "addr:full":"Muizelaarstraat 16 Pittem West-Vlaanderen 8740",
    "addr:housenumber":"16",
    "addr:postcode":"8740",
    "addr:street":"Muizelaarstraat",
    "iso:country":"BE",
    "sg:address":"Muizelaarstraat 16",
    "sg:city":"Pittem",
    "sg:orig_category":"Eleveurs de bovins. Producteurs de l\u00e9gumes",
    "sg:phone":"+32 51 46 62 00",
    "sg:postcode":"8740",
    "sg:province":"West-Vlaanderen",
    "wof:name":"Roland Verhelle",
    "wof:placetype":"venue"
},
  "geometry": {"coordinates":[3.2594020367,50.9747695923],"type":"Point"}
}