{
  "type": "Feature",
  "properties": {
    "iso:country":"BE",
    "sg:address":"Rue D'anderlues 29",
    "sg:city":"Binche (leval-trahegnies)",
    "sg:classifiers":[
        {
            "category":"Social Services",
            "subcategory":"Child Care",
            "type":"Services"
        }
    ],
    "sg:phone":"+32 64 45 05 41",
    "sg:postcode":"7134",
    "sg:province":"Hainaut",
    "sg:tags":[
        "baby",
        "nursery",
        "day",
        "sitting"
    ],
    "wof:name":"Petite Maison Des Enfants (la)",
    "wof:placetype":"venue"
},
  "geometry": {"coordinates":[4.2241020203,50.4220619202],"type":"Point"}
}