{
  "type": "Feature",
  "properties": {
    "iso:country":"BE",
    "sg:address":"Grote Markt 24ba",
    "sg:city":"Westerlo",
    "sg:orig_category":"Avocats and conseillers juridiques",
    "sg:phone":"+32 14 54 13 24",
    "sg:postcode":"2260",
    "sg:province":"Antwerpen",
    "wof:name":"W. Van Hove",
    "wof:placetype":"venue"
},
  "geometry": {"coordinates":[4.9179191589,51.0874481201],"type":"Point"}
}