{
  "type": "Feature",
  "properties": {
    "addr:full":"Rue De La Croisette 11 Saint-ghislain Hainaut 7334",
    "addr:housenumber":"11",
    "addr:postcode":"7334",
    "addr:street":"Rue De La Croisette;Hainaut",
    "iso:country":"BE",
    "sg:address":"Rue De La Croisette 11",
    "sg:city":"Saint-ghislain",
    "sg:orig_category":"Huisvuilophaling and -verwerking",
    "sg:phone":"+32 65 62 17 01",
    "sg:postcode":"7334",
    "sg:province":"Hainaut",
    "wof:name":"Olea",
    "wof:placetype":"venue"
},
  "geometry": {"coordinates":[3.7644500732,50.479675293],"type":"Point"}
}