{
  "type": "Feature",
  "properties": {
    "iso:country":"BE",
    "sg:address":"Hippodroomlaan 111",
    "sg:city":"Zaventem (sterrebeek)",
    "sg:classifiers":[
        {
            "category":"Real Estate",
            "subcategory":"Architect",
            "type":"Services"
        }
    ],
    "sg:phone":"+32 2 345 16 61",
    "sg:postcode":"1933",
    "sg:province":"Vlaams-Brabant",
    "wof:name":"Van Herstraeten J-m",
    "wof:placetype":"venue"
},
  "geometry": {"coordinates":[4.5076031685,50.8477783203],"type":"Point"}
}