{
  "type": "Feature",
  "properties": {
    "iso:country":"BE",
    "sg:address":"Rue Du Four \u00c0 Chaux 34",
    "sg:city":"Binche",
    "sg:orig_category":"Begrafeniswezen Bloemen and planten",
    "sg:phone":"+32 64 33 81 72",
    "sg:postcode":"7130",
    "sg:province":"Hainaut",
    "wof:name":"Fun\u00c9railles Decamps",
    "wof:placetype":"venue"
},
  "geometry": {"coordinates":[4.1655550003,50.4192047119],"type":"Point"}
}