{
  "type": "Feature",
  "properties": {
    "addr:full":"Kampenheuvel 1 Herzele Oost-Vlaanderen 9552",
    "addr:housenumber":"1",
    "addr:postcode":"9552",
    "addr:street":"Kampenheuvel;Oost-Vlaanderen",
    "iso:country":"BE",
    "sg:address":"Kampenheuvel 1",
    "sg:city":"Herzele",
    "sg:orig_category":"Eleveurs de bovins",
    "sg:phone":"+32 53 62 42 81",
    "sg:postcode":"9552",
    "sg:province":"Oost-Vlaanderen",
    "wof:name":"Aime Spranghers",
    "wof:placetype":"venue"
},
  "geometry": {"coordinates":[3.8876121044,50.9143218994],"type":"Point"}
}