{
  "type": "Feature",
  "properties": {
    "addr:full":"Vossenboslaan 30 Essen Antwerpen 2910",
    "addr:housenumber":"30",
    "addr:postcode":"2910",
    "addr:street":"Vossenboslaan",
    "iso:country":"BE",
    "sg:address":"Vossenboslaan 30",
    "sg:city":"Essen",
    "sg:orig_category":"Eleveurs de bovins",
    "sg:phone":"+32 3 667 25 68",
    "sg:postcode":"2910",
    "sg:province":"Antwerpen",
    "wof:name":"Walter Gommeren",
    "wof:placetype":"venue"
},
  "geometry": {"coordinates":[4.4467959404,51.4609985352],"type":"Point"}
}