{
  "type": "Feature",
  "properties": {
    "iso:country":"BE",
    "sg:address":"Urselseweg 58",
    "sg:city":"Knesselare",
    "sg:orig_category":"Poissonniers and \u00e9caillers",
    "sg:phone":"+32 9 374 56 53",
    "sg:postcode":"9910",
    "sg:province":"Oost-Vlaanderen",
    "wof:name":"Michel Claeys",
    "wof:placetype":"venue"
},
  "geometry": {"coordinates":[3.4275479317,51.1340522766],"type":"Point"}
}