{
  "type": "Feature",
  "properties": {
    "addr:full":"Schildekensstraat 34 Lede (smetlede) Oost-Vlaanderen 9340",
    "addr:housenumber":"34",
    "addr:postcode":"9340",
    "addr:street":"Schildekensstraat",
    "iso:country":"BE",
    "sg:address":"Schildekensstraat 34",
    "sg:city":"Lede (smetlede)",
    "sg:classifiers":[
        {
            "category":"Health Services",
            "subcategory":"Doctor",
            "type":"Services"
        }
    ],
    "sg:phone":"+32 9 369 66 84",
    "sg:postcode":"9340",
    "sg:province":"Oost-Vlaanderen",
    "sg:tags":[
        "psychotherapist",
        "psychoanalyst"
    ],
    "wof:name":"Focuscentrum Scheldeland Vzw",
    "wof:placetype":"venue"
},
  "geometry": {"coordinates":[3.9335250854,50.9666099548],"type":"Point"}
}