{
  "type": "Feature",
  "properties": {
    "iso:country":"BE",
    "sg:address":"Rue De Quevaucamps 17",
    "sg:city":"Beloeil",
    "sg:orig_category":"Kapsalons",
    "sg:phone":"+32 69 57 75 49",
    "sg:postcode":"7971",
    "sg:province":"Hainaut",
    "wof:name":"Sylvie Bocquillon",
    "wof:placetype":"venue"
},
  "geometry": {"coordinates":[3.6613841057,50.5224380493],"type":"Point"}
}