{
  "type": "Feature",
  "properties": {
    "iso:country":"BE",
    "sg:address":"Ransfortstraat 88",
    "sg:city":"Sint-jans-molenbeek/molenbeek-saint-jean",
    "sg:orig_category":"Apotheken",
    "sg:phone":"+32 2 410 12 36",
    "sg:postcode":"1080",
    "sg:province":"Bruxelles-Capitale",
    "wof:name":"Marc Hermans",
    "wof:placetype":"venue"
},
  "geometry": {"coordinates":[4.3349781036,50.850894928],"type":"Point"}
}