{
  "type": "Feature",
  "properties": {
    "addr:full":"Siemensln 5 Oostkamp West-Vlaanderen 8020",
    "addr:housenumber":"5",
    "addr:postcode":"8020",
    "addr:street":"Siemensln",
    "iso:country":"BE",
    "sg:address":"Siemensln 5",
    "sg:city":"Oostkamp",
    "sg:classifiers":[
        {
            "category":"Manufacturing",
            "subcategory":"Metals",
            "type":"Manufacturing & Wholesale Goods"
        }
    ],
    "sg:phone":"+32 50 83 11 83",
    "sg:postcode":"8020",
    "sg:province":"West-Vlaanderen",
    "sg:tags":[
        "-",
        "machine",
        "equipment",
        "engineering",
        "machinery",
        "mechanical"
    ],
    "wof:name":"Belmeko Bvba",
    "wof:placetype":"venue"
},
  "geometry": {"coordinates":[3.2350599766,51.1533241272],"type":"Point"}
}