{
  "type": "Feature",
  "properties": {
    "iso:country":"BE",
    "sg:address":"Graaf Van Hoornestraat 24",
    "sg:city":"Nevele",
    "sg:classifiers":[
        {
            "category":"Real Estate",
            "subcategory":"Architect",
            "type":"Services"
        }
    ],
    "sg:phone":"+32 9 371 63 04",
    "sg:postcode":"9850",
    "sg:province":"Oost-Vlaanderen",
    "wof:name":"Haelvoet W",
    "wof:placetype":"venue"
},
  "geometry": {"coordinates":[3.5424330235,51.0336036682],"type":"Point"}
}