{
  "type": "Feature",
  "properties": {
    "iso:country":"BE",
    "sg:address":"Route De Spa 23",
    "sg:city":"Havelange",
    "sg:orig_category":"Pharmaciens",
    "sg:phone":"+32 86 32 20 90",
    "sg:postcode":"5372",
    "sg:province":"Namur",
    "wof:name":"Raoul Bontemps",
    "wof:placetype":"venue"
},
  "geometry": {"coordinates":[5.3381080627,50.3634490967],"type":"Point"}
}