{
  "type": "Feature",
  "properties": {
    "addr:full":"Europalaan 59 Willebroek Antwerpen 2830",
    "addr:housenumber":"59",
    "addr:postcode":"2830",
    "addr:street":"Europalaan",
    "iso:country":"BE",
    "sg:address":"Europalaan 59",
    "sg:city":"Willebroek",
    "sg:orig_category":"Sportclubs",
    "sg:phone":"+32 3 886 56 72",
    "sg:postcode":"2830",
    "sg:province":"Antwerpen",
    "wof:name":"W.s.v. Willebroek",
    "wof:placetype":"venue"
},
  "geometry": {"coordinates":[4.3455839157,51.0523834229],"type":"Point"}
}