{
  "type": "Feature",
  "properties": {
    "iso:country":"BE",
    "sg:address":"Rodebergstraat 22",
    "sg:city":"Heuvelland",
    "sg:classifiers":[
        {
            "category":"Restaurant",
            "type":"Food & Drink"
        }
    ],
    "sg:phone":"+32 57 44 78 33",
    "sg:postcode":"8954",
    "sg:province":"West-Vlaanderen",
    "wof:name":"De Patrijs",
    "wof:placetype":"venue"
},
  "geometry": {"coordinates":[2.7637019157,50.7860679626],"type":"Point"}
}