{
  "type": "Feature",
  "properties": {
    "addr:full":"Legeweg 14 Jabbeke West-Vlaanderen 8490",
    "addr:housenumber":"14",
    "addr:postcode":"8490",
    "addr:street":"Legeweg",
    "iso:country":"BE",
    "sg:address":"Legeweg 14",
    "sg:city":"Jabbeke",
    "sg:orig_category":"Rundveehouders Varkenskwekers",
    "sg:phone":"+32 50 39 54 92",
    "sg:postcode":"8490",
    "sg:province":"West-Vlaanderen",
    "wof:name":"Robert Aneca",
    "wof:placetype":"venue"
},
  "geometry": {"coordinates":[3.128205061,51.1918869019],"type":"Point"}
}