{
  "type": "Feature",
  "properties": {
    "addr:full":"Blauwselstraat 8 Buggenhout Oost-Vlaanderen 9255",
    "addr:housenumber":"8",
    "addr:postcode":"9255",
    "addr:street":"Blauwselstraat",
    "iso:country":"BE",
    "sg:address":"Blauwselstraat 8",
    "sg:city":"Buggenhout",
    "sg:orig_category":"Experts-comptables",
    "sg:phone":"+32 52 35 06 19",
    "sg:postcode":"9255",
    "sg:province":"Oost-Vlaanderen",
    "wof:name":"Paul Saey",
    "wof:placetype":"venue"
},
  "geometry": {"coordinates":[4.1752109528,50.9975700378],"type":"Point"}
}