{
  "type": "Feature",
  "properties": {
    "iso:country":"BE",
    "sg:address":"Malmaison 7ba",
    "sg:city":"Fauvillers",
    "sg:orig_category":"Herstellingen and onderhoud van auto's",
    "sg:phone":"+32 61 21 24 07",
    "sg:postcode":"6637",
    "sg:province":"Luxembourg",
    "wof:name":"Fe. Noiset & Fils",
    "wof:placetype":"venue"
},
  "geometry": {"coordinates":[5.699942112,49.8973960876],"type":"Point"}
}