{
  "type": "Feature",
  "properties": {
    "addr:full":"Ambachtsstraat 5 Mol Antwerpen 2400",
    "addr:housenumber":"5",
    "addr:postcode":"2400",
    "addr:street":"Ambachtsstraat",
    "iso:country":"BE",
    "sg:address":"Ambachtsstraat 5",
    "sg:city":"Mol",
    "sg:classifiers":[
        {
            "category":"Utilities",
            "subcategory":"Refuse",
            "type":"Services"
        }
    ],
    "sg:phone":"+32 14 31 78 11",
    "sg:postcode":"2400",
    "sg:province":"Antwerpen",
    "sg:tags":[
        "miller"
    ],
    "wof:name":"Jan Gevers Bvba",
    "wof:placetype":"venue"
},
  "geometry": {"coordinates":[5.1005911827,51.190788269],"type":"Point"}
}