{
  "type": "Feature",
  "properties": {
    "iso:country":"BE",
    "sg:address":"Gebouw 706",
    "sg:city":"Zaventem",
    "sg:orig_category":"Luchtvaart volgens dienstregeling",
    "sg:phone":"+32 2 753 56 70",
    "sg:postcode":"1931",
    "wof:name":"Wilson Belgium",
    "wof:placetype":"venue"
},
  "geometry": {"coordinates":[4.4741148949,50.8835449219],"type":"Point"}
}