{
  "type": "Feature",
  "properties": {
    "addr:full":"Eikenlaan 31 Wijnegem Antwerpen 2110",
    "addr:housenumber":"31",
    "addr:postcode":"2110",
    "addr:street":"Eikenlaan",
    "iso:country":"BE",
    "sg:address":"Eikenlaan 31",
    "sg:city":"Wijnegem",
    "sg:orig_category":"Voertuigen",
    "sg:phone":"+32 3 353 98 00",
    "sg:postcode":"2110",
    "sg:province":"Antwerpen",
    "wof:name":"Garage Hernandez",
    "wof:placetype":"venue"
},
  "geometry": {"coordinates":[4.5239310265,51.2263565063],"type":"Point"}
}