{
  "type": "Feature",
  "properties": {
    "addr:full":"Luikerstraat 82 Sint-truiden Limburg 3800",
    "addr:housenumber":"82",
    "addr:postcode":"3800",
    "addr:street":"Luikerstraat",
    "iso:country":"BE",
    "sg:address":"Luikerstraat 82",
    "sg:city":"Sint-truiden",
    "sg:classifiers":[
        {
            "category":"Bars & Pubs",
            "type":"Food & Drink"
        }
    ],
    "sg:phone":"+32 11 70 71 81",
    "sg:postcode":"3800",
    "sg:province":"Limburg",
    "wof:name":"Extra-time",
    "wof:placetype":"venue"
},
  "geometry": {"coordinates":[5.1933522224,50.8094940186],"type":"Point"}
}