{
  "type": "Feature",
  "properties": {
    "addr:full":"Huiseplein 16 Zingem Oost-Vlaanderen 9750",
    "addr:housenumber":"16",
    "addr:postcode":"9750",
    "addr:street":"Huiseplein;Oost-Vlaanderen",
    "iso:country":"BE",
    "sg:address":"Huiseplein 16",
    "sg:city":"Zingem",
    "sg:orig_category":"Biblioth\u00e8ques and archives publiques",
    "sg:phone":"+32 9 383 57 77",
    "sg:postcode":"9750",
    "sg:province":"Oost-Vlaanderen",
    "wof:name":"Openbare Bibliotheek",
    "wof:placetype":"venue"
},
  "geometry": {"coordinates":[3.5904479027,50.8988075256],"type":"Point"}
}