{
  "type": "Feature",
  "properties": {
    "iso:country":"BE",
    "sg:address":"Houtstraat 14",
    "sg:city":"Zulte",
    "sg:orig_category":"Installation de menuiserie en bois and plastique",
    "sg:phone":"+32 9 388 93 80",
    "sg:postcode":"9870",
    "sg:province":"Oost-Vlaanderen",
    "wof:name":"Yves Vervaeck",
    "wof:placetype":"venue"
},
  "geometry": {"coordinates":[3.4636559486,50.926776886],"type":"Point"}
}