{
  "type": "Feature",
  "properties": {
    "iso:country":"BE",
    "sg:address":"Avenue Des Bergers 45",
    "sg:city":"Durbuy",
    "sg:orig_category":"Diensten voor huisdieren",
    "sg:phone":"+32 86 21 25 79",
    "sg:postcode":"6941",
    "sg:province":"Luxembourg",
    "wof:name":"Au Chien Chic",
    "wof:placetype":"venue"
},
  "geometry": {"coordinates":[5.524184227,50.3770332336],"type":"Point"}
}