{
  "type": "Feature",
  "properties": {
    "addr:full":"Volderslaan 17 Hasselt Limburg 3500",
    "addr:housenumber":"17",
    "addr:postcode":"3500",
    "addr:street":"Volderslaan",
    "iso:country":"BE",
    "sg:address":"Volderslaan 17",
    "sg:city":"Hasselt",
    "sg:classifiers":[
        {
            "category":"Health Services",
            "subcategory":"Dentist",
            "type":"Services"
        }
    ],
    "sg:phone":"+32 11 27 58 18",
    "sg:postcode":"3500",
    "sg:province":"Limburg",
    "wof:name":"Lukasse Esther",
    "wof:placetype":"venue"
},
  "geometry": {"coordinates":[5.3227329254,50.9234962463],"type":"Point"}
}