{
  "type": "Feature",
  "properties": {
    "addr:full":"Rue D'ath 26 Brugelette Hainaut 7941",
    "addr:housenumber":"26",
    "addr:postcode":"7941",
    "addr:street":"Rue D'Ath;Hainaut",
    "iso:country":"BE",
    "sg:address":"Rue D'ath 26",
    "sg:city":"Brugelette",
    "sg:orig_category":"Boissons",
    "sg:phone":"+32 68 45 57 84",
    "sg:postcode":"7941",
    "sg:province":"Hainaut",
    "wof:name":"Vininvest",
    "wof:placetype":"venue"
},
  "geometry": {"coordinates":[3.835474968,50.6113586426],"type":"Point"}
}