{
  "type": "Feature",
  "properties": {
    "iso:country":"BE",
    "sg:address":"Eduard Robeynslaan 16",
    "sg:city":"Diest",
    "sg:classifiers":[
        {
            "category":"Cafe",
            "type":"Food & Drink"
        }
    ],
    "sg:phone":"+32 13 31 31 09",
    "sg:postcode":"3290",
    "sg:province":"Vlaams-Brabant",
    "sg:tags":[
        "caf\u00e9s"
    ],
    "wof:name":"Marie Geukens",
    "wof:placetype":"venue"
},
  "geometry": {"coordinates":[5.0567708015,50.9792518616],"type":"Point"}
}