{
  "type": "Feature",
  "properties": {
    "addr:full":"Rue Pierreuse 22 Li\u00e8ge 1 Li\u00e8ge 4000",
    "addr:housenumber":"22;1",
    "addr:postcode":"4000",
    "addr:street":"Rue Pierreuse",
    "iso:country":"BE",
    "sg:address":"Rue Pierreuse 22",
    "sg:city":"Li\u00e8ge 1",
    "sg:classifiers":[
        {
            "category":"Banks & Credit Unions",
            "subcategory":"Bureau De Change",
            "type":"Services"
        }
    ],
    "sg:phone":"+32 4 223 34 71",
    "sg:postcode":"4000",
    "sg:province":"Li\u00e8ge",
    "sg:tags":[
        "model",
        "scale",
        "-"
    ],
    "wof:name":"Rausin A",
    "wof:placetype":"venue"
},
  "geometry": {"coordinates":[5.57371521,50.6468772888],"type":"Point"}
}