{
  "type": "Feature",
  "properties": {
    "iso:country":"BE",
    "sg:address":"Lenneke Marelaan 24 Box 7",
    "sg:city":"Zaventem (sint-stevens-woluwe)",
    "sg:classifiers":[
        {
            "category":"Professional",
            "subcategory":"Accounting & Tax Preparation",
            "type":"Services"
        }
    ],
    "sg:phone":"+32 2 725 60 20",
    "sg:postcode":"1932",
    "sg:province":"Vlaams-Brabant",
    "sg:tags":[
        "bookkeeper"
    ],
    "wof:name":"All Accounts Two Sprl",
    "wof:placetype":"venue"
},
  "geometry": {"coordinates":[4.4509820938,50.8574790955],"type":"Point"}
}