{
  "type": "Feature",
  "properties": {
    "iso:country":"BE",
    "sg:address":"Kartuizersstraat 21",
    "sg:city":"Brugge (sint-kruis)",
    "sg:classifiers":[
        {
            "category":"Professional",
            "subcategory":"Lawyer & Legal Services",
            "type":"Services"
        }
    ],
    "sg:phone":"+32 50 35 47 85",
    "sg:postcode":"8310",
    "sg:province":"West-Vlaanderen",
    "wof:name":"Decadt Stijn",
    "wof:placetype":"venue"
},
  "geometry": {"coordinates":[3.2415421009,51.2153434753],"type":"Point"}
}