{
  "type": "Feature",
  "properties": {
    "addr:full":"Edith Cavellstraat 120 Ukkel/uccle Bruxelles-Capitale 1180",
    "addr:housenumber":"120",
    "addr:postcode":"1180",
    "addr:street":"Edith Cavellstraat;/",
    "iso:country":"BE",
    "sg:address":"Edith Cavellstraat 120",
    "sg:city":"Ukkel/uccle",
    "sg:orig_category":"Artsen and specialisten",
    "sg:phone":"+32 2 347 01 25",
    "sg:postcode":"1180",
    "sg:province":"Bruxelles-Capitale",
    "wof:name":"Bernard Van Malleghem",
    "wof:placetype":"venue"
},
  "geometry": {"coordinates":[4.3573718071,50.8088722229],"type":"Point"}
}