{
  "type": "Feature",
  "properties": {
    "addr:full":"Bolognestraat 7 Koksijde West-Vlaanderen 8670",
    "addr:housenumber":"7",
    "addr:postcode":"8670",
    "addr:street":"Bolognestraat",
    "iso:country":"BE",
    "sg:address":"Bolognestraat 7",
    "sg:city":"Koksijde",
    "sg:orig_category":"HERSTELLING ELEKTRISCHE HUISHOUDAPPARATEN Huishoudapparaten, televisies and radio's",
    "sg:phone":"+32 58 51 27 28",
    "sg:postcode":"8670",
    "sg:province":"West-Vlaanderen",
    "wof:name":"Godfried Tryssessoone",
    "wof:placetype":"venue"
},
  "geometry": {"coordinates":[2.634898901,51.1178283691],"type":"Point"}
}