{
  "type": "Feature",
  "properties": {
    "addr:full":"Hoogboomsteenweg 133 Kapellen Antwerpen 2950",
    "addr:housenumber":"133",
    "addr:postcode":"2950",
    "addr:street":"Hoogboomsteenweg",
    "iso:country":"BE",
    "sg:address":"Hoogboomsteenweg 133",
    "sg:city":"Kapellen",
    "sg:orig_category":"Services pour animaux domestiques",
    "sg:phone":"+32 3 651 99 09",
    "sg:postcode":"2950",
    "sg:province":"Antwerpen",
    "wof:name":"De Mobiele Hondenwassalon",
    "wof:placetype":"venue"
},
  "geometry": {"coordinates":[4.4526572227,51.3124046326],"type":"Point"}
}