{
  "type": "Feature",
  "properties": {
    "addr:full":"Basse-cour 11 Durbuy Luxembourg 6940",
    "addr:housenumber":"11",
    "addr:postcode":"6940",
    "addr:street":"Basse-Cour",
    "iso:country":"BE",
    "sg:address":"Basse-cour 11",
    "sg:city":"Durbuy",
    "sg:classifiers":[
        {
            "category":"Government",
            "subcategory":"Police Station",
            "type":"Public Place"
        }
    ],
    "sg:phone":"+32 86 21 20 69",
    "sg:postcode":"6940",
    "sg:province":"Luxembourg",
    "sg:tags":[
        "gendarmerie"
    ],
    "wof:name":"Police F\u00c9d\u00c9rale",
    "wof:placetype":"venue"
},
  "geometry": {"coordinates":[5.4966077805,50.351474762],"type":"Point"}
}