{
  "type": "Feature",
  "properties": {
    "iso:country":"BE",
    "sg:address":"Mozartlaan 14b3",
    "sg:city":"Vorst/forest",
    "sg:orig_category":"Advocaten and juridische adviseurs",
    "sg:phone":"+32 2 346 49 77",
    "sg:postcode":"1190",
    "sg:province":"Bruxelles-Capitale",
    "wof:name":"F. Printz",
    "wof:placetype":"venue"
},
  "geometry": {"coordinates":[4.3356142044,50.8124542236],"type":"Point"}
}