{
  "type": "Feature",
  "properties": {
    "iso:country":"BE",
    "sg:address":"Oude Luikerbaan 9 Box 1",
    "sg:city":"Hasselt",
    "sg:classifiers":[
        {
            "category":"Real Estate",
            "subcategory":"Architect",
            "type":"Services"
        }
    ],
    "sg:phone":"+32 11 33 49 36",
    "sg:postcode":"3500",
    "sg:province":"Limburg",
    "wof:name":"Van Dael K",
    "wof:placetype":"venue"
},
  "geometry": {"coordinates":[5.3412699699,50.9232368469],"type":"Point"}
}