{
  "type": "Feature",
  "properties": {
    "addr:full":"Rue De Bruxelles 2 Braine-le-comte Hainaut 7090",
    "addr:housenumber":"2",
    "addr:postcode":"7090",
    "addr:street":"Rue De Bruxelles",
    "iso:country":"BE",
    "sg:address":"Rue De Bruxelles 2",
    "sg:city":"Braine-le-comte",
    "sg:orig_category":"Notaires",
    "sg:phone":"+32 67 55 30 90",
    "sg:postcode":"7090",
    "sg:province":"Hainaut",
    "wof:name":"A. Lecomte",
    "wof:placetype":"venue"
},
  "geometry": {"coordinates":[4.1375799179,50.6159515381],"type":"Point"}
}