{
  "type": "Feature",
  "properties": {
    "addr:full":"Rue D'hoffschmidt 1 Habay (habay-la-neuve) Luxembourg 6720",
    "addr:housenumber":"1",
    "addr:postcode":"6720",
    "addr:street":"Rue D'Hoffschmidt",
    "iso:country":"BE",
    "sg:address":"Rue D'hoffschmidt 1",
    "sg:city":"Habay (habay-la-neuve)",
    "sg:classifiers":[
        {
            "category":"Shopping",
            "subcategory":"Optician",
            "type":"Retail Goods"
        }
    ],
    "sg:phone":"+32 63 42 34 22",
    "sg:postcode":"6720",
    "sg:province":"Luxembourg",
    "sg:tags":[
        "-"
    ],
    "wof:name":"Hittelet R",
    "wof:placetype":"venue"
},
  "geometry": {"coordinates":[5.6451888084,49.7289428711],"type":"Point"}
}