{
  "type": "Feature",
  "properties": {
    "addr:full":"Brieversweg 43 Damme (moerkerke) West-Vlaanderen 8340",
    "addr:housenumber":"43",
    "addr:postcode":"8340",
    "addr:street":"Brieversweg",
    "iso:country":"BE",
    "sg:address":"Brieversweg 43",
    "sg:city":"Damme (moerkerke)",
    "sg:classifiers":[
        {
            "category":"Farming",
            "subcategory":"Crops",
            "type":"Manufacturing & Wholesale Goods"
        }
    ],
    "sg:phone":"+32 50 35 50 34",
    "sg:postcode":"8340",
    "sg:province":"West-Vlaanderen",
    "sg:tags":[
        "vegetable",
        "fruit",
        "-",
        "grower"
    ],
    "wof:name":"Missault F",
    "wof:placetype":"venue"
},
  "geometry": {"coordinates":[3.3196649551,51.2202110291],"type":"Point"}
}