{
  "type": "Feature",
  "properties": {
    "addr:full":"Schooldreef 5 Mol Antwerpen 2400",
    "addr:housenumber":"5",
    "addr:postcode":"2400",
    "addr:street":"Schooldreef",
    "iso:country":"BE",
    "sg:address":"Schooldreef 5",
    "sg:city":"Mol",
    "sg:orig_category":"M\u00e9decins and sp\u00e9cialistes",
    "sg:phone":"+32 14 81 30 00",
    "sg:postcode":"2400",
    "sg:province":"Antwerpen",
    "wof:name":"K. Dillen",
    "wof:placetype":"venue"
},
  "geometry": {"coordinates":[5.2068858147,51.2094192505],"type":"Point"}
}