{
  "type": "Feature",
  "properties": {
    "addr:full":"Schuiferskapelsesteenweg 39 Tielt West-Vlaanderen 8700",
    "addr:housenumber":"39",
    "addr:postcode":"8700",
    "addr:street":"Schuiferskapelsesteenweg",
    "iso:country":"BE",
    "sg:address":"Schuiferskapelsesteenweg 39",
    "sg:city":"Tielt",
    "sg:orig_category":"Eleveurs and marchands de porcs",
    "sg:phone":"+32 51 40 02 74",
    "sg:postcode":"8700",
    "sg:province":"West-Vlaanderen",
    "wof:name":"Mieke Vande Walle",
    "wof:placetype":"venue"
},
  "geometry": {"coordinates":[3.3309500217,51.0156974792],"type":"Point"}
}