{
  "type": "Feature",
  "properties": {
    "addr:full":"Avenue De La R\u00c9sistance 2d Soumagne Li\u00e8ge 4630",
    "addr:housenumber":"2d",
    "addr:postcode":"4630",
    "addr:street":"Avenue De La Re\u0301Sistance",
    "iso:country":"BE",
    "sg:address":"Avenue De La R\u00c9sistance 2d",
    "sg:city":"Soumagne",
    "sg:orig_category":"Afvalwaterverwerking and ontstoppingsdiensten",
    "sg:phone":"+32 4 377 32 01",
    "sg:postcode":"4630",
    "sg:province":"Li\u00e8ge",
    "wof:name":"Christian Duysens",
    "wof:placetype":"venue"
},
  "geometry": {"coordinates":[5.7231731415,50.6272392273],"type":"Point"}
}