{
  "type": "Feature",
  "properties": {
    "addr:full":"Alsembergsteenweg 1150 Beersel Vlaams-Brabant 1650",
    "addr:postcode":"1150;1650",
    "addr:street":"Alsembergsteenweg",
    "iso:country":"BE",
    "sg:address":"Alsembergsteenweg 1150",
    "sg:city":"Beersel",
    "sg:classifiers":[
        {
            "category":"Professional",
            "subcategory":"Lawyer & Legal Services",
            "type":"Services"
        }
    ],
    "sg:phone":"+32 2 380 51 54",
    "sg:postcode":"1650",
    "sg:province":"Vlaams-Brabant",
    "wof:name":"Declercq-bogaert M",
    "wof:placetype":"venue"
},
  "geometry": {"coordinates":[4.3297948837,50.7643585205],"type":"Point"}
}