{
  "type": "Feature",
  "properties": {
    "addr:full":"Prins Boudewijnlaan 14 Maldegem Oost-Vlaanderen 9991",
    "addr:housenumber":"14",
    "addr:postcode":"9991",
    "addr:street":"Prins Boudewijnlaan",
    "iso:country":"BE",
    "sg:address":"Prins Boudewijnlaan 14",
    "sg:city":"Maldegem",
    "sg:orig_category":"M\u00e9decins and sp\u00e9cialistes",
    "sg:phone":"+32 50 71 30 09",
    "sg:postcode":"9991",
    "sg:province":"Oost-Vlaanderen",
    "wof:name":"Roxane De Kesel",
    "wof:placetype":"venue"
},
  "geometry": {"coordinates":[3.4953589439,51.2037963867],"type":"Point"}
}