{
  "type": "Feature",
  "properties": {
    "iso:country":"BE",
    "sg:address":"Industrieweg 16",
    "sg:city":"Tessenderlo",
    "sg:orig_category":"Installatie van houten of kunststof schrijnwerk",
    "sg:phone":"+32 13 66 54 91",
    "sg:postcode":"3980",
    "sg:province":"Limburg",
    "wof:name":"Marcel Sannen",
    "wof:placetype":"venue"
},
  "geometry": {"coordinates":[5.0907659531,51.0521316528],"type":"Point"}
}