{
  "type": "Feature",
  "properties": {
    "addr:full":"Gruuthusestraat 62 Tielt West-Vlaanderen 8700",
    "addr:housenumber":"62",
    "addr:postcode":"8700",
    "addr:street":"Gruuthusestraat",
    "iso:country":"BE",
    "sg:address":"Gruuthusestraat 62",
    "sg:city":"Tielt",
    "sg:orig_category":"Eleveurs and marchands de porcs. Eleveurs de bovins",
    "sg:phone":"+32 51 40 34 33",
    "sg:postcode":"8700",
    "sg:province":"West-Vlaanderen",
    "wof:name":"Jozef Vande Maele",
    "wof:placetype":"venue"
},
  "geometry": {"coordinates":[3.3347001076,50.9892463684],"type":"Point"}
}