{
  "type": "Feature",
  "properties": {
    "iso:country":"BE",
    "sg:address":"Guido Gezellelaan 85",
    "sg:city":"Puurs",
    "sg:classifiers":[
        {
            "category":"Professional",
            "subcategory":"Computer Services",
            "type":"Services"
        }
    ],
    "sg:phone":"+32 3 899 67 87",
    "sg:postcode":"2870",
    "sg:province":"Antwerpen",
    "sg:tags":[
        "webdesign",
        "-",
        "internet"
    ],
    "wof:name":"Daeonic Media",
    "wof:placetype":"venue"
},
  "geometry": {"coordinates":[4.2877287865,51.0755004883],"type":"Point"}
}