{
  "type": "Feature",
  "properties": {
    "addr:full":"Lange Schouwenstraat 3 Zonhoven Limburg 3520",
    "addr:housenumber":"3",
    "addr:postcode":"3520",
    "addr:street":"Lange Schouwenstraat",
    "iso:country":"BE",
    "sg:address":"Lange Schouwenstraat 3",
    "sg:city":"Zonhoven",
    "sg:classifiers":[
        {
            "category":"Home & Garden",
            "subcategory":"Home Furnishings",
            "type":"Retail Goods"
        }
    ],
    "sg:phone":"+32 11 73 33 58",
    "sg:postcode":"3520",
    "sg:province":"Limburg",
    "sg:tags":[
        "interior",
        "decoration"
    ],
    "wof:name":"Duc I D Bvba",
    "wof:placetype":"venue"
},
  "geometry": {"coordinates":[5.3577928543,50.9845085144],"type":"Point"}
}