{
  "type": "Feature",
  "properties": {
    "iso:country":"BE",
    "sg:address":"Rue Dorez 15b",
    "sg:city":"Tournai",
    "sg:classifiers":[
        {
            "category":"Restaurant",
            "type":"Food & Drink"
        }
    ],
    "sg:phone":"+32 69 21 29 04",
    "sg:postcode":"7500",
    "sg:province":"Hainaut",
    "wof:name":"Les Palmiers",
    "wof:placetype":"venue"
},
  "geometry": {"coordinates":[3.382723093,50.6067733765],"type":"Point"}
}