{
  "type": "Feature",
  "properties": {
    "iso:country":"BE",
    "sg:address":"Mandelstraat 74",
    "sg:city":"Izegem",
    "sg:classifiers":[
        {
            "category":"Communications",
            "subcategory":"Radio Station",
            "type":"Services"
        }
    ],
    "sg:phone":"+32 51 33 19 40",
    "sg:postcode":"8870",
    "sg:province":"West-Vlaanderen",
    "sg:tags":[
        "transmission"
    ],
    "wof:name":"M.t.i.-firma Martin Nv",
    "wof:placetype":"venue"
},
  "geometry": {"coordinates":[3.2010951042,50.9234886169],"type":"Point"}
}