{
  "type": "Feature",
  "properties": {
    "iso:country":"BE",
    "sg:address":"Kerkstraat 20",
    "sg:city":"Nieuwpoort",
    "sg:orig_category":"Rev\u00eatements de sols and murs. Mat\u00e9riaux de construction Rev\u00eatements pour sols and murs",
    "sg:phone":"+32 58 23 55 78",
    "sg:postcode":"8620",
    "sg:province":"West-Vlaanderen",
    "wof:name":"Dirk Van Nieuwenhoven",
    "wof:placetype":"venue"
},
  "geometry": {"coordinates":[2.748333931,51.1290817261],"type":"Point"}
}