{
  "type": "Feature",
  "properties": {
    "iso:country":"BE",
    "sg:address":"Rue De Glatigny 12",
    "sg:city":"Perwez",
    "sg:orig_category":"Huishoudapparaten, televisies and radio's",
    "sg:phone":"+32 81 65 59 58",
    "sg:postcode":"1360",
    "sg:province":"Brabant Wallon",
    "wof:name":"De Jelin",
    "wof:placetype":"venue"
},
  "geometry": {"coordinates":[4.795083046,50.6469726562],"type":"Point"}
}