{
  "type": "Feature",
  "properties": {
    "iso:country":"BE",
    "sg:address":"Rijkenhoek 93",
    "sg:city":"Bornem",
    "sg:classifiers":[
        {
            "category":"Arena",
            "subcategory":"Sports Club",
            "type":"Entertainment"
        }
    ],
    "sg:phone":"+32 3 899 41 70",
    "sg:postcode":"2880",
    "sg:province":"Antwerpen",
    "sg:tags":[
        "de"
    ],
    "wof:name":"Dodentocht - Kadee",
    "wof:placetype":"venue"
},
  "geometry": {"coordinates":[4.2286372185,51.1024665833],"type":"Point"}
}