{
  "type": "Feature",
  "properties": {
    "addr:full":"Ijzerenveld 8 Sint-katelijne-waver Antwerpen 2860",
    "addr:housenumber":"8",
    "addr:postcode":"2860",
    "addr:street":"Ijzerenveld",
    "iso:country":"BE",
    "sg:address":"Ijzerenveld 8",
    "sg:city":"Sint-katelijne-waver",
    "sg:classifiers":[
        {
            "category":"Personal",
            "subcategory":"Beauty Salon",
            "type":"Services"
        }
    ],
    "sg:phone":"+32 15 55 13 39",
    "sg:postcode":"2860",
    "sg:province":"Antwerpen",
    "sg:tags":[
        "de",
        "coiffure"
    ],
    "wof:name":"Coiffure Daniel",
    "wof:placetype":"venue"
},
  "geometry": {"coordinates":[4.5338730812,51.0684928894],"type":"Point"}
}