{
  "type": "Feature",
  "properties": {
    "addr:full":"Rue Reine Astrid 13 Engis Li\u00e8ge 4480",
    "addr:housenumber":"13",
    "addr:postcode":"4480",
    "addr:street":"Rue Reine Astrid",
    "iso:country":"BE",
    "sg:address":"Rue Reine Astrid 13",
    "sg:city":"Engis",
    "sg:classifiers":[
        {
            "category":"Health Services",
            "subcategory":"Nursing And Care Facility",
            "type":"Services"
        }
    ],
    "sg:phone":"+32 4 275 39 74",
    "sg:postcode":"4480",
    "sg:province":"Li\u00e8ge",
    "sg:tags":[
        "public"
    ],
    "wof:name":"C.p.a.s.",
    "wof:placetype":"venue"
},
  "geometry": {"coordinates":[5.4044518471,50.5824394226],"type":"Point"}
}