{
  "type": "Feature",
  "properties": {
    "addr:full":"Steenpoelweg 4 Affligem Vlaams-Brabant 1790",
    "addr:housenumber":"4",
    "addr:postcode":"1790",
    "addr:street":"Steenpoelweg",
    "iso:country":"BE",
    "sg:address":"Steenpoelweg 4",
    "sg:city":"Affligem",
    "sg:orig_category":"Dakwerken Installatie van houten of kunststof schrijnwerk",
    "sg:phone":"+32 53 77 02 72",
    "sg:postcode":"1790",
    "sg:province":"Vlaams-Brabant",
    "wof:name":"Armand De Geyseleer",
    "wof:placetype":"venue"
},
  "geometry": {"coordinates":[4.0958499908,50.9169807434],"type":"Point"}
}