{
  "type": "Feature",
  "properties": {
    "addr:full":"Opwijksestraat 6 Lebbeke Oost-Vlaanderen 9280",
    "addr:housenumber":"6",
    "addr:postcode":"9280",
    "addr:street":"Opwijksestraat",
    "iso:country":"BE",
    "sg:address":"Opwijksestraat 6",
    "sg:city":"Lebbeke",
    "sg:classifiers":[
        {
            "category":"Personal",
            "subcategory":"Beauty Salon",
            "type":"Services"
        }
    ],
    "sg:phone":"+32 52 41 20 04",
    "sg:postcode":"9280",
    "sg:province":"Oost-Vlaanderen",
    "sg:tags":[
        "lady",
        "-",
        "hairdressing"
    ],
    "wof:name":"Natalie",
    "wof:placetype":"venue"
},
  "geometry": {"coordinates":[4.1315698624,50.9974555969],"type":"Point"}
}