{
  "type": "Feature",
  "properties": {
    "iso:country":"BE",
    "sg:address":"Engelbert Moensstraat 22",
    "sg:city":"Kortenberg",
    "sg:orig_category":"Groententeelt",
    "sg:phone":"+32 2 759 56 56",
    "sg:postcode":"3078",
    "sg:province":"Vlaams-Brabant",
    "wof:name":"Emiel De Winter",
    "wof:placetype":"venue"
},
  "geometry": {"coordinates":[4.5909371376,50.8803329468],"type":"Point"}
}