{
  "type": "Feature",
  "properties": {
    "addr:full":"Gaversesteenweg 362 Deinze (petegem-aan-de-leie) Oost-Vlaanderen 9800",
    "addr:housenumber":"362",
    "addr:postcode":"9800",
    "addr:street":"Gaversesteenweg;Oost-Vlaanderen",
    "iso:country":"BE",
    "sg:address":"Gaversesteenweg 362",
    "sg:city":"Deinze (petegem-aan-de-leie)",
    "sg:classifiers":[
        {
            "category":"Shopping",
            "subcategory":"Discount & Variety Stores",
            "type":"Retail Goods"
        }
    ],
    "sg:phone":"+32 9 386 51 04",
    "sg:postcode":"9800",
    "sg:province":"Oost-Vlaanderen",
    "sg:tags":[
        "shop",
        "clearers",
        "curiosity",
        "furniture"
    ],
    "wof:name":"Brocante",
    "wof:placetype":"venue"
},
  "geometry": {"coordinates":[3.530174017,50.9863166809],"type":"Point"}
}