{
  "type": "Feature",
  "properties": {
    "addr:full":"Lepelstraat 26 Brakel Oost-Vlaanderen 9660",
    "addr:housenumber":"26",
    "addr:postcode":"9660",
    "addr:street":"Lepelstraat",
    "iso:country":"BE",
    "sg:address":"Lepelstraat 26",
    "sg:city":"Brakel",
    "sg:classifiers":[
        {
            "category":"Personal",
            "subcategory":"Beauty Salon",
            "type":"Services"
        }
    ],
    "sg:phone":"+32 55 42 40 57",
    "sg:postcode":"9660",
    "sg:province":"Oost-Vlaanderen",
    "sg:tags":[
        "de",
        "coiffure"
    ],
    "wof:name":"Coifure Christine",
    "wof:placetype":"venue"
},
  "geometry": {"coordinates":[3.7642250061,50.8031082153],"type":"Point"}
}