{
  "type": "Feature",
  "properties": {
    "addr:full":"Korpsestraat 102 Herk-de-stad Limburg 3540",
    "addr:housenumber":"102",
    "addr:postcode":"3540",
    "addr:street":"Korpsestraat",
    "iso:country":"BE",
    "sg:address":"Korpsestraat 102",
    "sg:city":"Herk-de-stad",
    "sg:classifiers":[
        {
            "category":"Food & Beverages",
            "subcategory":"Fruits & Vegetables",
            "type":"Retail Goods"
        }
    ],
    "sg:phone":"+32 13 44 16 69",
    "sg:postcode":"3540",
    "sg:province":"Limburg",
    "sg:tags":[
        "groenten"
    ],
    "wof:name":"Alice Morren",
    "wof:placetype":"venue"
},
  "geometry": {"coordinates":[5.1383900642,50.920589447],"type":"Point"}
}