{
  "type": "Feature",
  "properties": {
    "addr:full":"Wielmakerstraat 2 Tielt West-Vlaanderen 8700",
    "addr:housenumber":"2",
    "addr:postcode":"8700",
    "addr:street":"Wielmakerstraat",
    "iso:country":"BE",
    "sg:address":"Wielmakerstraat 2",
    "sg:city":"Tielt",
    "sg:orig_category":"Rundveehouders Varkenskwekers",
    "sg:phone":"+32 51 40 18 05",
    "sg:postcode":"8700",
    "sg:province":"West-Vlaanderen",
    "wof:name":"Albert Maeyaert",
    "wof:placetype":"venue"
},
  "geometry": {"coordinates":[3.3504900932,50.9952659607],"type":"Point"}
}