{
  "type": "Feature",
  "properties": {
    "iso:country":"BE",
    "sg:address":"Noordhoekstraat 42",
    "sg:city":"De Panne (adinkerke)",
    "sg:classifiers":[
        {
            "category":"Parking",
            "subcategory":"Lot",
            "type":"Transportation"
        }
    ],
    "sg:phone":"+32 475 50 18 91",
    "sg:postcode":"8660",
    "sg:province":"West-Vlaanderen",
    "sg:tags":[
        "parking-places",
        "laying-out"
    ],
    "wof:name":"Coulier Marc",
    "wof:placetype":"venue"
},
  "geometry": {"coordinates":[2.6138749123,51.0775222778],"type":"Point"}
}