{
  "type": "Feature",
  "properties": {
    "iso:country":"BE",
    "sg:address":"Briscol 1",
    "sg:city":"Erez\u00e9e",
    "sg:classifiers":[
        {
            "category":"Utilities",
            "subcategory":"Fuel Oil & Lpg",
            "type":"Services"
        }
    ],
    "sg:phone":"+32 86 47 72 50",
    "sg:postcode":"6997",
    "sg:province":"Luxembourg",
    "wof:name":"Seron Ets",
    "wof:placetype":"venue"
},
  "geometry": {"coordinates":[5.6004858017,50.2950706482],"type":"Point"}
}