{
  "type": "Feature",
  "properties": {
    "addr:full":"Vrijdagmarkt 50 Gent Oost-Vlaanderen 9000",
    "addr:housenumber":"50",
    "addr:postcode":"9000",
    "addr:street":"Vrijdagmarkt;Oost-Vlaanderen",
    "iso:country":"BE",
    "sg:address":"Vrijdagmarkt 50",
    "sg:city":"Gent",
    "sg:classifiers":[
        {
            "category":"Cafe",
            "type":"Food & Drink"
        }
    ],
    "sg:phone":"+32 9 224 24 55",
    "sg:postcode":"9000",
    "sg:province":"Oost-Vlaanderen",
    "sg:tags":[
        "caf\u00e9s"
    ],
    "wof:name":"Caf\u00c9 Dulle Griet",
    "wof:placetype":"venue"
},
  "geometry": {"coordinates":[3.7252869606,51.0565605164],"type":"Point"}
}