{
  "type": "Feature",
  "properties": {
    "addr:full":"Ter Stratenweg 46 Oelegem Antwerpen 2520",
    "addr:housenumber":"46",
    "addr:postcode":"2520",
    "addr:street":"Ter Stratenweg",
    "iso:country":"BE",
    "sg:address":"Ter Stratenweg 46",
    "sg:city":"Oelegem",
    "sg:classifiers":[
        {
            "category":"Food & Beverages",
            "subcategory":"Dairy",
            "type":"Retail Goods"
        }
    ],
    "sg:phone":"+32 3 470 11 70",
    "sg:postcode":"2520",
    "sg:province":"Antwerpen",
    "sg:tags":[
        "product",
        "related"
    ],
    "wof:name":"Antwerpse Kaascentrale Nv",
    "wof:placetype":"venue"
},
  "geometry": {"coordinates":[4.5804100037,51.210483551],"type":"Point"}
}