{
  "type": "Feature",
  "properties": {
    "iso:country":"BE",
    "sg:address":"Rue Albert-huybrechts 3bc5",
    "sg:city":"Dinant",
    "sg:orig_category":"Beheer onroerend goed",
    "sg:phone":"+32 82 22 58 79",
    "sg:postcode":"5500",
    "sg:province":"Namur",
    "wof:name":"Andre Courtois",
    "wof:placetype":"venue"
},
  "geometry": {"coordinates":[4.9147400856,50.2555389404],"type":"Point"}
}