{
  "type": "Feature",
  "properties": {
    "iso:country":"BE",
    "sg:address":"Provinciebaan 55",
    "sg:city":"Hulshout (houtvenne)",
    "sg:classifiers":[
        {
            "category":"Bars & Pubs",
            "type":"Food & Drink"
        }
    ],
    "sg:phone":"+32 16 69 95 50",
    "sg:postcode":"2235",
    "sg:province":"Antwerpen",
    "wof:name":"Duivenlokaal",
    "wof:placetype":"venue"
},
  "geometry": {"coordinates":[4.8046398163,51.0572013855],"type":"Point"}
}