{
  "type": "Feature",
  "properties": {
    "addr:full":"Avenue Des Eaux Vives 13 Rixensart Brabant Wallon 1332",
    "addr:housenumber":"13",
    "addr:postcode":"1332",
    "addr:street":"Avenue Des Eaux Vives;Wallon",
    "iso:country":"BE",
    "sg:address":"Avenue Des Eaux Vives 13",
    "sg:city":"Rixensart",
    "sg:orig_category":"Hout and afgeleiden Gh IJzerwaren, bouw- and verfmaterialen",
    "sg:phone":"+32 2 653 13 79",
    "sg:postcode":"1332",
    "sg:province":"Brabant Wallon",
    "wof:name":"I.t.b.",
    "wof:placetype":"venue"
},
  "geometry": {"coordinates":[4.5105528831,50.7300033569],"type":"Point"}
}