{
  "type": "Feature",
  "properties": {
    "iso:country":"BE",
    "sg:address":"Britse Lei 55",
    "sg:city":"Antwerpen",
    "sg:classifiers":[
        {
            "category":"Professional",
            "subcategory":"Lawyer & Legal Services",
            "type":"Services"
        }
    ],
    "sg:phone":"+32 3 242 07 77",
    "sg:postcode":"2000",
    "sg:province":"Antwerpen",
    "wof:name":"Orde Van De Advocaten",
    "wof:placetype":"venue"
},
  "geometry": {"coordinates":[4.4043998718,51.2097206116],"type":"Point"}
}