{
  "type": "Feature",
  "properties": {
    "addr:full":"Koningin Astridlaan 25 Diest Vlaams-Brabant 3290",
    "addr:housenumber":"25",
    "addr:postcode":"3290",
    "addr:street":"Koningin Astridlaan",
    "iso:country":"BE",
    "sg:address":"Koningin Astridlaan 25",
    "sg:city":"Diest",
    "sg:classifiers":[
        {
            "category":"Professional",
            "subcategory":"Lawyer & Legal Services",
            "type":"Services"
        }
    ],
    "sg:phone":"+32 13 31 18 72",
    "sg:postcode":"3290",
    "sg:province":"Vlaams-Brabant",
    "wof:name":"Reynders G Jr",
    "wof:placetype":"venue"
},
  "geometry": {"coordinates":[5.0571022034,50.9801139832],"type":"Point"}
}