{
  "type": "Feature",
  "properties": {
    "addr:full":"Koornbloemstraat 211 Antwerpen (wilrijk) Antwerpen 2610",
    "addr:housenumber":"211",
    "addr:postcode":"2610",
    "addr:street":"Koornbloemstraat;Antwerpen",
    "iso:country":"BE",
    "sg:address":"Koornbloemstraat 211",
    "sg:city":"Antwerpen (wilrijk)",
    "sg:classifiers":[
        {
            "category":"Building & Trades",
            "subcategory":"Cleaning & Sanitation",
            "type":"Services"
        }
    ],
    "sg:phone":"+32 3 827 79 98",
    "sg:postcode":"2610",
    "sg:province":"Antwerpen",
    "sg:tags":[
        "cleaner",
        "window"
    ],
    "wof:name":"Luna",
    "wof:placetype":"venue"
},
  "geometry": {"coordinates":[4.3946051598,51.1691131592],"type":"Point"}
}