{
  "type": "Feature",
  "properties": {
    "addr:full":"Harfontaine 3 Neufchateau Luxembourg 6840",
    "addr:housenumber":"3",
    "addr:postcode":"6840",
    "addr:street":"Harfontaine",
    "iso:country":"BE",
    "sg:address":"Harfontaine 3",
    "sg:city":"Neufchateau",
    "sg:orig_category":"Eleveurs de bovins",
    "sg:phone":"+32 61 27 88 56",
    "sg:postcode":"6840",
    "sg:province":"Luxembourg",
    "wof:name":"Arsene Goebels",
    "wof:placetype":"venue"
},
  "geometry": {"coordinates":[5.4346451759,49.8411598206],"type":"Point"}
}