{
  "type": "Feature",
  "properties": {
    "iso:country":"BE",
    "sg:address":"Kleinmijlveld 38",
    "sg:city":"Lint",
    "sg:classifiers":[
        {
            "category":"Real Estate",
            "subcategory":"Developer",
            "type":"Services"
        }
    ],
    "sg:phone":"+32 3 454 25 79",
    "sg:postcode":"2547",
    "sg:province":"Antwerpen",
    "sg:tags":[
        "project"
    ],
    "wof:name":"Classics & Greens",
    "wof:placetype":"venue"
},
  "geometry": {"coordinates":[4.4742650986,51.1405601501],"type":"Point"}
}