{
  "type": "Feature",
  "properties": {
    "addr:full":"Genkerweg 67 Zutendaal Limburg 3690",
    "addr:housenumber":"67",
    "addr:postcode":"3690",
    "addr:street":"Genkerweg",
    "iso:country":"BE",
    "sg:address":"Genkerweg 67",
    "sg:city":"Zutendaal",
    "sg:classifiers":[
        {
            "category":"Transit Center",
            "subcategory":"Passenger",
            "type":"Transportation"
        }
    ],
    "sg:phone":"+32 89 61 13 22",
    "sg:postcode":"3690",
    "sg:province":"Limburg",
    "sg:tags":[
        "sand",
        "gravel"
    ],
    "wof:name":"Kempens Kiezelbedrijf Nv",
    "wof:placetype":"venue"
},
  "geometry": {"coordinates":[5.5508928299,50.9415359497],"type":"Point"}
}