{
  "type": "Feature",
  "properties": {
    "addr:full":"Boulevard Du Quatre-mars 105 Ronse/renaix Oost-Vlaanderen 9600",
    "addr:housenumber":"105",
    "addr:postcode":"9600",
    "addr:street":"Boulevard Du Quatre-Mars",
    "iso:country":"BE",
    "sg:address":"Boulevard Du Quatre-mars 105",
    "sg:city":"Ronse/renaix",
    "sg:classifiers":[
        {
            "category":"Cafe",
            "type":"Food & Drink"
        }
    ],
    "sg:phone":"+32 55 21 42 72",
    "sg:postcode":"9600",
    "sg:province":"Oost-Vlaanderen",
    "sg:tags":[
        "caf\u00e9s"
    ],
    "wof:name":"Caf\u00c9 Assa",
    "wof:placetype":"venue"
},
  "geometry": {"coordinates":[3.5925080776,50.7402153015],"type":"Point"}
}