{
  "type": "Feature",
  "properties": {
    "addr:full":"Kalverveld 8-12 Borgerhout Antwerpen 2140",
    "addr:housenumber":"8-12;2140",
    "addr:street":"Borgerhout Antwerpen",
    "iso:country":"BE",
    "sg:address":"Kalverveld 8-12",
    "sg:city":"Borgerhout",
    "sg:classifiers":[
        {
            "category":"Travel",
            "subcategory":"Hotels & Motels",
            "type":"Entertainment"
        }
    ],
    "sg:phone":"+32 3 217 40 40",
    "sg:postcode":"2140",
    "sg:province":"Antwerpen",
    "sg:tags":[
        "hotels",
        "business",
        "restaurant"
    ],
    "wof:name":"City Inn Suisse Nv",
    "wof:placetype":"venue"
},
  "geometry": {"coordinates":[4.4461121559,51.2074890137],"type":"Point"}
}