{
  "type": "Feature",
  "properties": {
    "iso:country":"BE",
    "sg:address":"Ulbeekstraat 20",
    "sg:city":"Wellen (ulbeek)",
    "sg:classifiers":[
        {
            "category":"Professional",
            "subcategory":"Art Services",
            "type":"Services"
        }
    ],
    "sg:phone":"+32 12 74 77 76",
    "sg:postcode":"3832",
    "sg:province":"Limburg",
    "sg:tags":[
        "photographer"
    ],
    "wof:name":"Georges Charlier Bvba",
    "wof:placetype":"venue"
},
  "geometry": {"coordinates":[5.3082938194,50.840839386],"type":"Point"}
}