{
  "type": "Feature",
  "properties": {
    "addr:full":"Guchtweg 15 Affligem Vlaams-Brabant 1790",
    "addr:housenumber":"15",
    "addr:postcode":"1790",
    "addr:street":"Guchtweg",
    "iso:country":"BE",
    "sg:address":"Guchtweg 15",
    "sg:city":"Affligem",
    "sg:orig_category":"Schoonheidssalons",
    "sg:phone":"+32 53 66 18 97",
    "sg:postcode":"1790",
    "sg:province":"Vlaams-Brabant",
    "wof:name":"Colette De Pauw",
    "wof:placetype":"venue"
},
  "geometry": {"coordinates":[4.1097798347,50.9137229919],"type":"Point"}
}