{
  "type": "Feature",
  "properties": {
    "addr:full":"Emile Bethuynelaan 2 Brugge (sint-michiels) West-Vlaanderen 8200",
    "addr:housenumber":"2",
    "addr:postcode":"8200",
    "addr:street":"Bethuynelaan",
    "iso:country":"BE",
    "sg:address":"Emile Bethuynelaan 2",
    "sg:city":"Brugge (sint-michiels)",
    "sg:classifiers":[
        {
            "category":"Real Estate",
            "subcategory":"Architect",
            "type":"Services"
        }
    ],
    "sg:phone":"+32 50 38 86 95",
    "sg:postcode":"8200",
    "sg:province":"West-Vlaanderen",
    "wof:name":"Pruuost J",
    "wof:placetype":"venue"
},
  "geometry": {"coordinates":[3.1894900799,51.1640205383],"type":"Point"}
}