{
  "type": "Feature",
  "properties": {
    "iso:country":"BE",
    "sg:address":"Rue De La Justice 24",
    "sg:city":"Saint-nicolas",
    "sg:classifiers":[
        {
            "category":"Wholesale",
            "subcategory":"Painting Supplies",
            "type":"Manufacturing & Wholesale Goods"
        }
    ],
    "sg:phone":"+32 4 252 42 26",
    "sg:postcode":"4420",
    "sg:province":"Li\u00e8ge",
    "sg:tags":[
        "spray"
    ],
    "wof:name":"All Paints",
    "wof:placetype":"venue"
},
  "geometry": {"coordinates":[5.5417151451,50.625415802],"type":"Point"}
}