{
  "type": "Feature",
  "properties": {
    "addr:full":"Elst 7 Drogenbos Vlaams-Brabant 1620",
    "addr:housenumber":"7",
    "addr:postcode":"1620",
    "addr:street":"Elst",
    "iso:country":"BE",
    "sg:address":"Elst 7",
    "sg:city":"Drogenbos",
    "sg:classifiers":[
        {
            "category":"Building & Trades",
            "subcategory":"Plumbing",
            "type":"Services"
        }
    ],
    "sg:phone":"+32 2 377 43 92",
    "sg:postcode":"1620",
    "sg:province":"Vlaams-Brabant",
    "sg:tags":[
        "contractor"
    ],
    "wof:name":"Tsp Plomberie",
    "wof:placetype":"venue"
},
  "geometry": {"coordinates":[4.3200268745,50.7841567993],"type":"Point"}
}