{
  "type": "Feature",
  "properties": {
    "iso:country":"BE",
    "sg:address":"Beekstraat 39",
    "sg:city":"Melle",
    "sg:orig_category":"Paramedische behandelingen",
    "sg:phone":"+32 9 252 15 22",
    "sg:postcode":"9090",
    "sg:province":"Oost-Vlaanderen",
    "wof:name":"V. Balcaen",
    "wof:placetype":"venue"
},
  "geometry": {"coordinates":[3.7980120182,50.9999694824],"type":"Point"}
}