{
  "type": "Feature",
  "properties": {
    "addr:full":"Rue Des R\u00c9collets 6 Bastogne Luxembourg 6600",
    "addr:housenumber":"6",
    "addr:postcode":"6600",
    "addr:street":"Rue Des Re\u0301Collets",
    "iso:country":"BE",
    "sg:address":"Rue Des R\u00c9collets 6",
    "sg:city":"Bastogne",
    "sg:classifiers":[
        {
            "category":"Health Services",
            "subcategory":"Nursing And Care Facility",
            "type":"Services"
        }
    ],
    "sg:phone":"+32 61 21 60 30",
    "sg:postcode":"6600",
    "sg:province":"Luxembourg",
    "sg:tags":[
        "public"
    ],
    "wof:name":"Admin. Contrib. Directes",
    "wof:placetype":"venue"
},
  "geometry": {"coordinates":[5.7178401947,50.0022315979],"type":"Point"}
}