{
  "type": "Feature",
  "properties": {
    "iso:country":"BE",
    "sg:address":"Rue Roton 10",
    "sg:city":"Anderlues",
    "sg:orig_category":"Installatie van houten of kunststof schrijnwerk",
    "sg:phone":"+32 71 52 42 15",
    "sg:postcode":"6150",
    "sg:province":"Hainaut",
    "wof:name":"Fabrice Quenon",
    "wof:placetype":"venue"
},
  "geometry": {"coordinates":[4.2855668068,50.4107017517],"type":"Point"}
}