{
  "type": "Feature",
  "properties": {
    "iso:country":"BE",
    "sg:address":"Oudstrijderslaan 31",
    "sg:city":"Kuurne",
    "sg:orig_category":"Herstellingen and onderhoud van auto's",
    "sg:phone":"+32 56 71 96 13",
    "sg:postcode":"8520",
    "sg:province":"West-Vlaanderen",
    "wof:name":"Eric Deschamps",
    "wof:placetype":"venue"
},
  "geometry": {"coordinates":[3.2904980183,50.8543243408],"type":"Point"}
}