{
  "type": "Feature",
  "properties": {
    "iso:country":"BE",
    "sg:address":"Gerard Le Grellelaan 9",
    "sg:city":"Antwerpen",
    "sg:classifiers":[
        {
            "category":"Bars & Pubs",
            "type":"Food & Drink"
        }
    ],
    "sg:phone":"+32 3 828 93 81",
    "sg:postcode":"2020",
    "sg:province":"Antwerpen",
    "sg:tags":[
        "tavern"
    ],
    "wof:name":"Melkerij Nachtegalenpark Bvba",
    "wof:placetype":"venue"
},
  "geometry": {"coordinates":[4.4045600891,51.1870994568],"type":"Point"}
}