{
  "type": "Feature",
  "properties": {
    "addr:full":"Gauwstraat 16 Brakel (nederbrakel) Oost-Vlaanderen 9660",
    "addr:housenumber":"16",
    "addr:postcode":"9660",
    "addr:street":"Gauwstraat",
    "iso:country":"BE",
    "sg:address":"Gauwstraat 16",
    "sg:city":"Brakel (nederbrakel)",
    "sg:classifiers":[
        {
            "category":"Health Services",
            "subcategory":"Health Practitioner",
            "type":"Services"
        }
    ],
    "sg:phone":"+32 55 42 47 23",
    "sg:postcode":"9660",
    "sg:province":"Oost-Vlaanderen",
    "sg:tags":[
        "physiotherapist"
    ],
    "wof:name":"Schotte Kurt",
    "wof:placetype":"venue"
},
  "geometry": {"coordinates":[3.7681310177,50.8032913208],"type":"Point"}
}