{
  "type": "Feature",
  "properties": {
    "iso:country":"BE",
    "sg:address":"Chemin Vert 53",
    "sg:city":"Celles",
    "sg:orig_category":"Boissons",
    "sg:phone":"+32 69 55 65 25",
    "sg:postcode":"7760",
    "sg:province":"Hainaut",
    "wof:name":"Maison Bourgi",
    "wof:placetype":"venue"
},
  "geometry": {"coordinates":[3.3973579407,50.6871261597],"type":"Point"}
}