{
  "type": "Feature",
  "properties": {
    "addr:full":"Kuringersteenweg 324 Kuringen Limburg 3511",
    "addr:housenumber":"324",
    "addr:postcode":"3511",
    "addr:street":"Kuringersteenweg",
    "iso:country":"BE",
    "sg:address":"Kuringersteenweg 324",
    "sg:city":"Kuringen",
    "sg:orig_category":"Huisdieren and benodigdheden Royal Canin",
    "sg:phone":"+32 11 25 34 73",
    "sg:postcode":"3511",
    "sg:province":"Limburg",
    "wof:name":"Kameleon",
    "wof:placetype":"venue"
},
  "geometry": {"coordinates":[5.3095059395,50.9389915466],"type":"Point"}
}