{
  "type": "Feature",
  "properties": {
    "iso:country":"BE",
    "sg:address":"Karabiniersplein 7",
    "sg:city":"Schaarbeek/schaerbeek",
    "sg:orig_category":"Film-, tv- and videoproductie Geluidsopnames",
    "sg:phone":"+32 2 745 04 35",
    "sg:postcode":"1030",
    "sg:province":"Bruxelles-Capitale",
    "wof:name":"Twins",
    "wof:placetype":"venue"
},
  "geometry": {"coordinates":[4.4000911713,50.8539199829],"type":"Point"}
}