{
  "type": "Feature",
  "properties": {
    "addr:full":"Koningin Fabiolalaan 1 Machelen (groot) Vlaams-Brabant 1830",
    "addr:housenumber":"1",
    "addr:postcode":"1830",
    "addr:street":"Koningin Fabiolalaan;Groot Vlaams-Brabant",
    "iso:country":"BE",
    "sg:address":"Koningin Fabiolalaan 1",
    "sg:city":"Machelen (groot)",
    "sg:orig_category":"Banques and organismes de cr\u00e9dit",
    "sg:phone":"+32 2 257 20 50",
    "sg:postcode":"1830",
    "sg:province":"Vlaams-Brabant",
    "wof:name":"Dexia",
    "wof:placetype":"venue"
},
  "geometry": {"coordinates":[4.4376659393,50.9121589661],"type":"Point"}
}