{
  "type": "Feature",
  "properties": {
    "iso:country":"BE",
    "sg:address":"Langendam 41",
    "sg:city":"Evergem (sleidinge)",
    "sg:classifiers":[
        {
            "category":"Building & Trades",
            "subcategory":"Construction",
            "type":"Services"
        }
    ],
    "sg:phone":"+32 9 357 72 35",
    "sg:postcode":"9940",
    "sg:province":"Oost-Vlaanderen",
    "sg:tags":[
        "stair"
    ],
    "wof:name":"Welvaert L",
    "wof:placetype":"venue"
},
  "geometry": {"coordinates":[3.6555490494,51.1382904053],"type":"Point"}
}