{
  "type": "Feature",
  "properties": {
    "addr:full":"Rue De La Dr\u00cave 76 Clavier Li\u00e8ge 4560",
    "addr:housenumber":"76",
    "addr:postcode":"4560",
    "addr:street":"Rue De La Dre\u0302Ve",
    "iso:country":"BE",
    "sg:address":"Rue De La Dr\u00cave 76",
    "sg:city":"Clavier",
    "sg:orig_category":"Diverse opleidingen and onderwijs",
    "sg:phone":"+32 86 34 44 03",
    "sg:postcode":"4560",
    "sg:province":"Li\u00e8ge",
    "wof:name":"Victor Guilmain",
    "wof:placetype":"venue"
},
  "geometry": {"coordinates":[5.3575191498,50.4288978577],"type":"Point"}
}