{
  "type": "Feature",
  "properties": {
    "addr:full":"Bredestraat 38 Kapelle-op-den-bos Vlaams-Brabant 1880",
    "addr:housenumber":"38",
    "addr:postcode":"1880",
    "addr:street":"Bredestraat",
    "iso:country":"BE",
    "sg:address":"Bredestraat 38",
    "sg:city":"Kapelle-op-den-bos",
    "sg:orig_category":"Rundveehouders",
    "sg:phone":"+32 15 71 22 15",
    "sg:postcode":"1880",
    "sg:province":"Vlaams-Brabant",
    "wof:name":"Frans Verelst",
    "wof:placetype":"venue"
},
  "geometry": {"coordinates":[4.3842048645,51.0083656311],"type":"Point"}
}