{
  "type": "Feature",
  "properties": {
    "addr:full":"Avenue Houzeau 64 Ukkel/uccle Bruxelles-Capitale 1180",
    "addr:housenumber":"64",
    "addr:postcode":"1180",
    "addr:street":"Avenue Houzeau;/",
    "iso:country":"BE",
    "sg:address":"Avenue Houzeau 64",
    "sg:city":"Ukkel/uccle",
    "sg:orig_category":"Agences de publicit\u00e9",
    "sg:phone":"+32 2 331 34 38",
    "sg:postcode":"1180",
    "sg:province":"Bruxelles-Capitale",
    "wof:name":"Tact",
    "wof:placetype":"venue"
},
  "geometry": {"coordinates":[4.3589577675,50.8015937805],"type":"Point"}
}