{
  "type": "Feature",
  "properties": {
    "iso:country":"BE",
    "sg:address":"Clos Sainte-anne 5",
    "sg:city":"Chaumont-gistoux",
    "sg:orig_category":"Boekhouders",
    "sg:phone":"+32 10 68 90 77",
    "sg:postcode":"1325",
    "sg:province":"Brabant Wallon",
    "wof:name":"Fr\u00c9d\u00c9ric Meys",
    "wof:placetype":"venue"
},
  "geometry": {"coordinates":[4.6850099564,50.6871604919],"type":"Point"}
}