{
  "type": "Feature",
  "properties": {
    "iso:country":"BE",
    "sg:address":"Gentseweg 364",
    "sg:city":"Beveren (beveren-waas)",
    "sg:classifiers":[
        {
            "category":"Travel",
            "subcategory":"Hotels & Motels",
            "type":"Entertainment"
        }
    ],
    "sg:phone":"+32 3 775 91 80",
    "sg:postcode":"9120",
    "sg:province":"Oost-Vlaanderen",
    "wof:name":"Alkoof (de)",
    "wof:placetype":"venue"
},
  "geometry": {"coordinates":[4.2185897827,51.1951789856],"type":"Point"}
}