{
  "type": "Feature",
  "properties": {
    "addr:full":"Chauss\u00c9e De Helmet 193 Brussel/bruxelles Bruxelles-Capitale 1030",
    "addr:housenumber":"193",
    "addr:postcode":"1030",
    "addr:street":"Chausse\u0301E De Helmet;/",
    "iso:country":"BE",
    "sg:address":"Chauss\u00c9e De Helmet 193",
    "sg:city":"Brussel/bruxelles",
    "sg:orig_category":"Opticiens. Articles m\u00e9dicaux and orthop\u00e9diques",
    "sg:phone":"+32 2 242 02 26",
    "sg:postcode":"1030",
    "sg:province":"Bruxelles-Capitale",
    "wof:name":"Opticien Degroote",
    "wof:placetype":"venue"
},
  "geometry": {"coordinates":[4.3857350349,50.8725852966],"type":"Point"}
}