{
  "type": "Feature",
  "properties": {
    "addr:full":"Menensesteenweg 290 Wervik West-Vlaanderen 8940",
    "addr:housenumber":"290",
    "addr:postcode":"8940",
    "addr:street":"Menensesteenweg",
    "iso:country":"BE",
    "sg:address":"Menensesteenweg 290",
    "sg:city":"Wervik",
    "sg:classifiers":[
        {
            "category":"Farming",
            "subcategory":"Nursery",
            "type":"Manufacturing & Wholesale Goods"
        }
    ],
    "sg:phone":"+32 56 30 13 11",
    "sg:postcode":"8940",
    "sg:province":"West-Vlaanderen",
    "sg:tags":[
        "growing",
        "flower"
    ],
    "wof:name":"Ghesqui\u00e8re Nv",
    "wof:placetype":"venue"
},
  "geometry": {"coordinates":[3.0869700909,50.7821426392],"type":"Point"}
}