{
  "type": "Feature",
  "properties": {
    "addr:full":"Fort V Straat 52 Edegem Antwerpen 2650",
    "addr:housenumber":"52",
    "addr:postcode":"2650",
    "addr:street":"V Straat",
    "iso:country":"BE",
    "sg:address":"Fort V Straat 52",
    "sg:city":"Edegem",
    "sg:classifiers":[
        {
            "category":"Professional",
            "subcategory":"Detective & Security Services",
            "type":"Services"
        }
    ],
    "sg:phone":"+32 3 440 61 43",
    "sg:postcode":"2650",
    "sg:province":"Antwerpen",
    "sg:tags":[
        "protection",
        "lightning"
    ],
    "wof:name":"D.a.b.i.b. Bvba-sprl",
    "wof:placetype":"venue"
},
  "geometry": {"coordinates":[4.433740139,51.1722488403],"type":"Point"}
}