{
  "type": "Feature",
  "properties": {
    "iso:country":"BE",
    "sg:address":"Rue Isidore Hoton 3",
    "sg:city":"Ath",
    "sg:orig_category":"Artsen and specialisten",
    "sg:phone":"+32 68 28 61 46",
    "sg:postcode":"7800",
    "sg:province":"Hainaut",
    "wof:name":"Joseph Decelle",
    "wof:placetype":"venue"
},
  "geometry": {"coordinates":[3.780823946,50.6326065063],"type":"Point"}
}