{
  "type": "Feature",
  "properties": {
    "addr:full":"Steenweg 3 Pepingen (heikruis) Vlaams-Brabant 1670",
    "addr:housenumber":"3",
    "addr:postcode":"1670",
    "addr:street":"Steenweg",
    "iso:country":"BE",
    "sg:address":"Steenweg 3",
    "sg:city":"Pepingen (heikruis)",
    "sg:classifiers":[
        {
            "category":"Building & Trades",
            "subcategory":"Construction",
            "type":"Services"
        }
    ],
    "sg:phone":"+32 2 396 10 63",
    "sg:postcode":"1670",
    "sg:province":"Vlaams-Brabant",
    "sg:tags":[
        "carpenter"
    ],
    "wof:name":"Leroux W",
    "wof:placetype":"venue"
},
  "geometry": {"coordinates":[4.0769319534,50.717590332],"type":"Point"}
}