{
  "type": "Feature",
  "properties": {
    "iso:country":"BE",
    "sg:address":"Rue De La Corniche 42a",
    "sg:city":"Esneux",
    "sg:classifiers":[
        {
            "category":"Health Services",
            "subcategory":"Health Practitioner",
            "type":"Services"
        }
    ],
    "sg:phone":"+32 4 380 38 87",
    "sg:postcode":"4130",
    "sg:province":"Li\u00e8ge",
    "sg:tags":[
        "therapist",
        "speech"
    ],
    "wof:name":"Schneider A",
    "wof:placetype":"venue"
},
  "geometry": {"coordinates":[5.5662970543,50.5255012512],"type":"Point"}
}