{
  "type": "Feature",
  "properties": {
    "addr:full":"Wiegstraat 26 Antwerpen Antwerpen 2000",
    "addr:housenumber":"26",
    "addr:postcode":"2000",
    "addr:street":"Wiegstraat",
    "iso:country":"BE",
    "sg:address":"Wiegstraat 26",
    "sg:city":"Antwerpen",
    "sg:orig_category":"Kapsalons",
    "sg:phone":"+32 3 231 34 12",
    "sg:postcode":"2000",
    "sg:province":"Antwerpen",
    "wof:name":"Salon Darifa",
    "wof:placetype":"venue"
},
  "geometry": {"coordinates":[4.4042301178,51.2179298401],"type":"Point"}
}