{
  "type": "Feature",
  "properties": {
    "addr:full":"Korte Klarenstraat 1 Antwerpen Antwerpen 2000",
    "addr:housenumber":"1",
    "addr:postcode":"2000",
    "addr:street":"Korte Klarenstraat",
    "iso:country":"BE",
    "sg:address":"Korte Klarenstraat 1",
    "sg:city":"Antwerpen",
    "sg:orig_category":"Effectenmakelaars and vermogensbeheer",
    "sg:phone":"+32 3 233 42 10",
    "sg:postcode":"2000",
    "sg:province":"Antwerpen",
    "wof:name":"Beursfondsen Beheer",
    "wof:placetype":"venue"
},
  "geometry": {"coordinates":[4.4068021774,51.2193641663],"type":"Point"}
}