{
  "type": "Feature",
  "properties": {
    "addr:full":"Rue En Bois 2 Li\u00c8ge Li\u00e8ge 4000",
    "addr:housenumber":"2",
    "addr:postcode":"4000",
    "addr:street":"Rue En Bois",
    "iso:country":"BE",
    "sg:address":"Rue En Bois 2",
    "sg:city":"Li\u00c8ge",
    "sg:orig_category":"Drogisterijen",
    "sg:phone":"+32 4 226 43 59",
    "sg:postcode":"4000",
    "sg:province":"Li\u00e8ge",
    "wof:name":"Lopez",
    "wof:placetype":"venue"
},
  "geometry": {"coordinates":[5.5529670715,50.6467437744],"type":"Point"}
}