{
  "type": "Feature",
  "properties": {
    "addr:full":"Avenue Paul Deschanel 99 Schaarbeek/schaerbeek Bruxelles-Capitale 1030",
    "addr:housenumber":"99",
    "addr:postcode":"1030",
    "addr:street":"Avenue Paul Deschanel",
    "iso:country":"BE",
    "sg:address":"Avenue Paul Deschanel 99",
    "sg:city":"Schaarbeek/schaerbeek",
    "sg:classifiers":[
        {
            "category":"Arena",
            "subcategory":"Sports Club",
            "type":"Entertainment"
        }
    ],
    "sg:phone":"+32 2 215 17 22",
    "sg:postcode":"1030",
    "sg:province":"Bruxelles-Capitale",
    "sg:tags":[
        "de"
    ],
    "wof:name":"R. O.i.a. H.c.",
    "wof:placetype":"venue"
},
  "geometry": {"coordinates":[4.3788380623,50.860080719],"type":"Point"}
}