{
  "type": "Feature",
  "properties": {
    "iso:country":"BE",
    "sg:address":"Clos De Hombiet 1b",
    "sg:city":"Dison (andrimont)",
    "sg:classifiers":[
        {
            "category":"Real Estate",
            "subcategory":"Real Estate Services",
            "type":"Services"
        }
    ],
    "sg:phone":"+32 87 35 22 62",
    "sg:postcode":"4821",
    "sg:province":"Li\u00e8ge",
    "wof:name":"Immo Concept",
    "wof:placetype":"venue"
},
  "geometry": {"coordinates":[5.881280899,50.6143875122],"type":"Point"}
}