{
  "type": "Feature",
  "properties": {
    "iso:country":"BE",
    "sg:address":"15",
    "sg:city":"Nederrij 2200 Herentals",
    "sg:orig_category":"Miscellaneous Products",
    "sg:phone":"+32 14 41 13 47",
    "sg:postcode":"15",
    "wof:name":"Begrafenissen Crematies Marcel Daneels Bvba",
    "wof:placetype":"venue"
},
  "geometry": {"coordinates":[4.8355498314,51.1833343506],"type":"Point"}
}