{
  "type": "Feature",
  "properties": {
    "addr:full":"Baasrodestraat 65 Dendermonde Oost-Vlaanderen 9200",
    "addr:housenumber":"65",
    "addr:postcode":"9200",
    "addr:street":"Baasrodestraat;Oost-Vlaanderen",
    "iso:country":"BE",
    "sg:address":"Baasrodestraat 65",
    "sg:city":"Dendermonde",
    "sg:orig_category":"Boucheries",
    "sg:phone":"+32 52 21 66 61",
    "sg:postcode":"9200",
    "sg:province":"Oost-Vlaanderen",
    "wof:name":"Slagerij Primus",
    "wof:placetype":"venue"
},
  "geometry": {"coordinates":[4.0983099937,51.0315208435],"type":"Point"}
}