{
  "type": "Feature",
  "properties": {
    "iso:country":"BE",
    "sg:address":"Biezekapelstraat 2",
    "sg:city":"Gent",
    "sg:orig_category":"Enseignement maternel and primaire",
    "sg:phone":"+32 9 225 73 92",
    "sg:postcode":"9000",
    "sg:province":"Oost-Vlaanderen",
    "wof:name":"Vrije Basisschool",
    "wof:placetype":"venue"
},
  "geometry": {"coordinates":[3.7265479565,51.0536651611],"type":"Point"}
}