{
  "type": "Feature",
  "properties": {
    "iso:country":"BE",
    "sg:address":"Lage Kaart 451",
    "sg:city":"Brasschaat",
    "sg:classifiers":[
        {
            "category":"Professional",
            "subcategory":"Management & Consulting",
            "type":"Services"
        }
    ],
    "sg:phone":"+32 3 653 42 81",
    "sg:postcode":"2930",
    "sg:province":"Antwerpen",
    "sg:tags":[
        "consultant"
    ],
    "wof:name":"L.m.c",
    "wof:placetype":"venue"
},
  "geometry": {"coordinates":[4.4929599762,51.3081054688],"type":"Point"}
}