{
  "type": "Feature",
  "properties": {
    "addr:full":"Rue De Liege 18 Verviers Li\u00e8ge 4800",
    "addr:housenumber":"18",
    "addr:postcode":"4800",
    "addr:street":"Rue De Liege",
    "iso:country":"BE",
    "sg:address":"Rue De Liege 18",
    "sg:city":"Verviers",
    "sg:classifiers":[
        {
            "category":"Restaurant",
            "type":"Food & Drink"
        }
    ],
    "sg:phone":"+32 87 23 09 04",
    "sg:postcode":"4800",
    "sg:province":"Li\u00e8ge",
    "sg:tags":[
        "hotels",
        "uniform",
        "staff"
    ],
    "wof:name":"Newwork Belgium S.a.",
    "wof:placetype":"venue"
},
  "geometry": {"coordinates":[5.8567199707,50.5868911743],"type":"Point"}
}