{
  "type": "Feature",
  "properties": {
    "addr:full":"Lepelstraat 9 Hooglede West-Vlaanderen 8830",
    "addr:housenumber":"9",
    "addr:postcode":"8830",
    "addr:street":"Lepelstraat",
    "iso:country":"BE",
    "sg:address":"Lepelstraat 9",
    "sg:city":"Hooglede",
    "sg:classifiers":[
        {
            "category":"Restaurant",
            "type":"Food & Drink"
        }
    ],
    "sg:phone":"+32 51 20 61 05",
    "sg:postcode":"8830",
    "sg:province":"West-Vlaanderen",
    "wof:name":"De Zilveren Lepel",
    "wof:placetype":"venue"
},
  "geometry": {"coordinates":[3.091561079,50.985748291],"type":"Point"}
}