{
  "type": "Feature",
  "properties": {
    "addr:full":"Stokstraat 58 Lede Oost-Vlaanderen 9340",
    "addr:housenumber":"58",
    "addr:postcode":"9340",
    "addr:street":"Stokstraat",
    "iso:country":"BE",
    "sg:address":"Stokstraat 58",
    "sg:city":"Lede",
    "sg:orig_category":"Artsen and specialisten",
    "sg:phone":"+32 53 80 59 66",
    "sg:postcode":"9340",
    "sg:province":"Oost-Vlaanderen",
    "wof:name":"Peter Van De Walle",
    "wof:placetype":"venue"
},
  "geometry": {"coordinates":[3.9877738953,50.9732246399],"type":"Point"}
}