{
  "type": "Feature",
  "properties": {
    "iso:country":"BE",
    "sg:address":"Keesdal 25",
    "sg:city":"Asse",
    "sg:classifiers":[
        {
            "category":"Health Services",
            "subcategory":"Doctor",
            "type":"Services"
        }
    ],
    "sg:phone":"+32 2 452 37 24",
    "sg:postcode":"1730",
    "sg:province":"Vlaams-Brabant",
    "sg:tags":[
        "psychotherapist",
        "psychoanalyst"
    ],
    "wof:name":"Meutermans M",
    "wof:placetype":"venue"
},
  "geometry": {"coordinates":[4.2224597931,50.9014129639],"type":"Point"}
}