{
  "type": "Feature",
  "properties": {
    "addr:full":"Rue Des Fileuses 94 Renaix Oost-Vlaanderen 9600",
    "addr:housenumber":"94",
    "addr:postcode":"9600",
    "addr:street":"Rue Des Fileuses",
    "iso:country":"BE",
    "sg:address":"Rue Des Fileuses 94",
    "sg:city":"Renaix",
    "sg:classifiers":[
        {
            "category":"Freight",
            "type":"Transportation"
        }
    ],
    "sg:phone":"+32 55 20 82 30",
    "sg:postcode":"9600",
    "sg:province":"Oost-Vlaanderen",
    "sg:tags":[
        "-",
        "transport"
    ],
    "wof:name":"Dimitris International Transport",
    "wof:placetype":"venue"
},
  "geometry": {"coordinates":[3.5899660587,50.7504920959],"type":"Point"}
}