{
  "type": "Feature",
  "properties": {
    "iso:country":"BE",
    "sg:address":"Olifantstraat 29",
    "sg:city":"Brakel (nederbrakel)",
    "sg:classifiers":[
        {
            "category":"Retail",
            "subcategory":"Auto Repair",
            "type":"Services"
        }
    ],
    "sg:phone":"+32 55 42 71 91",
    "sg:postcode":"9660",
    "sg:province":"Oost-Vlaanderen",
    "sg:tags":[
        "automobile-body"
    ],
    "wof:name":"Vanwinnendaele C",
    "wof:placetype":"venue"
},
  "geometry": {"coordinates":[3.772452116,50.7960968018],"type":"Point"}
}