{
  "type": "Feature",
  "properties": {
    "addr:full":"Hofstraat 39 Retie Antwerpen 2470",
    "addr:housenumber":"39",
    "addr:postcode":"2470",
    "addr:street":"Hofstraat",
    "iso:country":"BE",
    "sg:address":"Hofstraat 39",
    "sg:city":"Retie",
    "sg:classifiers":[
        {
            "category":"Professional",
            "subcategory":"Art Services",
            "type":"Services"
        }
    ],
    "sg:phone":"+32 14 67 81 41",
    "sg:postcode":"2470",
    "sg:province":"Antwerpen",
    "sg:tags":[
        "photography",
        "reporting",
        "-"
    ],
    "wof:name":"De Deken B",
    "wof:placetype":"venue"
},
  "geometry": {"coordinates":[5.0488181114,51.2906837463],"type":"Point"}
}