{
  "type": "Feature",
  "properties": {
    "addr:full":"Laagstraat 32 Ardooie West-Vlaanderen 8851",
    "addr:housenumber":"32",
    "addr:postcode":"8851",
    "addr:street":"Laagstraat",
    "iso:country":"BE",
    "sg:address":"Laagstraat 32",
    "sg:city":"Ardooie",
    "sg:orig_category":"Traitements param\u00e9dicaux",
    "sg:phone":"+32 51 74 48 46",
    "sg:postcode":"8851",
    "sg:province":"West-Vlaanderen",
    "wof:name":"M. Vanhecke",
    "wof:placetype":"venue"
},
  "geometry": {"coordinates":[3.2069370747,51.0078659058],"type":"Point"}
}