{
  "type": "Feature",
  "properties": {
    "addr:full":"Rue Bruy\u00e8re Saint-jean 10 Waterloo Brabant Wallon 1410",
    "addr:housenumber":"10",
    "addr:postcode":"1410",
    "addr:street":"Rue Bruye\u0300Re Saint-Jean",
    "iso:country":"BE",
    "sg:address":"Rue Bruy\u00e8re Saint-jean 10",
    "sg:city":"Waterloo",
    "sg:classifiers":[
        {
            "category":"Professional",
            "subcategory":"Management & Consulting",
            "type":"Services"
        }
    ],
    "sg:phone":"+32 2 351 21 45",
    "sg:postcode":"1410",
    "sg:province":"Brabant Wallon",
    "sg:tags":[
        "-",
        "processing",
        "data",
        "consultant"
    ],
    "wof:name":"All Data Consultants",
    "wof:placetype":"venue"
},
  "geometry": {"coordinates":[4.3822569847,50.7147789001],"type":"Point"}
}