{
  "type": "Feature",
  "properties": {
    "addr:full":"Rue Joseph Stallaert 6 Elsene/ixelles Bruxelles-Capitale 1050",
    "addr:housenumber":"6",
    "addr:postcode":"1050",
    "addr:street":"Rue Joseph Stallaert",
    "iso:country":"BE",
    "sg:address":"Rue Joseph Stallaert 6",
    "sg:city":"Elsene/ixelles",
    "sg:orig_category":"Action sociale avec h\u00e9bergement",
    "sg:phone":"+32 2 344 27 68",
    "sg:postcode":"1050",
    "sg:province":"Bruxelles-Capitale",
    "wof:name":"Centre De Service Social",
    "wof:placetype":"venue"
},
  "geometry": {"coordinates":[4.355284214,50.8166809082],"type":"Point"}
}