{
  "type": "Feature",
  "properties": {
    "iso:country":"BE",
    "sg:address":"Brusselbaan 146",
    "sg:city":"Affligem (hekelgem)",
    "sg:classifiers":[
        {
            "category":"Bakery",
            "type":"Food & Drink"
        }
    ],
    "sg:phone":"+32 53 66 45 44",
    "sg:postcode":"1790",
    "sg:province":"Vlaams-Brabant",
    "sg:tags":[
        "confectioner",
        "baker"
    ],
    "wof:name":"Callebaut D",
    "wof:placetype":"venue"
},
  "geometry": {"coordinates":[4.1102337837,50.9125938416],"type":"Point"}
}