{
  "type": "Feature",
  "properties": {
    "iso:country":"BE",
    "sg:address":"Boulevard Du Souverain 240",
    "sg:city":"Auderghem",
    "sg:orig_category":"Souvenirs and objets artisanaux",
    "sg:phone":"+32 2 660 75 36",
    "sg:postcode":"1160",
    "sg:province":"Bruxelles-Capitale",
    "wof:name":"La Carterie",
    "wof:placetype":"venue"
},
  "geometry": {"coordinates":[4.4257411957,50.8148841858],"type":"Point"}
}