{
  "type": "Feature",
  "properties": {
    "addr:full":"Groenstraat 98a Puurs Antwerpen 2870",
    "addr:housenumber":"98a",
    "addr:postcode":"2870",
    "addr:street":"Groenstraat",
    "iso:country":"BE",
    "sg:address":"Groenstraat 98a",
    "sg:city":"Puurs",
    "sg:classifiers":[
        {
            "category":"Freight",
            "type":"Transportation"
        }
    ],
    "sg:phone":"+32 3 886 42 33",
    "sg:postcode":"2870",
    "sg:province":"Antwerpen",
    "sg:tags":[
        "-",
        "transport"
    ],
    "wof:name":"Maerivoet D",
    "wof:placetype":"venue"
},
  "geometry": {"coordinates":[4.3078532219,51.0526504517],"type":"Point"}
}