{
  "type": "Feature",
  "properties": {
    "iso:country":"BE",
    "sg:address":"La Lienne 3",
    "sg:city":"Stoumont (lorc\u00e9)",
    "sg:classifiers":[
        {
            "category":"Retail",
            "subcategory":"Animal Services",
            "type":"Services"
        }
    ],
    "sg:phone":"+32 80 78 59 77",
    "sg:postcode":"4987",
    "sg:province":"Li\u00e8ge",
    "sg:tags":[
        "farrier"
    ],
    "wof:name":"Moureau E",
    "wof:placetype":"venue"
},
  "geometry": {"coordinates":[5.8098897934,50.4056663513],"type":"Point"}
}