{
  "type": "Feature",
  "properties": {
    "addr:full":"Rue Bois Du Prince 23 Mettet Namur 5640",
    "addr:housenumber":"23",
    "addr:postcode":"5640",
    "addr:street":"Rue Bois Du Prince",
    "iso:country":"BE",
    "sg:address":"Rue Bois Du Prince 23",
    "sg:city":"Mettet",
    "sg:classifiers":[
        {
            "category":"Arena",
            "subcategory":"Sports Club",
            "type":"Entertainment"
        }
    ],
    "sg:phone":"+32 71 72 63 68",
    "sg:postcode":"5640",
    "sg:province":"Namur",
    "sg:tags":[
        "de"
    ],
    "wof:name":"J.c. Djoban",
    "wof:placetype":"venue"
},
  "geometry": {"coordinates":[4.6475372314,50.3418540955],"type":"Point"}
}