{
  "type": "Feature",
  "properties": {
    "addr:full":"Chauss\u00c9e D'enghien 105 Tubeke Brabant Wallon 1480",
    "addr:housenumber":"105",
    "addr:postcode":"1480",
    "addr:street":"Chausse\u0301E D'Enghien;Wallon",
    "iso:country":"BE",
    "sg:address":"Chauss\u00c9e D'enghien 105",
    "sg:city":"Tubeke",
    "sg:orig_category":"Meubles D\u00e9taillants, Am\u00e9nagement de B\u00e2timents et de Cuisines",
    "sg:postcode":"1480",
    "sg:province":"Brabant Wallon",
    "wof:name":"Belgica",
    "wof:placetype":"venue"
},
  "geometry": {"coordinates":[4.1699199677,50.7106285095],"type":"Point"}
}