{
  "type": "Feature",
  "properties": {
    "iso:country":"BE",
    "sg:address":"Steenweg Op Blaasveld 103",
    "sg:city":"Mechelen",
    "sg:orig_category":"Entretien et r\u00e9parations de v\u00e9hicules \u00e0 domicile. Entretien and r\u00e9parations de voitures",
    "sg:phone":"+32 3 886 81 77",
    "sg:postcode":"2801",
    "sg:province":"Antwerpen",
    "wof:name":"V.o.f. Cuypers & Zonen",
    "wof:placetype":"venue"
},
  "geometry": {"coordinates":[4.4020619392,51.0469665527],"type":"Point"}
}