{
  "type": "Feature",
  "properties": {
    "iso:country":"BE",
    "sg:address":"De La Brassinnestraat 5",
    "sg:city":"Riemst",
    "sg:orig_category":"Krantenuitgeverijen Rookartikelen Tijdschriftenuitgeverijen",
    "sg:phone":"+32 12 45 18 38",
    "sg:postcode":"3770",
    "sg:province":"Limburg",
    "wof:name":"Bruninx Elizabeth",
    "wof:placetype":"venue"
},
  "geometry": {"coordinates":[5.5709018707,50.8062362671],"type":"Point"}
}