{
  "type": "Feature",
  "properties": {
    "iso:country":"BE",
    "sg:address":"Sint Kristoffelstraat 39",
    "sg:city":"Londerzeel",
    "sg:classifiers":[
        {
            "category":"Professional",
            "subcategory":"Accounting & Tax Preparation",
            "type":"Services"
        }
    ],
    "sg:phone":"+32 52 31 27 99",
    "sg:postcode":"1840",
    "sg:province":"Vlaams-Brabant",
    "sg:tags":[
        "additive",
        "baking"
    ],
    "wof:name":"Gumpert Et Company S.a.",
    "wof:placetype":"venue"
},
  "geometry": {"coordinates":[4.3083400726,51.0071144104],"type":"Point"}
}