{
  "type": "Feature",
  "properties": {
    "addr:full":"Heidelaan 29 De Haan West-Vlaanderen 8420",
    "addr:housenumber":"29",
    "addr:postcode":"8420",
    "addr:street":"Heidelaan",
    "iso:country":"BE",
    "sg:address":"Heidelaan 29",
    "sg:city":"De Haan",
    "sg:orig_category":"Pain, p\u00e2tisseries and confiseries",
    "sg:phone":"+32 59 23 47 39",
    "sg:postcode":"8420",
    "sg:province":"West-Vlaanderen",
    "wof:name":"Roger Vanmassenhove",
    "wof:placetype":"venue"
},
  "geometry": {"coordinates":[3.0037019253,51.2594833374],"type":"Point"}
}