{
  "type": "Feature",
  "properties": {
    "addr:full":"Rue De Fer 67 Namur Namur 5000",
    "addr:housenumber":"67",
    "addr:postcode":"5000",
    "addr:street":"Rue De Fer",
    "iso:country":"BE",
    "sg:address":"Rue De Fer 67",
    "sg:city":"Namur",
    "sg:orig_category":"Textiles. Eclairage et \u00e9quipements du foyer. Souvenirs and objets artisanaux. Jeux and jouets",
    "sg:phone":"+32 81 22 12 90",
    "sg:postcode":"5000",
    "sg:province":"Namur",
    "wof:name":"Blokker",
    "wof:placetype":"venue"
},
  "geometry": {"coordinates":[4.865196228,50.4662513733],"type":"Point"}
}