{
  "type": "Feature",
  "properties": {
    "iso:country":"BE",
    "sg:address":"Avenue Louis Piedboeuf 12",
    "sg:city":"Chaudfontaine (embourg)",
    "sg:classifiers":[
        {
            "category":"Health Services",
            "subcategory":"Doctor",
            "type":"Services"
        }
    ],
    "sg:phone":"+32 4 365 83 37",
    "sg:postcode":"4053",
    "sg:province":"Li\u00e8ge",
    "sg:tags":[
        "medicinephysicians",
        "surgeon"
    ],
    "wof:name":"Kulbertus Henri",
    "wof:placetype":"venue"
},
  "geometry": {"coordinates":[5.6030311584,50.5883712769],"type":"Point"}
}