{
  "type": "Feature",
  "properties": {
    "addr:full":"Avenue D'auderghem 115-117 Etterbeek/etterbeek Bruxelles-Capitale 1040",
    "addr:postcode":"115-117;1040",
    "addr:street":"Avenue D'Auderghem",
    "iso:country":"BE",
    "sg:address":"Avenue D'auderghem 115-117",
    "sg:city":"Etterbeek/etterbeek",
    "sg:orig_category":"Werk and personeelsselectie",
    "sg:phone":"+32 2 627 29 27",
    "sg:postcode":"1040",
    "sg:province":"Bruxelles-Capitale",
    "wof:name":"Ale Etterbeek",
    "wof:placetype":"venue"
},
  "geometry": {"coordinates":[4.3870258331,50.836139679],"type":"Point"}
}