{
  "type": "Feature",
  "properties": {
    "addr:full":"Emiel Clauslaan 18 Deinze Oost-Vlaanderen 9800",
    "addr:housenumber":"18",
    "addr:postcode":"9800",
    "addr:street":"Emiel Clauslaan",
    "iso:country":"BE",
    "sg:address":"Emiel Clauslaan 18",
    "sg:city":"Deinze",
    "sg:orig_category":"Voertuigen",
    "sg:phone":"+32 9 386 98 48",
    "sg:postcode":"9800",
    "sg:province":"Oost-Vlaanderen",
    "wof:name":"Garage Veldeman",
    "wof:placetype":"venue"
},
  "geometry": {"coordinates":[3.527684927,50.984752655],"type":"Point"}
}