{
  "type": "Feature",
  "properties": {
    "iso:country":"BE",
    "sg:address":"Rue Sambree 30a",
    "sg:city":"Court-saint-etienne",
    "sg:orig_category":"Desk Calendars",
    "sg:phone":"+32 10 62 17 20",
    "sg:postcode":"1490",
    "sg:province":"Brabant Wallon",
    "wof:name":"Cr\u00e9art & Co S.a.",
    "wof:placetype":"venue"
},
  "geometry": {"coordinates":[4.5621547699,50.6400260925],"type":"Point"}
}