{
  "type": "Feature",
  "properties": {
    "iso:country":"BE",
    "sg:address":"Rue De Genleau 70",
    "sg:city":"Lasne",
    "sg:classifiers":[
        {
            "category":"Restaurant",
            "type":"Food & Drink"
        }
    ],
    "sg:phone":"+32 2 633 13 70",
    "sg:postcode":"1380",
    "sg:province":"Brabant Wallon",
    "wof:name":"Le Four \u00c0 Pain",
    "wof:placetype":"venue"
},
  "geometry": {"coordinates":[4.4795041084,50.6847953796],"type":"Point"}
}