{
  "type": "Feature",
  "properties": {
    "addr:full":"Voorheide 54 Arendonk Antwerpen 2370",
    "addr:housenumber":"54",
    "addr:postcode":"2370",
    "addr:street":"Voorheide",
    "iso:country":"BE",
    "sg:address":"Voorheide 54",
    "sg:city":"Arendonk",
    "sg:classifiers":[
        {
            "category":"Building & Trades",
            "subcategory":"Landscaping Services",
            "type":"Services"
        }
    ],
    "sg:phone":"+32 14 67 92 12",
    "sg:postcode":"2370",
    "sg:province":"Antwerpen",
    "sg:tags":[
        "nurseryman"
    ],
    "wof:name":"Van Gorp F Exclusieve Tuinservice",
    "wof:placetype":"venue"
},
  "geometry": {"coordinates":[5.1023058891,51.3376960754],"type":"Point"}
}