{
  "type": "Feature",
  "properties": {
    "iso:country":"BE",
    "sg:address":"Koning Overwinnaarplein 9b13",
    "sg:city":"Etterbeek/etterbeek",
    "sg:orig_category":"Sportclubs",
    "sg:phone":"+32 2 735 28 18",
    "sg:postcode":"1040",
    "sg:province":"Bruxelles-Capitale",
    "wof:name":"R.b.b.c.u.a.a. Etterbeek",
    "wof:placetype":"venue"
},
  "geometry": {"coordinates":[4.3990259171,50.8328094482],"type":"Point"}
}