{
  "type": "Feature",
  "properties": {
    "iso:country":"BE",
    "sg:address":"Kuilenstraat 97",
    "sg:city":"Bree",
    "sg:classifiers":[
        {
            "category":"Autos & Motor Vehicles",
            "subcategory":"Motorcycle Sales",
            "type":"Retail Goods"
        }
    ],
    "sg:phone":"+32 89 46 74 39",
    "sg:postcode":"3960",
    "sg:province":"Limburg",
    "sg:tags":[
        "motorbike"
    ],
    "wof:name":"Horse-power Motorcycle Elektro",
    "wof:placetype":"venue"
},
  "geometry": {"coordinates":[5.6350269318,51.146232605],"type":"Point"}
}