{
  "type": "Feature",
  "properties": {
    "addr:full":"Avenue Brugmann 253 Uccle (bruxelles) Bruxelles-Capitale 1180",
    "addr:housenumber":"253",
    "addr:postcode":"1180",
    "addr:street":"Avenue Brugmann",
    "iso:country":"BE",
    "sg:address":"Avenue Brugmann 253",
    "sg:city":"Uccle (bruxelles)",
    "sg:orig_category":"Jeux and jouets",
    "sg:phone":"+32 2 343 37 00",
    "sg:postcode":"1180",
    "sg:province":"Bruxelles-Capitale",
    "wof:name":"Master Games",
    "wof:placetype":"venue"
},
  "geometry": {"coordinates":[4.3474569321,50.8132171631],"type":"Point"}
}