{
  "type": "Feature",
  "properties": {
    "addr:full":"Leliestraat 23 Ternat Vlaams-Brabant 1742",
    "addr:housenumber":"23",
    "addr:postcode":"1742",
    "addr:street":"Leliestraat",
    "iso:country":"BE",
    "sg:address":"Leliestraat 23",
    "sg:city":"Ternat",
    "sg:orig_category":"Produits surgel\u00e9s Gr",
    "sg:phone":"+32 53 68 07 27",
    "sg:postcode":"1742",
    "sg:province":"Vlaams-Brabant",
    "wof:name":"Diversi Foods",
    "wof:placetype":"venue"
},
  "geometry": {"coordinates":[4.1211957932,50.877243042],"type":"Point"}
}