{
  "type": "Feature",
  "properties": {
    "addr:full":"Place Verte 35 Verviers Li\u00e8ge 4800",
    "addr:housenumber":"35",
    "addr:postcode":"4800",
    "addr:street":"Place Verte",
    "iso:country":"BE",
    "sg:address":"Place Verte 35",
    "sg:city":"Verviers",
    "sg:orig_category":"Pain, p\u00e2tisseries and confiseries",
    "sg:phone":"+32 87 33 33 54",
    "sg:postcode":"4800",
    "sg:province":"Li\u00e8ge",
    "wof:name":"Leonidas",
    "wof:placetype":"venue"
},
  "geometry": {"coordinates":[5.8617758751,50.5923271179],"type":"Point"}
}