{
  "type": "Feature",
  "properties": {
    "addr:full":"Gemeenteplein 2 Knokke-heist West-Vlaanderen 8300",
    "addr:housenumber":"2",
    "addr:postcode":"8300",
    "addr:street":"Gemeenteplein",
    "iso:country":"BE",
    "sg:address":"Gemeenteplein 2",
    "sg:city":"Knokke-heist",
    "sg:orig_category":"E-activit\u00e9s. Entretien and r\u00e9parations de machines de bureau and ordinateurs. Mat\u00e9riel de T\u00e9l\u00e9commun",
    "sg:phone":"+32 50 62 02 03",
    "sg:postcode":"8300",
    "sg:province":"West-Vlaanderen",
    "wof:name":"Peters Computer Services",
    "wof:placetype":"venue"
},
  "geometry": {"coordinates":[3.2893669605,51.3408088684],"type":"Point"}
}