{
  "type": "Feature",
  "properties": {
    "addr:full":"Helenboslaan 53 Aartselaar Antwerpen 2630",
    "addr:housenumber":"53",
    "addr:postcode":"2630",
    "addr:street":"Helenboslaan",
    "iso:country":"BE",
    "sg:address":"Helenboslaan 53",
    "sg:city":"Aartselaar",
    "sg:orig_category":"Artsen and specialisten",
    "sg:phone":"+32 3 887 27 24",
    "sg:postcode":"2630",
    "sg:province":"Antwerpen",
    "wof:name":"Kate Jacobs",
    "wof:placetype":"venue"
},
  "geometry": {"coordinates":[4.386051178,51.1392021179],"type":"Point"}
}