{
  "type": "Feature",
  "properties": {
    "addr:full":"Doornemaatsweg 2 Middelkerke (leffinge) West-Vlaanderen 8432",
    "addr:housenumber":"2",
    "addr:postcode":"8432",
    "addr:street":"Doornemaatsweg",
    "iso:country":"BE",
    "sg:address":"Doornemaatsweg 2",
    "sg:city":"Middelkerke (leffinge)",
    "sg:classifiers":[
        {
            "category":"Banks & Credit Unions",
            "subcategory":"Bureau De Change",
            "type":"Services"
        }
    ],
    "sg:phone":"+32 59 32 14 42",
    "sg:postcode":"8432",
    "sg:province":"West-Vlaanderen",
    "sg:tags":[
        "model",
        "scale",
        "-"
    ],
    "wof:name":"Noordzee Scheepsmodellen",
    "wof:placetype":"venue"
},
  "geometry": {"coordinates":[2.9037380219,51.1788024902],"type":"Point"}
}