{
  "type": "Feature",
  "properties": {
    "iso:country":"BE",
    "sg:address":"Kerkhofstraat 2ba",
    "sg:city":"Lebbeke",
    "sg:orig_category":"M\u00e9decins and sp\u00e9cialistes",
    "sg:phone":"+32 53 77 80 90",
    "sg:postcode":"9280",
    "sg:province":"Oost-Vlaanderen",
    "wof:name":"Marcel Van Mulders",
    "wof:placetype":"venue"
},
  "geometry": {"coordinates":[4.0850949287,50.9792251587],"type":"Point"}
}