{
  "type": "Feature",
  "properties": {
    "addr:full":"Rue Rossini 7 Anderlecht Bruxelles-Capitale 1070",
    "addr:housenumber":"7",
    "addr:postcode":"1070",
    "addr:street":"Rue Rossini",
    "iso:country":"BE",
    "sg:address":"Rue Rossini 7",
    "sg:city":"Anderlecht",
    "sg:orig_category":"Graphologues, astrologues, voyants and radiesth\u00e9sistes",
    "sg:phone":"+32 2 522 52 71",
    "sg:postcode":"1070",
    "sg:province":"Bruxelles-Capitale",
    "wof:name":"Kadere",
    "wof:placetype":"venue"
},
  "geometry": {"coordinates":[4.3302030563,50.838558197],"type":"Point"}
}