{
  "type": "Feature",
  "properties": {
    "iso:country":"BE",
    "sg:address":"Rollegemstraat 111",
    "sg:city":"Ledegem",
    "sg:classifiers":[
        {
            "category":"Sports & Exercise",
            "subcategory":"Gym",
            "type":"Entertainment"
        }
    ],
    "sg:phone":"+32 56 50 98 77",
    "sg:postcode":"8880",
    "sg:province":"West-Vlaanderen",
    "sg:tags":[
        "fitness"
    ],
    "wof:name":"Ampe Luc",
    "wof:placetype":"venue"
},
  "geometry": {"coordinates":[3.1327869892,50.8590507507],"type":"Point"}
}