{
  "type": "Feature",
  "properties": {
    "iso:country":"BE",
    "sg:address":"Rue Joseph Wauters 54",
    "sg:city":"Sambreville",
    "sg:orig_category":"Charpentes and couvertures",
    "sg:phone":"+32 71 77 67 87",
    "sg:postcode":"5060",
    "sg:province":"Namur",
    "wof:name":"Lenoir-burton",
    "wof:placetype":"venue"
},
  "geometry": {"coordinates":[4.6280989647,50.4236221313],"type":"Point"}
}