{
  "type": "Feature",
  "properties": {
    "addr:full":"Rue Du P\u00e9trau 12 Grez-doiceau Brabant Wallon 1390",
    "addr:housenumber":"12",
    "addr:postcode":"1390",
    "addr:street":"Rue Du Pe\u0301Trau",
    "iso:country":"BE",
    "sg:address":"Rue Du P\u00e9trau 12",
    "sg:city":"Grez-doiceau",
    "sg:classifiers":[
        {
            "category":"Professional",
            "subcategory":"Accounting & Tax Preparation",
            "type":"Services"
        }
    ],
    "sg:phone":"+32 10 84 09 44",
    "sg:postcode":"1390",
    "sg:province":"Brabant Wallon",
    "sg:tags":[
        "bookkeeper"
    ],
    "wof:name":"Boutet C",
    "wof:placetype":"venue"
},
  "geometry": {"coordinates":[4.7202148438,50.721950531],"type":"Point"}
}