{
  "type": "Feature",
  "properties": {
    "addr:full":"Chauss\u00e9e De Huy 138 Chaumont-gistoux (dion-valmont) Brabant Wallon 1325",
    "addr:housenumber":"138;1325",
    "addr:street":"Chausse\u0301E De Huy;Chaumont-Gistoux Dion-Valmont Brabant Wallon",
    "iso:country":"BE",
    "sg:address":"Chauss\u00e9e De Huy 138",
    "sg:city":"Chaumont-gistoux (dion-valmont)",
    "sg:classifiers":[
        {
            "category":"Building & Trades",
            "subcategory":"Electrical",
            "type":"Services"
        }
    ],
    "sg:phone":"+32 10 88 09 40",
    "sg:postcode":"1325",
    "sg:province":"Brabant Wallon",
    "sg:tags":[
        "-",
        "electric",
        "contractor"
    ],
    "wof:name":"Hendrickx A",
    "wof:placetype":"venue"
},
  "geometry": {"coordinates":[4.6882600784,50.6891021729],"type":"Point"}
}