{
  "type": "Feature",
  "properties": {
    "addr:full":"Kattestraat 11 Mechelen (hombeek) Antwerpen 2811",
    "addr:housenumber":"11",
    "addr:postcode":"2811",
    "addr:street":"Kattestraat",
    "iso:country":"BE",
    "sg:address":"Kattestraat 11",
    "sg:city":"Mechelen (hombeek)",
    "sg:classifiers":[
        {
            "category":"Building & Trades",
            "subcategory":"Electrical",
            "type":"Services"
        }
    ],
    "sg:phone":"+32 15 43 61 05",
    "sg:postcode":"2811",
    "sg:province":"Antwerpen",
    "sg:tags":[
        "electric",
        "-",
        "housewiring",
        "contractor"
    ],
    "wof:name":"Vgc Elec",
    "wof:placetype":"venue"
},
  "geometry": {"coordinates":[4.431953907,51.0092506409],"type":"Point"}
}