{
  "type": "Feature",
  "properties": {
    "addr:full":"Noordlaan 36 Genk Limburg 3600",
    "addr:housenumber":"36",
    "addr:postcode":"3600",
    "addr:street":"Noordlaan",
    "iso:country":"BE",
    "sg:address":"Noordlaan 36",
    "sg:city":"Genk",
    "sg:classifiers":[
        {
            "category":"Travel",
            "subcategory":"Hotels & Motels",
            "type":"Entertainment"
        }
    ],
    "sg:phone":"+32 89 35 61 80",
    "sg:postcode":"3600",
    "sg:province":"Limburg",
    "wof:name":"De Schacht **",
    "wof:placetype":"venue"
},
  "geometry": {"coordinates":[5.4852190018,50.9782600403],"type":"Point"}
}