{
  "type": "Feature",
  "properties": {
    "iso:country":"BE",
    "sg:address":"Europark 13",
    "sg:city":"Lanaken",
    "sg:classifiers":[
        {
            "category":"Communications",
            "subcategory":"Film & Video Production",
            "type":"Services"
        }
    ],
    "sg:phone":"+32 89 73 09 60",
    "sg:postcode":"3620",
    "sg:province":"Limburg",
    "sg:tags":[
        "equipment",
        "-",
        "sale",
        "supply"
    ],
    "wof:name":"Campipe Technologies Nv",
    "wof:placetype":"venue"
},
  "geometry": {"coordinates":[5.6628251076,50.8838729858],"type":"Point"}
}