{
  "type": "Feature",
  "properties": {
    "iso:country":"BE",
    "sg:address":"Rue Eysden-mines 43ba",
    "sg:city":"Vielsalm",
    "sg:orig_category":"Boomkwekerijen",
    "sg:phone":"+32 80 21 57 93",
    "sg:postcode":"6698",
    "sg:province":"Luxembourg",
    "wof:name":"Bioplant In Vitro",
    "wof:placetype":"venue"
},
  "geometry": {"coordinates":[5.8920779228,50.3258552551],"type":"Point"}
}