{
  "type": "Feature",
  "properties": {
    "addr:full":"Rue Du Grand Enclos 29 Bertrix (orgeo) Luxembourg 6880",
    "addr:housenumber":"29",
    "addr:postcode":"6880",
    "addr:street":"Rue Du Grand Enclos",
    "iso:country":"BE",
    "sg:address":"Rue Du Grand Enclos 29",
    "sg:city":"Bertrix (orgeo)",
    "sg:classifiers":[
        {
            "category":"Farming",
            "subcategory":"Livestock Farm",
            "type":"Manufacturing & Wholesale Goods"
        }
    ],
    "sg:phone":"+32 61 41 51 56",
    "sg:postcode":"6880",
    "sg:province":"Luxembourg",
    "sg:tags":[
        "buyer"
    ],
    "wof:name":"Guissart Fraselle J-l",
    "wof:placetype":"venue"
},
  "geometry": {"coordinates":[5.3400950432,49.8335456848],"type":"Point"}
}