{
  "type": "Feature",
  "properties": {
    "addr:full":"Avenue Du Roi Albert 20 Bruxelles (berchem-sainte-agathe) Bruxelles-Capitale 1082",
    "addr:housenumber":"20",
    "addr:postcode":"1082",
    "addr:street":"Avenue Du Roi Albert",
    "iso:country":"BE",
    "sg:address":"Avenue Du Roi Albert 20",
    "sg:city":"Bruxelles (berchem-sainte-agathe)",
    "sg:classifiers":[
        {
            "category":"Shopping",
            "subcategory":"Jewelry",
            "type":"Retail Goods"
        }
    ],
    "sg:phone":"+32 2 463 14 21",
    "sg:postcode":"1082",
    "sg:province":"Bruxelles-Capitale",
    "sg:tags":[
        "jeweller",
        "-"
    ],
    "wof:name":"Tessie Goudsmid Bvba",
    "wof:placetype":"venue"
},
  "geometry": {"coordinates":[4.2952709198,50.8644142151],"type":"Point"}
}