{
  "type": "Feature",
  "properties": {
    "addr:full":"Langerbruggestraat 59 Gent Oost-Vlaanderen 9000",
    "addr:housenumber":"59",
    "addr:postcode":"9000",
    "addr:street":"Langerbruggestraat;Oost-Vlaanderen",
    "iso:country":"BE",
    "sg:address":"Langerbruggestraat 59",
    "sg:city":"Gent",
    "sg:classifiers":[
        {
            "category":"Wholesale",
            "subcategory":"Wine & Distilled Alcoholic Beverages",
            "type":"Manufacturing & Wholesale Goods"
        }
    ],
    "sg:phone":"+32 9 251 53 20",
    "sg:postcode":"9000",
    "sg:province":"Oost-Vlaanderen",
    "sg:tags":[
        "whol",
        "-",
        "spirit",
        "mfg"
    ],
    "wof:name":"Reintje",
    "wof:placetype":"venue"
},
  "geometry": {"coordinates":[3.7564721107,51.1045532227],"type":"Point"}
}