{
  "type": "Feature",
  "properties": {
    "iso:country":"BE",
    "sg:address":"Berg 38",
    "sg:city":"Retie",
    "sg:orig_category":"Installation de menuiserie m\u00e9tallique",
    "sg:phone":"+32 14 37 03 28",
    "sg:postcode":"2470",
    "sg:province":"Antwerpen",
    "wof:name":"De Bie",
    "wof:placetype":"venue"
},
  "geometry": {"coordinates":[5.0688328743,51.2812767029],"type":"Point"}
}