{
  "type": "Feature",
  "properties": {
    "addr:full":"Zonhoverweg 37 Genk Limburg 3600",
    "addr:housenumber":"37",
    "addr:postcode":"3600",
    "addr:street":"Zonhoverweg",
    "iso:country":"BE",
    "sg:address":"Zonhoverweg 37",
    "sg:city":"Genk",
    "sg:orig_category":"Artsen and specialisten",
    "sg:phone":"+32 89 36 39 39",
    "sg:postcode":"3600",
    "sg:province":"Limburg",
    "wof:name":"Emilienne Ampe",
    "wof:placetype":"venue"
},
  "geometry": {"coordinates":[5.4366779327,50.9786911011],"type":"Point"}
}