{
  "type": "Feature",
  "properties": {
    "iso:country":"BE",
    "sg:address":"Waldreef 2a",
    "sg:city":"Wingene (zwevezele)",
    "sg:classifiers":[
        {
            "category":"Building & Trades",
            "subcategory":"Pest Control",
            "type":"Services"
        }
    ],
    "sg:phone":"+32 51 61 25 12",
    "sg:postcode":"8750",
    "sg:province":"West-Vlaanderen",
    "sg:tags":[
        "painting",
        "contractor"
    ],
    "wof:name":"Verlinde Schilderbedrijf Bvba",
    "wof:placetype":"venue"
},
  "geometry": {"coordinates":[3.2107460499,51.0355453491],"type":"Point"}
}