{
  "type": "Feature",
  "properties": {
    "iso:country":"BE",
    "sg:address":"Azalealaan 1",
    "sg:city":"Sint-niklaas",
    "sg:classifiers":[
        {
            "category":"Health Services",
            "subcategory":"Health Practitioner",
            "type":"Services"
        }
    ],
    "sg:phone":"+32 3 766 41 95",
    "sg:postcode":"9100",
    "sg:province":"Oost-Vlaanderen",
    "sg:tags":[
        "physiotherapist"
    ],
    "wof:name":"Wauters Karl",
    "wof:placetype":"venue"
},
  "geometry": {"coordinates":[4.1535429955,51.1613388062],"type":"Point"}
}