{
  "type": "Feature",
  "properties": {
    "iso:country":"BE",
    "sg:address":"Laarstraat 41",
    "sg:city":"Ranst",
    "sg:orig_category":"Rundveehouders",
    "sg:phone":"+32 3 485 55 93",
    "sg:postcode":"2520",
    "sg:province":"Antwerpen",
    "wof:name":"Marcel De Herdt",
    "wof:placetype":"venue"
},
  "geometry": {"coordinates":[4.5773668289,51.1945343018],"type":"Point"}
}