{
  "type": "Feature",
  "properties": {
    "iso:country":"BE",
    "sg:address":"Noorderlaan 175",
    "sg:city":"Antwerpen",
    "sg:orig_category":"Transports routiers de marchandises",
    "sg:phone":"+32 3 542 48 70",
    "sg:postcode":"2030",
    "sg:province":"Antwerpen",
    "wof:name":"Van Den Bulck",
    "wof:placetype":"venue"
},
  "geometry": {"coordinates":[4.3779430389,51.2707138062],"type":"Point"}
}