{
  "type": "Feature",
  "properties": {
    "addr:full":"Steenkensbeemdstraat 12 Kortessem Limburg 3722",
    "addr:housenumber":"12",
    "addr:postcode":"3722",
    "addr:street":"Steenkensbeemdstraat;Limburg",
    "iso:country":"BE",
    "sg:address":"Steenkensbeemdstraat 12",
    "sg:city":"Kortessem",
    "sg:orig_category":"Transports routiers de marchandises",
    "sg:phone":"+32 11 37 71 61",
    "sg:postcode":"3722",
    "sg:province":"Limburg",
    "wof:name":"Marova",
    "wof:placetype":"venue"
},
  "geometry": {"coordinates":[5.4162697792,50.8503494263],"type":"Point"}
}