{
  "type": "Feature",
  "properties": {
    "addr:full":"Avenue De La Lib\u00c9ration 4 Perwez Brabant Wallon 1360",
    "addr:housenumber":"4",
    "addr:postcode":"1360",
    "addr:street":"Avenue De La Libe\u0301Ration",
    "iso:country":"BE",
    "sg:address":"Avenue De La Lib\u00c9ration 4",
    "sg:city":"Perwez",
    "sg:orig_category":"Installation de menuiserie en bois and plastique",
    "sg:phone":"+32 81 65 61 11",
    "sg:postcode":"1360",
    "sg:province":"Brabant Wallon",
    "wof:name":"Quoidbach",
    "wof:placetype":"venue"
},
  "geometry": {"coordinates":[4.8034639359,50.6220016479],"type":"Point"}
}