{
  "type": "Feature",
  "properties": {
    "addr:full":"Hoogvonderstraat 8 Hasselt Limburg 3500",
    "addr:housenumber":"8",
    "addr:postcode":"3500",
    "addr:street":"Hoogvonderstraat",
    "iso:country":"BE",
    "sg:address":"Hoogvonderstraat 8",
    "sg:city":"Hasselt",
    "sg:orig_category":"Artsen and specialisten",
    "sg:phone":"+32 11 85 13 10",
    "sg:postcode":"3500",
    "sg:province":"Limburg",
    "wof:name":"Andr\u00c9 Brammerloo",
    "wof:placetype":"venue"
},
  "geometry": {"coordinates":[5.329433918,50.9402198792],"type":"Point"}
}