{
  "type": "Feature",
  "properties": {
    "addr:full":"Dorp-west 122 Lochristi Oost-Vlaanderen 9080",
    "addr:housenumber":"122",
    "addr:postcode":"9080",
    "iso:country":"BE",
    "sg:address":"Dorp-west 122",
    "sg:city":"Lochristi",
    "sg:classifiers":[
        {
            "category":"Banks & Credit Unions",
            "subcategory":"Financial Services",
            "type":"Services"
        }
    ],
    "sg:phone":"+32 9 355 63 67",
    "sg:postcode":"9080",
    "sg:province":"Oost-Vlaanderen",
    "sg:tags":[
        "loan",
        "mortgage"
    ],
    "wof:name":"De Koning Verzekeringen Nv",
    "wof:placetype":"venue"
},
  "geometry": {"coordinates":[3.826967001,51.0949211121],"type":"Point"}
}