{
  "type": "Feature",
  "properties": {
    "addr:full":"Hoofstraat 6 Voeren/fourons Limburg 3793",
    "addr:housenumber":"6",
    "addr:postcode":"3793",
    "addr:street":"Hoofstraat",
    "iso:country":"BE",
    "sg:address":"Hoofstraat 6",
    "sg:city":"Voeren/fourons",
    "sg:classifiers":[
        {
            "category":"Travel",
            "subcategory":"Hotels & Motels",
            "type":"Entertainment"
        }
    ],
    "sg:phone":"+32 4 381 10 17",
    "sg:postcode":"3793",
    "sg:province":"Limburg",
    "sg:tags":[
        "organisatie",
        "catering",
        "feesten",
        "van",
        "restaurant"
    ],
    "wof:name":"Hotel Hof De Draeck",
    "wof:placetype":"venue"
},
  "geometry": {"coordinates":[5.8739619255,50.7553100586],"type":"Point"}
}