{
  "type": "Feature",
  "properties": {
    "addr:full":"D'eike 24 Zoersel Antwerpen 2980",
    "addr:housenumber":"24",
    "addr:postcode":"2980",
    "addr:street":"D'Eike",
    "iso:country":"BE",
    "sg:address":"D'eike 24",
    "sg:city":"Zoersel",
    "sg:orig_category":"Travaux de finition and nettoyage de b\u00e2timents. Peinture. Rev\u00eatements pour sols and murs",
    "sg:phone":"+32 3 383 63 10",
    "sg:postcode":"2980",
    "sg:province":"Antwerpen",
    "wof:name":"Eco - Decor",
    "wof:placetype":"venue"
},
  "geometry": {"coordinates":[4.6416621208,51.244178772],"type":"Point"}
}