{
  "type": "Feature",
  "properties": {
    "addr:full":"Stationsstraat 80bb Herselt Antwerpen 2230",
    "addr:housenumber":"80bb",
    "addr:postcode":"2230",
    "addr:street":"Stationsstraat",
    "iso:country":"BE",
    "sg:address":"Stationsstraat 80bb",
    "sg:city":"Herselt",
    "sg:orig_category":"Bijouteries and horlogeries",
    "sg:phone":"+32 16 69 91 00",
    "sg:postcode":"2230",
    "sg:province":"Antwerpen",
    "wof:name":"Daems Juwelen",
    "wof:placetype":"venue"
},
  "geometry": {"coordinates":[4.8235359192,51.0316543579],"type":"Point"}
}