{
  "type": "Feature",
  "properties": {
    "iso:country":"BE",
    "sg:address":"Rue Eug\u00c8ne Dupont 57",
    "sg:city":"Lessines",
    "sg:orig_category":"Pain, p\u00e2tisseries and confiseries",
    "sg:phone":"+32 68 33 22 11",
    "sg:postcode":"7860",
    "sg:province":"Hainaut",
    "wof:name":"Mario Secci",
    "wof:placetype":"venue"
},
  "geometry": {"coordinates":[3.8373980522,50.7085418701],"type":"Point"}
}