{
  "type": "Feature",
  "properties": {
    "addr:full":"Rue De Dave 45 Namur Namur 5100",
    "addr:housenumber":"45",
    "addr:postcode":"5100",
    "addr:street":"Rue De Dave",
    "iso:country":"BE",
    "sg:address":"Rue De Dave 45",
    "sg:city":"Namur",
    "sg:orig_category":"Avocats and conseillers juridiques",
    "sg:phone":"+32 81 30 42 27",
    "sg:postcode":"5100",
    "sg:province":"Namur",
    "wof:name":"Blaise Ghesquiere",
    "wof:placetype":"venue"
},
  "geometry": {"coordinates":[4.8713750839,50.4566345215],"type":"Point"}
}