{
  "type": "Feature",
  "properties": {
    "addr:full":"Dr Charles Leemansstraat 45 Sint-agatha-berchem/berchem-sainte-agathe Bruxelles-Capitale 1082",
    "addr:housenumber":"45",
    "addr:postcode":"1082",
    "addr:street":"Leemansstraat;/",
    "iso:country":"BE",
    "sg:address":"Dr Charles Leemansstraat 45",
    "sg:city":"Sint-agatha-berchem/berchem-sainte-agathe",
    "sg:orig_category":"Herstelling horloges and juwelen",
    "sg:phone":"+32 2 465 53 97",
    "sg:postcode":"1082",
    "sg:province":"Bruxelles-Capitale",
    "wof:name":"Jean-pierre Freese/j.p. Freese",
    "wof:placetype":"venue"
},
  "geometry": {"coordinates":[4.2945518494,50.8625183105],"type":"Point"}
}