{
  "type": "Feature",
  "properties": {
    "iso:country":"BE",
    "sg:address":"Avenue Richard Neybergh 133",
    "sg:city":"Bruxelles",
    "sg:classifiers":[
        {
            "category":"Retail",
            "subcategory":"Laundry & Dry Cleaning",
            "type":"Services"
        }
    ],
    "sg:phone":"+32 2 425 47 35",
    "sg:postcode":"1020",
    "sg:province":"Bruxelles-Capitale",
    "sg:tags":[
        "dyer",
        "cleaner"
    ],
    "wof:name":"Okapi",
    "wof:placetype":"venue"
},
  "geometry": {"coordinates":[4.3435258865,50.8752708435],"type":"Point"}
}