{
  "type": "Feature",
  "properties": {
    "addr:full":"Acacialaan 2 Knokke-heist West-Vlaanderen 8301",
    "addr:housenumber":"2",
    "addr:postcode":"8301",
    "addr:street":"Acacialaan",
    "iso:country":"BE",
    "sg:address":"Acacialaan 2",
    "sg:city":"Knokke-heist",
    "sg:orig_category":"Instellingen voor probleemkinderen Kindertehuizen",
    "sg:phone":"+32 50 60 75 88",
    "sg:postcode":"8301",
    "sg:province":"West-Vlaanderen",
    "wof:name":"Home Kleine Dennen",
    "wof:placetype":"venue"
},
  "geometry": {"coordinates":[3.2704930305,51.3418121338],"type":"Point"}
}