{
  "type": "Feature",
  "properties": {
    "addr:full":"Chauss\u00e9e De Bruxelles 233 Charleroi (lodelinsart) Hainaut 6042",
    "addr:housenumber":"233",
    "addr:postcode":"6042",
    "addr:street":"Chausse\u0301E De Bruxelles",
    "iso:country":"BE",
    "sg:address":"Chauss\u00e9e De Bruxelles 233",
    "sg:city":"Charleroi (lodelinsart)",
    "sg:classifiers":[
        {
            "category":"Manufacturing",
            "subcategory":"Wood Products",
            "type":"Manufacturing & Wholesale Goods"
        }
    ],
    "sg:phone":"+32 71 32 09 09",
    "sg:postcode":"6042",
    "sg:province":"Hainaut",
    "sg:tags":[
        "chip",
        "fiber",
        "board"
    ],
    "wof:name":"M\u00e9tiers Du Bois Sa",
    "wof:placetype":"venue"
},
  "geometry": {"coordinates":[4.4366087914,50.4432258606],"type":"Point"}
}