{
  "type": "Feature",
  "properties": {
    "addr:full":"Warandestraat 10 Nazareth Oost-Vlaanderen 9810",
    "addr:housenumber":"10",
    "addr:postcode":"9810",
    "addr:street":"Warandestraat",
    "iso:country":"BE",
    "sg:address":"Warandestraat 10",
    "sg:city":"Nazareth",
    "sg:classifiers":[
        {
            "category":"Professional",
            "subcategory":"Management & Consulting",
            "type":"Services"
        }
    ],
    "sg:phone":"+32 9 385 71 21",
    "sg:postcode":"9810",
    "sg:province":"Oost-Vlaanderen",
    "sg:tags":[
        "marketing",
        "-",
        "consultant"
    ],
    "wof:name":"A & B Partners Cv",
    "wof:placetype":"venue"
},
  "geometry": {"coordinates":[3.5916481018,50.9552001953],"type":"Point"}
}