{
  "type": "Feature",
  "properties": {
    "iso:country":"BE",
    "sg:address":"Wijnendalestraat 7",
    "sg:city":"Diksmuide",
    "sg:orig_category":"Brood, gebak and snoepgoed",
    "sg:phone":"+32 51 50 16 90",
    "sg:postcode":"8600",
    "sg:province":"West-Vlaanderen",
    "wof:name":"Guy Vanpoucke",
    "wof:placetype":"venue"
},
  "geometry": {"coordinates":[2.901309967,51.060710907],"type":"Point"}
}