{
  "type": "Feature",
  "properties": {
    "addr:full":"Oudburg 1 Gent Oost-Vlaanderen 9000",
    "addr:housenumber":"1",
    "addr:postcode":"9000",
    "addr:street":"Oudburg;Oost-Vlaanderen",
    "iso:country":"BE",
    "sg:address":"Oudburg 1",
    "sg:city":"Gent",
    "sg:orig_category":"Kantoormateriaal Meubelzaken, woning- and keukeninrichting",
    "sg:phone":"+32 9 224 28 86",
    "sg:postcode":"9000",
    "sg:province":"Oost-Vlaanderen",
    "wof:name":"Frank De Clercq",
    "wof:placetype":"venue"
},
  "geometry": {"coordinates":[3.7238070965,51.0578956604],"type":"Point"}
}