{
  "type": "Feature",
  "properties": {
    "iso:country":"BE",
    "sg:address":"Oud-dorpsstraat 61",
    "sg:city":"Wuustwezel",
    "sg:classifiers":[
        {
            "category":"Personal",
            "subcategory":"Beauty Salon",
            "type":"Services"
        }
    ],
    "sg:phone":"+32 3 669 56 76",
    "sg:postcode":"2990",
    "sg:province":"Antwerpen",
    "sg:tags":[
        "de",
        "coiffure"
    ],
    "wof:name":"Haircreations Cindy",
    "wof:placetype":"venue"
},
  "geometry": {"coordinates":[4.5953831673,51.3883323669],"type":"Point"}
}