{
  "type": "Feature",
  "properties": {
    "iso:country":"BE",
    "sg:address":"Boelare 133",
    "sg:city":"Eeklo",
    "sg:orig_category":"Installation de menuiserie en bois and plastique. Installation de serres, double vitrage and fen\u00eatre",
    "sg:phone":"+32 9 377 69 11",
    "sg:postcode":"9900",
    "sg:province":"Oost-Vlaanderen",
    "wof:name":"Wilfried Lippens",
    "wof:placetype":"venue"
},
  "geometry": {"coordinates":[3.5675499439,51.1884117126],"type":"Point"}
}