{
  "type": "Feature",
  "properties": {
    "iso:country":"BE",
    "sg:address":"Guido Gezellelaan 6",
    "sg:city":"Mechelen",
    "sg:classifiers":[
        {
            "category":"Shopping",
            "subcategory":"Clothing, Apparel, & Fashions",
            "type":"Retail Goods"
        }
    ],
    "sg:phone":"+32 15 20 11 58",
    "sg:postcode":"2800",
    "sg:province":"Antwerpen",
    "sg:tags":[
        "clothing",
        "-",
        "gentleman"
    ],
    "wof:name":"Comad (vedea) Men's Fashion",
    "wof:placetype":"venue"
},
  "geometry": {"coordinates":[4.4721550941,51.0322227478],"type":"Point"}
}