{
  "type": "Feature",
  "properties": {
    "iso:country":"BE",
    "sg:address":"Beauduinstraat 151",
    "sg:city":"Tienen",
    "sg:orig_category":"Sportclubs Sportterreinen and installaties behalve sportcentra",
    "sg:phone":"+32 16 81 37 14",
    "sg:postcode":"3300",
    "sg:province":"Vlaams-Brabant",
    "wof:name":"Zwembad Tienen",
    "wof:placetype":"venue"
},
  "geometry": {"coordinates":[4.9456801414,50.8031387329],"type":"Point"}
}