{
  "type": "Feature",
  "properties": {
    "iso:country":"BE",
    "sg:address":"Rue Pisseroule 275-277",
    "sg:city":"Dison",
    "sg:orig_category":"Notaires",
    "sg:phone":"+32 87 33 12 56",
    "sg:postcode":"4820",
    "sg:province":"Li\u00e8ge",
    "wof:name":"Emmanuel Voisin",
    "wof:placetype":"venue"
},
  "geometry": {"coordinates":[5.8531599045,50.598777771],"type":"Point"}
}