{
  "type": "Feature",
  "properties": {
    "addr:full":"Kemphoekstraat 47 Sint-gillis-waas Oost-Vlaanderen 9170",
    "addr:housenumber":"47",
    "addr:postcode":"9170",
    "addr:street":"Kemphoekstraat",
    "iso:country":"BE",
    "sg:address":"Kemphoekstraat 47",
    "sg:city":"Sint-gillis-waas",
    "sg:orig_category":"V\u00e9t\u00e9rinaires",
    "sg:phone":"+32 3 770 51 45",
    "sg:postcode":"9170",
    "sg:province":"Oost-Vlaanderen",
    "wof:name":"F. Vivier",
    "wof:placetype":"venue"
},
  "geometry": {"coordinates":[4.1341600418,51.227809906],"type":"Point"}
}