{
  "type": "Feature",
  "properties": {
    "addr:full":"Slachthuiskaai 8 Hasselt Limburg 3500",
    "addr:housenumber":"8",
    "addr:postcode":"3500",
    "addr:street":"Slachthuiskaai",
    "iso:country":"BE",
    "sg:address":"Slachthuiskaai 8",
    "sg:city":"Hasselt",
    "sg:orig_category":"Epiceries",
    "sg:phone":"+32 11 30 04 10",
    "sg:postcode":"3500",
    "sg:province":"Limburg",
    "wof:name":"Supermarkt",
    "wof:placetype":"venue"
},
  "geometry": {"coordinates":[5.3368849754,50.9340934753],"type":"Point"}
}