{
  "type": "Feature",
  "properties": {
    "addr:full":"Aardenburgkalseide 388b Maldegem Oost-Vlaanderen 9990",
    "addr:housenumber":"388b",
    "addr:postcode":"9990",
    "iso:country":"BE",
    "sg:address":"Aardenburgkalseide 388b",
    "sg:city":"Maldegem",
    "sg:classifiers":[
        {
            "category":"Building & Trades",
            "subcategory":"Landscaping Services",
            "type":"Services"
        }
    ],
    "sg:phone":"+32 50 71 21 87",
    "sg:postcode":"9990",
    "sg:province":"Oost-Vlaanderen",
    "sg:tags":[
        "nurseryman"
    ],
    "wof:name":"Van Hulle C & C",
    "wof:placetype":"venue"
},
  "geometry": {"coordinates":[3.4474360943,51.2391738892],"type":"Point"}
}