{
  "type": "Feature",
  "properties": {
    "addr:full":"Rue Cl\u00c9menceau 193 Colfontaine Hainaut 7340",
    "addr:housenumber":"193",
    "addr:postcode":"7340",
    "addr:street":"Rue Cle\u0301Menceau",
    "iso:country":"BE",
    "sg:address":"Rue Cl\u00c9menceau 193",
    "sg:city":"Colfontaine",
    "sg:classifiers":[
        {
            "category":"Shopping",
            "subcategory":"Clothing, Apparel, & Fashions",
            "type":"Retail Goods"
        }
    ],
    "sg:phone":"+32 65 67 63 25",
    "sg:postcode":"7340",
    "sg:province":"Hainaut",
    "sg:tags":[
        "v\u00eatements",
        "pour",
        "dame"
    ],
    "wof:name":"Au Biau D\u00b4zou",
    "wof:placetype":"venue"
},
  "geometry": {"coordinates":[3.8430950642,50.4104690552],"type":"Point"}
}