{
  "type": "Feature",
  "properties": {
    "addr:full":"Hallesesteenweg 122 Sint-genesius-rode/rhode-saint-genese Vlaams-Brabant 1640",
    "addr:housenumber":"122",
    "addr:postcode":"1640",
    "addr:street":"Hallesesteenweg",
    "iso:country":"BE",
    "sg:address":"Hallesesteenweg 122",
    "sg:city":"Sint-genesius-rode/rhode-saint-genese",
    "sg:orig_category":"Artiesten and kunstenaars",
    "sg:phone":"+32 2 649 26 10",
    "sg:postcode":"1640",
    "sg:province":"Vlaams-Brabant",
    "wof:name":"H. Beaumont",
    "wof:placetype":"venue"
},
  "geometry": {"coordinates":[4.3325328827,50.7380332947],"type":"Point"}
}