{
  "type": "Feature",
  "properties": {
    "iso:country":"BE",
    "sg:address":"Chemin Du Pic De L'esquinterie 15",
    "sg:city":"Ath (meslin - L'ev\u00eaque)",
    "sg:classifiers":[
        {
            "category":"Manufacturing",
            "subcategory":"Furniture",
            "type":"Manufacturing & Wholesale Goods"
        }
    ],
    "sg:phone":"+32 68 55 28 20",
    "sg:postcode":"7822",
    "sg:province":"Hainaut",
    "sg:tags":[
        "made",
        "-",
        "custom"
    ],
    "wof:name":"Pettiaux C",
    "wof:placetype":"venue"
},
  "geometry": {"coordinates":[3.8480899334,50.6549186707],"type":"Point"}
}