{
  "type": "Feature",
  "properties": {
    "addr:full":"Florastraat 77 De Pinte Oost-Vlaanderen 9840",
    "addr:housenumber":"77",
    "addr:postcode":"9840",
    "addr:street":"Florastraat",
    "iso:country":"BE",
    "sg:address":"Florastraat 77",
    "sg:city":"De Pinte",
    "sg:orig_category":"Pi\u00e8ces and accessoires de v\u00e9hicules automobiles Gr",
    "sg:phone":"+32 9 282 59 05",
    "sg:postcode":"9840",
    "sg:province":"Oost-Vlaanderen",
    "wof:name":"British Car Parts",
    "wof:placetype":"venue"
},
  "geometry": {"coordinates":[3.6538100243,50.9984397888],"type":"Point"}
}