{
  "type": "Feature",
  "properties": {
    "addr:full":"Augustijnslei 2 Brasschaat 2130",
    "addr:housenumber":"2",
    "addr:postcode":"2130",
    "addr:street":"Augustijnslei",
    "iso:country":"BE",
    "sg:address":"Augustijnslei 2",
    "sg:city":"Brasschaat",
    "sg:classifiers":[
        {
            "category":"Banks & Credit Unions",
            "subcategory":"Bank",
            "type":"Services"
        }
    ],
    "sg:phone":"+32 3 651 42 01",
    "sg:postcode":"2130",
    "wof:name":"Bank J.van Breda & Co",
    "wof:placetype":"venue"
},
  "geometry": {"coordinates":[151.1344909668,-33.8310546875],"type":"Point"}
}