{
  "type": "Feature",
  "properties": {
    "addr:full":"Rue Des Viaducs 145 Mons Hainaut 7020",
    "addr:housenumber":"145",
    "addr:postcode":"7020",
    "addr:street":"Rue Des Viaducs;Hainaut",
    "iso:country":"BE",
    "sg:address":"Rue Des Viaducs 145",
    "sg:city":"Mons",
    "sg:orig_category":"Herstellingen and onderhoud van auto's Voertuigen",
    "sg:phone":"+32 65 35 14 35",
    "sg:postcode":"7020",
    "sg:province":"Hainaut",
    "wof:name":"Lust Nimy",
    "wof:placetype":"venue"
},
  "geometry": {"coordinates":[3.9553449154,50.4761772156],"type":"Point"}
}