{
  "type": "Feature",
  "properties": {
    "addr:full":"Rue Trou Lina 5 Trooz Li\u00e8ge 4870",
    "addr:housenumber":"5",
    "addr:postcode":"4870",
    "addr:street":"Rue Trou Lina",
    "iso:country":"BE",
    "sg:address":"Rue Trou Lina 5",
    "sg:city":"Trooz",
    "sg:orig_category":"Installatie van houten of kunststof schrijnwerk",
    "sg:phone":"+32 4 351 63 91",
    "sg:postcode":"4870",
    "sg:province":"Li\u00e8ge",
    "wof:name":"Ivan Giovannini",
    "wof:placetype":"venue"
},
  "geometry": {"coordinates":[5.6673841476,50.5772285461],"type":"Point"}
}