{
  "type": "Feature",
  "properties": {
    "iso:country":"BE",
    "sg:address":"Boulevard Du Roi Albert 80",
    "sg:city":"Tournai",
    "sg:orig_category":"Artsen and specialisten",
    "sg:phone":"+32 69 22 40 57",
    "sg:postcode":"7500",
    "sg:province":"Hainaut",
    "wof:name":"Isabelle Schlikker",
    "wof:placetype":"venue"
},
  "geometry": {"coordinates":[3.393640995,50.6007537842],"type":"Point"}
}