{
  "type": "Feature",
  "properties": {
    "addr:full":"Stationsstraat 128 Willebroek Antwerpen 2830",
    "addr:housenumber":"128",
    "addr:postcode":"2830",
    "addr:street":"Stationsstraat",
    "iso:country":"BE",
    "sg:address":"Stationsstraat 128",
    "sg:city":"Willebroek",
    "sg:orig_category":"Werk and personeelsselectie",
    "sg:phone":"+32 3 886 62 55",
    "sg:postcode":"2830",
    "sg:province":"Antwerpen",
    "wof:name":"Vdab",
    "wof:placetype":"venue"
},
  "geometry": {"coordinates":[4.357421875,51.0660171509],"type":"Point"}
}