{
  "type": "Feature",
  "properties": {
    "addr:full":"Rue Vifquin 26 Bruxelles (schaerbeek) Bruxelles-Capitale 1030",
    "addr:housenumber":"26",
    "addr:postcode":"1030",
    "addr:street":"Rue Vifquin",
    "iso:country":"BE",
    "sg:address":"Rue Vifquin 26",
    "sg:city":"Bruxelles (schaerbeek)",
    "sg:orig_category":"Non-Classified Establishments",
    "sg:phone":"+32 2 215 43 12",
    "sg:postcode":"1030",
    "sg:province":"Bruxelles-Capitale",
    "wof:name":"Coulaksizoglou R",
    "wof:placetype":"venue"
},
  "geometry": {"coordinates":[4.3733868599,50.861656189],"type":"Point"}
}