{
  "type": "Feature",
  "properties": {
    "addr:full":"Philip Spetstraat 78 Kapellen Antwerpen 2950",
    "addr:housenumber":"78",
    "addr:postcode":"2950",
    "addr:street":"Spetstraat",
    "iso:country":"BE",
    "sg:address":"Philip Spetstraat 78",
    "sg:city":"Kapellen",
    "sg:orig_category":"Maatschappelijke dienstverlening",
    "sg:phone":"+32 3 665 35 71",
    "sg:postcode":"2950",
    "sg:province":"Antwerpen",
    "wof:name":"Rode Kruis Ekeren",
    "wof:placetype":"venue"
},
  "geometry": {"coordinates":[4.4280819893,51.3210754395],"type":"Point"}
}