{
  "type": "Feature",
  "properties": {
    "iso:country":"BE",
    "sg:address":"Chauss\u00c9e De Namur 22",
    "sg:city":"Sombreffe",
    "sg:orig_category":"Benzinestations and brandstoffen",
    "sg:phone":"+32 71 88 83 41",
    "sg:postcode":"5140",
    "sg:province":"Namur",
    "wof:name":"Josiane Piette",
    "wof:placetype":"venue"
},
  "geometry": {"coordinates":[4.6261200905,50.523601532],"type":"Point"}
}