{
  "type": "Feature",
  "properties": {
    "addr:full":"Route Des Canons 6 Bis Namur Namur 5000",
    "addr:housenumber":"6 bis",
    "addr:postcode":"5000",
    "addr:street":"Route Des Canons",
    "iso:country":"BE",
    "sg:address":"Route Des Canons 6 Bis",
    "sg:city":"Namur",
    "sg:classifiers":[
        {
            "category":"Banks & Credit Unions",
            "subcategory":"Investment Brokerage",
            "type":"Services"
        }
    ],
    "sg:phone":"+32 81 73 88 21",
    "sg:postcode":"5000",
    "sg:province":"Namur",
    "sg:tags":[
        "pension"
    ],
    "wof:name":"Deguelle",
    "wof:placetype":"venue"
},
  "geometry": {"coordinates":[4.8571372032,50.4596366882],"type":"Point"}
}