{
  "type": "Feature",
  "properties": {
    "addr:full":"Rue Eug\u00e8ne De Smet 7 Bruxelles (jette) Bruxelles-Capitale 1090",
    "addr:housenumber":"7",
    "addr:postcode":"1090",
    "addr:street":"Rue Euge\u0300Ne De Smet",
    "iso:country":"BE",
    "sg:address":"Rue Eug\u00e8ne De Smet 7",
    "sg:city":"Bruxelles (jette)",
    "sg:classifiers":[
        {
            "category":"Food & Beverages",
            "subcategory":"Groceries & Convenience Stores",
            "type":"Retail Goods"
        }
    ],
    "sg:phone":"+32 2 478 56 31",
    "sg:postcode":"1090",
    "sg:province":"Bruxelles-Capitale",
    "sg:tags":[
        "grocer"
    ],
    "wof:name":"Bhogal",
    "wof:placetype":"venue"
},
  "geometry": {"coordinates":[4.3183279037,50.885684967],"type":"Point"}
}