{
  "type": "Feature",
  "properties": {
    "iso:country":"BE",
    "sg:address":"Meerseweg 42",
    "sg:city":"Hoogstraten (meer)",
    "sg:classifiers":[
        {
            "category":"Banks & Credit Unions",
            "subcategory":"Investment Brokerage",
            "type":"Services"
        }
    ],
    "sg:phone":"+32 3 315 93 51",
    "sg:postcode":"2321",
    "sg:province":"Antwerpen",
    "sg:tags":[
        "fence"
    ],
    "wof:name":"Segers H",
    "wof:placetype":"venue"
},
  "geometry": {"coordinates":[4.7366099358,51.442325592],"type":"Point"}
}