{
  "type": "Feature",
  "properties": {
    "iso:country":"BE",
    "sg:address":"Kapelstraat 88",
    "sg:city":"Temse (steendorp)",
    "sg:classifiers":[
        {
            "category":"Bakery",
            "type":"Food & Drink"
        }
    ],
    "sg:phone":"+32 3 774 10 85",
    "sg:postcode":"9140",
    "sg:province":"Oost-Vlaanderen",
    "sg:tags":[
        "confectioner",
        "baker"
    ],
    "wof:name":"Nielandt",
    "wof:placetype":"venue"
},
  "geometry": {"coordinates":[4.2477002144,51.1289482117],"type":"Point"}
}