{
  "type": "Feature",
  "properties": {
    "addr:full":"Boulevard G\u00e9n\u00e9ral Jacques 138-140 Bruxelles (ixelles) Bruxelles-Capitale 1050",
    "addr:postcode":"138-140;1050",
    "addr:street":"Boulevard Ge\u0301Ne\u0301Ral Jacques",
    "iso:country":"BE",
    "sg:address":"Boulevard G\u00e9n\u00e9ral Jacques 138-140",
    "sg:city":"Bruxelles (ixelles)",
    "sg:classifiers":[
        {
            "category":"Professional",
            "subcategory":"Testing Lab",
            "type":"Services"
        }
    ],
    "sg:phone":"+32 2 647 80 05",
    "sg:postcode":"1050",
    "sg:province":"Bruxelles-Capitale",
    "sg:tags":[
        "laboratory",
        "medical"
    ],
    "wof:name":"Laboratoires De Biologie M\u00e9dicale V.r.",
    "wof:placetype":"venue"
},
  "geometry": {"coordinates":[4.3830709457,50.8201980591],"type":"Point"}
}