{
  "type": "Feature",
  "properties": {
    "addr:full":"Chauss\u00c9e De Ch\u00c2telet 174 Charleroi Hainaut 6060",
    "addr:housenumber":"174",
    "addr:postcode":"6060",
    "addr:street":"Chausse\u0301E De Cha\u0302Telet;Hainaut",
    "iso:country":"BE",
    "sg:address":"Chauss\u00c9e De Ch\u00c2telet 174",
    "sg:city":"Charleroi",
    "sg:orig_category":"Location d'appareils audio-visuels",
    "sg:phone":"+32 71 42 32 03",
    "sg:postcode":"6060",
    "sg:province":"Hainaut",
    "wof:name":"P.s.b. Sonorisation",
    "wof:placetype":"venue"
},
  "geometry": {"coordinates":[4.4880981445,50.4251937866],"type":"Point"}
}