{
  "type": "Feature",
  "properties": {
    "addr:full":"Rue Colonel Bourg 133 Bruxelles Bruxelles-Capitale 1140",
    "addr:housenumber":"133",
    "addr:postcode":"1140",
    "addr:street":"Rue Colonel Bourg",
    "iso:country":"BE",
    "sg:address":"Rue Colonel Bourg 133",
    "sg:city":"Bruxelles",
    "sg:orig_category":"Non-Classified Establishments",
    "sg:phone":"+32 2 730 44 11",
    "sg:postcode":"1140",
    "sg:province":"Bruxelles-Capitale",
    "wof:name":"R\u00e9gie M\u00e9dia Belge -rmb S.a.",
    "wof:placetype":"venue"
},
  "geometry": {"coordinates":[4.4179167747,50.8557510376],"type":"Point"}
}