{
  "type": "Feature",
  "properties": {
    "iso:country":"BE",
    "sg:address":"Binderveldseweg 8",
    "sg:city":"Sint-truiden (runkelen)",
    "sg:classifiers":[
        {
            "category":"Farming",
            "subcategory":"Farm & Veterinary Services",
            "type":"Manufacturing & Wholesale Goods"
        }
    ],
    "sg:phone":"+32 11 68 25 24",
    "sg:postcode":"3803",
    "sg:province":"Limburg",
    "sg:tags":[
        "agricultural",
        "contractor"
    ],
    "wof:name":"Goffard Gebr",
    "wof:placetype":"venue"
},
  "geometry": {"coordinates":[5.14351511,50.8200912476],"type":"Point"}
}