{
  "type": "Feature",
  "properties": {
    "addr:full":"Busch 2 Lontzen Li\u00e8ge 4710",
    "addr:housenumber":"2",
    "addr:postcode":"4710",
    "addr:street":"Busch",
    "iso:country":"BE",
    "sg:address":"Busch 2",
    "sg:city":"Lontzen",
    "sg:classifiers":[
        {
            "category":"Food & Beverages",
            "subcategory":"Fruits & Vegetables",
            "type":"Retail Goods"
        }
    ],
    "sg:phone":"+32 87 65 98 21",
    "sg:postcode":"4710",
    "sg:province":"Li\u00e8ge",
    "sg:tags":[
        "-",
        "shirt"
    ],
    "wof:name":"Maroja Sprl",
    "wof:placetype":"venue"
},
  "geometry": {"coordinates":[5.9977998734,50.6814193726],"type":"Point"}
}