{
  "type": "Feature",
  "properties": {
    "iso:country":"BE",
    "sg:address":"Rue De Haut-ittre 29",
    "sg:city":"Ittre",
    "sg:orig_category":"Assistances juridiques",
    "sg:phone":"+32 67 21 03 67",
    "sg:postcode":"1460",
    "sg:province":"Brabant Wallon",
    "wof:name":"D.y.g. Services",
    "wof:placetype":"venue"
},
  "geometry": {"coordinates":[4.2821512222,50.6548500061],"type":"Point"}
}