{
  "type": "Feature",
  "properties": {
    "iso:country":"BE",
    "sg:address":"Rue De Houssoi 302",
    "sg:city":"Andenne",
    "sg:orig_category":"Eleveurs de bovins",
    "sg:phone":"+32 81 58 87 56",
    "sg:postcode":"5300",
    "sg:province":"Namur",
    "wof:name":"Michel Baseil",
    "wof:placetype":"venue"
},
  "geometry": {"coordinates":[5.0982642174,50.4863739014],"type":"Point"}
}