{
  "type": "Feature",
  "properties": {
    "addr:full":"Oudenaardsesteenweg 847 Erpe-mere (erpe) Oost-Vlaanderen 9420",
    "addr:housenumber":"847",
    "addr:postcode":"9420",
    "addr:street":"Oudenaardsesteenweg",
    "iso:country":"BE",
    "sg:address":"Oudenaardsesteenweg 847",
    "sg:city":"Erpe-mere (erpe)",
    "sg:classifiers":[
        {
            "category":"Bars & Pubs",
            "type":"Food & Drink"
        }
    ],
    "sg:phone":"+32 53 62 17 01",
    "sg:postcode":"9420",
    "sg:province":"Oost-Vlaanderen",
    "wof:name":"Per Tutti Swingcafe",
    "wof:placetype":"venue"
},
  "geometry": {"coordinates":[3.9178359509,50.9123916626],"type":"Point"}
}