{
  "type": "Feature",
  "properties": {
    "addr:full":"Overheulestraat 235 Wevelgem West-Vlaanderen 8560",
    "addr:housenumber":"235",
    "addr:postcode":"8560",
    "addr:street":"Overheulestraat",
    "iso:country":"BE",
    "sg:address":"Overheulestraat 235",
    "sg:city":"Wevelgem",
    "sg:orig_category":"Ruimtes voor conferenties, recepties and feesten Sportterreinen and installaties behalve sportcentra",
    "sg:phone":"+32 56 50 34 09",
    "sg:postcode":"8560",
    "sg:province":"West-Vlaanderen",
    "wof:name":"R.c. Zilveren Spoor",
    "wof:placetype":"venue"
},
  "geometry": {"coordinates":[3.1587159634,50.8502197266],"type":"Point"}
}