{
  "type": "Feature",
  "properties": {
    "iso:country":"BE",
    "sg:address":"Smisseweg 20",
    "sg:city":"Ruiselede",
    "sg:orig_category":"Boucheries",
    "sg:phone":"+32 51 68 87 61",
    "sg:postcode":"8755",
    "sg:province":"West-Vlaanderen",
    "wof:name":"Van Wontergem",
    "wof:placetype":"venue"
},
  "geometry": {"coordinates":[3.3603820801,51.0571136475],"type":"Point"}
}