{
  "type": "Feature",
  "properties": {
    "iso:country":"BE",
    "sg:address":"Honsfeld 42",
    "sg:city":"B\u00dcllingen/bullange",
    "sg:orig_category":"Eleveurs de bovins",
    "sg:phone":"+32 80 64 24 51",
    "sg:postcode":"4760",
    "sg:province":"Li\u00e8ge",
    "wof:name":"Arnold Gruen",
    "wof:placetype":"venue"
},
  "geometry": {"coordinates":[6.2823548317,50.3811187744],"type":"Point"}
}