{
  "type": "Feature",
  "properties": {
    "addr:full":"Hondsklinkstraat 2 Ardooie West-Vlaanderen 8851",
    "addr:housenumber":"2",
    "addr:postcode":"8851",
    "addr:street":"Hondsklinkstraat",
    "iso:country":"BE",
    "sg:address":"Hondsklinkstraat 2",
    "sg:city":"Ardooie",
    "sg:orig_category":"Producteurs de fruits. Producteurs de l\u00e9gumes",
    "sg:phone":"+32 51 74 51 47",
    "sg:postcode":"8851",
    "sg:province":"West-Vlaanderen",
    "wof:name":"Wilfried Cortvriendt",
    "wof:placetype":"venue"
},
  "geometry": {"coordinates":[3.1815030575,51.0094337463],"type":"Point"}
}