{
  "type": "Feature",
  "properties": {
    "iso:country":"BE",
    "sg:address":"Rue De Courtrai 50",
    "sg:city":"Tournai",
    "sg:classifiers":[
        {
            "category":"Home & Garden",
            "subcategory":"Home Furnishings",
            "type":"Retail Goods"
        }
    ],
    "sg:phone":"+32 69 84 42 02",
    "sg:postcode":"7500",
    "sg:province":"Hainaut",
    "sg:tags":[
        "interior",
        "decoration"
    ],
    "wof:name":"H.l.b. D\u00e9cor Sa",
    "wof:placetype":"venue"
},
  "geometry": {"coordinates":[3.3881800175,50.6079101562],"type":"Point"}
}