{
  "type": "Feature",
  "properties": {
    "iso:country":"BE",
    "sg:address":"Rue Du T\u00e9nimont 10",
    "sg:city":"Durbuy (barvaux-sur-ourthe)",
    "sg:classifiers":[
        {
            "category":"Health Services",
            "subcategory":"Doctor",
            "type":"Services"
        }
    ],
    "sg:phone":"+32 86 21 25 21",
    "sg:postcode":"6940",
    "sg:province":"Luxembourg",
    "sg:tags":[
        "medicinephysicians",
        "surgeon"
    ],
    "wof:name":"Banneux Catherine",
    "wof:placetype":"venue"
},
  "geometry": {"coordinates":[5.4973278046,50.3495330811],"type":"Point"}
}