{
  "type": "Feature",
  "properties": {
    "iso:country":"BE",
    "sg:address":"Bistweg 35",
    "sg:city":"Ranst",
    "sg:orig_category":"Producteurs de l\u00e9gumes",
    "sg:phone":"+32 3 475 16 08",
    "sg:postcode":"2520",
    "sg:province":"Antwerpen",
    "wof:name":"Luc Moortgat",
    "wof:placetype":"venue"
},
  "geometry": {"coordinates":[4.6145019531,51.1881370544],"type":"Point"}
}