{
  "type": "Feature",
  "properties": {
    "addr:full":"Weverijstraat 57 Aalst Oost-Vlaanderen 9300",
    "addr:housenumber":"57",
    "addr:postcode":"9300",
    "addr:street":"Weverijstraat",
    "iso:country":"BE",
    "sg:address":"Weverijstraat 57",
    "sg:city":"Aalst",
    "sg:classifiers":[
        {
            "category":"Professional",
            "subcategory":"Accounting & Tax Preparation",
            "type":"Services"
        }
    ],
    "sg:phone":"+32 53 75 05 96",
    "sg:postcode":"9300",
    "sg:province":"Oost-Vlaanderen",
    "sg:tags":[
        "bookkeeper"
    ],
    "wof:name":"De Bie Guy & Co Com V",
    "wof:placetype":"venue"
},
  "geometry": {"coordinates":[4.0438890457,50.9484977722],"type":"Point"}
}