{
  "type": "Feature",
  "properties": {
    "iso:country":"BE",
    "sg:address":"Route De Givet 24",
    "sg:city":"Somme-leuze",
    "sg:classifiers":[
        {
            "category":"Fast Food",
            "type":"Food & Drink"
        }
    ],
    "sg:phone":"+32 86 32 28 12",
    "sg:postcode":"5377",
    "sg:province":"Namur",
    "sg:tags":[
        "\u00c0",
        "restaurants",
        "emporter",
        "restaurant"
    ],
    "wof:name":"Le Pr\u00c9 Mondain",
    "wof:placetype":"venue"
},
  "geometry": {"coordinates":[5.2975478172,50.2971954346],"type":"Point"}
}