{
  "type": "Feature",
  "properties": {
    "addr:full":"Route De Luxembourg 300 Arlon Luxembourg 6700",
    "addr:housenumber":"300",
    "addr:postcode":"6700",
    "addr:street":"Route De Luxembourg",
    "iso:country":"BE",
    "sg:address":"Route De Luxembourg 300",
    "sg:city":"Arlon",
    "sg:orig_category":"Bouwmaterialen Gh",
    "sg:phone":"+32 63 24 69 90",
    "sg:postcode":"6700",
    "sg:province":"Luxembourg",
    "wof:name":"Van Marcke",
    "wof:placetype":"venue"
},
  "geometry": {"coordinates":[5.8251018524,49.6736488342],"type":"Point"}
}