{
  "type": "Feature",
  "properties": {
    "iso:country":"BE",
    "sg:address":"Zandstraat 27b",
    "sg:city":"Heist-op-den-berg (schriek)",
    "sg:classifiers":[
        {
            "category":"Personal",
            "subcategory":"Sauna",
            "type":"Services"
        }
    ],
    "sg:phone":"+32 15 23 62 00",
    "sg:postcode":"2223",
    "sg:province":"Antwerpen",
    "wof:name":"Helios",
    "wof:placetype":"venue"
},
  "geometry": {"coordinates":[4.715171814,51.0149116516],"type":"Point"}
}