{
  "type": "Feature",
  "properties": {
    "addr:full":"H. Wammesstraat 5 Maaseik Limburg 3680",
    "addr:housenumber":"5",
    "addr:postcode":"3680",
    "addr:street":"Wammesstraat",
    "iso:country":"BE",
    "sg:address":"H. Wammesstraat 5",
    "sg:city":"Maaseik",
    "sg:classifiers":[
        {
            "category":"Retail",
            "subcategory":"Veterinary Services",
            "type":"Services"
        }
    ],
    "sg:phone":"+32 89 56 61 49",
    "sg:postcode":"3680",
    "sg:province":"Limburg",
    "sg:tags":[
        "veterinarian"
    ],
    "wof:name":"Delrue B",
    "wof:placetype":"venue"
},
  "geometry": {"coordinates":[5.781897068,51.0940551758],"type":"Point"}
}