{
  "type": "Feature",
  "properties": {
    "addr:full":"Tiensesteenweg 113 Bierbeek (korbeek-lo) Vlaams-Brabant 3360",
    "addr:housenumber":"113",
    "addr:postcode":"3360",
    "addr:street":"Tiensesteenweg",
    "iso:country":"BE",
    "sg:address":"Tiensesteenweg 113",
    "sg:city":"Bierbeek (korbeek-lo)",
    "sg:classifiers":[
        {
            "category":"Health Services",
            "subcategory":"Health Practitioner",
            "type":"Services"
        }
    ],
    "sg:phone":"+32 16 46 18 96",
    "sg:postcode":"3360",
    "sg:province":"Vlaams-Brabant",
    "sg:tags":[
        "physiotherapist"
    ],
    "wof:name":"Van Bogaert L",
    "wof:placetype":"venue"
},
  "geometry": {"coordinates":[4.7623529434,50.8626861572],"type":"Point"}
}