{
  "type": "Feature",
  "properties": {
    "addr:full":"Chauss\u00e9e De Haecht 6 Bruxelles (saint-josse-ten-noode) Bruxelles-Capitale 1210",
    "addr:housenumber":"6",
    "addr:postcode":"1210",
    "addr:street":"Chausse\u0301E De Haecht",
    "iso:country":"BE",
    "sg:address":"Chauss\u00e9e De Haecht 6",
    "sg:city":"Bruxelles (saint-josse-ten-noode)",
    "sg:classifiers":[
        {
            "category":"Personal",
            "subcategory":"Beauty Salon",
            "type":"Services"
        }
    ],
    "sg:phone":"+32 2 218 22 30",
    "sg:postcode":"1210",
    "sg:province":"Bruxelles-Capitale",
    "sg:tags":[
        "lady",
        "-",
        "hairdressing"
    ],
    "wof:name":"Internationale (coiffure) Canan",
    "wof:placetype":"venue"
},
  "geometry": {"coordinates":[4.3666238785,50.854637146],"type":"Point"}
}