{
  "type": "Feature",
  "properties": {
    "addr:full":"1201 Waterloosesteenweg 1180 Ukkel 1201",
    "addr:housenumber":"1201;1180",
    "addr:postcode":"1201",
    "addr:street":"Waterloosesteenweg",
    "iso:country":"BE",
    "sg:address":"1201",
    "sg:city":"Waterloosesteenweg 1180 Ukkel",
    "sg:classifiers":[
        {
            "category":"Bakery",
            "type":"Food & Drink"
        }
    ],
    "sg:phone":"+32 2 374 51 96",
    "sg:postcode":"1201",
    "sg:tags":[
        "cake",
        "product",
        "related",
        "bread"
    ],
    "wof:name":"Renders Nv",
    "wof:placetype":"venue"
},
  "geometry": {"coordinates":[4.3678050041,50.8136901855],"type":"Point"}
}