{
  "type": "Feature",
  "properties": {
    "addr:full":"Baverikstraat 26 Waasmunster Oost-Vlaanderen 9250",
    "addr:housenumber":"26",
    "addr:postcode":"9250",
    "addr:street":"Baverikstraat",
    "iso:country":"BE",
    "sg:address":"Baverikstraat 26",
    "sg:city":"Waasmunster",
    "sg:classifiers":[
        {
            "category":"Professional",
            "subcategory":"Business Services",
            "type":"Services"
        }
    ],
    "sg:phone":"+32 3 772 14 29",
    "sg:postcode":"9250",
    "sg:province":"Oost-Vlaanderen",
    "sg:tags":[
        "bookkeeping"
    ],
    "wof:name":"Vincere Adviesgroep Bvba",
    "wof:placetype":"venue"
},
  "geometry": {"coordinates":[4.0646100044,51.1325683594],"type":"Point"}
}