{
  "type": "Feature",
  "properties": {
    "addr:full":"Leopold I-straat 464 Jette Bruxelles-Capitale 1090",
    "addr:housenumber":"464",
    "addr:postcode":"1090",
    "addr:street":"Leopold I-Straat",
    "iso:country":"BE",
    "sg:address":"Leopold I-straat 464",
    "sg:city":"Jette",
    "sg:orig_category":"Tijdelijke werkgelegenheid and uitzendkantoren Vedior",
    "sg:phone":"+32 2 421 76 10",
    "sg:postcode":"1090",
    "sg:province":"Bruxelles-Capitale",
    "wof:name":"Vedior Interim",
    "wof:placetype":"venue"
},
  "geometry": {"coordinates":[4.3268098831,50.8728256226],"type":"Point"}
}