{
  "type": "Feature",
  "properties": {
    "addr:full":"Chemin Du Champs De Mars 49 Mons Hainaut 7000",
    "addr:housenumber":"49",
    "addr:postcode":"7000",
    "addr:street":"Chemin Du Champs De Mars;Hainaut",
    "iso:country":"BE",
    "sg:address":"Chemin Du Champs De Mars 49",
    "sg:city":"Mons",
    "sg:classifiers":[
        {
            "category":"Professional",
            "subcategory":"Art Services",
            "type":"Services"
        }
    ],
    "sg:phone":"+32 65 84 33 70",
    "sg:postcode":"7000",
    "sg:province":"Hainaut",
    "sg:tags":[
        "technical",
        "photographer",
        "industrial",
        "-"
    ],
    "wof:name":"Dakota Sprl",
    "wof:placetype":"venue"
},
  "geometry": {"coordinates":[3.9543960094,50.4646682739],"type":"Point"}
}