{
  "type": "Feature",
  "properties": {
    "iso:country":"BE",
    "sg:address":"Petit Marais 1",
    "sg:city":"Celles",
    "sg:orig_category":"Sportclubs",
    "sg:phone":"+32 69 45 60 68",
    "sg:postcode":"7760",
    "sg:province":"Hainaut",
    "wof:name":"Pigeon De L'escaut",
    "wof:placetype":"venue"
},
  "geometry": {"coordinates":[3.4096260071,50.734413147],"type":"Point"}
}