{
  "type": "Feature",
  "properties": {
    "addr:full":"Processiestraat 22 Opwijk Vlaams-Brabant 1745",
    "addr:housenumber":"22",
    "addr:postcode":"1745",
    "addr:street":"Processiestraat",
    "iso:country":"BE",
    "sg:address":"Processiestraat 22",
    "sg:city":"Opwijk",
    "sg:classifiers":[
        {
            "category":"Government",
            "subcategory":"Police Station",
            "type":"Public Place"
        }
    ],
    "sg:phone":"+32 52 35 50 02",
    "sg:postcode":"1745",
    "sg:province":"Vlaams-Brabant",
    "sg:tags":[
        "gendarmerie"
    ],
    "wof:name":"Federale Politie",
    "wof:placetype":"venue"
},
  "geometry": {"coordinates":[4.1865730286,50.970161438],"type":"Point"}
}