{
  "type": "Feature",
  "properties": {
    "addr:full":"Rue Des Ardennes 2a Saint-hubert Luxembourg 6870",
    "addr:housenumber":"2a",
    "addr:postcode":"6870",
    "addr:street":"Rue Des Ardennes",
    "iso:country":"BE",
    "sg:address":"Rue Des Ardennes 2a",
    "sg:city":"Saint-hubert",
    "sg:classifiers":[
        {
            "category":"Social Services",
            "subcategory":"Job Training",
            "type":"Services"
        }
    ],
    "sg:phone":"+32 61 61 30 31",
    "sg:postcode":"6870",
    "sg:province":"Luxembourg",
    "sg:tags":[
        "de",
        "terrain",
        "camping"
    ],
    "wof:name":"Camping La Vall\u00c9e De Naredet",
    "wof:placetype":"venue"
},
  "geometry": {"coordinates":[5.2938699722,50.0199012756],"type":"Point"}
}