{
  "type": "Feature",
  "properties": {
    "addr:full":"Hoevenstraat 45 Wommelgem Antwerpen 2160",
    "addr:housenumber":"45",
    "addr:postcode":"2160",
    "addr:street":"Hoevenstraat",
    "iso:country":"BE",
    "sg:address":"Hoevenstraat 45",
    "sg:city":"Wommelgem",
    "sg:classifiers":[
        {
            "category":"Communications",
            "subcategory":"Film & Video Production",
            "type":"Services"
        }
    ],
    "sg:phone":"+32 3 353 26 36",
    "sg:postcode":"2160",
    "sg:province":"Antwerpen",
    "sg:tags":[
        "material",
        "audio-visual"
    ],
    "wof:name":"Mitra-home Theaters",
    "wof:placetype":"venue"
},
  "geometry": {"coordinates":[4.516602993,51.2042694092],"type":"Point"}
}