{
  "type": "Feature",
  "properties": {
    "iso:country":"BE",
    "sg:address":"Vierbunderweg 9",
    "sg:city":"Geraardsbergen (onkerzele)",
    "sg:classifiers":[
        {
            "category":"Health Services",
            "subcategory":"Doctor",
            "type":"Services"
        }
    ],
    "sg:phone":"+32 54 41 58 48",
    "sg:postcode":"9500",
    "sg:province":"Oost-Vlaanderen",
    "sg:tags":[
        "medicinephysicians",
        "surgeon"
    ],
    "wof:name":"D'herde D",
    "wof:placetype":"venue"
},
  "geometry": {"coordinates":[3.891012907,50.765663147],"type":"Point"}
}