{
  "type": "Feature",
  "properties": {
    "addr:full":"Blauwesteenstraat 16a Heusden-zolder Oost-Vlaanderen 9070",
    "addr:housenumber":"16a",
    "addr:postcode":"9070",
    "addr:street":"Blauwesteenstraat",
    "iso:country":"BE",
    "sg:address":"Blauwesteenstraat 16a",
    "sg:city":"Heusden-zolder",
    "sg:orig_category":"Architectes",
    "sg:phone":"+32 9 239 93 12",
    "sg:postcode":"9070",
    "sg:province":"Oost-Vlaanderen",
    "wof:name":"Verplanken Frank",
    "wof:placetype":"venue"
},
  "geometry": {"coordinates":[3.7968919277,51.0559501648],"type":"Point"}
}