{
  "type": "Feature",
  "properties": {
    "addr:full":"Nieuwstraat 22 Zonnebeke (beselare) West-Vlaanderen 8980",
    "addr:housenumber":"22",
    "addr:postcode":"8980",
    "addr:street":"Nieuwstraat",
    "iso:country":"BE",
    "sg:address":"Nieuwstraat 22",
    "sg:city":"Zonnebeke (beselare)",
    "sg:classifiers":[
        {
            "category":"Food & Beverages",
            "subcategory":"Supermarket",
            "type":"Retail Goods"
        }
    ],
    "sg:phone":"+32 57 46 62 84",
    "sg:postcode":"8980",
    "sg:province":"West-Vlaanderen",
    "sg:tags":[
        "department",
        "store"
    ],
    "wof:name":"Bij Mariette Bvba",
    "wof:placetype":"venue"
},
  "geometry": {"coordinates":[3.0249168873,50.8503265381],"type":"Point"}
}