{
  "type": "Feature",
  "properties": {
    "iso:country":"BE",
    "sg:address":"Daalstraat 39",
    "sg:city":"Grimbergen",
    "sg:orig_category":"Tuinen",
    "sg:phone":"+32 2 269 22 98",
    "sg:postcode":"1852",
    "sg:province":"Vlaams-Brabant",
    "wof:name":"Fa. Bas & Schoonejans",
    "wof:placetype":"venue"
},
  "geometry": {"coordinates":[4.3698301315,50.9538269043],"type":"Point"}
}