{
  "type": "Feature",
  "properties": {
    "addr:full":"Rue Bellefontaine 91bv Etalle Luxembourg 6740",
    "addr:housenumber":"91bv",
    "addr:postcode":"6740",
    "addr:street":"Rue Bellefontaine",
    "iso:country":"BE",
    "sg:address":"Rue Bellefontaine 91bv",
    "sg:city":"Etalle",
    "sg:orig_category":"Woningbouw",
    "sg:phone":"+32 63 45 50 18",
    "sg:postcode":"6740",
    "sg:province":"Luxembourg",
    "wof:name":"Jean-claude Calande",
    "wof:placetype":"venue"
},
  "geometry": {"coordinates":[5.6007847786,49.6738510132],"type":"Point"}
}