{
  "type": "Feature",
  "properties": {
    "addr:full":"Place Paul Pastur 13 Anderlues Hainaut 6150",
    "addr:housenumber":"13",
    "addr:postcode":"6150",
    "addr:street":"Place Paul Pastur",
    "iso:country":"BE",
    "sg:address":"Place Paul Pastur 13",
    "sg:city":"Anderlues",
    "sg:classifiers":[
        {
            "category":"Health Services",
            "subcategory":"Health Practitioner",
            "type":"Services"
        }
    ],
    "sg:phone":"+32 71 54 26 29",
    "sg:postcode":"6150",
    "sg:province":"Hainaut",
    "sg:tags":[
        "therapist",
        "speech"
    ],
    "wof:name":"Dialexis",
    "wof:placetype":"venue"
},
  "geometry": {"coordinates":[4.2698287964,50.4082565308],"type":"Point"}
}