{
  "type": "Feature",
  "properties": {
    "iso:country":"BE",
    "sg:address":"Rue Du Ch\u00eane 10",
    "sg:city":"Andenne (nam\u00eache)",
    "sg:classifiers":[
        {
            "category":"Banks & Credit Unions",
            "subcategory":"Investment Brokerage",
            "type":"Services"
        }
    ],
    "sg:phone":"+32 81 58 01 17",
    "sg:postcode":"5300",
    "sg:province":"Namur",
    "sg:tags":[
        "repair",
        "-",
        "installation",
        "sanitary",
        "article"
    ],
    "wof:name":"Delhalle J-p",
    "wof:placetype":"venue"
},
  "geometry": {"coordinates":[4.9937610626,50.4722480774],"type":"Point"}
}