{
  "type": "Feature",
  "properties": {
    "iso:country":"BE",
    "sg:address":"Avenue Ernest Cambier 19",
    "sg:city":"Schaarbeek/schaerbeek",
    "sg:orig_category":"Production de films, t\u00e9l\u00e9films and vid\u00e9os",
    "sg:phone":"+32 2 215 83 05",
    "sg:postcode":"1030",
    "sg:province":"Bruxelles-Capitale",
    "wof:name":"Wannabee",
    "wof:placetype":"venue"
},
  "geometry": {"coordinates":[4.3920550346,50.8586463928],"type":"Point"}
}