{
  "type": "Feature",
  "properties": {
    "addr:full":"Rue Sabli\u00c8re 1bb Sivry-rance Hainaut 6470",
    "addr:housenumber":"1bb",
    "addr:postcode":"6470",
    "addr:street":"Rue Sablie\u0300Re",
    "iso:country":"BE",
    "sg:address":"Rue Sabli\u00c8re 1bb",
    "sg:city":"Sivry-rance",
    "sg:orig_category":"Herstellingen and onderhoud van auto's",
    "sg:phone":"+32 60 45 67 31",
    "sg:postcode":"6470",
    "sg:province":"Hainaut",
    "wof:name":"Fe. Autocarreau",
    "wof:placetype":"venue"
},
  "geometry": {"coordinates":[4.1816868782,50.1991271973],"type":"Point"}
}