{
  "type": "Feature",
  "properties": {
    "addr:full":"Rue De Rouillon 26 Anhee Namur 5537",
    "addr:housenumber":"26",
    "addr:postcode":"5537",
    "addr:street":"Rue De Rouillon;Namur",
    "iso:country":"BE",
    "sg:address":"Rue De Rouillon 26",
    "sg:city":"Anhee",
    "sg:orig_category":"Peinture. Rev\u00eatements pour sols and murs",
    "sg:phone":"+32 71 79 90 07",
    "sg:postcode":"5537",
    "sg:province":"Namur",
    "wof:name":"Jules Simon",
    "wof:placetype":"venue"
},
  "geometry": {"coordinates":[4.8052978516,50.3347053528],"type":"Point"}
}