{
  "type": "Feature",
  "properties": {
    "iso:country":"BE",
    "sg:address":"Lossingstraat 144",
    "sg:city":"Schoten",
    "sg:classifiers":[
        {
            "category":"Home & Garden",
            "subcategory":"Garden Supply",
            "type":"Retail Goods"
        }
    ],
    "sg:phone":"+32 3 658 12 29",
    "sg:postcode":"2900",
    "sg:province":"Antwerpen",
    "sg:tags":[
        "lawn",
        "mower"
    ],
    "wof:name":"Bonnel Jean-pierre",
    "wof:placetype":"venue"
},
  "geometry": {"coordinates":[4.5094242096,51.2553215027],"type":"Point"}
}