{
  "type": "Feature",
  "properties": {
    "addr:full":"Avenue Louise  149b28 1050",
    "addr:housenumber":"149b28",
    "addr:postcode":"1050",
    "addr:street":"Avenue Louise",
    "iso:country":"BE",
    "sg:address":"Avenue Louise  149b28",
    "sg:classifiers":[
        {
            "category":"Professional",
            "subcategory":"Computer Services",
            "type":"Services"
        }
    ],
    "sg:postcode":"1050",
    "sg:website":"http://www.kiala.co.uk/",
    "wof:name":"Kiala",
    "wof:placetype":"venue"
},
  "geometry": {"coordinates":[4.3652584,50.8256038],"type":"Point"}
}