{
  "type": "Feature",
  "properties": {
    "addr:full":"Ringlaan 133 Merksem Antwerpen 2170",
    "addr:housenumber":"133",
    "addr:postcode":"2170",
    "addr:street":"Ringlaan",
    "iso:country":"BE",
    "sg:address":"Ringlaan 133",
    "sg:city":"Merksem",
    "sg:classifiers":[
        {
            "category":"Professional",
            "type":"Services"
        }
    ],
    "sg:phone":"+32 3 448 06 50",
    "sg:postcode":"2170",
    "sg:province":"Antwerpen",
    "sg:tags":[
        "transport",
        "road"
    ],
    "wof:name":"Kohler Belgie Bvba",
    "wof:placetype":"venue"
},
  "geometry": {"coordinates":[4.4495358467,51.2548675537],"type":"Point"}
}