{
  "type": "Feature",
  "properties": {
    "addr:full":"Drijdijk 3 Sint-laureins Oost-Vlaanderen 9988",
    "addr:housenumber":"3",
    "addr:postcode":"9988",
    "addr:street":"Drijdijk",
    "iso:country":"BE",
    "sg:address":"Drijdijk 3",
    "sg:city":"Sint-laureins",
    "sg:classifiers":[
        {
            "category":"Food & Beverages",
            "subcategory":"Fruits & Vegetables",
            "type":"Retail Goods"
        }
    ],
    "sg:phone":"+32 9 379 82 73",
    "sg:postcode":"9988",
    "sg:province":"Oost-Vlaanderen",
    "sg:tags":[
        "l\u00e9gumes",
        "gr"
    ],
    "wof:name":"Van Driessen G. & L.",
    "wof:placetype":"venue"
},
  "geometry": {"coordinates":[3.5899000168,51.2713394165],"type":"Point"}
}