{
  "type": "Feature",
  "properties": {
    "iso:country":"BE",
    "sg:address":"Rue De La Brasserie 39",
    "sg:city":"Tournai (vaulx)",
    "sg:classifiers":[
        {
            "category":"Social Services",
            "type":"Services"
        }
    ],
    "sg:phone":"+32 69 55 74 82",
    "sg:postcode":"7536",
    "sg:province":"Hainaut",
    "wof:name":"Goudini\u00e8re (la) Asbl",
    "wof:placetype":"venue"
},
  "geometry": {"coordinates":[3.4263501167,50.5929222107],"type":"Point"}
}