{
  "type": "Feature",
  "properties": {
    "iso:country":"BE",
    "sg:address":"Magerhoek 16",
    "sg:city":"Destelbergen (heusden)",
    "sg:classifiers":[
        {
            "category":"Structure",
            "subcategory":"Office Building",
            "type":"Public Place"
        }
    ],
    "sg:phone":"+32 9 231 24 05",
    "sg:postcode":"9070",
    "sg:province":"Oost-Vlaanderen",
    "sg:tags":[
        "drawing"
    ],
    "wof:name":"Mno-cad Service",
    "wof:placetype":"venue"
},
  "geometry": {"coordinates":[3.8156750202,51.0245018005],"type":"Point"}
}