{
  "type": "Feature",
  "properties": {
    "addr:full":"Blankenbergse Steenweg 6 Brugge West-Vlaanderen 8000",
    "addr:housenumber":"6",
    "addr:postcode":"8000",
    "addr:street":"Blankenbergse Steenweg",
    "iso:country":"BE",
    "sg:address":"Blankenbergse Steenweg 6",
    "sg:city":"Brugge",
    "sg:classifiers":[
        {
            "category":"Building & Trades",
            "subcategory":"Construction",
            "type":"Services"
        }
    ],
    "sg:phone":"+32 50 31 22 05",
    "sg:postcode":"8000",
    "sg:province":"West-Vlaanderen",
    "sg:tags":[
        "scaffolding"
    ],
    "wof:name":"Alklimat",
    "wof:placetype":"venue"
},
  "geometry": {"coordinates":[3.2239320278,51.208278656],"type":"Point"}
}