{
  "type": "Feature",
  "properties": {
    "addr:full":"Hoogstraat 15 Brussel/bruxelles Bruxelles-Capitale 1000",
    "addr:housenumber":"15",
    "addr:postcode":"1000",
    "addr:street":"Hoogstraat;/",
    "iso:country":"BE",
    "sg:address":"Hoogstraat 15",
    "sg:city":"Brussel/bruxelles",
    "sg:orig_category":"Herstellingswinkels voor diverse persoonlijke and huishoudartikelen",
    "sg:phone":"+32 2 511 21 59",
    "sg:postcode":"1000",
    "sg:province":"Bruxelles-Capitale",
    "wof:name":"Maison Devroede",
    "wof:placetype":"venue"
},
  "geometry": {"coordinates":[4.3519787788,50.8419113159],"type":"Point"}
}