{
  "type": "Feature",
  "properties": {
    "addr:full":"Niklaas Desparsstraat 2 Box 1 Brugge West-Vlaanderen 8000",
    "addr:housenumber":"2;1",
    "addr:postcode":"8000",
    "addr:street":"Niklaas Desparsstraat;Box",
    "iso:country":"BE",
    "sg:address":"Niklaas Desparsstraat 2 Box 1",
    "sg:city":"Brugge",
    "sg:classifiers":[
        {
            "category":"Real Estate",
            "subcategory":"Architect",
            "type":"Services"
        }
    ],
    "sg:phone":"+32 50 33 30 89",
    "sg:postcode":"8000",
    "sg:province":"West-Vlaanderen",
    "wof:name":"Van Der Ghote F",
    "wof:placetype":"venue"
},
  "geometry": {"coordinates":[3.2234299183,51.2095947266],"type":"Point"}
}