{
  "type": "Feature",
  "properties": {
    "addr:full":"Rue Des Champs Elys\u00e9es 84 Bruxelles (ixelles) Bruxelles-Capitale 1050",
    "addr:housenumber":"84",
    "addr:postcode":"1050",
    "addr:street":"Rue Des Champs Elyse\u0301Es",
    "iso:country":"BE",
    "sg:address":"Rue Des Champs Elys\u00e9es 84",
    "sg:city":"Bruxelles (ixelles)",
    "sg:classifiers":[
        {
            "category":"Health Services",
            "subcategory":"Doctor",
            "type":"Services"
        }
    ],
    "sg:phone":"+32 475 78 04 69",
    "sg:postcode":"1050",
    "sg:province":"Bruxelles-Capitale",
    "sg:tags":[
        "psychotherapist",
        "psychoanalyst"
    ],
    "wof:name":"Laplace Charlotte",
    "wof:placetype":"venue"
},
  "geometry": {"coordinates":[4.3691692352,50.8289756775],"type":"Point"}
}