{
  "type": "Feature",
  "properties": {
    "iso:country":"BE",
    "sg:address":"Kortrijkstraat 45",
    "sg:city":"Deinze",
    "sg:orig_category":"Artsen and specialisten",
    "sg:phone":"+32 9 386 49 29",
    "sg:postcode":"9800",
    "sg:province":"Oost-Vlaanderen",
    "wof:name":"Eddy Van Maerken",
    "wof:placetype":"venue"
},
  "geometry": {"coordinates":[3.5289549828,50.9783821106],"type":"Point"}
}