{
  "type": "Feature",
  "properties": {
    "addr:full":"Rue Longue Voie 14 Soumagne (ayeneux) Li\u00e8ge 4630",
    "addr:housenumber":"14",
    "addr:postcode":"4630",
    "addr:street":"Rue Longue Voie",
    "iso:country":"BE",
    "sg:address":"Rue Longue Voie 14",
    "sg:city":"Soumagne (ayeneux)",
    "sg:classifiers":[
        {
            "category":"Professional",
            "subcategory":"Art Services",
            "type":"Services"
        }
    ],
    "sg:phone":"+32 4 358 04 44",
    "sg:postcode":"4630",
    "sg:province":"Li\u00e8ge",
    "sg:tags":[
        "graphic",
        "designer"
    ],
    "wof:name":"Picto",
    "wof:placetype":"venue"
},
  "geometry": {"coordinates":[5.7176918983,50.6077308655],"type":"Point"}
}