{
  "type": "Feature",
  "properties": {
    "addr:full":"Ringlaan 146 Overpelt Limburg 3900",
    "addr:housenumber":"146",
    "addr:postcode":"3900",
    "addr:street":"Ringlaan",
    "iso:country":"BE",
    "sg:address":"Ringlaan 146",
    "sg:city":"Overpelt",
    "sg:classifiers":[
        {
            "category":"Health Services",
            "subcategory":"Dentist",
            "type":"Services"
        }
    ],
    "sg:phone":"+32 11 66 18 20",
    "sg:postcode":"3900",
    "sg:province":"Limburg",
    "wof:name":"Peeters Mieke",
    "wof:placetype":"venue"
},
  "geometry": {"coordinates":[5.432390213,51.2114982605],"type":"Point"}
}