{
  "type": "Feature",
  "properties": {
    "iso:country":"BE",
    "sg:address":"Ophovenstraat 22",
    "sg:city":"Meeuwen-gruitrode (gruitrode)",
    "sg:classifiers":[
        {
            "category":"Retail",
            "subcategory":"Repair Shop",
            "type":"Services"
        }
    ],
    "sg:phone":"+32 89 85 40 34",
    "sg:postcode":"3670",
    "sg:province":"Limburg",
    "sg:tags":[
        "-",
        "mainten",
        "watch",
        "clock"
    ],
    "wof:name":"Buntinx V",
    "wof:placetype":"venue"
},
  "geometry": {"coordinates":[5.5348110199,51.0683021545],"type":"Point"}
}