{
  "type": "Feature",
  "properties": {
    "addr:full":"Essenhoutstraat 36 Kapellen Antwerpen 2950",
    "addr:housenumber":"36",
    "addr:postcode":"2950",
    "addr:street":"Essenhoutstraat",
    "iso:country":"BE",
    "sg:address":"Essenhoutstraat 36",
    "sg:city":"Kapellen",
    "sg:classifiers":[
        {
            "category":"Bars & Pubs",
            "type":"Food & Drink"
        }
    ],
    "sg:phone":"+32 3 605 60 15",
    "sg:postcode":"2950",
    "sg:province":"Antwerpen",
    "wof:name":"Den Bumper",
    "wof:placetype":"venue"
},
  "geometry": {"coordinates":[4.4259600639,51.3131141663],"type":"Point"}
}