{
  "type": "Feature",
  "properties": {
    "addr:full":"Vijverstraat 2 Puurs Antwerpen 2870",
    "addr:housenumber":"2",
    "addr:postcode":"2870",
    "addr:street":"Vijverstraat",
    "iso:country":"BE",
    "sg:address":"Vijverstraat 2",
    "sg:city":"Puurs",
    "sg:classifiers":[
        {
            "category":"Transit Center",
            "subcategory":"Passenger",
            "type":"Transportation"
        }
    ],
    "sg:phone":"+32 3 899 02 07",
    "sg:postcode":"2870",
    "sg:province":"Antwerpen",
    "sg:tags":[
        "car",
        "trailer"
    ],
    "wof:name":"Van Dingenen E",
    "wof:placetype":"venue"
},
  "geometry": {"coordinates":[4.3057222366,51.0750160217],"type":"Point"}
}