{
  "type": "Feature",
  "properties": {
    "addr:full":"Jan Van Gentstraat 6 Antwerpen Antwerpen 2000",
    "addr:housenumber":"6",
    "addr:postcode":"2000",
    "addr:street":"Jan Van Gentstraat",
    "iso:country":"BE",
    "sg:address":"Jan Van Gentstraat 6",
    "sg:city":"Antwerpen",
    "sg:classifiers":[
        {
            "category":"Utilities",
            "subcategory":"Fuel Oil & Lpg",
            "type":"Services"
        }
    ],
    "sg:phone":"+32 3 238 59 10",
    "sg:postcode":"2000",
    "sg:province":"Antwerpen",
    "sg:tags":[
        "product"
    ],
    "wof:name":"De Smet & Van Diest Nv",
    "wof:placetype":"venue"
},
  "geometry": {"coordinates":[4.3873829842,51.2054672241],"type":"Point"}
}