{
  "type": "Feature",
  "properties": {
    "iso:country":"BE",
    "sg:address":"Frans Tittelmansstraat 10",
    "sg:city":"Hasselt",
    "sg:classifiers":[
        {
            "category":"Structure",
            "subcategory":"Office Building",
            "type":"Public Place"
        }
    ],
    "sg:phone":"+32 11 24 27 84",
    "sg:postcode":"3500",
    "sg:province":"Limburg",
    "sg:tags":[
        "drawing"
    ],
    "wof:name":"Archico",
    "wof:placetype":"venue"
},
  "geometry": {"coordinates":[5.3489089012,50.944606781],"type":"Point"}
}