{
  "type": "Feature",
  "properties": {
    "addr:full":"Avenue Des Rousserolles 59 Rhode-saint-gen\u00e8se Vlaams-Brabant 1640",
    "addr:housenumber":"59",
    "addr:postcode":"1640",
    "addr:street":"Avenue Des Rousserolles",
    "iso:country":"BE",
    "sg:address":"Avenue Des Rousserolles 59",
    "sg:city":"Rhode-saint-gen\u00e8se",
    "sg:classifiers":[
        {
            "category":"Professional",
            "subcategory":"Management & Consulting",
            "type":"Services"
        }
    ],
    "sg:phone":"+32 2 381 01 65",
    "sg:postcode":"1640",
    "sg:province":"Vlaams-Brabant",
    "sg:tags":[
        "consultant"
    ],
    "wof:name":"Score Sprl",
    "wof:placetype":"venue"
},
  "geometry": {"coordinates":[4.3557801247,50.7566604614],"type":"Point"}
}