{
  "type": "Feature",
  "properties": {
    "addr:full":"Rue Du Grand-babin 54 Namur Namur 5020",
    "addr:housenumber":"54",
    "addr:postcode":"5020",
    "addr:street":"Rue Du Grand-Babin",
    "iso:country":"BE",
    "sg:address":"Rue Du Grand-babin 54",
    "sg:city":"Namur",
    "sg:orig_category":"Entretien and r\u00e9parations de voitures",
    "sg:phone":"+32 81 45 04 47",
    "sg:postcode":"5020",
    "sg:province":"Namur",
    "wof:name":"Garage Du Babin",
    "wof:placetype":"venue"
},
  "geometry": {"coordinates":[4.7952418327,50.4352035522],"type":"Point"}
}