{
  "type": "Feature",
  "properties": {
    "addr:full":"Pamelstraat 156 Ninove Oost-Vlaanderen 9400",
    "addr:housenumber":"156",
    "addr:postcode":"9400",
    "addr:street":"Pamelstraat",
    "iso:country":"BE",
    "sg:address":"Pamelstraat 156",
    "sg:city":"Ninove",
    "sg:orig_category":"Loodgieterij, verwarming and sanitaire installaties",
    "sg:phone":"+32 54 33 70 09",
    "sg:postcode":"9400",
    "sg:province":"Oost-Vlaanderen",
    "wof:name":"Jean-luc Seys",
    "wof:placetype":"venue"
},
  "geometry": {"coordinates":[4.0302510262,50.838142395],"type":"Point"}
}