{
  "type": "Feature",
  "properties": {
    "addr:full":"Mottedreef 2a Maldegem Oost-Vlaanderen 9990",
    "addr:housenumber":"2a",
    "addr:postcode":"9990",
    "addr:street":"Mottedreef",
    "iso:country":"BE",
    "sg:address":"Mottedreef 2a",
    "sg:city":"Maldegem",
    "sg:classifiers":[
        {
            "category":"Manufacturing",
            "subcategory":"Tools & Machinery",
            "type":"Manufacturing & Wholesale Goods"
        }
    ],
    "sg:phone":"+32 50 71 40 23",
    "sg:postcode":"9990",
    "sg:province":"Oost-Vlaanderen",
    "sg:tags":[
        "stone",
        "working"
    ],
    "wof:name":"Mebotek",
    "wof:placetype":"venue"
},
  "geometry": {"coordinates":[3.4353780746,51.2161865234],"type":"Point"}
}