{
  "type": "Feature",
  "properties": {
    "iso:country":"BE",
    "sg:address":"Rue Saint Bruno 18",
    "sg:city":"Tournai",
    "sg:orig_category":"Architecten",
    "sg:phone":"+32 69 21 30 05",
    "sg:postcode":"7500",
    "sg:province":"Hainaut",
    "wof:name":"Wilbaux Quentin",
    "wof:placetype":"venue"
},
  "geometry": {"coordinates":[3.3889040947,50.6114234924],"type":"Point"}
}