{
  "type": "Feature",
  "properties": {
    "iso:country":"BE",
    "sg:address":"Rue De Bourgogne 24",
    "sg:city":"Li\u00c8ge",
    "sg:orig_category":"Dierenartsen",
    "sg:phone":"+32 4 253 03 63",
    "sg:postcode":"4000",
    "sg:province":"Li\u00e8ge",
    "wof:name":"Clinique V\u00c9t\u00c9rinaire",
    "wof:placetype":"venue"
},
  "geometry": {"coordinates":[5.5606827736,50.6195411682],"type":"Point"}
}