{
  "type": "Feature",
  "properties": {
    "addr:full":"Rue De La Gare 36ba Bertrix Luxembourg 6880",
    "addr:housenumber":"36ba",
    "addr:postcode":"6880",
    "addr:street":"Rue De La Gare",
    "iso:country":"BE",
    "sg:address":"Rue De La Gare 36ba",
    "sg:city":"Bertrix",
    "sg:orig_category":"Boekhouders",
    "sg:phone":"+32 61 41 33 94",
    "sg:postcode":"6880",
    "sg:province":"Luxembourg",
    "wof:name":"M. Guillaume",
    "wof:placetype":"venue"
},
  "geometry": {"coordinates":[5.2562689781,49.8548355103],"type":"Point"}
}