{
  "type": "Feature",
  "properties": {
    "addr:full":"Rue Bois Madame 6 Charleroi Hainaut 6032",
    "addr:housenumber":"6",
    "addr:postcode":"6032",
    "addr:street":"Rue Bois Madame;Hainaut",
    "iso:country":"BE",
    "sg:address":"Rue Bois Madame 6",
    "sg:city":"Charleroi",
    "sg:orig_category":"Elektrische installaties voor woningen",
    "sg:phone":"+32 71 43 27 00",
    "sg:postcode":"6032",
    "sg:province":"Hainaut",
    "wof:name":"Jean Flemal",
    "wof:placetype":"venue"
},
  "geometry": {"coordinates":[4.4185571671,50.3755645752],"type":"Point"}
}