{
  "type": "Feature",
  "properties": {
    "addr:full":"Rue D\u00b4eghez\u00c9e 45 Fernelmont Namur 5380",
    "addr:housenumber":"45",
    "addr:postcode":"5380",
    "addr:street":"Rue D\u00b4Egheze\u0301E",
    "iso:country":"BE",
    "sg:address":"Rue D\u00b4eghez\u00c9e 45",
    "sg:city":"Fernelmont",
    "sg:orig_category":"Cr\u00e9dit \u00e0 la consommation",
    "sg:phone":"+32 81 83 43 00",
    "sg:postcode":"5380",
    "sg:province":"Namur",
    "wof:name":"Bureau Goreux V.",
    "wof:placetype":"venue"
},
  "geometry": {"coordinates":[4.9861078262,50.5531463623],"type":"Point"}
}