{
  "type": "Feature",
  "properties": {
    "iso:country":"BE",
    "sg:address":"Waverse Steenweg 1728",
    "sg:city":"Oudergem/auderghem",
    "sg:orig_category":"Benzinestations and brandstoffen Herstellingen and onderhoud van auto's",
    "sg:phone":"+32 2 672 70 42",
    "sg:postcode":"1160",
    "sg:province":"Bruxelles-Capitale",
    "wof:name":"Q8",
    "wof:placetype":"venue"
},
  "geometry": {"coordinates":[4.4317970276,50.8158874512],"type":"Point"}
}