{
  "type": "Feature",
  "properties": {
    "iso:country":"BE",
    "sg:address":"Kouterstraat 11b",
    "sg:city":"Wevelgem",
    "sg:orig_category":"Mobilier and \u00e9quipement m\u00e9nager Gr",
    "sg:phone":"+32 56 41 77 24",
    "sg:postcode":"8560",
    "sg:province":"West-Vlaanderen",
    "wof:name":"Kortim",
    "wof:placetype":"venue"
},
  "geometry": {"coordinates":[3.2070479393,50.8137130737],"type":"Point"}
}