{
  "type": "Feature",
  "properties": {
    "addr:full":"Vis\u00e9steenweg 211 Riemst (zichen-zussen-bolder) Limburg 3770",
    "addr:housenumber":"211",
    "addr:postcode":"3770",
    "addr:street":"Vise\u0301Steenweg",
    "iso:country":"BE",
    "sg:address":"Vis\u00e9steenweg 211",
    "sg:city":"Riemst (zichen-zussen-bolder)",
    "sg:classifiers":[
        {
            "category":"Professional",
            "subcategory":"Testing Lab",
            "type":"Services"
        }
    ],
    "sg:phone":"+32 12 45 13 82",
    "sg:postcode":"3770",
    "sg:province":"Limburg",
    "sg:tags":[
        "chemist"
    ],
    "wof:name":"Jans Nv",
    "wof:placetype":"venue"
},
  "geometry": {"coordinates":[5.6054201126,50.8047485352],"type":"Point"}
}