{
  "type": "Feature",
  "properties": {
    "addr:full":"Wellingstraat 109 Beernem West-Vlaanderen 8730",
    "addr:housenumber":"109",
    "addr:postcode":"8730",
    "addr:street":"Wellingstraat",
    "iso:country":"BE",
    "sg:address":"Wellingstraat 109",
    "sg:city":"Beernem",
    "sg:orig_category":"Slagers",
    "sg:phone":"+32 50 78 91 01",
    "sg:postcode":"8730",
    "sg:province":"West-Vlaanderen",
    "wof:name":"Gema",
    "wof:placetype":"venue"
},
  "geometry": {"coordinates":[3.3002979755,51.1268081665],"type":"Point"}
}