{
  "type": "Feature",
  "properties": {
    "addr:full":"Boulevard Delwart 25 Tournai Hainaut 7500",
    "addr:housenumber":"25",
    "addr:postcode":"7500",
    "addr:street":"Boulevard Delwart",
    "iso:country":"BE",
    "sg:address":"Boulevard Delwart 25",
    "sg:city":"Tournai",
    "sg:orig_category":"Loodgieterij, verwarming and sanitaire installaties",
    "sg:phone":"+32 69 23 31 60",
    "sg:postcode":"7500",
    "sg:province":"Hainaut",
    "wof:name":"Fe. Beuscart",
    "wof:placetype":"venue"
},
  "geometry": {"coordinates":[3.3850529194,50.6144981384],"type":"Point"}
}