{
  "type": "Feature",
  "properties": {
    "iso:country":"BE",
    "sg:address":"Vrijheidsstraat 4",
    "sg:city":"Grobbendonk",
    "sg:classifiers":[
        {
            "category":"Personal",
            "subcategory":"Beauty Salon",
            "type":"Services"
        }
    ],
    "sg:phone":"+32 14 51 16 33",
    "sg:postcode":"2280",
    "sg:province":"Antwerpen",
    "sg:tags":[
        "de",
        "coiffure"
    ],
    "wof:name":"Coiffure Jeannine",
    "wof:placetype":"venue"
},
  "geometry": {"coordinates":[4.7432961464,51.1773452759],"type":"Point"}
}