{
  "type": "Feature",
  "properties": {
    "addr:full":"Avenue Des Flandres 23 Leuze-en-hainaut Hainaut 7900",
    "addr:housenumber":"23",
    "addr:postcode":"7900",
    "addr:street":"Avenue Des Flandres",
    "iso:country":"BE",
    "sg:address":"Avenue Des Flandres 23",
    "sg:city":"Leuze-en-hainaut",
    "sg:orig_category":"Installation de menuiserie m\u00e9tallique. Installation de menuiserie en bois and plastique",
    "sg:phone":"+32 69 66 31 08",
    "sg:postcode":"7900",
    "sg:province":"Hainaut",
    "wof:name":"Emd Stores (p.s.)",
    "wof:placetype":"venue"
},
  "geometry": {"coordinates":[3.616549015,50.6071128845],"type":"Point"}
}