{
  "type": "Feature",
  "properties": {
    "iso:country":"BE",
    "sg:address":"Boulevard G\u00e9n\u00e9ral Jacques 263a",
    "sg:city":"Bruxelles (ixelles)",
    "sg:classifiers":[
        {
            "category":"Bars & Pubs",
            "type":"Food & Drink"
        }
    ],
    "sg:phone":"+32 2 644 54 20",
    "sg:postcode":"1050",
    "sg:province":"Bruxelles-Capitale",
    "sg:tags":[
        "tavern"
    ],
    "wof:name":"Phare (le)",
    "wof:placetype":"venue"
},
  "geometry": {"coordinates":[4.3891820908,50.8220748901],"type":"Point"}
}