{
  "type": "Feature",
  "properties": {
    "addr:full":"Aarschotsesteenweg 147 Rotselaar Vlaams-Brabant 3111",
    "addr:housenumber":"147",
    "addr:postcode":"3111",
    "addr:street":"Aarschotsesteenweg",
    "iso:country":"BE",
    "sg:address":"Aarschotsesteenweg 147",
    "sg:city":"Rotselaar",
    "sg:orig_category":"Epiceries",
    "sg:phone":"+32 16 58 03 30",
    "sg:postcode":"3111",
    "sg:province":"Vlaams-Brabant",
    "wof:name":"Super C.",
    "wof:placetype":"venue"
},
  "geometry": {"coordinates":[4.7547087669,50.9484176636],"type":"Point"}
}