{
  "type": "Feature",
  "properties": {
    "iso:country":"BE",
    "sg:address":"Lauwerijkstraat 34",
    "sg:city":"Boechout",
    "sg:orig_category":"Eleveurs de bovins",
    "sg:phone":"+32 3 455 70 52",
    "sg:postcode":"2530",
    "sg:province":"Antwerpen",
    "wof:name":"Fa. Wellens Gebrs",
    "wof:placetype":"venue"
},
  "geometry": {"coordinates":[4.5200529099,51.1455497742],"type":"Point"}
}