{
  "type": "Feature",
  "properties": {
    "iso:country":"BE",
    "sg:address":"Meester Van Der Borghtstraat 110",
    "sg:city":"Putte",
    "sg:classifiers":[
        {
            "category":"Insurance",
            "subcategory":"Insurance Agent",
            "type":"Services"
        }
    ],
    "sg:phone":"+32 15 23 31 89",
    "sg:postcode":"2580",
    "sg:province":"Antwerpen",
    "sg:tags":[
        "broker"
    ],
    "wof:name":"De Wachter L Bvba",
    "wof:placetype":"venue"
},
  "geometry": {"coordinates":[4.6590499878,51.0335617065],"type":"Point"}
}