{
  "type": "Feature",
  "properties": {
    "addr:full":"Beneluxlaan 7 Poperinge West-Vlaanderen 8970",
    "addr:housenumber":"7",
    "addr:postcode":"8970",
    "addr:street":"Beneluxlaan",
    "iso:country":"BE",
    "sg:address":"Beneluxlaan 7",
    "sg:city":"Poperinge",
    "sg:classifiers":[
        {
            "category":"Home & Garden",
            "subcategory":"Building Materials",
            "type":"Retail Goods"
        }
    ],
    "sg:phone":"+32 57 30 00 41",
    "sg:postcode":"8970",
    "sg:province":"West-Vlaanderen",
    "sg:tags":[
        "-",
        "fireplace",
        "open",
        "ornamental"
    ],
    "wof:name":"Drafab Green",
    "wof:placetype":"venue"
},
  "geometry": {"coordinates":[2.7450499535,50.8509483337],"type":"Point"}
}