{
  "type": "Feature",
  "properties": {
    "addr:full":"Avenue Du Marouset 55 Braine-le-comte Hainaut 7090",
    "addr:housenumber":"55",
    "addr:postcode":"7090",
    "addr:street":"Avenue Du Marouset",
    "iso:country":"BE",
    "sg:address":"Avenue Du Marouset 55",
    "sg:city":"Braine-le-comte",
    "sg:classifiers":[
        {
            "category":"Autos & Motor Vehicles",
            "subcategory":"Fuel & Gas Station",
            "type":"Retail Goods"
        }
    ],
    "sg:phone":"+32 67 55 22 49",
    "sg:postcode":"7090",
    "sg:province":"Hainaut",
    "sg:tags":[
        "stations-service",
        "carburants"
    ],
    "wof:name":"Richard Sirault",
    "wof:placetype":"venue"
},
  "geometry": {"coordinates":[4.158288002,50.6084327698],"type":"Point"}
}