{
  "type": "Feature",
  "properties": {
    "addr:full":"Betekomsestraat 1 Baal Vlaams-Brabant 3128",
    "addr:housenumber":"1",
    "addr:postcode":"3128",
    "addr:street":"Betekomsestraat",
    "iso:country":"BE",
    "sg:address":"Betekomsestraat 1",
    "sg:city":"Baal",
    "sg:classifiers":[
        {
            "category":"Banks & Credit Unions",
            "subcategory":"Investment Brokerage",
            "type":"Services"
        }
    ],
    "sg:phone":"+32 16 53 41 58",
    "sg:postcode":"3128",
    "sg:province":"Vlaams-Brabant",
    "sg:tags":[
        "shutter",
        "roller"
    ],
    "wof:name":"Algemene Rolluikenfabriek B.v.b.a.",
    "wof:placetype":"venue"
},
  "geometry": {"coordinates":[4.7532839775,50.9955291748],"type":"Point"}
}