{
  "type": "Feature",
  "properties": {
    "addr:full":"Veldstraat 15 Lint Antwerpen 2547",
    "addr:housenumber":"15",
    "addr:postcode":"2547",
    "addr:street":"Veldstraat",
    "iso:country":"BE",
    "sg:address":"Veldstraat 15",
    "sg:city":"Lint",
    "sg:orig_category":"Woningbouw",
    "sg:phone":"+32 3 455 45 78",
    "sg:postcode":"2547",
    "sg:province":"Antwerpen",
    "wof:name":"Vermeulen",
    "wof:placetype":"venue"
},
  "geometry": {"coordinates":[4.488088131,51.1299285889],"type":"Point"}
}