{
  "type": "Feature",
  "properties": {
    "addr:full":"Dorpsplein 8 Wevelgem (gullegem) West-Vlaanderen 8560",
    "addr:housenumber":"8",
    "addr:postcode":"8560",
    "addr:street":"Dorpsplein",
    "iso:country":"BE",
    "sg:address":"Dorpsplein 8",
    "sg:city":"Wevelgem (gullegem)",
    "sg:classifiers":[
        {
            "category":"Bars & Pubs",
            "type":"Food & Drink"
        }
    ],
    "sg:phone":"+32 56 40 11 00",
    "sg:postcode":"8560",
    "sg:province":"West-Vlaanderen",
    "wof:name":"De Klokke",
    "wof:placetype":"venue"
},
  "geometry": {"coordinates":[3.2042200565,50.843547821],"type":"Point"}
}