{
  "type": "Feature",
  "properties": {
    "addr:full":"Molenkouterstraat 61 Zulte Oost-Vlaanderen 9870",
    "addr:housenumber":"61",
    "addr:postcode":"9870",
    "addr:street":"Molenkouterstraat",
    "iso:country":"BE",
    "sg:address":"Molenkouterstraat 61",
    "sg:city":"Zulte",
    "sg:orig_category":"Schoonheidssalons",
    "sg:phone":"+32 9 386 63 83",
    "sg:postcode":"9870",
    "sg:province":"Oost-Vlaanderen",
    "wof:name":"Carine Vindevogel",
    "wof:placetype":"venue"
},
  "geometry": {"coordinates":[3.4975810051,50.9586868286],"type":"Point"}
}