{
  "type": "Feature",
  "properties": {
    "addr:full":"Kiezelweg 255 Mol Antwerpen 2400",
    "addr:housenumber":"255",
    "addr:postcode":"2400",
    "addr:street":"Kiezelweg",
    "iso:country":"BE",
    "sg:address":"Kiezelweg 255",
    "sg:city":"Mol",
    "sg:classifiers":[
        {
            "category":"Fast Food",
            "type":"Food & Drink"
        }
    ],
    "sg:phone":"+32 14 81 69 83",
    "sg:postcode":"2400",
    "sg:province":"Antwerpen",
    "sg:tags":[
        "\u00c0",
        "restaurants",
        "emporter",
        "restaurant"
    ],
    "wof:name":"Restaurant Incontri",
    "wof:placetype":"venue"
},
  "geometry": {"coordinates":[5.1930098534,51.2158508301],"type":"Point"}
}