{
  "type": "Feature",
  "properties": {
    "iso:country":"BE",
    "sg:address":"Rue De L'invasion 19",
    "sg:city":"Baelen/baelen",
    "sg:orig_category":"Installation \u00e9lectrique r\u00e9sidentielle",
    "sg:phone":"+32 87 55 22 86",
    "sg:postcode":"4837",
    "sg:province":"Li\u00e8ge",
    "wof:name":"Roger Gregoire",
    "wof:placetype":"venue"
},
  "geometry": {"coordinates":[6.0066919327,50.6111450195],"type":"Point"}
}