{
  "type": "Feature",
  "properties": {
    "iso:country":"BE",
    "sg:address":"Rue De Fontaine-l\u00b4ev\u00caque 15",
    "sg:city":"Charleroi",
    "sg:orig_category":"Quincailleries. Mat\u00e9riel pour plomberie and chauffage Gr",
    "sg:phone":"+32 71 45 37 40",
    "sg:postcode":"6044",
    "sg:province":"Hainaut",
    "wof:name":"Po\u00calerie Du Martinet",
    "wof:placetype":"venue"
},
  "geometry": {"coordinates":[4.3825349808,50.4351844788],"type":"Point"}
}