{
  "type": "Feature",
  "properties": {
    "iso:country":"BE",
    "sg:address":"Jozef Tielemansstraat 30",
    "sg:city":"Aarschot",
    "sg:classifiers":[
        {
            "category":"Restaurant",
            "type":"Food & Drink"
        }
    ],
    "sg:phone":"+32 16 57 08 70",
    "sg:postcode":"3200",
    "sg:province":"Vlaams-Brabant",
    "wof:name":"Eetkafee",
    "wof:placetype":"venue"
},
  "geometry": {"coordinates":[4.8355441093,50.9847183228],"type":"Point"}
}