{
  "type": "Feature",
  "properties": {
    "addr:full":"Rue Du Centre 83 Saint-georges-sur-meuse Li\u00e8ge 4470",
    "addr:housenumber":"83",
    "addr:postcode":"4470",
    "addr:street":"Rue Du Centre",
    "iso:country":"BE",
    "sg:address":"Rue Du Centre 83",
    "sg:city":"Saint-georges-sur-meuse",
    "sg:orig_category":"Installation de menuiserie en bois and plastique. Installation de menuiserie m\u00e9tallique",
    "sg:phone":"+32 4 259 62 12",
    "sg:postcode":"4470",
    "sg:province":"Li\u00e8ge",
    "wof:name":"D'awans",
    "wof:placetype":"venue"
},
  "geometry": {"coordinates":[5.3656158447,50.6089897156],"type":"Point"}
}