{
  "type": "Feature",
  "properties": {
    "addr:full":"Tongerenstraat 24 Etterbeek Bruxelles-Capitale 1040",
    "addr:housenumber":"24",
    "addr:postcode":"1040",
    "addr:street":"Tongerenstraat",
    "iso:country":"BE",
    "sg:address":"Tongerenstraat 24",
    "sg:city":"Etterbeek",
    "sg:orig_category":"Reisbureaus",
    "sg:phone":"+32 2 738 99 99",
    "sg:postcode":"1040",
    "sg:province":"Bruxelles-Capitale",
    "wof:name":"Nouvelles Fronti\u00c8res",
    "wof:placetype":"venue"
},
  "geometry": {"coordinates":[4.3996629715,50.8398857117],"type":"Point"}
}