{
  "type": "Feature",
  "properties": {
    "iso:country":"BE",
    "sg:address":"Steenweg 275",
    "sg:city":"Alken",
    "sg:orig_category":"Rev\u00eatements pour sols and murs. Peinture",
    "sg:phone":"+32 11 31 27 79",
    "sg:postcode":"3570",
    "sg:province":"Limburg",
    "wof:name":"Urbain Billen",
    "wof:placetype":"venue"
},
  "geometry": {"coordinates":[5.2706098557,50.8781585693],"type":"Point"}
}