{
  "type": "Feature",
  "properties": {
    "iso:country":"BE",
    "sg:address":"Jozef Vervaenestraat 17",
    "sg:city":"Gent",
    "sg:orig_category":"Journaux. Tabac",
    "sg:phone":"+32 9 230 03 08",
    "sg:postcode":"9050",
    "sg:province":"Oost-Vlaanderen",
    "wof:name":"Code",
    "wof:placetype":"venue"
},
  "geometry": {"coordinates":[3.7439889908,51.0327224731],"type":"Point"}
}