{
  "type": "Feature",
  "properties": {
    "iso:country":"BE",
    "sg:address":"Alfons Jeurissenstraat 12",
    "sg:city":"Hasselt",
    "sg:orig_category":"Animaux domestiques and accessoires",
    "sg:phone":"+32 11 21 49 72",
    "sg:postcode":"3500",
    "sg:province":"Limburg",
    "wof:name":"Cattery De Sheduba",
    "wof:placetype":"venue"
},
  "geometry": {"coordinates":[5.3492898941,50.9480705261],"type":"Point"}
}