{
  "type": "Feature",
  "properties": {
    "addr:full":"Alliers 24 Ranst Antwerpen 2520",
    "addr:housenumber":"24",
    "addr:postcode":"2520",
    "addr:street":"Alliers",
    "iso:country":"BE",
    "sg:address":"Alliers 24",
    "sg:city":"Ranst",
    "sg:orig_category":"Agences d'exp\u00e9dition",
    "sg:phone":"+32 3 480 84 34",
    "sg:postcode":"2520",
    "sg:province":"Antwerpen",
    "wof:name":"Gabriella Nauwelaers",
    "wof:placetype":"venue"
},
  "geometry": {"coordinates":[4.5720100403,51.1529846191],"type":"Point"}
}