{
  "type": "Feature",
  "properties": {
    "iso:country":"BE",
    "sg:address":"Large Voie 69",
    "sg:city":"Herstal",
    "sg:orig_category":"Drukkerijen and copyshops Kantoormateriaal",
    "sg:phone":"+32 4 264 00 41",
    "sg:postcode":"4040",
    "sg:province":"Li\u00e8ge",
    "wof:name":"Jeurissen",
    "wof:placetype":"venue"
},
  "geometry": {"coordinates":[5.6340060234,50.6668014526],"type":"Point"}
}