{
  "type": "Feature",
  "properties": {
    "addr:full":"Turnhoutsebaan 85 Kasterlee Antwerpen 2460",
    "addr:housenumber":"85",
    "addr:postcode":"2460",
    "addr:street":"Turnhoutsebaan",
    "iso:country":"BE",
    "sg:address":"Turnhoutsebaan 85",
    "sg:city":"Kasterlee",
    "sg:orig_category":"Installation de menuiserie en bois and plastique",
    "sg:phone":"+32 14 85 19 12",
    "sg:postcode":"2460",
    "sg:province":"Antwerpen",
    "wof:name":"Van Laer",
    "wof:placetype":"venue"
},
  "geometry": {"coordinates":[4.9645380974,51.2457885742],"type":"Point"}
}