{
  "type": "Feature",
  "properties": {
    "iso:country":"BE",
    "sg:address":"Roost 16",
    "sg:city":"Ninove",
    "sg:orig_category":"Eleveurs de bovins",
    "sg:phone":"+32 54 33 56 86",
    "sg:postcode":"9400",
    "sg:province":"Oost-Vlaanderen",
    "wof:name":"Jules Cosijn",
    "wof:placetype":"venue"
},
  "geometry": {"coordinates":[3.9876430035,50.8082847595],"type":"Point"}
}