{
  "type": "Feature",
  "properties": {
    "addr:full":"Donkersteeg 11 - 13 Gent Oost-Vlaanderen 9000",
    "addr:housenumber":"11 13",
    "addr:postcode":"9000",
    "addr:street":"Donkersteeg;Oost-Vlaanderen",
    "iso:country":"BE",
    "sg:address":"Donkersteeg 11 - 13",
    "sg:city":"Gent",
    "sg:classifiers":[
        {
            "category":"Restaurant",
            "type":"Food & Drink"
        }
    ],
    "sg:phone":"+32 9 224 21 88",
    "sg:postcode":"9000",
    "sg:province":"Oost-Vlaanderen",
    "wof:name":"New China",
    "wof:placetype":"venue"
},
  "geometry": {"coordinates":[3.7232611179,51.0544815063],"type":"Point"}
}