{
  "type": "Feature",
  "properties": {
    "iso:country":"BE",
    "sg:address":"Place Du Perron 27",
    "sg:city":"Chatelet",
    "sg:orig_category":"Epiceries",
    "sg:phone":"+32 71 38 02 79",
    "sg:postcode":"6200",
    "sg:province":"Hainaut",
    "wof:name":"Michel Alcover",
    "wof:placetype":"venue"
},
  "geometry": {"coordinates":[4.5210528374,50.4044799805],"type":"Point"}
}