{
  "type": "Feature",
  "properties": {
    "addr:full":"Zeger Van Heulestraat 2 Kortrijk West-Vlaanderen 8501",
    "addr:housenumber":"2",
    "addr:postcode":"8501",
    "addr:street":"Zeger Van Heulestraat",
    "iso:country":"BE",
    "sg:address":"Zeger Van Heulestraat 2",
    "sg:city":"Kortrijk",
    "sg:orig_category":"Banken and kredietinstellingen",
    "sg:phone":"+32 56 35 22 99",
    "sg:postcode":"8501",
    "sg:province":"West-Vlaanderen",
    "wof:name":"Bbl",
    "wof:placetype":"venue"
},
  "geometry": {"coordinates":[3.2357940674,50.8435668945],"type":"Point"}
}