{
  "type": "Feature",
  "properties": {
    "iso:country":"BE",
    "sg:address":"Sint-antoniusstraat 1 Box 3",
    "sg:city":"Kortenberg (meerbeek)",
    "sg:classifiers":[
        {
            "category":"Communications",
            "type":"Services"
        }
    ],
    "sg:phone":"+32 2 757 98 82",
    "sg:postcode":"3078",
    "sg:province":"Vlaams-Brabant",
    "sg:tags":[
        "translator"
    ],
    "wof:name":"Fobe F",
    "wof:placetype":"venue"
},
  "geometry": {"coordinates":[4.5867009163,50.8807258606],"type":"Point"}
}