{
  "type": "Feature",
  "properties": {
    "iso:country":"BE",
    "sg:address":"Rue Grande Coyarde 41",
    "sg:city":"Ramillies (mont-saint-andr\u00e9)",
    "sg:classifiers":[
        {
            "category":"Building & Trades",
            "subcategory":"Pest Control",
            "type":"Services"
        }
    ],
    "sg:phone":"+32 81 87 70 40",
    "sg:postcode":"1367",
    "sg:province":"Brabant Wallon",
    "sg:tags":[
        "painting",
        "contractor"
    ],
    "wof:name":"Mouchart Ets",
    "wof:placetype":"venue"
},
  "geometry": {"coordinates":[4.870059967,50.661857605],"type":"Point"}
}