{
  "type": "Feature",
  "properties": {
    "iso:country":"BE",
    "sg:address":"Rue Du Ch\u00c2teau-ferme 13",
    "sg:city":"Onhaye",
    "sg:orig_category":"Mus\u00e9es and patrimoine culturel",
    "sg:phone":"+32 82 69 96 26",
    "sg:postcode":"5522",
    "sg:province":"Namur",
    "wof:name":"Mus\u00c9e Ch\u00c2t.-ferme Falaen",
    "wof:placetype":"venue"
},
  "geometry": {"coordinates":[4.7962579727,50.2780990601],"type":"Point"}
}