{
  "type": "Feature",
  "properties": {
    "iso:country":"BE",
    "sg:address":"Avenue Des Olympiades 20",
    "sg:city":"Evere",
    "sg:classifiers":[
        {
            "category":"Restaurant",
            "type":"Food & Drink"
        }
    ],
    "sg:phone":"+32 2 729 23 56",
    "sg:postcode":"1140",
    "sg:province":"Bruxelles-Capitale",
    "wof:name":"Lunch Garden",
    "wof:placetype":"venue"
},
  "geometry": {"coordinates":[4.4034700394,50.8673934937],"type":"Point"}
}