{
  "type": "Feature",
  "properties": {
    "addr:full":"Burgemeester Vercruysselaan 29 Kortrijk West-Vlaanderen 8500",
    "addr:housenumber":"29",
    "addr:postcode":"8500",
    "addr:street":"Burgemeester Vercruysselaan",
    "iso:country":"BE",
    "sg:address":"Burgemeester Vercruysselaan 29",
    "sg:city":"Kortrijk",
    "sg:classifiers":[
        {
            "category":"Manufacturing",
            "subcategory":"Textiles",
            "type":"Manufacturing & Wholesale Goods"
        }
    ],
    "sg:phone":"+32 56 35 38 43",
    "sg:postcode":"8500",
    "sg:province":"West-Vlaanderen",
    "sg:tags":[
        "raw",
        "material",
        "-"
    ],
    "wof:name":"Lemaitre Bvba",
    "wof:placetype":"venue"
},
  "geometry": {"coordinates":[3.2621779442,50.835319519],"type":"Point"}
}