{
  "type": "Feature",
  "properties": {
    "iso:country":"BE",
    "sg:address":"Neutralstrasse 130",
    "sg:city":"Lontzen",
    "sg:classifiers":[
        {
            "category":"Health Services",
            "subcategory":"Dentist",
            "type":"Services"
        }
    ],
    "sg:phone":"+32 87 89 05 21",
    "sg:postcode":"4710",
    "sg:province":"Li\u00e8ge",
    "wof:name":"Oepen D",
    "wof:placetype":"venue"
},
  "geometry": {"coordinates":[5.9620499611,50.6794281006],"type":"Point"}
}