{
  "type": "Feature",
  "properties": {
    "iso:country":"BE",
    "sg:address":"Meiliedstraat 16",
    "sg:city":"Hasselt",
    "sg:orig_category":"Catering and organisation de f\u00eates",
    "sg:phone":"+32 11 27 45 81",
    "sg:postcode":"3500",
    "sg:province":"Limburg",
    "wof:name":"Vanhees",
    "wof:placetype":"venue"
},
  "geometry": {"coordinates":[5.3394351006,50.9197769165],"type":"Point"}
}