{
  "type": "Feature",
  "properties": {
    "addr:full":"Chauss\u00c9e De Tongres 231 Amay Li\u00e8ge 4540",
    "addr:housenumber":"231",
    "addr:postcode":"4540",
    "addr:street":"Chausse\u0301E De Tongres",
    "iso:country":"BE",
    "sg:address":"Chauss\u00c9e De Tongres 231",
    "sg:city":"Amay",
    "sg:classifiers":[
        {
            "category":"Cafe",
            "type":"Food & Drink"
        }
    ],
    "sg:phone":"+32 85 31 44 05",
    "sg:postcode":"4540",
    "sg:province":"Li\u00e8ge",
    "sg:tags":[
        "caf\u00e9s"
    ],
    "wof:name":"Van Brabant",
    "wof:placetype":"venue"
},
  "geometry": {"coordinates":[5.305978775,50.5562171936],"type":"Point"}
}