{
  "type": "Feature",
  "properties": {
    "iso:country":"BE",
    "sg:address":"Kampdreef 6",
    "sg:city":"Schilde",
    "sg:orig_category":"V\u00e9t\u00e9rinaires",
    "sg:phone":"+32 3 385 35 60",
    "sg:postcode":"2970",
    "sg:province":"Antwerpen",
    "wof:name":"Chris Vanden Wijngaert",
    "wof:placetype":"venue"
},
  "geometry": {"coordinates":[4.6133680344,51.2769241333],"type":"Point"}
}