{
  "type": "Feature",
  "properties": {
    "addr:full":"Oudenaardsesteenweg 8 Erpe-mere Oost-Vlaanderen 9420",
    "addr:housenumber":"8",
    "addr:postcode":"9420",
    "addr:street":"Oudenaardsesteenweg",
    "iso:country":"BE",
    "sg:address":"Oudenaardsesteenweg 8",
    "sg:city":"Erpe-mere",
    "sg:classifiers":[
        {
            "category":"Autos & Motor Vehicles",
            "subcategory":"Fuel & Gas Station",
            "type":"Retail Goods"
        }
    ],
    "sg:phone":"+32 53 80 05 78",
    "sg:postcode":"9420",
    "sg:province":"Oost-Vlaanderen",
    "sg:tags":[
        "stations-service",
        "carburants"
    ],
    "wof:name":"Texaco",
    "wof:placetype":"venue"
},
  "geometry": {"coordinates":[3.9918138981,50.9416923523],"type":"Point"}
}