{
  "type": "Feature",
  "properties": {
    "iso:country":"BE",
    "sg:address":"Rue Emile Vandervelde 101",
    "sg:city":"Ans",
    "sg:orig_category":"Diensten voor huisdieren",
    "sg:phone":"+32 4 239 12 60",
    "sg:postcode":"4431",
    "sg:province":"Li\u00e8ge",
    "wof:name":"Toilettage Actual Doggy",
    "wof:placetype":"venue"
},
  "geometry": {"coordinates":[5.5060749054,50.6585083008],"type":"Point"}
}