{
  "type": "Feature",
  "properties": {
    "addr:full":"Gatti De Gamondstraat 174 Ukkel/uccle Bruxelles-Capitale 1180",
    "addr:housenumber":"174",
    "addr:postcode":"1180",
    "addr:street":"Gamondstraat;/",
    "iso:country":"BE",
    "sg:address":"Gatti De Gamondstraat 174",
    "sg:city":"Ukkel/uccle",
    "sg:orig_category":"Advocaten and juridische adviseurs",
    "sg:phone":"+32 2 376 43 59",
    "sg:postcode":"1180",
    "sg:province":"Bruxelles-Capitale",
    "wof:name":"M. Gaillard",
    "wof:placetype":"venue"
},
  "geometry": {"coordinates":[4.3276648521,50.8009681702],"type":"Point"}
}