{
  "type": "Feature",
  "properties": {
    "iso:country":"BE",
    "sg:address":"Faubourg De Lille 4",
    "sg:city":"Komen-waasten/comines-warneton",
    "sg:classifiers":[
        {
            "category":"Home & Garden",
            "subcategory":"Carpets & Floor Coverings",
            "type":"Retail Goods"
        }
    ],
    "sg:phone":"+32 56 55 59 30",
    "sg:postcode":"7784",
    "sg:province":"Hainaut",
    "sg:tags":[
        "l\u00e9gumes",
        "fruit",
        "gr"
    ],
    "wof:name":"Werner Dhantschotter",
    "wof:placetype":"venue"
},
  "geometry": {"coordinates":[2.9414350986,50.7495651245],"type":"Point"}
}