{
  "type": "Feature",
  "properties": {
    "iso:country":"BE",
    "sg:address":"Koning Albertstraat 23",
    "sg:city":"Lint",
    "sg:orig_category":"Diverse bedrijfsbeheeradviesbureaus",
    "sg:phone":"+32 3 455 07 27",
    "sg:postcode":"2547",
    "sg:province":"Antwerpen",
    "wof:name":"Rowley Roevens Associates",
    "wof:placetype":"venue"
},
  "geometry": {"coordinates":[4.4953341484,51.1275672913],"type":"Point"}
}