{
  "type": "Feature",
  "properties": {
    "iso:country":"BE",
    "sg:address":"Rue De Bois Seigneur Isaac 40",
    "sg:city":"Braine L'alleud (ophain-bois-seigneur-isaac)",
    "sg:classifiers":[
        {
            "category":"Organizations",
            "subcategory":"Professional Association",
            "type":"Services"
        }
    ],
    "sg:phone":"+32 2 389 07 50",
    "sg:postcode":"1421",
    "sg:province":"Brabant Wallon",
    "sg:tags":[
        "organisation",
        "seminar"
    ],
    "wof:name":"Del Goutte (espace)",
    "wof:placetype":"venue"
},
  "geometry": {"coordinates":[4.3260340691,50.6664619446],"type":"Point"}
}