{
  "type": "Feature",
  "properties": {
    "addr:full":"Poel 8 Gent Oost-Vlaanderen 9000",
    "addr:housenumber":"8",
    "addr:postcode":"9000",
    "addr:street":"Poel;Oost-Vlaanderen",
    "iso:country":"BE",
    "sg:address":"Poel 8",
    "sg:city":"Gent",
    "sg:orig_category":"S\u00e9curit\u00e9 sociale",
    "sg:phone":"+32 9 225 51 85",
    "sg:postcode":"9000",
    "sg:province":"Oost-Vlaanderen",
    "wof:name":"Christelijke Mutualiteit",
    "wof:placetype":"venue"
},
  "geometry": {"coordinates":[3.7177510262,51.0543937683],"type":"Point"}
}