{
  "type": "Feature",
  "properties": {
    "addr:full":"Bilkske 48 Brugge West-Vlaanderen 8000",
    "addr:housenumber":"48",
    "addr:postcode":"8000",
    "addr:street":"Bilkske",
    "iso:country":"BE",
    "sg:address":"Bilkske 48",
    "sg:city":"Brugge",
    "sg:orig_category":"Installatie van houten of kunststof schrijnwerk Installatie van metalen schrijnwerk",
    "sg:phone":"+32 50 34 09 06",
    "sg:postcode":"8000",
    "sg:province":"West-Vlaanderen",
    "wof:name":"Agso",
    "wof:placetype":"venue"
},
  "geometry": {"coordinates":[3.2374930382,51.2080574036],"type":"Point"}
}