{
  "type": "Feature",
  "properties": {
    "iso:country":"BE",
    "sg:address":"Willem Elsschotstraat 1",
    "sg:city":"Vilvoorde",
    "sg:orig_category":"Agences d'exp\u00e9dition",
    "sg:phone":"+32 2 255 64 11",
    "sg:postcode":"1800",
    "sg:province":"Vlaams-Brabant",
    "wof:name":"Intertrans",
    "wof:placetype":"venue"
},
  "geometry": {"coordinates":[4.427341938,50.9393234253],"type":"Point"}
}