{
  "type": "Feature",
  "properties": {
    "addr:full":"Collegestraat 37 Herentals Antwerpen 2200",
    "addr:housenumber":"37",
    "addr:postcode":"2200",
    "addr:street":"Collegestraat",
    "iso:country":"BE",
    "sg:address":"Collegestraat 37",
    "sg:city":"Herentals",
    "sg:classifiers":[
        {
            "category":"Education",
            "subcategory":"School",
            "type":"Public Place"
        }
    ],
    "sg:phone":"+32 14 30 74 73",
    "sg:postcode":"2200",
    "sg:province":"Antwerpen",
    "sg:tags":[
        "primary"
    ],
    "wof:name":"Katholiek Onderwijs Stad Herentals",
    "wof:placetype":"venue"
},
  "geometry": {"coordinates":[4.8333859444,51.1766853333],"type":"Point"}
}