{
  "type": "Feature",
  "properties": {
    "addr:full":"Rue Du Roi Chevalier 2 Leuze-en-hainaut (willaupuis) Hainaut 7904",
    "addr:housenumber":"2;7904",
    "addr:street":"Rue Du Roi Chevalier;Willaupuis Hainaut",
    "iso:country":"BE",
    "sg:address":"Rue Du Roi Chevalier 2",
    "sg:city":"Leuze-en-hainaut (willaupuis)",
    "sg:classifiers":[
        {
            "category":"Building & Trades",
            "subcategory":"Equipment Rental",
            "type":"Services"
        }
    ],
    "sg:phone":"+32 69 66 25 09",
    "sg:postcode":"7904",
    "sg:province":"Hainaut",
    "sg:tags":[
        "sound",
        "-",
        "system"
    ],
    "wof:name":"City Sound",
    "wof:placetype":"venue"
},
  "geometry": {"coordinates":[3.6030330658,50.566242218],"type":"Point"}
}