{
  "type": "Feature",
  "properties": {
    "iso:country":"BE",
    "sg:address":"Molenstraat 45 Box 6",
    "sg:city":"Aalst",
    "sg:classifiers":[
        {
            "category":"Building & Trades",
            "subcategory":"Construction",
            "type":"Services"
        }
    ],
    "sg:phone":"+32 53 78 18 81",
    "sg:postcode":"9300",
    "sg:province":"Oost-Vlaanderen",
    "sg:tags":[
        "tapestry"
    ],
    "wof:name":"De Gaepaert",
    "wof:placetype":"venue"
},
  "geometry": {"coordinates":[4.0419268608,50.9390563965],"type":"Point"}
}