{
  "type": "Feature",
  "properties": {
    "addr:full":"Wijtschatestraat 39 Heuvelland West-Vlaanderen 8950",
    "addr:housenumber":"39",
    "addr:postcode":"8950",
    "addr:street":"Wijtschatestraat",
    "iso:country":"BE",
    "sg:address":"Wijtschatestraat 39",
    "sg:city":"Heuvelland",
    "sg:orig_category":"Immobili\u00ebnkantoren Verzekeringsmakelaars and experts",
    "sg:phone":"+32 57 44 64 46",
    "sg:postcode":"8950",
    "sg:province":"West-Vlaanderen",
    "wof:name":"Vlimm",
    "wof:placetype":"venue"
},
  "geometry": {"coordinates":[2.825979948,50.74634552],"type":"Point"}
}