{
  "type": "Feature",
  "properties": {
    "addr:full":"Wayai 53 Jalhay Li\u00e8ge 4845",
    "addr:housenumber":"53",
    "addr:postcode":"4845",
    "addr:street":"Wayai",
    "iso:country":"BE",
    "sg:address":"Wayai 53",
    "sg:city":"Jalhay",
    "sg:classifiers":[
        {
            "category":"Recreation",
            "type":"Entertainment"
        }
    ],
    "sg:phone":"+32 87 47 52 18",
    "sg:postcode":"4845",
    "sg:province":"Li\u00e8ge",
    "sg:tags":[
        "diver",
        "amusement"
    ],
    "wof:name":"D.j. Moustique",
    "wof:placetype":"venue"
},
  "geometry": {"coordinates":[5.9508261681,50.5039138794],"type":"Point"}
}