{
  "type": "Feature",
  "properties": {
    "iso:country":"BE",
    "sg:address":"Leuvensesteenweg 42",
    "sg:city":"Aarschot (gelrode)",
    "sg:classifiers":[
        {
            "category":"Health Services",
            "subcategory":"Dentist",
            "type":"Services"
        }
    ],
    "sg:phone":"+32 16 56 05 60",
    "sg:postcode":"3200",
    "sg:province":"Vlaams-Brabant",
    "wof:name":"Asselberghs W",
    "wof:placetype":"venue"
},
  "geometry": {"coordinates":[4.8230700493,50.9806289673],"type":"Point"}
}