{
  "type": "Feature",
  "properties": {
    "addr:full":"Osylei 20 Mortsel Antwerpen 2640",
    "addr:housenumber":"20",
    "addr:postcode":"2640",
    "addr:street":"Osylei",
    "iso:country":"BE",
    "sg:address":"Osylei 20",
    "sg:city":"Mortsel",
    "sg:classifiers":[
        {
            "category":"Shopping",
            "subcategory":"Jewelry",
            "type":"Retail Goods"
        }
    ],
    "sg:phone":"+32 3 449 79 00",
    "sg:postcode":"2640",
    "sg:province":"Antwerpen",
    "sg:tags":[
        "fab",
        "bijou"
    ],
    "wof:name":"Defosse En Zoon",
    "wof:placetype":"venue"
},
  "geometry": {"coordinates":[4.4502000809,51.1808242798],"type":"Point"}
}