{
  "type": "Feature",
  "properties": {
    "iso:country":"BE",
    "sg:address":"Moleneinde 5",
    "sg:city":"Dendermonde (schoonaarde)",
    "sg:classifiers":[
        {
            "category":"Health Services",
            "subcategory":"Health Practitioner",
            "type":"Services"
        }
    ],
    "sg:phone":"+32 52 42 34 66",
    "sg:postcode":"9200",
    "sg:province":"Oost-Vlaanderen",
    "sg:tags":[
        "physiotherapist"
    ],
    "wof:name":"Cooreman Theo",
    "wof:placetype":"venue"
},
  "geometry": {"coordinates":[4.0152797699,51.003692627],"type":"Point"}
}