{
  "type": "Feature",
  "properties": {
    "addr:full":"Wouwerstraat 5 Hemiksem Antwerpen 2620",
    "addr:housenumber":"5",
    "addr:postcode":"2620",
    "addr:street":"Wouwerstraat",
    "iso:country":"BE",
    "sg:address":"Wouwerstraat 5",
    "sg:city":"Hemiksem",
    "sg:classifiers":[
        {
            "category":"Cafe",
            "type":"Food & Drink"
        }
    ],
    "sg:phone":"+32 3 887 62 62",
    "sg:postcode":"2620",
    "sg:province":"Antwerpen",
    "sg:tags":[
        "caf\u00e9s"
    ],
    "wof:name":"Caf\u00c9 Zonnestraal",
    "wof:placetype":"venue"
},
  "geometry": {"coordinates":[4.3391737938,51.1407241821],"type":"Point"}
}