{
  "type": "Feature",
  "properties": {
    "iso:country":"BE",
    "sg:address":"Gasthuisstraat 7 Box 7",
    "sg:city":"Asse",
    "sg:classifiers":[
        {
            "category":"Social Services",
            "type":"Services"
        }
    ],
    "sg:phone":"+32 2 453 06 29",
    "sg:postcode":"1730",
    "sg:province":"Vlaams-Brabant",
    "sg:tags":[
        "handicapped",
        "-"
    ],
    "wof:name":"Hopperank Vzw",
    "wof:placetype":"venue"
},
  "geometry": {"coordinates":[4.2008700371,50.912071228],"type":"Point"}
}