{
  "type": "Feature",
  "properties": {
    "addr:full":"Rue De Sclessin 24 Li\u00e8ge 1 Li\u00e8ge 4000",
    "addr:housenumber":"24;1",
    "addr:postcode":"4000",
    "addr:street":"Rue De Sclessin",
    "iso:country":"BE",
    "sg:address":"Rue De Sclessin 24",
    "sg:city":"Li\u00e8ge 1",
    "sg:classifiers":[
        {
            "category":"Professional",
            "subcategory":"Management & Consulting",
            "type":"Services"
        }
    ],
    "sg:phone":"+32 4 252 65 29",
    "sg:postcode":"4000",
    "sg:province":"Li\u00e8ge",
    "sg:tags":[
        "consultant"
    ],
    "wof:name":"C.m.k. Consult Sprl",
    "wof:placetype":"venue"
},
  "geometry": {"coordinates":[5.5693039894,50.6251449585],"type":"Point"}
}