{
  "type": "Feature",
  "properties": {
    "addr:full":"Eierstraat 36 Harelbeke West-Vlaanderen 8530",
    "addr:housenumber":"36",
    "addr:postcode":"8530",
    "addr:street":"Eierstraat",
    "iso:country":"BE",
    "sg:address":"Eierstraat 36",
    "sg:city":"Harelbeke",
    "sg:classifiers":[
        {
            "category":"Retail",
            "subcategory":"Auto Repair",
            "type":"Services"
        }
    ],
    "sg:phone":"+32 56 71 10 46",
    "sg:postcode":"8530",
    "sg:province":"West-Vlaanderen",
    "sg:tags":[
        "garage"
    ],
    "wof:name":"Vanassche Dominiek",
    "wof:placetype":"venue"
},
  "geometry": {"coordinates":[3.3071510792,50.861240387],"type":"Point"}
}