{
  "type": "Feature",
  "properties": {
    "addr:full":"Noordstraat 86 Roeselare West-Vlaanderen 8800",
    "addr:housenumber":"86",
    "addr:postcode":"8800",
    "addr:street":"Noordstraat",
    "iso:country":"BE",
    "sg:address":"Noordstraat 86",
    "sg:city":"Roeselare",
    "sg:orig_category":"Rookartikelen",
    "sg:phone":"+32 51 20 07 37",
    "sg:postcode":"8800",
    "sg:province":"West-Vlaanderen",
    "wof:name":"Fa. Tabarin",
    "wof:placetype":"venue"
},
  "geometry": {"coordinates":[3.1220860481,50.9476852417],"type":"Point"}
}