{
  "type": "Feature",
  "properties": {
    "addr:full":"Delaunoystraat 135 Sint-jans-molenbeek/molenbeek-saint-jean Bruxelles-Capitale 1080",
    "addr:housenumber":"135;/",
    "addr:postcode":"1080",
    "addr:street":"Delaunoystraat;Sint-Jans-Molenbeek",
    "iso:country":"BE",
    "sg:address":"Delaunoystraat 135",
    "sg:city":"Sint-jans-molenbeek/molenbeek-saint-jean",
    "sg:orig_category":"Brood, gebak and snoepgoed Kantoormateriaal Krantenwinkels Rookartikelen",
    "sg:phone":"+32 2 410 78 11",
    "sg:postcode":"1080",
    "sg:province":"Bruxelles-Capitale",
    "wof:name":"Librairie Delgleize",
    "wof:placetype":"venue"
},
  "geometry": {"coordinates":[4.3300261497,50.8533973694],"type":"Point"}
}