{
  "type": "Feature",
  "properties": {
    "addr:full":"Avenue Des Bouleaux 23 Grez-doiceau Brabant Wallon 1390",
    "addr:housenumber":"23",
    "addr:postcode":"1390",
    "addr:street":"Avenue Des Bouleaux",
    "iso:country":"BE",
    "sg:address":"Avenue Des Bouleaux 23",
    "sg:city":"Grez-doiceau",
    "sg:classifiers":[
        {
            "category":"Professional",
            "subcategory":"Printing & Photocopies",
            "type":"Services"
        }
    ],
    "sg:phone":"+32 10 68 71 02",
    "sg:postcode":"1390",
    "sg:province":"Brabant Wallon",
    "sg:tags":[
        "-",
        "publishing",
        "desktop"
    ],
    "wof:name":"Chs International",
    "wof:placetype":"venue"
},
  "geometry": {"coordinates":[4.7179260254,50.7237129211],"type":"Point"}
}