{
  "type": "Feature",
  "properties": {
    "iso:country":"BE",
    "sg:address":"Adolf Stocletlaan 87",
    "sg:city":"Duffel",
    "sg:classifiers":[
        {
            "category":"Manufacturing",
            "subcategory":"Metals",
            "type":"Manufacturing & Wholesale Goods"
        }
    ],
    "sg:phone":"+32 15 30 21 11",
    "sg:postcode":"2570",
    "sg:province":"Antwerpen",
    "sg:tags":[
        "metallurgy",
        "steel",
        "metalworking"
    ],
    "wof:name":"Corus Aluminium Service Center Nv",
    "wof:placetype":"venue"
},
  "geometry": {"coordinates":[4.4820141792,51.0863342285],"type":"Point"}
}