{
  "type": "Feature",
  "properties": {
    "addr:full":"Rue Devreux 12bis Mons (cuesmes) Hainaut 7033",
    "addr:housenumber":"12bis",
    "addr:postcode":"7033",
    "addr:street":"Rue Devreux",
    "iso:country":"BE",
    "sg:address":"Rue Devreux 12bis",
    "sg:city":"Mons (cuesmes)",
    "sg:classifiers":[
        {
            "category":"Retail",
            "subcategory":"Repair Shop",
            "type":"Services"
        }
    ],
    "sg:phone":"+32 65 35 34 03",
    "sg:postcode":"7033",
    "sg:province":"Hainaut",
    "sg:tags":[
        "denture"
    ],
    "wof:name":"Belladent Sprl",
    "wof:placetype":"venue"
},
  "geometry": {"coordinates":[3.9253261089,50.4366378784],"type":"Point"}
}