{
  "type": "Feature",
  "properties": {
    "addr:full":"Rue De La Strat\u00c9gie 25 Oudergem Bruxelles-Capitale 1160",
    "addr:housenumber":"25",
    "addr:postcode":"1160",
    "addr:street":"Rue De La Strate\u0301Gie",
    "iso:country":"BE",
    "sg:address":"Rue De La Strat\u00c9gie 25",
    "sg:city":"Oudergem",
    "sg:orig_category":"Installation de menuiserie en bois and plastique. Construction de maisons",
    "sg:phone":"+32 2 640 38 92",
    "sg:postcode":"1160",
    "sg:province":"Bruxelles-Capitale",
    "wof:name":"Wood And Light",
    "wof:placetype":"venue"
},
  "geometry": {"coordinates":[4.4006748199,50.8232154846],"type":"Point"}
}