{
  "type": "Feature",
  "properties": {
    "addr:full":"Ardooisesteenweg 4 Roeselare West-Vlaanderen 8800",
    "addr:housenumber":"4",
    "addr:postcode":"8800",
    "addr:street":"Ardooisesteenweg",
    "iso:country":"BE",
    "sg:address":"Ardooisesteenweg 4",
    "sg:city":"Roeselare",
    "sg:orig_category":"Centres de relaxation and bien-\u00eatre. Instituts de beaut\u00e9",
    "sg:phone":"+32 51 20 79 56",
    "sg:postcode":"8800",
    "sg:province":"West-Vlaanderen",
    "wof:name":"Schoonheidsinstituut Sissi",
    "wof:placetype":"venue"
},
  "geometry": {"coordinates":[3.1311380863,50.9486122131],"type":"Point"}
}