{
  "type": "Feature",
  "properties": {
    "addr:full":"Place De La Gare 3 Jemeppe-sur-sambre Namur 5190",
    "addr:housenumber":"3",
    "addr:postcode":"5190",
    "addr:street":"Place De La Gare",
    "iso:country":"BE",
    "sg:address":"Place De La Gare 3",
    "sg:city":"Jemeppe-sur-sambre",
    "sg:classifiers":[
        {
            "category":"Fast Food",
            "type":"Food & Drink"
        }
    ],
    "sg:phone":"+32 71 78 80 55",
    "sg:postcode":"5190",
    "sg:province":"Namur",
    "sg:tags":[
        "\u00c0",
        "emporter",
        "restaurants"
    ],
    "wof:name":"Pizzeria Valentino",
    "wof:placetype":"venue"
},
  "geometry": {"coordinates":[4.6951618195,50.4531211853],"type":"Point"}
}