{
  "type": "Feature",
  "properties": {
    "iso:country":"BE",
    "sg:address":"Boulevard De L'europe",
    "sg:city":"Wavre",
    "sg:orig_category":"Rev\u00eatements de sols and murs. Rev\u00eatements pour sols and murs",
    "sg:phone":"+32 10 23 04 90",
    "sg:postcode":"1300",
    "sg:province":"Brabant Wallon",
    "wof:name":"Ceramega",
    "wof:placetype":"venue"
},
  "geometry": {"coordinates":[4.6094279289,50.7138824463],"type":"Point"}
}