{
  "type": "Feature",
  "properties": {
    "iso:country":"BE",
    "sg:address":"Boulevard D'avroy 65b93",
    "sg:city":"Li\u00c8ge",
    "sg:orig_category":"Agences immobili\u00e8res. Evaluation and estimation de biens immobiliers",
    "sg:phone":"+32 4 221 30 86",
    "sg:postcode":"4000",
    "sg:province":"Li\u00e8ge",
    "wof:name":"Bureau Imbel",
    "wof:placetype":"venue"
},
  "geometry": {"coordinates":[5.5693998337,50.6402435303],"type":"Point"}
}