{
  "type": "Feature",
  "properties": {
    "addr:full":"Rue Des Acacias 39 Saint-georges-sur-meuse Li\u00e8ge 4470",
    "addr:housenumber":"39",
    "addr:postcode":"4470",
    "addr:street":"Rue Des Acacias",
    "iso:country":"BE",
    "sg:address":"Rue Des Acacias 39",
    "sg:city":"Saint-georges-sur-meuse",
    "sg:classifiers":[
        {
            "category":"Personal",
            "subcategory":"Nail Salon",
            "type":"Services"
        }
    ],
    "sg:phone":"+32 4 275 67 67",
    "sg:postcode":"4470",
    "sg:province":"Li\u00e8ge",
    "sg:tags":[
        "pedicure"
    ],
    "wof:name":"Gal\u00e8re R",
    "wof:placetype":"venue"
},
  "geometry": {"coordinates":[5.3628578186,50.5768661499],"type":"Point"}
}