{
  "type": "Feature",
  "properties": {
    "iso:country":"BE",
    "sg:address":"Rue Des Lattes 1",
    "sg:city":"Cerfontaine",
    "sg:orig_category":"Rundveehouders",
    "sg:phone":"+32 71 61 15 37",
    "sg:postcode":"5630",
    "sg:province":"Namur",
    "wof:name":"Gerard Galand",
    "wof:placetype":"venue"
},
  "geometry": {"coordinates":[4.4580860138,50.2178382874],"type":"Point"}
}