{
  "type": "Feature",
  "properties": {
    "iso:country":"BE",
    "sg:address":"Avenue Des M\u00fbriers 15",
    "sg:city":"Beloeil (quevaucamps)",
    "sg:classifiers":[
        {
            "category":"Communications",
            "subcategory":"Television Station",
            "type":"Services"
        }
    ],
    "sg:phone":"+32 69 58 08 44",
    "sg:postcode":"7972",
    "sg:province":"Hainaut",
    "sg:tags":[
        "antenna"
    ],
    "wof:name":"Microsat",
    "wof:placetype":"venue"
},
  "geometry": {"coordinates":[3.6921050549,50.5274238586],"type":"Point"}
}