{
  "type": "Feature",
  "properties": {
    "addr:full":"Route D'eghez\u00c9e 47 Jemeppe-sur-sambre Namur 5190",
    "addr:housenumber":"47",
    "addr:postcode":"5190",
    "addr:street":"Route D'Egheze \u0301E",
    "iso:country":"BE",
    "sg:address":"Route D'eghez\u00c9e 47",
    "sg:city":"Jemeppe-sur-sambre",
    "sg:orig_category":"Epuration des eaux",
    "sg:phone":"+32 71 78 51 71",
    "sg:postcode":"5190",
    "sg:province":"Namur",
    "wof:name":"Servais",
    "wof:placetype":"venue"
},
  "geometry": {"coordinates":[4.6638031006,50.4623374939],"type":"Point"}
}