{
  "type": "Feature",
  "properties": {
    "iso:country":"BE",
    "sg:address":"Kapellestraat 74",
    "sg:city":"Oostende",
    "sg:orig_category":"Fleurs and plantes",
    "sg:phone":"+32 59 70 97 63",
    "sg:postcode":"8400",
    "sg:province":"West-Vlaanderen",
    "wof:name":"Naida Flowers",
    "wof:placetype":"venue"
},
  "geometry": {"coordinates":[2.9205420017,51.2288284302],"type":"Point"}
}