{
  "type": "Feature",
  "properties": {
    "addr:full":"130 Rue Franklin 1000 Bruxelles 130",
    "addr:housenumber":"130;130",
    "addr:postcode":"1000",
    "addr:street":"Rue Franklin",
    "iso:country":"BE",
    "sg:address":"130",
    "sg:city":"Rue Franklin 1000 Bruxelles",
    "sg:classifiers":[
        {
            "category":"Wholesale",
            "subcategory":"Machinery & Supplies",
            "type":"Manufacturing & Wholesale Goods"
        }
    ],
    "sg:phone":"+32 2 735 94 92",
    "sg:postcode":"130",
    "sg:tags":[
        "handling",
        "material",
        "-",
        "machine",
        "equipment",
        "engineering",
        "mechanical"
    ],
    "wof:name":"Jacques Reix Sprl",
    "wof:placetype":"venue"
},
  "geometry": {"coordinates":[4.3904500008,50.846786499],"type":"Point"}
}