{
  "type": "Feature",
  "properties": {
    "addr:full":"Willem De Ganckstraat 32 Asse Vlaams-Brabant 1730",
    "addr:housenumber":"32",
    "addr:postcode":"1730",
    "addr:street":"Willem De Ganckstraat",
    "iso:country":"BE",
    "sg:address":"Willem De Ganckstraat 32",
    "sg:city":"Asse",
    "sg:classifiers":[
        {
            "category":"Arena",
            "subcategory":"Sports Club",
            "type":"Entertainment"
        }
    ],
    "sg:phone":"+32 2 452 85 46",
    "sg:postcode":"1730",
    "sg:province":"Vlaams-Brabant",
    "sg:tags":[
        "de"
    ],
    "wof:name":"Op De Plank En Binnen",
    "wof:placetype":"venue"
},
  "geometry": {"coordinates":[4.2477378845,50.9078369141],"type":"Point"}
}