{
  "type": "Feature",
  "properties": {
    "iso:country":"BE",
    "sg:address":"Generaal Dumonceaulaan 40",
    "sg:city":"Vorst/forest",
    "sg:orig_category":"Gespecialiseerde niet-residenti\u00eble bouw Installatie van houten of kunststof schrijnwerk Installatie ",
    "sg:phone":"+32 2 376 51 58",
    "sg:postcode":"1190",
    "sg:province":"Bruxelles-Capitale",
    "wof:name":"Sotra - V.m.",
    "wof:placetype":"venue"
},
  "geometry": {"coordinates":[4.3167848587,50.8066101074],"type":"Point"}
}