{
  "type": "Feature",
  "properties": {
    "iso:country":"BE",
    "sg:address":"Rue Paul Janson 252",
    "sg:city":"Grace-hollogne",
    "sg:orig_category":"Services de Nettoyage and de D\u00e9sinfection",
    "sg:phone":"+32 4 231 20 11",
    "sg:postcode":"4460",
    "sg:province":"Li\u00e8ge",
    "wof:name":"Josue Weytsman",
    "wof:placetype":"venue"
},
  "geometry": {"coordinates":[5.4999570847,50.6254692078],"type":"Point"}
}