{
  "type": "Feature",
  "properties": {
    "iso:country":"BE",
    "sg:address":"Derde Straat 1",
    "sg:city":"Maaseik",
    "sg:classifiers":[
        {
            "category":"Shopping",
            "subcategory":"Clothing, Apparel, & Fashions",
            "type":"Retail Goods"
        }
    ],
    "sg:phone":"+32 89 56 34 96",
    "sg:postcode":"3680",
    "sg:province":"Limburg",
    "sg:tags":[
        "lady",
        "clothing",
        "-"
    ],
    "wof:name":"Thoolen Confectie",
    "wof:placetype":"venue"
},
  "geometry": {"coordinates":[5.7872700691,51.0855903625],"type":"Point"}
}