{
  "type": "Feature",
  "properties": {
    "iso:country":"BE",
    "sg:address":"Ledestraat 34 A",
    "sg:city":"Wannegem-lede",
    "sg:orig_category":"Microsoft. Entretien and r\u00e9parations de machines de bureau and ordinateurs. R\u00e9alisation de programme",
    "sg:phone":"+32 9 383 84 56",
    "sg:postcode":"9772",
    "sg:province":"Oost-Vlaanderen",
    "wof:name":"Solid Systems",
    "wof:placetype":"venue"
},
  "geometry": {"coordinates":[3.57178092,50.89012146],"type":"Point"}
}