{
  "type": "Feature",
  "properties": {
    "iso:country":"BE",
    "sg:address":"Rendekensstraat 27",
    "sg:city":"Heusden",
    "sg:classifiers":[
        {
            "category":"Shopping",
            "subcategory":"Clothing, Apparel, & Fashions",
            "type":"Retail Goods"
        }
    ],
    "sg:phone":"+32 9 230 04 06",
    "sg:postcode":"9070",
    "sg:province":"Oost-Vlaanderen",
    "sg:tags":[
        "textile",
        "clothing",
        "clothes"
    ],
    "wof:name":"Dhr Etienne De Cock",
    "wof:placetype":"venue"
},
  "geometry": {"coordinates":[3.8146278858,51.0382270813],"type":"Point"}
}