{
  "type": "Feature",
  "properties": {
    "addr:full":"Place D\u00b4hautrage 28 Saint-ghislain Hainaut 7334",
    "addr:housenumber":"28",
    "addr:postcode":"7334",
    "addr:street":"Place D\u00b4Hautrage;Hainaut",
    "iso:country":"BE",
    "sg:address":"Place D\u00b4hautrage 28",
    "sg:city":"Saint-ghislain",
    "sg:orig_category":"Slagers",
    "sg:phone":"+32 65 62 25 57",
    "sg:postcode":"7334",
    "sg:province":"Hainaut",
    "wof:name":"Boucherie Nino",
    "wof:placetype":"venue"
},
  "geometry": {"coordinates":[3.7644500732,50.479675293],"type":"Point"}
}