{
  "type": "Feature",
  "properties": {
    "iso:country":"BE",
    "sg:address":"Lange Zoutstraat 11",
    "sg:city":"Aalst",
    "sg:classifiers":[
        {
            "category":"Shopping",
            "subcategory":"Shoes",
            "type":"Retail Goods"
        }
    ],
    "sg:phone":"+32 53 70 60 87",
    "sg:postcode":"9300",
    "sg:province":"Oost-Vlaanderen",
    "sg:tags":[
        "slipper",
        "-"
    ],
    "wof:name":"Buffalo Junior (the)",
    "wof:placetype":"venue"
},
  "geometry": {"coordinates":[4.0390768051,50.937713623],"type":"Point"}
}