{
  "type": "Feature",
  "properties": {
    "addr:full":"Rue Du Tige 34 Ciney Namur 5590",
    "addr:housenumber":"34",
    "addr:postcode":"5590",
    "addr:street":"Rue Du Tige",
    "iso:country":"BE",
    "sg:address":"Rue Du Tige 34",
    "sg:city":"Ciney",
    "sg:orig_category":"Artsen and specialisten",
    "sg:phone":"+32 83 21 26 86",
    "sg:postcode":"5590",
    "sg:province":"Namur",
    "wof:name":"C. Br\u00c9dart",
    "wof:placetype":"venue"
},
  "geometry": {"coordinates":[5.1022520065,50.297088623],"type":"Point"}
}