{
  "type": "Feature",
  "properties": {
    "iso:country":"BE",
    "sg:address":"Tarweland 17",
    "sg:city":"Rotselaar",
    "sg:orig_category":"Dierenartsen",
    "sg:phone":"+32 16 60 58 59",
    "sg:postcode":"3118",
    "sg:province":"Vlaams-Brabant",
    "wof:name":"Gisele Thirionet",
    "wof:placetype":"venue"
},
  "geometry": {"coordinates":[4.6940898895,50.970489502],"type":"Point"}
}