{
  "type": "Feature",
  "properties": {
    "iso:country":"BE",
    "sg:address":"Stoofstraat 26",
    "sg:city":"Merchtem",
    "sg:orig_category":"M\u00e9decins and sp\u00e9cialistes",
    "sg:phone":"+32 52 37 27 66",
    "sg:postcode":"1785",
    "sg:province":"Vlaams-Brabant",
    "wof:name":"Teresia Saerens",
    "wof:placetype":"venue"
},
  "geometry": {"coordinates":[4.2334399223,50.9567985535],"type":"Point"}
}