{
  "type": "Feature",
  "properties": {
    "addr:full":"Moerenstraat 75 Arendonk Antwerpen 2370",
    "addr:housenumber":"75",
    "addr:postcode":"2370",
    "addr:street":"Moerenstraat",
    "iso:country":"BE",
    "sg:address":"Moerenstraat 75",
    "sg:city":"Arendonk",
    "sg:orig_category":"Huisdierenkwekers",
    "sg:phone":"+32 14 67 90 20",
    "sg:postcode":"2370",
    "sg:province":"Antwerpen",
    "wof:name":"Kennel Vom Royshof",
    "wof:placetype":"venue"
},
  "geometry": {"coordinates":[5.1137099266,51.3194503784],"type":"Point"}
}