{
  "type": "Feature",
  "properties": {
    "addr:full":"Torenpark 51 Deinze Oost-Vlaanderen 9800",
    "addr:housenumber":"51",
    "addr:postcode":"9800",
    "addr:street":"Torenpark",
    "iso:country":"BE",
    "sg:address":"Torenpark 51",
    "sg:city":"Deinze",
    "sg:classifiers":[
        {
            "category":"Shopping",
            "subcategory":"Crafts & Fabrics",
            "type":"Retail Goods"
        }
    ],
    "sg:phone":"+32 9 386 18 41",
    "sg:postcode":"9800",
    "sg:province":"Oost-Vlaanderen",
    "sg:tags":[
        "textile",
        "clothing"
    ],
    "wof:name":"Marc Van Hulle Nv",
    "wof:placetype":"venue"
},
  "geometry": {"coordinates":[3.530174017,50.9863166809],"type":"Point"}
}