{
  "type": "Feature",
  "properties": {
    "iso:country":"BE",
    "sg:address":"Hubertusplein 2",
    "sg:city":"Asse",
    "sg:classifiers":[
        {
            "category":"Shopping",
            "subcategory":"Bicycles & Sporting Goods",
            "type":"Retail Goods"
        }
    ],
    "sg:phone":"+32 2 453 12 77",
    "sg:postcode":"1730",
    "sg:province":"Vlaams-Brabant",
    "sg:tags":[
        "article",
        "de",
        "sport",
        "camping"
    ],
    "wof:name":"Ruitershop Verhulst",
    "wof:placetype":"venue"
},
  "geometry": {"coordinates":[4.1572618484,50.9182014465],"type":"Point"}
}