{
  "type": "Feature",
  "properties": {
    "iso:country":"BE",
    "sg:address":"Fortlaan 10",
    "sg:city":"Zwijndrecht",
    "sg:orig_category":"Sportcentra Sportterreinen and installaties behalve sportcentra",
    "sg:phone":"+32 3 253 15 16",
    "sg:postcode":"2070",
    "sg:province":"Antwerpen",
    "wof:name":"Sportcentrum Zwijndrecht",
    "wof:placetype":"venue"
},
  "geometry": {"coordinates":[4.3277931213,51.2142524719],"type":"Point"}
}