{
  "type": "Feature",
  "properties": {
    "iso:country":"BE",
    "sg:address":"Rue Konkel 127",
    "sg:city":"Sint-pieters-woluwe/woluwe-saint-pierre",
    "sg:orig_category":"M\u00e9decins and sp\u00e9cialistes",
    "sg:phone":"+32 2 772 54 91",
    "sg:postcode":"1150",
    "sg:province":"Bruxelles-Capitale",
    "wof:name":"I. Ramallo Pallast",
    "wof:placetype":"venue"
},
  "geometry": {"coordinates":[4.4464001656,50.838809967],"type":"Point"}
}