{
  "type": "Feature",
  "properties": {
    "addr:full":"Izegemsestraat 133 Roeselare (rumbeke) West-Vlaanderen 8800",
    "addr:housenumber":"133",
    "addr:postcode":"8800",
    "addr:street":"Izegemsestraat",
    "iso:country":"BE",
    "sg:address":"Izegemsestraat 133",
    "sg:city":"Roeselare (rumbeke)",
    "sg:classifiers":[
        {
            "category":"Manufacturing",
            "subcategory":"Motor Vehicles & Parts",
            "type":"Manufacturing & Wholesale Goods"
        }
    ],
    "sg:phone":"+32 51 25 22 33",
    "sg:postcode":"8800",
    "sg:province":"West-Vlaanderen",
    "sg:tags":[
        "body",
        "automobile",
        "construction",
        "-"
    ],
    "wof:name":"A & D Trucks En Trailers",
    "wof:placetype":"venue"
},
  "geometry": {"coordinates":[3.1715419292,50.930770874],"type":"Point"}
}