{
  "type": "Feature",
  "properties": {
    "addr:full":"Rue St-denis 325 Vorst/forest Bruxelles-Capitale 1190",
    "addr:housenumber":"325",
    "addr:postcode":"1190",
    "addr:street":"Rue St-Denis;/ Forest",
    "iso:country":"BE",
    "sg:address":"Rue St-denis 325",
    "sg:city":"Vorst/forest",
    "sg:orig_category":"Pi\u00e8ces and accessoires de v\u00e9hicules automobiles Gr",
    "sg:phone":"+32 2 341 12 41",
    "sg:postcode":"1190",
    "sg:province":"Bruxelles-Capitale",
    "wof:name":"Centuri Service Rapide/centuri Snelservice",
    "wof:placetype":"venue"
},
  "geometry": {"coordinates":[4.3210811615,50.8194580078],"type":"Point"}
}