{
  "type": "Feature",
  "properties": {
    "iso:country":"BE",
    "sg:address":"Antwerpsesteenweg 135",
    "sg:city":"Vosselaar",
    "sg:orig_category":"Electrom\u00e9nager, t\u00e9l\u00e9visions and radios. R\u00e9parations d'appareils \u00e9lectrom\u00e9nagers",
    "sg:phone":"+32 14 61 23 05",
    "sg:postcode":"2350",
    "sg:province":"Antwerpen",
    "wof:name":"Hejo",
    "wof:placetype":"venue"
},
  "geometry": {"coordinates":[4.8885779381,51.3147087097],"type":"Point"}
}