{
  "type": "Feature",
  "properties": {
    "addr:full":"Sint-truiderstraat 38 Tongeren Limburg 3700",
    "addr:housenumber":"38",
    "addr:postcode":"3700",
    "addr:street":"Sint-Truiderstraat",
    "iso:country":"BE",
    "sg:address":"Sint-truiderstraat 38",
    "sg:city":"Tongeren",
    "sg:classifiers":[
        {
            "category":"Shopping",
            "subcategory":"Clothing, Apparel, & Fashions",
            "type":"Retail Goods"
        }
    ],
    "sg:phone":"+32 12 26 13 29",
    "sg:postcode":"3700",
    "sg:province":"Limburg",
    "sg:tags":[
        "boutique"
    ],
    "wof:name":"Connection",
    "wof:placetype":"venue"
},
  "geometry": {"coordinates":[5.4613118172,50.7800865173],"type":"Point"}
}