{
  "type": "Feature",
  "properties": {
    "addr:full":"Willem Van Doornyckstr. 78 Beveren Oost-Vlaanderen 9120",
    "addr:housenumber":"78",
    "addr:postcode":"9120",
    "addr:street":"Willem Van Doornyckstr.",
    "iso:country":"BE",
    "sg:address":"Willem Van Doornyckstr. 78",
    "sg:city":"Beveren",
    "sg:orig_category":"Boissons",
    "sg:phone":"+32 3 775 78 92",
    "sg:postcode":"9120",
    "sg:province":"Oost-Vlaanderen",
    "wof:name":"De Vogel A & Zoon",
    "wof:placetype":"venue"
},
  "geometry": {"coordinates":[4.2332668304,51.1796607971],"type":"Point"}
}