{
  "type": "Feature",
  "properties": {
    "addr:full":"Vuurkruiserslaan 12 Izegem West-Vlaanderen 8870",
    "addr:housenumber":"12",
    "addr:postcode":"8870",
    "addr:street":"Vuurkruiserslaan",
    "iso:country":"BE",
    "sg:address":"Vuurkruiserslaan 12",
    "sg:city":"Izegem",
    "sg:classifiers":[
        {
            "category":"Health Services",
            "subcategory":"Health Practitioner",
            "type":"Services"
        }
    ],
    "sg:phone":"+32 51 30 47 14",
    "sg:postcode":"8870",
    "sg:province":"West-Vlaanderen",
    "sg:tags":[
        "physiotherapist"
    ],
    "wof:name":"Deplancke Ann",
    "wof:placetype":"venue"
},
  "geometry": {"coordinates":[3.1898601055,50.922996521],"type":"Point"}
}