{
  "type": "Feature",
  "properties": {
    "addr:full":"G. Levisstraat 2 Vilvorde Vlaams-Brabant 1800",
    "addr:housenumber":"2",
    "addr:postcode":"1800",
    "addr:street":"Levisstraat",
    "iso:country":"BE",
    "sg:address":"G. Levisstraat 2",
    "sg:city":"Vilvorde",
    "sg:orig_category":"Mat\u00e9riaux de construction Gr",
    "sg:phone":"+32 2 254 22 11",
    "sg:postcode":"1800",
    "sg:province":"Vlaams-Brabant",
    "wof:name":"Akzo Nobel Decorative Coatings",
    "wof:placetype":"venue"
},
  "geometry": {"coordinates":[4.442595005,50.926158905],"type":"Point"}
}