{
  "type": "Feature",
  "properties": {
    "iso:country":"BE",
    "sg:address":"Zespenningenstraat 56",
    "sg:city":"Brussel/bruxelles",
    "sg:orig_category":"Verplichte sociale verzekeringen",
    "sg:phone":"+32 2 512 11 67",
    "sg:postcode":"1000",
    "sg:province":"Bruxelles-Capitale",
    "wof:name":"Mutualit\u00c9 Lib\u00c9rale",
    "wof:placetype":"venue"
},
  "geometry": {"coordinates":[4.3439970016,50.8470687866],"type":"Point"}
}