{
  "type": "Feature",
  "properties": {
    "addr:full":"Place Du Grand Sablon 35 Brussel/bruxelles Bruxelles-Capitale 1000",
    "addr:housenumber":"35",
    "addr:postcode":"1000",
    "addr:street":"Place Du Grand Sablon;/",
    "iso:country":"BE",
    "sg:address":"Place Du Grand Sablon 35",
    "sg:city":"Brussel/bruxelles",
    "sg:orig_category":"Antiquit\u00e9s. Services divers aux entreprises. Assurances. Salles de spectacles",
    "sg:phone":"+32 2 511 37 04",
    "sg:postcode":"1000",
    "sg:province":"Bruxelles-Capitale",
    "wof:name":"Galerie D'huysser",
    "wof:placetype":"venue"
},
  "geometry": {"coordinates":[4.3546490669,50.8406906128],"type":"Point"}
}