{
  "type": "Feature",
  "properties": {
    "addr:full":"Rijselstraat 182 Menen West-Vlaanderen 8930",
    "addr:housenumber":"182",
    "addr:postcode":"8930",
    "addr:street":"Rijselstraat",
    "iso:country":"BE",
    "sg:address":"Rijselstraat 182",
    "sg:city":"Menen",
    "sg:classifiers":[
        {
            "category":"Cafe",
            "type":"Food & Drink"
        }
    ],
    "sg:phone":"+32 56 51 73 25",
    "sg:postcode":"8930",
    "sg:province":"West-Vlaanderen",
    "sg:tags":[
        "caf\u00e9s"
    ],
    "wof:name":"Christine Bulckaen",
    "wof:placetype":"venue"
},
  "geometry": {"coordinates":[3.1261799335,50.7897186279],"type":"Point"}
}