{
  "type": "Feature",
  "properties": {
    "addr:full":"Biezeweg 13 Wetteren Oost-Vlaanderen 9230",
    "addr:housenumber":"13",
    "addr:postcode":"9230",
    "addr:street":"Biezeweg",
    "iso:country":"BE",
    "sg:address":"Biezeweg 13",
    "sg:city":"Wetteren",
    "sg:classifiers":[
        {
            "category":"Wholesale",
            "subcategory":"Machinery & Supplies",
            "type":"Manufacturing & Wholesale Goods"
        }
    ],
    "sg:phone":"+32 9 252 42 22",
    "sg:postcode":"9230",
    "sg:province":"Oost-Vlaanderen",
    "sg:tags":[
        "handling",
        "material",
        "-",
        "machine",
        "equipment",
        "engineering",
        "mechanical"
    ],
    "wof:name":"Heli Nv",
    "wof:placetype":"venue"
},
  "geometry": {"coordinates":[3.838727951,50.9899139404],"type":"Point"}
}