{
  "type": "Feature",
  "properties": {
    "addr:full":"Avenue De Tabora 20 Namur Namur 5000",
    "addr:housenumber":"20",
    "addr:postcode":"5000",
    "addr:street":"Avenue De Tabora",
    "iso:country":"BE",
    "sg:address":"Avenue De Tabora 20",
    "sg:city":"Namur",
    "sg:orig_category":"M\u00e9decins and sp\u00e9cialistes",
    "sg:phone":"+32 81 74 33 55",
    "sg:postcode":"5000",
    "sg:province":"Namur",
    "wof:name":"Guy Laurent",
    "wof:placetype":"venue"
},
  "geometry": {"coordinates":[4.8514099121,50.4682617188],"type":"Point"}
}