{
  "type": "Feature",
  "properties": {
    "addr:full":"Eindestraat 25 Kortenaken Vlaams-Brabant 3473",
    "addr:housenumber":"25",
    "addr:postcode":"3473",
    "addr:street":"Eindestraat",
    "iso:country":"BE",
    "sg:address":"Eindestraat 25",
    "sg:city":"Kortenaken",
    "sg:orig_category":"Peinture. Rev\u00eatements pour sols and murs",
    "sg:phone":"+32 16 77 96 61",
    "sg:postcode":"3473",
    "sg:province":"Vlaams-Brabant",
    "wof:name":"Jaak Nates",
    "wof:placetype":"venue"
},
  "geometry": {"coordinates":[4.9794149399,50.9157676697],"type":"Point"}
}