{
  "type": "Feature",
  "properties": {
    "iso:country":"BE",
    "sg:address":"Rue De Loncin 28b1",
    "sg:city":"Sint-gillis/saint-gilles",
    "sg:orig_category":"Agences de publicit\u00e9",
    "sg:phone":"+32 2 534 41 15",
    "sg:postcode":"1060",
    "sg:province":"Bruxelles-Capitale",
    "wof:name":"Bureau Copybox",
    "wof:placetype":"venue"
},
  "geometry": {"coordinates":[4.3444461823,50.8242950439],"type":"Point"}
}