{
  "type": "Feature",
  "properties": {
    "addr:full":"Grand'place 19 Nivelles Brabant Wallon 1400",
    "addr:housenumber":"19",
    "addr:postcode":"1400",
    "addr:street":"Grand'Place",
    "iso:country":"BE",
    "sg:address":"Grand'place 19",
    "sg:city":"Nivelles",
    "sg:classifiers":[
        {
            "category":"Shopping",
            "subcategory":"Clothing, Apparel, & Fashions",
            "type":"Retail Goods"
        }
    ],
    "sg:phone":"+32 67 21 22 56",
    "sg:postcode":"1400",
    "sg:province":"Brabant Wallon",
    "sg:tags":[
        "lady",
        "clothing",
        "-"
    ],
    "wof:name":"Dufer Sprl",
    "wof:placetype":"venue"
},
  "geometry": {"coordinates":[4.3232650757,50.596786499],"type":"Point"}
}