{
  "type": "Feature",
  "properties": {
    "iso:country":"BE",
    "sg:address":"Heuvelstraat 21",
    "sg:city":"Mol",
    "sg:classifiers":[
        {
            "category":"Recreation",
            "type":"Entertainment"
        }
    ],
    "sg:phone":"+32 14 31 43 71",
    "sg:postcode":"2400",
    "sg:province":"Antwerpen",
    "sg:tags":[
        "diver",
        "amusement"
    ],
    "wof:name":"Rockwell-crew",
    "wof:placetype":"venue"
},
  "geometry": {"coordinates":[5.134499073,51.2034568787],"type":"Point"}
}