{
  "type": "Feature",
  "properties": {
    "iso:country":"BE",
    "sg:address":"Padderijstraat 12",
    "sg:city":"Ardooie",
    "sg:orig_category":"Installation \u00e9lectrique r\u00e9sidentielle",
    "sg:phone":"+32 51 74 57 08",
    "sg:postcode":"8851",
    "sg:province":"West-Vlaanderen",
    "wof:name":"Erik Decleer",
    "wof:placetype":"venue"
},
  "geometry": {"coordinates":[3.2115180492,51.0034866333],"type":"Point"}
}