{
  "type": "Feature",
  "properties": {
    "addr:full":"Dorpsstraat 83 Box 1 Erpe-mere (erpe) Oost-Vlaanderen 9420",
    "addr:housenumber":"83;1",
    "addr:postcode":"9420",
    "addr:street":"Dorpsstraat;Box",
    "iso:country":"BE",
    "sg:address":"Dorpsstraat 83 Box 1",
    "sg:city":"Erpe-mere (erpe)",
    "sg:classifiers":[
        {
            "category":"Shopping",
            "subcategory":"Clothing, Apparel, & Fashions",
            "type":"Retail Goods"
        }
    ],
    "sg:phone":"+32 53 41 39 11",
    "sg:postcode":"9420",
    "sg:province":"Oost-Vlaanderen",
    "sg:tags":[
        "underwear",
        "lingerie",
        "-"
    ],
    "wof:name":"Elys\u00e9e",
    "wof:placetype":"venue"
},
  "geometry": {"coordinates":[3.9775409698,50.9343299866],"type":"Point"}
}