{
  "type": "Feature",
  "properties": {
    "addr:full":"Place De Bronckart 25 Li\u00e8ge 1 Li\u00e8ge 4000",
    "addr:housenumber":"25;1",
    "addr:postcode":"4000",
    "addr:street":"Place De Bronckart",
    "iso:country":"BE",
    "sg:address":"Place De Bronckart 25",
    "sg:city":"Li\u00e8ge 1",
    "sg:classifiers":[
        {
            "category":"Health Services",
            "subcategory":"Doctor",
            "type":"Services"
        }
    ],
    "sg:phone":"+32 4 252 02 10",
    "sg:postcode":"4000",
    "sg:province":"Li\u00e8ge",
    "sg:tags":[
        "medicinephysicians",
        "surgeon"
    ],
    "wof:name":"Maisse Andr\u00e9",
    "wof:placetype":"venue"
},
  "geometry": {"coordinates":[5.5661997795,50.629032135],"type":"Point"}
}