{
  "type": "Feature",
  "properties": {
    "addr:full":"Overstraat 49 Diest Vlaams-Brabant 3290",
    "addr:housenumber":"49",
    "addr:postcode":"3290",
    "addr:street":"Overstraat",
    "iso:country":"BE",
    "sg:address":"Overstraat 49",
    "sg:city":"Diest",
    "sg:orig_category":"Avocats and conseillers juridiques",
    "sg:phone":"+32 13 31 11 99",
    "sg:postcode":"3290",
    "sg:province":"Vlaams-Brabant",
    "wof:name":"M. Remans",
    "wof:placetype":"venue"
},
  "geometry": {"coordinates":[5.0559067726,50.9866828918],"type":"Point"}
}