{
  "type": "Feature",
  "properties": {
    "iso:country":"BE",
    "sg:address":"Menenstraat 11",
    "sg:city":"Wervik",
    "sg:orig_category":"G\u00e9om\u00e8tres",
    "sg:phone":"+32 56 51 18 26",
    "sg:postcode":"8940",
    "sg:province":"West-Vlaanderen",
    "wof:name":"Jaak Lecluyse",
    "wof:placetype":"venue"
},
  "geometry": {"coordinates":[3.079472065,50.8096847534],"type":"Point"}
}