{
  "type": "Feature",
  "properties": {
    "iso:country":"BE",
    "sg:address":"Rue L\u00c9opold I 108",
    "sg:city":"Brussel/bruxelles",
    "sg:orig_category":"RESTAURANTS: PAIN, P\u00c2TISSERIES AND CONFISERIES",
    "sg:phone":"+32 2 428 52 24",
    "sg:postcode":"1020",
    "sg:province":"Bruxelles-Capitale",
    "wof:name":"Glacier Reddy",
    "wof:placetype":"venue"
},
  "geometry": {"coordinates":[4.3465771675,50.87733078],"type":"Point"}
}