{
  "type": "Feature",
  "properties": {
    "addr:full":"Rue D'armenti\u00c8res 389 Komen-waasten/comines-warneton Hainaut 7783",
    "addr:housenumber":"389;7783",
    "addr:street":"Rue D'Armentie \u0300Res",
    "iso:country":"BE",
    "sg:address":"Rue D'armenti\u00c8res 389",
    "sg:city":"Komen-waasten/comines-warneton",
    "sg:orig_category":"Pain, p\u00e2tisseries and confiseries",
    "sg:phone":"+32 56 58 86 34",
    "sg:postcode":"7783",
    "sg:province":"Hainaut",
    "wof:name":"Egidio Soetaert",
    "wof:placetype":"venue"
},
  "geometry": {"coordinates":[2.8832828999,50.7069206238],"type":"Point"}
}