{
  "type": "Feature",
  "properties": {
    "addr:full":"Rue De La Tour 17 Jemeppe-sur-sambre Namur 5190",
    "addr:housenumber":"17",
    "addr:postcode":"5190",
    "addr:street":"Rue De La Tour",
    "iso:country":"BE",
    "sg:address":"Rue De La Tour 17",
    "sg:city":"Jemeppe-sur-sambre",
    "sg:orig_category":"Artsen and specialisten",
    "sg:phone":"+32 71 78 80 96",
    "sg:postcode":"5190",
    "sg:province":"Namur",
    "wof:name":"Jos\u00c9 Martin Villagra",
    "wof:placetype":"venue"
},
  "geometry": {"coordinates":[4.7059707642,50.4847412109],"type":"Point"}
}