{
  "type": "Feature",
  "properties": {
    "iso:country":"BE",
    "sg:address":"Th\u00c9o Vanp\u00c9laan 16b14",
    "sg:city":"Oudergem/auderghem",
    "sg:orig_category":"Artsen and specialisten",
    "sg:phone":"+32 2 675 32 73",
    "sg:postcode":"1160",
    "sg:province":"Bruxelles-Capitale",
    "wof:name":"Sophie Thiry",
    "wof:placetype":"venue"
},
  "geometry": {"coordinates":[4.4266901016,50.8108901978],"type":"Point"}
}