{
  "type": "Feature",
  "properties": {
    "addr:full":"Grotestraat 11 Geraardsbergen Oost-Vlaanderen 9500",
    "addr:housenumber":"11",
    "addr:postcode":"9500",
    "addr:street":"Grotestraat",
    "iso:country":"BE",
    "sg:address":"Grotestraat 11",
    "sg:city":"Geraardsbergen",
    "sg:orig_category":"Agences de voyages",
    "sg:phone":"+32 54 41 10 75",
    "sg:postcode":"9500",
    "sg:province":"Oost-Vlaanderen",
    "wof:name":"Ibis Reizen",
    "wof:placetype":"venue"
},
  "geometry": {"coordinates":[3.8792788982,50.7717933655],"type":"Point"}
}