{
  "type": "Feature",
  "properties": {
    "addr:full":"Place De Petit-roeulx 11 Seneffe Hainaut 7181",
    "addr:housenumber":"11",
    "addr:postcode":"7181",
    "addr:street":"Place De Petit-Roeulx",
    "iso:country":"BE",
    "sg:address":"Place De Petit-roeulx 11",
    "sg:city":"Seneffe",
    "sg:orig_category":"M\u00e9decins and sp\u00e9cialistes",
    "sg:phone":"+32 67 87 77 10",
    "sg:postcode":"7181",
    "sg:province":"Hainaut",
    "wof:name":"M. Valfer",
    "wof:placetype":"venue"
},
  "geometry": {"coordinates":[4.3143048286,50.5538368225],"type":"Point"}
}