{
  "type": "Feature",
  "properties": {
    "iso:country":"BE",
    "sg:address":"Ezelstraat 147",
    "sg:city":"Brugge",
    "sg:orig_category":"Centres de relaxation and bien-\u00eatre. Instituts de beaut\u00e9",
    "sg:phone":"+32 50 33 92 59",
    "sg:postcode":"8000",
    "sg:province":"West-Vlaanderen",
    "wof:name":"Studio Esthetiek",
    "wof:placetype":"venue"
},
  "geometry": {"coordinates":[3.2163228989,51.2147941589],"type":"Point"}
}