{
  "type": "Feature",
  "properties": {
    "iso:country":"BE",
    "sg:address":"Rue Defays 7",
    "sg:city":"Pepinster",
    "sg:orig_category":"Diverse bedrijfsbeheeradviesbureaus",
    "sg:phone":"+32 87 46 98 53",
    "sg:postcode":"4860",
    "sg:province":"Li\u00e8ge",
    "wof:name":"Smb Consult",
    "wof:placetype":"venue"
},
  "geometry": {"coordinates":[5.8031687737,50.5644569397],"type":"Point"}
}