{
  "type": "Feature",
  "properties": {
    "addr:full":"Chemin Du Stade 3 Champ De Harre Luxembourg 6960",
    "addr:housenumber":"3",
    "addr:postcode":"6960",
    "addr:street":"Chemin Du Stade",
    "iso:country":"BE",
    "sg:address":"Chemin Du Stade 3",
    "sg:city":"Champ De Harre",
    "sg:orig_category":"Catering and organisation de f\u00eates. H\u00f4tels. Installations and terrains de sport hors centres sportif",
    "sg:phone":"+32 86 43 00 04",
    "sg:postcode":"6960",
    "sg:province":"Luxembourg",
    "wof:name":"Hanciaux Western Ranch",
    "wof:placetype":"venue"
},
  "geometry": {"coordinates":[5.6700458527,50.3604545593],"type":"Point"}
}