{
  "type": "Feature",
  "properties": {
    "addr:full":"Gaston Roelandtsstraat 1 Box 6 Oostkamp West-Vlaanderen 8020",
    "addr:housenumber":"1;6",
    "addr:postcode":"8020",
    "addr:street":"Gaston Roelandtsstraat;Box",
    "iso:country":"BE",
    "sg:address":"Gaston Roelandtsstraat 1 Box 6",
    "sg:city":"Oostkamp",
    "sg:classifiers":[
        {
            "category":"Autos & Motor Vehicles",
            "subcategory":"Motorcycle Sales",
            "type":"Retail Goods"
        }
    ],
    "sg:phone":"+32 50 39 55 15",
    "sg:postcode":"8020",
    "sg:province":"West-Vlaanderen",
    "sg:tags":[
        "motorbike"
    ],
    "wof:name":"S & T Harley Davidson",
    "wof:placetype":"venue"
},
  "geometry": {"coordinates":[3.2334420681,51.1713523865],"type":"Point"}
}