{
  "type": "Feature",
  "properties": {
    "iso:country":"BE",
    "sg:address":"Rue Golard 32",
    "sg:city":"Chastre",
    "sg:orig_category":"Artsen and specialisten",
    "sg:phone":"+32 71 87 95 98",
    "sg:postcode":"1450",
    "sg:province":"Brabant Wallon",
    "wof:name":"O. Berny",
    "wof:placetype":"venue"
},
  "geometry": {"coordinates":[4.636452198,50.6085243225],"type":"Point"}
}