{
  "type": "Feature",
  "properties": {
    "addr:full":"Vogelenzangstraat 170 Kortenberg Vlaams-Brabant 3070",
    "addr:housenumber":"170",
    "addr:postcode":"3070",
    "addr:street":"Vogelenzangstraat;Vlaams-Brabant",
    "iso:country":"BE",
    "sg:address":"Vogelenzangstraat 170",
    "sg:city":"Kortenberg",
    "sg:orig_category":"Cr\u00e9meries",
    "sg:phone":"+32 2 759 34 56",
    "sg:postcode":"3070",
    "sg:province":"Vlaams-Brabant",
    "wof:name":"Roger De Cnijf",
    "wof:placetype":"venue"
},
  "geometry": {"coordinates":[4.5351519585,50.8790588379],"type":"Point"}
}