{
  "type": "Feature",
  "properties": {
    "addr:full":"Gouvernementstraat 7 Gent Oost-Vlaanderen 9000",
    "addr:housenumber":"7",
    "addr:postcode":"9000",
    "addr:street":"Gouvernementstraat;Oost-Vlaanderen",
    "iso:country":"BE",
    "sg:address":"Gouvernementstraat 7",
    "sg:city":"Gent",
    "sg:classifiers":[
        {
            "category":"Shopping",
            "subcategory":"Clothing, Apparel, & Fashions",
            "type":"Retail Goods"
        }
    ],
    "sg:phone":"+32 9 269 05 13",
    "sg:postcode":"9000",
    "sg:province":"Oost-Vlaanderen",
    "sg:tags":[
        "-",
        "clothing",
        "child"
    ],
    "wof:name":"Janssen (meneer) En Juffrouw Kaat",
    "wof:placetype":"venue"
},
  "geometry": {"coordinates":[3.72696805,51.05235672],"type":"Point"}
}