{
  "type": "Feature",
  "properties": {
    "iso:country":"BE",
    "sg:address":"Beveren Dries 50",
    "sg:city":"Waregem (beveren-leie)",
    "sg:classifiers":[
        {
            "category":"Professional",
            "subcategory":"Computer Services",
            "type":"Services"
        }
    ],
    "sg:phone":"+32 474 93 62 16",
    "sg:postcode":"8791",
    "sg:province":"West-Vlaanderen",
    "sg:tags":[
        "webdesign",
        "-",
        "internet"
    ],
    "wof:name":"Cyberware Bvba",
    "wof:placetype":"venue"
},
  "geometry": {"coordinates":[3.3557779789,50.8738861084],"type":"Point"}
}