{
  "type": "Feature",
  "properties": {
    "iso:country":"BE",
    "sg:address":".",
    "sg:city":"Morlanwelz",
    "sg:orig_category":"Afbraak- and draineerwerken",
    "sg:phone":"+32 64 43 14 14",
    "sg:postcode":"7140",
    "sg:province":"Hainaut",
    "wof:name":"De Dorlodot",
    "wof:placetype":"venue"
},
  "geometry": {"coordinates":[4.2483000755,50.4520645142],"type":"Point"}
}