{
  "type": "Feature",
  "properties": {
    "addr:full":"Boulevard De La Batterie 29 Nivelles Brabant Wallon 1400",
    "addr:housenumber":"29",
    "addr:postcode":"1400",
    "addr:street":"Boulevard De La Batterie",
    "iso:country":"BE",
    "sg:address":"Boulevard De La Batterie 29",
    "sg:city":"Nivelles",
    "sg:orig_category":"Services fun\u00e9raires",
    "sg:phone":"+32 67 21 14 85",
    "sg:postcode":"1400",
    "sg:province":"Brabant Wallon",
    "wof:name":"Lesseigne Pompes Fun\u00c8bres",
    "wof:placetype":"venue"
},
  "geometry": {"coordinates":[4.3186278343,50.596206665],"type":"Point"}
}