{
  "type": "Feature",
  "properties": {
    "iso:country":"BE",
    "sg:address":"Nieuwbedelf 5",
    "sg:city":"Sint-laureins",
    "sg:classifiers":[
        {
            "category":"Food & Beverages",
            "subcategory":"Fruits & Vegetables",
            "type":"Retail Goods"
        }
    ],
    "sg:phone":"+32 9 379 80 91",
    "sg:postcode":"9980",
    "sg:province":"Oost-Vlaanderen",
    "sg:tags":[
        "-"
    ],
    "wof:name":"Looghe A",
    "wof:placetype":"venue"
},
  "geometry": {"coordinates":[3.5239169598,51.2404632568],"type":"Point"}
}