{
  "type": "Feature",
  "properties": {
    "iso:country":"BE",
    "sg:address":"Industrieweg 105",
    "sg:city":"Beringen",
    "sg:orig_category":"Plomberie, chauffage and installations sanitaires",
    "sg:phone":"+32 11 42 91 84",
    "sg:postcode":"3583",
    "sg:province":"Limburg",
    "wof:name":"I.c.s.",
    "wof:placetype":"venue"
},
  "geometry": {"coordinates":[5.1706700325,51.0389442444],"type":"Point"}
}