{
  "type": "Feature",
  "properties": {
    "iso:country":"BE",
    "sg:address":"Aux Piedroux 100",
    "sg:city":"Li\u00e8ge 1 (ch\u00ean\u00e9e)",
    "sg:classifiers":[
        {
            "category":"Sports & Exercise",
            "subcategory":"Stables",
            "type":"Entertainment"
        }
    ],
    "sg:phone":"+32 4 366 10 00",
    "sg:postcode":"4032",
    "sg:province":"Li\u00e8ge",
    "sg:tags":[
        "riding",
        "school"
    ],
    "wof:name":"Kentucky Two (le)",
    "wof:placetype":"venue"
},
  "geometry": {"coordinates":[5.6252260208,50.6120376587],"type":"Point"}
}