{
  "type": "Feature",
  "properties": {
    "addr:full":"Chemin De Lecelles 6 Brunehaut (rongy) Hainaut 7623",
    "addr:housenumber":"6",
    "addr:postcode":"7623",
    "addr:street":"Chemin De Lecelles;Hainaut",
    "iso:country":"BE",
    "sg:address":"Chemin De Lecelles 6",
    "sg:city":"Brunehaut (rongy)",
    "sg:classifiers":[
        {
            "category":"Health Services",
            "subcategory":"Health Practitioner",
            "type":"Services"
        }
    ],
    "sg:phone":"+32 69 34 58 58",
    "sg:postcode":"7623",
    "sg:province":"Hainaut",
    "sg:tags":[
        "physiotherapist"
    ],
    "wof:name":"Despret Fabienne",
    "wof:placetype":"venue"
},
  "geometry": {"coordinates":[3.3869760036,50.5033454895],"type":"Point"}
}