{
  "type": "Feature",
  "properties": {
    "iso:country":"BE",
    "sg:address":"Oude Eedstraat 8",
    "sg:city":"Nazareth",
    "sg:orig_category":"Ordinateurs and \u00e9quipement informatique",
    "sg:phone":"+32 9 382 72 62",
    "sg:postcode":"9810",
    "sg:province":"Oost-Vlaanderen",
    "wof:name":"Bizz Disti",
    "wof:placetype":"venue"
},
  "geometry": {"coordinates":[3.6617400646,50.9706954956],"type":"Point"}
}