{
  "type": "Feature",
  "properties": {
    "addr:full":"Driehoekstraat 29 Geel Antwerpen 2440",
    "addr:housenumber":"29",
    "addr:postcode":"2440",
    "addr:street":"Driehoekstraat",
    "iso:country":"BE",
    "sg:address":"Driehoekstraat 29",
    "sg:city":"Geel",
    "sg:orig_category":"Plaatsen van vloer- and muurbekleding Schilders",
    "sg:phone":"+32 14 72 37 87",
    "sg:postcode":"2440",
    "sg:province":"Antwerpen",
    "wof:name":"Carlo\u00b4s Schilderwerken",
    "wof:placetype":"venue"
},
  "geometry": {"coordinates":[4.9906659126,51.1610794067],"type":"Point"}
}