{
  "type": "Feature",
  "properties": {
    "iso:country":"BE",
    "sg:address":"Meenseweg 30",
    "sg:city":"Ieper",
    "sg:orig_category":"Supermarch\u00e9s",
    "sg:phone":"+32 57 20 75 26",
    "sg:postcode":"8900",
    "sg:province":"West-Vlaanderen",
    "wof:name":"Battard",
    "wof:placetype":"venue"
},
  "geometry": {"coordinates":[2.8966441154,50.8522071838],"type":"Point"}
}