{
  "type": "Feature",
  "properties": {
    "addr:full":"Place De La R\u00e9publique Fran\u00e7aise 41 Li\u00e8ge 1 Li\u00e8ge 4000",
    "addr:housenumber":"41;1",
    "addr:postcode":"4000",
    "addr:street":"Place De La Re\u0301Publique;Lie\u0300Ge",
    "iso:country":"BE",
    "sg:address":"Place De La R\u00e9publique Fran\u00e7aise 41",
    "sg:city":"Li\u00e8ge 1",
    "sg:classifiers":[
        {
            "category":"Travel",
            "subcategory":"Hotels & Motels",
            "type":"Entertainment"
        }
    ],
    "sg:phone":"+32 4 223 60 85",
    "sg:postcode":"4000",
    "sg:province":"Li\u00e8ge",
    "wof:name":"Ibis H\u00f4tel",
    "wof:placetype":"venue"
},
  "geometry": {"coordinates":[5.5716958046,50.6432495117],"type":"Point"}
}