{
  "type": "Feature",
  "properties": {
    "iso:country":"BE",
    "sg:address":"Bosstraat 12ba",
    "sg:city":"Sint-gillis-waas",
    "sg:orig_category":"Woningbouw",
    "sg:phone":"+32 3 770 78 91",
    "sg:postcode":"9170",
    "sg:province":"Oost-Vlaanderen",
    "wof:name":"Werner En Luc Ruys",
    "wof:placetype":"venue"
},
  "geometry": {"coordinates":[4.1292967796,51.2126083374],"type":"Point"}
}