{
  "type": "Feature",
  "properties": {
    "iso:country":"BE",
    "sg:address":"Meensestraat 39",
    "sg:city":"Kortrijk",
    "sg:orig_category":"Kapsalons",
    "sg:phone":"+32 56 35 73 22",
    "sg:postcode":"8500",
    "sg:province":"West-Vlaanderen",
    "wof:name":"Coiffure Boy's",
    "wof:placetype":"venue"
},
  "geometry": {"coordinates":[3.2576069832,50.8332138062],"type":"Point"}
}