{
  "type": "Feature",
  "properties": {
    "addr:full":"Rue De Gembloux 666 La Bruyere Namur 5080",
    "addr:housenumber":"666",
    "addr:postcode":"5080",
    "addr:street":"Rue De Gembloux;La Bruyere",
    "iso:country":"BE",
    "sg:address":"Rue De Gembloux 666",
    "sg:city":"La Bruyere",
    "sg:orig_category":"Entretien and r\u00e9parations de voitures",
    "sg:phone":"+32 81 56 90 10",
    "sg:postcode":"5080",
    "sg:province":"Namur",
    "wof:name":"Garage Monmart Jaumes",
    "wof:placetype":"venue"
},
  "geometry": {"coordinates":[4.7835679054,50.5073928833],"type":"Point"}
}