{
  "type": "Feature",
  "properties": {
    "iso:country":"BE",
    "sg:address":"Zevekoteheirweg 175",
    "sg:city":"Gistel",
    "sg:orig_category":"M\u00e9decins and sp\u00e9cialistes",
    "sg:phone":"+32 59 27 42 76",
    "sg:postcode":"8470",
    "sg:province":"West-Vlaanderen",
    "wof:name":"Hilde Jacobs",
    "wof:placetype":"venue"
},
  "geometry": {"coordinates":[2.9877979755,51.156337738],"type":"Point"}
}