{
  "type": "Feature",
  "properties": {
    "iso:country":"BE",
    "sg:address":"Handzamestraat 85ba",
    "sg:city":"Kortemark",
    "sg:orig_category":"Boucheries",
    "sg:phone":"+32 51 56 75 18",
    "sg:postcode":"8610",
    "sg:province":"West-Vlaanderen",
    "wof:name":"Keurslager Jacky",
    "wof:placetype":"venue"
},
  "geometry": {"coordinates":[3.0317420959,51.0294380188],"type":"Point"}
}