{
  "type": "Feature",
  "properties": {
    "iso:country":"BE",
    "sg:address":"Hospitaalstraat 15-1",
    "sg:city":"Bilzen",
    "sg:classifiers":[
        {
            "category":"Health Services",
            "subcategory":"Hospital",
            "type":"Services"
        }
    ],
    "sg:phone":"+32 89 32 80 65",
    "sg:postcode":"3740",
    "sg:province":"Limburg",
    "wof:name":"Kraamzorg De Ooievaar Campus St-martinus",
    "wof:placetype":"venue"
},
  "geometry": {"coordinates":[5.5132908821,50.8721199036],"type":"Point"}
}