{
  "type": "Feature",
  "properties": {
    "iso:country":"BE",
    "sg:address":"Chauss\u00c9e De L\u00b4europe 36",
    "sg:city":"Couvin",
    "sg:orig_category":"Toeristische diensten",
    "sg:phone":"+32 60 37 70 03",
    "sg:postcode":"5660",
    "sg:province":"Namur",
    "wof:name":"Syndicat D\u00b4initiative",
    "wof:placetype":"venue"
},
  "geometry": {"coordinates":[4.449698925,49.9533996582],"type":"Point"}
}