{
  "type": "Feature",
  "properties": {
    "iso:country":"BE",
    "sg:address":"Turnhoutsebaan 339",
    "sg:city":"Wijnegem",
    "sg:classifiers":[
        {
            "category":"Shopping",
            "subcategory":"Clothing, Apparel, & Fashions",
            "type":"Retail Goods"
        }
    ],
    "sg:phone":"+32 3 353 98 44",
    "sg:postcode":"2110",
    "sg:province":"Antwerpen",
    "sg:tags":[
        "lingerie",
        "sous-v\u00eatements"
    ],
    "wof:name":"Lingerieshop Tineke",
    "wof:placetype":"venue"
},
  "geometry": {"coordinates":[4.5217561722,51.2272415161],"type":"Point"}
}