{
  "type": "Feature",
  "properties": {
    "addr:full":"Rue Hollogne Sur Geer 1 Berloz (rosoux-crenwick) Li\u00e8ge 4257",
    "addr:housenumber":"1",
    "addr:postcode":"4257",
    "addr:street":"Rue Hollogne Sur Geer;Rosoux-Crenwick",
    "iso:country":"BE",
    "sg:address":"Rue Hollogne Sur Geer 1",
    "sg:city":"Berloz (rosoux-crenwick)",
    "sg:classifiers":[
        {
            "category":"Health Services",
            "subcategory":"Doctor",
            "type":"Services"
        }
    ],
    "sg:phone":"+32 19 32 75 57",
    "sg:postcode":"4257",
    "sg:province":"Li\u00e8ge",
    "sg:tags":[
        "medicinephysicians",
        "surgeon"
    ],
    "wof:name":"Magotteaux P",
    "wof:placetype":"venue"
},
  "geometry": {"coordinates":[5.1894178391,50.7059211731],"type":"Point"}
}