{
  "type": "Feature",
  "properties": {
    "addr:full":"Oude Heirweg 46 Ardooie West-Vlaanderen 8851",
    "addr:housenumber":"46",
    "addr:postcode":"8851",
    "addr:street":"Oude Heirweg",
    "iso:country":"BE",
    "sg:address":"Oude Heirweg 46",
    "sg:city":"Ardooie",
    "sg:orig_category":"Producteurs de l\u00e9gumes. Eleveurs and marchands de porcs",
    "sg:phone":"+32 51 74 45 68",
    "sg:postcode":"8851",
    "sg:province":"West-Vlaanderen",
    "wof:name":"Andre Vanrobays",
    "wof:placetype":"venue"
},
  "geometry": {"coordinates":[3.1741380692,51.0025558472],"type":"Point"}
}