{
  "type": "Feature",
  "properties": {
    "iso:country":"BE",
    "sg:address":"Rue Du Coq 21b",
    "sg:city":"Anderlues",
    "sg:classifiers":[
        {
            "category":"Home & Garden",
            "subcategory":"Carpets & Floor Coverings",
            "type":"Retail Goods"
        }
    ],
    "sg:phone":"+32 71 54 20 13",
    "sg:postcode":"6150",
    "sg:province":"Hainaut",
    "sg:tags":[
        "layer",
        "mosaicists"
    ],
    "wof:name":"Carrelages Del Fabbro Sprl",
    "wof:placetype":"venue"
},
  "geometry": {"coordinates":[4.2806348801,50.4111175537],"type":"Point"}
}