{
  "type": "Feature",
  "properties": {
    "addr:full":"Rue De La Blocqui\u00e8re 4 Mont-saint-guibert Brabant Wallon 1435",
    "addr:housenumber":"4",
    "addr:postcode":"1435",
    "addr:street":"Rue De La Blocquie\u0300Re",
    "iso:country":"BE",
    "sg:address":"Rue De La Blocqui\u00e8re 4",
    "sg:city":"Mont-saint-guibert",
    "sg:classifiers":[
        {
            "category":"Building & Trades",
            "subcategory":"Construction",
            "type":"Services"
        }
    ],
    "sg:phone":"+32 10 65 16 80",
    "sg:postcode":"1435",
    "sg:province":"Brabant Wallon",
    "sg:tags":[
        "ceiling"
    ],
    "wof:name":"Daumont Renovation",
    "wof:placetype":"venue"
},
  "geometry": {"coordinates":[4.6064910889,50.6308631897],"type":"Point"}
}