{
  "type": "Feature",
  "properties": {
    "addr:full":"Flekeleerstraat 9 Genk Limburg 3600",
    "addr:housenumber":"9",
    "addr:postcode":"3600",
    "addr:street":"Flekeleerstraat",
    "iso:country":"BE",
    "sg:address":"Flekeleerstraat 9",
    "sg:city":"Genk",
    "sg:classifiers":[
        {
            "category":"Cafe",
            "type":"Food & Drink"
        }
    ],
    "sg:phone":"+32 89 35 97 60",
    "sg:postcode":"3600",
    "sg:province":"Limburg",
    "sg:tags":[
        "caf\u00e9s"
    ],
    "wof:name":"Rocco Scolozzi",
    "wof:placetype":"venue"
},
  "geometry": {"coordinates":[5.483479023,50.9568786621],"type":"Point"}
}