{
  "type": "Feature",
  "properties": {
    "addr:full":"Rue Fontaine-au-biez 206 Verviers (heusy) Li\u00e8ge 4802",
    "addr:housenumber":"206",
    "addr:postcode":"4802",
    "addr:street":"Rue Fontaine-Au-Biez",
    "iso:country":"BE",
    "sg:address":"Rue Fontaine-au-biez 206",
    "sg:city":"Verviers (heusy)",
    "sg:classifiers":[
        {
            "category":"Building & Trades",
            "subcategory":"Landscaping Services",
            "type":"Services"
        }
    ],
    "sg:phone":"+32 87 22 00 37",
    "sg:postcode":"4802",
    "sg:province":"Li\u00e8ge",
    "sg:tags":[
        "gardening",
        "garden",
        "maintenance"
    ],
    "wof:name":"G.p.s.",
    "wof:placetype":"venue"
},
  "geometry": {"coordinates":[5.8864498138,50.5757904053],"type":"Point"}
}