{
  "type": "Feature",
  "properties": {
    "addr:full":"Naamsestraat 39b2 Leuven Vlaams-Brabant 3000",
    "addr:housenumber":"39b2",
    "addr:postcode":"3000",
    "addr:street":"Naamsestraat",
    "iso:country":"BE",
    "sg:address":"Naamsestraat 39b2",
    "sg:city":"Leuven",
    "sg:orig_category":"Advocaten and juridische adviseurs",
    "sg:phone":"+32 16 29 70 75",
    "sg:postcode":"3000",
    "sg:province":"Vlaams-Brabant",
    "wof:name":"F. Raymaekers",
    "wof:placetype":"venue"
},
  "geometry": {"coordinates":[4.7006859779,50.8769073486],"type":"Point"}
}