{
  "type": "Feature",
  "properties": {
    "iso:country":"BE",
    "sg:address":"Auguste Demaeghtlaan 158",
    "sg:city":"Halle",
    "sg:classifiers":[
        {
            "category":"Building & Trades",
            "subcategory":"Electrical",
            "type":"Services"
        }
    ],
    "sg:phone":"+32 2 356 86 95",
    "sg:postcode":"1500",
    "sg:province":"Vlaams-Brabant",
    "sg:tags":[
        "electric",
        "-",
        "housewiring",
        "contractor"
    ],
    "wof:name":"Halelek Bvba",
    "wof:placetype":"venue"
},
  "geometry": {"coordinates":[4.231192112,50.7367897034],"type":"Point"}
}