{
  "type": "Feature",
  "properties": {
    "addr:full":"Generaal Lemanstraat 45 Antwerpen Antwerpen 2018",
    "addr:housenumber":"45",
    "addr:postcode":"2018",
    "addr:street":"Generaal Lemanstraat",
    "iso:country":"BE",
    "sg:address":"Generaal Lemanstraat 45",
    "sg:city":"Antwerpen",
    "sg:classifiers":[
        {
            "category":"Cafe",
            "type":"Food & Drink"
        }
    ],
    "sg:phone":"+32 3 237 14 95",
    "sg:postcode":"2018",
    "sg:province":"Antwerpen",
    "sg:tags":[
        "snack-bars"
    ],
    "wof:name":"Bistro Meivis",
    "wof:placetype":"venue"
},
  "geometry": {"coordinates":[4.4112358093,51.1948051453],"type":"Point"}
}