{
  "type": "Feature",
  "properties": {
    "addr:full":"Smeekolenstraat 4 Merelbeke Oost-Vlaanderen 9820",
    "addr:housenumber":"4",
    "addr:postcode":"9820",
    "addr:street":"Smeekolenstraat",
    "iso:country":"BE",
    "sg:address":"Smeekolenstraat 4",
    "sg:city":"Merelbeke",
    "sg:orig_category":"Installation de serres, double vitrage and fen\u00eatres. Vitrage",
    "sg:phone":"+32 9 231 99 28",
    "sg:postcode":"9820",
    "sg:province":"Oost-Vlaanderen",
    "wof:name":"New Glas Art",
    "wof:placetype":"venue"
},
  "geometry": {"coordinates":[3.7418470383,50.9819030762],"type":"Point"}
}