{
  "type": "Feature",
  "properties": {
    "iso:country":"BE",
    "sg:address":"Rue De Theux 61",
    "sg:city":"Bruxelles (etterbeek)",
    "sg:classifiers":[
        {
            "category":"Home & Garden",
            "subcategory":"Carpets & Floor Coverings",
            "type":"Retail Goods"
        }
    ],
    "sg:phone":"+32 2 770 03 28",
    "sg:postcode":"1040",
    "sg:province":"Bruxelles-Capitale",
    "sg:tags":[
        "parquet"
    ],
    "wof:name":"Da Silva Janssens Sa",
    "wof:placetype":"venue"
},
  "geometry": {"coordinates":[4.382381916,50.8331565857],"type":"Point"}
}