{
  "type": "Feature",
  "properties": {
    "iso:country":"BE",
    "sg:address":"Boulevard Joseph Tirou 69",
    "sg:city":"Charleroi",
    "sg:classifiers":[
        {
            "category":"Insurance",
            "subcategory":"Insurance Agent",
            "type":"Services"
        }
    ],
    "sg:phone":"+32 71 31 40 57",
    "sg:postcode":"6000",
    "sg:province":"Hainaut",
    "sg:tags":[
        "broker"
    ],
    "wof:name":"Amant Assurances",
    "wof:placetype":"venue"
},
  "geometry": {"coordinates":[4.4409627914,50.4086837769],"type":"Point"}
}