{
  "type": "Feature",
  "properties": {
    "addr:full":"Ch De Bastogne Vaux-sur-sure Luxembourg 6640",
    "addr:postcode":"6640",
    "addr:street":"Ch De Bastogne",
    "iso:country":"BE",
    "sg:address":"Ch De Bastogne",
    "sg:city":"Vaux-sur-sure",
    "sg:classifiers":[
        {
            "category":"Wholesale",
            "subcategory":"Meat",
            "type":"Manufacturing & Wholesale Goods"
        }
    ],
    "sg:phone":"+32 61 21 69 81",
    "sg:postcode":"6640",
    "sg:province":"Luxembourg",
    "sg:tags":[
        "food",
        "cooked",
        "product",
        "related"
    ],
    "wof:name":"Belardenne Sa",
    "wof:placetype":"venue"
},
  "geometry": {"coordinates":[5.5678348541,49.9125099182],"type":"Point"}
}