{
  "type": "Feature",
  "properties": {
    "iso:country":"BE",
    "sg:address":"Danegemstraat 17ba",
    "sg:city":"Beernem",
    "sg:classifiers":[
        {
            "category":"Sports & Exercise",
            "subcategory":"Sports Center",
            "type":"Entertainment"
        }
    ],
    "sg:phone":"+32 50 78 08 00",
    "sg:postcode":"8730",
    "sg:province":"West-Vlaanderen",
    "sg:tags":[
        "terrain",
        "hors",
        "de",
        "installation",
        "sportifs"
    ],
    "wof:name":"Hippo D'haenegem",
    "wof:placetype":"venue"
},
  "geometry": {"coordinates":[3.3481299877,51.1787452698],"type":"Point"}
}