{
  "type": "Feature",
  "properties": {
    "addr:full":"Leopold Wienerplein 3 Brussel Bruxelles-Capitale 1170",
    "addr:housenumber":"3",
    "addr:postcode":"1170",
    "addr:street":"Leopold Wienerplein",
    "iso:country":"BE",
    "sg:address":"Leopold Wienerplein 3",
    "sg:city":"Brussel",
    "sg:classifiers":[
        {
            "category":"Bakery",
            "type":"Food & Drink"
        }
    ],
    "sg:phone":"+32 2 672 27 37",
    "sg:postcode":"1170",
    "sg:province":"Bruxelles-Capitale",
    "sg:tags":[
        "cake",
        "product",
        "related",
        "bread"
    ],
    "wof:name":"Patisserie Novelty Bvba",
    "wof:placetype":"venue"
},
  "geometry": {"coordinates":[4.4061150551,50.8088417053],"type":"Point"}
}