{
  "type": "Feature",
  "properties": {
    "iso:country":"BE",
    "sg:address":"Av.air Marshal Coningham 5b8",
    "sg:city":"Brussel/bruxelles",
    "sg:orig_category":"Administration d'immeubles",
    "sg:phone":"+32 2 647 14 10",
    "sg:postcode":"1000",
    "sg:province":"Bruxelles-Capitale",
    "wof:name":"Philippe Lepez",
    "wof:placetype":"venue"
},
  "geometry": {"coordinates":[4.3871321678,50.8058166504],"type":"Point"}
}