{
  "type": "Feature",
  "properties": {
    "addr:full":"Chauss\u00c9e De Drogenbos 86 Ukkel/uccle Bruxelles-Capitale 1180",
    "addr:housenumber":"86",
    "addr:postcode":"1180",
    "addr:street":"Chausse\u0301E De Drogenbos;/",
    "iso:country":"BE",
    "sg:address":"Chauss\u00c9e De Drogenbos 86",
    "sg:city":"Ukkel/uccle",
    "sg:orig_category":"V\u00e9t\u00e9rinaires",
    "sg:phone":"+32 2 376 17 91",
    "sg:postcode":"1180",
    "sg:province":"Bruxelles-Capitale",
    "wof:name":"Dominique Demblon",
    "wof:placetype":"venue"
},
  "geometry": {"coordinates":[4.3263177872,50.7867774963],"type":"Point"}
}