{
  "type": "Feature",
  "properties": {
    "addr:full":"Avenue Du Condor 17b18 Sint-jans-molenbeek/molenbeek-saint-jean Bruxelles-Capitale 1080",
    "addr:housenumber":"17b18",
    "addr:postcode":"1080",
    "addr:street":"Avenue Du Condor",
    "iso:country":"BE",
    "sg:address":"Avenue Du Condor 17b18",
    "sg:city":"Sint-jans-molenbeek/molenbeek-saint-jean",
    "sg:orig_category":"Administration d'immeubles. Evaluation and estimation de biens immobiliers. Architectes",
    "sg:phone":"+32 2 732 89 10",
    "sg:postcode":"1080",
    "sg:province":"Bruxelles-Capitale",
    "wof:name":"Antoine Costa",
    "wof:placetype":"venue"
},
  "geometry": {"coordinates":[4.3047990799,50.8525505066],"type":"Point"}
}