{
  "type": "Feature",
  "properties": {
    "iso:country":"BE",
    "sg:address":"Boekweitstraat 19",
    "sg:city":"Diksmuide",
    "sg:classifiers":[
        {
            "category":"Real Estate",
            "subcategory":"Architect",
            "type":"Services"
        }
    ],
    "sg:phone":"+32 51 50 16 41",
    "sg:postcode":"8600",
    "sg:province":"West-Vlaanderen",
    "wof:name":"Maeyaert E",
    "wof:placetype":"venue"
},
  "geometry": {"coordinates":[2.8756740093,51.0285072327],"type":"Point"}
}