{
  "type": "Feature",
  "properties": {
    "iso:country":"BE",
    "sg:address":"Steenstraat 91",
    "sg:city":"Kortemark (werken)",
    "sg:classifiers":[
        {
            "category":"Freight",
            "type":"Transportation"
        }
    ],
    "sg:phone":"+32 51 58 19 34",
    "sg:postcode":"8610",
    "sg:province":"West-Vlaanderen",
    "sg:tags":[
        "container",
        "-",
        "transport"
    ],
    "wof:name":"Jovatrans",
    "wof:placetype":"venue"
},
  "geometry": {"coordinates":[2.9877409935,51.0497665405],"type":"Point"}
}