{
  "type": "Feature",
  "properties": {
    "iso:country":"BE",
    "sg:address":"Kapelstraat 78",
    "sg:city":"Deerlijk",
    "sg:orig_category":"Slagers",
    "sg:phone":"+32 56 77 22 11",
    "sg:postcode":"8540",
    "sg:province":"West-Vlaanderen",
    "wof:name":"Jo Snauwaert",
    "wof:placetype":"venue"
},
  "geometry": {"coordinates":[3.3765599728,50.8195304871],"type":"Point"}
}