{
  "type": "Feature",
  "properties": {
    "iso:country":"BE",
    "sg:address":"Wittestraat 1",
    "sg:city":"Kortrijk (heule)",
    "sg:classifiers":[
        {
            "category":"Wholesale",
            "subcategory":"Chemicals & Plastics",
            "type":"Manufacturing & Wholesale Goods"
        }
    ],
    "sg:phone":"+32 56 35 19 64",
    "sg:postcode":"8501",
    "sg:province":"West-Vlaanderen",
    "sg:tags":[
        "packing"
    ],
    "wof:name":"Isomo Nv",
    "wof:placetype":"venue"
},
  "geometry": {"coordinates":[3.2399799824,50.8488082886],"type":"Point"}
}