{
  "type": "Feature",
  "properties": {
    "addr:full":"Antwerpse Steenweg 90 Sint-niklaas Oost-Vlaanderen 9100",
    "addr:housenumber":"90",
    "addr:postcode":"9100",
    "addr:street":"Antwerpse Steenweg",
    "iso:country":"BE",
    "sg:address":"Antwerpse Steenweg 90",
    "sg:city":"Sint-niklaas",
    "sg:classifiers":[
        {
            "category":"Personal",
            "subcategory":"Beauty Salon",
            "type":"Services"
        }
    ],
    "sg:phone":"+32 3 776 79 48",
    "sg:postcode":"9100",
    "sg:province":"Oost-Vlaanderen",
    "sg:tags":[
        "de",
        "coiffure"
    ],
    "wof:name":"Coiffure Andrea",
    "wof:placetype":"venue"
},
  "geometry": {"coordinates":[4.1548762321,51.1690368652],"type":"Point"}
}