{
  "type": "Feature",
  "properties": {
    "addr:full":"Jan Verspeyenstraat 26 Gent Oost-Vlaanderen 9000",
    "addr:housenumber":"26",
    "addr:postcode":"9000",
    "addr:street":"Jan Verspeyenstraat;Oost-Vlaanderen",
    "iso:country":"BE",
    "sg:address":"Jan Verspeyenstraat 26",
    "sg:city":"Gent",
    "sg:classifiers":[
        {
            "category":"Retail",
            "subcategory":"Repair Shop",
            "type":"Services"
        }
    ],
    "sg:phone":"+32 9 224 05 22",
    "sg:postcode":"9000",
    "sg:province":"Oost-Vlaanderen",
    "sg:tags":[
        "radio",
        "television",
        "-",
        "maintenance"
    ],
    "wof:name":"Hoste H",
    "wof:placetype":"venue"
},
  "geometry": {"coordinates":[3.7123959064,51.0587272644],"type":"Point"}
}