{
  "type": "Feature",
  "properties": {
    "addr:full":"Sint-katriensteenweg 216 Kuurne West-Vlaanderen 8520",
    "addr:housenumber":"216",
    "addr:postcode":"8520",
    "iso:country":"BE",
    "sg:address":"Sint-katriensteenweg 216",
    "sg:city":"Kuurne",
    "sg:orig_category":"Experts-comptables",
    "sg:phone":"+32 56 35 66 59",
    "sg:postcode":"8520",
    "sg:province":"West-Vlaanderen",
    "wof:name":"Jozef Gekiere",
    "wof:placetype":"venue"
},
  "geometry": {"coordinates":[3.2537119389,50.8671417236],"type":"Point"}
}