{
  "type": "Feature",
  "properties": {
    "addr:full":"Rozebeeksestraat 14 Lendelede West-Vlaanderen 8860",
    "addr:housenumber":"14",
    "addr:postcode":"8860",
    "addr:street":"Rozebeeksestraat",
    "iso:country":"BE",
    "sg:address":"Rozebeeksestraat 14",
    "sg:city":"Lendelede",
    "sg:orig_category":"Postkantoren Verzekeringsmakelaars and experts",
    "sg:phone":"+32 51 30 20 70",
    "sg:postcode":"8860",
    "sg:province":"West-Vlaanderen",
    "wof:name":"De Post",
    "wof:placetype":"venue"
},
  "geometry": {"coordinates":[3.2412700653,50.8872184753],"type":"Point"}
}