{
  "type": "Feature",
  "properties": {
    "iso:country":"BE",
    "sg:address":"Rue Joseph Joppart 54",
    "sg:city":"Wavre",
    "sg:orig_category":"Peinture. Rev\u00eatements pour sols and murs",
    "sg:phone":"+32 10 22 40 11",
    "sg:postcode":"1300",
    "sg:province":"Brabant Wallon",
    "wof:name":"Pola",
    "wof:placetype":"venue"
},
  "geometry": {"coordinates":[4.615213871,50.7217636108],"type":"Point"}
}