{
  "type": "Feature",
  "properties": {
    "addr:full":"Smitstraat 15 Berlaar (groot) Antwerpen 2590",
    "addr:housenumber":"15",
    "addr:postcode":"2590",
    "addr:street":"Smitstraat;Groot Antwerpen",
    "iso:country":"BE",
    "sg:address":"Smitstraat 15",
    "sg:city":"Berlaar (groot)",
    "sg:classifiers":[
        {
            "category":"Personal",
            "subcategory":"Beauty Salon",
            "type":"Services"
        }
    ],
    "sg:phone":"+32 3 422 60 73",
    "sg:postcode":"2590",
    "sg:province":"Antwerpen",
    "sg:tags":[
        "de",
        "coiffure"
    ],
    "wof:name":"Matisse",
    "wof:placetype":"venue"
},
  "geometry": {"coordinates":[4.6562581062,51.1169624329],"type":"Point"}
}