{
  "type": "Feature",
  "properties": {
    "addr:full":"Avenue De Bouillon 16ba Libramont-chevigny Luxembourg 6800",
    "addr:postcode":"6800",
    "addr:street":"Avenue De Bouillon 16Ba",
    "iso:country":"BE",
    "sg:address":"Avenue De Bouillon 16ba",
    "sg:city":"Libramont-chevigny",
    "sg:orig_category":"Landmeters and schatters",
    "sg:phone":"+32 61 23 43 00",
    "sg:postcode":"6800",
    "sg:province":"Luxembourg",
    "wof:name":"Bureau Rossignol",
    "wof:placetype":"venue"
},
  "geometry": {"coordinates":[5.374765873,49.9189147949],"type":"Point"}
}