{
  "type": "Feature",
  "properties": {
    "addr:full":"Bierweg 38 Aalter Oost-Vlaanderen 9880",
    "addr:housenumber":"38",
    "addr:postcode":"9880",
    "addr:street":"Bierweg",
    "iso:country":"BE",
    "sg:address":"Bierweg 38",
    "sg:city":"Aalter",
    "sg:classifiers":[
        {
            "category":"Home & Garden",
            "subcategory":"Home Furnishings",
            "type":"Retail Goods"
        }
    ],
    "sg:phone":"+32 9 374 27 78",
    "sg:postcode":"9880",
    "sg:province":"Oost-Vlaanderen",
    "sg:tags":[
        "interior",
        "decoration"
    ],
    "wof:name":"Altra Decor Bvba",
    "wof:placetype":"venue"
},
  "geometry": {"coordinates":[3.4408240318,51.0876617432],"type":"Point"}
}