{
  "type": "Feature",
  "properties": {
    "addr:full":"Koninginnelaan 105 Maasmechelen Limburg 3630",
    "addr:housenumber":"105",
    "addr:postcode":"3630",
    "addr:street":"Koninginnelaan",
    "iso:country":"BE",
    "sg:address":"Koninginnelaan 105",
    "sg:city":"Maasmechelen",
    "sg:orig_category":"Avocats and conseillers juridiques",
    "sg:phone":"+32 89 76 62 56",
    "sg:postcode":"3630",
    "sg:province":"Limburg",
    "wof:name":"Lieve Tack",
    "wof:placetype":"venue"
},
  "geometry": {"coordinates":[5.7009902,50.9814796448],"type":"Point"}
}