{
  "type": "Feature",
  "properties": {
    "addr:full":"Kleine Dries 25 Diksmuide West-Vlaanderen 8600",
    "addr:housenumber":"25",
    "addr:postcode":"8600",
    "addr:street":"Kleine Dries",
    "iso:country":"BE",
    "sg:address":"Kleine Dries 25",
    "sg:city":"Diksmuide",
    "sg:orig_category":"Herstellingen and onderhoud van auto's Voertuigen",
    "sg:phone":"+32 51 50 44 96",
    "sg:postcode":"8600",
    "sg:province":"West-Vlaanderen",
    "wof:name":"Carrosserie Tanghe",
    "wof:placetype":"venue"
},
  "geometry": {"coordinates":[2.8602440357,51.0181808472],"type":"Point"}
}