{
  "type": "Feature",
  "properties": {
    "iso:country":"BE",
    "sg:address":"Zwanestraat 12",
    "sg:city":"Ingelmunster",
    "sg:classifiers":[
        {
            "category":"Banks & Credit Unions",
            "subcategory":"Bank",
            "type":"Services"
        }
    ],
    "sg:phone":"+32 51 48 95 06",
    "sg:postcode":"8770",
    "sg:province":"West-Vlaanderen",
    "sg:tags":[
        "savings-banks"
    ],
    "wof:name":"Vanneste-lapeere",
    "wof:placetype":"venue"
},
  "geometry": {"coordinates":[3.2472269535,50.9401435852],"type":"Point"}
}