{
  "type": "Feature",
  "properties": {
    "addr:full":"Rue Du Douaire 50 Anderlues Hainaut 6150",
    "addr:housenumber":"50",
    "addr:postcode":"6150",
    "addr:street":"Rue Du Douaire",
    "iso:country":"BE",
    "sg:address":"Rue Du Douaire 50",
    "sg:city":"Anderlues",
    "sg:classifiers":[
        {
            "category":"Wholesale",
            "subcategory":"Beer",
            "type":"Manufacturing & Wholesale Goods"
        }
    ],
    "sg:phone":"+32 71 52 43 85",
    "sg:postcode":"6150",
    "sg:province":"Hainaut",
    "sg:tags":[
        "ale",
        "-"
    ],
    "wof:name":"Gusbin E",
    "wof:placetype":"venue"
},
  "geometry": {"coordinates":[4.2752041817,50.3973426819],"type":"Point"}
}