{
  "type": "Feature",
  "properties": {
    "iso:country":"BE",
    "sg:address":"Herentalsebaan 215",
    "sg:city":"Deurne",
    "sg:classifiers":[
        {
            "category":"Shopping",
            "subcategory":"Clothing, Apparel, & Fashions",
            "type":"Retail Goods"
        }
    ],
    "sg:phone":"+32 3 322 64 29",
    "sg:postcode":"2100",
    "sg:province":"Antwerpen",
    "sg:tags":[
        "textile",
        "clothing",
        "clothes"
    ],
    "wof:name":"Swynen L Bvba",
    "wof:placetype":"venue"
},
  "geometry": {"coordinates":[4.4624657631,51.2088546753],"type":"Point"}
}