{
  "type": "Feature",
  "properties": {
    "iso:country":"BE",
    "sg:address":"Archimedesstraat 46",
    "sg:city":"Brussel/bruxelles",
    "sg:orig_category":"Herstelling horloges and juwelen Juwelen and horloges",
    "sg:phone":"+32 2 230 72 91",
    "sg:postcode":"1000",
    "sg:province":"Bruxelles-Capitale",
    "wof:name":"Horlogerie Van Gompen M.",
    "wof:placetype":"venue"
},
  "geometry": {"coordinates":[4.3834910393,50.8454856873],"type":"Point"}
}