{
  "type": "Feature",
  "properties": {
    "addr:full":"Getestraat 69 Linter Vlaams-Brabant 3350",
    "addr:housenumber":"69",
    "addr:postcode":"3350",
    "addr:street":"Getestraat;Vlaams-Brabant",
    "iso:country":"BE",
    "sg:address":"Getestraat 69",
    "sg:city":"Linter",
    "sg:orig_category":"HUISBRANDOLIE",
    "sg:phone":"+32 11 78 10 87",
    "sg:postcode":"3350",
    "sg:province":"Vlaams-Brabant",
    "wof:name":"Georges Denruyter",
    "wof:placetype":"venue"
},
  "geometry": {"coordinates":[5.0643911362,50.8061676025],"type":"Point"}
}