{
  "type": "Feature",
  "properties": {
    "addr:full":"Abelenlaan 6 Grimbergen Vlaams-Brabant 1851",
    "addr:housenumber":"6",
    "addr:postcode":"1851",
    "addr:street":"Abelenlaan",
    "iso:country":"BE",
    "sg:address":"Abelenlaan 6",
    "sg:city":"Grimbergen",
    "sg:orig_category":"Meubles D\u00e9taillants, Am\u00e9nagement de B\u00e2timents et de Cuisines",
    "sg:phone":"+32 2 270 80 88",
    "sg:postcode":"1851",
    "sg:province":"Vlaams-Brabant",
    "wof:name":"Eduard Moons",
    "wof:placetype":"venue"
},
  "geometry": {"coordinates":[4.374712944,50.9645271301],"type":"Point"}
}