{
  "type": "Feature",
  "properties": {
    "addr:full":"Molenstraat 14 Hoeilaart Vlaams-Brabant 1560",
    "addr:housenumber":"14",
    "addr:postcode":"1560",
    "addr:street":"Molenstraat",
    "iso:country":"BE",
    "sg:address":"Molenstraat 14",
    "sg:city":"Hoeilaart",
    "sg:classifiers":[
        {
            "category":"Professional",
            "subcategory":"Accounting & Tax Preparation",
            "type":"Services"
        }
    ],
    "sg:phone":"+32 2 657 33 59",
    "sg:postcode":"1560",
    "sg:province":"Vlaams-Brabant",
    "sg:tags":[
        "accountant"
    ],
    "wof:name":"Demaerschalk P",
    "wof:placetype":"venue"
},
  "geometry": {"coordinates":[4.4891657829,50.7667312622],"type":"Point"}
}