{
  "type": "Feature",
  "properties": {
    "addr:full":"Bosstraat 68 Maaseik Limburg 3680",
    "addr:housenumber":"68",
    "addr:postcode":"3680",
    "addr:street":"Bosstraat",
    "iso:country":"BE",
    "sg:address":"Bosstraat 68",
    "sg:city":"Maaseik",
    "sg:orig_category":"Diverse grafische activiteiten",
    "sg:phone":"+32 89 56 43 15",
    "sg:postcode":"3680",
    "sg:province":"Limburg",
    "wof:name":"Mathieu Corstjens",
    "wof:placetype":"venue"
},
  "geometry": {"coordinates":[5.7876858711,51.0955734253],"type":"Point"}
}