{
  "type": "Feature",
  "properties": {
    "addr:full":"Lange Gasthuisstraat 45 Antwerpen Antwerpen 2000",
    "addr:housenumber":"45",
    "addr:postcode":"2000",
    "addr:street":"Lange Gasthuisstraat",
    "iso:country":"BE",
    "sg:address":"Lange Gasthuisstraat 45",
    "sg:city":"Antwerpen",
    "sg:orig_category":"H\u00f4tels",
    "sg:phone":"+32 3 202 77 70",
    "sg:postcode":"2000",
    "sg:province":"Antwerpen",
    "wof:name":"'t Elzenveld",
    "wof:placetype":"venue"
},
  "geometry": {"coordinates":[4.4052410126,51.2134513855],"type":"Point"}
}