{
  "type": "Feature",
  "properties": {
    "addr:full":"Baan Naar Bree 121b Peer Limburg 3990",
    "addr:housenumber":"121b",
    "addr:postcode":"3990",
    "addr:street":"Baan Naar Bree",
    "iso:country":"BE",
    "sg:address":"Baan Naar Bree 121b",
    "sg:city":"Peer",
    "sg:orig_category":"Meubles D\u00e9taillants, Am\u00e9nagement de B\u00e2timents et de Cuisines",
    "sg:phone":"+32 11 61 06 65",
    "sg:postcode":"3990",
    "sg:province":"Limburg",
    "wof:name":"Trendhopper",
    "wof:placetype":"venue"
},
  "geometry": {"coordinates":[5.4986982346,51.1355247498],"type":"Point"}
}