{
  "type": "Feature",
  "properties": {
    "addr:full":"Slot 1 Berlare Oost-Vlaanderen 9290",
    "addr:housenumber":"1",
    "addr:postcode":"9290",
    "addr:street":"Slot",
    "iso:country":"BE",
    "sg:address":"Slot 1",
    "sg:city":"Berlare",
    "sg:orig_category":"Gespecialiseerde residenti\u00eble bouw",
    "sg:phone":"+32 9 367 92 92",
    "sg:postcode":"9290",
    "sg:province":"Oost-Vlaanderen",
    "wof:name":"Ronny Melis",
    "wof:placetype":"venue"
},
  "geometry": {"coordinates":[3.9496569633,51.0222434998],"type":"Point"}
}