{
  "type": "Feature",
  "properties": {
    "addr:full":"Place Joseph Thiry 23 Aywaille Li\u00e8ge 4920",
    "addr:housenumber":"23",
    "addr:postcode":"4920",
    "addr:street":"Place Joseph Thiry",
    "iso:country":"BE",
    "sg:address":"Place Joseph Thiry 23",
    "sg:city":"Aywaille",
    "sg:classifiers":[
        {
            "category":"Bars & Pubs",
            "type":"Food & Drink"
        }
    ],
    "sg:phone":"+32 4 384 79 70",
    "sg:postcode":"4920",
    "sg:province":"Li\u00e8ge",
    "sg:tags":[
        "tavern"
    ],
    "wof:name":"Gambrinus",
    "wof:placetype":"venue"
},
  "geometry": {"coordinates":[5.6750659943,50.4742393494],"type":"Point"}
}