{
  "type": "Feature",
  "properties": {
    "addr:full":"Rue Sainte-marguerite 119 Li\u00e8ge 1 Li\u00e8ge 4000",
    "addr:housenumber":"119;1",
    "addr:postcode":"4000",
    "addr:street":"Rue Sainte-Marguerite",
    "iso:country":"BE",
    "sg:address":"Rue Sainte-marguerite 119",
    "sg:city":"Li\u00e8ge 1",
    "sg:classifiers":[
        {
            "category":"Bars & Pubs",
            "type":"Food & Drink"
        }
    ],
    "sg:phone":"+32 4 224 08 43",
    "sg:postcode":"4000",
    "sg:province":"Li\u00e8ge",
    "wof:name":"Capotokia",
    "wof:placetype":"venue"
},
  "geometry": {"coordinates":[5.5582838058,50.6461143494],"type":"Point"}
}