{
  "type": "Feature",
  "properties": {
    "addr:full":"Rue De France 63 Chimay Hainaut 6460",
    "addr:housenumber":"63",
    "addr:postcode":"6460",
    "addr:street":"Rue De France",
    "iso:country":"BE",
    "sg:address":"Rue De France 63",
    "sg:city":"Chimay",
    "sg:orig_category":"Enseignement maternel and primaire",
    "sg:phone":"+32 60 21 33 30",
    "sg:postcode":"6460",
    "sg:province":"Hainaut",
    "wof:name":"Ecole Fond. Communale",
    "wof:placetype":"venue"
},
  "geometry": {"coordinates":[4.2942042351,50.0456161499],"type":"Point"}
}