{
  "type": "Feature",
  "properties": {
    "addr:full":"Herentalsesteenweg 41 Herselt Antwerpen 2230",
    "addr:housenumber":"41",
    "addr:postcode":"2230",
    "addr:street":"Herentalsesteenweg",
    "iso:country":"BE",
    "sg:address":"Herentalsesteenweg 41",
    "sg:city":"Herselt",
    "sg:classifiers":[
        {
            "category":"Manufacturing",
            "subcategory":"Glass & Minerals",
            "type":"Manufacturing & Wholesale Goods"
        }
    ],
    "sg:phone":"+32 14 54 52 83",
    "sg:postcode":"2230",
    "sg:province":"Antwerpen",
    "sg:tags":[
        "safety"
    ],
    "wof:name":"Glaswerken Van Regenmortel Bvba",
    "wof:placetype":"venue"
},
  "geometry": {"coordinates":[4.8832402229,51.0592498779],"type":"Point"}
}