{
  "type": "Feature",
  "properties": {
    "addr:full":"Av. Reine Astrid 165 B Spa Li\u00e8ge 4900",
    "addr:housenumber":"165 b",
    "addr:postcode":"4900",
    "addr:street":"Av. Reine Astrid",
    "iso:country":"BE",
    "sg:address":"Av. Reine Astrid 165 B",
    "sg:city":"Spa",
    "sg:orig_category":"Mat\u00e9riel de T\u00e9l\u00e9communication. R\u00e9parations d'appareils \u00e9lectrom\u00e9nagers. Electrom\u00e9nager, t\u00e9l\u00e9visions ",
    "sg:phone":"+32 87 77 57 59",
    "sg:postcode":"4900",
    "sg:province":"Li\u00e8ge",
    "wof:name":"Eldi",
    "wof:placetype":"venue"
},
  "geometry": {"coordinates":[5.8458948135,50.4901161194],"type":"Point"}
}