{
  "type": "Feature",
  "properties": {
    "iso:country":"BE",
    "sg:address":"Van Maelelaan 37",
    "sg:city":"Tremelo",
    "sg:classifiers":[
        {
            "category":"Insurance",
            "subcategory":"Insurance Agent",
            "type":"Services"
        }
    ],
    "sg:phone":"+32 15 23 54 31",
    "sg:postcode":"3120",
    "sg:province":"Vlaams-Brabant",
    "sg:tags":[
        "broker"
    ],
    "wof:name":"Heremans Consulting Bvba",
    "wof:placetype":"venue"
},
  "geometry": {"coordinates":[4.7150950432,51.0129890442],"type":"Point"}
}