{
  "type": "Feature",
  "properties": {
    "addr:full":"Brusselsesteenweg 489 Melle Oost-Vlaanderen 9090",
    "addr:housenumber":"489",
    "addr:postcode":"9090",
    "addr:street":"Brusselsesteenweg",
    "iso:country":"BE",
    "sg:address":"Brusselsesteenweg 489",
    "sg:city":"Melle",
    "sg:orig_category":"Installation de menuiserie en bois and plastique",
    "sg:phone":"+32 9 252 42 11",
    "sg:postcode":"9090",
    "sg:province":"Oost-Vlaanderen",
    "wof:name":"C.c.r.",
    "wof:placetype":"venue"
},
  "geometry": {"coordinates":[3.8211209774,50.9948348999],"type":"Point"}
}