{
  "type": "Feature",
  "properties": {
    "addr:full":"Michel Vergauwenstraat 8bv1 Zwijndrecht Antwerpen 2070",
    "addr:postcode":"2070",
    "addr:street":"Vergauwenstraat 8Bv1",
    "iso:country":"BE",
    "sg:address":"Michel Vergauwenstraat 8bv1",
    "sg:city":"Zwijndrecht",
    "sg:orig_category":"M\u00e9decins and sp\u00e9cialistes",
    "sg:phone":"+32 3 252 77 41",
    "sg:postcode":"2070",
    "sg:province":"Antwerpen",
    "wof:name":"Fideel Bernaers",
    "wof:placetype":"venue"
},
  "geometry": {"coordinates":[4.3270430565,51.2193489075],"type":"Point"}
}