{
  "type": "Feature",
  "properties": {
    "addr:full":"106 Rue De Chevron Chevron Li\u00e8ge 4987",
    "addr:housenumber":"106",
    "addr:postcode":"4987",
    "addr:street":"Rue De",
    "iso:country":"BE",
    "sg:address":"106 Rue De Chevron",
    "sg:city":"Chevron",
    "sg:classifiers":[
        {
            "category":"Professional",
            "subcategory":"Printing & Photocopies",
            "type":"Services"
        }
    ],
    "sg:phone":"+32 86 43 01 01",
    "sg:postcode":"4987",
    "sg:province":"Li\u00e8ge",
    "sg:tags":[
        "publishing"
    ],
    "wof:name":"Editions Hemma Sa",
    "wof:placetype":"venue"
},
  "geometry": {"coordinates":[5.729932785,50.3835296631],"type":"Point"}
}