{
  "type": "Feature",
  "properties": {
    "iso:country":"BE",
    "sg:address":"Prinses Jos.-charlotteln 71",
    "sg:city":"Sint-niklaas",
    "sg:orig_category":"Avocats and conseillers juridiques",
    "sg:phone":"+32 3 777 17 71",
    "sg:postcode":"9100",
    "sg:province":"Oost-Vlaanderen",
    "wof:name":"F. Van Royen",
    "wof:placetype":"venue"
},
  "geometry": {"coordinates":[4.1413240433,51.1526069641],"type":"Point"}
}