{
  "type": "Feature",
  "properties": {
    "iso:country":"BE",
    "sg:address":"Erneuville 12",
    "sg:city":"Tenneville",
    "sg:orig_category":"Eleveurs de bovins",
    "sg:phone":"+32 84 45 53 38",
    "sg:postcode":"6972",
    "sg:province":"Luxembourg",
    "wof:name":"Rene Ansias",
    "wof:placetype":"venue"
},
  "geometry": {"coordinates":[5.5519142151,50.1140365601],"type":"Point"}
}