{
  "type": "Feature",
  "properties": {
    "iso:country":"BE",
    "sg:address":"Jean Dubrucqlaan 228",
    "sg:city":"Sint-jans-molenbeek",
    "sg:classifiers":[
        {
            "category":"Wholesale",
            "subcategory":"Sporting Goods",
            "type":"Manufacturing & Wholesale Goods"
        }
    ],
    "sg:phone":"+32 2 426 80 00",
    "sg:postcode":"1080",
    "sg:province":"Bruxelles-Capitale",
    "sg:tags":[
        "sport-",
        "kampeermateriaal"
    ],
    "wof:name":"Brussels Nautical Services",
    "wof:placetype":"venue"
},
  "geometry": {"coordinates":[4.3414301872,50.8708152771],"type":"Point"}
}