{
  "type": "Feature",
  "properties": {
    "iso:country":"BE",
    "sg:address":"Ridderstraat 22b",
    "sg:city":"Hoegaarden",
    "sg:orig_category":"Plomberie, chauffage and installations sanitaires",
    "sg:phone":"+32 16 82 31 91",
    "sg:postcode":"3320",
    "sg:province":"Vlaams-Brabant",
    "wof:name":"Dns",
    "wof:placetype":"venue"
},
  "geometry": {"coordinates":[4.874707222,50.7998542786],"type":"Point"}
}