{
  "type": "Feature",
  "properties": {
    "iso:country":"BE",
    "sg:address":"Kasterlindenstraat 7",
    "sg:city":"Sint-agatha-berchem/berchem-sainte-agathe",
    "sg:orig_category":"Kinderopvang",
    "sg:phone":"+32 2 465 86 76",
    "sg:postcode":"1082",
    "sg:province":"Bruxelles-Capitale",
    "wof:name":"Cr\u00c8che Jardin De L'eveil",
    "wof:placetype":"venue"
},
  "geometry": {"coordinates":[4.2954850197,50.8596801758],"type":"Point"}
}