{
  "type": "Feature",
  "properties": {
    "addr:full":"Heerstraat 1 Hamont-achel (hamont) Limburg 3930",
    "addr:housenumber":"1",
    "addr:postcode":"3930",
    "addr:street":"Heerstraat",
    "iso:country":"BE",
    "sg:address":"Heerstraat 1",
    "sg:city":"Hamont-achel (hamont)",
    "sg:classifiers":[
        {
            "category":"Professional",
            "subcategory":"Computer Services",
            "type":"Services"
        }
    ],
    "sg:phone":"+32 11 66 72 57",
    "sg:postcode":"3930",
    "sg:province":"Limburg",
    "sg:tags":[
        "-",
        "processing",
        "data"
    ],
    "wof:name":"In Progress Bvba",
    "wof:placetype":"venue"
},
  "geometry": {"coordinates":[5.5450549126,51.2511863708],"type":"Point"}
}