{
  "type": "Feature",
  "properties": {
    "addr:full":"Egemstraat 144 Pittem West-Vlaanderen 8740",
    "addr:housenumber":"144",
    "addr:postcode":"8740",
    "addr:street":"Egemstraat",
    "iso:country":"BE",
    "sg:address":"Egemstraat 144",
    "sg:city":"Pittem",
    "sg:orig_category":"Entretien and r\u00e9parations de voitures",
    "sg:phone":"+32 51 46 62 65",
    "sg:postcode":"8740",
    "sg:province":"West-Vlaanderen",
    "wof:name":"F. Cools",
    "wof:placetype":"venue"
},
  "geometry": {"coordinates":[3.2578499317,51.0061988831],"type":"Point"}
}