{
  "type": "Feature",
  "properties": {
    "addr:full":"Kruisken 3 Sint-laureins Oost-Vlaanderen 9988",
    "addr:housenumber":"3",
    "addr:postcode":"9988",
    "addr:street":"Kruisken",
    "iso:country":"BE",
    "sg:address":"Kruisken 3",
    "sg:city":"Sint-laureins",
    "sg:orig_category":"Koerierbedrijven",
    "sg:phone":"+32 9 379 00 75",
    "sg:postcode":"9988",
    "sg:province":"Oost-Vlaanderen",
    "wof:name":"Omicron Transport Service",
    "wof:placetype":"venue"
},
  "geometry": {"coordinates":[3.6089200974,51.2770767212],"type":"Point"}
}