{
  "type": "Feature",
  "properties": {
    "addr:full":"Leopoldplein 5 De Haan West-Vlaanderen 8420",
    "addr:housenumber":"5",
    "addr:postcode":"8420",
    "addr:street":"Leopoldplein",
    "iso:country":"BE",
    "sg:address":"Leopoldplein 5",
    "sg:city":"De Haan",
    "sg:classifiers":[
        {
            "category":"Travel",
            "subcategory":"Hotels & Motels",
            "type":"Entertainment"
        }
    ],
    "sg:phone":"+32 59 23 31 46",
    "sg:postcode":"8420",
    "sg:province":"West-Vlaanderen",
    "wof:name":"Hotel Des Dunes",
    "wof:placetype":"venue"
},
  "geometry": {"coordinates":[3.0293030739,51.277015686],"type":"Point"}
}