{
  "type": "Feature",
  "properties": {
    "addr:full":"Sint-janstraat 17 Kortrijk West-Vlaanderen 8500",
    "addr:housenumber":"17",
    "addr:postcode":"8500",
    "addr:street":"Sint-Janstraat",
    "iso:country":"BE",
    "sg:address":"Sint-janstraat 17",
    "sg:city":"Kortrijk",
    "sg:classifiers":[
        {
            "category":"Restaurant",
            "type":"Food & Drink"
        }
    ],
    "sg:phone":"+32 56 22 79 69",
    "sg:postcode":"8500",
    "sg:province":"West-Vlaanderen",
    "wof:name":"Nectar",
    "wof:placetype":"venue"
},
  "geometry": {"coordinates":[3.2710499763,50.8273162842],"type":"Point"}
}