{
  "type": "Feature",
  "properties": {
    "addr:full":"Boulevard De Smet De Naeyer 180 Bruxelles Bruxelles-Capitale 1090",
    "addr:housenumber":"180",
    "addr:postcode":"1090",
    "addr:street":"Boulevard De Smet De Naeyer",
    "iso:country":"BE",
    "sg:address":"Boulevard De Smet De Naeyer 180",
    "sg:city":"Bruxelles",
    "sg:classifiers":[
        {
            "category":"Utilities",
            "subcategory":"Telephone",
            "type":"Services"
        }
    ],
    "sg:phone":"+32 2 428 10 30",
    "sg:postcode":"1090",
    "sg:province":"Bruxelles-Capitale",
    "sg:tags":[
        "device",
        "electromechanical",
        "assembly",
        "electronic"
    ],
    "wof:name":"Laser Beam International S.p.r.l.",
    "wof:placetype":"venue"
},
  "geometry": {"coordinates":[4.3299889565,50.8754768372],"type":"Point"}
}