{
  "type": "Feature",
  "properties": {
    "addr:full":"Brouwersstraat 1b1 Leuven Vlaams-Brabant 3000",
    "addr:housenumber":"1b1",
    "addr:postcode":"3000",
    "addr:street":"Brouwersstraat",
    "iso:country":"BE",
    "sg:address":"Brouwersstraat 1b1",
    "sg:city":"Leuven",
    "sg:orig_category":"Services de Nettoyage and de D\u00e9sinfection",
    "sg:phone":"+32 16 29 21 78",
    "sg:postcode":"3000",
    "sg:province":"Vlaams-Brabant",
    "wof:name":"Hygi Clean",
    "wof:placetype":"venue"
},
  "geometry": {"coordinates":[4.6954951286,50.8825798035],"type":"Point"}
}