{
  "type": "Feature",
  "properties": {
    "iso:country":"BE",
    "sg:address":"Goedendagstraat 10",
    "sg:city":"Wevelgem",
    "sg:classifiers":[
        {
            "category":"Utilities",
            "subcategory":"Fuel Oil & Lpg",
            "type":"Services"
        }
    ],
    "sg:phone":"+32 56 41 12 67",
    "sg:postcode":"8560",
    "sg:province":"West-Vlaanderen",
    "wof:name":"Noppe",
    "wof:placetype":"venue"
},
  "geometry": {"coordinates":[3.182790041,50.8176841736],"type":"Point"}
}