{
  "type": "Feature",
  "properties": {
    "addr:full":"Rue Du Quatre Ao\u00fbt 37 Wavre Brabant Wallon 1300",
    "addr:housenumber":"37;1300",
    "addr:street":"Rue Du Quatre Aou\u0302T",
    "iso:country":"BE",
    "sg:address":"Rue Du Quatre Ao\u00fbt 37",
    "sg:city":"Wavre",
    "sg:classifiers":[
        {
            "category":"Banks & Credit Unions",
            "subcategory":"Investment Brokerage",
            "type":"Services"
        }
    ],
    "sg:phone":"+32 10 22 36 36",
    "sg:postcode":"1300",
    "sg:province":"Brabant Wallon",
    "sg:tags":[
        "printing",
        "-"
    ],
    "wof:name":"Lambol Imprimerie",
    "wof:placetype":"venue"
},
  "geometry": {"coordinates":[4.6097750664,50.7192420959],"type":"Point"}
}