{
  "type": "Feature",
  "properties": {
    "addr:full":"Kapelstraat 24 Tienen Vlaams-Brabant 3300",
    "addr:housenumber":"24",
    "addr:postcode":"3300",
    "addr:street":"Kapelstraat",
    "iso:country":"BE",
    "sg:address":"Kapelstraat 24",
    "sg:city":"Tienen",
    "sg:orig_category":"Advocaten and juridische adviseurs",
    "sg:phone":"+32 16 81 00 42",
    "sg:postcode":"3300",
    "sg:province":"Vlaams-Brabant",
    "wof:name":"J. Lejeune",
    "wof:placetype":"venue"
},
  "geometry": {"coordinates":[4.9424071312,50.8061943054],"type":"Point"}
}