{
  "type": "Feature",
  "properties": {
    "iso:country":"BE",
    "sg:address":"Brunheidelaan 14 Iz Veedijk",
    "sg:city":"Turnhout",
    "sg:classifiers":[
        {
            "category":"Shopping",
            "subcategory":"Clothing, Apparel, & Fashions",
            "type":"Retail Goods"
        }
    ],
    "sg:phone":"+32 14 41 37 86",
    "sg:postcode":"2300",
    "sg:province":"Antwerpen",
    "sg:tags":[
        "textile",
        "clothing",
        "clothes"
    ],
    "wof:name":"Veditex Nv",
    "wof:placetype":"venue"
},
  "geometry": {"coordinates":[4.9474601746,51.2964477539],"type":"Point"}
}