{
  "type": "Feature",
  "properties": {
    "iso:country":"BE",
    "sg:address":"Dubbeekstraat 112",
    "sg:city":"Aarschot",
    "sg:orig_category":"Traitement and rev\u00eatement des m\u00e9taux",
    "sg:phone":"+32 16 56 45 60",
    "sg:postcode":"3200",
    "sg:province":"Vlaams-Brabant",
    "wof:name":"Metal Aarschot",
    "wof:placetype":"venue"
},
  "geometry": {"coordinates":[4.8416309357,50.9685134888],"type":"Point"}
}