{
  "type": "Feature",
  "properties": {
    "addr:full":"Rijselvoorstad 29 Komen-waasten/comines-warneton Hainaut 7784",
    "addr:housenumber":"29;7784",
    "addr:street":"Rijselvoorstad",
    "iso:country":"BE",
    "sg:address":"Rijselvoorstad 29",
    "sg:city":"Komen-waasten/comines-warneton",
    "sg:orig_category":"Bloemen and planten Tuinen",
    "sg:phone":"+32 56 55 65 33",
    "sg:postcode":"7784",
    "sg:province":"Hainaut",
    "wof:name":"J. Verhaeghe",
    "wof:placetype":"venue"
},
  "geometry": {"coordinates":[2.9385099411,50.738319397],"type":"Point"}
}