{
  "type": "Feature",
  "properties": {
    "iso:country":"BE",
    "sg:address":"Slagmeersenstraat 1",
    "sg:city":"Izegem",
    "sg:classifiers":[
        {
            "category":"Professional",
            "subcategory":"Art Services",
            "type":"Services"
        }
    ],
    "sg:phone":"+32 51 30 39 34",
    "sg:postcode":"8870",
    "sg:province":"West-Vlaanderen",
    "sg:tags":[
        "designer",
        "display"
    ],
    "wof:name":"Guwy M",
    "wof:placetype":"venue"
},
  "geometry": {"coordinates":[3.2163290977,50.9120330811],"type":"Point"}
}