{
  "type": "Feature",
  "properties": {
    "addr:full":"Rue Des Moissons 51 Bruxelles (saint-josse-ten-noode) Bruxelles-Capitale 1210",
    "addr:housenumber":"51",
    "addr:postcode":"1210",
    "addr:street":"Rue Des Moissons",
    "iso:country":"BE",
    "sg:address":"Rue Des Moissons 51",
    "sg:city":"Bruxelles (saint-josse-ten-noode)",
    "sg:classifiers":[
        {
            "category":"Professional",
            "subcategory":"Art Services",
            "type":"Services"
        }
    ],
    "sg:phone":"+32 2 219 92 54",
    "sg:postcode":"1210",
    "sg:province":"Bruxelles-Capitale",
    "sg:tags":[
        "picture",
        "framer"
    ],
    "wof:name":"Cadre 2000",
    "wof:placetype":"venue"
},
  "geometry": {"coordinates":[4.3768072128,50.8530845642],"type":"Point"}
}