{
  "type": "Feature",
  "properties": {
    "addr:full":"Kloosterstraat 32 Moeskroen/mouscron Hainaut 7700",
    "addr:housenumber":"32",
    "addr:postcode":"7700",
    "addr:street":"Kloosterstraat",
    "iso:country":"BE",
    "sg:address":"Kloosterstraat 32",
    "sg:city":"Moeskroen/mouscron",
    "sg:orig_category":"Bloemen and planten",
    "sg:phone":"+32 56 33 66 58",
    "sg:postcode":"7700",
    "sg:province":"Hainaut",
    "wof:name":"Maison Bokado",
    "wof:placetype":"venue"
},
  "geometry": {"coordinates":[3.2323200703,50.7400932312],"type":"Point"}
}