{
  "type": "Feature",
  "properties": {
    "iso:country":"BE",
    "sg:address":"Avenue Cardinal Mercier 50",
    "sg:city":"Namur",
    "sg:orig_category":"M\u00e9decins and sp\u00e9cialistes",
    "sg:phone":"+32 81 73 63 53",
    "sg:postcode":"5000",
    "sg:province":"Namur",
    "wof:name":"Patrick Delahaut",
    "wof:placetype":"venue"
},
  "geometry": {"coordinates":[4.8508491516,50.4654045105],"type":"Point"}
}