{
  "type": "Feature",
  "properties": {
    "addr:full":"Driesstraat 36 Geraardsbergen Oost-Vlaanderen 9506",
    "addr:housenumber":"36",
    "addr:postcode":"9506",
    "addr:street":"Driesstraat",
    "iso:country":"BE",
    "sg:address":"Driesstraat 36",
    "sg:city":"Geraardsbergen",
    "sg:orig_category":"Pain, p\u00e2tisseries and confiseries",
    "sg:phone":"+32 54 50 01 12",
    "sg:postcode":"9506",
    "sg:province":"Oost-Vlaanderen",
    "wof:name":"Marc Van Daele",
    "wof:placetype":"venue"
},
  "geometry": {"coordinates":[3.8985300064,50.7987060547],"type":"Point"}
}