{
  "type": "Feature",
  "properties": {
    "addr:full":"Avenue Albert 1er 1 Pepinster Li\u00e8ge 4860",
    "addr:housenumber":"1",
    "addr:postcode":"4860",
    "addr:street":"Avenue Albert 1Er",
    "iso:country":"BE",
    "sg:address":"Avenue Albert 1er 1",
    "sg:city":"Pepinster",
    "sg:orig_category":"Treinen and spoorwegen",
    "sg:phone":"+32 87 30 83 08",
    "sg:postcode":"4860",
    "sg:province":"Li\u00e8ge",
    "wof:name":"Gare De Pepinster",
    "wof:placetype":"venue"
},
  "geometry": {"coordinates":[5.8050627708,50.5680999756],"type":"Point"}
}