{
  "type": "Feature",
  "properties": {
    "iso:country":"BE",
    "sg:address":"Groenevelddreef 5",
    "sg:city":"Deinze (bachte-maria-leerne)",
    "sg:classifiers":[
        {
            "category":"Professional",
            "subcategory":"Business Services",
            "type":"Services"
        }
    ],
    "sg:phone":"+32 9 380 33 84",
    "sg:postcode":"9800",
    "sg:province":"Oost-Vlaanderen",
    "sg:tags":[
        "automobile",
        "-",
        "assessor"
    ],
    "wof:name":"Expertisebureau Becue Gent",
    "wof:placetype":"venue"
},
  "geometry": {"coordinates":[3.530174017,50.9863166809],"type":"Point"}
}