{
  "type": "Feature",
  "properties": {
    "addr:full":"Grand'rue 64 Aubange Luxembourg 6791",
    "addr:housenumber":"64",
    "addr:postcode":"6791",
    "addr:street":"Grand'Rue",
    "iso:country":"BE",
    "sg:address":"Grand'rue 64",
    "sg:city":"Aubange",
    "sg:orig_category":"V\u00eatements pour Dames. V\u00eatements de mariage and c\u00e9r\u00e9monies",
    "sg:phone":"+32 63 38 80 85",
    "sg:postcode":"6791",
    "sg:province":"Luxembourg",
    "wof:name":"Hachel",
    "wof:placetype":"venue"
},
  "geometry": {"coordinates":[5.8356189728,49.5628623962],"type":"Point"}
}