{
  "type": "Feature",
  "properties": {
    "iso:country":"BE",
    "sg:address":"Brugstraat 55",
    "sg:city":"Brecht",
    "sg:orig_category":"Kapsalons",
    "sg:phone":"+32 3 636 35 79",
    "sg:postcode":"2960",
    "sg:province":"Antwerpen",
    "wof:name":"Creative Hair",
    "wof:placetype":"venue"
},
  "geometry": {"coordinates":[4.5753660202,51.2949447632],"type":"Point"}
}