{
  "type": "Feature",
  "properties": {
    "iso:country":"BE",
    "sg:address":"Grote Markt 5",
    "sg:city":"Brussel/bruxelles",
    "sg:orig_category":"Hypotheken and hypotheekbanken Verbruikerskredietinstellingen",
    "sg:phone":"+32 2 547 12 11",
    "sg:postcode":"1000",
    "sg:province":"Bruxelles-Capitale",
    "wof:name":"Si\u00c8ge Cbc Banque",
    "wof:placetype":"venue"
},
  "geometry": {"coordinates":[4.3518018723,50.8471069336],"type":"Point"}
}