{
  "type": "Feature",
  "properties": {
    "addr:full":"Arbeidstraat 65b7 Aalst Oost-Vlaanderen 9300",
    "addr:housenumber":"65b7",
    "addr:postcode":"9300",
    "addr:street":"Arbeidstraat",
    "iso:country":"BE",
    "sg:address":"Arbeidstraat 65b7",
    "sg:city":"Aalst",
    "sg:orig_category":"Artsen and specialisten",
    "sg:phone":"+32 53 70 91 83",
    "sg:postcode":"9300",
    "sg:province":"Oost-Vlaanderen",
    "wof:name":"Pieter Van Dyck",
    "wof:placetype":"venue"
},
  "geometry": {"coordinates":[4.029214859,50.9362602234],"type":"Point"}
}