{
  "type": "Feature",
  "properties": {
    "addr:full":"Rijmenamseweg 171 Bonheiden Antwerpen 2820",
    "addr:housenumber":"171",
    "addr:postcode":"2820",
    "addr:street":"Rijmenamseweg",
    "iso:country":"BE",
    "sg:address":"Rijmenamseweg 171",
    "sg:city":"Bonheiden",
    "sg:orig_category":"Fabrication and montage de mobilier",
    "sg:phone":"+32 15 52 89 99",
    "sg:postcode":"2820",
    "sg:province":"Antwerpen",
    "wof:name":"Dimi",
    "wof:placetype":"venue"
},
  "geometry": {"coordinates":[4.5493650436,51.0046195984],"type":"Point"}
}