{
  "type": "Feature",
  "properties": {
    "addr:full":"Hofkwartier 33 Herentals Antwerpen 2200",
    "addr:housenumber":"33",
    "addr:postcode":"2200",
    "addr:street":"Hofkwartier",
    "iso:country":"BE",
    "sg:address":"Hofkwartier 33",
    "sg:city":"Herentals",
    "sg:classifiers":[
        {
            "category":"Shopping",
            "subcategory":"Hobbies, Toys, & Games",
            "type":"Retail Goods"
        }
    ],
    "sg:phone":"+32 14 21 61 93",
    "sg:postcode":"2200",
    "sg:province":"Antwerpen",
    "sg:tags":[
        "toy",
        "-"
    ],
    "wof:name":"Toys 4 All",
    "wof:placetype":"venue"
},
  "geometry": {"coordinates":[4.8351449966,51.1790847778],"type":"Point"}
}