{
  "type": "Feature",
  "properties": {
    "addr:full":"Gebr. De Winterstraat 7 Lille Antwerpen 2275",
    "addr:housenumber":"7",
    "addr:postcode":"2275",
    "addr:street":"Winterstraat",
    "iso:country":"BE",
    "sg:address":"Gebr. De Winterstraat 7",
    "sg:city":"Lille",
    "sg:orig_category":"Boucheries",
    "sg:phone":"+32 3 312 03 96",
    "sg:postcode":"2275",
    "sg:province":"Antwerpen",
    "wof:name":"Beenh. Jonkers-verheyen",
    "wof:placetype":"venue"
},
  "geometry": {"coordinates":[4.7868180275,51.2630233765],"type":"Point"}
}