{
  "type": "Feature",
  "properties": {
    "iso:country":"BE",
    "sg:address":"Rue Haute 17",
    "sg:city":"Stavelot",
    "sg:classifiers":[
        {
            "category":"Restaurant",
            "type":"Food & Drink"
        }
    ],
    "sg:phone":"+32 80 86 34 38",
    "sg:postcode":"4970",
    "sg:province":"Li\u00e8ge",
    "wof:name":"L'ane Culotte",
    "wof:placetype":"venue"
},
  "geometry": {"coordinates":[5.9309649467,50.3957748413],"type":"Point"}
}