{
  "type": "Feature",
  "properties": {
    "addr:full":"Moerkerkse Steenweg 269 Brugge (sint-kruis) West-Vlaanderen 8310",
    "addr:housenumber":"269",
    "addr:postcode":"8310",
    "addr:street":"Moerkerkse Steenweg",
    "iso:country":"BE",
    "sg:address":"Moerkerkse Steenweg 269",
    "sg:city":"Brugge (sint-kruis)",
    "sg:classifiers":[
        {
            "category":"Health Services",
            "subcategory":"Doctor",
            "type":"Services"
        }
    ],
    "sg:phone":"+32 50 36 45 53",
    "sg:postcode":"8310",
    "sg:province":"West-Vlaanderen",
    "sg:tags":[
        "medicinephysicians",
        "surgeon"
    ],
    "wof:name":"Claerhout Virginie",
    "wof:placetype":"venue"
},
  "geometry": {"coordinates":[3.2540099621,51.2140388489],"type":"Point"}
}