{
  "type": "Feature",
  "properties": {
    "iso:country":"BE",
    "sg:address":"Rue Du Calvaire 55",
    "sg:city":"Li\u00c8ge",
    "sg:orig_category":"Elektrische installaties voor woningen",
    "sg:phone":"+32 4 252 87 45",
    "sg:postcode":"4000",
    "sg:province":"Li\u00e8ge",
    "wof:name":"Serge Bihin",
    "wof:placetype":"venue"
},
  "geometry": {"coordinates":[5.5532698631,50.638256073],"type":"Point"}
}