{
  "type": "Feature",
  "properties": {
    "addr:full":"Priester Poppestraat 72 Mortsel Antwerpen 2640",
    "addr:housenumber":"72",
    "addr:postcode":"2640",
    "addr:street":"Priester Poppestraat",
    "iso:country":"BE",
    "sg:address":"Priester Poppestraat 72",
    "sg:city":"Mortsel",
    "sg:classifiers":[
        {
            "category":"Professional",
            "subcategory":"Accounting & Tax Preparation",
            "type":"Services"
        }
    ],
    "sg:phone":"+32 3 454 28 90",
    "sg:postcode":"2640",
    "sg:province":"Antwerpen",
    "sg:tags":[
        "bookkeeper"
    ],
    "wof:name":"Hofmans L",
    "wof:placetype":"venue"
},
  "geometry": {"coordinates":[4.479391098,51.1715164185],"type":"Point"}
}