{
  "type": "Feature",
  "properties": {
    "addr:full":"Rue Au Bois 155 Bruxelles (woluwe-saint-pierre) Bruxelles-Capitale 1150",
    "addr:housenumber":"155",
    "addr:postcode":"1150",
    "addr:street":"Rue Au Bois",
    "iso:country":"BE",
    "sg:address":"Rue Au Bois 155",
    "sg:city":"Bruxelles (woluwe-saint-pierre)",
    "sg:classifiers":[
        {
            "category":"Shopping",
            "subcategory":"Clothing, Apparel, & Fashions",
            "type":"Retail Goods"
        }
    ],
    "sg:phone":"+32 2 771 40 45",
    "sg:postcode":"1150",
    "sg:province":"Bruxelles-Capitale",
    "sg:tags":[
        "designer",
        "stylist"
    ],
    "wof:name":"Contours Sc",
    "wof:placetype":"venue"
},
  "geometry": {"coordinates":[4.445306778,50.8339157104],"type":"Point"}
}