{
  "type": "Feature",
  "properties": {
    "iso:country":"BE",
    "sg:address":"Rue De La Sucrerie 20",
    "sg:city":"Pecq",
    "sg:orig_category":"Agences d'exp\u00e9dition",
    "sg:phone":"+32 69 55 63 82",
    "sg:postcode":"7740",
    "sg:province":"Hainaut",
    "wof:name":"Reheul Andr\u00c9",
    "wof:placetype":"venue"
},
  "geometry": {"coordinates":[3.3454101086,50.7051506042],"type":"Point"}
}