{
  "type": "Feature",
  "properties": {
    "iso:country":"BE",
    "sg:address":"Rue Champ Du V\u00c9n\u00c9rable 10",
    "sg:city":"Villers-la-ville",
    "sg:orig_category":"Plomberie, chauffage and installations sanitaires",
    "sg:phone":"+32 71 87 87 77",
    "sg:postcode":"1495",
    "sg:province":"Brabant Wallon",
    "wof:name":"Dynatube",
    "wof:placetype":"venue"
},
  "geometry": {"coordinates":[4.5682029724,50.5853004456],"type":"Point"}
}