{
  "type": "Feature",
  "properties": {
    "addr:full":"Route Provinciale 29 Colfontaine (wasmes) Hainaut 7340",
    "addr:housenumber":"29",
    "addr:postcode":"7340",
    "addr:street":"Route Provinciale",
    "iso:country":"BE",
    "sg:address":"Route Provinciale 29",
    "sg:city":"Colfontaine (wasmes)",
    "sg:classifiers":[
        {
            "category":"Airport",
            "subcategory":"International",
            "type":"Transportation"
        }
    ],
    "sg:phone":"+32 65 51 25 39",
    "sg:postcode":"7340",
    "sg:province":"Hainaut",
    "sg:tags":[
        "-",
        "transport"
    ],
    "wof:name":"Transanastaze",
    "wof:placetype":"venue"
},
  "geometry": {"coordinates":[3.8575470448,50.4115371704],"type":"Point"}
}