{
  "type": "Feature",
  "properties": {
    "addr:full":"Sakramentstraat 5 Sint-niklaas Oost-Vlaanderen 9100",
    "addr:housenumber":"5",
    "addr:postcode":"9100",
    "addr:street":"Sakramentstraat",
    "iso:country":"BE",
    "sg:address":"Sakramentstraat 5",
    "sg:city":"Sint-niklaas",
    "sg:classifiers":[
        {
            "category":"Restaurant",
            "type":"Food & Drink"
        }
    ],
    "sg:phone":"+32 3 776 72 69",
    "sg:postcode":"9100",
    "sg:province":"Oost-Vlaanderen",
    "wof:name":"Het Laatste Avondmaal",
    "wof:placetype":"venue"
},
  "geometry": {"coordinates":[4.1429839134,51.1644935608],"type":"Point"}
}