{
  "type": "Feature",
  "properties": {
    "iso:country":"BE",
    "sg:address":"Galerie Louise 36b",
    "sg:city":"Elsene/ixelles",
    "sg:classifiers":[
        {
            "category":"Shopping",
            "subcategory":"Clothing, Apparel, & Fashions",
            "type":"Retail Goods"
        }
    ],
    "sg:phone":"+32 2 513 31 24",
    "sg:postcode":"1050",
    "sg:province":"Bruxelles-Capitale",
    "sg:tags":[
        "ondergoed",
        "lingerie"
    ],
    "wof:name":"Body And Clyde",
    "wof:placetype":"venue"
},
  "geometry": {"coordinates":[4.357380867,50.8362121582],"type":"Point"}
}