{
  "type": "Feature",
  "properties": {
    "addr:full":"Rue De La Flani\u00e8re 150 Charleroi (ransart) Hainaut 6043",
    "addr:housenumber":"150",
    "addr:postcode":"6043",
    "addr:street":"Rue De La Flanie\u0300Re",
    "iso:country":"BE",
    "sg:address":"Rue De La Flani\u00e8re 150",
    "sg:city":"Charleroi (ransart)",
    "sg:classifiers":[
        {
            "category":"Retail",
            "subcategory":"Auto Repair",
            "type":"Services"
        }
    ],
    "sg:phone":"+32 71 35 83 53",
    "sg:postcode":"6043",
    "sg:province":"Hainaut",
    "sg:tags":[
        "garage"
    ],
    "wof:name":"Vervloessem",
    "wof:placetype":"venue"
},
  "geometry": {"coordinates":[4.4839549065,50.4479637146],"type":"Point"}
}