{
  "type": "Feature",
  "properties": {
    "iso:country":"BE",
    "sg:address":"Weihoek 4",
    "sg:city":"Zaventem",
    "sg:orig_category":"Quincailleries",
    "sg:phone":"+32 2 714 09 00",
    "sg:postcode":"1930",
    "sg:province":"Vlaams-Brabant",
    "wof:name":"Facom Belgique",
    "wof:placetype":"venue"
},
  "geometry": {"coordinates":[4.5050759315,50.873008728],"type":"Point"}
}