{
  "type": "Feature",
  "properties": {
    "iso:country":"BE",
    "sg:address":"Rue Simonis 19",
    "sg:city":"Namur",
    "sg:classifiers":[
        {
            "category":"Structure",
            "subcategory":"Office Building",
            "type":"Public Place"
        }
    ],
    "sg:phone":"+32 81 73 64 33",
    "sg:postcode":"5000",
    "sg:province":"Namur",
    "sg:tags":[
        "drawing"
    ],
    "wof:name":"Bouvy N",
    "wof:placetype":"venue"
},
  "geometry": {"coordinates":[4.842484951,50.4619636536],"type":"Point"}
}