{
  "type": "Feature",
  "properties": {
    "addr:full":"Rue Des Carm\u00e9lites 170 Bruxelles (uccle) Bruxelles-Capitale 1180",
    "addr:housenumber":"170",
    "addr:postcode":"1180",
    "addr:street":"Rue Des Carme\u0301Lites",
    "iso:country":"BE",
    "sg:address":"Rue Des Carm\u00e9lites 170",
    "sg:city":"Bruxelles (uccle)",
    "sg:classifiers":[
        {
            "category":"Retail",
            "subcategory":"Event Space",
            "type":"Services"
        }
    ],
    "sg:phone":"+32 2 343 89 80",
    "sg:postcode":"1180",
    "sg:province":"Bruxelles-Capitale",
    "sg:tags":[
        "organisation"
    ],
    "wof:name":"Rivage",
    "wof:placetype":"venue"
},
  "geometry": {"coordinates":[4.3462920189,50.8126678467],"type":"Point"}
}