{
  "type": "Feature",
  "properties": {
    "addr:full":"Vlyminckshoek 119 Sint-niklaas Oost-Vlaanderen 9100",
    "addr:housenumber":"119",
    "addr:postcode":"9100",
    "addr:street":"Vlyminckshoek",
    "iso:country":"BE",
    "sg:address":"Vlyminckshoek 119",
    "sg:city":"Sint-niklaas",
    "sg:classifiers":[
        {
            "category":"Autos & Motor Vehicles",
            "subcategory":"Fuel & Gas Station",
            "type":"Retail Goods"
        }
    ],
    "sg:phone":"+32 3 776 14 68",
    "sg:postcode":"9100",
    "sg:province":"Oost-Vlaanderen",
    "wof:name":"Shell-verdeco",
    "wof:placetype":"venue"
},
  "geometry": {"coordinates":[4.1125612259,51.1754722595],"type":"Point"}
}