{
  "type": "Feature",
  "properties": {
    "iso:country":"BE",
    "sg:address":"Route De Coo 90",
    "sg:city":"Trois-ponts",
    "sg:orig_category":"Fietsen Herstellingen and onderhoud van auto's Motorfietsen Tuinbenodigdheden",
    "sg:phone":"+32 80 68 42 50",
    "sg:postcode":"4980",
    "sg:province":"Li\u00e8ge",
    "wof:name":"Garage Maesen",
    "wof:placetype":"venue"
},
  "geometry": {"coordinates":[5.8734002113,50.3754692078],"type":"Point"}
}