{
  "type": "Feature",
  "properties": {
    "iso:country":"BE",
    "sg:address":"Rue Joseph Wauters 37",
    "sg:city":"Charleroi (gosselies)",
    "sg:classifiers":[
        {
            "category":"Personal",
            "subcategory":"Nail Salon",
            "type":"Services"
        }
    ],
    "sg:phone":"+32 71 37 70 99",
    "sg:postcode":"6041",
    "sg:province":"Hainaut",
    "sg:tags":[
        "pedicure"
    ],
    "wof:name":"Hiernaut A",
    "wof:placetype":"venue"
},
  "geometry": {"coordinates":[4.4586420059,50.4247093201],"type":"Point"}
}