{
  "type": "Feature",
  "properties": {
    "addr:full":"Industrieter. Ravenshout 3137 Tessenderlo Limburg 3980",
    "addr:postcode":"3137 tessenderlo;3980",
    "addr:street":"Ravenshout",
    "iso:country":"BE",
    "sg:address":"Industrieter. Ravenshout 3137",
    "sg:city":"Tessenderlo",
    "sg:orig_category":"V\u00eatements, chaussures and accessoires Imprimeries and copyshops",
    "sg:phone":"+32 13 67 13 67",
    "sg:postcode":"3980",
    "sg:province":"Limburg",
    "wof:name":"Bio-racer, Ten-men",
    "wof:placetype":"venue"
},
  "geometry": {"coordinates":[5.1427359581,51.0711669922],"type":"Point"}
}