{
  "type": "Feature",
  "properties": {
    "addr:full":"Provincieweg 73 Herzele Oost-Vlaanderen 9552",
    "addr:housenumber":"73",
    "addr:postcode":"9552",
    "addr:street":"Provincieweg;Oost-Vlaanderen",
    "iso:country":"BE",
    "sg:address":"Provincieweg 73",
    "sg:city":"Herzele",
    "sg:orig_category":"Enseignement maternel and primaire",
    "sg:phone":"+32 53 62 43 77",
    "sg:postcode":"9552",
    "sg:province":"Oost-Vlaanderen",
    "wof:name":"Vrije Basisschool",
    "wof:placetype":"venue"
},
  "geometry": {"coordinates":[3.8929040432,50.9047431946],"type":"Point"}
}