{
  "type": "Feature",
  "properties": {
    "iso:country":"BE",
    "sg:address":"Lange Lozanastraat 290",
    "sg:city":"Antwerpen",
    "sg:classifiers":[
        {
            "category":"Home & Garden",
            "subcategory":"Home Furnishings",
            "type":"Retail Goods"
        }
    ],
    "sg:phone":"+32 3 238 37 00",
    "sg:postcode":"2018",
    "sg:province":"Antwerpen",
    "sg:tags":[
        "interior",
        "decoration"
    ],
    "wof:name":"Indigo Woondecoratie Nv",
    "wof:placetype":"venue"
},
  "geometry": {"coordinates":[4.4072070122,51.1983985901],"type":"Point"}
}