{
  "type": "Feature",
  "properties": {
    "addr:full":"La Boverie 97 Rendeux Luxembourg 6987",
    "addr:housenumber":"97",
    "addr:postcode":"6987",
    "addr:street":"La Boverie",
    "iso:country":"BE",
    "sg:address":"La Boverie 97",
    "sg:city":"Rendeux",
    "sg:classifiers":[
        {
            "category":"Restaurant",
            "type":"Food & Drink"
        }
    ],
    "sg:phone":"+32 84 47 77 97",
    "sg:postcode":"6987",
    "sg:province":"Luxembourg",
    "wof:name":"Restaurant Le Magni",
    "wof:placetype":"venue"
},
  "geometry": {"coordinates":[5.503636837,50.2335166931],"type":"Point"}
}