{
  "type": "Feature",
  "properties": {
    "iso:country":"BE",
    "sg:address":"Steenweg Op Ravels 4b1",
    "sg:city":"Oud-turnhout",
    "sg:orig_category":"Installation \u00e9lectrique r\u00e9sidentielle",
    "sg:phone":"+32 14 42 43 78",
    "sg:postcode":"2360",
    "sg:province":"Antwerpen",
    "wof:name":"A.i.t.",
    "wof:placetype":"venue"
},
  "geometry": {"coordinates":[4.9676299095,51.3359489441],"type":"Point"}
}