{
  "type": "Feature",
  "properties": {
    "addr:full":"Rue Haute 2 Lens Hainaut 7870",
    "addr:housenumber":"2",
    "addr:postcode":"7870",
    "addr:street":"Rue Haute",
    "iso:country":"BE",
    "sg:address":"Rue Haute 2",
    "sg:city":"Lens",
    "sg:orig_category":"Enseignement maternel and primaire",
    "sg:phone":"+32 68 45 54 19",
    "sg:postcode":"7870",
    "sg:province":"Hainaut",
    "wof:name":"Ecole Fond. Communale",
    "wof:placetype":"venue"
},
  "geometry": {"coordinates":[3.9177520275,50.5829162598],"type":"Point"}
}