{
  "type": "Feature",
  "properties": {
    "addr:full":"Avenue Gevaert 196 Rixensart (genval) Brabant Wallon 1332",
    "addr:housenumber":"196",
    "addr:postcode":"1332",
    "addr:street":"Avenue Gevaert",
    "iso:country":"BE",
    "sg:address":"Avenue Gevaert 196",
    "sg:city":"Rixensart (genval)",
    "sg:classifiers":[
        {
            "category":"Professional",
            "subcategory":"Management & Consulting",
            "type":"Services"
        }
    ],
    "sg:phone":"+32 2 653 06 59",
    "sg:postcode":"1332",
    "sg:province":"Brabant Wallon",
    "sg:tags":[
        "consultant"
    ],
    "wof:name":"Lucrificus",
    "wof:placetype":"venue"
},
  "geometry": {"coordinates":[4.5060348511,50.7240524292],"type":"Point"}
}