{
  "type": "Feature",
  "properties": {
    "addr:full":"Industrieweg 1315 Zonhoven Limburg 3520",
    "addr:postcode":"1315 zonhoven;3520",
    "addr:street":"Industrieweg",
    "iso:country":"BE",
    "sg:address":"Industrieweg 1315",
    "sg:city":"Zonhoven",
    "sg:classifiers":[
        {
            "category":"Manufacturing",
            "subcategory":"Metals",
            "type":"Manufacturing & Wholesale Goods"
        }
    ],
    "sg:phone":"+32 11 81 37 91",
    "sg:postcode":"3520",
    "sg:province":"Limburg",
    "sg:tags":[
        "steel",
        "stainless"
    ],
    "wof:name":"Karremans Nv",
    "wof:placetype":"venue"
},
  "geometry": {"coordinates":[5.3905029297,51.001865387],"type":"Point"}
}