{
  "type": "Feature",
  "properties": {
    "addr:full":"Grotestraat 90 Moeskroen/mouscron Hainaut 7700",
    "addr:housenumber":"90",
    "addr:postcode":"7700",
    "addr:street":"Grotestraat",
    "iso:country":"BE",
    "sg:address":"Grotestraat 90",
    "sg:city":"Moeskroen/mouscron",
    "sg:classifiers":[
        {
            "category":"Communications",
            "subcategory":"Television Station",
            "type":"Services"
        }
    ],
    "sg:phone":"+32 56 33 21 47",
    "sg:postcode":"7700",
    "sg:province":"Hainaut",
    "sg:tags":[
        "video",
        "audio",
        "verhuur"
    ],
    "wof:name":"Serge Vandewalle",
    "wof:placetype":"venue"
},
  "geometry": {"coordinates":[3.2323200703,50.7400932312],"type":"Point"}
}