{
  "type": "Feature",
  "properties": {
    "addr:full":"Lindelsebaan 273 Overpelt Limburg 3900",
    "addr:housenumber":"273",
    "addr:postcode":"3900",
    "addr:street":"Lindelsebaan",
    "iso:country":"BE",
    "sg:address":"Lindelsebaan 273",
    "sg:city":"Overpelt",
    "sg:orig_category":"Kinderopvang",
    "sg:phone":"+32 11 66 59 12",
    "sg:postcode":"3900",
    "sg:province":"Limburg",
    "wof:name":"'t Ravotterke",
    "wof:placetype":"venue"
},
  "geometry": {"coordinates":[5.4038248062,51.2006797791],"type":"Point"}
}