{
  "type": "Feature",
  "properties": {
    "addr:full":"Rue Defize 21 Ans Li\u00e8ge 4431",
    "addr:housenumber":"21",
    "addr:postcode":"4431",
    "addr:street":"Rue Defize",
    "iso:country":"BE",
    "sg:address":"Rue Defize 21",
    "sg:city":"Ans",
    "sg:orig_category":"Kapsalons",
    "sg:phone":"+32 4 263 67 37",
    "sg:postcode":"4431",
    "sg:province":"Li\u00e8ge",
    "wof:name":"Eugene Gerard",
    "wof:placetype":"venue"
},
  "geometry": {"coordinates":[5.5043897629,50.6645622253],"type":"Point"}
}