{
  "type": "Feature",
  "properties": {
    "iso:country":"BE",
    "sg:address":"Cellebroersstraat 59",
    "sg:city":"Brussel/bruxelles",
    "sg:orig_category":"Zalen voor culturele evenementen",
    "sg:phone":"+32 2 511 04 11",
    "sg:postcode":"1000",
    "sg:province":"Bruxelles-Capitale",
    "wof:name":"Galerie Art En Marge",
    "wof:placetype":"venue"
},
  "geometry": {"coordinates":[4.3507819176,50.8427810669],"type":"Point"}
}