{
  "type": "Feature",
  "properties": {
    "addr:full":"Brucargo Building 746 Brucargo 1931",
    "addr:housenumber":"746",
    "addr:postcode":"1931",
    "addr:street":"Brucargo",
    "iso:country":"BE",
    "sg:address":"Brucargo Building 746",
    "sg:city":"Brucargo",
    "sg:classifiers":[
        {
            "category":"Airport",
            "type":"Transportation"
        }
    ],
    "sg:phone":"+32 2 752 25 11",
    "sg:postcode":"1931",
    "sg:tags":[
        "air-freight",
        "forwarders"
    ],
    "wof:name":"Abx Nv",
    "wof:placetype":"venue"
},
  "geometry": {"coordinates":[-98.1283187866,18.5928096771],"type":"Point"}
}