{
  "type": "Feature",
  "properties": {
    "addr:full":"Hogeweg 67 Aalst (erembodegem) Oost-Vlaanderen 9320",
    "addr:housenumber":"67",
    "addr:postcode":"9320",
    "addr:street":"Hogeweg",
    "iso:country":"BE",
    "sg:address":"Hogeweg 67",
    "sg:city":"Aalst (erembodegem)",
    "sg:classifiers":[
        {
            "category":"Shopping",
            "subcategory":"Clothing, Apparel, & Fashions",
            "type":"Retail Goods"
        }
    ],
    "sg:phone":"+32 53 70 22 30",
    "sg:postcode":"9320",
    "sg:province":"Oost-Vlaanderen",
    "sg:tags":[
        "underwear",
        "lingerie",
        "-"
    ],
    "wof:name":"Reni's",
    "wof:placetype":"venue"
},
  "geometry": {"coordinates":[4.0553851128,50.9209976196],"type":"Point"}
}