{
  "type": "Feature",
  "properties": {
    "addr:full":"Rue Neufch\u00c2tel 34 Bruxelles-saint-gilles Bruxelles-Capitale 1060",
    "addr:housenumber":"34",
    "addr:postcode":"1060",
    "addr:street":"Rue Neufcha\u0302Tel",
    "iso:country":"BE",
    "sg:address":"Rue Neufch\u00c2tel 34",
    "sg:city":"Bruxelles-saint-gilles",
    "sg:orig_category":"Erotische Etablissementen",
    "sg:phone":"+32 2 537 37 25",
    "sg:postcode":"1060",
    "sg:province":"Bruxelles-Capitale",
    "wof:name":"Le 34",
    "wof:placetype":"venue"
},
  "geometry": {"coordinates":[4.353635788,50.8274040222],"type":"Point"}
}