{
  "type": "Feature",
  "properties": {
    "addr:full":". Luik Li\u00e8ge 4000",
    "addr:postcode":"4000",
    "iso:country":"BE",
    "sg:address":".",
    "sg:city":"Luik",
    "sg:orig_category":"Warenhuizen",
    "sg:phone":"+32 4 349 37 11",
    "sg:postcode":"4000",
    "sg:province":"Li\u00e8ge",
    "wof:name":"Hema",
    "wof:placetype":"venue"
},
  "geometry": {"coordinates":[5.5725908279,50.6450042725],"type":"Point"}
}