{
  "type": "Feature",
  "properties": {
    "iso:country":"BE",
    "sg:address":"Rameistraat 62",
    "sg:city":"Overijse",
    "sg:classifiers":[
        {
            "category":"Wholesale",
            "subcategory":"Wine & Distilled Alcoholic Beverages",
            "type":"Manufacturing & Wholesale Goods"
        }
    ],
    "sg:phone":"+32 2 687 76 00",
    "sg:postcode":"3090",
    "sg:province":"Vlaams-Brabant",
    "sg:tags":[
        "whol",
        "-",
        "spirit",
        "mfg"
    ],
    "wof:name":"All Drinks Brux-ale",
    "wof:placetype":"venue"
},
  "geometry": {"coordinates":[4.5385890007,50.7509765625],"type":"Point"}
}