{
  "type": "Feature",
  "properties": {
    "addr:full":"Sprietestraat 216 Waregem (desselgem) West-Vlaanderen 8792",
    "addr:housenumber":"216",
    "addr:postcode":"8792",
    "addr:street":"Sprietestraat",
    "iso:country":"BE",
    "sg:address":"Sprietestraat 216",
    "sg:city":"Waregem (desselgem)",
    "sg:classifiers":[
        {
            "category":"Manufacturing",
            "subcategory":"Printing",
            "type":"Manufacturing & Wholesale Goods"
        }
    ],
    "sg:phone":"+32 56 70 03 48",
    "sg:postcode":"8792",
    "sg:province":"West-Vlaanderen",
    "sg:tags":[
        "textile",
        "-"
    ],
    "wof:name":"Catch Letter",
    "wof:placetype":"venue"
},
  "geometry": {"coordinates":[3.3672049046,50.8728256226],"type":"Point"}
}