{
  "type": "Feature",
  "properties": {
    "addr:full":"Chemin De Xh\u00e9norie 1 Thimister-clermont (thimister) Li\u00e8ge 4890",
    "addr:housenumber":"1",
    "addr:postcode":"4890",
    "addr:street":"Chemin De Xhe\u0301Norie",
    "iso:country":"BE",
    "sg:address":"Chemin De Xh\u00e9norie 1",
    "sg:city":"Thimister-clermont (thimister)",
    "sg:classifiers":[
        {
            "category":"Building & Trades",
            "subcategory":"Construction",
            "type":"Services"
        }
    ],
    "sg:phone":"+32 87 32 30 40",
    "sg:postcode":"4890",
    "sg:province":"Li\u00e8ge",
    "sg:tags":[
        "duct",
        "underground",
        "ducting"
    ],
    "wof:name":"Sageco Sa",
    "wof:placetype":"venue"
},
  "geometry": {"coordinates":[5.875690937,50.6317863464],"type":"Point"}
}