{
  "type": "Feature",
  "properties": {
    "iso:country":"BE",
    "sg:address":"Rue Lafoug\u00c8re 8",
    "sg:city":"Binche",
    "sg:orig_category":"Apotheken",
    "sg:phone":"+32 64 33 10 30",
    "sg:postcode":"7131",
    "sg:province":"Hainaut",
    "wof:name":"Pharmacie De Waudrez",
    "wof:placetype":"venue"
},
  "geometry": {"coordinates":[4.1579217911,50.4120674133],"type":"Point"}
}