{
  "type": "Feature",
  "properties": {
    "iso:country":"BE",
    "sg:address":"Torenveld 38",
    "sg:city":"Tessenderlo",
    "sg:orig_category":"Maatkleding Fab",
    "sg:phone":"+32 13 67 16 03",
    "sg:postcode":"3980",
    "sg:province":"Limburg",
    "wof:name":"Louisa Thues",
    "wof:placetype":"venue"
},
  "geometry": {"coordinates":[5.0780701637,51.0567016602],"type":"Point"}
}