{
  "type": "Feature",
  "properties": {
    "iso:country":"BE",
    "sg:address":"Hannuitsesteenweg 111",
    "sg:city":"Landen",
    "sg:classifiers":[
        {
            "category":"Health Services",
            "subcategory":"Dentist",
            "type":"Services"
        }
    ],
    "sg:phone":"+32 11 88 38 70",
    "sg:postcode":"3400",
    "sg:province":"Vlaams-Brabant",
    "wof:name":"Wouters Rudy",
    "wof:placetype":"venue"
},
  "geometry": {"coordinates":[5.0812969208,50.7430610657],"type":"Point"}
}