{
  "type": "Feature",
  "properties": {
    "iso:country":"BE",
    "sg:address":"Rue Commune 1",
    "sg:city":"Pont-a-celles",
    "sg:orig_category":"Rundveehouders",
    "sg:phone":"+32 71 84 46 94",
    "sg:postcode":"6230",
    "sg:province":"Hainaut",
    "wof:name":"Michel Paternoster",
    "wof:placetype":"venue"
},
  "geometry": {"coordinates":[4.3665099144,50.5268821716],"type":"Point"}
}