{
  "type": "Feature",
  "properties": {
    "iso:country":"BE",
    "sg:address":"Rue De La Place 15",
    "sg:city":"Antoing",
    "sg:orig_category":"Paramedische behandelingen",
    "sg:phone":"+32 69 44 42 50",
    "sg:postcode":"7640",
    "sg:province":"Hainaut",
    "wof:name":"C\u00c9cile Colin",
    "wof:placetype":"venue"
},
  "geometry": {"coordinates":[3.4551160336,50.5516548157],"type":"Point"}
}