{
  "type": "Feature",
  "properties": {
    "iso:country":"BE",
    "sg:address":"Rue Des Fabriques 15b1",
    "sg:city":"Waremme",
    "sg:orig_category":"Gespecialiseerde residenti\u00eble bouw Woningbouw",
    "sg:phone":"+32 19 33 08 94",
    "sg:postcode":"4300",
    "sg:province":"Li\u00e8ge",
    "wof:name":"Caspers Entreprises",
    "wof:placetype":"venue"
},
  "geometry": {"coordinates":[5.2485880852,50.6926116943],"type":"Point"}
}