{
  "type": "Feature",
  "properties": {
    "iso:country":"BE",
    "sg:address":"Avenue Eug\u00c8ne Plasky 31",
    "sg:city":"Schaarbeek/schaerbeek",
    "sg:orig_category":"Salles de spectacles",
    "sg:phone":"+32 2 742 93 83",
    "sg:postcode":"1030",
    "sg:province":"Bruxelles-Capitale",
    "wof:name":"Th\u00c9\u00c2tre Altane",
    "wof:placetype":"venue"
},
  "geometry": {"coordinates":[4.3958258629,50.8487663269],"type":"Point"}
}