{
  "type": "Feature",
  "properties": {
    "addr:full":"Rue Gaucet 50 Li\u00c8ge Li\u00e8ge 4020",
    "addr:housenumber":"50",
    "addr:postcode":"4020",
    "addr:street":"Rue Gaucet",
    "iso:country":"BE",
    "sg:address":"Rue Gaucet 50",
    "sg:city":"Li\u00c8ge",
    "sg:orig_category":"Sportclubs",
    "sg:phone":"+32 486 53 67 91",
    "sg:postcode":"4020",
    "sg:province":"Li\u00e8ge",
    "wof:name":"J.c. Dojo Li\u00c9geois",
    "wof:placetype":"venue"
},
  "geometry": {"coordinates":[5.5822949409,50.6248321533],"type":"Point"}
}