{
  "type": "Feature",
  "properties": {
    "addr:full":"Industrieweg 114h Gent (wondelgem) Oost-Vlaanderen 9032",
    "addr:housenumber":"114h",
    "addr:postcode":"9032",
    "addr:street":"Industrieweg",
    "iso:country":"BE",
    "sg:address":"Industrieweg 114h",
    "sg:city":"Gent (wondelgem)",
    "sg:classifiers":[
        {
            "category":"Manufacturing",
            "subcategory":"Tools & Machinery",
            "type":"Manufacturing & Wholesale Goods"
        }
    ],
    "sg:phone":"+32 9 216 60 20",
    "sg:postcode":"9032",
    "sg:province":"Oost-Vlaanderen",
    "sg:tags":[
        "pneumatic"
    ],
    "wof:name":"Scanrotor Nv",
    "wof:placetype":"venue"
},
  "geometry": {"coordinates":[3.6899850368,51.0904388428],"type":"Point"}
}