{
  "type": "Feature",
  "properties": {
    "iso:country":"BE",
    "sg:address":"Hoogstraat 121",
    "sg:city":"As",
    "sg:classifiers":[
        {
            "category":"Health Services",
            "subcategory":"Dentist",
            "type":"Services"
        }
    ],
    "sg:phone":"+32 89 65 83 73",
    "sg:postcode":"3665",
    "sg:province":"Limburg",
    "wof:name":"Schreurs Philip",
    "wof:placetype":"venue"
},
  "geometry": {"coordinates":[5.5937099457,51.0107917786],"type":"Point"}
}