{
  "type": "Feature",
  "properties": {
    "addr:full":"Campus Universitaire Mons Hainaut 7000",
    "addr:postcode":"7000",
    "addr:street":"Hainaut",
    "iso:country":"BE",
    "sg:address":"Campus Universitaire",
    "sg:city":"Mons",
    "sg:classifiers":[
        {
            "category":"Cinema",
            "subcategory":"Movie Theater",
            "type":"Entertainment"
        }
    ],
    "sg:phone":"+32 65 35 46 73",
    "sg:postcode":"7000",
    "sg:province":"Hainaut",
    "wof:name":"Imagimons Sa",
    "wof:placetype":"venue"
},
  "geometry": {"coordinates":[3.9476399422,50.4596786499],"type":"Point"}
}