{
  "type": "Feature",
  "properties": {
    "addr:full":"Windeweg 1 Ieper (dikkebus) West-Vlaanderen 8900",
    "addr:housenumber":"1",
    "addr:postcode":"8900",
    "addr:street":"Windeweg",
    "iso:country":"BE",
    "sg:address":"Windeweg 1",
    "sg:city":"Ieper (dikkebus)",
    "sg:classifiers":[
        {
            "category":"Building & Trades",
            "subcategory":"Electrical",
            "type":"Services"
        }
    ],
    "sg:phone":"+32 57 20 22 02",
    "sg:postcode":"8900",
    "sg:province":"West-Vlaanderen",
    "sg:tags":[
        "electric",
        "-",
        "housewiring",
        "contractor"
    ],
    "wof:name":"Vandamme G",
    "wof:placetype":"venue"
},
  "geometry": {"coordinates":[2.830780983,50.8235969543],"type":"Point"}
}