{
  "type": "Feature",
  "properties": {
    "addr:full":"Grootloonstraat 115 Borgloon Limburg 3840",
    "addr:housenumber":"115",
    "addr:postcode":"3840",
    "addr:street":"Grootloonstraat",
    "iso:country":"BE",
    "sg:address":"Grootloonstraat 115",
    "sg:city":"Borgloon",
    "sg:orig_category":"Fruitteelt Varkenskwekers",
    "sg:phone":"+32 12 74 22 91",
    "sg:postcode":"3840",
    "sg:province":"Limburg",
    "wof:name":"Edmond Ghysens",
    "wof:placetype":"venue"
},
  "geometry": {"coordinates":[5.3589439392,50.7962188721],"type":"Point"}
}