{
  "type": "Feature",
  "properties": {
    "addr:full":"Zerkegemstraat 21 Ichtegem (bekegem) West-Vlaanderen 8480",
    "addr:housenumber":"21",
    "addr:postcode":"8480",
    "addr:street":"Zerkegemstraat",
    "iso:country":"BE",
    "sg:address":"Zerkegemstraat 21",
    "sg:city":"Ichtegem (bekegem)",
    "sg:orig_category":"Non-Classified Establishments",
    "sg:phone":"+32 50 81 12 45",
    "sg:postcode":"8480",
    "sg:province":"West-Vlaanderen",
    "wof:name":"Claeys M",
    "wof:placetype":"venue"
},
  "geometry": {"coordinates":[3.0562319756,51.1587600708],"type":"Point"}
}