{
  "type": "Feature",
  "properties": {
    "addr:full":"Roetaard 42 Lint Antwerpen 2547",
    "addr:housenumber":"42",
    "addr:postcode":"2547",
    "addr:street":"Roetaard",
    "iso:country":"BE",
    "sg:address":"Roetaard 42",
    "sg:city":"Lint",
    "sg:orig_category":"M\u00e9decins and sp\u00e9cialistes",
    "sg:phone":"+32 3 454 22 12",
    "sg:postcode":"2547",
    "sg:province":"Antwerpen",
    "wof:name":"An Wouters",
    "wof:placetype":"venue"
},
  "geometry": {"coordinates":[4.4960260391,51.1207084656],"type":"Point"}
}