{
  "type": "Feature",
  "properties": {
    "addr:full":"R Du Cercle De Tir 3 Achene Namur 5590",
    "addr:housenumber":"3",
    "addr:postcode":"5590",
    "addr:street":"R;Achene Namur",
    "iso:country":"BE",
    "sg:address":"R Du Cercle De Tir 3",
    "sg:city":"Achene",
    "sg:classifiers":[
        {
            "category":"Home & Garden",
            "subcategory":"Building Materials",
            "type":"Retail Goods"
        }
    ],
    "sg:phone":"+32 83 21 70 97",
    "sg:postcode":"5590",
    "sg:province":"Namur",
    "sg:tags":[
        "cutting",
        "laser",
        "welding"
    ],
    "wof:name":"O.c.b.",
    "wof:placetype":"venue"
},
  "geometry": {"coordinates":[5.1022520065,50.297088623],"type":"Point"}
}