{
  "type": "Feature",
  "properties": {
    "addr:full":"Avenue Des Combattants 126 Genappe Brabant Wallon 1470",
    "addr:housenumber":"126",
    "addr:postcode":"1470",
    "addr:street":"Avenue Des Combattants;Wallon",
    "iso:country":"BE",
    "sg:address":"Avenue Des Combattants 126",
    "sg:city":"Genappe",
    "sg:classifiers":[
        {
            "category":"Cafe",
            "type":"Food & Drink"
        }
    ],
    "sg:phone":"+32 10 61 58 43",
    "sg:postcode":"1470",
    "sg:province":"Brabant Wallon",
    "sg:tags":[
        "caf\u00e9s"
    ],
    "wof:name":"Josevski Lube",
    "wof:placetype":"venue"
},
  "geometry": {"coordinates":[4.5296697617,50.625667572],"type":"Point"}
}