{
  "type": "Feature",
  "properties": {
    "iso:country":"BE",
    "sg:address":"Kerkstraat 59",
    "sg:city":"De Haan (wenduine)",
    "sg:classifiers":[
        {
            "category":"Real Estate",
            "subcategory":"Real Estate Services",
            "type":"Services"
        }
    ],
    "sg:phone":"+32 50 41 38 29",
    "sg:postcode":"8420",
    "sg:province":"West-Vlaanderen",
    "wof:name":"Immo Florizoone",
    "wof:placetype":"venue"
},
  "geometry": {"coordinates":[3.0811970234,51.2992591858],"type":"Point"}
}