{
  "type": "Feature",
  "properties": {
    "addr:full":"Rue De L'eglise 116-118 Woluwe-saint-pierre Bruxelles-Capitale 1150",
    "addr:postcode":"116-118;1150",
    "addr:street":"Rue De L'Eglise",
    "iso:country":"BE",
    "sg:address":"Rue De L'eglise 116-118",
    "sg:city":"Woluwe-saint-pierre",
    "sg:orig_category":"Cosmetica and toiletartikelen Drogisterijen",
    "sg:phone":"+32 2 772 83 13",
    "sg:postcode":"1150",
    "sg:province":"Bruxelles-Capitale",
    "wof:name":"Di",
    "wof:placetype":"venue"
},
  "geometry": {"coordinates":[4.4647488594,50.8405952454],"type":"Point"}
}