{
  "type": "Feature",
  "properties": {
    "iso:country":"BE",
    "sg:address":"Bloempotstraat 41",
    "sg:city":"Sint-gillis-waas",
    "sg:orig_category":"Eleveurs de bovins",
    "sg:phone":"+32 3 773 43 87",
    "sg:postcode":"9170",
    "sg:province":"Oost-Vlaanderen",
    "wof:name":"Gustaaf Verherbruggen",
    "wof:placetype":"venue"
},
  "geometry": {"coordinates":[4.1575880051,51.2536582947],"type":"Point"}
}