{
  "type": "Feature",
  "properties": {
    "addr:full":"Leopold Ii Laan 78 Sint-jans-molenbeek/molenbeek-saint-jean Bruxelles-Capitale 1080",
    "addr:housenumber":"78",
    "addr:postcode":"1080",
    "addr:street":"Leopold Ii Laan",
    "iso:country":"BE",
    "sg:address":"Leopold Ii Laan 78",
    "sg:city":"Sint-jans-molenbeek/molenbeek-saint-jean",
    "sg:orig_category":"Industri\u00eble wasserijen and droogkuis",
    "sg:phone":"+32 2 414 18 61",
    "sg:postcode":"1080",
    "sg:province":"Bruxelles-Capitale",
    "wof:name":"New Quality Cleaning",
    "wof:placetype":"venue"
},
  "geometry": {"coordinates":[4.3410248756,50.8598747253],"type":"Point"}
}