{
  "type": "Feature",
  "properties": {
    "iso:country":"BE",
    "sg:address":"Ch D'aelbeke 223",
    "sg:city":"Mouscron",
    "sg:orig_category":"Installation \u00e9lectrique r\u00e9sidentielle",
    "sg:phone":"+32 475 86 51 53",
    "sg:postcode":"7700",
    "sg:province":"Hainaut",
    "wof:name":"Courcelles",
    "wof:placetype":"venue"
},
  "geometry": {"coordinates":[3.2218658924,50.7575263977],"type":"Point"}
}