{
  "type": "Feature",
  "properties": {
    "iso:country":"BE",
    "sg:address":"Rue De La Liesse 92",
    "sg:city":"Moeskroen/mouscron",
    "sg:classifiers":[
        {
            "category":"Food & Beverages",
            "subcategory":"Fruits & Vegetables",
            "type":"Retail Goods"
        }
    ],
    "sg:phone":"+32 56 33 12 39",
    "sg:postcode":"7700",
    "sg:province":"Hainaut",
    "sg:tags":[
        "l\u00e9gumes",
        "gr"
    ],
    "wof:name":"Brouckaert",
    "wof:placetype":"venue"
},
  "geometry": {"coordinates":[3.2323200703,50.7400932312],"type":"Point"}
}