{
  "type": "Feature",
  "properties": {
    "iso:country":"BE",
    "sg:address":"Rue Du Remblai 38",
    "sg:city":"Brussel/bruxelles",
    "sg:orig_category":"Salles de spectacles",
    "sg:phone":"+32 2 534 30 97",
    "sg:postcode":"1000",
    "sg:province":"Bruxelles-Capitale",
    "wof:name":"Compagnie Na",
    "wof:placetype":"venue"
},
  "geometry": {"coordinates":[4.3445768356,50.833946228],"type":"Point"}
}