{
  "type": "Feature",
  "properties": {
    "addr:full":"Rue Du Pacifique 34 Ukkel/uccle Bruxelles-Capitale 1180",
    "addr:housenumber":"34",
    "addr:postcode":"1180",
    "addr:street":"Rue Du Pacifique;/",
    "iso:country":"BE",
    "sg:address":"Rue Du Pacifique 34",
    "sg:city":"Ukkel/uccle",
    "sg:orig_category":"Agences immobili\u00e8res",
    "sg:phone":"+32 2 346 00 01",
    "sg:postcode":"1180",
    "sg:province":"Bruxelles-Capitale",
    "wof:name":"Eric Debroux",
    "wof:placetype":"venue"
},
  "geometry": {"coordinates":[4.3550419807,50.8134422302],"type":"Point"}
}