{
  "type": "Feature",
  "properties": {
    "addr:full":"Poelkapellestraat 49 Langemark West-Vlaanderen 8920",
    "addr:housenumber":"49",
    "addr:postcode":"8920",
    "addr:street":"Poelkapellestraat",
    "iso:country":"BE",
    "sg:address":"Poelkapellestraat 49",
    "sg:city":"Langemark",
    "sg:classifiers":[
        {
            "category":"Real Estate",
            "subcategory":"Architect",
            "type":"Services"
        }
    ],
    "sg:phone":"+32 57 48 87 71",
    "sg:postcode":"8920",
    "sg:province":"West-Vlaanderen",
    "sg:tags":[
        "concrete",
        "masonry",
        "work",
        "supraregional"
    ],
    "wof:name":"Verkinderen Wegenisbouw Nv",
    "wof:placetype":"venue"
},
  "geometry": {"coordinates":[2.9321451187,50.9173545837],"type":"Point"}
}