{
  "type": "Feature",
  "properties": {
    "iso:country":"BE",
    "sg:address":"Kerkstraat 26",
    "sg:city":"Rotselaar",
    "sg:orig_category":"Diverse zakelijke dienstverlening",
    "sg:phone":"+32 16 58 97 60",
    "sg:postcode":"3111",
    "sg:province":"Vlaams-Brabant",
    "wof:name":"Ziezo",
    "wof:placetype":"venue"
},
  "geometry": {"coordinates":[4.7548718452,50.9479560852],"type":"Point"}
}