{
  "type": "Feature",
  "properties": {
    "addr:full":"Av. Des Croix De Guerre 125b7 Brussel/bruxelles Bruxelles-Capitale 1120",
    "addr:housenumber":"125b7",
    "addr:postcode":"1120",
    "addr:street":"Av. Des Croix De Guerre;/",
    "iso:country":"BE",
    "sg:address":"Av. Des Croix De Guerre 125b7",
    "sg:city":"Brussel/bruxelles",
    "sg:orig_category":"Editeurs de revues and p\u00e9riodiques. Editeurs de journaux",
    "sg:phone":"+32 2 242 27 58",
    "sg:postcode":"1120",
    "sg:province":"Bruxelles-Capitale",
    "wof:name":"Union Royal. Fleur. Belg.",
    "wof:placetype":"venue"
},
  "geometry": {"coordinates":[4.3820509911,50.8901634216],"type":"Point"}
}