{
  "type": "Feature",
  "properties": {
    "addr:full":"Avenue Charles Quint 420 Bruxelles-berchem-sainte-agathe Bruxelles-Capitale 1082",
    "addr:housenumber":"420",
    "addr:postcode":"1082",
    "addr:street":"Avenue Charles Quint",
    "iso:country":"BE",
    "sg:address":"Avenue Charles Quint 420",
    "sg:city":"Bruxelles-berchem-sainte-agathe",
    "sg:orig_category":"Syst\u00e8mes de t\u00e9l\u00e9communications. The Phone House",
    "sg:phone":"+32 2 481 59 20",
    "sg:postcode":"1082",
    "sg:province":"Bruxelles-Capitale",
    "wof:name":"The Phone House",
    "wof:placetype":"venue"
},
  "geometry": {"coordinates":[4.2939829826,50.8710212708],"type":"Point"}
}