{
  "type": "Feature",
  "properties": {
    "iso:country":"BE",
    "sg:address":"Rue Neufcour 20",
    "sg:city":"Beyne-heusay",
    "sg:classifiers":[
        {
            "category":"Retail",
            "subcategory":"Repair Shop",
            "type":"Services"
        }
    ],
    "sg:phone":"+32 4 365 35 74",
    "sg:postcode":"4610",
    "sg:province":"Li\u00e8ge",
    "sg:tags":[
        "denture"
    ],
    "wof:name":"Bourdouxhe",
    "wof:placetype":"venue"
},
  "geometry": {"coordinates":[5.6496682167,50.6231803894],"type":"Point"}
}