{
  "type": "Feature",
  "properties": {
    "addr:full":"Rue De Wattimez 15 Rumes Hainaut 7618",
    "addr:housenumber":"15",
    "addr:postcode":"7618",
    "addr:street":"Rue De Wattimez",
    "iso:country":"BE",
    "sg:address":"Rue De Wattimez 15",
    "sg:city":"Rumes",
    "sg:orig_category":"Eleveurs de bovins",
    "sg:phone":"+32 69 64 89 02",
    "sg:postcode":"7618",
    "sg:province":"Hainaut",
    "wof:name":"Jean-michel De Witte",
    "wof:placetype":"venue"
},
  "geometry": {"coordinates":[3.3510069847,50.5482215881],"type":"Point"}
}