{
  "type": "Feature",
  "properties": {
    "iso:country":"BE",
    "sg:address":"Rue Du Parc Industriel 1a",
    "sg:city":"Amay",
    "sg:classifiers":[
        {
            "category":"Insurance",
            "subcategory":"Insurance Agent",
            "type":"Services"
        }
    ],
    "sg:phone":"+32 85 23 00 32",
    "sg:postcode":"4540",
    "sg:province":"Li\u00e8ge",
    "sg:tags":[
        "broker"
    ],
    "wof:name":"F\u00e9d\u00e9ration Wallonne Des Services",
    "wof:placetype":"venue"
},
  "geometry": {"coordinates":[5.3277201653,50.5457115173],"type":"Point"}
}