{
  "type": "Feature",
  "properties": {
    "addr:full":"Tulpenstraat 43 Geel Antwerpen 2440",
    "addr:housenumber":"43",
    "addr:postcode":"2440",
    "addr:street":"Tulpenstraat",
    "iso:country":"BE",
    "sg:address":"Tulpenstraat 43",
    "sg:city":"Geel",
    "sg:orig_category":"Alimentation sp\u00e9cialis\u00e9e",
    "sg:phone":"+32 14 58 00 54",
    "sg:postcode":"2440",
    "sg:province":"Antwerpen",
    "wof:name":"Peter Kennis",
    "wof:placetype":"venue"
},
  "geometry": {"coordinates":[4.979309082,51.1599807739],"type":"Point"}
}