{
  "type": "Feature",
  "properties": {
    "addr:full":"Minister Pieter Tacklaan 31 Kortrijk West-Vlaanderen 8500",
    "addr:housenumber":"31",
    "addr:postcode":"8500",
    "addr:street":"Minister Pieter Tacklaan",
    "iso:country":"BE",
    "sg:address":"Minister Pieter Tacklaan 31",
    "sg:city":"Kortrijk",
    "sg:classifiers":[
        {
            "category":"Professional",
            "subcategory":"Management & Consulting",
            "type":"Services"
        }
    ],
    "sg:phone":"+32 56 22 80 64",
    "sg:postcode":"8500",
    "sg:province":"West-Vlaanderen",
    "sg:tags":[
        "hr",
        "resource",
        "consultancy",
        "human"
    ],
    "wof:name":"Ago International Nv",
    "wof:placetype":"venue"
},
  "geometry": {"coordinates":[3.2657220364,50.8237190247],"type":"Point"}
}