{
  "type": "Feature",
  "properties": {
    "addr:full":"R De La Fontaine Dieu 100 Eghezee Namur 5310",
    "addr:housenumber":"100",
    "addr:postcode":"5310",
    "addr:street":"Fontaine Dieu;Namur",
    "iso:country":"BE",
    "sg:address":"R De La Fontaine Dieu 100",
    "sg:city":"Eghezee",
    "sg:classifiers":[
        {
            "category":"Insurance",
            "subcategory":"Insurance Agent",
            "type":"Services"
        }
    ],
    "sg:phone":"+32 81 81 12 52",
    "sg:postcode":"5310",
    "sg:province":"Namur",
    "sg:tags":[
        "broker"
    ],
    "wof:name":"Agence G\u00e9n\u00e9rali Belgium",
    "wof:placetype":"venue"
},
  "geometry": {"coordinates":[4.8790202141,50.599811554],"type":"Point"}
}