{
  "type": "Feature",
  "properties": {
    "addr:full":"Spoorwegstraat 7 Zaventem Vlaams-Brabant 1930",
    "addr:housenumber":"7",
    "addr:postcode":"1930",
    "addr:street":"Spoorwegstraat",
    "iso:country":"BE",
    "sg:address":"Spoorwegstraat 7",
    "sg:city":"Zaventem",
    "sg:classifiers":[
        {
            "category":"Insurance",
            "subcategory":"Life Insurance",
            "type":"Services"
        }
    ],
    "sg:phone":"+32 2 725 50 55",
    "sg:postcode":"1930",
    "sg:province":"Vlaams-Brabant",
    "sg:tags":[
        "assurance"
    ],
    "wof:name":"P. Van Eetvelde",
    "wof:placetype":"venue"
},
  "geometry": {"coordinates":[4.4731001854,50.8844108582],"type":"Point"}
}