{
  "type": "Feature",
  "properties": {
    "addr:full":"Lange Heihoekstraat 1 Kruibeke Oost-Vlaanderen 9150",
    "addr:housenumber":"1",
    "addr:postcode":"9150",
    "addr:street":"Lange Heihoekstraat",
    "iso:country":"BE",
    "sg:address":"Lange Heihoekstraat 1",
    "sg:city":"Kruibeke",
    "sg:classifiers":[
        {
            "category":"Retail",
            "subcategory":"Auto Repair",
            "type":"Services"
        }
    ],
    "sg:phone":"+32 3 774 28 80",
    "sg:postcode":"9150",
    "sg:province":"Oost-Vlaanderen",
    "sg:tags":[
        "garage"
    ],
    "wof:name":"De Kerf P",
    "wof:placetype":"venue"
},
  "geometry": {"coordinates":[4.2712769508,51.1702461243],"type":"Point"}
}