{
  "type": "Feature",
  "properties": {
    "addr:full":"Rue De La Station 137 Jemeppe-sur-sambre (moustier-sur-sambre) Namur 5190",
    "addr:housenumber":"137",
    "addr:postcode":"5190",
    "addr:street":"Rue De La Station;Moustier-Sur-Sambre",
    "iso:country":"BE",
    "sg:address":"Rue De La Station 137",
    "sg:city":"Jemeppe-sur-sambre (moustier-sur-sambre)",
    "sg:classifiers":[
        {
            "category":"Real Estate",
            "subcategory":"Architect",
            "type":"Services"
        }
    ],
    "sg:phone":"+32 71 78 89 14",
    "sg:postcode":"5190",
    "sg:province":"Namur",
    "wof:name":"Dehoubert J-l",
    "wof:placetype":"venue"
},
  "geometry": {"coordinates":[4.6952271461,50.4557533264],"type":"Point"}
}