{
  "type": "Feature",
  "properties": {
    "iso:country":"BE",
    "sg:address":"Zandbergstraat 4ba",
    "sg:city":"Aarschot",
    "sg:orig_category":"Travaux de pl\u00e2trage",
    "sg:phone":"+32 16 56 90 03",
    "sg:postcode":"3201",
    "sg:province":"Vlaams-Brabant",
    "wof:name":"Paul Smets",
    "wof:placetype":"venue"
},
  "geometry": {"coordinates":[4.8501009941,51.0069541931],"type":"Point"}
}