{
  "type": "Feature",
  "properties": {
    "addr:full":"Larstraat 28 Menen West-Vlaanderen 8930",
    "addr:housenumber":"28",
    "addr:postcode":"8930",
    "addr:street":"Larstraat",
    "iso:country":"BE",
    "sg:address":"Larstraat 28",
    "sg:city":"Menen",
    "sg:orig_category":"M\u00e9decins and sp\u00e9cialistes",
    "sg:phone":"+32 56 41 90 04",
    "sg:postcode":"8930",
    "sg:province":"West-Vlaanderen",
    "wof:name":"Elke De Boever",
    "wof:placetype":"venue"
},
  "geometry": {"coordinates":[3.1943130493,50.7747154236],"type":"Point"}
}