{
  "type": "Feature",
  "properties": {
    "iso:country":"BE",
    "sg:address":"Kerkstraat 65",
    "sg:city":"Knesselare",
    "sg:orig_category":"Glaszetten and glaswerk",
    "sg:phone":"+32 9 374 13 80",
    "sg:postcode":"9910",
    "sg:province":"Oost-Vlaanderen",
    "wof:name":"Maenhout",
    "wof:placetype":"venue"
},
  "geometry": {"coordinates":[3.4121909142,51.135269165],"type":"Point"}
}