{
  "type": "Feature",
  "properties": {
    "addr:full":"Chauss\u00c9e De Gilly 358ba Charleroi Hainaut 6043",
    "addr:postcode":"6043",
    "addr:street":"Chausse\u0301E De Gilly 358Ba;Hainaut",
    "iso:country":"BE",
    "sg:address":"Chauss\u00c9e De Gilly 358ba",
    "sg:city":"Charleroi",
    "sg:orig_category":"Woningbouw",
    "sg:phone":"+32 71 34 56 73",
    "sg:postcode":"6043",
    "sg:province":"Hainaut",
    "wof:name":"Serge Delcorps",
    "wof:placetype":"venue"
},
  "geometry": {"coordinates":[4.4839549065,50.4479637146],"type":"Point"}
}