{
  "type": "Feature",
  "properties": {
    "iso:country":"BE",
    "sg:address":"Brogelerweg 52",
    "sg:city":"Bocholt",
    "sg:orig_category":"Assistances juridiques. Comptables. Conseillers fiscaux",
    "sg:phone":"+32 89 46 13 21",
    "sg:postcode":"3950",
    "sg:province":"Limburg",
    "wof:name":"Renaat Clauwers",
    "wof:placetype":"venue"
},
  "geometry": {"coordinates":[5.5728092194,51.1700286865],"type":"Point"}
}