{
  "type": "Feature",
  "properties": {
    "addr:full":"Evence Copp\u00e9elaan 91 Genk Limburg 3600",
    "addr:housenumber":"91",
    "addr:postcode":"3600",
    "addr:street":"Coppe\u0301Elaan",
    "iso:country":"BE",
    "sg:address":"Evence Copp\u00e9elaan 91",
    "sg:city":"Genk",
    "sg:classifiers":[
        {
            "category":"Organizations",
            "subcategory":"Professional Association",
            "type":"Services"
        }
    ],
    "sg:phone":"+32 89 50 43 26",
    "sg:postcode":"3600",
    "sg:province":"Limburg",
    "sg:tags":[
        "trade-union",
        "federation"
    ],
    "wof:name":"Ftml",
    "wof:placetype":"venue"
},
  "geometry": {"coordinates":[5.4943470955,50.9773292542],"type":"Point"}
}