{
  "type": "Feature",
  "properties": {
    "iso:country":"BE",
    "sg:address":"Rue De Binche 21",
    "sg:city":"Beaumont",
    "sg:classifiers":[
        {
            "category":"Wholesale",
            "subcategory":"Farm Supplies",
            "type":"Manufacturing & Wholesale Goods"
        }
    ],
    "sg:phone":"+32 71 58 80 78",
    "sg:postcode":"6500",
    "sg:province":"Hainaut",
    "sg:tags":[
        "machine",
        "agricoles",
        "mat\u00e9riel",
        "gr"
    ],
    "wof:name":"Fe. Vandeput G. & Fils",
    "wof:placetype":"venue"
},
  "geometry": {"coordinates":[4.2351741791,50.238571167],"type":"Point"}
}