{
  "type": "Feature",
  "properties": {
    "addr:full":"Kerselarenlaan 221 Sint-lambrechts-woluwe/woluwe-saint-lambert Bruxelles-Capitale 1200",
    "addr:housenumber":"221",
    "addr:postcode":"1200",
    "addr:street":"Kerselarenlaan",
    "iso:country":"BE",
    "sg:address":"Kerselarenlaan 221",
    "sg:city":"Sint-lambrechts-woluwe/woluwe-saint-lambert",
    "sg:orig_category":"Artsen and specialisten",
    "sg:phone":"+32 2 771 96 65",
    "sg:postcode":"1200",
    "sg:province":"Bruxelles-Capitale",
    "wof:name":"Martin Hostenbach",
    "wof:placetype":"venue"
},
  "geometry": {"coordinates":[4.4154171944,50.8458786011],"type":"Point"}
}