{
  "type": "Feature",
  "properties": {
    "addr:full":"Avenue Adolphe Schattens 27 Box 18 Waterloo Brabant Wallon 1410",
    "addr:housenumber":"27 box 18",
    "addr:postcode":"1410",
    "addr:street":"Avenue Adolphe Schattens",
    "iso:country":"BE",
    "sg:address":"Avenue Adolphe Schattens 27 Box 18",
    "sg:city":"Waterloo",
    "sg:classifiers":[
        {
            "category":"Health Services",
            "subcategory":"Health Practitioner",
            "type":"Services"
        }
    ],
    "sg:phone":"+32 2 354 96 30",
    "sg:postcode":"1410",
    "sg:province":"Brabant Wallon",
    "sg:tags":[
        "osteopath"
    ],
    "wof:name":"Ruwet J D.o.",
    "wof:placetype":"venue"
},
  "geometry": {"coordinates":[4.3950309753,50.7142410278],"type":"Point"}
}