{
  "type": "Feature",
  "properties": {
    "addr:full":"Ch De Wavre Bruxelles Bruxelles-Capitale 1160",
    "addr:postcode":"1160",
    "addr:street":"Ch De Wavre",
    "iso:country":"BE",
    "sg:address":"Ch De Wavre",
    "sg:city":"Bruxelles",
    "sg:classifiers":[
        {
            "category":"Farming",
            "subcategory":"Farm",
            "type":"Manufacturing & Wholesale Goods"
        }
    ],
    "sg:phone":"+32 2 743 38 38",
    "sg:postcode":"1160",
    "sg:province":"Bruxelles-Capitale",
    "sg:tags":[
        "horticulture",
        "agriculture",
        "livestock"
    ],
    "wof:name":"Laraucaria Sprl",
    "wof:placetype":"venue"
},
  "geometry": {"coordinates":[4.3987751007,50.8251953125],"type":"Point"}
}