{
  "type": "Feature",
  "properties": {
    "iso:country":"BE",
    "sg:address":"Steenweg Baarle 64",
    "sg:city":"Ravels (poppel)",
    "sg:classifiers":[
        {
            "category":"Utilities",
            "subcategory":"Water",
            "type":"Services"
        }
    ],
    "sg:phone":"+32 14 65 21 80",
    "sg:postcode":"2382",
    "sg:province":"Antwerpen",
    "sg:tags":[
        "purification"
    ],
    "wof:name":"Rietland",
    "wof:placetype":"venue"
},
  "geometry": {"coordinates":[5.0177998543,51.4513893127],"type":"Point"}
}