{
  "type": "Feature",
  "properties": {
    "addr:full":"Torhoutsestraat 349 Oostkamp West-Vlaanderen 8020",
    "addr:housenumber":"349",
    "addr:postcode":"8020",
    "addr:street":"Torhoutsestraat",
    "iso:country":"BE",
    "sg:address":"Torhoutsestraat 349",
    "sg:city":"Oostkamp",
    "sg:orig_category":"Installation \u00e9lectrique r\u00e9sidentielle",
    "sg:phone":"+32 50 27 54 92",
    "sg:postcode":"8020",
    "sg:province":"West-Vlaanderen",
    "wof:name":"Ivan Neirynck",
    "wof:placetype":"venue"
},
  "geometry": {"coordinates":[3.1645948887,51.0739402771],"type":"Point"}
}