{
  "type": "Feature",
  "properties": {
    "iso:country":"BE",
    "sg:address":"Huisepontweg 64",
    "sg:city":"Nazareth",
    "sg:orig_category":"Avocats and conseillers juridiques. Balie van Gent. Avocats and conseillers juridiques",
    "sg:phone":"+32 9 384 54 40",
    "sg:postcode":"9810",
    "sg:province":"Oost-Vlaanderen",
    "wof:name":"De Smijter Pierre",
    "wof:placetype":"venue"
},
  "geometry": {"coordinates":[3.5740818977,50.9351959229],"type":"Point"}
}