{
  "type": "Feature",
  "properties": {
    "iso:country":"BE",
    "sg:address":"Rue De La Station 89",
    "sg:city":"Havelange",
    "sg:orig_category":"Brood, gebak and snoepgoed",
    "sg:phone":"+32 83 63 34 49",
    "sg:postcode":"5370",
    "sg:province":"Namur",
    "wof:name":"Boulangerie Kempinaire",
    "wof:placetype":"venue"
},
  "geometry": {"coordinates":[5.2445201874,50.3860473633],"type":"Point"}
}