{
  "type": "Feature",
  "properties": {
    "iso:country":"BE",
    "sg:address":"Rue Truhaut 9",
    "sg:city":"Frasnes-lez-anvaing",
    "sg:orig_category":"Eleveurs de bovins",
    "sg:phone":"+32 69 45 42 12",
    "sg:postcode":"7910",
    "sg:province":"Hainaut",
    "wof:name":"Rene Vangrootenbrul",
    "wof:placetype":"venue"
},
  "geometry": {"coordinates":[3.5095779896,50.710193634],"type":"Point"}
}