{
  "type": "Feature",
  "properties": {
    "addr:full":"Avenue Bel-air 69 Ukkel/uccle Bruxelles-Capitale 1180",
    "addr:housenumber":"69",
    "addr:postcode":"1180",
    "addr:street":"Avenue Bel-Air;/",
    "iso:country":"BE",
    "sg:address":"Avenue Bel-air 69",
    "sg:city":"Ukkel/uccle",
    "sg:orig_category":"M\u00e9decins and sp\u00e9cialistes",
    "sg:phone":"+32 2 347 58 02",
    "sg:postcode":"1180",
    "sg:province":"Bruxelles-Capitale",
    "wof:name":"H. Krutzen",
    "wof:placetype":"venue"
},
  "geometry": {"coordinates":[4.3638510704,50.81300354],"type":"Point"}
}