{
  "type": "Feature",
  "properties": {
    "addr:full":"Schrovestraat 12 Lebbeke Oost-Vlaanderen 9280",
    "addr:housenumber":"12",
    "addr:postcode":"9280",
    "addr:street":"Schrovestraat",
    "iso:country":"BE",
    "sg:address":"Schrovestraat 12",
    "sg:city":"Lebbeke",
    "sg:orig_category":"Slagers",
    "sg:phone":"+32 53 21 45 16",
    "sg:postcode":"9280",
    "sg:province":"Oost-Vlaanderen",
    "wof:name":"Slagerij Staes-cami",
    "wof:placetype":"venue"
},
  "geometry": {"coordinates":[4.0820832253,50.9724502563],"type":"Point"}
}