{
  "type": "Feature",
  "properties": {
    "iso:country":"BE",
    "sg:address":"Draakplaats 3",
    "sg:city":"Antwerpen",
    "sg:classifiers":[
        {
            "category":"Cafe",
            "type":"Food & Drink"
        }
    ],
    "sg:phone":"+32 3 272 08 37",
    "sg:postcode":"2018",
    "sg:province":"Antwerpen",
    "sg:tags":[
        "caf\u00e9s"
    ],
    "wof:name":"Anna Dubelloy",
    "wof:placetype":"venue"
},
  "geometry": {"coordinates":[4.4306077957,51.2067222595],"type":"Point"}
}