{
  "type": "Feature",
  "properties": {
    "addr:full":"Leopoldstraat 19 Duffel Antwerpen 2570",
    "addr:housenumber":"19",
    "addr:postcode":"2570",
    "addr:street":"Leopoldstraat",
    "iso:country":"BE",
    "sg:address":"Leopoldstraat 19",
    "sg:city":"Duffel",
    "sg:classifiers":[
        {
            "category":"Restaurant",
            "type":"Food & Drink"
        }
    ],
    "sg:phone":"+32 15 31 62 22",
    "sg:postcode":"2570",
    "sg:province":"Antwerpen",
    "wof:name":"Angolo",
    "wof:placetype":"venue"
},
  "geometry": {"coordinates":[4.5026021004,51.0961799622],"type":"Point"}
}