{
  "type": "Feature",
  "properties": {
    "iso:country":"BE",
    "sg:address":"Hoogstraat 346",
    "sg:city":"Brussel/bruxelles",
    "sg:classifiers":[
        {
            "category":"Bars & Pubs",
            "subcategory":"Nightclub",
            "type":"Food & Drink"
        }
    ],
    "sg:phone":"+32 2 537 62 36",
    "sg:postcode":"1000",
    "sg:province":"Bruxelles-Capitale",
    "sg:tags":[
        "nachtclubs",
        "dancing"
    ],
    "wof:name":"Mini Mil",
    "wof:placetype":"venue"
},
  "geometry": {"coordinates":[4.3453388214,50.8336181641],"type":"Point"}
}