{
  "type": "Feature",
  "properties": {
    "addr:full":"Stationsstraat 131 Waregem West-Vlaanderen 8790",
    "addr:housenumber":"131",
    "addr:postcode":"8790",
    "addr:street":"Stationsstraat",
    "iso:country":"BE",
    "sg:address":"Stationsstraat 131",
    "sg:city":"Waregem",
    "sg:classifiers":[
        {
            "category":"Insurance",
            "subcategory":"Insurance Agent",
            "type":"Services"
        }
    ],
    "sg:phone":"+32 56 60 43 06",
    "sg:postcode":"8790",
    "sg:province":"West-Vlaanderen",
    "sg:tags":[
        "broker"
    ],
    "wof:name":"Dvv-verzekeringen & Leningen",
    "wof:placetype":"venue"
},
  "geometry": {"coordinates":[3.4283559322,50.8906784058],"type":"Point"}
}