{
  "type": "Feature",
  "properties": {
    "addr:full":"S. Morretln 13 Pb 32 Antwerpen Antwerpen 2050",
    "addr:housenumber":"13;32",
    "addr:postcode":"2050",
    "addr:street":"Pb",
    "iso:country":"BE",
    "sg:address":"S. Morretln 13 Pb 32",
    "sg:city":"Antwerpen",
    "sg:classifiers":[
        {
            "category":"Social Services",
            "subcategory":"Job Training",
            "type":"Services"
        }
    ],
    "sg:phone":"+32 3 219 03 35",
    "sg:postcode":"2050",
    "sg:province":"Antwerpen",
    "sg:tags":[
        "information",
        "peripheral",
        "-",
        "technology",
        "software"
    ],
    "wof:name":"European Color Software Nv",
    "wof:placetype":"venue"
},
  "geometry": {"coordinates":[4.3689899445,51.2226295471],"type":"Point"}
}