{
  "type": "Feature",
  "properties": {
    "addr:full":"Rue Chisaire 10 Mons Hainaut 7000",
    "addr:housenumber":"10",
    "addr:postcode":"7000",
    "addr:street":"Rue Chisaire;Hainaut",
    "iso:country":"BE",
    "sg:address":"Rue Chisaire 10",
    "sg:city":"Mons",
    "sg:classifiers":[
        {
            "category":"Professional",
            "subcategory":"Accounting & Tax Preparation",
            "type":"Services"
        }
    ],
    "sg:phone":"+32 65 37 77 78",
    "sg:postcode":"7000",
    "sg:province":"Hainaut",
    "sg:tags":[
        "bookkeeper"
    ],
    "wof:name":"Allard J-m",
    "wof:placetype":"venue"
},
  "geometry": {"coordinates":[3.943185091,50.4521980286],"type":"Point"}
}