{
  "type": "Feature",
  "properties": {
    "addr:full":"Rue Gr\u00c9goire Wincqz 232 Soignies Hainaut 7060",
    "addr:housenumber":"232",
    "addr:postcode":"7060",
    "addr:street":"Rue Gre\u0301Goire Wincqz",
    "iso:country":"BE",
    "sg:address":"Rue Gr\u00c9goire Wincqz 232",
    "sg:city":"Soignies",
    "sg:classifiers":[
        {
            "category":"Personal",
            "subcategory":"Beauty Salon",
            "type":"Services"
        }
    ],
    "sg:phone":"+32 67 34 07 00",
    "sg:postcode":"7060",
    "sg:province":"Hainaut",
    "sg:tags":[
        "de",
        "coiffure"
    ],
    "wof:name":"Coiffeur Laurent",
    "wof:placetype":"venue"
},
  "geometry": {"coordinates":[4.0778012276,50.5715141296],"type":"Point"}
}