{
  "type": "Feature",
  "properties": {
    "addr:full":"Chauss\u00e9e De La Hulpe 27 Bruxelles (uccle) Bruxelles-Capitale 1180",
    "addr:housenumber":"27",
    "addr:postcode":"1180",
    "addr:street":"Chausse\u0301E De La Hulpe",
    "iso:country":"BE",
    "sg:address":"Chauss\u00e9e De La Hulpe 27",
    "sg:city":"Bruxelles (uccle)",
    "sg:classifiers":[
        {
            "category":"Transit Center",
            "subcategory":"Freight",
            "type":"Transportation"
        }
    ],
    "sg:phone":"+32 2 374 49 40",
    "sg:postcode":"1180",
    "sg:province":"Bruxelles-Capitale",
    "sg:tags":[
        "import",
        "export",
        "-"
    ],
    "wof:name":"Klederka Scrl",
    "wof:placetype":"venue"
},
  "geometry": {"coordinates":[4.3776059151,50.7993164062],"type":"Point"}
}