{
  "type": "Feature",
  "properties": {
    "iso:country":"BE",
    "sg:address":"Fond Leval 23",
    "sg:city":"Sprimont",
    "sg:orig_category":"S\u00e9curit\u00e9 sociale",
    "sg:phone":"+32 4 382 13 77",
    "sg:postcode":"4140",
    "sg:province":"Li\u00e8ge",
    "wof:name":"Mutualit\u00c9 Socialiste",
    "wof:placetype":"venue"
},
  "geometry": {"coordinates":[5.661260128,50.5072288513],"type":"Point"}
}