{
  "type": "Feature",
  "properties": {
    "addr:full":"Nauterkensstraat 8 Aalter (lotenhulle) Oost-Vlaanderen 9880",
    "addr:housenumber":"8",
    "addr:postcode":"9880",
    "addr:street":"Nauterkensstraat",
    "iso:country":"BE",
    "sg:address":"Nauterkensstraat 8",
    "sg:city":"Aalter (lotenhulle)",
    "sg:orig_category":"Non-Classified Establishments",
    "sg:phone":"+32 9 374 68 72",
    "sg:postcode":"9880",
    "sg:province":"Oost-Vlaanderen",
    "wof:name":"Vleurick P",
    "wof:placetype":"venue"
},
  "geometry": {"coordinates":[3.4521598816,51.05809021],"type":"Point"}
}