{
  "type": "Feature",
  "properties": {
    "addr:full":"Guido Gezellelaan 209 Kortrijk (heule) West-Vlaanderen 8501",
    "addr:housenumber":"209",
    "addr:postcode":"8501",
    "addr:street":"Guido Gezellelaan",
    "iso:country":"BE",
    "sg:address":"Guido Gezellelaan 209",
    "sg:city":"Kortrijk (heule)",
    "sg:classifiers":[
        {
            "category":"Professional",
            "subcategory":"Advertising",
            "type":"Services"
        }
    ],
    "sg:phone":"+32 56 35 66 60",
    "sg:postcode":"8501",
    "sg:province":"West-Vlaanderen",
    "sg:tags":[
        "painter"
    ],
    "wof:name":"Publi-rudy Bvba",
    "wof:placetype":"venue"
},
  "geometry": {"coordinates":[3.2365050316,50.8361778259],"type":"Point"}
}