{
  "type": "Feature",
  "properties": {
    "addr:full":"Route Vieux Campinaire 85 Fleurus Hainaut 6220",
    "addr:housenumber":"85",
    "addr:postcode":"6220",
    "addr:street":"Route Vieux Campinaire",
    "iso:country":"BE",
    "sg:address":"Route Vieux Campinaire 85",
    "sg:city":"Fleurus",
    "sg:orig_category":"Restaurants Ruimtes voor conferenties, recepties and feesten",
    "sg:phone":"+32 71 81 18 10",
    "sg:postcode":"6220",
    "sg:province":"Hainaut",
    "wof:name":"Les Tilleuls",
    "wof:placetype":"venue"
},
  "geometry": {"coordinates":[4.5294299126,50.4521255493],"type":"Point"}
}