{
  "type": "Feature",
  "properties": {
    "addr:full":"Rue Grande 295 Beloeil Hainaut 7971",
    "addr:housenumber":"295",
    "addr:postcode":"7971",
    "addr:street":"Rue Grande",
    "iso:country":"BE",
    "sg:address":"Rue Grande 295",
    "sg:city":"Beloeil",
    "sg:orig_category":"R\u00e9paration and restauration de meubles",
    "sg:phone":"+32 69 57 85 83",
    "sg:postcode":"7971",
    "sg:province":"Hainaut",
    "wof:name":"Jerry Dufour",
    "wof:placetype":"venue"
},
  "geometry": {"coordinates":[3.663038969,50.5196418762],"type":"Point"}
}