{
  "type": "Feature",
  "properties": {
    "addr:full":"Rue Du Cerisier 35 Charleroi Hainaut 6032",
    "addr:housenumber":"35",
    "addr:postcode":"6032",
    "addr:street":"Rue Du Cerisier;Hainaut",
    "iso:country":"BE",
    "sg:address":"Rue Du Cerisier 35",
    "sg:city":"Charleroi",
    "sg:orig_category":"Installation \u00e9lectrique industrielle. Installation \u00e9lectrique r\u00e9sidentielle. Electrom\u00e9nager, t\u00e9l\u00e9vis",
    "sg:phone":"+32 71 43 12 77",
    "sg:postcode":"6032",
    "sg:province":"Hainaut",
    "wof:name":"Surelec",
    "wof:placetype":"venue"
},
  "geometry": {"coordinates":[4.4107160568,50.3854560852],"type":"Point"}
}