{
  "type": "Feature",
  "properties": {
    "addr:full":"Berchemlei 105 Borgerhout Antwerpen 2140",
    "addr:housenumber":"105;2140",
    "addr:street":"Borgerhout Antwerpen",
    "iso:country":"BE",
    "sg:address":"Berchemlei 105",
    "sg:city":"Borgerhout",
    "sg:classifiers":[
        {
            "category":"Shopping",
            "subcategory":"Gifts & Souvenirs",
            "type":"Retail Goods"
        }
    ],
    "sg:phone":"+32 3 271 18 38",
    "sg:postcode":"2140",
    "sg:province":"Antwerpen",
    "sg:tags":[
        "product",
        "miscellaneous"
    ],
    "wof:name":"Smidt-imex Bvba",
    "wof:placetype":"venue"
},
  "geometry": {"coordinates":[4.4480957985,51.2048797607],"type":"Point"}
}