{
  "type": "Feature",
  "properties": {
    "addr:full":"Industrieweg 47 Roeselare West-Vlaanderen 8800",
    "addr:housenumber":"47",
    "addr:postcode":"8800",
    "addr:street":"Industrieweg",
    "iso:country":"BE",
    "sg:address":"Industrieweg 47",
    "sg:city":"Roeselare",
    "sg:orig_category":"Papier- and kartonverpakkingen Fab",
    "sg:phone":"+32 51 26 27 60",
    "sg:postcode":"8800",
    "sg:province":"West-Vlaanderen",
    "wof:name":"Carir Cartonnage",
    "wof:placetype":"venue"
},
  "geometry": {"coordinates":[3.1260740757,50.9777488708],"type":"Point"}
}