{
  "type": "Feature",
  "properties": {
    "addr:full":"Rue J. B. Wauthier 16 Andenne Namur 5300",
    "addr:housenumber":"16",
    "addr:postcode":"5300",
    "addr:street":"Rue J. B.",
    "iso:country":"BE",
    "sg:address":"Rue J. B. Wauthier 16",
    "sg:city":"Andenne",
    "sg:orig_category":"Enseignement maternel and primaire",
    "sg:phone":"+32 81 58 13 61",
    "sg:postcode":"5300",
    "sg:province":"Namur",
    "wof:name":"Ecole Primaire Libre",
    "wof:placetype":"venue"
},
  "geometry": {"coordinates":[5.0982642174,50.4863739014],"type":"Point"}
}