{
  "type": "Feature",
  "properties": {
    "addr:full":"Stationsstraat 3ba Diepenbeek Limburg 3590",
    "addr:housenumber":"3ba",
    "addr:postcode":"3590",
    "addr:street":"Stationsstraat",
    "iso:country":"BE",
    "sg:address":"Stationsstraat 3ba",
    "sg:city":"Diepenbeek",
    "sg:classifiers":[
        {
            "category":"Restaurant",
            "type":"Food & Drink"
        }
    ],
    "sg:phone":"+32 11 35 12 02",
    "sg:postcode":"3590",
    "sg:province":"Limburg",
    "wof:name":"Tweety",
    "wof:placetype":"venue"
},
  "geometry": {"coordinates":[5.4192237854,50.9093437195],"type":"Point"}
}