{
  "type": "Feature",
  "properties": {
    "iso:country":"BE",
    "sg:address":"Stationsstraat 14b3",
    "sg:city":"Aalst",
    "sg:orig_category":"M\u00e9decins and sp\u00e9cialistes",
    "sg:phone":"+32 53 71 09 88",
    "sg:postcode":"9300",
    "sg:province":"Oost-Vlaanderen",
    "wof:name":"Bernard De Hauwere",
    "wof:placetype":"venue"
},
  "geometry": {"coordinates":[4.0374732018,50.9418754578],"type":"Point"}
}