{
  "type": "Feature",
  "properties": {
    "iso:country":"BE",
    "sg:address":"Rue Sainte-barbe 14",
    "sg:city":"Nivelles",
    "sg:orig_category":"Sportclubs",
    "sg:phone":"+32 67 21 55 58",
    "sg:postcode":"1400",
    "sg:province":"Brabant Wallon",
    "wof:name":"B.c. Nivelles",
    "wof:placetype":"venue"
},
  "geometry": {"coordinates":[4.312789917,50.5964279175],"type":"Point"}
}