{
  "type": "Feature",
  "properties": {
    "iso:country":"BE",
    "sg:address":"Vermorgenstraat 13b6",
    "sg:city":"Sint-niklaas",
    "sg:orig_category":"Artiesten and kunstenaars Diverse grafische activiteiten",
    "sg:phone":"+32 3 765 93 76",
    "sg:postcode":"9100",
    "sg:province":"Oost-Vlaanderen",
    "wof:name":"Kristof Caluwaerts",
    "wof:placetype":"venue"
},
  "geometry": {"coordinates":[4.1453971863,51.1690673828],"type":"Point"}
}