{
  "type": "Feature",
  "properties": {
    "addr:full":"Route De Battice 6 Thimister-clermont (thimister) Li\u00e8ge 4890",
    "addr:housenumber":"6",
    "addr:postcode":"4890",
    "addr:street":"Route De Battice",
    "iso:country":"BE",
    "sg:address":"Route De Battice 6",
    "sg:city":"Thimister-clermont (thimister)",
    "sg:classifiers":[
        {
            "category":"Building & Trades",
            "subcategory":"Construction",
            "type":"Services"
        }
    ],
    "sg:phone":"+32 87 44 55 23",
    "sg:postcode":"4890",
    "sg:province":"Li\u00e8ge",
    "sg:tags":[
        "carpenter"
    ],
    "wof:name":"Habay J-l",
    "wof:placetype":"venue"
},
  "geometry": {"coordinates":[5.8402299881,50.6627006531],"type":"Point"}
}