{
  "type": "Feature",
  "properties": {
    "addr:full":"Kortrijksestraat 266 Izegem West-Vlaanderen 8870",
    "addr:housenumber":"266",
    "addr:postcode":"8870",
    "addr:street":"Kortrijksestraat",
    "iso:country":"BE",
    "sg:address":"Kortrijksestraat 266",
    "sg:city":"Izegem",
    "sg:orig_category":"Supermarch\u00e9s",
    "sg:phone":"+32 51 30 53 57",
    "sg:postcode":"8870",
    "sg:province":"West-Vlaanderen",
    "wof:name":"Delhaize",
    "wof:placetype":"venue"
},
  "geometry": {"coordinates":[3.2206060886,50.9055137634],"type":"Point"}
}