{
  "type": "Feature",
  "properties": {
    "iso:country":"BE",
    "sg:address":"Avenue Alexander Fleming",
    "sg:city":"Ottignies-louvain-la-neuve (louvain-la-neuve)",
    "sg:classifiers":[
        {
            "category":"Manufacturing",
            "subcategory":"Metals",
            "type":"Manufacturing & Wholesale Goods"
        }
    ],
    "sg:phone":"+32 10 47 01 11",
    "sg:postcode":"1348",
    "sg:province":"Brabant Wallon",
    "sg:tags":[
        "steel",
        "stainless"
    ],
    "wof:name":"Cotubel",
    "wof:placetype":"venue"
},
  "geometry": {"coordinates":[4.6374001503,50.6631660461],"type":"Point"}
}