{
  "type": "Feature",
  "properties": {
    "iso:country":"BE",
    "sg:address":"Rue De L'ile-monsin 10",
    "sg:city":"Li\u00c8ge",
    "sg:orig_category":"HUISBRANDOLIE",
    "sg:phone":"+32 4 264 93 40",
    "sg:postcode":"4020",
    "sg:province":"Li\u00e8ge",
    "wof:name":"Terval",
    "wof:placetype":"venue"
},
  "geometry": {"coordinates":[5.6286458969,50.6508483887],"type":"Point"}
}