{
  "type": "Feature",
  "properties": {
    "addr:full":"Rue De Monin 75 Hamois (achet) Namur 5362",
    "addr:housenumber":"75",
    "addr:postcode":"5362",
    "addr:street":"Rue De Monin",
    "iso:country":"BE",
    "sg:address":"Rue De Monin 75",
    "sg:city":"Hamois (achet)",
    "sg:classifiers":[
        {
            "category":"Building & Trades",
            "subcategory":"Pest Control",
            "type":"Services"
        }
    ],
    "sg:phone":"+32 83 61 27 22",
    "sg:postcode":"5362",
    "sg:province":"Namur",
    "sg:tags":[
        "painting",
        "contractor"
    ],
    "wof:name":"Marion L",
    "wof:placetype":"venue"
},
  "geometry": {"coordinates":[5.1512331963,50.3157691956],"type":"Point"}
}