{
  "type": "Feature",
  "properties": {
    "addr:full":"Rue Du Vert Velu 48 Peruwelz Hainaut 7608",
    "addr:housenumber":"48",
    "addr:postcode":"7608",
    "addr:street":"Rue Du Vert Velu;Hainaut",
    "iso:country":"BE",
    "sg:address":"Rue Du Vert Velu 48",
    "sg:city":"Peruwelz",
    "sg:orig_category":"M\u00e9decins and sp\u00e9cialistes",
    "sg:phone":"+32 69 77 18 90",
    "sg:postcode":"7608",
    "sg:province":"Hainaut",
    "wof:name":"G. Senelle",
    "wof:placetype":"venue"
},
  "geometry": {"coordinates":[3.536618948,50.5170288086],"type":"Point"}
}