{
  "type": "Feature",
  "properties": {
    "addr:full":"Italielei 187 Antwerpen Antwerpen 2000",
    "addr:housenumber":"187",
    "addr:postcode":"2000",
    "addr:street":"Italielei",
    "iso:country":"BE",
    "sg:address":"Italielei 187",
    "sg:city":"Antwerpen",
    "sg:classifiers":[
        {
            "category":"Insurance",
            "subcategory":"Insurance Agent",
            "type":"Services"
        }
    ],
    "sg:phone":"+32 3 226 10 14",
    "sg:postcode":"2000",
    "sg:province":"Antwerpen",
    "sg:tags":[
        "verzekeringsmakelaars",
        "expert"
    ],
    "wof:name":"Confidentia",
    "wof:placetype":"venue"
},
  "geometry": {"coordinates":[4.4165701866,51.2226028442],"type":"Point"}
}