{
  "type": "Feature",
  "properties": {
    "addr:full":"Av Rogier 240 Bruxelles Bruxelles-Capitale 1030",
    "addr:housenumber":"240",
    "addr:postcode":"1030",
    "addr:street":"Av Rogier",
    "iso:country":"BE",
    "sg:address":"Av Rogier 240",
    "sg:city":"Bruxelles",
    "sg:classifiers":[
        {
            "category":"Professional",
            "subcategory":"Advertising",
            "type":"Services"
        }
    ],
    "sg:phone":"+32 2 215 19 30",
    "sg:postcode":"1030",
    "sg:province":"Bruxelles-Capitale",
    "sg:tags":[
        "marketing",
        "medium",
        "communication"
    ],
    "wof:name":"Dimarso Sa",
    "wof:placetype":"venue"
},
  "geometry": {"coordinates":[4.3873968124,50.8575019836],"type":"Point"}
}