{
  "type": "Feature",
  "properties": {
    "iso:country":"BE",
    "sg:address":"Avenue Guillaume Joachim 29",
    "sg:city":"Waremme",
    "sg:classifiers":[
        {
            "category":"Restaurant",
            "type":"Food & Drink"
        }
    ],
    "sg:phone":"+32 19 32 38 10",
    "sg:postcode":"4300",
    "sg:province":"Li\u00e8ge",
    "wof:name":"Le Soleil D'italie",
    "wof:placetype":"venue"
},
  "geometry": {"coordinates":[5.258248806,50.6968078613],"type":"Point"}
}