{
  "type": "Feature",
  "properties": {
    "iso:country":"BE",
    "sg:address":"Wildebeekstraat 28",
    "sg:city":"Zedelgem",
    "sg:orig_category":"Ordinateurs and \u00e9quipement informatique",
    "sg:phone":"+32 50 24 07 31",
    "sg:postcode":"8211",
    "sg:province":"West-Vlaanderen",
    "wof:name":"A.g.o.",
    "wof:placetype":"venue"
},
  "geometry": {"coordinates":[3.0889649391,51.1200408936],"type":"Point"}
}