{
  "type": "Feature",
  "properties": {
    "iso:country":"BE",
    "sg:address":"Chemin Du Breucq 7",
    "sg:city":"Ath",
    "sg:orig_category":"Woningbouw",
    "sg:phone":"+32 68 28 55 04",
    "sg:postcode":"7800",
    "sg:province":"Hainaut",
    "wof:name":"Pascal Galant",
    "wof:placetype":"venue"
},
  "geometry": {"coordinates":[3.7854390144,50.6250305176],"type":"Point"}
}