{
  "type": "Feature",
  "properties": {
    "addr:full":"Rue Chaumont 8ba Engis Li\u00e8ge 4480",
    "addr:housenumber":"8ba",
    "addr:postcode":"4480",
    "addr:street":"Rue Chaumont",
    "iso:country":"BE",
    "sg:address":"Rue Chaumont 8ba",
    "sg:city":"Engis",
    "sg:orig_category":"Installatie van houten of kunststof schrijnwerk",
    "sg:phone":"+32 85 31 12 39",
    "sg:postcode":"4480",
    "sg:province":"Li\u00e8ge",
    "wof:name":"Fe. Delhalle & Fils",
    "wof:placetype":"venue"
},
  "geometry": {"coordinates":[5.3656158447,50.5627250671],"type":"Point"}
}