{
  "type": "Feature",
  "properties": {
    "addr:full":"Tenbos 149 Elsene/ixelles Bruxelles-Capitale 1050",
    "addr:housenumber":"149",
    "addr:postcode":"1050",
    "addr:street":"Tenbos",
    "iso:country":"BE",
    "sg:address":"Tenbos 149",
    "sg:city":"Elsene/ixelles",
    "sg:orig_category":"Antiek Decoratieve kunst and kunstbenodigdheden",
    "sg:phone":"+32 2 538 44 42",
    "sg:postcode":"1050",
    "sg:province":"Bruxelles-Capitale",
    "wof:name":"Everard De Harzir",
    "wof:placetype":"venue"
},
  "geometry": {"coordinates":[4.3596282005,50.8202629089],"type":"Point"}
}