{
  "type": "Feature",
  "properties": {
    "iso:country":"BE",
    "sg:address":"Moerbroek 18",
    "sg:city":"Herenthout",
    "sg:classifiers":[
        {
            "category":"Food & Beverages",
            "subcategory":"Meat & Fish",
            "type":"Retail Goods"
        }
    ],
    "sg:phone":"+32 14 23 01 86",
    "sg:postcode":"2270",
    "sg:province":"Antwerpen",
    "sg:tags":[
        "vi",
        "zeevruchten"
    ],
    "wof:name":"'t Vismijntje",
    "wof:placetype":"venue"
},
  "geometry": {"coordinates":[4.7977218628,51.1536331177],"type":"Point"}
}