{
  "type": "Feature",
  "properties": {
    "addr:full":"Sint-gilliskerkstraat 65 Sint-gillis/saint-gilles Bruxelles-Capitale 1060",
    "addr:housenumber":"65",
    "addr:postcode":"1060",
    "addr:street":"Sint-Gilliskerkstraat",
    "iso:country":"BE",
    "sg:address":"Sint-gilliskerkstraat 65",
    "sg:city":"Sint-gillis/saint-gilles",
    "sg:orig_category":"Tweedehandsgoederen",
    "sg:phone":"+32 2 538 46 09",
    "sg:postcode":"1060",
    "sg:province":"Bruxelles-Capitale",
    "wof:name":"Entraide",
    "wof:placetype":"venue"
},
  "geometry": {"coordinates":[4.3432822227,50.83045578],"type":"Point"}
}