{
  "type": "Feature",
  "properties": {
    "addr:full":"Stationsstraat V. Woluwe 122 Sint-lambrechts-woluwe/woluwe-saint-lambert Bruxelles-Capitale 1200",
    "addr:housenumber":"122;/",
    "addr:postcode":"1200",
    "addr:street":"Stationsstraat V. Woluwe;Sint-Lambrechts-Woluwe",
    "iso:country":"BE",
    "sg:address":"Stationsstraat V. Woluwe 122",
    "sg:city":"Sint-lambrechts-woluwe/woluwe-saint-lambert",
    "sg:orig_category":"Reclamebureaus",
    "sg:phone":"+32 2 763 13 24",
    "sg:postcode":"1200",
    "sg:province":"Bruxelles-Capitale",
    "wof:name":"Tempo",
    "wof:placetype":"venue"
},
  "geometry": {"coordinates":[4.446269989,50.8563690186],"type":"Point"}
}