{
  "type": "Feature",
  "properties": {
    "addr:full":"Rue Neuve Cour 140 Tubize Brabant Wallon 1480",
    "addr:housenumber":"140",
    "addr:postcode":"1480",
    "addr:street":"Rue Neuve Cour;Wallon",
    "iso:country":"BE",
    "sg:address":"Rue Neuve Cour 140",
    "sg:city":"Tubize",
    "sg:classifiers":[
        {
            "category":"Education",
            "subcategory":"School",
            "type":"Public Place"
        }
    ],
    "sg:phone":"+32 2 355 89 47",
    "sg:postcode":"1480",
    "sg:province":"Brabant Wallon",
    "sg:tags":[
        "primary"
    ],
    "wof:name":"Ecole Maternelle St Joseph",
    "wof:placetype":"venue"
},
  "geometry": {"coordinates":[4.1955227852,50.6948776245],"type":"Point"}
}