{
  "type": "Feature",
  "properties": {
    "iso:country":"BE",
    "sg:address":"Gevaertlaan 132",
    "sg:city":"Westerlo",
    "sg:orig_category":"Dakwerken",
    "sg:phone":"+32 16 69 97 98",
    "sg:postcode":"2260",
    "sg:province":"Antwerpen",
    "wof:name":"Van De Sande",
    "wof:placetype":"venue"
},
  "geometry": {"coordinates":[4.8500199318,51.0872497559],"type":"Point"}
}