{
  "type": "Feature",
  "properties": {
    "addr:full":"Zilverstraat 12 Brugge West-Vlaanderen 8000",
    "addr:housenumber":"12",
    "addr:postcode":"8000",
    "addr:street":"Zilverstraat",
    "iso:country":"BE",
    "sg:address":"Zilverstraat 12",
    "sg:city":"Brugge",
    "sg:orig_category":"Bioscopen",
    "sg:phone":"+32 50 33 20 70",
    "sg:postcode":"8000",
    "sg:province":"West-Vlaanderen",
    "wof:name":"Kennedy Komplex",
    "wof:placetype":"venue"
},
  "geometry": {"coordinates":[3.2224199772,51.207649231],"type":"Point"}
}