{
  "type": "Feature",
  "properties": {
    "addr:full":"Rue De Lhommal 59 Libramont-chevigny Luxembourg 6800",
    "addr:housenumber":"59",
    "addr:postcode":"6800",
    "addr:street":"Rue De Lhommal",
    "iso:country":"BE",
    "sg:address":"Rue De Lhommal 59",
    "sg:city":"Libramont-chevigny",
    "sg:orig_category":"Rundveehouders",
    "sg:phone":"+32 61 61 11 45",
    "sg:postcode":"6800",
    "sg:province":"Luxembourg",
    "wof:name":"Albert Collignon",
    "wof:placetype":"venue"
},
  "geometry": {"coordinates":[5.3811769485,49.9865684509],"type":"Point"}
}