{
  "type": "Feature",
  "properties": {
    "iso:country":"BE",
    "sg:address":"Eikenstraat 66",
    "sg:city":"Harelbeke",
    "sg:orig_category":"Installatie van houten of kunststof schrijnwerk Installatie van metalen schrijnwerk",
    "sg:phone":"+32 56 75 81 05",
    "sg:postcode":"8530",
    "sg:province":"West-Vlaanderen",
    "wof:name":"Vandenbroucke Gebroeders",
    "wof:placetype":"venue"
},
  "geometry": {"coordinates":[3.3155829906,50.8376808167],"type":"Point"}
}