{
  "type": "Feature",
  "properties": {
    "addr:full":"Kerkstraat 18a Brecht (sint-lenaarts) Antwerpen 2960",
    "addr:housenumber":"18a",
    "addr:postcode":"2960",
    "addr:street":"Kerkstraat",
    "iso:country":"BE",
    "sg:address":"Kerkstraat 18a",
    "sg:city":"Brecht (sint-lenaarts)",
    "sg:classifiers":[
        {
            "category":"Shopping",
            "subcategory":"Computers & Home Electronics",
            "type":"Retail Goods"
        }
    ],
    "sg:phone":"+32 3 313 96 36",
    "sg:postcode":"2960",
    "sg:province":"Antwerpen",
    "sg:tags":[
        "-",
        "television",
        "radio"
    ],
    "wof:name":"Rombouts",
    "wof:placetype":"venue"
},
  "geometry": {"coordinates":[4.5743432045,51.2922744751],"type":"Point"}
}