{
  "type": "Feature",
  "properties": {
    "addr:full":"Lambermontlaan 169 Schaarbeek/schaerbeek Bruxelles-Capitale 1030",
    "addr:housenumber":"169",
    "addr:postcode":"1030",
    "addr:street":"Lambermontlaan",
    "iso:country":"BE",
    "sg:address":"Lambermontlaan 169",
    "sg:city":"Schaarbeek/schaerbeek",
    "sg:orig_category":"Installatie van houten of kunststof schrijnwerk Meubelzaken, woning- and keukeninrichting",
    "sg:phone":"+32 2 245 48 31",
    "sg:postcode":"1030",
    "sg:province":"Bruxelles-Capitale",
    "wof:name":"C. & M.",
    "wof:placetype":"venue"
},
  "geometry": {"coordinates":[4.3821578026,50.8705787659],"type":"Point"}
}