{
  "type": "Feature",
  "properties": {
    "addr:full":"Punt 36 Herenthout Antwerpen 2270",
    "addr:housenumber":"36",
    "addr:postcode":"2270",
    "addr:street":"Punt",
    "iso:country":"BE",
    "sg:address":"Punt 36",
    "sg:city":"Herenthout",
    "sg:orig_category":"Artsen and specialisten",
    "sg:phone":"+32 14 51 63 35",
    "sg:postcode":"2270",
    "sg:province":"Antwerpen",
    "wof:name":"B. Ariens",
    "wof:placetype":"venue"
},
  "geometry": {"coordinates":[4.7439041138,51.1364021301],"type":"Point"}
}