{
  "type": "Feature",
  "properties": {
    "iso:country":"BE",
    "sg:address":"Hospitaalstraat 22",
    "sg:city":"Bilzen",
    "sg:orig_category":"Bloemen and planten Meubelzaken, woning- and keukeninrichting",
    "sg:phone":"+32 89 41 31 03",
    "sg:postcode":"3740",
    "sg:province":"Limburg",
    "wof:name":"Meubelen Nectar",
    "wof:placetype":"venue"
},
  "geometry": {"coordinates":[5.5132322311,50.8712158203],"type":"Point"}
}