{
  "type": "Feature",
  "properties": {
    "addr:full":"Brusselsesteenweg 313-315 Mechelen Antwerpen 2800",
    "addr:housenumber":"313-315",
    "addr:postcode":"2800",
    "addr:street":"Brusselsesteenweg",
    "iso:country":"BE",
    "sg:address":"Brusselsesteenweg 313-315",
    "sg:city":"Mechelen",
    "sg:classifiers":[
        {
            "category":"Arena",
            "subcategory":"Sports Club",
            "type":"Entertainment"
        }
    ],
    "sg:phone":"+32 15 29 04 86",
    "sg:postcode":"2800",
    "sg:province":"Antwerpen",
    "wof:name":"Duiksportfederatie Vlaanderen-n.e.l.o.s. Vzw",
    "wof:placetype":"venue"
},
  "geometry": {"coordinates":[4.4745650291,51.0073661804],"type":"Point"}
}