{
  "type": "Feature",
  "properties": {
    "addr:full":"Kaaldries 118 Hamme Oost-Vlaanderen 9220",
    "addr:housenumber":"118",
    "addr:postcode":"9220",
    "iso:country":"BE",
    "sg:address":"Kaaldries 118",
    "sg:city":"Hamme",
    "sg:orig_category":"Boucheries",
    "sg:phone":"+32 52 47 79 10",
    "sg:postcode":"9220",
    "sg:province":"Oost-Vlaanderen",
    "wof:name":"Kurt Brusselmans",
    "wof:placetype":"venue"
},
  "geometry": {"coordinates":[4.122399807,51.0979614258],"type":"Point"}
}