{
  "type": "Feature",
  "properties": {
    "iso:country":"BE",
    "sg:address":"Rue Neuve 47",
    "sg:city":"Bruxelles",
    "sg:classifiers":[
        {
            "category":"Shopping",
            "subcategory":"Clothing, Apparel, & Fashions",
            "type":"Retail Goods"
        }
    ],
    "sg:phone":"+32 2 219 27 80",
    "sg:postcode":"1000",
    "sg:province":"Bruxelles-Capitale",
    "sg:tags":[
        "clothing",
        "-",
        "gentleman"
    ],
    "wof:name":"A4",
    "wof:placetype":"venue"
},
  "geometry": {"coordinates":[4.3554849625,50.852142334],"type":"Point"}
}