{
  "type": "Feature",
  "properties": {
    "addr:full":"Kooigemsestraat 31 Kortrijk (kooigem) West-Vlaanderen 8510",
    "addr:housenumber":"31",
    "addr:postcode":"8510",
    "addr:street":"Kooigemsestraat",
    "iso:country":"BE",
    "sg:address":"Kooigemsestraat 31",
    "sg:city":"Kortrijk (kooigem)",
    "sg:classifiers":[
        {
            "category":"Home & Garden",
            "subcategory":"Carpets & Floor Coverings",
            "type":"Retail Goods"
        }
    ],
    "sg:phone":"+32 56 45 55 16",
    "sg:postcode":"8510",
    "sg:province":"West-Vlaanderen",
    "sg:tags":[
        "tile"
    ],
    "wof:name":"Van Glabeke Bouwmaterialen Bvba",
    "wof:placetype":"venue"
},
  "geometry": {"coordinates":[3.3362720013,50.7399978638],"type":"Point"}
}