{
  "type": "Feature",
  "properties": {
    "iso:country":"BE",
    "sg:address":"Domaine Des Mara\u00cechers 63",
    "sg:city":"Quaregnon",
    "sg:classifiers":[
        {
            "category":"Insurance",
            "subcategory":"Life Insurance",
            "type":"Services"
        }
    ],
    "sg:phone":"+32 65 77 72 76",
    "sg:postcode":"7390",
    "sg:province":"Hainaut",
    "sg:tags":[
        "assurance"
    ],
    "wof:name":"Andre Boulanger",
    "wof:placetype":"venue"
},
  "geometry": {"coordinates":[3.8532099724,50.4458427429],"type":"Point"}
}