{
  "type": "Feature",
  "properties": {
    "iso:country":"BE",
    "sg:address":"Rue De Fragn\u00c9e 155",
    "sg:city":"Li\u00c8ge",
    "sg:orig_category":"Drukkerijen and copyshops Fotogravure and zetwerk Secretariaatsdiensten",
    "sg:phone":"+32 4 252 23 99",
    "sg:postcode":"4000",
    "sg:province":"Li\u00e8ge",
    "wof:name":"Micromegas",
    "wof:placetype":"venue"
},
  "geometry": {"coordinates":[5.5734610558,50.6217498779],"type":"Point"}
}