{
  "type": "Feature",
  "properties": {
    "addr:full":"Aerschotstraat 114 Sint-niklaas Oost-Vlaanderen 9100",
    "addr:housenumber":"114",
    "addr:postcode":"9100",
    "addr:street":"Aerschotstraat",
    "iso:country":"BE",
    "sg:address":"Aerschotstraat 114",
    "sg:city":"Sint-niklaas",
    "sg:classifiers":[
        {
            "category":"Manufacturing",
            "subcategory":"Printing",
            "type":"Manufacturing & Wholesale Goods"
        }
    ],
    "sg:phone":"+32 3 777 09 61",
    "sg:postcode":"9100",
    "sg:province":"Oost-Vlaanderen",
    "sg:tags":[
        "house",
        "book"
    ],
    "wof:name":"Svk Nv",
    "wof:placetype":"venue"
},
  "geometry": {"coordinates":[4.1303272247,51.1657562256],"type":"Point"}
}