{
  "type": "Feature",
  "properties": {
    "iso:country":"BE",
    "sg:address":"Grimbert 1",
    "sg:city":"Borsbeek",
    "sg:orig_category":"Banken and kredietinstellingen",
    "sg:phone":"+32 3 366 43 72",
    "sg:postcode":"2150",
    "sg:province":"Antwerpen",
    "wof:name":"Groep Argenta",
    "wof:placetype":"venue"
},
  "geometry": {"coordinates":[4.4866437912,51.1988868713],"type":"Point"}
}