{
  "type": "Feature",
  "properties": {
    "iso:country":"BE",
    "sg:address":"Hoogstr 58",
    "sg:city":"Rosmeer-bilzen",
    "sg:classifiers":[
        {
            "category":"Home & Garden",
            "subcategory":"Furniture",
            "type":"Retail Goods"
        }
    ],
    "sg:phone":"+32 12 45 15 50",
    "sg:postcode":"3740",
    "sg:province":"Limburg",
    "sg:tags":[
        "household",
        "wood"
    ],
    "wof:name":"Greven Nv",
    "wof:placetype":"venue"
},
  "geometry": {"coordinates":[5.4791321754,50.9003791809],"type":"Point"}
}