{
  "type": "Feature",
  "properties": {
    "addr:full":"Warden Oomlaan 7 Zonnebeke West-Vlaanderen 8980",
    "addr:housenumber":"7",
    "addr:postcode":"8980",
    "addr:street":"Oomlaan",
    "iso:country":"BE",
    "sg:address":"Warden Oomlaan 7",
    "sg:city":"Zonnebeke",
    "sg:orig_category":"Installatie van houten of kunststof schrijnwerk MEUBELONTWERP AND -INSTALLATIE",
    "sg:phone":"+32 57 46 65 64",
    "sg:postcode":"8980",
    "sg:province":"West-Vlaanderen",
    "wof:name":"Schrijnwerkerij Santy",
    "wof:placetype":"venue"
},
  "geometry": {"coordinates":[3.0221059322,50.8478927612],"type":"Point"}
}