{
  "type": "Feature",
  "properties": {
    "iso:country":"BE",
    "sg:address":"Rue Du Soleil 125",
    "sg:city":"Ronse",
    "sg:orig_category":"Plomberie, chauffage and installations sanitaires. Charpentes and couvertures. Mat\u00e9riaux de construc",
    "sg:phone":"+32 55 21 25 71",
    "sg:postcode":"9600",
    "sg:province":"Oost-Vlaanderen",
    "wof:name":"Vanden Abeele Gebrs",
    "wof:placetype":"venue"
},
  "geometry": {"coordinates":[3.5882060528,50.749622345],"type":"Point"}
}