{
  "type": "Feature",
  "properties": {
    "addr:full":"Rue Van Humbeeck 18 Chimay Hainaut 6460",
    "addr:housenumber":"18",
    "addr:postcode":"6460",
    "addr:street":"Rue Van Humbeeck",
    "iso:country":"BE",
    "sg:address":"Rue Van Humbeeck 18",
    "sg:city":"Chimay",
    "sg:orig_category":"Dameskledingzaken",
    "sg:phone":"+32 60 21 28 62",
    "sg:postcode":"6460",
    "sg:province":"Hainaut",
    "wof:name":"Maison L\u00b4elegance",
    "wof:placetype":"venue"
},
  "geometry": {"coordinates":[4.3207798004,50.047958374],"type":"Point"}
}