{
  "type": "Feature",
  "properties": {
    "iso:country":"BE",
    "sg:address":"Rue Des Frontaliers 10-14",
    "sg:city":"Mouscron (herseaux)",
    "sg:classifiers":[
        {
            "category":"Insurance",
            "subcategory":"Insurance Agent",
            "type":"Services"
        }
    ],
    "sg:phone":"+32 56 84 52 99",
    "sg:postcode":"7712",
    "sg:province":"Hainaut",
    "sg:tags":[
        "broker"
    ],
    "wof:name":"Crikilion",
    "wof:placetype":"venue"
},
  "geometry": {"coordinates":[3.2314479351,50.7231750488],"type":"Point"}
}