{
  "type": "Feature",
  "properties": {
    "iso:country":"BE",
    "sg:address":"Ekkelenbergstraat 21",
    "sg:city":"Herne",
    "sg:classifiers":[
        {
            "category":"Food & Beverages",
            "subcategory":"Meat & Fish",
            "type":"Retail Goods"
        }
    ],
    "sg:phone":"+32 2 396 21 14",
    "sg:postcode":"1540",
    "sg:province":"Vlaams-Brabant",
    "sg:tags":[
        "poultry",
        "whol",
        "game",
        "-"
    ],
    "wof:name":"De Tre C",
    "wof:placetype":"venue"
},
  "geometry": {"coordinates":[4.0655431747,50.7299919128],"type":"Point"}
}