{
  "type": "Feature",
  "properties": {
    "iso:country":"BE",
    "sg:address":"Strostraat 5",
    "sg:city":"Brussel/bruxelles",
    "sg:orig_category":"Verbruikerskredietinstellingen",
    "sg:phone":"+32 2 502 45 35",
    "sg:postcode":"1000",
    "sg:province":"Bruxelles-Capitale",
    "wof:name":"Belgische Kredietkas",
    "wof:placetype":"venue"
},
  "geometry": {"coordinates":[4.3549728394,50.8422622681],"type":"Point"}
}