{
  "type": "Feature",
  "properties": {
    "iso:country":"BE",
    "sg:address":"Jagersstraat 40",
    "sg:city":"Hasselt",
    "sg:classifiers":[
        {
            "category":"Arena",
            "subcategory":"Sports Club",
            "type":"Entertainment"
        }
    ],
    "sg:phone":"+32 11 27 05 06",
    "sg:postcode":"3500",
    "sg:province":"Limburg",
    "sg:tags":[
        "de"
    ],
    "wof:name":"W.s.v. De Trotters",
    "wof:placetype":"venue"
},
  "geometry": {"coordinates":[5.3269548416,50.9243240356],"type":"Point"}
}