{
  "type": "Feature",
  "properties": {
    "addr:full":"Hengelhoefdreef 5 Houthalen-helchteren Limburg 3530",
    "addr:housenumber":"5",
    "addr:postcode":"3530",
    "addr:street":"Hengelhoefdreef",
    "iso:country":"BE",
    "sg:address":"Hengelhoefdreef 5",
    "sg:city":"Houthalen-helchteren",
    "sg:classifiers":[
        {
            "category":"Health Services",
            "subcategory":"Nursing And Care Facility",
            "type":"Services"
        }
    ],
    "sg:phone":"+32 89 38 07 76",
    "sg:postcode":"3530",
    "sg:province":"Limburg",
    "sg:tags":[
        "public"
    ],
    "wof:name":"Onhaalcentrum Voor Vluchtelingen Te Houthalen",
    "wof:placetype":"venue"
},
  "geometry": {"coordinates":[5.4630470276,51.0078010559],"type":"Point"}
}