{
  "type": "Feature",
  "properties": {
    "addr:full":"Galerie Cath\u00e9drale 98 Li\u00e8ge 1 Li\u00e8ge 4000",
    "addr:housenumber":"98;1",
    "addr:postcode":"4000",
    "addr:street":"Lie\u0300Ge",
    "iso:country":"BE",
    "sg:address":"Galerie Cath\u00e9drale 98",
    "sg:city":"Li\u00e8ge 1",
    "sg:classifiers":[
        {
            "category":"Personal",
            "subcategory":"Barber",
            "type":"Services"
        }
    ],
    "sg:phone":"+32 4 223 23 05",
    "sg:postcode":"4000",
    "sg:province":"Li\u00e8ge",
    "sg:tags":[
        "gentleman",
        "salon",
        "-",
        "hairdressing"
    ],
    "wof:name":"Moens Coiffure",
    "wof:placetype":"venue"
},
  "geometry": {"coordinates":[5.5722761154,50.6416625977],"type":"Point"}
}