{
  "type": "Feature",
  "properties": {
    "addr:full":"Rue Hydraulique 24 Sint-joost-ten-node/saint-josse-ten-noode Bruxelles-Capitale 1210",
    "addr:housenumber":"24",
    "addr:postcode":"1210",
    "addr:street":"Rue Hydraulique",
    "iso:country":"BE",
    "sg:address":"Rue Hydraulique 24",
    "sg:city":"Sint-joost-ten-node/saint-josse-ten-noode",
    "sg:classifiers":[
        {
            "category":"Building & Trades",
            "subcategory":"Plumbing",
            "type":"Services"
        }
    ],
    "sg:phone":"+32 2 218 47 62",
    "sg:postcode":"1210",
    "sg:province":"Bruxelles-Capitale",
    "sg:tags":[
        "diver",
        "commerce",
        "gr",
        "pour",
        "equipement"
    ],
    "wof:name":"Epac",
    "wof:placetype":"venue"
},
  "geometry": {"coordinates":[4.3719410896,50.8481407166],"type":"Point"}
}