{
  "type": "Feature",
  "properties": {
    "iso:country":"BE",
    "sg:address":"Ommegangstraat 3",
    "sg:city":"Kluisbergen (kwaremont)",
    "sg:classifiers":[
        {
            "category":"Arts & Performance",
            "subcategory":"Art Gallery",
            "type":"Entertainment"
        }
    ],
    "sg:phone":"+32 55 38 60 53",
    "sg:postcode":"9690",
    "sg:province":"Oost-Vlaanderen",
    "wof:name":"Galerie Theaxus",
    "wof:placetype":"venue"
},
  "geometry": {"coordinates":[3.5235900879,50.7762298584],"type":"Point"}
}