{
  "type": "Feature",
  "properties": {
    "addr:full":"Polder 4 Rumst (terhagen) Antwerpen 2840",
    "addr:housenumber":"4",
    "addr:postcode":"2840",
    "addr:street":"Polder",
    "iso:country":"BE",
    "sg:address":"Polder 4",
    "sg:city":"Rumst (terhagen)",
    "sg:classifiers":[
        {
            "category":"Manufacturing",
            "subcategory":"Metals",
            "type":"Manufacturing & Wholesale Goods"
        }
    ],
    "sg:phone":"+32 3 888 08 88",
    "sg:postcode":"2840",
    "sg:province":"Antwerpen",
    "sg:tags":[
        "work",
        "sheet"
    ],
    "wof:name":"Almecon Bvba",
    "wof:placetype":"venue"
},
  "geometry": {"coordinates":[4.3888602257,51.0827598572],"type":"Point"}
}