{
  "type": "Feature",
  "properties": {
    "addr:full":"Rue De Bruxelles 199 Awans Li\u00e8ge 4340",
    "addr:housenumber":"199",
    "addr:postcode":"4340",
    "addr:street":"Rue De Bruxelles",
    "iso:country":"BE",
    "sg:address":"Rue De Bruxelles 199",
    "sg:city":"Awans",
    "sg:classifiers":[
        {
            "category":"Bars & Pubs",
            "type":"Food & Drink"
        }
    ],
    "sg:phone":"+32 4 263 71 35",
    "sg:postcode":"4340",
    "sg:province":"Li\u00e8ge",
    "wof:name":"Cabane (la)",
    "wof:placetype":"venue"
},
  "geometry": {"coordinates":[5.4883317947,50.6731491089],"type":"Point"}
}