{
  "type": "Feature",
  "properties": {
    "addr:full":"Grand'place 1 Ouffet Li\u00e8ge 4590",
    "addr:housenumber":"1",
    "addr:postcode":"4590",
    "addr:street":"Grand'Place",
    "iso:country":"BE",
    "sg:address":"Grand'place 1",
    "sg:city":"Ouffet",
    "sg:classifiers":[
        {
            "category":"Personal",
            "subcategory":"Nail Salon",
            "type":"Services"
        }
    ],
    "sg:phone":"+32 86 36 74 46",
    "sg:postcode":"4590",
    "sg:province":"Li\u00e8ge",
    "sg:tags":[
        "pedicure"
    ],
    "wof:name":"Legros M",
    "wof:placetype":"venue"
},
  "geometry": {"coordinates":[5.464630127,50.4380836487],"type":"Point"}
}