{
  "type": "Feature",
  "properties": {
    "addr:full":"Doornestraat 3 Herentals (morkhoven) Antwerpen 2200",
    "addr:housenumber":"3",
    "addr:postcode":"2200",
    "addr:street":"Doornestraat",
    "iso:country":"BE",
    "sg:address":"Doornestraat 3",
    "sg:city":"Herentals (morkhoven)",
    "sg:classifiers":[
        {
            "category":"Freight",
            "type":"Transportation"
        }
    ],
    "sg:phone":"+32 14 26 34 31",
    "sg:postcode":"2200",
    "sg:province":"Antwerpen",
    "sg:tags":[
        "-",
        "transport"
    ],
    "wof:name":"Van Dijck Nv",
    "wof:placetype":"venue"
},
  "geometry": {"coordinates":[4.8173809052,51.1202392578],"type":"Point"}
}