{
  "type": "Feature",
  "properties": {
    "iso:country":"BE",
    "sg:address":"Turnhoutsebaan 267",
    "sg:city":"Wijnegem",
    "sg:orig_category":"Krantenuitgeverijen Tijdschriftenuitgeverijen",
    "sg:phone":"+32 3 353 86 39",
    "sg:postcode":"2110",
    "sg:province":"Antwerpen",
    "wof:name":"Berch. Post & Groenenhoek",
    "wof:placetype":"venue"
},
  "geometry": {"coordinates":[4.5176539421,51.2266578674],"type":"Point"}
}