{
  "type": "Feature",
  "properties": {
    "addr:full":"Vieille Rue Du Moulin 360 Ukkel/uccle Bruxelles-Capitale 1180",
    "addr:housenumber":"360",
    "addr:postcode":"1180",
    "addr:street":"Vieille Rue Du Moulin;/",
    "iso:country":"BE",
    "sg:address":"Vieille Rue Du Moulin 360",
    "sg:city":"Ukkel/uccle",
    "sg:orig_category":"Studios photographiques. Grossistes divers",
    "sg:phone":"+32 2 372 08 42",
    "sg:postcode":"1180",
    "sg:province":"Bruxelles-Capitale",
    "wof:name":"Studio A. Javor Internat",
    "wof:placetype":"venue"
},
  "geometry": {"coordinates":[4.3723168373,50.7895507812],"type":"Point"}
}