{
  "type": "Feature",
  "properties": {
    "addr:full":"Ellebogten 59 Destelbergen Oost-Vlaanderen 9070",
    "addr:housenumber":"59",
    "addr:postcode":"9070",
    "addr:street":"Ellebogten",
    "iso:country":"BE",
    "sg:address":"Ellebogten 59",
    "sg:city":"Destelbergen",
    "sg:classifiers":[
        {
            "category":"Recreation",
            "type":"Entertainment"
        }
    ],
    "sg:phone":"+32 9 230 99 26",
    "sg:postcode":"9070",
    "sg:province":"Oost-Vlaanderen",
    "sg:tags":[
        "diver",
        "amusement"
    ],
    "wof:name":"Studio Caroline",
    "wof:placetype":"venue"
},
  "geometry": {"coordinates":[3.798541069,51.0399703979],"type":"Point"}
}