{
  "type": "Feature",
  "properties": {
    "addr:full":"Rue Vin\u00c2ve 23 Grace-hollogne Li\u00e8ge 4460",
    "addr:housenumber":"23",
    "addr:postcode":"4460",
    "addr:street":"Rue Vina\u0302Ve",
    "iso:country":"BE",
    "sg:address":"Rue Vin\u00c2ve 23",
    "sg:city":"Grace-hollogne",
    "sg:orig_category":"Volwassenenonderwijs",
    "sg:phone":"+32 4 233 03 77",
    "sg:postcode":"4460",
    "sg:province":"Li\u00e8ge",
    "wof:name":"Inst.enseign.prom.sociale",
    "wof:placetype":"venue"
},
  "geometry": {"coordinates":[5.4745168686,50.6341781616],"type":"Point"}
}