{
  "type": "Feature",
  "properties": {
    "addr:full":"Herentalsebaan 69 Ranst Antwerpen 2520",
    "addr:housenumber":"69",
    "addr:postcode":"2520",
    "addr:street":"Herentalsebaan",
    "iso:country":"BE",
    "sg:address":"Herentalsebaan 69",
    "sg:city":"Ranst",
    "sg:orig_category":"V\u00eatements sur mesure Fab",
    "sg:phone":"+32 3 485 82 14",
    "sg:postcode":"2520",
    "sg:province":"Antwerpen",
    "wof:name":"Jozef Van Den Eeden",
    "wof:placetype":"venue"
},
  "geometry": {"coordinates":[4.5468091965,51.1852607727],"type":"Point"}
}