{
  "type": "Feature",
  "properties": {
    "addr:full":"Rue De Namur 16 Namur (beez) Namur 5000",
    "addr:housenumber":"16",
    "addr:postcode":"5000",
    "addr:street":"Rue De Namur",
    "iso:country":"BE",
    "sg:address":"Rue De Namur 16",
    "sg:city":"Namur (beez)",
    "sg:classifiers":[
        {
            "category":"Home & Garden",
            "subcategory":"Building Materials",
            "type":"Retail Goods"
        }
    ],
    "sg:phone":"+32 81 22 02 33",
    "sg:postcode":"5000",
    "sg:province":"Namur",
    "sg:tags":[
        "aluminium",
        "construction",
        "-"
    ],
    "wof:name":"Meuse & Sambre Sa",
    "wof:placetype":"venue"
},
  "geometry": {"coordinates":[4.8986229897,50.4677276611],"type":"Point"}
}