{
  "type": "Feature",
  "properties": {
    "addr:full":"Ringlaan 50 Koekelare West-Vlaanderen 8680",
    "addr:housenumber":"50",
    "addr:postcode":"8680",
    "addr:street":"Ringlaan",
    "iso:country":"BE",
    "sg:address":"Ringlaan 50",
    "sg:city":"Koekelare",
    "sg:classifiers":[
        {
            "category":"Professional",
            "subcategory":"Accounting & Tax Preparation",
            "type":"Services"
        }
    ],
    "sg:phone":"+32 51 58 96 00",
    "sg:postcode":"8680",
    "sg:province":"West-Vlaanderen",
    "sg:tags":[
        "bookkeeper"
    ],
    "wof:name":"Balduyck L",
    "wof:placetype":"venue"
},
  "geometry": {"coordinates":[2.9748210907,51.0923652649],"type":"Point"}
}