{
  "type": "Feature",
  "properties": {
    "addr:full":"Dorekesveld 15 Grimbergen (groot) Vlaams-Brabant 1853",
    "addr:housenumber":"15;1853",
    "addr:street":"Dorekesveld;Groot Vlaams-Brabant",
    "iso:country":"BE",
    "sg:address":"Dorekesveld 15",
    "sg:city":"Grimbergen (groot)",
    "sg:orig_category":"Kapsalons",
    "sg:phone":"+32 2 267 14 07",
    "sg:postcode":"1853",
    "sg:province":"Vlaams-Brabant",
    "wof:name":"Odette",
    "wof:placetype":"venue"
},
  "geometry": {"coordinates":[4.3526439667,50.9136390686],"type":"Point"}
}