{
  "type": "Feature",
  "properties": {
    "iso:country":"BE",
    "sg:address":"Godveerdegemstraat 128",
    "sg:city":"Zottegem",
    "sg:classifiers":[
        {
            "category":"Shopping",
            "subcategory":"Clothing, Apparel, & Fashions",
            "type":"Retail Goods"
        }
    ],
    "sg:phone":"+32 9 360 32 84",
    "sg:postcode":"9620",
    "sg:province":"Oost-Vlaanderen",
    "sg:tags":[
        "maternity",
        "wear"
    ],
    "wof:name":"Pr\u00e9maman",
    "wof:placetype":"venue"
},
  "geometry": {"coordinates":[3.8213939667,50.8642463684],"type":"Point"}
}