{
  "type": "Feature",
  "properties": {
    "addr:full":"Koninklijk Plein 3 De Haan (klemskerke) West-Vlaanderen 8420",
    "addr:housenumber":"3",
    "addr:postcode":"8420",
    "addr:street":"Koninklijk Plein",
    "iso:country":"BE",
    "sg:address":"Koninklijk Plein 3",
    "sg:city":"De Haan (klemskerke)",
    "sg:classifiers":[
        {
            "category":"Shopping",
            "subcategory":"Clothing, Apparel, & Fashions",
            "type":"Retail Goods"
        }
    ],
    "sg:phone":"+32 59 23 87 05",
    "sg:postcode":"8420",
    "sg:province":"West-Vlaanderen",
    "sg:tags":[
        "boutique"
    ],
    "wof:name":"Cool Waves",
    "wof:placetype":"venue"
},
  "geometry": {"coordinates":[3.0327920914,51.273059845],"type":"Point"}
}