{
  "type": "Feature",
  "properties": {
    "addr:full":"Rue De La Station 4 Courcelles Hainaut 6181",
    "addr:housenumber":"4",
    "addr:postcode":"6181",
    "addr:street":"Rue De La Station",
    "iso:country":"BE",
    "sg:address":"Rue De La Station 4",
    "sg:city":"Courcelles",
    "sg:orig_category":"Traitements param\u00e9dicaux",
    "sg:phone":"+32 71 84 32 74",
    "sg:postcode":"6181",
    "sg:province":"Hainaut",
    "wof:name":"M. Dehaye",
    "wof:placetype":"venue"
},
  "geometry": {"coordinates":[4.3296627998,50.4873275757],"type":"Point"}
}