{
  "type": "Feature",
  "properties": {
    "addr:full":"Rue H. Marichal 37 Elsene/ixelles Bruxelles-Capitale 1050",
    "addr:housenumber":"37",
    "addr:postcode":"1050",
    "addr:street":"Rue H. Marichal",
    "iso:country":"BE",
    "sg:address":"Rue H. Marichal 37",
    "sg:city":"Elsene/ixelles",
    "sg:orig_category":"Avocats and conseillers juridiques",
    "sg:phone":"+32 2 647 66 24",
    "sg:postcode":"1050",
    "sg:province":"Bruxelles-Capitale",
    "wof:name":"De Bock C.",
    "wof:placetype":"venue"
},
  "geometry": {"coordinates":[4.3841338158,50.8237495422],"type":"Point"}
}