{
  "type": "Feature",
  "properties": {
    "addr:full":"4 Diksmuide Boterweg Hooglede West-Vlaanderen 8830",
    "addr:housenumber":"4",
    "addr:postcode":"8830",
    "addr:street":"Boterweg",
    "iso:country":"BE",
    "sg:address":"4 Diksmuide Boterweg",
    "sg:city":"Hooglede",
    "sg:classifiers":[
        {
            "category":"Farming",
            "subcategory":"Crops",
            "type":"Manufacturing & Wholesale Goods"
        }
    ],
    "sg:phone":"+32 51 72 21 03",
    "sg:postcode":"8830",
    "sg:province":"West-Vlaanderen",
    "sg:tags":[
        "vegetable",
        "fruit",
        "agriculture",
        "livestock"
    ],
    "wof:name":"Vanacker Hubert & Ronny M.",
    "wof:placetype":"venue"
},
  "geometry": {"coordinates":[3.0944449902,51.0060348511],"type":"Point"}
}