{
  "type": "Feature",
  "properties": {
    "addr:full":"Rue Du March\u00e9 Au Charbon 37-39 Bruxelles Bruxelles-Capitale 1000",
    "addr:postcode":"37-39;1000",
    "addr:street":"Rue Du Marche\u0301 Au Charbon",
    "iso:country":"BE",
    "sg:address":"Rue Du March\u00e9 Au Charbon 37-39",
    "sg:city":"Bruxelles",
    "sg:classifiers":[
        {
            "category":"Shopping",
            "subcategory":"Musical Instruments",
            "type":"Retail Goods"
        }
    ],
    "sg:phone":"+32 2 512 77 71",
    "sg:postcode":"1000",
    "sg:province":"Bruxelles-Capitale",
    "sg:tags":[
        "-"
    ],
    "wof:name":"Hill's Music Sprl",
    "wof:placetype":"venue"
},
  "geometry": {"coordinates":[4.3492631912,50.8465766907],"type":"Point"}
}