{
  "type": "Feature",
  "properties": {
    "addr:full":"Plassendale 10 Oudenburg West-Vlaanderen 8460",
    "addr:housenumber":"10",
    "addr:postcode":"8460",
    "addr:street":"Plassendale",
    "iso:country":"BE",
    "sg:address":"Plassendale 10",
    "sg:city":"Oudenburg",
    "sg:classifiers":[
        {
            "category":"Retail",
            "subcategory":"Animal Services",
            "type":"Services"
        }
    ],
    "sg:phone":"+32 59 26 60 16",
    "sg:postcode":"8460",
    "sg:province":"West-Vlaanderen",
    "sg:tags":[
        "oil",
        "-",
        "fat"
    ],
    "wof:name":"Beltrom",
    "wof:placetype":"venue"
},
  "geometry": {"coordinates":[3.0029659271,51.2078437805],"type":"Point"}
}