{
  "type": "Feature",
  "properties": {
    "iso:country":"BE",
    "sg:address":"Edixvelde 1",
    "sg:city":"Aalst",
    "sg:orig_category":"Enseignement maternel and primaire",
    "sg:phone":"+32 53 83 49 16",
    "sg:postcode":"9320",
    "sg:province":"Oost-Vlaanderen",
    "wof:name":"Stedelijke Kleuterschool",
    "wof:placetype":"venue"
},
  "geometry": {"coordinates":[4.0553851128,50.9209976196],"type":"Point"}
}