{
  "type": "Feature",
  "properties": {
    "addr:full":"Achelmansstraat 74 Peer Limburg 3990",
    "addr:housenumber":"74",
    "addr:postcode":"3990",
    "addr:street":"Achelmansstraat",
    "iso:country":"BE",
    "sg:address":"Achelmansstraat 74",
    "sg:city":"Peer",
    "sg:orig_category":"Eleveurs de bovins",
    "sg:phone":"+32 11 63 28 45",
    "sg:postcode":"3990",
    "sg:province":"Limburg",
    "wof:name":"Jozef Broekx",
    "wof:placetype":"venue"
},
  "geometry": {"coordinates":[5.4104971886,51.115524292],"type":"Point"}
}