{
  "type": "Feature",
  "properties": {
    "addr:full":"Ter Beke 7ba Brugge West-Vlaanderen 8200",
    "addr:housenumber":"7ba",
    "addr:postcode":"8200",
    "addr:street":"Ter Beke",
    "iso:country":"BE",
    "sg:address":"Ter Beke 7ba",
    "sg:city":"Brugge",
    "sg:orig_category":"Rusthuizen and serviceflats",
    "sg:phone":"+32 50 38 21 58",
    "sg:postcode":"8200",
    "sg:province":"West-Vlaanderen",
    "wof:name":"Rustoord Ten Boomgaarde",
    "wof:placetype":"venue"
},
  "geometry": {"coordinates":[3.2133591175,51.1891593933],"type":"Point"}
}