{
  "type": "Feature",
  "properties": {
    "addr:full":"Technologiestraat 61 Sint-agatha-berchem/berchem-sainte-agathe Bruxelles-Capitale 1082",
    "addr:housenumber":"61",
    "addr:postcode":"1082",
    "addr:street":"Technologiestraat;/",
    "iso:country":"BE",
    "sg:address":"Technologiestraat 61",
    "sg:city":"Sint-agatha-berchem/berchem-sainte-agathe",
    "sg:orig_category":"Foto-uitrusting",
    "sg:phone":"+32 2 465 20 20",
    "sg:postcode":"1082",
    "sg:province":"Bruxelles-Capitale",
    "wof:name":"Hasselblad Image Centre",
    "wof:placetype":"venue"
},
  "geometry": {"coordinates":[4.2918248177,50.8742828369],"type":"Point"}
}