{
  "type": "Feature",
  "properties": {
    "iso:country":"BE",
    "sg:address":"Rue Fernand Chaumont 33",
    "sg:city":"Verviers (petit-rechain)",
    "sg:classifiers":[
        {
            "category":"Manufacturing",
            "subcategory":"Furniture",
            "type":"Manufacturing & Wholesale Goods"
        }
    ],
    "sg:phone":"+32 87 31 30 60",
    "sg:postcode":"4800",
    "sg:province":"Li\u00e8ge",
    "sg:tags":[
        "made",
        "-",
        "custom"
    ],
    "wof:name":"Wegnez Ph",
    "wof:placetype":"venue"
},
  "geometry": {"coordinates":[5.8334321976,50.6158676147],"type":"Point"}
}