{
  "type": "Feature",
  "properties": {
    "addr:full":"Riet 3 Stekene Oost-Vlaanderen 9190",
    "addr:housenumber":"3",
    "addr:postcode":"9190",
    "addr:street":"Riet",
    "iso:country":"BE",
    "sg:address":"Riet 3",
    "sg:city":"Stekene",
    "sg:orig_category":"Plaatsen van vloer- and muurbekleding Schilders Verlichting and huishoudartikelen",
    "sg:phone":"+32 3 779 70 08",
    "sg:postcode":"9190",
    "sg:province":"Oost-Vlaanderen",
    "wof:name":"Carlo Van Berckelaer",
    "wof:placetype":"venue"
},
  "geometry": {"coordinates":[3.990696907,51.2257728577],"type":"Point"}
}