{
  "type": "Feature",
  "properties": {
    "addr:full":"Raspaillebosstraat 89 Geraardsbergen Oost-Vlaanderen 9506",
    "addr:housenumber":"89",
    "addr:postcode":"9506",
    "addr:street":"Raspaillebosstraat",
    "iso:country":"BE",
    "sg:address":"Raspaillebosstraat 89",
    "sg:city":"Geraardsbergen",
    "sg:orig_category":"Woningbouw",
    "sg:phone":"+32 54 33 87 59",
    "sg:postcode":"9506",
    "sg:province":"Oost-Vlaanderen",
    "wof:name":"Raphael Ronsijn",
    "wof:placetype":"venue"
},
  "geometry": {"coordinates":[3.9458498955,50.7842903137],"type":"Point"}
}