{
  "type": "Feature",
  "properties": {
    "iso:country":"BE",
    "sg:address":"Leuvensesteenweg 292",
    "sg:city":"Boortmeerbeek",
    "sg:classifiers":[
        {
            "category":"Retail",
            "subcategory":"Auto Repair",
            "type":"Services"
        }
    ],
    "sg:phone":"+32 15 51 10 89",
    "sg:postcode":"3190",
    "sg:province":"Vlaams-Brabant",
    "sg:tags":[
        "garage"
    ],
    "wof:name":"Edvacar",
    "wof:placetype":"venue"
},
  "geometry": {"coordinates":[4.5693340302,50.9706039429],"type":"Point"}
}