{
  "type": "Feature",
  "properties": {
    "iso:country":"BE",
    "sg:address":"Groene Corniche 8",
    "sg:city":"Sint-pieters-woluwe/woluwe-saint-pierre",
    "sg:orig_category":"Advocaten and juridische adviseurs",
    "sg:phone":"+32 2 772 87 64",
    "sg:postcode":"1150",
    "sg:province":"Bruxelles-Capitale",
    "wof:name":"F. Dehousse",
    "wof:placetype":"venue"
},
  "geometry": {"coordinates":[4.4665970802,50.8319587708],"type":"Point"}
}