{
  "type": "Feature",
  "properties": {
    "addr:full":"Torhoutbaan 39 Ichtegem West-Vlaanderen 8480",
    "addr:housenumber":"39",
    "addr:postcode":"8480",
    "addr:street":"Torhoutbaan",
    "iso:country":"BE",
    "sg:address":"Torhoutbaan 39",
    "sg:city":"Ichtegem",
    "sg:classifiers":[
        {
            "category":"Retail",
            "subcategory":"Auto Repair",
            "type":"Services"
        }
    ],
    "sg:phone":"+32 51 58 36 24",
    "sg:postcode":"8480",
    "sg:province":"West-Vlaanderen",
    "sg:tags":[
        "garage"
    ],
    "wof:name":"Sd Motors",
    "wof:placetype":"venue"
},
  "geometry": {"coordinates":[3.0352408886,51.0995597839],"type":"Point"}
}