{
  "type": "Feature",
  "properties": {
    "addr:full":"Avenue Notre-dame 109 Evere Bruxelles-Capitale 1140",
    "addr:housenumber":"109",
    "addr:postcode":"1140",
    "addr:street":"Avenue Notre-Dame",
    "iso:country":"BE",
    "sg:address":"Avenue Notre-dame 109",
    "sg:city":"Evere",
    "sg:orig_category":"Banques and organismes de cr\u00e9dit",
    "sg:phone":"+32 2 245 88 25",
    "sg:postcode":"1140",
    "sg:province":"Bruxelles-Capitale",
    "wof:name":"Eural",
    "wof:placetype":"venue"
},
  "geometry": {"coordinates":[4.4006690979,50.8714103699],"type":"Point"}
}