{
  "type": "Feature",
  "properties": {
    "iso:country":"BE",
    "sg:address":"Voordelaan 23",
    "sg:city":"Leuven (heverlee)",
    "sg:classifiers":[
        {
            "category":"Health Services",
            "subcategory":"Doctor",
            "type":"Services"
        }
    ],
    "sg:phone":"+32 16 38 92 11",
    "sg:postcode":"3001",
    "sg:province":"Vlaams-Brabant",
    "sg:tags":[
        "medicinephysicians",
        "surgeon"
    ],
    "wof:name":"Lorr\u00e9 Benedikte",
    "wof:placetype":"venue"
},
  "geometry": {"coordinates":[4.7091917992,50.8615760803],"type":"Point"}
}