{
  "type": "Feature",
  "properties": {
    "addr:full":"Zoning De La Cale S\u00e8che 36 Oupeye (haccourt) Li\u00e8ge 4684",
    "addr:housenumber":"36",
    "addr:postcode":"4684",
    "addr:street":"Zoning De La Cale Se\u0300Che",
    "iso:country":"BE",
    "sg:address":"Zoning De La Cale S\u00e8che 36",
    "sg:city":"Oupeye (haccourt)",
    "sg:classifiers":[
        {
            "category":"Utilities",
            "subcategory":"Natural Gas",
            "type":"Services"
        }
    ],
    "sg:phone":"+32 4 379 88 45",
    "sg:postcode":"4684",
    "sg:province":"Li\u00e8ge",
    "sg:tags":[
        "welding"
    ],
    "wof:name":"Dieu M",
    "wof:placetype":"venue"
},
  "geometry": {"coordinates":[5.673019886,50.727519989],"type":"Point"}
}