{
  "type": "Feature",
  "properties": {
    "addr:full":"Honsfeld 221 B\u00dcllingen/bullange Li\u00e8ge 4760",
    "addr:housenumber":"221",
    "addr:postcode":"4760",
    "addr:street":"Honsfeld",
    "iso:country":"BE",
    "sg:address":"Honsfeld 221",
    "sg:city":"B\u00dcllingen/bullange",
    "sg:orig_category":"Landbouwmachines Gh",
    "sg:phone":"+32 80 64 77 21",
    "sg:postcode":"4760",
    "sg:province":"Li\u00e8ge",
    "wof:name":"Collas Jean",
    "wof:placetype":"venue"
},
  "geometry": {"coordinates":[6.2787179947,50.3852043152],"type":"Point"}
}