{
  "type": "Feature",
  "properties": {
    "iso:country":"BE",
    "sg:address":"Julie Billiartplein 2",
    "sg:city":"Zele",
    "sg:orig_category":"Enseignement maternel and primaire",
    "sg:phone":"+32 52 45 03 88",
    "sg:postcode":"9240",
    "sg:province":"Oost-Vlaanderen",
    "wof:name":"Vrije Kleuterschool",
    "wof:placetype":"venue"
},
  "geometry": {"coordinates":[4.0265002251,51.0667533875],"type":"Point"}
}