{
  "type": "Feature",
  "properties": {
    "addr:full":"Julie Billiartplein 2 Zele Oost-Vlaanderen 9240",
    "addr:housenumber":"2",
    "addr:postcode":"9240",
    "addr:street":"Billiartplein",
    "iso:country":"BE",
    "sg:address":"Julie Billiartplein 2",
    "sg:city":"Zele",
    "sg:orig_category":"Enseignement maternel and primaire",
    "sg:phone":"+32 52 45 03 88",
    "sg:postcode":"9240",
    "sg:province":"Oost-Vlaanderen",
    "wof:name":"Vrije Kleuterschool",
    "wof:placetype":"venue"
},
  "geometry": {"coordinates":[4.0265002251,51.0667533875],"type":"Point"}
}