{
  "type": "Feature",
  "properties": {
    "iso:country":"BE",
    "sg:address":"Rue Neuve 19",
    "sg:city":"Gembloux",
    "sg:orig_category":"Advocaten and juridische adviseurs",
    "sg:phone":"+32 81 56 06 76",
    "sg:postcode":"5030",
    "sg:province":"Namur",
    "wof:name":"David Poelaert",
    "wof:placetype":"venue"
},
  "geometry": {"coordinates":[4.7502889633,50.5323562622],"type":"Point"}
}