{
  "type": "Feature",
  "properties": {
    "iso:country":"BE",
    "sg:address":"Afspanningsstraat 17",
    "sg:city":"Harelbeke",
    "sg:orig_category":"Groenten and fruit Gh",
    "sg:phone":"+32 56 70 31 13",
    "sg:postcode":"8531",
    "sg:province":"West-Vlaanderen",
    "wof:name":"Krikro",
    "wof:placetype":"venue"
},
  "geometry": {"coordinates":[3.3112299442,50.8675231934],"type":"Point"}
}