{
  "type": "Feature",
  "properties": {
    "iso:country":"BE",
    "sg:address":"Kouterstraat 50",
    "sg:city":"Kortenberg (erps-kwerps)",
    "sg:classifiers":[
        {
            "category":"Professional",
            "subcategory":"Management & Consulting",
            "type":"Services"
        }
    ],
    "sg:phone":"+32 2 759 36 00",
    "sg:postcode":"3071",
    "sg:province":"Vlaams-Brabant",
    "sg:tags":[
        "consultant",
        "agency",
        "advertising"
    ],
    "wof:name":"R A & M",
    "wof:placetype":"venue"
},
  "geometry": {"coordinates":[4.5734472275,50.9019851685],"type":"Point"}
}