{
  "type": "Feature",
  "properties": {
    "addr:full":"Rue Colo-hugue 69 Braine-l'alleud Brabant Wallon 1420",
    "addr:housenumber":"69",
    "addr:postcode":"1420",
    "addr:street":"Rue Colo-Hugue",
    "iso:country":"BE",
    "sg:address":"Rue Colo-hugue 69",
    "sg:city":"Braine-l'alleud",
    "sg:classifiers":[
        {
            "category":"Autos & Motor Vehicles",
            "subcategory":"Automobile Sales",
            "type":"Retail Goods"
        }
    ],
    "sg:phone":"+32 2 384 25 63",
    "sg:postcode":"1420",
    "sg:province":"Brabant Wallon",
    "sg:tags":[
        "equipment",
        "motor-cars",
        "transport"
    ],
    "wof:name":"Ets Becker Henri",
    "wof:placetype":"venue"
},
  "geometry": {"coordinates":[-105.5509109497,38.9978408813],"type":"Point"}
}