{
  "type": "Feature",
  "properties": {
    "addr:full":"Rue Voie De Li\u00e8ge 82-86 Herstal Li\u00e8ge 4040",
    "addr:postcode":"82-86;4040",
    "addr:street":"Rue Voie De Lie\u0300Ge",
    "iso:country":"BE",
    "sg:address":"Rue Voie De Li\u00e8ge 82-86",
    "sg:city":"Herstal",
    "sg:classifiers":[
        {
            "category":"Home & Garden",
            "subcategory":"Home Furnishings",
            "type":"Retail Goods"
        }
    ],
    "sg:phone":"+32 4 264 00 53",
    "sg:postcode":"4040",
    "sg:province":"Li\u00e8ge",
    "sg:tags":[
        "fitting"
    ],
    "wof:name":"Bayard-richelle Jointcam",
    "wof:placetype":"venue"
},
  "geometry": {"coordinates":[5.6310281754,50.6682319641],"type":"Point"}
}