{
  "type": "Feature",
  "properties": {
    "addr:full":"Neringenstraat 42 Tielt West-Vlaanderen 8700",
    "addr:housenumber":"42",
    "addr:postcode":"8700",
    "addr:street":"Neringenstraat",
    "iso:country":"BE",
    "sg:address":"Neringenstraat 42",
    "sg:city":"Tielt",
    "sg:orig_category":"Eleveurs de bovins. Eleveurs and marchands de porcs",
    "sg:phone":"+32 51 63 34 91",
    "sg:postcode":"8700",
    "sg:province":"West-Vlaanderen",
    "wof:name":"Daniel Van Dorpe",
    "wof:placetype":"venue"
},
  "geometry": {"coordinates":[3.4070999622,51.0088539124],"type":"Point"}
}