{
  "type": "Feature",
  "properties": {
    "addr:full":"Okkerdriesstraat 102 Avelgem (outrijve) West-Vlaanderen 8582",
    "addr:housenumber":"102",
    "addr:postcode":"8582",
    "addr:street":"Okkerdriesstraat",
    "iso:country":"BE",
    "sg:address":"Okkerdriesstraat 102",
    "sg:city":"Avelgem (outrijve)",
    "sg:classifiers":[
        {
            "category":"Freight",
            "type":"Transportation"
        }
    ],
    "sg:phone":"+32 56 64 46 17",
    "sg:postcode":"8582",
    "sg:province":"West-Vlaanderen",
    "sg:tags":[
        "-",
        "transport"
    ],
    "wof:name":"Exelsior Bvba",
    "wof:placetype":"venue"
},
  "geometry": {"coordinates":[3.4226279259,50.767578125],"type":"Point"}
}