{
  "type": "Feature",
  "properties": {
    "addr:full":"Impasse De La Cha\u00cene 27 Li\u00c8ge Li\u00e8ge 4000",
    "addr:housenumber":"27",
    "addr:postcode":"4000",
    "addr:street":"Impasse De La Chai\u0302Ne",
    "iso:country":"BE",
    "sg:address":"Impasse De La Cha\u00cene 27",
    "sg:city":"Li\u00c8ge",
    "sg:orig_category":"Architectes",
    "sg:phone":"+32 4 221 35 48",
    "sg:postcode":"4000",
    "sg:province":"Li\u00e8ge",
    "wof:name":"Sandra Humblet",
    "wof:placetype":"venue"
},
  "geometry": {"coordinates":[5.5772538185,50.6560096741],"type":"Point"}
}