{
  "type": "Feature",
  "properties": {
    "iso:country":"BE",
    "sg:address":"Rue Guillaume Delarge 114",
    "sg:city":"Herstal",
    "sg:orig_category":"Boucheries",
    "sg:phone":"+32 4 264 13 47",
    "sg:postcode":"4040",
    "sg:province":"Li\u00e8ge",
    "wof:name":"Francis Bohet",
    "wof:placetype":"venue"
},
  "geometry": {"coordinates":[5.6235570908,50.6629753113],"type":"Point"}
}