{
  "type": "Feature",
  "properties": {
    "addr:full":"Avenue De Jette 53 Koekelberg Bruxelles-Capitale 1081",
    "addr:housenumber":"53",
    "addr:postcode":"1081",
    "addr:street":"Avenue De Jette",
    "iso:country":"BE",
    "sg:address":"Avenue De Jette 53",
    "sg:city":"Koekelberg",
    "sg:classifiers":[
        {
            "category":"Insurance",
            "subcategory":"Life Insurance",
            "type":"Services"
        }
    ],
    "sg:phone":"+32 2 425 92 47",
    "sg:postcode":"1081",
    "sg:province":"Bruxelles-Capitale",
    "sg:tags":[
        "assurance"
    ],
    "wof:name":"Hypassur",
    "wof:placetype":"venue"
},
  "geometry": {"coordinates":[4.3269948959,50.8667526245],"type":"Point"}
}