{
  "type": "Feature",
  "properties": {
    "iso:country":"BE",
    "sg:address":"Leopoldstraat 24",
    "sg:city":"Zemst",
    "sg:orig_category":"Epiceries",
    "sg:phone":"+32 15 61 12 77",
    "sg:postcode":"1980",
    "sg:province":"Vlaams-Brabant",
    "wof:name":"De Coninck",
    "wof:placetype":"venue"
},
  "geometry": {"coordinates":[4.4618301392,50.9837417603],"type":"Point"}
}