{
  "type": "Feature",
  "properties": {
    "addr:full":"Rue Martin Herman 62 Herstal Li\u00e8ge 4040",
    "addr:housenumber":"62",
    "addr:postcode":"4040",
    "addr:street":"Rue Martin Herman",
    "iso:country":"BE",
    "sg:address":"Rue Martin Herman 62",
    "sg:city":"Herstal",
    "sg:classifiers":[
        {
            "category":"Personal",
            "subcategory":"Beauty Salon",
            "type":"Services"
        }
    ],
    "sg:phone":"+32 4 264 78 48",
    "sg:postcode":"4040",
    "sg:province":"Li\u00e8ge",
    "sg:tags":[
        "lady",
        "-",
        "hairdressing"
    ],
    "wof:name":"Christiane",
    "wof:placetype":"venue"
},
  "geometry": {"coordinates":[5.6236357689,50.6676254272],"type":"Point"}
}