{
  "type": "Feature",
  "properties": {
    "iso:country":"BE",
    "sg:address":"Fond-al-gotte 1",
    "sg:city":"Dinant (sorinnes)",
    "sg:classifiers":[
        {
            "category":"Real Estate",
            "subcategory":"Surveying",
            "type":"Services"
        }
    ],
    "sg:phone":"+32 82 22 21 48",
    "sg:postcode":"5503",
    "sg:province":"Namur",
    "sg:tags":[
        "lettering",
        "letter"
    ],
    "wof:name":"Precis Services",
    "wof:placetype":"venue"
},
  "geometry": {"coordinates":[4.9799208641,50.2595214844],"type":"Point"}
}