{
  "type": "Feature",
  "properties": {
    "addr:full":"Avenue De Ninove 168 Rochefort (jemelle) Namur 5580",
    "addr:housenumber":"168",
    "addr:postcode":"5580",
    "addr:street":"Avenue De Ninove",
    "iso:country":"BE",
    "sg:address":"Avenue De Ninove 168",
    "sg:city":"Rochefort (jemelle)",
    "sg:classifiers":[
        {
            "category":"Communications",
            "type":"Services"
        }
    ],
    "sg:phone":"+32 84 37 82 66",
    "sg:postcode":"5580",
    "sg:province":"Namur",
    "sg:tags":[
        "translator"
    ],
    "wof:name":"Bastin I",
    "wof:placetype":"venue"
},
  "geometry": {"coordinates":[5.2499289513,50.1627006531],"type":"Point"}
}