{
  "type": "Feature",
  "properties": {
    "addr:full":"Roestraat 3 Waregem West-Vlaanderen 8791",
    "addr:housenumber":"3",
    "addr:postcode":"8791",
    "addr:street":"Roestraat",
    "iso:country":"BE",
    "sg:address":"Roestraat 3",
    "sg:city":"Waregem",
    "sg:classifiers":[
        {
            "category":"Building & Trades",
            "subcategory":"Landscaping Services",
            "type":"Services"
        }
    ],
    "sg:phone":"+32 56 71 96 83",
    "sg:postcode":"8791",
    "sg:province":"West-Vlaanderen",
    "sg:tags":[
        "etude",
        "technique",
        "ing\u00e9nierie"
    ],
    "wof:name":"Interim Tek",
    "wof:placetype":"venue"
},
  "geometry": {"coordinates":[3.3364980221,50.8721122742],"type":"Point"}
}