{
  "type": "Feature",
  "properties": {
    "iso:country":"BE",
    "sg:address":"Dorpsstraat 51",
    "sg:city":"Beveren (kieldrecht)",
    "sg:classifiers":[
        {
            "category":"Home & Garden",
            "subcategory":"Building Materials",
            "type":"Retail Goods"
        }
    ],
    "sg:phone":"+32 3 773 42 58",
    "sg:postcode":"9130",
    "sg:province":"Oost-Vlaanderen",
    "sg:tags":[
        "bathroom",
        "installation",
        "accessory"
    ],
    "wof:name":"Van Kruyssen W",
    "wof:placetype":"venue"
},
  "geometry": {"coordinates":[4.1738700867,51.2913131714],"type":"Point"}
}