{
  "type": "Feature",
  "properties": {
    "addr:full":"Acacialaan 48 Turnhout Antwerpen 2300",
    "addr:housenumber":"48",
    "addr:postcode":"2300",
    "addr:street":"Acacialaan",
    "iso:country":"BE",
    "sg:address":"Acacialaan 48",
    "sg:city":"Turnhout",
    "sg:orig_category":"Rev\u00eatements de sols and murs",
    "sg:phone":"+32 14 41 09 23",
    "sg:postcode":"2300",
    "sg:province":"Antwerpen",
    "wof:name":"Verdijck",
    "wof:placetype":"venue"
},
  "geometry": {"coordinates":[4.9528107643,51.3016166687],"type":"Point"}
}