{
  "type": "Feature",
  "properties": {
    "addr:full":"De Keizerlei 5b39 Antwerpen 28520180",
    "addr:housenumber":"5b39",
    "addr:postcode":"28520180",
    "iso:country":"BE",
    "sg:address":"De Keizerlei 5b39",
    "sg:city":"Antwerpen",
    "sg:orig_category":"Produits chimiques Gr",
    "sg:phone":"+32 3 206 06 00",
    "sg:postcode":"28520180",
    "wof:name":"Belgium Marketing Service",
    "wof:placetype":"venue"
},
  "geometry": {"coordinates":[4.4061779976,51.2219200134],"type":"Point"}
}