{
  "type": "Feature",
  "properties": {
    "addr:full":"Rue De L'arbre \u00c0 La Croix 300 Grace-hollogne Li\u00e8ge 4460",
    "addr:housenumber":"300",
    "addr:postcode":"4460",
    "addr:street":"Rue De L'Arbre A\u0300 La Croix",
    "iso:country":"BE",
    "sg:address":"Rue De L'arbre \u00c0 La Croix 300",
    "sg:city":"Grace-hollogne",
    "sg:orig_category":"Kapsalons",
    "sg:phone":"+32 4 250 52 84",
    "sg:postcode":"4460",
    "sg:province":"Li\u00e8ge",
    "wof:name":"Coiffure Dominitif",
    "wof:placetype":"venue"
},
  "geometry": {"coordinates":[5.3800439835,50.6340332031],"type":"Point"}
}