{
  "type": "Feature",
  "properties": {
    "iso:country":"BE",
    "sg:address":"Rue Longue 245",
    "sg:city":"Drogenbos/drogenbos",
    "sg:orig_category":"M\u00e9decins and sp\u00e9cialistes",
    "sg:phone":"+32 2 331 35 94",
    "sg:postcode":"1620",
    "sg:province":"Vlaams-Brabant",
    "wof:name":"E. Van Gelder",
    "wof:placetype":"venue"
},
  "geometry": {"coordinates":[4.314139843,50.7942085266],"type":"Point"}
}