{
  "type": "Feature",
  "properties": {
    "addr:full":"Rue De Baume 147 La Louvi\u00c8re Hainaut 7100",
    "addr:housenumber":"147",
    "addr:postcode":"7100",
    "addr:street":"Rue De Baume",
    "iso:country":"BE",
    "sg:address":"Rue De Baume 147",
    "sg:city":"La Louvi\u00c8re",
    "sg:orig_category":"Boekhouders",
    "sg:phone":"+32 64 28 20 99",
    "sg:postcode":"7100",
    "sg:province":"Hainaut",
    "wof:name":"Philippe Delhaye",
    "wof:placetype":"venue"
},
  "geometry": {"coordinates":[4.2042098045,50.4739379883],"type":"Point"}
}