{
  "type": "Feature",
  "properties": {
    "addr:full":"Kapellendries 90 Wetteren Oost-Vlaanderen 9230",
    "addr:housenumber":"90",
    "addr:postcode":"9230",
    "addr:street":"Kapellendries",
    "iso:country":"BE",
    "sg:address":"Kapellendries 90",
    "sg:city":"Wetteren",
    "sg:classifiers":[
        {
            "category":"Building & Trades",
            "subcategory":"Construction",
            "type":"Services"
        }
    ],
    "sg:phone":"+32 9 324 04 21",
    "sg:postcode":"9230",
    "sg:province":"Oost-Vlaanderen",
    "sg:tags":[
        "paper",
        "hanger"
    ],
    "wof:name":"De Feijter S",
    "wof:placetype":"venue"
},
  "geometry": {"coordinates":[3.8812439442,51.012386322],"type":"Point"}
}