{
  "type": "Feature",
  "properties": {
    "addr:full":"Seringenlaan 3 Rumst Antwerpen 2840",
    "addr:housenumber":"3",
    "addr:postcode":"2840",
    "addr:street":"Seringenlaan",
    "iso:country":"BE",
    "sg:address":"Seringenlaan 3",
    "sg:city":"Rumst",
    "sg:classifiers":[
        {
            "category":"Personal",
            "subcategory":"Beauty Salon",
            "type":"Services"
        }
    ],
    "sg:phone":"+32 3 844 48 13",
    "sg:postcode":"2840",
    "sg:province":"Antwerpen",
    "sg:tags":[
        "de",
        "coiffure"
    ],
    "wof:name":"Coiffure Kristel",
    "wof:placetype":"venue"
},
  "geometry": {"coordinates":[4.3899941444,51.1076850891],"type":"Point"}
}