{
  "type": "Feature",
  "properties": {
    "iso:country":"BE",
    "sg:address":"Chauss\u00c9e De Vleurgat 206",
    "sg:city":"Brussel/bruxelles",
    "sg:orig_category":"Agences immobili\u00e8res",
    "sg:phone":"+32 2 640 87 70",
    "sg:postcode":"1000",
    "sg:province":"Bruxelles-Capitale",
    "wof:name":"Vleurgat Center House",
    "wof:placetype":"venue"
},
  "geometry": {"coordinates":[4.3667931557,50.8213424683],"type":"Point"}
}