{
  "type": "Feature",
  "properties": {
    "addr:full":"Tieltstraat 33 Pittem West-Vlaanderen 8740",
    "addr:housenumber":"33",
    "addr:postcode":"8740",
    "addr:street":"Tieltstraat",
    "iso:country":"BE",
    "sg:address":"Tieltstraat 33",
    "sg:city":"Pittem",
    "sg:orig_category":"Etalage- and showroomontwerpers",
    "sg:phone":"+32 51 46 79 35",
    "sg:postcode":"8740",
    "sg:province":"West-Vlaanderen",
    "wof:name":"Jo Vervaeke",
    "wof:placetype":"venue"
},
  "geometry": {"coordinates":[3.2665100098,50.9931488037],"type":"Point"}
}