{
  "type": "Feature",
  "properties": {
    "addr:full":"Kleinebeerstraat 16 Antwerpen Antwerpen 2018",
    "addr:housenumber":"16",
    "addr:postcode":"2018",
    "addr:street":"Kleinebeerstraat",
    "iso:country":"BE",
    "sg:address":"Kleinebeerstraat 16",
    "sg:city":"Antwerpen",
    "sg:orig_category":"Artsen and specialisten",
    "sg:phone":"+32 3 230 27 30",
    "sg:postcode":"2018",
    "sg:province":"Antwerpen",
    "wof:name":"Consultatiebur.jonge Kind",
    "wof:placetype":"venue"
},
  "geometry": {"coordinates":[4.4278302193,51.2074584961],"type":"Point"}
}