{
  "type": "Feature",
  "properties": {
    "addr:full":"Avenue Franklin Roosevelt 103 Bruxelles (ixelles) Bruxelles-Capitale 1050",
    "addr:housenumber":"103",
    "addr:postcode":"1050",
    "addr:street":"Avenue Franklin Roosevelt",
    "iso:country":"BE",
    "sg:address":"Avenue Franklin Roosevelt 103",
    "sg:city":"Bruxelles (ixelles)",
    "sg:classifiers":[
        {
            "category":"Communications",
            "type":"Services"
        }
    ],
    "sg:phone":"+32 2 660 29 42",
    "sg:postcode":"1050",
    "sg:province":"Bruxelles-Capitale",
    "sg:tags":[
        "translator"
    ],
    "wof:name":"Ioltaa International Sa",
    "wof:placetype":"venue"
},
  "geometry": {"coordinates":[4.3886761665,50.8020973206],"type":"Point"}
}