{
  "type": "Feature",
  "properties": {
    "addr:full":"Rue Bois-des-chanoines 2 Fosses-la-ville Namur 5070",
    "addr:housenumber":"2",
    "addr:postcode":"5070",
    "addr:street":"Rue Bois-Des-Chanoines",
    "iso:country":"BE",
    "sg:address":"Rue Bois-des-chanoines 2",
    "sg:city":"Fosses-la-ville",
    "sg:orig_category":"Eleveurs de bovins",
    "sg:phone":"+32 71 71 12 38",
    "sg:postcode":"5070",
    "sg:province":"Namur",
    "wof:name":"Arthur Besombe",
    "wof:placetype":"venue"
},
  "geometry": {"coordinates":[4.6668448448,50.3708992004],"type":"Point"}
}