{
  "type": "Feature",
  "properties": {
    "addr:full":"Baerdonckstraat 70 Wetteren Oost-Vlaanderen 9230",
    "addr:housenumber":"70",
    "addr:postcode":"9230",
    "addr:street":"Baerdonckstraat",
    "iso:country":"BE",
    "sg:address":"Baerdonckstraat 70",
    "sg:city":"Wetteren",
    "sg:classifiers":[
        {
            "category":"Retail",
            "subcategory":"Event Space",
            "type":"Services"
        }
    ],
    "sg:phone":"+32 9 368 10 32",
    "sg:postcode":"9230",
    "sg:province":"Oost-Vlaanderen",
    "sg:tags":[
        "organisation"
    ],
    "wof:name":"G'ethics",
    "wof:placetype":"venue"
},
  "geometry": {"coordinates":[3.8880770206,51.0159111023],"type":"Point"}
}