{
  "type": "Feature",
  "properties": {
    "iso:country":"BE",
    "sg:address":"Paalsteenlaan 49",
    "sg:city":"Lanaken (neerharen)",
    "sg:classifiers":[
        {
            "category":"Professional",
            "subcategory":"Art Services",
            "type":"Services"
        }
    ],
    "sg:phone":"+32 89 71 85 70",
    "sg:postcode":"3620",
    "sg:province":"Limburg",
    "sg:tags":[
        "graphic",
        "designer"
    ],
    "wof:name":"Grafiekbureau",
    "wof:placetype":"venue"
},
  "geometry": {"coordinates":[5.6744990349,50.912437439],"type":"Point"}
}