{
  "type": "Feature",
  "properties": {
    "iso:country":"BE",
    "sg:address":"Patrijzenlaan 35",
    "sg:city":"Essen",
    "sg:classifiers":[
        {
            "category":"Building & Trades",
            "subcategory":"Landscaping Services",
            "type":"Services"
        }
    ],
    "sg:phone":"+32 3 667 15 39",
    "sg:postcode":"2910",
    "sg:province":"Antwerpen",
    "sg:tags":[
        "equipment",
        "swimming",
        "-",
        "pool",
        "contractor"
    ],
    "wof:name":"Be-ne Schoonmaak Diensten",
    "wof:placetype":"venue"
},
  "geometry": {"coordinates":[4.4455099106,51.4393806458],"type":"Point"}
}