{
  "type": "Feature",
  "properties": {
    "iso:country":"BE",
    "sg:address":"Lippenslaan 288",
    "sg:city":"Knokke-heist (knokke)",
    "sg:classifiers":[
        {
            "category":"Shopping",
            "subcategory":"Gifts & Souvenirs",
            "type":"Retail Goods"
        }
    ],
    "sg:phone":"+32 50 60 05 11",
    "sg:postcode":"8300",
    "sg:province":"West-Vlaanderen",
    "sg:tags":[
        "postcard",
        "picture",
        "greeting",
        "card"
    ],
    "wof:name":"Avant",
    "wof:placetype":"venue"
},
  "geometry": {"coordinates":[3.2887101173,51.3489112854],"type":"Point"}
}