{
  "type": "Feature",
  "properties": {
    "iso:country":"BE",
    "sg:address":"Oeselgemstraat 78",
    "sg:city":"Zulte",
    "sg:orig_category":"Maisons de repos and r\u00e9sidences",
    "sg:phone":"+32 9 388 88 93",
    "sg:postcode":"9870",
    "sg:province":"Oost-Vlaanderen",
    "wof:name":"Fa. Bel Age",
    "wof:placetype":"venue"
},
  "geometry": {"coordinates":[3.4420850277,50.9263267517],"type":"Point"}
}