{
  "type": "Feature",
  "properties": {
    "iso:country":"BE",
    "sg:address":"Rue Du Couvent 11",
    "sg:city":"Beaumont",
    "sg:classifiers":[
        {
            "category":"Restaurant",
            "type":"Food & Drink"
        }
    ],
    "sg:phone":"+32 71 58 99 27",
    "sg:postcode":"6500",
    "sg:province":"Hainaut",
    "wof:name":"Le Barben\u00c7on",
    "wof:placetype":"venue"
},
  "geometry": {"coordinates":[4.2805700302,50.2243614197],"type":"Point"}
}