{
  "type": "Feature",
  "properties": {
    "iso:country":"BE",
    "sg:address":"Rue Sablonni\u00e8re 67",
    "sg:city":"Rebecq (wisbecq)",
    "sg:classifiers":[
        {
            "category":"Communications",
            "type":"Services"
        }
    ],
    "sg:phone":"+32 67 63 81 92",
    "sg:postcode":"1430",
    "sg:province":"Brabant Wallon",
    "sg:tags":[
        "translator"
    ],
    "wof:name":"Peelaers Sprl",
    "wof:placetype":"venue"
},
  "geometry": {"coordinates":[4.1461658478,50.6806945801],"type":"Point"}
}