{
  "type": "Feature",
  "properties": {
    "iso:country":"BE",
    "sg:address":"Rue Leon Autrique 15-17",
    "sg:city":"Bruxelles",
    "sg:orig_category":"Label Printing Systems",
    "sg:phone":"+32 2 411 57 51",
    "sg:postcode":"1081",
    "sg:province":"Bruxelles-Capitale",
    "wof:name":"American Supply Corporation S.p.r.l.",
    "wof:placetype":"venue"
},
  "geometry": {"coordinates":[4.3289170265,50.8588829041],"type":"Point"}
}