{
  "type": "Feature",
  "properties": {
    "iso:country":"BE",
    "sg:address":"Chauss\u00c9e De Chimay 26",
    "sg:city":"Beaumont",
    "sg:orig_category":"Benzinestations and brandstoffen Herstellingen and onderhoud van auto's Metaalafval, schrootrecyclag",
    "sg:phone":"+32 71 58 83 39",
    "sg:postcode":"6500",
    "sg:province":"Hainaut",
    "wof:name":"Garage Collinet",
    "wof:placetype":"venue"
},
  "geometry": {"coordinates":[4.2346258163,50.230342865],"type":"Point"}
}