{
  "type": "Feature",
  "properties": {
    "iso:country":"BE",
    "sg:address":"Oudestraat 19",
    "sg:city":"Kampenhout",
    "sg:orig_category":"Editeurs de revues and p\u00e9riodiques. Editeurs de journaux",
    "sg:phone":"+32 16 61 91 50",
    "sg:postcode":"1910",
    "sg:province":"Vlaams-Brabant",
    "wof:name":"De Streekkrant",
    "wof:placetype":"venue"
},
  "geometry": {"coordinates":[4.6008400917,50.9607696533],"type":"Point"}
}