{
  "type": "Feature",
  "properties": {
    "iso:country":"BE",
    "sg:address":"Bethani\u00ebnlei 193",
    "sg:city":"Zoersel",
    "sg:classifiers":[
        {
            "category":"Building & Trades",
            "subcategory":"Electrical",
            "type":"Services"
        }
    ],
    "sg:phone":"+32 3 383 42 93",
    "sg:postcode":"2980",
    "sg:province":"Antwerpen",
    "sg:tags":[
        "electric",
        "-",
        "housewiring",
        "contractor"
    ],
    "wof:name":"Mertes G",
    "wof:placetype":"venue"
},
  "geometry": {"coordinates":[4.628182888,51.276725769],"type":"Point"}
}