{
  "type": "Feature",
  "properties": {
    "iso:country":"BE",
    "sg:address":"Mechelsesteenweg 106",
    "sg:city":"Edegem",
    "sg:orig_category":"Kinderopvang",
    "sg:phone":"+32 3 454 51 36",
    "sg:postcode":"2650",
    "sg:province":"Antwerpen",
    "wof:name":"Kribbe Benito",
    "wof:placetype":"venue"
},
  "geometry": {"coordinates":[4.4633169174,51.1485137939],"type":"Point"}
}