{
  "type": "Feature",
  "properties": {
    "addr:full":"Onze-lieve-vrouwstraat 130 Heusden-zolder Limburg 3550",
    "addr:housenumber":"130",
    "addr:postcode":"3550",
    "addr:street":"Onze-Lieve-Vrouwstraat",
    "iso:country":"BE",
    "sg:address":"Onze-lieve-vrouwstraat 130",
    "sg:city":"Heusden-zolder",
    "sg:orig_category":"Kapsalons",
    "sg:phone":"+32 11 53 72 27",
    "sg:postcode":"3550",
    "sg:province":"Limburg",
    "wof:name":"Julia Peeters",
    "wof:placetype":"venue"
},
  "geometry": {"coordinates":[5.2752690315,51.0121574402],"type":"Point"}
}