{
  "type": "Feature",
  "properties": {
    "addr:full":"Sint-jorislaan 53 Herk-de-stad Limburg 3540",
    "addr:housenumber":"53",
    "addr:postcode":"3540",
    "addr:street":"Sint-Jorislaan",
    "iso:country":"BE",
    "sg:address":"Sint-jorislaan 53",
    "sg:city":"Herk-de-stad",
    "sg:classifiers":[
        {
            "category":"Arena",
            "subcategory":"Sports Club",
            "type":"Entertainment"
        }
    ],
    "sg:phone":"+32 13 55 44 84",
    "sg:postcode":"3540",
    "sg:province":"Limburg",
    "sg:tags":[
        "de"
    ],
    "wof:name":"Turnclub Herk De Stad",
    "wof:placetype":"venue"
},
  "geometry": {"coordinates":[5.1893458366,50.9604034424],"type":"Point"}
}