{
  "type": "Feature",
  "properties": {
    "addr:full":"Place Eug\u00c8ne Flagey 7b1 Elsene/ixelles Bruxelles-Capitale 1050",
    "addr:housenumber":"7b1",
    "addr:postcode":"1050",
    "addr:street":"Place Euge\u0300Ne Flagey",
    "iso:country":"BE",
    "sg:address":"Place Eug\u00c8ne Flagey 7b1",
    "sg:city":"Elsene/ixelles",
    "sg:classifiers":[
        {
            "category":"Building & Trades",
            "subcategory":"Plumbing",
            "type":"Services"
        }
    ],
    "sg:phone":"+32 2 640 05 00",
    "sg:postcode":"1050",
    "sg:province":"Bruxelles-Capitale",
    "sg:tags":[
        "diver",
        "commerce",
        "gr",
        "pour",
        "equipement"
    ],
    "wof:name":"Fiac Indola",
    "wof:placetype":"venue"
},
  "geometry": {"coordinates":[4.3718628883,50.8283843994],"type":"Point"}
}