{
  "type": "Feature",
  "properties": {
    "iso:country":"BE",
    "sg:address":"Rue Des Sarts 68",
    "sg:city":"Charleroi",
    "sg:classifiers":[
        {
            "category":"Insurance",
            "subcategory":"Life Insurance",
            "type":"Services"
        }
    ],
    "sg:phone":"+32 71 43 32 47",
    "sg:postcode":"6010",
    "sg:province":"Hainaut",
    "sg:tags":[
        "assurance"
    ],
    "wof:name":"Ph. Hanquet",
    "wof:placetype":"venue"
},
  "geometry": {"coordinates":[4.4722900391,50.3792037964],"type":"Point"}
}