{
  "type": "Feature",
  "properties": {
    "addr:full":"Heide 1 Puurs Antwerpen 2870",
    "addr:housenumber":"1",
    "addr:postcode":"2870",
    "addr:street":"Heide",
    "iso:country":"BE",
    "sg:address":"Heide 1",
    "sg:city":"Puurs",
    "sg:orig_category":"Dakwerken Loodgieterij, verwarming and sanitaire installaties",
    "sg:phone":"+32 3 889 03 94",
    "sg:postcode":"2870",
    "sg:province":"Antwerpen",
    "wof:name":"Moens Sanidak",
    "wof:placetype":"venue"
},
  "geometry": {"coordinates":[4.2754020691,51.0710220337],"type":"Point"}
}