{
  "type": "Feature",
  "properties": {
    "addr:full":"Dr\u00e8ve Richelle 161p Waterloo Brabant Wallon 1410",
    "addr:housenumber":"161p",
    "addr:postcode":"1410",
    "addr:street":"Dre\u0300Ve Richelle",
    "iso:country":"BE",
    "sg:address":"Dr\u00e8ve Richelle 161p",
    "sg:city":"Waterloo",
    "sg:classifiers":[
        {
            "category":"Banks & Credit Unions",
            "subcategory":"Financial Services",
            "type":"Services"
        }
    ],
    "sg:phone":"+32 2 357 14 10",
    "sg:postcode":"1410",
    "sg:province":"Brabant Wallon",
    "sg:tags":[
        "group"
    ],
    "wof:name":"Vanguard Investments Europe",
    "wof:placetype":"venue"
},
  "geometry": {"coordinates":[4.4104981422,50.7075843811],"type":"Point"}
}