{
  "type": "Feature",
  "properties": {
    "addr:full":"Kruisweg 8 Antwerpen Antwerpen 2040",
    "addr:housenumber":"8",
    "addr:postcode":"2040",
    "addr:street":"Kruisweg",
    "iso:country":"BE",
    "sg:address":"Kruisweg 8",
    "sg:city":"Antwerpen",
    "sg:orig_category":"Logistics For The Chemical Industry",
    "sg:phone":"+32 3 568 30 30",
    "sg:postcode":"2040",
    "sg:province":"Antwerpen",
    "wof:name":"De Rijke Nv",
    "wof:placetype":"venue"
},
  "geometry": {"coordinates":[4.3253707886,51.3140716553],"type":"Point"}
}