{
  "type": "Feature",
  "properties": {
    "addr:full":"Rue Louvi\u00e8re 61 Tournai (gaurain-ramecroix) Hainaut 7530",
    "addr:housenumber":"61",
    "addr:postcode":"7530",
    "addr:street":"Rue Louvie\u0300Re",
    "iso:country":"BE",
    "sg:address":"Rue Louvi\u00e8re 61",
    "sg:city":"Tournai (gaurain-ramecroix)",
    "sg:classifiers":[
        {
            "category":"Building & Trades",
            "subcategory":"Electrical",
            "type":"Services"
        }
    ],
    "sg:phone":"+32 69 54 82 44",
    "sg:postcode":"7530",
    "sg:province":"Hainaut",
    "sg:tags":[
        "electric",
        "-",
        "housewiring",
        "contractor"
    ],
    "wof:name":"I.d.c. Electro",
    "wof:placetype":"venue"
},
  "geometry": {"coordinates":[3.4959840775,50.5858192444],"type":"Point"}
}