{
  "type": "Feature",
  "properties": {
    "addr:full":"Place Cardinal Mercier 16 Box 11 Dinant Namur 5500",
    "addr:housenumber":"16 box 11",
    "addr:postcode":"5500",
    "addr:street":"Place Cardinal Mercier",
    "iso:country":"BE",
    "sg:address":"Place Cardinal Mercier 16 Box 11",
    "sg:city":"Dinant",
    "sg:classifiers":[
        {
            "category":"Professional",
            "subcategory":"Computer Services",
            "type":"Services"
        }
    ],
    "sg:phone":"+32 82 22 44 98",
    "sg:postcode":"5500",
    "sg:province":"Namur",
    "sg:tags":[
        "-",
        "processing",
        "data",
        "software"
    ],
    "wof:name":"Adam's Computer Dinant Sprl",
    "wof:placetype":"venue"
},
  "geometry": {"coordinates":[4.8964138031,50.2705154419],"type":"Point"}
}