{
  "type": "Feature",
  "properties": {
    "addr:full":"Dorpstraat 11 Wichelen Oost-Vlaanderen 9260",
    "addr:housenumber":"11",
    "addr:postcode":"9260",
    "addr:street":"Dorpstraat",
    "iso:country":"BE",
    "sg:address":"Dorpstraat 11",
    "sg:city":"Wichelen",
    "sg:orig_category":"Dakwerken",
    "sg:phone":"+32 9 369 34 45",
    "sg:postcode":"9260",
    "sg:province":"Oost-Vlaanderen",
    "wof:name":"Danny De Clercq",
    "wof:placetype":"venue"
},
  "geometry": {"coordinates":[3.9303998947,50.988368988],"type":"Point"}
}