{
  "type": "Feature",
  "properties": {
    "iso:country":"BE",
    "sg:address":"Rue D'angleur 62",
    "sg:city":"Saint-nicolas",
    "sg:orig_category":"Paramedische behandelingen Schoonheidssalons",
    "sg:phone":"+32 4 263 13 01",
    "sg:postcode":"4420",
    "sg:province":"Li\u00e8ge",
    "wof:name":"Sorgi",
    "wof:placetype":"venue"
},
  "geometry": {"coordinates":[5.5121130943,50.637638092],"type":"Point"}
}