{
  "type": "Feature",
  "properties": {
    "iso:country":"BE",
    "sg:address":"Sint-jansstraat 8bc",
    "sg:city":"Riemst",
    "sg:orig_category":"Sportcentra",
    "sg:phone":"+32 12 45 61 20",
    "sg:postcode":"3770",
    "sg:province":"Limburg",
    "wof:name":"Sporthal Hirtheren",
    "wof:placetype":"venue"
},
  "geometry": {"coordinates":[5.5734119415,50.8082237244],"type":"Point"}
}