{
  "type": "Feature",
  "properties": {
    "addr:full":"Zandstraat 57-61 Herentals Antwerpen 2200",
    "addr:postcode":"57-61;2200",
    "addr:street":"Zandstraat",
    "iso:country":"BE",
    "sg:address":"Zandstraat 57-61",
    "sg:city":"Herentals",
    "sg:classifiers":[
        {
            "category":"Shopping",
            "subcategory":"Clothing, Apparel, & Fashions",
            "type":"Retail Goods"
        }
    ],
    "sg:phone":"+32 14 21 36 95",
    "sg:postcode":"2200",
    "sg:province":"Antwerpen",
    "sg:tags":[
        "underwear",
        "lingerie",
        "-"
    ],
    "wof:name":"Demolder G Bvba",
    "wof:placetype":"venue"
},
  "geometry": {"coordinates":[4.8322520256,51.1770095825],"type":"Point"}
}