{
  "type": "Feature",
  "properties": {
    "addr:full":"Leopold Ii Laan 45 Koksijde West-Vlaanderen 8670",
    "addr:housenumber":"45",
    "addr:postcode":"8670",
    "addr:street":"Leopold Ii Laan",
    "iso:country":"BE",
    "sg:address":"Leopold Ii Laan 45",
    "sg:city":"Koksijde",
    "sg:orig_category":"Pain, p\u00e2tisseries and confiseries",
    "sg:phone":"+32 58 51 56 32",
    "sg:postcode":"8670",
    "sg:province":"West-Vlaanderen",
    "wof:name":"Bakkerij Koen",
    "wof:placetype":"venue"
},
  "geometry": {"coordinates":[2.6813011169,51.1171760559],"type":"Point"}
}