{
  "type": "Feature",
  "properties": {
    "addr:full":"Rue Pierre Deby 23 Vis\u00c9 Li\u00e8ge 4600",
    "addr:housenumber":"23",
    "addr:postcode":"4600",
    "addr:street":"Rue Pierre Deby",
    "iso:country":"BE",
    "sg:address":"Rue Pierre Deby 23",
    "sg:city":"Vis\u00c9",
    "sg:orig_category":"Boekhouders",
    "sg:phone":"+32 4 379 39 70",
    "sg:postcode":"4600",
    "sg:province":"Li\u00e8ge",
    "wof:name":"Annie Loverix",
    "wof:placetype":"venue"
},
  "geometry": {"coordinates":[5.7034068108,50.7138328552],"type":"Point"}
}