{
  "type": "Feature",
  "properties": {
    "addr:full":"Rue Leonard Lacroix 2 Geer Li\u00e8ge 4250",
    "addr:housenumber":"2",
    "addr:postcode":"4250",
    "addr:street":"Rue Leonard Lacroix",
    "iso:country":"BE",
    "sg:address":"Rue Leonard Lacroix 2",
    "sg:city":"Geer",
    "sg:orig_category":"Traitements param\u00e9dicaux",
    "sg:phone":"+32 19 32 60 70",
    "sg:postcode":"4250",
    "sg:province":"Li\u00e8ge",
    "wof:name":"Log. Vriamont Lindekens",
    "wof:placetype":"venue"
},
  "geometry": {"coordinates":[5.2110991478,50.6786499023],"type":"Point"}
}