{
  "type": "Feature",
  "properties": {
    "iso:country":"BE",
    "sg:address":"Chauss\u00c9e De Stockel 45",
    "sg:city":"Sint-lambrechts-woluwe/woluwe-saint-lambert",
    "sg:orig_category":"Salles de spectacles",
    "sg:phone":"+32 2 761 27 67",
    "sg:postcode":"1200",
    "sg:province":"Bruxelles-Capitale",
    "wof:name":"Galerie Pr\u00cat Oeuvres Art",
    "wof:placetype":"venue"
},
  "geometry": {"coordinates":[4.4388680458,50.8406791687],"type":"Point"}
}