{
  "type": "Feature",
  "properties": {
    "iso:country":"BE",
    "sg:address":"Boulevard Roi Albert Ii 1",
    "sg:city":"Sint-joost-ten-node/saint-josse-ten-noode",
    "sg:orig_category":"Cr\u00e9dit \u00e0 la consommation",
    "sg:phone":"+32 2 208 88 11",
    "sg:postcode":"1210",
    "sg:province":"Bruxelles-Capitale",
    "wof:name":"Si\u00c8ge Tradego",
    "wof:placetype":"venue"
},
  "geometry": {"coordinates":[4.3559098244,50.856426239],"type":"Point"}
}