{
  "type": "Feature",
  "properties": {
    "addr:full":"Koning Albert Ii-laan 1 Sint-joost-ten-node/saint-josse-ten-noode Bruxelles-Capitale 1210",
    "addr:housenumber":"1",
    "addr:postcode":"1210",
    "addr:street":"Koning Albert Ii-Laan",
    "iso:country":"BE",
    "sg:address":"Koning Albert Ii-laan 1",
    "sg:city":"Sint-joost-ten-node/saint-josse-ten-noode",
    "sg:orig_category":"Software ontwikkeling and ontwerp",
    "sg:phone":"+32 2 204 91 00",
    "sg:postcode":"1210",
    "sg:province":"Bruxelles-Capitale",
    "wof:name":"Sales + Europe Dentrite",
    "wof:placetype":"venue"
},
  "geometry": {"coordinates":[4.3559098244,50.856426239],"type":"Point"}
}