{
  "type": "Feature",
  "properties": {
    "addr:full":"Hoogstraat 4 Puurs Antwerpen 2870",
    "addr:housenumber":"4",
    "addr:postcode":"2870",
    "addr:street":"Hoogstraat",
    "iso:country":"BE",
    "sg:address":"Hoogstraat 4",
    "sg:city":"Puurs",
    "sg:orig_category":"Eclairage et \u00e9quipements du foyer",
    "sg:phone":"+32 3 889 37 66",
    "sg:postcode":"2870",
    "sg:province":"Antwerpen",
    "wof:name":"Huis Bokado",
    "wof:placetype":"venue"
},
  "geometry": {"coordinates":[4.2781300545,51.0762290955],"type":"Point"}
}