{
  "type": "Feature",
  "properties": {
    "addr:full":"Chauss\u00e9e De Lodelinsart 11 Charleroi (gilly) Hainaut 6060",
    "addr:housenumber":"11",
    "addr:postcode":"6060",
    "addr:street":"Chausse\u0301E De Lodelinsart",
    "iso:country":"BE",
    "sg:address":"Chauss\u00e9e De Lodelinsart 11",
    "sg:city":"Charleroi (gilly)",
    "sg:classifiers":[
        {
            "category":"Retail",
            "subcategory":"Laundry & Dry Cleaning",
            "type":"Services"
        }
    ],
    "sg:phone":"+32 71 41 53 44",
    "sg:postcode":"6060",
    "sg:province":"Hainaut",
    "sg:tags":[
        "knitwear",
        "-"
    ],
    "wof:name":"Delire",
    "wof:placetype":"venue"
},
  "geometry": {"coordinates":[4.4493408203,50.4186515808],"type":"Point"}
}