{
  "type": "Feature",
  "properties": {
    "addr:full":"Molenstraat 54 Wetteren Oost-Vlaanderen 9230",
    "addr:housenumber":"54",
    "addr:postcode":"9230",
    "addr:street":"Molenstraat",
    "iso:country":"BE",
    "sg:address":"Molenstraat 54",
    "sg:city":"Wetteren",
    "sg:orig_category":"Herstellingen and onderhoud van auto's Voertuigen",
    "sg:phone":"+32 9 369 54 05",
    "sg:postcode":"9230",
    "sg:province":"Oost-Vlaanderen",
    "wof:name":"De Bruycker Willy",
    "wof:placetype":"venue"
},
  "geometry": {"coordinates":[3.8882679939,51.0044746399],"type":"Point"}
}