{
  "type": "Feature",
  "properties": {
    "addr:full":"Kapelstraat 43 Baarle-hertog Antwerpen 2387",
    "addr:housenumber":"43",
    "addr:postcode":"2387",
    "addr:street":"Kapelstraat",
    "iso:country":"BE",
    "sg:address":"Kapelstraat 43",
    "sg:city":"Baarle-hertog",
    "sg:orig_category":"Eleveurs de bovins",
    "sg:phone":"+32 14 69 91 87",
    "sg:postcode":"2387",
    "sg:province":"Antwerpen",
    "wof:name":"Aloisius Jansens",
    "wof:placetype":"venue"
},
  "geometry": {"coordinates":[4.9338598251,51.442199707],"type":"Point"}
}