{
  "type": "Feature",
  "properties": {
    "iso:country":"BE",
    "sg:address":"Lange Bergstraat 27",
    "sg:city":"Wetteren",
    "sg:classifiers":[
        {
            "category":"Retail",
            "subcategory":"Driving School",
            "type":"Services"
        }
    ],
    "sg:phone":"+32 9 366 29 26",
    "sg:postcode":"9230",
    "sg:province":"Oost-Vlaanderen",
    "sg:tags":[
        "automobile",
        "officially",
        "-",
        "recognized"
    ],
    "wof:name":"Autorijschool Baetens Bvba/ Baetens Nele Nv",
    "wof:placetype":"venue"
},
  "geometry": {"coordinates":[3.8828189373,51.0053100586],"type":"Point"}
}