{
  "type": "Feature",
  "properties": {
    "iso:country":"BE",
    "sg:address":"Holstraat 19",
    "sg:city":"Waregem",
    "sg:classifiers":[
        {
            "category":"Personal",
            "subcategory":"Beauty Salon",
            "type":"Services"
        }
    ],
    "sg:phone":"+32 56 61 34 51",
    "sg:postcode":"8790",
    "sg:province":"West-Vlaanderen",
    "wof:name":"Manicure (la)",
    "wof:placetype":"venue"
},
  "geometry": {"coordinates":[3.4343049526,50.8858642578],"type":"Point"}
}