{
  "type": "Feature",
  "properties": {
    "iso:country":"BE",
    "sg:address":"Balen Neetlaan 11",
    "sg:city":"Balen",
    "sg:orig_category":"Jardinage",
    "sg:phone":"+32 14 81 07 25",
    "sg:postcode":"2490",
    "sg:province":"Antwerpen",
    "wof:name":"Luyten",
    "wof:placetype":"venue"
},
  "geometry": {"coordinates":[5.2271881104,51.1940307617],"type":"Point"}
}