{
  "type": "Feature",
  "properties": {
    "iso:country":"BE",
    "sg:address":"Dahlialaan 21",
    "sg:city":"Koksijde (oostduinkerke)",
    "sg:classifiers":[
        {
            "category":"Professional",
            "subcategory":"Accounting & Tax Preparation",
            "type":"Services"
        }
    ],
    "sg:phone":"+32 58 51 04 57",
    "sg:postcode":"8670",
    "sg:province":"West-Vlaanderen",
    "sg:tags":[
        "bookkeeper"
    ],
    "wof:name":"Price & Quality Consulting Nv",
    "wof:placetype":"venue"
},
  "geometry": {"coordinates":[2.6803660393,51.1279220581],"type":"Point"}
}