{
  "type": "Feature",
  "properties": {
    "addr:full":"Frezenbergstraat 62 Zonnebeke West-Vlaanderen 8980",
    "addr:housenumber":"62",
    "addr:postcode":"8980",
    "addr:street":"Frezenbergstraat",
    "iso:country":"BE",
    "sg:address":"Frezenbergstraat 62",
    "sg:city":"Zonnebeke",
    "sg:classifiers":[
        {
            "category":"Utilities",
            "subcategory":"Fuel Oil & Lpg",
            "type":"Services"
        }
    ],
    "sg:phone":"+32 51 77 83 57",
    "sg:postcode":"8980",
    "sg:province":"West-Vlaanderen",
    "wof:name":"Decroix Brandstoffen & Vervoer Bvba",
    "wof:placetype":"venue"
},
  "geometry": {"coordinates":[2.9602630138,50.8551979065],"type":"Point"}
}