{
  "type": "Feature",
  "properties": {
    "iso:country":"BE",
    "sg:address":"Van Trierstraat 10",
    "sg:city":"Antwerpen",
    "sg:classifiers":[
        {
            "category":"Real Estate",
            "subcategory":"Architect",
            "type":"Services"
        }
    ],
    "sg:phone":"+32 486 11 07 14",
    "sg:postcode":"2018",
    "sg:province":"Antwerpen",
    "wof:name":"Boonen K",
    "wof:placetype":"venue"
},
  "geometry": {"coordinates":[4.4016699791,51.2010345459],"type":"Point"}
}