{
  "type": "Feature",
  "properties": {
    "addr:full":"Kard. Mercierstraat 32 Knokke-heist West-Vlaanderen 8300",
    "addr:housenumber":"32",
    "addr:postcode":"8300",
    "addr:street":"Kard. Mercierstraat",
    "iso:country":"BE",
    "sg:address":"Kard. Mercierstraat 32",
    "sg:city":"Knokke-heist",
    "sg:orig_category":"Baby- and kinderkleding Babyspullen",
    "sg:phone":"+32 50 51 71 26",
    "sg:postcode":"8300",
    "sg:province":"West-Vlaanderen",
    "wof:name":"Nathanic",
    "wof:placetype":"venue"
},
  "geometry": {"coordinates":[3.287694931,51.3467254639],"type":"Point"}
}