{
  "type": "Feature",
  "properties": {
    "addr:full":"Deidenberg 149 Amel Li\u00e8ge 4770",
    "addr:housenumber":"149",
    "addr:postcode":"4770",
    "addr:street":"Deidenberg",
    "iso:country":"BE",
    "sg:address":"Deidenberg 149",
    "sg:city":"Amel",
    "sg:classifiers":[
        {
            "category":"Manufacturing",
            "subcategory":"Metals",
            "type":"Manufacturing & Wholesale Goods"
        }
    ],
    "sg:phone":"+32 80 34 93 01",
    "sg:postcode":"4770",
    "sg:province":"Li\u00e8ge",
    "sg:tags":[
        "metallurgy",
        "metalworking",
        "processing"
    ],
    "wof:name":"M Gerhard Mertes Bv",
    "wof:placetype":"venue"
},
  "geometry": {"coordinates":[6.1512641907,50.3556022644],"type":"Point"}
}