{
  "type": "Feature",
  "properties": {
    "iso:country":"BE",
    "sg:address":"Roeselveld 10",
    "sg:city":"Herent",
    "sg:classifiers":[
        {
            "category":"Banks & Credit Unions",
            "subcategory":"Investment Brokerage",
            "type":"Services"
        }
    ],
    "sg:phone":"+32 16 23 99 02",
    "sg:postcode":"3020",
    "sg:province":"Vlaams-Brabant",
    "sg:tags":[
        "repair",
        "-",
        "installation",
        "sanitary",
        "article"
    ],
    "wof:name":"De Waele W",
    "wof:placetype":"venue"
},
  "geometry": {"coordinates":[4.6842980385,50.8990325928],"type":"Point"}
}