{
  "type": "Feature",
  "properties": {
    "addr:full":"Moerdijkstraat 94 Ichtegem West-Vlaanderen 8480",
    "addr:housenumber":"94",
    "addr:postcode":"8480",
    "addr:street":"Moerdijkstraat",
    "iso:country":"BE",
    "sg:address":"Moerdijkstraat 94",
    "sg:city":"Ichtegem",
    "sg:classifiers":[
        {
            "category":"Retail",
            "subcategory":"Event Space",
            "type":"Services"
        }
    ],
    "sg:phone":"+32 51 58 92 68",
    "sg:postcode":"8480",
    "sg:province":"West-Vlaanderen",
    "sg:tags":[
        "rental",
        "-",
        "hall"
    ],
    "wof:name":"Salons De Vrede",
    "wof:placetype":"venue"
},
  "geometry": {"coordinates":[3.01197505,51.1029052734],"type":"Point"}
}