{
  "type": "Feature",
  "properties": {
    "iso:country":"BE",
    "sg:address":"Bergstraat 75",
    "sg:city":"Heist-op-den-berg",
    "sg:orig_category":"Equipement photographique. Studios photographiques",
    "sg:phone":"+32 15 24 15 21",
    "sg:postcode":"2220",
    "sg:province":"Antwerpen",
    "wof:name":"Gaston Van Den Broeck",
    "wof:placetype":"venue"
},
  "geometry": {"coordinates":[4.7218618393,51.0760345459],"type":"Point"}
}