{
  "type": "Feature",
  "properties": {
    "iso:country":"BE",
    "sg:address":"17",
    "sg:city":"Verbrandendijk 2070 Zwijndrecht Burcht",
    "sg:classifiers":[
        {
            "category":"Manufacturing",
            "subcategory":"Chemicals & Compounds",
            "type":"Manufacturing & Wholesale Goods"
        }
    ],
    "sg:phone":"+32 3 252 72 74",
    "sg:postcode":"17",
    "sg:tags":[
        "pharmaceutical",
        "chemistry",
        "-",
        "by-product"
    ],
    "wof:name":"Zelfwasserij De Zonnebloem Bvba",
    "wof:placetype":"venue"
},
  "geometry": {"coordinates":[4.3396000862,51.219619751],"type":"Point"}
}