{
  "type": "Feature",
  "properties": {
    "addr:full":"Avenue De L'arbre Ballon 3 Brussel/bruxelles Bruxelles-Capitale 1020",
    "addr:housenumber":"3",
    "addr:postcode":"1020",
    "addr:street":"Avenue De L'Arbre Ballon;/",
    "iso:country":"BE",
    "sg:address":"Avenue De L'arbre Ballon 3",
    "sg:city":"Brussel/bruxelles",
    "sg:orig_category":"Banques and organismes de cr\u00e9dit",
    "sg:phone":"+32 2 478 03 76",
    "sg:postcode":"1020",
    "sg:province":"Bruxelles-Capitale",
    "wof:name":"Bbl",
    "wof:placetype":"venue"
},
  "geometry": {"coordinates":[4.3267521858,50.8938293457],"type":"Point"}
}