{
  "type": "Feature",
  "properties": {
    "iso:country":"BE",
    "sg:address":"Rue De L' Espinette 297",
    "sg:city":"Quaregnon",
    "sg:orig_category":"Gespecialiseerde residenti\u00eble bouw Woningbouw",
    "sg:phone":"+32 65 67 51 25",
    "sg:postcode":"7390",
    "sg:province":"Hainaut",
    "wof:name":"Melchiorre Entrepreneur",
    "wof:placetype":"venue"
},
  "geometry": {"coordinates":[3.8527629375,50.4301452637],"type":"Point"}
}