{
  "type": "Feature",
  "properties": {
    "addr:full":"Kroonwinningstraat 101 Hasselt Limburg 3500",
    "addr:housenumber":"101",
    "addr:postcode":"3500",
    "addr:street":"Kroonwinningstraat",
    "iso:country":"BE",
    "sg:address":"Kroonwinningstraat 101",
    "sg:city":"Hasselt",
    "sg:orig_category":"Woningbouw",
    "sg:phone":"+32 11 27 47 60",
    "sg:postcode":"3500",
    "sg:province":"Limburg",
    "wof:name":"Valere Cosemans",
    "wof:placetype":"venue"
},
  "geometry": {"coordinates":[5.3566021919,50.9176635742],"type":"Point"}
}