{
  "type": "Feature",
  "properties": {
    "iso:country":"BE",
    "sg:address":"Zuidlaan 153",
    "sg:city":"Wetteren",
    "sg:orig_category":"Installation de menuiserie m\u00e9tallique",
    "sg:phone":"+32 9 365 30 30",
    "sg:postcode":"9230",
    "sg:province":"Oost-Vlaanderen",
    "wof:name":"Fa. De Witte",
    "wof:placetype":"venue"
},
  "geometry": {"coordinates":[3.8763709068,50.9978866577],"type":"Point"}
}