{
  "type": "Feature",
  "properties": {
    "addr:full":"Rue Auguste Hainaut 20 Bruxelles (jette) Bruxelles-Capitale 1090",
    "addr:housenumber":"20",
    "addr:postcode":"1090",
    "addr:street":"Rue Auguste Hainaut",
    "iso:country":"BE",
    "sg:address":"Rue Auguste Hainaut 20",
    "sg:city":"Bruxelles (jette)",
    "sg:classifiers":[
        {
            "category":"Bars & Pubs",
            "type":"Food & Drink"
        }
    ],
    "sg:phone":"+32 2 427 05 50",
    "sg:postcode":"1090",
    "sg:province":"Bruxelles-Capitale",
    "sg:tags":[
        "tavern"
    ],
    "wof:name":"Werrie",
    "wof:placetype":"venue"
},
  "geometry": {"coordinates":[4.3355779648,50.8684463501],"type":"Point"}
}