{
  "type": "Feature",
  "properties": {
    "iso:country":"BE",
    "sg:address":"Rue Des Li\u00c9geois 37",
    "sg:city":"Elsene/ixelles",
    "sg:orig_category":"Artistes ind\u00e9pendants",
    "sg:phone":"+32 2 647 51 74",
    "sg:postcode":"1050",
    "sg:province":"Bruxelles-Capitale",
    "wof:name":"Micheline Dieu",
    "wof:placetype":"venue"
},
  "geometry": {"coordinates":[4.3779191971,50.8288078308],"type":"Point"}
}