{
  "type": "Feature",
  "properties": {
    "iso:country":"BE",
    "sg:address":"Koningin Astridlaan 29",
    "sg:city":"Hasselt",
    "sg:orig_category":"Rev\u00eatements de sols and murs. Eclairage et \u00e9quipements du foyer",
    "sg:phone":"+32 11 23 61 42",
    "sg:postcode":"3500",
    "sg:province":"Limburg",
    "wof:name":"Konya",
    "wof:placetype":"venue"
},
  "geometry": {"coordinates":[5.3316578865,50.9313240051],"type":"Point"}
}