{
  "type": "Feature",
  "properties": {
    "addr:full":"Martijn Van Torhoutstraat 15 Oudenaarde Oost-Vlaanderen 9700",
    "addr:housenumber":"15",
    "addr:postcode":"9700",
    "addr:street":"Martijn Van Torhoutstraat",
    "iso:country":"BE",
    "sg:address":"Martijn Van Torhoutstraat 15",
    "sg:city":"Oudenaarde",
    "sg:classifiers":[
        {
            "category":"Professional",
            "subcategory":"Engineering",
            "type":"Services"
        }
    ],
    "sg:phone":"+32 55 31 35 61",
    "sg:postcode":"9700",
    "sg:province":"Oost-Vlaanderen",
    "sg:tags":[
        "precision"
    ],
    "wof:name":"Pedeo Techniek Nv",
    "wof:placetype":"venue"
},
  "geometry": {"coordinates":[3.629709959,50.855140686],"type":"Point"}
}