{
  "type": "Feature",
  "properties": {
    "iso:country":"BE",
    "sg:address":"Boulevard De La Dodaine 15",
    "sg:city":"Nivelles",
    "sg:orig_category":"Artsen and specialisten",
    "sg:phone":"+32 67 21 40 93",
    "sg:postcode":"1400",
    "sg:province":"Brabant Wallon",
    "wof:name":"Marie-christine Nisolle",
    "wof:placetype":"venue"
},
  "geometry": {"coordinates":[4.3262910843,50.5945777893],"type":"Point"}
}