{
  "type": "Feature",
  "properties": {
    "addr:full":"Kerkstraat 11 Pittem West-Vlaanderen 8740",
    "addr:housenumber":"11",
    "addr:postcode":"8740",
    "addr:street":"Kerkstraat",
    "iso:country":"BE",
    "sg:address":"Kerkstraat 11",
    "sg:city":"Pittem",
    "sg:classifiers":[
        {
            "category":"Personal",
            "subcategory":"Beauty Salon",
            "type":"Services"
        }
    ],
    "sg:phone":"+32 51 46 66 73",
    "sg:postcode":"8740",
    "sg:province":"West-Vlaanderen",
    "sg:tags":[
        "lady",
        "-",
        "hairdressing"
    ],
    "wof:name":"Rose",
    "wof:placetype":"venue"
},
  "geometry": {"coordinates":[3.2663719654,50.9935455322],"type":"Point"}
}