{
  "type": "Feature",
  "properties": {
    "addr:full":"Meigemheidestraat 14 Beersel (alsemberg) Vlaams-Brabant 1652",
    "addr:housenumber":"14",
    "addr:postcode":"1652",
    "addr:street":"Meigemheidestraat",
    "iso:country":"BE",
    "sg:address":"Meigemheidestraat 14",
    "sg:city":"Beersel (alsemberg)",
    "sg:classifiers":[
        {
            "category":"Professional",
            "subcategory":"Engineering",
            "type":"Services"
        }
    ],
    "sg:phone":"+32 2 381 19 17",
    "sg:postcode":"1652",
    "sg:province":"Vlaams-Brabant",
    "sg:tags":[
        "-"
    ],
    "wof:name":"C.l.s. Engineering Bvba",
    "wof:placetype":"venue"
},
  "geometry": {"coordinates":[4.3098258972,50.7557296753],"type":"Point"}
}