{
  "type": "Feature",
  "properties": {
    "addr:full":"Oude Bruggestraat 2 Wingene West-Vlaanderen 8750",
    "addr:housenumber":"2",
    "addr:postcode":"8750",
    "addr:street":"Oude Bruggestraat",
    "iso:country":"BE",
    "sg:address":"Oude Bruggestraat 2",
    "sg:city":"Wingene",
    "sg:orig_category":"Epiceries",
    "sg:phone":"+32 51 65 65 44",
    "sg:postcode":"8750",
    "sg:province":"West-Vlaanderen",
    "wof:name":"Walter Vandendriessche",
    "wof:placetype":"venue"
},
  "geometry": {"coordinates":[3.2781660557,51.0577774048],"type":"Point"}
}