{
  "type": "Feature",
  "properties": {
    "addr:full":"Rue Joseph Lef\u00e8vre 41 Charleroi (marchienne-au-pont) Hainaut 6030",
    "addr:housenumber":"41",
    "addr:postcode":"6030",
    "addr:street":"Rue Joseph Lefe\u0300Vre",
    "iso:country":"BE",
    "sg:address":"Rue Joseph Lef\u00e8vre 41",
    "sg:city":"Charleroi (marchienne-au-pont)",
    "sg:classifiers":[
        {
            "category":"Home & Garden",
            "subcategory":"Home Furnishings",
            "type":"Retail Goods"
        }
    ],
    "sg:phone":"+32 71 51 75 64",
    "sg:postcode":"6030",
    "sg:province":"Hainaut",
    "sg:tags":[
        "interior",
        "decoration"
    ],
    "wof:name":"Viano C",
    "wof:placetype":"venue"
},
  "geometry": {"coordinates":[4.3932070732,50.4036712646],"type":"Point"}
}