{
  "type": "Feature",
  "properties": {
    "iso:country":"BE",
    "sg:address":"Nives 34",
    "sg:city":"Vaux-sur-sure",
    "sg:orig_category":"Brood, gebak and snoepgoed",
    "sg:phone":"+32 61 26 61 40",
    "sg:postcode":"6640",
    "sg:province":"Luxembourg",
    "wof:name":"Lexcellent Thierry",
    "wof:placetype":"venue"
},
  "geometry": {"coordinates":[5.5671000481,49.91065979],"type":"Point"}
}