{
  "type": "Feature",
  "properties": {
    "addr:full":"Rue Reine Astrid 12 Genappe (glabais) Brabant Wallon 1473",
    "addr:housenumber":"12",
    "addr:postcode":"1473",
    "addr:street":"Rue Reine Astrid;Wallon",
    "iso:country":"BE",
    "sg:address":"Rue Reine Astrid 12",
    "sg:city":"Genappe (glabais)",
    "sg:classifiers":[
        {
            "category":"Shopping",
            "subcategory":"Antiques",
            "type":"Retail Goods"
        }
    ],
    "sg:phone":"+32 67 78 07 56",
    "sg:postcode":"1473",
    "sg:province":"Brabant Wallon",
    "sg:tags":[
        "restoration"
    ],
    "wof:name":"Gallet M",
    "wof:placetype":"venue"
},
  "geometry": {"coordinates":[4.4541349411,50.6297836304],"type":"Point"}
}