{
  "type": "Feature",
  "properties": {
    "addr:full":"Heirweg Noord 31 Ingelmunster West-Vlaanderen 8770",
    "addr:housenumber":"31",
    "addr:postcode":"8770",
    "addr:street":"Heirweg Noord",
    "iso:country":"BE",
    "sg:address":"Heirweg Noord 31",
    "sg:city":"Ingelmunster",
    "sg:orig_category":"Eleveurs and marchands de porcs. Producteurs de l\u00e9gumes",
    "sg:phone":"+32 51 30 07 11",
    "sg:postcode":"8770",
    "sg:province":"West-Vlaanderen",
    "wof:name":"Roland D'hoore",
    "wof:placetype":"venue"
},
  "geometry": {"coordinates":[3.2506129742,50.9405784607],"type":"Point"}
}