{
  "type": "Feature",
  "properties": {
    "iso:country":"BE",
    "sg:address":"Chauss\u00c9e Braine-le-comte 70",
    "sg:city":"Nivelles",
    "sg:orig_category":"Immobili\u00ebnkantoren",
    "sg:phone":"+32 67 84 45 63",
    "sg:postcode":"1400",
    "sg:province":"Brabant Wallon",
    "wof:name":"Bureau Detr\u00c9",
    "wof:placetype":"venue"
},
  "geometry": {"coordinates":[4.3051199913,50.5983505249],"type":"Point"}
}