{
  "type": "Feature",
  "properties": {
    "iso:country":"BE",
    "sg:address":"Hasselbroekstraat 181",
    "sg:city":"Gingelom",
    "sg:orig_category":"Fruitteelt",
    "sg:phone":"+32 11 48 57 24",
    "sg:postcode":"3890",
    "sg:province":"Limburg",
    "wof:name":"Sylvie Pieraerts",
    "wof:placetype":"venue"
},
  "geometry": {"coordinates":[5.2110691071,50.7242698669],"type":"Point"}
}