{
  "type": "Feature",
  "properties": {
    "addr:full":"Damstraat 32 Sint-niklaas Oost-Vlaanderen 9100",
    "addr:housenumber":"32",
    "addr:postcode":"9100",
    "addr:street":"Damstraat",
    "iso:country":"BE",
    "sg:address":"Damstraat 32",
    "sg:city":"Sint-niklaas",
    "sg:orig_category":"Tabac",
    "sg:phone":"+32 3 776 81 88",
    "sg:postcode":"9100",
    "sg:province":"Oost-Vlaanderen",
    "wof:name":"Eric Van Raemdonck",
    "wof:placetype":"venue"
},
  "geometry": {"coordinates":[4.1741838455,51.1569824219],"type":"Point"}
}