{
  "type": "Feature",
  "properties": {
    "addr:full":"Engelhoekstraat 1 Deinze Oost-Vlaanderen 9800",
    "addr:housenumber":"1",
    "addr:postcode":"9800",
    "addr:street":"Engelhoekstraat",
    "iso:country":"BE",
    "sg:address":"Engelhoekstraat 1",
    "sg:city":"Deinze",
    "sg:classifiers":[
        {
            "category":"Wholesale",
            "subcategory":"Machinery & Supplies",
            "type":"Manufacturing & Wholesale Goods"
        }
    ],
    "sg:phone":"+32 9 282 48 77",
    "sg:postcode":"9800",
    "sg:province":"Oost-Vlaanderen",
    "sg:tags":[
        "agricultural",
        "equipment"
    ],
    "wof:name":"Morti Nv",
    "wof:placetype":"venue"
},
  "geometry": {"coordinates":[3.5866689682,51.0171203613],"type":"Point"}
}