{
  "type": "Feature",
  "properties": {
    "iso:country":"BE",
    "sg:address":"Rue Hubert Krains 2",
    "sg:city":"Waremme",
    "sg:classifiers":[
        {
            "category":"Food & Beverages",
            "subcategory":"Fruits & Vegetables",
            "type":"Retail Goods"
        }
    ],
    "sg:phone":"+32 19 32 75 80",
    "sg:postcode":"4300",
    "sg:province":"Li\u00e8ge",
    "sg:tags":[
        "l\u00e9gumes"
    ],
    "wof:name":"Marc Delvaux",
    "wof:placetype":"venue"
},
  "geometry": {"coordinates":[5.2451291084,50.6944618225],"type":"Point"}
}