{
  "type": "Feature",
  "properties": {
    "iso:country":"BE",
    "sg:address":"Rue Haute 197",
    "sg:city":"Hastiere",
    "sg:orig_category":"Charpentes and couvertures",
    "sg:phone":"+32 82 64 58 31",
    "sg:postcode":"5543",
    "sg:province":"Namur",
    "wof:name":"Claude Bourgeois",
    "wof:placetype":"venue"
},
  "geometry": {"coordinates":[4.834031105,50.164150238],"type":"Point"}
}