{
  "type": "Feature",
  "properties": {
    "iso:country":"BE",
    "sg:address":"Rue Des Fabriques 6 G",
    "sg:city":"Le Roeulx",
    "sg:orig_category":"Metaalafval, schrootrecyclage and sloperijen Voertuigen",
    "sg:phone":"+32 65 87 35 48",
    "sg:postcode":"7070",
    "sg:province":"Hainaut",
    "wof:name":"Technics-motors",
    "wof:placetype":"venue"
},
  "geometry": {"coordinates":[4.1086750031,50.5015830994],"type":"Point"}
}