{
  "type": "Feature",
  "properties": {
    "addr:full":"Place Du Ch\u00e2teau 18 Le Roeulx Hainaut 7070",
    "addr:housenumber":"18",
    "addr:postcode":"7070",
    "addr:street":"Place Du Cha\u0302Teau",
    "iso:country":"BE",
    "sg:address":"Place Du Ch\u00e2teau 18",
    "sg:city":"Le Roeulx",
    "sg:classifiers":[
        {
            "category":"Shopping",
            "subcategory":"Books",
            "type":"Retail Goods"
        }
    ],
    "sg:phone":"+32 64 67 51 29",
    "sg:postcode":"7070",
    "sg:province":"Hainaut",
    "sg:tags":[
        "bookseller"
    ],
    "wof:name":"Ch\u00e2teau (librairie Du)",
    "wof:placetype":"venue"
},
  "geometry": {"coordinates":[4.1102199554,50.5043182373],"type":"Point"}
}