{
  "type": "Feature",
  "properties": {
    "iso:country":"BE",
    "sg:address":"Knaptandstraat 54",
    "sg:city":"Sint-niklaas",
    "sg:orig_category":"Biens d'occasion",
    "sg:phone":"+32 3 766 42 55",
    "sg:postcode":"9100",
    "sg:province":"Oost-Vlaanderen",
    "wof:name":"Huis 't Ruitje",
    "wof:placetype":"venue"
},
  "geometry": {"coordinates":[4.1438941956,51.1595993042],"type":"Point"}
}