{
  "type": "Feature",
  "properties": {
    "iso:country":"BE",
    "sg:address":"Boulevard De La Constitution 19b2",
    "sg:city":"Liege",
    "sg:classifiers":[
        {
            "category":"Organizations",
            "subcategory":"Community Association",
            "type":"Services"
        }
    ],
    "sg:phone":"+32 4 349 51 11",
    "sg:postcode":"4020",
    "sg:province":"Li\u00e8ge",
    "sg:tags":[
        "organisation"
    ],
    "wof:name":"Service Provincial D'info Sur L'environnement",
    "wof:placetype":"venue"
},
  "geometry": {"coordinates":[5.5835580826,50.6432685852],"type":"Point"}
}