{
  "type": "Feature",
  "properties": {
    "addr:full":"Fraeysstraat 8 Torhout West-Vlaanderen 8820",
    "addr:housenumber":"8",
    "addr:postcode":"8820",
    "addr:street":"Fraeysstraat",
    "iso:country":"BE",
    "sg:address":"Fraeysstraat 8",
    "sg:city":"Torhout",
    "sg:classifiers":[
        {
            "category":"Arena",
            "subcategory":"Sports Club",
            "type":"Entertainment"
        }
    ],
    "sg:phone":"+32 475 61 48 29",
    "sg:postcode":"8820",
    "sg:province":"West-Vlaanderen",
    "sg:tags":[
        "terrain",
        "hors",
        "de",
        "installation",
        "sportifs"
    ],
    "wof:name":"F.c. N.h. Logistics",
    "wof:placetype":"venue"
},
  "geometry": {"coordinates":[3.099725008,51.0660896301],"type":"Point"}
}