{
  "type": "Feature",
  "properties": {
    "addr:full":"Westergemstraat 255 Gent (wondelgem) Oost-Vlaanderen 9032",
    "addr:housenumber":"255",
    "addr:postcode":"9032",
    "addr:street":"Westergemstraat",
    "iso:country":"BE",
    "sg:address":"Westergemstraat 255",
    "sg:city":"Gent (wondelgem)",
    "sg:classifiers":[
        {
            "category":"Social Services",
            "type":"Services"
        }
    ],
    "sg:phone":"+32 9 258 14 60",
    "sg:postcode":"9032",
    "sg:province":"Oost-Vlaanderen",
    "wof:name":"Claeys M",
    "wof:placetype":"venue"
},
  "geometry": {"coordinates":[3.7162549496,51.0900535583],"type":"Point"}
}