{
  "type": "Feature",
  "properties": {
    "addr:full":"Vaartstraat 209 Brecht Antwerpen 2960",
    "addr:housenumber":"209",
    "addr:postcode":"2960",
    "addr:street":"Vaartstraat",
    "iso:country":"BE",
    "sg:address":"Vaartstraat 209",
    "sg:city":"Brecht",
    "sg:classifiers":[
        {
            "category":"Professional",
            "subcategory":"Computer Services",
            "type":"Services"
        }
    ],
    "sg:phone":"+32 3 330 10 10",
    "sg:postcode":"2960",
    "sg:province":"Antwerpen",
    "sg:tags":[
        "-",
        "processing",
        "data"
    ],
    "wof:name":"Gps Trading Nv",
    "wof:placetype":"venue"
},
  "geometry": {"coordinates":[4.6542901993,51.3424301147],"type":"Point"}
}