{
  "type": "Feature",
  "properties": {
    "addr:full":"Kerkedries 4 Heusden-zolder Limburg 3550",
    "addr:housenumber":"4",
    "addr:postcode":"3550",
    "addr:street":"Kerkedries",
    "iso:country":"BE",
    "sg:address":"Kerkedries 4",
    "sg:city":"Heusden-zolder",
    "sg:classifiers":[
        {
            "category":"Cafe",
            "type":"Food & Drink"
        }
    ],
    "sg:phone":"+32 11 42 46 26",
    "sg:postcode":"3550",
    "sg:province":"Limburg",
    "sg:tags":[
        "caf\u00e9s"
    ],
    "wof:name":"Ines Romero-ordiales",
    "wof:placetype":"venue"
},
  "geometry": {"coordinates":[5.2505331039,50.9973373413],"type":"Point"}
}