{
  "type": "Feature",
  "properties": {
    "addr:full":"Snyersput 8 De Pinte Oost-Vlaanderen 9840",
    "addr:housenumber":"8",
    "addr:postcode":"9840",
    "addr:street":"Snyersput",
    "iso:country":"BE",
    "sg:address":"Snyersput 8",
    "sg:city":"De Pinte",
    "sg:classifiers":[
        {
            "category":"Real Estate",
            "subcategory":"Architect",
            "type":"Services"
        }
    ],
    "sg:phone":"+32 9 385 45 78",
    "sg:postcode":"9840",
    "sg:province":"Oost-Vlaanderen",
    "wof:name":"Kint P",
    "wof:placetype":"venue"
},
  "geometry": {"coordinates":[3.6471550465,50.9745063782],"type":"Point"}
}