{
  "type": "Feature",
  "properties": {
    "iso:country":"BE",
    "sg:address":"Rue Des P\u00e9pini\u00e8res 9",
    "sg:city":"L\u00e9glise (ebly)",
    "sg:classifiers":[
        {
            "category":"Retail",
            "subcategory":"Veterinary Services",
            "type":"Services"
        }
    ],
    "sg:phone":"+32 61 25 53 31",
    "sg:postcode":"6860",
    "sg:province":"Luxembourg",
    "sg:tags":[
        "veterinarian"
    ],
    "wof:name":"Bordet C",
    "wof:placetype":"venue"
},
  "geometry": {"coordinates":[5.5432949066,49.84790802],"type":"Point"}
}