{
  "type": "Feature",
  "properties": {
    "addr:full":"Grote Baan 84 Houthalen-helchteren Limburg 3530",
    "addr:housenumber":"84",
    "addr:postcode":"3530",
    "addr:street":"Grote Baan",
    "iso:country":"BE",
    "sg:address":"Grote Baan 84",
    "sg:city":"Houthalen-helchteren",
    "sg:orig_category":"Rev\u00eatements de sols and murs",
    "sg:phone":"+32 11 52 51 53",
    "sg:postcode":"3530",
    "sg:province":"Limburg",
    "wof:name":"Put R",
    "wof:placetype":"venue"
},
  "geometry": {"coordinates":[5.3763689995,51.0295524597],"type":"Point"}
}