{
  "type": "Feature",
  "properties": {
    "iso:country":"BE",
    "sg:address":"41",
    "sg:city":"Rue Geron 5300 Andenne",
    "sg:classifiers":[
        {
            "category":"Building & Trades",
            "subcategory":"Construction",
            "type":"Services"
        }
    ],
    "sg:phone":"+32 85 82 36 36",
    "sg:postcode":"41",
    "sg:tags":[
        "work",
        "public"
    ],
    "wof:name":"T.w.t. Sa",
    "wof:placetype":"venue"
},
  "geometry": {"coordinates":[5.0764231682,50.4754142761],"type":"Point"}
}