{
  "type": "Feature",
  "properties": {
    "iso:country":"BE",
    "sg:address":"Vaart Rechteroever 55",
    "sg:city":"Deinze",
    "sg:classifiers":[
        {
            "category":"Building & Trades",
            "subcategory":"Construction",
            "type":"Services"
        }
    ],
    "sg:phone":"+32 9 386 14 62",
    "sg:postcode":"9800",
    "sg:province":"Oost-Vlaanderen",
    "sg:tags":[
        "roofing",
        "material",
        "-"
    ],
    "wof:name":"Idp/inter Dak Pan Nv",
    "wof:placetype":"venue"
},
  "geometry": {"coordinates":[3.5280849934,50.9915390015],"type":"Point"}
}