{
  "type": "Feature",
  "properties": {
    "iso:country":"BE",
    "sg:address":"Rue De Li\u00c8ge 133",
    "sg:city":"Oupeye",
    "sg:orig_category":"Alimentation sp\u00e9cialis\u00e9e. Boucheries",
    "sg:phone":"+32 4 379 19 47",
    "sg:postcode":"4684",
    "sg:province":"Li\u00e8ge",
    "wof:name":"N. Wers",
    "wof:placetype":"venue"
},
  "geometry": {"coordinates":[5.6688899994,50.7276992798],"type":"Point"}
}