{
  "type": "Feature",
  "properties": {
    "iso:country":"BE",
    "sg:address":"Franseliniestraat 52a",
    "sg:city":"Aarschot (langdorp)",
    "sg:classifiers":[
        {
            "category":"Arts & Performance",
            "subcategory":"Symphony",
            "type":"Entertainment"
        }
    ],
    "sg:phone":"+32 16 56 36 01",
    "sg:postcode":"3201",
    "sg:province":"Vlaams-Brabant",
    "sg:tags":[
        "orchestra"
    ],
    "wof:name":"New Rockets",
    "wof:placetype":"venue"
},
  "geometry": {"coordinates":[4.8649058342,50.9917678833],"type":"Point"}
}