{
  "type": "Feature",
  "properties": {
    "addr:full":"Avenue Notre-dame 135 Bruxelles (evere) Bruxelles-Capitale 1140",
    "addr:housenumber":"135",
    "addr:postcode":"1140",
    "addr:street":"Avenue Notre-Dame",
    "iso:country":"BE",
    "sg:address":"Avenue Notre-dame 135",
    "sg:city":"Bruxelles (evere)",
    "sg:classifiers":[
        {
            "category":"Shopping",
            "subcategory":"Discount & Variety Stores",
            "type":"Retail Goods"
        }
    ],
    "sg:phone":"+32 2 242 73 94",
    "sg:postcode":"1140",
    "sg:province":"Bruxelles-Capitale",
    "sg:tags":[
        "shop",
        "clearers",
        "curiosity",
        "furniture"
    ],
    "wof:name":"Grande Folie (ma)",
    "wof:placetype":"venue"
},
  "geometry": {"coordinates":[4.4016628265,50.8716087341],"type":"Point"}
}