{
  "type": "Feature",
  "properties": {
    "addr:full":"Kragendijk 147 Knokke-heist (westkapelle) West-Vlaanderen 8300",
    "addr:housenumber":"147",
    "addr:postcode":"8300",
    "addr:street":"Knokke-Heist",
    "iso:country":"BE",
    "sg:address":"Kragendijk 147",
    "sg:city":"Knokke-heist (westkapelle)",
    "sg:classifiers":[
        {
            "category":"Food & Beverages",
            "subcategory":"Meat & Fish",
            "type":"Retail Goods"
        }
    ],
    "sg:phone":"+32 50 60 78 64",
    "sg:postcode":"8300",
    "sg:province":"West-Vlaanderen",
    "sg:tags":[
        "bedspread",
        "blanket",
        "-"
    ],
    "wof:name":"Lambert Slaapcomfort",
    "wof:placetype":"venue"
},
  "geometry": {"coordinates":[3.287694931,51.3467254639],"type":"Point"}
}