{
  "type": "Feature",
  "properties": {
    "iso:country":"BE",
    "sg:address":"Rue De Verviers 22",
    "sg:city":"Dison",
    "sg:orig_category":"Poissonniers and \u00e9caillers",
    "sg:phone":"+32 87 33 91 17",
    "sg:postcode":"4821",
    "sg:province":"Li\u00e8ge",
    "wof:name":"Said Akdim",
    "wof:placetype":"venue"
},
  "geometry": {"coordinates":[5.8601708412,50.5987892151],"type":"Point"}
}