{
  "type": "Feature",
  "properties": {
    "addr:full":"Bredestraat 15 Putte Antwerpen 2580",
    "addr:housenumber":"15",
    "addr:postcode":"2580",
    "addr:street":"Bredestraat",
    "iso:country":"BE",
    "sg:address":"Bredestraat 15",
    "sg:city":"Putte",
    "sg:orig_category":"Domotics",
    "sg:phone":"+32 15 76 11 36",
    "sg:postcode":"2580",
    "sg:province":"Antwerpen",
    "wof:name":"Van Den Dries P Elektro Bvba",
    "wof:placetype":"venue"
},
  "geometry": {"coordinates":[4.6303157806,51.0598564148],"type":"Point"}
}