{
  "type": "Feature",
  "properties": {
    "addr:full":"Rue De Beaumont 189 Charleroi Hainaut 6030",
    "addr:housenumber":"189",
    "addr:postcode":"6030",
    "addr:street":"Rue De Beaumont;Hainaut",
    "iso:country":"BE",
    "sg:address":"Rue De Beaumont 189",
    "sg:city":"Charleroi",
    "sg:orig_category":"S\u00e9curit\u00e9 sociale",
    "sg:phone":"+32 71 20 88 60",
    "sg:postcode":"6030",
    "sg:province":"Hainaut",
    "wof:name":"Mutualite Socialiste",
    "wof:placetype":"venue"
},
  "geometry": {"coordinates":[4.3945641518,50.4007225037],"type":"Point"}
}