{
  "type": "Feature",
  "properties": {
    "addr:full":"Place De Houffalize 18 Bruxelles (schaerbeek) Bruxelles-Capitale 1030",
    "addr:housenumber":"18",
    "addr:postcode":"1030",
    "addr:street":"Place De Houffalize",
    "iso:country":"BE",
    "sg:address":"Place De Houffalize 18",
    "sg:city":"Bruxelles (schaerbeek)",
    "sg:classifiers":[
        {
            "category":"Communications",
            "subcategory":"Film & Video Production",
            "type":"Services"
        }
    ],
    "sg:phone":"+32 475 65 75 33",
    "sg:postcode":"1030",
    "sg:province":"Bruxelles-Capitale",
    "sg:tags":[
        "hiring",
        "-"
    ],
    "wof:name":"New Yvan Video",
    "wof:placetype":"venue"
},
  "geometry": {"coordinates":[4.3768987656,50.8650665283],"type":"Point"}
}