{
  "type": "Feature",
  "properties": {
    "addr:full":"Kerkestukstraat 16 Izegem West-Vlaanderen 8870",
    "addr:housenumber":"16",
    "addr:postcode":"8870",
    "addr:street":"Kerkestukstraat",
    "iso:country":"BE",
    "sg:address":"Kerkestukstraat 16",
    "sg:city":"Izegem",
    "sg:orig_category":"Kapsalons",
    "sg:phone":"+32 51 30 01 61",
    "sg:postcode":"8870",
    "sg:province":"West-Vlaanderen",
    "wof:name":"Coiffure Martine",
    "wof:placetype":"venue"
},
  "geometry": {"coordinates":[3.1870670319,50.9350166321],"type":"Point"}
}