{
  "type": "Feature",
  "properties": {
    "addr:full":"Feronstree 71 Liege 1 Li\u00e8ge 4000",
    "addr:housenumber":"71;1",
    "addr:postcode":"4000",
    "addr:street":"Feronstree",
    "iso:country":"BE",
    "sg:address":"Feronstree 71",
    "sg:city":"Liege 1",
    "sg:orig_category":"Ice-cream parlours",
    "sg:phone":"+32 4 222 41 68",
    "sg:postcode":"4000",
    "sg:province":"Li\u00e8ge",
    "wof:name":"Glacier Dubois (le) Sprl",
    "wof:placetype":"venue"
},
  "geometry": {"coordinates":[5.5790071487,50.646522522],"type":"Point"}
}