{
  "type": "Feature",
  "properties": {
    "addr:full":"Stuikberg 121 Londerzeel Vlaams-Brabant 1840",
    "addr:housenumber":"121",
    "addr:postcode":"1840",
    "addr:street":"Stuikberg",
    "iso:country":"BE",
    "sg:address":"Stuikberg 121",
    "sg:city":"Londerzeel",
    "sg:classifiers":[
        {
            "category":"Cafe",
            "type":"Food & Drink"
        }
    ],
    "sg:phone":"+32 52 30 26 61",
    "sg:postcode":"1840",
    "sg:province":"Vlaams-Brabant",
    "sg:tags":[
        "caf\u00e9s"
    ],
    "wof:name":"Caf\u00c9 Spieke",
    "wof:placetype":"venue"
},
  "geometry": {"coordinates":[4.3132410049,51.029548645],"type":"Point"}
}