{
  "type": "Feature",
  "properties": {
    "iso:country":"BE",
    "sg:address":"Nieuwstraat 1",
    "sg:city":"Bornem",
    "sg:classifiers":[
        {
            "category":"Recreation",
            "subcategory":"Fishing",
            "type":"Entertainment"
        }
    ],
    "sg:phone":"+32 3 889 39 20",
    "sg:postcode":"2880",
    "sg:province":"Antwerpen",
    "sg:tags":[
        "tackle"
    ],
    "wof:name":"Casteleyn R",
    "wof:placetype":"venue"
},
  "geometry": {"coordinates":[4.2340478897,51.0980873108],"type":"Point"}
}