{
  "type": "Feature",
  "properties": {
    "iso:country":"BE",
    "sg:address":"Rue Du Bourdeau 10",
    "sg:city":"Tournai (mont-saint-aubert)",
    "sg:classifiers":[
        {
            "category":"Health Services",
            "subcategory":"Doctor",
            "type":"Services"
        }
    ],
    "sg:phone":"+32 69 21 30 62",
    "sg:postcode":"7542",
    "sg:province":"Hainaut",
    "sg:tags":[
        "medicinephysicians",
        "surgeon"
    ],
    "wof:name":"Marquet T",
    "wof:placetype":"venue"
},
  "geometry": {"coordinates":[3.4140460491,50.6551399231],"type":"Point"}
}