{
  "type": "Feature",
  "properties": {
    "iso:country":"BE",
    "sg:address":"Rue Paul-dubois 75",
    "sg:city":"Libin",
    "sg:orig_category":"Eleveurs de bovins",
    "sg:phone":"+32 61 65 53 68",
    "sg:postcode":"6890",
    "sg:province":"Luxembourg",
    "wof:name":"Courard",
    "wof:placetype":"venue"
},
  "geometry": {"coordinates":[5.252808094,49.9877204895],"type":"Point"}
}