{
  "type": "Feature",
  "properties": {
    "addr:full":"Chemin Des Ramiers 3 Rhode-saint-gen\u00e8se Vlaams-Brabant 1640",
    "addr:housenumber":"3",
    "addr:postcode":"1640",
    "addr:street":"Chemin Des Ramiers",
    "iso:country":"BE",
    "sg:address":"Chemin Des Ramiers 3",
    "sg:city":"Rhode-saint-gen\u00e8se",
    "sg:classifiers":[
        {
            "category":"Professional",
            "subcategory":"Art Services",
            "type":"Services"
        }
    ],
    "sg:phone":"+32 2 356 03 93",
    "sg:postcode":"1640",
    "sg:province":"Vlaams-Brabant",
    "sg:tags":[
        "interior",
        "designer"
    ],
    "wof:name":"Marchal S",
    "wof:placetype":"venue"
},
  "geometry": {"coordinates":[4.3698759079,50.760974884],"type":"Point"}
}