{
  "type": "Feature",
  "properties": {
    "iso:country":"BE",
    "sg:address":"Rue L\u00c9on Defuisseaux 31",
    "sg:city":"Frameries",
    "sg:orig_category":"Banques and organismes de cr\u00e9dit",
    "sg:phone":"+32 65 66 78 73",
    "sg:postcode":"7080",
    "sg:province":"Hainaut",
    "wof:name":"Cbc",
    "wof:placetype":"venue"
},
  "geometry": {"coordinates":[3.896780014,50.4066696167],"type":"Point"}
}