{
  "type": "Feature",
  "properties": {
    "iso:country":"BE",
    "sg:address":"Rue De L\u00b4a\u00c9rodrome 38",
    "sg:city":"Brussel/bruxelles",
    "sg:classifiers":[
        {
            "category":"Health Services",
            "subcategory":"Hospital",
            "type":"Services"
        }
    ],
    "sg:phone":"+32 2 726 96 60",
    "sg:postcode":"1130",
    "sg:province":"Bruxelles-Capitale",
    "sg:tags":[
        "ambulance"
    ],
    "wof:name":"Limo-master",
    "wof:placetype":"venue"
},
  "geometry": {"coordinates":[4.4262928963,50.8876724243],"type":"Point"}
}