{
  "type": "Feature",
  "properties": {
    "iso:country":"BE",
    "sg:address":"Rue De Dampremy 81",
    "sg:city":"Charleroi",
    "sg:orig_category":"Pharmaciens",
    "sg:phone":"+32 71 31 04 58",
    "sg:postcode":"6000",
    "sg:province":"Hainaut",
    "wof:name":"Pharmacie Regniers",
    "wof:placetype":"venue"
},
  "geometry": {"coordinates":[4.418612957,50.431350708],"type":"Point"}
}