{
  "type": "Feature",
  "properties": {
    "iso:country":"BE",
    "sg:address":"Rue De La Converserie 24",
    "sg:city":"Saint-hubert",
    "sg:orig_category":"Woningbouw",
    "sg:phone":"+32 61 61 33 20",
    "sg:postcode":"6870",
    "sg:province":"Luxembourg",
    "wof:name":"Andre Thiry",
    "wof:placetype":"venue"
},
  "geometry": {"coordinates":[5.377530098,50.0282936096],"type":"Point"}
}