{
  "type": "Feature",
  "properties": {
    "addr:full":"Rue Briart 61 Chapelle-lez-herlaimont Hainaut 7160",
    "addr:housenumber":"61",
    "addr:postcode":"7160",
    "addr:street":"Rue Briart;Hainaut",
    "iso:country":"BE",
    "sg:address":"Rue Briart 61",
    "sg:city":"Chapelle-lez-herlaimont",
    "sg:classifiers":[
        {
            "category":"Food & Beverages",
            "subcategory":"Groceries & Convenience Stores",
            "type":"Retail Goods"
        }
    ],
    "sg:phone":"+32 64 44 86 69",
    "sg:postcode":"7160",
    "sg:province":"Hainaut",
    "sg:tags":[
        "grocer"
    ],
    "wof:name":"Nadia (chez)",
    "wof:placetype":"venue"
},
  "geometry": {"coordinates":[4.284263134,50.4723777771],"type":"Point"}
}