{
  "type": "Feature",
  "properties": {
    "addr:full":"Rue Saint-gilles 121 Li\u00e8ge 1 Li\u00e8ge 4000",
    "addr:housenumber":"121;1",
    "addr:postcode":"4000",
    "addr:street":"Rue Saint-Gilles",
    "iso:country":"BE",
    "sg:address":"Rue Saint-gilles 121",
    "sg:city":"Li\u00e8ge 1",
    "sg:classifiers":[
        {
            "category":"Building & Trades",
            "subcategory":"Landscaping Services",
            "type":"Services"
        }
    ],
    "sg:phone":"+32 4 223 44 88",
    "sg:postcode":"4000",
    "sg:province":"Li\u00e8ge",
    "sg:tags":[
        "handicraft"
    ],
    "wof:name":"Quelque Chose D'autre",
    "wof:placetype":"venue"
},
  "geometry": {"coordinates":[5.5632429123,50.6379241943],"type":"Point"}
}