{
  "type": "Feature",
  "properties": {
    "addr:full":"Rue Traversi\u00c8re 25 Boussu Hainaut 7301",
    "addr:housenumber":"25",
    "addr:postcode":"7301",
    "addr:street":"Rue Traversie\u0300Re",
    "iso:country":"BE",
    "sg:address":"Rue Traversi\u00c8re 25",
    "sg:city":"Boussu",
    "sg:orig_category":"Pharmaciens",
    "sg:phone":"+32 65 78 31 88",
    "sg:postcode":"7301",
    "sg:province":"Hainaut",
    "wof:name":"Martine Scheepers",
    "wof:placetype":"venue"
},
  "geometry": {"coordinates":[3.8257451057,50.4362258911],"type":"Point"}
}