{
  "type": "Feature",
  "properties": {
    "addr:full":"Chauss\u00e9e De Wavre 1737 Bruxelles (auderghem) Bruxelles-Capitale 1160",
    "addr:postcode":"1737;1160",
    "addr:street":"Chausse\u0301E De Wavre",
    "iso:country":"BE",
    "sg:address":"Chauss\u00e9e De Wavre 1737",
    "sg:city":"Bruxelles (auderghem)",
    "sg:classifiers":[
        {
            "category":"Arts & Performance",
            "subcategory":"Art Gallery",
            "type":"Entertainment"
        }
    ],
    "sg:phone":"+32 2 662 12 44",
    "sg:postcode":"1160",
    "sg:province":"Bruxelles-Capitale",
    "wof:name":"Schots Fr\u00e9d\u00e9ric Galerie",
    "wof:placetype":"venue"
},
  "geometry": {"coordinates":[4.4274258614,50.8162155151],"type":"Point"}
}