{
  "type": "Feature",
  "properties": {
    "addr:full":"Kapelaan Staslaan 7 Wommelgem Antwerpen 2160",
    "addr:housenumber":"7",
    "addr:postcode":"2160",
    "addr:street":"Kapelaan Staslaan",
    "iso:country":"BE",
    "sg:address":"Kapelaan Staslaan 7",
    "sg:city":"Wommelgem",
    "sg:classifiers":[
        {
            "category":"Banks & Credit Unions",
            "subcategory":"Investment Brokerage",
            "type":"Services"
        }
    ],
    "sg:phone":"+32 3 322 07 95",
    "sg:postcode":"2160",
    "sg:province":"Antwerpen",
    "sg:tags":[
        "auditor"
    ],
    "wof:name":"Verbist L",
    "wof:placetype":"venue"
},
  "geometry": {"coordinates":[4.5020480156,51.1972770691],"type":"Point"}
}