{
  "type": "Feature",
  "properties": {
    "addr:full":"Hoogstr 202 Zaventem Vlaams-Brabant 1930",
    "addr:housenumber":"202",
    "addr:postcode":"1930",
    "iso:country":"BE",
    "sg:address":"Hoogstr 202",
    "sg:city":"Zaventem",
    "sg:classifiers":[
        {
            "category":"Manufacturing",
            "subcategory":"Wood Products",
            "type":"Manufacturing & Wholesale Goods"
        }
    ],
    "sg:phone":"+32 2 720 72 03",
    "sg:postcode":"1930",
    "sg:province":"Vlaams-Brabant",
    "sg:tags":[
        "professional",
        "furniture"
    ],
    "wof:name":"New John Nissen Mannequins Nv",
    "wof:placetype":"venue"
},
  "geometry": {"coordinates":[4.4648799896,50.8824691772],"type":"Point"}
}