{
  "type": "Feature",
  "properties": {
    "addr:full":"Dikkebusseweg 507 Ieper West-Vlaanderen 8900",
    "addr:housenumber":"507",
    "addr:postcode":"8900",
    "iso:country":"BE",
    "sg:address":"Dikkebusseweg 507",
    "sg:city":"Ieper",
    "sg:classifiers":[
        {
            "category":"Arts & Performance",
            "subcategory":"Music",
            "type":"Entertainment"
        }
    ],
    "sg:phone":"+32 473 99 16 94",
    "sg:postcode":"8900",
    "sg:province":"West-Vlaanderen",
    "sg:tags":[
        "disc-jockeys"
    ],
    "wof:name":"Studio Five",
    "wof:placetype":"venue"
},
  "geometry": {"coordinates":[2.8651199341,50.8389701843],"type":"Point"}
}