{
  "type": "Feature",
  "properties": {
    "iso:country":"BE",
    "sg:address":"Rue Saint-victor 5",
    "sg:city":"Huy",
    "sg:orig_category":"Sportclubs",
    "sg:phone":"+32 85 41 16 54",
    "sg:postcode":"4500",
    "sg:province":"Li\u00e8ge",
    "wof:name":"Sakura Dojo",
    "wof:placetype":"venue"
},
  "geometry": {"coordinates":[5.2252202034,50.5203094482],"type":"Point"}
}