{
  "type": "Feature",
  "properties": {
    "addr:full":"Kuringersteenweg 413 Hasselt Limburg 3511",
    "addr:housenumber":"413",
    "addr:postcode":"3511",
    "addr:street":"Kuringersteenweg",
    "iso:country":"BE",
    "sg:address":"Kuringersteenweg 413",
    "sg:city":"Hasselt",
    "sg:orig_category":"RESTAURANTS: CAF\u00c9S",
    "sg:phone":"+32 11 85 09 85",
    "sg:postcode":"3511",
    "sg:province":"Limburg",
    "wof:name":"Het Aldenhof",
    "wof:placetype":"venue"
},
  "geometry": {"coordinates":[5.3034238815,50.9432487488],"type":"Point"}
}