{
  "type": "Feature",
  "properties": {
    "iso:country":"BE",
    "sg:address":"Hoogstraat 1",
    "sg:city":"Beernem",
    "sg:orig_category":"Dierenartsen",
    "sg:phone":"+32 50 79 09 19",
    "sg:postcode":"8730",
    "sg:province":"West-Vlaanderen",
    "wof:name":"Joris Mattart",
    "wof:placetype":"venue"
},
  "geometry": {"coordinates":[3.3521409035,51.1676254272],"type":"Point"}
}