{
  "type": "Feature",
  "properties": {
    "addr:full":"Rue Du Petit-audenarde 91 Moeskroen/mouscron Hainaut 7712",
    "addr:housenumber":"91",
    "addr:postcode":"7712",
    "addr:street":"Rue Du Petit-Audenarde",
    "iso:country":"BE",
    "sg:address":"Rue Du Petit-audenarde 91",
    "sg:city":"Moeskroen/mouscron",
    "sg:classifiers":[
        {
            "category":"Social Services",
            "subcategory":"Job Training",
            "type":"Services"
        }
    ],
    "sg:phone":"+32 56 33 08 63",
    "sg:postcode":"7712",
    "sg:province":"Hainaut",
    "sg:tags":[
        "agricoles",
        "plantes",
        "gr",
        "fleurs",
        "machine",
        "mat\u00e9riel"
    ],
    "wof:name":"Maison Gerbera",
    "wof:placetype":"venue"
},
  "geometry": {"coordinates":[3.2535879612,50.714931488],"type":"Point"}
}