{
  "type": "Feature",
  "properties": {
    "addr:full":"Rue Franklin 50 Brussel/bruxelles Bruxelles-Capitale 1000",
    "addr:housenumber":"50",
    "addr:postcode":"1000",
    "addr:street":"Rue Franklin;/",
    "iso:country":"BE",
    "sg:address":"Rue Franklin 50",
    "sg:city":"Brussel/bruxelles",
    "sg:classifiers":[
        {
            "category":"Professional",
            "subcategory":"Business Services",
            "type":"Services"
        }
    ],
    "sg:phone":"+32 2 734 45 41",
    "sg:postcode":"1000",
    "sg:province":"Bruxelles-Capitale",
    "sg:tags":[
        "aux",
        "diver",
        "entreprises"
    ],
    "wof:name":"Quinzaine Du Parfum",
    "wof:placetype":"venue"
},
  "geometry": {"coordinates":[4.3860960007,50.8451957703],"type":"Point"}
}