{
  "type": "Feature",
  "properties": {
    "addr:full":"Kapelbergweg 24 Zonhoven Limburg 3520",
    "addr:housenumber":"24",
    "addr:postcode":"3520",
    "addr:street":"Kapelbergweg",
    "iso:country":"BE",
    "sg:address":"Kapelbergweg 24",
    "sg:city":"Zonhoven",
    "sg:classifiers":[
        {
            "category":"Personal",
            "subcategory":"Beauty Salon",
            "type":"Services"
        }
    ],
    "sg:phone":"+32 11 81 66 33",
    "sg:postcode":"3520",
    "sg:province":"Limburg",
    "sg:tags":[
        "lady",
        "-",
        "hairdressing"
    ],
    "wof:name":"New Fashion",
    "wof:placetype":"venue"
},
  "geometry": {"coordinates":[5.3696451187,50.9869003296],"type":"Point"}
}