{
  "type": "Feature",
  "properties": {
    "addr:full":"Harmoniestraat 122 Antwerpen Antwerpen 2018",
    "addr:housenumber":"122",
    "addr:postcode":"2018",
    "addr:street":"Harmoniestraat",
    "iso:country":"BE",
    "sg:address":"Harmoniestraat 122",
    "sg:city":"Antwerpen",
    "sg:orig_category":"Artsen and specialisten",
    "sg:phone":"+32 3 238 88 99",
    "sg:postcode":"2018",
    "sg:province":"Antwerpen",
    "wof:name":"Pierre De Monie",
    "wof:placetype":"venue"
},
  "geometry": {"coordinates":[4.4083862305,51.2001647949],"type":"Point"}
}