{
  "type": "Feature",
  "properties": {
    "addr:full":"Rue Houlbouse 23 Fl\u00c9malle Li\u00e8ge 4400",
    "addr:housenumber":"23",
    "addr:postcode":"4400",
    "addr:street":"Rue Houlbouse",
    "iso:country":"BE",
    "sg:address":"Rue Houlbouse 23",
    "sg:city":"Fl\u00c9malle",
    "sg:orig_category":"Traitements param\u00e9dicaux",
    "sg:phone":"+32 4 273 09 31",
    "sg:postcode":"4400",
    "sg:province":"Li\u00e8ge",
    "wof:name":"Y. Straat",
    "wof:placetype":"venue"
},
  "geometry": {"coordinates":[5.4431490898,50.5973777771],"type":"Point"}
}