{
  "type": "Feature",
  "properties": {
    "addr:full":"Avenue Herbofin 16b Libramont-chevigny (libramont) Luxembourg 6800",
    "addr:housenumber":"16b",
    "addr:postcode":"6800",
    "addr:street":"Avenue Herbofin",
    "iso:country":"BE",
    "sg:address":"Avenue Herbofin 16b",
    "sg:city":"Libramont-chevigny (libramont)",
    "sg:classifiers":[
        {
            "category":"Professional",
            "subcategory":"Management & Consulting",
            "type":"Services"
        }
    ],
    "sg:phone":"+32 61 23 34 76",
    "sg:postcode":"6800",
    "sg:province":"Luxembourg",
    "sg:tags":[
        "consultant",
        "agency",
        "advertising"
    ],
    "wof:name":"Espace Media",
    "wof:placetype":"venue"
},
  "geometry": {"coordinates":[5.3761348724,49.9199943542],"type":"Point"}
}