{
  "type": "Feature",
  "properties": {
    "iso:country":"BE",
    "sg:address":"Krepelstraat 6",
    "sg:city":"Ninove",
    "sg:orig_category":"HERSTELLING ELEKTRISCHE HUISHOUDAPPARATEN Huishoudapparaten, televisies and radio's Telecommunicatie",
    "sg:phone":"+32 54 33 45 49",
    "sg:postcode":"9400",
    "sg:province":"Oost-Vlaanderen",
    "wof:name":"Electro Shop Desert",
    "wof:placetype":"venue"
},
  "geometry": {"coordinates":[4.0221481323,50.7976112366],"type":"Point"}
}