{
  "type": "Feature",
  "properties": {
    "iso:country":"BE",
    "sg:address":"Rue Redoute 3",
    "sg:city":"Aywaille",
    "sg:orig_category":"Installation \u00e9lectrique r\u00e9sidentielle",
    "sg:phone":"+32 4 384 30 14",
    "sg:postcode":"4920",
    "sg:province":"Li\u00e8ge",
    "wof:name":"Didier Jacobs",
    "wof:placetype":"venue"
},
  "geometry": {"coordinates":[5.6782069206,50.4738540649],"type":"Point"}
}