{
  "type": "Feature",
  "properties": {
    "addr:full":"Fazantenlaan 11bb Kraainem/kraainem Vlaams-Brabant 1950",
    "addr:housenumber":"11bb",
    "addr:postcode":"1950",
    "addr:street":"Fazantenlaan",
    "iso:country":"BE",
    "sg:address":"Fazantenlaan 11bb",
    "sg:city":"Kraainem/kraainem",
    "sg:orig_category":"Schoonheidssalons",
    "sg:phone":"+32 2 731 99 53",
    "sg:postcode":"1950",
    "sg:province":"Vlaams-Brabant",
    "wof:name":"Brigitte Baudot",
    "wof:placetype":"venue"
},
  "geometry": {"coordinates":[4.4752678871,50.8290786743],"type":"Point"}
}