{
  "type": "Feature",
  "properties": {
    "iso:country":"BE",
    "sg:address":"Rue De Sclef 59",
    "sg:city":"La Bruy\u00e8re (meux)",
    "sg:classifiers":[
        {
            "category":"Real Estate",
            "subcategory":"Real Estate Services",
            "type":"Services"
        }
    ],
    "sg:phone":"+32 81 56 03 21",
    "sg:postcode":"5081",
    "sg:province":"Namur",
    "wof:name":"Axigo Immobilier",
    "wof:placetype":"venue"
},
  "geometry": {"coordinates":[4.8039240837,50.559928894],"type":"Point"}
}