{
  "type": "Feature",
  "properties": {
    "addr:full":"Rue Du Cimeti\u00c8re 7 Braine-l'alleud Brabant Wallon 1421",
    "addr:housenumber":"7",
    "addr:postcode":"1421",
    "addr:street":"Rue Du Cimetie\u0300Re",
    "iso:country":"BE",
    "sg:address":"Rue Du Cimeti\u00c8re 7",
    "sg:city":"Braine-l'alleud",
    "sg:classifiers":[
        {
            "category":"Personal",
            "subcategory":"Beauty Salon",
            "type":"Services"
        }
    ],
    "sg:phone":"+32 2 384 08 67",
    "sg:postcode":"1421",
    "sg:province":"Brabant Wallon",
    "sg:tags":[
        "de",
        "coiffure"
    ],
    "wof:name":"Coiffure Anne",
    "wof:placetype":"venue"
},
  "geometry": {"coordinates":[-75.60595703120001,37.7877616882],"type":"Point"}
}