{
  "type": "Feature",
  "properties": {
    "addr:full":"Mechelse Steenweg 204-206 Antwerpen Antwerpen 2018",
    "addr:housenumber":"204-206",
    "addr:postcode":"2018",
    "addr:street":"Steenweg",
    "iso:country":"BE",
    "sg:address":"Mechelse Steenweg 204-206",
    "sg:city":"Antwerpen",
    "sg:classifiers":[
        {
            "category":"Health Services",
            "subcategory":"Hospital",
            "type":"Services"
        }
    ],
    "sg:phone":"+32 3 216 92 92",
    "sg:postcode":"2018",
    "sg:province":"Antwerpen",
    "wof:name":"Belgische Vereniging Voor Osteoporosepati\u00ebnten",
    "wof:placetype":"venue"
},
  "geometry": {"coordinates":[4.411262989,51.203289032],"type":"Point"}
}