{
  "type": "Feature",
  "properties": {
    "addr:full":"Djef Antenstraat 69 Hasselt Limburg 3500",
    "addr:housenumber":"69",
    "addr:postcode":"3500",
    "addr:street":"Antenstraat",
    "iso:country":"BE",
    "sg:address":"Djef Antenstraat 69",
    "sg:city":"Hasselt",
    "sg:classifiers":[
        {
            "category":"Community Center",
            "type":"Public Place"
        }
    ],
    "sg:phone":"+32 11 23 29 91",
    "sg:postcode":"3500",
    "sg:province":"Limburg",
    "sg:tags":[
        "medical"
    ],
    "wof:name":"Abortus Centrum Bourgogne Centrum",
    "wof:placetype":"venue"
},
  "geometry": {"coordinates":[5.3189067841,50.9292144775],"type":"Point"}
}