{
  "type": "Feature",
  "properties": {
    "iso:country":"BE",
    "sg:address":"Heirstraat 218 Box 2-3",
    "sg:city":"Maasmechelen",
    "sg:classifiers":[
        {
            "category":"Real Estate",
            "subcategory":"Developer",
            "type":"Services"
        }
    ],
    "sg:phone":"+32 89 76 11 41",
    "sg:postcode":"3630",
    "sg:province":"Limburg",
    "sg:tags":[
        "project"
    ],
    "wof:name":"H.g. Construct Nv",
    "wof:placetype":"venue"
},
  "geometry": {"coordinates":[5.6961350441,50.963848114],"type":"Point"}
}