{
  "type": "Feature",
  "properties": {
    "iso:country":"BE",
    "sg:address":"Oudestraat 10",
    "sg:city":"Aartselaar",
    "sg:classifiers":[
        {
            "category":"Industrial Area",
            "type":"Public Place"
        }
    ],
    "sg:phone":"+32 3 870 96 90",
    "sg:postcode":"2630",
    "sg:province":"Antwerpen",
    "sg:tags":[
        "-",
        "lighting"
    ],
    "wof:name":"Glamox-framaz",
    "wof:placetype":"venue"
},
  "geometry": {"coordinates":[4.3833580017,51.1442108154],"type":"Point"}
}