{
  "type": "Feature",
  "properties": {
    "addr:full":"Rue Delwaide 41 Oupeye Li\u00e8ge 4681",
    "addr:housenumber":"41",
    "addr:postcode":"4681",
    "addr:street":"Rue Delwaide",
    "iso:country":"BE",
    "sg:address":"Rue Delwaide 41",
    "sg:city":"Oupeye",
    "sg:orig_category":"Installatie van houten of kunststof schrijnwerk Meubelzaken, woning- and keukeninrichting",
    "sg:phone":"+32 4 379 18 05",
    "sg:postcode":"4681",
    "sg:province":"Li\u00e8ge",
    "wof:name":"Marc Lucassen",
    "wof:placetype":"venue"
},
  "geometry": {"coordinates":[5.6845221519,50.7177047729],"type":"Point"}
}