{
  "type": "Feature",
  "properties": {
    "addr:full":"Witte Vrouwenlaan 72 Sint-pieters-woluwe/woluwe-saint-pierre Bruxelles-Capitale 1150",
    "addr:housenumber":"72",
    "addr:postcode":"1150",
    "addr:street":"Witte Vrouwenlaan;/",
    "iso:country":"BE",
    "sg:address":"Witte Vrouwenlaan 72",
    "sg:city":"Sint-pieters-woluwe/woluwe-saint-pierre",
    "sg:orig_category":"Plaatsen van vloer- and muurbekleding Schilders",
    "sg:phone":"+32 2 771 65 98",
    "sg:postcode":"1150",
    "sg:province":"Bruxelles-Capitale",
    "wof:name":"Frederic Goemans",
    "wof:placetype":"venue"
},
  "geometry": {"coordinates":[4.4624438286,50.8264579773],"type":"Point"}
}