{
  "type": "Feature",
  "properties": {
    "iso:country":"BE",
    "sg:address":"Weg Naar As 285",
    "sg:city":"Genk",
    "sg:orig_category":"Charpentes and couvertures. Services de Nettoyage and de D\u00e9sinfection",
    "sg:phone":"+32 89 35 53 70",
    "sg:postcode":"3600",
    "sg:province":"Limburg",
    "wof:name":"Dakwerken Marcel Hendrikx",
    "wof:placetype":"venue"
},
  "geometry": {"coordinates":[5.5309300423,50.9804916382],"type":"Point"}
}