{
  "type": "Feature",
  "properties": {
    "addr:full":"Rue Gouv. Alex Galopin 63 Andenne Namur 5300",
    "addr:housenumber":"63",
    "addr:postcode":"5300",
    "addr:street":"Rue Gouv.;Galopin",
    "iso:country":"BE",
    "sg:address":"Rue Gouv. Alex Galopin 63",
    "sg:city":"Andenne",
    "sg:classifiers":[
        {
            "category":"Personal",
            "subcategory":"Beauty Salon",
            "type":"Services"
        }
    ],
    "sg:phone":"+32 81 58 82 04",
    "sg:postcode":"5300",
    "sg:province":"Namur",
    "sg:tags":[
        "de",
        "coiffure"
    ],
    "wof:name":"Jean-claude Sacre",
    "wof:placetype":"venue"
},
  "geometry": {"coordinates":[5.0982642174,50.4863739014],"type":"Point"}
}