{
  "type": "Feature",
  "properties": {
    "iso:country":"BE",
    "sg:address":"Foyr 91",
    "sg:city":"Jalhay",
    "sg:orig_category":"Eleveurs and marchands de porcs",
    "sg:phone":"+32 87 64 71 65",
    "sg:postcode":"4845",
    "sg:province":"Li\u00e8ge",
    "wof:name":"Henri Jacquemin",
    "wof:placetype":"venue"
},
  "geometry": {"coordinates":[5.9364957809,50.5687675476],"type":"Point"}
}