{
  "type": "Feature",
  "properties": {
    "addr:full":"Place De Pipaix 9 Leuze-en-hainaut Hainaut 7904",
    "addr:housenumber":"9",
    "addr:postcode":"7904",
    "addr:street":"Place De Pipaix",
    "iso:country":"BE",
    "sg:address":"Place De Pipaix 9",
    "sg:city":"Leuze-en-hainaut",
    "sg:orig_category":"Installation de menuiserie m\u00e9tallique",
    "sg:phone":"+32 69 66 21 67",
    "sg:postcode":"7904",
    "sg:province":"Hainaut",
    "wof:name":"Jean-marie Degouys",
    "wof:placetype":"venue"
},
  "geometry": {"coordinates":[3.5791180134,50.5836486816],"type":"Point"}
}