{
  "type": "Feature",
  "properties": {
    "iso:country":"BE",
    "sg:address":"Chaufheid 48",
    "sg:city":"Theux",
    "sg:classifiers":[
        {
            "category":"Building & Trades",
            "subcategory":"Construction",
            "type":"Services"
        }
    ],
    "sg:phone":"+32 87 53 05 13",
    "sg:postcode":"4910",
    "sg:province":"Li\u00e8ge",
    "sg:tags":[
        "carpenter"
    ],
    "wof:name":"Mahy F",
    "wof:placetype":"venue"
},
  "geometry": {"coordinates":[5.8399300575,50.5260887146],"type":"Point"}
}