{
  "type": "Feature",
  "properties": {
    "addr:full":"Rue Du Mont\u00c9n\u00c9gro 173 Vorst/forest Bruxelles-Capitale 1190",
    "addr:housenumber":"173",
    "addr:postcode":"1190",
    "addr:street":"Rue Du Monte\u0301Ne\u0301Gro;/ Forest",
    "iso:country":"BE",
    "sg:address":"Rue Du Mont\u00c9n\u00c9gro 173",
    "sg:city":"Vorst/forest",
    "sg:orig_category":"Entretien and r\u00e9parations de machines de bureau and ordinateurs",
    "sg:phone":"+32 2 537 86 51",
    "sg:postcode":"1190",
    "sg:province":"Bruxelles-Capitale",
    "wof:name":"Electronics 2000",
    "wof:placetype":"venue"
},
  "geometry": {"coordinates":[4.3303580284,50.82654953],"type":"Point"}
}