{
  "type": "Feature",
  "properties": {
    "addr:full":"Rue Notre-dame 14 Gembloux Namur 5030",
    "addr:housenumber":"14",
    "addr:postcode":"5030",
    "addr:street":"Rue Notre-Dame;Namur",
    "iso:country":"BE",
    "sg:address":"Rue Notre-dame 14",
    "sg:city":"Gembloux",
    "sg:orig_category":"Fleurs and plantes",
    "sg:phone":"+32 81 61 23 54",
    "sg:postcode":"5030",
    "sg:province":"Namur",
    "wof:name":"Jardin D'ana\u00cfs",
    "wof:placetype":"venue"
},
  "geometry": {"coordinates":[4.6922969818,50.5607414246],"type":"Point"}
}