{
  "type": "Feature",
  "properties": {
    "addr:full":"Huissegemstraat 3 Denderleeuw Oost-Vlaanderen 9470",
    "addr:housenumber":"3",
    "addr:postcode":"9470",
    "addr:street":"Huissegemstraat",
    "iso:country":"BE",
    "sg:address":"Huissegemstraat 3",
    "sg:city":"Denderleeuw",
    "sg:classifiers":[
        {
            "category":"Health Services",
            "subcategory":"Dentist",
            "type":"Services"
        }
    ],
    "sg:phone":"+32 53 67 09 77",
    "sg:postcode":"9470",
    "sg:province":"Oost-Vlaanderen",
    "wof:name":"Sonck L",
    "wof:placetype":"venue"
},
  "geometry": {"coordinates":[4.0755529404,50.8750610352],"type":"Point"}
}