{
  "type": "Feature",
  "properties": {
    "addr:full":"Heuvelplein 31 Essen Antwerpen 2910",
    "addr:housenumber":"31",
    "addr:postcode":"2910",
    "addr:street":"Heuvelplein",
    "iso:country":"BE",
    "sg:address":"Heuvelplein 31",
    "sg:city":"Essen",
    "sg:classifiers":[
        {
            "category":"Personal",
            "subcategory":"Barber",
            "type":"Services"
        }
    ],
    "sg:phone":"+32 3 677 08 04",
    "sg:postcode":"2910",
    "sg:province":"Antwerpen",
    "sg:tags":[
        "gentleman",
        "salon",
        "-",
        "hairdressing"
    ],
    "wof:name":"Gerrie-uw Kapper",
    "wof:placetype":"venue"
},
  "geometry": {"coordinates":[4.4716038704,51.464969635],"type":"Point"}
}