{
  "type": "Feature",
  "properties": {
    "addr:full":"Adolphe Willemynsstraat 334 Anderlecht/anderlecht Bruxelles-Capitale 1070",
    "addr:housenumber":"334",
    "addr:postcode":"1070",
    "addr:street":"Adolphe Willemynsstraat",
    "iso:country":"BE",
    "sg:address":"Adolphe Willemynsstraat 334",
    "sg:city":"Anderlecht/anderlecht",
    "sg:orig_category":"Apotheken",
    "sg:phone":"+32 2 524 36 01",
    "sg:postcode":"1070",
    "sg:province":"Bruxelles-Capitale",
    "wof:name":"Christiane Croen",
    "wof:placetype":"venue"
},
  "geometry": {"coordinates":[4.2876849174,50.8398284912],"type":"Point"}
}