{
  "type": "Feature",
  "properties": {
    "addr:full":"Astridlaan 90 Tongeren Limburg 3700",
    "addr:housenumber":"90",
    "addr:postcode":"3700",
    "addr:street":"Astridlaan",
    "iso:country":"BE",
    "sg:address":"Astridlaan 90",
    "sg:city":"Tongeren",
    "sg:classifiers":[
        {
            "category":"Shopping",
            "subcategory":"Clothing, Apparel, & Fashions",
            "type":"Retail Goods"
        }
    ],
    "sg:phone":"+32 12 23 02 48",
    "sg:postcode":"3700",
    "sg:province":"Limburg",
    "sg:tags":[
        "v\u00eatements",
        "pour",
        "dame"
    ],
    "wof:name":"Caroline Moermans",
    "wof:placetype":"venue"
},
  "geometry": {"coordinates":[5.4590702057,50.7743797302],"type":"Point"}
}