{
  "type": "Feature",
  "properties": {
    "addr:full":"Rue Peltzer De Clermont 20 Verviers Li\u00e8ge 4800",
    "addr:housenumber":"20",
    "addr:postcode":"4800",
    "addr:street":"Rue Peltzer De Clermont",
    "iso:country":"BE",
    "sg:address":"Rue Peltzer De Clermont 20",
    "sg:city":"Verviers",
    "sg:orig_category":"Antiquit\u00e9s",
    "sg:phone":"+32 87 33 01 00",
    "sg:postcode":"4800",
    "sg:province":"Li\u00e8ge",
    "wof:name":"B. Legros",
    "wof:placetype":"venue"
},
  "geometry": {"coordinates":[5.8537869453,50.5917472839],"type":"Point"}
}