{
  "type": "Feature",
  "properties": {
    "addr:full":"Sint-adriaanveld 6 Haacht Vlaams-Brabant 3150",
    "addr:housenumber":"6",
    "addr:postcode":"3150",
    "addr:street":"Sint-Adriaanveld",
    "iso:country":"BE",
    "sg:address":"Sint-adriaanveld 6",
    "sg:city":"Haacht",
    "sg:classifiers":[
        {
            "category":"Cafe",
            "type":"Food & Drink"
        }
    ],
    "sg:phone":"+32 16 60 77 44",
    "sg:postcode":"3150",
    "sg:province":"Vlaams-Brabant",
    "sg:tags":[
        "caf\u00e9s"
    ],
    "wof:name":"Luc Meulders",
    "wof:placetype":"venue"
},
  "geometry": {"coordinates":[4.6191449165,50.9817314148],"type":"Point"}
}