{
  "type": "Feature",
  "properties": {
    "addr:full":"Rue Crocq 55 Sint-lambrechts-woluwe/woluwe-saint-lambert Bruxelles-Capitale 1200",
    "addr:housenumber":"55",
    "addr:postcode":"1200",
    "addr:street":"Rue Crocq",
    "iso:country":"BE",
    "sg:address":"Rue Crocq 55",
    "sg:city":"Sint-lambrechts-woluwe/woluwe-saint-lambert",
    "sg:orig_category":"Artistes ind\u00e9pendants",
    "sg:phone":"+32 2 771 55 14",
    "sg:postcode":"1200",
    "sg:province":"Bruxelles-Capitale",
    "wof:name":"Christian Libotton",
    "wof:placetype":"venue"
},
  "geometry": {"coordinates":[4.4218850136,50.8466491699],"type":"Point"}
}