{
  "type": "Feature",
  "properties": {
    "addr:full":"Beverenstraat 54 Alveringem (leisele) West-Vlaanderen 8691",
    "addr:housenumber":"54",
    "addr:postcode":"8691",
    "addr:street":"Beverenstraat",
    "iso:country":"BE",
    "sg:address":"Beverenstraat 54",
    "sg:city":"Alveringem (leisele)",
    "sg:classifiers":[
        {
            "category":"Building & Trades",
            "subcategory":"Construction",
            "type":"Services"
        }
    ],
    "sg:phone":"+32 58 29 92 74",
    "sg:postcode":"8691",
    "sg:province":"West-Vlaanderen",
    "sg:tags":[
        "carpenter"
    ],
    "wof:name":"Vanalme-huys",
    "wof:placetype":"venue"
},
  "geometry": {"coordinates":[2.6265609264,50.9827194214],"type":"Point"}
}