{
  "type": "Feature",
  "properties": {
    "iso:country":"BE",
    "sg:address":"Uilenstraat 72",
    "sg:city":"Sint-niklaas",
    "sg:orig_category":"Elektrische installaties voor woningen",
    "sg:phone":"+32 3 777 06 31",
    "sg:postcode":"9100",
    "sg:province":"Oost-Vlaanderen",
    "wof:name":"Dimitri Van Hese",
    "wof:placetype":"venue"
},
  "geometry": {"coordinates":[4.1663808823,51.1831855774],"type":"Point"}
}