{
  "type": "Feature",
  "properties": {
    "iso:country":"BE",
    "sg:address":"Sint-jorisstraat 7",
    "sg:city":"Maasmechelen (boorsem)",
    "sg:classifiers":[
        {
            "category":"Juice Bar",
            "subcategory":"None",
            "type":"Food & Drink"
        }
    ],
    "sg:phone":"+32 89 76 46 77",
    "sg:postcode":"3631",
    "sg:province":"Limburg",
    "sg:tags":[
        "water",
        "soft"
    ],
    "wof:name":"Milissen Dranken Nv",
    "wof:placetype":"venue"
},
  "geometry": {"coordinates":[5.7193460464,50.9411621094],"type":"Point"}
}