{
  "type": "Feature",
  "properties": {
    "addr:full":"Markt 50 Zele Oost-Vlaanderen 9240",
    "addr:housenumber":"50",
    "addr:postcode":"9240",
    "addr:street":"Markt",
    "iso:country":"BE",
    "sg:address":"Markt 50",
    "sg:city":"Zele",
    "sg:orig_category":"Overheidsdiensten",
    "sg:phone":"+32 52 45 98 14",
    "sg:postcode":"9240",
    "sg:province":"Oost-Vlaanderen",
    "wof:name":"Gemeentebestuur",
    "wof:placetype":"venue"
},
  "geometry": {"coordinates":[4.0371999741,51.0689811707],"type":"Point"}
}