{
  "type": "Feature",
  "properties": {
    "addr:full":"Vlierbeekstraat 8 Oud-heverlee (blanden) Vlaams-Brabant 3052",
    "addr:housenumber":"8",
    "addr:postcode":"3052",
    "addr:street":"Vlierbeekstraat",
    "iso:country":"BE",
    "sg:address":"Vlierbeekstraat 8",
    "sg:city":"Oud-heverlee (blanden)",
    "sg:classifiers":[
        {
            "category":"Professional",
            "subcategory":"Management & Consulting",
            "type":"Services"
        }
    ],
    "sg:phone":"+32 16 40 09 77",
    "sg:postcode":"3052",
    "sg:province":"Vlaams-Brabant",
    "sg:tags":[
        "consultant"
    ],
    "wof:name":"Comatech Bvba",
    "wof:placetype":"venue"
},
  "geometry": {"coordinates":[4.7106781006,50.8300590515],"type":"Point"}
}