{
  "type": "Feature",
  "properties": {
    "iso:country":"BE",
    "sg:address":"Avenue Des Martyrs 265",
    "sg:city":"Fl\u00e9ron",
    "sg:classifiers":[
        {
            "category":"Shopping",
            "subcategory":"Clothing, Apparel, & Fashions",
            "type":"Retail Goods"
        }
    ],
    "sg:phone":"+32 4 358 73 60",
    "sg:postcode":"4620",
    "sg:province":"Li\u00e8ge",
    "sg:tags":[
        "boutique"
    ],
    "wof:name":"Frivole Boutique",
    "wof:placetype":"venue"
},
  "geometry": {"coordinates":[5.6848220825,50.6148414612],"type":"Point"}
}