{
  "type": "Feature",
  "properties": {
    "addr:full":"Rue De Limbourg 52 Verviers Li\u00e8ge 4800",
    "addr:housenumber":"52",
    "addr:postcode":"4800",
    "addr:street":"Rue De Limbourg",
    "iso:country":"BE",
    "sg:address":"Rue De Limbourg 52",
    "sg:city":"Verviers",
    "sg:classifiers":[
        {
            "category":"Utilities",
            "subcategory":"Fuel Oil & Lpg",
            "type":"Services"
        }
    ],
    "sg:phone":"+32 87 33 12 75",
    "sg:postcode":"4800",
    "sg:province":"Li\u00e8ge",
    "wof:name":"Knodt Et Fils",
    "wof:placetype":"venue"
},
  "geometry": {"coordinates":[5.8789801598,50.5994682312],"type":"Point"}
}