{
  "type": "Feature",
  "properties": {
    "addr:full":"Keizersplein 19 Aalst Oost-Vlaanderen 9300",
    "addr:housenumber":"19",
    "addr:postcode":"9300",
    "addr:street":"Keizersplein",
    "iso:country":"BE",
    "sg:address":"Keizersplein 19",
    "sg:city":"Aalst",
    "sg:orig_category":"Enseignement sup\u00e9rieur",
    "sg:phone":"+32 53 21 23 21",
    "sg:postcode":"9300",
    "sg:province":"Oost-Vlaanderen",
    "wof:name":"Hogeschool Gent",
    "wof:placetype":"venue"
},
  "geometry": {"coordinates":[4.0348677635,50.9371795654],"type":"Point"}
}