{
  "type": "Feature",
  "properties": {
    "iso:country":"BE",
    "sg:address":"Stationsstraat 41",
    "sg:city":"Berlaar",
    "sg:orig_category":"S\u00e9curit\u00e9 sociale",
    "sg:phone":"+32 3 482 11 62",
    "sg:postcode":"2590",
    "sg:province":"Antwerpen",
    "wof:name":"Socialist. Mutualiteit",
    "wof:placetype":"venue"
},
  "geometry": {"coordinates":[4.6484937668,51.1160888672],"type":"Point"}
}