{
  "type": "Feature",
  "properties": {
    "iso:country":"BE",
    "sg:address":"Bouresse 28",
    "sg:city":"Clavier",
    "sg:orig_category":"Gespecialiseerde residenti\u00eble bouw",
    "sg:phone":"+32 86 34 47 24",
    "sg:postcode":"4560",
    "sg:province":"Li\u00e8ge",
    "wof:name":"Alain Collette",
    "wof:placetype":"venue"
},
  "geometry": {"coordinates":[5.3197898865,50.3909301758],"type":"Point"}
}