{
  "type": "Feature",
  "properties": {
    "addr:full":"Rue De Bretagne 25 Bruxelles (woluwe-saint-lambert) Bruxelles-Capitale 1200",
    "addr:housenumber":"25",
    "addr:postcode":"1200",
    "addr:street":"Rue De Bretagne",
    "iso:country":"BE",
    "sg:address":"Rue De Bretagne 25",
    "sg:city":"Bruxelles (woluwe-saint-lambert)",
    "sg:classifiers":[
        {
            "category":"Professional",
            "subcategory":"Art Services",
            "type":"Services"
        }
    ],
    "sg:phone":"+32 2 771 11 90",
    "sg:postcode":"1200",
    "sg:province":"Bruxelles-Capitale",
    "sg:tags":[
        "design",
        "packing",
        "-",
        "realization"
    ],
    "wof:name":"New Pack",
    "wof:placetype":"venue"
},
  "geometry": {"coordinates":[4.4257321358,50.8555793762],"type":"Point"}
}