{
  "type": "Feature",
  "properties": {
    "iso:country":"BE",
    "sg:address":"Rue De L'eglise 9",
    "sg:city":"Rumes",
    "sg:orig_category":"Notaires",
    "sg:phone":"+32 69 64 65 00",
    "sg:postcode":"7618",
    "sg:province":"Hainaut",
    "wof:name":"Edouard Jacmin",
    "wof:placetype":"venue"
},
  "geometry": {"coordinates":[3.3433339596,50.5509490967],"type":"Point"}
}