{
  "type": "Feature",
  "properties": {
    "addr:full":"Winkelstraat 19 Genk (waterschei) Limburg 3600",
    "addr:housenumber":"19",
    "addr:postcode":"3600",
    "addr:street":"Winkelstraat",
    "iso:country":"BE",
    "sg:address":"Winkelstraat 19",
    "sg:city":"Genk (waterschei)",
    "sg:classifiers":[
        {
            "category":"Health Services",
            "subcategory":"Health Practitioner",
            "type":"Services"
        }
    ],
    "sg:phone":"+32 89 38 48 84",
    "sg:postcode":"3600",
    "sg:province":"Limburg",
    "sg:tags":[
        "physiotherapist"
    ],
    "wof:name":"Bens Erik",
    "wof:placetype":"venue"
},
  "geometry": {"coordinates":[5.5224990845,50.987361908],"type":"Point"}
}