{
  "type": "Feature",
  "properties": {
    "addr:full":"124 Bredabaan 2170 Antwerpen 124",
    "addr:housenumber":"124;124",
    "addr:postcode":"2170",
    "addr:street":"Bredabaan;Antwerpen",
    "iso:country":"BE",
    "sg:address":"124",
    "sg:city":"Bredabaan 2170 Antwerpen",
    "sg:classifiers":[
        {
            "category":"Park",
            "type":"Public Place"
        }
    ],
    "sg:phone":"+32 3 644 44 50",
    "sg:postcode":"124",
    "sg:tags":[
        "work",
        "construction",
        "sport"
    ],
    "wof:name":"Gp Construct Algemene Bouwmaatschappij Bvba",
    "wof:placetype":"venue"
},
  "geometry": {"coordinates":[4.4505147934,51.246723175],"type":"Point"}
}