{
  "type": "Feature",
  "properties": {
    "addr:full":"Zwaluwenlaan 19 Liedekerke Vlaams-Brabant 1770",
    "addr:housenumber":"19",
    "addr:postcode":"1770",
    "addr:street":"Zwaluwenlaan;Vlaams-Brabant",
    "iso:country":"BE",
    "sg:address":"Zwaluwenlaan 19",
    "sg:city":"Liedekerke",
    "sg:classifiers":[
        {
            "category":"Health Services",
            "subcategory":"Health Practitioner",
            "type":"Services"
        }
    ],
    "sg:phone":"+32 53 66 40 41",
    "sg:postcode":"1770",
    "sg:province":"Vlaams-Brabant",
    "sg:tags":[
        "physiotherapist"
    ],
    "wof:name":"Tcherniaeff Georges",
    "wof:placetype":"venue"
},
  "geometry": {"coordinates":[4.118584156,50.8599090576],"type":"Point"}
}