{
  "type": "Feature",
  "properties": {
    "addr:full":"Kortrijkstraat 325 Wevelgem West-Vlaanderen 8560",
    "addr:housenumber":"325",
    "addr:postcode":"8560",
    "addr:street":"Kortrijkstraat",
    "iso:country":"BE",
    "sg:address":"Kortrijkstraat 325",
    "sg:city":"Wevelgem",
    "sg:classifiers":[
        {
            "category":"Fast Food",
            "type":"Food & Drink"
        }
    ],
    "sg:phone":"+32 56 41 64 46",
    "sg:postcode":"8560",
    "sg:province":"West-Vlaanderen",
    "sg:tags":[
        "\u00c0",
        "emporter",
        "restaurants"
    ],
    "wof:name":"Mcdonald's",
    "wof:placetype":"venue"
},
  "geometry": {"coordinates":[3.2042860985,50.8152770996],"type":"Point"}
}