{
  "type": "Feature",
  "properties": {
    "iso:country":"BE",
    "sg:address":"Place Royale 29",
    "sg:city":"Spa",
    "sg:classifiers":[
        {
            "category":"Restaurant",
            "type":"Food & Drink"
        }
    ],
    "sg:phone":"+32 87 77 57 79",
    "sg:postcode":"4900",
    "sg:province":"Li\u00e8ge",
    "sg:tags":[
        "caf\u00e9s"
    ],
    "wof:name":"Brasserie Le Royal",
    "wof:placetype":"venue"
},
  "geometry": {"coordinates":[5.8630681038,50.4928665161],"type":"Point"}
}