{
  "type": "Feature",
  "properties": {
    "addr:full":"Rue Ernest Martel 6 Ecaussinnes (ecaussinnes-d'enghien) Hainaut 7190",
    "addr:housenumber":"6",
    "addr:postcode":"7190",
    "addr:street":"Rue Ernest Martel;Ecaussinnes-D'Enghien Hainaut",
    "iso:country":"BE",
    "sg:address":"Rue Ernest Martel 6",
    "sg:city":"Ecaussinnes (ecaussinnes-d'enghien)",
    "sg:classifiers":[
        {
            "category":"Education",
            "subcategory":"University",
            "type":"Public Place"
        }
    ],
    "sg:phone":"+32 67 44 38 32",
    "sg:postcode":"7190",
    "sg:province":"Hainaut",
    "sg:tags":[
        "higher"
    ],
    "wof:name":"Ecole Industrielle & Commerciale",
    "wof:placetype":"venue"
},
  "geometry": {"coordinates":[4.1751251221,50.5696868896],"type":"Point"}
}