{
  "type": "Feature",
  "properties": {
    "addr:full":"Spijker 90 Essen Antwerpen 2910",
    "addr:housenumber":"90",
    "addr:postcode":"2910",
    "addr:street":"Spijker",
    "iso:country":"BE",
    "sg:address":"Spijker 90",
    "sg:city":"Essen",
    "sg:classifiers":[
        {
            "category":"Fast Food",
            "type":"Food & Drink"
        }
    ],
    "sg:phone":"+32 3 677 35 55",
    "sg:postcode":"2910",
    "sg:province":"Antwerpen",
    "sg:tags":[
        "restaurant",
        "\u00c0",
        "domicile",
        "emporter",
        "livraison",
        "restaurants"
    ],
    "wof:name":"Speyckerslot",
    "wof:placetype":"venue"
},
  "geometry": {"coordinates":[4.4747219086,51.4504165649],"type":"Point"}
}