{
  "type": "Feature",
  "properties": {
    "iso:country":"BE",
    "sg:address":"Kerkstraat 102",
    "sg:city":"Beveren (vrasene)",
    "sg:classifiers":[
        {
            "category":"Wholesale",
            "subcategory":"Beer",
            "type":"Manufacturing & Wholesale Goods"
        }
    ],
    "sg:phone":"+32 3 775 40 46",
    "sg:postcode":"9120",
    "sg:province":"Oost-Vlaanderen",
    "sg:tags":[
        "ale",
        "-"
    ],
    "wof:name":"Maes D",
    "wof:placetype":"venue"
},
  "geometry": {"coordinates":[4.1950788498,51.2117462158],"type":"Point"}
}