{
  "type": "Feature",
  "properties": {
    "addr:full":"Rue Ch\u00caneau 6 Erquelinnes Hainaut 6560",
    "addr:housenumber":"6",
    "addr:postcode":"6560",
    "addr:street":"Rue Che\u0302Neau",
    "iso:country":"BE",
    "sg:address":"Rue Ch\u00caneau 6",
    "sg:city":"Erquelinnes",
    "sg:orig_category":"Rundveehouders",
    "sg:phone":"+32 71 55 51 61",
    "sg:postcode":"6560",
    "sg:province":"Hainaut",
    "wof:name":"Boucher B. & Decat M.",
    "wof:placetype":"venue"
},
  "geometry": {"coordinates":[4.1777691841,50.3052787781],"type":"Point"}
}