{
  "type": "Feature",
  "properties": {
    "iso:country":"BE",
    "sg:address":"Rue De La Jonqui\u00c8re 27",
    "sg:city":"Morlanwelz",
    "sg:orig_category":"HUISBRANDOLIE Huishoudapparaten, televisies and radio's MEUBELONTWERP AND -INSTALLATIE",
    "sg:phone":"+32 64 33 30 74",
    "sg:postcode":"7141",
    "sg:province":"Hainaut",
    "wof:name":"Imbert",
    "wof:placetype":"venue"
},
  "geometry": {"coordinates":[4.2543048859,50.4436531067],"type":"Point"}
}