{
  "type": "Feature",
  "properties": {
    "addr:full":"Rue Boucher 69 Tournai Hainaut 7548",
    "addr:housenumber":"69",
    "addr:postcode":"7548",
    "addr:street":"Rue Boucher",
    "iso:country":"BE",
    "sg:address":"Rue Boucher 69",
    "sg:city":"Tournai",
    "sg:classifiers":[
        {
            "category":"Personal",
            "subcategory":"Beauty Salon",
            "type":"Services"
        }
    ],
    "sg:phone":"+32 69 23 33 68",
    "sg:postcode":"7548",
    "sg:province":"Hainaut",
    "sg:tags":[
        "de",
        "coiffure"
    ],
    "wof:name":"Jean Bilouez",
    "wof:placetype":"venue"
},
  "geometry": {"coordinates":[3.4179899693,50.6135559082],"type":"Point"}
}