{
  "type": "Feature",
  "properties": {
    "addr:full":"Provincieweg 76 Herzele (borsbeke) Oost-Vlaanderen 9552",
    "addr:housenumber":"76",
    "addr:postcode":"9552",
    "addr:street":"Provincieweg;Borsbeke Oost-Vlaanderen",
    "iso:country":"BE",
    "sg:address":"Provincieweg 76",
    "sg:city":"Herzele (borsbeke)",
    "sg:classifiers":[
        {
            "category":"Manufacturing",
            "subcategory":"Tools & Machinery",
            "type":"Manufacturing & Wholesale Goods"
        }
    ],
    "sg:phone":"+32 53 62 22 05",
    "sg:postcode":"9552",
    "sg:province":"Oost-Vlaanderen",
    "sg:tags":[
        "-"
    ],
    "wof:name":"Polet Quality Tools",
    "wof:placetype":"venue"
},
  "geometry": {"coordinates":[3.8934979439,50.9051704407],"type":"Point"}
}