{
  "type": "Feature",
  "properties": {
    "addr:full":"36 Grandroute 4367 Crisnee 36",
    "addr:housenumber":"36;36",
    "addr:postcode":"4367",
    "addr:street":"Grandroute;Crisnee",
    "iso:country":"BE",
    "sg:address":"36",
    "sg:city":"Grandroute 4367 Crisnee",
    "sg:classifiers":[
        {
            "category":"Professional",
            "type":"Services"
        }
    ],
    "sg:phone":"+32 4 257 45 41",
    "sg:postcode":"36",
    "sg:tags":[
        "transport",
        "road"
    ],
    "wof:name":"Transports Raymackers Sprl",
    "wof:placetype":"venue"
},
  "geometry": {"coordinates":[5.3981599808,50.7090759277],"type":"Point"}
}