{
  "type": "Feature",
  "properties": {
    "addr:full":"Solwaster 3 Jalhay Li\u00e8ge 4845",
    "addr:housenumber":"3",
    "addr:postcode":"4845",
    "addr:street":"Solwaster",
    "iso:country":"BE",
    "sg:address":"Solwaster 3",
    "sg:city":"Jalhay",
    "sg:orig_category":"Avocats and conseillers juridiques",
    "sg:phone":"+32 87 47 52 12",
    "sg:postcode":"4845",
    "sg:province":"Li\u00e8ge",
    "wof:name":"Jo\u00cblle Falize",
    "wof:placetype":"venue"
},
  "geometry": {"coordinates":[5.967151165,50.5330314636],"type":"Point"}
}