{
  "type": "Feature",
  "properties": {
    "addr:full":"Paul De Smet De Naeyerplein 10 Gent Oost-Vlaanderen 9000",
    "addr:housenumber":"10",
    "addr:postcode":"9000",
    "addr:street":"Paul De Smet De Naeyerplein;Oost-Vlaanderen",
    "iso:country":"BE",
    "sg:address":"Paul De Smet De Naeyerplein 10",
    "sg:city":"Gent",
    "sg:classifiers":[
        {
            "category":"Health Services",
            "subcategory":"Dentist",
            "type":"Services"
        }
    ],
    "sg:phone":"+32 9 222 02 89",
    "sg:postcode":"9000",
    "sg:province":"Oost-Vlaanderen",
    "wof:name":"Malchair Fran\u00e7oise",
    "wof:placetype":"venue"
},
  "geometry": {"coordinates":[3.7184491158,51.0308265686],"type":"Point"}
}