{
  "type": "Feature",
  "properties": {
    "iso:country":"BE",
    "sg:address":"Hogenakkerstraat 68",
    "sg:city":"Temse",
    "sg:orig_category":"Varkenskwekers",
    "sg:phone":"+32 3 771 22 17",
    "sg:postcode":"9140",
    "sg:province":"Oost-Vlaanderen",
    "wof:name":"Eric Van De Voorde",
    "wof:placetype":"venue"
},
  "geometry": {"coordinates":[4.1624779701,51.1211471558],"type":"Point"}
}