{
  "type": "Feature",
  "properties": {
    "iso:country":"BE",
    "sg:address":"Kattenberg 2",
    "sg:city":"Oosterzele",
    "sg:classifiers":[
        {
            "category":"Cafe",
            "type":"Food & Drink"
        }
    ],
    "sg:phone":"+32 9 362 90 91",
    "sg:postcode":"9860",
    "sg:province":"Oost-Vlaanderen",
    "sg:tags":[
        "caf\u00e9s"
    ],
    "wof:name":"Marie-jose Haelterman",
    "wof:placetype":"venue"
},
  "geometry": {"coordinates":[3.7926499844,50.9238815308],"type":"Point"}
}