{
  "type": "Feature",
  "properties": {
    "addr:full":"Perksestraat 11 - 17 Vilvoorde Vlaams-Brabant 1800",
    "addr:housenumber":"11 17",
    "addr:postcode":"1800",
    "addr:street":"Perksestraat",
    "iso:country":"BE",
    "sg:address":"Perksestraat 11 - 17",
    "sg:city":"Vilvoorde",
    "sg:orig_category":"Pi\u00e8ces and accessoires de v\u00e9hicules automobiles D\u00e9taillants en pi\u00e8ces and accessoires de voitures. V",
    "sg:phone":"+32 2 251 94 36",
    "sg:postcode":"1800",
    "sg:province":"Vlaams-Brabant",
    "wof:name":"Lauwers Patrick Garage",
    "wof:placetype":"venue"
},
  "geometry": {"coordinates":[4.4362769127,50.928352356],"type":"Point"}
}