{
  "type": "Feature",
  "properties": {
    "addr:full":"Avenue Paquay 49 Chaudfontaine (beaufays) Li\u00e8ge 4052",
    "addr:housenumber":"49",
    "addr:postcode":"4052",
    "addr:street":"Avenue Paquay;Beaufays",
    "iso:country":"BE",
    "sg:address":"Avenue Paquay 49",
    "sg:city":"Chaudfontaine (beaufays)",
    "sg:classifiers":[
        {
            "category":"Health Services",
            "subcategory":"Health Practitioner",
            "type":"Services"
        }
    ],
    "sg:phone":"+32 474 24 30 80",
    "sg:postcode":"4052",
    "sg:province":"Li\u00e8ge",
    "sg:tags":[
        "physiotherapist"
    ],
    "wof:name":"Liepin B\u00e9n\u00e9dicte",
    "wof:placetype":"venue"
},
  "geometry": {"coordinates":[5.6222748756,50.5627288818],"type":"Point"}
}