{
  "type": "Feature",
  "properties": {
    "iso:country":"BE",
    "sg:address":"Everdijstraat 8",
    "sg:city":"Antwerpen",
    "sg:classifiers":[
        {
            "category":"Banks & Credit Unions",
            "subcategory":"Investment Brokerage",
            "type":"Services"
        }
    ],
    "sg:phone":"+32 3 226 82 07",
    "sg:postcode":"2000",
    "sg:province":"Antwerpen",
    "sg:tags":[
        "rental",
        "-",
        "yacht",
        "boat",
        "pleasure"
    ],
    "wof:name":"Leers Yachtcharter",
    "wof:placetype":"venue"
},
  "geometry": {"coordinates":[4.402176857,51.2164077759],"type":"Point"}
}