{
  "type": "Feature",
  "properties": {
    "iso:country":"BE",
    "sg:address":"Koekamerstraat 34",
    "sg:city":"Maarkedal (schorisse)",
    "sg:classifiers":[
        {
            "category":"Building & Trades",
            "subcategory":"Electrical",
            "type":"Services"
        }
    ],
    "sg:phone":"+32 55 21 18 67",
    "sg:postcode":"9688",
    "sg:province":"Oost-Vlaanderen",
    "sg:tags":[
        "electric",
        "-",
        "housewiring",
        "contractor"
    ],
    "wof:name":"Besard",
    "wof:placetype":"venue"
},
  "geometry": {"coordinates":[3.6667490005,50.773399353],"type":"Point"}
}