{
  "type": "Feature",
  "properties": {
    "addr:full":"Prinses Elisabethlaan 56bb Schaarbeek/schaerbeek Bruxelles-Capitale 1030",
    "addr:housenumber":"56bb",
    "addr:postcode":"1030",
    "addr:street":"Prinses Elisabethlaan",
    "iso:country":"BE",
    "sg:address":"Prinses Elisabethlaan 56bb",
    "sg:city":"Schaarbeek/schaerbeek",
    "sg:orig_category":"Apotheken",
    "sg:phone":"+32 2 215 24 71",
    "sg:postcode":"1030",
    "sg:province":"Bruxelles-Capitale",
    "wof:name":"Anna De Ruiter/de Ruiter",
    "wof:placetype":"venue"
},
  "geometry": {"coordinates":[4.3774600029,50.8737258911],"type":"Point"}
}