{
  "type": "Feature",
  "properties": {
    "addr:full":"Rue Auguste Scohy 52 Aiseau-presles (pont-de-loup) Hainaut 6250",
    "addr:housenumber":"52",
    "addr:postcode":"6250",
    "addr:street":"Rue Auguste Scohy",
    "iso:country":"BE",
    "sg:address":"Rue Auguste Scohy 52",
    "sg:city":"Aiseau-presles (pont-de-loup)",
    "sg:classifiers":[
        {
            "category":"Retail",
            "subcategory":"Event Space",
            "type":"Services"
        }
    ],
    "sg:phone":"+32 71 39 07 04",
    "sg:postcode":"6250",
    "sg:province":"Hainaut",
    "sg:tags":[
        "rental",
        "-",
        "hall"
    ],
    "wof:name":"Collard A",
    "wof:placetype":"venue"
},
  "geometry": {"coordinates":[4.5681881905,50.4138565063],"type":"Point"}
}