{
  "type": "Feature",
  "properties": {
    "addr:full":"Boulevaerd Du Souverain 55 Oudergem/auderghem Bruxelles-Capitale 1160",
    "addr:housenumber":"55",
    "addr:postcode":"1160",
    "addr:street":"/",
    "iso:country":"BE",
    "sg:address":"Boulevaerd Du Souverain 55",
    "sg:city":"Oudergem/auderghem",
    "sg:orig_category":"Journaux. Restaurants. Stations-service and carburants. Tabac",
    "sg:phone":"+32 2 672 18 96",
    "sg:postcode":"1160",
    "sg:province":"Bruxelles-Capitale",
    "wof:name":"Shell",
    "wof:placetype":"venue"
},
  "geometry": {"coordinates":[4.4280080795,50.8119049072],"type":"Point"}
}