{
  "type": "Feature",
  "properties": {
    "iso:country":"BE",
    "sg:address":"Happaertstraat 23",
    "sg:city":"Antwerpen",
    "sg:orig_category":"Transports routiers de marchandises",
    "sg:phone":"+32 3 226 65 70",
    "sg:postcode":"2000",
    "sg:province":"Antwerpen",
    "wof:name":"Transport Frevag",
    "wof:placetype":"venue"
},
  "geometry": {"coordinates":[4.4013080597,51.2154502869],"type":"Point"}
}