{
  "type": "Feature",
  "properties": {
    "addr:full":"Av Des Pagodes 435 Bruxelles Bruxelles-Capitale 1020",
    "addr:housenumber":"435",
    "addr:postcode":"1020",
    "addr:street":"Av Des Pagodes",
    "iso:country":"BE",
    "sg:address":"Av Des Pagodes 435",
    "sg:city":"Bruxelles",
    "sg:classifiers":[
        {
            "category":"Professional",
            "subcategory":"Advertising",
            "type":"Services"
        }
    ],
    "sg:phone":"+32 2 262 14 48",
    "sg:postcode":"1020",
    "sg:province":"Bruxelles-Capitale",
    "sg:tags":[
        "marketing",
        "medium",
        "communication"
    ],
    "wof:name":"Imd Nv Sa",
    "wof:placetype":"venue"
},
  "geometry": {"coordinates":[4.357585907,50.8958587646],"type":"Point"}
}