{
  "type": "Feature",
  "properties": {
    "iso:country":"BE",
    "sg:address":"Montgomerystraat 45",
    "sg:city":"Edingen/enghien",
    "sg:orig_category":"Banken and kredietinstellingen",
    "sg:phone":"+32 2 395 57 76",
    "sg:postcode":"7850",
    "sg:province":"Hainaut",
    "wof:name":"Nagelmackers",
    "wof:placetype":"venue"
},
  "geometry": {"coordinates":[4.0362849236,50.693195343],"type":"Point"}
}