{
  "type": "Feature",
  "properties": {
    "iso:country":"BE",
    "sg:address":"Korhaanstraat 18",
    "sg:city":"Zonhoven",
    "sg:classifiers":[
        {
            "category":"Airport",
            "subcategory":"International",
            "type":"Transportation"
        }
    ],
    "sg:phone":"+32 11 82 51 28",
    "sg:postcode":"3520",
    "sg:province":"Limburg",
    "sg:tags":[
        "-",
        "transport"
    ],
    "wof:name":"Dendas R",
    "wof:placetype":"venue"
},
  "geometry": {"coordinates":[5.3251471519,50.9906349182],"type":"Point"}
}