{
  "type": "Feature",
  "properties": {
    "addr:full":"Lerenveld 44 Lint Antwerpen 2547",
    "addr:housenumber":"44",
    "addr:postcode":"2547",
    "addr:street":"Lerenveld",
    "iso:country":"BE",
    "sg:address":"Lerenveld 44",
    "sg:city":"Lint",
    "sg:classifiers":[
        {
            "category":"Autos & Motor Vehicles",
            "subcategory":"Auto Supplies",
            "type":"Retail Goods"
        }
    ],
    "sg:phone":"+32 3 480 07 06",
    "sg:postcode":"2547",
    "sg:province":"Antwerpen",
    "sg:tags":[
        "automobile",
        "-",
        "truck",
        "gear-boxes"
    ],
    "wof:name":"Autrac Bvba",
    "wof:placetype":"venue"
},
  "geometry": {"coordinates":[4.5115442276,51.1278038025],"type":"Point"}
}