{
  "type": "Feature",
  "properties": {
    "iso:country":"BE",
    "sg:address":"Avenue Des Glycines 3",
    "sg:city":"Bruxelles (schaerbeek)",
    "sg:classifiers":[
        {
            "category":"Government",
            "subcategory":"Court House",
            "type":"Public Place"
        }
    ],
    "sg:phone":"+32 2 245 88 20",
    "sg:postcode":"1030",
    "sg:province":"Bruxelles-Capitale",
    "sg:tags":[
        "consultant",
        "outplacement"
    ],
    "wof:name":"Zadig",
    "wof:placetype":"venue"
},
  "geometry": {"coordinates":[4.3856840134,50.8660011292],"type":"Point"}
}