{
  "type": "Feature",
  "properties": {
    "addr:full":"Schrieksteenweg 58 Putte Antwerpen 2580",
    "addr:housenumber":"58",
    "addr:postcode":"2580",
    "addr:street":"Schrieksteenweg",
    "iso:country":"BE",
    "sg:address":"Schrieksteenweg 58",
    "sg:city":"Putte",
    "sg:orig_category":"Produits \u00e0 base de pommes de terre Combustibles. Fruits and l\u00e9gumes Gr",
    "sg:phone":"+32 15 75 75 32",
    "sg:postcode":"2580",
    "sg:province":"Antwerpen",
    "wof:name":"Jozef Van Der Veken",
    "wof:placetype":"venue"
},
  "geometry": {"coordinates":[4.6493492126,51.0416107178],"type":"Point"}
}