{
  "type": "Feature",
  "properties": {
    "addr:full":"Donckstraat 13b1 Dendermonde Oost-Vlaanderen 9200",
    "addr:housenumber":"13b1",
    "addr:postcode":"9200",
    "addr:street":"Donckstraat;Oost-Vlaanderen",
    "iso:country":"BE",
    "sg:address":"Donckstraat 13b1",
    "sg:city":"Dendermonde",
    "sg:classifiers":[
        {
            "category":"Cafe",
            "type":"Food & Drink"
        }
    ],
    "sg:phone":"+32 52 22 30 40",
    "sg:postcode":"9200",
    "sg:province":"Oost-Vlaanderen",
    "sg:tags":[
        "caf\u00e9s"
    ],
    "wof:name":"Maria Dierick",
    "wof:placetype":"venue"
},
  "geometry": {"coordinates":[4.0879859924,51.0324401855],"type":"Point"}
}