{
  "type": "Feature",
  "properties": {
    "iso:country":"BE",
    "sg:address":"Iepersestraat 70",
    "sg:city":"Roeselare",
    "sg:classifiers":[
        {
            "category":"Social Services",
            "type":"Services"
        }
    ],
    "sg:phone":"+32 51 22 21 27",
    "sg:postcode":"8800",
    "sg:province":"West-Vlaanderen",
    "wof:name":"Bond Van Grote En Van Jonge Gezinnen-west-vlaanderen",
    "wof:placetype":"venue"
},
  "geometry": {"coordinates":[3.1209750175,50.9421195984],"type":"Point"}
}