{
  "type": "Feature",
  "properties": {
    "addr:full":"Bonestraat 63 Meulebeke West-Vlaanderen 8760",
    "addr:housenumber":"63",
    "addr:postcode":"8760",
    "addr:street":"Bonestraat",
    "iso:country":"BE",
    "sg:address":"Bonestraat 63",
    "sg:city":"Meulebeke",
    "sg:orig_category":"Diensten voor huisdieren Huisdieren and benodigdheden",
    "sg:phone":"+32 51 48 78 78",
    "sg:postcode":"8760",
    "sg:province":"West-Vlaanderen",
    "wof:name":"Bijoux",
    "wof:placetype":"venue"
},
  "geometry": {"coordinates":[3.3163330555,50.9570198059],"type":"Point"}
}