{
  "type": "Feature",
  "properties": {
    "iso:country":"BE",
    "sg:address":"Steenweg Op Zevendonk 195",
    "sg:city":"Turnhout",
    "sg:orig_category":"Non-Classified Establishments",
    "sg:phone":"+32 14 42 88 74",
    "sg:postcode":"2300",
    "sg:province":"Antwerpen",
    "wof:name":"Look Unique",
    "wof:placetype":"venue"
},
  "geometry": {"coordinates":[4.9512228966,51.3030204773],"type":"Point"}
}