{
  "type": "Feature",
  "properties": {
    "iso:country":"BE",
    "sg:address":"Berghomstraat 23",
    "sg:city":"Gooik",
    "sg:orig_category":"Rundveehouders",
    "sg:phone":"+32 54 56 70 68",
    "sg:postcode":"1755",
    "sg:province":"Vlaams-Brabant",
    "wof:name":"Willy Van Ongeval",
    "wof:placetype":"venue"
},
  "geometry": {"coordinates":[4.1051797867,50.7712516785],"type":"Point"}
}