{
  "type": "Feature",
  "properties": {
    "addr:full":"Rue De La Barge 40 Li\u00e8ge 1 (sclessin) Li\u00e8ge 4000",
    "addr:housenumber":"40;1",
    "addr:postcode":"4000",
    "addr:street":"Rue De La Barge;Sclessin Lie\u0300Ge",
    "iso:country":"BE",
    "sg:address":"Rue De La Barge 40",
    "sg:city":"Li\u00e8ge 1 (sclessin)",
    "sg:classifiers":[
        {
            "category":"Building & Trades",
            "subcategory":"Plumbing",
            "type":"Services"
        }
    ],
    "sg:phone":"+32 4 233 41 27",
    "sg:postcode":"4000",
    "sg:province":"Li\u00e8ge",
    "sg:tags":[
        "repair",
        "mainten",
        "-",
        "central",
        "heating"
    ],
    "wof:name":"Delcourt Entreprises",
    "wof:placetype":"venue"
},
  "geometry": {"coordinates":[5.5371098518,50.6098213196],"type":"Point"}
}