{
  "type": "Feature",
  "properties": {
    "iso:country":"BE",
    "sg:address":"Stationsstr 21",
    "sg:city":"Keerbergen",
    "sg:classifiers":[
        {
            "category":"Professional",
            "type":"Services"
        }
    ],
    "sg:phone":"+32 15 23 67 67",
    "sg:postcode":"3140",
    "sg:province":"Vlaams-Brabant",
    "sg:tags":[
        "transport",
        "road"
    ],
    "wof:name":"Keerbergens Transportbedrijf Bvba",
    "wof:placetype":"venue"
},
  "geometry": {"coordinates":[4.6320180893,51.0049934387],"type":"Point"}
}