{
  "type": "Feature",
  "properties": {
    "iso:country":"BE",
    "sg:address":"Diestersteenweg 80",
    "sg:city":"Sint-truiden",
    "sg:orig_category":"Dakwerken",
    "sg:phone":"+32 11 68 50 96",
    "sg:postcode":"3800",
    "sg:province":"Limburg",
    "wof:name":"Moens Francis",
    "wof:placetype":"venue"
},
  "geometry": {"coordinates":[5.1838488579,50.8208045959],"type":"Point"}
}