{
  "type": "Feature",
  "properties": {
    "addr:full":"Karmelietenstraat 72 Ukkel/uccle Bruxelles-Capitale 1180",
    "addr:housenumber":"72",
    "addr:postcode":"1180",
    "addr:street":"Karmelietenstraat;/",
    "iso:country":"BE",
    "sg:address":"Karmelietenstraat 72",
    "sg:city":"Ukkel/uccle",
    "sg:classifiers":[
        {
            "category":"Taxi",
            "type":"Transportation"
        }
    ],
    "sg:phone":"+32 2 344 46 11",
    "sg:postcode":"1180",
    "sg:province":"Bruxelles-Capitale",
    "sg:tags":[
        "taxi's"
    ],
    "wof:name":"Taxi Van Hemelrijck",
    "wof:placetype":"venue"
},
  "geometry": {"coordinates":[4.3417468071,50.8124465942],"type":"Point"}
}