{
  "type": "Feature",
  "properties": {
    "iso:country":"BE",
    "sg:address":"Rue Sans Souci 107",
    "sg:city":"Elsene/ixelles",
    "sg:orig_category":"Informaticaconsulenten Vertalers and tolken",
    "sg:phone":"+32 2 647 66 06",
    "sg:postcode":"1050",
    "sg:province":"Bruxelles-Capitale",
    "wof:name":"Crehan P",
    "wof:placetype":"venue"
},
  "geometry": {"coordinates":[4.3719391823,50.8326835632],"type":"Point"}
}