{
  "type": "Feature",
  "properties": {
    "addr:full":"Achterburg 1 Box 14 Oudenaarde Oost-Vlaanderen 9700",
    "addr:housenumber":"1 box 14",
    "addr:postcode":"9700",
    "addr:street":"Achterburg",
    "iso:country":"BE",
    "sg:address":"Achterburg 1 Box 14",
    "sg:city":"Oudenaarde",
    "sg:classifiers":[
        {
            "category":"Health Services",
            "subcategory":"Health Practitioner",
            "type":"Services"
        }
    ],
    "sg:phone":"+32 55 30 33 21",
    "sg:postcode":"9700",
    "sg:province":"Oost-Vlaanderen",
    "sg:tags":[
        "therapist",
        "speech"
    ],
    "wof:name":"Praktijk Logopedie",
    "wof:placetype":"venue"
},
  "geometry": {"coordinates":[3.6056919098,50.841293335],"type":"Point"}
}