{
  "type": "Feature",
  "properties": {
    "iso:country":"BE",
    "sg:address":"Rue De Robiano 83",
    "sg:city":"Binche",
    "sg:orig_category":"Kapsalons",
    "sg:phone":"+32 64 33 27 16",
    "sg:postcode":"7130",
    "sg:province":"Hainaut",
    "wof:name":"Coiffure Jacky M",
    "wof:placetype":"venue"
},
  "geometry": {"coordinates":[4.1699171066,50.4095916748],"type":"Point"}
}