{
  "type": "Feature",
  "properties": {
    "iso:country":"BE",
    "sg:address":"Ieperstraat 35",
    "sg:city":"Zonnebeke",
    "sg:classifiers":[
        {
            "category":"Banks & Credit Unions",
            "subcategory":"Bank",
            "type":"Services"
        }
    ],
    "sg:phone":"+32 51 77 25 78",
    "sg:postcode":"8980",
    "sg:province":"West-Vlaanderen",
    "sg:tags":[
        "savings-banks"
    ],
    "wof:name":"Mercator Bank En Verzekeringen",
    "wof:placetype":"venue"
},
  "geometry": {"coordinates":[2.9844698906,50.870639801],"type":"Point"}
}