{
  "type": "Feature",
  "properties": {
    "addr:full":"Miksebaan 242b1 Brasschaat Antwerpen 2930",
    "addr:housenumber":"242b1",
    "addr:postcode":"2930",
    "addr:street":"Miksebaan",
    "iso:country":"BE",
    "sg:address":"Miksebaan 242b1",
    "sg:city":"Brasschaat",
    "sg:orig_category":"Beautyfarms, relaxatie and lichamelijk welzijn Schoonheidssalons",
    "sg:phone":"+32 3 653 17 58",
    "sg:postcode":"2930",
    "sg:province":"Antwerpen",
    "wof:name":"Beauty Center Koala Blue",
    "wof:placetype":"venue"
},
  "geometry": {"coordinates":[4.5156979561,51.2963104248],"type":"Point"}
}