{
  "type": "Feature",
  "properties": {
    "addr:full":"Bld Edmond Machtens 135b11 Sint-jans-molenbeek/molenbeek-saint-jean Bruxelles-Capitale 1080",
    "addr:housenumber":"135b11 sint-jans-molenbeek",
    "addr:postcode":"1080",
    "addr:street":"Bld Edmond Machtens",
    "iso:country":"BE",
    "sg:address":"Bld Edmond Machtens 135b11",
    "sg:city":"Sint-jans-molenbeek/molenbeek-saint-jean",
    "sg:orig_category":"Experts-comptables",
    "sg:phone":"+32 2 411 19 46",
    "sg:postcode":"1080",
    "sg:province":"Bruxelles-Capitale",
    "wof:name":"Alexandre Lefebvre",
    "wof:placetype":"venue"
},
  "geometry": {"coordinates":[4.3049178123,50.8508529663],"type":"Point"}
}