{
  "type": "Feature",
  "properties": {
    "addr:full":"Eglantierenlaan 65 Sint-pieters-woluwe/woluwe-saint-pierre Bruxelles-Capitale 1150",
    "addr:housenumber":"65",
    "addr:postcode":"1150",
    "addr:street":"Eglantierenlaan;/",
    "iso:country":"BE",
    "sg:address":"Eglantierenlaan 65",
    "sg:city":"Sint-pieters-woluwe/woluwe-saint-pierre",
    "sg:orig_category":"Artsen and specialisten",
    "sg:phone":"+32 2 770 45 42",
    "sg:postcode":"1150",
    "sg:province":"Bruxelles-Capitale",
    "wof:name":"Robert Legrand",
    "wof:placetype":"venue"
},
  "geometry": {"coordinates":[4.4144377708,50.8268318176],"type":"Point"}
}