{
  "type": "Feature",
  "properties": {
    "iso:country":"BE",
    "sg:address":"Fr. De Peuterstraat 31",
    "sg:city":"Kapellen",
    "sg:orig_category":"Agences d'exp\u00e9dition",
    "sg:phone":"+32 3 664 04 35",
    "sg:postcode":"2950",
    "sg:province":"Antwerpen",
    "wof:name":"Valdeco",
    "wof:placetype":"venue"
},
  "geometry": {"coordinates":[4.4292321205,51.3055801392],"type":"Point"}
}