{
  "type": "Feature",
  "properties": {
    "addr:full":"Rue Albert Ier 208 Erquelinnes Hainaut 6560",
    "addr:housenumber":"208",
    "addr:postcode":"6560",
    "addr:street":"Rue Albert Ier",
    "iso:country":"BE",
    "sg:address":"Rue Albert Ier 208",
    "sg:city":"Erquelinnes",
    "sg:classifiers":[
        {
            "category":"Personal",
            "subcategory":"Beauty Salon",
            "type":"Services"
        }
    ],
    "sg:phone":"+32 71 55 79 87",
    "sg:postcode":"6560",
    "sg:province":"Hainaut",
    "sg:tags":[
        "de",
        "coiffure"
    ],
    "wof:name":"Emeridys",
    "wof:placetype":"venue"
},
  "geometry": {"coordinates":[4.1161551476,50.3067054749],"type":"Point"}
}