{
  "type": "Feature",
  "properties": {
    "iso:country":"BE",
    "sg:address":"De Keyserlei 5b55",
    "sg:city":"Anvers",
    "sg:orig_category":"Diverse bedrijfsbeheeradviesbureaus",
    "sg:phone":"+32 3 232 03 20",
    "sg:postcode":"2018",
    "sg:province":"Antwerpen",
    "wof:name":"T.d.r.",
    "wof:placetype":"venue"
},
  "geometry": {"coordinates":[4.4162421227,51.2180023193],"type":"Point"}
}