{
  "type": "Feature",
  "properties": {
    "addr:full":"Dudzeelse Steenweg 511 Brugge (dudzele) West-Vlaanderen 8380",
    "addr:housenumber":"511",
    "addr:postcode":"8380",
    "addr:street":"Dudzeelse Steenweg",
    "iso:country":"BE",
    "sg:address":"Dudzeelse Steenweg 511",
    "sg:city":"Brugge (dudzele)",
    "sg:classifiers":[
        {
            "category":"Home & Garden",
            "subcategory":"Carpets & Floor Coverings",
            "type":"Retail Goods"
        }
    ],
    "sg:phone":"+32 50 59 83 79",
    "sg:postcode":"8380",
    "sg:province":"West-Vlaanderen",
    "sg:tags":[
        "parquet"
    ],
    "wof:name":"Opsomer T",
    "wof:placetype":"venue"
},
  "geometry": {"coordinates":[3.2288448811,51.2742958069],"type":"Point"}
}