{
  "type": "Feature",
  "properties": {
    "addr:full":"90 Industrieweg Iz 8 Nr. 8079 3620 Lanaken 90",
    "addr:housenumber":"8;90",
    "addr:postcode":"3620",
    "addr:street":"Industrieweg Iz;Lanaken",
    "iso:country":"BE",
    "sg:address":"90",
    "sg:city":"Industrieweg Iz 8 Nr. 8079 3620 Lanaken",
    "sg:classifiers":[
        {
            "category":"Manufacturing",
            "subcategory":"Chemicals & Compounds",
            "type":"Manufacturing & Wholesale Goods"
        }
    ],
    "sg:phone":"+32 89 73 02 22",
    "sg:postcode":"90",
    "sg:tags":[
        "pharmaceutical",
        "chemistry"
    ],
    "wof:name":"Silmaco Nv",
    "wof:placetype":"venue"
},
  "geometry": {"coordinates":[5.6551351547,50.8912277222],"type":"Point"}
}