{
  "type": "Feature",
  "properties": {
    "iso:country":"BE",
    "sg:address":"Th\u00c9odore Verhaegenstraat 158",
    "sg:city":"Sint-gillis/saint-gilles",
    "sg:orig_category":"Fotografen and fotostudio's",
    "sg:phone":"+32 2 534 70 26",
    "sg:postcode":"1060",
    "sg:province":"Bruxelles-Capitale",
    "wof:name":"Emmanuel Piron",
    "wof:placetype":"venue"
},
  "geometry": {"coordinates":[4.3367638588,50.8302650452],"type":"Point"}
}