{
  "type": "Feature",
  "properties": {
    "addr:full":"Bredestraat 83 Hemiksem Antwerpen 2620",
    "addr:housenumber":"83",
    "addr:postcode":"2620",
    "addr:street":"Bredestraat",
    "iso:country":"BE",
    "sg:address":"Bredestraat 83",
    "sg:city":"Hemiksem",
    "sg:classifiers":[
        {
            "category":"Building & Trades",
            "subcategory":"Plumbing",
            "type":"Services"
        }
    ],
    "sg:phone":"+32 3 887 25 97",
    "sg:postcode":"2620",
    "sg:province":"Antwerpen",
    "sg:tags":[
        "repair",
        "mainten",
        "-",
        "central",
        "heating"
    ],
    "wof:name":"Huybrechts J",
    "wof:placetype":"venue"
},
  "geometry": {"coordinates":[4.3426790237,51.1540985107],"type":"Point"}
}