{
  "type": "Feature",
  "properties": {
    "addr:full":"Bredaseweg 38ba Hoogstraten Antwerpen 2322",
    "addr:housenumber":"38ba",
    "addr:postcode":"2322",
    "addr:street":"Bredaseweg",
    "iso:country":"BE",
    "sg:address":"Bredaseweg 38ba",
    "sg:city":"Hoogstraten",
    "sg:classifiers":[
        {
            "category":"Arena",
            "subcategory":"Sports Club",
            "type":"Entertainment"
        }
    ],
    "sg:phone":"+32 3 315 03 21",
    "sg:postcode":"2322",
    "sg:province":"Antwerpen",
    "sg:tags":[
        "installation",
        "sportifs",
        "de",
        "terrain",
        "hors",
        "caf\u00e9s"
    ],
    "wof:name":"Minderhout V.v.",
    "wof:placetype":"venue"
},
  "geometry": {"coordinates":[4.763384819,51.4160041809],"type":"Point"}
}