{
  "type": "Feature",
  "properties": {
    "iso:country":"BE",
    "sg:address":"Mechelbaan 404",
    "sg:city":"Putte",
    "sg:classifiers":[
        {
            "category":"Bars & Pubs",
            "type":"Food & Drink"
        }
    ],
    "sg:phone":"+32 15 76 20 97",
    "sg:postcode":"2580",
    "sg:province":"Antwerpen",
    "wof:name":"Den Artist Bvba",
    "wof:placetype":"venue"
},
  "geometry": {"coordinates":[4.6416621208,51.0595436096],"type":"Point"}
}