{
  "type": "Feature",
  "properties": {
    "iso:country":"BE",
    "sg:address":"Mangelschotsstraat 11",
    "sg:city":"Meise",
    "sg:classifiers":[
        {
            "category":"Arena",
            "subcategory":"Sports Club",
            "type":"Entertainment"
        }
    ],
    "sg:phone":"+32 2 270 19 61",
    "sg:postcode":"1860",
    "sg:province":"Vlaams-Brabant",
    "sg:tags":[
        "de"
    ],
    "wof:name":"Shito Ippon",
    "wof:placetype":"venue"
},
  "geometry": {"coordinates":[4.3062720299,50.9520797729],"type":"Point"}
}