{
  "type": "Feature",
  "properties": {
    "iso:country":"BE",
    "sg:address":"Rue D'aische En-refail 43",
    "sg:city":"Gembloux-sur-orneau (grand-leez)",
    "sg:classifiers":[
        {
            "category":"Building & Trades",
            "subcategory":"Electrical",
            "type":"Services"
        }
    ],
    "sg:phone":"+32 81 64 09 34",
    "sg:postcode":"5031",
    "sg:province":"Namur",
    "sg:tags":[
        "electric",
        "-",
        "housewiring",
        "contractor"
    ],
    "wof:name":"Gilson A",
    "wof:placetype":"venue"
},
  "geometry": {"coordinates":[4.7815141678,50.5868186951],"type":"Point"}
}