{
  "type": "Feature",
  "properties": {
    "addr:full":"Rue Lesbroussart 43 Bruxelles (ixelles) Bruxelles-Capitale 1050",
    "addr:housenumber":"43",
    "addr:postcode":"1050",
    "addr:street":"Rue Lesbroussart",
    "iso:country":"BE",
    "sg:address":"Rue Lesbroussart 43",
    "sg:city":"Bruxelles (ixelles)",
    "sg:classifiers":[
        {
            "category":"Travel",
            "subcategory":"Travel Agent",
            "type":"Entertainment"
        }
    ],
    "sg:phone":"+32 2 649 51 02",
    "sg:postcode":"1050",
    "sg:province":"Bruxelles-Capitale",
    "sg:tags":[
        "agency"
    ],
    "wof:name":"Geo-xl Sprl",
    "wof:placetype":"venue"
},
  "geometry": {"coordinates":[4.3691339493,50.827583313],"type":"Point"}
}