{
  "type": "Feature",
  "properties": {
    "addr:full":"Spelemanstraat 154 Knokke-heist West-Vlaanderen 8301",
    "addr:housenumber":"154",
    "addr:postcode":"8301",
    "addr:street":"Spelemanstraat",
    "iso:country":"BE",
    "sg:address":"Spelemanstraat 154",
    "sg:city":"Knokke-heist",
    "sg:orig_category":"Rundveehouders Varkenskwekers",
    "sg:phone":"+32 50 51 10 92",
    "sg:postcode":"8301",
    "sg:province":"West-Vlaanderen",
    "wof:name":"Robert Huys",
    "wof:placetype":"venue"
},
  "geometry": {"coordinates":[3.2566590309,51.319683075],"type":"Point"}
}