{
  "type": "Feature",
  "properties": {
    "addr:full":"Zeedijk 92 Blankenberge West-Vlaanderen 8370",
    "addr:housenumber":"92",
    "addr:postcode":"8370",
    "addr:street":"Zeedijk",
    "iso:country":"BE",
    "sg:address":"Zeedijk 92",
    "sg:city":"Blankenberge",
    "sg:classifiers":[
        {
            "category":"Restaurant",
            "type":"Food & Drink"
        }
    ],
    "sg:phone":"+32 50 42 86 96",
    "sg:postcode":"8370",
    "sg:province":"West-Vlaanderen",
    "wof:name":"Triton",
    "wof:placetype":"venue"
},
  "geometry": {"coordinates":[3.1232988834,51.3150253296],"type":"Point"}
}