{
  "type": "Feature",
  "properties": {
    "addr:full":"Rue Trou Bourbon 10 La Roche-en-ardenne Luxembourg 6980",
    "addr:housenumber":"10",
    "addr:postcode":"6980",
    "addr:street":"Rue Trou Bourbon",
    "iso:country":"BE",
    "sg:address":"Rue Trou Bourbon 10",
    "sg:city":"La Roche-en-ardenne",
    "sg:classifiers":[
        {
            "category":"Health Services",
            "subcategory":"Health Practitioner",
            "type":"Services"
        }
    ],
    "sg:phone":"+32 84 47 80 74",
    "sg:postcode":"6980",
    "sg:province":"Luxembourg",
    "sg:tags":[
        "physiotherapist"
    ],
    "wof:name":"Sonet Dominique",
    "wof:placetype":"venue"
},
  "geometry": {"coordinates":[5.5795760155,50.1839790344],"type":"Point"}
}