{
  "type": "Feature",
  "properties": {
    "iso:country":"BE",
    "sg:address":"Rue Des Bada 27",
    "sg:city":"Celles (les Waleffes)",
    "sg:classifiers":[
        {
            "category":"Insurance",
            "subcategory":"Insurance Agent",
            "type":"Services"
        }
    ],
    "sg:phone":"+32 19 56 61 59",
    "sg:postcode":"4317",
    "sg:province":"Li\u00e8ge",
    "sg:tags":[
        "broker"
    ],
    "wof:name":"Grommen Assurances Sprl",
    "wof:placetype":"venue"
},
  "geometry": {"coordinates":[5.2618951797,50.6657218933],"type":"Point"}
}