{
  "type": "Feature",
  "properties": {
    "addr:full":"Kooigemstraat 45bc Zwevegem West-Vlaanderen 8554",
    "addr:housenumber":"45bc",
    "addr:postcode":"8554",
    "addr:street":"Kooigemstraat",
    "iso:country":"BE",
    "sg:address":"Kooigemstraat 45bc",
    "sg:city":"Zwevegem",
    "sg:classifiers":[
        {
            "category":"Food & Beverages",
            "subcategory":"Fruits & Vegetables",
            "type":"Retail Goods"
        }
    ],
    "sg:phone":"+32 56 45 52 06",
    "sg:postcode":"8554",
    "sg:province":"West-Vlaanderen",
    "sg:tags":[
        "groenten"
    ],
    "wof:name":"Eco Verrue Piet",
    "wof:placetype":"venue"
},
  "geometry": {"coordinates":[3.3706920147,50.7496185303],"type":"Point"}
}