{
  "type": "Feature",
  "properties": {
    "addr:full":"Rue De Baili\u00e8vre 96 Chimay (robechies) Hainaut 6460",
    "addr:housenumber":"96",
    "addr:postcode":"6460",
    "addr:street":"Rue De Bailie\u0300Vre",
    "iso:country":"BE",
    "sg:address":"Rue De Baili\u00e8vre 96",
    "sg:city":"Chimay (robechies)",
    "sg:classifiers":[
        {
            "category":"Professional",
            "subcategory":"Art Services",
            "type":"Services"
        }
    ],
    "sg:phone":"+32 60 21 90 60",
    "sg:postcode":"6460",
    "sg:province":"Hainaut",
    "sg:tags":[
        "photographer"
    ],
    "wof:name":"Photo Velle Sprl",
    "wof:placetype":"venue"
},
  "geometry": {"coordinates":[4.2590088844,50.0724449158],"type":"Point"}
}