{
  "type": "Feature",
  "properties": {
    "iso:country":"BE",
    "sg:address":"Rue Du Long Thier 53a",
    "sg:city":"Huy",
    "sg:orig_category":"Installatie van houten of kunststof schrijnwerk",
    "sg:phone":"+32 85 23 07 67",
    "sg:postcode":"4500",
    "sg:province":"Li\u00e8ge",
    "wof:name":"Fe. Montfort",
    "wof:placetype":"venue"
},
  "geometry": {"coordinates":[5.2559118271,50.5186729431],"type":"Point"}
}