{
  "type": "Feature",
  "properties": {
    "addr:full":"Kruindersweg 12 Maasmechelen Limburg 3630",
    "addr:housenumber":"12",
    "addr:postcode":"3630",
    "addr:street":"Kruindersweg",
    "iso:country":"BE",
    "sg:address":"Kruindersweg 12",
    "sg:city":"Maasmechelen",
    "sg:classifiers":[
        {
            "category":"Restaurant",
            "type":"Food & Drink"
        }
    ],
    "sg:phone":"+32 89 76 26 66",
    "sg:postcode":"3630",
    "sg:province":"Limburg",
    "wof:name":"De Griek",
    "wof:placetype":"venue"
},
  "geometry": {"coordinates":[5.6961350441,50.963848114],"type":"Point"}
}