{
  "type": "Feature",
  "properties": {
    "iso:country":"BE",
    "sg:address":"Rue Haute Voie 4",
    "sg:city":"Verlaine",
    "sg:orig_category":"Mat\u00e9riaux de construction Gr",
    "sg:phone":"+32 4 259 56 49",
    "sg:postcode":"4537",
    "sg:province":"Li\u00e8ge",
    "wof:name":"Europan",
    "wof:placetype":"venue"
},
  "geometry": {"coordinates":[5.3145680428,50.6007232666],"type":"Point"}
}