{
  "type": "Feature",
  "properties": {
    "addr:full":"Zeelaan 176 De Panne West-Vlaanderen 8660",
    "addr:housenumber":"176",
    "addr:postcode":"8660",
    "addr:street":"Zeelaan",
    "iso:country":"BE",
    "sg:address":"Zeelaan 176",
    "sg:city":"De Panne",
    "sg:classifiers":[
        {
            "category":"Shopping",
            "subcategory":"Clothing, Apparel, & Fashions",
            "type":"Retail Goods"
        }
    ],
    "sg:phone":"+32 58 41 57 54",
    "sg:postcode":"8660",
    "sg:province":"West-Vlaanderen",
    "sg:tags":[
        "boutique"
    ],
    "wof:name":"Profil",
    "wof:placetype":"venue"
},
  "geometry": {"coordinates":[2.5915389061,51.1020774841],"type":"Point"}
}