{
  "type": "Feature",
  "properties": {
    "iso:country":"BE",
    "sg:address":"Rue Masui 16",
    "sg:city":"Bruxelles",
    "sg:classifiers":[
        {
            "category":"Communications",
            "subcategory":"Radio Station",
            "type":"Services"
        }
    ],
    "sg:phone":"+32 2 203 46 59",
    "sg:postcode":"1000",
    "sg:province":"Bruxelles-Capitale",
    "sg:tags":[
        "telephony"
    ],
    "wof:name":"Radio Service Asselman R",
    "wof:placetype":"venue"
},
  "geometry": {"coordinates":[4.3559699059,50.865562439],"type":"Point"}
}