{
  "type": "Feature",
  "properties": {
    "iso:country":"BE",
    "sg:address":"Melkstraat 100",
    "sg:city":"Machelen",
    "sg:classifiers":[
        {
            "category":"Fast Food",
            "type":"Food & Drink"
        }
    ],
    "sg:phone":"+32 2 251 25 19",
    "sg:postcode":"1830",
    "sg:province":"Vlaams-Brabant",
    "sg:tags":[
        "meeneem",
        "restaurant"
    ],
    "wof:name":"Restaurant De Molen",
    "wof:placetype":"venue"
},
  "geometry": {"coordinates":[4.4364538193,50.9052619934],"type":"Point"}
}