{
  "type": "Feature",
  "properties": {
    "addr:full":"Rue De Huy 27 Villers-le-bouillet Li\u00e8ge 4530",
    "addr:housenumber":"27",
    "addr:postcode":"4530",
    "addr:street":"Rue De Huy",
    "iso:country":"BE",
    "sg:address":"Rue De Huy 27",
    "sg:city":"Villers-le-bouillet",
    "sg:orig_category":"Herstellingen and onderhoud van auto's",
    "sg:phone":"+32 85 21 35 01",
    "sg:postcode":"4530",
    "sg:province":"Li\u00e8ge",
    "wof:name":"F. Riga",
    "wof:placetype":"venue"
},
  "geometry": {"coordinates":[5.2679867744,50.5636787415],"type":"Point"}
}