{
  "type": "Feature",
  "properties": {
    "iso:country":"BE",
    "sg:address":"Boulevard Leopold-iii 19",
    "sg:city":"Schaarbeek/schaerbeek",
    "sg:orig_category":"R\u00e9paration and restauration de meubles",
    "sg:phone":"+32 2 705 75 84",
    "sg:postcode":"1030",
    "sg:province":"Bruxelles-Capitale",
    "wof:name":"De Jonge D\u00c9cor",
    "wof:placetype":"venue"
},
  "geometry": {"coordinates":[4.3992972374,50.8579330444],"type":"Point"}
}