{
  "type": "Feature",
  "properties": {
    "iso:country":"BE",
    "sg:address":"Vital Decosterstraat 89b42",
    "sg:city":"Leuven",
    "sg:orig_category":"Advocaten and juridische adviseurs",
    "sg:phone":"+32 16 22 08 90",
    "sg:postcode":"3000",
    "sg:province":"Vlaams-Brabant",
    "wof:name":"Dominique Pignolet",
    "wof:placetype":"venue"
},
  "geometry": {"coordinates":[4.7015500069,50.8828544617],"type":"Point"}
}