{
  "type": "Feature",
  "properties": {
    "iso:country":"BE",
    "sg:address":"Rue Des Halles 252",
    "sg:city":"Florennes",
    "sg:orig_category":"Epiceries",
    "sg:phone":"+32 71 68 70 81",
    "sg:postcode":"5621",
    "sg:province":"Namur",
    "wof:name":"Epicerie Des Halles",
    "wof:placetype":"venue"
},
  "geometry": {"coordinates":[4.5644140244,50.2771034241],"type":"Point"}
}