{
  "type": "Feature",
  "properties": {
    "addr:full":"Rue Des Coquelicots 12 Chaudfontaine Li\u00e8ge 4053",
    "addr:housenumber":"12",
    "addr:postcode":"4053",
    "addr:street":"Rue Des Coquelicots",
    "iso:country":"BE",
    "sg:address":"Rue Des Coquelicots 12",
    "sg:city":"Chaudfontaine",
    "sg:orig_category":"Enseignement maternel and primaire",
    "sg:phone":"+32 4 365 75 06",
    "sg:postcode":"4053",
    "sg:province":"Li\u00e8ge",
    "wof:name":"E.p.l. Notre-dame",
    "wof:placetype":"venue"
},
  "geometry": {"coordinates":[5.6211681366,50.5996818542],"type":"Point"}
}