{
  "type": "Feature",
  "properties": {
    "iso:country":"BE",
    "sg:address":"Smetledesteenweg 222",
    "sg:city":"Wetteren",
    "sg:orig_category":"P\u00e9pini\u00e9ristes",
    "sg:phone":"+32 9 369 03 56",
    "sg:postcode":"9230",
    "sg:province":"Oost-Vlaanderen",
    "wof:name":"Jozef Sleeuwaert",
    "wof:placetype":"venue"
},
  "geometry": {"coordinates":[3.9058549404,50.9816970825],"type":"Point"}
}