{
  "type": "Feature",
  "properties": {
    "addr:full":"Rue De Flandre 201 Brussel/bruxelles Bruxelles-Capitale 1000",
    "addr:housenumber":"201",
    "addr:postcode":"1000",
    "addr:street":"Rue De Flandre;/",
    "iso:country":"BE",
    "sg:address":"Rue De Flandre 201",
    "sg:city":"Brussel/bruxelles",
    "sg:classifiers":[
        {
            "category":"Cafe",
            "type":"Food & Drink"
        }
    ],
    "sg:phone":"+32 2 223 58 97",
    "sg:postcode":"1000",
    "sg:province":"Bruxelles-Capitale",
    "sg:tags":[
        "caf\u00e9s"
    ],
    "wof:name":"Caf\u00c9 Morjane",
    "wof:placetype":"venue"
},
  "geometry": {"coordinates":[4.341588974,50.8532218933],"type":"Point"}
}