{
  "type": "Feature",
  "properties": {
    "addr:full":"Vitseroelstraat 12 Ternat Vlaams-Brabant 1740",
    "addr:housenumber":"12",
    "addr:postcode":"1740",
    "addr:street":"Vitseroelstraat",
    "iso:country":"BE",
    "sg:address":"Vitseroelstraat 12",
    "sg:city":"Ternat",
    "sg:orig_category":"Pleisterwerk Woningbouw",
    "sg:phone":"+32 2 453 90 70",
    "sg:postcode":"1740",
    "sg:province":"Vlaams-Brabant",
    "wof:name":"Bajo Construct",
    "wof:placetype":"venue"
},
  "geometry": {"coordinates":[4.1915102005,50.8811683655],"type":"Point"}
}