{
  "type": "Feature",
  "properties": {
    "iso:country":"BE",
    "sg:address":"Mont 65ba",
    "sg:city":"Comblain-au-pont",
    "sg:classifiers":[
        {
            "category":"Insurance",
            "subcategory":"Insurance Agent",
            "type":"Services"
        }
    ],
    "sg:phone":"+32 4 369 35 43",
    "sg:postcode":"4170",
    "sg:province":"Li\u00e8ge",
    "sg:tags":[
        "verzekeringsmakelaars",
        "expert"
    ],
    "wof:name":"Mar\u00c9chal Assurances",
    "wof:placetype":"venue"
},
  "geometry": {"coordinates":[5.562792778,50.4852104187],"type":"Point"}
}