{
  "type": "Feature",
  "properties": {
    "addr:full":"Rue Champ De La Couronne 13 Brussel/bruxelles Bruxelles-Capitale 1020",
    "addr:housenumber":"13",
    "addr:postcode":"1020",
    "addr:street":"Rue Champ De La Couronne;/",
    "iso:country":"BE",
    "sg:address":"Rue Champ De La Couronne 13",
    "sg:city":"Brussel/bruxelles",
    "sg:classifiers":[
        {
            "category":"Building & Trades",
            "subcategory":"Plumbing",
            "type":"Services"
        }
    ],
    "sg:phone":"+32 2 479 20 91",
    "sg:postcode":"1020",
    "sg:province":"Bruxelles-Capitale",
    "sg:tags":[
        "diver",
        "commerce",
        "gr",
        "pour",
        "equipement"
    ],
    "wof:name":"Veg'etal",
    "wof:placetype":"venue"
},
  "geometry": {"coordinates":[4.350892067,50.8789749146],"type":"Point"}
}