{
  "type": "Feature",
  "properties": {
    "addr:full":"Rue De La Luzerne 43 Bruxelles (schaerbeek) Bruxelles-Capitale 1030",
    "addr:housenumber":"43",
    "addr:postcode":"1030",
    "addr:street":"Rue De La Luzerne",
    "iso:country":"BE",
    "sg:address":"Rue De La Luzerne 43",
    "sg:city":"Bruxelles (schaerbeek)",
    "sg:classifiers":[
        {
            "category":"Health Services",
            "subcategory":"Doctor",
            "type":"Services"
        }
    ],
    "sg:phone":"+32 2 732 51 99",
    "sg:postcode":"1030",
    "sg:province":"Bruxelles-Capitale",
    "sg:tags":[
        "medicinephysicians",
        "surgeon"
    ],
    "wof:name":"Eeckhout Emmanuel",
    "wof:placetype":"venue"
},
  "geometry": {"coordinates":[4.3929839134,50.8550338745],"type":"Point"}
}