{
  "type": "Feature",
  "properties": {
    "iso:country":"BE",
    "sg:address":"Av Des Wallons 49",
    "sg:city":"Waterloo",
    "sg:classifiers":[
        {
            "category":"Shopping",
            "subcategory":"Gifts & Souvenirs",
            "type":"Retail Goods"
        }
    ],
    "sg:phone":"+32 2 354 42 40",
    "sg:postcode":"1410",
    "sg:province":"Brabant Wallon",
    "sg:tags":[
        "product",
        "miscellaneous"
    ],
    "wof:name":"Symbiose International",
    "wof:placetype":"venue"
},
  "geometry": {"coordinates":[4.3980250359,50.7174263],"type":"Point"}
}