{
  "type": "Feature",
  "properties": {
    "iso:country":"BE",
    "sg:address":"Van Eycklaan 2",
    "sg:city":"De Pinte",
    "sg:classifiers":[
        {
            "category":"Personal",
            "subcategory":"Beauty Salon",
            "type":"Services"
        }
    ],
    "sg:phone":"+32 9 282 68 75",
    "sg:postcode":"9840",
    "sg:province":"Oost-Vlaanderen",
    "sg:tags":[
        "lady",
        "-",
        "hairdressing"
    ],
    "wof:name":"Rita's Hair Cv",
    "wof:placetype":"venue"
},
  "geometry": {"coordinates":[3.6410009861,50.994140625],"type":"Point"}
}