{
  "type": "Feature",
  "properties": {
    "addr:full":"Avenue De Cortenbergh 93 Bruxelles Bruxelles-Capitale 1000",
    "addr:housenumber":"93",
    "addr:postcode":"1000",
    "addr:street":"Avenue De Cortenbergh",
    "iso:country":"BE",
    "sg:address":"Avenue De Cortenbergh 93",
    "sg:city":"Bruxelles",
    "sg:classifiers":[
        {
            "category":"Professional",
            "subcategory":"Lawyer & Legal Services",
            "type":"Services"
        }
    ],
    "sg:phone":"+32 2 733 39 61",
    "sg:postcode":"1000",
    "sg:province":"Bruxelles-Capitale",
    "wof:name":"Staquet Jean",
    "wof:placetype":"venue"
},
  "geometry": {"coordinates":[4.3910918236,50.8453865051],"type":"Point"}
}