{
  "type": "Feature",
  "properties": {
    "iso:country":"BE",
    "sg:address":"Hendrik I Lei 127",
    "sg:city":"Vilvoorde",
    "sg:orig_category":"Voertuigen",
    "sg:phone":"+32 2 251 34 19",
    "sg:postcode":"1800",
    "sg:province":"Vlaams-Brabant",
    "wof:name":"Supercars",
    "wof:placetype":"venue"
},
  "geometry": {"coordinates":[4.430398941,50.9340057373],"type":"Point"}
}