{
  "type": "Feature",
  "properties": {
    "addr:full":"Moeskroensesteenweg 65 Box 2 Kortrijk (aalbeke) West-Vlaanderen 8511",
    "addr:housenumber":"65;2",
    "addr:postcode":"8511",
    "addr:street":"Moeskroensesteenweg;Box",
    "iso:country":"BE",
    "sg:address":"Moeskroensesteenweg 65 Box 2",
    "sg:city":"Kortrijk (aalbeke)",
    "sg:classifiers":[
        {
            "category":"Travel",
            "subcategory":"Travel Agent",
            "type":"Entertainment"
        }
    ],
    "sg:phone":"+32 56 42 62 61",
    "sg:postcode":"8511",
    "sg:province":"West-Vlaanderen",
    "sg:tags":[
        "agency"
    ],
    "wof:name":"Suntrips Bevekom",
    "wof:placetype":"venue"
},
  "geometry": {"coordinates":[3.2312619686,50.7791404724],"type":"Point"}
}