{
  "type": "Feature",
  "properties": {
    "iso:country":"BE",
    "sg:address":"Heibrugstraat 37",
    "sg:city":"Izegem",
    "sg:orig_category":"Transports routiers de marchandises",
    "sg:phone":"+32 51 30 33 35",
    "sg:postcode":"8870",
    "sg:province":"West-Vlaanderen",
    "wof:name":"Transport D'haene",
    "wof:placetype":"venue"
},
  "geometry": {"coordinates":[3.1941599846,50.916519165],"type":"Point"}
}