{
  "type": "Feature",
  "properties": {
    "addr:full":"Wegvoeringsstraat 64 Sint-niklaas Oost-Vlaanderen 9100",
    "addr:housenumber":"64",
    "addr:postcode":"9100",
    "addr:street":"Wegvoeringsstraat",
    "iso:country":"BE",
    "sg:address":"Wegvoeringsstraat 64",
    "sg:city":"Sint-niklaas",
    "sg:classifiers":[
        {
            "category":"Health Services",
            "subcategory":"Doctor",
            "type":"Services"
        }
    ],
    "sg:phone":"+32 3 766 61 58",
    "sg:postcode":"9100",
    "sg:province":"Oost-Vlaanderen",
    "sg:tags":[
        "medicinephysicians",
        "surgeon"
    ],
    "wof:name":"Lievens Serge",
    "wof:placetype":"venue"
},
  "geometry": {"coordinates":[4.1311712265,51.1717224121],"type":"Point"}
}