{
  "type": "Feature",
  "properties": {
    "addr:full":"Rue Saint-l\u00c9onard 225 Li\u00c8ge Li\u00e8ge 4000",
    "addr:housenumber":"225",
    "addr:postcode":"4000",
    "addr:street":"Rue Saint-Le\u0301Onard",
    "iso:country":"BE",
    "sg:address":"Rue Saint-l\u00c9onard 225",
    "sg:city":"Li\u00c8ge",
    "sg:orig_category":"Diverse zakelijke dienstverlening",
    "sg:phone":"+32 4 227 53 15",
    "sg:postcode":"4000",
    "sg:province":"Li\u00e8ge",
    "wof:name":"La Maison Bizzzarre",
    "wof:placetype":"venue"
},
  "geometry": {"coordinates":[5.5955600739,50.6509094238],"type":"Point"}
}