{
  "type": "Feature",
  "properties": {
    "iso:country":"BE",
    "sg:address":"Place Saint-pierre 11",
    "sg:city":"Tournai",
    "sg:classifiers":[
        {
            "category":"Home & Garden",
            "subcategory":"Household Appliances",
            "type":"Retail Goods"
        }
    ],
    "sg:phone":"+32 69 22 54 84",
    "sg:postcode":"7500",
    "sg:province":"Hainaut",
    "sg:tags":[
        "housewares",
        "-"
    ],
    "wof:name":"Maison Tellin",
    "wof:placetype":"venue"
},
  "geometry": {"coordinates":[3.3911969662,50.6065597534],"type":"Point"}
}