{
  "type": "Feature",
  "properties": {
    "addr:full":"Ren\u00e9 Sabbestraat 1 Waregem West-Vlaanderen 8790",
    "addr:housenumber":"1",
    "addr:postcode":"8790",
    "addr:street":"Rene\u0301 Sabbestraat",
    "iso:country":"BE",
    "sg:address":"Ren\u00e9 Sabbestraat 1",
    "sg:city":"Waregem",
    "sg:classifiers":[
        {
            "category":"Insurance",
            "subcategory":"Insurance Agent",
            "type":"Services"
        }
    ],
    "sg:phone":"+32 56 61 25 79",
    "sg:postcode":"8790",
    "sg:province":"West-Vlaanderen",
    "sg:tags":[
        "broker"
    ],
    "wof:name":"Hoorens-beulque Cie Bvba",
    "wof:placetype":"venue"
},
  "geometry": {"coordinates":[3.4219601154,50.8886108398],"type":"Point"}
}