{
  "type": "Feature",
  "properties": {
    "addr:full":"Rue Des Ecoles 56a Hotton Luxembourg 6990",
    "addr:housenumber":"56a",
    "addr:postcode":"6990",
    "addr:street":"Rue Des Ecoles",
    "iso:country":"BE",
    "sg:address":"Rue Des Ecoles 56a",
    "sg:city":"Hotton",
    "sg:classifiers":[
        {
            "category":"Government",
            "subcategory":"Department Of Motor Vehicles",
            "type":"Public Place"
        }
    ],
    "sg:phone":"+32 84 46 61 35",
    "sg:postcode":"6990",
    "sg:province":"Luxembourg",
    "sg:tags":[
        "planing",
        "wood",
        "sawing"
    ],
    "wof:name":"Hotton Bois-gralinger & Fils Sa",
    "wof:placetype":"venue"
},
  "geometry": {"coordinates":[5.4497270584,50.2708969116],"type":"Point"}
}