{
  "type": "Feature",
  "properties": {
    "addr:full":"Oude Tramweg 13 Bilzen Limburg 3740",
    "addr:housenumber":"13",
    "addr:postcode":"3740",
    "addr:street":"Oude Tramweg",
    "iso:country":"BE",
    "sg:address":"Oude Tramweg 13",
    "sg:city":"Bilzen",
    "sg:orig_category":"Fleurs and plantes",
    "sg:phone":"+32 89 41 43 62",
    "sg:postcode":"3740",
    "sg:province":"Limburg",
    "wof:name":"Mathijs Thijs",
    "wof:placetype":"venue"
},
  "geometry": {"coordinates":[5.5218749046,50.8961868286],"type":"Point"}
}