{
  "type": "Feature",
  "properties": {
    "addr:full":"Rue Du Rouge Clo\u00cetre 29 La Hulpe Brabant Wallon 1310",
    "addr:housenumber":"29",
    "addr:postcode":"1310",
    "addr:street":"Rue Du Rouge Cloi\u0302Tre",
    "iso:country":"BE",
    "sg:address":"Rue Du Rouge Clo\u00cetre 29",
    "sg:city":"La Hulpe",
    "sg:orig_category":"Boekhouders",
    "sg:phone":"+32 2 652 10 38",
    "sg:postcode":"1310",
    "sg:province":"Brabant Wallon",
    "wof:name":"Yves Roossens",
    "wof:placetype":"venue"
},
  "geometry": {"coordinates":[4.4919710159,50.7506828308],"type":"Point"}
}