{
  "type": "Feature",
  "properties": {
    "iso:country":"BE",
    "sg:address":"Rue Du Christ 90",
    "sg:city":"Mouscron",
    "sg:classifiers":[
        {
            "category":"Travel",
            "subcategory":"Travel Agent",
            "type":"Entertainment"
        }
    ],
    "sg:phone":"+32 56 84 31 38",
    "sg:postcode":"7700",
    "sg:province":"Hainaut",
    "sg:tags":[
        "agency"
    ],
    "wof:name":"Voyages Regis",
    "wof:placetype":"venue"
},
  "geometry": {"coordinates":[3.2055521011,50.743598938],"type":"Point"}
}