{
  "type": "Feature",
  "properties": {
    "iso:country":"BE",
    "sg:address":"Abelestraat 22",
    "sg:city":"Izegem",
    "sg:classifiers":[
        {
            "category":"Home & Garden",
            "subcategory":"Hardware",
            "type":"Retail Goods"
        }
    ],
    "sg:phone":"+32 51 31 90 31",
    "sg:postcode":"8870",
    "sg:province":"West-Vlaanderen",
    "sg:tags":[
        "gate",
        "opener",
        "door",
        "automatic"
    ],
    "wof:name":"Degelek",
    "wof:placetype":"venue"
},
  "geometry": {"coordinates":[3.1889810562,50.9225082397],"type":"Point"}
}