{
  "type": "Feature",
  "properties": {
    "addr:full":"Antwerpsesteenweg 282 Kapellen Antwerpen 2950",
    "addr:housenumber":"282",
    "addr:postcode":"2950",
    "addr:street":"Antwerpsesteenweg",
    "iso:country":"BE",
    "sg:address":"Antwerpsesteenweg 282",
    "sg:city":"Kapellen",
    "sg:classifiers":[
        {
            "category":"Autos & Motor Vehicles",
            "subcategory":"Fuel & Gas Station",
            "type":"Retail Goods"
        }
    ],
    "sg:phone":"+32 3 605 19 34",
    "sg:postcode":"2950",
    "sg:province":"Antwerpen",
    "sg:tags":[
        "stations-service",
        "carburants"
    ],
    "wof:name":"De Smet & Van Diest",
    "wof:placetype":"venue"
},
  "geometry": {"coordinates":[4.4370450974,51.3016738892],"type":"Point"}
}