{
  "type": "Feature",
  "properties": {
    "addr:full":"Doorniksestraat 31 Kortrijk West-Vlaanderen 8500",
    "addr:housenumber":"31",
    "addr:postcode":"8500",
    "addr:street":"Doorniksestraat",
    "iso:country":"BE",
    "sg:address":"Doorniksestraat 31",
    "sg:city":"Kortrijk",
    "sg:orig_category":"Dameskledingzaken",
    "sg:phone":"+32 56 20 42 14",
    "sg:postcode":"8500",
    "sg:province":"West-Vlaanderen",
    "wof:name":"Cache-cache",
    "wof:placetype":"venue"
},
  "geometry": {"coordinates":[3.2662210464,50.8270568848],"type":"Point"}
}