{
  "type": "Feature",
  "properties": {
    "iso:country":"BE",
    "sg:address":"Wateringstraat 60",
    "sg:city":"Bredene",
    "sg:classifiers":[
        {
            "category":"Building & Trades",
            "subcategory":"Construction",
            "type":"Services"
        }
    ],
    "sg:phone":"+32 59 32 43 62",
    "sg:postcode":"8450",
    "sg:province":"West-Vlaanderen",
    "sg:tags":[
        "carpenter"
    ],
    "wof:name":"Vanhoorne N",
    "wof:placetype":"venue"
},
  "geometry": {"coordinates":[2.9748289585,51.2313346863],"type":"Point"}
}