{
  "type": "Feature",
  "properties": {
    "addr:full":"Rijksweg 370 Maasmechelen Limburg 3630",
    "addr:housenumber":"370",
    "addr:postcode":"3630",
    "addr:street":"Rijksweg",
    "iso:country":"BE",
    "sg:address":"Rijksweg 370",
    "sg:city":"Maasmechelen",
    "sg:classifiers":[
        {
            "category":"Manufacturing",
            "subcategory":"Musical Instruments",
            "type":"Manufacturing & Wholesale Goods"
        }
    ],
    "sg:phone":"+32 89 76 41 45",
    "sg:postcode":"3630",
    "sg:province":"Limburg",
    "sg:tags":[
        "piano"
    ],
    "wof:name":"Piano's Driesen Bvba",
    "wof:placetype":"venue"
},
  "geometry": {"coordinates":[5.6964931488,50.9657211304],"type":"Point"}
}