{
  "type": "Feature",
  "properties": {
    "addr:full":"Dorp 41 Herselt 3170",
    "addr:housenumber":"41",
    "addr:postcode":"3170",
    "addr:street":"Dorp",
    "iso:country":"BE",
    "sg:address":"Dorp 41",
    "sg:city":"Herselt",
    "sg:classifiers":[
        {
            "category":"Banks & Credit Unions",
            "subcategory":"Bank",
            "type":"Services"
        }
    ],
    "sg:phone":"+32 14 54 56 23",
    "sg:postcode":"3170",
    "wof:name":"Gemeentekrediet",
    "wof:placetype":"venue"
},
  "geometry": {"coordinates":[4.8810811043,51.0524368286],"type":"Point"}
}