{
  "type": "Feature",
  "properties": {
    "iso:country":"BE",
    "sg:address":"Regentstraat 24",
    "sg:city":"Antwerpen",
    "sg:classifiers":[
        {
            "category":"Home & Garden",
            "subcategory":"Carpets & Floor Coverings",
            "type":"Retail Goods"
        }
    ],
    "sg:phone":"+32 3 272 42 84",
    "sg:postcode":"2060",
    "sg:province":"Antwerpen",
    "sg:tags":[
        "tile"
    ],
    "wof:name":"Gosselin H",
    "wof:placetype":"venue"
},
  "geometry": {"coordinates":[4.4286990166,51.2199554443],"type":"Point"}
}