{
  "type": "Feature",
  "properties": {
    "addr:full":"Teirlinckstraat 1 Eeklo Oost-Vlaanderen 9900",
    "addr:housenumber":"1",
    "addr:postcode":"9900",
    "addr:street":"Teirlinckstraat",
    "iso:country":"BE",
    "sg:address":"Teirlinckstraat 1",
    "sg:city":"Eeklo",
    "sg:classifiers":[
        {
            "category":"Parking",
            "subcategory":"Lot",
            "type":"Transportation"
        }
    ],
    "sg:phone":"+32 9 356 92 43",
    "sg:postcode":"9900",
    "sg:province":"Oost-Vlaanderen",
    "sg:tags":[
        "parking-places",
        "laying-out"
    ],
    "wof:name":"Avygro Bvba",
    "wof:placetype":"venue"
},
  "geometry": {"coordinates":[3.5668139458,51.1875343323],"type":"Point"}
}