{
  "type": "Feature",
  "properties": {
    "iso:country":"BE",
    "sg:address":"Rue Des Anciens Etangs 40",
    "sg:city":"Bruxelles",
    "sg:classifiers":[
        {
            "category":"Professional",
            "subcategory":"Computer Services",
            "type":"Services"
        }
    ],
    "sg:phone":"+32 53 70 61 26",
    "sg:postcode":"1190",
    "sg:province":"Bruxelles-Capitale",
    "sg:tags":[
        "informatics",
        "consulting"
    ],
    "wof:name":"Real Information Services Nv",
    "wof:placetype":"venue"
},
  "geometry": {"coordinates":[4.0455479622,50.9155235291],"type":"Point"}
}