{
  "type": "Feature",
  "properties": {
    "iso:country":"BE",
    "sg:address":"Mont Saint-martin 46",
    "sg:city":"Li\u00c8ge",
    "sg:orig_category":"Avocats and conseillers juridiques",
    "sg:phone":"+32 4 223 55 31",
    "sg:postcode":"4000",
    "sg:province":"Li\u00e8ge",
    "wof:name":"R. Thiry",
    "wof:placetype":"venue"
},
  "geometry": {"coordinates":[5.5655150414,50.6446495056],"type":"Point"}
}