{
  "type": "Feature",
  "properties": {
    "iso:country":"BE",
    "sg:address":"Molenweg 47",
    "sg:city":"Zonhoven",
    "sg:classifiers":[
        {
            "category":"Insurance",
            "subcategory":"Insurance Agent",
            "type":"Services"
        }
    ],
    "sg:phone":"+32 11 81 34 63",
    "sg:postcode":"3520",
    "sg:province":"Limburg",
    "sg:tags":[
        "verzekeringsmakelaars",
        "expert"
    ],
    "wof:name":"Kantoor Beysen",
    "wof:placetype":"venue"
},
  "geometry": {"coordinates":[5.4084467888,50.9879837036],"type":"Point"}
}