{
  "type": "Feature",
  "properties": {
    "addr:full":"Chauss\u00e9e De Nivel 351 Temploux Namur 5020",
    "addr:housenumber":"351",
    "addr:postcode":"5020",
    "addr:street":"Chausse\u0301E De Nivel",
    "iso:country":"BE",
    "sg:address":"Chauss\u00e9e De Nivel 351",
    "sg:city":"Temploux",
    "sg:classifiers":[
        {
            "category":"Wholesale",
            "subcategory":"Medical Equipment & Supplies",
            "type":"Manufacturing & Wholesale Goods"
        }
    ],
    "sg:phone":"+32 81 74 28 84",
    "sg:postcode":"5020",
    "sg:province":"Namur",
    "sg:tags":[
        "instrument",
        "health",
        "-",
        "precision"
    ],
    "wof:name":"Dorge Medic Sprl",
    "wof:placetype":"venue"
},
  "geometry": {"coordinates":[4.7544441223,50.4872703552],"type":"Point"}
}