{
  "type": "Feature",
  "properties": {
    "addr:full":"Rue Duribreu 2 Komen-waasten/comines-warneton Hainaut 7783",
    "addr:housenumber":"2;7783",
    "addr:street":"Rue Duribreu",
    "iso:country":"BE",
    "sg:address":"Rue Duribreu 2",
    "sg:city":"Komen-waasten/comines-warneton",
    "sg:classifiers":[
        {
            "category":"Personal",
            "subcategory":"Beauty Salon",
            "type":"Services"
        }
    ],
    "sg:phone":"+32 56 58 82 94",
    "sg:postcode":"7783",
    "sg:province":"Hainaut",
    "sg:tags":[
        "de",
        "coiffure"
    ],
    "wof:name":"J. Gaveele",
    "wof:placetype":"venue"
},
  "geometry": {"coordinates":[2.8828949928,50.7069244385],"type":"Point"}
}