{
  "type": "Feature",
  "properties": {
    "addr:full":"Chauss\u00c9e De Neerstalle 226 Vorst/forest Bruxelles-Capitale 1190",
    "addr:housenumber":"226",
    "addr:postcode":"1190",
    "addr:street":"Chausse\u0301E De Neerstalle;/ Forest",
    "iso:country":"BE",
    "sg:address":"Chauss\u00c9e De Neerstalle 226",
    "sg:city":"Vorst/forest",
    "sg:classifiers":[
        {
            "category":"Personal",
            "subcategory":"Beauty Salon",
            "type":"Services"
        }
    ],
    "sg:phone":"+32 2 376 44 16",
    "sg:postcode":"1190",
    "sg:province":"Bruxelles-Capitale",
    "sg:tags":[
        "de",
        "coiffure"
    ],
    "wof:name":"Mohamed Zarfani",
    "wof:placetype":"venue"
},
  "geometry": {"coordinates":[4.3149199486,50.8034172058],"type":"Point"}
}