{
  "type": "Feature",
  "properties": {
    "iso:country":"BE",
    "sg:address":"Energieweg 10",
    "sg:city":"Malle",
    "sg:orig_category":"Quincailleries. Travaux de pl\u00e2trage. Construction de maisons. Constructions r\u00e9sidentielles sp\u00e9cifiqu",
    "sg:phone":"+32 3 312 56 41",
    "sg:postcode":"2390",
    "sg:province":"Antwerpen",
    "wof:name":"Renbo",
    "wof:placetype":"venue"
},
  "geometry": {"coordinates":[4.7161388397,51.2935562134],"type":"Point"}
}