{
  "type": "Feature",
  "properties": {
    "iso:country":"BE",
    "sg:address":"Domien Craccostraat 40",
    "sg:city":"Roeselare",
    "sg:orig_category":"R\u00e9alisation de programmes and logiciels",
    "sg:phone":"+32 51 22 36 20",
    "sg:postcode":"8800",
    "sg:province":"West-Vlaanderen",
    "wof:name":"General Informat. Techno",
    "wof:placetype":"venue"
},
  "geometry": {"coordinates":[3.1054298878,50.942691803],"type":"Point"}
}