{
  "type": "Feature",
  "properties": {
    "addr:full":"Rue Des Hetres 23 Linkebeek/linkebeek Vlaams-Brabant 1630",
    "addr:housenumber":"23",
    "addr:postcode":"1630",
    "addr:street":"Rue Des Hetres",
    "iso:country":"BE",
    "sg:address":"Rue Des Hetres 23",
    "sg:city":"Linkebeek/linkebeek",
    "sg:classifiers":[
        {
            "category":"Health Services",
            "subcategory":"Nursing And Care Facility",
            "type":"Services"
        }
    ],
    "sg:phone":"+32 2 380 69 23",
    "sg:postcode":"1630",
    "sg:province":"Vlaams-Brabant",
    "sg:tags":[
        "public"
    ],
    "wof:name":"O.c.m.w.",
    "wof:placetype":"venue"
},
  "geometry": {"coordinates":[4.3256959915,50.770866394],"type":"Point"}
}