{
  "type": "Feature",
  "properties": {
    "addr:full":"Brugsesteenweg 324 Roeselare West-Vlaanderen 8800",
    "addr:housenumber":"324",
    "addr:postcode":"8800",
    "addr:street":"Brugsesteenweg",
    "iso:country":"BE",
    "sg:address":"Brugsesteenweg 324",
    "sg:city":"Roeselare",
    "sg:orig_category":"Immobili\u00ebnkantoren",
    "sg:phone":"+32 51 22 01 58",
    "sg:postcode":"8800",
    "sg:province":"West-Vlaanderen",
    "wof:name":"Daja",
    "wof:placetype":"venue"
},
  "geometry": {"coordinates":[3.1207549572,50.9650039673],"type":"Point"}
}