{
  "type": "Feature",
  "properties": {
    "iso:country":"BE",
    "sg:address":"Vrijwilligerslaan 15",
    "sg:city":"Zelzate",
    "sg:classifiers":[
        {
            "category":"Cafe",
            "type":"Food & Drink"
        }
    ],
    "sg:phone":"+32 9 344 60 55",
    "sg:postcode":"9060",
    "sg:province":"Oost-Vlaanderen",
    "sg:tags":[
        "caf\u00e9s"
    ],
    "wof:name":"Caf\u00c9 Rita",
    "wof:placetype":"venue"
},
  "geometry": {"coordinates":[3.7930510044,51.19090271],"type":"Point"}
}