{
  "type": "Feature",
  "properties": {
    "addr:full":"Zevenbergenlaan 3 Ranst Antwerpen 2520",
    "addr:housenumber":"3",
    "addr:postcode":"2520",
    "addr:street":"Zevenbergenlaan",
    "iso:country":"BE",
    "sg:address":"Zevenbergenlaan 3",
    "sg:city":"Ranst",
    "sg:classifiers":[
        {
            "category":"Structure",
            "subcategory":"Office Building",
            "type":"Public Place"
        }
    ],
    "sg:phone":"+32 3 485 61 12",
    "sg:postcode":"2520",
    "sg:province":"Antwerpen",
    "sg:tags":[
        "drawing"
    ],
    "wof:name":"Jorens L",
    "wof:placetype":"venue"
},
  "geometry": {"coordinates":[4.5605049133,51.192237854],"type":"Point"}
}