{
  "type": "Feature",
  "properties": {
    "addr:full":"Dorpsstraat 52 Bocholt Limburg 3950",
    "addr:housenumber":"52",
    "addr:postcode":"3950",
    "addr:street":"Dorpsstraat",
    "iso:country":"BE",
    "sg:address":"Dorpsstraat 52",
    "sg:city":"Bocholt",
    "sg:orig_category":"S\u00e9curit\u00e9 sociale",
    "sg:phone":"+32 11 44 72 25",
    "sg:postcode":"3950",
    "sg:province":"Limburg",
    "wof:name":"De Voorzorg",
    "wof:placetype":"venue"
},
  "geometry": {"coordinates":[5.5809221268,51.1706008911],"type":"Point"}
}