{
  "type": "Feature",
  "properties": {
    "iso:country":"BE",
    "sg:address":"De Stropersstraat 12",
    "sg:city":"Stekene (kemzeke)",
    "sg:classifiers":[
        {
            "category":"Retail",
            "subcategory":"Laundry & Dry Cleaning",
            "type":"Services"
        }
    ],
    "sg:phone":"+32 3 770 71 54",
    "sg:postcode":"9190",
    "sg:province":"Oost-Vlaanderen",
    "sg:tags":[
        "dyer",
        "cleaner"
    ],
    "wof:name":"Edelwit",
    "wof:placetype":"venue"
},
  "geometry": {"coordinates":[4.0644378662,51.2469024658],"type":"Point"}
}