{
  "type": "Feature",
  "properties": {
    "addr:full":"Ooststraat 3 Veurne West-Vlaanderen 8630",
    "addr:housenumber":"3",
    "addr:postcode":"8630",
    "addr:street":"Ooststraat",
    "iso:country":"BE",
    "sg:address":"Ooststraat 3",
    "sg:city":"Veurne",
    "sg:orig_category":"Banques and organismes de cr\u00e9dit",
    "sg:phone":"+32 58 31 10 34",
    "sg:postcode":"8630",
    "sg:province":"West-Vlaanderen",
    "wof:name":"Fortis",
    "wof:placetype":"venue"
},
  "geometry": {"coordinates":[2.6627779007,51.0725860596],"type":"Point"}
}