{
  "type": "Feature",
  "properties": {
    "iso:country":"BE",
    "sg:address":"Chaussee De Namur 99",
    "sg:city":"Nivelles",
    "sg:orig_category":"Laser Printer Accessories",
    "sg:phone":"+32 67 84 06 08",
    "sg:postcode":"1400",
    "sg:province":"Brabant Wallon",
    "wof:name":"Pro-form S.p.r.l.",
    "wof:placetype":"venue"
},
  "geometry": {"coordinates":[4.3289790154,50.5994491577],"type":"Point"}
}