{
  "type": "Feature",
  "properties": {
    "iso:country":"BE",
    "sg:address":"Avenue Du Pont Rouge 11",
    "sg:city":"Mons",
    "sg:classifiers":[
        {
            "category":"Health Services",
            "subcategory":"Dentist",
            "type":"Services"
        }
    ],
    "sg:phone":"+32 65 36 15 27",
    "sg:postcode":"7000",
    "sg:province":"Hainaut",
    "wof:name":"Hacquin J",
    "wof:placetype":"venue"
},
  "geometry": {"coordinates":[3.9593060017,50.4495162964],"type":"Point"}
}