{
  "type": "Feature",
  "properties": {
    "addr:full":"Staatsbaan 58 Halen Limburg 3545",
    "addr:housenumber":"58",
    "addr:postcode":"3545",
    "addr:street":"Staatsbaan",
    "iso:country":"BE",
    "sg:address":"Staatsbaan 58",
    "sg:city":"Halen",
    "sg:classifiers":[
        {
            "category":"Professional",
            "type":"Services"
        }
    ],
    "sg:phone":"+32 13 33 89 25",
    "sg:postcode":"3545",
    "sg:province":"Limburg",
    "sg:tags":[
        "auction",
        "room"
    ],
    "wof:name":"Mervanco Bvba",
    "wof:placetype":"venue"
},
  "geometry": {"coordinates":[5.0964207649,50.9554214478],"type":"Point"}
}