{
  "type": "Feature",
  "properties": {
    "iso:country":"BE",
    "sg:address":"Rue Georges Simenon 7",
    "sg:city":"Li\u00c8ge",
    "sg:orig_category":"Etalage- and showroomontwerpers Installatie van houten of kunststof schrijnwerk",
    "sg:phone":"+32 4 343 40 69",
    "sg:postcode":"4020",
    "sg:province":"Li\u00e8ge",
    "wof:name":"Ets. Milles",
    "wof:placetype":"venue"
},
  "geometry": {"coordinates":[5.5843019485,50.6418075562],"type":"Point"}
}