{
  "type": "Feature",
  "properties": {
    "addr:full":"Rue De La Halle 39 Mons Hainaut 7000",
    "addr:housenumber":"39",
    "addr:postcode":"7000",
    "addr:street":"Rue De La Halle;Hainaut",
    "iso:country":"BE",
    "sg:address":"Rue De La Halle 39",
    "sg:city":"Mons",
    "sg:orig_category":"Banken and kredietinstellingen",
    "sg:phone":"+32 65 34 63 30",
    "sg:postcode":"7000",
    "sg:province":"Hainaut",
    "wof:name":"Ippa",
    "wof:placetype":"venue"
},
  "geometry": {"coordinates":[3.9539439678,50.4507446289],"type":"Point"}
}