{
  "type": "Feature",
  "properties": {
    "iso:country":"BE",
    "sg:address":"Dorp 35",
    "sg:city":"Zandhoven",
    "sg:orig_category":"Salles de conf\u00e9rences and de r\u00e9ceptions. Alimentation sp\u00e9cialis\u00e9e",
    "sg:phone":"+32 3 464 04 05",
    "sg:postcode":"2242",
    "sg:province":"Antwerpen",
    "wof:name":"Pulderhof",
    "wof:placetype":"venue"
},
  "geometry": {"coordinates":[4.6916651726,51.2182121277],"type":"Point"}
}