{
  "type": "Feature",
  "properties": {
    "addr:full":"Simarstrasse 36 Eupen/eupen Li\u00e8ge 4700",
    "addr:housenumber":"36",
    "addr:postcode":"4700",
    "addr:street":"Simarstrasse",
    "iso:country":"BE",
    "sg:address":"Simarstrasse 36",
    "sg:city":"Eupen/eupen",
    "sg:orig_category":"Woningbouw",
    "sg:phone":"+32 87 59 14 50",
    "sg:postcode":"4700",
    "sg:province":"Li\u00e8ge",
    "wof:name":"Convents J./convents Jean",
    "wof:placetype":"venue"
},
  "geometry": {"coordinates":[6.0287480354,50.6349105835],"type":"Point"}
}