{
  "type": "Feature",
  "properties": {
    "iso:country":"BE",
    "sg:address":"Sint-antoniusstraat 29ba",
    "sg:city":"Zele",
    "sg:classifiers":[
        {
            "category":"Cafe",
            "type":"Food & Drink"
        }
    ],
    "sg:phone":"+32 52 44 60 85",
    "sg:postcode":"9240",
    "sg:province":"Oost-Vlaanderen",
    "sg:tags":[
        "caf\u00e9s"
    ],
    "wof:name":"Camillus Van Extergem",
    "wof:placetype":"venue"
},
  "geometry": {"coordinates":[4.0509138107,51.0667495728],"type":"Point"}
}