{
  "type": "Feature",
  "properties": {
    "iso:country":"BE",
    "sg:address":"Beneluxlaan 26",
    "sg:city":"Harelbeke",
    "sg:orig_category":"Pain, p\u00e2tisseries and confiseries",
    "sg:phone":"+32 56 21 63 22",
    "sg:postcode":"8530",
    "sg:province":"West-Vlaanderen",
    "wof:name":"Gaverbrood",
    "wof:placetype":"venue"
},
  "geometry": {"coordinates":[3.3156280518,50.8354110718],"type":"Point"}
}