{
  "type": "Feature",
  "properties": {
    "addr:full":"Heikant 13 Hamont-achel (achel) Limburg 3930",
    "addr:housenumber":"13",
    "addr:postcode":"3930",
    "addr:street":"Heikant",
    "iso:country":"BE",
    "sg:address":"Heikant 13",
    "sg:city":"Hamont-achel (achel)",
    "sg:classifiers":[
        {
            "category":"Autos & Motor Vehicles",
            "subcategory":"Boat Sales",
            "type":"Retail Goods"
        }
    ],
    "sg:phone":"+32 11 80 02 80",
    "sg:postcode":"3930",
    "sg:province":"Limburg",
    "sg:tags":[
        "automobile",
        "racing",
        "accessory"
    ],
    "wof:name":"Vit-rts Nv",
    "wof:placetype":"venue"
},
  "geometry": {"coordinates":[5.4707150459,51.276725769],"type":"Point"}
}