{
  "type": "Feature",
  "properties": {
    "iso:country":"BE",
    "sg:address":"Kalkoven 6",
    "sg:city":"Asse",
    "sg:classifiers":[
        {
            "category":"Cafe",
            "type":"Food & Drink"
        }
    ],
    "sg:phone":"+32 2 452 39 20",
    "sg:postcode":"1730",
    "sg:province":"Vlaams-Brabant",
    "sg:tags":[
        "caf\u00e9s"
    ],
    "wof:name":"Caf\u00c9 Klaverke Vier",
    "wof:placetype":"venue"
},
  "geometry": {"coordinates":[4.19622612,50.912273407],"type":"Point"}
}