{
  "type": "Feature",
  "properties": {
    "iso:country":"BE",
    "sg:address":"Kapelstraat 106",
    "sg:city":"Heusden-zolder",
    "sg:orig_category":"SMEEDWERK, METAALBEWERKING AND POEDERMETALLURGIE",
    "sg:phone":"+32 11 43 37 26",
    "sg:postcode":"3550",
    "sg:province":"Limburg",
    "wof:name":"Cuppers Jos Metaalwerken",
    "wof:placetype":"venue"
},
  "geometry": {"coordinates":[5.2694997787,51.0331573486],"type":"Point"}
}