{
  "type": "Feature",
  "properties": {
    "addr:full":"Vlaanderenstraat 36 Kortrijk West-Vlaanderen 8500",
    "addr:housenumber":"36",
    "addr:postcode":"8500",
    "addr:street":"Vlaanderenstraat",
    "iso:country":"BE",
    "sg:address":"Vlaanderenstraat 36",
    "sg:city":"Kortrijk",
    "sg:classifiers":[
        {
            "category":"Cafe",
            "type":"Food & Drink"
        }
    ],
    "sg:phone":"+32 56 35 35 44",
    "sg:postcode":"8500",
    "sg:province":"West-Vlaanderen",
    "sg:tags":[
        "caf\u00e9s"
    ],
    "wof:name":"Caf\u00c9 Century",
    "wof:placetype":"venue"
},
  "geometry": {"coordinates":[3.2714400291,50.834148407],"type":"Point"}
}