{
  "type": "Feature",
  "properties": {
    "iso:country":"BE",
    "sg:address":"Hernestraat 6",
    "sg:city":"Edingen/enghien",
    "sg:orig_category":"Plaatsen van vloer- and muurbekleding Schilders Verlichting and huishoudartikelen",
    "sg:phone":"+32 2 395 39 03",
    "sg:postcode":"7850",
    "sg:province":"Hainaut",
    "wof:name":"Lambert",
    "wof:placetype":"venue"
},
  "geometry": {"coordinates":[4.0391359329,50.6935997009],"type":"Point"}
}