{
  "type": "Feature",
  "properties": {
    "addr:full":"Nieuwstraat 84 Westerlo Antwerpen 2260",
    "addr:housenumber":"84",
    "addr:postcode":"2260",
    "addr:street":"Nieuwstraat",
    "iso:country":"BE",
    "sg:address":"Nieuwstraat 84",
    "sg:city":"Westerlo",
    "sg:orig_category":"Installation \u00e9lectrique r\u00e9sidentielle",
    "sg:phone":"+32 14 54 78 68",
    "sg:postcode":"2260",
    "sg:province":"Antwerpen",
    "wof:name":"Tom Pauwels",
    "wof:placetype":"venue"
},
  "geometry": {"coordinates":[4.9115948677,51.085899353],"type":"Point"}
}