{
  "type": "Feature",
  "properties": {
    "iso:country":"BE",
    "sg:address":"Rue Des Raines 96",
    "sg:city":"Verviers",
    "sg:classifiers":[
        {
            "category":"Building & Trades",
            "subcategory":"Electrical",
            "type":"Services"
        }
    ],
    "sg:phone":"+32 87 31 74 57",
    "sg:postcode":"4800",
    "sg:province":"Li\u00e8ge",
    "sg:tags":[
        "-",
        "electric",
        "contractor"
    ],
    "wof:name":"Fairon R-g",
    "wof:placetype":"venue"
},
  "geometry": {"coordinates":[5.8659601212,50.5946388245],"type":"Point"}
}