{
  "type": "Feature",
  "properties": {
    "iso:country":"BE",
    "sg:address":"Bruggestraat 23",
    "sg:city":"Menen",
    "sg:classifiers":[
        {
            "category":"Bars & Pubs",
            "type":"Food & Drink"
        }
    ],
    "sg:phone":"+32 56 51 59 04",
    "sg:postcode":"8930",
    "sg:province":"West-Vlaanderen",
    "wof:name":"Kerpel (de)",
    "wof:placetype":"venue"
},
  "geometry": {"coordinates":[3.1219050884,50.796875],"type":"Point"}
}