{
  "type": "Feature",
  "properties": {
    "addr:full":"Avenue Joseph Abras 83 Namur Namur 5001",
    "addr:housenumber":"83",
    "addr:postcode":"5001",
    "addr:street":"Avenue Joseph Abras",
    "iso:country":"BE",
    "sg:address":"Avenue Joseph Abras 83",
    "sg:city":"Namur",
    "sg:orig_category":"Plomberie, chauffage and installations sanitaires",
    "sg:phone":"+32 81 73 59 90",
    "sg:postcode":"5001",
    "sg:province":"Namur",
    "wof:name":"Yuksek Faik",
    "wof:placetype":"venue"
},
  "geometry": {"coordinates":[4.8257050514,50.4722557068],"type":"Point"}
}