{
  "type": "Feature",
  "properties": {
    "addr:full":"Koerselsesteenweg 54 Beringen Limburg 3580",
    "addr:housenumber":"54",
    "addr:postcode":"3580",
    "addr:street":"Koerselsesteenweg",
    "iso:country":"BE",
    "sg:address":"Koerselsesteenweg 54",
    "sg:city":"Beringen",
    "sg:orig_category":"M\u00e9decins and sp\u00e9cialistes",
    "sg:phone":"+32 11 42 54 94",
    "sg:postcode":"3580",
    "sg:province":"Limburg",
    "wof:name":"Eddy Cerstelotte",
    "wof:placetype":"venue"
},
  "geometry": {"coordinates":[5.2296299934,51.0498962402],"type":"Point"}
}