{
  "type": "Feature",
  "properties": {
    "iso:country":"BE",
    "sg:address":"Sint-amandsstraat 8",
    "sg:city":"Roeselare",
    "sg:orig_category":"Opticiens",
    "sg:phone":"+32 51 20 18 32",
    "sg:postcode":"8800",
    "sg:province":"West-Vlaanderen",
    "wof:name":"Optiek Hoet-van Heghe",
    "wof:placetype":"venue"
},
  "geometry": {"coordinates":[3.1221349239,50.9478797913],"type":"Point"}
}