{
  "type": "Feature",
  "properties": {
    "addr:full":"Boulevard Fulgence Masson 5 Mons Hainaut 7000",
    "addr:housenumber":"5",
    "addr:postcode":"7000",
    "addr:street":"Boulevard Fulgence Masson;Hainaut",
    "iso:country":"BE",
    "sg:address":"Boulevard Fulgence Masson 5",
    "sg:city":"Mons",
    "sg:classifiers":[
        {
            "category":"Social Services",
            "subcategory":"Child Care",
            "type":"Services"
        }
    ],
    "sg:phone":"+32 65 35 90 37",
    "sg:postcode":"7000",
    "sg:province":"Hainaut",
    "sg:tags":[
        "baby",
        "nursery",
        "day",
        "sitting"
    ],
    "wof:name":"Cr\u00e8che St-joseph",
    "wof:placetype":"venue"
},
  "geometry": {"coordinates":[3.9604730606,50.4553489685],"type":"Point"}
}