{
  "type": "Feature",
  "properties": {
    "iso:country":"BE",
    "sg:address":"Kleerkopersstraat 3",
    "sg:city":"Brussel/bruxelles",
    "sg:orig_category":"Boekhandels",
    "sg:phone":"+32 2 218 70 17",
    "sg:postcode":"1000",
    "sg:province":"Bruxelles-Capitale",
    "wof:name":"Maxi Livres",
    "wof:placetype":"venue"
},
  "geometry": {"coordinates":[4.3519310951,50.8483200073],"type":"Point"}
}