{
  "type": "Feature",
  "properties": {
    "addr:full":"Avenue De Tervuren 24 Bruxelles Bruxelles-Capitale 1040",
    "addr:housenumber":"24",
    "addr:postcode":"1040",
    "addr:street":"Avenue De Tervuren",
    "iso:country":"BE",
    "sg:address":"Avenue De Tervuren 24",
    "sg:city":"Bruxelles",
    "sg:orig_category":"H\u00f4tels",
    "sg:phone":"+32 2 733 75 81",
    "sg:postcode":"1040",
    "sg:province":"Bruxelles-Capitale",
    "wof:name":"Derby",
    "wof:placetype":"venue"
},
  "geometry": {"coordinates":[4.3994951248,50.83934021],"type":"Point"}
}