{
  "type": "Feature",
  "properties": {
    "iso:country":"BE",
    "sg:address":"Windhalmstraat 26",
    "sg:city":"Antwerpen",
    "sg:classifiers":[
        {
            "category":"Health Services",
            "subcategory":"Doctor",
            "type":"Services"
        }
    ],
    "sg:phone":"+32 3 568 83 97",
    "sg:postcode":"2040",
    "sg:province":"Antwerpen",
    "sg:tags":[
        "psychotherapist",
        "psychoanalyst"
    ],
    "wof:name":"Panta Rei Cvba",
    "wof:placetype":"venue"
},
  "geometry": {"coordinates":[4.3141150475,51.3429756165],"type":"Point"}
}