{
  "type": "Feature",
  "properties": {
    "iso:country":"BE",
    "sg:address":"Rue De Wanferc\u00c9e-baulet 121",
    "sg:city":"Fleurus",
    "sg:orig_category":"Epiceries",
    "sg:phone":"+32 71 81 65 70",
    "sg:postcode":"6224",
    "sg:province":"Hainaut",
    "wof:name":"Maria Deplano",
    "wof:placetype":"venue"
},
  "geometry": {"coordinates":[4.5621638298,50.4814300537],"type":"Point"}
}