{
  "type": "Feature",
  "properties": {
    "iso:country":"BE",
    "sg:address":"Oogststraat 18",
    "sg:city":"Kuurne",
    "sg:orig_category":"Houtbewerking and -behandeling",
    "sg:phone":"+32 56 71 48 21",
    "sg:postcode":"8520",
    "sg:province":"West-Vlaanderen",
    "wof:name":"Bernard Sabbe",
    "wof:placetype":"venue"
},
  "geometry": {"coordinates":[3.2881119251,50.8582649231],"type":"Point"}
}