{
  "type": "Feature",
  "properties": {
    "addr:full":"Rue Du Bois Gilles 15 Erquelinnes Hainaut 6560",
    "addr:housenumber":"15",
    "addr:postcode":"6560",
    "addr:street":"Rue Du Bois Gilles",
    "iso:country":"BE",
    "sg:address":"Rue Du Bois Gilles 15",
    "sg:city":"Erquelinnes",
    "sg:classifiers":[
        {
            "category":"Sports & Exercise",
            "subcategory":"Stables",
            "type":"Entertainment"
        }
    ],
    "sg:phone":"+32 475 63 40 21",
    "sg:postcode":"6560",
    "sg:province":"Hainaut",
    "sg:tags":[
        "riding",
        "school"
    ],
    "wof:name":"Manege Du Bois Gilles Sprl",
    "wof:placetype":"venue"
},
  "geometry": {"coordinates":[4.1038370132,50.3187522888],"type":"Point"}
}