{
  "type": "Feature",
  "properties": {
    "addr:full":"Heerstraat 33 Neerpelt Limburg 3910",
    "addr:housenumber":"33",
    "addr:postcode":"3910",
    "addr:street":"Heerstraat",
    "iso:country":"BE",
    "sg:address":"Heerstraat 33",
    "sg:city":"Neerpelt",
    "sg:classifiers":[
        {
            "category":"Health Services",
            "subcategory":"Health Practitioner",
            "type":"Services"
        }
    ],
    "sg:phone":"+32 11 64 58 53",
    "sg:postcode":"3910",
    "sg:province":"Limburg",
    "sg:tags":[
        "physiotherapist"
    ],
    "wof:name":"Straetemans-jutten Eliane",
    "wof:placetype":"venue"
},
  "geometry": {"coordinates":[5.4364829063,51.2293357849],"type":"Point"}
}