{
  "type": "Feature",
  "properties": {
    "addr:full":"Baudelostraat 32 Gent Oost-Vlaanderen 9000",
    "addr:housenumber":"32",
    "addr:postcode":"9000",
    "addr:street":"Baudelostraat;Oost-Vlaanderen",
    "iso:country":"BE",
    "sg:address":"Baudelostraat 32",
    "sg:city":"Gent",
    "sg:orig_category":"Studios photographiques",
    "sg:phone":"+32 9 225 94 15",
    "sg:postcode":"9000",
    "sg:province":"Oost-Vlaanderen",
    "wof:name":"Piet Maebe",
    "wof:placetype":"venue"
},
  "geometry": {"coordinates":[3.7272310257,51.0578384399],"type":"Point"}
}