{
  "type": "Feature",
  "properties": {
    "iso:country":"BE",
    "sg:address":"Place Gabrielle Petit 10-2",
    "sg:city":"Tournai",
    "sg:classifiers":[
        {
            "category":"Real Estate",
            "subcategory":"Architect",
            "type":"Services"
        }
    ],
    "sg:phone":"+32 69 21 07 04",
    "sg:postcode":"7500",
    "sg:province":"Hainaut",
    "wof:name":"Bethume P",
    "wof:placetype":"venue"
},
  "geometry": {"coordinates":[3.3967769146,50.6054573059],"type":"Point"}
}