{
  "type": "Feature",
  "properties": {
    "addr:full":"Rue G\u00c9n\u00c9ral De Gaulle 42 Courcelles Hainaut 6180",
    "addr:housenumber":"42",
    "addr:postcode":"6180",
    "addr:street":"Rue Ge\u0301Ne\u0301Ral De Gaulle",
    "iso:country":"BE",
    "sg:address":"Rue G\u00c9n\u00c9ral De Gaulle 42",
    "sg:city":"Courcelles",
    "sg:classifiers":[
        {
            "category":"Utilities",
            "subcategory":"Telephone",
            "type":"Services"
        }
    ],
    "sg:phone":"+32 71 46 55 42",
    "sg:postcode":"6180",
    "sg:province":"Hainaut",
    "sg:tags":[
        "house",
        "phone",
        "telecommunicatieapparaten"
    ],
    "wof:name":"The Phone House",
    "wof:placetype":"venue"
},
  "geometry": {"coordinates":[4.3796648979,50.4594955444],"type":"Point"}
}