{
  "type": "Feature",
  "properties": {
    "addr:full":"Rue De Fouron 57 Dalhem Li\u00e8ge 4607",
    "addr:housenumber":"57",
    "addr:postcode":"4607",
    "addr:street":"Rue De Fouron",
    "iso:country":"BE",
    "sg:address":"Rue De Fouron 57",
    "sg:city":"Dalhem",
    "sg:orig_category":"Producteurs de fruits. Fruits and l\u00e9gumes",
    "sg:phone":"+32 4 379 62 73",
    "sg:postcode":"4607",
    "sg:province":"Li\u00e8ge",
    "wof:name":"Camille Meyers",
    "wof:placetype":"venue"
},
  "geometry": {"coordinates":[5.7438988686,50.7477760315],"type":"Point"}
}