{
  "type": "Feature",
  "properties": {
    "addr:full":"Molenstraat 13 Heist-op-den-berg Antwerpen 2220",
    "addr:housenumber":"13",
    "addr:postcode":"2220",
    "addr:street":"Molenstraat",
    "iso:country":"BE",
    "sg:address":"Molenstraat 13",
    "sg:city":"Heist-op-den-berg",
    "sg:classifiers":[
        {
            "category":"Professional",
            "subcategory":"Lawyer & Legal Services",
            "type":"Services"
        }
    ],
    "sg:phone":"+32 15 33 01 41",
    "sg:postcode":"2220",
    "sg:province":"Antwerpen",
    "sg:tags":[
        "-",
        "foreign"
    ],
    "wof:name":"Wouters W",
    "wof:placetype":"venue"
},
  "geometry": {"coordinates":[4.7164039612,51.0780830383],"type":"Point"}
}