{
  "type": "Feature",
  "properties": {
    "addr:full":"Rue Du Bois Rosine 27 Modave (str\u00e9e-lez-huy) Li\u00e8ge 4577",
    "addr:housenumber":"27",
    "addr:postcode":"4577",
    "addr:street":"Rue Du Bois Rosine;Stre\u0301E-Lez-Huy",
    "iso:country":"BE",
    "sg:address":"Rue Du Bois Rosine 27",
    "sg:city":"Modave (str\u00e9e-lez-huy)",
    "sg:classifiers":[
        {
            "category":"Health Services",
            "subcategory":"Doctor",
            "type":"Services"
        }
    ],
    "sg:phone":"+32 85 51 25 34",
    "sg:postcode":"4577",
    "sg:province":"Li\u00e8ge",
    "sg:tags":[
        "medicinephysicians",
        "surgeon"
    ],
    "wof:name":"Huberlant Ph",
    "wof:placetype":"venue"
},
  "geometry": {"coordinates":[5.3267598152,50.4918899536],"type":"Point"}
}