{
  "type": "Feature",
  "properties": {
    "iso:country":"BE",
    "sg:address":"Weg Naar As 220",
    "sg:city":"Genk",
    "sg:classifiers":[
        {
            "category":"Restaurant",
            "type":"Food & Drink"
        }
    ],
    "sg:phone":"+32 89 36 75 65",
    "sg:postcode":"3600",
    "sg:province":"Limburg",
    "wof:name":"Alexandros",
    "wof:placetype":"venue"
},
  "geometry": {"coordinates":[5.5224561691,50.9756546021],"type":"Point"}
}