{
  "type": "Feature",
  "properties": {
    "addr:full":"Kanaaldijkstraat 4 Bilzen Limburg 3740",
    "addr:housenumber":"4",
    "addr:postcode":"3740",
    "addr:street":"Kanaaldijkstraat",
    "iso:country":"BE",
    "sg:address":"Kanaaldijkstraat 4",
    "sg:city":"Bilzen",
    "sg:orig_category":"Rundveehouders",
    "sg:phone":"+32 89 71 44 87",
    "sg:postcode":"3740",
    "sg:province":"Limburg",
    "wof:name":"Mathieu Valkenborg",
    "wof:placetype":"venue"
},
  "geometry": {"coordinates":[5.5733499527,50.8925209045],"type":"Point"}
}