{
  "type": "Feature",
  "properties": {
    "iso:country":"BE",
    "sg:address":"De-billemontstraat 47",
    "sg:city":"Geel",
    "sg:orig_category":"Installatie van houten of kunststof schrijnwerk",
    "sg:phone":"+32 14 58 02 28",
    "sg:postcode":"2440",
    "sg:province":"Antwerpen",
    "wof:name":"Huybrechts",
    "wof:placetype":"venue"
},
  "geometry": {"coordinates":[4.9973888397,51.1630935669],"type":"Point"}
}