{
  "type": "Feature",
  "properties": {
    "addr:full":"Berckhovenstraat 24 Malle (westmalle) Antwerpen 2390",
    "addr:housenumber":"24",
    "addr:postcode":"2390",
    "addr:street":"Berckhovenstraat",
    "iso:country":"BE",
    "sg:address":"Berckhovenstraat 24",
    "sg:city":"Malle (westmalle)",
    "sg:classifiers":[
        {
            "category":"Building & Trades",
            "subcategory":"Landscaping Services",
            "type":"Services"
        }
    ],
    "sg:phone":"+32 3 311 59 15",
    "sg:postcode":"2390",
    "sg:province":"Antwerpen",
    "sg:tags":[
        "gardening",
        "garden",
        "maintenance"
    ],
    "wof:name":"Philipsen",
    "wof:placetype":"venue"
},
  "geometry": {"coordinates":[4.6939549446,51.2967758179],"type":"Point"}
}