{
  "type": "Feature",
  "properties": {
    "addr:full":"Chemin De Royenne 95 Chaumont-gistoux Brabant Wallon 1325",
    "addr:housenumber":"95",
    "addr:postcode":"1325",
    "addr:street":"Chemin De Royenne",
    "iso:country":"BE",
    "sg:address":"Chemin De Royenne 95",
    "sg:city":"Chaumont-gistoux",
    "sg:orig_category":"Promoteurs immobiliers",
    "sg:phone":"+32 10 84 14 04",
    "sg:postcode":"1325",
    "sg:province":"Brabant Wallon",
    "wof:name":"Cogexim",
    "wof:placetype":"venue"
},
  "geometry": {"coordinates":[4.7223548889,50.6729545593],"type":"Point"}
}