{
  "type": "Feature",
  "properties": {
    "iso:country":"BE",
    "sg:address":"Blijstraat 6",
    "sg:city":"Kortenaken (waanrode)",
    "sg:classifiers":[
        {
            "category":"Retail",
            "subcategory":"Auto Repair",
            "type":"Services"
        }
    ],
    "sg:phone":"+32 16 77 77 16",
    "sg:postcode":"3473",
    "sg:province":"Vlaams-Brabant",
    "sg:tags":[
        "automobile-body"
    ],
    "wof:name":"Govaerts O & Zn Bvba",
    "wof:placetype":"venue"
},
  "geometry": {"coordinates":[5.0121870041,50.9144058228],"type":"Point"}
}