{
  "type": "Feature",
  "properties": {
    "addr:full":"Blocqmont 5 Yvoir Namur 5530",
    "addr:housenumber":"5",
    "addr:postcode":"5530",
    "addr:street":"Blocqmont",
    "iso:country":"BE",
    "sg:address":"Blocqmont 5",
    "sg:city":"Yvoir",
    "sg:orig_category":"Rundveehouders",
    "sg:phone":"+32 82 61 11 46",
    "sg:postcode":"5530",
    "sg:province":"Namur",
    "wof:name":"Jules Mailleux",
    "wof:placetype":"venue"
},
  "geometry": {"coordinates":[4.9199728966,50.3045883179],"type":"Point"}
}