{
  "type": "Feature",
  "properties": {
    "iso:country":"BE",
    "sg:address":"Sint-truidensesteenweg 63",
    "sg:city":"Tienen",
    "sg:orig_category":"Speciaalzaken",
    "sg:phone":"+32 16 81 60 10",
    "sg:postcode":"3300",
    "sg:province":"Vlaams-Brabant",
    "wof:name":"Ginorino",
    "wof:placetype":"venue"
},
  "geometry": {"coordinates":[4.9560689926,50.8007965088],"type":"Point"}
}