{
  "type": "Feature",
  "properties": {
    "addr:full":"Molendamstraat 15 Zedelgem West-Vlaanderen 8210",
    "addr:housenumber":"15",
    "addr:postcode":"8210",
    "addr:street":"Molendamstraat",
    "iso:country":"BE",
    "sg:address":"Molendamstraat 15",
    "sg:city":"Zedelgem",
    "sg:classifiers":[
        {
            "category":"Real Estate",
            "subcategory":"Architect",
            "type":"Services"
        }
    ],
    "sg:phone":"+32 50 20 06 80",
    "sg:postcode":"8210",
    "sg:province":"West-Vlaanderen",
    "wof:name":"Delrue G",
    "wof:placetype":"venue"
},
  "geometry": {"coordinates":[3.1445178986,51.125579834],"type":"Point"}
}