{
  "type": "Feature",
  "properties": {
    "addr:full":"Massestraat 41 Ternat Vlaams-Brabant 1741",
    "addr:housenumber":"41",
    "addr:postcode":"1741",
    "addr:street":"Massestraat",
    "iso:country":"BE",
    "sg:address":"Massestraat 41",
    "sg:city":"Ternat",
    "sg:classifiers":[
        {
            "category":"Insurance",
            "subcategory":"Life Insurance",
            "type":"Services"
        }
    ],
    "sg:phone":"+32 2 582 23 49",
    "sg:postcode":"1741",
    "sg:province":"Vlaams-Brabant",
    "sg:tags":[
        "assurance"
    ],
    "wof:name":"Fa. Mertens M. & Zn.",
    "wof:placetype":"venue"
},
  "geometry": {"coordinates":[4.1703400612,50.8482818604],"type":"Point"}
}