{
  "type": "Feature",
  "properties": {
    "iso:country":"BE",
    "sg:address":"Rue Derri\u00c8re Les Haies 5",
    "sg:city":"Quevy",
    "sg:orig_category":"Verplichte sociale verzekeringen",
    "sg:phone":"+32 65 56 87 75",
    "sg:postcode":"7041",
    "sg:province":"Hainaut",
    "wof:name":"Mutualit\u00c9 Libre",
    "wof:placetype":"venue"
},
  "geometry": {"coordinates":[3.9825189114,50.3617095947],"type":"Point"}
}