{
  "type": "Feature",
  "properties": {
    "addr:full":"Ch\u00canemont 11bb Genappe Brabant Wallon 1470",
    "addr:postcode":"1470",
    "addr:street":"Che\u0302Nemont 11Bb;Brabant Wallon",
    "iso:country":"BE",
    "sg:address":"Ch\u00canemont 11bb",
    "sg:city":"Genappe",
    "sg:orig_category":"Dierenartsen",
    "sg:phone":"+32 67 77 34 96",
    "sg:postcode":"1470",
    "sg:province":"Brabant Wallon",
    "wof:name":"Didier Serteyn",
    "wof:placetype":"venue"
},
  "geometry": {"coordinates":[4.4490060806,50.610458374],"type":"Point"}
}