{
  "type": "Feature",
  "properties": {
    "addr:full":"Rue Du Saucy 33 Namen Namur 5020",
    "addr:housenumber":"33",
    "addr:postcode":"5020",
    "addr:street":"Rue Du Saucy",
    "iso:country":"BE",
    "sg:address":"Rue Du Saucy 33",
    "sg:city":"Namen",
    "sg:classifiers":[
        {
            "category":"Building & Trades",
            "subcategory":"Plumbing",
            "type":"Services"
        }
    ],
    "sg:phone":"+32 71 78 10 57",
    "sg:postcode":"5020",
    "sg:province":"Namur",
    "sg:tags":[
        "diver",
        "commerce",
        "gr",
        "pour",
        "equipement"
    ],
    "wof:name":"Egelec",
    "wof:placetype":"venue"
},
  "geometry": {"coordinates":[4.7952418327,50.4352035522],"type":"Point"}
}