{
  "type": "Feature",
  "properties": {
    "iso:country":"BE",
    "sg:address":"Pannenhuisstraat 47",
    "sg:city":"Lier",
    "sg:classifiers":[
        {
            "category":"Arena",
            "subcategory":"Sports Club",
            "type":"Entertainment"
        }
    ],
    "sg:phone":"+32 3 489 00 24",
    "sg:postcode":"2500",
    "sg:province":"Antwerpen",
    "sg:tags":[
        "de"
    ],
    "wof:name":"Allitalliana",
    "wof:placetype":"venue"
},
  "geometry": {"coordinates":[4.5586051941,51.139793396],"type":"Point"}
}