{
  "type": "Feature",
  "properties": {
    "iso:country":"BE",
    "sg:address":"Sint-jorisstraat 30",
    "sg:city":"Beringen",
    "sg:classifiers":[
        {
            "category":"Shopping Center",
            "type":"Public Place"
        }
    ],
    "sg:phone":"+32 11 43 32 79",
    "sg:postcode":"3583",
    "sg:province":"Limburg",
    "sg:tags":[
        "enseignement",
        "formation"
    ],
    "wof:name":"Dominique Schreurs",
    "wof:placetype":"venue"
},
  "geometry": {"coordinates":[5.1523060799,51.0446968079],"type":"Point"}
}