{
  "type": "Feature",
  "properties": {
    "iso:country":"BE",
    "sg:address":"Willy Vandersteenplein 1",
    "sg:city":"Antwerpen",
    "sg:orig_category":"M\u00e9decins and sp\u00e9cialistes",
    "sg:phone":"+32 3 235 62 73",
    "sg:postcode":"2060",
    "sg:province":"Antwerpen",
    "wof:name":"Consultatiebur.jonge Kind",
    "wof:placetype":"venue"
},
  "geometry": {"coordinates":[4.4292378426,51.2179603577],"type":"Point"}
}