{
  "type": "Feature",
  "properties": {
    "addr:full":"Rue Lat\u00c9rale 8 Tournai Hainaut 7522",
    "addr:housenumber":"8",
    "addr:postcode":"7522",
    "addr:street":"Rue Late\u0301Rale",
    "iso:country":"BE",
    "sg:address":"Rue Lat\u00c9rale 8",
    "sg:city":"Tournai",
    "sg:orig_category":"Rundveehouders",
    "sg:phone":"+32 69 84 61 24",
    "sg:postcode":"7522",
    "sg:province":"Hainaut",
    "wof:name":"Rene Dekeyser",
    "wof:placetype":"venue"
},
  "geometry": {"coordinates":[3.3215820789,50.6052856445],"type":"Point"}
}