{
  "type": "Feature",
  "properties": {
    "iso:country":"BE",
    "sg:address":"Kruisstraat 14",
    "sg:city":"Zomergem",
    "sg:classifiers":[
        {
            "category":"Manufacturing",
            "subcategory":"Rubber & Plastics",
            "type":"Manufacturing & Wholesale Goods"
        }
    ],
    "sg:phone":"+32 9 372 88 94",
    "sg:postcode":"9930",
    "sg:province":"Oost-Vlaanderen",
    "wof:name":"Van Laecke J Nv",
    "wof:placetype":"venue"
},
  "geometry": {"coordinates":[3.5814869404,51.1116676331],"type":"Point"}
}