{
  "type": "Feature",
  "properties": {
    "iso:country":"BE",
    "sg:address":"Pastoor Mellaertsstraat 53a",
    "sg:city":"Heist-op-den-berg",
    "sg:classifiers":[
        {
            "category":"Personal",
            "subcategory":"Barber",
            "type":"Services"
        }
    ],
    "sg:phone":"+32 15 24 12 11",
    "sg:postcode":"2220",
    "sg:province":"Antwerpen",
    "sg:tags":[
        "gentleman",
        "salon",
        "-",
        "hairdressing"
    ],
    "wof:name":"Busschots J",
    "wof:placetype":"venue"
},
  "geometry": {"coordinates":[4.7191228867,51.0440101624],"type":"Point"}
}