{
  "type": "Feature",
  "properties": {
    "addr:full":"Tempeliersstraat 2 Nevele Oost-Vlaanderen 9850",
    "addr:housenumber":"2",
    "addr:postcode":"9850",
    "addr:street":"Tempeliersstraat",
    "iso:country":"BE",
    "sg:address":"Tempeliersstraat 2",
    "sg:city":"Nevele",
    "sg:classifiers":[
        {
            "category":"Wholesale",
            "subcategory":"Sporting Goods",
            "type":"Manufacturing & Wholesale Goods"
        }
    ],
    "sg:phone":"+32 9 371 96 35",
    "sg:postcode":"9850",
    "sg:province":"Oost-Vlaanderen",
    "sg:tags":[
        "sport-",
        "kampeermateriaal"
    ],
    "wof:name":"Equilux",
    "wof:placetype":"venue"
},
  "geometry": {"coordinates":[3.573570013,51.0397186279],"type":"Point"}
}