{
  "type": "Feature",
  "properties": {
    "addr:full":"Rue D'accolay 34 Brussel/bruxelles Bruxelles-Capitale 1000",
    "addr:housenumber":"34",
    "addr:postcode":"1000",
    "addr:street":"Rue D'Accolay;/",
    "iso:country":"BE",
    "sg:address":"Rue D'accolay 34",
    "sg:city":"Brussel/bruxelles",
    "sg:orig_category":"Architectes",
    "sg:phone":"+32 2 513 08 11",
    "sg:postcode":"1000",
    "sg:province":"Bruxelles-Capitale",
    "wof:name":"Renaud De Backer",
    "wof:placetype":"venue"
},
  "geometry": {"coordinates":[4.3507208824,50.8424682617],"type":"Point"}
}