{
  "type": "Feature",
  "properties": {
    "iso:country":"BE",
    "sg:address":"Viconiastraat 35",
    "sg:city":"Diksmuide",
    "sg:classifiers":[
        {
            "category":"Farming",
            "subcategory":"Farm & Veterinary Services",
            "type":"Manufacturing & Wholesale Goods"
        }
    ],
    "sg:phone":"+32 51 55 53 13",
    "sg:postcode":"8600",
    "sg:province":"West-Vlaanderen",
    "sg:tags":[
        "agricultural",
        "contractor"
    ],
    "wof:name":"Dewispelaere F",
    "wof:placetype":"venue"
},
  "geometry": {"coordinates":[2.8263199329,51.0577087402],"type":"Point"}
}