{
  "type": "Feature",
  "properties": {
    "iso:country":"BE",
    "sg:address":"Place De L'eglise 16",
    "sg:city":"Jalhay",
    "sg:orig_category":"Journaux. Tabac",
    "sg:phone":"+32 87 64 73 68",
    "sg:postcode":"4948",
    "wof:name":"Liliane De Jonge",
    "wof:placetype":"venue"
},
  "geometry": {"coordinates":[5.9652309418,50.5588912964],"type":"Point"}
}