{
  "type": "Feature",
  "properties": {
    "iso:country":"BE",
    "sg:address":"Gladiolenlaan 17",
    "sg:city":"Rumst",
    "sg:classifiers":[
        {
            "category":"Personal",
            "subcategory":"Piercing",
            "type":"Services"
        }
    ],
    "sg:phone":"+32 3 888 50 03",
    "sg:postcode":"2840",
    "sg:province":"Antwerpen",
    "sg:tags":[
        "piercings",
        "tatouages"
    ],
    "wof:name":"Tattoo Thierry",
    "wof:placetype":"venue"
},
  "geometry": {"coordinates":[4.3913397789,51.1062355042],"type":"Point"}
}