{
  "type": "Feature",
  "properties": {
    "iso:country":"BE",
    "sg:address":"Korenmarkt 55",
    "sg:city":"Mechelen",
    "sg:orig_category":"Gestion de portefeuilles and fortunes, conseils en placements. Assurances. Agences immobili\u00e8res",
    "sg:phone":"+32 15 41 12 83",
    "sg:postcode":"2800",
    "sg:province":"Antwerpen",
    "wof:name":"Simonis Joss & Co",
    "wof:placetype":"venue"
},
  "geometry": {"coordinates":[4.4756422043,51.0240325928],"type":"Point"}
}