{
  "type": "Feature",
  "properties": {
    "addr:full":"Doorniksewijk 114 Kortrijk West-Vlaanderen 8500",
    "addr:housenumber":"114",
    "addr:postcode":"8500",
    "iso:country":"BE",
    "sg:address":"Doorniksewijk 114",
    "sg:city":"Kortrijk",
    "sg:classifiers":[
        {
            "category":"Real Estate",
            "subcategory":"Real Estate Services",
            "type":"Services"
        }
    ],
    "sg:phone":"+32 56 20 07 35",
    "sg:postcode":"8500",
    "sg:province":"West-Vlaanderen",
    "wof:name":"Century 21 Immo Wooncentrum",
    "wof:placetype":"venue"
},
  "geometry": {"coordinates":[3.2690598965,50.8200149536],"type":"Point"}
}