{
  "type": "Feature",
  "properties": {
    "iso:country":"BE",
    "sg:address":"Paradijsstraat 3",
    "sg:city":"Brugge",
    "sg:orig_category":"Installatie van houten of kunststof schrijnwerk",
    "sg:phone":"+32 50 35 10 26",
    "sg:postcode":"8310",
    "sg:province":"West-Vlaanderen",
    "wof:name":"Verhelst",
    "wof:placetype":"venue"
},
  "geometry": {"coordinates":[3.2377970219,51.2184677124],"type":"Point"}
}