{
  "type": "Feature",
  "properties": {
    "addr:full":"Mechelsesteenweg 2009 Herent (veltem-beisem) Vlaams-Brabant 3020",
    "addr:postcode":"2009;3020",
    "addr:street":"Mechelsesteenweg",
    "iso:country":"BE",
    "sg:address":"Mechelsesteenweg 2009",
    "sg:city":"Herent (veltem-beisem)",
    "sg:classifiers":[
        {
            "category":"Building & Trades",
            "subcategory":"Landscaping Services",
            "type":"Services"
        }
    ],
    "sg:phone":"+32 16 60 50 81",
    "sg:postcode":"3020",
    "sg:province":"Vlaams-Brabant",
    "sg:tags":[
        "gardening",
        "garden",
        "maintenance"
    ],
    "wof:name":"Mannaerts R",
    "wof:placetype":"venue"
},
  "geometry": {"coordinates":[4.64812994,50.9203414917],"type":"Point"}
}