{
  "type": "Feature",
  "properties": {
    "addr:full":"Rue De La Broucheterre 52b Charleroi Hainaut 6000",
    "addr:housenumber":"52b",
    "addr:postcode":"6000",
    "addr:street":"Rue De La Broucheterre;Hainaut",
    "iso:country":"BE",
    "sg:address":"Rue De La Broucheterre 52b",
    "sg:city":"Charleroi",
    "sg:classifiers":[
        {
            "category":"Education",
            "subcategory":"School",
            "type":"Public Place"
        }
    ],
    "sg:phone":"+32 71 53 17 54",
    "sg:postcode":"6000",
    "sg:province":"Hainaut",
    "sg:tags":[
        "secondary"
    ],
    "wof:name":"Institut Jean Jaures",
    "wof:placetype":"venue"
},
  "geometry": {"coordinates":[4.4436597824,50.4198989868],"type":"Point"}
}