{
  "type": "Feature",
  "properties": {
    "iso:country":"BE",
    "sg:address":"Rue Mar\u00e9chal Foch 6",
    "sg:city":"Charleroi (roux)",
    "sg:classifiers":[
        {
            "category":"Shopping",
            "subcategory":"Books",
            "type":"Retail Goods"
        }
    ],
    "sg:phone":"+32 71 45 14 54",
    "sg:postcode":"6044",
    "sg:province":"Hainaut",
    "sg:tags":[
        "bookseller"
    ],
    "wof:name":"Siebenberger G",
    "wof:placetype":"venue"
},
  "geometry": {"coordinates":[4.3923840523,50.4408531189],"type":"Point"}
}