{
  "type": "Feature",
  "properties": {
    "addr:full":"Rijselstraat 251 Menen West-Vlaanderen 8930",
    "addr:housenumber":"251",
    "addr:postcode":"8930",
    "addr:street":"Rijselstraat",
    "iso:country":"BE",
    "sg:address":"Rijselstraat 251",
    "sg:city":"Menen",
    "sg:orig_category":"Jeux de hasard",
    "sg:phone":"+32 56 51 34 89",
    "sg:postcode":"8930",
    "sg:province":"West-Vlaanderen",
    "wof:name":"Ladbroke",
    "wof:placetype":"venue"
},
  "geometry": {"coordinates":[3.1267039776,50.7872848511],"type":"Point"}
}