{
  "type": "Feature",
  "properties": {
    "addr:full":"Komenseweg 78 Ieper West-Vlaanderen 8902",
    "addr:housenumber":"78",
    "addr:postcode":"8902",
    "addr:street":"Komenseweg",
    "iso:country":"BE",
    "sg:address":"Komenseweg 78",
    "sg:city":"Ieper",
    "sg:orig_category":"Eleveurs de bovins. Eleveurs and marchands de porcs",
    "sg:phone":"+32 57 20 39 72",
    "sg:postcode":"8902",
    "sg:province":"West-Vlaanderen",
    "wof:name":"Josephus Lierman",
    "wof:placetype":"venue"
},
  "geometry": {"coordinates":[2.9233870506,50.8233566284],"type":"Point"}
}