{
  "type": "Feature",
  "properties": {
    "addr:full":"Chauss\u00c9e De Charleroi 67b69 Gembloux Namur 5030",
    "addr:housenumber":"67b69",
    "addr:postcode":"5030",
    "addr:street":"Chausse\u0301E De Charleroi;Namur",
    "iso:country":"BE",
    "sg:address":"Chauss\u00c9e De Charleroi 67b69",
    "sg:city":"Gembloux",
    "sg:orig_category":"Plaatsen van vloer- and muurbekleding Schilders Vloer- and muurbekleding",
    "sg:phone":"+32 81 61 39 69",
    "sg:postcode":"5030",
    "sg:province":"Namur",
    "wof:name":"Id\u00c9al-d\u00c9cor",
    "wof:placetype":"venue"
},
  "geometry": {"coordinates":[4.6868457794,50.5637245178],"type":"Point"}
}