{
  "type": "Feature",
  "properties": {
    "iso:country":"BE",
    "sg:address":"Rue Cord\u00c9mont 17",
    "sg:city":"Juprelle",
    "sg:orig_category":"Overheidsdiensten",
    "sg:phone":"+32 4 278 58 48",
    "sg:postcode":"4450",
    "sg:province":"Li\u00e8ge",
    "wof:name":"C.p.a.s.",
    "wof:placetype":"venue"
},
  "geometry": {"coordinates":[5.527659893,50.7088737488],"type":"Point"}
}