{
  "type": "Feature",
  "properties": {
    "addr:full":"Britselei 1b7 Antwerpen Antwerpen 2000",
    "addr:housenumber":"1b7",
    "addr:postcode":"2000",
    "addr:street":"Britselei",
    "iso:country":"BE",
    "sg:address":"Britselei 1b7",
    "sg:city":"Antwerpen",
    "sg:orig_category":"Antiquit\u00e9s",
    "sg:phone":"+32 3 257 10 46",
    "sg:postcode":"2000",
    "sg:province":"Antwerpen",
    "wof:name":"Carl Suijkerbuijk",
    "wof:placetype":"venue"
},
  "geometry": {"coordinates":[4.407761097,51.2107810974],"type":"Point"}
}