{
  "type": "Feature",
  "properties": {
    "addr:full":"Rue De La Croix 17ba Welkenraedt Li\u00e8ge 4840",
    "addr:postcode":"4840",
    "addr:street":"Rue De La Croix 17Ba",
    "iso:country":"BE",
    "sg:address":"Rue De La Croix 17ba",
    "sg:city":"Welkenraedt",
    "sg:classifiers":[
        {
            "category":"Insurance",
            "subcategory":"Insurance Agent",
            "type":"Services"
        }
    ],
    "sg:phone":"+32 87 89 13 46",
    "sg:postcode":"4840",
    "sg:province":"Li\u00e8ge",
    "sg:tags":[
        "verzekeringsmakelaars",
        "expert"
    ],
    "wof:name":"Fe. Marchica",
    "wof:placetype":"venue"
},
  "geometry": {"coordinates":[5.9745850563,50.6641578674],"type":"Point"}
}