{
  "type": "Feature",
  "properties": {
    "addr:full":"Albert Servaeslaan 19 Waregem West-Vlaanderen 8790",
    "addr:housenumber":"19",
    "addr:postcode":"8790",
    "addr:street":"Albert Servaeslaan",
    "iso:country":"BE",
    "sg:address":"Albert Servaeslaan 19",
    "sg:city":"Waregem",
    "sg:orig_category":"Boissons",
    "sg:phone":"+32 56 60 27 79",
    "sg:postcode":"8790",
    "sg:province":"West-Vlaanderen",
    "wof:name":"Casa Do Porto-euroflor",
    "wof:placetype":"venue"
},
  "geometry": {"coordinates":[3.4431951046,50.892490387],"type":"Point"}
}