{
  "type": "Feature",
  "properties": {
    "addr:full":"Engelstraat 63-69 Ichtegem West-Vlaanderen 8480",
    "addr:postcode":"63-69;8480",
    "addr:street":"Engelstraat",
    "iso:country":"BE",
    "sg:address":"Engelstraat 63-69",
    "sg:city":"Ichtegem",
    "sg:classifiers":[
        {
            "category":"Shopping",
            "subcategory":"Gifts & Souvenirs",
            "type":"Retail Goods"
        }
    ],
    "sg:phone":"+32 51 58 82 32",
    "sg:postcode":"8480",
    "sg:province":"West-Vlaanderen",
    "sg:tags":[
        "-"
    ],
    "wof:name":"Huyghe J (huis)",
    "wof:placetype":"venue"
},
  "geometry": {"coordinates":[3.0162949562,51.0934677124],"type":"Point"}
}