{
  "type": "Feature",
  "properties": {
    "addr:full":"Rue D'houdr\u00e9mont 60 Bi\u00e8vre Namur 5555",
    "addr:housenumber":"60",
    "addr:postcode":"5555",
    "addr:street":"Rue D'Houdre \u0301Mont",
    "iso:country":"BE",
    "sg:address":"Rue D'houdr\u00e9mont 60",
    "sg:city":"Bi\u00e8vre",
    "sg:classifiers":[
        {
            "category":"Retail",
            "subcategory":"Veterinary Services",
            "type":"Services"
        }
    ],
    "sg:phone":"+32 61 51 15 05",
    "sg:postcode":"5555",
    "sg:province":"Namur",
    "sg:tags":[
        "veterinarian"
    ],
    "wof:name":"Dion A",
    "wof:placetype":"venue"
},
  "geometry": {"coordinates":[5.0066919327,49.9406166077],"type":"Point"}
}