{
  "type": "Feature",
  "properties": {
    "addr:full":"Avenue Edmond Parmentier 34 Bruxelles (woluwe-saint-pierre) Bruxelles-Capitale 1150",
    "addr:housenumber":"34",
    "addr:postcode":"1150",
    "addr:street":"Avenue Edmond Parmentier",
    "iso:country":"BE",
    "sg:address":"Avenue Edmond Parmentier 34",
    "sg:city":"Bruxelles (woluwe-saint-pierre)",
    "sg:classifiers":[
        {
            "category":"Shopping",
            "subcategory":"Clothing, Apparel, & Fashions",
            "type":"Retail Goods"
        }
    ],
    "sg:phone":"+32 2 770 45 60",
    "sg:postcode":"1150",
    "sg:province":"Bruxelles-Capitale",
    "sg:tags":[
        "-",
        "clothing",
        "child"
    ],
    "wof:name":"Monin-lego",
    "wof:placetype":"venue"
},
  "geometry": {"coordinates":[4.437707901,50.8315048218],"type":"Point"}
}