{
  "type": "Feature",
  "properties": {
    "iso:country":"BE",
    "sg:address":"Avenue Du Jolibois 358",
    "sg:city":"Seraing (jemeppe-sur-meuse)",
    "sg:classifiers":[
        {
            "category":"Professional",
            "subcategory":"Management & Consulting",
            "type":"Services"
        }
    ],
    "sg:phone":"+32 4 234 74 44",
    "sg:postcode":"4101",
    "sg:province":"Li\u00e8ge",
    "sg:tags":[
        "tax-consultants"
    ],
    "wof:name":"Heusdens P",
    "wof:placetype":"venue"
},
  "geometry": {"coordinates":[5.5059008598,50.6226654053],"type":"Point"}
}