{
  "type": "Feature",
  "properties": {
    "addr:full":"Rue Flament 8 P\u00e9ruwelz Hainaut 7600",
    "addr:housenumber":"8",
    "addr:postcode":"7600",
    "addr:street":"Rue Flament",
    "iso:country":"BE",
    "sg:address":"Rue Flament 8",
    "sg:city":"P\u00e9ruwelz",
    "sg:classifiers":[
        {
            "category":"Health Services",
            "subcategory":"Dentist",
            "type":"Services"
        }
    ],
    "sg:phone":"+32 69 77 46 29",
    "sg:postcode":"7600",
    "sg:province":"Hainaut",
    "wof:name":"Massaux Ch",
    "wof:placetype":"venue"
},
  "geometry": {"coordinates":[3.5909171104,50.5121307373],"type":"Point"}
}