{
  "type": "Feature",
  "properties": {
    "iso:country":"BE",
    "sg:address":"Rue Ferrer 25",
    "sg:city":"Charleroi",
    "sg:orig_category":"Enseignement maternel and primaire",
    "sg:phone":"+32 71 31 78 69",
    "sg:postcode":"6030",
    "sg:province":"Hainaut",
    "wof:name":"E.f.c. La Docherie",
    "wof:placetype":"venue"
},
  "geometry": {"coordinates":[4.4107809067,50.4218864441],"type":"Point"}
}