{
  "type": "Feature",
  "properties": {
    "addr:full":"Route De Burdinne 4 Heron Li\u00e8ge 4217",
    "addr:housenumber":"4",
    "addr:postcode":"4217",
    "addr:street":"Route De Burdinne;Heron Lie\u0300Ge",
    "iso:country":"BE",
    "sg:address":"Route De Burdinne 4",
    "sg:city":"Heron",
    "sg:orig_category":"Boucheries",
    "sg:phone":"+32 85 71 34 86",
    "sg:postcode":"4217",
    "sg:province":"Li\u00e8ge",
    "wof:name":"Philippe Minette",
    "wof:placetype":"venue"
},
  "geometry": {"coordinates":[5.0954089165,50.5553512573],"type":"Point"}
}