{
  "type": "Feature",
  "properties": {
    "addr:full":"Kloosterstraat 4ba Damme West-Vlaanderen 8340",
    "addr:housenumber":"4ba",
    "addr:postcode":"8340",
    "addr:street":"Kloosterstraat",
    "iso:country":"BE",
    "sg:address":"Kloosterstraat 4ba",
    "sg:city":"Damme",
    "sg:orig_category":"Enseignement maternel and primaire",
    "sg:phone":"+32 50 36 32 25",
    "sg:postcode":"8340",
    "sg:province":"West-Vlaanderen",
    "wof:name":"Vrije Basisschool",
    "wof:placetype":"venue"
},
  "geometry": {"coordinates":[3.3226699829,51.2023277283],"type":"Point"}
}