{
  "type": "Feature",
  "properties": {
    "addr:full":"Rue Docteur Desire Coffee 15 La Louvi\u00e8re (str\u00e9py-bracquegnies) Hainaut 7110",
    "addr:housenumber":"15",
    "addr:postcode":"7110",
    "addr:street":"Rue Docteur;La",
    "iso:country":"BE",
    "sg:address":"Rue Docteur Desire Coffee 15",
    "sg:city":"La Louvi\u00e8re (str\u00e9py-bracquegnies)",
    "sg:classifiers":[
        {
            "category":"Health Services",
            "subcategory":"Nursing And Care Facility",
            "type":"Services"
        }
    ],
    "sg:phone":"+32 64 66 30 53",
    "sg:postcode":"7110",
    "sg:province":"Hainaut",
    "sg:tags":[
        "home",
        "rest"
    ],
    "wof:name":"Home Familial",
    "wof:placetype":"venue"
},
  "geometry": {"coordinates":[4.1505050659,50.4826698303],"type":"Point"}
}