{
  "type": "Feature",
  "properties": {
    "addr:full":"Rue De Charleville 57 Gedinne Namur 5575",
    "addr:housenumber":"57",
    "addr:postcode":"5575",
    "addr:street":"Rue De Charleville",
    "iso:country":"BE",
    "sg:address":"Rue De Charleville 57",
    "sg:city":"Gedinne",
    "sg:orig_category":"Traitements param\u00e9dicaux",
    "sg:phone":"+32 61 58 87 14",
    "sg:postcode":"5575",
    "sg:province":"Namur",
    "wof:name":"S. Lambert",
    "wof:placetype":"venue"
},
  "geometry": {"coordinates":[4.9342741966,49.975769043],"type":"Point"}
}