{
  "type": "Feature",
  "properties": {
    "iso:country":"BE",
    "sg:address":"Rue Des Wallons 91",
    "sg:city":"Li\u00c8ge",
    "sg:classifiers":[
        {
            "category":"Health Services",
            "subcategory":"Hospital",
            "type":"Services"
        }
    ],
    "sg:phone":"+32 4 254 34 00",
    "sg:postcode":"4000",
    "sg:province":"Li\u00e8ge",
    "sg:tags":[
        "ambulance"
    ],
    "wof:name":"Trans Ambu",
    "wof:placetype":"venue"
},
  "geometry": {"coordinates":[5.555727005,50.6293449402],"type":"Point"}
}