{
  "type": "Feature",
  "properties": {
    "addr:full":"Sint-lambertusstraat 33ba Westerlo Antwerpen 2260",
    "addr:housenumber":"33ba",
    "addr:postcode":"2260",
    "addr:street":"Sint-Lambertusstraat",
    "iso:country":"BE",
    "sg:address":"Sint-lambertusstraat 33ba",
    "sg:city":"Westerlo",
    "sg:orig_category":"Pharmaciens",
    "sg:phone":"+32 14 54 73 02",
    "sg:postcode":"2260",
    "sg:province":"Antwerpen",
    "wof:name":"Apoteek De Volksmacht",
    "wof:placetype":"venue"
},
  "geometry": {"coordinates":[4.919025898,51.0902481079],"type":"Point"}
}