{
  "type": "Feature",
  "properties": {
    "iso:country":"BE",
    "sg:address":"Rue Du Tombu 2",
    "sg:city":"Braives",
    "sg:orig_category":"Voertuigen",
    "sg:phone":"+32 19 69 81 80",
    "sg:postcode":"4260",
    "sg:province":"Li\u00e8ge",
    "wof:name":"J.f.k. Auto",
    "wof:placetype":"venue"
},
  "geometry": {"coordinates":[5.1376018524,50.618927002],"type":"Point"}
}