{
  "type": "Feature",
  "properties": {
    "addr:full":"Dorpstraat 2a Koekelare West-Vlaanderen 8680",
    "addr:housenumber":"2a",
    "addr:postcode":"8680",
    "addr:street":"Dorpstraat",
    "iso:country":"BE",
    "sg:address":"Dorpstraat 2a",
    "sg:city":"Koekelare",
    "sg:classifiers":[
        {
            "category":"Insurance",
            "subcategory":"Insurance Agent",
            "type":"Services"
        }
    ],
    "sg:phone":"+32 51 58 08 41",
    "sg:postcode":"8680",
    "sg:province":"West-Vlaanderen",
    "sg:tags":[
        "broker"
    ],
    "wof:name":"Lootens J M (beleggingen)",
    "wof:placetype":"venue"
},
  "geometry": {"coordinates":[2.9777328968,51.0902099609],"type":"Point"}
}