{
  "type": "Feature",
  "properties": {
    "addr:full":"Veurnseweg 597 Ieper West-Vlaanderen 8906",
    "addr:housenumber":"597",
    "addr:postcode":"8906",
    "addr:street":"Veurnseweg",
    "iso:country":"BE",
    "sg:address":"Veurnseweg 597",
    "sg:city":"Ieper",
    "sg:orig_category":"Woningbouw",
    "sg:phone":"+32 57 42 26 45",
    "sg:postcode":"8906",
    "sg:province":"West-Vlaanderen",
    "wof:name":"Johannes Vallaeys",
    "wof:placetype":"venue"
},
  "geometry": {"coordinates":[2.8101611137,50.888092041],"type":"Point"}
}