{
  "type": "Feature",
  "properties": {
    "iso:country":"BE",
    "sg:address":"Leeuwerikenlei 12",
    "sg:city":"Schoten",
    "sg:orig_category":"Diverse intermediaire producten Gh",
    "sg:phone":"+32 3 226 60 42",
    "sg:postcode":"2900",
    "sg:province":"Antwerpen",
    "wof:name":"Rimbaut Kitty",
    "wof:placetype":"venue"
},
  "geometry": {"coordinates":[4.5211229324,51.2531814575],"type":"Point"}
}