{
  "type": "Feature",
  "properties": {
    "iso:country":"BE",
    "sg:address":"Rue Du Patronage 45",
    "sg:city":"Libramont-chevigny",
    "sg:orig_category":"V\u00e9t\u00e9rinaires",
    "sg:phone":"+32 61 22 45 39",
    "sg:postcode":"6800",
    "sg:province":"Luxembourg",
    "wof:name":"Cabinet V\u00c9t\u00c9rinaire Du Dr. De Grave",
    "wof:placetype":"venue"
},
  "geometry": {"coordinates":[5.3966598511,49.9707717896],"type":"Point"}
}