{
  "type": "Feature",
  "properties": {
    "addr:full":"Neerzijstraat 75 Genk Limburg 3600",
    "addr:housenumber":"75",
    "addr:postcode":"3600",
    "addr:street":"Neerzijstraat",
    "iso:country":"BE",
    "sg:address":"Neerzijstraat 75",
    "sg:city":"Genk",
    "sg:classifiers":[
        {
            "category":"Manufacturing",
            "subcategory":"Metals",
            "type":"Manufacturing & Wholesale Goods"
        }
    ],
    "sg:phone":"+32 89 35 24 12",
    "sg:postcode":"3600",
    "sg:province":"Limburg",
    "sg:tags":[
        "ornamental",
        "work",
        "-"
    ],
    "wof:name":"Bobbaers N",
    "wof:placetype":"venue"
},
  "geometry": {"coordinates":[5.5361747742,50.9721374512],"type":"Point"}
}