{
  "type": "Feature",
  "properties": {
    "addr:full":"Bruggestraat 213 Torhout West-Vlaanderen 8820",
    "addr:housenumber":"213",
    "addr:postcode":"8820",
    "addr:street":"Bruggestraat",
    "iso:country":"BE",
    "sg:address":"Bruggestraat 213",
    "sg:city":"Torhout",
    "sg:classifiers":[
        {
            "category":"Banks & Credit Unions",
            "subcategory":"Investment Brokerage",
            "type":"Services"
        }
    ],
    "sg:phone":"+32 50 21 22 28",
    "sg:postcode":"8820",
    "sg:province":"West-Vlaanderen",
    "sg:tags":[
        "varnishing",
        "firms",
        "industrial"
    ],
    "wof:name":"Van Wassenhove A. - Declerck Fietsenlakkerij Nv",
    "wof:placetype":"venue"
},
  "geometry": {"coordinates":[3.119781971,51.0862083435],"type":"Point"}
}