{
  "type": "Feature",
  "properties": {
    "addr:full":"Rue De L'aise 7 Jemeppe-sur-sambre Namur 5190",
    "addr:housenumber":"7",
    "addr:postcode":"5190",
    "addr:street":"Rue De L'Aise",
    "iso:country":"BE",
    "sg:address":"Rue De L'aise 7",
    "sg:city":"Jemeppe-sur-sambre",
    "sg:classifiers":[
        {
            "category":"Bakery",
            "type":"Food & Drink"
        }
    ],
    "sg:phone":"+32 71 78 52 38",
    "sg:postcode":"5190",
    "sg:province":"Namur",
    "sg:tags":[
        "confectioner",
        "baker"
    ],
    "wof:name":"A La Source Des Douceurs",
    "wof:placetype":"venue"
},
  "geometry": {"coordinates":[4.6686000824,50.4660148621],"type":"Point"}
}