{
  "type": "Feature",
  "properties": {
    "addr:full":"Rue De La Brasserie 8 Box 2 Eghez\u00e9e (saint-germain) Namur 5310",
    "addr:housenumber":"8;2",
    "addr:postcode":"5310",
    "addr:street":"Rue De La Brasserie;Box",
    "iso:country":"BE",
    "sg:address":"Rue De La Brasserie 8 Box 2",
    "sg:city":"Eghez\u00e9e (saint-germain)",
    "sg:classifiers":[
        {
            "category":"Health Services",
            "subcategory":"Health Practitioner",
            "type":"Services"
        }
    ],
    "sg:phone":"+32 81 74 78 56",
    "sg:postcode":"5310",
    "sg:province":"Namur",
    "sg:tags":[
        "dietitian"
    ],
    "wof:name":"Wilpart V",
    "wof:placetype":"venue"
},
  "geometry": {"coordinates":[4.8403749466,50.5755577087],"type":"Point"}
}