{
  "type": "Feature",
  "properties": {
    "iso:country":"BE",
    "sg:address":"Lindestraat 14",
    "sg:city":"Gingelom",
    "sg:orig_category":"Dakwerken Installatie van houten of kunststof schrijnwerk",
    "sg:phone":"+32 11 48 64 40",
    "sg:postcode":"3891",
    "sg:province":"Limburg",
    "wof:name":"Scheepers L. & Zn",
    "wof:placetype":"venue"
},
  "geometry": {"coordinates":[5.2206850052,50.7515525818],"type":"Point"}
}