{
  "type": "Feature",
  "properties": {
    "iso:country":"BE",
    "sg:address":"Kongostraat 20",
    "sg:city":"Kuurne",
    "sg:orig_category":"Non-Classified Establishments",
    "sg:phone":"+32 56 36 31 61",
    "sg:postcode":"8520",
    "sg:province":"West-Vlaanderen",
    "wof:name":"Devos Elektro Nv",
    "wof:placetype":"venue"
},
  "geometry": {"coordinates":[3.2684049606,50.8509216309],"type":"Point"}
}