{
  "type": "Feature",
  "properties": {
    "iso:country":"BE",
    "sg:address":"Rue Albert Ier 15",
    "sg:city":"Tournai",
    "sg:orig_category":"Installatie van houten of kunststof schrijnwerk Installatie van metalen schrijnwerk MEUBELONTWERP AN",
    "sg:phone":"+32 69 44 28 43",
    "sg:postcode":"7538",
    "sg:province":"Hainaut",
    "wof:name":"Maison Fontaine",
    "wof:placetype":"venue"
},
  "geometry": {"coordinates":[3.500494957,50.5717964172],"type":"Point"}
}