{
  "type": "Feature",
  "properties": {
    "iso:country":"BE",
    "sg:address":"Rue De La Laiterie 2",
    "sg:city":"Celles",
    "sg:classifiers":[
        {
            "category":"Arena",
            "subcategory":"Sports Club",
            "type":"Entertainment"
        }
    ],
    "sg:phone":"+32 69 85 97 71",
    "sg:postcode":"7760",
    "sg:province":"Hainaut",
    "sg:tags":[
        "de"
    ],
    "wof:name":"La Justice",
    "wof:placetype":"venue"
},
  "geometry": {"coordinates":[3.456125021,50.6806907654],"type":"Point"}
}