{
  "type": "Feature",
  "properties": {
    "addr:full":"Rue De Nazareth 43 Manage (la Hestre) Hainaut 7170",
    "addr:housenumber":"43",
    "addr:postcode":"7170",
    "addr:street":"Rue De Nazareth;La;Hainaut",
    "iso:country":"BE",
    "sg:address":"Rue De Nazareth 43",
    "sg:city":"Manage (la Hestre)",
    "sg:classifiers":[
        {
            "category":"Real Estate",
            "subcategory":"Surveying",
            "type":"Services"
        }
    ],
    "sg:phone":"+32 64 21 64 87",
    "sg:postcode":"7170",
    "sg:province":"Hainaut",
    "sg:tags":[
        "surveyor",
        "land"
    ],
    "wof:name":"Hoyaux J",
    "wof:placetype":"venue"
},
  "geometry": {"coordinates":[4.2275309563,50.4711418152],"type":"Point"}
}