{
  "type": "Feature",
  "properties": {
    "addr:full":"Rue Maison Blanche 135 Fourons (mouland) Limburg 3790",
    "addr:housenumber":"135",
    "addr:postcode":"3790",
    "addr:street":"Rue Maison Blanche;Mouland Limburg",
    "iso:country":"BE",
    "sg:address":"Rue Maison Blanche 135",
    "sg:city":"Fourons (mouland)",
    "sg:classifiers":[
        {
            "category":"Bakery",
            "type":"Food & Drink"
        }
    ],
    "sg:phone":"+32 4 381 04 59",
    "sg:postcode":"3790",
    "sg:province":"Limburg",
    "sg:tags":[
        "confectioner",
        "baker"
    ],
    "wof:name":"Theunissen B",
    "wof:placetype":"venue"
},
  "geometry": {"coordinates":[5.721350193,50.763999939],"type":"Point"}
}