{
  "type": "Feature",
  "properties": {
    "iso:country":"BE",
    "sg:address":"Maerestraat 6",
    "sg:city":"De Panne",
    "sg:orig_category":"Jeux de hasard",
    "sg:phone":"+32 58 41 45 58",
    "sg:postcode":"8660",
    "sg:province":"West-Vlaanderen",
    "wof:name":"Ladbroke",
    "wof:placetype":"venue"
},
  "geometry": {"coordinates":[2.5627629757,51.0587005615],"type":"Point"}
}