{
  "type": "Feature",
  "properties": {
    "addr:full":"Sint-godfriedstraat 10 Sint-truiden Limburg 3800",
    "addr:housenumber":"10",
    "addr:postcode":"3800",
    "addr:street":"Sint-Godfriedstraat",
    "iso:country":"BE",
    "sg:address":"Sint-godfriedstraat 10",
    "sg:city":"Sint-truiden",
    "sg:orig_category":"Kapsalons",
    "sg:phone":"+32 11 68 65 20",
    "sg:postcode":"3800",
    "sg:province":"Limburg",
    "wof:name":"Josine Diepenrijkx",
    "wof:placetype":"venue"
},
  "geometry": {"coordinates":[5.1990737915,50.8307037354],"type":"Point"}
}