{
  "type": "Feature",
  "properties": {
    "iso:country":"BE",
    "sg:address":"Oudler 47",
    "sg:city":"Burg-reuland",
    "sg:orig_category":"Dakwerken Installatie van houten of kunststof schrijnwerk Loodgieterij, verwarming and sanitaire ins",
    "sg:phone":"+32 80 32 97 22",
    "sg:postcode":"4791",
    "sg:province":"Li\u00e8ge",
    "wof:name":"Richard Mutsch/mutsch Richard & Cie",
    "wof:placetype":"venue"
},
  "geometry": {"coordinates":[6.0944099426,50.2024497986],"type":"Point"}
}