{
  "type": "Feature",
  "properties": {
    "iso:country":"BE",
    "sg:address":"Keperenberg 37a",
    "sg:city":"Dilbeek",
    "sg:orig_category":"Salles de spectacles. Caf\u00e9s",
    "sg:phone":"+32 2 569 00 48",
    "sg:postcode":"1700",
    "sg:province":"Vlaams-Brabant",
    "wof:name":"Recreatiecentrum Itterbeek",
    "wof:placetype":"venue"
},
  "geometry": {"coordinates":[4.2489171028,50.8360671997],"type":"Point"}
}