{
  "type": "Feature",
  "properties": {
    "addr:full":"Geraetsstraat 21 Hasselt Limburg 3500",
    "addr:housenumber":"21",
    "addr:postcode":"3500",
    "addr:street":"Geraetsstraat",
    "iso:country":"BE",
    "sg:address":"Geraetsstraat 21",
    "sg:city":"Hasselt",
    "sg:orig_category":"Architecten Artiesten and kunstenaars",
    "sg:phone":"+32 11 22 84 25",
    "sg:postcode":"3500",
    "sg:province":"Limburg",
    "wof:name":"Luc Baert",
    "wof:placetype":"venue"
},
  "geometry": {"coordinates":[5.3311390877,50.9309501648],"type":"Point"}
}