{
  "type": "Feature",
  "properties": {
    "iso:country":"BE",
    "sg:address":"33 Rue Du Foss\u00c9 Au Loup",
    "sg:city":"Brussel/bruxelles",
    "sg:orig_category":"Etablissements Erotiques",
    "sg:phone":"+32 476 90 96 84",
    "sg:postcode":"1000",
    "sg:province":"Bruxelles-Capitale",
    "wof:name":"Maitresse Adolfa",
    "wof:placetype":"venue"
},
  "geometry": {"coordinates":[4.3538651466,50.8505058289],"type":"Point"}
}