{
  "type": "Feature",
  "properties": {
    "addr:full":"Kortrijkseheerweg 47a Nazareth Oost-Vlaanderen 9800",
    "addr:housenumber":"47a",
    "addr:postcode":"9800",
    "addr:street":"Kortrijkseheerweg",
    "iso:country":"BE",
    "sg:address":"Kortrijkseheerweg 47a",
    "sg:city":"Nazareth",
    "sg:classifiers":[
        {
            "category":"Insurance",
            "subcategory":"Insurance Agent",
            "type":"Services"
        }
    ],
    "sg:phone":"+32 9 386 21 25",
    "sg:postcode":"9800",
    "sg:province":"Oost-Vlaanderen",
    "sg:tags":[
        "verzekeringsmakelaars",
        "expert"
    ],
    "wof:name":"Verzekeringen Maere",
    "wof:placetype":"venue"
},
  "geometry": {"coordinates":[-85.4866104126,37.8500823975],"type":"Point"}
}