{
  "type": "Feature",
  "properties": {
    "iso:country":"BE",
    "sg:address":"Avenue De Vis\u00c9 109",
    "sg:city":"Watermaal-bosvoorde/watermael-boitsfort",
    "sg:orig_category":"Installation \u00e9lectrique r\u00e9sidentielle. Articles m\u00e9talliques ouvr\u00e9s divers Fab. Installation \u00e9lectriq",
    "sg:phone":"+32 2 672 44 11",
    "sg:postcode":"1170",
    "sg:province":"Bruxelles-Capitale",
    "wof:name":"Sirien",
    "wof:placetype":"venue"
},
  "geometry": {"coordinates":[4.3932790756,50.8118171692],"type":"Point"}
}