{
  "type": "Feature",
  "properties": {
    "addr:full":"Rue Du Cimeti\u00c8re 33 Ans Li\u00e8ge 4430",
    "addr:housenumber":"33",
    "addr:postcode":"4430",
    "addr:street":"Rue Du Cimetie\u0300Re",
    "iso:country":"BE",
    "sg:address":"Rue Du Cimeti\u00c8re 33",
    "sg:city":"Ans",
    "sg:orig_category":"Activit\u00e9s r\u00e9cr\u00e9atives diverses",
    "sg:phone":"+32 4 226 18 26",
    "sg:postcode":"4430",
    "sg:province":"Li\u00e8ge",
    "wof:name":"Club Philat. Le Perron",
    "wof:placetype":"venue"
},
  "geometry": {"coordinates":[5.5390501022,50.6546173096],"type":"Point"}
}