{
  "type": "Feature",
  "properties": {
    "addr:full":"416 Chaussee Dalsemberg 1180 Uccle 416",
    "addr:housenumber":"416",
    "addr:postcode":"1180;416",
    "addr:street":"Chaussee Dalsemberg",
    "iso:country":"BE",
    "sg:address":"416",
    "sg:city":"Chaussee Dalsemberg 1180 Uccle",
    "sg:classifiers":[
        {
            "category":"Autos & Motor Vehicles",
            "subcategory":"Automobile Sales",
            "type":"Retail Goods"
        }
    ],
    "sg:phone":"+32 2 344 49 70",
    "sg:postcode":"416",
    "sg:tags":[
        "equipment",
        "motor-cars",
        "transport"
    ],
    "wof:name":"Carrosserie Du Karreveld Sud Sa",
    "wof:placetype":"venue"
},
  "geometry": {"coordinates":[4.3319702148,50.8036155701],"type":"Point"}
}