{
  "type": "Feature",
  "properties": {
    "iso:country":"BE",
    "sg:address":"Woluwelaan 29",
    "sg:city":"Machelen",
    "sg:classifiers":[
        {
            "category":"Retail",
            "subcategory":"Auto Repair",
            "type":"Services"
        }
    ],
    "sg:phone":"+32 2 252 55 33",
    "sg:postcode":"1830",
    "sg:province":"Vlaams-Brabant",
    "sg:tags":[
        "garage"
    ],
    "wof:name":"Machelen Motors Sprl",
    "wof:placetype":"venue"
},
  "geometry": {"coordinates":[4.4279828072,50.9075508118],"type":"Point"}
}