{
  "type": "Feature",
  "properties": {
    "addr:full":"Petite Rue Mahiermont 11 Rixensart (genval) Brabant Wallon 1332",
    "addr:housenumber":"11",
    "addr:postcode":"1332",
    "addr:street":"Petite Rue Mahiermont",
    "iso:country":"BE",
    "sg:address":"Petite Rue Mahiermont 11",
    "sg:city":"Rixensart (genval)",
    "sg:classifiers":[
        {
            "category":"Professional",
            "subcategory":"Computer Services",
            "type":"Services"
        }
    ],
    "sg:phone":"+32 2 653 12 10",
    "sg:postcode":"1332",
    "sg:province":"Brabant Wallon",
    "sg:tags":[
        "-",
        "processing",
        "data"
    ],
    "wof:name":"Frs Informatica",
    "wof:placetype":"venue"
},
  "geometry": {"coordinates":[4.4937157631,50.7131652832],"type":"Point"}
}