{
  "type": "Feature",
  "properties": {
    "iso:country":"BE",
    "sg:address":"Lindestraat 90",
    "sg:city":"Zwalm",
    "sg:orig_category":"Jardinage",
    "sg:phone":"+32 55 49 68 68",
    "sg:postcode":"9630",
    "sg:province":"Oost-Vlaanderen",
    "wof:name":"De Meuleneire Christian",
    "wof:placetype":"venue"
},
  "geometry": {"coordinates":[3.6939730644,50.8970870972],"type":"Point"}
}