{
  "type": "Feature",
  "properties": {
    "iso:country":"BE",
    "sg:address":"Geraetsstraat 19",
    "sg:city":"Hasselt",
    "sg:orig_category":"Advocaten and juridische adviseurs",
    "sg:phone":"+32 11 22 16 46",
    "sg:postcode":"3500",
    "sg:province":"Limburg",
    "wof:name":"T. Nuyens",
    "wof:placetype":"venue"
},
  "geometry": {"coordinates":[5.3310542107,50.9309082031],"type":"Point"}
}