{
  "type": "Feature",
  "properties": {
    "addr:full":"Opstalstraat 6 Dendermonde Oost-Vlaanderen 9200",
    "addr:housenumber":"6",
    "addr:postcode":"9200",
    "addr:street":"Opstalstraat;Oost-Vlaanderen",
    "iso:country":"BE",
    "sg:address":"Opstalstraat 6",
    "sg:city":"Dendermonde",
    "sg:orig_category":"Entretien and r\u00e9parations de voitures",
    "sg:phone":"+32 52 42 72 77",
    "sg:postcode":"9200",
    "sg:province":"Oost-Vlaanderen",
    "wof:name":"Gunther Hofman",
    "wof:placetype":"venue"
},
  "geometry": {"coordinates":[4.0276579857,51.006111145],"type":"Point"}
}