{
  "type": "Feature",
  "properties": {
    "addr:full":"Klokjeslaan 32 Watermaal-bosvoorde/watermael-boitsfort Bruxelles-Capitale 1170",
    "addr:housenumber":"32",
    "addr:postcode":"1170",
    "addr:street":"Klokjeslaan",
    "iso:country":"BE",
    "sg:address":"Klokjeslaan 32",
    "sg:city":"Watermaal-bosvoorde/watermael-boitsfort",
    "sg:orig_category":"Diverse grafische activiteiten",
    "sg:phone":"+32 2 660 84 37",
    "sg:postcode":"1170",
    "sg:province":"Bruxelles-Capitale",
    "wof:name":"Thierry Disneur",
    "wof:placetype":"venue"
},
  "geometry": {"coordinates":[4.400165081,50.8012886047],"type":"Point"}
}