{
  "type": "Feature",
  "properties": {
    "addr:full":"Doorniksesteenweg 202 Avelgem West-Vlaanderen 8580",
    "addr:housenumber":"202",
    "addr:postcode":"8580",
    "addr:street":"Doorniksesteenweg",
    "iso:country":"BE",
    "sg:address":"Doorniksesteenweg 202",
    "sg:city":"Avelgem",
    "sg:classifiers":[
        {
            "category":"Manufacturing",
            "subcategory":"Lumber",
            "type":"Manufacturing & Wholesale Goods"
        }
    ],
    "sg:phone":"+32 56 64 40 42",
    "sg:postcode":"8580",
    "sg:province":"West-Vlaanderen",
    "sg:tags":[
        "timber"
    ],
    "wof:name":"Houtmagazijn Verdonckt Sa",
    "wof:placetype":"venue"
},
  "geometry": {"coordinates":[3.4453070164,50.7709579468],"type":"Point"}
}