{
  "type": "Feature",
  "properties": {
    "addr:full":"Avenue F\u00e9lix Marchal 126 Bruxelles (schaerbeek) Bruxelles-Capitale 1030",
    "addr:housenumber":"126",
    "addr:postcode":"1030",
    "addr:street":"Avenue Fe\u0301Lix Marchal",
    "iso:country":"BE",
    "sg:address":"Avenue F\u00e9lix Marchal 126",
    "sg:city":"Bruxelles (schaerbeek)",
    "sg:classifiers":[
        {
            "category":"Real Estate",
            "subcategory":"Surveying",
            "type":"Services"
        }
    ],
    "sg:phone":"+32 2 734 97 79",
    "sg:postcode":"1030",
    "sg:province":"Bruxelles-Capitale",
    "sg:tags":[
        "surveyor",
        "land"
    ],
    "wof:name":"Allar M",
    "wof:placetype":"venue"
},
  "geometry": {"coordinates":[4.3929538727,50.850566864],"type":"Point"}
}