{
  "type": "Feature",
  "properties": {
    "iso:country":"BE",
    "sg:address":"Rue Jean Schoenaerts 1",
    "sg:city":"Awans",
    "sg:classifiers":[
        {
            "category":"Health Services",
            "subcategory":"Dentist",
            "type":"Services"
        }
    ],
    "sg:phone":"+32 4 239 70 60",
    "sg:postcode":"4340",
    "sg:province":"Li\u00e8ge",
    "wof:name":"Lucas P",
    "wof:placetype":"venue"
},
  "geometry": {"coordinates":[5.4662399292,50.6668205261],"type":"Point"}
}