{
  "type": "Feature",
  "properties": {
    "addr:full":"Kaaistraat 43 Affligem (teralfene) Vlaams-Brabant 1790",
    "addr:housenumber":"43",
    "addr:postcode":"1790",
    "addr:street":"Kaaistraat",
    "iso:country":"BE",
    "sg:address":"Kaaistraat 43",
    "sg:city":"Affligem (teralfene)",
    "sg:classifiers":[
        {
            "category":"Utilities",
            "subcategory":"Fuel Oil & Lpg",
            "type":"Services"
        }
    ],
    "sg:phone":"+32 53 66 12 82",
    "sg:postcode":"1790",
    "sg:province":"Vlaams-Brabant",
    "wof:name":"Warin Louis Bvba",
    "wof:placetype":"venue"
},
  "geometry": {"coordinates":[4.105984211,50.9132232666],"type":"Point"}
}