{
  "type": "Feature",
  "properties": {
    "iso:country":"BE",
    "sg:address":"Hoge Mauw 2",
    "sg:city":"Arendonk",
    "sg:classifiers":[
        {
            "category":"Autos & Motor Vehicles",
            "subcategory":"Motorcycle Sales",
            "type":"Retail Goods"
        }
    ],
    "sg:phone":"+32 14 42 98 91",
    "sg:postcode":"2370",
    "sg:province":"Antwerpen",
    "sg:tags":[
        "motorbike"
    ],
    "wof:name":"Bg Bikes",
    "wof:placetype":"venue"
},
  "geometry": {"coordinates":[5.1116471291,51.3018722534],"type":"Point"}
}