{
  "type": "Feature",
  "properties": {
    "iso:country":"BE",
    "sg:address":"Bouledard Raymond Poincar\u00c9 103",
    "sg:city":"Li\u00c8ge",
    "sg:orig_category":"Jeux and jouets",
    "sg:phone":"+32 4 344 33 44",
    "sg:postcode":"4020",
    "sg:province":"Li\u00e8ge",
    "wof:name":"Maxi-toys",
    "wof:placetype":"venue"
},
  "geometry": {"coordinates":[5.5842299461,50.6291885376],"type":"Point"}
}