{
  "type": "Feature",
  "properties": {
    "addr:full":"Grote Markt 37 Sint-niklaas (groot) Oost-Vlaanderen 9100",
    "addr:housenumber":"37",
    "addr:postcode":"9100",
    "addr:street":"Grote Markt;Groot Oost-Vlaanderen",
    "iso:country":"BE",
    "sg:address":"Grote Markt 37",
    "sg:city":"Sint-niklaas (groot)",
    "sg:orig_category":"Artsen and specialisten Ziekenhuizen and zorginstellingen",
    "sg:phone":"+32 3 760 00 40",
    "sg:postcode":"9100",
    "sg:province":"Oost-Vlaanderen",
    "wof:name":"Geneesk. Inst. St.michael",
    "wof:placetype":"venue"
},
  "geometry": {"coordinates":[4.1417069435,51.1635017395],"type":"Point"}
}