{
  "type": "Feature",
  "properties": {
    "addr:full":"De Merodelei 94 Turnhout Antwerpen 2300",
    "addr:housenumber":"94",
    "addr:postcode":"2300",
    "addr:street":"De Merodelei",
    "iso:country":"BE",
    "sg:address":"De Merodelei 94",
    "sg:city":"Turnhout",
    "sg:classifiers":[
        {
            "category":"Fast Food",
            "type":"Food & Drink"
        }
    ],
    "sg:phone":"+32 14 41 35 54",
    "sg:postcode":"2300",
    "sg:province":"Antwerpen",
    "sg:tags":[
        "fried",
        "stand",
        "potato"
    ],
    "wof:name":"Mosselhuis (het)",
    "wof:placetype":"venue"
},
  "geometry": {"coordinates":[4.9388608932,51.3219528198],"type":"Point"}
}