{
  "type": "Feature",
  "properties": {
    "addr:full":"K. L. Ledeganckstraat 4 Gent Oost-Vlaanderen 9000",
    "addr:housenumber":"4",
    "addr:postcode":"9000",
    "addr:street":"K.;Ledeganckstraat;Oost-Vlaanderen",
    "iso:country":"BE",
    "sg:address":"K. L. Ledeganckstraat 4",
    "sg:city":"Gent",
    "sg:orig_category":"Enseignement maternel and primaire",
    "sg:phone":"+32 9 243 93 59",
    "sg:postcode":"9000",
    "sg:province":"Oost-Vlaanderen",
    "wof:name":"Basisschool",
    "wof:placetype":"venue"
},
  "geometry": {"coordinates":[3.7246539593,51.036693573],"type":"Point"}
}