{
  "type": "Feature",
  "properties": {
    "iso:country":"BE",
    "sg:address":"Rue De Beaumont 97",
    "sg:city":"Thuin",
    "sg:orig_category":"Installatie van houten of kunststof schrijnwerk Installatie van metalen schrijnwerk",
    "sg:phone":"+32 71 53 41 43",
    "sg:postcode":"6536",
    "sg:province":"Hainaut",
    "wof:name":"Gaume",
    "wof:placetype":"venue"
},
  "geometry": {"coordinates":[4.3301010132,50.3132476807],"type":"Point"}
}