{
  "type": "Feature",
  "properties": {
    "iso:country":"BE",
    "sg:address":"Markegemstraat 70",
    "sg:city":"Dentergem (wakken)",
    "sg:classifiers":[
        {
            "category":"Professional",
            "subcategory":"Printing & Photocopies",
            "type":"Services"
        }
    ],
    "sg:phone":"+32 56 60 22 47",
    "sg:postcode":"8720",
    "sg:province":"West-Vlaanderen",
    "sg:tags":[
        "-",
        "offset"
    ],
    "wof:name":"Desmet-dhondt",
    "wof:placetype":"venue"
},
  "geometry": {"coordinates":[3.3962459564,50.9342041016],"type":"Point"}
}