{
  "type": "Feature",
  "properties": {
    "addr:full":"Tombroekmolenstraat 13 Kortrijk West-Vlaanderen 8510",
    "addr:housenumber":"13",
    "addr:postcode":"8510",
    "addr:street":"Tombroekmolenstraat",
    "iso:country":"BE",
    "sg:address":"Tombroekmolenstraat 13",
    "sg:city":"Kortrijk",
    "sg:orig_category":"Plaatsen van vloer- and muurbekleding Schilders",
    "sg:phone":"+32 56 21 54 04",
    "sg:postcode":"8510",
    "sg:province":"West-Vlaanderen",
    "wof:name":"Stijn Eggermont",
    "wof:placetype":"venue"
},
  "geometry": {"coordinates":[3.2636380196,50.7513122559],"type":"Point"}
}