{
  "type": "Feature",
  "properties": {
    "addr:full":"Lichtaartsebaan 24-25 Kasterlee Antwerpen 2460",
    "addr:housenumber":"24-25",
    "addr:postcode":"2460",
    "iso:country":"BE",
    "sg:address":"Lichtaartsebaan 24-25",
    "sg:city":"Kasterlee",
    "sg:classifiers":[
        {
            "category":"Manufacturing",
            "subcategory":"Motor Vehicles & Parts",
            "type":"Manufacturing & Wholesale Goods"
        }
    ],
    "sg:phone":"+32 14 85 18 44",
    "sg:postcode":"2460",
    "sg:province":"Antwerpen",
    "sg:tags":[
        "body",
        "automobile",
        "construction",
        "-"
    ],
    "wof:name":"Van Laer",
    "wof:placetype":"venue"
},
  "geometry": {"coordinates":[4.9597401619,51.239528656],"type":"Point"}
}