{
  "type": "Feature",
  "properties": {
    "iso:country":"BE",
    "sg:address":"Kerkstraat 19a",
    "sg:city":"Willebroek",
    "sg:classifiers":[
        {
            "category":"Health Services",
            "subcategory":"Dentist",
            "type":"Services"
        }
    ],
    "sg:phone":"+32 3 886 81 19",
    "sg:postcode":"2830",
    "sg:province":"Antwerpen",
    "wof:name":"Vercruysse J",
    "wof:placetype":"venue"
},
  "geometry": {"coordinates":[4.3598899841,51.0645828247],"type":"Point"}
}