{
  "type": "Feature",
  "properties": {
    "iso:country":"BE",
    "sg:address":"Rue De La Roche 5",
    "sg:city":"Rendeux",
    "sg:classifiers":[
        {
            "category":"Bakery",
            "type":"Food & Drink"
        }
    ],
    "sg:phone":"+32 84 47 81 30",
    "sg:postcode":"6987",
    "sg:province":"Luxembourg",
    "sg:tags":[
        "confectioner",
        "baker"
    ],
    "wof:name":"Collignon D",
    "wof:placetype":"venue"
},
  "geometry": {"coordinates":[5.5109510422,50.2341842651],"type":"Point"}
}