{
  "type": "Feature",
  "properties": {
    "addr:full":"Rue Des Fr\u00c8res Dulait 17 Braine-le-comte Hainaut 7090",
    "addr:housenumber":"17",
    "addr:postcode":"7090",
    "addr:street":"Rue Des Fre\u0300Res Dulait",
    "iso:country":"BE",
    "sg:address":"Rue Des Fr\u00c8res Dulait 17",
    "sg:city":"Braine-le-comte",
    "sg:orig_category":"Diverse organisaties and verenigingen",
    "sg:phone":"+32 67 55 72 20",
    "sg:postcode":"7090",
    "sg:province":"Hainaut",
    "wof:name":"Maison Des Jeunes",
    "wof:placetype":"venue"
},
  "geometry": {"coordinates":[4.1340742111,50.6023101807],"type":"Point"}
}