{
  "type": "Feature",
  "properties": {
    "iso:country":"BE",
    "sg:address":"Hoogleedsesteenweg 346",
    "sg:city":"Roeselare",
    "sg:classifiers":[
        {
            "category":"Professional",
            "subcategory":"Testing Lab",
            "type":"Services"
        }
    ],
    "sg:phone":"+32 51 24 75 73",
    "sg:postcode":"8800",
    "sg:province":"West-Vlaanderen",
    "sg:tags":[
        "chemist"
    ],
    "wof:name":"Follebout D",
    "wof:placetype":"venue"
},
  "geometry": {"coordinates":[3.1016449928,50.9608001709],"type":"Point"}
}