{
  "type": "Feature",
  "properties": {
    "iso:country":"BE",
    "sg:address":"Parvis Sainte-alix 20",
    "sg:city":"Bruxelles (woluwe-saint-pierre)",
    "sg:classifiers":[
        {
            "category":"Shopping",
            "subcategory":"Clothing, Apparel, & Fashions",
            "type":"Retail Goods"
        }
    ],
    "sg:phone":"+32 2 771 73 76",
    "sg:postcode":"1150",
    "sg:province":"Bruxelles-Capitale",
    "sg:tags":[
        "underwear",
        "lingerie",
        "-"
    ],
    "wof:name":"Marie-france",
    "wof:placetype":"venue"
},
  "geometry": {"coordinates":[4.4612212181,50.8280029297],"type":"Point"}
}