{
  "type": "Feature",
  "properties": {
    "addr:full":"Sparrestraat 14 Lovendegem Oost-Vlaanderen 9920",
    "addr:housenumber":"14",
    "addr:postcode":"9920",
    "addr:street":"Sparrestraat",
    "iso:country":"BE",
    "sg:address":"Sparrestraat 14",
    "sg:city":"Lovendegem",
    "sg:classifiers":[
        {
            "category":"Professional",
            "type":"Services"
        }
    ],
    "sg:phone":"+32 9 224 04 85",
    "sg:postcode":"9920",
    "sg:province":"Oost-Vlaanderen",
    "sg:tags":[
        "entertainer"
    ],
    "wof:name":"Vranckx P",
    "wof:placetype":"venue"
},
  "geometry": {"coordinates":[3.6321918964,51.1072998047],"type":"Point"}
}