{
  "type": "Feature",
  "properties": {
    "iso:country":"BE",
    "sg:address":"Rue De L'union 17",
    "sg:city":"La Louviere",
    "sg:orig_category":"Boucheries",
    "sg:phone":"+32 64 26 13 48",
    "sg:postcode":"7100",
    "sg:province":"Hainaut",
    "wof:name":"Romuald Gravis",
    "wof:placetype":"venue"
},
  "geometry": {"coordinates":[4.2147631645,50.4644012451],"type":"Point"}
}