{
  "type": "Feature",
  "properties": {
    "iso:country":"BE",
    "sg:address":"Wildersedreef 4",
    "sg:city":"Kampenhout",
    "sg:classifiers":[
        {
            "category":"Health Services",
            "subcategory":"Health Practitioner",
            "type":"Services"
        }
    ],
    "sg:phone":"+32 16 65 67 08",
    "sg:postcode":"1910",
    "sg:province":"Vlaams-Brabant",
    "sg:tags":[
        "physiotherapist"
    ],
    "wof:name":"Schoevaerts Cindy",
    "wof:placetype":"venue"
},
  "geometry": {"coordinates":[4.5670418739,50.9403953552],"type":"Point"}
}