{
  "type": "Feature",
  "properties": {
    "iso:country":"BE",
    "sg:address":"Edward Vlietinckstraat 15",
    "sg:city":"Oostende",
    "sg:orig_category":"Herstellingen and onderhoud van auto's Voertuigen",
    "sg:phone":"+32 59 80 64 44",
    "sg:postcode":"8400",
    "sg:province":"West-Vlaanderen",
    "wof:name":"Etn. De Coninck D.",
    "wof:placetype":"venue"
},
  "geometry": {"coordinates":[2.9377019405,51.2075576782],"type":"Point"}
}