{
  "type": "Feature",
  "properties": {
    "iso:country":"BE",
    "sg:address":"Avenue Reine Astrid 19",
    "sg:city":"Huy",
    "sg:orig_category":"M\u00e9decins and sp\u00e9cialistes",
    "sg:phone":"+32 85 21 67 59",
    "sg:postcode":"4500",
    "sg:province":"Li\u00e8ge",
    "wof:name":"Anne-charlotte W\u00c9gria",
    "wof:placetype":"venue"
},
  "geometry": {"coordinates":[5.2278060913,50.5255737305],"type":"Point"}
}