{
  "type": "Feature",
  "properties": {
    "addr:full":"Gustaaf Woutersstraat 13 Balen Antwerpen 2490",
    "addr:housenumber":"13",
    "addr:postcode":"2490",
    "addr:street":"Gustaaf Woutersstraat",
    "iso:country":"BE",
    "sg:address":"Gustaaf Woutersstraat 13",
    "sg:city":"Balen",
    "sg:orig_category":"Enseignement maternel and primaire",
    "sg:phone":"+32 14 81 19 25",
    "sg:postcode":"2490",
    "sg:province":"Antwerpen",
    "wof:name":"Vrije Basisschool",
    "wof:placetype":"venue"
},
  "geometry": {"coordinates":[5.1710281372,51.1714515686],"type":"Point"}
}