{
  "type": "Feature",
  "properties": {
    "addr:full":"Rue De L\u00b4eglise 2 Braine-l\u00b4alleud Brabant Wallon 1421",
    "addr:housenumber":"2;1421",
    "addr:street":"Rue De L\u00b4Eglise;Brabant Wallon",
    "iso:country":"BE",
    "sg:address":"Rue De L\u00b4eglise 2",
    "sg:city":"Braine-l\u00b4alleud",
    "sg:classifiers":[
        {
            "category":"Restaurant",
            "type":"Food & Drink"
        }
    ],
    "sg:phone":"+32 2 385 07 76",
    "sg:postcode":"1421",
    "sg:province":"Brabant Wallon",
    "sg:tags":[
        "de",
        "organisation",
        "\u00e0",
        "fast",
        "catering",
        "emporter",
        "f\u00eates",
        "restaurants"
    ],
    "wof:name":"Le Chabichou",
    "wof:placetype":"venue"
},
  "geometry": {"coordinates":[4.3490509987,50.6662902832],"type":"Point"}
}