{
  "type": "Feature",
  "properties": {
    "iso:country":"BE",
    "sg:address":"Bruggesteenweg 67 A",
    "sg:city":"Hooglede Gits",
    "sg:orig_category":"Non-Classified Establishments",
    "sg:phone":"+32 51 22 82 48",
    "sg:postcode":"8830",
    "sg:province":"West-Vlaanderen",
    "wof:name":"Van Clooster",
    "wof:placetype":"venue"
},
  "geometry": {"coordinates":[3.1161620617,51.0010643005],"type":"Point"}
}