{
  "type": "Feature",
  "properties": {
    "iso:country":"BE",
    "sg:address":"Kwakkelstraat 2",
    "sg:city":"Torhout",
    "sg:orig_category":"Production de films, t\u00e9l\u00e9films and vid\u00e9os",
    "sg:phone":"+32 51 72 28 91",
    "sg:postcode":"8820",
    "sg:province":"West-Vlaanderen",
    "wof:name":"Koen Lavens",
    "wof:placetype":"venue"
},
  "geometry": {"coordinates":[3.1140089035,51.0333862305],"type":"Point"}
}