{
  "type": "Feature",
  "properties": {
    "addr:full":"Troonplaats 2 Antwerpen Antwerpen 2018",
    "addr:housenumber":"2",
    "addr:postcode":"2018",
    "addr:street":"Troonplaats",
    "iso:country":"BE",
    "sg:address":"Troonplaats 2",
    "sg:city":"Antwerpen",
    "sg:orig_category":"S\u00e9curit\u00e9 sociale",
    "sg:phone":"+32 3 237 32 10",
    "sg:postcode":"2018",
    "sg:province":"Antwerpen",
    "wof:name":"Vl. Neutraal Ziekenfonds",
    "wof:placetype":"venue"
},
  "geometry": {"coordinates":[4.3923082352,51.2033843994],"type":"Point"}
}