{
  "type": "Feature",
  "properties": {
    "addr:full":"Rechtestraat 26 Dilsen-stokkem (stokkem) Limburg 3650",
    "addr:housenumber":"26",
    "addr:postcode":"3650",
    "addr:street":"Rechtestraat",
    "iso:country":"BE",
    "sg:address":"Rechtestraat 26",
    "sg:city":"Dilsen-stokkem (stokkem)",
    "sg:classifiers":[
        {
            "category":"Home & Garden",
            "subcategory":"Home Furnishings",
            "type":"Retail Goods"
        }
    ],
    "sg:phone":"+32 89 75 76 16",
    "sg:postcode":"3650",
    "sg:province":"Limburg",
    "sg:tags":[
        "interior",
        "decoration"
    ],
    "wof:name":"Peeters P",
    "wof:placetype":"venue"
},
  "geometry": {"coordinates":[5.727396965,51.0364189148],"type":"Point"}
}