{
  "type": "Feature",
  "properties": {
    "addr:full":"Rue Nicolas Kinet 38 Li\u00c8ge Li\u00e8ge 4020",
    "addr:housenumber":"38",
    "addr:postcode":"4020",
    "addr:street":"Rue Nicolas Kinet",
    "iso:country":"BE",
    "sg:address":"Rue Nicolas Kinet 38",
    "sg:city":"Li\u00c8ge",
    "sg:orig_category":"Antiquit\u00e9s",
    "sg:phone":"+32 4 342 07 15",
    "sg:postcode":"4020",
    "sg:province":"Li\u00e8ge",
    "wof:name":"Pierre Delsemme",
    "wof:placetype":"venue"
},
  "geometry": {"coordinates":[5.6082229614,50.6476516724],"type":"Point"}
}