{
  "type": "Feature",
  "properties": {
    "iso:country":"BE",
    "sg:address":"Ijzendijkestraat 15",
    "sg:city":"Gent",
    "sg:classifiers":[
        {
            "category":"Real Estate",
            "subcategory":"Architect",
            "type":"Services"
        }
    ],
    "sg:phone":"+32 9 269 03 17",
    "sg:postcode":"9000",
    "sg:province":"Oost-Vlaanderen",
    "wof:name":"Schelstraete E",
    "wof:placetype":"venue"
},
  "geometry": {"coordinates":[3.7181949615,51.0658416748],"type":"Point"}
}