{
  "type": "Feature",
  "properties": {
    "iso:country":"BE",
    "sg:address":"R. Salzinnes Les Moulins 163",
    "sg:city":"Namur",
    "sg:orig_category":"Dakwerken",
    "sg:phone":"+32 81 74 71 44",
    "sg:postcode":"5000",
    "sg:province":"Namur",
    "wof:name":"Toiture Philippe",
    "wof:placetype":"venue"
},
  "geometry": {"coordinates":[4.8452811241,50.4707870483],"type":"Point"}
}