{
  "type": "Feature",
  "properties": {
    "addr:full":"Werkhuizenstraat 13 Vilvoorde Vlaams-Brabant 1800",
    "addr:housenumber":"13",
    "addr:postcode":"1800",
    "addr:street":"Werkhuizenstraat",
    "iso:country":"BE",
    "sg:address":"Werkhuizenstraat 13",
    "sg:city":"Vilvoorde",
    "sg:orig_category":"Mat\u00e9riel \u00e9lectrique and \u00e9lectronique Gr",
    "sg:phone":"+32 2 253 07 00",
    "sg:postcode":"1800",
    "sg:province":"Vlaams-Brabant",
    "wof:name":"Delaby New",
    "wof:placetype":"venue"
},
  "geometry": {"coordinates":[4.4218859673,50.9334602356],"type":"Point"}
}