{
  "type": "Feature",
  "properties": {
    "addr:full":"Chauss\u00e9e De Louvain 217 Wavre Brabant Wallon 1300",
    "addr:housenumber":"217;1300",
    "addr:street":"Chausse\u0301E De Louvain",
    "iso:country":"BE",
    "sg:address":"Chauss\u00e9e De Louvain 217",
    "sg:city":"Wavre",
    "sg:classifiers":[
        {
            "category":"Bakery",
            "type":"Food & Drink"
        }
    ],
    "sg:phone":"+32 10 24 79 82",
    "sg:postcode":"1300",
    "sg:province":"Brabant Wallon",
    "sg:tags":[
        "confectioner",
        "baker"
    ],
    "wof:name":"Pain D'antan (le)",
    "wof:placetype":"venue"
},
  "geometry": {"coordinates":[4.6228890419,50.7177238464],"type":"Point"}
}