{
  "type": "Feature",
  "properties": {
    "iso:country":"BE",
    "sg:address":"Mechelsesteenweg 284",
    "sg:city":"Edegem",
    "sg:classifiers":[
        {
            "category":"Parking",
            "subcategory":"Bicycle",
            "type":"Transportation"
        }
    ],
    "sg:phone":"+32 3 455 90 67",
    "sg:postcode":"2650",
    "sg:province":"Antwerpen",
    "sg:tags":[
        "rack"
    ],
    "wof:name":"Bozarc",
    "wof:placetype":"venue"
},
  "geometry": {"coordinates":[4.4613752365,51.1547088623],"type":"Point"}
}