{
  "type": "Feature",
  "properties": {
    "addr:full":"Place Reine-astrid 14 Li\u00e8ge 1 Li\u00e8ge 4000",
    "addr:housenumber":"14;1",
    "addr:postcode":"4000",
    "addr:street":"Place Reine-Astrid",
    "iso:country":"BE",
    "sg:address":"Place Reine-astrid 14",
    "sg:city":"Li\u00e8ge 1",
    "sg:classifiers":[
        {
            "category":"Health Services",
            "subcategory":"Dentist",
            "type":"Services"
        }
    ],
    "sg:phone":"+32 4 246 15 00",
    "sg:postcode":"4000",
    "sg:province":"Li\u00e8ge",
    "wof:name":"Vandenbulcke Richard",
    "wof:placetype":"venue"
},
  "geometry": {"coordinates":[5.5458898544,50.6760025024],"type":"Point"}
}