{
  "type": "Feature",
  "properties": {
    "addr:full":"Torenstraat 7b5 Roeselare West-Vlaanderen 8800",
    "addr:housenumber":"7b5",
    "addr:postcode":"8800",
    "addr:street":"Torenstraat",
    "iso:country":"BE",
    "sg:address":"Torenstraat 7b5",
    "sg:city":"Roeselare",
    "sg:classifiers":[
        {
            "category":"Shopping Center",
            "type":"Public Place"
        }
    ],
    "sg:phone":"+32 51 24 37 27",
    "sg:postcode":"8800",
    "sg:province":"West-Vlaanderen",
    "sg:tags":[
        "enseignement",
        "formation"
    ],
    "wof:name":"Centrum Voor Levenskunst",
    "wof:placetype":"venue"
},
  "geometry": {"coordinates":[3.1270060539,50.948348999],"type":"Point"}
}