{
  "type": "Feature",
  "properties": {
    "iso:country":"BE",
    "sg:address":"Rue Emile Gossiaux 4",
    "sg:city":"Les Bons Villers (villers-perwin)",
    "sg:classifiers":[
        {
            "category":"Home & Garden",
            "subcategory":"Building Materials",
            "type":"Retail Goods"
        }
    ],
    "sg:phone":"+32 71 85 24 29",
    "sg:postcode":"6210",
    "sg:province":"Hainaut",
    "sg:tags":[
        "shutter"
    ],
    "wof:name":"Dibat Sprl",
    "wof:placetype":"venue"
},
  "geometry": {"coordinates":[4.4511561394,50.5378227234],"type":"Point"}
}