{
  "type": "Feature",
  "properties": {
    "iso:country":"BE",
    "sg:address":"Rue Tribomont 43",
    "sg:city":"Pepinster (wegnez)",
    "sg:classifiers":[
        {
            "category":"Real Estate",
            "subcategory":"Surveying",
            "type":"Services"
        }
    ],
    "sg:phone":"+32 87 46 91 96",
    "sg:postcode":"4860",
    "sg:province":"Li\u00e8ge",
    "sg:tags":[
        "surveyor",
        "land"
    ],
    "wof:name":"R\u00e9simont P",
    "wof:placetype":"venue"
},
  "geometry": {"coordinates":[5.8120770454,50.5870895386],"type":"Point"}
}