{
  "type": "Feature",
  "properties": {
    "addr:full":"Place De L'eglise 2 Juprelle (slins) Li\u00e8ge 4450",
    "addr:housenumber":"2",
    "addr:postcode":"4450",
    "addr:street":"Place De L'Eglise;Slins",
    "iso:country":"BE",
    "sg:address":"Place De L'eglise 2",
    "sg:city":"Juprelle (slins)",
    "sg:classifiers":[
        {
            "category":"Building & Trades",
            "subcategory":"Electrical",
            "type":"Services"
        }
    ],
    "sg:phone":"+32 4 278 13 45",
    "sg:postcode":"4450",
    "sg:province":"Li\u00e8ge",
    "sg:tags":[
        "electric",
        "-",
        "housewiring",
        "contractor"
    ],
    "wof:name":"Nandelec Sprl",
    "wof:placetype":"venue"
},
  "geometry": {"coordinates":[5.5386519432,50.656036377],"type":"Point"}
}