{
  "type": "Feature",
  "properties": {
    "addr:full":"Poederleese Weg 16 Lille Antwerpen 2275",
    "addr:housenumber":"16",
    "addr:postcode":"2275",
    "addr:street":"Poederleese Weg",
    "iso:country":"BE",
    "sg:address":"Poederleese Weg 16",
    "sg:city":"Lille",
    "sg:classifiers":[
        {
            "category":"Food & Beverages",
            "subcategory":"Fruits & Vegetables",
            "type":"Retail Goods"
        }
    ],
    "sg:phone":"+32 14 88 02 75",
    "sg:postcode":"2275",
    "sg:province":"Antwerpen",
    "sg:tags":[
        "-"
    ],
    "wof:name":"Krawaatje ('t)",
    "wof:placetype":"venue"
},
  "geometry": {"coordinates":[4.8247442245,51.2377471924],"type":"Point"}
}