{
  "type": "Feature",
  "properties": {
    "addr:full":"Driesstraat 56 Bekkevoort Vlaams-Brabant 3461",
    "addr:housenumber":"56",
    "addr:postcode":"3461",
    "addr:street":"Driesstraat",
    "iso:country":"BE",
    "sg:address":"Driesstraat 56",
    "sg:city":"Bekkevoort",
    "sg:orig_category":"Fruitteelt",
    "sg:phone":"+32 16 63 44 86",
    "sg:postcode":"3461",
    "sg:province":"Vlaams-Brabant",
    "wof:name":"Georges Swillen",
    "wof:placetype":"venue"
},
  "geometry": {"coordinates":[4.9438471794,50.9253311157],"type":"Point"}
}