{
  "type": "Feature",
  "properties": {
    "iso:country":"BE",
    "sg:address":"Chauss\u00e9e De Luingne 26 Box 2b",
    "sg:city":"Mouscron (herseaux)",
    "sg:classifiers":[
        {
            "category":"Food & Beverages",
            "subcategory":"Meat & Fish",
            "type":"Retail Goods"
        }
    ],
    "sg:phone":"+32 56 34 69 89",
    "sg:postcode":"7712",
    "sg:province":"Hainaut",
    "sg:tags":[
        "-",
        "livestock"
    ],
    "wof:name":"Marc Walcarius Vanassche",
    "wof:placetype":"venue"
},
  "geometry": {"coordinates":[3.2535879612,50.714931488],"type":"Point"}
}