{
  "type": "Feature",
  "properties": {
    "addr:full":"Rue Baron De Castro 49 Bruxelles (etterbeek) Bruxelles-Capitale 1040",
    "addr:housenumber":"49",
    "addr:postcode":"1040",
    "addr:street":"Rue Baron De Castro",
    "iso:country":"BE",
    "sg:address":"Rue Baron De Castro 49",
    "sg:city":"Bruxelles (etterbeek)",
    "sg:classifiers":[
        {
            "category":"Health Services",
            "subcategory":"Doctor",
            "type":"Services"
        }
    ],
    "sg:phone":"+32 2 735 67 32",
    "sg:postcode":"1040",
    "sg:province":"Bruxelles-Capitale",
    "sg:tags":[
        "medicinephysicians",
        "surgeon"
    ],
    "wof:name":"De Dorlodot Ga\u00ebtan",
    "wof:placetype":"venue"
},
  "geometry": {"coordinates":[4.4064898491,50.8297653198],"type":"Point"}
}