{
  "type": "Feature",
  "properties": {
    "addr:full":"Moli\u00c8relaan 10 Vorst/forest Bruxelles-Capitale 1190",
    "addr:housenumber":"10",
    "addr:postcode":"1190",
    "addr:street":"Molie\u0300Relaan;/ Forest",
    "iso:country":"BE",
    "sg:address":"Moli\u00c8relaan 10",
    "sg:city":"Vorst/forest",
    "sg:orig_category":"Apotheken",
    "sg:phone":"+32 2 343 69 63",
    "sg:postcode":"1190",
    "sg:province":"Bruxelles-Capitale",
    "wof:name":"Carine Tombeur/c. Tombeur",
    "wof:placetype":"venue"
},
  "geometry": {"coordinates":[4.3402571678,50.8155021667],"type":"Point"}
}