{
  "type": "Feature",
  "properties": {
    "iso:country":"BE",
    "sg:address":"Meredorp 1",
    "sg:city":"Erpe-mere",
    "sg:orig_category":"Banken and kredietinstellingen",
    "sg:phone":"+32 53 83 34 53",
    "sg:postcode":"9420",
    "sg:province":"Oost-Vlaanderen",
    "wof:name":"Bbl",
    "wof:placetype":"venue"
},
  "geometry": {"coordinates":[3.9719600677,50.9228935242],"type":"Point"}
}