{
  "type": "Feature",
  "properties": {
    "iso:country":"BE",
    "sg:address":"Meldertsestraat 83",
    "sg:city":"Halen",
    "sg:orig_category":"Travaux de pl\u00e2trage",
    "sg:phone":"+32 13 33 42 47",
    "sg:postcode":"3545",
    "sg:province":"Limburg",
    "wof:name":"Leonardus Oyen",
    "wof:placetype":"venue"
},
  "geometry": {"coordinates":[5.1270289421,50.9917106628],"type":"Point"}
}