{
  "type": "Feature",
  "properties": {
    "iso:country":"BE",
    "sg:address":"Hippoliet Spilleboutdreef 1",
    "sg:city":"Roeselare",
    "sg:classifiers":[
        {
            "category":"Organizations",
            "subcategory":"Community Association",
            "type":"Services"
        }
    ],
    "sg:phone":"+32 51 26 57 00",
    "sg:postcode":"8800",
    "sg:province":"West-Vlaanderen",
    "sg:tags":[
        "cultural"
    ],
    "wof:name":"Cultureel Centrumde Spil Vzw",
    "wof:placetype":"venue"
},
  "geometry": {"coordinates":[3.1243329048,50.9376907349],"type":"Point"}
}