{
  "type": "Feature",
  "properties": {
    "addr:full":"Route De L'etat 178 Lasne Brabant Wallon 1380",
    "addr:housenumber":"178",
    "addr:postcode":"1380",
    "addr:street":"Route De L'Etat",
    "iso:country":"BE",
    "sg:address":"Route De L'etat 178",
    "sg:city":"Lasne",
    "sg:orig_category":"Peinture. Rev\u00eatements pour sols and murs. Eclairage et \u00e9quipements du foyer",
    "sg:phone":"+32 2 633 12 24",
    "sg:postcode":"1380",
    "sg:province":"Brabant Wallon",
    "wof:name":"Charlier Peinture",
    "wof:placetype":"venue"
},
  "geometry": {"coordinates":[4.4671797752,50.671043396],"type":"Point"}
}