{
  "type": "Feature",
  "properties": {
    "iso:country":"BE",
    "sg:address":"Goorstraat 95",
    "sg:city":"Boortmeerbeek",
    "sg:orig_category":"V\u00eatements",
    "sg:phone":"+32 15 62 07 79",
    "sg:postcode":"3191",
    "sg:province":"Vlaams-Brabant",
    "wof:name":"L.a. Sportwear",
    "wof:placetype":"venue"
},
  "geometry": {"coordinates":[4.529736042,50.9910850525],"type":"Point"}
}