{
  "type": "Feature",
  "properties": {
    "addr:full":"Leo De B\u00c9thunelaan 119 Aalst Oost-Vlaanderen 9300",
    "addr:housenumber":"119",
    "addr:postcode":"9300",
    "addr:street":"Leo;Be\u0301Thunelaan",
    "iso:country":"BE",
    "sg:address":"Leo De B\u00c9thunelaan 119",
    "sg:city":"Aalst",
    "sg:orig_category":"Boekhouders",
    "sg:phone":"+32 53 77 38 46",
    "sg:postcode":"9300",
    "sg:province":"Oost-Vlaanderen",
    "wof:name":"Veerle De Wilde",
    "wof:placetype":"venue"
},
  "geometry": {"coordinates":[4.0312719345,50.9320907593],"type":"Point"}
}