{
  "type": "Feature",
  "properties": {
    "iso:country":"BE",
    "sg:address":"Berkenstraat 6a",
    "sg:city":"Heist-op-den-berg",
    "sg:classifiers":[
        {
            "category":"Health Services",
            "subcategory":"Health Practitioner",
            "type":"Services"
        }
    ],
    "sg:phone":"+32 486 75 49 61",
    "sg:postcode":"2220",
    "sg:province":"Antwerpen",
    "sg:tags":[
        "alternative",
        "therapy",
        "treatment"
    ],
    "wof:name":"Hybbym Verhaegen A",
    "wof:placetype":"venue"
},
  "geometry": {"coordinates":[4.716905117,51.0762443542],"type":"Point"}
}