{
  "type": "Feature",
  "properties": {
    "iso:country":"BE",
    "sg:address":"Noorderlaan 111",
    "sg:city":"Antwerpen",
    "sg:orig_category":"Speciaalzaken",
    "sg:phone":"+32 3 544 96 66",
    "sg:postcode":"2030",
    "sg:province":"Antwerpen",
    "wof:name":"Nijkerk",
    "wof:placetype":"venue"
},
  "geometry": {"coordinates":[4.4181270599,51.2620811462],"type":"Point"}
}