{
  "type": "Feature",
  "properties": {
    "addr:full":"Chauss\u00e9e De Wavre 950 Bruxelles (etterbeek) Bruxelles-Capitale 1040",
    "addr:housenumber":"950",
    "addr:postcode":"1040",
    "addr:street":"Chausse\u0301E De Wavre",
    "iso:country":"BE",
    "sg:address":"Chauss\u00e9e De Wavre 950",
    "sg:city":"Bruxelles (etterbeek)",
    "sg:orig_category":"Non-Classified Establishments",
    "sg:phone":"+32 2 203 55 71",
    "sg:postcode":"1040",
    "sg:province":"Bruxelles-Capitale",
    "wof:name":"Garello",
    "wof:placetype":"venue"
},
  "geometry": {"coordinates":[4.3950099945,50.8274917603],"type":"Point"}
}