{
  "type": "Feature",
  "properties": {
    "iso:country":"BE",
    "sg:address":"Guido Gezellelaan 13",
    "sg:city":"Mortsel",
    "sg:orig_category":"Boekhouders",
    "sg:phone":"+32 3 440 67 32",
    "sg:postcode":"2640",
    "sg:province":"Antwerpen",
    "wof:name":"Nicole Du Tre",
    "wof:placetype":"venue"
},
  "geometry": {"coordinates":[4.445086956,51.1737556458],"type":"Point"}
}