{
  "type": "Feature",
  "properties": {
    "iso:country":"BE",
    "sg:address":"Kanunnik De Deckerstraat 58",
    "sg:city":"Mechelen",
    "sg:classifiers":[
        {
            "category":"Banks & Credit Unions",
            "subcategory":"Investment Brokerage",
            "type":"Services"
        }
    ],
    "sg:phone":"+32 15 20 23 64",
    "sg:postcode":"2800",
    "sg:province":"Antwerpen",
    "sg:tags":[
        "repair",
        "-",
        "installation",
        "sanitary",
        "article"
    ],
    "wof:name":"Lenie Bvba",
    "wof:placetype":"venue"
},
  "geometry": {"coordinates":[4.4769501686,51.0314903259],"type":"Point"}
}