{
  "type": "Feature",
  "properties": {
    "addr:full":"Rue Albert 1er 1 Peruwelz Hainaut 7600",
    "addr:housenumber":"1",
    "addr:postcode":"7600",
    "addr:street":"Rue Albert 1Er;Hainaut",
    "iso:country":"BE",
    "sg:address":"Rue Albert 1er 1",
    "sg:city":"Peruwelz",
    "sg:orig_category":"Supermarkten",
    "sg:phone":"+32 69 77 21 21",
    "sg:postcode":"7600",
    "sg:province":"Hainaut",
    "wof:name":"Gb Contact",
    "wof:placetype":"venue"
},
  "geometry": {"coordinates":[3.5908999443,50.508140564],"type":"Point"}
}