{
  "type": "Feature",
  "properties": {
    "iso:country":"BE",
    "sg:address":"Rue De Marbaix 149",
    "sg:city":"Montigny-le-tilleul",
    "sg:classifiers":[
        {
            "category":"Shopping",
            "subcategory":"Florist",
            "type":"Retail Goods"
        }
    ],
    "sg:phone":"+32 71 51 70 91",
    "sg:postcode":"6110",
    "sg:province":"Hainaut",
    "wof:name":"Fairy Flore",
    "wof:placetype":"venue"
},
  "geometry": {"coordinates":[4.3721761703,50.3667106628],"type":"Point"}
}