{
  "type": "Feature",
  "properties": {
    "iso:country":"BE",
    "sg:address":"Hulstestraat 2",
    "sg:city":"Oostrozebeke",
    "sg:orig_category":"Quincailleries",
    "sg:phone":"+32 56 66 85 63",
    "sg:postcode":"8780",
    "sg:province":"West-Vlaanderen",
    "wof:name":"Oostropaints",
    "wof:placetype":"venue"
},
  "geometry": {"coordinates":[3.3070819378,50.9172172546],"type":"Point"}
}