{
  "type": "Feature",
  "properties": {
    "addr:full":"Rue Du Grand Jour 7 Mons Hainaut 7000",
    "addr:housenumber":"7",
    "addr:postcode":"7000",
    "addr:street":"Rue Du Grand Jour;Hainaut",
    "iso:country":"BE",
    "sg:address":"Rue Du Grand Jour 7",
    "sg:city":"Mons",
    "sg:orig_category":"Accessoires vestimentaires. V\u00eatements pour Dames. Accessoires vestimentaires",
    "sg:phone":"+32 65 34 05 26",
    "sg:postcode":"7000",
    "sg:province":"Hainaut",
    "wof:name":"Perlei",
    "wof:placetype":"venue"
},
  "geometry": {"coordinates":[3.9553101063,50.4593696594],"type":"Point"}
}