{
  "type": "Feature",
  "properties": {
    "iso:country":"BE",
    "sg:address":"Hospicestraat 16",
    "sg:city":"Moerbeke",
    "sg:orig_category":"Algemeen secundair onderwijs Technisch and beroeps secundair onderwijs",
    "sg:phone":"+32 9 346 82 04",
    "sg:postcode":"9180",
    "sg:province":"Oost-Vlaanderen",
    "wof:name":"Middenschool",
    "wof:placetype":"venue"
},
  "geometry": {"coordinates":[3.9455609322,51.1747322083],"type":"Point"}
}