{
  "type": "Feature",
  "properties": {
    "iso:country":"BE",
    "sg:address":"Rue D'ailette 2",
    "sg:city":"P\u00e9ruwelz (baugnies)",
    "sg:classifiers":[
        {
            "category":"Professional",
            "subcategory":"Art Services",
            "type":"Services"
        }
    ],
    "sg:phone":"+32 69 35 48 26",
    "sg:postcode":"7604",
    "sg:province":"Hainaut",
    "sg:tags":[
        "interior",
        "designer"
    ],
    "wof:name":"Extenso Sprl",
    "wof:placetype":"venue"
},
  "geometry": {"coordinates":[3.5478711128,50.5596427917],"type":"Point"}
}