{
  "type": "Feature",
  "properties": {
    "iso:country":"BE",
    "sg:address":"Krokusstraat 26",
    "sg:city":"Sint-truiden",
    "sg:classifiers":[
        {
            "category":"Cinema",
            "subcategory":"Movie Rental",
            "type":"Entertainment"
        }
    ],
    "sg:phone":"+32 11 69 60 34",
    "sg:postcode":"3800",
    "sg:province":"Limburg",
    "sg:tags":[
        "de",
        "cassette",
        "location",
        "vid\u00e9o",
        "audio"
    ],
    "wof:name":"Dreams Factory",
    "wof:placetype":"venue"
},
  "geometry": {"coordinates":[5.1807260513,50.8249397278],"type":"Point"}
}