{
  "type": "Feature",
  "properties": {
    "iso:country":"BE",
    "sg:address":"Kasteelstraat 16",
    "sg:city":"Temse",
    "sg:orig_category":"Musea and historische gebouwen",
    "sg:phone":"+32 3 771 48 18",
    "sg:postcode":"9140",
    "sg:province":"Oost-Vlaanderen",
    "wof:name":"Gemeentemuseum Temse",
    "wof:placetype":"venue"
},
  "geometry": {"coordinates":[4.2151141167,51.1247177124],"type":"Point"}
}