{
  "type": "Feature",
  "properties": {
    "addr:full":"Dadizelestraat 34a Wervik (geluwe) West-Vlaanderen 8940",
    "addr:housenumber":"34a",
    "addr:postcode":"8940",
    "addr:street":"Dadizelestraat",
    "iso:country":"BE",
    "sg:address":"Dadizelestraat 34a",
    "sg:city":"Wervik (geluwe)",
    "sg:classifiers":[
        {
            "category":"Professional",
            "subcategory":"Management & Consulting",
            "type":"Services"
        }
    ],
    "sg:phone":"+32 56 50 29 74",
    "sg:postcode":"8940",
    "sg:province":"West-Vlaanderen",
    "sg:tags":[
        "consultant"
    ],
    "wof:name":"Conduct",
    "wof:placetype":"venue"
},
  "geometry": {"coordinates":[3.0862059593,50.8297538757],"type":"Point"}
}