{
  "type": "Feature",
  "properties": {
    "addr:full":"Rue De Jemelle 35 Nassogne Luxembourg 6953",
    "addr:housenumber":"35",
    "addr:postcode":"6953",
    "addr:street":"Rue De Jemelle",
    "iso:country":"BE",
    "sg:address":"Rue De Jemelle 35",
    "sg:city":"Nassogne",
    "sg:orig_category":"Services de Nettoyage and de D\u00e9sinfection",
    "sg:phone":"+32 84 21 37 84",
    "sg:postcode":"6953",
    "sg:province":"Luxembourg",
    "wof:name":"Marc Ancion",
    "wof:placetype":"venue"
},
  "geometry": {"coordinates":[5.2792630196,50.1362342834],"type":"Point"}
}