{
  "type": "Feature",
  "properties": {
    "addr:full":"Rue De La P\u00eacherie 19 Antoing Hainaut 7640",
    "addr:housenumber":"19",
    "addr:postcode":"7640",
    "addr:street":"Rue De La Pe\u0302Cherie",
    "iso:country":"BE",
    "sg:address":"Rue De La P\u00eacherie 19",
    "sg:city":"Antoing",
    "sg:classifiers":[
        {
            "category":"Health Services",
            "subcategory":"Doctor",
            "type":"Services"
        }
    ],
    "sg:phone":"+32 69 44 31 31",
    "sg:postcode":"7640",
    "sg:province":"Hainaut",
    "sg:tags":[
        "medicinephysicians",
        "surgeon"
    ],
    "wof:name":"Bonsignore S",
    "wof:placetype":"venue"
},
  "geometry": {"coordinates":[3.4444589615,50.5664367676],"type":"Point"}
}