{
  "type": "Feature",
  "properties": {
    "addr:full":"Chauss\u00e9e Des Barri\u00e8res 33 Neufch\u00e2teau (tournay) Luxembourg 6840",
    "addr:housenumber":"33",
    "addr:postcode":"6840",
    "addr:street":"Chausse\u0301E Des Barrie\u0300Res",
    "iso:country":"BE",
    "sg:address":"Chauss\u00e9e Des Barri\u00e8res 33",
    "sg:city":"Neufch\u00e2teau (tournay)",
    "sg:classifiers":[
        {
            "category":"Retail",
            "subcategory":"Veterinary Services",
            "type":"Services"
        }
    ],
    "sg:phone":"+32 61 27 75 55",
    "sg:postcode":"6840",
    "sg:province":"Luxembourg",
    "sg:tags":[
        "veterinarian"
    ],
    "wof:name":"Spronck Ch",
    "wof:placetype":"venue"
},
  "geometry": {"coordinates":[5.3754191399,49.841594696],"type":"Point"}
}