{
  "type": "Feature",
  "properties": {
    "addr:full":"Lange Zandstraat 6a Sint-katelijne-waver Antwerpen 2860",
    "addr:housenumber":"6a",
    "addr:postcode":"2860",
    "addr:street":"Lange Zandstraat",
    "iso:country":"BE",
    "sg:address":"Lange Zandstraat 6a",
    "sg:city":"Sint-katelijne-waver",
    "sg:classifiers":[
        {
            "category":"Wholesale",
            "subcategory":"Home Furnishings",
            "type":"Manufacturing & Wholesale Goods"
        }
    ],
    "sg:phone":"+32 15 30 63 30",
    "sg:postcode":"2860",
    "sg:province":"Antwerpen",
    "sg:tags":[
        "-",
        "processing",
        "data",
        "computerroom"
    ],
    "wof:name":"Data Cabling & Connect Bvba",
    "wof:placetype":"venue"
},
  "geometry": {"coordinates":[4.4849200249,51.0701904297],"type":"Point"}
}