{
  "type": "Feature",
  "properties": {
    "iso:country":"BE",
    "sg:address":"Zoning Industriel",
    "sg:city":"Foret",
    "sg:classifiers":[
        {
            "category":"Manufacturing",
            "subcategory":"Building Materials",
            "type":"Manufacturing & Wholesale Goods"
        }
    ],
    "sg:phone":"+32 4 351 74 10",
    "sg:postcode":"4870",
    "sg:province":"Li\u00e8ge",
    "sg:tags":[
        "boiler",
        "manufacturer"
    ],
    "wof:name":"Atelier Berton",
    "wof:placetype":"venue"
},
  "geometry": {"coordinates":[5.6710000038,50.5784950256],"type":"Point"}
}