{
  "type": "Feature",
  "properties": {
    "addr:full":"Sneeuwbespad 2 Aarschot Vlaams-Brabant 3200",
    "addr:housenumber":"2",
    "addr:postcode":"3200",
    "addr:street":"Sneeuwbespad",
    "iso:country":"BE",
    "sg:address":"Sneeuwbespad 2",
    "sg:city":"Aarschot",
    "sg:classifiers":[
        {
            "category":"Arena",
            "subcategory":"Sports Club",
            "type":"Entertainment"
        }
    ],
    "sg:phone":"+32 16 56 15 13",
    "sg:postcode":"3200",
    "sg:province":"Vlaams-Brabant",
    "sg:tags":[
        "de"
    ],
    "wof:name":"B.b.c. Gele Ster Gelrode",
    "wof:placetype":"venue"
},
  "geometry": {"coordinates":[4.848443985,50.9988021851],"type":"Point"}
}