{
  "type": "Feature",
  "properties": {
    "iso:country":"BE",
    "sg:address":"Rue Du Cheminot 1",
    "sg:city":"Erquelinnes (bersillies - L'abbaye)",
    "sg:classifiers":[
        {
            "category":"Health Services",
            "subcategory":"Health Practitioner",
            "type":"Services"
        }
    ],
    "sg:phone":"+32 71 55 88 91",
    "sg:postcode":"6560",
    "sg:province":"Hainaut",
    "sg:tags":[
        "physiotherapist"
    ],
    "wof:name":"Penasse Stephanie",
    "wof:placetype":"venue"
},
  "geometry": {"coordinates":[4.1467747688,50.2644844055],"type":"Point"}
}