{
  "type": "Feature",
  "properties": {
    "iso:country":"BE",
    "sg:address":"Av. Des Croix De Guerre 190bb10",
    "sg:city":"Brussel/bruxelles",
    "sg:orig_category":"Experts-comptables",
    "sg:phone":"+32 2 268 02 26",
    "sg:postcode":"1120",
    "sg:province":"Bruxelles-Capitale",
    "wof:name":"Gaetano Mazzola",
    "wof:placetype":"venue"
},
  "geometry": {"coordinates":[4.3841781616,50.8915176392],"type":"Point"}
}