{
  "type": "Feature",
  "properties": {
    "addr:full":"Rue D'ordin 1 Jemeppe-sur-sambre (moustier-sur-sambre) Namur 5190",
    "addr:housenumber":"1",
    "addr:postcode":"5190",
    "addr:street":"Rue D'Ordin;Moustier-Sur-Sambre",
    "iso:country":"BE",
    "sg:address":"Rue D'ordin 1",
    "sg:city":"Jemeppe-sur-sambre (moustier-sur-sambre)",
    "sg:classifiers":[
        {
            "category":"Shopping",
            "subcategory":"Books",
            "type":"Retail Goods"
        }
    ],
    "sg:phone":"+32 71 78 14 79",
    "sg:postcode":"5190",
    "sg:province":"Namur",
    "sg:tags":[
        "bookseller"
    ],
    "wof:name":"Page \u00e0 Page",
    "wof:placetype":"venue"
},
  "geometry": {"coordinates":[4.6971030235,50.4666748047],"type":"Point"}
}