{
  "type": "Feature",
  "properties": {
    "iso:country":"BE",
    "sg:address":"Stoofstraat 43",
    "sg:city":"Merchtem",
    "sg:classifiers":[
        {
            "category":"Shopping",
            "subcategory":"Bicycles & Sporting Goods",
            "type":"Retail Goods"
        }
    ],
    "sg:phone":"+32 52 37 66 66",
    "sg:postcode":"1785",
    "sg:province":"Vlaams-Brabant",
    "sg:tags":[
        "tyre"
    ],
    "wof:name":"G S Bandencentrale",
    "wof:placetype":"venue"
},
  "geometry": {"coordinates":[4.2350411415,50.9572753906],"type":"Point"}
}