{
  "type": "Feature",
  "properties": {
    "addr:full":"Rue Joseph Wauters 31 Charleroi (dampremy) Hainaut 6020",
    "addr:housenumber":"31",
    "addr:postcode":"6020",
    "addr:street":"Rue Joseph Wauters",
    "iso:country":"BE",
    "sg:address":"Rue Joseph Wauters 31",
    "sg:city":"Charleroi (dampremy)",
    "sg:classifiers":[
        {
            "category":"Education",
            "subcategory":"Dance Studio",
            "type":"Public Place"
        }
    ],
    "sg:phone":"+32 71 30 31 65",
    "sg:postcode":"6020",
    "sg:province":"Hainaut",
    "sg:tags":[
        "pallet"
    ],
    "wof:name":"B.m.p. Sprl",
    "wof:placetype":"venue"
},
  "geometry": {"coordinates":[4.4313192368,50.4148025513],"type":"Point"}
}