{
  "type": "Feature",
  "properties": {
    "addr:full":"Nijverheidsweg 89 Ham (oostham) Limburg 3945",
    "addr:housenumber":"89",
    "addr:postcode":"oostham;3945",
    "addr:street":"Nijverheidsweg",
    "iso:country":"BE",
    "sg:address":"Nijverheidsweg 89",
    "sg:city":"Ham (oostham)",
    "sg:classifiers":[
        {
            "category":"Home & Garden",
            "subcategory":"Carpets & Floor Coverings",
            "type":"Retail Goods"
        }
    ],
    "sg:phone":"+32 11 34 04 32",
    "sg:postcode":"3945",
    "sg:province":"Limburg",
    "sg:tags":[
        "material",
        "waterproofing"
    ],
    "wof:name":"Thoro",
    "wof:placetype":"venue"
},
  "geometry": {"coordinates":[5.1776199341,51.1046104431],"type":"Point"}
}