{
  "type": "Feature",
  "properties": {
    "addr:full":"Rue Richard Vandevelde 44 Bruxelles (schaerbeek) Bruxelles-Capitale 1030",
    "addr:housenumber":"44",
    "addr:postcode":"1030",
    "addr:street":"Rue Richard Vandevelde",
    "iso:country":"BE",
    "sg:address":"Rue Richard Vandevelde 44",
    "sg:city":"Bruxelles (schaerbeek)",
    "sg:classifiers":[
        {
            "category":"Shopping",
            "subcategory":"Clothing, Apparel, & Fashions",
            "type":"Retail Goods"
        }
    ],
    "sg:phone":"+32 2 242 49 94",
    "sg:postcode":"1030",
    "sg:province":"Bruxelles-Capitale",
    "sg:tags":[
        "boutique"
    ],
    "wof:name":"North-east",
    "wof:placetype":"venue"
},
  "geometry": {"coordinates":[4.3885908127,50.8730583191],"type":"Point"}
}