{
  "type": "Feature",
  "properties": {
    "iso:country":"BE",
    "sg:address":"Brieversweg 79",
    "sg:city":"Damme",
    "sg:orig_category":"Eclairage et \u00e9quipements du foyer",
    "sg:phone":"+32 50 50 02 30",
    "sg:postcode":"8340",
    "sg:province":"West-Vlaanderen",
    "wof:name":"Stefaan Huys",
    "wof:placetype":"venue"
},
  "geometry": {"coordinates":[3.3196649551,51.2202110291],"type":"Point"}
}