{
  "type": "Feature",
  "properties": {
    "iso:country":"BE",
    "sg:address":"Akkerveken 20",
    "sg:city":"Wuustwezel",
    "sg:orig_category":"Eleveurs de bovins",
    "sg:phone":"+32 3 669 75 86",
    "sg:postcode":"2990",
    "sg:province":"Antwerpen",
    "wof:name":"Willy Augustijns",
    "wof:placetype":"venue"
},
  "geometry": {"coordinates":[4.5465807915,51.3714828491],"type":"Point"}
}