{
  "type": "Feature",
  "properties": {
    "addr:full":"Koning Albert-i-laan 100 Blankenberge West-Vlaanderen 8370",
    "addr:housenumber":"100",
    "addr:postcode":"8370",
    "addr:street":"Koning Albert-I-Laan",
    "iso:country":"BE",
    "sg:address":"Koning Albert-i-laan 100",
    "sg:city":"Blankenberge",
    "sg:orig_category":"Rev\u00eatements pour sols and murs. Peinture",
    "sg:phone":"+32 50 42 69 33",
    "sg:postcode":"8370",
    "sg:province":"West-Vlaanderen",
    "wof:name":"Christiaan Vervoort",
    "wof:placetype":"venue"
},
  "geometry": {"coordinates":[3.1402230263,51.3139228821],"type":"Point"}
}