{
  "type": "Feature",
  "properties": {
    "iso:country":"BE",
    "sg:address":"Weg Naar Zwartberg 240",
    "sg:city":"Opglabbeek",
    "sg:classifiers":[
        {
            "category":"Home & Garden",
            "subcategory":"Home Furnishings",
            "type":"Retail Goods"
        }
    ],
    "sg:phone":"+32 89 85 23 19",
    "sg:postcode":"3660",
    "sg:province":"Limburg",
    "sg:tags":[
        "curtain",
        "-",
        "fixture"
    ],
    "wof:name":"Sandra Decoratie Technieken",
    "wof:placetype":"venue"
},
  "geometry": {"coordinates":[5.5497097969,51.0332603455],"type":"Point"}
}