{
  "type": "Feature",
  "properties": {
    "addr:full":"Langestraat 183 Brugge West-Vlaanderen 8000",
    "addr:housenumber":"183",
    "addr:postcode":"8000",
    "addr:street":"Langestraat",
    "iso:country":"BE",
    "sg:address":"Langestraat 183",
    "sg:city":"Brugge",
    "sg:orig_category":"Decoratieve kunst and kunstbenodigdheden Glaszetten and glaswerk Serres and speciale beglazing",
    "sg:phone":"+32 50 33 74 23",
    "sg:postcode":"8000",
    "sg:province":"West-Vlaanderen",
    "wof:name":"Glaslux",
    "wof:placetype":"venue"
},
  "geometry": {"coordinates":[3.2394421101,51.2126502991],"type":"Point"}
}