{
  "type": "Feature",
  "properties": {
    "iso:country":"BE",
    "sg:address":"Maaseikersteenweg 235",
    "sg:city":"Lanaken",
    "sg:classifiers":[
        {
            "category":"Retail",
            "subcategory":"Auto Repair",
            "type":"Services"
        }
    ],
    "sg:phone":"+32 89 72 14 04",
    "sg:postcode":"3620",
    "sg:province":"Limburg",
    "sg:tags":[
        "garage"
    ],
    "wof:name":"Carlise M",
    "wof:placetype":"venue"
},
  "geometry": {"coordinates":[5.6746788025,50.8935966492],"type":"Point"}
}