{
  "type": "Feature",
  "properties": {
    "addr:full":"Rue Du Romarin 79 Comines-warneton (ploegsteert) Hainaut 7782",
    "addr:housenumber":"79",
    "addr:postcode":"7782",
    "addr:street":"Rue Du Romarin",
    "iso:country":"BE",
    "sg:address":"Rue Du Romarin 79",
    "sg:city":"Comines-warneton (ploegsteert)",
    "sg:classifiers":[
        {
            "category":"Bars & Pubs",
            "subcategory":"Sports Bar",
            "type":"Food & Drink"
        }
    ],
    "sg:phone":"+32 56 58 72 33",
    "sg:postcode":"7782",
    "sg:province":"Hainaut",
    "wof:name":"L & S Dyna Life",
    "wof:placetype":"venue"
},
  "geometry": {"coordinates":[2.8795371056,50.7278747559],"type":"Point"}
}