{
  "type": "Feature",
  "properties": {
    "addr:full":"Rue Du Centenaire 8 Sombreffe Namur 5140",
    "addr:housenumber":"8",
    "addr:postcode":"5140",
    "addr:street":"Rue Du Centenaire",
    "iso:country":"BE",
    "sg:address":"Rue Du Centenaire 8",
    "sg:city":"Sombreffe",
    "sg:orig_category":"Epiceries",
    "sg:phone":"+32 71 88 93 64",
    "sg:postcode":"5140",
    "sg:province":"Namur",
    "wof:name":"Poids D'or",
    "wof:placetype":"venue"
},
  "geometry": {"coordinates":[4.5725870132,50.512336731],"type":"Point"}
}