{
  "type": "Feature",
  "properties": {
    "iso:country":"BE",
    "sg:address":"Rue De La Hestre 107",
    "sg:city":"La Louviere",
    "sg:orig_category":"Salles de conf\u00e9rences and de r\u00e9ceptions",
    "sg:phone":"+32 64 28 02 69",
    "sg:postcode":"7100",
    "sg:province":"Hainaut",
    "wof:name":"Salons La Fontaine",
    "wof:placetype":"venue"
},
  "geometry": {"coordinates":[4.1850848198,50.4748649597],"type":"Point"}
}