{
  "type": "Feature",
  "properties": {
    "iso:country":"BE",
    "sg:address":"Chauss\u00e9e De Nivelles 3h",
    "sg:city":"Gembloux-sur-orneau (mazy)",
    "sg:classifiers":[
        {
            "category":"Wholesale",
            "subcategory":"Construction Materials",
            "type":"Manufacturing & Wholesale Goods"
        }
    ],
    "sg:phone":"+32 2 772 30 85",
    "sg:postcode":"5032",
    "sg:province":"Namur",
    "sg:tags":[
        "elevator"
    ],
    "wof:name":"Elfac Sprl",
    "wof:placetype":"venue"
},
  "geometry": {"coordinates":[4.6812200546,50.5105743408],"type":"Point"}
}