{
  "type": "Feature",
  "properties": {
    "iso:country":"BE",
    "sg:address":"Dellestraat 3ba",
    "sg:city":"Lummen",
    "sg:orig_category":"G\u00e2teaux, p\u00e2tisserie and biscuits Fab",
    "sg:phone":"+32 13 53 12 79",
    "sg:postcode":"3560",
    "sg:province":"Limburg",
    "wof:name":"Huis Vide Marleen",
    "wof:placetype":"venue"
},
  "geometry": {"coordinates":[5.2362089157,50.9942512512],"type":"Point"}
}