{
  "type": "Feature",
  "properties": {
    "iso:country":"BE",
    "sg:address":"Zeedijk 290",
    "sg:city":"Oostende",
    "sg:orig_category":"Villages de vacances",
    "sg:phone":"+32 59 55 27 55",
    "sg:postcode":"8400",
    "sg:province":"West-Vlaanderen",
    "wof:name":"Ravelingen",
    "wof:placetype":"venue"
},
  "geometry": {"coordinates":[2.8583700657,51.2067070007],"type":"Point"}
}