{
  "type": "Feature",
  "properties": {
    "addr:full":"Walplein 39 Brugge West-Vlaanderen 8000",
    "addr:housenumber":"39",
    "addr:postcode":"8000",
    "addr:street":"Walplein",
    "iso:country":"BE",
    "sg:address":"Walplein 39",
    "sg:city":"Brugge",
    "sg:classifiers":[
        {
            "category":"Professional",
            "subcategory":"Art Services",
            "type":"Services"
        }
    ],
    "sg:phone":"+32 477 42 47 91",
    "sg:postcode":"8000",
    "sg:province":"West-Vlaanderen",
    "sg:tags":[
        "interior",
        "designer"
    ],
    "wof:name":"Gryp A",
    "wof:placetype":"venue"
},
  "geometry": {"coordinates":[3.2241289616,51.2030677795],"type":"Point"}
}