{
  "type": "Feature",
  "properties": {
    "addr:full":"Aardenburgkalseide 254 Maldegem Oost-Vlaanderen 9990",
    "addr:housenumber":"254",
    "addr:postcode":"9990",
    "iso:country":"BE",
    "sg:address":"Aardenburgkalseide 254",
    "sg:city":"Maldegem",
    "sg:classifiers":[
        {
            "category":"Professional",
            "subcategory":"Computer Services",
            "type":"Services"
        }
    ],
    "sg:phone":"+32 50 71 84 00",
    "sg:postcode":"9990",
    "sg:province":"Oost-Vlaanderen",
    "sg:tags":[
        "webdesign",
        "-",
        "internet"
    ],
    "wof:name":"Ncc+",
    "wof:placetype":"venue"
},
  "geometry": {"coordinates":[3.4467310905,51.2226448059],"type":"Point"}
}