{
  "type": "Feature",
  "properties": {
    "iso:country":"BE",
    "sg:address":"Rue Libert Lanis 51",
    "sg:city":"Braine-le-chateau",
    "sg:orig_category":"Rusthuizen and serviceflats",
    "sg:phone":"+32 2 366 91 13",
    "sg:postcode":"1440",
    "sg:province":"Brabant Wallon",
    "wof:name":"Les Primev\u00c8res",
    "wof:placetype":"venue"
},
  "geometry": {"coordinates":[4.2755479813,50.6821098328],"type":"Point"}
}