{
  "type": "Feature",
  "properties": {
    "iso:country":"BE",
    "sg:address":"Zeedijk 146",
    "sg:city":"Oostende",
    "sg:classifiers":[
        {
            "category":"Shopping",
            "subcategory":"Clothing, Apparel, & Fashions",
            "type":"Retail Goods"
        }
    ],
    "sg:phone":"+32 59 70 92 80",
    "sg:postcode":"8400",
    "sg:province":"West-Vlaanderen",
    "sg:tags":[
        "lady",
        "clothing",
        "-"
    ],
    "wof:name":"Neptune (boetiek)",
    "wof:placetype":"venue"
},
  "geometry": {"coordinates":[2.8583700657,51.2067070007],"type":"Point"}
}