{
  "type": "Feature",
  "properties": {
    "addr:full":"Zilverstraat 3 Linter Vlaams-Brabant 3350",
    "addr:housenumber":"3",
    "addr:postcode":"3350",
    "addr:street":"Zilverstraat;Vlaams-Brabant",
    "iso:country":"BE",
    "sg:address":"Zilverstraat 3",
    "sg:city":"Linter",
    "sg:orig_category":"Tuinbenodigdheden",
    "sg:phone":"+32 11 78 27 19",
    "sg:postcode":"3350",
    "sg:province":"Vlaams-Brabant",
    "wof:name":"Fa. Vangrimde",
    "wof:placetype":"venue"
},
  "geometry": {"coordinates":[5.0576720238,50.8210372925],"type":"Point"}
}