{
  "type": "Feature",
  "properties": {
    "iso:country":"BE",
    "sg:address":"Rue De La Station 142",
    "sg:city":"Le Roeulx",
    "sg:orig_category":"MEUBELONTWERP AND -INSTALLATIE",
    "sg:phone":"+32 64 67 75 60",
    "sg:postcode":"7070",
    "sg:province":"Hainaut",
    "wof:name":"C.m. Hennecart",
    "wof:placetype":"venue"
},
  "geometry": {"coordinates":[4.1193099022,50.5094604492],"type":"Point"}
}