{
  "type": "Feature",
  "properties": {
    "addr:full":"Rue Fr\u00e9d\u00e9ric Mohrfeld 1 Bruxelles (jette) Bruxelles-Capitale 1090",
    "addr:housenumber":"1",
    "addr:postcode":"1090",
    "addr:street":"Rue Fre\u0301De\u0301Ric Mohrfeld",
    "iso:country":"BE",
    "sg:address":"Rue Fr\u00e9d\u00e9ric Mohrfeld 1",
    "sg:city":"Bruxelles (jette)",
    "sg:classifiers":[
        {
            "category":"Personal",
            "subcategory":"Beauty Salon",
            "type":"Services"
        }
    ],
    "sg:phone":"+32 2 479 28 27",
    "sg:postcode":"1090",
    "sg:province":"Bruxelles-Capitale",
    "sg:tags":[
        "lady",
        "-",
        "hairdressing"
    ],
    "wof:name":"Jany",
    "wof:placetype":"venue"
},
  "geometry": {"coordinates":[4.3234729767,50.8846588135],"type":"Point"}
}