{
  "type": "Feature",
  "properties": {
    "addr:full":"Beukenlaan 7 Beveren (kieldrecht) Oost-Vlaanderen 9130",
    "addr:housenumber":"7",
    "addr:postcode":"9130",
    "addr:street":"Beukenlaan",
    "iso:country":"BE",
    "sg:address":"Beukenlaan 7",
    "sg:city":"Beveren (kieldrecht)",
    "sg:classifiers":[
        {
            "category":"Professional",
            "subcategory":"Lawyer & Legal Services",
            "type":"Services"
        }
    ],
    "sg:phone":"+32 3 773 47 12",
    "sg:postcode":"9130",
    "sg:province":"Oost-Vlaanderen",
    "sg:tags":[
        "notary"
    ],
    "wof:name":"Van Der Auwermeulen M",
    "wof:placetype":"venue"
},
  "geometry": {"coordinates":[4.1764068604,51.2904701233],"type":"Point"}
}