{
  "type": "Feature",
  "properties": {
    "addr:full":"Markt Bilzen Limburg 3740",
    "addr:postcode":"3740",
    "addr:street":"Markt",
    "iso:country":"BE",
    "sg:address":"Markt",
    "sg:city":"Bilzen",
    "sg:classifiers":[
        {
            "category":"Food & Beverages",
            "subcategory":"Chocolate",
            "type":"Retail Goods"
        }
    ],
    "sg:phone":"+32 89 41 53 75",
    "sg:postcode":"3740",
    "sg:province":"Limburg",
    "sg:tags":[
        "confectionery",
        "-"
    ],
    "wof:name":"Leonidas Bilzen",
    "wof:placetype":"venue"
},
  "geometry": {"coordinates":[5.5168099403,50.8704566956],"type":"Point"}
}