{
  "type": "Feature",
  "properties": {
    "iso:country":"BE",
    "sg:address":"Rue De La Brasserie 1",
    "sg:city":"Wasseiges",
    "sg:orig_category":"Instituts de beaut\u00e9",
    "sg:phone":"+32 81 85 58 63",
    "sg:postcode":"4219",
    "sg:province":"Li\u00e8ge",
    "wof:name":"Annie Godbille",
    "wof:placetype":"venue"
},
  "geometry": {"coordinates":[5.0174489021,50.6091766357],"type":"Point"}
}