{
  "type": "Feature",
  "properties": {
    "addr:full":"Harelbekestraat 12 Deerlijk West-Vlaanderen 8540",
    "addr:housenumber":"12",
    "addr:postcode":"8540",
    "addr:street":"Harelbekestraat",
    "iso:country":"BE",
    "sg:address":"Harelbekestraat 12",
    "sg:city":"Deerlijk",
    "sg:orig_category":"Diverse kredietdiensten",
    "sg:postcode":"8540",
    "sg:province":"West-Vlaanderen",
    "wof:name":"Bancontact-mister Cash",
    "wof:placetype":"venue"
},
  "geometry": {"coordinates":[3.352864027,50.8525619507],"type":"Point"}
}