{
  "type": "Feature",
  "properties": {
    "addr:full":"Route De Gembloux 97 Eghez\u00c9e Namur 5310",
    "addr:housenumber":"97",
    "addr:postcode":"5310",
    "addr:street":"Route De Gembloux",
    "iso:country":"BE",
    "sg:address":"Route De Gembloux 97",
    "sg:city":"Eghez\u00c9e",
    "sg:orig_category":"Administration d'immeubles",
    "sg:phone":"+32 81 81 24 96",
    "sg:postcode":"5310",
    "sg:province":"Namur",
    "wof:name":"Kotimmo",
    "wof:placetype":"venue"
},
  "geometry": {"coordinates":[4.9023051262,50.591632843],"type":"Point"}
}