{
  "type": "Feature",
  "properties": {
    "addr:full":"Rue Des Faweux 39 Beyne-heusay (queue-du-bois) Li\u00e8ge 4610",
    "addr:housenumber":"39",
    "addr:postcode":"4610",
    "addr:street":"Rue Des Faweux",
    "iso:country":"BE",
    "sg:address":"Rue Des Faweux 39",
    "sg:city":"Beyne-heusay (queue-du-bois)",
    "sg:classifiers":[
        {
            "category":"Professional",
            "subcategory":"Management & Consulting",
            "type":"Services"
        }
    ],
    "sg:phone":"+32 4 367 67 64",
    "sg:postcode":"4610",
    "sg:province":"Li\u00e8ge",
    "sg:tags":[
        "-",
        "processing",
        "data",
        "consultant"
    ],
    "wof:name":"Abaye Faweux (l')",
    "wof:placetype":"venue"
},
  "geometry": {"coordinates":[5.6586241722,50.630405426],"type":"Point"}
}