{
  "type": "Feature",
  "properties": {
    "iso:country":"BE",
    "sg:address":"Rue De Soignies 14",
    "sg:city":"Nivelles",
    "sg:classifiers":[
        {
            "category":"Health Services",
            "subcategory":"Dentist",
            "type":"Services"
        }
    ],
    "sg:phone":"+32 67 84 08 48",
    "sg:postcode":"1400",
    "sg:province":"Brabant Wallon",
    "wof:name":"Nolmans B\u00e9n\u00e9dicte",
    "wof:placetype":"venue"
},
  "geometry": {"coordinates":[4.3210849762,50.5975494385],"type":"Point"}
}