{
  "type": "Feature",
  "properties": {
    "addr:full":"Savaartlindestraat 1 Heuvelland (kemmel) West-Vlaanderen 8956",
    "addr:housenumber":"1",
    "addr:postcode":"8956",
    "addr:street":"Savaartlindestraat",
    "iso:country":"BE",
    "sg:address":"Savaartlindestraat 1",
    "sg:city":"Heuvelland (kemmel)",
    "sg:classifiers":[
        {
            "category":"Wholesale",
            "subcategory":"Plants",
            "type":"Manufacturing & Wholesale Goods"
        }
    ],
    "sg:phone":"+32 57 44 88 80",
    "sg:postcode":"8956",
    "sg:province":"West-Vlaanderen",
    "sg:tags":[
        "whol",
        "flower",
        "-",
        "grower"
    ],
    "wof:name":"Debraeve M",
    "wof:placetype":"venue"
},
  "geometry": {"coordinates":[2.851788044,50.7849845886],"type":"Point"}
}