{
  "type": "Feature",
  "properties": {
    "iso:country":"BE",
    "sg:address":"Houte 33",
    "sg:city":"Oosterzele (balegem)",
    "sg:classifiers":[
        {
            "category":"Bars & Pubs",
            "type":"Food & Drink"
        }
    ],
    "sg:phone":"+32 9 362 18 27",
    "sg:postcode":"9860",
    "sg:province":"Oost-Vlaanderen",
    "wof:name":"Gasthof Ganzenhof",
    "wof:placetype":"venue"
},
  "geometry": {"coordinates":[3.8230929375,50.9421424866],"type":"Point"}
}