{
  "type": "Feature",
  "properties": {
    "addr:full":"Rietmusweg 87 Tongeren Limburg 3700",
    "addr:housenumber":"87",
    "addr:postcode":"3700",
    "addr:street":"Rietmusweg",
    "iso:country":"BE",
    "sg:address":"Rietmusweg 87",
    "sg:city":"Tongeren",
    "sg:classifiers":[
        {
            "category":"Professional",
            "subcategory":"Business Services",
            "type":"Services"
        }
    ],
    "sg:phone":"+32 12 23 53 65",
    "sg:postcode":"3700",
    "sg:province":"Limburg",
    "sg:tags":[
        "travel",
        "fair"
    ],
    "wof:name":"Carpe Diem Nv",
    "wof:placetype":"venue"
},
  "geometry": {"coordinates":[5.4734559059,50.7686882019],"type":"Point"}
}