{
  "type": "Feature",
  "properties": {
    "iso:country":"BE",
    "sg:address":"Brakenlaan 38",
    "sg:city":"De Panne",
    "sg:orig_category":"Installation \u00e9lectrique r\u00e9sidentielle",
    "sg:phone":"+32 58 41 23 64",
    "sg:postcode":"8660",
    "sg:province":"West-Vlaanderen",
    "wof:name":"Elektro Verstraete",
    "wof:placetype":"venue"
},
  "geometry": {"coordinates":[2.5945010185,51.100112915],"type":"Point"}
}