{
  "type": "Feature",
  "properties": {
    "addr:full":"Brandestraat 33 Berlaar Antwerpen 2590",
    "addr:housenumber":"33",
    "addr:postcode":"2590",
    "addr:street":"Brandestraat",
    "iso:country":"BE",
    "sg:address":"Brandestraat 33",
    "sg:city":"Berlaar",
    "sg:orig_category":"Producteurs de l\u00e9gumes",
    "sg:phone":"+32 3 482 34 45",
    "sg:postcode":"2590",
    "sg:province":"Antwerpen",
    "wof:name":"Jozef Belmans",
    "wof:placetype":"venue"
},
  "geometry": {"coordinates":[4.6341347694,51.0931625366],"type":"Point"}
}