{
  "type": "Feature",
  "properties": {
    "iso:country":"BE",
    "sg:address":"Maagdenstraat 28",
    "sg:city":"Brugge",
    "sg:classifiers":[
        {
            "category":"Professional",
            "subcategory":"Art Services",
            "type":"Services"
        }
    ],
    "sg:phone":"+32 50 33 81 19",
    "sg:postcode":"8000",
    "sg:province":"West-Vlaanderen",
    "sg:tags":[
        "photographer"
    ],
    "wof:name":"Proot B",
    "wof:placetype":"venue"
},
  "geometry": {"coordinates":[3.2139310837,51.2039756775],"type":"Point"}
}