{
  "type": "Feature",
  "properties": {
    "addr:full":"Chauss\u00c9e De Jodoigne 56 Grez-doiceau Brabant Wallon 1390",
    "addr:housenumber":"56",
    "addr:postcode":"1390",
    "addr:street":"Chausse\u0301E De Jodoigne",
    "iso:country":"BE",
    "sg:address":"Chauss\u00c9e De Jodoigne 56",
    "sg:city":"Grez-doiceau",
    "sg:orig_category":"Artsen and specialisten",
    "sg:phone":"+32 10 84 43 60",
    "sg:postcode":"1390",
    "sg:province":"Brabant Wallon",
    "wof:name":"Jean-louis Huge",
    "wof:placetype":"venue"
},
  "geometry": {"coordinates":[4.7026848793,50.7364578247],"type":"Point"}
}