{
  "type": "Feature",
  "properties": {
    "addr:full":"Rue De La Rivierette 53 Saint-ghislain Hainaut 7330",
    "addr:housenumber":"53",
    "addr:postcode":"7330",
    "addr:street":"Rue De La Rivierette;Hainaut",
    "iso:country":"BE",
    "sg:address":"Rue De La Rivierette 53",
    "sg:city":"Saint-ghislain",
    "sg:orig_category":"Ecoles de pilotage de bateaux and d\u00b4avions",
    "sg:phone":"+32 65 64 27 27",
    "sg:postcode":"7330",
    "sg:province":"Hainaut",
    "wof:name":"Aeroclub Du Borinage",
    "wof:placetype":"venue"
},
  "geometry": {"coordinates":[3.8164761066,50.4583816528],"type":"Point"}
}