{
  "type": "Feature",
  "properties": {
    "iso:country":"BE",
    "sg:address":"Diksmuidse Heerweg 159",
    "sg:city":"Brugge",
    "sg:orig_category":"Enseignement maternel and primaire",
    "sg:phone":"+32 50 39 13 23",
    "sg:postcode":"8200",
    "sg:province":"West-Vlaanderen",
    "wof:name":"Gemeentelijke Basisschool",
    "wof:placetype":"venue"
},
  "geometry": {"coordinates":[3.1981649399,51.1982803345],"type":"Point"}
}