{
  "type": "Feature",
  "properties": {
    "addr:full":"Stationsstraat 63 Opwijk Vlaams-Brabant 1745",
    "addr:housenumber":"63",
    "addr:postcode":"1745",
    "addr:street":"Stationsstraat",
    "iso:country":"BE",
    "sg:address":"Stationsstraat 63",
    "sg:city":"Opwijk",
    "sg:classifiers":[
        {
            "category":"Health Services",
            "subcategory":"Health Practitioner",
            "type":"Services"
        }
    ],
    "sg:phone":"+32 52 35 11 35",
    "sg:postcode":"1745",
    "sg:province":"Vlaams-Brabant",
    "sg:tags":[
        "physiotherapist"
    ],
    "wof:name":"De Cock Harry",
    "wof:placetype":"venue"
},
  "geometry": {"coordinates":[4.1868700981,50.9746398926],"type":"Point"}
}