{
  "type": "Feature",
  "properties": {
    "iso:country":"BE",
    "sg:address":"Rue Pieds D'allouettes 51-53",
    "sg:city":"Naninne",
    "sg:orig_category":"Miscellaneous Products",
    "sg:phone":"+32 81 40 91 11",
    "sg:postcode":"5100",
    "sg:province":"Namur",
    "wof:name":"Mosa Import Sa",
    "wof:placetype":"venue"
},
  "geometry": {"coordinates":[4.9179000854,50.4181289673],"type":"Point"}
}