{
  "type": "Feature",
  "properties": {
    "iso:country":"BE",
    "sg:address":"Av De L'universit\u00e9 42",
    "sg:city":"Bruxelles",
    "sg:classifiers":[
        {
            "category":"Wholesale",
            "subcategory":"Machinery & Supplies",
            "type":"Manufacturing & Wholesale Goods"
        }
    ],
    "sg:phone":"+32 2 647 12 60",
    "sg:postcode":"1050",
    "sg:province":"Bruxelles-Capitale",
    "sg:tags":[
        "food",
        "processing",
        "-",
        "machine",
        "equipment",
        "engineering",
        "mechanical"
    ],
    "wof:name":"Van Reet Frederic M.",
    "wof:placetype":"venue"
},
  "geometry": {"coordinates":[4.3876299858,50.8147277832],"type":"Point"}
}