{
  "type": "Feature",
  "properties": {
    "addr:full":"Montl\u00c9on 108 Florenville Luxembourg 6823",
    "addr:housenumber":"108",
    "addr:postcode":"6823",
    "iso:country":"BE",
    "sg:address":"Montl\u00c9on 108",
    "sg:city":"Florenville",
    "sg:orig_category":"Rundveehouders",
    "sg:phone":"+32 61 31 18 94",
    "sg:postcode":"6823",
    "sg:province":"Luxembourg",
    "wof:name":"Dewitte Daniel & Valere",
    "wof:placetype":"venue"
},
  "geometry": {"coordinates":[5.3363361359,49.6183891296],"type":"Point"}
}