{
  "type": "Feature",
  "properties": {
    "iso:country":"BE",
    "sg:address":"Rue Du Vicinal 10",
    "sg:city":"Manhay (vaux-chavanne)",
    "sg:classifiers":[
        {
            "category":"Insurance",
            "subcategory":"Insurance Agent",
            "type":"Services"
        }
    ],
    "sg:phone":"+32 86 43 42 62",
    "sg:postcode":"6960",
    "sg:province":"Luxembourg",
    "sg:tags":[
        "broker"
    ],
    "wof:name":"Pottier M",
    "wof:placetype":"venue"
},
  "geometry": {"coordinates":[5.6800460815,50.2869567871],"type":"Point"}
}