{
  "type": "Feature",
  "properties": {
    "addr:full":"Gellenberg 53 Lubbeek Vlaams-Brabant 3210",
    "addr:housenumber":"53",
    "addr:postcode":"3210",
    "addr:street":"Gellenberg",
    "iso:country":"BE",
    "sg:address":"Gellenberg 53",
    "sg:city":"Lubbeek",
    "sg:classifiers":[
        {
            "category":"Professional",
            "subcategory":"Accounting & Tax Preparation",
            "type":"Services"
        }
    ],
    "sg:phone":"+32 16 64 00 53",
    "sg:postcode":"3210",
    "sg:province":"Vlaams-Brabant",
    "sg:tags":[
        "accountant"
    ],
    "wof:name":"G. Huyghebaert",
    "wof:placetype":"venue"
},
  "geometry": {"coordinates":[4.8355979919,50.8857040405],"type":"Point"}
}