{
  "type": "Feature",
  "properties": {
    "iso:country":"BE",
    "sg:address":"Kleine Snijdersstraat 44",
    "sg:city":"Lebbeke",
    "sg:classifiers":[
        {
            "category":"Building & Trades",
            "subcategory":"Electrical",
            "type":"Services"
        }
    ],
    "sg:phone":"+32 52 41 49 30",
    "sg:postcode":"9280",
    "sg:province":"Oost-Vlaanderen",
    "sg:tags":[
        "electric",
        "-",
        "housewiring",
        "contractor"
    ],
    "wof:name":"Fieremans E",
    "wof:placetype":"venue"
},
  "geometry": {"coordinates":[4.1491370201,51.0064926147],"type":"Point"}
}