{
  "type": "Feature",
  "properties": {
    "iso:country":"BE",
    "sg:address":"Clos Chapelle-aux-champs 31",
    "sg:city":"Brussel/bruxelles",
    "sg:orig_category":"Imprimeries and copyshops",
    "sg:phone":"+32 2 762 63 78",
    "sg:postcode":"1200",
    "sg:province":"Bruxelles-Capitale",
    "wof:name":"Clear Copy",
    "wof:placetype":"venue"
},
  "geometry": {"coordinates":[4.446914196,50.8487548828],"type":"Point"}
}