{
  "type": "Feature",
  "properties": {
    "addr:full":"Kon. Albertlaan 118 Lommel Limburg 3920",
    "addr:housenumber":"118",
    "addr:postcode":"3920",
    "addr:street":"Kon. Albertlaan",
    "iso:country":"BE",
    "sg:address":"Kon. Albertlaan 118",
    "sg:city":"Lommel",
    "sg:orig_category":"Telecommunicatieapparaten",
    "sg:phone":"+32 11 61 13 47",
    "sg:postcode":"3920",
    "sg:province":"Limburg",
    "wof:name":"Godeco",
    "wof:placetype":"venue"
},
  "geometry": {"coordinates":[5.3150830269,51.2379150391],"type":"Point"}
}