{
  "type": "Feature",
  "properties": {
    "iso:country":"BE",
    "sg:address":"Maria Theresialei 7",
    "sg:city":"Antwerpen (groot)",
    "sg:classifiers":[
        {
            "category":"Insurance",
            "subcategory":"Insurance Agent",
            "type":"Services"
        }
    ],
    "sg:phone":"+32 3 203 41 41",
    "sg:postcode":"2018",
    "sg:province":"Antwerpen",
    "sg:tags":[
        "verzekeringsmakelaars",
        "expert"
    ],
    "wof:name":"Omob",
    "wof:placetype":"venue"
},
  "geometry": {"coordinates":[4.4148879051,51.2156524658],"type":"Point"}
}