{
  "type": "Feature",
  "properties": {
    "addr:full":"Bronckaertsstraat 10a Geetbets (grazen) Vlaams-Brabant 3450",
    "addr:housenumber":"10a",
    "addr:postcode":"3450",
    "addr:street":"Bronckaertsstraat",
    "iso:country":"BE",
    "sg:address":"Bronckaertsstraat 10a",
    "sg:city":"Geetbets (grazen)",
    "sg:classifiers":[
        {
            "category":"Professional",
            "subcategory":"Accounting & Tax Preparation",
            "type":"Services"
        }
    ],
    "sg:phone":"+32 11 58 84 37",
    "sg:postcode":"3450",
    "sg:province":"Vlaams-Brabant",
    "sg:tags":[
        "accountant"
    ],
    "wof:name":"Accountants Gooris & Belien Bvba",
    "wof:placetype":"venue"
},
  "geometry": {"coordinates":[5.1377458572,50.8711891174],"type":"Point"}
}