{
  "type": "Feature",
  "properties": {
    "iso:country":"BE",
    "sg:address":"Becco Village 645ba",
    "sg:city":"Theux",
    "sg:orig_category":"Tuinen",
    "sg:phone":"+32 87 37 64 15",
    "sg:postcode":"4910",
    "sg:province":"Li\u00e8ge",
    "wof:name":"Alain Fonsny",
    "wof:placetype":"venue"
},
  "geometry": {"coordinates":[5.7875652313,50.5046272278],"type":"Point"}
}