{
  "type": "Feature",
  "properties": {
    "iso:country":"BE",
    "sg:address":"Rue De Chatelet 159",
    "sg:city":"Charleroi (marchienne-au-pont)",
    "sg:classifiers":[
        {
            "category":"Parking",
            "subcategory":"Lot",
            "type":"Transportation"
        }
    ],
    "sg:phone":"+32 71 47 20 86",
    "sg:postcode":"6030",
    "sg:province":"Hainaut",
    "sg:tags":[
        "armoured",
        "door",
        "fireproof"
    ],
    "wof:name":"Technimetal Sa",
    "wof:placetype":"venue"
},
  "geometry": {"coordinates":[4.4043259621,50.4066963196],"type":"Point"}
}