{
  "type": "Feature",
  "properties": {
    "addr:full":"Keuvelhoekstraat 120 Knokke-heist (knokke) West-Vlaanderen 8300",
    "addr:housenumber":"120",
    "addr:postcode":"8300",
    "addr:street":"Keuvelhoekstraat",
    "iso:country":"BE",
    "sg:address":"Keuvelhoekstraat 120",
    "sg:city":"Knokke-heist (knokke)",
    "sg:classifiers":[
        {
            "category":"Retail",
            "subcategory":"Repair Shop",
            "type":"Services"
        }
    ],
    "sg:phone":"+32 50 61 06 41",
    "sg:postcode":"8300",
    "sg:province":"West-Vlaanderen",
    "sg:tags":[
        "-",
        "mainten",
        "watch",
        "clock"
    ],
    "wof:name":"De Mulder L",
    "wof:placetype":"venue"
},
  "geometry": {"coordinates":[3.3029260635,51.339263916],"type":"Point"}
}