{
  "type": "Feature",
  "properties": {
    "addr:full":"Rue Asty-moulin 3 Namur Namur 5000",
    "addr:housenumber":"3",
    "addr:postcode":"5000",
    "addr:street":"Rue Asty-Moulin",
    "iso:country":"BE",
    "sg:address":"Rue Asty-moulin 3",
    "sg:city":"Namur",
    "sg:orig_category":"Diverse juridische dienstverlening",
    "sg:phone":"+32 81 74 69 30",
    "sg:postcode":"5000",
    "sg:province":"Namur",
    "wof:name":"Salle De Vente L'entrep\u00d4t",
    "wof:placetype":"venue"
},
  "geometry": {"coordinates":[4.8593797684,50.4701805115],"type":"Point"}
}