{
  "type": "Feature",
  "properties": {
    "addr:full":"Statiestraat 116 Zonnebeke (passendale) West-Vlaanderen 8980",
    "addr:housenumber":"116",
    "addr:postcode":"8980",
    "addr:street":"Statiestraat",
    "iso:country":"BE",
    "sg:address":"Statiestraat 116",
    "sg:city":"Zonnebeke (passendale)",
    "sg:classifiers":[
        {
            "category":"Manufacturing",
            "subcategory":"Metals",
            "type":"Manufacturing & Wholesale Goods"
        }
    ],
    "sg:phone":"+32 51 78 00 30",
    "sg:postcode":"8980",
    "sg:province":"West-Vlaanderen",
    "sg:tags":[
        "non-ferrous",
        "-"
    ],
    "wof:name":"Vandenbroucke Metalen Nv",
    "wof:placetype":"venue"
},
  "geometry": {"coordinates":[3.0355501175,50.895450592],"type":"Point"}
}