{
  "type": "Feature",
  "properties": {
    "addr:full":"Delaerestraat 10 Belgium West-Vlaanderen 8800",
    "addr:housenumber":"10",
    "addr:postcode":"8800",
    "addr:street":"Delaerestraat",
    "iso:country":"BE",
    "sg:address":"Delaerestraat 10",
    "sg:city":"Belgium",
    "sg:orig_category":"Informaticaconsulenten Software ontwikkeling and ontwerp",
    "sg:phone":"+32 51 25 23 11",
    "sg:postcode":"8800",
    "sg:province":"West-Vlaanderen",
    "wof:name":"Pro Db Solutions",
    "wof:placetype":"venue"
},
  "geometry": {"coordinates":[3.1276791096,50.9464187622],"type":"Point"}
}