{
  "type": "Feature",
  "properties": {
    "addr:full":"Rue Emile Vandervelde 19 Charleroi Hainaut 6001",
    "addr:housenumber":"19",
    "addr:postcode":"6001",
    "addr:street":"Rue Emile Vandervelde;Hainaut",
    "iso:country":"BE",
    "sg:address":"Rue Emile Vandervelde 19",
    "sg:city":"Charleroi",
    "sg:classifiers":[
        {
            "category":"Insurance",
            "subcategory":"Life Insurance",
            "type":"Services"
        }
    ],
    "sg:phone":"+32 71 36 09 70",
    "sg:postcode":"6001",
    "sg:province":"Hainaut",
    "sg:tags":[
        "assurance"
    ],
    "wof:name":"M. Minart",
    "wof:placetype":"venue"
},
  "geometry": {"coordinates":[4.4414410591,50.3929176331],"type":"Point"}
}