{
  "type": "Feature",
  "properties": {
    "addr:full":"Broekstraat 14 Buggenhout Oost-Vlaanderen 9255",
    "addr:housenumber":"14",
    "addr:postcode":"9255",
    "addr:street":"Broekstraat",
    "iso:country":"BE",
    "sg:address":"Broekstraat 14",
    "sg:city":"Buggenhout",
    "sg:orig_category":"Installatie van houten of kunststof schrijnwerk",
    "sg:phone":"+32 52 35 54 46",
    "sg:postcode":"9255",
    "sg:province":"Oost-Vlaanderen",
    "wof:name":"Van Assche Gebrs",
    "wof:placetype":"venue"
},
  "geometry": {"coordinates":[4.1677398682,50.988368988],"type":"Point"}
}