{
  "type": "Feature",
  "properties": {
    "addr:full":"Stasegemsesteenweg 1gik Kortrijk West-Vlaanderen 8500",
    "addr:postcode":"8500",
    "addr:street":"Stasegemsesteenweg",
    "iso:country":"BE",
    "sg:address":"Stasegemsesteenweg 1gik",
    "sg:city":"Kortrijk",
    "sg:orig_category":"Winkelinrichting and handelsuitrusting Gh",
    "sg:phone":"+32 56 22 40 44",
    "sg:postcode":"8500",
    "sg:province":"West-Vlaanderen",
    "wof:name":"Floorpul International",
    "wof:placetype":"venue"
},
  "geometry": {"coordinates":[3.2893440723,50.8310852051],"type":"Point"}
}