{
  "type": "Feature",
  "properties": {
    "iso:country":"BE",
    "sg:address":"Route D'eghez\u00e9e 78",
    "sg:city":"Jemeppe-sur-sambre",
    "sg:classifiers":[
        {
            "category":"Professional",
            "subcategory":"Accounting & Tax Preparation",
            "type":"Services"
        }
    ],
    "sg:phone":"+32 71 78 04 98",
    "sg:postcode":"5190",
    "sg:province":"Namur",
    "sg:tags":[
        "bookkeeper"
    ],
    "wof:name":"Fadeur M",
    "wof:placetype":"venue"
},
  "geometry": {"coordinates":[4.6707940102,50.4640884399],"type":"Point"}
}