{
  "type": "Feature",
  "properties": {
    "addr:full":"Proosdijstraat 109 Oostkamp West-Vlaanderen 8020",
    "addr:housenumber":"109",
    "addr:postcode":"8020",
    "addr:street":"Proosdijstraat",
    "iso:country":"BE",
    "sg:address":"Proosdijstraat 109",
    "sg:city":"Oostkamp",
    "sg:orig_category":"Eleveurs and marchands de porcs. Eleveurs de bovins",
    "sg:phone":"+32 50 27 71 39",
    "sg:postcode":"8020",
    "sg:province":"West-Vlaanderen",
    "wof:name":"Erik Rutsaert",
    "wof:placetype":"venue"
},
  "geometry": {"coordinates":[3.2696299553,51.1088790894],"type":"Point"}
}