{
  "type": "Feature",
  "properties": {
    "iso:country":"BE",
    "sg:address":"Fr.rooseveltlaan 100",
    "sg:city":"Vilvoorde",
    "sg:classifiers":[
        {
            "category":"Government",
            "subcategory":"Fire Station",
            "type":"Public Place"
        }
    ],
    "sg:phone":"+32 2 255 89 40",
    "sg:postcode":"1800",
    "sg:province":"Vlaams-Brabant",
    "sg:tags":[
        "packard",
        "nec",
        "bell"
    ],
    "wof:name":"Solutions Vilvoorde",
    "wof:placetype":"venue"
},
  "geometry": {"coordinates":[4.425093174,50.9310493469],"type":"Point"}
}