{
  "type": "Feature",
  "properties": {
    "iso:country":"BE",
    "sg:address":"Heldenlaan 33",
    "sg:city":"Zottegem",
    "sg:orig_category":"Banken and kredietinstellingen",
    "sg:phone":"+32 9 360 67 93",
    "sg:postcode":"9620",
    "sg:province":"Oost-Vlaanderen",
    "wof:name":"Dexia",
    "wof:placetype":"venue"
},
  "geometry": {"coordinates":[3.8105180264,50.8705329895],"type":"Point"}
}