{
  "type": "Feature",
  "properties": {
    "addr:full":"Provinciebaan 87 Box A Laarne (kalken) Oost-Vlaanderen 9270",
    "addr:housenumber":"87",
    "addr:postcode":"9270",
    "addr:street":"Provinciebaan;A",
    "iso:country":"BE",
    "sg:address":"Provinciebaan 87 Box A",
    "sg:city":"Laarne (kalken)",
    "sg:orig_category":"Autombile concessionaires",
    "sg:phone":"+32 9 366 02 60",
    "sg:postcode":"9270",
    "sg:province":"Oost-Vlaanderen",
    "wof:name":"Gar Marc Bvba",
    "wof:placetype":"venue"
},
  "geometry": {"coordinates":[3.8489339352,51.0294075012],"type":"Point"}
}