{
  "type": "Feature",
  "properties": {
    "iso:country":"BE",
    "sg:address":"Boulvard Des Archers 5",
    "sg:city":"Nivelles",
    "sg:orig_category":"Articles m\u00e9dicaux and orthop\u00e9diques",
    "sg:phone":"+32 67 84 18 07",
    "sg:postcode":"1400",
    "sg:province":"Brabant Wallon",
    "wof:name":"Jiholabo",
    "wof:placetype":"venue"
},
  "geometry": {"coordinates":[4.3223128319,50.5998458862],"type":"Point"}
}