{
  "type": "Feature",
  "properties": {
    "iso:country":"BE",
    "sg:address":"Rue De Fleurus 144",
    "sg:city":"Sambreville",
    "sg:orig_category":"D\u00e9chets and d\u00e9bris Gr",
    "sg:phone":"+32 71 77 39 35",
    "sg:postcode":"5060",
    "sg:province":"Namur",
    "wof:name":"Jean-marie Lombet",
    "wof:placetype":"venue"
},
  "geometry": {"coordinates":[4.5830078125,50.4471511841],"type":"Point"}
}