{
  "type": "Feature",
  "properties": {
    "iso:country":"BE",
    "sg:address":"Wilgenlaan 1",
    "sg:city":"Oostkamp",
    "sg:orig_category":"Installation \u00e9lectrique r\u00e9sidentielle",
    "sg:phone":"+32 50 27 69 25",
    "sg:postcode":"8020",
    "sg:province":"West-Vlaanderen",
    "wof:name":"Johan Eeckhout",
    "wof:placetype":"venue"
},
  "geometry": {"coordinates":[3.2164990902,51.1133880615],"type":"Point"}
}