{
  "type": "Feature",
  "properties": {
    "iso:country":"BE",
    "sg:address":"Chauss\u00c9e De Lodelinsart 11",
    "sg:city":"Charleroi",
    "sg:classifiers":[
        {
            "category":"Shopping",
            "subcategory":"Clothing, Apparel, & Fashions",
            "type":"Retail Goods"
        }
    ],
    "sg:phone":"+32 71 41 53 44",
    "sg:postcode":"6060",
    "sg:province":"Hainaut",
    "sg:tags":[
        "ondergoed",
        "lingerie"
    ],
    "wof:name":"Maison Delire",
    "wof:placetype":"venue"
},
  "geometry": {"coordinates":[4.4493408203,50.4186515808],"type":"Point"}
}