{
  "type": "Feature",
  "properties": {
    "iso:country":"BE",
    "sg:address":"Oude Dendermondse Stwg 284",
    "sg:city":"Aalst",
    "sg:classifiers":[
        {
            "category":"Personal",
            "subcategory":"Beauty Salon",
            "type":"Services"
        }
    ],
    "sg:phone":"+32 53 70 14 85",
    "sg:postcode":"9300",
    "sg:province":"Oost-Vlaanderen",
    "sg:tags":[
        "de",
        "coiffure"
    ],
    "wof:name":"Coiffure Clejo",
    "wof:placetype":"venue"
},
  "geometry": {"coordinates":[4.0306310654,50.9498748779],"type":"Point"}
}