{
  "type": "Feature",
  "properties": {
    "addr:full":"Grote Baan 25b2 Hasselt Limburg 3511",
    "addr:housenumber":"25b2",
    "addr:postcode":"3511",
    "addr:street":"Grote Baan",
    "iso:country":"BE",
    "sg:address":"Grote Baan 25b2",
    "sg:city":"Hasselt",
    "sg:orig_category":"Woningbouw",
    "sg:phone":"+32 11 87 14 13",
    "sg:postcode":"3511",
    "sg:province":"Limburg",
    "wof:name":"Benny Peeters",
    "wof:placetype":"venue"
},
  "geometry": {"coordinates":[5.3069911003,50.9402160645],"type":"Point"}
}