{
  "type": "Feature",
  "properties": {
    "addr:full":"Aardeweg 61 Overijse Vlaams-Brabant 3090",
    "addr:housenumber":"61",
    "addr:postcode":"3090",
    "addr:street":"Aardeweg",
    "iso:country":"BE",
    "sg:address":"Aardeweg 61",
    "sg:city":"Overijse",
    "sg:classifiers":[
        {
            "category":"Professional",
            "subcategory":"Management & Consulting",
            "type":"Services"
        }
    ],
    "sg:phone":"+32 496 87 82 41",
    "sg:postcode":"3090",
    "sg:province":"Vlaams-Brabant",
    "sg:tags":[
        "consultant"
    ],
    "wof:name":"Isode",
    "wof:placetype":"venue"
},
  "geometry": {"coordinates":[4.562538147,50.8055267334],"type":"Point"}
}