{
  "type": "Feature",
  "properties": {
    "iso:country":"BE",
    "sg:address":"Botermarkt 6",
    "sg:city":"Herenthout",
    "sg:classifiers":[
        {
            "category":"Cafe",
            "type":"Food & Drink"
        }
    ],
    "sg:phone":"+32 14 51 93 66",
    "sg:postcode":"2270",
    "sg:province":"Antwerpen",
    "sg:tags":[
        "caf\u00e9s"
    ],
    "wof:name":"Caf\u00c9 \u00b4t Hamerke",
    "wof:placetype":"venue"
},
  "geometry": {"coordinates":[4.7558059692,51.1396751404],"type":"Point"}
}