{
  "type": "Feature",
  "properties": {
    "iso:country":"BE",
    "sg:address":"Aalterstraat 34",
    "sg:city":"Aalter",
    "sg:classifiers":[
        {
            "category":"Health Services",
            "subcategory":"Health Practitioner",
            "type":"Services"
        }
    ],
    "sg:phone":"+32 9 374 33 88",
    "sg:postcode":"9880",
    "sg:province":"Oost-Vlaanderen",
    "sg:tags":[
        "physiotherapist"
    ],
    "wof:name":"Beirnaert Josiane",
    "wof:placetype":"venue"
},
  "geometry": {"coordinates":[3.4621911049,51.0699005127],"type":"Point"}
}