{
  "type": "Feature",
  "properties": {
    "iso:country":"BE",
    "sg:address":"Hovenierstraat 8",
    "sg:city":"Ranst",
    "sg:orig_category":"Producteurs de l\u00e9gumes",
    "sg:phone":"+32 3 485 52 36",
    "sg:postcode":"2520",
    "sg:province":"Antwerpen",
    "wof:name":"Willem Peers",
    "wof:placetype":"venue"
},
  "geometry": {"coordinates":[4.5517902374,51.1786842346],"type":"Point"}
}