{
  "type": "Feature",
  "properties": {
    "addr:full":"Rue De Jemeppe 68 Ans (loncin) Li\u00e8ge 4431",
    "addr:housenumber":"68",
    "addr:postcode":"4431",
    "addr:street":"Rue De Jemeppe",
    "iso:country":"BE",
    "sg:address":"Rue De Jemeppe 68",
    "sg:city":"Ans (loncin)",
    "sg:classifiers":[
        {
            "category":"Real Estate",
            "subcategory":"Architect",
            "type":"Services"
        }
    ],
    "sg:phone":"+32 4 263 14 81",
    "sg:postcode":"4431",
    "sg:province":"Li\u00e8ge",
    "wof:name":"Laport P",
    "wof:placetype":"venue"
},
  "geometry": {"coordinates":[5.5014262199,50.6643028259],"type":"Point"}
}