{
  "type": "Feature",
  "properties": {
    "iso:country":"BE",
    "sg:address":"Leopold Ii-laan 2b6",
    "sg:city":"Oostende",
    "sg:orig_category":"Beheer onroerend goed",
    "sg:phone":"+32 59 70 21 75",
    "sg:postcode":"8400",
    "sg:province":"West-Vlaanderen",
    "wof:name":"R. Hosten",
    "wof:placetype":"venue"
},
  "geometry": {"coordinates":[2.9142289162,51.2296867371],"type":"Point"}
}