{
  "type": "Feature",
  "properties": {
    "iso:country":"BE",
    "sg:address":"Molenbergstraat 52",
    "sg:city":"Landen",
    "sg:classifiers":[
        {
            "category":"Real Estate",
            "subcategory":"Architect",
            "type":"Services"
        }
    ],
    "sg:phone":"+32 11 88 12 01",
    "sg:postcode":"3400",
    "sg:province":"Vlaams-Brabant",
    "wof:name":"Peeters J",
    "wof:placetype":"venue"
},
  "geometry": {"coordinates":[5.0874872208,50.7519760132],"type":"Point"}
}