{
  "type": "Feature",
  "properties": {
    "addr:full":"Diestsesteenweg 38 Herk-de-stad Limburg 3540",
    "addr:housenumber":"38",
    "addr:postcode":"3540",
    "addr:street":"Diestsesteenweg",
    "iso:country":"BE",
    "sg:address":"Diestsesteenweg 38",
    "sg:city":"Herk-de-stad",
    "sg:orig_category":"Afbraak- and draineerwerken Bloemen and planten Groententeelt Tuinen",
    "sg:phone":"+32 13 55 20 24",
    "sg:postcode":"3540",
    "sg:province":"Limburg",
    "wof:name":"Het Groen",
    "wof:placetype":"venue"
},
  "geometry": {"coordinates":[5.1579990387,50.941608429],"type":"Point"}
}