{
  "type": "Feature",
  "properties": {
    "addr:full":"Ommegangstraat 78 Zele Oost-Vlaanderen 9240",
    "addr:housenumber":"78",
    "addr:postcode":"9240",
    "addr:street":"Ommegangstraat",
    "iso:country":"BE",
    "sg:address":"Ommegangstraat 78",
    "sg:city":"Zele",
    "sg:orig_category":"G\u00e9om\u00e8tres",
    "sg:phone":"+32 52 44 60 00",
    "sg:postcode":"9240",
    "sg:province":"Oost-Vlaanderen",
    "wof:name":"Robin Van Den Bossche",
    "wof:placetype":"venue"
},
  "geometry": {"coordinates":[4.0426669121,51.0634117126],"type":"Point"}
}