{
  "type": "Feature",
  "properties": {
    "iso:country":"BE",
    "sg:address":"Avenue De La Garemelreux 37",
    "sg:city":"Hotton",
    "sg:classifiers":[
        {
            "category":"Building & Trades",
            "subcategory":"Electrical",
            "type":"Services"
        }
    ],
    "sg:phone":"+32 84 46 62 97",
    "sg:postcode":"6990",
    "sg:province":"Luxembourg",
    "sg:tags":[
        "work",
        "installation"
    ],
    "wof:name":"C. Tixhon S.p.r.l.",
    "wof:placetype":"venue"
},
  "geometry": {"coordinates":[5.4473900795,50.2685241699],"type":"Point"}
}