{
  "type": "Feature",
  "properties": {
    "iso:country":"BE",
    "sg:address":"Kattestraat 112",
    "sg:city":"Sint-amands",
    "sg:orig_category":"Producteurs de l\u00e9gumes",
    "sg:phone":"+32 3 889 31 57",
    "sg:postcode":"2890",
    "sg:province":"Antwerpen",
    "wof:name":"Constant Seghers",
    "wof:placetype":"venue"
},
  "geometry": {"coordinates":[4.2355489731,51.0698432922],"type":"Point"}
}