{
  "type": "Feature",
  "properties": {
    "addr:full":"Rue Victor Orianne 2 Marche-en-famenne Luxembourg 6900",
    "addr:housenumber":"2",
    "addr:postcode":"6900",
    "addr:street":"Rue Victor Orianne",
    "iso:country":"BE",
    "sg:address":"Rue Victor Orianne 2",
    "sg:city":"Marche-en-famenne",
    "sg:orig_category":"Eleveurs de bovins",
    "sg:phone":"+32 84 21 14 90",
    "sg:postcode":"6900",
    "sg:province":"Luxembourg",
    "wof:name":"Ernest Maldague",
    "wof:placetype":"venue"
},
  "geometry": {"coordinates":[5.2911658287,50.1743812561],"type":"Point"}
}