{
  "type": "Feature",
  "properties": {
    "iso:country":"BE",
    "sg:address":"Chemin De Blanchamps 47",
    "sg:city":"Philippeville",
    "sg:orig_category":"Artiesten and kunstenaars",
    "sg:phone":"+32 82 67 77 86",
    "sg:postcode":"5600",
    "sg:province":"Namur",
    "wof:name":"Marcel Lupsin",
    "wof:placetype":"venue"
},
  "geometry": {"coordinates":[4.7026181221,50.1807937622],"type":"Point"}
}