{
  "type": "Feature",
  "properties": {
    "iso:country":"BE",
    "sg:address":"Generaal Jacqueslaan 179",
    "sg:city":"Elsene/ixelles",
    "sg:classifiers":[
        {
            "category":"Cafe",
            "type":"Food & Drink"
        }
    ],
    "sg:phone":"+32 2 646 45 11",
    "sg:postcode":"1050",
    "sg:province":"Bruxelles-Capitale",
    "sg:tags":[
        "caf\u00e9s"
    ],
    "wof:name":"Caf\u00c9 Color",
    "wof:placetype":"venue"
},
  "geometry": {"coordinates":[4.3855099678,50.8204727173],"type":"Point"}
}