{
  "type": "Feature",
  "properties": {
    "addr:full":"Rue De Boussu 98 Dour Hainaut 7370",
    "addr:housenumber":"98",
    "addr:postcode":"7370",
    "addr:street":"Rue De Boussu;Hainaut",
    "iso:country":"BE",
    "sg:address":"Rue De Boussu 98",
    "sg:city":"Dour",
    "sg:classifiers":[
        {
            "category":"Insurance",
            "subcategory":"Insurance Agent",
            "type":"Services"
        }
    ],
    "sg:phone":"+32 65 65 26 00",
    "sg:postcode":"7370",
    "sg:province":"Hainaut",
    "sg:tags":[
        "verzekeringsmakelaars",
        "expert"
    ],
    "wof:name":"M. Dupont",
    "wof:placetype":"venue"
},
  "geometry": {"coordinates":[3.7824890614,50.4039077759],"type":"Point"}
}