{
  "type": "Feature",
  "properties": {
    "addr:full":"Galeidestraat 12 Dendermonde (sint-gillis-bij-dendermonde) Oost-Vlaanderen 9200",
    "addr:housenumber":"12",
    "addr:postcode":"9200",
    "addr:street":"Galeidestraat",
    "iso:country":"BE",
    "sg:address":"Galeidestraat 12",
    "sg:city":"Dendermonde (sint-gillis-bij-dendermonde)",
    "sg:classifiers":[
        {
            "category":"Health Services",
            "subcategory":"Health Practitioner",
            "type":"Services"
        }
    ],
    "sg:phone":"+32 478 24 60 42",
    "sg:postcode":"9200",
    "sg:province":"Oost-Vlaanderen",
    "sg:tags":[
        "physiotherapist"
    ],
    "wof:name":"De Meulemeester Caroline",
    "wof:placetype":"venue"
},
  "geometry": {"coordinates":[4.0933489799,51.0228767395],"type":"Point"}
}