{
  "type": "Feature",
  "properties": {
    "iso:country":"BE",
    "sg:address":"Route De Xhoffraix 22",
    "sg:city":"Stavelot (francorchamps)",
    "sg:classifiers":[
        {
            "category":"Health Services",
            "subcategory":"Doctor",
            "type":"Services"
        }
    ],
    "sg:phone":"+32 87 27 55 62",
    "sg:postcode":"4970",
    "sg:province":"Li\u00e8ge",
    "sg:tags":[
        "medicinephysicians",
        "surgeon"
    ],
    "wof:name":"Jordant Joseph",
    "wof:placetype":"venue"
},
  "geometry": {"coordinates":[5.930850029,50.3942909241],"type":"Point"}
}