{
  "type": "Feature",
  "properties": {
    "addr:full":"Grand'rue 1 Virton Luxembourg 6760",
    "addr:housenumber":"1",
    "addr:postcode":"6760",
    "addr:street":"Grand'Rue",
    "iso:country":"BE",
    "sg:address":"Grand'rue 1",
    "sg:city":"Virton",
    "sg:classifiers":[
        {
            "category":"Fast Food",
            "type":"Food & Drink"
        }
    ],
    "sg:phone":"+32 63 57 05 71",
    "sg:postcode":"6760",
    "sg:province":"Luxembourg",
    "sg:tags":[
        "\u00c0",
        "restaurants",
        "emporter",
        "restaurant"
    ],
    "wof:name":"Pizzeria Venezia",
    "wof:placetype":"venue"
},
  "geometry": {"coordinates":[5.5965709686,49.5601654053],"type":"Point"}
}