{
  "type": "Feature",
  "properties": {
    "iso:country":"BE",
    "sg:address":"Verenigde Natielaan 9",
    "sg:city":"Oostende",
    "sg:orig_category":"Informaticaconsulenten",
    "sg:phone":"+32 59 50 05 87",
    "sg:postcode":"8400",
    "sg:province":"West-Vlaanderen",
    "wof:name":"Sailors Boutiek Bv",
    "wof:placetype":"venue"
},
  "geometry": {"coordinates":[2.9175000191,51.2226295471],"type":"Point"}
}