{
  "type": "Feature",
  "properties": {
    "addr:full":"Edingsesteenweg 450 Ninove Oost-Vlaanderen 9400",
    "addr:housenumber":"450",
    "addr:postcode":"9400",
    "addr:street":"Edingsesteenweg",
    "iso:country":"BE",
    "sg:address":"Edingsesteenweg 450",
    "sg:city":"Ninove",
    "sg:orig_category":"Woningbouw",
    "sg:phone":"+32 54 32 00 23",
    "sg:postcode":"9400",
    "sg:province":"Oost-Vlaanderen",
    "wof:name":"Patrick Stalpaert",
    "wof:placetype":"venue"
},
  "geometry": {"coordinates":[4.0253529549,50.79296875],"type":"Point"}
}