{
  "type": "Feature",
  "properties": {
    "addr:full":"Rue Eunesse 2 Seraing Li\u00e8ge 4100",
    "addr:housenumber":"2",
    "addr:postcode":"4100",
    "addr:street":"Rue Eunesse",
    "iso:country":"BE",
    "sg:address":"Rue Eunesse 2",
    "sg:city":"Seraing",
    "sg:orig_category":"Salles de conf\u00e9rences and de r\u00e9ceptions",
    "sg:phone":"+32 4 371 51 49",
    "sg:postcode":"4100",
    "sg:province":"Li\u00e8ge",
    "wof:name":"Jardin Perdu",
    "wof:placetype":"venue"
},
  "geometry": {"coordinates":[5.5135030746,50.6105766296],"type":"Point"}
}