{
  "type": "Feature",
  "properties": {
    "addr:full":"Schrijnbroekstraat 3 Hasselt Limburg 3500",
    "addr:housenumber":"3",
    "addr:postcode":"3500",
    "addr:street":"Schrijnbroekstraat",
    "iso:country":"BE",
    "sg:address":"Schrijnbroekstraat 3",
    "sg:city":"Hasselt",
    "sg:orig_category":"Woningbouw",
    "sg:phone":"+32 11 21 11 03",
    "sg:postcode":"3500",
    "sg:province":"Limburg",
    "wof:name":"Krisa",
    "wof:placetype":"venue"
},
  "geometry": {"coordinates":[5.3496928215,50.9560394287],"type":"Point"}
}