{
  "type": "Feature",
  "properties": {
    "iso:country":"BE",
    "sg:address":"Place De Moustier 5-6",
    "sg:city":"Jemeppe-sur-sambre (moustier-sur-sambre)",
    "sg:classifiers":[
        {
            "category":"Health Services",
            "subcategory":"Dentist",
            "type":"Services"
        }
    ],
    "sg:phone":"+32 71 78 54 25",
    "sg:postcode":"5190",
    "sg:province":"Namur",
    "wof:name":"Wouters P",
    "wof:placetype":"venue"
},
  "geometry": {"coordinates":[4.6979141235,50.4660491943],"type":"Point"}
}