{
  "type": "Feature",
  "properties": {
    "iso:country":"BE",
    "sg:address":"Overleiestraat 9",
    "sg:city":"Harelbeke",
    "sg:classifiers":[
        {
            "category":"Real Estate",
            "subcategory":"Architect",
            "type":"Services"
        }
    ],
    "sg:phone":"+32 56 72 53 54",
    "sg:postcode":"8530",
    "sg:province":"West-Vlaanderen",
    "wof:name":"Bleuz\u00e9 M",
    "wof:placetype":"venue"
},
  "geometry": {"coordinates":[3.3080489635,50.8580627441],"type":"Point"}
}