{
  "type": "Feature",
  "properties": {
    "iso:country":"BE",
    "sg:address":"Heidebadlaan 23",
    "sg:city":"Schoten",
    "sg:classifiers":[
        {
            "category":"Building & Trades",
            "subcategory":"Equipment Rental",
            "type":"Services"
        }
    ],
    "sg:phone":"+32 3 663 10 97",
    "sg:postcode":"2900",
    "sg:province":"Antwerpen",
    "sg:tags":[
        "sound",
        "-",
        "system"
    ],
    "wof:name":"Stage Track Bvba",
    "wof:placetype":"venue"
},
  "geometry": {"coordinates":[4.5386691093,51.2988586426],"type":"Point"}
}