{
  "type": "Feature",
  "properties": {
    "iso:country":"BE",
    "sg:address":"Globelaan 16",
    "sg:city":"Vorst/forest",
    "sg:orig_category":"Drukkerijen and copyshops",
    "sg:phone":"+32 2 343 57 87",
    "sg:postcode":"1190",
    "sg:province":"Bruxelles-Capitale",
    "wof:name":"Copy Service Center",
    "wof:placetype":"venue"
},
  "geometry": {"coordinates":[4.3251948357,50.8096237183],"type":"Point"}
}