{
  "type": "Feature",
  "properties": {
    "iso:country":"BE",
    "sg:address":"Avenue Fleming 32",
    "sg:city":"Wavre",
    "sg:orig_category":"Ordinateurs and \u00e9quipement informatique",
    "sg:phone":"+32 10 23 88 23",
    "sg:postcode":"1300",
    "sg:province":"Brabant Wallon",
    "wof:name":"Fe. Mage\u00b4elan",
    "wof:placetype":"venue"
},
  "geometry": {"coordinates":[4.613008976,50.7389602661],"type":"Point"}
}