{
  "type": "Feature",
  "properties": {
    "addr:full":"Veerledorp 33 Laakdal Antwerpen 2431",
    "addr:housenumber":"33",
    "addr:postcode":"2431",
    "addr:street":"Veerledorp",
    "iso:country":"BE",
    "sg:address":"Veerledorp 33",
    "sg:city":"Laakdal",
    "sg:classifiers":[
        {
            "category":"Travel",
            "subcategory":"Travel Agent",
            "type":"Entertainment"
        }
    ],
    "sg:phone":"+32 14 84 14 14",
    "sg:postcode":"2431",
    "sg:province":"Antwerpen",
    "sg:tags":[
        "holiday",
        "flash",
        "plus",
        "reisbureaus"
    ],
    "wof:name":"Alom Travel",
    "wof:placetype":"venue"
},
  "geometry": {"coordinates":[4.9848599434,51.0695953369],"type":"Point"}
}