{
  "type": "Feature",
  "properties": {
    "iso:country":"BE",
    "sg:address":"Leopold Ii-laan 81 A",
    "sg:city":"Oostduinkerke",
    "sg:orig_category":"Mazda. Entretien and r\u00e9parations de voitures",
    "sg:phone":"+32 58 51 19 34",
    "sg:postcode":"8670",
    "sg:province":"West-Vlaanderen",
    "wof:name":"Garage Carrosserie Hancke",
    "wof:placetype":"venue"
},
  "geometry": {"coordinates":[2.6796009541,51.1187973022],"type":"Point"}
}