{
  "type": "Feature",
  "properties": {
    "addr:full":"Rue Du Ham 51 Ukkel/uccle Bruxelles-Capitale 1180",
    "addr:housenumber":"51",
    "addr:postcode":"1180",
    "addr:street":"Rue Du Ham;/",
    "iso:country":"BE",
    "sg:address":"Rue Du Ham 51",
    "sg:city":"Ukkel/uccle",
    "sg:orig_category":"M\u00e9decins and sp\u00e9cialistes",
    "sg:phone":"+32 2 374 10 05",
    "sg:postcode":"1180",
    "sg:province":"Bruxelles-Capitale",
    "wof:name":"L. Bruers",
    "wof:placetype":"venue"
},
  "geometry": {"coordinates":[4.3674020767,50.7912521362],"type":"Point"}
}