{
  "type": "Feature",
  "properties": {
    "addr:full":"Heindonksesteenweg 202 Willebroek Antwerpen 2830",
    "addr:housenumber":"202",
    "addr:postcode":"2830",
    "addr:street":"Heindonksesteenweg",
    "iso:country":"BE",
    "sg:address":"Heindonksesteenweg 202",
    "sg:city":"Willebroek",
    "sg:classifiers":[
        {
            "category":"Home & Garden",
            "subcategory":"Building Materials",
            "type":"Retail Goods"
        }
    ],
    "sg:phone":"+32 3 886 35 54",
    "sg:postcode":"2830",
    "sg:province":"Antwerpen",
    "sg:tags":[
        "bathroom",
        "installation",
        "accessory"
    ],
    "wof:name":"Candries Bvba",
    "wof:placetype":"venue"
},
  "geometry": {"coordinates":[4.3793411255,51.0649642944],"type":"Point"}
}