{
  "type": "Feature",
  "properties": {
    "iso:country":"BE",
    "sg:address":"Jardin Des Fleurs 80",
    "sg:city":"Linkebeek",
    "sg:classifiers":[
        {
            "category":"Communications",
            "subcategory":"Film & Video Production",
            "type":"Services"
        }
    ],
    "sg:phone":"+32 2 380 78 76",
    "sg:postcode":"1630",
    "sg:province":"Vlaams-Brabant",
    "sg:tags":[
        "movie",
        "maker"
    ],
    "wof:name":"Graff Ph",
    "wof:placetype":"venue"
},
  "geometry": {"coordinates":[4.3414697647,50.7719154358],"type":"Point"}
}