{
  "type": "Feature",
  "properties": {
    "addr:full":"Mutsaardplein 20 Strombeek-bever Vlaams-Brabant 1853",
    "addr:housenumber":"20;1853",
    "addr:street":"Mutsaardplein;Vlaams-Brabant",
    "iso:country":"BE",
    "sg:address":"Mutsaardplein 20",
    "sg:city":"Strombeek-bever",
    "sg:classifiers":[
        {
            "category":"Restaurant",
            "type":"Food & Drink"
        }
    ],
    "sg:phone":"+32 2 267 02 70",
    "sg:postcode":"1853",
    "sg:province":"Vlaams-Brabant",
    "wof:name":"Imperial",
    "wof:placetype":"venue"
},
  "geometry": {"coordinates":[4.3604769707,50.9015426636],"type":"Point"}
}