{
  "type": "Feature",
  "properties": {
    "addr:full":"Chauss\u00c9e Paul Houtart 147 La Louvi\u00c8re Hainaut 7110",
    "addr:housenumber":"147",
    "addr:postcode":"7110",
    "addr:street":"Chausse\u0301E Paul Houtart",
    "iso:country":"BE",
    "sg:address":"Chauss\u00c9e Paul Houtart 147",
    "sg:city":"La Louvi\u00c8re",
    "sg:classifiers":[
        {
            "category":"Restaurant",
            "type":"Food & Drink"
        }
    ],
    "sg:phone":"+32 64 26 68 69",
    "sg:postcode":"7110",
    "sg:province":"Hainaut",
    "wof:name":"Family Flunch",
    "wof:placetype":"venue"
},
  "geometry": {"coordinates":[4.1627550125,50.4840049744],"type":"Point"}
}