{
  "type": "Feature",
  "properties": {
    "iso:country":"BE",
    "sg:address":"Boulevard Emile De Laveleye 161",
    "sg:city":"Liege",
    "sg:orig_category":"Installation \u00e9lectrique industrielle",
    "sg:phone":"+32 4 344 44 21",
    "sg:postcode":"4020",
    "sg:province":"Li\u00e8ge",
    "wof:name":"Alpha Ascenseurs",
    "wof:placetype":"venue"
},
  "geometry": {"coordinates":[5.5912342072,50.6208724976],"type":"Point"}
}