{
  "type": "Feature",
  "properties": {
    "iso:country":"BE",
    "sg:address":"Steenakker 2",
    "sg:city":"Wervik",
    "sg:orig_category":"Charpentes and couvertures",
    "sg:phone":"+32 56 31 54 92",
    "sg:postcode":"8940",
    "sg:province":"West-Vlaanderen",
    "wof:name":"Idealpan",
    "wof:placetype":"venue"
},
  "geometry": {"coordinates":[3.044686079,50.7796707153],"type":"Point"}
}