{
  "type": "Feature",
  "properties": {
    "iso:country":"BE",
    "sg:address":"Rue De Li\u00c8ge 25b3",
    "sg:city":"Verviers",
    "sg:orig_category":"Artsen and specialisten",
    "sg:phone":"+32 87 22 79 66",
    "sg:postcode":"4800",
    "sg:province":"Li\u00e8ge",
    "wof:name":"Fran\u00c7oise Mathonet",
    "wof:placetype":"venue"
},
  "geometry": {"coordinates":[5.8567638397,50.5864982605],"type":"Point"}
}