{
  "type": "Feature",
  "properties": {
    "iso:country":"BE",
    "sg:address":"Chauss\u00c9e D'anvers 264",
    "sg:city":"Brussel/bruxelles",
    "sg:orig_category":"Epiceries. Poissonniers and \u00e9caillers",
    "sg:phone":"+32 2 203 43 08",
    "sg:postcode":"1000",
    "sg:province":"Bruxelles-Capitale",
    "wof:name":"Evangelos Stathis",
    "wof:placetype":"venue"
},
  "geometry": {"coordinates":[4.3587670326,50.8678207397],"type":"Point"}
}