{
  "type": "Feature",
  "properties": {
    "addr:full":"Turnhoutsebaan 41 Kasterlee Antwerpen 2460",
    "addr:housenumber":"41",
    "addr:postcode":"2460",
    "addr:street":"Turnhoutsebaan",
    "iso:country":"BE",
    "sg:address":"Turnhoutsebaan 41",
    "sg:city":"Kasterlee",
    "sg:orig_category":"R\u00e9parations de chaussures and articles en cuir",
    "sg:phone":"+32 14 85 05 92",
    "sg:postcode":"2460",
    "sg:province":"Antwerpen",
    "wof:name":"Guy De Cuyper",
    "wof:placetype":"venue"
},
  "geometry": {"coordinates":[4.9653987885,51.2422561646],"type":"Point"}
}