{
  "type": "Feature",
  "properties": {
    "iso:country":"BE",
    "sg:address":"Rue De La Chapelle 3",
    "sg:city":"Bastogne",
    "sg:classifiers":[
        {
            "category":"Professional",
            "subcategory":"Lawyer & Legal Services",
            "type":"Services"
        }
    ],
    "sg:phone":"+32 61 21 89 11",
    "sg:postcode":"6600",
    "sg:province":"Luxembourg",
    "wof:name":"Burton Catherine",
    "wof:placetype":"venue"
},
  "geometry": {"coordinates":[5.7227602005,50.0038032532],"type":"Point"}
}