{
  "type": "Feature",
  "properties": {
    "addr:full":"Wijngaardstraat 27-29 Brugge West-Vlaanderen 8000",
    "addr:postcode":"27-29;8000",
    "addr:street":"Wijngaardstraat",
    "iso:country":"BE",
    "sg:address":"Wijngaardstraat 27-29",
    "sg:city":"Brugge",
    "sg:orig_category":"Non-Classified Establishments",
    "sg:phone":"+32 50 34 30 60",
    "sg:postcode":"8000",
    "sg:province":"West-Vlaanderen",
    "wof:name":"Lauwers",
    "wof:placetype":"venue"
},
  "geometry": {"coordinates":[3.2249469757,51.2017097473],"type":"Point"}
}