{
  "type": "Feature",
  "properties": {
    "addr:full":"Thimstrasse 36 Kelmis/la Calamine Li\u00e8ge 4720",
    "addr:housenumber":"36",
    "addr:postcode":"4720",
    "addr:street":"Thimstrasse",
    "iso:country":"BE",
    "sg:address":"Thimstrasse 36",
    "sg:city":"Kelmis/la Calamine",
    "sg:orig_category":"Boekhouders",
    "sg:phone":"+32 87 65 99 20",
    "sg:postcode":"4720",
    "sg:province":"Li\u00e8ge",
    "wof:name":"Ir\u00c8ne Baltus",
    "wof:placetype":"venue"
},
  "geometry": {"coordinates":[6.0109968185,50.7173728943],"type":"Point"}
}