{
  "type": "Feature",
  "properties": {
    "addr:full":"Rue Hocheporte 29 Theux Li\u00e8ge 4910",
    "addr:housenumber":"29",
    "addr:postcode":"4910",
    "addr:street":"Rue Hocheporte",
    "iso:country":"BE",
    "sg:address":"Rue Hocheporte 29",
    "sg:city":"Theux",
    "sg:classifiers":[
        {
            "category":"Bars & Pubs",
            "type":"Food & Drink"
        }
    ],
    "sg:phone":"+32 87 54 26 55",
    "sg:postcode":"4910",
    "sg:province":"Li\u00e8ge",
    "wof:name":"Hocheporte (le)",
    "wof:placetype":"venue"
},
  "geometry": {"coordinates":[5.8128662109,50.5355300903],"type":"Point"}
}