{
  "type": "Feature",
  "properties": {
    "addr:full":"Halstraat 179 Heusden-zolder Limburg 3550",
    "addr:housenumber":"179",
    "addr:postcode":"3550",
    "addr:street":"Halstraat",
    "iso:country":"BE",
    "sg:address":"Halstraat 179",
    "sg:city":"Heusden-zolder",
    "sg:orig_category":"Meubles D\u00e9taillants, Am\u00e9nagement de B\u00e2timents et de Cuisines. R\u00e9paration and restauration de meubles",
    "sg:phone":"+32 11 57 35 24",
    "sg:postcode":"3550",
    "sg:province":"Limburg",
    "wof:name":"Joseph Vanherck",
    "wof:placetype":"venue"
},
  "geometry": {"coordinates":[5.3207731247,51.0509376526],"type":"Point"}
}