{
  "type": "Feature",
  "properties": {
    "addr:full":"Castelsebaan 151 Mol Antwerpen 2400",
    "addr:housenumber":"151",
    "addr:postcode":"2400",
    "addr:street":"Castelsebaan",
    "iso:country":"BE",
    "sg:address":"Castelsebaan 151",
    "sg:city":"Mol",
    "sg:orig_category":"Diverse bedrijfsbeheeradviesbureaus",
    "sg:phone":"+32 14 58 07 64",
    "sg:postcode":"2400",
    "sg:province":"Antwerpen",
    "wof:name":"Berkenrode",
    "wof:placetype":"venue"
},
  "geometry": {"coordinates":[5.0594201088,51.1999092102],"type":"Point"}
}