{
  "type": "Feature",
  "properties": {
    "addr:full":"Hubert D'ydewallestraat 80 Beernem West-Vlaanderen 8730",
    "addr:housenumber":"80",
    "addr:postcode":"8730",
    "addr:street":"Hubert D'Ydewallestraat",
    "iso:country":"BE",
    "sg:address":"Hubert D'ydewallestraat 80",
    "sg:city":"Beernem",
    "sg:classifiers":[
        {
            "category":"Personal",
            "subcategory":"Beauty Salon",
            "type":"Services"
        }
    ],
    "sg:phone":"+32 50 78 02 97",
    "sg:postcode":"8730",
    "sg:province":"West-Vlaanderen",
    "sg:tags":[
        "de",
        "coiffure"
    ],
    "wof:name":"Francine Devisch",
    "wof:placetype":"venue"
},
  "geometry": {"coordinates":[3.3190848827,51.1299552917],"type":"Point"}
}