{
  "type": "Feature",
  "properties": {
    "addr:full":"Kardinaal Mercierlaan 6 Leuven (heverlee) Vlaams-Brabant 3001",
    "addr:housenumber":"6",
    "addr:postcode":"3001",
    "addr:street":"Kardinaal Mercierlaan",
    "iso:country":"BE",
    "sg:address":"Kardinaal Mercierlaan 6",
    "sg:city":"Leuven (heverlee)",
    "sg:classifiers":[
        {
            "category":"Health Services",
            "subcategory":"Dentist",
            "type":"Services"
        }
    ],
    "sg:phone":"+32 16 23 65 69",
    "sg:postcode":"3001",
    "sg:province":"Vlaams-Brabant",
    "wof:name":"Heidbuchel Vanderbeeken M",
    "wof:placetype":"venue"
},
  "geometry": {"coordinates":[4.6971430779,50.8680114746],"type":"Point"}
}