{
  "type": "Feature",
  "properties": {
    "addr:full":"Hoogstraat 24 Antwerpen Antwerpen 2000",
    "addr:housenumber":"24",
    "addr:postcode":"2000",
    "addr:street":"Hoogstraat",
    "iso:country":"BE",
    "sg:address":"Hoogstraat 24",
    "sg:city":"Antwerpen",
    "sg:classifiers":[
        {
            "category":"Banks & Credit Unions",
            "subcategory":"Investment Brokerage",
            "type":"Services"
        }
    ],
    "sg:phone":"+32 3 233 76 64",
    "sg:postcode":"2000",
    "sg:province":"Antwerpen",
    "sg:tags":[
        "jean",
        "casual",
        "wear"
    ],
    "wof:name":"Unica Bella Bvba",
    "wof:placetype":"venue"
},
  "geometry": {"coordinates":[4.3985791206,51.2201652527],"type":"Point"}
}