{
  "type": "Feature",
  "properties": {
    "addr:full":"Kapucijnenvoer 33 Leuven Vlaams-Brabant 3000",
    "addr:housenumber":"33",
    "addr:postcode":"3000",
    "addr:street":"Kapucijnenvoer",
    "iso:country":"BE",
    "sg:address":"Kapucijnenvoer 33",
    "sg:city":"Leuven",
    "sg:orig_category":"Rusthuizen and serviceflats Ziekenhuizen and zorginstellingen",
    "sg:phone":"+32 16 24 80 11",
    "sg:postcode":"3000",
    "sg:province":"Vlaams-Brabant",
    "wof:name":"Rusthuis Ziekenhuis St.rafa\u00cbl",
    "wof:placetype":"venue"
},
  "geometry": {"coordinates":[4.6925039291,50.8792037964],"type":"Point"}
}