{
  "type": "Feature",
  "properties": {
    "addr:full":"Biezeweide 248 Halle Vlaams-Brabant 1500",
    "addr:housenumber":"248",
    "addr:postcode":"1500",
    "iso:country":"BE",
    "sg:address":"Biezeweide 248",
    "sg:city":"Halle",
    "sg:orig_category":"Artiesten and kunstenaars",
    "sg:phone":"+32 2 360 35 72",
    "sg:postcode":"1500",
    "sg:province":"Vlaams-Brabant",
    "wof:name":"Maria Desadeleer",
    "wof:placetype":"venue"
},
  "geometry": {"coordinates":[4.2366991043,50.722984314],"type":"Point"}
}