{
  "type": "Feature",
  "properties": {
    "addr:full":"Peter Benoitlaan 39 Brugge (sint-andries) West-Vlaanderen 8200",
    "addr:housenumber":"39",
    "addr:postcode":"8200",
    "addr:street":"Peter Benoitlaan",
    "iso:country":"BE",
    "sg:address":"Peter Benoitlaan 39",
    "sg:city":"Brugge (sint-andries)",
    "sg:classifiers":[
        {
            "category":"Retail",
            "subcategory":"Animal Services",
            "type":"Services"
        }
    ],
    "sg:phone":"+32 50 31 59 31",
    "sg:postcode":"8200",
    "sg:province":"West-Vlaanderen",
    "sg:tags":[
        "grooming",
        "-",
        "dog"
    ],
    "wof:name":"Deleu A",
    "wof:placetype":"venue"
},
  "geometry": {"coordinates":[3.2062399387,51.2090454102],"type":"Point"}
}