{
  "type": "Feature",
  "properties": {
    "addr:full":"Rue Du Village 45 Flemalle Li\u00e8ge 4400",
    "addr:housenumber":"45",
    "addr:postcode":"4400",
    "addr:street":"Rue Du Village",
    "iso:country":"BE",
    "sg:address":"Rue Du Village 45",
    "sg:city":"Flemalle",
    "sg:orig_category":"Offices du tourisme",
    "sg:phone":"+32 4 233 67 87",
    "sg:postcode":"4400",
    "sg:province":"Li\u00e8ge",
    "wof:name":"Office Du Tourisme De Fl\u00c9malle",
    "wof:placetype":"venue"
},
  "geometry": {"coordinates":[5.4633498192,50.5991592407],"type":"Point"}
}