{
  "type": "Feature",
  "properties": {
    "addr:full":"Rue De La Tulipe 59 Bruxelles (ixelles) Bruxelles-Capitale 1050",
    "addr:housenumber":"59",
    "addr:postcode":"1050",
    "addr:street":"Rue De La Tulipe",
    "iso:country":"BE",
    "sg:address":"Rue De La Tulipe 59",
    "sg:city":"Bruxelles (ixelles)",
    "sg:classifiers":[
        {
            "category":"Food & Beverages",
            "subcategory":"Meat & Fish",
            "type":"Retail Goods"
        }
    ],
    "sg:phone":"+32 2 511 85 35",
    "sg:postcode":"1050",
    "sg:province":"Bruxelles-Capitale",
    "sg:tags":[
        "poultry",
        "whol",
        "game",
        "-"
    ],
    "wof:name":"Poularde D'opwijk (la)",
    "wof:placetype":"venue"
},
  "geometry": {"coordinates":[4.3681120872,50.835483551],"type":"Point"}
}