{
  "type": "Feature",
  "properties": {
    "addr:full":"Rue Du Moulin 159 La Louviere Hainaut 7100",
    "addr:housenumber":"159",
    "addr:postcode":"7100",
    "addr:street":"Rue Du Moulin",
    "iso:country":"BE",
    "sg:address":"Rue Du Moulin 159",
    "sg:city":"La Louviere",
    "sg:orig_category":"Begrafeniswezen",
    "sg:phone":"+32 64 22 36 49",
    "sg:postcode":"7100",
    "sg:province":"Hainaut",
    "wof:name":"Fun\u00c9railles Caudron",
    "wof:placetype":"venue"
},
  "geometry": {"coordinates":[4.1989750862,50.4808769226],"type":"Point"}
}