{
  "type": "Feature",
  "properties": {
    "addr:full":"Bredabaan 513 Brasschaat Antwerpen 2930",
    "addr:housenumber":"513",
    "addr:postcode":"2930",
    "addr:street":"Bredabaan",
    "iso:country":"BE",
    "sg:address":"Bredabaan 513",
    "sg:city":"Brasschaat",
    "sg:classifiers":[
        {
            "category":"Real Estate",
            "subcategory":"Architect",
            "type":"Services"
        }
    ],
    "sg:phone":"+32 3 651 51 68",
    "sg:postcode":"2930",
    "sg:province":"Antwerpen",
    "wof:name":"Architektenburo W De Jongh Bvba",
    "wof:placetype":"venue"
},
  "geometry": {"coordinates":[4.4970870018,51.295463562],"type":"Point"}
}