{
  "type": "Feature",
  "properties": {
    "iso:country":"BE",
    "sg:address":"Rue Fichaux 10",
    "sg:city":"Pont-a-celles",
    "sg:orig_category":"V\u00e9t\u00e9rinaires",
    "sg:phone":"+32 71 84 51 01",
    "sg:postcode":"6230",
    "sg:province":"Hainaut",
    "wof:name":"Pol Sibille",
    "wof:placetype":"venue"
},
  "geometry": {"coordinates":[4.3552980423,50.5144042969],"type":"Point"}
}