{
  "type": "Feature",
  "properties": {
    "addr:full":"Rue Haute 26 Oreye Li\u00e8ge 4360",
    "addr:housenumber":"26",
    "addr:postcode":"4360",
    "addr:street":"Rue Haute",
    "iso:country":"BE",
    "sg:address":"Rue Haute 26",
    "sg:city":"Oreye",
    "sg:orig_category":"Rundveehouders",
    "sg:phone":"+32 19 67 72 55",
    "sg:postcode":"4360",
    "sg:province":"Li\u00e8ge",
    "wof:name":"Jean Derwa",
    "wof:placetype":"venue"
},
  "geometry": {"coordinates":[5.3359951973,50.7217330933],"type":"Point"}
}