{
  "type": "Feature",
  "properties": {
    "addr:full":"Landsmanstraat 21 Wingene (zwevezele) West-Vlaanderen 8750",
    "addr:housenumber":"21",
    "addr:postcode":"8750",
    "addr:street":"Landsmanstraat",
    "iso:country":"BE",
    "sg:address":"Landsmanstraat 21",
    "sg:city":"Wingene (zwevezele)",
    "sg:classifiers":[
        {
            "category":"Farming",
            "subcategory":"Farm & Veterinary Services",
            "type":"Manufacturing & Wholesale Goods"
        }
    ],
    "sg:phone":"+32 51 61 19 97",
    "sg:postcode":"8750",
    "sg:province":"West-Vlaanderen",
    "sg:tags":[
        "agricultural",
        "contractor"
    ],
    "wof:name":"Behaegel J & Zn",
    "wof:placetype":"venue"
},
  "geometry": {"coordinates":[3.2144210339,51.0581512451],"type":"Point"}
}