{
  "type": "Feature",
  "properties": {
    "iso:country":"BE",
    "sg:address":"Kere 23",
    "sg:city":"Waarschoot",
    "sg:orig_category":"Woningbouw",
    "sg:phone":"+32 9 377 90 67",
    "sg:postcode":"9950",
    "sg:province":"Oost-Vlaanderen",
    "wof:name":"Roger Tournois",
    "wof:placetype":"venue"
},
  "geometry": {"coordinates":[3.5959160328,51.1543617249],"type":"Point"}
}