{
  "type": "Feature",
  "properties": {
    "addr:full":"Hofbilkstraat 52a Evergem Oost-Vlaanderen 9940",
    "addr:housenumber":"52a",
    "addr:postcode":"9940",
    "addr:street":"Hofbilkstraat;Oost-Vlaanderen",
    "iso:country":"BE",
    "sg:address":"Hofbilkstraat 52a",
    "sg:city":"Evergem",
    "sg:classifiers":[
        {
            "category":"Food & Beverages",
            "subcategory":"Chocolate",
            "type":"Retail Goods"
        }
    ],
    "sg:phone":"+32 9 253 59 39",
    "sg:postcode":"9940",
    "sg:province":"Oost-Vlaanderen",
    "sg:tags":[
        "confectionery",
        "-"
    ],
    "wof:name":"Leonidas-bonbolino",
    "wof:placetype":"venue"
},
  "geometry": {"coordinates":[3.7073531151,51.1132354736],"type":"Point"}
}