{
  "type": "Feature",
  "properties": {
    "iso:country":"BE",
    "sg:address":"Geelhandlaan 1",
    "sg:city":"Hove",
    "sg:orig_category":"Openbare veiligheid",
    "sg:phone":"+32 3 454 22 99",
    "sg:postcode":"2540",
    "sg:province":"Antwerpen",
    "wof:name":"Federale Politie",
    "wof:placetype":"venue"
},
  "geometry": {"coordinates":[4.4739899635,51.1475601196],"type":"Point"}
}