{
  "type": "Feature",
  "properties": {
    "addr:full":"Rue Du Sequo\u00cfa 10 Ath Hainaut 7800",
    "addr:housenumber":"10",
    "addr:postcode":"7800",
    "addr:street":"Rue Du Sequoi\u0308A",
    "iso:country":"BE",
    "sg:address":"Rue Du Sequo\u00cfa 10",
    "sg:city":"Ath",
    "sg:orig_category":"Sportclubs",
    "sg:phone":"+32 68 28 24 84",
    "sg:postcode":"7800",
    "sg:province":"Hainaut",
    "wof:name":"T.c. Sequoia Ath",
    "wof:placetype":"venue"
},
  "geometry": {"coordinates":[3.7814040184,50.6231155396],"type":"Point"}
}