{
  "type": "Feature",
  "properties": {
    "addr:full":"Rue G\u00c9rard Wilket 34 Blegny Li\u00e8ge 4672",
    "addr:housenumber":"34",
    "addr:postcode":"4672",
    "addr:street":"Rue Ge\u0301Rard Wilket",
    "iso:country":"BE",
    "sg:address":"Rue G\u00c9rard Wilket 34",
    "sg:city":"Blegny",
    "sg:orig_category":"Tuinen",
    "sg:phone":"+32 4 387 42 18",
    "sg:postcode":"4672",
    "sg:province":"Li\u00e8ge",
    "wof:name":"Jean-paul Paggen",
    "wof:placetype":"venue"
},
  "geometry": {"coordinates":[5.6983470917,50.6922149658],"type":"Point"}
}