{
  "type": "Feature",
  "properties": {
    "addr:full":"Achterstraat 22 Erpe-mere Oost-Vlaanderen 9420",
    "addr:housenumber":"22",
    "addr:postcode":"9420",
    "addr:street":"Achterstraat",
    "iso:country":"BE",
    "sg:address":"Achterstraat 22",
    "sg:city":"Erpe-mere",
    "sg:orig_category":"Peinture. Rev\u00eatements pour sols and murs",
    "sg:phone":"+32 53 83 20 08",
    "sg:postcode":"9420",
    "sg:province":"Oost-Vlaanderen",
    "wof:name":"L.j.p.-decor",
    "wof:placetype":"venue"
},
  "geometry": {"coordinates":[3.9608590603,50.9138679504],"type":"Point"}
}