{
  "type": "Feature",
  "properties": {
    "addr:full":"Koningsbeemdstraat 10 Lommel Limburg 3920",
    "addr:housenumber":"10",
    "addr:postcode":"3920",
    "addr:street":"Koningsbeemdstraat",
    "iso:country":"BE",
    "sg:address":"Koningsbeemdstraat 10",
    "sg:city":"Lommel",
    "sg:classifiers":[
        {
            "category":"Real Estate",
            "subcategory":"Surveying",
            "type":"Services"
        }
    ],
    "sg:phone":"+32 11 54 25 54",
    "sg:postcode":"3920",
    "sg:province":"Limburg",
    "sg:tags":[
        "surveyor",
        "land"
    ],
    "wof:name":"Grevendonck T",
    "wof:placetype":"venue"
},
  "geometry": {"coordinates":[5.3386340141,51.2413597107],"type":"Point"}
}