{
  "type": "Feature",
  "properties": {
    "iso:country":"BE",
    "sg:address":"Drijvelingslos 18",
    "sg:city":"Ternat",
    "sg:orig_category":"Kapsalons",
    "sg:phone":"+32 2 582 45 53",
    "sg:postcode":"1741",
    "sg:province":"Vlaams-Brabant",
    "wof:name":"Nanda Sergooris",
    "wof:placetype":"venue"
},
  "geometry": {"coordinates":[4.1623549461,50.8534507751],"type":"Point"}
}