{
  "type": "Feature",
  "properties": {
    "addr:full":"Bree\u00cbrsteenweg 256b1 Kinrooi Limburg 3640",
    "addr:housenumber":"256b1",
    "addr:postcode":"3640",
    "addr:street":"Breee\u0308Rsteenweg",
    "iso:country":"BE",
    "sg:address":"Bree\u00cbrsteenweg 256b1",
    "sg:city":"Kinrooi",
    "sg:orig_category":"Banques and organismes de cr\u00e9dit",
    "sg:phone":"+32 89 70 23 93",
    "sg:postcode":"3640",
    "sg:province":"Limburg",
    "wof:name":"Bacob",
    "wof:placetype":"venue"
},
  "geometry": {"coordinates":[5.7440490723,51.1458053589],"type":"Point"}
}