{
  "type": "Feature",
  "properties": {
    "addr:full":"Winterslagstraat 13 Genk Limburg 3600",
    "addr:housenumber":"13",
    "addr:postcode":"3600",
    "addr:street":"Winterslagstraat",
    "iso:country":"BE",
    "sg:address":"Winterslagstraat 13",
    "sg:city":"Genk",
    "sg:classifiers":[
        {
            "category":"Personal",
            "subcategory":"Beauty Salon",
            "type":"Services"
        }
    ],
    "sg:phone":"+32 89 36 42 82",
    "sg:postcode":"3600",
    "sg:province":"Limburg",
    "sg:tags":[
        "lady",
        "-",
        "hairdressing"
    ],
    "wof:name":"Eurokapper",
    "wof:placetype":"venue"
},
  "geometry": {"coordinates":[5.4982700348,50.9641304016],"type":"Point"}
}