{
  "type": "Feature",
  "properties": {
    "iso:country":"BE",
    "sg:address":"Grote Baan 153",
    "sg:city":"Haacht",
    "sg:orig_category":"Herstelling and restauratie van meubelen Plaatsen van vloer- and muurbekleding Schilders",
    "sg:phone":"+32 16 60 46 65",
    "sg:postcode":"3150",
    "sg:province":"Vlaams-Brabant",
    "wof:name":"Jules Van Rillaer",
    "wof:placetype":"venue"
},
  "geometry": {"coordinates":[4.6252741814,50.9604606628],"type":"Point"}
}