{
  "type": "Feature",
  "properties": {
    "addr:full":"Rue De La Fontaine 7 Braives Li\u00e8ge 4260",
    "addr:housenumber":"7",
    "addr:postcode":"4260",
    "addr:street":"Rue De La Fontaine",
    "iso:country":"BE",
    "sg:address":"Rue De La Fontaine 7",
    "sg:city":"Braives",
    "sg:classifiers":[
        {
            "category":"Restaurant",
            "type":"Food & Drink"
        }
    ],
    "sg:phone":"+32 19 69 99 38",
    "sg:postcode":"4260",
    "sg:province":"Li\u00e8ge",
    "sg:tags":[
        "caf\u00e9s"
    ],
    "wof:name":"Taverne Fontaine Gauloise",
    "wof:placetype":"venue"
},
  "geometry": {"coordinates":[5.1074800491,50.6302146912],"type":"Point"}
}