{
  "type": "Feature",
  "properties": {
    "iso:country":"BE",
    "sg:address":"Koningin Astridplein 43",
    "sg:city":"Antwerpen",
    "sg:orig_category":"H\u00f4tels",
    "sg:phone":"+32 3 231 21 21",
    "sg:postcode":"2018",
    "sg:province":"Antwerpen",
    "wof:name":"Agora Hotel",
    "wof:placetype":"venue"
},
  "geometry": {"coordinates":[4.4204850197,51.2187767029],"type":"Point"}
}