{
  "type": "Feature",
  "properties": {
    "addr:full":"Scailquinstraat 55 Sint-joost-ten-node/saint-josse-ten-noode Bruxelles-Capitale 1210",
    "addr:housenumber":"55",
    "addr:postcode":"1210",
    "addr:street":"Scailquinstraat",
    "iso:country":"BE",
    "sg:address":"Scailquinstraat 55",
    "sg:city":"Sint-joost-ten-node/saint-josse-ten-noode",
    "sg:orig_category":"Boekenuitgeverijen Krantenuitgeverijen Tijdschriftenuitgeverijen",
    "sg:phone":"+32 2 217 55 55",
    "sg:postcode":"1210",
    "sg:province":"Bruxelles-Capitale",
    "wof:name":"Delta Editions Guides",
    "wof:placetype":"venue"
},
  "geometry": {"coordinates":[4.3714938164,50.850112915],"type":"Point"}
}