{
  "type": "Feature",
  "properties": {
    "iso:country":"BE",
    "sg:address":"Avenue De Tervueren 202",
    "sg:city":"Bruxelles (woluwe-saint-pierre)",
    "sg:classifiers":[
        {
            "category":"Shopping",
            "subcategory":"Beauty & Cosmetics",
            "type":"Retail Goods"
        }
    ],
    "sg:phone":"+32 2 770 17 27",
    "sg:postcode":"1150",
    "sg:province":"Bruxelles-Capitale",
    "sg:tags":[
        "-",
        "perfumery"
    ],
    "wof:name":"Sabourin M",
    "wof:placetype":"venue"
},
  "geometry": {"coordinates":[4.4133291245,50.8366546631],"type":"Point"}
}