{
  "type": "Feature",
  "properties": {
    "addr:full":"Paardenmarkt 66 Antwerpen Antwerpen 2000",
    "addr:housenumber":"66",
    "addr:postcode":"2000",
    "addr:street":"Paardenmarkt",
    "iso:country":"BE",
    "sg:address":"Paardenmarkt 66",
    "sg:city":"Antwerpen",
    "sg:orig_category":"Kansspelen",
    "sg:phone":"+32 3 232 97 24",
    "sg:postcode":"2000",
    "sg:province":"Antwerpen",
    "wof:name":"Tierc\u00c9 Franco-belge",
    "wof:placetype":"venue"
},
  "geometry": {"coordinates":[4.411342144,51.2249221802],"type":"Point"}
}