{
  "type": "Feature",
  "properties": {
    "iso:country":"BE",
    "sg:address":"Rue Fran\u00c7ois Dorz\u00c9e 54",
    "sg:city":"Boussu",
    "sg:orig_category":"Schoonheidssalons",
    "sg:phone":"+32 65 77 03 91",
    "sg:postcode":"7300",
    "sg:province":"Hainaut",
    "wof:name":"Institut Jouvence",
    "wof:placetype":"venue"
},
  "geometry": {"coordinates":[3.8000309467,50.4333839417],"type":"Point"}
}