{
  "type": "Feature",
  "properties": {
    "addr:full":"Rue Du Baty 13 Mont-saint-guibert (corbais) Brabant Wallon 1435",
    "addr:housenumber":"13",
    "addr:postcode":"1435",
    "addr:street":"Rue Du Baty;Corbais;Wallon",
    "iso:country":"BE",
    "sg:address":"Rue Du Baty 13",
    "sg:city":"Mont-saint-guibert (corbais)",
    "sg:classifiers":[
        {
            "category":"Arena",
            "subcategory":"Sports Club",
            "type":"Entertainment"
        }
    ],
    "sg:phone":"+32 10 65 07 07",
    "sg:postcode":"1435",
    "sg:province":"Brabant Wallon",
    "wof:name":"Volley Ball Club Sg Ottintois Asbl",
    "wof:placetype":"venue"
},
  "geometry": {"coordinates":[4.6512460709,50.6489753723],"type":"Point"}
}