{
  "type": "Feature",
  "properties": {
    "addr:full":"Hamstraat 7 Borgloon Limburg 3840",
    "addr:housenumber":"7",
    "addr:postcode":"3840",
    "addr:street":"Hamstraat",
    "iso:country":"BE",
    "sg:address":"Hamstraat 7",
    "sg:city":"Borgloon",
    "sg:classifiers":[
        {
            "category":"Personal",
            "subcategory":"Beauty Salon",
            "type":"Services"
        }
    ],
    "sg:phone":"+32 12 74 18 24",
    "sg:postcode":"3840",
    "sg:province":"Limburg",
    "sg:tags":[
        "de",
        "coiffure"
    ],
    "wof:name":"Alfons Knapen",
    "wof:placetype":"venue"
},
  "geometry": {"coordinates":[5.2916631699,50.808921814],"type":"Point"}
}