{
  "type": "Feature",
  "properties": {
    "iso:country":"BE",
    "sg:address":"Stampkotmolenstraat 2",
    "sg:city":"Wingene",
    "sg:orig_category":"Fabrication and montage de mobilier. Installation de menuiserie en bois and plastique",
    "sg:phone":"+32 51 61 17 99",
    "sg:postcode":"8750",
    "sg:province":"West-Vlaanderen",
    "wof:name":"Hein Vandendriessche",
    "wof:placetype":"venue"
},
  "geometry": {"coordinates":[3.1896688938,51.0410346985],"type":"Point"}
}