{
  "type": "Feature",
  "properties": {
    "iso:country":"BE",
    "sg:address":"Velodroomstraat 13",
    "sg:city":"Boom",
    "sg:orig_category":"Kantoormateriaal",
    "sg:phone":"+32 3 844 47 02",
    "sg:postcode":"2850",
    "sg:province":"Antwerpen",
    "wof:name":"Claes",
    "wof:placetype":"venue"
},
  "geometry": {"coordinates":[4.3685531616,51.0966453552],"type":"Point"}
}