{
  "type": "Feature",
  "properties": {
    "iso:country":"BE",
    "sg:address":"Koben Geertsstraat 92-1",
    "sg:city":"Beveren (beveren-waas)",
    "sg:classifiers":[
        {
            "category":"Professional",
            "type":"Services"
        }
    ],
    "sg:phone":"+32 3 651 46 76",
    "sg:postcode":"9120",
    "sg:province":"Oost-Vlaanderen",
    "sg:tags":[
        "packing",
        "-"
    ],
    "wof:name":"Linflex Nv",
    "wof:placetype":"venue"
},
  "geometry": {"coordinates":[4.2498979568,51.2182044983],"type":"Point"}
}