{
  "type": "Feature",
  "properties": {
    "iso:country":"BE",
    "sg:address":"Grand'route 34",
    "sg:city":"Fexhe-le-haut-clocher",
    "sg:orig_category":"Apotheken",
    "sg:phone":"+32 4 250 12 38",
    "sg:postcode":"4347",
    "sg:province":"Li\u00e8ge",
    "wof:name":"Roland Jamart",
    "wof:placetype":"venue"
},
  "geometry": {"coordinates":[5.3987898827,50.6656417847],"type":"Point"}
}