{
  "type": "Feature",
  "properties": {
    "iso:country":"BE",
    "sg:address":"Zandvoordestraat 469",
    "sg:city":"Oostende",
    "sg:classifiers":[
        {
            "category":"Retail",
            "subcategory":"Auto Repair",
            "type":"Services"
        }
    ],
    "sg:phone":"+32 59 80 32 30",
    "sg:postcode":"8400",
    "sg:province":"West-Vlaanderen",
    "sg:tags":[
        "breakdown",
        "automobile",
        "-",
        "recovery"
    ],
    "wof:name":"Schoutteet Hendrik & Zoon",
    "wof:placetype":"venue"
},
  "geometry": {"coordinates":[2.968059063,51.2086143494],"type":"Point"}
}