{
  "type": "Feature",
  "properties": {
    "addr:full":"Brugsesteenweg 311 Kuurne West-Vlaanderen 8520",
    "addr:housenumber":"311",
    "addr:postcode":"8520",
    "addr:street":"Brugsesteenweg",
    "iso:country":"BE",
    "sg:address":"Brugsesteenweg 311",
    "sg:city":"Kuurne",
    "sg:classifiers":[
        {
            "category":"Bars & Pubs",
            "type":"Food & Drink"
        }
    ],
    "sg:phone":"+32 56 72 26 41",
    "sg:postcode":"8520",
    "sg:province":"West-Vlaanderen",
    "wof:name":"Astrid",
    "wof:placetype":"venue"
},
  "geometry": {"coordinates":[3.2705841064,50.8628540039],"type":"Point"}
}