{
  "type": "Feature",
  "properties": {
    "iso:country":"BE",
    "sg:address":"Industrieweg 16",
    "sg:city":"Boortmeerbeek (groot)",
    "sg:classifiers":[
        {
            "category":"Shopping Center",
            "type":"Public Place"
        }
    ],
    "sg:phone":"+32 16 40 85 67",
    "sg:postcode":"3190",
    "sg:province":"Vlaams-Brabant",
    "sg:tags":[
        "enseignement",
        "formation"
    ],
    "wof:name":"Safe Drivers Plan",
    "wof:placetype":"venue"
},
  "geometry": {"coordinates":[4.5843458176,50.9640159607],"type":"Point"}
}