{
  "type": "Feature",
  "properties": {
    "iso:country":"BE",
    "sg:address":"Leuvensesteenweg 393",
    "sg:city":"Kortenberg",
    "sg:classifiers":[
        {
            "category":"Communications",
            "subcategory":"Television Station",
            "type":"Services"
        }
    ],
    "sg:phone":"+32 2 759 59 02",
    "sg:postcode":"3070",
    "sg:province":"Vlaams-Brabant",
    "sg:tags":[
        "video",
        "audio",
        "verhuur"
    ],
    "wof:name":"Spelier Electronics Rent",
    "wof:placetype":"venue"
},
  "geometry": {"coordinates":[4.5422239304,50.888004303],"type":"Point"}
}