{
  "type": "Feature",
  "properties": {
    "addr:full":"Boulevard Industriel 98 Mouscron Hainaut 7700",
    "addr:housenumber":"98",
    "addr:postcode":"7700",
    "addr:street":"Boulevard Industriel",
    "iso:country":"BE",
    "sg:address":"Boulevard Industriel 98",
    "sg:city":"Mouscron",
    "sg:classifiers":[
        {
            "category":"Home & Garden",
            "subcategory":"Building Materials",
            "type":"Retail Goods"
        }
    ],
    "sg:phone":"+32 56 84 33 90",
    "sg:postcode":"7700",
    "sg:province":"Hainaut",
    "sg:tags":[
        "yarn",
        "carpet"
    ],
    "wof:name":"Laini\u00e8re Du Nord S.p.r.l.",
    "wof:placetype":"venue"
},
  "geometry": {"coordinates":[3.2503800392,50.7498931885],"type":"Point"}
}