{
  "type": "Feature",
  "properties": {
    "iso:country":"BE",
    "sg:address":"Rue Marquais 28",
    "sg:city":"Bernissart",
    "sg:orig_category":"Kansspelen",
    "sg:phone":"+32 69 56 21 62",
    "sg:postcode":"7321",
    "sg:province":"Hainaut",
    "wof:name":"Tierc\u00c9 Vincennes",
    "wof:placetype":"venue"
},
  "geometry": {"coordinates":[3.6876299381,50.475818634],"type":"Point"}
}