{
  "type": "Feature",
  "properties": {
    "addr:full":"Espeler 4c Burg-reuland (thommen) Li\u00e8ge 4791",
    "addr:housenumber":"4c",
    "addr:postcode":"4791",
    "addr:street":"Espeler;Thommen",
    "iso:country":"BE",
    "sg:address":"Espeler 4c",
    "sg:city":"Burg-reuland (thommen)",
    "sg:classifiers":[
        {
            "category":"Building & Trades",
            "subcategory":"Electrical",
            "type":"Services"
        }
    ],
    "sg:phone":"+32 80 42 01 85",
    "sg:postcode":"4791",
    "sg:province":"Li\u00e8ge",
    "sg:tags":[
        "electric",
        "-",
        "housewiring",
        "contractor"
    ],
    "wof:name":"Bongen A",
    "wof:placetype":"venue"
},
  "geometry": {"coordinates":[6.0944099426,50.2024497986],"type":"Point"}
}