{
  "type": "Feature",
  "properties": {
    "iso:country":"BE",
    "sg:address":"Marais D'ergies 1",
    "sg:city":"Frasnes-lez-anvaing",
    "sg:orig_category":"Equipements pour la construction D\u00e9molition d\u00b4immeubles and terrassements",
    "sg:phone":"+32 69 86 79 43",
    "sg:postcode":"7911",
    "sg:province":"Hainaut",
    "wof:name":"Vermeire D.",
    "wof:placetype":"venue"
},
  "geometry": {"coordinates":[3.6267259121,50.6684608459],"type":"Point"}
}