{
  "type": "Feature",
  "properties": {
    "addr:full":"All\u00c9e Des Patriotes 15 Tournai Hainaut 7501",
    "addr:housenumber":"15",
    "addr:postcode":"7501",
    "addr:street":"Alle\u0301E Des Patriotes",
    "iso:country":"BE",
    "sg:address":"All\u00c9e Des Patriotes 15",
    "sg:city":"Tournai",
    "sg:orig_category":"Epiceries",
    "sg:phone":"+32 69 21 09 41",
    "sg:postcode":"7501",
    "sg:province":"Hainaut",
    "wof:name":"Patrick Delaunoy",
    "wof:placetype":"venue"
},
  "geometry": {"coordinates":[3.3569309711,50.6055145264],"type":"Point"}
}