{
  "type": "Feature",
  "properties": {
    "addr:full":"Heuem 6ba Sankt Vith/saint-vith Li\u00e8ge 4783",
    "addr:housenumber":"6ba",
    "addr:postcode":"4783",
    "addr:street":"Heuem",
    "iso:country":"BE",
    "sg:address":"Heuem 6ba",
    "sg:city":"Sankt Vith/saint-vith",
    "sg:orig_category":"Banken and kredietinstellingen",
    "sg:phone":"+32 80 22 60 93",
    "sg:postcode":"4783",
    "sg:province":"Li\u00e8ge",
    "wof:name":"Centea",
    "wof:placetype":"venue"
},
  "geometry": {"coordinates":[6.2361302376,50.2862586975],"type":"Point"}
}