{
  "type": "Feature",
  "properties": {
    "iso:country":"BE",
    "sg:address":"Jozef De Somerlaan 20",
    "sg:city":"Erpe-mere",
    "sg:orig_category":"Herstellingen and onderhoud van auto's",
    "sg:phone":"+32 53 80 64 59",
    "sg:postcode":"9420",
    "sg:province":"Oost-Vlaanderen",
    "wof:name":"Fa.van Hecke-de Schrijver",
    "wof:placetype":"venue"
},
  "geometry": {"coordinates":[3.9708631039,50.9401473999],"type":"Point"}
}