{
  "type": "Feature",
  "properties": {
    "iso:country":"BE",
    "sg:address":"Meesterstraat 48",
    "sg:city":"Sint-niklaas",
    "sg:classifiers":[
        {
            "category":"Arena",
            "subcategory":"Sports Club",
            "type":"Entertainment"
        }
    ],
    "sg:phone":"+32 3 776 67 51",
    "sg:postcode":"9100",
    "sg:province":"Oost-Vlaanderen",
    "sg:tags":[
        "de"
    ],
    "wof:name":"De Snelle Postduif",
    "wof:placetype":"venue"
},
  "geometry": {"coordinates":[4.17796278,51.1874923706],"type":"Point"}
}