{
  "type": "Feature",
  "properties": {
    "addr:full":"Hasseltsestraat 21 Bilzen Limburg 3740",
    "addr:housenumber":"21",
    "addr:postcode":"3740",
    "addr:street":"Hasseltsestraat",
    "iso:country":"BE",
    "sg:address":"Hasseltsestraat 21",
    "sg:city":"Bilzen",
    "sg:classifiers":[
        {
            "category":"Home & Garden",
            "subcategory":"Building Materials",
            "type":"Retail Goods"
        }
    ],
    "sg:phone":"+32 89 41 18 29",
    "sg:postcode":"3740",
    "sg:province":"Limburg",
    "sg:tags":[
        "veranda"
    ],
    "wof:name":"Moosen & Fils",
    "wof:placetype":"venue"
},
  "geometry": {"coordinates":[5.513712883,50.8730926514],"type":"Point"}
}