{
  "type": "Feature",
  "properties": {
    "addr:full":"Koning Albertstraat 49 Diest Vlaams-Brabant 3290",
    "addr:housenumber":"49",
    "addr:postcode":"3290",
    "addr:street":"Koning Albertstraat",
    "iso:country":"BE",
    "sg:address":"Koning Albertstraat 49",
    "sg:city":"Diest",
    "sg:classifiers":[
        {
            "category":"Professional",
            "subcategory":"Testing Lab",
            "type":"Services"
        }
    ],
    "sg:phone":"+32 13 33 33 17",
    "sg:postcode":"3290",
    "sg:province":"Vlaams-Brabant",
    "sg:tags":[
        "chemist"
    ],
    "wof:name":"Coertjens L",
    "wof:placetype":"venue"
},
  "geometry": {"coordinates":[5.0537481308,50.9862136841],"type":"Point"}
}