{
  "type": "Feature",
  "properties": {
    "iso:country":"BE",
    "sg:address":"Varenberg 5",
    "sg:city":"Ninove",
    "sg:orig_category":"Rundveehouders",
    "sg:phone":"+32 54 33 76 54",
    "sg:postcode":"9400",
    "sg:province":"Oost-Vlaanderen",
    "wof:name":"Aime Timmermans",
    "wof:placetype":"venue"
},
  "geometry": {"coordinates":[4.033572197,50.803943634],"type":"Point"}
}