{
  "type": "Feature",
  "properties": {
    "iso:country":"BE",
    "sg:address":"Avenue De Sheut 143 A",
    "sg:city":"Anderlecht",
    "sg:orig_category":"Produits d'entretien Gr",
    "sg:phone":"+32 2 527 50 55",
    "sg:postcode":"1070",
    "sg:province":"Bruxelles-Capitale",
    "wof:name":"Uni Trade",
    "wof:placetype":"venue"
},
  "geometry": {"coordinates":[4.3115978241,50.8451118469],"type":"Point"}
}