{
  "type": "Feature",
  "properties": {
    "iso:country":"BE",
    "sg:address":"Lisperstw 269",
    "sg:city":"Lier",
    "sg:classifiers":[
        {
            "category":"Banks & Credit Unions",
            "subcategory":"Bank",
            "type":"Services"
        }
    ],
    "sg:phone":"+32 3 480 40 90",
    "sg:postcode":"2500",
    "sg:province":"Antwerpen",
    "wof:name":"Aslk-cger Bank",
    "wof:placetype":"venue"
},
  "geometry": {"coordinates":[4.5755329132,51.1447486877],"type":"Point"}
}