{
  "type": "Feature",
  "properties": {
    "addr:full":"Waagstraat 2 Ninove (aspelare) Oost-Vlaanderen 9404",
    "addr:housenumber":"2",
    "addr:postcode":"9404",
    "addr:street":"Waagstraat",
    "iso:country":"BE",
    "sg:address":"Waagstraat 2",
    "sg:city":"Ninove (aspelare)",
    "sg:classifiers":[
        {
            "category":"Animal Shelter",
            "type":"Public Place"
        }
    ],
    "sg:phone":"+32 54 50 10 61",
    "sg:postcode":"9404",
    "sg:province":"Oost-Vlaanderen",
    "sg:tags":[
        "clinic"
    ],
    "wof:name":"Equicare",
    "wof:placetype":"venue"
},
  "geometry": {"coordinates":[3.9570000172,50.8419036865],"type":"Point"}
}