{
  "type": "Feature",
  "properties": {
    "addr:full":"Kalfortdorp 46 Puurs Antwerpen 2870",
    "addr:housenumber":"46",
    "addr:postcode":"2870",
    "addr:street":"Kalfortdorp",
    "iso:country":"BE",
    "sg:address":"Kalfortdorp 46",
    "sg:city":"Puurs",
    "sg:orig_category":"Plomberie, chauffage and installations sanitaires",
    "sg:phone":"+32 3 889 73 70",
    "sg:postcode":"2870",
    "sg:province":"Antwerpen",
    "wof:name":"Yoeri Szapinszki",
    "wof:placetype":"venue"
},
  "geometry": {"coordinates":[4.2772698402,51.0763244629],"type":"Point"}
}