{
  "type": "Feature",
  "properties": {
    "iso:country":"BE",
    "sg:address":"Boulevard Heynen 14",
    "sg:city":"Bouillon",
    "sg:orig_category":"Artsen and specialisten",
    "sg:phone":"+32 61 46 57 40",
    "sg:postcode":"6830",
    "sg:province":"Luxembourg",
    "wof:name":"Centre Provincial De Sant\u00c9",
    "wof:placetype":"venue"
},
  "geometry": {"coordinates":[5.0699400902,49.7964706421],"type":"Point"}
}