{
  "type": "Feature",
  "properties": {
    "addr:full":"Industripark 1243 Halen Limburg 3545",
    "addr:postcode":"1243 halen;3545",
    "addr:street":"Industripark",
    "iso:country":"BE",
    "sg:address":"Industripark 1243",
    "sg:city":"Halen",
    "sg:orig_category":"Mat\u00e9riel de contr\u00f4le des processus industriels Fab",
    "sg:phone":"+32 13 44 17 46",
    "sg:postcode":"3545",
    "sg:province":"Limburg",
    "wof:name":"Dastronic",
    "wof:placetype":"venue"
},
  "geometry": {"coordinates":[5.1109762192,50.953453064],"type":"Point"}
}