{
  "type": "Feature",
  "properties": {
    "iso:country":"BE",
    "sg:address":"Ekestraat 7",
    "sg:city":"Alveringem (leisele)",
    "sg:classifiers":[
        {
            "category":"Travel",
            "subcategory":"Resort",
            "type":"Entertainment"
        }
    ],
    "sg:phone":"+32 57 33 79 30",
    "sg:postcode":"8691",
    "sg:province":"West-Vlaanderen",
    "sg:tags":[
        "farm",
        "house",
        "holiday",
        "guest"
    ],
    "wof:name":"Eikhoeve (de)",
    "wof:placetype":"venue"
},
  "geometry": {"coordinates":[2.6668748856,50.9602241516],"type":"Point"}
}