{
  "type": "Feature",
  "properties": {
    "addr:full":"Rue Charlemont 62 Chastre Brabant Wallon 1450",
    "addr:housenumber":"62",
    "addr:postcode":"1450",
    "addr:street":"Rue Charlemont",
    "iso:country":"BE",
    "sg:address":"Rue Charlemont 62",
    "sg:city":"Chastre",
    "sg:orig_category":"M\u00e9decins and sp\u00e9cialistes",
    "sg:phone":"+32 71 87 72 46",
    "sg:postcode":"1450",
    "sg:province":"Brabant Wallon",
    "wof:name":"Marc Willem",
    "wof:placetype":"venue"
},
  "geometry": {"coordinates":[4.636452198,50.6085243225],"type":"Point"}
}