{
  "type": "Feature",
  "properties": {
    "iso:country":"BE",
    "sg:address":"Westerring 35",
    "sg:city":"Oudenaarde",
    "sg:orig_category":"R\u00e9alisation de programmes and logiciels. Fournitures de bureau. Mobilier and \u00e9quipement m\u00e9nager Gr",
    "sg:phone":"+32 55 33 12 12",
    "sg:postcode":"9700",
    "sg:province":"Oost-Vlaanderen",
    "wof:name":"Lumap",
    "wof:placetype":"venue"
},
  "geometry": {"coordinates":[3.6073288918,50.8692359924],"type":"Point"}
}