{
  "type": "Feature",
  "properties": {
    "iso:country":"BE",
    "sg:address":"Torhoutsesteenweg 661",
    "sg:city":"Oostende",
    "sg:classifiers":[
        {
            "category":"Home & Garden",
            "subcategory":"Hardware",
            "type":"Retail Goods"
        }
    ],
    "sg:phone":"+32 59 80 16 23",
    "sg:postcode":"8400",
    "sg:province":"West-Vlaanderen",
    "sg:tags":[
        "machine",
        "horticultural"
    ],
    "wof:name":"Knap-op Nv",
    "wof:placetype":"venue"
},
  "geometry": {"coordinates":[2.9048330784,51.2084617615],"type":"Point"}
}