{
  "type": "Feature",
  "properties": {
    "iso:country":"BE",
    "sg:address":"Hoogstraat 79",
    "sg:city":"Antwerpen",
    "sg:orig_category":"Antiek Tweedehandsgoederen",
    "sg:phone":"+32 3 321 67 63",
    "sg:postcode":"2000",
    "sg:province":"Antwerpen",
    "wof:name":"Antiek Taeymans",
    "wof:placetype":"venue"
},
  "geometry": {"coordinates":[4.3970150948,51.2183837891],"type":"Point"}
}