{
  "type": "Feature",
  "properties": {
    "addr:full":"Rue De Landen 2 Hannut Li\u00e8ge 4280",
    "addr:housenumber":"2",
    "addr:postcode":"4280",
    "addr:street":"Rue De Landen",
    "iso:country":"BE",
    "sg:address":"Rue De Landen 2",
    "sg:city":"Hannut",
    "sg:classifiers":[
        {
            "category":"Fast Food",
            "type":"Food & Drink"
        }
    ],
    "sg:phone":"+32 19 51 15 16",
    "sg:postcode":"4280",
    "sg:province":"Li\u00e8ge",
    "sg:tags":[
        "meeneem",
        "restaurant"
    ],
    "wof:name":"Le Greco",
    "wof:placetype":"venue"
},
  "geometry": {"coordinates":[5.0788621902,50.672618866],"type":"Point"}
}