{
  "type": "Feature",
  "properties": {
    "addr:full":"Veurterstraat 5 Neerpelt (sint-huibrechts-lille) Limburg 3910",
    "addr:housenumber":"5",
    "addr:postcode":"3910",
    "addr:street":"Veurterstraat",
    "iso:country":"BE",
    "sg:address":"Veurterstraat 5",
    "sg:city":"Neerpelt (sint-huibrechts-lille)",
    "sg:classifiers":[
        {
            "category":"Professional",
            "subcategory":"Management & Consulting",
            "type":"Services"
        }
    ],
    "sg:phone":"+32 11 64 00 24",
    "sg:postcode":"3910",
    "sg:province":"Limburg",
    "sg:tags":[
        "consultant",
        "agency",
        "advertising"
    ],
    "wof:name":"Coenen E",
    "wof:placetype":"venue"
},
  "geometry": {"coordinates":[5.484705925,51.2228507996],"type":"Point"}
}