{
  "type": "Feature",
  "properties": {
    "iso:country":"BE",
    "sg:address":"Schonenberg 52",
    "sg:city":"Herzele",
    "sg:classifiers":[
        {
            "category":"Restaurant",
            "type":"Food & Drink"
        }
    ],
    "sg:phone":"+32 54 50 27 35",
    "sg:postcode":"9550",
    "sg:province":"Oost-Vlaanderen",
    "wof:name":"Gasthof Bautendoorn",
    "wof:placetype":"venue"
},
  "geometry": {"coordinates":[3.8716449738,50.8572235107],"type":"Point"}
}