{
  "type": "Feature",
  "properties": {
    "iso:country":"BE",
    "sg:address":"Meersenweg 72",
    "sg:city":"Beveren",
    "sg:orig_category":"Woningbouw",
    "sg:phone":"+32 3 775 99 27",
    "sg:postcode":"9120",
    "sg:province":"Oost-Vlaanderen",
    "wof:name":"Fa. Van Nieuwenhove Gebrs",
    "wof:placetype":"venue"
},
  "geometry": {"coordinates":[4.265378952,51.2236709595],"type":"Point"}
}