{
  "type": "Feature",
  "properties": {
    "addr:full":"Staalputstraat 8 Aalter Oost-Vlaanderen 9880",
    "addr:housenumber":"8",
    "addr:postcode":"9880",
    "addr:street":"Staalputstraat",
    "iso:country":"BE",
    "sg:address":"Staalputstraat 8",
    "sg:city":"Aalter",
    "sg:orig_category":"Installation \u00e9lectrique r\u00e9sidentielle",
    "sg:phone":"+32 9 375 22 62",
    "sg:postcode":"9880",
    "sg:province":"Oost-Vlaanderen",
    "wof:name":"Mario Colpaert",
    "wof:placetype":"venue"
},
  "geometry": {"coordinates":[3.4362249374,51.08568573],"type":"Point"}
}