{
  "type": "Feature",
  "properties": {
    "addr:full":"Sleepstraat 128 Gent Oost-Vlaanderen 9000",
    "addr:housenumber":"128",
    "addr:postcode":"9000",
    "addr:street":"Sleepstraat;Oost-Vlaanderen",
    "iso:country":"BE",
    "sg:address":"Sleepstraat 128",
    "sg:city":"Gent",
    "sg:orig_category":"Boucheries",
    "sg:phone":"+32 9 233 46 66",
    "sg:postcode":"9000",
    "sg:province":"Oost-Vlaanderen",
    "wof:name":"Slagerij Sultan",
    "wof:placetype":"venue"
},
  "geometry": {"coordinates":[3.7275900841,51.0621032715],"type":"Point"}
}