{
  "type": "Feature",
  "properties": {
    "iso:country":"BE",
    "sg:address":"Varkensmarkt 13",
    "sg:city":"Brussel/bruxelles",
    "sg:classifiers":[
        {
            "category":"Restaurant",
            "type":"Food & Drink"
        }
    ],
    "sg:phone":"+32 2 512 32 93",
    "sg:postcode":"1000",
    "sg:province":"Bruxelles-Capitale",
    "sg:tags":[
        "organisatie",
        "feesten",
        "van",
        "catering"
    ],
    "wof:name":"Restaurant Strofilia",
    "wof:placetype":"venue"
},
  "geometry": {"coordinates":[4.3461527824,50.8532295227],"type":"Point"}
}