{
  "type": "Feature",
  "properties": {
    "addr:full":"Ruststraat 22 Gent Oost-Vlaanderen 9000",
    "addr:housenumber":"22",
    "addr:postcode":"9000",
    "addr:street":"Ruststraat;Oost-Vlaanderen",
    "iso:country":"BE",
    "sg:address":"Ruststraat 22",
    "sg:city":"Gent",
    "sg:orig_category":"Artistes ind\u00e9pendants",
    "sg:phone":"+32 9 220 03 63",
    "sg:postcode":"9000",
    "sg:province":"Oost-Vlaanderen",
    "wof:name":"Henry's Gallery",
    "wof:placetype":"venue"
},
  "geometry": {"coordinates":[3.7283289433,51.0288887024],"type":"Point"}
}