{
  "type": "Feature",
  "properties": {
    "addr:full":"Vilvoordelaan 67-69 Zaventem Vlaams-Brabant 1930",
    "addr:postcode":"67-69;1930",
    "addr:street":"Vilvoordelaan",
    "iso:country":"BE",
    "sg:address":"Vilvoordelaan 67-69",
    "sg:city":"Zaventem",
    "sg:orig_category":"Herstellingen and onderhoud van auto's Voertuigen",
    "sg:phone":"+32 2 720 18 37",
    "sg:postcode":"1930",
    "sg:province":"Vlaams-Brabant",
    "wof:name":"J. P. Motors",
    "wof:placetype":"venue"
},
  "geometry": {"coordinates":[4.4706110954,50.8892326355],"type":"Point"}
}