{
  "type": "Feature",
  "properties": {
    "addr:full":"Nederstraat 47 Oudenaarde Oost-Vlaanderen 9700",
    "addr:housenumber":"47",
    "addr:postcode":"9700",
    "addr:street":"Nederstraat",
    "iso:country":"BE",
    "sg:address":"Nederstraat 47",
    "sg:city":"Oudenaarde",
    "sg:orig_category":"Cosmetica and toiletartikelen Drogisterijen",
    "sg:phone":"+32 55 30 39 15",
    "sg:postcode":"9700",
    "sg:province":"Oost-Vlaanderen",
    "wof:name":"Kruidvat",
    "wof:placetype":"venue"
},
  "geometry": {"coordinates":[3.603192091,50.8452148438],"type":"Point"}
}