{
  "type": "Feature",
  "properties": {
    "addr:full":"Avenue Le Marinel 10 Bruxelles (etterbeek) Bruxelles-Capitale 1040",
    "addr:housenumber":"10",
    "addr:postcode":"1040",
    "addr:street":"Avenue Le Marinel",
    "iso:country":"BE",
    "sg:address":"Avenue Le Marinel 10",
    "sg:city":"Bruxelles (etterbeek)",
    "sg:classifiers":[
        {
            "category":"Building & Trades",
            "subcategory":"Construction",
            "type":"Services"
        }
    ],
    "sg:phone":"+32 2 736 38 63",
    "sg:postcode":"1040",
    "sg:province":"Bruxelles-Capitale",
    "sg:tags":[
        "glazier"
    ],
    "wof:name":"Daems W",
    "wof:placetype":"venue"
},
  "geometry": {"coordinates":[4.3971018791,50.8308944702],"type":"Point"}
}