{
  "type": "Feature",
  "properties": {
    "addr:full":"Sint-jansstraat 0 Poperinge West-Vlaanderen 8970",
    "addr:housenumber":"0",
    "addr:postcode":"8970",
    "addr:street":"Sint-Jansstraat",
    "iso:country":"BE",
    "sg:address":"Sint-jansstraat 0",
    "sg:city":"Poperinge",
    "sg:orig_category":"Installatie van houten of kunststof schrijnwerk",
    "sg:phone":"+32 57 33 58 61",
    "sg:postcode":"8970",
    "sg:province":"West-Vlaanderen",
    "wof:name":"Fa. Carton H.",
    "wof:placetype":"venue"
},
  "geometry": {"coordinates":[2.762237072,50.8546791077],"type":"Point"}
}