{
  "type": "Feature",
  "properties": {
    "iso:country":"BE",
    "sg:address":"Diesterstraat 80",
    "sg:city":"Tessenderlo",
    "sg:orig_category":"Epiceries",
    "sg:phone":"+32 13 67 34 51",
    "sg:postcode":"3980",
    "sg:province":"Limburg",
    "wof:name":"Maria Fierens",
    "wof:placetype":"venue"
},
  "geometry": {"coordinates":[5.0885219574,51.0634880066],"type":"Point"}
}