{
  "type": "Feature",
  "properties": {
    "iso:country":"BE",
    "sg:address":"Tervuursesteenweg 216",
    "sg:city":"Steenokkerzeel",
    "sg:orig_category":"Woningbouw",
    "sg:phone":"+32 2 751 99 92",
    "sg:postcode":"1820",
    "sg:province":"Vlaams-Brabant",
    "wof:name":"Verdoodt-smets",
    "wof:placetype":"venue"
},
  "geometry": {"coordinates":[4.4997029305,50.9213867188],"type":"Point"}
}