{
  "type": "Feature",
  "properties": {
    "iso:country":"BE",
    "sg:address":"Beau Site 1\u00c8re Avenue 26",
    "sg:city":"Rixensart",
    "sg:orig_category":"Cr\u00e8ches and garderies d'enfants",
    "sg:phone":"+32 2 653 13 69",
    "sg:postcode":"1330",
    "sg:province":"Brabant Wallon",
    "wof:name":"Les Dauphins",
    "wof:placetype":"venue"
},
  "geometry": {"coordinates":[4.5411100388,50.7141990662],"type":"Point"}
}