{
  "type": "Feature",
  "properties": {
    "iso:country":"BE",
    "sg:address":"Paradis 28",
    "sg:city":"Ellezelles",
    "sg:classifiers":[
        {
            "category":"Insurance",
            "subcategory":"Insurance Agent",
            "type":"Services"
        }
    ],
    "sg:phone":"+32 68 44 81 82",
    "sg:postcode":"7890",
    "sg:province":"Hainaut",
    "sg:tags":[
        "verzekeringsmakelaars",
        "expert"
    ],
    "wof:name":"Lenoir",
    "wof:placetype":"venue"
},
  "geometry": {"coordinates":[3.707752943,50.7321739197],"type":"Point"}
}