{
  "type": "Feature",
  "properties": {
    "iso:country":"BE",
    "sg:address":"Diksmuidesteenweg 17",
    "sg:city":"Hooglede",
    "sg:orig_category":"R\u00e9alisation de programmes and logiciels. Conseils en syst\u00e8mes informatiques",
    "sg:phone":"+32 51 26 50 88",
    "sg:postcode":"8830",
    "sg:province":"West-Vlaanderen",
    "wof:name":"Easy Solutions",
    "wof:placetype":"venue"
},
  "geometry": {"coordinates":[3.0761380196,50.958732605],"type":"Point"}
}