{
  "type": "Feature",
  "properties": {
    "addr:full":"Matstraat 14 Essen Antwerpen 2910",
    "addr:housenumber":"14",
    "addr:postcode":"2910",
    "addr:street":"Matstraat",
    "iso:country":"BE",
    "sg:address":"Matstraat 14",
    "sg:city":"Essen",
    "sg:classifiers":[
        {
            "category":"Insurance",
            "subcategory":"Insurance Agent",
            "type":"Services"
        }
    ],
    "sg:phone":"+32 3 667 44 36",
    "sg:postcode":"2910",
    "sg:province":"Antwerpen",
    "sg:tags":[
        "verzekeringsmakelaars",
        "expert"
    ],
    "wof:name":"Groep T",
    "wof:placetype":"venue"
},
  "geometry": {"coordinates":[4.4436788559,51.4547386169],"type":"Point"}
}