{
  "type": "Feature",
  "properties": {
    "iso:country":"BE",
    "sg:address":"Kalkendorp 49",
    "sg:city":"Laarne (kalken)",
    "sg:classifiers":[
        {
            "category":"Retail",
            "subcategory":"Event Space",
            "type":"Services"
        }
    ],
    "sg:phone":"+32 9 326 07 43",
    "sg:postcode":"9270",
    "sg:province":"Oost-Vlaanderen",
    "sg:tags":[
        "rental",
        "-",
        "hall"
    ],
    "wof:name":"Reigersnest",
    "wof:placetype":"venue"
},
  "geometry": {"coordinates":[3.9175400734,51.0364494324],"type":"Point"}
}