{
  "type": "Feature",
  "properties": {
    "addr:full":"Route De Ch\u00c2telet 186 Charleroi Hainaut 6010",
    "addr:housenumber":"186",
    "addr:postcode":"6010",
    "addr:street":"Route De Cha\u0302Telet;Hainaut",
    "iso:country":"BE",
    "sg:address":"Route De Ch\u00c2telet 186",
    "sg:city":"Charleroi",
    "sg:orig_category":"Installation \u00e9lectrique r\u00e9sidentielle",
    "sg:phone":"+32 71 36 37 54",
    "sg:postcode":"6010",
    "sg:province":"Hainaut",
    "wof:name":"Ctre S\u00c9curit\u00c9 Vol & Incen",
    "wof:placetype":"venue"
},
  "geometry": {"coordinates":[4.4637928009,50.3919296265],"type":"Point"}
}