{
  "type": "Feature",
  "properties": {
    "addr:full":"Bullingen 106 B\u00dcllingen/bullange Li\u00e8ge 4760",
    "addr:housenumber":"106",
    "addr:postcode":"4760",
    "addr:street":"Bullingen",
    "iso:country":"BE",
    "sg:address":"Bullingen 106",
    "sg:city":"B\u00dcllingen/bullange",
    "sg:classifiers":[
        {
            "category":"Cafe",
            "type":"Food & Drink"
        }
    ],
    "sg:phone":"+32 80 64 31 77",
    "sg:postcode":"4760",
    "sg:province":"Li\u00e8ge",
    "sg:tags":[
        "caf\u00e9s"
    ],
    "wof:name":"Manfred Peters",
    "wof:placetype":"venue"
},
  "geometry": {"coordinates":[6.304910183,50.4083137512],"type":"Point"}
}