{
  "type": "Feature",
  "properties": {
    "iso:country":"BE",
    "sg:address":"Hertoginstr 82",
    "sg:city":"Turnhout",
    "sg:classifiers":[
        {
            "category":"Wholesale",
            "subcategory":"Medical Equipment & Supplies",
            "type":"Manufacturing & Wholesale Goods"
        }
    ],
    "sg:phone":"+32 14 47 08 90",
    "sg:postcode":"2300",
    "sg:province":"Antwerpen",
    "sg:tags":[
        "instrument",
        "health",
        "-",
        "precision"
    ],
    "wof:name":"Diamed Benelux Nv",
    "wof:placetype":"venue"
},
  "geometry": {"coordinates":[4.9241018295,51.3255271912],"type":"Point"}
}