{
  "type": "Feature",
  "properties": {
    "addr:full":"Boomsesteenweg 609 Wilrijk Antwerpen 2610",
    "addr:housenumber":"609",
    "addr:postcode":"2610",
    "addr:street":"Boomsesteenweg;Antwerpen",
    "iso:country":"BE",
    "sg:address":"Boomsesteenweg 609",
    "sg:city":"Wilrijk",
    "sg:classifiers":[
        {
            "category":"Shopping",
            "subcategory":"Hobbies, Toys, & Games",
            "type":"Retail Goods"
        }
    ],
    "sg:phone":"+32 3 825 40 40",
    "sg:postcode":"2610",
    "sg:province":"Antwerpen",
    "sg:tags":[
        "product",
        "miscellaneous",
        "entertainment"
    ],
    "wof:name":"Funtastic Antes Nv",
    "wof:placetype":"venue"
},
  "geometry": {"coordinates":[4.3846359253,51.1599197388],"type":"Point"}
}