{
  "type": "Feature",
  "properties": {
    "iso:country":"BE",
    "sg:address":"Albertlaan (koning) 9",
    "sg:city":"Brussel",
    "sg:classifiers":[
        {
            "category":"Banks & Credit Unions",
            "subcategory":"Bureau De Change",
            "type":"Services"
        }
    ],
    "sg:phone":"+32 2 205 82 61",
    "sg:postcode":"1120",
    "sg:province":"Bruxelles-Capitale",
    "sg:tags":[
        "card"
    ],
    "wof:name":"Europay Belgium C.v.b.a.",
    "wof:placetype":"venue"
},
  "geometry": {"coordinates":[4.3721008301,50.8951034546],"type":"Point"}
}