{
  "type": "Feature",
  "properties": {
    "iso:country":"BE",
    "sg:address":"Nieuwe Westweg",
    "sg:city":"Antwerpen",
    "sg:classifiers":[
        {
            "category":"Harbor",
            "type":"Transportation"
        }
    ],
    "sg:phone":"+32 3 561 55 11",
    "sg:postcode":"2040",
    "sg:province":"Antwerpen",
    "sg:tags":[
        "port",
        "facility"
    ],
    "wof:name":"P & O Ports Nv",
    "wof:placetype":"venue"
},
  "geometry": {"coordinates":[4.3392300606,51.3332061768],"type":"Point"}
}