{
  "type": "Feature",
  "properties": {
    "iso:country":"BE",
    "sg:address":"Stationsstraat 169",
    "sg:city":"Herselt (ramsel)",
    "sg:classifiers":[
        {
            "category":"Arts & Performance",
            "subcategory":"Music",
            "type":"Entertainment"
        }
    ],
    "sg:phone":"+32 475 91 18 01",
    "sg:postcode":"2230",
    "sg:province":"Antwerpen",
    "sg:tags":[
        "disc-jockeys"
    ],
    "wof:name":"Scoebidoe Discobar",
    "wof:placetype":"venue"
},
  "geometry": {"coordinates":[4.8247737885,51.0318756104],"type":"Point"}
}