{
  "type": "Feature",
  "properties": {
    "iso:country":"BE",
    "sg:address":"Jan-bapt.de Keyzerstraat 154",
    "sg:city":"Wezembeek-oppem",
    "sg:orig_category":"Bloemen and planten",
    "sg:phone":"+32 2 731 71 66",
    "sg:postcode":"1970",
    "sg:province":"Vlaams-Brabant",
    "wof:name":"Etn. Schoonbroodt",
    "wof:placetype":"venue"
},
  "geometry": {"coordinates":[4.489511013,50.8471565247],"type":"Point"}
}