{
  "type": "Feature",
  "properties": {
    "addr:full":"Rue Du Haut-bois 8b1 Mons Hainaut 7000",
    "addr:housenumber":"8b1",
    "addr:postcode":"7000",
    "addr:street":"Rue Du Haut-Bois;Hainaut",
    "iso:country":"BE",
    "sg:address":"Rue Du Haut-bois 8b1",
    "sg:city":"Mons",
    "sg:orig_category":"Chaussures",
    "sg:phone":"+32 65 35 23 76",
    "sg:postcode":"7000",
    "sg:province":"Hainaut",
    "wof:name":"Sabot De L'yser",
    "wof:placetype":"venue"
},
  "geometry": {"coordinates":[3.9542050362,50.4524879456],"type":"Point"}
}