{
  "type": "Feature",
  "properties": {
    "addr:full":"Rue Du Roetaert 99 Bruxelles (uccle) Bruxelles-Capitale 1180",
    "addr:housenumber":"99",
    "addr:postcode":"1180",
    "addr:street":"Rue Du Roetaert",
    "iso:country":"BE",
    "sg:address":"Rue Du Roetaert 99",
    "sg:city":"Bruxelles (uccle)",
    "sg:classifiers":[
        {
            "category":"Health Services",
            "subcategory":"Health Practitioner",
            "type":"Services"
        }
    ],
    "sg:phone":"+32 2 376 33 31",
    "sg:postcode":"1180",
    "sg:province":"Bruxelles-Capitale",
    "sg:tags":[
        "physiotherapist"
    ],
    "wof:name":"Lombart E",
    "wof:placetype":"venue"
},
  "geometry": {"coordinates":[4.3258261681,50.799079895],"type":"Point"}
}