{
  "type": "Feature",
  "properties": {
    "addr:full":"Meerskant 5 Deinze Oost-Vlaanderen 9800",
    "addr:housenumber":"5",
    "addr:postcode":"9800",
    "addr:street":"Meerskant",
    "iso:country":"BE",
    "sg:address":"Meerskant 5",
    "sg:city":"Deinze",
    "sg:orig_category":"Rundveehouders",
    "sg:phone":"+32 9 386 15 64",
    "sg:postcode":"9800",
    "sg:province":"Oost-Vlaanderen",
    "wof:name":"Didier Hautekeete",
    "wof:placetype":"venue"
},
  "geometry": {"coordinates":[3.530174017,50.9863166809],"type":"Point"}
}