{
  "type": "Feature",
  "properties": {
    "iso:country":"BE",
    "sg:address":"Rue De Malaise 2a",
    "sg:city":"Rixensart (rosi\u00e8res)",
    "sg:classifiers":[
        {
            "category":"Professional",
            "subcategory":"Art Services",
            "type":"Services"
        }
    ],
    "sg:phone":"+32 2 654 15 15",
    "sg:postcode":"1331",
    "sg:province":"Brabant Wallon",
    "sg:tags":[
        "photographer"
    ],
    "wof:name":"Heyvaert A",
    "wof:placetype":"venue"
},
  "geometry": {"coordinates":[4.5341391563,50.7376899719],"type":"Point"}
}