{
  "type": "Feature",
  "properties": {
    "addr:full":"Avenue De La Basilique 1 P\u00e9ruwelz (bon-secours) Hainaut 7603",
    "addr:housenumber":"1",
    "addr:postcode":"7603",
    "addr:street":"Avenue De La Basilique",
    "iso:country":"BE",
    "sg:address":"Avenue De La Basilique 1",
    "sg:city":"P\u00e9ruwelz (bon-secours)",
    "sg:classifiers":[
        {
            "category":"Shopping",
            "subcategory":"Gifts & Souvenirs",
            "type":"Retail Goods"
        }
    ],
    "sg:phone":"+32 69 77 57 30",
    "sg:postcode":"7603",
    "sg:province":"Hainaut",
    "sg:tags":[
        "-"
    ],
    "wof:name":"Big Cado",
    "wof:placetype":"venue"
},
  "geometry": {"coordinates":[3.6066830158,50.4975242615],"type":"Point"}
}