{
  "type": "Feature",
  "properties": {
    "addr:full":"Les-grands-champs 36 Vielsalm Luxembourg 6690",
    "addr:housenumber":"36",
    "addr:postcode":"6690",
    "addr:street":"Les-Grands-Champs",
    "iso:country":"BE",
    "sg:address":"Les-grands-champs 36",
    "sg:city":"Vielsalm",
    "sg:orig_category":"Boekhandels Kantoormateriaal Krantenwinkels Rookartikelen",
    "sg:phone":"+32 80 21 70 90",
    "sg:postcode":"6690",
    "sg:province":"Luxembourg",
    "wof:name":"Librairie Flammang",
    "wof:placetype":"venue"
},
  "geometry": {"coordinates":[5.9188261032,50.2832870483],"type":"Point"}
}