{
  "type": "Feature",
  "properties": {
    "addr:full":"Gatti De Gamondstraat 222 Ukkel/uccle Bruxelles-Capitale 1180",
    "addr:housenumber":"222",
    "addr:postcode":"1180",
    "addr:street":"Gamondstraat;/",
    "iso:country":"BE",
    "sg:address":"Gatti De Gamondstraat 222",
    "sg:city":"Ukkel/uccle",
    "sg:orig_category":"Boekhouders",
    "sg:phone":"+32 2 376 54 92",
    "sg:postcode":"1180",
    "sg:province":"Bruxelles-Capitale",
    "wof:name":"Etienne Martou",
    "wof:placetype":"venue"
},
  "geometry": {"coordinates":[4.3277168274,50.7987136841],"type":"Point"}
}