{
  "type": "Feature",
  "properties": {
    "addr:full":"Rue Des Sorbiers 18 Auvelais Namur 5060",
    "addr:housenumber":"18",
    "addr:postcode":"5060",
    "addr:street":"Rue Des Sorbiers",
    "iso:country":"BE",
    "sg:address":"Rue Des Sorbiers 18",
    "sg:city":"Auvelais",
    "sg:orig_category":"Huisdierenkwekers",
    "sg:phone":"+32 71 74 08 70",
    "sg:postcode":"5060",
    "sg:province":"Namur",
    "wof:name":"Au Chaton D\u00b4argent",
    "wof:placetype":"venue"
},
  "geometry": {"coordinates":[4.6287641525,50.4418106079],"type":"Point"}
}