{
  "type": "Feature",
  "properties": {
    "addr:full":"Kapelainlaan 18b3 Temse Oost-Vlaanderen 9140",
    "addr:housenumber":"18b3",
    "addr:postcode":"9140",
    "addr:street":"Kapelainlaan",
    "iso:country":"BE",
    "sg:address":"Kapelainlaan 18b3",
    "sg:city":"Temse",
    "sg:orig_category":"Bouwwerktuigen Gh Verhuur bouwmachines",
    "sg:phone":"+32 3 771 63 59",
    "sg:postcode":"9140",
    "sg:province":"Oost-Vlaanderen",
    "wof:name":"S.g.b.",
    "wof:placetype":"venue"
},
  "geometry": {"coordinates":[4.179210186,51.1396064758],"type":"Point"}
}