{
  "type": "Feature",
  "properties": {
    "iso:country":"BE",
    "sg:address":"Karel Suykensstraat 75",
    "sg:city":"Bornem (hingene)",
    "sg:classifiers":[
        {
            "category":"Autos & Motor Vehicles",
            "subcategory":"Fuel & Gas Station",
            "type":"Retail Goods"
        }
    ],
    "sg:phone":"+32 3 889 10 63",
    "sg:postcode":"2880",
    "sg:province":"Antwerpen",
    "wof:name":"Spiessens-bruylants",
    "wof:placetype":"venue"
},
  "geometry": {"coordinates":[4.242205143,51.0998497009],"type":"Point"}
}