{
  "type": "Feature",
  "properties": {
    "iso:country":"BE",
    "sg:address":"Av. Dieudonn\u00c9 Lambrecht 29",
    "sg:city":"Li\u00c8ge",
    "sg:orig_category":"Boekhouders",
    "sg:phone":"+32 4 227 81 18",
    "sg:postcode":"4000",
    "sg:province":"Li\u00e8ge",
    "wof:name":"Roger Burnay",
    "wof:placetype":"venue"
},
  "geometry": {"coordinates":[5.5931978226,50.6627960205],"type":"Point"}
}