{
  "type": "Feature",
  "properties": {
    "iso:country":"BE",
    "sg:address":"Mevrouw Courtmanslaan 80",
    "sg:city":"Maldegem",
    "sg:orig_category":"Enseignement maternel and primaire",
    "sg:phone":"+32 50 71 90 57",
    "sg:postcode":"9990",
    "sg:province":"Oost-Vlaanderen",
    "wof:name":"Basisschool",
    "wof:placetype":"venue"
},
  "geometry": {"coordinates":[3.4504749775,51.2086448669],"type":"Point"}
}