{
  "type": "Feature",
  "properties": {
    "iso:country":"BE",
    "sg:address":"Rue Des Cailloux 7",
    "sg:city":"Rixensart",
    "sg:classifiers":[
        {
            "category":"Parking",
            "subcategory":"Bicycle",
            "type":"Transportation"
        }
    ],
    "sg:phone":"+32 2 384 61 36",
    "sg:postcode":"1330",
    "sg:province":"Brabant Wallon",
    "sg:tags":[
        "chiropodist"
    ],
    "wof:name":"Dujardin S",
    "wof:placetype":"venue"
},
  "geometry": {"coordinates":[4.5107741356,50.7099227905],"type":"Point"}
}