{
  "type": "Feature",
  "properties": {
    "addr:full":"Krijgslaan 11 Gavere Oost-Vlaanderen 9890",
    "addr:housenumber":"11",
    "addr:postcode":"9890",
    "addr:street":"Krijgslaan",
    "iso:country":"BE",
    "sg:address":"Krijgslaan 11",
    "sg:city":"Gavere",
    "sg:classifiers":[
        {
            "category":"Insurance",
            "subcategory":"Insurance Agent",
            "type":"Services"
        }
    ],
    "sg:phone":"+32 9 384 51 07",
    "sg:postcode":"9890",
    "sg:province":"Oost-Vlaanderen",
    "sg:tags":[
        "verzekeringsmakelaars",
        "expert"
    ],
    "wof:name":"D. Peire",
    "wof:placetype":"venue"
},
  "geometry": {"coordinates":[3.6686239243,50.9237060547],"type":"Point"}
}