{
  "type": "Feature",
  "properties": {
    "addr:full":"Stationsstraat 41-43 Ieper West-Vlaanderen 8900",
    "addr:housenumber":"41-43",
    "addr:postcode":"8900",
    "addr:street":"Stationsstraat",
    "iso:country":"BE",
    "sg:address":"Stationsstraat 41-43",
    "sg:city":"Ieper",
    "sg:classifiers":[
        {
            "category":"Utilities",
            "subcategory":"Mobile Phone",
            "type":"Services"
        }
    ],
    "sg:phone":"+32 57 21 30 64",
    "sg:postcode":"8900",
    "sg:province":"West-Vlaanderen",
    "sg:tags":[
        "access",
        "gsm",
        "-",
        "apparatus"
    ],
    "wof:name":"Db-tronic",
    "wof:placetype":"venue"
},
  "geometry": {"coordinates":[2.8796908855,50.8486595154],"type":"Point"}
}