{
  "type": "Feature",
  "properties": {
    "addr:full":"Regentiestraat 29 Sint-niklaas Oost-Vlaanderen 9100",
    "addr:housenumber":"29",
    "addr:postcode":"9100",
    "addr:street":"Regentiestraat",
    "iso:country":"BE",
    "sg:address":"Regentiestraat 29",
    "sg:city":"Sint-niklaas",
    "sg:classifiers":[
        {
            "category":"Education",
            "subcategory":"Dance Studio",
            "type":"Public Place"
        }
    ],
    "sg:phone":"+32 3 272 36 60",
    "sg:postcode":"9100",
    "sg:province":"Oost-Vlaanderen",
    "sg:tags":[
        "ballet",
        "school"
    ],
    "wof:name":"Laffont Du Toit",
    "wof:placetype":"venue"
},
  "geometry": {"coordinates":[4.1427621841,51.1684875488],"type":"Point"}
}