{
  "type": "Feature",
  "properties": {
    "iso:country":"BE",
    "sg:address":"Square Du Castel Fleuri 16",
    "sg:city":"Watermaal-bosvoorde/watermael-",
    "sg:orig_category":"Boekhouders",
    "sg:phone":"+32 2 672 05 85",
    "sg:postcode":"1170",
    "sg:province":"Bruxelles-Capitale",
    "wof:name":"Harmegnies Philippe",
    "wof:placetype":"venue"
},
  "geometry": {"coordinates":[4.4140820503,50.7981529236],"type":"Point"}
}