{
  "type": "Feature",
  "properties": {
    "addr:full":"Beringenbaan 53 Diest (schaffen) Vlaams-Brabant 3290",
    "addr:housenumber":"53",
    "addr:postcode":"3290",
    "addr:street":"Beringenbaan",
    "iso:country":"BE",
    "sg:address":"Beringenbaan 53",
    "sg:city":"Diest (schaffen)",
    "sg:classifiers":[
        {
            "category":"Social Services",
            "subcategory":"Job Training",
            "type":"Services"
        }
    ],
    "sg:phone":"+32 13 35 10 80",
    "sg:postcode":"3290",
    "sg:province":"Vlaams-Brabant",
    "sg:tags":[
        "coordinator",
        "safety"
    ],
    "wof:name":"Gorremans Engineering Nv",
    "wof:placetype":"venue"
},
  "geometry": {"coordinates":[5.1506748199,51.0259399414],"type":"Point"}
}