{
  "type": "Feature",
  "properties": {
    "iso:country":"BE",
    "sg:address":"Schansstraat 23a",
    "sg:city":"Halen",
    "sg:orig_category":"Jardinage",
    "sg:phone":"+32 13 44 33 55",
    "sg:postcode":"3545",
    "sg:province":"Limburg",
    "wof:name":"Brems D.",
    "wof:placetype":"venue"
},
  "geometry": {"coordinates":[5.1090598106,50.9753265381],"type":"Point"}
}