{
  "type": "Feature",
  "properties": {
    "iso:country":"BE",
    "sg:address":"Stationsstraat 119",
    "sg:city":"Lommel",
    "sg:orig_category":"Banken and kredietinstellingen",
    "sg:phone":"+32 11 54 11 88",
    "sg:postcode":"3920",
    "sg:province":"Limburg",
    "wof:name":"Citibank",
    "wof:placetype":"venue"
},
  "geometry": {"coordinates":[5.3141222,51.2226371765],"type":"Point"}
}