{
  "type": "Feature",
  "properties": {
    "addr:full":"Av. Des Paquerettes 55 Braine-le-chateau Brabant Wallon 1410",
    "addr:housenumber":"55",
    "addr:postcode":"1410",
    "addr:street":"Av. Des Paquerettes;Brabant Wallon",
    "iso:country":"BE",
    "sg:address":"Av. Des Paquerettes 55",
    "sg:city":"Braine-le-chateau",
    "sg:classifiers":[
        {
            "category":"Fast Food",
            "type":"Food & Drink"
        }
    ],
    "sg:phone":"+32 71 74 23 25",
    "sg:postcode":"1410",
    "sg:province":"Brabant Wallon",
    "sg:tags":[
        "meeneem",
        "restaurant"
    ],
    "wof:name":"Friterie",
    "wof:placetype":"venue"
},
  "geometry": {"coordinates":[23.8774108887,47.1442298889],"type":"Point"}
}