{
  "type": "Feature",
  "properties": {
    "addr:full":"Waterloos 34 Geraardsbergen Oost-Vlaanderen 9500",
    "addr:housenumber":"34",
    "addr:postcode":"9500",
    "addr:street":"Waterloos",
    "iso:country":"BE",
    "sg:address":"Waterloos 34",
    "sg:city":"Geraardsbergen",
    "sg:orig_category":"Maatkleding Fab",
    "sg:phone":"+32 54 50 18 88",
    "sg:postcode":"9500",
    "sg:province":"Oost-Vlaanderen",
    "wof:name":"Diane De Turck",
    "wof:placetype":"venue"
},
  "geometry": {"coordinates":[3.8843801022,50.7716445923],"type":"Point"}
}