{
  "type": "Feature",
  "properties": {
    "iso:country":"BE",
    "sg:address":"Moerkerkse Steenweg 137",
    "sg:city":"Brugge",
    "sg:orig_category":"Instituts de beaut\u00e9",
    "sg:phone":"+32 50 35 75 86",
    "sg:postcode":"8310",
    "sg:province":"West-Vlaanderen",
    "wof:name":"Martine De Pretre",
    "wof:placetype":"venue"
},
  "geometry": {"coordinates":[3.2477369308,51.2135162354],"type":"Point"}
}