{
  "type": "Feature",
  "properties": {
    "iso:country":"BE",
    "sg:address":"Rue De Chamb\u00c9ry 9",
    "sg:city":"Brussel-etterbeek",
    "sg:orig_category":"Travaux de finition and nettoyage de b\u00e2timents. Rev\u00eatements pour sols and murs. Peinture",
    "sg:phone":"+32 2 646 85 84",
    "sg:postcode":"1040",
    "sg:province":"Bruxelles-Capitale",
    "wof:name":"L'aurore",
    "wof:placetype":"venue"
},
  "geometry": {"coordinates":[4.3867988586,50.8312644958],"type":"Point"}
}