{
  "type": "Feature",
  "properties": {
    "addr:full":"Rue De Gilly 164 Charleroi Hainaut 6010",
    "addr:housenumber":"164",
    "addr:postcode":"6010",
    "addr:street":"Rue De Gilly;Hainaut",
    "iso:country":"BE",
    "sg:address":"Rue De Gilly 164",
    "sg:city":"Charleroi",
    "sg:orig_category":"Supermarch\u00e9s",
    "sg:phone":"+32 71 47 83 50",
    "sg:postcode":"6010",
    "sg:province":"Hainaut",
    "wof:name":"Battard",
    "wof:placetype":"venue"
},
  "geometry": {"coordinates":[4.4677200317,50.3921051025],"type":"Point"}
}