{
  "type": "Feature",
  "properties": {
    "addr:full":"Rue Du Gros-gland 14 Li\u00e8ge 1 Li\u00e8ge 4000",
    "addr:housenumber":"14;1",
    "addr:postcode":"4000",
    "addr:street":"Rue Du Gros-Gland",
    "iso:country":"BE",
    "sg:address":"Rue Du Gros-gland 14",
    "sg:city":"Li\u00e8ge 1",
    "sg:classifiers":[
        {
            "category":"Health Services",
            "subcategory":"Health Practitioner",
            "type":"Services"
        }
    ],
    "sg:phone":"+32 4 252 54 67",
    "sg:postcode":"4000",
    "sg:province":"Li\u00e8ge",
    "sg:tags":[
        "physiotherapist"
    ],
    "wof:name":"Degey Christelle",
    "wof:placetype":"venue"
},
  "geometry": {"coordinates":[5.5524001122,50.6185379028],"type":"Point"}
}