{
  "type": "Feature",
  "properties": {
    "iso:country":"BE",
    "sg:address":"Rue Pierre Van Dyck 49",
    "sg:city":"La Hulpe",
    "sg:classifiers":[
        {
            "category":"Home & Garden",
            "subcategory":"Home Furnishings",
            "type":"Retail Goods"
        }
    ],
    "sg:phone":"+32 2 652 37 70",
    "sg:postcode":"1310",
    "sg:province":"Brabant Wallon",
    "sg:tags":[
        "interior",
        "decoration"
    ],
    "wof:name":"Pierlot C",
    "wof:placetype":"venue"
},
  "geometry": {"coordinates":[4.5005397797,50.7539138794],"type":"Point"}
}