{
  "type": "Feature",
  "properties": {
    "addr:full":"Rue Petite Chenevi\u00e8re 127 Charleroi (marcinelle) Hainaut 6001",
    "addr:housenumber":"127",
    "addr:postcode":"6001",
    "addr:street":"Rue Petite Chenevie\u0300Re",
    "iso:country":"BE",
    "sg:address":"Rue Petite Chenevi\u00e8re 127",
    "sg:city":"Charleroi (marcinelle)",
    "sg:classifiers":[
        {
            "category":"Health Services",
            "subcategory":"Medical Lab",
            "type":"Services"
        }
    ],
    "sg:phone":"+32 71 36 91 66",
    "sg:postcode":"6001",
    "sg:province":"Hainaut",
    "sg:tags":[
        "laboratory",
        "dental"
    ],
    "wof:name":"Legros M",
    "wof:placetype":"venue"
},
  "geometry": {"coordinates":[4.4413208961,50.3867950439],"type":"Point"}
}