{
  "type": "Feature",
  "properties": {
    "iso:country":"BE",
    "sg:address":"Rue Nishaye 32",
    "sg:city":"Welkenraedt (henri-chapelle)",
    "sg:classifiers":[
        {
            "category":"Insurance",
            "subcategory":"Insurance Agent",
            "type":"Services"
        }
    ],
    "sg:phone":"+32 87 88 07 88",
    "sg:postcode":"4841",
    "sg:province":"Li\u00e8ge",
    "sg:tags":[
        "broker"
    ],
    "wof:name":"Michel-pirotte Sprl",
    "wof:placetype":"venue"
},
  "geometry": {"coordinates":[5.9336218834,50.6766967773],"type":"Point"}
}