{
  "type": "Feature",
  "properties": {
    "iso:country":"BE",
    "sg:address":"Rue Pisseroule 133",
    "sg:city":"Dison",
    "sg:classifiers":[
        {
            "category":"Building & Trades",
            "subcategory":"Electrical",
            "type":"Services"
        }
    ],
    "sg:phone":"+32 87 33 55 28",
    "sg:postcode":"4820",
    "sg:province":"Li\u00e8ge",
    "sg:tags":[
        "electric",
        "-",
        "housewiring",
        "contractor"
    ],
    "wof:name":"Farnir Georges Sprl",
    "wof:placetype":"venue"
},
  "geometry": {"coordinates":[5.8545742035,50.6028060913],"type":"Point"}
}