{
  "type": "Feature",
  "properties": {
    "addr:full":"Meulebekestraat 29 A Ingelmunster West-Vlaanderen 8770",
    "addr:housenumber":"29 a",
    "addr:postcode":"8770",
    "addr:street":"Meulebekestraat",
    "iso:country":"BE",
    "sg:address":"Meulebekestraat 29 A",
    "sg:city":"Ingelmunster",
    "sg:orig_category":"Jardinage",
    "sg:phone":"+32 51 31 40 35",
    "sg:postcode":"8770",
    "sg:province":"West-Vlaanderen",
    "wof:name":"Sabbe T",
    "wof:placetype":"venue"
},
  "geometry": {"coordinates":[3.259665966,50.9266891479],"type":"Point"}
}