{
  "type": "Feature",
  "properties": {
    "addr:full":"Geerstraat 32b2 Hechtel-eksel Limburg 3941",
    "addr:housenumber":"32b2",
    "addr:postcode":"3941",
    "addr:street":"Geerstraat",
    "iso:country":"BE",
    "sg:address":"Geerstraat 32b2",
    "sg:city":"Hechtel-eksel",
    "sg:orig_category":"Agences d'exp\u00e9dition",
    "sg:phone":"+32 11 73 23 41",
    "sg:postcode":"3941",
    "sg:province":"Limburg",
    "wof:name":"Transport Essers H. & Zn",
    "wof:placetype":"venue"
},
  "geometry": {"coordinates":[5.3958511353,51.1584587097],"type":"Point"}
}