{
  "type": "Feature",
  "properties": {
    "iso:country":"BE",
    "sg:address":"Slachthuisstraat 10",
    "sg:city":"Ieper",
    "sg:orig_category":"Kapsalons",
    "sg:phone":"+32 57 20 94 82",
    "sg:postcode":"8900",
    "sg:province":"West-Vlaanderen",
    "wof:name":"Coiffure Ilse",
    "wof:placetype":"venue"
},
  "geometry": {"coordinates":[2.8854389191,50.854549408],"type":"Point"}
}