{
  "type": "Feature",
  "properties": {
    "addr:full":"Processiestraat 24 Gooik Vlaams-Brabant 1755",
    "addr:housenumber":"24",
    "addr:postcode":"1755",
    "addr:street":"Processiestraat",
    "iso:country":"BE",
    "sg:address":"Processiestraat 24",
    "sg:city":"Gooik",
    "sg:classifiers":[
        {
            "category":"Insurance",
            "subcategory":"Life Insurance",
            "type":"Services"
        }
    ],
    "sg:phone":"+32 54 56 71 71",
    "sg:postcode":"1755",
    "sg:province":"Vlaams-Brabant",
    "sg:tags":[
        "assurance"
    ],
    "wof:name":"Verzekering Beeckmans",
    "wof:placetype":"venue"
},
  "geometry": {"coordinates":[4.0883722305,50.7882995605],"type":"Point"}
}