{
  "type": "Feature",
  "properties": {
    "iso:country":"BE",
    "sg:address":"Wondelgemstraat 70",
    "sg:city":"Gent",
    "sg:classifiers":[
        {
            "category":"Shopping",
            "subcategory":"Jewelry",
            "type":"Retail Goods"
        }
    ],
    "sg:phone":"+32 9 225 54 05",
    "sg:postcode":"9000",
    "sg:province":"Oost-Vlaanderen",
    "sg:tags":[
        "jeweller",
        "-"
    ],
    "wof:name":"Strobbe P",
    "wof:placetype":"venue"
},
  "geometry": {"coordinates":[3.7103009224,51.062297821],"type":"Point"}
}