{
  "type": "Feature",
  "properties": {
    "iso:country":"BE",
    "sg:address":"Quai Marcellis 17",
    "sg:city":"Li\u00e8ge 1 (li\u00e8ge 2)",
    "sg:classifiers":[
        {
            "category":"Professional",
            "subcategory":"Lawyer & Legal Services",
            "type":"Services"
        }
    ],
    "sg:phone":"+32 4 221 36 32",
    "sg:postcode":"4020",
    "sg:province":"Li\u00e8ge",
    "wof:name":"Roumans Marie France",
    "wof:placetype":"venue"
},
  "geometry": {"coordinates":[5.5753998756,50.6348190308],"type":"Point"}
}