{
  "type": "Feature",
  "properties": {
    "addr:full":"Rue Mitoyenne 1 Baelen Li\u00e8ge 4837",
    "addr:housenumber":"1",
    "addr:postcode":"4837",
    "addr:street":"Rue Mitoyenne",
    "iso:country":"BE",
    "sg:address":"Rue Mitoyenne 1",
    "sg:city":"Baelen",
    "sg:orig_category":"Rev\u00eatements de sols and murs. Articles de jardin",
    "sg:phone":"+32 87 89 04 04",
    "sg:postcode":"4837",
    "sg:province":"Li\u00e8ge",
    "wof:name":"Kwantum",
    "wof:placetype":"venue"
},
  "geometry": {"coordinates":[6.0075678825,50.6448860168],"type":"Point"}
}