{
  "type": "Feature",
  "properties": {
    "addr:full":"Tieltsesteenweg 191 Eeklo Oost-Vlaanderen 9900",
    "addr:housenumber":"191",
    "addr:postcode":"9900",
    "addr:street":"Tieltsesteenweg",
    "iso:country":"BE",
    "sg:address":"Tieltsesteenweg 191",
    "sg:city":"Eeklo",
    "sg:classifiers":[
        {
            "category":"Utilities",
            "subcategory":"Fuel Oil & Lpg",
            "type":"Services"
        }
    ],
    "sg:phone":"+32 9 377 63 35",
    "sg:postcode":"9900",
    "sg:province":"Oost-Vlaanderen",
    "wof:name":"Penny's Oil",
    "wof:placetype":"venue"
},
  "geometry": {"coordinates":[3.5504949093,51.1787528992],"type":"Point"}
}