{
  "type": "Feature",
  "properties": {
    "iso:country":"BE",
    "sg:address":"Brusselsesteenweg 708",
    "sg:city":"Gentbrugge",
    "sg:classifiers":[
        {
            "category":"Government",
            "subcategory":"Office",
            "type":"Public Place"
        }
    ],
    "sg:phone":"+32 9 272 86 09",
    "sg:postcode":"9050",
    "sg:province":"Oost-Vlaanderen",
    "sg:tags":[
        "intranet",
        "cd-rom",
        "integration",
        "internet"
    ],
    "wof:name":"The Independents",
    "wof:placetype":"venue"
},
  "geometry": {"coordinates":[3.768955946,51.0273704529],"type":"Point"}
}