{
  "type": "Feature",
  "properties": {
    "iso:country":"BE",
    "sg:address":"Kreitenborgstraat 1",
    "sg:city":"Mechelen",
    "sg:orig_category":"Diverse grafische activiteiten",
    "sg:phone":"+32 15 20 42 17",
    "sg:postcode":"2800",
    "sg:province":"Antwerpen",
    "wof:name":"Diane Voet",
    "wof:placetype":"venue"
},
  "geometry": {"coordinates":[4.463809967,51.0415763855],"type":"Point"}
}