{
  "type": "Feature",
  "properties": {
    "addr:full":"Chauss\u00e9e De Louvain 531 Bruxelles (schaerbeek) Bruxelles-Capitale 1030",
    "addr:housenumber":"531",
    "addr:postcode":"1030",
    "addr:street":"Chausse\u0301E De Louvain",
    "iso:country":"BE",
    "sg:address":"Chauss\u00e9e De Louvain 531",
    "sg:city":"Bruxelles (schaerbeek)",
    "sg:classifiers":[
        {
            "category":"Shopping",
            "subcategory":"Crafts & Fabrics",
            "type":"Retail Goods"
        }
    ],
    "sg:phone":"+32 2 705 41 37",
    "sg:postcode":"1030",
    "sg:province":"Bruxelles-Capitale",
    "sg:tags":[
        "pleating",
        "embroidery"
    ],
    "wof:name":"Euro Brode",
    "wof:placetype":"venue"
},
  "geometry": {"coordinates":[4.3999128342,50.8555679321],"type":"Point"}
}