{
  "type": "Feature",
  "properties": {
    "iso:country":"BE",
    "sg:address":"Rue No\u00ebl Ulysse 1",
    "sg:city":"Marche-en-famenne (on)",
    "sg:classifiers":[
        {
            "category":"Building & Trades",
            "subcategory":"Construction",
            "type":"Services"
        }
    ],
    "sg:phone":"+32 84 21 43 22",
    "sg:postcode":"6900",
    "sg:province":"Luxembourg",
    "sg:tags":[
        "asphalt",
        "contractor"
    ],
    "wof:name":"Dumortier Alexandre",
    "wof:placetype":"venue"
},
  "geometry": {"coordinates":[5.2875161171,50.1742553711],"type":"Point"}
}