{
  "type": "Feature",
  "properties": {
    "addr:full":"Alsembergsesteenweg 151 Linkebeek Vlaams-Brabant 1630",
    "addr:housenumber":"151",
    "addr:postcode":"1630",
    "addr:street":"Alsembergsesteenweg",
    "iso:country":"BE",
    "sg:address":"Alsembergsesteenweg 151",
    "sg:city":"Linkebeek",
    "sg:orig_category":"Installatie van houten of kunststof schrijnwerk",
    "sg:phone":"+32 2 381 33 34",
    "sg:postcode":"1630",
    "sg:province":"Vlaams-Brabant",
    "wof:name":"Fe. Kirchner & Partners",
    "wof:placetype":"venue"
},
  "geometry": {"coordinates":[4.3285651207,50.7686080933],"type":"Point"}
}