{
  "type": "Feature",
  "properties": {
    "iso:country":"BE",
    "sg:address":"Keizer Karellaan 131",
    "sg:city":"Sint-agatha-berchem/berchem-sainte-agathe",
    "sg:orig_category":"Slagers Voedingsspeciaalzaken",
    "sg:phone":"+32 2 465 00 59",
    "sg:postcode":"1082",
    "sg:province":"Bruxelles-Capitale",
    "wof:name":"Andre Bisschop",
    "wof:placetype":"venue"
},
  "geometry": {"coordinates":[4.3098158836,50.8689651489],"type":"Point"}
}