{
  "type": "Feature",
  "properties": {
    "iso:country":"BE",
    "sg:address":"Rue Gontran Bachy 7",
    "sg:city":"Mons",
    "sg:orig_category":"Eleveurs de bovins",
    "sg:phone":"+32 65 33 54 30",
    "sg:postcode":"7032",
    "sg:province":"Hainaut",
    "wof:name":"Pol Deprez",
    "wof:placetype":"venue"
},
  "geometry": {"coordinates":[3.9869709015,50.4255142212],"type":"Point"}
}