{
  "type": "Feature",
  "properties": {
    "iso:country":"BE",
    "sg:address":"Rue Des Roches 6",
    "sg:city":"Blegny",
    "sg:orig_category":"Instituts de beaut\u00e9. M\u00e9decines alternatives",
    "sg:phone":"+32 4 387 52 50",
    "sg:postcode":"4670",
    "sg:province":"Li\u00e8ge",
    "wof:name":"Centre Beaut\u00c9 Jacqueline",
    "wof:placetype":"venue"
},
  "geometry": {"coordinates":[5.7100529671,50.6708908081],"type":"Point"}
}