{
  "type": "Feature",
  "properties": {
    "addr:full":"Rue Royale 46 Tournai Hainaut 7500",
    "addr:housenumber":"46",
    "addr:postcode":"7500",
    "addr:street":"Rue Royale",
    "iso:country":"BE",
    "sg:address":"Rue Royale 46",
    "sg:city":"Tournai",
    "sg:classifiers":[
        {
            "category":"Restaurant",
            "type":"Food & Drink"
        }
    ],
    "sg:phone":"+32 69 22 18 37",
    "sg:postcode":"7500",
    "sg:province":"Hainaut",
    "sg:tags":[
        "caf\u00e9s"
    ],
    "wof:name":"Taverne Royale",
    "wof:placetype":"venue"
},
  "geometry": {"coordinates":[3.3929240704,50.6100082397],"type":"Point"}
}