{
  "type": "Feature",
  "properties": {
    "iso:country":"BE",
    "sg:address":"Rue Du Ham 124 Box 31",
    "sg:city":"Bruxelles (uccle)",
    "sg:classifiers":[
        {
            "category":"Health Services",
            "subcategory":"Health Practitioner",
            "type":"Services"
        }
    ],
    "sg:phone":"+32 56 51 33 83",
    "sg:postcode":"1180",
    "sg:province":"Bruxelles-Capitale",
    "sg:tags":[
        "osteopath"
    ],
    "wof:name":"U.b.o.-b.u.o. (union Belge Des Ostheopathes-belgis",
    "wof:placetype":"venue"
},
  "geometry": {"coordinates":[4.3711781502,50.7903327942],"type":"Point"}
}