{
  "type": "Feature",
  "properties": {
    "iso:country":"BE",
    "sg:address":"Damstraat 52",
    "sg:city":"Vilvoorde",
    "sg:orig_category":"Sportclubs",
    "sg:phone":"+32 2 253 16 80",
    "sg:postcode":"1800",
    "sg:province":"Vlaams-Brabant",
    "wof:name":"B.b.c. Bloks Houtem",
    "wof:placetype":"venue"
},
  "geometry": {"coordinates":[4.4597301483,50.9444198608],"type":"Point"}
}