{
  "type": "Feature",
  "properties": {
    "addr:full":"Astridlaan 229 Overpelt Limburg 3900",
    "addr:housenumber":"229",
    "addr:postcode":"3900",
    "addr:street":"Astridlaan",
    "iso:country":"BE",
    "sg:address":"Astridlaan 229",
    "sg:city":"Overpelt",
    "sg:classifiers":[
        {
            "category":"Personal",
            "subcategory":"Beauty Salon",
            "type":"Services"
        }
    ],
    "sg:phone":"+32 11 66 55 63",
    "sg:postcode":"3900",
    "sg:province":"Limburg",
    "sg:tags":[
        "lady",
        "-",
        "hairdressing"
    ],
    "wof:name":"Capelli",
    "wof:placetype":"venue"
},
  "geometry": {"coordinates":[5.3867540359,51.2129516602],"type":"Point"}
}