{
  "type": "Feature",
  "properties": {
    "iso:country":"BE",
    "sg:address":"Gill\u00c8s De P\u00c9lichylei 107",
    "sg:city":"Schilde",
    "sg:orig_category":"Projectontwikkelaars Woningbouw",
    "sg:phone":"+32 3 680 16 16",
    "sg:postcode":"2970",
    "sg:province":"Antwerpen",
    "wof:name":"Sels G.",
    "wof:placetype":"venue"
},
  "geometry": {"coordinates":[4.5633349419,51.2522201538],"type":"Point"}
}