{
  "type": "Feature",
  "properties": {
    "addr:full":"Steenhouwersvest 9 Antwerpen Antwerpen 2000",
    "addr:housenumber":"9",
    "addr:postcode":"2000",
    "addr:street":"Steenhouwersvest",
    "iso:country":"BE",
    "sg:address":"Steenhouwersvest 9",
    "sg:city":"Antwerpen",
    "sg:orig_category":"Souvenirs and objets artisanaux. Eclairage et \u00e9quipements du foyer",
    "sg:phone":"+32 3 231 56 62",
    "sg:postcode":"2000",
    "sg:province":"Antwerpen",
    "wof:name":"Huis Art Depot",
    "wof:placetype":"venue"
},
  "geometry": {"coordinates":[4.3975148201,51.2182884216],"type":"Point"}
}