{
  "type": "Feature",
  "properties": {
    "addr:full":"Oudebaan 161 Bierbeek Vlaams-Brabant 3360",
    "addr:housenumber":"161",
    "addr:postcode":"3360",
    "addr:street":"Oudebaan",
    "iso:country":"BE",
    "sg:address":"Oudebaan 161",
    "sg:city":"Bierbeek",
    "sg:orig_category":"Artsen and specialisten",
    "sg:phone":"+32 16 46 03 94",
    "sg:postcode":"3360",
    "sg:province":"Vlaams-Brabant",
    "wof:name":"J. Cobbaert",
    "wof:placetype":"venue"
},
  "geometry": {"coordinates":[4.7468738556,50.8626327515],"type":"Point"}
}