{
  "type": "Feature",
  "properties": {
    "iso:country":"BE",
    "sg:address":"Vrijheidsstraat 15",
    "sg:city":"Denderleeuw",
    "sg:classifiers":[
        {
            "category":"Social Services",
            "subcategory":"Child Care",
            "type":"Services"
        }
    ],
    "sg:phone":"+32 53 68 17 25",
    "sg:postcode":"9470",
    "sg:province":"Oost-Vlaanderen",
    "sg:tags":[
        "baby",
        "nursery",
        "day",
        "sitting"
    ],
    "wof:name":"Ravotterke ('t)",
    "wof:placetype":"venue"
},
  "geometry": {"coordinates":[4.0718231201,50.876285553],"type":"Point"}
}