{
  "type": "Feature",
  "properties": {
    "iso:country":"BE",
    "sg:address":"Montenakenweg 46",
    "sg:city":"Sint-truiden",
    "sg:orig_category":"Quincailleries",
    "sg:phone":"+32 11 68 12 58",
    "sg:postcode":"3800",
    "sg:province":"Limburg",
    "wof:name":"Doe Het Zelf Discount",
    "wof:placetype":"venue"
},
  "geometry": {"coordinates":[5.1789398193,50.8131332397],"type":"Point"}
}