{
  "type": "Feature",
  "properties": {
    "iso:country":"BE",
    "sg:address":"Zevenster 12",
    "sg:city":"De Pinte",
    "sg:classifiers":[
        {
            "category":"Insurance",
            "subcategory":"Insurance Agent",
            "type":"Services"
        }
    ],
    "sg:phone":"+32 9 282 76 70",
    "sg:postcode":"9840",
    "sg:province":"Oost-Vlaanderen",
    "sg:tags":[
        "verzekeringsmakelaars",
        "expert"
    ],
    "wof:name":"A. & L. Depaepe",
    "wof:placetype":"venue"
},
  "geometry": {"coordinates":[3.6714880466,50.9937171936],"type":"Point"}
}