{
  "type": "Feature",
  "properties": {
    "iso:country":"BE",
    "sg:address":"Menensesteenweg 8",
    "sg:city":"Wervik",
    "sg:orig_category":"Loodgieterij, verwarming and sanitaire installaties",
    "sg:phone":"+32 56 31 41 87",
    "sg:postcode":"8940",
    "sg:province":"West-Vlaanderen",
    "wof:name":"Debrabandere Hans",
    "wof:placetype":"venue"
},
  "geometry": {"coordinates":[3.0548169613,50.7812385559],"type":"Point"}
}