{
  "type": "Feature",
  "properties": {
    "iso:country":"BE",
    "sg:address":"Mollei 3",
    "sg:city":"Brasschaat",
    "sg:classifiers":[
        {
            "category":"Wholesale",
            "subcategory":"Tobacco Products",
            "type":"Manufacturing & Wholesale Goods"
        }
    ],
    "sg:phone":"+32 3 653 14 10",
    "sg:postcode":"2930",
    "sg:province":"Antwerpen",
    "sg:tags":[
        "import",
        "wood",
        "-"
    ],
    "wof:name":"Hofkens L Nv",
    "wof:placetype":"venue"
},
  "geometry": {"coordinates":[4.4807949066,51.2898178101],"type":"Point"}
}