{
  "type": "Feature",
  "properties": {
    "iso:country":"BE",
    "sg:address":"Peter Benoitstraat 8",
    "sg:city":"Aalst",
    "sg:classifiers":[
        {
            "category":"Professional",
            "subcategory":"Accounting & Tax Preparation",
            "type":"Services"
        }
    ],
    "sg:phone":"+32 53 71 02 79",
    "sg:postcode":"9300",
    "sg:province":"Oost-Vlaanderen",
    "sg:tags":[
        "accountant"
    ],
    "wof:name":"Account + Bvba",
    "wof:placetype":"venue"
},
  "geometry": {"coordinates":[4.03150177,50.9447402954],"type":"Point"}
}