{
  "type": "Feature",
  "properties": {
    "iso:country":"BE",
    "sg:address":"Gentsesteenweg 440",
    "sg:city":"Aalst (groot)",
    "sg:orig_category":"Bruids- and ceremoniekledij Kleding",
    "sg:phone":"+32 53 78 34 45",
    "sg:postcode":"9300",
    "sg:province":"Oost-Vlaanderen",
    "wof:name":"Pierre Yves",
    "wof:placetype":"venue"
},
  "geometry": {"coordinates":[4.0032939911,50.9412231445],"type":"Point"}
}