{
  "type": "Feature",
  "properties": {
    "addr:full":"Leopold Iii-laan 9b4 Schaarbeek/schaerbeek Bruxelles-Capitale 1030",
    "addr:housenumber":"9b4",
    "addr:postcode":"1030",
    "addr:street":"Leopold Iii-Laan",
    "iso:country":"BE",
    "sg:address":"Leopold Iii-laan 9b4",
    "sg:city":"Schaarbeek/schaerbeek",
    "sg:orig_category":"Rookartikelen",
    "sg:phone":"+32 2 216 05 05",
    "sg:postcode":"1030",
    "sg:province":"Bruxelles-Capitale",
    "wof:name":"Romanus Dops",
    "wof:placetype":"venue"
},
  "geometry": {"coordinates":[4.3984618187,50.8574409485],"type":"Point"}
}