{
  "type": "Feature",
  "properties": {
    "addr:full":"Voie Cardijn 8 Louvain-la-neuve Brabant Wallon 1348",
    "addr:housenumber":"8",
    "addr:postcode":"1348",
    "addr:street":"Voie Cardijn",
    "iso:country":"BE",
    "sg:address":"Voie Cardijn 8",
    "sg:city":"Louvain-la-neuve",
    "sg:classifiers":[
        {
            "category":"Shopping Center",
            "type":"Public Place"
        }
    ],
    "sg:phone":"+32 10 45 10 44",
    "sg:postcode":"1348",
    "sg:province":"Brabant Wallon",
    "sg:tags":[
        "enseignement",
        "formation"
    ],
    "wof:name":"Cll Centres De Langues",
    "wof:placetype":"venue"
},
  "geometry": {"coordinates":[4.6097550392,50.6707420349],"type":"Point"}
}