{
  "type": "Feature",
  "properties": {
    "iso:country":"BE",
    "sg:address":"Bahnhofstrasse 25a",
    "sg:city":"B\u00fctgenbach",
    "sg:classifiers":[
        {
            "category":"Building & Trades",
            "subcategory":"Electrical",
            "type":"Services"
        }
    ],
    "sg:phone":"+32 80 44 42 60",
    "sg:postcode":"4750",
    "sg:province":"Li\u00e8ge",
    "sg:tags":[
        "electric",
        "-",
        "housewiring",
        "contractor"
    ],
    "wof:name":"Comoth-wolff B",
    "wof:placetype":"venue"
},
  "geometry": {"coordinates":[6.1664237976,50.4298248291],"type":"Point"}
}