{
  "type": "Feature",
  "properties": {
    "iso:country":"BE",
    "sg:address":"Amsterdamstraat 26",
    "sg:city":"Hoogstraten (meer)",
    "sg:classifiers":[
        {
            "category":"Professional",
            "type":"Services"
        }
    ],
    "sg:phone":"+32 3 317 01 20",
    "sg:postcode":"2321",
    "sg:province":"Antwerpen",
    "sg:tags":[
        "forwarding",
        "agency"
    ],
    "wof:name":"Optiflex Bvba",
    "wof:placetype":"venue"
},
  "geometry": {"coordinates":[4.7366099358,51.442325592],"type":"Point"}
}