{
  "type": "Feature",
  "properties": {
    "iso:country":"BE",
    "sg:address":"Rue Saint-martin 28bb",
    "sg:city":"Tournai",
    "sg:orig_category":"Artistes ind\u00e9pendants",
    "sg:phone":"+32 69 21 10 73",
    "sg:postcode":"7500",
    "sg:province":"Hainaut",
    "wof:name":"Guy Colombien",
    "wof:placetype":"venue"
},
  "geometry": {"coordinates":[3.3938798904,50.5897941589],"type":"Point"}
}