{
  "type": "Feature",
  "properties": {
    "addr:full":"Stationsstraat 127 Beernem West-Vlaanderen 8730",
    "addr:housenumber":"127",
    "addr:postcode":"8730",
    "addr:street":"Stationsstraat",
    "iso:country":"BE",
    "sg:address":"Stationsstraat 127",
    "sg:city":"Beernem",
    "sg:classifiers":[
        {
            "category":"Social Services",
            "type":"Services"
        }
    ],
    "sg:phone":"+32 50 78 16 66",
    "sg:postcode":"8730",
    "sg:province":"West-Vlaanderen",
    "wof:name":"Klus (de)",
    "wof:placetype":"venue"
},
  "geometry": {"coordinates":[3.330509901,51.1297988892],"type":"Point"}
}