{
  "type": "Feature",
  "properties": {
    "iso:country":"BE",
    "sg:address":"Kwadestraat 99",
    "sg:city":"Wevelgem",
    "sg:orig_category":"HUISBRANDOLIE Loodgieterij, verwarming and sanitaire installaties",
    "sg:phone":"+32 56 42 22 70",
    "sg:postcode":"8560",
    "sg:province":"West-Vlaanderen",
    "wof:name":"Ignace Stove",
    "wof:placetype":"venue"
},
  "geometry": {"coordinates":[3.2047009468,50.8510513306],"type":"Point"}
}