{
  "type": "Feature",
  "properties": {
    "addr:full":"Route De Beaumont 28 Lasne (lasne-chapelle-saint-lambert) Brabant Wallon 1380",
    "addr:housenumber":"28",
    "addr:postcode":"1380",
    "addr:street":"Route De Beaumont;Wallon",
    "iso:country":"BE",
    "sg:address":"Route De Beaumont 28",
    "sg:city":"Lasne (lasne-chapelle-saint-lambert)",
    "sg:classifiers":[
        {
            "category":"Structure",
            "subcategory":"Office Building",
            "type":"Public Place"
        }
    ],
    "sg:phone":"+32 2 633 32 90",
    "sg:postcode":"1380",
    "sg:province":"Brabant Wallon",
    "sg:tags":[
        "drawing"
    ],
    "wof:name":"Feuillat Ch",
    "wof:placetype":"venue"
},
  "geometry": {"coordinates":[4.493584156,50.6766319275],"type":"Point"}
}