{
  "type": "Feature",
  "properties": {
    "iso:country":"BE",
    "sg:address":"Stationsstraat 8",
    "sg:city":"Zaventem",
    "sg:orig_category":"Werk and personeelsselectie",
    "sg:phone":"+32 2 721 50 82",
    "sg:postcode":"1930",
    "sg:province":"Vlaams-Brabant",
    "wof:name":"Pwa Zaventem",
    "wof:placetype":"venue"
},
  "geometry": {"coordinates":[4.4728498459,50.8804626465],"type":"Point"}
}