{
  "type": "Feature",
  "properties": {
    "iso:country":"BE",
    "sg:address":"Rue Jean Stas 19",
    "sg:city":"Bruxelles (saint-gilles)",
    "sg:classifiers":[
        {
            "category":"Shopping",
            "subcategory":"Crafts & Fabrics",
            "type":"Retail Goods"
        }
    ],
    "sg:phone":"+32 2 534 38 33",
    "sg:postcode":"1060",
    "sg:province":"Bruxelles-Capitale",
    "sg:tags":[
        "silk",
        "-"
    ],
    "wof:name":"Serica Sprl",
    "wof:placetype":"venue"
},
  "geometry": {"coordinates":[4.355424881,50.8340568542],"type":"Point"}
}