{
  "type": "Feature",
  "properties": {
    "iso:country":"BE",
    "sg:address":"Vlasbloemstraat 7",
    "sg:city":"Waregem",
    "sg:classifiers":[
        {
            "category":"Airport",
            "subcategory":"International",
            "type":"Transportation"
        }
    ],
    "sg:phone":"+32 56 61 20 08",
    "sg:postcode":"8790",
    "sg:province":"West-Vlaanderen",
    "sg:tags":[
        "-",
        "transport"
    ],
    "wof:name":"Claeys R",
    "wof:placetype":"venue"
},
  "geometry": {"coordinates":[3.4175679684,50.8778419495],"type":"Point"}
}