{
  "type": "Feature",
  "properties": {
    "iso:country":"BE",
    "sg:address":"Maastrichterstraat 48",
    "sg:city":"Tongeren",
    "sg:orig_category":"Vedior. Agences d\u00b4interim and personnel temporaire",
    "sg:phone":"+32 12 39 83 20",
    "sg:postcode":"3700",
    "sg:province":"Limburg",
    "wof:name":"Vedior Interim",
    "wof:placetype":"venue"
},
  "geometry": {"coordinates":[5.4660010338,50.7822532654],"type":"Point"}
}