{
  "type": "Feature",
  "properties": {
    "iso:country":"BE",
    "sg:address":"Rue De Villers 2",
    "sg:city":"Crisn\u00e9e",
    "sg:classifiers":[
        {
            "category":"Shopping",
            "subcategory":"Shoes",
            "type":"Retail Goods"
        }
    ],
    "sg:phone":"+32 4 257 41 23",
    "sg:postcode":"4367",
    "sg:province":"Li\u00e8ge",
    "sg:tags":[
        "slipper",
        "-"
    ],
    "wof:name":"Devivier M",
    "wof:placetype":"venue"
},
  "geometry": {"coordinates":[5.4069418907,50.69713974],"type":"Point"}
}