{
  "type": "Feature",
  "properties": {
    "addr:full":"Zandstraat 13 Duffel Antwerpen 2570",
    "addr:housenumber":"13",
    "addr:postcode":"2570",
    "addr:street":"Zandstraat",
    "iso:country":"BE",
    "sg:address":"Zandstraat 13",
    "sg:city":"Duffel",
    "sg:orig_category":"Herstellingen and onderhoud van auto's Voertuigen",
    "sg:phone":"+32 15 31 50 35",
    "sg:postcode":"2570",
    "sg:province":"Antwerpen",
    "wof:name":"Paul Somers",
    "wof:placetype":"venue"
},
  "geometry": {"coordinates":[4.487030983,51.0766220093],"type":"Point"}
}