{
  "type": "Feature",
  "properties": {
    "addr:full":"Chauss\u00e9e De Wavre 79 Gembloux-sur-orneau (gembloux) Namur 5030",
    "addr:housenumber":"79",
    "addr:postcode":"5030",
    "addr:street":"Chausse\u0301E De Wavre;Namur",
    "iso:country":"BE",
    "sg:address":"Chauss\u00e9e De Wavre 79",
    "sg:city":"Gembloux-sur-orneau (gembloux)",
    "sg:classifiers":[
        {
            "category":"Building & Trades",
            "subcategory":"Construction",
            "type":"Services"
        }
    ],
    "sg:phone":"+32 81 61 02 13",
    "sg:postcode":"5030",
    "sg:province":"Namur",
    "sg:tags":[
        "carpenter"
    ],
    "wof:name":"Dyle (la) Sprl",
    "wof:placetype":"venue"
},
  "geometry": {"coordinates":[4.6890788078,50.5762672424],"type":"Point"}
}