{
  "type": "Feature",
  "properties": {
    "addr:full":"Rue Z. Fontaine 76 Binche Hainaut 7130",
    "addr:housenumber":"76",
    "addr:postcode":"7130",
    "addr:street":"Rue Z. Fontaine",
    "iso:country":"BE",
    "sg:address":"Rue Z. Fontaine 76",
    "sg:city":"Binche",
    "sg:orig_category":"HERSTELLING ELEKTRISCHE HUISHOUDAPPARATEN Huishoudapparaten, televisies and radio's Telecommunicatie",
    "sg:phone":"+32 64 33 21 32",
    "sg:postcode":"7130",
    "sg:province":"Hainaut",
    "wof:name":"Eldi",
    "wof:placetype":"venue"
},
  "geometry": {"coordinates":[4.1660728455,50.412311554],"type":"Point"}
}