{
  "type": "Feature",
  "properties": {
    "iso:country":"BE",
    "sg:address":"Gebuurweg 11",
    "sg:city":"Wichelen",
    "sg:orig_category":"Rev\u00eatements de sols and murs. Peinture. Rev\u00eatements pour sols and murs",
    "sg:phone":"+32 52 42 38 69",
    "sg:postcode":"9260",
    "sg:province":"Oost-Vlaanderen",
    "wof:name":"Bauwens",
    "wof:placetype":"venue"
},
  "geometry": {"coordinates":[3.9697759151,51.005531311],"type":"Point"}
}