{
  "type": "Feature",
  "properties": {
    "iso:country":"BE",
    "sg:address":"Rue De Berry 30",
    "sg:city":"Beauraing",
    "sg:classifiers":[
        {
            "category":"Building & Trades",
            "subcategory":"Locksmith",
            "type":"Services"
        }
    ],
    "sg:phone":"+32 82 71 11 53",
    "sg:postcode":"5570",
    "sg:province":"Namur",
    "sg:tags":[
        "lock",
        "key"
    ],
    "wof:name":"Evrard W",
    "wof:placetype":"venue"
},
  "geometry": {"coordinates":[4.9559698105,50.1111183167],"type":"Point"}
}