{
  "type": "Feature",
  "properties": {
    "addr:full":"Rue Des Moges 1 Neupr\u00e9 (rotheux-rimi\u00e8re) Li\u00e8ge 4120",
    "addr:housenumber":"1",
    "addr:postcode":"4120",
    "addr:street":"Rue Des Moges;Rotheux-Rimie\u0300Re",
    "iso:country":"BE",
    "sg:address":"Rue Des Moges 1",
    "sg:city":"Neupr\u00e9 (rotheux-rimi\u00e8re)",
    "sg:classifiers":[
        {
            "category":"Fast Food",
            "type":"Food & Drink"
        }
    ],
    "sg:phone":"+32 4 372 08 00",
    "sg:postcode":"4120",
    "sg:province":"Li\u00e8ge",
    "sg:tags":[
        "fried",
        "stand",
        "potato"
    ],
    "wof:name":"Moges (friterie Des)",
    "wof:placetype":"venue"
},
  "geometry": {"coordinates":[5.4804568291,50.5346031189],"type":"Point"}
}