{
  "type": "Feature",
  "properties": {
    "addr:full":"Kiezelstraat 107 Hasselt Limburg 3500",
    "addr:housenumber":"107",
    "addr:postcode":"3500",
    "addr:street":"Kiezelstraat",
    "iso:country":"BE",
    "sg:address":"Kiezelstraat 107",
    "sg:city":"Hasselt",
    "sg:classifiers":[
        {
            "category":"Education",
            "subcategory":"School",
            "type":"Public Place"
        }
    ],
    "sg:phone":"+32 11 22 46 40",
    "sg:postcode":"3500",
    "sg:province":"Limburg",
    "sg:tags":[
        "-",
        "private"
    ],
    "wof:name":"Remedial Teaching Center",
    "wof:placetype":"venue"
},
  "geometry": {"coordinates":[5.3740749359,50.9294395447],"type":"Point"}
}