{
  "type": "Feature",
  "properties": {
    "addr:full":"Boulevard Du Jubil\u00c9 94 Sint-jans-molenbeek/molenbeek-saint-jean Bruxelles-Capitale 1080",
    "addr:housenumber":"94",
    "addr:postcode":"1080",
    "addr:street":"Boulevard Du Jubile\u0301",
    "iso:country":"BE",
    "sg:address":"Boulevard Du Jubil\u00c9 94",
    "sg:city":"Sint-jans-molenbeek/molenbeek-saint-jean",
    "sg:orig_category":"Avocats and conseillers juridiques",
    "sg:phone":"+32 2 426 43 22",
    "sg:postcode":"1080",
    "sg:province":"Bruxelles-Capitale",
    "wof:name":"R. Strowel",
    "wof:placetype":"venue"
},
  "geometry": {"coordinates":[4.3378300667,50.8646507263],"type":"Point"}
}