{
  "type": "Feature",
  "properties": {
    "addr:full":"Rue Albert I 218 Erquelinnes Hainaut 6560",
    "addr:housenumber":"218",
    "addr:postcode":"6560",
    "addr:street":"Rue Albert I",
    "iso:country":"BE",
    "sg:address":"Rue Albert I 218",
    "sg:city":"Erquelinnes",
    "sg:classifiers":[
        {
            "category":"Shopping",
            "subcategory":"Clothing, Apparel, & Fashions",
            "type":"Retail Goods"
        }
    ],
    "sg:phone":"+32 71 55 55 81",
    "sg:postcode":"6560",
    "sg:province":"Hainaut",
    "sg:tags":[
        "lady",
        "clothing",
        "-"
    ],
    "wof:name":"Delvaux",
    "wof:placetype":"venue"
},
  "geometry": {"coordinates":[4.1207499504,50.3097915649],"type":"Point"}
}