{
  "type": "Feature",
  "properties": {
    "addr:full":"Kontichstraat 139 Edegem Antwerpen 2650",
    "addr:housenumber":"139",
    "addr:postcode":"2650",
    "addr:street":"Kontichstraat",
    "iso:country":"BE",
    "sg:address":"Kontichstraat 139",
    "sg:city":"Edegem",
    "sg:orig_category":"Metaalbehandeling and -bekleding",
    "sg:phone":"+32 3 457 03 28",
    "sg:postcode":"2650",
    "sg:province":"Antwerpen",
    "wof:name":"Tecknora",
    "wof:placetype":"venue"
},
  "geometry": {"coordinates":[4.4464921951,51.1492347717],"type":"Point"}
}