{
  "type": "Feature",
  "properties": {
    "addr:full":"Broekelken 44 Maldegem Oost-Vlaanderen 9991",
    "addr:housenumber":"44",
    "addr:postcode":"9991",
    "addr:street":"Broekelken",
    "iso:country":"BE",
    "sg:address":"Broekelken 44",
    "sg:city":"Maldegem",
    "sg:orig_category":"Rundveehouders",
    "sg:phone":"+32 50 71 24 04",
    "sg:postcode":"9991",
    "sg:province":"Oost-Vlaanderen",
    "wof:name":"Gabriel Schoors",
    "wof:placetype":"venue"
},
  "geometry": {"coordinates":[3.4986538887,51.2115783691],"type":"Point"}
}