{
  "type": "Feature",
  "properties": {
    "iso:country":"BE",
    "sg:address":"Antwerpsesteenweg 11",
    "sg:city":"Malle",
    "sg:classifiers":[
        {
            "category":"Restaurant",
            "type":"Food & Drink"
        }
    ],
    "sg:phone":"+32 3 309 40 08",
    "sg:postcode":"2390",
    "sg:province":"Antwerpen",
    "sg:tags":[
        "organisatie",
        "feesten",
        "van",
        "catering"
    ],
    "wof:name":"Het Malle Broodje",
    "wof:placetype":"venue"
},
  "geometry": {"coordinates":[4.7325267792,51.3010025024],"type":"Point"}
}