{
  "type": "Feature",
  "properties": {
    "addr:full":"Strya 67 Durbuy Luxembourg 6941",
    "addr:housenumber":"67",
    "addr:postcode":"6941",
    "addr:street":"Strya",
    "iso:country":"BE",
    "sg:address":"Strya 67",
    "sg:city":"Durbuy",
    "sg:orig_category":"Eleveurs de bovins",
    "sg:phone":"+32 86 49 90 18",
    "sg:postcode":"6941",
    "sg:province":"Luxembourg",
    "wof:name":"Benoit Rouxhet",
    "wof:placetype":"venue"
},
  "geometry": {"coordinates":[5.524184227,50.3770332336],"type":"Point"}
}