{
  "type": "Feature",
  "properties": {
    "iso:country":"BE",
    "sg:address":"Genkersteenweg 303ba",
    "sg:city":"Hasselt",
    "sg:orig_category":"Meubelzaken, woning- and keukeninrichting",
    "sg:phone":"+32 11 23 32 77",
    "sg:postcode":"3500",
    "sg:province":"Limburg",
    "wof:name":"Wood, Wood & Co",
    "wof:placetype":"venue"
},
  "geometry": {"coordinates":[5.3801698685,50.9444885254],"type":"Point"}
}