{
  "type": "Feature",
  "properties": {
    "iso:country":"BE",
    "sg:address":"Grasdreef 3",
    "sg:city":"Waregem",
    "sg:orig_category":"Installatie van houten of kunststof schrijnwerk Installatie van metalen schrijnwerk",
    "sg:phone":"+32 56 60 76 09",
    "sg:postcode":"8790",
    "sg:province":"West-Vlaanderen",
    "wof:name":"Luc Verhoeyen",
    "wof:placetype":"venue"
},
  "geometry": {"coordinates":[3.4527359009,50.8935585022],"type":"Point"}
}