{
  "type": "Feature",
  "properties": {
    "addr:full":"Passage Du Centre 20 Mons Hainaut 7000",
    "addr:housenumber":"20",
    "addr:postcode":"7000",
    "addr:street":"Passage Du Centre;Hainaut",
    "iso:country":"BE",
    "sg:address":"Passage Du Centre 20",
    "sg:city":"Mons",
    "sg:orig_category":"R\u00e9parations de chaussures and articles en cuir. Magasins de r\u00e9parations d'articles personnels et m\u00e9n",
    "sg:phone":"+32 65 34 94 34",
    "sg:postcode":"7000",
    "sg:province":"Hainaut",
    "wof:name":"A Toute Pompe",
    "wof:placetype":"venue"
},
  "geometry": {"coordinates":[3.9487760067,50.4511909485],"type":"Point"}
}