{
  "type": "Feature",
  "properties": {
    "addr:full":"Avenue Du Prieur\u00e9 70 Rhode-saint-gen\u00e8se Vlaams-Brabant 1640",
    "addr:housenumber":"70",
    "addr:postcode":"1640",
    "addr:street":"Avenue Du Prieure\u0301",
    "iso:country":"BE",
    "sg:address":"Avenue Du Prieur\u00e9 70",
    "sg:city":"Rhode-saint-gen\u00e8se",
    "sg:classifiers":[
        {
            "category":"Building & Trades",
            "subcategory":"Construction",
            "type":"Services"
        }
    ],
    "sg:phone":"+32 2 381 17 88",
    "sg:postcode":"1640",
    "sg:province":"Vlaams-Brabant",
    "sg:tags":[
        "installation",
        "-",
        "central",
        "heating"
    ],
    "wof:name":"Dubuc D.t.s. Sa",
    "wof:placetype":"venue"
},
  "geometry": {"coordinates":[4.3633332253,50.7184333801],"type":"Point"}
}