{
  "type": "Feature",
  "properties": {
    "iso:country":"BE",
    "sg:address":"Rue Du Sartia 5",
    "sg:city":"Fosses-la-ville (sart-eustache)",
    "sg:classifiers":[
        {
            "category":"Building & Trades",
            "subcategory":"Landscaping Services",
            "type":"Services"
        }
    ],
    "sg:phone":"+32 71 38 00 37",
    "sg:postcode":"5070",
    "sg:province":"Namur",
    "sg:tags":[
        "equipment",
        "swimming",
        "-",
        "pool",
        "contractor"
    ],
    "wof:name":"Waterair Zwembaden",
    "wof:placetype":"venue"
},
  "geometry": {"coordinates":[4.6127810478,50.3676757812],"type":"Point"}
}