{
  "type": "Feature",
  "properties": {
    "iso:country":"BE",
    "sg:address":"Avenue Mar\u00c9chal Foch 751",
    "sg:city":"Mons",
    "sg:classifiers":[
        {
            "category":"Recreation",
            "type":"Entertainment"
        }
    ],
    "sg:phone":"+32 65 82 35 89",
    "sg:postcode":"7012",
    "sg:province":"Hainaut",
    "sg:tags":[
        "diver",
        "amusement"
    ],
    "wof:name":"Ch. Jude",
    "wof:placetype":"venue"
},
  "geometry": {"coordinates":[3.8894600868,50.4481964111],"type":"Point"}
}