{
  "type": "Feature",
  "properties": {
    "iso:country":"BE",
    "sg:address":"Prinsenhof 38 -",
    "sg:city":"Gand",
    "sg:classifiers":[
        {
            "category":"Professional",
            "subcategory":"Art Services",
            "type":"Services"
        }
    ],
    "sg:phone":"+32 9 223 10 43",
    "sg:postcode":"9000",
    "sg:province":"Oost-Vlaanderen",
    "sg:tags":[
        "export-import"
    ],
    "wof:name":"Guatemala Consulate",
    "wof:placetype":"venue"
},
  "geometry": {"coordinates":[3.7166121006,51.0585670471],"type":"Point"}
}