{
  "type": "Feature",
  "properties": {
    "iso:country":"BE",
    "sg:address":"Place Du General-leman 21",
    "sg:city":"Li\u00e8ge",
    "sg:classifiers":[
        {
            "category":"Government",
            "subcategory":"Post Office",
            "type":"Public Place"
        }
    ],
    "sg:phone":"+32 4 252 52 70",
    "sg:postcode":"4000",
    "sg:province":"Li\u00e8ge",
    "sg:tags":[
        "lettering"
    ],
    "wof:name":"Publifix Lettrage",
    "wof:placetype":"venue"
},
  "geometry": {"coordinates":[5.5742621422,50.6200256348],"type":"Point"}
}