{
  "type": "Feature",
  "properties": {
    "addr:full":"Rue Grande-champlon 94bb Tenneville Luxembourg 6971",
    "addr:housenumber":"94bb",
    "addr:postcode":"6971",
    "addr:street":"Rue Grande-Champlon",
    "iso:country":"BE",
    "sg:address":"Rue Grande-champlon 94bb",
    "sg:city":"Tenneville",
    "sg:orig_category":"Offices du tourisme",
    "sg:phone":"+32 84 45 54 26",
    "sg:postcode":"6971",
    "sg:province":"Luxembourg",
    "wof:name":"Syndicat D\u00b4initiative",
    "wof:placetype":"venue"
},
  "geometry": {"coordinates":[5.4861598015,50.1077690125],"type":"Point"}
}