{
  "type": "Feature",
  "properties": {
    "addr:full":"Langepijpestraat 21 Torhout West-Vlaanderen 8820",
    "addr:housenumber":"21",
    "addr:postcode":"8820",
    "addr:street":"Langepijpestraat",
    "iso:country":"BE",
    "sg:address":"Langepijpestraat 21",
    "sg:city":"Torhout",
    "sg:classifiers":[
        {
            "category":"Food & Beverages",
            "subcategory":"Meat & Fish",
            "type":"Retail Goods"
        }
    ],
    "sg:phone":"+32 50 21 23 30",
    "sg:postcode":"8820",
    "sg:province":"West-Vlaanderen",
    "sg:tags":[
        "sausage"
    ],
    "wof:name":"Degryse Nv",
    "wof:placetype":"venue"
},
  "geometry": {"coordinates":[3.0957670212,51.0653800964],"type":"Point"}
}