{
  "type": "Feature",
  "properties": {
    "addr:full":"Rue De L\u00b4ath\u00c9n\u00c9e 26 Elsene/ixelles Bruxelles-Capitale 1050",
    "addr:housenumber":"26",
    "addr:postcode":"1050",
    "addr:street":"Rue De L\u00b4Athe\u0301Ne\u0301E",
    "iso:country":"BE",
    "sg:address":"Rue De L\u00b4ath\u00c9n\u00c9e 26",
    "sg:city":"Elsene/ixelles",
    "sg:orig_category":"Action sociale avec h\u00e9bergement",
    "sg:phone":"+32 2 511 77 38",
    "sg:postcode":"1050",
    "sg:province":"Bruxelles-Capitale",
    "wof:name":"Centre De Service Social",
    "wof:placetype":"venue"
},
  "geometry": {"coordinates":[4.3656787872,50.8351631165],"type":"Point"}
}