{
  "type": "Feature",
  "properties": {
    "addr:full":"Maastrichterstraat 1b40 Hasselt Limburg 3500",
    "addr:housenumber":"1b40",
    "addr:postcode":"3500",
    "addr:street":"Maastrichterstraat",
    "iso:country":"BE",
    "sg:address":"Maastrichterstraat 1b40",
    "sg:city":"Hasselt",
    "sg:orig_category":"V\u00eatements. V\u00eatements pour b\u00e9b\u00e9s and enfants",
    "sg:phone":"+32 11 23 24 73",
    "sg:postcode":"3500",
    "sg:province":"Limburg",
    "wof:name":"Tobago",
    "wof:placetype":"venue"
},
  "geometry": {"coordinates":[5.3379402161,50.9291534424],"type":"Point"}
}