{
  "type": "Feature",
  "properties": {
    "iso:country":"BE",
    "sg:address":"Koning Albert I Laan 157",
    "sg:city":"Brugge (sint-michiels)",
    "sg:classifiers":[
        {
            "category":"Banks & Credit Unions",
            "subcategory":"Investment Brokerage",
            "type":"Services"
        }
    ],
    "sg:phone":"+32 50 39 31 25",
    "sg:postcode":"8200",
    "sg:province":"West-Vlaanderen",
    "wof:name":"Verhinvest Nv",
    "wof:placetype":"venue"
},
  "geometry": {"coordinates":[3.1942210197,51.1648864746],"type":"Point"}
}