{
  "type": "Feature",
  "properties": {
    "iso:country":"BE",
    "sg:address":"Kalandestraat 19",
    "sg:city":"Gent",
    "sg:classifiers":[
        {
            "category":"Shopping",
            "subcategory":"Clothing, Apparel, & Fashions",
            "type":"Retail Goods"
        }
    ],
    "sg:phone":"+32 9 233 62 85",
    "sg:postcode":"9000",
    "sg:province":"Oost-Vlaanderen",
    "sg:tags":[
        "lady",
        "clothing",
        "-"
    ],
    "wof:name":"Strelli O",
    "wof:placetype":"venue"
},
  "geometry": {"coordinates":[3.7255349159,51.0518302917],"type":"Point"}
}