{
  "type": "Feature",
  "properties": {
    "iso:country":"BE",
    "sg:address":"Stokkelsesteenweg 387",
    "sg:city":"Sint-pieters-woluwe/woluwe-saint-pierre",
    "sg:orig_category":"Herstellingen and onderhoud van auto's Voertuigen",
    "sg:phone":"+32 2 770 88 32",
    "sg:postcode":"1150",
    "sg:province":"Bruxelles-Capitale",
    "wof:name":"A.v.h.",
    "wof:placetype":"venue"
},
  "geometry": {"coordinates":[4.4554390907,50.8425254822],"type":"Point"}
}