{
  "type": "Feature",
  "properties": {
    "addr:full":"Rue Des Acanthes 4-2 Bruxelles (watermael-boitsfort) Bruxelles-Capitale 1170",
    "addr:housenumber":"4-2",
    "addr:postcode":"1170",
    "addr:street":"Rue Des Acanthes",
    "iso:country":"BE",
    "sg:address":"Rue Des Acanthes 4-2",
    "sg:city":"Bruxelles (watermael-boitsfort)",
    "sg:classifiers":[
        {
            "category":"Professional",
            "subcategory":"Management & Consulting",
            "type":"Services"
        }
    ],
    "sg:phone":"+32 2 660 34 75",
    "sg:postcode":"1170",
    "sg:province":"Bruxelles-Capitale",
    "sg:tags":[
        "consultant"
    ],
    "wof:name":"Coumanne C",
    "wof:placetype":"venue"
},
  "geometry": {"coordinates":[4.4209589958,50.807888031],"type":"Point"}
}