{
  "type": "Feature",
  "properties": {
    "addr:full":"Rue Du Prince 16 Verviers Li\u00e8ge 4800",
    "addr:housenumber":"16",
    "addr:postcode":"4800",
    "addr:street":"Rue Du Prince",
    "iso:country":"BE",
    "sg:address":"Rue Du Prince 16",
    "sg:city":"Verviers",
    "sg:orig_category":"D\u00e9chets and d\u00e9bris Ramassage and traitement des d\u00e9chets m\u00e9nagers. R\u00e9cup\u00e9ration de mati\u00e8res m\u00e9talliqu",
    "sg:phone":"+32 87 31 67 53",
    "sg:postcode":"4800",
    "sg:province":"Li\u00e8ge",
    "wof:name":"F Noirfalise Et Fils",
    "wof:placetype":"venue"
},
  "geometry": {"coordinates":[5.8750801086,50.5974273682],"type":"Point"}
}