{
  "type": "Feature",
  "properties": {
    "addr:full":"Boulevard Z\u00e9nobe Gramme 25 Herstal Li\u00e8ge 4040",
    "addr:housenumber":"25",
    "addr:postcode":"4040",
    "addr:street":"Boulevard Ze\u0301Nobe Gramme",
    "iso:country":"BE",
    "sg:address":"Boulevard Z\u00e9nobe Gramme 25",
    "sg:city":"Herstal",
    "sg:classifiers":[
        {
            "category":"Retail",
            "subcategory":"Auto Repair",
            "type":"Services"
        }
    ],
    "sg:phone":"+32 4 264 61 51",
    "sg:postcode":"4040",
    "sg:province":"Li\u00e8ge",
    "sg:tags":[
        "automobile-body"
    ],
    "wof:name":"Stepcar Sc",
    "wof:placetype":"venue"
},
  "geometry": {"coordinates":[5.632130146,50.6621398926],"type":"Point"}
}