{
  "type": "Feature",
  "properties": {
    "addr:full":"Avenue Winston Churchill 137 Box 26 Bruxelles (uccle) Bruxelles-Capitale 1180",
    "addr:housenumber":"137 box 26",
    "addr:postcode":"1180",
    "addr:street":"Avenue Winston Churchill",
    "iso:country":"BE",
    "sg:address":"Avenue Winston Churchill 137 Box 26",
    "sg:city":"Bruxelles (uccle)",
    "sg:classifiers":[
        {
            "category":"Banks & Credit Unions",
            "subcategory":"Bureau De Change",
            "type":"Services"
        }
    ],
    "sg:phone":"+32 2 344 77 08",
    "sg:postcode":"1180",
    "sg:province":"Bruxelles-Capitale",
    "sg:tags":[
        "belgian",
        "-",
        "broker",
        "exchange"
    ],
    "wof:name":"Ropsy & Cie Sa",
    "wof:placetype":"venue"
},
  "geometry": {"coordinates":[4.3579058647,50.8114967346],"type":"Point"}
}