{
  "type": "Feature",
  "properties": {
    "iso:country":"BE",
    "sg:address":"Kransvijver 4",
    "sg:city":"Kortrijk",
    "sg:orig_category":"Centres de relaxation and bien-\u00eatre. Instituts de beaut\u00e9",
    "sg:phone":"+32 56 37 10 87",
    "sg:postcode":"8501",
    "sg:province":"West-Vlaanderen",
    "wof:name":"Instituut Venus",
    "wof:placetype":"venue"
},
  "geometry": {"coordinates":[3.2321460247,50.8395385742],"type":"Point"}
}