{
  "type": "Feature",
  "properties": {
    "addr:full":"Turnhoutsebaan 451 Schilde Antwerpen 2970",
    "addr:housenumber":"451",
    "addr:postcode":"2970",
    "addr:street":"Turnhoutsebaan",
    "iso:country":"BE",
    "sg:address":"Turnhoutsebaan 451",
    "sg:city":"Schilde",
    "sg:orig_category":"Agences d'exp\u00e9dition",
    "sg:phone":"+32 3 385 09 78",
    "sg:postcode":"2970",
    "sg:province":"Antwerpen",
    "wof:name":"Continental Decotrade",
    "wof:placetype":"venue"
},
  "geometry": {"coordinates":[4.6125588417,51.2525596619],"type":"Point"}
}