{
  "type": "Feature",
  "properties": {
    "addr:full":"Grote Markt 48d Herentals Antwerpen 2200",
    "addr:housenumber":"48d",
    "addr:postcode":"2200",
    "addr:street":"Grote Markt",
    "iso:country":"BE",
    "sg:address":"Grote Markt 48d",
    "sg:city":"Herentals",
    "sg:classifiers":[
        {
            "category":"Real Estate",
            "subcategory":"Architect",
            "type":"Services"
        }
    ],
    "sg:phone":"+32 14 21 97 45",
    "sg:postcode":"2200",
    "sg:province":"Antwerpen",
    "wof:name":"Van Gorp G",
    "wof:placetype":"venue"
},
  "geometry": {"coordinates":[4.8360090256,51.1777458191],"type":"Point"}
}