{
  "type": "Feature",
  "properties": {
    "iso:country":"BE",
    "sg:address":"Sint-maartensplein 11ba",
    "sg:city":"Koekelare",
    "sg:orig_category":"Diverse kredietdiensten",
    "sg:postcode":"8680",
    "sg:province":"West-Vlaanderen",
    "wof:name":"Bancontact-mister Cash",
    "wof:placetype":"venue"
},
  "geometry": {"coordinates":[2.9788548946,51.0891609192],"type":"Point"}
}