{
  "type": "Feature",
  "properties": {
    "addr:full":"Camp Et Haie 36 Ellezelles Hainaut 7890",
    "addr:housenumber":"36",
    "addr:postcode":"7890",
    "iso:country":"BE",
    "sg:address":"Camp Et Haie 36",
    "sg:city":"Ellezelles",
    "sg:classifiers":[
        {
            "category":"Government",
            "subcategory":"Post Office",
            "type":"Public Place"
        }
    ],
    "sg:phone":"+32 68 54 20 14",
    "sg:postcode":"7890",
    "sg:province":"Hainaut",
    "sg:tags":[
        "base",
        "data"
    ],
    "wof:name":"Fast-line",
    "wof:placetype":"venue"
},
  "geometry": {"coordinates":[3.6668789387,50.7288780212],"type":"Point"}
}