{
  "type": "Feature",
  "properties": {
    "addr:full":"Ossenberg 99b2 Balen Antwerpen 2490",
    "addr:housenumber":"99b2",
    "addr:postcode":"2490",
    "addr:street":"Ossenberg",
    "iso:country":"BE",
    "sg:address":"Ossenberg 99b2",
    "sg:city":"Balen",
    "sg:orig_category":"Epiceries",
    "sg:phone":"+32 14 30 04 88",
    "sg:postcode":"2490",
    "sg:province":"Antwerpen",
    "wof:name":"Supra",
    "wof:placetype":"venue"
},
  "geometry": {"coordinates":[5.1157569885,51.148475647],"type":"Point"}
}