{
  "type": "Feature",
  "properties": {
    "addr:full":"Schoolstraat 15 Beveren Oost-Vlaanderen 9120",
    "addr:housenumber":"15",
    "addr:postcode":"9120",
    "addr:street":"Schoolstraat",
    "iso:country":"BE",
    "sg:address":"Schoolstraat 15",
    "sg:city":"Beveren",
    "sg:orig_category":"Enseignement maternel and primaire",
    "sg:phone":"+32 3 775 79 83",
    "sg:postcode":"9120",
    "sg:province":"Oost-Vlaanderen",
    "wof:name":"Gemeentelijke Basisschool",
    "wof:placetype":"venue"
},
  "geometry": {"coordinates":[4.2789840698,51.2206306458],"type":"Point"}
}