{
  "type": "Feature",
  "properties": {
    "iso:country":"BE",
    "sg:address":"Gaversesteenweg 476ba",
    "sg:city":"Merelbeke",
    "sg:orig_category":"Artsen and specialisten",
    "sg:phone":"+32 9 362 74 79",
    "sg:postcode":"9820",
    "sg:province":"Oost-Vlaanderen",
    "wof:name":"J. Jonckheere",
    "wof:placetype":"venue"
},
  "geometry": {"coordinates":[3.7177629471,50.9731521606],"type":"Point"}
}