{
  "type": "Feature",
  "properties": {
    "iso:country":"BE",
    "sg:address":"Gentstraat 71",
    "sg:city":"Oudenaarde",
    "sg:classifiers":[
        {
            "category":"Autos & Motor Vehicles",
            "subcategory":"Fuel & Gas Station",
            "type":"Retail Goods"
        }
    ],
    "sg:phone":"+32 55 30 17 37",
    "sg:postcode":"9700",
    "sg:province":"Oost-Vlaanderen",
    "wof:name":"Texaco Van Dijcke",
    "wof:placetype":"venue"
},
  "geometry": {"coordinates":[3.5998520851,50.8523635864],"type":"Point"}
}