{
  "type": "Feature",
  "properties": {
    "iso:country":"BE",
    "sg:address":"Astridlaan 106",
    "sg:city":"Brugge",
    "sg:orig_category":"Plomberie, chauffage and installations sanitaires",
    "sg:phone":"+32 50 36 06 42",
    "sg:postcode":"8310",
    "sg:province":"West-Vlaanderen",
    "wof:name":"De Busscher",
    "wof:placetype":"venue"
},
  "geometry": {"coordinates":[3.2512879372,51.1976737976],"type":"Point"}
}