{
  "type": "Feature",
  "properties": {
    "addr:full":"Brusselsestw 550 Overijse Vlaams-Brabant 3090",
    "addr:housenumber":"550",
    "addr:postcode":"3090",
    "iso:country":"BE",
    "sg:address":"Brusselsestw 550",
    "sg:city":"Overijse",
    "sg:orig_category":"Kapsalons",
    "sg:phone":"+32 2 657 37 02",
    "sg:postcode":"3090",
    "sg:province":"Vlaams-Brabant",
    "wof:name":"Hendrickx",
    "wof:placetype":"venue"
},
  "geometry": {"coordinates":[4.4868078232,50.7918701172],"type":"Point"}
}