{
  "type": "Feature",
  "properties": {
    "iso:country":"BE",
    "sg:address":"Rue De La Chasse 50",
    "sg:city":"Charleroi",
    "sg:orig_category":"Sportclubs Sportterreinen and installaties behalve sportcentra",
    "sg:phone":"+32 71 45 01 72",
    "sg:postcode":"6061",
    "sg:province":"Hainaut",
    "wof:name":"F.c. Mont-sur-marchienne",
    "wof:placetype":"venue"
},
  "geometry": {"coordinates":[4.4874720573,50.4051895142],"type":"Point"}
}