{
  "type": "Feature",
  "properties": {
    "addr:full":"Frans Reyniersstraat 42 Mechelen Antwerpen 2811",
    "addr:housenumber":"42",
    "addr:postcode":"2811",
    "addr:street":"Frans Reyniersstraat",
    "iso:country":"BE",
    "sg:address":"Frans Reyniersstraat 42",
    "sg:city":"Mechelen",
    "sg:classifiers":[
        {
            "category":"Shopping",
            "subcategory":"Clothing, Apparel, & Fashions",
            "type":"Retail Goods"
        }
    ],
    "sg:phone":"+32 15 41 45 81",
    "sg:postcode":"2811",
    "sg:province":"Antwerpen",
    "sg:tags":[
        "v\u00eatements",
        "pour",
        "dame"
    ],
    "wof:name":"Huis Marjet",
    "wof:placetype":"venue"
},
  "geometry": {"coordinates":[4.4448008537,51.0144348145],"type":"Point"}
}