{
  "type": "Feature",
  "properties": {
    "addr:full":"Balendijk 42 Lommel Limburg 3920",
    "addr:housenumber":"42",
    "addr:postcode":"3920",
    "addr:street":"Balendijk",
    "iso:country":"BE",
    "sg:address":"Balendijk 42",
    "sg:city":"Lommel",
    "sg:orig_category":"Boucheries",
    "sg:phone":"+32 11 55 37 67",
    "sg:postcode":"3920",
    "sg:province":"Limburg",
    "wof:name":"Budgetslager",
    "wof:placetype":"venue"
},
  "geometry": {"coordinates":[5.3030238152,51.2239608765],"type":"Point"}
}