{
  "type": "Feature",
  "properties": {
    "iso:country":"BE",
    "sg:address":"Rue De La Cayauderie 47",
    "sg:city":"Charleroi",
    "sg:classifiers":[
        {
            "category":"Personal",
            "subcategory":"Beauty Salon",
            "type":"Services"
        }
    ],
    "sg:phone":"+32 71 41 82 11",
    "sg:postcode":"6000",
    "sg:province":"Hainaut",
    "sg:tags":[
        "lady",
        "-",
        "hairdressing"
    ],
    "wof:name":"Rendace",
    "wof:placetype":"venue"
},
  "geometry": {"coordinates":[4.4595689774,50.4227638245],"type":"Point"}
}