{
  "type": "Feature",
  "properties": {
    "addr:full":"Hollandstraat 26 Antwerpen Antwerpen 2060",
    "addr:housenumber":"26",
    "addr:postcode":"2060",
    "addr:street":"Hollandstraat",
    "iso:country":"BE",
    "sg:address":"Hollandstraat 26",
    "sg:city":"Antwerpen",
    "sg:classifiers":[
        {
            "category":"Professional",
            "subcategory":"Art Services",
            "type":"Services"
        }
    ],
    "sg:phone":"+32 3 297 42 82",
    "sg:postcode":"2060",
    "sg:province":"Antwerpen",
    "sg:tags":[
        "-",
        "painter",
        "artist"
    ],
    "wof:name":"Ecuatorial Vzw",
    "wof:placetype":"venue"
},
  "geometry": {"coordinates":[4.4194641113,51.2239303589],"type":"Point"}
}