{
  "type": "Feature",
  "properties": {
    "iso:country":"BE",
    "sg:address":"Lunderstraat 57",
    "sg:city":"Londerzeel",
    "sg:orig_category":"Boucheries",
    "sg:phone":"+32 52 30 54 04",
    "sg:postcode":"1840",
    "sg:province":"Vlaams-Brabant",
    "wof:name":"Guido Verstricht",
    "wof:placetype":"venue"
},
  "geometry": {"coordinates":[4.3032078743,51.0096321106],"type":"Point"}
}