{
  "type": "Feature",
  "properties": {
    "addr:full":"Enclos De Bellaire 4 Neupr\u00e9 (neuville-en-condroz) Li\u00e8ge 4121",
    "addr:housenumber":"4",
    "addr:postcode":"4121",
    "addr:street":"Enclos De Bellaire",
    "iso:country":"BE",
    "sg:address":"Enclos De Bellaire 4",
    "sg:city":"Neupr\u00e9 (neuville-en-condroz)",
    "sg:classifiers":[
        {
            "category":"Manufacturing",
            "subcategory":"Leather Goods",
            "type":"Manufacturing & Wholesale Goods"
        }
    ],
    "sg:phone":"+32 4 371 59 78",
    "sg:postcode":"4121",
    "sg:province":"Li\u00e8ge",
    "sg:tags":[
        "repair",
        "buckskin",
        "-",
        "fur",
        "cleaning"
    ],
    "wof:name":"Block J",
    "wof:placetype":"venue"
},
  "geometry": {"coordinates":[5.469312191,50.5383453369],"type":"Point"}
}