{
  "type": "Feature",
  "properties": {
    "iso:country":"BE",
    "sg:address":"Adriaan Brouwerlaan 5",
    "sg:city":"Rumst (reet)",
    "sg:classifiers":[
        {
            "category":"Professional",
            "type":"Services"
        }
    ],
    "sg:phone":"+32 3 888 27 33",
    "sg:postcode":"2840",
    "sg:province":"Antwerpen",
    "sg:tags":[
        "entertainer"
    ],
    "wof:name":"Guinelli",
    "wof:placetype":"venue"
},
  "geometry": {"coordinates":[4.4038381577,51.1031417847],"type":"Point"}
}