{
  "type": "Feature",
  "properties": {
    "iso:country":"BE",
    "sg:address":"Rue De Chassepierre 25",
    "sg:city":"Florenville (sainte-c\u00e9cile)",
    "sg:classifiers":[
        {
            "category":"Recreation",
            "subcategory":"Campground",
            "type":"Entertainment"
        }
    ],
    "sg:phone":"+32 61 31 21 87",
    "sg:postcode":"6820",
    "sg:province":"Luxembourg",
    "sg:tags":[
        "site",
        "camping"
    ],
    "wof:name":"Semois (de La)",
    "wof:placetype":"venue"
},
  "geometry": {"coordinates":[5.2437701225,49.7268218994],"type":"Point"}
}