{
  "type": "Feature",
  "properties": {
    "iso:country":"BE",
    "sg:address":"Tuinlaan 28",
    "sg:city":"Sint-niklaas (belsele)",
    "sg:classifiers":[
        {
            "category":"Building & Trades",
            "subcategory":"Pest Control",
            "type":"Services"
        }
    ],
    "sg:phone":"+32 3 772 41 73",
    "sg:postcode":"9111",
    "sg:province":"Oost-Vlaanderen",
    "sg:tags":[
        "painting",
        "contractor"
    ],
    "wof:name":"Laureys W Bvba",
    "wof:placetype":"venue"
},
  "geometry": {"coordinates":[4.1058092117,51.1504936218],"type":"Point"}
}