{
  "type": "Feature",
  "properties": {
    "addr:full":"Rue Puits-en-sock 120-1 Li\u00e8ge 1 (li\u00e8ge 2) Li\u00e8ge 4020",
    "addr:housenumber":"2",
    "addr:postcode":"120-1;4020",
    "addr:street":"Rue Puits-En-Sock;Lie\u0300Ge",
    "iso:country":"BE",
    "sg:address":"Rue Puits-en-sock 120-1",
    "sg:city":"Li\u00e8ge 1 (li\u00e8ge 2)",
    "sg:classifiers":[
        {
            "category":"Retail",
            "subcategory":"Laundry & Dry Cleaning",
            "type":"Services"
        }
    ],
    "sg:phone":"+32 4 343 38 29",
    "sg:postcode":"4020",
    "sg:province":"Li\u00e8ge",
    "wof:name":"Quick Shop Sprl",
    "wof:placetype":"venue"
},
  "geometry": {"coordinates":[5.5852460861,50.6389770508],"type":"Point"}
}