{
  "type": "Feature",
  "properties": {
    "addr:full":"Nukkerstraat 24 Bredene West-Vlaanderen 8450",
    "addr:housenumber":"24",
    "addr:postcode":"8450",
    "addr:street":"Nukkerstraat",
    "iso:country":"BE",
    "sg:address":"Nukkerstraat 24",
    "sg:city":"Bredene",
    "sg:orig_category":"Verplichte sociale verzekeringen",
    "sg:phone":"+32 59 32 57 57",
    "sg:postcode":"8450",
    "sg:province":"West-Vlaanderen",
    "wof:name":"Bond Moyson",
    "wof:placetype":"venue"
},
  "geometry": {"coordinates":[2.9578111172,51.221496582],"type":"Point"}
}