{
  "type": "Feature",
  "properties": {
    "iso:country":"BE",
    "sg:address":"Liersesteenweg 45",
    "sg:city":"Lint",
    "sg:orig_category":"Herstellingen and onderhoud van auto's Voertuigen",
    "sg:phone":"+32 3 455 33 41",
    "sg:postcode":"2547",
    "sg:province":"Antwerpen",
    "wof:name":"Garage Patrick",
    "wof:placetype":"venue"
},
  "geometry": {"coordinates":[4.4995670319,51.1273078918],"type":"Point"}
}