{
  "type": "Feature",
  "properties": {
    "addr:full":"Rue Des Ecoliers 23 Mons Hainaut 7000",
    "addr:housenumber":"23",
    "addr:postcode":"7000",
    "addr:street":"Rue Des Ecoliers;Hainaut",
    "iso:country":"BE",
    "sg:address":"Rue Des Ecoliers 23",
    "sg:city":"Mons",
    "sg:classifiers":[
        {
            "category":"Social Services",
            "type":"Services"
        }
    ],
    "sg:phone":"+32 65 36 11 36",
    "sg:postcode":"7000",
    "sg:province":"Hainaut",
    "wof:name":"Sos Enfants Mons-borinage",
    "wof:placetype":"venue"
},
  "geometry": {"coordinates":[3.9437639713,50.4500427246],"type":"Point"}
}