{
  "type": "Feature",
  "properties": {
    "addr:full":"Rue Egide Van Ophem 108 Bruxelles Bruxelles-Capitale 1180",
    "addr:housenumber":"108",
    "addr:postcode":"1180",
    "addr:street":"Rue Egide Van Ophem",
    "iso:country":"BE",
    "sg:address":"Rue Egide Van Ophem 108",
    "sg:city":"Bruxelles",
    "sg:orig_category":"Mineral Preparations",
    "sg:phone":"+32 2 370 46 01",
    "sg:postcode":"1180",
    "sg:province":"Bruxelles-Capitale",
    "wof:name":"Laboratoire Therabel N.v. S.a.",
    "wof:placetype":"venue"
},
  "geometry": {"coordinates":[4.3290829659,50.793510437],"type":"Point"}
}