{
  "type": "Feature",
  "properties": {
    "iso:country":"BE",
    "sg:address":"Parvis Sainte-alix 21",
    "sg:city":"Sint-pieters-woluwe/woluwe-sai",
    "sg:orig_category":"Opticiens",
    "sg:phone":"+32 2 779 43 25",
    "sg:postcode":"1150",
    "sg:province":"Bruxelles-Capitale",
    "wof:name":"Maison Optolux",
    "wof:placetype":"venue"
},
  "geometry": {"coordinates":[4.4619998932,50.8275108337],"type":"Point"}
}