{
  "type": "Feature",
  "properties": {
    "iso:country":"BE",
    "sg:address":"Vinkenlaan 9",
    "sg:city":"Malle (oostmalle)",
    "sg:classifiers":[
        {
            "category":"Professional",
            "type":"Services"
        }
    ],
    "sg:phone":"+32 3 309 38 69",
    "sg:postcode":"2390",
    "sg:province":"Antwerpen",
    "sg:tags":[
        "surveyor",
        "-",
        "valuer"
    ],
    "wof:name":"Carell Nv",
    "wof:placetype":"venue"
},
  "geometry": {"coordinates":[4.7193827629,51.2880439758],"type":"Point"}
}