{
  "type": "Feature",
  "properties": {
    "addr:full":"Rue Brigade Piron 66 Edingen/enghien Hainaut 7850",
    "addr:housenumber":"66",
    "addr:postcode":"7850",
    "addr:street":"Rue Brigade Piron",
    "iso:country":"BE",
    "sg:address":"Rue Brigade Piron 66",
    "sg:city":"Edingen/enghien",
    "sg:orig_category":"M\u00e9decins and sp\u00e9cialistes",
    "sg:phone":"+32 2 395 68 90",
    "sg:postcode":"7850",
    "sg:province":"Hainaut",
    "wof:name":"Sylvie Moinie",
    "wof:placetype":"venue"
},
  "geometry": {"coordinates":[4.0928640366,50.6901855469],"type":"Point"}
}