{
  "type": "Feature",
  "properties": {
    "addr:full":"Rue Des Wallons 3a Ottignies-louvain-la-neuve (louvain-la-neuve) Brabant Wallon 1348",
    "addr:housenumber":"3a",
    "addr:postcode":"1348",
    "addr:street":"Rue Des Wallons",
    "iso:country":"BE",
    "sg:address":"Rue Des Wallons 3a",
    "sg:city":"Ottignies-louvain-la-neuve (louvain-la-neuve)",
    "sg:classifiers":[
        {
            "category":"Shopping",
            "subcategory":"Crafts & Fabrics",
            "type":"Retail Goods"
        }
    ],
    "sg:phone":"+32 10 45 12 13",
    "sg:postcode":"1348",
    "sg:province":"Brabant Wallon",
    "sg:tags":[
        "hi-fi",
        "equipment",
        "stereophonic",
        "-"
    ],
    "wof:name":"Watt's",
    "wof:placetype":"venue"
},
  "geometry": {"coordinates":[4.6154670715,50.6696395874],"type":"Point"}
}