{
  "type": "Feature",
  "properties": {
    "iso:country":"BE",
    "sg:address":"Lindestraat 10",
    "sg:city":"Lochristi",
    "sg:orig_category":"Transports routiers de marchandises",
    "sg:phone":"+32 9 355 13 59",
    "sg:postcode":"9080",
    "sg:province":"Oost-Vlaanderen",
    "wof:name":"Buysse E",
    "wof:placetype":"venue"
},
  "geometry": {"coordinates":[3.8282020092,51.1215896606],"type":"Point"}
}