{
  "type": "Feature",
  "properties": {
    "addr:full":"Chauss\u00e9e De Wavre 268a Wanze Li\u00e8ge 4520",
    "addr:housenumber":"268a",
    "addr:postcode":"4520",
    "addr:street":"Chausse\u0301E De Wavre",
    "iso:country":"BE",
    "sg:address":"Chauss\u00e9e De Wavre 268a",
    "sg:city":"Wanze",
    "sg:classifiers":[
        {
            "category":"Home & Garden",
            "subcategory":"Building Materials",
            "type":"Retail Goods"
        }
    ],
    "sg:phone":"+32 85 23 36 39",
    "sg:postcode":"4520",
    "sg:province":"Li\u00e8ge",
    "sg:tags":[
        "window"
    ],
    "wof:name":"L.m. Ch\u00e2ssis Sa",
    "wof:placetype":"venue"
},
  "geometry": {"coordinates":[5.1927700043,50.5396499634],"type":"Point"}
}