{
  "type": "Feature",
  "properties": {
    "addr:full":"Driebruggenstraat 74 Oudergem/auderghem Bruxelles-Capitale 1160",
    "addr:housenumber":"74",
    "addr:postcode":"1160",
    "addr:street":"Driebruggenstraat;/",
    "iso:country":"BE",
    "sg:address":"Driebruggenstraat 74",
    "sg:city":"Oudergem/auderghem",
    "sg:orig_category":"Diverse grafische activiteiten",
    "sg:phone":"+32 2 662 21 32",
    "sg:postcode":"1160",
    "sg:province":"Bruxelles-Capitale",
    "wof:name":"Bureau Jaune & Bleu",
    "wof:placetype":"venue"
},
  "geometry": {"coordinates":[4.4055891037,50.8199501038],"type":"Point"}
}