{
  "type": "Feature",
  "properties": {
    "iso:country":"BE",
    "sg:address":"Obsinnich 2ba",
    "sg:city":"Voeren/fourons",
    "sg:orig_category":"Eleveurs de bovins",
    "sg:phone":"+32 4 381 07 00",
    "sg:postcode":"3791",
    "sg:province":"Limburg",
    "wof:name":"Christian Pinckaers",
    "wof:placetype":"venue"
},
  "geometry": {"coordinates":[5.8900208473,50.741027832],"type":"Point"}
}