{
  "type": "Feature",
  "properties": {
    "iso:country":"BE",
    "sg:address":"Bavegemstraat 57ba",
    "sg:city":"Oosterzele",
    "sg:orig_category":"Boucheries",
    "sg:phone":"+32 9 362 08 53",
    "sg:postcode":"9860",
    "sg:province":"Oost-Vlaanderen",
    "wof:name":"Freddy Impens",
    "wof:placetype":"venue"
},
  "geometry": {"coordinates":[3.8378200531,50.9527320862],"type":"Point"}
}