{
  "type": "Feature",
  "properties": {
    "iso:country":"BE",
    "sg:address":"Industrieter. Heikemp 1518",
    "sg:city":"Kinrooi",
    "sg:orig_category":"Afbraak- and draineerwerken",
    "sg:phone":"+32 89 70 10 49",
    "sg:postcode":"3640",
    "sg:province":"Limburg",
    "wof:name":"Van De Vorst",
    "wof:placetype":"venue"
},
  "geometry": {"coordinates":[5.7191729546,51.1794433594],"type":"Point"}
}