{
  "type": "Feature",
  "properties": {
    "addr:full":"Avenue De Houffalize 56bc Libramont-chevigny Luxembourg 6800",
    "addr:housenumber":"56bc",
    "addr:postcode":"6800",
    "addr:street":"Avenue De Houffalize",
    "iso:country":"BE",
    "sg:address":"Avenue De Houffalize 56bc",
    "sg:city":"Libramont-chevigny",
    "sg:orig_category":"Location de cassettes vid\u00e9o and audio. Disquaires",
    "sg:phone":"+32 61 22 43 20",
    "sg:postcode":"6800",
    "sg:province":"Luxembourg",
    "wof:name":"La M\u00c9diath\u00c8que Commun.fr.",
    "wof:placetype":"venue"
},
  "geometry": {"coordinates":[5.3761348724,49.9199943542],"type":"Point"}
}