{
  "type": "Feature",
  "properties": {
    "iso:country":"BE",
    "sg:address":"Rue Du Baron D'obin 85",
    "sg:city":"Wasseiges",
    "sg:classifiers":[
        {
            "category":"Retail",
            "subcategory":"Funeral Services",
            "type":"Services"
        }
    ],
    "sg:phone":"+32 81 85 51 59",
    "sg:postcode":"4219",
    "sg:province":"Li\u00e8ge",
    "sg:tags":[
        "director"
    ],
    "wof:name":"Fontaine",
    "wof:placetype":"venue"
},
  "geometry": {"coordinates":[5.0126919746,50.6222686768],"type":"Point"}
}