{
  "type": "Feature",
  "properties": {
    "addr:full":"Rue D'esneux 142 Sprimont Li\u00e8ge 4140",
    "addr:housenumber":"142",
    "addr:postcode":"4140",
    "addr:street":"Rue D'Esneux",
    "iso:country":"BE",
    "sg:address":"Rue D'esneux 142",
    "sg:city":"Sprimont",
    "sg:orig_category":"G\u00e9om\u00e8tres",
    "sg:phone":"+32 4 380 27 51",
    "sg:postcode":"4140",
    "sg:province":"Li\u00e8ge",
    "wof:name":"Dominique Francois",
    "wof:placetype":"venue"
},
  "geometry": {"coordinates":[5.6084699631,50.5309333801],"type":"Point"}
}