{
  "type": "Feature",
  "properties": {
    "addr:full":"Neerharenweg 36 Lanaken Limburg 3620",
    "addr:housenumber":"36",
    "addr:postcode":"3620",
    "addr:street":"Neerharenweg",
    "iso:country":"BE",
    "sg:address":"Neerharenweg 36",
    "sg:city":"Lanaken",
    "sg:classifiers":[
        {
            "category":"Science Facility",
            "type":"Public Place"
        }
    ],
    "sg:phone":"+32 89 71 21 74",
    "sg:postcode":"3620",
    "sg:province":"Limburg",
    "sg:tags":[
        "packaging",
        "consulting",
        "engineering"
    ],
    "wof:name":"Lanko International B.v.",
    "wof:placetype":"venue"
},
  "geometry": {"coordinates":[5.6563501358,50.9025917053],"type":"Point"}
}