{
  "type": "Feature",
  "properties": {
    "addr:full":"Wondelgemstraat 91 Gent Oost-Vlaanderen 9000",
    "addr:housenumber":"91",
    "addr:postcode":"9000",
    "addr:street":"Wondelgemstraat;Oost-Vlaanderen",
    "iso:country":"BE",
    "sg:address":"Wondelgemstraat 91",
    "sg:city":"Gent",
    "sg:orig_category":"Boucheries. Supermarch\u00e9s",
    "sg:phone":"+32 9 225 12 80",
    "sg:postcode":"9000",
    "sg:province":"Oost-Vlaanderen",
    "wof:name":"Unic",
    "wof:placetype":"venue"
},
  "geometry": {"coordinates":[3.7098801136,51.0622444153],"type":"Point"}
}