{
  "type": "Feature",
  "properties": {
    "addr:full":"Klaverbloemstraat 34 Antwerpen Antwerpen 2170",
    "addr:housenumber":"34",
    "addr:postcode":"2170",
    "addr:street":"Klaverbloemstraat",
    "iso:country":"BE",
    "sg:address":"Klaverbloemstraat 34",
    "sg:city":"Antwerpen",
    "sg:classifiers":[
        {
            "category":"Food & Beverages",
            "subcategory":"Fruits & Vegetables",
            "type":"Retail Goods"
        }
    ],
    "sg:phone":"+32 3 646 40 86",
    "sg:postcode":"2170",
    "sg:province":"Antwerpen",
    "sg:tags":[
        "l\u00e9gumes"
    ],
    "wof:name":"Eduard Verhoeven",
    "wof:placetype":"venue"
},
  "geometry": {"coordinates":[4.4505147934,51.246723175],"type":"Point"}
}