{
  "type": "Feature",
  "properties": {
    "addr:full":"Grand'rue 342 Charleroi Hainaut 6061",
    "addr:housenumber":"342",
    "addr:postcode":"6061",
    "addr:street":"Grand'Rue;Hainaut",
    "iso:country":"BE",
    "sg:address":"Grand'rue 342",
    "sg:city":"Charleroi",
    "sg:orig_category":"Entretien and r\u00e9parations de voitures",
    "sg:phone":"+32 71 42 08 86",
    "sg:postcode":"6061",
    "sg:province":"Hainaut",
    "wof:name":"Albert Raeymaekers",
    "wof:placetype":"venue"
},
  "geometry": {"coordinates":[4.459209919,50.4121246338],"type":"Point"}
}