{
  "type": "Feature",
  "properties": {
    "addr:full":"Genenbosstraat 91 Lummen Limburg 3560",
    "addr:housenumber":"91",
    "addr:postcode":"3560",
    "addr:street":"Genenbosstraat",
    "iso:country":"BE",
    "sg:address":"Genenbosstraat 91",
    "sg:city":"Lummen",
    "sg:classifiers":[
        {
            "category":"Professional",
            "subcategory":"Computer Services",
            "type":"Services"
        }
    ],
    "sg:phone":"+32 11 45 16 20",
    "sg:postcode":"3560",
    "sg:province":"Limburg",
    "sg:tags":[
        "-",
        "processing",
        "data",
        "software"
    ],
    "wof:name":"Computrac",
    "wof:placetype":"venue"
},
  "geometry": {"coordinates":[5.2383899689,51.0165748596],"type":"Point"}
}