{
  "type": "Feature",
  "properties": {
    "iso:country":"BE",
    "sg:address":"Impasse Lahaut 13",
    "sg:city":"Beyne-heusay",
    "sg:orig_category":"Woningbouw",
    "sg:phone":"+32 4 365 78 04",
    "sg:postcode":"4610",
    "sg:province":"Li\u00e8ge",
    "wof:name":"Termonia",
    "wof:placetype":"venue"
},
  "geometry": {"coordinates":[5.6421098709,50.6249198914],"type":"Point"}
}