{
  "type": "Feature",
  "properties": {
    "iso:country":"BE",
    "sg:address":"Tieltstraat 117b",
    "sg:city":"Pittem",
    "sg:classifiers":[
        {
            "category":"Retail",
            "subcategory":"Veterinary Services",
            "type":"Services"
        }
    ],
    "sg:phone":"+32 51 46 72 38",
    "sg:postcode":"8740",
    "sg:province":"West-Vlaanderen",
    "sg:tags":[
        "veterinarian"
    ],
    "wof:name":"Lafaut G",
    "wof:placetype":"venue"
},
  "geometry": {"coordinates":[3.2769479752,50.9924278259],"type":"Point"}
}