{
  "type": "Feature",
  "properties": {
    "iso:country":"BE",
    "sg:address":"L. Kriegelstraat 38",
    "sg:city":"Huldenberg",
    "sg:orig_category":"Fruitteelt",
    "sg:phone":"+32 16 47 73 35",
    "sg:postcode":"3040",
    "sg:province":"Vlaams-Brabant",
    "wof:name":"Victor Caron",
    "wof:placetype":"venue"
},
  "geometry": {"coordinates":[4.599134922,50.7961463928],"type":"Point"}
}