{
  "type": "Feature",
  "properties": {
    "addr:full":"Genkersteenweg 215 Hasselt Limburg 3500",
    "addr:housenumber":"215",
    "addr:postcode":"3500",
    "addr:street":"Genkersteenweg",
    "iso:country":"BE",
    "sg:address":"Genkersteenweg 215",
    "sg:city":"Hasselt",
    "sg:orig_category":"Babyspullen",
    "sg:phone":"+32 11 23 15 29",
    "sg:postcode":"3500",
    "sg:province":"Limburg",
    "wof:name":"Baby 2000",
    "wof:placetype":"venue"
},
  "geometry": {"coordinates":[5.3801698685,50.9444885254],"type":"Point"}
}