{
  "type": "Feature",
  "properties": {
    "addr:full":"Kreupelstraat 13 Zwevegem West-Vlaanderen 8550",
    "addr:housenumber":"13",
    "addr:postcode":"8550",
    "addr:street":"Kreupelstraat",
    "iso:country":"BE",
    "sg:address":"Kreupelstraat 13",
    "sg:city":"Zwevegem",
    "sg:orig_category":"Eleveurs de bovins",
    "sg:phone":"+32 56 75 51 36",
    "sg:postcode":"8550",
    "sg:province":"West-Vlaanderen",
    "wof:name":"Alain Renard",
    "wof:placetype":"venue"
},
  "geometry": {"coordinates":[3.3338410854,50.7913475037],"type":"Point"}
}