{
  "type": "Feature",
  "properties": {
    "addr:full":"Rue Hamerenne 0 Rochefort Namur 5580",
    "addr:housenumber":"0",
    "addr:postcode":"5580",
    "addr:street":"Rue Hamerenne",
    "iso:country":"BE",
    "sg:address":"Rue Hamerenne 0",
    "sg:city":"Rochefort",
    "sg:orig_category":"M\u00e9decins and sp\u00e9cialistes",
    "sg:phone":"+32 84 21 00 20",
    "sg:postcode":"5580",
    "sg:province":"Namur",
    "wof:name":"J. Marin",
    "wof:placetype":"venue"
},
  "geometry": {"coordinates":[5.2137451172,50.1451377869],"type":"Point"}
}