{
  "type": "Feature",
  "properties": {
    "addr:full":"Frankrijkstraat 11 Temse Oost-Vlaanderen 9140",
    "addr:housenumber":"11",
    "addr:postcode":"9140",
    "addr:street":"Frankrijkstraat",
    "iso:country":"BE",
    "sg:address":"Frankrijkstraat 11",
    "sg:city":"Temse",
    "sg:orig_category":"Non-Classified Establishments",
    "sg:phone":"+32 3 711 25 05",
    "sg:postcode":"9140",
    "sg:province":"Oost-Vlaanderen",
    "wof:name":"Creline Cosmetique",
    "wof:placetype":"venue"
},
  "geometry": {"coordinates":[4.1984901428,51.1405220032],"type":"Point"}
}