{
  "type": "Feature",
  "properties": {
    "addr:full":"Rue Mazeure 31 Sprimont Li\u00e8ge 4140",
    "addr:housenumber":"31",
    "addr:postcode":"4140",
    "addr:street":"Rue Mazeure",
    "iso:country":"BE",
    "sg:address":"Rue Mazeure 31",
    "sg:city":"Sprimont",
    "sg:classifiers":[
        {
            "category":"Real Estate",
            "subcategory":"Architect",
            "type":"Services"
        }
    ],
    "sg:phone":"+32 4 382 20 82",
    "sg:postcode":"4140",
    "sg:province":"Li\u00e8ge",
    "wof:name":"Vo Thanh T",
    "wof:placetype":"venue"
},
  "geometry": {"coordinates":[5.6597499847,50.5072059631],"type":"Point"}
}