{
  "type": "Feature",
  "properties": {
    "iso:country":"BE",
    "sg:address":"Stationsstraat 32",
    "sg:city":"Glabbeek",
    "sg:orig_category":"Varkenskwekers",
    "sg:phone":"+32 16 77 77 97",
    "sg:postcode":"3381",
    "sg:province":"Vlaams-Brabant",
    "wof:name":"Camillus Delaet",
    "wof:placetype":"venue"
},
  "geometry": {"coordinates":[4.953417778,50.886428833],"type":"Point"}
}