{
  "type": "Feature",
  "properties": {
    "addr:full":"Naamsevest 56 Sint-truiden Limburg 3800",
    "addr:housenumber":"56",
    "addr:postcode":"3800",
    "addr:street":"Naamsevest",
    "iso:country":"BE",
    "sg:address":"Naamsevest 56",
    "sg:city":"Sint-truiden",
    "sg:orig_category":"Epiceries",
    "sg:phone":"+32 11 69 27 84",
    "sg:postcode":"3800",
    "sg:province":"Limburg",
    "wof:name":"Jeannine Uytterhaegen",
    "wof:placetype":"venue"
},
  "geometry": {"coordinates":[5.1859350204,50.812412262],"type":"Point"}
}