{
  "type": "Feature",
  "properties": {
    "iso:country":"BE",
    "sg:address":"Rue Joseph-dejardin 25",
    "sg:city":"Li\u00e8ge",
    "sg:classifiers":[
        {
            "category":"Professional",
            "subcategory":"Advertising",
            "type":"Services"
        }
    ],
    "sg:phone":"+32 4 342 78 17",
    "sg:postcode":"4020",
    "sg:province":"Li\u00e8ge",
    "sg:tags":[
        "agency"
    ],
    "wof:name":"Signes S.c.r.l.",
    "wof:placetype":"venue"
},
  "geometry": {"coordinates":[5.5956058502,50.6356391907],"type":"Point"}
}