{
  "type": "Feature",
  "properties": {
    "iso:country":"BE",
    "sg:address":"Kauwensteinlaan 53",
    "sg:city":"Stabroek",
    "sg:orig_category":"Instituts de beaut\u00e9",
    "sg:phone":"+32 3 665 25 68",
    "sg:postcode":"2940",
    "sg:province":"Antwerpen",
    "wof:name":"Alexandra Delforge",
    "wof:placetype":"venue"
},
  "geometry": {"coordinates":[4.3649148941,51.331943512],"type":"Point"}
}