{
  "type": "Feature",
  "properties": {
    "addr:full":"Molenveld 11 Beringen Limburg 3580",
    "addr:housenumber":"11",
    "addr:postcode":"3580",
    "addr:street":"Molenveld",
    "iso:country":"BE",
    "sg:address":"Molenveld 11",
    "sg:city":"Beringen",
    "sg:classifiers":[
        {
            "category":"Building & Trades",
            "subcategory":"Plumbing",
            "type":"Services"
        }
    ],
    "sg:phone":"+32 11 42 23 17",
    "sg:postcode":"3580",
    "sg:province":"Limburg",
    "sg:tags":[
        "contractor"
    ],
    "wof:name":"Hermans M",
    "wof:placetype":"venue"
},
  "geometry": {"coordinates":[5.2272639275,51.0524864197],"type":"Point"}
}