{
  "type": "Feature",
  "properties": {
    "addr:full":"Berendrechtstraat 63 Antwerpen Antwerpen 2020",
    "addr:housenumber":"63",
    "addr:postcode":"2020",
    "addr:street":"Berendrechtstraat",
    "iso:country":"BE",
    "sg:address":"Berendrechtstraat 63",
    "sg:city":"Antwerpen",
    "sg:classifiers":[
        {
            "category":"Personal",
            "subcategory":"Beauty Salon",
            "type":"Services"
        }
    ],
    "sg:phone":"+32 3 238 49 02",
    "sg:postcode":"2020",
    "sg:province":"Antwerpen",
    "sg:tags":[
        "de",
        "coiffure"
    ],
    "wof:name":"Coiffure Urbain",
    "wof:placetype":"venue"
},
  "geometry": {"coordinates":[4.3857898712,51.1866989136],"type":"Point"}
}