{
  "type": "Feature",
  "properties": {
    "addr:full":"Ruelle Cromb\u00e9 17 Court-saint-etienne Brabant Wallon 1490",
    "addr:housenumber":"17;1490",
    "addr:street":"Ruelle Crombe\u0301",
    "iso:country":"BE",
    "sg:address":"Ruelle Cromb\u00e9 17",
    "sg:city":"Court-saint-etienne",
    "sg:classifiers":[
        {
            "category":"Real Estate",
            "subcategory":"Surveying",
            "type":"Services"
        }
    ],
    "sg:phone":"+32 10 61 70 82",
    "sg:postcode":"1490",
    "sg:province":"Brabant Wallon",
    "sg:tags":[
        "surveyor",
        "land"
    ],
    "wof:name":"Hage S",
    "wof:placetype":"venue"
},
  "geometry": {"coordinates":[4.5710067749,50.644657135],"type":"Point"}
}