{
  "type": "Feature",
  "properties": {
    "addr:full":"Reningelstseweg 23 Poperinge West-Vlaanderen 8970",
    "addr:housenumber":"23",
    "addr:postcode":"8970",
    "addr:street":"Reningelstseweg",
    "iso:country":"BE",
    "sg:address":"Reningelstseweg 23",
    "sg:city":"Poperinge",
    "sg:classifiers":[
        {
            "category":"Personal",
            "subcategory":"Beauty Salon",
            "type":"Services"
        }
    ],
    "sg:phone":"+32 57 33 44 49",
    "sg:postcode":"8970",
    "sg:province":"West-Vlaanderen",
    "sg:tags":[
        "lady",
        "-",
        "hairdressing"
    ],
    "wof:name":"Deroo M",
    "wof:placetype":"venue"
},
  "geometry": {"coordinates":[2.7410728931,50.8402786255],"type":"Point"}
}