{
  "type": "Feature",
  "properties": {
    "addr:full":"Rue Louis Hymans 45 Elsene/ixelles Bruxelles-Capitale 1050",
    "addr:housenumber":"45",
    "addr:postcode":"1050",
    "addr:street":"Rue Louis Hymans",
    "iso:country":"BE",
    "sg:address":"Rue Louis Hymans 45",
    "sg:city":"Elsene/ixelles",
    "sg:classifiers":[
        {
            "category":"Insurance",
            "subcategory":"Life Insurance",
            "type":"Services"
        }
    ],
    "sg:phone":"+32 2 345 03 40",
    "sg:postcode":"1050",
    "sg:province":"Bruxelles-Capitale",
    "sg:tags":[
        "assurance"
    ],
    "wof:name":"K. & S. Associates",
    "wof:placetype":"venue"
},
  "geometry": {"coordinates":[4.355659008,50.8173522949],"type":"Point"}
}