{
  "type": "Feature",
  "properties": {
    "addr:full":"Poekstraat 21 Gent Oost-Vlaanderen 9031",
    "addr:housenumber":"21",
    "addr:postcode":"9031",
    "addr:street":"Poekstraat;Oost-Vlaanderen",
    "iso:country":"BE",
    "sg:address":"Poekstraat 21",
    "sg:city":"Gent",
    "sg:orig_category":"Rundveehouders",
    "sg:phone":"+32 9 226 39 62",
    "sg:postcode":"9031",
    "sg:province":"Oost-Vlaanderen",
    "wof:name":"Dossche M. & Stockman R.",
    "wof:placetype":"venue"
},
  "geometry": {"coordinates":[3.6169440746,51.0734596252],"type":"Point"}
}