{
  "type": "Feature",
  "properties": {
    "addr:full":"Oude Pittemstraat 38 Tielt West-Vlaanderen 8700",
    "addr:housenumber":"38",
    "addr:postcode":"8700",
    "addr:street":"Oude Pittemstraat",
    "iso:country":"BE",
    "sg:address":"Oude Pittemstraat 38",
    "sg:city":"Tielt",
    "sg:classifiers":[
        {
            "category":"Arena",
            "subcategory":"Sports Club",
            "type":"Entertainment"
        }
    ],
    "sg:phone":"+32 51 40 36 22",
    "sg:postcode":"8700",
    "sg:province":"West-Vlaanderen",
    "sg:tags":[
        "terrain",
        "hors",
        "de",
        "installation",
        "sportifs"
    ],
    "wof:name":"K.f.c. Tielt",
    "wof:placetype":"venue"
},
  "geometry": {"coordinates":[3.3158431053,50.9957046509],"type":"Point"}
}