{
  "type": "Feature",
  "properties": {
    "addr:full":"Tieltsteenweg 117 Oostrozebeke West-Vlaanderen 8780",
    "addr:housenumber":"117",
    "addr:postcode":"8780",
    "addr:street":"Tieltsteenweg",
    "iso:country":"BE",
    "sg:address":"Tieltsteenweg 117",
    "sg:city":"Oostrozebeke",
    "sg:classifiers":[
        {
            "category":"Retail",
            "subcategory":"Veterinary Services",
            "type":"Services"
        }
    ],
    "sg:phone":"+32 56 66 49 94",
    "sg:postcode":"8780",
    "sg:province":"West-Vlaanderen",
    "sg:tags":[
        "veterinarian"
    ],
    "wof:name":"Landuyt J",
    "wof:placetype":"venue"
},
  "geometry": {"coordinates":[3.3319900036,50.9330825806],"type":"Point"}
}