{
  "type": "Feature",
  "properties": {
    "addr:full":"Hoogveldstraat 43 Herent Vlaams-Brabant 3020",
    "addr:housenumber":"43",
    "addr:postcode":"3020",
    "addr:street":"Hoogveldstraat",
    "iso:country":"BE",
    "sg:address":"Hoogveldstraat 43",
    "sg:city":"Herent",
    "sg:orig_category":"Huishoudapparaten, televisies and radio's",
    "sg:phone":"+32 16 48 87 49",
    "sg:postcode":"3020",
    "sg:province":"Vlaams-Brabant",
    "wof:name":"Guy Dehaeseleer",
    "wof:placetype":"venue"
},
  "geometry": {"coordinates":[4.6749200821,50.9079055786],"type":"Point"}
}