{
  "type": "Feature",
  "properties": {
    "addr:full":"Kasteelpleinstraat 31 Antwerpen Antwerpen 2000",
    "addr:housenumber":"31",
    "addr:postcode":"2000",
    "addr:street":"Kasteelpleinstraat",
    "iso:country":"BE",
    "sg:address":"Kasteelpleinstraat 31",
    "sg:city":"Antwerpen",
    "sg:classifiers":[
        {
            "category":"Education",
            "subcategory":"School",
            "type":"Public Place"
        }
    ],
    "sg:phone":"+32 3 231 81 88",
    "sg:postcode":"2000",
    "sg:province":"Antwerpen",
    "sg:tags":[
        "secondary"
    ],
    "wof:name":"Sint-lievenscollege",
    "wof:placetype":"venue"
},
  "geometry": {"coordinates":[4.4018001556,51.2106971741],"type":"Point"}
}