{
  "type": "Feature",
  "properties": {
    "iso:country":"BE",
    "sg:address":"Begijnendijksesteenweg 103",
    "sg:city":"Herselt (ramsel)",
    "sg:classifiers":[
        {
            "category":"Professional",
            "subcategory":"Art Services",
            "type":"Services"
        }
    ],
    "sg:phone":"+32 16 77 27 74",
    "sg:postcode":"2230",
    "sg:province":"Antwerpen",
    "sg:tags":[
        "graphic",
        "designer"
    ],
    "wof:name":"Graf X Be",
    "wof:placetype":"venue"
},
  "geometry": {"coordinates":[4.8093352318,51.0251922607],"type":"Point"}
}