{
  "type": "Feature",
  "properties": {
    "iso:country":"BE",
    "sg:address":"Marvie 104",
    "sg:city":"Bastogne",
    "sg:orig_category":"Eleveurs de bovins",
    "sg:phone":"+32 61 21 15 57",
    "sg:postcode":"6600",
    "sg:province":"Luxembourg",
    "wof:name":"Annet E. Et Conrard M.p.",
    "wof:placetype":"venue"
},
  "geometry": {"coordinates":[5.745426178,49.9854393005],"type":"Point"}
}