{
  "type": "Feature",
  "properties": {
    "addr:full":"Avennesdreef 32 Gent Oost-Vlaanderen 9031",
    "addr:housenumber":"32",
    "addr:postcode":"9031",
    "addr:street":"Avennesdreef;Oost-Vlaanderen",
    "iso:country":"BE",
    "sg:address":"Avennesdreef 32",
    "sg:city":"Gent",
    "sg:orig_category":"Informaticaconsulenten",
    "sg:phone":"+32 9 227 15 89",
    "sg:postcode":"9031",
    "sg:province":"Oost-Vlaanderen",
    "wof:name":"Technology Manag. & Cons.",
    "wof:placetype":"venue"
},
  "geometry": {"coordinates":[3.6359500885,51.0665512085],"type":"Point"}
}