{
  "type": "Feature",
  "properties": {
    "addr:full":"Turnhoutsebaan 278 Schilde Antwerpen 2970",
    "addr:housenumber":"278",
    "addr:postcode":"2970",
    "addr:street":"Turnhoutsebaan",
    "iso:country":"BE",
    "sg:address":"Turnhoutsebaan 278",
    "sg:city":"Schilde",
    "sg:classifiers":[
        {
            "category":"Shopping",
            "subcategory":"Musical Instruments",
            "type":"Retail Goods"
        }
    ],
    "sg:phone":"+32 3 383 04 51",
    "sg:postcode":"2970",
    "sg:province":"Antwerpen",
    "sg:tags":[
        "piano",
        "-",
        "tuning"
    ],
    "wof:name":"Jageneau Muziekhandel Nv",
    "wof:placetype":"venue"
},
  "geometry": {"coordinates":[4.5818901062,51.2400970459],"type":"Point"}
}