{
  "type": "Feature",
  "properties": {
    "iso:country":"BE",
    "sg:address":"Zur Held 9",
    "sg:city":"B\u00fctgenbach (elsenborn)",
    "sg:classifiers":[
        {
            "category":"Real Estate",
            "subcategory":"Architect",
            "type":"Services"
        }
    ],
    "sg:phone":"+32 80 44 60 67",
    "sg:postcode":"4750",
    "sg:province":"Li\u00e8ge",
    "wof:name":"Boemer J",
    "wof:placetype":"venue"
},
  "geometry": {"coordinates":[6.2012000084,50.4238090515],"type":"Point"}
}