{
  "type": "Feature",
  "properties": {
    "iso:country":"BE",
    "sg:address":"Schoonheidsleerlaan 9",
    "sg:city":"Bredene",
    "sg:orig_category":"Enseignement maternel and primaire",
    "sg:phone":"+32 59 32 28 18",
    "sg:postcode":"8450",
    "sg:province":"West-Vlaanderen",
    "wof:name":"B.s.g.o. Groenendijk",
    "wof:placetype":"venue"
},
  "geometry": {"coordinates":[2.9496190548,51.2415771484],"type":"Point"}
}