{
  "type": "Feature",
  "properties": {
    "addr:full":"Meir 39 Laakdal Antwerpen 2430",
    "addr:housenumber":"39",
    "addr:postcode":"2430",
    "addr:street":"Meir",
    "iso:country":"BE",
    "sg:address":"Meir 39",
    "sg:city":"Laakdal",
    "sg:orig_category":"Kapsalons",
    "sg:phone":"+32 14 86 63 75",
    "sg:postcode":"2430",
    "sg:province":"Antwerpen",
    "wof:name":"Coiffure Luc",
    "wof:placetype":"venue"
},
  "geometry": {"coordinates":[4.9971299171,51.1007118225],"type":"Point"}
}