{
  "type": "Feature",
  "properties": {
    "iso:country":"BE",
    "sg:address":"Chauss\u00c9e D'alsemberg 621",
    "sg:city":"Ukkel/uccle",
    "sg:classifiers":[
        {
            "category":"Cafe",
            "type":"Food & Drink"
        }
    ],
    "sg:phone":"+32 2 344 34 55",
    "sg:postcode":"1180",
    "sg:province":"Bruxelles-Capitale",
    "sg:tags":[
        "caf\u00e9s"
    ],
    "wof:name":"Au Vieux Spijtigen Duivel",
    "wof:placetype":"venue"
},
  "geometry": {"coordinates":[4.336689949,50.8079414368],"type":"Point"}
}