{
  "type": "Feature",
  "properties": {
    "iso:country":"BE",
    "sg:address":"Rue Du Cimeti\u00c8re 46",
    "sg:city":"Aubange",
    "sg:orig_category":"Services fun\u00e9raires",
    "sg:phone":"+32 63 67 74 31",
    "sg:postcode":"6792",
    "sg:province":"Luxembourg",
    "wof:name":"Fun\u00c9railles Bentz",
    "wof:placetype":"venue"
},
  "geometry": {"coordinates":[5.7446508408,49.5618133545],"type":"Point"}
}