{
  "type": "Feature",
  "properties": {
    "iso:country":"BE",
    "sg:address":"Rue Marie-christine 98",
    "sg:city":"Brussel/bruxelles",
    "sg:orig_category":"Pain, p\u00e2tisseries and confiseries",
    "sg:phone":"+32 2 425 53 38",
    "sg:postcode":"1020",
    "sg:province":"Bruxelles-Capitale",
    "wof:name":"Fatiha Bendadou",
    "wof:placetype":"venue"
},
  "geometry": {"coordinates":[4.3547887802,50.8750152588],"type":"Point"}
}