{
  "type": "Feature",
  "properties": {
    "addr:full":"Priesterage 13 Sint-martens-latem Oost-Vlaanderen 9830",
    "addr:housenumber":"13",
    "addr:postcode":"9830",
    "addr:street":"Priesterage",
    "iso:country":"BE",
    "sg:address":"Priesterage 13",
    "sg:city":"Sint-martens-latem",
    "sg:classifiers":[
        {
            "category":"Health Services",
            "subcategory":"Nursing And Care Facility",
            "type":"Services"
        }
    ],
    "sg:phone":"+32 9 282 78 36",
    "sg:postcode":"9830",
    "sg:province":"Oost-Vlaanderen",
    "sg:tags":[
        "public"
    ],
    "wof:name":"O.c.m.w.",
    "wof:placetype":"venue"
},
  "geometry": {"coordinates":[3.635684967,51.0186080933],"type":"Point"}
}