{
  "type": "Feature",
  "properties": {
    "iso:country":"BE",
    "sg:address":"Beenhouwersstraat 115",
    "sg:city":"Brugge",
    "sg:orig_category":"Equipement photographique",
    "sg:phone":"+32 50 33 40 01",
    "sg:postcode":"8000",
    "sg:province":"West-Vlaanderen",
    "wof:name":"Georges Manertz",
    "wof:placetype":"venue"
},
  "geometry": {"coordinates":[3.2148349285,51.2112121582],"type":"Point"}
}