{
  "type": "Feature",
  "properties": {
    "iso:country":"BE",
    "sg:address":"Chauss\u00e9e De Ch\u00e2telet 174",
    "sg:city":"Charleroi (gilly)",
    "sg:classifiers":[
        {
            "category":"Arts & Performance",
            "subcategory":"Music",
            "type":"Entertainment"
        }
    ],
    "sg:phone":"+32 71 42 32 03",
    "sg:postcode":"6060",
    "sg:province":"Hainaut",
    "sg:tags":[
        "disc-jockeys"
    ],
    "wof:name":"Psb Sonorisation",
    "wof:placetype":"venue"
},
  "geometry": {"coordinates":[4.4880981445,50.4251937866],"type":"Point"}
}