{
  "type": "Feature",
  "properties": {
    "addr:full":"Rue De Saint-amand 183 Peruwelz Hainaut 7600",
    "addr:housenumber":"183",
    "addr:postcode":"7600",
    "addr:street":"Rue De Saint-Amand;Hainaut",
    "iso:country":"BE",
    "sg:address":"Rue De Saint-amand 183",
    "sg:city":"Peruwelz",
    "sg:orig_category":"Charpentes and couvertures",
    "sg:phone":"+32 69 77 14 71",
    "sg:postcode":"7600",
    "sg:province":"Hainaut",
    "wof:name":"Rene Younsi",
    "wof:placetype":"venue"
},
  "geometry": {"coordinates":[3.5933160782,50.4918289185],"type":"Point"}
}