{
  "type": "Feature",
  "properties": {
    "addr:full":"Malosewaver 77 Geel Antwerpen 2440",
    "addr:housenumber":"77",
    "addr:postcode":"2440",
    "addr:street":"Malosewaver",
    "iso:country":"BE",
    "sg:address":"Malosewaver 77",
    "sg:city":"Geel",
    "sg:classifiers":[
        {
            "category":"Retail",
            "subcategory":"Auto Repair",
            "type":"Services"
        }
    ],
    "sg:phone":"+32 14 58 95 14",
    "sg:postcode":"2440",
    "sg:province":"Antwerpen",
    "sg:tags":[
        "garage"
    ],
    "wof:name":"Nova",
    "wof:placetype":"venue"
},
  "geometry": {"coordinates":[5.0280637741,51.1553421021],"type":"Point"}
}