{
  "type": "Feature",
  "properties": {
    "addr:full":"Sint-trudoplein 14 Houthalen-helchteren (helchteren) Limburg 3530",
    "addr:housenumber":"14",
    "addr:postcode":"3530",
    "addr:street":"Sint-Trudoplein",
    "iso:country":"BE",
    "sg:address":"Sint-trudoplein 14",
    "sg:city":"Houthalen-helchteren (helchteren)",
    "sg:classifiers":[
        {
            "category":"Health Services",
            "subcategory":"Hospital",
            "type":"Services"
        }
    ],
    "sg:phone":"+32 11 52 20 47",
    "sg:postcode":"3530",
    "sg:province":"Limburg",
    "wof:name":"Thuisgezondheidszorg Midden Limburg Vzw",
    "wof:placetype":"venue"
},
  "geometry": {"coordinates":[5.3719201088,51.0310020447],"type":"Point"}
}