{
  "type": "Feature",
  "properties": {
    "addr:full":"Avenue Louise 19 Bruxelles (ixelles) Bruxelles-Capitale 1050",
    "addr:housenumber":"19",
    "addr:postcode":"1050",
    "addr:street":"Avenue Louise",
    "iso:country":"BE",
    "sg:address":"Avenue Louise 19",
    "sg:city":"Bruxelles (ixelles)",
    "sg:classifiers":[
        {
            "category":"Shopping",
            "subcategory":"Clothing, Apparel, & Fashions",
            "type":"Retail Goods"
        }
    ],
    "sg:phone":"+32 2 538 36 61",
    "sg:postcode":"1050",
    "sg:province":"Bruxelles-Capitale",
    "sg:tags":[
        "lady",
        "clothing",
        "-"
    ],
    "wof:name":"Maxmara",
    "wof:placetype":"venue"
},
  "geometry": {"coordinates":[4.3560500145,50.8346443176],"type":"Point"}
}