{
  "type": "Feature",
  "properties": {
    "iso:country":"BE",
    "sg:address":"Rue Verte Voie 1ba",
    "sg:city":"Ciney",
    "sg:orig_category":"Alternatieve geneeskunde",
    "sg:phone":"+32 477 32 95 39",
    "sg:postcode":"5590",
    "sg:province":"Namur",
    "wof:name":"Au Centre St.hubert",
    "wof:placetype":"venue"
},
  "geometry": {"coordinates":[5.1071810722,50.2937583923],"type":"Point"}
}