{
  "type": "Feature",
  "properties": {
    "iso:country":"BE",
    "sg:address":"Binnensteenweg 180",
    "sg:city":"Boechout",
    "sg:classifiers":[
        {
            "category":"Organizations",
            "subcategory":"Professional Association",
            "type":"Services"
        }
    ],
    "sg:phone":"+32 3 460 02 31",
    "sg:postcode":"2530",
    "sg:province":"Antwerpen",
    "sg:tags":[
        "trade-union",
        "federation"
    ],
    "wof:name":"E S F",
    "wof:placetype":"venue"
},
  "geometry": {"coordinates":[4.4913258553,51.1665878296],"type":"Point"}
}