{
  "type": "Feature",
  "properties": {
    "iso:country":"BE",
    "sg:address":"Route Charlemagne 23",
    "sg:city":"Florennes",
    "sg:orig_category":"Benzinestations and brandstoffen Loodgieterij, verwarming and sanitaire installaties",
    "sg:phone":"+32 82 68 83 75",
    "sg:postcode":"5620",
    "sg:province":"Namur",
    "wof:name":"Jean-louis Valtin",
    "wof:placetype":"venue"
},
  "geometry": {"coordinates":[4.6845178604,50.2334823608],"type":"Point"}
}