{
  "type": "Feature",
  "properties": {
    "addr:full":"Rue Du Panier-vert 74 Nivelles Brabant Wallon 1400",
    "addr:housenumber":"74",
    "addr:postcode":"1400",
    "addr:street":"Rue Du Panier-Vert",
    "iso:country":"BE",
    "sg:address":"Rue Du Panier-vert 74",
    "sg:city":"Nivelles",
    "sg:orig_category":"Postkantoren Verzekeringsmakelaars and experts",
    "sg:phone":"+32 67 89 38 40",
    "sg:postcode":"1400",
    "sg:province":"Brabant Wallon",
    "wof:name":"La Poste",
    "wof:placetype":"venue"
},
  "geometry": {"coordinates":[4.3049898148,50.592250824],"type":"Point"}
}