{
  "type": "Feature",
  "properties": {
    "addr:full":"Rue De Bruxelles 43 Wavre Brabant Wallon 1300",
    "addr:housenumber":"43;1300",
    "addr:street":"Rue De Bruxelles",
    "iso:country":"BE",
    "sg:address":"Rue De Bruxelles 43",
    "sg:city":"Wavre",
    "sg:orig_category":"Kapsalons",
    "sg:phone":"+32 10 22 65 13",
    "sg:postcode":"1300",
    "sg:province":"Brabant Wallon",
    "wof:name":"France Mairesse",
    "wof:placetype":"venue"
},
  "geometry": {"coordinates":[4.613049984,50.7185134888],"type":"Point"}
}