{
  "type": "Feature",
  "properties": {
    "iso:country":"BE",
    "sg:address":"Leon Spillaertstraat 91b2",
    "sg:city":"Oostende",
    "sg:orig_category":"Services de recherches and bureaux de d\u00e9tectives",
    "sg:phone":"+32 59 43 42 41",
    "sg:postcode":"8400",
    "sg:province":"West-Vlaanderen",
    "wof:name":"Patrick De Pauw",
    "wof:placetype":"venue"
},
  "geometry": {"coordinates":[2.9139609337,51.2261772156],"type":"Point"}
}