{
  "type": "Feature",
  "properties": {
    "iso:country":"BE",
    "sg:address":"Collaertplein 21",
    "sg:city":"Ieper",
    "sg:orig_category":"Agences d\u00b4interim and personnel temporaire",
    "sg:phone":"+32 57 21 64 00",
    "sg:postcode":"8900",
    "sg:province":"West-Vlaanderen",
    "wof:name":"Adecco",
    "wof:placetype":"venue"
},
  "geometry": {"coordinates":[2.8782069683,50.8490524292],"type":"Point"}
}