{
  "type": "Feature",
  "properties": {
    "addr:full":"Roosbeekstraat 52 Sint-truiden Limburg 3800",
    "addr:housenumber":"52",
    "addr:postcode":"3800",
    "addr:street":"Roosbeekstraat",
    "iso:country":"BE",
    "sg:address":"Roosbeekstraat 52",
    "sg:city":"Sint-truiden",
    "sg:orig_category":"Landbouwmachines Gh",
    "sg:phone":"+32 11 68 44 10",
    "sg:postcode":"3800",
    "sg:province":"Limburg",
    "wof:name":"Fa. Nicolai",
    "wof:placetype":"venue"
},
  "geometry": {"coordinates":[5.2644920349,50.8347320557],"type":"Point"}
}