{
  "type": "Feature",
  "properties": {
    "iso:country":"BE",
    "sg:address":"Wolfstraat 7",
    "sg:city":"Lanaken",
    "sg:orig_category":"Forge, Moulage and Profilage des M\u00e9taux. Traitement and rev\u00eatement des m\u00e9taux",
    "sg:phone":"+32 89 73 27 16",
    "sg:postcode":"3620",
    "sg:province":"Limburg",
    "wof:name":"Vanderhoven",
    "wof:placetype":"venue"
},
  "geometry": {"coordinates":[5.6636967659,50.8868522644],"type":"Point"}
}