{
  "type": "Feature",
  "properties": {
    "iso:country":"BE",
    "sg:address":"Kapellensteenweg 203",
    "sg:city":"Kalmthout",
    "sg:classifiers":[
        {
            "category":"Banks & Credit Unions",
            "subcategory":"Bank",
            "type":"Services"
        }
    ],
    "sg:phone":"+32 3 666 73 65",
    "sg:postcode":"2920",
    "sg:province":"Antwerpen",
    "sg:tags":[
        "savings-banks"
    ],
    "wof:name":"Saint-pol-de Leeuw Bvba",
    "wof:placetype":"venue"
},
  "geometry": {"coordinates":[4.4750981331,51.3805274963],"type":"Point"}
}