{
  "type": "Feature",
  "properties": {
    "addr:full":"R.ramlotstraat 66 Dendermonde Oost-Vlaanderen 9200",
    "addr:housenumber":"66",
    "addr:postcode":"9200",
    "addr:street":"R.Ramlotstraat;Oost-Vlaanderen",
    "iso:country":"BE",
    "sg:address":"R.ramlotstraat 66",
    "sg:city":"Dendermonde",
    "sg:classifiers":[
        {
            "category":"Insurance",
            "subcategory":"Life Insurance",
            "type":"Services"
        }
    ],
    "sg:phone":"+32 52 21 36 92",
    "sg:postcode":"9200",
    "sg:province":"Oost-Vlaanderen",
    "sg:tags":[
        "assurance"
    ],
    "wof:name":"De Batselier",
    "wof:placetype":"venue"
},
  "geometry": {"coordinates":[4.0983099937,51.0315208435],"type":"Point"}
}