{
  "type": "Feature",
  "properties": {
    "addr:full":"Posthoornstraat 6 Aalst Oost-Vlaanderen 9300",
    "addr:housenumber":"6",
    "addr:postcode":"9300",
    "addr:street":"Posthoornstraat",
    "iso:country":"BE",
    "sg:address":"Posthoornstraat 6",
    "sg:city":"Aalst",
    "sg:classifiers":[
        {
            "category":"Health Services",
            "subcategory":"Doctor",
            "type":"Services"
        }
    ],
    "sg:phone":"+32 53 78 34 65",
    "sg:postcode":"9300",
    "sg:province":"Oost-Vlaanderen",
    "sg:tags":[
        "medicinephysicians",
        "surgeon"
    ],
    "wof:name":"Degrande J F",
    "wof:placetype":"venue"
},
  "geometry": {"coordinates":[4.0270137787,50.9369277954],"type":"Point"}
}