{
  "type": "Feature",
  "properties": {
    "addr:full":"Oude Beurs 23 Antwerpen Antwerpen 2000",
    "addr:housenumber":"23",
    "addr:postcode":"2000",
    "addr:street":"Oude Beurs",
    "iso:country":"BE",
    "sg:address":"Oude Beurs 23",
    "sg:city":"Antwerpen",
    "sg:classifiers":[
        {
            "category":"Personal",
            "subcategory":"Shoe Repair & Shine",
            "type":"Services"
        }
    ],
    "sg:phone":"+32 3 232 00 61",
    "sg:postcode":"2000",
    "sg:province":"Antwerpen",
    "sg:tags":[
        "shoemaker"
    ],
    "wof:name":"Hamels L",
    "wof:placetype":"venue"
},
  "geometry": {"coordinates":[4.4003958702,51.2221908569],"type":"Point"}
}