{
  "type": "Feature",
  "properties": {
    "addr:full":"Statiestraat 41 Zwijndrecht Antwerpen 2070",
    "addr:housenumber":"41",
    "addr:postcode":"2070",
    "addr:street":"Statiestraat",
    "iso:country":"BE",
    "sg:address":"Statiestraat 41",
    "sg:city":"Zwijndrecht",
    "sg:classifiers":[
        {
            "category":"Insurance",
            "subcategory":"Life Insurance",
            "type":"Services"
        }
    ],
    "sg:phone":"+32 3 253 20 96",
    "sg:postcode":"2070",
    "sg:province":"Antwerpen",
    "sg:tags":[
        "assurance"
    ],
    "wof:name":"Van Remoortere-malschaert",
    "wof:placetype":"venue"
},
  "geometry": {"coordinates":[4.3272938728,51.2176208496],"type":"Point"}
}