{
  "type": "Feature",
  "properties": {
    "addr:full":"Couloury 1 Verviers Li\u00e8ge 4800",
    "addr:housenumber":"1",
    "addr:postcode":"4800",
    "addr:street":"Couloury",
    "iso:country":"BE",
    "sg:address":"Couloury 1",
    "sg:city":"Verviers",
    "sg:orig_category":"Mat\u00e9riel de contr\u00f4le des processus industriels Fab",
    "sg:phone":"+32 87 39 42 40",
    "sg:postcode":"4800",
    "sg:province":"Li\u00e8ge",
    "wof:name":"Tech - Nobel",
    "wof:placetype":"venue"
},
  "geometry": {"coordinates":[5.8594508171,50.5917663574],"type":"Point"}
}