{
  "type": "Feature",
  "properties": {
    "addr:full":"Warandewegel 13 Sint-gillis-waas Oost-Vlaanderen 9170",
    "addr:housenumber":"13",
    "addr:postcode":"9170",
    "addr:street":"Warandewegel",
    "iso:country":"BE",
    "sg:address":"Warandewegel 13",
    "sg:city":"Sint-gillis-waas",
    "sg:orig_category":"Woningbouw",
    "sg:phone":"+32 3 770 62 98",
    "sg:postcode":"9170",
    "sg:province":"Oost-Vlaanderen",
    "wof:name":"De Warande",
    "wof:placetype":"venue"
},
  "geometry": {"coordinates":[4.1062459946,51.2617225647],"type":"Point"}
}