{
  "type": "Feature",
  "properties": {
    "addr:full":"Kloosterstraat 33 Sint-gillis-waas Oost-Vlaanderen 9170",
    "addr:housenumber":"33",
    "addr:postcode":"9170",
    "addr:street":"Kloosterstraat",
    "iso:country":"BE",
    "sg:address":"Kloosterstraat 33",
    "sg:city":"Sint-gillis-waas",
    "sg:orig_category":"Installation \u00e9lectrique r\u00e9sidentielle",
    "sg:phone":"+32 3 773 30 54",
    "sg:postcode":"9170",
    "sg:province":"Oost-Vlaanderen",
    "wof:name":"Koenraad De Tobel",
    "wof:placetype":"venue"
},
  "geometry": {"coordinates":[4.1521658897,51.2610816956],"type":"Point"}
}