{
  "type": "Feature",
  "properties": {
    "iso:country":"BE",
    "sg:address":"Bierbeekstraat 22",
    "sg:city":"Oud-heverlee (blanden)",
    "sg:classifiers":[
        {
            "category":"Home & Garden",
            "subcategory":"Carpets & Floor Coverings",
            "type":"Retail Goods"
        }
    ],
    "sg:phone":"+32 16 40 26 94",
    "sg:postcode":"3052",
    "sg:province":"Vlaams-Brabant",
    "sg:tags":[
        "tile"
    ],
    "wof:name":"Dupont R",
    "wof:placetype":"venue"
},
  "geometry": {"coordinates":[4.7063660622,50.825881958],"type":"Point"}
}