{
  "type": "Feature",
  "properties": {
    "addr:full":"Rue Chisaire 12 Mons Hainaut 7000",
    "addr:housenumber":"12",
    "addr:postcode":"7000",
    "addr:street":"Rue Chisaire;Hainaut",
    "iso:country":"BE",
    "sg:address":"Rue Chisaire 12",
    "sg:city":"Mons",
    "sg:orig_category":"Non-Classified Establishments",
    "sg:phone":"+32 65 39 90 33",
    "sg:postcode":"7000",
    "sg:province":"Hainaut",
    "wof:name":"Orchel Belgium Sa",
    "wof:placetype":"venue"
},
  "geometry": {"coordinates":[3.9431180954,50.4521369934],"type":"Point"}
}