{
  "type": "Feature",
  "properties": {
    "iso:country":"BE",
    "sg:address":"Rue De Fragn\u00e9e 169",
    "sg:city":"Li\u00e8ge 1",
    "sg:classifiers":[
        {
            "category":"Cafe",
            "type":"Food & Drink"
        }
    ],
    "sg:phone":"+32 4 253 62 88",
    "sg:postcode":"4000",
    "sg:province":"Li\u00e8ge",
    "sg:tags":[
        "snack-bars"
    ],
    "wof:name":"Efes Pita",
    "wof:placetype":"venue"
},
  "geometry": {"coordinates":[5.5735049248,50.621257782],"type":"Point"}
}