{
  "type": "Feature",
  "properties": {
    "iso:country":"BE",
    "sg:address":"Livornostraat 86",
    "sg:city":"Brussel/bruxelles",
    "sg:orig_category":"Beautyfarms, relaxatie and lichamelijk welzijn",
    "sg:phone":"+32 2 534 20 74",
    "sg:postcode":"1000",
    "sg:province":"Bruxelles-Capitale",
    "wof:name":"Le Lagon",
    "wof:placetype":"venue"
},
  "geometry": {"coordinates":[4.3609848022,50.8283004761],"type":"Point"}
}