{
  "type": "Feature",
  "properties": {
    "iso:country":"BE",
    "sg:address":"Avenue Edmond Leburton 96-2",
    "sg:city":"Waremme",
    "sg:classifiers":[
        {
            "category":"Real Estate",
            "subcategory":"Real Estate Services",
            "type":"Services"
        }
    ],
    "sg:phone":"+32 19 33 25 80",
    "sg:postcode":"4300",
    "sg:province":"Li\u00e8ge",
    "sg:tags":[
        "-",
        "abroad"
    ],
    "wof:name":"Bureau Immobilier Frederic Renier",
    "wof:placetype":"venue"
},
  "geometry": {"coordinates":[5.2607097626,50.698059082],"type":"Point"}
}