{
  "type": "Feature",
  "properties": {
    "addr:full":"Place De L\u00b4europe 5 Ottignies-louvain-la-neuve Brabant Wallon 1342",
    "addr:housenumber":"5",
    "addr:postcode":"1342",
    "addr:street":"Place De L\u00b4Europe",
    "iso:country":"BE",
    "sg:address":"Place De L\u00b4europe 5",
    "sg:city":"Ottignies-louvain-la-neuve",
    "sg:orig_category":"Installation \u00e9lectrique r\u00e9sidentielle",
    "sg:phone":"+32 10 41 28 43",
    "sg:postcode":"1342",
    "sg:province":"Brabant Wallon",
    "wof:name":"F M Fusion",
    "wof:placetype":"venue"
},
  "geometry": {"coordinates":[4.5682549477,50.6845550537],"type":"Point"}
}