{
  "type": "Feature",
  "properties": {
    "addr:full":"Dorpsstraat 66 Staden (westrozebeke) West-Vlaanderen 8840",
    "addr:housenumber":"66",
    "addr:postcode":"8840",
    "addr:street":"Dorpsstraat",
    "iso:country":"BE",
    "sg:address":"Dorpsstraat 66",
    "sg:city":"Staden (westrozebeke)",
    "sg:classifiers":[
        {
            "category":"Wholesale",
            "subcategory":"Meat",
            "type":"Manufacturing & Wholesale Goods"
        }
    ],
    "sg:phone":"+32 51 78 84 00",
    "sg:postcode":"8840",
    "sg:province":"West-Vlaanderen",
    "sg:tags":[
        "whol",
        "-"
    ],
    "wof:name":"Westvlees",
    "wof:placetype":"venue"
},
  "geometry": {"coordinates":[3.0118439198,50.9314956665],"type":"Point"}
}