{
  "type": "Feature",
  "properties": {
    "iso:country":"BE",
    "sg:address":"Boulevard Sylvain Dupuis 1",
    "sg:city":"Bruxelles (anderlecht)",
    "sg:classifiers":[
        {
            "category":"Restaurant",
            "type":"Food & Drink"
        }
    ],
    "sg:phone":"+32 2 520 29 65",
    "sg:postcode":"1070",
    "sg:province":"Bruxelles-Capitale",
    "wof:name":"Pizza Bottega",
    "wof:placetype":"venue"
},
  "geometry": {"coordinates":[4.3047909737,50.8377113342],"type":"Point"}
}