{
  "type": "Feature",
  "properties": {
    "addr:full":"Rue Reine Astrid 67 Sambreville Namur 5060",
    "addr:housenumber":"67",
    "addr:postcode":"5060",
    "addr:street":"Rue Reine Astrid",
    "iso:country":"BE",
    "sg:address":"Rue Reine Astrid 67",
    "sg:city":"Sambreville",
    "sg:orig_category":"Paramedische behandelingen",
    "sg:phone":"+32 71 81 77 81",
    "sg:postcode":"5060",
    "sg:province":"Namur",
    "wof:name":"P. Jonnart",
    "wof:placetype":"venue"
},
  "geometry": {"coordinates":[4.5912208557,50.4631767273],"type":"Point"}
}