{
  "type": "Feature",
  "properties": {
    "iso:country":"BE",
    "sg:address":"Weversberg 38",
    "sg:city":"Meerhout",
    "sg:classifiers":[
        {
            "category":"Cafe",
            "type":"Food & Drink"
        }
    ],
    "sg:phone":"+32 14 30 85 70",
    "sg:postcode":"2450",
    "sg:province":"Antwerpen",
    "sg:tags":[
        "caf\u00e9s"
    ],
    "wof:name":"Jeanne Dello",
    "wof:placetype":"venue"
},
  "geometry": {"coordinates":[5.085873127,51.130695343],"type":"Point"}
}