{
  "type": "Feature",
  "properties": {
    "iso:country":"BE",
    "sg:address":"Spoorwegstraat 12",
    "sg:city":"Brugge",
    "sg:orig_category":"Hoger onderwijs",
    "sg:phone":"+32 50 40 51 20",
    "sg:postcode":"8200",
    "sg:province":"West-Vlaanderen",
    "wof:name":"Khbo-dep. Gezondheidszorg",
    "wof:placetype":"venue"
},
  "geometry": {"coordinates":[3.2162430286,51.1959228516],"type":"Point"}
}