{
  "type": "Feature",
  "properties": {
    "addr:full":"Rue Hector Denis 155 Box 23 Charleroi (dampremy) Hainaut 6020",
    "addr:housenumber":"155 box 23",
    "addr:postcode":"6020",
    "addr:street":"Rue Hector Denis",
    "iso:country":"BE",
    "sg:address":"Rue Hector Denis 155 Box 23",
    "sg:city":"Charleroi (dampremy)",
    "sg:classifiers":[
        {
            "category":"Health Services",
            "subcategory":"Health Practitioner",
            "type":"Services"
        }
    ],
    "sg:phone":"+32 71 32 38 99",
    "sg:postcode":"6020",
    "sg:province":"Hainaut",
    "sg:tags":[
        "therapist",
        "speech"
    ],
    "wof:name":"Hellin Ch",
    "wof:placetype":"venue"
},
  "geometry": {"coordinates":[4.4354348183,50.4227638245],"type":"Point"}
}