{
  "type": "Feature",
  "properties": {
    "addr:full":"Nattenhaasdonkstraat 13 Bornem Antwerpen 2880",
    "addr:housenumber":"13",
    "addr:postcode":"2880",
    "addr:street":"Nattenhaasdonkstraat",
    "iso:country":"BE",
    "sg:address":"Nattenhaasdonkstraat 13",
    "sg:city":"Bornem",
    "sg:orig_category":"Mus\u00e9es and patrimoine culturel",
    "sg:phone":"+32 3 889 18 47",
    "sg:postcode":"2880",
    "sg:province":"Antwerpen",
    "wof:name":"Havesdonckhoeve",
    "wof:placetype":"venue"
},
  "geometry": {"coordinates":[4.242205143,51.0998497009],"type":"Point"}
}