{
  "type": "Feature",
  "properties": {
    "iso:country":"BE",
    "sg:address":"Kaplotestraat 10",
    "sg:city":"Wingene",
    "sg:classifiers":[
        {
            "category":"Farming",
            "subcategory":"Livestock Farm",
            "type":"Manufacturing & Wholesale Goods"
        }
    ],
    "sg:phone":"+32 51 65 54 60",
    "sg:postcode":"8750",
    "sg:province":"West-Vlaanderen",
    "sg:tags":[
        "breeding",
        "agriculture",
        "animal"
    ],
    "wof:name":"Mevr Maria Verhamme",
    "wof:placetype":"venue"
},
  "geometry": {"coordinates":[3.2817919254,51.0574150085],"type":"Point"}
}