{
  "type": "Feature",
  "properties": {
    "addr:full":"Avenue Adolphe Schattens 59b10 Waterloo Brabant Wallon 1410",
    "addr:housenumber":"59b10",
    "addr:postcode":"1410",
    "addr:street":"Avenue Adolphe Schattens",
    "iso:country":"BE",
    "sg:address":"Avenue Adolphe Schattens 59b10",
    "sg:city":"Waterloo",
    "sg:orig_category":"Avocats and conseillers juridiques",
    "sg:phone":"+32 2 354 69 63",
    "sg:postcode":"1410",
    "sg:province":"Brabant Wallon",
    "wof:name":"M. Haulotte",
    "wof:placetype":"venue"
},
  "geometry": {"coordinates":[4.3920969963,50.7139053345],"type":"Point"}
}