{
  "type": "Feature",
  "properties": {
    "iso:country":"BE",
    "sg:address":"Lieven Bauwensstraat 21",
    "sg:city":"Sint-andries",
    "sg:classifiers":[
        {
            "category":"Shopping",
            "subcategory":"Crafts & Fabrics",
            "type":"Retail Goods"
        }
    ],
    "sg:phone":"+32 50 31 56 64",
    "sg:postcode":"8200",
    "sg:province":"West-Vlaanderen",
    "sg:tags":[
        "textile",
        "clothing"
    ],
    "wof:name":"Zwartjes Gebroeders Bvba",
    "wof:placetype":"venue"
},
  "geometry": {"coordinates":[3.1930160522,51.2136230469],"type":"Point"}
}