{
  "type": "Feature",
  "properties": {
    "addr:full":"Place De La Libert\u00e9 17 Seraing Li\u00e8ge 4100",
    "addr:housenumber":"17",
    "addr:postcode":"4100",
    "addr:street":"Place De La Liberte\u0301",
    "iso:country":"BE",
    "sg:address":"Place De La Libert\u00e9 17",
    "sg:city":"Seraing",
    "sg:classifiers":[
        {
            "category":"Health Services",
            "subcategory":"Doctor",
            "type":"Services"
        }
    ],
    "sg:phone":"+32 4 337 54 77",
    "sg:postcode":"4100",
    "sg:province":"Li\u00e8ge",
    "sg:tags":[
        "medicinephysicians",
        "surgeon"
    ],
    "wof:name":"Andreatta Jean-marc",
    "wof:placetype":"venue"
},
  "geometry": {"coordinates":[5.5085101128,50.5855026245],"type":"Point"}
}