{
  "type": "Feature",
  "properties": {
    "iso:country":"BE",
    "sg:address":"Rootenstraat 8",
    "sg:city":"Genk",
    "sg:classifiers":[
        {
            "category":"Restaurant",
            "type":"Food & Drink"
        }
    ],
    "sg:phone":"+32 89 35 57 15",
    "sg:postcode":"3600",
    "sg:province":"Limburg",
    "sg:tags":[
        "caf\u00e9s"
    ],
    "wof:name":"Taverne Intermezzo",
    "wof:placetype":"venue"
},
  "geometry": {"coordinates":[5.5032610893,50.9652328491],"type":"Point"}
}