{
  "type": "Feature",
  "properties": {
    "addr:full":"Oude Booischotsebaan 38 Bonheiden Antwerpen 2820",
    "addr:housenumber":"38",
    "addr:postcode":"2820",
    "addr:street":"Oude Booischotsebaan",
    "iso:country":"BE",
    "sg:address":"Oude Booischotsebaan 38",
    "sg:city":"Bonheiden",
    "sg:orig_category":"Diverse bedrijfsbeheeradviesbureaus",
    "sg:phone":"+32 475 67 43 18",
    "sg:postcode":"2820",
    "sg:province":"Antwerpen",
    "wof:name":"Belgian Center For Quality Management",
    "wof:placetype":"venue"
},
  "geometry": {"coordinates":[4.6010451317,51.0259819031],"type":"Point"}
}