{
  "type": "Feature",
  "properties": {
    "iso:country":"BE",
    "sg:address":"Rue Trieu Gossiaux 5",
    "sg:city":"Fleurus",
    "sg:orig_category":"R\u00e9parations de chaussures and articles en cuir",
    "sg:phone":"+32 71 81 19 73",
    "sg:postcode":"6224",
    "sg:province":"Hainaut",
    "wof:name":"Giuseppe Verna",
    "wof:placetype":"venue"
},
  "geometry": {"coordinates":[4.5847439766,50.4657287598],"type":"Point"}
}