{
  "type": "Feature",
  "properties": {
    "addr:full":"Brouwersvliet 5 Box 4 Antwerpen Antwerpen 2000",
    "addr:housenumber":"5;4",
    "addr:postcode":"2000",
    "addr:street":"Brouwersvliet;Box",
    "iso:country":"BE",
    "sg:address":"Brouwersvliet 5 Box 4",
    "sg:city":"Antwerpen",
    "sg:classifiers":[
        {
            "category":"Organizations",
            "subcategory":"Professional Association",
            "type":"Services"
        }
    ],
    "sg:phone":"+32 3 202 44 00",
    "sg:postcode":"2000",
    "sg:province":"Antwerpen",
    "sg:tags":[
        "trade-union",
        "federation"
    ],
    "wof:name":"Vlaams Economisch Verbond Vzw",
    "wof:placetype":"venue"
},
  "geometry": {"coordinates":[4.4024138451,51.2272491455],"type":"Point"}
}