{
  "type": "Feature",
  "properties": {
    "iso:country":"BE",
    "sg:address":"Liersesteenweg 118",
    "sg:city":"Ranst",
    "sg:orig_category":"Sportclubs",
    "sg:phone":"+32 3 489 12 06",
    "sg:postcode":"2520",
    "sg:province":"Antwerpen",
    "wof:name":"B.c. Op De Meir",
    "wof:placetype":"venue"
},
  "geometry": {"coordinates":[4.5809221268,51.1527137756],"type":"Point"}
}