{
  "type": "Feature",
  "properties": {
    "addr:full":"Avenue Leopold Iii 226 Binche (p\u00e9ronnes-lez-binche) Hainaut 7134",
    "addr:housenumber":"226",
    "addr:postcode":"7134",
    "addr:street":"Avenue Leopold Iii",
    "iso:country":"BE",
    "sg:address":"Avenue Leopold Iii 226",
    "sg:city":"Binche (p\u00e9ronnes-lez-binche)",
    "sg:classifiers":[
        {
            "category":"Health Services",
            "subcategory":"Health Practitioner",
            "type":"Services"
        }
    ],
    "sg:phone":"+32 64 33 74 04",
    "sg:postcode":"7134",
    "sg:province":"Hainaut",
    "sg:tags":[
        "physiotherapist"
    ],
    "wof:name":"Hirsoux B",
    "wof:placetype":"venue"
},
  "geometry": {"coordinates":[4.2175779343,50.4159622192],"type":"Point"}
}