{
  "type": "Feature",
  "properties": {
    "addr:full":"Rue Victor Lagneau 31-24 Sambreville (tamines) Namur 5060",
    "addr:housenumber":"31-24",
    "addr:postcode":"5060",
    "addr:street":"Rue Victor Lagneau",
    "iso:country":"BE",
    "sg:address":"Rue Victor Lagneau 31-24",
    "sg:city":"Sambreville (tamines)",
    "sg:classifiers":[
        {
            "category":"Freight",
            "type":"Transportation"
        }
    ],
    "sg:phone":"+32 71 78 37 77",
    "sg:postcode":"5060",
    "sg:province":"Namur",
    "sg:tags":[
        "-",
        "transport"
    ],
    "wof:name":"Gtl",
    "wof:placetype":"venue"
},
  "geometry": {"coordinates":[4.6285200119,50.4448738098],"type":"Point"}
}