{
  "type": "Feature",
  "properties": {
    "addr:full":"Chauss\u00e9e De Renaix 322 Lessines (ogy) Hainaut 7862",
    "addr:housenumber":"322",
    "addr:postcode":"7862",
    "addr:street":"Chausse\u0301E De Renaix",
    "iso:country":"BE",
    "sg:address":"Chauss\u00e9e De Renaix 322",
    "sg:city":"Lessines (ogy)",
    "sg:classifiers":[
        {
            "category":"Bars & Pubs",
            "type":"Food & Drink"
        }
    ],
    "sg:phone":"+32 68 44 88 49",
    "sg:postcode":"7862",
    "sg:province":"Hainaut",
    "wof:name":"Parrain Maestrich",
    "wof:placetype":"venue"
},
  "geometry": {"coordinates":[3.7815079689,50.7196235657],"type":"Point"}
}