{
  "type": "Feature",
  "properties": {
    "addr:full":"Albert Meunierstraat 33 Oudergem/auderghem Bruxelles-Capitale 1160",
    "addr:housenumber":"33",
    "addr:postcode":"1160",
    "addr:street":"Albert Meunierstraat;/",
    "iso:country":"BE",
    "sg:address":"Albert Meunierstraat 33",
    "sg:city":"Oudergem/auderghem",
    "sg:orig_category":"Kapsalons",
    "sg:phone":"+32 2 673 73 44",
    "sg:postcode":"1160",
    "sg:province":"Bruxelles-Capitale",
    "wof:name":"Coiffure Anne",
    "wof:placetype":"venue"
},
  "geometry": {"coordinates":[4.4380049706,50.8112449646],"type":"Point"}
}