{
  "type": "Feature",
  "properties": {
    "iso:country":"BE",
    "sg:address":"Rue Des Lilas 54",
    "sg:city":"Etalle",
    "sg:orig_category":"Salons de coiffure. Centres de relaxation and bien-\u00eatre",
    "sg:phone":"+32 63 45 54 05",
    "sg:postcode":"6743",
    "sg:province":"Luxembourg",
    "wof:name":"Atelier Coiffure",
    "wof:placetype":"venue"
},
  "geometry": {"coordinates":[5.5948181152,49.6454582214],"type":"Point"}
}