{
  "type": "Feature",
  "properties": {
    "addr:full":"Leestdorp 22b1 Mechelen Antwerpen 2811",
    "addr:housenumber":"22b1",
    "addr:postcode":"2811",
    "addr:street":"Leestdorp",
    "iso:country":"BE",
    "sg:address":"Leestdorp 22b1",
    "sg:city":"Mechelen",
    "sg:orig_category":"Eclairage et \u00e9quipements du foyer. D\u00e9corateurs d'int\u00e9rieur",
    "sg:phone":"+32 15 27 28 56",
    "sg:postcode":"2811",
    "sg:province":"Antwerpen",
    "wof:name":"Luc Cooreman",
    "wof:placetype":"venue"
},
  "geometry": {"coordinates":[4.4183988571,51.0327301025],"type":"Point"}
}