{
  "type": "Feature",
  "properties": {
    "iso:country":"BE",
    "sg:address":"Romershovenstraat 188",
    "sg:city":"Hoeselt",
    "sg:classifiers":[
        {
            "category":"Social Services",
            "subcategory":"Job Training",
            "type":"Services"
        }
    ],
    "sg:phone":"+32 89 41 14 37",
    "sg:postcode":"3730",
    "sg:province":"Limburg",
    "sg:tags":[
        "de",
        "terrain",
        "camping"
    ],
    "wof:name":"Op Den Dries",
    "wof:placetype":"venue"
},
  "geometry": {"coordinates":[5.4555439949,50.8739929199],"type":"Point"}
}