{
  "type": "Feature",
  "properties": {
    "iso:country":"BE",
    "sg:address":"Ouren 34",
    "sg:city":"Burg-reuland",
    "sg:classifiers":[
        {
            "category":"Food & Beverages",
            "subcategory":"Groceries & Convenience Stores",
            "type":"Retail Goods"
        }
    ],
    "sg:phone":"+32 80 32 90 39",
    "sg:postcode":"4790",
    "sg:province":"Li\u00e8ge",
    "sg:tags":[
        "grocer"
    ],
    "wof:name":"Maurer E",
    "wof:placetype":"venue"
},
  "geometry": {"coordinates":[6.1344199181,50.1398735046],"type":"Point"}
}