{
  "type": "Feature",
  "properties": {
    "addr:full":"Tabakvest 50 Antwerpen Antwerpen 2000",
    "addr:housenumber":"50",
    "addr:postcode":"2000",
    "addr:street":"Tabakvest",
    "iso:country":"BE",
    "sg:address":"Tabakvest 50",
    "sg:city":"Antwerpen",
    "sg:classifiers":[
        {
            "category":"Health Services",
            "subcategory":"Nursing And Care Facility",
            "type":"Services"
        }
    ],
    "sg:phone":"+32 3 222 47 11",
    "sg:postcode":"2000",
    "sg:province":"Antwerpen",
    "sg:tags":[
        "public"
    ],
    "wof:name":"Admin. Directe Belast.",
    "wof:placetype":"venue"
},
  "geometry": {"coordinates":[4.4115610123,51.2151527405],"type":"Point"}
}