{
  "type": "Feature",
  "properties": {
    "addr:full":"Rue Des Pieds D'alouette 39 Namur (naninne) Namur 5100",
    "addr:housenumber":"39",
    "addr:postcode":"5100",
    "addr:street":"Rue Des Pieds D'Alouette",
    "iso:country":"BE",
    "sg:address":"Rue Des Pieds D'alouette 39",
    "sg:city":"Namur (naninne)",
    "sg:classifiers":[
        {
            "category":"Military Area",
            "subcategory":"Air Force Base",
            "type":"Public Place"
        }
    ],
    "sg:phone":"+32 81 40 01 19",
    "sg:postcode":"5100",
    "sg:province":"Namur",
    "sg:tags":[
        "fire",
        "protection"
    ],
    "wof:name":"Somati Sud Sa",
    "wof:placetype":"venue"
},
  "geometry": {"coordinates":[4.9245581627,50.4265937805],"type":"Point"}
}