{
  "type": "Feature",
  "properties": {
    "iso:country":"BE",
    "sg:address":"Rue De L'eglise 3",
    "sg:city":"Saint-hubert (hatrival)",
    "sg:classifiers":[
        {
            "category":"Banks & Credit Unions",
            "subcategory":"Bureau De Change",
            "type":"Services"
        }
    ],
    "sg:phone":"+32 61 61 15 95",
    "sg:postcode":"6870",
    "sg:province":"Luxembourg",
    "sg:tags":[
        "-",
        "household",
        "gas"
    ],
    "wof:name":"Liban S",
    "wof:placetype":"venue"
},
  "geometry": {"coordinates":[5.34770298,50.0061073303],"type":"Point"}
}