{
  "type": "Feature",
  "properties": {
    "addr:full":"Watermolenweg 8ba Wichelen Oost-Vlaanderen 9260",
    "addr:housenumber":"8ba",
    "addr:postcode":"9260",
    "addr:street":"Watermolenweg",
    "iso:country":"BE",
    "sg:address":"Watermolenweg 8ba",
    "sg:city":"Wichelen",
    "sg:orig_category":"Begrafeniswezen",
    "sg:phone":"+32 52 42 41 50",
    "sg:postcode":"9260",
    "sg:province":"Oost-Vlaanderen",
    "wof:name":"Hector Govaert",
    "wof:placetype":"venue"
},
  "geometry": {"coordinates":[3.9728450775,50.9923057556],"type":"Point"}
}