{
  "type": "Feature",
  "properties": {
    "addr:full":"Overheulestraat 332 Wevelgem West-Vlaanderen 8560",
    "addr:housenumber":"332",
    "addr:postcode":"8560",
    "addr:street":"Overheulestraat",
    "iso:country":"BE",
    "sg:address":"Overheulestraat 332",
    "sg:city":"Wevelgem",
    "sg:orig_category":"Producteurs de l\u00e9gumes",
    "sg:phone":"+32 56 50 90 25",
    "sg:postcode":"8560",
    "sg:province":"West-Vlaanderen",
    "wof:name":"Filip Staelens",
    "wof:placetype":"venue"
},
  "geometry": {"coordinates":[3.1558558941,50.8562507629],"type":"Point"}
}