{
  "type": "Feature",
  "properties": {
    "addr:full":"Oostberg 79 Temse Oost-Vlaanderen 9140",
    "addr:housenumber":"79",
    "addr:postcode":"9140",
    "addr:street":"Oostberg",
    "iso:country":"BE",
    "sg:address":"Oostberg 79",
    "sg:city":"Temse",
    "sg:orig_category":"Woningbouw",
    "sg:phone":"+32 3 711 19 14",
    "sg:postcode":"9140",
    "sg:province":"Oost-Vlaanderen",
    "wof:name":"Cop J.",
    "wof:placetype":"venue"
},
  "geometry": {"coordinates":[4.2365288734,51.126033783],"type":"Point"}
}