{
  "type": "Feature",
  "properties": {
    "addr:full":"Rauwelkoven 184 Geel Antwerpen 2440",
    "addr:housenumber":"184",
    "addr:postcode":"2440",
    "addr:street":"Rauwelkoven",
    "iso:country":"BE",
    "sg:address":"Rauwelkoven 184",
    "sg:city":"Geel",
    "sg:orig_category":"Plaatsen van vloer- and muurbekleding",
    "sg:phone":"+32 14 58 75 25",
    "sg:postcode":"2440",
    "sg:province":"Antwerpen",
    "wof:name":"Cuyvers - Mens En Zonen",
    "wof:placetype":"venue"
},
  "geometry": {"coordinates":[4.9468097687,51.1699905396],"type":"Point"}
}