{
  "type": "Feature",
  "properties": {
    "addr:full":"Congreslaan 34 Gent Oost-Vlaanderen 9000",
    "addr:housenumber":"34",
    "addr:postcode":"9000",
    "addr:street":"Congreslaan;Oost-Vlaanderen",
    "iso:country":"BE",
    "sg:address":"Congreslaan 34",
    "sg:city":"Gent",
    "sg:orig_category":"M\u00e9decins and sp\u00e9cialistes",
    "sg:phone":"+32 9 222 50 93",
    "sg:postcode":"9000",
    "sg:province":"Oost-Vlaanderen",
    "wof:name":"Patrick Dierickx",
    "wof:placetype":"venue"
},
  "geometry": {"coordinates":[3.7161989212,51.0317573547],"type":"Point"}
}