{
  "type": "Feature",
  "properties": {
    "addr:full":"Rue Du H\u00eatre Pourpre 53 Chaudfontaine (embourg) Li\u00e8ge 4053",
    "addr:housenumber":"53",
    "addr:postcode":"4053",
    "addr:street":"Rue Du He\u0302Tre Pourpre",
    "iso:country":"BE",
    "sg:address":"Rue Du H\u00eatre Pourpre 53",
    "sg:city":"Chaudfontaine (embourg)",
    "sg:classifiers":[
        {
            "category":"Home & Garden",
            "subcategory":"Household Appliances",
            "type":"Retail Goods"
        }
    ],
    "sg:phone":"+32 4 365 56 69",
    "sg:postcode":"4053",
    "sg:province":"Li\u00e8ge",
    "sg:tags":[
        "repair",
        "mainten",
        "-",
        "electric"
    ],
    "wof:name":"Alixin J",
    "wof:placetype":"venue"
},
  "geometry": {"coordinates":[5.6036748886,50.5958480835],"type":"Point"}
}