{
  "type": "Feature",
  "properties": {
    "addr:full":"Keizerenberg 27 Kontich Antwerpen 2550",
    "addr:housenumber":"27",
    "addr:postcode":"2550",
    "addr:street":"Keizerenberg",
    "iso:country":"BE",
    "sg:address":"Keizerenberg 27",
    "sg:city":"Kontich",
    "sg:orig_category":"Rundveehouders",
    "sg:phone":"+32 15 31 17 76",
    "sg:postcode":"2550",
    "sg:province":"Antwerpen",
    "wof:name":"Julien Fierens",
    "wof:placetype":"venue"
},
  "geometry": {"coordinates":[4.4613461494,51.0967063904],"type":"Point"}
}