{
  "type": "Feature",
  "properties": {
    "iso:country":"BE",
    "sg:address":"Heldenlaan 61",
    "sg:city":"Zottegem",
    "sg:orig_category":"Banques and organismes de cr\u00e9dit",
    "sg:phone":"+32 9 360 20 21",
    "sg:postcode":"9620",
    "sg:province":"Oost-Vlaanderen",
    "wof:name":"Fortis",
    "wof:placetype":"venue"
},
  "geometry": {"coordinates":[3.8100790977,50.8715438843],"type":"Point"}
}