{
  "type": "Feature",
  "properties": {
    "iso:country":"BE",
    "sg:address":"Stationsstraat 75",
    "sg:city":"Damme",
    "sg:orig_category":"Boissons",
    "sg:phone":"+32 50 35 28 35",
    "sg:postcode":"8340",
    "sg:province":"West-Vlaanderen",
    "wof:name":"Dranken Maenhout",
    "wof:placetype":"venue"
},
  "geometry": {"coordinates":[3.3179900646,51.2072029114],"type":"Point"}
}