{
  "type": "Feature",
  "properties": {
    "iso:country":"BE",
    "sg:address":"Leieland 41",
    "sg:city":"Wevelgem",
    "sg:classifiers":[
        {
            "category":"Parking",
            "subcategory":"Lot",
            "type":"Transportation"
        }
    ],
    "sg:phone":"+32 56 42 19 39",
    "sg:postcode":"8560",
    "sg:province":"West-Vlaanderen",
    "sg:tags":[
        "armoured",
        "door",
        "fireproof"
    ],
    "wof:name":"Van Raes F",
    "wof:placetype":"venue"
},
  "geometry": {"coordinates":[3.1955089569,50.8071098328],"type":"Point"}
}