{
  "type": "Feature",
  "properties": {
    "iso:country":"BE",
    "sg:address":"Industriepark De Bruwaan 25",
    "sg:city":"Oudenaarde",
    "sg:classifiers":[
        {
            "category":"Banks & Credit Unions",
            "subcategory":"Investment Brokerage",
            "type":"Services"
        }
    ],
    "sg:phone":"+32 55 31 68 01",
    "sg:postcode":"9700",
    "sg:province":"Oost-Vlaanderen",
    "sg:tags":[
        "printing",
        "-"
    ],
    "wof:name":"Mepa Nv",
    "wof:placetype":"venue"
},
  "geometry": {"coordinates":[3.5997750759,50.8656692505],"type":"Point"}
}