{
  "type": "Feature",
  "properties": {
    "addr:full":"Mekingenweg 54 Sint-pieters-leeuw Vlaams-Brabant 1600",
    "addr:housenumber":"54",
    "addr:postcode":"1600",
    "addr:street":"Mekingenweg",
    "iso:country":"BE",
    "sg:address":"Mekingenweg 54",
    "sg:city":"Sint-pieters-leeuw",
    "sg:orig_category":"Metaalbehandeling and -bekleding",
    "sg:phone":"+32 2 331 32 73",
    "sg:postcode":"1600",
    "sg:province":"Vlaams-Brabant",
    "wof:name":"Stofkooper",
    "wof:placetype":"venue"
},
  "geometry": {"coordinates":[4.239109993,50.7730522156],"type":"Point"}
}