{
  "type": "Feature",
  "properties": {
    "iso:country":"BE",
    "sg:address":"Rue Grande Chenevi\u00c8re 147",
    "sg:city":"Charleroi",
    "sg:orig_category":"Zuivelproducten",
    "sg:phone":"+32 71 36 96 11",
    "sg:postcode":"6001",
    "sg:province":"Hainaut",
    "wof:name":"Le D\u00c9lice Des Souris",
    "wof:placetype":"venue"
},
  "geometry": {"coordinates":[4.443215847,50.3870010376],"type":"Point"}
}