{
  "type": "Feature",
  "properties": {
    "addr:full":"Bollebergen 15a Gent (zwijnaarde) Oost-Vlaanderen 9052",
    "addr:housenumber":"15a",
    "addr:postcode":"9052",
    "addr:street":"Bollebergen",
    "iso:country":"BE",
    "sg:address":"Bollebergen 15a",
    "sg:city":"Gent (zwijnaarde)",
    "sg:classifiers":[
        {
            "category":"Cafe",
            "type":"Food & Drink"
        }
    ],
    "sg:phone":"+32 9 221 43 93",
    "sg:postcode":"9052",
    "sg:province":"Oost-Vlaanderen",
    "sg:tags":[
        "snack-bars"
    ],
    "wof:name":"At The Woody's",
    "wof:placetype":"venue"
},
  "geometry": {"coordinates":[3.7167270184,51.0002937317],"type":"Point"}
}