{
  "type": "Feature",
  "properties": {
    "addr:full":"Rue Caremberg 40 Edingen/enghien Hainaut 7850",
    "addr:housenumber":"40",
    "addr:postcode":"7850",
    "addr:street":"Rue Caremberg",
    "iso:country":"BE",
    "sg:address":"Rue Caremberg 40",
    "sg:city":"Edingen/enghien",
    "sg:orig_category":"Entretien and r\u00e9parations de voitures",
    "sg:phone":"+32 2 395 83 22",
    "sg:postcode":"7850",
    "sg:province":"Hainaut",
    "wof:name":"Jean Derue",
    "wof:placetype":"venue"
},
  "geometry": {"coordinates":[4.0723609924,50.6936378479],"type":"Point"}
}