{
  "type": "Feature",
  "properties": {
    "addr:full":"Liersesteenweg 1 Mortsel Antwerpen 2640",
    "addr:housenumber":"1",
    "addr:postcode":"2640",
    "addr:street":"Liersesteenweg",
    "iso:country":"BE",
    "sg:address":"Liersesteenweg 1",
    "sg:city":"Mortsel",
    "sg:classifiers":[
        {
            "category":"Government",
            "subcategory":"Police Station",
            "type":"Public Place"
        }
    ],
    "sg:phone":"+32 3 444 18 88",
    "sg:postcode":"2640",
    "sg:province":"Antwerpen",
    "sg:tags":[
        "gendarmerie"
    ],
    "wof:name":"Federale Politie",
    "wof:placetype":"venue"
},
  "geometry": {"coordinates":[4.4570808411,51.1702079773],"type":"Point"}
}