{
  "type": "Feature",
  "properties": {
    "addr:full":"Zavelvennestraat 275 Hasselt Limburg 3500",
    "addr:housenumber":"275",
    "addr:postcode":"3500",
    "addr:street":"Zavelvennestraat",
    "iso:country":"BE",
    "sg:address":"Zavelvennestraat 275",
    "sg:city":"Hasselt",
    "sg:orig_category":"Messageries",
    "sg:phone":"+32 11 23 10 01",
    "sg:postcode":"3500",
    "sg:province":"Limburg",
    "wof:name":"Transport Medacars",
    "wof:placetype":"venue"
},
  "geometry": {"coordinates":[5.396903038,50.9687614441],"type":"Point"}
}