{
  "type": "Feature",
  "properties": {
    "addr:full":"Rue Van Moer 11-13 Brussel Bruxelles-Capitale 1000",
    "addr:postcode":"11-13;1000",
    "addr:street":"Rue Van Moer",
    "iso:country":"BE",
    "sg:address":"Rue Van Moer 11-13",
    "sg:city":"Brussel",
    "sg:orig_category":"Eclairage et \u00e9quipements du foyer",
    "sg:phone":"+32 2 511 28 35",
    "sg:postcode":"1000",
    "sg:province":"Bruxelles-Capitale",
    "wof:name":"Argus",
    "wof:placetype":"venue"
},
  "geometry": {"coordinates":[4.3540759087,50.8390350342],"type":"Point"}
}