{
  "type": "Feature",
  "properties": {
    "addr:full":"Noordzandstraat 5 Brugge West-Vlaanderen 8000",
    "addr:housenumber":"5",
    "addr:postcode":"8000",
    "addr:street":"Noordzandstraat",
    "iso:country":"BE",
    "sg:address":"Noordzandstraat 5",
    "sg:city":"Brugge",
    "sg:orig_category":"Blanchisseries and teintureries",
    "sg:phone":"+32 50 33 02 82",
    "sg:postcode":"8000",
    "sg:province":"West-Vlaanderen",
    "wof:name":"Press Shop",
    "wof:placetype":"venue"
},
  "geometry": {"coordinates":[3.2211420536,51.2082252502],"type":"Point"}
}