{
  "type": "Feature",
  "properties": {
    "addr:full":"Bormenville 2 Havelange Namur 5370",
    "addr:housenumber":"2",
    "addr:postcode":"5370",
    "addr:street":"Bormenville",
    "iso:country":"BE",
    "sg:address":"Bormenville 2",
    "sg:city":"Havelange",
    "sg:orig_category":"Boekhouders",
    "sg:phone":"+32 83 61 24 66",
    "sg:postcode":"5370",
    "sg:province":"Namur",
    "wof:name":"Pol Renard",
    "wof:placetype":"venue"
},
  "geometry": {"coordinates":[5.1820049286,50.3660621643],"type":"Point"}
}