{
  "type": "Feature",
  "properties": {
    "addr:full":"Kruisstraat 139 Kortenberg Vlaams-Brabant 3078",
    "addr:housenumber":"139",
    "addr:postcode":"3078",
    "addr:street":"Kruisstraat;Vlaams-Brabant",
    "iso:country":"BE",
    "sg:address":"Kruisstraat 139",
    "sg:city":"Kortenberg",
    "sg:orig_category":"Evaluation and estimation de biens immobiliers",
    "sg:phone":"+32 2 757 09 00",
    "sg:postcode":"3078",
    "sg:province":"Vlaams-Brabant",
    "wof:name":"Bureau Van Eijcken Jan",
    "wof:placetype":"venue"
},
  "geometry": {"coordinates":[4.5411729813,50.8759651184],"type":"Point"}
}