{
  "type": "Feature",
  "properties": {
    "addr:full":"Meensestraat 54 Kortrijk West-Vlaanderen 8500",
    "addr:housenumber":"54",
    "addr:postcode":"8500",
    "addr:street":"Meensestraat",
    "iso:country":"BE",
    "sg:address":"Meensestraat 54",
    "sg:city":"Kortrijk",
    "sg:classifiers":[
        {
            "category":"Shopping",
            "subcategory":"Clothing, Apparel, & Fashions",
            "type":"Retail Goods"
        }
    ],
    "sg:phone":"+32 56 37 38 55",
    "sg:postcode":"8500",
    "sg:province":"West-Vlaanderen",
    "sg:tags":[
        "underwear",
        "lingerie",
        "-"
    ],
    "wof:name":"Saluti Lingerie",
    "wof:placetype":"venue"
},
  "geometry": {"coordinates":[3.2508990765,50.8305130005],"type":"Point"}
}