{
  "type": "Feature",
  "properties": {
    "iso:country":"BE",
    "sg:address":"Bijlkenstraat 13",
    "sg:city":"Nevele",
    "sg:orig_category":"Groententeelt",
    "sg:phone":"+32 9 371 69 08",
    "sg:postcode":"9850",
    "sg:province":"Oost-Vlaanderen",
    "wof:name":"Philippe Gaudisabois",
    "wof:placetype":"venue"
},
  "geometry": {"coordinates":[3.5316970348,51.0423774719],"type":"Point"}
}