{
  "type": "Feature",
  "properties": {
    "addr:full":"Fruitmarkt 8 Genk Limburg 3600",
    "addr:housenumber":"8",
    "addr:postcode":"3600",
    "addr:street":"Fruitmarkt",
    "iso:country":"BE",
    "sg:address":"Fruitmarkt 8",
    "sg:city":"Genk",
    "sg:orig_category":"Verhuur textielartikelen and schoenen",
    "sg:phone":"+32 89 36 18 75",
    "sg:postcode":"3600",
    "sg:province":"Limburg",
    "wof:name":"Boyen Tailors",
    "wof:placetype":"venue"
},
  "geometry": {"coordinates":[5.4999980927,50.9647865295],"type":"Point"}
}