{
  "type": "Feature",
  "properties": {
    "addr:full":"Hasseltsestraat 86a Diest Vlaams-Brabant 3290",
    "addr:housenumber":"86a",
    "addr:postcode":"3290",
    "addr:street":"Hasseltsestraat",
    "iso:country":"BE",
    "sg:address":"Hasseltsestraat 86a",
    "sg:city":"Diest",
    "sg:classifiers":[
        {
            "category":"Professional",
            "subcategory":"Testing Lab",
            "type":"Services"
        }
    ],
    "sg:phone":"+32 13 31 22 28",
    "sg:postcode":"3290",
    "sg:province":"Vlaams-Brabant",
    "sg:tags":[
        "chemist"
    ],
    "wof:name":"Hasseltsepoort Nv Apotheek",
    "wof:placetype":"venue"
},
  "geometry": {"coordinates":[5.0547599792,50.9803237915],"type":"Point"}
}