{
  "type": "Feature",
  "properties": {
    "addr:full":"Schooldreef 39 Mol Antwerpen 2400",
    "addr:housenumber":"39",
    "addr:postcode":"2400",
    "addr:street":"Schooldreef",
    "iso:country":"BE",
    "sg:address":"Schooldreef 39",
    "sg:city":"Mol",
    "sg:orig_category":"Kapsalons",
    "sg:phone":"+32 14 82 80 45",
    "sg:postcode":"2400",
    "sg:province":"Antwerpen",
    "wof:name":"Haarstudio Cindy",
    "wof:placetype":"venue"
},
  "geometry": {"coordinates":[5.2068858147,51.2094192505],"type":"Point"}
}