{
  "type": "Feature",
  "properties": {
    "addr:full":"'t Serclaesstraat 16 Ternat Vlaams-Brabant 1740",
    "addr:housenumber":"16",
    "addr:postcode":"1740",
    "addr:street":"';Serclaesstraat",
    "iso:country":"BE",
    "sg:address":"'t Serclaesstraat 16",
    "sg:city":"Ternat",
    "sg:classifiers":[
        {
            "category":"Health Services",
            "subcategory":"Doctor",
            "type":"Services"
        }
    ],
    "sg:phone":"+32 2 582 19 78",
    "sg:postcode":"1740",
    "sg:province":"Vlaams-Brabant",
    "sg:tags":[
        "medicinephysicians",
        "surgeon"
    ],
    "wof:name":"Gadeyne Marc",
    "wof:placetype":"venue"
},
  "geometry": {"coordinates":[4.170527935,50.8681411743],"type":"Point"}
}