{
  "type": "Feature",
  "properties": {
    "iso:country":"BE",
    "sg:address":"Rue Du Crampon 66bbis",
    "sg:city":"Tournai",
    "sg:orig_category":"Artistes ind\u00e9pendants",
    "sg:phone":"+32 69 22 63 60",
    "sg:postcode":"7500",
    "sg:province":"Hainaut",
    "wof:name":"Noel Leriche",
    "wof:placetype":"venue"
},
  "geometry": {"coordinates":[3.3958399296,50.6179618835],"type":"Point"}
}