{
  "type": "Feature",
  "properties": {
    "iso:country":"BE",
    "sg:address":"Vijverstraat 26",
    "sg:city":"Roeselare",
    "sg:orig_category":"Beheer van reclamemedia",
    "sg:phone":"+32 51 20 53 63",
    "sg:postcode":"8800",
    "sg:province":"West-Vlaanderen",
    "wof:name":"Thierry Debecker",
    "wof:placetype":"venue"
},
  "geometry": {"coordinates":[3.1395900249,50.9527778625],"type":"Point"}
}