{
  "type": "Feature",
  "properties": {
    "addr:full":"Felix Timmermanslaan 7 Hoeilaart Vlaams-Brabant 1560",
    "addr:housenumber":"7",
    "addr:postcode":"1560",
    "addr:street":"Felix Timmermanslaan",
    "iso:country":"BE",
    "sg:address":"Felix Timmermanslaan 7",
    "sg:city":"Hoeilaart",
    "sg:classifiers":[
        {
            "category":"Personal",
            "subcategory":"Beauty Salon",
            "type":"Services"
        }
    ],
    "sg:phone":"+32 2 657 17 56",
    "sg:postcode":"1560",
    "sg:province":"Vlaams-Brabant",
    "sg:tags":[
        "lady",
        "-",
        "hairdressing"
    ],
    "wof:name":"Monica",
    "wof:placetype":"venue"
},
  "geometry": {"coordinates":[4.4751200676,50.7706031799],"type":"Point"}
}