{
  "type": "Feature",
  "properties": {
    "addr:full":"Tenbergen 15 Brakel (opbrakel) Oost-Vlaanderen 9660",
    "addr:housenumber":"15",
    "addr:postcode":"9660",
    "addr:street":"Tenbergen",
    "iso:country":"BE",
    "sg:address":"Tenbergen 15",
    "sg:city":"Brakel (opbrakel)",
    "sg:classifiers":[
        {
            "category":"Real Estate",
            "subcategory":"Surveying",
            "type":"Services"
        }
    ],
    "sg:phone":"+32 55 42 54 92",
    "sg:postcode":"9660",
    "sg:province":"Oost-Vlaanderen",
    "sg:tags":[
        "surveyor",
        "land"
    ],
    "wof:name":"Verhelst A",
    "wof:placetype":"venue"
},
  "geometry": {"coordinates":[3.7466170788,50.7804450989],"type":"Point"}
}