{
  "type": "Feature",
  "properties": {
    "iso:country":"BE",
    "sg:address":"Rue D\u00b4houdeng 165",
    "sg:city":"Le Roeulx",
    "sg:classifiers":[
        {
            "category":"Insurance",
            "subcategory":"Life Insurance",
            "type":"Services"
        }
    ],
    "sg:phone":"+32 64 67 39 04",
    "sg:postcode":"7070",
    "sg:province":"Hainaut",
    "sg:tags":[
        "assurance"
    ],
    "wof:name":"B. Scutenaire",
    "wof:placetype":"venue"
},
  "geometry": {"coordinates":[4.1208810806,50.4998245239],"type":"Point"}
}