{
  "type": "Feature",
  "properties": {
    "addr:full":"Route De Luxembourg 351 Arlon Luxembourg 6706",
    "addr:housenumber":"351",
    "addr:postcode":"6706",
    "addr:street":"Route De Luxembourg",
    "iso:country":"BE",
    "sg:address":"Route De Luxembourg 351",
    "sg:city":"Arlon",
    "sg:orig_category":"Diverse organisaties and verenigingen",
    "sg:phone":"+32 63 22 17 54",
    "sg:postcode":"6706",
    "sg:province":"Luxembourg",
    "wof:name":"Soc. Protect. Des Animaux",
    "wof:placetype":"venue"
},
  "geometry": {"coordinates":[5.8697757721,49.6491928101],"type":"Point"}
}