{
  "type": "Feature",
  "properties": {
    "iso:country":"BE",
    "sg:address":"Appelweg 162",
    "sg:city":"Holsbeek",
    "sg:orig_category":"Verbruikerskredietinstellingen",
    "sg:phone":"+32 16 56 82 30",
    "sg:postcode":"3221",
    "sg:province":"Vlaams-Brabant",
    "wof:name":"Hagelands-krediet",
    "wof:placetype":"venue"
},
  "geometry": {"coordinates":[4.8101501465,50.9452095032],"type":"Point"}
}