{
  "type": "Feature",
  "properties": {
    "addr:full":"Rue Arthur Gailly 56 Fleurus (wanferc\u00e9e-baulet) Hainaut 6224",
    "addr:housenumber":"56",
    "addr:postcode":"6224",
    "addr:street":"Rue Arthur Gailly",
    "iso:country":"BE",
    "sg:address":"Rue Arthur Gailly 56",
    "sg:city":"Fleurus (wanferc\u00e9e-baulet)",
    "sg:classifiers":[
        {
            "category":"Health Services",
            "subcategory":"Nursing And Care Facility",
            "type":"Services"
        }
    ],
    "sg:phone":"+32 71 81 09 16",
    "sg:postcode":"6224",
    "sg:province":"Hainaut",
    "sg:tags":[
        "home"
    ],
    "wof:name":"Spadaccini G",
    "wof:placetype":"venue"
},
  "geometry": {"coordinates":[4.5827980042,50.4691047668],"type":"Point"}
}