{
  "type": "Feature",
  "properties": {
    "addr:full":"Rue Des Echasseurs 4 Namur Namur 5000",
    "addr:housenumber":"4",
    "addr:postcode":"5000",
    "addr:street":"Rue Des Echasseurs",
    "iso:country":"BE",
    "sg:address":"Rue Des Echasseurs 4",
    "sg:city":"Namur",
    "sg:classifiers":[
        {
            "category":"Professional",
            "subcategory":"Testing Lab",
            "type":"Services"
        }
    ],
    "sg:phone":"+32 81 22 85 28",
    "sg:postcode":"5000",
    "sg:province":"Namur",
    "sg:tags":[
        "chemist"
    ],
    "wof:name":"Genette Ph",
    "wof:placetype":"venue"
},
  "geometry": {"coordinates":[4.8660578728,50.4626693726],"type":"Point"}
}