{
  "type": "Feature",
  "properties": {
    "addr:full":"Denderhoutembaan 64 Ninove Oost-Vlaanderen 9400",
    "addr:housenumber":"64",
    "addr:postcode":"9400",
    "addr:street":"Denderhoutembaan",
    "iso:country":"BE",
    "sg:address":"Denderhoutembaan 64",
    "sg:city":"Ninove",
    "sg:orig_category":"Artiesten and kunstenaars",
    "sg:phone":"+32 54 33 34 51",
    "sg:postcode":"9400",
    "sg:province":"Oost-Vlaanderen",
    "wof:name":"Van Liefferinge",
    "wof:placetype":"venue"
},
  "geometry": {"coordinates":[4.0209789276,50.8432197571],"type":"Point"}
}