{
  "type": "Feature",
  "properties": {
    "addr:full":"Roeselarestraat 118 Diksmuide West-Vlaanderen 8600",
    "addr:housenumber":"118",
    "addr:postcode":"8600",
    "addr:street":"Roeselarestraat",
    "iso:country":"BE",
    "sg:address":"Roeselarestraat 118",
    "sg:city":"Diksmuide",
    "sg:orig_category":"Non-Classified Establishments",
    "sg:phone":"+32 51 50 03 72",
    "sg:postcode":"8600",
    "sg:province":"West-Vlaanderen",
    "wof:name":"Vandevelde C",
    "wof:placetype":"venue"
},
  "geometry": {"coordinates":[2.9293820858,51.0215263367],"type":"Point"}
}