{
  "type": "Feature",
  "properties": {
    "addr:full":"Sur Les Keyeux 21 Soumagne Li\u00e8ge 4630",
    "addr:housenumber":"21",
    "addr:postcode":"4630",
    "addr:street":"Sur Les Keyeux",
    "iso:country":"BE",
    "sg:address":"Sur Les Keyeux 21",
    "sg:city":"Soumagne",
    "sg:classifiers":[
        {
            "category":"Professional",
            "subcategory":"Engineering",
            "type":"Services"
        }
    ],
    "sg:phone":"+32 4 377 44 80",
    "sg:postcode":"4630",
    "sg:province":"Li\u00e8ge",
    "sg:tags":[
        "civil"
    ],
    "wof:name":"Jld Engineering S.p.r.l.",
    "wof:placetype":"venue"
},
  "geometry": {"coordinates":[5.7195901871,50.6247138977],"type":"Point"}
}