{
  "type": "Feature",
  "properties": {
    "iso:country":"BE",
    "sg:address":"Bellegemstraat 1",
    "sg:city":"Zwevegem",
    "sg:orig_category":"Benzinestations and brandstoffen",
    "sg:phone":"+32 56 75 58 43",
    "sg:postcode":"8550",
    "sg:province":"West-Vlaanderen",
    "wof:name":"Fa. Petros-ter Linde",
    "wof:placetype":"venue"
},
  "geometry": {"coordinates":[3.3384480476,50.7994880676],"type":"Point"}
}