{
  "type": "Feature",
  "properties": {
    "addr:full":"Steenweg 175 Lanaken (groot) Limburg 3621",
    "addr:housenumber":"175",
    "addr:postcode":"3621",
    "addr:street":"Steenweg;Groot Limburg",
    "iso:country":"BE",
    "sg:address":"Steenweg 175",
    "sg:city":"Lanaken (groot)",
    "sg:orig_category":"Brood, gebak and snoepgoed",
    "sg:phone":"+32 89 71 39 04",
    "sg:postcode":"3621",
    "sg:province":"Limburg",
    "wof:name":"'t Suikerboontje",
    "wof:placetype":"venue"
},
  "geometry": {"coordinates":[5.685795784,50.9230308533],"type":"Point"}
}