{
  "type": "Feature",
  "properties": {
    "addr:full":"Noordkaai 9 Izegem West-Vlaanderen 8870",
    "addr:housenumber":"9",
    "addr:postcode":"8870",
    "addr:street":"Noordkaai",
    "iso:country":"BE",
    "sg:address":"Noordkaai 9",
    "sg:city":"Izegem",
    "sg:classifiers":[
        {
            "category":"Shopping",
            "subcategory":"Pharmacy",
            "type":"Retail Goods"
        }
    ],
    "sg:phone":"+32 51 33 30 60",
    "sg:postcode":"8870",
    "sg:province":"West-Vlaanderen",
    "sg:tags":[
        "pharmaceutical"
    ],
    "wof:name":"Inter Nos C.v.",
    "wof:placetype":"venue"
},
  "geometry": {"coordinates":[3.1895198822,50.929019928],"type":"Point"}
}