{
  "type": "Feature",
  "properties": {
    "addr:full":"Potteriestraat 33 Zonnebeke West-Vlaanderen 8980",
    "addr:housenumber":"33",
    "addr:postcode":"8980",
    "addr:street":"Potteriestraat",
    "iso:country":"BE",
    "sg:address":"Potteriestraat 33",
    "sg:city":"Zonnebeke",
    "sg:orig_category":"Varkenskwekers",
    "sg:phone":"+32 57 46 72 66",
    "sg:postcode":"8980",
    "sg:province":"West-Vlaanderen",
    "wof:name":"Joris Wyseur",
    "wof:placetype":"venue"
},
  "geometry": {"coordinates":[3.0437419415,50.8492698669],"type":"Point"}
}