{
  "type": "Feature",
  "properties": {
    "iso:country":"BE",
    "sg:address":"Rue Des Juifs 10",
    "sg:city":"Doische",
    "sg:orig_category":"Rundveehouders",
    "sg:phone":"+32 60 39 94 81",
    "sg:postcode":"5680",
    "sg:province":"Namur",
    "wof:name":"Bernard Gilles",
    "wof:placetype":"venue"
},
  "geometry": {"coordinates":[4.6240530014,50.1190948486],"type":"Point"}
}