{
  "type": "Feature",
  "properties": {
    "addr:full":"Rue Saint-remy 10bb Li\u00c8ge Li\u00e8ge 4000",
    "addr:housenumber":"10bb",
    "addr:postcode":"4000",
    "addr:street":"Rue Saint-Remy",
    "iso:country":"BE",
    "sg:address":"Rue Saint-remy 10bb",
    "sg:city":"Li\u00c8ge",
    "sg:orig_category":"Advocaten and juridische adviseurs",
    "sg:phone":"+32 4 223 53 25",
    "sg:postcode":"4000",
    "sg:province":"Li\u00e8ge",
    "wof:name":"A.m Hanquet",
    "wof:placetype":"venue"
},
  "geometry": {"coordinates":[5.5696687698,50.6386070251],"type":"Point"}
}