{
  "type": "Feature",
  "properties": {
    "addr:full":"Steenweg 145 Alken Limburg 3570",
    "addr:housenumber":"145",
    "addr:postcode":"3570",
    "addr:street":"Steenweg",
    "iso:country":"BE",
    "sg:address":"Steenweg 145",
    "sg:city":"Alken",
    "sg:classifiers":[
        {
            "category":"Real Estate",
            "subcategory":"Architect",
            "type":"Services"
        }
    ],
    "sg:phone":"+32 11 59 30 24",
    "sg:postcode":"3570",
    "sg:province":"Limburg",
    "wof:name":"Bosmans S",
    "wof:placetype":"venue"
},
  "geometry": {"coordinates":[5.2869749069,50.8872070312],"type":"Point"}
}