{
  "type": "Feature",
  "properties": {
    "addr:full":"Brusselsesteenweg 41 Tervuren Vlaams-Brabant 3080",
    "addr:housenumber":"41",
    "addr:postcode":"3080",
    "addr:street":"Brusselsesteenweg",
    "iso:country":"BE",
    "sg:address":"Brusselsesteenweg 41",
    "sg:city":"Tervuren",
    "sg:classifiers":[
        {
            "category":"Professional",
            "subcategory":"Testing Lab",
            "type":"Services"
        }
    ],
    "sg:phone":"+32 2 767 34 56",
    "sg:postcode":"3080",
    "sg:province":"Vlaams-Brabant",
    "sg:tags":[
        "chemist"
    ],
    "wof:name":"Graf",
    "wof:placetype":"venue"
},
  "geometry": {"coordinates":[4.5102310181,50.8246841431],"type":"Point"}
}