{
  "type": "Feature",
  "properties": {
    "addr:full":"Rue Van Aa 14 Elsene/ixelles Bruxelles-Capitale 1050",
    "addr:housenumber":"14",
    "addr:postcode":"1050",
    "addr:street":"Rue Van Aa",
    "iso:country":"BE",
    "sg:address":"Rue Van Aa 14",
    "sg:city":"Elsene/ixelles",
    "sg:orig_category":"M\u00e9decins and sp\u00e9cialistes",
    "sg:phone":"+32 2 514 46 59",
    "sg:postcode":"1050",
    "sg:province":"Bruxelles-Capitale",
    "wof:name":"Pierre Lutula Katako",
    "wof:placetype":"venue"
},
  "geometry": {"coordinates":[4.3690700531,50.8335914612],"type":"Point"}
}