{
  "type": "Feature",
  "properties": {
    "addr:full":"Avenue Du Derby 51 Box 7 Bruxelles (ixelles) Bruxelles-Capitale 1050",
    "addr:housenumber":"51;7",
    "addr:postcode":"1050",
    "addr:street":"Avenue Du Derby;Box",
    "iso:country":"BE",
    "sg:address":"Avenue Du Derby 51 Box 7",
    "sg:city":"Bruxelles (ixelles)",
    "sg:classifiers":[
        {
            "category":"Home & Garden",
            "subcategory":"Home Furnishings",
            "type":"Retail Goods"
        }
    ],
    "sg:phone":"+32 2 660 96 49",
    "sg:postcode":"1050",
    "sg:province":"Bruxelles-Capitale",
    "sg:tags":[
        "interior",
        "decoration"
    ],
    "wof:name":"De Gottal F",
    "wof:placetype":"venue"
},
  "geometry": {"coordinates":[4.3897380829,50.803314209],"type":"Point"}
}