{
  "type": "Feature",
  "properties": {
    "addr:full":"Chauss\u00e9e De Tubize 57 Braine-le-ch\u00e2teau (wauthier-braine) Brabant Wallon 1440",
    "addr:housenumber":"57",
    "addr:postcode":"1440",
    "addr:street":"Chausse\u0301E De Tubize",
    "iso:country":"BE",
    "sg:address":"Chauss\u00e9e De Tubize 57",
    "sg:city":"Braine-le-ch\u00e2teau (wauthier-braine)",
    "sg:orig_category":"Non-Classified Establishments",
    "sg:phone":"+32 2 366 27 47",
    "sg:postcode":"1440",
    "sg:province":"Brabant Wallon",
    "wof:name":"Taste Development Sa",
    "wof:placetype":"venue"
},
  "geometry": {"coordinates":[4.2592167854,50.6804656982],"type":"Point"}
}