{
  "type": "Feature",
  "properties": {
    "addr:full":"Bergensesteenweg 332 Sint-pieters-leeuw Vlaams-Brabant 1600",
    "addr:housenumber":"332",
    "addr:postcode":"1600",
    "addr:street":"Bergensesteenweg",
    "iso:country":"BE",
    "sg:address":"Bergensesteenweg 332",
    "sg:city":"Sint-pieters-leeuw",
    "sg:classifiers":[
        {
            "category":"Personal",
            "subcategory":"Beauty Salon",
            "type":"Services"
        }
    ],
    "sg:phone":"+32 2 377 04 78",
    "sg:postcode":"1600",
    "sg:province":"Vlaams-Brabant",
    "sg:tags":[
        "de",
        "coiffure"
    ],
    "wof:name":"Coiffure De Gauquier",
    "wof:placetype":"venue"
},
  "geometry": {"coordinates":[4.2801699638,50.7895507812],"type":"Point"}
}