{
  "type": "Feature",
  "properties": {
    "addr:full":"Rue Grande 130 Dinant Namur 5500",
    "addr:housenumber":"130",
    "addr:postcode":"5500",
    "addr:street":"Rue Grande",
    "iso:country":"BE",
    "sg:address":"Rue Grande 130",
    "sg:city":"Dinant",
    "sg:orig_category":"Eclairage et \u00e9quipements du foyer",
    "sg:phone":"+32 82 22 29 61",
    "sg:postcode":"5500",
    "sg:province":"Namur",
    "wof:name":"M. Bocca",
    "wof:placetype":"venue"
},
  "geometry": {"coordinates":[4.912938118,50.2597618103],"type":"Point"}
}