{
  "type": "Feature",
  "properties": {
    "iso:country":"BE",
    "sg:address":"De Smet De Naeyerlaan 54b8",
    "sg:city":"Jette",
    "sg:orig_category":"Boekhouders",
    "sg:phone":"+32 2 426 70 22",
    "sg:postcode":"1090",
    "sg:province":"Bruxelles-Capitale",
    "wof:name":"Jeannine Campeert",
    "wof:placetype":"venue"
},
  "geometry": {"coordinates":[4.3289179802,50.8728408813],"type":"Point"}
}