{
  "type": "Feature",
  "properties": {
    "addr:full":"Rue Laurent Delvaux 33 Uccle Bruxelles-Capitale 1180",
    "addr:housenumber":"33",
    "addr:postcode":"1180",
    "addr:street":"Rue Laurent Delvaux",
    "iso:country":"BE",
    "sg:address":"Rue Laurent Delvaux 33",
    "sg:city":"Uccle",
    "sg:classifiers":[
        {
            "category":"Building & Trades",
            "subcategory":"Construction",
            "type":"Services"
        }
    ],
    "sg:phone":"+32 2 378 47 24",
    "sg:postcode":"1180",
    "sg:province":"Bruxelles-Capitale",
    "sg:tags":[
        "ventilation",
        "conditionn\u00e9",
        "air"
    ],
    "wof:name":"Coolwave",
    "wof:placetype":"venue"
},
  "geometry": {"coordinates":[4.3396701813,50.8000144958],"type":"Point"}
}