{
  "type": "Feature",
  "properties": {
    "addr:full":"Rue De Rosi\u00c8res 22 Rixensart Brabant Wallon 1332",
    "addr:housenumber":"22",
    "addr:postcode":"1332",
    "addr:street":"Rue De Rosie\u0300Res;Wallon",
    "iso:country":"BE",
    "sg:address":"Rue De Rosi\u00c8res 22",
    "sg:city":"Rixensart",
    "sg:orig_category":"Dierenartsen",
    "sg:phone":"+32 496 43 61 95",
    "sg:postcode":"1332",
    "sg:province":"Brabant Wallon",
    "wof:name":"M. Lauvau",
    "wof:placetype":"venue"
},
  "geometry": {"coordinates":[4.515996933,50.7243118286],"type":"Point"}
}