{
  "type": "Feature",
  "properties": {
    "addr:full":"Zoerselsteenweg 17 Zoersel Antwerpen 2980",
    "addr:housenumber":"17",
    "addr:postcode":"2980",
    "addr:street":"Zoerselsteenweg",
    "iso:country":"BE",
    "sg:address":"Zoerselsteenweg 17",
    "sg:city":"Zoersel",
    "sg:orig_category":"Banques and organismes de cr\u00e9dit",
    "sg:phone":"+32 3 385 81 13",
    "sg:postcode":"2980",
    "sg:province":"Antwerpen",
    "wof:name":"Groep Argenta",
    "wof:placetype":"venue"
},
  "geometry": {"coordinates":[4.6539587975,51.262172699],"type":"Point"}
}