{
  "type": "Feature",
  "properties": {
    "addr:full":"Rue De L'eglise 5a Philippeville (villers-en-fagne) Namur 5600",
    "addr:housenumber":"5a",
    "addr:postcode":"5600",
    "addr:street":"Rue De L'Eglise",
    "iso:country":"BE",
    "sg:address":"Rue De L'eglise 5a",
    "sg:city":"Philippeville (villers-en-fagne)",
    "sg:classifiers":[
        {
            "category":"Cafe",
            "type":"Food & Drink"
        }
    ],
    "sg:phone":"+32 71 66 98 61",
    "sg:postcode":"5600",
    "sg:province":"Namur",
    "sg:tags":[
        "snack-bars"
    ],
    "wof:name":"L'actuel",
    "wof:placetype":"venue"
},
  "geometry": {"coordinates":[4.5852928162,50.145904541],"type":"Point"}
}