{
  "type": "Feature",
  "properties": {
    "iso:country":"BE",
    "sg:address":"Rue Fricotte 3",
    "sg:city":"Mettet",
    "sg:orig_category":"Pharmaciens",
    "sg:phone":"+32 71 72 97 55",
    "sg:postcode":"5644",
    "sg:province":"Namur",
    "wof:name":"Francoise Lahaut",
    "wof:placetype":"venue"
},
  "geometry": {"coordinates":[4.7214870453,50.3003387451],"type":"Point"}
}