{
  "type": "Feature",
  "properties": {
    "iso:country":"BE",
    "sg:address":"Leopoldlaan 100-101",
    "sg:city":"Middelkerke",
    "sg:orig_category":"Kapsalons",
    "sg:phone":"+32 59 30 45 27",
    "sg:postcode":"8430",
    "sg:province":"West-Vlaanderen",
    "wof:name":"Coiffure Nymf",
    "wof:placetype":"venue"
},
  "geometry": {"coordinates":[2.8137030602,51.1872367859],"type":"Point"}
}