{
  "type": "Feature",
  "properties": {
    "addr:full":"Onderstraat 10 Gent Oost-Vlaanderen 9000",
    "addr:housenumber":"10",
    "addr:postcode":"9000",
    "addr:street":"Onderstraat;Oost-Vlaanderen",
    "iso:country":"BE",
    "sg:address":"Onderstraat 10",
    "sg:city":"Gent",
    "sg:orig_category":"Enseignement maternel and primaire",
    "sg:phone":"+32 9 225 26 58",
    "sg:postcode":"9000",
    "sg:province":"Oost-Vlaanderen",
    "wof:name":"Stedelijke Basisschool",
    "wof:placetype":"venue"
},
  "geometry": {"coordinates":[3.724531889,51.0559883118],"type":"Point"}
}