{
  "type": "Feature",
  "properties": {
    "iso:country":"BE",
    "sg:address":"Sint-annastraat 35",
    "sg:city":"Merelbeke",
    "sg:orig_category":"Boucheries",
    "sg:phone":"+32 9 362 94 09",
    "sg:postcode":"9820",
    "sg:province":"Oost-Vlaanderen",
    "wof:name":"Slagerij Mattheeuws",
    "wof:placetype":"venue"
},
  "geometry": {"coordinates":[3.7518379688,50.9648475647],"type":"Point"}
}