{
  "type": "Feature",
  "properties": {
    "addr:full":"Avenue Jacques Pastur 8 Bruxelles (uccle) Bruxelles-Capitale 1180",
    "addr:housenumber":"8",
    "addr:postcode":"1180",
    "addr:street":"Avenue Jacques Pastur",
    "iso:country":"BE",
    "sg:address":"Avenue Jacques Pastur 8",
    "sg:city":"Bruxelles (uccle)",
    "sg:classifiers":[
        {
            "category":"Insurance",
            "subcategory":"Insurance Agent",
            "type":"Services"
        }
    ],
    "sg:phone":"+32 2 374 19 64",
    "sg:postcode":"1180",
    "sg:province":"Bruxelles-Capitale",
    "sg:tags":[
        "broker"
    ],
    "wof:name":"F.a.c.",
    "wof:placetype":"venue"
},
  "geometry": {"coordinates":[4.3744220734,50.7880859375],"type":"Point"}
}