{
  "type": "Feature",
  "properties": {
    "addr:full":"Rue Des Fabriques 56-58 Bruxelles Bruxelles-Capitale 1000",
    "addr:postcode":"56-58;1000",
    "addr:street":"Rue Des Fabriques",
    "iso:country":"BE",
    "sg:address":"Rue Des Fabriques 56-58",
    "sg:city":"Bruxelles",
    "sg:classifiers":[
        {
            "category":"Organizations",
            "subcategory":"Community Association",
            "type":"Services"
        }
    ],
    "sg:phone":"+32 2 502 70 17",
    "sg:postcode":"1000",
    "sg:province":"Bruxelles-Capitale",
    "sg:tags":[
        "cultural"
    ],
    "wof:name":"Al Imam Al Bokhari",
    "wof:placetype":"venue"
},
  "geometry": {"coordinates":[4.3400788307,50.848865509],"type":"Point"}
}