{
  "type": "Feature",
  "properties": {
    "iso:country":"BE",
    "sg:address":"Preshoekstraat 180",
    "sg:city":"Kortrijk",
    "sg:orig_category":"Rundveehouders",
    "sg:phone":"+32 56 22 24 61",
    "sg:postcode":"8510",
    "sg:province":"West-Vlaanderen",
    "wof:name":"Noel Beyls",
    "wof:placetype":"venue"
},
  "geometry": {"coordinates":[3.2236299515,50.7985191345],"type":"Point"}
}