{
  "type": "Feature",
  "properties": {
    "iso:country":"BE",
    "sg:address":"Provinciesteenweg 471",
    "sg:city":"Boechout",
    "sg:classifiers":[
        {
            "category":"Home & Garden",
            "subcategory":"Hardware",
            "type":"Retail Goods"
        }
    ],
    "sg:phone":"+32 3 455 24 86",
    "sg:postcode":"2530",
    "sg:province":"Antwerpen",
    "sg:tags":[
        "-"
    ],
    "wof:name":"In Den Boerenhandel",
    "wof:placetype":"venue"
},
  "geometry": {"coordinates":[4.5146150589,51.1581382751],"type":"Point"}
}