{
  "type": "Feature",
  "properties": {
    "addr:full":"Weertersteenweg 196 Kinrooi Limburg 3640",
    "addr:housenumber":"196",
    "addr:postcode":"3640",
    "addr:street":"Weertersteenweg",
    "iso:country":"BE",
    "sg:address":"Weertersteenweg 196",
    "sg:city":"Kinrooi",
    "sg:classifiers":[
        {
            "category":"Personal",
            "subcategory":"Beauty Salon",
            "type":"Services"
        }
    ],
    "sg:phone":"+32 89 70 26 21",
    "sg:postcode":"3640",
    "sg:province":"Limburg",
    "sg:tags":[
        "de",
        "coiffure"
    ],
    "wof:name":"Coiffure Madelein",
    "wof:placetype":"venue"
},
  "geometry": {"coordinates":[5.7420988083,51.1491737366],"type":"Point"}
}