{
  "type": "Feature",
  "properties": {
    "iso:country":"BE",
    "sg:address":"Bouwelsesteenweg 40",
    "sg:city":"Nijlen",
    "sg:orig_category":"Diepvriesproducten Gh",
    "sg:phone":"+32 3 411 06 25",
    "sg:postcode":"2560",
    "sg:province":"Antwerpen",
    "wof:name":"O\u00b4cool",
    "wof:placetype":"venue"
},
  "geometry": {"coordinates":[4.6781201363,51.1637687683],"type":"Point"}
}