{
  "type": "Feature",
  "properties": {
    "addr:full":"Kleine Hollestraat 8 Bertem (korbeek-dijle) Vlaams-Brabant 3060",
    "addr:housenumber":"8",
    "addr:postcode":"3060",
    "addr:street":"Kleine Hollestraat",
    "iso:country":"BE",
    "sg:address":"Kleine Hollestraat 8",
    "sg:city":"Bertem (korbeek-dijle)",
    "sg:classifiers":[
        {
            "category":"Health Services",
            "subcategory":"Doctor",
            "type":"Services"
        }
    ],
    "sg:phone":"+32 16 47 03 77",
    "sg:postcode":"3060",
    "sg:province":"Vlaams-Brabant",
    "sg:tags":[
        "medicinephysicians",
        "surgeon"
    ],
    "wof:name":"Dermaux Annemie",
    "wof:placetype":"venue"
},
  "geometry": {"coordinates":[4.6346287727,50.8400878906],"type":"Point"}
}