{
  "type": "Feature",
  "properties": {
    "addr:full":"Jozef Ii Straat 50 Oostende West-Vlaanderen 8400",
    "addr:housenumber":"50",
    "addr:postcode":"8400",
    "addr:street":"Jozef Ii Straat",
    "iso:country":"BE",
    "sg:address":"Jozef Ii Straat 50",
    "sg:city":"Oostende",
    "sg:orig_category":"Industri\u00eble wasserijen and droogkuis",
    "sg:phone":"+32 59 50 30 13",
    "sg:postcode":"8400",
    "sg:province":"West-Vlaanderen",
    "wof:name":"Droogkuis Hit Press",
    "wof:placetype":"venue"
},
  "geometry": {"coordinates":[2.9197030067,51.2291030884],"type":"Point"}
}