{
  "type": "Feature",
  "properties": {
    "addr:full":"Tulpenlaan 1 Harelbeke West-Vlaanderen 8531",
    "addr:housenumber":"1",
    "addr:postcode":"8531",
    "addr:street":"Tulpenlaan",
    "iso:country":"BE",
    "sg:address":"Tulpenlaan 1",
    "sg:city":"Harelbeke",
    "sg:orig_category":"Woningbouw",
    "sg:phone":"+32 56 70 53 42",
    "sg:postcode":"8531",
    "sg:province":"West-Vlaanderen",
    "wof:name":"Rik Mullie",
    "wof:placetype":"venue"
},
  "geometry": {"coordinates":[3.2938649654,50.8859786987],"type":"Point"}
}