{
  "type": "Feature",
  "properties": {
    "iso:country":"BE",
    "sg:address":"Luxemburghof 9",
    "sg:city":"Harelbeke",
    "sg:classifiers":[
        {
            "category":"Real Estate",
            "subcategory":"Surveying",
            "type":"Services"
        }
    ],
    "sg:phone":"+32 56 72 31 48",
    "sg:postcode":"8530",
    "sg:province":"West-Vlaanderen",
    "sg:tags":[
        "lettering",
        "letter"
    ],
    "wof:name":"Dilly Graphics",
    "wof:placetype":"venue"
},
  "geometry": {"coordinates":[3.3269000053,50.856842041],"type":"Point"}
}