{
  "type": "Feature",
  "properties": {
    "addr:full":"Wallerode 47ba Sankt Vith/saint-vith Li\u00e8ge 4780",
    "addr:housenumber":"47ba",
    "addr:postcode":"4780",
    "addr:street":"Wallerode",
    "iso:country":"BE",
    "sg:address":"Wallerode 47ba",
    "sg:city":"Sankt Vith/saint-vith",
    "sg:orig_category":"Elektrische installaties voor woningen",
    "sg:phone":"+32 80 22 11 23",
    "sg:postcode":"4780",
    "sg:province":"Li\u00e8ge",
    "wof:name":"Arnold Seffer",
    "wof:placetype":"venue"
},
  "geometry": {"coordinates":[6.1602201462,50.2983818054],"type":"Point"}
}