{
  "type": "Feature",
  "properties": {
    "addr:full":"Louis Titecastraat 51 Sint-pieters-woluwe/woluwe-saint-pierre Bruxelles-Capitale 1150",
    "addr:housenumber":"51",
    "addr:postcode":"1150",
    "addr:street":"Louis Titecastraat;/",
    "iso:country":"BE",
    "sg:address":"Louis Titecastraat 51",
    "sg:city":"Sint-pieters-woluwe/woluwe-saint-pierre",
    "sg:orig_category":"Diverse zakelijke dienstverlening Marktonderzoekbureaus Public-relationsbureaus",
    "sg:phone":"+32 2 763 19 96",
    "sg:postcode":"1150",
    "sg:province":"Bruxelles-Capitale",
    "wof:name":"Bureau Inedithing",
    "wof:placetype":"venue"
},
  "geometry": {"coordinates":[4.4320449829,50.8340835571],"type":"Point"}
}