{
  "type": "Feature",
  "properties": {
    "addr:full":"Armentierestraat 395 Komen-waasten/comines-warneton Hainaut 7783",
    "addr:housenumber":"395;7783",
    "addr:street":"Armentierestraat",
    "iso:country":"BE",
    "sg:address":"Armentierestraat 395",
    "sg:city":"Komen-waasten/comines-warneton",
    "sg:orig_category":"Kapsalons",
    "sg:phone":"+32 56 58 90 42",
    "sg:postcode":"7783",
    "sg:province":"Hainaut",
    "wof:name":"Coiffure Nicole",
    "wof:placetype":"venue"
},
  "geometry": {"coordinates":[2.8828949928,50.7069244385],"type":"Point"}
}