{
  "type": "Feature",
  "properties": {
    "iso:country":"BE",
    "sg:address":"Avenue L\u00e9opold Wiener 127 Box 11",
    "sg:city":"Bruxelles (watermael-boitsfort)",
    "sg:classifiers":[
        {
            "category":"Building & Trades",
            "subcategory":"Construction",
            "type":"Services"
        }
    ],
    "sg:phone":"+32 2 675 85 85",
    "sg:postcode":"1170",
    "sg:province":"Bruxelles-Capitale",
    "sg:tags":[
        "surveyor",
        "-"
    ],
    "wof:name":"G.i.s. Sa",
    "wof:placetype":"venue"
},
  "geometry": {"coordinates":[4.4084339142,50.8050956726],"type":"Point"}
}