{
  "type": "Feature",
  "properties": {
    "addr:full":"Faiderstraat 18 Sint-gillis/saint-gilles Bruxelles-Capitale 1060",
    "addr:housenumber":"18",
    "addr:postcode":"1060",
    "addr:street":"Faiderstraat",
    "iso:country":"BE",
    "sg:address":"Faiderstraat 18",
    "sg:city":"Sint-gillis/saint-gilles",
    "sg:orig_category":"Advocaten and juridische adviseurs",
    "sg:phone":"+32 2 538 89 17",
    "sg:postcode":"1060",
    "sg:province":"Bruxelles-Capitale",
    "wof:name":"P. Brimeyer",
    "wof:placetype":"venue"
},
  "geometry": {"coordinates":[4.3569231033,50.8289222717],"type":"Point"}
}