{
  "type": "Feature",
  "properties": {
    "addr:full":"Quai Saint-l\u00c9onard 80 Li\u00c8ge Li\u00e8ge 4000",
    "addr:housenumber":"80",
    "addr:postcode":"4000",
    "addr:street":"Quai Saint-Le\u0301Onard",
    "iso:country":"BE",
    "sg:address":"Quai Saint-l\u00c9onard 80",
    "sg:city":"Li\u00c8ge",
    "sg:orig_category":"Enseignement secondaire g\u00e9n\u00e9ral. Enseignement secondaire technique and professionnel",
    "sg:phone":"+32 4 227 27 56",
    "sg:postcode":"4000",
    "sg:province":"Li\u00e8ge",
    "wof:name":"Ath\u00c9n\u00c9e Royal Atlas",
    "wof:placetype":"venue"
},
  "geometry": {"coordinates":[5.5987901688,50.6499862671],"type":"Point"}
}