{
  "type": "Feature",
  "properties": {
    "iso:country":"BE",
    "sg:address":"Thomasboslaan 34",
    "sg:city":"Maasmechelen",
    "sg:classifiers":[
        {
            "category":"Fast Food",
            "type":"Food & Drink"
        }
    ],
    "sg:phone":"+32 89 76 25 26",
    "sg:postcode":"3630",
    "sg:province":"Limburg",
    "sg:tags":[
        "\u00c0",
        "emporter",
        "restaurants"
    ],
    "wof:name":"Verheyen",
    "wof:placetype":"venue"
},
  "geometry": {"coordinates":[5.6772069931,50.9771385193],"type":"Point"}
}