{
  "type": "Feature",
  "properties": {
    "addr:full":"Rue Pr\u00c9-binet 16 Li\u00c8ge Li\u00e8ge 4020",
    "addr:housenumber":"16",
    "addr:postcode":"4020",
    "addr:street":"Rue Pre\u0301-Binet",
    "iso:country":"BE",
    "sg:address":"Rue Pr\u00c9-binet 16",
    "sg:city":"Li\u00c8ge",
    "sg:orig_category":"Quincailleries. Installation de menuiserie en bois and plastique. Mat\u00e9riaux de construction Gr",
    "sg:phone":"+32 4 343 34 17",
    "sg:postcode":"4020",
    "sg:province":"Li\u00e8ge",
    "wof:name":"Brico-defi Cataldo",
    "wof:placetype":"venue"
},
  "geometry": {"coordinates":[5.5849862099,50.6295585632],"type":"Point"}
}