{
  "type": "Feature",
  "properties": {
    "addr:full":"Chauss\u00e9e D'alsemberg 1063 Bruxelles (uccle) Bruxelles-Capitale 1180",
    "addr:postcode":"1063;1180",
    "addr:street":"Chausse\u0301E D'Alsemberg",
    "iso:country":"BE",
    "sg:address":"Chauss\u00e9e D'alsemberg 1063",
    "sg:city":"Bruxelles (uccle)",
    "sg:classifiers":[
        {
            "category":"Bars & Pubs",
            "type":"Food & Drink"
        }
    ],
    "sg:phone":"+32 2 376 06 06",
    "sg:postcode":"1180",
    "sg:province":"Bruxelles-Capitale",
    "sg:tags":[
        "tavern"
    ],
    "wof:name":"Goualante (la)",
    "wof:placetype":"venue"
},
  "geometry": {"coordinates":[4.3325428963,50.7917747498],"type":"Point"}
}